Compiled from "SubsetConstruction.scala"
public class scala.util.automata.SubsetConstruction extends java.lang.Object implements scala.ScalaObject
  SourceFile: "SubsetConstruction.scala"
  Signature: length = 0x2
   01 22 
  ScalaSig: length = 0x1CB
   05 00 4B 06 04 01 02 00 09 02 12 53 75 62 73 65
   74 43 6F 6E 73 74 72 75 63 74 69 6F 6E 0A 02 03
   04 01 08 61 75 74 6F 6D 61 74 61 0A 02 05 06 01
   04 75 74 69 6C 0A 01 07 01 05 73 63 61 6C 61 03
   00 15 02 0A 20 13 03 00 0B 13 10 02 0C 11 0D 01
   0D 0A 02 0E 0F 01 04 6C 61 6E 67 0A 01 10 01 04
   6A 61 76 61 09 02 12 0D 02 06 4F 62 6A 65 63 74
   10 02 14 15 0D 01 06 09 02 16 06 02 0B 53 63 61
   6C 61 4F 62 6A 65 63 74 08 08 18 00 FFFFFF82 FFFFFFC2 FFFFFF80 FFFFFF84
   00 19 01 03 6E 66 61 15 01 1A 10 03 1B 1C 1E 0D
   01 02 09 02 1D 02 02 0F 4E 6F 6E 64 65 74 57 6F
   72 64 41 75 74 6F 6D 10 02 1F 20 0C 00 04 08 21
   00 FFFFFF84 FFFFFF80 FFFFFF80 FFFFFFC2 00 22 02 01 54 11 02 23 26 10 02
   14 24 09 02 25 06 02 07 4E 6F 74 68 69 6E 67 10
   02 14 27 09 02 28 06 02 06 41 6E 79 52 65 66 08
   08 2A 00 FFFFFF82 FFFFFF80 FFFFFFA0 FFFFFF80 04 1A 01 04 6E 66 61 20 08
   05 2C 00 FFFFFF84 00 2D 01 06 3C 69 6E 69 74 3E 14 02
   2E 2F 10 03 1B 00 1E 08 05 18 2B FFFFFFC0 00 1A 08 05
   31 00 FFFFFF84 00 32 01 09 73 65 6C 65 63 74 54 61 67
   14 03 33 36 40 10 02 14 34 09 02 35 06 02 03 49
   6E 74 08 05 37 30 FFFFFFC0 00 38 01 01 51 10 02 39 3E
   0D 01 3A 0A 02 3B 3C 01 09 69 6D 6D 75 74 61 62
   6C 65 0A 02 3D 06 01 0A 63 6F 6C 6C 65 63 74 69
   6F 6E 09 02 3F 3A 02 06 42 69 74 53 65 74 08 05
   41 30 FFFFFFC0 00 42 01 06 66 69 6E 61 6C 73 10 03 14
   43 33 09 02 44 06 02 05 41 72 72 61 79 08 05 46
   00 FFFFFF84 00 47 01 0B 64 65 74 65 72 6D 69 6E 69 7A
   65 15 01 48 10 03 1B 49 1E 09 02 4A 02 02 0C 44
   65 74 57 6F 72 64 41 75 74 6F 6D 
  InnerClass: 
   public #295= #154 of #294; //ArrowAssoc=class scala/Predef$ArrowAssoc of class scala/Predef
   public final #296= #190 of #12; //$anon$1=class scala/util/automata/SubsetConstruction$$anon$1 of class scala/util/automata/SubsetConstruction
   public #297= #281 of #270; //ComparableTraversableOps=class scala/collection/Traversable$ComparableTraversableOps of class scala/collection/Traversable
   public final #298= #261 of #12; //$anonfun$selectTag$1=class scala/util/automata/SubsetConstruction$$anonfun$selectTag$1 of class scala/util/automata/SubsetConstruction
   public final #299= #174 of #12; //$anonfun$determinize$2=class scala/util/automata/SubsetConstruction$$anonfun$determinize$2 of class scala/util/automata/SubsetConstruction
   public final #300= #212 of #12; //$anonfun$determinize$1=class scala/util/automata/SubsetConstruction$$anonfun$determinize$1 of class scala/util/automata/SubsetConstruction
   public final #301= #185 of #12; //$anonfun$determinize$3=class scala/util/automata/SubsetConstruction$$anonfun$determinize$3 of class scala/util/automata/SubsetConstruction
  minor version: 0
  major version: 49
  Constant pool:
const #1 = Asciz	SourceFile;
const #2 = Asciz	SubsetConstruction.scala;
const #3 = Asciz	nfa;
const #4 = Asciz	Lscala/util/automata/NondetWordAutom;;
const #5 = Asciz	Lscala/util/automata/NondetWordAutom<TT;>;;
const #6 = Asciz	Signature;
const #7 = Asciz	<init>;
const #8 = Asciz	(Lscala/util/automata/NondetWordAutom;)V;
const #9 = Asciz	Code;
const #10 = Asciz	LineNumberTable;
const #11 = Asciz	scala/util/automata/SubsetConstruction;
const #12 = class	#11;	//  scala/util/automata/SubsetConstruction
const #13 = NameAndType	#3:#4;//  nfa:Lscala/util/automata/NondetWordAutom;
const #14 = Field	#12.#13;	//  scala/util/automata/SubsetConstruction.nfa:Lscala/util/automata/NondetWordAutom;
const #15 = Asciz	java/lang/Object;
const #16 = class	#15;	//  java/lang/Object
const #17 = Asciz	()V;
const #18 = NameAndType	#7:#17;//  "<init>":()V
const #19 = Method	#16.#18;	//  java/lang/Object."<init>":()V
const #20 = Asciz	this;
const #21 = Asciz	Lscala/util/automata/SubsetConstruction;;
const #22 = Asciz	LocalVariableTable;
const #23 = Asciz	(Lscala/util/automata/NondetWordAutom<TT;>;)V;
const #24 = Asciz	add$1;
const #25 = Asciz	(Lscala/collection/immutable/BitSet;Lscala/runtime/ObjectRef;Lscala/runtime/ObjectRef;Lscala/collection/mutable/Stack;)V;
const #26 = Asciz	scala/runtime/ObjectRef;
const #27 = class	#26;	//  scala/runtime/ObjectRef
const #28 = Asciz	elem;
const #29 = Asciz	Ljava/lang/Object;;
const #30 = NameAndType	#28:#29;//  elem:Ljava/lang/Object;
const #31 = Field	#27.#30;	//  scala/runtime/ObjectRef.elem:Ljava/lang/Object;
const #32 = Asciz	scala/collection/immutable/Set;
const #33 = class	#32;	//  scala/collection/immutable/Set
const #34 = Asciz	scala/collection/generic/SetTemplate;
const #35 = class	#34;	//  scala/collection/generic/SetTemplate
const #36 = Asciz	contains;
const #37 = Asciz	(Ljava/lang/Object;)Z;
const #38 = NameAndType	#36:#37;//  contains:(Ljava/lang/Object;)Z
const #39 = InterfaceMethod	#35.#38;	//  scala/collection/generic/SetTemplate.contains:(Ljava/lang/Object;)Z
const #40 = Asciz	$plus;
const #41 = Asciz	(Ljava/lang/Object;)Lscala/collection/generic/SetTemplate;;
const #42 = NameAndType	#40:#41;//  $plus:(Ljava/lang/Object;)Lscala/collection/generic/SetTemplate;
const #43 = InterfaceMethod	#35.#42;	//  scala/collection/generic/SetTemplate.$plus:(Ljava/lang/Object;)Lscala/collection/generic/SetTemplate;
const #44 = Asciz	scala/collection/mutable/Stack;
const #45 = class	#44;	//  scala/collection/mutable/Stack
const #46 = Asciz	push;
const #47 = Asciz	(Ljava/lang/Object;)Lscala/collection/mutable/Stack;;
const #48 = NameAndType	#46:#47;//  push:(Ljava/lang/Object;)Lscala/collection/mutable/Stack;
const #49 = Method	#45.#48;	//  scala/collection/mutable/Stack.push:(Ljava/lang/Object;)Lscala/collection/mutable/Stack;
const #50 = Asciz	addFinal$1;
const #51 = Asciz	(Lscala/collection/immutable/BitSet;Lscala/runtime/ObjectRef;)V;
const #52 = NameAndType	#50:#51;//  addFinal$1:(Lscala/collection/immutable/BitSet;Lscala/runtime/ObjectRef;)V
const #53 = Method	#12.#52;	//  scala/util/automata/SubsetConstruction.addFinal$1:(Lscala/collection/immutable/BitSet;Lscala/runtime/ObjectRef;)V
const #54 = Asciz	Q;
const #55 = Asciz	Lscala/collection/immutable/BitSet;;
const #56 = Asciz	()Lscala/util/automata/NondetWordAutom;;
const #57 = NameAndType	#3:#56;//  nfa:()Lscala/util/automata/NondetWordAutom;
const #58 = Method	#12.#57;	//  scala/util/automata/SubsetConstruction.nfa:()Lscala/util/automata/NondetWordAutom;
const #59 = Asciz	scala/util/automata/NondetWordAutom;
const #60 = class	#59;	//  scala/util/automata/NondetWordAutom
const #61 = Asciz	containsFinal;
const #62 = Asciz	(Lscala/collection/immutable/BitSet;)Z;
const #63 = NameAndType	#61:#62;//  containsFinal:(Lscala/collection/immutable/BitSet;)Z
const #64 = Method	#60.#63;	//  scala/util/automata/NondetWordAutom.containsFinal:(Lscala/collection/immutable/BitSet;)Z
const #65 = Asciz	scala/collection/Map;
const #66 = class	#65;	//  scala/collection/Map
const #67 = Asciz	finals;
const #68 = Asciz	()[I;
const #69 = NameAndType	#67:#68;//  finals:()[I
const #70 = Method	#60.#69;	//  scala/util/automata/NondetWordAutom.finals:()[I
const #71 = Asciz	selectTag;
const #72 = Asciz	(Lscala/collection/immutable/BitSet;[I)I;
const #73 = NameAndType	#71:#72;//  selectTag:(Lscala/collection/immutable/BitSet;[I)I
const #74 = Method	#12.#73;	//  scala/util/automata/SubsetConstruction.selectTag:(Lscala/collection/immutable/BitSet;[I)I
const #75 = Asciz	scala/runtime/BoxesRunTime;
const #76 = class	#75;	//  scala/runtime/BoxesRunTime
const #77 = Asciz	boxToInteger;
const #78 = Asciz	(I)Ljava/lang/Integer;;
const #79 = NameAndType	#77:#78;//  boxToInteger:(I)Ljava/lang/Integer;
const #80 = Method	#76.#79;	//  scala/runtime/BoxesRunTime.boxToInteger:(I)Ljava/lang/Integer;
const #81 = Asciz	scala/collection/generic/MapTemplate;
const #82 = class	#81;	//  scala/collection/generic/MapTemplate
const #83 = Asciz	updated;
const #84 = Asciz	(Ljava/lang/Object;Ljava/lang/Object;)Lscala/collection/Map;;
const #85 = NameAndType	#83:#84;//  updated:(Ljava/lang/Object;Ljava/lang/Object;)Lscala/collection/Map;
const #86 = InterfaceMethod	#82.#85;	//  scala/collection/generic/MapTemplate.updated:(Ljava/lang/Object;Ljava/lang/Object;)Lscala/collection/Map;
const #87 = Asciz	q;
const #88 = Asciz	determinize;
const #89 = Asciz	()Lscala/util/automata/DetWordAutom;;
const #90 = Asciz	scala/collection/Map$;
const #91 = class	#90;	//  scala/collection/Map$
const #92 = Asciz	MODULE$;
const #93 = Asciz	Lscala/collection/Map$;;
const #94 = NameAndType	#92:#93;//  MODULE$:Lscala/collection/Map$;
const #95 = Field	#91.#94;	//  scala/collection/Map$.MODULE$:Lscala/collection/Map$;
const #96 = Asciz	scala/runtime/ScalaRunTime$;
const #97 = class	#96;	//  scala/runtime/ScalaRunTime$
const #98 = Asciz	Lscala/runtime/ScalaRunTime$;;
const #99 = NameAndType	#92:#98;//  MODULE$:Lscala/runtime/ScalaRunTime$;
const #100 = Field	#97.#99;	//  scala/runtime/ScalaRunTime$.MODULE$:Lscala/runtime/ScalaRunTime$;
const #101 = Asciz	scala/Tuple2;
const #102 = class	#101;	//  scala/Tuple2
const #103 = Asciz	boxArray;
const #104 = Asciz	(Ljava/lang/Object;)Lscala/runtime/BoxedArray;;
const #105 = NameAndType	#103:#104;//  boxArray:(Ljava/lang/Object;)Lscala/runtime/BoxedArray;
const #106 = Method	#97.#105;	//  scala/runtime/ScalaRunTime$.boxArray:(Ljava/lang/Object;)Lscala/runtime/BoxedArray;
const #107 = Asciz	apply;
const #108 = Asciz	(Lscala/collection/Sequence;)Lscala/collection/Map;;
const #109 = NameAndType	#107:#108;//  apply:(Lscala/collection/Sequence;)Lscala/collection/Map;
const #110 = Method	#91.#109;	//  scala/collection/Map$.apply:(Lscala/collection/Sequence;)Lscala/collection/Map;
const #111 = Asciz	scala/collection/immutable/Map;
const #112 = class	#111;	//  scala/collection/immutable/Map
const #113 = Asciz	(Ljava/lang/Object;)V;
const #114 = NameAndType	#7:#113;//  "<init>":(Ljava/lang/Object;)V
const #115 = Method	#27.#114;	//  scala/runtime/ObjectRef."<init>":(Ljava/lang/Object;)V
const #116 = Asciz	scala/collection/immutable/BitSet$;
const #117 = class	#116;	//  scala/collection/immutable/BitSet$
const #118 = Asciz	Lscala/collection/immutable/BitSet$;;
const #119 = NameAndType	#92:#118;//  MODULE$:Lscala/collection/immutable/BitSet$;
const #120 = Field	#117.#119;	//  scala/collection/immutable/BitSet$.MODULE$:Lscala/collection/immutable/BitSet$;
const #121 = Asciz	scala/collection/generic/BitSetFactory;
const #122 = class	#121;	//  scala/collection/generic/BitSetFactory
const #123 = Asciz	(Lscala/collection/Sequence;)Lscala/collection/BitSet;;
const #124 = NameAndType	#107:#123;//  apply:(Lscala/collection/Sequence;)Lscala/collection/BitSet;
const #125 = InterfaceMethod	#122.#124;	//  scala/collection/generic/BitSetFactory.apply:(Lscala/collection/Sequence;)Lscala/collection/BitSet;
const #126 = Asciz	scala/collection/immutable/BitSet;
const #127 = class	#126;	//  scala/collection/immutable/BitSet
const #128 = Asciz	empty;
const #129 = Asciz	()Lscala/collection/immutable/BitSet;;
const #130 = NameAndType	#128:#129;//  empty:()Lscala/collection/immutable/BitSet;
const #131 = Method	#117.#130;	//  scala/collection/immutable/BitSet$.empty:()Lscala/collection/immutable/BitSet;
const #132 = Asciz	scala/Predef$;
const #133 = class	#132;	//  scala/Predef$
const #134 = Asciz	Lscala/Predef$;;
const #135 = NameAndType	#92:#134;//  MODULE$:Lscala/Predef$;
const #136 = Field	#133.#135;	//  scala/Predef$.MODULE$:Lscala/Predef$;
const #137 = Asciz	Set;
const #138 = Asciz	()Lscala/collection/immutable/Set$;;
const #139 = NameAndType	#137:#138;//  Set:()Lscala/collection/immutable/Set$;
const #140 = Method	#133.#139;	//  scala/Predef$.Set:()Lscala/collection/immutable/Set$;
const #141 = Asciz	scala/collection/immutable/Set$;
const #142 = class	#141;	//  scala/collection/immutable/Set$
const #143 = Asciz	(Lscala/collection/Sequence;)Lscala/collection/Traversable;;
const #144 = NameAndType	#107:#143;//  apply:(Lscala/collection/Sequence;)Lscala/collection/Traversable;
const #145 = Method	#142.#144;	//  scala/collection/immutable/Set$.apply:(Lscala/collection/Sequence;)Lscala/collection/Traversable;
const #146 = Asciz	scala/collection/mutable/HashMap;
const #147 = class	#146;	//  scala/collection/mutable/HashMap
const #148 = Method	#147.#18;	//  scala/collection/mutable/HashMap."<init>":()V
const #149 = Asciz	any2ArrowAssoc;
const #150 = Asciz	(Ljava/lang/Object;)Lscala/Predef$ArrowAssoc;;
const #151 = NameAndType	#149:#150;//  any2ArrowAssoc:(Ljava/lang/Object;)Lscala/Predef$ArrowAssoc;
const #152 = Method	#133.#151;	//  scala/Predef$.any2ArrowAssoc:(Ljava/lang/Object;)Lscala/Predef$ArrowAssoc;
const #153 = Asciz	scala/Predef$ArrowAssoc;
const #154 = class	#153;	//  scala/Predef$ArrowAssoc
const #155 = Asciz	$minus$greater;
const #156 = Asciz	(Ljava/lang/Object;)Lscala/Tuple2;;
const #157 = NameAndType	#155:#156;//  $minus$greater:(Ljava/lang/Object;)Lscala/Tuple2;
const #158 = Method	#154.#157;	//  scala/Predef$ArrowAssoc.$minus$greater:(Ljava/lang/Object;)Lscala/Tuple2;
const #159 = Method	#45.#18;	//  scala/collection/mutable/Stack."<init>":()V
const #160 = Asciz	(Ljava/lang/Object;Ljava/lang/Object;Lscala/collection/Sequence;)Lscala/collection/mutable/Stack;;
const #161 = NameAndType	#46:#160;//  push:(Ljava/lang/Object;Ljava/lang/Object;Lscala/collection/Sequence;)Lscala/collection/mutable/Stack;
const #162 = Method	#45.#161;	//  scala/collection/mutable/Stack.push:(Ljava/lang/Object;Ljava/lang/Object;Lscala/collection/Sequence;)Lscala/collection/mutable/Stack;
const #163 = Asciz	isEmpty;
const #164 = Asciz	()Z;
const #165 = NameAndType	#163:#164;//  isEmpty:()Z
const #166 = Method	#45.#165;	//  scala/collection/mutable/Stack.isEmpty:()Z
const #167 = Asciz	scala/collection/generic/TraversableTemplate;
const #168 = class	#167;	//  scala/collection/generic/TraversableTemplate
const #169 = Asciz	size;
const #170 = Asciz	()I;
const #171 = NameAndType	#169:#170;//  size:()I
const #172 = InterfaceMethod	#168.#171;	//  scala/collection/generic/TraversableTemplate.size:()I
const #173 = Asciz	scala/util/automata/SubsetConstruction$$anonfun$determinize$2;
const #174 = class	#173;	//  scala/util/automata/SubsetConstruction$$anonfun$determinize$2
const #175 = Asciz	(Lscala/util/automata/SubsetConstruction;Lscala/runtime/ObjectRef;Lscala/collection/mutable/HashMap;Lscala/runtime/ObjectRef;[Lscala/collection/Map;[I)V;
const #176 = NameAndType	#7:#175;//  "<init>":(Lscala/util/automata/SubsetConstruction;Lscala/runtime/ObjectRef;Lscala/collection/mutable/HashMap;Lscala/runtime/ObjectRef;[Lscala/collection/Map;[I)V
const #177 = Method	#174.#176;	//  scala/util/automata/SubsetConstruction$$anonfun$determinize$2."<init>":(Lscala/util/automata/SubsetConstruction;Lscala/runtime/ObjectRef;Lscala/collection/mutable/HashMap;Lscala/runtime/ObjectRef;[Lscala/collection/Map;[I)V
const #178 = Asciz	scala/collection/generic/IterableTemplate;
const #179 = class	#178;	//  scala/collection/generic/IterableTemplate
const #180 = Asciz	foreach;
const #181 = Asciz	(Lscala/Function1;)V;
const #182 = NameAndType	#180:#181;//  foreach:(Lscala/Function1;)V
const #183 = InterfaceMethod	#179.#182;	//  scala/collection/generic/IterableTemplate.foreach:(Lscala/Function1;)V
const #184 = Asciz	scala/util/automata/SubsetConstruction$$anonfun$determinize$3;
const #185 = class	#184;	//  scala/util/automata/SubsetConstruction$$anonfun$determinize$3
const #186 = Asciz	(Lscala/util/automata/SubsetConstruction;Lscala/runtime/ObjectRef;[I)V;
const #187 = NameAndType	#7:#186;//  "<init>":(Lscala/util/automata/SubsetConstruction;Lscala/runtime/ObjectRef;[I)V
const #188 = Method	#185.#187;	//  scala/util/automata/SubsetConstruction$$anonfun$determinize$3."<init>":(Lscala/util/automata/SubsetConstruction;Lscala/runtime/ObjectRef;[I)V
const #189 = Asciz	scala/util/automata/SubsetConstruction$$anon$1;
const #190 = class	#189;	//  scala/util/automata/SubsetConstruction$$anon$1
const #191 = Asciz	(Lscala/util/automata/SubsetConstruction;I[Lscala/collection/Map;[I[I)V;
const #192 = NameAndType	#7:#191;//  "<init>":(Lscala/util/automata/SubsetConstruction;I[Lscala/collection/Map;[I[I)V
const #193 = Method	#190.#192;	//  scala/util/automata/SubsetConstruction$$anon$1."<init>":(Lscala/util/automata/SubsetConstruction;I[Lscala/collection/Map;[I[I)V
const #194 = Asciz	pop;
const #195 = Asciz	()Ljava/lang/Object;;
const #196 = NameAndType	#194:#195;//  pop:()Ljava/lang/Object;
const #197 = Method	#45.#196;	//  scala/collection/mutable/Stack.pop:()Ljava/lang/Object;
const #198 = Asciz	scala/collection/generic/ImmutableMapTemplate;
const #199 = class	#198;	//  scala/collection/generic/ImmutableMapTemplate
const #200 = Asciz	(Ljava/lang/Object;Ljava/lang/Object;)Lscala/collection/immutable/Map;;
const #201 = NameAndType	#83:#200;//  updated:(Ljava/lang/Object;Ljava/lang/Object;)Lscala/collection/immutable/Map;
const #202 = InterfaceMethod	#199.#201;	//  scala/collection/generic/ImmutableMapTemplate.updated:(Ljava/lang/Object;Ljava/lang/Object;)Lscala/collection/immutable/Map;
const #203 = Asciz	update;
const #204 = Asciz	(Ljava/lang/Object;Ljava/lang/Object;)V;
const #205 = NameAndType	#203:#204;//  update:(Ljava/lang/Object;Ljava/lang/Object;)V
const #206 = Method	#147.#205;	//  scala/collection/mutable/HashMap.update:(Ljava/lang/Object;Ljava/lang/Object;)V
const #207 = Asciz	labels;
const #208 = Asciz	()Lscala/collection/Sequence;;
const #209 = NameAndType	#207:#208;//  labels:()Lscala/collection/Sequence;
const #210 = Method	#60.#209;	//  scala/util/automata/NondetWordAutom.labels:()Lscala/collection/Sequence;
const #211 = Asciz	scala/util/automata/SubsetConstruction$$anonfun$determinize$1;
const #212 = class	#211;	//  scala/util/automata/SubsetConstruction$$anonfun$determinize$1
const #213 = Asciz	(Lscala/util/automata/SubsetConstruction;Lscala/runtime/ObjectRef;Lscala/runtime/ObjectRef;Lscala/collection/mutable/Stack;Lscala/collection/immutable/BitSet;Lscala/collection/mutable/HashMap;)V;
const #214 = NameAndType	#7:#213;//  "<init>":(Lscala/util/automata/SubsetConstruction;Lscala/runtime/ObjectRef;Lscala/runtime/ObjectRef;Lscala/collection/mutable/Stack;Lscala/collection/immutable/BitSet;Lscala/collection/mutable/HashMap;)V
const #215 = Method	#212.#214;	//  scala/util/automata/SubsetConstruction$$anonfun$determinize$1."<init>":(Lscala/util/automata/SubsetConstruction;Lscala/runtime/ObjectRef;Lscala/runtime/ObjectRef;Lscala/collection/mutable/Stack;Lscala/collection/immutable/BitSet;Lscala/collection/mutable/HashMap;)V
const #216 = Asciz	nextDefault;
const #217 = Asciz	(Lscala/collection/immutable/BitSet;)Lscala/collection/immutable/BitSet;;
const #218 = NameAndType	#216:#217;//  nextDefault:(Lscala/collection/immutable/BitSet;)Lscala/collection/immutable/BitSet;
const #219 = Method	#60.#218;	//  scala/util/automata/NondetWordAutom.nextDefault:(Lscala/collection/immutable/BitSet;)Lscala/collection/immutable/BitSet;
const #220 = NameAndType	#24:#25;//  add$1:(Lscala/collection/immutable/BitSet;Lscala/runtime/ObjectRef;Lscala/runtime/ObjectRef;Lscala/collection/mutable/Stack;)V
const #221 = Method	#12.#220;	//  scala/util/automata/SubsetConstruction.add$1:(Lscala/collection/immutable/BitSet;Lscala/runtime/ObjectRef;Lscala/runtime/ObjectRef;Lscala/collection/mutable/Stack;)V
const #222 = Asciz	indexMap$1;
const #223 = Asciz	Lscala/runtime/ObjectRef;;
const #224 = Asciz	invIndexMap;
const #225 = Asciz	Lscala/collection/immutable/Map;;
const #226 = Asciz	ix;
const #227 = Asciz	I;
const #228 = Asciz	q0;
const #229 = Asciz	sink;
const #230 = Asciz	states$1;
const #231 = Asciz	delta$1;
const #232 = Asciz	Lscala/collection/mutable/HashMap;;
const #233 = Asciz	deftrans$1;
const #234 = Asciz	finals$1;
const #235 = Asciz	rest$1;
const #236 = Asciz	Lscala/collection/mutable/Stack;;
const #237 = Asciz	P$1;
const #238 = Asciz	Pdelta$1;
const #239 = Asciz	Pdef;
const #240 = Asciz	nstatesR$1;
const #241 = Asciz	deltaR$1;
const #242 = Asciz	[Lscala/collection/Map;;
const #243 = Asciz	defaultR$1;
const #244 = Asciz	[I;
const #245 = Asciz	finalsR$1;
const #246 = Asciz	()Lscala/util/automata/DetWordAutom<TT;>;;
const #247 = Asciz	scala/collection/Traversable$;
const #248 = class	#247;	//  scala/collection/Traversable$
const #249 = Asciz	Lscala/collection/Traversable$;;
const #250 = NameAndType	#92:#249;//  MODULE$:Lscala/collection/Traversable$;
const #251 = Field	#248.#250;	//  scala/collection/Traversable$.MODULE$:Lscala/collection/Traversable$;
const #252 = Asciz	builderFactory;
const #253 = Asciz	()Lscala/collection/generic/BuilderFactory;;
const #254 = NameAndType	#252:#253;//  builderFactory:()Lscala/collection/generic/BuilderFactory;
const #255 = Method	#117.#254;	//  scala/collection/immutable/BitSet$.builderFactory:()Lscala/collection/generic/BuilderFactory;
const #256 = Asciz	map;
const #257 = Asciz	(Lscala/Function1;Lscala/collection/generic/BuilderFactory;)Ljava/lang/Object;;
const #258 = NameAndType	#256:#257;//  map:(Lscala/Function1;Lscala/collection/generic/BuilderFactory;)Ljava/lang/Object;
const #259 = InterfaceMethod	#168.#258;	//  scala/collection/generic/TraversableTemplate.map:(Lscala/Function1;Lscala/collection/generic/BuilderFactory;)Ljava/lang/Object;
const #260 = Asciz	scala/util/automata/SubsetConstruction$$anonfun$selectTag$1;
const #261 = class	#260;	//  scala/util/automata/SubsetConstruction$$anonfun$selectTag$1
const #262 = Asciz	(Lscala/util/automata/SubsetConstruction;)V;
const #263 = NameAndType	#7:#262;//  "<init>":(Lscala/util/automata/SubsetConstruction;)V
const #264 = Method	#261.#263;	//  scala/util/automata/SubsetConstruction$$anonfun$selectTag$1."<init>":(Lscala/util/automata/SubsetConstruction;)V
const #265 = Asciz	filter;
const #266 = Asciz	(Lscala/Function1;)Lscala/collection/generic/TraversableTemplate;;
const #267 = NameAndType	#265:#266;//  filter:(Lscala/Function1;)Lscala/collection/generic/TraversableTemplate;
const #268 = InterfaceMethod	#168.#267;	//  scala/collection/generic/TraversableTemplate.filter:(Lscala/Function1;)Lscala/collection/generic/TraversableTemplate;
const #269 = Asciz	scala/collection/Traversable;
const #270 = class	#269;	//  scala/collection/Traversable
const #271 = Asciz	scala/Ordering$Int$;
const #272 = class	#271;	//  scala/Ordering$Int$
const #273 = Asciz	Lscala/Ordering$Int$;;
const #274 = NameAndType	#92:#273;//  MODULE$:Lscala/Ordering$Int$;
const #275 = Field	#272.#274;	//  scala/Ordering$Int$.MODULE$:Lscala/Ordering$Int$;
const #276 = Asciz	comparableTraversableWrapper;
const #277 = Asciz	(Lscala/collection/Traversable;Lscala/Ordering;)Lscala/collection/Traversable$ComparableTraversableOps;;
const #278 = NameAndType	#276:#277;//  comparableTraversableWrapper:(Lscala/collection/Traversable;Lscala/Ordering;)Lscala/collection/Traversable$ComparableTraversableOps;
const #279 = Method	#248.#278;	//  scala/collection/Traversable$.comparableTraversableWrapper:(Lscala/collection/Traversable;Lscala/Ordering;)Lscala/collection/Traversable$ComparableTraversableOps;
const #280 = Asciz	scala/collection/Traversable$ComparableTraversableOps;
const #281 = class	#280;	//  scala/collection/Traversable$ComparableTraversableOps
const #282 = Asciz	min;
const #283 = NameAndType	#282:#195;//  min:()Ljava/lang/Object;
const #284 = Method	#281.#283;	//  scala/collection/Traversable$ComparableTraversableOps.min:()Ljava/lang/Object;
const #285 = Asciz	unboxToInt;
const #286 = Asciz	(Ljava/lang/Object;)I;
const #287 = NameAndType	#285:#286;//  unboxToInt:(Ljava/lang/Object;)I
const #288 = Method	#76.#287;	//  scala/runtime/BoxesRunTime.unboxToInt:(Ljava/lang/Object;)I
const #289 = Asciz	()Lscala/util/automata/NondetWordAutom<TT;>;;
const #290 = Asciz	<T:Ljava/lang/Object;>Ljava/lang/Object;Lscala/ScalaObject;;
const #291 = Asciz	ScalaSig;
const #292 = Asciz	InnerClasses;
const #293 = Asciz	scala/Predef;
const #294 = class	#293;	//  scala/Predef
const #295 = Asciz	ArrowAssoc;
const #296 = Asciz	$anon$1;
const #297 = Asciz	ComparableTraversableOps;
const #298 = Asciz	$anonfun$selectTag$1;
const #299 = Asciz	$anonfun$determinize$2;
const #300 = Asciz	$anonfun$determinize$1;
const #301 = Asciz	$anonfun$determinize$3;
const #302 = Asciz	scala/ScalaObject;
const #303 = class	#302;	//  scala/ScalaObject

{
public scala.util.automata.SubsetConstruction(scala.util.automata.NondetWordAutom);
  Code:
   Stack=2, Locals=2, Args_size=2
   0:	aload_0
   1:	aload_1
   2:	putfield	#14; //Field nfa:Lscala/util/automata/NondetWordAutom;
   5:	aload_0
   6:	invokespecial	#19; //Method java/lang/Object."<init>":()V
   9:	return
  LineNumberTable: 
   line 13: 0

  LocalVariableTable: 
   Start  Length  Slot  Name   Signature
   0      10      0    this       Lscala/util/automata/SubsetConstruction;
   0      10      1    nfa       Lscala/util/automata/NondetWordAutom;

  Signature: length = 0x2
   00 17 

public final void add$1(scala.collection.immutable.BitSet, scala.runtime.ObjectRef, scala.runtime.ObjectRef, scala.collection.mutable.Stack);
  Code:
   Stack=3, Locals=5, Args_size=5
   0:	aload_2
   1:	getfield	#31; //Field scala/runtime/ObjectRef.elem:Ljava/lang/Object;
   4:	checkcast	#33; //class scala/collection/immutable/Set
   7:	aload_1
   8:	invokeinterface	#39,  2; //InterfaceMethod scala/collection/generic/SetTemplate.contains:(Ljava/lang/Object;)Z
   13:	ifne	49
   16:	aload_2
   17:	aload_2
   18:	getfield	#31; //Field scala/runtime/ObjectRef.elem:Ljava/lang/Object;
   21:	checkcast	#33; //class scala/collection/immutable/Set
   24:	aload_1
   25:	invokeinterface	#43,  2; //InterfaceMethod scala/collection/generic/SetTemplate.$plus:(Ljava/lang/Object;)Lscala/collection/generic/SetTemplate;
   30:	checkcast	#33; //class scala/collection/immutable/Set
   33:	putfield	#31; //Field scala/runtime/ObjectRef.elem:Ljava/lang/Object;
   36:	aload	4
   38:	aload_1
   39:	invokevirtual	#49; //Method scala/collection/mutable/Stack.push:(Ljava/lang/Object;)Lscala/collection/mutable/Stack;
   42:	pop
   43:	aload_0
   44:	aload_1
   45:	aload_3
   46:	invokespecial	#53; //Method addFinal$1:(Lscala/collection/immutable/BitSet;Lscala/runtime/ObjectRef;)V
   49:	return
  LineNumberTable: 
   line 44: 0
   line 45: 16
   line 46: 36
   line 47: 43
   line 44: 49

  LocalVariableTable: 
   Start  Length  Slot  Name   Signature
   0      50      0    this       Lscala/util/automata/SubsetConstruction;
   0      50      1    Q       Lscala/collection/immutable/BitSet;


public scala.util.automata.DetWordAutom determinize();
  Code:
   Stack=9, Locals=18, Args_size=1
   0:	new	#27; //class scala/runtime/ObjectRef
   3:	dup
   4:	getstatic	#95; //Field scala/collection/Map$.MODULE$:Lscala/collection/Map$;
   7:	getstatic	#100; //Field scala/runtime/ScalaRunTime$.MODULE$:Lscala/runtime/ScalaRunTime$;
   10:	iconst_0
   11:	anewarray	#102; //class scala/Tuple2
   14:	invokevirtual	#106; //Method scala/runtime/ScalaRunTime$.boxArray:(Ljava/lang/Object;)Lscala/runtime/BoxedArray;
   17:	invokevirtual	#110; //Method scala/collection/Map$.apply:(Lscala/collection/Sequence;)Lscala/collection/Map;
   20:	checkcast	#112; //class scala/collection/immutable/Map
   23:	invokespecial	#115; //Method scala/runtime/ObjectRef."<init>":(Ljava/lang/Object;)V
   26:	astore_1
   27:	getstatic	#95; //Field scala/collection/Map$.MODULE$:Lscala/collection/Map$;
   30:	getstatic	#100; //Field scala/runtime/ScalaRunTime$.MODULE$:Lscala/runtime/ScalaRunTime$;
   33:	iconst_0
   34:	anewarray	#102; //class scala/Tuple2
   37:	invokevirtual	#106; //Method scala/runtime/ScalaRunTime$.boxArray:(Ljava/lang/Object;)Lscala/runtime/BoxedArray;
   40:	invokevirtual	#110; //Method scala/collection/Map$.apply:(Lscala/collection/Sequence;)Lscala/collection/Map;
   43:	checkcast	#112; //class scala/collection/immutable/Map
   46:	astore_2
   47:	iconst_0
   48:	istore_3
   49:	getstatic	#120; //Field scala/collection/immutable/BitSet$.MODULE$:Lscala/collection/immutable/BitSet$;
   52:	getstatic	#100; //Field scala/runtime/ScalaRunTime$.MODULE$:Lscala/runtime/ScalaRunTime$;
   55:	iconst_1
   56:	newarray int
   58:	dup
   59:	iconst_0
   60:	iconst_0
   61:	iastore
   62:	invokevirtual	#106; //Method scala/runtime/ScalaRunTime$.boxArray:(Ljava/lang/Object;)Lscala/runtime/BoxedArray;
   65:	invokeinterface	#125,  2; //InterfaceMethod scala/collection/generic/BitSetFactory.apply:(Lscala/collection/Sequence;)Lscala/collection/BitSet;
   70:	checkcast	#127; //class scala/collection/immutable/BitSet
   73:	astore	4
   75:	getstatic	#120; //Field scala/collection/immutable/BitSet$.MODULE$:Lscala/collection/immutable/BitSet$;
   78:	invokevirtual	#131; //Method scala/collection/immutable/BitSet$.empty:()Lscala/collection/immutable/BitSet;
   81:	astore	5
   83:	new	#27; //class scala/runtime/ObjectRef
   86:	dup
   87:	getstatic	#136; //Field scala/Predef$.MODULE$:Lscala/Predef$;
   90:	invokevirtual	#140; //Method scala/Predef$.Set:()Lscala/collection/immutable/Set$;
   93:	getstatic	#100; //Field scala/runtime/ScalaRunTime$.MODULE$:Lscala/runtime/ScalaRunTime$;
   96:	iconst_2
   97:	anewarray	#127; //class scala/collection/immutable/BitSet
   100:	dup
   101:	iconst_0
   102:	aload	4
   104:	aastore
   105:	dup
   106:	iconst_1
   107:	aload	5
   109:	aastore
   110:	invokevirtual	#106; //Method scala/runtime/ScalaRunTime$.boxArray:(Ljava/lang/Object;)Lscala/runtime/BoxedArray;
   113:	invokevirtual	#145; //Method scala/collection/immutable/Set$.apply:(Lscala/collection/Sequence;)Lscala/collection/Traversable;
   116:	checkcast	#33; //class scala/collection/immutable/Set
   119:	invokespecial	#115; //Method scala/runtime/ObjectRef."<init>":(Ljava/lang/Object;)V
   122:	astore	6
   124:	new	#147; //class scala/collection/mutable/HashMap
   127:	dup
   128:	invokespecial	#148; //Method scala/collection/mutable/HashMap."<init>":()V
   131:	astore	7
   133:	new	#27; //class scala/runtime/ObjectRef
   136:	dup
   137:	getstatic	#95; //Field scala/collection/Map$.MODULE$:Lscala/collection/Map$;
   140:	getstatic	#100; //Field scala/runtime/ScalaRunTime$.MODULE$:Lscala/runtime/ScalaRunTime$;
   143:	iconst_2
   144:	anewarray	#102; //class scala/Tuple2
   147:	dup
   148:	iconst_0
   149:	getstatic	#136; //Field scala/Predef$.MODULE$:Lscala/Predef$;
   152:	aload	4
   154:	invokevirtual	#152; //Method scala/Predef$.any2ArrowAssoc:(Ljava/lang/Object;)Lscala/Predef$ArrowAssoc;
   157:	aload	5
   159:	invokevirtual	#158; //Method scala/Predef$ArrowAssoc.$minus$greater:(Ljava/lang/Object;)Lscala/Tuple2;
   162:	aastore
   163:	dup
   164:	iconst_1
   165:	getstatic	#136; //Field scala/Predef$.MODULE$:Lscala/Predef$;
   168:	aload	5
   170:	invokevirtual	#152; //Method scala/Predef$.any2ArrowAssoc:(Ljava/lang/Object;)Lscala/Predef$ArrowAssoc;
   173:	aload	5
   175:	invokevirtual	#158; //Method scala/Predef$ArrowAssoc.$minus$greater:(Ljava/lang/Object;)Lscala/Tuple2;
   178:	aastore
   179:	invokevirtual	#106; //Method scala/runtime/ScalaRunTime$.boxArray:(Ljava/lang/Object;)Lscala/runtime/BoxedArray;
   182:	invokevirtual	#110; //Method scala/collection/Map$.apply:(Lscala/collection/Sequence;)Lscala/collection/Map;
   185:	checkcast	#112; //class scala/collection/immutable/Map
   188:	invokespecial	#115; //Method scala/runtime/ObjectRef."<init>":(Ljava/lang/Object;)V
   191:	astore	8
   193:	new	#27; //class scala/runtime/ObjectRef
   196:	dup
   197:	getstatic	#95; //Field scala/collection/Map$.MODULE$:Lscala/collection/Map$;
   200:	getstatic	#100; //Field scala/runtime/ScalaRunTime$.MODULE$:Lscala/runtime/ScalaRunTime$;
   203:	iconst_0
   204:	anewarray	#102; //class scala/Tuple2
   207:	invokevirtual	#106; //Method scala/runtime/ScalaRunTime$.boxArray:(Ljava/lang/Object;)Lscala/runtime/BoxedArray;
   210:	invokevirtual	#110; //Method scala/collection/Map$.apply:(Lscala/collection/Sequence;)Lscala/collection/Map;
   213:	invokespecial	#115; //Method scala/runtime/ObjectRef."<init>":(Ljava/lang/Object;)V
   216:	astore	9
   218:	new	#45; //class scala/collection/mutable/Stack
   221:	dup
   222:	invokespecial	#159; //Method scala/collection/mutable/Stack."<init>":()V
   225:	astore	10
   227:	aload	10
   229:	aload	5
   231:	aload	4
   233:	getstatic	#100; //Field scala/runtime/ScalaRunTime$.MODULE$:Lscala/runtime/ScalaRunTime$;
   236:	iconst_0
   237:	anewarray	#127; //class scala/collection/immutable/BitSet
   240:	invokevirtual	#106; //Method scala/runtime/ScalaRunTime$.boxArray:(Ljava/lang/Object;)Lscala/runtime/BoxedArray;
   243:	invokevirtual	#162; //Method scala/collection/mutable/Stack.push:(Ljava/lang/Object;Ljava/lang/Object;Lscala/collection/Sequence;)Lscala/collection/mutable/Stack;
   246:	pop
   247:	aload_0
   248:	aload	4
   250:	aload	9
   252:	invokespecial	#53; //Method addFinal$1:(Lscala/collection/immutable/BitSet;Lscala/runtime/ObjectRef;)V
   255:	aload	10
   257:	invokevirtual	#166; //Method scala/collection/mutable/Stack.isEmpty:()Z
   260:	ifeq	368
   263:	aload	6
   265:	getfield	#31; //Field scala/runtime/ObjectRef.elem:Ljava/lang/Object;
   268:	checkcast	#33; //class scala/collection/immutable/Set
   271:	invokeinterface	#172,  1; //InterfaceMethod scala/collection/generic/TraversableTemplate.size:()I
   276:	istore	14
   278:	iload	14
   280:	anewarray	#66; //class scala/collection/Map
   283:	astore	15
   285:	iload	14
   287:	newarray int
   289:	astore	16
   291:	iload	14
   293:	newarray int
   295:	astore	17
   297:	aload	6
   299:	getfield	#31; //Field scala/runtime/ObjectRef.elem:Ljava/lang/Object;
   302:	checkcast	#33; //class scala/collection/immutable/Set
   305:	new	#174; //class scala/util/automata/SubsetConstruction$$anonfun$determinize$2
   308:	dup
   309:	aload_0
   310:	aload_1
   311:	aload	7
   313:	aload	8
   315:	aload	15
   317:	aload	16
   319:	invokespecial	#177; //Method scala/util/automata/SubsetConstruction$$anonfun$determinize$2."<init>":(Lscala/util/automata/SubsetConstruction;Lscala/runtime/ObjectRef;Lscala/collection/mutable/HashMap;Lscala/runtime/ObjectRef;[Lscala/collection/Map;[I)V
   322:	invokeinterface	#183,  2; //InterfaceMethod scala/collection/generic/IterableTemplate.foreach:(Lscala/Function1;)V
   327:	aload	9
   329:	getfield	#31; //Field scala/runtime/ObjectRef.elem:Ljava/lang/Object;
   332:	checkcast	#66; //class scala/collection/Map
   335:	new	#185; //class scala/util/automata/SubsetConstruction$$anonfun$determinize$3
   338:	dup
   339:	aload_0
   340:	aload_1
   341:	aload	17
   343:	invokespecial	#188; //Method scala/util/automata/SubsetConstruction$$anonfun$determinize$3."<init>":(Lscala/util/automata/SubsetConstruction;Lscala/runtime/ObjectRef;[I)V
   346:	invokeinterface	#183,  2; //InterfaceMethod scala/collection/generic/IterableTemplate.foreach:(Lscala/Function1;)V
   351:	new	#190; //class scala/util/automata/SubsetConstruction$$anon$1
   354:	dup
   355:	aload_0
   356:	iload	14
   358:	aload	15
   360:	aload	16
   362:	aload	17
   364:	invokespecial	#193; //Method scala/util/automata/SubsetConstruction$$anon$1."<init>":(Lscala/util/automata/SubsetConstruction;I[Lscala/collection/Map;[I[I)V
   367:	areturn
   368:	aload	10
   370:	invokevirtual	#197; //Method scala/collection/mutable/Stack.pop:()Ljava/lang/Object;
   373:	checkcast	#127; //class scala/collection/immutable/BitSet
   376:	astore	11
   378:	aload_1
   379:	aload_1
   380:	getfield	#31; //Field scala/runtime/ObjectRef.elem:Ljava/lang/Object;
   383:	checkcast	#112; //class scala/collection/immutable/Map
   386:	aload	11
   388:	iload_3
   389:	invokestatic	#80; //Method scala/runtime/BoxesRunTime.boxToInteger:(I)Ljava/lang/Integer;
   392:	invokeinterface	#202,  3; //InterfaceMethod scala/collection/generic/ImmutableMapTemplate.updated:(Ljava/lang/Object;Ljava/lang/Object;)Lscala/collection/immutable/Map;
   397:	putfield	#31; //Field scala/runtime/ObjectRef.elem:Ljava/lang/Object;
   400:	aload_2
   401:	iload_3
   402:	invokestatic	#80; //Method scala/runtime/BoxesRunTime.boxToInteger:(I)Ljava/lang/Integer;
   405:	aload	11
   407:	invokeinterface	#202,  3; //InterfaceMethod scala/collection/generic/ImmutableMapTemplate.updated:(Ljava/lang/Object;Ljava/lang/Object;)Lscala/collection/immutable/Map;
   412:	astore_2
   413:	iload_3
   414:	iconst_1
   415:	iadd
   416:	istore_3
   417:	new	#147; //class scala/collection/mutable/HashMap
   420:	dup
   421:	invokespecial	#148; //Method scala/collection/mutable/HashMap."<init>":()V
   424:	astore	12
   426:	aload	7
   428:	aload	11
   430:	aload	12
   432:	invokevirtual	#206; //Method scala/collection/mutable/HashMap.update:(Ljava/lang/Object;Ljava/lang/Object;)V
   435:	aload_0
   436:	invokevirtual	#58; //Method nfa:()Lscala/util/automata/NondetWordAutom;
   439:	invokevirtual	#210; //Method scala/util/automata/NondetWordAutom.labels:()Lscala/collection/Sequence;
   442:	new	#212; //class scala/util/automata/SubsetConstruction$$anonfun$determinize$1
   445:	dup
   446:	aload_0
   447:	aload	6
   449:	aload	9
   451:	aload	10
   453:	aload	11
   455:	aload	12
   457:	invokespecial	#215; //Method scala/util/automata/SubsetConstruction$$anonfun$determinize$1."<init>":(Lscala/util/automata/SubsetConstruction;Lscala/runtime/ObjectRef;Lscala/runtime/ObjectRef;Lscala/collection/mutable/Stack;Lscala/collection/immutable/BitSet;Lscala/collection/mutable/HashMap;)V
   460:	invokeinterface	#183,  2; //InterfaceMethod scala/collection/generic/IterableTemplate.foreach:(Lscala/Function1;)V
   465:	aload_0
   466:	invokevirtual	#58; //Method nfa:()Lscala/util/automata/NondetWordAutom;
   469:	aload	11
   471:	invokevirtual	#219; //Method scala/util/automata/NondetWordAutom.nextDefault:(Lscala/collection/immutable/BitSet;)Lscala/collection/immutable/BitSet;
   474:	astore	13
   476:	aload	8
   478:	aload	8
   480:	getfield	#31; //Field scala/runtime/ObjectRef.elem:Ljava/lang/Object;
   483:	checkcast	#112; //class scala/collection/immutable/Map
   486:	aload	11
   488:	aload	13
   490:	invokeinterface	#202,  3; //InterfaceMethod scala/collection/generic/ImmutableMapTemplate.updated:(Ljava/lang/Object;Ljava/lang/Object;)Lscala/collection/immutable/Map;
   495:	putfield	#31; //Field scala/runtime/ObjectRef.elem:Ljava/lang/Object;
   498:	aload_0
   499:	aload	13
   501:	aload	6
   503:	aload	9
   505:	aload	10
   507:	invokevirtual	#221; //Method add$1:(Lscala/collection/immutable/BitSet;Lscala/runtime/ObjectRef;Lscala/runtime/ObjectRef;Lscala/collection/mutable/Stack;)V
   510:	goto	255
  LineNumberTable: 
   line 23: 0
   line 24: 27
   line 25: 47
   line 28: 49
   line 29: 75
   line 31: 83
   line 32: 124
   line 33: 133
   line 34: 193
   line 36: 218
   line 37: 227
   line 51: 247
   line 53: 255
   line 77: 263
   line 78: 278
   line 79: 285
   line 80: 291
   line 82: 297
   line 99: 327
   line 101: 351
   line 54: 368
   line 56: 378
   line 57: 400
   line 58: 413
   line 61: 417
   line 62: 426
   line 64: 435
   line 71: 465
   line 72: 476
   line 73: 498
   line 53: 510

  LocalVariableTable: 
   Start  Length  Slot  Name   Signature
   0      513      0    this       Lscala/util/automata/SubsetConstruction;
   27      340      1    indexMap$1       Lscala/runtime/ObjectRef;
   368      145      1    indexMap$1       Lscala/runtime/ObjectRef;
   47      320      2    invIndexMap       Lscala/collection/immutable/Map;
   368      145      2    invIndexMap       Lscala/collection/immutable/Map;
   49      318      3    ix       I
   368      145      3    ix       I
   75      292      4    q0       Lscala/collection/immutable/BitSet;
   368      145      4    q0       Lscala/collection/immutable/BitSet;
   83      284      5    sink       Lscala/collection/immutable/BitSet;
   368      145      5    sink       Lscala/collection/immutable/BitSet;
   124      243      6    states$1       Lscala/runtime/ObjectRef;
   368      145      6    states$1       Lscala/runtime/ObjectRef;
   133      234      7    delta$1       Lscala/collection/mutable/HashMap;
   368      145      7    delta$1       Lscala/collection/mutable/HashMap;
   193      174      8    deftrans$1       Lscala/runtime/ObjectRef;
   368      145      8    deftrans$1       Lscala/runtime/ObjectRef;
   218      149      9    finals$1       Lscala/runtime/ObjectRef;
   368      145      9    finals$1       Lscala/runtime/ObjectRef;
   227      140      10    rest$1       Lscala/collection/mutable/Stack;
   368      145      10    rest$1       Lscala/collection/mutable/Stack;
   378      132      11    P$1       Lscala/collection/immutable/BitSet;
   426      84      12    Pdelta$1       Lscala/collection/mutable/HashMap;
   476      34      13    Pdef       Lscala/collection/immutable/BitSet;
   278      89      14    nstatesR$1       I
   285      82      15    deltaR$1       [Lscala/collection/Map;
   291      76      16    defaultR$1       [I
   297      70      17    finalsR$1       [I

  Signature: length = 0x2
   00 FFFFFFF6 

public int selectTag(scala.collection.immutable.BitSet, int[]);
  Code:
   Stack=5, Locals=4, Args_size=3
   0:	getstatic	#251; //Field scala/collection/Traversable$.MODULE$:Lscala/collection/Traversable$;
   3:	aload_1
   4:	getstatic	#100; //Field scala/runtime/ScalaRunTime$.MODULE$:Lscala/runtime/ScalaRunTime$;
   7:	aload_2
   8:	invokevirtual	#106; //Method scala/runtime/ScalaRunTime$.boxArray:(Ljava/lang/Object;)Lscala/runtime/BoxedArray;
   11:	getstatic	#120; //Field scala/collection/immutable/BitSet$.MODULE$:Lscala/collection/immutable/BitSet$;
   14:	invokevirtual	#255; //Method scala/collection/immutable/BitSet$.builderFactory:()Lscala/collection/generic/BuilderFactory;
   17:	invokeinterface	#259,  3; //InterfaceMethod scala/collection/generic/TraversableTemplate.map:(Lscala/Function1;Lscala/collection/generic/BuilderFactory;)Ljava/lang/Object;
   22:	astore_3
   23:	aload_3
   24:	instanceof	#168; //class scala/collection/generic/TraversableTemplate
   27:	ifeq	34
   30:	aload_3
   31:	goto	41
   34:	getstatic	#100; //Field scala/runtime/ScalaRunTime$.MODULE$:Lscala/runtime/ScalaRunTime$;
   37:	aload_3
   38:	invokevirtual	#106; //Method scala/runtime/ScalaRunTime$.boxArray:(Ljava/lang/Object;)Lscala/runtime/BoxedArray;
   41:	checkcast	#168; //class scala/collection/generic/TraversableTemplate
   44:	new	#261; //class scala/util/automata/SubsetConstruction$$anonfun$selectTag$1
   47:	dup
   48:	aload_0
   49:	invokespecial	#264; //Method scala/util/automata/SubsetConstruction$$anonfun$selectTag$1."<init>":(Lscala/util/automata/SubsetConstruction;)V
   52:	invokeinterface	#268,  2; //InterfaceMethod scala/collection/generic/TraversableTemplate.filter:(Lscala/Function1;)Lscala/collection/generic/TraversableTemplate;
   57:	checkcast	#270; //class scala/collection/Traversable
   60:	getstatic	#275; //Field scala/Ordering$Int$.MODULE$:Lscala/Ordering$Int$;
   63:	invokevirtual	#279; //Method scala/collection/Traversable$.comparableTraversableWrapper:(Lscala/collection/Traversable;Lscala/Ordering;)Lscala/collection/Traversable$ComparableTraversableOps;
   66:	invokevirtual	#284; //Method scala/collection/Traversable$ComparableTraversableOps.min:()Ljava/lang/Object;
   69:	invokestatic	#288; //Method scala/runtime/BoxesRunTime.unboxToInt:(Ljava/lang/Object;)I
   72:	ireturn
  LineNumberTable: 
   line 19: 0

  LocalVariableTable: 
   Start  Length  Slot  Name   Signature
   0      73      0    this       Lscala/util/automata/SubsetConstruction;
   0      73      1    Q       Lscala/collection/immutable/BitSet;
   0      73      2    finals       [I


public scala.util.automata.NondetWordAutom nfa();
  Code:
   Stack=1, Locals=1, Args_size=1
   0:	aload_0
   1:	getfield	#14; //Field nfa:Lscala/util/automata/NondetWordAutom;
   4:	areturn
  LineNumberTable: 
   line 13: 0

  Signature: length = 0x2
   01 21 

}

