Compiled from "WordBerrySethi.scala"
public final class scala.util.automata.WordBerrySethi$$anonfun$collectTransitions$2$$anonfun$apply$1 extends java.lang.Object implements scala.Function1,scala.ScalaObject,java.io.Serializable
  SourceFile: "WordBerrySethi.scala"
  Scala: length = 0x
   
  InnerClass: 
   public abstract #123= #98 of #122; //Label=class scala/util/regexp/WordExp$Label of class scala/util/regexp/WordExp
   public final #124= #59 of #64; //$anonfun$collectTransitions$2=class scala/util/automata/WordBerrySethi$$anonfun$collectTransitions$2 of class scala/util/automata/WordBerrySethi
   public final #125= #9 of #59; //$anonfun$apply$1=class scala/util/automata/WordBerrySethi$$anonfun$collectTransitions$2$$anonfun$apply$1 of class scala/util/automata/WordBerrySethi$$anonfun$collectTransitions$2
  minor version: 0
  major version: 49
  Constant pool:
const #1 = Asciz	SourceFile;
const #2 = Asciz	WordBerrySethi.scala;
const #3 = Asciz	<clinit>;
const #4 = Asciz	()V;
const #5 = Asciz	Code;
const #6 = Asciz	serialVersionUID;
const #7 = Asciz	J;
const #8 = Asciz	scala/util/automata/WordBerrySethi$$anonfun$collectTransitions$2$$anonfun$apply$1;
const #9 = class	#8;	//  scala/util/automata/WordBerrySethi$$anonfun$collectTransitions$2$$anonfun$apply$1
const #10 = NameAndType	#6:#7;//  serialVersionUID:J
const #11 = Field	#9.#10;	//  scala/util/automata/WordBerrySethi$$anonfun$collectTransitions$2$$anonfun$apply$1.serialVersionUID:J
const #12 = Asciz	j$1;
const #13 = Asciz	I;
const #14 = Asciz	$outer;
const #15 = Asciz	Lscala/util/automata/WordBerrySethi$$anonfun$collectTransitions$2;;
const #16 = Asciz	<init>;
const #17 = Asciz	(Lscala/util/automata/WordBerrySethi$$anonfun$collectTransitions$2;I)V;
const #18 = Asciz	LineNumberTable;
const #19 = Asciz	java/lang/NullPointerException;
const #20 = class	#19;	//  java/lang/NullPointerException
const #21 = NameAndType	#16:#4;//  "<init>":()V
const #22 = Method	#20.#21;	//  java/lang/NullPointerException."<init>":()V
const #23 = NameAndType	#14:#15;//  $outer:Lscala/util/automata/WordBerrySethi$$anonfun$collectTransitions$2;
const #24 = Field	#9.#23;	//  scala/util/automata/WordBerrySethi$$anonfun$collectTransitions$2$$anonfun$apply$1.$outer:Lscala/util/automata/WordBerrySethi$$anonfun$collectTransitions$2;
const #25 = NameAndType	#12:#13;//  j$1:I
const #26 = Field	#9.#25;	//  scala/util/automata/WordBerrySethi$$anonfun$collectTransitions$2$$anonfun$apply$1.j$1:I
const #27 = Asciz	java/lang/Object;
const #28 = class	#27;	//  java/lang/Object
const #29 = Method	#28.#21;	//  java/lang/Object."<init>":()V
const #30 = Asciz	scala/Function1$class;
const #31 = class	#30;	//  scala/Function1$class
const #32 = Asciz	$init$;
const #33 = Asciz	(Lscala/Function1;)V;
const #34 = NameAndType	#32:#33;//  $init$:(Lscala/Function1;)V
const #35 = Method	#31.#34;	//  scala/Function1$class.$init$:(Lscala/Function1;)V
const #36 = Asciz	this;
const #37 = Asciz	Lscala/util/automata/WordBerrySethi$$anonfun$collectTransitions$2$$anonfun$apply$1;;
const #38 = Asciz	LocalVariableTable;
const #39 = Asciz	apply;
const #40 = Asciz	(Ljava/lang/Object;)Ljava/lang/Object;;
const #41 = Asciz	scala/runtime/BoxesRunTime;
const #42 = class	#41;	//  scala/runtime/BoxesRunTime
const #43 = Asciz	unboxToInt;
const #44 = Asciz	(Ljava/lang/Object;)I;
const #45 = NameAndType	#43:#44;//  unboxToInt:(Ljava/lang/Object;)I
const #46 = Method	#42.#45;	//  scala/runtime/BoxesRunTime.unboxToInt:(Ljava/lang/Object;)I
const #47 = Asciz	(I)V;
const #48 = NameAndType	#39:#47;//  apply:(I)V
const #49 = Method	#9.#48;	//  scala/util/automata/WordBerrySethi$$anonfun$collectTransitions$2$$anonfun$apply$1.apply:(I)V
const #50 = Asciz	scala/runtime/BoxedUnit;
const #51 = class	#50;	//  scala/runtime/BoxedUnit
const #52 = Asciz	UNIT;
const #53 = Asciz	Lscala/runtime/BoxedUnit;;
const #54 = NameAndType	#52:#53;//  UNIT:Lscala/runtime/BoxedUnit;
const #55 = Field	#51.#54;	//  scala/runtime/BoxedUnit.UNIT:Lscala/runtime/BoxedUnit;
const #56 = Asciz	v1;
const #57 = Asciz	Ljava/lang/Object;;
const #58 = Asciz	scala/util/automata/WordBerrySethi$$anonfun$collectTransitions$2;
const #59 = class	#58;	//  scala/util/automata/WordBerrySethi$$anonfun$collectTransitions$2
const #60 = Asciz	Lscala/util/automata/WordBerrySethi;;
const #61 = NameAndType	#14:#60;//  $outer:Lscala/util/automata/WordBerrySethi;
const #62 = Field	#59.#61;	//  scala/util/automata/WordBerrySethi$$anonfun$collectTransitions$2.$outer:Lscala/util/automata/WordBerrySethi;
const #63 = Asciz	scala/util/automata/WordBerrySethi;
const #64 = class	#63;	//  scala/util/automata/WordBerrySethi
const #65 = Asciz	pos;
const #66 = Asciz	()I;
const #67 = NameAndType	#65:#66;//  pos:()I
const #68 = Method	#64.#67;	//  scala/util/automata/WordBerrySethi.pos:()I
const #69 = Asciz	finals;
const #70 = Asciz	()Lscala/collection/immutable/Map;;
const #71 = NameAndType	#69:#70;//  finals:()Lscala/collection/immutable/Map;
const #72 = Method	#64.#71;	//  scala/util/automata/WordBerrySethi.finals:()Lscala/collection/immutable/Map;
const #73 = Asciz	boxToInteger;
const #74 = Asciz	(I)Ljava/lang/Integer;;
const #75 = NameAndType	#73:#74;//  boxToInteger:(I)Ljava/lang/Integer;
const #76 = Method	#42.#75;	//  scala/runtime/BoxesRunTime.boxToInteger:(I)Ljava/lang/Integer;
const #77 = Asciz	finalTag;
const #78 = NameAndType	#77:#66;//  finalTag:()I
const #79 = Method	#64.#78;	//  scala/util/automata/WordBerrySethi.finalTag:()I
const #80 = Asciz	scala/collection/immutable/MapLike;
const #81 = class	#80;	//  scala/collection/immutable/MapLike
const #82 = Asciz	updated;
const #83 = Asciz	(Ljava/lang/Object;Ljava/lang/Object;)Lscala/collection/immutable/Map;;
const #84 = NameAndType	#82:#83;//  updated:(Ljava/lang/Object;Ljava/lang/Object;)Lscala/collection/immutable/Map;
const #85 = InterfaceMethod	#81.#84;	//  scala/collection/immutable/MapLike.updated:(Ljava/lang/Object;Ljava/lang/Object;)Lscala/collection/immutable/Map;
const #86 = Asciz	finals_$eq;
const #87 = Asciz	(Lscala/collection/immutable/Map;)V;
const #88 = NameAndType	#86:#87;//  finals_$eq:(Lscala/collection/immutable/Map;)V
const #89 = Method	#64.#88;	//  scala/util/automata/WordBerrySethi.finals_$eq:(Lscala/collection/immutable/Map;)V
const #90 = Asciz	labelAt;
const #91 = NameAndType	#90:#70;//  labelAt:()Lscala/collection/immutable/Map;
const #92 = Method	#64.#91;	//  scala/util/automata/WordBerrySethi.labelAt:()Lscala/collection/immutable/Map;
const #93 = Asciz	scala/collection/MapLike;
const #94 = class	#93;	//  scala/collection/MapLike
const #95 = NameAndType	#39:#40;//  apply:(Ljava/lang/Object;)Ljava/lang/Object;
const #96 = InterfaceMethod	#94.#95;	//  scala/collection/MapLike.apply:(Ljava/lang/Object;)Ljava/lang/Object;
const #97 = Asciz	scala/util/regexp/WordExp$Label;
const #98 = class	#97;	//  scala/util/regexp/WordExp$Label
const #99 = Asciz	makeTransition;
const #100 = Asciz	(IILscala/util/regexp/WordExp$Label;)V;
const #101 = NameAndType	#99:#100;//  makeTransition:(IILscala/util/regexp/WordExp$Label;)V
const #102 = Method	#64.#101;	//  scala/util/automata/WordBerrySethi.makeTransition:(IILscala/util/regexp/WordExp$Label;)V
const #103 = Asciz	k;
const #104 = Asciz	andThen;
const #105 = Asciz	(Lscala/Function1;)Lscala/Function1;;
const #106 = Asciz	(Lscala/Function1;Lscala/Function1;)Lscala/Function1;;
const #107 = NameAndType	#104:#106;//  andThen:(Lscala/Function1;Lscala/Function1;)Lscala/Function1;
const #108 = Method	#31.#107;	//  scala/Function1$class.andThen:(Lscala/Function1;Lscala/Function1;)Lscala/Function1;
const #109 = Asciz	g;
const #110 = Asciz	Lscala/Function1;;
const #111 = Asciz	compose;
const #112 = NameAndType	#111:#106;//  compose:(Lscala/Function1;Lscala/Function1;)Lscala/Function1;
const #113 = Method	#31.#112;	//  scala/Function1$class.compose:(Lscala/Function1;Lscala/Function1;)Lscala/Function1;
const #114 = Asciz	toString;
const #115 = Asciz	()Ljava/lang/String;;
const #116 = Asciz	(Lscala/Function1;)Ljava/lang/String;;
const #117 = NameAndType	#114:#116;//  toString:(Lscala/Function1;)Ljava/lang/String;
const #118 = Method	#31.#117;	//  scala/Function1$class.toString:(Lscala/Function1;)Ljava/lang/String;
const #119 = Asciz	Scala;
const #120 = Asciz	InnerClasses;
const #121 = Asciz	scala/util/regexp/WordExp;
const #122 = class	#121;	//  scala/util/regexp/WordExp
const #123 = Asciz	Label;
const #124 = Asciz	$anonfun$collectTransitions$2;
const #125 = Asciz	$anonfun$apply$1;
const #126 = Asciz	scala/Function1;
const #127 = class	#126;	//  scala/Function1
const #128 = Asciz	scala/ScalaObject;
const #129 = class	#128;	//  scala/ScalaObject
const #130 = Asciz	java/io/Serializable;
const #131 = class	#130;	//  java/io/Serializable

{
public static final long serialVersionUID;

public static {};
  Code:
   Stack=2, Locals=0, Args_size=0
   0:	lconst_0
   1:	putstatic	#11; //Field serialVersionUID:J
   4:	return

public scala.util.automata.WordBerrySethi$$anonfun$collectTransitions$2$$anonfun$apply$1(scala.util.automata.WordBerrySethi$$anonfun$collectTransitions$2, int);
  Code:
   Stack=2, Locals=3, Args_size=3
   0:	aload_1
   1:	ifnonnull	12
   4:	new	#20; //class java/lang/NullPointerException
   7:	dup
   8:	invokespecial	#22; //Method java/lang/NullPointerException."<init>":()V
   11:	athrow
   12:	aload_0
   13:	aload_1
   14:	putfield	#24; //Field $outer:Lscala/util/automata/WordBerrySethi$$anonfun$collectTransitions$2;
   17:	aload_0
   18:	iload_2
   19:	putfield	#26; //Field j$1:I
   22:	aload_0
   23:	invokespecial	#29; //Method java/lang/Object."<init>":()V
   26:	aload_0
   27:	invokestatic	#35; //Method scala/Function1$class.$init$:(Lscala/Function1;)V
   30:	return
  LineNumberTable: 
   line 128: 0

  LocalVariableTable: 
   Start  Length  Slot  Name   Signature
   0      31      0    this       Lscala/util/automata/WordBerrySethi$$anonfun$collectTransitions$2$$anonfun$apply$1;
   0      31      1    $outer       Lscala/util/automata/WordBerrySethi$$anonfun$collectTransitions$2;


public final java.lang.Object apply(java.lang.Object);
  Code:
   Stack=2, Locals=3, Args_size=2
   0:	aload_0
   1:	getfield	#24; //Field $outer:Lscala/util/automata/WordBerrySethi$$anonfun$collectTransitions$2;
   4:	astore_2
   5:	aload_0
   6:	aload_1
   7:	invokestatic	#46; //Method scala/runtime/BoxesRunTime.unboxToInt:(Ljava/lang/Object;)I
   10:	invokevirtual	#49; //Method apply:(I)V
   13:	getstatic	#55; //Field scala/runtime/BoxedUnit.UNIT:Lscala/runtime/BoxedUnit;
   16:	areturn
  LineNumberTable: 
   line 128: 0

  LocalVariableTable: 
   Start  Length  Slot  Name   Signature
   0      17      0    this       Lscala/util/automata/WordBerrySethi$$anonfun$collectTransitions$2$$anonfun$apply$1;
   5      12      1    v1       Ljava/lang/Object;


public final void apply(int);
  Code:
   Stack=5, Locals=11, Args_size=2
   0:	aload_0
   1:	getfield	#24; //Field $outer:Lscala/util/automata/WordBerrySethi$$anonfun$collectTransitions$2;
   4:	astore	10
   6:	aload_0
   7:	getfield	#24; //Field $outer:Lscala/util/automata/WordBerrySethi$$anonfun$collectTransitions$2;
   10:	astore_2
   11:	aload_2
   12:	getfield	#62; //Field scala/util/automata/WordBerrySethi$$anonfun$collectTransitions$2.$outer:Lscala/util/automata/WordBerrySethi;
   15:	invokevirtual	#68; //Method scala/util/automata/WordBerrySethi.pos:()I
   18:	iload_1
   19:	if_icmpne	88
   22:	aload_0
   23:	getfield	#24; //Field $outer:Lscala/util/automata/WordBerrySethi$$anonfun$collectTransitions$2;
   26:	astore_3
   27:	aload_3
   28:	getfield	#62; //Field scala/util/automata/WordBerrySethi$$anonfun$collectTransitions$2.$outer:Lscala/util/automata/WordBerrySethi;
   31:	aload_0
   32:	getfield	#24; //Field $outer:Lscala/util/automata/WordBerrySethi$$anonfun$collectTransitions$2;
   35:	astore	4
   37:	aload	4
   39:	getfield	#62; //Field scala/util/automata/WordBerrySethi$$anonfun$collectTransitions$2.$outer:Lscala/util/automata/WordBerrySethi;
   42:	invokevirtual	#72; //Method scala/util/automata/WordBerrySethi.finals:()Lscala/collection/immutable/Map;
   45:	aload_0
   46:	getfield	#26; //Field j$1:I
   49:	istore	5
   51:	iload	5
   53:	invokestatic	#76; //Method scala/runtime/BoxesRunTime.boxToInteger:(I)Ljava/lang/Integer;
   56:	aload_0
   57:	getfield	#24; //Field $outer:Lscala/util/automata/WordBerrySethi$$anonfun$collectTransitions$2;
   60:	astore	6
   62:	aload	6
   64:	getfield	#62; //Field scala/util/automata/WordBerrySethi$$anonfun$collectTransitions$2.$outer:Lscala/util/automata/WordBerrySethi;
   67:	invokevirtual	#79; //Method scala/util/automata/WordBerrySethi.finalTag:()I
   70:	istore	7
   72:	iload	7
   74:	invokestatic	#76; //Method scala/runtime/BoxesRunTime.boxToInteger:(I)Ljava/lang/Integer;
   77:	invokeinterface	#85,  3; //InterfaceMethod scala/collection/immutable/MapLike.updated:(Ljava/lang/Object;Ljava/lang/Object;)Lscala/collection/immutable/Map;
   82:	invokevirtual	#89; //Method scala/util/automata/WordBerrySethi.finals_$eq:(Lscala/collection/immutable/Map;)V
   85:	goto	133
   88:	aload_0
   89:	getfield	#24; //Field $outer:Lscala/util/automata/WordBerrySethi$$anonfun$collectTransitions$2;
   92:	astore	8
   94:	aload	8
   96:	getfield	#62; //Field scala/util/automata/WordBerrySethi$$anonfun$collectTransitions$2.$outer:Lscala/util/automata/WordBerrySethi;
   99:	aload_0
   100:	getfield	#26; //Field j$1:I
   103:	iload_1
   104:	aload_0
   105:	getfield	#24; //Field $outer:Lscala/util/automata/WordBerrySethi$$anonfun$collectTransitions$2;
   108:	astore	9
   110:	aload	9
   112:	getfield	#62; //Field scala/util/automata/WordBerrySethi$$anonfun$collectTransitions$2.$outer:Lscala/util/automata/WordBerrySethi;
   115:	invokevirtual	#92; //Method scala/util/automata/WordBerrySethi.labelAt:()Lscala/collection/immutable/Map;
   118:	iload_1
   119:	invokestatic	#76; //Method scala/runtime/BoxesRunTime.boxToInteger:(I)Ljava/lang/Integer;
   122:	invokeinterface	#96,  2; //InterfaceMethod scala/collection/MapLike.apply:(Ljava/lang/Object;)Ljava/lang/Object;
   127:	checkcast	#98; //class scala/util/regexp/WordExp$Label
   130:	invokevirtual	#102; //Method scala/util/automata/WordBerrySethi.makeTransition:(IILscala/util/regexp/WordExp$Label;)V
   133:	return
  LineNumberTable: 
   line 129: 0
   line 130: 88
   line 129: 133

  LocalVariableTable: 
   Start  Length  Slot  Name   Signature
   0      134      0    this       Lscala/util/automata/WordBerrySethi$$anonfun$collectTransitions$2$$anonfun$apply$1;
   6      128      1    k       I


public scala.Function1 andThen(scala.Function1);
  Code:
   Stack=2, Locals=2, Args_size=2
   0:	aload_0
   1:	aload_1
   2:	invokestatic	#108; //Method scala/Function1$class.andThen:(Lscala/Function1;Lscala/Function1;)Lscala/Function1;
   5:	areturn
  LineNumberTable: 
   line 128: 0

  LocalVariableTable: 
   Start  Length  Slot  Name   Signature
   0      6      0    this       Lscala/util/automata/WordBerrySethi$$anonfun$collectTransitions$2$$anonfun$apply$1;
   0      6      1    g       Lscala/Function1;


public scala.Function1 compose(scala.Function1);
  Code:
   Stack=2, Locals=2, Args_size=2
   0:	aload_0
   1:	aload_1
   2:	invokestatic	#113; //Method scala/Function1$class.compose:(Lscala/Function1;Lscala/Function1;)Lscala/Function1;
   5:	areturn
  LineNumberTable: 
   line 128: 0

  LocalVariableTable: 
   Start  Length  Slot  Name   Signature
   0      6      0    this       Lscala/util/automata/WordBerrySethi$$anonfun$collectTransitions$2$$anonfun$apply$1;
   0      6      1    g       Lscala/Function1;


public java.lang.String toString();
  Code:
   Stack=1, Locals=1, Args_size=1
   0:	aload_0
   1:	invokestatic	#118; //Method scala/Function1$class.toString:(Lscala/Function1;)Ljava/lang/String;
   4:	areturn
  LineNumberTable: 
   line 128: 0


}

