Compiled from "WordBerrySethi.scala"
public abstract class scala.util.automata.WordBerrySethi extends scala.util.automata.BaseBerrySethi implements scala.ScalaObject
  SourceFile: "WordBerrySethi.scala"
  ScalaSig: length = 0x56D
   05 00 FFFFFF81 3F 06 08 01 02 FFFFFF84 FFFFFF80 FFFFFF80 FFFFFF81 00 09 02 0E
   57 6F 72 64 42 65 72 72 79 53 65 74 68 69 0A 02
   03 04 01 08 61 75 74 6F 6D 61 74 61 0A 02 05 06
   01 04 75 74 69 6C 0A 01 07 01 05 73 63 61 6C 61
   03 00 13 03 00 0A 0E 10 02 0B 0C 0D 01 02 09 02
   0D 02 02 0E 42 61 73 65 42 65 72 72 79 53 65 74
   68 69 10 02 0F 10 0D 01 06 09 02 11 06 02 0B 53
   63 61 6C 61 4F 62 6A 65 63 74 08 05 13 00 FFFFFF84 00
   14 01 06 3C 69 6E 69 74 3E 14 01 15 10 02 0B 00
   08 07 17 00 FFFFFFC2 FFFFFF80 FFFFFF86 20 18 01 04 6C 61 6E 67 15
   01 19 10 02 1A 1D 0D 01 1B 0A 02 1C 04 01 06 72
   65 67 65 78 70 09 02 1E 1B 02 07 57 6F 72 64 45
   78 70 08 07 20 00 FFFFFFC0 FFFFFF80 FFFFFF84 08 21 01 06 6C 61 62
   65 6C 73 15 01 22 10 03 23 28 2A 0D 01 24 0A 02
   25 26 01 07 6D 75 74 61 62 6C 65 0A 02 27 06 01
   0A 63 6F 6C 6C 65 63 74 69 6F 6E 09 02 29 24 02
   07 48 61 73 68 53 65 74 10 02 2B 2D 0E 02 2C 16
   0D 01 00 09 02 2E 1D 02 07 5F 6C 61 62 65 6C 54
   08 07 30 00 FFFFFFC0 FFFFFF80 FFFFFF84 08 31 01 0A 6C 61 62 65 6C
   73 5F 24 65 71 14 02 32 35 10 02 0F 33 09 02 34
   06 02 04 55 6E 69 74 08 07 36 2F FFFFFF81 FFFFFF80 FFFFFFC0 00 22
   01 03 78 24 31 08 06 38 00 FFFFFFA0 FFFFFFA0 04 22 01 07 6C
   61 62 65 6C 73 20 08 07 3A 00 FFFFFFC0 FFFFFF80 FFFFFF84 08 3B 01
   07 6C 61 62 65 6C 41 74 15 01 3C 10 04 3D 40 42
   2A 0D 01 3E 0A 02 3F 26 01 09 69 6D 6D 75 74 61
   62 6C 65 09 02 41 3E 02 03 4D 61 70 10 02 0F 43
   09 02 44 06 02 03 49 6E 74 08 07 46 00 FFFFFFC0 FFFFFF80 FFFFFF84
   08 47 01 0B 6C 61 62 65 6C 41 74 5F 24 65 71 14
   02 32 48 08 07 36 45 FFFFFF81 FFFFFF80 FFFFFFC0 00 3C 08 06 4A 00
   FFFFFFA0 FFFFFFA0 04 3C 01 08 6C 61 62 65 6C 41 74 20 08 07
   4C 00 FFFFFFC0 FFFFFF80 FFFFFF84 08 4D 01 06 64 65 6C 74 61 71 15
   01 4E 10 03 0F 4F 51 09 02 50 06 02 05 41 72 72
   61 79 10 04 23 52 2A 54 09 02 53 24 02 07 48 61
   73 68 4D 61 70 10 03 55 5D 42 0E 02 56 5B 0E 02
   57 5A 0D 01 58 0A 02 59 08 01 06 3C 72 6F 6F 74
   3E 09 01 07 09 02 5C 06 01 07 70 61 63 6B 61 67
   65 09 02 5E 5F 02 04 4C 69 73 74 0A 02 5C 06 08
   07 61 00 FFFFFFC0 FFFFFF80 FFFFFF84 08 62 01 0A 64 65 6C 74 61 71
   5F 24 65 71 14 02 32 63 08 07 36 60 FFFFFF81 FFFFFF80 FFFFFFC0 00
   4E 08 06 65 00 FFFFFFA0 FFFFFFA0 04 4E 01 07 64 65 6C 74 61
   71 20 08 07 67 00 FFFFFFC0 FFFFFF80 FFFFFF84 08 68 01 08 64 65 66
   61 75 6C 74 71 15 01 69 10 03 0F 4F 54 08 07 6B
   00 FFFFFFC0 FFFFFF80 FFFFFF84 08 6C 01 0C 64 65 66 61 75 6C 74 71
   5F 24 65 71 14 02 32 6D 08 07 36 6A FFFFFF81 FFFFFF80 FFFFFFC0 00
   69 08 06 6F 00 FFFFFFA0 FFFFFFA0 04 69 01 09 64 65 66 61 75
   6C 74 71 20 08 07 71 00 FFFFFFC0 FFFFFF80 FFFFFF84 08 72 01 08 69
   6E 69 74 69 61 6C 73 15 01 73 10 03 3D 74 42 09
   02 75 3E 02 03 53 65 74 08 07 77 00 FFFFFFC0 FFFFFF80 FFFFFF84 08
   78 01 0C 69 6E 69 74 69 61 6C 73 5F 24 65 71 14
   02 32 79 08 07 36 76 FFFFFF81 FFFFFF80 FFFFFFC0 00 73 08 06 7B 00
   FFFFFFA0 FFFFFFA0 04 73 01 09 69 6E 69 74 69 61 6C 73 20 08
   05 7D 00 FFFFFF84 28 7E 01 09 63 6F 6D 70 46 69 72 73
   74 14 02 73 7F 08 07 FFFFFF81 00 7C FFFFFFC0 00 FFFFFF81 01 01 01
   72 10 03 2B FFFFFF81 02 09 04 FFFFFF81 03 FFFFFF81 04 02 06 52 65
   67 45 78 70 09 03 FFFFFF81 05 1B 02 04 42 61 73 65 08
   07 FFFFFF81 07 00 FFFFFF84 28 FFFFFF81 08 01 08 63 6F 6D 70 4C 61
   73 74 14 03 73 FFFFFF81 09 08 08 FFFFFF81 00 FFFFFF81 06 FFFFFFC0 00 FFFFFF81
   01 08 07 FFFFFF81 0B 00 FFFFFF84 28 FFFFFF81 0C 01 0B 63 6F 6D 70
   46 6F 6C 6C 6F 77 31 14 05 73 FFFFFF81 0D FFFFFF81 0F 08 07
   FFFFFF81 0E FFFFFF81 0A FFFFFFC0 00 73 01 04 66 6F 6C 31 08 08 FFFFFF81
   00 FFFFFF81 0A FFFFFFC0 00 FFFFFF81 01 08 07 FFFFFF81 11 00 FFFFFF84 08 FFFFFF81 12
   01 09 73 65 65 6E 4C 61 62 65 6C 14 07 32 FFFFFF81 13
   FFFFFF81 14 FFFFFF81 16 08 08 FFFFFF81 00 FFFFFF81 10 FFFFFFC0 00 FFFFFF81 01 08 07
   FFFFFF81 15 FFFFFF81 10 FFFFFFC0 00 42 01 01 69 08 07 FFFFFF81 17 FFFFFF81 10
   FFFFFFC0 00 2A 01 05 6C 61 62 65 6C 08 07 FFFFFF81 11 00 FFFFFF84
   08 FFFFFF81 19 14 05 42 FFFFFF81 1A FFFFFF81 1B 08 08 FFFFFF81 00 FFFFFF81 18
   FFFFFFC0 00 FFFFFF81 01 08 07 FFFFFF81 17 FFFFFF81 18 FFFFFFC0 00 2A 08 07 FFFFFF81
   1D 00 FFFFFF84 20 FFFFFF81 1E 01 08 74 72 61 76 65 72 73 65
   14 03 32 FFFFFF81 1F 08 08 FFFFFF81 00 FFFFFF81 1C FFFFFFC0 00 FFFFFF81 01 08
   07 FFFFFF81 21 00 FFFFFF84 08 FFFFFF81 22 01 0E 6D 61 6B 65 54 72
   61 6E 73 69 74 69 6F 6E 14 07 32 FFFFFF81 23 FFFFFF81 25 FFFFFF81
   27 08 07 FFFFFF81 24 FFFFFF81 20 FFFFFFC0 00 42 01 03 73 72 63 08
   07 FFFFFF81 26 FFFFFF81 20 FFFFFFC0 00 42 01 04 64 65 73 74 08 07
   FFFFFF81 17 FFFFFF81 20 FFFFFFC0 00 2A 08 07 FFFFFF81 29 00 FFFFFF84 08 FFFFFF81 2A
   01 0A 69 6E 69 74 69 61 6C 69 7A 65 14 03 32 FFFFFF81
   2B 08 08 FFFFFF81 2C FFFFFF81 28 FFFFFFC0 00 FFFFFF81 2D 01 07 73 75 62
   65 78 70 72 10 05 55 FFFFFF81 2E FFFFFF81 01 09 03 FFFFFF81 2F 5F
   02 03 53 65 71 08 07 FFFFFF81 31 00 FFFFFF84 08 FFFFFF81 32 01 0F
   69 6E 69 74 69 61 6C 69 7A 65 41 75 74 6F 6D 14
   01 32 08 07 FFFFFF81 34 00 FFFFFF84 08 FFFFFF81 32 01 12 63 6F 6C
   6C 65 63 74 54 72 61 6E 73 69 74 69 6F 6E 73 08
   07 FFFFFF81 36 00 FFFFFF84 00 FFFFFF81 37 01 0D 61 75 74 6F 6D 61
   74 6F 6E 46 72 6F 6D 14 06 FFFFFF81 38 FFFFFF81 3B FFFFFF81 3D 10
   04 0B FFFFFF81 39 2A 09 03 FFFFFF81 3A 02 02 0F 4E 6F 6E 64
   65 74 57 6F 72 64 41 75 74 6F 6D 08 08 FFFFFF81 3C FFFFFF81
   35 FFFFFFC0 00 FFFFFF81 01 01 03 70 61 74 08 07 FFFFFF81 3E FFFFFF81 35
   FFFFFFC0 00 42 01 08 66 69 6E 61 6C 54 61 67 
  InnerClass: 
   public #295= #36 of #512; //Sequ=class scala/util/regexp/Base$Sequ of class scala/util/regexp/Base
   public abstract #515= #343 of #514; //ByOne=class scala/collection/immutable/Range$ByOne of class scala/collection/immutable/Range
   public abstract #516= #285 of #512; //RegExp=class scala/util/regexp/Base$RegExp of class scala/util/regexp/Base
   public final #519= #170 of #518; //$anon$2=class scala/Array$$anon$2 of class scala/Array
   public abstract #520= #123 of #294; //Label=class scala/util/regexp/WordExp$Label of class scala/util/regexp/WordExp
   public #521= #424 of #294; //Letter=class scala/util/regexp/WordExp$Letter of class scala/util/regexp/WordExp
   public #524= #103 of #523; //ofRef=class scala/collection/mutable/ArrayOps$ofRef of class scala/collection/mutable/ArrayOps
   public final #527= #116 of #526; //$anon$15=class scala/reflect/Manifest$$anon$15 of class scala/reflect/Manifest
   public final #528= #145 of #245; //$anon$1=class scala/reflect/ClassManifest$$anon$1 of class scala/reflect/ClassManifest
   public final #528= #278 of #30; //$anon$1=class scala/util/automata/WordBerrySethi$$anon$1 of class scala/util/automata/WordBerrySethi
   public final #529= #273 of #30; //$anonfun$4=class scala/util/automata/WordBerrySethi$$anonfun$4 of class scala/util/automata/WordBerrySethi
   public final #530= #256 of #30; //$anonfun$3=class scala/util/automata/WordBerrySethi$$anonfun$3 of class scala/util/automata/WordBerrySethi
   public final #531= #234 of #30; //$anonfun$2=class scala/util/automata/WordBerrySethi$$anonfun$2 of class scala/util/automata/WordBerrySethi
   public final #532= #181 of #30; //$anonfun$1=class scala/util/automata/WordBerrySethi$$anonfun$1 of class scala/util/automata/WordBerrySethi
   public #533= #131 of #245; //ClassTypeManifest=class scala/reflect/ClassManifest$ClassTypeManifest of class scala/reflect/ClassManifest
   public final #534= #376 of #30; //$anonfun$initialize$1=class scala/util/automata/WordBerrySethi$$anonfun$initialize$1 of class scala/util/automata/WordBerrySethi
   public final #535= #403 of #30; //$anonfun$makeTransition$1=class scala/util/automata/WordBerrySethi$$anonfun$makeTransition$1 of class scala/util/automata/WordBerrySethi
   public final #536= #345 of #30; //$anonfun$initializeAutom$1=class scala/util/automata/WordBerrySethi$$anonfun$initializeAutom$1 of class scala/util/automata/WordBerrySethi
   public final #537= #325 of #30; //$anonfun$collectTransitions$2=class scala/util/automata/WordBerrySethi$$anonfun$collectTransitions$2 of class scala/util/automata/WordBerrySethi
   public final #538= #322 of #30; //$anonfun$collectTransitions$1=class scala/util/automata/WordBerrySethi$$anonfun$collectTransitions$1 of class scala/util/automata/WordBerrySethi
  minor version: 0
  major version: 49
  Constant pool:
const #1 = Asciz	SourceFile;
const #2 = Asciz	WordBerrySethi.scala;
const #3 = Asciz	initials;
const #4 = Asciz	Lscala/collection/immutable/Set;;
const #5 = Asciz	Lscala/collection/immutable/Set<Ljava/lang/Integer;>;;
const #6 = Asciz	Signature;
const #7 = Asciz	defaultq;
const #8 = Asciz	[Lscala/collection/immutable/List;;
const #9 = Asciz	[Lscala/collection/immutable/List<Ljava/lang/Integer;>;;
const #10 = Asciz	deltaq;
const #11 = Asciz	[Lscala/collection/mutable/HashMap;;
const #12 = Asciz	[Lscala/collection/mutable/HashMap<Lscala/util/regexp/WordExp$Label;Lscala/collection/immutable/List<Ljava/lang/Integer;>;>;;
const #13 = Asciz	labelAt;
const #14 = Asciz	Lscala/collection/immutable/Map;;
const #15 = Asciz	Lscala/collection/immutable/Map<Ljava/lang/Integer;Lscala/util/regexp/WordExp$Label;>;;
const #16 = Asciz	labels;
const #17 = Asciz	Lscala/collection/mutable/HashSet;;
const #18 = Asciz	Lscala/collection/mutable/HashSet<Lscala/util/regexp/WordExp$Label;>;;
const #19 = Asciz	<init>;
const #20 = Asciz	()V;
const #21 = Asciz	Code;
const #22 = Asciz	LineNumberTable;
const #23 = Asciz	scala/util/automata/BaseBerrySethi;
const #24 = class	#23;	//  scala/util/automata/BaseBerrySethi
const #25 = NameAndType	#19:#20;//  "<init>":()V
const #26 = Method	#24.#25;	//  scala/util/automata/BaseBerrySethi."<init>":()V
const #27 = Asciz	automatonFrom;
const #28 = Asciz	(Lscala/util/regexp/Base$RegExp;I)Lscala/util/automata/NondetWordAutom;;
const #29 = Asciz	scala/util/automata/WordBerrySethi;
const #30 = class	#29;	//  scala/util/automata/WordBerrySethi
const #31 = Asciz	finalTag_$eq;
const #32 = Asciz	(I)V;
const #33 = NameAndType	#31:#32;//  finalTag_$eq:(I)V
const #34 = Method	#30.#33;	//  scala/util/automata/WordBerrySethi.finalTag_$eq:(I)V
const #35 = Asciz	scala/util/regexp/Base$Sequ;
const #36 = class	#35;	//  scala/util/regexp/Base$Sequ
const #37 = Asciz	rs;
const #38 = Asciz	()Lscala/collection/Seq;;
const #39 = NameAndType	#37:#38;//  rs:()Lscala/collection/Seq;
const #40 = Method	#36.#39;	//  scala/util/regexp/Base$Sequ.rs:()Lscala/collection/Seq;
const #41 = Asciz	initialize;
const #42 = Asciz	(Lscala/collection/Seq;)V;
const #43 = NameAndType	#41:#42;//  initialize:(Lscala/collection/Seq;)V
const #44 = Method	#30.#43;	//  scala/util/automata/WordBerrySethi.initialize:(Lscala/collection/Seq;)V
const #45 = Asciz	pos;
const #46 = Asciz	()I;
const #47 = NameAndType	#45:#46;//  pos:()I
const #48 = Method	#30.#47;	//  scala/util/automata/WordBerrySethi.pos:()I
const #49 = Asciz	pos_$eq;
const #50 = NameAndType	#49:#32;//  pos_$eq:(I)V
const #51 = Method	#30.#50;	//  scala/util/automata/WordBerrySethi.pos_$eq:(I)V
const #52 = Asciz	compFollow;
const #53 = Asciz	(Lscala/collection/Seq;)Lscala/collection/immutable/Set;;
const #54 = NameAndType	#52:#53;//  compFollow:(Lscala/collection/Seq;)Lscala/collection/immutable/Set;
const #55 = Method	#30.#54;	//  scala/util/automata/WordBerrySethi.compFollow:(Lscala/collection/Seq;)Lscala/collection/immutable/Set;
const #56 = Asciz	initializeAutom;
const #57 = NameAndType	#56:#20;//  initializeAutom:()V
const #58 = Method	#30.#57;	//  scala/util/automata/WordBerrySethi.initializeAutom:()V
const #59 = Asciz	collectTransitions;
const #60 = NameAndType	#59:#20;//  collectTransitions:()V
const #61 = Method	#30.#60;	//  scala/util/automata/WordBerrySethi.collectTransitions:()V
const #62 = Asciz	isNullable;
const #63 = Asciz	()Z;
const #64 = NameAndType	#62:#63;//  isNullable:()Z
const #65 = Method	#36.#64;	//  scala/util/regexp/Base$Sequ.isNullable:()Z
const #66 = Asciz	finals;
const #67 = Asciz	()Lscala/collection/immutable/Map;;
const #68 = NameAndType	#66:#67;//  finals:()Lscala/collection/immutable/Map;
const #69 = Method	#30.#68;	//  scala/util/automata/WordBerrySethi.finals:()Lscala/collection/immutable/Map;
const #70 = Asciz	scala/runtime/BoxesRunTime;
const #71 = class	#70;	//  scala/runtime/BoxesRunTime
const #72 = Asciz	boxToInteger;
const #73 = Asciz	(I)Ljava/lang/Integer;;
const #74 = NameAndType	#72:#73;//  boxToInteger:(I)Ljava/lang/Integer;
const #75 = Method	#71.#74;	//  scala/runtime/BoxesRunTime.boxToInteger:(I)Ljava/lang/Integer;
const #76 = Asciz	scala/collection/immutable/MapLike;
const #77 = class	#76;	//  scala/collection/immutable/MapLike
const #78 = Asciz	updated;
const #79 = Asciz	(Ljava/lang/Object;Ljava/lang/Object;)Lscala/collection/immutable/Map;;
const #80 = NameAndType	#78:#79;//  updated:(Ljava/lang/Object;Ljava/lang/Object;)Lscala/collection/immutable/Map;
const #81 = InterfaceMethod	#77.#80;	//  scala/collection/immutable/MapLike.updated:(Ljava/lang/Object;Ljava/lang/Object;)Lscala/collection/immutable/Map;
const #82 = Asciz	finals_$eq;
const #83 = Asciz	(Lscala/collection/immutable/Map;)V;
const #84 = NameAndType	#82:#83;//  finals_$eq:(Lscala/collection/immutable/Map;)V
const #85 = Method	#30.#84;	//  scala/util/automata/WordBerrySethi.finals_$eq:(Lscala/collection/immutable/Map;)V
const #86 = Asciz	scala/collection/immutable/Map$;
const #87 = class	#86;	//  scala/collection/immutable/Map$
const #88 = Asciz	MODULE$;
const #89 = Asciz	Lscala/collection/immutable/Map$;;
const #90 = NameAndType	#88:#89;//  MODULE$:Lscala/collection/immutable/Map$;
const #91 = Field	#87.#90;	//  scala/collection/immutable/Map$.MODULE$:Lscala/collection/immutable/Map$;
const #92 = Asciz	scala/Predef$;
const #93 = class	#92;	//  scala/Predef$
const #94 = Asciz	Lscala/Predef$;;
const #95 = NameAndType	#88:#94;//  MODULE$:Lscala/Predef$;
const #96 = Field	#93.#95;	//  scala/Predef$.MODULE$:Lscala/Predef$;
const #97 = Asciz	()[Lscala/collection/mutable/HashMap;;
const #98 = NameAndType	#10:#97;//  deltaq:()[Lscala/collection/mutable/HashMap;
const #99 = Method	#30.#98;	//  scala/util/automata/WordBerrySethi.deltaq:()[Lscala/collection/mutable/HashMap;
const #100 = Asciz	[Ljava/lang/Object;;
const #101 = class	#100;	//  "[Ljava/lang/Object;"
const #102 = Asciz	scala/collection/mutable/ArrayOps$ofRef;
const #103 = class	#102;	//  scala/collection/mutable/ArrayOps$ofRef
const #104 = Asciz	([Ljava/lang/Object;)V;
const #105 = NameAndType	#19:#104;//  "<init>":([Ljava/lang/Object;)V
const #106 = Method	#103.#105;	//  scala/collection/mutable/ArrayOps$ofRef."<init>":([Ljava/lang/Object;)V
const #107 = Asciz	scala/Tuple2;
const #108 = class	#107;	//  scala/Tuple2
const #109 = Asciz	scala/collection/mutable/HashMap;
const #110 = class	#109;	//  scala/collection/mutable/HashMap
const #111 = Asciz	lang;
const #112 = Asciz	()Lscala/util/regexp/WordExp;;
const #113 = NameAndType	#111:#112;//  lang:()Lscala/util/regexp/WordExp;
const #114 = Method	#30.#113;	//  scala/util/automata/WordBerrySethi.lang:()Lscala/util/regexp/WordExp;
const #115 = Asciz	scala/reflect/Manifest$$anon$15;
const #116 = class	#115;	//  scala/reflect/Manifest$$anon$15
const #117 = Asciz	(Ljava/lang/Object;)V;
const #118 = NameAndType	#19:#117;//  "<init>":(Ljava/lang/Object;)V
const #119 = Method	#116.#118;	//  scala/reflect/Manifest$$anon$15."<init>":(Ljava/lang/Object;)V
const #120 = Asciz	_labelT;
const #121 = String	#120;	//  _labelT
const #122 = Asciz	scala/util/regexp/WordExp$Label;
const #123 = class	#122;	//  scala/util/regexp/WordExp$Label
const #124 = Asciz	scala/reflect/OptManifest;
const #125 = class	#124;	//  scala/reflect/OptManifest
const #126 = Asciz	wrapRefArray;
const #127 = Asciz	([Ljava/lang/Object;)Lscala/collection/mutable/WrappedArray;;
const #128 = NameAndType	#126:#127;//  wrapRefArray:([Ljava/lang/Object;)Lscala/collection/mutable/WrappedArray;
const #129 = Method	#93.#128;	//  scala/Predef$.wrapRefArray:([Ljava/lang/Object;)Lscala/collection/mutable/WrappedArray;
const #130 = Asciz	scala/reflect/ClassManifest$ClassTypeManifest;
const #131 = class	#130;	//  scala/reflect/ClassManifest$ClassTypeManifest
const #132 = Asciz	scala/Some;
const #133 = class	#132;	//  scala/Some
const #134 = Method	#133.#118;	//  scala/Some."<init>":(Ljava/lang/Object;)V
const #135 = Asciz	scala/collection/TraversableLike;
const #136 = class	#135;	//  scala/collection/TraversableLike
const #137 = Asciz	toList;
const #138 = Asciz	()Lscala/collection/immutable/List;;
const #139 = NameAndType	#137:#138;//  toList:()Lscala/collection/immutable/List;
const #140 = InterfaceMethod	#136.#139;	//  scala/collection/TraversableLike.toList:()Lscala/collection/immutable/List;
const #141 = Asciz	(Lscala/Option;Ljava/lang/Class;Lscala/collection/immutable/List;)V;
const #142 = NameAndType	#19:#141;//  "<init>":(Lscala/Option;Ljava/lang/Class;Lscala/collection/immutable/List;)V
const #143 = Method	#131.#142;	//  scala/reflect/ClassManifest$ClassTypeManifest."<init>":(Lscala/Option;Ljava/lang/Class;Lscala/collection/immutable/List;)V
const #144 = Asciz	scala/reflect/ClassManifest$$anon$1;
const #145 = class	#144;	//  scala/reflect/ClassManifest$$anon$1
const #146 = Asciz	(Lscala/reflect/OptManifest;Ljava/lang/String;Lscala/reflect/ClassManifest;Lscala/collection/Seq;)V;
const #147 = NameAndType	#19:#146;//  "<init>":(Lscala/reflect/OptManifest;Ljava/lang/String;Lscala/reflect/ClassManifest;Lscala/collection/Seq;)V
const #148 = Method	#145.#147;	//  scala/reflect/ClassManifest$$anon$1."<init>":(Lscala/reflect/OptManifest;Ljava/lang/String;Lscala/reflect/ClassManifest;Lscala/collection/Seq;)V
const #149 = Asciz	scala/collection/immutable/List;
const #150 = class	#149;	//  scala/collection/immutable/List
const #151 = Asciz	scala/reflect/Manifest$;
const #152 = class	#151;	//  scala/reflect/Manifest$
const #153 = Asciz	Lscala/reflect/Manifest$;;
const #154 = NameAndType	#88:#153;//  MODULE$:Lscala/reflect/Manifest$;
const #155 = Field	#152.#154;	//  scala/reflect/Manifest$.MODULE$:Lscala/reflect/Manifest$;
const #156 = Asciz	Int;
const #157 = Asciz	()Ljava/lang/Object;;
const #158 = NameAndType	#156:#157;//  Int:()Ljava/lang/Object;
const #159 = Method	#152.#158;	//  scala/reflect/Manifest$.Int:()Ljava/lang/Object;
const #160 = Asciz	scala/None$;
const #161 = class	#160;	//  scala/None$
const #162 = Asciz	Lscala/None$;;
const #163 = NameAndType	#88:#162;//  MODULE$:Lscala/None$;
const #164 = Field	#161.#163;	//  scala/None$.MODULE$:Lscala/None$;
const #165 = Asciz	$colon$colon;
const #166 = Asciz	(Ljava/lang/Object;)Lscala/collection/immutable/List;;
const #167 = NameAndType	#165:#166;//  $colon$colon:(Ljava/lang/Object;)Lscala/collection/immutable/List;
const #168 = Method	#150.#167;	//  scala/collection/immutable/List.$colon$colon:(Ljava/lang/Object;)Lscala/collection/immutable/List;
const #169 = Asciz	scala/Array$$anon$2;
const #170 = class	#169;	//  scala/Array$$anon$2
const #171 = Asciz	(Lscala/reflect/ClassManifest;)V;
const #172 = NameAndType	#19:#171;//  "<init>":(Lscala/reflect/ClassManifest;)V
const #173 = Method	#170.#172;	//  scala/Array$$anon$2."<init>":(Lscala/reflect/ClassManifest;)V
const #174 = Asciz	scala/collection/IndexedSeqLike;
const #175 = class	#174;	//  scala/collection/IndexedSeqLike
const #176 = Asciz	zipWithIndex;
const #177 = Asciz	(Lscala/collection/generic/CanBuildFrom;)Ljava/lang/Object;;
const #178 = NameAndType	#176:#177;//  zipWithIndex:(Lscala/collection/generic/CanBuildFrom;)Ljava/lang/Object;
const #179 = InterfaceMethod	#175.#178;	//  scala/collection/IndexedSeqLike.zipWithIndex:(Lscala/collection/generic/CanBuildFrom;)Ljava/lang/Object;
const #180 = Asciz	scala/util/automata/WordBerrySethi$$anonfun$1;
const #181 = class	#180;	//  scala/util/automata/WordBerrySethi$$anonfun$1
const #182 = Asciz	(Lscala/util/automata/WordBerrySethi;)V;
const #183 = NameAndType	#19:#182;//  "<init>":(Lscala/util/automata/WordBerrySethi;)V
const #184 = Method	#181.#183;	//  scala/util/automata/WordBerrySethi$$anonfun$1."<init>":(Lscala/util/automata/WordBerrySethi;)V
const #185 = Asciz	scala/Array$;
const #186 = class	#185;	//  scala/Array$
const #187 = Asciz	Lscala/Array$;;
const #188 = NameAndType	#88:#187;//  MODULE$:Lscala/Array$;
const #189 = Field	#186.#188;	//  scala/Array$.MODULE$:Lscala/Array$;
const #190 = Asciz	scala/reflect/ClassManifest$;
const #191 = class	#190;	//  scala/reflect/ClassManifest$
const #192 = Asciz	Lscala/reflect/ClassManifest$;;
const #193 = NameAndType	#88:#192;//  MODULE$:Lscala/reflect/ClassManifest$;
const #194 = Field	#191.#193;	//  scala/reflect/ClassManifest$.MODULE$:Lscala/reflect/ClassManifest$;
const #195 = Asciz	singleType;
const #196 = Asciz	(Ljava/lang/Object;)Lscala/reflect/Manifest;;
const #197 = NameAndType	#195:#196;//  singleType:(Ljava/lang/Object;)Lscala/reflect/Manifest;
const #198 = Method	#191.#197;	//  scala/reflect/ClassManifest$.singleType:(Ljava/lang/Object;)Lscala/reflect/Manifest;
const #199 = Asciz	abstractType;
const #200 = Asciz	(Lscala/reflect/OptManifest;Ljava/lang/String;Lscala/reflect/ClassManifest;Lscala/collection/Seq;)Lscala/reflect/ClassManifest;;
const #201 = NameAndType	#199:#200;//  abstractType:(Lscala/reflect/OptManifest;Ljava/lang/String;Lscala/reflect/ClassManifest;Lscala/collection/Seq;)Lscala/reflect/ClassManifest;
const #202 = Method	#191.#201;	//  scala/reflect/ClassManifest$.abstractType:(Lscala/reflect/OptManifest;Ljava/lang/String;Lscala/reflect/ClassManifest;Lscala/collection/Seq;)Lscala/reflect/ClassManifest;
const #203 = Asciz	classType;
const #204 = Asciz	(Ljava/lang/Class;Lscala/reflect/OptManifest;Lscala/collection/Seq;)Lscala/reflect/ClassManifest;;
const #205 = NameAndType	#203:#204;//  classType:(Ljava/lang/Class;Lscala/reflect/OptManifest;Lscala/collection/Seq;)Lscala/reflect/ClassManifest;
const #206 = Method	#191.#205;	//  scala/reflect/ClassManifest$.classType:(Ljava/lang/Class;Lscala/reflect/OptManifest;Lscala/collection/Seq;)Lscala/reflect/ClassManifest;
const #207 = Asciz	canBuildFrom;
const #208 = Asciz	(Lscala/reflect/ClassManifest;)Lscala/collection/generic/CanBuildFrom;;
const #209 = NameAndType	#207:#208;//  canBuildFrom:(Lscala/reflect/ClassManifest;)Lscala/collection/generic/CanBuildFrom;
const #210 = Method	#186.#209;	//  scala/Array$.canBuildFrom:(Lscala/reflect/ClassManifest;)Lscala/collection/generic/CanBuildFrom;
const #211 = Asciz	map;
const #212 = Asciz	(Lscala/Function1;Lscala/collection/generic/CanBuildFrom;)Ljava/lang/Object;;
const #213 = NameAndType	#211:#212;//  map:(Lscala/Function1;Lscala/collection/generic/CanBuildFrom;)Ljava/lang/Object;
const #214 = InterfaceMethod	#136.#213;	//  scala/collection/TraversableLike.map:(Lscala/Function1;Lscala/collection/generic/CanBuildFrom;)Ljava/lang/Object;
const #215 = Asciz	[Lscala/Tuple2;;
const #216 = class	#215;	//  "[Lscala/Tuple2;"
const #217 = Asciz	apply;
const #218 = Asciz	(Lscala/collection/Seq;)Lscala/collection/Map;;
const #219 = NameAndType	#217:#218;//  apply:(Lscala/collection/Seq;)Lscala/collection/Map;
const #220 = Method	#87.#219;	//  scala/collection/immutable/Map$.apply:(Lscala/collection/Seq;)Lscala/collection/Map;
const #221 = Asciz	scala/collection/immutable/Map;
const #222 = class	#221;	//  scala/collection/immutable/Map
const #223 = Asciz	intWrapper;
const #224 = Asciz	(I)Lscala/runtime/RichInt;;
const #225 = NameAndType	#223:#224;//  intWrapper:(I)Lscala/runtime/RichInt;
const #226 = Method	#93.#225;	//  scala/Predef$.intWrapper:(I)Lscala/runtime/RichInt;
const #227 = Asciz	scala/runtime/RichInt;
const #228 = class	#227;	//  scala/runtime/RichInt
const #229 = Asciz	until;
const #230 = Asciz	(I)Lscala/collection/immutable/Range;;
const #231 = NameAndType	#229:#230;//  until:(I)Lscala/collection/immutable/Range;
const #232 = Method	#228.#231;	//  scala/runtime/RichInt.until:(I)Lscala/collection/immutable/Range;
const #233 = Asciz	scala/util/automata/WordBerrySethi$$anonfun$2;
const #234 = class	#233;	//  scala/util/automata/WordBerrySethi$$anonfun$2
const #235 = Method	#234.#183;	//  scala/util/automata/WordBerrySethi$$anonfun$2."<init>":(Lscala/util/automata/WordBerrySethi;)V
const #236 = Asciz	scala/collection/immutable/IndexedSeq$;
const #237 = class	#236;	//  scala/collection/immutable/IndexedSeq$
const #238 = Asciz	Lscala/collection/immutable/IndexedSeq$;;
const #239 = NameAndType	#88:#238;//  MODULE$:Lscala/collection/immutable/IndexedSeq$;
const #240 = Field	#237.#239;	//  scala/collection/immutable/IndexedSeq$.MODULE$:Lscala/collection/immutable/IndexedSeq$;
const #241 = Asciz	()Lscala/collection/generic/CanBuildFrom;;
const #242 = NameAndType	#207:#241;//  canBuildFrom:()Lscala/collection/generic/CanBuildFrom;
const #243 = Method	#237.#242;	//  scala/collection/immutable/IndexedSeq$.canBuildFrom:()Lscala/collection/generic/CanBuildFrom;
const #244 = Asciz	scala/reflect/ClassManifest;
const #245 = class	#244;	//  scala/reflect/ClassManifest
const #246 = Asciz	toArray;
const #247 = Asciz	(Lscala/reflect/ClassManifest;)Ljava/lang/Object;;
const #248 = NameAndType	#246:#247;//  toArray:(Lscala/reflect/ClassManifest;)Ljava/lang/Object;
const #249 = InterfaceMethod	#136.#248;	//  scala/collection/TraversableLike.toArray:(Lscala/reflect/ClassManifest;)Ljava/lang/Object;
const #250 = Asciz	[I;
const #251 = class	#250;	//  "[I"
const #252 = Asciz	()Lscala/collection/immutable/Set;;
const #253 = NameAndType	#3:#252;//  initials:()Lscala/collection/immutable/Set;
const #254 = Method	#30.#253;	//  scala/util/automata/WordBerrySethi.initials:()Lscala/collection/immutable/Set;
const #255 = Asciz	scala/util/automata/WordBerrySethi$$anonfun$3;
const #256 = class	#255;	//  scala/util/automata/WordBerrySethi$$anonfun$3
const #257 = Asciz	(Lscala/util/automata/WordBerrySethi;Lscala/collection/immutable/Map;)V;
const #258 = NameAndType	#19:#257;//  "<init>":(Lscala/util/automata/WordBerrySethi;Lscala/collection/immutable/Map;)V
const #259 = Method	#256.#258;	//  scala/util/automata/WordBerrySethi$$anonfun$3."<init>":(Lscala/util/automata/WordBerrySethi;Lscala/collection/immutable/Map;)V
const #260 = Asciz	scala/collection/Map;
const #261 = class	#260;	//  scala/collection/Map
const #262 = Asciz	(Lscala/reflect/OptManifest;Ljava/lang/Class;Lscala/collection/Seq;)Lscala/reflect/ClassManifest;;
const #263 = NameAndType	#203:#262;//  classType:(Lscala/reflect/OptManifest;Ljava/lang/Class;Lscala/collection/Seq;)Lscala/reflect/ClassManifest;
const #264 = Method	#191.#263;	//  scala/reflect/ClassManifest$.classType:(Lscala/reflect/OptManifest;Ljava/lang/Class;Lscala/collection/Seq;)Lscala/reflect/ClassManifest;
const #265 = Asciz	scala/collection/immutable/BitSet;
const #266 = class	#265;	//  scala/collection/immutable/BitSet
const #267 = Asciz	(Ljava/lang/Class;)Lscala/reflect/ClassManifest;;
const #268 = NameAndType	#203:#267;//  classType:(Ljava/lang/Class;)Lscala/reflect/ClassManifest;
const #269 = Method	#191.#268;	//  scala/reflect/ClassManifest$.classType:(Ljava/lang/Class;)Lscala/reflect/ClassManifest;
const #270 = Asciz	[Lscala/collection/Map;;
const #271 = class	#270;	//  "[Lscala/collection/Map;"
const #272 = Asciz	scala/util/automata/WordBerrySethi$$anonfun$4;
const #273 = class	#272;	//  scala/util/automata/WordBerrySethi$$anonfun$4
const #274 = Method	#273.#183;	//  scala/util/automata/WordBerrySethi$$anonfun$4."<init>":(Lscala/util/automata/WordBerrySethi;)V
const #275 = Asciz	[Lscala/collection/immutable/BitSet;;
const #276 = class	#275;	//  "[Lscala/collection/immutable/BitSet;"
const #277 = Asciz	scala/util/automata/WordBerrySethi$$anon$1;
const #278 = class	#277;	//  scala/util/automata/WordBerrySethi$$anon$1
const #279 = Asciz	(Lscala/util/automata/WordBerrySethi;[I[I[Lscala/collection/Map;[Lscala/collection/immutable/BitSet;)V;
const #280 = NameAndType	#19:#279;//  "<init>":(Lscala/util/automata/WordBerrySethi;[I[I[Lscala/collection/Map;[Lscala/collection/immutable/BitSet;)V
const #281 = Method	#278.#280;	//  scala/util/automata/WordBerrySethi$$anon$1."<init>":(Lscala/util/automata/WordBerrySethi;[I[I[Lscala/collection/Map;[Lscala/collection/immutable/BitSet;)V
const #282 = Asciz	scala/MatchError;
const #283 = class	#282;	//  scala/MatchError
const #284 = Asciz	scala/util/regexp/Base$RegExp;
const #285 = class	#284;	//  scala/util/regexp/Base$RegExp
const #286 = Asciz	toString;
const #287 = Asciz	()Ljava/lang/String;;
const #288 = NameAndType	#286:#287;//  toString:()Ljava/lang/String;
const #289 = Method	#285.#288;	//  scala/util/regexp/Base$RegExp.toString:()Ljava/lang/String;
const #290 = Asciz	(Ljava/lang/String;)V;
const #291 = NameAndType	#19:#290;//  "<init>":(Ljava/lang/String;)V
const #292 = Method	#283.#291;	//  scala/MatchError."<init>":(Ljava/lang/String;)V
const #293 = Asciz	scala/util/regexp/WordExp;
const #294 = class	#293;	//  scala/util/regexp/WordExp
const #295 = Asciz	Sequ;
const #296 = Asciz	()Lscala/util/regexp/Base$Sequ$;;
const #297 = NameAndType	#295:#296;//  Sequ:()Lscala/util/regexp/Base$Sequ$;
const #298 = Method	#294.#297;	//  scala/util/regexp/WordExp.Sequ:()Lscala/util/regexp/Base$Sequ$;
const #299 = Asciz	scala/util/regexp/Base$Sequ$;
const #300 = class	#299;	//  scala/util/regexp/Base$Sequ$
const #301 = Asciz	(Lscala/collection/Seq;)Lscala/util/regexp/Base$RegExp;;
const #302 = NameAndType	#217:#301;//  apply:(Lscala/collection/Seq;)Lscala/util/regexp/Base$RegExp;
const #303 = Method	#300.#302;	//  scala/util/regexp/Base$Sequ$.apply:(Lscala/collection/Seq;)Lscala/util/regexp/Base$RegExp;
const #304 = NameAndType	#27:#28;//  automatonFrom:(Lscala/util/regexp/Base$RegExp;I)Lscala/util/automata/NondetWordAutom;
const #305 = Method	#30.#304;	//  scala/util/automata/WordBerrySethi.automatonFrom:(Lscala/util/regexp/Base$RegExp;I)Lscala/util/automata/NondetWordAutom;
const #306 = Asciz	this;
const #307 = Asciz	Lscala/util/automata/WordBerrySethi;;
const #308 = Asciz	pat;
const #309 = Asciz	Lscala/util/regexp/Base$RegExp;;
const #310 = Asciz	finalTag;
const #311 = Asciz	I;
const #312 = Asciz	temp20;
const #313 = Asciz	Lscala/util/regexp/Base$Sequ;;
const #314 = Asciz	delta1$1;
const #315 = Asciz	finalsArr$1;
const #316 = Asciz	initialsArr$1;
const #317 = Asciz	deltaArr$1;
const #318 = Asciz	defaultArr$1;
const #319 = Asciz	LocalVariableTable;
const #320 = Asciz	(Lscala/util/regexp/Base$RegExp;I)Lscala/util/automata/NondetWordAutom<Lscala/util/regexp/WordExp$Label;>;;
const #321 = Asciz	scala/util/automata/WordBerrySethi$$anonfun$collectTransitions$1;
const #322 = class	#321;	//  scala/util/automata/WordBerrySethi$$anonfun$collectTransitions$1
const #323 = Method	#322.#183;	//  scala/util/automata/WordBerrySethi$$anonfun$collectTransitions$1."<init>":(Lscala/util/automata/WordBerrySethi;)V
const #324 = Asciz	scala/util/automata/WordBerrySethi$$anonfun$collectTransitions$2;
const #325 = class	#324;	//  scala/util/automata/WordBerrySethi$$anonfun$collectTransitions$2
const #326 = Method	#325.#183;	//  scala/util/automata/WordBerrySethi$$anonfun$collectTransitions$2."<init>":(Lscala/util/automata/WordBerrySethi;)V
const #327 = Asciz	foreach;
const #328 = Asciz	(Lscala/Function1;)V;
const #329 = NameAndType	#327:#328;//  foreach:(Lscala/Function1;)V
const #330 = InterfaceMethod	#175.#329;	//  scala/collection/IndexedSeqLike.foreach:(Lscala/Function1;)V
const #331 = Asciz	empty;
const #332 = NameAndType	#331:#67;//  empty:()Lscala/collection/immutable/Map;
const #333 = Method	#87.#332;	//  scala/collection/immutable/Map$.empty:()Lscala/collection/immutable/Map;
const #334 = Asciz	deltaq_$eq;
const #335 = Asciz	([Lscala/collection/mutable/HashMap;)V;
const #336 = NameAndType	#334:#335;//  deltaq_$eq:([Lscala/collection/mutable/HashMap;)V
const #337 = Method	#30.#336;	//  scala/util/automata/WordBerrySethi.deltaq_$eq:([Lscala/collection/mutable/HashMap;)V
const #338 = Asciz	defaultq_$eq;
const #339 = Asciz	([Lscala/collection/immutable/List;)V;
const #340 = NameAndType	#338:#339;//  defaultq_$eq:([Lscala/collection/immutable/List;)V
const #341 = Method	#30.#340;	//  scala/util/automata/WordBerrySethi.defaultq_$eq:([Lscala/collection/immutable/List;)V
const #342 = Asciz	scala/collection/immutable/Range$ByOne;
const #343 = class	#342;	//  scala/collection/immutable/Range$ByOne
const #344 = Asciz	scala/util/automata/WordBerrySethi$$anonfun$initializeAutom$1;
const #345 = class	#344;	//  scala/util/automata/WordBerrySethi$$anonfun$initializeAutom$1
const #346 = Method	#345.#183;	//  scala/util/automata/WordBerrySethi$$anonfun$initializeAutom$1."<init>":(Lscala/util/automata/WordBerrySethi;)V
const #347 = InterfaceMethod	#343.#329;	//  scala/collection/immutable/Range$ByOne.foreach:(Lscala/Function1;)V
const #348 = Asciz	labelAt_$eq;
const #349 = NameAndType	#348:#83;//  labelAt_$eq:(Lscala/collection/immutable/Map;)V
const #350 = Method	#30.#349;	//  scala/util/automata/WordBerrySethi.labelAt_$eq:(Lscala/collection/immutable/Map;)V
const #351 = Asciz	scala/collection/mutable/HashMap$;
const #352 = class	#351;	//  scala/collection/mutable/HashMap$
const #353 = Asciz	Lscala/collection/mutable/HashMap$;;
const #354 = NameAndType	#88:#353;//  MODULE$:Lscala/collection/mutable/HashMap$;
const #355 = Field	#352.#354;	//  scala/collection/mutable/HashMap$.MODULE$:Lscala/collection/mutable/HashMap$;
const #356 = Method	#352.#219;	//  scala/collection/mutable/HashMap$.apply:(Lscala/collection/Seq;)Lscala/collection/Map;
const #357 = Asciz	follow_$eq;
const #358 = Asciz	(Lscala/collection/mutable/HashMap;)V;
const #359 = NameAndType	#357:#358;//  follow_$eq:(Lscala/collection/mutable/HashMap;)V
const #360 = Method	#30.#359;	//  scala/util/automata/WordBerrySethi.follow_$eq:(Lscala/collection/mutable/HashMap;)V
const #361 = Asciz	scala/collection/mutable/HashSet$;
const #362 = class	#361;	//  scala/collection/mutable/HashSet$
const #363 = Asciz	Lscala/collection/mutable/HashSet$;;
const #364 = NameAndType	#88:#363;//  MODULE$:Lscala/collection/mutable/HashSet$;
const #365 = Field	#362.#364;	//  scala/collection/mutable/HashSet$.MODULE$:Lscala/collection/mutable/HashSet$;
const #366 = Asciz	(Lscala/collection/Seq;)Lscala/collection/Traversable;;
const #367 = NameAndType	#217:#366;//  apply:(Lscala/collection/Seq;)Lscala/collection/Traversable;
const #368 = Method	#362.#367;	//  scala/collection/mutable/HashSet$.apply:(Lscala/collection/Seq;)Lscala/collection/Traversable;
const #369 = Asciz	scala/collection/mutable/HashSet;
const #370 = class	#369;	//  scala/collection/mutable/HashSet
const #371 = Asciz	labels_$eq;
const #372 = Asciz	(Lscala/collection/mutable/HashSet;)V;
const #373 = NameAndType	#371:#372;//  labels_$eq:(Lscala/collection/mutable/HashSet;)V
const #374 = Method	#30.#373;	//  scala/util/automata/WordBerrySethi.labels_$eq:(Lscala/collection/mutable/HashSet;)V
const #375 = Asciz	scala/util/automata/WordBerrySethi$$anonfun$initialize$1;
const #376 = class	#375;	//  scala/util/automata/WordBerrySethi$$anonfun$initialize$1
const #377 = Method	#376.#183;	//  scala/util/automata/WordBerrySethi$$anonfun$initialize$1."<init>":(Lscala/util/automata/WordBerrySethi;)V
const #378 = Asciz	scala/collection/IterableLike;
const #379 = class	#378;	//  scala/collection/IterableLike
const #380 = InterfaceMethod	#379.#329;	//  scala/collection/IterableLike.foreach:(Lscala/Function1;)V
const #381 = Asciz	scala/collection/immutable/Set$;
const #382 = class	#381;	//  scala/collection/immutable/Set$
const #383 = Asciz	Lscala/collection/immutable/Set$;;
const #384 = NameAndType	#88:#383;//  MODULE$:Lscala/collection/immutable/Set$;
const #385 = Field	#382.#384;	//  scala/collection/immutable/Set$.MODULE$:Lscala/collection/immutable/Set$;
const #386 = Asciz	wrapIntArray;
const #387 = Asciz	([I)Lscala/collection/mutable/WrappedArray;;
const #388 = NameAndType	#386:#387;//  wrapIntArray:([I)Lscala/collection/mutable/WrappedArray;
const #389 = Method	#93.#388;	//  scala/Predef$.wrapIntArray:([I)Lscala/collection/mutable/WrappedArray;
const #390 = Method	#382.#367;	//  scala/collection/immutable/Set$.apply:(Lscala/collection/Seq;)Lscala/collection/Traversable;
const #391 = Asciz	scala/collection/immutable/Set;
const #392 = class	#391;	//  scala/collection/immutable/Set
const #393 = Asciz	initials_$eq;
const #394 = Asciz	(Lscala/collection/immutable/Set;)V;
const #395 = NameAndType	#393:#394;//  initials_$eq:(Lscala/collection/immutable/Set;)V
const #396 = Method	#30.#395;	//  scala/util/automata/WordBerrySethi.initials_$eq:(Lscala/collection/immutable/Set;)V
const #397 = Asciz	subexpr;
const #398 = Asciz	Lscala/collection/Seq;;
const #399 = Asciz	(Lscala/collection/Seq<Lscala/util/regexp/Base$RegExp;>;)V;
const #400 = Asciz	makeTransition;
const #401 = Asciz	(IILscala/util/regexp/WordExp$Label;)V;
const #402 = Asciz	scala/util/automata/WordBerrySethi$$anonfun$makeTransition$1;
const #403 = class	#402;	//  scala/util/automata/WordBerrySethi$$anonfun$makeTransition$1
const #404 = Method	#403.#183;	//  scala/util/automata/WordBerrySethi$$anonfun$makeTransition$1."<init>":(Lscala/util/automata/WordBerrySethi;)V
const #405 = Asciz	scala/collection/MapLike;
const #406 = class	#405;	//  scala/collection/MapLike
const #407 = Asciz	getOrElse;
const #408 = Asciz	(Ljava/lang/Object;Lscala/Function0;)Ljava/lang/Object;;
const #409 = NameAndType	#407:#408;//  getOrElse:(Ljava/lang/Object;Lscala/Function0;)Ljava/lang/Object;
const #410 = InterfaceMethod	#406.#409;	//  scala/collection/MapLike.getOrElse:(Ljava/lang/Object;Lscala/Function0;)Ljava/lang/Object;
const #411 = Asciz	update;
const #412 = Asciz	(Ljava/lang/Object;Ljava/lang/Object;)V;
const #413 = NameAndType	#411:#412;//  update:(Ljava/lang/Object;Ljava/lang/Object;)V
const #414 = Method	#110.#413;	//  scala/collection/mutable/HashMap.update:(Ljava/lang/Object;Ljava/lang/Object;)V
const #415 = Asciz	src;
const #416 = Asciz	dest;
const #417 = Asciz	label;
const #418 = Asciz	Lscala/util/regexp/WordExp$Label;;
const #419 = Asciz	q;
const #420 = Asciz	Lscala/collection/mutable/HashMap;;
const #421 = Asciz	traverse;
const #422 = Asciz	(Lscala/util/regexp/Base$RegExp;)V;
const #423 = Asciz	scala/util/regexp/WordExp$Letter;
const #424 = class	#423;	//  scala/util/regexp/WordExp$Letter
const #425 = Asciz	a;
const #426 = Asciz	()Lscala/util/regexp/WordExp$Label;;
const #427 = NameAndType	#425:#426;//  a:()Lscala/util/regexp/WordExp$Label;
const #428 = Method	#424.#427;	//  scala/util/regexp/WordExp$Letter.a:()Lscala/util/regexp/WordExp$Label;
const #429 = Asciz	seenLabel;
const #430 = Asciz	(Lscala/util/regexp/Base$RegExp;Lscala/util/regexp/WordExp$Label;)I;
const #431 = NameAndType	#429:#430;//  seenLabel:(Lscala/util/regexp/Base$RegExp;Lscala/util/regexp/WordExp$Label;)I
const #432 = Method	#30.#431;	//  scala/util/automata/WordBerrySethi.seenLabel:(Lscala/util/regexp/Base$RegExp;Lscala/util/regexp/WordExp$Label;)I
const #433 = Method	#424.#50;	//  scala/util/regexp/WordExp$Letter.pos_$eq:(I)V
const #434 = Asciz	Eps;
const #435 = Asciz	()Lscala/util/regexp/Base$Eps$;;
const #436 = NameAndType	#434:#435;//  Eps:()Lscala/util/regexp/Base$Eps$;
const #437 = Method	#294.#436;	//  scala/util/regexp/WordExp.Eps:()Lscala/util/regexp/Base$Eps$;
const #438 = Asciz	java/lang/Object;
const #439 = class	#438;	//  java/lang/Object
const #440 = Asciz	equals;
const #441 = Asciz	(Ljava/lang/Object;)Z;
const #442 = NameAndType	#440:#441;//  equals:(Ljava/lang/Object;)Z
const #443 = Method	#439.#442;	//  java/lang/Object.equals:(Ljava/lang/Object;)Z
const #444 = NameAndType	#421:#422;//  traverse:(Lscala/util/regexp/Base$RegExp;)V
const #445 = Method	#24.#444;	//  scala/util/automata/BaseBerrySethi.traverse:(Lscala/util/regexp/Base$RegExp;)V
const #446 = Asciz	r;
const #447 = Asciz	temp11;
const #448 = Asciz	Lscala/util/regexp/WordExp$Letter;;
const #449 = Asciz	temp12;
const #450 = Asciz	(Lscala/util/regexp/Base$RegExp;ILscala/util/regexp/WordExp$Label;)V;
const #451 = NameAndType	#429:#450;//  seenLabel:(Lscala/util/regexp/Base$RegExp;ILscala/util/regexp/WordExp$Label;)V
const #452 = Method	#30.#451;	//  scala/util/automata/WordBerrySethi.seenLabel:(Lscala/util/regexp/Base$RegExp;ILscala/util/regexp/WordExp$Label;)V
const #453 = NameAndType	#13:#67;//  labelAt:()Lscala/collection/immutable/Map;
const #454 = Method	#30.#453;	//  scala/util/automata/WordBerrySethi.labelAt:()Lscala/collection/immutable/Map;
const #455 = Asciz	()Lscala/collection/mutable/HashSet;;
const #456 = NameAndType	#16:#455;//  labels:()Lscala/collection/mutable/HashSet;
const #457 = Method	#30.#456;	//  scala/util/automata/WordBerrySethi.labels:()Lscala/collection/mutable/HashSet;
const #458 = Asciz	$plus$eq;
const #459 = Asciz	(Ljava/lang/Object;)Lscala/collection/mutable/HashSet;;
const #460 = NameAndType	#458:#459;//  $plus$eq:(Ljava/lang/Object;)Lscala/collection/mutable/HashSet;
const #461 = Method	#370.#460;	//  scala/collection/mutable/HashSet.$plus$eq:(Ljava/lang/Object;)Lscala/collection/mutable/HashSet;
const #462 = Asciz	i;
const #463 = Asciz	compFollow1;
const #464 = Asciz	(Lscala/collection/immutable/Set;Lscala/util/regexp/Base$RegExp;)Lscala/collection/immutable/Set;;
const #465 = Asciz	follow;
const #466 = Asciz	()Lscala/collection/mutable/HashMap;;
const #467 = NameAndType	#465:#466;//  follow:()Lscala/collection/mutable/HashMap;
const #468 = Method	#30.#467;	//  scala/util/automata/WordBerrySethi.follow:()Lscala/collection/mutable/HashMap;
const #469 = Method	#424.#47;	//  scala/util/regexp/WordExp$Letter.pos:()I
const #470 = Asciz	emptySet;
const #471 = NameAndType	#470:#252;//  emptySet:()Lscala/collection/immutable/Set;
const #472 = Method	#30.#471;	//  scala/util/automata/WordBerrySethi.emptySet:()Lscala/collection/immutable/Set;
const #473 = NameAndType	#463:#464;//  compFollow1:(Lscala/collection/immutable/Set;Lscala/util/regexp/Base$RegExp;)Lscala/collection/immutable/Set;
const #474 = Method	#24.#473;	//  scala/util/automata/BaseBerrySethi.compFollow1:(Lscala/collection/immutable/Set;Lscala/util/regexp/Base$RegExp;)Lscala/collection/immutable/Set;
const #475 = Asciz	fol1;
const #476 = Asciz	temp8;
const #477 = Asciz	(Lscala/collection/immutable/Set<Ljava/lang/Integer;>;Lscala/util/regexp/Base$RegExp;)Lscala/collection/immutable/Set<Ljava/lang/Integer;>;;
const #478 = Asciz	compLast;
const #479 = Asciz	(Lscala/util/regexp/Base$RegExp;)Lscala/collection/immutable/Set;;
const #480 = NameAndType	#478:#479;//  compLast:(Lscala/util/regexp/Base$RegExp;)Lscala/collection/immutable/Set;
const #481 = Method	#24.#480;	//  scala/util/automata/BaseBerrySethi.compLast:(Lscala/util/regexp/Base$RegExp;)Lscala/collection/immutable/Set;
const #482 = Asciz	temp5;
const #483 = Asciz	(Lscala/util/regexp/Base$RegExp;)Lscala/collection/immutable/Set<Ljava/lang/Integer;>;;
const #484 = Asciz	compFirst;
const #485 = NameAndType	#484:#479;//  compFirst:(Lscala/util/regexp/Base$RegExp;)Lscala/collection/immutable/Set;
const #486 = Method	#24.#485;	//  scala/util/automata/BaseBerrySethi.compFirst:(Lscala/util/regexp/Base$RegExp;)Lscala/collection/immutable/Set;
const #487 = Asciz	temp2;
const #488 = NameAndType	#3:#4;//  initials:Lscala/collection/immutable/Set;
const #489 = Field	#30.#488;	//  scala/util/automata/WordBerrySethi.initials:Lscala/collection/immutable/Set;
const #490 = Asciz	(Lscala/collection/immutable/Set<Ljava/lang/Integer;>;)V;
const #491 = Asciz	()Lscala/collection/immutable/Set<Ljava/lang/Integer;>;;
const #492 = NameAndType	#7:#8;//  defaultq:[Lscala/collection/immutable/List;
const #493 = Field	#30.#492;	//  scala/util/automata/WordBerrySethi.defaultq:[Lscala/collection/immutable/List;
const #494 = Asciz	([Lscala/collection/immutable/List<Ljava/lang/Integer;>;)V;
const #495 = Asciz	()[Lscala/collection/immutable/List;;
const #496 = Asciz	()[Lscala/collection/immutable/List<Ljava/lang/Integer;>;;
const #497 = NameAndType	#10:#11;//  deltaq:[Lscala/collection/mutable/HashMap;
const #498 = Field	#30.#497;	//  scala/util/automata/WordBerrySethi.deltaq:[Lscala/collection/mutable/HashMap;
const #499 = Asciz	([Lscala/collection/mutable/HashMap<Lscala/util/regexp/WordExp$Label;Lscala/collection/immutable/List<Ljava/lang/Integer;>;>;)V;
const #500 = Asciz	()[Lscala/collection/mutable/HashMap<Lscala/util/regexp/WordExp$Label;Lscala/collection/immutable/List<Ljava/lang/Integer;>;>;;
const #501 = NameAndType	#13:#14;//  labelAt:Lscala/collection/immutable/Map;
const #502 = Field	#30.#501;	//  scala/util/automata/WordBerrySethi.labelAt:Lscala/collection/immutable/Map;
const #503 = Asciz	(Lscala/collection/immutable/Map<Ljava/lang/Integer;Lscala/util/regexp/WordExp$Label;>;)V;
const #504 = Asciz	()Lscala/collection/immutable/Map<Ljava/lang/Integer;Lscala/util/regexp/WordExp$Label;>;;
const #505 = NameAndType	#16:#17;//  labels:Lscala/collection/mutable/HashSet;
const #506 = Field	#30.#505;	//  scala/util/automata/WordBerrySethi.labels:Lscala/collection/mutable/HashSet;
const #507 = Asciz	(Lscala/collection/mutable/HashSet<Lscala/util/regexp/WordExp$Label;>;)V;
const #508 = Asciz	()Lscala/collection/mutable/HashSet<Lscala/util/regexp/WordExp$Label;>;;
const #509 = Asciz	ScalaSig;
const #510 = Asciz	InnerClasses;
const #511 = Asciz	scala/util/regexp/Base;
const #512 = class	#511;	//  scala/util/regexp/Base
const #513 = Asciz	scala/collection/immutable/Range;
const #514 = class	#513;	//  scala/collection/immutable/Range
const #515 = Asciz	ByOne;
const #516 = Asciz	RegExp;
const #517 = Asciz	scala/Array;
const #518 = class	#517;	//  scala/Array
const #519 = Asciz	$anon$2;
const #520 = Asciz	Label;
const #521 = Asciz	Letter;
const #522 = Asciz	scala/collection/mutable/ArrayOps;
const #523 = class	#522;	//  scala/collection/mutable/ArrayOps
const #524 = Asciz	ofRef;
const #525 = Asciz	scala/reflect/Manifest;
const #526 = class	#525;	//  scala/reflect/Manifest
const #527 = Asciz	$anon$15;
const #528 = Asciz	$anon$1;
const #529 = Asciz	$anonfun$4;
const #530 = Asciz	$anonfun$3;
const #531 = Asciz	$anonfun$2;
const #532 = Asciz	$anonfun$1;
const #533 = Asciz	ClassTypeManifest;
const #534 = Asciz	$anonfun$initialize$1;
const #535 = Asciz	$anonfun$makeTransition$1;
const #536 = Asciz	$anonfun$initializeAutom$1;
const #537 = Asciz	$anonfun$collectTransitions$2;
const #538 = Asciz	$anonfun$collectTransitions$1;
const #539 = Asciz	scala/ScalaObject;
const #540 = class	#539;	//  scala/ScalaObject

{
public scala.util.automata.WordBerrySethi();
  Code:
   Stack=1, Locals=1, Args_size=1
   0:	aload_0
   1:	invokespecial	#26; //Method scala/util/automata/BaseBerrySethi."<init>":()V
   4:	return
  LineNumberTable: 
   line 26: 0


public scala.util.automata.NondetWordAutom automatonFrom(scala.util.regexp.Base$RegExp, int);
  Code:
   Stack=24, Locals=35, Args_size=3
   0:	aload_0
   1:	iload_2
   2:	invokevirtual	#34; //Method finalTag_$eq:(I)V
   5:	aload_1
   6:	instanceof	#36; //class scala/util/regexp/Base$Sequ
   9:	ifeq	938
   12:	aload_1
   13:	checkcast	#36; //class scala/util/regexp/Base$Sequ
   16:	astore_3
   17:	iconst_1
   18:	ifeq	926
   21:	aload_0
   22:	aload_3
   23:	invokevirtual	#40; //Method scala/util/regexp/Base$Sequ.rs:()Lscala/collection/Seq;
   26:	invokevirtual	#44; //Method initialize:(Lscala/collection/Seq;)V
   29:	aload_0
   30:	aload_0
   31:	invokevirtual	#48; //Method pos:()I
   34:	iconst_1
   35:	iadd
   36:	invokevirtual	#51; //Method pos_$eq:(I)V
   39:	aload_0
   40:	aload_3
   41:	invokevirtual	#40; //Method scala/util/regexp/Base$Sequ.rs:()Lscala/collection/Seq;
   44:	invokevirtual	#55; //Method compFollow:(Lscala/collection/Seq;)Lscala/collection/immutable/Set;
   47:	pop
   48:	aload_0
   49:	invokevirtual	#58; //Method initializeAutom:()V
   52:	aload_0
   53:	invokevirtual	#61; //Method collectTransitions:()V
   56:	aload_3
   57:	invokevirtual	#65; //Method scala/util/regexp/Base$Sequ.isNullable:()Z
   60:	ifeq	88
   63:	aload_0
   64:	aload_0
   65:	invokevirtual	#69; //Method finals:()Lscala/collection/immutable/Map;
   68:	iconst_0
   69:	istore	4
   71:	iload	4
   73:	invokestatic	#75; //Method scala/runtime/BoxesRunTime.boxToInteger:(I)Ljava/lang/Integer;
   76:	iload_2
   77:	invokestatic	#75; //Method scala/runtime/BoxesRunTime.boxToInteger:(I)Ljava/lang/Integer;
   80:	invokeinterface	#81,  3; //InterfaceMethod scala/collection/immutable/MapLike.updated:(Ljava/lang/Object;Ljava/lang/Object;)Lscala/collection/immutable/Map;
   85:	invokevirtual	#85; //Method finals_$eq:(Lscala/collection/immutable/Map;)V
   88:	getstatic	#91; //Field scala/collection/immutable/Map$.MODULE$:Lscala/collection/immutable/Map$;
   91:	getstatic	#96; //Field scala/Predef$.MODULE$:Lscala/Predef$;
   94:	aload_0
   95:	invokevirtual	#99; //Method deltaq:()[Lscala/collection/mutable/HashMap;
   98:	checkcast	#101; //class "[Ljava/lang/Object;"
   101:	astore	5
   103:	new	#103; //class scala/collection/mutable/ArrayOps$ofRef
   106:	dup
   107:	aload	5
   109:	invokespecial	#106; //Method scala/collection/mutable/ArrayOps$ofRef."<init>":([Ljava/lang/Object;)V
   112:	ldc	#108; //class scala/Tuple2
   114:	ldc	#110; //class scala/collection/mutable/HashMap
   116:	aload_0
   117:	invokevirtual	#114; //Method lang:()Lscala/util/regexp/WordExp;
   120:	astore	6
   122:	new	#116; //class scala/reflect/Manifest$$anon$15
   125:	dup
   126:	aload	6
   128:	invokespecial	#119; //Method scala/reflect/Manifest$$anon$15."<init>":(Ljava/lang/Object;)V
   131:	ldc	#121; //String _labelT
   133:	aload_0
   134:	invokevirtual	#114; //Method lang:()Lscala/util/regexp/WordExp;
   137:	astore	7
   139:	new	#116; //class scala/reflect/Manifest$$anon$15
   142:	dup
   143:	aload	7
   145:	invokespecial	#119; //Method scala/reflect/Manifest$$anon$15."<init>":(Ljava/lang/Object;)V
   148:	ldc	#123; //class scala/util/regexp/WordExp$Label
   150:	getstatic	#96; //Field scala/Predef$.MODULE$:Lscala/Predef$;
   153:	iconst_0
   154:	anewarray	#125; //class scala/reflect/OptManifest
   157:	checkcast	#101; //class "[Ljava/lang/Object;"
   160:	invokevirtual	#129; //Method scala/Predef$.wrapRefArray:([Ljava/lang/Object;)Lscala/collection/mutable/WrappedArray;
   163:	astore	10
   165:	astore	9
   167:	astore	8
   169:	new	#131; //class scala/reflect/ClassManifest$ClassTypeManifest
   172:	dup
   173:	new	#133; //class scala/Some
   176:	dup
   177:	aload	8
   179:	invokespecial	#134; //Method scala/Some."<init>":(Ljava/lang/Object;)V
   182:	aload	9
   184:	aload	10
   186:	invokeinterface	#140,  1; //InterfaceMethod scala/collection/TraversableLike.toList:()Lscala/collection/immutable/List;
   191:	invokespecial	#143; //Method scala/reflect/ClassManifest$ClassTypeManifest."<init>":(Lscala/Option;Ljava/lang/Class;Lscala/collection/immutable/List;)V
   194:	getstatic	#96; //Field scala/Predef$.MODULE$:Lscala/Predef$;
   197:	iconst_0
   198:	anewarray	#125; //class scala/reflect/OptManifest
   201:	checkcast	#101; //class "[Ljava/lang/Object;"
   204:	invokevirtual	#129; //Method scala/Predef$.wrapRefArray:([Ljava/lang/Object;)Lscala/collection/mutable/WrappedArray;
   207:	astore	14
   209:	astore	13
   211:	astore	12
   213:	astore	11
   215:	new	#145; //class scala/reflect/ClassManifest$$anon$1
   218:	dup
   219:	aload	11
   221:	aload	12
   223:	aload	13
   225:	aload	14
   227:	invokespecial	#148; //Method scala/reflect/ClassManifest$$anon$1."<init>":(Lscala/reflect/OptManifest;Ljava/lang/String;Lscala/reflect/ClassManifest;Lscala/collection/Seq;)V
   230:	getstatic	#96; //Field scala/Predef$.MODULE$:Lscala/Predef$;
   233:	iconst_1
   234:	anewarray	#125; //class scala/reflect/OptManifest
   237:	dup
   238:	iconst_0
   239:	ldc	#150; //class scala/collection/immutable/List
   241:	getstatic	#155; //Field scala/reflect/Manifest$.MODULE$:Lscala/reflect/Manifest$;
   244:	invokevirtual	#159; //Method scala/reflect/Manifest$.Int:()Ljava/lang/Object;
   247:	checkcast	#125; //class scala/reflect/OptManifest
   250:	getstatic	#96; //Field scala/Predef$.MODULE$:Lscala/Predef$;
   253:	iconst_0
   254:	anewarray	#125; //class scala/reflect/OptManifest
   257:	checkcast	#101; //class "[Ljava/lang/Object;"
   260:	invokevirtual	#129; //Method scala/Predef$.wrapRefArray:([Ljava/lang/Object;)Lscala/collection/mutable/WrappedArray;
   263:	astore	16
   265:	astore	17
   267:	astore	15
   269:	new	#131; //class scala/reflect/ClassManifest$ClassTypeManifest
   272:	dup
   273:	getstatic	#164; //Field scala/None$.MODULE$:Lscala/None$;
   276:	aload	15
   278:	aload	16
   280:	invokeinterface	#140,  1; //InterfaceMethod scala/collection/TraversableLike.toList:()Lscala/collection/immutable/List;
   285:	aload	17
   287:	invokevirtual	#168; //Method scala/collection/immutable/List.$colon$colon:(Ljava/lang/Object;)Lscala/collection/immutable/List;
   290:	invokespecial	#143; //Method scala/reflect/ClassManifest$ClassTypeManifest."<init>":(Lscala/Option;Ljava/lang/Class;Lscala/collection/immutable/List;)V
   293:	aastore
   294:	checkcast	#101; //class "[Ljava/lang/Object;"
   297:	invokevirtual	#129; //Method scala/Predef$.wrapRefArray:([Ljava/lang/Object;)Lscala/collection/mutable/WrappedArray;
   300:	astore	19
   302:	astore	20
   304:	astore	18
   306:	new	#131; //class scala/reflect/ClassManifest$ClassTypeManifest
   309:	dup
   310:	getstatic	#164; //Field scala/None$.MODULE$:Lscala/None$;
   313:	aload	18
   315:	aload	19
   317:	invokeinterface	#140,  1; //InterfaceMethod scala/collection/TraversableLike.toList:()Lscala/collection/immutable/List;
   322:	aload	20
   324:	invokevirtual	#168; //Method scala/collection/immutable/List.$colon$colon:(Ljava/lang/Object;)Lscala/collection/immutable/List;
   327:	invokespecial	#143; //Method scala/reflect/ClassManifest$ClassTypeManifest."<init>":(Lscala/Option;Ljava/lang/Class;Lscala/collection/immutable/List;)V
   330:	getstatic	#96; //Field scala/Predef$.MODULE$:Lscala/Predef$;
   333:	iconst_1
   334:	anewarray	#125; //class scala/reflect/OptManifest
   337:	dup
   338:	iconst_0
   339:	getstatic	#155; //Field scala/reflect/Manifest$.MODULE$:Lscala/reflect/Manifest$;
   342:	invokevirtual	#159; //Method scala/reflect/Manifest$.Int:()Ljava/lang/Object;
   345:	checkcast	#125; //class scala/reflect/OptManifest
   348:	aastore
   349:	checkcast	#101; //class "[Ljava/lang/Object;"
   352:	invokevirtual	#129; //Method scala/Predef$.wrapRefArray:([Ljava/lang/Object;)Lscala/collection/mutable/WrappedArray;
   355:	astore	22
   357:	astore	23
   359:	astore	21
   361:	new	#131; //class scala/reflect/ClassManifest$ClassTypeManifest
   364:	dup
   365:	getstatic	#164; //Field scala/None$.MODULE$:Lscala/None$;
   368:	aload	21
   370:	aload	22
   372:	invokeinterface	#140,  1; //InterfaceMethod scala/collection/TraversableLike.toList:()Lscala/collection/immutable/List;
   377:	aload	23
   379:	invokevirtual	#168; //Method scala/collection/immutable/List.$colon$colon:(Ljava/lang/Object;)Lscala/collection/immutable/List;
   382:	invokespecial	#143; //Method scala/reflect/ClassManifest$ClassTypeManifest."<init>":(Lscala/Option;Ljava/lang/Class;Lscala/collection/immutable/List;)V
   385:	astore	24
   387:	new	#170; //class scala/Array$$anon$2
   390:	dup
   391:	aload	24
   393:	invokespecial	#173; //Method scala/Array$$anon$2."<init>":(Lscala/reflect/ClassManifest;)V
   396:	invokeinterface	#179,  2; //InterfaceMethod scala/collection/IndexedSeqLike.zipWithIndex:(Lscala/collection/generic/CanBuildFrom;)Ljava/lang/Object;
   401:	checkcast	#101; //class "[Ljava/lang/Object;"
   404:	astore	25
   406:	new	#103; //class scala/collection/mutable/ArrayOps$ofRef
   409:	dup
   410:	aload	25
   412:	invokespecial	#106; //Method scala/collection/mutable/ArrayOps$ofRef."<init>":([Ljava/lang/Object;)V
   415:	new	#181; //class scala/util/automata/WordBerrySethi$$anonfun$1
   418:	dup
   419:	aload_0
   420:	invokespecial	#184; //Method scala/util/automata/WordBerrySethi$$anonfun$1."<init>":(Lscala/util/automata/WordBerrySethi;)V
   423:	getstatic	#189; //Field scala/Array$.MODULE$:Lscala/Array$;
   426:	getstatic	#194; //Field scala/reflect/ClassManifest$.MODULE$:Lscala/reflect/ClassManifest$;
   429:	ldc	#108; //class scala/Tuple2
   431:	getstatic	#155; //Field scala/reflect/Manifest$.MODULE$:Lscala/reflect/Manifest$;
   434:	invokevirtual	#159; //Method scala/reflect/Manifest$.Int:()Ljava/lang/Object;
   437:	checkcast	#125; //class scala/reflect/OptManifest
   440:	getstatic	#96; //Field scala/Predef$.MODULE$:Lscala/Predef$;
   443:	iconst_1
   444:	anewarray	#125; //class scala/reflect/OptManifest
   447:	dup
   448:	iconst_0
   449:	getstatic	#194; //Field scala/reflect/ClassManifest$.MODULE$:Lscala/reflect/ClassManifest$;
   452:	ldc	#110; //class scala/collection/mutable/HashMap
   454:	getstatic	#194; //Field scala/reflect/ClassManifest$.MODULE$:Lscala/reflect/ClassManifest$;
   457:	aload_0
   458:	invokevirtual	#114; //Method lang:()Lscala/util/regexp/WordExp;
   461:	astore	26
   463:	new	#116; //class scala/reflect/Manifest$$anon$15
   466:	dup
   467:	aload	26
   469:	invokespecial	#119; //Method scala/reflect/Manifest$$anon$15."<init>":(Ljava/lang/Object;)V
   472:	ldc	#121; //String _labelT
   474:	getstatic	#194; //Field scala/reflect/ClassManifest$.MODULE$:Lscala/reflect/ClassManifest$;
   477:	aload_0
   478:	invokevirtual	#114; //Method lang:()Lscala/util/regexp/WordExp;
   481:	invokevirtual	#198; //Method scala/reflect/ClassManifest$.singleType:(Ljava/lang/Object;)Lscala/reflect/Manifest;
   484:	ldc	#123; //class scala/util/regexp/WordExp$Label
   486:	getstatic	#96; //Field scala/Predef$.MODULE$:Lscala/Predef$;
   489:	iconst_0
   490:	anewarray	#125; //class scala/reflect/OptManifest
   493:	checkcast	#101; //class "[Ljava/lang/Object;"
   496:	invokevirtual	#129; //Method scala/Predef$.wrapRefArray:([Ljava/lang/Object;)Lscala/collection/mutable/WrappedArray;
   499:	astore	29
   501:	astore	28
   503:	astore	27
   505:	new	#131; //class scala/reflect/ClassManifest$ClassTypeManifest
   508:	dup
   509:	new	#133; //class scala/Some
   512:	dup
   513:	aload	27
   515:	invokespecial	#134; //Method scala/Some."<init>":(Ljava/lang/Object;)V
   518:	aload	28
   520:	aload	29
   522:	invokeinterface	#140,  1; //InterfaceMethod scala/collection/TraversableLike.toList:()Lscala/collection/immutable/List;
   527:	invokespecial	#143; //Method scala/reflect/ClassManifest$ClassTypeManifest."<init>":(Lscala/Option;Ljava/lang/Class;Lscala/collection/immutable/List;)V
   530:	getstatic	#96; //Field scala/Predef$.MODULE$:Lscala/Predef$;
   533:	iconst_0
   534:	anewarray	#125; //class scala/reflect/OptManifest
   537:	checkcast	#101; //class "[Ljava/lang/Object;"
   540:	invokevirtual	#129; //Method scala/Predef$.wrapRefArray:([Ljava/lang/Object;)Lscala/collection/mutable/WrappedArray;
   543:	invokevirtual	#202; //Method scala/reflect/ClassManifest$.abstractType:(Lscala/reflect/OptManifest;Ljava/lang/String;Lscala/reflect/ClassManifest;Lscala/collection/Seq;)Lscala/reflect/ClassManifest;
   546:	getstatic	#96; //Field scala/Predef$.MODULE$:Lscala/Predef$;
   549:	iconst_1
   550:	anewarray	#125; //class scala/reflect/OptManifest
   553:	dup
   554:	iconst_0
   555:	getstatic	#194; //Field scala/reflect/ClassManifest$.MODULE$:Lscala/reflect/ClassManifest$;
   558:	ldc	#150; //class scala/collection/immutable/List
   560:	getstatic	#155; //Field scala/reflect/Manifest$.MODULE$:Lscala/reflect/Manifest$;
   563:	invokevirtual	#159; //Method scala/reflect/Manifest$.Int:()Ljava/lang/Object;
   566:	checkcast	#125; //class scala/reflect/OptManifest
   569:	getstatic	#96; //Field scala/Predef$.MODULE$:Lscala/Predef$;
   572:	iconst_0
   573:	anewarray	#125; //class scala/reflect/OptManifest
   576:	checkcast	#101; //class "[Ljava/lang/Object;"
   579:	invokevirtual	#129; //Method scala/Predef$.wrapRefArray:([Ljava/lang/Object;)Lscala/collection/mutable/WrappedArray;
   582:	invokevirtual	#206; //Method scala/reflect/ClassManifest$.classType:(Ljava/lang/Class;Lscala/reflect/OptManifest;Lscala/collection/Seq;)Lscala/reflect/ClassManifest;
   585:	aastore
   586:	checkcast	#101; //class "[Ljava/lang/Object;"
   589:	invokevirtual	#129; //Method scala/Predef$.wrapRefArray:([Ljava/lang/Object;)Lscala/collection/mutable/WrappedArray;
   592:	invokevirtual	#206; //Method scala/reflect/ClassManifest$.classType:(Ljava/lang/Class;Lscala/reflect/OptManifest;Lscala/collection/Seq;)Lscala/reflect/ClassManifest;
   595:	aastore
   596:	checkcast	#101; //class "[Ljava/lang/Object;"
   599:	invokevirtual	#129; //Method scala/Predef$.wrapRefArray:([Ljava/lang/Object;)Lscala/collection/mutable/WrappedArray;
   602:	invokevirtual	#206; //Method scala/reflect/ClassManifest$.classType:(Ljava/lang/Class;Lscala/reflect/OptManifest;Lscala/collection/Seq;)Lscala/reflect/ClassManifest;
   605:	invokevirtual	#210; //Method scala/Array$.canBuildFrom:(Lscala/reflect/ClassManifest;)Lscala/collection/generic/CanBuildFrom;
   608:	invokeinterface	#214,  3; //InterfaceMethod scala/collection/TraversableLike.map:(Lscala/Function1;Lscala/collection/generic/CanBuildFrom;)Ljava/lang/Object;
   613:	checkcast	#216; //class "[Lscala/Tuple2;"
   616:	checkcast	#101; //class "[Ljava/lang/Object;"
   619:	invokevirtual	#129; //Method scala/Predef$.wrapRefArray:([Ljava/lang/Object;)Lscala/collection/mutable/WrappedArray;
   622:	invokevirtual	#220; //Method scala/collection/immutable/Map$.apply:(Lscala/collection/Seq;)Lscala/collection/Map;
   625:	checkcast	#222; //class scala/collection/immutable/Map
   628:	astore	30
   630:	getstatic	#96; //Field scala/Predef$.MODULE$:Lscala/Predef$;
   633:	iconst_0
   634:	invokevirtual	#226; //Method scala/Predef$.intWrapper:(I)Lscala/runtime/RichInt;
   637:	aload_0
   638:	invokevirtual	#48; //Method pos:()I
   641:	invokevirtual	#232; //Method scala/runtime/RichInt.until:(I)Lscala/collection/immutable/Range;
   644:	new	#234; //class scala/util/automata/WordBerrySethi$$anonfun$2
   647:	dup
   648:	aload_0
   649:	invokespecial	#235; //Method scala/util/automata/WordBerrySethi$$anonfun$2."<init>":(Lscala/util/automata/WordBerrySethi;)V
   652:	getstatic	#240; //Field scala/collection/immutable/IndexedSeq$.MODULE$:Lscala/collection/immutable/IndexedSeq$;
   655:	invokevirtual	#243; //Method scala/collection/immutable/IndexedSeq$.canBuildFrom:()Lscala/collection/generic/CanBuildFrom;
   658:	invokeinterface	#214,  3; //InterfaceMethod scala/collection/TraversableLike.map:(Lscala/Function1;Lscala/collection/generic/CanBuildFrom;)Ljava/lang/Object;
   663:	checkcast	#136; //class scala/collection/TraversableLike
   666:	getstatic	#155; //Field scala/reflect/Manifest$.MODULE$:Lscala/reflect/Manifest$;
   669:	invokevirtual	#159; //Method scala/reflect/Manifest$.Int:()Ljava/lang/Object;
   672:	checkcast	#245; //class scala/reflect/ClassManifest
   675:	invokeinterface	#249,  2; //InterfaceMethod scala/collection/TraversableLike.toArray:(Lscala/reflect/ClassManifest;)Ljava/lang/Object;
   680:	checkcast	#251; //class "[I"
   683:	astore	31
   685:	aload_0
   686:	invokevirtual	#254; //Method initials:()Lscala/collection/immutable/Set;
   689:	getstatic	#155; //Field scala/reflect/Manifest$.MODULE$:Lscala/reflect/Manifest$;
   692:	invokevirtual	#159; //Method scala/reflect/Manifest$.Int:()Ljava/lang/Object;
   695:	checkcast	#245; //class scala/reflect/ClassManifest
   698:	invokeinterface	#249,  2; //InterfaceMethod scala/collection/TraversableLike.toArray:(Lscala/reflect/ClassManifest;)Ljava/lang/Object;
   703:	checkcast	#251; //class "[I"
   706:	astore	32
   708:	getstatic	#96; //Field scala/Predef$.MODULE$:Lscala/Predef$;
   711:	iconst_0
   712:	invokevirtual	#226; //Method scala/Predef$.intWrapper:(I)Lscala/runtime/RichInt;
   715:	aload_0
   716:	invokevirtual	#48; //Method pos:()I
   719:	invokevirtual	#232; //Method scala/runtime/RichInt.until:(I)Lscala/collection/immutable/Range;
   722:	new	#256; //class scala/util/automata/WordBerrySethi$$anonfun$3
   725:	dup
   726:	aload_0
   727:	aload	30
   729:	invokespecial	#259; //Method scala/util/automata/WordBerrySethi$$anonfun$3."<init>":(Lscala/util/automata/WordBerrySethi;Lscala/collection/immutable/Map;)V
   732:	getstatic	#240; //Field scala/collection/immutable/IndexedSeq$.MODULE$:Lscala/collection/immutable/IndexedSeq$;
   735:	invokevirtual	#243; //Method scala/collection/immutable/IndexedSeq$.canBuildFrom:()Lscala/collection/generic/CanBuildFrom;
   738:	invokeinterface	#214,  3; //InterfaceMethod scala/collection/TraversableLike.map:(Lscala/Function1;Lscala/collection/generic/CanBuildFrom;)Ljava/lang/Object;
   743:	checkcast	#136; //class scala/collection/TraversableLike
   746:	getstatic	#194; //Field scala/reflect/ClassManifest$.MODULE$:Lscala/reflect/ClassManifest$;
   749:	ldc_w	#261; //class scala/collection/Map
   752:	getstatic	#194; //Field scala/reflect/ClassManifest$.MODULE$:Lscala/reflect/ClassManifest$;
   755:	getstatic	#194; //Field scala/reflect/ClassManifest$.MODULE$:Lscala/reflect/ClassManifest$;
   758:	aload_0
   759:	invokevirtual	#114; //Method lang:()Lscala/util/regexp/WordExp;
   762:	invokevirtual	#198; //Method scala/reflect/ClassManifest$.singleType:(Ljava/lang/Object;)Lscala/reflect/Manifest;
   765:	ldc	#121; //String _labelT
   767:	getstatic	#194; //Field scala/reflect/ClassManifest$.MODULE$:Lscala/reflect/ClassManifest$;
   770:	getstatic	#194; //Field scala/reflect/ClassManifest$.MODULE$:Lscala/reflect/ClassManifest$;
   773:	aload_0
   774:	invokevirtual	#114; //Method lang:()Lscala/util/regexp/WordExp;
   777:	invokevirtual	#198; //Method scala/reflect/ClassManifest$.singleType:(Ljava/lang/Object;)Lscala/reflect/Manifest;
   780:	ldc	#123; //class scala/util/regexp/WordExp$Label
   782:	getstatic	#96; //Field scala/Predef$.MODULE$:Lscala/Predef$;
   785:	iconst_0
   786:	anewarray	#125; //class scala/reflect/OptManifest
   789:	checkcast	#101; //class "[Ljava/lang/Object;"
   792:	invokevirtual	#129; //Method scala/Predef$.wrapRefArray:([Ljava/lang/Object;)Lscala/collection/mutable/WrappedArray;
   795:	invokevirtual	#264; //Method scala/reflect/ClassManifest$.classType:(Lscala/reflect/OptManifest;Ljava/lang/Class;Lscala/collection/Seq;)Lscala/reflect/ClassManifest;
   798:	getstatic	#96; //Field scala/Predef$.MODULE$:Lscala/Predef$;
   801:	iconst_0
   802:	anewarray	#125; //class scala/reflect/OptManifest
   805:	checkcast	#101; //class "[Ljava/lang/Object;"
   808:	invokevirtual	#129; //Method scala/Predef$.wrapRefArray:([Ljava/lang/Object;)Lscala/collection/mutable/WrappedArray;
   811:	invokevirtual	#202; //Method scala/reflect/ClassManifest$.abstractType:(Lscala/reflect/OptManifest;Ljava/lang/String;Lscala/reflect/ClassManifest;Lscala/collection/Seq;)Lscala/reflect/ClassManifest;
   814:	getstatic	#96; //Field scala/Predef$.MODULE$:Lscala/Predef$;
   817:	iconst_1
   818:	anewarray	#125; //class scala/reflect/OptManifest
   821:	dup
   822:	iconst_0
   823:	getstatic	#194; //Field scala/reflect/ClassManifest$.MODULE$:Lscala/reflect/ClassManifest$;
   826:	ldc_w	#266; //class scala/collection/immutable/BitSet
   829:	invokevirtual	#269; //Method scala/reflect/ClassManifest$.classType:(Ljava/lang/Class;)Lscala/reflect/ClassManifest;
   832:	aastore
   833:	checkcast	#101; //class "[Ljava/lang/Object;"
   836:	invokevirtual	#129; //Method scala/Predef$.wrapRefArray:([Ljava/lang/Object;)Lscala/collection/mutable/WrappedArray;
   839:	invokevirtual	#206; //Method scala/reflect/ClassManifest$.classType:(Ljava/lang/Class;Lscala/reflect/OptManifest;Lscala/collection/Seq;)Lscala/reflect/ClassManifest;
   842:	invokeinterface	#249,  2; //InterfaceMethod scala/collection/TraversableLike.toArray:(Lscala/reflect/ClassManifest;)Ljava/lang/Object;
   847:	checkcast	#271; //class "[Lscala/collection/Map;"
   850:	astore	33
   852:	getstatic	#96; //Field scala/Predef$.MODULE$:Lscala/Predef$;
   855:	iconst_0
   856:	invokevirtual	#226; //Method scala/Predef$.intWrapper:(I)Lscala/runtime/RichInt;
   859:	aload_0
   860:	invokevirtual	#48; //Method pos:()I
   863:	invokevirtual	#232; //Method scala/runtime/RichInt.until:(I)Lscala/collection/immutable/Range;
   866:	new	#273; //class scala/util/automata/WordBerrySethi$$anonfun$4
   869:	dup
   870:	aload_0
   871:	invokespecial	#274; //Method scala/util/automata/WordBerrySethi$$anonfun$4."<init>":(Lscala/util/automata/WordBerrySethi;)V
   874:	getstatic	#240; //Field scala/collection/immutable/IndexedSeq$.MODULE$:Lscala/collection/immutable/IndexedSeq$;
   877:	invokevirtual	#243; //Method scala/collection/immutable/IndexedSeq$.canBuildFrom:()Lscala/collection/generic/CanBuildFrom;
   880:	invokeinterface	#214,  3; //InterfaceMethod scala/collection/TraversableLike.map:(Lscala/Function1;Lscala/collection/generic/CanBuildFrom;)Ljava/lang/Object;
   885:	checkcast	#136; //class scala/collection/TraversableLike
   888:	getstatic	#194; //Field scala/reflect/ClassManifest$.MODULE$:Lscala/reflect/ClassManifest$;
   891:	ldc_w	#266; //class scala/collection/immutable/BitSet
   894:	invokevirtual	#269; //Method scala/reflect/ClassManifest$.classType:(Ljava/lang/Class;)Lscala/reflect/ClassManifest;
   897:	invokeinterface	#249,  2; //InterfaceMethod scala/collection/TraversableLike.toArray:(Lscala/reflect/ClassManifest;)Ljava/lang/Object;
   902:	checkcast	#276; //class "[Lscala/collection/immutable/BitSet;"
   905:	astore	34
   907:	new	#278; //class scala/util/automata/WordBerrySethi$$anon$1
   910:	dup
   911:	aload_0
   912:	aload	31
   914:	aload	32
   916:	aload	33
   918:	aload	34
   920:	invokespecial	#281; //Method scala/util/automata/WordBerrySethi$$anon$1."<init>":(Lscala/util/automata/WordBerrySethi;[I[I[Lscala/collection/Map;[Lscala/collection/immutable/BitSet;)V
   923:	goto	974
   926:	new	#283; //class scala/MatchError
   929:	dup
   930:	aload_1
   931:	invokevirtual	#289; //Method scala/util/regexp/Base$RegExp.toString:()Ljava/lang/String;
   934:	invokespecial	#292; //Method scala/MatchError."<init>":(Ljava/lang/String;)V
   937:	athrow
   938:	iconst_1
   939:	ifeq	975
   942:	aload_0
   943:	aload_0
   944:	invokevirtual	#114; //Method lang:()Lscala/util/regexp/WordExp;
   947:	invokevirtual	#298; //Method scala/util/regexp/WordExp.Sequ:()Lscala/util/regexp/Base$Sequ$;
   950:	getstatic	#96; //Field scala/Predef$.MODULE$:Lscala/Predef$;
   953:	iconst_1
   954:	anewarray	#285; //class scala/util/regexp/Base$RegExp
   957:	dup
   958:	iconst_0
   959:	aload_1
   960:	aastore
   961:	checkcast	#101; //class "[Ljava/lang/Object;"
   964:	invokevirtual	#129; //Method scala/Predef$.wrapRefArray:([Ljava/lang/Object;)Lscala/collection/mutable/WrappedArray;
   967:	invokevirtual	#303; //Method scala/util/regexp/Base$Sequ$.apply:(Lscala/collection/Seq;)Lscala/util/regexp/Base$RegExp;
   970:	iload_2
   971:	invokevirtual	#305; //Method automatonFrom:(Lscala/util/regexp/Base$RegExp;I)Lscala/util/automata/NondetWordAutom;
   974:	areturn
   975:	new	#283; //class scala/MatchError
   978:	dup
   979:	aload_1
   980:	invokevirtual	#289; //Method scala/util/regexp/Base$RegExp.toString:()Ljava/lang/String;
   983:	invokespecial	#292; //Method scala/MatchError."<init>":(Ljava/lang/String;)V
   986:	athrow
  LineNumberTable: 
   line 134: 0
   line 136: 5
   line 133: 12
   line 21: 17
   line 139: 21
   line 140: 29
   line 141: 39
   line 144: 48
   line 145: 52
   line 147: 56
   line 148: 63
   line 150: 88
   line 151: 630
   line 152: 685
   line 155: 708
   line 157: 746
   line 154: 850
   line 159: 852
   line 161: 907
   line 136: 926
   line 21: 938
   line 170: 942
   line 133: 974
   line 136: 975

  LocalVariableTable: 
   Start  Length  Slot  Name   Signature
   0      987      0    this       Lscala/util/automata/WordBerrySethi;
   0      987      1    pat       Lscala/util/regexp/Base$RegExp;
   0      987      2    finalTag       I
   17      921      3    temp20       Lscala/util/regexp/Base$Sequ;
   630      293      30    delta1$1       Lscala/collection/immutable/Map;
   685      238      31    finalsArr$1       [I
   708      215      32    initialsArr$1       [I
   852      71      33    deltaArr$1       [Lscala/collection/Map;
   907      16      34    defaultArr$1       [Lscala/collection/immutable/BitSet;

  Signature: length = 0x2
   01 40 

public void collectTransitions();
  Code:
   Stack=4, Locals=1, Args_size=1
   0:	getstatic	#96; //Field scala/Predef$.MODULE$:Lscala/Predef$;
   3:	iconst_0
   4:	invokevirtual	#226; //Method scala/Predef$.intWrapper:(I)Lscala/runtime/RichInt;
   7:	aload_0
   8:	invokevirtual	#48; //Method pos:()I
   11:	invokevirtual	#232; //Method scala/runtime/RichInt.until:(I)Lscala/collection/immutable/Range;
   14:	new	#322; //class scala/util/automata/WordBerrySethi$$anonfun$collectTransitions$1
   17:	dup
   18:	aload_0
   19:	invokespecial	#323; //Method scala/util/automata/WordBerrySethi$$anonfun$collectTransitions$1."<init>":(Lscala/util/automata/WordBerrySethi;)V
   22:	getstatic	#240; //Field scala/collection/immutable/IndexedSeq$.MODULE$:Lscala/collection/immutable/IndexedSeq$;
   25:	invokevirtual	#243; //Method scala/collection/immutable/IndexedSeq$.canBuildFrom:()Lscala/collection/generic/CanBuildFrom;
   28:	invokeinterface	#214,  3; //InterfaceMethod scala/collection/TraversableLike.map:(Lscala/Function1;Lscala/collection/generic/CanBuildFrom;)Ljava/lang/Object;
   33:	checkcast	#175; //class scala/collection/IndexedSeqLike
   36:	new	#325; //class scala/util/automata/WordBerrySethi$$anonfun$collectTransitions$2
   39:	dup
   40:	aload_0
   41:	invokespecial	#326; //Method scala/util/automata/WordBerrySethi$$anonfun$collectTransitions$2."<init>":(Lscala/util/automata/WordBerrySethi;)V
   44:	invokeinterface	#330,  2; //InterfaceMethod scala/collection/IndexedSeqLike.foreach:(Lscala/Function1;)V
   49:	return
  LineNumberTable: 
   line 128: 0


public void initializeAutom();
  Code:
   Stack=4, Locals=1, Args_size=1
   0:	aload_0
   1:	getstatic	#91; //Field scala/collection/immutable/Map$.MODULE$:Lscala/collection/immutable/Map$;
   4:	invokevirtual	#333; //Method scala/collection/immutable/Map$.empty:()Lscala/collection/immutable/Map;
   7:	invokevirtual	#85; //Method finals_$eq:(Lscala/collection/immutable/Map;)V
   10:	aload_0
   11:	aload_0
   12:	invokevirtual	#48; //Method pos:()I
   15:	anewarray	#110; //class scala/collection/mutable/HashMap
   18:	invokevirtual	#337; //Method deltaq_$eq:([Lscala/collection/mutable/HashMap;)V
   21:	aload_0
   22:	aload_0
   23:	invokevirtual	#48; //Method pos:()I
   26:	anewarray	#150; //class scala/collection/immutable/List
   29:	invokevirtual	#341; //Method defaultq_$eq:([Lscala/collection/immutable/List;)V
   32:	getstatic	#96; //Field scala/Predef$.MODULE$:Lscala/Predef$;
   35:	iconst_0
   36:	invokevirtual	#226; //Method scala/Predef$.intWrapper:(I)Lscala/runtime/RichInt;
   39:	aload_0
   40:	invokevirtual	#48; //Method pos:()I
   43:	invokevirtual	#232; //Method scala/runtime/RichInt.until:(I)Lscala/collection/immutable/Range;
   46:	checkcast	#343; //class scala/collection/immutable/Range$ByOne
   49:	new	#345; //class scala/util/automata/WordBerrySethi$$anonfun$initializeAutom$1
   52:	dup
   53:	aload_0
   54:	invokespecial	#346; //Method scala/util/automata/WordBerrySethi$$anonfun$initializeAutom$1."<init>":(Lscala/util/automata/WordBerrySethi;)V
   57:	invokeinterface	#347,  2; //InterfaceMethod scala/collection/immutable/Range$ByOne.foreach:(Lscala/Function1;)V
   62:	return
  LineNumberTable: 
   line 117: 0
   line 118: 10
   line 119: 21
   line 121: 32


public void initialize(scala.collection.Seq);
  Code:
   Stack=7, Locals=2, Args_size=2
   0:	aload_0
   1:	getstatic	#91; //Field scala/collection/immutable/Map$.MODULE$:Lscala/collection/immutable/Map$;
   4:	getstatic	#96; //Field scala/Predef$.MODULE$:Lscala/Predef$;
   7:	iconst_0
   8:	anewarray	#108; //class scala/Tuple2
   11:	checkcast	#101; //class "[Ljava/lang/Object;"
   14:	invokevirtual	#129; //Method scala/Predef$.wrapRefArray:([Ljava/lang/Object;)Lscala/collection/mutable/WrappedArray;
   17:	invokevirtual	#220; //Method scala/collection/immutable/Map$.apply:(Lscala/collection/Seq;)Lscala/collection/Map;
   20:	checkcast	#222; //class scala/collection/immutable/Map
   23:	invokevirtual	#350; //Method labelAt_$eq:(Lscala/collection/immutable/Map;)V
   26:	aload_0
   27:	getstatic	#355; //Field scala/collection/mutable/HashMap$.MODULE$:Lscala/collection/mutable/HashMap$;
   30:	getstatic	#96; //Field scala/Predef$.MODULE$:Lscala/Predef$;
   33:	iconst_0
   34:	anewarray	#108; //class scala/Tuple2
   37:	checkcast	#101; //class "[Ljava/lang/Object;"
   40:	invokevirtual	#129; //Method scala/Predef$.wrapRefArray:([Ljava/lang/Object;)Lscala/collection/mutable/WrappedArray;
   43:	invokevirtual	#356; //Method scala/collection/mutable/HashMap$.apply:(Lscala/collection/Seq;)Lscala/collection/Map;
   46:	checkcast	#110; //class scala/collection/mutable/HashMap
   49:	invokevirtual	#360; //Method follow_$eq:(Lscala/collection/mutable/HashMap;)V
   52:	aload_0
   53:	getstatic	#365; //Field scala/collection/mutable/HashSet$.MODULE$:Lscala/collection/mutable/HashSet$;
   56:	getstatic	#96; //Field scala/Predef$.MODULE$:Lscala/Predef$;
   59:	iconst_0
   60:	anewarray	#123; //class scala/util/regexp/WordExp$Label
   63:	checkcast	#101; //class "[Ljava/lang/Object;"
   66:	invokevirtual	#129; //Method scala/Predef$.wrapRefArray:([Ljava/lang/Object;)Lscala/collection/mutable/WrappedArray;
   69:	invokevirtual	#368; //Method scala/collection/mutable/HashSet$.apply:(Lscala/collection/Seq;)Lscala/collection/Traversable;
   72:	checkcast	#370; //class scala/collection/mutable/HashSet
   75:	invokevirtual	#374; //Method labels_$eq:(Lscala/collection/mutable/HashSet;)V
   78:	aload_0
   79:	iconst_0
   80:	invokevirtual	#51; //Method pos_$eq:(I)V
   83:	aload_1
   84:	new	#376; //class scala/util/automata/WordBerrySethi$$anonfun$initialize$1
   87:	dup
   88:	aload_0
   89:	invokespecial	#377; //Method scala/util/automata/WordBerrySethi$$anonfun$initialize$1."<init>":(Lscala/util/automata/WordBerrySethi;)V
   92:	invokeinterface	#380,  2; //InterfaceMethod scala/collection/IterableLike.foreach:(Lscala/Function1;)V
   97:	aload_0
   98:	getstatic	#385; //Field scala/collection/immutable/Set$.MODULE$:Lscala/collection/immutable/Set$;
   101:	getstatic	#96; //Field scala/Predef$.MODULE$:Lscala/Predef$;
   104:	iconst_1
   105:	newarray int
   107:	dup
   108:	iconst_0
   109:	iconst_0
   110:	iastore
   111:	invokevirtual	#389; //Method scala/Predef$.wrapIntArray:([I)Lscala/collection/mutable/WrappedArray;
   114:	invokevirtual	#390; //Method scala/collection/immutable/Set$.apply:(Lscala/collection/Seq;)Lscala/collection/Traversable;
   117:	checkcast	#392; //class scala/collection/immutable/Set
   120:	invokevirtual	#396; //Method initials_$eq:(Lscala/collection/immutable/Set;)V
   123:	return
  LineNumberTable: 
   line 105: 0
   line 106: 26
   line 107: 52
   line 108: 78
   line 111: 83
   line 113: 97

  LocalVariableTable: 
   Start  Length  Slot  Name   Signature
   0      124      0    this       Lscala/util/automata/WordBerrySethi;
   0      124      1    subexpr       Lscala/collection/Seq;

  Signature: length = 0x2
   01 FFFFFF8F 

public void makeTransition(int, int, scala.util.regexp.WordExp$Label);
  Code:
   Stack=7, Locals=5, Args_size=4
   0:	aload_0
   1:	invokevirtual	#99; //Method deltaq:()[Lscala/collection/mutable/HashMap;
   4:	iload_1
   5:	aaload
   6:	astore	4
   8:	aload	4
   10:	aload_3
   11:	aload	4
   13:	aload_3
   14:	new	#403; //class scala/util/automata/WordBerrySethi$$anonfun$makeTransition$1
   17:	dup
   18:	aload_0
   19:	invokespecial	#404; //Method scala/util/automata/WordBerrySethi$$anonfun$makeTransition$1."<init>":(Lscala/util/automata/WordBerrySethi;)V
   22:	invokeinterface	#410,  3; //InterfaceMethod scala/collection/MapLike.getOrElse:(Ljava/lang/Object;Lscala/Function0;)Ljava/lang/Object;
   27:	checkcast	#150; //class scala/collection/immutable/List
   30:	iload_2
   31:	invokestatic	#75; //Method scala/runtime/BoxesRunTime.boxToInteger:(I)Ljava/lang/Integer;
   34:	invokevirtual	#168; //Method scala/collection/immutable/List.$colon$colon:(Ljava/lang/Object;)Lscala/collection/immutable/List;
   37:	invokevirtual	#414; //Method scala/collection/mutable/HashMap.update:(Ljava/lang/Object;Ljava/lang/Object;)V
   40:	return
  LineNumberTable: 
   line 100: 0
   line 101: 8

  LocalVariableTable: 
   Start  Length  Slot  Name   Signature
   0      41      0    this       Lscala/util/automata/WordBerrySethi;
   0      41      1    src       I
   0      41      2    dest       I
   0      41      3    label       Lscala/util/regexp/WordExp$Label;
   8      32      4    q       Lscala/collection/mutable/HashMap;


public void traverse(scala.util.regexp.Base$RegExp);
  Code:
   Stack=4, Locals=5, Args_size=2
   0:	aload_1
   1:	instanceof	#424; //class scala/util/regexp/WordExp$Letter
   4:	ifeq	46
   7:	aload_1
   8:	checkcast	#424; //class scala/util/regexp/WordExp$Letter
   11:	astore_2
   12:	aload_2
   13:	invokevirtual	#428; //Method scala/util/regexp/WordExp$Letter.a:()Lscala/util/regexp/WordExp$Label;
   16:	astore_3
   17:	iconst_1
   18:	ifeq	34
   21:	aload_2
   22:	aload_0
   23:	aload_1
   24:	aload_3
   25:	invokevirtual	#432; //Method seenLabel:(Lscala/util/regexp/Base$RegExp;Lscala/util/regexp/WordExp$Label;)I
   28:	invokevirtual	#433; //Method scala/util/regexp/WordExp$Letter.pos_$eq:(I)V
   31:	goto	102
   34:	new	#283; //class scala/MatchError
   37:	dup
   38:	aload_1
   39:	invokevirtual	#289; //Method scala/util/regexp/Base$RegExp.toString:()Ljava/lang/String;
   42:	invokespecial	#292; //Method scala/MatchError."<init>":(Ljava/lang/String;)V
   45:	athrow
   46:	aload_1
   47:	aload_0
   48:	invokevirtual	#114; //Method lang:()Lscala/util/regexp/WordExp;
   51:	invokevirtual	#437; //Method scala/util/regexp/WordExp.Eps:()Lscala/util/regexp/Base$Eps$;
   54:	astore	4
   56:	dup
   57:	ifnonnull	69
   60:	pop
   61:	aload	4
   63:	ifnull	77
   66:	goto	93
   69:	aload	4
   71:	invokevirtual	#443; //Method java/lang/Object.equals:(Ljava/lang/Object;)Z
   74:	ifeq	93
   77:	iconst_1
   78:	ifne	102
   81:	new	#283; //class scala/MatchError
   84:	dup
   85:	aload_1
   86:	invokevirtual	#289; //Method scala/util/regexp/Base$RegExp.toString:()Ljava/lang/String;
   89:	invokespecial	#292; //Method scala/MatchError."<init>":(Ljava/lang/String;)V
   92:	athrow
   93:	iconst_1
   94:	ifeq	103
   97:	aload_0
   98:	aload_1
   99:	invokespecial	#445; //Method scala/util/automata/BaseBerrySethi.traverse:(Lscala/util/regexp/Base$RegExp;)V
   102:	return
   103:	new	#283; //class scala/MatchError
   106:	dup
   107:	aload_1
   108:	invokevirtual	#289; //Method scala/util/regexp/Base$RegExp.toString:()Ljava/lang/String;
   111:	invokespecial	#292; //Method scala/MatchError."<init>":(Ljava/lang/String;)V
   114:	athrow
  LineNumberTable: 
   line 92: 0
   line 21: 17
   line 93: 21
   line 92: 34
   line 21: 77
   line 92: 81
   line 21: 93
   line 95: 97
   line 92: 102

  LocalVariableTable: 
   Start  Length  Slot  Name   Signature
   0      115      0    this       Lscala/util/automata/WordBerrySethi;
   0      115      1    r       Lscala/util/regexp/Base$RegExp;
   12      34      2    temp11       Lscala/util/regexp/WordExp$Letter;
   17      29      3    temp12       Lscala/util/regexp/WordExp$Label;


public int seenLabel(scala.util.regexp.Base$RegExp, scala.util.regexp.WordExp$Label);
  Code:
   Stack=4, Locals=3, Args_size=3
   0:	aload_0
   1:	aload_0
   2:	invokevirtual	#48; //Method pos:()I
   5:	iconst_1
   6:	iadd
   7:	invokevirtual	#51; //Method pos_$eq:(I)V
   10:	aload_0
   11:	aload_1
   12:	aload_0
   13:	invokevirtual	#48; //Method pos:()I
   16:	aload_2
   17:	invokevirtual	#452; //Method seenLabel:(Lscala/util/regexp/Base$RegExp;ILscala/util/regexp/WordExp$Label;)V
   20:	aload_0
   21:	invokevirtual	#48; //Method pos:()I
   24:	ireturn
  LineNumberTable: 
   line 86: 0
   line 87: 10
   line 88: 20

  LocalVariableTable: 
   Start  Length  Slot  Name   Signature
   0      25      0    this       Lscala/util/automata/WordBerrySethi;
   0      25      1    r       Lscala/util/regexp/Base$RegExp;
   0      25      2    label       Lscala/util/regexp/WordExp$Label;


public void seenLabel(scala.util.regexp.Base$RegExp, int, scala.util.regexp.WordExp$Label);
  Code:
   Stack=4, Locals=4, Args_size=4
   0:	aload_0
   1:	aload_0
   2:	invokevirtual	#454; //Method labelAt:()Lscala/collection/immutable/Map;
   5:	iload_2
   6:	invokestatic	#75; //Method scala/runtime/BoxesRunTime.boxToInteger:(I)Ljava/lang/Integer;
   9:	aload_3
   10:	invokeinterface	#81,  3; //InterfaceMethod scala/collection/immutable/MapLike.updated:(Ljava/lang/Object;Ljava/lang/Object;)Lscala/collection/immutable/Map;
   15:	invokevirtual	#350; //Method labelAt_$eq:(Lscala/collection/immutable/Map;)V
   18:	aload_0
   19:	invokevirtual	#457; //Method labels:()Lscala/collection/mutable/HashSet;
   22:	aload_3
   23:	invokevirtual	#461; //Method scala/collection/mutable/HashSet.$plus$eq:(Ljava/lang/Object;)Lscala/collection/mutable/HashSet;
   26:	pop
   27:	return
  LineNumberTable: 
   line 80: 0
   line 81: 18

  LocalVariableTable: 
   Start  Length  Slot  Name   Signature
   0      28      0    this       Lscala/util/automata/WordBerrySethi;
   0      28      1    r       Lscala/util/regexp/Base$RegExp;
   0      28      2    i       I
   0      28      3    label       Lscala/util/regexp/WordExp$Label;


public scala.collection.immutable.Set compFollow1(scala.collection.immutable.Set, scala.util.regexp.Base$RegExp);
  Code:
   Stack=6, Locals=6, Args_size=3
   0:	aload_2
   1:	instanceof	#424; //class scala/util/regexp/WordExp$Letter
   4:	ifeq	76
   7:	aload_2
   8:	checkcast	#424; //class scala/util/regexp/WordExp$Letter
   11:	astore	4
   13:	iconst_1
   14:	ifeq	64
   17:	aload_0
   18:	invokevirtual	#468; //Method follow:()Lscala/collection/mutable/HashMap;
   21:	aload	4
   23:	invokevirtual	#469; //Method scala/util/regexp/WordExp$Letter.pos:()I
   26:	istore_3
   27:	iload_3
   28:	invokestatic	#75; //Method scala/runtime/BoxesRunTime.boxToInteger:(I)Ljava/lang/Integer;
   31:	aload_1
   32:	invokevirtual	#414; //Method scala/collection/mutable/HashMap.update:(Ljava/lang/Object;Ljava/lang/Object;)V
   35:	getstatic	#385; //Field scala/collection/immutable/Set$.MODULE$:Lscala/collection/immutable/Set$;
   38:	getstatic	#96; //Field scala/Predef$.MODULE$:Lscala/Predef$;
   41:	iconst_1
   42:	newarray int
   44:	dup
   45:	iconst_0
   46:	aload	4
   48:	invokevirtual	#469; //Method scala/util/regexp/WordExp$Letter.pos:()I
   51:	iastore
   52:	invokevirtual	#389; //Method scala/Predef$.wrapIntArray:([I)Lscala/collection/mutable/WrappedArray;
   55:	invokevirtual	#390; //Method scala/collection/immutable/Set$.apply:(Lscala/collection/Seq;)Lscala/collection/Traversable;
   58:	checkcast	#392; //class scala/collection/immutable/Set
   61:	goto	140
   64:	new	#283; //class scala/MatchError
   67:	dup
   68:	aload_2
   69:	invokevirtual	#289; //Method scala/util/regexp/Base$RegExp.toString:()Ljava/lang/String;
   72:	invokespecial	#292; //Method scala/MatchError."<init>":(Ljava/lang/String;)V
   75:	athrow
   76:	aload_2
   77:	aload_0
   78:	invokevirtual	#114; //Method lang:()Lscala/util/regexp/WordExp;
   81:	invokevirtual	#437; //Method scala/util/regexp/WordExp.Eps:()Lscala/util/regexp/Base$Eps$;
   84:	astore	5
   86:	dup
   87:	ifnonnull	99
   90:	pop
   91:	aload	5
   93:	ifnull	107
   96:	goto	130
   99:	aload	5
   101:	invokevirtual	#443; //Method java/lang/Object.equals:(Ljava/lang/Object;)Z
   104:	ifeq	130
   107:	iconst_1
   108:	ifeq	118
   111:	aload_0
   112:	invokevirtual	#472; //Method emptySet:()Lscala/collection/immutable/Set;
   115:	goto	140
   118:	new	#283; //class scala/MatchError
   121:	dup
   122:	aload_2
   123:	invokevirtual	#289; //Method scala/util/regexp/Base$RegExp.toString:()Ljava/lang/String;
   126:	invokespecial	#292; //Method scala/MatchError."<init>":(Ljava/lang/String;)V
   129:	athrow
   130:	iconst_1
   131:	ifeq	141
   134:	aload_0
   135:	aload_1
   136:	aload_2
   137:	invokespecial	#474; //Method scala/util/automata/BaseBerrySethi.compFollow1:(Lscala/collection/immutable/Set;Lscala/util/regexp/Base$RegExp;)Lscala/collection/immutable/Set;
   140:	areturn
   141:	new	#283; //class scala/MatchError
   144:	dup
   145:	aload_2
   146:	invokevirtual	#289; //Method scala/util/regexp/Base$RegExp.toString:()Ljava/lang/String;
   149:	invokespecial	#292; //Method scala/MatchError."<init>":(Ljava/lang/String;)V
   152:	athrow
  LineNumberTable: 
   line 68: 0
   line 21: 13
   line 69: 17
   line 68: 64
   line 21: 107
   line 70: 111
   line 68: 118
   line 21: 130
   line 71: 134
   line 68: 140

  LocalVariableTable: 
   Start  Length  Slot  Name   Signature
   0      153      0    this       Lscala/util/automata/WordBerrySethi;
   0      153      1    fol1       Lscala/collection/immutable/Set;
   0      153      2    r       Lscala/util/regexp/Base$RegExp;
   13      63      4    temp8       Lscala/util/regexp/WordExp$Letter;

  Signature: length = 0x2
   01 FFFFFFDD 

public scala.collection.immutable.Set compLast(scala.util.regexp.Base$RegExp);
  Code:
   Stack=6, Locals=3, Args_size=2
   0:	aload_1
   1:	instanceof	#424; //class scala/util/regexp/WordExp$Letter
   4:	ifeq	56
   7:	aload_1
   8:	checkcast	#424; //class scala/util/regexp/WordExp$Letter
   11:	astore_2
   12:	iconst_1
   13:	ifeq	44
   16:	getstatic	#385; //Field scala/collection/immutable/Set$.MODULE$:Lscala/collection/immutable/Set$;
   19:	getstatic	#96; //Field scala/Predef$.MODULE$:Lscala/Predef$;
   22:	iconst_1
   23:	newarray int
   25:	dup
   26:	iconst_0
   27:	aload_2
   28:	invokevirtual	#469; //Method scala/util/regexp/WordExp$Letter.pos:()I
   31:	iastore
   32:	invokevirtual	#389; //Method scala/Predef$.wrapIntArray:([I)Lscala/collection/mutable/WrappedArray;
   35:	invokevirtual	#390; //Method scala/collection/immutable/Set$.apply:(Lscala/collection/Seq;)Lscala/collection/Traversable;
   38:	checkcast	#392; //class scala/collection/immutable/Set
   41:	goto	65
   44:	new	#283; //class scala/MatchError
   47:	dup
   48:	aload_1
   49:	invokevirtual	#289; //Method scala/util/regexp/Base$RegExp.toString:()Ljava/lang/String;
   52:	invokespecial	#292; //Method scala/MatchError."<init>":(Ljava/lang/String;)V
   55:	athrow
   56:	iconst_1
   57:	ifeq	66
   60:	aload_0
   61:	aload_1
   62:	invokespecial	#481; //Method scala/util/automata/BaseBerrySethi.compLast:(Lscala/util/regexp/Base$RegExp;)Lscala/collection/immutable/Set;
   65:	areturn
   66:	new	#283; //class scala/MatchError
   69:	dup
   70:	aload_1
   71:	invokevirtual	#289; //Method scala/util/regexp/Base$RegExp.toString:()Ljava/lang/String;
   74:	invokespecial	#292; //Method scala/MatchError."<init>":(Ljava/lang/String;)V
   77:	athrow
  LineNumberTable: 
   line 56: 0
   line 21: 12
   line 57: 16
   line 56: 44
   line 21: 56
   line 58: 60
   line 56: 65

  LocalVariableTable: 
   Start  Length  Slot  Name   Signature
   0      78      0    this       Lscala/util/automata/WordBerrySethi;
   0      78      1    r       Lscala/util/regexp/Base$RegExp;
   12      44      2    temp5       Lscala/util/regexp/WordExp$Letter;

  Signature: length = 0x2
   01 FFFFFFE3 

public scala.collection.immutable.Set compFirst(scala.util.regexp.Base$RegExp);
  Code:
   Stack=6, Locals=3, Args_size=2
   0:	aload_1
   1:	instanceof	#424; //class scala/util/regexp/WordExp$Letter
   4:	ifeq	56
   7:	aload_1
   8:	checkcast	#424; //class scala/util/regexp/WordExp$Letter
   11:	astore_2
   12:	iconst_1
   13:	ifeq	44
   16:	getstatic	#385; //Field scala/collection/immutable/Set$.MODULE$:Lscala/collection/immutable/Set$;
   19:	getstatic	#96; //Field scala/Predef$.MODULE$:Lscala/Predef$;
   22:	iconst_1
   23:	newarray int
   25:	dup
   26:	iconst_0
   27:	aload_2
   28:	invokevirtual	#469; //Method scala/util/regexp/WordExp$Letter.pos:()I
   31:	iastore
   32:	invokevirtual	#389; //Method scala/Predef$.wrapIntArray:([I)Lscala/collection/mutable/WrappedArray;
   35:	invokevirtual	#390; //Method scala/collection/immutable/Set$.apply:(Lscala/collection/Seq;)Lscala/collection/Traversable;
   38:	checkcast	#392; //class scala/collection/immutable/Set
   41:	goto	65
   44:	new	#283; //class scala/MatchError
   47:	dup
   48:	aload_1
   49:	invokevirtual	#289; //Method scala/util/regexp/Base$RegExp.toString:()Ljava/lang/String;
   52:	invokespecial	#292; //Method scala/MatchError."<init>":(Ljava/lang/String;)V
   55:	athrow
   56:	iconst_1
   57:	ifeq	66
   60:	aload_0
   61:	aload_1
   62:	invokespecial	#486; //Method scala/util/automata/BaseBerrySethi.compFirst:(Lscala/util/regexp/Base$RegExp;)Lscala/collection/immutable/Set;
   65:	areturn
   66:	new	#283; //class scala/MatchError
   69:	dup
   70:	aload_1
   71:	invokevirtual	#289; //Method scala/util/regexp/Base$RegExp.toString:()Ljava/lang/String;
   74:	invokespecial	#292; //Method scala/MatchError."<init>":(Ljava/lang/String;)V
   77:	athrow
  LineNumberTable: 
   line 46: 0
   line 21: 12
   line 47: 16
   line 46: 44
   line 21: 56
   line 48: 60
   line 46: 65

  LocalVariableTable: 
   Start  Length  Slot  Name   Signature
   0      78      0    this       Lscala/util/automata/WordBerrySethi;
   0      78      1    r       Lscala/util/regexp/Base$RegExp;
   12      44      2    temp2       Lscala/util/regexp/WordExp$Letter;

  Signature: length = 0x2
   01 FFFFFFE3 

public void initials_$eq(scala.collection.immutable.Set);
  Code:
   Stack=2, Locals=2, Args_size=2
   0:	aload_0
   1:	aload_1
   2:	putfield	#489; //Field initials:Lscala/collection/immutable/Set;
   5:	return
  LineNumberTable: 
   line 39: 0

  Signature: length = 0x2
   01 FFFFFFEA 

public scala.collection.immutable.Set initials();
  Code:
   Stack=1, Locals=1, Args_size=1
   0:	aload_0
   1:	getfield	#489; //Field initials:Lscala/collection/immutable/Set;
   4:	areturn
  LineNumberTable: 
   line 39: 0

  Signature: length = 0x2
   01 FFFFFFEB 

public void defaultq_$eq(scala.collection.immutable.List[]);
  Code:
   Stack=2, Locals=2, Args_size=2
   0:	aload_0
   1:	aload_1
   2:	putfield	#493; //Field defaultq:[Lscala/collection/immutable/List;
   5:	return
  LineNumberTable: 
   line 37: 0

  Signature: length = 0x2
   01 FFFFFFEE 

public scala.collection.immutable.List[] defaultq();
  Code:
   Stack=1, Locals=1, Args_size=1
   0:	aload_0
   1:	getfield	#493; //Field defaultq:[Lscala/collection/immutable/List;
   4:	areturn
  LineNumberTable: 
   line 37: 0

  Signature: length = 0x2
   01 FFFFFFF0 

public void deltaq_$eq(scala.collection.mutable.HashMap[]);
  Code:
   Stack=2, Locals=2, Args_size=2
   0:	aload_0
   1:	aload_1
   2:	putfield	#498; //Field deltaq:[Lscala/collection/mutable/HashMap;
   5:	return
  LineNumberTable: 
   line 35: 0

  Signature: length = 0x2
   01 FFFFFFF3 

public scala.collection.mutable.HashMap[] deltaq();
  Code:
   Stack=1, Locals=1, Args_size=1
   0:	aload_0
   1:	getfield	#498; //Field deltaq:[Lscala/collection/mutable/HashMap;
   4:	areturn
  LineNumberTable: 
   line 35: 0

  Signature: length = 0x2
   01 FFFFFFF4 

public void labelAt_$eq(scala.collection.immutable.Map);
  Code:
   Stack=2, Locals=2, Args_size=2
   0:	aload_0
   1:	aload_1
   2:	putfield	#502; //Field labelAt:Lscala/collection/immutable/Map;
   5:	return
  LineNumberTable: 
   line 33: 0

  Signature: length = 0x2
   01 FFFFFFF7 

public scala.collection.immutable.Map labelAt();
  Code:
   Stack=1, Locals=1, Args_size=1
   0:	aload_0
   1:	getfield	#502; //Field labelAt:Lscala/collection/immutable/Map;
   4:	areturn
  LineNumberTable: 
   line 33: 0

  Signature: length = 0x2
   01 FFFFFFF8 

public void labels_$eq(scala.collection.mutable.HashSet);
  Code:
   Stack=2, Locals=2, Args_size=2
   0:	aload_0
   1:	aload_1
   2:	putfield	#506; //Field labels:Lscala/collection/mutable/HashSet;
   5:	return
  LineNumberTable: 
   line 31: 0

  Signature: length = 0x2
   01 FFFFFFFB 

public scala.collection.mutable.HashSet labels();
  Code:
   Stack=1, Locals=1, Args_size=1
   0:	aload_0
   1:	getfield	#506; //Field labels:Lscala/collection/mutable/HashSet;
   4:	areturn
  LineNumberTable: 
   line 31: 0

  Signature: length = 0x2
   01 FFFFFFFC 

public abstract scala.util.regexp.WordExp lang();

}

