Compiled from "WordBerrySethi.scala"
public final class scala.util.automata.WordBerrySethi$$anonfun$collectTransitions$2$$anonfun$apply$1 extends java.lang.Object implements scala.Function1,scala.ScalaObject,java.io.Serializable
  SourceFile: "WordBerrySethi.scala"
  Scala: length = 0x
   
  InnerClass: 
   public abstract Label=class scala/util/regexp/WordExp$Label of class scala/util/regexp/WordExp
   public final $anonfun$collectTransitions$2=class scala/util/automata/WordBerrySethi$$anonfun$collectTransitions$2 of class scala/util/automata/WordBerrySethi
   public final $anonfun$apply$1=class scala/util/automata/WordBerrySethi$$anonfun$collectTransitions$2$$anonfun$apply$1 of class scala/util/automata/WordBerrySethi$$anonfun$collectTransitions$2
  minor version: 0
  major version: 49
  Constant pool:
Asciz	SourceFile;
Asciz	WordBerrySethi.scala;
Asciz	<clinit>;
Asciz	()V;
Asciz	Code;
Asciz	serialVersionUID;
Asciz	J;
Asciz	scala/util/automata/WordBerrySethi$$anonfun$collectTransitions$2$$anonfun$apply$1;
class	scala/util/automata/WordBerrySethi$$anonfun$collectTransitions$2$$anonfun$apply$1
NameAndType	serialVersionUID:J
Field	scala/util/automata/WordBerrySethi$$anonfun$collectTransitions$2$$anonfun$apply$1.serialVersionUID:J
Asciz	j$1;
Asciz	I;
Asciz	$outer;
Asciz	Lscala/util/automata/WordBerrySethi$$anonfun$collectTransitions$2;;
Asciz	<init>;
Asciz	(Lscala/util/automata/WordBerrySethi$$anonfun$collectTransitions$2;I)V;
Asciz	LineNumberTable;
Asciz	java/lang/NullPointerException;
class	java/lang/NullPointerException
NameAndType	"<init>":()V
Method	java/lang/NullPointerException."<init>":()V
NameAndType	$outer:Lscala/util/automata/WordBerrySethi$$anonfun$collectTransitions$2;
Field	scala/util/automata/WordBerrySethi$$anonfun$collectTransitions$2$$anonfun$apply$1.$outer:Lscala/util/automata/WordBerrySethi$$anonfun$collectTransitions$2;
NameAndType	j$1:I
Field	scala/util/automata/WordBerrySethi$$anonfun$collectTransitions$2$$anonfun$apply$1.j$1:I
Asciz	java/lang/Object;
class	java/lang/Object
Method	java/lang/Object."<init>":()V
Asciz	scala/Function1$class;
class	scala/Function1$class
Asciz	$init$;
Asciz	(Lscala/Function1;)V;
NameAndType	$init$:(Lscala/Function1;)V
Method	scala/Function1$class.$init$:(Lscala/Function1;)V
Asciz	this;
Asciz	Lscala/util/automata/WordBerrySethi$$anonfun$collectTransitions$2$$anonfun$apply$1;;
Asciz	LocalVariableTable;
Asciz	apply;
Asciz	(Ljava/lang/Object;)Ljava/lang/Object;;
Asciz	scala/runtime/BoxesRunTime;
class	scala/runtime/BoxesRunTime
Asciz	unboxToInt;
Asciz	(Ljava/lang/Object;)I;
NameAndType	unboxToInt:(Ljava/lang/Object;)I
Method	scala/runtime/BoxesRunTime.unboxToInt:(Ljava/lang/Object;)I
Asciz	(I)V;
NameAndType	apply:(I)V
Method	scala/util/automata/WordBerrySethi$$anonfun$collectTransitions$2$$anonfun$apply$1.apply:(I)V
Asciz	scala/runtime/BoxedUnit;
class	scala/runtime/BoxedUnit
Asciz	UNIT;
Asciz	Lscala/runtime/BoxedUnit;;
NameAndType	UNIT:Lscala/runtime/BoxedUnit;
Field	scala/runtime/BoxedUnit.UNIT:Lscala/runtime/BoxedUnit;
Asciz	v1;
Asciz	Ljava/lang/Object;;
Asciz	scala/util/automata/WordBerrySethi$$anonfun$collectTransitions$2;
class	scala/util/automata/WordBerrySethi$$anonfun$collectTransitions$2
Asciz	Lscala/util/automata/WordBerrySethi;;
NameAndType	$outer:Lscala/util/automata/WordBerrySethi;
Field	scala/util/automata/WordBerrySethi$$anonfun$collectTransitions$2.$outer:Lscala/util/automata/WordBerrySethi;
Asciz	scala/util/automata/WordBerrySethi;
class	scala/util/automata/WordBerrySethi
Asciz	pos;
Asciz	()I;
NameAndType	pos:()I
Method	scala/util/automata/WordBerrySethi.pos:()I
Asciz	finals;
Asciz	()Lscala/collection/immutable/Map;;
NameAndType	finals:()Lscala/collection/immutable/Map;
Method	scala/util/automata/WordBerrySethi.finals:()Lscala/collection/immutable/Map;
Asciz	boxToInteger;
Asciz	(I)Ljava/lang/Integer;;
NameAndType	boxToInteger:(I)Ljava/lang/Integer;
Method	scala/runtime/BoxesRunTime.boxToInteger:(I)Ljava/lang/Integer;
Asciz	finalTag;
NameAndType	finalTag:()I
Method	scala/util/automata/WordBerrySethi.finalTag:()I
Asciz	scala/collection/immutable/MapLike;
class	scala/collection/immutable/MapLike
Asciz	updated;
Asciz	(Ljava/lang/Object;Ljava/lang/Object;)Lscala/collection/immutable/Map;;
NameAndType	updated:(Ljava/lang/Object;Ljava/lang/Object;)Lscala/collection/immutable/Map;
InterfaceMethod	scala/collection/immutable/MapLike.updated:(Ljava/lang/Object;Ljava/lang/Object;)Lscala/collection/immutable/Map;
Asciz	finals_$eq;
Asciz	(Lscala/collection/immutable/Map;)V;
NameAndType	finals_$eq:(Lscala/collection/immutable/Map;)V
Method	scala/util/automata/WordBerrySethi.finals_$eq:(Lscala/collection/immutable/Map;)V
Asciz	labelAt;
NameAndType	labelAt:()Lscala/collection/immutable/Map;
Method	scala/util/automata/WordBerrySethi.labelAt:()Lscala/collection/immutable/Map;
Asciz	scala/collection/MapLike;
class	scala/collection/MapLike
NameAndType	apply:(Ljava/lang/Object;)Ljava/lang/Object;
InterfaceMethod	scala/collection/MapLike.apply:(Ljava/lang/Object;)Ljava/lang/Object;
Asciz	scala/util/regexp/WordExp$Label;
class	scala/util/regexp/WordExp$Label
Asciz	makeTransition;
Asciz	(IILscala/util/regexp/WordExp$Label;)V;
NameAndType	makeTransition:(IILscala/util/regexp/WordExp$Label;)V
Method	scala/util/automata/WordBerrySethi.makeTransition:(IILscala/util/regexp/WordExp$Label;)V
Asciz	k;
Asciz	andThen;
Asciz	(Lscala/Function1;)Lscala/Function1;;
Asciz	(Lscala/Function1;Lscala/Function1;)Lscala/Function1;;
NameAndType	andThen:(Lscala/Function1;Lscala/Function1;)Lscala/Function1;
Method	scala/Function1$class.andThen:(Lscala/Function1;Lscala/Function1;)Lscala/Function1;
Asciz	g;
Asciz	Lscala/Function1;;
Asciz	compose;
NameAndType	compose:(Lscala/Function1;Lscala/Function1;)Lscala/Function1;
Method	scala/Function1$class.compose:(Lscala/Function1;Lscala/Function1;)Lscala/Function1;
Asciz	toString;
Asciz	()Ljava/lang/String;;
Asciz	(Lscala/Function1;)Ljava/lang/String;;
NameAndType	toString:(Lscala/Function1;)Ljava/lang/String;
Method	scala/Function1$class.toString:(Lscala/Function1;)Ljava/lang/String;
Asciz	Scala;
Asciz	InnerClasses;
Asciz	scala/util/regexp/WordExp;
class	scala/util/regexp/WordExp
Asciz	Label;
Asciz	$anonfun$collectTransitions$2;
Asciz	$anonfun$apply$1;
Asciz	scala/Function1;
class	scala/Function1
Asciz	scala/ScalaObject;
class	scala/ScalaObject
Asciz	java/io/Serializable;
class	java/io/Serializable

{
public static final long serialVersionUID;
  Signature: J

private final int j$1;
  Signature: I

private final scala.util.automata.WordBerrySethi$$anonfun$collectTransitions$2 $outer;
  Signature: Lscala/util/automata/WordBerrySethi$$anonfun$collectTransitions$2;

public static {};
  Signature: ()V
  Code:
   Stack=2, Locals=0, Args_size=0
	lconst_0
	putstatic	Field serialVersionUID:J
	return
  Labels:

public scala.util.automata.WordBerrySethi$$anonfun$collectTransitions$2$$anonfun$apply$1(scala.util.automata.WordBerrySethi$$anonfun$collectTransitions$2, int);
  Signature: (Lscala/util/automata/WordBerrySethi$$anonfun$collectTransitions$2;I)V
  Code:
   Stack=2, Locals=3, Args_size=3
	aload_1
	ifnonnull	l1 // aload_0
	new	class java/lang/NullPointerException
	dup
	invokespecial	Method java/lang/NullPointerException."<init>":()V
	athrow
l1	aload_0
	aload_1
	putfield	Field $outer:Lscala/util/automata/WordBerrySethi$$anonfun$collectTransitions$2;
	aload_0
	iload_2
	putfield	Field j$1:I
	aload_0
	invokespecial	Method java/lang/Object."<init>":()V
	aload_0
	invokestatic	Method scala/Function1$class.$init$:(Lscala/Function1;)V
	return
  Labels:
   	l1 = 12 // aload_0
  LocalVariableTable: 
   Start  Length  Slot  Name   Signature
   0      31      0    this       Lscala/util/automata/WordBerrySethi$$anonfun$collectTransitions$2$$anonfun$apply$1;
   0      31      1    $outer       Lscala/util/automata/WordBerrySethi$$anonfun$collectTransitions$2;


public final java.lang.Object apply(java.lang.Object);
  Signature: (Ljava/lang/Object;)Ljava/lang/Object;
  Code:
   Stack=2, Locals=3, Args_size=2
	aload_0
	getfield	Field $outer:Lscala/util/automata/WordBerrySethi$$anonfun$collectTransitions$2;
	astore_2
	aload_0
	aload_1
	invokestatic	Method scala/runtime/BoxesRunTime.unboxToInt:(Ljava/lang/Object;)I
	invokevirtual	Method apply:(I)V
	getstatic	Field scala/runtime/BoxedUnit.UNIT:Lscala/runtime/BoxedUnit;
	areturn
  Labels:
  LocalVariableTable: 
   Start  Length  Slot  Name   Signature
   0      17      0    this       Lscala/util/automata/WordBerrySethi$$anonfun$collectTransitions$2$$anonfun$apply$1;
   5      12      1    v1       Ljava/lang/Object;


public final void apply(int);
  Signature: (I)V
  Code:
   Stack=5, Locals=11, Args_size=2
	aload_0
	getfield	Field $outer:Lscala/util/automata/WordBerrySethi$$anonfun$collectTransitions$2;
	astore	10
	aload_0
	getfield	Field $outer:Lscala/util/automata/WordBerrySethi$$anonfun$collectTransitions$2;
	astore_2
	aload_2
	getfield	Field scala/util/automata/WordBerrySethi$$anonfun$collectTransitions$2.$outer:Lscala/util/automata/WordBerrySethi;
	invokevirtual	Method scala/util/automata/WordBerrySethi.pos:()I
	iload_1
	if_icmpne	l1 // aload_0
	aload_0
	getfield	Field $outer:Lscala/util/automata/WordBerrySethi$$anonfun$collectTransitions$2;
	astore_3
	aload_3
	getfield	Field scala/util/automata/WordBerrySethi$$anonfun$collectTransitions$2.$outer:Lscala/util/automata/WordBerrySethi;
	aload_0
	getfield	Field $outer:Lscala/util/automata/WordBerrySethi$$anonfun$collectTransitions$2;
	astore	4
	aload	4
	getfield	Field scala/util/automata/WordBerrySethi$$anonfun$collectTransitions$2.$outer:Lscala/util/automata/WordBerrySethi;
	invokevirtual	Method scala/util/automata/WordBerrySethi.finals:()Lscala/collection/immutable/Map;
	aload_0
	getfield	Field j$1:I
	istore	5
	iload	5
	invokestatic	Method scala/runtime/BoxesRunTime.boxToInteger:(I)Ljava/lang/Integer;
	aload_0
	getfield	Field $outer:Lscala/util/automata/WordBerrySethi$$anonfun$collectTransitions$2;
	astore	6
	aload	6
	getfield	Field scala/util/automata/WordBerrySethi$$anonfun$collectTransitions$2.$outer:Lscala/util/automata/WordBerrySethi;
	invokevirtual	Method scala/util/automata/WordBerrySethi.finalTag:()I
	istore	7
	iload	7
	invokestatic	Method scala/runtime/BoxesRunTime.boxToInteger:(I)Ljava/lang/Integer;
	invokeinterface	InterfaceMethod scala/collection/immutable/MapLike.updated:(Ljava/lang/Object;Ljava/lang/Object;)Lscala/collection/immutable/Map;
	invokevirtual	Method scala/util/automata/WordBerrySethi.finals_$eq:(Lscala/collection/immutable/Map;)V
	goto	l2 // return
l1	aload_0
	getfield	Field $outer:Lscala/util/automata/WordBerrySethi$$anonfun$collectTransitions$2;
	astore	8
	aload	8
	getfield	Field scala/util/automata/WordBerrySethi$$anonfun$collectTransitions$2.$outer:Lscala/util/automata/WordBerrySethi;
	aload_0
	getfield	Field j$1:I
	iload_1
	aload_0
	getfield	Field $outer:Lscala/util/automata/WordBerrySethi$$anonfun$collectTransitions$2;
	astore	9
	aload	9
	getfield	Field scala/util/automata/WordBerrySethi$$anonfun$collectTransitions$2.$outer:Lscala/util/automata/WordBerrySethi;
	invokevirtual	Method scala/util/automata/WordBerrySethi.labelAt:()Lscala/collection/immutable/Map;
	iload_1
	invokestatic	Method scala/runtime/BoxesRunTime.boxToInteger:(I)Ljava/lang/Integer;
	invokeinterface	InterfaceMethod scala/collection/MapLike.apply:(Ljava/lang/Object;)Ljava/lang/Object;
	checkcast	class scala/util/regexp/WordExp$Label
	invokevirtual	Method scala/util/automata/WordBerrySethi.makeTransition:(IILscala/util/regexp/WordExp$Label;)V
l2	return
  Labels:
   	l1 = 88 // aload_0
   	l2 = 133 // return
  LocalVariableTable: 
   Start  Length  Slot  Name   Signature
   0      134      0    this       Lscala/util/automata/WordBerrySethi$$anonfun$collectTransitions$2$$anonfun$apply$1;
   6      128      1    k       I


public scala.Function1 andThen(scala.Function1);
  Signature: (Lscala/Function1;)Lscala/Function1;
  Code:
   Stack=2, Locals=2, Args_size=2
	aload_0
	aload_1
	invokestatic	Method scala/Function1$class.andThen:(Lscala/Function1;Lscala/Function1;)Lscala/Function1;
	areturn
  Labels:
  LocalVariableTable: 
   Start  Length  Slot  Name   Signature
   0      6      0    this       Lscala/util/automata/WordBerrySethi$$anonfun$collectTransitions$2$$anonfun$apply$1;
   0      6      1    g       Lscala/Function1;


public scala.Function1 compose(scala.Function1);
  Signature: (Lscala/Function1;)Lscala/Function1;
  Code:
   Stack=2, Locals=2, Args_size=2
	aload_0
	aload_1
	invokestatic	Method scala/Function1$class.compose:(Lscala/Function1;Lscala/Function1;)Lscala/Function1;
	areturn
  Labels:
  LocalVariableTable: 
   Start  Length  Slot  Name   Signature
   0      6      0    this       Lscala/util/automata/WordBerrySethi$$anonfun$collectTransitions$2$$anonfun$apply$1;
   0      6      1    g       Lscala/Function1;


public java.lang.String toString();
  Signature: ()Ljava/lang/String;
  Code:
   Stack=1, Locals=1, Args_size=1
	aload_0
	invokestatic	Method scala/Function1$class.toString:(Lscala/Function1;)Ljava/lang/String;
	areturn
  Labels:

}

