Compiled from "WordBerrySethi.scala"
public final class scala.util.automata.WordBerrySethi$$anonfun$collectTransitions$2 extends java.lang.Object implements scala.Function1,scala.ScalaObject,java.io.Serializable
  SourceFile: "WordBerrySethi.scala"
  Scala: length = 0x
   
  InnerClass: 
   public final $anonfun$collectTransitions$2=class scala/util/automata/WordBerrySethi$$anonfun$collectTransitions$2 of class scala/util/automata/WordBerrySethi
   public final $anonfun$apply$1=class scala/util/automata/WordBerrySethi$$anonfun$collectTransitions$2$$anonfun$apply$1 of class scala/util/automata/WordBerrySethi$$anonfun$collectTransitions$2
  minor version: 0
  major version: 49
  Constant pool:
Asciz	SourceFile;
Asciz	WordBerrySethi.scala;
Asciz	<clinit>;
Asciz	()V;
Asciz	Code;
Asciz	serialVersionUID;
Asciz	J;
Asciz	scala/util/automata/WordBerrySethi$$anonfun$collectTransitions$2;
class	scala/util/automata/WordBerrySethi$$anonfun$collectTransitions$2
NameAndType	serialVersionUID:J
Field	scala/util/automata/WordBerrySethi$$anonfun$collectTransitions$2.serialVersionUID:J
Asciz	$outer;
Asciz	Lscala/util/automata/WordBerrySethi;;
Asciz	<init>;
Asciz	(Lscala/util/automata/WordBerrySethi;)V;
Asciz	LineNumberTable;
Asciz	java/lang/NullPointerException;
class	java/lang/NullPointerException
NameAndType	"<init>":()V
Method	java/lang/NullPointerException."<init>":()V
NameAndType	$outer:Lscala/util/automata/WordBerrySethi;
Field	scala/util/automata/WordBerrySethi$$anonfun$collectTransitions$2.$outer:Lscala/util/automata/WordBerrySethi;
Asciz	java/lang/Object;
class	java/lang/Object
Method	java/lang/Object."<init>":()V
Asciz	scala/Function1$class;
class	scala/Function1$class
Asciz	$init$;
Asciz	(Lscala/Function1;)V;
NameAndType	$init$:(Lscala/Function1;)V
Method	scala/Function1$class.$init$:(Lscala/Function1;)V
Asciz	this;
Asciz	Lscala/util/automata/WordBerrySethi$$anonfun$collectTransitions$2;;
Asciz	LocalVariableTable;
Asciz	apply;
Asciz	(Ljava/lang/Object;)Ljava/lang/Object;;
Asciz	scala/Tuple2;
class	scala/Tuple2
Asciz	(Lscala/Tuple2;)V;
NameAndType	apply:(Lscala/Tuple2;)V
Method	scala/util/automata/WordBerrySethi$$anonfun$collectTransitions$2.apply:(Lscala/Tuple2;)V
Asciz	scala/runtime/BoxedUnit;
class	scala/runtime/BoxedUnit
Asciz	UNIT;
Asciz	Lscala/runtime/BoxedUnit;;
NameAndType	UNIT:Lscala/runtime/BoxedUnit;
Field	scala/runtime/BoxedUnit.UNIT:Lscala/runtime/BoxedUnit;
Asciz	v1;
Asciz	Ljava/lang/Object;;
Asciz	scala$util$automata$WordBerrySethi$$anonfun$$$outer;
Asciz	()Lscala/util/automata/WordBerrySethi;;
Asciz	_1;
Asciz	()Ljava/lang/Object;;
NameAndType	_1:()Ljava/lang/Object;
Method	scala/Tuple2._1:()Ljava/lang/Object;
Asciz	scala/runtime/BoxesRunTime;
class	scala/runtime/BoxesRunTime
Asciz	unboxToInt;
Asciz	(Ljava/lang/Object;)I;
NameAndType	unboxToInt:(Ljava/lang/Object;)I
Method	scala/runtime/BoxesRunTime.unboxToInt:(Ljava/lang/Object;)I
Asciz	_2;
NameAndType	_2:()Ljava/lang/Object;
Method	scala/Tuple2._2:()Ljava/lang/Object;
Asciz	scala/collection/immutable/Set;
class	scala/collection/immutable/Set
Asciz	scala/util/automata/WordBerrySethi$$anonfun$collectTransitions$2$$anonfun$apply$1;
class	scala/util/automata/WordBerrySethi$$anonfun$collectTransitions$2$$anonfun$apply$1
Asciz	(Lscala/util/automata/WordBerrySethi$$anonfun$collectTransitions$2;I)V;
NameAndType	"<init>":(Lscala/util/automata/WordBerrySethi$$anonfun$collectTransitions$2;I)V
Method	scala/util/automata/WordBerrySethi$$anonfun$collectTransitions$2$$anonfun$apply$1."<init>":(Lscala/util/automata/WordBerrySethi$$anonfun$collectTransitions$2;I)V
Asciz	scala/collection/IterableLike;
class	scala/collection/IterableLike
Asciz	foreach;
NameAndType	foreach:(Lscala/Function1;)V
InterfaceMethod	scala/collection/IterableLike.foreach:(Lscala/Function1;)V
Asciz	scala/MatchError;
class	scala/MatchError
Asciz	toString;
Asciz	()Ljava/lang/String;;
NameAndType	toString:()Ljava/lang/String;
Method	scala/Tuple2.toString:()Ljava/lang/String;
Asciz	(Ljava/lang/String;)V;
NameAndType	"<init>":(Ljava/lang/String;)V
Method	scala/MatchError."<init>":(Ljava/lang/String;)V
Asciz	temp15;
Asciz	Lscala/collection/immutable/Set;;
Asciz	temp14;
Asciz	I;
Asciz	(Lscala/Tuple2<Ljava/lang/Integer;Lscala/collection/immutable/Set<Ljava/lang/Integer;>;>;)V;
Asciz	Signature;
Asciz	andThen;
Asciz	(Lscala/Function1;)Lscala/Function1;;
Asciz	(Lscala/Function1;Lscala/Function1;)Lscala/Function1;;
NameAndType	andThen:(Lscala/Function1;Lscala/Function1;)Lscala/Function1;
Method	scala/Function1$class.andThen:(Lscala/Function1;Lscala/Function1;)Lscala/Function1;
Asciz	g;
Asciz	Lscala/Function1;;
Asciz	compose;
NameAndType	compose:(Lscala/Function1;Lscala/Function1;)Lscala/Function1;
Method	scala/Function1$class.compose:(Lscala/Function1;Lscala/Function1;)Lscala/Function1;
Asciz	(Lscala/Function1;)Ljava/lang/String;;
NameAndType	toString:(Lscala/Function1;)Ljava/lang/String;
Method	scala/Function1$class.toString:(Lscala/Function1;)Ljava/lang/String;
Asciz	Scala;
Asciz	InnerClasses;
Asciz	scala/util/automata/WordBerrySethi;
class	scala/util/automata/WordBerrySethi
Asciz	$anonfun$collectTransitions$2;
Asciz	$anonfun$apply$1;
Asciz	scala/Function1;
class	scala/Function1
Asciz	scala/ScalaObject;
class	scala/ScalaObject
Asciz	java/io/Serializable;
class	java/io/Serializable

{
public static final long serialVersionUID;
  Signature: J

public final scala.util.automata.WordBerrySethi $outer;
  Signature: Lscala/util/automata/WordBerrySethi;

public static {};
  Signature: ()V
  Code:
   Stack=2, Locals=0, Args_size=0
	lconst_0
	putstatic	Field serialVersionUID:J
	return
  Labels:

public scala.util.automata.WordBerrySethi$$anonfun$collectTransitions$2(scala.util.automata.WordBerrySethi);
  Signature: (Lscala/util/automata/WordBerrySethi;)V
  Code:
   Stack=2, Locals=2, Args_size=2
	aload_1
	ifnonnull	l1 // aload_0
	new	class java/lang/NullPointerException
	dup
	invokespecial	Method java/lang/NullPointerException."<init>":()V
	athrow
l1	aload_0
	aload_1
	putfield	Field $outer:Lscala/util/automata/WordBerrySethi;
	aload_0
	invokespecial	Method java/lang/Object."<init>":()V
	aload_0
	invokestatic	Method scala/Function1$class.$init$:(Lscala/Function1;)V
	return
  Labels:
   	l1 = 12 // aload_0
  LocalVariableTable: 
   Start  Length  Slot  Name   Signature
   0      26      0    this       Lscala/util/automata/WordBerrySethi$$anonfun$collectTransitions$2;
   0      26      1    $outer       Lscala/util/automata/WordBerrySethi;


public final java.lang.Object apply(java.lang.Object);
  Signature: (Ljava/lang/Object;)Ljava/lang/Object;
  Code:
   Stack=2, Locals=3, Args_size=2
	aload_0
	getfield	Field $outer:Lscala/util/automata/WordBerrySethi;
	astore_2
	aload_0
	aload_1
	checkcast	class scala/Tuple2
	invokevirtual	Method apply:(Lscala/Tuple2;)V
	getstatic	Field scala/runtime/BoxedUnit.UNIT:Lscala/runtime/BoxedUnit;
	areturn
  Labels:
  LocalVariableTable: 
   Start  Length  Slot  Name   Signature
   0      17      0    this       Lscala/util/automata/WordBerrySethi$$anonfun$collectTransitions$2;
   5      12      1    v1       Ljava/lang/Object;


public scala.util.automata.WordBerrySethi scala$util$automata$WordBerrySethi$$anonfun$$$outer();
  Signature: ()Lscala/util/automata/WordBerrySethi;
  Code:
   Stack=1, Locals=1, Args_size=1
	aload_0
	getfield	Field $outer:Lscala/util/automata/WordBerrySethi;
	areturn
  Labels:

public final void apply(scala.Tuple2);
  Signature: (Lscala/Tuple2;)V
  Code:
   Stack=5, Locals=5, Args_size=2
	aload_0
	getfield	Field $outer:Lscala/util/automata/WordBerrySethi;
	astore	4
	aload_1
	ifnull	l1 // new
	aload_1
	invokevirtual	Method scala/Tuple2._1:()Ljava/lang/Object;
	invokestatic	Method scala/runtime/BoxesRunTime.unboxToInt:(Ljava/lang/Object;)I
	istore_3
	aload_1
	invokevirtual	Method scala/Tuple2._2:()Ljava/lang/Object;
	checkcast	class scala/collection/immutable/Set
	astore_2
	iconst_1
	ifeq	l2 // new
	aload_2
	new	class scala/util/automata/WordBerrySethi$$anonfun$collectTransitions$2$$anonfun$apply$1
	dup
	aload_0
	iload_3
	invokespecial	Method scala/util/automata/WordBerrySethi$$anonfun$collectTransitions$2$$anonfun$apply$1."<init>":(Lscala/util/automata/WordBerrySethi$$anonfun$collectTransitions$2;I)V
	invokeinterface	InterfaceMethod scala/collection/IterableLike.foreach:(Lscala/Function1;)V
	return
l2	new	class scala/MatchError
	dup
	aload_1
	invokevirtual	Method scala/Tuple2.toString:()Ljava/lang/String;
	invokespecial	Method scala/MatchError."<init>":(Ljava/lang/String;)V
	athrow
l1	new	class scala/MatchError
	dup
	aload_1
	invokevirtual	Method scala/Tuple2.toString:()Ljava/lang/String;
	invokespecial	Method scala/MatchError."<init>":(Ljava/lang/String;)V
	athrow
  Labels:
   	l2 = 46 // new
   	l1 = 58 // new
  LocalVariableTable: 
   Start  Length  Slot  Name   Signature
   0      70      0    this       Lscala/util/automata/WordBerrySethi$$anonfun$collectTransitions$2;
   26      32      2    temp15       Lscala/collection/immutable/Set;
   18      40      3    temp14       I

  Signature: length = 0x2
   00 5A 

public scala.Function1 andThen(scala.Function1);
  Signature: (Lscala/Function1;)Lscala/Function1;
  Code:
   Stack=2, Locals=2, Args_size=2
	aload_0
	aload_1
	invokestatic	Method scala/Function1$class.andThen:(Lscala/Function1;Lscala/Function1;)Lscala/Function1;
	areturn
  Labels:
  LocalVariableTable: 
   Start  Length  Slot  Name   Signature
   0      6      0    this       Lscala/util/automata/WordBerrySethi$$anonfun$collectTransitions$2;
   0      6      1    g       Lscala/Function1;


public scala.Function1 compose(scala.Function1);
  Signature: (Lscala/Function1;)Lscala/Function1;
  Code:
   Stack=2, Locals=2, Args_size=2
	aload_0
	aload_1
	invokestatic	Method scala/Function1$class.compose:(Lscala/Function1;Lscala/Function1;)Lscala/Function1;
	areturn
  Labels:
  LocalVariableTable: 
   Start  Length  Slot  Name   Signature
   0      6      0    this       Lscala/util/automata/WordBerrySethi$$anonfun$collectTransitions$2;
   0      6      1    g       Lscala/Function1;


public java.lang.String toString();
  Signature: ()Ljava/lang/String;
  Code:
   Stack=1, Locals=1, Args_size=1
	aload_0
	invokestatic	Method scala/Function1$class.toString:(Lscala/Function1;)Ljava/lang/String;
	areturn
  Labels:

}

