Compiled from "WordBerrySethi.scala"
public final class scala.util.automata.WordBerrySethi$$anonfun$3 extends java.lang.Object implements scala.Function1,scala.ScalaObject,java.io.Serializable
  SourceFile: "WordBerrySethi.scala"
  Scala: length = 0x
   
  InnerClass: 
   public final #115= #9 of #114; //$anonfun$3=class scala/util/automata/WordBerrySethi$$anonfun$3 of class scala/util/automata/WordBerrySethi
   public final #116= #68 of #9; //$anonfun$apply$3=class scala/util/automata/WordBerrySethi$$anonfun$3$$anonfun$apply$3 of class scala/util/automata/WordBerrySethi$$anonfun$3
  minor version: 0
  major version: 49
  Constant pool:
const #1 = Asciz	SourceFile;
const #2 = Asciz	WordBerrySethi.scala;
const #3 = Asciz	<clinit>;
const #4 = Asciz	()V;
const #5 = Asciz	Code;
const #6 = Asciz	serialVersionUID;
const #7 = Asciz	J;
const #8 = Asciz	scala/util/automata/WordBerrySethi$$anonfun$3;
const #9 = class	#8;	//  scala/util/automata/WordBerrySethi$$anonfun$3
const #10 = NameAndType	#6:#7;//  serialVersionUID:J
const #11 = Field	#9.#10;	//  scala/util/automata/WordBerrySethi$$anonfun$3.serialVersionUID:J
const #12 = Asciz	delta1$1;
const #13 = Asciz	Lscala/collection/immutable/Map;;
const #14 = Asciz	<init>;
const #15 = Asciz	(Lscala/util/automata/WordBerrySethi;Lscala/collection/immutable/Map;)V;
const #16 = Asciz	LineNumberTable;
const #17 = NameAndType	#12:#13;//  delta1$1:Lscala/collection/immutable/Map;
const #18 = Field	#9.#17;	//  scala/util/automata/WordBerrySethi$$anonfun$3.delta1$1:Lscala/collection/immutable/Map;
const #19 = Asciz	java/lang/Object;
const #20 = class	#19;	//  java/lang/Object
const #21 = NameAndType	#14:#4;//  "<init>":()V
const #22 = Method	#20.#21;	//  java/lang/Object."<init>":()V
const #23 = Asciz	scala/Function1$class;
const #24 = class	#23;	//  scala/Function1$class
const #25 = Asciz	$init$;
const #26 = Asciz	(Lscala/Function1;)V;
const #27 = NameAndType	#25:#26;//  $init$:(Lscala/Function1;)V
const #28 = Method	#24.#27;	//  scala/Function1$class.$init$:(Lscala/Function1;)V
const #29 = Asciz	this;
const #30 = Asciz	Lscala/util/automata/WordBerrySethi$$anonfun$3;;
const #31 = Asciz	$outer;
const #32 = Asciz	Lscala/util/automata/WordBerrySethi;;
const #33 = Asciz	LocalVariableTable;
const #34 = Asciz	apply;
const #35 = Asciz	(Ljava/lang/Object;)Ljava/lang/Object;;
const #36 = Asciz	scala/runtime/BoxesRunTime;
const #37 = class	#36;	//  scala/runtime/BoxesRunTime
const #38 = Asciz	unboxToInt;
const #39 = Asciz	(Ljava/lang/Object;)I;
const #40 = NameAndType	#38:#39;//  unboxToInt:(Ljava/lang/Object;)I
const #41 = Method	#37.#40;	//  scala/runtime/BoxesRunTime.unboxToInt:(Ljava/lang/Object;)I
const #42 = Asciz	(I)Lscala/collection/mutable/HashMap;;
const #43 = NameAndType	#34:#42;//  apply:(I)Lscala/collection/mutable/HashMap;
const #44 = Method	#9.#43;	//  scala/util/automata/WordBerrySethi$$anonfun$3.apply:(I)Lscala/collection/mutable/HashMap;
const #45 = Asciz	v1;
const #46 = Asciz	Ljava/lang/Object;;
const #47 = Asciz	scala/collection/mutable/HashMap$;
const #48 = class	#47;	//  scala/collection/mutable/HashMap$
const #49 = Asciz	MODULE$;
const #50 = Asciz	Lscala/collection/mutable/HashMap$;;
const #51 = NameAndType	#49:#50;//  MODULE$:Lscala/collection/mutable/HashMap$;
const #52 = Field	#48.#51;	//  scala/collection/mutable/HashMap$.MODULE$:Lscala/collection/mutable/HashMap$;
const #53 = Asciz	boxToInteger;
const #54 = Asciz	(I)Ljava/lang/Integer;;
const #55 = NameAndType	#53:#54;//  boxToInteger:(I)Ljava/lang/Integer;
const #56 = Method	#37.#55;	//  scala/runtime/BoxesRunTime.boxToInteger:(I)Ljava/lang/Integer;
const #57 = Asciz	scala/collection/MapLike;
const #58 = class	#57;	//  scala/collection/MapLike
const #59 = NameAndType	#34:#35;//  apply:(Ljava/lang/Object;)Ljava/lang/Object;
const #60 = InterfaceMethod	#58.#59;	//  scala/collection/MapLike.apply:(Ljava/lang/Object;)Ljava/lang/Object;
const #61 = Asciz	scala/collection/TraversableLike;
const #62 = class	#61;	//  scala/collection/TraversableLike
const #63 = Asciz	toSeq;
const #64 = Asciz	()Lscala/collection/Seq;;
const #65 = NameAndType	#63:#64;//  toSeq:()Lscala/collection/Seq;
const #66 = InterfaceMethod	#62.#65;	//  scala/collection/TraversableLike.toSeq:()Lscala/collection/Seq;
const #67 = Asciz	scala/util/automata/WordBerrySethi$$anonfun$3$$anonfun$apply$3;
const #68 = class	#67;	//  scala/util/automata/WordBerrySethi$$anonfun$3$$anonfun$apply$3
const #69 = Asciz	(Lscala/util/automata/WordBerrySethi$$anonfun$3;)V;
const #70 = NameAndType	#14:#69;//  "<init>":(Lscala/util/automata/WordBerrySethi$$anonfun$3;)V
const #71 = Method	#68.#70;	//  scala/util/automata/WordBerrySethi$$anonfun$3$$anonfun$apply$3."<init>":(Lscala/util/automata/WordBerrySethi$$anonfun$3;)V
const #72 = Asciz	scala/collection/Seq$;
const #73 = class	#72;	//  scala/collection/Seq$
const #74 = Asciz	Lscala/collection/Seq$;;
const #75 = NameAndType	#49:#74;//  MODULE$:Lscala/collection/Seq$;
const #76 = Field	#73.#75;	//  scala/collection/Seq$.MODULE$:Lscala/collection/Seq$;
const #77 = Asciz	canBuildFrom;
const #78 = Asciz	()Lscala/collection/generic/CanBuildFrom;;
const #79 = NameAndType	#77:#78;//  canBuildFrom:()Lscala/collection/generic/CanBuildFrom;
const #80 = Method	#73.#79;	//  scala/collection/Seq$.canBuildFrom:()Lscala/collection/generic/CanBuildFrom;
const #81 = Asciz	map;
const #82 = Asciz	(Lscala/Function1;Lscala/collection/generic/CanBuildFrom;)Ljava/lang/Object;;
const #83 = NameAndType	#81:#82;//  map:(Lscala/Function1;Lscala/collection/generic/CanBuildFrom;)Ljava/lang/Object;
const #84 = InterfaceMethod	#62.#83;	//  scala/collection/TraversableLike.map:(Lscala/Function1;Lscala/collection/generic/CanBuildFrom;)Ljava/lang/Object;
const #85 = Asciz	scala/collection/Seq;
const #86 = class	#85;	//  scala/collection/Seq
const #87 = Asciz	(Lscala/collection/Seq;)Lscala/collection/Map;;
const #88 = NameAndType	#34:#87;//  apply:(Lscala/collection/Seq;)Lscala/collection/Map;
const #89 = Method	#48.#88;	//  scala/collection/mutable/HashMap$.apply:(Lscala/collection/Seq;)Lscala/collection/Map;
const #90 = Asciz	scala/collection/mutable/HashMap;
const #91 = class	#90;	//  scala/collection/mutable/HashMap
const #92 = Asciz	x;
const #93 = Asciz	I;
const #94 = Asciz	(I)Lscala/collection/mutable/HashMap<Lscala/util/regexp/WordExp$Label;Lscala/collection/immutable/BitSet;>;;
const #95 = Asciz	Signature;
const #96 = Asciz	andThen;
const #97 = Asciz	(Lscala/Function1;)Lscala/Function1;;
const #98 = Asciz	(Lscala/Function1;Lscala/Function1;)Lscala/Function1;;
const #99 = NameAndType	#96:#98;//  andThen:(Lscala/Function1;Lscala/Function1;)Lscala/Function1;
const #100 = Method	#24.#99;	//  scala/Function1$class.andThen:(Lscala/Function1;Lscala/Function1;)Lscala/Function1;
const #101 = Asciz	g;
const #102 = Asciz	Lscala/Function1;;
const #103 = Asciz	compose;
const #104 = NameAndType	#103:#98;//  compose:(Lscala/Function1;Lscala/Function1;)Lscala/Function1;
const #105 = Method	#24.#104;	//  scala/Function1$class.compose:(Lscala/Function1;Lscala/Function1;)Lscala/Function1;
const #106 = Asciz	toString;
const #107 = Asciz	()Ljava/lang/String;;
const #108 = Asciz	(Lscala/Function1;)Ljava/lang/String;;
const #109 = NameAndType	#106:#108;//  toString:(Lscala/Function1;)Ljava/lang/String;
const #110 = Method	#24.#109;	//  scala/Function1$class.toString:(Lscala/Function1;)Ljava/lang/String;
const #111 = Asciz	Scala;
const #112 = Asciz	InnerClasses;
const #113 = Asciz	scala/util/automata/WordBerrySethi;
const #114 = class	#113;	//  scala/util/automata/WordBerrySethi
const #115 = Asciz	$anonfun$3;
const #116 = Asciz	$anonfun$apply$3;
const #117 = Asciz	scala/Function1;
const #118 = class	#117;	//  scala/Function1
const #119 = Asciz	scala/ScalaObject;
const #120 = class	#119;	//  scala/ScalaObject
const #121 = Asciz	java/io/Serializable;
const #122 = class	#121;	//  java/io/Serializable

{
public static final long serialVersionUID;

public static {};
  Code:
   Stack=2, Locals=0, Args_size=0
   0:	lconst_0
   1:	putstatic	#11; //Field serialVersionUID:J
   4:	return

public scala.util.automata.WordBerrySethi$$anonfun$3(scala.util.automata.WordBerrySethi, scala.collection.immutable.Map);
  Code:
   Stack=2, Locals=3, Args_size=3
   0:	aload_0
   1:	aload_2
   2:	putfield	#18; //Field delta1$1:Lscala/collection/immutable/Map;
   5:	aload_0
   6:	invokespecial	#22; //Method java/lang/Object."<init>":()V
   9:	aload_0
   10:	invokestatic	#28; //Method scala/Function1$class.$init$:(Lscala/Function1;)V
   13:	return
  LineNumberTable: 
   line 155: 0

  LocalVariableTable: 
   Start  Length  Slot  Name   Signature
   0      14      0    this       Lscala/util/automata/WordBerrySethi$$anonfun$3;
   0      14      1    $outer       Lscala/util/automata/WordBerrySethi;


public final java.lang.Object apply(java.lang.Object);
  Code:
   Stack=2, Locals=2, Args_size=2
   0:	aload_0
   1:	aload_1
   2:	invokestatic	#41; //Method scala/runtime/BoxesRunTime.unboxToInt:(Ljava/lang/Object;)I
   5:	invokevirtual	#44; //Method apply:(I)Lscala/collection/mutable/HashMap;
   8:	areturn
  LineNumberTable: 
   line 155: 0

  LocalVariableTable: 
   Start  Length  Slot  Name   Signature
   0      9      0    this       Lscala/util/automata/WordBerrySethi$$anonfun$3;
   0      9      1    v1       Ljava/lang/Object;


public final scala.collection.mutable.HashMap apply(int);
  Code:
   Stack=5, Locals=2, Args_size=2
   0:	getstatic	#52; //Field scala/collection/mutable/HashMap$.MODULE$:Lscala/collection/mutable/HashMap$;
   3:	aload_0
   4:	getfield	#18; //Field delta1$1:Lscala/collection/immutable/Map;
   7:	iload_1
   8:	invokestatic	#56; //Method scala/runtime/BoxesRunTime.boxToInteger:(I)Ljava/lang/Integer;
   11:	invokeinterface	#60,  2; //InterfaceMethod scala/collection/MapLike.apply:(Ljava/lang/Object;)Ljava/lang/Object;
   16:	checkcast	#62; //class scala/collection/TraversableLike
   19:	invokeinterface	#66,  1; //InterfaceMethod scala/collection/TraversableLike.toSeq:()Lscala/collection/Seq;
   24:	new	#68; //class scala/util/automata/WordBerrySethi$$anonfun$3$$anonfun$apply$3
   27:	dup
   28:	aload_0
   29:	invokespecial	#71; //Method scala/util/automata/WordBerrySethi$$anonfun$3$$anonfun$apply$3."<init>":(Lscala/util/automata/WordBerrySethi$$anonfun$3;)V
   32:	getstatic	#76; //Field scala/collection/Seq$.MODULE$:Lscala/collection/Seq$;
   35:	invokevirtual	#80; //Method scala/collection/Seq$.canBuildFrom:()Lscala/collection/generic/CanBuildFrom;
   38:	invokeinterface	#84,  3; //InterfaceMethod scala/collection/TraversableLike.map:(Lscala/Function1;Lscala/collection/generic/CanBuildFrom;)Ljava/lang/Object;
   43:	checkcast	#86; //class scala/collection/Seq
   46:	invokevirtual	#89; //Method scala/collection/mutable/HashMap$.apply:(Lscala/collection/Seq;)Lscala/collection/Map;
   49:	checkcast	#91; //class scala/collection/mutable/HashMap
   52:	areturn
  LineNumberTable: 
   line 156: 0

  LocalVariableTable: 
   Start  Length  Slot  Name   Signature
   0      53      0    this       Lscala/util/automata/WordBerrySethi$$anonfun$3;
   0      53      1    x       I

  Signature: length = 0x2
   00 5E 

public scala.Function1 andThen(scala.Function1);
  Code:
   Stack=2, Locals=2, Args_size=2
   0:	aload_0
   1:	aload_1
   2:	invokestatic	#100; //Method scala/Function1$class.andThen:(Lscala/Function1;Lscala/Function1;)Lscala/Function1;
   5:	areturn
  LineNumberTable: 
   line 155: 0

  LocalVariableTable: 
   Start  Length  Slot  Name   Signature
   0      6      0    this       Lscala/util/automata/WordBerrySethi$$anonfun$3;
   0      6      1    g       Lscala/Function1;


public scala.Function1 compose(scala.Function1);
  Code:
   Stack=2, Locals=2, Args_size=2
   0:	aload_0
   1:	aload_1
   2:	invokestatic	#105; //Method scala/Function1$class.compose:(Lscala/Function1;Lscala/Function1;)Lscala/Function1;
   5:	areturn
  LineNumberTable: 
   line 155: 0

  LocalVariableTable: 
   Start  Length  Slot  Name   Signature
   0      6      0    this       Lscala/util/automata/WordBerrySethi$$anonfun$3;
   0      6      1    g       Lscala/Function1;


public java.lang.String toString();
  Code:
   Stack=1, Locals=1, Args_size=1
   0:	aload_0
   1:	invokestatic	#110; //Method scala/Function1$class.toString:(Lscala/Function1;)Ljava/lang/String;
   4:	areturn
  LineNumberTable: 
   line 155: 0


}

