Compiled from "WordBerrySethi.scala"
public final class scala.util.automata.WordBerrySethi$$anonfun$initializeAutom$1 extends java.lang.Object implements scala.Function1,scala.ScalaObject,java.io.Serializable
  SourceFile: "WordBerrySethi.scala"
  Scala: length = 0x
   
  InnerClass: 
   public final $anonfun$initializeAutom$1=class scala/util/automata/WordBerrySethi$$anonfun$initializeAutom$1 of class scala/util/automata/WordBerrySethi
  minor version: 0
  major version: 49
  Constant pool:
Asciz	SourceFile;
Asciz	WordBerrySethi.scala;
Asciz	<clinit>;
Asciz	()V;
Asciz	Code;
Asciz	serialVersionUID;
Asciz	J;
Asciz	scala/util/automata/WordBerrySethi$$anonfun$initializeAutom$1;
class	scala/util/automata/WordBerrySethi$$anonfun$initializeAutom$1
NameAndType	serialVersionUID:J
Field	scala/util/automata/WordBerrySethi$$anonfun$initializeAutom$1.serialVersionUID:J
Asciz	$outer;
Asciz	Lscala/util/automata/WordBerrySethi;;
Asciz	<init>;
Asciz	(Lscala/util/automata/WordBerrySethi;)V;
Asciz	LineNumberTable;
Asciz	java/lang/NullPointerException;
class	java/lang/NullPointerException
NameAndType	"<init>":()V
Method	java/lang/NullPointerException."<init>":()V
NameAndType	$outer:Lscala/util/automata/WordBerrySethi;
Field	scala/util/automata/WordBerrySethi$$anonfun$initializeAutom$1.$outer:Lscala/util/automata/WordBerrySethi;
Asciz	java/lang/Object;
class	java/lang/Object
Method	java/lang/Object."<init>":()V
Asciz	scala/Function1$class;
class	scala/Function1$class
Asciz	$init$;
Asciz	(Lscala/Function1;)V;
NameAndType	$init$:(Lscala/Function1;)V
Method	scala/Function1$class.$init$:(Lscala/Function1;)V
Asciz	this;
Asciz	Lscala/util/automata/WordBerrySethi$$anonfun$initializeAutom$1;;
Asciz	LocalVariableTable;
Asciz	apply;
Asciz	(Ljava/lang/Object;)Ljava/lang/Object;;
Asciz	scala/runtime/BoxesRunTime;
class	scala/runtime/BoxesRunTime
Asciz	unboxToInt;
Asciz	(Ljava/lang/Object;)I;
NameAndType	unboxToInt:(Ljava/lang/Object;)I
Method	scala/runtime/BoxesRunTime.unboxToInt:(Ljava/lang/Object;)I
Asciz	(I)V;
NameAndType	apply:(I)V
Method	scala/util/automata/WordBerrySethi$$anonfun$initializeAutom$1.apply:(I)V
Asciz	scala/runtime/BoxedUnit;
class	scala/runtime/BoxedUnit
Asciz	UNIT;
Asciz	Lscala/runtime/BoxedUnit;;
NameAndType	UNIT:Lscala/runtime/BoxedUnit;
Field	scala/runtime/BoxedUnit.UNIT:Lscala/runtime/BoxedUnit;
Asciz	v1;
Asciz	Ljava/lang/Object;;
Asciz	scala/util/automata/WordBerrySethi;
class	scala/util/automata/WordBerrySethi
Asciz	deltaq;
Asciz	()[Lscala/collection/mutable/HashMap;;
NameAndType	deltaq:()[Lscala/collection/mutable/HashMap;
Method	scala/util/automata/WordBerrySethi.deltaq:()[Lscala/collection/mutable/HashMap;
Asciz	scala/collection/mutable/HashMap$;
class	scala/collection/mutable/HashMap$
Asciz	MODULE$;
Asciz	Lscala/collection/mutable/HashMap$;;
NameAndType	MODULE$:Lscala/collection/mutable/HashMap$;
Field	scala/collection/mutable/HashMap$.MODULE$:Lscala/collection/mutable/HashMap$;
Asciz	scala/Predef$;
class	scala/Predef$
Asciz	Lscala/Predef$;;
NameAndType	MODULE$:Lscala/Predef$;
Field	scala/Predef$.MODULE$:Lscala/Predef$;
Asciz	scala/Tuple2;
class	scala/Tuple2
Asciz	[Ljava/lang/Object;;
class	"[Ljava/lang/Object;"
Asciz	wrapRefArray;
Asciz	([Ljava/lang/Object;)Lscala/collection/mutable/WrappedArray;;
NameAndType	wrapRefArray:([Ljava/lang/Object;)Lscala/collection/mutable/WrappedArray;
Method	scala/Predef$.wrapRefArray:([Ljava/lang/Object;)Lscala/collection/mutable/WrappedArray;
Asciz	(Lscala/collection/Seq;)Lscala/collection/Map;;
NameAndType	apply:(Lscala/collection/Seq;)Lscala/collection/Map;
Method	scala/collection/mutable/HashMap$.apply:(Lscala/collection/Seq;)Lscala/collection/Map;
Asciz	scala/collection/mutable/HashMap;
class	scala/collection/mutable/HashMap
Asciz	defaultq;
Asciz	()[Lscala/collection/immutable/List;;
NameAndType	defaultq:()[Lscala/collection/immutable/List;
Method	scala/util/automata/WordBerrySethi.defaultq:()[Lscala/collection/immutable/List;
Asciz	scala/collection/immutable/Nil$;
class	scala/collection/immutable/Nil$
Asciz	Lscala/collection/immutable/Nil$;;
NameAndType	MODULE$:Lscala/collection/immutable/Nil$;
Field	scala/collection/immutable/Nil$.MODULE$:Lscala/collection/immutable/Nil$;
Asciz	j;
Asciz	I;
Asciz	andThen;
Asciz	(Lscala/Function1;)Lscala/Function1;;
Asciz	(Lscala/Function1;Lscala/Function1;)Lscala/Function1;;
NameAndType	andThen:(Lscala/Function1;Lscala/Function1;)Lscala/Function1;
Method	scala/Function1$class.andThen:(Lscala/Function1;Lscala/Function1;)Lscala/Function1;
Asciz	g;
Asciz	Lscala/Function1;;
Asciz	compose;
NameAndType	compose:(Lscala/Function1;Lscala/Function1;)Lscala/Function1;
Method	scala/Function1$class.compose:(Lscala/Function1;Lscala/Function1;)Lscala/Function1;
Asciz	toString;
Asciz	()Ljava/lang/String;;
Asciz	(Lscala/Function1;)Ljava/lang/String;;
NameAndType	toString:(Lscala/Function1;)Ljava/lang/String;
Method	scala/Function1$class.toString:(Lscala/Function1;)Ljava/lang/String;
Asciz	Scala;
Asciz	InnerClasses;
Asciz	$anonfun$initializeAutom$1;
Asciz	scala/Function1;
class	scala/Function1
Asciz	scala/ScalaObject;
class	scala/ScalaObject
Asciz	java/io/Serializable;
class	java/io/Serializable

{
public static final long serialVersionUID;
  Signature: J

private final scala.util.automata.WordBerrySethi $outer;
  Signature: Lscala/util/automata/WordBerrySethi;

public static {};
  Signature: ()V
  Code:
   Stack=2, Locals=0, Args_size=0
	lconst_0
	putstatic	Field serialVersionUID:J
	return
  Labels:

public scala.util.automata.WordBerrySethi$$anonfun$initializeAutom$1(scala.util.automata.WordBerrySethi);
  Signature: (Lscala/util/automata/WordBerrySethi;)V
  Code:
   Stack=2, Locals=2, Args_size=2
	aload_1
	ifnonnull	l1 // aload_0
	new	class java/lang/NullPointerException
	dup
	invokespecial	Method java/lang/NullPointerException."<init>":()V
	athrow
l1	aload_0
	aload_1
	putfield	Field $outer:Lscala/util/automata/WordBerrySethi;
	aload_0
	invokespecial	Method java/lang/Object."<init>":()V
	aload_0
	invokestatic	Method scala/Function1$class.$init$:(Lscala/Function1;)V
	return
  Labels:
   	l1 = 12 // aload_0
  LocalVariableTable: 
   Start  Length  Slot  Name   Signature
   0      26      0    this       Lscala/util/automata/WordBerrySethi$$anonfun$initializeAutom$1;
   0      26      1    $outer       Lscala/util/automata/WordBerrySethi;


public final java.lang.Object apply(java.lang.Object);
  Signature: (Ljava/lang/Object;)Ljava/lang/Object;
  Code:
   Stack=2, Locals=3, Args_size=2
	aload_0
	getfield	Field $outer:Lscala/util/automata/WordBerrySethi;
	astore_2
	aload_0
	aload_1
	invokestatic	Method scala/runtime/BoxesRunTime.unboxToInt:(Ljava/lang/Object;)I
	invokevirtual	Method apply:(I)V
	getstatic	Field scala/runtime/BoxedUnit.UNIT:Lscala/runtime/BoxedUnit;
	areturn
  Labels:
  LocalVariableTable: 
   Start  Length  Slot  Name   Signature
   0      17      0    this       Lscala/util/automata/WordBerrySethi$$anonfun$initializeAutom$1;
   5      12      1    v1       Ljava/lang/Object;


public final void apply(int);
  Signature: (I)V
  Code:
   Stack=5, Locals=3, Args_size=2
	aload_0
	getfield	Field $outer:Lscala/util/automata/WordBerrySethi;
	astore_2
	aload_0
	getfield	Field $outer:Lscala/util/automata/WordBerrySethi;
	invokevirtual	Method scala/util/automata/WordBerrySethi.deltaq:()[Lscala/collection/mutable/HashMap;
	iload_1
	getstatic	Field scala/collection/mutable/HashMap$.MODULE$:Lscala/collection/mutable/HashMap$;
	getstatic	Field scala/Predef$.MODULE$:Lscala/Predef$;
	iconst_0
	anewarray	class scala/Tuple2
	checkcast	class "[Ljava/lang/Object;"
	invokevirtual	Method scala/Predef$.wrapRefArray:([Ljava/lang/Object;)Lscala/collection/mutable/WrappedArray;
	invokevirtual	Method scala/collection/mutable/HashMap$.apply:(Lscala/collection/Seq;)Lscala/collection/Map;
	checkcast	class scala/collection/mutable/HashMap
	aastore
	aload_0
	getfield	Field $outer:Lscala/util/automata/WordBerrySethi;
	invokevirtual	Method scala/util/automata/WordBerrySethi.defaultq:()[Lscala/collection/immutable/List;
	iload_1
	getstatic	Field scala/collection/immutable/Nil$.MODULE$:Lscala/collection/immutable/Nil$;
	aastore
	return
  Labels:
  LocalVariableTable: 
   Start  Length  Slot  Name   Signature
   0      49      0    this       Lscala/util/automata/WordBerrySethi$$anonfun$initializeAutom$1;
   5      44      1    j       I


public scala.Function1 andThen(scala.Function1);
  Signature: (Lscala/Function1;)Lscala/Function1;
  Code:
   Stack=2, Locals=2, Args_size=2
	aload_0
	aload_1
	invokestatic	Method scala/Function1$class.andThen:(Lscala/Function1;Lscala/Function1;)Lscala/Function1;
	areturn
  Labels:
  LocalVariableTable: 
   Start  Length  Slot  Name   Signature
   0      6      0    this       Lscala/util/automata/WordBerrySethi$$anonfun$initializeAutom$1;
   0      6      1    g       Lscala/Function1;


public scala.Function1 compose(scala.Function1);
  Signature: (Lscala/Function1;)Lscala/Function1;
  Code:
   Stack=2, Locals=2, Args_size=2
	aload_0
	aload_1
	invokestatic	Method scala/Function1$class.compose:(Lscala/Function1;Lscala/Function1;)Lscala/Function1;
	areturn
  Labels:
  LocalVariableTable: 
   Start  Length  Slot  Name   Signature
   0      6      0    this       Lscala/util/automata/WordBerrySethi$$anonfun$initializeAutom$1;
   0      6      1    g       Lscala/Function1;


public java.lang.String toString();
  Signature: ()Ljava/lang/String;
  Code:
   Stack=1, Locals=1, Args_size=1
	aload_0
	invokestatic	Method scala/Function1$class.toString:(Lscala/Function1;)Ljava/lang/String;
	areturn
  Labels:

}

