Compiled from "WordBerrySethi.scala"
public final class scala.util.automata.WordBerrySethi$$anonfun$3$$anonfun$apply$3 extends scala.runtime.AbstractFunction1 implements java.io.Serializable
  SourceFile: "WordBerrySethi.scala"
  Scala: length = 0x
   
  InnerClass: 
   public abstract Label=class scala/util/regexp/WordExp$Label of class scala/util/regexp/WordExp
   public final ArrowAssoc=class scala/Predef$ArrowAssoc of class scala/Predef
   public final $anonfun$3=class scala/util/automata/WordBerrySethi$$anonfun$3 of class scala/util/automata/WordBerrySethi
   public final $anonfun$apply$3=class scala/util/automata/WordBerrySethi$$anonfun$3$$anonfun$apply$3 of class scala/util/automata/WordBerrySethi$$anonfun$3
  minor version: 0
  major version: 49
  Constant pool:
Asciz	SourceFile;
Asciz	WordBerrySethi.scala;
Asciz	<clinit>;
Asciz	()V;
Asciz	Code;
Asciz	serialVersionUID;
Asciz	J;
Asciz	scala/util/automata/WordBerrySethi$$anonfun$3$$anonfun$apply$3;
class	scala/util/automata/WordBerrySethi$$anonfun$3$$anonfun$apply$3
NameAndType	serialVersionUID:J
Field	scala/util/automata/WordBerrySethi$$anonfun$3$$anonfun$apply$3.serialVersionUID:J
Asciz	apply;
Asciz	(Lscala/Tuple2;)Lscala/Tuple2;;
Asciz	LineNumberTable;
Asciz	scala/Tuple2;
class	scala/Tuple2
Asciz	_1;
Asciz	()Ljava/lang/Object;;
NameAndType	_1:()Ljava/lang/Object;
Method	scala/Tuple2._1:()Ljava/lang/Object;
Asciz	scala/util/regexp/WordExp$Label;
class	scala/util/regexp/WordExp$Label
Asciz	_2;
NameAndType	_2:()Ljava/lang/Object;
Method	scala/Tuple2._2:()Ljava/lang/Object;
Asciz	scala/collection/immutable/List;
class	scala/collection/immutable/List
Asciz	scala/Predef$ArrowAssoc;
class	scala/Predef$ArrowAssoc
Asciz	<init>;
Asciz	(Ljava/lang/Object;)V;
NameAndType	"<init>":(Ljava/lang/Object;)V
Method	scala/Predef$ArrowAssoc."<init>":(Ljava/lang/Object;)V
Asciz	scala/collection/immutable/BitSet$;
class	scala/collection/immutable/BitSet$
Asciz	MODULE$;
Asciz	Lscala/collection/immutable/BitSet$;;
NameAndType	MODULE$:Lscala/collection/immutable/BitSet$;
Field	scala/collection/immutable/BitSet$.MODULE$:Lscala/collection/immutable/BitSet$;
Asciz	scala/collection/generic/BitSetFactory$class;
class	scala/collection/generic/BitSetFactory$class
Asciz	(Lscala/collection/generic/BitSetFactory;Lscala/collection/Seq;)Lscala/collection/BitSet;;
NameAndType	apply:(Lscala/collection/generic/BitSetFactory;Lscala/collection/Seq;)Lscala/collection/BitSet;
Method	scala/collection/generic/BitSetFactory$class.apply:(Lscala/collection/generic/BitSetFactory;Lscala/collection/Seq;)Lscala/collection/BitSet;
Asciz	(Ljava/lang/Object;Ljava/lang/Object;)V;
NameAndType	"<init>":(Ljava/lang/Object;Ljava/lang/Object;)V
Method	scala/Tuple2."<init>":(Ljava/lang/Object;Ljava/lang/Object;)V
Asciz	scala/MatchError;
class	scala/MatchError
Asciz	toString;
Asciz	()Ljava/lang/String;;
NameAndType	toString:()Ljava/lang/String;
Method	scala/Tuple2.toString:()Ljava/lang/String;
Asciz	(Ljava/lang/String;)V;
NameAndType	"<init>":(Ljava/lang/String;)V
Method	scala/MatchError."<init>":(Ljava/lang/String;)V
Asciz	this;
Asciz	Lscala/util/automata/WordBerrySethi$$anonfun$3$$anonfun$apply$3;;
Asciz	temp18;
Asciz	Lscala/collection/immutable/List;;
Asciz	temp17;
Asciz	Lscala/util/regexp/WordExp$Label;;
Asciz	LocalVariableTable;
Asciz	(Lscala/Tuple2<Lscala/util/regexp/WordExp$Label;Lscala/collection/immutable/List<Ljava/lang/Integer;>;>;)Lscala/Tuple2<Lscala/util/regexp/WordExp$Label;Lscala/collection/immutable/BitSet;>;;
Asciz	Signature;
Asciz	(Ljava/lang/Object;)Ljava/lang/Object;;
NameAndType	apply:(Lscala/Tuple2;)Lscala/Tuple2;
Method	scala/util/automata/WordBerrySethi$$anonfun$3$$anonfun$apply$3.apply:(Lscala/Tuple2;)Lscala/Tuple2;
Asciz	v1;
Asciz	Ljava/lang/Object;;
Asciz	(Lscala/util/automata/WordBerrySethi$$anonfun$3;)V;
Asciz	scala/runtime/AbstractFunction1;
class	scala/runtime/AbstractFunction1
NameAndType	"<init>":()V
Method	scala/runtime/AbstractFunction1."<init>":()V
Asciz	$outer;
Asciz	Lscala/util/automata/WordBerrySethi$$anonfun$3;;
Asciz	Scala;
Asciz	InnerClasses;
Asciz	scala/util/regexp/WordExp;
class	scala/util/regexp/WordExp
Asciz	Label;
Asciz	scala/Predef;
class	scala/Predef
Asciz	ArrowAssoc;
Asciz	scala/util/automata/WordBerrySethi$$anonfun$3;
class	scala/util/automata/WordBerrySethi$$anonfun$3
Asciz	scala/util/automata/WordBerrySethi;
class	scala/util/automata/WordBerrySethi
Asciz	$anonfun$3;
Asciz	$anonfun$apply$3;
Asciz	java/io/Serializable;
class	java/io/Serializable

{
public static final long serialVersionUID;
  Signature: J

public static {};
  Signature: ()V
  Code:
   Stack=2, Locals=0, Args_size=0
	lconst_0
	putstatic	Field serialVersionUID:J
	return
  Labels:

public final scala.Tuple2 apply(scala.Tuple2);
  Signature: (Lscala/Tuple2;)Lscala/Tuple2;
  Code:
   Stack=4, Locals=6, Args_size=2
	aload_1
	ifnull	l1 // new
	aload_1
	invokevirtual	Method scala/Tuple2._1:()Ljava/lang/Object;
	checkcast	class scala/util/regexp/WordExp$Label
	astore	4
	aload_1
	invokevirtual	Method scala/Tuple2._2:()Ljava/lang/Object;
	checkcast	class scala/collection/immutable/List
	astore_3
	new	class scala/Predef$ArrowAssoc
	dup
	aload	4
	invokespecial	Method scala/Predef$ArrowAssoc."<init>":(Ljava/lang/Object;)V
	pop
	getstatic	Field scala/collection/immutable/BitSet$.MODULE$:Lscala/collection/immutable/BitSet$;
	astore_2
	aload_2
	aload_3
	invokestatic	Method scala/collection/generic/BitSetFactory$class.apply:(Lscala/collection/generic/BitSetFactory;Lscala/collection/Seq;)Lscala/collection/BitSet;
	astore	5
	new	class scala/Tuple2
	dup
	aload	4
	aload	5
	invokespecial	Method scala/Tuple2."<init>":(Ljava/lang/Object;Ljava/lang/Object;)V
	areturn
l1	new	class scala/MatchError
	dup
	aload_1
	invokevirtual	Method scala/Tuple2.toString:()Ljava/lang/String;
	invokespecial	Method scala/MatchError."<init>":(Ljava/lang/String;)V
	athrow
  Labels:
   	l1 = 54 // new
  LocalVariableTable: 
   Start  Length  Slot  Name   Signature
   0      66      0    this       Lscala/util/automata/WordBerrySethi$$anonfun$3$$anonfun$apply$3;
   21      32      3    temp18       Lscala/collection/immutable/List;
   13      40      4    temp17       Lscala/util/regexp/WordExp$Label;

  Signature: length = 0x2
   00 40 

public final java.lang.Object apply(java.lang.Object);
  Signature: (Ljava/lang/Object;)Ljava/lang/Object;
  Code:
   Stack=2, Locals=2, Args_size=2
	aload_0
	aload_1
	checkcast	class scala/Tuple2
	invokevirtual	Method apply:(Lscala/Tuple2;)Lscala/Tuple2;
	areturn
  Labels:
  LocalVariableTable: 
   Start  Length  Slot  Name   Signature
   0      9      0    this       Lscala/util/automata/WordBerrySethi$$anonfun$3$$anonfun$apply$3;
   0      9      1    v1       Ljava/lang/Object;


public scala.util.automata.WordBerrySethi$$anonfun$3$$anonfun$apply$3(scala.util.automata.WordBerrySethi$$anonfun$3);
  Signature: (Lscala/util/automata/WordBerrySethi$$anonfun$3;)V
  Code:
   Stack=1, Locals=2, Args_size=2
	aload_0
	invokespecial	Method scala/runtime/AbstractFunction1."<init>":()V
	return
  Labels:
  LocalVariableTable: 
   Start  Length  Slot  Name   Signature
   0      5      0    this       Lscala/util/automata/WordBerrySethi$$anonfun$3$$anonfun$apply$3;
   0      5      1    $outer       Lscala/util/automata/WordBerrySethi$$anonfun$3;


}

