Compiled from "WordBerrySethi.scala"
public abstract class scala.util.automata.WordBerrySethi extends scala.util.automata.BaseBerrySethi implements scala.ScalaObject
  SourceFile: "WordBerrySethi.scala"
  ScalaSig: length = 0x56D
   05 00 FFFFFF81 3F 06 08 01 02 FFFFFF84 FFFFFF80 FFFFFF80 FFFFFF81 00 09 02 0E
   57 6F 72 64 42 65 72 72 79 53 65 74 68 69 0A 02
   03 04 01 08 61 75 74 6F 6D 61 74 61 0A 02 05 06
   01 04 75 74 69 6C 0A 01 07 01 05 73 63 61 6C 61
   03 00 13 03 00 0A 0E 10 02 0B 0C 0D 01 02 09 02
   0D 02 02 0E 42 61 73 65 42 65 72 72 79 53 65 74
   68 69 10 02 0F 10 0D 01 06 09 02 11 06 02 0B 53
   63 61 6C 61 4F 62 6A 65 63 74 08 05 13 00 FFFFFF84 00
   14 01 06 3C 69 6E 69 74 3E 14 01 15 10 02 0B 00
   08 07 17 00 FFFFFFC2 FFFFFF80 FFFFFF86 20 18 01 04 6C 61 6E 67 15
   01 19 10 02 1A 1D 0D 01 1B 0A 02 1C 04 01 06 72
   65 67 65 78 70 09 02 1E 1B 02 07 57 6F 72 64 45
   78 70 08 07 20 00 FFFFFFC0 FFFFFF80 FFFFFF84 08 21 01 06 6C 61 62
   65 6C 73 15 01 22 10 03 23 28 2A 0D 01 24 0A 02
   25 26 01 07 6D 75 74 61 62 6C 65 0A 02 27 06 01
   0A 63 6F 6C 6C 65 63 74 69 6F 6E 09 02 29 24 02
   07 48 61 73 68 53 65 74 10 02 2B 2D 0E 02 2C 16
   0D 01 00 09 02 2E 1D 02 07 5F 6C 61 62 65 6C 54
   08 07 30 00 FFFFFFC0 FFFFFF80 FFFFFF84 08 31 01 0A 6C 61 62 65 6C
   73 5F 24 65 71 14 02 32 35 10 02 0F 33 09 02 34
   06 02 04 55 6E 69 74 08 07 36 2F FFFFFF81 FFFFFF80 FFFFFFC0 00 22
   01 03 78 24 31 08 06 38 00 FFFFFFA0 FFFFFFA0 04 22 01 07 6C
   61 62 65 6C 73 20 08 07 3A 00 FFFFFFC0 FFFFFF80 FFFFFF84 08 3B 01
   07 6C 61 62 65 6C 41 74 15 01 3C 10 04 3D 40 42
   2A 0D 01 3E 0A 02 3F 26 01 09 69 6D 6D 75 74 61
   62 6C 65 09 02 41 3E 02 03 4D 61 70 10 02 0F 43
   09 02 44 06 02 03 49 6E 74 08 07 46 00 FFFFFFC0 FFFFFF80 FFFFFF84
   08 47 01 0B 6C 61 62 65 6C 41 74 5F 24 65 71 14
   02 32 48 08 07 36 45 FFFFFF81 FFFFFF80 FFFFFFC0 00 3C 08 06 4A 00
   FFFFFFA0 FFFFFFA0 04 3C 01 08 6C 61 62 65 6C 41 74 20 08 07
   4C 00 FFFFFFC0 FFFFFF80 FFFFFF84 08 4D 01 06 64 65 6C 74 61 71 15
   01 4E 10 03 0F 4F 51 09 02 50 06 02 05 41 72 72
   61 79 10 04 23 52 2A 54 09 02 53 24 02 07 48 61
   73 68 4D 61 70 10 03 55 5D 42 0E 02 56 5B 0E 02
   57 5A 0D 01 58 0A 02 59 08 01 06 3C 72 6F 6F 74
   3E 09 01 07 09 02 5C 06 01 07 70 61 63 6B 61 67
   65 09 02 5E 5F 02 04 4C 69 73 74 0A 02 5C 06 08
   07 61 00 FFFFFFC0 FFFFFF80 FFFFFF84 08 62 01 0A 64 65 6C 74 61 71
   5F 24 65 71 14 02 32 63 08 07 36 60 FFFFFF81 FFFFFF80 FFFFFFC0 00
   4E 08 06 65 00 FFFFFFA0 FFFFFFA0 04 4E 01 07 64 65 6C 74 61
   71 20 08 07 67 00 FFFFFFC0 FFFFFF80 FFFFFF84 08 68 01 08 64 65 66
   61 75 6C 74 71 15 01 69 10 03 0F 4F 54 08 07 6B
   00 FFFFFFC0 FFFFFF80 FFFFFF84 08 6C 01 0C 64 65 66 61 75 6C 74 71
   5F 24 65 71 14 02 32 6D 08 07 36 6A FFFFFF81 FFFFFF80 FFFFFFC0 00
   69 08 06 6F 00 FFFFFFA0 FFFFFFA0 04 69 01 09 64 65 66 61 75
   6C 74 71 20 08 07 71 00 FFFFFFC0 FFFFFF80 FFFFFF84 08 72 01 08 69
   6E 69 74 69 61 6C 73 15 01 73 10 03 3D 74 42 09
   02 75 3E 02 03 53 65 74 08 07 77 00 FFFFFFC0 FFFFFF80 FFFFFF84 08
   78 01 0C 69 6E 69 74 69 61 6C 73 5F 24 65 71 14
   02 32 79 08 07 36 76 FFFFFF81 FFFFFF80 FFFFFFC0 00 73 08 06 7B 00
   FFFFFFA0 FFFFFFA0 04 73 01 09 69 6E 69 74 69 61 6C 73 20 08
   05 7D 00 FFFFFF84 28 7E 01 09 63 6F 6D 70 46 69 72 73
   74 14 02 73 7F 08 07 FFFFFF81 00 7C FFFFFFC0 00 FFFFFF81 01 01 01
   72 10 03 2B FFFFFF81 02 09 04 FFFFFF81 03 FFFFFF81 04 02 06 52 65
   67 45 78 70 09 03 FFFFFF81 05 1B 02 04 42 61 73 65 08
   07 FFFFFF81 07 00 FFFFFF84 28 FFFFFF81 08 01 08 63 6F 6D 70 4C 61
   73 74 14 03 73 FFFFFF81 09 08 08 FFFFFF81 00 FFFFFF81 06 FFFFFFC0 00 FFFFFF81
   01 08 07 FFFFFF81 0B 00 FFFFFF84 28 FFFFFF81 0C 01 0B 63 6F 6D 70
   46 6F 6C 6C 6F 77 31 14 05 73 FFFFFF81 0D FFFFFF81 0F 08 07
   FFFFFF81 0E FFFFFF81 0A FFFFFFC0 00 73 01 04 66 6F 6C 31 08 08 FFFFFF81
   00 FFFFFF81 0A FFFFFFC0 00 FFFFFF81 01 08 07 FFFFFF81 11 00 FFFFFF84 08 FFFFFF81 12
   01 09 73 65 65 6E 4C 61 62 65 6C 14 07 32 FFFFFF81 13
   FFFFFF81 14 FFFFFF81 16 08 08 FFFFFF81 00 FFFFFF81 10 FFFFFFC0 00 FFFFFF81 01 08 07
   FFFFFF81 15 FFFFFF81 10 FFFFFFC0 00 42 01 01 69 08 07 FFFFFF81 17 FFFFFF81 10
   FFFFFFC0 00 2A 01 05 6C 61 62 65 6C 08 07 FFFFFF81 11 00 FFFFFF84
   08 FFFFFF81 19 14 05 42 FFFFFF81 1A FFFFFF81 1B 08 08 FFFFFF81 00 FFFFFF81 18
   FFFFFFC0 00 FFFFFF81 01 08 07 FFFFFF81 17 FFFFFF81 18 FFFFFFC0 00 2A 08 07 FFFFFF81
   1D 00 FFFFFF84 20 FFFFFF81 1E 01 08 74 72 61 76 65 72 73 65
   14 03 32 FFFFFF81 1F 08 08 FFFFFF81 00 FFFFFF81 1C FFFFFFC0 00 FFFFFF81 01 08
   07 FFFFFF81 21 00 FFFFFF84 08 FFFFFF81 22 01 0E 6D 61 6B 65 54 72
   61 6E 73 69 74 69 6F 6E 14 07 32 FFFFFF81 23 FFFFFF81 25 FFFFFF81
   27 08 07 FFFFFF81 24 FFFFFF81 20 FFFFFFC0 00 42 01 03 73 72 63 08
   07 FFFFFF81 26 FFFFFF81 20 FFFFFFC0 00 42 01 04 64 65 73 74 08 07
   FFFFFF81 17 FFFFFF81 20 FFFFFFC0 00 2A 08 07 FFFFFF81 29 00 FFFFFF84 08 FFFFFF81 2A
   01 0A 69 6E 69 74 69 61 6C 69 7A 65 14 03 32 FFFFFF81
   2B 08 08 FFFFFF81 2C FFFFFF81 28 FFFFFFC0 00 FFFFFF81 2D 01 07 73 75 62
   65 78 70 72 10 05 55 FFFFFF81 2E FFFFFF81 01 09 03 FFFFFF81 2F 5F
   02 03 53 65 71 08 07 FFFFFF81 31 00 FFFFFF84 08 FFFFFF81 32 01 0F
   69 6E 69 74 69 61 6C 69 7A 65 41 75 74 6F 6D 14
   01 32 08 07 FFFFFF81 34 00 FFFFFF84 08 FFFFFF81 32 01 12 63 6F 6C
   6C 65 63 74 54 72 61 6E 73 69 74 69 6F 6E 73 08
   07 FFFFFF81 36 00 FFFFFF84 00 FFFFFF81 37 01 0D 61 75 74 6F 6D 61
   74 6F 6E 46 72 6F 6D 14 06 FFFFFF81 38 FFFFFF81 3B FFFFFF81 3D 10
   04 0B FFFFFF81 39 2A 09 03 FFFFFF81 3A 02 02 0F 4E 6F 6E 64
   65 74 57 6F 72 64 41 75 74 6F 6D 08 08 FFFFFF81 3C FFFFFF81
   35 FFFFFFC0 00 FFFFFF81 01 01 03 70 61 74 08 07 FFFFFF81 3E FFFFFF81 35
   FFFFFFC0 00 42 01 08 66 69 6E 61 6C 54 61 67 
  InnerClass: 
   public Sequ=class scala/util/regexp/Base$Sequ of class scala/util/regexp/Base
   public abstract ByOne=class scala/collection/immutable/Range$ByOne of class scala/collection/immutable/Range
   public abstract RegExp=class scala/util/regexp/Base$RegExp of class scala/util/regexp/Base
   public final $anon$2=class scala/Array$$anon$2 of class scala/Array
   public abstract Label=class scala/util/regexp/WordExp$Label of class scala/util/regexp/WordExp
   public Letter=class scala/util/regexp/WordExp$Letter of class scala/util/regexp/WordExp
   public ofRef=class scala/collection/mutable/ArrayOps$ofRef of class scala/collection/mutable/ArrayOps
   public final $anon$15=class scala/reflect/Manifest$$anon$15 of class scala/reflect/Manifest
   public final $anon$1=class scala/reflect/ClassManifest$$anon$1 of class scala/reflect/ClassManifest
   public final $anon$1=class scala/util/automata/WordBerrySethi$$anon$1 of class scala/util/automata/WordBerrySethi
   public final $anonfun$4=class scala/util/automata/WordBerrySethi$$anonfun$4 of class scala/util/automata/WordBerrySethi
   public final $anonfun$3=class scala/util/automata/WordBerrySethi$$anonfun$3 of class scala/util/automata/WordBerrySethi
   public final $anonfun$2=class scala/util/automata/WordBerrySethi$$anonfun$2 of class scala/util/automata/WordBerrySethi
   public final $anonfun$1=class scala/util/automata/WordBerrySethi$$anonfun$1 of class scala/util/automata/WordBerrySethi
   public ClassTypeManifest=class scala/reflect/ClassManifest$ClassTypeManifest of class scala/reflect/ClassManifest
   public final $anonfun$initialize$1=class scala/util/automata/WordBerrySethi$$anonfun$initialize$1 of class scala/util/automata/WordBerrySethi
   public final $anonfun$makeTransition$1=class scala/util/automata/WordBerrySethi$$anonfun$makeTransition$1 of class scala/util/automata/WordBerrySethi
   public final $anonfun$initializeAutom$1=class scala/util/automata/WordBerrySethi$$anonfun$initializeAutom$1 of class scala/util/automata/WordBerrySethi
   public final $anonfun$collectTransitions$2=class scala/util/automata/WordBerrySethi$$anonfun$collectTransitions$2 of class scala/util/automata/WordBerrySethi
   public final $anonfun$collectTransitions$1=class scala/util/automata/WordBerrySethi$$anonfun$collectTransitions$1 of class scala/util/automata/WordBerrySethi
  minor version: 0
  major version: 49
  Constant pool:
Asciz	SourceFile;
Asciz	WordBerrySethi.scala;
Asciz	initials;
Asciz	Lscala/collection/immutable/Set;;
Asciz	Lscala/collection/immutable/Set<Ljava/lang/Integer;>;;
Asciz	Signature;
Asciz	defaultq;
Asciz	[Lscala/collection/immutable/List;;
Asciz	[Lscala/collection/immutable/List<Ljava/lang/Integer;>;;
Asciz	deltaq;
Asciz	[Lscala/collection/mutable/HashMap;;
Asciz	[Lscala/collection/mutable/HashMap<Lscala/util/regexp/WordExp$Label;Lscala/collection/immutable/List<Ljava/lang/Integer;>;>;;
Asciz	labelAt;
Asciz	Lscala/collection/immutable/Map;;
Asciz	Lscala/collection/immutable/Map<Ljava/lang/Integer;Lscala/util/regexp/WordExp$Label;>;;
Asciz	labels;
Asciz	Lscala/collection/mutable/HashSet;;
Asciz	Lscala/collection/mutable/HashSet<Lscala/util/regexp/WordExp$Label;>;;
Asciz	<init>;
Asciz	()V;
Asciz	Code;
Asciz	LineNumberTable;
Asciz	scala/util/automata/BaseBerrySethi;
class	scala/util/automata/BaseBerrySethi
NameAndType	"<init>":()V
Method	scala/util/automata/BaseBerrySethi."<init>":()V
Asciz	automatonFrom;
Asciz	(Lscala/util/regexp/Base$RegExp;I)Lscala/util/automata/NondetWordAutom;;
Asciz	scala/util/automata/WordBerrySethi;
class	scala/util/automata/WordBerrySethi
Asciz	finalTag_$eq;
Asciz	(I)V;
NameAndType	finalTag_$eq:(I)V
Method	scala/util/automata/WordBerrySethi.finalTag_$eq:(I)V
Asciz	scala/util/regexp/Base$Sequ;
class	scala/util/regexp/Base$Sequ
Asciz	rs;
Asciz	()Lscala/collection/Seq;;
NameAndType	rs:()Lscala/collection/Seq;
Method	scala/util/regexp/Base$Sequ.rs:()Lscala/collection/Seq;
Asciz	initialize;
Asciz	(Lscala/collection/Seq;)V;
NameAndType	initialize:(Lscala/collection/Seq;)V
Method	scala/util/automata/WordBerrySethi.initialize:(Lscala/collection/Seq;)V
Asciz	pos;
Asciz	()I;
NameAndType	pos:()I
Method	scala/util/automata/WordBerrySethi.pos:()I
Asciz	pos_$eq;
NameAndType	pos_$eq:(I)V
Method	scala/util/automata/WordBerrySethi.pos_$eq:(I)V
Asciz	compFollow;
Asciz	(Lscala/collection/Seq;)Lscala/collection/immutable/Set;;
NameAndType	compFollow:(Lscala/collection/Seq;)Lscala/collection/immutable/Set;
Method	scala/util/automata/WordBerrySethi.compFollow:(Lscala/collection/Seq;)Lscala/collection/immutable/Set;
Asciz	initializeAutom;
NameAndType	initializeAutom:()V
Method	scala/util/automata/WordBerrySethi.initializeAutom:()V
Asciz	collectTransitions;
NameAndType	collectTransitions:()V
Method	scala/util/automata/WordBerrySethi.collectTransitions:()V
Asciz	isNullable;
Asciz	()Z;
NameAndType	isNullable:()Z
Method	scala/util/regexp/Base$Sequ.isNullable:()Z
Asciz	finals;
Asciz	()Lscala/collection/immutable/Map;;
NameAndType	finals:()Lscala/collection/immutable/Map;
Method	scala/util/automata/WordBerrySethi.finals:()Lscala/collection/immutable/Map;
Asciz	scala/runtime/BoxesRunTime;
class	scala/runtime/BoxesRunTime
Asciz	boxToInteger;
Asciz	(I)Ljava/lang/Integer;;
NameAndType	boxToInteger:(I)Ljava/lang/Integer;
Method	scala/runtime/BoxesRunTime.boxToInteger:(I)Ljava/lang/Integer;
Asciz	scala/collection/immutable/MapLike;
class	scala/collection/immutable/MapLike
Asciz	updated;
Asciz	(Ljava/lang/Object;Ljava/lang/Object;)Lscala/collection/immutable/Map;;
NameAndType	updated:(Ljava/lang/Object;Ljava/lang/Object;)Lscala/collection/immutable/Map;
InterfaceMethod	scala/collection/immutable/MapLike.updated:(Ljava/lang/Object;Ljava/lang/Object;)Lscala/collection/immutable/Map;
Asciz	finals_$eq;
Asciz	(Lscala/collection/immutable/Map;)V;
NameAndType	finals_$eq:(Lscala/collection/immutable/Map;)V
Method	scala/util/automata/WordBerrySethi.finals_$eq:(Lscala/collection/immutable/Map;)V
Asciz	scala/collection/immutable/Map$;
class	scala/collection/immutable/Map$
Asciz	MODULE$;
Asciz	Lscala/collection/immutable/Map$;;
NameAndType	MODULE$:Lscala/collection/immutable/Map$;
Field	scala/collection/immutable/Map$.MODULE$:Lscala/collection/immutable/Map$;
Asciz	scala/Predef$;
class	scala/Predef$
Asciz	Lscala/Predef$;;
NameAndType	MODULE$:Lscala/Predef$;
Field	scala/Predef$.MODULE$:Lscala/Predef$;
Asciz	()[Lscala/collection/mutable/HashMap;;
NameAndType	deltaq:()[Lscala/collection/mutable/HashMap;
Method	scala/util/automata/WordBerrySethi.deltaq:()[Lscala/collection/mutable/HashMap;
Asciz	[Ljava/lang/Object;;
class	"[Ljava/lang/Object;"
Asciz	scala/collection/mutable/ArrayOps$ofRef;
class	scala/collection/mutable/ArrayOps$ofRef
Asciz	([Ljava/lang/Object;)V;
NameAndType	"<init>":([Ljava/lang/Object;)V
Method	scala/collection/mutable/ArrayOps$ofRef."<init>":([Ljava/lang/Object;)V
Asciz	scala/Tuple2;
class	scala/Tuple2
Asciz	scala/collection/mutable/HashMap;
class	scala/collection/mutable/HashMap
Asciz	lang;
Asciz	()Lscala/util/regexp/WordExp;;
NameAndType	lang:()Lscala/util/regexp/WordExp;
Method	scala/util/automata/WordBerrySethi.lang:()Lscala/util/regexp/WordExp;
Asciz	scala/reflect/Manifest$$anon$15;
class	scala/reflect/Manifest$$anon$15
Asciz	(Ljava/lang/Object;)V;
NameAndType	"<init>":(Ljava/lang/Object;)V
Method	scala/reflect/Manifest$$anon$15."<init>":(Ljava/lang/Object;)V
Asciz	_labelT;
String	_labelT
Asciz	scala/util/regexp/WordExp$Label;
class	scala/util/regexp/WordExp$Label
Asciz	scala/reflect/OptManifest;
class	scala/reflect/OptManifest
Asciz	wrapRefArray;
Asciz	([Ljava/lang/Object;)Lscala/collection/mutable/WrappedArray;;
NameAndType	wrapRefArray:([Ljava/lang/Object;)Lscala/collection/mutable/WrappedArray;
Method	scala/Predef$.wrapRefArray:([Ljava/lang/Object;)Lscala/collection/mutable/WrappedArray;
Asciz	scala/reflect/ClassManifest$ClassTypeManifest;
class	scala/reflect/ClassManifest$ClassTypeManifest
Asciz	scala/Some;
class	scala/Some
Method	scala/Some."<init>":(Ljava/lang/Object;)V
Asciz	scala/collection/TraversableLike;
class	scala/collection/TraversableLike
Asciz	toList;
Asciz	()Lscala/collection/immutable/List;;
NameAndType	toList:()Lscala/collection/immutable/List;
InterfaceMethod	scala/collection/TraversableLike.toList:()Lscala/collection/immutable/List;
Asciz	(Lscala/Option;Ljava/lang/Class;Lscala/collection/immutable/List;)V;
NameAndType	"<init>":(Lscala/Option;Ljava/lang/Class;Lscala/collection/immutable/List;)V
Method	scala/reflect/ClassManifest$ClassTypeManifest."<init>":(Lscala/Option;Ljava/lang/Class;Lscala/collection/immutable/List;)V
Asciz	scala/reflect/ClassManifest$$anon$1;
class	scala/reflect/ClassManifest$$anon$1
Asciz	(Lscala/reflect/OptManifest;Ljava/lang/String;Lscala/reflect/ClassManifest;Lscala/collection/Seq;)V;
NameAndType	"<init>":(Lscala/reflect/OptManifest;Ljava/lang/String;Lscala/reflect/ClassManifest;Lscala/collection/Seq;)V
Method	scala/reflect/ClassManifest$$anon$1."<init>":(Lscala/reflect/OptManifest;Ljava/lang/String;Lscala/reflect/ClassManifest;Lscala/collection/Seq;)V
Asciz	scala/collection/immutable/List;
class	scala/collection/immutable/List
Asciz	scala/reflect/Manifest$;
class	scala/reflect/Manifest$
Asciz	Lscala/reflect/Manifest$;;
NameAndType	MODULE$:Lscala/reflect/Manifest$;
Field	scala/reflect/Manifest$.MODULE$:Lscala/reflect/Manifest$;
Asciz	Int;
Asciz	()Ljava/lang/Object;;
NameAndType	Int:()Ljava/lang/Object;
Method	scala/reflect/Manifest$.Int:()Ljava/lang/Object;
Asciz	scala/None$;
class	scala/None$
Asciz	Lscala/None$;;
NameAndType	MODULE$:Lscala/None$;
Field	scala/None$.MODULE$:Lscala/None$;
Asciz	$colon$colon;
Asciz	(Ljava/lang/Object;)Lscala/collection/immutable/List;;
NameAndType	$colon$colon:(Ljava/lang/Object;)Lscala/collection/immutable/List;
Method	scala/collection/immutable/List.$colon$colon:(Ljava/lang/Object;)Lscala/collection/immutable/List;
Asciz	scala/Array$$anon$2;
class	scala/Array$$anon$2
Asciz	(Lscala/reflect/ClassManifest;)V;
NameAndType	"<init>":(Lscala/reflect/ClassManifest;)V
Method	scala/Array$$anon$2."<init>":(Lscala/reflect/ClassManifest;)V
Asciz	scala/collection/IndexedSeqLike;
class	scala/collection/IndexedSeqLike
Asciz	zipWithIndex;
Asciz	(Lscala/collection/generic/CanBuildFrom;)Ljava/lang/Object;;
NameAndType	zipWithIndex:(Lscala/collection/generic/CanBuildFrom;)Ljava/lang/Object;
InterfaceMethod	scala/collection/IndexedSeqLike.zipWithIndex:(Lscala/collection/generic/CanBuildFrom;)Ljava/lang/Object;
Asciz	scala/util/automata/WordBerrySethi$$anonfun$1;
class	scala/util/automata/WordBerrySethi$$anonfun$1
Asciz	(Lscala/util/automata/WordBerrySethi;)V;
NameAndType	"<init>":(Lscala/util/automata/WordBerrySethi;)V
Method	scala/util/automata/WordBerrySethi$$anonfun$1."<init>":(Lscala/util/automata/WordBerrySethi;)V
Asciz	scala/Array$;
class	scala/Array$
Asciz	Lscala/Array$;;
NameAndType	MODULE$:Lscala/Array$;
Field	scala/Array$.MODULE$:Lscala/Array$;
Asciz	scala/reflect/ClassManifest$;
class	scala/reflect/ClassManifest$
Asciz	Lscala/reflect/ClassManifest$;;
NameAndType	MODULE$:Lscala/reflect/ClassManifest$;
Field	scala/reflect/ClassManifest$.MODULE$:Lscala/reflect/ClassManifest$;
Asciz	singleType;
Asciz	(Ljava/lang/Object;)Lscala/reflect/Manifest;;
NameAndType	singleType:(Ljava/lang/Object;)Lscala/reflect/Manifest;
Method	scala/reflect/ClassManifest$.singleType:(Ljava/lang/Object;)Lscala/reflect/Manifest;
Asciz	abstractType;
Asciz	(Lscala/reflect/OptManifest;Ljava/lang/String;Lscala/reflect/ClassManifest;Lscala/collection/Seq;)Lscala/reflect/ClassManifest;;
NameAndType	abstractType:(Lscala/reflect/OptManifest;Ljava/lang/String;Lscala/reflect/ClassManifest;Lscala/collection/Seq;)Lscala/reflect/ClassManifest;
Method	scala/reflect/ClassManifest$.abstractType:(Lscala/reflect/OptManifest;Ljava/lang/String;Lscala/reflect/ClassManifest;Lscala/collection/Seq;)Lscala/reflect/ClassManifest;
Asciz	classType;
Asciz	(Ljava/lang/Class;Lscala/reflect/OptManifest;Lscala/collection/Seq;)Lscala/reflect/ClassManifest;;
NameAndType	classType:(Ljava/lang/Class;Lscala/reflect/OptManifest;Lscala/collection/Seq;)Lscala/reflect/ClassManifest;
Method	scala/reflect/ClassManifest$.classType:(Ljava/lang/Class;Lscala/reflect/OptManifest;Lscala/collection/Seq;)Lscala/reflect/ClassManifest;
Asciz	canBuildFrom;
Asciz	(Lscala/reflect/ClassManifest;)Lscala/collection/generic/CanBuildFrom;;
NameAndType	canBuildFrom:(Lscala/reflect/ClassManifest;)Lscala/collection/generic/CanBuildFrom;
Method	scala/Array$.canBuildFrom:(Lscala/reflect/ClassManifest;)Lscala/collection/generic/CanBuildFrom;
Asciz	map;
Asciz	(Lscala/Function1;Lscala/collection/generic/CanBuildFrom;)Ljava/lang/Object;;
NameAndType	map:(Lscala/Function1;Lscala/collection/generic/CanBuildFrom;)Ljava/lang/Object;
InterfaceMethod	scala/collection/TraversableLike.map:(Lscala/Function1;Lscala/collection/generic/CanBuildFrom;)Ljava/lang/Object;
Asciz	[Lscala/Tuple2;;
class	"[Lscala/Tuple2;"
Asciz	apply;
Asciz	(Lscala/collection/Seq;)Lscala/collection/Map;;
NameAndType	apply:(Lscala/collection/Seq;)Lscala/collection/Map;
Method	scala/collection/immutable/Map$.apply:(Lscala/collection/Seq;)Lscala/collection/Map;
Asciz	scala/collection/immutable/Map;
class	scala/collection/immutable/Map
Asciz	intWrapper;
Asciz	(I)Lscala/runtime/RichInt;;
NameAndType	intWrapper:(I)Lscala/runtime/RichInt;
Method	scala/Predef$.intWrapper:(I)Lscala/runtime/RichInt;
Asciz	scala/runtime/RichInt;
class	scala/runtime/RichInt
Asciz	until;
Asciz	(I)Lscala/collection/immutable/Range;;
NameAndType	until:(I)Lscala/collection/immutable/Range;
Method	scala/runtime/RichInt.until:(I)Lscala/collection/immutable/Range;
Asciz	scala/util/automata/WordBerrySethi$$anonfun$2;
class	scala/util/automata/WordBerrySethi$$anonfun$2
Method	scala/util/automata/WordBerrySethi$$anonfun$2."<init>":(Lscala/util/automata/WordBerrySethi;)V
Asciz	scala/collection/immutable/IndexedSeq$;
class	scala/collection/immutable/IndexedSeq$
Asciz	Lscala/collection/immutable/IndexedSeq$;;
NameAndType	MODULE$:Lscala/collection/immutable/IndexedSeq$;
Field	scala/collection/immutable/IndexedSeq$.MODULE$:Lscala/collection/immutable/IndexedSeq$;
Asciz	()Lscala/collection/generic/CanBuildFrom;;
NameAndType	canBuildFrom:()Lscala/collection/generic/CanBuildFrom;
Method	scala/collection/immutable/IndexedSeq$.canBuildFrom:()Lscala/collection/generic/CanBuildFrom;
Asciz	scala/reflect/ClassManifest;
class	scala/reflect/ClassManifest
Asciz	toArray;
Asciz	(Lscala/reflect/ClassManifest;)Ljava/lang/Object;;
NameAndType	toArray:(Lscala/reflect/ClassManifest;)Ljava/lang/Object;
InterfaceMethod	scala/collection/TraversableLike.toArray:(Lscala/reflect/ClassManifest;)Ljava/lang/Object;
Asciz	[I;
class	"[I"
Asciz	()Lscala/collection/immutable/Set;;
NameAndType	initials:()Lscala/collection/immutable/Set;
Method	scala/util/automata/WordBerrySethi.initials:()Lscala/collection/immutable/Set;
Asciz	scala/util/automata/WordBerrySethi$$anonfun$3;
class	scala/util/automata/WordBerrySethi$$anonfun$3
Asciz	(Lscala/util/automata/WordBerrySethi;Lscala/collection/immutable/Map;)V;
NameAndType	"<init>":(Lscala/util/automata/WordBerrySethi;Lscala/collection/immutable/Map;)V
Method	scala/util/automata/WordBerrySethi$$anonfun$3."<init>":(Lscala/util/automata/WordBerrySethi;Lscala/collection/immutable/Map;)V
Asciz	scala/collection/Map;
class	scala/collection/Map
Asciz	(Lscala/reflect/OptManifest;Ljava/lang/Class;Lscala/collection/Seq;)Lscala/reflect/ClassManifest;;
NameAndType	classType:(Lscala/reflect/OptManifest;Ljava/lang/Class;Lscala/collection/Seq;)Lscala/reflect/ClassManifest;
Method	scala/reflect/ClassManifest$.classType:(Lscala/reflect/OptManifest;Ljava/lang/Class;Lscala/collection/Seq;)Lscala/reflect/ClassManifest;
Asciz	scala/collection/immutable/BitSet;
class	scala/collection/immutable/BitSet
Asciz	(Ljava/lang/Class;)Lscala/reflect/ClassManifest;;
NameAndType	classType:(Ljava/lang/Class;)Lscala/reflect/ClassManifest;
Method	scala/reflect/ClassManifest$.classType:(Ljava/lang/Class;)Lscala/reflect/ClassManifest;
Asciz	[Lscala/collection/Map;;
class	"[Lscala/collection/Map;"
Asciz	scala/util/automata/WordBerrySethi$$anonfun$4;
class	scala/util/automata/WordBerrySethi$$anonfun$4
Method	scala/util/automata/WordBerrySethi$$anonfun$4."<init>":(Lscala/util/automata/WordBerrySethi;)V
Asciz	[Lscala/collection/immutable/BitSet;;
class	"[Lscala/collection/immutable/BitSet;"
Asciz	scala/util/automata/WordBerrySethi$$anon$1;
class	scala/util/automata/WordBerrySethi$$anon$1
Asciz	(Lscala/util/automata/WordBerrySethi;[I[I[Lscala/collection/Map;[Lscala/collection/immutable/BitSet;)V;
NameAndType	"<init>":(Lscala/util/automata/WordBerrySethi;[I[I[Lscala/collection/Map;[Lscala/collection/immutable/BitSet;)V
Method	scala/util/automata/WordBerrySethi$$anon$1."<init>":(Lscala/util/automata/WordBerrySethi;[I[I[Lscala/collection/Map;[Lscala/collection/immutable/BitSet;)V
Asciz	scala/MatchError;
class	scala/MatchError
Asciz	scala/util/regexp/Base$RegExp;
class	scala/util/regexp/Base$RegExp
Asciz	toString;
Asciz	()Ljava/lang/String;;
NameAndType	toString:()Ljava/lang/String;
Method	scala/util/regexp/Base$RegExp.toString:()Ljava/lang/String;
Asciz	(Ljava/lang/String;)V;
NameAndType	"<init>":(Ljava/lang/String;)V
Method	scala/MatchError."<init>":(Ljava/lang/String;)V
Asciz	scala/util/regexp/WordExp;
class	scala/util/regexp/WordExp
Asciz	Sequ;
Asciz	()Lscala/util/regexp/Base$Sequ$;;
NameAndType	Sequ:()Lscala/util/regexp/Base$Sequ$;
Method	scala/util/regexp/WordExp.Sequ:()Lscala/util/regexp/Base$Sequ$;
Asciz	scala/util/regexp/Base$Sequ$;
class	scala/util/regexp/Base$Sequ$
Asciz	(Lscala/collection/Seq;)Lscala/util/regexp/Base$RegExp;;
NameAndType	apply:(Lscala/collection/Seq;)Lscala/util/regexp/Base$RegExp;
Method	scala/util/regexp/Base$Sequ$.apply:(Lscala/collection/Seq;)Lscala/util/regexp/Base$RegExp;
NameAndType	automatonFrom:(Lscala/util/regexp/Base$RegExp;I)Lscala/util/automata/NondetWordAutom;
Method	scala/util/automata/WordBerrySethi.automatonFrom:(Lscala/util/regexp/Base$RegExp;I)Lscala/util/automata/NondetWordAutom;
Asciz	this;
Asciz	Lscala/util/automata/WordBerrySethi;;
Asciz	pat;
Asciz	Lscala/util/regexp/Base$RegExp;;
Asciz	finalTag;
Asciz	I;
Asciz	temp20;
Asciz	Lscala/util/regexp/Base$Sequ;;
Asciz	delta1$1;
Asciz	finalsArr$1;
Asciz	initialsArr$1;
Asciz	deltaArr$1;
Asciz	defaultArr$1;
Asciz	LocalVariableTable;
Asciz	(Lscala/util/regexp/Base$RegExp;I)Lscala/util/automata/NondetWordAutom<Lscala/util/regexp/WordExp$Label;>;;
Asciz	scala/util/automata/WordBerrySethi$$anonfun$collectTransitions$1;
class	scala/util/automata/WordBerrySethi$$anonfun$collectTransitions$1
Method	scala/util/automata/WordBerrySethi$$anonfun$collectTransitions$1."<init>":(Lscala/util/automata/WordBerrySethi;)V
Asciz	scala/util/automata/WordBerrySethi$$anonfun$collectTransitions$2;
class	scala/util/automata/WordBerrySethi$$anonfun$collectTransitions$2
Method	scala/util/automata/WordBerrySethi$$anonfun$collectTransitions$2."<init>":(Lscala/util/automata/WordBerrySethi;)V
Asciz	foreach;
Asciz	(Lscala/Function1;)V;
NameAndType	foreach:(Lscala/Function1;)V
InterfaceMethod	scala/collection/IndexedSeqLike.foreach:(Lscala/Function1;)V
Asciz	empty;
NameAndType	empty:()Lscala/collection/immutable/Map;
Method	scala/collection/immutable/Map$.empty:()Lscala/collection/immutable/Map;
Asciz	deltaq_$eq;
Asciz	([Lscala/collection/mutable/HashMap;)V;
NameAndType	deltaq_$eq:([Lscala/collection/mutable/HashMap;)V
Method	scala/util/automata/WordBerrySethi.deltaq_$eq:([Lscala/collection/mutable/HashMap;)V
Asciz	defaultq_$eq;
Asciz	([Lscala/collection/immutable/List;)V;
NameAndType	defaultq_$eq:([Lscala/collection/immutable/List;)V
Method	scala/util/automata/WordBerrySethi.defaultq_$eq:([Lscala/collection/immutable/List;)V
Asciz	scala/collection/immutable/Range$ByOne;
class	scala/collection/immutable/Range$ByOne
Asciz	scala/util/automata/WordBerrySethi$$anonfun$initializeAutom$1;
class	scala/util/automata/WordBerrySethi$$anonfun$initializeAutom$1
Method	scala/util/automata/WordBerrySethi$$anonfun$initializeAutom$1."<init>":(Lscala/util/automata/WordBerrySethi;)V
InterfaceMethod	scala/collection/immutable/Range$ByOne.foreach:(Lscala/Function1;)V
Asciz	labelAt_$eq;
NameAndType	labelAt_$eq:(Lscala/collection/immutable/Map;)V
Method	scala/util/automata/WordBerrySethi.labelAt_$eq:(Lscala/collection/immutable/Map;)V
Asciz	scala/collection/mutable/HashMap$;
class	scala/collection/mutable/HashMap$
Asciz	Lscala/collection/mutable/HashMap$;;
NameAndType	MODULE$:Lscala/collection/mutable/HashMap$;
Field	scala/collection/mutable/HashMap$.MODULE$:Lscala/collection/mutable/HashMap$;
Method	scala/collection/mutable/HashMap$.apply:(Lscala/collection/Seq;)Lscala/collection/Map;
Asciz	follow_$eq;
Asciz	(Lscala/collection/mutable/HashMap;)V;
NameAndType	follow_$eq:(Lscala/collection/mutable/HashMap;)V
Method	scala/util/automata/WordBerrySethi.follow_$eq:(Lscala/collection/mutable/HashMap;)V
Asciz	scala/collection/mutable/HashSet$;
class	scala/collection/mutable/HashSet$
Asciz	Lscala/collection/mutable/HashSet$;;
NameAndType	MODULE$:Lscala/collection/mutable/HashSet$;
Field	scala/collection/mutable/HashSet$.MODULE$:Lscala/collection/mutable/HashSet$;
Asciz	(Lscala/collection/Seq;)Lscala/collection/Traversable;;
NameAndType	apply:(Lscala/collection/Seq;)Lscala/collection/Traversable;
Method	scala/collection/mutable/HashSet$.apply:(Lscala/collection/Seq;)Lscala/collection/Traversable;
Asciz	scala/collection/mutable/HashSet;
class	scala/collection/mutable/HashSet
Asciz	labels_$eq;
Asciz	(Lscala/collection/mutable/HashSet;)V;
NameAndType	labels_$eq:(Lscala/collection/mutable/HashSet;)V
Method	scala/util/automata/WordBerrySethi.labels_$eq:(Lscala/collection/mutable/HashSet;)V
Asciz	scala/util/automata/WordBerrySethi$$anonfun$initialize$1;
class	scala/util/automata/WordBerrySethi$$anonfun$initialize$1
Method	scala/util/automata/WordBerrySethi$$anonfun$initialize$1."<init>":(Lscala/util/automata/WordBerrySethi;)V
Asciz	scala/collection/IterableLike;
class	scala/collection/IterableLike
InterfaceMethod	scala/collection/IterableLike.foreach:(Lscala/Function1;)V
Asciz	scala/collection/immutable/Set$;
class	scala/collection/immutable/Set$
Asciz	Lscala/collection/immutable/Set$;;
NameAndType	MODULE$:Lscala/collection/immutable/Set$;
Field	scala/collection/immutable/Set$.MODULE$:Lscala/collection/immutable/Set$;
Asciz	wrapIntArray;
Asciz	([I)Lscala/collection/mutable/WrappedArray;;
NameAndType	wrapIntArray:([I)Lscala/collection/mutable/WrappedArray;
Method	scala/Predef$.wrapIntArray:([I)Lscala/collection/mutable/WrappedArray;
Method	scala/collection/immutable/Set$.apply:(Lscala/collection/Seq;)Lscala/collection/Traversable;
Asciz	scala/collection/immutable/Set;
class	scala/collection/immutable/Set
Asciz	initials_$eq;
Asciz	(Lscala/collection/immutable/Set;)V;
NameAndType	initials_$eq:(Lscala/collection/immutable/Set;)V
Method	scala/util/automata/WordBerrySethi.initials_$eq:(Lscala/collection/immutable/Set;)V
Asciz	subexpr;
Asciz	Lscala/collection/Seq;;
Asciz	(Lscala/collection/Seq<Lscala/util/regexp/Base$RegExp;>;)V;
Asciz	makeTransition;
Asciz	(IILscala/util/regexp/WordExp$Label;)V;
Asciz	scala/util/automata/WordBerrySethi$$anonfun$makeTransition$1;
class	scala/util/automata/WordBerrySethi$$anonfun$makeTransition$1
Method	scala/util/automata/WordBerrySethi$$anonfun$makeTransition$1."<init>":(Lscala/util/automata/WordBerrySethi;)V
Asciz	scala/collection/MapLike;
class	scala/collection/MapLike
Asciz	getOrElse;
Asciz	(Ljava/lang/Object;Lscala/Function0;)Ljava/lang/Object;;
NameAndType	getOrElse:(Ljava/lang/Object;Lscala/Function0;)Ljava/lang/Object;
InterfaceMethod	scala/collection/MapLike.getOrElse:(Ljava/lang/Object;Lscala/Function0;)Ljava/lang/Object;
Asciz	update;
Asciz	(Ljava/lang/Object;Ljava/lang/Object;)V;
NameAndType	update:(Ljava/lang/Object;Ljava/lang/Object;)V
Method	scala/collection/mutable/HashMap.update:(Ljava/lang/Object;Ljava/lang/Object;)V
Asciz	src;
Asciz	dest;
Asciz	label;
Asciz	Lscala/util/regexp/WordExp$Label;;
Asciz	q;
Asciz	Lscala/collection/mutable/HashMap;;
Asciz	traverse;
Asciz	(Lscala/util/regexp/Base$RegExp;)V;
Asciz	scala/util/regexp/WordExp$Letter;
class	scala/util/regexp/WordExp$Letter
Asciz	a;
Asciz	()Lscala/util/regexp/WordExp$Label;;
NameAndType	a:()Lscala/util/regexp/WordExp$Label;
Method	scala/util/regexp/WordExp$Letter.a:()Lscala/util/regexp/WordExp$Label;
Asciz	seenLabel;
Asciz	(Lscala/util/regexp/Base$RegExp;Lscala/util/regexp/WordExp$Label;)I;
NameAndType	seenLabel:(Lscala/util/regexp/Base$RegExp;Lscala/util/regexp/WordExp$Label;)I
Method	scala/util/automata/WordBerrySethi.seenLabel:(Lscala/util/regexp/Base$RegExp;Lscala/util/regexp/WordExp$Label;)I
Method	scala/util/regexp/WordExp$Letter.pos_$eq:(I)V
Asciz	Eps;
Asciz	()Lscala/util/regexp/Base$Eps$;;
NameAndType	Eps:()Lscala/util/regexp/Base$Eps$;
Method	scala/util/regexp/WordExp.Eps:()Lscala/util/regexp/Base$Eps$;
Asciz	java/lang/Object;
class	java/lang/Object
Asciz	equals;
Asciz	(Ljava/lang/Object;)Z;
NameAndType	equals:(Ljava/lang/Object;)Z
Method	java/lang/Object.equals:(Ljava/lang/Object;)Z
NameAndType	traverse:(Lscala/util/regexp/Base$RegExp;)V
Method	scala/util/automata/BaseBerrySethi.traverse:(Lscala/util/regexp/Base$RegExp;)V
Asciz	r;
Asciz	temp11;
Asciz	Lscala/util/regexp/WordExp$Letter;;
Asciz	temp12;
Asciz	(Lscala/util/regexp/Base$RegExp;ILscala/util/regexp/WordExp$Label;)V;
NameAndType	seenLabel:(Lscala/util/regexp/Base$RegExp;ILscala/util/regexp/WordExp$Label;)V
Method	scala/util/automata/WordBerrySethi.seenLabel:(Lscala/util/regexp/Base$RegExp;ILscala/util/regexp/WordExp$Label;)V
NameAndType	labelAt:()Lscala/collection/immutable/Map;
Method	scala/util/automata/WordBerrySethi.labelAt:()Lscala/collection/immutable/Map;
Asciz	()Lscala/collection/mutable/HashSet;;
NameAndType	labels:()Lscala/collection/mutable/HashSet;
Method	scala/util/automata/WordBerrySethi.labels:()Lscala/collection/mutable/HashSet;
Asciz	$plus$eq;
Asciz	(Ljava/lang/Object;)Lscala/collection/mutable/HashSet;;
NameAndType	$plus$eq:(Ljava/lang/Object;)Lscala/collection/mutable/HashSet;
Method	scala/collection/mutable/HashSet.$plus$eq:(Ljava/lang/Object;)Lscala/collection/mutable/HashSet;
Asciz	i;
Asciz	compFollow1;
Asciz	(Lscala/collection/immutable/Set;Lscala/util/regexp/Base$RegExp;)Lscala/collection/immutable/Set;;
Asciz	follow;
Asciz	()Lscala/collection/mutable/HashMap;;
NameAndType	follow:()Lscala/collection/mutable/HashMap;
Method	scala/util/automata/WordBerrySethi.follow:()Lscala/collection/mutable/HashMap;
Method	scala/util/regexp/WordExp$Letter.pos:()I
Asciz	emptySet;
NameAndType	emptySet:()Lscala/collection/immutable/Set;
Method	scala/util/automata/WordBerrySethi.emptySet:()Lscala/collection/immutable/Set;
NameAndType	compFollow1:(Lscala/collection/immutable/Set;Lscala/util/regexp/Base$RegExp;)Lscala/collection/immutable/Set;
Method	scala/util/automata/BaseBerrySethi.compFollow1:(Lscala/collection/immutable/Set;Lscala/util/regexp/Base$RegExp;)Lscala/collection/immutable/Set;
Asciz	fol1;
Asciz	temp8;
Asciz	(Lscala/collection/immutable/Set<Ljava/lang/Integer;>;Lscala/util/regexp/Base$RegExp;)Lscala/collection/immutable/Set<Ljava/lang/Integer;>;;
Asciz	compLast;
Asciz	(Lscala/util/regexp/Base$RegExp;)Lscala/collection/immutable/Set;;
NameAndType	compLast:(Lscala/util/regexp/Base$RegExp;)Lscala/collection/immutable/Set;
Method	scala/util/automata/BaseBerrySethi.compLast:(Lscala/util/regexp/Base$RegExp;)Lscala/collection/immutable/Set;
Asciz	temp5;
Asciz	(Lscala/util/regexp/Base$RegExp;)Lscala/collection/immutable/Set<Ljava/lang/Integer;>;;
Asciz	compFirst;
NameAndType	compFirst:(Lscala/util/regexp/Base$RegExp;)Lscala/collection/immutable/Set;
Method	scala/util/automata/BaseBerrySethi.compFirst:(Lscala/util/regexp/Base$RegExp;)Lscala/collection/immutable/Set;
Asciz	temp2;
NameAndType	initials:Lscala/collection/immutable/Set;
Field	scala/util/automata/WordBerrySethi.initials:Lscala/collection/immutable/Set;
Asciz	(Lscala/collection/immutable/Set<Ljava/lang/Integer;>;)V;
Asciz	()Lscala/collection/immutable/Set<Ljava/lang/Integer;>;;
NameAndType	defaultq:[Lscala/collection/immutable/List;
Field	scala/util/automata/WordBerrySethi.defaultq:[Lscala/collection/immutable/List;
Asciz	([Lscala/collection/immutable/List<Ljava/lang/Integer;>;)V;
Asciz	()[Lscala/collection/immutable/List;;
Asciz	()[Lscala/collection/immutable/List<Ljava/lang/Integer;>;;
NameAndType	deltaq:[Lscala/collection/mutable/HashMap;
Field	scala/util/automata/WordBerrySethi.deltaq:[Lscala/collection/mutable/HashMap;
Asciz	([Lscala/collection/mutable/HashMap<Lscala/util/regexp/WordExp$Label;Lscala/collection/immutable/List<Ljava/lang/Integer;>;>;)V;
Asciz	()[Lscala/collection/mutable/HashMap<Lscala/util/regexp/WordExp$Label;Lscala/collection/immutable/List<Ljava/lang/Integer;>;>;;
NameAndType	labelAt:Lscala/collection/immutable/Map;
Field	scala/util/automata/WordBerrySethi.labelAt:Lscala/collection/immutable/Map;
Asciz	(Lscala/collection/immutable/Map<Ljava/lang/Integer;Lscala/util/regexp/WordExp$Label;>;)V;
Asciz	()Lscala/collection/immutable/Map<Ljava/lang/Integer;Lscala/util/regexp/WordExp$Label;>;;
NameAndType	labels:Lscala/collection/mutable/HashSet;
Field	scala/util/automata/WordBerrySethi.labels:Lscala/collection/mutable/HashSet;
Asciz	(Lscala/collection/mutable/HashSet<Lscala/util/regexp/WordExp$Label;>;)V;
Asciz	()Lscala/collection/mutable/HashSet<Lscala/util/regexp/WordExp$Label;>;;
Asciz	ScalaSig;
Asciz	InnerClasses;
Asciz	scala/util/regexp/Base;
class	scala/util/regexp/Base
Asciz	scala/collection/immutable/Range;
class	scala/collection/immutable/Range
Asciz	ByOne;
Asciz	RegExp;
Asciz	scala/Array;
class	scala/Array
Asciz	$anon$2;
Asciz	Label;
Asciz	Letter;
Asciz	scala/collection/mutable/ArrayOps;
class	scala/collection/mutable/ArrayOps
Asciz	ofRef;
Asciz	scala/reflect/Manifest;
class	scala/reflect/Manifest
Asciz	$anon$15;
Asciz	$anon$1;
Asciz	$anonfun$4;
Asciz	$anonfun$3;
Asciz	$anonfun$2;
Asciz	$anonfun$1;
Asciz	ClassTypeManifest;
Asciz	$anonfun$initialize$1;
Asciz	$anonfun$makeTransition$1;
Asciz	$anonfun$initializeAutom$1;
Asciz	$anonfun$collectTransitions$2;
Asciz	$anonfun$collectTransitions$1;
Asciz	scala/ScalaObject;
class	scala/ScalaObject

{
private scala.collection.immutable.Set initials;
  Signature: Lscala/collection/immutable/Set;
  Signature: length = 0x2
   00 05 

private scala.collection.immutable.List[] defaultq;
  Signature: [Lscala/collection/immutable/List;
  Signature: length = 0x2
   00 09 

private scala.collection.mutable.HashMap[] deltaq;
  Signature: [Lscala/collection/mutable/HashMap;
  Signature: length = 0x2
   00 0C 

private scala.collection.immutable.Map labelAt;
  Signature: Lscala/collection/immutable/Map;
  Signature: length = 0x2
   00 0F 

private scala.collection.mutable.HashSet labels;
  Signature: Lscala/collection/mutable/HashSet;
  Signature: length = 0x2
   00 12 

public scala.util.automata.WordBerrySethi();
  Signature: ()V
  Code:
   Stack=1, Locals=1, Args_size=1
	aload_0
	invokespecial	Method scala/util/automata/BaseBerrySethi."<init>":()V
	return
  Labels:

public scala.util.automata.NondetWordAutom automatonFrom(scala.util.regexp.Base$RegExp, int);
  Signature: (Lscala/util/regexp/Base$RegExp;I)Lscala/util/automata/NondetWordAutom;
  Code:
   Stack=24, Locals=35, Args_size=3
	aload_0
	iload_2
	invokevirtual	Method finalTag_$eq:(I)V
	aload_1
	instanceof	class scala/util/regexp/Base$Sequ
	ifeq	l1 // iconst_1
	aload_1
	checkcast	class scala/util/regexp/Base$Sequ
	astore_3
	iconst_1
	ifeq	l2 // new
	aload_0
	aload_3
	invokevirtual	Method scala/util/regexp/Base$Sequ.rs:()Lscala/collection/Seq;
	invokevirtual	Method initialize:(Lscala/collection/Seq;)V
	aload_0
	aload_0
	invokevirtual	Method pos:()I
	iconst_1
	iadd
	invokevirtual	Method pos_$eq:(I)V
	aload_0
	aload_3
	invokevirtual	Method scala/util/regexp/Base$Sequ.rs:()Lscala/collection/Seq;
	invokevirtual	Method compFollow:(Lscala/collection/Seq;)Lscala/collection/immutable/Set;
	pop
	aload_0
	invokevirtual	Method initializeAutom:()V
	aload_0
	invokevirtual	Method collectTransitions:()V
	aload_3
	invokevirtual	Method scala/util/regexp/Base$Sequ.isNullable:()Z
	ifeq	l3 // getstatic
	aload_0
	aload_0
	invokevirtual	Method finals:()Lscala/collection/immutable/Map;
	iconst_0
	istore	4
	iload	4
	invokestatic	Method scala/runtime/BoxesRunTime.boxToInteger:(I)Ljava/lang/Integer;
	iload_2
	invokestatic	Method scala/runtime/BoxesRunTime.boxToInteger:(I)Ljava/lang/Integer;
	invokeinterface	InterfaceMethod scala/collection/immutable/MapLike.updated:(Ljava/lang/Object;Ljava/lang/Object;)Lscala/collection/immutable/Map;
	invokevirtual	Method finals_$eq:(Lscala/collection/immutable/Map;)V
l3	getstatic	Field scala/collection/immutable/Map$.MODULE$:Lscala/collection/immutable/Map$;
	getstatic	Field scala/Predef$.MODULE$:Lscala/Predef$;
	aload_0
	invokevirtual	Method deltaq:()[Lscala/collection/mutable/HashMap;
	checkcast	class "[Ljava/lang/Object;"
	astore	5
	new	class scala/collection/mutable/ArrayOps$ofRef
	dup
	aload	5
	invokespecial	Method scala/collection/mutable/ArrayOps$ofRef."<init>":([Ljava/lang/Object;)V
	ldc	class scala/Tuple2
	ldc	class scala/collection/mutable/HashMap
	aload_0
	invokevirtual	Method lang:()Lscala/util/regexp/WordExp;
	astore	6
	new	class scala/reflect/Manifest$$anon$15
	dup
	aload	6
	invokespecial	Method scala/reflect/Manifest$$anon$15."<init>":(Ljava/lang/Object;)V
	ldc	String _labelT
	aload_0
	invokevirtual	Method lang:()Lscala/util/regexp/WordExp;
	astore	7
	new	class scala/reflect/Manifest$$anon$15
	dup
	aload	7
	invokespecial	Method scala/reflect/Manifest$$anon$15."<init>":(Ljava/lang/Object;)V
	ldc	class scala/util/regexp/WordExp$Label
	getstatic	Field scala/Predef$.MODULE$:Lscala/Predef$;
	iconst_0
	anewarray	class scala/reflect/OptManifest
	checkcast	class "[Ljava/lang/Object;"
	invokevirtual	Method scala/Predef$.wrapRefArray:([Ljava/lang/Object;)Lscala/collection/mutable/WrappedArray;
	astore	10
	astore	9
	astore	8
	new	class scala/reflect/ClassManifest$ClassTypeManifest
	dup
	new	class scala/Some
	dup
	aload	8
	invokespecial	Method scala/Some."<init>":(Ljava/lang/Object;)V
	aload	9
	aload	10
	invokeinterface	InterfaceMethod scala/collection/TraversableLike.toList:()Lscala/collection/immutable/List;
	invokespecial	Method scala/reflect/ClassManifest$ClassTypeManifest."<init>":(Lscala/Option;Ljava/lang/Class;Lscala/collection/immutable/List;)V
	getstatic	Field scala/Predef$.MODULE$:Lscala/Predef$;
	iconst_0
	anewarray	class scala/reflect/OptManifest
	checkcast	class "[Ljava/lang/Object;"
	invokevirtual	Method scala/Predef$.wrapRefArray:([Ljava/lang/Object;)Lscala/collection/mutable/WrappedArray;
	astore	14
	astore	13
	astore	12
	astore	11
	new	class scala/reflect/ClassManifest$$anon$1
	dup
	aload	11
	aload	12
	aload	13
	aload	14
	invokespecial	Method scala/reflect/ClassManifest$$anon$1."<init>":(Lscala/reflect/OptManifest;Ljava/lang/String;Lscala/reflect/ClassManifest;Lscala/collection/Seq;)V
	getstatic	Field scala/Predef$.MODULE$:Lscala/Predef$;
	iconst_1
	anewarray	class scala/reflect/OptManifest
	dup
	iconst_0
	ldc	class scala/collection/immutable/List
	getstatic	Field scala/reflect/Manifest$.MODULE$:Lscala/reflect/Manifest$;
	invokevirtual	Method scala/reflect/Manifest$.Int:()Ljava/lang/Object;
	checkcast	class scala/reflect/OptManifest
	getstatic	Field scala/Predef$.MODULE$:Lscala/Predef$;
	iconst_0
	anewarray	class scala/reflect/OptManifest
	checkcast	class "[Ljava/lang/Object;"
	invokevirtual	Method scala/Predef$.wrapRefArray:([Ljava/lang/Object;)Lscala/collection/mutable/WrappedArray;
	astore	16
	astore	17
	astore	15
	new	class scala/reflect/ClassManifest$ClassTypeManifest
	dup
	getstatic	Field scala/None$.MODULE$:Lscala/None$;
	aload	15
	aload	16
	invokeinterface	InterfaceMethod scala/collection/TraversableLike.toList:()Lscala/collection/immutable/List;
	aload	17
	invokevirtual	Method scala/collection/immutable/List.$colon$colon:(Ljava/lang/Object;)Lscala/collection/immutable/List;
	invokespecial	Method scala/reflect/ClassManifest$ClassTypeManifest."<init>":(Lscala/Option;Ljava/lang/Class;Lscala/collection/immutable/List;)V
	aastore
	checkcast	class "[Ljava/lang/Object;"
	invokevirtual	Method scala/Predef$.wrapRefArray:([Ljava/lang/Object;)Lscala/collection/mutable/WrappedArray;
	astore	19
	astore	20
	astore	18
	new	class scala/reflect/ClassManifest$ClassTypeManifest
	dup
	getstatic	Field scala/None$.MODULE$:Lscala/None$;
	aload	18
	aload	19
	invokeinterface	InterfaceMethod scala/collection/TraversableLike.toList:()Lscala/collection/immutable/List;
	aload	20
	invokevirtual	Method scala/collection/immutable/List.$colon$colon:(Ljava/lang/Object;)Lscala/collection/immutable/List;
	invokespecial	Method scala/reflect/ClassManifest$ClassTypeManifest."<init>":(Lscala/Option;Ljava/lang/Class;Lscala/collection/immutable/List;)V
	getstatic	Field scala/Predef$.MODULE$:Lscala/Predef$;
	iconst_1
	anewarray	class scala/reflect/OptManifest
	dup
	iconst_0
	getstatic	Field scala/reflect/Manifest$.MODULE$:Lscala/reflect/Manifest$;
	invokevirtual	Method scala/reflect/Manifest$.Int:()Ljava/lang/Object;
	checkcast	class scala/reflect/OptManifest
	aastore
	checkcast	class "[Ljava/lang/Object;"
	invokevirtual	Method scala/Predef$.wrapRefArray:([Ljava/lang/Object;)Lscala/collection/mutable/WrappedArray;
	astore	22
	astore	23
	astore	21
	new	class scala/reflect/ClassManifest$ClassTypeManifest
	dup
	getstatic	Field scala/None$.MODULE$:Lscala/None$;
	aload	21
	aload	22
	invokeinterface	InterfaceMethod scala/collection/TraversableLike.toList:()Lscala/collection/immutable/List;
	aload	23
	invokevirtual	Method scala/collection/immutable/List.$colon$colon:(Ljava/lang/Object;)Lscala/collection/immutable/List;
	invokespecial	Method scala/reflect/ClassManifest$ClassTypeManifest."<init>":(Lscala/Option;Ljava/lang/Class;Lscala/collection/immutable/List;)V
	astore	24
	new	class scala/Array$$anon$2
	dup
	aload	24
	invokespecial	Method scala/Array$$anon$2."<init>":(Lscala/reflect/ClassManifest;)V
	invokeinterface	InterfaceMethod scala/collection/IndexedSeqLike.zipWithIndex:(Lscala/collection/generic/CanBuildFrom;)Ljava/lang/Object;
	checkcast	class "[Ljava/lang/Object;"
	astore	25
	new	class scala/collection/mutable/ArrayOps$ofRef
	dup
	aload	25
	invokespecial	Method scala/collection/mutable/ArrayOps$ofRef."<init>":([Ljava/lang/Object;)V
	new	class scala/util/automata/WordBerrySethi$$anonfun$1
	dup
	aload_0
	invokespecial	Method scala/util/automata/WordBerrySethi$$anonfun$1."<init>":(Lscala/util/automata/WordBerrySethi;)V
	getstatic	Field scala/Array$.MODULE$:Lscala/Array$;
	getstatic	Field scala/reflect/ClassManifest$.MODULE$:Lscala/reflect/ClassManifest$;
	ldc	class scala/Tuple2
	getstatic	Field scala/reflect/Manifest$.MODULE$:Lscala/reflect/Manifest$;
	invokevirtual	Method scala/reflect/Manifest$.Int:()Ljava/lang/Object;
	checkcast	class scala/reflect/OptManifest
	getstatic	Field scala/Predef$.MODULE$:Lscala/Predef$;
	iconst_1
	anewarray	class scala/reflect/OptManifest
	dup
	iconst_0
	getstatic	Field scala/reflect/ClassManifest$.MODULE$:Lscala/reflect/ClassManifest$;
	ldc	class scala/collection/mutable/HashMap
	getstatic	Field scala/reflect/ClassManifest$.MODULE$:Lscala/reflect/ClassManifest$;
	aload_0
	invokevirtual	Method lang:()Lscala/util/regexp/WordExp;
	astore	26
	new	class scala/reflect/Manifest$$anon$15
	dup
	aload	26
	invokespecial	Method scala/reflect/Manifest$$anon$15."<init>":(Ljava/lang/Object;)V
	ldc	String _labelT
	getstatic	Field scala/reflect/ClassManifest$.MODULE$:Lscala/reflect/ClassManifest$;
	aload_0
	invokevirtual	Method lang:()Lscala/util/regexp/WordExp;
	invokevirtual	Method scala/reflect/ClassManifest$.singleType:(Ljava/lang/Object;)Lscala/reflect/Manifest;
	ldc	class scala/util/regexp/WordExp$Label
	getstatic	Field scala/Predef$.MODULE$:Lscala/Predef$;
	iconst_0
	anewarray	class scala/reflect/OptManifest
	checkcast	class "[Ljava/lang/Object;"
	invokevirtual	Method scala/Predef$.wrapRefArray:([Ljava/lang/Object;)Lscala/collection/mutable/WrappedArray;
	astore	29
	astore	28
	astore	27
	new	class scala/reflect/ClassManifest$ClassTypeManifest
	dup
	new	class scala/Some
	dup
	aload	27
	invokespecial	Method scala/Some."<init>":(Ljava/lang/Object;)V
	aload	28
	aload	29
	invokeinterface	InterfaceMethod scala/collection/TraversableLike.toList:()Lscala/collection/immutable/List;
	invokespecial	Method scala/reflect/ClassManifest$ClassTypeManifest."<init>":(Lscala/Option;Ljava/lang/Class;Lscala/collection/immutable/List;)V
	getstatic	Field scala/Predef$.MODULE$:Lscala/Predef$;
	iconst_0
	anewarray	class scala/reflect/OptManifest
	checkcast	class "[Ljava/lang/Object;"
	invokevirtual	Method scala/Predef$.wrapRefArray:([Ljava/lang/Object;)Lscala/collection/mutable/WrappedArray;
	invokevirtual	Method scala/reflect/ClassManifest$.abstractType:(Lscala/reflect/OptManifest;Ljava/lang/String;Lscala/reflect/ClassManifest;Lscala/collection/Seq;)Lscala/reflect/ClassManifest;
	getstatic	Field scala/Predef$.MODULE$:Lscala/Predef$;
	iconst_1
	anewarray	class scala/reflect/OptManifest
	dup
	iconst_0
	getstatic	Field scala/reflect/ClassManifest$.MODULE$:Lscala/reflect/ClassManifest$;
	ldc	class scala/collection/immutable/List
	getstatic	Field scala/reflect/Manifest$.MODULE$:Lscala/reflect/Manifest$;
	invokevirtual	Method scala/reflect/Manifest$.Int:()Ljava/lang/Object;
	checkcast	class scala/reflect/OptManifest
	getstatic	Field scala/Predef$.MODULE$:Lscala/Predef$;
	iconst_0
	anewarray	class scala/reflect/OptManifest
	checkcast	class "[Ljava/lang/Object;"
	invokevirtual	Method scala/Predef$.wrapRefArray:([Ljava/lang/Object;)Lscala/collection/mutable/WrappedArray;
	invokevirtual	Method scala/reflect/ClassManifest$.classType:(Ljava/lang/Class;Lscala/reflect/OptManifest;Lscala/collection/Seq;)Lscala/reflect/ClassManifest;
	aastore
	checkcast	class "[Ljava/lang/Object;"
	invokevirtual	Method scala/Predef$.wrapRefArray:([Ljava/lang/Object;)Lscala/collection/mutable/WrappedArray;
	invokevirtual	Method scala/reflect/ClassManifest$.classType:(Ljava/lang/Class;Lscala/reflect/OptManifest;Lscala/collection/Seq;)Lscala/reflect/ClassManifest;
	aastore
	checkcast	class "[Ljava/lang/Object;"
	invokevirtual	Method scala/Predef$.wrapRefArray:([Ljava/lang/Object;)Lscala/collection/mutable/WrappedArray;
	invokevirtual	Method scala/reflect/ClassManifest$.classType:(Ljava/lang/Class;Lscala/reflect/OptManifest;Lscala/collection/Seq;)Lscala/reflect/ClassManifest;
	invokevirtual	Method scala/Array$.canBuildFrom:(Lscala/reflect/ClassManifest;)Lscala/collection/generic/CanBuildFrom;
	invokeinterface	InterfaceMethod scala/collection/TraversableLike.map:(Lscala/Function1;Lscala/collection/generic/CanBuildFrom;)Ljava/lang/Object;
	checkcast	class "[Lscala/Tuple2;"
	checkcast	class "[Ljava/lang/Object;"
	invokevirtual	Method scala/Predef$.wrapRefArray:([Ljava/lang/Object;)Lscala/collection/mutable/WrappedArray;
	invokevirtual	Method scala/collection/immutable/Map$.apply:(Lscala/collection/Seq;)Lscala/collection/Map;
	checkcast	class scala/collection/immutable/Map
	astore	30
	getstatic	Field scala/Predef$.MODULE$:Lscala/Predef$;
	iconst_0
	invokevirtual	Method scala/Predef$.intWrapper:(I)Lscala/runtime/RichInt;
	aload_0
	invokevirtual	Method pos:()I
	invokevirtual	Method scala/runtime/RichInt.until:(I)Lscala/collection/immutable/Range;
	new	class scala/util/automata/WordBerrySethi$$anonfun$2
	dup
	aload_0
	invokespecial	Method scala/util/automata/WordBerrySethi$$anonfun$2."<init>":(Lscala/util/automata/WordBerrySethi;)V
	getstatic	Field scala/collection/immutable/IndexedSeq$.MODULE$:Lscala/collection/immutable/IndexedSeq$;
	invokevirtual	Method scala/collection/immutable/IndexedSeq$.canBuildFrom:()Lscala/collection/generic/CanBuildFrom;
	invokeinterface	InterfaceMethod scala/collection/TraversableLike.map:(Lscala/Function1;Lscala/collection/generic/CanBuildFrom;)Ljava/lang/Object;
	checkcast	class scala/collection/TraversableLike
	getstatic	Field scala/reflect/Manifest$.MODULE$:Lscala/reflect/Manifest$;
	invokevirtual	Method scala/reflect/Manifest$.Int:()Ljava/lang/Object;
	checkcast	class scala/reflect/ClassManifest
	invokeinterface	InterfaceMethod scala/collection/TraversableLike.toArray:(Lscala/reflect/ClassManifest;)Ljava/lang/Object;
	checkcast	class "[I"
	astore	31
	aload_0
	invokevirtual	Method initials:()Lscala/collection/immutable/Set;
	getstatic	Field scala/reflect/Manifest$.MODULE$:Lscala/reflect/Manifest$;
	invokevirtual	Method scala/reflect/Manifest$.Int:()Ljava/lang/Object;
	checkcast	class scala/reflect/ClassManifest
	invokeinterface	InterfaceMethod scala/collection/TraversableLike.toArray:(Lscala/reflect/ClassManifest;)Ljava/lang/Object;
	checkcast	class "[I"
	astore	32
	getstatic	Field scala/Predef$.MODULE$:Lscala/Predef$;
	iconst_0
	invokevirtual	Method scala/Predef$.intWrapper:(I)Lscala/runtime/RichInt;
	aload_0
	invokevirtual	Method pos:()I
	invokevirtual	Method scala/runtime/RichInt.until:(I)Lscala/collection/immutable/Range;
	new	class scala/util/automata/WordBerrySethi$$anonfun$3
	dup
	aload_0
	aload	30
	invokespecial	Method scala/util/automata/WordBerrySethi$$anonfun$3."<init>":(Lscala/util/automata/WordBerrySethi;Lscala/collection/immutable/Map;)V
	getstatic	Field scala/collection/immutable/IndexedSeq$.MODULE$:Lscala/collection/immutable/IndexedSeq$;
	invokevirtual	Method scala/collection/immutable/IndexedSeq$.canBuildFrom:()Lscala/collection/generic/CanBuildFrom;
	invokeinterface	InterfaceMethod scala/collection/TraversableLike.map:(Lscala/Function1;Lscala/collection/generic/CanBuildFrom;)Ljava/lang/Object;
	checkcast	class scala/collection/TraversableLike
	getstatic	Field scala/reflect/ClassManifest$.MODULE$:Lscala/reflect/ClassManifest$;
	ldc_w	class scala/collection/Map
	getstatic	Field scala/reflect/ClassManifest$.MODULE$:Lscala/reflect/ClassManifest$;
	getstatic	Field scala/reflect/ClassManifest$.MODULE$:Lscala/reflect/ClassManifest$;
	aload_0
	invokevirtual	Method lang:()Lscala/util/regexp/WordExp;
	invokevirtual	Method scala/reflect/ClassManifest$.singleType:(Ljava/lang/Object;)Lscala/reflect/Manifest;
	ldc	String _labelT
	getstatic	Field scala/reflect/ClassManifest$.MODULE$:Lscala/reflect/ClassManifest$;
	getstatic	Field scala/reflect/ClassManifest$.MODULE$:Lscala/reflect/ClassManifest$;
	aload_0
	invokevirtual	Method lang:()Lscala/util/regexp/WordExp;
	invokevirtual	Method scala/reflect/ClassManifest$.singleType:(Ljava/lang/Object;)Lscala/reflect/Manifest;
	ldc	class scala/util/regexp/WordExp$Label
	getstatic	Field scala/Predef$.MODULE$:Lscala/Predef$;
	iconst_0
	anewarray	class scala/reflect/OptManifest
	checkcast	class "[Ljava/lang/Object;"
	invokevirtual	Method scala/Predef$.wrapRefArray:([Ljava/lang/Object;)Lscala/collection/mutable/WrappedArray;
	invokevirtual	Method scala/reflect/ClassManifest$.classType:(Lscala/reflect/OptManifest;Ljava/lang/Class;Lscala/collection/Seq;)Lscala/reflect/ClassManifest;
	getstatic	Field scala/Predef$.MODULE$:Lscala/Predef$;
	iconst_0
	anewarray	class scala/reflect/OptManifest
	checkcast	class "[Ljava/lang/Object;"
	invokevirtual	Method scala/Predef$.wrapRefArray:([Ljava/lang/Object;)Lscala/collection/mutable/WrappedArray;
	invokevirtual	Method scala/reflect/ClassManifest$.abstractType:(Lscala/reflect/OptManifest;Ljava/lang/String;Lscala/reflect/ClassManifest;Lscala/collection/Seq;)Lscala/reflect/ClassManifest;
	getstatic	Field scala/Predef$.MODULE$:Lscala/Predef$;
	iconst_1
	anewarray	class scala/reflect/OptManifest
	dup
	iconst_0
	getstatic	Field scala/reflect/ClassManifest$.MODULE$:Lscala/reflect/ClassManifest$;
	ldc_w	class scala/collection/immutable/BitSet
	invokevirtual	Method scala/reflect/ClassManifest$.classType:(Ljava/lang/Class;)Lscala/reflect/ClassManifest;
	aastore
	checkcast	class "[Ljava/lang/Object;"
	invokevirtual	Method scala/Predef$.wrapRefArray:([Ljava/lang/Object;)Lscala/collection/mutable/WrappedArray;
	invokevirtual	Method scala/reflect/ClassManifest$.classType:(Ljava/lang/Class;Lscala/reflect/OptManifest;Lscala/collection/Seq;)Lscala/reflect/ClassManifest;
	invokeinterface	InterfaceMethod scala/collection/TraversableLike.toArray:(Lscala/reflect/ClassManifest;)Ljava/lang/Object;
	checkcast	class "[Lscala/collection/Map;"
	astore	33
	getstatic	Field scala/Predef$.MODULE$:Lscala/Predef$;
	iconst_0
	invokevirtual	Method scala/Predef$.intWrapper:(I)Lscala/runtime/RichInt;
	aload_0
	invokevirtual	Method pos:()I
	invokevirtual	Method scala/runtime/RichInt.until:(I)Lscala/collection/immutable/Range;
	new	class scala/util/automata/WordBerrySethi$$anonfun$4
	dup
	aload_0
	invokespecial	Method scala/util/automata/WordBerrySethi$$anonfun$4."<init>":(Lscala/util/automata/WordBerrySethi;)V
	getstatic	Field scala/collection/immutable/IndexedSeq$.MODULE$:Lscala/collection/immutable/IndexedSeq$;
	invokevirtual	Method scala/collection/immutable/IndexedSeq$.canBuildFrom:()Lscala/collection/generic/CanBuildFrom;
	invokeinterface	InterfaceMethod scala/collection/TraversableLike.map:(Lscala/Function1;Lscala/collection/generic/CanBuildFrom;)Ljava/lang/Object;
	checkcast	class scala/collection/TraversableLike
	getstatic	Field scala/reflect/ClassManifest$.MODULE$:Lscala/reflect/ClassManifest$;
	ldc_w	class scala/collection/immutable/BitSet
	invokevirtual	Method scala/reflect/ClassManifest$.classType:(Ljava/lang/Class;)Lscala/reflect/ClassManifest;
	invokeinterface	InterfaceMethod scala/collection/TraversableLike.toArray:(Lscala/reflect/ClassManifest;)Ljava/lang/Object;
	checkcast	class "[Lscala/collection/immutable/BitSet;"
	astore	34
	new	class scala/util/automata/WordBerrySethi$$anon$1
	dup
	aload_0
	aload	31
	aload	32
	aload	33
	aload	34
	invokespecial	Method scala/util/automata/WordBerrySethi$$anon$1."<init>":(Lscala/util/automata/WordBerrySethi;[I[I[Lscala/collection/Map;[Lscala/collection/immutable/BitSet;)V
	goto	l4 // areturn
l2	new	class scala/MatchError
	dup
	aload_1
	invokevirtual	Method scala/util/regexp/Base$RegExp.toString:()Ljava/lang/String;
	invokespecial	Method scala/MatchError."<init>":(Ljava/lang/String;)V
	athrow
l1	iconst_1
	ifeq	l5 // new
	aload_0
	aload_0
	invokevirtual	Method lang:()Lscala/util/regexp/WordExp;
	invokevirtual	Method scala/util/regexp/WordExp.Sequ:()Lscala/util/regexp/Base$Sequ$;
	getstatic	Field scala/Predef$.MODULE$:Lscala/Predef$;
	iconst_1
	anewarray	class scala/util/regexp/Base$RegExp
	dup
	iconst_0
	aload_1
	aastore
	checkcast	class "[Ljava/lang/Object;"
	invokevirtual	Method scala/Predef$.wrapRefArray:([Ljava/lang/Object;)Lscala/collection/mutable/WrappedArray;
	invokevirtual	Method scala/util/regexp/Base$Sequ$.apply:(Lscala/collection/Seq;)Lscala/util/regexp/Base$RegExp;
	iload_2
	invokevirtual	Method automatonFrom:(Lscala/util/regexp/Base$RegExp;I)Lscala/util/automata/NondetWordAutom;
l4	areturn
l5	new	class scala/MatchError
	dup
	aload_1
	invokevirtual	Method scala/util/regexp/Base$RegExp.toString:()Ljava/lang/String;
	invokespecial	Method scala/MatchError."<init>":(Ljava/lang/String;)V
	athrow
  Labels:
   	l3 = 88 // getstatic
   	l2 = 926 // new
   	l1 = 938 // iconst_1
   	l4 = 974 // areturn
   	l5 = 975 // new
  LocalVariableTable: 
   Start  Length  Slot  Name   Signature
   0      987      0    this       Lscala/util/automata/WordBerrySethi;
   0      987      1    pat       Lscala/util/regexp/Base$RegExp;
   0      987      2    finalTag       I
   17      921      3    temp20       Lscala/util/regexp/Base$Sequ;
   630      293      30    delta1$1       Lscala/collection/immutable/Map;
   685      238      31    finalsArr$1       [I
   708      215      32    initialsArr$1       [I
   852      71      33    deltaArr$1       [Lscala/collection/Map;
   907      16      34    defaultArr$1       [Lscala/collection/immutable/BitSet;

  Signature: length = 0x2
   01 40 

public void collectTransitions();
  Signature: ()V
  Code:
   Stack=4, Locals=1, Args_size=1
	getstatic	Field scala/Predef$.MODULE$:Lscala/Predef$;
	iconst_0
	invokevirtual	Method scala/Predef$.intWrapper:(I)Lscala/runtime/RichInt;
	aload_0
	invokevirtual	Method pos:()I
	invokevirtual	Method scala/runtime/RichInt.until:(I)Lscala/collection/immutable/Range;
	new	class scala/util/automata/WordBerrySethi$$anonfun$collectTransitions$1
	dup
	aload_0
	invokespecial	Method scala/util/automata/WordBerrySethi$$anonfun$collectTransitions$1."<init>":(Lscala/util/automata/WordBerrySethi;)V
	getstatic	Field scala/collection/immutable/IndexedSeq$.MODULE$:Lscala/collection/immutable/IndexedSeq$;
	invokevirtual	Method scala/collection/immutable/IndexedSeq$.canBuildFrom:()Lscala/collection/generic/CanBuildFrom;
	invokeinterface	InterfaceMethod scala/collection/TraversableLike.map:(Lscala/Function1;Lscala/collection/generic/CanBuildFrom;)Ljava/lang/Object;
	checkcast	class scala/collection/IndexedSeqLike
	new	class scala/util/automata/WordBerrySethi$$anonfun$collectTransitions$2
	dup
	aload_0
	invokespecial	Method scala/util/automata/WordBerrySethi$$anonfun$collectTransitions$2."<init>":(Lscala/util/automata/WordBerrySethi;)V
	invokeinterface	InterfaceMethod scala/collection/IndexedSeqLike.foreach:(Lscala/Function1;)V
	return
  Labels:

public void initializeAutom();
  Signature: ()V
  Code:
   Stack=4, Locals=1, Args_size=1
	aload_0
	getstatic	Field scala/collection/immutable/Map$.MODULE$:Lscala/collection/immutable/Map$;
	invokevirtual	Method scala/collection/immutable/Map$.empty:()Lscala/collection/immutable/Map;
	invokevirtual	Method finals_$eq:(Lscala/collection/immutable/Map;)V
	aload_0
	aload_0
	invokevirtual	Method pos:()I
	anewarray	class scala/collection/mutable/HashMap
	invokevirtual	Method deltaq_$eq:([Lscala/collection/mutable/HashMap;)V
	aload_0
	aload_0
	invokevirtual	Method pos:()I
	anewarray	class scala/collection/immutable/List
	invokevirtual	Method defaultq_$eq:([Lscala/collection/immutable/List;)V
	getstatic	Field scala/Predef$.MODULE$:Lscala/Predef$;
	iconst_0
	invokevirtual	Method scala/Predef$.intWrapper:(I)Lscala/runtime/RichInt;
	aload_0
	invokevirtual	Method pos:()I
	invokevirtual	Method scala/runtime/RichInt.until:(I)Lscala/collection/immutable/Range;
	checkcast	class scala/collection/immutable/Range$ByOne
	new	class scala/util/automata/WordBerrySethi$$anonfun$initializeAutom$1
	dup
	aload_0
	invokespecial	Method scala/util/automata/WordBerrySethi$$anonfun$initializeAutom$1."<init>":(Lscala/util/automata/WordBerrySethi;)V
	invokeinterface	InterfaceMethod scala/collection/immutable/Range$ByOne.foreach:(Lscala/Function1;)V
	return
  Labels:

public void initialize(scala.collection.Seq);
  Signature: (Lscala/collection/Seq;)V
  Code:
   Stack=7, Locals=2, Args_size=2
	aload_0
	getstatic	Field scala/collection/immutable/Map$.MODULE$:Lscala/collection/immutable/Map$;
	getstatic	Field scala/Predef$.MODULE$:Lscala/Predef$;
	iconst_0
	anewarray	class scala/Tuple2
	checkcast	class "[Ljava/lang/Object;"
	invokevirtual	Method scala/Predef$.wrapRefArray:([Ljava/lang/Object;)Lscala/collection/mutable/WrappedArray;
	invokevirtual	Method scala/collection/immutable/Map$.apply:(Lscala/collection/Seq;)Lscala/collection/Map;
	checkcast	class scala/collection/immutable/Map
	invokevirtual	Method labelAt_$eq:(Lscala/collection/immutable/Map;)V
	aload_0
	getstatic	Field scala/collection/mutable/HashMap$.MODULE$:Lscala/collection/mutable/HashMap$;
	getstatic	Field scala/Predef$.MODULE$:Lscala/Predef$;
	iconst_0
	anewarray	class scala/Tuple2
	checkcast	class "[Ljava/lang/Object;"
	invokevirtual	Method scala/Predef$.wrapRefArray:([Ljava/lang/Object;)Lscala/collection/mutable/WrappedArray;
	invokevirtual	Method scala/collection/mutable/HashMap$.apply:(Lscala/collection/Seq;)Lscala/collection/Map;
	checkcast	class scala/collection/mutable/HashMap
	invokevirtual	Method follow_$eq:(Lscala/collection/mutable/HashMap;)V
	aload_0
	getstatic	Field scala/collection/mutable/HashSet$.MODULE$:Lscala/collection/mutable/HashSet$;
	getstatic	Field scala/Predef$.MODULE$:Lscala/Predef$;
	iconst_0
	anewarray	class scala/util/regexp/WordExp$Label
	checkcast	class "[Ljava/lang/Object;"
	invokevirtual	Method scala/Predef$.wrapRefArray:([Ljava/lang/Object;)Lscala/collection/mutable/WrappedArray;
	invokevirtual	Method scala/collection/mutable/HashSet$.apply:(Lscala/collection/Seq;)Lscala/collection/Traversable;
	checkcast	class scala/collection/mutable/HashSet
	invokevirtual	Method labels_$eq:(Lscala/collection/mutable/HashSet;)V
	aload_0
	iconst_0
	invokevirtual	Method pos_$eq:(I)V
	aload_1
	new	class scala/util/automata/WordBerrySethi$$anonfun$initialize$1
	dup
	aload_0
	invokespecial	Method scala/util/automata/WordBerrySethi$$anonfun$initialize$1."<init>":(Lscala/util/automata/WordBerrySethi;)V
	invokeinterface	InterfaceMethod scala/collection/IterableLike.foreach:(Lscala/Function1;)V
	aload_0
	getstatic	Field scala/collection/immutable/Set$.MODULE$:Lscala/collection/immutable/Set$;
	getstatic	Field scala/Predef$.MODULE$:Lscala/Predef$;
	iconst_1
	newarray int
	dup
	iconst_0
	iconst_0
	iastore
	invokevirtual	Method scala/Predef$.wrapIntArray:([I)Lscala/collection/mutable/WrappedArray;
	invokevirtual	Method scala/collection/immutable/Set$.apply:(Lscala/collection/Seq;)Lscala/collection/Traversable;
	checkcast	class scala/collection/immutable/Set
	invokevirtual	Method initials_$eq:(Lscala/collection/immutable/Set;)V
	return
  Labels:
  LocalVariableTable: 
   Start  Length  Slot  Name   Signature
   0      124      0    this       Lscala/util/automata/WordBerrySethi;
   0      124      1    subexpr       Lscala/collection/Seq;

  Signature: length = 0x2
   01 FFFFFF8F 

public void makeTransition(int, int, scala.util.regexp.WordExp$Label);
  Signature: (IILscala/util/regexp/WordExp$Label;)V
  Code:
   Stack=7, Locals=5, Args_size=4
	aload_0
	invokevirtual	Method deltaq:()[Lscala/collection/mutable/HashMap;
	iload_1
	aaload
	astore	4
	aload	4
	aload_3
	aload	4
	aload_3
	new	class scala/util/automata/WordBerrySethi$$anonfun$makeTransition$1
	dup
	aload_0
	invokespecial	Method scala/util/automata/WordBerrySethi$$anonfun$makeTransition$1."<init>":(Lscala/util/automata/WordBerrySethi;)V
	invokeinterface	InterfaceMethod scala/collection/MapLike.getOrElse:(Ljava/lang/Object;Lscala/Function0;)Ljava/lang/Object;
	checkcast	class scala/collection/immutable/List
	iload_2
	invokestatic	Method scala/runtime/BoxesRunTime.boxToInteger:(I)Ljava/lang/Integer;
	invokevirtual	Method scala/collection/immutable/List.$colon$colon:(Ljava/lang/Object;)Lscala/collection/immutable/List;
	invokevirtual	Method scala/collection/mutable/HashMap.update:(Ljava/lang/Object;Ljava/lang/Object;)V
	return
  Labels:
  LocalVariableTable: 
   Start  Length  Slot  Name   Signature
   0      41      0    this       Lscala/util/automata/WordBerrySethi;
   0      41      1    src       I
   0      41      2    dest       I
   0      41      3    label       Lscala/util/regexp/WordExp$Label;
   8      32      4    q       Lscala/collection/mutable/HashMap;


public void traverse(scala.util.regexp.Base$RegExp);
  Signature: (Lscala/util/regexp/Base$RegExp;)V
  Code:
   Stack=4, Locals=5, Args_size=2
	aload_1
	instanceof	class scala/util/regexp/WordExp$Letter
	ifeq	l1 // aload_1
	aload_1
	checkcast	class scala/util/regexp/WordExp$Letter
	astore_2
	aload_2
	invokevirtual	Method scala/util/regexp/WordExp$Letter.a:()Lscala/util/regexp/WordExp$Label;
	astore_3
	iconst_1
	ifeq	l2 // new
	aload_2
	aload_0
	aload_1
	aload_3
	invokevirtual	Method seenLabel:(Lscala/util/regexp/Base$RegExp;Lscala/util/regexp/WordExp$Label;)I
	invokevirtual	Method scala/util/regexp/WordExp$Letter.pos_$eq:(I)V
	goto	l3 // return
l2	new	class scala/MatchError
	dup
	aload_1
	invokevirtual	Method scala/util/regexp/Base$RegExp.toString:()Ljava/lang/String;
	invokespecial	Method scala/MatchError."<init>":(Ljava/lang/String;)V
	athrow
l1	aload_1
	aload_0
	invokevirtual	Method lang:()Lscala/util/regexp/WordExp;
	invokevirtual	Method scala/util/regexp/WordExp.Eps:()Lscala/util/regexp/Base$Eps$;
	astore	4
	dup
	ifnonnull	l4 // aload
	pop
	aload	4
	ifnull	l5 // iconst_1
	goto	l6 // iconst_1
l4	aload	4
	invokevirtual	Method java/lang/Object.equals:(Ljava/lang/Object;)Z
	ifeq	l6 // iconst_1
l5	iconst_1
	ifne	l3 // return
	new	class scala/MatchError
	dup
	aload_1
	invokevirtual	Method scala/util/regexp/Base$RegExp.toString:()Ljava/lang/String;
	invokespecial	Method scala/MatchError."<init>":(Ljava/lang/String;)V
	athrow
l6	iconst_1
	ifeq	l7 // new
	aload_0
	aload_1
	invokespecial	Method scala/util/automata/BaseBerrySethi.traverse:(Lscala/util/regexp/Base$RegExp;)V
l3	return
l7	new	class scala/MatchError
	dup
	aload_1
	invokevirtual	Method scala/util/regexp/Base$RegExp.toString:()Ljava/lang/String;
	invokespecial	Method scala/MatchError."<init>":(Ljava/lang/String;)V
	athrow
  Labels:
   	l2 = 34 // new
   	l1 = 46 // aload_1
   	l4 = 69 // aload
   	l5 = 77 // iconst_1
   	l6 = 93 // iconst_1
   	l3 = 102 // return
   	l7 = 103 // new
  LocalVariableTable: 
   Start  Length  Slot  Name   Signature
   0      115      0    this       Lscala/util/automata/WordBerrySethi;
   0      115      1    r       Lscala/util/regexp/Base$RegExp;
   12      34      2    temp11       Lscala/util/regexp/WordExp$Letter;
   17      29      3    temp12       Lscala/util/regexp/WordExp$Label;


public int seenLabel(scala.util.regexp.Base$RegExp, scala.util.regexp.WordExp$Label);
  Signature: (Lscala/util/regexp/Base$RegExp;Lscala/util/regexp/WordExp$Label;)I
  Code:
   Stack=4, Locals=3, Args_size=3
	aload_0
	aload_0
	invokevirtual	Method pos:()I
	iconst_1
	iadd
	invokevirtual	Method pos_$eq:(I)V
	aload_0
	aload_1
	aload_0
	invokevirtual	Method pos:()I
	aload_2
	invokevirtual	Method seenLabel:(Lscala/util/regexp/Base$RegExp;ILscala/util/regexp/WordExp$Label;)V
	aload_0
	invokevirtual	Method pos:()I
	ireturn
  Labels:
  LocalVariableTable: 
   Start  Length  Slot  Name   Signature
   0      25      0    this       Lscala/util/automata/WordBerrySethi;
   0      25      1    r       Lscala/util/regexp/Base$RegExp;
   0      25      2    label       Lscala/util/regexp/WordExp$Label;


public void seenLabel(scala.util.regexp.Base$RegExp, int, scala.util.regexp.WordExp$Label);
  Signature: (Lscala/util/regexp/Base$RegExp;ILscala/util/regexp/WordExp$Label;)V
  Code:
   Stack=4, Locals=4, Args_size=4
	aload_0
	aload_0
	invokevirtual	Method labelAt:()Lscala/collection/immutable/Map;
	iload_2
	invokestatic	Method scala/runtime/BoxesRunTime.boxToInteger:(I)Ljava/lang/Integer;
	aload_3
	invokeinterface	InterfaceMethod scala/collection/immutable/MapLike.updated:(Ljava/lang/Object;Ljava/lang/Object;)Lscala/collection/immutable/Map;
	invokevirtual	Method labelAt_$eq:(Lscala/collection/immutable/Map;)V
	aload_0
	invokevirtual	Method labels:()Lscala/collection/mutable/HashSet;
	aload_3
	invokevirtual	Method scala/collection/mutable/HashSet.$plus$eq:(Ljava/lang/Object;)Lscala/collection/mutable/HashSet;
	pop
	return
  Labels:
  LocalVariableTable: 
   Start  Length  Slot  Name   Signature
   0      28      0    this       Lscala/util/automata/WordBerrySethi;
   0      28      1    r       Lscala/util/regexp/Base$RegExp;
   0      28      2    i       I
   0      28      3    label       Lscala/util/regexp/WordExp$Label;


public scala.collection.immutable.Set compFollow1(scala.collection.immutable.Set, scala.util.regexp.Base$RegExp);
  Signature: (Lscala/collection/immutable/Set;Lscala/util/regexp/Base$RegExp;)Lscala/collection/immutable/Set;
  Code:
   Stack=6, Locals=6, Args_size=3
	aload_2
	instanceof	class scala/util/regexp/WordExp$Letter
	ifeq	l1 // aload_2
	aload_2
	checkcast	class scala/util/regexp/WordExp$Letter
	astore	4
	iconst_1
	ifeq	l2 // new
	aload_0
	invokevirtual	Method follow:()Lscala/collection/mutable/HashMap;
	aload	4
	invokevirtual	Method scala/util/regexp/WordExp$Letter.pos:()I
	istore_3
	iload_3
	invokestatic	Method scala/runtime/BoxesRunTime.boxToInteger:(I)Ljava/lang/Integer;
	aload_1
	invokevirtual	Method scala/collection/mutable/HashMap.update:(Ljava/lang/Object;Ljava/lang/Object;)V
	getstatic	Field scala/collection/immutable/Set$.MODULE$:Lscala/collection/immutable/Set$;
	getstatic	Field scala/Predef$.MODULE$:Lscala/Predef$;
	iconst_1
	newarray int
	dup
	iconst_0
	aload	4
	invokevirtual	Method scala/util/regexp/WordExp$Letter.pos:()I
	iastore
	invokevirtual	Method scala/Predef$.wrapIntArray:([I)Lscala/collection/mutable/WrappedArray;
	invokevirtual	Method scala/collection/immutable/Set$.apply:(Lscala/collection/Seq;)Lscala/collection/Traversable;
	checkcast	class scala/collection/immutable/Set
	goto	l3 // areturn
l2	new	class scala/MatchError
	dup
	aload_2
	invokevirtual	Method scala/util/regexp/Base$RegExp.toString:()Ljava/lang/String;
	invokespecial	Method scala/MatchError."<init>":(Ljava/lang/String;)V
	athrow
l1	aload_2
	aload_0
	invokevirtual	Method lang:()Lscala/util/regexp/WordExp;
	invokevirtual	Method scala/util/regexp/WordExp.Eps:()Lscala/util/regexp/Base$Eps$;
	astore	5
	dup
	ifnonnull	l4 // aload
	pop
	aload	5
	ifnull	l5 // iconst_1
	goto	l6 // iconst_1
l4	aload	5
	invokevirtual	Method java/lang/Object.equals:(Ljava/lang/Object;)Z
	ifeq	l6 // iconst_1
l5	iconst_1
	ifeq	l7 // new
	aload_0
	invokevirtual	Method emptySet:()Lscala/collection/immutable/Set;
	goto	l3 // areturn
l7	new	class scala/MatchError
	dup
	aload_2
	invokevirtual	Method scala/util/regexp/Base$RegExp.toString:()Ljava/lang/String;
	invokespecial	Method scala/MatchError."<init>":(Ljava/lang/String;)V
	athrow
l6	iconst_1
	ifeq	l8 // new
	aload_0
	aload_1
	aload_2
	invokespecial	Method scala/util/automata/BaseBerrySethi.compFollow1:(Lscala/collection/immutable/Set;Lscala/util/regexp/Base$RegExp;)Lscala/collection/immutable/Set;
l3	areturn
l8	new	class scala/MatchError
	dup
	aload_2
	invokevirtual	Method scala/util/regexp/Base$RegExp.toString:()Ljava/lang/String;
	invokespecial	Method scala/MatchError."<init>":(Ljava/lang/String;)V
	athrow
  Labels:
   	l2 = 64 // new
   	l1 = 76 // aload_2
   	l4 = 99 // aload
   	l5 = 107 // iconst_1
   	l7 = 118 // new
   	l6 = 130 // iconst_1
   	l3 = 140 // areturn
   	l8 = 141 // new
  LocalVariableTable: 
   Start  Length  Slot  Name   Signature
   0      153      0    this       Lscala/util/automata/WordBerrySethi;
   0      153      1    fol1       Lscala/collection/immutable/Set;
   0      153      2    r       Lscala/util/regexp/Base$RegExp;
   13      63      4    temp8       Lscala/util/regexp/WordExp$Letter;

  Signature: length = 0x2
   01 FFFFFFDD 

public scala.collection.immutable.Set compLast(scala.util.regexp.Base$RegExp);
  Signature: (Lscala/util/regexp/Base$RegExp;)Lscala/collection/immutable/Set;
  Code:
   Stack=6, Locals=3, Args_size=2
	aload_1
	instanceof	class scala/util/regexp/WordExp$Letter
	ifeq	l1 // iconst_1
	aload_1
	checkcast	class scala/util/regexp/WordExp$Letter
	astore_2
	iconst_1
	ifeq	l2 // new
	getstatic	Field scala/collection/immutable/Set$.MODULE$:Lscala/collection/immutable/Set$;
	getstatic	Field scala/Predef$.MODULE$:Lscala/Predef$;
	iconst_1
	newarray int
	dup
	iconst_0
	aload_2
	invokevirtual	Method scala/util/regexp/WordExp$Letter.pos:()I
	iastore
	invokevirtual	Method scala/Predef$.wrapIntArray:([I)Lscala/collection/mutable/WrappedArray;
	invokevirtual	Method scala/collection/immutable/Set$.apply:(Lscala/collection/Seq;)Lscala/collection/Traversable;
	checkcast	class scala/collection/immutable/Set
	goto	l3 // areturn
l2	new	class scala/MatchError
	dup
	aload_1
	invokevirtual	Method scala/util/regexp/Base$RegExp.toString:()Ljava/lang/String;
	invokespecial	Method scala/MatchError."<init>":(Ljava/lang/String;)V
	athrow
l1	iconst_1
	ifeq	l4 // new
	aload_0
	aload_1
	invokespecial	Method scala/util/automata/BaseBerrySethi.compLast:(Lscala/util/regexp/Base$RegExp;)Lscala/collection/immutable/Set;
l3	areturn
l4	new	class scala/MatchError
	dup
	aload_1
	invokevirtual	Method scala/util/regexp/Base$RegExp.toString:()Ljava/lang/String;
	invokespecial	Method scala/MatchError."<init>":(Ljava/lang/String;)V
	athrow
  Labels:
   	l2 = 44 // new
   	l1 = 56 // iconst_1
   	l3 = 65 // areturn
   	l4 = 66 // new
  LocalVariableTable: 
   Start  Length  Slot  Name   Signature
   0      78      0    this       Lscala/util/automata/WordBerrySethi;
   0      78      1    r       Lscala/util/regexp/Base$RegExp;
   12      44      2    temp5       Lscala/util/regexp/WordExp$Letter;

  Signature: length = 0x2
   01 FFFFFFE3 

public scala.collection.immutable.Set compFirst(scala.util.regexp.Base$RegExp);
  Signature: (Lscala/util/regexp/Base$RegExp;)Lscala/collection/immutable/Set;
  Code:
   Stack=6, Locals=3, Args_size=2
	aload_1
	instanceof	class scala/util/regexp/WordExp$Letter
	ifeq	l1 // iconst_1
	aload_1
	checkcast	class scala/util/regexp/WordExp$Letter
	astore_2
	iconst_1
	ifeq	l2 // new
	getstatic	Field scala/collection/immutable/Set$.MODULE$:Lscala/collection/immutable/Set$;
	getstatic	Field scala/Predef$.MODULE$:Lscala/Predef$;
	iconst_1
	newarray int
	dup
	iconst_0
	aload_2
	invokevirtual	Method scala/util/regexp/WordExp$Letter.pos:()I
	iastore
	invokevirtual	Method scala/Predef$.wrapIntArray:([I)Lscala/collection/mutable/WrappedArray;
	invokevirtual	Method scala/collection/immutable/Set$.apply:(Lscala/collection/Seq;)Lscala/collection/Traversable;
	checkcast	class scala/collection/immutable/Set
	goto	l3 // areturn
l2	new	class scala/MatchError
	dup
	aload_1
	invokevirtual	Method scala/util/regexp/Base$RegExp.toString:()Ljava/lang/String;
	invokespecial	Method scala/MatchError."<init>":(Ljava/lang/String;)V
	athrow
l1	iconst_1
	ifeq	l4 // new
	aload_0
	aload_1
	invokespecial	Method scala/util/automata/BaseBerrySethi.compFirst:(Lscala/util/regexp/Base$RegExp;)Lscala/collection/immutable/Set;
l3	areturn
l4	new	class scala/MatchError
	dup
	aload_1
	invokevirtual	Method scala/util/regexp/Base$RegExp.toString:()Ljava/lang/String;
	invokespecial	Method scala/MatchError."<init>":(Ljava/lang/String;)V
	athrow
  Labels:
   	l2 = 44 // new
   	l1 = 56 // iconst_1
   	l3 = 65 // areturn
   	l4 = 66 // new
  LocalVariableTable: 
   Start  Length  Slot  Name   Signature
   0      78      0    this       Lscala/util/automata/WordBerrySethi;
   0      78      1    r       Lscala/util/regexp/Base$RegExp;
   12      44      2    temp2       Lscala/util/regexp/WordExp$Letter;

  Signature: length = 0x2
   01 FFFFFFE3 

public void initials_$eq(scala.collection.immutable.Set);
  Signature: (Lscala/collection/immutable/Set;)V
  Code:
   Stack=2, Locals=2, Args_size=2
	aload_0
	aload_1
	putfield	Field initials:Lscala/collection/immutable/Set;
	return
  Labels:
  Signature: length = 0x2
   01 FFFFFFEA 

public scala.collection.immutable.Set initials();
  Signature: ()Lscala/collection/immutable/Set;
  Code:
   Stack=1, Locals=1, Args_size=1
	aload_0
	getfield	Field initials:Lscala/collection/immutable/Set;
	areturn
  Labels:
  Signature: length = 0x2
   01 FFFFFFEB 

public void defaultq_$eq(scala.collection.immutable.List[]);
  Signature: ([Lscala/collection/immutable/List;)V
  Code:
   Stack=2, Locals=2, Args_size=2
	aload_0
	aload_1
	putfield	Field defaultq:[Lscala/collection/immutable/List;
	return
  Labels:
  Signature: length = 0x2
   01 FFFFFFEE 

public scala.collection.immutable.List[] defaultq();
  Signature: ()[Lscala/collection/immutable/List;
  Code:
   Stack=1, Locals=1, Args_size=1
	aload_0
	getfield	Field defaultq:[Lscala/collection/immutable/List;
	areturn
  Labels:
  Signature: length = 0x2
   01 FFFFFFF0 

public void deltaq_$eq(scala.collection.mutable.HashMap[]);
  Signature: ([Lscala/collection/mutable/HashMap;)V
  Code:
   Stack=2, Locals=2, Args_size=2
	aload_0
	aload_1
	putfield	Field deltaq:[Lscala/collection/mutable/HashMap;
	return
  Labels:
  Signature: length = 0x2
   01 FFFFFFF3 

public scala.collection.mutable.HashMap[] deltaq();
  Signature: ()[Lscala/collection/mutable/HashMap;
  Code:
   Stack=1, Locals=1, Args_size=1
	aload_0
	getfield	Field deltaq:[Lscala/collection/mutable/HashMap;
	areturn
  Labels:
  Signature: length = 0x2
   01 FFFFFFF4 

public void labelAt_$eq(scala.collection.immutable.Map);
  Signature: (Lscala/collection/immutable/Map;)V
  Code:
   Stack=2, Locals=2, Args_size=2
	aload_0
	aload_1
	putfield	Field labelAt:Lscala/collection/immutable/Map;
	return
  Labels:
  Signature: length = 0x2
   01 FFFFFFF7 

public scala.collection.immutable.Map labelAt();
  Signature: ()Lscala/collection/immutable/Map;
  Code:
   Stack=1, Locals=1, Args_size=1
	aload_0
	getfield	Field labelAt:Lscala/collection/immutable/Map;
	areturn
  Labels:
  Signature: length = 0x2
   01 FFFFFFF8 

public void labels_$eq(scala.collection.mutable.HashSet);
  Signature: (Lscala/collection/mutable/HashSet;)V
  Code:
   Stack=2, Locals=2, Args_size=2
	aload_0
	aload_1
	putfield	Field labels:Lscala/collection/mutable/HashSet;
	return
  Labels:
  Signature: length = 0x2
   01 FFFFFFFB 

public scala.collection.mutable.HashSet labels();
  Signature: ()Lscala/collection/mutable/HashSet;
  Code:
   Stack=1, Locals=1, Args_size=1
	aload_0
	getfield	Field labels:Lscala/collection/mutable/HashSet;
	areturn
  Labels:
  Signature: length = 0x2
   01 FFFFFFFC 

public abstract scala.util.regexp.WordExp lang();
  Signature: ()Lscala/util/regexp/WordExp;

}

