Compiled from "WordBerrySethi.scala"
public final class scala.util.automata.WordBerrySethi$$anon$1 extends scala.util.automata.NondetWordAutom
  SourceFile: "WordBerrySethi.scala"
  Signature: length = 0x2
   00 44 
  Scala: length = 0x
   
  InnerClass: 
   public final $anon$1=class scala/util/automata/WordBerrySethi$$anon$1 of class scala/util/automata/WordBerrySethi
  minor version: 0
  major version: 49
  Constant pool:
Asciz	SourceFile;
Asciz	WordBerrySethi.scala;
Asciz	default;
Asciz	[Lscala/collection/immutable/BitSet;;
Asciz	delta;
Asciz	[Lscala/collection/Map;;
Asciz	[Lscala/collection/Map<Lscala/util/regexp/WordExp$Label;Lscala/collection/immutable/BitSet;>;;
Asciz	Signature;
Asciz	finals;
Asciz	[I;
Asciz	initials;
Asciz	labels;
Asciz	Lscala/collection/immutable/List;;
Asciz	Lscala/collection/immutable/List<Lscala/util/regexp/WordExp$Label;>;;
Asciz	nstates;
Asciz	I;
Asciz	()I;
Asciz	Code;
Asciz	LineNumberTable;
Asciz	scala/util/automata/WordBerrySethi$$anon$1;
class	scala/util/automata/WordBerrySethi$$anon$1
NameAndType	nstates:I
Field	scala/util/automata/WordBerrySethi$$anon$1.nstates:I
Asciz	()Lscala/collection/immutable/List;;
NameAndType	labels:Lscala/collection/immutable/List;
Field	scala/util/automata/WordBerrySethi$$anon$1.labels:Lscala/collection/immutable/List;
Asciz	()Lscala/collection/immutable/List<Lscala/util/regexp/WordExp$Label;>;;
Asciz	()[I;
NameAndType	initials:[I
Field	scala/util/automata/WordBerrySethi$$anon$1.initials:[I
NameAndType	finals:[I
Field	scala/util/automata/WordBerrySethi$$anon$1.finals:[I
Asciz	()[Lscala/collection/Map;;
NameAndType	delta:[Lscala/collection/Map;
Field	scala/util/automata/WordBerrySethi$$anon$1.delta:[Lscala/collection/Map;
Asciz	()[Lscala/collection/Map<Lscala/util/regexp/WordExp$Label;Lscala/collection/immutable/BitSet;>;;
Asciz	()[Lscala/collection/immutable/BitSet;;
NameAndType	default:[Lscala/collection/immutable/BitSet;
Field	scala/util/automata/WordBerrySethi$$anon$1.default:[Lscala/collection/immutable/BitSet;
Asciz	()Lscala/collection/Seq;;
NameAndType	labels:()Lscala/collection/immutable/List;
Method	scala/util/automata/WordBerrySethi$$anon$1.labels:()Lscala/collection/immutable/List;
Asciz	<init>;
Asciz	(Lscala/util/automata/WordBerrySethi;[I[I[Lscala/collection/Map;[Lscala/collection/immutable/BitSet;)V;
Asciz	scala/util/automata/NondetWordAutom;
class	scala/util/automata/NondetWordAutom
Asciz	()V;
NameAndType	"<init>":()V
Method	scala/util/automata/NondetWordAutom."<init>":()V
Asciz	scala/util/automata/WordBerrySethi;
class	scala/util/automata/WordBerrySethi
Asciz	pos;
NameAndType	pos:()I
Method	scala/util/automata/WordBerrySethi.pos:()I
Asciz	()Lscala/collection/mutable/HashSet;;
NameAndType	labels:()Lscala/collection/mutable/HashSet;
Method	scala/util/automata/WordBerrySethi.labels:()Lscala/collection/mutable/HashSet;
Asciz	scala/collection/TraversableLike;
class	scala/collection/TraversableLike
Asciz	toList;
NameAndType	toList:()Lscala/collection/immutable/List;
InterfaceMethod	scala/collection/TraversableLike.toList:()Lscala/collection/immutable/List;
Asciz	this;
Asciz	Lscala/util/automata/WordBerrySethi$$anon$1;;
Asciz	$outer;
Asciz	Lscala/util/automata/WordBerrySethi;;
Asciz	LocalVariableTable;
Asciz	Lscala/util/automata/NondetWordAutom<Lscala/util/regexp/WordExp$Label;>;;
Asciz	Scala;
Asciz	InnerClasses;
Asciz	$anon$1;

{
private final scala.collection.immutable.BitSet[] default;
  Signature: [Lscala/collection/immutable/BitSet;

private final scala.collection.Map[] delta;
  Signature: [Lscala/collection/Map;
  Signature: length = 0x2
   00 07 

private final int[] finals;
  Signature: [I

private final int[] initials;
  Signature: [I

private final scala.collection.immutable.List labels;
  Signature: Lscala/collection/immutable/List;
  Signature: length = 0x2
   00 0E 

private final int nstates;
  Signature: I

public int nstates();
  Signature: ()I
  Code:
   Stack=1, Locals=1, Args_size=1
	aload_0
	getfield	Field nstates:I
	ireturn
  Labels:

public scala.collection.immutable.List labels();
  Signature: ()Lscala/collection/immutable/List;
  Code:
   Stack=1, Locals=1, Args_size=1
	aload_0
	getfield	Field labels:Lscala/collection/immutable/List;
	areturn
  Labels:
  Signature: length = 0x2
   00 1B 

private int[] initials();
  Signature: ()[I
  Code:
   Stack=1, Locals=1, Args_size=1
	aload_0
	getfield	Field initials:[I
	areturn
  Labels:

public int[] finals();
  Signature: ()[I
  Code:
   Stack=1, Locals=1, Args_size=1
	aload_0
	getfield	Field finals:[I
	areturn
  Labels:

public scala.collection.Map[] delta();
  Signature: ()[Lscala/collection/Map;
  Code:
   Stack=1, Locals=1, Args_size=1
	aload_0
	getfield	Field delta:[Lscala/collection/Map;
	areturn
  Labels:
  Signature: length = 0x2
   00 24 

public scala.collection.immutable.BitSet[] default();
  Signature: ()[Lscala/collection/immutable/BitSet;
  Code:
   Stack=1, Locals=1, Args_size=1
	aload_0
	getfield	Field default:[Lscala/collection/immutable/BitSet;
	areturn
  Labels:

public scala.collection.Seq labels();
  Signature: ()Lscala/collection/Seq;
  Code:
   Stack=1, Locals=1, Args_size=1
	aload_0
	invokevirtual	Method labels:()Lscala/collection/immutable/List;
	areturn
  Labels:

public scala.util.automata.WordBerrySethi$$anon$1(scala.util.automata.WordBerrySethi, int[], int[], scala.collection.Map[], scala.collection.immutable.BitSet[]);
  Signature: (Lscala/util/automata/WordBerrySethi;[I[I[Lscala/collection/Map;[Lscala/collection/immutable/BitSet;)V
  Code:
   Stack=2, Locals=6, Args_size=6
	aload_0
	invokespecial	Method scala/util/automata/NondetWordAutom."<init>":()V
	aload_0
	aload_1
	invokevirtual	Method scala/util/automata/WordBerrySethi.pos:()I
	putfield	Field nstates:I
	aload_0
	aload_1
	invokevirtual	Method scala/util/automata/WordBerrySethi.labels:()Lscala/collection/mutable/HashSet;
	invokeinterface	InterfaceMethod scala/collection/TraversableLike.toList:()Lscala/collection/immutable/List;
	putfield	Field labels:Lscala/collection/immutable/List;
	aload_0
	aload_3
	putfield	Field initials:[I
	aload_0
	aload_2
	putfield	Field finals:[I
	aload_0
	aload	4
	putfield	Field delta:[Lscala/collection/Map;
	aload_0
	aload	5
	putfield	Field default:[Lscala/collection/immutable/BitSet;
	return
  Labels:
  LocalVariableTable: 
   Start  Length  Slot  Name   Signature
   0      48      0    this       Lscala/util/automata/WordBerrySethi$$anon$1;
   0      48      1    $outer       Lscala/util/automata/WordBerrySethi;


}

