Compiled from "WordBerrySethi.scala"
public final class scala.util.automata.WordBerrySethi$$anon$1 extends scala.util.automata.NondetWordAutom
  SourceFile: "WordBerrySethi.scala"
  Signature: length = 0x2
   00 44 
  Scala: length = 0x
   
  InnerClass: 
   public final #71= #33 of #27; //$anon$1=class scala/util/automata/WordBerrySethi$$anon$1 of class scala/util/automata/WordBerrySethi
  minor version: 0
  major version: 49
  Constant pool:
const #1 = Asciz	SourceFile;
const #2 = Asciz	WordBerrySethi.scala;
const #3 = Asciz	default;
const #4 = Asciz	[Lscala/collection/immutable/BitSet;;
const #5 = Asciz	delta;
const #6 = Asciz	[Lscala/collection/Map;;
const #7 = Asciz	[Lscala/collection/Map<Lscala/util/regexp/WordExp$Label;Lscala/collection/immutable/BitSet;>;;
const #8 = Asciz	Signature;
const #9 = Asciz	finals;
const #10 = Asciz	[I;
const #11 = Asciz	initials;
const #12 = Asciz	labels;
const #13 = Asciz	Lscala/collection/immutable/List;;
const #14 = Asciz	Lscala/collection/immutable/List<Lscala/util/regexp/WordExp$Label;>;;
const #15 = Asciz	nstates;
const #16 = Asciz	I;
const #17 = Asciz	<init>;
const #18 = Asciz	(Lscala/util/automata/WordBerrySethi;[I[I[Lscala/collection/Map;[Lscala/collection/immutable/BitSet;)V;
const #19 = Asciz	Code;
const #20 = Asciz	LineNumberTable;
const #21 = Asciz	scala/util/automata/NondetWordAutom;
const #22 = class	#21;	//  scala/util/automata/NondetWordAutom
const #23 = Asciz	()V;
const #24 = NameAndType	#17:#23;//  "<init>":()V
const #25 = Method	#22.#24;	//  scala/util/automata/NondetWordAutom."<init>":()V
const #26 = Asciz	scala/util/automata/WordBerrySethi;
const #27 = class	#26;	//  scala/util/automata/WordBerrySethi
const #28 = Asciz	pos;
const #29 = Asciz	()I;
const #30 = NameAndType	#28:#29;//  pos:()I
const #31 = Method	#27.#30;	//  scala/util/automata/WordBerrySethi.pos:()I
const #32 = Asciz	scala/util/automata/WordBerrySethi$$anon$1;
const #33 = class	#32;	//  scala/util/automata/WordBerrySethi$$anon$1
const #34 = NameAndType	#15:#16;//  nstates:I
const #35 = Field	#33.#34;	//  scala/util/automata/WordBerrySethi$$anon$1.nstates:I
const #36 = Asciz	()Lscala/collection/mutable/HashSet;;
const #37 = NameAndType	#12:#36;//  labels:()Lscala/collection/mutable/HashSet;
const #38 = Method	#27.#37;	//  scala/util/automata/WordBerrySethi.labels:()Lscala/collection/mutable/HashSet;
const #39 = Asciz	scala/collection/TraversableLike;
const #40 = class	#39;	//  scala/collection/TraversableLike
const #41 = Asciz	toList;
const #42 = Asciz	()Lscala/collection/immutable/List;;
const #43 = NameAndType	#41:#42;//  toList:()Lscala/collection/immutable/List;
const #44 = InterfaceMethod	#40.#43;	//  scala/collection/TraversableLike.toList:()Lscala/collection/immutable/List;
const #45 = NameAndType	#12:#13;//  labels:Lscala/collection/immutable/List;
const #46 = Field	#33.#45;	//  scala/util/automata/WordBerrySethi$$anon$1.labels:Lscala/collection/immutable/List;
const #47 = NameAndType	#11:#10;//  initials:[I
const #48 = Field	#33.#47;	//  scala/util/automata/WordBerrySethi$$anon$1.initials:[I
const #49 = NameAndType	#9:#10;//  finals:[I
const #50 = Field	#33.#49;	//  scala/util/automata/WordBerrySethi$$anon$1.finals:[I
const #51 = NameAndType	#5:#6;//  delta:[Lscala/collection/Map;
const #52 = Field	#33.#51;	//  scala/util/automata/WordBerrySethi$$anon$1.delta:[Lscala/collection/Map;
const #53 = NameAndType	#3:#4;//  default:[Lscala/collection/immutable/BitSet;
const #54 = Field	#33.#53;	//  scala/util/automata/WordBerrySethi$$anon$1.default:[Lscala/collection/immutable/BitSet;
const #55 = Asciz	this;
const #56 = Asciz	Lscala/util/automata/WordBerrySethi$$anon$1;;
const #57 = Asciz	$outer;
const #58 = Asciz	Lscala/util/automata/WordBerrySethi;;
const #59 = Asciz	LocalVariableTable;
const #60 = Asciz	()Lscala/collection/Seq;;
const #61 = NameAndType	#12:#42;//  labels:()Lscala/collection/immutable/List;
const #62 = Method	#33.#61;	//  scala/util/automata/WordBerrySethi$$anon$1.labels:()Lscala/collection/immutable/List;
const #63 = Asciz	()[Lscala/collection/immutable/BitSet;;
const #64 = Asciz	()[Lscala/collection/Map;;
const #65 = Asciz	()[Lscala/collection/Map<Lscala/util/regexp/WordExp$Label;Lscala/collection/immutable/BitSet;>;;
const #66 = Asciz	()[I;
const #67 = Asciz	()Lscala/collection/immutable/List<Lscala/util/regexp/WordExp$Label;>;;
const #68 = Asciz	Lscala/util/automata/NondetWordAutom<Lscala/util/regexp/WordExp$Label;>;;
const #69 = Asciz	Scala;
const #70 = Asciz	InnerClasses;
const #71 = Asciz	$anon$1;

{
public scala.util.automata.WordBerrySethi$$anon$1(scala.util.automata.WordBerrySethi, int[], int[], scala.collection.Map[], scala.collection.immutable.BitSet[]);
  Code:
   Stack=2, Locals=6, Args_size=6
   0:	aload_0
   1:	invokespecial	#25; //Method scala/util/automata/NondetWordAutom."<init>":()V
   4:	aload_0
   5:	aload_1
   6:	invokevirtual	#31; //Method scala/util/automata/WordBerrySethi.pos:()I
   9:	putfield	#35; //Field nstates:I
   12:	aload_0
   13:	aload_1
   14:	invokevirtual	#38; //Method scala/util/automata/WordBerrySethi.labels:()Lscala/collection/mutable/HashSet;
   17:	invokeinterface	#44,  1; //InterfaceMethod scala/collection/TraversableLike.toList:()Lscala/collection/immutable/List;
   22:	putfield	#46; //Field labels:Lscala/collection/immutable/List;
   25:	aload_0
   26:	aload_3
   27:	putfield	#48; //Field initials:[I
   30:	aload_0
   31:	aload_2
   32:	putfield	#50; //Field finals:[I
   35:	aload_0
   36:	aload	4
   38:	putfield	#52; //Field delta:[Lscala/collection/Map;
   41:	aload_0
   42:	aload	5
   44:	putfield	#54; //Field default:[Lscala/collection/immutable/BitSet;
   47:	return
  LineNumberTable: 
   line 161: 0
   line 162: 4
   line 163: 12
   line 164: 25
   line 165: 30
   line 166: 35
   line 167: 41

  LocalVariableTable: 
   Start  Length  Slot  Name   Signature
   0      48      0    this       Lscala/util/automata/WordBerrySethi$$anon$1;
   0      48      1    $outer       Lscala/util/automata/WordBerrySethi;


public scala.collection.Seq labels();
  Code:
   Stack=1, Locals=1, Args_size=1
   0:	aload_0
   1:	invokevirtual	#62; //Method labels:()Lscala/collection/immutable/List;
   4:	areturn
  LineNumberTable: 
   line 161: 0


public scala.collection.immutable.BitSet[] default();
  Code:
   Stack=1, Locals=1, Args_size=1
   0:	aload_0
   1:	getfield	#54; //Field default:[Lscala/collection/immutable/BitSet;
   4:	areturn
  LineNumberTable: 
   line 167: 0


public scala.collection.Map[] delta();
  Code:
   Stack=1, Locals=1, Args_size=1
   0:	aload_0
   1:	getfield	#52; //Field delta:[Lscala/collection/Map;
   4:	areturn
  LineNumberTable: 
   line 166: 0

  Signature: length = 0x2
   00 41 

public int[] finals();
  Code:
   Stack=1, Locals=1, Args_size=1
   0:	aload_0
   1:	getfield	#50; //Field finals:[I
   4:	areturn
  LineNumberTable: 
   line 165: 0


public scala.collection.immutable.List labels();
  Code:
   Stack=1, Locals=1, Args_size=1
   0:	aload_0
   1:	getfield	#46; //Field labels:Lscala/collection/immutable/List;
   4:	areturn
  LineNumberTable: 
   line 163: 0

  Signature: length = 0x2
   00 43 

public int nstates();
  Code:
   Stack=1, Locals=1, Args_size=1
   0:	aload_0
   1:	getfield	#35; //Field nstates:I
   4:	ireturn
  LineNumberTable: 
   line 162: 0


}

