Compiled from "WordBerrySethi.scala"
public final class scala.util.automata.WordBerrySethi$$anonfun$3 extends java.lang.Object implements scala.Function1,scala.ScalaObject,java.io.Serializable
  SourceFile: "WordBerrySethi.scala"
  Scala: length = 0x
   
  InnerClass: 
   public final $anonfun$3=class scala/util/automata/WordBerrySethi$$anonfun$3 of class scala/util/automata/WordBerrySethi
   public final $anonfun$apply$3=class scala/util/automata/WordBerrySethi$$anonfun$3$$anonfun$apply$3 of class scala/util/automata/WordBerrySethi$$anonfun$3
  minor version: 0
  major version: 49
  Constant pool:
Asciz	SourceFile;
Asciz	WordBerrySethi.scala;
Asciz	<clinit>;
Asciz	()V;
Asciz	Code;
Asciz	serialVersionUID;
Asciz	J;
Asciz	scala/util/automata/WordBerrySethi$$anonfun$3;
class	scala/util/automata/WordBerrySethi$$anonfun$3
NameAndType	serialVersionUID:J
Field	scala/util/automata/WordBerrySethi$$anonfun$3.serialVersionUID:J
Asciz	delta1$1;
Asciz	Lscala/collection/immutable/Map;;
Asciz	<init>;
Asciz	(Lscala/util/automata/WordBerrySethi;Lscala/collection/immutable/Map;)V;
Asciz	LineNumberTable;
NameAndType	delta1$1:Lscala/collection/immutable/Map;
Field	scala/util/automata/WordBerrySethi$$anonfun$3.delta1$1:Lscala/collection/immutable/Map;
Asciz	java/lang/Object;
class	java/lang/Object
NameAndType	"<init>":()V
Method	java/lang/Object."<init>":()V
Asciz	scala/Function1$class;
class	scala/Function1$class
Asciz	$init$;
Asciz	(Lscala/Function1;)V;
NameAndType	$init$:(Lscala/Function1;)V
Method	scala/Function1$class.$init$:(Lscala/Function1;)V
Asciz	this;
Asciz	Lscala/util/automata/WordBerrySethi$$anonfun$3;;
Asciz	$outer;
Asciz	Lscala/util/automata/WordBerrySethi;;
Asciz	LocalVariableTable;
Asciz	apply;
Asciz	(Ljava/lang/Object;)Ljava/lang/Object;;
Asciz	scala/runtime/BoxesRunTime;
class	scala/runtime/BoxesRunTime
Asciz	unboxToInt;
Asciz	(Ljava/lang/Object;)I;
NameAndType	unboxToInt:(Ljava/lang/Object;)I
Method	scala/runtime/BoxesRunTime.unboxToInt:(Ljava/lang/Object;)I
Asciz	(I)Lscala/collection/mutable/HashMap;;
NameAndType	apply:(I)Lscala/collection/mutable/HashMap;
Method	scala/util/automata/WordBerrySethi$$anonfun$3.apply:(I)Lscala/collection/mutable/HashMap;
Asciz	v1;
Asciz	Ljava/lang/Object;;
Asciz	scala/collection/mutable/HashMap$;
class	scala/collection/mutable/HashMap$
Asciz	MODULE$;
Asciz	Lscala/collection/mutable/HashMap$;;
NameAndType	MODULE$:Lscala/collection/mutable/HashMap$;
Field	scala/collection/mutable/HashMap$.MODULE$:Lscala/collection/mutable/HashMap$;
Asciz	boxToInteger;
Asciz	(I)Ljava/lang/Integer;;
NameAndType	boxToInteger:(I)Ljava/lang/Integer;
Method	scala/runtime/BoxesRunTime.boxToInteger:(I)Ljava/lang/Integer;
Asciz	scala/collection/MapLike;
class	scala/collection/MapLike
NameAndType	apply:(Ljava/lang/Object;)Ljava/lang/Object;
InterfaceMethod	scala/collection/MapLike.apply:(Ljava/lang/Object;)Ljava/lang/Object;
Asciz	scala/collection/TraversableLike;
class	scala/collection/TraversableLike
Asciz	toSeq;
Asciz	()Lscala/collection/Seq;;
NameAndType	toSeq:()Lscala/collection/Seq;
InterfaceMethod	scala/collection/TraversableLike.toSeq:()Lscala/collection/Seq;
Asciz	scala/util/automata/WordBerrySethi$$anonfun$3$$anonfun$apply$3;
class	scala/util/automata/WordBerrySethi$$anonfun$3$$anonfun$apply$3
Asciz	(Lscala/util/automata/WordBerrySethi$$anonfun$3;)V;
NameAndType	"<init>":(Lscala/util/automata/WordBerrySethi$$anonfun$3;)V
Method	scala/util/automata/WordBerrySethi$$anonfun$3$$anonfun$apply$3."<init>":(Lscala/util/automata/WordBerrySethi$$anonfun$3;)V
Asciz	scala/collection/Seq$;
class	scala/collection/Seq$
Asciz	Lscala/collection/Seq$;;
NameAndType	MODULE$:Lscala/collection/Seq$;
Field	scala/collection/Seq$.MODULE$:Lscala/collection/Seq$;
Asciz	canBuildFrom;
Asciz	()Lscala/collection/generic/CanBuildFrom;;
NameAndType	canBuildFrom:()Lscala/collection/generic/CanBuildFrom;
Method	scala/collection/Seq$.canBuildFrom:()Lscala/collection/generic/CanBuildFrom;
Asciz	map;
Asciz	(Lscala/Function1;Lscala/collection/generic/CanBuildFrom;)Ljava/lang/Object;;
NameAndType	map:(Lscala/Function1;Lscala/collection/generic/CanBuildFrom;)Ljava/lang/Object;
InterfaceMethod	scala/collection/TraversableLike.map:(Lscala/Function1;Lscala/collection/generic/CanBuildFrom;)Ljava/lang/Object;
Asciz	scala/collection/Seq;
class	scala/collection/Seq
Asciz	(Lscala/collection/Seq;)Lscala/collection/Map;;
NameAndType	apply:(Lscala/collection/Seq;)Lscala/collection/Map;
Method	scala/collection/mutable/HashMap$.apply:(Lscala/collection/Seq;)Lscala/collection/Map;
Asciz	scala/collection/mutable/HashMap;
class	scala/collection/mutable/HashMap
Asciz	x;
Asciz	I;
Asciz	(I)Lscala/collection/mutable/HashMap<Lscala/util/regexp/WordExp$Label;Lscala/collection/immutable/BitSet;>;;
Asciz	Signature;
Asciz	andThen;
Asciz	(Lscala/Function1;)Lscala/Function1;;
Asciz	(Lscala/Function1;Lscala/Function1;)Lscala/Function1;;
NameAndType	andThen:(Lscala/Function1;Lscala/Function1;)Lscala/Function1;
Method	scala/Function1$class.andThen:(Lscala/Function1;Lscala/Function1;)Lscala/Function1;
Asciz	g;
Asciz	Lscala/Function1;;
Asciz	compose;
NameAndType	compose:(Lscala/Function1;Lscala/Function1;)Lscala/Function1;
Method	scala/Function1$class.compose:(Lscala/Function1;Lscala/Function1;)Lscala/Function1;
Asciz	toString;
Asciz	()Ljava/lang/String;;
Asciz	(Lscala/Function1;)Ljava/lang/String;;
NameAndType	toString:(Lscala/Function1;)Ljava/lang/String;
Method	scala/Function1$class.toString:(Lscala/Function1;)Ljava/lang/String;
Asciz	Scala;
Asciz	InnerClasses;
Asciz	scala/util/automata/WordBerrySethi;
class	scala/util/automata/WordBerrySethi
Asciz	$anonfun$3;
Asciz	$anonfun$apply$3;
Asciz	scala/Function1;
class	scala/Function1
Asciz	scala/ScalaObject;
class	scala/ScalaObject
Asciz	java/io/Serializable;
class	java/io/Serializable

{
public static final long serialVersionUID;
  Signature: J

private final scala.collection.immutable.Map delta1$1;
  Signature: Lscala/collection/immutable/Map;

public static {};
  Signature: ()V
  Code:
   Stack=2, Locals=0, Args_size=0
	lconst_0
	putstatic	Field serialVersionUID:J
	return
  Labels:

public scala.util.automata.WordBerrySethi$$anonfun$3(scala.util.automata.WordBerrySethi, scala.collection.immutable.Map);
  Signature: (Lscala/util/automata/WordBerrySethi;Lscala/collection/immutable/Map;)V
  Code:
   Stack=2, Locals=3, Args_size=3
	aload_0
	aload_2
	putfield	Field delta1$1:Lscala/collection/immutable/Map;
	aload_0
	invokespecial	Method java/lang/Object."<init>":()V
	aload_0
	invokestatic	Method scala/Function1$class.$init$:(Lscala/Function1;)V
	return
  Labels:
  LocalVariableTable: 
   Start  Length  Slot  Name   Signature
   0      14      0    this       Lscala/util/automata/WordBerrySethi$$anonfun$3;
   0      14      1    $outer       Lscala/util/automata/WordBerrySethi;


public final java.lang.Object apply(java.lang.Object);
  Signature: (Ljava/lang/Object;)Ljava/lang/Object;
  Code:
   Stack=2, Locals=2, Args_size=2
	aload_0
	aload_1
	invokestatic	Method scala/runtime/BoxesRunTime.unboxToInt:(Ljava/lang/Object;)I
	invokevirtual	Method apply:(I)Lscala/collection/mutable/HashMap;
	areturn
  Labels:
  LocalVariableTable: 
   Start  Length  Slot  Name   Signature
   0      9      0    this       Lscala/util/automata/WordBerrySethi$$anonfun$3;
   0      9      1    v1       Ljava/lang/Object;


public final scala.collection.mutable.HashMap apply(int);
  Signature: (I)Lscala/collection/mutable/HashMap;
  Code:
   Stack=5, Locals=2, Args_size=2
	getstatic	Field scala/collection/mutable/HashMap$.MODULE$:Lscala/collection/mutable/HashMap$;
	aload_0
	getfield	Field delta1$1:Lscala/collection/immutable/Map;
	iload_1
	invokestatic	Method scala/runtime/BoxesRunTime.boxToInteger:(I)Ljava/lang/Integer;
	invokeinterface	InterfaceMethod scala/collection/MapLike.apply:(Ljava/lang/Object;)Ljava/lang/Object;
	checkcast	class scala/collection/TraversableLike
	invokeinterface	InterfaceMethod scala/collection/TraversableLike.toSeq:()Lscala/collection/Seq;
	new	class scala/util/automata/WordBerrySethi$$anonfun$3$$anonfun$apply$3
	dup
	aload_0
	invokespecial	Method scala/util/automata/WordBerrySethi$$anonfun$3$$anonfun$apply$3."<init>":(Lscala/util/automata/WordBerrySethi$$anonfun$3;)V
	getstatic	Field scala/collection/Seq$.MODULE$:Lscala/collection/Seq$;
	invokevirtual	Method scala/collection/Seq$.canBuildFrom:()Lscala/collection/generic/CanBuildFrom;
	invokeinterface	InterfaceMethod scala/collection/TraversableLike.map:(Lscala/Function1;Lscala/collection/generic/CanBuildFrom;)Ljava/lang/Object;
	checkcast	class scala/collection/Seq
	invokevirtual	Method scala/collection/mutable/HashMap$.apply:(Lscala/collection/Seq;)Lscala/collection/Map;
	checkcast	class scala/collection/mutable/HashMap
	areturn
  Labels:
  LocalVariableTable: 
   Start  Length  Slot  Name   Signature
   0      53      0    this       Lscala/util/automata/WordBerrySethi$$anonfun$3;
   0      53      1    x       I

  Signature: length = 0x2
   00 5E 

public scala.Function1 andThen(scala.Function1);
  Signature: (Lscala/Function1;)Lscala/Function1;
  Code:
   Stack=2, Locals=2, Args_size=2
	aload_0
	aload_1
	invokestatic	Method scala/Function1$class.andThen:(Lscala/Function1;Lscala/Function1;)Lscala/Function1;
	areturn
  Labels:
  LocalVariableTable: 
   Start  Length  Slot  Name   Signature
   0      6      0    this       Lscala/util/automata/WordBerrySethi$$anonfun$3;
   0      6      1    g       Lscala/Function1;


public scala.Function1 compose(scala.Function1);
  Signature: (Lscala/Function1;)Lscala/Function1;
  Code:
   Stack=2, Locals=2, Args_size=2
	aload_0
	aload_1
	invokestatic	Method scala/Function1$class.compose:(Lscala/Function1;Lscala/Function1;)Lscala/Function1;
	areturn
  Labels:
  LocalVariableTable: 
   Start  Length  Slot  Name   Signature
   0      6      0    this       Lscala/util/automata/WordBerrySethi$$anonfun$3;
   0      6      1    g       Lscala/Function1;


public java.lang.String toString();
  Signature: ()Ljava/lang/String;
  Code:
   Stack=1, Locals=1, Args_size=1
	aload_0
	invokestatic	Method scala/Function1$class.toString:(Lscala/Function1;)Ljava/lang/String;
	areturn
  Labels:

}

