Compiled from "WordBerrySethi.scala"
public final class scala.util.automata.WordBerrySethi$$anonfun$2$$anonfun$apply$2 extends java.lang.Object implements scala.Function0,scala.ScalaObject,java.io.Serializable
  SourceFile: "WordBerrySethi.scala"
  Scala: length = 0x
   
  InnerClass: 
   public final $anonfun$2=class scala/util/automata/WordBerrySethi$$anonfun$2 of class scala/util/automata/WordBerrySethi
   public final $anonfun$apply$2=class scala/util/automata/WordBerrySethi$$anonfun$2$$anonfun$apply$2 of class scala/util/automata/WordBerrySethi$$anonfun$2
  minor version: 0
  major version: 49
  Constant pool:
Asciz	SourceFile;
Asciz	WordBerrySethi.scala;
Asciz	<clinit>;
Asciz	()V;
Asciz	Code;
Asciz	serialVersionUID;
Asciz	J;
Asciz	scala/util/automata/WordBerrySethi$$anonfun$2$$anonfun$apply$2;
class	scala/util/automata/WordBerrySethi$$anonfun$2$$anonfun$apply$2
NameAndType	serialVersionUID:J
Field	scala/util/automata/WordBerrySethi$$anonfun$2$$anonfun$apply$2.serialVersionUID:J
Asciz	<init>;
Asciz	(Lscala/util/automata/WordBerrySethi$$anonfun$2;)V;
Asciz	LineNumberTable;
Asciz	java/lang/Object;
class	java/lang/Object
NameAndType	"<init>":()V
Method	java/lang/Object."<init>":()V
Asciz	scala/Function0$class;
class	scala/Function0$class
Asciz	$init$;
Asciz	(Lscala/Function0;)V;
NameAndType	$init$:(Lscala/Function0;)V
Method	scala/Function0$class.$init$:(Lscala/Function0;)V
Asciz	this;
Asciz	Lscala/util/automata/WordBerrySethi$$anonfun$2$$anonfun$apply$2;;
Asciz	$outer;
Asciz	Lscala/util/automata/WordBerrySethi$$anonfun$2;;
Asciz	LocalVariableTable;
Asciz	apply;
Asciz	()Ljava/lang/Object;;
Asciz	()I;
NameAndType	apply:()I
Method	scala/util/automata/WordBerrySethi$$anonfun$2$$anonfun$apply$2.apply:()I
Asciz	scala/runtime/BoxesRunTime;
class	scala/runtime/BoxesRunTime
Asciz	boxToInteger;
Asciz	(I)Ljava/lang/Integer;;
NameAndType	boxToInteger:(I)Ljava/lang/Integer;
Method	scala/runtime/BoxesRunTime.boxToInteger:(I)Ljava/lang/Integer;
Asciz	toString;
Asciz	()Ljava/lang/String;;
Asciz	(Lscala/Function0;)Ljava/lang/String;;
NameAndType	toString:(Lscala/Function0;)Ljava/lang/String;
Method	scala/Function0$class.toString:(Lscala/Function0;)Ljava/lang/String;
Asciz	Scala;
Asciz	InnerClasses;
Asciz	scala/util/automata/WordBerrySethi$$anonfun$2;
class	scala/util/automata/WordBerrySethi$$anonfun$2
Asciz	scala/util/automata/WordBerrySethi;
class	scala/util/automata/WordBerrySethi
Asciz	$anonfun$2;
Asciz	$anonfun$apply$2;
Asciz	scala/Function0;
class	scala/Function0
Asciz	scala/ScalaObject;
class	scala/ScalaObject
Asciz	java/io/Serializable;
class	java/io/Serializable

{
public static final long serialVersionUID;
  Signature: J

public static {};
  Signature: ()V
  Code:
   Stack=2, Locals=0, Args_size=0
	lconst_0
	putstatic	Field serialVersionUID:J
	return
  Labels:

public scala.util.automata.WordBerrySethi$$anonfun$2$$anonfun$apply$2(scala.util.automata.WordBerrySethi$$anonfun$2);
  Signature: (Lscala/util/automata/WordBerrySethi$$anonfun$2;)V
  Code:
   Stack=1, Locals=2, Args_size=2
	aload_0
	invokespecial	Method java/lang/Object."<init>":()V
	aload_0
	invokestatic	Method scala/Function0$class.$init$:(Lscala/Function0;)V
	return
  Labels:
  LocalVariableTable: 
   Start  Length  Slot  Name   Signature
   0      9      0    this       Lscala/util/automata/WordBerrySethi$$anonfun$2$$anonfun$apply$2;
   0      9      1    $outer       Lscala/util/automata/WordBerrySethi$$anonfun$2;


public final java.lang.Object apply();
  Signature: ()Ljava/lang/Object;
  Code:
   Stack=1, Locals=2, Args_size=1
	aload_0
	invokevirtual	Method apply:()I
	istore_1
	iload_1
	invokestatic	Method scala/runtime/BoxesRunTime.boxToInteger:(I)Ljava/lang/Integer;
	areturn
  Labels:

public final int apply();
  Signature: ()I
  Code:
   Stack=1, Locals=1, Args_size=1
	iconst_0
	ireturn
  Labels:

public java.lang.String toString();
  Signature: ()Ljava/lang/String;
  Code:
   Stack=1, Locals=1, Args_size=1
	aload_0
	invokestatic	Method scala/Function0$class.toString:(Lscala/Function0;)Ljava/lang/String;
	areturn
  Labels:

}

