Compiled from "Channel.scala"
public final class scala.actors.$bang$ extends java.lang.Object implements scala.ScalaObject
  SourceFile: "Channel.scala"
  Scala: length = 0x
   
  minor version: 0
  major version: 49
  Constant pool:
Asciz	SourceFile;
Asciz	Channel.scala;
Asciz	Scala;
Asciz	MODULE$;
Asciz	Lscala/actors/$bang$;;
Asciz	<clinit>;
Asciz	()V;
Asciz	Code;
Asciz	scala/actors/$bang$;
class	scala/actors/$bang$
Asciz	<init>;
NameAndType	"<init>":()V
Method	scala/actors/$bang$."<init>":()V
Asciz	unapply;
Asciz	(Lscala/actors/$bang;)Lscala/Option;;
Asciz	LineNumberTable;
Asciz	java/lang/Object;
class	java/lang/Object
Asciz	equals;
Asciz	(Ljava/lang/Object;)Z;
NameAndType	equals:(Ljava/lang/Object;)Z
Method	java/lang/Object.equals:(Ljava/lang/Object;)Z
Asciz	scala/None$;
class	scala/None$
Asciz	Lscala/None$;;
NameAndType	MODULE$:Lscala/None$;
Field	scala/None$.MODULE$:Lscala/None$;
Asciz	scala/Some;
class	scala/Some
Asciz	scala/Tuple2;
class	scala/Tuple2
Asciz	scala/actors/$bang;
class	scala/actors/$bang
Asciz	ch;
Asciz	()Lscala/actors/Channel;;
NameAndType	ch:()Lscala/actors/Channel;
Method	scala/actors/$bang.ch:()Lscala/actors/Channel;
Asciz	msg;
Asciz	()Ljava/lang/Object;;
NameAndType	msg:()Ljava/lang/Object;
Method	scala/actors/$bang.msg:()Ljava/lang/Object;
Asciz	(Ljava/lang/Object;Ljava/lang/Object;)V;
NameAndType	"<init>":(Ljava/lang/Object;Ljava/lang/Object;)V
Method	scala/Tuple2."<init>":(Ljava/lang/Object;Ljava/lang/Object;)V
Asciz	(Ljava/lang/Object;)V;
NameAndType	"<init>":(Ljava/lang/Object;)V
Method	scala/Some."<init>":(Ljava/lang/Object;)V
Asciz	this;
Asciz	x$0;
Asciz	Lscala/actors/$bang;;
Asciz	LocalVariableTable;
Asciz	apply;
Asciz	(Lscala/actors/Channel;Ljava/lang/Object;)Lscala/actors/$bang;;
Asciz	(Lscala/actors/Channel;Ljava/lang/Object;)V;
NameAndType	"<init>":(Lscala/actors/Channel;Ljava/lang/Object;)V
Method	scala/actors/$bang."<init>":(Lscala/actors/Channel;Ljava/lang/Object;)V
Asciz	Lscala/actors/Channel;;
Asciz	Ljava/lang/Object;;
Method	java/lang/Object."<init>":()V
NameAndType	MODULE$:Lscala/actors/$bang$;
Field	scala/actors/$bang$.MODULE$:Lscala/actors/$bang$;
Asciz	scala/ScalaObject;
class	scala/ScalaObject

{
public static final scala.actors.$bang$ MODULE$;
  Signature: Lscala/actors/$bang$;

public static {};
  Signature: ()V
  Code:
   Stack=1, Locals=0, Args_size=0
	new	class scala/actors/$bang$
	invokespecial	Method "<init>":()V
	return
  Labels:

public scala.Option unapply(scala.actors.$bang);
  Signature: (Lscala/actors/$bang;)Lscala/Option;
  Code:
   Stack=6, Locals=2, Args_size=2
	aload_1
	dup
	pop
	ifnull	l1 // getstatic
	aload_1
	aconst_null
	invokevirtual	Method java/lang/Object.equals:(Ljava/lang/Object;)Z
	ifeq	l2 // new
l1	getstatic	Field scala/None$.MODULE$:Lscala/None$;
	goto	l3 // areturn
l2	new	class scala/Some
	dup
	new	class scala/Tuple2
	dup
	aload_1
	invokevirtual	Method scala/actors/$bang.ch:()Lscala/actors/Channel;
	aload_1
	invokevirtual	Method scala/actors/$bang.msg:()Ljava/lang/Object;
	invokespecial	Method scala/Tuple2."<init>":(Ljava/lang/Object;Ljava/lang/Object;)V
	invokespecial	Method scala/Some."<init>":(Ljava/lang/Object;)V
l3	areturn
  Labels:
   	l1 = 14 // getstatic
   	l2 = 20 // new
   	l3 = 42 // areturn
  LocalVariableTable: 
   Start  Length  Slot  Name   Signature
   0      43      0    this       Lscala/actors/$bang$;
   0      43      1    x$0       Lscala/actors/$bang;


public scala.actors.$bang apply(scala.actors.Channel, java.lang.Object);
  Signature: (Lscala/actors/Channel;Ljava/lang/Object;)Lscala/actors/$bang;
  Code:
   Stack=4, Locals=3, Args_size=3
	new	class scala/actors/$bang
	dup
	aload_1
	aload_2
	invokespecial	Method scala/actors/$bang."<init>":(Lscala/actors/Channel;Ljava/lang/Object;)V
	areturn
  Labels:
  LocalVariableTable: 
   Start  Length  Slot  Name   Signature
   0      10      0    this       Lscala/actors/$bang$;
   0      10      1    ch       Lscala/actors/Channel;
   0      10      2    msg       Ljava/lang/Object;


private scala.actors.$bang$();
  Signature: ()V
  Code:
   Stack=1, Locals=1, Args_size=1
	aload_0
	invokespecial	Method java/lang/Object."<init>":()V
	aload_0
	putstatic	Field MODULE$:Lscala/actors/$bang$;
	return
  Labels:

}

