Compiled from "Channel.scala"
public class scala.actors.$bang extends java.lang.Object implements scala.ScalaObject,scala.Product,java.io.Serializable
  SourceFile: "Channel.scala"
  Signature: length = 0x2
   00 7A 
  ScalaSig: length = 0x43C
   05 00 FFFFFF81 21 06 04 01 02 40 07 02 05 24 62 61 6E
   67 0A 02 03 04 01 06 61 63 74 6F 72 73 0A 01 05
   01 05 73 63 61 6C 61 03 00 15 02 08 21 13 04 00
   09 11 15 10 02 0A 0F 0D 01 0B 0A 02 0C 0D 01 04
   6C 61 6E 67 0A 01 0E 01 04 6A 61 76 61 09 02 10
   0B 02 06 4F 62 6A 65 63 74 10 02 12 13 0D 01 04
   09 02 14 04 02 0B 53 63 61 6C 61 4F 62 6A 65 63
   74 10 02 12 16 09 02 17 04 02 07 50 72 6F 64 75
   63 74 08 08 19 00 FFFFFF82 FFFFFFCA FFFFFF80 FFFFFF84 00 1A 01 02 63 68
   15 01 1B 10 03 1C 1D 1F 0D 01 02 09 02 1E 02 02
   07 43 68 61 6E 6E 65 6C 10 02 20 21 0C 00 04 08
   22 00 FFFFFF84 FFFFFF80 FFFFFF80 FFFFFFC2 00 23 02 01 61 11 02 24 27 10
   02 12 25 09 02 26 04 02 07 4E 6F 74 68 69 6E 67
   10 02 12 28 09 02 29 04 02 03 41 6E 79 08 08 2B
   00 FFFFFF82 FFFFFF88 FFFFFFA0 FFFFFF80 04 1B 01 03 63 68 20 08 08 2D 00
   FFFFFF82 FFFFFFCA FFFFFF80 FFFFFF84 00 2E 01 03 6D 73 67 15 01 1F 08 08
   30 00 FFFFFF82 FFFFFF88 FFFFFFA0 FFFFFF80 04 1F 01 04 6D 73 67 20 08 05
   32 00 FFFFFF84 00 33 01 06 3C 69 6E 69 74 3E 14 03 34
   35 36 10 03 1C 00 1F 08 05 19 31 FFFFFFC0 00 1B 08 05
   2D 31 FFFFFFC0 00 1F 08 07 38 00 FFFFFF81 FFFFFF80 FFFFFF84 00 39 01 04
   63 6F 70 79 15 02 3A 3D 14 03 3B 3E 4E 10 03 1C
   00 3C 10 02 20 3D 04 08 22 37 FFFFFF84 FFFFFF80 FFFFFF80 FFFFFFC2 00 23
   08 08 40 19 37 FFFFFF90 FFFFFF80 FFFFFFC0 00 3F 10 03 1C 1D 3C 08
   07 41 00 FFFFFF91 FFFFFF80 FFFFFF84 00 42 01 0E 63 6F 70 79 24 64
   65 66 61 75 6C 74 24 31 15 02 43 4D 2A 02 1B 44
   2B 01 45 10 02 46 4B 0D 01 47 0A 02 48 49 01 09
   75 6E 63 68 65 63 6B 65 64 0A 02 4A 04 01 0A 61
   6E 6E 6F 74 61 74 69 6F 6E 09 02 4C 47 02 11 75
   6E 63 68 65 63 6B 65 64 56 61 72 69 61 6E 63 65
   04 08 22 40 FFFFFF84 FFFFFF80 FFFFFF80 FFFFFFC2 00 23 08 08 4F 2D 37 FFFFFF90
   FFFFFF80 FFFFFFC0 00 3C 08 07 50 00 FFFFFF91 FFFFFF80 FFFFFF84 00 51 01 0E 63
   6F 70 79 24 64 65 66 61 75 6C 74 24 32 15 02 52
   53 2A 02 1F 44 04 08 22 4F FFFFFF84 FFFFFF80 FFFFFF80 FFFFFFC2 00 23 08
   08 55 00 FFFFFF84 FFFFFF80 FFFFFF80 FFFFFF84 20 56 01 08 68 61 73 68 43
   6F 64 65 14 01 57 10 02 12 58 09 02 59 04 02 03
   49 6E 74 08 08 5B 00 FFFFFF84 FFFFFF80 FFFFFF80 FFFFFF84 20 5C 01 08 74
   6F 53 74 72 69 6E 67 14 01 5D 10 02 5E 61 0E 02
   12 5F 09 02 60 04 01 06 50 72 65 64 65 66 09 02
   62 63 02 06 53 74 72 69 6E 67 0A 02 60 04 08 08
   65 00 FFFFFF84 FFFFFF80 FFFFFF80 FFFFFF84 20 66 01 06 65 71 75 61 6C 73
   14 02 67 6A 10 02 12 68 09 02 69 04 02 07 42 6F
   6F 6C 65 61 6E 08 07 6B 64 FFFFFF81 FFFFFF80 FFFFFFC0 00 27 01 03
   78 24 31 08 08 6D 00 FFFFFF84 FFFFFF80 FFFFFF80 FFFFFF84 20 6E 01 0D 70
   72 6F 64 75 63 74 50 72 65 66 69 78 15 01 6F 10
   02 0A 70 09 02 62 0B 08 08 72 00 FFFFFF84 FFFFFF80 FFFFFF80 FFFFFF84 20
   73 01 0C 70 72 6F 64 75 63 74 41 72 69 74 79 15
   01 57 08 08 75 00 FFFFFF84 FFFFFF80 FFFFFF80 FFFFFF84 20 76 01 0E 70 72
   6F 64 75 63 74 45 6C 65 6D 65 6E 74 14 02 27 77
   08 07 6B 74 FFFFFF81 FFFFFF80 FFFFFFC0 00 57 08 08 79 00 FFFFFF84 FFFFFF80 FFFFFF80
   FFFFFF84 20 7A 01 08 63 61 6E 45 71 75 61 6C 14 02 67
   7B 08 07 6B 78 FFFFFF81 FFFFFF80 FFFFFFC0 00 27 28 02 00 7D 10 02
   12 7E 09 02 7F 04 02 0C 73 65 72 69 61 6C 69 7A
   61 62 6C 65 07 09 FFFFFF81 01 02 FFFFFF81 FFFFFF80 FFFFFF88 02 FFFFFF81 02 01
   05 24 62 61 6E 67 10 03 1C FFFFFF81 03 06 09 01 02 FFFFFF84
   FFFFFF81 FFFFFF80 FFFFFF88 02 FFFFFF81 04 13 04 FFFFFF81 03 09 11 08 07 32 FFFFFF81
   03 FFFFFF84 00 FFFFFF81 06 14 02 FFFFFF81 02 08 0A FFFFFF81 08 FFFFFF81 03 FFFFFF81
   FFFFFF80 FFFFFF84 40 FFFFFF81 09 01 05 61 70 70 6C 79 15 04 FFFFFF81 0A
   FFFFFF81 0D 14 06 FFFFFF81 0B FFFFFF81 0E FFFFFF81 10 10 04 1C 00 FFFFFF81 0C
   10 03 20 FFFFFF81 0D 04 09 22 FFFFFF81 07 FFFFFF84 FFFFFF80 FFFFFF80 FFFFFFC2 00 23
   08 07 19 FFFFFF81 07 FFFFFFC0 00 FFFFFF81 0F 10 04 1C 1D FFFFFF81 0C 08
   07 2D FFFFFF81 07 FFFFFFC0 00 FFFFFF81 0C 08 0A FFFFFF81 12 FFFFFF81 03 FFFFFF81 FFFFFF80
   FFFFFF84 40 FFFFFF81 13 01 07 75 6E 61 70 70 6C 79 15 04 FFFFFF81
   14 FFFFFF81 1D 14 04 FFFFFF81 15 FFFFFF81 1E 10 05 12 FFFFFF81 16 FFFFFF81 18
   09 03 FFFFFF81 17 04 02 04 53 6F 6D 65 10 07 12 FFFFFF81 19
   FFFFFF81 1B FFFFFF81 1C 09 03 FFFFFF81 1A 04 02 06 54 75 70 6C 65
   32 10 04 1C 1D FFFFFF81 1C 10 03 20 FFFFFF81 1D 04 09 22 FFFFFF81
   11 FFFFFF84 FFFFFF80 FFFFFF80 FFFFFFC2 00 23 08 08 FFFFFF81 1F FFFFFF81 11 FFFFFFC0 00 FFFFFF81
   20 01 03 78 24 30 10 04 1C 00 FFFFFF81 1C 
  minor version: 0
  major version: 49
  Constant pool:
Asciz	SourceFile;
Asciz	Channel.scala;
Asciz	msg;
Asciz	Ljava/lang/Object;;
Asciz	Ta;;
Asciz	Signature;
Asciz	ch;
Asciz	Lscala/actors/Channel;;
Asciz	Lscala/actors/Channel<Ta;>;;
Asciz	<init>;
Asciz	(Lscala/actors/Channel;Ljava/lang/Object;)V;
Asciz	Code;
Asciz	LineNumberTable;
Asciz	scala/actors/$bang;
class	scala/actors/$bang
NameAndType	ch:Lscala/actors/Channel;
Field	scala/actors/$bang.ch:Lscala/actors/Channel;
NameAndType	msg:Ljava/lang/Object;
Field	scala/actors/$bang.msg:Ljava/lang/Object;
Asciz	java/lang/Object;
class	java/lang/Object
Asciz	()V;
NameAndType	"<init>":()V
Method	java/lang/Object."<init>":()V
Asciz	scala/Product$class;
class	scala/Product$class
Asciz	$init$;
Asciz	(Lscala/Product;)V;
NameAndType	$init$:(Lscala/Product;)V
Method	scala/Product$class.$init$:(Lscala/Product;)V
Asciz	this;
Asciz	Lscala/actors/$bang;;
Asciz	LocalVariableTable;
Asciz	(Lscala/actors/Channel<Ta;>;Ta;)V;
Asciz	gd1$1;
Asciz	(Lscala/actors/Channel;Ljava/lang/Object;)Z;
Asciz	()Lscala/actors/Channel;;
NameAndType	ch:()Lscala/actors/Channel;
Method	scala/actors/$bang.ch:()Lscala/actors/Channel;
Asciz	equals;
Asciz	(Ljava/lang/Object;)Z;
NameAndType	equals:(Ljava/lang/Object;)Z
Method	java/lang/Object.equals:(Ljava/lang/Object;)Z
Asciz	()Ljava/lang/Object;;
NameAndType	msg:()Ljava/lang/Object;
Method	scala/actors/$bang.msg:()Ljava/lang/Object;
Asciz	java/lang/Number;
class	java/lang/Number
Asciz	java/lang/Character;
class	java/lang/Character
Asciz	scala/runtime/BoxesRunTime;
class	scala/runtime/BoxesRunTime
Asciz	equals2;
Asciz	(Ljava/lang/Object;Ljava/lang/Object;)Z;
NameAndType	equals2:(Ljava/lang/Object;Ljava/lang/Object;)Z
Method	scala/runtime/BoxesRunTime.equals2:(Ljava/lang/Object;Ljava/lang/Object;)Z
Asciz	canEqual;
Asciz	productElement;
Asciz	(I)Ljava/lang/Object;;
Asciz	java/lang/IndexOutOfBoundsException;
class	java/lang/IndexOutOfBoundsException
Asciz	boxToInteger;
Asciz	(I)Ljava/lang/Integer;;
NameAndType	boxToInteger:(I)Ljava/lang/Integer;
Method	scala/runtime/BoxesRunTime.boxToInteger:(I)Ljava/lang/Integer;
Asciz	toString;
Asciz	()Ljava/lang/String;;
NameAndType	toString:()Ljava/lang/String;
Method	java/lang/Object.toString:()Ljava/lang/String;
Asciz	(Ljava/lang/String;)V;
NameAndType	"<init>":(Ljava/lang/String;)V
Method	java/lang/IndexOutOfBoundsException."<init>":(Ljava/lang/String;)V
Asciz	scala/MatchError;
class	scala/MatchError
Method	scala/MatchError."<init>":(Ljava/lang/String;)V
Asciz	productArity;
Asciz	()I;
Asciz	productPrefix;
Asciz	!;
String	!
NameAndType	gd1$1:(Lscala/actors/Channel;Ljava/lang/Object;)Z
Method	scala/actors/$bang.gd1$1:(Lscala/actors/Channel;Ljava/lang/Object;)Z
Asciz	scala/Equals;
class	scala/Equals
NameAndType	canEqual:(Ljava/lang/Object;)Z
InterfaceMethod	scala/Equals.canEqual:(Ljava/lang/Object;)Z
Asciz	temp2;
Asciz	temp3;
Asciz	temp4;
Asciz	scala/runtime/ScalaRunTime$;
class	scala/runtime/ScalaRunTime$
Asciz	MODULE$;
Asciz	Lscala/runtime/ScalaRunTime$;;
NameAndType	MODULE$:Lscala/runtime/ScalaRunTime$;
Field	scala/runtime/ScalaRunTime$.MODULE$:Lscala/runtime/ScalaRunTime$;
Asciz	_toString;
Asciz	(Lscala/Product;)Ljava/lang/String;;
NameAndType	_toString:(Lscala/Product;)Ljava/lang/String;
Method	scala/runtime/ScalaRunTime$._toString:(Lscala/Product;)Ljava/lang/String;
Asciz	hashCode;
Asciz	_hashCode;
Asciz	(Lscala/Product;)I;
NameAndType	_hashCode:(Lscala/Product;)I
Method	scala/runtime/ScalaRunTime$._hashCode:(Lscala/Product;)I
Asciz	copy;
Asciz	(Lscala/actors/Channel;Ljava/lang/Object;)Lscala/actors/$bang;;
NameAndType	"<init>":(Lscala/actors/Channel;Ljava/lang/Object;)V
Method	scala/actors/$bang."<init>":(Lscala/actors/Channel;Ljava/lang/Object;)V
Asciz	()Ta;;
Asciz	()Lscala/actors/Channel<Ta;>;;
Asciz	copy$default$1;
Asciz	copy$default$2;
Asciz	productElements;
Asciz	()Lscala/collection/Iterator;;
Asciz	(Lscala/Product;)Lscala/collection/Iterator;;
NameAndType	productElements:(Lscala/Product;)Lscala/collection/Iterator;
Method	scala/Product$class.productElements:(Lscala/Product;)Lscala/collection/Iterator;
Asciz	Deprecated;
Asciz	productIterator;
NameAndType	productIterator:(Lscala/Product;)Lscala/collection/Iterator;
Method	scala/Product$class.productIterator:(Lscala/Product;)Lscala/collection/Iterator;
Asciz	<a:Ljava/lang/Object;>Ljava/lang/Object;Lscala/ScalaObject;Lscala/Product;;
Asciz	ScalaSig;
Asciz	scala/ScalaObject;
class	scala/ScalaObject
Asciz	scala/Product;
class	scala/Product
Asciz	java/io/Serializable;
class	java/io/Serializable

{
private final java.lang.Object msg;
  Signature: Ljava/lang/Object;
  Signature: length = 0x2
   00 05 

private final scala.actors.Channel ch;
  Signature: Lscala/actors/Channel;
  Signature: length = 0x2
   00 09 

public scala.actors.$bang(scala.actors.Channel, java.lang.Object);
  Signature: (Lscala/actors/Channel;Ljava/lang/Object;)V
  Code:
   Stack=2, Locals=3, Args_size=3
	aload_0
	aload_1
	putfield	Field ch:Lscala/actors/Channel;
	aload_0
	aload_2
	putfield	Field msg:Ljava/lang/Object;
	aload_0
	invokespecial	Method java/lang/Object."<init>":()V
	aload_0
	invokestatic	Method scala/Product$class.$init$:(Lscala/Product;)V
	return
  Labels:
  LocalVariableTable: 
   Start  Length  Slot  Name   Signature
   0      19      0    this       Lscala/actors/$bang;
   0      19      1    ch       Lscala/actors/Channel;
   0      19      2    msg       Ljava/lang/Object;

  Signature: length = 0x2
   00 22 

private final boolean gd1$1(scala.actors.Channel, java.lang.Object);
  Signature: (Lscala/actors/Channel;Ljava/lang/Object;)Z
  Code:
   Stack=2, Locals=5, Args_size=3
	aload_1
	aload_0
	invokevirtual	Method ch:()Lscala/actors/Channel;
	astore_3
	dup
	ifnonnull	l1 // aload_3
	pop
	aload_3
	ifnull	l2 // aload_0
	goto	l3 // iconst_0
l1	aload_3
	invokevirtual	Method java/lang/Object.equals:(Ljava/lang/Object;)Z
	ifeq	l3 // iconst_0
l2	aload_0
	invokevirtual	Method msg:()Ljava/lang/Object;
	astore	4
	aload_2
	aload	4
	if_acmpeq	l4 // iconst_1
	aload_2
	ifnull	l5 // iconst_0
	aload_2
	instanceof	class java/lang/Number
	ifne	l6 // aload_2
	aload_2
	instanceof	class java/lang/Character
	ifne	l6 // aload_2
	aload_2
	aload	4
	invokevirtual	Method java/lang/Object.equals:(Ljava/lang/Object;)Z
	goto	l7 // ifeq
l6	aload_2
	aload	4
	invokestatic	Method scala/runtime/BoxesRunTime.equals2:(Ljava/lang/Object;Ljava/lang/Object;)Z
	goto	l7 // ifeq
l5	iconst_0
	goto	l7 // ifeq
l4	iconst_1
l7	ifeq	l3 // iconst_0
	iconst_1
	goto	l8 // ireturn
l3	iconst_0
l8	ireturn
  Labels:
   	l1 = 18 // aload_3
   	l2 = 25 // aload_0
   	l6 = 64 // aload_2
   	l5 = 73 // iconst_0
   	l4 = 77 // iconst_1
   	l7 = 78 // ifeq
   	l3 = 85 // iconst_0
   	l8 = 86 // ireturn
  LocalVariableTable: 
   Start  Length  Slot  Name   Signature
   0      87      0    this       Lscala/actors/$bang;


public boolean canEqual(java.lang.Object);
  Signature: (Ljava/lang/Object;)Z
  Code:
   Stack=1, Locals=2, Args_size=2
	aload_1
	instanceof	class scala/actors/$bang
	ireturn
  Labels:

public java.lang.Object productElement(int);
  Signature: (I)Ljava/lang/Object;
  Code:
   Stack=3, Locals=2, Args_size=2
	iload_1
	tableswitch{ //0 to 1
		0: 84;
		1: 58;
		default: 24 }
	iconst_1
	ifeq	l1 // new
	new	class java/lang/IndexOutOfBoundsException
	dup
	iload_1
	invokestatic	Method scala/runtime/BoxesRunTime.boxToInteger:(I)Ljava/lang/Integer;
	invokevirtual	Method java/lang/Object.toString:()Ljava/lang/String;
	invokespecial	Method java/lang/IndexOutOfBoundsException."<init>":(Ljava/lang/String;)V
	athrow
l1	new	class scala/MatchError
	dup
	iload_1
	invokestatic	Method scala/runtime/BoxesRunTime.boxToInteger:(I)Ljava/lang/Integer;
	invokevirtual	Method java/lang/Object.toString:()Ljava/lang/String;
	invokespecial	Method scala/MatchError."<init>":(Ljava/lang/String;)V
	athrow
	iconst_1
	ifeq	l2 // new
	aload_0
	invokevirtual	Method msg:()Ljava/lang/Object;
	goto	l3 // areturn
l2	new	class scala/MatchError
	dup
	iload_1
	invokestatic	Method scala/runtime/BoxesRunTime.boxToInteger:(I)Ljava/lang/Integer;
	invokevirtual	Method java/lang/Object.toString:()Ljava/lang/String;
	invokespecial	Method scala/MatchError."<init>":(Ljava/lang/String;)V
	athrow
	iconst_1
	ifeq	l4 // new
	aload_0
	invokevirtual	Method ch:()Lscala/actors/Channel;
l3	areturn
l4	new	class scala/MatchError
	dup
	iload_1
	invokestatic	Method scala/runtime/BoxesRunTime.boxToInteger:(I)Ljava/lang/Integer;
	invokevirtual	Method java/lang/Object.toString:()Ljava/lang/String;
	invokespecial	Method scala/MatchError."<init>":(Ljava/lang/String;)V
	athrow
  Labels:
   	l1 = 43 // new
   	l2 = 69 // new
   	l3 = 92 // areturn
   	l4 = 93 // new

public int productArity();
  Signature: ()I
  Code:
   Stack=1, Locals=1, Args_size=1
	iconst_2
	ireturn
  Labels:

public java.lang.String productPrefix();
  Signature: ()Ljava/lang/String;
  Code:
   Stack=1, Locals=1, Args_size=1
	ldc	String !
	areturn
  Labels:

public boolean equals(java.lang.Object);
  Signature: (Ljava/lang/Object;)Z
  Code:
   Stack=3, Locals=5, Args_size=2
	aload_0
	aload_1
	if_acmpeq	l1 // iconst_1
	aload_1
	instanceof	class scala/actors/$bang
	ifeq	l2 // iconst_1
	aload_1
	checkcast	class scala/actors/$bang
	astore_2
	aload_2
	invokevirtual	Method ch:()Lscala/actors/Channel;
	astore_3
	aload_2
	invokevirtual	Method msg:()Ljava/lang/Object;
	astore	4
	aload_0
	aload_3
	aload	4
	invokespecial	Method gd1$1:(Lscala/actors/Channel;Ljava/lang/Object;)Z
	ifeq	l3 // iconst_1
	aload_1
	checkcast	class scala/actors/$bang
	aload_0
	invokeinterface	InterfaceMethod scala/Equals.canEqual:(Ljava/lang/Object;)Z
	goto	l4 // ifeq
l3	iconst_1
	ifeq	l5 // new
	iconst_0
	goto	l4 // ifeq
l5	new	class scala/MatchError
	dup
	aload_1
	invokevirtual	Method java/lang/Object.toString:()Ljava/lang/String;
	invokespecial	Method scala/MatchError."<init>":(Ljava/lang/String;)V
	athrow
l2	iconst_1
	ifeq	l6 // new
	iconst_0
l4	ifeq	l7 // iconst_0
l1	iconst_1
	goto	l8 // ireturn
l7	iconst_0
l8	ireturn
l6	new	class scala/MatchError
	dup
	aload_1
	invokevirtual	Method java/lang/Object.toString:()Ljava/lang/String;
	invokespecial	Method scala/MatchError."<init>":(Ljava/lang/String;)V
	athrow
  Labels:
   	l3 = 51 // iconst_1
   	l5 = 59 // new
   	l2 = 71 // iconst_1
   	l4 = 76 // ifeq
   	l1 = 79 // iconst_1
   	l7 = 83 // iconst_0
   	l8 = 84 // ireturn
   	l6 = 85 // new
  LocalVariableTable: 
   Start  Length  Slot  Name   Signature
   0      97      0    this       Lscala/actors/$bang;
   17      54      2    temp2       Lscala/actors/$bang;
   22      49      3    temp3       Lscala/actors/Channel;
   28      43      4    temp4       Ljava/lang/Object;


public java.lang.String toString();
  Signature: ()Ljava/lang/String;
  Code:
   Stack=2, Locals=1, Args_size=1
	getstatic	Field scala/runtime/ScalaRunTime$.MODULE$:Lscala/runtime/ScalaRunTime$;
	aload_0
	invokevirtual	Method scala/runtime/ScalaRunTime$._toString:(Lscala/Product;)Ljava/lang/String;
	areturn
  Labels:

public int hashCode();
  Signature: ()I
  Code:
   Stack=2, Locals=1, Args_size=1
	getstatic	Field scala/runtime/ScalaRunTime$.MODULE$:Lscala/runtime/ScalaRunTime$;
	aload_0
	invokevirtual	Method scala/runtime/ScalaRunTime$._hashCode:(Lscala/Product;)I
	ireturn
  Labels:

public scala.actors.$bang copy(scala.actors.Channel, java.lang.Object);
  Signature: (Lscala/actors/Channel;Ljava/lang/Object;)Lscala/actors/$bang;
  Code:
   Stack=4, Locals=3, Args_size=3
	new	class scala/actors/$bang
	dup
	aload_1
	aload_2
	invokespecial	Method "<init>":(Lscala/actors/Channel;Ljava/lang/Object;)V
	areturn
  Labels:
  LocalVariableTable: 
   Start  Length  Slot  Name   Signature
   0      10      0    this       Lscala/actors/$bang;
   0      10      1    ch       Lscala/actors/Channel;
   0      10      2    msg       Ljava/lang/Object;


public java.lang.Object msg();
  Signature: ()Ljava/lang/Object;
  Code:
   Stack=1, Locals=1, Args_size=1
	aload_0
	getfield	Field msg:Ljava/lang/Object;
	areturn
  Labels:
  Signature: length = 0x2
   00 6D 

public scala.actors.Channel ch();
  Signature: ()Lscala/actors/Channel;
  Code:
   Stack=1, Locals=1, Args_size=1
	aload_0
	getfield	Field ch:Lscala/actors/Channel;
	areturn
  Labels:
  Signature: length = 0x2
   00 6E 

public scala.actors.Channel copy$default$1();
  Signature: ()Lscala/actors/Channel;
  Code:
   Stack=1, Locals=1, Args_size=1
	aload_0
	invokevirtual	Method ch:()Lscala/actors/Channel;
	areturn
  Labels:

public java.lang.Object copy$default$2();
  Signature: ()Ljava/lang/Object;
  Code:
   Stack=1, Locals=1, Args_size=1
	aload_0
	invokevirtual	Method msg:()Ljava/lang/Object;
	areturn
  Labels:

public scala.collection.Iterator productElements();
  Signature: ()Lscala/collection/Iterator;
  Code:
   Stack=1, Locals=1, Args_size=1
	aload_0
	invokestatic	Method scala/Product$class.productElements:(Lscala/Product;)Lscala/collection/Iterator;
	areturn
  Labels:
  Deprecated: true

public scala.collection.Iterator productIterator();
  Signature: ()Lscala/collection/Iterator;
  Code:
   Stack=1, Locals=1, Args_size=1
	aload_0
	invokestatic	Method scala/Product$class.productIterator:(Lscala/Product;)Lscala/collection/Iterator;
	areturn
  Labels:

}

