Compiled from "AbstractActor.scala"
public abstract class scala.actors.AbstractActor$class extends java.lang.Object
  SourceFile: "AbstractActor.scala"
  Scala: length = 0x
   
  minor version: 0
  major version: 49
  Constant pool:
const #1 = Asciz	SourceFile;
const #2 = Asciz	AbstractActor.scala;
const #3 = Asciz	$init$;
const #4 = Asciz	(Lscala/actors/AbstractActor;)V;
const #5 = Asciz	Code;
const #6 = Asciz	LineNumberTable;
const #7 = Asciz	scala/actors/AbstractActor;
const #8 = class	#7;	//  scala/actors/AbstractActor
const #9 = Asciz	exiting_$eq;
const #10 = Asciz	(Z)V;
const #11 = NameAndType	#9:#10;//  exiting_$eq:(Z)V
const #12 = InterfaceMethod	#8.#11;	//  scala/actors/AbstractActor.exiting_$eq:(Z)V
const #13 = Asciz	$this;
const #14 = Asciz	Lscala/actors/AbstractActor;;
const #15 = Asciz	LocalVariableTable;
const #16 = Asciz	Scala;
const #17 = Asciz	scala/actors/AbstractActor$class;
const #18 = class	#17;	//  scala/actors/AbstractActor$class
const #19 = Asciz	java/lang/Object;
const #20 = class	#19;	//  java/lang/Object

{
public static void $init$(scala.actors.AbstractActor);
  Code:
   Stack=2, Locals=1, Args_size=1
   0:	aload_0
   1:	iconst_0
   2:	invokeinterface	#12,  2; //InterfaceMethod scala/actors/AbstractActor.exiting_$eq:(Z)V
   7:	return
  LineNumberTable: 
   line 21: 0

  LocalVariableTable: 
   Start  Length  Slot  Name   Signature
   0      8      0    $this       Lscala/actors/AbstractActor;


}

