Compiled from "ActorTask.scala"
public class scala.actors.ActorTask extends scala.actors.ReplyReactorTask implements scala.ScalaObject
  SourceFile: "ActorTask.scala"
  ScalaSig: length = 0x3
   05 00 00 
  RuntimeVisibleAnnotations: length = 0xB
   00 01 00 60 00 01 00 61 73 00 62 
  minor version: 0
  major version: 49
  Constant pool:
Asciz	SourceFile;
Asciz	ActorTask.scala;
Asciz	actor;
Asciz	Lscala/actors/Actor;;
Asciz	msg;
Asciz	Ljava/lang/Object;;
Asciz	beginExecution;
Asciz	()V;
Asciz	Code;
Asciz	LineNumberTable;
Asciz	scala/actors/ReplyReactorTask;
class	scala/actors/ReplyReactorTask
NameAndType	beginExecution:()V
Method	scala/actors/ReplyReactorTask.beginExecution:()V
Asciz	scala/actors/ActorTask;
class	scala/actors/ActorTask
NameAndType	actor:Lscala/actors/Actor;
Field	scala/actors/ActorTask.actor:Lscala/actors/Actor;
Asciz	scala/actors/Actor;
class	scala/actors/Actor
Asciz	shouldExit;
Asciz	()Z;
NameAndType	shouldExit:()Z
InterfaceMethod	scala/actors/Actor.shouldExit:()Z
Asciz	exit;
Asciz	()Lscala/runtime/Nothing$;;
NameAndType	exit:()Lscala/runtime/Nothing$;
InterfaceMethod	scala/actors/Actor.exit:()Lscala/runtime/Nothing$;
Asciz	terminateExecution;
Asciz	(Ljava/lang/Exception;)V;
Asciz	scala/Some;
class	scala/Some
Asciz	scala/actors/ReplyReactor;
class	scala/actors/ReplyReactor
Asciz	sender;
Asciz	()Lscala/actors/OutputChannel;;
NameAndType	sender:()Lscala/actors/OutputChannel;
InterfaceMethod	scala/actors/ReplyReactor.sender:()Lscala/actors/OutputChannel;
Asciz	<init>;
Asciz	(Ljava/lang/Object;)V;
NameAndType	"<init>":(Ljava/lang/Object;)V
Method	scala/Some."<init>":(Ljava/lang/Object;)V
Asciz	scala/None$;
class	scala/None$
Asciz	MODULE$;
Asciz	Lscala/None$;;
NameAndType	MODULE$:Lscala/None$;
Field	scala/None$.MODULE$:Lscala/None$;
Asciz	scala/actors/UncaughtException;
class	scala/actors/UncaughtException
NameAndType	msg:Ljava/lang/Object;
Field	scala/actors/ActorTask.msg:Ljava/lang/Object;
Asciz	java/lang/Thread;
class	java/lang/Thread
Asciz	currentThread;
Asciz	()Ljava/lang/Thread;;
NameAndType	currentThread:()Ljava/lang/Thread;
Method	java/lang/Thread.currentThread:()Ljava/lang/Thread;
Asciz	(Lscala/actors/Reactor;Lscala/Option;Lscala/Option;Ljava/lang/Thread;Ljava/lang/Exception;)V;
NameAndType	"<init>":(Lscala/actors/Reactor;Lscala/Option;Lscala/Option;Ljava/lang/Thread;Ljava/lang/Exception;)V
Method	scala/actors/UncaughtException."<init>":(Lscala/actors/Reactor;Lscala/Option;Lscala/Option;Ljava/lang/Thread;Ljava/lang/Exception;)V
Asciz	links;
Asciz	()Lscala/collection/immutable/List;;
NameAndType	links:()Lscala/collection/immutable/List;
InterfaceMethod	scala/actors/Actor.links:()Lscala/collection/immutable/List;
Asciz	scala/collection/IterableLike;
class	scala/collection/IterableLike
Asciz	isEmpty;
NameAndType	isEmpty:()Z
InterfaceMethod	scala/collection/IterableLike.isEmpty:()Z
Asciz	exitLinked;
NameAndType	exitLinked:(Ljava/lang/Object;)V
InterfaceMethod	scala/actors/Actor.exitLinked:(Ljava/lang/Object;)V
Asciz	java/lang/Exception;
class	java/lang/Exception
Asciz	this;
Asciz	Lscala/actors/ActorTask;;
Asciz	e;
Asciz	Ljava/lang/Exception;;
Asciz	exceptionResult1;
Asciz	Lscala/Option;;
Asciz	uncaught;
Asciz	Lscala/actors/UncaughtException;;
Asciz	LocalVariableTable;
Asciz	(Lscala/actors/Actor;Lscala/Function0;Lscala/PartialFunction;Ljava/lang/Object;)V;
Asciz	(Lscala/actors/ReplyReactor;Lscala/Function0;Lscala/PartialFunction;Ljava/lang/Object;)V;
NameAndType	"<init>":(Lscala/actors/ReplyReactor;Lscala/Function0;Lscala/PartialFunction;Ljava/lang/Object;)V
Method	scala/actors/ReplyReactorTask."<init>":(Lscala/actors/ReplyReactor;Lscala/Function0;Lscala/PartialFunction;Ljava/lang/Object;)V
Asciz	fun;
Asciz	Lscala/Function0;;
Asciz	handler;
Asciz	Lscala/PartialFunction;;
Asciz	(Lscala/actors/Actor;Lscala/Function0<Ljava/lang/Object;>;Lscala/PartialFunction<Ljava/lang/Object;Ljava/lang/Object;>;Ljava/lang/Object;)V;
Asciz	Signature;
Asciz	ScalaSig;
Asciz	Lscala/reflect/ScalaSignature;;
Asciz	bytes;
Asciz	\r3\"\tAGo:UCN\'BA\t7\r^8sg*\tQ!AtGdmE-\"C\tI!A!I+\=SKGo:UCN\C!B-6-7b\nTWm;\tA!!Q\nI\tQ!Y2u_J\t'%AC$xN\t-\t)A/a-81A\"$\t\tIa)8di&|g\r\tmI!\tUs\t=\t)A?9.8eY!E\tJ!!\tA'^5bY+hn;j_:\"D\n\"!aA!os\"AaBB%!%AngDQ%\naP5oSRtD#,Y5rCr11r1qr1 1s1#\"29WmZ5ob,7-;j_:$Ag!\tNiX.8bi,0Z2vi&|gk!)aG\rao\tQ\r9:HuujayE\ta:p_Rt\"A\n}\"a9bG.w-Z\n\"=dKB$n8}\";
Asciz	RuntimeVisibleAnnotations;
Asciz	scala/ScalaObject;
class	scala/ScalaObject

{
private final scala.actors.Actor actor;
  Signature: Lscala/actors/Actor;

private final java.lang.Object msg;
  Signature: Ljava/lang/Object;

public void beginExecution();
  Signature: ()V
  Code:
   Stack=1, Locals=1, Args_size=1
	aload_0
	invokespecial	Method scala/actors/ReplyReactorTask.beginExecution:()V
	aload_0
	getfield	Field actor:Lscala/actors/Actor;
	invokeinterface	InterfaceMethod scala/actors/Actor.shouldExit:()Z
	ifeq	l1 // return
	aload_0
	getfield	Field actor:Lscala/actors/Actor;
	invokeinterface	InterfaceMethod scala/actors/Actor.exit:()Lscala/runtime/Nothing$;
	athrow
l1	return
  Labels:
   	l1 = 26 // return

public void terminateExecution(java.lang.Exception);
  Signature: (Ljava/lang/Exception;)V
  Code:
   Stack=7, Locals=5, Args_size=2
	new	class scala/Some
	dup
	aload_0
	getfield	Field actor:Lscala/actors/Actor;
	invokeinterface	InterfaceMethod scala/actors/ReplyReactor.sender:()Lscala/actors/OutputChannel;
	invokespecial	Method scala/Some."<init>":(Ljava/lang/Object;)V
	astore_2
	goto	l1 // new
	pop
	getstatic	Field scala/None$.MODULE$:Lscala/None$;
	astore_2
l1	new	class scala/actors/UncaughtException
	dup
	aload_0
	getfield	Field actor:Lscala/actors/Actor;
	aload_0
	getfield	Field msg:Ljava/lang/Object;
	ifnonnull	l2 // new
	getstatic	Field scala/None$.MODULE$:Lscala/None$;
	goto	l3 // aload_2
l2	new	class scala/Some
	dup
	aload_0
	getfield	Field msg:Ljava/lang/Object;
	invokespecial	Method scala/Some."<init>":(Ljava/lang/Object;)V
l3	aload_2
	invokestatic	Method java/lang/Thread.currentThread:()Ljava/lang/Thread;
	aload_1
	invokespecial	Method scala/actors/UncaughtException."<init>":(Lscala/actors/Reactor;Lscala/Option;Lscala/Option;Ljava/lang/Thread;Ljava/lang/Exception;)V
	astore_3
	aload_0
	getfield	Field actor:Lscala/actors/Actor;
	dup
	astore	4
	monitorenter
	aload_0
	getfield	Field actor:Lscala/actors/Actor;
	invokeinterface	InterfaceMethod scala/actors/Actor.links:()Lscala/collection/immutable/List;
	invokeinterface	InterfaceMethod scala/collection/IterableLike.isEmpty:()Z
	ifeq	l4 // aload_0
	goto	l5 // aload
l4	aload_0
	getfield	Field actor:Lscala/actors/Actor;
	aload_3
	invokeinterface	InterfaceMethod scala/actors/Actor.exitLinked:(Ljava/lang/Object;)V
l5	aload	4
	monitorexit
	return
	aload	4
	monitorexit
	athrow
  Labels:
   	l1 = 25 // new
   	l2 = 46 // new
   	l3 = 57 // aload_2
   	l4 = 94 // aload_0
   	l5 = 104 // aload
  Exception table:
   from   to  target type
    74   107   108   any
     0    20    20   Class java/lang/Exception

  LocalVariableTable: 
   Start  Length  Slot  Name   Signature
   0      112      0    this       Lscala/actors/ActorTask;
   0      112      1    e       Ljava/lang/Exception;
   0      25      2    exceptionResult1       Lscala/Option;
   66      46      3    uncaught       Lscala/actors/UncaughtException;


public scala.actors.ActorTask(scala.actors.Actor, scala.Function0, scala.PartialFunction, java.lang.Object);
  Signature: (Lscala/actors/Actor;Lscala/Function0;Lscala/PartialFunction;Ljava/lang/Object;)V
  Code:
   Stack=5, Locals=5, Args_size=5
	aload_0
	aload_1
	putfield	Field actor:Lscala/actors/Actor;
	aload_0
	aload	4
	putfield	Field msg:Ljava/lang/Object;
	aload_0
	aload_1
	aload_2
	aload_3
	aload	4
	invokespecial	Method scala/actors/ReplyReactorTask."<init>":(Lscala/actors/ReplyReactor;Lscala/Function0;Lscala/PartialFunction;Ljava/lang/Object;)V
	return
  Labels:
  LocalVariableTable: 
   Start  Length  Slot  Name   Signature
   0      21      0    this       Lscala/actors/ActorTask;
   0      21      1    actor       Lscala/actors/Actor;
   0      21      2    fun       Lscala/Function0;
   0      21      3    handler       Lscala/PartialFunction;
   0      21      4    msg       Ljava/lang/Object;

  Signature: length = 0x2
   00 5D 

}

