Compiled from "Actor.scala"
public final class scala.actors.Actor$ extends java.lang.Object implements scala.ScalaObject
  SourceFile: "Actor.scala"
  Scala: length = 0x
   
  InnerClass: 
   public abstract Body=class scala/actors/Actor$Body of class scala/actors/Actor
   public final $anon$3=class scala/actors/Actor$$anon$3 of class scala/actors/Actor
   public final $anon$6=class scala/actors/Actor$$anon$6 of class scala/actors/Actor
   public final $anon$5=class scala/actors/Actor$$anon$5 of class scala/actors/Actor
   public final $anon$7=class scala/actors/Actor$$anon$7 of class scala/actors/Actor
   public final $anon$2=class scala/actors/Actor$$anon$2 of class scala/actors/Actor
   public final $anon$1=class scala/actors/Actor$$anon$1 of class scala/actors/Actor
   public final $anonfun$9=class scala/actors/Actor$$anonfun$9 of class scala/actors/Actor
   public final $anonfun$8=class scala/actors/Actor$$anonfun$8 of class scala/actors/Actor
   public final $anonfun$7=class scala/actors/Actor$$anonfun$7 of class scala/actors/Actor
   public final $anonfun$6=class scala/actors/Actor$$anonfun$6 of class scala/actors/Actor
   public final $anonfun$5=class scala/actors/Actor$$anonfun$5 of class scala/actors/Actor
   public final $anonfun$4=class scala/actors/Actor$$anonfun$4 of class scala/actors/Actor
   public final $anonfun$3=class scala/actors/Actor$$anonfun$3 of class scala/actors/Actor
   public final $anonfun$2=class scala/actors/Actor$$anonfun$2 of class scala/actors/Actor
   public final $anonfun$1=class scala/actors/Actor$$anonfun$1 of class scala/actors/Actor
   public final $anonfun$10=class scala/actors/Actor$$anonfun$10 of class scala/actors/Actor
   public final $anonfun$link$2=class scala/actors/Actor$$anonfun$link$2 of class scala/actors/Actor
   public final $anonfun$link$1=class scala/actors/Actor$$anonfun$link$1 of class scala/actors/Actor
   public final $anonfun$loop$1=class scala/actors/Actor$$anonfun$loop$1 of class scala/actors/Actor
   public final $anonfun$react$1=class scala/actors/Actor$$anonfun$react$1 of class scala/actors/Actor
   public final $anonfun$unlink$1=class scala/actors/Actor$$anonfun$unlink$1 of class scala/actors/Actor
   public final $anonfun$$qmark$1=class scala/actors/Actor$$anonfun$$qmark$1 of class scala/actors/Actor
   public final $anonfun$receive$1=class scala/actors/Actor$$anonfun$receive$1 of class scala/actors/Actor
   public final $anonfun$loopWhile$1=class scala/actors/Actor$$anonfun$loopWhile$1 of class scala/actors/Actor
   public final $anonfun$respondOn$1=class scala/actors/Actor$$anonfun$respondOn$1 of class scala/actors/Actor
   public final $anonfun$exitLinked$1=class scala/actors/Actor$$anonfun$exitLinked$1 of class scala/actors/Actor
   public final $anonfun$unlinkFrom$1=class scala/actors/Actor$$anonfun$unlinkFrom$1 of class scala/actors/Actor
   public RecursiveProxyHandler=class scala/actors/Actor$RecursiveProxyHandler of class scala/actors/Actor
   public final $anonfun$reactWithin$2=class scala/actors/Actor$$anonfun$reactWithin$2 of class scala/actors/Actor
   public final $anonfun$reactWithin$1=class scala/actors/Actor$$anonfun$reactWithin$1 of class scala/actors/Actor
   public final $anonfun$startSearch$1=class scala/actors/Actor$$anonfun$startSearch$1 of class scala/actors/Actor
   public final $anonfun$receiveWithin$2=class scala/actors/Actor$$anonfun$receiveWithin$2 of class scala/actors/Actor
   public final $anonfun$receiveWithin$1=class scala/actors/Actor$$anonfun$receiveWithin$1 of class scala/actors/Actor
  minor version: 0
  major version: 49
  Constant pool:
Asciz	SourceFile;
Asciz	Actor.scala;
Asciz	Scala;
Asciz	MODULE$;
Asciz	Lscala/actors/Actor$;;
Asciz	<clinit>;
Asciz	()V;
Asciz	Code;
Asciz	scala/actors/Actor$;
class	scala/actors/Actor$
Asciz	<init>;
NameAndType	"<init>":()V
Method	scala/actors/Actor$."<init>":()V
Asciz	suspendException;
Asciz	Lscala/actors/SuspendActorException;;
Asciz	timer;
Asciz	Ljava/util/Timer;;
Asciz	tl;
Asciz	Ljava/lang/ThreadLocal;;
Asciz	Ljava/lang/ThreadLocal<Lscala/actors/Reactor;>;;
Asciz	Signature;
Asciz	()Ljava/lang/ThreadLocal;;
Asciz	LineNumberTable;
NameAndType	tl:Ljava/lang/ThreadLocal;
Field	scala/actors/Actor$.tl:Ljava/lang/ThreadLocal;
Asciz	()Ljava/lang/ThreadLocal<Lscala/actors/Reactor;>;;
Asciz	()Ljava/util/Timer;;
NameAndType	timer:Ljava/util/Timer;
Field	scala/actors/Actor$.timer:Ljava/util/Timer;
Asciz	()Lscala/actors/SuspendActorException;;
NameAndType	suspendException:Lscala/actors/SuspendActorException;
Field	scala/actors/Actor$.suspendException:Lscala/actors/SuspendActorException;
Asciz	self;
Asciz	()Lscala/actors/Actor;;
Asciz	scala/actors/Scheduler$;
class	scala/actors/Scheduler$
Asciz	Lscala/actors/Scheduler$;;
NameAndType	MODULE$:Lscala/actors/Scheduler$;
Field	scala/actors/Scheduler$.MODULE$:Lscala/actors/Scheduler$;
Asciz	(Lscala/actors/IScheduler;)Lscala/actors/Actor;;
NameAndType	self:(Lscala/actors/IScheduler;)Lscala/actors/Actor;
Method	scala/actors/Actor$.self:(Lscala/actors/IScheduler;)Lscala/actors/Actor;
Asciz	rawSelf;
Asciz	(Lscala/actors/IScheduler;)Lscala/actors/Reactor;;
NameAndType	rawSelf:(Lscala/actors/IScheduler;)Lscala/actors/Reactor;
Method	scala/actors/Actor$.rawSelf:(Lscala/actors/IScheduler;)Lscala/actors/Reactor;
Asciz	scala/actors/Actor;
class	scala/actors/Actor
Asciz	this;
Asciz	sched;
Asciz	Lscala/actors/IScheduler;;
Asciz	LocalVariableTable;
Asciz	()Lscala/actors/Reactor;;
Asciz	java/lang/ThreadLocal;
class	java/lang/ThreadLocal
Asciz	get;
Asciz	()Ljava/lang/Object;;
NameAndType	get:()Ljava/lang/Object;
Method	java/lang/ThreadLocal.get:()Ljava/lang/Object;
Asciz	scala/actors/Reactor;
class	scala/actors/Reactor
Asciz	scala/actors/ActorProxy;
class	scala/actors/ActorProxy
Asciz	java/lang/Thread;
class	java/lang/Thread
Asciz	currentThread;
Asciz	()Ljava/lang/Thread;;
NameAndType	currentThread:()Ljava/lang/Thread;
Method	java/lang/Thread.currentThread:()Ljava/lang/Thread;
Asciz	(Ljava/lang/Thread;Lscala/actors/IScheduler;)V;
NameAndType	"<init>":(Ljava/lang/Thread;Lscala/actors/IScheduler;)V
Method	scala/actors/ActorProxy."<init>":(Ljava/lang/Thread;Lscala/actors/IScheduler;)V
Asciz	set;
Asciz	(Ljava/lang/Object;)V;
NameAndType	set:(Ljava/lang/Object;)V
Method	java/lang/ThreadLocal.set:(Ljava/lang/Object;)V
Asciz	r;
Asciz	Lscala/actors/ActorProxy;;
Asciz	s;
Asciz	Lscala/actors/Reactor;;
Asciz	scala$actors$Actor$$parentScheduler;
Asciz	()Lscala/actors/IScheduler;;
Asciz	scheduler;
NameAndType	scheduler:()Lscala/actors/IScheduler;
InterfaceMethod	scala/actors/Reactor.scheduler:()Lscala/actors/IScheduler;
Asciz	resetProxy;
NameAndType	scala$actors$Actor$$parentScheduler:()Lscala/actors/IScheduler;
Method	scala/actors/Actor$.scala$actors$Actor$$parentScheduler:()Lscala/actors/IScheduler;
Asciz	a;
Asciz	clearSelf;
NameAndType	tl:()Ljava/lang/ThreadLocal;
Method	scala/actors/Actor$.tl:()Ljava/lang/ThreadLocal;
Asciz	actor;
Asciz	(Lscala/Function0;)Lscala/actors/Actor;;
Asciz	scala/actors/Actor$$anon$1;
class	scala/actors/Actor$$anon$1
Asciz	(Lscala/Function0;)V;
NameAndType	"<init>":(Lscala/Function0;)V
Method	scala/actors/Actor$$anon$1."<init>":(Lscala/Function0;)V
Asciz	start;
NameAndType	start:()Lscala/actors/Actor;
InterfaceMethod	scala/actors/Actor.start:()Lscala/actors/Actor;
Asciz	body$1;
Asciz	Lscala/Function0;;
Asciz	Lscala/actors/Actor;;
Asciz	(Lscala/Function0<Ljava/lang/Object;>;)Lscala/actors/Actor;;
Asciz	reactor;
Asciz	scala/actors/Actor$$anon$2;
class	scala/actors/Actor$$anon$2
Method	scala/actors/Actor$$anon$2."<init>":(Lscala/Function0;)V
Asciz	body$2;
Asciz	(Lscala/Function0<Lscala/Responder<Ljava/lang/Object;>;>;)Lscala/actors/Actor;;
Asciz	$qmark;
NameAndType	self:()Lscala/actors/Actor;
Method	scala/actors/Actor$.self:()Lscala/actors/Actor;
NameAndType	$qmark:()Ljava/lang/Object;
InterfaceMethod	scala/actors/Actor.$qmark:()Ljava/lang/Object;
Asciz	receive;
Asciz	(Lscala/PartialFunction;)Ljava/lang/Object;;
NameAndType	receive:(Lscala/PartialFunction;)Ljava/lang/Object;
InterfaceMethod	scala/actors/Actor.receive:(Lscala/PartialFunction;)Ljava/lang/Object;
Asciz	f;
Asciz	Lscala/PartialFunction;;
Asciz	<A:Ljava/lang/Object;>(Lscala/PartialFunction<Ljava/lang/Object;TA;>;)TA;;
Asciz	receiveWithin;
Asciz	(JLscala/PartialFunction;)Ljava/lang/Object;;
NameAndType	receiveWithin:(JLscala/PartialFunction;)Ljava/lang/Object;
InterfaceMethod	scala/actors/Actor.receiveWithin:(JLscala/PartialFunction;)Ljava/lang/Object;
Asciz	msec;
Asciz	J;
Asciz	<R:Ljava/lang/Object;>(JLscala/PartialFunction<Ljava/lang/Object;TR;>;)TR;;
Asciz	react;
Asciz	(Lscala/PartialFunction;)Lscala/runtime/Nothing$;;
NameAndType	rawSelf:()Lscala/actors/Reactor;
Method	scala/actors/Actor$.rawSelf:()Lscala/actors/Reactor;
NameAndType	react:(Lscala/PartialFunction;)Lscala/runtime/Nothing$;
InterfaceMethod	scala/actors/Reactor.react:(Lscala/PartialFunction;)Lscala/runtime/Nothing$;
Asciz	(Lscala/PartialFunction<Ljava/lang/Object;Ljava/lang/Object;>;)Lscala/runtime/Nothing$;;
Asciz	reactWithin;
Asciz	(JLscala/PartialFunction;)Lscala/runtime/Nothing$;;
NameAndType	reactWithin:(JLscala/PartialFunction;)Lscala/runtime/Nothing$;
InterfaceMethod	scala/actors/Actor.reactWithin:(JLscala/PartialFunction;)Lscala/runtime/Nothing$;
Asciz	(JLscala/PartialFunction<Ljava/lang/Object;Ljava/lang/Object;>;)Lscala/runtime/Nothing$;;
Asciz	eventloop;
Asciz	scala/actors/Actor$RecursiveProxyHandler;
class	scala/actors/Actor$RecursiveProxyHandler
Asciz	(Lscala/actors/Reactor;Lscala/PartialFunction;)V;
NameAndType	"<init>":(Lscala/actors/Reactor;Lscala/PartialFunction;)V
Method	scala/actors/Actor$RecursiveProxyHandler."<init>":(Lscala/actors/Reactor;Lscala/PartialFunction;)V
Asciz	sender;
Asciz	()Lscala/actors/OutputChannel;;
Asciz	scala/actors/ReplyReactor;
class	scala/actors/ReplyReactor
NameAndType	sender:()Lscala/actors/OutputChannel;
InterfaceMethod	scala/actors/ReplyReactor.sender:()Lscala/actors/OutputChannel;
Asciz	()Lscala/actors/OutputChannel<Ljava/lang/Object;>;;
Asciz	reply;
NameAndType	reply:(Ljava/lang/Object;)V
InterfaceMethod	scala/actors/ReplyReactor.reply:(Ljava/lang/Object;)V
Asciz	msg;
Asciz	Ljava/lang/Object;;
Asciz	scala/runtime/BoxedUnit;
class	scala/runtime/BoxedUnit
Asciz	UNIT;
Asciz	Lscala/runtime/BoxedUnit;;
NameAndType	UNIT:Lscala/runtime/BoxedUnit;
Field	scala/runtime/BoxedUnit.UNIT:Lscala/runtime/BoxedUnit;
Asciz	mailboxSize;
Asciz	()I;
NameAndType	mailboxSize:()I
InterfaceMethod	scala/actors/Reactor.mailboxSize:()I
Asciz	respondOn;
Asciz	(Lscala/Function1;)Lscala/Function1;;
Asciz	scala/actors/Actor$$anonfun$respondOn$1;
class	scala/actors/Actor$$anonfun$respondOn$1
Asciz	(Lscala/Function1;)V;
NameAndType	"<init>":(Lscala/Function1;)V
Method	scala/actors/Actor$$anonfun$respondOn$1."<init>":(Lscala/Function1;)V
Asciz	fun$1;
Asciz	Lscala/Function1;;
Asciz	<A:Ljava/lang/Object;B:Ljava/lang/Object;>(Lscala/Function1<Lscala/PartialFunction<TA;Ljava/lang/Object;>;Lscala/runtime/Nothing$;>;)Lscala/Function1<Lscala/PartialFunction<TA;TB;>;Lscala/Responder<TB;>;>;;
Asciz	mkBody;
Asciz	(Lscala/Function0;)Lscala/actors/Actor$Body;;
Asciz	scala/actors/Actor$$anon$7;
class	scala/actors/Actor$$anon$7
Method	scala/actors/Actor$$anon$7."<init>":(Lscala/Function0;)V
Asciz	body$3;
Asciz	<a:Ljava/lang/Object;>(Lscala/Function0<Ta;>;)Ljava/lang/Object;;
Asciz	loop;
Asciz	scala/actors/Actor$$anonfun$loop$1;
class	scala/actors/Actor$$anonfun$loop$1
Method	scala/actors/Actor$$anonfun$loop$1."<init>":(Lscala/Function0;)V
NameAndType	MODULE$:Lscala/actors/Actor$;
Field	scala/actors/Actor$.MODULE$:Lscala/actors/Actor$;
Asciz	seq;
Asciz	(Lscala/Function0;Lscala/Function0;)V;
NameAndType	seq:(Lscala/Function0;Lscala/Function0;)V
InterfaceMethod	scala/actors/Reactor.seq:(Lscala/Function0;Lscala/Function0;)V
Asciz	body$4;
Asciz	(Lscala/Function0<Ljava/lang/Object;>;)V;
Asciz	loopWhile;
Asciz	scala/Function0;
class	scala/Function0
Asciz	apply;
NameAndType	apply:()Ljava/lang/Object;
InterfaceMethod	scala/Function0.apply:()Ljava/lang/Object;
Asciz	scala/runtime/BoxesRunTime;
class	scala/runtime/BoxesRunTime
Asciz	unboxToBoolean;
Asciz	(Ljava/lang/Object;)Z;
NameAndType	unboxToBoolean:(Ljava/lang/Object;)Z
Method	scala/runtime/BoxesRunTime.unboxToBoolean:(Ljava/lang/Object;)Z
Asciz	scala/actors/Actor$$anonfun$loopWhile$1;
class	scala/actors/Actor$$anonfun$loopWhile$1
NameAndType	"<init>":(Lscala/Function0;Lscala/Function0;)V
Method	scala/actors/Actor$$anonfun$loopWhile$1."<init>":(Lscala/Function0;Lscala/Function0;)V
Asciz	scala/actors/KillActorException;
class	scala/actors/KillActorException
Method	scala/actors/KillActorException."<init>":()V
Asciz	cond$1;
Asciz	body$5;
Asciz	(Lscala/Function0<Ljava/lang/Boolean;>;Lscala/Function0<Ljava/lang/Object;>;)V;
Asciz	link;
Asciz	(Lscala/actors/AbstractActor;)Lscala/actors/AbstractActor;;
NameAndType	link:(Lscala/actors/AbstractActor;)Lscala/actors/AbstractActor;
InterfaceMethod	scala/actors/Actor.link:(Lscala/actors/AbstractActor;)Lscala/actors/AbstractActor;
Asciz	to;
Asciz	Lscala/actors/AbstractActor;;
NameAndType	link:(Lscala/Function0;)Lscala/actors/Actor;
InterfaceMethod	scala/actors/Actor.link:(Lscala/Function0;)Lscala/actors/Actor;
Asciz	body;
Asciz	unlink;
Asciz	(Lscala/actors/Actor;)V;
Asciz	(Lscala/actors/AbstractActor;)V;
NameAndType	unlink:(Lscala/actors/AbstractActor;)V
InterfaceMethod	scala/actors/Actor.unlink:(Lscala/actors/AbstractActor;)V
Asciz	from;
Asciz	exit;
Asciz	(Ljava/lang/Object;)Lscala/runtime/Nothing$;;
NameAndType	exit:(Ljava/lang/Object;)Lscala/runtime/Nothing$;
InterfaceMethod	scala/actors/Actor.exit:(Ljava/lang/Object;)Lscala/runtime/Nothing$;
Asciz	reason;
Asciz	()Lscala/runtime/Nothing$;;
NameAndType	exit:()Lscala/runtime/Nothing$;
InterfaceMethod	scala/actors/Actor.exit:()Lscala/runtime/Nothing$;
Asciz	continue;
Asciz	java/lang/Object;
class	java/lang/Object
Method	java/lang/Object."<init>":()V
Method	java/lang/ThreadLocal."<init>":()V
Asciz	java/util/Timer;
class	java/util/Timer
Asciz	(Z)V;
NameAndType	"<init>":(Z)V
Method	java/util/Timer."<init>":(Z)V
Asciz	scala/actors/SuspendActorException;
class	scala/actors/SuspendActorException
Method	scala/actors/SuspendActorException."<init>":()V
Asciz	InnerClasses;
Asciz	scala/actors/Actor$Body;
class	scala/actors/Actor$Body
Asciz	Body;
Asciz	scala/actors/Actor$$anon$3;
class	scala/actors/Actor$$anon$3
Asciz	$anon$3;
Asciz	scala/actors/Actor$$anon$6;
class	scala/actors/Actor$$anon$6
Asciz	$anon$6;
Asciz	scala/actors/Actor$$anon$5;
class	scala/actors/Actor$$anon$5
Asciz	$anon$5;
Asciz	$anon$7;
Asciz	$anon$2;
Asciz	$anon$1;
Asciz	scala/actors/Actor$$anonfun$9;
class	scala/actors/Actor$$anonfun$9
Asciz	$anonfun$9;
Asciz	scala/actors/Actor$$anonfun$8;
class	scala/actors/Actor$$anonfun$8
Asciz	$anonfun$8;
Asciz	scala/actors/Actor$$anonfun$7;
class	scala/actors/Actor$$anonfun$7
Asciz	$anonfun$7;
Asciz	scala/actors/Actor$$anonfun$6;
class	scala/actors/Actor$$anonfun$6
Asciz	$anonfun$6;
Asciz	scala/actors/Actor$$anonfun$5;
class	scala/actors/Actor$$anonfun$5
Asciz	$anonfun$5;
Asciz	scala/actors/Actor$$anonfun$4;
class	scala/actors/Actor$$anonfun$4
Asciz	$anonfun$4;
Asciz	scala/actors/Actor$$anonfun$3;
class	scala/actors/Actor$$anonfun$3
Asciz	$anonfun$3;
Asciz	scala/actors/Actor$$anonfun$2;
class	scala/actors/Actor$$anonfun$2
Asciz	$anonfun$2;
Asciz	scala/actors/Actor$$anonfun$1;
class	scala/actors/Actor$$anonfun$1
Asciz	$anonfun$1;
Asciz	scala/actors/Actor$$anonfun$10;
class	scala/actors/Actor$$anonfun$10
Asciz	$anonfun$10;
Asciz	scala/actors/Actor$$anonfun$link$2;
class	scala/actors/Actor$$anonfun$link$2
Asciz	$anonfun$link$2;
Asciz	scala/actors/Actor$$anonfun$link$1;
class	scala/actors/Actor$$anonfun$link$1
Asciz	$anonfun$link$1;
Asciz	$anonfun$loop$1;
Asciz	scala/actors/Actor$$anonfun$react$1;
class	scala/actors/Actor$$anonfun$react$1
Asciz	$anonfun$react$1;
Asciz	scala/actors/Actor$$anonfun$unlink$1;
class	scala/actors/Actor$$anonfun$unlink$1
Asciz	$anonfun$unlink$1;
Asciz	scala/actors/Actor$$anonfun$$qmark$1;
class	scala/actors/Actor$$anonfun$$qmark$1
Asciz	$anonfun$$qmark$1;
Asciz	scala/actors/Actor$$anonfun$receive$1;
class	scala/actors/Actor$$anonfun$receive$1
Asciz	$anonfun$receive$1;
Asciz	$anonfun$loopWhile$1;
Asciz	$anonfun$respondOn$1;
Asciz	scala/actors/Actor$$anonfun$exitLinked$1;
class	scala/actors/Actor$$anonfun$exitLinked$1
Asciz	$anonfun$exitLinked$1;
Asciz	scala/actors/Actor$$anonfun$unlinkFrom$1;
class	scala/actors/Actor$$anonfun$unlinkFrom$1
Asciz	$anonfun$unlinkFrom$1;
Asciz	RecursiveProxyHandler;
Asciz	scala/actors/Actor$$anonfun$reactWithin$2;
class	scala/actors/Actor$$anonfun$reactWithin$2
Asciz	$anonfun$reactWithin$2;
Asciz	scala/actors/Actor$$anonfun$reactWithin$1;
class	scala/actors/Actor$$anonfun$reactWithin$1
Asciz	$anonfun$reactWithin$1;
Asciz	scala/actors/Actor$$anonfun$startSearch$1;
class	scala/actors/Actor$$anonfun$startSearch$1
Asciz	$anonfun$startSearch$1;
Asciz	scala/actors/Actor$$anonfun$receiveWithin$2;
class	scala/actors/Actor$$anonfun$receiveWithin$2
Asciz	$anonfun$receiveWithin$2;
Asciz	scala/actors/Actor$$anonfun$receiveWithin$1;
class	scala/actors/Actor$$anonfun$receiveWithin$1
Asciz	$anonfun$receiveWithin$1;
Asciz	scala/ScalaObject;
class	scala/ScalaObject

{
public static final scala.actors.Actor$ MODULE$;
  Signature: Lscala/actors/Actor$;

private final scala.actors.SuspendActorException suspendException;
  Signature: Lscala/actors/SuspendActorException;

private final java.util.Timer timer;
  Signature: Ljava/util/Timer;

private final java.lang.ThreadLocal tl;
  Signature: Ljava/lang/ThreadLocal;
  Signature: length = 0x2
   00 14 

public static {};
  Signature: ()V
  Code:
   Stack=1, Locals=0, Args_size=0
	new	class scala/actors/Actor$
	invokespecial	Method "<init>":()V
	return
  Labels:

public java.lang.ThreadLocal tl();
  Signature: ()Ljava/lang/ThreadLocal;
  Code:
   Stack=1, Locals=1, Args_size=1
	aload_0
	getfield	Field tl:Ljava/lang/ThreadLocal;
	areturn
  Labels:
  Signature: length = 0x2
   00 1A 

public java.util.Timer timer();
  Signature: ()Ljava/util/Timer;
  Code:
   Stack=1, Locals=1, Args_size=1
	aload_0
	getfield	Field timer:Ljava/util/Timer;
	areturn
  Labels:

public scala.actors.SuspendActorException suspendException();
  Signature: ()Lscala/actors/SuspendActorException;
  Code:
   Stack=1, Locals=1, Args_size=1
	aload_0
	getfield	Field suspendException:Lscala/actors/SuspendActorException;
	areturn
  Labels:

public scala.actors.Actor self();
  Signature: ()Lscala/actors/Actor;
  Code:
   Stack=2, Locals=1, Args_size=1
	aload_0
	getstatic	Field scala/actors/Scheduler$.MODULE$:Lscala/actors/Scheduler$;
	invokevirtual	Method self:(Lscala/actors/IScheduler;)Lscala/actors/Actor;
	areturn
  Labels:

public scala.actors.Actor self(scala.actors.IScheduler);
  Signature: (Lscala/actors/IScheduler;)Lscala/actors/Actor;
  Code:
   Stack=2, Locals=2, Args_size=2
	aload_0
	aload_1
	invokevirtual	Method rawSelf:(Lscala/actors/IScheduler;)Lscala/actors/Reactor;
	checkcast	class scala/actors/Actor
	areturn
  Labels:
  LocalVariableTable: 
   Start  Length  Slot  Name   Signature
   0      9      0    this       Lscala/actors/Actor$;
   0      9      1    sched       Lscala/actors/IScheduler;


public scala.actors.Reactor rawSelf();
  Signature: ()Lscala/actors/Reactor;
  Code:
   Stack=2, Locals=1, Args_size=1
	aload_0
	getstatic	Field scala/actors/Scheduler$.MODULE$:Lscala/actors/Scheduler$;
	invokevirtual	Method rawSelf:(Lscala/actors/IScheduler;)Lscala/actors/Reactor;
	areturn
  Labels:

public scala.actors.Reactor rawSelf(scala.actors.IScheduler);
  Signature: (Lscala/actors/IScheduler;)Lscala/actors/Reactor;
  Code:
   Stack=4, Locals=4, Args_size=2
	aload_0
	getfield	Field tl:Ljava/lang/ThreadLocal;
	invokevirtual	Method java/lang/ThreadLocal.get:()Ljava/lang/Object;
	checkcast	class scala/actors/Reactor
	astore_3
	aload_3
	ifnonnull	l1 // aload_3
	new	class scala/actors/ActorProxy
	dup
	invokestatic	Method java/lang/Thread.currentThread:()Ljava/lang/Thread;
	aload_1
	invokespecial	Method scala/actors/ActorProxy."<init>":(Ljava/lang/Thread;Lscala/actors/IScheduler;)V
	astore_2
	aload_0
	getfield	Field tl:Ljava/lang/ThreadLocal;
	aload_2
	invokevirtual	Method java/lang/ThreadLocal.set:(Ljava/lang/Object;)V
	aload_2
	goto	l2 // areturn
l1	aload_3
l2	areturn
  Labels:
   	l1 = 39 // aload_3
   	l2 = 40 // areturn
  LocalVariableTable: 
   Start  Length  Slot  Name   Signature
   0      41      0    this       Lscala/actors/Actor$;
   0      41      1    sched       Lscala/actors/IScheduler;
   27      9      2    r       Lscala/actors/ActorProxy;
   11      30      3    s       Lscala/actors/Reactor;


public final scala.actors.IScheduler scala$actors$Actor$$parentScheduler();
  Signature: ()Lscala/actors/IScheduler;
  Code:
   Stack=1, Locals=2, Args_size=1
	aload_0
	getfield	Field tl:Ljava/lang/ThreadLocal;
	invokevirtual	Method java/lang/ThreadLocal.get:()Ljava/lang/Object;
	checkcast	class scala/actors/Reactor
	astore_1
	aload_1
	ifnonnull	l1 // aload_1
	getstatic	Field scala/actors/Scheduler$.MODULE$:Lscala/actors/Scheduler$;
	goto	l2 // areturn
l1	aload_1
	invokeinterface	InterfaceMethod scala/actors/Reactor.scheduler:()Lscala/actors/IScheduler;
l2	areturn
  Labels:
   	l1 = 21 // aload_1
   	l2 = 27 // areturn
  LocalVariableTable: 
   Start  Length  Slot  Name   Signature
   0      28      0    this       Lscala/actors/Actor$;
   11      17      1    s       Lscala/actors/Reactor;


public void resetProxy();
  Signature: ()V
  Code:
   Stack=5, Locals=2, Args_size=1
	aload_0
	getfield	Field tl:Ljava/lang/ThreadLocal;
	invokevirtual	Method java/lang/ThreadLocal.get:()Ljava/lang/Object;
	checkcast	class scala/actors/Reactor
	astore_1
	aload_1
	ifnull	l1 // return
	aload_1
	instanceof	class scala/actors/ActorProxy
	ifeq	l1 // return
	aload_0
	getfield	Field tl:Ljava/lang/ThreadLocal;
	new	class scala/actors/ActorProxy
	dup
	invokestatic	Method java/lang/Thread.currentThread:()Ljava/lang/Thread;
	aload_0
	invokevirtual	Method scala$actors$Actor$$parentScheduler:()Lscala/actors/IScheduler;
	invokespecial	Method scala/actors/ActorProxy."<init>":(Ljava/lang/Thread;Lscala/actors/IScheduler;)V
	invokevirtual	Method java/lang/ThreadLocal.set:(Ljava/lang/Object;)V
l1	return
  Labels:
   	l1 = 43 // return
  LocalVariableTable: 
   Start  Length  Slot  Name   Signature
   0      44      0    this       Lscala/actors/Actor$;
   11      33      1    a       Lscala/actors/Reactor;


public void clearSelf();
  Signature: ()V
  Code:
   Stack=2, Locals=1, Args_size=1
	aload_0
	invokevirtual	Method tl:()Ljava/lang/ThreadLocal;
	aconst_null
	invokevirtual	Method java/lang/ThreadLocal.set:(Ljava/lang/Object;)V
	return
  Labels:

public scala.actors.Actor actor(scala.Function0);
  Signature: (Lscala/Function0;)Lscala/actors/Actor;
  Code:
   Stack=3, Locals=3, Args_size=2
	new	class scala/actors/Actor$$anon$1
	dup
	aload_1
	invokespecial	Method scala/actors/Actor$$anon$1."<init>":(Lscala/Function0;)V
	astore_2
	aload_2
	invokeinterface	InterfaceMethod scala/actors/Actor.start:()Lscala/actors/Actor;
	pop
	aload_2
	areturn
  Labels:
  LocalVariableTable: 
   Start  Length  Slot  Name   Signature
   0      18      0    this       Lscala/actors/Actor$;
   0      18      1    body$1       Lscala/Function0;
   9      8      2    a       Lscala/actors/Actor;

  Signature: length = 0x2
   00 6A 

public scala.actors.Actor reactor(scala.Function0);
  Signature: (Lscala/Function0;)Lscala/actors/Actor;
  Code:
   Stack=3, Locals=3, Args_size=2
	new	class scala/actors/Actor$$anon$2
	dup
	aload_1
	invokespecial	Method scala/actors/Actor$$anon$2."<init>":(Lscala/Function0;)V
	astore_2
	aload_2
	invokeinterface	InterfaceMethod scala/actors/Actor.start:()Lscala/actors/Actor;
	pop
	aload_2
	areturn
  Labels:
  LocalVariableTable: 
   Start  Length  Slot  Name   Signature
   0      18      0    this       Lscala/actors/Actor$;
   0      18      1    body$2       Lscala/Function0;
   9      8      2    a       Lscala/actors/Actor;

  Signature: length = 0x2
   00 70 

public java.lang.Object $qmark();
  Signature: ()Ljava/lang/Object;
  Code:
   Stack=1, Locals=1, Args_size=1
	aload_0
	invokevirtual	Method self:()Lscala/actors/Actor;
	invokeinterface	InterfaceMethod scala/actors/Actor.$qmark:()Ljava/lang/Object;
	areturn
  Labels:

public java.lang.Object receive(scala.PartialFunction);
  Signature: (Lscala/PartialFunction;)Ljava/lang/Object;
  Code:
   Stack=2, Locals=2, Args_size=2
	aload_0
	invokevirtual	Method self:()Lscala/actors/Actor;
	aload_1
	invokeinterface	InterfaceMethod scala/actors/Actor.receive:(Lscala/PartialFunction;)Ljava/lang/Object;
	areturn
  Labels:
  LocalVariableTable: 
   Start  Length  Slot  Name   Signature
   0      11      0    this       Lscala/actors/Actor$;
   0      11      1    f       Lscala/PartialFunction;

  Signature: length = 0x2
   00 7C 

public java.lang.Object receiveWithin(long, scala.PartialFunction);
  Signature: (JLscala/PartialFunction;)Ljava/lang/Object;
  Code:
   Stack=4, Locals=4, Args_size=3
	aload_0
	invokevirtual	Method self:()Lscala/actors/Actor;
	lload_1
	aload_3
	invokeinterface	InterfaceMethod scala/actors/Actor.receiveWithin:(JLscala/PartialFunction;)Ljava/lang/Object;
	areturn
  Labels:
  LocalVariableTable: 
   Start  Length  Slot  Name   Signature
   0      12      0    this       Lscala/actors/Actor$;
   0      12      1    msec       J
   0      12      3    f       Lscala/PartialFunction;

  Signature: length = 0x2
   00 FFFFFF83 

public scala.runtime.Nothing$ react(scala.PartialFunction);
  Signature: (Lscala/PartialFunction;)Lscala/runtime/Nothing$;
  Code:
   Stack=2, Locals=2, Args_size=2
	aload_0
	invokevirtual	Method rawSelf:()Lscala/actors/Reactor;
	aload_1
	invokeinterface	InterfaceMethod scala/actors/Reactor.react:(Lscala/PartialFunction;)Lscala/runtime/Nothing$;
	areturn
  Labels:
  LocalVariableTable: 
   Start  Length  Slot  Name   Signature
   0      11      0    this       Lscala/actors/Actor$;
   0      11      1    f       Lscala/PartialFunction;

  Signature: length = 0x2
   00 FFFFFF8A 

public scala.runtime.Nothing$ reactWithin(long, scala.PartialFunction);
  Signature: (JLscala/PartialFunction;)Lscala/runtime/Nothing$;
  Code:
   Stack=4, Locals=4, Args_size=3
	aload_0
	invokevirtual	Method self:()Lscala/actors/Actor;
	lload_1
	aload_3
	invokeinterface	InterfaceMethod scala/actors/Actor.reactWithin:(JLscala/PartialFunction;)Lscala/runtime/Nothing$;
	areturn
  Labels:
  LocalVariableTable: 
   Start  Length  Slot  Name   Signature
   0      12      0    this       Lscala/actors/Actor$;
   0      12      1    msec       J
   0      12      3    f       Lscala/PartialFunction;

  Signature: length = 0x2
   00 FFFFFF8F 

public scala.runtime.Nothing$ eventloop(scala.PartialFunction);
  Signature: (Lscala/PartialFunction;)Lscala/runtime/Nothing$;
  Code:
   Stack=5, Locals=2, Args_size=2
	aload_0
	invokevirtual	Method rawSelf:()Lscala/actors/Reactor;
	new	class scala/actors/Actor$RecursiveProxyHandler
	dup
	aload_0
	invokevirtual	Method rawSelf:()Lscala/actors/Reactor;
	aload_1
	invokespecial	Method scala/actors/Actor$RecursiveProxyHandler."<init>":(Lscala/actors/Reactor;Lscala/PartialFunction;)V
	invokeinterface	InterfaceMethod scala/actors/Reactor.react:(Lscala/PartialFunction;)Lscala/runtime/Nothing$;
	areturn
  Labels:
  LocalVariableTable: 
   Start  Length  Slot  Name   Signature
   0      22      0    this       Lscala/actors/Actor$;
   0      22      1    f       Lscala/PartialFunction;

  Signature: length = 0x2
   00 FFFFFF8A 

public scala.actors.OutputChannel sender();
  Signature: ()Lscala/actors/OutputChannel;
  Code:
   Stack=1, Locals=1, Args_size=1
	aload_0
	invokevirtual	Method rawSelf:()Lscala/actors/Reactor;
	checkcast	class scala/actors/ReplyReactor
	invokeinterface	InterfaceMethod scala/actors/ReplyReactor.sender:()Lscala/actors/OutputChannel;
	areturn
  Labels:
  Signature: length = 0x2
   00 FFFFFF9C 

public void reply(java.lang.Object);
  Signature: (Ljava/lang/Object;)V
  Code:
   Stack=2, Locals=2, Args_size=2
	aload_0
	invokevirtual	Method rawSelf:()Lscala/actors/Reactor;
	checkcast	class scala/actors/ReplyReactor
	aload_1
	invokeinterface	InterfaceMethod scala/actors/ReplyReactor.reply:(Ljava/lang/Object;)V
	return
  Labels:
  LocalVariableTable: 
   Start  Length  Slot  Name   Signature
   0      14      0    this       Lscala/actors/Actor$;
   0      14      1    msg       Ljava/lang/Object;


public void reply();
  Signature: ()V
  Code:
   Stack=2, Locals=1, Args_size=1
	aload_0
	invokevirtual	Method rawSelf:()Lscala/actors/Reactor;
	checkcast	class scala/actors/ReplyReactor
	getstatic	Field scala/runtime/BoxedUnit.UNIT:Lscala/runtime/BoxedUnit;
	invokeinterface	InterfaceMethod scala/actors/ReplyReactor.reply:(Ljava/lang/Object;)V
	return
  Labels:

public int mailboxSize();
  Signature: ()I
  Code:
   Stack=1, Locals=1, Args_size=1
	aload_0
	invokevirtual	Method rawSelf:()Lscala/actors/Reactor;
	invokeinterface	InterfaceMethod scala/actors/Reactor.mailboxSize:()I
	ireturn
  Labels:

public scala.Function1 respondOn(scala.Function1);
  Signature: (Lscala/Function1;)Lscala/Function1;
  Code:
   Stack=3, Locals=2, Args_size=2
	new	class scala/actors/Actor$$anonfun$respondOn$1
	dup
	aload_1
	invokespecial	Method scala/actors/Actor$$anonfun$respondOn$1."<init>":(Lscala/Function1;)V
	areturn
  Labels:
  LocalVariableTable: 
   Start  Length  Slot  Name   Signature
   0      9      0    this       Lscala/actors/Actor$;
   0      9      1    fun$1       Lscala/Function1;

  Signature: length = 0x2
   00 FFFFFFB5 

public scala.actors.Actor$Body mkBody(scala.Function0);
  Signature: (Lscala/Function0;)Lscala/actors/Actor$Body;
  Code:
   Stack=3, Locals=2, Args_size=2
	new	class scala/actors/Actor$$anon$7
	dup
	aload_1
	invokespecial	Method scala/actors/Actor$$anon$7."<init>":(Lscala/Function0;)V
	areturn
  Labels:
  LocalVariableTable: 
   Start  Length  Slot  Name   Signature
   0      9      0    this       Lscala/actors/Actor$;
   0      9      1    body$3       Lscala/Function0;

  Signature: length = 0x2
   00 FFFFFFBC 

public void loop(scala.Function0);
  Signature: (Lscala/Function0;)V
  Code:
   Stack=3, Locals=4, Args_size=2
	new	class scala/actors/Actor$$anon$7
	dup
	aload_1
	invokespecial	Method scala/actors/Actor$$anon$7."<init>":(Lscala/Function0;)V
	pop
	new	class scala/actors/Actor$$anonfun$loop$1
	dup
	aload_1
	invokespecial	Method scala/actors/Actor$$anonfun$loop$1."<init>":(Lscala/Function0;)V
	astore_3
	getstatic	Field MODULE$:Lscala/actors/Actor$;
	astore_2
	aload_2
	getstatic	Field scala/actors/Scheduler$.MODULE$:Lscala/actors/Scheduler$;
	invokevirtual	Method rawSelf:(Lscala/actors/IScheduler;)Lscala/actors/Reactor;
	aload_1
	aload_3
	invokeinterface	InterfaceMethod scala/actors/Reactor.seq:(Lscala/Function0;Lscala/Function0;)V
	return
  Labels:
  LocalVariableTable: 
   Start  Length  Slot  Name   Signature
   0      37      0    this       Lscala/actors/Actor$;
   0      37      1    body$4       Lscala/Function0;

  Signature: length = 0x2
   00 FFFFFFC8 

public void loopWhile(scala.Function0, scala.Function0);
  Signature: (Lscala/Function0;Lscala/Function0;)V
  Code:
   Stack=4, Locals=5, Args_size=3
	aload_1
	invokeinterface	InterfaceMethod scala/Function0.apply:()Ljava/lang/Object;
	invokestatic	Method scala/runtime/BoxesRunTime.unboxToBoolean:(Ljava/lang/Object;)Z
	ifeq	l1 // new
	new	class scala/actors/Actor$$anon$7
	dup
	aload_2
	invokespecial	Method scala/actors/Actor$$anon$7."<init>":(Lscala/Function0;)V
	pop
	new	class scala/actors/Actor$$anonfun$loopWhile$1
	dup
	aload_1
	aload_2
	invokespecial	Method scala/actors/Actor$$anonfun$loopWhile$1."<init>":(Lscala/Function0;Lscala/Function0;)V
	astore	4
	getstatic	Field MODULE$:Lscala/actors/Actor$;
	astore_3
	aload_3
	getstatic	Field scala/actors/Scheduler$.MODULE$:Lscala/actors/Scheduler$;
	invokevirtual	Method rawSelf:(Lscala/actors/IScheduler;)Lscala/actors/Reactor;
	aload_2
	aload	4
	invokeinterface	InterfaceMethod scala/actors/Reactor.seq:(Lscala/Function0;Lscala/Function0;)V
	return
l1	new	class scala/actors/KillActorException
	dup
	invokespecial	Method scala/actors/KillActorException."<init>":()V
	athrow
  Labels:
   	l1 = 52 // new
  LocalVariableTable: 
   Start  Length  Slot  Name   Signature
   0      60      0    this       Lscala/actors/Actor$;
   0      60      1    cond$1       Lscala/Function0;
   0      60      2    body$5       Lscala/Function0;

  Signature: length = 0x2
   00 FFFFFFDE 

public scala.actors.AbstractActor link(scala.actors.AbstractActor);
  Signature: (Lscala/actors/AbstractActor;)Lscala/actors/AbstractActor;
  Code:
   Stack=2, Locals=2, Args_size=2
	aload_0
	invokevirtual	Method self:()Lscala/actors/Actor;
	aload_1
	invokeinterface	InterfaceMethod scala/actors/Actor.link:(Lscala/actors/AbstractActor;)Lscala/actors/AbstractActor;
	areturn
  Labels:
  LocalVariableTable: 
   Start  Length  Slot  Name   Signature
   0      11      0    this       Lscala/actors/Actor$;
   0      11      1    to       Lscala/actors/AbstractActor;


public scala.actors.Actor link(scala.Function0);
  Signature: (Lscala/Function0;)Lscala/actors/Actor;
  Code:
   Stack=2, Locals=2, Args_size=2
	aload_0
	invokevirtual	Method self:()Lscala/actors/Actor;
	aload_1
	invokeinterface	InterfaceMethod scala/actors/Actor.link:(Lscala/Function0;)Lscala/actors/Actor;
	areturn
  Labels:
  LocalVariableTable: 
   Start  Length  Slot  Name   Signature
   0      11      0    this       Lscala/actors/Actor$;
   0      11      1    body       Lscala/Function0;

  Signature: length = 0x2
   00 6A 

public void unlink(scala.actors.Actor);
  Signature: (Lscala/actors/Actor;)V
  Code:
   Stack=2, Locals=2, Args_size=2
	aload_0
	invokevirtual	Method self:()Lscala/actors/Actor;
	aload_1
	invokeinterface	InterfaceMethod scala/actors/Actor.unlink:(Lscala/actors/AbstractActor;)V
	return
  Labels:
  LocalVariableTable: 
   Start  Length  Slot  Name   Signature
   0      11      0    this       Lscala/actors/Actor$;
   0      11      1    from       Lscala/actors/Actor;


public scala.runtime.Nothing$ exit(java.lang.Object);
  Signature: (Ljava/lang/Object;)Lscala/runtime/Nothing$;
  Code:
   Stack=2, Locals=2, Args_size=2
	aload_0
	invokevirtual	Method self:()Lscala/actors/Actor;
	aload_1
	invokeinterface	InterfaceMethod scala/actors/Actor.exit:(Ljava/lang/Object;)Lscala/runtime/Nothing$;
	areturn
  Labels:
  LocalVariableTable: 
   Start  Length  Slot  Name   Signature
   0      11      0    this       Lscala/actors/Actor$;
   0      11      1    reason       Ljava/lang/Object;


public scala.runtime.Nothing$ exit();
  Signature: ()Lscala/runtime/Nothing$;
  Code:
   Stack=1, Locals=1, Args_size=1
	aload_0
	invokevirtual	Method self:()Lscala/actors/Actor;
	invokeinterface	InterfaceMethod scala/actors/Actor.exit:()Lscala/runtime/Nothing$;
	areturn
  Labels:

public void continue();
  Signature: ()V
  Code:
   Stack=2, Locals=1, Args_size=1
	new	class scala/actors/KillActorException
	dup
	invokespecial	Method scala/actors/KillActorException."<init>":()V
	athrow
  Labels:

private scala.actors.Actor$();
  Signature: ()V
  Code:
   Stack=4, Locals=1, Args_size=1
	aload_0
	invokespecial	Method java/lang/Object."<init>":()V
	aload_0
	putstatic	Field MODULE$:Lscala/actors/Actor$;
	aload_0
	new	class java/lang/ThreadLocal
	dup
	invokespecial	Method java/lang/ThreadLocal."<init>":()V
	putfield	Field tl:Ljava/lang/ThreadLocal;
	aload_0
	new	class java/util/Timer
	dup
	iconst_1
	invokespecial	Method java/util/Timer."<init>":(Z)V
	putfield	Field timer:Ljava/util/Timer;
	aload_0
	new	class scala/actors/SuspendActorException
	dup
	invokespecial	Method scala/actors/SuspendActorException."<init>":()V
	putfield	Field suspendException:Lscala/actors/SuspendActorException;
	return
  Labels:

}

