Compiled from "Actor.scala"
public final class scala.actors.Actor$$anonfun$respondOn$1$$anon$4 extends scala.Responder
  SourceFile: "Actor.scala"
  Signature: length = 0x2
   00 38 
  Scala: length = 0x
   
  InnerClass: 
   public final #61= #36 of #60; //$anonfun$respondOn$1=class scala/actors/Actor$$anonfun$respondOn$1 of class scala/actors/Actor
   public final #62= #17 of #36; //$anon$4=class scala/actors/Actor$$anonfun$respondOn$1$$anon$4 of class scala/actors/Actor$$anonfun$respondOn$1
  minor version: 0
  major version: 49
  Constant pool:
const #1 = Asciz	SourceFile;
const #2 = Asciz	Actor.scala;
const #3 = Asciz	caseBlock$1;
const #4 = Asciz	Lscala/PartialFunction;;
const #5 = Asciz	$outer;
const #6 = Asciz	Lscala/actors/Actor$$anonfun$respondOn$1;;
const #7 = Asciz	<init>;
const #8 = Asciz	(Lscala/actors/Actor$$anonfun$respondOn$1;Lscala/PartialFunction;)V;
const #9 = Asciz	Code;
const #10 = Asciz	LineNumberTable;
const #11 = Asciz	java/lang/NullPointerException;
const #12 = class	#11;	//  java/lang/NullPointerException
const #13 = Asciz	()V;
const #14 = NameAndType	#7:#13;//  "<init>":()V
const #15 = Method	#12.#14;	//  java/lang/NullPointerException."<init>":()V
const #16 = Asciz	scala/actors/Actor$$anonfun$respondOn$1$$anon$4;
const #17 = class	#16;	//  scala/actors/Actor$$anonfun$respondOn$1$$anon$4
const #18 = NameAndType	#5:#6;//  $outer:Lscala/actors/Actor$$anonfun$respondOn$1;
const #19 = Field	#17.#18;	//  scala/actors/Actor$$anonfun$respondOn$1$$anon$4.$outer:Lscala/actors/Actor$$anonfun$respondOn$1;
const #20 = NameAndType	#3:#4;//  caseBlock$1:Lscala/PartialFunction;
const #21 = Field	#17.#20;	//  scala/actors/Actor$$anonfun$respondOn$1$$anon$4.caseBlock$1:Lscala/PartialFunction;
const #22 = Asciz	scala/Responder;
const #23 = class	#22;	//  scala/Responder
const #24 = Method	#23.#14;	//  scala/Responder."<init>":()V
const #25 = Asciz	this;
const #26 = Asciz	Lscala/actors/Actor$$anonfun$respondOn$1$$anon$4;;
const #27 = Asciz	LocalVariableTable;
const #28 = Asciz	respond;
const #29 = Asciz	(Lscala/Function1;)V;
const #30 = Asciz	(Lscala/Function1;)Lscala/runtime/Nothing$;;
const #31 = NameAndType	#28:#30;//  respond:(Lscala/Function1;)Lscala/runtime/Nothing$;
const #32 = Method	#17.#31;	//  scala/actors/Actor$$anonfun$respondOn$1$$anon$4.respond:(Lscala/Function1;)Lscala/runtime/Nothing$;
const #33 = Asciz	k;
const #34 = Asciz	Lscala/Function1;;
const #35 = Asciz	scala/actors/Actor$$anonfun$respondOn$1;
const #36 = class	#35;	//  scala/actors/Actor$$anonfun$respondOn$1
const #37 = Asciz	fun$1;
const #38 = NameAndType	#37:#34;//  fun$1:Lscala/Function1;
const #39 = Field	#36.#38;	//  scala/actors/Actor$$anonfun$respondOn$1.fun$1:Lscala/Function1;
const #40 = Asciz	scala/PartialFunction;
const #41 = class	#40;	//  scala/PartialFunction
const #42 = Asciz	andThen;
const #43 = Asciz	(Lscala/Function1;)Lscala/PartialFunction;;
const #44 = NameAndType	#42:#43;//  andThen:(Lscala/Function1;)Lscala/PartialFunction;
const #45 = InterfaceMethod	#41.#44;	//  scala/PartialFunction.andThen:(Lscala/Function1;)Lscala/PartialFunction;
const #46 = Asciz	scala/Function1;
const #47 = class	#46;	//  scala/Function1
const #48 = Asciz	apply;
const #49 = Asciz	(Ljava/lang/Object;)Ljava/lang/Object;;
const #50 = NameAndType	#48:#49;//  apply:(Ljava/lang/Object;)Ljava/lang/Object;
const #51 = InterfaceMethod	#47.#50;	//  scala/Function1.apply:(Ljava/lang/Object;)Ljava/lang/Object;
const #52 = Asciz	scala/runtime/Nothing$;
const #53 = class	#52;	//  scala/runtime/Nothing$
const #54 = Asciz	(Lscala/Function1<TB;Ljava/lang/Object;>;)Lscala/runtime/Nothing$;;
const #55 = Asciz	Signature;
const #56 = Asciz	Lscala/Responder<TB;>;;
const #57 = Asciz	Scala;
const #58 = Asciz	InnerClasses;
const #59 = Asciz	scala/actors/Actor;
const #60 = class	#59;	//  scala/actors/Actor
const #61 = Asciz	$anonfun$respondOn$1;
const #62 = Asciz	$anon$4;

{
public scala.actors.Actor$$anonfun$respondOn$1$$anon$4(scala.actors.Actor$$anonfun$respondOn$1, scala.PartialFunction);
  Code:
   Stack=2, Locals=3, Args_size=3
   0:	aload_1
   1:	ifnonnull	12
   4:	new	#12; //class java/lang/NullPointerException
   7:	dup
   8:	invokespecial	#15; //Method java/lang/NullPointerException."<init>":()V
   11:	athrow
   12:	aload_0
   13:	aload_1
   14:	putfield	#19; //Field $outer:Lscala/actors/Actor$$anonfun$respondOn$1;
   17:	aload_0
   18:	aload_2
   19:	putfield	#21; //Field caseBlock$1:Lscala/PartialFunction;
   22:	aload_0
   23:	invokespecial	#24; //Method scala/Responder."<init>":()V
   26:	return
  LineNumberTable: 
   line 267: 0

  LocalVariableTable: 
   Start  Length  Slot  Name   Signature
   0      27      0    this       Lscala/actors/Actor$$anonfun$respondOn$1$$anon$4;
   0      27      1    $outer       Lscala/actors/Actor$$anonfun$respondOn$1;


public void respond(scala.Function1);
  Code:
   Stack=2, Locals=2, Args_size=2
   0:	aload_0
   1:	aload_1
   2:	invokevirtual	#32; //Method respond:(Lscala/Function1;)Lscala/runtime/Nothing$;
   5:	athrow
  LineNumberTable: 
   line 267: 0

  LocalVariableTable: 
   Start  Length  Slot  Name   Signature
   0      6      0    this       Lscala/actors/Actor$$anonfun$respondOn$1$$anon$4;
   0      6      1    k       Lscala/Function1;


public scala.runtime.Nothing$ respond(scala.Function1);
  Code:
   Stack=3, Locals=2, Args_size=2
   0:	aload_0
   1:	getfield	#19; //Field $outer:Lscala/actors/Actor$$anonfun$respondOn$1;
   4:	getfield	#39; //Field scala/actors/Actor$$anonfun$respondOn$1.fun$1:Lscala/Function1;
   7:	aload_0
   8:	getfield	#21; //Field caseBlock$1:Lscala/PartialFunction;
   11:	aload_1
   12:	invokeinterface	#45,  2; //InterfaceMethod scala/PartialFunction.andThen:(Lscala/Function1;)Lscala/PartialFunction;
   17:	invokeinterface	#51,  2; //InterfaceMethod scala/Function1.apply:(Ljava/lang/Object;)Ljava/lang/Object;
   22:	checkcast	#53; //class scala/runtime/Nothing$
   25:	areturn
  LineNumberTable: 
   line 268: 0

  LocalVariableTable: 
   Start  Length  Slot  Name   Signature
   0      26      0    this       Lscala/actors/Actor$$anonfun$respondOn$1$$anon$4;
   0      26      1    k       Lscala/Function1;

  Signature: length = 0x2
   00 36 

}

