Compiled from "Actor.scala"
public final class scala.actors.Actor$$anonfun$exitLinked$1 extends java.lang.Object implements scala.Function1,scala.ScalaObject,java.io.Serializable
  SourceFile: "Actor.scala"
  Scala: length = 0x
   
  InnerClass: 
   public final $anonfun$exitLinked$1=class scala/actors/Actor$$anonfun$exitLinked$1 of class scala/actors/Actor
  minor version: 0
  major version: 49
  Constant pool:
Asciz	SourceFile;
Asciz	Actor.scala;
Asciz	<clinit>;
Asciz	()V;
Asciz	Code;
Asciz	serialVersionUID;
Asciz	J;
Asciz	scala/actors/Actor$$anonfun$exitLinked$1;
class	scala/actors/Actor$$anonfun$exitLinked$1
NameAndType	serialVersionUID:J
Field	scala/actors/Actor$$anonfun$exitLinked$1.serialVersionUID:J
Asciz	$outer;
Asciz	Lscala/actors/Actor;;
Asciz	<init>;
Asciz	(Lscala/actors/Actor;)V;
Asciz	LineNumberTable;
Asciz	java/lang/NullPointerException;
class	java/lang/NullPointerException
NameAndType	"<init>":()V
Method	java/lang/NullPointerException."<init>":()V
NameAndType	$outer:Lscala/actors/Actor;
Field	scala/actors/Actor$$anonfun$exitLinked$1.$outer:Lscala/actors/Actor;
Asciz	java/lang/Object;
class	java/lang/Object
Method	java/lang/Object."<init>":()V
Asciz	scala/Function1$class;
class	scala/Function1$class
Asciz	$init$;
Asciz	(Lscala/Function1;)V;
NameAndType	$init$:(Lscala/Function1;)V
Method	scala/Function1$class.$init$:(Lscala/Function1;)V
Asciz	this;
Asciz	Lscala/actors/Actor$$anonfun$exitLinked$1;;
Asciz	LocalVariableTable;
Asciz	apply;
Asciz	(Ljava/lang/Object;)Ljava/lang/Object;;
Asciz	scala/actors/AbstractActor;
class	scala/actors/AbstractActor
Asciz	(Lscala/actors/AbstractActor;)V;
NameAndType	apply:(Lscala/actors/AbstractActor;)V
Method	scala/actors/Actor$$anonfun$exitLinked$1.apply:(Lscala/actors/AbstractActor;)V
Asciz	scala/runtime/BoxedUnit;
class	scala/runtime/BoxedUnit
Asciz	UNIT;
Asciz	Lscala/runtime/BoxedUnit;;
NameAndType	UNIT:Lscala/runtime/BoxedUnit;
Field	scala/runtime/BoxedUnit.UNIT:Lscala/runtime/BoxedUnit;
Asciz	v1;
Asciz	Ljava/lang/Object;;
Asciz	scala/actors/Actor;
class	scala/actors/Actor
Asciz	unlink;
NameAndType	unlink:(Lscala/actors/AbstractActor;)V
InterfaceMethod	scala/actors/Actor.unlink:(Lscala/actors/AbstractActor;)V
Asciz	exiting;
Asciz	()Z;
NameAndType	exiting:()Z
InterfaceMethod	scala/actors/AbstractActor.exiting:()Z
Asciz	exitReason;
Asciz	()Ljava/lang/Object;;
NameAndType	exitReason:()Ljava/lang/Object;
InterfaceMethod	scala/actors/Actor.exitReason:()Ljava/lang/Object;
Asciz	exit;
Asciz	(Lscala/actors/AbstractActor;Ljava/lang/Object;)V;
NameAndType	exit:(Lscala/actors/AbstractActor;Ljava/lang/Object;)V
InterfaceMethod	scala/actors/AbstractActor.exit:(Lscala/actors/AbstractActor;Ljava/lang/Object;)V
Asciz	linked;
Asciz	Lscala/actors/AbstractActor;;
Asciz	andThen;
Asciz	(Lscala/Function1;)Lscala/Function1;;
Asciz	(Lscala/Function1;Lscala/Function1;)Lscala/Function1;;
NameAndType	andThen:(Lscala/Function1;Lscala/Function1;)Lscala/Function1;
Method	scala/Function1$class.andThen:(Lscala/Function1;Lscala/Function1;)Lscala/Function1;
Asciz	g;
Asciz	Lscala/Function1;;
Asciz	compose;
NameAndType	compose:(Lscala/Function1;Lscala/Function1;)Lscala/Function1;
Method	scala/Function1$class.compose:(Lscala/Function1;Lscala/Function1;)Lscala/Function1;
Asciz	toString;
Asciz	()Ljava/lang/String;;
Asciz	(Lscala/Function1;)Ljava/lang/String;;
NameAndType	toString:(Lscala/Function1;)Ljava/lang/String;
Method	scala/Function1$class.toString:(Lscala/Function1;)Ljava/lang/String;
Asciz	Scala;
Asciz	InnerClasses;
Asciz	$anonfun$exitLinked$1;
Asciz	scala/Function1;
class	scala/Function1
Asciz	scala/ScalaObject;
class	scala/ScalaObject
Asciz	java/io/Serializable;
class	java/io/Serializable

{
public static final long serialVersionUID;
  Signature: J

private final scala.actors.Actor $outer;
  Signature: Lscala/actors/Actor;

public static {};
  Signature: ()V
  Code:
   Stack=2, Locals=0, Args_size=0
	lconst_0
	putstatic	Field serialVersionUID:J
	return
  Labels:

public scala.actors.Actor$$anonfun$exitLinked$1(scala.actors.Actor);
  Signature: (Lscala/actors/Actor;)V
  Code:
   Stack=2, Locals=2, Args_size=2
	aload_1
	ifnonnull	l1 // aload_0
	new	class java/lang/NullPointerException
	dup
	invokespecial	Method java/lang/NullPointerException."<init>":()V
	athrow
l1	aload_0
	aload_1
	putfield	Field $outer:Lscala/actors/Actor;
	aload_0
	invokespecial	Method java/lang/Object."<init>":()V
	aload_0
	invokestatic	Method scala/Function1$class.$init$:(Lscala/Function1;)V
	return
  Labels:
   	l1 = 12 // aload_0
  LocalVariableTable: 
   Start  Length  Slot  Name   Signature
   0      26      0    this       Lscala/actors/Actor$$anonfun$exitLinked$1;
   0      26      1    $outer       Lscala/actors/Actor;


public final java.lang.Object apply(java.lang.Object);
  Signature: (Ljava/lang/Object;)Ljava/lang/Object;
  Code:
   Stack=2, Locals=3, Args_size=2
	aload_0
	getfield	Field $outer:Lscala/actors/Actor;
	astore_2
	aload_0
	aload_1
	checkcast	class scala/actors/AbstractActor
	invokevirtual	Method apply:(Lscala/actors/AbstractActor;)V
	getstatic	Field scala/runtime/BoxedUnit.UNIT:Lscala/runtime/BoxedUnit;
	areturn
  Labels:
  LocalVariableTable: 
   Start  Length  Slot  Name   Signature
   0      17      0    this       Lscala/actors/Actor$$anonfun$exitLinked$1;
   5      12      1    v1       Ljava/lang/Object;


public final void apply(scala.actors.AbstractActor);
  Signature: (Lscala/actors/AbstractActor;)V
  Code:
   Stack=3, Locals=3, Args_size=2
	aload_0
	getfield	Field $outer:Lscala/actors/Actor;
	astore_2
	aload_0
	getfield	Field $outer:Lscala/actors/Actor;
	aload_1
	invokeinterface	InterfaceMethod scala/actors/Actor.unlink:(Lscala/actors/AbstractActor;)V
	aload_1
	invokeinterface	InterfaceMethod scala/actors/AbstractActor.exiting:()Z
	ifne	l1 // return
	aload_1
	aload_0
	getfield	Field $outer:Lscala/actors/Actor;
	aload_0
	getfield	Field $outer:Lscala/actors/Actor;
	invokeinterface	InterfaceMethod scala/actors/Actor.exitReason:()Ljava/lang/Object;
	invokeinterface	InterfaceMethod scala/actors/AbstractActor.exit:(Lscala/actors/AbstractActor;Ljava/lang/Object;)V
l1	return
  Labels:
   	l1 = 43 // return
  LocalVariableTable: 
   Start  Length  Slot  Name   Signature
   0      44      0    this       Lscala/actors/Actor$$anonfun$exitLinked$1;
   5      39      1    linked       Lscala/actors/AbstractActor;


public scala.Function1 andThen(scala.Function1);
  Signature: (Lscala/Function1;)Lscala/Function1;
  Code:
   Stack=2, Locals=2, Args_size=2
	aload_0
	aload_1
	invokestatic	Method scala/Function1$class.andThen:(Lscala/Function1;Lscala/Function1;)Lscala/Function1;
	areturn
  Labels:
  LocalVariableTable: 
   Start  Length  Slot  Name   Signature
   0      6      0    this       Lscala/actors/Actor$$anonfun$exitLinked$1;
   0      6      1    g       Lscala/Function1;


public scala.Function1 compose(scala.Function1);
  Signature: (Lscala/Function1;)Lscala/Function1;
  Code:
   Stack=2, Locals=2, Args_size=2
	aload_0
	aload_1
	invokestatic	Method scala/Function1$class.compose:(Lscala/Function1;Lscala/Function1;)Lscala/Function1;
	areturn
  Labels:
  LocalVariableTable: 
   Start  Length  Slot  Name   Signature
   0      6      0    this       Lscala/actors/Actor$$anonfun$exitLinked$1;
   0      6      1    g       Lscala/Function1;


public java.lang.String toString();
  Signature: ()Ljava/lang/String;
  Code:
   Stack=1, Locals=1, Args_size=1
	aload_0
	invokestatic	Method scala/Function1$class.toString:(Lscala/Function1;)Ljava/lang/String;
	areturn
  Labels:

}

