Compiled from "Actor.scala"
public final class scala.actors.Actor$$anon$5 extends java.util.TimerTask
  SourceFile: "Actor.scala"
  Scala: length = 0x
   
  InnerClass: 
   public final #39= #10 of #38; //$anon$5=class scala/actors/Actor$$anon$5 of class scala/actors/Actor
  minor version: 0
  major version: 49
  Constant pool:
const #1 = Asciz	SourceFile;
const #2 = Asciz	Actor.scala;
const #3 = Asciz	thisActor$1;
const #4 = Asciz	Lscala/actors/Actor;;
const #5 = Asciz	<init>;
const #6 = Asciz	(Lscala/actors/Actor;Lscala/actors/Actor;)V;
const #7 = Asciz	Code;
const #8 = Asciz	LineNumberTable;
const #9 = Asciz	scala/actors/Actor$$anon$5;
const #10 = class	#9;	//  scala/actors/Actor$$anon$5
const #11 = NameAndType	#3:#4;//  thisActor$1:Lscala/actors/Actor;
const #12 = Field	#10.#11;	//  scala/actors/Actor$$anon$5.thisActor$1:Lscala/actors/Actor;
const #13 = Asciz	java/util/TimerTask;
const #14 = class	#13;	//  java/util/TimerTask
const #15 = Asciz	()V;
const #16 = NameAndType	#5:#15;//  "<init>":()V
const #17 = Method	#14.#16;	//  java/util/TimerTask."<init>":()V
const #18 = Asciz	this;
const #19 = Asciz	Lscala/actors/Actor$$anon$5;;
const #20 = Asciz	$outer;
const #21 = Asciz	LocalVariableTable;
const #22 = Asciz	run;
const #23 = Asciz	scala/actors/TIMEOUT$;
const #24 = class	#23;	//  scala/actors/TIMEOUT$
const #25 = Asciz	MODULE$;
const #26 = Asciz	Lscala/actors/TIMEOUT$;;
const #27 = NameAndType	#25:#26;//  MODULE$:Lscala/actors/TIMEOUT$;
const #28 = Field	#24.#27;	//  scala/actors/TIMEOUT$.MODULE$:Lscala/actors/TIMEOUT$;
const #29 = Asciz	scala/actors/Reactor;
const #30 = class	#29;	//  scala/actors/Reactor
const #31 = Asciz	send;
const #32 = Asciz	(Ljava/lang/Object;Lscala/actors/OutputChannel;)V;
const #33 = NameAndType	#31:#32;//  send:(Ljava/lang/Object;Lscala/actors/OutputChannel;)V
const #34 = InterfaceMethod	#30.#33;	//  scala/actors/Reactor.send:(Ljava/lang/Object;Lscala/actors/OutputChannel;)V
const #35 = Asciz	Scala;
const #36 = Asciz	InnerClasses;
const #37 = Asciz	scala/actors/Actor;
const #38 = class	#37;	//  scala/actors/Actor
const #39 = Asciz	$anon$5;

{
public scala.actors.Actor$$anon$5(scala.actors.Actor, scala.actors.Actor);
  Code:
   Stack=2, Locals=3, Args_size=3
   0:	aload_0
   1:	aload_2
   2:	putfield	#12; //Field thisActor$1:Lscala/actors/Actor;
   5:	aload_0
   6:	invokespecial	#17; //Method java/util/TimerTask."<init>":()V
   9:	return
  LineNumberTable: 
   line 608: 0

  LocalVariableTable: 
   Start  Length  Slot  Name   Signature
   0      10      0    this       Lscala/actors/Actor$$anon$5;
   0      10      1    $outer       Lscala/actors/Actor;


public void run();
  Code:
   Stack=3, Locals=1, Args_size=1
   0:	aload_0
   1:	getfield	#12; //Field thisActor$1:Lscala/actors/Actor;
   4:	getstatic	#28; //Field scala/actors/TIMEOUT$.MODULE$:Lscala/actors/TIMEOUT$;
   7:	aload_0
   8:	getfield	#12; //Field thisActor$1:Lscala/actors/Actor;
   11:	invokeinterface	#34,  3; //InterfaceMethod scala/actors/Reactor.send:(Ljava/lang/Object;Lscala/actors/OutputChannel;)V
   16:	return
  LineNumberTable: 
   line 609: 0


}

