Compiled from "Actor.scala"
public abstract class scala.actors.Actor$class extends java.lang.Object
  SourceFile: "Actor.scala"
  Scala: length = 0x
   
  InnerClass: 
   public final $anon$5=class scala/actors/Actor$$anon$5 of class scala/actors/Actor
   public final $anon$6=class scala/actors/Actor$$anon$6 of class scala/actors/Actor
   public final $anon$3=class scala/actors/Actor$$anon$3 of class scala/actors/Actor
   public final $anonfun$1=class scala/actors/Actor$$anonfun$1 of class scala/actors/Actor
   public final $anonfun$4=class scala/actors/Actor$$anonfun$4 of class scala/actors/Actor
   public final $anonfun$5=class scala/actors/Actor$$anonfun$5 of class scala/actors/Actor
   public final $anonfun$3=class scala/actors/Actor$$anonfun$3 of class scala/actors/Actor
   public final $anonfun$2=class scala/actors/Actor$$anonfun$2 of class scala/actors/Actor
   public final $anonfun$8=class scala/actors/Actor$$anonfun$8 of class scala/actors/Actor
   public final $anonfun$9=class scala/actors/Actor$$anonfun$9 of class scala/actors/Actor
   public final $anonfun$7=class scala/actors/Actor$$anonfun$7 of class scala/actors/Actor
   public final $anonfun$6=class scala/actors/Actor$$anonfun$6 of class scala/actors/Actor
   public final $anonfun$10=class scala/actors/Actor$$anonfun$10 of class scala/actors/Actor
   public final $anonfun$$qmark$1=class scala/actors/Actor$$anonfun$$qmark$1 of class scala/actors/Actor
   public final $anonfun$unlinkFrom$1=class scala/actors/Actor$$anonfun$unlinkFrom$1 of class scala/actors/Actor
   public final $anonfun$exitLinked$1=class scala/actors/Actor$$anonfun$exitLinked$1 of class scala/actors/Actor
   public final $anonfun$startSearch$1=class scala/actors/Actor$$anonfun$startSearch$1 of class scala/actors/Actor
   public final $anonfun$reactWithin$2=class scala/actors/Actor$$anonfun$reactWithin$2 of class scala/actors/Actor
   public final $anonfun$receiveWithin$2=class scala/actors/Actor$$anonfun$receiveWithin$2 of class scala/actors/Actor
  minor version: 0
  major version: 49
  Constant pool:
Asciz	SourceFile;
Asciz	Actor.scala;
Asciz	<clinit>;
Asciz	()V;
Asciz	Code;
Asciz	scala/Symbol$;
class	scala/Symbol$
Asciz	MODULE$;
Asciz	Lscala/Symbol$;;
NameAndType	MODULE$:Lscala/Symbol$;
Field	scala/Symbol$.MODULE$:Lscala/Symbol$;
Asciz	LineNumberTable;
Asciz	normal;
String	normal
Asciz	apply;
Asciz	(Ljava/lang/Object;)Ljava/lang/Object;;
NameAndType	apply:(Ljava/lang/Object;)Ljava/lang/Object;
Method	scala/Symbol$.apply:(Ljava/lang/Object;)Ljava/lang/Object;
Asciz	scala/Symbol;
class	scala/Symbol
Asciz	scala/actors/Actor$class;
class	scala/actors/Actor$class
Asciz	symbol$1;
Asciz	Lscala/Symbol;;
NameAndType	symbol$1:Lscala/Symbol;
Field	scala/actors/Actor$class.symbol$1:Lscala/Symbol;
Asciz	$init$;
Asciz	(Lscala/actors/Actor;)V;
Asciz	scala/actors/Actor;
class	scala/actors/Actor
Asciz	scala$actors$Actor$$isSuspended_$eq;
Asciz	(Z)V;
NameAndType	scala$actors$Actor$$isSuspended_$eq:(Z)V
InterfaceMethod	scala/actors/Actor.scala$actors$Actor$$isSuspended_$eq:(Z)V
Asciz	scala/None$;
class	scala/None$
Asciz	Lscala/None$;;
NameAndType	MODULE$:Lscala/None$;
Field	scala/None$.MODULE$:Lscala/None$;
Asciz	scala$actors$Actor$$received_$eq;
Asciz	(Lscala/Option;)V;
NameAndType	scala$actors$Actor$$received_$eq:(Lscala/Option;)V
InterfaceMethod	scala/actors/Actor.scala$actors$Actor$$received_$eq:(Lscala/Option;)V
Asciz	scala$actors$Actor$$onTimeout_$eq;
NameAndType	scala$actors$Actor$$onTimeout_$eq:(Lscala/Option;)V
InterfaceMethod	scala/actors/Actor.scala$actors$Actor$$onTimeout_$eq:(Lscala/Option;)V
Asciz	scala/collection/immutable/Nil$;
class	scala/collection/immutable/Nil$
Asciz	Lscala/collection/immutable/Nil$;;
NameAndType	MODULE$:Lscala/collection/immutable/Nil$;
Field	scala/collection/immutable/Nil$.MODULE$:Lscala/collection/immutable/Nil$;
Asciz	links_$eq;
Asciz	(Lscala/collection/immutable/List;)V;
NameAndType	links_$eq:(Lscala/collection/immutable/List;)V
InterfaceMethod	scala/actors/Actor.links_$eq:(Lscala/collection/immutable/List;)V
Asciz	trapExit_$eq;
NameAndType	trapExit_$eq:(Z)V
InterfaceMethod	scala/actors/Actor.trapExit_$eq:(Z)V
Asciz	exitReason_$eq;
Asciz	(Ljava/lang/Object;)V;
NameAndType	exitReason_$eq:(Ljava/lang/Object;)V
InterfaceMethod	scala/actors/Actor.exitReason_$eq:(Ljava/lang/Object;)V
Asciz	shouldExit_$eq;
NameAndType	shouldExit_$eq:(Z)V
InterfaceMethod	scala/actors/Actor.shouldExit_$eq:(Z)V
Asciz	$this;
Asciz	Lscala/actors/Actor;;
Asciz	LocalVariableTable;
Asciz	liftedTree1$1;
Asciz	java/lang/Object;
class	java/lang/Object
Asciz	wait;
NameAndType	wait:()V
Method	java/lang/Object.wait:()V
Asciz	java/lang/InterruptedException;
class	java/lang/InterruptedException
Asciz	onTerminate;
Asciz	(Lscala/actors/Actor;Lscala/Function0;)V;
Asciz	scheduler;
Asciz	()Lscala/actors/IScheduler;;
NameAndType	scheduler:()Lscala/actors/IScheduler;
InterfaceMethod	scala/actors/Actor.scheduler:()Lscala/actors/IScheduler;
Asciz	scala/actors/IScheduler;
class	scala/actors/IScheduler
Asciz	(Lscala/actors/Reactor;Lscala/Function0;)V;
NameAndType	onTerminate:(Lscala/actors/Reactor;Lscala/Function0;)V
InterfaceMethod	scala/actors/IScheduler.onTerminate:(Lscala/actors/Reactor;Lscala/Function0;)V
Asciz	f;
Asciz	Lscala/Function0;;
Asciz	exit;
Asciz	(Lscala/actors/Actor;Lscala/actors/AbstractActor;Ljava/lang/Object;)V;
Asciz	trapExit;
Asciz	()Z;
NameAndType	trapExit:()Z
InterfaceMethod	scala/actors/Actor.trapExit:()Z
Asciz	scala/actors/Exit;
class	scala/actors/Exit
Asciz	<init>;
Asciz	(Lscala/actors/AbstractActor;Ljava/lang/Object;)V;
NameAndType	"<init>":(Lscala/actors/AbstractActor;Ljava/lang/Object;)V
Method	scala/actors/Exit."<init>":(Lscala/actors/AbstractActor;Ljava/lang/Object;)V
Asciz	scala/actors/ReplyReactor;
class	scala/actors/ReplyReactor
Asciz	$bang;
NameAndType	$bang:(Ljava/lang/Object;)V
InterfaceMethod	scala/actors/ReplyReactor.$bang:(Ljava/lang/Object;)V
Asciz	equals;
Asciz	(Ljava/lang/Object;)Z;
NameAndType	equals:(Ljava/lang/Object;)Z
Method	java/lang/Object.equals:(Ljava/lang/Object;)Z
Asciz	scala$actors$Actor$$isSuspended;
NameAndType	scala$actors$Actor$$isSuspended:()Z
InterfaceMethod	scala/actors/Actor.scala$actors$Actor$$isSuspended:()Z
Asciz	scala$actors$Actor$$resumeActor;
NameAndType	scala$actors$Actor$$resumeActor:(Lscala/actors/Actor;)V
Method	scala/actors/Actor$class.scala$actors$Actor$$resumeActor:(Lscala/actors/Actor;)V
Asciz	scala/actors/Reactor;
class	scala/actors/Reactor
Asciz	waitingFor;
Asciz	()Lscala/PartialFunction;;
NameAndType	waitingFor:()Lscala/PartialFunction;
InterfaceMethod	scala/actors/Reactor.waitingFor:()Lscala/PartialFunction;
Asciz	waitingForNone;
NameAndType	waitingForNone:()Lscala/PartialFunction;
InterfaceMethod	scala/actors/Reactor.waitingForNone:()Lscala/PartialFunction;
Asciz	scheduleActor;
Asciz	(Lscala/PartialFunction;Ljava/lang/Object;)V;
NameAndType	scheduleActor:(Lscala/PartialFunction;Ljava/lang/Object;)V
InterfaceMethod	scala/actors/Actor.scheduleActor:(Lscala/PartialFunction;Ljava/lang/Object;)V
Asciz	from;
Asciz	Lscala/actors/AbstractActor;;
Asciz	reason;
Asciz	Ljava/lang/Object;;
Asciz	exitLinked;
Asciz	(Lscala/actors/Actor;Ljava/lang/Object;)V;
NameAndType	exitLinked:()V
InterfaceMethod	scala/actors/Actor.exitLinked:()V
Asciz	scala/actors/AbstractActor;
class	scala/actors/AbstractActor
Asciz	exiting_$eq;
NameAndType	exiting_$eq:(Z)V
InterfaceMethod	scala/actors/AbstractActor.exiting_$eq:(Z)V
Asciz	links;
Asciz	()Lscala/collection/immutable/List;;
NameAndType	links:()Lscala/collection/immutable/List;
InterfaceMethod	scala/actors/Actor.links:()Lscala/collection/immutable/List;
Asciz	scala/actors/Actor$$anonfun$10;
class	scala/actors/Actor$$anonfun$10
NameAndType	"<init>":(Lscala/actors/Actor;)V
Method	scala/actors/Actor$$anonfun$10."<init>":(Lscala/actors/Actor;)V
Asciz	scala/collection/TraversableLike;
class	scala/collection/TraversableLike
Asciz	filterNot;
Asciz	(Lscala/Function1;)Ljava/lang/Object;;
NameAndType	filterNot:(Lscala/Function1;)Ljava/lang/Object;
InterfaceMethod	scala/collection/TraversableLike.filterNot:(Lscala/Function1;)Ljava/lang/Object;
Asciz	scala/collection/immutable/List;
class	scala/collection/immutable/List
Asciz	scala/actors/Actor$$anonfun$exitLinked$1;
class	scala/actors/Actor$$anonfun$exitLinked$1
Method	scala/actors/Actor$$anonfun$exitLinked$1."<init>":(Lscala/actors/Actor;)V
Asciz	scala/collection/LinearSeqLike;
class	scala/collection/LinearSeqLike
Asciz	foreach;
Asciz	(Lscala/Function1;)V;
NameAndType	foreach:(Lscala/Function1;)V
InterfaceMethod	scala/collection/LinearSeqLike.foreach:(Lscala/Function1;)V
Asciz	mylinks;
Asciz	Lscala/collection/immutable/List;;
Asciz	(Lscala/actors/Actor;)Lscala/runtime/Nothing$;;
Asciz	scala/collection/IterableLike;
class	scala/collection/IterableLike
Asciz	isEmpty;
NameAndType	isEmpty:()Z
InterfaceMethod	scala/collection/IterableLike.isEmpty:()Z
Asciz	terminated;
NameAndType	terminated:()V
InterfaceMethod	scala/actors/Reactor.terminated:()V
Asciz	scala/actors/Actor$;
class	scala/actors/Actor$
Asciz	Lscala/actors/Actor$;;
NameAndType	MODULE$:Lscala/actors/Actor$;
Field	scala/actors/Actor$.MODULE$:Lscala/actors/Actor$;
Asciz	suspendException;
Asciz	()Lscala/actors/SuspendActorException;;
NameAndType	suspendException:()Lscala/actors/SuspendActorException;
Method	scala/actors/Actor$.suspendException:()Lscala/actors/SuspendActorException;
Asciz	(Lscala/actors/Actor;Ljava/lang/Object;)Lscala/runtime/Nothing$;;
Asciz	()Lscala/runtime/Nothing$;;
NameAndType	exit:()Lscala/runtime/Nothing$;
InterfaceMethod	scala/actors/Actor.exit:()Lscala/runtime/Nothing$;
Asciz	unlinkFrom;
Asciz	(Lscala/actors/Actor;Lscala/actors/AbstractActor;)V;
Asciz	scala/actors/Actor$$anonfun$unlinkFrom$1;
class	scala/actors/Actor$$anonfun$unlinkFrom$1
NameAndType	"<init>":(Lscala/actors/Actor;Lscala/actors/AbstractActor;)V
Method	scala/actors/Actor$$anonfun$unlinkFrom$1."<init>":(Lscala/actors/Actor;Lscala/actors/AbstractActor;)V
Asciz	from$2;
Asciz	unlink;
Asciz	rawSelf;
Asciz	(Lscala/actors/IScheduler;)Lscala/actors/Reactor;;
NameAndType	rawSelf:(Lscala/actors/IScheduler;)Lscala/actors/Reactor;
Method	scala/actors/Actor$.rawSelf:(Lscala/actors/IScheduler;)Lscala/actors/Reactor;
Asciz	java/lang/AssertionError;
class	java/lang/AssertionError
Asciz	scala/collection/mutable/StringBuilder;
class	scala/collection/mutable/StringBuilder
NameAndType	"<init>":()V
Method	scala/collection/mutable/StringBuilder."<init>":()V
Asciz	assertion failed: ;
String	assertion failed: 
Asciz	append;
Asciz	(Ljava/lang/Object;)Lscala/collection/mutable/StringBuilder;;
NameAndType	append:(Ljava/lang/Object;)Lscala/collection/mutable/StringBuilder;
Method	scala/collection/mutable/StringBuilder.append:(Ljava/lang/Object;)Lscala/collection/mutable/StringBuilder;
Asciz	unlink called on actor different from self;
String	unlink called on actor different from self
Asciz	toString;
Asciz	()Ljava/lang/String;;
NameAndType	toString:()Ljava/lang/String;
Method	scala/collection/mutable/StringBuilder.toString:()Ljava/lang/String;
NameAndType	"<init>":(Ljava/lang/Object;)V
Method	java/lang/AssertionError."<init>":(Ljava/lang/Object;)V
Asciz	(Lscala/actors/AbstractActor;)V;
NameAndType	unlinkFrom:(Lscala/actors/AbstractActor;)V
InterfaceMethod	scala/actors/Actor.unlinkFrom:(Lscala/actors/AbstractActor;)V
InterfaceMethod	scala/actors/AbstractActor.unlinkFrom:(Lscala/actors/AbstractActor;)V
Asciz	linkTo;
Asciz	$colon$colon;
Asciz	(Ljava/lang/Object;)Lscala/collection/immutable/List;;
NameAndType	$colon$colon:(Ljava/lang/Object;)Lscala/collection/immutable/List;
Method	scala/collection/immutable/List.$colon$colon:(Ljava/lang/Object;)Lscala/collection/immutable/List;
Asciz	to;
Asciz	link;
Asciz	(Lscala/actors/Actor;Lscala/Function0;)Lscala/actors/Actor;;
Asciz	link called on actor different from self;
String	link called on actor different from self
Asciz	scala/actors/Actor$$anon$3;
class	scala/actors/Actor$$anon$3
NameAndType	"<init>":(Lscala/actors/Actor;Lscala/Function0;)V
Method	scala/actors/Actor$$anon$3."<init>":(Lscala/actors/Actor;Lscala/Function0;)V
Asciz	(Lscala/actors/AbstractActor;)Lscala/actors/AbstractActor;;
NameAndType	link:(Lscala/actors/AbstractActor;)Lscala/actors/AbstractActor;
InterfaceMethod	scala/actors/Actor.link:(Lscala/actors/AbstractActor;)Lscala/actors/AbstractActor;
Asciz	start;
Asciz	(Lscala/actors/Actor;)Lscala/actors/Actor;;
NameAndType	start:(Lscala/actors/Actor;)Lscala/actors/Actor;
Method	scala/actors/Actor$class.start:(Lscala/actors/Actor;)Lscala/actors/Actor;
Asciz	body$6;
Asciz	a;
Asciz	(Lscala/actors/Actor;Lscala/actors/AbstractActor;)Lscala/actors/AbstractActor;;
NameAndType	linkTo:(Lscala/actors/AbstractActor;)V
InterfaceMethod	scala/actors/Actor.linkTo:(Lscala/actors/AbstractActor;)V
InterfaceMethod	scala/actors/AbstractActor.linkTo:(Lscala/actors/AbstractActor;)V
Asciz	newActor;
Asciz	(Lscala/actors/Reactor;)V;
NameAndType	newActor:(Lscala/actors/Reactor;)V
InterfaceMethod	scala/actors/IScheduler.newActor:(Lscala/actors/Reactor;)V
Asciz	scala/actors/Reaction;
class	scala/actors/Reaction
Method	scala/actors/Reaction."<init>":(Lscala/actors/Actor;)V
Asciz	execute;
Asciz	(Ljava/lang/Runnable;)V;
NameAndType	execute:(Ljava/lang/Runnable;)V
InterfaceMethod	scala/actors/IScheduler.execute:(Ljava/lang/Runnable;)V
Asciz	notify;
NameAndType	notify:()V
Method	java/lang/Object.notify:()V
Asciz	scala$actors$Actor$$suspendActor;
NameAndType	liftedTree1$1:(Lscala/actors/Actor;)V
Method	scala/actors/Actor$class.liftedTree1$1:(Lscala/actors/Actor;)V
Asciz	shouldExit;
NameAndType	shouldExit:()Z
InterfaceMethod	scala/actors/Actor.shouldExit:()Z
Asciz	(Lscala/actors/Actor;Lscala/PartialFunction;Ljava/lang/Object;)V;
NameAndType	"<init>":(Lscala/actors/Actor;Lscala/PartialFunction;Ljava/lang/Object;)V
Method	scala/actors/Reaction."<init>":(Lscala/actors/Actor;Lscala/PartialFunction;Ljava/lang/Object;)V
Asciz	executeFromActor;
NameAndType	executeFromActor:(Ljava/lang/Runnable;)V
InterfaceMethod	scala/actors/IScheduler.executeFromActor:(Ljava/lang/Runnable;)V
Asciz	Lscala/PartialFunction;;
Asciz	msg;
Asciz	task;
Asciz	Lscala/actors/Reaction;;
Asciz	$qmark;
Asciz	(Lscala/actors/Actor;)Ljava/lang/Object;;
Asciz	scala/actors/Actor$$anonfun$$qmark$1;
class	scala/actors/Actor$$anonfun$$qmark$1
Method	scala/actors/Actor$$anonfun$$qmark$1."<init>":(Lscala/actors/Actor;)V
Asciz	receive;
Asciz	(Lscala/PartialFunction;)Ljava/lang/Object;;
NameAndType	receive:(Lscala/PartialFunction;)Ljava/lang/Object;
InterfaceMethod	scala/actors/Actor.receive:(Lscala/PartialFunction;)Ljava/lang/Object;
Asciz	reactWithin;
Asciz	(Lscala/actors/Actor;JLscala/PartialFunction;)Lscala/runtime/Nothing$;;
Asciz	react on channel belonging to other actor;
String	react on channel belonging to other actor
Asciz	mailbox;
Asciz	()Lscala/actors/MQueue;;
NameAndType	mailbox:()Lscala/actors/MQueue;
InterfaceMethod	scala/actors/Reactor.mailbox:()Lscala/actors/MQueue;
Asciz	drainSendBuffer;
Asciz	(Lscala/actors/MQueue;)V;
NameAndType	drainSendBuffer:(Lscala/actors/MQueue;)V
InterfaceMethod	scala/actors/Reactor.drainSendBuffer:(Lscala/actors/MQueue;)V
Asciz	scala/actors/Actor$$anonfun$reactWithin$2;
class	scala/actors/Actor$$anonfun$reactWithin$2
Method	scala/actors/Actor$$anonfun$reactWithin$2."<init>":(Lscala/actors/Actor;)V
Asciz	scala/actors/MQueue;
class	scala/actors/MQueue
Asciz	extractFirst;
Asciz	(Lscala/Function2;)Lscala/actors/MQueueElement;;
NameAndType	extractFirst:(Lscala/Function2;)Lscala/actors/MQueueElement;
Method	scala/actors/MQueue.extractFirst:(Lscala/Function2;)Lscala/actors/MQueueElement;
Asciz	scala/actors/Actor$$anonfun$6;
class	scala/actors/Actor$$anonfun$6
Asciz	(Lscala/actors/Actor;Lscala/PartialFunction;)V;
NameAndType	"<init>":(Lscala/actors/Actor;Lscala/PartialFunction;)V
Method	scala/actors/Actor$$anonfun$6."<init>":(Lscala/actors/Actor;Lscala/PartialFunction;)V
Asciz	scala/actors/Actor$$anonfun$7;
class	scala/actors/Actor$$anonfun$7
Method	scala/actors/Actor$$anonfun$7."<init>":(Lscala/actors/Actor;Lscala/PartialFunction;)V
Asciz	sendBuffer;
NameAndType	sendBuffer:()Lscala/actors/MQueue;
InterfaceMethod	scala/actors/Reactor.sendBuffer:()Lscala/actors/MQueue;
Method	scala/actors/MQueue.isEmpty:()Z
Asciz	waitingFor_$eq;
Asciz	(Lscala/PartialFunction;)V;
NameAndType	waitingFor_$eq:(Lscala/PartialFunction;)V
InterfaceMethod	scala/actors/Reactor.waitingFor_$eq:(Lscala/PartialFunction;)V
Asciz	scala/Some;
class	scala/Some
Asciz	scala/actors/Actor$$anon$6;
class	scala/actors/Actor$$anon$6
Asciz	(Lscala/actors/Actor;Lscala/actors/Actor;)V;
NameAndType	"<init>":(Lscala/actors/Actor;Lscala/actors/Actor;)V
Method	scala/actors/Actor$$anon$6."<init>":(Lscala/actors/Actor;Lscala/actors/Actor;)V
Method	scala/Some."<init>":(Ljava/lang/Object;)V
Asciz	timer;
Asciz	()Ljava/util/Timer;;
NameAndType	timer:()Ljava/util/Timer;
Method	scala/actors/Actor$.timer:()Ljava/util/Timer;
Asciz	scala$actors$Actor$$onTimeout;
Asciz	()Lscala/Option;;
NameAndType	scala$actors$Actor$$onTimeout:()Lscala/Option;
InterfaceMethod	scala/actors/Actor.scala$actors$Actor$$onTimeout:()Lscala/Option;
Asciz	scala/Option;
class	scala/Option
Asciz	get;
Asciz	()Ljava/lang/Object;;
NameAndType	get:()Ljava/lang/Object;
Method	scala/Option.get:()Ljava/lang/Object;
Asciz	java/util/TimerTask;
class	java/util/TimerTask
Asciz	java/util/Timer;
class	java/util/Timer
Asciz	schedule;
Asciz	(Ljava/util/TimerTask;J)V;
NameAndType	schedule:(Ljava/util/TimerTask;J)V
Method	java/util/Timer.schedule:(Ljava/util/TimerTask;J)V
Asciz	scala/actors/Actor$$anonfun$9;
class	scala/actors/Actor$$anonfun$9
Method	scala/actors/Actor$$anonfun$9."<init>":(Lscala/actors/Actor;)V
Asciz	scala/actors/Actor$$anonfun$8;
class	scala/actors/Actor$$anonfun$8
Method	scala/actors/Actor$$anonfun$8."<init>":(Lscala/actors/Actor;)V
Asciz	scala/Function0;
class	scala/Function0
NameAndType	apply:()Ljava/lang/Object;
InterfaceMethod	scala/Function0.apply:()Ljava/lang/Object;
Asciz	scala/collection/immutable/List$;
class	scala/collection/immutable/List$
Asciz	Lscala/collection/immutable/List$;;
NameAndType	MODULE$:Lscala/collection/immutable/List$;
Field	scala/collection/immutable/List$.MODULE$:Lscala/collection/immutable/List$;
Asciz	scala/Predef$;
class	scala/Predef$
Asciz	Lscala/Predef$;;
NameAndType	MODULE$:Lscala/Predef$;
Field	scala/Predef$.MODULE$:Lscala/Predef$;
Asciz	scala/actors/OutputChannel;
class	scala/actors/OutputChannel
Asciz	scala/actors/MQueueElement;
class	scala/actors/MQueueElement
Asciz	session;
Asciz	()Lscala/actors/OutputChannel;;
NameAndType	session:()Lscala/actors/OutputChannel;
Method	scala/actors/MQueueElement.session:()Lscala/actors/OutputChannel;
Asciz	[Ljava/lang/Object;;
class	"[Ljava/lang/Object;"
Asciz	wrapRefArray;
Asciz	([Ljava/lang/Object;)Lscala/collection/mutable/WrappedArray;;
NameAndType	wrapRefArray:([Ljava/lang/Object;)Lscala/collection/mutable/WrappedArray;
Method	scala/Predef$.wrapRefArray:([Ljava/lang/Object;)Lscala/collection/mutable/WrappedArray;
Asciz	(Lscala/collection/Seq;)Lscala/collection/immutable/List;;
NameAndType	apply:(Lscala/collection/Seq;)Lscala/collection/immutable/List;
Method	scala/collection/immutable/List$.apply:(Lscala/collection/Seq;)Lscala/collection/immutable/List;
Asciz	senders_$eq;
NameAndType	senders_$eq:(Lscala/collection/immutable/List;)V
InterfaceMethod	scala/actors/ReplyReactor.senders_$eq:(Lscala/collection/immutable/List;)V
NameAndType	msg:()Ljava/lang/Object;
Method	scala/actors/MQueueElement.msg:()Ljava/lang/Object;
Asciz	scala/runtime/BoxedUnit;
class	scala/runtime/BoxedUnit
Asciz	UNIT;
Asciz	Lscala/runtime/BoxedUnit;;
NameAndType	UNIT:Lscala/runtime/BoxedUnit;
Field	scala/runtime/BoxedUnit.UNIT:Lscala/runtime/BoxedUnit;
Asciz	msec;
Asciz	J;
Asciz	f$3;
Asciz	receiveTimeout;
Asciz	todo;
Asciz	qel;
Asciz	Lscala/actors/MQueueElement;;
Asciz	done;
Asciz	Z;
Asciz	react;
Asciz	(Lscala/actors/Actor;Lscala/PartialFunction;)Lscala/runtime/Nothing$;;
Asciz	searchMailbox;
Asciz	(Lscala/actors/MQueue;Lscala/PartialFunction;Z)V;
NameAndType	searchMailbox:(Lscala/actors/MQueue;Lscala/PartialFunction;Z)V
InterfaceMethod	scala/actors/ReplyReactor.searchMailbox:(Lscala/actors/MQueue;Lscala/PartialFunction;Z)V
Asciz	receiveWithin;
Asciz	(Lscala/actors/Actor;JLscala/PartialFunction;)Ljava/lang/Object;;
Asciz	receive from channel belonging to other actor;
String	receive from channel belonging to other actor
Asciz	scala/actors/Actor$$anonfun$receiveWithin$2;
class	scala/actors/Actor$$anonfun$receiveWithin$2
Method	scala/actors/Actor$$anonfun$receiveWithin$2."<init>":(Lscala/actors/Actor;)V
Asciz	scala/actors/Actor$$anonfun$2;
class	scala/actors/Actor$$anonfun$2
Method	scala/actors/Actor$$anonfun$2."<init>":(Lscala/actors/Actor;Lscala/PartialFunction;)V
Asciz	scala$actors$Actor$$received;
NameAndType	scala$actors$Actor$$received:()Lscala/Option;
InterfaceMethod	scala/actors/Actor.scala$actors$Actor$$received:()Lscala/Option;
Asciz	scala/Function1;
class	scala/Function1
InterfaceMethod	scala/Function1.apply:(Ljava/lang/Object;)Ljava/lang/Object;
Asciz	senders;
NameAndType	senders:()Lscala/collection/immutable/List;
InterfaceMethod	scala/actors/ReplyReactor.senders:()Lscala/collection/immutable/List;
Asciz	tail;
NameAndType	tail:()Ljava/lang/Object;
InterfaceMethod	scala/collection/TraversableLike.tail:()Ljava/lang/Object;
Asciz	scala/actors/Actor$$anonfun$3;
class	scala/actors/Actor$$anonfun$3
Method	scala/actors/Actor$$anonfun$3."<init>":(Lscala/actors/Actor;Lscala/PartialFunction;)V
Asciz	scala/actors/Actor$$anon$5;
class	scala/actors/Actor$$anon$5
Method	scala/actors/Actor$$anon$5."<init>":(Lscala/actors/Actor;Lscala/actors/Actor;)V
Asciz	scala$actors$Actor$$blocker;
Asciz	()Lscala/actors/Actor$blocker$;;
NameAndType	scala$actors$Actor$$blocker:()Lscala/actors/Actor$blocker$;
InterfaceMethod	scala/actors/Actor.scala$actors$Actor$$blocker:()Lscala/actors/Actor$blocker$;
Asciz	managedBlock;
Asciz	(Lscala/concurrent/ManagedBlocker;)V;
NameAndType	managedBlock:(Lscala/concurrent/ManagedBlocker;)V
InterfaceMethod	scala/actors/IScheduler.managedBlock:(Lscala/concurrent/ManagedBlocker;)V
Asciz	scala/actors/Actor$$anonfun$5;
class	scala/actors/Actor$$anonfun$5
Method	scala/actors/Actor$$anonfun$5."<init>":(Lscala/actors/Actor;)V
Asciz	scala/actors/Actor$$anonfun$4;
class	scala/actors/Actor$$anonfun$4
Method	scala/actors/Actor$$anonfun$4."<init>":(Lscala/actors/Actor;)V
Method	scala/Option.isEmpty:()Z
Asciz	cancel;
NameAndType	cancel:()Z
Method	java/util/TimerTask.cancel:()Z
Asciz	f$2;
Asciz	result;
Asciz	(Lscala/actors/Actor;Lscala/PartialFunction;)Ljava/lang/Object;;
Asciz	scala/actors/Actor$$anonfun$1;
class	scala/actors/Actor$$anonfun$1
Method	scala/actors/Actor$$anonfun$1."<init>":(Lscala/actors/Actor;Lscala/PartialFunction;)V
Asciz	f$1;
Asciz	resumeReceiver;
Asciz	(Lscala/actors/Actor;Lscala/Tuple2;Lscala/PartialFunction;Z)V;
Asciz	scala/Tuple2;
class	scala/Tuple2
Asciz	_2;
NameAndType	_2:()Ljava/lang/Object;
Method	scala/Tuple2._2:()Ljava/lang/Object;
Asciz	scala$actors$Actor$$super$resumeReceiver;
Asciz	(Lscala/Tuple2;Lscala/PartialFunction;Z)V;
NameAndType	scala$actors$Actor$$super$resumeReceiver:(Lscala/Tuple2;Lscala/PartialFunction;Z)V
InterfaceMethod	scala/actors/Actor.scala$actors$Actor$$super$resumeReceiver:(Lscala/Tuple2;Lscala/PartialFunction;Z)V
Asciz	item;
Asciz	Lscala/Tuple2;;
Asciz	handler;
Asciz	onSameThread;
Asciz	makeReaction;
Asciz	(Lscala/actors/Actor;Lscala/Function0;)Ljava/lang/Runnable;;
Asciz	scala/actors/ActorTask;
class	scala/actors/ActorTask
Method	scala/actors/ActorTask."<init>":(Lscala/actors/Actor;Lscala/Function0;)V
Asciz	fun;
Asciz	startSearch;
Asciz	(Lscala/actors/Actor;Ljava/lang/Object;Lscala/actors/OutputChannel;Lscala/PartialFunction;)Lscala/Function0;;
Asciz	scala/actors/Actor$$anonfun$startSearch$1;
class	scala/actors/Actor$$anonfun$startSearch$1
Asciz	(Lscala/actors/Actor;Ljava/lang/Object;Lscala/actors/OutputChannel;)V;
NameAndType	"<init>":(Lscala/actors/Actor;Ljava/lang/Object;Lscala/actors/OutputChannel;)V
Method	scala/actors/Actor$$anonfun$startSearch$1."<init>":(Lscala/actors/Actor;Ljava/lang/Object;Lscala/actors/OutputChannel;)V
Asciz	scala$actors$Actor$$super$startSearch;
Asciz	(Ljava/lang/Object;Lscala/actors/OutputChannel;Lscala/PartialFunction;)Lscala/Function0;;
NameAndType	scala$actors$Actor$$super$startSearch:(Ljava/lang/Object;Lscala/actors/OutputChannel;Lscala/PartialFunction;)Lscala/Function0;
InterfaceMethod	scala/actors/Actor.scala$actors$Actor$$super$startSearch:(Ljava/lang/Object;Lscala/actors/OutputChannel;Lscala/PartialFunction;)Lscala/Function0;
Asciz	msg$1;
Asciz	replyTo$1;
Asciz	Lscala/actors/OutputChannel;;
Asciz	(Lscala/actors/Actor;)Lscala/actors/IScheduler;;
Asciz	scala/actors/Scheduler$;
class	scala/actors/Scheduler$
Asciz	Lscala/actors/Scheduler$;;
NameAndType	MODULE$:Lscala/actors/Scheduler$;
Field	scala/actors/Scheduler$.MODULE$:Lscala/actors/Scheduler$;
Asciz	Scala;
Asciz	InnerClasses;
Asciz	$anon$5;
Asciz	$anon$6;
Asciz	$anon$3;
Asciz	$anonfun$1;
Asciz	$anonfun$4;
Asciz	$anonfun$5;
Asciz	$anonfun$3;
Asciz	$anonfun$2;
Asciz	$anonfun$8;
Asciz	$anonfun$9;
Asciz	$anonfun$7;
Asciz	$anonfun$6;
Asciz	$anonfun$10;
Asciz	$anonfun$$qmark$1;
Asciz	$anonfun$unlinkFrom$1;
Asciz	$anonfun$exitLinked$1;
Asciz	$anonfun$startSearch$1;
Asciz	$anonfun$reactWithin$2;
Asciz	$anonfun$receiveWithin$2;

{
private static final scala.Symbol symbol$1;
  Signature: Lscala/Symbol;

public static {};
  Signature: ()V
  Code:
   Stack=2, Locals=0, Args_size=0
	getstatic	Field scala/Symbol$.MODULE$:Lscala/Symbol$;
	ldc	String normal
	invokevirtual	Method scala/Symbol$.apply:(Ljava/lang/Object;)Ljava/lang/Object;
	checkcast	class scala/Symbol
	putstatic	Field symbol$1:Lscala/Symbol;
	return
  Labels:

public static void $init$(scala.actors.Actor);
  Signature: (Lscala/actors/Actor;)V
  Code:
   Stack=2, Locals=1, Args_size=1
	aload_0
	iconst_0
	invokeinterface	InterfaceMethod scala/actors/Actor.scala$actors$Actor$$isSuspended_$eq:(Z)V
	aload_0
	getstatic	Field scala/None$.MODULE$:Lscala/None$;
	invokeinterface	InterfaceMethod scala/actors/Actor.scala$actors$Actor$$received_$eq:(Lscala/Option;)V
	aload_0
	getstatic	Field scala/None$.MODULE$:Lscala/None$;
	invokeinterface	InterfaceMethod scala/actors/Actor.scala$actors$Actor$$onTimeout_$eq:(Lscala/Option;)V
	aload_0
	getstatic	Field scala/collection/immutable/Nil$.MODULE$:Lscala/collection/immutable/Nil$;
	invokeinterface	InterfaceMethod scala/actors/Actor.links_$eq:(Lscala/collection/immutable/List;)V
	aload_0
	iconst_0
	invokeinterface	InterfaceMethod scala/actors/Actor.trapExit_$eq:(Z)V
	aload_0
	getstatic	Field symbol$1:Lscala/Symbol;
	invokeinterface	InterfaceMethod scala/actors/Actor.exitReason_$eq:(Ljava/lang/Object;)V
	aload_0
	iconst_0
	invokeinterface	InterfaceMethod scala/actors/Actor.shouldExit_$eq:(Z)V
	return
  Labels:
  LocalVariableTable: 
   Start  Length  Slot  Name   Signature
   0      58      0    $this       Lscala/actors/Actor;


private static final void liftedTree1$1(scala.actors.Actor);
  Signature: (Lscala/actors/Actor;)V
  Code:
   Stack=1, Locals=1, Args_size=1
	aload_0
	invokevirtual	Method java/lang/Object.wait:()V
	goto	l1 // return
	pop
l1	return
  Labels:
   	l1 = 8 // return
  Exception table:
   from   to  target type
     0     7     7   Class java/lang/InterruptedException

  LocalVariableTable: 
   Start  Length  Slot  Name   Signature
   0      9      0    $this       Lscala/actors/Actor;


public static void onTerminate(scala.actors.Actor, scala.Function0);
  Signature: (Lscala/actors/Actor;Lscala/Function0;)V
  Code:
   Stack=3, Locals=2, Args_size=2
	aload_0
	invokeinterface	InterfaceMethod scala/actors/Actor.scheduler:()Lscala/actors/IScheduler;
	aload_0
	aload_1
	invokeinterface	InterfaceMethod scala/actors/IScheduler.onTerminate:(Lscala/actors/Reactor;Lscala/Function0;)V
	return
  Labels:
  LocalVariableTable: 
   Start  Length  Slot  Name   Signature
   0      14      0    $this       Lscala/actors/Actor;
   0      14      1    f       Lscala/Function0;


public static void exit(scala.actors.Actor, scala.actors.AbstractActor, java.lang.Object);
  Signature: (Lscala/actors/Actor;Lscala/actors/AbstractActor;Ljava/lang/Object;)V
  Code:
   Stack=5, Locals=4, Args_size=3
	aload_0
	invokeinterface	InterfaceMethod scala/actors/Actor.trapExit:()Z
	ifeq	l1 // aload_2
	aload_0
	new	class scala/actors/Exit
	dup
	aload_1
	aload_2
	invokespecial	Method scala/actors/Exit."<init>":(Lscala/actors/AbstractActor;Ljava/lang/Object;)V
	invokeinterface	InterfaceMethod scala/actors/ReplyReactor.$bang:(Ljava/lang/Object;)V
	goto	l2 // return
l1	aload_2
	getstatic	Field symbol$1:Lscala/Symbol;
	astore_3
	dup
	ifnonnull	l3 // aload_3
	pop
	aload_3
	ifnull	l2 // return
	goto	l4 // aload_0
l3	aload_3
	invokevirtual	Method java/lang/Object.equals:(Ljava/lang/Object;)Z
	ifne	l2 // return
l4	aload_0
	dup
	pop
	monitorenter
	aload_0
	iconst_1
	invokeinterface	InterfaceMethod scala/actors/Actor.shouldExit_$eq:(Z)V
	aload_0
	aload_2
	invokeinterface	InterfaceMethod scala/actors/Actor.exitReason_$eq:(Ljava/lang/Object;)V
	aload_0
	invokeinterface	InterfaceMethod scala/actors/Actor.scala$actors$Actor$$isSuspended:()Z
	ifeq	l5 // aload_0
	aload_0
	invokestatic	Method scala$actors$Actor$$resumeActor:(Lscala/actors/Actor;)V
	goto	l6 // aload_0
l5	aload_0
	invokeinterface	InterfaceMethod scala/actors/Reactor.waitingFor:()Lscala/PartialFunction;
	aload_0
	invokeinterface	InterfaceMethod scala/actors/Reactor.waitingForNone:()Lscala/PartialFunction;
	if_acmpeq	l6 // aload_0
	aload_0
	aload_0
	invokeinterface	InterfaceMethod scala/actors/Reactor.waitingFor:()Lscala/PartialFunction;
	aconst_null
	invokeinterface	InterfaceMethod scala/actors/Actor.scheduleActor:(Lscala/PartialFunction;Ljava/lang/Object;)V
	goto	l6 // aload_0
l6	aload_0
	monitorexit
l2	return
	aload_0
	monitorexit
	athrow
  Labels:
   	l1 = 27 // aload_2
   	l3 = 44 // aload_3
   	l4 = 51 // aload_0
   	l5 = 85 // aload_0
   	l6 = 116 // aload_0
   	l2 = 118 // return
  Exception table:
   from   to  target type
    55   118   119   any
  LocalVariableTable: 
   Start  Length  Slot  Name   Signature
   0      122      0    $this       Lscala/actors/Actor;
   0      122      1    from       Lscala/actors/AbstractActor;
   0      122      2    reason       Ljava/lang/Object;


public static void exitLinked(scala.actors.Actor, java.lang.Object);
  Signature: (Lscala/actors/Actor;Ljava/lang/Object;)V
  Code:
   Stack=2, Locals=2, Args_size=2
	aload_0
	aload_1
	invokeinterface	InterfaceMethod scala/actors/Actor.exitReason_$eq:(Ljava/lang/Object;)V
	aload_0
	invokeinterface	InterfaceMethod scala/actors/Actor.exitLinked:()V
	return
  Labels:
  LocalVariableTable: 
   Start  Length  Slot  Name   Signature
   0      14      0    $this       Lscala/actors/Actor;
   0      14      1    reason       Ljava/lang/Object;


public static void exitLinked(scala.actors.Actor);
  Signature: (Lscala/actors/Actor;)V
  Code:
   Stack=4, Locals=2, Args_size=1
	aload_0
	iconst_1
	invokeinterface	InterfaceMethod scala/actors/AbstractActor.exiting_$eq:(Z)V
	aload_0
	invokeinterface	InterfaceMethod scala/actors/Actor.links:()Lscala/collection/immutable/List;
	new	class scala/actors/Actor$$anonfun$10
	dup
	aload_0
	invokespecial	Method scala/actors/Actor$$anonfun$10."<init>":(Lscala/actors/Actor;)V
	invokeinterface	InterfaceMethod scala/collection/TraversableLike.filterNot:(Lscala/Function1;)Ljava/lang/Object;
	checkcast	class scala/collection/immutable/List
	astore_1
	aload_1
	new	class scala/actors/Actor$$anonfun$exitLinked$1
	dup
	aload_0
	invokespecial	Method scala/actors/Actor$$anonfun$exitLinked$1."<init>":(Lscala/actors/Actor;)V
	invokeinterface	InterfaceMethod scala/collection/LinearSeqLike.foreach:(Lscala/Function1;)V
	return
  Labels:
  LocalVariableTable: 
   Start  Length  Slot  Name   Signature
   0      45      0    $this       Lscala/actors/Actor;
   30      14      1    mylinks       Lscala/collection/immutable/List;


public static scala.runtime.Nothing$ exit(scala.actors.Actor);
  Signature: (Lscala/actors/Actor;)Lscala/runtime/Nothing$;
  Code:
   Stack=1, Locals=1, Args_size=1
	aload_0
	invokeinterface	InterfaceMethod scala/actors/Actor.links:()Lscala/collection/immutable/List;
	invokeinterface	InterfaceMethod scala/collection/IterableLike.isEmpty:()Z
	ifne	l1 // aload_0
	aload_0
	invokeinterface	InterfaceMethod scala/actors/Actor.exitLinked:()V
l1	aload_0
	invokeinterface	InterfaceMethod scala/actors/Reactor.terminated:()V
	getstatic	Field scala/actors/Actor$.MODULE$:Lscala/actors/Actor$;
	invokevirtual	Method scala/actors/Actor$.suspendException:()Lscala/actors/SuspendActorException;
	athrow
  Labels:
   	l1 = 20 // aload_0
  LocalVariableTable: 
   Start  Length  Slot  Name   Signature
   0      33      0    $this       Lscala/actors/Actor;


public static scala.runtime.Nothing$ exit(scala.actors.Actor, java.lang.Object);
  Signature: (Lscala/actors/Actor;Ljava/lang/Object;)Lscala/runtime/Nothing$;
  Code:
   Stack=2, Locals=2, Args_size=2
	aload_0
	aload_1
	invokeinterface	InterfaceMethod scala/actors/Actor.exitReason_$eq:(Ljava/lang/Object;)V
	aload_0
	invokeinterface	InterfaceMethod scala/actors/Actor.exit:()Lscala/runtime/Nothing$;
	areturn
  Labels:
  LocalVariableTable: 
   Start  Length  Slot  Name   Signature
   0      14      0    $this       Lscala/actors/Actor;
   0      14      1    reason       Ljava/lang/Object;


public static void unlinkFrom(scala.actors.Actor, scala.actors.AbstractActor);
  Signature: (Lscala/actors/Actor;Lscala/actors/AbstractActor;)V
  Code:
   Stack=6, Locals=2, Args_size=2
	aload_0
	dup
	pop
	monitorenter
	aload_0
	aload_0
	invokeinterface	InterfaceMethod scala/actors/Actor.links:()Lscala/collection/immutable/List;
	new	class scala/actors/Actor$$anonfun$unlinkFrom$1
	dup
	aload_0
	aload_1
	invokespecial	Method scala/actors/Actor$$anonfun$unlinkFrom$1."<init>":(Lscala/actors/Actor;Lscala/actors/AbstractActor;)V
	invokeinterface	InterfaceMethod scala/collection/TraversableLike.filterNot:(Lscala/Function1;)Ljava/lang/Object;
	checkcast	class scala/collection/immutable/List
	invokeinterface	InterfaceMethod scala/actors/Actor.links_$eq:(Lscala/collection/immutable/List;)V
	aload_0
	monitorexit
	return
	aload_0
	monitorexit
	athrow
  Labels:
  Exception table:
   from   to  target type
     4    35    36   any
  LocalVariableTable: 
   Start  Length  Slot  Name   Signature
   0      39      0    $this       Lscala/actors/Actor;
   0      39      1    from$2       Lscala/actors/AbstractActor;


public static void unlink(scala.actors.Actor, scala.actors.AbstractActor);
  Signature: (Lscala/actors/Actor;Lscala/actors/AbstractActor;)V
  Code:
   Stack=4, Locals=5, Args_size=2
	getstatic	Field scala/actors/Actor$.MODULE$:Lscala/actors/Actor$;
	aload_0
	invokeinterface	InterfaceMethod scala/actors/Actor.scheduler:()Lscala/actors/IScheduler;
	astore_3
	astore_2
	aload_2
	aload_3
	invokevirtual	Method scala/actors/Actor$.rawSelf:(Lscala/actors/IScheduler;)Lscala/actors/Reactor;
	checkcast	class scala/actors/Actor
	dup
	ifnonnull	l1 // aload_0
	pop
	aload_0
	ifnull	l2 // iconst_1
	goto	l3 // iconst_0
l1	aload_0
	invokevirtual	Method java/lang/Object.equals:(Ljava/lang/Object;)Z
	ifeq	l3 // iconst_0
l2	iconst_1
	goto	l4 // istore
l3	iconst_0
l4	istore	4
	iload	4
	ifne	l5 // aload_0
	new	class java/lang/AssertionError
	dup
	new	class scala/collection/mutable/StringBuilder
	dup
	invokespecial	Method scala/collection/mutable/StringBuilder."<init>":()V
	ldc	String assertion failed: 
	invokevirtual	Method scala/collection/mutable/StringBuilder.append:(Ljava/lang/Object;)Lscala/collection/mutable/StringBuilder;
	ldc	String unlink called on actor different from self
	invokevirtual	Method scala/collection/mutable/StringBuilder.append:(Ljava/lang/Object;)Lscala/collection/mutable/StringBuilder;
	invokevirtual	Method scala/collection/mutable/StringBuilder.toString:()Ljava/lang/String;
	invokespecial	Method java/lang/AssertionError."<init>":(Ljava/lang/Object;)V
	athrow
l5	aload_0
	aload_1
	invokeinterface	InterfaceMethod scala/actors/Actor.unlinkFrom:(Lscala/actors/AbstractActor;)V
	aload_1
	aload_0
	invokeinterface	InterfaceMethod scala/actors/AbstractActor.unlinkFrom:(Lscala/actors/AbstractActor;)V
	return
  Labels:
   	l1 = 31 // aload_0
   	l2 = 38 // iconst_1
   	l3 = 42 // iconst_0
   	l4 = 43 // istore
   	l5 = 78 // aload_0
  LocalVariableTable: 
   Start  Length  Slot  Name   Signature
   0      93      0    $this       Lscala/actors/Actor;
   0      93      1    from       Lscala/actors/AbstractActor;


public static void linkTo(scala.actors.Actor, scala.actors.AbstractActor);
  Signature: (Lscala/actors/Actor;Lscala/actors/AbstractActor;)V
  Code:
   Stack=3, Locals=2, Args_size=2
	aload_0
	dup
	pop
	monitorenter
	aload_0
	aload_0
	invokeinterface	InterfaceMethod scala/actors/Actor.links:()Lscala/collection/immutable/List;
	aload_1
	invokevirtual	Method scala/collection/immutable/List.$colon$colon:(Ljava/lang/Object;)Lscala/collection/immutable/List;
	invokeinterface	InterfaceMethod scala/actors/Actor.links_$eq:(Lscala/collection/immutable/List;)V
	aload_0
	monitorexit
	return
	aload_0
	monitorexit
	athrow
  Labels:
  Exception table:
   from   to  target type
     4    22    23   any
  LocalVariableTable: 
   Start  Length  Slot  Name   Signature
   0      26      0    $this       Lscala/actors/Actor;
   0      26      1    to       Lscala/actors/AbstractActor;


public static scala.actors.Actor link(scala.actors.Actor, scala.Function0);
  Signature: (Lscala/actors/Actor;Lscala/Function0;)Lscala/actors/Actor;
  Code:
   Stack=4, Locals=6, Args_size=2
	getstatic	Field scala/actors/Actor$.MODULE$:Lscala/actors/Actor$;
	aload_0
	invokeinterface	InterfaceMethod scala/actors/Actor.scheduler:()Lscala/actors/IScheduler;
	astore_3
	astore_2
	aload_2
	aload_3
	invokevirtual	Method scala/actors/Actor$.rawSelf:(Lscala/actors/IScheduler;)Lscala/actors/Reactor;
	checkcast	class scala/actors/Actor
	dup
	ifnonnull	l1 // aload_0
	pop
	aload_0
	ifnull	l2 // iconst_1
	goto	l3 // iconst_0
l1	aload_0
	invokevirtual	Method java/lang/Object.equals:(Ljava/lang/Object;)Z
	ifeq	l3 // iconst_0
l2	iconst_1
	goto	l4 // istore
l3	iconst_0
l4	istore	4
	iload	4
	ifne	l5 // new
	new	class java/lang/AssertionError
	dup
	new	class scala/collection/mutable/StringBuilder
	dup
	invokespecial	Method scala/collection/mutable/StringBuilder."<init>":()V
	ldc	String assertion failed: 
	invokevirtual	Method scala/collection/mutable/StringBuilder.append:(Ljava/lang/Object;)Lscala/collection/mutable/StringBuilder;
	ldc	String link called on actor different from self
	invokevirtual	Method scala/collection/mutable/StringBuilder.append:(Ljava/lang/Object;)Lscala/collection/mutable/StringBuilder;
	invokevirtual	Method scala/collection/mutable/StringBuilder.toString:()Ljava/lang/String;
	invokespecial	Method java/lang/AssertionError."<init>":(Ljava/lang/Object;)V
	athrow
l5	new	class scala/actors/Actor$$anon$3
	dup
	aload_0
	aload_1
	invokespecial	Method scala/actors/Actor$$anon$3."<init>":(Lscala/actors/Actor;Lscala/Function0;)V
	astore	5
	aload_0
	aload	5
	invokeinterface	InterfaceMethod scala/actors/Actor.link:(Lscala/actors/AbstractActor;)Lscala/actors/AbstractActor;
	pop
	aload	5
	invokestatic	Method start:(Lscala/actors/Actor;)Lscala/actors/Actor;
	pop
	aload	5
	areturn
  Labels:
   	l1 = 31 // aload_0
   	l2 = 38 // iconst_1
   	l3 = 42 // iconst_0
   	l4 = 43 // istore
   	l5 = 78 // new
  LocalVariableTable: 
   Start  Length  Slot  Name   Signature
   0      107      0    $this       Lscala/actors/Actor;
   0      107      1    body$6       Lscala/Function0;
   89      17      5    a       Lscala/actors/Actor;


public static scala.actors.AbstractActor link(scala.actors.Actor, scala.actors.AbstractActor);
  Signature: (Lscala/actors/Actor;Lscala/actors/AbstractActor;)Lscala/actors/AbstractActor;
  Code:
   Stack=4, Locals=5, Args_size=2
	getstatic	Field scala/actors/Actor$.MODULE$:Lscala/actors/Actor$;
	aload_0
	invokeinterface	InterfaceMethod scala/actors/Actor.scheduler:()Lscala/actors/IScheduler;
	astore_3
	astore_2
	aload_2
	aload_3
	invokevirtual	Method scala/actors/Actor$.rawSelf:(Lscala/actors/IScheduler;)Lscala/actors/Reactor;
	checkcast	class scala/actors/Actor
	dup
	ifnonnull	l1 // aload_0
	pop
	aload_0
	ifnull	l2 // iconst_1
	goto	l3 // iconst_0
l1	aload_0
	invokevirtual	Method java/lang/Object.equals:(Ljava/lang/Object;)Z
	ifeq	l3 // iconst_0
l2	iconst_1
	goto	l4 // istore
l3	iconst_0
l4	istore	4
	iload	4
	ifne	l5 // aload_0
	new	class java/lang/AssertionError
	dup
	new	class scala/collection/mutable/StringBuilder
	dup
	invokespecial	Method scala/collection/mutable/StringBuilder."<init>":()V
	ldc	String assertion failed: 
	invokevirtual	Method scala/collection/mutable/StringBuilder.append:(Ljava/lang/Object;)Lscala/collection/mutable/StringBuilder;
	ldc	String link called on actor different from self
	invokevirtual	Method scala/collection/mutable/StringBuilder.append:(Ljava/lang/Object;)Lscala/collection/mutable/StringBuilder;
	invokevirtual	Method scala/collection/mutable/StringBuilder.toString:()Ljava/lang/String;
	invokespecial	Method java/lang/AssertionError."<init>":(Ljava/lang/Object;)V
	athrow
l5	aload_0
	aload_1
	invokeinterface	InterfaceMethod scala/actors/Actor.linkTo:(Lscala/actors/AbstractActor;)V
	aload_1
	aload_0
	invokeinterface	InterfaceMethod scala/actors/AbstractActor.linkTo:(Lscala/actors/AbstractActor;)V
	aload_1
	areturn
  Labels:
   	l1 = 31 // aload_0
   	l2 = 38 // iconst_1
   	l3 = 42 // iconst_0
   	l4 = 43 // istore
   	l5 = 78 // aload_0
  LocalVariableTable: 
   Start  Length  Slot  Name   Signature
   0      94      0    $this       Lscala/actors/Actor;
   0      94      1    to       Lscala/actors/AbstractActor;


public static scala.actors.Actor start(scala.actors.Actor);
  Signature: (Lscala/actors/Actor;)Lscala/actors/Actor;
  Code:
   Stack=4, Locals=1, Args_size=1
	aload_0
	dup
	pop
	monitorenter
	aload_0
	getstatic	Field symbol$1:Lscala/Symbol;
	invokeinterface	InterfaceMethod scala/actors/Actor.exitReason_$eq:(Ljava/lang/Object;)V
	aload_0
	iconst_0
	invokeinterface	InterfaceMethod scala/actors/AbstractActor.exiting_$eq:(Z)V
	aload_0
	iconst_0
	invokeinterface	InterfaceMethod scala/actors/Actor.shouldExit_$eq:(Z)V
	aload_0
	invokeinterface	InterfaceMethod scala/actors/Actor.scheduler:()Lscala/actors/IScheduler;
	aload_0
	invokeinterface	InterfaceMethod scala/actors/IScheduler.newActor:(Lscala/actors/Reactor;)V
	aload_0
	invokeinterface	InterfaceMethod scala/actors/Actor.scheduler:()Lscala/actors/IScheduler;
	new	class scala/actors/Reaction
	dup
	aload_0
	invokespecial	Method scala/actors/Reaction."<init>":(Lscala/actors/Actor;)V
	invokeinterface	InterfaceMethod scala/actors/IScheduler.execute:(Ljava/lang/Runnable;)V
	aload_0
	monitorexit
	aload_0
	checkcast	class scala/actors/Actor
	areturn
	aload_0
	monitorexit
	athrow
  Labels:
  Exception table:
   from   to  target type
     4    60    65   any
  LocalVariableTable: 
   Start  Length  Slot  Name   Signature
   0      68      0    $this       Lscala/actors/Actor;


public static final void scala$actors$Actor$$resumeActor(scala.actors.Actor);
  Signature: (Lscala/actors/Actor;)V
  Code:
   Stack=2, Locals=1, Args_size=1
	aload_0
	iconst_0
	invokeinterface	InterfaceMethod scala/actors/Actor.scala$actors$Actor$$isSuspended_$eq:(Z)V
	aload_0
	invokevirtual	Method java/lang/Object.notify:()V
	return
  Labels:
  LocalVariableTable: 
   Start  Length  Slot  Name   Signature
   0      12      0    $this       Lscala/actors/Actor;


public static final void scala$actors$Actor$$suspendActor(scala.actors.Actor);
  Signature: (Lscala/actors/Actor;)V
  Code:
   Stack=2, Locals=1, Args_size=1
	aload_0
	dup
	pop
	monitorenter
l2	aload_0
	invokeinterface	InterfaceMethod scala/actors/Actor.scala$actors$Actor$$isSuspended:()Z
	ifeq	l1 // aload_0
	aload_0
	invokestatic	Method liftedTree1$1:(Lscala/actors/Actor;)V
	goto	l2 // aload_0
l1	aload_0
	invokeinterface	InterfaceMethod scala/actors/Actor.shouldExit:()Z
	ifeq	l3 // aload_0
	aload_0
	invokeinterface	InterfaceMethod scala/actors/Actor.exit:()Lscala/runtime/Nothing$;
	athrow
l3	aload_0
	monitorexit
	return
	aload_0
	monitorexit
	athrow
  Labels:
   	l2 = 4 // aload_0
   	l1 = 20 // aload_0
   	l3 = 36 // aload_0
  Exception table:
   from   to  target type
     4    38    39   any
  LocalVariableTable: 
   Start  Length  Slot  Name   Signature
   0      42      0    $this       Lscala/actors/Actor;


public static void scheduleActor(scala.actors.Actor, scala.PartialFunction, java.lang.Object);
  Signature: (Lscala/actors/Actor;Lscala/PartialFunction;Ljava/lang/Object;)V
  Code:
   Stack=5, Locals=4, Args_size=3
	aload_1
	ifnull	l1 // return
	new	class scala/actors/Reaction
	dup
	aload_0
	aload_1
	aload_2
	invokespecial	Method scala/actors/Reaction."<init>":(Lscala/actors/Actor;Lscala/PartialFunction;Ljava/lang/Object;)V
	astore_3
	aload_0
	invokeinterface	InterfaceMethod scala/actors/Actor.scheduler:()Lscala/actors/IScheduler;
	aload_3
	invokeinterface	InterfaceMethod scala/actors/IScheduler.executeFromActor:(Ljava/lang/Runnable;)V
l1	return
  Labels:
   	l1 = 27 // return
  LocalVariableTable: 
   Start  Length  Slot  Name   Signature
   0      28      0    $this       Lscala/actors/Actor;
   0      28      1    f       Lscala/PartialFunction;
   0      28      2    msg       Ljava/lang/Object;
   15      12      3    task       Lscala/actors/Reaction;


public static java.lang.Object $qmark(scala.actors.Actor);
  Signature: (Lscala/actors/Actor;)Ljava/lang/Object;
  Code:
   Stack=4, Locals=1, Args_size=1
	aload_0
	new	class scala/actors/Actor$$anonfun$$qmark$1
	dup
	aload_0
	invokespecial	Method scala/actors/Actor$$anonfun$$qmark$1."<init>":(Lscala/actors/Actor;)V
	invokeinterface	InterfaceMethod scala/actors/Actor.receive:(Lscala/PartialFunction;)Ljava/lang/Object;
	areturn
  Labels:
  LocalVariableTable: 
   Start  Length  Slot  Name   Signature
   0      15      0    $this       Lscala/actors/Actor;


public static scala.runtime.Nothing$ reactWithin(scala.actors.Actor, long, scala.PartialFunction);
  Signature: (Lscala/actors/Actor;JLscala/PartialFunction;)Lscala/runtime/Nothing$;
  Code:
   Stack=7, Locals=12, Args_size=3
	getstatic	Field scala/actors/Actor$.MODULE$:Lscala/actors/Actor$;
	aload_0
	invokeinterface	InterfaceMethod scala/actors/Actor.scheduler:()Lscala/actors/IScheduler;
	astore	5
	astore	4
	aload	4
	aload	5
	invokevirtual	Method scala/actors/Actor$.rawSelf:(Lscala/actors/IScheduler;)Lscala/actors/Reactor;
	checkcast	class scala/actors/Actor
	dup
	ifnonnull	l1 // aload_0
	pop
	aload_0
	ifnull	l2 // iconst_1
	goto	l3 // iconst_0
l1	aload_0
	invokevirtual	Method java/lang/Object.equals:(Ljava/lang/Object;)Z
	ifeq	l3 // iconst_0
l2	iconst_1
	goto	l4 // istore
l3	iconst_0
l4	istore	6
	iload	6
	ifne	l5 // aload_0
	new	class java/lang/AssertionError
	dup
	new	class scala/collection/mutable/StringBuilder
	dup
	invokespecial	Method scala/collection/mutable/StringBuilder."<init>":()V
	ldc	String assertion failed: 
	invokevirtual	Method scala/collection/mutable/StringBuilder.append:(Ljava/lang/Object;)Lscala/collection/mutable/StringBuilder;
	ldc_w	String react on channel belonging to other actor
	invokevirtual	Method scala/collection/mutable/StringBuilder.append:(Ljava/lang/Object;)Lscala/collection/mutable/StringBuilder;
	invokevirtual	Method scala/collection/mutable/StringBuilder.toString:()Ljava/lang/String;
	invokespecial	Method java/lang/AssertionError."<init>":(Ljava/lang/Object;)V
	athrow
l5	aload_0
	dup
	pop
	monitorenter
	aload_0
	invokeinterface	InterfaceMethod scala/actors/Actor.shouldExit:()Z
	ifeq	l6 // aload_0
	aload_0
	invokeinterface	InterfaceMethod scala/actors/Actor.exit:()Lscala/runtime/Nothing$;
	athrow
l6	aload_0
	aload_0
	invokeinterface	InterfaceMethod scala/actors/Reactor.mailbox:()Lscala/actors/MQueue;
	invokeinterface	InterfaceMethod scala/actors/Reactor.drainSendBuffer:(Lscala/actors/MQueue;)V
	aload_0
	monitorexit
	aload_0
	invokeinterface	InterfaceMethod scala/actors/Reactor.mailbox:()Lscala/actors/MQueue;
	new	class scala/actors/Actor$$anonfun$reactWithin$2
	dup
	aload_0
	invokespecial	Method scala/actors/Actor$$anonfun$reactWithin$2."<init>":(Lscala/actors/Actor;)V
	invokevirtual	Method scala/actors/MQueue.extractFirst:(Lscala/Function2;)Lscala/actors/MQueueElement;
	pop
	new	class scala/actors/Actor$$anonfun$6
	dup
	aload_0
	aload_3
	invokespecial	Method scala/actors/Actor$$anonfun$6."<init>":(Lscala/actors/Actor;Lscala/PartialFunction;)V
	astore	7
	iconst_0
	istore	11
l13	iload	11
	ifeq	l7 // aload_0
	getstatic	Field scala/actors/Actor$.MODULE$:Lscala/actors/Actor$;
	invokevirtual	Method scala/actors/Actor$.suspendException:()Lscala/actors/SuspendActorException;
	athrow
l7	aload_0
	invokeinterface	InterfaceMethod scala/actors/Reactor.mailbox:()Lscala/actors/MQueue;
	new	class scala/actors/Actor$$anonfun$7
	dup
	aload_0
	aload_3
	invokespecial	Method scala/actors/Actor$$anonfun$7."<init>":(Lscala/actors/Actor;Lscala/PartialFunction;)V
	invokevirtual	Method scala/actors/MQueue.extractFirst:(Lscala/Function2;)Lscala/actors/MQueueElement;
	astore	10
	aload	10
	ifnonnull	l8 // aload_0
	aload_0
	dup
	pop
	monitorenter
	aload_0
	invokeinterface	InterfaceMethod scala/actors/Reactor.sendBuffer:()Lscala/actors/MQueue;
	invokevirtual	Method scala/actors/MQueue.isEmpty:()Z
	ifeq	l9 // aload_0
	lload_1
	lconst_0
	lcmp
	ifne	l10 // aload_0
	iconst_1
	istore	11
	aload	7
	goto	l11 // astore
l10	aload_0
	aload_3
	invokeinterface	InterfaceMethod scala/actors/Reactor.waitingFor_$eq:(Lscala/PartialFunction;)V
	aload_0
	new	class scala/Some
	dup
	new	class scala/actors/Actor$$anon$6
	dup
	aload_0
	aload_0
	invokespecial	Method scala/actors/Actor$$anon$6."<init>":(Lscala/actors/Actor;Lscala/actors/Actor;)V
	invokespecial	Method scala/Some."<init>":(Ljava/lang/Object;)V
	invokeinterface	InterfaceMethod scala/actors/Actor.scala$actors$Actor$$onTimeout_$eq:(Lscala/Option;)V
	getstatic	Field scala/actors/Actor$.MODULE$:Lscala/actors/Actor$;
	invokevirtual	Method scala/actors/Actor$.timer:()Ljava/util/Timer;
	aload_0
	invokeinterface	InterfaceMethod scala/actors/Actor.scala$actors$Actor$$onTimeout:()Lscala/Option;
	invokevirtual	Method scala/Option.get:()Ljava/lang/Object;
	checkcast	class java/util/TimerTask
	lload_1
	invokevirtual	Method java/util/Timer.schedule:(Ljava/util/TimerTask;J)V
	iconst_1
	istore	11
	new	class scala/actors/Actor$$anonfun$9
	dup
	aload_0
	invokespecial	Method scala/actors/Actor$$anonfun$9."<init>":(Lscala/actors/Actor;)V
	goto	l11 // astore
l9	aload_0
	aload_0
	invokeinterface	InterfaceMethod scala/actors/Reactor.mailbox:()Lscala/actors/MQueue;
	invokeinterface	InterfaceMethod scala/actors/Reactor.drainSendBuffer:(Lscala/actors/MQueue;)V
	new	class scala/actors/Actor$$anonfun$8
	dup
	aload_0
	invokespecial	Method scala/actors/Actor$$anonfun$8."<init>":(Lscala/actors/Actor;)V
l11	astore	8
	aload_0
	monitorexit
	aload	8
	checkcast	class scala/Function0
	astore	9
	aload	9
	invokeinterface	InterfaceMethod scala/Function0.apply:()Ljava/lang/Object;
	goto	l12 // pop
l8	aload_0
	getstatic	Field scala/collection/immutable/List$.MODULE$:Lscala/collection/immutable/List$;
	getstatic	Field scala/Predef$.MODULE$:Lscala/Predef$;
	iconst_1
	anewarray	class scala/actors/OutputChannel
	dup
	iconst_0
	aload	10
	invokevirtual	Method scala/actors/MQueueElement.session:()Lscala/actors/OutputChannel;
	aastore
	checkcast	class "[Ljava/lang/Object;"
	invokevirtual	Method scala/Predef$.wrapRefArray:([Ljava/lang/Object;)Lscala/collection/mutable/WrappedArray;
	invokevirtual	Method scala/collection/immutable/List$.apply:(Lscala/collection/Seq;)Lscala/collection/immutable/List;
	invokeinterface	InterfaceMethod scala/actors/ReplyReactor.senders_$eq:(Lscala/collection/immutable/List;)V
	aload_0
	aload_3
	aload	10
	invokevirtual	Method scala/actors/MQueueElement.msg:()Ljava/lang/Object;
	invokeinterface	InterfaceMethod scala/actors/Actor.scheduleActor:(Lscala/PartialFunction;Ljava/lang/Object;)V
	iconst_1
	istore	11
	getstatic	Field scala/runtime/BoxedUnit.UNIT:Lscala/runtime/BoxedUnit;
l12	pop
	goto	l13 // iload
	aload_0
	monitorexit
	athrow
	aload_0
	monitorexit
	athrow
  Labels:
   	l1 = 35 // aload_0
   	l2 = 42 // iconst_1
   	l3 = 46 // iconst_0
   	l4 = 47 // istore
   	l5 = 83 // aload_0
   	l6 = 103 // aload_0
   	l13 = 149 // iload
   	l7 = 161 // aload_0
   	l10 = 216 // aload_0
   	l9 = 281 // aload_0
   	l11 = 301 // astore
   	l8 = 322 // aload_0
   	l12 = 373 // pop
  Exception table:
   from   to  target type
   190   305   380   any
    87   117   377   any
  LocalVariableTable: 
   Start  Length  Slot  Name   Signature
   0      383      0    $this       Lscala/actors/Actor;
   0      383      1    msec       J
   0      383      3    f$3       Lscala/PartialFunction;
   146      231      7    receiveTimeout       Lscala/Function0;
   380      3      7    receiveTimeout       Lscala/Function0;
   312      7      9    todo       Lscala/Function0;
   181      193      10    qel       Lscala/actors/MQueueElement;
   380      3      10    qel       Lscala/actors/MQueueElement;
   149      228      11    done       Z
   380      3      11    done       Z


public static scala.runtime.Nothing$ react(scala.actors.Actor, scala.PartialFunction);
  Signature: (Lscala/actors/Actor;Lscala/PartialFunction;)Lscala/runtime/Nothing$;
  Code:
   Stack=4, Locals=5, Args_size=2
	getstatic	Field scala/actors/Actor$.MODULE$:Lscala/actors/Actor$;
	aload_0
	invokeinterface	InterfaceMethod scala/actors/Actor.scheduler:()Lscala/actors/IScheduler;
	astore_3
	astore_2
	aload_2
	aload_3
	invokevirtual	Method scala/actors/Actor$.rawSelf:(Lscala/actors/IScheduler;)Lscala/actors/Reactor;
	checkcast	class scala/actors/Actor
	dup
	ifnonnull	l1 // aload_0
	pop
	aload_0
	ifnull	l2 // iconst_1
	goto	l3 // iconst_0
l1	aload_0
	invokevirtual	Method java/lang/Object.equals:(Ljava/lang/Object;)Z
	ifeq	l3 // iconst_0
l2	iconst_1
	goto	l4 // istore
l3	iconst_0
l4	istore	4
	iload	4
	ifne	l5 // aload_0
	new	class java/lang/AssertionError
	dup
	new	class scala/collection/mutable/StringBuilder
	dup
	invokespecial	Method scala/collection/mutable/StringBuilder."<init>":()V
	ldc	String assertion failed: 
	invokevirtual	Method scala/collection/mutable/StringBuilder.append:(Ljava/lang/Object;)Lscala/collection/mutable/StringBuilder;
	ldc_w	String react on channel belonging to other actor
	invokevirtual	Method scala/collection/mutable/StringBuilder.append:(Ljava/lang/Object;)Lscala/collection/mutable/StringBuilder;
	invokevirtual	Method scala/collection/mutable/StringBuilder.toString:()Ljava/lang/String;
	invokespecial	Method java/lang/AssertionError."<init>":(Ljava/lang/Object;)V
	athrow
l5	aload_0
	dup
	pop
	monitorenter
	aload_0
	invokeinterface	InterfaceMethod scala/actors/Actor.shouldExit:()Z
	ifeq	l6 // aload_0
	aload_0
	invokeinterface	InterfaceMethod scala/actors/Actor.exit:()Lscala/runtime/Nothing$;
	athrow
l6	aload_0
	aload_0
	invokeinterface	InterfaceMethod scala/actors/Reactor.mailbox:()Lscala/actors/MQueue;
	invokeinterface	InterfaceMethod scala/actors/Reactor.drainSendBuffer:(Lscala/actors/MQueue;)V
	aload_0
	monitorexit
	aload_0
	aload_0
	invokeinterface	InterfaceMethod scala/actors/Reactor.mailbox:()Lscala/actors/MQueue;
	aload_1
	iconst_0
	invokeinterface	InterfaceMethod scala/actors/ReplyReactor.searchMailbox:(Lscala/actors/MQueue;Lscala/PartialFunction;Z)V
	getstatic	Field scala/actors/Actor$.MODULE$:Lscala/actors/Actor$;
	invokevirtual	Method scala/actors/Actor$.suspendException:()Lscala/actors/SuspendActorException;
	athrow
	aload_0
	monitorexit
	athrow
  Labels:
   	l1 = 31 // aload_0
   	l2 = 38 // iconst_1
   	l3 = 42 // iconst_0
   	l4 = 43 // istore
   	l5 = 79 // aload_0
   	l6 = 99 // aload_0
  Exception table:
   from   to  target type
    83   113   134   any
  LocalVariableTable: 
   Start  Length  Slot  Name   Signature
   0      137      0    $this       Lscala/actors/Actor;
   0      137      1    f       Lscala/PartialFunction;


public static java.lang.Object receiveWithin(scala.actors.Actor, long, scala.PartialFunction);
  Signature: (Lscala/actors/Actor;JLscala/PartialFunction;)Ljava/lang/Object;
  Code:
   Stack=7, Locals=14, Args_size=3
	getstatic	Field scala/actors/Actor$.MODULE$:Lscala/actors/Actor$;
	aload_0
	invokeinterface	InterfaceMethod scala/actors/Actor.scheduler:()Lscala/actors/IScheduler;
	astore	5
	astore	4
	aload	4
	aload	5
	invokevirtual	Method scala/actors/Actor$.rawSelf:(Lscala/actors/IScheduler;)Lscala/actors/Reactor;
	checkcast	class scala/actors/Actor
	dup
	ifnonnull	l1 // aload_0
	pop
	aload_0
	ifnull	l2 // iconst_1
	goto	l3 // iconst_0
l1	aload_0
	invokevirtual	Method java/lang/Object.equals:(Ljava/lang/Object;)Z
	ifeq	l3 // iconst_0
l2	iconst_1
	goto	l4 // istore
l3	iconst_0
l4	istore	6
	iload	6
	ifne	l5 // aload_0
	new	class java/lang/AssertionError
	dup
	new	class scala/collection/mutable/StringBuilder
	dup
	invokespecial	Method scala/collection/mutable/StringBuilder."<init>":()V
	ldc	String assertion failed: 
	invokevirtual	Method scala/collection/mutable/StringBuilder.append:(Ljava/lang/Object;)Lscala/collection/mutable/StringBuilder;
	ldc_w	String receive from channel belonging to other actor
	invokevirtual	Method scala/collection/mutable/StringBuilder.append:(Ljava/lang/Object;)Lscala/collection/mutable/StringBuilder;
	invokevirtual	Method scala/collection/mutable/StringBuilder.toString:()Ljava/lang/String;
	invokespecial	Method java/lang/AssertionError."<init>":(Ljava/lang/Object;)V
	athrow
l5	aload_0
	dup
	pop
	monitorenter
	aload_0
	invokeinterface	InterfaceMethod scala/actors/Actor.shouldExit:()Z
	ifeq	l6 // aload_0
	aload_0
	invokeinterface	InterfaceMethod scala/actors/Actor.exit:()Lscala/runtime/Nothing$;
	athrow
l6	aload_0
	aload_0
	invokeinterface	InterfaceMethod scala/actors/Reactor.mailbox:()Lscala/actors/MQueue;
	invokeinterface	InterfaceMethod scala/actors/Reactor.drainSendBuffer:(Lscala/actors/MQueue;)V
	aload_0
	monitorexit
	aload_0
	invokeinterface	InterfaceMethod scala/actors/Reactor.mailbox:()Lscala/actors/MQueue;
	new	class scala/actors/Actor$$anonfun$receiveWithin$2
	dup
	aload_0
	invokespecial	Method scala/actors/Actor$$anonfun$receiveWithin$2."<init>":(Lscala/actors/Actor;)V
	invokevirtual	Method scala/actors/MQueue.extractFirst:(Lscala/Function2;)Lscala/actors/MQueueElement;
	pop
	new	class scala/actors/Actor$$anonfun$2
	dup
	aload_0
	aload_3
	invokespecial	Method scala/actors/Actor$$anonfun$2."<init>":(Lscala/actors/Actor;Lscala/PartialFunction;)V
	astore	8
	iconst_0
	istore	13
l15	iload	13
	ifeq	l7 // aload_0
	aload_3
	aload_0
	invokeinterface	InterfaceMethod scala/actors/Actor.scala$actors$Actor$$received:()Lscala/Option;
	invokevirtual	Method scala/Option.get:()Ljava/lang/Object;
	invokeinterface	InterfaceMethod scala/Function1.apply:(Ljava/lang/Object;)Ljava/lang/Object;
	astore	7
	aload_0
	getstatic	Field scala/None$.MODULE$:Lscala/None$;
	invokeinterface	InterfaceMethod scala/actors/Actor.scala$actors$Actor$$received_$eq:(Lscala/Option;)V
	aload_0
	aload_0
	invokeinterface	InterfaceMethod scala/actors/ReplyReactor.senders:()Lscala/collection/immutable/List;
	invokeinterface	InterfaceMethod scala/collection/TraversableLike.tail:()Ljava/lang/Object;
	checkcast	class scala/collection/immutable/List
	invokeinterface	InterfaceMethod scala/actors/ReplyReactor.senders_$eq:(Lscala/collection/immutable/List;)V
	aload	7
	areturn
l7	aload_0
	invokeinterface	InterfaceMethod scala/actors/Reactor.mailbox:()Lscala/actors/MQueue;
	new	class scala/actors/Actor$$anonfun$3
	dup
	aload_0
	aload_3
	invokespecial	Method scala/actors/Actor$$anonfun$3."<init>":(Lscala/actors/Actor;Lscala/PartialFunction;)V
	invokevirtual	Method scala/actors/MQueue.extractFirst:(Lscala/Function2;)Lscala/actors/MQueueElement;
	astore	11
	aload	11
	ifnonnull	l8 // aload_0
	aload_0
	dup
	pop
	monitorenter
	aload_0
	invokeinterface	InterfaceMethod scala/actors/Reactor.sendBuffer:()Lscala/actors/MQueue;
	invokevirtual	Method scala/actors/MQueue.isEmpty:()Z
	ifeq	l9 // aload_0
	lload_1
	lconst_0
	lcmp
	ifne	l10 // aload_0
	iconst_1
	istore	13
	aload	8
	goto	l11 // astore
l10	aload_0
	aload_3
	invokeinterface	InterfaceMethod scala/actors/Reactor.waitingFor_$eq:(Lscala/PartialFunction;)V
	aload_0
	getstatic	Field scala/None$.MODULE$:Lscala/None$;
	invokeinterface	InterfaceMethod scala/actors/Actor.scala$actors$Actor$$received_$eq:(Lscala/Option;)V
	aload_0
	iconst_1
	invokeinterface	InterfaceMethod scala/actors/Actor.scala$actors$Actor$$isSuspended_$eq:(Z)V
	aload_0
	new	class scala/Some
	dup
	new	class scala/actors/Actor$$anon$5
	dup
	aload_0
	aload_0
	invokespecial	Method scala/actors/Actor$$anon$5."<init>":(Lscala/actors/Actor;Lscala/actors/Actor;)V
	invokespecial	Method scala/Some."<init>":(Ljava/lang/Object;)V
	invokeinterface	InterfaceMethod scala/actors/Actor.scala$actors$Actor$$onTimeout_$eq:(Lscala/Option;)V
	getstatic	Field scala/actors/Actor$.MODULE$:Lscala/actors/Actor$;
	invokevirtual	Method scala/actors/Actor$.timer:()Ljava/util/Timer;
	aload_0
	invokeinterface	InterfaceMethod scala/actors/Actor.scala$actors$Actor$$onTimeout:()Lscala/Option;
	invokevirtual	Method scala/Option.get:()Ljava/lang/Object;
	checkcast	class java/util/TimerTask
	lload_1
	invokevirtual	Method java/util/Timer.schedule:(Ljava/util/TimerTask;J)V
	aload_0
	invokeinterface	InterfaceMethod scala/actors/Actor.scheduler:()Lscala/actors/IScheduler;
	aload_0
	invokeinterface	InterfaceMethod scala/actors/Actor.scala$actors$Actor$$blocker:()Lscala/actors/Actor$blocker$;
	invokeinterface	InterfaceMethod scala/actors/IScheduler.managedBlock:(Lscala/concurrent/ManagedBlocker;)V
	aload_0
	aload_0
	invokeinterface	InterfaceMethod scala/actors/Reactor.mailbox:()Lscala/actors/MQueue;
	invokeinterface	InterfaceMethod scala/actors/Reactor.drainSendBuffer:(Lscala/actors/MQueue;)V
	new	class scala/actors/Actor$$anonfun$5
	dup
	aload_0
	invokespecial	Method scala/actors/Actor$$anonfun$5."<init>":(Lscala/actors/Actor;)V
	goto	l11 // astore
l9	aload_0
	aload_0
	invokeinterface	InterfaceMethod scala/actors/Reactor.mailbox:()Lscala/actors/MQueue;
	invokeinterface	InterfaceMethod scala/actors/Reactor.drainSendBuffer:(Lscala/actors/MQueue;)V
	new	class scala/actors/Actor$$anonfun$4
	dup
	aload_0
	invokespecial	Method scala/actors/Actor$$anonfun$4."<init>":(Lscala/actors/Actor;)V
l11	astore	9
	aload_0
	monitorexit
	aload	9
	checkcast	class scala/Function0
	astore	10
	aload	10
	invokeinterface	InterfaceMethod scala/Function0.apply:()Ljava/lang/Object;
	goto	l12 // pop
l8	aload_0
	dup
	pop
	monitorenter
	aload_0
	invokeinterface	InterfaceMethod scala/actors/Actor.scala$actors$Actor$$onTimeout:()Lscala/Option;
	invokevirtual	Method scala/Option.isEmpty:()Z
	ifeq	l13 // aload_0
	goto	l14 // aload_0
l13	aload_0
	invokeinterface	InterfaceMethod scala/actors/Actor.scala$actors$Actor$$onTimeout:()Lscala/Option;
	invokevirtual	Method scala/Option.get:()Ljava/lang/Object;
	checkcast	class java/util/TimerTask
	invokevirtual	Method java/util/TimerTask.cancel:()Z
	pop
	aload_0
	getstatic	Field scala/None$.MODULE$:Lscala/None$;
	invokeinterface	InterfaceMethod scala/actors/Actor.scala$actors$Actor$$onTimeout_$eq:(Lscala/Option;)V
l14	aload_0
	monitorexit
	aload_0
	new	class scala/Some
	dup
	aload	11
	invokevirtual	Method scala/actors/MQueueElement.msg:()Ljava/lang/Object;
	invokespecial	Method scala/Some."<init>":(Ljava/lang/Object;)V
	invokeinterface	InterfaceMethod scala/actors/Actor.scala$actors$Actor$$received_$eq:(Lscala/Option;)V
	aload_0
	aload	11
	invokevirtual	Method scala/actors/MQueueElement.session:()Lscala/actors/OutputChannel;
	astore	12
	aload_0
	invokeinterface	InterfaceMethod scala/actors/ReplyReactor.senders:()Lscala/collection/immutable/List;
	aload	12
	invokevirtual	Method scala/collection/immutable/List.$colon$colon:(Ljava/lang/Object;)Lscala/collection/immutable/List;
	invokeinterface	InterfaceMethod scala/actors/ReplyReactor.senders_$eq:(Lscala/collection/immutable/List;)V
	iconst_1
	istore	13
	getstatic	Field scala/runtime/BoxedUnit.UNIT:Lscala/runtime/BoxedUnit;
l12	pop
	goto	l15 // iload
	aload_0
	monitorexit
	athrow
	aload_0
	monitorexit
	athrow
	aload_0
	monitorexit
	athrow
  Labels:
   	l1 = 35 // aload_0
   	l2 = 42 // iconst_1
   	l3 = 46 // iconst_0
   	l4 = 47 // istore
   	l5 = 83 // aload_0
   	l6 = 103 // aload_0
   	l15 = 149 // iload
   	l7 = 203 // aload_0
   	l10 = 258 // aload_0
   	l9 = 365 // aload_0
   	l11 = 385 // astore
   	l8 = 406 // aload_0
   	l13 = 425 // aload_0
   	l14 = 450 // aload_0
   	l12 = 500 // pop
  Exception table:
   from   to  target type
   410   452   510   any
   232   389   507   any
    87   117   504   any
  LocalVariableTable: 
   Start  Length  Slot  Name   Signature
   0      513      0    $this       Lscala/actors/Actor;
   0      513      1    msec       J
   0      513      3    f$2       Lscala/PartialFunction;
   171      31      7    result       Ljava/lang/Object;
   146      56      8    receiveTimeout       Lscala/Function0;
   203      301      8    receiveTimeout       Lscala/Function0;
   507      6      8    receiveTimeout       Lscala/Function0;
   396      7      10    todo       Lscala/Function0;
   223      278      11    qel       Lscala/actors/MQueueElement;
   507      6      11    qel       Lscala/actors/MQueueElement;
   149      53      13    done       Z
   203      301      13    done       Z
   507      6      13    done       Z


public static java.lang.Object receive(scala.actors.Actor, scala.PartialFunction);
  Signature: (Lscala/actors/Actor;Lscala/PartialFunction;)Ljava/lang/Object;
  Code:
   Stack=5, Locals=9, Args_size=2
	getstatic	Field scala/actors/Actor$.MODULE$:Lscala/actors/Actor$;
	aload_0
	invokeinterface	InterfaceMethod scala/actors/Actor.scheduler:()Lscala/actors/IScheduler;
	astore_3
	astore_2
	aload_2
	aload_3
	invokevirtual	Method scala/actors/Actor$.rawSelf:(Lscala/actors/IScheduler;)Lscala/actors/Reactor;
	checkcast	class scala/actors/Actor
	dup
	ifnonnull	l1 // aload_0
	pop
	aload_0
	ifnull	l2 // iconst_1
	goto	l3 // iconst_0
l1	aload_0
	invokevirtual	Method java/lang/Object.equals:(Ljava/lang/Object;)Z
	ifeq	l3 // iconst_0
l2	iconst_1
	goto	l4 // istore
l3	iconst_0
l4	istore	4
	iload	4
	ifne	l5 // aload_0
	new	class java/lang/AssertionError
	dup
	new	class scala/collection/mutable/StringBuilder
	dup
	invokespecial	Method scala/collection/mutable/StringBuilder."<init>":()V
	ldc	String assertion failed: 
	invokevirtual	Method scala/collection/mutable/StringBuilder.append:(Ljava/lang/Object;)Lscala/collection/mutable/StringBuilder;
	ldc_w	String receive from channel belonging to other actor
	invokevirtual	Method scala/collection/mutable/StringBuilder.append:(Ljava/lang/Object;)Lscala/collection/mutable/StringBuilder;
	invokevirtual	Method scala/collection/mutable/StringBuilder.toString:()Ljava/lang/String;
	invokespecial	Method java/lang/AssertionError."<init>":(Ljava/lang/Object;)V
	athrow
l5	aload_0
	dup
	pop
	monitorenter
	aload_0
	invokeinterface	InterfaceMethod scala/actors/Actor.shouldExit:()Z
	ifeq	l6 // aload_0
	aload_0
	invokeinterface	InterfaceMethod scala/actors/Actor.exit:()Lscala/runtime/Nothing$;
	athrow
l6	aload_0
	aload_0
	invokeinterface	InterfaceMethod scala/actors/Reactor.mailbox:()Lscala/actors/MQueue;
	invokeinterface	InterfaceMethod scala/actors/Reactor.drainSendBuffer:(Lscala/actors/MQueue;)V
	aload_0
	monitorexit
	iconst_0
	istore	8
l12	iload	8
	ifeq	l7 // aload_0
	aload_1
	aload_0
	invokeinterface	InterfaceMethod scala/actors/Actor.scala$actors$Actor$$received:()Lscala/Option;
	invokevirtual	Method scala/Option.get:()Ljava/lang/Object;
	invokeinterface	InterfaceMethod scala/Function1.apply:(Ljava/lang/Object;)Ljava/lang/Object;
	astore	5
	aload_0
	getstatic	Field scala/None$.MODULE$:Lscala/None$;
	invokeinterface	InterfaceMethod scala/actors/Actor.scala$actors$Actor$$received_$eq:(Lscala/Option;)V
	aload_0
	aload_0
	invokeinterface	InterfaceMethod scala/actors/ReplyReactor.senders:()Lscala/collection/immutable/List;
	invokeinterface	InterfaceMethod scala/collection/TraversableLike.tail:()Ljava/lang/Object;
	checkcast	class scala/collection/immutable/List
	invokeinterface	InterfaceMethod scala/actors/ReplyReactor.senders_$eq:(Lscala/collection/immutable/List;)V
	aload	5
	areturn
l7	aload_0
	invokeinterface	InterfaceMethod scala/actors/Reactor.mailbox:()Lscala/actors/MQueue;
	new	class scala/actors/Actor$$anonfun$1
	dup
	aload_0
	aload_1
	invokespecial	Method scala/actors/Actor$$anonfun$1."<init>":(Lscala/actors/Actor;Lscala/PartialFunction;)V
	invokevirtual	Method scala/actors/MQueue.extractFirst:(Lscala/Function2;)Lscala/actors/MQueueElement;
	astore	6
	aload	6
	ifnonnull	l8 // aload_0
	aload_0
	dup
	pop
	monitorenter
	aload_0
	invokeinterface	InterfaceMethod scala/actors/Reactor.sendBuffer:()Lscala/actors/MQueue;
	invokevirtual	Method scala/actors/MQueue.isEmpty:()Z
	ifeq	l9 // aload_0
	aload_0
	aload_1
	invokeinterface	InterfaceMethod scala/actors/Reactor.waitingFor_$eq:(Lscala/PartialFunction;)V
	aload_0
	iconst_1
	invokeinterface	InterfaceMethod scala/actors/Actor.scala$actors$Actor$$isSuspended_$eq:(Z)V
	aload_0
	invokeinterface	InterfaceMethod scala/actors/Actor.scheduler:()Lscala/actors/IScheduler;
	aload_0
	invokeinterface	InterfaceMethod scala/actors/Actor.scala$actors$Actor$$blocker:()Lscala/actors/Actor$blocker$;
	invokeinterface	InterfaceMethod scala/actors/IScheduler.managedBlock:(Lscala/concurrent/ManagedBlocker;)V
	aload_0
	aload_0
	invokeinterface	InterfaceMethod scala/actors/Reactor.mailbox:()Lscala/actors/MQueue;
	invokeinterface	InterfaceMethod scala/actors/Reactor.drainSendBuffer:(Lscala/actors/MQueue;)V
	goto	l10 // aload_0
l9	aload_0
	aload_0
	invokeinterface	InterfaceMethod scala/actors/Reactor.mailbox:()Lscala/actors/MQueue;
	invokeinterface	InterfaceMethod scala/actors/Reactor.drainSendBuffer:(Lscala/actors/MQueue;)V
l10	aload_0
	monitorexit
	goto	l11 // goto
l8	aload_0
	new	class scala/Some
	dup
	aload	6
	invokevirtual	Method scala/actors/MQueueElement.msg:()Ljava/lang/Object;
	invokespecial	Method scala/Some."<init>":(Ljava/lang/Object;)V
	invokeinterface	InterfaceMethod scala/actors/Actor.scala$actors$Actor$$received_$eq:(Lscala/Option;)V
	aload_0
	aload	6
	invokevirtual	Method scala/actors/MQueueElement.session:()Lscala/actors/OutputChannel;
	astore	7
	aload_0
	invokeinterface	InterfaceMethod scala/actors/ReplyReactor.senders:()Lscala/collection/immutable/List;
	aload	7
	invokevirtual	Method scala/collection/immutable/List.$colon$colon:(Ljava/lang/Object;)Lscala/collection/immutable/List;
	invokeinterface	InterfaceMethod scala/actors/ReplyReactor.senders_$eq:(Lscala/collection/immutable/List;)V
	iconst_1
	istore	8
l11	goto	l12 // iload
	aload_0
	monitorexit
	athrow
	aload_0
	monitorexit
	athrow
  Labels:
   	l1 = 31 // aload_0
   	l2 = 38 // iconst_1
   	l3 = 42 // iconst_0
   	l4 = 43 // istore
   	l5 = 79 // aload_0
   	l6 = 99 // aload_0
   	l12 = 116 // iload
   	l7 = 170 // aload_0
   	l9 = 257 // aload_0
   	l10 = 269 // aload_0
   	l8 = 274 // aload_0
   	l11 = 319 // goto
  Exception table:
   from   to  target type
   199   271   325   any
    83   113   322   any
  LocalVariableTable: 
   Start  Length  Slot  Name   Signature
   0      328      0    $this       Lscala/actors/Actor;
   0      328      1    f$1       Lscala/PartialFunction;
   138      31      5    result       Ljava/lang/Object;
   190      129      6    qel       Lscala/actors/MQueueElement;
   325      3      6    qel       Lscala/actors/MQueueElement;
   116      53      8    done       Z
   170      152      8    done       Z
   325      3      8    done       Z


public static void resumeReceiver(scala.actors.Actor, scala.Tuple2, scala.PartialFunction, boolean);
  Signature: (Lscala/actors/Actor;Lscala/Tuple2;Lscala/PartialFunction;Z)V
  Code:
   Stack=7, Locals=4, Args_size=4
	aload_0
	dup
	pop
	monitorenter
	aload_0
	invokeinterface	InterfaceMethod scala/actors/Actor.scala$actors$Actor$$onTimeout:()Lscala/Option;
	invokevirtual	Method scala/Option.isEmpty:()Z
	ifeq	l1 // aload_0
	goto	l2 // aload_0
l1	aload_0
	invokeinterface	InterfaceMethod scala/actors/Actor.scala$actors$Actor$$onTimeout:()Lscala/Option;
	invokevirtual	Method scala/Option.get:()Ljava/lang/Object;
	checkcast	class java/util/TimerTask
	invokevirtual	Method java/util/TimerTask.cancel:()Z
	pop
	aload_0
	getstatic	Field scala/None$.MODULE$:Lscala/None$;
	invokeinterface	InterfaceMethod scala/actors/Actor.scala$actors$Actor$$onTimeout_$eq:(Lscala/Option;)V
l2	aload_0
	monitorexit
	aload_0
	getstatic	Field scala/collection/immutable/List$.MODULE$:Lscala/collection/immutable/List$;
	getstatic	Field scala/Predef$.MODULE$:Lscala/Predef$;
	iconst_1
	anewarray	class scala/actors/OutputChannel
	dup
	iconst_0
	aload_1
	invokevirtual	Method scala/Tuple2._2:()Ljava/lang/Object;
	checkcast	class scala/actors/OutputChannel
	aastore
	checkcast	class "[Ljava/lang/Object;"
	invokevirtual	Method scala/Predef$.wrapRefArray:([Ljava/lang/Object;)Lscala/collection/mutable/WrappedArray;
	invokevirtual	Method scala/collection/immutable/List$.apply:(Lscala/collection/Seq;)Lscala/collection/immutable/List;
	invokeinterface	InterfaceMethod scala/actors/ReplyReactor.senders_$eq:(Lscala/collection/immutable/List;)V
	aload_0
	aload_1
	aload_2
	iload_3
	invokeinterface	InterfaceMethod scala/actors/Actor.scala$actors$Actor$$super$resumeReceiver:(Lscala/Tuple2;Lscala/PartialFunction;Z)V
	return
	aload_0
	monitorexit
	athrow
  Labels:
   	l1 = 19 // aload_0
   	l2 = 44 // aload_0
  Exception table:
   from   to  target type
     4    46    91   any
  LocalVariableTable: 
   Start  Length  Slot  Name   Signature
   0      94      0    $this       Lscala/actors/Actor;
   0      94      1    item       Lscala/Tuple2;
   0      94      2    handler       Lscala/PartialFunction;
   0      94      3    onSameThread       Z


public static java.lang.Runnable makeReaction(scala.actors.Actor, scala.Function0);
  Signature: (Lscala/actors/Actor;Lscala/Function0;)Ljava/lang/Runnable;
  Code:
   Stack=4, Locals=2, Args_size=2
	new	class scala/actors/ActorTask
	dup
	aload_0
	aload_1
	invokespecial	Method scala/actors/ActorTask."<init>":(Lscala/actors/Actor;Lscala/Function0;)V
	areturn
  Labels:
  LocalVariableTable: 
   Start  Length  Slot  Name   Signature
   0      10      0    $this       Lscala/actors/Actor;
   0      10      1    fun       Lscala/Function0;


public static scala.Function0 startSearch(scala.actors.Actor, java.lang.Object, scala.actors.OutputChannel, scala.PartialFunction);
  Signature: (Lscala/actors/Actor;Ljava/lang/Object;Lscala/actors/OutputChannel;Lscala/PartialFunction;)Lscala/Function0;
  Code:
   Stack=5, Locals=4, Args_size=4
	aload_0
	invokeinterface	InterfaceMethod scala/actors/Actor.scala$actors$Actor$$isSuspended:()Z
	ifeq	l1 // aload_0
	new	class scala/actors/Actor$$anonfun$startSearch$1
	dup
	aload_0
	aload_1
	aload_2
	invokespecial	Method scala/actors/Actor$$anonfun$startSearch$1."<init>":(Lscala/actors/Actor;Ljava/lang/Object;Lscala/actors/OutputChannel;)V
	goto	l2 // areturn
l1	aload_0
	aload_1
	aload_2
	aload_3
	invokeinterface	InterfaceMethod scala/actors/Actor.scala$actors$Actor$$super$startSearch:(Ljava/lang/Object;Lscala/actors/OutputChannel;Lscala/PartialFunction;)Lscala/Function0;
l2	areturn
  Labels:
   	l1 = 22 // aload_0
   	l2 = 31 // areturn
  LocalVariableTable: 
   Start  Length  Slot  Name   Signature
   0      32      0    $this       Lscala/actors/Actor;
   0      32      1    msg$1       Ljava/lang/Object;
   0      32      2    replyTo$1       Lscala/actors/OutputChannel;
   0      32      3    handler       Lscala/PartialFunction;


public static scala.actors.IScheduler scheduler(scala.actors.Actor);
  Signature: (Lscala/actors/Actor;)Lscala/actors/IScheduler;
  Code:
   Stack=1, Locals=1, Args_size=1
	getstatic	Field scala/actors/Scheduler$.MODULE$:Lscala/actors/Scheduler$;
	areturn
  Labels:
  LocalVariableTable: 
   Start  Length  Slot  Name   Signature
   0      4      0    $this       Lscala/actors/Actor;


}

