Compiled from "Actor.scala"
public final class scala.actors.Actor$$anonfun$unlinkFrom$1 extends scala.runtime.AbstractFunction1 implements java.io.Serializable
  SourceFile: "Actor.scala"
  Scala: length = 0x
   
  InnerClass: 
   public final $anonfun$unlinkFrom$1=class scala/actors/Actor$$anonfun$unlinkFrom$1 of class scala/actors/Actor
  minor version: 0
  major version: 49
  Constant pool:
Asciz	SourceFile;
Asciz	Actor.scala;
Asciz	<clinit>;
Asciz	()V;
Asciz	Code;
Asciz	serialVersionUID;
Asciz	J;
Asciz	scala/actors/Actor$$anonfun$unlinkFrom$1;
class	scala/actors/Actor$$anonfun$unlinkFrom$1
NameAndType	serialVersionUID:J
Field	scala/actors/Actor$$anonfun$unlinkFrom$1.serialVersionUID:J
Asciz	from$2;
Asciz	Lscala/actors/AbstractActor;;
Asciz	<init>;
Asciz	(Lscala/actors/Actor;Lscala/actors/AbstractActor;)V;
Asciz	LineNumberTable;
NameAndType	from$2:Lscala/actors/AbstractActor;
Field	scala/actors/Actor$$anonfun$unlinkFrom$1.from$2:Lscala/actors/AbstractActor;
Asciz	scala/runtime/AbstractFunction1;
class	scala/runtime/AbstractFunction1
NameAndType	"<init>":()V
Method	scala/runtime/AbstractFunction1."<init>":()V
Asciz	this;
Asciz	Lscala/actors/Actor$$anonfun$unlinkFrom$1;;
Asciz	$outer;
Asciz	Lscala/actors/Actor;;
Asciz	LocalVariableTable;
Asciz	apply;
Asciz	(Ljava/lang/Object;)Ljava/lang/Object;;
Asciz	(Ljava/lang/Object;)Z;
NameAndType	apply:(Ljava/lang/Object;)Z
Method	scala/actors/Actor$$anonfun$unlinkFrom$1.apply:(Ljava/lang/Object;)Z
Asciz	scala/runtime/BoxesRunTime;
class	scala/runtime/BoxesRunTime
Asciz	boxToBoolean;
Asciz	(Z)Ljava/lang/Boolean;;
NameAndType	boxToBoolean:(Z)Ljava/lang/Boolean;
Method	scala/runtime/BoxesRunTime.boxToBoolean:(Z)Ljava/lang/Boolean;
Asciz	v1;
Asciz	Ljava/lang/Object;;
Asciz	java/lang/Object;
class	java/lang/Object
Asciz	equals;
NameAndType	equals:(Ljava/lang/Object;)Z
Method	java/lang/Object.equals:(Ljava/lang/Object;)Z
Asciz	Scala;
Asciz	InnerClasses;
Asciz	scala/actors/Actor;
class	scala/actors/Actor
Asciz	$anonfun$unlinkFrom$1;
Asciz	java/io/Serializable;
class	java/io/Serializable

{
public static final long serialVersionUID;
  Signature: J

private final scala.actors.AbstractActor from$2;
  Signature: Lscala/actors/AbstractActor;

public static {};
  Signature: ()V
  Code:
   Stack=2, Locals=0, Args_size=0
	lconst_0
	putstatic	Field serialVersionUID:J
	return
  Labels:

public scala.actors.Actor$$anonfun$unlinkFrom$1(scala.actors.Actor, scala.actors.AbstractActor);
  Signature: (Lscala/actors/Actor;Lscala/actors/AbstractActor;)V
  Code:
   Stack=2, Locals=3, Args_size=3
	aload_0
	aload_2
	putfield	Field from$2:Lscala/actors/AbstractActor;
	aload_0
	invokespecial	Method scala/runtime/AbstractFunction1."<init>":()V
	return
  Labels:
  LocalVariableTable: 
   Start  Length  Slot  Name   Signature
   0      10      0    this       Lscala/actors/Actor$$anonfun$unlinkFrom$1;
   0      10      1    $outer       Lscala/actors/Actor;


public final java.lang.Object apply(java.lang.Object);
  Signature: (Ljava/lang/Object;)Ljava/lang/Object;
  Code:
   Stack=2, Locals=3, Args_size=2
	aload_0
	aload_1
	invokevirtual	Method apply:(Ljava/lang/Object;)Z
	istore_2
	iload_2
	invokestatic	Method scala/runtime/BoxesRunTime.boxToBoolean:(Z)Ljava/lang/Boolean;
	areturn
  Labels:
  LocalVariableTable: 
   Start  Length  Slot  Name   Signature
   0      11      0    this       Lscala/actors/Actor$$anonfun$unlinkFrom$1;
   0      11      1    v1       Ljava/lang/Object;


public final boolean apply(java.lang.Object);
  Signature: (Ljava/lang/Object;)Z
  Code:
   Stack=2, Locals=2, Args_size=2
	aload_0
	getfield	Field from$2:Lscala/actors/AbstractActor;
	dup
	ifnonnull	l1 // aload_1
	pop
	aload_1
	ifnull	l2 // iconst_1
	goto	l3 // iconst_0
l1	aload_1
	invokevirtual	Method java/lang/Object.equals:(Ljava/lang/Object;)Z
	ifeq	l3 // iconst_0
l2	iconst_1
	goto	l4 // ireturn
l3	iconst_0
l4	ireturn
  Labels:
   	l1 = 16 // aload_1
   	l2 = 23 // iconst_1
   	l3 = 27 // iconst_0
   	l4 = 28 // ireturn

}

