Compiled from "Actor.scala"
public final class scala.actors.Actor$$anonfun$respondOn$1 extends java.lang.Object implements scala.Function1,scala.ScalaObject,java.io.Serializable
  SourceFile: "Actor.scala"
  Scala: length = 0x
   
  InnerClass: 
   public final $anonfun$respondOn$1=class scala/actors/Actor$$anonfun$respondOn$1 of class scala/actors/Actor
   public final $anon$4=class scala/actors/Actor$$anonfun$respondOn$1$$anon$4 of class scala/actors/Actor$$anonfun$respondOn$1
  minor version: 0
  major version: 49
  Constant pool:
Asciz	SourceFile;
Asciz	Actor.scala;
Asciz	<clinit>;
Asciz	()V;
Asciz	Code;
Asciz	serialVersionUID;
Asciz	J;
Asciz	scala/actors/Actor$$anonfun$respondOn$1;
class	scala/actors/Actor$$anonfun$respondOn$1
NameAndType	serialVersionUID:J
Field	scala/actors/Actor$$anonfun$respondOn$1.serialVersionUID:J
Asciz	fun$1;
Asciz	Lscala/Function1;;
Asciz	<init>;
Asciz	(Lscala/Function1;)V;
Asciz	LineNumberTable;
NameAndType	fun$1:Lscala/Function1;
Field	scala/actors/Actor$$anonfun$respondOn$1.fun$1:Lscala/Function1;
Asciz	java/lang/Object;
class	java/lang/Object
NameAndType	"<init>":()V
Method	java/lang/Object."<init>":()V
Asciz	scala/Function1$class;
class	scala/Function1$class
Asciz	$init$;
NameAndType	$init$:(Lscala/Function1;)V
Method	scala/Function1$class.$init$:(Lscala/Function1;)V
Asciz	apply;
Asciz	(Ljava/lang/Object;)Ljava/lang/Object;;
Asciz	scala/PartialFunction;
class	scala/PartialFunction
Asciz	(Lscala/PartialFunction;)Lscala/Responder;;
NameAndType	apply:(Lscala/PartialFunction;)Lscala/Responder;
Method	scala/actors/Actor$$anonfun$respondOn$1.apply:(Lscala/PartialFunction;)Lscala/Responder;
Asciz	this;
Asciz	Lscala/actors/Actor$$anonfun$respondOn$1;;
Asciz	v1;
Asciz	Ljava/lang/Object;;
Asciz	LocalVariableTable;
Asciz	scala/actors/Actor$$anonfun$respondOn$1$$anon$4;
class	scala/actors/Actor$$anonfun$respondOn$1$$anon$4
Asciz	(Lscala/actors/Actor$$anonfun$respondOn$1;Lscala/PartialFunction;)V;
NameAndType	"<init>":(Lscala/actors/Actor$$anonfun$respondOn$1;Lscala/PartialFunction;)V
Method	scala/actors/Actor$$anonfun$respondOn$1$$anon$4."<init>":(Lscala/actors/Actor$$anonfun$respondOn$1;Lscala/PartialFunction;)V
Asciz	caseBlock$1;
Asciz	Lscala/PartialFunction;;
Asciz	(Lscala/PartialFunction<TA;TB;>;)Lscala/Responder<TB;>;;
Asciz	Signature;
Asciz	andThen;
Asciz	(Lscala/Function1;)Lscala/Function1;;
Asciz	(Lscala/Function1;Lscala/Function1;)Lscala/Function1;;
NameAndType	andThen:(Lscala/Function1;Lscala/Function1;)Lscala/Function1;
Method	scala/Function1$class.andThen:(Lscala/Function1;Lscala/Function1;)Lscala/Function1;
Asciz	g;
Asciz	compose;
NameAndType	compose:(Lscala/Function1;Lscala/Function1;)Lscala/Function1;
Method	scala/Function1$class.compose:(Lscala/Function1;Lscala/Function1;)Lscala/Function1;
Asciz	toString;
Asciz	()Ljava/lang/String;;
Asciz	(Lscala/Function1;)Ljava/lang/String;;
NameAndType	toString:(Lscala/Function1;)Ljava/lang/String;
Method	scala/Function1$class.toString:(Lscala/Function1;)Ljava/lang/String;
Asciz	Scala;
Asciz	InnerClasses;
Asciz	scala/actors/Actor;
class	scala/actors/Actor
Asciz	$anonfun$respondOn$1;
Asciz	$anon$4;
Asciz	scala/Function1;
class	scala/Function1
Asciz	scala/ScalaObject;
class	scala/ScalaObject
Asciz	java/io/Serializable;
class	java/io/Serializable

{
public static final long serialVersionUID;
  Signature: J

public final scala.Function1 fun$1;
  Signature: Lscala/Function1;

public static {};
  Signature: ()V
  Code:
   Stack=2, Locals=0, Args_size=0
	lconst_0
	putstatic	Field serialVersionUID:J
	return
  Labels:

public scala.actors.Actor$$anonfun$respondOn$1(scala.Function1);
  Signature: (Lscala/Function1;)V
  Code:
   Stack=2, Locals=2, Args_size=2
	aload_0
	aload_1
	putfield	Field fun$1:Lscala/Function1;
	aload_0
	invokespecial	Method java/lang/Object."<init>":()V
	aload_0
	invokestatic	Method scala/Function1$class.$init$:(Lscala/Function1;)V
	return
  Labels:

public final java.lang.Object apply(java.lang.Object);
  Signature: (Ljava/lang/Object;)Ljava/lang/Object;
  Code:
   Stack=2, Locals=2, Args_size=2
	aload_0
	aload_1
	checkcast	class scala/PartialFunction
	invokevirtual	Method apply:(Lscala/PartialFunction;)Lscala/Responder;
	areturn
  Labels:
  LocalVariableTable: 
   Start  Length  Slot  Name   Signature
   0      9      0    this       Lscala/actors/Actor$$anonfun$respondOn$1;
   0      9      1    v1       Ljava/lang/Object;


public final scala.Responder apply(scala.PartialFunction);
  Signature: (Lscala/PartialFunction;)Lscala/Responder;
  Code:
   Stack=4, Locals=2, Args_size=2
	new	class scala/actors/Actor$$anonfun$respondOn$1$$anon$4
	dup
	aload_0
	aload_1
	invokespecial	Method scala/actors/Actor$$anonfun$respondOn$1$$anon$4."<init>":(Lscala/actors/Actor$$anonfun$respondOn$1;Lscala/PartialFunction;)V
	areturn
  Labels:
  LocalVariableTable: 
   Start  Length  Slot  Name   Signature
   0      10      0    this       Lscala/actors/Actor$$anonfun$respondOn$1;
   0      10      1    caseBlock$1       Lscala/PartialFunction;

  Signature: length = 0x2
   00 2F 

public scala.Function1 andThen(scala.Function1);
  Signature: (Lscala/Function1;)Lscala/Function1;
  Code:
   Stack=2, Locals=2, Args_size=2
	aload_0
	aload_1
	invokestatic	Method scala/Function1$class.andThen:(Lscala/Function1;Lscala/Function1;)Lscala/Function1;
	areturn
  Labels:
  LocalVariableTable: 
   Start  Length  Slot  Name   Signature
   0      6      0    this       Lscala/actors/Actor$$anonfun$respondOn$1;
   0      6      1    g       Lscala/Function1;


public scala.Function1 compose(scala.Function1);
  Signature: (Lscala/Function1;)Lscala/Function1;
  Code:
   Stack=2, Locals=2, Args_size=2
	aload_0
	aload_1
	invokestatic	Method scala/Function1$class.compose:(Lscala/Function1;Lscala/Function1;)Lscala/Function1;
	areturn
  Labels:
  LocalVariableTable: 
   Start  Length  Slot  Name   Signature
   0      6      0    this       Lscala/actors/Actor$$anonfun$respondOn$1;
   0      6      1    g       Lscala/Function1;


public java.lang.String toString();
  Signature: ()Ljava/lang/String;
  Code:
   Stack=1, Locals=1, Args_size=1
	aload_0
	invokestatic	Method scala/Function1$class.toString:(Lscala/Function1;)Ljava/lang/String;
	areturn
  Labels:

}

