Compiled from "Actor.scala"
public final class scala.actors.Actor$$anonfun$loop$1 extends scala.runtime.AbstractFunction0 implements java.io.Serializable
  SourceFile: "Actor.scala"
  Scala: length = 0x
   
  InnerClass: 
   public final $anon$7=class scala/actors/Actor$$anon$7 of class scala/actors/Actor
   public final $anonfun$loop$1=class scala/actors/Actor$$anonfun$loop$1 of class scala/actors/Actor
  minor version: 0
  major version: 49
  Constant pool:
Asciz	SourceFile;
Asciz	Actor.scala;
Asciz	<clinit>;
Asciz	()V;
Asciz	Code;
Asciz	serialVersionUID;
Asciz	J;
Asciz	scala/actors/Actor$$anonfun$loop$1;
class	scala/actors/Actor$$anonfun$loop$1
NameAndType	serialVersionUID:J
Field	scala/actors/Actor$$anonfun$loop$1.serialVersionUID:J
Asciz	body$4;
Asciz	Lscala/Function0;;
Asciz	apply;
Asciz	LineNumberTable;
NameAndType	body$4:Lscala/Function0;
Field	scala/actors/Actor$$anonfun$loop$1.body$4:Lscala/Function0;
Asciz	scala/actors/Actor$$anon$7;
class	scala/actors/Actor$$anon$7
Asciz	<init>;
Asciz	(Lscala/Function0;)V;
NameAndType	"<init>":(Lscala/Function0;)V
Method	scala/actors/Actor$$anon$7."<init>":(Lscala/Function0;)V
Method	scala/actors/Actor$$anonfun$loop$1."<init>":(Lscala/Function0;)V
Asciz	scala/actors/Actor$;
class	scala/actors/Actor$
Asciz	MODULE$;
Asciz	Lscala/actors/Actor$;;
NameAndType	MODULE$:Lscala/actors/Actor$;
Field	scala/actors/Actor$.MODULE$:Lscala/actors/Actor$;
Asciz	scala/actors/Scheduler$;
class	scala/actors/Scheduler$
Asciz	Lscala/actors/Scheduler$;;
NameAndType	MODULE$:Lscala/actors/Scheduler$;
Field	scala/actors/Scheduler$.MODULE$:Lscala/actors/Scheduler$;
Asciz	rawSelf;
Asciz	(Lscala/actors/IScheduler;)Lscala/actors/Reactor;;
NameAndType	rawSelf:(Lscala/actors/IScheduler;)Lscala/actors/Reactor;
Method	scala/actors/Actor$.rawSelf:(Lscala/actors/IScheduler;)Lscala/actors/Reactor;
Asciz	scala/actors/Reactor;
class	scala/actors/Reactor
Asciz	seq;
Asciz	(Lscala/Function0;Lscala/Function0;)V;
NameAndType	seq:(Lscala/Function0;Lscala/Function0;)V
InterfaceMethod	scala/actors/Reactor.seq:(Lscala/Function0;Lscala/Function0;)V
Asciz	this;
Asciz	Lscala/actors/Actor$$anonfun$loop$1;;
Asciz	LocalVariableTable;
Asciz	()Ljava/lang/Object;;
NameAndType	apply:()V
Method	scala/actors/Actor$$anonfun$loop$1.apply:()V
Asciz	scala/runtime/BoxedUnit;
class	scala/runtime/BoxedUnit
Asciz	UNIT;
Asciz	Lscala/runtime/BoxedUnit;;
NameAndType	UNIT:Lscala/runtime/BoxedUnit;
Field	scala/runtime/BoxedUnit.UNIT:Lscala/runtime/BoxedUnit;
Asciz	scala/runtime/AbstractFunction0;
class	scala/runtime/AbstractFunction0
NameAndType	"<init>":()V
Method	scala/runtime/AbstractFunction0."<init>":()V
Asciz	Scala;
Asciz	InnerClasses;
Asciz	scala/actors/Actor;
class	scala/actors/Actor
Asciz	$anon$7;
Asciz	$anonfun$loop$1;
Asciz	java/io/Serializable;
class	java/io/Serializable

{
public static final long serialVersionUID;
  Signature: J

public final scala.Function0 body$4;
  Signature: Lscala/Function0;

public static {};
  Signature: ()V
  Code:
   Stack=2, Locals=0, Args_size=0
	lconst_0
	putstatic	Field serialVersionUID:J
	return
  Labels:

public final void apply();
  Signature: ()V
  Code:
   Stack=3, Locals=4, Args_size=1
	aload_0
	getfield	Field body$4:Lscala/Function0;
	astore_2
	new	class scala/actors/Actor$$anon$7
	dup
	aload_2
	invokespecial	Method scala/actors/Actor$$anon$7."<init>":(Lscala/Function0;)V
	pop
	new	class scala/actors/Actor$$anonfun$loop$1
	dup
	aload_2
	invokespecial	Method "<init>":(Lscala/Function0;)V
	astore_3
	getstatic	Field scala/actors/Actor$.MODULE$:Lscala/actors/Actor$;
	astore_1
	aload_1
	getstatic	Field scala/actors/Scheduler$.MODULE$:Lscala/actors/Scheduler$;
	invokevirtual	Method scala/actors/Actor$.rawSelf:(Lscala/actors/IScheduler;)Lscala/actors/Reactor;
	aload_2
	aload_3
	invokeinterface	InterfaceMethod scala/actors/Reactor.seq:(Lscala/Function0;Lscala/Function0;)V
	return
  Labels:
  LocalVariableTable: 
   Start  Length  Slot  Name   Signature
   0      42      0    this       Lscala/actors/Actor$$anonfun$loop$1;


public final java.lang.Object apply();
  Signature: ()Ljava/lang/Object;
  Code:
   Stack=1, Locals=1, Args_size=1
	aload_0
	invokevirtual	Method apply:()V
	getstatic	Field scala/runtime/BoxedUnit.UNIT:Lscala/runtime/BoxedUnit;
	areturn
  Labels:

public scala.actors.Actor$$anonfun$loop$1(scala.Function0);
  Signature: (Lscala/Function0;)V
  Code:
   Stack=2, Locals=2, Args_size=2
	aload_0
	aload_1
	putfield	Field body$4:Lscala/Function0;
	aload_0
	invokespecial	Method scala/runtime/AbstractFunction0."<init>":()V
	return
  Labels:

}

