Compiled from "Actor.scala"
public final class scala.actors.Actor$blocker$ extends java.lang.Object implements scala.concurrent.ManagedBlocker,scala.ScalaObject
  SourceFile: "Actor.scala"
  Scala: length = 0x
   
  minor version: 0
  major version: 49
  Constant pool:
const #1 = Asciz	SourceFile;
const #2 = Asciz	Actor.scala;
const #3 = Asciz	Scala;
const #4 = Asciz	$outer;
const #5 = Asciz	Lscala/actors/Actor;;
const #6 = Asciz	<init>;
const #7 = Asciz	(Lscala/actors/Actor;)V;
const #8 = Asciz	Code;
const #9 = Asciz	LineNumberTable;
const #10 = Asciz	java/lang/NullPointerException;
const #11 = class	#10;	//  java/lang/NullPointerException
const #12 = Asciz	()V;
const #13 = NameAndType	#6:#12;//  "<init>":()V
const #14 = Method	#11.#13;	//  java/lang/NullPointerException."<init>":()V
const #15 = Asciz	scala/actors/Actor$blocker$;
const #16 = class	#15;	//  scala/actors/Actor$blocker$
const #17 = NameAndType	#4:#5;//  $outer:Lscala/actors/Actor;
const #18 = Field	#16.#17;	//  scala/actors/Actor$blocker$.$outer:Lscala/actors/Actor;
const #19 = Asciz	java/lang/Object;
const #20 = class	#19;	//  java/lang/Object
const #21 = Method	#20.#13;	//  java/lang/Object."<init>":()V
const #22 = Asciz	this;
const #23 = Asciz	Lscala/actors/Actor$blocker$;;
const #24 = Asciz	LocalVariableTable;
const #25 = Asciz	isReleasable;
const #26 = Asciz	()Z;
const #27 = Asciz	scala/actors/Actor;
const #28 = class	#27;	//  scala/actors/Actor
const #29 = Asciz	scala$actors$Actor$$isSuspended;
const #30 = NameAndType	#29:#26;//  scala$actors$Actor$$isSuspended:()Z
const #31 = InterfaceMethod	#28.#30;	//  scala/actors/Actor.scala$actors$Actor$$isSuspended:()Z
const #32 = Asciz	block;
const #33 = Asciz	scala/actors/Actor$class;
const #34 = class	#33;	//  scala/actors/Actor$class
const #35 = Asciz	scala$actors$Actor$$suspendActor;
const #36 = NameAndType	#35:#7;//  scala$actors$Actor$$suspendActor:(Lscala/actors/Actor;)V
const #37 = Method	#34.#36;	//  scala/actors/Actor$class.scala$actors$Actor$$suspendActor:(Lscala/actors/Actor;)V
const #38 = Asciz	scala/concurrent/ManagedBlocker;
const #39 = class	#38;	//  scala/concurrent/ManagedBlocker
const #40 = Asciz	scala/ScalaObject;
const #41 = class	#40;	//  scala/ScalaObject

{
public scala.actors.Actor$blocker$(scala.actors.Actor);
  Code:
   Stack=2, Locals=2, Args_size=2
   0:	aload_1
   1:	ifnonnull	12
   4:	new	#11; //class java/lang/NullPointerException
   7:	dup
   8:	invokespecial	#14; //Method java/lang/NullPointerException."<init>":()V
   11:	athrow
   12:	aload_0
   13:	aload_1
   14:	putfield	#18; //Field $outer:Lscala/actors/Actor;
   17:	aload_0
   18:	invokespecial	#21; //Method java/lang/Object."<init>":()V
   21:	return
  LineNumberTable: 
   line 661: 0

  LocalVariableTable: 
   Start  Length  Slot  Name   Signature
   0      22      0    this       Lscala/actors/Actor$blocker$;
   0      22      1    $outer       Lscala/actors/Actor;


public boolean isReleasable();
  Code:
   Stack=1, Locals=1, Args_size=1
   0:	aload_0
   1:	getfield	#18; //Field $outer:Lscala/actors/Actor;
   4:	invokeinterface	#31,  1; //InterfaceMethod scala/actors/Actor.scala$actors$Actor$$isSuspended:()Z
   9:	ifeq	16
   12:	iconst_0
   13:	goto	17
   16:	iconst_1
   17:	ireturn
  LineNumberTable: 
   line 667: 0


public boolean block();
  Code:
   Stack=1, Locals=1, Args_size=1
   0:	aload_0
   1:	getfield	#18; //Field $outer:Lscala/actors/Actor;
   4:	invokestatic	#37; //Method scala/actors/Actor$class.scala$actors$Actor$$suspendActor:(Lscala/actors/Actor;)V
   7:	iconst_1
   8:	ireturn
  LineNumberTable: 
   line 663: 0
   line 664: 7


}

