Compiled from "Actor.scala"
public final class scala.actors.Actor$State$ extends scala.Enumeration implements scala.ScalaObject
  SourceFile: "Actor.scala"
  Scala: length = 0x
   
  InnerClass: 
   public abstract Value=class scala/Enumeration$Value of class scala/Enumeration
  minor version: 0
  major version: 49
  Constant pool:
Asciz	SourceFile;
Asciz	Actor.scala;
Asciz	MODULE$;
Asciz	Lscala/actors/Actor$State$;;
Asciz	<clinit>;
Asciz	()V;
Asciz	Code;
Asciz	scala/actors/Actor$State$;
class	scala/actors/Actor$State$
Asciz	<init>;
NameAndType	"<init>":()V
Method	scala/actors/Actor$State$."<init>":()V
Asciz	New;
Asciz	Lscala/Enumeration$Value;;
Asciz	Runnable;
Asciz	Suspended;
Asciz	TimedSuspended;
Asciz	Blocked;
Asciz	TimedBlocked;
Asciz	Terminated;
Asciz	()Lscala/Enumeration$Value;;
Asciz	LineNumberTable;
NameAndType	New:Lscala/Enumeration$Value;
Field	scala/actors/Actor$State$.New:Lscala/Enumeration$Value;
NameAndType	Runnable:Lscala/Enumeration$Value;
Field	scala/actors/Actor$State$.Runnable:Lscala/Enumeration$Value;
NameAndType	Suspended:Lscala/Enumeration$Value;
Field	scala/actors/Actor$State$.Suspended:Lscala/Enumeration$Value;
NameAndType	TimedSuspended:Lscala/Enumeration$Value;
Field	scala/actors/Actor$State$.TimedSuspended:Lscala/Enumeration$Value;
NameAndType	Blocked:Lscala/Enumeration$Value;
Field	scala/actors/Actor$State$.Blocked:Lscala/Enumeration$Value;
NameAndType	TimedBlocked:Lscala/Enumeration$Value;
Field	scala/actors/Actor$State$.TimedBlocked:Lscala/Enumeration$Value;
NameAndType	Terminated:Lscala/Enumeration$Value;
Field	scala/actors/Actor$State$.Terminated:Lscala/Enumeration$Value;
Asciz	scala/Enumeration;
class	scala/Enumeration
Method	scala/Enumeration."<init>":()V
NameAndType	MODULE$:Lscala/actors/Actor$State$;
Field	scala/actors/Actor$State$.MODULE$:Lscala/actors/Actor$State$;
Asciz	Value;
NameAndType	Value:()Lscala/Enumeration$Value;
Method	scala/actors/Actor$State$.Value:()Lscala/Enumeration$Value;
Asciz	Scala;
Asciz	InnerClasses;
Asciz	scala/Enumeration$Value;
class	scala/Enumeration$Value
Asciz	scala/ScalaObject;
class	scala/ScalaObject

{
public static final scala.actors.Actor$State$ MODULE$;
  Signature: Lscala/actors/Actor$State$;

private final scala.Enumeration$Value New;
  Signature: Lscala/Enumeration$Value;

private final scala.Enumeration$Value Runnable;
  Signature: Lscala/Enumeration$Value;

private final scala.Enumeration$Value Suspended;
  Signature: Lscala/Enumeration$Value;

private final scala.Enumeration$Value TimedSuspended;
  Signature: Lscala/Enumeration$Value;

private final scala.Enumeration$Value Blocked;
  Signature: Lscala/Enumeration$Value;

private final scala.Enumeration$Value TimedBlocked;
  Signature: Lscala/Enumeration$Value;

private final scala.Enumeration$Value Terminated;
  Signature: Lscala/Enumeration$Value;

public static {};
  Signature: ()V
  Code:
   Stack=1, Locals=0, Args_size=0
	new	class scala/actors/Actor$State$
	invokespecial	Method "<init>":()V
	return
  Labels:

public scala.Enumeration$Value New();
  Signature: ()Lscala/Enumeration$Value;
  Code:
   Stack=1, Locals=1, Args_size=1
	aload_0
	getfield	Field New:Lscala/Enumeration$Value;
	areturn
  Labels:

public scala.Enumeration$Value Runnable();
  Signature: ()Lscala/Enumeration$Value;
  Code:
   Stack=1, Locals=1, Args_size=1
	aload_0
	getfield	Field Runnable:Lscala/Enumeration$Value;
	areturn
  Labels:

public scala.Enumeration$Value Suspended();
  Signature: ()Lscala/Enumeration$Value;
  Code:
   Stack=1, Locals=1, Args_size=1
	aload_0
	getfield	Field Suspended:Lscala/Enumeration$Value;
	areturn
  Labels:

public scala.Enumeration$Value TimedSuspended();
  Signature: ()Lscala/Enumeration$Value;
  Code:
   Stack=1, Locals=1, Args_size=1
	aload_0
	getfield	Field TimedSuspended:Lscala/Enumeration$Value;
	areturn
  Labels:

public scala.Enumeration$Value Blocked();
  Signature: ()Lscala/Enumeration$Value;
  Code:
   Stack=1, Locals=1, Args_size=1
	aload_0
	getfield	Field Blocked:Lscala/Enumeration$Value;
	areturn
  Labels:

public scala.Enumeration$Value TimedBlocked();
  Signature: ()Lscala/Enumeration$Value;
  Code:
   Stack=1, Locals=1, Args_size=1
	aload_0
	getfield	Field TimedBlocked:Lscala/Enumeration$Value;
	areturn
  Labels:

public scala.Enumeration$Value Terminated();
  Signature: ()Lscala/Enumeration$Value;
  Code:
   Stack=1, Locals=1, Args_size=1
	aload_0
	getfield	Field Terminated:Lscala/Enumeration$Value;
	areturn
  Labels:

public scala.actors.Actor$State$();
  Signature: ()V
  Code:
   Stack=2, Locals=1, Args_size=1
	aload_0
	invokespecial	Method scala/Enumeration."<init>":()V
	aload_0
	putstatic	Field MODULE$:Lscala/actors/Actor$State$;
	aload_0
	aload_0
	invokevirtual	Method Value:()Lscala/Enumeration$Value;
	putfield	Field New:Lscala/Enumeration$Value;
	aload_0
	aload_0
	invokevirtual	Method Value:()Lscala/Enumeration$Value;
	putfield	Field Runnable:Lscala/Enumeration$Value;
	aload_0
	aload_0
	invokevirtual	Method Value:()Lscala/Enumeration$Value;
	putfield	Field Suspended:Lscala/Enumeration$Value;
	aload_0
	aload_0
	invokevirtual	Method Value:()Lscala/Enumeration$Value;
	putfield	Field TimedSuspended:Lscala/Enumeration$Value;
	aload_0
	aload_0
	invokevirtual	Method Value:()Lscala/Enumeration$Value;
	putfield	Field Blocked:Lscala/Enumeration$Value;
	aload_0
	aload_0
	invokevirtual	Method Value:()Lscala/Enumeration$Value;
	putfield	Field TimedBlocked:Lscala/Enumeration$Value;
	aload_0
	aload_0
	invokevirtual	Method Value:()Lscala/Enumeration$Value;
	putfield	Field Terminated:Lscala/Enumeration$Value;
	return
  Labels:

}

