Compiled from "Actor.scala"
public final class scala.actors.Actor$$anonfun$respondOn$1$$anon$4 extends scala.Responder
  SourceFile: "Actor.scala"
  Signature: length = 0x2
   00 38 
  Scala: length = 0x
   
  InnerClass: 
   public final $anonfun$respondOn$1=class scala/actors/Actor$$anonfun$respondOn$1 of class scala/actors/Actor
   public final $anon$4=class scala/actors/Actor$$anonfun$respondOn$1$$anon$4 of class scala/actors/Actor$$anonfun$respondOn$1
  minor version: 0
  major version: 49
  Constant pool:
Asciz	SourceFile;
Asciz	Actor.scala;
Asciz	caseBlock$1;
Asciz	Lscala/PartialFunction;;
Asciz	$outer;
Asciz	Lscala/actors/Actor$$anonfun$respondOn$1;;
Asciz	<init>;
Asciz	(Lscala/actors/Actor$$anonfun$respondOn$1;Lscala/PartialFunction;)V;
Asciz	Code;
Asciz	LineNumberTable;
Asciz	java/lang/NullPointerException;
class	java/lang/NullPointerException
Asciz	()V;
NameAndType	"<init>":()V
Method	java/lang/NullPointerException."<init>":()V
Asciz	scala/actors/Actor$$anonfun$respondOn$1$$anon$4;
class	scala/actors/Actor$$anonfun$respondOn$1$$anon$4
NameAndType	$outer:Lscala/actors/Actor$$anonfun$respondOn$1;
Field	scala/actors/Actor$$anonfun$respondOn$1$$anon$4.$outer:Lscala/actors/Actor$$anonfun$respondOn$1;
NameAndType	caseBlock$1:Lscala/PartialFunction;
Field	scala/actors/Actor$$anonfun$respondOn$1$$anon$4.caseBlock$1:Lscala/PartialFunction;
Asciz	scala/Responder;
class	scala/Responder
Method	scala/Responder."<init>":()V
Asciz	this;
Asciz	Lscala/actors/Actor$$anonfun$respondOn$1$$anon$4;;
Asciz	LocalVariableTable;
Asciz	respond;
Asciz	(Lscala/Function1;)V;
Asciz	(Lscala/Function1;)Lscala/runtime/Nothing$;;
NameAndType	respond:(Lscala/Function1;)Lscala/runtime/Nothing$;
Method	scala/actors/Actor$$anonfun$respondOn$1$$anon$4.respond:(Lscala/Function1;)Lscala/runtime/Nothing$;
Asciz	k;
Asciz	Lscala/Function1;;
Asciz	scala/actors/Actor$$anonfun$respondOn$1;
class	scala/actors/Actor$$anonfun$respondOn$1
Asciz	fun$1;
NameAndType	fun$1:Lscala/Function1;
Field	scala/actors/Actor$$anonfun$respondOn$1.fun$1:Lscala/Function1;
Asciz	scala/PartialFunction;
class	scala/PartialFunction
Asciz	andThen;
Asciz	(Lscala/Function1;)Lscala/PartialFunction;;
NameAndType	andThen:(Lscala/Function1;)Lscala/PartialFunction;
InterfaceMethod	scala/PartialFunction.andThen:(Lscala/Function1;)Lscala/PartialFunction;
Asciz	scala/Function1;
class	scala/Function1
Asciz	apply;
Asciz	(Ljava/lang/Object;)Ljava/lang/Object;;
NameAndType	apply:(Ljava/lang/Object;)Ljava/lang/Object;
InterfaceMethod	scala/Function1.apply:(Ljava/lang/Object;)Ljava/lang/Object;
Asciz	scala/runtime/Nothing$;
class	scala/runtime/Nothing$
Asciz	(Lscala/Function1<TB;Ljava/lang/Object;>;)Lscala/runtime/Nothing$;;
Asciz	Signature;
Asciz	Lscala/Responder<TB;>;;
Asciz	Scala;
Asciz	InnerClasses;
Asciz	scala/actors/Actor;
class	scala/actors/Actor
Asciz	$anonfun$respondOn$1;
Asciz	$anon$4;

{
private final scala.PartialFunction caseBlock$1;
  Signature: Lscala/PartialFunction;

private final scala.actors.Actor$$anonfun$respondOn$1 $outer;
  Signature: Lscala/actors/Actor$$anonfun$respondOn$1;

public scala.actors.Actor$$anonfun$respondOn$1$$anon$4(scala.actors.Actor$$anonfun$respondOn$1, scala.PartialFunction);
  Signature: (Lscala/actors/Actor$$anonfun$respondOn$1;Lscala/PartialFunction;)V
  Code:
   Stack=2, Locals=3, Args_size=3
	aload_1
	ifnonnull	l1 // aload_0
	new	class java/lang/NullPointerException
	dup
	invokespecial	Method java/lang/NullPointerException."<init>":()V
	athrow
l1	aload_0
	aload_1
	putfield	Field $outer:Lscala/actors/Actor$$anonfun$respondOn$1;
	aload_0
	aload_2
	putfield	Field caseBlock$1:Lscala/PartialFunction;
	aload_0
	invokespecial	Method scala/Responder."<init>":()V
	return
  Labels:
   	l1 = 12 // aload_0
  LocalVariableTable: 
   Start  Length  Slot  Name   Signature
   0      27      0    this       Lscala/actors/Actor$$anonfun$respondOn$1$$anon$4;
   0      27      1    $outer       Lscala/actors/Actor$$anonfun$respondOn$1;


public void respond(scala.Function1);
  Signature: (Lscala/Function1;)V
  Code:
   Stack=2, Locals=2, Args_size=2
	aload_0
	aload_1
	invokevirtual	Method respond:(Lscala/Function1;)Lscala/runtime/Nothing$;
	athrow
  Labels:
  LocalVariableTable: 
   Start  Length  Slot  Name   Signature
   0      6      0    this       Lscala/actors/Actor$$anonfun$respondOn$1$$anon$4;
   0      6      1    k       Lscala/Function1;


public scala.runtime.Nothing$ respond(scala.Function1);
  Signature: (Lscala/Function1;)Lscala/runtime/Nothing$;
  Code:
   Stack=3, Locals=2, Args_size=2
	aload_0
	getfield	Field $outer:Lscala/actors/Actor$$anonfun$respondOn$1;
	getfield	Field scala/actors/Actor$$anonfun$respondOn$1.fun$1:Lscala/Function1;
	aload_0
	getfield	Field caseBlock$1:Lscala/PartialFunction;
	aload_1
	invokeinterface	InterfaceMethod scala/PartialFunction.andThen:(Lscala/Function1;)Lscala/PartialFunction;
	invokeinterface	InterfaceMethod scala/Function1.apply:(Ljava/lang/Object;)Ljava/lang/Object;
	checkcast	class scala/runtime/Nothing$
	areturn
  Labels:
  LocalVariableTable: 
   Start  Length  Slot  Name   Signature
   0      26      0    this       Lscala/actors/Actor$$anonfun$respondOn$1$$anon$4;
   0      26      1    k       Lscala/Function1;

  Signature: length = 0x2
   00 36 

}

