Compiled from "Actor.scala"
public class scala.actors.Actor$RecursiveProxyHandler extends java.lang.Object implements scala.PartialFunction,scala.ScalaObject
  SourceFile: "Actor.scala"
  Signature: length = 0x2
   00 64 
  Scala: length = 0x
   
  InnerClass: 
   public RecursiveProxyHandler=class scala/actors/Actor$RecursiveProxyHandler of class scala/actors/Actor
  minor version: 0
  major version: 49
  Constant pool:
Asciz	SourceFile;
Asciz	Actor.scala;
Asciz	f;
Asciz	Lscala/PartialFunction;;
Asciz	Lscala/PartialFunction<Ljava/lang/Object;Ljava/lang/Object;>;;
Asciz	Signature;
Asciz	a;
Asciz	Lscala/actors/Reactor;;
Asciz	orElse;
Asciz	(Lscala/PartialFunction;)Lscala/PartialFunction;;
Asciz	Code;
Asciz	LineNumberTable;
Asciz	scala/PartialFunction$class;
class	scala/PartialFunction$class
Asciz	(Lscala/PartialFunction;Lscala/PartialFunction;)Lscala/PartialFunction;;
NameAndType	orElse:(Lscala/PartialFunction;Lscala/PartialFunction;)Lscala/PartialFunction;
Method	scala/PartialFunction$class.orElse:(Lscala/PartialFunction;Lscala/PartialFunction;)Lscala/PartialFunction;
Asciz	this;
Asciz	Lscala/actors/Actor$RecursiveProxyHandler;;
Asciz	that;
Asciz	LocalVariableTable;
Asciz	andThen;
Asciz	(Lscala/Function1;)Lscala/PartialFunction;;
Asciz	(Lscala/PartialFunction;Lscala/Function1;)Lscala/PartialFunction;;
NameAndType	andThen:(Lscala/PartialFunction;Lscala/Function1;)Lscala/PartialFunction;
Method	scala/PartialFunction$class.andThen:(Lscala/PartialFunction;Lscala/Function1;)Lscala/PartialFunction;
Asciz	k;
Asciz	Lscala/Function1;;
Asciz	lift;
Asciz	()Lscala/Function1;;
Asciz	(Lscala/PartialFunction;)Lscala/Function1;;
NameAndType	lift:(Lscala/PartialFunction;)Lscala/Function1;
Method	scala/PartialFunction$class.lift:(Lscala/PartialFunction;)Lscala/Function1;
Asciz	toString;
Asciz	()Ljava/lang/String;;
Asciz	scala/Function1$class;
class	scala/Function1$class
Asciz	(Lscala/Function1;)Ljava/lang/String;;
NameAndType	toString:(Lscala/Function1;)Ljava/lang/String;
Method	scala/Function1$class.toString:(Lscala/Function1;)Ljava/lang/String;
Asciz	compose;
Asciz	(Lscala/Function1;)Lscala/Function1;;
Asciz	(Lscala/Function1;Lscala/Function1;)Lscala/Function1;;
NameAndType	compose:(Lscala/Function1;Lscala/Function1;)Lscala/Function1;
Method	scala/Function1$class.compose:(Lscala/Function1;Lscala/Function1;)Lscala/Function1;
Asciz	g;
Asciz	isDefinedAt;
Asciz	(Ljava/lang/Object;)Z;
Asciz	m;
Asciz	Ljava/lang/Object;;
Asciz	apply;
Asciz	(Ljava/lang/Object;)V;
Asciz	scala/actors/Actor$RecursiveProxyHandler;
class	scala/actors/Actor$RecursiveProxyHandler
NameAndType	f:Lscala/PartialFunction;
Field	scala/actors/Actor$RecursiveProxyHandler.f:Lscala/PartialFunction;
Asciz	scala/PartialFunction;
class	scala/PartialFunction
NameAndType	isDefinedAt:(Ljava/lang/Object;)Z
InterfaceMethod	scala/PartialFunction.isDefinedAt:(Ljava/lang/Object;)Z
Asciz	scala/Function1;
class	scala/Function1
Asciz	(Ljava/lang/Object;)Ljava/lang/Object;;
NameAndType	apply:(Ljava/lang/Object;)Ljava/lang/Object;
InterfaceMethod	scala/Function1.apply:(Ljava/lang/Object;)Ljava/lang/Object;
Asciz	scala/runtime/BoxedUnit;
class	scala/runtime/BoxedUnit
Asciz	UNIT;
Asciz	Lscala/runtime/BoxedUnit;;
NameAndType	UNIT:Lscala/runtime/BoxedUnit;
Field	scala/runtime/BoxedUnit.UNIT:Lscala/runtime/BoxedUnit;
NameAndType	a:Lscala/actors/Reactor;
Field	scala/actors/Actor$RecursiveProxyHandler.a:Lscala/actors/Reactor;
Asciz	scala/actors/Reactor;
class	scala/actors/Reactor
Asciz	react;
Asciz	(Lscala/PartialFunction;)Lscala/runtime/Nothing$;;
NameAndType	react:(Lscala/PartialFunction;)Lscala/runtime/Nothing$;
InterfaceMethod	scala/actors/Reactor.react:(Lscala/PartialFunction;)Lscala/runtime/Nothing$;
NameAndType	andThen:(Lscala/Function1;)Lscala/PartialFunction;
InterfaceMethod	scala/PartialFunction.andThen:(Lscala/Function1;)Lscala/PartialFunction;
NameAndType	apply:(Ljava/lang/Object;)V
Method	scala/actors/Actor$RecursiveProxyHandler.apply:(Ljava/lang/Object;)V
Asciz	v1;
Asciz	<init>;
Asciz	(Lscala/actors/Reactor;Lscala/PartialFunction;)V;
Asciz	java/lang/Object;
class	java/lang/Object
Asciz	()V;
NameAndType	"<init>":()V
Method	java/lang/Object."<init>":()V
Asciz	$init$;
Asciz	(Lscala/Function1;)V;
NameAndType	$init$:(Lscala/Function1;)V
Method	scala/Function1$class.$init$:(Lscala/Function1;)V
Asciz	(Lscala/PartialFunction;)V;
NameAndType	$init$:(Lscala/PartialFunction;)V
Method	scala/PartialFunction$class.$init$:(Lscala/PartialFunction;)V
Asciz	(Lscala/actors/Reactor;Lscala/PartialFunction<Ljava/lang/Object;Ljava/lang/Object;>;)V;
Asciz	Ljava/lang/Object;Lscala/PartialFunction<Ljava/lang/Object;Ljava/lang/Object;>;Lscala/ScalaObject;;
Asciz	Scala;
Asciz	InnerClasses;
Asciz	scala/actors/Actor;
class	scala/actors/Actor
Asciz	RecursiveProxyHandler;
Asciz	scala/ScalaObject;
class	scala/ScalaObject

{
private final scala.PartialFunction f;
  Signature: Lscala/PartialFunction;
  Signature: length = 0x2
   00 05 

private final scala.actors.Reactor a;
  Signature: Lscala/actors/Reactor;

public scala.PartialFunction orElse(scala.PartialFunction);
  Signature: (Lscala/PartialFunction;)Lscala/PartialFunction;
  Code:
   Stack=2, Locals=2, Args_size=2
	aload_0
	aload_1
	invokestatic	Method scala/PartialFunction$class.orElse:(Lscala/PartialFunction;Lscala/PartialFunction;)Lscala/PartialFunction;
	areturn
  Labels:
  LocalVariableTable: 
   Start  Length  Slot  Name   Signature
   0      6      0    this       Lscala/actors/Actor$RecursiveProxyHandler;
   0      6      1    that       Lscala/PartialFunction;


public scala.PartialFunction andThen(scala.Function1);
  Signature: (Lscala/Function1;)Lscala/PartialFunction;
  Code:
   Stack=2, Locals=2, Args_size=2
	aload_0
	aload_1
	invokestatic	Method scala/PartialFunction$class.andThen:(Lscala/PartialFunction;Lscala/Function1;)Lscala/PartialFunction;
	areturn
  Labels:
  LocalVariableTable: 
   Start  Length  Slot  Name   Signature
   0      6      0    this       Lscala/actors/Actor$RecursiveProxyHandler;
   0      6      1    k       Lscala/Function1;


public scala.Function1 lift();
  Signature: ()Lscala/Function1;
  Code:
   Stack=1, Locals=1, Args_size=1
	aload_0
	invokestatic	Method scala/PartialFunction$class.lift:(Lscala/PartialFunction;)Lscala/Function1;
	areturn
  Labels:

public java.lang.String toString();
  Signature: ()Ljava/lang/String;
  Code:
   Stack=1, Locals=1, Args_size=1
	aload_0
	invokestatic	Method scala/Function1$class.toString:(Lscala/Function1;)Ljava/lang/String;
	areturn
  Labels:

public scala.Function1 compose(scala.Function1);
  Signature: (Lscala/Function1;)Lscala/Function1;
  Code:
   Stack=2, Locals=2, Args_size=2
	aload_0
	aload_1
	invokestatic	Method scala/Function1$class.compose:(Lscala/Function1;Lscala/Function1;)Lscala/Function1;
	areturn
  Labels:
  LocalVariableTable: 
   Start  Length  Slot  Name   Signature
   0      6      0    this       Lscala/actors/Actor$RecursiveProxyHandler;
   0      6      1    g       Lscala/Function1;


public boolean isDefinedAt(java.lang.Object);
  Signature: (Ljava/lang/Object;)Z
  Code:
   Stack=1, Locals=2, Args_size=2
	iconst_1
	ireturn
  Labels:
  LocalVariableTable: 
   Start  Length  Slot  Name   Signature
   0      2      0    this       Lscala/actors/Actor$RecursiveProxyHandler;
   0      2      1    m       Ljava/lang/Object;


public void apply(java.lang.Object);
  Signature: (Ljava/lang/Object;)V
  Code:
   Stack=2, Locals=2, Args_size=2
	aload_0
	getfield	Field f:Lscala/PartialFunction;
	aload_1
	invokeinterface	InterfaceMethod scala/PartialFunction.isDefinedAt:(Ljava/lang/Object;)Z
	ifeq	l1 // getstatic
	aload_0
	getfield	Field f:Lscala/PartialFunction;
	aload_1
	invokeinterface	InterfaceMethod scala/Function1.apply:(Ljava/lang/Object;)Ljava/lang/Object;
	goto	l2 // pop
l1	getstatic	Field scala/runtime/BoxedUnit.UNIT:Lscala/runtime/BoxedUnit;
l2	pop
	aload_0
	getfield	Field a:Lscala/actors/Reactor;
	aload_0
	invokeinterface	InterfaceMethod scala/actors/Reactor.react:(Lscala/PartialFunction;)Lscala/runtime/Nothing$;
	athrow
  Labels:
   	l1 = 26 // getstatic
   	l2 = 29 // pop
  LocalVariableTable: 
   Start  Length  Slot  Name   Signature
   0      41      0    this       Lscala/actors/Actor$RecursiveProxyHandler;
   0      41      1    m       Ljava/lang/Object;


public scala.Function1 andThen(scala.Function1);
  Signature: (Lscala/Function1;)Lscala/Function1;
  Code:
   Stack=2, Locals=2, Args_size=2
	aload_0
	aload_1
	invokeinterface	InterfaceMethod scala/PartialFunction.andThen:(Lscala/Function1;)Lscala/PartialFunction;
	areturn
  Labels:
  LocalVariableTable: 
   Start  Length  Slot  Name   Signature
   0      8      0    this       Lscala/actors/Actor$RecursiveProxyHandler;
   0      8      1    g       Lscala/Function1;


public java.lang.Object apply(java.lang.Object);
  Signature: (Ljava/lang/Object;)Ljava/lang/Object;
  Code:
   Stack=2, Locals=2, Args_size=2
	aload_0
	aload_1
	invokevirtual	Method apply:(Ljava/lang/Object;)V
	getstatic	Field scala/runtime/BoxedUnit.UNIT:Lscala/runtime/BoxedUnit;
	areturn
  Labels:
  LocalVariableTable: 
   Start  Length  Slot  Name   Signature
   0      9      0    this       Lscala/actors/Actor$RecursiveProxyHandler;
   0      9      1    v1       Ljava/lang/Object;


public scala.actors.Actor$RecursiveProxyHandler(scala.actors.Reactor, scala.PartialFunction);
  Signature: (Lscala/actors/Reactor;Lscala/PartialFunction;)V
  Code:
   Stack=2, Locals=3, Args_size=3
	aload_0
	aload_1
	putfield	Field a:Lscala/actors/Reactor;
	aload_0
	aload_2
	putfield	Field f:Lscala/PartialFunction;
	aload_0
	invokespecial	Method java/lang/Object."<init>":()V
	aload_0
	invokestatic	Method scala/Function1$class.$init$:(Lscala/Function1;)V
	aload_0
	invokestatic	Method scala/PartialFunction$class.$init$:(Lscala/PartialFunction;)V
	return
  Labels:
  LocalVariableTable: 
   Start  Length  Slot  Name   Signature
   0      23      0    this       Lscala/actors/Actor$RecursiveProxyHandler;
   0      23      1    a       Lscala/actors/Reactor;
   0      23      2    f       Lscala/PartialFunction;

  Signature: length = 0x2
   00 63 

}

