Compiled from "ActorGC.scala"
public abstract class scala.actors.ActorGC$class extends java.lang.Object
  SourceFile: "ActorGC.scala"
  Scala: length = 0x
   
  InnerClass: 
   public #237= #171 of #236; //ArrowAssoc=class scala/Predef$ArrowAssoc of class scala/Predef
   public final #238= #122 of #8; //$anonfun$terminated$1=class scala/actors/ActorGC$$anonfun$terminated$1 of class scala/actors/ActorGC
  minor version: 0
  major version: 49
  Constant pool:
const #1 = Asciz	SourceFile;
const #2 = Asciz	ActorGC.scala;
const #3 = Asciz	$init$;
const #4 = Asciz	(Lscala/actors/ActorGC;)V;
const #5 = Asciz	Code;
const #6 = Asciz	LineNumberTable;
const #7 = Asciz	scala/actors/ActorGC;
const #8 = class	#7;	//  scala/actors/ActorGC
const #9 = Asciz	scala$actors$ActorGC$$pendingReactions_$eq;
const #10 = Asciz	(I)V;
const #11 = NameAndType	#9:#10;//  scala$actors$ActorGC$$pendingReactions_$eq:(I)V
const #12 = InterfaceMethod	#8.#11;	//  scala/actors/ActorGC.scala$actors$ActorGC$$pendingReactions_$eq:(I)V
const #13 = Asciz	scala/collection/mutable/HashMap;
const #14 = class	#13;	//  scala/collection/mutable/HashMap
const #15 = Asciz	<init>;
const #16 = Asciz	()V;
const #17 = NameAndType	#15:#16;//  "<init>":()V
const #18 = Method	#14.#17;	//  scala/collection/mutable/HashMap."<init>":()V
const #19 = Asciz	scala$actors$ActorGC$_setter_$scala$actors$ActorGC$$termHandlers_$eq;
const #20 = Asciz	(Lscala/collection/mutable/HashMap;)V;
const #21 = NameAndType	#19:#20;//  scala$actors$ActorGC$_setter_$scala$actors$ActorGC$$termHandlers_$eq:(Lscala/collection/mutable/HashMap;)V
const #22 = InterfaceMethod	#8.#21;	//  scala/actors/ActorGC.scala$actors$ActorGC$_setter_$scala$actors$ActorGC$$termHandlers_$eq:(Lscala/collection/mutable/HashMap;)V
const #23 = Asciz	java/lang/ref/ReferenceQueue;
const #24 = class	#23;	//  java/lang/ref/ReferenceQueue
const #25 = Method	#24.#17;	//  java/lang/ref/ReferenceQueue."<init>":()V
const #26 = Asciz	scala$actors$ActorGC$_setter_$scala$actors$ActorGC$$refQ_$eq;
const #27 = Asciz	(Ljava/lang/ref/ReferenceQueue;)V;
const #28 = NameAndType	#26:#27;//  scala$actors$ActorGC$_setter_$scala$actors$ActorGC$$refQ_$eq:(Ljava/lang/ref/ReferenceQueue;)V
const #29 = InterfaceMethod	#8.#28;	//  scala/actors/ActorGC.scala$actors$ActorGC$_setter_$scala$actors$ActorGC$$refQ_$eq:(Ljava/lang/ref/ReferenceQueue;)V
const #30 = Asciz	scala/collection/mutable/HashSet;
const #31 = class	#30;	//  scala/collection/mutable/HashSet
const #32 = Method	#31.#17;	//  scala/collection/mutable/HashSet."<init>":()V
const #33 = Asciz	scala$actors$ActorGC$_setter_$scala$actors$ActorGC$$refSet_$eq;
const #34 = Asciz	(Lscala/collection/mutable/HashSet;)V;
const #35 = NameAndType	#33:#34;//  scala$actors$ActorGC$_setter_$scala$actors$ActorGC$$refSet_$eq:(Lscala/collection/mutable/HashSet;)V
const #36 = InterfaceMethod	#8.#35;	//  scala/actors/ActorGC.scala$actors$ActorGC$_setter_$scala$actors$ActorGC$$refSet_$eq:(Lscala/collection/mutable/HashSet;)V
const #37 = Asciz	$this;
const #38 = Asciz	Lscala/actors/ActorGC;;
const #39 = Asciz	LocalVariableTable;
const #40 = Asciz	drainRefQ$1;
const #41 = Asciz	scala$actors$ActorGC$$refQ;
const #42 = Asciz	()Ljava/lang/ref/ReferenceQueue;;
const #43 = NameAndType	#41:#42;//  scala$actors$ActorGC$$refQ:()Ljava/lang/ref/ReferenceQueue;
const #44 = InterfaceMethod	#8.#43;	//  scala/actors/ActorGC.scala$actors$ActorGC$$refQ:()Ljava/lang/ref/ReferenceQueue;
const #45 = Asciz	poll;
const #46 = Asciz	()Ljava/lang/ref/Reference;;
const #47 = NameAndType	#45:#46;//  poll:()Ljava/lang/ref/Reference;
const #48 = Method	#24.#47;	//  java/lang/ref/ReferenceQueue.poll:()Ljava/lang/ref/Reference;
const #49 = Asciz	java/lang/Object;
const #50 = class	#49;	//  java/lang/Object
const #51 = Asciz	equals;
const #52 = Asciz	(Ljava/lang/Object;)Z;
const #53 = NameAndType	#51:#52;//  equals:(Ljava/lang/Object;)Z
const #54 = Method	#50.#53;	//  java/lang/Object.equals:(Ljava/lang/Object;)Z
const #55 = Asciz	scala$actors$ActorGC$$pendingReactions;
const #56 = Asciz	()I;
const #57 = NameAndType	#55:#56;//  scala$actors$ActorGC$$pendingReactions:()I
const #58 = InterfaceMethod	#8.#57;	//  scala/actors/ActorGC.scala$actors$ActorGC$$pendingReactions:()I
const #59 = Asciz	scala$actors$ActorGC$$refSet;
const #60 = Asciz	()Lscala/collection/mutable/HashSet;;
const #61 = NameAndType	#59:#60;//  scala$actors$ActorGC$$refSet:()Lscala/collection/mutable/HashSet;
const #62 = InterfaceMethod	#8.#61;	//  scala/actors/ActorGC.scala$actors$ActorGC$$refSet:()Lscala/collection/mutable/HashSet;
const #63 = Asciz	$minus$eq;
const #64 = Asciz	(Ljava/lang/Object;)Lscala/collection/mutable/HashSet;;
const #65 = NameAndType	#63:#64;//  $minus$eq:(Ljava/lang/Object;)Lscala/collection/mutable/HashSet;
const #66 = Method	#31.#65;	//  scala/collection/mutable/HashSet.$minus$eq:(Ljava/lang/Object;)Lscala/collection/mutable/HashSet;
const #67 = Asciz	wr;
const #68 = Asciz	Ljava/lang/ref/Reference;;
const #69 = Asciz	setPendingCount;
const #70 = Asciz	(Lscala/actors/ActorGC;I)V;
const #71 = Asciz	scala/runtime/BoxedUnit;
const #72 = class	#71;	//  scala/runtime/BoxedUnit
const #73 = Asciz	UNIT;
const #74 = Asciz	Lscala/runtime/BoxedUnit;;
const #75 = NameAndType	#73:#74;//  UNIT:Lscala/runtime/BoxedUnit;
const #76 = Field	#72.#75;	//  scala/runtime/BoxedUnit.UNIT:Lscala/runtime/BoxedUnit;
const #77 = Asciz	cnt;
const #78 = Asciz	I;
const #79 = Asciz	getPendingCount;
const #80 = Asciz	(Lscala/actors/ActorGC;)I;
const #81 = Asciz	scala/runtime/BoxesRunTime;
const #82 = class	#81;	//  scala/runtime/BoxesRunTime
const #83 = Asciz	boxToInteger;
const #84 = Asciz	(I)Ljava/lang/Integer;;
const #85 = NameAndType	#83:#84;//  boxToInteger:(I)Ljava/lang/Integer;
const #86 = Method	#82.#85;	//  scala/runtime/BoxesRunTime.boxToInteger:(I)Ljava/lang/Integer;
const #87 = Asciz	unboxToInt;
const #88 = Asciz	(Ljava/lang/Object;)I;
const #89 = NameAndType	#87:#88;//  unboxToInt:(Ljava/lang/Object;)I
const #90 = Method	#82.#89;	//  scala/runtime/BoxesRunTime.unboxToInt:(Ljava/lang/Object;)I
const #91 = Asciz	terminated;
const #92 = Asciz	(Lscala/actors/ActorGC;Lscala/actors/Reactor;)V;
const #93 = Asciz	scala$actors$ActorGC$$termHandlers;
const #94 = Asciz	()Lscala/collection/mutable/HashMap;;
const #95 = NameAndType	#93:#94;//  scala$actors$ActorGC$$termHandlers:()Lscala/collection/mutable/HashMap;
const #96 = InterfaceMethod	#8.#95;	//  scala/actors/ActorGC.scala$actors$ActorGC$$termHandlers:()Lscala/collection/mutable/HashMap;
const #97 = Asciz	get;
const #98 = Asciz	(Ljava/lang/Object;)Lscala/Option;;
const #99 = NameAndType	#97:#98;//  get:(Ljava/lang/Object;)Lscala/Option;
const #100 = Method	#14.#99;	//  scala/collection/mutable/HashMap.get:(Ljava/lang/Object;)Lscala/Option;
const #101 = Asciz	scala/Some;
const #102 = class	#101;	//  scala/Some
const #103 = Asciz	x;
const #104 = Asciz	()Ljava/lang/Object;;
const #105 = NameAndType	#103:#104;//  x:()Ljava/lang/Object;
const #106 = Method	#102.#105;	//  scala/Some.x:()Ljava/lang/Object;
const #107 = Asciz	scala/Function0;
const #108 = class	#107;	//  scala/Function0
const #109 = Asciz	apply;
const #110 = NameAndType	#109:#104;//  apply:()Ljava/lang/Object;
const #111 = InterfaceMethod	#108.#110;	//  scala/Function0.apply:()Ljava/lang/Object;
const #112 = Asciz	(Ljava/lang/Object;)Lscala/collection/mutable/HashMap;;
const #113 = NameAndType	#63:#112;//  $minus$eq:(Ljava/lang/Object;)Lscala/collection/mutable/HashMap;
const #114 = Method	#14.#113;	//  scala/collection/mutable/HashMap.$minus$eq:(Ljava/lang/Object;)Lscala/collection/mutable/HashMap;
const #115 = Asciz	scala/None$;
const #116 = class	#115;	//  scala/None$
const #117 = Asciz	MODULE$;
const #118 = Asciz	Lscala/None$;;
const #119 = NameAndType	#117:#118;//  MODULE$:Lscala/None$;
const #120 = Field	#116.#119;	//  scala/None$.MODULE$:Lscala/None$;
const #121 = Asciz	scala/actors/ActorGC$$anonfun$terminated$1;
const #122 = class	#121;	//  scala/actors/ActorGC$$anonfun$terminated$1
const #123 = NameAndType	#15:#92;//  "<init>":(Lscala/actors/ActorGC;Lscala/actors/Reactor;)V
const #124 = Method	#122.#123;	//  scala/actors/ActorGC$$anonfun$terminated$1."<init>":(Lscala/actors/ActorGC;Lscala/actors/Reactor;)V
const #125 = Asciz	scala/collection/generic/TraversableTemplate;
const #126 = class	#125;	//  scala/collection/generic/TraversableTemplate
const #127 = Asciz	find;
const #128 = Asciz	(Lscala/Function1;)Lscala/Option;;
const #129 = NameAndType	#127:#128;//  find:(Lscala/Function1;)Lscala/Option;
const #130 = InterfaceMethod	#126.#129;	//  scala/collection/generic/TraversableTemplate.find:(Lscala/Function1;)Lscala/Option;
const #131 = Asciz	java/lang/ref/Reference;
const #132 = class	#131;	//  java/lang/ref/Reference
const #133 = Asciz	clear;
const #134 = NameAndType	#133:#16;//  clear:()V
const #135 = Method	#132.#134;	//  java/lang/ref/Reference.clear:()V
const #136 = Asciz	scala/MatchError;
const #137 = class	#136;	//  scala/MatchError
const #138 = Asciz	scala/Option;
const #139 = class	#138;	//  scala/Option
const #140 = Asciz	toString;
const #141 = Asciz	()Ljava/lang/String;;
const #142 = NameAndType	#140:#141;//  toString:()Ljava/lang/String;
const #143 = Method	#139.#142;	//  scala/Option.toString:()Ljava/lang/String;
const #144 = Asciz	(Ljava/lang/String;)V;
const #145 = NameAndType	#15:#144;//  "<init>":(Ljava/lang/String;)V
const #146 = Method	#137.#145;	//  scala/MatchError."<init>":(Ljava/lang/String;)V
const #147 = Asciz	a$1;
const #148 = Asciz	Lscala/actors/Reactor;;
const #149 = Asciz	temp1;
const #150 = Asciz	Lscala/Option;;
const #151 = Asciz	temp2;
const #152 = Asciz	Lscala/Some;;
const #153 = Asciz	temp3;
const #154 = Asciz	Lscala/Function0;;
const #155 = Asciz	temp5;
const #156 = Asciz	temp6;
const #157 = Asciz	temp7;
const #158 = Asciz	r;
const #159 = Asciz	onTerminate;
const #160 = Asciz	(Lscala/actors/ActorGC;Lscala/actors/Reactor;Lscala/Function0;)V;
const #161 = Asciz	scala/Predef$;
const #162 = class	#161;	//  scala/Predef$
const #163 = Asciz	Lscala/Predef$;;
const #164 = NameAndType	#117:#163;//  MODULE$:Lscala/Predef$;
const #165 = Field	#162.#164;	//  scala/Predef$.MODULE$:Lscala/Predef$;
const #166 = Asciz	any2ArrowAssoc;
const #167 = Asciz	(Ljava/lang/Object;)Lscala/Predef$ArrowAssoc;;
const #168 = NameAndType	#166:#167;//  any2ArrowAssoc:(Ljava/lang/Object;)Lscala/Predef$ArrowAssoc;
const #169 = Method	#162.#168;	//  scala/Predef$.any2ArrowAssoc:(Ljava/lang/Object;)Lscala/Predef$ArrowAssoc;
const #170 = Asciz	scala/Predef$ArrowAssoc;
const #171 = class	#170;	//  scala/Predef$ArrowAssoc
const #172 = Asciz	$minus$greater;
const #173 = Asciz	(Ljava/lang/Object;)Lscala/Tuple2;;
const #174 = NameAndType	#172:#173;//  $minus$greater:(Ljava/lang/Object;)Lscala/Tuple2;
const #175 = Method	#171.#174;	//  scala/Predef$ArrowAssoc.$minus$greater:(Ljava/lang/Object;)Lscala/Tuple2;
const #176 = Asciz	$plus$eq;
const #177 = Asciz	(Lscala/Tuple2;)Lscala/collection/mutable/HashMap;;
const #178 = NameAndType	#176:#177;//  $plus$eq:(Lscala/Tuple2;)Lscala/collection/mutable/HashMap;
const #179 = Method	#14.#178;	//  scala/collection/mutable/HashMap.$plus$eq:(Lscala/Tuple2;)Lscala/collection/mutable/HashMap;
const #180 = Asciz	a;
const #181 = Asciz	f;
const #182 = Asciz	allTerminated;
const #183 = Asciz	(Lscala/actors/ActorGC;)Z;
const #184 = Asciz	boxToBoolean;
const #185 = Asciz	(Z)Ljava/lang/Boolean;;
const #186 = NameAndType	#184:#185;//  boxToBoolean:(Z)Ljava/lang/Boolean;
const #187 = Method	#82.#186;	//  scala/runtime/BoxesRunTime.boxToBoolean:(Z)Ljava/lang/Boolean;
const #188 = Asciz	unboxToBoolean;
const #189 = NameAndType	#188:#52;//  unboxToBoolean:(Ljava/lang/Object;)Z
const #190 = Method	#82.#189;	//  scala/runtime/BoxesRunTime.unboxToBoolean:(Ljava/lang/Object;)Z
const #191 = Asciz	status;
const #192 = Asciz	scala/collection/mutable/StringBuilder;
const #193 = class	#192;	//  scala/collection/mutable/StringBuilder
const #194 = Method	#193.#17;	//  scala/collection/mutable/StringBuilder."<init>":()V
const #195 = Asciz	any2stringadd;
const #196 = Asciz	(Ljava/lang/Object;)Lscala/runtime/StringAdd;;
const #197 = NameAndType	#195:#196;//  any2stringadd:(Ljava/lang/Object;)Lscala/runtime/StringAdd;
const #198 = Method	#162.#197;	//  scala/Predef$.any2stringadd:(Ljava/lang/Object;)Lscala/runtime/StringAdd;
const #199 = Asciz	: size of refSet: ;
const #200 = String	#199;	//  : size of refSet: 
const #201 = Asciz	scala/runtime/StringAdd;
const #202 = class	#201;	//  scala/runtime/StringAdd
const #203 = Asciz	$plus;
const #204 = Asciz	(Ljava/lang/String;)Ljava/lang/String;;
const #205 = NameAndType	#203:#204;//  $plus:(Ljava/lang/String;)Ljava/lang/String;
const #206 = Method	#202.#205;	//  scala/runtime/StringAdd.$plus:(Ljava/lang/String;)Ljava/lang/String;
const #207 = Asciz	append;
const #208 = Asciz	(Ljava/lang/Object;)Lscala/collection/mutable/StringBuilder;;
const #209 = NameAndType	#207:#208;//  append:(Ljava/lang/Object;)Lscala/collection/mutable/StringBuilder;
const #210 = Method	#193.#209;	//  scala/collection/mutable/StringBuilder.append:(Ljava/lang/Object;)Lscala/collection/mutable/StringBuilder;
const #211 = Asciz	size;
const #212 = NameAndType	#211:#56;//  size:()I
const #213 = Method	#31.#212;	//  scala/collection/mutable/HashSet.size:()I
const #214 = Method	#193.#142;	//  scala/collection/mutable/StringBuilder.toString:()Ljava/lang/String;
const #215 = Asciz	println;
const #216 = Asciz	(Ljava/lang/Object;)V;
const #217 = NameAndType	#215:#216;//  println:(Ljava/lang/Object;)V
const #218 = Method	#162.#217;	//  scala/Predef$.println:(Ljava/lang/Object;)V
const #219 = Asciz	gc;
const #220 = Asciz	scala/actors/ActorGC$class;
const #221 = class	#220;	//  scala/actors/ActorGC$class
const #222 = NameAndType	#40:#4;//  drainRefQ$1:(Lscala/actors/ActorGC;)V
const #223 = Method	#221.#222;	//  scala/actors/ActorGC$class.drainRefQ$1:(Lscala/actors/ActorGC;)V
const #224 = Asciz	newActor;
const #225 = Asciz	java/lang/ref/WeakReference;
const #226 = class	#225;	//  java/lang/ref/WeakReference
const #227 = Asciz	(Ljava/lang/Object;Ljava/lang/ref/ReferenceQueue;)V;
const #228 = NameAndType	#15:#227;//  "<init>":(Ljava/lang/Object;Ljava/lang/ref/ReferenceQueue;)V
const #229 = Method	#226.#228;	//  java/lang/ref/WeakReference."<init>":(Ljava/lang/Object;Ljava/lang/ref/ReferenceQueue;)V
const #230 = NameAndType	#176:#64;//  $plus$eq:(Ljava/lang/Object;)Lscala/collection/mutable/HashSet;
const #231 = Method	#31.#230;	//  scala/collection/mutable/HashSet.$plus$eq:(Ljava/lang/Object;)Lscala/collection/mutable/HashSet;
const #232 = Asciz	Ljava/lang/ref/WeakReference;;
const #233 = Asciz	Scala;
const #234 = Asciz	InnerClasses;
const #235 = Asciz	scala/Predef;
const #236 = class	#235;	//  scala/Predef
const #237 = Asciz	ArrowAssoc;
const #238 = Asciz	$anonfun$terminated$1;

{
public static void $init$(scala.actors.ActorGC);
  Code:
   Stack=3, Locals=1, Args_size=1
   0:	aload_0
   1:	iconst_0
   2:	invokeinterface	#12,  2; //InterfaceMethod scala/actors/ActorGC.scala$actors$ActorGC$$pendingReactions_$eq:(I)V
   7:	aload_0
   8:	new	#14; //class scala/collection/mutable/HashMap
   11:	dup
   12:	invokespecial	#18; //Method scala/collection/mutable/HashMap."<init>":()V
   15:	invokeinterface	#22,  2; //InterfaceMethod scala/actors/ActorGC.scala$actors$ActorGC$_setter_$scala$actors$ActorGC$$termHandlers_$eq:(Lscala/collection/mutable/HashMap;)V
   20:	aload_0
   21:	new	#24; //class java/lang/ref/ReferenceQueue
   24:	dup
   25:	invokespecial	#25; //Method java/lang/ref/ReferenceQueue."<init>":()V
   28:	invokeinterface	#29,  2; //InterfaceMethod scala/actors/ActorGC.scala$actors$ActorGC$_setter_$scala$actors$ActorGC$$refQ_$eq:(Ljava/lang/ref/ReferenceQueue;)V
   33:	aload_0
   34:	new	#31; //class scala/collection/mutable/HashSet
   37:	dup
   38:	invokespecial	#32; //Method scala/collection/mutable/HashSet."<init>":()V
   41:	invokeinterface	#36,  2; //InterfaceMethod scala/actors/ActorGC.scala$actors$ActorGC$_setter_$scala$actors$ActorGC$$refSet_$eq:(Lscala/collection/mutable/HashSet;)V
   46:	return
  LineNumberTable: 
   line 29: 0
   line 30: 7
   line 33: 20
   line 40: 33

  LocalVariableTable: 
   Start  Length  Slot  Name   Signature
   0      47      0    $this       Lscala/actors/ActorGC;


public static void setPendingCount(scala.actors.ActorGC, int);
  Code:
   Stack=2, Locals=3, Args_size=2
   0:	aload_0
   1:	dup
   2:	astore_2
   3:	monitorenter
   4:	aload_0
   5:	iload_1
   6:	invokeinterface	#12,  2; //InterfaceMethod scala/actors/ActorGC.scala$actors$ActorGC$$pendingReactions_$eq:(I)V
   11:	getstatic	#76; //Field scala/runtime/BoxedUnit.UNIT:Lscala/runtime/BoxedUnit;
   14:	pop
   15:	aload_2
   16:	monitorexit
   17:	return
   18:	aload_2
   19:	monitorexit
   20:	athrow
  Exception table:
   from   to  target type
     4    17    18   any
  LineNumberTable: 
   line 107: 0
   line 108: 4
   line 107: 16

  LocalVariableTable: 
   Start  Length  Slot  Name   Signature
   0      21      0    $this       Lscala/actors/ActorGC;
   0      21      1    cnt       I


public static int getPendingCount(scala.actors.ActorGC);
  Code:
   Stack=2, Locals=2, Args_size=1
   0:	aload_0
   1:	dup
   2:	astore_1
   3:	monitorenter
   4:	aload_0
   5:	invokeinterface	#58,  1; //InterfaceMethod scala/actors/ActorGC.scala$actors$ActorGC$$pendingReactions:()I
   10:	invokestatic	#86; //Method scala/runtime/BoxesRunTime.boxToInteger:(I)Ljava/lang/Integer;
   13:	aload_1
   14:	monitorexit
   15:	invokestatic	#90; //Method scala/runtime/BoxesRunTime.unboxToInt:(Ljava/lang/Object;)I
   18:	ireturn
   19:	aload_1
   20:	monitorexit
   21:	athrow
  Exception table:
   from   to  target type
     4    15    19   any
  LineNumberTable: 
   line 103: 0
   line 104: 4
   line 103: 14

  LocalVariableTable: 
   Start  Length  Slot  Name   Signature
   0      22      0    $this       Lscala/actors/ActorGC;


public static void terminated(scala.actors.ActorGC, scala.actors.Reactor);
  Code:
   Stack=5, Locals=12, Args_size=2
   0:	aload_0
   1:	dup
   2:	astore_2
   3:	monitorenter
   4:	aload_0
   5:	invokeinterface	#96,  1; //InterfaceMethod scala/actors/ActorGC.scala$actors$ActorGC$$termHandlers:()Lscala/collection/mutable/HashMap;
   10:	aload_1
   11:	invokevirtual	#100; //Method scala/collection/mutable/HashMap.get:(Ljava/lang/Object;)Lscala/Option;
   14:	astore_3
   15:	aload_3
   16:	instanceof	#102; //class scala/Some
   19:	ifeq	59
   22:	aload_3
   23:	checkcast	#102; //class scala/Some
   26:	astore	4
   28:	aload	4
   30:	invokevirtual	#106; //Method scala/Some.x:()Ljava/lang/Object;
   33:	checkcast	#108; //class scala/Function0
   36:	astore	5
   38:	aload	5
   40:	invokeinterface	#111,  1; //InterfaceMethod scala/Function0.apply:()Ljava/lang/Object;
   45:	pop
   46:	aload_0
   47:	invokeinterface	#96,  1; //InterfaceMethod scala/actors/ActorGC.scala$actors$ActorGC$$termHandlers:()Lscala/collection/mutable/HashMap;
   52:	aload_1
   53:	invokevirtual	#114; //Method scala/collection/mutable/HashMap.$minus$eq:(Ljava/lang/Object;)Lscala/collection/mutable/HashMap;
   56:	goto	96
   59:	getstatic	#120; //Field scala/None$.MODULE$:Lscala/None$;
   62:	aload_3
   63:	astore	6
   65:	dup
   66:	ifnonnull	78
   69:	pop
   70:	aload	6
   72:	ifnull	86
   75:	goto	241
   78:	aload	6
   80:	invokevirtual	#54; //Method java/lang/Object.equals:(Ljava/lang/Object;)Z
   83:	ifeq	241
   86:	aload_3
   87:	instanceof	#116; //class scala/None$
   90:	ifeq	241
   93:	getstatic	#76; //Field scala/runtime/BoxedUnit.UNIT:Lscala/runtime/BoxedUnit;
   96:	pop
   97:	aload_0
   98:	invokeinterface	#62,  1; //InterfaceMethod scala/actors/ActorGC.scala$actors$ActorGC$$refSet:()Lscala/collection/mutable/HashSet;
   103:	new	#122; //class scala/actors/ActorGC$$anonfun$terminated$1
   106:	dup
   107:	aload_0
   108:	aload_1
   109:	invokespecial	#124; //Method scala/actors/ActorGC$$anonfun$terminated$1."<init>":(Lscala/actors/ActorGC;Lscala/actors/Reactor;)V
   112:	invokeinterface	#130,  2; //InterfaceMethod scala/collection/generic/TraversableTemplate.find:(Lscala/Function1;)Lscala/Option;
   117:	astore	7
   119:	aload	7
   121:	instanceof	#102; //class scala/Some
   124:	ifeq	167
   127:	aload	7
   129:	checkcast	#102; //class scala/Some
   132:	astore	8
   134:	aload	8
   136:	invokevirtual	#106; //Method scala/Some.x:()Ljava/lang/Object;
   139:	checkcast	#132; //class java/lang/ref/Reference
   142:	astore	9
   144:	aload	9
   146:	astore	10
   148:	aload	10
   150:	invokevirtual	#135; //Method java/lang/ref/Reference.clear:()V
   153:	aload_0
   154:	invokeinterface	#62,  1; //InterfaceMethod scala/actors/ActorGC.scala$actors$ActorGC$$refSet:()Lscala/collection/mutable/HashSet;
   159:	aload	10
   161:	invokevirtual	#66; //Method scala/collection/mutable/HashSet.$minus$eq:(Ljava/lang/Object;)Lscala/collection/mutable/HashSet;
   164:	goto	206
   167:	getstatic	#120; //Field scala/None$.MODULE$:Lscala/None$;
   170:	aload	7
   172:	astore	11
   174:	dup
   175:	ifnonnull	187
   178:	pop
   179:	aload	11
   181:	ifnull	195
   184:	goto	228
   187:	aload	11
   189:	invokevirtual	#54; //Method java/lang/Object.equals:(Ljava/lang/Object;)Z
   192:	ifeq	228
   195:	aload	7
   197:	instanceof	#116; //class scala/None$
   200:	ifeq	228
   203:	getstatic	#76; //Field scala/runtime/BoxedUnit.UNIT:Lscala/runtime/BoxedUnit;
   206:	pop
   207:	aload_0
   208:	aload_0
   209:	invokeinterface	#58,  1; //InterfaceMethod scala/actors/ActorGC.scala$actors$ActorGC$$pendingReactions:()I
   214:	iconst_1
   215:	isub
   216:	invokeinterface	#12,  2; //InterfaceMethod scala/actors/ActorGC.scala$actors$ActorGC$$pendingReactions_$eq:(I)V
   221:	getstatic	#76; //Field scala/runtime/BoxedUnit.UNIT:Lscala/runtime/BoxedUnit;
   224:	pop
   225:	aload_2
   226:	monitorexit
   227:	return
   228:	new	#137; //class scala/MatchError
   231:	dup
   232:	aload	7
   234:	invokevirtual	#143; //Method scala/Option.toString:()Ljava/lang/String;
   237:	invokespecial	#146; //Method scala/MatchError."<init>":(Ljava/lang/String;)V
   240:	athrow
   241:	new	#137; //class scala/MatchError
   244:	dup
   245:	aload_3
   246:	invokevirtual	#143; //Method scala/Option.toString:()Ljava/lang/String;
   249:	invokespecial	#146; //Method scala/MatchError."<init>":(Ljava/lang/String;)V
   252:	athrow
   253:	aload_2
   254:	monitorexit
   255:	athrow
  Exception table:
   from   to  target type
     4   227   253   any
   228   253   253   any
  LineNumberTable: 
   line 79: 0
   line 81: 4
   line 82: 38
   line 83: 40
   line 85: 46
   line 81: 59
   line 91: 97
   line 92: 144
   line 94: 148
   line 95: 153
   line 91: 167
   line 100: 207
   line 79: 226
   line 91: 228
   line 81: 241
   line 79: 254

  LocalVariableTable: 
   Start  Length  Slot  Name   Signature
   0      256      0    $this       Lscala/actors/ActorGC;
   0      256      1    a$1       Lscala/actors/Reactor;
   15      82      3    temp1       Lscala/Option;
   241      12      3    temp1       Lscala/Option;
   28      28      4    temp2       Lscala/Some;
   38      18      5    temp3       Lscala/Function0;
   119      88      7    temp5       Lscala/Option;
   228      13      7    temp5       Lscala/Option;
   134      30      8    temp6       Lscala/Some;
   144      20      9    temp7       Ljava/lang/ref/Reference;
   148      16      10    r       Ljava/lang/ref/Reference;


public static void onTerminate(scala.actors.ActorGC, scala.actors.Reactor, scala.Function0);
  Code:
   Stack=3, Locals=4, Args_size=3
   0:	aload_0
   1:	dup
   2:	astore_3
   3:	monitorenter
   4:	aload_0
   5:	invokeinterface	#96,  1; //InterfaceMethod scala/actors/ActorGC.scala$actors$ActorGC$$termHandlers:()Lscala/collection/mutable/HashMap;
   10:	getstatic	#165; //Field scala/Predef$.MODULE$:Lscala/Predef$;
   13:	aload_1
   14:	invokevirtual	#169; //Method scala/Predef$.any2ArrowAssoc:(Ljava/lang/Object;)Lscala/Predef$ArrowAssoc;
   17:	aload_2
   18:	invokevirtual	#175; //Method scala/Predef$ArrowAssoc.$minus$greater:(Ljava/lang/Object;)Lscala/Tuple2;
   21:	invokevirtual	#179; //Method scala/collection/mutable/HashMap.$plus$eq:(Lscala/Tuple2;)Lscala/collection/mutable/HashMap;
   24:	pop
   25:	aload_3
   26:	monitorexit
   27:	return
   28:	aload_3
   29:	monitorexit
   30:	athrow
  Exception table:
   from   to  target type
     4    27    28   any
  LineNumberTable: 
   line 73: 0
   line 74: 4
   line 73: 26

  LocalVariableTable: 
   Start  Length  Slot  Name   Signature
   0      31      0    $this       Lscala/actors/ActorGC;
   0      31      1    a       Lscala/actors/Reactor;
   0      31      2    f       Lscala/Function0;


public static boolean allTerminated(scala.actors.ActorGC);
  Code:
   Stack=2, Locals=2, Args_size=1
   0:	aload_0
   1:	dup
   2:	astore_1
   3:	monitorenter
   4:	aload_0
   5:	invokeinterface	#58,  1; //InterfaceMethod scala/actors/ActorGC.scala$actors$ActorGC$$pendingReactions:()I
   10:	iconst_0
   11:	if_icmpgt	18
   14:	iconst_1
   15:	goto	19
   18:	iconst_0
   19:	invokestatic	#187; //Method scala/runtime/BoxesRunTime.boxToBoolean:(Z)Ljava/lang/Boolean;
   22:	aload_1
   23:	monitorexit
   24:	invokestatic	#190; //Method scala/runtime/BoxesRunTime.unboxToBoolean:(Ljava/lang/Object;)Z
   27:	ireturn
   28:	aload_1
   29:	monitorexit
   30:	athrow
  Exception table:
   from   to  target type
     4    24    28   any
  LineNumberTable: 
   line 69: 0
   line 70: 4
   line 69: 23

  LocalVariableTable: 
   Start  Length  Slot  Name   Signature
   0      31      0    $this       Lscala/actors/ActorGC;


public static void status(scala.actors.ActorGC);
  Code:
   Stack=4, Locals=1, Args_size=1
   0:	getstatic	#165; //Field scala/Predef$.MODULE$:Lscala/Predef$;
   3:	new	#193; //class scala/collection/mutable/StringBuilder
   6:	dup
   7:	invokespecial	#194; //Method scala/collection/mutable/StringBuilder."<init>":()V
   10:	getstatic	#165; //Field scala/Predef$.MODULE$:Lscala/Predef$;
   13:	aload_0
   14:	invokevirtual	#198; //Method scala/Predef$.any2stringadd:(Ljava/lang/Object;)Lscala/runtime/StringAdd;
   17:	ldc	#200; //String : size of refSet: 
   19:	invokevirtual	#206; //Method scala/runtime/StringAdd.$plus:(Ljava/lang/String;)Ljava/lang/String;
   22:	invokevirtual	#210; //Method scala/collection/mutable/StringBuilder.append:(Ljava/lang/Object;)Lscala/collection/mutable/StringBuilder;
   25:	aload_0
   26:	invokeinterface	#62,  1; //InterfaceMethod scala/actors/ActorGC.scala$actors$ActorGC$$refSet:()Lscala/collection/mutable/HashSet;
   31:	invokevirtual	#213; //Method scala/collection/mutable/HashSet.size:()I
   34:	invokestatic	#86; //Method scala/runtime/BoxesRunTime.boxToInteger:(I)Ljava/lang/Integer;
   37:	invokevirtual	#210; //Method scala/collection/mutable/StringBuilder.append:(Ljava/lang/Object;)Lscala/collection/mutable/StringBuilder;
   40:	invokevirtual	#214; //Method scala/collection/mutable/StringBuilder.toString:()Ljava/lang/String;
   43:	invokevirtual	#218; //Method scala/Predef$.println:(Ljava/lang/Object;)V
   46:	return
  LineNumberTable: 
   line 66: 0

  LocalVariableTable: 
   Start  Length  Slot  Name   Signature
   0      47      0    $this       Lscala/actors/ActorGC;


public static void gc(scala.actors.ActorGC);
  Code:
   Stack=2, Locals=2, Args_size=1
   0:	aload_0
   1:	dup
   2:	astore_1
   3:	monitorenter
   4:	aload_0
   5:	invokestatic	#223; //Method drainRefQ$1:(Lscala/actors/ActorGC;)V
   8:	getstatic	#76; //Field scala/runtime/BoxedUnit.UNIT:Lscala/runtime/BoxedUnit;
   11:	pop
   12:	aload_1
   13:	monitorexit
   14:	return
   15:	aload_1
   16:	monitorexit
   17:	athrow
  Exception table:
   from   to  target type
     4    14    15   any
  LineNumberTable: 
   line 51: 0
   line 62: 4
   line 51: 13

  LocalVariableTable: 
   Start  Length  Slot  Name   Signature
   0      18      0    $this       Lscala/actors/ActorGC;


public static void newActor(scala.actors.ActorGC, scala.actors.Reactor);
  Code:
   Stack=4, Locals=4, Args_size=2
   0:	aload_0
   1:	dup
   2:	astore_2
   3:	monitorenter
   4:	new	#226; //class java/lang/ref/WeakReference
   7:	dup
   8:	aload_1
   9:	aload_0
   10:	invokeinterface	#44,  1; //InterfaceMethod scala/actors/ActorGC.scala$actors$ActorGC$$refQ:()Ljava/lang/ref/ReferenceQueue;
   15:	invokespecial	#229; //Method java/lang/ref/WeakReference."<init>":(Ljava/lang/Object;Ljava/lang/ref/ReferenceQueue;)V
   18:	astore_3
   19:	aload_0
   20:	invokeinterface	#62,  1; //InterfaceMethod scala/actors/ActorGC.scala$actors$ActorGC$$refSet:()Lscala/collection/mutable/HashSet;
   25:	aload_3
   26:	invokevirtual	#231; //Method scala/collection/mutable/HashSet.$plus$eq:(Ljava/lang/Object;)Lscala/collection/mutable/HashSet;
   29:	pop
   30:	aload_0
   31:	aload_0
   32:	invokeinterface	#58,  1; //InterfaceMethod scala/actors/ActorGC.scala$actors$ActorGC$$pendingReactions:()I
   37:	iconst_1
   38:	iadd
   39:	invokeinterface	#12,  2; //InterfaceMethod scala/actors/ActorGC.scala$actors$ActorGC$$pendingReactions_$eq:(I)V
   44:	getstatic	#76; //Field scala/runtime/BoxedUnit.UNIT:Lscala/runtime/BoxedUnit;
   47:	pop
   48:	aload_2
   49:	monitorexit
   50:	return
   51:	aload_2
   52:	monitorexit
   53:	athrow
  Exception table:
   from   to  target type
     4    50    51   any
  LineNumberTable: 
   line 43: 0
   line 45: 4
   line 46: 19
   line 47: 30
   line 43: 49

  LocalVariableTable: 
   Start  Length  Slot  Name   Signature
   0      54      0    $this       Lscala/actors/ActorGC;
   0      54      1    a       Lscala/actors/Reactor;
   19      29      3    wr       Ljava/lang/ref/WeakReference;


}

