Compiled from "Actor.scala"
public final class scala.actors.Actor$$anonfun$1 extends java.lang.Object implements scala.Function2,scala.ScalaObject,java.io.Serializable
  SourceFile: "Actor.scala"
  Scala: length = 0x
   
  InnerClass: 
   public final #104= #9 of #103; //$anonfun$1=class scala/actors/Actor$$anonfun$1 of class scala/actors/Actor
  minor version: 0
  major version: 49
  Constant pool:
const #1 = Asciz	SourceFile;
const #2 = Asciz	Actor.scala;
const #3 = Asciz	<clinit>;
const #4 = Asciz	()V;
const #5 = Asciz	Code;
const #6 = Asciz	serialVersionUID;
const #7 = Asciz	J;
const #8 = Asciz	scala/actors/Actor$$anonfun$1;
const #9 = class	#8;	//  scala/actors/Actor$$anonfun$1
const #10 = NameAndType	#6:#7;//  serialVersionUID:J
const #11 = Field	#9.#10;	//  scala/actors/Actor$$anonfun$1.serialVersionUID:J
const #12 = Asciz	f$1;
const #13 = Asciz	Lscala/PartialFunction;;
const #14 = Asciz	$outer;
const #15 = Asciz	Lscala/actors/Actor;;
const #16 = Asciz	<init>;
const #17 = Asciz	(Lscala/actors/Actor;Lscala/PartialFunction;)V;
const #18 = Asciz	LineNumberTable;
const #19 = Asciz	java/lang/NullPointerException;
const #20 = class	#19;	//  java/lang/NullPointerException
const #21 = NameAndType	#16:#4;//  "<init>":()V
const #22 = Method	#20.#21;	//  java/lang/NullPointerException."<init>":()V
const #23 = NameAndType	#14:#15;//  $outer:Lscala/actors/Actor;
const #24 = Field	#9.#23;	//  scala/actors/Actor$$anonfun$1.$outer:Lscala/actors/Actor;
const #25 = NameAndType	#12:#13;//  f$1:Lscala/PartialFunction;
const #26 = Field	#9.#25;	//  scala/actors/Actor$$anonfun$1.f$1:Lscala/PartialFunction;
const #27 = Asciz	java/lang/Object;
const #28 = class	#27;	//  java/lang/Object
const #29 = Method	#28.#21;	//  java/lang/Object."<init>":()V
const #30 = Asciz	scala/Function2$class;
const #31 = class	#30;	//  scala/Function2$class
const #32 = Asciz	$init$;
const #33 = Asciz	(Lscala/Function2;)V;
const #34 = NameAndType	#32:#33;//  $init$:(Lscala/Function2;)V
const #35 = Method	#31.#34;	//  scala/Function2$class.$init$:(Lscala/Function2;)V
const #36 = Asciz	this;
const #37 = Asciz	Lscala/actors/Actor$$anonfun$1;;
const #38 = Asciz	LocalVariableTable;
const #39 = Asciz	apply;
const #40 = Asciz	(Ljava/lang/Object;Ljava/lang/Object;)Ljava/lang/Object;;
const #41 = Asciz	scala/actors/OutputChannel;
const #42 = class	#41;	//  scala/actors/OutputChannel
const #43 = Asciz	(Ljava/lang/Object;Lscala/actors/OutputChannel;)Z;
const #44 = NameAndType	#39:#43;//  apply:(Ljava/lang/Object;Lscala/actors/OutputChannel;)Z
const #45 = Method	#9.#44;	//  scala/actors/Actor$$anonfun$1.apply:(Ljava/lang/Object;Lscala/actors/OutputChannel;)Z
const #46 = Asciz	scala/runtime/BoxesRunTime;
const #47 = class	#46;	//  scala/runtime/BoxesRunTime
const #48 = Asciz	boxToBoolean;
const #49 = Asciz	(Z)Ljava/lang/Boolean;;
const #50 = NameAndType	#48:#49;//  boxToBoolean:(Z)Ljava/lang/Boolean;
const #51 = Method	#47.#50;	//  scala/runtime/BoxesRunTime.boxToBoolean:(Z)Ljava/lang/Boolean;
const #52 = Asciz	v1;
const #53 = Asciz	Ljava/lang/Object;;
const #54 = Asciz	v2;
const #55 = Asciz	scala/actors/ReplyReactor;
const #56 = class	#55;	//  scala/actors/ReplyReactor
const #57 = Asciz	senders;
const #58 = Asciz	()Lscala/collection/immutable/List;;
const #59 = NameAndType	#57:#58;//  senders:()Lscala/collection/immutable/List;
const #60 = InterfaceMethod	#56.#59;	//  scala/actors/ReplyReactor.senders:()Lscala/collection/immutable/List;
const #61 = Asciz	scala/collection/immutable/List;
const #62 = class	#61;	//  scala/collection/immutable/List
const #63 = Asciz	$colon$colon;
const #64 = Asciz	(Ljava/lang/Object;)Lscala/collection/immutable/List;;
const #65 = NameAndType	#63:#64;//  $colon$colon:(Ljava/lang/Object;)Lscala/collection/immutable/List;
const #66 = Method	#62.#65;	//  scala/collection/immutable/List.$colon$colon:(Ljava/lang/Object;)Lscala/collection/immutable/List;
const #67 = Asciz	senders_$eq;
const #68 = Asciz	(Lscala/collection/immutable/List;)V;
const #69 = NameAndType	#67:#68;//  senders_$eq:(Lscala/collection/immutable/List;)V
const #70 = InterfaceMethod	#56.#69;	//  scala/actors/ReplyReactor.senders_$eq:(Lscala/collection/immutable/List;)V
const #71 = Asciz	scala/PartialFunction;
const #72 = class	#71;	//  scala/PartialFunction
const #73 = Asciz	isDefinedAt;
const #74 = Asciz	(Ljava/lang/Object;)Z;
const #75 = NameAndType	#73:#74;//  isDefinedAt:(Ljava/lang/Object;)Z
const #76 = InterfaceMethod	#72.#75;	//  scala/PartialFunction.isDefinedAt:(Ljava/lang/Object;)Z
const #77 = Asciz	scala/collection/TraversableLike;
const #78 = class	#77;	//  scala/collection/TraversableLike
const #79 = Asciz	tail;
const #80 = Asciz	()Ljava/lang/Object;;
const #81 = NameAndType	#79:#80;//  tail:()Ljava/lang/Object;
const #82 = InterfaceMethod	#78.#81;	//  scala/collection/TraversableLike.tail:()Ljava/lang/Object;
const #83 = Asciz	m;
const #84 = Asciz	replyTo;
const #85 = Asciz	Lscala/actors/OutputChannel;;
const #86 = Asciz	matches;
const #87 = Asciz	Z;
const #88 = Asciz	(Ljava/lang/Object;Lscala/actors/OutputChannel<Ljava/lang/Object;>;)Z;
const #89 = Asciz	Signature;
const #90 = Asciz	curry;
const #91 = Asciz	()Lscala/Function1;;
const #92 = Asciz	(Lscala/Function2;)Lscala/Function1;;
const #93 = NameAndType	#90:#92;//  curry:(Lscala/Function2;)Lscala/Function1;
const #94 = Method	#31.#93;	//  scala/Function2$class.curry:(Lscala/Function2;)Lscala/Function1;
const #95 = Asciz	toString;
const #96 = Asciz	()Ljava/lang/String;;
const #97 = Asciz	(Lscala/Function2;)Ljava/lang/String;;
const #98 = NameAndType	#95:#97;//  toString:(Lscala/Function2;)Ljava/lang/String;
const #99 = Method	#31.#98;	//  scala/Function2$class.toString:(Lscala/Function2;)Ljava/lang/String;
const #100 = Asciz	Scala;
const #101 = Asciz	InnerClasses;
const #102 = Asciz	scala/actors/Actor;
const #103 = class	#102;	//  scala/actors/Actor
const #104 = Asciz	$anonfun$1;
const #105 = Asciz	scala/Function2;
const #106 = class	#105;	//  scala/Function2
const #107 = Asciz	scala/ScalaObject;
const #108 = class	#107;	//  scala/ScalaObject
const #109 = Asciz	java/io/Serializable;
const #110 = class	#109;	//  java/io/Serializable

{
public static final long serialVersionUID;

public static {};
  Code:
   Stack=2, Locals=0, Args_size=0
   0:	lconst_0
   1:	putstatic	#11; //Field serialVersionUID:J
   4:	return

public scala.actors.Actor$$anonfun$1(scala.actors.Actor, scala.PartialFunction);
  Code:
   Stack=2, Locals=3, Args_size=3
   0:	aload_1
   1:	ifnonnull	12
   4:	new	#20; //class java/lang/NullPointerException
   7:	dup
   8:	invokespecial	#22; //Method java/lang/NullPointerException."<init>":()V
   11:	athrow
   12:	aload_0
   13:	aload_1
   14:	putfield	#24; //Field $outer:Lscala/actors/Actor;
   17:	aload_0
   18:	aload_2
   19:	putfield	#26; //Field f$1:Lscala/PartialFunction;
   22:	aload_0
   23:	invokespecial	#29; //Method java/lang/Object."<init>":()V
   26:	aload_0
   27:	invokestatic	#35; //Method scala/Function2$class.$init$:(Lscala/Function2;)V
   30:	return
  LineNumberTable: 
   line 441: 0

  LocalVariableTable: 
   Start  Length  Slot  Name   Signature
   0      31      0    this       Lscala/actors/Actor$$anonfun$1;
   0      31      1    $outer       Lscala/actors/Actor;


public final java.lang.Object apply(java.lang.Object, java.lang.Object);
  Code:
   Stack=3, Locals=5, Args_size=3
   0:	aload_0
   1:	getfield	#24; //Field $outer:Lscala/actors/Actor;
   4:	astore	4
   6:	aload_0
   7:	aload_1
   8:	aload_2
   9:	checkcast	#42; //class scala/actors/OutputChannel
   12:	invokevirtual	#45; //Method apply:(Ljava/lang/Object;Lscala/actors/OutputChannel;)Z
   15:	istore_3
   16:	iload_3
   17:	invokestatic	#51; //Method scala/runtime/BoxesRunTime.boxToBoolean:(Z)Ljava/lang/Boolean;
   20:	areturn
  LineNumberTable: 
   line 441: 0

  LocalVariableTable: 
   Start  Length  Slot  Name   Signature
   0      21      0    this       Lscala/actors/Actor$$anonfun$1;
   6      15      1    v1       Ljava/lang/Object;
   6      15      2    v2       Ljava/lang/Object;


public final boolean apply(java.lang.Object, scala.actors.OutputChannel);
  Code:
   Stack=3, Locals=5, Args_size=3
   0:	aload_0
   1:	getfield	#24; //Field $outer:Lscala/actors/Actor;
   4:	astore	4
   6:	aload_0
   7:	getfield	#24; //Field $outer:Lscala/actors/Actor;
   10:	aload_0
   11:	getfield	#24; //Field $outer:Lscala/actors/Actor;
   14:	invokeinterface	#60,  1; //InterfaceMethod scala/actors/ReplyReactor.senders:()Lscala/collection/immutable/List;
   19:	aload_2
   20:	invokevirtual	#66; //Method scala/collection/immutable/List.$colon$colon:(Ljava/lang/Object;)Lscala/collection/immutable/List;
   23:	invokeinterface	#70,  2; //InterfaceMethod scala/actors/ReplyReactor.senders_$eq:(Lscala/collection/immutable/List;)V
   28:	aload_0
   29:	getfield	#26; //Field f$1:Lscala/PartialFunction;
   32:	aload_1
   33:	invokeinterface	#76,  2; //InterfaceMethod scala/PartialFunction.isDefinedAt:(Ljava/lang/Object;)Z
   38:	istore_3
   39:	aload_0
   40:	getfield	#24; //Field $outer:Lscala/actors/Actor;
   43:	aload_0
   44:	getfield	#24; //Field $outer:Lscala/actors/Actor;
   47:	invokeinterface	#60,  1; //InterfaceMethod scala/actors/ReplyReactor.senders:()Lscala/collection/immutable/List;
   52:	invokeinterface	#82,  1; //InterfaceMethod scala/collection/TraversableLike.tail:()Ljava/lang/Object;
   57:	checkcast	#62; //class scala/collection/immutable/List
   60:	invokeinterface	#70,  2; //InterfaceMethod scala/actors/ReplyReactor.senders_$eq:(Lscala/collection/immutable/List;)V
   65:	iload_3
   66:	ireturn
  LineNumberTable: 
   line 442: 0
   line 443: 28
   line 444: 39
   line 445: 65

  LocalVariableTable: 
   Start  Length  Slot  Name   Signature
   0      67      0    this       Lscala/actors/Actor$$anonfun$1;
   6      61      1    m       Ljava/lang/Object;
   6      61      2    replyTo       Lscala/actors/OutputChannel;
   39      27      3    matches       Z

  Signature: length = 0x2
   00 58 

public scala.Function1 curry();
  Code:
   Stack=1, Locals=1, Args_size=1
   0:	aload_0
   1:	invokestatic	#94; //Method scala/Function2$class.curry:(Lscala/Function2;)Lscala/Function1;
   4:	areturn
  LineNumberTable: 
   line 441: 0


public java.lang.String toString();
  Code:
   Stack=1, Locals=1, Args_size=1
   0:	aload_0
   1:	invokestatic	#99; //Method scala/Function2$class.toString:(Lscala/Function2;)Ljava/lang/String;
   4:	areturn
  LineNumberTable: 
   line 441: 0


}

