Compiled from "Actor.scala"
public final class scala.actors.Actor$$anonfun$1 extends java.lang.Object implements scala.Function2,scala.ScalaObject,java.io.Serializable
  SourceFile: "Actor.scala"
  Scala: length = 0x
   
  InnerClass: 
   public final $anonfun$1=class scala/actors/Actor$$anonfun$1 of class scala/actors/Actor
  minor version: 0
  major version: 49
  Constant pool:
Asciz	SourceFile;
Asciz	Actor.scala;
Asciz	<clinit>;
Asciz	()V;
Asciz	Code;
Asciz	serialVersionUID;
Asciz	J;
Asciz	scala/actors/Actor$$anonfun$1;
class	scala/actors/Actor$$anonfun$1
NameAndType	serialVersionUID:J
Field	scala/actors/Actor$$anonfun$1.serialVersionUID:J
Asciz	f$1;
Asciz	Lscala/PartialFunction;;
Asciz	$outer;
Asciz	Lscala/actors/Actor;;
Asciz	<init>;
Asciz	(Lscala/actors/Actor;Lscala/PartialFunction;)V;
Asciz	LineNumberTable;
Asciz	java/lang/NullPointerException;
class	java/lang/NullPointerException
NameAndType	"<init>":()V
Method	java/lang/NullPointerException."<init>":()V
NameAndType	$outer:Lscala/actors/Actor;
Field	scala/actors/Actor$$anonfun$1.$outer:Lscala/actors/Actor;
NameAndType	f$1:Lscala/PartialFunction;
Field	scala/actors/Actor$$anonfun$1.f$1:Lscala/PartialFunction;
Asciz	java/lang/Object;
class	java/lang/Object
Method	java/lang/Object."<init>":()V
Asciz	scala/Function2$class;
class	scala/Function2$class
Asciz	$init$;
Asciz	(Lscala/Function2;)V;
NameAndType	$init$:(Lscala/Function2;)V
Method	scala/Function2$class.$init$:(Lscala/Function2;)V
Asciz	this;
Asciz	Lscala/actors/Actor$$anonfun$1;;
Asciz	LocalVariableTable;
Asciz	apply;
Asciz	(Ljava/lang/Object;Ljava/lang/Object;)Ljava/lang/Object;;
Asciz	scala/actors/OutputChannel;
class	scala/actors/OutputChannel
Asciz	(Ljava/lang/Object;Lscala/actors/OutputChannel;)Z;
NameAndType	apply:(Ljava/lang/Object;Lscala/actors/OutputChannel;)Z
Method	scala/actors/Actor$$anonfun$1.apply:(Ljava/lang/Object;Lscala/actors/OutputChannel;)Z
Asciz	scala/runtime/BoxesRunTime;
class	scala/runtime/BoxesRunTime
Asciz	boxToBoolean;
Asciz	(Z)Ljava/lang/Boolean;;
NameAndType	boxToBoolean:(Z)Ljava/lang/Boolean;
Method	scala/runtime/BoxesRunTime.boxToBoolean:(Z)Ljava/lang/Boolean;
Asciz	v1;
Asciz	Ljava/lang/Object;;
Asciz	v2;
Asciz	scala/actors/ReplyReactor;
class	scala/actors/ReplyReactor
Asciz	senders;
Asciz	()Lscala/collection/immutable/List;;
NameAndType	senders:()Lscala/collection/immutable/List;
InterfaceMethod	scala/actors/ReplyReactor.senders:()Lscala/collection/immutable/List;
Asciz	scala/collection/immutable/List;
class	scala/collection/immutable/List
Asciz	$colon$colon;
Asciz	(Ljava/lang/Object;)Lscala/collection/immutable/List;;
NameAndType	$colon$colon:(Ljava/lang/Object;)Lscala/collection/immutable/List;
Method	scala/collection/immutable/List.$colon$colon:(Ljava/lang/Object;)Lscala/collection/immutable/List;
Asciz	senders_$eq;
Asciz	(Lscala/collection/immutable/List;)V;
NameAndType	senders_$eq:(Lscala/collection/immutable/List;)V
InterfaceMethod	scala/actors/ReplyReactor.senders_$eq:(Lscala/collection/immutable/List;)V
Asciz	scala/PartialFunction;
class	scala/PartialFunction
Asciz	isDefinedAt;
Asciz	(Ljava/lang/Object;)Z;
NameAndType	isDefinedAt:(Ljava/lang/Object;)Z
InterfaceMethod	scala/PartialFunction.isDefinedAt:(Ljava/lang/Object;)Z
Asciz	scala/collection/TraversableLike;
class	scala/collection/TraversableLike
Asciz	tail;
Asciz	()Ljava/lang/Object;;
NameAndType	tail:()Ljava/lang/Object;
InterfaceMethod	scala/collection/TraversableLike.tail:()Ljava/lang/Object;
Asciz	m;
Asciz	replyTo;
Asciz	Lscala/actors/OutputChannel;;
Asciz	matches;
Asciz	Z;
Asciz	(Ljava/lang/Object;Lscala/actors/OutputChannel<Ljava/lang/Object;>;)Z;
Asciz	Signature;
Asciz	curry;
Asciz	()Lscala/Function1;;
Asciz	(Lscala/Function2;)Lscala/Function1;;
NameAndType	curry:(Lscala/Function2;)Lscala/Function1;
Method	scala/Function2$class.curry:(Lscala/Function2;)Lscala/Function1;
Asciz	toString;
Asciz	()Ljava/lang/String;;
Asciz	(Lscala/Function2;)Ljava/lang/String;;
NameAndType	toString:(Lscala/Function2;)Ljava/lang/String;
Method	scala/Function2$class.toString:(Lscala/Function2;)Ljava/lang/String;
Asciz	Scala;
Asciz	InnerClasses;
Asciz	scala/actors/Actor;
class	scala/actors/Actor
Asciz	$anonfun$1;
Asciz	scala/Function2;
class	scala/Function2
Asciz	scala/ScalaObject;
class	scala/ScalaObject
Asciz	java/io/Serializable;
class	java/io/Serializable

{
public static final long serialVersionUID;
  Signature: J

private final scala.PartialFunction f$1;
  Signature: Lscala/PartialFunction;

private final scala.actors.Actor $outer;
  Signature: Lscala/actors/Actor;

public static {};
  Signature: ()V
  Code:
   Stack=2, Locals=0, Args_size=0
	lconst_0
	putstatic	Field serialVersionUID:J
	return
  Labels:

public scala.actors.Actor$$anonfun$1(scala.actors.Actor, scala.PartialFunction);
  Signature: (Lscala/actors/Actor;Lscala/PartialFunction;)V
  Code:
   Stack=2, Locals=3, Args_size=3
	aload_1
	ifnonnull	l1 // aload_0
	new	class java/lang/NullPointerException
	dup
	invokespecial	Method java/lang/NullPointerException."<init>":()V
	athrow
l1	aload_0
	aload_1
	putfield	Field $outer:Lscala/actors/Actor;
	aload_0
	aload_2
	putfield	Field f$1:Lscala/PartialFunction;
	aload_0
	invokespecial	Method java/lang/Object."<init>":()V
	aload_0
	invokestatic	Method scala/Function2$class.$init$:(Lscala/Function2;)V
	return
  Labels:
   	l1 = 12 // aload_0
  LocalVariableTable: 
   Start  Length  Slot  Name   Signature
   0      31      0    this       Lscala/actors/Actor$$anonfun$1;
   0      31      1    $outer       Lscala/actors/Actor;


public final java.lang.Object apply(java.lang.Object, java.lang.Object);
  Signature: (Ljava/lang/Object;Ljava/lang/Object;)Ljava/lang/Object;
  Code:
   Stack=3, Locals=5, Args_size=3
	aload_0
	getfield	Field $outer:Lscala/actors/Actor;
	astore	4
	aload_0
	aload_1
	aload_2
	checkcast	class scala/actors/OutputChannel
	invokevirtual	Method apply:(Ljava/lang/Object;Lscala/actors/OutputChannel;)Z
	istore_3
	iload_3
	invokestatic	Method scala/runtime/BoxesRunTime.boxToBoolean:(Z)Ljava/lang/Boolean;
	areturn
  Labels:
  LocalVariableTable: 
   Start  Length  Slot  Name   Signature
   0      21      0    this       Lscala/actors/Actor$$anonfun$1;
   6      15      1    v1       Ljava/lang/Object;
   6      15      2    v2       Ljava/lang/Object;


public final boolean apply(java.lang.Object, scala.actors.OutputChannel);
  Signature: (Ljava/lang/Object;Lscala/actors/OutputChannel;)Z
  Code:
   Stack=3, Locals=5, Args_size=3
	aload_0
	getfield	Field $outer:Lscala/actors/Actor;
	astore	4
	aload_0
	getfield	Field $outer:Lscala/actors/Actor;
	aload_0
	getfield	Field $outer:Lscala/actors/Actor;
	invokeinterface	InterfaceMethod scala/actors/ReplyReactor.senders:()Lscala/collection/immutable/List;
	aload_2
	invokevirtual	Method scala/collection/immutable/List.$colon$colon:(Ljava/lang/Object;)Lscala/collection/immutable/List;
	invokeinterface	InterfaceMethod scala/actors/ReplyReactor.senders_$eq:(Lscala/collection/immutable/List;)V
	aload_0
	getfield	Field f$1:Lscala/PartialFunction;
	aload_1
	invokeinterface	InterfaceMethod scala/PartialFunction.isDefinedAt:(Ljava/lang/Object;)Z
	istore_3
	aload_0
	getfield	Field $outer:Lscala/actors/Actor;
	aload_0
	getfield	Field $outer:Lscala/actors/Actor;
	invokeinterface	InterfaceMethod scala/actors/ReplyReactor.senders:()Lscala/collection/immutable/List;
	invokeinterface	InterfaceMethod scala/collection/TraversableLike.tail:()Ljava/lang/Object;
	checkcast	class scala/collection/immutable/List
	invokeinterface	InterfaceMethod scala/actors/ReplyReactor.senders_$eq:(Lscala/collection/immutable/List;)V
	iload_3
	ireturn
  Labels:
  LocalVariableTable: 
   Start  Length  Slot  Name   Signature
   0      67      0    this       Lscala/actors/Actor$$anonfun$1;
   6      61      1    m       Ljava/lang/Object;
   6      61      2    replyTo       Lscala/actors/OutputChannel;
   39      27      3    matches       Z

  Signature: length = 0x2
   00 58 

public scala.Function1 curry();
  Signature: ()Lscala/Function1;
  Code:
   Stack=1, Locals=1, Args_size=1
	aload_0
	invokestatic	Method scala/Function2$class.curry:(Lscala/Function2;)Lscala/Function1;
	areturn
  Labels:

public java.lang.String toString();
  Signature: ()Ljava/lang/String;
  Code:
   Stack=1, Locals=1, Args_size=1
	aload_0
	invokestatic	Method scala/Function2$class.toString:(Lscala/Function2;)Ljava/lang/String;
	areturn
  Labels:

}

