Compiled from "Actor.scala"
public final class scala.actors.Actor$$anonfun$startSearch$1 extends java.lang.Object implements scala.Function0,scala.ScalaObject,java.io.Serializable
  SourceFile: "Actor.scala"
  Scala: length = 0x
   
  InnerClass: 
   public final $anonfun$startSearch$1=class scala/actors/Actor$$anonfun$startSearch$1 of class scala/actors/Actor
  minor version: 0
  major version: 49
  Constant pool:
Asciz	SourceFile;
Asciz	Actor.scala;
Asciz	<clinit>;
Asciz	()V;
Asciz	Code;
Asciz	serialVersionUID;
Asciz	J;
Asciz	scala/actors/Actor$$anonfun$startSearch$1;
class	scala/actors/Actor$$anonfun$startSearch$1
NameAndType	serialVersionUID:J
Field	scala/actors/Actor$$anonfun$startSearch$1.serialVersionUID:J
Asciz	replyTo$1;
Asciz	Lscala/actors/OutputChannel;;
Asciz	msg$1;
Asciz	Ljava/lang/Object;;
Asciz	$outer;
Asciz	Lscala/actors/Actor;;
Asciz	<init>;
Asciz	(Lscala/actors/Actor;Ljava/lang/Object;Lscala/actors/OutputChannel;)V;
Asciz	LineNumberTable;
Asciz	java/lang/NullPointerException;
class	java/lang/NullPointerException
NameAndType	"<init>":()V
Method	java/lang/NullPointerException."<init>":()V
NameAndType	$outer:Lscala/actors/Actor;
Field	scala/actors/Actor$$anonfun$startSearch$1.$outer:Lscala/actors/Actor;
NameAndType	msg$1:Ljava/lang/Object;
Field	scala/actors/Actor$$anonfun$startSearch$1.msg$1:Ljava/lang/Object;
NameAndType	replyTo$1:Lscala/actors/OutputChannel;
Field	scala/actors/Actor$$anonfun$startSearch$1.replyTo$1:Lscala/actors/OutputChannel;
Asciz	java/lang/Object;
class	java/lang/Object
Method	java/lang/Object."<init>":()V
Asciz	scala/Function0$class;
class	scala/Function0$class
Asciz	$init$;
Asciz	(Lscala/Function0;)V;
NameAndType	$init$:(Lscala/Function0;)V
Method	scala/Function0$class.$init$:(Lscala/Function0;)V
Asciz	this;
Asciz	Lscala/actors/Actor$$anonfun$startSearch$1;;
Asciz	LocalVariableTable;
Asciz	apply;
Asciz	()Ljava/lang/Object;;
NameAndType	apply:()V
Method	scala/actors/Actor$$anonfun$startSearch$1.apply:()V
Asciz	scala/runtime/BoxedUnit;
class	scala/runtime/BoxedUnit
Asciz	UNIT;
Asciz	Lscala/runtime/BoxedUnit;;
NameAndType	UNIT:Lscala/runtime/BoxedUnit;
Field	scala/runtime/BoxedUnit.UNIT:Lscala/runtime/BoxedUnit;
Asciz	scala/actors/Reactor;
class	scala/actors/Reactor
Asciz	mailbox;
Asciz	()Lscala/actors/MessageQueue;;
NameAndType	mailbox:()Lscala/actors/MessageQueue;
InterfaceMethod	scala/actors/Reactor.mailbox:()Lscala/actors/MessageQueue;
Asciz	scala/actors/MessageQueue;
class	scala/actors/MessageQueue
Asciz	append;
Asciz	(Ljava/lang/Object;Lscala/actors/OutputChannel;)V;
NameAndType	append:(Ljava/lang/Object;Lscala/actors/OutputChannel;)V
Method	scala/actors/MessageQueue.append:(Ljava/lang/Object;Lscala/actors/OutputChannel;)V
Asciz	scala/actors/Actor$class;
class	scala/actors/Actor$class
Asciz	scala$actors$Actor$$resumeActor;
Asciz	(Lscala/actors/Actor;)V;
NameAndType	scala$actors$Actor$$resumeActor:(Lscala/actors/Actor;)V
Method	scala/actors/Actor$class.scala$actors$Actor$$resumeActor:(Lscala/actors/Actor;)V
Asciz	toString;
Asciz	()Ljava/lang/String;;
Asciz	(Lscala/Function0;)Ljava/lang/String;;
NameAndType	toString:(Lscala/Function0;)Ljava/lang/String;
Method	scala/Function0$class.toString:(Lscala/Function0;)Ljava/lang/String;
Asciz	Scala;
Asciz	InnerClasses;
Asciz	scala/actors/Actor;
class	scala/actors/Actor
Asciz	$anonfun$startSearch$1;
Asciz	scala/Function0;
class	scala/Function0
Asciz	scala/ScalaObject;
class	scala/ScalaObject
Asciz	java/io/Serializable;
class	java/io/Serializable

{
public static final long serialVersionUID;
  Signature: J

private final scala.actors.OutputChannel replyTo$1;
  Signature: Lscala/actors/OutputChannel;

private final java.lang.Object msg$1;
  Signature: Ljava/lang/Object;

private final scala.actors.Actor $outer;
  Signature: Lscala/actors/Actor;

public static {};
  Signature: ()V
  Code:
   Stack=2, Locals=0, Args_size=0
	lconst_0
	putstatic	Field serialVersionUID:J
	return
  Labels:

public scala.actors.Actor$$anonfun$startSearch$1(scala.actors.Actor, java.lang.Object, scala.actors.OutputChannel);
  Signature: (Lscala/actors/Actor;Ljava/lang/Object;Lscala/actors/OutputChannel;)V
  Code:
   Stack=2, Locals=4, Args_size=4
	aload_1
	ifnonnull	l1 // aload_0
	new	class java/lang/NullPointerException
	dup
	invokespecial	Method java/lang/NullPointerException."<init>":()V
	athrow
l1	aload_0
	aload_1
	putfield	Field $outer:Lscala/actors/Actor;
	aload_0
	aload_2
	putfield	Field msg$1:Ljava/lang/Object;
	aload_0
	aload_3
	putfield	Field replyTo$1:Lscala/actors/OutputChannel;
	aload_0
	invokespecial	Method java/lang/Object."<init>":()V
	aload_0
	invokestatic	Method scala/Function0$class.$init$:(Lscala/Function0;)V
	return
  Labels:
   	l1 = 12 // aload_0
  LocalVariableTable: 
   Start  Length  Slot  Name   Signature
   0      36      0    this       Lscala/actors/Actor$$anonfun$startSearch$1;
   0      36      1    $outer       Lscala/actors/Actor;


public final java.lang.Object apply();
  Signature: ()Ljava/lang/Object;
  Code:
   Stack=1, Locals=2, Args_size=1
	aload_0
	getfield	Field $outer:Lscala/actors/Actor;
	astore_1
	aload_0
	invokevirtual	Method apply:()V
	getstatic	Field scala/runtime/BoxedUnit.UNIT:Lscala/runtime/BoxedUnit;
	areturn
  Labels:
  LocalVariableTable: 
   Start  Length  Slot  Name   Signature
   0      13      0    this       Lscala/actors/Actor$$anonfun$startSearch$1;


public final void apply();
  Signature: ()V
  Code:
   Stack=3, Locals=3, Args_size=1
	aload_0
	getfield	Field $outer:Lscala/actors/Actor;
	astore_2
	aload_0
	getfield	Field $outer:Lscala/actors/Actor;
	dup
	astore_1
	monitorenter
	aload_0
	getfield	Field $outer:Lscala/actors/Actor;
	invokeinterface	InterfaceMethod scala/actors/Reactor.mailbox:()Lscala/actors/MessageQueue;
	aload_0
	getfield	Field msg$1:Ljava/lang/Object;
	aload_0
	getfield	Field replyTo$1:Lscala/actors/OutputChannel;
	invokevirtual	Method scala/actors/MessageQueue.append:(Ljava/lang/Object;Lscala/actors/OutputChannel;)V
	aload_0
	getfield	Field $outer:Lscala/actors/Actor;
	invokestatic	Method scala/actors/Actor$class.scala$actors$Actor$$resumeActor:(Lscala/actors/Actor;)V
	aload_1
	monitorexit
	return
	aload_1
	monitorexit
	athrow
  Labels:
  Exception table:
   from   to  target type
    12    41    42   any
  LocalVariableTable: 
   Start  Length  Slot  Name   Signature
   0      45      0    this       Lscala/actors/Actor$$anonfun$startSearch$1;


public java.lang.String toString();
  Signature: ()Ljava/lang/String;
  Code:
   Stack=1, Locals=1, Args_size=1
	aload_0
	invokestatic	Method scala/Function0$class.toString:(Lscala/Function0;)Ljava/lang/String;
	areturn
  Labels:

}

