Compiled from "Actor.scala"
public final class scala.actors.Actor$$anon$6 extends java.lang.Object implements scala.actors.Actor$Body
  SourceFile: "Actor.scala"
  Signature: length = 0x2
   00 29 
  Scala: length = 0x
   
  InnerClass: 
   public abstract #48= #45 of #47; //Body=class scala/actors/Actor$Body of class scala/actors/Actor
   public final #49= #10 of #47; //$anon$6=class scala/actors/Actor$$anon$6 of class scala/actors/Actor
  minor version: 0
  major version: 49
  Constant pool:
const #1 = Asciz	SourceFile;
const #2 = Asciz	Actor.scala;
const #3 = Asciz	body$3;
const #4 = Asciz	Lscala/Function0;;
const #5 = Asciz	<init>;
const #6 = Asciz	(Lscala/Function0;)V;
const #7 = Asciz	Code;
const #8 = Asciz	LineNumberTable;
const #9 = Asciz	scala/actors/Actor$$anon$6;
const #10 = class	#9;	//  scala/actors/Actor$$anon$6
const #11 = NameAndType	#3:#4;//  body$3:Lscala/Function0;
const #12 = Field	#10.#11;	//  scala/actors/Actor$$anon$6.body$3:Lscala/Function0;
const #13 = Asciz	java/lang/Object;
const #14 = class	#13;	//  java/lang/Object
const #15 = Asciz	()V;
const #16 = NameAndType	#5:#15;//  "<init>":()V
const #17 = Method	#14.#16;	//  java/lang/Object."<init>":()V
const #18 = Asciz	andThen;
const #19 = Asciz	scala/actors/Actor$;
const #20 = class	#19;	//  scala/actors/Actor$
const #21 = Asciz	MODULE$;
const #22 = Asciz	Lscala/actors/Actor$;;
const #23 = NameAndType	#21:#22;//  MODULE$:Lscala/actors/Actor$;
const #24 = Field	#20.#23;	//  scala/actors/Actor$.MODULE$:Lscala/actors/Actor$;
const #25 = Asciz	rawSelf;
const #26 = Asciz	()Lscala/actors/Reactor;;
const #27 = NameAndType	#25:#26;//  rawSelf:()Lscala/actors/Reactor;
const #28 = Method	#20.#27;	//  scala/actors/Actor$.rawSelf:()Lscala/actors/Reactor;
const #29 = Asciz	scala/actors/Reactor;
const #30 = class	#29;	//  scala/actors/Reactor
const #31 = Asciz	seq;
const #32 = Asciz	(Lscala/Function0;Lscala/Function0;)V;
const #33 = NameAndType	#31:#32;//  seq:(Lscala/Function0;Lscala/Function0;)V
const #34 = InterfaceMethod	#30.#33;	//  scala/actors/Reactor.seq:(Lscala/Function0;Lscala/Function0;)V
const #35 = Asciz	this;
const #36 = Asciz	Lscala/actors/Actor$$anon$6;;
const #37 = Asciz	other;
const #38 = Asciz	LocalVariableTable;
const #39 = Asciz	<b:Ljava/lang/Object;>(Lscala/Function0<Tb;>;)V;
const #40 = Asciz	Signature;
const #41 = Asciz	Ljava/lang/Object;Lscala/actors/Actor$Body<Ta;>;;
const #42 = Asciz	Scala;
const #43 = Asciz	InnerClasses;
const #44 = Asciz	scala/actors/Actor$Body;
const #45 = class	#44;	//  scala/actors/Actor$Body
const #46 = Asciz	scala/actors/Actor;
const #47 = class	#46;	//  scala/actors/Actor
const #48 = Asciz	Body;
const #49 = Asciz	$anon$6;

{
public scala.actors.Actor$$anon$6(scala.Function0);
  Code:
   Stack=2, Locals=2, Args_size=2
   0:	aload_0
   1:	aload_1
   2:	putfield	#12; //Field body$3:Lscala/Function0;
   5:	aload_0
   6:	invokespecial	#17; //Method java/lang/Object."<init>":()V
   9:	return
  LineNumberTable: 
   line 275: 0


public void andThen(scala.Function0);
  Code:
   Stack=3, Locals=2, Args_size=2
   0:	getstatic	#24; //Field scala/actors/Actor$.MODULE$:Lscala/actors/Actor$;
   3:	invokevirtual	#28; //Method scala/actors/Actor$.rawSelf:()Lscala/actors/Reactor;
   6:	aload_0
   7:	getfield	#12; //Field body$3:Lscala/Function0;
   10:	aload_1
   11:	invokeinterface	#34,  3; //InterfaceMethod scala/actors/Reactor.seq:(Lscala/Function0;Lscala/Function0;)V
   16:	return
  LineNumberTable: 
   line 276: 0

  LocalVariableTable: 
   Start  Length  Slot  Name   Signature
   0      17      0    this       Lscala/actors/Actor$$anon$6;
   0      17      1    other       Lscala/Function0;

  Signature: length = 0x2
   00 27 

}

