Compiled from "Actor.scala"
public final class scala.actors.Actor$$anonfun$2 extends java.lang.Object implements scala.Function0,scala.ScalaObject,java.io.Serializable
  SourceFile: "Actor.scala"
  Scala: length = 0x
   
  InnerClass: 
   public final $anonfun$2=class scala/actors/Actor$$anonfun$2 of class scala/actors/Actor
  minor version: 0
  major version: 49
  Constant pool:
Asciz	SourceFile;
Asciz	Actor.scala;
Asciz	<clinit>;
Asciz	()V;
Asciz	Code;
Asciz	serialVersionUID;
Asciz	J;
Asciz	scala/actors/Actor$$anonfun$2;
class	scala/actors/Actor$$anonfun$2
NameAndType	serialVersionUID:J
Field	scala/actors/Actor$$anonfun$2.serialVersionUID:J
Asciz	f$2;
Asciz	Lscala/PartialFunction;;
Asciz	$outer;
Asciz	Lscala/actors/Actor;;
Asciz	<init>;
Asciz	(Lscala/actors/Actor;Lscala/PartialFunction;)V;
Asciz	LineNumberTable;
Asciz	java/lang/NullPointerException;
class	java/lang/NullPointerException
NameAndType	"<init>":()V
Method	java/lang/NullPointerException."<init>":()V
NameAndType	$outer:Lscala/actors/Actor;
Field	scala/actors/Actor$$anonfun$2.$outer:Lscala/actors/Actor;
NameAndType	f$2:Lscala/PartialFunction;
Field	scala/actors/Actor$$anonfun$2.f$2:Lscala/PartialFunction;
Asciz	java/lang/Object;
class	java/lang/Object
Method	java/lang/Object."<init>":()V
Asciz	scala/Function0$class;
class	scala/Function0$class
Asciz	$init$;
Asciz	(Lscala/Function0;)V;
NameAndType	$init$:(Lscala/Function0;)V
Method	scala/Function0$class.$init$:(Lscala/Function0;)V
Asciz	this;
Asciz	Lscala/actors/Actor$$anonfun$2;;
Asciz	LocalVariableTable;
Asciz	apply;
Asciz	()Ljava/lang/Object;;
NameAndType	apply:()V
Method	scala/actors/Actor$$anonfun$2.apply:()V
Asciz	scala/runtime/BoxedUnit;
class	scala/runtime/BoxedUnit
Asciz	UNIT;
Asciz	Lscala/runtime/BoxedUnit;;
NameAndType	UNIT:Lscala/runtime/BoxedUnit;
Field	scala/runtime/BoxedUnit.UNIT:Lscala/runtime/BoxedUnit;
Asciz	scala/actors/TIMEOUT$;
class	scala/actors/TIMEOUT$
Asciz	MODULE$;
Asciz	Lscala/actors/TIMEOUT$;;
NameAndType	MODULE$:Lscala/actors/TIMEOUT$;
Field	scala/actors/TIMEOUT$.MODULE$:Lscala/actors/TIMEOUT$;
Asciz	scala/PartialFunction;
class	scala/PartialFunction
Asciz	isDefinedAt;
Asciz	(Ljava/lang/Object;)Z;
NameAndType	isDefinedAt:(Ljava/lang/Object;)Z
InterfaceMethod	scala/PartialFunction.isDefinedAt:(Ljava/lang/Object;)Z
Asciz	scala/Some;
class	scala/Some
Asciz	(Ljava/lang/Object;)V;
NameAndType	"<init>":(Ljava/lang/Object;)V
Method	scala/Some."<init>":(Ljava/lang/Object;)V
Asciz	scala/actors/Actor;
class	scala/actors/Actor
Asciz	scala$actors$Actor$$received_$eq;
Asciz	(Lscala/Option;)V;
NameAndType	scala$actors$Actor$$received_$eq:(Lscala/Option;)V
InterfaceMethod	scala/actors/Actor.scala$actors$Actor$$received_$eq:(Lscala/Option;)V
Asciz	scala/actors/ReplyReactor;
class	scala/actors/ReplyReactor
Asciz	senders;
Asciz	()Lscala/collection/immutable/List;;
NameAndType	senders:()Lscala/collection/immutable/List;
InterfaceMethod	scala/actors/ReplyReactor.senders:()Lscala/collection/immutable/List;
Asciz	scala/collection/immutable/List;
class	scala/collection/immutable/List
Asciz	$colon$colon;
Asciz	(Ljava/lang/Object;)Lscala/collection/immutable/List;;
NameAndType	$colon$colon:(Ljava/lang/Object;)Lscala/collection/immutable/List;
Method	scala/collection/immutable/List.$colon$colon:(Ljava/lang/Object;)Lscala/collection/immutable/List;
Asciz	senders_$eq;
Asciz	(Lscala/collection/immutable/List;)V;
NameAndType	senders_$eq:(Lscala/collection/immutable/List;)V
InterfaceMethod	scala/actors/ReplyReactor.senders_$eq:(Lscala/collection/immutable/List;)V
Asciz	unhandled timeout;
String	unhandled timeout
Asciz	java/lang/RuntimeException;
class	java/lang/RuntimeException
Asciz	(Ljava/lang/String;)V;
NameAndType	"<init>":(Ljava/lang/String;)V
Method	java/lang/RuntimeException."<init>":(Ljava/lang/String;)V
Asciz	toString;
Asciz	()Ljava/lang/String;;
Asciz	(Lscala/Function0;)Ljava/lang/String;;
NameAndType	toString:(Lscala/Function0;)Ljava/lang/String;
Method	scala/Function0$class.toString:(Lscala/Function0;)Ljava/lang/String;
Asciz	Scala;
Asciz	InnerClasses;
Asciz	$anonfun$2;
Asciz	scala/Function0;
class	scala/Function0
Asciz	scala/ScalaObject;
class	scala/ScalaObject
Asciz	java/io/Serializable;
class	java/io/Serializable

{
public static final long serialVersionUID;
  Signature: J

private final scala.PartialFunction f$2;
  Signature: Lscala/PartialFunction;

private final scala.actors.Actor $outer;
  Signature: Lscala/actors/Actor;

public static {};
  Signature: ()V
  Code:
   Stack=2, Locals=0, Args_size=0
	lconst_0
	putstatic	Field serialVersionUID:J
	return
  Labels:

public scala.actors.Actor$$anonfun$2(scala.actors.Actor, scala.PartialFunction);
  Signature: (Lscala/actors/Actor;Lscala/PartialFunction;)V
  Code:
   Stack=2, Locals=3, Args_size=3
	aload_1
	ifnonnull	l1 // aload_0
	new	class java/lang/NullPointerException
	dup
	invokespecial	Method java/lang/NullPointerException."<init>":()V
	athrow
l1	aload_0
	aload_1
	putfield	Field $outer:Lscala/actors/Actor;
	aload_0
	aload_2
	putfield	Field f$2:Lscala/PartialFunction;
	aload_0
	invokespecial	Method java/lang/Object."<init>":()V
	aload_0
	invokestatic	Method scala/Function0$class.$init$:(Lscala/Function0;)V
	return
  Labels:
   	l1 = 12 // aload_0
  LocalVariableTable: 
   Start  Length  Slot  Name   Signature
   0      31      0    this       Lscala/actors/Actor$$anonfun$2;
   0      31      1    $outer       Lscala/actors/Actor;


public final java.lang.Object apply();
  Signature: ()Ljava/lang/Object;
  Code:
   Stack=1, Locals=2, Args_size=1
	aload_0
	getfield	Field $outer:Lscala/actors/Actor;
	astore_1
	aload_0
	invokevirtual	Method apply:()V
	getstatic	Field scala/runtime/BoxedUnit.UNIT:Lscala/runtime/BoxedUnit;
	areturn
  Labels:
  LocalVariableTable: 
   Start  Length  Slot  Name   Signature
   0      13      0    this       Lscala/actors/Actor$$anonfun$2;


public final void apply();
  Signature: ()V
  Code:
   Stack=4, Locals=4, Args_size=1
	aload_0
	getfield	Field $outer:Lscala/actors/Actor;
	astore_3
	aload_0
	getfield	Field f$2:Lscala/PartialFunction;
	getstatic	Field scala/actors/TIMEOUT$.MODULE$:Lscala/actors/TIMEOUT$;
	invokeinterface	InterfaceMethod scala/PartialFunction.isDefinedAt:(Ljava/lang/Object;)Z
	ifeq	l1 // ldc
	aload_0
	getfield	Field $outer:Lscala/actors/Actor;
	new	class scala/Some
	dup
	getstatic	Field scala/actors/TIMEOUT$.MODULE$:Lscala/actors/TIMEOUT$;
	invokespecial	Method scala/Some."<init>":(Ljava/lang/Object;)V
	invokeinterface	InterfaceMethod scala/actors/Actor.scala$actors$Actor$$received_$eq:(Lscala/Option;)V
	aload_0
	getfield	Field $outer:Lscala/actors/Actor;
	aload_0
	getfield	Field $outer:Lscala/actors/Actor;
	astore_1
	aload_0
	getfield	Field $outer:Lscala/actors/Actor;
	invokeinterface	InterfaceMethod scala/actors/ReplyReactor.senders:()Lscala/collection/immutable/List;
	aload_1
	invokevirtual	Method scala/collection/immutable/List.$colon$colon:(Ljava/lang/Object;)Lscala/collection/immutable/List;
	invokeinterface	InterfaceMethod scala/actors/ReplyReactor.senders_$eq:(Lscala/collection/immutable/List;)V
	return
l1	ldc	String unhandled timeout
	astore_2
	new	class java/lang/RuntimeException
	dup
	aload_2
	invokespecial	Method java/lang/RuntimeException."<init>":(Ljava/lang/String;)V
	athrow
  Labels:
   	l1 = 67 // ldc
  LocalVariableTable: 
   Start  Length  Slot  Name   Signature
   0      79      0    this       Lscala/actors/Actor$$anonfun$2;


public java.lang.String toString();
  Signature: ()Ljava/lang/String;
  Code:
   Stack=1, Locals=1, Args_size=1
	aload_0
	invokestatic	Method scala/Function0$class.toString:(Lscala/Function0;)Ljava/lang/String;
	areturn
  Labels:

}

