Compiled from "Actor.scala"
public final class scala.actors.Actor$ extends java.lang.Object implements scala.ScalaObject
  SourceFile: "Actor.scala"
  Scala: length = 0x
   
  InnerClass: 
   public abstract #262= #105 of #56; //Body=class scala/actors/Actor$Body of class scala/actors/Actor
   public final #265= #264 of #56; //$anon$3=class scala/actors/Actor$$anon$3 of class scala/actors/Actor
   public final #268= #267 of #56; //$anon$6=class scala/actors/Actor$$anon$6 of class scala/actors/Actor
   public final #271= #270 of #56; //$anon$5=class scala/actors/Actor$$anon$5 of class scala/actors/Actor
   public final #272= #209 of #56; //$anon$1=class scala/actors/Actor$$anon$1 of class scala/actors/Actor
   public final #273= #199 of #56; //$anon$2=class scala/actors/Actor$$anon$2 of class scala/actors/Actor
   public final #274= #100 of #56; //$anon$7=class scala/actors/Actor$$anon$7 of class scala/actors/Actor
   public final #277= #276 of #56; //$anonfun$9=class scala/actors/Actor$$anonfun$9 of class scala/actors/Actor
   public final #280= #279 of #56; //$anonfun$8=class scala/actors/Actor$$anonfun$8 of class scala/actors/Actor
   public final #283= #282 of #56; //$anonfun$7=class scala/actors/Actor$$anonfun$7 of class scala/actors/Actor
   public final #286= #285 of #56; //$anonfun$6=class scala/actors/Actor$$anonfun$6 of class scala/actors/Actor
   public final #289= #288 of #56; //$anonfun$5=class scala/actors/Actor$$anonfun$5 of class scala/actors/Actor
   public final #292= #291 of #56; //$anonfun$4=class scala/actors/Actor$$anonfun$4 of class scala/actors/Actor
   public final #295= #294 of #56; //$anonfun$3=class scala/actors/Actor$$anonfun$3 of class scala/actors/Actor
   public final #298= #297 of #56; //$anonfun$2=class scala/actors/Actor$$anonfun$2 of class scala/actors/Actor
   public final #301= #300 of #56; //$anonfun$1=class scala/actors/Actor$$anonfun$1 of class scala/actors/Actor
   public final #304= #303 of #56; //$anonfun$12=class scala/actors/Actor$$anonfun$12 of class scala/actors/Actor
   public final #307= #306 of #56; //$anonfun$11=class scala/actors/Actor$$anonfun$11 of class scala/actors/Actor
   public final #310= #309 of #56; //$anonfun$10=class scala/actors/Actor$$anonfun$10 of class scala/actors/Actor
   public final #313= #312 of #56; //$anonfun$link$2=class scala/actors/Actor$$anonfun$link$2 of class scala/actors/Actor
   public final #316= #315 of #56; //$anonfun$link$1=class scala/actors/Actor$$anonfun$link$1 of class scala/actors/Actor
   public final #317= #118 of #56; //$anonfun$loop$1=class scala/actors/Actor$$anonfun$loop$1 of class scala/actors/Actor
   public final #320= #319 of #56; //$anonfun$react$2=class scala/actors/Actor$$anonfun$react$2 of class scala/actors/Actor
   public final #323= #322 of #56; //$anonfun$react$1=class scala/actors/Actor$$anonfun$react$1 of class scala/actors/Actor
   public final #326= #325 of #56; //$anonfun$unlink$1=class scala/actors/Actor$$anonfun$unlink$1 of class scala/actors/Actor
   public final #329= #328 of #56; //$anonfun$$qmark$1=class scala/actors/Actor$$anonfun$$qmark$1 of class scala/actors/Actor
   public final #332= #331 of #56; //$anonfun$receive$2=class scala/actors/Actor$$anonfun$receive$2 of class scala/actors/Actor
   public final #335= #334 of #56; //$anonfun$receive$1=class scala/actors/Actor$$anonfun$receive$1 of class scala/actors/Actor
   public final #336= #129 of #56; //$anonfun$respondOn$1=class scala/actors/Actor$$anonfun$respondOn$1 of class scala/actors/Actor
   public final #337= #107 of #56; //$anonfun$loopWhile$1=class scala/actors/Actor$$anonfun$loopWhile$1 of class scala/actors/Actor
   public final #340= #339 of #56; //$anonfun$exitLinked$1=class scala/actors/Actor$$anonfun$exitLinked$1 of class scala/actors/Actor
   public final #343= #342 of #56; //$anonfun$unlinkFrom$1=class scala/actors/Actor$$anonfun$unlinkFrom$1 of class scala/actors/Actor
   public #344= #167 of #56; //RecursiveProxyHandler=class scala/actors/Actor$RecursiveProxyHandler of class scala/actors/Actor
   public final #347= #346 of #56; //$anonfun$reactWithin$2=class scala/actors/Actor$$anonfun$reactWithin$2 of class scala/actors/Actor
   public final #350= #349 of #56; //$anonfun$reactWithin$1=class scala/actors/Actor$$anonfun$reactWithin$1 of class scala/actors/Actor
   public final #353= #352 of #56; //$anonfun$startSearch$1=class scala/actors/Actor$$anonfun$startSearch$1 of class scala/actors/Actor
   public final #356= #355 of #56; //$anonfun$receiveWithin$2=class scala/actors/Actor$$anonfun$receiveWithin$2 of class scala/actors/Actor
   public final #359= #358 of #56; //$anonfun$receiveWithin$1=class scala/actors/Actor$$anonfun$receiveWithin$1 of class scala/actors/Actor
  minor version: 0
  major version: 49
  Constant pool:
const #1 = Asciz	SourceFile;
const #2 = Asciz	Actor.scala;
const #3 = Asciz	Scala;
const #4 = Asciz	MODULE$;
const #5 = Asciz	Lscala/actors/Actor$;;
const #6 = Asciz	<clinit>;
const #7 = Asciz	()V;
const #8 = Asciz	Code;
const #9 = Asciz	scala/actors/Actor$;
const #10 = class	#9;	//  scala/actors/Actor$
const #11 = Asciz	<init>;
const #12 = NameAndType	#11:#7;//  "<init>":()V
const #13 = Method	#10.#12;	//  scala/actors/Actor$."<init>":()V
const #14 = Asciz	suspendException;
const #15 = Asciz	Lscala/actors/SuspendActorException;;
const #16 = Asciz	timer;
const #17 = Asciz	Ljava/util/Timer;;
const #18 = Asciz	tl;
const #19 = Asciz	Ljava/lang/ThreadLocal;;
const #20 = Asciz	Ljava/lang/ThreadLocal<Lscala/actors/Reactor;>;;
const #21 = Asciz	Signature;
const #22 = Asciz	LineNumberTable;
const #23 = Asciz	java/lang/Object;
const #24 = class	#23;	//  java/lang/Object
const #25 = Method	#24.#12;	//  java/lang/Object."<init>":()V
const #26 = NameAndType	#4:#5;//  MODULE$:Lscala/actors/Actor$;
const #27 = Field	#10.#26;	//  scala/actors/Actor$.MODULE$:Lscala/actors/Actor$;
const #28 = Asciz	java/lang/ThreadLocal;
const #29 = class	#28;	//  java/lang/ThreadLocal
const #30 = Method	#29.#12;	//  java/lang/ThreadLocal."<init>":()V
const #31 = NameAndType	#18:#19;//  tl:Ljava/lang/ThreadLocal;
const #32 = Field	#10.#31;	//  scala/actors/Actor$.tl:Ljava/lang/ThreadLocal;
const #33 = Asciz	java/util/Timer;
const #34 = class	#33;	//  java/util/Timer
const #35 = Asciz	(Z)V;
const #36 = NameAndType	#11:#35;//  "<init>":(Z)V
const #37 = Method	#34.#36;	//  java/util/Timer."<init>":(Z)V
const #38 = NameAndType	#16:#17;//  timer:Ljava/util/Timer;
const #39 = Field	#10.#38;	//  scala/actors/Actor$.timer:Ljava/util/Timer;
const #40 = Asciz	scala/actors/SuspendActorException;
const #41 = class	#40;	//  scala/actors/SuspendActorException
const #42 = Method	#41.#12;	//  scala/actors/SuspendActorException."<init>":()V
const #43 = NameAndType	#14:#15;//  suspendException:Lscala/actors/SuspendActorException;
const #44 = Field	#10.#43;	//  scala/actors/Actor$.suspendException:Lscala/actors/SuspendActorException;
const #45 = Asciz	continue;
const #46 = Asciz	scala/actors/KillActorException;
const #47 = class	#46;	//  scala/actors/KillActorException
const #48 = Method	#47.#12;	//  scala/actors/KillActorException."<init>":()V
const #49 = Asciz	exit;
const #50 = Asciz	()Lscala/runtime/Nothing$;;
const #51 = Asciz	self;
const #52 = Asciz	()Lscala/actors/Actor;;
const #53 = NameAndType	#51:#52;//  self:()Lscala/actors/Actor;
const #54 = Method	#10.#53;	//  scala/actors/Actor$.self:()Lscala/actors/Actor;
const #55 = Asciz	scala/actors/Actor;
const #56 = class	#55;	//  scala/actors/Actor
const #57 = NameAndType	#49:#50;//  exit:()Lscala/runtime/Nothing$;
const #58 = InterfaceMethod	#56.#57;	//  scala/actors/Actor.exit:()Lscala/runtime/Nothing$;
const #59 = Asciz	(Ljava/lang/Object;)Lscala/runtime/Nothing$;;
const #60 = NameAndType	#49:#59;//  exit:(Ljava/lang/Object;)Lscala/runtime/Nothing$;
const #61 = InterfaceMethod	#56.#60;	//  scala/actors/Actor.exit:(Ljava/lang/Object;)Lscala/runtime/Nothing$;
const #62 = Asciz	this;
const #63 = Asciz	reason;
const #64 = Asciz	Ljava/lang/Object;;
const #65 = Asciz	LocalVariableTable;
const #66 = Asciz	unlink;
const #67 = Asciz	(Lscala/actors/Actor;)V;
const #68 = Asciz	(Lscala/actors/AbstractActor;)V;
const #69 = NameAndType	#66:#68;//  unlink:(Lscala/actors/AbstractActor;)V
const #70 = InterfaceMethod	#56.#69;	//  scala/actors/Actor.unlink:(Lscala/actors/AbstractActor;)V
const #71 = Asciz	from;
const #72 = Asciz	Lscala/actors/Actor;;
const #73 = Asciz	link;
const #74 = Asciz	(Lscala/Function0;)Lscala/actors/Actor;;
const #75 = NameAndType	#73:#74;//  link:(Lscala/Function0;)Lscala/actors/Actor;
const #76 = InterfaceMethod	#56.#75;	//  scala/actors/Actor.link:(Lscala/Function0;)Lscala/actors/Actor;
const #77 = Asciz	body;
const #78 = Asciz	Lscala/Function0;;
const #79 = Asciz	(Lscala/Function0<Ljava/lang/Object;>;)Lscala/actors/Actor;;
const #80 = Asciz	(Lscala/actors/AbstractActor;)Lscala/actors/AbstractActor;;
const #81 = NameAndType	#73:#80;//  link:(Lscala/actors/AbstractActor;)Lscala/actors/AbstractActor;
const #82 = InterfaceMethod	#56.#81;	//  scala/actors/Actor.link:(Lscala/actors/AbstractActor;)Lscala/actors/AbstractActor;
const #83 = Asciz	to;
const #84 = Asciz	Lscala/actors/AbstractActor;;
const #85 = Asciz	loopWhile;
const #86 = Asciz	(Lscala/Function0;Lscala/Function0;)V;
const #87 = Asciz	scala/Function0;
const #88 = class	#87;	//  scala/Function0
const #89 = Asciz	apply;
const #90 = Asciz	()Ljava/lang/Object;;
const #91 = NameAndType	#89:#90;//  apply:()Ljava/lang/Object;
const #92 = InterfaceMethod	#88.#91;	//  scala/Function0.apply:()Ljava/lang/Object;
const #93 = Asciz	scala/runtime/BoxesRunTime;
const #94 = class	#93;	//  scala/runtime/BoxesRunTime
const #95 = Asciz	unboxToBoolean;
const #96 = Asciz	(Ljava/lang/Object;)Z;
const #97 = NameAndType	#95:#96;//  unboxToBoolean:(Ljava/lang/Object;)Z
const #98 = Method	#94.#97;	//  scala/runtime/BoxesRunTime.unboxToBoolean:(Ljava/lang/Object;)Z
const #99 = Asciz	scala/actors/Actor$$anon$7;
const #100 = class	#99;	//  scala/actors/Actor$$anon$7
const #101 = Asciz	(Lscala/Function0;)V;
const #102 = NameAndType	#11:#101;//  "<init>":(Lscala/Function0;)V
const #103 = Method	#100.#102;	//  scala/actors/Actor$$anon$7."<init>":(Lscala/Function0;)V
const #104 = Asciz	scala/actors/Actor$Body;
const #105 = class	#104;	//  scala/actors/Actor$Body
const #106 = Asciz	scala/actors/Actor$$anonfun$loopWhile$1;
const #107 = class	#106;	//  scala/actors/Actor$$anonfun$loopWhile$1
const #108 = NameAndType	#11:#86;//  "<init>":(Lscala/Function0;Lscala/Function0;)V
const #109 = Method	#107.#108;	//  scala/actors/Actor$$anonfun$loopWhile$1."<init>":(Lscala/Function0;Lscala/Function0;)V
const #110 = Asciz	andThen;
const #111 = NameAndType	#110:#101;//  andThen:(Lscala/Function0;)V
const #112 = InterfaceMethod	#105.#111;	//  scala/actors/Actor$Body.andThen:(Lscala/Function0;)V
const #113 = Asciz	cond$1;
const #114 = Asciz	body$5;
const #115 = Asciz	(Lscala/Function0<Ljava/lang/Boolean;>;Lscala/Function0<Ljava/lang/Object;>;)V;
const #116 = Asciz	loop;
const #117 = Asciz	scala/actors/Actor$$anonfun$loop$1;
const #118 = class	#117;	//  scala/actors/Actor$$anonfun$loop$1
const #119 = Method	#118.#102;	//  scala/actors/Actor$$anonfun$loop$1."<init>":(Lscala/Function0;)V
const #120 = Asciz	body$4;
const #121 = Asciz	(Lscala/Function0<Ljava/lang/Object;>;)V;
const #122 = Asciz	mkBody;
const #123 = Asciz	(Lscala/Function0;)Ljava/lang/Object;;
const #124 = Asciz	body$3;
const #125 = Asciz	<a:Ljava/lang/Object;>(Lscala/Function0<Ta;>;)Ljava/lang/Object;;
const #126 = Asciz	respondOn;
const #127 = Asciz	(Lscala/Function1;)Lscala/Function1;;
const #128 = Asciz	scala/actors/Actor$$anonfun$respondOn$1;
const #129 = class	#128;	//  scala/actors/Actor$$anonfun$respondOn$1
const #130 = Asciz	(Lscala/Function1;)V;
const #131 = NameAndType	#11:#130;//  "<init>":(Lscala/Function1;)V
const #132 = Method	#129.#131;	//  scala/actors/Actor$$anonfun$respondOn$1."<init>":(Lscala/Function1;)V
const #133 = Asciz	fun$1;
const #134 = Asciz	Lscala/Function1;;
const #135 = Asciz	<A:Ljava/lang/Object;B:Ljava/lang/Object;>(Lscala/Function1<Lscala/PartialFunction<TA;Ljava/lang/Object;>;Lscala/runtime/Nothing$;>;)Lscala/Function1<Lscala/PartialFunction<TA;TB;>;Lscala/Responder<TB;>;>;;
const #136 = Asciz	mailboxSize;
const #137 = Asciz	()I;
const #138 = Asciz	rawSelf;
const #139 = Asciz	()Lscala/actors/Reactor;;
const #140 = NameAndType	#138:#139;//  rawSelf:()Lscala/actors/Reactor;
const #141 = Method	#10.#140;	//  scala/actors/Actor$.rawSelf:()Lscala/actors/Reactor;
const #142 = Asciz	scala/actors/Reactor;
const #143 = class	#142;	//  scala/actors/Reactor
const #144 = NameAndType	#136:#137;//  mailboxSize:()I
const #145 = InterfaceMethod	#143.#144;	//  scala/actors/Reactor.mailboxSize:()I
const #146 = Asciz	reply;
const #147 = Asciz	scala/actors/ReplyReactor;
const #148 = class	#147;	//  scala/actors/ReplyReactor
const #149 = Asciz	scala/runtime/BoxedUnit;
const #150 = class	#149;	//  scala/runtime/BoxedUnit
const #151 = Asciz	UNIT;
const #152 = Asciz	Lscala/runtime/BoxedUnit;;
const #153 = NameAndType	#151:#152;//  UNIT:Lscala/runtime/BoxedUnit;
const #154 = Field	#150.#153;	//  scala/runtime/BoxedUnit.UNIT:Lscala/runtime/BoxedUnit;
const #155 = Asciz	(Ljava/lang/Object;)V;
const #156 = NameAndType	#146:#155;//  reply:(Ljava/lang/Object;)V
const #157 = InterfaceMethod	#148.#156;	//  scala/actors/ReplyReactor.reply:(Ljava/lang/Object;)V
const #158 = Asciz	msg;
const #159 = Asciz	sender;
const #160 = Asciz	()Lscala/actors/OutputChannel;;
const #161 = NameAndType	#159:#160;//  sender:()Lscala/actors/OutputChannel;
const #162 = InterfaceMethod	#148.#161;	//  scala/actors/ReplyReactor.sender:()Lscala/actors/OutputChannel;
const #163 = Asciz	()Lscala/actors/OutputChannel<Ljava/lang/Object;>;;
const #164 = Asciz	eventloop;
const #165 = Asciz	(Lscala/PartialFunction;)Lscala/runtime/Nothing$;;
const #166 = Asciz	scala/actors/Actor$RecursiveProxyHandler;
const #167 = class	#166;	//  scala/actors/Actor$RecursiveProxyHandler
const #168 = Asciz	(Lscala/actors/Reactor;Lscala/PartialFunction;)V;
const #169 = NameAndType	#11:#168;//  "<init>":(Lscala/actors/Reactor;Lscala/PartialFunction;)V
const #170 = Method	#167.#169;	//  scala/actors/Actor$RecursiveProxyHandler."<init>":(Lscala/actors/Reactor;Lscala/PartialFunction;)V
const #171 = Asciz	react;
const #172 = NameAndType	#171:#165;//  react:(Lscala/PartialFunction;)Lscala/runtime/Nothing$;
const #173 = InterfaceMethod	#143.#172;	//  scala/actors/Reactor.react:(Lscala/PartialFunction;)Lscala/runtime/Nothing$;
const #174 = Asciz	f;
const #175 = Asciz	Lscala/PartialFunction;;
const #176 = Asciz	(Lscala/PartialFunction<Ljava/lang/Object;Ljava/lang/Object;>;)Lscala/runtime/Nothing$;;
const #177 = Asciz	reactWithin;
const #178 = Asciz	(JLscala/PartialFunction;)Lscala/runtime/Nothing$;;
const #179 = NameAndType	#177:#178;//  reactWithin:(JLscala/PartialFunction;)Lscala/runtime/Nothing$;
const #180 = InterfaceMethod	#56.#179;	//  scala/actors/Actor.reactWithin:(JLscala/PartialFunction;)Lscala/runtime/Nothing$;
const #181 = Asciz	msec;
const #182 = Asciz	J;
const #183 = Asciz	(JLscala/PartialFunction<Ljava/lang/Object;Ljava/lang/Object;>;)Lscala/runtime/Nothing$;;
const #184 = Asciz	receiveWithin;
const #185 = Asciz	(JLscala/PartialFunction;)Ljava/lang/Object;;
const #186 = NameAndType	#184:#185;//  receiveWithin:(JLscala/PartialFunction;)Ljava/lang/Object;
const #187 = InterfaceMethod	#56.#186;	//  scala/actors/Actor.receiveWithin:(JLscala/PartialFunction;)Ljava/lang/Object;
const #188 = Asciz	<R:Ljava/lang/Object;>(JLscala/PartialFunction<Ljava/lang/Object;TR;>;)TR;;
const #189 = Asciz	receive;
const #190 = Asciz	(Lscala/PartialFunction;)Ljava/lang/Object;;
const #191 = NameAndType	#189:#190;//  receive:(Lscala/PartialFunction;)Ljava/lang/Object;
const #192 = InterfaceMethod	#56.#191;	//  scala/actors/Actor.receive:(Lscala/PartialFunction;)Ljava/lang/Object;
const #193 = Asciz	<A:Ljava/lang/Object;>(Lscala/PartialFunction<Ljava/lang/Object;TA;>;)TA;;
const #194 = Asciz	$qmark;
const #195 = NameAndType	#194:#90;//  $qmark:()Ljava/lang/Object;
const #196 = InterfaceMethod	#56.#195;	//  scala/actors/Actor.$qmark:()Ljava/lang/Object;
const #197 = Asciz	reactor;
const #198 = Asciz	scala/actors/Actor$$anon$2;
const #199 = class	#198;	//  scala/actors/Actor$$anon$2
const #200 = Method	#199.#102;	//  scala/actors/Actor$$anon$2."<init>":(Lscala/Function0;)V
const #201 = Asciz	start;
const #202 = NameAndType	#201:#52;//  start:()Lscala/actors/Actor;
const #203 = InterfaceMethod	#56.#202;	//  scala/actors/Actor.start:()Lscala/actors/Actor;
const #204 = Asciz	body$2;
const #205 = Asciz	a;
const #206 = Asciz	(Lscala/Function0<Lscala/Responder<Ljava/lang/Object;>;>;)Lscala/actors/Actor;;
const #207 = Asciz	actor;
const #208 = Asciz	scala/actors/Actor$$anon$1;
const #209 = class	#208;	//  scala/actors/Actor$$anon$1
const #210 = Method	#209.#102;	//  scala/actors/Actor$$anon$1."<init>":(Lscala/Function0;)V
const #211 = Asciz	body$1;
const #212 = Asciz	clearSelf;
const #213 = Asciz	()Ljava/lang/ThreadLocal;;
const #214 = NameAndType	#18:#213;//  tl:()Ljava/lang/ThreadLocal;
const #215 = Method	#10.#214;	//  scala/actors/Actor$.tl:()Ljava/lang/ThreadLocal;
const #216 = Asciz	set;
const #217 = NameAndType	#216:#155;//  set:(Ljava/lang/Object;)V
const #218 = Method	#29.#217;	//  java/lang/ThreadLocal.set:(Ljava/lang/Object;)V
const #219 = Asciz	resetProxy;
const #220 = Asciz	get;
const #221 = NameAndType	#220:#90;//  get:()Ljava/lang/Object;
const #222 = Method	#29.#221;	//  java/lang/ThreadLocal.get:()Ljava/lang/Object;
const #223 = Asciz	scala/actors/ActorProxy;
const #224 = class	#223;	//  scala/actors/ActorProxy
const #225 = Asciz	java/lang/Thread;
const #226 = class	#225;	//  java/lang/Thread
const #227 = Asciz	currentThread;
const #228 = Asciz	()Ljava/lang/Thread;;
const #229 = NameAndType	#227:#228;//  currentThread:()Ljava/lang/Thread;
const #230 = Method	#226.#229;	//  java/lang/Thread.currentThread:()Ljava/lang/Thread;
const #231 = Asciz	scala$actors$Actor$$parentScheduler;
const #232 = Asciz	()Lscala/actors/IScheduler;;
const #233 = NameAndType	#231:#232;//  scala$actors$Actor$$parentScheduler:()Lscala/actors/IScheduler;
const #234 = Method	#10.#233;	//  scala/actors/Actor$.scala$actors$Actor$$parentScheduler:()Lscala/actors/IScheduler;
const #235 = Asciz	(Ljava/lang/Thread;Lscala/actors/IScheduler;)V;
const #236 = NameAndType	#11:#235;//  "<init>":(Ljava/lang/Thread;Lscala/actors/IScheduler;)V
const #237 = Method	#224.#236;	//  scala/actors/ActorProxy."<init>":(Ljava/lang/Thread;Lscala/actors/IScheduler;)V
const #238 = Asciz	Lscala/actors/Reactor;;
const #239 = Asciz	scala/actors/Scheduler$;
const #240 = class	#239;	//  scala/actors/Scheduler$
const #241 = Asciz	Lscala/actors/Scheduler$;;
const #242 = NameAndType	#4:#241;//  MODULE$:Lscala/actors/Scheduler$;
const #243 = Field	#240.#242;	//  scala/actors/Scheduler$.MODULE$:Lscala/actors/Scheduler$;
const #244 = Asciz	scheduler;
const #245 = NameAndType	#244:#232;//  scheduler:()Lscala/actors/IScheduler;
const #246 = InterfaceMethod	#143.#245;	//  scala/actors/Reactor.scheduler:()Lscala/actors/IScheduler;
const #247 = Asciz	s;
const #248 = Asciz	(Lscala/actors/IScheduler;)Lscala/actors/Reactor;;
const #249 = Asciz	sched;
const #250 = Asciz	Lscala/actors/IScheduler;;
const #251 = Asciz	r;
const #252 = Asciz	Lscala/actors/ActorProxy;;
const #253 = NameAndType	#138:#248;//  rawSelf:(Lscala/actors/IScheduler;)Lscala/actors/Reactor;
const #254 = Method	#10.#253;	//  scala/actors/Actor$.rawSelf:(Lscala/actors/IScheduler;)Lscala/actors/Reactor;
const #255 = Asciz	(Lscala/actors/IScheduler;)Lscala/actors/Actor;;
const #256 = NameAndType	#51:#255;//  self:(Lscala/actors/IScheduler;)Lscala/actors/Actor;
const #257 = Method	#10.#256;	//  scala/actors/Actor$.self:(Lscala/actors/IScheduler;)Lscala/actors/Actor;
const #258 = Asciz	()Lscala/actors/SuspendActorException;;
const #259 = Asciz	()Ljava/util/Timer;;
const #260 = Asciz	()Ljava/lang/ThreadLocal<Lscala/actors/Reactor;>;;
const #261 = Asciz	InnerClasses;
const #262 = Asciz	Body;
const #263 = Asciz	scala/actors/Actor$$anon$3;
const #264 = class	#263;	//  scala/actors/Actor$$anon$3
const #265 = Asciz	$anon$3;
const #266 = Asciz	scala/actors/Actor$$anon$6;
const #267 = class	#266;	//  scala/actors/Actor$$anon$6
const #268 = Asciz	$anon$6;
const #269 = Asciz	scala/actors/Actor$$anon$5;
const #270 = class	#269;	//  scala/actors/Actor$$anon$5
const #271 = Asciz	$anon$5;
const #272 = Asciz	$anon$1;
const #273 = Asciz	$anon$2;
const #274 = Asciz	$anon$7;
const #275 = Asciz	scala/actors/Actor$$anonfun$9;
const #276 = class	#275;	//  scala/actors/Actor$$anonfun$9
const #277 = Asciz	$anonfun$9;
const #278 = Asciz	scala/actors/Actor$$anonfun$8;
const #279 = class	#278;	//  scala/actors/Actor$$anonfun$8
const #280 = Asciz	$anonfun$8;
const #281 = Asciz	scala/actors/Actor$$anonfun$7;
const #282 = class	#281;	//  scala/actors/Actor$$anonfun$7
const #283 = Asciz	$anonfun$7;
const #284 = Asciz	scala/actors/Actor$$anonfun$6;
const #285 = class	#284;	//  scala/actors/Actor$$anonfun$6
const #286 = Asciz	$anonfun$6;
const #287 = Asciz	scala/actors/Actor$$anonfun$5;
const #288 = class	#287;	//  scala/actors/Actor$$anonfun$5
const #289 = Asciz	$anonfun$5;
const #290 = Asciz	scala/actors/Actor$$anonfun$4;
const #291 = class	#290;	//  scala/actors/Actor$$anonfun$4
const #292 = Asciz	$anonfun$4;
const #293 = Asciz	scala/actors/Actor$$anonfun$3;
const #294 = class	#293;	//  scala/actors/Actor$$anonfun$3
const #295 = Asciz	$anonfun$3;
const #296 = Asciz	scala/actors/Actor$$anonfun$2;
const #297 = class	#296;	//  scala/actors/Actor$$anonfun$2
const #298 = Asciz	$anonfun$2;
const #299 = Asciz	scala/actors/Actor$$anonfun$1;
const #300 = class	#299;	//  scala/actors/Actor$$anonfun$1
const #301 = Asciz	$anonfun$1;
const #302 = Asciz	scala/actors/Actor$$anonfun$12;
const #303 = class	#302;	//  scala/actors/Actor$$anonfun$12
const #304 = Asciz	$anonfun$12;
const #305 = Asciz	scala/actors/Actor$$anonfun$11;
const #306 = class	#305;	//  scala/actors/Actor$$anonfun$11
const #307 = Asciz	$anonfun$11;
const #308 = Asciz	scala/actors/Actor$$anonfun$10;
const #309 = class	#308;	//  scala/actors/Actor$$anonfun$10
const #310 = Asciz	$anonfun$10;
const #311 = Asciz	scala/actors/Actor$$anonfun$link$2;
const #312 = class	#311;	//  scala/actors/Actor$$anonfun$link$2
const #313 = Asciz	$anonfun$link$2;
const #314 = Asciz	scala/actors/Actor$$anonfun$link$1;
const #315 = class	#314;	//  scala/actors/Actor$$anonfun$link$1
const #316 = Asciz	$anonfun$link$1;
const #317 = Asciz	$anonfun$loop$1;
const #318 = Asciz	scala/actors/Actor$$anonfun$react$2;
const #319 = class	#318;	//  scala/actors/Actor$$anonfun$react$2
const #320 = Asciz	$anonfun$react$2;
const #321 = Asciz	scala/actors/Actor$$anonfun$react$1;
const #322 = class	#321;	//  scala/actors/Actor$$anonfun$react$1
const #323 = Asciz	$anonfun$react$1;
const #324 = Asciz	scala/actors/Actor$$anonfun$unlink$1;
const #325 = class	#324;	//  scala/actors/Actor$$anonfun$unlink$1
const #326 = Asciz	$anonfun$unlink$1;
const #327 = Asciz	scala/actors/Actor$$anonfun$$qmark$1;
const #328 = class	#327;	//  scala/actors/Actor$$anonfun$$qmark$1
const #329 = Asciz	$anonfun$$qmark$1;
const #330 = Asciz	scala/actors/Actor$$anonfun$receive$2;
const #331 = class	#330;	//  scala/actors/Actor$$anonfun$receive$2
const #332 = Asciz	$anonfun$receive$2;
const #333 = Asciz	scala/actors/Actor$$anonfun$receive$1;
const #334 = class	#333;	//  scala/actors/Actor$$anonfun$receive$1
const #335 = Asciz	$anonfun$receive$1;
const #336 = Asciz	$anonfun$respondOn$1;
const #337 = Asciz	$anonfun$loopWhile$1;
const #338 = Asciz	scala/actors/Actor$$anonfun$exitLinked$1;
const #339 = class	#338;	//  scala/actors/Actor$$anonfun$exitLinked$1
const #340 = Asciz	$anonfun$exitLinked$1;
const #341 = Asciz	scala/actors/Actor$$anonfun$unlinkFrom$1;
const #342 = class	#341;	//  scala/actors/Actor$$anonfun$unlinkFrom$1
const #343 = Asciz	$anonfun$unlinkFrom$1;
const #344 = Asciz	RecursiveProxyHandler;
const #345 = Asciz	scala/actors/Actor$$anonfun$reactWithin$2;
const #346 = class	#345;	//  scala/actors/Actor$$anonfun$reactWithin$2
const #347 = Asciz	$anonfun$reactWithin$2;
const #348 = Asciz	scala/actors/Actor$$anonfun$reactWithin$1;
const #349 = class	#348;	//  scala/actors/Actor$$anonfun$reactWithin$1
const #350 = Asciz	$anonfun$reactWithin$1;
const #351 = Asciz	scala/actors/Actor$$anonfun$startSearch$1;
const #352 = class	#351;	//  scala/actors/Actor$$anonfun$startSearch$1
const #353 = Asciz	$anonfun$startSearch$1;
const #354 = Asciz	scala/actors/Actor$$anonfun$receiveWithin$2;
const #355 = class	#354;	//  scala/actors/Actor$$anonfun$receiveWithin$2
const #356 = Asciz	$anonfun$receiveWithin$2;
const #357 = Asciz	scala/actors/Actor$$anonfun$receiveWithin$1;
const #358 = class	#357;	//  scala/actors/Actor$$anonfun$receiveWithin$1
const #359 = Asciz	$anonfun$receiveWithin$1;
const #360 = Asciz	scala/ScalaObject;
const #361 = class	#360;	//  scala/ScalaObject

{
public static final scala.actors.Actor$ MODULE$;

public static {};
  Code:
   Stack=1, Locals=0, Args_size=0
   0:	new	#10; //class scala/actors/Actor$
   3:	invokespecial	#13; //Method "<init>":()V
   6:	return

public void continue();
  Code:
   Stack=2, Locals=1, Args_size=1
   0:	new	#47; //class scala/actors/KillActorException
   3:	dup
   4:	invokespecial	#48; //Method scala/actors/KillActorException."<init>":()V
   7:	athrow
  LineNumberTable: 
   line 353: 0


public scala.runtime.Nothing$ exit();
  Code:
   Stack=1, Locals=1, Args_size=1
   0:	aload_0
   1:	invokevirtual	#54; //Method self:()Lscala/actors/Actor;
   4:	invokeinterface	#58,  1; //InterfaceMethod scala/actors/Actor.exit:()Lscala/runtime/Nothing$;
   9:	areturn
  LineNumberTable: 
   line 351: 0


public scala.runtime.Nothing$ exit(java.lang.Object);
  Code:
   Stack=2, Locals=2, Args_size=2
   0:	aload_0
   1:	invokevirtual	#54; //Method self:()Lscala/actors/Actor;
   4:	aload_1
   5:	invokeinterface	#61,  2; //InterfaceMethod scala/actors/Actor.exit:(Ljava/lang/Object;)Lscala/runtime/Nothing$;
   10:	areturn
  LineNumberTable: 
   line 338: 0

  LocalVariableTable: 
   Start  Length  Slot  Name   Signature
   0      11      0    this       Lscala/actors/Actor$;
   0      11      1    reason       Ljava/lang/Object;


public void unlink(scala.actors.Actor);
  Code:
   Stack=2, Locals=2, Args_size=2
   0:	aload_0
   1:	invokevirtual	#54; //Method self:()Lscala/actors/Actor;
   4:	aload_1
   5:	invokeinterface	#70,  2; //InterfaceMethod scala/actors/Actor.unlink:(Lscala/actors/AbstractActor;)V
   10:	return
  LineNumberTable: 
   line 319: 0

  LocalVariableTable: 
   Start  Length  Slot  Name   Signature
   0      11      0    this       Lscala/actors/Actor$;
   0      11      1    from       Lscala/actors/Actor;


public scala.actors.Actor link(scala.Function0);
  Code:
   Stack=2, Locals=2, Args_size=2
   0:	aload_0
   1:	invokevirtual	#54; //Method self:()Lscala/actors/Actor;
   4:	aload_1
   5:	invokeinterface	#76,  2; //InterfaceMethod scala/actors/Actor.link:(Lscala/Function0;)Lscala/actors/Actor;
   10:	areturn
  LineNumberTable: 
   line 312: 0

  LocalVariableTable: 
   Start  Length  Slot  Name   Signature
   0      11      0    this       Lscala/actors/Actor$;
   0      11      1    body       Lscala/Function0;

  Signature: length = 0x2
   00 4F 

public scala.actors.AbstractActor link(scala.actors.AbstractActor);
  Code:
   Stack=2, Locals=2, Args_size=2
   0:	aload_0
   1:	invokevirtual	#54; //Method self:()Lscala/actors/Actor;
   4:	aload_1
   5:	invokeinterface	#82,  2; //InterfaceMethod scala/actors/Actor.link:(Lscala/actors/AbstractActor;)Lscala/actors/AbstractActor;
   10:	areturn
  LineNumberTable: 
   line 304: 0

  LocalVariableTable: 
   Start  Length  Slot  Name   Signature
   0      11      0    this       Lscala/actors/Actor$;
   0      11      1    to       Lscala/actors/AbstractActor;


public void loopWhile(scala.Function0, scala.Function0);
  Code:
   Stack=5, Locals=3, Args_size=3
   0:	aload_1
   1:	invokeinterface	#92,  1; //InterfaceMethod scala/Function0.apply:()Ljava/lang/Object;
   6:	invokestatic	#98; //Method scala/runtime/BoxesRunTime.unboxToBoolean:(Ljava/lang/Object;)Z
   9:	ifeq	38
   12:	new	#100; //class scala/actors/Actor$$anon$7
   15:	dup
   16:	aload_2
   17:	invokespecial	#103; //Method scala/actors/Actor$$anon$7."<init>":(Lscala/Function0;)V
   20:	checkcast	#105; //class scala/actors/Actor$Body
   23:	new	#107; //class scala/actors/Actor$$anonfun$loopWhile$1
   26:	dup
   27:	aload_1
   28:	aload_2
   29:	invokespecial	#109; //Method scala/actors/Actor$$anonfun$loopWhile$1."<init>":(Lscala/Function0;Lscala/Function0;)V
   32:	invokeinterface	#112,  2; //InterfaceMethod scala/actors/Actor$Body.andThen:(Lscala/Function0;)V
   37:	return
   38:	new	#47; //class scala/actors/KillActorException
   41:	dup
   42:	invokespecial	#48; //Method scala/actors/KillActorException."<init>":()V
   45:	athrow
  LineNumberTable: 
   line 295: 0
   line 296: 38

  LocalVariableTable: 
   Start  Length  Slot  Name   Signature
   0      46      0    this       Lscala/actors/Actor$;
   0      46      1    cond$1       Lscala/Function0;
   0      46      2    body$5       Lscala/Function0;

  Signature: length = 0x2
   00 73 

public void loop(scala.Function0);
  Code:
   Stack=4, Locals=2, Args_size=2
   0:	new	#100; //class scala/actors/Actor$$anon$7
   3:	dup
   4:	aload_1
   5:	invokespecial	#103; //Method scala/actors/Actor$$anon$7."<init>":(Lscala/Function0;)V
   8:	checkcast	#105; //class scala/actors/Actor$Body
   11:	new	#118; //class scala/actors/Actor$$anonfun$loop$1
   14:	dup
   15:	aload_1
   16:	invokespecial	#119; //Method scala/actors/Actor$$anonfun$loop$1."<init>":(Lscala/Function0;)V
   19:	invokeinterface	#112,  2; //InterfaceMethod scala/actors/Actor$Body.andThen:(Lscala/Function0;)V
   24:	return
  LineNumberTable: 
   line 284: 0

  LocalVariableTable: 
   Start  Length  Slot  Name   Signature
   0      25      0    this       Lscala/actors/Actor$;
   0      25      1    body$4       Lscala/Function0;

  Signature: length = 0x2
   00 79 

public java.lang.Object mkBody(scala.Function0);
  Code:
   Stack=3, Locals=2, Args_size=2
   0:	new	#100; //class scala/actors/Actor$$anon$7
   3:	dup
   4:	aload_1
   5:	invokespecial	#103; //Method scala/actors/Actor$$anon$7."<init>":(Lscala/Function0;)V
   8:	areturn
  LineNumberTable: 
   line 274: 0

  LocalVariableTable: 
   Start  Length  Slot  Name   Signature
   0      9      0    this       Lscala/actors/Actor$;
   0      9      1    body$3       Lscala/Function0;

  Signature: length = 0x2
   00 7D 

public scala.Function1 respondOn(scala.Function1);
  Code:
   Stack=3, Locals=2, Args_size=2
   0:	new	#129; //class scala/actors/Actor$$anonfun$respondOn$1
   3:	dup
   4:	aload_1
   5:	invokespecial	#132; //Method scala/actors/Actor$$anonfun$respondOn$1."<init>":(Lscala/Function1;)V
   8:	areturn
  LineNumberTable: 
   line 266: 0

  LocalVariableTable: 
   Start  Length  Slot  Name   Signature
   0      9      0    this       Lscala/actors/Actor$;
   0      9      1    fun$1       Lscala/Function1;

  Signature: length = 0x2
   00 FFFFFF87 

public int mailboxSize();
  Code:
   Stack=1, Locals=1, Args_size=1
   0:	aload_0
   1:	invokevirtual	#141; //Method rawSelf:()Lscala/actors/Reactor;
   4:	invokeinterface	#145,  1; //InterfaceMethod scala/actors/Reactor.mailboxSize:()I
   9:	ireturn
  LineNumberTable: 
   line 246: 0


public void reply();
  Code:
   Stack=2, Locals=1, Args_size=1
   0:	aload_0
   1:	invokevirtual	#141; //Method rawSelf:()Lscala/actors/Reactor;
   4:	checkcast	#148; //class scala/actors/ReplyReactor
   7:	getstatic	#154; //Field scala/runtime/BoxedUnit.UNIT:Lscala/runtime/BoxedUnit;
   10:	invokeinterface	#157,  2; //InterfaceMethod scala/actors/ReplyReactor.reply:(Ljava/lang/Object;)V
   15:	return
  LineNumberTable: 
   line 239: 0


public void reply(java.lang.Object);
  Code:
   Stack=2, Locals=2, Args_size=2
   0:	aload_0
   1:	invokevirtual	#141; //Method rawSelf:()Lscala/actors/Reactor;
   4:	checkcast	#148; //class scala/actors/ReplyReactor
   7:	aload_1
   8:	invokeinterface	#157,  2; //InterfaceMethod scala/actors/ReplyReactor.reply:(Ljava/lang/Object;)V
   13:	return
  LineNumberTable: 
   line 232: 0

  LocalVariableTable: 
   Start  Length  Slot  Name   Signature
   0      14      0    this       Lscala/actors/Actor$;
   0      14      1    msg       Ljava/lang/Object;


public scala.actors.OutputChannel sender();
  Code:
   Stack=1, Locals=1, Args_size=1
   0:	aload_0
   1:	invokevirtual	#141; //Method rawSelf:()Lscala/actors/Reactor;
   4:	checkcast	#148; //class scala/actors/ReplyReactor
   7:	invokeinterface	#162,  1; //InterfaceMethod scala/actors/ReplyReactor.sender:()Lscala/actors/OutputChannel;
   12:	areturn
  LineNumberTable: 
   line 225: 0

  Signature: length = 0x2
   00 FFFFFFA3 

public scala.runtime.Nothing$ eventloop(scala.PartialFunction);
  Code:
   Stack=5, Locals=2, Args_size=2
   0:	aload_0
   1:	invokevirtual	#141; //Method rawSelf:()Lscala/actors/Reactor;
   4:	new	#167; //class scala/actors/Actor$RecursiveProxyHandler
   7:	dup
   8:	aload_0
   9:	invokevirtual	#141; //Method rawSelf:()Lscala/actors/Reactor;
   12:	aload_1
   13:	invokespecial	#170; //Method scala/actors/Actor$RecursiveProxyHandler."<init>":(Lscala/actors/Reactor;Lscala/PartialFunction;)V
   16:	invokeinterface	#173,  2; //InterfaceMethod scala/actors/Reactor.react:(Lscala/PartialFunction;)Lscala/runtime/Nothing$;
   21:	areturn
  LineNumberTable: 
   line 209: 0

  LocalVariableTable: 
   Start  Length  Slot  Name   Signature
   0      22      0    this       Lscala/actors/Actor$;
   0      22      1    f       Lscala/PartialFunction;

  Signature: length = 0x2
   00 FFFFFFB0 

public scala.runtime.Nothing$ reactWithin(long, scala.PartialFunction);
  Code:
   Stack=4, Locals=4, Args_size=3
   0:	aload_0
   1:	invokevirtual	#54; //Method self:()Lscala/actors/Actor;
   4:	lload_1
   5:	aload_3
   6:	invokeinterface	#180,  4; //InterfaceMethod scala/actors/Actor.reactWithin:(JLscala/PartialFunction;)Lscala/runtime/Nothing$;
   11:	areturn
  LineNumberTable: 
   line 206: 0

  LocalVariableTable: 
   Start  Length  Slot  Name   Signature
   0      12      0    this       Lscala/actors/Actor$;
   0      12      1    msec       J
   0      12      3    f       Lscala/PartialFunction;

  Signature: length = 0x2
   00 FFFFFFB7 

public scala.runtime.Nothing$ react(scala.PartialFunction);
  Code:
   Stack=2, Locals=2, Args_size=2
   0:	aload_0
   1:	invokevirtual	#141; //Method rawSelf:()Lscala/actors/Reactor;
   4:	aload_1
   5:	invokeinterface	#173,  2; //InterfaceMethod scala/actors/Reactor.react:(Lscala/PartialFunction;)Lscala/runtime/Nothing$;
   10:	areturn
  LineNumberTable: 
   line 192: 0

  LocalVariableTable: 
   Start  Length  Slot  Name   Signature
   0      11      0    this       Lscala/actors/Actor$;
   0      11      1    f       Lscala/PartialFunction;

  Signature: length = 0x2
   00 FFFFFFB0 

public java.lang.Object receiveWithin(long, scala.PartialFunction);
  Code:
   Stack=4, Locals=4, Args_size=3
   0:	aload_0
   1:	invokevirtual	#54; //Method self:()Lscala/actors/Actor;
   4:	lload_1
   5:	aload_3
   6:	invokeinterface	#187,  4; //InterfaceMethod scala/actors/Actor.receiveWithin:(JLscala/PartialFunction;)Ljava/lang/Object;
   11:	areturn
  LineNumberTable: 
   line 179: 0

  LocalVariableTable: 
   Start  Length  Slot  Name   Signature
   0      12      0    this       Lscala/actors/Actor$;
   0      12      1    msec       J
   0      12      3    f       Lscala/PartialFunction;

  Signature: length = 0x2
   00 FFFFFFBC 

public java.lang.Object receive(scala.PartialFunction);
  Code:
   Stack=2, Locals=2, Args_size=2
   0:	aload_0
   1:	invokevirtual	#54; //Method self:()Lscala/actors/Actor;
   4:	aload_1
   5:	invokeinterface	#192,  2; //InterfaceMethod scala/actors/Actor.receive:(Lscala/PartialFunction;)Ljava/lang/Object;
   10:	areturn
  LineNumberTable: 
   line 164: 0

  LocalVariableTable: 
   Start  Length  Slot  Name   Signature
   0      11      0    this       Lscala/actors/Actor$;
   0      11      1    f       Lscala/PartialFunction;

  Signature: length = 0x2
   00 FFFFFFC1 

public java.lang.Object $qmark();
  Code:
   Stack=1, Locals=1, Args_size=1
   0:	aload_0
   1:	invokevirtual	#54; //Method self:()Lscala/actors/Actor;
   4:	invokeinterface	#196,  1; //InterfaceMethod scala/actors/Actor.$qmark:()Ljava/lang/Object;
   9:	areturn
  LineNumberTable: 
   line 153: 0


public scala.actors.Actor reactor(scala.Function0);
  Code:
   Stack=3, Locals=3, Args_size=2
   0:	new	#199; //class scala/actors/Actor$$anon$2
   3:	dup
   4:	aload_1
   5:	invokespecial	#200; //Method scala/actors/Actor$$anon$2."<init>":(Lscala/Function0;)V
   8:	astore_2
   9:	aload_2
   10:	checkcast	#56; //class scala/actors/Actor
   13:	invokeinterface	#203,  1; //InterfaceMethod scala/actors/Actor.start:()Lscala/actors/Actor;
   18:	pop
   19:	aload_2
   20:	checkcast	#56; //class scala/actors/Actor
   23:	areturn
  LineNumberTable: 
   line 139: 0
   line 146: 9
   line 145: 10
   line 146: 19

  LocalVariableTable: 
   Start  Length  Slot  Name   Signature
   0      24      0    this       Lscala/actors/Actor$;
   0      24      1    body$2       Lscala/Function0;
   9      14      2    a       Ljava/lang/Object;

  Signature: length = 0x2
   00 FFFFFFCE 

public scala.actors.Actor actor(scala.Function0);
  Code:
   Stack=3, Locals=3, Args_size=2
   0:	new	#209; //class scala/actors/Actor$$anon$1
   3:	dup
   4:	aload_1
   5:	invokespecial	#210; //Method scala/actors/Actor$$anon$1."<init>":(Lscala/Function0;)V
   8:	astore_2
   9:	aload_2
   10:	checkcast	#56; //class scala/actors/Actor
   13:	invokeinterface	#203,  1; //InterfaceMethod scala/actors/Actor.start:()Lscala/actors/Actor;
   18:	pop
   19:	aload_2
   20:	checkcast	#56; //class scala/actors/Actor
   23:	areturn
  LineNumberTable: 
   line 107: 0
   line 112: 9
   line 111: 10
   line 112: 19

  LocalVariableTable: 
   Start  Length  Slot  Name   Signature
   0      24      0    this       Lscala/actors/Actor$;
   0      24      1    body$1       Lscala/Function0;
   9      14      2    a       Ljava/lang/Object;

  Signature: length = 0x2
   00 4F 

public void clearSelf();
  Code:
   Stack=2, Locals=1, Args_size=1
   0:	aload_0
   1:	invokevirtual	#215; //Method tl:()Ljava/lang/ThreadLocal;
   4:	aconst_null
   5:	invokevirtual	#218; //Method java/lang/ThreadLocal.set:(Ljava/lang/Object;)V
   8:	return
  LineNumberTable: 
   line 87: 0


public void resetProxy();
  Code:
   Stack=5, Locals=2, Args_size=1
   0:	aload_0
   1:	getfield	#32; //Field tl:Ljava/lang/ThreadLocal;
   4:	invokevirtual	#222; //Method java/lang/ThreadLocal.get:()Ljava/lang/Object;
   7:	checkcast	#143; //class scala/actors/Reactor
   10:	astore_1
   11:	aload_1
   12:	ifnull	43
   15:	aload_1
   16:	instanceof	#224; //class scala/actors/ActorProxy
   19:	ifeq	43
   22:	aload_0
   23:	getfield	#32; //Field tl:Ljava/lang/ThreadLocal;
   26:	new	#224; //class scala/actors/ActorProxy
   29:	dup
   30:	invokestatic	#230; //Method java/lang/Thread.currentThread:()Ljava/lang/Thread;
   33:	aload_0
   34:	invokevirtual	#234; //Method scala$actors$Actor$$parentScheduler:()Lscala/actors/IScheduler;
   37:	invokespecial	#237; //Method scala/actors/ActorProxy."<init>":(Ljava/lang/Thread;Lscala/actors/IScheduler;)V
   40:	invokevirtual	#218; //Method java/lang/ThreadLocal.set:(Ljava/lang/Object;)V
   43:	return
  LineNumberTable: 
   line 72: 0
   line 73: 11
   line 74: 22
   line 71: 43

  LocalVariableTable: 
   Start  Length  Slot  Name   Signature
   0      44      0    this       Lscala/actors/Actor$;
   11      33      1    a       Lscala/actors/Reactor;


public final scala.actors.IScheduler scala$actors$Actor$$parentScheduler();
  Code:
   Stack=1, Locals=2, Args_size=1
   0:	aload_0
   1:	getfield	#32; //Field tl:Ljava/lang/ThreadLocal;
   4:	invokevirtual	#222; //Method java/lang/ThreadLocal.get:()Ljava/lang/Object;
   7:	checkcast	#143; //class scala/actors/Reactor
   10:	astore_1
   11:	aload_1
   12:	ifnonnull	21
   15:	getstatic	#243; //Field scala/actors/Scheduler$.MODULE$:Lscala/actors/Scheduler$;
   18:	goto	27
   21:	aload_1
   22:	invokeinterface	#246,  1; //InterfaceMethod scala/actors/Reactor.scheduler:()Lscala/actors/IScheduler;
   27:	areturn
  LineNumberTable: 
   line 59: 0
   line 60: 11
   line 58: 27

  LocalVariableTable: 
   Start  Length  Slot  Name   Signature
   0      28      0    this       Lscala/actors/Actor$;
   11      17      1    s       Lscala/actors/Reactor;


public scala.actors.Reactor rawSelf(scala.actors.IScheduler);
  Code:
   Stack=4, Locals=4, Args_size=2
   0:	aload_0
   1:	getfield	#32; //Field tl:Ljava/lang/ThreadLocal;
   4:	invokevirtual	#222; //Method java/lang/ThreadLocal.get:()Ljava/lang/Object;
   7:	checkcast	#143; //class scala/actors/Reactor
   10:	astore_3
   11:	aload_3
   12:	ifnonnull	39
   15:	new	#224; //class scala/actors/ActorProxy
   18:	dup
   19:	invokestatic	#230; //Method java/lang/Thread.currentThread:()Ljava/lang/Thread;
   22:	aload_1
   23:	invokespecial	#237; //Method scala/actors/ActorProxy."<init>":(Ljava/lang/Thread;Lscala/actors/IScheduler;)V
   26:	astore_2
   27:	aload_0
   28:	getfield	#32; //Field tl:Ljava/lang/ThreadLocal;
   31:	aload_2
   32:	invokevirtual	#218; //Method java/lang/ThreadLocal.set:(Ljava/lang/Object;)V
   35:	aload_2
   36:	goto	40
   39:	aload_3
   40:	areturn
  LineNumberTable: 
   line 49: 0
   line 50: 11
   line 51: 15
   line 52: 27
   line 53: 31
   line 52: 32
   line 53: 35
   line 55: 39
   line 48: 40

  LocalVariableTable: 
   Start  Length  Slot  Name   Signature
   0      41      0    this       Lscala/actors/Actor$;
   0      41      1    sched       Lscala/actors/IScheduler;
   27      9      2    r       Lscala/actors/ActorProxy;
   11      30      3    s       Lscala/actors/Reactor;


public scala.actors.Reactor rawSelf();
  Code:
   Stack=2, Locals=1, Args_size=1
   0:	aload_0
   1:	getstatic	#243; //Field scala/actors/Scheduler$.MODULE$:Lscala/actors/Scheduler$;
   4:	invokevirtual	#254; //Method rawSelf:(Lscala/actors/IScheduler;)Lscala/actors/Reactor;
   7:	areturn
  LineNumberTable: 
   line 46: 0


public scala.actors.Actor self(scala.actors.IScheduler);
  Code:
   Stack=2, Locals=2, Args_size=2
   0:	aload_0
   1:	aload_1
   2:	invokevirtual	#254; //Method rawSelf:(Lscala/actors/IScheduler;)Lscala/actors/Reactor;
   5:	checkcast	#56; //class scala/actors/Actor
   8:	areturn
  LineNumberTable: 
   line 44: 0

  LocalVariableTable: 
   Start  Length  Slot  Name   Signature
   0      9      0    this       Lscala/actors/Actor$;
   0      9      1    sched       Lscala/actors/IScheduler;


public scala.actors.Actor self();
  Code:
   Stack=2, Locals=1, Args_size=1
   0:	aload_0
   1:	getstatic	#243; //Field scala/actors/Scheduler$.MODULE$:Lscala/actors/Scheduler$;
   4:	invokevirtual	#257; //Method self:(Lscala/actors/IScheduler;)Lscala/actors/Actor;
   7:	areturn
  LineNumberTable: 
   line 41: 0


public scala.actors.SuspendActorException suspendException();
  Code:
   Stack=1, Locals=1, Args_size=1
   0:	aload_0
   1:	getfield	#44; //Field suspendException:Lscala/actors/SuspendActorException;
   4:	areturn
  LineNumberTable: 
   line 32: 0


public java.util.Timer timer();
  Code:
   Stack=1, Locals=1, Args_size=1
   0:	aload_0
   1:	getfield	#39; //Field timer:Ljava/util/Timer;
   4:	areturn
  LineNumberTable: 
   line 30: 0


public java.lang.ThreadLocal tl();
  Code:
   Stack=1, Locals=1, Args_size=1
   0:	aload_0
   1:	getfield	#32; //Field tl:Ljava/lang/ThreadLocal;
   4:	areturn
  LineNumberTable: 
   line 27: 0

  Signature: length = 0x2
   01 04 

}

