Compiled from "Actor.scala"
public final class scala.actors.Actor$$anonfun$startSearch$1 extends java.lang.Object implements scala.Function0,scala.ScalaObject,java.io.Serializable
  SourceFile: "Actor.scala"
  Scala: length = 0x
   
  InnerClass: 
   public final #80= #9 of #79; //$anonfun$startSearch$1=class scala/actors/Actor$$anonfun$startSearch$1 of class scala/actors/Actor
  minor version: 0
  major version: 49
  Constant pool:
const #1 = Asciz	SourceFile;
const #2 = Asciz	Actor.scala;
const #3 = Asciz	<clinit>;
const #4 = Asciz	()V;
const #5 = Asciz	Code;
const #6 = Asciz	serialVersionUID;
const #7 = Asciz	J;
const #8 = Asciz	scala/actors/Actor$$anonfun$startSearch$1;
const #9 = class	#8;	//  scala/actors/Actor$$anonfun$startSearch$1
const #10 = NameAndType	#6:#7;//  serialVersionUID:J
const #11 = Field	#9.#10;	//  scala/actors/Actor$$anonfun$startSearch$1.serialVersionUID:J
const #12 = Asciz	replyTo$1;
const #13 = Asciz	Lscala/actors/OutputChannel;;
const #14 = Asciz	msg$1;
const #15 = Asciz	Ljava/lang/Object;;
const #16 = Asciz	$outer;
const #17 = Asciz	Lscala/actors/Actor;;
const #18 = Asciz	<init>;
const #19 = Asciz	(Lscala/actors/Actor;Ljava/lang/Object;Lscala/actors/OutputChannel;)V;
const #20 = Asciz	LineNumberTable;
const #21 = Asciz	java/lang/NullPointerException;
const #22 = class	#21;	//  java/lang/NullPointerException
const #23 = NameAndType	#18:#4;//  "<init>":()V
const #24 = Method	#22.#23;	//  java/lang/NullPointerException."<init>":()V
const #25 = NameAndType	#16:#17;//  $outer:Lscala/actors/Actor;
const #26 = Field	#9.#25;	//  scala/actors/Actor$$anonfun$startSearch$1.$outer:Lscala/actors/Actor;
const #27 = NameAndType	#14:#15;//  msg$1:Ljava/lang/Object;
const #28 = Field	#9.#27;	//  scala/actors/Actor$$anonfun$startSearch$1.msg$1:Ljava/lang/Object;
const #29 = NameAndType	#12:#13;//  replyTo$1:Lscala/actors/OutputChannel;
const #30 = Field	#9.#29;	//  scala/actors/Actor$$anonfun$startSearch$1.replyTo$1:Lscala/actors/OutputChannel;
const #31 = Asciz	java/lang/Object;
const #32 = class	#31;	//  java/lang/Object
const #33 = Method	#32.#23;	//  java/lang/Object."<init>":()V
const #34 = Asciz	scala/Function0$class;
const #35 = class	#34;	//  scala/Function0$class
const #36 = Asciz	$init$;
const #37 = Asciz	(Lscala/Function0;)V;
const #38 = NameAndType	#36:#37;//  $init$:(Lscala/Function0;)V
const #39 = Method	#35.#38;	//  scala/Function0$class.$init$:(Lscala/Function0;)V
const #40 = Asciz	this;
const #41 = Asciz	Lscala/actors/Actor$$anonfun$startSearch$1;;
const #42 = Asciz	LocalVariableTable;
const #43 = Asciz	apply;
const #44 = Asciz	()Ljava/lang/Object;;
const #45 = NameAndType	#43:#4;//  apply:()V
const #46 = Method	#9.#45;	//  scala/actors/Actor$$anonfun$startSearch$1.apply:()V
const #47 = Asciz	scala/runtime/BoxedUnit;
const #48 = class	#47;	//  scala/runtime/BoxedUnit
const #49 = Asciz	UNIT;
const #50 = Asciz	Lscala/runtime/BoxedUnit;;
const #51 = NameAndType	#49:#50;//  UNIT:Lscala/runtime/BoxedUnit;
const #52 = Field	#48.#51;	//  scala/runtime/BoxedUnit.UNIT:Lscala/runtime/BoxedUnit;
const #53 = Asciz	scala/actors/Reactor;
const #54 = class	#53;	//  scala/actors/Reactor
const #55 = Asciz	mailbox;
const #56 = Asciz	()Lscala/actors/MessageQueue;;
const #57 = NameAndType	#55:#56;//  mailbox:()Lscala/actors/MessageQueue;
const #58 = InterfaceMethod	#54.#57;	//  scala/actors/Reactor.mailbox:()Lscala/actors/MessageQueue;
const #59 = Asciz	scala/actors/MessageQueue;
const #60 = class	#59;	//  scala/actors/MessageQueue
const #61 = Asciz	append;
const #62 = Asciz	(Ljava/lang/Object;Lscala/actors/OutputChannel;)V;
const #63 = NameAndType	#61:#62;//  append:(Ljava/lang/Object;Lscala/actors/OutputChannel;)V
const #64 = Method	#60.#63;	//  scala/actors/MessageQueue.append:(Ljava/lang/Object;Lscala/actors/OutputChannel;)V
const #65 = Asciz	scala/actors/Actor$class;
const #66 = class	#65;	//  scala/actors/Actor$class
const #67 = Asciz	scala$actors$Actor$$resumeActor;
const #68 = Asciz	(Lscala/actors/Actor;)V;
const #69 = NameAndType	#67:#68;//  scala$actors$Actor$$resumeActor:(Lscala/actors/Actor;)V
const #70 = Method	#66.#69;	//  scala/actors/Actor$class.scala$actors$Actor$$resumeActor:(Lscala/actors/Actor;)V
const #71 = Asciz	toString;
const #72 = Asciz	()Ljava/lang/String;;
const #73 = Asciz	(Lscala/Function0;)Ljava/lang/String;;
const #74 = NameAndType	#71:#73;//  toString:(Lscala/Function0;)Ljava/lang/String;
const #75 = Method	#35.#74;	//  scala/Function0$class.toString:(Lscala/Function0;)Ljava/lang/String;
const #76 = Asciz	Scala;
const #77 = Asciz	InnerClasses;
const #78 = Asciz	scala/actors/Actor;
const #79 = class	#78;	//  scala/actors/Actor
const #80 = Asciz	$anonfun$startSearch$1;
const #81 = Asciz	scala/Function0;
const #82 = class	#81;	//  scala/Function0
const #83 = Asciz	scala/ScalaObject;
const #84 = class	#83;	//  scala/ScalaObject
const #85 = Asciz	java/io/Serializable;
const #86 = class	#85;	//  java/io/Serializable

{
public static final long serialVersionUID;

public static {};
  Code:
   Stack=2, Locals=0, Args_size=0
   0:	lconst_0
   1:	putstatic	#11; //Field serialVersionUID:J
   4:	return

public scala.actors.Actor$$anonfun$startSearch$1(scala.actors.Actor, java.lang.Object, scala.actors.OutputChannel);
  Code:
   Stack=2, Locals=4, Args_size=4
   0:	aload_1
   1:	ifnonnull	12
   4:	new	#22; //class java/lang/NullPointerException
   7:	dup
   8:	invokespecial	#24; //Method java/lang/NullPointerException."<init>":()V
   11:	athrow
   12:	aload_0
   13:	aload_1
   14:	putfield	#26; //Field $outer:Lscala/actors/Actor;
   17:	aload_0
   18:	aload_2
   19:	putfield	#28; //Field msg$1:Ljava/lang/Object;
   22:	aload_0
   23:	aload_3
   24:	putfield	#30; //Field replyTo$1:Lscala/actors/OutputChannel;
   27:	aload_0
   28:	invokespecial	#33; //Method java/lang/Object."<init>":()V
   31:	aload_0
   32:	invokestatic	#39; //Method scala/Function0$class.$init$:(Lscala/Function0;)V
   35:	return
  LineNumberTable: 
   line 405: 0

  LocalVariableTable: 
   Start  Length  Slot  Name   Signature
   0      36      0    this       Lscala/actors/Actor$$anonfun$startSearch$1;
   0      36      1    $outer       Lscala/actors/Actor;


public final java.lang.Object apply();
  Code:
   Stack=1, Locals=2, Args_size=1
   0:	aload_0
   1:	getfield	#26; //Field $outer:Lscala/actors/Actor;
   4:	astore_1
   5:	aload_0
   6:	invokevirtual	#46; //Method apply:()V
   9:	getstatic	#52; //Field scala/runtime/BoxedUnit.UNIT:Lscala/runtime/BoxedUnit;
   12:	areturn
  LineNumberTable: 
   line 405: 0

  LocalVariableTable: 
   Start  Length  Slot  Name   Signature
   0      13      0    this       Lscala/actors/Actor$$anonfun$startSearch$1;


public final void apply();
  Code:
   Stack=3, Locals=3, Args_size=1
   0:	aload_0
   1:	getfield	#26; //Field $outer:Lscala/actors/Actor;
   4:	astore_2
   5:	aload_0
   6:	getfield	#26; //Field $outer:Lscala/actors/Actor;
   9:	dup
   10:	astore_1
   11:	monitorenter
   12:	aload_0
   13:	getfield	#26; //Field $outer:Lscala/actors/Actor;
   16:	invokeinterface	#58,  1; //InterfaceMethod scala/actors/Reactor.mailbox:()Lscala/actors/MessageQueue;
   21:	aload_0
   22:	getfield	#28; //Field msg$1:Ljava/lang/Object;
   25:	aload_0
   26:	getfield	#30; //Field replyTo$1:Lscala/actors/OutputChannel;
   29:	invokevirtual	#64; //Method scala/actors/MessageQueue.append:(Ljava/lang/Object;Lscala/actors/OutputChannel;)V
   32:	aload_0
   33:	getfield	#26; //Field $outer:Lscala/actors/Actor;
   36:	invokestatic	#70; //Method scala/actors/Actor$class.scala$actors$Actor$$resumeActor:(Lscala/actors/Actor;)V
   39:	aload_1
   40:	monitorexit
   41:	return
   42:	aload_1
   43:	monitorexit
   44:	athrow
  Exception table:
   from   to  target type
    12    41    42   any
  LineNumberTable: 
   line 405: 0
   line 406: 12
   line 407: 32
   line 405: 40

  LocalVariableTable: 
   Start  Length  Slot  Name   Signature
   0      45      0    this       Lscala/actors/Actor$$anonfun$startSearch$1;


public java.lang.String toString();
  Code:
   Stack=1, Locals=1, Args_size=1
   0:	aload_0
   1:	invokestatic	#75; //Method scala/Function0$class.toString:(Lscala/Function0;)Ljava/lang/String;
   4:	areturn
  LineNumberTable: 
   line 405: 0


}

