Compiled from "ActorGC.scala"
public final class scala.actors.ActorGC$$anonfun$terminated$1 extends java.lang.Object implements scala.Function1,scala.ScalaObject,java.io.Serializable
  SourceFile: "ActorGC.scala"
  Scala: length = 0x
   
  InnerClass: 
   public final $anonfun$terminated$1=class scala/actors/ActorGC$$anonfun$terminated$1 of class scala/actors/ActorGC
  minor version: 0
  major version: 49
  Constant pool:
Asciz	SourceFile;
Asciz	ActorGC.scala;
Asciz	<clinit>;
Asciz	()V;
Asciz	Code;
Asciz	serialVersionUID;
Asciz	J;
Asciz	scala/actors/ActorGC$$anonfun$terminated$1;
class	scala/actors/ActorGC$$anonfun$terminated$1
NameAndType	serialVersionUID:J
Field	scala/actors/ActorGC$$anonfun$terminated$1.serialVersionUID:J
Asciz	a$1;
Asciz	Lscala/actors/Reactor;;
Asciz	<init>;
Asciz	(Lscala/actors/ActorGC;Lscala/actors/Reactor;)V;
Asciz	LineNumberTable;
NameAndType	a$1:Lscala/actors/Reactor;
Field	scala/actors/ActorGC$$anonfun$terminated$1.a$1:Lscala/actors/Reactor;
Asciz	java/lang/Object;
class	java/lang/Object
NameAndType	"<init>":()V
Method	java/lang/Object."<init>":()V
Asciz	scala/Function1$class;
class	scala/Function1$class
Asciz	$init$;
Asciz	(Lscala/Function1;)V;
NameAndType	$init$:(Lscala/Function1;)V
Method	scala/Function1$class.$init$:(Lscala/Function1;)V
Asciz	this;
Asciz	Lscala/actors/ActorGC$$anonfun$terminated$1;;
Asciz	$outer;
Asciz	Lscala/actors/ActorGC;;
Asciz	LocalVariableTable;
Asciz	apply;
Asciz	(Ljava/lang/Object;)Ljava/lang/Object;;
Asciz	java/lang/ref/Reference;
class	java/lang/ref/Reference
Asciz	(Ljava/lang/ref/Reference;)Z;
NameAndType	apply:(Ljava/lang/ref/Reference;)Z
Method	scala/actors/ActorGC$$anonfun$terminated$1.apply:(Ljava/lang/ref/Reference;)Z
Asciz	scala/runtime/BoxesRunTime;
class	scala/runtime/BoxesRunTime
Asciz	boxToBoolean;
Asciz	(Z)Ljava/lang/Boolean;;
NameAndType	boxToBoolean:(Z)Ljava/lang/Boolean;
Method	scala/runtime/BoxesRunTime.boxToBoolean:(Z)Ljava/lang/Boolean;
Asciz	v1;
Asciz	Ljava/lang/Object;;
Asciz	get;
Asciz	()Ljava/lang/Object;;
NameAndType	get:()Ljava/lang/Object;
Method	java/lang/ref/Reference.get:()Ljava/lang/Object;
Asciz	equals;
Asciz	(Ljava/lang/Object;)Z;
NameAndType	equals:(Ljava/lang/Object;)Z
Method	java/lang/Object.equals:(Ljava/lang/Object;)Z
Asciz	ref;
Asciz	Ljava/lang/ref/Reference;;
Asciz	(Ljava/lang/ref/Reference<+Lscala/actors/Reactor;>;)Z;
Asciz	Signature;
Asciz	andThen;
Asciz	(Lscala/Function1;)Lscala/Function1;;
Asciz	(Lscala/Function1;Lscala/Function1;)Lscala/Function1;;
NameAndType	andThen:(Lscala/Function1;Lscala/Function1;)Lscala/Function1;
Method	scala/Function1$class.andThen:(Lscala/Function1;Lscala/Function1;)Lscala/Function1;
Asciz	g;
Asciz	Lscala/Function1;;
Asciz	compose;
NameAndType	compose:(Lscala/Function1;Lscala/Function1;)Lscala/Function1;
Method	scala/Function1$class.compose:(Lscala/Function1;Lscala/Function1;)Lscala/Function1;
Asciz	toString;
Asciz	()Ljava/lang/String;;
Asciz	(Lscala/Function1;)Ljava/lang/String;;
NameAndType	toString:(Lscala/Function1;)Ljava/lang/String;
Method	scala/Function1$class.toString:(Lscala/Function1;)Ljava/lang/String;
Asciz	Scala;
Asciz	InnerClasses;
Asciz	scala/actors/ActorGC;
class	scala/actors/ActorGC
Asciz	$anonfun$terminated$1;
Asciz	scala/Function1;
class	scala/Function1
Asciz	scala/ScalaObject;
class	scala/ScalaObject
Asciz	java/io/Serializable;
class	java/io/Serializable

{
public static final long serialVersionUID;
  Signature: J

private final scala.actors.Reactor a$1;
  Signature: Lscala/actors/Reactor;

public static {};
  Signature: ()V
  Code:
   Stack=2, Locals=0, Args_size=0
	lconst_0
	putstatic	Field serialVersionUID:J
	return
  Labels:

public scala.actors.ActorGC$$anonfun$terminated$1(scala.actors.ActorGC, scala.actors.Reactor);
  Signature: (Lscala/actors/ActorGC;Lscala/actors/Reactor;)V
  Code:
   Stack=2, Locals=3, Args_size=3
	aload_0
	aload_2
	putfield	Field a$1:Lscala/actors/Reactor;
	aload_0
	invokespecial	Method java/lang/Object."<init>":()V
	aload_0
	invokestatic	Method scala/Function1$class.$init$:(Lscala/Function1;)V
	return
  Labels:
  LocalVariableTable: 
   Start  Length  Slot  Name   Signature
   0      14      0    this       Lscala/actors/ActorGC$$anonfun$terminated$1;
   0      14      1    $outer       Lscala/actors/ActorGC;


public final java.lang.Object apply(java.lang.Object);
  Signature: (Ljava/lang/Object;)Ljava/lang/Object;
  Code:
   Stack=2, Locals=3, Args_size=2
	aload_0
	aload_1
	checkcast	class java/lang/ref/Reference
	invokevirtual	Method apply:(Ljava/lang/ref/Reference;)Z
	istore_2
	iload_2
	invokestatic	Method scala/runtime/BoxesRunTime.boxToBoolean:(Z)Ljava/lang/Boolean;
	areturn
  Labels:
  LocalVariableTable: 
   Start  Length  Slot  Name   Signature
   0      14      0    this       Lscala/actors/ActorGC$$anonfun$terminated$1;
   0      14      1    v1       Ljava/lang/Object;


public final boolean apply(java.lang.ref.Reference);
  Signature: (Ljava/lang/ref/Reference;)Z
  Code:
   Stack=2, Locals=3, Args_size=2
	aload_1
	invokevirtual	Method java/lang/ref/Reference.get:()Ljava/lang/Object;
	aload_0
	getfield	Field a$1:Lscala/actors/Reactor;
	astore_2
	dup
	ifnonnull	l1 // aload_2
	pop
	aload_2
	ifnull	l2 // iconst_1
	goto	l3 // iconst_0
l1	aload_2
	invokevirtual	Method java/lang/Object.equals:(Ljava/lang/Object;)Z
	ifeq	l3 // iconst_0
l2	iconst_1
	goto	l4 // ireturn
l3	iconst_0
l4	ireturn
  Labels:
   	l1 = 21 // aload_2
   	l2 = 28 // iconst_1
   	l3 = 32 // iconst_0
   	l4 = 33 // ireturn
  LocalVariableTable: 
   Start  Length  Slot  Name   Signature
   0      34      0    this       Lscala/actors/ActorGC$$anonfun$terminated$1;
   0      34      1    ref       Ljava/lang/ref/Reference;

  Signature: length = 0x2
   00 3B 

public scala.Function1 andThen(scala.Function1);
  Signature: (Lscala/Function1;)Lscala/Function1;
  Code:
   Stack=2, Locals=2, Args_size=2
	aload_0
	aload_1
	invokestatic	Method scala/Function1$class.andThen:(Lscala/Function1;Lscala/Function1;)Lscala/Function1;
	areturn
  Labels:
  LocalVariableTable: 
   Start  Length  Slot  Name   Signature
   0      6      0    this       Lscala/actors/ActorGC$$anonfun$terminated$1;
   0      6      1    g       Lscala/Function1;


public scala.Function1 compose(scala.Function1);
  Signature: (Lscala/Function1;)Lscala/Function1;
  Code:
   Stack=2, Locals=2, Args_size=2
	aload_0
	aload_1
	invokestatic	Method scala/Function1$class.compose:(Lscala/Function1;Lscala/Function1;)Lscala/Function1;
	areturn
  Labels:
  LocalVariableTable: 
   Start  Length  Slot  Name   Signature
   0      6      0    this       Lscala/actors/ActorGC$$anonfun$terminated$1;
   0      6      1    g       Lscala/Function1;


public java.lang.String toString();
  Signature: ()Ljava/lang/String;
  Code:
   Stack=1, Locals=1, Args_size=1
	aload_0
	invokestatic	Method scala/Function1$class.toString:(Lscala/Function1;)Ljava/lang/String;
	areturn
  Labels:

}

