Compiled from "Actor.scala"
public final class scala.actors.Actor$$anonfun$reactWithin$2 extends scala.runtime.AbstractFunction2 implements java.io.Serializable
  SourceFile: "Actor.scala"
  Scala: length = 0x
   
  InnerClass: 
   public final $anonfun$reactWithin$2=class scala/actors/Actor$$anonfun$reactWithin$2 of class scala/actors/Actor
  minor version: 0
  major version: 49
  Constant pool:
Asciz	SourceFile;
Asciz	Actor.scala;
Asciz	<clinit>;
Asciz	()V;
Asciz	Code;
Asciz	serialVersionUID;
Asciz	J;
Asciz	scala/actors/Actor$$anonfun$reactWithin$2;
class	scala/actors/Actor$$anonfun$reactWithin$2
NameAndType	serialVersionUID:J
Field	scala/actors/Actor$$anonfun$reactWithin$2.serialVersionUID:J
Asciz	apply;
Asciz	(Ljava/lang/Object;Lscala/actors/OutputChannel;)Z;
Asciz	LineNumberTable;
Asciz	scala/actors/TIMEOUT$;
class	scala/actors/TIMEOUT$
Asciz	MODULE$;
Asciz	Lscala/actors/TIMEOUT$;;
NameAndType	MODULE$:Lscala/actors/TIMEOUT$;
Field	scala/actors/TIMEOUT$.MODULE$:Lscala/actors/TIMEOUT$;
Asciz	java/lang/Object;
class	java/lang/Object
Asciz	equals;
Asciz	(Ljava/lang/Object;)Z;
NameAndType	equals:(Ljava/lang/Object;)Z
Method	java/lang/Object.equals:(Ljava/lang/Object;)Z
Asciz	this;
Asciz	Lscala/actors/Actor$$anonfun$reactWithin$2;;
Asciz	m;
Asciz	Ljava/lang/Object;;
Asciz	replyTo;
Asciz	Lscala/actors/OutputChannel;;
Asciz	LocalVariableTable;
Asciz	(Ljava/lang/Object;Lscala/actors/OutputChannel<Ljava/lang/Object;>;)Z;
Asciz	Signature;
Asciz	(Ljava/lang/Object;Ljava/lang/Object;)Ljava/lang/Object;;
Asciz	scala/actors/OutputChannel;
class	scala/actors/OutputChannel
NameAndType	apply:(Ljava/lang/Object;Lscala/actors/OutputChannel;)Z
Method	scala/actors/Actor$$anonfun$reactWithin$2.apply:(Ljava/lang/Object;Lscala/actors/OutputChannel;)Z
Asciz	scala/runtime/BoxesRunTime;
class	scala/runtime/BoxesRunTime
Asciz	boxToBoolean;
Asciz	(Z)Ljava/lang/Boolean;;
NameAndType	boxToBoolean:(Z)Ljava/lang/Boolean;
Method	scala/runtime/BoxesRunTime.boxToBoolean:(Z)Ljava/lang/Boolean;
Asciz	v1;
Asciz	v2;
Asciz	<init>;
Asciz	(Lscala/actors/Actor;)V;
Asciz	scala/runtime/AbstractFunction2;
class	scala/runtime/AbstractFunction2
NameAndType	"<init>":()V
Method	scala/runtime/AbstractFunction2."<init>":()V
Asciz	$outer;
Asciz	Lscala/actors/Actor;;
Asciz	Scala;
Asciz	InnerClasses;
Asciz	scala/actors/Actor;
class	scala/actors/Actor
Asciz	$anonfun$reactWithin$2;
Asciz	java/io/Serializable;
class	java/io/Serializable

{
public static final long serialVersionUID;
  Signature: J

public static {};
  Signature: ()V
  Code:
   Stack=2, Locals=0, Args_size=0
	lconst_0
	putstatic	Field serialVersionUID:J
	return
  Labels:

public final boolean apply(java.lang.Object, scala.actors.OutputChannel);
  Signature: (Ljava/lang/Object;Lscala/actors/OutputChannel;)Z
  Code:
   Stack=2, Locals=4, Args_size=3
	aload_1
	getstatic	Field scala/actors/TIMEOUT$.MODULE$:Lscala/actors/TIMEOUT$;
	astore_3
	dup
	ifnonnull	l1 // aload_3
	pop
	aload_3
	ifnull	l2 // iconst_1
	goto	l3 // iconst_0
l1	aload_3
	invokevirtual	Method java/lang/Object.equals:(Ljava/lang/Object;)Z
	ifeq	l3 // iconst_0
l2	iconst_1
	goto	l4 // ireturn
l3	iconst_0
l4	ireturn
  Labels:
   	l1 = 17 // aload_3
   	l2 = 24 // iconst_1
   	l3 = 28 // iconst_0
   	l4 = 29 // ireturn
  LocalVariableTable: 
   Start  Length  Slot  Name   Signature
   0      30      0    this       Lscala/actors/Actor$$anonfun$reactWithin$2;
   0      30      1    m       Ljava/lang/Object;
   0      30      2    replyTo       Lscala/actors/OutputChannel;

  Signature: length = 0x2
   00 22 

public final java.lang.Object apply(java.lang.Object, java.lang.Object);
  Signature: (Ljava/lang/Object;Ljava/lang/Object;)Ljava/lang/Object;
  Code:
   Stack=3, Locals=4, Args_size=3
	aload_0
	aload_1
	aload_2
	checkcast	class scala/actors/OutputChannel
	invokevirtual	Method apply:(Ljava/lang/Object;Lscala/actors/OutputChannel;)Z
	istore_3
	iload_3
	invokestatic	Method scala/runtime/BoxesRunTime.boxToBoolean:(Z)Ljava/lang/Boolean;
	areturn
  Labels:
  LocalVariableTable: 
   Start  Length  Slot  Name   Signature
   0      15      0    this       Lscala/actors/Actor$$anonfun$reactWithin$2;
   0      15      1    v1       Ljava/lang/Object;
   0      15      2    v2       Ljava/lang/Object;


public scala.actors.Actor$$anonfun$reactWithin$2(scala.actors.Actor);
  Signature: (Lscala/actors/Actor;)V
  Code:
   Stack=1, Locals=2, Args_size=2
	aload_0
	invokespecial	Method scala/runtime/AbstractFunction2."<init>":()V
	return
  Labels:
  LocalVariableTable: 
   Start  Length  Slot  Name   Signature
   0      5      0    this       Lscala/actors/Actor$$anonfun$reactWithin$2;
   0      5      1    $outer       Lscala/actors/Actor;


}

