Compiled from "Actor.scala"
public final class scala.actors.Actor$$anonfun$loopWhile$1 extends java.lang.Object implements scala.Function0,scala.ScalaObject,java.io.Serializable
  SourceFile: "Actor.scala"
  Scala: length = 0x
   
  InnerClass: 
   public final $anonfun$loopWhile$1=class scala/actors/Actor$$anonfun$loopWhile$1 of class scala/actors/Actor
  minor version: 0
  major version: 49
  Constant pool:
Asciz	SourceFile;
Asciz	Actor.scala;
Asciz	<clinit>;
Asciz	()V;
Asciz	Code;
Asciz	serialVersionUID;
Asciz	J;
Asciz	scala/actors/Actor$$anonfun$loopWhile$1;
class	scala/actors/Actor$$anonfun$loopWhile$1
NameAndType	serialVersionUID:J
Field	scala/actors/Actor$$anonfun$loopWhile$1.serialVersionUID:J
Asciz	body$5;
Asciz	Lscala/Function0;;
Asciz	cond$1;
Asciz	<init>;
Asciz	(Lscala/Function0;Lscala/Function0;)V;
Asciz	LineNumberTable;
NameAndType	cond$1:Lscala/Function0;
Field	scala/actors/Actor$$anonfun$loopWhile$1.cond$1:Lscala/Function0;
NameAndType	body$5:Lscala/Function0;
Field	scala/actors/Actor$$anonfun$loopWhile$1.body$5:Lscala/Function0;
Asciz	java/lang/Object;
class	java/lang/Object
NameAndType	"<init>":()V
Method	java/lang/Object."<init>":()V
Asciz	scala/Function0$class;
class	scala/Function0$class
Asciz	$init$;
Asciz	(Lscala/Function0;)V;
NameAndType	$init$:(Lscala/Function0;)V
Method	scala/Function0$class.$init$:(Lscala/Function0;)V
Asciz	apply;
Asciz	()Ljava/lang/Object;;
NameAndType	apply:()V
Method	scala/actors/Actor$$anonfun$loopWhile$1.apply:()V
Asciz	scala/runtime/BoxedUnit;
class	scala/runtime/BoxedUnit
Asciz	UNIT;
Asciz	Lscala/runtime/BoxedUnit;;
NameAndType	UNIT:Lscala/runtime/BoxedUnit;
Field	scala/runtime/BoxedUnit.UNIT:Lscala/runtime/BoxedUnit;
Asciz	scala/actors/Actor$;
class	scala/actors/Actor$
Asciz	MODULE$;
Asciz	Lscala/actors/Actor$;;
NameAndType	MODULE$:Lscala/actors/Actor$;
Field	scala/actors/Actor$.MODULE$:Lscala/actors/Actor$;
Asciz	loopWhile;
NameAndType	loopWhile:(Lscala/Function0;Lscala/Function0;)V
Method	scala/actors/Actor$.loopWhile:(Lscala/Function0;Lscala/Function0;)V
Asciz	toString;
Asciz	()Ljava/lang/String;;
Asciz	(Lscala/Function0;)Ljava/lang/String;;
NameAndType	toString:(Lscala/Function0;)Ljava/lang/String;
Method	scala/Function0$class.toString:(Lscala/Function0;)Ljava/lang/String;
Asciz	Scala;
Asciz	InnerClasses;
Asciz	scala/actors/Actor;
class	scala/actors/Actor
Asciz	$anonfun$loopWhile$1;
Asciz	scala/Function0;
class	scala/Function0
Asciz	scala/ScalaObject;
class	scala/ScalaObject
Asciz	java/io/Serializable;
class	java/io/Serializable

{
public static final long serialVersionUID;
  Signature: J

private final scala.Function0 body$5;
  Signature: Lscala/Function0;

private final scala.Function0 cond$1;
  Signature: Lscala/Function0;

public static {};
  Signature: ()V
  Code:
   Stack=2, Locals=0, Args_size=0
	lconst_0
	putstatic	Field serialVersionUID:J
	return
  Labels:

public scala.actors.Actor$$anonfun$loopWhile$1(scala.Function0, scala.Function0);
  Signature: (Lscala/Function0;Lscala/Function0;)V
  Code:
   Stack=2, Locals=3, Args_size=3
	aload_0
	aload_1
	putfield	Field cond$1:Lscala/Function0;
	aload_0
	aload_2
	putfield	Field body$5:Lscala/Function0;
	aload_0
	invokespecial	Method java/lang/Object."<init>":()V
	aload_0
	invokestatic	Method scala/Function0$class.$init$:(Lscala/Function0;)V
	return
  Labels:

public final java.lang.Object apply();
  Signature: ()Ljava/lang/Object;
  Code:
   Stack=1, Locals=1, Args_size=1
	aload_0
	invokevirtual	Method apply:()V
	getstatic	Field scala/runtime/BoxedUnit.UNIT:Lscala/runtime/BoxedUnit;
	areturn
  Labels:

public final void apply();
  Signature: ()V
  Code:
   Stack=3, Locals=1, Args_size=1
	getstatic	Field scala/actors/Actor$.MODULE$:Lscala/actors/Actor$;
	aload_0
	getfield	Field cond$1:Lscala/Function0;
	aload_0
	getfield	Field body$5:Lscala/Function0;
	invokevirtual	Method scala/actors/Actor$.loopWhile:(Lscala/Function0;Lscala/Function0;)V
	return
  Labels:

public java.lang.String toString();
  Signature: ()Ljava/lang/String;
  Code:
   Stack=1, Locals=1, Args_size=1
	aload_0
	invokestatic	Method scala/Function0$class.toString:(Lscala/Function0;)Ljava/lang/String;
	areturn
  Labels:

}

