Compiled from "Actor.scala"
public final class scala.actors.Actor$$anonfun$reactWithin$2 extends java.lang.Object implements scala.Function2,scala.ScalaObject,java.io.Serializable
  SourceFile: "Actor.scala"
  Scala: length = 0x
   
  InnerClass: 
   public final #75= #9 of #74; //$anonfun$reactWithin$2=class scala/actors/Actor$$anonfun$reactWithin$2 of class scala/actors/Actor
  minor version: 0
  major version: 49
  Constant pool:
const #1 = Asciz	SourceFile;
const #2 = Asciz	Actor.scala;
const #3 = Asciz	<clinit>;
const #4 = Asciz	()V;
const #5 = Asciz	Code;
const #6 = Asciz	serialVersionUID;
const #7 = Asciz	J;
const #8 = Asciz	scala/actors/Actor$$anonfun$reactWithin$2;
const #9 = class	#8;	//  scala/actors/Actor$$anonfun$reactWithin$2
const #10 = NameAndType	#6:#7;//  serialVersionUID:J
const #11 = Field	#9.#10;	//  scala/actors/Actor$$anonfun$reactWithin$2.serialVersionUID:J
const #12 = Asciz	<init>;
const #13 = Asciz	(Lscala/actors/Actor;)V;
const #14 = Asciz	LineNumberTable;
const #15 = Asciz	java/lang/Object;
const #16 = class	#15;	//  java/lang/Object
const #17 = NameAndType	#12:#4;//  "<init>":()V
const #18 = Method	#16.#17;	//  java/lang/Object."<init>":()V
const #19 = Asciz	scala/Function2$class;
const #20 = class	#19;	//  scala/Function2$class
const #21 = Asciz	$init$;
const #22 = Asciz	(Lscala/Function2;)V;
const #23 = NameAndType	#21:#22;//  $init$:(Lscala/Function2;)V
const #24 = Method	#20.#23;	//  scala/Function2$class.$init$:(Lscala/Function2;)V
const #25 = Asciz	this;
const #26 = Asciz	Lscala/actors/Actor$$anonfun$reactWithin$2;;
const #27 = Asciz	$outer;
const #28 = Asciz	Lscala/actors/Actor;;
const #29 = Asciz	LocalVariableTable;
const #30 = Asciz	apply;
const #31 = Asciz	(Ljava/lang/Object;Ljava/lang/Object;)Ljava/lang/Object;;
const #32 = Asciz	scala/actors/OutputChannel;
const #33 = class	#32;	//  scala/actors/OutputChannel
const #34 = Asciz	(Ljava/lang/Object;Lscala/actors/OutputChannel;)Z;
const #35 = NameAndType	#30:#34;//  apply:(Ljava/lang/Object;Lscala/actors/OutputChannel;)Z
const #36 = Method	#9.#35;	//  scala/actors/Actor$$anonfun$reactWithin$2.apply:(Ljava/lang/Object;Lscala/actors/OutputChannel;)Z
const #37 = Asciz	scala/runtime/BoxesRunTime;
const #38 = class	#37;	//  scala/runtime/BoxesRunTime
const #39 = Asciz	boxToBoolean;
const #40 = Asciz	(Z)Ljava/lang/Boolean;;
const #41 = NameAndType	#39:#40;//  boxToBoolean:(Z)Ljava/lang/Boolean;
const #42 = Method	#38.#41;	//  scala/runtime/BoxesRunTime.boxToBoolean:(Z)Ljava/lang/Boolean;
const #43 = Asciz	v1;
const #44 = Asciz	Ljava/lang/Object;;
const #45 = Asciz	v2;
const #46 = Asciz	scala/actors/TIMEOUT$;
const #47 = class	#46;	//  scala/actors/TIMEOUT$
const #48 = Asciz	MODULE$;
const #49 = Asciz	Lscala/actors/TIMEOUT$;;
const #50 = NameAndType	#48:#49;//  MODULE$:Lscala/actors/TIMEOUT$;
const #51 = Field	#47.#50;	//  scala/actors/TIMEOUT$.MODULE$:Lscala/actors/TIMEOUT$;
const #52 = Asciz	equals;
const #53 = Asciz	(Ljava/lang/Object;)Z;
const #54 = NameAndType	#52:#53;//  equals:(Ljava/lang/Object;)Z
const #55 = Method	#16.#54;	//  java/lang/Object.equals:(Ljava/lang/Object;)Z
const #56 = Asciz	m;
const #57 = Asciz	replyTo;
const #58 = Asciz	Lscala/actors/OutputChannel;;
const #59 = Asciz	(Ljava/lang/Object;Lscala/actors/OutputChannel<Ljava/lang/Object;>;)Z;
const #60 = Asciz	Signature;
const #61 = Asciz	curry;
const #62 = Asciz	()Lscala/Function1;;
const #63 = Asciz	(Lscala/Function2;)Lscala/Function1;;
const #64 = NameAndType	#61:#63;//  curry:(Lscala/Function2;)Lscala/Function1;
const #65 = Method	#20.#64;	//  scala/Function2$class.curry:(Lscala/Function2;)Lscala/Function1;
const #66 = Asciz	toString;
const #67 = Asciz	()Ljava/lang/String;;
const #68 = Asciz	(Lscala/Function2;)Ljava/lang/String;;
const #69 = NameAndType	#66:#68;//  toString:(Lscala/Function2;)Ljava/lang/String;
const #70 = Method	#20.#69;	//  scala/Function2$class.toString:(Lscala/Function2;)Ljava/lang/String;
const #71 = Asciz	Scala;
const #72 = Asciz	InnerClasses;
const #73 = Asciz	scala/actors/Actor;
const #74 = class	#73;	//  scala/actors/Actor
const #75 = Asciz	$anonfun$reactWithin$2;
const #76 = Asciz	scala/Function2;
const #77 = class	#76;	//  scala/Function2
const #78 = Asciz	scala/ScalaObject;
const #79 = class	#78;	//  scala/ScalaObject
const #80 = Asciz	java/io/Serializable;
const #81 = class	#80;	//  java/io/Serializable

{
public static final long serialVersionUID;

public static {};
  Code:
   Stack=2, Locals=0, Args_size=0
   0:	lconst_0
   1:	putstatic	#11; //Field serialVersionUID:J
   4:	return

public scala.actors.Actor$$anonfun$reactWithin$2(scala.actors.Actor);
  Code:
   Stack=1, Locals=2, Args_size=2
   0:	aload_0
   1:	invokespecial	#18; //Method java/lang/Object."<init>":()V
   4:	aload_0
   5:	invokestatic	#24; //Method scala/Function2$class.$init$:(Lscala/Function2;)V
   8:	return
  LineNumberTable: 
   line 592: 0

  LocalVariableTable: 
   Start  Length  Slot  Name   Signature
   0      9      0    this       Lscala/actors/Actor$$anonfun$reactWithin$2;
   0      9      1    $outer       Lscala/actors/Actor;


public final java.lang.Object apply(java.lang.Object, java.lang.Object);
  Code:
   Stack=3, Locals=4, Args_size=3
   0:	aload_0
   1:	aload_1
   2:	aload_2
   3:	checkcast	#33; //class scala/actors/OutputChannel
   6:	invokevirtual	#36; //Method apply:(Ljava/lang/Object;Lscala/actors/OutputChannel;)Z
   9:	istore_3
   10:	iload_3
   11:	invokestatic	#42; //Method scala/runtime/BoxesRunTime.boxToBoolean:(Z)Ljava/lang/Boolean;
   14:	areturn
  LineNumberTable: 
   line 592: 0

  LocalVariableTable: 
   Start  Length  Slot  Name   Signature
   0      15      0    this       Lscala/actors/Actor$$anonfun$reactWithin$2;
   0      15      1    v1       Ljava/lang/Object;
   0      15      2    v2       Ljava/lang/Object;


public final boolean apply(java.lang.Object, scala.actors.OutputChannel);
  Code:
   Stack=2, Locals=4, Args_size=3
   0:	aload_1
   1:	getstatic	#51; //Field scala/actors/TIMEOUT$.MODULE$:Lscala/actors/TIMEOUT$;
   4:	astore_3
   5:	dup
   6:	ifnonnull	17
   9:	pop
   10:	aload_3
   11:	ifnull	24
   14:	goto	28
   17:	aload_3
   18:	invokevirtual	#55; //Method java/lang/Object.equals:(Ljava/lang/Object;)Z
   21:	ifeq	28
   24:	iconst_1
   25:	goto	29
   28:	iconst_0
   29:	ireturn
  LineNumberTable: 
   line 592: 0

  LocalVariableTable: 
   Start  Length  Slot  Name   Signature
   0      30      0    this       Lscala/actors/Actor$$anonfun$reactWithin$2;
   0      30      1    m       Ljava/lang/Object;
   0      30      2    replyTo       Lscala/actors/OutputChannel;

  Signature: length = 0x2
   00 3B 

public scala.Function1 curry();
  Code:
   Stack=1, Locals=1, Args_size=1
   0:	aload_0
   1:	invokestatic	#65; //Method scala/Function2$class.curry:(Lscala/Function2;)Lscala/Function1;
   4:	areturn
  LineNumberTable: 
   line 592: 0


public java.lang.String toString();
  Code:
   Stack=1, Locals=1, Args_size=1
   0:	aload_0
   1:	invokestatic	#70; //Method scala/Function2$class.toString:(Lscala/Function2;)Ljava/lang/String;
   4:	areturn
  LineNumberTable: 
   line 592: 0


}

