Compiled from "CanReply.scala"
public final class scala.actors.CanReply$$anonfun$$bang$bang$2 extends scala.runtime.AbstractFunction0 implements java.io.Serializable
  SourceFile: "CanReply.scala"
  Scala: length = 0x
   
  InnerClass: 
   public final $anonfun$$bang$bang$2=class scala/actors/CanReply$$anonfun$$bang$bang$2 of class scala/actors/CanReply
  minor version: 0
  major version: 49
  Constant pool:
Asciz	SourceFile;
Asciz	CanReply.scala;
Asciz	<clinit>;
Asciz	()V;
Asciz	Code;
Asciz	serialVersionUID;
Asciz	J;
Asciz	scala/actors/CanReply$$anonfun$$bang$bang$2;
class	scala/actors/CanReply$$anonfun$$bang$bang$2
NameAndType	serialVersionUID:J
Field	scala/actors/CanReply$$anonfun$$bang$bang$2.serialVersionUID:J
Asciz	$outer;
Asciz	Lscala/actors/CanReply;;
Asciz	msg$1;
Asciz	Ljava/lang/Object;;
Asciz	handler$1;
Asciz	Lscala/PartialFunction;;
Asciz	apply;
Asciz	()Ljava/lang/Object;;
Asciz	LineNumberTable;
NameAndType	handler$1:Lscala/PartialFunction;
Field	scala/actors/CanReply$$anonfun$$bang$bang$2.handler$1:Lscala/PartialFunction;
NameAndType	$outer:Lscala/actors/CanReply;
Field	scala/actors/CanReply$$anonfun$$bang$bang$2.$outer:Lscala/actors/CanReply;
NameAndType	msg$1:Ljava/lang/Object;
Field	scala/actors/CanReply$$anonfun$$bang$bang$2.msg$1:Ljava/lang/Object;
Asciz	scala/actors/CanReply;
class	scala/actors/CanReply
Asciz	$bang$qmark;
Asciz	(Ljava/lang/Object;)Ljava/lang/Object;;
NameAndType	$bang$qmark:(Ljava/lang/Object;)Ljava/lang/Object;
InterfaceMethod	scala/actors/CanReply.$bang$qmark:(Ljava/lang/Object;)Ljava/lang/Object;
Asciz	scala/Function1;
class	scala/Function1
NameAndType	apply:(Ljava/lang/Object;)Ljava/lang/Object;
InterfaceMethod	scala/Function1.apply:(Ljava/lang/Object;)Ljava/lang/Object;
Asciz	()TP;;
Asciz	Signature;
Asciz	<init>;
Asciz	(Lscala/actors/CanReply;Ljava/lang/Object;Lscala/PartialFunction;)V;
Asciz	java/lang/NullPointerException;
class	java/lang/NullPointerException
NameAndType	"<init>":()V
Method	java/lang/NullPointerException."<init>":()V
Asciz	scala/runtime/AbstractFunction0;
class	scala/runtime/AbstractFunction0
Method	scala/runtime/AbstractFunction0."<init>":()V
Asciz	this;
Asciz	Lscala/actors/CanReply$$anonfun$$bang$bang$2;;
Asciz	LocalVariableTable;
Asciz	(Lscala/actors/CanReply<TT;TR;>;)V;
Asciz	Scala;
Asciz	InnerClasses;
Asciz	$anonfun$$bang$bang$2;
Asciz	java/io/Serializable;
class	java/io/Serializable

{
public static final long serialVersionUID;
  Signature: J

private final scala.actors.CanReply $outer;
  Signature: Lscala/actors/CanReply;

private final java.lang.Object msg$1;
  Signature: Ljava/lang/Object;

private final scala.PartialFunction handler$1;
  Signature: Lscala/PartialFunction;

public static {};
  Signature: ()V
  Code:
   Stack=2, Locals=0, Args_size=0
	lconst_0
	putstatic	Field serialVersionUID:J
	return
  Labels:

public final java.lang.Object apply();
  Signature: ()Ljava/lang/Object;
  Code:
   Stack=3, Locals=1, Args_size=1
	aload_0
	getfield	Field handler$1:Lscala/PartialFunction;
	aload_0
	getfield	Field $outer:Lscala/actors/CanReply;
	aload_0
	getfield	Field msg$1:Ljava/lang/Object;
	invokeinterface	InterfaceMethod scala/actors/CanReply.$bang$qmark:(Ljava/lang/Object;)Ljava/lang/Object;
	invokeinterface	InterfaceMethod scala/Function1.apply:(Ljava/lang/Object;)Ljava/lang/Object;
	areturn
  Labels:
  Signature: length = 0x2
   00 25 

public scala.actors.CanReply$$anonfun$$bang$bang$2(scala.actors.CanReply, java.lang.Object, scala.PartialFunction);
  Signature: (Lscala/actors/CanReply;Ljava/lang/Object;Lscala/PartialFunction;)V
  Code:
   Stack=2, Locals=4, Args_size=4
	aload_1
	ifnonnull	l1 // aload_0
	new	class java/lang/NullPointerException
	dup
	invokespecial	Method java/lang/NullPointerException."<init>":()V
	athrow
l1	aload_0
	aload_1
	putfield	Field $outer:Lscala/actors/CanReply;
	aload_0
	aload_2
	putfield	Field msg$1:Ljava/lang/Object;
	aload_0
	aload_3
	putfield	Field handler$1:Lscala/PartialFunction;
	aload_0
	invokespecial	Method scala/runtime/AbstractFunction0."<init>":()V
	return
  Labels:
   	l1 = 12 // aload_0
  LocalVariableTable: 
   Start  Length  Slot  Name   Signature
   0      32      0    this       Lscala/actors/CanReply$$anonfun$$bang$bang$2;
   0      32      1    $outer       Lscala/actors/CanReply;

  Signature: length = 0x2
   00 33 

}

