Compiled from "Channel.scala"
public class scala.actors.Channel extends java.lang.Object implements scala.actors.InputChannel,scala.actors.OutputChannel,scala.ScalaObject
  SourceFile: "Channel.scala"
  Signature: length = 0x2
   00 FFFFFF8D 
  ScalaSig: length = 0x308
   05 00 7D 06 04 01 02 00 07 02 07 43 68 61 6E 6E
   65 6C 0A 02 03 04 01 06 61 63 74 6F 72 73 0A 01
   05 01 05 73 63 61 6C 61 03 00 15 02 08 17 13 05
   00 09 11 21 24 10 02 0A 0F 0D 01 0B 0A 02 0C 0D
   01 04 6C 61 6E 67 0A 01 0E 01 04 6A 61 76 61 09
   02 10 0B 02 06 4F 62 6A 65 63 74 10 03 12 13 15
   0D 01 02 09 02 14 02 02 0C 49 6E 70 75 74 43 68
   61 6E 6E 65 6C 10 02 16 17 0C 00 04 08 18 00 FFFFFF84
   FFFFFF80 FFFFFF80 FFFFFFC2 00 19 02 03 4D 73 67 11 02 1A 1E 10 02
   1B 1C 0D 01 04 09 02 1D 04 02 07 4E 6F 74 68 69
   6E 67 10 02 1B 1F 09 02 20 04 02 03 41 6E 79 10
   03 12 22 15 09 02 23 02 02 0D 4F 75 74 70 75 74
   43 68 61 6E 6E 65 6C 10 02 1B 25 09 02 26 04 02
   0B 53 63 61 6C 61 4F 62 6A 65 63 74 08 08 28 00
   FFFFFF82 FFFFFFC2 FFFFFF80 FFFFFF84 00 29 01 08 72 65 63 65 69 76 65 72
   15 01 2A 10 02 12 2B 09 02 2C 02 02 07 52 65 61
   63 74 6F 72 08 08 2E 00 FFFFFF82 FFFFFF80 FFFFFFA0 FFFFFF80 04 2A 01 09
   72 65 63 65 69 76 65 72 20 08 05 30 00 FFFFFF84 00 31
   01 06 3C 69 6E 69 74 3E 14 02 32 33 10 03 12 00
   15 08 05 28 2F FFFFFFC0 00 2A 08 05 30 00 FFFFFF84 00 35 14
   01 32 08 05 37 00 FFFFFF84 00 38 01 05 24 62 61 6E 67
   14 02 39 3C 10 02 1B 3A 09 02 3B 04 02 04 55 6E
   69 74 08 05 3D 36 FFFFFFC0 00 15 01 03 6D 73 67 08 05
   3F 00 FFFFFF84 00 40 01 04 73 65 6E 64 14 03 39 41 42
   08 05 3D 3E FFFFFFC0 00 15 08 05 43 3E FFFFFFC0 00 44 01 07
   72 65 70 6C 79 54 6F 10 03 12 22 1E 08 05 46 00
   FFFFFF84 00 47 01 07 66 6F 72 77 61 72 64 14 02 39 48
   08 05 3D 45 FFFFFFC0 00 15 08 05 4A 00 FFFFFF84 00 4B 01 07
   72 65 63 65 69 76 65 15 02 4C 4E 14 02 4D 50 10
   02 16 4E 04 08 4F 49 FFFFFF84 FFFFFF80 FFFFFF80 FFFFFFC2 00 19 02 01 52
   08 05 51 49 FFFFFFC0 00 52 01 01 66 10 04 1B 53 15 4D
   09 02 54 04 02 0F 50 61 72 74 69 61 6C 46 75 6E
   63 74 69 6F 6E 08 05 56 00 FFFFFF84 00 57 01 06 24 71
   6D 61 72 6B 15 01 15 08 05 59 00 FFFFFF84 00 5A 01 0D
   72 65 63 65 69 76 65 57 69 74 68 69 6E 15 02 5B
   5E 14 02 5C 61 14 02 5D 5F 10 02 16 5E 04 08 4F
   58 FFFFFF84 FFFFFF80 FFFFFF80 FFFFFFC2 00 19 08 05 51 58 FFFFFFC0 00 60 10 04
   1B 53 1E 5D 08 05 62 58 FFFFFFC0 00 63 01 04 6D 73 65
   63 10 02 1B 64 09 02 65 04 02 04 4C 6F 6E 67 08
   05 67 00 FFFFFF84 00 68 01 05 72 65 61 63 74 14 02 1A
   69 08 05 51 66 FFFFFFC0 00 6A 10 04 1B 53 15 39 08 05
   6C 00 FFFFFF84 00 6D 01 0B 72 65 61 63 74 57 69 74 68
   69 6E 14 02 6E 71 14 02 1A 6F 08 05 51 6B FFFFFFC0 00
   70 10 04 1B 53 1E 39 08 05 62 6B FFFFFFC0 00 63 08 05
   73 00 FFFFFF84 00 74 01 0B 24 62 61 6E 67 24 71 6D 61
   72 6B 14 02 1E 75 08 05 3D 72 FFFFFFC0 00 15 08 05 73
   00 FFFFFF84 00 77 14 03 78 7B 7C 10 03 1B 79 1E 09 02
   7A 04 02 06 4F 70 74 69 6F 6E 08 05 62 76 FFFFFFC0 00
   63 08 05 3D 76 FFFFFFC0 00 15 
  InnerClass: 
   public final #144= #100 of #10; //$anonfun$react$1=class scala/actors/Channel$$anonfun$react$1 of class scala/actors/Channel
   public final #145= #117 of #10; //$anonfun$$qmark$1=class scala/actors/Channel$$anonfun$$qmark$1 of class scala/actors/Channel
   public final #146= #121 of #10; //$anonfun$receive$1=class scala/actors/Channel$$anonfun$receive$1 of class scala/actors/Channel
   public final #147= #73 of #10; //$anonfun$$bang$qmark$1=class scala/actors/Channel$$anonfun$$bang$qmark$1 of class scala/actors/Channel
   public final #148= #55 of #10; //$anonfun$$bang$qmark$2=class scala/actors/Channel$$anonfun$$bang$qmark$2 of class scala/actors/Channel
   public final #149= #85 of #10; //$anonfun$reactWithin$1=class scala/actors/Channel$$anonfun$reactWithin$1 of class scala/actors/Channel
   public final #150= #108 of #10; //$anonfun$receiveWithin$1=class scala/actors/Channel$$anonfun$receiveWithin$1 of class scala/actors/Channel
  minor version: 0
  major version: 49
  Constant pool:
const #1 = Asciz	SourceFile;
const #2 = Asciz	Channel.scala;
const #3 = Asciz	receiver;
const #4 = Asciz	Lscala/actors/Reactor;;
const #5 = Asciz	<init>;
const #6 = Asciz	(Lscala/actors/Reactor;)V;
const #7 = Asciz	Code;
const #8 = Asciz	LineNumberTable;
const #9 = Asciz	scala/actors/Channel;
const #10 = class	#9;	//  scala/actors/Channel
const #11 = NameAndType	#3:#4;//  receiver:Lscala/actors/Reactor;
const #12 = Field	#10.#11;	//  scala/actors/Channel.receiver:Lscala/actors/Reactor;
const #13 = Asciz	java/lang/Object;
const #14 = class	#13;	//  java/lang/Object
const #15 = Asciz	()V;
const #16 = NameAndType	#5:#15;//  "<init>":()V
const #17 = Method	#14.#16;	//  java/lang/Object."<init>":()V
const #18 = Asciz	this;
const #19 = Asciz	Lscala/actors/Channel;;
const #20 = Asciz	LocalVariableTable;
const #21 = Asciz	Signature;
const #22 = Asciz	$bang$qmark;
const #23 = Asciz	(JLjava/lang/Object;)Lscala/Option;;
const #24 = Asciz	scala/actors/Actor$;
const #25 = class	#24;	//  scala/actors/Actor$
const #26 = Asciz	MODULE$;
const #27 = Asciz	Lscala/actors/Actor$;;
const #28 = NameAndType	#26:#27;//  MODULE$:Lscala/actors/Actor$;
const #29 = Field	#25.#28;	//  scala/actors/Actor$.MODULE$:Lscala/actors/Actor$;
const #30 = Asciz	()Lscala/actors/Reactor;;
const #31 = NameAndType	#3:#30;//  receiver:()Lscala/actors/Reactor;
const #32 = Method	#10.#31;	//  scala/actors/Channel.receiver:()Lscala/actors/Reactor;
const #33 = Asciz	scala/actors/Reactor;
const #34 = class	#33;	//  scala/actors/Reactor
const #35 = Asciz	scheduler;
const #36 = Asciz	()Lscala/actors/IScheduler;;
const #37 = NameAndType	#35:#36;//  scheduler:()Lscala/actors/IScheduler;
const #38 = InterfaceMethod	#34.#37;	//  scala/actors/Reactor.scheduler:()Lscala/actors/IScheduler;
const #39 = Asciz	self;
const #40 = Asciz	(Lscala/actors/IScheduler;)Lscala/actors/Actor;;
const #41 = NameAndType	#39:#40;//  self:(Lscala/actors/IScheduler;)Lscala/actors/Actor;
const #42 = Method	#25.#41;	//  scala/actors/Actor$.self:(Lscala/actors/IScheduler;)Lscala/actors/Actor;
const #43 = NameAndType	#5:#6;//  "<init>":(Lscala/actors/Reactor;)V
const #44 = Method	#10.#43;	//  scala/actors/Channel."<init>":(Lscala/actors/Reactor;)V
const #45 = Asciz	scala/actors/$bang;
const #46 = class	#45;	//  scala/actors/$bang
const #47 = Asciz	(Lscala/actors/Channel;Ljava/lang/Object;)V;
const #48 = NameAndType	#5:#47;//  "<init>":(Lscala/actors/Channel;Ljava/lang/Object;)V
const #49 = Method	#46.#48;	//  scala/actors/$bang."<init>":(Lscala/actors/Channel;Ljava/lang/Object;)V
const #50 = Asciz	send;
const #51 = Asciz	(Ljava/lang/Object;Lscala/actors/OutputChannel;)V;
const #52 = NameAndType	#50:#51;//  send:(Ljava/lang/Object;Lscala/actors/OutputChannel;)V
const #53 = InterfaceMethod	#34.#52;	//  scala/actors/Reactor.send:(Ljava/lang/Object;Lscala/actors/OutputChannel;)V
const #54 = Asciz	scala/actors/Channel$$anonfun$$bang$qmark$2;
const #55 = class	#54;	//  scala/actors/Channel$$anonfun$$bang$qmark$2
const #56 = Asciz	(Lscala/actors/Channel;)V;
const #57 = NameAndType	#5:#56;//  "<init>":(Lscala/actors/Channel;)V
const #58 = Method	#55.#57;	//  scala/actors/Channel$$anonfun$$bang$qmark$2."<init>":(Lscala/actors/Channel;)V
const #59 = Asciz	receiveWithin;
const #60 = Asciz	(JLscala/PartialFunction;)Ljava/lang/Object;;
const #61 = NameAndType	#59:#60;//  receiveWithin:(JLscala/PartialFunction;)Ljava/lang/Object;
const #62 = Method	#10.#61;	//  scala/actors/Channel.receiveWithin:(JLscala/PartialFunction;)Ljava/lang/Object;
const #63 = Asciz	scala/Option;
const #64 = class	#63;	//  scala/Option
const #65 = Asciz	msec;
const #66 = Asciz	J;
const #67 = Asciz	msg;
const #68 = Asciz	Ljava/lang/Object;;
const #69 = Asciz	replyCh;
const #70 = Asciz	(JTMsg;)Lscala/Option<Ljava/lang/Object;>;;
const #71 = Asciz	(Ljava/lang/Object;)Ljava/lang/Object;;
const #72 = Asciz	scala/actors/Channel$$anonfun$$bang$qmark$1;
const #73 = class	#72;	//  scala/actors/Channel$$anonfun$$bang$qmark$1
const #74 = Method	#73.#57;	//  scala/actors/Channel$$anonfun$$bang$qmark$1."<init>":(Lscala/actors/Channel;)V
const #75 = Asciz	receive;
const #76 = Asciz	(Lscala/PartialFunction;)Ljava/lang/Object;;
const #77 = NameAndType	#75:#76;//  receive:(Lscala/PartialFunction;)Ljava/lang/Object;
const #78 = Method	#10.#77;	//  scala/actors/Channel.receive:(Lscala/PartialFunction;)Ljava/lang/Object;
const #79 = Asciz	(TMsg;)Ljava/lang/Object;;
const #80 = Asciz	reactWithin;
const #81 = Asciz	(JLscala/PartialFunction;)Lscala/runtime/Nothing$;;
const #82 = Asciz	scala/actors/Actor;
const #83 = class	#82;	//  scala/actors/Actor
const #84 = Asciz	scala/actors/Channel$$anonfun$reactWithin$1;
const #85 = class	#84;	//  scala/actors/Channel$$anonfun$reactWithin$1
const #86 = Asciz	(Lscala/actors/Channel;Lscala/PartialFunction;Lscala/actors/Channel;)V;
const #87 = NameAndType	#5:#86;//  "<init>":(Lscala/actors/Channel;Lscala/PartialFunction;Lscala/actors/Channel;)V
const #88 = Method	#85.#87;	//  scala/actors/Channel$$anonfun$reactWithin$1."<init>":(Lscala/actors/Channel;Lscala/PartialFunction;Lscala/actors/Channel;)V
const #89 = NameAndType	#80:#81;//  reactWithin:(JLscala/PartialFunction;)Lscala/runtime/Nothing$;
const #90 = InterfaceMethod	#83.#89;	//  scala/actors/Actor.reactWithin:(JLscala/PartialFunction;)Lscala/runtime/Nothing$;
const #91 = Asciz	f$4;
const #92 = Asciz	Lscala/PartialFunction;;
const #93 = Asciz	C$4;
const #94 = Asciz	recvActor;
const #95 = Asciz	Lscala/actors/Actor;;
const #96 = Asciz	(JLscala/PartialFunction<Ljava/lang/Object;Ljava/lang/Object;>;)Lscala/runtime/Nothing$;;
const #97 = Asciz	react;
const #98 = Asciz	(Lscala/PartialFunction;)Lscala/runtime/Nothing$;;
const #99 = Asciz	scala/actors/Channel$$anonfun$react$1;
const #100 = class	#99;	//  scala/actors/Channel$$anonfun$react$1
const #101 = Method	#100.#87;	//  scala/actors/Channel$$anonfun$react$1."<init>":(Lscala/actors/Channel;Lscala/PartialFunction;Lscala/actors/Channel;)V
const #102 = NameAndType	#97:#98;//  react:(Lscala/PartialFunction;)Lscala/runtime/Nothing$;
const #103 = InterfaceMethod	#34.#102;	//  scala/actors/Reactor.react:(Lscala/PartialFunction;)Lscala/runtime/Nothing$;
const #104 = Asciz	f$3;
const #105 = Asciz	C$3;
const #106 = Asciz	(Lscala/PartialFunction<TMsg;Ljava/lang/Object;>;)Lscala/runtime/Nothing$;;
const #107 = Asciz	scala/actors/Channel$$anonfun$receiveWithin$1;
const #108 = class	#107;	//  scala/actors/Channel$$anonfun$receiveWithin$1
const #109 = Method	#108.#87;	//  scala/actors/Channel$$anonfun$receiveWithin$1."<init>":(Lscala/actors/Channel;Lscala/PartialFunction;Lscala/actors/Channel;)V
const #110 = InterfaceMethod	#83.#61;	//  scala/actors/Actor.receiveWithin:(JLscala/PartialFunction;)Ljava/lang/Object;
const #111 = Asciz	f$2;
const #112 = Asciz	C$2;
const #113 = Asciz	<R:Ljava/lang/Object;>(JLscala/PartialFunction<Ljava/lang/Object;TR;>;)TR;;
const #114 = Asciz	$qmark;
const #115 = Asciz	()Ljava/lang/Object;;
const #116 = Asciz	scala/actors/Channel$$anonfun$$qmark$1;
const #117 = class	#116;	//  scala/actors/Channel$$anonfun$$qmark$1
const #118 = Method	#117.#57;	//  scala/actors/Channel$$anonfun$$qmark$1."<init>":(Lscala/actors/Channel;)V
const #119 = Asciz	()TMsg;;
const #120 = Asciz	scala/actors/Channel$$anonfun$receive$1;
const #121 = class	#120;	//  scala/actors/Channel$$anonfun$receive$1
const #122 = Method	#121.#87;	//  scala/actors/Channel$$anonfun$receive$1."<init>":(Lscala/actors/Channel;Lscala/PartialFunction;Lscala/actors/Channel;)V
const #123 = InterfaceMethod	#83.#77;	//  scala/actors/Actor.receive:(Lscala/PartialFunction;)Ljava/lang/Object;
const #124 = Asciz	f$1;
const #125 = Asciz	C$1;
const #126 = Asciz	<R:Ljava/lang/Object;>(Lscala/PartialFunction<TMsg;TR;>;)TR;;
const #127 = Asciz	forward;
const #128 = Asciz	(Ljava/lang/Object;)V;
const #129 = NameAndType	#127:#128;//  forward:(Ljava/lang/Object;)V
const #130 = InterfaceMethod	#34.#129;	//  scala/actors/Reactor.forward:(Ljava/lang/Object;)V
const #131 = Asciz	(TMsg;)V;
const #132 = Asciz	replyTo;
const #133 = Asciz	Lscala/actors/OutputChannel;;
const #134 = Asciz	(TMsg;Lscala/actors/OutputChannel<Ljava/lang/Object;>;)V;
const #135 = Asciz	$bang;
const #136 = NameAndType	#135:#128;//  $bang:(Ljava/lang/Object;)V
const #137 = InterfaceMethod	#34.#136;	//  scala/actors/Reactor.$bang:(Ljava/lang/Object;)V
const #138 = Asciz	rawSelf;
const #139 = NameAndType	#138:#30;//  rawSelf:()Lscala/actors/Reactor;
const #140 = Method	#25.#139;	//  scala/actors/Actor$.rawSelf:()Lscala/actors/Reactor;
const #141 = Asciz	<Msg:Ljava/lang/Object;>Ljava/lang/Object;Lscala/actors/InputChannel<TMsg;>;Lscala/actors/OutputChannel<TMsg;>;Lscala/ScalaObject;;
const #142 = Asciz	ScalaSig;
const #143 = Asciz	InnerClasses;
const #144 = Asciz	$anonfun$react$1;
const #145 = Asciz	$anonfun$$qmark$1;
const #146 = Asciz	$anonfun$receive$1;
const #147 = Asciz	$anonfun$$bang$qmark$1;
const #148 = Asciz	$anonfun$$bang$qmark$2;
const #149 = Asciz	$anonfun$reactWithin$1;
const #150 = Asciz	$anonfun$receiveWithin$1;
const #151 = Asciz	scala/actors/InputChannel;
const #152 = class	#151;	//  scala/actors/InputChannel
const #153 = Asciz	scala/actors/OutputChannel;
const #154 = class	#153;	//  scala/actors/OutputChannel
const #155 = Asciz	scala/ScalaObject;
const #156 = class	#155;	//  scala/ScalaObject

{
public scala.actors.Channel(scala.actors.Reactor);
  Code:
   Stack=2, Locals=2, Args_size=2
   0:	aload_0
   1:	aload_1
   2:	putfield	#12; //Field receiver:Lscala/actors/Reactor;
   5:	aload_0
   6:	invokespecial	#17; //Method java/lang/Object."<init>":()V
   9:	return
  LineNumberTable: 
   line 41: 0

  LocalVariableTable: 
   Start  Length  Slot  Name   Signature
   0      10      0    this       Lscala/actors/Channel;
   0      10      1    receiver       Lscala/actors/Reactor;

  Signature: length = 0x2
   00 06 

public scala.Option $bang$qmark(long, java.lang.Object);
  Code:
   Stack=6, Locals=5, Args_size=3
   0:	new	#10; //class scala/actors/Channel
   3:	dup
   4:	getstatic	#29; //Field scala/actors/Actor$.MODULE$:Lscala/actors/Actor$;
   7:	aload_0
   8:	invokevirtual	#32; //Method receiver:()Lscala/actors/Reactor;
   11:	invokeinterface	#38,  1; //InterfaceMethod scala/actors/Reactor.scheduler:()Lscala/actors/IScheduler;
   16:	invokevirtual	#42; //Method scala/actors/Actor$.self:(Lscala/actors/IScheduler;)Lscala/actors/Actor;
   19:	invokespecial	#44; //Method "<init>":(Lscala/actors/Reactor;)V
   22:	astore	4
   24:	aload_0
   25:	invokevirtual	#32; //Method receiver:()Lscala/actors/Reactor;
   28:	new	#46; //class scala/actors/$bang
   31:	dup
   32:	aload_0
   33:	aload_3
   34:	invokespecial	#49; //Method scala/actors/$bang."<init>":(Lscala/actors/Channel;Ljava/lang/Object;)V
   37:	aload	4
   39:	invokeinterface	#53,  3; //InterfaceMethod scala/actors/Reactor.send:(Ljava/lang/Object;Lscala/actors/OutputChannel;)V
   44:	aload	4
   46:	lload_1
   47:	new	#55; //class scala/actors/Channel$$anonfun$$bang$qmark$2
   50:	dup
   51:	aload_0
   52:	invokespecial	#58; //Method scala/actors/Channel$$anonfun$$bang$qmark$2."<init>":(Lscala/actors/Channel;)V
   55:	invokevirtual	#62; //Method receiveWithin:(JLscala/PartialFunction;)Ljava/lang/Object;
   58:	checkcast	#64; //class scala/Option
   61:	areturn
  LineNumberTable: 
   line 170: 0
   line 171: 24
   line 172: 44

  LocalVariableTable: 
   Start  Length  Slot  Name   Signature
   0      62      0    this       Lscala/actors/Channel;
   0      62      1    msec       J
   0      62      3    msg       Ljava/lang/Object;
   24      37      4    replyCh       Lscala/actors/Channel;

  Signature: length = 0x2
   00 46 

public java.lang.Object $bang$qmark(java.lang.Object);
  Code:
   Stack=5, Locals=3, Args_size=2
   0:	new	#10; //class scala/actors/Channel
   3:	dup
   4:	getstatic	#29; //Field scala/actors/Actor$.MODULE$:Lscala/actors/Actor$;
   7:	aload_0
   8:	invokevirtual	#32; //Method receiver:()Lscala/actors/Reactor;
   11:	invokeinterface	#38,  1; //InterfaceMethod scala/actors/Reactor.scheduler:()Lscala/actors/IScheduler;
   16:	invokevirtual	#42; //Method scala/actors/Actor$.self:(Lscala/actors/IScheduler;)Lscala/actors/Actor;
   19:	invokespecial	#44; //Method "<init>":(Lscala/actors/Reactor;)V
   22:	astore_2
   23:	aload_0
   24:	invokevirtual	#32; //Method receiver:()Lscala/actors/Reactor;
   27:	new	#46; //class scala/actors/$bang
   30:	dup
   31:	aload_0
   32:	aload_1
   33:	invokespecial	#49; //Method scala/actors/$bang."<init>":(Lscala/actors/Channel;Ljava/lang/Object;)V
   36:	aload_2
   37:	invokeinterface	#53,  3; //InterfaceMethod scala/actors/Reactor.send:(Ljava/lang/Object;Lscala/actors/OutputChannel;)V
   42:	aload_2
   43:	new	#73; //class scala/actors/Channel$$anonfun$$bang$qmark$1
   46:	dup
   47:	aload_0
   48:	invokespecial	#74; //Method scala/actors/Channel$$anonfun$$bang$qmark$1."<init>":(Lscala/actors/Channel;)V
   51:	invokevirtual	#78; //Method receive:(Lscala/PartialFunction;)Ljava/lang/Object;
   54:	areturn
  LineNumberTable: 
   line 153: 0
   line 154: 23
   line 155: 42

  LocalVariableTable: 
   Start  Length  Slot  Name   Signature
   0      55      0    this       Lscala/actors/Channel;
   0      55      1    msg       Ljava/lang/Object;
   23      31      2    replyCh       Lscala/actors/Channel;

  Signature: length = 0x2
   00 4F 

public scala.runtime.Nothing$ reactWithin(long, scala.PartialFunction);
  Code:
   Stack=8, Locals=6, Args_size=3
   0:	aload_0
   1:	astore	4
   3:	aload_0
   4:	invokevirtual	#32; //Method receiver:()Lscala/actors/Reactor;
   7:	checkcast	#83; //class scala/actors/Actor
   10:	astore	5
   12:	aload	5
   14:	lload_1
   15:	new	#85; //class scala/actors/Channel$$anonfun$reactWithin$1
   18:	dup
   19:	aload_0
   20:	aload_3
   21:	aload	4
   23:	invokespecial	#88; //Method scala/actors/Channel$$anonfun$reactWithin$1."<init>":(Lscala/actors/Channel;Lscala/PartialFunction;Lscala/actors/Channel;)V
   26:	invokeinterface	#90,  4; //InterfaceMethod scala/actors/Actor.reactWithin:(JLscala/PartialFunction;)Lscala/runtime/Nothing$;
   31:	areturn
  LineNumberTable: 
   line 137: 0
   line 138: 3
   line 139: 12

  LocalVariableTable: 
   Start  Length  Slot  Name   Signature
   0      32      0    this       Lscala/actors/Channel;
   0      32      1    msec       J
   0      32      3    f$4       Lscala/PartialFunction;
   3      28      4    C$4       Lscala/actors/Channel;
   12      19      5    recvActor       Lscala/actors/Actor;

  Signature: length = 0x2
   00 60 

public scala.runtime.Nothing$ react(scala.PartialFunction);
  Code:
   Stack=6, Locals=3, Args_size=2
   0:	aload_0
   1:	astore_2
   2:	aload_0
   3:	invokevirtual	#32; //Method receiver:()Lscala/actors/Reactor;
   6:	new	#100; //class scala/actors/Channel$$anonfun$react$1
   9:	dup
   10:	aload_0
   11:	aload_1
   12:	aload_2
   13:	invokespecial	#101; //Method scala/actors/Channel$$anonfun$react$1."<init>":(Lscala/actors/Channel;Lscala/PartialFunction;Lscala/actors/Channel;)V
   16:	invokeinterface	#103,  2; //InterfaceMethod scala/actors/Reactor.react:(Lscala/PartialFunction;)Lscala/runtime/Nothing$;
   21:	areturn
  LineNumberTable: 
   line 120: 0
   line 121: 2

  LocalVariableTable: 
   Start  Length  Slot  Name   Signature
   0      22      0    this       Lscala/actors/Channel;
   0      22      1    f$3       Lscala/PartialFunction;
   2      19      2    C$3       Lscala/actors/Channel;

  Signature: length = 0x2
   00 6A 

public java.lang.Object receiveWithin(long, scala.PartialFunction);
  Code:
   Stack=8, Locals=6, Args_size=3
   0:	aload_0
   1:	astore	4
   3:	aload_0
   4:	invokevirtual	#32; //Method receiver:()Lscala/actors/Reactor;
   7:	checkcast	#83; //class scala/actors/Actor
   10:	astore	5
   12:	aload	5
   14:	lload_1
   15:	new	#108; //class scala/actors/Channel$$anonfun$receiveWithin$1
   18:	dup
   19:	aload_0
   20:	aload_3
   21:	aload	4
   23:	invokespecial	#109; //Method scala/actors/Channel$$anonfun$receiveWithin$1."<init>":(Lscala/actors/Channel;Lscala/PartialFunction;Lscala/actors/Channel;)V
   26:	invokeinterface	#110,  4; //InterfaceMethod scala/actors/Actor.receiveWithin:(JLscala/PartialFunction;)Ljava/lang/Object;
   31:	areturn
  LineNumberTable: 
   line 103: 0
   line 104: 3
   line 105: 12

  LocalVariableTable: 
   Start  Length  Slot  Name   Signature
   0      32      0    this       Lscala/actors/Channel;
   0      32      1    msec       J
   0      32      3    f$2       Lscala/PartialFunction;
   3      28      4    C$2       Lscala/actors/Channel;
   12      19      5    recvActor       Lscala/actors/Actor;

  Signature: length = 0x2
   00 71 

public java.lang.Object $qmark();
  Code:
   Stack=4, Locals=1, Args_size=1
   0:	aload_0
   1:	new	#117; //class scala/actors/Channel$$anonfun$$qmark$1
   4:	dup
   5:	aload_0
   6:	invokespecial	#118; //Method scala/actors/Channel$$anonfun$$qmark$1."<init>":(Lscala/actors/Channel;)V
   9:	invokevirtual	#78; //Method receive:(Lscala/PartialFunction;)Ljava/lang/Object;
   12:	areturn
  LineNumberTable: 
   line 90: 0

  Signature: length = 0x2
   00 77 

public java.lang.Object receive(scala.PartialFunction);
  Code:
   Stack=6, Locals=4, Args_size=2
   0:	aload_0
   1:	astore_2
   2:	aload_0
   3:	invokevirtual	#32; //Method receiver:()Lscala/actors/Reactor;
   6:	checkcast	#83; //class scala/actors/Actor
   9:	astore_3
   10:	aload_3
   11:	new	#121; //class scala/actors/Channel$$anonfun$receive$1
   14:	dup
   15:	aload_0
   16:	aload_1
   17:	aload_2
   18:	invokespecial	#122; //Method scala/actors/Channel$$anonfun$receive$1."<init>":(Lscala/actors/Channel;Lscala/PartialFunction;Lscala/actors/Channel;)V
   21:	invokeinterface	#123,  2; //InterfaceMethod scala/actors/Actor.receive:(Lscala/PartialFunction;)Ljava/lang/Object;
   26:	areturn
  LineNumberTable: 
   line 80: 0
   line 81: 2
   line 82: 10

  LocalVariableTable: 
   Start  Length  Slot  Name   Signature
   0      27      0    this       Lscala/actors/Channel;
   0      27      1    f$1       Lscala/PartialFunction;
   2      24      2    C$1       Lscala/actors/Channel;
   10      16      3    recvActor       Lscala/actors/Actor;

  Signature: length = 0x2
   00 7E 

public void forward(java.lang.Object);
  Code:
   Stack=5, Locals=2, Args_size=2
   0:	aload_0
   1:	invokevirtual	#32; //Method receiver:()Lscala/actors/Reactor;
   4:	new	#46; //class scala/actors/$bang
   7:	dup
   8:	aload_0
   9:	aload_1
   10:	invokespecial	#49; //Method scala/actors/$bang."<init>":(Lscala/actors/Channel;Ljava/lang/Object;)V
   13:	invokeinterface	#130,  2; //InterfaceMethod scala/actors/Reactor.forward:(Ljava/lang/Object;)V
   18:	return
  LineNumberTable: 
   line 70: 0

  LocalVariableTable: 
   Start  Length  Slot  Name   Signature
   0      19      0    this       Lscala/actors/Channel;
   0      19      1    msg       Ljava/lang/Object;

  Signature: length = 0x2
   00 FFFFFF83 

public void send(java.lang.Object, scala.actors.OutputChannel);
  Code:
   Stack=5, Locals=3, Args_size=3
   0:	aload_0
   1:	invokevirtual	#32; //Method receiver:()Lscala/actors/Reactor;
   4:	new	#46; //class scala/actors/$bang
   7:	dup
   8:	aload_0
   9:	aload_1
   10:	invokespecial	#49; //Method scala/actors/$bang."<init>":(Lscala/actors/Channel;Ljava/lang/Object;)V
   13:	aload_2
   14:	invokeinterface	#53,  3; //InterfaceMethod scala/actors/Reactor.send:(Ljava/lang/Object;Lscala/actors/OutputChannel;)V
   19:	return
  LineNumberTable: 
   line 62: 0

  LocalVariableTable: 
   Start  Length  Slot  Name   Signature
   0      20      0    this       Lscala/actors/Channel;
   0      20      1    msg       Ljava/lang/Object;
   0      20      2    replyTo       Lscala/actors/OutputChannel;

  Signature: length = 0x2
   00 FFFFFF86 

public void $bang(java.lang.Object);
  Code:
   Stack=5, Locals=2, Args_size=2
   0:	aload_0
   1:	invokevirtual	#32; //Method receiver:()Lscala/actors/Reactor;
   4:	new	#46; //class scala/actors/$bang
   7:	dup
   8:	aload_0
   9:	aload_1
   10:	invokespecial	#49; //Method scala/actors/$bang."<init>":(Lscala/actors/Channel;Ljava/lang/Object;)V
   13:	invokeinterface	#137,  2; //InterfaceMethod scala/actors/Reactor.$bang:(Ljava/lang/Object;)V
   18:	return
  LineNumberTable: 
   line 51: 0

  LocalVariableTable: 
   Start  Length  Slot  Name   Signature
   0      19      0    this       Lscala/actors/Channel;
   0      19      1    msg       Ljava/lang/Object;

  Signature: length = 0x2
   00 FFFFFF83 

public scala.actors.Channel();
  Code:
   Stack=2, Locals=1, Args_size=1
   0:	aload_0
   1:	getstatic	#29; //Field scala/actors/Actor$.MODULE$:Lscala/actors/Actor$;
   4:	invokevirtual	#140; //Method scala/actors/Actor$.rawSelf:()Lscala/actors/Reactor;
   7:	invokespecial	#44; //Method "<init>":(Lscala/actors/Reactor;)V
   10:	return
  LineNumberTable: 
   line 43: 0

  Signature: length = 0x2
   00 0F 

public scala.actors.Reactor receiver();
  Code:
   Stack=1, Locals=1, Args_size=1
   0:	aload_0
   1:	getfield	#12; //Field receiver:Lscala/actors/Reactor;
   4:	areturn
  LineNumberTable: 
   line 41: 0


}

