Compiled from "Channel.scala"
public class scala.actors.Channel extends java.lang.Object implements scala.actors.InputChannel,scala.actors.OutputChannel,scala.actors.CanReply,scala.ScalaObject
  SourceFile: "Channel.scala"
  ScalaSig: length = 0x3
   05 00 00 
  Signature: length = 0x2
   00 FFFFFF9A 
  RuntimeVisibleAnnotations: length = 0xB
   00 01 00 FFFFFF9B 00 01 00 FFFFFF9C 73 00 FFFFFF9D 
  InnerClass: 
   public final $anonfun$react$1=class scala/actors/Channel$$anonfun$react$1 of class scala/actors/Channel
   public final $anonfun$$qmark$1=class scala/actors/Channel$$anonfun$$qmark$1 of class scala/actors/Channel
   public final $anonfun$receive$1=class scala/actors/Channel$$anonfun$receive$1 of class scala/actors/Channel
   public final $anonfun$$bang$qmark$2=class scala/actors/Channel$$anonfun$$bang$qmark$2 of class scala/actors/Channel
   public final $anonfun$$bang$qmark$1=class scala/actors/Channel$$anonfun$$bang$qmark$1 of class scala/actors/Channel
   public final $anonfun$reactWithin$1=class scala/actors/Channel$$anonfun$reactWithin$1 of class scala/actors/Channel
   public final $anonfun$receiveWithin$1=class scala/actors/Channel$$anonfun$receiveWithin$1 of class scala/actors/Channel
  minor version: 0
  major version: 49
  Constant pool:
Asciz	SourceFile;
Asciz	Channel.scala;
Asciz	receiver;
Asciz	Lscala/actors/Actor;;
Asciz	$bang$bang;
Asciz	(Ljava/lang/Object;)Lscala/Function0;;
Asciz	Code;
Asciz	LineNumberTable;
Asciz	scala/actors/CanReply$class;
class	scala/actors/CanReply$class
Asciz	(Lscala/actors/CanReply;Ljava/lang/Object;)Lscala/Function0;;
NameAndType	$bang$bang:(Lscala/actors/CanReply;Ljava/lang/Object;)Lscala/Function0;
Method	scala/actors/CanReply$class.$bang$bang:(Lscala/actors/CanReply;Ljava/lang/Object;)Lscala/Function0;
Asciz	this;
Asciz	Lscala/actors/Channel;;
Asciz	msg;
Asciz	Ljava/lang/Object;;
Asciz	LocalVariableTable;
Asciz	(Ljava/lang/Object;Lscala/PartialFunction;)Lscala/Function0;;
Asciz	(Lscala/actors/CanReply;Ljava/lang/Object;Lscala/PartialFunction;)Lscala/Function0;;
NameAndType	$bang$bang:(Lscala/actors/CanReply;Ljava/lang/Object;Lscala/PartialFunction;)Lscala/Function0;
Method	scala/actors/CanReply$class.$bang$bang:(Lscala/actors/CanReply;Ljava/lang/Object;Lscala/PartialFunction;)Lscala/Function0;
Asciz	handler;
Asciz	Lscala/PartialFunction;;
Asciz	()Lscala/actors/Actor;;
Asciz	scala/actors/Channel;
class	scala/actors/Channel
NameAndType	receiver:Lscala/actors/Actor;
Field	scala/actors/Channel.receiver:Lscala/actors/Actor;
Asciz	<init>;
Asciz	()V;
Asciz	scala/actors/Actor$;
class	scala/actors/Actor$
Asciz	MODULE$;
Asciz	Lscala/actors/Actor$;;
NameAndType	MODULE$:Lscala/actors/Actor$;
Field	scala/actors/Actor$.MODULE$:Lscala/actors/Actor$;
Asciz	self;
NameAndType	self:()Lscala/actors/Actor;
Method	scala/actors/Actor$.self:()Lscala/actors/Actor;
Asciz	(Lscala/actors/Actor;)V;
NameAndType	"<init>":(Lscala/actors/Actor;)V
Method	scala/actors/Channel."<init>":(Lscala/actors/Actor;)V
Asciz	Signature;
Asciz	$bang;
Asciz	(Ljava/lang/Object;)V;
NameAndType	receiver:()Lscala/actors/Actor;
Method	scala/actors/Channel.receiver:()Lscala/actors/Actor;
Asciz	scala/actors/$bang;
class	scala/actors/$bang
Asciz	(Lscala/actors/Channel;Ljava/lang/Object;)V;
NameAndType	"<init>":(Lscala/actors/Channel;Ljava/lang/Object;)V
Method	scala/actors/$bang."<init>":(Lscala/actors/Channel;Ljava/lang/Object;)V
Asciz	scala/actors/ReplyReactor;
class	scala/actors/ReplyReactor
NameAndType	$bang:(Ljava/lang/Object;)V
InterfaceMethod	scala/actors/ReplyReactor.$bang:(Ljava/lang/Object;)V
Asciz	(TMsg;)V;
Asciz	send;
Asciz	(Ljava/lang/Object;Lscala/actors/OutputChannel;)V;
Asciz	scala/actors/Reactor;
class	scala/actors/Reactor
NameAndType	send:(Ljava/lang/Object;Lscala/actors/OutputChannel;)V
InterfaceMethod	scala/actors/Reactor.send:(Ljava/lang/Object;Lscala/actors/OutputChannel;)V
Asciz	replyTo;
Asciz	Lscala/actors/OutputChannel;;
Asciz	(TMsg;Lscala/actors/OutputChannel<Ljava/lang/Object;>;)V;
Asciz	forward;
NameAndType	forward:(Ljava/lang/Object;)V
InterfaceMethod	scala/actors/ReplyReactor.forward:(Ljava/lang/Object;)V
Asciz	receive;
Asciz	(Lscala/PartialFunction;)Ljava/lang/Object;;
Asciz	scala/actors/Channel$$anonfun$receive$1;
class	scala/actors/Channel$$anonfun$receive$1
Asciz	(Lscala/actors/Channel;Lscala/PartialFunction;Lscala/actors/Channel;)V;
NameAndType	"<init>":(Lscala/actors/Channel;Lscala/PartialFunction;Lscala/actors/Channel;)V
Method	scala/actors/Channel$$anonfun$receive$1."<init>":(Lscala/actors/Channel;Lscala/PartialFunction;Lscala/actors/Channel;)V
Asciz	scala/actors/Actor;
class	scala/actors/Actor
NameAndType	receive:(Lscala/PartialFunction;)Ljava/lang/Object;
InterfaceMethod	scala/actors/Actor.receive:(Lscala/PartialFunction;)Ljava/lang/Object;
Asciz	f$1;
Asciz	recvActor;
Asciz	<R:Ljava/lang/Object;>(Lscala/PartialFunction<TMsg;TR;>;)TR;;
Asciz	$qmark;
Asciz	()Ljava/lang/Object;;
Asciz	scala/actors/Channel$$anonfun$$qmark$1;
class	scala/actors/Channel$$anonfun$$qmark$1
Asciz	(Lscala/actors/Channel;)V;
NameAndType	"<init>":(Lscala/actors/Channel;)V
Method	scala/actors/Channel$$anonfun$$qmark$1."<init>":(Lscala/actors/Channel;)V
Method	scala/actors/Channel.receive:(Lscala/PartialFunction;)Ljava/lang/Object;
Asciz	()TMsg;;
Asciz	receiveWithin;
Asciz	(JLscala/PartialFunction;)Ljava/lang/Object;;
Asciz	scala/actors/Channel$$anonfun$receiveWithin$1;
class	scala/actors/Channel$$anonfun$receiveWithin$1
Method	scala/actors/Channel$$anonfun$receiveWithin$1."<init>":(Lscala/actors/Channel;Lscala/PartialFunction;Lscala/actors/Channel;)V
NameAndType	receiveWithin:(JLscala/PartialFunction;)Ljava/lang/Object;
InterfaceMethod	scala/actors/Actor.receiveWithin:(JLscala/PartialFunction;)Ljava/lang/Object;
Asciz	msec;
Asciz	J;
Asciz	f$2;
Asciz	<R:Ljava/lang/Object;>(JLscala/PartialFunction<Ljava/lang/Object;TR;>;)TR;;
Asciz	react;
Asciz	(Lscala/PartialFunction;)Lscala/runtime/Nothing$;;
Asciz	scala/actors/Channel$$anonfun$react$1;
class	scala/actors/Channel$$anonfun$react$1
Method	scala/actors/Channel$$anonfun$react$1."<init>":(Lscala/actors/Channel;Lscala/PartialFunction;Lscala/actors/Channel;)V
NameAndType	react:(Lscala/PartialFunction;)Lscala/runtime/Nothing$;
InterfaceMethod	scala/actors/Actor.react:(Lscala/PartialFunction;)Lscala/runtime/Nothing$;
Asciz	f$3;
Asciz	(Lscala/PartialFunction<TMsg;Ljava/lang/Object;>;)Lscala/runtime/Nothing$;;
Asciz	reactWithin;
Asciz	(JLscala/PartialFunction;)Lscala/runtime/Nothing$;;
Asciz	scala/actors/Channel$$anonfun$reactWithin$1;
class	scala/actors/Channel$$anonfun$reactWithin$1
Method	scala/actors/Channel$$anonfun$reactWithin$1."<init>":(Lscala/actors/Channel;Lscala/PartialFunction;Lscala/actors/Channel;)V
NameAndType	reactWithin:(JLscala/PartialFunction;)Lscala/runtime/Nothing$;
InterfaceMethod	scala/actors/Actor.reactWithin:(JLscala/PartialFunction;)Lscala/runtime/Nothing$;
Asciz	f$4;
Asciz	(JLscala/PartialFunction<Ljava/lang/Object;Ljava/lang/Object;>;)Lscala/runtime/Nothing$;;
Asciz	$bang$qmark;
Asciz	(Ljava/lang/Object;)Ljava/lang/Object;;
Asciz	scheduler;
Asciz	()Lscala/actors/IScheduler;;
NameAndType	scheduler:()Lscala/actors/IScheduler;
InterfaceMethod	scala/actors/Actor.scheduler:()Lscala/actors/IScheduler;
Asciz	(Lscala/actors/IScheduler;)Lscala/actors/Actor;;
NameAndType	self:(Lscala/actors/IScheduler;)Lscala/actors/Actor;
Method	scala/actors/Actor$.self:(Lscala/actors/IScheduler;)Lscala/actors/Actor;
Asciz	scala/actors/Channel$$anonfun$$bang$qmark$1;
class	scala/actors/Channel$$anonfun$$bang$qmark$1
Method	scala/actors/Channel$$anonfun$$bang$qmark$1."<init>":(Lscala/actors/Channel;)V
Asciz	replyCh;
Asciz	(TMsg;)Ljava/lang/Object;;
Asciz	(JLjava/lang/Object;)Lscala/Option;;
Asciz	scala/actors/Channel$$anonfun$$bang$qmark$2;
class	scala/actors/Channel$$anonfun$$bang$qmark$2
Method	scala/actors/Channel$$anonfun$$bang$qmark$2."<init>":(Lscala/actors/Channel;)V
Method	scala/actors/Channel.receiveWithin:(JLscala/PartialFunction;)Ljava/lang/Object;
Asciz	scala/Option;
class	scala/Option
Asciz	(JTMsg;)Lscala/Option<Ljava/lang/Object;>;;
Asciz	java/lang/Object;
class	java/lang/Object
NameAndType	"<init>":()V
Method	java/lang/Object."<init>":()V
Asciz	$init$;
Asciz	(Lscala/actors/CanReply;)V;
NameAndType	$init$:(Lscala/actors/CanReply;)V
Method	scala/actors/CanReply$class.$init$:(Lscala/actors/CanReply;)V
Asciz	ScalaSig;
Asciz	<Msg:Ljava/lang/Object;>Ljava/lang/Object;Lscala/actors/InputChannel<TMsg;>;Lscala/actors/OutputChannel<TMsg;>;Lscala/actors/CanReply<TMsg;Ljava/lang/Object;>;Lscala/ScalaObject;;
Asciz	Lscala/reflect/ScalaSignature;;
Asciz	bytes;
Asciz	aBqa5b]:,GN\t1m;peNT!BgG.Y+\tAqcE\tCe\n\t=ia5\tA\1oO*\ta\"kCZB\ty%M[3diB!cE\tI!%s/;DQtg.7Y9B\t1!\t!b3\tQj]4iqCA!BAqu5j]\"aG\n\"!aA!osB!CI\n\r!!D(viB,Ho5b]:,GKUqB!M*fa2LCA)\tICAATGdm2kK$CII,7-Z5wKJ,!\t%9J!aGo:\tE!!Q\n5\nB]3dK&4XM\tMA\rqJg.;?)\t)dEUAQaA5BQa\ra\"!u!\taOI\tgny}\"aG\ny\"!B+oSRDQQAU\t1!\:h\"DXM3q\"U\tCAQCGq)AsKBdV8IcCJ!*Ag_J<M3qZ\"!I)\"B'\tqa:fGLg/ZF#\"U*Y\tF*M\t)A\rICQ'AUA\t7Y++X\t\ty+:uSdg)8di&|gCZ!,%c6'o[+!)AC;i!/Z2fSZ,w+;iS:,\"AX1}#GC1c!\t1\rS7\tQ1!61d!YbK1\t\4\t5Xm\t7L!\t1{gnU!\ta[e7\r51DQV5A5Ba,y!)qCaY!/Z1di^KG[5o)\t\tHe\")AKagB!1D=)g1g1\"x-!#-8hIElM]6yA\"!v)\"<\tQHcA>B1 \nu$!AB(qi&|gCfsa\rCAsQ;
Asciz	RuntimeVisibleAnnotations;
Asciz	InnerClasses;
Asciz	$anonfun$react$1;
Asciz	$anonfun$$qmark$1;
Asciz	$anonfun$receive$1;
Asciz	$anonfun$$bang$qmark$2;
Asciz	$anonfun$$bang$qmark$1;
Asciz	$anonfun$reactWithin$1;
Asciz	$anonfun$receiveWithin$1;
Asciz	scala/actors/InputChannel;
class	scala/actors/InputChannel
Asciz	scala/actors/OutputChannel;
class	scala/actors/OutputChannel
Asciz	scala/actors/CanReply;
class	scala/actors/CanReply
Asciz	scala/ScalaObject;
class	scala/ScalaObject

{
private final scala.actors.Actor receiver;
  Signature: Lscala/actors/Actor;

public scala.Function0 $bang$bang(java.lang.Object);
  Signature: (Ljava/lang/Object;)Lscala/Function0;
  Code:
   Stack=2, Locals=2, Args_size=2
	aload_0
	aload_1
	invokestatic	Method scala/actors/CanReply$class.$bang$bang:(Lscala/actors/CanReply;Ljava/lang/Object;)Lscala/Function0;
	areturn
  Labels:
  LocalVariableTable: 
   Start  Length  Slot  Name   Signature
   0      6      0    this       Lscala/actors/Channel;
   0      6      1    msg       Ljava/lang/Object;


public scala.Function0 $bang$bang(java.lang.Object, scala.PartialFunction);
  Signature: (Ljava/lang/Object;Lscala/PartialFunction;)Lscala/Function0;
  Code:
   Stack=3, Locals=3, Args_size=3
	aload_0
	aload_1
	aload_2
	invokestatic	Method scala/actors/CanReply$class.$bang$bang:(Lscala/actors/CanReply;Ljava/lang/Object;Lscala/PartialFunction;)Lscala/Function0;
	areturn
  Labels:
  LocalVariableTable: 
   Start  Length  Slot  Name   Signature
   0      7      0    this       Lscala/actors/Channel;
   0      7      1    msg       Ljava/lang/Object;
   0      7      2    handler       Lscala/PartialFunction;


public scala.actors.Actor receiver();
  Signature: ()Lscala/actors/Actor;
  Code:
   Stack=1, Locals=1, Args_size=1
	aload_0
	getfield	Field receiver:Lscala/actors/Actor;
	areturn
  Labels:

public scala.actors.Channel();
  Signature: ()V
  Code:
   Stack=2, Locals=1, Args_size=1
	aload_0
	getstatic	Field scala/actors/Actor$.MODULE$:Lscala/actors/Actor$;
	invokevirtual	Method scala/actors/Actor$.self:()Lscala/actors/Actor;
	invokespecial	Method "<init>":(Lscala/actors/Actor;)V
	return
  Labels:
  Signature: length = 0x2
   00 1F 

public void $bang(java.lang.Object);
  Signature: (Ljava/lang/Object;)V
  Code:
   Stack=5, Locals=2, Args_size=2
	aload_0
	invokevirtual	Method receiver:()Lscala/actors/Actor;
	new	class scala/actors/$bang
	dup
	aload_0
	aload_1
	invokespecial	Method scala/actors/$bang."<init>":(Lscala/actors/Channel;Ljava/lang/Object;)V
	invokeinterface	InterfaceMethod scala/actors/ReplyReactor.$bang:(Ljava/lang/Object;)V
	return
  Labels:
  LocalVariableTable: 
   Start  Length  Slot  Name   Signature
   0      19      0    this       Lscala/actors/Channel;
   0      19      1    msg       Ljava/lang/Object;

  Signature: length = 0x2
   00 3A 

public void send(java.lang.Object, scala.actors.OutputChannel);
  Signature: (Ljava/lang/Object;Lscala/actors/OutputChannel;)V
  Code:
   Stack=5, Locals=3, Args_size=3
	aload_0
	invokevirtual	Method receiver:()Lscala/actors/Actor;
	new	class scala/actors/$bang
	dup
	aload_0
	aload_1
	invokespecial	Method scala/actors/$bang."<init>":(Lscala/actors/Channel;Ljava/lang/Object;)V
	aload_2
	invokeinterface	InterfaceMethod scala/actors/Reactor.send:(Ljava/lang/Object;Lscala/actors/OutputChannel;)V
	return
  Labels:
  LocalVariableTable: 
   Start  Length  Slot  Name   Signature
   0      20      0    this       Lscala/actors/Channel;
   0      20      1    msg       Ljava/lang/Object;
   0      20      2    replyTo       Lscala/actors/OutputChannel;

  Signature: length = 0x2
   00 43 

public void forward(java.lang.Object);
  Signature: (Ljava/lang/Object;)V
  Code:
   Stack=5, Locals=2, Args_size=2
	aload_0
	invokevirtual	Method receiver:()Lscala/actors/Actor;
	new	class scala/actors/$bang
	dup
	aload_0
	aload_1
	invokespecial	Method scala/actors/$bang."<init>":(Lscala/actors/Channel;Ljava/lang/Object;)V
	invokeinterface	InterfaceMethod scala/actors/ReplyReactor.forward:(Ljava/lang/Object;)V
	return
  Labels:
  LocalVariableTable: 
   Start  Length  Slot  Name   Signature
   0      19      0    this       Lscala/actors/Channel;
   0      19      1    msg       Ljava/lang/Object;

  Signature: length = 0x2
   00 3A 

public java.lang.Object receive(scala.PartialFunction);
  Signature: (Lscala/PartialFunction;)Ljava/lang/Object;
  Code:
   Stack=6, Locals=3, Args_size=2
	aload_0
	invokevirtual	Method receiver:()Lscala/actors/Actor;
	astore_2
	aload_2
	new	class scala/actors/Channel$$anonfun$receive$1
	dup
	aload_0
	aload_1
	aload_0
	invokespecial	Method scala/actors/Channel$$anonfun$receive$1."<init>":(Lscala/actors/Channel;Lscala/PartialFunction;Lscala/actors/Channel;)V
	invokeinterface	InterfaceMethod scala/actors/Actor.receive:(Lscala/PartialFunction;)Ljava/lang/Object;
	areturn
  Labels:
  LocalVariableTable: 
   Start  Length  Slot  Name   Signature
   0      22      0    this       Lscala/actors/Channel;
   0      22      1    f$1       Lscala/PartialFunction;
   5      16      2    recvActor       Lscala/actors/Actor;

  Signature: length = 0x2
   00 54 

public java.lang.Object $qmark();
  Signature: ()Ljava/lang/Object;
  Code:
   Stack=4, Locals=1, Args_size=1
	aload_0
	new	class scala/actors/Channel$$anonfun$$qmark$1
	dup
	aload_0
	invokespecial	Method scala/actors/Channel$$anonfun$$qmark$1."<init>":(Lscala/actors/Channel;)V
	invokevirtual	Method receive:(Lscala/PartialFunction;)Ljava/lang/Object;
	areturn
  Labels:
  Signature: length = 0x2
   00 5D 

public java.lang.Object receiveWithin(long, scala.PartialFunction);
  Signature: (JLscala/PartialFunction;)Ljava/lang/Object;
  Code:
   Stack=8, Locals=5, Args_size=3
	aload_0
	invokevirtual	Method receiver:()Lscala/actors/Actor;
	astore	4
	aload	4
	lload_1
	new	class scala/actors/Channel$$anonfun$receiveWithin$1
	dup
	aload_0
	aload_3
	aload_0
	invokespecial	Method scala/actors/Channel$$anonfun$receiveWithin$1."<init>":(Lscala/actors/Channel;Lscala/PartialFunction;Lscala/actors/Channel;)V
	invokeinterface	InterfaceMethod scala/actors/Actor.receiveWithin:(JLscala/PartialFunction;)Ljava/lang/Object;
	areturn
  Labels:
  LocalVariableTable: 
   Start  Length  Slot  Name   Signature
   0      25      0    this       Lscala/actors/Channel;
   0      25      1    msec       J
   0      25      3    f$2       Lscala/PartialFunction;
   6      18      4    recvActor       Lscala/actors/Actor;

  Signature: length = 0x2
   00 68 

public scala.runtime.Nothing$ react(scala.PartialFunction);
  Signature: (Lscala/PartialFunction;)Lscala/runtime/Nothing$;
  Code:
   Stack=6, Locals=2, Args_size=2
	aload_0
	invokevirtual	Method receiver:()Lscala/actors/Actor;
	new	class scala/actors/Channel$$anonfun$react$1
	dup
	aload_0
	aload_1
	aload_0
	invokespecial	Method scala/actors/Channel$$anonfun$react$1."<init>":(Lscala/actors/Channel;Lscala/PartialFunction;Lscala/actors/Channel;)V
	invokeinterface	InterfaceMethod scala/actors/Actor.react:(Lscala/PartialFunction;)Lscala/runtime/Nothing$;
	areturn
  Labels:
  LocalVariableTable: 
   Start  Length  Slot  Name   Signature
   0      20      0    this       Lscala/actors/Channel;
   0      20      1    f$3       Lscala/PartialFunction;

  Signature: length = 0x2
   00 71 

public scala.runtime.Nothing$ reactWithin(long, scala.PartialFunction);
  Signature: (JLscala/PartialFunction;)Lscala/runtime/Nothing$;
  Code:
   Stack=8, Locals=5, Args_size=3
	aload_0
	invokevirtual	Method receiver:()Lscala/actors/Actor;
	astore	4
	aload	4
	lload_1
	new	class scala/actors/Channel$$anonfun$reactWithin$1
	dup
	aload_0
	aload_3
	aload_0
	invokespecial	Method scala/actors/Channel$$anonfun$reactWithin$1."<init>":(Lscala/actors/Channel;Lscala/PartialFunction;Lscala/actors/Channel;)V
	invokeinterface	InterfaceMethod scala/actors/Actor.reactWithin:(JLscala/PartialFunction;)Lscala/runtime/Nothing$;
	areturn
  Labels:
  LocalVariableTable: 
   Start  Length  Slot  Name   Signature
   0      25      0    this       Lscala/actors/Channel;
   0      25      1    msec       J
   0      25      3    f$4       Lscala/PartialFunction;
   6      18      4    recvActor       Lscala/actors/Actor;

  Signature: length = 0x2
   00 7A 

public java.lang.Object $bang$qmark(java.lang.Object);
  Signature: (Ljava/lang/Object;)Ljava/lang/Object;
  Code:
   Stack=5, Locals=3, Args_size=2
	new	class scala/actors/Channel
	dup
	getstatic	Field scala/actors/Actor$.MODULE$:Lscala/actors/Actor$;
	aload_0
	invokevirtual	Method receiver:()Lscala/actors/Actor;
	invokeinterface	InterfaceMethod scala/actors/Actor.scheduler:()Lscala/actors/IScheduler;
	invokevirtual	Method scala/actors/Actor$.self:(Lscala/actors/IScheduler;)Lscala/actors/Actor;
	invokespecial	Method "<init>":(Lscala/actors/Actor;)V
	astore_2
	aload_0
	invokevirtual	Method receiver:()Lscala/actors/Actor;
	new	class scala/actors/$bang
	dup
	aload_0
	aload_1
	invokespecial	Method scala/actors/$bang."<init>":(Lscala/actors/Channel;Ljava/lang/Object;)V
	aload_2
	invokeinterface	InterfaceMethod scala/actors/Reactor.send:(Ljava/lang/Object;Lscala/actors/OutputChannel;)V
	aload_2
	new	class scala/actors/Channel$$anonfun$$bang$qmark$1
	dup
	aload_0
	invokespecial	Method scala/actors/Channel$$anonfun$$bang$qmark$1."<init>":(Lscala/actors/Channel;)V
	invokevirtual	Method receive:(Lscala/PartialFunction;)Ljava/lang/Object;
	areturn
  Labels:
  LocalVariableTable: 
   Start  Length  Slot  Name   Signature
   0      55      0    this       Lscala/actors/Channel;
   0      55      1    msg       Ljava/lang/Object;
   23      31      2    replyCh       Lscala/actors/Channel;

  Signature: length = 0x2
   00 FFFFFF88 

public scala.Option $bang$qmark(long, java.lang.Object);
  Signature: (JLjava/lang/Object;)Lscala/Option;
  Code:
   Stack=6, Locals=5, Args_size=3
	new	class scala/actors/Channel
	dup
	getstatic	Field scala/actors/Actor$.MODULE$:Lscala/actors/Actor$;
	aload_0
	invokevirtual	Method receiver:()Lscala/actors/Actor;
	invokeinterface	InterfaceMethod scala/actors/Actor.scheduler:()Lscala/actors/IScheduler;
	invokevirtual	Method scala/actors/Actor$.self:(Lscala/actors/IScheduler;)Lscala/actors/Actor;
	invokespecial	Method "<init>":(Lscala/actors/Actor;)V
	astore	4
	aload_0
	invokevirtual	Method receiver:()Lscala/actors/Actor;
	new	class scala/actors/$bang
	dup
	aload_0
	aload_3
	invokespecial	Method scala/actors/$bang."<init>":(Lscala/actors/Channel;Ljava/lang/Object;)V
	aload	4
	invokeinterface	InterfaceMethod scala/actors/Reactor.send:(Ljava/lang/Object;Lscala/actors/OutputChannel;)V
	aload	4
	lload_1
	new	class scala/actors/Channel$$anonfun$$bang$qmark$2
	dup
	aload_0
	invokespecial	Method scala/actors/Channel$$anonfun$$bang$qmark$2."<init>":(Lscala/actors/Channel;)V
	invokevirtual	Method receiveWithin:(JLscala/PartialFunction;)Ljava/lang/Object;
	checkcast	class scala/Option
	areturn
  Labels:
  LocalVariableTable: 
   Start  Length  Slot  Name   Signature
   0      62      0    this       Lscala/actors/Channel;
   0      62      1    msec       J
   0      62      3    msg       Ljava/lang/Object;
   24      37      4    replyCh       Lscala/actors/Channel;

  Signature: length = 0x2
   00 FFFFFF90 

public scala.actors.Channel(scala.actors.Actor);
  Signature: (Lscala/actors/Actor;)V
  Code:
   Stack=2, Locals=2, Args_size=2
	aload_0
	aload_1
	putfield	Field receiver:Lscala/actors/Actor;
	aload_0
	invokespecial	Method java/lang/Object."<init>":()V
	aload_0
	invokestatic	Method scala/actors/CanReply$class.$init$:(Lscala/actors/CanReply;)V
	return
  Labels:
  LocalVariableTable: 
   Start  Length  Slot  Name   Signature
   0      14      0    this       Lscala/actors/Channel;
   0      14      1    receiver       Lscala/actors/Actor;

  Signature: length = 0x2
   00 29 

}

