Compiled from "Channel.scala"
public final class scala.actors.Channel$$anonfun$reactWithin$1 extends java.lang.Object implements scala.PartialFunction,java.io.Serializable
  SourceFile: "Channel.scala"
  Scala: length = 0x
   
  InnerClass: 
   public final $anonfun$reactWithin$1=class scala/actors/Channel$$anonfun$reactWithin$1 of class scala/actors/Channel
  minor version: 0
  major version: 49
  Constant pool:
Asciz	SourceFile;
Asciz	Channel.scala;
Asciz	<clinit>;
Asciz	()V;
Asciz	Code;
Asciz	serialVersionUID;
Asciz	J;
Asciz	scala/actors/Channel$$anonfun$reactWithin$1;
class	scala/actors/Channel$$anonfun$reactWithin$1
NameAndType	serialVersionUID:J
Field	scala/actors/Channel$$anonfun$reactWithin$1.serialVersionUID:J
Asciz	C$4;
Asciz	Lscala/actors/Channel;;
Asciz	f$4;
Asciz	Lscala/PartialFunction;;
Asciz	<init>;
Asciz	(Lscala/actors/Channel;Lscala/PartialFunction;Lscala/actors/Channel;)V;
Asciz	LineNumberTable;
NameAndType	f$4:Lscala/PartialFunction;
Field	scala/actors/Channel$$anonfun$reactWithin$1.f$4:Lscala/PartialFunction;
NameAndType	C$4:Lscala/actors/Channel;
Field	scala/actors/Channel$$anonfun$reactWithin$1.C$4:Lscala/actors/Channel;
Asciz	java/lang/Object;
class	java/lang/Object
NameAndType	"<init>":()V
Method	java/lang/Object."<init>":()V
Asciz	scala/Function1$class;
class	scala/Function1$class
Asciz	$init$;
Asciz	(Lscala/Function1;)V;
NameAndType	$init$:(Lscala/Function1;)V
Method	scala/Function1$class.$init$:(Lscala/Function1;)V
Asciz	scala/PartialFunction$class;
class	scala/PartialFunction$class
Asciz	(Lscala/PartialFunction;)V;
NameAndType	$init$:(Lscala/PartialFunction;)V
Method	scala/PartialFunction$class.$init$:(Lscala/PartialFunction;)V
Asciz	this;
Asciz	Lscala/actors/Channel$$anonfun$reactWithin$1;;
Asciz	$outer;
Asciz	LocalVariableTable;
Asciz	(Lscala/actors/Channel<TMsg;>;)V;
Asciz	Signature;
Asciz	gd9$1;
Asciz	(Ljava/lang/Object;)Z;
Asciz	scala/PartialFunction;
class	scala/PartialFunction
Asciz	isDefinedAt;
NameAndType	isDefinedAt:(Ljava/lang/Object;)Z
InterfaceMethod	scala/PartialFunction.isDefinedAt:(Ljava/lang/Object;)Z
Asciz	gd8$1;
Asciz	apply;
Asciz	(Ljava/lang/Object;)Ljava/lang/Object;;
Asciz	(Ljava/lang/Object;)V;
NameAndType	apply:(Ljava/lang/Object;)V
Method	scala/actors/Channel$$anonfun$reactWithin$1.apply:(Ljava/lang/Object;)V
Asciz	scala/runtime/BoxedUnit;
class	scala/runtime/BoxedUnit
Asciz	UNIT;
Asciz	Lscala/runtime/BoxedUnit;;
NameAndType	UNIT:Lscala/runtime/BoxedUnit;
Field	scala/runtime/BoxedUnit.UNIT:Lscala/runtime/BoxedUnit;
Asciz	v1;
Asciz	Ljava/lang/Object;;
Asciz	andThen;
Asciz	(Lscala/Function1;)Lscala/Function1;;
Asciz	(Lscala/Function1;)Lscala/PartialFunction;;
NameAndType	andThen:(Lscala/Function1;)Lscala/PartialFunction;
InterfaceMethod	scala/PartialFunction.andThen:(Lscala/Function1;)Lscala/PartialFunction;
Asciz	g;
Asciz	Lscala/Function1;;
Asciz	scala/actors/$bang;
class	scala/actors/$bang
Asciz	ch;
Asciz	()Lscala/actors/Channel;;
NameAndType	ch:()Lscala/actors/Channel;
Method	scala/actors/$bang.ch:()Lscala/actors/Channel;
Asciz	equals;
NameAndType	equals:(Ljava/lang/Object;)Z
Method	java/lang/Object.equals:(Ljava/lang/Object;)Z
Asciz	msg;
Asciz	()Ljava/lang/Object;;
NameAndType	msg:()Ljava/lang/Object;
Method	scala/actors/$bang.msg:()Ljava/lang/Object;
NameAndType	gd9$1:(Ljava/lang/Object;)Z
Method	scala/actors/Channel$$anonfun$reactWithin$1.gd9$1:(Ljava/lang/Object;)Z
Asciz	scala/MatchError;
class	scala/MatchError
Asciz	toString;
Asciz	()Ljava/lang/String;;
NameAndType	toString:()Ljava/lang/String;
Method	java/lang/Object.toString:()Ljava/lang/String;
Asciz	(Ljava/lang/String;)V;
NameAndType	"<init>":(Ljava/lang/String;)V
Method	scala/MatchError."<init>":(Ljava/lang/String;)V
Asciz	scala/actors/TIMEOUT$;
class	scala/actors/TIMEOUT$
Asciz	MODULE$;
Asciz	Lscala/actors/TIMEOUT$;;
NameAndType	MODULE$:Lscala/actors/TIMEOUT$;
Field	scala/actors/TIMEOUT$.MODULE$:Lscala/actors/TIMEOUT$;
Asciz	temp46;
Asciz	Lscala/actors/$bang;;
NameAndType	gd8$1:(Ljava/lang/Object;)Z
Method	scala/actors/Channel$$anonfun$reactWithin$1.gd8$1:(Ljava/lang/Object;)Z
Asciz	scala/Function1;
class	scala/Function1
NameAndType	apply:(Ljava/lang/Object;)Ljava/lang/Object;
InterfaceMethod	scala/Function1.apply:(Ljava/lang/Object;)Ljava/lang/Object;
Asciz	temp40;
Asciz	temp42;
Asciz	compose;
Asciz	(Lscala/Function1;Lscala/Function1;)Lscala/Function1;;
NameAndType	compose:(Lscala/Function1;Lscala/Function1;)Lscala/Function1;
Method	scala/Function1$class.compose:(Lscala/Function1;Lscala/Function1;)Lscala/Function1;
Asciz	(Lscala/Function1;)Ljava/lang/String;;
NameAndType	toString:(Lscala/Function1;)Ljava/lang/String;
Method	scala/Function1$class.toString:(Lscala/Function1;)Ljava/lang/String;
Asciz	lift;
Asciz	()Lscala/Function1;;
Asciz	(Lscala/PartialFunction;)Lscala/Function1;;
NameAndType	lift:(Lscala/PartialFunction;)Lscala/Function1;
Method	scala/PartialFunction$class.lift:(Lscala/PartialFunction;)Lscala/Function1;
Asciz	(Lscala/PartialFunction;Lscala/Function1;)Lscala/PartialFunction;;
NameAndType	andThen:(Lscala/PartialFunction;Lscala/Function1;)Lscala/PartialFunction;
Method	scala/PartialFunction$class.andThen:(Lscala/PartialFunction;Lscala/Function1;)Lscala/PartialFunction;
Asciz	k;
Asciz	orElse;
Asciz	(Lscala/PartialFunction;)Lscala/PartialFunction;;
Asciz	(Lscala/PartialFunction;Lscala/PartialFunction;)Lscala/PartialFunction;;
NameAndType	orElse:(Lscala/PartialFunction;Lscala/PartialFunction;)Lscala/PartialFunction;
Method	scala/PartialFunction$class.orElse:(Lscala/PartialFunction;Lscala/PartialFunction;)Lscala/PartialFunction;
Asciz	that;
Asciz	Scala;
Asciz	InnerClasses;
Asciz	scala/actors/Channel;
class	scala/actors/Channel
Asciz	$anonfun$reactWithin$1;
Asciz	java/io/Serializable;
class	java/io/Serializable

{
public static final long serialVersionUID;
  Signature: J

public final scala.actors.Channel C$4;
  Signature: Lscala/actors/Channel;

private final scala.PartialFunction f$4;
  Signature: Lscala/PartialFunction;

public static {};
  Signature: ()V
  Code:
   Stack=2, Locals=0, Args_size=0
	lconst_0
	putstatic	Field serialVersionUID:J
	return
  Labels:

public scala.actors.Channel$$anonfun$reactWithin$1(scala.actors.Channel, scala.PartialFunction, scala.actors.Channel);
  Signature: (Lscala/actors/Channel;Lscala/PartialFunction;Lscala/actors/Channel;)V
  Code:
   Stack=2, Locals=4, Args_size=4
	aload_0
	aload_2
	putfield	Field f$4:Lscala/PartialFunction;
	aload_0
	aload_3
	putfield	Field C$4:Lscala/actors/Channel;
	aload_0
	invokespecial	Method java/lang/Object."<init>":()V
	aload_0
	invokestatic	Method scala/Function1$class.$init$:(Lscala/Function1;)V
	aload_0
	invokestatic	Method scala/PartialFunction$class.$init$:(Lscala/PartialFunction;)V
	return
  Labels:
  LocalVariableTable: 
   Start  Length  Slot  Name   Signature
   0      23      0    this       Lscala/actors/Channel$$anonfun$reactWithin$1;
   0      23      1    $outer       Lscala/actors/Channel;

  Signature: length = 0x2
   00 2A 

private final boolean gd9$1(java.lang.Object);
  Signature: (Ljava/lang/Object;)Z
  Code:
   Stack=2, Locals=2, Args_size=2
	aload_0
	getfield	Field f$4:Lscala/PartialFunction;
	aload_1
	invokeinterface	InterfaceMethod scala/PartialFunction.isDefinedAt:(Ljava/lang/Object;)Z
	ireturn
  Labels:

private final boolean gd8$1(java.lang.Object);
  Signature: (Ljava/lang/Object;)Z
  Code:
   Stack=2, Locals=2, Args_size=2
	aload_0
	getfield	Field f$4:Lscala/PartialFunction;
	aload_1
	invokeinterface	InterfaceMethod scala/PartialFunction.isDefinedAt:(Ljava/lang/Object;)Z
	ireturn
  Labels:

public final java.lang.Object apply(java.lang.Object);
  Signature: (Ljava/lang/Object;)Ljava/lang/Object;
  Code:
   Stack=2, Locals=2, Args_size=2
	aload_0
	aload_1
	invokevirtual	Method apply:(Ljava/lang/Object;)V
	getstatic	Field scala/runtime/BoxedUnit.UNIT:Lscala/runtime/BoxedUnit;
	areturn
  Labels:
  LocalVariableTable: 
   Start  Length  Slot  Name   Signature
   0      9      0    this       Lscala/actors/Channel$$anonfun$reactWithin$1;
   0      9      1    v1       Ljava/lang/Object;


public scala.Function1 andThen(scala.Function1);
  Signature: (Lscala/Function1;)Lscala/Function1;
  Code:
   Stack=2, Locals=2, Args_size=2
	aload_0
	aload_1
	invokeinterface	InterfaceMethod scala/PartialFunction.andThen:(Lscala/Function1;)Lscala/PartialFunction;
	areturn
  Labels:
  LocalVariableTable: 
   Start  Length  Slot  Name   Signature
   0      8      0    this       Lscala/actors/Channel$$anonfun$reactWithin$1;
   0      8      1    g       Lscala/Function1;


public final boolean isDefinedAt(java.lang.Object);
  Signature: (Ljava/lang/Object;)Z
  Code:
   Stack=3, Locals=4, Args_size=2
	aload_1
	instanceof	class scala/actors/$bang
	ifeq	l1 // getstatic
	aload_1
	checkcast	class scala/actors/$bang
	astore_3
	aload_0
	getfield	Field C$4:Lscala/actors/Channel;
	aload_3
	invokevirtual	Method scala/actors/$bang.ch:()Lscala/actors/Channel;
	astore_2
	dup
	ifnonnull	l2 // aload_2
	pop
	aload_2
	ifnull	l3 // aload_0
	goto	l4 // iconst_1
l2	aload_2
	invokevirtual	Method java/lang/Object.equals:(Ljava/lang/Object;)Z
	ifeq	l4 // iconst_1
l3	aload_0
	aload_3
	invokevirtual	Method scala/actors/$bang.msg:()Ljava/lang/Object;
	invokespecial	Method gd9$1:(Ljava/lang/Object;)Z
	ifeq	l5 // iconst_1
	iconst_1
	goto	l6 // ireturn
l5	iconst_1
	ifeq	l7 // new
	iconst_0
	goto	l6 // ireturn
l7	new	class scala/MatchError
	dup
	aload_1
	invokevirtual	Method java/lang/Object.toString:()Ljava/lang/String;
	invokespecial	Method scala/MatchError."<init>":(Ljava/lang/String;)V
	athrow
l4	iconst_1
	ifeq	l8 // new
	iconst_0
	goto	l6 // ireturn
l8	new	class scala/MatchError
	dup
	aload_1
	invokevirtual	Method java/lang/Object.toString:()Ljava/lang/String;
	invokespecial	Method scala/MatchError."<init>":(Ljava/lang/String;)V
	athrow
l1	getstatic	Field scala/actors/TIMEOUT$.MODULE$:Lscala/actors/TIMEOUT$;
	dup
	ifnonnull	l9 // aload_1
	pop
	aload_1
	ifnull	l10 // iconst_1
	goto	l11 // iconst_1
l9	aload_1
	invokevirtual	Method java/lang/Object.equals:(Ljava/lang/Object;)Z
	ifeq	l11 // iconst_1
l10	iconst_1
	ifeq	l12 // new
	iconst_1
	goto	l6 // ireturn
l12	new	class scala/MatchError
	dup
	aload_1
	invokevirtual	Method java/lang/Object.toString:()Ljava/lang/String;
	invokespecial	Method scala/MatchError."<init>":(Ljava/lang/String;)V
	athrow
l11	iconst_1
	ifeq	l13 // new
	iconst_0
l6	ireturn
l13	new	class scala/MatchError
	dup
	aload_1
	invokevirtual	Method java/lang/Object.toString:()Ljava/lang/String;
	invokespecial	Method scala/MatchError."<init>":(Ljava/lang/String;)V
	athrow
  Labels:
   	l2 = 33 // aload_2
   	l3 = 40 // aload_0
   	l5 = 55 // iconst_1
   	l7 = 63 // new
   	l4 = 75 // iconst_1
   	l8 = 83 // new
   	l1 = 95 // getstatic
   	l9 = 110 // aload_1
   	l10 = 117 // iconst_1
   	l12 = 125 // new
   	l11 = 137 // iconst_1
   	l6 = 142 // ireturn
   	l13 = 143 // new
  LocalVariableTable: 
   Start  Length  Slot  Name   Signature
   0      155      0    this       Lscala/actors/Channel$$anonfun$reactWithin$1;
   12      83      3    temp46       Lscala/actors/$bang;


public final void apply(java.lang.Object);
  Signature: (Ljava/lang/Object;)V
  Code:
   Stack=3, Locals=5, Args_size=2
	aload_1
	instanceof	class scala/actors/$bang
	ifeq	l1 // getstatic
	aload_1
	checkcast	class scala/actors/$bang
	astore_2
	aload_2
	invokevirtual	Method scala/actors/$bang.msg:()Ljava/lang/Object;
	astore	4
	aload_0
	getfield	Field C$4:Lscala/actors/Channel;
	aload_2
	invokevirtual	Method scala/actors/$bang.ch:()Lscala/actors/Channel;
	astore_3
	dup
	ifnonnull	l2 // aload_3
	pop
	aload_3
	ifnull	l3 // aload_0
	goto	l4 // new
l2	aload_3
	invokevirtual	Method java/lang/Object.equals:(Ljava/lang/Object;)Z
	ifeq	l4 // new
l3	aload_0
	aload	4
	invokespecial	Method gd8$1:(Ljava/lang/Object;)Z
	ifeq	l5 // new
	aload_0
	getfield	Field f$4:Lscala/PartialFunction;
	aload	4
	invokeinterface	InterfaceMethod scala/Function1.apply:(Ljava/lang/Object;)Ljava/lang/Object;
	pop
	goto	l6 // return
l5	new	class scala/MatchError
	dup
	aload_1
	invokevirtual	Method java/lang/Object.toString:()Ljava/lang/String;
	invokespecial	Method scala/MatchError."<init>":(Ljava/lang/String;)V
	athrow
l4	new	class scala/MatchError
	dup
	aload_1
	invokevirtual	Method java/lang/Object.toString:()Ljava/lang/String;
	invokespecial	Method scala/MatchError."<init>":(Ljava/lang/String;)V
	athrow
l1	getstatic	Field scala/actors/TIMEOUT$.MODULE$:Lscala/actors/TIMEOUT$;
	dup
	ifnonnull	l7 // aload_1
	pop
	aload_1
	ifnull	l8 // iconst_1
	goto	l9 // new
l7	aload_1
	invokevirtual	Method java/lang/Object.equals:(Ljava/lang/Object;)Z
	ifeq	l9 // new
l8	iconst_1
	ifeq	l10 // new
	aload_0
	getfield	Field f$4:Lscala/PartialFunction;
	getstatic	Field scala/actors/TIMEOUT$.MODULE$:Lscala/actors/TIMEOUT$;
	invokeinterface	InterfaceMethod scala/Function1.apply:(Ljava/lang/Object;)Ljava/lang/Object;
	pop
l6	return
l10	new	class scala/MatchError
	dup
	aload_1
	invokevirtual	Method java/lang/Object.toString:()Ljava/lang/String;
	invokespecial	Method scala/MatchError."<init>":(Ljava/lang/String;)V
	athrow
l9	new	class scala/MatchError
	dup
	aload_1
	invokevirtual	Method java/lang/Object.toString:()Ljava/lang/String;
	invokespecial	Method scala/MatchError."<init>":(Ljava/lang/String;)V
	athrow
  Labels:
   	l2 = 39 // aload_3
   	l3 = 46 // aload_0
   	l5 = 70 // new
   	l4 = 82 // new
   	l1 = 94 // getstatic
   	l7 = 109 // aload_1
   	l8 = 116 // iconst_1
   	l6 = 133 // return
   	l10 = 134 // new
   	l9 = 146 // new
  LocalVariableTable: 
   Start  Length  Slot  Name   Signature
   0      158      0    this       Lscala/actors/Channel$$anonfun$reactWithin$1;
   12      82      2    temp40       Lscala/actors/$bang;
   18      76      4    temp42       Ljava/lang/Object;


public scala.Function1 compose(scala.Function1);
  Signature: (Lscala/Function1;)Lscala/Function1;
  Code:
   Stack=2, Locals=2, Args_size=2
	aload_0
	aload_1
	invokestatic	Method scala/Function1$class.compose:(Lscala/Function1;Lscala/Function1;)Lscala/Function1;
	areturn
  Labels:
  LocalVariableTable: 
   Start  Length  Slot  Name   Signature
   0      6      0    this       Lscala/actors/Channel$$anonfun$reactWithin$1;
   0      6      1    g       Lscala/Function1;


public java.lang.String toString();
  Signature: ()Ljava/lang/String;
  Code:
   Stack=1, Locals=1, Args_size=1
	aload_0
	invokestatic	Method scala/Function1$class.toString:(Lscala/Function1;)Ljava/lang/String;
	areturn
  Labels:

public scala.Function1 lift();
  Signature: ()Lscala/Function1;
  Code:
   Stack=1, Locals=1, Args_size=1
	aload_0
	invokestatic	Method scala/PartialFunction$class.lift:(Lscala/PartialFunction;)Lscala/Function1;
	areturn
  Labels:

public scala.PartialFunction andThen(scala.Function1);
  Signature: (Lscala/Function1;)Lscala/PartialFunction;
  Code:
   Stack=2, Locals=2, Args_size=2
	aload_0
	aload_1
	invokestatic	Method scala/PartialFunction$class.andThen:(Lscala/PartialFunction;Lscala/Function1;)Lscala/PartialFunction;
	areturn
  Labels:
  LocalVariableTable: 
   Start  Length  Slot  Name   Signature
   0      6      0    this       Lscala/actors/Channel$$anonfun$reactWithin$1;
   0      6      1    k       Lscala/Function1;


public scala.PartialFunction orElse(scala.PartialFunction);
  Signature: (Lscala/PartialFunction;)Lscala/PartialFunction;
  Code:
   Stack=2, Locals=2, Args_size=2
	aload_0
	aload_1
	invokestatic	Method scala/PartialFunction$class.orElse:(Lscala/PartialFunction;Lscala/PartialFunction;)Lscala/PartialFunction;
	areturn
  Labels:
  LocalVariableTable: 
   Start  Length  Slot  Name   Signature
   0      6      0    this       Lscala/actors/Channel$$anonfun$reactWithin$1;
   0      6      1    that       Lscala/PartialFunction;


}

