Compiled from "Combinators.scala"
public final class scala.actors.Combinators$$anonfun$loopWhile$1 extends scala.runtime.AbstractFunction0 implements java.io.Serializable
  SourceFile: "Combinators.scala"
  Scala: length = 0x
   
  InnerClass: 
   public final $anonfun$loopWhile$1=class scala/actors/Combinators$$anonfun$loopWhile$1 of class scala/actors/Combinators
  minor version: 0
  major version: 49
  Constant pool:
Asciz	SourceFile;
Asciz	Combinators.scala;
Asciz	<clinit>;
Asciz	()V;
Asciz	Code;
Asciz	serialVersionUID;
Asciz	J;
Asciz	scala/actors/Combinators$$anonfun$loopWhile$1;
class	scala/actors/Combinators$$anonfun$loopWhile$1
NameAndType	serialVersionUID:J
Field	scala/actors/Combinators$$anonfun$loopWhile$1.serialVersionUID:J
Asciz	$outer;
Asciz	Lscala/actors/Combinators;;
Asciz	cond$1;
Asciz	Lscala/Function0;;
Asciz	body$2;
Asciz	apply;
Asciz	LineNumberTable;
NameAndType	$outer:Lscala/actors/Combinators;
Field	scala/actors/Combinators$$anonfun$loopWhile$1.$outer:Lscala/actors/Combinators;
NameAndType	cond$1:Lscala/Function0;
Field	scala/actors/Combinators$$anonfun$loopWhile$1.cond$1:Lscala/Function0;
NameAndType	body$2:Lscala/Function0;
Field	scala/actors/Combinators$$anonfun$loopWhile$1.body$2:Lscala/Function0;
Asciz	scala/actors/Combinators;
class	scala/actors/Combinators
Asciz	loopWhile;
Asciz	(Lscala/Function0;Lscala/Function0;)V;
NameAndType	loopWhile:(Lscala/Function0;Lscala/Function0;)V
InterfaceMethod	scala/actors/Combinators.loopWhile:(Lscala/Function0;Lscala/Function0;)V
Asciz	()Ljava/lang/Object;;
NameAndType	apply:()V
Method	scala/actors/Combinators$$anonfun$loopWhile$1.apply:()V
Asciz	scala/runtime/BoxedUnit;
class	scala/runtime/BoxedUnit
Asciz	UNIT;
Asciz	Lscala/runtime/BoxedUnit;;
NameAndType	UNIT:Lscala/runtime/BoxedUnit;
Field	scala/runtime/BoxedUnit.UNIT:Lscala/runtime/BoxedUnit;
Asciz	<init>;
Asciz	(Lscala/actors/Combinators;Lscala/Function0;Lscala/Function0;)V;
Asciz	java/lang/NullPointerException;
class	java/lang/NullPointerException
NameAndType	"<init>":()V
Method	java/lang/NullPointerException."<init>":()V
Asciz	scala/runtime/AbstractFunction0;
class	scala/runtime/AbstractFunction0
Method	scala/runtime/AbstractFunction0."<init>":()V
Asciz	this;
Asciz	Lscala/actors/Combinators$$anonfun$loopWhile$1;;
Asciz	LocalVariableTable;
Asciz	Scala;
Asciz	InnerClasses;
Asciz	$anonfun$loopWhile$1;
Asciz	java/io/Serializable;
class	java/io/Serializable

{
public static final long serialVersionUID;
  Signature: J

public final scala.actors.Combinators $outer;
  Signature: Lscala/actors/Combinators;

public final scala.Function0 cond$1;
  Signature: Lscala/Function0;

public final scala.Function0 body$2;
  Signature: Lscala/Function0;

public static {};
  Signature: ()V
  Code:
   Stack=2, Locals=0, Args_size=0
	lconst_0
	putstatic	Field serialVersionUID:J
	return
  Labels:

public final void apply();
  Signature: ()V
  Code:
   Stack=3, Locals=1, Args_size=1
	aload_0
	getfield	Field $outer:Lscala/actors/Combinators;
	aload_0
	getfield	Field cond$1:Lscala/Function0;
	aload_0
	getfield	Field body$2:Lscala/Function0;
	invokeinterface	InterfaceMethod scala/actors/Combinators.loopWhile:(Lscala/Function0;Lscala/Function0;)V
	return
  Labels:

public final java.lang.Object apply();
  Signature: ()Ljava/lang/Object;
  Code:
   Stack=1, Locals=1, Args_size=1
	aload_0
	invokevirtual	Method apply:()V
	getstatic	Field scala/runtime/BoxedUnit.UNIT:Lscala/runtime/BoxedUnit;
	areturn
  Labels:

public scala.actors.Combinators$$anonfun$loopWhile$1(scala.actors.Combinators, scala.Function0, scala.Function0);
  Signature: (Lscala/actors/Combinators;Lscala/Function0;Lscala/Function0;)V
  Code:
   Stack=2, Locals=4, Args_size=4
	aload_1
	ifnonnull	l1 // aload_0
	new	class java/lang/NullPointerException
	dup
	invokespecial	Method java/lang/NullPointerException."<init>":()V
	athrow
l1	aload_0
	aload_1
	putfield	Field $outer:Lscala/actors/Combinators;
	aload_0
	aload_2
	putfield	Field cond$1:Lscala/Function0;
	aload_0
	aload_3
	putfield	Field body$2:Lscala/Function0;
	aload_0
	invokespecial	Method scala/runtime/AbstractFunction0."<init>":()V
	return
  Labels:
   	l1 = 12 // aload_0
  LocalVariableTable: 
   Start  Length  Slot  Name   Signature
   0      32      0    this       Lscala/actors/Combinators$$anonfun$loopWhile$1;
   0      32      1    $outer       Lscala/actors/Combinators;


}

