Compiled from "Debug.scala"
public class scala.actors.Debug extends java.lang.Object implements scala.ScalaObject
  SourceFile: "Debug.scala"
  ScalaSig: length = 0x2A7
   05 00 6F 07 05 01 02 FFFFFF88 02 07 01 05 44 65 62 75
   67 0A 02 03 04 01 06 61 63 74 6F 72 73 0A 01 05
   01 05 73 63 61 6C 61 03 00 10 02 08 09 0D 01 02
   06 08 0A 02 FFFFFF84 FFFFFF80 FFFFFF80 FFFFFF88 02 0B 02 05 44 65 62 75
   67 13 03 09 0C 14 10 02 0D 12 0D 01 0E 0A 02 0F
   10 01 04 6C 61 6E 67 0A 01 11 01 04 6A 61 76 61
   09 02 13 0E 02 06 4F 62 6A 65 63 74 10 02 15 16
   0D 01 04 09 02 17 04 02 0B 53 63 61 6C 61 4F 62
   6A 65 63 74 08 05 19 09 FFFFFF84 00 1A 01 06 3C 69 6E
   69 74 3E 14 01 07 08 07 1C 09 FFFFFFC0 FFFFFF80 FFFFFF84 04 1D 01
   03 6C 65 76 15 01 1E 10 02 15 1F 09 02 20 04 02
   03 49 6E 74 08 07 22 09 FFFFFFC0 FFFFFF80 FFFFFF84 04 23 01 07 6C
   65 76 5F 24 65 71 14 02 24 27 10 02 15 25 09 02
   26 04 02 04 55 6E 69 74 08 07 28 21 FFFFFF81 FFFFFF80 FFFFFFC0 00
   1E 01 03 78 24 31 08 06 2A 09 FFFFFFA0 FFFFFFA0 04 1E 01 04
   6C 65 76 20 08 05 2C 09 FFFFFF84 00 1D 01 05 6C 65 76
   65 6C 08 05 2E 09 FFFFFF84 00 2F 01 09 6C 65 76 65 6C
   5F 24 65 71 14 02 24 30 08 05 1C 2D FFFFFFC0 00 1E 08
   05 32 09 FFFFFF84 00 33 01 04 69 6E 66 6F 14 02 24 34
   08 05 35 31 FFFFFFC0 00 36 01 01 73 10 02 37 3A 0E 02
   15 38 09 02 39 04 01 06 50 72 65 64 65 66 09 02
   3B 3C 02 06 53 74 72 69 6E 67 0A 02 39 04 08 05
   3E 09 FFFFFF84 00 3F 01 07 77 61 72 6E 69 6E 67 14 02
   24 40 08 05 35 3D FFFFFFC0 00 36 08 05 42 09 FFFFFF84 00 43
   01 05 65 72 72 6F 72 14 02 24 44 08 05 35 41 FFFFFFC0
   00 36 08 05 46 09 FFFFFF84 00 47 01 06 64 6F 49 6E 66
   6F 14 02 24 48 08 06 49 45 FFFFFF84 FFFFFFC0 00 4A 01 01 62
   10 03 15 4B 24 09 02 4C 04 02 08 3C 62 79 6E 61
   6D 65 3E 08 05 4E 09 FFFFFF84 00 4F 01 09 64 6F 57 61
   72 6E 69 6E 67 14 02 24 50 08 06 49 4D FFFFFF84 FFFFFFC0 00
   4A 08 05 52 09 FFFFFF84 00 53 01 07 64 6F 45 72 72 6F
   72 14 02 24 54 08 06 49 51 FFFFFF84 FFFFFFC0 00 4A 06 08 0A
   02 FFFFFF84 FFFFFF80 FFFFFF80 FFFFFF80 00 56 13 03 55 0C 14 08 08 58 55
   FFFFFF82 FFFFFF80 FFFFFFA0 FFFFFF80 04 36 01 03 74 61 67 08 05 19 55 FFFFFF84
   00 5A 14 02 5B 5C 10 02 08 55 08 05 58 59 FFFFFFC0 00
   36 08 07 1C 55 FFFFFFC0 FFFFFF80 FFFFFF84 04 1D 08 07 22 55 FFFFFFC0 FFFFFF80
   FFFFFF84 04 5F 14 02 24 60 08 07 28 5E FFFFFF81 FFFFFF80 FFFFFFC0 00 1E
   08 06 2A 55 FFFFFFA0 FFFFFFA0 04 1E 08 05 2C 55 FFFFFF84 00 1D 08
   05 2E 55 FFFFFF84 00 64 14 02 24 65 08 05 1C 63 FFFFFFC0 00
   1E 08 05 32 55 FFFFFF84 00 67 14 02 24 68 08 05 35 66
   FFFFFFC0 00 36 08 05 3E 55 FFFFFF84 00 6A 14 02 24 6B 08 05
   35 69 FFFFFFC0 00 36 08 05 42 55 FFFFFF84 00 6D 14 02 24 6E
   08 05 35 6C FFFFFFC0 00 36 
  minor version: 0
  major version: 49
  Constant pool:
Asciz	SourceFile;
Asciz	Debug.scala;
Asciz	doError;
Asciz	(Lscala/Function0;)V;
Asciz	Code;
Asciz	scala/actors/Debug$;
class	scala/actors/Debug$
Asciz	MODULE$;
Asciz	Lscala/actors/Debug$;;
NameAndType	MODULE$:Lscala/actors/Debug$;
Field	scala/actors/Debug$.MODULE$:Lscala/actors/Debug$;
NameAndType	doError:(Lscala/Function0;)V
Method	scala/actors/Debug$.doError:(Lscala/Function0;)V
Asciz	(Lscala/Function0<Ljava/lang/Object;>;)V;
Asciz	Signature;
Asciz	doWarning;
NameAndType	doWarning:(Lscala/Function0;)V
Method	scala/actors/Debug$.doWarning:(Lscala/Function0;)V
Asciz	doInfo;
NameAndType	doInfo:(Lscala/Function0;)V
Method	scala/actors/Debug$.doInfo:(Lscala/Function0;)V
Asciz	lev;
Asciz	I;
Asciz	tag;
Asciz	Ljava/lang/String;;
Asciz	<init>;
Asciz	(Ljava/lang/String;)V;
Asciz	LineNumberTable;
Asciz	scala/actors/Debug;
class	scala/actors/Debug
NameAndType	tag:Ljava/lang/String;
Field	scala/actors/Debug.tag:Ljava/lang/String;
Asciz	java/lang/Object;
class	java/lang/Object
Asciz	()V;
NameAndType	"<init>":()V
Method	java/lang/Object."<init>":()V
NameAndType	lev:I
Field	scala/actors/Debug.lev:I
Asciz	this;
Asciz	Lscala/actors/Debug;;
Asciz	LocalVariableTable;
Asciz	error;
Asciz	()I;
NameAndType	lev:()I
Method	scala/actors/Debug.lev:()I
Asciz	java/lang/System;
class	java/lang/System
Asciz	err;
Asciz	Ljava/io/PrintStream;;
NameAndType	err:Ljava/io/PrintStream;
Field	java/lang/System.err:Ljava/io/PrintStream;
Asciz	scala/collection/mutable/StringBuilder;
class	scala/collection/mutable/StringBuilder
Method	scala/collection/mutable/StringBuilder."<init>":()V
Asciz	append;
Asciz	(Ljava/lang/Object;)Lscala/collection/mutable/StringBuilder;;
NameAndType	append:(Ljava/lang/Object;)Lscala/collection/mutable/StringBuilder;
Method	scala/collection/mutable/StringBuilder.append:(Ljava/lang/Object;)Lscala/collection/mutable/StringBuilder;
Asciz	 (erro): ;
String	 (erro): 
Asciz	toString;
Asciz	()Ljava/lang/String;;
NameAndType	toString:()Ljava/lang/String;
Method	scala/collection/mutable/StringBuilder.toString:()Ljava/lang/String;
Asciz	java/io/PrintStream;
class	java/io/PrintStream
Asciz	println;
NameAndType	println:(Ljava/lang/String;)V
Method	java/io/PrintStream.println:(Ljava/lang/String;)V
Asciz	s;
Asciz	warning;
Asciz	 (warn): ;
String	 (warn): 
Asciz	info;
Asciz	out;
NameAndType	out:Ljava/io/PrintStream;
Field	java/lang/System.out:Ljava/io/PrintStream;
Asciz	 (info): ;
String	 (info): 
Asciz	level_$eq;
Asciz	(I)V;
Asciz	lev_$eq;
NameAndType	lev_$eq:(I)V
Method	scala/actors/Debug.lev_$eq:(I)V
Asciz	level;
Asciz	ScalaSig;
Asciz	scala/ScalaObject;
class	scala/ScalaObject

{
private int lev;
  Signature: I

private final java.lang.String tag;
  Signature: Ljava/lang/String;

public static final void doError(scala.Function0);
  Signature: (Lscala/Function0;)V
  Code:
   Stack=2, Locals=1, Args_size=1
	getstatic	Field scala/actors/Debug$.MODULE$:Lscala/actors/Debug$;
	aload_0
	invokevirtual	Method scala/actors/Debug$.doError:(Lscala/Function0;)V
	return
  Labels:
  Signature: length = 0x2
   00 0E 

public static final void doWarning(scala.Function0);
  Signature: (Lscala/Function0;)V
  Code:
   Stack=2, Locals=1, Args_size=1
	getstatic	Field scala/actors/Debug$.MODULE$:Lscala/actors/Debug$;
	aload_0
	invokevirtual	Method scala/actors/Debug$.doWarning:(Lscala/Function0;)V
	return
  Labels:
  Signature: length = 0x2
   00 0E 

public static final void doInfo(scala.Function0);
  Signature: (Lscala/Function0;)V
  Code:
   Stack=2, Locals=1, Args_size=1
	getstatic	Field scala/actors/Debug$.MODULE$:Lscala/actors/Debug$;
	aload_0
	invokevirtual	Method scala/actors/Debug$.doInfo:(Lscala/Function0;)V
	return
  Labels:
  Signature: length = 0x2
   00 0E 

public scala.actors.Debug(java.lang.String);
  Signature: (Ljava/lang/String;)V
  Code:
   Stack=2, Locals=2, Args_size=2
	aload_0
	aload_1
	putfield	Field tag:Ljava/lang/String;
	aload_0
	invokespecial	Method java/lang/Object."<init>":()V
	aload_0
	iconst_2
	putfield	Field lev:I
	return
  Labels:
  LocalVariableTable: 
   Start  Length  Slot  Name   Signature
   0      15      0    this       Lscala/actors/Debug;
   0      15      1    tag       Ljava/lang/String;


public void error(java.lang.String);
  Signature: (Ljava/lang/String;)V
  Code:
   Stack=3, Locals=2, Args_size=2
	aload_0
	invokespecial	Method lev:()I
	iconst_0
	if_icmple	l1 // return
	getstatic	Field java/lang/System.err:Ljava/io/PrintStream;
	new	class scala/collection/mutable/StringBuilder
	dup
	invokespecial	Method scala/collection/mutable/StringBuilder."<init>":()V
	aload_0
	getfield	Field tag:Ljava/lang/String;
	invokevirtual	Method scala/collection/mutable/StringBuilder.append:(Ljava/lang/Object;)Lscala/collection/mutable/StringBuilder;
	ldc	String  (erro): 
	invokevirtual	Method scala/collection/mutable/StringBuilder.append:(Ljava/lang/Object;)Lscala/collection/mutable/StringBuilder;
	aload_1
	invokevirtual	Method scala/collection/mutable/StringBuilder.append:(Ljava/lang/Object;)Lscala/collection/mutable/StringBuilder;
	invokevirtual	Method scala/collection/mutable/StringBuilder.toString:()Ljava/lang/String;
	invokevirtual	Method java/io/PrintStream.println:(Ljava/lang/String;)V
l1	return
  Labels:
   	l1 = 40 // return
  LocalVariableTable: 
   Start  Length  Slot  Name   Signature
   0      41      0    this       Lscala/actors/Debug;
   0      41      1    s       Ljava/lang/String;


public void warning(java.lang.String);
  Signature: (Ljava/lang/String;)V
  Code:
   Stack=3, Locals=2, Args_size=2
	aload_0
	invokespecial	Method lev:()I
	iconst_1
	if_icmple	l1 // return
	getstatic	Field java/lang/System.err:Ljava/io/PrintStream;
	new	class scala/collection/mutable/StringBuilder
	dup
	invokespecial	Method scala/collection/mutable/StringBuilder."<init>":()V
	aload_0
	getfield	Field tag:Ljava/lang/String;
	invokevirtual	Method scala/collection/mutable/StringBuilder.append:(Ljava/lang/Object;)Lscala/collection/mutable/StringBuilder;
	ldc	String  (warn): 
	invokevirtual	Method scala/collection/mutable/StringBuilder.append:(Ljava/lang/Object;)Lscala/collection/mutable/StringBuilder;
	aload_1
	invokevirtual	Method scala/collection/mutable/StringBuilder.append:(Ljava/lang/Object;)Lscala/collection/mutable/StringBuilder;
	invokevirtual	Method scala/collection/mutable/StringBuilder.toString:()Ljava/lang/String;
	invokevirtual	Method java/io/PrintStream.println:(Ljava/lang/String;)V
l1	return
  Labels:
   	l1 = 40 // return
  LocalVariableTable: 
   Start  Length  Slot  Name   Signature
   0      41      0    this       Lscala/actors/Debug;
   0      41      1    s       Ljava/lang/String;


public void info(java.lang.String);
  Signature: (Ljava/lang/String;)V
  Code:
   Stack=3, Locals=2, Args_size=2
	aload_0
	invokespecial	Method lev:()I
	iconst_2
	if_icmple	l1 // return
	getstatic	Field java/lang/System.out:Ljava/io/PrintStream;
	new	class scala/collection/mutable/StringBuilder
	dup
	invokespecial	Method scala/collection/mutable/StringBuilder."<init>":()V
	aload_0
	getfield	Field tag:Ljava/lang/String;
	invokevirtual	Method scala/collection/mutable/StringBuilder.append:(Ljava/lang/Object;)Lscala/collection/mutable/StringBuilder;
	ldc	String  (info): 
	invokevirtual	Method scala/collection/mutable/StringBuilder.append:(Ljava/lang/Object;)Lscala/collection/mutable/StringBuilder;
	aload_1
	invokevirtual	Method scala/collection/mutable/StringBuilder.append:(Ljava/lang/Object;)Lscala/collection/mutable/StringBuilder;
	invokevirtual	Method scala/collection/mutable/StringBuilder.toString:()Ljava/lang/String;
	invokevirtual	Method java/io/PrintStream.println:(Ljava/lang/String;)V
l1	return
  Labels:
   	l1 = 40 // return
  LocalVariableTable: 
   Start  Length  Slot  Name   Signature
   0      41      0    this       Lscala/actors/Debug;
   0      41      1    s       Ljava/lang/String;


public void level_$eq(int);
  Signature: (I)V
  Code:
   Stack=2, Locals=2, Args_size=2
	aload_0
	iload_1
	invokespecial	Method lev_$eq:(I)V
	return
  Labels:
  LocalVariableTable: 
   Start  Length  Slot  Name   Signature
   0      6      0    this       Lscala/actors/Debug;
   0      6      1    lev       I


public int level();
  Signature: ()I
  Code:
   Stack=1, Locals=1, Args_size=1
	aload_0
	invokespecial	Method lev:()I
	ireturn
  Labels:

private void lev_$eq(int);
  Signature: (I)V
  Code:
   Stack=2, Locals=2, Args_size=2
	aload_0
	iload_1
	putfield	Field lev:I
	return
  Labels:

private int lev();
  Signature: ()I
  Code:
   Stack=1, Locals=1, Args_size=1
	aload_0
	getfield	Field lev:I
	ireturn
  Labels:

}

