Compiled from "Debug.scala"
public final class scala.actors.Debug$ extends java.lang.Object implements scala.ScalaObject
  SourceFile: "Debug.scala"
  Scala: length = 0x
   
  minor version: 0
  major version: 49
  Constant pool:
Asciz	SourceFile;
Asciz	Debug.scala;
Asciz	MODULE$;
Asciz	Lscala/actors/Debug$;;
Asciz	<clinit>;
Asciz	()V;
Asciz	Code;
Asciz	scala/actors/Debug$;
class	scala/actors/Debug$
Asciz	<init>;
NameAndType	"<init>":()V
Method	scala/actors/Debug$."<init>":()V
Asciz	lev;
Asciz	I;
Asciz	()I;
Asciz	LineNumberTable;
NameAndType	lev:I
Field	scala/actors/Debug$.lev:I
Asciz	lev_$eq;
Asciz	(I)V;
Asciz	level;
NameAndType	lev:()I
Method	scala/actors/Debug$.lev:()I
Asciz	level_$eq;
NameAndType	lev_$eq:(I)V
Method	scala/actors/Debug$.lev_$eq:(I)V
Asciz	this;
Asciz	LocalVariableTable;
Asciz	info;
Asciz	(Ljava/lang/String;)V;
Asciz	java/lang/System;
class	java/lang/System
Asciz	out;
Asciz	Ljava/io/PrintStream;;
NameAndType	out:Ljava/io/PrintStream;
Field	java/lang/System.out:Ljava/io/PrintStream;
Asciz	scala/collection/mutable/StringBuilder;
class	scala/collection/mutable/StringBuilder
Method	scala/collection/mutable/StringBuilder."<init>":()V
Asciz	Info: ;
String	Info: 
Asciz	append;
Asciz	(Ljava/lang/Object;)Lscala/collection/mutable/StringBuilder;;
NameAndType	append:(Ljava/lang/Object;)Lscala/collection/mutable/StringBuilder;
Method	scala/collection/mutable/StringBuilder.append:(Ljava/lang/Object;)Lscala/collection/mutable/StringBuilder;
Asciz	toString;
Asciz	()Ljava/lang/String;;
NameAndType	toString:()Ljava/lang/String;
Method	scala/collection/mutable/StringBuilder.toString:()Ljava/lang/String;
Asciz	java/io/PrintStream;
class	java/io/PrintStream
Asciz	println;
NameAndType	println:(Ljava/lang/String;)V
Method	java/io/PrintStream.println:(Ljava/lang/String;)V
Asciz	s;
Asciz	Ljava/lang/String;;
Asciz	warning;
Asciz	err;
NameAndType	err:Ljava/io/PrintStream;
Field	java/lang/System.err:Ljava/io/PrintStream;
Asciz	Warning: ;
String	Warning: 
Asciz	error;
Asciz	Error: ;
String	Error: 
Asciz	doInfo;
Asciz	(Lscala/Function0;)V;
Asciz	scala/Function0;
class	scala/Function0
Asciz	apply;
Asciz	()Ljava/lang/Object;;
NameAndType	apply:()Ljava/lang/Object;
InterfaceMethod	scala/Function0.apply:()Ljava/lang/Object;
Asciz	b;
Asciz	Lscala/Function0;;
Asciz	(Lscala/Function0<Ljava/lang/Object;>;)V;
Asciz	Signature;
Asciz	doWarning;
Asciz	doError;
Asciz	java/lang/Object;
class	java/lang/Object
Method	java/lang/Object."<init>":()V
NameAndType	MODULE$:Lscala/actors/Debug$;
Field	scala/actors/Debug$.MODULE$:Lscala/actors/Debug$;
Asciz	Scala;
Asciz	scala/ScalaObject;
class	scala/ScalaObject

{
public static final scala.actors.Debug$ MODULE$;
  Signature: Lscala/actors/Debug$;

private int lev;
  Signature: I

public static {};
  Signature: ()V
  Code:
   Stack=1, Locals=0, Args_size=0
	new	class scala/actors/Debug$
	invokespecial	Method "<init>":()V
	return
  Labels:

private int lev();
  Signature: ()I
  Code:
   Stack=1, Locals=1, Args_size=1
	aload_0
	getfield	Field lev:I
	ireturn
  Labels:

private void lev_$eq(int);
  Signature: (I)V
  Code:
   Stack=2, Locals=2, Args_size=2
	aload_0
	iload_1
	putfield	Field lev:I
	return
  Labels:

public int level();
  Signature: ()I
  Code:
   Stack=1, Locals=1, Args_size=1
	aload_0
	invokespecial	Method lev:()I
	ireturn
  Labels:

public void level_$eq(int);
  Signature: (I)V
  Code:
   Stack=2, Locals=2, Args_size=2
	aload_0
	iload_1
	invokespecial	Method lev_$eq:(I)V
	return
  Labels:
  LocalVariableTable: 
   Start  Length  Slot  Name   Signature
   0      6      0    this       Lscala/actors/Debug$;
   0      6      1    lev       I


public void info(java.lang.String);
  Signature: (Ljava/lang/String;)V
  Code:
   Stack=3, Locals=2, Args_size=2
	aload_0
	invokespecial	Method lev:()I
	iconst_2
	if_icmple	l1 // return
	getstatic	Field java/lang/System.out:Ljava/io/PrintStream;
	new	class scala/collection/mutable/StringBuilder
	dup
	invokespecial	Method scala/collection/mutable/StringBuilder."<init>":()V
	ldc	String Info: 
	invokevirtual	Method scala/collection/mutable/StringBuilder.append:(Ljava/lang/Object;)Lscala/collection/mutable/StringBuilder;
	aload_1
	invokevirtual	Method scala/collection/mutable/StringBuilder.append:(Ljava/lang/Object;)Lscala/collection/mutable/StringBuilder;
	invokevirtual	Method scala/collection/mutable/StringBuilder.toString:()Ljava/lang/String;
	invokevirtual	Method java/io/PrintStream.println:(Ljava/lang/String;)V
l1	return
  Labels:
   	l1 = 33 // return
  LocalVariableTable: 
   Start  Length  Slot  Name   Signature
   0      34      0    this       Lscala/actors/Debug$;
   0      34      1    s       Ljava/lang/String;


public void warning(java.lang.String);
  Signature: (Ljava/lang/String;)V
  Code:
   Stack=3, Locals=2, Args_size=2
	aload_0
	invokespecial	Method lev:()I
	iconst_1
	if_icmple	l1 // return
	getstatic	Field java/lang/System.err:Ljava/io/PrintStream;
	new	class scala/collection/mutable/StringBuilder
	dup
	invokespecial	Method scala/collection/mutable/StringBuilder."<init>":()V
	ldc	String Warning: 
	invokevirtual	Method scala/collection/mutable/StringBuilder.append:(Ljava/lang/Object;)Lscala/collection/mutable/StringBuilder;
	aload_1
	invokevirtual	Method scala/collection/mutable/StringBuilder.append:(Ljava/lang/Object;)Lscala/collection/mutable/StringBuilder;
	invokevirtual	Method scala/collection/mutable/StringBuilder.toString:()Ljava/lang/String;
	invokevirtual	Method java/io/PrintStream.println:(Ljava/lang/String;)V
l1	return
  Labels:
   	l1 = 33 // return
  LocalVariableTable: 
   Start  Length  Slot  Name   Signature
   0      34      0    this       Lscala/actors/Debug$;
   0      34      1    s       Ljava/lang/String;


public void error(java.lang.String);
  Signature: (Ljava/lang/String;)V
  Code:
   Stack=3, Locals=2, Args_size=2
	aload_0
	invokespecial	Method lev:()I
	iconst_0
	if_icmple	l1 // return
	getstatic	Field java/lang/System.err:Ljava/io/PrintStream;
	new	class scala/collection/mutable/StringBuilder
	dup
	invokespecial	Method scala/collection/mutable/StringBuilder."<init>":()V
	ldc	String Error: 
	invokevirtual	Method scala/collection/mutable/StringBuilder.append:(Ljava/lang/Object;)Lscala/collection/mutable/StringBuilder;
	aload_1
	invokevirtual	Method scala/collection/mutable/StringBuilder.append:(Ljava/lang/Object;)Lscala/collection/mutable/StringBuilder;
	invokevirtual	Method scala/collection/mutable/StringBuilder.toString:()Ljava/lang/String;
	invokevirtual	Method java/io/PrintStream.println:(Ljava/lang/String;)V
l1	return
  Labels:
   	l1 = 33 // return
  LocalVariableTable: 
   Start  Length  Slot  Name   Signature
   0      34      0    this       Lscala/actors/Debug$;
   0      34      1    s       Ljava/lang/String;


public void doInfo(scala.Function0);
  Signature: (Lscala/Function0;)V
  Code:
   Stack=2, Locals=2, Args_size=2
	aload_0
	invokespecial	Method lev:()I
	iconst_2
	if_icmple	l1 // return
	aload_1
	invokeinterface	InterfaceMethod scala/Function0.apply:()Ljava/lang/Object;
	pop
l1	return
  Labels:
   	l1 = 15 // return
  LocalVariableTable: 
   Start  Length  Slot  Name   Signature
   0      16      0    this       Lscala/actors/Debug$;
   0      16      1    b       Lscala/Function0;

  Signature: length = 0x2
   00 4C 

public void doWarning(scala.Function0);
  Signature: (Lscala/Function0;)V
  Code:
   Stack=2, Locals=2, Args_size=2
	aload_0
	invokespecial	Method lev:()I
	iconst_1
	if_icmple	l1 // return
	aload_1
	invokeinterface	InterfaceMethod scala/Function0.apply:()Ljava/lang/Object;
	pop
l1	return
  Labels:
   	l1 = 15 // return
  LocalVariableTable: 
   Start  Length  Slot  Name   Signature
   0      16      0    this       Lscala/actors/Debug$;
   0      16      1    b       Lscala/Function0;

  Signature: length = 0x2
   00 4C 

public void doError(scala.Function0);
  Signature: (Lscala/Function0;)V
  Code:
   Stack=2, Locals=2, Args_size=2
	aload_0
	invokespecial	Method lev:()I
	iconst_0
	if_icmple	l1 // return
	aload_1
	invokeinterface	InterfaceMethod scala/Function0.apply:()Ljava/lang/Object;
	pop
l1	return
  Labels:
   	l1 = 15 // return
  LocalVariableTable: 
   Start  Length  Slot  Name   Signature
   0      16      0    this       Lscala/actors/Debug$;
   0      16      1    b       Lscala/Function0;

  Signature: length = 0x2
   00 4C 

private scala.actors.Debug$();
  Signature: ()V
  Code:
   Stack=2, Locals=1, Args_size=1
	aload_0
	invokespecial	Method java/lang/Object."<init>":()V
	aload_0
	putstatic	Field MODULE$:Lscala/actors/Debug$;
	aload_0
	iconst_2
	putfield	Field lev:I
	return
  Labels:

}

