Compiled from "Debug.scala"
public class scala.actors.Debug extends java.lang.Object implements scala.ScalaObject
  SourceFile: "Debug.scala"
  ScalaSig: length = 0x23C
   05 00 5F 07 05 01 02 FFFFFF88 02 07 01 05 44 65 62 75
   67 0A 02 03 04 01 06 61 63 74 6F 72 73 0A 01 05
   01 05 73 63 61 6C 61 03 00 10 02 08 09 0D 01 02
   06 08 0A 02 FFFFFF84 FFFFFF80 FFFFFF80 FFFFFF88 02 0B 02 05 44 65 62 75
   67 13 03 09 0C 14 10 02 0D 12 0D 01 0E 0A 02 0F
   10 01 04 6C 61 6E 67 0A 01 11 01 04 6A 61 76 61
   09 02 13 0E 02 06 4F 62 6A 65 63 74 10 02 15 16
   0D 01 04 09 02 17 04 02 0B 53 63 61 6C 61 4F 62
   6A 65 63 74 08 05 19 09 FFFFFF84 00 1A 01 06 3C 69 6E
   69 74 3E 14 01 07 08 07 1C 09 FFFFFFC0 FFFFFF80 FFFFFF84 04 1D 01
   03 6C 65 76 15 01 1E 10 02 15 1F 09 02 20 04 02
   03 49 6E 74 08 07 22 09 FFFFFFC0 FFFFFF80 FFFFFF84 04 23 01 07 6C
   65 76 5F 24 65 71 14 02 24 27 10 02 15 25 09 02
   26 04 02 04 55 6E 69 74 08 07 28 21 FFFFFF81 FFFFFF80 FFFFFFC0 00
   1E 01 03 78 24 31 08 06 2A 09 FFFFFFA0 FFFFFFA0 04 1E 01 04
   6C 65 76 20 08 05 2C 09 FFFFFF84 00 1D 01 05 6C 65 76
   65 6C 08 05 2E 09 FFFFFF84 00 2F 01 09 6C 65 76 65 6C
   5F 24 65 71 14 02 24 30 08 05 1C 2D FFFFFFC0 00 1E 08
   05 32 09 FFFFFF84 00 33 01 04 69 6E 66 6F 14 02 24 34
   08 05 35 31 FFFFFFC0 00 36 01 01 73 10 02 37 3A 0E 02
   15 38 09 02 39 04 01 06 50 72 65 64 65 66 09 02
   3B 3C 02 06 53 74 72 69 6E 67 0A 02 39 04 08 05
   3E 09 FFFFFF84 00 3F 01 07 77 61 72 6E 69 6E 67 14 02
   24 40 08 05 35 3D FFFFFFC0 00 36 08 05 42 09 FFFFFF84 00 43
   01 05 65 72 72 6F 72 14 02 24 44 08 05 35 41 FFFFFFC0
   00 36 06 08 0A 02 FFFFFF84 FFFFFF80 FFFFFF80 FFFFFF80 00 46 13 03 45 0C
   14 08 08 48 45 FFFFFF82 FFFFFF80 FFFFFFA0 FFFFFF80 04 36 01 03 74 61 67
   08 05 19 45 FFFFFF84 00 4A 14 02 4B 4C 10 02 08 45 08
   05 48 49 FFFFFFC0 00 36 08 07 1C 45 FFFFFFC0 FFFFFF80 FFFFFF84 04 1D 08
   07 22 45 FFFFFFC0 FFFFFF80 FFFFFF84 04 4F 14 02 24 50 08 07 28 4E
   FFFFFF81 FFFFFF80 FFFFFFC0 00 1E 08 06 2A 45 FFFFFFA0 FFFFFFA0 04 1E 08 05 2C
   45 FFFFFF84 00 1D 08 05 2E 45 FFFFFF84 00 54 14 02 24 55 08
   05 1C 53 FFFFFFC0 00 1E 08 05 32 45 FFFFFF84 00 57 14 02 24
   58 08 05 35 56 FFFFFFC0 00 36 08 05 3E 45 FFFFFF84 00 5A 14
   02 24 5B 08 05 35 59 FFFFFFC0 00 36 08 05 42 45 FFFFFF84 00
   5D 14 02 24 5E 08 05 35 5C FFFFFFC0 00 36 
  minor version: 0
  major version: 49
  Constant pool:
const #1 = Asciz	SourceFile;
const #2 = Asciz	Debug.scala;
const #3 = Asciz	lev;
const #4 = Asciz	I;
const #5 = Asciz	tag;
const #6 = Asciz	Ljava/lang/String;;
const #7 = Asciz	<init>;
const #8 = Asciz	(Ljava/lang/String;)V;
const #9 = Asciz	Code;
const #10 = Asciz	LineNumberTable;
const #11 = Asciz	scala/actors/Debug;
const #12 = class	#11;	//  scala/actors/Debug
const #13 = NameAndType	#5:#6;//  tag:Ljava/lang/String;
const #14 = Field	#12.#13;	//  scala/actors/Debug.tag:Ljava/lang/String;
const #15 = Asciz	java/lang/Object;
const #16 = class	#15;	//  java/lang/Object
const #17 = Asciz	()V;
const #18 = NameAndType	#7:#17;//  "<init>":()V
const #19 = Method	#16.#18;	//  java/lang/Object."<init>":()V
const #20 = NameAndType	#3:#4;//  lev:I
const #21 = Field	#12.#20;	//  scala/actors/Debug.lev:I
const #22 = Asciz	this;
const #23 = Asciz	Lscala/actors/Debug;;
const #24 = Asciz	LocalVariableTable;
const #25 = Asciz	error;
const #26 = Asciz	()I;
const #27 = NameAndType	#3:#26;//  lev:()I
const #28 = Method	#12.#27;	//  scala/actors/Debug.lev:()I
const #29 = Asciz	java/lang/System;
const #30 = class	#29;	//  java/lang/System
const #31 = Asciz	err;
const #32 = Asciz	Ljava/io/PrintStream;;
const #33 = NameAndType	#31:#32;//  err:Ljava/io/PrintStream;
const #34 = Field	#30.#33;	//  java/lang/System.err:Ljava/io/PrintStream;
const #35 = Asciz	scala/collection/mutable/StringBuilder;
const #36 = class	#35;	//  scala/collection/mutable/StringBuilder
const #37 = Method	#36.#18;	//  scala/collection/mutable/StringBuilder."<init>":()V
const #38 = Asciz	append;
const #39 = Asciz	(Ljava/lang/Object;)Lscala/collection/mutable/StringBuilder;;
const #40 = NameAndType	#38:#39;//  append:(Ljava/lang/Object;)Lscala/collection/mutable/StringBuilder;
const #41 = Method	#36.#40;	//  scala/collection/mutable/StringBuilder.append:(Ljava/lang/Object;)Lscala/collection/mutable/StringBuilder;
const #42 = Asciz	 (erro): ;
const #43 = String	#42;	//   (erro): 
const #44 = Asciz	toString;
const #45 = Asciz	()Ljava/lang/String;;
const #46 = NameAndType	#44:#45;//  toString:()Ljava/lang/String;
const #47 = Method	#36.#46;	//  scala/collection/mutable/StringBuilder.toString:()Ljava/lang/String;
const #48 = Asciz	java/io/PrintStream;
const #49 = class	#48;	//  java/io/PrintStream
const #50 = Asciz	println;
const #51 = NameAndType	#50:#8;//  println:(Ljava/lang/String;)V
const #52 = Method	#49.#51;	//  java/io/PrintStream.println:(Ljava/lang/String;)V
const #53 = Asciz	s;
const #54 = Asciz	warning;
const #55 = Asciz	 (warn): ;
const #56 = String	#55;	//   (warn): 
const #57 = Asciz	info;
const #58 = Asciz	out;
const #59 = NameAndType	#58:#32;//  out:Ljava/io/PrintStream;
const #60 = Field	#30.#59;	//  java/lang/System.out:Ljava/io/PrintStream;
const #61 = Asciz	 (info): ;
const #62 = String	#61;	//   (info): 
const #63 = Asciz	level_$eq;
const #64 = Asciz	(I)V;
const #65 = Asciz	lev_$eq;
const #66 = NameAndType	#65:#64;//  lev_$eq:(I)V
const #67 = Method	#12.#66;	//  scala/actors/Debug.lev_$eq:(I)V
const #68 = Asciz	level;
const #69 = Asciz	ScalaSig;
const #70 = Asciz	scala/ScalaObject;
const #71 = class	#70;	//  scala/ScalaObject

{
public scala.actors.Debug(java.lang.String);
  Code:
   Stack=2, Locals=2, Args_size=2
   0:	aload_0
   1:	aload_1
   2:	putfield	#14; //Field tag:Ljava/lang/String;
   5:	aload_0
   6:	invokespecial	#19; //Method java/lang/Object."<init>":()V
   9:	aload_0
   10:	iconst_2
   11:	putfield	#21; //Field lev:I
   14:	return
  LineNumberTable: 
   line 32: 0
   line 33: 9

  LocalVariableTable: 
   Start  Length  Slot  Name   Signature
   0      15      0    this       Lscala/actors/Debug;
   0      15      1    tag       Ljava/lang/String;


public void error(java.lang.String);
  Code:
   Stack=3, Locals=2, Args_size=2
   0:	aload_0
   1:	invokespecial	#28; //Method lev:()I
   4:	iconst_0
   5:	if_icmple	40
   8:	getstatic	#34; //Field java/lang/System.err:Ljava/io/PrintStream;
   11:	new	#36; //class scala/collection/mutable/StringBuilder
   14:	dup
   15:	invokespecial	#37; //Method scala/collection/mutable/StringBuilder."<init>":()V
   18:	aload_0
   19:	getfield	#14; //Field tag:Ljava/lang/String;
   22:	invokevirtual	#41; //Method scala/collection/mutable/StringBuilder.append:(Ljava/lang/Object;)Lscala/collection/mutable/StringBuilder;
   25:	ldc	#43; //String  (erro): 
   27:	invokevirtual	#41; //Method scala/collection/mutable/StringBuilder.append:(Ljava/lang/Object;)Lscala/collection/mutable/StringBuilder;
   30:	aload_1
   31:	invokevirtual	#41; //Method scala/collection/mutable/StringBuilder.append:(Ljava/lang/Object;)Lscala/collection/mutable/StringBuilder;
   34:	invokevirtual	#47; //Method scala/collection/mutable/StringBuilder.toString:()Ljava/lang/String;
   37:	invokevirtual	#52; //Method java/io/PrintStream.println:(Ljava/lang/String;)V
   40:	return
  LineNumberTable: 
   line 45: 0

  LocalVariableTable: 
   Start  Length  Slot  Name   Signature
   0      41      0    this       Lscala/actors/Debug;
   0      41      1    s       Ljava/lang/String;


public void warning(java.lang.String);
  Code:
   Stack=3, Locals=2, Args_size=2
   0:	aload_0
   1:	invokespecial	#28; //Method lev:()I
   4:	iconst_1
   5:	if_icmple	40
   8:	getstatic	#34; //Field java/lang/System.err:Ljava/io/PrintStream;
   11:	new	#36; //class scala/collection/mutable/StringBuilder
   14:	dup
   15:	invokespecial	#37; //Method scala/collection/mutable/StringBuilder."<init>":()V
   18:	aload_0
   19:	getfield	#14; //Field tag:Ljava/lang/String;
   22:	invokevirtual	#41; //Method scala/collection/mutable/StringBuilder.append:(Ljava/lang/Object;)Lscala/collection/mutable/StringBuilder;
   25:	ldc	#56; //String  (warn): 
   27:	invokevirtual	#41; //Method scala/collection/mutable/StringBuilder.append:(Ljava/lang/Object;)Lscala/collection/mutable/StringBuilder;
   30:	aload_1
   31:	invokevirtual	#41; //Method scala/collection/mutable/StringBuilder.append:(Ljava/lang/Object;)Lscala/collection/mutable/StringBuilder;
   34:	invokevirtual	#47; //Method scala/collection/mutable/StringBuilder.toString:()Ljava/lang/String;
   37:	invokevirtual	#52; //Method java/io/PrintStream.println:(Ljava/lang/String;)V
   40:	return
  LineNumberTable: 
   line 42: 0

  LocalVariableTable: 
   Start  Length  Slot  Name   Signature
   0      41      0    this       Lscala/actors/Debug;
   0      41      1    s       Ljava/lang/String;


public void info(java.lang.String);
  Code:
   Stack=3, Locals=2, Args_size=2
   0:	aload_0
   1:	invokespecial	#28; //Method lev:()I
   4:	iconst_2
   5:	if_icmple	40
   8:	getstatic	#60; //Field java/lang/System.out:Ljava/io/PrintStream;
   11:	new	#36; //class scala/collection/mutable/StringBuilder
   14:	dup
   15:	invokespecial	#37; //Method scala/collection/mutable/StringBuilder."<init>":()V
   18:	aload_0
   19:	getfield	#14; //Field tag:Ljava/lang/String;
   22:	invokevirtual	#41; //Method scala/collection/mutable/StringBuilder.append:(Ljava/lang/Object;)Lscala/collection/mutable/StringBuilder;
   25:	ldc	#62; //String  (info): 
   27:	invokevirtual	#41; //Method scala/collection/mutable/StringBuilder.append:(Ljava/lang/Object;)Lscala/collection/mutable/StringBuilder;
   30:	aload_1
   31:	invokevirtual	#41; //Method scala/collection/mutable/StringBuilder.append:(Ljava/lang/Object;)Lscala/collection/mutable/StringBuilder;
   34:	invokevirtual	#47; //Method scala/collection/mutable/StringBuilder.toString:()Ljava/lang/String;
   37:	invokevirtual	#52; //Method java/io/PrintStream.println:(Ljava/lang/String;)V
   40:	return
  LineNumberTable: 
   line 39: 0

  LocalVariableTable: 
   Start  Length  Slot  Name   Signature
   0      41      0    this       Lscala/actors/Debug;
   0      41      1    s       Ljava/lang/String;


public void level_$eq(int);
  Code:
   Stack=2, Locals=2, Args_size=2
   0:	aload_0
   1:	iload_1
   2:	invokespecial	#67; //Method lev_$eq:(I)V
   5:	return
  LineNumberTable: 
   line 36: 0

  LocalVariableTable: 
   Start  Length  Slot  Name   Signature
   0      6      0    this       Lscala/actors/Debug;
   0      6      1    lev       I


public int level();
  Code:
   Stack=1, Locals=1, Args_size=1
   0:	aload_0
   1:	invokespecial	#28; //Method lev:()I
   4:	ireturn
  LineNumberTable: 
   line 35: 0


}

