Compiled from "Actor.scala"
public final class scala.actors.Exit$ extends java.lang.Object implements scala.Function2,scala.ScalaObject
  SourceFile: "Actor.scala"
  Scala: length = 0x
   
  minor version: 0
  major version: 49
  Constant pool:
Asciz	SourceFile;
Asciz	Actor.scala;
Asciz	Scala;
Asciz	MODULE$;
Asciz	Lscala/actors/Exit$;;
Asciz	<clinit>;
Asciz	()V;
Asciz	Code;
Asciz	scala/actors/Exit$;
class	scala/actors/Exit$
Asciz	<init>;
NameAndType	"<init>":()V
Method	scala/actors/Exit$."<init>":()V
Asciz	toString;
Asciz	()Ljava/lang/String;;
Asciz	LineNumberTable;
Asciz	scala/Function2$class;
class	scala/Function2$class
Asciz	(Lscala/Function2;)Ljava/lang/String;;
NameAndType	toString:(Lscala/Function2;)Ljava/lang/String;
Method	scala/Function2$class.toString:(Lscala/Function2;)Ljava/lang/String;
Asciz	curried;
Asciz	()Lscala/Function1;;
Asciz	(Lscala/Function2;)Lscala/Function1;;
NameAndType	curried:(Lscala/Function2;)Lscala/Function1;
Method	scala/Function2$class.curried:(Lscala/Function2;)Lscala/Function1;
Asciz	curry;
NameAndType	curry:(Lscala/Function2;)Lscala/Function1;
Method	scala/Function2$class.curry:(Lscala/Function2;)Lscala/Function1;
Asciz	Deprecated;
Asciz	tupled;
NameAndType	tupled:(Lscala/Function2;)Lscala/Function1;
Method	scala/Function2$class.tupled:(Lscala/Function2;)Lscala/Function1;
Asciz	unapply;
Asciz	(Lscala/actors/Exit;)Lscala/Option;;
Asciz	java/lang/Object;
class	java/lang/Object
Asciz	equals;
Asciz	(Ljava/lang/Object;)Z;
NameAndType	equals:(Ljava/lang/Object;)Z
Method	java/lang/Object.equals:(Ljava/lang/Object;)Z
Asciz	scala/None$;
class	scala/None$
Asciz	Lscala/None$;;
NameAndType	MODULE$:Lscala/None$;
Field	scala/None$.MODULE$:Lscala/None$;
Asciz	scala/Some;
class	scala/Some
Asciz	scala/Tuple2;
class	scala/Tuple2
Asciz	scala/actors/Exit;
class	scala/actors/Exit
Asciz	from;
Asciz	()Lscala/actors/AbstractActor;;
NameAndType	from:()Lscala/actors/AbstractActor;
Method	scala/actors/Exit.from:()Lscala/actors/AbstractActor;
Asciz	reason;
Asciz	()Ljava/lang/Object;;
NameAndType	reason:()Ljava/lang/Object;
Method	scala/actors/Exit.reason:()Ljava/lang/Object;
Asciz	(Ljava/lang/Object;Ljava/lang/Object;)V;
NameAndType	"<init>":(Ljava/lang/Object;Ljava/lang/Object;)V
Method	scala/Tuple2."<init>":(Ljava/lang/Object;Ljava/lang/Object;)V
Asciz	(Ljava/lang/Object;)V;
NameAndType	"<init>":(Ljava/lang/Object;)V
Method	scala/Some."<init>":(Ljava/lang/Object;)V
Asciz	this;
Asciz	x$0;
Asciz	Lscala/actors/Exit;;
Asciz	LocalVariableTable;
Asciz	apply;
Asciz	(Lscala/actors/AbstractActor;Ljava/lang/Object;)Lscala/actors/Exit;;
Asciz	(Lscala/actors/AbstractActor;Ljava/lang/Object;)V;
NameAndType	"<init>":(Lscala/actors/AbstractActor;Ljava/lang/Object;)V
Method	scala/actors/Exit."<init>":(Lscala/actors/AbstractActor;Ljava/lang/Object;)V
Asciz	Lscala/actors/AbstractActor;;
Asciz	Ljava/lang/Object;;
Asciz	(Ljava/lang/Object;Ljava/lang/Object;)Ljava/lang/Object;;
Asciz	scala/actors/AbstractActor;
class	scala/actors/AbstractActor
NameAndType	apply:(Lscala/actors/AbstractActor;Ljava/lang/Object;)Lscala/actors/Exit;
Method	scala/actors/Exit$.apply:(Lscala/actors/AbstractActor;Ljava/lang/Object;)Lscala/actors/Exit;
Asciz	v1;
Asciz	v2;
Method	java/lang/Object."<init>":()V
NameAndType	MODULE$:Lscala/actors/Exit$;
Field	scala/actors/Exit$.MODULE$:Lscala/actors/Exit$;
Asciz	$init$;
Asciz	(Lscala/Function2;)V;
NameAndType	$init$:(Lscala/Function2;)V
Method	scala/Function2$class.$init$:(Lscala/Function2;)V
Asciz	scala/Function2;
class	scala/Function2
Asciz	scala/ScalaObject;
class	scala/ScalaObject

{
public static final scala.actors.Exit$ MODULE$;
  Signature: Lscala/actors/Exit$;

public static {};
  Signature: ()V
  Code:
   Stack=1, Locals=0, Args_size=0
	new	class scala/actors/Exit$
	invokespecial	Method "<init>":()V
	return
  Labels:

public java.lang.String toString();
  Signature: ()Ljava/lang/String;
  Code:
   Stack=1, Locals=1, Args_size=1
	aload_0
	invokestatic	Method scala/Function2$class.toString:(Lscala/Function2;)Ljava/lang/String;
	areturn
  Labels:

public scala.Function1 curried();
  Signature: ()Lscala/Function1;
  Code:
   Stack=1, Locals=1, Args_size=1
	aload_0
	invokestatic	Method scala/Function2$class.curried:(Lscala/Function2;)Lscala/Function1;
	areturn
  Labels:

public scala.Function1 curry();
  Signature: ()Lscala/Function1;
  Code:
   Stack=1, Locals=1, Args_size=1
	aload_0
	invokestatic	Method scala/Function2$class.curry:(Lscala/Function2;)Lscala/Function1;
	areturn
  Labels:
  Deprecated: true

public scala.Function1 tupled();
  Signature: ()Lscala/Function1;
  Code:
   Stack=1, Locals=1, Args_size=1
	aload_0
	invokestatic	Method scala/Function2$class.tupled:(Lscala/Function2;)Lscala/Function1;
	areturn
  Labels:

public scala.Option unapply(scala.actors.Exit);
  Signature: (Lscala/actors/Exit;)Lscala/Option;
  Code:
   Stack=6, Locals=3, Args_size=2
	aload_1
	dup
	astore_2
	ifnull	l1 // getstatic
	aload_2
	aconst_null
	invokevirtual	Method java/lang/Object.equals:(Ljava/lang/Object;)Z
	ifeq	l2 // new
l1	getstatic	Field scala/None$.MODULE$:Lscala/None$;
	goto	l3 // areturn
l2	new	class scala/Some
	dup
	new	class scala/Tuple2
	dup
	aload_1
	invokevirtual	Method scala/actors/Exit.from:()Lscala/actors/AbstractActor;
	aload_1
	invokevirtual	Method scala/actors/Exit.reason:()Ljava/lang/Object;
	invokespecial	Method scala/Tuple2."<init>":(Ljava/lang/Object;Ljava/lang/Object;)V
	invokespecial	Method scala/Some."<init>":(Ljava/lang/Object;)V
l3	areturn
  Labels:
   	l1 = 14 // getstatic
   	l2 = 20 // new
   	l3 = 42 // areturn
  LocalVariableTable: 
   Start  Length  Slot  Name   Signature
   0      43      0    this       Lscala/actors/Exit$;
   0      43      1    x$0       Lscala/actors/Exit;


public scala.actors.Exit apply(scala.actors.AbstractActor, java.lang.Object);
  Signature: (Lscala/actors/AbstractActor;Ljava/lang/Object;)Lscala/actors/Exit;
  Code:
   Stack=4, Locals=3, Args_size=3
	new	class scala/actors/Exit
	dup
	aload_1
	aload_2
	invokespecial	Method scala/actors/Exit."<init>":(Lscala/actors/AbstractActor;Ljava/lang/Object;)V
	areturn
  Labels:
  LocalVariableTable: 
   Start  Length  Slot  Name   Signature
   0      10      0    this       Lscala/actors/Exit$;
   0      10      1    from       Lscala/actors/AbstractActor;
   0      10      2    reason       Ljava/lang/Object;


public java.lang.Object apply(java.lang.Object, java.lang.Object);
  Signature: (Ljava/lang/Object;Ljava/lang/Object;)Ljava/lang/Object;
  Code:
   Stack=3, Locals=3, Args_size=3
	aload_0
	aload_1
	checkcast	class scala/actors/AbstractActor
	aload_2
	invokevirtual	Method apply:(Lscala/actors/AbstractActor;Ljava/lang/Object;)Lscala/actors/Exit;
	areturn
  Labels:
  LocalVariableTable: 
   Start  Length  Slot  Name   Signature
   0      10      0    this       Lscala/actors/Exit$;
   0      10      1    v1       Ljava/lang/Object;
   0      10      2    v2       Ljava/lang/Object;


private scala.actors.Exit$();
  Signature: ()V
  Code:
   Stack=1, Locals=1, Args_size=1
	aload_0
	invokespecial	Method java/lang/Object."<init>":()V
	aload_0
	putstatic	Field MODULE$:Lscala/actors/Exit$;
	aload_0
	invokestatic	Method scala/Function2$class.$init$:(Lscala/Function2;)V
	return
  Labels:

}

