public final class scala.actors.FJTaskRunner$VolatileTaskRef extends java.lang.Object
  InnerClass: 
   final #17= #3 of #22; //VolatileTaskRef=class scala/actors/FJTaskRunner$VolatileTaskRef of class scala/actors/FJTaskRunner
  minor version: 0
  major version: 49
  Constant pool:
const #1 = Method	#5.#20;	//  java/lang/Object."<init>":()V
const #2 = Field	#3.#21;	//  scala/actors/FJTaskRunner$VolatileTaskRef.ref:Lscala/actors/FJTask;
const #3 = class	#23;	//  scala/actors/FJTaskRunner$VolatileTaskRef
const #4 = Method	#3.#20;	//  scala/actors/FJTaskRunner$VolatileTaskRef."<init>":()V
const #5 = class	#24;	//  java/lang/Object
const #6 = Asciz	ref;
const #7 = Asciz	Lscala/actors/FJTask;;
const #8 = Asciz	<init>;
const #9 = Asciz	()V;
const #10 = Asciz	Code;
const #11 = Asciz	put;
const #12 = Asciz	(Lscala/actors/FJTask;)V;
const #13 = Asciz	get;
const #14 = Asciz	()Lscala/actors/FJTask;;
const #15 = Asciz	take;
const #16 = Asciz	newArray;
const #17 = Asciz	VolatileTaskRef;
const #18 = Asciz	InnerClasses;
const #19 = Asciz	(I)[Lscala/actors/FJTaskRunner$VolatileTaskRef;;
const #20 = NameAndType	#8:#9;//  "<init>":()V
const #21 = NameAndType	#6:#7;//  ref:Lscala/actors/FJTask;
const #22 = class	#25;	//  scala/actors/FJTaskRunner
const #23 = Asciz	scala/actors/FJTaskRunner$VolatileTaskRef;
const #24 = Asciz	java/lang/Object;
const #25 = Asciz	scala/actors/FJTaskRunner;

{
protected volatile scala.actors.FJTask ref;

protected scala.actors.FJTaskRunner$VolatileTaskRef();
  Code:
   Stack=1, Locals=1, Args_size=1
   0:	aload_0
   1:	invokespecial	#1; //Method java/lang/Object."<init>":()V
   4:	return

protected final void put(scala.actors.FJTask);
  Code:
   Stack=2, Locals=2, Args_size=2
   0:	aload_0
   1:	aload_1
   2:	putfield	#2; //Field ref:Lscala/actors/FJTask;
   5:	return

protected final scala.actors.FJTask get();
  Code:
   Stack=1, Locals=1, Args_size=1
   0:	aload_0
   1:	getfield	#2; //Field ref:Lscala/actors/FJTask;
   4:	areturn

protected final scala.actors.FJTask take();
  Code:
   Stack=2, Locals=2, Args_size=1
   0:	aload_0
   1:	getfield	#2; //Field ref:Lscala/actors/FJTask;
   4:	astore_1
   5:	aload_0
   6:	aconst_null
   7:	putfield	#2; //Field ref:Lscala/actors/FJTask;
   10:	aload_1
   11:	areturn

protected static scala.actors.FJTaskRunner$VolatileTaskRef[] newArray(int);
  Code:
   Stack=4, Locals=3, Args_size=1
   0:	iload_0
   1:	anewarray	#3; //class scala/actors/FJTaskRunner$VolatileTaskRef
   4:	astore_1
   5:	iconst_0
   6:	istore_2
   7:	iload_2
   8:	iload_0
   9:	if_icmpge	28
   12:	aload_1
   13:	iload_2
   14:	new	#3; //class scala/actors/FJTaskRunner$VolatileTaskRef
   17:	dup
   18:	invokespecial	#4; //Method "<init>":()V
   21:	aastore
   22:	iinc	2, 1
   25:	goto	7
   28:	aload_1
   29:	areturn

}

