public class scala.actors.FJTask$Par extends scala.actors.FJTask
  InnerClass: 
   public #19= #5 of #3; //Par=class scala/actors/FJTask$Par of class scala/actors/FJTask
  minor version: 0
  major version: 49
  Constant pool:
const #1 = Method	#3.#14;	//  scala/actors/FJTask."<init>":()V
const #2 = Field	#5.#15;	//  scala/actors/FJTask$Par.tasks:[Lscala/actors/FJTask;
const #3 = class	#16;	//  scala/actors/FJTask
const #4 = Method	#3.#17;	//  scala/actors/FJTask.coInvoke:([Lscala/actors/FJTask;)V
const #5 = class	#18;	//  scala/actors/FJTask$Par
const #6 = Asciz	tasks;
const #7 = Asciz	[Lscala/actors/FJTask;;
const #8 = Asciz	<init>;
const #9 = Asciz	([Lscala/actors/FJTask;)V;
const #10 = Asciz	Code;
const #11 = Asciz	(Lscala/actors/FJTask;Lscala/actors/FJTask;)V;
const #12 = Asciz	run;
const #13 = Asciz	()V;
const #14 = NameAndType	#8:#13;//  "<init>":()V
const #15 = NameAndType	#6:#7;//  tasks:[Lscala/actors/FJTask;
const #16 = Asciz	scala/actors/FJTask;
const #17 = NameAndType	#21:#9;//  coInvoke:([Lscala/actors/FJTask;)V
const #18 = Asciz	scala/actors/FJTask$Par;
const #19 = Asciz	Par;
const #20 = Asciz	InnerClasses;
const #21 = Asciz	coInvoke;

{
protected final scala.actors.FJTask[] tasks;

public scala.actors.FJTask$Par(scala.actors.FJTask[]);
  Code:
   Stack=2, Locals=2, Args_size=2
   0:	aload_0
   1:	invokespecial	#1; //Method scala/actors/FJTask."<init>":()V
   4:	aload_0
   5:	aload_1
   6:	putfield	#2; //Field tasks:[Lscala/actors/FJTask;
   9:	return

public scala.actors.FJTask$Par(scala.actors.FJTask, scala.actors.FJTask);
  Code:
   Stack=5, Locals=3, Args_size=3
   0:	aload_0
   1:	invokespecial	#1; //Method scala/actors/FJTask."<init>":()V
   4:	aload_0
   5:	iconst_2
   6:	anewarray	#3; //class scala/actors/FJTask
   9:	dup
   10:	iconst_0
   11:	aload_1
   12:	aastore
   13:	dup
   14:	iconst_1
   15:	aload_2
   16:	aastore
   17:	putfield	#2; //Field tasks:[Lscala/actors/FJTask;
   20:	return

public void run();
  Code:
   Stack=1, Locals=1, Args_size=1
   0:	aload_0
   1:	getfield	#2; //Field tasks:[Lscala/actors/FJTask;
   4:	invokestatic	#4; //Method scala/actors/FJTask.coInvoke:([Lscala/actors/FJTask;)V
   7:	return

}

