Compiled from "Future.scala"
public abstract class scala.actors.Future extends scala.Responder implements scala.Function0,scala.ScalaObject
  SourceFile: "Future.scala"
  Signature: length = 0x2
   00 37 
  ScalaSig: length = 0x1A0
   05 00 42 06 05 01 02 FFFFFF81 00 07 02 06 46 75 74 75
   72 65 0A 02 03 04 01 06 61 63 74 6F 72 73 0A 01
   05 01 05 73 63 61 6C 61 03 00 15 02 08 0F 13 04
   00 09 18 1B 10 03 0A 0B 0D 0D 01 04 09 02 0C 04
   02 09 52 65 73 70 6F 6E 64 65 72 10 02 0E 0F 0C
   00 04 08 10 00 FFFFFF84 FFFFFF80 FFFFFF84 FFFFFFC2 00 11 02 01 54 11 02
   12 15 10 02 0A 13 09 02 14 04 02 07 4E 6F 74 68
   69 6E 67 10 02 0A 16 09 02 17 04 02 03 41 6E 79
   10 03 0A 19 0D 09 02 1A 04 02 09 46 75 6E 63 74
   69 6F 6E 30 10 02 0A 1C 09 02 1D 04 02 0B 53 63
   61 6C 61 4F 62 6A 65 63 74 08 08 1F 00 FFFFFF82 FFFFFFC2 FFFFFF80
   FFFFFF84 00 20 01 0C 69 6E 70 75 74 43 68 61 6E 6E 65
   6C 15 01 21 10 03 22 23 0D 0D 01 02 09 02 24 02
   02 0C 49 6E 70 75 74 43 68 61 6E 6E 65 6C 08 08
   26 00 FFFFFF82 FFFFFF80 FFFFFFA0 FFFFFF80 04 21 01 0D 69 6E 70 75 74 43
   68 61 6E 6E 65 6C 20 08 05 28 00 FFFFFF84 00 29 01 06
   3C 69 6E 69 74 3E 14 02 2A 2B 10 03 22 00 0D 08
   05 1F 27 FFFFFFC0 00 21 08 07 2D 00 FFFFFFC0 FFFFFF80 FFFFFF84 08 2E 01
   05 76 61 6C 75 65 15 01 2F 10 03 0A 30 15 09 02
   31 04 02 06 4F 70 74 69 6F 6E 08 07 33 00 FFFFFFC0 FFFFFF80
   FFFFFF84 08 34 01 09 76 61 6C 75 65 5F 24 65 71 14 02
   35 38 10 02 0A 36 09 02 37 04 02 04 55 6E 69 74
   08 07 39 32 FFFFFF81 FFFFFF80 FFFFFFC0 00 2F 01 03 78 24 31 08 06
   3B 00 FFFFFFA0 FFFFFFA0 04 2F 01 06 76 61 6C 75 65 20 08 05
   3D 00 FFFFFF86 00 3E 01 05 69 73 53 65 74 15 01 3F 10
   02 0A 40 09 02 41 04 02 07 42 6F 6F 6C 65 61 6E
   
  minor version: 0
  major version: 49
  Constant pool:
const #1 = Asciz	SourceFile;
const #2 = Asciz	Future.scala;
const #3 = Asciz	value;
const #4 = Asciz	Lscala/Option;;
const #5 = Asciz	Lscala/Option<Ljava/lang/Object;>;;
const #6 = Asciz	Signature;
const #7 = Asciz	inputChannel;
const #8 = Asciz	Lscala/actors/InputChannel;;
const #9 = Asciz	Lscala/actors/InputChannel<TT;>;;
const #10 = Asciz	<init>;
const #11 = Asciz	(Lscala/actors/InputChannel;)V;
const #12 = Asciz	Code;
const #13 = Asciz	LineNumberTable;
const #14 = Asciz	scala/actors/Future;
const #15 = class	#14;	//  scala/actors/Future
const #16 = NameAndType	#7:#8;//  inputChannel:Lscala/actors/InputChannel;
const #17 = Field	#15.#16;	//  scala/actors/Future.inputChannel:Lscala/actors/InputChannel;
const #18 = Asciz	scala/Responder;
const #19 = class	#18;	//  scala/Responder
const #20 = Asciz	()V;
const #21 = NameAndType	#10:#20;//  "<init>":()V
const #22 = Method	#19.#21;	//  scala/Responder."<init>":()V
const #23 = Asciz	scala/Function0$class;
const #24 = class	#23;	//  scala/Function0$class
const #25 = Asciz	$init$;
const #26 = Asciz	(Lscala/Function0;)V;
const #27 = NameAndType	#25:#26;//  $init$:(Lscala/Function0;)V
const #28 = Method	#24.#27;	//  scala/Function0$class.$init$:(Lscala/Function0;)V
const #29 = Asciz	scala/None$;
const #30 = class	#29;	//  scala/None$
const #31 = Asciz	MODULE$;
const #32 = Asciz	Lscala/None$;;
const #33 = NameAndType	#31:#32;//  MODULE$:Lscala/None$;
const #34 = Field	#30.#33;	//  scala/None$.MODULE$:Lscala/None$;
const #35 = NameAndType	#3:#4;//  value:Lscala/Option;
const #36 = Field	#15.#35;	//  scala/actors/Future.value:Lscala/Option;
const #37 = Asciz	this;
const #38 = Asciz	Lscala/actors/Future;;
const #39 = Asciz	LocalVariableTable;
const #40 = Asciz	(Lscala/actors/InputChannel<TT;>;)V;
const #41 = Asciz	isSet;
const #42 = Asciz	()Z;
const #43 = Asciz	value_$eq;
const #44 = Asciz	(Lscala/Option;)V;
const #45 = Asciz	(Lscala/Option<Ljava/lang/Object;>;)V;
const #46 = Asciz	()Lscala/Option;;
const #47 = Asciz	()Lscala/Option<Ljava/lang/Object;>;;
const #48 = Asciz	()Lscala/actors/InputChannel;;
const #49 = Asciz	()Lscala/actors/InputChannel<TT;>;;
const #50 = Asciz	toString;
const #51 = Asciz	()Ljava/lang/String;;
const #52 = Asciz	(Lscala/Function0;)Ljava/lang/String;;
const #53 = NameAndType	#50:#52;//  toString:(Lscala/Function0;)Ljava/lang/String;
const #54 = Method	#24.#53;	//  scala/Function0$class.toString:(Lscala/Function0;)Ljava/lang/String;
const #55 = Asciz	<T:Ljava/lang/Object;>Lscala/Responder<TT;>;Lscala/Function0<TT;>;Lscala/ScalaObject;;
const #56 = Asciz	ScalaSig;
const #57 = Asciz	scala/Function0;
const #58 = class	#57;	//  scala/Function0
const #59 = Asciz	scala/ScalaObject;
const #60 = class	#59;	//  scala/ScalaObject

{
public scala.actors.Future(scala.actors.InputChannel);
  Code:
   Stack=2, Locals=2, Args_size=2
   0:	aload_0
   1:	aload_1
   2:	putfield	#17; //Field inputChannel:Lscala/actors/InputChannel;
   5:	aload_0
   6:	invokespecial	#22; //Method scala/Responder."<init>":()V
   9:	aload_0
   10:	invokestatic	#28; //Method scala/Function0$class.$init$:(Lscala/Function0;)V
   13:	aload_0
   14:	getstatic	#34; //Field scala/None$.MODULE$:Lscala/None$;
   17:	putfield	#36; //Field value:Lscala/Option;
   20:	return
  LineNumberTable: 
   line 30: 0
   line 31: 13

  LocalVariableTable: 
   Start  Length  Slot  Name   Signature
   0      21      0    this       Lscala/actors/Future;
   0      21      1    inputChannel       Lscala/actors/InputChannel;

  Signature: length = 0x2
   00 28 

public abstract boolean isSet();

public void value_$eq(scala.Option);
  Code:
   Stack=2, Locals=2, Args_size=2
   0:	aload_0
   1:	aload_1
   2:	putfield	#36; //Field value:Lscala/Option;
   5:	return
  LineNumberTable: 
   line 31: 0

  Signature: length = 0x2
   00 2D 

public scala.Option value();
  Code:
   Stack=1, Locals=1, Args_size=1
   0:	aload_0
   1:	getfield	#36; //Field value:Lscala/Option;
   4:	areturn
  LineNumberTable: 
   line 31: 0

  Signature: length = 0x2
   00 2F 

public scala.actors.InputChannel inputChannel();
  Code:
   Stack=1, Locals=1, Args_size=1
   0:	aload_0
   1:	getfield	#17; //Field inputChannel:Lscala/actors/InputChannel;
   4:	areturn
  LineNumberTable: 
   line 30: 0

  Signature: length = 0x2
   00 31 

public java.lang.String toString();
  Code:
   Stack=1, Locals=1, Args_size=1
   0:	aload_0
   1:	invokestatic	#54; //Method scala/Function0$class.toString:(Lscala/Function0;)Ljava/lang/String;
   4:	areturn
  LineNumberTable: 
   line 30: 0


}

