Compiled from "Future.scala"
public final class scala.actors.Futures$$anon$3 extends java.lang.Object implements scala.PartialFunction
  SourceFile: "Future.scala"
  Signature: length = 0x2
   00 FFFFFFED 
  Scala: length = 0x
   
  InnerClass: 
   public final $anon$3=class scala/actors/Futures$$anon$3 of class scala/actors/Futures
   public final $anonfun$6=class scala/actors/Futures$$anon$3$$anonfun$6 of class scala/actors/Futures$$anon$3
   public final $anonfun$5=class scala/actors/Futures$$anon$3$$anonfun$5 of class scala/actors/Futures$$anon$3
   public final $anonfun$isDefinedAt$1=class scala/actors/Futures$$anon$3$$anonfun$isDefinedAt$1 of class scala/actors/Futures$$anon$3
  minor version: 0
  major version: 49
  Constant pool:
Asciz	SourceFile;
Asciz	Future.scala;
Asciz	partFuns$1;
Asciz	Lscala/collection/Seq;;
Asciz	resultsMap$1;
Asciz	Lscala/runtime/ObjectRef;;
Asciz	<init>;
Asciz	(Lscala/runtime/ObjectRef;Lscala/collection/Seq;)V;
Asciz	Code;
Asciz	LineNumberTable;
Asciz	scala/actors/Futures$$anon$3;
class	scala/actors/Futures$$anon$3
NameAndType	resultsMap$1:Lscala/runtime/ObjectRef;
Field	scala/actors/Futures$$anon$3.resultsMap$1:Lscala/runtime/ObjectRef;
NameAndType	partFuns$1:Lscala/collection/Seq;
Field	scala/actors/Futures$$anon$3.partFuns$1:Lscala/collection/Seq;
Asciz	java/lang/Object;
class	java/lang/Object
Asciz	()V;
NameAndType	"<init>":()V
Method	java/lang/Object."<init>":()V
Asciz	scala/Function1$class;
class	scala/Function1$class
Asciz	$init$;
Asciz	(Lscala/Function1;)V;
NameAndType	$init$:(Lscala/Function1;)V
Method	scala/Function1$class.$init$:(Lscala/Function1;)V
Asciz	scala/PartialFunction$class;
class	scala/PartialFunction$class
Asciz	(Lscala/PartialFunction;)V;
NameAndType	$init$:(Lscala/PartialFunction;)V
Method	scala/PartialFunction$class.$init$:(Lscala/PartialFunction;)V
Asciz	apply;
Asciz	(Ljava/lang/Object;)Ljava/lang/Object;;
Asciz	(Ljava/lang/Object;)V;
NameAndType	apply:(Ljava/lang/Object;)V
Method	scala/actors/Futures$$anon$3.apply:(Ljava/lang/Object;)V
Asciz	scala/runtime/BoxedUnit;
class	scala/runtime/BoxedUnit
Asciz	UNIT;
Asciz	Lscala/runtime/BoxedUnit;;
NameAndType	UNIT:Lscala/runtime/BoxedUnit;
Field	scala/runtime/BoxedUnit.UNIT:Lscala/runtime/BoxedUnit;
Asciz	this;
Asciz	Lscala/actors/Futures$$anon$3;;
Asciz	v1;
Asciz	Ljava/lang/Object;;
Asciz	LocalVariableTable;
Asciz	andThen;
Asciz	(Lscala/Function1;)Lscala/Function1;;
Asciz	scala/PartialFunction;
class	scala/PartialFunction
Asciz	(Lscala/Function1;)Lscala/PartialFunction;;
NameAndType	andThen:(Lscala/Function1;)Lscala/PartialFunction;
InterfaceMethod	scala/PartialFunction.andThen:(Lscala/Function1;)Lscala/PartialFunction;
Asciz	g;
Asciz	Lscala/Function1;;
Asciz	scala/actors/TIMEOUT$;
class	scala/actors/TIMEOUT$
Asciz	MODULE$;
Asciz	Lscala/actors/TIMEOUT$;;
NameAndType	MODULE$:Lscala/actors/TIMEOUT$;
Field	scala/actors/TIMEOUT$.MODULE$:Lscala/actors/TIMEOUT$;
Asciz	equals;
Asciz	(Ljava/lang/Object;)Z;
NameAndType	equals:(Ljava/lang/Object;)Z
Method	java/lang/Object.equals:(Ljava/lang/Object;)Z
Asciz	scala/MatchError;
class	scala/MatchError
Asciz	toString;
Asciz	()Ljava/lang/String;;
NameAndType	toString:()Ljava/lang/String;
Method	java/lang/Object.toString:()Ljava/lang/String;
Asciz	(Ljava/lang/String;)V;
NameAndType	"<init>":(Ljava/lang/String;)V
Method	scala/MatchError."<init>":(Ljava/lang/String;)V
Asciz	scala/actors/Futures$$anon$3$$anonfun$5;
class	scala/actors/Futures$$anon$3$$anonfun$5
Asciz	(Lscala/actors/Futures$$anon$3;Ljava/lang/Object;)V;
NameAndType	"<init>":(Lscala/actors/Futures$$anon$3;Ljava/lang/Object;)V
Method	scala/actors/Futures$$anon$3$$anonfun$5."<init>":(Lscala/actors/Futures$$anon$3;Ljava/lang/Object;)V
Asciz	scala/collection/IterableLike;
class	scala/collection/IterableLike
Asciz	find;
Asciz	(Lscala/Function1;)Lscala/Option;;
NameAndType	find:(Lscala/Function1;)Lscala/Option;
InterfaceMethod	scala/collection/IterableLike.find:(Lscala/Function1;)Lscala/Option;
Asciz	scala/Option;
class	scala/Option
Asciz	get;
Asciz	()Ljava/lang/Object;;
NameAndType	get:()Ljava/lang/Object;
Method	scala/Option.get:()Ljava/lang/Object;
Asciz	scala/Function1;
class	scala/Function1
NameAndType	apply:(Ljava/lang/Object;)Ljava/lang/Object;
InterfaceMethod	scala/Function1.apply:(Ljava/lang/Object;)Ljava/lang/Object;
Asciz	scala/Tuple2;
class	scala/Tuple2
Asciz	scala/Predef$Pair$;
class	scala/Predef$Pair$
Asciz	Lscala/Predef$Pair$;;
NameAndType	MODULE$:Lscala/Predef$Pair$;
Field	scala/Predef$Pair$.MODULE$:Lscala/Predef$Pair$;
Asciz	unapply;
Asciz	(Lscala/Tuple2;)Lscala/Option;;
NameAndType	unapply:(Lscala/Tuple2;)Lscala/Option;
Method	scala/Predef$Pair$.unapply:(Lscala/Tuple2;)Lscala/Option;
Asciz	isEmpty;
Asciz	()Z;
NameAndType	isEmpty:()Z
Method	scala/Option.isEmpty:()Z
Method	scala/Tuple2.toString:()Ljava/lang/String;
Asciz	_1;
NameAndType	_1:()Ljava/lang/Object;
Method	scala/Tuple2._1:()Ljava/lang/Object;
Asciz	scala/runtime/BoxesRunTime;
class	scala/runtime/BoxesRunTime
Asciz	unboxToInt;
Asciz	(Ljava/lang/Object;)I;
NameAndType	unboxToInt:(Ljava/lang/Object;)I
Method	scala/runtime/BoxesRunTime.unboxToInt:(Ljava/lang/Object;)I
Asciz	_2;
NameAndType	_2:()Ljava/lang/Object;
Method	scala/Tuple2._2:()Ljava/lang/Object;
Asciz	boxToInteger;
Asciz	(I)Ljava/lang/Integer;;
NameAndType	boxToInteger:(I)Ljava/lang/Integer;
Method	scala/runtime/BoxesRunTime.boxToInteger:(I)Ljava/lang/Integer;
Asciz	(Ljava/lang/Object;Ljava/lang/Object;)V;
NameAndType	"<init>":(Ljava/lang/Object;Ljava/lang/Object;)V
Method	scala/Tuple2."<init>":(Ljava/lang/Object;Ljava/lang/Object;)V
Asciz	scala/runtime/ObjectRef;
class	scala/runtime/ObjectRef
Asciz	elem;
NameAndType	elem:Ljava/lang/Object;
Field	scala/runtime/ObjectRef.elem:Ljava/lang/Object;
Asciz	scala/collection/mutable/Map;
class	scala/collection/mutable/Map
Asciz	scala/Some;
class	scala/Some
NameAndType	"<init>":(Ljava/lang/Object;)V
Method	scala/Some."<init>":(Ljava/lang/Object;)V
Asciz	scala/collection/mutable/MapLike;
class	scala/collection/mutable/MapLike
Asciz	update;
NameAndType	update:(Ljava/lang/Object;Ljava/lang/Object;)V
InterfaceMethod	scala/collection/mutable/MapLike.update:(Ljava/lang/Object;Ljava/lang/Object;)V
Asciz	scala/actors/Futures$$anon$3$$anonfun$6;
class	scala/actors/Futures$$anon$3$$anonfun$6
Asciz	(Lscala/actors/Futures$$anon$3;Lscala/PartialFunction;)V;
NameAndType	"<init>":(Lscala/actors/Futures$$anon$3;Lscala/PartialFunction;)V
Method	scala/actors/Futures$$anon$3$$anonfun$6."<init>":(Lscala/actors/Futures$$anon$3;Lscala/PartialFunction;)V
Asciz	scala/collection/TraversableLike;
class	scala/collection/TraversableLike
Asciz	filter;
Asciz	(Lscala/Function1;)Ljava/lang/Object;;
NameAndType	filter:(Lscala/Function1;)Ljava/lang/Object;
InterfaceMethod	scala/collection/TraversableLike.filter:(Lscala/Function1;)Ljava/lang/Object;
Asciz	scala/collection/Seq;
class	scala/collection/Seq
Asciz	scala/collection/SeqLike;
class	scala/collection/SeqLike
Asciz	length;
Asciz	()I;
NameAndType	length:()I
InterfaceMethod	scala/collection/SeqLike.length:()I
NameAndType	"<init>":(Lscala/runtime/ObjectRef;Lscala/collection/Seq;)V
Method	scala/actors/Futures$$anon$3."<init>":(Lscala/runtime/ObjectRef;Lscala/collection/Seq;)V
Asciz	scala/actors/Actor$;
class	scala/actors/Actor$
Asciz	Lscala/actors/Actor$;;
NameAndType	MODULE$:Lscala/actors/Actor$;
Field	scala/actors/Actor$.MODULE$:Lscala/actors/Actor$;
Asciz	scala/actors/Scheduler$;
class	scala/actors/Scheduler$
Asciz	Lscala/actors/Scheduler$;;
NameAndType	MODULE$:Lscala/actors/Scheduler$;
Field	scala/actors/Scheduler$.MODULE$:Lscala/actors/Scheduler$;
Asciz	rawSelf;
Asciz	(Lscala/actors/IScheduler;)Lscala/actors/Reactor;;
NameAndType	rawSelf:(Lscala/actors/IScheduler;)Lscala/actors/Reactor;
Method	scala/actors/Actor$.rawSelf:(Lscala/actors/IScheduler;)Lscala/actors/Reactor;
Asciz	scala/actors/Actor;
class	scala/actors/Actor
Asciz	receive;
Asciz	(Lscala/PartialFunction;)Ljava/lang/Object;;
NameAndType	receive:(Lscala/PartialFunction;)Ljava/lang/Object;
InterfaceMethod	scala/actors/Actor.receive:(Lscala/PartialFunction;)Ljava/lang/Object;
Asciz	msg$2;
Asciz	pfOpt;
Asciz	Lscala/Option;;
Asciz	temp36;
Asciz	temp37;
Asciz	Lscala/Tuple2;;
Asciz	temp38;
Asciz	I;
Asciz	temp39;
Asciz	idx;
Asciz	subres;
Asciz	pf$1;
Asciz	Lscala/PartialFunction;;
Asciz	partFunsRest;
Asciz	reaction0;
Asciz	temp35;
Asciz	isDefinedAt;
Asciz	scala/actors/Futures$$anon$3$$anonfun$isDefinedAt$1;
class	scala/actors/Futures$$anon$3$$anonfun$isDefinedAt$1
Method	scala/actors/Futures$$anon$3$$anonfun$isDefinedAt$1."<init>":(Lscala/actors/Futures$$anon$3;Ljava/lang/Object;)V
Asciz	exists;
Asciz	(Lscala/Function1;)Z;
NameAndType	exists:(Lscala/Function1;)Z
InterfaceMethod	scala/collection/IterableLike.exists:(Lscala/Function1;)Z
Asciz	msg$1;
Asciz	compose;
Asciz	(Lscala/Function1;Lscala/Function1;)Lscala/Function1;;
NameAndType	compose:(Lscala/Function1;Lscala/Function1;)Lscala/Function1;
Method	scala/Function1$class.compose:(Lscala/Function1;Lscala/Function1;)Lscala/Function1;
Asciz	(Lscala/Function1;)Ljava/lang/String;;
NameAndType	toString:(Lscala/Function1;)Ljava/lang/String;
Method	scala/Function1$class.toString:(Lscala/Function1;)Ljava/lang/String;
Asciz	lift;
Asciz	()Lscala/Function1;;
Asciz	(Lscala/PartialFunction;)Lscala/Function1;;
NameAndType	lift:(Lscala/PartialFunction;)Lscala/Function1;
Method	scala/PartialFunction$class.lift:(Lscala/PartialFunction;)Lscala/Function1;
Asciz	(Lscala/PartialFunction;Lscala/Function1;)Lscala/PartialFunction;;
NameAndType	andThen:(Lscala/PartialFunction;Lscala/Function1;)Lscala/PartialFunction;
Method	scala/PartialFunction$class.andThen:(Lscala/PartialFunction;Lscala/Function1;)Lscala/PartialFunction;
Asciz	k;
Asciz	orElse;
Asciz	(Lscala/PartialFunction;)Lscala/PartialFunction;;
Asciz	(Lscala/PartialFunction;Lscala/PartialFunction;)Lscala/PartialFunction;;
NameAndType	orElse:(Lscala/PartialFunction;Lscala/PartialFunction;)Lscala/PartialFunction;
Method	scala/PartialFunction$class.orElse:(Lscala/PartialFunction;Lscala/PartialFunction;)Lscala/PartialFunction;
Asciz	that;
Asciz	Ljava/lang/Object;Lscala/PartialFunction<Ljava/lang/Object;Ljava/lang/Object;>;;
Asciz	Signature;
Asciz	Scala;
Asciz	InnerClasses;
Asciz	scala/actors/Futures;
class	scala/actors/Futures
Asciz	$anon$3;
Asciz	$anonfun$6;
Asciz	$anonfun$5;
Asciz	$anonfun$isDefinedAt$1;

{
private final scala.collection.Seq partFuns$1;
  Signature: Lscala/collection/Seq;

private final scala.runtime.ObjectRef resultsMap$1;
  Signature: Lscala/runtime/ObjectRef;

public scala.actors.Futures$$anon$3(scala.runtime.ObjectRef, scala.collection.Seq);
  Signature: (Lscala/runtime/ObjectRef;Lscala/collection/Seq;)V
  Code:
   Stack=2, Locals=3, Args_size=3
	aload_0
	aload_1
	putfield	Field resultsMap$1:Lscala/runtime/ObjectRef;
	aload_0
	aload_2
	putfield	Field partFuns$1:Lscala/collection/Seq;
	aload_0
	invokespecial	Method java/lang/Object."<init>":()V
	aload_0
	invokestatic	Method scala/Function1$class.$init$:(Lscala/Function1;)V
	aload_0
	invokestatic	Method scala/PartialFunction$class.$init$:(Lscala/PartialFunction;)V
	return
  Labels:

public java.lang.Object apply(java.lang.Object);
  Signature: (Ljava/lang/Object;)Ljava/lang/Object;
  Code:
   Stack=2, Locals=2, Args_size=2
	aload_0
	aload_1
	invokevirtual	Method apply:(Ljava/lang/Object;)V
	getstatic	Field scala/runtime/BoxedUnit.UNIT:Lscala/runtime/BoxedUnit;
	areturn
  Labels:
  LocalVariableTable: 
   Start  Length  Slot  Name   Signature
   0      9      0    this       Lscala/actors/Futures$$anon$3;
   0      9      1    v1       Ljava/lang/Object;


public scala.Function1 andThen(scala.Function1);
  Signature: (Lscala/Function1;)Lscala/Function1;
  Code:
   Stack=2, Locals=2, Args_size=2
	aload_0
	aload_1
	invokeinterface	InterfaceMethod scala/PartialFunction.andThen:(Lscala/Function1;)Lscala/PartialFunction;
	areturn
  Labels:
  LocalVariableTable: 
   Start  Length  Slot  Name   Signature
   0      8      0    this       Lscala/actors/Futures$$anon$3;
   0      8      1    g       Lscala/Function1;


public void apply(java.lang.Object);
  Signature: (Ljava/lang/Object;)V
  Code:
   Stack=5, Locals=17, Args_size=2
	getstatic	Field scala/actors/TIMEOUT$.MODULE$:Lscala/actors/TIMEOUT$;
	dup
	ifnonnull	l1 // aload_1
	pop
	aload_1
	ifnull	l2 // iconst_1
	goto	l3 // iconst_1
l1	aload_1
	invokevirtual	Method java/lang/Object.equals:(Ljava/lang/Object;)Z
	ifeq	l3 // iconst_1
l2	iconst_1
	ifne	l4 // return
	new	class scala/MatchError
	dup
	aload_1
	invokevirtual	Method java/lang/Object.toString:()Ljava/lang/String;
	invokespecial	Method scala/MatchError."<init>":(Ljava/lang/String;)V
	athrow
l3	iconst_1
	ifeq	l5 // new
	aload_0
	getfield	Field partFuns$1:Lscala/collection/Seq;
	new	class scala/actors/Futures$$anon$3$$anonfun$5
	dup
	aload_0
	aload_1
	invokespecial	Method scala/actors/Futures$$anon$3$$anonfun$5."<init>":(Lscala/actors/Futures$$anon$3;Ljava/lang/Object;)V
	invokeinterface	InterfaceMethod scala/collection/IterableLike.find:(Lscala/Function1;)Lscala/Option;
	astore_2
	aload_2
	invokevirtual	Method scala/Option.get:()Ljava/lang/Object;
	checkcast	class scala/PartialFunction
	astore	10
	aload	10
	aload_1
	invokeinterface	InterfaceMethod scala/Function1.apply:(Ljava/lang/Object;)Ljava/lang/Object;
	checkcast	class scala/Tuple2
	astore	16
	getstatic	Field scala/Predef$Pair$.MODULE$:Lscala/Predef$Pair$;
	aload	16
	invokevirtual	Method scala/Predef$Pair$.unapply:(Lscala/Tuple2;)Lscala/Option;
	astore_3
	aload_3
	invokevirtual	Method scala/Option.isEmpty:()Z
	ifeq	l6 // aload_3
	new	class scala/MatchError
	dup
	aload	16
	invokevirtual	Method scala/Tuple2.toString:()Ljava/lang/String;
	invokespecial	Method scala/MatchError."<init>":(Ljava/lang/String;)V
	athrow
l6	aload_3
	invokevirtual	Method scala/Option.get:()Ljava/lang/Object;
	checkcast	class scala/Tuple2
	astore	4
	aload	4
	invokevirtual	Method scala/Tuple2._1:()Ljava/lang/Object;
	invokestatic	Method scala/runtime/BoxesRunTime.unboxToInt:(Ljava/lang/Object;)I
	istore	5
	aload	4
	invokevirtual	Method scala/Tuple2._2:()Ljava/lang/Object;
	astore	6
	iconst_1
	ifeq	l7 // new
	new	class scala/Tuple2
	dup
	iload	5
	invokestatic	Method scala/runtime/BoxesRunTime.boxToInteger:(I)Ljava/lang/Integer;
	aload	6
	invokespecial	Method scala/Tuple2."<init>":(Ljava/lang/Object;Ljava/lang/Object;)V
	astore	7
	aload	7
	invokevirtual	Method scala/Tuple2._1:()Ljava/lang/Object;
	invokestatic	Method scala/runtime/BoxesRunTime.unboxToInt:(Ljava/lang/Object;)I
	istore	8
	aload	7
	invokevirtual	Method scala/Tuple2._2:()Ljava/lang/Object;
	astore	9
	aload_0
	getfield	Field resultsMap$1:Lscala/runtime/ObjectRef;
	getfield	Field scala/runtime/ObjectRef.elem:Ljava/lang/Object;
	checkcast	class scala/collection/mutable/Map
	iload	8
	invokestatic	Method scala/runtime/BoxesRunTime.boxToInteger:(I)Ljava/lang/Integer;
	new	class scala/Some
	dup
	aload	9
	invokespecial	Method scala/Some."<init>":(Ljava/lang/Object;)V
	invokeinterface	InterfaceMethod scala/collection/mutable/MapLike.update:(Ljava/lang/Object;Ljava/lang/Object;)V
	aload_0
	getfield	Field partFuns$1:Lscala/collection/Seq;
	new	class scala/actors/Futures$$anon$3$$anonfun$6
	dup
	aload_0
	aload	10
	invokespecial	Method scala/actors/Futures$$anon$3$$anonfun$6."<init>":(Lscala/actors/Futures$$anon$3;Lscala/PartialFunction;)V
	invokeinterface	InterfaceMethod scala/collection/TraversableLike.filter:(Lscala/Function1;)Ljava/lang/Object;
	checkcast	class scala/collection/Seq
	astore	12
	aload	12
	invokeinterface	InterfaceMethod scala/collection/SeqLike.length:()I
	iconst_0
	if_icmple	l4 // return
	aload_0
	getfield	Field resultsMap$1:Lscala/runtime/ObjectRef;
	astore	11
	new	class scala/actors/Futures$$anon$3
	dup
	aload	11
	aload	12
	invokespecial	Method "<init>":(Lscala/runtime/ObjectRef;Lscala/collection/Seq;)V
	astore	15
	getstatic	Field scala/actors/Actor$.MODULE$:Lscala/actors/Actor$;
	astore	13
	getstatic	Field scala/actors/Scheduler$.MODULE$:Lscala/actors/Scheduler$;
	astore	14
	aload	13
	aload	14
	invokevirtual	Method scala/actors/Actor$.rawSelf:(Lscala/actors/IScheduler;)Lscala/actors/Reactor;
	checkcast	class scala/actors/Actor
	aload	15
	invokeinterface	InterfaceMethod scala/actors/Actor.receive:(Lscala/PartialFunction;)Ljava/lang/Object;
	pop
l4	return
l7	new	class scala/MatchError
	dup
	aload	16
	invokevirtual	Method scala/Tuple2.toString:()Ljava/lang/String;
	invokespecial	Method scala/MatchError."<init>":(Ljava/lang/String;)V
	athrow
l5	new	class scala/MatchError
	dup
	aload_1
	invokevirtual	Method java/lang/Object.toString:()Ljava/lang/String;
	invokespecial	Method scala/MatchError."<init>":(Ljava/lang/String;)V
	athrow
  Labels:
   	l1 = 15 // aload_1
   	l2 = 22 // iconst_1
   	l3 = 38 // iconst_1
   	l6 = 112 // aload_3
   	l4 = 286 // return
   	l7 = 287 // new
   	l5 = 300 // new
  LocalVariableTable: 
   Start  Length  Slot  Name   Signature
   0      312      0    this       Lscala/actors/Futures$$anon$3;
   0      312      1    msg$2       Ljava/lang/Object;
   61      225      2    pfOpt       Lscala/Option;
   287      13      2    pfOpt       Lscala/Option;
   92      147      3    temp36       Lscala/Option;
   287      13      3    temp36       Lscala/Option;
   121      118      4    temp37       Lscala/Tuple2;
   287      13      4    temp37       Lscala/Tuple2;
   131      108      5    temp38       I
   287      13      5    temp38       I
   138      101      6    temp39       Ljava/lang/Object;
   287      13      6    temp39       Ljava/lang/Object;
   168      118      8    idx       I
   175      111      9    subres       Ljava/lang/Object;
   70      216      10    pf$1       Lscala/PartialFunction;
   287      13      10    pf$1       Lscala/PartialFunction;
   228      58      12    partFunsRest       Lscala/collection/Seq;
   258      28      15    reaction0       Lscala/PartialFunction;
   83      156      16    temp35       Lscala/Tuple2;
   287      13      16    temp35       Lscala/Tuple2;


public boolean isDefinedAt(java.lang.Object);
  Signature: (Ljava/lang/Object;)Z
  Code:
   Stack=5, Locals=2, Args_size=2
	getstatic	Field scala/actors/TIMEOUT$.MODULE$:Lscala/actors/TIMEOUT$;
	dup
	ifnonnull	l1 // aload_1
	pop
	aload_1
	ifnull	l2 // iconst_1
	goto	l3 // iconst_1
l1	aload_1
	invokevirtual	Method java/lang/Object.equals:(Ljava/lang/Object;)Z
	ifeq	l3 // iconst_1
l2	iconst_1
	ifeq	l4 // new
	iconst_1
	goto	l5 // ireturn
l4	new	class scala/MatchError
	dup
	aload_1
	invokevirtual	Method java/lang/Object.toString:()Ljava/lang/String;
	invokespecial	Method scala/MatchError."<init>":(Ljava/lang/String;)V
	athrow
l3	iconst_1
	ifeq	l6 // new
	aload_0
	getfield	Field partFuns$1:Lscala/collection/Seq;
	new	class scala/actors/Futures$$anon$3$$anonfun$isDefinedAt$1
	dup
	aload_0
	aload_1
	invokespecial	Method scala/actors/Futures$$anon$3$$anonfun$isDefinedAt$1."<init>":(Lscala/actors/Futures$$anon$3;Ljava/lang/Object;)V
	invokeinterface	InterfaceMethod scala/collection/IterableLike.exists:(Lscala/Function1;)Z
l5	ireturn
l6	new	class scala/MatchError
	dup
	aload_1
	invokevirtual	Method java/lang/Object.toString:()Ljava/lang/String;
	invokespecial	Method scala/MatchError."<init>":(Ljava/lang/String;)V
	athrow
  Labels:
   	l1 = 15 // aload_1
   	l2 = 22 // iconst_1
   	l4 = 30 // new
   	l3 = 42 // iconst_1
   	l5 = 64 // ireturn
   	l6 = 65 // new
  LocalVariableTable: 
   Start  Length  Slot  Name   Signature
   0      77      0    this       Lscala/actors/Futures$$anon$3;
   0      77      1    msg$1       Ljava/lang/Object;


public scala.Function1 compose(scala.Function1);
  Signature: (Lscala/Function1;)Lscala/Function1;
  Code:
   Stack=2, Locals=2, Args_size=2
	aload_0
	aload_1
	invokestatic	Method scala/Function1$class.compose:(Lscala/Function1;Lscala/Function1;)Lscala/Function1;
	areturn
  Labels:
  LocalVariableTable: 
   Start  Length  Slot  Name   Signature
   0      6      0    this       Lscala/actors/Futures$$anon$3;
   0      6      1    g       Lscala/Function1;


public java.lang.String toString();
  Signature: ()Ljava/lang/String;
  Code:
   Stack=1, Locals=1, Args_size=1
	aload_0
	invokestatic	Method scala/Function1$class.toString:(Lscala/Function1;)Ljava/lang/String;
	areturn
  Labels:

public scala.Function1 lift();
  Signature: ()Lscala/Function1;
  Code:
   Stack=1, Locals=1, Args_size=1
	aload_0
	invokestatic	Method scala/PartialFunction$class.lift:(Lscala/PartialFunction;)Lscala/Function1;
	areturn
  Labels:

public scala.PartialFunction andThen(scala.Function1);
  Signature: (Lscala/Function1;)Lscala/PartialFunction;
  Code:
   Stack=2, Locals=2, Args_size=2
	aload_0
	aload_1
	invokestatic	Method scala/PartialFunction$class.andThen:(Lscala/PartialFunction;Lscala/Function1;)Lscala/PartialFunction;
	areturn
  Labels:
  LocalVariableTable: 
   Start  Length  Slot  Name   Signature
   0      6      0    this       Lscala/actors/Futures$$anon$3;
   0      6      1    k       Lscala/Function1;


public scala.PartialFunction orElse(scala.PartialFunction);
  Signature: (Lscala/PartialFunction;)Lscala/PartialFunction;
  Code:
   Stack=2, Locals=2, Args_size=2
	aload_0
	aload_1
	invokestatic	Method scala/PartialFunction$class.orElse:(Lscala/PartialFunction;Lscala/PartialFunction;)Lscala/PartialFunction;
	areturn
  Labels:
  LocalVariableTable: 
   Start  Length  Slot  Name   Signature
   0      6      0    this       Lscala/actors/Futures$$anon$3;
   0      6      1    that       Lscala/PartialFunction;


}

