Compiled from "Future.scala"
public final class scala.actors.Futures$FutureActor$$anonfun$act$2 extends scala.runtime.AbstractFunction0 implements java.io.Serializable
  SourceFile: "Future.scala"
  Scala: length = 0x
   
  InnerClass: 
   public final $anon$7=class scala/actors/Actor$$anon$7 of class scala/actors/Actor
   public FutureActor=class scala/actors/Futures$FutureActor of class scala/actors/Futures
   public final $anonfun$loop$1=class scala/actors/Actor$$anonfun$loop$1 of class scala/actors/Actor
   public final $anonfun$act$2=class scala/actors/Futures$FutureActor$$anonfun$act$2 of class scala/actors/Futures$FutureActor
   public final $anonfun$apply$1=class scala/actors/Futures$FutureActor$$anonfun$act$2$$anonfun$apply$1 of class scala/actors/Futures$FutureActor$$anonfun$act$2
  minor version: 0
  major version: 49
  Constant pool:
Asciz	SourceFile;
Asciz	Future.scala;
Asciz	<clinit>;
Asciz	()V;
Asciz	Code;
Asciz	serialVersionUID;
Asciz	J;
Asciz	scala/actors/Futures$FutureActor$$anonfun$act$2;
class	scala/actors/Futures$FutureActor$$anonfun$act$2
NameAndType	serialVersionUID:J
Field	scala/actors/Futures$FutureActor$$anonfun$act$2.serialVersionUID:J
Asciz	res$1;
Asciz	Lscala/concurrent/SyncVar;;
Asciz	$outer;
Asciz	Lscala/actors/Futures$FutureActor;;
Asciz	apply;
Asciz	LineNumberTable;
NameAndType	$outer:Lscala/actors/Futures$FutureActor;
Field	scala/actors/Futures$FutureActor$$anonfun$act$2.$outer:Lscala/actors/Futures$FutureActor;
Asciz	scala/Some;
class	scala/Some
NameAndType	res$1:Lscala/concurrent/SyncVar;
Field	scala/actors/Futures$FutureActor$$anonfun$act$2.res$1:Lscala/concurrent/SyncVar;
Asciz	scala/concurrent/SyncVar;
class	scala/concurrent/SyncVar
Asciz	get;
Asciz	()Ljava/lang/Object;;
NameAndType	get:()Ljava/lang/Object;
Method	scala/concurrent/SyncVar.get:()Ljava/lang/Object;
Asciz	<init>;
Asciz	(Ljava/lang/Object;)V;
NameAndType	"<init>":(Ljava/lang/Object;)V
Method	scala/Some."<init>":(Ljava/lang/Object;)V
Asciz	scala/actors/Futures$FutureActor;
class	scala/actors/Futures$FutureActor
Asciz	fvalue_$eq;
Asciz	(Lscala/Option;)V;
NameAndType	fvalue_$eq:(Lscala/Option;)V
Method	scala/actors/Futures$FutureActor.fvalue_$eq:(Lscala/Option;)V
Asciz	scala$actors$Futures$FutureActor$$super$inputChannel;
Asciz	()Lscala/actors/InputChannel;;
NameAndType	scala$actors$Futures$FutureActor$$super$inputChannel:()Lscala/actors/InputChannel;
Method	scala/actors/Futures$FutureActor.scala$actors$Futures$FutureActor$$super$inputChannel:()Lscala/actors/InputChannel;
Asciz	scala/actors/Channel;
class	scala/actors/Channel
Asciz	$bang;
NameAndType	$bang:(Ljava/lang/Object;)V
Method	scala/actors/Channel.$bang:(Ljava/lang/Object;)V
Asciz	scala/actors/Futures$FutureActor$$anonfun$act$2$$anonfun$apply$1;
class	scala/actors/Futures$FutureActor$$anonfun$act$2$$anonfun$apply$1
Asciz	(Lscala/actors/Futures$FutureActor$$anonfun$act$2;)V;
NameAndType	"<init>":(Lscala/actors/Futures$FutureActor$$anonfun$act$2;)V
Method	scala/actors/Futures$FutureActor$$anonfun$act$2$$anonfun$apply$1."<init>":(Lscala/actors/Futures$FutureActor$$anonfun$act$2;)V
Asciz	scala/actors/Actor$$anon$7;
class	scala/actors/Actor$$anon$7
Asciz	(Lscala/Function0;)V;
NameAndType	"<init>":(Lscala/Function0;)V
Method	scala/actors/Actor$$anon$7."<init>":(Lscala/Function0;)V
Asciz	scala/actors/Actor$$anonfun$loop$1;
class	scala/actors/Actor$$anonfun$loop$1
Method	scala/actors/Actor$$anonfun$loop$1."<init>":(Lscala/Function0;)V
Asciz	scala/actors/Actor$;
class	scala/actors/Actor$
Asciz	MODULE$;
Asciz	Lscala/actors/Actor$;;
NameAndType	MODULE$:Lscala/actors/Actor$;
Field	scala/actors/Actor$.MODULE$:Lscala/actors/Actor$;
Asciz	scala/actors/Scheduler$;
class	scala/actors/Scheduler$
Asciz	Lscala/actors/Scheduler$;;
NameAndType	MODULE$:Lscala/actors/Scheduler$;
Field	scala/actors/Scheduler$.MODULE$:Lscala/actors/Scheduler$;
Asciz	rawSelf;
Asciz	(Lscala/actors/IScheduler;)Lscala/actors/Reactor;;
NameAndType	rawSelf:(Lscala/actors/IScheduler;)Lscala/actors/Reactor;
Method	scala/actors/Actor$.rawSelf:(Lscala/actors/IScheduler;)Lscala/actors/Reactor;
Asciz	scala/actors/Reactor;
class	scala/actors/Reactor
Asciz	seq;
Asciz	(Lscala/Function0;Lscala/Function0;)V;
NameAndType	seq:(Lscala/Function0;Lscala/Function0;)V
InterfaceMethod	scala/actors/Reactor.seq:(Lscala/Function0;Lscala/Function0;)V
Asciz	this;
Asciz	Lscala/actors/Futures$FutureActor$$anonfun$act$2;;
Asciz	LocalVariableTable;
Asciz	scala$actors$Futures$FutureActor$$anonfun$$$outer;
Asciz	()Lscala/actors/Futures$FutureActor;;
NameAndType	apply:()V
Method	scala/actors/Futures$FutureActor$$anonfun$act$2.apply:()V
Asciz	scala/runtime/BoxedUnit;
class	scala/runtime/BoxedUnit
Asciz	UNIT;
Asciz	Lscala/runtime/BoxedUnit;;
NameAndType	UNIT:Lscala/runtime/BoxedUnit;
Field	scala/runtime/BoxedUnit.UNIT:Lscala/runtime/BoxedUnit;
Asciz	(Lscala/actors/Futures$FutureActor;Lscala/concurrent/SyncVar;)V;
Asciz	java/lang/NullPointerException;
class	java/lang/NullPointerException
NameAndType	"<init>":()V
Method	java/lang/NullPointerException."<init>":()V
Asciz	scala/runtime/AbstractFunction0;
class	scala/runtime/AbstractFunction0
Method	scala/runtime/AbstractFunction0."<init>":()V
Asciz	(Lscala/actors/Futures$FutureActor<TT;>;)V;
Asciz	Signature;
Asciz	Scala;
Asciz	InnerClasses;
Asciz	scala/actors/Actor;
class	scala/actors/Actor
Asciz	$anon$7;
Asciz	scala/actors/Futures;
class	scala/actors/Futures
Asciz	FutureActor;
Asciz	$anonfun$loop$1;
Asciz	$anonfun$act$2;
Asciz	$anonfun$apply$1;
Asciz	java/io/Serializable;
class	java/io/Serializable

{
public static final long serialVersionUID;
  Signature: J

public final scala.concurrent.SyncVar res$1;
  Signature: Lscala/concurrent/SyncVar;

public final scala.actors.Futures$FutureActor $outer;
  Signature: Lscala/actors/Futures$FutureActor;

public static {};
  Signature: ()V
  Code:
   Stack=2, Locals=0, Args_size=0
	lconst_0
	putstatic	Field serialVersionUID:J
	return
  Labels:

public final void apply();
  Signature: ()V
  Code:
   Stack=4, Locals=4, Args_size=1
	aload_0
	getfield	Field $outer:Lscala/actors/Futures$FutureActor;
	new	class scala/Some
	dup
	aload_0
	getfield	Field res$1:Lscala/concurrent/SyncVar;
	invokevirtual	Method scala/concurrent/SyncVar.get:()Ljava/lang/Object;
	invokespecial	Method scala/Some."<init>":(Ljava/lang/Object;)V
	invokevirtual	Method scala/actors/Futures$FutureActor.fvalue_$eq:(Lscala/Option;)V
	aload_0
	getfield	Field $outer:Lscala/actors/Futures$FutureActor;
	invokevirtual	Method scala/actors/Futures$FutureActor.scala$actors$Futures$FutureActor$$super$inputChannel:()Lscala/actors/InputChannel;
	checkcast	class scala/actors/Channel
	aload_0
	getfield	Field res$1:Lscala/concurrent/SyncVar;
	invokevirtual	Method scala/concurrent/SyncVar.get:()Ljava/lang/Object;
	invokevirtual	Method scala/actors/Channel.$bang:(Ljava/lang/Object;)V
	new	class scala/actors/Futures$FutureActor$$anonfun$act$2$$anonfun$apply$1
	dup
	aload_0
	invokespecial	Method scala/actors/Futures$FutureActor$$anonfun$act$2$$anonfun$apply$1."<init>":(Lscala/actors/Futures$FutureActor$$anonfun$act$2;)V
	astore_2
	new	class scala/actors/Actor$$anon$7
	dup
	aload_2
	invokespecial	Method scala/actors/Actor$$anon$7."<init>":(Lscala/Function0;)V
	pop
	new	class scala/actors/Actor$$anonfun$loop$1
	dup
	aload_2
	invokespecial	Method scala/actors/Actor$$anonfun$loop$1."<init>":(Lscala/Function0;)V
	astore_3
	getstatic	Field scala/actors/Actor$.MODULE$:Lscala/actors/Actor$;
	astore_1
	aload_1
	getstatic	Field scala/actors/Scheduler$.MODULE$:Lscala/actors/Scheduler$;
	invokevirtual	Method scala/actors/Actor$.rawSelf:(Lscala/actors/IScheduler;)Lscala/actors/Reactor;
	aload_2
	aload_3
	invokeinterface	InterfaceMethod scala/actors/Reactor.seq:(Lscala/Function0;Lscala/Function0;)V
	return
  Labels:
  LocalVariableTable: 
   Start  Length  Slot  Name   Signature
   0      87      0    this       Lscala/actors/Futures$FutureActor$$anonfun$act$2;


public scala.actors.Futures$FutureActor scala$actors$Futures$FutureActor$$anonfun$$$outer();
  Signature: ()Lscala/actors/Futures$FutureActor;
  Code:
   Stack=1, Locals=1, Args_size=1
	aload_0
	getfield	Field $outer:Lscala/actors/Futures$FutureActor;
	areturn
  Labels:

public final java.lang.Object apply();
  Signature: ()Ljava/lang/Object;
  Code:
   Stack=1, Locals=1, Args_size=1
	aload_0
	invokevirtual	Method apply:()V
	getstatic	Field scala/runtime/BoxedUnit.UNIT:Lscala/runtime/BoxedUnit;
	areturn
  Labels:

public scala.actors.Futures$FutureActor$$anonfun$act$2(scala.actors.Futures$FutureActor, scala.concurrent.SyncVar);
  Signature: (Lscala/actors/Futures$FutureActor;Lscala/concurrent/SyncVar;)V
  Code:
   Stack=2, Locals=3, Args_size=3
	aload_1
	ifnonnull	l1 // aload_0
	new	class java/lang/NullPointerException
	dup
	invokespecial	Method java/lang/NullPointerException."<init>":()V
	athrow
l1	aload_0
	aload_1
	putfield	Field $outer:Lscala/actors/Futures$FutureActor;
	aload_0
	aload_2
	putfield	Field res$1:Lscala/concurrent/SyncVar;
	aload_0
	invokespecial	Method scala/runtime/AbstractFunction0."<init>":()V
	return
  Labels:
   	l1 = 12 // aload_0
  LocalVariableTable: 
   Start  Length  Slot  Name   Signature
   0      27      0    this       Lscala/actors/Futures$FutureActor$$anonfun$act$2;
   0      27      1    $outer       Lscala/actors/Futures$FutureActor;

  Signature: length = 0x2
   00 68 

}

