Compiled from "Future.scala"
public final class scala.actors.Futures$$anonfun$3 extends java.lang.Object implements scala.Function1,scala.ScalaObject,java.io.Serializable
  SourceFile: "Future.scala"
  Scala: length = 0x
   
  InnerClass: 
   public final $anonfun$3=class scala/actors/Futures$$anonfun$3 of class scala/actors/Futures
  minor version: 0
  major version: 49
  Constant pool:
Asciz	SourceFile;
Asciz	Future.scala;
Asciz	<clinit>;
Asciz	()V;
Asciz	Code;
Asciz	serialVersionUID;
Asciz	J;
Asciz	scala/actors/Futures$$anonfun$3;
class	scala/actors/Futures$$anonfun$3
NameAndType	serialVersionUID:J
Field	scala/actors/Futures$$anonfun$3.serialVersionUID:J
Asciz	resultsMap$1;
Asciz	Lscala/runtime/ObjectRef;;
Asciz	<init>;
Asciz	(Lscala/runtime/ObjectRef;)V;
Asciz	LineNumberTable;
NameAndType	resultsMap$1:Lscala/runtime/ObjectRef;
Field	scala/actors/Futures$$anonfun$3.resultsMap$1:Lscala/runtime/ObjectRef;
Asciz	java/lang/Object;
class	java/lang/Object
NameAndType	"<init>":()V
Method	java/lang/Object."<init>":()V
Asciz	scala/Function1$class;
class	scala/Function1$class
Asciz	$init$;
Asciz	(Lscala/Function1;)V;
NameAndType	$init$:(Lscala/Function1;)V
Method	scala/Function1$class.$init$:(Lscala/Function1;)V
Asciz	apply;
Asciz	(Ljava/lang/Object;)Ljava/lang/Object;;
Asciz	scala/Tuple2;
class	scala/Tuple2
Asciz	(Lscala/Tuple2;)Z;
NameAndType	apply:(Lscala/Tuple2;)Z
Method	scala/actors/Futures$$anonfun$3.apply:(Lscala/Tuple2;)Z
Asciz	scala/runtime/BoxesRunTime;
class	scala/runtime/BoxesRunTime
Asciz	boxToBoolean;
Asciz	(Z)Ljava/lang/Boolean;;
NameAndType	boxToBoolean:(Z)Ljava/lang/Boolean;
Method	scala/runtime/BoxesRunTime.boxToBoolean:(Z)Ljava/lang/Boolean;
Asciz	this;
Asciz	Lscala/actors/Futures$$anonfun$3;;
Asciz	v1;
Asciz	Ljava/lang/Object;;
Asciz	LocalVariableTable;
Asciz	_2;
Asciz	()Ljava/lang/Object;;
NameAndType	_2:()Ljava/lang/Object;
Method	scala/Tuple2._2:()Ljava/lang/Object;
Asciz	scala/actors/Future;
class	scala/actors/Future
Asciz	isSet;
Asciz	()Z;
NameAndType	isSet:()Z
Method	scala/actors/Future.isSet:()Z
Asciz	scala/runtime/ObjectRef;
class	scala/runtime/ObjectRef
Asciz	elem;
NameAndType	elem:Ljava/lang/Object;
Field	scala/runtime/ObjectRef.elem:Ljava/lang/Object;
Asciz	scala/collection/mutable/Map;
class	scala/collection/mutable/Map
Asciz	_1;
NameAndType	_1:()Ljava/lang/Object;
Method	scala/Tuple2._1:()Ljava/lang/Object;
Asciz	scala/Some;
class	scala/Some
Asciz	scala/Function0;
class	scala/Function0
NameAndType	apply:()Ljava/lang/Object;
InterfaceMethod	scala/Function0.apply:()Ljava/lang/Object;
Asciz	(Ljava/lang/Object;)V;
NameAndType	"<init>":(Ljava/lang/Object;)V
Method	scala/Some."<init>":(Ljava/lang/Object;)V
Asciz	scala/collection/mutable/MapLike;
class	scala/collection/mutable/MapLike
Asciz	update;
Asciz	(Ljava/lang/Object;Ljava/lang/Object;)V;
NameAndType	update:(Ljava/lang/Object;Ljava/lang/Object;)V
InterfaceMethod	scala/collection/mutable/MapLike.update:(Ljava/lang/Object;Ljava/lang/Object;)V
Asciz	scala/None$;
class	scala/None$
Asciz	MODULE$;
Asciz	Lscala/None$;;
NameAndType	MODULE$:Lscala/None$;
Field	scala/None$.MODULE$:Lscala/None$;
Asciz	p;
Asciz	Lscala/Tuple2;;
Asciz	(Lscala/Tuple2<Ljava/lang/Integer;Lscala/actors/Future<Ljava/lang/Object;>;>;)Z;
Asciz	Signature;
Asciz	andThen;
Asciz	(Lscala/Function1;)Lscala/Function1;;
Asciz	(Lscala/Function1;Lscala/Function1;)Lscala/Function1;;
NameAndType	andThen:(Lscala/Function1;Lscala/Function1;)Lscala/Function1;
Method	scala/Function1$class.andThen:(Lscala/Function1;Lscala/Function1;)Lscala/Function1;
Asciz	g;
Asciz	Lscala/Function1;;
Asciz	compose;
NameAndType	compose:(Lscala/Function1;Lscala/Function1;)Lscala/Function1;
Method	scala/Function1$class.compose:(Lscala/Function1;Lscala/Function1;)Lscala/Function1;
Asciz	toString;
Asciz	()Ljava/lang/String;;
Asciz	(Lscala/Function1;)Ljava/lang/String;;
NameAndType	toString:(Lscala/Function1;)Ljava/lang/String;
Method	scala/Function1$class.toString:(Lscala/Function1;)Ljava/lang/String;
Asciz	Scala;
Asciz	InnerClasses;
Asciz	scala/actors/Futures;
class	scala/actors/Futures
Asciz	$anonfun$3;
Asciz	scala/Function1;
class	scala/Function1
Asciz	scala/ScalaObject;
class	scala/ScalaObject
Asciz	java/io/Serializable;
class	java/io/Serializable

{
public static final long serialVersionUID;
  Signature: J

private final scala.runtime.ObjectRef resultsMap$1;
  Signature: Lscala/runtime/ObjectRef;

public static {};
  Signature: ()V
  Code:
   Stack=2, Locals=0, Args_size=0
	lconst_0
	putstatic	Field serialVersionUID:J
	return
  Labels:

public scala.actors.Futures$$anonfun$3(scala.runtime.ObjectRef);
  Signature: (Lscala/runtime/ObjectRef;)V
  Code:
   Stack=2, Locals=2, Args_size=2
	aload_0
	aload_1
	putfield	Field resultsMap$1:Lscala/runtime/ObjectRef;
	aload_0
	invokespecial	Method java/lang/Object."<init>":()V
	aload_0
	invokestatic	Method scala/Function1$class.$init$:(Lscala/Function1;)V
	return
  Labels:

public final java.lang.Object apply(java.lang.Object);
  Signature: (Ljava/lang/Object;)Ljava/lang/Object;
  Code:
   Stack=2, Locals=3, Args_size=2
	aload_0
	aload_1
	checkcast	class scala/Tuple2
	invokevirtual	Method apply:(Lscala/Tuple2;)Z
	istore_2
	iload_2
	invokestatic	Method scala/runtime/BoxesRunTime.boxToBoolean:(Z)Ljava/lang/Boolean;
	areturn
  Labels:
  LocalVariableTable: 
   Start  Length  Slot  Name   Signature
   0      14      0    this       Lscala/actors/Futures$$anonfun$3;
   0      14      1    v1       Ljava/lang/Object;


public final boolean apply(scala.Tuple2);
  Signature: (Lscala/Tuple2;)Z
  Code:
   Stack=5, Locals=2, Args_size=2
	aload_1
	invokevirtual	Method scala/Tuple2._2:()Ljava/lang/Object;
	checkcast	class scala/actors/Future
	invokevirtual	Method scala/actors/Future.isSet:()Z
	ifeq	l1 // aload_0
	aload_0
	getfield	Field resultsMap$1:Lscala/runtime/ObjectRef;
	getfield	Field scala/runtime/ObjectRef.elem:Ljava/lang/Object;
	checkcast	class scala/collection/mutable/Map
	aload_1
	invokevirtual	Method scala/Tuple2._1:()Ljava/lang/Object;
	new	class scala/Some
	dup
	aload_1
	invokevirtual	Method scala/Tuple2._2:()Ljava/lang/Object;
	checkcast	class scala/Function0
	invokeinterface	InterfaceMethod scala/Function0.apply:()Ljava/lang/Object;
	invokespecial	Method scala/Some."<init>":(Ljava/lang/Object;)V
	invokeinterface	InterfaceMethod scala/collection/mutable/MapLike.update:(Ljava/lang/Object;Ljava/lang/Object;)V
	iconst_0
	goto	l2 // ireturn
l1	aload_0
	getfield	Field resultsMap$1:Lscala/runtime/ObjectRef;
	getfield	Field scala/runtime/ObjectRef.elem:Ljava/lang/Object;
	checkcast	class scala/collection/mutable/Map
	aload_1
	invokevirtual	Method scala/Tuple2._1:()Ljava/lang/Object;
	getstatic	Field scala/None$.MODULE$:Lscala/None$;
	invokeinterface	InterfaceMethod scala/collection/mutable/MapLike.update:(Ljava/lang/Object;Ljava/lang/Object;)V
	iconst_1
l2	ireturn
  Labels:
   	l1 = 55 // aload_0
   	l2 = 78 // ireturn
  LocalVariableTable: 
   Start  Length  Slot  Name   Signature
   0      79      0    this       Lscala/actors/Futures$$anonfun$3;
   0      79      1    p       Lscala/Tuple2;

  Signature: length = 0x2
   00 5A 

public scala.Function1 andThen(scala.Function1);
  Signature: (Lscala/Function1;)Lscala/Function1;
  Code:
   Stack=2, Locals=2, Args_size=2
	aload_0
	aload_1
	invokestatic	Method scala/Function1$class.andThen:(Lscala/Function1;Lscala/Function1;)Lscala/Function1;
	areturn
  Labels:
  LocalVariableTable: 
   Start  Length  Slot  Name   Signature
   0      6      0    this       Lscala/actors/Futures$$anonfun$3;
   0      6      1    g       Lscala/Function1;


public scala.Function1 compose(scala.Function1);
  Signature: (Lscala/Function1;)Lscala/Function1;
  Code:
   Stack=2, Locals=2, Args_size=2
	aload_0
	aload_1
	invokestatic	Method scala/Function1$class.compose:(Lscala/Function1;Lscala/Function1;)Lscala/Function1;
	areturn
  Labels:
  LocalVariableTable: 
   Start  Length  Slot  Name   Signature
   0      6      0    this       Lscala/actors/Futures$$anonfun$3;
   0      6      1    g       Lscala/Function1;


public java.lang.String toString();
  Signature: ()Ljava/lang/String;
  Code:
   Stack=1, Locals=1, Args_size=1
	aload_0
	invokestatic	Method scala/Function1$class.toString:(Lscala/Function1;)Ljava/lang/String;
	areturn
  Labels:

}

