Compiled from "Future.scala"
public final class scala.actors.Futures$$anon$3$$anonfun$6 extends java.lang.Object implements scala.Function1,scala.ScalaObject,java.io.Serializable
  SourceFile: "Future.scala"
  Scala: length = 0x
   
  InnerClass: 
   public final $anon$3=class scala/actors/Futures$$anon$3 of class scala/actors/Futures
   public final $anonfun$6=class scala/actors/Futures$$anon$3$$anonfun$6 of class scala/actors/Futures$$anon$3
  minor version: 0
  major version: 49
  Constant pool:
Asciz	SourceFile;
Asciz	Future.scala;
Asciz	<clinit>;
Asciz	()V;
Asciz	Code;
Asciz	serialVersionUID;
Asciz	J;
Asciz	scala/actors/Futures$$anon$3$$anonfun$6;
class	scala/actors/Futures$$anon$3$$anonfun$6
NameAndType	serialVersionUID:J
Field	scala/actors/Futures$$anon$3$$anonfun$6.serialVersionUID:J
Asciz	pf$1;
Asciz	Lscala/PartialFunction;;
Asciz	<init>;
Asciz	(Lscala/actors/Futures$$anon$3;Lscala/PartialFunction;)V;
Asciz	LineNumberTable;
NameAndType	pf$1:Lscala/PartialFunction;
Field	scala/actors/Futures$$anon$3$$anonfun$6.pf$1:Lscala/PartialFunction;
Asciz	java/lang/Object;
class	java/lang/Object
NameAndType	"<init>":()V
Method	java/lang/Object."<init>":()V
Asciz	scala/Function1$class;
class	scala/Function1$class
Asciz	$init$;
Asciz	(Lscala/Function1;)V;
NameAndType	$init$:(Lscala/Function1;)V
Method	scala/Function1$class.$init$:(Lscala/Function1;)V
Asciz	this;
Asciz	Lscala/actors/Futures$$anon$3$$anonfun$6;;
Asciz	$outer;
Asciz	Lscala/actors/Futures$$anon$3;;
Asciz	LocalVariableTable;
Asciz	apply;
Asciz	(Ljava/lang/Object;)Ljava/lang/Object;;
Asciz	scala/PartialFunction;
class	scala/PartialFunction
Asciz	(Lscala/PartialFunction;)Z;
NameAndType	apply:(Lscala/PartialFunction;)Z
Method	scala/actors/Futures$$anon$3$$anonfun$6.apply:(Lscala/PartialFunction;)Z
Asciz	scala/runtime/BoxesRunTime;
class	scala/runtime/BoxesRunTime
Asciz	boxToBoolean;
Asciz	(Z)Ljava/lang/Boolean;;
NameAndType	boxToBoolean:(Z)Ljava/lang/Boolean;
Method	scala/runtime/BoxesRunTime.boxToBoolean:(Z)Ljava/lang/Boolean;
Asciz	v1;
Asciz	Ljava/lang/Object;;
Asciz	equals;
Asciz	(Ljava/lang/Object;)Z;
NameAndType	equals:(Ljava/lang/Object;)Z
Method	java/lang/Object.equals:(Ljava/lang/Object;)Z
Asciz	(Lscala/PartialFunction<Ljava/lang/Object;Lscala/Tuple2<Ljava/lang/Integer;Ljava/lang/Object;>;>;)Z;
Asciz	Signature;
Asciz	andThen;
Asciz	(Lscala/Function1;)Lscala/Function1;;
Asciz	(Lscala/Function1;Lscala/Function1;)Lscala/Function1;;
NameAndType	andThen:(Lscala/Function1;Lscala/Function1;)Lscala/Function1;
Method	scala/Function1$class.andThen:(Lscala/Function1;Lscala/Function1;)Lscala/Function1;
Asciz	g;
Asciz	Lscala/Function1;;
Asciz	compose;
NameAndType	compose:(Lscala/Function1;Lscala/Function1;)Lscala/Function1;
Method	scala/Function1$class.compose:(Lscala/Function1;Lscala/Function1;)Lscala/Function1;
Asciz	toString;
Asciz	()Ljava/lang/String;;
Asciz	(Lscala/Function1;)Ljava/lang/String;;
NameAndType	toString:(Lscala/Function1;)Ljava/lang/String;
Method	scala/Function1$class.toString:(Lscala/Function1;)Ljava/lang/String;
Asciz	Scala;
Asciz	InnerClasses;
Asciz	scala/actors/Futures$$anon$3;
class	scala/actors/Futures$$anon$3
Asciz	scala/actors/Futures;
class	scala/actors/Futures
Asciz	$anon$3;
Asciz	$anonfun$6;
Asciz	scala/Function1;
class	scala/Function1
Asciz	scala/ScalaObject;
class	scala/ScalaObject
Asciz	java/io/Serializable;
class	java/io/Serializable

{
public static final long serialVersionUID;
  Signature: J

private final scala.PartialFunction pf$1;
  Signature: Lscala/PartialFunction;

public static {};
  Signature: ()V
  Code:
   Stack=2, Locals=0, Args_size=0
	lconst_0
	putstatic	Field serialVersionUID:J
	return
  Labels:

public scala.actors.Futures$$anon$3$$anonfun$6(scala.actors.Futures$$anon$3, scala.PartialFunction);
  Signature: (Lscala/actors/Futures$$anon$3;Lscala/PartialFunction;)V
  Code:
   Stack=2, Locals=3, Args_size=3
	aload_0
	aload_2
	putfield	Field pf$1:Lscala/PartialFunction;
	aload_0
	invokespecial	Method java/lang/Object."<init>":()V
	aload_0
	invokestatic	Method scala/Function1$class.$init$:(Lscala/Function1;)V
	return
  Labels:
  LocalVariableTable: 
   Start  Length  Slot  Name   Signature
   0      14      0    this       Lscala/actors/Futures$$anon$3$$anonfun$6;
   0      14      1    $outer       Lscala/actors/Futures$$anon$3;


public final java.lang.Object apply(java.lang.Object);
  Signature: (Ljava/lang/Object;)Ljava/lang/Object;
  Code:
   Stack=2, Locals=3, Args_size=2
	aload_0
	aload_1
	checkcast	class scala/PartialFunction
	invokevirtual	Method apply:(Lscala/PartialFunction;)Z
	istore_2
	iload_2
	invokestatic	Method scala/runtime/BoxesRunTime.boxToBoolean:(Z)Ljava/lang/Boolean;
	areturn
  Labels:
  LocalVariableTable: 
   Start  Length  Slot  Name   Signature
   0      14      0    this       Lscala/actors/Futures$$anon$3$$anonfun$6;
   0      14      1    v1       Ljava/lang/Object;


public final boolean apply(scala.PartialFunction);
  Signature: (Lscala/PartialFunction;)Z
  Code:
   Stack=2, Locals=3, Args_size=2
	aload_1
	aload_0
	getfield	Field pf$1:Lscala/PartialFunction;
	astore_2
	dup
	ifnonnull	l1 // aload_2
	pop
	aload_2
	ifnull	l2 // iconst_0
	goto	l3 // iconst_1
l1	aload_2
	invokevirtual	Method java/lang/Object.equals:(Ljava/lang/Object;)Z
	ifeq	l3 // iconst_1
l2	iconst_0
	goto	l4 // ireturn
l3	iconst_1
l4	ireturn
  Labels:
   	l1 = 18 // aload_2
   	l2 = 25 // iconst_0
   	l3 = 29 // iconst_1
   	l4 = 30 // ireturn
  Signature: length = 0x2
   00 35 

public scala.Function1 andThen(scala.Function1);
  Signature: (Lscala/Function1;)Lscala/Function1;
  Code:
   Stack=2, Locals=2, Args_size=2
	aload_0
	aload_1
	invokestatic	Method scala/Function1$class.andThen:(Lscala/Function1;Lscala/Function1;)Lscala/Function1;
	areturn
  Labels:
  LocalVariableTable: 
   Start  Length  Slot  Name   Signature
   0      6      0    this       Lscala/actors/Futures$$anon$3$$anonfun$6;
   0      6      1    g       Lscala/Function1;


public scala.Function1 compose(scala.Function1);
  Signature: (Lscala/Function1;)Lscala/Function1;
  Code:
   Stack=2, Locals=2, Args_size=2
	aload_0
	aload_1
	invokestatic	Method scala/Function1$class.compose:(Lscala/Function1;Lscala/Function1;)Lscala/Function1;
	areturn
  Labels:
  LocalVariableTable: 
   Start  Length  Slot  Name   Signature
   0      6      0    this       Lscala/actors/Futures$$anon$3$$anonfun$6;
   0      6      1    g       Lscala/Function1;


public java.lang.String toString();
  Signature: ()Ljava/lang/String;
  Code:
   Stack=1, Locals=1, Args_size=1
	aload_0
	invokestatic	Method scala/Function1$class.toString:(Lscala/Function1;)Ljava/lang/String;
	areturn
  Labels:

}

