Compiled from "Future.scala"
public final class scala.actors.Futures$$anonfun$4 extends java.lang.Object implements scala.Function1,scala.ScalaObject,java.io.Serializable
  SourceFile: "Future.scala"
  Scala: length = 0x
   
  InnerClass: 
   public final $anonfun$4=class scala/actors/Futures$$anonfun$4 of class scala/actors/Futures
   public final $anonfun$1=class scala/actors/Futures$$anonfun$4$$anonfun$1 of class scala/actors/Futures$$anonfun$4
  minor version: 0
  major version: 49
  Constant pool:
Asciz	SourceFile;
Asciz	Future.scala;
Asciz	<clinit>;
Asciz	()V;
Asciz	Code;
Asciz	serialVersionUID;
Asciz	J;
Asciz	scala/actors/Futures$$anonfun$4;
class	scala/actors/Futures$$anonfun$4
NameAndType	serialVersionUID:J
Field	scala/actors/Futures$$anonfun$4.serialVersionUID:J
Asciz	<init>;
Asciz	LineNumberTable;
Asciz	java/lang/Object;
class	java/lang/Object
NameAndType	"<init>":()V
Method	java/lang/Object."<init>":()V
Asciz	scala/Function1$class;
class	scala/Function1$class
Asciz	$init$;
Asciz	(Lscala/Function1;)V;
NameAndType	$init$:(Lscala/Function1;)V
Method	scala/Function1$class.$init$:(Lscala/Function1;)V
Asciz	apply;
Asciz	(Ljava/lang/Object;)Ljava/lang/Object;;
Asciz	scala/Tuple2;
class	scala/Tuple2
Asciz	(Lscala/Tuple2;)Lscala/PartialFunction;;
NameAndType	apply:(Lscala/Tuple2;)Lscala/PartialFunction;
Method	scala/actors/Futures$$anonfun$4.apply:(Lscala/Tuple2;)Lscala/PartialFunction;
Asciz	this;
Asciz	Lscala/actors/Futures$$anonfun$4;;
Asciz	v1;
Asciz	Ljava/lang/Object;;
Asciz	LocalVariableTable;
Asciz	_2;
Asciz	()Ljava/lang/Object;;
NameAndType	_2:()Ljava/lang/Object;
Method	scala/Tuple2._2:()Ljava/lang/Object;
Asciz	scala/actors/Future;
class	scala/actors/Future
Asciz	inputChannel;
Asciz	()Lscala/actors/InputChannel;;
NameAndType	inputChannel:()Lscala/actors/InputChannel;
Method	scala/actors/Future.inputChannel:()Lscala/actors/InputChannel;
Asciz	scala/actors/Futures$$anonfun$4$$anonfun$1;
class	scala/actors/Futures$$anonfun$4$$anonfun$1
Asciz	(Lscala/actors/Futures$$anonfun$4;Lscala/Tuple2;Lscala/actors/InputChannel;)V;
NameAndType	"<init>":(Lscala/actors/Futures$$anonfun$4;Lscala/Tuple2;Lscala/actors/InputChannel;)V
Method	scala/actors/Futures$$anonfun$4$$anonfun$1."<init>":(Lscala/actors/Futures$$anonfun$4;Lscala/Tuple2;Lscala/actors/InputChannel;)V
Asciz	p$1;
Asciz	Lscala/Tuple2;;
Asciz	FutCh$1;
Asciz	Lscala/actors/InputChannel;;
Asciz	singleCase;
Asciz	Lscala/PartialFunction;;
Asciz	(Lscala/Tuple2<Ljava/lang/Integer;Lscala/actors/Future<Ljava/lang/Object;>;>;)Lscala/PartialFunction<Ljava/lang/Object;Lscala/Tuple2<Ljava/lang/Integer;Ljava/lang/Object;>;>;;
Asciz	Signature;
Asciz	andThen;
Asciz	(Lscala/Function1;)Lscala/Function1;;
Asciz	(Lscala/Function1;Lscala/Function1;)Lscala/Function1;;
NameAndType	andThen:(Lscala/Function1;Lscala/Function1;)Lscala/Function1;
Method	scala/Function1$class.andThen:(Lscala/Function1;Lscala/Function1;)Lscala/Function1;
Asciz	g;
Asciz	Lscala/Function1;;
Asciz	compose;
NameAndType	compose:(Lscala/Function1;Lscala/Function1;)Lscala/Function1;
Method	scala/Function1$class.compose:(Lscala/Function1;Lscala/Function1;)Lscala/Function1;
Asciz	toString;
Asciz	()Ljava/lang/String;;
Asciz	(Lscala/Function1;)Ljava/lang/String;;
NameAndType	toString:(Lscala/Function1;)Ljava/lang/String;
Method	scala/Function1$class.toString:(Lscala/Function1;)Ljava/lang/String;
Asciz	Scala;
Asciz	InnerClasses;
Asciz	scala/actors/Futures;
class	scala/actors/Futures
Asciz	$anonfun$4;
Asciz	$anonfun$1;
Asciz	scala/Function1;
class	scala/Function1
Asciz	scala/ScalaObject;
class	scala/ScalaObject
Asciz	java/io/Serializable;
class	java/io/Serializable

{
public static final long serialVersionUID;
  Signature: J

public static {};
  Signature: ()V
  Code:
   Stack=2, Locals=0, Args_size=0
	lconst_0
	putstatic	Field serialVersionUID:J
	return
  Labels:

public scala.actors.Futures$$anonfun$4();
  Signature: ()V
  Code:
   Stack=1, Locals=1, Args_size=1
	aload_0
	invokespecial	Method java/lang/Object."<init>":()V
	aload_0
	invokestatic	Method scala/Function1$class.$init$:(Lscala/Function1;)V
	return
  Labels:

public final java.lang.Object apply(java.lang.Object);
  Signature: (Ljava/lang/Object;)Ljava/lang/Object;
  Code:
   Stack=2, Locals=2, Args_size=2
	aload_0
	aload_1
	checkcast	class scala/Tuple2
	invokevirtual	Method apply:(Lscala/Tuple2;)Lscala/PartialFunction;
	areturn
  Labels:
  LocalVariableTable: 
   Start  Length  Slot  Name   Signature
   0      9      0    this       Lscala/actors/Futures$$anonfun$4;
   0      9      1    v1       Ljava/lang/Object;


public final scala.PartialFunction apply(scala.Tuple2);
  Signature: (Lscala/Tuple2;)Lscala/PartialFunction;
  Code:
   Stack=5, Locals=4, Args_size=2
	aload_1
	invokevirtual	Method scala/Tuple2._2:()Ljava/lang/Object;
	checkcast	class scala/actors/Future
	invokevirtual	Method scala/actors/Future.inputChannel:()Lscala/actors/InputChannel;
	astore_2
	new	class scala/actors/Futures$$anonfun$4$$anonfun$1
	dup
	aload_0
	aload_1
	aload_2
	invokespecial	Method scala/actors/Futures$$anonfun$4$$anonfun$1."<init>":(Lscala/actors/Futures$$anonfun$4;Lscala/Tuple2;Lscala/actors/InputChannel;)V
	astore_3
	aload_3
	areturn
  Labels:
  LocalVariableTable: 
   Start  Length  Slot  Name   Signature
   0      24      0    this       Lscala/actors/Futures$$anonfun$4;
   0      24      1    p$1       Lscala/Tuple2;
   11      12      2    FutCh$1       Lscala/actors/InputChannel;
   22      1      3    singleCase       Lscala/PartialFunction;

  Signature: length = 0x2
   00 39 

public scala.Function1 andThen(scala.Function1);
  Signature: (Lscala/Function1;)Lscala/Function1;
  Code:
   Stack=2, Locals=2, Args_size=2
	aload_0
	aload_1
	invokestatic	Method scala/Function1$class.andThen:(Lscala/Function1;Lscala/Function1;)Lscala/Function1;
	areturn
  Labels:
  LocalVariableTable: 
   Start  Length  Slot  Name   Signature
   0      6      0    this       Lscala/actors/Futures$$anonfun$4;
   0      6      1    g       Lscala/Function1;


public scala.Function1 compose(scala.Function1);
  Signature: (Lscala/Function1;)Lscala/Function1;
  Code:
   Stack=2, Locals=2, Args_size=2
	aload_0
	aload_1
	invokestatic	Method scala/Function1$class.compose:(Lscala/Function1;Lscala/Function1;)Lscala/Function1;
	areturn
  Labels:
  LocalVariableTable: 
   Start  Length  Slot  Name   Signature
   0      6      0    this       Lscala/actors/Futures$$anonfun$4;
   0      6      1    g       Lscala/Function1;


public java.lang.String toString();
  Signature: ()Ljava/lang/String;
  Code:
   Stack=1, Locals=1, Args_size=1
	aload_0
	invokestatic	Method scala/Function1$class.toString:(Lscala/Function1;)Ljava/lang/String;
	areturn
  Labels:

}

