Compiled from "Future.scala"
public final class scala.actors.Futures$$anon$2 extends scala.actors.Future
  SourceFile: "Future.scala"
  Signature: length = 0x2
   00 68 
  Scala: length = 0x
   
  InnerClass: 
   public final #109= #14 of #108; //$anon$2=class scala/actors/Futures$$anon$2 of class scala/actors/Futures
   public final #110= #97 of #14; //$anonfun$apply$2=class scala/actors/Futures$$anon$2$$anonfun$apply$2 of class scala/actors/Futures$$anon$2
   public final #111= #36 of #14; //$anonfun$isSet$1=class scala/actors/Futures$$anon$2$$anonfun$isSet$1 of class scala/actors/Futures$$anon$2
   public final #112= #84 of #14; //$anonfun$respond$1=class scala/actors/Futures$$anon$2$$anonfun$respond$1 of class scala/actors/Futures$$anon$2
  minor version: 0
  major version: 49
  Constant pool:
const #1 = Asciz	SourceFile;
const #2 = Asciz	Future.scala;
const #3 = Asciz	<init>;
const #4 = Asciz	(Lscala/actors/InputChannel;)V;
const #5 = Asciz	Code;
const #6 = Asciz	LineNumberTable;
const #7 = Asciz	scala/actors/Future;
const #8 = class	#7;	//  scala/actors/Future
const #9 = NameAndType	#3:#4;//  "<init>":(Lscala/actors/InputChannel;)V
const #10 = Method	#8.#9;	//  scala/actors/Future."<init>":(Lscala/actors/InputChannel;)V
const #11 = Asciz	isSet;
const #12 = Asciz	()Z;
const #13 = Asciz	scala/actors/Futures$$anon$2;
const #14 = class	#13;	//  scala/actors/Futures$$anon$2
const #15 = Asciz	value;
const #16 = Asciz	()Lscala/Option;;
const #17 = NameAndType	#15:#16;//  value:()Lscala/Option;
const #18 = Method	#14.#17;	//  scala/actors/Futures$$anon$2.value:()Lscala/Option;
const #19 = Asciz	scala/None$;
const #20 = class	#19;	//  scala/None$
const #21 = Asciz	MODULE$;
const #22 = Asciz	Lscala/None$;;
const #23 = NameAndType	#21:#22;//  MODULE$:Lscala/None$;
const #24 = Field	#20.#23;	//  scala/None$.MODULE$:Lscala/None$;
const #25 = Asciz	java/lang/Object;
const #26 = class	#25;	//  java/lang/Object
const #27 = Asciz	equals;
const #28 = Asciz	(Ljava/lang/Object;)Z;
const #29 = NameAndType	#27:#28;//  equals:(Ljava/lang/Object;)Z
const #30 = Method	#26.#29;	//  java/lang/Object.equals:(Ljava/lang/Object;)Z
const #31 = Asciz	inputChannel;
const #32 = Asciz	()Lscala/actors/InputChannel;;
const #33 = NameAndType	#31:#32;//  inputChannel:()Lscala/actors/InputChannel;
const #34 = Method	#14.#33;	//  scala/actors/Futures$$anon$2.inputChannel:()Lscala/actors/InputChannel;
const #35 = Asciz	scala/actors/Futures$$anon$2$$anonfun$isSet$1;
const #36 = class	#35;	//  scala/actors/Futures$$anon$2$$anonfun$isSet$1
const #37 = Asciz	(Lscala/actors/Futures$$anon$2;)V;
const #38 = NameAndType	#3:#37;//  "<init>":(Lscala/actors/Futures$$anon$2;)V
const #39 = Method	#36.#38;	//  scala/actors/Futures$$anon$2$$anonfun$isSet$1."<init>":(Lscala/actors/Futures$$anon$2;)V
const #40 = Asciz	scala/actors/InputChannel;
const #41 = class	#40;	//  scala/actors/InputChannel
const #42 = Asciz	receiveWithin;
const #43 = Asciz	(JLscala/PartialFunction;)Ljava/lang/Object;;
const #44 = NameAndType	#42:#43;//  receiveWithin:(JLscala/PartialFunction;)Ljava/lang/Object;
const #45 = InterfaceMethod	#41.#44;	//  scala/actors/InputChannel.receiveWithin:(JLscala/PartialFunction;)Ljava/lang/Object;
const #46 = Asciz	scala/runtime/BoxesRunTime;
const #47 = class	#46;	//  scala/runtime/BoxesRunTime
const #48 = Asciz	unboxToBoolean;
const #49 = NameAndType	#48:#28;//  unboxToBoolean:(Ljava/lang/Object;)Z
const #50 = Method	#47.#49;	//  scala/runtime/BoxesRunTime.unboxToBoolean:(Ljava/lang/Object;)Z
const #51 = Asciz	scala/MatchError;
const #52 = class	#51;	//  scala/MatchError
const #53 = Asciz	scala/Option;
const #54 = class	#53;	//  scala/Option
const #55 = Asciz	toString;
const #56 = Asciz	()Ljava/lang/String;;
const #57 = NameAndType	#55:#56;//  toString:()Ljava/lang/String;
const #58 = Method	#54.#57;	//  scala/Option.toString:()Ljava/lang/String;
const #59 = Asciz	(Ljava/lang/String;)V;
const #60 = NameAndType	#3:#59;//  "<init>":(Ljava/lang/String;)V
const #61 = Method	#52.#60;	//  scala/MatchError."<init>":(Ljava/lang/String;)V
const #62 = Asciz	scala/Some;
const #63 = class	#62;	//  scala/Some
const #64 = Asciz	this;
const #65 = Asciz	Lscala/actors/Futures$$anon$2;;
const #66 = Asciz	temp46;
const #67 = Asciz	Lscala/Option;;
const #68 = Asciz	LocalVariableTable;
const #69 = Asciz	respond;
const #70 = Asciz	(Lscala/Function1;)V;
const #71 = NameAndType	#11:#12;//  isSet:()Z
const #72 = Method	#14.#71;	//  scala/actors/Futures$$anon$2.isSet:()Z
const #73 = Asciz	get;
const #74 = Asciz	()Ljava/lang/Object;;
const #75 = NameAndType	#73:#74;//  get:()Ljava/lang/Object;
const #76 = Method	#54.#75;	//  scala/Option.get:()Ljava/lang/Object;
const #77 = Asciz	scala/Function1;
const #78 = class	#77;	//  scala/Function1
const #79 = Asciz	apply;
const #80 = Asciz	(Ljava/lang/Object;)Ljava/lang/Object;;
const #81 = NameAndType	#79:#80;//  apply:(Ljava/lang/Object;)Ljava/lang/Object;
const #82 = InterfaceMethod	#78.#81;	//  scala/Function1.apply:(Ljava/lang/Object;)Ljava/lang/Object;
const #83 = Asciz	scala/actors/Futures$$anon$2$$anonfun$respond$1;
const #84 = class	#83;	//  scala/actors/Futures$$anon$2$$anonfun$respond$1
const #85 = Asciz	(Lscala/actors/Futures$$anon$2;Lscala/Function1;)V;
const #86 = NameAndType	#3:#85;//  "<init>":(Lscala/actors/Futures$$anon$2;Lscala/Function1;)V
const #87 = Method	#84.#86;	//  scala/actors/Futures$$anon$2$$anonfun$respond$1."<init>":(Lscala/actors/Futures$$anon$2;Lscala/Function1;)V
const #88 = Asciz	react;
const #89 = Asciz	(Lscala/PartialFunction;)Lscala/runtime/Nothing$;;
const #90 = NameAndType	#88:#89;//  react:(Lscala/PartialFunction;)Lscala/runtime/Nothing$;
const #91 = InterfaceMethod	#41.#90;	//  scala/actors/InputChannel.react:(Lscala/PartialFunction;)Lscala/runtime/Nothing$;
const #92 = Asciz	k$1;
const #93 = Asciz	Lscala/Function1;;
const #94 = Asciz	(Lscala/Function1<TT;Ljava/lang/Object;>;)V;
const #95 = Asciz	Signature;
const #96 = Asciz	scala/actors/Futures$$anon$2$$anonfun$apply$2;
const #97 = class	#96;	//  scala/actors/Futures$$anon$2$$anonfun$apply$2
const #98 = Method	#97.#38;	//  scala/actors/Futures$$anon$2$$anonfun$apply$2."<init>":(Lscala/actors/Futures$$anon$2;)V
const #99 = Asciz	receive;
const #100 = Asciz	(Lscala/PartialFunction;)Ljava/lang/Object;;
const #101 = NameAndType	#99:#100;//  receive:(Lscala/PartialFunction;)Ljava/lang/Object;
const #102 = InterfaceMethod	#41.#101;	//  scala/actors/InputChannel.receive:(Lscala/PartialFunction;)Ljava/lang/Object;
const #103 = Asciz	()TT;;
const #104 = Asciz	Lscala/actors/Future<TT;>;;
const #105 = Asciz	Scala;
const #106 = Asciz	InnerClasses;
const #107 = Asciz	scala/actors/Futures;
const #108 = class	#107;	//  scala/actors/Futures
const #109 = Asciz	$anon$2;
const #110 = Asciz	$anonfun$apply$2;
const #111 = Asciz	$anonfun$isSet$1;
const #112 = Asciz	$anonfun$respond$1;

{
public scala.actors.Futures$$anon$2(scala.actors.InputChannel);
  Code:
   Stack=2, Locals=2, Args_size=2
   0:	aload_0
   1:	aload_1
   2:	invokespecial	#10; //Method scala/actors/Future."<init>":(Lscala/actors/InputChannel;)V
   5:	return
  LineNumberTable: 
   line 146: 0


public boolean isSet();
  Code:
   Stack=6, Locals=2, Args_size=1
   0:	aload_0
   1:	invokevirtual	#18; //Method value:()Lscala/Option;
   4:	astore_1
   5:	getstatic	#24; //Field scala/None$.MODULE$:Lscala/None$;
   8:	dup
   9:	ifnonnull	20
   12:	pop
   13:	aload_1
   14:	ifnull	27
   17:	goto	67
   20:	aload_1
   21:	invokevirtual	#30; //Method java/lang/Object.equals:(Ljava/lang/Object;)Z
   24:	ifeq	67
   27:	iconst_1
   28:	ifeq	55
   31:	aload_0
   32:	invokevirtual	#34; //Method inputChannel:()Lscala/actors/InputChannel;
   35:	lconst_0
   36:	new	#36; //class scala/actors/Futures$$anon$2$$anonfun$isSet$1
   39:	dup
   40:	aload_0
   41:	invokespecial	#39; //Method scala/actors/Futures$$anon$2$$anonfun$isSet$1."<init>":(Lscala/actors/Futures$$anon$2;)V
   44:	invokeinterface	#45,  4; //InterfaceMethod scala/actors/InputChannel.receiveWithin:(JLscala/PartialFunction;)Ljava/lang/Object;
   49:	invokestatic	#50; //Method scala/runtime/BoxesRunTime.unboxToBoolean:(Ljava/lang/Object;)Z
   52:	goto	79
   55:	new	#52; //class scala/MatchError
   58:	dup
   59:	aload_1
   60:	invokevirtual	#58; //Method scala/Option.toString:()Ljava/lang/String;
   63:	invokespecial	#61; //Method scala/MatchError."<init>":(Ljava/lang/String;)V
   66:	athrow
   67:	aload_1
   68:	instanceof	#63; //class scala/Some
   71:	ifeq	92
   74:	iconst_1
   75:	ifeq	80
   78:	iconst_1
   79:	ireturn
   80:	new	#52; //class scala/MatchError
   83:	dup
   84:	aload_1
   85:	invokevirtual	#58; //Method scala/Option.toString:()Ljava/lang/String;
   88:	invokespecial	#61; //Method scala/MatchError."<init>":(Ljava/lang/String;)V
   91:	athrow
   92:	new	#52; //class scala/MatchError
   95:	dup
   96:	aload_1
   97:	invokevirtual	#58; //Method scala/Option.toString:()Ljava/lang/String;
   100:	invokespecial	#61; //Method scala/MatchError."<init>":(Ljava/lang/String;)V
   103:	athrow
  LineNumberTable: 
   line 157: 0
   line 644: 27
   line 158: 31
   line 157: 55
   line 644: 74
   line 162: 78
   line 157: 79

  LocalVariableTable: 
   Start  Length  Slot  Name   Signature
   0      104      0    this       Lscala/actors/Futures$$anon$2;
   5      99      1    temp46       Lscala/Option;


public void respond(scala.Function1);
  Code:
   Stack=5, Locals=2, Args_size=2
   0:	aload_0
   1:	invokevirtual	#72; //Method isSet:()Z
   4:	ifeq	22
   7:	aload_1
   8:	aload_0
   9:	invokevirtual	#18; //Method value:()Lscala/Option;
   12:	invokevirtual	#76; //Method scala/Option.get:()Ljava/lang/Object;
   15:	invokeinterface	#82,  2; //InterfaceMethod scala/Function1.apply:(Ljava/lang/Object;)Ljava/lang/Object;
   20:	pop
   21:	return
   22:	aload_0
   23:	invokevirtual	#34; //Method inputChannel:()Lscala/actors/InputChannel;
   26:	new	#84; //class scala/actors/Futures$$anon$2$$anonfun$respond$1
   29:	dup
   30:	aload_0
   31:	aload_1
   32:	invokespecial	#87; //Method scala/actors/Futures$$anon$2$$anonfun$respond$1."<init>":(Lscala/actors/Futures$$anon$2;Lscala/Function1;)V
   35:	invokeinterface	#91,  2; //InterfaceMethod scala/actors/InputChannel.react:(Lscala/PartialFunction;)Lscala/runtime/Nothing$;
   40:	athrow
  LineNumberTable: 
   line 153: 0
   line 154: 22

  LocalVariableTable: 
   Start  Length  Slot  Name   Signature
   0      41      0    this       Lscala/actors/Futures$$anon$2;
   0      41      1    k$1       Lscala/Function1;

  Signature: length = 0x2
   00 5E 

public java.lang.Object apply();
  Code:
   Stack=4, Locals=1, Args_size=1
   0:	aload_0
   1:	invokevirtual	#72; //Method isSet:()Z
   4:	ifeq	17
   7:	aload_0
   8:	invokevirtual	#18; //Method value:()Lscala/Option;
   11:	invokevirtual	#76; //Method scala/Option.get:()Ljava/lang/Object;
   14:	goto	34
   17:	aload_0
   18:	invokevirtual	#34; //Method inputChannel:()Lscala/actors/InputChannel;
   21:	new	#97; //class scala/actors/Futures$$anon$2$$anonfun$apply$2
   24:	dup
   25:	aload_0
   26:	invokespecial	#98; //Method scala/actors/Futures$$anon$2$$anonfun$apply$2."<init>":(Lscala/actors/Futures$$anon$2;)V
   29:	invokeinterface	#102,  2; //InterfaceMethod scala/actors/InputChannel.receive:(Lscala/PartialFunction;)Ljava/lang/Object;
   34:	areturn
  LineNumberTable: 
   line 148: 0
   line 149: 17
   line 148: 34

  Signature: length = 0x2
   00 67 

}

