Compiled from "Future.scala"
public final class scala.actors.Futures$$anon$2 extends java.lang.Object implements scala.PartialFunction
  SourceFile: "Future.scala"
  Scala: length = 0x
   
  Signature: length = 0x2
   01 FFFFFF8D 
  InnerClass: 
   public final $anon$2=class scala/actors/Futures$$anon$2 of class scala/actors/Futures
   public final $anonfun$8=class scala/actors/Futures$$anon$2$$anonfun$8 of class scala/actors/Futures$$anon$2
   public final $anonfun$7=class scala/actors/Futures$$anon$2$$anonfun$7 of class scala/actors/Futures$$anon$2
   public final $anonfun$isDefinedAt$1=class scala/actors/Futures$$anon$2$$anonfun$isDefinedAt$1 of class scala/actors/Futures$$anon$2
  minor version: 0
  major version: 49
  Constant pool:
Asciz	SourceFile;
Asciz	Future.scala;
Asciz	resultsMap$1;
Asciz	Lscala/runtime/ObjectRef;;
Asciz	partFuns$1;
Asciz	Lscala/collection/Seq;;
Asciz	orElse;
Asciz	(Lscala/PartialFunction;)Lscala/PartialFunction;;
Asciz	Code;
Asciz	LineNumberTable;
Asciz	scala/PartialFunction$class;
class	scala/PartialFunction$class
Asciz	(Lscala/PartialFunction;Lscala/PartialFunction;)Lscala/PartialFunction;;
NameAndType	orElse:(Lscala/PartialFunction;Lscala/PartialFunction;)Lscala/PartialFunction;
Method	scala/PartialFunction$class.orElse:(Lscala/PartialFunction;Lscala/PartialFunction;)Lscala/PartialFunction;
Asciz	this;
Asciz	Lscala/actors/Futures$$anon$2;;
Asciz	that;
Asciz	Lscala/PartialFunction;;
Asciz	LocalVariableTable;
Asciz	andThen;
Asciz	(Lscala/Function1;)Lscala/PartialFunction;;
Asciz	(Lscala/PartialFunction;Lscala/Function1;)Lscala/PartialFunction;;
NameAndType	andThen:(Lscala/PartialFunction;Lscala/Function1;)Lscala/PartialFunction;
Method	scala/PartialFunction$class.andThen:(Lscala/PartialFunction;Lscala/Function1;)Lscala/PartialFunction;
Asciz	k;
Asciz	Lscala/Function1;;
Asciz	lift;
Asciz	()Lscala/Function1;;
Asciz	(Lscala/PartialFunction;)Lscala/Function1;;
NameAndType	lift:(Lscala/PartialFunction;)Lscala/Function1;
Method	scala/PartialFunction$class.lift:(Lscala/PartialFunction;)Lscala/Function1;
Asciz	apply$mcVI$sp;
Asciz	(I)V;
Asciz	scala/Function1$class;
class	scala/Function1$class
Asciz	(Lscala/Function1;I)V;
NameAndType	apply$mcVI$sp:(Lscala/Function1;I)V
Method	scala/Function1$class.apply$mcVI$sp:(Lscala/Function1;I)V
Asciz	v1;
Asciz	I;
Asciz	apply$mcZI$sp;
Asciz	(I)Z;
Asciz	(Lscala/Function1;I)Z;
NameAndType	apply$mcZI$sp:(Lscala/Function1;I)Z
Method	scala/Function1$class.apply$mcZI$sp:(Lscala/Function1;I)Z
Asciz	apply$mcII$sp;
Asciz	(I)I;
Asciz	(Lscala/Function1;I)I;
NameAndType	apply$mcII$sp:(Lscala/Function1;I)I
Method	scala/Function1$class.apply$mcII$sp:(Lscala/Function1;I)I
Asciz	apply$mcLI$sp;
Asciz	(I)J;
Asciz	(Lscala/Function1;I)J;
NameAndType	apply$mcLI$sp:(Lscala/Function1;I)J
Method	scala/Function1$class.apply$mcLI$sp:(Lscala/Function1;I)J
Asciz	apply$mcDI$sp;
Asciz	(I)D;
Asciz	(Lscala/Function1;I)D;
NameAndType	apply$mcDI$sp:(Lscala/Function1;I)D
Method	scala/Function1$class.apply$mcDI$sp:(Lscala/Function1;I)D
Asciz	apply$mcVL$sp;
Asciz	(J)V;
Asciz	(Lscala/Function1;J)V;
NameAndType	apply$mcVL$sp:(Lscala/Function1;J)V
Method	scala/Function1$class.apply$mcVL$sp:(Lscala/Function1;J)V
Asciz	J;
Asciz	apply$mcZL$sp;
Asciz	(J)Z;
Asciz	(Lscala/Function1;J)Z;
NameAndType	apply$mcZL$sp:(Lscala/Function1;J)Z
Method	scala/Function1$class.apply$mcZL$sp:(Lscala/Function1;J)Z
Asciz	apply$mcIL$sp;
Asciz	(J)I;
Asciz	(Lscala/Function1;J)I;
NameAndType	apply$mcIL$sp:(Lscala/Function1;J)I
Method	scala/Function1$class.apply$mcIL$sp:(Lscala/Function1;J)I
Asciz	apply$mcLL$sp;
Asciz	(J)J;
Asciz	(Lscala/Function1;J)J;
NameAndType	apply$mcLL$sp:(Lscala/Function1;J)J
Method	scala/Function1$class.apply$mcLL$sp:(Lscala/Function1;J)J
Asciz	apply$mcDL$sp;
Asciz	(J)D;
Asciz	(Lscala/Function1;J)D;
NameAndType	apply$mcDL$sp:(Lscala/Function1;J)D
Method	scala/Function1$class.apply$mcDL$sp:(Lscala/Function1;J)D
Asciz	apply$mcVD$sp;
Asciz	(D)V;
Asciz	(Lscala/Function1;D)V;
NameAndType	apply$mcVD$sp:(Lscala/Function1;D)V
Method	scala/Function1$class.apply$mcVD$sp:(Lscala/Function1;D)V
Asciz	D;
Asciz	apply$mcZD$sp;
Asciz	(D)Z;
Asciz	(Lscala/Function1;D)Z;
NameAndType	apply$mcZD$sp:(Lscala/Function1;D)Z
Method	scala/Function1$class.apply$mcZD$sp:(Lscala/Function1;D)Z
Asciz	apply$mcID$sp;
Asciz	(D)I;
Asciz	(Lscala/Function1;D)I;
NameAndType	apply$mcID$sp:(Lscala/Function1;D)I
Method	scala/Function1$class.apply$mcID$sp:(Lscala/Function1;D)I
Asciz	apply$mcLD$sp;
Asciz	(D)J;
Asciz	(Lscala/Function1;D)J;
NameAndType	apply$mcLD$sp:(Lscala/Function1;D)J
Method	scala/Function1$class.apply$mcLD$sp:(Lscala/Function1;D)J
Asciz	apply$mcDD$sp;
Asciz	(D)D;
Asciz	(Lscala/Function1;D)D;
NameAndType	apply$mcDD$sp:(Lscala/Function1;D)D
Method	scala/Function1$class.apply$mcDD$sp:(Lscala/Function1;D)D
Asciz	toString;
Asciz	()Ljava/lang/String;;
Asciz	(Lscala/Function1;)Ljava/lang/String;;
NameAndType	toString:(Lscala/Function1;)Ljava/lang/String;
Method	scala/Function1$class.toString:(Lscala/Function1;)Ljava/lang/String;
Asciz	compose;
Asciz	(Lscala/Function1;)Lscala/Function1;;
Asciz	(Lscala/Function1;Lscala/Function1;)Lscala/Function1;;
NameAndType	compose:(Lscala/Function1;Lscala/Function1;)Lscala/Function1;
Method	scala/Function1$class.compose:(Lscala/Function1;Lscala/Function1;)Lscala/Function1;
Asciz	g;
Asciz	compose$mcVI$sp;
NameAndType	compose$mcVI$sp:(Lscala/Function1;Lscala/Function1;)Lscala/Function1;
Method	scala/Function1$class.compose$mcVI$sp:(Lscala/Function1;Lscala/Function1;)Lscala/Function1;
Asciz	compose$mcZI$sp;
NameAndType	compose$mcZI$sp:(Lscala/Function1;Lscala/Function1;)Lscala/Function1;
Method	scala/Function1$class.compose$mcZI$sp:(Lscala/Function1;Lscala/Function1;)Lscala/Function1;
Asciz	compose$mcII$sp;
NameAndType	compose$mcII$sp:(Lscala/Function1;Lscala/Function1;)Lscala/Function1;
Method	scala/Function1$class.compose$mcII$sp:(Lscala/Function1;Lscala/Function1;)Lscala/Function1;
Asciz	compose$mcLI$sp;
NameAndType	compose$mcLI$sp:(Lscala/Function1;Lscala/Function1;)Lscala/Function1;
Method	scala/Function1$class.compose$mcLI$sp:(Lscala/Function1;Lscala/Function1;)Lscala/Function1;
Asciz	compose$mcDI$sp;
NameAndType	compose$mcDI$sp:(Lscala/Function1;Lscala/Function1;)Lscala/Function1;
Method	scala/Function1$class.compose$mcDI$sp:(Lscala/Function1;Lscala/Function1;)Lscala/Function1;
Asciz	compose$mcVL$sp;
NameAndType	compose$mcVL$sp:(Lscala/Function1;Lscala/Function1;)Lscala/Function1;
Method	scala/Function1$class.compose$mcVL$sp:(Lscala/Function1;Lscala/Function1;)Lscala/Function1;
Asciz	compose$mcZL$sp;
NameAndType	compose$mcZL$sp:(Lscala/Function1;Lscala/Function1;)Lscala/Function1;
Method	scala/Function1$class.compose$mcZL$sp:(Lscala/Function1;Lscala/Function1;)Lscala/Function1;
Asciz	compose$mcIL$sp;
NameAndType	compose$mcIL$sp:(Lscala/Function1;Lscala/Function1;)Lscala/Function1;
Method	scala/Function1$class.compose$mcIL$sp:(Lscala/Function1;Lscala/Function1;)Lscala/Function1;
Asciz	compose$mcLL$sp;
NameAndType	compose$mcLL$sp:(Lscala/Function1;Lscala/Function1;)Lscala/Function1;
Method	scala/Function1$class.compose$mcLL$sp:(Lscala/Function1;Lscala/Function1;)Lscala/Function1;
Asciz	compose$mcDL$sp;
NameAndType	compose$mcDL$sp:(Lscala/Function1;Lscala/Function1;)Lscala/Function1;
Method	scala/Function1$class.compose$mcDL$sp:(Lscala/Function1;Lscala/Function1;)Lscala/Function1;
Asciz	compose$mcVD$sp;
NameAndType	compose$mcVD$sp:(Lscala/Function1;Lscala/Function1;)Lscala/Function1;
Method	scala/Function1$class.compose$mcVD$sp:(Lscala/Function1;Lscala/Function1;)Lscala/Function1;
Asciz	compose$mcZD$sp;
NameAndType	compose$mcZD$sp:(Lscala/Function1;Lscala/Function1;)Lscala/Function1;
Method	scala/Function1$class.compose$mcZD$sp:(Lscala/Function1;Lscala/Function1;)Lscala/Function1;
Asciz	compose$mcID$sp;
NameAndType	compose$mcID$sp:(Lscala/Function1;Lscala/Function1;)Lscala/Function1;
Method	scala/Function1$class.compose$mcID$sp:(Lscala/Function1;Lscala/Function1;)Lscala/Function1;
Asciz	compose$mcLD$sp;
NameAndType	compose$mcLD$sp:(Lscala/Function1;Lscala/Function1;)Lscala/Function1;
Method	scala/Function1$class.compose$mcLD$sp:(Lscala/Function1;Lscala/Function1;)Lscala/Function1;
Asciz	compose$mcDD$sp;
NameAndType	compose$mcDD$sp:(Lscala/Function1;Lscala/Function1;)Lscala/Function1;
Method	scala/Function1$class.compose$mcDD$sp:(Lscala/Function1;Lscala/Function1;)Lscala/Function1;
Asciz	andThen$mcVI$sp;
NameAndType	andThen$mcVI$sp:(Lscala/Function1;Lscala/Function1;)Lscala/Function1;
Method	scala/Function1$class.andThen$mcVI$sp:(Lscala/Function1;Lscala/Function1;)Lscala/Function1;
Asciz	andThen$mcZI$sp;
NameAndType	andThen$mcZI$sp:(Lscala/Function1;Lscala/Function1;)Lscala/Function1;
Method	scala/Function1$class.andThen$mcZI$sp:(Lscala/Function1;Lscala/Function1;)Lscala/Function1;
Asciz	andThen$mcII$sp;
NameAndType	andThen$mcII$sp:(Lscala/Function1;Lscala/Function1;)Lscala/Function1;
Method	scala/Function1$class.andThen$mcII$sp:(Lscala/Function1;Lscala/Function1;)Lscala/Function1;
Asciz	andThen$mcLI$sp;
NameAndType	andThen$mcLI$sp:(Lscala/Function1;Lscala/Function1;)Lscala/Function1;
Method	scala/Function1$class.andThen$mcLI$sp:(Lscala/Function1;Lscala/Function1;)Lscala/Function1;
Asciz	andThen$mcDI$sp;
NameAndType	andThen$mcDI$sp:(Lscala/Function1;Lscala/Function1;)Lscala/Function1;
Method	scala/Function1$class.andThen$mcDI$sp:(Lscala/Function1;Lscala/Function1;)Lscala/Function1;
Asciz	andThen$mcVL$sp;
NameAndType	andThen$mcVL$sp:(Lscala/Function1;Lscala/Function1;)Lscala/Function1;
Method	scala/Function1$class.andThen$mcVL$sp:(Lscala/Function1;Lscala/Function1;)Lscala/Function1;
Asciz	andThen$mcZL$sp;
NameAndType	andThen$mcZL$sp:(Lscala/Function1;Lscala/Function1;)Lscala/Function1;
Method	scala/Function1$class.andThen$mcZL$sp:(Lscala/Function1;Lscala/Function1;)Lscala/Function1;
Asciz	andThen$mcIL$sp;
NameAndType	andThen$mcIL$sp:(Lscala/Function1;Lscala/Function1;)Lscala/Function1;
Method	scala/Function1$class.andThen$mcIL$sp:(Lscala/Function1;Lscala/Function1;)Lscala/Function1;
Asciz	andThen$mcLL$sp;
NameAndType	andThen$mcLL$sp:(Lscala/Function1;Lscala/Function1;)Lscala/Function1;
Method	scala/Function1$class.andThen$mcLL$sp:(Lscala/Function1;Lscala/Function1;)Lscala/Function1;
Asciz	andThen$mcDL$sp;
NameAndType	andThen$mcDL$sp:(Lscala/Function1;Lscala/Function1;)Lscala/Function1;
Method	scala/Function1$class.andThen$mcDL$sp:(Lscala/Function1;Lscala/Function1;)Lscala/Function1;
Asciz	andThen$mcVD$sp;
NameAndType	andThen$mcVD$sp:(Lscala/Function1;Lscala/Function1;)Lscala/Function1;
Method	scala/Function1$class.andThen$mcVD$sp:(Lscala/Function1;Lscala/Function1;)Lscala/Function1;
Asciz	andThen$mcZD$sp;
NameAndType	andThen$mcZD$sp:(Lscala/Function1;Lscala/Function1;)Lscala/Function1;
Method	scala/Function1$class.andThen$mcZD$sp:(Lscala/Function1;Lscala/Function1;)Lscala/Function1;
Asciz	andThen$mcID$sp;
NameAndType	andThen$mcID$sp:(Lscala/Function1;Lscala/Function1;)Lscala/Function1;
Method	scala/Function1$class.andThen$mcID$sp:(Lscala/Function1;Lscala/Function1;)Lscala/Function1;
Asciz	andThen$mcLD$sp;
NameAndType	andThen$mcLD$sp:(Lscala/Function1;Lscala/Function1;)Lscala/Function1;
Method	scala/Function1$class.andThen$mcLD$sp:(Lscala/Function1;Lscala/Function1;)Lscala/Function1;
Asciz	andThen$mcDD$sp;
NameAndType	andThen$mcDD$sp:(Lscala/Function1;Lscala/Function1;)Lscala/Function1;
Method	scala/Function1$class.andThen$mcDD$sp:(Lscala/Function1;Lscala/Function1;)Lscala/Function1;
Asciz	isDefinedAt;
Asciz	(Ljava/lang/Object;)Z;
Asciz	scala/actors/TIMEOUT$;
class	scala/actors/TIMEOUT$
Asciz	MODULE$;
Asciz	Lscala/actors/TIMEOUT$;;
NameAndType	MODULE$:Lscala/actors/TIMEOUT$;
Field	scala/actors/TIMEOUT$.MODULE$:Lscala/actors/TIMEOUT$;
Asciz	java/lang/Object;
class	java/lang/Object
Asciz	equals;
NameAndType	equals:(Ljava/lang/Object;)Z
Method	java/lang/Object.equals:(Ljava/lang/Object;)Z
Asciz	scala/actors/Futures$$anon$2;
class	scala/actors/Futures$$anon$2
NameAndType	partFuns$1:Lscala/collection/Seq;
Field	scala/actors/Futures$$anon$2.partFuns$1:Lscala/collection/Seq;
Asciz	scala/actors/Futures$$anon$2$$anonfun$isDefinedAt$1;
class	scala/actors/Futures$$anon$2$$anonfun$isDefinedAt$1
Asciz	<init>;
Asciz	(Lscala/actors/Futures$$anon$2;Ljava/lang/Object;)V;
NameAndType	"<init>":(Lscala/actors/Futures$$anon$2;Ljava/lang/Object;)V
Method	scala/actors/Futures$$anon$2$$anonfun$isDefinedAt$1."<init>":(Lscala/actors/Futures$$anon$2;Ljava/lang/Object;)V
Asciz	scala/collection/IterableLike;
class	scala/collection/IterableLike
Asciz	exists;
Asciz	(Lscala/Function1;)Z;
NameAndType	exists:(Lscala/Function1;)Z
InterfaceMethod	scala/collection/IterableLike.exists:(Lscala/Function1;)Z
Asciz	msg$1;
Asciz	Ljava/lang/Object;;
Asciz	apply;
Asciz	(Ljava/lang/Object;)V;
Asciz	scala/actors/Futures$$anon$2$$anonfun$7;
class	scala/actors/Futures$$anon$2$$anonfun$7
Method	scala/actors/Futures$$anon$2$$anonfun$7."<init>":(Lscala/actors/Futures$$anon$2;Ljava/lang/Object;)V
Asciz	find;
Asciz	(Lscala/Function1;)Lscala/Option;;
NameAndType	find:(Lscala/Function1;)Lscala/Option;
InterfaceMethod	scala/collection/IterableLike.find:(Lscala/Function1;)Lscala/Option;
Asciz	scala/Option;
class	scala/Option
Asciz	get;
Asciz	()Ljava/lang/Object;;
NameAndType	get:()Ljava/lang/Object;
Method	scala/Option.get:()Ljava/lang/Object;
Asciz	scala/PartialFunction;
class	scala/PartialFunction
Asciz	scala/Function1;
class	scala/Function1
Asciz	(Ljava/lang/Object;)Ljava/lang/Object;;
NameAndType	apply:(Ljava/lang/Object;)Ljava/lang/Object;
InterfaceMethod	scala/Function1.apply:(Ljava/lang/Object;)Ljava/lang/Object;
Asciz	scala/Tuple2;
class	scala/Tuple2
Asciz	scala/Predef$Pair$;
class	scala/Predef$Pair$
Asciz	Lscala/Predef$Pair$;;
NameAndType	MODULE$:Lscala/Predef$Pair$;
Field	scala/Predef$Pair$.MODULE$:Lscala/Predef$Pair$;
Asciz	unapply;
Asciz	(Lscala/Tuple2;)Lscala/Option;;
NameAndType	unapply:(Lscala/Tuple2;)Lscala/Option;
Method	scala/Predef$Pair$.unapply:(Lscala/Tuple2;)Lscala/Option;
Asciz	isEmpty;
Asciz	()Z;
NameAndType	isEmpty:()Z
Method	scala/Option.isEmpty:()Z
Asciz	scala/MatchError;
class	scala/MatchError
NameAndType	"<init>":(Ljava/lang/Object;)V
Method	scala/MatchError."<init>":(Ljava/lang/Object;)V
Asciz	_1;
NameAndType	_1:()Ljava/lang/Object;
Method	scala/Tuple2._1:()Ljava/lang/Object;
Asciz	_2;
NameAndType	_2:()Ljava/lang/Object;
Method	scala/Tuple2._2:()Ljava/lang/Object;
Asciz	(Ljava/lang/Object;Ljava/lang/Object;)V;
NameAndType	"<init>":(Ljava/lang/Object;Ljava/lang/Object;)V
Method	scala/Tuple2."<init>":(Ljava/lang/Object;Ljava/lang/Object;)V
Asciz	_1$mcI$sp;
Asciz	()I;
NameAndType	_1$mcI$sp:()I
Method	scala/Tuple2._1$mcI$sp:()I
NameAndType	resultsMap$1:Lscala/runtime/ObjectRef;
Field	scala/actors/Futures$$anon$2.resultsMap$1:Lscala/runtime/ObjectRef;
Asciz	scala/runtime/ObjectRef;
class	scala/runtime/ObjectRef
Asciz	elem;
NameAndType	elem:Ljava/lang/Object;
Field	scala/runtime/ObjectRef.elem:Ljava/lang/Object;
Asciz	scala/collection/mutable/Map;
class	scala/collection/mutable/Map
Asciz	scala/runtime/BoxesRunTime;
class	scala/runtime/BoxesRunTime
Asciz	boxToInteger;
Asciz	(I)Ljava/lang/Integer;;
NameAndType	boxToInteger:(I)Ljava/lang/Integer;
Method	scala/runtime/BoxesRunTime.boxToInteger:(I)Ljava/lang/Integer;
Asciz	scala/Some;
class	scala/Some
Method	scala/Some."<init>":(Ljava/lang/Object;)V
Asciz	scala/collection/mutable/MapLike;
class	scala/collection/mutable/MapLike
Asciz	update;
NameAndType	update:(Ljava/lang/Object;Ljava/lang/Object;)V
InterfaceMethod	scala/collection/mutable/MapLike.update:(Ljava/lang/Object;Ljava/lang/Object;)V
Asciz	scala/actors/Futures$$anon$2$$anonfun$8;
class	scala/actors/Futures$$anon$2$$anonfun$8
Asciz	(Lscala/actors/Futures$$anon$2;Lscala/PartialFunction;)V;
NameAndType	"<init>":(Lscala/actors/Futures$$anon$2;Lscala/PartialFunction;)V
Method	scala/actors/Futures$$anon$2$$anonfun$8."<init>":(Lscala/actors/Futures$$anon$2;Lscala/PartialFunction;)V
Asciz	scala/collection/TraversableLike;
class	scala/collection/TraversableLike
Asciz	filter;
Asciz	(Lscala/Function1;)Ljava/lang/Object;;
NameAndType	filter:(Lscala/Function1;)Ljava/lang/Object;
InterfaceMethod	scala/collection/TraversableLike.filter:(Lscala/Function1;)Ljava/lang/Object;
Asciz	scala/collection/Seq;
class	scala/collection/Seq
Asciz	scala/collection/SeqLike;
class	scala/collection/SeqLike
Asciz	length;
NameAndType	length:()I
InterfaceMethod	scala/collection/SeqLike.length:()I
Asciz	(Lscala/runtime/ObjectRef;Lscala/collection/Seq;)V;
NameAndType	"<init>":(Lscala/runtime/ObjectRef;Lscala/collection/Seq;)V
Method	scala/actors/Futures$$anon$2."<init>":(Lscala/runtime/ObjectRef;Lscala/collection/Seq;)V
Asciz	scala/actors/Actor$;
class	scala/actors/Actor$
Asciz	Lscala/actors/Actor$;;
NameAndType	MODULE$:Lscala/actors/Actor$;
Field	scala/actors/Actor$.MODULE$:Lscala/actors/Actor$;
Asciz	scala/actors/Scheduler$;
class	scala/actors/Scheduler$
Asciz	Lscala/actors/Scheduler$;;
NameAndType	MODULE$:Lscala/actors/Scheduler$;
Field	scala/actors/Scheduler$.MODULE$:Lscala/actors/Scheduler$;
Asciz	rawSelf;
Asciz	(Lscala/actors/IScheduler;)Lscala/actors/ReplyReactor;;
NameAndType	rawSelf:(Lscala/actors/IScheduler;)Lscala/actors/ReplyReactor;
Method	scala/actors/Actor$.rawSelf:(Lscala/actors/IScheduler;)Lscala/actors/ReplyReactor;
Asciz	scala/actors/Actor;
class	scala/actors/Actor
Asciz	receive;
Asciz	(Lscala/PartialFunction;)Ljava/lang/Object;;
NameAndType	receive:(Lscala/PartialFunction;)Ljava/lang/Object;
InterfaceMethod	scala/actors/Actor.receive:(Lscala/PartialFunction;)Ljava/lang/Object;
Asciz	msg$2;
Asciz	pfOpt;
Asciz	Lscala/Option;;
Asciz	temp35;
Asciz	Lscala/Tuple2;;
Asciz	temp36;
Asciz	temp37;
Asciz	idx;
Asciz	subres;
Asciz	pf$1;
Asciz	partFunsRest;
Asciz	reaction0;
NameAndType	andThen:(Lscala/Function1;)Lscala/PartialFunction;
InterfaceMethod	scala/PartialFunction.andThen:(Lscala/Function1;)Lscala/PartialFunction;
NameAndType	apply:(Ljava/lang/Object;)V
Method	scala/actors/Futures$$anon$2.apply:(Ljava/lang/Object;)V
Asciz	scala/runtime/BoxedUnit;
class	scala/runtime/BoxedUnit
Asciz	UNIT;
Asciz	Lscala/runtime/BoxedUnit;;
NameAndType	UNIT:Lscala/runtime/BoxedUnit;
Field	scala/runtime/BoxedUnit.UNIT:Lscala/runtime/BoxedUnit;
Asciz	()V;
NameAndType	"<init>":()V
Method	java/lang/Object."<init>":()V
Asciz	$init$;
Asciz	(Lscala/Function1;)V;
NameAndType	$init$:(Lscala/Function1;)V
Method	scala/Function1$class.$init$:(Lscala/Function1;)V
Asciz	(Lscala/PartialFunction;)V;
NameAndType	$init$:(Lscala/PartialFunction;)V
Method	scala/PartialFunction$class.$init$:(Lscala/PartialFunction;)V
Asciz	Scala;
Asciz	Ljava/lang/Object;Lscala/PartialFunction<Ljava/lang/Object;Ljava/lang/Object;>;;
Asciz	Signature;
Asciz	InnerClasses;
Asciz	scala/actors/Futures;
class	scala/actors/Futures
Asciz	$anon$2;
Asciz	$anonfun$8;
Asciz	$anonfun$7;
Asciz	$anonfun$isDefinedAt$1;

{
public final scala.runtime.ObjectRef resultsMap$1;
  Signature: Lscala/runtime/ObjectRef;

public final scala.collection.Seq partFuns$1;
  Signature: Lscala/collection/Seq;

public scala.PartialFunction orElse(scala.PartialFunction);
  Signature: (Lscala/PartialFunction;)Lscala/PartialFunction;
  Code:
   Stack=2, Locals=2, Args_size=2
	aload_0
	aload_1
	invokestatic	Method scala/PartialFunction$class.orElse:(Lscala/PartialFunction;Lscala/PartialFunction;)Lscala/PartialFunction;
	areturn
  Labels:
  LocalVariableTable: 
   Start  Length  Slot  Name   Signature
   0      6      0    this       Lscala/actors/Futures$$anon$2;
   0      6      1    that       Lscala/PartialFunction;


public scala.PartialFunction andThen(scala.Function1);
  Signature: (Lscala/Function1;)Lscala/PartialFunction;
  Code:
   Stack=2, Locals=2, Args_size=2
	aload_0
	aload_1
	invokestatic	Method scala/PartialFunction$class.andThen:(Lscala/PartialFunction;Lscala/Function1;)Lscala/PartialFunction;
	areturn
  Labels:
  LocalVariableTable: 
   Start  Length  Slot  Name   Signature
   0      6      0    this       Lscala/actors/Futures$$anon$2;
   0      6      1    k       Lscala/Function1;


public scala.Function1 lift();
  Signature: ()Lscala/Function1;
  Code:
   Stack=1, Locals=1, Args_size=1
	aload_0
	invokestatic	Method scala/PartialFunction$class.lift:(Lscala/PartialFunction;)Lscala/Function1;
	areturn
  Labels:

public void apply$mcVI$sp(int);
  Signature: (I)V
  Code:
   Stack=2, Locals=2, Args_size=2
	aload_0
	iload_1
	invokestatic	Method scala/Function1$class.apply$mcVI$sp:(Lscala/Function1;I)V
	return
  Labels:
  LocalVariableTable: 
   Start  Length  Slot  Name   Signature
   0      6      0    this       Lscala/actors/Futures$$anon$2;
   0      6      1    v1       I


public boolean apply$mcZI$sp(int);
  Signature: (I)Z
  Code:
   Stack=2, Locals=2, Args_size=2
	aload_0
	iload_1
	invokestatic	Method scala/Function1$class.apply$mcZI$sp:(Lscala/Function1;I)Z
	ireturn
  Labels:
  LocalVariableTable: 
   Start  Length  Slot  Name   Signature
   0      6      0    this       Lscala/actors/Futures$$anon$2;
   0      6      1    v1       I


public int apply$mcII$sp(int);
  Signature: (I)I
  Code:
   Stack=2, Locals=2, Args_size=2
	aload_0
	iload_1
	invokestatic	Method scala/Function1$class.apply$mcII$sp:(Lscala/Function1;I)I
	ireturn
  Labels:
  LocalVariableTable: 
   Start  Length  Slot  Name   Signature
   0      6      0    this       Lscala/actors/Futures$$anon$2;
   0      6      1    v1       I


public long apply$mcLI$sp(int);
  Signature: (I)J
  Code:
   Stack=2, Locals=2, Args_size=2
	aload_0
	iload_1
	invokestatic	Method scala/Function1$class.apply$mcLI$sp:(Lscala/Function1;I)J
	lreturn
  Labels:
  LocalVariableTable: 
   Start  Length  Slot  Name   Signature
   0      6      0    this       Lscala/actors/Futures$$anon$2;
   0      6      1    v1       I


public double apply$mcDI$sp(int);
  Signature: (I)D
  Code:
   Stack=2, Locals=2, Args_size=2
	aload_0
	iload_1
	invokestatic	Method scala/Function1$class.apply$mcDI$sp:(Lscala/Function1;I)D
	dreturn
  Labels:
  LocalVariableTable: 
   Start  Length  Slot  Name   Signature
   0      6      0    this       Lscala/actors/Futures$$anon$2;
   0      6      1    v1       I


public void apply$mcVL$sp(long);
  Signature: (J)V
  Code:
   Stack=3, Locals=3, Args_size=2
	aload_0
	lload_1
	invokestatic	Method scala/Function1$class.apply$mcVL$sp:(Lscala/Function1;J)V
	return
  Labels:
  LocalVariableTable: 
   Start  Length  Slot  Name   Signature
   0      6      0    this       Lscala/actors/Futures$$anon$2;
   0      6      1    v1       J


public boolean apply$mcZL$sp(long);
  Signature: (J)Z
  Code:
   Stack=3, Locals=3, Args_size=2
	aload_0
	lload_1
	invokestatic	Method scala/Function1$class.apply$mcZL$sp:(Lscala/Function1;J)Z
	ireturn
  Labels:
  LocalVariableTable: 
   Start  Length  Slot  Name   Signature
   0      6      0    this       Lscala/actors/Futures$$anon$2;
   0      6      1    v1       J


public int apply$mcIL$sp(long);
  Signature: (J)I
  Code:
   Stack=3, Locals=3, Args_size=2
	aload_0
	lload_1
	invokestatic	Method scala/Function1$class.apply$mcIL$sp:(Lscala/Function1;J)I
	ireturn
  Labels:
  LocalVariableTable: 
   Start  Length  Slot  Name   Signature
   0      6      0    this       Lscala/actors/Futures$$anon$2;
   0      6      1    v1       J


public long apply$mcLL$sp(long);
  Signature: (J)J
  Code:
   Stack=3, Locals=3, Args_size=2
	aload_0
	lload_1
	invokestatic	Method scala/Function1$class.apply$mcLL$sp:(Lscala/Function1;J)J
	lreturn
  Labels:
  LocalVariableTable: 
   Start  Length  Slot  Name   Signature
   0      6      0    this       Lscala/actors/Futures$$anon$2;
   0      6      1    v1       J


public double apply$mcDL$sp(long);
  Signature: (J)D
  Code:
   Stack=3, Locals=3, Args_size=2
	aload_0
	lload_1
	invokestatic	Method scala/Function1$class.apply$mcDL$sp:(Lscala/Function1;J)D
	dreturn
  Labels:
  LocalVariableTable: 
   Start  Length  Slot  Name   Signature
   0      6      0    this       Lscala/actors/Futures$$anon$2;
   0      6      1    v1       J


public void apply$mcVD$sp(double);
  Signature: (D)V
  Code:
   Stack=3, Locals=3, Args_size=2
	aload_0
	dload_1
	invokestatic	Method scala/Function1$class.apply$mcVD$sp:(Lscala/Function1;D)V
	return
  Labels:
  LocalVariableTable: 
   Start  Length  Slot  Name   Signature
   0      6      0    this       Lscala/actors/Futures$$anon$2;
   0      6      1    v1       D


public boolean apply$mcZD$sp(double);
  Signature: (D)Z
  Code:
   Stack=3, Locals=3, Args_size=2
	aload_0
	dload_1
	invokestatic	Method scala/Function1$class.apply$mcZD$sp:(Lscala/Function1;D)Z
	ireturn
  Labels:
  LocalVariableTable: 
   Start  Length  Slot  Name   Signature
   0      6      0    this       Lscala/actors/Futures$$anon$2;
   0      6      1    v1       D


public int apply$mcID$sp(double);
  Signature: (D)I
  Code:
   Stack=3, Locals=3, Args_size=2
	aload_0
	dload_1
	invokestatic	Method scala/Function1$class.apply$mcID$sp:(Lscala/Function1;D)I
	ireturn
  Labels:
  LocalVariableTable: 
   Start  Length  Slot  Name   Signature
   0      6      0    this       Lscala/actors/Futures$$anon$2;
   0      6      1    v1       D


public long apply$mcLD$sp(double);
  Signature: (D)J
  Code:
   Stack=3, Locals=3, Args_size=2
	aload_0
	dload_1
	invokestatic	Method scala/Function1$class.apply$mcLD$sp:(Lscala/Function1;D)J
	lreturn
  Labels:
  LocalVariableTable: 
   Start  Length  Slot  Name   Signature
   0      6      0    this       Lscala/actors/Futures$$anon$2;
   0      6      1    v1       D


public double apply$mcDD$sp(double);
  Signature: (D)D
  Code:
   Stack=3, Locals=3, Args_size=2
	aload_0
	dload_1
	invokestatic	Method scala/Function1$class.apply$mcDD$sp:(Lscala/Function1;D)D
	dreturn
  Labels:
  LocalVariableTable: 
   Start  Length  Slot  Name   Signature
   0      6      0    this       Lscala/actors/Futures$$anon$2;
   0      6      1    v1       D


public java.lang.String toString();
  Signature: ()Ljava/lang/String;
  Code:
   Stack=1, Locals=1, Args_size=1
	aload_0
	invokestatic	Method scala/Function1$class.toString:(Lscala/Function1;)Ljava/lang/String;
	areturn
  Labels:

public scala.Function1 compose(scala.Function1);
  Signature: (Lscala/Function1;)Lscala/Function1;
  Code:
   Stack=2, Locals=2, Args_size=2
	aload_0
	aload_1
	invokestatic	Method scala/Function1$class.compose:(Lscala/Function1;Lscala/Function1;)Lscala/Function1;
	areturn
  Labels:
  LocalVariableTable: 
   Start  Length  Slot  Name   Signature
   0      6      0    this       Lscala/actors/Futures$$anon$2;
   0      6      1    g       Lscala/Function1;


public scala.Function1 compose$mcVI$sp(scala.Function1);
  Signature: (Lscala/Function1;)Lscala/Function1;
  Code:
   Stack=2, Locals=2, Args_size=2
	aload_0
	aload_1
	invokestatic	Method scala/Function1$class.compose$mcVI$sp:(Lscala/Function1;Lscala/Function1;)Lscala/Function1;
	areturn
  Labels:
  LocalVariableTable: 
   Start  Length  Slot  Name   Signature
   0      6      0    this       Lscala/actors/Futures$$anon$2;
   0      6      1    g       Lscala/Function1;


public scala.Function1 compose$mcZI$sp(scala.Function1);
  Signature: (Lscala/Function1;)Lscala/Function1;
  Code:
   Stack=2, Locals=2, Args_size=2
	aload_0
	aload_1
	invokestatic	Method scala/Function1$class.compose$mcZI$sp:(Lscala/Function1;Lscala/Function1;)Lscala/Function1;
	areturn
  Labels:
  LocalVariableTable: 
   Start  Length  Slot  Name   Signature
   0      6      0    this       Lscala/actors/Futures$$anon$2;
   0      6      1    g       Lscala/Function1;


public scala.Function1 compose$mcII$sp(scala.Function1);
  Signature: (Lscala/Function1;)Lscala/Function1;
  Code:
   Stack=2, Locals=2, Args_size=2
	aload_0
	aload_1
	invokestatic	Method scala/Function1$class.compose$mcII$sp:(Lscala/Function1;Lscala/Function1;)Lscala/Function1;
	areturn
  Labels:
  LocalVariableTable: 
   Start  Length  Slot  Name   Signature
   0      6      0    this       Lscala/actors/Futures$$anon$2;
   0      6      1    g       Lscala/Function1;


public scala.Function1 compose$mcLI$sp(scala.Function1);
  Signature: (Lscala/Function1;)Lscala/Function1;
  Code:
   Stack=2, Locals=2, Args_size=2
	aload_0
	aload_1
	invokestatic	Method scala/Function1$class.compose$mcLI$sp:(Lscala/Function1;Lscala/Function1;)Lscala/Function1;
	areturn
  Labels:
  LocalVariableTable: 
   Start  Length  Slot  Name   Signature
   0      6      0    this       Lscala/actors/Futures$$anon$2;
   0      6      1    g       Lscala/Function1;


public scala.Function1 compose$mcDI$sp(scala.Function1);
  Signature: (Lscala/Function1;)Lscala/Function1;
  Code:
   Stack=2, Locals=2, Args_size=2
	aload_0
	aload_1
	invokestatic	Method scala/Function1$class.compose$mcDI$sp:(Lscala/Function1;Lscala/Function1;)Lscala/Function1;
	areturn
  Labels:
  LocalVariableTable: 
   Start  Length  Slot  Name   Signature
   0      6      0    this       Lscala/actors/Futures$$anon$2;
   0      6      1    g       Lscala/Function1;


public scala.Function1 compose$mcVL$sp(scala.Function1);
  Signature: (Lscala/Function1;)Lscala/Function1;
  Code:
   Stack=2, Locals=2, Args_size=2
	aload_0
	aload_1
	invokestatic	Method scala/Function1$class.compose$mcVL$sp:(Lscala/Function1;Lscala/Function1;)Lscala/Function1;
	areturn
  Labels:
  LocalVariableTable: 
   Start  Length  Slot  Name   Signature
   0      6      0    this       Lscala/actors/Futures$$anon$2;
   0      6      1    g       Lscala/Function1;


public scala.Function1 compose$mcZL$sp(scala.Function1);
  Signature: (Lscala/Function1;)Lscala/Function1;
  Code:
   Stack=2, Locals=2, Args_size=2
	aload_0
	aload_1
	invokestatic	Method scala/Function1$class.compose$mcZL$sp:(Lscala/Function1;Lscala/Function1;)Lscala/Function1;
	areturn
  Labels:
  LocalVariableTable: 
   Start  Length  Slot  Name   Signature
   0      6      0    this       Lscala/actors/Futures$$anon$2;
   0      6      1    g       Lscala/Function1;


public scala.Function1 compose$mcIL$sp(scala.Function1);
  Signature: (Lscala/Function1;)Lscala/Function1;
  Code:
   Stack=2, Locals=2, Args_size=2
	aload_0
	aload_1
	invokestatic	Method scala/Function1$class.compose$mcIL$sp:(Lscala/Function1;Lscala/Function1;)Lscala/Function1;
	areturn
  Labels:
  LocalVariableTable: 
   Start  Length  Slot  Name   Signature
   0      6      0    this       Lscala/actors/Futures$$anon$2;
   0      6      1    g       Lscala/Function1;


public scala.Function1 compose$mcLL$sp(scala.Function1);
  Signature: (Lscala/Function1;)Lscala/Function1;
  Code:
   Stack=2, Locals=2, Args_size=2
	aload_0
	aload_1
	invokestatic	Method scala/Function1$class.compose$mcLL$sp:(Lscala/Function1;Lscala/Function1;)Lscala/Function1;
	areturn
  Labels:
  LocalVariableTable: 
   Start  Length  Slot  Name   Signature
   0      6      0    this       Lscala/actors/Futures$$anon$2;
   0      6      1    g       Lscala/Function1;


public scala.Function1 compose$mcDL$sp(scala.Function1);
  Signature: (Lscala/Function1;)Lscala/Function1;
  Code:
   Stack=2, Locals=2, Args_size=2
	aload_0
	aload_1
	invokestatic	Method scala/Function1$class.compose$mcDL$sp:(Lscala/Function1;Lscala/Function1;)Lscala/Function1;
	areturn
  Labels:
  LocalVariableTable: 
   Start  Length  Slot  Name   Signature
   0      6      0    this       Lscala/actors/Futures$$anon$2;
   0      6      1    g       Lscala/Function1;


public scala.Function1 compose$mcVD$sp(scala.Function1);
  Signature: (Lscala/Function1;)Lscala/Function1;
  Code:
   Stack=2, Locals=2, Args_size=2
	aload_0
	aload_1
	invokestatic	Method scala/Function1$class.compose$mcVD$sp:(Lscala/Function1;Lscala/Function1;)Lscala/Function1;
	areturn
  Labels:
  LocalVariableTable: 
   Start  Length  Slot  Name   Signature
   0      6      0    this       Lscala/actors/Futures$$anon$2;
   0      6      1    g       Lscala/Function1;


public scala.Function1 compose$mcZD$sp(scala.Function1);
  Signature: (Lscala/Function1;)Lscala/Function1;
  Code:
   Stack=2, Locals=2, Args_size=2
	aload_0
	aload_1
	invokestatic	Method scala/Function1$class.compose$mcZD$sp:(Lscala/Function1;Lscala/Function1;)Lscala/Function1;
	areturn
  Labels:
  LocalVariableTable: 
   Start  Length  Slot  Name   Signature
   0      6      0    this       Lscala/actors/Futures$$anon$2;
   0      6      1    g       Lscala/Function1;


public scala.Function1 compose$mcID$sp(scala.Function1);
  Signature: (Lscala/Function1;)Lscala/Function1;
  Code:
   Stack=2, Locals=2, Args_size=2
	aload_0
	aload_1
	invokestatic	Method scala/Function1$class.compose$mcID$sp:(Lscala/Function1;Lscala/Function1;)Lscala/Function1;
	areturn
  Labels:
  LocalVariableTable: 
   Start  Length  Slot  Name   Signature
   0      6      0    this       Lscala/actors/Futures$$anon$2;
   0      6      1    g       Lscala/Function1;


public scala.Function1 compose$mcLD$sp(scala.Function1);
  Signature: (Lscala/Function1;)Lscala/Function1;
  Code:
   Stack=2, Locals=2, Args_size=2
	aload_0
	aload_1
	invokestatic	Method scala/Function1$class.compose$mcLD$sp:(Lscala/Function1;Lscala/Function1;)Lscala/Function1;
	areturn
  Labels:
  LocalVariableTable: 
   Start  Length  Slot  Name   Signature
   0      6      0    this       Lscala/actors/Futures$$anon$2;
   0      6      1    g       Lscala/Function1;


public scala.Function1 compose$mcDD$sp(scala.Function1);
  Signature: (Lscala/Function1;)Lscala/Function1;
  Code:
   Stack=2, Locals=2, Args_size=2
	aload_0
	aload_1
	invokestatic	Method scala/Function1$class.compose$mcDD$sp:(Lscala/Function1;Lscala/Function1;)Lscala/Function1;
	areturn
  Labels:
  LocalVariableTable: 
   Start  Length  Slot  Name   Signature
   0      6      0    this       Lscala/actors/Futures$$anon$2;
   0      6      1    g       Lscala/Function1;


public scala.Function1 andThen$mcVI$sp(scala.Function1);
  Signature: (Lscala/Function1;)Lscala/Function1;
  Code:
   Stack=2, Locals=2, Args_size=2
	aload_0
	aload_1
	invokestatic	Method scala/Function1$class.andThen$mcVI$sp:(Lscala/Function1;Lscala/Function1;)Lscala/Function1;
	areturn
  Labels:
  LocalVariableTable: 
   Start  Length  Slot  Name   Signature
   0      6      0    this       Lscala/actors/Futures$$anon$2;
   0      6      1    g       Lscala/Function1;


public scala.Function1 andThen$mcZI$sp(scala.Function1);
  Signature: (Lscala/Function1;)Lscala/Function1;
  Code:
   Stack=2, Locals=2, Args_size=2
	aload_0
	aload_1
	invokestatic	Method scala/Function1$class.andThen$mcZI$sp:(Lscala/Function1;Lscala/Function1;)Lscala/Function1;
	areturn
  Labels:
  LocalVariableTable: 
   Start  Length  Slot  Name   Signature
   0      6      0    this       Lscala/actors/Futures$$anon$2;
   0      6      1    g       Lscala/Function1;


public scala.Function1 andThen$mcII$sp(scala.Function1);
  Signature: (Lscala/Function1;)Lscala/Function1;
  Code:
   Stack=2, Locals=2, Args_size=2
	aload_0
	aload_1
	invokestatic	Method scala/Function1$class.andThen$mcII$sp:(Lscala/Function1;Lscala/Function1;)Lscala/Function1;
	areturn
  Labels:
  LocalVariableTable: 
   Start  Length  Slot  Name   Signature
   0      6      0    this       Lscala/actors/Futures$$anon$2;
   0      6      1    g       Lscala/Function1;


public scala.Function1 andThen$mcLI$sp(scala.Function1);
  Signature: (Lscala/Function1;)Lscala/Function1;
  Code:
   Stack=2, Locals=2, Args_size=2
	aload_0
	aload_1
	invokestatic	Method scala/Function1$class.andThen$mcLI$sp:(Lscala/Function1;Lscala/Function1;)Lscala/Function1;
	areturn
  Labels:
  LocalVariableTable: 
   Start  Length  Slot  Name   Signature
   0      6      0    this       Lscala/actors/Futures$$anon$2;
   0      6      1    g       Lscala/Function1;


public scala.Function1 andThen$mcDI$sp(scala.Function1);
  Signature: (Lscala/Function1;)Lscala/Function1;
  Code:
   Stack=2, Locals=2, Args_size=2
	aload_0
	aload_1
	invokestatic	Method scala/Function1$class.andThen$mcDI$sp:(Lscala/Function1;Lscala/Function1;)Lscala/Function1;
	areturn
  Labels:
  LocalVariableTable: 
   Start  Length  Slot  Name   Signature
   0      6      0    this       Lscala/actors/Futures$$anon$2;
   0      6      1    g       Lscala/Function1;


public scala.Function1 andThen$mcVL$sp(scala.Function1);
  Signature: (Lscala/Function1;)Lscala/Function1;
  Code:
   Stack=2, Locals=2, Args_size=2
	aload_0
	aload_1
	invokestatic	Method scala/Function1$class.andThen$mcVL$sp:(Lscala/Function1;Lscala/Function1;)Lscala/Function1;
	areturn
  Labels:
  LocalVariableTable: 
   Start  Length  Slot  Name   Signature
   0      6      0    this       Lscala/actors/Futures$$anon$2;
   0      6      1    g       Lscala/Function1;


public scala.Function1 andThen$mcZL$sp(scala.Function1);
  Signature: (Lscala/Function1;)Lscala/Function1;
  Code:
   Stack=2, Locals=2, Args_size=2
	aload_0
	aload_1
	invokestatic	Method scala/Function1$class.andThen$mcZL$sp:(Lscala/Function1;Lscala/Function1;)Lscala/Function1;
	areturn
  Labels:
  LocalVariableTable: 
   Start  Length  Slot  Name   Signature
   0      6      0    this       Lscala/actors/Futures$$anon$2;
   0      6      1    g       Lscala/Function1;


public scala.Function1 andThen$mcIL$sp(scala.Function1);
  Signature: (Lscala/Function1;)Lscala/Function1;
  Code:
   Stack=2, Locals=2, Args_size=2
	aload_0
	aload_1
	invokestatic	Method scala/Function1$class.andThen$mcIL$sp:(Lscala/Function1;Lscala/Function1;)Lscala/Function1;
	areturn
  Labels:
  LocalVariableTable: 
   Start  Length  Slot  Name   Signature
   0      6      0    this       Lscala/actors/Futures$$anon$2;
   0      6      1    g       Lscala/Function1;


public scala.Function1 andThen$mcLL$sp(scala.Function1);
  Signature: (Lscala/Function1;)Lscala/Function1;
  Code:
   Stack=2, Locals=2, Args_size=2
	aload_0
	aload_1
	invokestatic	Method scala/Function1$class.andThen$mcLL$sp:(Lscala/Function1;Lscala/Function1;)Lscala/Function1;
	areturn
  Labels:
  LocalVariableTable: 
   Start  Length  Slot  Name   Signature
   0      6      0    this       Lscala/actors/Futures$$anon$2;
   0      6      1    g       Lscala/Function1;


public scala.Function1 andThen$mcDL$sp(scala.Function1);
  Signature: (Lscala/Function1;)Lscala/Function1;
  Code:
   Stack=2, Locals=2, Args_size=2
	aload_0
	aload_1
	invokestatic	Method scala/Function1$class.andThen$mcDL$sp:(Lscala/Function1;Lscala/Function1;)Lscala/Function1;
	areturn
  Labels:
  LocalVariableTable: 
   Start  Length  Slot  Name   Signature
   0      6      0    this       Lscala/actors/Futures$$anon$2;
   0      6      1    g       Lscala/Function1;


public scala.Function1 andThen$mcVD$sp(scala.Function1);
  Signature: (Lscala/Function1;)Lscala/Function1;
  Code:
   Stack=2, Locals=2, Args_size=2
	aload_0
	aload_1
	invokestatic	Method scala/Function1$class.andThen$mcVD$sp:(Lscala/Function1;Lscala/Function1;)Lscala/Function1;
	areturn
  Labels:
  LocalVariableTable: 
   Start  Length  Slot  Name   Signature
   0      6      0    this       Lscala/actors/Futures$$anon$2;
   0      6      1    g       Lscala/Function1;


public scala.Function1 andThen$mcZD$sp(scala.Function1);
  Signature: (Lscala/Function1;)Lscala/Function1;
  Code:
   Stack=2, Locals=2, Args_size=2
	aload_0
	aload_1
	invokestatic	Method scala/Function1$class.andThen$mcZD$sp:(Lscala/Function1;Lscala/Function1;)Lscala/Function1;
	areturn
  Labels:
  LocalVariableTable: 
   Start  Length  Slot  Name   Signature
   0      6      0    this       Lscala/actors/Futures$$anon$2;
   0      6      1    g       Lscala/Function1;


public scala.Function1 andThen$mcID$sp(scala.Function1);
  Signature: (Lscala/Function1;)Lscala/Function1;
  Code:
   Stack=2, Locals=2, Args_size=2
	aload_0
	aload_1
	invokestatic	Method scala/Function1$class.andThen$mcID$sp:(Lscala/Function1;Lscala/Function1;)Lscala/Function1;
	areturn
  Labels:
  LocalVariableTable: 
   Start  Length  Slot  Name   Signature
   0      6      0    this       Lscala/actors/Futures$$anon$2;
   0      6      1    g       Lscala/Function1;


public scala.Function1 andThen$mcLD$sp(scala.Function1);
  Signature: (Lscala/Function1;)Lscala/Function1;
  Code:
   Stack=2, Locals=2, Args_size=2
	aload_0
	aload_1
	invokestatic	Method scala/Function1$class.andThen$mcLD$sp:(Lscala/Function1;Lscala/Function1;)Lscala/Function1;
	areturn
  Labels:
  LocalVariableTable: 
   Start  Length  Slot  Name   Signature
   0      6      0    this       Lscala/actors/Futures$$anon$2;
   0      6      1    g       Lscala/Function1;


public scala.Function1 andThen$mcDD$sp(scala.Function1);
  Signature: (Lscala/Function1;)Lscala/Function1;
  Code:
   Stack=2, Locals=2, Args_size=2
	aload_0
	aload_1
	invokestatic	Method scala/Function1$class.andThen$mcDD$sp:(Lscala/Function1;Lscala/Function1;)Lscala/Function1;
	areturn
  Labels:
  LocalVariableTable: 
   Start  Length  Slot  Name   Signature
   0      6      0    this       Lscala/actors/Futures$$anon$2;
   0      6      1    g       Lscala/Function1;


public boolean isDefinedAt(java.lang.Object);
  Signature: (Ljava/lang/Object;)Z
  Code:
   Stack=5, Locals=2, Args_size=2
	getstatic	Field scala/actors/TIMEOUT$.MODULE$:Lscala/actors/TIMEOUT$;
	dup
	ifnonnull	l1 // aload_1
	pop
	aload_1
	ifnull	l2 // iconst_1
	goto	l3 // aload_0
l1	aload_1
	invokevirtual	Method java/lang/Object.equals:(Ljava/lang/Object;)Z
	ifeq	l3 // aload_0
l2	iconst_1
	goto	l4 // ireturn
l3	aload_0
	getfield	Field partFuns$1:Lscala/collection/Seq;
	new	class scala/actors/Futures$$anon$2$$anonfun$isDefinedAt$1
	dup
	aload_0
	aload_1
	invokespecial	Method scala/actors/Futures$$anon$2$$anonfun$isDefinedAt$1."<init>":(Lscala/actors/Futures$$anon$2;Ljava/lang/Object;)V
	invokeinterface	InterfaceMethod scala/collection/IterableLike.exists:(Lscala/Function1;)Z
l4	ireturn
  Labels:
   	l1 = 15 // aload_1
   	l2 = 22 // iconst_1
   	l3 = 26 // aload_0
   	l4 = 44 // ireturn
  LocalVariableTable: 
   Start  Length  Slot  Name   Signature
   0      45      0    this       Lscala/actors/Futures$$anon$2;
   0      45      1    msg$1       Ljava/lang/Object;


public void apply(java.lang.Object);
  Signature: (Ljava/lang/Object;)V
  Code:
   Stack=5, Locals=15, Args_size=2
	getstatic	Field scala/actors/TIMEOUT$.MODULE$:Lscala/actors/TIMEOUT$;
	dup
	ifnonnull	l1 // aload_1
	pop
	aload_1
	ifnull	l2 // return
	goto	l3 // aload_0
l1	aload_1
	invokevirtual	Method java/lang/Object.equals:(Ljava/lang/Object;)Z
	ifne	l2 // return
l3	aload_0
	getfield	Field partFuns$1:Lscala/collection/Seq;
	new	class scala/actors/Futures$$anon$2$$anonfun$7
	dup
	aload_0
	aload_1
	invokespecial	Method scala/actors/Futures$$anon$2$$anonfun$7."<init>":(Lscala/actors/Futures$$anon$2;Ljava/lang/Object;)V
	invokeinterface	InterfaceMethod scala/collection/IterableLike.find:(Lscala/Function1;)Lscala/Option;
	astore_2
	aload_2
	invokevirtual	Method scala/Option.get:()Ljava/lang/Object;
	checkcast	class scala/PartialFunction
	astore	9
	aload	9
	aload_1
	invokeinterface	InterfaceMethod scala/Function1.apply:(Ljava/lang/Object;)Ljava/lang/Object;
	checkcast	class scala/Tuple2
	astore_3
	getstatic	Field scala/Predef$Pair$.MODULE$:Lscala/Predef$Pair$;
	aload_3
	invokevirtual	Method scala/Predef$Pair$.unapply:(Lscala/Tuple2;)Lscala/Option;
	astore	4
	aload	4
	invokevirtual	Method scala/Option.isEmpty:()Z
	ifeq	l4 // aload
	new	class scala/MatchError
	dup
	aload_3
	invokespecial	Method scala/MatchError."<init>":(Ljava/lang/Object;)V
	athrow
l4	aload	4
	invokevirtual	Method scala/Option.get:()Ljava/lang/Object;
	checkcast	class scala/Tuple2
	astore	5
	new	class scala/Tuple2
	dup
	aload	5
	invokevirtual	Method scala/Tuple2._1:()Ljava/lang/Object;
	aload	5
	invokevirtual	Method scala/Tuple2._2:()Ljava/lang/Object;
	invokespecial	Method scala/Tuple2."<init>":(Ljava/lang/Object;Ljava/lang/Object;)V
	astore	6
	aload	6
	invokevirtual	Method scala/Tuple2._1$mcI$sp:()I
	istore	7
	aload	6
	invokevirtual	Method scala/Tuple2._2:()Ljava/lang/Object;
	astore	8
	aload_0
	getfield	Field resultsMap$1:Lscala/runtime/ObjectRef;
	getfield	Field scala/runtime/ObjectRef.elem:Ljava/lang/Object;
	checkcast	class scala/collection/mutable/Map
	iload	7
	invokestatic	Method scala/runtime/BoxesRunTime.boxToInteger:(I)Ljava/lang/Integer;
	new	class scala/Some
	dup
	aload	8
	invokespecial	Method scala/Some."<init>":(Ljava/lang/Object;)V
	invokeinterface	InterfaceMethod scala/collection/mutable/MapLike.update:(Ljava/lang/Object;Ljava/lang/Object;)V
	aload_0
	getfield	Field partFuns$1:Lscala/collection/Seq;
	new	class scala/actors/Futures$$anon$2$$anonfun$8
	dup
	aload_0
	aload	9
	invokespecial	Method scala/actors/Futures$$anon$2$$anonfun$8."<init>":(Lscala/actors/Futures$$anon$2;Lscala/PartialFunction;)V
	invokeinterface	InterfaceMethod scala/collection/TraversableLike.filter:(Lscala/Function1;)Ljava/lang/Object;
	checkcast	class scala/collection/Seq
	astore	11
	aload	11
	invokeinterface	InterfaceMethod scala/collection/SeqLike.length:()I
	iconst_0
	if_icmple	l2 // return
	aload_0
	getfield	Field resultsMap$1:Lscala/runtime/ObjectRef;
	astore	10
	new	class scala/actors/Futures$$anon$2
	dup
	aload	10
	aload	11
	invokespecial	Method "<init>":(Lscala/runtime/ObjectRef;Lscala/collection/Seq;)V
	astore	14
	getstatic	Field scala/actors/Actor$.MODULE$:Lscala/actors/Actor$;
	astore	12
	getstatic	Field scala/actors/Scheduler$.MODULE$:Lscala/actors/Scheduler$;
	astore	13
	aload	12
	aload	13
	invokevirtual	Method scala/actors/Actor$.rawSelf:(Lscala/actors/IScheduler;)Lscala/actors/ReplyReactor;
	checkcast	class scala/actors/Actor
	aload	14
	invokeinterface	InterfaceMethod scala/actors/Actor.receive:(Lscala/PartialFunction;)Ljava/lang/Object;
	pop
l2	return
  Labels:
   	l1 = 15 // aload_1
   	l3 = 22 // aload_0
   	l4 = 88 // aload
   	l2 = 242 // return
  LocalVariableTable: 
   Start  Length  Slot  Name   Signature
   0      243      0    this       Lscala/actors/Futures$$anon$2;
   0      243      1    msg$2       Ljava/lang/Object;
   41      201      2    pfOpt       Lscala/Option;
   62      133      3    temp35       Lscala/Tuple2;
   71      124      4    temp36       Lscala/Option;
   98      17      5    temp37       Lscala/Tuple2;
   124      118      7    idx       I
   131      111      8    subres       Ljava/lang/Object;
   50      192      9    pf$1       Lscala/PartialFunction;
   184      58      11    partFunsRest       Lscala/collection/Seq;
   214      28      14    reaction0       Lscala/PartialFunction;


public scala.Function1 andThen(scala.Function1);
  Signature: (Lscala/Function1;)Lscala/Function1;
  Code:
   Stack=2, Locals=2, Args_size=2
	aload_0
	aload_1
	invokeinterface	InterfaceMethod scala/PartialFunction.andThen:(Lscala/Function1;)Lscala/PartialFunction;
	areturn
  Labels:
  LocalVariableTable: 
   Start  Length  Slot  Name   Signature
   0      8      0    this       Lscala/actors/Futures$$anon$2;
   0      8      1    g       Lscala/Function1;


public java.lang.Object apply(java.lang.Object);
  Signature: (Ljava/lang/Object;)Ljava/lang/Object;
  Code:
   Stack=2, Locals=2, Args_size=2
	aload_0
	aload_1
	invokevirtual	Method apply:(Ljava/lang/Object;)V
	getstatic	Field scala/runtime/BoxedUnit.UNIT:Lscala/runtime/BoxedUnit;
	areturn
  Labels:
  LocalVariableTable: 
   Start  Length  Slot  Name   Signature
   0      9      0    this       Lscala/actors/Futures$$anon$2;
   0      9      1    v1       Ljava/lang/Object;


public scala.actors.Futures$$anon$2(scala.runtime.ObjectRef, scala.collection.Seq);
  Signature: (Lscala/runtime/ObjectRef;Lscala/collection/Seq;)V
  Code:
   Stack=2, Locals=3, Args_size=3
	aload_0
	aload_1
	putfield	Field resultsMap$1:Lscala/runtime/ObjectRef;
	aload_0
	aload_2
	putfield	Field partFuns$1:Lscala/collection/Seq;
	aload_0
	invokespecial	Method java/lang/Object."<init>":()V
	aload_0
	invokestatic	Method scala/Function1$class.$init$:(Lscala/Function1;)V
	aload_0
	invokestatic	Method scala/PartialFunction$class.$init$:(Lscala/PartialFunction;)V
	return
  Labels:

}

