Compiled from "Future.scala"
public final class scala.actors.Futures$$anon$1 extends java.lang.Object implements scala.actors.DaemonActor
  SourceFile: "Future.scala"
  Scala: length = 0x
   
  InnerClass: 
   public final $anon$1=class scala/actors/Futures$$anon$1 of class scala/actors/Futures
   public final $anonfun$act$1=class scala/actors/Futures$$anon$1$$anonfun$act$1 of class scala/actors/Futures$$anon$1
  minor version: 0
  major version: 49
  Constant pool:
Asciz	SourceFile;
Asciz	Future.scala;
Asciz	scala$actors$Actor$$blocker$module;
Asciz	Lscala/actors/Actor$blocker$;;
Asciz	exiting;
Asciz	Z;
Asciz	kill;
Asciz	Lscala/Function0;;
Asciz	waitingFor;
Asciz	Lscala/Function1;;
Asciz	waitingForNone;
Asciz	continuation;
Asciz	Lscala/PartialFunction;;
Asciz	sendBuffer;
Asciz	Lscala/collection/mutable/Queue;;
Asciz	mailbox;
Asciz	Lscala/actors/MessageQueue;;
Asciz	senders;
Asciz	Lscala/collection/immutable/List;;
Asciz	shouldExit;
Asciz	exitReason;
Asciz	Ljava/lang/Object;;
Asciz	trapExit;
Asciz	links;
Asciz	scala$actors$Actor$$onTimeout;
Asciz	Lscala/Option;;
Asciz	scala$actors$Actor$$received;
Asciz	scala$actors$Actor$$isSuspended;
Asciz	body$1;
Asciz	<init>;
Asciz	(Lscala/Function0;)V;
Asciz	Code;
Asciz	LineNumberTable;
Asciz	scala/actors/Futures$$anon$1;
class	scala/actors/Futures$$anon$1
NameAndType	body$1:Lscala/Function0;
Field	scala/actors/Futures$$anon$1.body$1:Lscala/Function0;
Asciz	java/lang/Object;
class	java/lang/Object
Asciz	()V;
NameAndType	"<init>":()V
Method	java/lang/Object."<init>":()V
Asciz	scala/actors/Replyable$class;
class	scala/actors/Replyable$class
Asciz	$init$;
Asciz	(Lscala/actors/Replyable;)V;
NameAndType	$init$:(Lscala/actors/Replyable;)V
Method	scala/actors/Replyable$class.$init$:(Lscala/actors/Replyable;)V
Asciz	scala/actors/AbstractActor$class;
class	scala/actors/AbstractActor$class
Asciz	(Lscala/actors/AbstractActor;)V;
NameAndType	$init$:(Lscala/actors/AbstractActor;)V
Method	scala/actors/AbstractActor$class.$init$:(Lscala/actors/AbstractActor;)V
Asciz	scala/actors/Reactor$class;
class	scala/actors/Reactor$class
Asciz	(Lscala/actors/Reactor;)V;
NameAndType	$init$:(Lscala/actors/Reactor;)V
Method	scala/actors/Reactor$class.$init$:(Lscala/actors/Reactor;)V
Asciz	scala/actors/ReplyableReactor$class;
class	scala/actors/ReplyableReactor$class
Asciz	(Lscala/actors/ReplyReactor;)V;
NameAndType	$init$:(Lscala/actors/ReplyReactor;)V
Method	scala/actors/ReplyableReactor$class.$init$:(Lscala/actors/ReplyReactor;)V
Asciz	scala/actors/ReplyReactor$class;
class	scala/actors/ReplyReactor$class
Method	scala/actors/ReplyReactor$class.$init$:(Lscala/actors/ReplyReactor;)V
Asciz	scala/actors/ReplyableActor$class;
class	scala/actors/ReplyableActor$class
Asciz	(Lscala/actors/ReplyableActor;)V;
NameAndType	$init$:(Lscala/actors/ReplyableActor;)V
Method	scala/actors/ReplyableActor$class.$init$:(Lscala/actors/ReplyableActor;)V
Asciz	scala/actors/Actor$class;
class	scala/actors/Actor$class
Asciz	(Lscala/actors/Actor;)V;
NameAndType	$init$:(Lscala/actors/Actor;)V
Method	scala/actors/Actor$class.$init$:(Lscala/actors/Actor;)V
Asciz	scala/actors/DaemonActor$class;
class	scala/actors/DaemonActor$class
Asciz	(Lscala/actors/DaemonActor;)V;
NameAndType	$init$:(Lscala/actors/DaemonActor;)V
Method	scala/actors/DaemonActor$class.$init$:(Lscala/actors/DaemonActor;)V
Asciz	start;
Asciz	()Lscala/actors/Reactor;;
Asciz	scala/actors/Actor;
class	scala/actors/Actor
Asciz	()Lscala/actors/Actor;;
NameAndType	start:()Lscala/actors/Actor;
InterfaceMethod	scala/actors/Actor.start:()Lscala/actors/Actor;
Asciz	$bang$bang;
Asciz	(Ljava/lang/Object;Lscala/PartialFunction;)Lscala/Function0;;
Asciz	scala/actors/ReplyableActor;
class	scala/actors/ReplyableActor
Asciz	(Ljava/lang/Object;Lscala/PartialFunction;)Lscala/actors/Future;;
NameAndType	$bang$bang:(Ljava/lang/Object;Lscala/PartialFunction;)Lscala/actors/Future;
InterfaceMethod	scala/actors/ReplyableActor.$bang$bang:(Ljava/lang/Object;Lscala/PartialFunction;)Lscala/actors/Future;
Asciz	this;
Asciz	Lscala/actors/Futures$$anon$1;;
Asciz	msg;
Asciz	f;
Asciz	LocalVariableTable;
Asciz	(Ljava/lang/Object;)Lscala/Function0;;
Asciz	(Ljava/lang/Object;)Lscala/actors/Future;;
NameAndType	$bang$bang:(Ljava/lang/Object;)Lscala/actors/Future;
InterfaceMethod	scala/actors/ReplyableActor.$bang$bang:(Ljava/lang/Object;)Lscala/actors/Future;
Asciz	act;
Asciz	scala/actors/Actor$;
class	scala/actors/Actor$
Asciz	MODULE$;
Asciz	Lscala/actors/Actor$;;
NameAndType	MODULE$:Lscala/actors/Actor$;
Field	scala/actors/Actor$.MODULE$:Lscala/actors/Actor$;
Asciz	scala/actors/Futures$$anon$1$$anonfun$act$1;
class	scala/actors/Futures$$anon$1$$anonfun$act$1
Asciz	(Lscala/actors/Futures$$anon$1;)V;
NameAndType	"<init>":(Lscala/actors/Futures$$anon$1;)V
Method	scala/actors/Futures$$anon$1$$anonfun$act$1."<init>":(Lscala/actors/Futures$$anon$1;)V
Asciz	react;
Asciz	(Lscala/PartialFunction;)Lscala/runtime/Nothing$;;
NameAndType	react:(Lscala/PartialFunction;)Lscala/runtime/Nothing$;
Method	scala/actors/Actor$.react:(Lscala/PartialFunction;)Lscala/runtime/Nothing$;
Asciz	exiting_$eq;
Asciz	(Z)V;
NameAndType	exiting:Z
Field	scala/actors/Futures$$anon$1.exiting:Z
Asciz	()Z;
Asciz	terminated;
NameAndType	terminated:(Lscala/actors/Reactor;)V
Method	scala/actors/Reactor$class.terminated:(Lscala/actors/Reactor;)V
Asciz	seq;
Asciz	(Lscala/Function0;Lscala/Function0;)V;
Asciz	(Lscala/actors/Reactor;Lscala/Function0;Lscala/Function0;)V;
NameAndType	seq:(Lscala/actors/Reactor;Lscala/Function0;Lscala/Function0;)V
Method	scala/actors/Reactor$class.seq:(Lscala/actors/Reactor;Lscala/Function0;Lscala/Function0;)V
Asciz	first;
Asciz	next;
Asciz	drainSendBuffer;
Asciz	(Lscala/actors/MessageQueue;)V;
Asciz	(Lscala/actors/Reactor;Lscala/actors/MessageQueue;)V;
NameAndType	drainSendBuffer:(Lscala/actors/Reactor;Lscala/actors/MessageQueue;)V
Method	scala/actors/Reactor$class.drainSendBuffer:(Lscala/actors/Reactor;Lscala/actors/MessageQueue;)V
Asciz	mbox;
Asciz	receiver;
Asciz	(Lscala/actors/Reactor;)Lscala/actors/Actor;;
NameAndType	receiver:(Lscala/actors/Reactor;)Lscala/actors/Actor;
Method	scala/actors/Reactor$class.receiver:(Lscala/actors/Reactor;)Lscala/actors/Actor;
Asciz	send;
Asciz	(Ljava/lang/Object;Lscala/actors/OutputChannel;)V;
Asciz	(Lscala/actors/Reactor;Ljava/lang/Object;Lscala/actors/OutputChannel;)V;
NameAndType	send:(Lscala/actors/Reactor;Ljava/lang/Object;Lscala/actors/OutputChannel;)V
Method	scala/actors/Reactor$class.send:(Lscala/actors/Reactor;Ljava/lang/Object;Lscala/actors/OutputChannel;)V
Asciz	replyTo;
Asciz	Lscala/actors/OutputChannel;;
Asciz	mailboxSize;
Asciz	()I;
Asciz	(Lscala/actors/Reactor;)I;
NameAndType	mailboxSize:(Lscala/actors/Reactor;)I
Method	scala/actors/Reactor$class.mailboxSize:(Lscala/actors/Reactor;)I
Asciz	exceptionHandler;
Asciz	()Lscala/PartialFunction;;
Asciz	(Lscala/actors/Reactor;)Lscala/PartialFunction;;
NameAndType	exceptionHandler:(Lscala/actors/Reactor;)Lscala/PartialFunction;
Method	scala/actors/Reactor$class.exceptionHandler:(Lscala/actors/Reactor;)Lscala/PartialFunction;
Asciz	scala$actors$Reactor$_setter_$waitingForNone_$eq;
Asciz	(Lscala/Function1;)V;
NameAndType	waitingForNone:Lscala/Function1;
Field	scala/actors/Futures$$anon$1.waitingForNone:Lscala/Function1;
Asciz	scala$actors$Reactor$_setter_$sendBuffer_$eq;
Asciz	(Lscala/collection/mutable/Queue;)V;
NameAndType	sendBuffer:Lscala/collection/mutable/Queue;
Field	scala/actors/Futures$$anon$1.sendBuffer:Lscala/collection/mutable/Queue;
Asciz	scala$actors$Reactor$_setter_$mailbox_$eq;
NameAndType	mailbox:Lscala/actors/MessageQueue;
Field	scala/actors/Futures$$anon$1.mailbox:Lscala/actors/MessageQueue;
Asciz	kill_$eq;
NameAndType	kill:Lscala/Function0;
Field	scala/actors/Futures$$anon$1.kill:Lscala/Function0;
Asciz	()Lscala/Function0;;
Asciz	waitingFor_$eq;
NameAndType	waitingFor:Lscala/Function1;
Field	scala/actors/Futures$$anon$1.waitingFor:Lscala/Function1;
Asciz	()Lscala/Function1;;
Asciz	continuation_$eq;
Asciz	(Lscala/PartialFunction;)V;
NameAndType	continuation:Lscala/PartialFunction;
Field	scala/actors/Futures$$anon$1.continuation:Lscala/PartialFunction;
Asciz	()Lscala/collection/mutable/Queue;;
Asciz	()Lscala/actors/MessageQueue;;
Asciz	searchMailbox;
Asciz	(Lscala/actors/MessageQueue;Lscala/Function1;Z)V;
Asciz	(Lscala/actors/ReplyReactor;Lscala/actors/MessageQueue;Lscala/Function1;Z)V;
NameAndType	searchMailbox:(Lscala/actors/ReplyReactor;Lscala/actors/MessageQueue;Lscala/Function1;Z)V
Method	scala/actors/ReplyReactor$class.searchMailbox:(Lscala/actors/ReplyReactor;Lscala/actors/MessageQueue;Lscala/Function1;Z)V
Asciz	startMbox;
Asciz	handlesMessage;
Asciz	resumeOnSameThread;
Asciz	forward;
Asciz	(Ljava/lang/Object;)V;
Asciz	(Lscala/actors/ReplyReactor;Ljava/lang/Object;)V;
NameAndType	forward:(Lscala/actors/ReplyReactor;Ljava/lang/Object;)V
Method	scala/actors/ReplyReactor$class.forward:(Lscala/actors/ReplyReactor;Ljava/lang/Object;)V
Asciz	$bang;
NameAndType	$bang:(Lscala/actors/ReplyReactor;Ljava/lang/Object;)V
Method	scala/actors/ReplyReactor$class.$bang:(Lscala/actors/ReplyReactor;Ljava/lang/Object;)V
Asciz	reply;
NameAndType	reply:(Lscala/actors/ReplyReactor;Ljava/lang/Object;)V
Method	scala/actors/ReplyReactor$class.reply:(Lscala/actors/ReplyReactor;Ljava/lang/Object;)V
Asciz	sender;
Asciz	()Lscala/actors/OutputChannel;;
Asciz	(Lscala/actors/ReplyReactor;)Lscala/actors/OutputChannel;;
NameAndType	sender:(Lscala/actors/ReplyReactor;)Lscala/actors/OutputChannel;
Method	scala/actors/ReplyReactor$class.sender:(Lscala/actors/ReplyReactor;)Lscala/actors/OutputChannel;
Asciz	senders_$eq;
Asciz	(Lscala/collection/immutable/List;)V;
NameAndType	senders:Lscala/collection/immutable/List;
Field	scala/actors/Futures$$anon$1.senders:Lscala/collection/immutable/List;
Asciz	()Lscala/collection/immutable/List;;
Asciz	(Lscala/actors/ReplyableActor;Ljava/lang/Object;)Lscala/actors/Future;;
NameAndType	$bang$bang:(Lscala/actors/ReplyableActor;Ljava/lang/Object;)Lscala/actors/Future;
Method	scala/actors/ReplyableActor$class.$bang$bang:(Lscala/actors/ReplyableActor;Ljava/lang/Object;)Lscala/actors/Future;
Asciz	(Lscala/actors/ReplyableActor;Ljava/lang/Object;Lscala/PartialFunction;)Lscala/actors/Future;;
NameAndType	$bang$bang:(Lscala/actors/ReplyableActor;Ljava/lang/Object;Lscala/PartialFunction;)Lscala/actors/Future;
Method	scala/actors/ReplyableActor$class.$bang$bang:(Lscala/actors/ReplyableActor;Ljava/lang/Object;Lscala/PartialFunction;)Lscala/actors/Future;
Asciz	$bang$qmark;
Asciz	(JLjava/lang/Object;)Lscala/Option;;
Asciz	(Lscala/actors/ReplyableActor;JLjava/lang/Object;)Lscala/Option;;
NameAndType	$bang$qmark:(Lscala/actors/ReplyableActor;JLjava/lang/Object;)Lscala/Option;
Method	scala/actors/ReplyableActor$class.$bang$qmark:(Lscala/actors/ReplyableActor;JLjava/lang/Object;)Lscala/Option;
Asciz	msec;
Asciz	J;
Asciz	(Ljava/lang/Object;)Ljava/lang/Object;;
Asciz	(Lscala/actors/ReplyableActor;Ljava/lang/Object;)Ljava/lang/Object;;
NameAndType	$bang$qmark:(Lscala/actors/ReplyableActor;Ljava/lang/Object;)Ljava/lang/Object;
Method	scala/actors/ReplyableActor$class.$bang$qmark:(Lscala/actors/ReplyableActor;Ljava/lang/Object;)Ljava/lang/Object;
Asciz	onTerminate;
Asciz	(Lscala/actors/Actor;Lscala/Function0;)V;
NameAndType	onTerminate:(Lscala/actors/Actor;Lscala/Function0;)V
Method	scala/actors/Actor$class.onTerminate:(Lscala/actors/Actor;Lscala/Function0;)V
Asciz	exit;
Asciz	(Lscala/actors/AbstractActor;Ljava/lang/Object;)V;
Asciz	(Lscala/actors/Actor;Lscala/actors/AbstractActor;Ljava/lang/Object;)V;
NameAndType	exit:(Lscala/actors/Actor;Lscala/actors/AbstractActor;Ljava/lang/Object;)V
Method	scala/actors/Actor$class.exit:(Lscala/actors/Actor;Lscala/actors/AbstractActor;Ljava/lang/Object;)V
Asciz	from;
Asciz	Lscala/actors/AbstractActor;;
Asciz	reason;
Asciz	exitLinked;
Asciz	(Lscala/actors/Actor;Ljava/lang/Object;)V;
NameAndType	exitLinked:(Lscala/actors/Actor;Ljava/lang/Object;)V
Method	scala/actors/Actor$class.exitLinked:(Lscala/actors/Actor;Ljava/lang/Object;)V
NameAndType	exitLinked:(Lscala/actors/Actor;)V
Method	scala/actors/Actor$class.exitLinked:(Lscala/actors/Actor;)V
Asciz	()Lscala/runtime/Nothing$;;
Asciz	(Lscala/actors/Actor;)Lscala/runtime/Nothing$;;
NameAndType	exit:(Lscala/actors/Actor;)Lscala/runtime/Nothing$;
Method	scala/actors/Actor$class.exit:(Lscala/actors/Actor;)Lscala/runtime/Nothing$;
Asciz	(Ljava/lang/Object;)Lscala/runtime/Nothing$;;
Asciz	(Lscala/actors/Actor;Ljava/lang/Object;)Lscala/runtime/Nothing$;;
NameAndType	exit:(Lscala/actors/Actor;Ljava/lang/Object;)Lscala/runtime/Nothing$;
Method	scala/actors/Actor$class.exit:(Lscala/actors/Actor;Ljava/lang/Object;)Lscala/runtime/Nothing$;
Asciz	unlinkFrom;
Asciz	(Lscala/actors/Actor;Lscala/actors/AbstractActor;)V;
NameAndType	unlinkFrom:(Lscala/actors/Actor;Lscala/actors/AbstractActor;)V
Method	scala/actors/Actor$class.unlinkFrom:(Lscala/actors/Actor;Lscala/actors/AbstractActor;)V
Asciz	unlink;
NameAndType	unlink:(Lscala/actors/Actor;Lscala/actors/AbstractActor;)V
Method	scala/actors/Actor$class.unlink:(Lscala/actors/Actor;Lscala/actors/AbstractActor;)V
Asciz	linkTo;
NameAndType	linkTo:(Lscala/actors/Actor;Lscala/actors/AbstractActor;)V
Method	scala/actors/Actor$class.linkTo:(Lscala/actors/Actor;Lscala/actors/AbstractActor;)V
Asciz	to;
Asciz	link;
Asciz	(Lscala/Function0;)Lscala/actors/Actor;;
Asciz	(Lscala/actors/Actor;Lscala/Function0;)Lscala/actors/Actor;;
NameAndType	link:(Lscala/actors/Actor;Lscala/Function0;)Lscala/actors/Actor;
Method	scala/actors/Actor$class.link:(Lscala/actors/Actor;Lscala/Function0;)Lscala/actors/Actor;
Asciz	body;
Asciz	(Lscala/actors/AbstractActor;)Lscala/actors/AbstractActor;;
Asciz	(Lscala/actors/Actor;Lscala/actors/AbstractActor;)Lscala/actors/AbstractActor;;
NameAndType	link:(Lscala/actors/Actor;Lscala/actors/AbstractActor;)Lscala/actors/AbstractActor;
Method	scala/actors/Actor$class.link:(Lscala/actors/Actor;Lscala/actors/AbstractActor;)Lscala/actors/AbstractActor;
Asciz	(Lscala/actors/Actor;)Lscala/actors/Actor;;
NameAndType	start:(Lscala/actors/Actor;)Lscala/actors/Actor;
Method	scala/actors/Actor$class.start:(Lscala/actors/Actor;)Lscala/actors/Actor;
Asciz	scheduleActor;
Asciz	(Lscala/PartialFunction;Ljava/lang/Object;)V;
Asciz	(Lscala/actors/Actor;Lscala/PartialFunction;Ljava/lang/Object;)V;
NameAndType	scheduleActor:(Lscala/actors/Actor;Lscala/PartialFunction;Ljava/lang/Object;)V
Method	scala/actors/Actor$class.scheduleActor:(Lscala/actors/Actor;Lscala/PartialFunction;Ljava/lang/Object;)V
Asciz	$qmark;
Asciz	()Ljava/lang/Object;;
Asciz	(Lscala/actors/Actor;)Ljava/lang/Object;;
NameAndType	$qmark:(Lscala/actors/Actor;)Ljava/lang/Object;
Method	scala/actors/Actor$class.$qmark:(Lscala/actors/Actor;)Ljava/lang/Object;
Asciz	reactWithin;
Asciz	(JLscala/PartialFunction;)Lscala/runtime/Nothing$;;
Asciz	(Lscala/actors/Actor;JLscala/PartialFunction;)Lscala/runtime/Nothing$;;
NameAndType	reactWithin:(Lscala/actors/Actor;JLscala/PartialFunction;)Lscala/runtime/Nothing$;
Method	scala/actors/Actor$class.reactWithin:(Lscala/actors/Actor;JLscala/PartialFunction;)Lscala/runtime/Nothing$;
Asciz	(Lscala/actors/Actor;Lscala/PartialFunction;)Lscala/runtime/Nothing$;;
NameAndType	react:(Lscala/actors/Actor;Lscala/PartialFunction;)Lscala/runtime/Nothing$;
Method	scala/actors/Actor$class.react:(Lscala/actors/Actor;Lscala/PartialFunction;)Lscala/runtime/Nothing$;
Asciz	receiveWithin;
Asciz	(JLscala/PartialFunction;)Ljava/lang/Object;;
Asciz	(Lscala/actors/Actor;JLscala/PartialFunction;)Ljava/lang/Object;;
NameAndType	receiveWithin:(Lscala/actors/Actor;JLscala/PartialFunction;)Ljava/lang/Object;
Method	scala/actors/Actor$class.receiveWithin:(Lscala/actors/Actor;JLscala/PartialFunction;)Ljava/lang/Object;
Asciz	receive;
Asciz	(Lscala/PartialFunction;)Ljava/lang/Object;;
Asciz	(Lscala/actors/Actor;Lscala/PartialFunction;)Ljava/lang/Object;;
NameAndType	receive:(Lscala/actors/Actor;Lscala/PartialFunction;)Ljava/lang/Object;
Method	scala/actors/Actor$class.receive:(Lscala/actors/Actor;Lscala/PartialFunction;)Ljava/lang/Object;
Asciz	resumeReceiver;
Asciz	(Lscala/Tuple2;Z)V;
Asciz	(Lscala/actors/Actor;Lscala/Tuple2;Z)V;
NameAndType	resumeReceiver:(Lscala/actors/Actor;Lscala/Tuple2;Z)V
Method	scala/actors/Actor$class.resumeReceiver:(Lscala/actors/Actor;Lscala/Tuple2;Z)V
Asciz	item;
Asciz	Lscala/Tuple2;;
Asciz	onSameThread;
Asciz	makeReaction;
Asciz	(Lscala/Function0;)Ljava/lang/Runnable;;
Asciz	(Lscala/actors/Actor;Lscala/Function0;)Ljava/lang/Runnable;;
NameAndType	makeReaction:(Lscala/actors/Actor;Lscala/Function0;)Ljava/lang/Runnable;
Method	scala/actors/Actor$class.makeReaction:(Lscala/actors/Actor;Lscala/Function0;)Ljava/lang/Runnable;
Asciz	fun;
Asciz	startSearch;
Asciz	(Ljava/lang/Object;Lscala/actors/OutputChannel;Lscala/Function1;)Lscala/Function0;;
Asciz	(Lscala/actors/Actor;Ljava/lang/Object;Lscala/actors/OutputChannel;Lscala/Function1;)Lscala/Function0;;
NameAndType	startSearch:(Lscala/actors/Actor;Ljava/lang/Object;Lscala/actors/OutputChannel;Lscala/Function1;)Lscala/Function0;
Method	scala/actors/Actor$class.startSearch:(Lscala/actors/Actor;Ljava/lang/Object;Lscala/actors/OutputChannel;Lscala/Function1;)Lscala/Function0;
Asciz	handler;
Asciz	scala$actors$Actor$$super$resumeReceiver;
Asciz	(Lscala/actors/ReplyReactor;Lscala/Tuple2;Z)V;
NameAndType	resumeReceiver:(Lscala/actors/ReplyReactor;Lscala/Tuple2;Z)V
Method	scala/actors/ReplyReactor$class.resumeReceiver:(Lscala/actors/ReplyReactor;Lscala/Tuple2;Z)V
Asciz	scala$actors$Actor$$super$startSearch;
Asciz	(Lscala/actors/Reactor;Ljava/lang/Object;Lscala/actors/OutputChannel;Lscala/Function1;)Lscala/Function0;;
NameAndType	startSearch:(Lscala/actors/Reactor;Ljava/lang/Object;Lscala/actors/OutputChannel;Lscala/Function1;)Lscala/Function0;
Method	scala/actors/Reactor$class.startSearch:(Lscala/actors/Reactor;Ljava/lang/Object;Lscala/actors/OutputChannel;Lscala/Function1;)Lscala/Function0;
Asciz	shouldExit_$eq;
NameAndType	shouldExit:Z
Field	scala/actors/Futures$$anon$1.shouldExit:Z
Asciz	exitReason_$eq;
NameAndType	exitReason:Ljava/lang/Object;
Field	scala/actors/Futures$$anon$1.exitReason:Ljava/lang/Object;
Asciz	trapExit_$eq;
NameAndType	trapExit:Z
Field	scala/actors/Futures$$anon$1.trapExit:Z
Asciz	links_$eq;
NameAndType	links:Lscala/collection/immutable/List;
Field	scala/actors/Futures$$anon$1.links:Lscala/collection/immutable/List;
Asciz	scala$actors$Actor$$blocker;
Asciz	()Lscala/actors/Actor$blocker$;;
NameAndType	scala$actors$Actor$$blocker$module:Lscala/actors/Actor$blocker$;
Field	scala/actors/Futures$$anon$1.scala$actors$Actor$$blocker$module:Lscala/actors/Actor$blocker$;
Asciz	scala/actors/Actor$blocker$;
class	scala/actors/Actor$blocker$
NameAndType	"<init>":(Lscala/actors/Actor;)V
Method	scala/actors/Actor$blocker$."<init>":(Lscala/actors/Actor;)V
Asciz	scala$actors$Actor$$onTimeout_$eq;
Asciz	(Lscala/Option;)V;
NameAndType	scala$actors$Actor$$onTimeout:Lscala/Option;
Field	scala/actors/Futures$$anon$1.scala$actors$Actor$$onTimeout:Lscala/Option;
Asciz	()Lscala/Option;;
Asciz	scala$actors$Actor$$received_$eq;
NameAndType	scala$actors$Actor$$received:Lscala/Option;
Field	scala/actors/Futures$$anon$1.scala$actors$Actor$$received:Lscala/Option;
Asciz	scala$actors$Actor$$isSuspended_$eq;
NameAndType	scala$actors$Actor$$isSuspended:Z
Field	scala/actors/Futures$$anon$1.scala$actors$Actor$$isSuspended:Z
Asciz	scheduler;
Asciz	()Lscala/actors/IScheduler;;
Asciz	(Lscala/actors/DaemonActor;)Lscala/actors/IScheduler;;
NameAndType	scheduler:(Lscala/actors/DaemonActor;)Lscala/actors/IScheduler;
Method	scala/actors/DaemonActor$class.scheduler:(Lscala/actors/DaemonActor;)Lscala/actors/IScheduler;
Asciz	Scala;
Asciz	InnerClasses;
Asciz	scala/actors/Futures;
class	scala/actors/Futures
Asciz	$anon$1;
Asciz	$anonfun$act$1;
Asciz	scala/actors/DaemonActor;
class	scala/actors/DaemonActor

{
private scala.actors.Actor$blocker$ scala$actors$Actor$$blocker$module;
  Signature: Lscala/actors/Actor$blocker$;

private boolean exiting;
  Signature: Z

private volatile scala.Function0 kill;
  Signature: Lscala/Function0;

private scala.Function1 waitingFor;
  Signature: Lscala/Function1;

private final scala.Function1 waitingForNone;
  Signature: Lscala/Function1;

private volatile scala.PartialFunction continuation;
  Signature: Lscala/PartialFunction;

private final scala.collection.mutable.Queue sendBuffer;
  Signature: Lscala/collection/mutable/Queue;

private final scala.actors.MessageQueue mailbox;
  Signature: Lscala/actors/MessageQueue;

private volatile scala.collection.immutable.List senders;
  Signature: Lscala/collection/immutable/List;

private boolean shouldExit;
  Signature: Z

private java.lang.Object exitReason;
  Signature: Ljava/lang/Object;

private boolean trapExit;
  Signature: Z

private scala.collection.immutable.List links;
  Signature: Lscala/collection/immutable/List;

private scala.Option scala$actors$Actor$$onTimeout;
  Signature: Lscala/Option;

private volatile scala.Option scala$actors$Actor$$received;
  Signature: Lscala/Option;

private volatile boolean scala$actors$Actor$$isSuspended;
  Signature: Z

public final scala.Function0 body$1;
  Signature: Lscala/Function0;

public scala.actors.Futures$$anon$1(scala.Function0);
  Signature: (Lscala/Function0;)V
  Code:
   Stack=2, Locals=2, Args_size=2
	aload_0
	aload_1
	putfield	Field body$1:Lscala/Function0;
	aload_0
	invokespecial	Method java/lang/Object."<init>":()V
	aload_0
	invokestatic	Method scala/actors/Replyable$class.$init$:(Lscala/actors/Replyable;)V
	aload_0
	invokestatic	Method scala/actors/AbstractActor$class.$init$:(Lscala/actors/AbstractActor;)V
	aload_0
	invokestatic	Method scala/actors/Reactor$class.$init$:(Lscala/actors/Reactor;)V
	aload_0
	invokestatic	Method scala/actors/ReplyableReactor$class.$init$:(Lscala/actors/ReplyReactor;)V
	aload_0
	invokestatic	Method scala/actors/ReplyReactor$class.$init$:(Lscala/actors/ReplyReactor;)V
	aload_0
	invokestatic	Method scala/actors/ReplyableActor$class.$init$:(Lscala/actors/ReplyableActor;)V
	aload_0
	invokestatic	Method scala/actors/Actor$class.$init$:(Lscala/actors/Actor;)V
	aload_0
	invokestatic	Method scala/actors/DaemonActor$class.$init$:(Lscala/actors/DaemonActor;)V
	return
  Labels:

public scala.actors.Reactor start();
  Signature: ()Lscala/actors/Reactor;
  Code:
   Stack=1, Locals=1, Args_size=1
	aload_0
	invokeinterface	InterfaceMethod scala/actors/Actor.start:()Lscala/actors/Actor;
	areturn
  Labels:

public scala.Function0 $bang$bang(java.lang.Object, scala.PartialFunction);
  Signature: (Ljava/lang/Object;Lscala/PartialFunction;)Lscala/Function0;
  Code:
   Stack=3, Locals=3, Args_size=3
	aload_0
	aload_1
	aload_2
	invokeinterface	InterfaceMethod scala/actors/ReplyableActor.$bang$bang:(Ljava/lang/Object;Lscala/PartialFunction;)Lscala/actors/Future;
	areturn
  Labels:
  LocalVariableTable: 
   Start  Length  Slot  Name   Signature
   0      9      0    this       Lscala/actors/Futures$$anon$1;
   0      9      1    msg       Ljava/lang/Object;
   0      9      2    f       Lscala/PartialFunction;


public scala.Function0 $bang$bang(java.lang.Object);
  Signature: (Ljava/lang/Object;)Lscala/Function0;
  Code:
   Stack=2, Locals=2, Args_size=2
	aload_0
	aload_1
	invokeinterface	InterfaceMethod scala/actors/ReplyableActor.$bang$bang:(Ljava/lang/Object;)Lscala/actors/Future;
	areturn
  Labels:
  LocalVariableTable: 
   Start  Length  Slot  Name   Signature
   0      8      0    this       Lscala/actors/Futures$$anon$1;
   0      8      1    msg       Ljava/lang/Object;


public void act();
  Signature: ()V
  Code:
   Stack=4, Locals=1, Args_size=1
	getstatic	Field scala/actors/Actor$.MODULE$:Lscala/actors/Actor$;
	new	class scala/actors/Futures$$anon$1$$anonfun$act$1
	dup
	aload_0
	invokespecial	Method scala/actors/Futures$$anon$1$$anonfun$act$1."<init>":(Lscala/actors/Futures$$anon$1;)V
	invokevirtual	Method scala/actors/Actor$.react:(Lscala/PartialFunction;)Lscala/runtime/Nothing$;
	athrow
  Labels:

public void exiting_$eq(boolean);
  Signature: (Z)V
  Code:
   Stack=2, Locals=2, Args_size=2
	aload_0
	iload_1
	putfield	Field exiting:Z
	return
  Labels:

public boolean exiting();
  Signature: ()Z
  Code:
   Stack=1, Locals=1, Args_size=1
	aload_0
	getfield	Field exiting:Z
	ireturn
  Labels:

public void terminated();
  Signature: ()V
  Code:
   Stack=1, Locals=1, Args_size=1
	aload_0
	invokestatic	Method scala/actors/Reactor$class.terminated:(Lscala/actors/Reactor;)V
	return
  Labels:

public void seq(scala.Function0, scala.Function0);
  Signature: (Lscala/Function0;Lscala/Function0;)V
  Code:
   Stack=3, Locals=3, Args_size=3
	aload_0
	aload_1
	aload_2
	invokestatic	Method scala/actors/Reactor$class.seq:(Lscala/actors/Reactor;Lscala/Function0;Lscala/Function0;)V
	return
  Labels:
  LocalVariableTable: 
   Start  Length  Slot  Name   Signature
   0      7      0    this       Lscala/actors/Futures$$anon$1;
   0      7      1    first       Lscala/Function0;
   0      7      2    next       Lscala/Function0;


public void drainSendBuffer(scala.actors.MessageQueue);
  Signature: (Lscala/actors/MessageQueue;)V
  Code:
   Stack=2, Locals=2, Args_size=2
	aload_0
	aload_1
	invokestatic	Method scala/actors/Reactor$class.drainSendBuffer:(Lscala/actors/Reactor;Lscala/actors/MessageQueue;)V
	return
  Labels:
  LocalVariableTable: 
   Start  Length  Slot  Name   Signature
   0      6      0    this       Lscala/actors/Futures$$anon$1;
   0      6      1    mbox       Lscala/actors/MessageQueue;


public scala.actors.Actor receiver();
  Signature: ()Lscala/actors/Actor;
  Code:
   Stack=1, Locals=1, Args_size=1
	aload_0
	invokestatic	Method scala/actors/Reactor$class.receiver:(Lscala/actors/Reactor;)Lscala/actors/Actor;
	areturn
  Labels:

public void send(java.lang.Object, scala.actors.OutputChannel);
  Signature: (Ljava/lang/Object;Lscala/actors/OutputChannel;)V
  Code:
   Stack=3, Locals=3, Args_size=3
	aload_0
	aload_1
	aload_2
	invokestatic	Method scala/actors/Reactor$class.send:(Lscala/actors/Reactor;Ljava/lang/Object;Lscala/actors/OutputChannel;)V
	return
  Labels:
  LocalVariableTable: 
   Start  Length  Slot  Name   Signature
   0      7      0    this       Lscala/actors/Futures$$anon$1;
   0      7      1    msg       Ljava/lang/Object;
   0      7      2    replyTo       Lscala/actors/OutputChannel;


public int mailboxSize();
  Signature: ()I
  Code:
   Stack=1, Locals=1, Args_size=1
	aload_0
	invokestatic	Method scala/actors/Reactor$class.mailboxSize:(Lscala/actors/Reactor;)I
	ireturn
  Labels:

public scala.PartialFunction exceptionHandler();
  Signature: ()Lscala/PartialFunction;
  Code:
   Stack=1, Locals=1, Args_size=1
	aload_0
	invokestatic	Method scala/actors/Reactor$class.exceptionHandler:(Lscala/actors/Reactor;)Lscala/PartialFunction;
	areturn
  Labels:

public void scala$actors$Reactor$_setter_$waitingForNone_$eq(scala.Function1);
  Signature: (Lscala/Function1;)V
  Code:
   Stack=2, Locals=2, Args_size=2
	aload_0
	aload_1
	putfield	Field waitingForNone:Lscala/Function1;
	return
  Labels:

public void scala$actors$Reactor$_setter_$sendBuffer_$eq(scala.collection.mutable.Queue);
  Signature: (Lscala/collection/mutable/Queue;)V
  Code:
   Stack=2, Locals=2, Args_size=2
	aload_0
	aload_1
	putfield	Field sendBuffer:Lscala/collection/mutable/Queue;
	return
  Labels:

public void scala$actors$Reactor$_setter_$mailbox_$eq(scala.actors.MessageQueue);
  Signature: (Lscala/actors/MessageQueue;)V
  Code:
   Stack=2, Locals=2, Args_size=2
	aload_0
	aload_1
	putfield	Field mailbox:Lscala/actors/MessageQueue;
	return
  Labels:

public void kill_$eq(scala.Function0);
  Signature: (Lscala/Function0;)V
  Code:
   Stack=2, Locals=2, Args_size=2
	aload_0
	aload_1
	putfield	Field kill:Lscala/Function0;
	return
  Labels:

public scala.Function0 kill();
  Signature: ()Lscala/Function0;
  Code:
   Stack=1, Locals=1, Args_size=1
	aload_0
	getfield	Field kill:Lscala/Function0;
	areturn
  Labels:

public void waitingFor_$eq(scala.Function1);
  Signature: (Lscala/Function1;)V
  Code:
   Stack=2, Locals=2, Args_size=2
	aload_0
	aload_1
	putfield	Field waitingFor:Lscala/Function1;
	return
  Labels:

public scala.Function1 waitingFor();
  Signature: ()Lscala/Function1;
  Code:
   Stack=1, Locals=1, Args_size=1
	aload_0
	getfield	Field waitingFor:Lscala/Function1;
	areturn
  Labels:

public scala.Function1 waitingForNone();
  Signature: ()Lscala/Function1;
  Code:
   Stack=1, Locals=1, Args_size=1
	aload_0
	getfield	Field waitingForNone:Lscala/Function1;
	areturn
  Labels:

public void continuation_$eq(scala.PartialFunction);
  Signature: (Lscala/PartialFunction;)V
  Code:
   Stack=2, Locals=2, Args_size=2
	aload_0
	aload_1
	putfield	Field continuation:Lscala/PartialFunction;
	return
  Labels:

public scala.PartialFunction continuation();
  Signature: ()Lscala/PartialFunction;
  Code:
   Stack=1, Locals=1, Args_size=1
	aload_0
	getfield	Field continuation:Lscala/PartialFunction;
	areturn
  Labels:

public scala.collection.mutable.Queue sendBuffer();
  Signature: ()Lscala/collection/mutable/Queue;
  Code:
   Stack=1, Locals=1, Args_size=1
	aload_0
	getfield	Field sendBuffer:Lscala/collection/mutable/Queue;
	areturn
  Labels:

public scala.actors.MessageQueue mailbox();
  Signature: ()Lscala/actors/MessageQueue;
  Code:
   Stack=1, Locals=1, Args_size=1
	aload_0
	getfield	Field mailbox:Lscala/actors/MessageQueue;
	areturn
  Labels:

public void searchMailbox(scala.actors.MessageQueue, scala.Function1, boolean);
  Signature: (Lscala/actors/MessageQueue;Lscala/Function1;Z)V
  Code:
   Stack=4, Locals=4, Args_size=4
	aload_0
	aload_1
	aload_2
	iload_3
	invokestatic	Method scala/actors/ReplyReactor$class.searchMailbox:(Lscala/actors/ReplyReactor;Lscala/actors/MessageQueue;Lscala/Function1;Z)V
	return
  Labels:
  LocalVariableTable: 
   Start  Length  Slot  Name   Signature
   0      8      0    this       Lscala/actors/Futures$$anon$1;
   0      8      1    startMbox       Lscala/actors/MessageQueue;
   0      8      2    handlesMessage       Lscala/Function1;
   0      8      3    resumeOnSameThread       Z


public void forward(java.lang.Object);
  Signature: (Ljava/lang/Object;)V
  Code:
   Stack=2, Locals=2, Args_size=2
	aload_0
	aload_1
	invokestatic	Method scala/actors/ReplyReactor$class.forward:(Lscala/actors/ReplyReactor;Ljava/lang/Object;)V
	return
  Labels:
  LocalVariableTable: 
   Start  Length  Slot  Name   Signature
   0      6      0    this       Lscala/actors/Futures$$anon$1;
   0      6      1    msg       Ljava/lang/Object;


public void $bang(java.lang.Object);
  Signature: (Ljava/lang/Object;)V
  Code:
   Stack=2, Locals=2, Args_size=2
	aload_0
	aload_1
	invokestatic	Method scala/actors/ReplyReactor$class.$bang:(Lscala/actors/ReplyReactor;Ljava/lang/Object;)V
	return
  Labels:
  LocalVariableTable: 
   Start  Length  Slot  Name   Signature
   0      6      0    this       Lscala/actors/Futures$$anon$1;
   0      6      1    msg       Ljava/lang/Object;


public void reply(java.lang.Object);
  Signature: (Ljava/lang/Object;)V
  Code:
   Stack=2, Locals=2, Args_size=2
	aload_0
	aload_1
	invokestatic	Method scala/actors/ReplyReactor$class.reply:(Lscala/actors/ReplyReactor;Ljava/lang/Object;)V
	return
  Labels:
  LocalVariableTable: 
   Start  Length  Slot  Name   Signature
   0      6      0    this       Lscala/actors/Futures$$anon$1;
   0      6      1    msg       Ljava/lang/Object;


public scala.actors.OutputChannel sender();
  Signature: ()Lscala/actors/OutputChannel;
  Code:
   Stack=1, Locals=1, Args_size=1
	aload_0
	invokestatic	Method scala/actors/ReplyReactor$class.sender:(Lscala/actors/ReplyReactor;)Lscala/actors/OutputChannel;
	areturn
  Labels:

public void senders_$eq(scala.collection.immutable.List);
  Signature: (Lscala/collection/immutable/List;)V
  Code:
   Stack=2, Locals=2, Args_size=2
	aload_0
	aload_1
	putfield	Field senders:Lscala/collection/immutable/List;
	return
  Labels:

public scala.collection.immutable.List senders();
  Signature: ()Lscala/collection/immutable/List;
  Code:
   Stack=1, Locals=1, Args_size=1
	aload_0
	getfield	Field senders:Lscala/collection/immutable/List;
	areturn
  Labels:

public scala.actors.Future $bang$bang(java.lang.Object);
  Signature: (Ljava/lang/Object;)Lscala/actors/Future;
  Code:
   Stack=2, Locals=2, Args_size=2
	aload_0
	aload_1
	invokestatic	Method scala/actors/ReplyableActor$class.$bang$bang:(Lscala/actors/ReplyableActor;Ljava/lang/Object;)Lscala/actors/Future;
	areturn
  Labels:
  LocalVariableTable: 
   Start  Length  Slot  Name   Signature
   0      6      0    this       Lscala/actors/Futures$$anon$1;
   0      6      1    msg       Ljava/lang/Object;


public scala.actors.Future $bang$bang(java.lang.Object, scala.PartialFunction);
  Signature: (Ljava/lang/Object;Lscala/PartialFunction;)Lscala/actors/Future;
  Code:
   Stack=3, Locals=3, Args_size=3
	aload_0
	aload_1
	aload_2
	invokestatic	Method scala/actors/ReplyableActor$class.$bang$bang:(Lscala/actors/ReplyableActor;Ljava/lang/Object;Lscala/PartialFunction;)Lscala/actors/Future;
	areturn
  Labels:
  LocalVariableTable: 
   Start  Length  Slot  Name   Signature
   0      7      0    this       Lscala/actors/Futures$$anon$1;
   0      7      1    msg       Ljava/lang/Object;
   0      7      2    f       Lscala/PartialFunction;


public scala.Option $bang$qmark(long, java.lang.Object);
  Signature: (JLjava/lang/Object;)Lscala/Option;
  Code:
   Stack=4, Locals=4, Args_size=3
	aload_0
	lload_1
	aload_3
	invokestatic	Method scala/actors/ReplyableActor$class.$bang$qmark:(Lscala/actors/ReplyableActor;JLjava/lang/Object;)Lscala/Option;
	areturn
  Labels:
  LocalVariableTable: 
   Start  Length  Slot  Name   Signature
   0      7      0    this       Lscala/actors/Futures$$anon$1;
   0      7      1    msec       J
   0      7      3    msg       Ljava/lang/Object;


public java.lang.Object $bang$qmark(java.lang.Object);
  Signature: (Ljava/lang/Object;)Ljava/lang/Object;
  Code:
   Stack=2, Locals=2, Args_size=2
	aload_0
	aload_1
	invokestatic	Method scala/actors/ReplyableActor$class.$bang$qmark:(Lscala/actors/ReplyableActor;Ljava/lang/Object;)Ljava/lang/Object;
	areturn
  Labels:
  LocalVariableTable: 
   Start  Length  Slot  Name   Signature
   0      6      0    this       Lscala/actors/Futures$$anon$1;
   0      6      1    msg       Ljava/lang/Object;


public void onTerminate(scala.Function0);
  Signature: (Lscala/Function0;)V
  Code:
   Stack=2, Locals=2, Args_size=2
	aload_0
	aload_1
	invokestatic	Method scala/actors/Actor$class.onTerminate:(Lscala/actors/Actor;Lscala/Function0;)V
	return
  Labels:
  LocalVariableTable: 
   Start  Length  Slot  Name   Signature
   0      6      0    this       Lscala/actors/Futures$$anon$1;
   0      6      1    f       Lscala/Function0;


public void exit(scala.actors.AbstractActor, java.lang.Object);
  Signature: (Lscala/actors/AbstractActor;Ljava/lang/Object;)V
  Code:
   Stack=3, Locals=3, Args_size=3
	aload_0
	aload_1
	aload_2
	invokestatic	Method scala/actors/Actor$class.exit:(Lscala/actors/Actor;Lscala/actors/AbstractActor;Ljava/lang/Object;)V
	return
  Labels:
  LocalVariableTable: 
   Start  Length  Slot  Name   Signature
   0      7      0    this       Lscala/actors/Futures$$anon$1;
   0      7      1    from       Lscala/actors/AbstractActor;
   0      7      2    reason       Ljava/lang/Object;


public void exitLinked(java.lang.Object);
  Signature: (Ljava/lang/Object;)V
  Code:
   Stack=2, Locals=2, Args_size=2
	aload_0
	aload_1
	invokestatic	Method scala/actors/Actor$class.exitLinked:(Lscala/actors/Actor;Ljava/lang/Object;)V
	return
  Labels:
  LocalVariableTable: 
   Start  Length  Slot  Name   Signature
   0      6      0    this       Lscala/actors/Futures$$anon$1;
   0      6      1    reason       Ljava/lang/Object;


public void exitLinked();
  Signature: ()V
  Code:
   Stack=1, Locals=1, Args_size=1
	aload_0
	invokestatic	Method scala/actors/Actor$class.exitLinked:(Lscala/actors/Actor;)V
	return
  Labels:

public scala.runtime.Nothing$ exit();
  Signature: ()Lscala/runtime/Nothing$;
  Code:
   Stack=1, Locals=1, Args_size=1
	aload_0
	invokestatic	Method scala/actors/Actor$class.exit:(Lscala/actors/Actor;)Lscala/runtime/Nothing$;
	areturn
  Labels:

public scala.runtime.Nothing$ exit(java.lang.Object);
  Signature: (Ljava/lang/Object;)Lscala/runtime/Nothing$;
  Code:
   Stack=2, Locals=2, Args_size=2
	aload_0
	aload_1
	invokestatic	Method scala/actors/Actor$class.exit:(Lscala/actors/Actor;Ljava/lang/Object;)Lscala/runtime/Nothing$;
	areturn
  Labels:
  LocalVariableTable: 
   Start  Length  Slot  Name   Signature
   0      6      0    this       Lscala/actors/Futures$$anon$1;
   0      6      1    reason       Ljava/lang/Object;


public void unlinkFrom(scala.actors.AbstractActor);
  Signature: (Lscala/actors/AbstractActor;)V
  Code:
   Stack=2, Locals=2, Args_size=2
	aload_0
	aload_1
	invokestatic	Method scala/actors/Actor$class.unlinkFrom:(Lscala/actors/Actor;Lscala/actors/AbstractActor;)V
	return
  Labels:
  LocalVariableTable: 
   Start  Length  Slot  Name   Signature
   0      6      0    this       Lscala/actors/Futures$$anon$1;
   0      6      1    from       Lscala/actors/AbstractActor;


public void unlink(scala.actors.AbstractActor);
  Signature: (Lscala/actors/AbstractActor;)V
  Code:
   Stack=2, Locals=2, Args_size=2
	aload_0
	aload_1
	invokestatic	Method scala/actors/Actor$class.unlink:(Lscala/actors/Actor;Lscala/actors/AbstractActor;)V
	return
  Labels:
  LocalVariableTable: 
   Start  Length  Slot  Name   Signature
   0      6      0    this       Lscala/actors/Futures$$anon$1;
   0      6      1    from       Lscala/actors/AbstractActor;


public void linkTo(scala.actors.AbstractActor);
  Signature: (Lscala/actors/AbstractActor;)V
  Code:
   Stack=2, Locals=2, Args_size=2
	aload_0
	aload_1
	invokestatic	Method scala/actors/Actor$class.linkTo:(Lscala/actors/Actor;Lscala/actors/AbstractActor;)V
	return
  Labels:
  LocalVariableTable: 
   Start  Length  Slot  Name   Signature
   0      6      0    this       Lscala/actors/Futures$$anon$1;
   0      6      1    to       Lscala/actors/AbstractActor;


public scala.actors.Actor link(scala.Function0);
  Signature: (Lscala/Function0;)Lscala/actors/Actor;
  Code:
   Stack=2, Locals=2, Args_size=2
	aload_0
	aload_1
	invokestatic	Method scala/actors/Actor$class.link:(Lscala/actors/Actor;Lscala/Function0;)Lscala/actors/Actor;
	areturn
  Labels:
  LocalVariableTable: 
   Start  Length  Slot  Name   Signature
   0      6      0    this       Lscala/actors/Futures$$anon$1;
   0      6      1    body       Lscala/Function0;


public scala.actors.AbstractActor link(scala.actors.AbstractActor);
  Signature: (Lscala/actors/AbstractActor;)Lscala/actors/AbstractActor;
  Code:
   Stack=2, Locals=2, Args_size=2
	aload_0
	aload_1
	invokestatic	Method scala/actors/Actor$class.link:(Lscala/actors/Actor;Lscala/actors/AbstractActor;)Lscala/actors/AbstractActor;
	areturn
  Labels:
  LocalVariableTable: 
   Start  Length  Slot  Name   Signature
   0      6      0    this       Lscala/actors/Futures$$anon$1;
   0      6      1    to       Lscala/actors/AbstractActor;


public scala.actors.Actor start();
  Signature: ()Lscala/actors/Actor;
  Code:
   Stack=1, Locals=1, Args_size=1
	aload_0
	invokestatic	Method scala/actors/Actor$class.start:(Lscala/actors/Actor;)Lscala/actors/Actor;
	areturn
  Labels:

public void scheduleActor(scala.PartialFunction, java.lang.Object);
  Signature: (Lscala/PartialFunction;Ljava/lang/Object;)V
  Code:
   Stack=3, Locals=3, Args_size=3
	aload_0
	aload_1
	aload_2
	invokestatic	Method scala/actors/Actor$class.scheduleActor:(Lscala/actors/Actor;Lscala/PartialFunction;Ljava/lang/Object;)V
	return
  Labels:
  LocalVariableTable: 
   Start  Length  Slot  Name   Signature
   0      7      0    this       Lscala/actors/Futures$$anon$1;
   0      7      1    f       Lscala/PartialFunction;
   0      7      2    msg       Ljava/lang/Object;


public java.lang.Object $qmark();
  Signature: ()Ljava/lang/Object;
  Code:
   Stack=1, Locals=1, Args_size=1
	aload_0
	invokestatic	Method scala/actors/Actor$class.$qmark:(Lscala/actors/Actor;)Ljava/lang/Object;
	areturn
  Labels:

public scala.runtime.Nothing$ reactWithin(long, scala.PartialFunction);
  Signature: (JLscala/PartialFunction;)Lscala/runtime/Nothing$;
  Code:
   Stack=4, Locals=4, Args_size=3
	aload_0
	lload_1
	aload_3
	invokestatic	Method scala/actors/Actor$class.reactWithin:(Lscala/actors/Actor;JLscala/PartialFunction;)Lscala/runtime/Nothing$;
	areturn
  Labels:
  LocalVariableTable: 
   Start  Length  Slot  Name   Signature
   0      7      0    this       Lscala/actors/Futures$$anon$1;
   0      7      1    msec       J
   0      7      3    f       Lscala/PartialFunction;


public scala.runtime.Nothing$ react(scala.PartialFunction);
  Signature: (Lscala/PartialFunction;)Lscala/runtime/Nothing$;
  Code:
   Stack=2, Locals=2, Args_size=2
	aload_0
	aload_1
	invokestatic	Method scala/actors/Actor$class.react:(Lscala/actors/Actor;Lscala/PartialFunction;)Lscala/runtime/Nothing$;
	areturn
  Labels:
  LocalVariableTable: 
   Start  Length  Slot  Name   Signature
   0      6      0    this       Lscala/actors/Futures$$anon$1;
   0      6      1    f       Lscala/PartialFunction;


public java.lang.Object receiveWithin(long, scala.PartialFunction);
  Signature: (JLscala/PartialFunction;)Ljava/lang/Object;
  Code:
   Stack=4, Locals=4, Args_size=3
	aload_0
	lload_1
	aload_3
	invokestatic	Method scala/actors/Actor$class.receiveWithin:(Lscala/actors/Actor;JLscala/PartialFunction;)Ljava/lang/Object;
	areturn
  Labels:
  LocalVariableTable: 
   Start  Length  Slot  Name   Signature
   0      7      0    this       Lscala/actors/Futures$$anon$1;
   0      7      1    msec       J
   0      7      3    f       Lscala/PartialFunction;


public java.lang.Object receive(scala.PartialFunction);
  Signature: (Lscala/PartialFunction;)Ljava/lang/Object;
  Code:
   Stack=2, Locals=2, Args_size=2
	aload_0
	aload_1
	invokestatic	Method scala/actors/Actor$class.receive:(Lscala/actors/Actor;Lscala/PartialFunction;)Ljava/lang/Object;
	areturn
  Labels:
  LocalVariableTable: 
   Start  Length  Slot  Name   Signature
   0      6      0    this       Lscala/actors/Futures$$anon$1;
   0      6      1    f       Lscala/PartialFunction;


public void resumeReceiver(scala.Tuple2, boolean);
  Signature: (Lscala/Tuple2;Z)V
  Code:
   Stack=3, Locals=3, Args_size=3
	aload_0
	aload_1
	iload_2
	invokestatic	Method scala/actors/Actor$class.resumeReceiver:(Lscala/actors/Actor;Lscala/Tuple2;Z)V
	return
  Labels:
  LocalVariableTable: 
   Start  Length  Slot  Name   Signature
   0      7      0    this       Lscala/actors/Futures$$anon$1;
   0      7      1    item       Lscala/Tuple2;
   0      7      2    onSameThread       Z


public java.lang.Runnable makeReaction(scala.Function0);
  Signature: (Lscala/Function0;)Ljava/lang/Runnable;
  Code:
   Stack=2, Locals=2, Args_size=2
	aload_0
	aload_1
	invokestatic	Method scala/actors/Actor$class.makeReaction:(Lscala/actors/Actor;Lscala/Function0;)Ljava/lang/Runnable;
	areturn
  Labels:
  LocalVariableTable: 
   Start  Length  Slot  Name   Signature
   0      6      0    this       Lscala/actors/Futures$$anon$1;
   0      6      1    fun       Lscala/Function0;


public scala.Function0 startSearch(java.lang.Object, scala.actors.OutputChannel, scala.Function1);
  Signature: (Ljava/lang/Object;Lscala/actors/OutputChannel;Lscala/Function1;)Lscala/Function0;
  Code:
   Stack=4, Locals=4, Args_size=4
	aload_0
	aload_1
	aload_2
	aload_3
	invokestatic	Method scala/actors/Actor$class.startSearch:(Lscala/actors/Actor;Ljava/lang/Object;Lscala/actors/OutputChannel;Lscala/Function1;)Lscala/Function0;
	areturn
  Labels:
  LocalVariableTable: 
   Start  Length  Slot  Name   Signature
   0      8      0    this       Lscala/actors/Futures$$anon$1;
   0      8      1    msg       Ljava/lang/Object;
   0      8      2    replyTo       Lscala/actors/OutputChannel;
   0      8      3    handler       Lscala/Function1;


public final void scala$actors$Actor$$super$resumeReceiver(scala.Tuple2, boolean);
  Signature: (Lscala/Tuple2;Z)V
  Code:
   Stack=3, Locals=3, Args_size=3
	aload_0
	aload_1
	iload_2
	invokestatic	Method scala/actors/ReplyReactor$class.resumeReceiver:(Lscala/actors/ReplyReactor;Lscala/Tuple2;Z)V
	return
  Labels:
  LocalVariableTable: 
   Start  Length  Slot  Name   Signature
   0      7      0    this       Lscala/actors/Futures$$anon$1;
   0      7      1    item       Lscala/Tuple2;
   0      7      2    onSameThread       Z


public final scala.Function0 scala$actors$Actor$$super$startSearch(java.lang.Object, scala.actors.OutputChannel, scala.Function1);
  Signature: (Ljava/lang/Object;Lscala/actors/OutputChannel;Lscala/Function1;)Lscala/Function0;
  Code:
   Stack=4, Locals=4, Args_size=4
	aload_0
	aload_1
	aload_2
	aload_3
	invokestatic	Method scala/actors/Reactor$class.startSearch:(Lscala/actors/Reactor;Ljava/lang/Object;Lscala/actors/OutputChannel;Lscala/Function1;)Lscala/Function0;
	areturn
  Labels:
  LocalVariableTable: 
   Start  Length  Slot  Name   Signature
   0      8      0    this       Lscala/actors/Futures$$anon$1;
   0      8      1    msg       Ljava/lang/Object;
   0      8      2    replyTo       Lscala/actors/OutputChannel;
   0      8      3    handler       Lscala/Function1;


public void shouldExit_$eq(boolean);
  Signature: (Z)V
  Code:
   Stack=2, Locals=2, Args_size=2
	aload_0
	iload_1
	putfield	Field shouldExit:Z
	return
  Labels:

public boolean shouldExit();
  Signature: ()Z
  Code:
   Stack=1, Locals=1, Args_size=1
	aload_0
	getfield	Field shouldExit:Z
	ireturn
  Labels:

public void exitReason_$eq(java.lang.Object);
  Signature: (Ljava/lang/Object;)V
  Code:
   Stack=2, Locals=2, Args_size=2
	aload_0
	aload_1
	putfield	Field exitReason:Ljava/lang/Object;
	return
  Labels:

public java.lang.Object exitReason();
  Signature: ()Ljava/lang/Object;
  Code:
   Stack=1, Locals=1, Args_size=1
	aload_0
	getfield	Field exitReason:Ljava/lang/Object;
	areturn
  Labels:

public void trapExit_$eq(boolean);
  Signature: (Z)V
  Code:
   Stack=2, Locals=2, Args_size=2
	aload_0
	iload_1
	putfield	Field trapExit:Z
	return
  Labels:

public boolean trapExit();
  Signature: ()Z
  Code:
   Stack=1, Locals=1, Args_size=1
	aload_0
	getfield	Field trapExit:Z
	ireturn
  Labels:

public void links_$eq(scala.collection.immutable.List);
  Signature: (Lscala/collection/immutable/List;)V
  Code:
   Stack=2, Locals=2, Args_size=2
	aload_0
	aload_1
	putfield	Field links:Lscala/collection/immutable/List;
	return
  Labels:

public scala.collection.immutable.List links();
  Signature: ()Lscala/collection/immutable/List;
  Code:
   Stack=1, Locals=1, Args_size=1
	aload_0
	getfield	Field links:Lscala/collection/immutable/List;
	areturn
  Labels:

public final scala.actors.Actor$blocker$ scala$actors$Actor$$blocker();
  Signature: ()Lscala/actors/Actor$blocker$;
  Code:
   Stack=4, Locals=1, Args_size=1
	aload_0
	getfield	Field scala$actors$Actor$$blocker$module:Lscala/actors/Actor$blocker$;
	ifnonnull	l1 // aload_0
	aload_0
	new	class scala/actors/Actor$blocker$
	dup
	aload_0
	invokespecial	Method scala/actors/Actor$blocker$."<init>":(Lscala/actors/Actor;)V
	putfield	Field scala$actors$Actor$$blocker$module:Lscala/actors/Actor$blocker$;
l1	aload_0
	getfield	Field scala$actors$Actor$$blocker$module:Lscala/actors/Actor$blocker$;
	areturn
  Labels:
   	l1 = 19 // aload_0

public final void scala$actors$Actor$$onTimeout_$eq(scala.Option);
  Signature: (Lscala/Option;)V
  Code:
   Stack=2, Locals=2, Args_size=2
	aload_0
	aload_1
	putfield	Field scala$actors$Actor$$onTimeout:Lscala/Option;
	return
  Labels:

public final scala.Option scala$actors$Actor$$onTimeout();
  Signature: ()Lscala/Option;
  Code:
   Stack=1, Locals=1, Args_size=1
	aload_0
	getfield	Field scala$actors$Actor$$onTimeout:Lscala/Option;
	areturn
  Labels:

public final void scala$actors$Actor$$received_$eq(scala.Option);
  Signature: (Lscala/Option;)V
  Code:
   Stack=2, Locals=2, Args_size=2
	aload_0
	aload_1
	putfield	Field scala$actors$Actor$$received:Lscala/Option;
	return
  Labels:

public final scala.Option scala$actors$Actor$$received();
  Signature: ()Lscala/Option;
  Code:
   Stack=1, Locals=1, Args_size=1
	aload_0
	getfield	Field scala$actors$Actor$$received:Lscala/Option;
	areturn
  Labels:

public final void scala$actors$Actor$$isSuspended_$eq(boolean);
  Signature: (Z)V
  Code:
   Stack=2, Locals=2, Args_size=2
	aload_0
	iload_1
	putfield	Field scala$actors$Actor$$isSuspended:Z
	return
  Labels:

public final boolean scala$actors$Actor$$isSuspended();
  Signature: ()Z
  Code:
   Stack=1, Locals=1, Args_size=1
	aload_0
	getfield	Field scala$actors$Actor$$isSuspended:Z
	ireturn
  Labels:

public scala.actors.IScheduler scheduler();
  Signature: ()Lscala/actors/IScheduler;
  Code:
   Stack=1, Locals=1, Args_size=1
	aload_0
	invokestatic	Method scala/actors/DaemonActor$class.scheduler:(Lscala/actors/DaemonActor;)Lscala/actors/IScheduler;
	areturn
  Labels:

}

