Compiled from "Future.scala"
public final class scala.actors.Futures extends java.lang.Object
  SourceFile: "Future.scala"
  ScalaSig: length = 0x2FA
   05 00 7C 07 05 01 02 FFFFFF88 02 07 01 07 46 75 74 75
   72 65 73 0A 02 03 04 01 06 61 63 74 6F 72 73 0A
   01 05 01 05 73 63 61 6C 61 03 00 10 02 08 09 0D
   01 02 06 08 0A 02 FFFFFF84 FFFFFF80 FFFFFF80 FFFFFF88 02 0B 02 07 46 75
   74 75 72 65 73 13 03 09 0C 14 10 02 0D 12 0D 01
   0E 0A 02 0F 10 01 04 6C 61 6E 67 0A 01 11 01 04
   6A 61 76 61 09 02 13 0E 02 06 4F 62 6A 65 63 74
   10 02 15 16 0D 01 04 09 02 17 04 02 0B 53 63 61
   6C 61 4F 62 6A 65 63 74 08 05 19 09 FFFFFF84 00 1A 01
   06 3C 69 6E 69 74 3E 14 01 07 08 08 1C 09 FFFFFF88 FFFFFFC2
   FFFFFF80 FFFFFF84 04 1D 01 05 73 63 68 65 64 15 01 1E 10 02
   1F 22 0D 01 20 0A 02 21 02 01 09 73 63 68 65 64
   75 6C 65 72 09 02 23 20 02 18 44 65 66 61 75 6C
   74 45 78 65 63 75 74 6F 72 53 63 68 65 64 75 6C
   65 72 08 08 25 09 FFFFFF88 FFFFFF80 FFFFFFA0 FFFFFFA0 04 1E 01 06 73 63
   68 65 64 20 08 05 27 09 FFFFFF84 00 28 01 06 66 75 74
   75 72 65 15 02 29 2F 14 02 2A 38 10 03 08 2B 2D
   09 02 2C 02 02 06 46 75 74 75 72 65 10 02 2E 2F
   0C 00 04 08 30 26 FFFFFF84 FFFFFF80 FFFFFF80 FFFFFFC2 00 31 02 01 54 11
   02 32 35 10 02 15 33 09 02 34 04 02 07 4E 6F 74
   68 69 6E 67 10 02 15 36 09 02 37 04 02 03 41 6E
   79 08 06 39 26 FFFFFF84 FFFFFFC0 00 3A 01 04 62 6F 64 79 10
   03 15 3B 2D 09 02 3C 04 02 08 3C 62 79 6E 61 6D
   65 3E 08 05 3E 09 FFFFFF84 00 3F 01 05 61 6C 61 72 6D
   14 02 40 41 10 03 08 2B 32 08 05 42 3D FFFFFFC0 00 43
   01 01 74 10 02 15 44 09 02 45 04 02 04 4C 6F 6E
   67 08 05 47 09 FFFFFF84 00 48 01 0B 61 77 61 69 74 45
   69 74 68 65 72 15 03 49 4E 54 14 03 35 4A 50 08
   05 4B 46 FFFFFFC0 00 4C 01 03 66 74 31 10 03 08 2B 4D
   10 02 2E 4E 04 08 4F 46 FFFFFF84 FFFFFF80 FFFFFF80 FFFFFFC2 00 31 02 01
   61 08 05 51 46 FFFFFFC0 00 52 01 03 66 74 32 10 03 08
   2B 53 10 02 2E 54 04 08 55 46 FFFFFF84 FFFFFF80 FFFFFF80 FFFFFFC2 00 31
   02 01 62 08 05 57 09 FFFFFF84 00 58 01 08 61 77 61 69
   74 41 6C 6C 14 03 59 68 6A 10 03 5A 62 65 0E 02
   5B 60 0E 02 5C 5F 0D 01 5D 0A 02 5E 06 01 06 3C
   72 6F 6F 74 3E 09 01 05 09 02 61 04 01 07 70 61
   63 6B 61 67 65 09 02 63 64 02 04 4C 69 73 74 0A
   02 61 04 10 03 15 66 35 09 02 67 04 02 06 4F 70
   74 69 6F 6E 08 05 69 56 FFFFFFC0 00 43 01 07 74 69 6D
   65 6F 75 74 08 05 6B 56 FFFFFFC0 00 6C 01 03 66 74 73
   10 03 15 6D 6F 09 02 6E 04 02 0A 3C 72 65 70 65
   61 74 65 64 3E 10 03 08 2B 35 08 05 71 09 FFFFFF84 00
   72 01 10 66 72 6F 6D 49 6E 70 75 74 43 68 61 6E
   6E 65 6C 15 02 73 76 14 02 74 77 10 03 08 2B 75
   10 02 2E 76 04 08 30 70 FFFFFF84 FFFFFF80 FFFFFF80 FFFFFFC2 00 31 08 05
   78 70 FFFFFFC0 00 79 01 0C 69 6E 70 75 74 43 68 61 6E
   6E 65 6C 10 03 08 7A 75 09 02 7B 02 02 0C 49 6E
   70 75 74 43 68 61 6E 6E 65 6C 
  InnerClass: 
   public final #50= #47 of #49; //Eval$2=class scala/actors/Futures$Eval$2$ of class scala/actors/Futures
   public final #53= #52 of #49; //$anon$4=class scala/actors/Futures$$anon$4 of class scala/actors/Futures
   public final #56= #55 of #49; //$anon$1=class scala/actors/Futures$$anon$1 of class scala/actors/Futures
   public final #59= #58 of #49; //$anon$3=class scala/actors/Futures$$anon$3 of class scala/actors/Futures
   public final #62= #61 of #49; //$anon$2=class scala/actors/Futures$$anon$2 of class scala/actors/Futures
   public final #65= #64 of #49; //$anonfun$4=class scala/actors/Futures$$anonfun$4 of class scala/actors/Futures
   public final #68= #67 of #49; //$anonfun$2=class scala/actors/Futures$$anonfun$2 of class scala/actors/Futures
   public final #71= #70 of #49; //$anonfun$3=class scala/actors/Futures$$anonfun$3 of class scala/actors/Futures
   public final #74= #73 of #49; //$anonfun$alarm$1=class scala/actors/Futures$$anonfun$alarm$1 of class scala/actors/Futures
   public final #77= #76 of #49; //$anonfun$future$1=class scala/actors/Futures$$anonfun$future$1 of class scala/actors/Futures
   public final #80= #79 of #49; //$anonfun$awaitAll$1=class scala/actors/Futures$$anonfun$awaitAll$1 of class scala/actors/Futures
   public final #83= #82 of #49; //$anonfun$awaitEither$1=class scala/actors/Futures$$anonfun$awaitEither$1 of class scala/actors/Futures
  minor version: 0
  major version: 49
  Constant pool:
const #1 = Asciz	SourceFile;
const #2 = Asciz	Future.scala;
const #3 = Asciz	awaitWith$1;
const #4 = Asciz	(Lscala/collection/Sequence;Lscala/runtime/ObjectRef;)V;
const #5 = Asciz	Code;
const #6 = Asciz	scala/actors/Futures$;
const #7 = class	#6;	//  scala/actors/Futures$
const #8 = Asciz	MODULE$;
const #9 = Asciz	Lscala/actors/Futures$;;
const #10 = NameAndType	#8:#9;//  MODULE$:Lscala/actors/Futures$;
const #11 = Field	#7.#10;	//  scala/actors/Futures$.MODULE$:Lscala/actors/Futures$;
const #12 = NameAndType	#3:#4;//  awaitWith$1:(Lscala/collection/Sequence;Lscala/runtime/ObjectRef;)V
const #13 = Method	#7.#12;	//  scala/actors/Futures$.awaitWith$1:(Lscala/collection/Sequence;Lscala/runtime/ObjectRef;)V
const #14 = Asciz	fromInputChannel;
const #15 = Asciz	(Lscala/actors/InputChannel;)Lscala/actors/Future;;
const #16 = NameAndType	#14:#15;//  fromInputChannel:(Lscala/actors/InputChannel;)Lscala/actors/Future;
const #17 = Method	#7.#16;	//  scala/actors/Futures$.fromInputChannel:(Lscala/actors/InputChannel;)Lscala/actors/Future;
const #18 = Asciz	<T:Ljava/lang/Object;>(Lscala/actors/InputChannel<TT;>;)Lscala/actors/Future<TT;>;;
const #19 = Asciz	Signature;
const #20 = Asciz	awaitAll;
const #21 = Asciz	(JLscala/collection/Sequence;)Lscala/collection/immutable/List;;
const #22 = NameAndType	#20:#21;//  awaitAll:(JLscala/collection/Sequence;)Lscala/collection/immutable/List;
const #23 = Method	#7.#22;	//  scala/actors/Futures$.awaitAll:(JLscala/collection/Sequence;)Lscala/collection/immutable/List;
const #24 = Asciz	(JLscala/collection/Sequence<Lscala/actors/Future<Ljava/lang/Object;>;>;)Lscala/collection/immutable/List<Lscala/Option<Ljava/lang/Object;>;>;;
const #25 = Asciz	awaitEither;
const #26 = Asciz	(Lscala/actors/Future;Lscala/actors/Future;)Ljava/lang/Object;;
const #27 = NameAndType	#25:#26;//  awaitEither:(Lscala/actors/Future;Lscala/actors/Future;)Ljava/lang/Object;
const #28 = Method	#7.#27;	//  scala/actors/Futures$.awaitEither:(Lscala/actors/Future;Lscala/actors/Future;)Ljava/lang/Object;
const #29 = Asciz	<a:Ljava/lang/Object;b:Ljava/lang/Object;>(Lscala/actors/Future<Ta;>;Lscala/actors/Future<Tb;>;)Ljava/lang/Object;;
const #30 = Asciz	alarm;
const #31 = Asciz	(J)Lscala/actors/Future;;
const #32 = NameAndType	#30:#31;//  alarm:(J)Lscala/actors/Future;
const #33 = Method	#7.#32;	//  scala/actors/Futures$.alarm:(J)Lscala/actors/Future;
const #34 = Asciz	(J)Lscala/actors/Future<Lscala/runtime/Nothing$;>;;
const #35 = Asciz	future;
const #36 = Asciz	(Lscala/Function0;)Lscala/actors/Future;;
const #37 = NameAndType	#35:#36;//  future:(Lscala/Function0;)Lscala/actors/Future;
const #38 = Method	#7.#37;	//  scala/actors/Futures$.future:(Lscala/Function0;)Lscala/actors/Future;
const #39 = Asciz	<T:Ljava/lang/Object;>(Lscala/Function0<TT;>;)Lscala/actors/Future<TT;>;;
const #40 = Asciz	scala$actors$Futures$$sched;
const #41 = Asciz	()Lscala/actors/scheduler/DefaultExecutorScheduler;;
const #42 = NameAndType	#40:#41;//  scala$actors$Futures$$sched:()Lscala/actors/scheduler/DefaultExecutorScheduler;
const #43 = Method	#7.#42;	//  scala/actors/Futures$.scala$actors$Futures$$sched:()Lscala/actors/scheduler/DefaultExecutorScheduler;
const #44 = Asciz	ScalaSig;
const #45 = Asciz	InnerClasses;
const #46 = Asciz	scala/actors/Futures$Eval$2$;
const #47 = class	#46;	//  scala/actors/Futures$Eval$2$
const #48 = Asciz	scala/actors/Futures;
const #49 = class	#48;	//  scala/actors/Futures
const #50 = Asciz	Eval$2;
const #51 = Asciz	scala/actors/Futures$$anon$4;
const #52 = class	#51;	//  scala/actors/Futures$$anon$4
const #53 = Asciz	$anon$4;
const #54 = Asciz	scala/actors/Futures$$anon$1;
const #55 = class	#54;	//  scala/actors/Futures$$anon$1
const #56 = Asciz	$anon$1;
const #57 = Asciz	scala/actors/Futures$$anon$3;
const #58 = class	#57;	//  scala/actors/Futures$$anon$3
const #59 = Asciz	$anon$3;
const #60 = Asciz	scala/actors/Futures$$anon$2;
const #61 = class	#60;	//  scala/actors/Futures$$anon$2
const #62 = Asciz	$anon$2;
const #63 = Asciz	scala/actors/Futures$$anonfun$4;
const #64 = class	#63;	//  scala/actors/Futures$$anonfun$4
const #65 = Asciz	$anonfun$4;
const #66 = Asciz	scala/actors/Futures$$anonfun$2;
const #67 = class	#66;	//  scala/actors/Futures$$anonfun$2
const #68 = Asciz	$anonfun$2;
const #69 = Asciz	scala/actors/Futures$$anonfun$3;
const #70 = class	#69;	//  scala/actors/Futures$$anonfun$3
const #71 = Asciz	$anonfun$3;
const #72 = Asciz	scala/actors/Futures$$anonfun$alarm$1;
const #73 = class	#72;	//  scala/actors/Futures$$anonfun$alarm$1
const #74 = Asciz	$anonfun$alarm$1;
const #75 = Asciz	scala/actors/Futures$$anonfun$future$1;
const #76 = class	#75;	//  scala/actors/Futures$$anonfun$future$1
const #77 = Asciz	$anonfun$future$1;
const #78 = Asciz	scala/actors/Futures$$anonfun$awaitAll$1;
const #79 = class	#78;	//  scala/actors/Futures$$anonfun$awaitAll$1
const #80 = Asciz	$anonfun$awaitAll$1;
const #81 = Asciz	scala/actors/Futures$$anonfun$awaitEither$1;
const #82 = class	#81;	//  scala/actors/Futures$$anonfun$awaitEither$1
const #83 = Asciz	$anonfun$awaitEither$1;
const #84 = Asciz	java/lang/Object;
const #85 = class	#84;	//  java/lang/Object

{
public static final void awaitWith$1(scala.collection.Sequence, scala.runtime.ObjectRef);
  Code:
   Stack=3, Locals=2, Args_size=2
   0:	getstatic	#11; //Field scala/actors/Futures$.MODULE$:Lscala/actors/Futures$;
   3:	aload_0
   4:	aload_1
   5:	invokevirtual	#13; //Method scala/actors/Futures$.awaitWith$1:(Lscala/collection/Sequence;Lscala/runtime/ObjectRef;)V
   8:	return

public static final scala.actors.Future fromInputChannel(scala.actors.InputChannel);
  Code:
   Stack=2, Locals=1, Args_size=1
   0:	getstatic	#11; //Field scala/actors/Futures$.MODULE$:Lscala/actors/Futures$;
   3:	aload_0
   4:	invokevirtual	#17; //Method scala/actors/Futures$.fromInputChannel:(Lscala/actors/InputChannel;)Lscala/actors/Future;
   7:	areturn
  Signature: length = 0x2
   00 12 

public static final scala.collection.immutable.List awaitAll(long, scala.collection.Sequence);
  Code:
   Stack=4, Locals=3, Args_size=2
   0:	getstatic	#11; //Field scala/actors/Futures$.MODULE$:Lscala/actors/Futures$;
   3:	lload_0
   4:	aload_2
   5:	invokevirtual	#23; //Method scala/actors/Futures$.awaitAll:(JLscala/collection/Sequence;)Lscala/collection/immutable/List;
   8:	areturn
  Signature: length = 0x2
   00 18 

public static final java.lang.Object awaitEither(scala.actors.Future, scala.actors.Future);
  Code:
   Stack=3, Locals=2, Args_size=2
   0:	getstatic	#11; //Field scala/actors/Futures$.MODULE$:Lscala/actors/Futures$;
   3:	aload_0
   4:	aload_1
   5:	invokevirtual	#28; //Method scala/actors/Futures$.awaitEither:(Lscala/actors/Future;Lscala/actors/Future;)Ljava/lang/Object;
   8:	areturn
  Signature: length = 0x2
   00 1D 

public static final scala.actors.Future alarm(long);
  Code:
   Stack=3, Locals=2, Args_size=1
   0:	getstatic	#11; //Field scala/actors/Futures$.MODULE$:Lscala/actors/Futures$;
   3:	lload_0
   4:	invokevirtual	#33; //Method scala/actors/Futures$.alarm:(J)Lscala/actors/Future;
   7:	areturn
  Signature: length = 0x2
   00 22 

public static final scala.actors.Future future(scala.Function0);
  Code:
   Stack=2, Locals=1, Args_size=1
   0:	getstatic	#11; //Field scala/actors/Futures$.MODULE$:Lscala/actors/Futures$;
   3:	aload_0
   4:	invokevirtual	#38; //Method scala/actors/Futures$.future:(Lscala/Function0;)Lscala/actors/Future;
   7:	areturn
  Signature: length = 0x2
   00 27 

public static final scala.actors.scheduler.DefaultExecutorScheduler scala$actors$Futures$$sched();
  Code:
   Stack=1, Locals=0, Args_size=0
   0:	getstatic	#11; //Field scala/actors/Futures$.MODULE$:Lscala/actors/Futures$;
   3:	invokevirtual	#43; //Method scala/actors/Futures$.scala$actors$Futures$$sched:()Lscala/actors/scheduler/DefaultExecutorScheduler;
   6:	areturn

}

