Compiled from "Future.scala"
public final class scala.actors.Futures$$anonfun$3 extends java.lang.Object implements scala.Function1,scala.ScalaObject,java.io.Serializable
  SourceFile: "Future.scala"
  Scala: length = 0x
   
  InnerClass: 
   public final #111= #9 of #110; //$anonfun$3=class scala/actors/Futures$$anonfun$3 of class scala/actors/Futures
  minor version: 0
  major version: 49
  Constant pool:
const #1 = Asciz	SourceFile;
const #2 = Asciz	Future.scala;
const #3 = Asciz	<clinit>;
const #4 = Asciz	()V;
const #5 = Asciz	Code;
const #6 = Asciz	serialVersionUID;
const #7 = Asciz	J;
const #8 = Asciz	scala/actors/Futures$$anonfun$3;
const #9 = class	#8;	//  scala/actors/Futures$$anonfun$3
const #10 = NameAndType	#6:#7;//  serialVersionUID:J
const #11 = Field	#9.#10;	//  scala/actors/Futures$$anonfun$3.serialVersionUID:J
const #12 = Asciz	resultsMap$1;
const #13 = Asciz	Lscala/runtime/ObjectRef;;
const #14 = Asciz	<init>;
const #15 = Asciz	(Lscala/runtime/ObjectRef;)V;
const #16 = Asciz	LineNumberTable;
const #17 = NameAndType	#12:#13;//  resultsMap$1:Lscala/runtime/ObjectRef;
const #18 = Field	#9.#17;	//  scala/actors/Futures$$anonfun$3.resultsMap$1:Lscala/runtime/ObjectRef;
const #19 = Asciz	java/lang/Object;
const #20 = class	#19;	//  java/lang/Object
const #21 = NameAndType	#14:#4;//  "<init>":()V
const #22 = Method	#20.#21;	//  java/lang/Object."<init>":()V
const #23 = Asciz	scala/Function1$class;
const #24 = class	#23;	//  scala/Function1$class
const #25 = Asciz	$init$;
const #26 = Asciz	(Lscala/Function1;)V;
const #27 = NameAndType	#25:#26;//  $init$:(Lscala/Function1;)V
const #28 = Method	#24.#27;	//  scala/Function1$class.$init$:(Lscala/Function1;)V
const #29 = Asciz	apply;
const #30 = Asciz	(Ljava/lang/Object;)Ljava/lang/Object;;
const #31 = Asciz	scala/Tuple2;
const #32 = class	#31;	//  scala/Tuple2
const #33 = Asciz	(Lscala/Tuple2;)Z;
const #34 = NameAndType	#29:#33;//  apply:(Lscala/Tuple2;)Z
const #35 = Method	#9.#34;	//  scala/actors/Futures$$anonfun$3.apply:(Lscala/Tuple2;)Z
const #36 = Asciz	scala/runtime/BoxesRunTime;
const #37 = class	#36;	//  scala/runtime/BoxesRunTime
const #38 = Asciz	boxToBoolean;
const #39 = Asciz	(Z)Ljava/lang/Boolean;;
const #40 = NameAndType	#38:#39;//  boxToBoolean:(Z)Ljava/lang/Boolean;
const #41 = Method	#37.#40;	//  scala/runtime/BoxesRunTime.boxToBoolean:(Z)Ljava/lang/Boolean;
const #42 = Asciz	this;
const #43 = Asciz	Lscala/actors/Futures$$anonfun$3;;
const #44 = Asciz	v1;
const #45 = Asciz	Ljava/lang/Object;;
const #46 = Asciz	LocalVariableTable;
const #47 = Asciz	_2;
const #48 = Asciz	()Ljava/lang/Object;;
const #49 = NameAndType	#47:#48;//  _2:()Ljava/lang/Object;
const #50 = Method	#32.#49;	//  scala/Tuple2._2:()Ljava/lang/Object;
const #51 = Asciz	scala/actors/Future;
const #52 = class	#51;	//  scala/actors/Future
const #53 = Asciz	isSet;
const #54 = Asciz	()Z;
const #55 = NameAndType	#53:#54;//  isSet:()Z
const #56 = Method	#52.#55;	//  scala/actors/Future.isSet:()Z
const #57 = Asciz	scala/runtime/ObjectRef;
const #58 = class	#57;	//  scala/runtime/ObjectRef
const #59 = Asciz	elem;
const #60 = NameAndType	#59:#45;//  elem:Ljava/lang/Object;
const #61 = Field	#58.#60;	//  scala/runtime/ObjectRef.elem:Ljava/lang/Object;
const #62 = Asciz	scala/collection/mutable/Map;
const #63 = class	#62;	//  scala/collection/mutable/Map
const #64 = Asciz	_1;
const #65 = NameAndType	#64:#48;//  _1:()Ljava/lang/Object;
const #66 = Method	#32.#65;	//  scala/Tuple2._1:()Ljava/lang/Object;
const #67 = Asciz	scala/Some;
const #68 = class	#67;	//  scala/Some
const #69 = Asciz	scala/Function0;
const #70 = class	#69;	//  scala/Function0
const #71 = NameAndType	#29:#48;//  apply:()Ljava/lang/Object;
const #72 = InterfaceMethod	#70.#71;	//  scala/Function0.apply:()Ljava/lang/Object;
const #73 = Asciz	(Ljava/lang/Object;)V;
const #74 = NameAndType	#14:#73;//  "<init>":(Ljava/lang/Object;)V
const #75 = Method	#68.#74;	//  scala/Some."<init>":(Ljava/lang/Object;)V
const #76 = Asciz	scala/collection/mutable/MapLike;
const #77 = class	#76;	//  scala/collection/mutable/MapLike
const #78 = Asciz	update;
const #79 = Asciz	(Ljava/lang/Object;Ljava/lang/Object;)V;
const #80 = NameAndType	#78:#79;//  update:(Ljava/lang/Object;Ljava/lang/Object;)V
const #81 = InterfaceMethod	#77.#80;	//  scala/collection/mutable/MapLike.update:(Ljava/lang/Object;Ljava/lang/Object;)V
const #82 = Asciz	scala/None$;
const #83 = class	#82;	//  scala/None$
const #84 = Asciz	MODULE$;
const #85 = Asciz	Lscala/None$;;
const #86 = NameAndType	#84:#85;//  MODULE$:Lscala/None$;
const #87 = Field	#83.#86;	//  scala/None$.MODULE$:Lscala/None$;
const #88 = Asciz	p;
const #89 = Asciz	Lscala/Tuple2;;
const #90 = Asciz	(Lscala/Tuple2<Ljava/lang/Integer;Lscala/actors/Future<Ljava/lang/Object;>;>;)Z;
const #91 = Asciz	Signature;
const #92 = Asciz	andThen;
const #93 = Asciz	(Lscala/Function1;)Lscala/Function1;;
const #94 = Asciz	(Lscala/Function1;Lscala/Function1;)Lscala/Function1;;
const #95 = NameAndType	#92:#94;//  andThen:(Lscala/Function1;Lscala/Function1;)Lscala/Function1;
const #96 = Method	#24.#95;	//  scala/Function1$class.andThen:(Lscala/Function1;Lscala/Function1;)Lscala/Function1;
const #97 = Asciz	g;
const #98 = Asciz	Lscala/Function1;;
const #99 = Asciz	compose;
const #100 = NameAndType	#99:#94;//  compose:(Lscala/Function1;Lscala/Function1;)Lscala/Function1;
const #101 = Method	#24.#100;	//  scala/Function1$class.compose:(Lscala/Function1;Lscala/Function1;)Lscala/Function1;
const #102 = Asciz	toString;
const #103 = Asciz	()Ljava/lang/String;;
const #104 = Asciz	(Lscala/Function1;)Ljava/lang/String;;
const #105 = NameAndType	#102:#104;//  toString:(Lscala/Function1;)Ljava/lang/String;
const #106 = Method	#24.#105;	//  scala/Function1$class.toString:(Lscala/Function1;)Ljava/lang/String;
const #107 = Asciz	Scala;
const #108 = Asciz	InnerClasses;
const #109 = Asciz	scala/actors/Futures;
const #110 = class	#109;	//  scala/actors/Futures
const #111 = Asciz	$anonfun$3;
const #112 = Asciz	scala/Function1;
const #113 = class	#112;	//  scala/Function1
const #114 = Asciz	scala/ScalaObject;
const #115 = class	#114;	//  scala/ScalaObject
const #116 = Asciz	java/io/Serializable;
const #117 = class	#116;	//  java/io/Serializable

{
public static final long serialVersionUID;

public static {};
  Code:
   Stack=2, Locals=0, Args_size=0
   0:	lconst_0
   1:	putstatic	#11; //Field serialVersionUID:J
   4:	return

public scala.actors.Futures$$anonfun$3(scala.runtime.ObjectRef);
  Code:
   Stack=2, Locals=2, Args_size=2
   0:	aload_0
   1:	aload_1
   2:	putfield	#18; //Field resultsMap$1:Lscala/runtime/ObjectRef;
   5:	aload_0
   6:	invokespecial	#22; //Method java/lang/Object."<init>":()V
   9:	aload_0
   10:	invokestatic	#28; //Method scala/Function1$class.$init$:(Lscala/Function1;)V
   13:	return
  LineNumberTable: 
   line 93: 0


public final java.lang.Object apply(java.lang.Object);
  Code:
   Stack=2, Locals=3, Args_size=2
   0:	aload_0
   1:	aload_1
   2:	checkcast	#32; //class scala/Tuple2
   5:	invokevirtual	#35; //Method apply:(Lscala/Tuple2;)Z
   8:	istore_2
   9:	iload_2
   10:	invokestatic	#41; //Method scala/runtime/BoxesRunTime.boxToBoolean:(Z)Ljava/lang/Boolean;
   13:	areturn
  LineNumberTable: 
   line 93: 0

  LocalVariableTable: 
   Start  Length  Slot  Name   Signature
   0      14      0    this       Lscala/actors/Futures$$anonfun$3;
   0      14      1    v1       Ljava/lang/Object;


public final boolean apply(scala.Tuple2);
  Code:
   Stack=5, Locals=2, Args_size=2
   0:	aload_1
   1:	invokevirtual	#50; //Method scala/Tuple2._2:()Ljava/lang/Object;
   4:	checkcast	#52; //class scala/actors/Future
   7:	invokevirtual	#56; //Method scala/actors/Future.isSet:()Z
   10:	ifeq	55
   13:	aload_0
   14:	getfield	#18; //Field resultsMap$1:Lscala/runtime/ObjectRef;
   17:	getfield	#61; //Field scala/runtime/ObjectRef.elem:Ljava/lang/Object;
   20:	checkcast	#63; //class scala/collection/mutable/Map
   23:	aload_1
   24:	invokevirtual	#66; //Method scala/Tuple2._1:()Ljava/lang/Object;
   27:	new	#68; //class scala/Some
   30:	dup
   31:	aload_1
   32:	invokevirtual	#50; //Method scala/Tuple2._2:()Ljava/lang/Object;
   35:	checkcast	#70; //class scala/Function0
   38:	invokeinterface	#72,  1; //InterfaceMethod scala/Function0.apply:()Ljava/lang/Object;
   43:	invokespecial	#75; //Method scala/Some."<init>":(Ljava/lang/Object;)V
   46:	invokeinterface	#81,  3; //InterfaceMethod scala/collection/mutable/MapLike.update:(Ljava/lang/Object;Ljava/lang/Object;)V
   51:	iconst_0
   52:	goto	78
   55:	aload_0
   56:	getfield	#18; //Field resultsMap$1:Lscala/runtime/ObjectRef;
   59:	getfield	#61; //Field scala/runtime/ObjectRef.elem:Ljava/lang/Object;
   62:	checkcast	#63; //class scala/collection/mutable/Map
   65:	aload_1
   66:	invokevirtual	#66; //Method scala/Tuple2._1:()Ljava/lang/Object;
   69:	getstatic	#87; //Field scala/None$.MODULE$:Lscala/None$;
   72:	invokeinterface	#81,  3; //InterfaceMethod scala/collection/mutable/MapLike.update:(Ljava/lang/Object;Ljava/lang/Object;)V
   77:	iconst_1
   78:	ireturn
  LineNumberTable: 
   line 94: 0
   line 95: 55
   line 94: 78

  LocalVariableTable: 
   Start  Length  Slot  Name   Signature
   0      79      0    this       Lscala/actors/Futures$$anonfun$3;
   0      79      1    p       Lscala/Tuple2;

  Signature: length = 0x2
   00 5A 

public scala.Function1 andThen(scala.Function1);
  Code:
   Stack=2, Locals=2, Args_size=2
   0:	aload_0
   1:	aload_1
   2:	invokestatic	#96; //Method scala/Function1$class.andThen:(Lscala/Function1;Lscala/Function1;)Lscala/Function1;
   5:	areturn
  LineNumberTable: 
   line 93: 0

  LocalVariableTable: 
   Start  Length  Slot  Name   Signature
   0      6      0    this       Lscala/actors/Futures$$anonfun$3;
   0      6      1    g       Lscala/Function1;


public scala.Function1 compose(scala.Function1);
  Code:
   Stack=2, Locals=2, Args_size=2
   0:	aload_0
   1:	aload_1
   2:	invokestatic	#101; //Method scala/Function1$class.compose:(Lscala/Function1;Lscala/Function1;)Lscala/Function1;
   5:	areturn
  LineNumberTable: 
   line 93: 0

  LocalVariableTable: 
   Start  Length  Slot  Name   Signature
   0      6      0    this       Lscala/actors/Futures$$anonfun$3;
   0      6      1    g       Lscala/Function1;


public java.lang.String toString();
  Code:
   Stack=1, Locals=1, Args_size=1
   0:	aload_0
   1:	invokestatic	#106; //Method scala/Function1$class.toString:(Lscala/Function1;)Ljava/lang/String;
   4:	areturn
  LineNumberTable: 
   line 93: 0


}

