Compiled from "Future.scala"
public final class scala.actors.Futures$FutureActor$$anonfun$act$2$$anonfun$apply$1$$anonfun$apply$2 extends java.lang.Object implements scala.PartialFunction,java.io.Serializable
  SourceFile: "Future.scala"
  Scala: length = 0x
   
  InnerClass: 
   public FutureActor=class scala/actors/Futures$FutureActor of class scala/actors/Futures
   public final $anonfun$act$2=class scala/actors/Futures$FutureActor$$anonfun$act$2 of class scala/actors/Futures$FutureActor
   public final $anonfun$apply$1=class scala/actors/Futures$FutureActor$$anonfun$act$2$$anonfun$apply$1 of class scala/actors/Futures$FutureActor$$anonfun$act$2
   public final $anonfun$apply$2=class scala/actors/Futures$FutureActor$$anonfun$act$2$$anonfun$apply$1$$anonfun$apply$2 of class scala/actors/Futures$FutureActor$$anonfun$act$2$$anonfun$apply$1
  minor version: 0
  major version: 49
  Constant pool:
Asciz	SourceFile;
Asciz	Future.scala;
Asciz	<clinit>;
Asciz	()V;
Asciz	Code;
Asciz	serialVersionUID;
Asciz	J;
Asciz	scala/actors/Futures$FutureActor$$anonfun$act$2$$anonfun$apply$1$$anonfun$apply$2;
class	scala/actors/Futures$FutureActor$$anonfun$act$2$$anonfun$apply$1$$anonfun$apply$2
NameAndType	serialVersionUID:J
Field	scala/actors/Futures$FutureActor$$anonfun$act$2$$anonfun$apply$1$$anonfun$apply$2.serialVersionUID:J
Asciz	$outer;
Asciz	Lscala/actors/Futures$FutureActor$$anonfun$act$2$$anonfun$apply$1;;
Asciz	orElse;
Asciz	(Lscala/PartialFunction;)Lscala/PartialFunction;;
Asciz	LineNumberTable;
Asciz	scala/PartialFunction$class;
class	scala/PartialFunction$class
Asciz	(Lscala/PartialFunction;Lscala/PartialFunction;)Lscala/PartialFunction;;
NameAndType	orElse:(Lscala/PartialFunction;Lscala/PartialFunction;)Lscala/PartialFunction;
Method	scala/PartialFunction$class.orElse:(Lscala/PartialFunction;Lscala/PartialFunction;)Lscala/PartialFunction;
Asciz	this;
Asciz	Lscala/actors/Futures$FutureActor$$anonfun$act$2$$anonfun$apply$1$$anonfun$apply$2;;
Asciz	that;
Asciz	Lscala/PartialFunction;;
Asciz	LocalVariableTable;
Asciz	andThen;
Asciz	(Lscala/Function1;)Lscala/PartialFunction;;
Asciz	(Lscala/PartialFunction;Lscala/Function1;)Lscala/PartialFunction;;
NameAndType	andThen:(Lscala/PartialFunction;Lscala/Function1;)Lscala/PartialFunction;
Method	scala/PartialFunction$class.andThen:(Lscala/PartialFunction;Lscala/Function1;)Lscala/PartialFunction;
Asciz	k;
Asciz	Lscala/Function1;;
Asciz	lift;
Asciz	()Lscala/Function1;;
Asciz	(Lscala/PartialFunction;)Lscala/Function1;;
NameAndType	lift:(Lscala/PartialFunction;)Lscala/Function1;
Method	scala/PartialFunction$class.lift:(Lscala/PartialFunction;)Lscala/Function1;
Asciz	toString;
Asciz	()Ljava/lang/String;;
Asciz	scala/Function1$class;
class	scala/Function1$class
Asciz	(Lscala/Function1;)Ljava/lang/String;;
NameAndType	toString:(Lscala/Function1;)Ljava/lang/String;
Method	scala/Function1$class.toString:(Lscala/Function1;)Ljava/lang/String;
Asciz	compose;
Asciz	(Lscala/Function1;)Lscala/Function1;;
Asciz	(Lscala/Function1;Lscala/Function1;)Lscala/Function1;;
NameAndType	compose:(Lscala/Function1;Lscala/Function1;)Lscala/Function1;
Method	scala/Function1$class.compose:(Lscala/Function1;Lscala/Function1;)Lscala/Function1;
Asciz	g;
Asciz	apply;
Asciz	(Ljava/lang/Object;)V;
Asciz	scala/actors/Futures$Eval$;
class	scala/actors/Futures$Eval$
Asciz	MODULE$;
Asciz	Lscala/actors/Futures$Eval$;;
NameAndType	MODULE$:Lscala/actors/Futures$Eval$;
Field	scala/actors/Futures$Eval$.MODULE$:Lscala/actors/Futures$Eval$;
Asciz	java/lang/Object;
class	java/lang/Object
Asciz	equals;
Asciz	(Ljava/lang/Object;)Z;
NameAndType	equals:(Ljava/lang/Object;)Z
Method	java/lang/Object.equals:(Ljava/lang/Object;)Z
NameAndType	$outer:Lscala/actors/Futures$FutureActor$$anonfun$act$2$$anonfun$apply$1;
Field	scala/actors/Futures$FutureActor$$anonfun$act$2$$anonfun$apply$1$$anonfun$apply$2.$outer:Lscala/actors/Futures$FutureActor$$anonfun$act$2$$anonfun$apply$1;
Asciz	scala/actors/Futures$FutureActor$$anonfun$act$2$$anonfun$apply$1;
class	scala/actors/Futures$FutureActor$$anonfun$act$2$$anonfun$apply$1
Asciz	Lscala/actors/Futures$FutureActor$$anonfun$act$2;;
NameAndType	$outer:Lscala/actors/Futures$FutureActor$$anonfun$act$2;
Field	scala/actors/Futures$FutureActor$$anonfun$act$2$$anonfun$apply$1.$outer:Lscala/actors/Futures$FutureActor$$anonfun$act$2;
Asciz	scala/actors/Futures$FutureActor$$anonfun$act$2;
class	scala/actors/Futures$FutureActor$$anonfun$act$2
Asciz	Lscala/actors/Futures$FutureActor;;
NameAndType	$outer:Lscala/actors/Futures$FutureActor;
Field	scala/actors/Futures$FutureActor$$anonfun$act$2.$outer:Lscala/actors/Futures$FutureActor;
Asciz	scala/runtime/BoxedUnit;
class	scala/runtime/BoxedUnit
Asciz	UNIT;
Asciz	Lscala/runtime/BoxedUnit;;
NameAndType	UNIT:Lscala/runtime/BoxedUnit;
Field	scala/runtime/BoxedUnit.UNIT:Lscala/runtime/BoxedUnit;
Asciz	scala/actors/ReplyReactor;
class	scala/actors/ReplyReactor
Asciz	reply;
NameAndType	reply:(Ljava/lang/Object;)V
InterfaceMethod	scala/actors/ReplyReactor.reply:(Ljava/lang/Object;)V
Asciz	scala/MatchError;
class	scala/MatchError
Asciz	<init>;
NameAndType	"<init>":(Ljava/lang/Object;)V
Method	scala/MatchError."<init>":(Ljava/lang/Object;)V
Asciz	isDefinedAt;
Asciz	scala/PartialFunction;
class	scala/PartialFunction
NameAndType	andThen:(Lscala/Function1;)Lscala/PartialFunction;
InterfaceMethod	scala/PartialFunction.andThen:(Lscala/Function1;)Lscala/PartialFunction;
Asciz	(Ljava/lang/Object;)Ljava/lang/Object;;
NameAndType	apply:(Ljava/lang/Object;)V
Method	scala/actors/Futures$FutureActor$$anonfun$act$2$$anonfun$apply$1$$anonfun$apply$2.apply:(Ljava/lang/Object;)V
Asciz	v1;
Asciz	Ljava/lang/Object;;
Asciz	(Lscala/actors/Futures$FutureActor$$anonfun$act$2$$anonfun$apply$1;)V;
Asciz	java/lang/NullPointerException;
class	java/lang/NullPointerException
NameAndType	"<init>":()V
Method	java/lang/NullPointerException."<init>":()V
Method	java/lang/Object."<init>":()V
Asciz	$init$;
Asciz	(Lscala/Function1;)V;
NameAndType	$init$:(Lscala/Function1;)V
Method	scala/Function1$class.$init$:(Lscala/Function1;)V
Asciz	(Lscala/PartialFunction;)V;
NameAndType	$init$:(Lscala/PartialFunction;)V
Method	scala/PartialFunction$class.$init$:(Lscala/PartialFunction;)V
Asciz	(Lscala/actors/Futures$FutureActor<TT;>.$anonfun$act$2.$anonfun$apply$1;)V;
Asciz	Signature;
Asciz	Scala;
Asciz	InnerClasses;
Asciz	scala/actors/Futures$FutureActor;
class	scala/actors/Futures$FutureActor
Asciz	scala/actors/Futures;
class	scala/actors/Futures
Asciz	FutureActor;
Asciz	$anonfun$act$2;
Asciz	$anonfun$apply$1;
Asciz	$anonfun$apply$2;
Asciz	java/io/Serializable;
class	java/io/Serializable

{
public static final long serialVersionUID;
  Signature: J

public final scala.actors.Futures$FutureActor$$anonfun$act$2$$anonfun$apply$1 $outer;
  Signature: Lscala/actors/Futures$FutureActor$$anonfun$act$2$$anonfun$apply$1;

public static {};
  Signature: ()V
  Code:
   Stack=2, Locals=0, Args_size=0
	lconst_0
	putstatic	Field serialVersionUID:J
	return
  Labels:

public scala.PartialFunction orElse(scala.PartialFunction);
  Signature: (Lscala/PartialFunction;)Lscala/PartialFunction;
  Code:
   Stack=2, Locals=2, Args_size=2
	aload_0
	aload_1
	invokestatic	Method scala/PartialFunction$class.orElse:(Lscala/PartialFunction;Lscala/PartialFunction;)Lscala/PartialFunction;
	areturn
  Labels:
  LocalVariableTable: 
   Start  Length  Slot  Name   Signature
   0      6      0    this       Lscala/actors/Futures$FutureActor$$anonfun$act$2$$anonfun$apply$1$$anonfun$apply$2;
   0      6      1    that       Lscala/PartialFunction;


public scala.PartialFunction andThen(scala.Function1);
  Signature: (Lscala/Function1;)Lscala/PartialFunction;
  Code:
   Stack=2, Locals=2, Args_size=2
	aload_0
	aload_1
	invokestatic	Method scala/PartialFunction$class.andThen:(Lscala/PartialFunction;Lscala/Function1;)Lscala/PartialFunction;
	areturn
  Labels:
  LocalVariableTable: 
   Start  Length  Slot  Name   Signature
   0      6      0    this       Lscala/actors/Futures$FutureActor$$anonfun$act$2$$anonfun$apply$1$$anonfun$apply$2;
   0      6      1    k       Lscala/Function1;


public scala.Function1 lift();
  Signature: ()Lscala/Function1;
  Code:
   Stack=1, Locals=1, Args_size=1
	aload_0
	invokestatic	Method scala/PartialFunction$class.lift:(Lscala/PartialFunction;)Lscala/Function1;
	areturn
  Labels:

public java.lang.String toString();
  Signature: ()Ljava/lang/String;
  Code:
   Stack=1, Locals=1, Args_size=1
	aload_0
	invokestatic	Method scala/Function1$class.toString:(Lscala/Function1;)Ljava/lang/String;
	areturn
  Labels:

public scala.Function1 compose(scala.Function1);
  Signature: (Lscala/Function1;)Lscala/Function1;
  Code:
   Stack=2, Locals=2, Args_size=2
	aload_0
	aload_1
	invokestatic	Method scala/Function1$class.compose:(Lscala/Function1;Lscala/Function1;)Lscala/Function1;
	areturn
  Labels:
  LocalVariableTable: 
   Start  Length  Slot  Name   Signature
   0      6      0    this       Lscala/actors/Futures$FutureActor$$anonfun$act$2$$anonfun$apply$1$$anonfun$apply$2;
   0      6      1    g       Lscala/Function1;


public final void apply(java.lang.Object);
  Signature: (Ljava/lang/Object;)V
  Code:
   Stack=3, Locals=4, Args_size=2
	getstatic	Field scala/actors/Futures$Eval$.MODULE$:Lscala/actors/Futures$Eval$;
	dup
	ifnonnull	l1 // aload_1
	pop
	aload_1
	ifnull	l2 // aload_0
	goto	l3 // new
l1	aload_1
	invokevirtual	Method java/lang/Object.equals:(Ljava/lang/Object;)Z
	ifeq	l3 // new
l2	aload_0
	getfield	Field $outer:Lscala/actors/Futures$FutureActor$$anonfun$act$2$$anonfun$apply$1;
	astore_2
	aload_2
	getfield	Field scala/actors/Futures$FutureActor$$anonfun$act$2$$anonfun$apply$1.$outer:Lscala/actors/Futures$FutureActor$$anonfun$act$2;
	astore_3
	aload_3
	getfield	Field scala/actors/Futures$FutureActor$$anonfun$act$2.$outer:Lscala/actors/Futures$FutureActor;
	getstatic	Field scala/runtime/BoxedUnit.UNIT:Lscala/runtime/BoxedUnit;
	invokeinterface	InterfaceMethod scala/actors/ReplyReactor.reply:(Ljava/lang/Object;)V
	return
l3	new	class scala/MatchError
	dup
	aload_1
	invokespecial	Method scala/MatchError."<init>":(Ljava/lang/Object;)V
	athrow
  Labels:
   	l1 = 15 // aload_1
   	l2 = 22 // aload_0
   	l3 = 45 // new
  LocalVariableTable: 
   Start  Length  Slot  Name   Signature
   0      54      0    this       Lscala/actors/Futures$FutureActor$$anonfun$act$2$$anonfun$apply$1$$anonfun$apply$2;


public final boolean isDefinedAt(java.lang.Object);
  Signature: (Ljava/lang/Object;)Z
  Code:
   Stack=2, Locals=2, Args_size=2
	getstatic	Field scala/actors/Futures$Eval$.MODULE$:Lscala/actors/Futures$Eval$;
	dup
	ifnonnull	l1 // aload_1
	pop
	aload_1
	ifnull	l2 // iconst_1
	goto	l3 // iconst_0
l1	aload_1
	invokevirtual	Method java/lang/Object.equals:(Ljava/lang/Object;)Z
	ifeq	l3 // iconst_0
l2	iconst_1
	goto	l4 // ireturn
l3	iconst_0
l4	ireturn
  Labels:
   	l1 = 15 // aload_1
   	l2 = 22 // iconst_1
   	l3 = 26 // iconst_0
   	l4 = 27 // ireturn

public scala.Function1 andThen(scala.Function1);
  Signature: (Lscala/Function1;)Lscala/Function1;
  Code:
   Stack=2, Locals=2, Args_size=2
	aload_0
	aload_1
	invokeinterface	InterfaceMethod scala/PartialFunction.andThen:(Lscala/Function1;)Lscala/PartialFunction;
	areturn
  Labels:
  LocalVariableTable: 
   Start  Length  Slot  Name   Signature
   0      8      0    this       Lscala/actors/Futures$FutureActor$$anonfun$act$2$$anonfun$apply$1$$anonfun$apply$2;
   0      8      1    g       Lscala/Function1;


public final java.lang.Object apply(java.lang.Object);
  Signature: (Ljava/lang/Object;)Ljava/lang/Object;
  Code:
   Stack=2, Locals=2, Args_size=2
	aload_0
	aload_1
	invokevirtual	Method apply:(Ljava/lang/Object;)V
	getstatic	Field scala/runtime/BoxedUnit.UNIT:Lscala/runtime/BoxedUnit;
	areturn
  Labels:
  LocalVariableTable: 
   Start  Length  Slot  Name   Signature
   0      9      0    this       Lscala/actors/Futures$FutureActor$$anonfun$act$2$$anonfun$apply$1$$anonfun$apply$2;
   0      9      1    v1       Ljava/lang/Object;


public scala.actors.Futures$FutureActor$$anonfun$act$2$$anonfun$apply$1$$anonfun$apply$2(scala.actors.Futures$FutureActor$$anonfun$act$2$$anonfun$apply$1);
  Signature: (Lscala/actors/Futures$FutureActor$$anonfun$act$2$$anonfun$apply$1;)V
  Code:
   Stack=2, Locals=2, Args_size=2
	aload_1
	ifnonnull	l1 // aload_0
	new	class java/lang/NullPointerException
	dup
	invokespecial	Method java/lang/NullPointerException."<init>":()V
	athrow
l1	aload_0
	aload_1
	putfield	Field $outer:Lscala/actors/Futures$FutureActor$$anonfun$act$2$$anonfun$apply$1;
	aload_0
	invokespecial	Method java/lang/Object."<init>":()V
	aload_0
	invokestatic	Method scala/Function1$class.$init$:(Lscala/Function1;)V
	aload_0
	invokestatic	Method scala/PartialFunction$class.$init$:(Lscala/PartialFunction;)V
	return
  Labels:
   	l1 = 12 // aload_0
  LocalVariableTable: 
   Start  Length  Slot  Name   Signature
   0      30      0    this       Lscala/actors/Futures$FutureActor$$anonfun$act$2$$anonfun$apply$1$$anonfun$apply$2;
   0      30      1    $outer       Lscala/actors/Futures$FutureActor$$anonfun$act$2$$anonfun$apply$1;

  Signature: length = 0x2
   00 75 

}

