Compiled from "Future.scala"
public final class scala.actors.Futures$FutureActor$$anonfun$act$1 extends scala.runtime.AbstractFunction0$mcV$sp implements java.io.Serializable
  SourceFile: "Future.scala"
  Scala: length = 0x
   
  InnerClass: 
   public FutureActor=class scala/actors/Futures$FutureActor of class scala/actors/Futures
   public final $anonfun$act$1=class scala/actors/Futures$FutureActor$$anonfun$act$1 of class scala/actors/Futures$FutureActor
  minor version: 0
  major version: 49
  Constant pool:
Asciz	SourceFile;
Asciz	Future.scala;
Asciz	<clinit>;
Asciz	()V;
Asciz	Code;
Asciz	serialVersionUID;
Asciz	J;
Asciz	scala/actors/Futures$FutureActor$$anonfun$act$1;
class	scala/actors/Futures$FutureActor$$anonfun$act$1
NameAndType	serialVersionUID:J
Field	scala/actors/Futures$FutureActor$$anonfun$act$1.serialVersionUID:J
Asciz	$outer;
Asciz	Lscala/actors/Futures$FutureActor;;
Asciz	res$1;
Asciz	Lscala/concurrent/SyncVar;;
Asciz	apply;
Asciz	LineNumberTable;
NameAndType	$outer:Lscala/actors/Futures$FutureActor;
Field	scala/actors/Futures$FutureActor$$anonfun$act$1.$outer:Lscala/actors/Futures$FutureActor;
Asciz	scala/actors/Futures$FutureActor;
class	scala/actors/Futures$FutureActor
Asciz	scala$actors$Futures$FutureActor$$fun;
Asciz	Lscala/Function1;;
NameAndType	scala$actors$Futures$FutureActor$$fun:Lscala/Function1;
Field	scala/actors/Futures$FutureActor.scala$actors$Futures$FutureActor$$fun:Lscala/Function1;
NameAndType	res$1:Lscala/concurrent/SyncVar;
Field	scala/actors/Futures$FutureActor$$anonfun$act$1.res$1:Lscala/concurrent/SyncVar;
Asciz	scala/Function1;
class	scala/Function1
Asciz	(Ljava/lang/Object;)Ljava/lang/Object;;
NameAndType	apply:(Ljava/lang/Object;)Ljava/lang/Object;
InterfaceMethod	scala/Function1.apply:(Ljava/lang/Object;)Ljava/lang/Object;
Asciz	apply$mcV$sp;
Asciz	()Ljava/lang/Object;;
NameAndType	apply:()V
Method	scala/actors/Futures$FutureActor$$anonfun$act$1.apply:()V
Asciz	scala/runtime/BoxedUnit;
class	scala/runtime/BoxedUnit
Asciz	UNIT;
Asciz	Lscala/runtime/BoxedUnit;;
NameAndType	UNIT:Lscala/runtime/BoxedUnit;
Field	scala/runtime/BoxedUnit.UNIT:Lscala/runtime/BoxedUnit;
Asciz	<init>;
Asciz	(Lscala/actors/Futures$FutureActor;Lscala/concurrent/SyncVar;)V;
Asciz	java/lang/NullPointerException;
class	java/lang/NullPointerException
NameAndType	"<init>":()V
Method	java/lang/NullPointerException."<init>":()V
Asciz	scala/runtime/AbstractFunction0$mcV$sp;
class	scala/runtime/AbstractFunction0$mcV$sp
Method	scala/runtime/AbstractFunction0$mcV$sp."<init>":()V
Asciz	this;
Asciz	Lscala/actors/Futures$FutureActor$$anonfun$act$1;;
Asciz	LocalVariableTable;
Asciz	(Lscala/actors/Futures$FutureActor<TT;>;)V;
Asciz	Signature;
Asciz	Scala;
Asciz	InnerClasses;
Asciz	scala/actors/Futures;
class	scala/actors/Futures
Asciz	FutureActor;
Asciz	$anonfun$act$1;
Asciz	java/io/Serializable;
class	java/io/Serializable

{
public static final long serialVersionUID;
  Signature: J

public final scala.actors.Futures$FutureActor $outer;
  Signature: Lscala/actors/Futures$FutureActor;

public final scala.concurrent.SyncVar res$1;
  Signature: Lscala/concurrent/SyncVar;

public static {};
  Signature: ()V
  Code:
   Stack=2, Locals=0, Args_size=0
	lconst_0
	putstatic	Field serialVersionUID:J
	return
  Labels:

public final void apply();
  Signature: ()V
  Code:
   Stack=2, Locals=1, Args_size=1
	aload_0
	getfield	Field $outer:Lscala/actors/Futures$FutureActor;
	getfield	Field scala/actors/Futures$FutureActor.scala$actors$Futures$FutureActor$$fun:Lscala/Function1;
	aload_0
	getfield	Field res$1:Lscala/concurrent/SyncVar;
	invokeinterface	InterfaceMethod scala/Function1.apply:(Ljava/lang/Object;)Ljava/lang/Object;
	pop
	return
  Labels:

public void apply$mcV$sp();
  Signature: ()V
  Code:
   Stack=2, Locals=1, Args_size=1
	aload_0
	getfield	Field $outer:Lscala/actors/Futures$FutureActor;
	getfield	Field scala/actors/Futures$FutureActor.scala$actors$Futures$FutureActor$$fun:Lscala/Function1;
	aload_0
	getfield	Field res$1:Lscala/concurrent/SyncVar;
	invokeinterface	InterfaceMethod scala/Function1.apply:(Ljava/lang/Object;)Ljava/lang/Object;
	pop
	return
  Labels:

public final java.lang.Object apply();
  Signature: ()Ljava/lang/Object;
  Code:
   Stack=1, Locals=1, Args_size=1
	aload_0
	invokevirtual	Method apply:()V
	getstatic	Field scala/runtime/BoxedUnit.UNIT:Lscala/runtime/BoxedUnit;
	areturn
  Labels:

public scala.actors.Futures$FutureActor$$anonfun$act$1(scala.actors.Futures$FutureActor, scala.concurrent.SyncVar);
  Signature: (Lscala/actors/Futures$FutureActor;Lscala/concurrent/SyncVar;)V
  Code:
   Stack=2, Locals=3, Args_size=3
	aload_1
	ifnonnull	l1 // aload_0
	new	class java/lang/NullPointerException
	dup
	invokespecial	Method java/lang/NullPointerException."<init>":()V
	athrow
l1	aload_0
	aload_1
	putfield	Field $outer:Lscala/actors/Futures$FutureActor;
	aload_0
	aload_2
	putfield	Field res$1:Lscala/concurrent/SyncVar;
	aload_0
	invokespecial	Method scala/runtime/AbstractFunction0$mcV$sp."<init>":()V
	return
  Labels:
   	l1 = 12 // aload_0
  LocalVariableTable: 
   Start  Length  Slot  Name   Signature
   0      27      0    this       Lscala/actors/Futures$FutureActor$$anonfun$act$1;
   0      27      1    $outer       Lscala/actors/Futures$FutureActor;

  Signature: length = 0x2
   00 37 

}

