Compiled from "Future.scala"
public final class scala.actors.Futures$FutureActor$$anonfun$act$2$$anonfun$apply$1 extends scala.runtime.AbstractFunction0 implements java.io.Serializable
  SourceFile: "Future.scala"
  Scala: length = 0x
   
  InnerClass: 
   public FutureActor=class scala/actors/Futures$FutureActor of class scala/actors/Futures
   public final $anonfun$act$2=class scala/actors/Futures$FutureActor$$anonfun$act$2 of class scala/actors/Futures$FutureActor
   public final $anonfun$apply$1=class scala/actors/Futures$FutureActor$$anonfun$act$2$$anonfun$apply$1 of class scala/actors/Futures$FutureActor$$anonfun$act$2
   public final $anonfun$apply$2=class scala/actors/Futures$FutureActor$$anonfun$act$2$$anonfun$apply$1$$anonfun$apply$2 of class scala/actors/Futures$FutureActor$$anonfun$act$2$$anonfun$apply$1
  minor version: 0
  major version: 49
  Constant pool:
Asciz	SourceFile;
Asciz	Future.scala;
Asciz	<clinit>;
Asciz	()V;
Asciz	Code;
Asciz	serialVersionUID;
Asciz	J;
Asciz	scala/actors/Futures$FutureActor$$anonfun$act$2$$anonfun$apply$1;
class	scala/actors/Futures$FutureActor$$anonfun$act$2$$anonfun$apply$1
NameAndType	serialVersionUID:J
Field	scala/actors/Futures$FutureActor$$anonfun$act$2$$anonfun$apply$1.serialVersionUID:J
Asciz	$outer;
Asciz	Lscala/actors/Futures$FutureActor$$anonfun$act$2;;
Asciz	apply;
Asciz	()Lscala/runtime/Nothing$;;
Asciz	LineNumberTable;
NameAndType	$outer:Lscala/actors/Futures$FutureActor$$anonfun$act$2;
Field	scala/actors/Futures$FutureActor$$anonfun$act$2$$anonfun$apply$1.$outer:Lscala/actors/Futures$FutureActor$$anonfun$act$2;
Asciz	scala/actors/Futures$FutureActor$$anonfun$act$2;
class	scala/actors/Futures$FutureActor$$anonfun$act$2
Asciz	Lscala/actors/Futures$FutureActor;;
NameAndType	$outer:Lscala/actors/Futures$FutureActor;
Field	scala/actors/Futures$FutureActor$$anonfun$act$2.$outer:Lscala/actors/Futures$FutureActor;
Asciz	scala/actors/Futures$FutureActor$$anonfun$act$2$$anonfun$apply$1$$anonfun$apply$2;
class	scala/actors/Futures$FutureActor$$anonfun$act$2$$anonfun$apply$1$$anonfun$apply$2
Asciz	<init>;
Asciz	(Lscala/actors/Futures$FutureActor$$anonfun$act$2$$anonfun$apply$1;)V;
NameAndType	"<init>":(Lscala/actors/Futures$FutureActor$$anonfun$act$2$$anonfun$apply$1;)V
Method	scala/actors/Futures$FutureActor$$anonfun$act$2$$anonfun$apply$1$$anonfun$apply$2."<init>":(Lscala/actors/Futures$FutureActor$$anonfun$act$2$$anonfun$apply$1;)V
Asciz	scala/actors/Actor;
class	scala/actors/Actor
Asciz	react;
Asciz	(Lscala/PartialFunction;)Lscala/runtime/Nothing$;;
NameAndType	react:(Lscala/PartialFunction;)Lscala/runtime/Nothing$;
InterfaceMethod	scala/actors/Actor.react:(Lscala/PartialFunction;)Lscala/runtime/Nothing$;
Asciz	this;
Asciz	Lscala/actors/Futures$FutureActor$$anonfun$act$2$$anonfun$apply$1;;
Asciz	LocalVariableTable;
Asciz	scala$actors$Futures$FutureActor$$anonfun$$anonfun$$$outer;
Asciz	()Lscala/actors/Futures$FutureActor$$anonfun$act$2;;
Asciz	()Ljava/lang/Object;;
NameAndType	apply:()Lscala/runtime/Nothing$;
Method	scala/actors/Futures$FutureActor$$anonfun$act$2$$anonfun$apply$1.apply:()Lscala/runtime/Nothing$;
Asciz	(Lscala/actors/Futures$FutureActor$$anonfun$act$2;)V;
Asciz	java/lang/NullPointerException;
class	java/lang/NullPointerException
NameAndType	"<init>":()V
Method	java/lang/NullPointerException."<init>":()V
Asciz	scala/runtime/AbstractFunction0;
class	scala/runtime/AbstractFunction0
Method	scala/runtime/AbstractFunction0."<init>":()V
Asciz	(Lscala/actors/Futures$FutureActor<TT;>.$anonfun$act$2;)V;
Asciz	Signature;
Asciz	Scala;
Asciz	InnerClasses;
Asciz	scala/actors/Futures$FutureActor;
class	scala/actors/Futures$FutureActor
Asciz	scala/actors/Futures;
class	scala/actors/Futures
Asciz	FutureActor;
Asciz	$anonfun$act$2;
Asciz	$anonfun$apply$1;
Asciz	$anonfun$apply$2;
Asciz	java/io/Serializable;
class	java/io/Serializable

{
public static final long serialVersionUID;
  Signature: J

public final scala.actors.Futures$FutureActor$$anonfun$act$2 $outer;
  Signature: Lscala/actors/Futures$FutureActor$$anonfun$act$2;

public static {};
  Signature: ()V
  Code:
   Stack=2, Locals=0, Args_size=0
	lconst_0
	putstatic	Field serialVersionUID:J
	return
  Labels:

public final scala.runtime.Nothing$ apply();
  Signature: ()Lscala/runtime/Nothing$;
  Code:
   Stack=4, Locals=2, Args_size=1
	aload_0
	getfield	Field $outer:Lscala/actors/Futures$FutureActor$$anonfun$act$2;
	astore_1
	aload_1
	getfield	Field scala/actors/Futures$FutureActor$$anonfun$act$2.$outer:Lscala/actors/Futures$FutureActor;
	new	class scala/actors/Futures$FutureActor$$anonfun$act$2$$anonfun$apply$1$$anonfun$apply$2
	dup
	aload_0
	invokespecial	Method scala/actors/Futures$FutureActor$$anonfun$act$2$$anonfun$apply$1$$anonfun$apply$2."<init>":(Lscala/actors/Futures$FutureActor$$anonfun$act$2$$anonfun$apply$1;)V
	invokeinterface	InterfaceMethod scala/actors/Actor.react:(Lscala/PartialFunction;)Lscala/runtime/Nothing$;
	areturn
  Labels:
  LocalVariableTable: 
   Start  Length  Slot  Name   Signature
   0      23      0    this       Lscala/actors/Futures$FutureActor$$anonfun$act$2$$anonfun$apply$1;


public scala.actors.Futures$FutureActor$$anonfun$act$2 scala$actors$Futures$FutureActor$$anonfun$$anonfun$$$outer();
  Signature: ()Lscala/actors/Futures$FutureActor$$anonfun$act$2;
  Code:
   Stack=1, Locals=1, Args_size=1
	aload_0
	getfield	Field $outer:Lscala/actors/Futures$FutureActor$$anonfun$act$2;
	areturn
  Labels:

public final java.lang.Object apply();
  Signature: ()Ljava/lang/Object;
  Code:
   Stack=1, Locals=1, Args_size=1
	aload_0
	invokevirtual	Method apply:()Lscala/runtime/Nothing$;
	athrow
  Labels:

public scala.actors.Futures$FutureActor$$anonfun$act$2$$anonfun$apply$1(scala.actors.Futures$FutureActor$$anonfun$act$2);
  Signature: (Lscala/actors/Futures$FutureActor$$anonfun$act$2;)V
  Code:
   Stack=2, Locals=2, Args_size=2
	aload_1
	ifnonnull	l1 // aload_0
	new	class java/lang/NullPointerException
	dup
	invokespecial	Method java/lang/NullPointerException."<init>":()V
	athrow
l1	aload_0
	aload_1
	putfield	Field $outer:Lscala/actors/Futures$FutureActor$$anonfun$act$2;
	aload_0
	invokespecial	Method scala/runtime/AbstractFunction0."<init>":()V
	return
  Labels:
   	l1 = 12 // aload_0
  LocalVariableTable: 
   Start  Length  Slot  Name   Signature
   0      22      0    this       Lscala/actors/Futures$FutureActor$$anonfun$act$2$$anonfun$apply$1;
   0      22      1    $outer       Lscala/actors/Futures$FutureActor$$anonfun$act$2;

  Signature: length = 0x2
   00 34 

}

