Compiled from "Future.scala"
public final class scala.actors.Futures extends java.lang.Object
  SourceFile: "Future.scala"
  ScalaSig: length = 0x5E4
   05 00 FFFFFF81 5A 07 05 01 02 FFFFFF88 02 07 01 07 46 75 74
   75 72 65 73 0A 02 03 04 01 06 61 63 74 6F 72 73
   0A 01 05 01 05 73 63 61 6C 61 03 00 10 02 08 09
   0D 01 02 06 08 0A 02 FFFFFF84 FFFFFF80 FFFFFF80 FFFFFF88 02 0B 02 07 46
   75 74 75 72 65 73 13 03 09 0C 14 10 02 0D 12 0D
   01 0E 0A 02 0F 10 01 04 6C 61 6E 67 0A 01 11 01
   04 6A 61 76 61 09 02 13 0E 02 06 4F 62 6A 65 63
   74 10 02 15 16 0D 01 04 09 02 17 04 02 0B 53 63
   61 6C 61 4F 62 6A 65 63 74 08 05 19 09 FFFFFF84 00 1A
   01 06 3C 69 6E 69 74 3E 14 01 07 07 05 1C 09 FFFFFF88
   46 1D 01 04 45 76 61 6C 10 02 1E 1F 0D 01 09 06
   08 20 09 FFFFFF84 FFFFFF80 FFFFFF80 FFFFFF88 46 21 02 04 45 76 61 6C 13
   04 1F 0C 14 22 10 02 15 23 09 02 24 04 02 07 50
   72 6F 64 75 63 74 08 05 19 1F FFFFFF84 00 26 14 01 1D
   08 08 28 1F FFFFFF84 FFFFFF80 FFFFFF80 FFFFFF84 22 29 01 08 74 6F 53 74
   72 69 6E 67 14 01 2A 10 02 0D 2B 09 02 2C 0E 02
   06 53 74 72 69 6E 67 08 08 2E 1F FFFFFF84 FFFFFF80 FFFFFF80 FFFFFF84 20
   2F 01 0D 70 72 6F 64 75 63 74 50 72 65 66 69 78
   15 01 2A 08 08 31 1F FFFFFF84 FFFFFF80 FFFFFF80 FFFFFF84 20 32 01 0C 70
   72 6F 64 75 63 74 41 72 69 74 79 15 01 33 10 02
   15 34 09 02 35 04 02 03 49 6E 74 08 08 37 1F FFFFFF84
   FFFFFF80 FFFFFF80 FFFFFF84 20 38 01 0E 70 72 6F 64 75 63 74 45 6C
   65 6D 65 6E 74 14 02 39 3C 10 02 15 3A 09 02 3B
   04 02 03 41 6E 79 08 07 3D 36 FFFFFF81 FFFFFF80 FFFFFFC0 00 33 01
   03 78 24 31 08 08 3F 1F FFFFFF84 FFFFFF80 FFFFFF80 FFFFFF84 20 40 01 12
   70 72 6F 64 75 63 74 45 6C 65 6D 65 6E 74 4E 61
   6D 65 14 02 2A 41 08 07 3D 3E FFFFFF81 FFFFFF80 FFFFFFC0 00 33 08
   08 43 1F FFFFFF84 FFFFFF80 FFFFFF80 FFFFFF84 20 44 01 08 63 61 6E 45 71
   75 61 6C 14 02 45 48 10 02 15 46 09 02 47 04 02
   07 42 6F 6F 6C 65 61 6E 08 07 3D 42 FFFFFF81 FFFFFF80 FFFFFFC0 00
   39 08 08 4A 1F FFFFFF84 FFFFFF80 FFFFFF80 FFFFFF84 08 4B 01 0B 72 65 61
   64 52 65 73 6F 6C 76 65 14 01 0C 28 02 1F 4D 10
   02 15 4E 09 02 4F 04 02 0C 73 65 72 69 61 6C 69
   7A 61 62 6C 65 06 04 51 09 04 52 02 0B 46 75 74
   75 72 65 41 63 74 6F 72 15 02 53 59 13 04 50 54
   5F 14 10 03 08 55 57 09 02 56 02 02 06 46 75 74
   75 72 65 10 02 58 59 0C 00 04 08 5A 50 FFFFFF84 FFFFFF80 FFFFFF80
   FFFFFFC2 00 5B 02 01 54 11 02 5C 39 10 02 15 5D 09 02
   5E 04 02 07 4E 6F 74 68 69 6E 67 10 02 08 60 09
   02 61 02 02 0B 44 61 65 6D 6F 6E 41 63 74 6F 72
   08 08 63 50 FFFFFF82 FFFFFF80 FFFFFFA0 FFFFFF80 04 64 01 03 66 75 6E 10
   04 15 65 67 6D 09 02 66 04 02 09 46 75 6E 63 74
   69 6F 6E 31 10 03 68 6B 57 0D 01 69 0A 02 6A 04
   01 0A 63 6F 6E 63 75 72 72 65 6E 74 09 02 6C 69
   02 07 53 79 6E 63 56 61 72 10 02 15 6E 09 02 6F
   04 02 04 55 6E 69 74 08 09 71 50 FFFFFF82 FFFFFF80 FFFFFFA0 FFFFFF80 04
   72 75 01 07 63 68 61 6E 6E 65 6C 10 03 08 73 57
   09 02 74 02 02 07 43 68 61 6E 6E 65 6C 09 02 76
   55 01 0C 69 6E 70 75 74 43 68 61 6E 6E 65 6C 08
   05 19 50 FFFFFF84 00 78 14 03 79 7A 7B 10 03 1E 50 57
   08 05 63 77 FFFFFFC0 00 64 08 05 71 77 FFFFFFC0 00 72 08 05
   7D 50 FFFFFF84 00 7E 01 05 69 73 53 65 74 15 01 45 08
   07 FFFFFF81 00 50 FFFFFF84 00 FFFFFF81 01 01 05 61 70 70 6C 79 14
   01 57 08 07 FFFFFF81 03 50 FFFFFF84 00 FFFFFF81 04 01 07 72 65 73
   70 6F 6E 64 14 03 6D FFFFFF81 05 08 08 FFFFFF81 06 FFFFFF81 02 FFFFFFC0
   00 FFFFFF81 07 01 01 6B 10 04 15 65 57 6D 08 07 FFFFFF81 09
   50 FFFFFF84 00 FFFFFF81 0A 01 03 61 63 74 14 01 6D 08 0B FFFFFF81
   0C 50 FFFFFF81 FFFFFF80 FFFFFF80 FFFFFF84 04 FFFFFF81 0D 75 01 12 73 75 70 65
   72 24 69 6E 70 75 74 43 68 61 6E 6E 65 6C 15 02
   FFFFFF81 0E 10 04 08 FFFFFF81 0F 57 09 03 FFFFFF81 10 02 02 0C 49
   6E 70 75 74 43 68 61 6E 6E 65 6C 08 07 FFFFFF81 12 09
   FFFFFF84 00 FFFFFF81 13 01 06 66 75 74 75 72 65 15 04 FFFFFF81 14
   FFFFFF81 17 14 04 FFFFFF81 15 FFFFFF81 18 10 04 08 55 FFFFFF81 16 10 03
   58 FFFFFF81 17 04 09 5A FFFFFF81 11 FFFFFF84 FFFFFF80 FFFFFF80 FFFFFFC2 00 5B 08 09
   FFFFFF81 19 FFFFFF81 11 FFFFFF84 FFFFFFC0 00 FFFFFF81 1A 01 04 62 6F 64 79 10
   05 15 FFFFFF81 1B FFFFFF81 16 09 03 FFFFFF81 1C 04 02 08 3C 62 79
   6E 61 6D 65 3E 08 07 FFFFFF81 1E 09 FFFFFF84 00 FFFFFF81 1F 01 05
   61 6C 61 72 6D 14 04 FFFFFF81 20 FFFFFF81 21 10 03 08 55 6D
   08 08 FFFFFF81 22 FFFFFF81 1D FFFFFFC0 00 FFFFFF81 23 01 08 74 69 6D 65
   73 70 61 6E 10 03 15 FFFFFF81 24 09 03 FFFFFF81 25 04 02 04
   4C 6F 6E 67 08 07 FFFFFF81 27 09 FFFFFF84 00 FFFFFF81 28 01 0B 61
   77 61 69 74 45 69 74 68 65 72 15 06 FFFFFF81 29 FFFFFF81 2F
   FFFFFF81 2B 14 06 FFFFFF81 2A FFFFFF81 31 FFFFFF81 34 10 03 58 FFFFFF81 2B 04
   0B FFFFFF81 2C FFFFFF81 26 FFFFFF84 FFFFFF80 FFFFFF80 FFFFFFC2 00 FFFFFF81 2D 02 01 42 11
   03 FFFFFF81 2E 39 10 03 58 FFFFFF81 2F 04 0A FFFFFF81 30 FFFFFF81 26 FFFFFF84
   FFFFFF80 FFFFFF80 FFFFFFC2 00 5B 02 01 41 08 08 FFFFFF81 32 FFFFFF81 26 FFFFFFC0 00
   FFFFFF81 33 01 03 66 74 31 10 04 08 55 FFFFFF81 2E 08 08 FFFFFF81
   35 FFFFFF81 26 FFFFFFC0 00 FFFFFF81 36 01 03 66 74 32 10 04 08 55
   FFFFFF81 2A 08 07 FFFFFF81 38 09 FFFFFF84 00 FFFFFF81 39 01 08 61 77 61
   69 74 41 6C 6C 14 06 FFFFFF81 3A FFFFFF81 49 FFFFFF81 4B 10 06 FFFFFF81
   3B FFFFFF81 43 FFFFFF81 46 0E 04 FFFFFF81 3C FFFFFF81 41 0E 04 FFFFFF81 3D FFFFFF81
   40 0D 02 FFFFFF81 3E 0A 03 FFFFFF81 3F 06 01 06 3C 72 6F 6F
   74 3E 09 01 05 09 03 FFFFFF81 42 04 01 07 70 61 63 6B
   61 67 65 09 04 FFFFFF81 44 FFFFFF81 45 02 04 4C 69 73 74 0A
   03 FFFFFF81 42 04 10 04 15 FFFFFF81 47 39 09 03 FFFFFF81 48 04 02
   06 4F 70 74 69 6F 6E 08 08 FFFFFF81 4A FFFFFF81 37 FFFFFFC0 00 FFFFFF81
   23 01 07 74 69 6D 65 6F 75 74 08 08 FFFFFF81 4C FFFFFF81 37
   FFFFFFC0 00 FFFFFF81 4D 01 03 66 74 73 10 05 15 FFFFFF81 4E FFFFFF81 50
   09 03 FFFFFF81 4F 04 02 0A 3C 72 65 70 65 61 74 65 64
   3E 10 03 08 55 39 08 08 FFFFFF81 52 09 FFFFFF84 00 02 FFFFFF81 53
   01 10 66 72 6F 6D 49 6E 70 75 74 43 68 61 6E 6E
   65 6C 15 04 FFFFFF81 54 FFFFFF81 57 14 04 FFFFFF81 55 FFFFFF81 58 10 04
   08 55 FFFFFF81 56 10 03 58 FFFFFF81 57 04 09 5A FFFFFF81 51 FFFFFF84 FFFFFF80
   FFFFFF80 FFFFFFC2 00 5B 08 07 76 FFFFFF81 51 FFFFFFC0 00 FFFFFF81 59 10 05 08
   FFFFFF81 0F FFFFFF81 56 
  InnerClass: 
   public final $anon$1=class scala/actors/Futures$$anon$1 of class scala/actors/Futures
   public final $anon$2=class scala/actors/Futures$$anon$2 of class scala/actors/Futures
   public final $anon$3=class scala/actors/Futures$$anon$3 of class scala/actors/Futures
   public final $anonfun$5=class scala/actors/Futures$$anonfun$5 of class scala/actors/Futures
   public final $anonfun$4=class scala/actors/Futures$$anonfun$4 of class scala/actors/Futures
   public final $anonfun$3=class scala/actors/Futures$$anonfun$3 of class scala/actors/Futures
   public final $anonfun$2=class scala/actors/Futures$$anonfun$2 of class scala/actors/Futures
   public final $anonfun$1=class scala/actors/Futures$$anonfun$1 of class scala/actors/Futures
   public FutureActor=class scala/actors/Futures$FutureActor of class scala/actors/Futures
   public final $anonfun$awaitAll$1=class scala/actors/Futures$$anonfun$awaitAll$1 of class scala/actors/Futures
   public final $anonfun$awaitEither$1=class scala/actors/Futures$$anonfun$awaitEither$1 of class scala/actors/Futures
  minor version: 0
  major version: 49
  Constant pool:
Asciz	SourceFile;
Asciz	Future.scala;
Asciz	awaitWith$1;
Asciz	(Lscala/collection/Seq;Lscala/runtime/ObjectRef;)V;
Asciz	Code;
Asciz	scala/actors/Futures$;
class	scala/actors/Futures$
Asciz	MODULE$;
Asciz	Lscala/actors/Futures$;;
NameAndType	MODULE$:Lscala/actors/Futures$;
Field	scala/actors/Futures$.MODULE$:Lscala/actors/Futures$;
NameAndType	awaitWith$1:(Lscala/collection/Seq;Lscala/runtime/ObjectRef;)V
Method	scala/actors/Futures$.awaitWith$1:(Lscala/collection/Seq;Lscala/runtime/ObjectRef;)V
Asciz	fromInputChannel;
Asciz	(Lscala/actors/InputChannel;)Lscala/actors/Future;;
NameAndType	fromInputChannel:(Lscala/actors/InputChannel;)Lscala/actors/Future;
Method	scala/actors/Futures$.fromInputChannel:(Lscala/actors/InputChannel;)Lscala/actors/Future;
Asciz	<T:Ljava/lang/Object;>(Lscala/actors/InputChannel<TT;>;)Lscala/actors/Future<TT;>;;
Asciz	Signature;
Asciz	awaitAll;
Asciz	(JLscala/collection/Seq;)Lscala/collection/immutable/List;;
NameAndType	awaitAll:(JLscala/collection/Seq;)Lscala/collection/immutable/List;
Method	scala/actors/Futures$.awaitAll:(JLscala/collection/Seq;)Lscala/collection/immutable/List;
Asciz	(JLscala/collection/Seq<Lscala/actors/Future<Ljava/lang/Object;>;>;)Lscala/collection/immutable/List<Lscala/Option<Ljava/lang/Object;>;>;;
Asciz	awaitEither;
Asciz	(Lscala/actors/Future;Lscala/actors/Future;)Ljava/lang/Object;;
NameAndType	awaitEither:(Lscala/actors/Future;Lscala/actors/Future;)Ljava/lang/Object;
Method	scala/actors/Futures$.awaitEither:(Lscala/actors/Future;Lscala/actors/Future;)Ljava/lang/Object;
Asciz	<A:Ljava/lang/Object;B:Ljava/lang/Object;>(Lscala/actors/Future<TA;>;Lscala/actors/Future<TB;>;)TB;;
Asciz	alarm;
Asciz	(J)Lscala/actors/Future;;
NameAndType	alarm:(J)Lscala/actors/Future;
Method	scala/actors/Futures$.alarm:(J)Lscala/actors/Future;
Asciz	(J)Lscala/actors/Future<Ljava/lang/Object;>;;
Asciz	future;
Asciz	(Lscala/Function0;)Lscala/actors/Future;;
NameAndType	future:(Lscala/Function0;)Lscala/actors/Future;
Method	scala/actors/Futures$.future:(Lscala/Function0;)Lscala/actors/Future;
Asciz	<T:Ljava/lang/Object;>(Lscala/Function0<TT;>;)Lscala/actors/Future<TT;>;;
Asciz	ScalaSig;
Asciz	InnerClasses;
Asciz	scala/actors/Futures$$anon$1;
class	scala/actors/Futures$$anon$1
Asciz	scala/actors/Futures;
class	scala/actors/Futures
Asciz	$anon$1;
Asciz	scala/actors/Futures$$anon$2;
class	scala/actors/Futures$$anon$2
Asciz	$anon$2;
Asciz	scala/actors/Futures$$anon$3;
class	scala/actors/Futures$$anon$3
Asciz	$anon$3;
Asciz	scala/actors/Futures$$anonfun$5;
class	scala/actors/Futures$$anonfun$5
Asciz	$anonfun$5;
Asciz	scala/actors/Futures$$anonfun$4;
class	scala/actors/Futures$$anonfun$4
Asciz	$anonfun$4;
Asciz	scala/actors/Futures$$anonfun$3;
class	scala/actors/Futures$$anonfun$3
Asciz	$anonfun$3;
Asciz	scala/actors/Futures$$anonfun$2;
class	scala/actors/Futures$$anonfun$2
Asciz	$anonfun$2;
Asciz	scala/actors/Futures$$anonfun$1;
class	scala/actors/Futures$$anonfun$1
Asciz	$anonfun$1;
Asciz	scala/actors/Futures$FutureActor;
class	scala/actors/Futures$FutureActor
Asciz	FutureActor;
Asciz	scala/actors/Futures$$anonfun$awaitAll$1;
class	scala/actors/Futures$$anonfun$awaitAll$1
Asciz	$anonfun$awaitAll$1;
Asciz	scala/actors/Futures$$anonfun$awaitEither$1;
class	scala/actors/Futures$$anonfun$awaitEither$1
Asciz	$anonfun$awaitEither$1;
Asciz	java/lang/Object;
class	java/lang/Object

{
public static final void awaitWith$1(scala.collection.Seq, scala.runtime.ObjectRef);
  Signature: (Lscala/collection/Seq;Lscala/runtime/ObjectRef;)V
  Code:
   Stack=3, Locals=2, Args_size=2
	getstatic	Field scala/actors/Futures$.MODULE$:Lscala/actors/Futures$;
	aload_0
	aload_1
	invokevirtual	Method scala/actors/Futures$.awaitWith$1:(Lscala/collection/Seq;Lscala/runtime/ObjectRef;)V
	return
  Labels:

public static final scala.actors.Future fromInputChannel(scala.actors.InputChannel);
  Signature: (Lscala/actors/InputChannel;)Lscala/actors/Future;
  Code:
   Stack=2, Locals=1, Args_size=1
	getstatic	Field scala/actors/Futures$.MODULE$:Lscala/actors/Futures$;
	aload_0
	invokevirtual	Method scala/actors/Futures$.fromInputChannel:(Lscala/actors/InputChannel;)Lscala/actors/Future;
	areturn
  Labels:
  Signature: length = 0x2
   00 12 

public static final scala.collection.immutable.List awaitAll(long, scala.collection.Seq);
  Signature: (JLscala/collection/Seq;)Lscala/collection/immutable/List;
  Code:
   Stack=4, Locals=3, Args_size=2
	getstatic	Field scala/actors/Futures$.MODULE$:Lscala/actors/Futures$;
	lload_0
	aload_2
	invokevirtual	Method scala/actors/Futures$.awaitAll:(JLscala/collection/Seq;)Lscala/collection/immutable/List;
	areturn
  Labels:
  Signature: length = 0x2
   00 18 

public static final java.lang.Object awaitEither(scala.actors.Future, scala.actors.Future);
  Signature: (Lscala/actors/Future;Lscala/actors/Future;)Ljava/lang/Object;
  Code:
   Stack=3, Locals=2, Args_size=2
	getstatic	Field scala/actors/Futures$.MODULE$:Lscala/actors/Futures$;
	aload_0
	aload_1
	invokevirtual	Method scala/actors/Futures$.awaitEither:(Lscala/actors/Future;Lscala/actors/Future;)Ljava/lang/Object;
	areturn
  Labels:
  Signature: length = 0x2
   00 1D 

public static final scala.actors.Future alarm(long);
  Signature: (J)Lscala/actors/Future;
  Code:
   Stack=3, Locals=2, Args_size=1
	getstatic	Field scala/actors/Futures$.MODULE$:Lscala/actors/Futures$;
	lload_0
	invokevirtual	Method scala/actors/Futures$.alarm:(J)Lscala/actors/Future;
	areturn
  Labels:
  Signature: length = 0x2
   00 22 

public static final scala.actors.Future future(scala.Function0);
  Signature: (Lscala/Function0;)Lscala/actors/Future;
  Code:
   Stack=2, Locals=1, Args_size=1
	getstatic	Field scala/actors/Futures$.MODULE$:Lscala/actors/Futures$;
	aload_0
	invokevirtual	Method scala/actors/Futures$.future:(Lscala/Function0;)Lscala/actors/Future;
	areturn
  Labels:
  Signature: length = 0x2
   00 27 

}

