Compiled from "Future.scala"
public final class scala.actors.Futures$$anon$3 extends java.lang.Object implements scala.PartialFunction
  SourceFile: "Future.scala"
  Signature: length = 0x2
   00 FFFFFFE8 
  Scala: length = 0x
   
  InnerClass: 
   public final #238= #12 of #237; //$anon$3=class scala/actors/Futures$$anon$3 of class scala/actors/Futures
   public final #239= #150 of #12; //$anonfun$6=class scala/actors/Futures$$anon$3$$anonfun$6 of class scala/actors/Futures$$anon$3
   public final #240= #78 of #12; //$anonfun$5=class scala/actors/Futures$$anon$3$$anonfun$5 of class scala/actors/Futures$$anon$3
   public final #241= #208 of #12; //$anonfun$isDefinedAt$1=class scala/actors/Futures$$anon$3$$anonfun$isDefinedAt$1 of class scala/actors/Futures$$anon$3
  minor version: 0
  major version: 49
  Constant pool:
const #1 = Asciz	SourceFile;
const #2 = Asciz	Future.scala;
const #3 = Asciz	partFuns$1;
const #4 = Asciz	Lscala/collection/Seq;;
const #5 = Asciz	resultsMap$1;
const #6 = Asciz	Lscala/runtime/ObjectRef;;
const #7 = Asciz	<init>;
const #8 = Asciz	(Lscala/runtime/ObjectRef;Lscala/collection/Seq;)V;
const #9 = Asciz	Code;
const #10 = Asciz	LineNumberTable;
const #11 = Asciz	scala/actors/Futures$$anon$3;
const #12 = class	#11;	//  scala/actors/Futures$$anon$3
const #13 = NameAndType	#5:#6;//  resultsMap$1:Lscala/runtime/ObjectRef;
const #14 = Field	#12.#13;	//  scala/actors/Futures$$anon$3.resultsMap$1:Lscala/runtime/ObjectRef;
const #15 = NameAndType	#3:#4;//  partFuns$1:Lscala/collection/Seq;
const #16 = Field	#12.#15;	//  scala/actors/Futures$$anon$3.partFuns$1:Lscala/collection/Seq;
const #17 = Asciz	java/lang/Object;
const #18 = class	#17;	//  java/lang/Object
const #19 = Asciz	()V;
const #20 = NameAndType	#7:#19;//  "<init>":()V
const #21 = Method	#18.#20;	//  java/lang/Object."<init>":()V
const #22 = Asciz	scala/Function1$class;
const #23 = class	#22;	//  scala/Function1$class
const #24 = Asciz	$init$;
const #25 = Asciz	(Lscala/Function1;)V;
const #26 = NameAndType	#24:#25;//  $init$:(Lscala/Function1;)V
const #27 = Method	#23.#26;	//  scala/Function1$class.$init$:(Lscala/Function1;)V
const #28 = Asciz	scala/PartialFunction$class;
const #29 = class	#28;	//  scala/PartialFunction$class
const #30 = Asciz	(Lscala/PartialFunction;)V;
const #31 = NameAndType	#24:#30;//  $init$:(Lscala/PartialFunction;)V
const #32 = Method	#29.#31;	//  scala/PartialFunction$class.$init$:(Lscala/PartialFunction;)V
const #33 = Asciz	apply;
const #34 = Asciz	(Ljava/lang/Object;)Ljava/lang/Object;;
const #35 = Asciz	(Ljava/lang/Object;)V;
const #36 = NameAndType	#33:#35;//  apply:(Ljava/lang/Object;)V
const #37 = Method	#12.#36;	//  scala/actors/Futures$$anon$3.apply:(Ljava/lang/Object;)V
const #38 = Asciz	scala/runtime/BoxedUnit;
const #39 = class	#38;	//  scala/runtime/BoxedUnit
const #40 = Asciz	UNIT;
const #41 = Asciz	Lscala/runtime/BoxedUnit;;
const #42 = NameAndType	#40:#41;//  UNIT:Lscala/runtime/BoxedUnit;
const #43 = Field	#39.#42;	//  scala/runtime/BoxedUnit.UNIT:Lscala/runtime/BoxedUnit;
const #44 = Asciz	this;
const #45 = Asciz	Lscala/actors/Futures$$anon$3;;
const #46 = Asciz	v1;
const #47 = Asciz	Ljava/lang/Object;;
const #48 = Asciz	LocalVariableTable;
const #49 = Asciz	andThen;
const #50 = Asciz	(Lscala/Function1;)Lscala/Function1;;
const #51 = Asciz	scala/PartialFunction;
const #52 = class	#51;	//  scala/PartialFunction
const #53 = Asciz	(Lscala/Function1;)Lscala/PartialFunction;;
const #54 = NameAndType	#49:#53;//  andThen:(Lscala/Function1;)Lscala/PartialFunction;
const #55 = InterfaceMethod	#52.#54;	//  scala/PartialFunction.andThen:(Lscala/Function1;)Lscala/PartialFunction;
const #56 = Asciz	g;
const #57 = Asciz	Lscala/Function1;;
const #58 = Asciz	scala/actors/TIMEOUT$;
const #59 = class	#58;	//  scala/actors/TIMEOUT$
const #60 = Asciz	MODULE$;
const #61 = Asciz	Lscala/actors/TIMEOUT$;;
const #62 = NameAndType	#60:#61;//  MODULE$:Lscala/actors/TIMEOUT$;
const #63 = Field	#59.#62;	//  scala/actors/TIMEOUT$.MODULE$:Lscala/actors/TIMEOUT$;
const #64 = Asciz	equals;
const #65 = Asciz	(Ljava/lang/Object;)Z;
const #66 = NameAndType	#64:#65;//  equals:(Ljava/lang/Object;)Z
const #67 = Method	#18.#66;	//  java/lang/Object.equals:(Ljava/lang/Object;)Z
const #68 = Asciz	scala/MatchError;
const #69 = class	#68;	//  scala/MatchError
const #70 = Asciz	toString;
const #71 = Asciz	()Ljava/lang/String;;
const #72 = NameAndType	#70:#71;//  toString:()Ljava/lang/String;
const #73 = Method	#18.#72;	//  java/lang/Object.toString:()Ljava/lang/String;
const #74 = Asciz	(Ljava/lang/String;)V;
const #75 = NameAndType	#7:#74;//  "<init>":(Ljava/lang/String;)V
const #76 = Method	#69.#75;	//  scala/MatchError."<init>":(Ljava/lang/String;)V
const #77 = Asciz	scala/actors/Futures$$anon$3$$anonfun$5;
const #78 = class	#77;	//  scala/actors/Futures$$anon$3$$anonfun$5
const #79 = Asciz	(Lscala/actors/Futures$$anon$3;Ljava/lang/Object;)V;
const #80 = NameAndType	#7:#79;//  "<init>":(Lscala/actors/Futures$$anon$3;Ljava/lang/Object;)V
const #81 = Method	#78.#80;	//  scala/actors/Futures$$anon$3$$anonfun$5."<init>":(Lscala/actors/Futures$$anon$3;Ljava/lang/Object;)V
const #82 = Asciz	scala/collection/IterableLike;
const #83 = class	#82;	//  scala/collection/IterableLike
const #84 = Asciz	find;
const #85 = Asciz	(Lscala/Function1;)Lscala/Option;;
const #86 = NameAndType	#84:#85;//  find:(Lscala/Function1;)Lscala/Option;
const #87 = InterfaceMethod	#83.#86;	//  scala/collection/IterableLike.find:(Lscala/Function1;)Lscala/Option;
const #88 = Asciz	scala/Option;
const #89 = class	#88;	//  scala/Option
const #90 = Asciz	get;
const #91 = Asciz	()Ljava/lang/Object;;
const #92 = NameAndType	#90:#91;//  get:()Ljava/lang/Object;
const #93 = Method	#89.#92;	//  scala/Option.get:()Ljava/lang/Object;
const #94 = Asciz	scala/Function1;
const #95 = class	#94;	//  scala/Function1
const #96 = NameAndType	#33:#34;//  apply:(Ljava/lang/Object;)Ljava/lang/Object;
const #97 = InterfaceMethod	#95.#96;	//  scala/Function1.apply:(Ljava/lang/Object;)Ljava/lang/Object;
const #98 = Asciz	scala/Tuple2;
const #99 = class	#98;	//  scala/Tuple2
const #100 = Asciz	scala/Predef$Pair$;
const #101 = class	#100;	//  scala/Predef$Pair$
const #102 = Asciz	Lscala/Predef$Pair$;;
const #103 = NameAndType	#60:#102;//  MODULE$:Lscala/Predef$Pair$;
const #104 = Field	#101.#103;	//  scala/Predef$Pair$.MODULE$:Lscala/Predef$Pair$;
const #105 = Asciz	unapply;
const #106 = Asciz	(Lscala/Tuple2;)Lscala/Option;;
const #107 = NameAndType	#105:#106;//  unapply:(Lscala/Tuple2;)Lscala/Option;
const #108 = Method	#101.#107;	//  scala/Predef$Pair$.unapply:(Lscala/Tuple2;)Lscala/Option;
const #109 = Asciz	isEmpty;
const #110 = Asciz	()Z;
const #111 = NameAndType	#109:#110;//  isEmpty:()Z
const #112 = Method	#89.#111;	//  scala/Option.isEmpty:()Z
const #113 = Method	#99.#72;	//  scala/Tuple2.toString:()Ljava/lang/String;
const #114 = Asciz	_1;
const #115 = NameAndType	#114:#91;//  _1:()Ljava/lang/Object;
const #116 = Method	#99.#115;	//  scala/Tuple2._1:()Ljava/lang/Object;
const #117 = Asciz	scala/runtime/BoxesRunTime;
const #118 = class	#117;	//  scala/runtime/BoxesRunTime
const #119 = Asciz	unboxToInt;
const #120 = Asciz	(Ljava/lang/Object;)I;
const #121 = NameAndType	#119:#120;//  unboxToInt:(Ljava/lang/Object;)I
const #122 = Method	#118.#121;	//  scala/runtime/BoxesRunTime.unboxToInt:(Ljava/lang/Object;)I
const #123 = Asciz	_2;
const #124 = NameAndType	#123:#91;//  _2:()Ljava/lang/Object;
const #125 = Method	#99.#124;	//  scala/Tuple2._2:()Ljava/lang/Object;
const #126 = Asciz	boxToInteger;
const #127 = Asciz	(I)Ljava/lang/Integer;;
const #128 = NameAndType	#126:#127;//  boxToInteger:(I)Ljava/lang/Integer;
const #129 = Method	#118.#128;	//  scala/runtime/BoxesRunTime.boxToInteger:(I)Ljava/lang/Integer;
const #130 = Asciz	(Ljava/lang/Object;Ljava/lang/Object;)V;
const #131 = NameAndType	#7:#130;//  "<init>":(Ljava/lang/Object;Ljava/lang/Object;)V
const #132 = Method	#99.#131;	//  scala/Tuple2."<init>":(Ljava/lang/Object;Ljava/lang/Object;)V
const #133 = Asciz	scala/runtime/ObjectRef;
const #134 = class	#133;	//  scala/runtime/ObjectRef
const #135 = Asciz	elem;
const #136 = NameAndType	#135:#47;//  elem:Ljava/lang/Object;
const #137 = Field	#134.#136;	//  scala/runtime/ObjectRef.elem:Ljava/lang/Object;
const #138 = Asciz	scala/collection/mutable/Map;
const #139 = class	#138;	//  scala/collection/mutable/Map
const #140 = Asciz	scala/Some;
const #141 = class	#140;	//  scala/Some
const #142 = NameAndType	#7:#35;//  "<init>":(Ljava/lang/Object;)V
const #143 = Method	#141.#142;	//  scala/Some."<init>":(Ljava/lang/Object;)V
const #144 = Asciz	scala/collection/mutable/MapLike;
const #145 = class	#144;	//  scala/collection/mutable/MapLike
const #146 = Asciz	update;
const #147 = NameAndType	#146:#130;//  update:(Ljava/lang/Object;Ljava/lang/Object;)V
const #148 = InterfaceMethod	#145.#147;	//  scala/collection/mutable/MapLike.update:(Ljava/lang/Object;Ljava/lang/Object;)V
const #149 = Asciz	scala/actors/Futures$$anon$3$$anonfun$6;
const #150 = class	#149;	//  scala/actors/Futures$$anon$3$$anonfun$6
const #151 = Asciz	(Lscala/actors/Futures$$anon$3;Lscala/PartialFunction;)V;
const #152 = NameAndType	#7:#151;//  "<init>":(Lscala/actors/Futures$$anon$3;Lscala/PartialFunction;)V
const #153 = Method	#150.#152;	//  scala/actors/Futures$$anon$3$$anonfun$6."<init>":(Lscala/actors/Futures$$anon$3;Lscala/PartialFunction;)V
const #154 = Asciz	scala/collection/TraversableLike;
const #155 = class	#154;	//  scala/collection/TraversableLike
const #156 = Asciz	filter;
const #157 = Asciz	(Lscala/Function1;)Ljava/lang/Object;;
const #158 = NameAndType	#156:#157;//  filter:(Lscala/Function1;)Ljava/lang/Object;
const #159 = InterfaceMethod	#155.#158;	//  scala/collection/TraversableLike.filter:(Lscala/Function1;)Ljava/lang/Object;
const #160 = Asciz	scala/collection/Seq;
const #161 = class	#160;	//  scala/collection/Seq
const #162 = Asciz	scala/collection/SeqLike;
const #163 = class	#162;	//  scala/collection/SeqLike
const #164 = Asciz	length;
const #165 = Asciz	()I;
const #166 = NameAndType	#164:#165;//  length:()I
const #167 = InterfaceMethod	#163.#166;	//  scala/collection/SeqLike.length:()I
const #168 = NameAndType	#7:#8;//  "<init>":(Lscala/runtime/ObjectRef;Lscala/collection/Seq;)V
const #169 = Method	#12.#168;	//  scala/actors/Futures$$anon$3."<init>":(Lscala/runtime/ObjectRef;Lscala/collection/Seq;)V
const #170 = Asciz	scala/actors/Actor$;
const #171 = class	#170;	//  scala/actors/Actor$
const #172 = Asciz	Lscala/actors/Actor$;;
const #173 = NameAndType	#60:#172;//  MODULE$:Lscala/actors/Actor$;
const #174 = Field	#171.#173;	//  scala/actors/Actor$.MODULE$:Lscala/actors/Actor$;
const #175 = Asciz	scala/actors/Scheduler$;
const #176 = class	#175;	//  scala/actors/Scheduler$
const #177 = Asciz	Lscala/actors/Scheduler$;;
const #178 = NameAndType	#60:#177;//  MODULE$:Lscala/actors/Scheduler$;
const #179 = Field	#176.#178;	//  scala/actors/Scheduler$.MODULE$:Lscala/actors/Scheduler$;
const #180 = Asciz	rawSelf;
const #181 = Asciz	(Lscala/actors/IScheduler;)Lscala/actors/Reactor;;
const #182 = NameAndType	#180:#181;//  rawSelf:(Lscala/actors/IScheduler;)Lscala/actors/Reactor;
const #183 = Method	#171.#182;	//  scala/actors/Actor$.rawSelf:(Lscala/actors/IScheduler;)Lscala/actors/Reactor;
const #184 = Asciz	scala/actors/Actor;
const #185 = class	#184;	//  scala/actors/Actor
const #186 = Asciz	receive;
const #187 = Asciz	(Lscala/PartialFunction;)Ljava/lang/Object;;
const #188 = NameAndType	#186:#187;//  receive:(Lscala/PartialFunction;)Ljava/lang/Object;
const #189 = InterfaceMethod	#185.#188;	//  scala/actors/Actor.receive:(Lscala/PartialFunction;)Ljava/lang/Object;
const #190 = Asciz	msg$2;
const #191 = Asciz	pfOpt;
const #192 = Asciz	Lscala/Option;;
const #193 = Asciz	temp36;
const #194 = Asciz	temp37;
const #195 = Asciz	Lscala/Tuple2;;
const #196 = Asciz	temp38;
const #197 = Asciz	I;
const #198 = Asciz	temp39;
const #199 = Asciz	idx;
const #200 = Asciz	subres;
const #201 = Asciz	pf$1;
const #202 = Asciz	Lscala/PartialFunction;;
const #203 = Asciz	partFunsRest;
const #204 = Asciz	reaction0;
const #205 = Asciz	temp35;
const #206 = Asciz	isDefinedAt;
const #207 = Asciz	scala/actors/Futures$$anon$3$$anonfun$isDefinedAt$1;
const #208 = class	#207;	//  scala/actors/Futures$$anon$3$$anonfun$isDefinedAt$1
const #209 = Method	#208.#80;	//  scala/actors/Futures$$anon$3$$anonfun$isDefinedAt$1."<init>":(Lscala/actors/Futures$$anon$3;Ljava/lang/Object;)V
const #210 = Asciz	exists;
const #211 = Asciz	(Lscala/Function1;)Z;
const #212 = NameAndType	#210:#211;//  exists:(Lscala/Function1;)Z
const #213 = InterfaceMethod	#83.#212;	//  scala/collection/IterableLike.exists:(Lscala/Function1;)Z
const #214 = Asciz	msg$1;
const #215 = Asciz	compose;
const #216 = Asciz	(Lscala/Function1;Lscala/Function1;)Lscala/Function1;;
const #217 = NameAndType	#215:#216;//  compose:(Lscala/Function1;Lscala/Function1;)Lscala/Function1;
const #218 = Method	#23.#217;	//  scala/Function1$class.compose:(Lscala/Function1;Lscala/Function1;)Lscala/Function1;
const #219 = Asciz	(Lscala/Function1;)Ljava/lang/String;;
const #220 = NameAndType	#70:#219;//  toString:(Lscala/Function1;)Ljava/lang/String;
const #221 = Method	#23.#220;	//  scala/Function1$class.toString:(Lscala/Function1;)Ljava/lang/String;
const #222 = Asciz	(Lscala/PartialFunction;Lscala/Function1;)Lscala/PartialFunction;;
const #223 = NameAndType	#49:#222;//  andThen:(Lscala/PartialFunction;Lscala/Function1;)Lscala/PartialFunction;
const #224 = Method	#29.#223;	//  scala/PartialFunction$class.andThen:(Lscala/PartialFunction;Lscala/Function1;)Lscala/PartialFunction;
const #225 = Asciz	k;
const #226 = Asciz	orElse;
const #227 = Asciz	(Lscala/PartialFunction;)Lscala/PartialFunction;;
const #228 = Asciz	(Lscala/PartialFunction;Lscala/PartialFunction;)Lscala/PartialFunction;;
const #229 = NameAndType	#226:#228;//  orElse:(Lscala/PartialFunction;Lscala/PartialFunction;)Lscala/PartialFunction;
const #230 = Method	#29.#229;	//  scala/PartialFunction$class.orElse:(Lscala/PartialFunction;Lscala/PartialFunction;)Lscala/PartialFunction;
const #231 = Asciz	that;
const #232 = Asciz	Ljava/lang/Object;Lscala/PartialFunction<Ljava/lang/Object;Ljava/lang/Object;>;;
const #233 = Asciz	Signature;
const #234 = Asciz	Scala;
const #235 = Asciz	InnerClasses;
const #236 = Asciz	scala/actors/Futures;
const #237 = class	#236;	//  scala/actors/Futures
const #238 = Asciz	$anon$3;
const #239 = Asciz	$anonfun$6;
const #240 = Asciz	$anonfun$5;
const #241 = Asciz	$anonfun$isDefinedAt$1;

{
public scala.actors.Futures$$anon$3(scala.runtime.ObjectRef, scala.collection.Seq);
  Code:
   Stack=2, Locals=3, Args_size=3
   0:	aload_0
   1:	aload_1
   2:	putfield	#14; //Field resultsMap$1:Lscala/runtime/ObjectRef;
   5:	aload_0
   6:	aload_2
   7:	putfield	#16; //Field partFuns$1:Lscala/collection/Seq;
   10:	aload_0
   11:	invokespecial	#21; //Method java/lang/Object."<init>":()V
   14:	aload_0
   15:	invokestatic	#27; //Method scala/Function1$class.$init$:(Lscala/Function1;)V
   18:	aload_0
   19:	invokestatic	#32; //Method scala/PartialFunction$class.$init$:(Lscala/PartialFunction;)V
   22:	return
  LineNumberTable: 
   line 107: 0


public java.lang.Object apply(java.lang.Object);
  Code:
   Stack=2, Locals=2, Args_size=2
   0:	aload_0
   1:	aload_1
   2:	invokevirtual	#37; //Method apply:(Ljava/lang/Object;)V
   5:	getstatic	#43; //Field scala/runtime/BoxedUnit.UNIT:Lscala/runtime/BoxedUnit;
   8:	areturn
  LineNumberTable: 
   line 107: 0

  LocalVariableTable: 
   Start  Length  Slot  Name   Signature
   0      9      0    this       Lscala/actors/Futures$$anon$3;
   0      9      1    v1       Ljava/lang/Object;


public scala.Function1 andThen(scala.Function1);
  Code:
   Stack=2, Locals=2, Args_size=2
   0:	aload_0
   1:	aload_1
   2:	invokeinterface	#55,  2; //InterfaceMethod scala/PartialFunction.andThen:(Lscala/Function1;)Lscala/PartialFunction;
   7:	areturn
  LineNumberTable: 
   line 107: 0

  LocalVariableTable: 
   Start  Length  Slot  Name   Signature
   0      8      0    this       Lscala/actors/Futures$$anon$3;
   0      8      1    g       Lscala/Function1;


public void apply(java.lang.Object);
  Code:
   Stack=5, Locals=17, Args_size=2
   0:	getstatic	#63; //Field scala/actors/TIMEOUT$.MODULE$:Lscala/actors/TIMEOUT$;
   3:	dup
   4:	ifnonnull	15
   7:	pop
   8:	aload_1
   9:	ifnull	22
   12:	goto	38
   15:	aload_1
   16:	invokevirtual	#67; //Method java/lang/Object.equals:(Ljava/lang/Object;)Z
   19:	ifeq	38
   22:	iconst_1
   23:	ifne	286
   26:	new	#69; //class scala/MatchError
   29:	dup
   30:	aload_1
   31:	invokevirtual	#73; //Method java/lang/Object.toString:()Ljava/lang/String;
   34:	invokespecial	#76; //Method scala/MatchError."<init>":(Ljava/lang/String;)V
   37:	athrow
   38:	iconst_1
   39:	ifeq	300
   42:	aload_0
   43:	getfield	#16; //Field partFuns$1:Lscala/collection/Seq;
   46:	new	#78; //class scala/actors/Futures$$anon$3$$anonfun$5
   49:	dup
   50:	aload_0
   51:	aload_1
   52:	invokespecial	#81; //Method scala/actors/Futures$$anon$3$$anonfun$5."<init>":(Lscala/actors/Futures$$anon$3;Ljava/lang/Object;)V
   55:	invokeinterface	#87,  2; //InterfaceMethod scala/collection/IterableLike.find:(Lscala/Function1;)Lscala/Option;
   60:	astore_2
   61:	aload_2
   62:	invokevirtual	#93; //Method scala/Option.get:()Ljava/lang/Object;
   65:	checkcast	#52; //class scala/PartialFunction
   68:	astore	10
   70:	aload	10
   72:	aload_1
   73:	invokeinterface	#97,  2; //InterfaceMethod scala/Function1.apply:(Ljava/lang/Object;)Ljava/lang/Object;
   78:	checkcast	#99; //class scala/Tuple2
   81:	astore	16
   83:	getstatic	#104; //Field scala/Predef$Pair$.MODULE$:Lscala/Predef$Pair$;
   86:	aload	16
   88:	invokevirtual	#108; //Method scala/Predef$Pair$.unapply:(Lscala/Tuple2;)Lscala/Option;
   91:	astore_3
   92:	aload_3
   93:	invokevirtual	#112; //Method scala/Option.isEmpty:()Z
   96:	ifeq	112
   99:	new	#69; //class scala/MatchError
   102:	dup
   103:	aload	16
   105:	invokevirtual	#113; //Method scala/Tuple2.toString:()Ljava/lang/String;
   108:	invokespecial	#76; //Method scala/MatchError."<init>":(Ljava/lang/String;)V
   111:	athrow
   112:	aload_3
   113:	invokevirtual	#93; //Method scala/Option.get:()Ljava/lang/Object;
   116:	checkcast	#99; //class scala/Tuple2
   119:	astore	4
   121:	aload	4
   123:	invokevirtual	#116; //Method scala/Tuple2._1:()Ljava/lang/Object;
   126:	invokestatic	#122; //Method scala/runtime/BoxesRunTime.unboxToInt:(Ljava/lang/Object;)I
   129:	istore	5
   131:	aload	4
   133:	invokevirtual	#125; //Method scala/Tuple2._2:()Ljava/lang/Object;
   136:	astore	6
   138:	iconst_1
   139:	ifeq	287
   142:	new	#99; //class scala/Tuple2
   145:	dup
   146:	iload	5
   148:	invokestatic	#129; //Method scala/runtime/BoxesRunTime.boxToInteger:(I)Ljava/lang/Integer;
   151:	aload	6
   153:	invokespecial	#132; //Method scala/Tuple2."<init>":(Ljava/lang/Object;Ljava/lang/Object;)V
   156:	astore	7
   158:	aload	7
   160:	invokevirtual	#116; //Method scala/Tuple2._1:()Ljava/lang/Object;
   163:	invokestatic	#122; //Method scala/runtime/BoxesRunTime.unboxToInt:(Ljava/lang/Object;)I
   166:	istore	8
   168:	aload	7
   170:	invokevirtual	#125; //Method scala/Tuple2._2:()Ljava/lang/Object;
   173:	astore	9
   175:	aload_0
   176:	getfield	#14; //Field resultsMap$1:Lscala/runtime/ObjectRef;
   179:	getfield	#137; //Field scala/runtime/ObjectRef.elem:Ljava/lang/Object;
   182:	checkcast	#139; //class scala/collection/mutable/Map
   185:	iload	8
   187:	invokestatic	#129; //Method scala/runtime/BoxesRunTime.boxToInteger:(I)Ljava/lang/Integer;
   190:	new	#141; //class scala/Some
   193:	dup
   194:	aload	9
   196:	invokespecial	#143; //Method scala/Some."<init>":(Ljava/lang/Object;)V
   199:	invokeinterface	#148,  3; //InterfaceMethod scala/collection/mutable/MapLike.update:(Ljava/lang/Object;Ljava/lang/Object;)V
   204:	aload_0
   205:	getfield	#16; //Field partFuns$1:Lscala/collection/Seq;
   208:	new	#150; //class scala/actors/Futures$$anon$3$$anonfun$6
   211:	dup
   212:	aload_0
   213:	aload	10
   215:	invokespecial	#153; //Method scala/actors/Futures$$anon$3$$anonfun$6."<init>":(Lscala/actors/Futures$$anon$3;Lscala/PartialFunction;)V
   218:	invokeinterface	#159,  2; //InterfaceMethod scala/collection/TraversableLike.filter:(Lscala/Function1;)Ljava/lang/Object;
   223:	checkcast	#161; //class scala/collection/Seq
   226:	astore	12
   228:	aload	12
   230:	invokeinterface	#167,  1; //InterfaceMethod scala/collection/SeqLike.length:()I
   235:	iconst_0
   236:	if_icmple	286
   239:	aload_0
   240:	getfield	#14; //Field resultsMap$1:Lscala/runtime/ObjectRef;
   243:	astore	11
   245:	new	#12; //class scala/actors/Futures$$anon$3
   248:	dup
   249:	aload	11
   251:	aload	12
   253:	invokespecial	#169; //Method "<init>":(Lscala/runtime/ObjectRef;Lscala/collection/Seq;)V
   256:	astore	15
   258:	getstatic	#174; //Field scala/actors/Actor$.MODULE$:Lscala/actors/Actor$;
   261:	astore	13
   263:	getstatic	#179; //Field scala/actors/Scheduler$.MODULE$:Lscala/actors/Scheduler$;
   266:	astore	14
   268:	aload	13
   270:	aload	14
   272:	invokevirtual	#183; //Method scala/actors/Actor$.rawSelf:(Lscala/actors/IScheduler;)Lscala/actors/Reactor;
   275:	checkcast	#185; //class scala/actors/Actor
   278:	aload	15
   280:	invokeinterface	#189,  2; //InterfaceMethod scala/actors/Actor.receive:(Lscala/PartialFunction;)Ljava/lang/Object;
   285:	pop
   286:	return
   287:	new	#69; //class scala/MatchError
   290:	dup
   291:	aload	16
   293:	invokevirtual	#113; //Method scala/Tuple2.toString:()Ljava/lang/String;
   296:	invokespecial	#76; //Method scala/MatchError."<init>":(Ljava/lang/String;)V
   299:	athrow
   300:	new	#69; //class scala/MatchError
   303:	dup
   304:	aload_1
   305:	invokevirtual	#73; //Method java/lang/Object.toString:()Ljava/lang/String;
   308:	invokespecial	#76; //Method scala/MatchError."<init>":(Ljava/lang/String;)V
   311:	athrow
  LineNumberTable: 
   line 112: 0
   line 644: 22
   line 112: 26
   line 644: 38
   line 115: 42
   line 116: 61
   line 117: 70
   line 644: 138
   line 117: 142
   line 118: 175
   line 120: 204
   line 122: 228
   line 123: 239
   line 112: 286
   line 117: 287
   line 112: 300

  LocalVariableTable: 
   Start  Length  Slot  Name   Signature
   0      312      0    this       Lscala/actors/Futures$$anon$3;
   0      312      1    msg$2       Ljava/lang/Object;
   61      225      2    pfOpt       Lscala/Option;
   287      13      2    pfOpt       Lscala/Option;
   92      147      3    temp36       Lscala/Option;
   287      13      3    temp36       Lscala/Option;
   121      118      4    temp37       Lscala/Tuple2;
   287      13      4    temp37       Lscala/Tuple2;
   131      108      5    temp38       I
   287      13      5    temp38       I
   138      101      6    temp39       Ljava/lang/Object;
   287      13      6    temp39       Ljava/lang/Object;
   168      118      8    idx       I
   175      111      9    subres       Ljava/lang/Object;
   70      216      10    pf$1       Lscala/PartialFunction;
   287      13      10    pf$1       Lscala/PartialFunction;
   228      58      12    partFunsRest       Lscala/collection/Seq;
   258      28      15    reaction0       Lscala/PartialFunction;
   83      156      16    temp35       Lscala/Tuple2;
   287      13      16    temp35       Lscala/Tuple2;


public boolean isDefinedAt(java.lang.Object);
  Code:
   Stack=5, Locals=2, Args_size=2
   0:	getstatic	#63; //Field scala/actors/TIMEOUT$.MODULE$:Lscala/actors/TIMEOUT$;
   3:	dup
   4:	ifnonnull	15
   7:	pop
   8:	aload_1
   9:	ifnull	22
   12:	goto	42
   15:	aload_1
   16:	invokevirtual	#67; //Method java/lang/Object.equals:(Ljava/lang/Object;)Z
   19:	ifeq	42
   22:	iconst_1
   23:	ifeq	30
   26:	iconst_1
   27:	goto	64
   30:	new	#69; //class scala/MatchError
   33:	dup
   34:	aload_1
   35:	invokevirtual	#73; //Method java/lang/Object.toString:()Ljava/lang/String;
   38:	invokespecial	#76; //Method scala/MatchError."<init>":(Ljava/lang/String;)V
   41:	athrow
   42:	iconst_1
   43:	ifeq	65
   46:	aload_0
   47:	getfield	#16; //Field partFuns$1:Lscala/collection/Seq;
   50:	new	#208; //class scala/actors/Futures$$anon$3$$anonfun$isDefinedAt$1
   53:	dup
   54:	aload_0
   55:	aload_1
   56:	invokespecial	#209; //Method scala/actors/Futures$$anon$3$$anonfun$isDefinedAt$1."<init>":(Lscala/actors/Futures$$anon$3;Ljava/lang/Object;)V
   59:	invokeinterface	#213,  2; //InterfaceMethod scala/collection/IterableLike.exists:(Lscala/Function1;)Z
   64:	ireturn
   65:	new	#69; //class scala/MatchError
   68:	dup
   69:	aload_1
   70:	invokevirtual	#73; //Method java/lang/Object.toString:()Ljava/lang/String;
   73:	invokespecial	#76; //Method scala/MatchError."<init>":(Ljava/lang/String;)V
   76:	athrow
  LineNumberTable: 
   line 108: 0
   line 644: 22
   line 109: 26
   line 108: 30
   line 644: 42
   line 110: 46
   line 108: 64

  LocalVariableTable: 
   Start  Length  Slot  Name   Signature
   0      77      0    this       Lscala/actors/Futures$$anon$3;
   0      77      1    msg$1       Ljava/lang/Object;


public scala.Function1 compose(scala.Function1);
  Code:
   Stack=2, Locals=2, Args_size=2
   0:	aload_0
   1:	aload_1
   2:	invokestatic	#218; //Method scala/Function1$class.compose:(Lscala/Function1;Lscala/Function1;)Lscala/Function1;
   5:	areturn
  LineNumberTable: 
   line 107: 0

  LocalVariableTable: 
   Start  Length  Slot  Name   Signature
   0      6      0    this       Lscala/actors/Futures$$anon$3;
   0      6      1    g       Lscala/Function1;


public java.lang.String toString();
  Code:
   Stack=1, Locals=1, Args_size=1
   0:	aload_0
   1:	invokestatic	#221; //Method scala/Function1$class.toString:(Lscala/Function1;)Ljava/lang/String;
   4:	areturn
  LineNumberTable: 
   line 107: 0


public scala.PartialFunction andThen(scala.Function1);
  Code:
   Stack=2, Locals=2, Args_size=2
   0:	aload_0
   1:	aload_1
   2:	invokestatic	#224; //Method scala/PartialFunction$class.andThen:(Lscala/PartialFunction;Lscala/Function1;)Lscala/PartialFunction;
   5:	areturn
  LineNumberTable: 
   line 107: 0

  LocalVariableTable: 
   Start  Length  Slot  Name   Signature
   0      6      0    this       Lscala/actors/Futures$$anon$3;
   0      6      1    k       Lscala/Function1;


public scala.PartialFunction orElse(scala.PartialFunction);
  Code:
   Stack=2, Locals=2, Args_size=2
   0:	aload_0
   1:	aload_1
   2:	invokestatic	#230; //Method scala/PartialFunction$class.orElse:(Lscala/PartialFunction;Lscala/PartialFunction;)Lscala/PartialFunction;
   5:	areturn
  LineNumberTable: 
   line 107: 0

  LocalVariableTable: 
   Start  Length  Slot  Name   Signature
   0      6      0    this       Lscala/actors/Futures$$anon$3;
   0      6      1    that       Lscala/PartialFunction;


}

