Compiled from "Future.scala"
public final class scala.actors.Futures$ extends java.lang.Object implements scala.ScalaObject
  SourceFile: "Future.scala"
  Scala: length = 0x
   
  InnerClass: 
   public final #276= #55 of #275; //Eval$2=class scala/actors/Futures$Eval$2$ of class scala/actors/Futures
   public final #277= #81 of #275; //$anon$4=class scala/actors/Futures$$anon$4 of class scala/actors/Futures
   public final #278= #232 of #275; //$anon$1=class scala/actors/Futures$$anon$1 of class scala/actors/Futures
   public final #279= #27 of #275; //$anon$3=class scala/actors/Futures$$anon$3 of class scala/actors/Futures
   public final #280= #62 of #275; //$anon$2=class scala/actors/Futures$$anon$2 of class scala/actors/Futures
   public final #281= #141 of #275; //$anonfun$4=class scala/actors/Futures$$anonfun$4 of class scala/actors/Futures
   public final #282= #103 of #275; //$anonfun$2=class scala/actors/Futures$$anonfun$2 of class scala/actors/Futures
   public final #283= #134 of #275; //$anonfun$3=class scala/actors/Futures$$anonfun$3 of class scala/actors/Futures
   public final #284= #221 of #275; //$anonfun$alarm$1=class scala/actors/Futures$$anonfun$alarm$1 of class scala/actors/Futures
   public final #285= #246 of #275; //$anonfun$future$1=class scala/actors/Futures$$anonfun$future$1 of class scala/actors/Futures
   public final #286= #172 of #275; //$anonfun$awaitAll$1=class scala/actors/Futures$$anonfun$awaitAll$1 of class scala/actors/Futures
   public final #287= #208 of #275; //$anonfun$awaitEither$1=class scala/actors/Futures$$anonfun$awaitEither$1 of class scala/actors/Futures
  minor version: 0
  major version: 49
  Constant pool:
const #1 = Asciz	SourceFile;
const #2 = Asciz	Future.scala;
const #3 = Asciz	Scala;
const #4 = Asciz	MODULE$;
const #5 = Asciz	Lscala/actors/Futures$;;
const #6 = Asciz	<clinit>;
const #7 = Asciz	()V;
const #8 = Asciz	Code;
const #9 = Asciz	scala/actors/Futures$;
const #10 = class	#9;	//  scala/actors/Futures$
const #11 = Asciz	<init>;
const #12 = NameAndType	#11:#7;//  "<init>":()V
const #13 = Method	#10.#12;	//  scala/actors/Futures$."<init>":()V
const #14 = Asciz	bitmap$0;
const #15 = Asciz	I;
const #16 = Asciz	scala$actors$Futures$$sched;
const #17 = Asciz	Lscala/actors/scheduler/DefaultExecutorScheduler;;
const #18 = Asciz	LineNumberTable;
const #19 = Asciz	java/lang/Object;
const #20 = class	#19;	//  java/lang/Object
const #21 = Method	#20.#12;	//  java/lang/Object."<init>":()V
const #22 = NameAndType	#4:#5;//  MODULE$:Lscala/actors/Futures$;
const #23 = Field	#10.#22;	//  scala/actors/Futures$.MODULE$:Lscala/actors/Futures$;
const #24 = Asciz	awaitWith$1;
const #25 = Asciz	(Lscala/collection/Sequence;Lscala/runtime/ObjectRef;)V;
const #26 = Asciz	scala/actors/Futures$$anon$3;
const #27 = class	#26;	//  scala/actors/Futures$$anon$3
const #28 = Asciz	(Lscala/runtime/ObjectRef;Lscala/collection/Sequence;)V;
const #29 = NameAndType	#11:#28;//  "<init>":(Lscala/runtime/ObjectRef;Lscala/collection/Sequence;)V
const #30 = Method	#27.#29;	//  scala/actors/Futures$$anon$3."<init>":(Lscala/runtime/ObjectRef;Lscala/collection/Sequence;)V
const #31 = Asciz	scala/actors/Actor$;
const #32 = class	#31;	//  scala/actors/Actor$
const #33 = Asciz	Lscala/actors/Actor$;;
const #34 = NameAndType	#4:#33;//  MODULE$:Lscala/actors/Actor$;
const #35 = Field	#32.#34;	//  scala/actors/Actor$.MODULE$:Lscala/actors/Actor$;
const #36 = Asciz	receive;
const #37 = Asciz	(Lscala/PartialFunction;)Ljava/lang/Object;;
const #38 = NameAndType	#36:#37;//  receive:(Lscala/PartialFunction;)Ljava/lang/Object;
const #39 = Method	#32.#38;	//  scala/actors/Actor$.receive:(Lscala/PartialFunction;)Ljava/lang/Object;
const #40 = Asciz	this;
const #41 = Asciz	partFuns$1;
const #42 = Asciz	Lscala/collection/Sequence;;
const #43 = Asciz	reaction;
const #44 = Asciz	Lscala/PartialFunction;;
const #45 = Asciz	LocalVariableTable;
const #46 = Asciz	Eval$1;
const #47 = Asciz	(Lscala/runtime/ObjectRef;)Lscala/actors/Futures$Eval$2$;;
const #48 = Asciz	scala/runtime/ObjectRef;
const #49 = class	#48;	//  scala/runtime/ObjectRef
const #50 = Asciz	elem;
const #51 = Asciz	Ljava/lang/Object;;
const #52 = NameAndType	#50:#51;//  elem:Ljava/lang/Object;
const #53 = Field	#49.#52;	//  scala/runtime/ObjectRef.elem:Ljava/lang/Object;
const #54 = Asciz	scala/actors/Futures$Eval$2$;
const #55 = class	#54;	//  scala/actors/Futures$Eval$2$
const #56 = Asciz	(Lscala/runtime/ObjectRef;)V;
const #57 = NameAndType	#11:#56;//  "<init>":(Lscala/runtime/ObjectRef;)V
const #58 = Method	#55.#57;	//  scala/actors/Futures$Eval$2$."<init>":(Lscala/runtime/ObjectRef;)V
const #59 = Asciz	fromInputChannel;
const #60 = Asciz	(Lscala/actors/InputChannel;)Lscala/actors/Future;;
const #61 = Asciz	scala/actors/Futures$$anon$2;
const #62 = class	#61;	//  scala/actors/Futures$$anon$2
const #63 = Asciz	(Lscala/actors/InputChannel;)V;
const #64 = NameAndType	#11:#63;//  "<init>":(Lscala/actors/InputChannel;)V
const #65 = Method	#62.#64;	//  scala/actors/Futures$$anon$2."<init>":(Lscala/actors/InputChannel;)V
const #66 = Asciz	inputChannel$1;
const #67 = Asciz	Lscala/actors/InputChannel;;
const #68 = Asciz	<T:Ljava/lang/Object;>(Lscala/actors/InputChannel<TT;>;)Lscala/actors/Future<TT;>;;
const #69 = Asciz	Signature;
const #70 = Asciz	awaitAll;
const #71 = Asciz	(JLscala/collection/Sequence;)Lscala/collection/immutable/List;;
const #72 = Asciz	self;
const #73 = Asciz	()Lscala/actors/Actor;;
const #74 = NameAndType	#72:#73;//  self:()Lscala/actors/Actor;
const #75 = Method	#32.#74;	//  scala/actors/Actor$.self:()Lscala/actors/Actor;
const #76 = Asciz	timer;
const #77 = Asciz	()Ljava/util/Timer;;
const #78 = NameAndType	#76:#77;//  timer:()Ljava/util/Timer;
const #79 = Method	#32.#78;	//  scala/actors/Actor$.timer:()Ljava/util/Timer;
const #80 = Asciz	scala/actors/Futures$$anon$4;
const #81 = class	#80;	//  scala/actors/Futures$$anon$4
const #82 = Asciz	(Lscala/actors/Actor;)V;
const #83 = NameAndType	#11:#82;//  "<init>":(Lscala/actors/Actor;)V
const #84 = Method	#81.#83;	//  scala/actors/Futures$$anon$4."<init>":(Lscala/actors/Actor;)V
const #85 = Asciz	java/util/Timer;
const #86 = class	#85;	//  java/util/Timer
const #87 = Asciz	schedule;
const #88 = Asciz	(Ljava/util/TimerTask;J)V;
const #89 = NameAndType	#87:#88;//  schedule:(Ljava/util/TimerTask;J)V
const #90 = Method	#86.#89;	//  java/util/Timer.schedule:(Ljava/util/TimerTask;J)V
const #91 = Asciz	scala/collection/mutable/HashMap;
const #92 = class	#91;	//  scala/collection/mutable/HashMap
const #93 = Method	#92.#12;	//  scala/collection/mutable/HashMap."<init>":()V
const #94 = Asciz	(Ljava/lang/Object;)V;
const #95 = NameAndType	#11:#94;//  "<init>":(Ljava/lang/Object;)V
const #96 = Method	#49.#95;	//  scala/runtime/ObjectRef."<init>":(Ljava/lang/Object;)V
const #97 = Asciz	scala/runtime/IntRef;
const #98 = class	#97;	//  scala/runtime/IntRef
const #99 = Asciz	(I)V;
const #100 = NameAndType	#11:#99;//  "<init>":(I)V
const #101 = Method	#98.#100;	//  scala/runtime/IntRef."<init>":(I)V
const #102 = Asciz	scala/actors/Futures$$anonfun$2;
const #103 = class	#102;	//  scala/actors/Futures$$anonfun$2
const #104 = Asciz	(Lscala/runtime/IntRef;)V;
const #105 = NameAndType	#11:#104;//  "<init>":(Lscala/runtime/IntRef;)V
const #106 = Method	#103.#105;	//  scala/actors/Futures$$anonfun$2."<init>":(Lscala/runtime/IntRef;)V
const #107 = Asciz	scala/collection/Sequence$;
const #108 = class	#107;	//  scala/collection/Sequence$
const #109 = Asciz	Lscala/collection/Sequence$;;
const #110 = NameAndType	#4:#109;//  MODULE$:Lscala/collection/Sequence$;
const #111 = Field	#108.#110;	//  scala/collection/Sequence$.MODULE$:Lscala/collection/Sequence$;
const #112 = Asciz	builderFactory;
const #113 = Asciz	()Lscala/collection/generic/BuilderFactory;;
const #114 = NameAndType	#112:#113;//  builderFactory:()Lscala/collection/generic/BuilderFactory;
const #115 = Method	#108.#114;	//  scala/collection/Sequence$.builderFactory:()Lscala/collection/generic/BuilderFactory;
const #116 = Asciz	scala/collection/generic/TraversableTemplate;
const #117 = class	#116;	//  scala/collection/generic/TraversableTemplate
const #118 = Asciz	map;
const #119 = Asciz	(Lscala/Function1;Lscala/collection/generic/BuilderFactory;)Ljava/lang/Object;;
const #120 = NameAndType	#118:#119;//  map:(Lscala/Function1;Lscala/collection/generic/BuilderFactory;)Ljava/lang/Object;
const #121 = InterfaceMethod	#117.#120;	//  scala/collection/generic/TraversableTemplate.map:(Lscala/Function1;Lscala/collection/generic/BuilderFactory;)Ljava/lang/Object;
const #122 = Asciz	scala/collection/Sequence;
const #123 = class	#122;	//  scala/collection/Sequence
const #124 = Asciz	scala/runtime/ScalaRunTime$;
const #125 = class	#124;	//  scala/runtime/ScalaRunTime$
const #126 = Asciz	Lscala/runtime/ScalaRunTime$;;
const #127 = NameAndType	#4:#126;//  MODULE$:Lscala/runtime/ScalaRunTime$;
const #128 = Field	#125.#127;	//  scala/runtime/ScalaRunTime$.MODULE$:Lscala/runtime/ScalaRunTime$;
const #129 = Asciz	boxArray;
const #130 = Asciz	(Ljava/lang/Object;)Lscala/runtime/BoxedArray;;
const #131 = NameAndType	#129:#130;//  boxArray:(Ljava/lang/Object;)Lscala/runtime/BoxedArray;
const #132 = Method	#125.#131;	//  scala/runtime/ScalaRunTime$.boxArray:(Ljava/lang/Object;)Lscala/runtime/BoxedArray;
const #133 = Asciz	scala/actors/Futures$$anonfun$3;
const #134 = class	#133;	//  scala/actors/Futures$$anonfun$3
const #135 = Method	#134.#57;	//  scala/actors/Futures$$anonfun$3."<init>":(Lscala/runtime/ObjectRef;)V
const #136 = Asciz	filter;
const #137 = Asciz	(Lscala/Function1;)Lscala/collection/generic/TraversableTemplate;;
const #138 = NameAndType	#136:#137;//  filter:(Lscala/Function1;)Lscala/collection/generic/TraversableTemplate;
const #139 = InterfaceMethod	#117.#138;	//  scala/collection/generic/TraversableTemplate.filter:(Lscala/Function1;)Lscala/collection/generic/TraversableTemplate;
const #140 = Asciz	scala/actors/Futures$$anonfun$4;
const #141 = class	#140;	//  scala/actors/Futures$$anonfun$4
const #142 = Method	#141.#12;	//  scala/actors/Futures$$anonfun$4."<init>":()V
const #143 = NameAndType	#24:#25;//  awaitWith$1:(Lscala/collection/Sequence;Lscala/runtime/ObjectRef;)V
const #144 = Method	#10.#143;	//  scala/actors/Futures$.awaitWith$1:(Lscala/collection/Sequence;Lscala/runtime/ObjectRef;)V
const #145 = Asciz	scala/collection/immutable/Nil$;
const #146 = class	#145;	//  scala/collection/immutable/Nil$
const #147 = Asciz	Lscala/collection/immutable/Nil$;;
const #148 = NameAndType	#4:#147;//  MODULE$:Lscala/collection/immutable/Nil$;
const #149 = Field	#146.#148;	//  scala/collection/immutable/Nil$.MODULE$:Lscala/collection/immutable/Nil$;
const #150 = Asciz	scala/collection/mutable/Map;
const #151 = class	#150;	//  scala/collection/mutable/Map
const #152 = Asciz	size;
const #153 = Asciz	()I;
const #154 = NameAndType	#152:#153;//  size:()I
const #155 = InterfaceMethod	#117.#154;	//  scala/collection/generic/TraversableTemplate.size:()I
const #156 = Asciz	scala/Predef$;
const #157 = class	#156;	//  scala/Predef$
const #158 = Asciz	Lscala/Predef$;;
const #159 = NameAndType	#4:#158;//  MODULE$:Lscala/Predef$;
const #160 = Field	#157.#159;	//  scala/Predef$.MODULE$:Lscala/Predef$;
const #161 = Asciz	intWrapper;
const #162 = Asciz	(I)Lscala/runtime/RichInt;;
const #163 = NameAndType	#161:#162;//  intWrapper:(I)Lscala/runtime/RichInt;
const #164 = Method	#157.#163;	//  scala/Predef$.intWrapper:(I)Lscala/runtime/RichInt;
const #165 = Asciz	scala/runtime/RichInt;
const #166 = class	#165;	//  scala/runtime/RichInt
const #167 = Asciz	until;
const #168 = Asciz	(I)Lscala/Range;;
const #169 = NameAndType	#167:#168;//  until:(I)Lscala/Range;
const #170 = Method	#166.#169;	//  scala/runtime/RichInt.until:(I)Lscala/Range;
const #171 = Asciz	scala/actors/Futures$$anonfun$awaitAll$1;
const #172 = class	#171;	//  scala/actors/Futures$$anonfun$awaitAll$1
const #173 = Asciz	(Lscala/runtime/ObjectRef;Lscala/runtime/ObjectRef;I)V;
const #174 = NameAndType	#11:#173;//  "<init>":(Lscala/runtime/ObjectRef;Lscala/runtime/ObjectRef;I)V
const #175 = Method	#172.#174;	//  scala/actors/Futures$$anonfun$awaitAll$1."<init>":(Lscala/runtime/ObjectRef;Lscala/runtime/ObjectRef;I)V
const #176 = Asciz	scala/Range;
const #177 = class	#176;	//  scala/Range
const #178 = Asciz	foreach;
const #179 = Asciz	(Lscala/Function1;)V;
const #180 = NameAndType	#178:#179;//  foreach:(Lscala/Function1;)V
const #181 = Method	#177.#180;	//  scala/Range.foreach:(Lscala/Function1;)V
const #182 = Asciz	scala/collection/immutable/List;
const #183 = class	#182;	//  scala/collection/immutable/List
const #184 = Asciz	timeout;
const #185 = Asciz	J;
const #186 = Asciz	fts;
const #187 = Asciz	thisActor$1;
const #188 = Asciz	Lscala/actors/Actor;;
const #189 = Asciz	resultsMap$1;
const #190 = Asciz	Lscala/runtime/ObjectRef;;
const #191 = Asciz	cnt$1;
const #192 = Asciz	Lscala/runtime/IntRef;;
const #193 = Asciz	mappedFts;
const #194 = Asciz	unsetFts;
const #195 = Asciz	partFuns;
const #196 = Asciz	results$1;
const #197 = Asciz	size$1;
const #198 = Asciz	(JLscala/collection/Sequence<Lscala/actors/Future<Ljava/lang/Object;>;>;)Lscala/collection/immutable/List<Lscala/Option<Ljava/lang/Object;>;>;;
const #199 = Asciz	awaitEither;
const #200 = Asciz	(Lscala/actors/Future;Lscala/actors/Future;)Ljava/lang/Object;;
const #201 = Asciz	scala/actors/Future;
const #202 = class	#201;	//  scala/actors/Future
const #203 = Asciz	inputChannel;
const #204 = Asciz	()Lscala/actors/InputChannel;;
const #205 = NameAndType	#203:#204;//  inputChannel:()Lscala/actors/InputChannel;
const #206 = Method	#202.#205;	//  scala/actors/Future.inputChannel:()Lscala/actors/InputChannel;
const #207 = Asciz	scala/actors/Futures$$anonfun$awaitEither$1;
const #208 = class	#207;	//  scala/actors/Futures$$anonfun$awaitEither$1
const #209 = Asciz	(Lscala/actors/InputChannel;Lscala/actors/InputChannel;)V;
const #210 = NameAndType	#11:#209;//  "<init>":(Lscala/actors/InputChannel;Lscala/actors/InputChannel;)V
const #211 = Method	#208.#210;	//  scala/actors/Futures$$anonfun$awaitEither$1."<init>":(Lscala/actors/InputChannel;Lscala/actors/InputChannel;)V
const #212 = Asciz	ft1;
const #213 = Asciz	Lscala/actors/Future;;
const #214 = Asciz	ft2;
const #215 = Asciz	FutCh1$1;
const #216 = Asciz	FutCh2$1;
const #217 = Asciz	<a:Ljava/lang/Object;b:Ljava/lang/Object;>(Lscala/actors/Future<Ta;>;Lscala/actors/Future<Tb;>;)Ljava/lang/Object;;
const #218 = Asciz	alarm;
const #219 = Asciz	(J)Lscala/actors/Future;;
const #220 = Asciz	scala/actors/Futures$$anonfun$alarm$1;
const #221 = class	#220;	//  scala/actors/Futures$$anonfun$alarm$1
const #222 = Asciz	(J)V;
const #223 = NameAndType	#11:#222;//  "<init>":(J)V
const #224 = Method	#221.#223;	//  scala/actors/Futures$$anonfun$alarm$1."<init>":(J)V
const #225 = Asciz	future;
const #226 = Asciz	(Lscala/Function0;)Lscala/actors/Future;;
const #227 = NameAndType	#225:#226;//  future:(Lscala/Function0;)Lscala/actors/Future;
const #228 = Method	#10.#227;	//  scala/actors/Futures$.future:(Lscala/Function0;)Lscala/actors/Future;
const #229 = Asciz	t$1;
const #230 = Asciz	(J)Lscala/actors/Future<Lscala/runtime/Nothing$;>;;
const #231 = Asciz	scala/actors/Futures$$anon$1;
const #232 = class	#231;	//  scala/actors/Futures$$anon$1
const #233 = Asciz	(Lscala/Function0;Lscala/runtime/ObjectRef;)V;
const #234 = NameAndType	#11:#233;//  "<init>":(Lscala/Function0;Lscala/runtime/ObjectRef;)V
const #235 = Method	#232.#234;	//  scala/actors/Futures$$anon$1."<init>":(Lscala/Function0;Lscala/runtime/ObjectRef;)V
const #236 = Asciz	scala/actors/Actor;
const #237 = class	#236;	//  scala/actors/Actor
const #238 = Asciz	start;
const #239 = NameAndType	#238:#73;//  start:()Lscala/actors/Actor;
const #240 = InterfaceMethod	#237.#239;	//  scala/actors/Actor.start:()Lscala/actors/Actor;
const #241 = Asciz	scala/actors/ReplyableActor;
const #242 = class	#241;	//  scala/actors/ReplyableActor
const #243 = NameAndType	#46:#47;//  Eval$1:(Lscala/runtime/ObjectRef;)Lscala/actors/Futures$Eval$2$;
const #244 = Method	#10.#243;	//  scala/actors/Futures$.Eval$1:(Lscala/runtime/ObjectRef;)Lscala/actors/Futures$Eval$2$;
const #245 = Asciz	scala/actors/Futures$$anonfun$future$1;
const #246 = class	#245;	//  scala/actors/Futures$$anonfun$future$1
const #247 = Method	#246.#12;	//  scala/actors/Futures$$anonfun$future$1."<init>":()V
const #248 = Asciz	$bang$bang;
const #249 = Asciz	(Ljava/lang/Object;Lscala/PartialFunction;)Lscala/actors/Future;;
const #250 = NameAndType	#248:#249;//  $bang$bang:(Ljava/lang/Object;Lscala/PartialFunction;)Lscala/actors/Future;
const #251 = InterfaceMethod	#242.#250;	//  scala/actors/ReplyableActor.$bang$bang:(Ljava/lang/Object;Lscala/PartialFunction;)Lscala/actors/Future;
const #252 = Asciz	body$1;
const #253 = Asciz	Lscala/Function0;;
const #254 = Asciz	Eval$module$1;
const #255 = Asciz	a;
const #256 = Asciz	<T:Ljava/lang/Object;>(Lscala/Function0<TT;>;)Lscala/actors/Future<TT;>;;
const #257 = Asciz	()Lscala/actors/scheduler/DefaultExecutorScheduler;;
const #258 = NameAndType	#14:#15;//  bitmap$0:I
const #259 = Field	#10.#258;	//  scala/actors/Futures$.bitmap$0:I
const #260 = Asciz	scala/actors/scheduler/DefaultExecutorScheduler;
const #261 = class	#260;	//  scala/actors/scheduler/DefaultExecutorScheduler
const #262 = Asciz	(Z)V;
const #263 = NameAndType	#11:#262;//  "<init>":(Z)V
const #264 = Method	#261.#263;	//  scala/actors/scheduler/DefaultExecutorScheduler."<init>":(Z)V
const #265 = NameAndType	#16:#17;//  scala$actors$Futures$$sched:Lscala/actors/scheduler/DefaultExecutorScheduler;
const #266 = Field	#10.#265;	//  scala/actors/Futures$.scala$actors$Futures$$sched:Lscala/actors/scheduler/DefaultExecutorScheduler;
const #267 = Asciz	scala/runtime/BoxedUnit;
const #268 = class	#267;	//  scala/runtime/BoxedUnit
const #269 = Asciz	UNIT;
const #270 = Asciz	Lscala/runtime/BoxedUnit;;
const #271 = NameAndType	#269:#270;//  UNIT:Lscala/runtime/BoxedUnit;
const #272 = Field	#268.#271;	//  scala/runtime/BoxedUnit.UNIT:Lscala/runtime/BoxedUnit;
const #273 = Asciz	InnerClasses;
const #274 = Asciz	scala/actors/Futures;
const #275 = class	#274;	//  scala/actors/Futures
const #276 = Asciz	Eval$2;
const #277 = Asciz	$anon$4;
const #278 = Asciz	$anon$1;
const #279 = Asciz	$anon$3;
const #280 = Asciz	$anon$2;
const #281 = Asciz	$anonfun$4;
const #282 = Asciz	$anonfun$2;
const #283 = Asciz	$anonfun$3;
const #284 = Asciz	$anonfun$alarm$1;
const #285 = Asciz	$anonfun$future$1;
const #286 = Asciz	$anonfun$awaitAll$1;
const #287 = Asciz	$anonfun$awaitEither$1;
const #288 = Asciz	scala/ScalaObject;
const #289 = class	#288;	//  scala/ScalaObject

{
public static final scala.actors.Futures$ MODULE$;

public volatile int bitmap$0;

public static {};
  Code:
   Stack=1, Locals=0, Args_size=0
   0:	new	#10; //class scala/actors/Futures$
   3:	invokespecial	#13; //Method "<init>":()V
   6:	return

public final void awaitWith$1(scala.collection.Sequence, scala.runtime.ObjectRef);
  Code:
   Stack=4, Locals=4, Args_size=3
   0:	new	#27; //class scala/actors/Futures$$anon$3
   3:	dup
   4:	aload_2
   5:	aload_1
   6:	invokespecial	#30; //Method scala/actors/Futures$$anon$3."<init>":(Lscala/runtime/ObjectRef;Lscala/collection/Sequence;)V
   9:	astore_3
   10:	getstatic	#35; //Field scala/actors/Actor$.MODULE$:Lscala/actors/Actor$;
   13:	aload_3
   14:	invokevirtual	#39; //Method scala/actors/Actor$.receive:(Lscala/PartialFunction;)Ljava/lang/Object;
   17:	pop
   18:	return
  LineNumberTable: 
   line 109: 0
   line 129: 10

  LocalVariableTable: 
   Start  Length  Slot  Name   Signature
   0      19      0    this       Lscala/actors/Futures$;
   0      19      1    partFuns$1       Lscala/collection/Sequence;
   10      8      3    reaction       Lscala/PartialFunction;


public final scala.actors.Futures$Eval$2$ Eval$1(scala.runtime.ObjectRef);
  Code:
   Stack=4, Locals=2, Args_size=2
   0:	aload_1
   1:	getfield	#53; //Field scala/runtime/ObjectRef.elem:Ljava/lang/Object;
   4:	checkcast	#55; //class scala/actors/Futures$Eval$2$
   7:	ifnonnull	22
   10:	aload_1
   11:	new	#55; //class scala/actors/Futures$Eval$2$
   14:	dup
   15:	aload_1
   16:	invokespecial	#58; //Method scala/actors/Futures$Eval$2$."<init>":(Lscala/runtime/ObjectRef;)V
   19:	putfield	#53; //Field scala/runtime/ObjectRef.elem:Ljava/lang/Object;
   22:	aload_1
   23:	getfield	#53; //Field scala/runtime/ObjectRef.elem:Ljava/lang/Object;
   26:	checkcast	#55; //class scala/actors/Futures$Eval$2$
   29:	areturn
  LineNumberTable: 
   line 46: 0


public scala.actors.Future fromInputChannel(scala.actors.InputChannel);
  Code:
   Stack=3, Locals=2, Args_size=2
   0:	new	#62; //class scala/actors/Futures$$anon$2
   3:	dup
   4:	aload_1
   5:	invokespecial	#65; //Method scala/actors/Futures$$anon$2."<init>":(Lscala/actors/InputChannel;)V
   8:	areturn
  LineNumberTable: 
   line 143: 0

  LocalVariableTable: 
   Start  Length  Slot  Name   Signature
   0      9      0    this       Lscala/actors/Futures$;
   0      9      1    inputChannel$1       Lscala/actors/InputChannel;

  Signature: length = 0x2
   00 44 

public scala.collection.immutable.List awaitAll(long, scala.collection.Sequence);
  Code:
   Stack=6, Locals=14, Args_size=3
   0:	getstatic	#35; //Field scala/actors/Actor$.MODULE$:Lscala/actors/Actor$;
   3:	invokevirtual	#75; //Method scala/actors/Actor$.self:()Lscala/actors/Actor;
   6:	astore	4
   8:	getstatic	#35; //Field scala/actors/Actor$.MODULE$:Lscala/actors/Actor$;
   11:	invokevirtual	#79; //Method scala/actors/Actor$.timer:()Ljava/util/Timer;
   14:	new	#81; //class scala/actors/Futures$$anon$4
   17:	dup
   18:	aload	4
   20:	invokespecial	#84; //Method scala/actors/Futures$$anon$4."<init>":(Lscala/actors/Actor;)V
   23:	lload_1
   24:	invokevirtual	#90; //Method java/util/Timer.schedule:(Ljava/util/TimerTask;J)V
   27:	new	#49; //class scala/runtime/ObjectRef
   30:	dup
   31:	new	#92; //class scala/collection/mutable/HashMap
   34:	dup
   35:	invokespecial	#93; //Method scala/collection/mutable/HashMap."<init>":()V
   38:	invokespecial	#96; //Method scala/runtime/ObjectRef."<init>":(Ljava/lang/Object;)V
   41:	astore	5
   43:	new	#98; //class scala/runtime/IntRef
   46:	dup
   47:	iconst_0
   48:	invokespecial	#101; //Method scala/runtime/IntRef."<init>":(I)V
   51:	astore	6
   53:	aload_3
   54:	new	#103; //class scala/actors/Futures$$anonfun$2
   57:	dup
   58:	aload	6
   60:	invokespecial	#106; //Method scala/actors/Futures$$anonfun$2."<init>":(Lscala/runtime/IntRef;)V
   63:	getstatic	#111; //Field scala/collection/Sequence$.MODULE$:Lscala/collection/Sequence$;
   66:	invokevirtual	#115; //Method scala/collection/Sequence$.builderFactory:()Lscala/collection/generic/BuilderFactory;
   69:	invokeinterface	#121,  3; //InterfaceMethod scala/collection/generic/TraversableTemplate.map:(Lscala/Function1;Lscala/collection/generic/BuilderFactory;)Ljava/lang/Object;
   74:	astore	8
   76:	aload	8
   78:	instanceof	#123; //class scala/collection/Sequence
   81:	ifeq	89
   84:	aload	8
   86:	goto	97
   89:	getstatic	#128; //Field scala/runtime/ScalaRunTime$.MODULE$:Lscala/runtime/ScalaRunTime$;
   92:	aload	8
   94:	invokevirtual	#132; //Method scala/runtime/ScalaRunTime$.boxArray:(Ljava/lang/Object;)Lscala/runtime/BoxedArray;
   97:	checkcast	#123; //class scala/collection/Sequence
   100:	astore	7
   102:	aload	7
   104:	new	#134; //class scala/actors/Futures$$anonfun$3
   107:	dup
   108:	aload	5
   110:	invokespecial	#135; //Method scala/actors/Futures$$anonfun$3."<init>":(Lscala/runtime/ObjectRef;)V
   113:	invokeinterface	#139,  2; //InterfaceMethod scala/collection/generic/TraversableTemplate.filter:(Lscala/Function1;)Lscala/collection/generic/TraversableTemplate;
   118:	checkcast	#123; //class scala/collection/Sequence
   121:	astore	9
   123:	aload	9
   125:	new	#141; //class scala/actors/Futures$$anonfun$4
   128:	dup
   129:	invokespecial	#142; //Method scala/actors/Futures$$anonfun$4."<init>":()V
   132:	getstatic	#111; //Field scala/collection/Sequence$.MODULE$:Lscala/collection/Sequence$;
   135:	invokevirtual	#115; //Method scala/collection/Sequence$.builderFactory:()Lscala/collection/generic/BuilderFactory;
   138:	invokeinterface	#121,  3; //InterfaceMethod scala/collection/generic/TraversableTemplate.map:(Lscala/Function1;Lscala/collection/generic/BuilderFactory;)Ljava/lang/Object;
   143:	astore	11
   145:	aload	11
   147:	instanceof	#123; //class scala/collection/Sequence
   150:	ifeq	158
   153:	aload	11
   155:	goto	166
   158:	getstatic	#128; //Field scala/runtime/ScalaRunTime$.MODULE$:Lscala/runtime/ScalaRunTime$;
   161:	aload	11
   163:	invokevirtual	#132; //Method scala/runtime/ScalaRunTime$.boxArray:(Ljava/lang/Object;)Lscala/runtime/BoxedArray;
   166:	checkcast	#123; //class scala/collection/Sequence
   169:	astore	10
   171:	aload_0
   172:	aload	10
   174:	aload	5
   176:	invokevirtual	#144; //Method awaitWith$1:(Lscala/collection/Sequence;Lscala/runtime/ObjectRef;)V
   179:	new	#49; //class scala/runtime/ObjectRef
   182:	dup
   183:	getstatic	#149; //Field scala/collection/immutable/Nil$.MODULE$:Lscala/collection/immutable/Nil$;
   186:	invokespecial	#96; //Method scala/runtime/ObjectRef."<init>":(Ljava/lang/Object;)V
   189:	astore	12
   191:	aload	5
   193:	getfield	#53; //Field scala/runtime/ObjectRef.elem:Ljava/lang/Object;
   196:	checkcast	#151; //class scala/collection/mutable/Map
   199:	invokeinterface	#155,  1; //InterfaceMethod scala/collection/generic/TraversableTemplate.size:()I
   204:	istore	13
   206:	getstatic	#160; //Field scala/Predef$.MODULE$:Lscala/Predef$;
   209:	iconst_0
   210:	invokevirtual	#164; //Method scala/Predef$.intWrapper:(I)Lscala/runtime/RichInt;
   213:	iload	13
   215:	invokevirtual	#170; //Method scala/runtime/RichInt.until:(I)Lscala/Range;
   218:	new	#172; //class scala/actors/Futures$$anonfun$awaitAll$1
   221:	dup
   222:	aload	5
   224:	aload	12
   226:	iload	13
   228:	invokespecial	#175; //Method scala/actors/Futures$$anonfun$awaitAll$1."<init>":(Lscala/runtime/ObjectRef;Lscala/runtime/ObjectRef;I)V
   231:	invokevirtual	#181; //Method scala/Range.foreach:(Lscala/Function1;)V
   234:	aload	12
   236:	getfield	#53; //Field scala/runtime/ObjectRef.elem:Ljava/lang/Object;
   239:	checkcast	#183; //class scala/collection/immutable/List
   242:	areturn
  LineNumberTable: 
   line 84: 0
   line 85: 8
   line 87: 23
   line 85: 24
   line 89: 27
   line 91: 43
   line 92: 53
   line 100: 97
   line 92: 100
   line 95: 102
   line 100: 123
   line 132: 171
   line 134: 179
   line 135: 191
   line 136: 206
   line 139: 234

  LocalVariableTable: 
   Start  Length  Slot  Name   Signature
   0      243      0    this       Lscala/actors/Futures$;
   0      243      1    timeout       J
   0      243      3    fts       Lscala/collection/Sequence;
   8      234      4    thisActor$1       Lscala/actors/Actor;
   43      199      5    resultsMap$1       Lscala/runtime/ObjectRef;
   53      189      6    cnt$1       Lscala/runtime/IntRef;
   102      140      7    mappedFts       Lscala/collection/Sequence;
   123      119      9    unsetFts       Lscala/collection/Sequence;
   171      71      10    partFuns       Lscala/collection/Sequence;
   191      51      12    results$1       Lscala/runtime/ObjectRef;
   206      36      13    size$1       I

  Signature: length = 0x2
   00 FFFFFFC6 

public java.lang.Object awaitEither(scala.actors.Future, scala.actors.Future);
  Code:
   Stack=5, Locals=5, Args_size=3
   0:	aload_1
   1:	invokevirtual	#206; //Method scala/actors/Future.inputChannel:()Lscala/actors/InputChannel;
   4:	astore_3
   5:	aload_2
   6:	invokevirtual	#206; //Method scala/actors/Future.inputChannel:()Lscala/actors/InputChannel;
   9:	astore	4
   11:	getstatic	#35; //Field scala/actors/Actor$.MODULE$:Lscala/actors/Actor$;
   14:	new	#208; //class scala/actors/Futures$$anonfun$awaitEither$1
   17:	dup
   18:	aload_3
   19:	aload	4
   21:	invokespecial	#211; //Method scala/actors/Futures$$anonfun$awaitEither$1."<init>":(Lscala/actors/InputChannel;Lscala/actors/InputChannel;)V
   24:	invokevirtual	#39; //Method scala/actors/Actor$.receive:(Lscala/PartialFunction;)Ljava/lang/Object;
   27:	areturn
  LineNumberTable: 
   line 66: 0
   line 67: 5
   line 68: 11

  LocalVariableTable: 
   Start  Length  Slot  Name   Signature
   0      28      0    this       Lscala/actors/Futures$;
   0      28      1    ft1       Lscala/actors/Future;
   0      28      2    ft2       Lscala/actors/Future;
   5      22      3    FutCh1$1       Lscala/actors/InputChannel;
   11      16      4    FutCh2$1       Lscala/actors/InputChannel;

  Signature: length = 0x2
   00 FFFFFFD9 

public scala.actors.Future alarm(long);
  Code:
   Stack=5, Locals=3, Args_size=2
   0:	aload_0
   1:	new	#221; //class scala/actors/Futures$$anonfun$alarm$1
   4:	dup
   5:	lload_1
   6:	invokespecial	#224; //Method scala/actors/Futures$$anonfun$alarm$1."<init>":(J)V
   9:	invokevirtual	#228; //Method future:(Lscala/Function0;)Lscala/actors/Future;
   12:	areturn
  LineNumberTable: 
   line 59: 0
   line 60: 1
   line 59: 9

  LocalVariableTable: 
   Start  Length  Slot  Name   Signature
   0      13      0    this       Lscala/actors/Futures$;
   0      13      1    t$1       J

  Signature: length = 0x2
   00 FFFFFFE6 

public scala.actors.Future future(scala.Function0);
  Code:
   Stack=4, Locals=4, Args_size=2
   0:	new	#49; //class scala/runtime/ObjectRef
   3:	dup
   4:	aconst_null
   5:	pop
   6:	aconst_null
   7:	invokespecial	#96; //Method scala/runtime/ObjectRef."<init>":(Ljava/lang/Object;)V
   10:	astore_2
   11:	new	#232; //class scala/actors/Futures$$anon$1
   14:	dup
   15:	aload_1
   16:	aload_2
   17:	invokespecial	#235; //Method scala/actors/Futures$$anon$1."<init>":(Lscala/Function0;Lscala/runtime/ObjectRef;)V
   20:	astore_3
   21:	aload_3
   22:	checkcast	#237; //class scala/actors/Actor
   25:	invokeinterface	#240,  1; //InterfaceMethod scala/actors/Actor.start:()Lscala/actors/Actor;
   30:	pop
   31:	aload_3
   32:	checkcast	#242; //class scala/actors/ReplyableActor
   35:	aload_0
   36:	aload_2
   37:	invokevirtual	#244; //Method Eval$1:(Lscala/runtime/ObjectRef;)Lscala/actors/Futures$Eval$2$;
   40:	new	#246; //class scala/actors/Futures$$anonfun$future$1
   43:	dup
   44:	invokespecial	#247; //Method scala/actors/Futures$$anonfun$future$1."<init>":()V
   47:	invokeinterface	#251,  3; //InterfaceMethod scala/actors/ReplyableActor.$bang$bang:(Ljava/lang/Object;Lscala/PartialFunction;)Lscala/actors/Future;
   52:	areturn
  LineNumberTable: 
   line 46: 0
   line 47: 11
   line 55: 21
   line 56: 31

  LocalVariableTable: 
   Start  Length  Slot  Name   Signature
   0      53      0    this       Lscala/actors/Futures$;
   0      53      1    body$1       Lscala/Function0;
   11      41      2    Eval$module$1       Lscala/runtime/ObjectRef;
   21      31      3    a       Ljava/lang/Object;

  Signature: length = 0x2
   01 00 

public final scala.actors.scheduler.DefaultExecutorScheduler scala$actors$Futures$$sched();
  Code:
   Stack=4, Locals=2, Args_size=1
   0:	aload_0
   1:	getfield	#259; //Field bitmap$0:I
   4:	iconst_1
   5:	iand
   6:	iconst_0
   7:	if_icmpne	52
   10:	aload_0
   11:	dup
   12:	astore_1
   13:	monitorenter
   14:	aload_0
   15:	getfield	#259; //Field bitmap$0:I
   18:	iconst_1
   19:	iand
   20:	iconst_0
   21:	if_icmpne	46
   24:	aload_0
   25:	new	#261; //class scala/actors/scheduler/DefaultExecutorScheduler
   28:	dup
   29:	iconst_1
   30:	invokespecial	#264; //Method scala/actors/scheduler/DefaultExecutorScheduler."<init>":(Z)V
   33:	putfield	#266; //Field scala$actors$Futures$$sched:Lscala/actors/scheduler/DefaultExecutorScheduler;
   36:	aload_0
   37:	aload_0
   38:	getfield	#259; //Field bitmap$0:I
   41:	iconst_1
   42:	ior
   43:	putfield	#259; //Field bitmap$0:I
   46:	getstatic	#272; //Field scala/runtime/BoxedUnit.UNIT:Lscala/runtime/BoxedUnit;
   49:	pop
   50:	aload_1
   51:	monitorexit
   52:	aload_0
   53:	getfield	#266; //Field scala$actors$Futures$$sched:Lscala/actors/scheduler/DefaultExecutorScheduler;
   56:	areturn
   57:	aload_1
   58:	monitorexit
   59:	athrow
  Exception table:
   from   to  target type
    14    52    57   any
  LineNumberTable: 
   line 43: 0
   line 41: 6
   line 43: 10
   line 41: 20
   line 43: 24


}

