Compiled from "Future.scala"
public abstract class scala.actors.Future extends scala.Responder implements scala.Function0,scala.ScalaObject
  SourceFile: "Future.scala"
  Signature: length = 0x2
   00 4C 
  ScalaSig: length = 0x281
   05 00 5E 06 05 01 02 FFFFFF81 00 07 02 06 46 75 74 75
   72 65 0A 02 03 04 01 06 61 63 74 6F 72 73 0A 01
   05 01 05 73 63 61 6C 61 03 00 15 02 08 0F 13 04
   00 09 18 1B 10 03 0A 0B 0D 0D 01 04 09 02 0C 04
   02 09 52 65 73 70 6F 6E 64 65 72 10 02 0E 0F 0C
   00 04 08 10 00 FFFFFF84 FFFFFF80 FFFFFF84 FFFFFFC2 00 11 02 01 54 11 02
   12 15 10 02 0A 13 09 02 14 04 02 07 4E 6F 74 68
   69 6E 67 10 02 0A 16 09 02 17 04 02 03 41 6E 79
   10 03 0A 19 0D 09 02 1A 04 02 09 46 75 6E 63 74
   69 6F 6E 30 10 02 0A 1C 09 02 1D 04 02 0B 53 63
   61 6C 61 4F 62 6A 65 63 74 08 08 1F 00 FFFFFF82 FFFFFFC2 FFFFFF80
   FFFFFF84 00 20 01 0C 69 6E 70 75 74 43 68 61 6E 6E 65
   6C 15 01 21 10 03 22 23 0D 0D 01 02 09 02 24 02
   02 0C 49 6E 70 75 74 43 68 61 6E 6E 65 6C 08 08
   26 00 FFFFFF82 FFFFFF80 FFFFFFA0 FFFFFF80 04 21 01 0D 69 6E 70 75 74 43
   68 61 6E 6E 65 6C 20 08 05 28 00 FFFFFF84 00 29 01 06
   3C 69 6E 69 74 3E 14 02 2A 2B 10 03 22 00 0D 08
   05 1F 27 FFFFFFC0 00 21 08 08 2D 00 FFFFFFC0 FFFFFF80 FFFFFF84 00 02 2E
   01 06 66 76 61 6C 75 65 15 01 2F 10 03 0A 30 15
   09 02 31 04 02 06 4F 70 74 69 6F 6E 08 08 33 00
   FFFFFFC0 FFFFFF80 FFFFFF84 00 02 34 01 0A 66 76 61 6C 75 65 5F 24
   65 71 14 02 35 38 10 02 0A 36 09 02 37 04 02 04
   55 6E 69 74 08 07 39 32 FFFFFF81 FFFFFF80 FFFFFFC0 00 2F 01 03 78
   24 31 08 06 3B 00 FFFFFFA0 FFFFFFA0 04 2F 01 07 66 76 61 6C
   75 65 20 28 02 3A 3D 10 02 0A 3E 09 02 3F 04 02
   08 76 6F 6C 61 74 69 6C 65 08 06 41 00 FFFFFF84 00 02
   42 01 0B 66 76 61 6C 75 65 54 79 70 65 64 15 01
   0D 08 07 44 00 FFFFFFC2 FFFFFF80 FFFFFF84 00 45 01 02 63 68 15 01
   46 10 03 22 23 15 28 03 43 48 4B 10 02 0A 49 09
   02 4A 04 02 0A 64 65 70 72 65 63 61 74 65 64 21
   01 4C 01 36 74 68 69 73 20 6D 65 6D 62 65 72 20
   69 73 20 67 6F 69 6E 67 20 74 6F 20 62 65 20 72
   65 6D 6F 76 65 64 20 69 6E 20 61 20 66 75 74 75
   72 65 20 72 65 6C 65 61 73 65 08 06 4E 00 FFFFFFA0 FFFFFF80
   04 46 01 03 63 68 20 08 05 50 00 FFFFFF84 08 2E 01 05
   76 61 6C 75 65 28 03 4F 48 4B 08 05 53 00 FFFFFF84 08
   54 01 09 76 61 6C 75 65 5F 24 65 71 14 02 35 55
   08 05 56 52 FFFFFFC0 00 2F 01 01 78 28 03 52 48 4B 08
   05 59 00 FFFFFF86 00 5A 01 05 69 73 53 65 74 15 01 5B
   10 02 0A 5C 09 02 5D 04 02 07 42 6F 6F 6C 65 61
   6E 
  minor version: 0
  major version: 49
  Constant pool:
Asciz	SourceFile;
Asciz	Future.scala;
Asciz	ch;
Asciz	Lscala/actors/InputChannel;;
Asciz	Lscala/actors/InputChannel<Ljava/lang/Object;>;;
Asciz	Signature;
Asciz	fvalue;
Asciz	Lscala/Option;;
Asciz	Lscala/Option<Ljava/lang/Object;>;;
Asciz	inputChannel;
Asciz	Lscala/actors/InputChannel<TT;>;;
Asciz	toString;
Asciz	()Ljava/lang/String;;
Asciz	Code;
Asciz	LineNumberTable;
Asciz	scala/Function0$class;
class	scala/Function0$class
Asciz	(Lscala/Function0;)Ljava/lang/String;;
NameAndType	toString:(Lscala/Function0;)Ljava/lang/String;
Method	scala/Function0$class.toString:(Lscala/Function0;)Ljava/lang/String;
Asciz	()Lscala/actors/InputChannel;;
Asciz	scala/actors/Future;
class	scala/actors/Future
NameAndType	inputChannel:Lscala/actors/InputChannel;
Field	scala/actors/Future.inputChannel:Lscala/actors/InputChannel;
Asciz	()Lscala/actors/InputChannel<TT;>;;
Asciz	()Lscala/Option;;
NameAndType	fvalue:Lscala/Option;
Field	scala/actors/Future.fvalue:Lscala/Option;
Asciz	()Lscala/Option<Ljava/lang/Object;>;;
Asciz	fvalue_$eq;
Asciz	(Lscala/Option;)V;
Asciz	(Lscala/Option<Ljava/lang/Object;>;)V;
Asciz	fvalueTyped;
Asciz	()Ljava/lang/Object;;
NameAndType	fvalue:()Lscala/Option;
Method	scala/actors/Future.fvalue:()Lscala/Option;
Asciz	scala/Option;
class	scala/Option
Asciz	get;
NameAndType	get:()Ljava/lang/Object;
Method	scala/Option.get:()Ljava/lang/Object;
Asciz	()TT;;
NameAndType	ch:Lscala/actors/InputChannel;
Field	scala/actors/Future.ch:Lscala/actors/InputChannel;
Asciz	()Lscala/actors/InputChannel<Ljava/lang/Object;>;;
Asciz	Deprecated;
Asciz	value;
Asciz	value_$eq;
NameAndType	fvalue_$eq:(Lscala/Option;)V
Method	scala/actors/Future.fvalue_$eq:(Lscala/Option;)V
Asciz	this;
Asciz	Lscala/actors/Future;;
Asciz	x;
Asciz	LocalVariableTable;
Asciz	isSet;
Asciz	()Z;
Asciz	<init>;
Asciz	(Lscala/actors/InputChannel;)V;
Asciz	scala/Responder;
class	scala/Responder
Asciz	()V;
NameAndType	"<init>":()V
Method	scala/Responder."<init>":()V
Asciz	$init$;
Asciz	(Lscala/Function0;)V;
NameAndType	$init$:(Lscala/Function0;)V
Method	scala/Function0$class.$init$:(Lscala/Function0;)V
Asciz	scala/None$;
class	scala/None$
Asciz	MODULE$;
Asciz	Lscala/None$;;
NameAndType	MODULE$:Lscala/None$;
Field	scala/None$.MODULE$:Lscala/None$;
Asciz	(Lscala/actors/InputChannel<TT;>;)V;
Asciz	<T:Ljava/lang/Object;>Lscala/Responder<TT;>;Lscala/Function0<TT;>;Lscala/ScalaObject;;
Asciz	ScalaSig;
Asciz	scala/Function0;
class	scala/Function0
Asciz	scala/ScalaObject;
class	scala/ScalaObject

{
private final scala.actors.InputChannel ch;
  Signature: Lscala/actors/InputChannel;
  Signature: length = 0x2
   00 05 

private volatile scala.Option fvalue;
  Signature: Lscala/Option;
  Signature: length = 0x2
   00 09 

private final scala.actors.InputChannel inputChannel;
  Signature: Lscala/actors/InputChannel;
  Signature: length = 0x2
   00 0B 

public java.lang.String toString();
  Signature: ()Ljava/lang/String;
  Code:
   Stack=1, Locals=1, Args_size=1
	aload_0
	invokestatic	Method scala/Function0$class.toString:(Lscala/Function0;)Ljava/lang/String;
	areturn
  Labels:

public scala.actors.InputChannel inputChannel();
  Signature: ()Lscala/actors/InputChannel;
  Code:
   Stack=1, Locals=1, Args_size=1
	aload_0
	getfield	Field inputChannel:Lscala/actors/InputChannel;
	areturn
  Labels:
  Signature: length = 0x2
   00 1A 

public scala.Option fvalue();
  Signature: ()Lscala/Option;
  Code:
   Stack=1, Locals=1, Args_size=1
	aload_0
	getfield	Field fvalue:Lscala/Option;
	areturn
  Labels:
  Signature: length = 0x2
   00 1E 

public void fvalue_$eq(scala.Option);
  Signature: (Lscala/Option;)V
  Code:
   Stack=2, Locals=2, Args_size=2
	aload_0
	aload_1
	putfield	Field fvalue:Lscala/Option;
	return
  Labels:
  Signature: length = 0x2
   00 21 

public java.lang.Object fvalueTyped();
  Signature: ()Ljava/lang/Object;
  Code:
   Stack=1, Locals=1, Args_size=1
	aload_0
	invokevirtual	Method fvalue:()Lscala/Option;
	invokevirtual	Method scala/Option.get:()Ljava/lang/Object;
	areturn
  Labels:
  Signature: length = 0x2
   00 2B 

public scala.actors.InputChannel ch();
  Signature: ()Lscala/actors/InputChannel;
  Code:
   Stack=1, Locals=1, Args_size=1
	aload_0
	getfield	Field ch:Lscala/actors/InputChannel;
	areturn
  Labels:
  Signature: length = 0x2
   00 2E 
  Deprecated: true

public scala.Option value();
  Signature: ()Lscala/Option;
  Code:
   Stack=1, Locals=1, Args_size=1
	aload_0
	invokevirtual	Method fvalue:()Lscala/Option;
	areturn
  Labels:
  Signature: length = 0x2
   00 1E 
  Deprecated: true

public void value_$eq(scala.Option);
  Signature: (Lscala/Option;)V
  Code:
   Stack=2, Locals=2, Args_size=2
	aload_0
	aload_1
	invokevirtual	Method fvalue_$eq:(Lscala/Option;)V
	return
  Labels:
  LocalVariableTable: 
   Start  Length  Slot  Name   Signature
   0      6      0    this       Lscala/actors/Future;
   0      6      1    x       Lscala/Option;

  Signature: length = 0x2
   00 21 
  Deprecated: true

public abstract boolean isSet();
  Signature: ()Z

public scala.actors.Future(scala.actors.InputChannel);
  Signature: (Lscala/actors/InputChannel;)V
  Code:
   Stack=2, Locals=2, Args_size=2
	aload_0
	aload_1
	putfield	Field inputChannel:Lscala/actors/InputChannel;
	aload_0
	invokespecial	Method scala/Responder."<init>":()V
	aload_0
	invokestatic	Method scala/Function0$class.$init$:(Lscala/Function0;)V
	aload_0
	getstatic	Field scala/None$.MODULE$:Lscala/None$;
	putfield	Field fvalue:Lscala/Option;
	aload_0
	aload_1
	putfield	Field ch:Lscala/actors/InputChannel;
	return
  Labels:
  LocalVariableTable: 
   Start  Length  Slot  Name   Signature
   0      26      0    this       Lscala/actors/Future;
   0      26      1    inputChannel       Lscala/actors/InputChannel;

  Signature: length = 0x2
   00 4B 

}

