Compiled from "Future.scala"
public final class scala.actors.Futures$ extends java.lang.Object implements scala.ScalaObject
  SourceFile: "Future.scala"
  Scala: length = 0x
   
  InnerClass: 
   public abstract ByOne=class scala/collection/immutable/Range$ByOne of class scala/collection/immutable/Range
   public final $anon$2=class scala/actors/Futures$$anon$2 of class scala/actors/Futures
   public final $anon$3=class scala/actors/Futures$$anon$3 of class scala/actors/Futures
   public final $anon$4=class scala/actors/Futures$$anon$4 of class scala/actors/Futures
   public final $anon$1=class scala/actors/Futures$$anon$1 of class scala/actors/Futures
   public final $anonfun$3=class scala/actors/Futures$$anonfun$3 of class scala/actors/Futures
   public final $anonfun$2=class scala/actors/Futures$$anonfun$2 of class scala/actors/Futures
   public final $anonfun$1=class scala/actors/Futures$$anonfun$1 of class scala/actors/Futures
   public final $anonfun$alarm$1=class scala/actors/Futures$$anonfun$alarm$1 of class scala/actors/Futures
   public final $anonfun$future$1=class scala/actors/Futures$$anonfun$future$1 of class scala/actors/Futures
   public final $anonfun$awaitAll$1=class scala/actors/Futures$$anonfun$awaitAll$1 of class scala/actors/Futures
   public final $anonfun$awaitEither$1=class scala/actors/Futures$$anonfun$awaitEither$1 of class scala/actors/Futures
  minor version: 0
  major version: 49
  Constant pool:
Asciz	SourceFile;
Asciz	Future.scala;
Asciz	Scala;
Asciz	MODULE$;
Asciz	Lscala/actors/Futures$;;
Asciz	<clinit>;
Asciz	()V;
Asciz	Code;
Asciz	scala/actors/Futures$;
class	scala/actors/Futures$
Asciz	<init>;
NameAndType	"<init>":()V
Method	scala/actors/Futures$."<init>":()V
Asciz	LineNumberTable;
Asciz	java/lang/Object;
class	java/lang/Object
Method	java/lang/Object."<init>":()V
NameAndType	MODULE$:Lscala/actors/Futures$;
Field	scala/actors/Futures$.MODULE$:Lscala/actors/Futures$;
Asciz	awaitWith$1;
Asciz	(Lscala/collection/Seq;Lscala/runtime/ObjectRef;)V;
Asciz	scala/actors/Futures$$anon$3;
class	scala/actors/Futures$$anon$3
Asciz	(Lscala/runtime/ObjectRef;Lscala/collection/Seq;)V;
NameAndType	"<init>":(Lscala/runtime/ObjectRef;Lscala/collection/Seq;)V
Method	scala/actors/Futures$$anon$3."<init>":(Lscala/runtime/ObjectRef;Lscala/collection/Seq;)V
Asciz	scala/actors/Actor$;
class	scala/actors/Actor$
Asciz	Lscala/actors/Actor$;;
NameAndType	MODULE$:Lscala/actors/Actor$;
Field	scala/actors/Actor$.MODULE$:Lscala/actors/Actor$;
Asciz	receive;
Asciz	(Lscala/PartialFunction;)Ljava/lang/Object;;
NameAndType	receive:(Lscala/PartialFunction;)Ljava/lang/Object;
Method	scala/actors/Actor$.receive:(Lscala/PartialFunction;)Ljava/lang/Object;
Asciz	this;
Asciz	partFuns$1;
Asciz	Lscala/collection/Seq;;
Asciz	reaction;
Asciz	Lscala/PartialFunction;;
Asciz	LocalVariableTable;
Asciz	fromInputChannel;
Asciz	(Lscala/actors/InputChannel;)Lscala/actors/Future;;
Asciz	scala/actors/Futures$$anon$2;
class	scala/actors/Futures$$anon$2
Asciz	(Lscala/actors/InputChannel;)V;
NameAndType	"<init>":(Lscala/actors/InputChannel;)V
Method	scala/actors/Futures$$anon$2."<init>":(Lscala/actors/InputChannel;)V
Asciz	inputChannel$1;
Asciz	Lscala/actors/InputChannel;;
Asciz	<T:Ljava/lang/Object;>(Lscala/actors/InputChannel<TT;>;)Lscala/actors/Future<TT;>;;
Asciz	Signature;
Asciz	awaitAll;
Asciz	(JLscala/collection/Seq;)Lscala/collection/immutable/List;;
Asciz	scala/actors/Scheduler$;
class	scala/actors/Scheduler$
Asciz	Lscala/actors/Scheduler$;;
NameAndType	MODULE$:Lscala/actors/Scheduler$;
Field	scala/actors/Scheduler$.MODULE$:Lscala/actors/Scheduler$;
Asciz	rawSelf;
Asciz	(Lscala/actors/IScheduler;)Lscala/actors/Reactor;;
NameAndType	rawSelf:(Lscala/actors/IScheduler;)Lscala/actors/Reactor;
Method	scala/actors/Actor$.rawSelf:(Lscala/actors/IScheduler;)Lscala/actors/Reactor;
Asciz	scala/actors/Actor;
class	scala/actors/Actor
Asciz	scala/actors/Futures$$anon$4;
class	scala/actors/Futures$$anon$4
Asciz	(Lscala/actors/Actor;)V;
NameAndType	"<init>":(Lscala/actors/Actor;)V
Method	scala/actors/Futures$$anon$4."<init>":(Lscala/actors/Actor;)V
Asciz	timer;
Asciz	()Ljava/util/Timer;;
NameAndType	timer:()Ljava/util/Timer;
Method	scala/actors/Actor$.timer:()Ljava/util/Timer;
Asciz	java/util/Timer;
class	java/util/Timer
Asciz	schedule;
Asciz	(Ljava/util/TimerTask;J)V;
NameAndType	schedule:(Ljava/util/TimerTask;J)V
Method	java/util/Timer.schedule:(Ljava/util/TimerTask;J)V
Asciz	scala/runtime/ObjectRef;
class	scala/runtime/ObjectRef
Asciz	scala/collection/mutable/HashMap;
class	scala/collection/mutable/HashMap
Method	scala/collection/mutable/HashMap."<init>":()V
Asciz	(Ljava/lang/Object;)V;
NameAndType	"<init>":(Ljava/lang/Object;)V
Method	scala/runtime/ObjectRef."<init>":(Ljava/lang/Object;)V
Asciz	scala/runtime/IntRef;
class	scala/runtime/IntRef
Asciz	(I)V;
NameAndType	"<init>":(I)V
Method	scala/runtime/IntRef."<init>":(I)V
Asciz	scala/actors/Futures$$anonfun$1;
class	scala/actors/Futures$$anonfun$1
Asciz	(Lscala/runtime/IntRef;)V;
NameAndType	"<init>":(Lscala/runtime/IntRef;)V
Method	scala/actors/Futures$$anonfun$1."<init>":(Lscala/runtime/IntRef;)V
Asciz	scala/collection/Seq$;
class	scala/collection/Seq$
Asciz	Lscala/collection/Seq$;;
NameAndType	MODULE$:Lscala/collection/Seq$;
Field	scala/collection/Seq$.MODULE$:Lscala/collection/Seq$;
Asciz	canBuildFrom;
Asciz	()Lscala/collection/generic/CanBuildFrom;;
NameAndType	canBuildFrom:()Lscala/collection/generic/CanBuildFrom;
Method	scala/collection/Seq$.canBuildFrom:()Lscala/collection/generic/CanBuildFrom;
Asciz	scala/collection/TraversableLike;
class	scala/collection/TraversableLike
Asciz	map;
Asciz	(Lscala/Function1;Lscala/collection/generic/CanBuildFrom;)Ljava/lang/Object;;
NameAndType	map:(Lscala/Function1;Lscala/collection/generic/CanBuildFrom;)Ljava/lang/Object;
InterfaceMethod	scala/collection/TraversableLike.map:(Lscala/Function1;Lscala/collection/generic/CanBuildFrom;)Ljava/lang/Object;
Asciz	scala/collection/Seq;
class	scala/collection/Seq
Asciz	scala/actors/Futures$$anonfun$2;
class	scala/actors/Futures$$anonfun$2
Asciz	(Lscala/runtime/ObjectRef;)V;
NameAndType	"<init>":(Lscala/runtime/ObjectRef;)V
Method	scala/actors/Futures$$anonfun$2."<init>":(Lscala/runtime/ObjectRef;)V
Asciz	filter;
Asciz	(Lscala/Function1;)Ljava/lang/Object;;
NameAndType	filter:(Lscala/Function1;)Ljava/lang/Object;
InterfaceMethod	scala/collection/TraversableLike.filter:(Lscala/Function1;)Ljava/lang/Object;
Asciz	scala/actors/Futures$$anonfun$3;
class	scala/actors/Futures$$anonfun$3
Method	scala/actors/Futures$$anonfun$3."<init>":()V
Asciz	scala/collection/SeqLike;
class	scala/collection/SeqLike
Asciz	length;
Asciz	()I;
NameAndType	length:()I
InterfaceMethod	scala/collection/SeqLike.length:()I
InterfaceMethod	scala/actors/Actor.receive:(Lscala/PartialFunction;)Ljava/lang/Object;
Asciz	scala/collection/immutable/Nil$;
class	scala/collection/immutable/Nil$
Asciz	Lscala/collection/immutable/Nil$;;
NameAndType	MODULE$:Lscala/collection/immutable/Nil$;
Field	scala/collection/immutable/Nil$.MODULE$:Lscala/collection/immutable/Nil$;
Asciz	elem;
Asciz	Ljava/lang/Object;;
NameAndType	elem:Ljava/lang/Object;
Field	scala/runtime/ObjectRef.elem:Ljava/lang/Object;
Asciz	scala/collection/mutable/Map;
class	scala/collection/mutable/Map
Asciz	size;
NameAndType	size:()I
InterfaceMethod	scala/collection/TraversableLike.size:()I
Asciz	scala/runtime/RichInt;
class	scala/runtime/RichInt
Method	scala/runtime/RichInt."<init>":(I)V
Asciz	scala/collection/immutable/Range$;
class	scala/collection/immutable/Range$
Asciz	Lscala/collection/immutable/Range$;;
NameAndType	MODULE$:Lscala/collection/immutable/Range$;
Field	scala/collection/immutable/Range$.MODULE$:Lscala/collection/immutable/Range$;
Asciz	start;
NameAndType	start:()I
Method	scala/runtime/RichInt.start:()I
Asciz	apply;
Asciz	(II)Lscala/collection/immutable/Range$ByOne;;
NameAndType	apply:(II)Lscala/collection/immutable/Range$ByOne;
Method	scala/collection/immutable/Range$.apply:(II)Lscala/collection/immutable/Range$ByOne;
Asciz	scala/actors/Futures$$anonfun$awaitAll$1;
class	scala/actors/Futures$$anonfun$awaitAll$1
Asciz	(Lscala/runtime/ObjectRef;Lscala/runtime/ObjectRef;I)V;
NameAndType	"<init>":(Lscala/runtime/ObjectRef;Lscala/runtime/ObjectRef;I)V
Method	scala/actors/Futures$$anonfun$awaitAll$1."<init>":(Lscala/runtime/ObjectRef;Lscala/runtime/ObjectRef;I)V
Asciz	scala/collection/immutable/Range$ByOne;
class	scala/collection/immutable/Range$ByOne
Asciz	foreach;
Asciz	(Lscala/Function1;)V;
NameAndType	foreach:(Lscala/Function1;)V
InterfaceMethod	scala/collection/immutable/Range$ByOne.foreach:(Lscala/Function1;)V
Asciz	java/util/TimerTask;
class	java/util/TimerTask
Asciz	cancel;
Asciz	()Z;
NameAndType	cancel:()Z
Method	java/util/TimerTask.cancel:()Z
Asciz	scala/collection/immutable/List;
class	scala/collection/immutable/List
Asciz	timeout;
Asciz	J;
Asciz	fts;
Asciz	thisActor$1;
Asciz	Lscala/actors/Actor;;
Asciz	cnt$1;
Asciz	Lscala/runtime/IntRef;;
Asciz	mappedFts;
Asciz	unsetFts;
Asciz	partFuns;
Asciz	reaction0;
Asciz	resultsMap$1;
Asciz	Lscala/runtime/ObjectRef;;
Asciz	size$1;
Asciz	I;
Asciz	timerTask;
Asciz	Ljava/util/TimerTask;;
Asciz	results$1;
Asciz	(JLscala/collection/Seq<Lscala/actors/Future<Ljava/lang/Object;>;>;)Lscala/collection/immutable/List<Lscala/Option<Ljava/lang/Object;>;>;;
Asciz	awaitEither;
Asciz	(Lscala/actors/Future;Lscala/actors/Future;)Ljava/lang/Object;;
Asciz	scala/actors/Future;
class	scala/actors/Future
Asciz	inputChannel;
Asciz	()Lscala/actors/InputChannel;;
NameAndType	inputChannel:()Lscala/actors/InputChannel;
Method	scala/actors/Future.inputChannel:()Lscala/actors/InputChannel;
Asciz	scala/actors/Futures$$anonfun$awaitEither$1;
class	scala/actors/Futures$$anonfun$awaitEither$1
Asciz	(Lscala/actors/InputChannel;Lscala/actors/InputChannel;)V;
NameAndType	"<init>":(Lscala/actors/InputChannel;Lscala/actors/InputChannel;)V
Method	scala/actors/Futures$$anonfun$awaitEither$1."<init>":(Lscala/actors/InputChannel;Lscala/actors/InputChannel;)V
Asciz	ft1;
Asciz	Lscala/actors/Future;;
Asciz	ft2;
Asciz	FutCh1$1;
Asciz	FutCh2$1;
Asciz	<a:Ljava/lang/Object;b:Ljava/lang/Object;>(Lscala/actors/Future<Ta;>;Lscala/actors/Future<Tb;>;)Ljava/lang/Object;;
Asciz	alarm;
Asciz	(J)Lscala/actors/Future;;
Asciz	scala/actors/Futures$$anonfun$alarm$1;
class	scala/actors/Futures$$anonfun$alarm$1
Asciz	(J)V;
NameAndType	"<init>":(J)V
Method	scala/actors/Futures$$anonfun$alarm$1."<init>":(J)V
Asciz	scala/actors/Futures$$anon$1;
class	scala/actors/Futures$$anon$1
Asciz	(Lscala/Function0;)V;
NameAndType	"<init>":(Lscala/Function0;)V
Method	scala/actors/Futures$$anon$1."<init>":(Lscala/Function0;)V
Asciz	scala/actors/Actor$class;
class	scala/actors/Actor$class
Asciz	(Lscala/actors/Actor;)Lscala/actors/Actor;;
NameAndType	start:(Lscala/actors/Actor;)Lscala/actors/Actor;
Method	scala/actors/Actor$class.start:(Lscala/actors/Actor;)Lscala/actors/Actor;
Asciz	scala/actors/Futures$Eval$;
class	scala/actors/Futures$Eval$
Asciz	Lscala/actors/Futures$Eval$;;
NameAndType	MODULE$:Lscala/actors/Futures$Eval$;
Field	scala/actors/Futures$Eval$.MODULE$:Lscala/actors/Futures$Eval$;
Asciz	scala/actors/Futures$$anonfun$future$1;
class	scala/actors/Futures$$anonfun$future$1
Method	scala/actors/Futures$$anonfun$future$1."<init>":()V
Asciz	scala/actors/ReplyableActor$class;
class	scala/actors/ReplyableActor$class
Asciz	$bang$bang;
Asciz	(Lscala/actors/AbstractActor;Ljava/lang/Object;Lscala/PartialFunction;)Lscala/actors/Future;;
NameAndType	$bang$bang:(Lscala/actors/AbstractActor;Ljava/lang/Object;Lscala/PartialFunction;)Lscala/actors/Future;
Method	scala/actors/ReplyableActor$class.$bang$bang:(Lscala/actors/AbstractActor;Ljava/lang/Object;Lscala/PartialFunction;)Lscala/actors/Future;
Asciz	t$1;
Asciz	a0;
Asciz	Lscala/actors/DaemonActor;;
Asciz	(J)Lscala/actors/Future<Lscala/runtime/Nothing$;>;;
Asciz	future;
Asciz	(Lscala/Function0;)Lscala/actors/Future;;
Asciz	()Lscala/actors/Actor;;
NameAndType	start:()Lscala/actors/Actor;
InterfaceMethod	scala/actors/Actor.start:()Lscala/actors/Actor;
Asciz	scala/actors/ReplyableActor;
class	scala/actors/ReplyableActor
Asciz	(Ljava/lang/Object;Lscala/PartialFunction;)Lscala/actors/Future;;
NameAndType	$bang$bang:(Ljava/lang/Object;Lscala/PartialFunction;)Lscala/actors/Future;
InterfaceMethod	scala/actors/ReplyableActor.$bang$bang:(Ljava/lang/Object;Lscala/PartialFunction;)Lscala/actors/Future;
Asciz	body$1;
Asciz	Lscala/Function0;;
Asciz	a;
Asciz	<T:Ljava/lang/Object;>(Lscala/Function0<TT;>;)Lscala/actors/Future<TT;>;;
Asciz	InnerClasses;
Asciz	scala/collection/immutable/Range;
class	scala/collection/immutable/Range
Asciz	ByOne;
Asciz	scala/actors/Futures;
class	scala/actors/Futures
Asciz	$anon$2;
Asciz	$anon$3;
Asciz	$anon$4;
Asciz	$anon$1;
Asciz	$anonfun$3;
Asciz	$anonfun$2;
Asciz	$anonfun$1;
Asciz	$anonfun$alarm$1;
Asciz	$anonfun$future$1;
Asciz	$anonfun$awaitAll$1;
Asciz	$anonfun$awaitEither$1;
Asciz	scala/ScalaObject;
class	scala/ScalaObject

{
public static final scala.actors.Futures$ MODULE$;
  Signature: Lscala/actors/Futures$;

public static {};
  Signature: ()V
  Code:
   Stack=1, Locals=0, Args_size=0
	new	class scala/actors/Futures$
	invokespecial	Method "<init>":()V
	return
  Labels:

private scala.actors.Futures$();
  Signature: ()V
  Code:
   Stack=1, Locals=1, Args_size=1
	aload_0
	invokespecial	Method java/lang/Object."<init>":()V
	aload_0
	putstatic	Field MODULE$:Lscala/actors/Futures$;
	return
  Labels:

public final void awaitWith$1(scala.collection.Seq, scala.runtime.ObjectRef);
  Signature: (Lscala/collection/Seq;Lscala/runtime/ObjectRef;)V
  Code:
   Stack=4, Locals=4, Args_size=3
	new	class scala/actors/Futures$$anon$3
	dup
	aload_2
	aload_1
	invokespecial	Method scala/actors/Futures$$anon$3."<init>":(Lscala/runtime/ObjectRef;Lscala/collection/Seq;)V
	astore_3
	getstatic	Field scala/actors/Actor$.MODULE$:Lscala/actors/Actor$;
	aload_3
	invokevirtual	Method scala/actors/Actor$.receive:(Lscala/PartialFunction;)Ljava/lang/Object;
	pop
	return
  Labels:
  LocalVariableTable: 
   Start  Length  Slot  Name   Signature
   0      19      0    this       Lscala/actors/Futures$;
   0      19      1    partFuns$1       Lscala/collection/Seq;
   10      8      3    reaction       Lscala/PartialFunction;


public scala.actors.Future fromInputChannel(scala.actors.InputChannel);
  Signature: (Lscala/actors/InputChannel;)Lscala/actors/Future;
  Code:
   Stack=3, Locals=2, Args_size=2
	new	class scala/actors/Futures$$anon$2
	dup
	aload_1
	invokespecial	Method scala/actors/Futures$$anon$2."<init>":(Lscala/actors/InputChannel;)V
	areturn
  Labels:
  LocalVariableTable: 
   Start  Length  Slot  Name   Signature
   0      9      0    this       Lscala/actors/Futures$;
   0      9      1    inputChannel$1       Lscala/actors/InputChannel;

  Signature: length = 0x2
   00 33 

public scala.collection.immutable.List awaitAll(long, scala.collection.Seq);
  Signature: (JLscala/collection/Seq;)Lscala/collection/immutable/List;
  Code:
   Stack=6, Locals=20, Args_size=3
	getstatic	Field scala/actors/Actor$.MODULE$:Lscala/actors/Actor$;
	astore	4
	getstatic	Field scala/actors/Scheduler$.MODULE$:Lscala/actors/Scheduler$;
	astore	5
	aload	4
	aload	5
	invokevirtual	Method scala/actors/Actor$.rawSelf:(Lscala/actors/IScheduler;)Lscala/actors/Reactor;
	checkcast	class scala/actors/Actor
	astore	6
	new	class scala/actors/Futures$$anon$4
	dup
	aload	6
	invokespecial	Method scala/actors/Futures$$anon$4."<init>":(Lscala/actors/Actor;)V
	astore	18
	getstatic	Field scala/actors/Actor$.MODULE$:Lscala/actors/Actor$;
	invokevirtual	Method scala/actors/Actor$.timer:()Ljava/util/Timer;
	aload	18
	lload_1
	invokevirtual	Method java/util/Timer.schedule:(Ljava/util/TimerTask;J)V
	new	class scala/runtime/ObjectRef
	dup
	new	class scala/collection/mutable/HashMap
	dup
	invokespecial	Method scala/collection/mutable/HashMap."<init>":()V
	invokespecial	Method scala/runtime/ObjectRef."<init>":(Ljava/lang/Object;)V
	astore	16
	new	class scala/runtime/IntRef
	dup
	iconst_0
	invokespecial	Method scala/runtime/IntRef."<init>":(I)V
	astore	7
	aload_3
	new	class scala/actors/Futures$$anonfun$1
	dup
	aload	7
	invokespecial	Method scala/actors/Futures$$anonfun$1."<init>":(Lscala/runtime/IntRef;)V
	getstatic	Field scala/collection/Seq$.MODULE$:Lscala/collection/Seq$;
	invokevirtual	Method scala/collection/Seq$.canBuildFrom:()Lscala/collection/generic/CanBuildFrom;
	invokeinterface	InterfaceMethod scala/collection/TraversableLike.map:(Lscala/Function1;Lscala/collection/generic/CanBuildFrom;)Ljava/lang/Object;
	checkcast	class scala/collection/Seq
	astore	8
	aload	8
	new	class scala/actors/Futures$$anonfun$2
	dup
	aload	16
	invokespecial	Method scala/actors/Futures$$anonfun$2."<init>":(Lscala/runtime/ObjectRef;)V
	invokeinterface	InterfaceMethod scala/collection/TraversableLike.filter:(Lscala/Function1;)Ljava/lang/Object;
	checkcast	class scala/collection/Seq
	astore	9
	aload	9
	new	class scala/actors/Futures$$anonfun$3
	dup
	invokespecial	Method scala/actors/Futures$$anonfun$3."<init>":()V
	getstatic	Field scala/collection/Seq$.MODULE$:Lscala/collection/Seq$;
	invokevirtual	Method scala/collection/Seq$.canBuildFrom:()Lscala/collection/generic/CanBuildFrom;
	invokeinterface	InterfaceMethod scala/collection/TraversableLike.map:(Lscala/Function1;Lscala/collection/generic/CanBuildFrom;)Ljava/lang/Object;
	checkcast	class scala/collection/Seq
	astore	10
	aload	10
	invokeinterface	InterfaceMethod scala/collection/SeqLike.length:()I
	iconst_0
	if_icmple	l1 // new
	new	class scala/actors/Futures$$anon$3
	dup
	aload	16
	aload	10
	invokespecial	Method scala/actors/Futures$$anon$3."<init>":(Lscala/runtime/ObjectRef;Lscala/collection/Seq;)V
	astore	13
	getstatic	Field scala/actors/Actor$.MODULE$:Lscala/actors/Actor$;
	astore	11
	getstatic	Field scala/actors/Scheduler$.MODULE$:Lscala/actors/Scheduler$;
	astore	12
	aload	11
	aload	12
	invokevirtual	Method scala/actors/Actor$.rawSelf:(Lscala/actors/IScheduler;)Lscala/actors/Reactor;
	checkcast	class scala/actors/Actor
	aload	13
	invokeinterface	InterfaceMethod scala/actors/Actor.receive:(Lscala/PartialFunction;)Ljava/lang/Object;
	pop
l1	new	class scala/runtime/ObjectRef
	dup
	getstatic	Field scala/collection/immutable/Nil$.MODULE$:Lscala/collection/immutable/Nil$;
	invokespecial	Method scala/runtime/ObjectRef."<init>":(Ljava/lang/Object;)V
	astore	19
	aload	16
	getfield	Field scala/runtime/ObjectRef.elem:Ljava/lang/Object;
	checkcast	class scala/collection/mutable/Map
	invokeinterface	InterfaceMethod scala/collection/TraversableLike.size:()I
	istore	17
	iconst_0
	istore	14
	new	class scala/runtime/RichInt
	dup
	iload	14
	invokespecial	Method scala/runtime/RichInt."<init>":(I)V
	astore	15
	getstatic	Field scala/collection/immutable/Range$.MODULE$:Lscala/collection/immutable/Range$;
	aload	15
	invokevirtual	Method scala/runtime/RichInt.start:()I
	iload	17
	invokevirtual	Method scala/collection/immutable/Range$.apply:(II)Lscala/collection/immutable/Range$ByOne;
	new	class scala/actors/Futures$$anonfun$awaitAll$1
	dup
	aload	16
	aload	19
	iload	17
	invokespecial	Method scala/actors/Futures$$anonfun$awaitAll$1."<init>":(Lscala/runtime/ObjectRef;Lscala/runtime/ObjectRef;I)V
	invokeinterface	InterfaceMethod scala/collection/immutable/Range$ByOne.foreach:(Lscala/Function1;)V
	aload	18
	invokevirtual	Method java/util/TimerTask.cancel:()Z
	pop
	aload	19
	getfield	Field scala/runtime/ObjectRef.elem:Ljava/lang/Object;
	checkcast	class scala/collection/immutable/List
	areturn
  Labels:
   	l1 = 195 // new
  LocalVariableTable: 
   Start  Length  Slot  Name   Signature
   0      282      0    this       Lscala/actors/Futures$;
   0      282      1    timeout       J
   0      282      3    fts       Lscala/collection/Seq;
   22      259      6    thisActor$1       Lscala/actors/Actor;
   71      210      7    cnt$1       Lscala/runtime/IntRef;
   97      184      8    mappedFts       Lscala/collection/Seq;
   118      163      9    unsetFts       Lscala/collection/Seq;
   143      138      10    partFuns       Lscala/collection/Seq;
   167      28      13    reaction0       Lscala/PartialFunction;
   61      220      16    resultsMap$1       Lscala/runtime/ObjectRef;
   222      59      17    size$1       I
   33      248      18    timerTask       Ljava/util/TimerTask;
   207      74      19    results$1       Lscala/runtime/ObjectRef;

  Signature: length = 0x2
   00 FFFFFFC9 

public java.lang.Object awaitEither(scala.actors.Future, scala.actors.Future);
  Signature: (Lscala/actors/Future;Lscala/actors/Future;)Ljava/lang/Object;
  Code:
   Stack=5, Locals=5, Args_size=3
	aload_1
	invokevirtual	Method scala/actors/Future.inputChannel:()Lscala/actors/InputChannel;
	astore_3
	aload_2
	invokevirtual	Method scala/actors/Future.inputChannel:()Lscala/actors/InputChannel;
	astore	4
	getstatic	Field scala/actors/Actor$.MODULE$:Lscala/actors/Actor$;
	new	class scala/actors/Futures$$anonfun$awaitEither$1
	dup
	aload_3
	aload	4
	invokespecial	Method scala/actors/Futures$$anonfun$awaitEither$1."<init>":(Lscala/actors/InputChannel;Lscala/actors/InputChannel;)V
	invokevirtual	Method scala/actors/Actor$.receive:(Lscala/PartialFunction;)Ljava/lang/Object;
	areturn
  Labels:
  LocalVariableTable: 
   Start  Length  Slot  Name   Signature
   0      28      0    this       Lscala/actors/Futures$;
   0      28      1    ft1       Lscala/actors/Future;
   0      28      2    ft2       Lscala/actors/Future;
   5      22      3    FutCh1$1       Lscala/actors/InputChannel;
   11      16      4    FutCh2$1       Lscala/actors/InputChannel;

  Signature: length = 0x2
   00 FFFFFFDC 

public scala.actors.Future alarm(long);
  Signature: (J)Lscala/actors/Future;
  Code:
   Stack=4, Locals=7, Args_size=2
	new	class scala/actors/Futures$$anonfun$alarm$1
	dup
	lload_1
	invokespecial	Method scala/actors/Futures$$anonfun$alarm$1."<init>":(J)V
	astore_3
	new	class scala/actors/Futures$$anon$1
	dup
	aload_3
	invokespecial	Method scala/actors/Futures$$anon$1."<init>":(Lscala/Function0;)V
	astore	4
	aload	4
	invokestatic	Method scala/actors/Actor$class.start:(Lscala/actors/Actor;)Lscala/actors/Actor;
	pop
	getstatic	Field scala/actors/Futures$Eval$.MODULE$:Lscala/actors/Futures$Eval$;
	new	class scala/actors/Futures$$anonfun$future$1
	dup
	invokespecial	Method scala/actors/Futures$$anonfun$future$1."<init>":()V
	astore	6
	astore	5
	aload	4
	aload	5
	aload	6
	invokestatic	Method scala/actors/ReplyableActor$class.$bang$bang:(Lscala/actors/AbstractActor;Ljava/lang/Object;Lscala/PartialFunction;)Lscala/actors/Future;
	areturn
  Labels:
  LocalVariableTable: 
   Start  Length  Slot  Name   Signature
   0      49      0    this       Lscala/actors/Futures$;
   0      49      1    t$1       J
   19      29      4    a0       Lscala/actors/DaemonActor;

  Signature: length = 0x2
   00 FFFFFFFF 

public scala.actors.Future future(scala.Function0);
  Signature: (Lscala/Function0;)Lscala/actors/Future;
  Code:
   Stack=4, Locals=3, Args_size=2
	new	class scala/actors/Futures$$anon$1
	dup
	aload_1
	invokespecial	Method scala/actors/Futures$$anon$1."<init>":(Lscala/Function0;)V
	astore_2
	aload_2
	invokeinterface	InterfaceMethod scala/actors/Actor.start:()Lscala/actors/Actor;
	pop
	aload_2
	getstatic	Field scala/actors/Futures$Eval$.MODULE$:Lscala/actors/Futures$Eval$;
	new	class scala/actors/Futures$$anonfun$future$1
	dup
	invokespecial	Method scala/actors/Futures$$anonfun$future$1."<init>":()V
	invokeinterface	InterfaceMethod scala/actors/ReplyableActor.$bang$bang:(Ljava/lang/Object;Lscala/PartialFunction;)Lscala/actors/Future;
	areturn
  Labels:
  LocalVariableTable: 
   Start  Length  Slot  Name   Signature
   0      33      0    this       Lscala/actors/Futures$;
   0      33      1    body$1       Lscala/Function0;
   9      23      2    a       Lscala/actors/DaemonActor;

  Signature: length = 0x2
   01 0D 

}

