Compiled from "Future.scala"
public class scala.actors.Futures$FutureActor extends scala.actors.Future implements scala.actors.DaemonActor,scala.ScalaObject
  SourceFile: "Future.scala"
  Signature: length = 0x2
   01 FFFFFFF0 
  Scala: length = 0x
   
  InnerClass: 
   public abstract Body=class scala/actors/Actor$Body of class scala/actors/Actor
   public final $anon$6=class scala/actors/Actor$$anon$6 of class scala/actors/Actor
   public abstract Value=class scala/Enumeration$Value of class scala/Enumeration
   public FutureActor=class scala/actors/Futures$FutureActor of class scala/actors/Futures
   public final $anonfun$act$2=class scala/actors/Futures$FutureActor$$anonfun$act$2 of class scala/actors/Futures$FutureActor
   public final $anonfun$act$1=class scala/actors/Futures$FutureActor$$anonfun$act$1 of class scala/actors/Futures$FutureActor
   public final $anonfun$respond$1=class scala/actors/Futures$FutureActor$$anonfun$respond$1 of class scala/actors/Futures$FutureActor
  minor version: 0
  major version: 49
  Constant pool:
Asciz	SourceFile;
Asciz	Future.scala;
Asciz	scala$actors$Actor$$blocker$module;
Asciz	Lscala/actors/Actor$blocker$;;
Asciz	kill;
Asciz	Lscala/Function0;;
Asciz	_state;
Asciz	Lscala/Enumeration$Value;;
Asciz	waitingFor;
Asciz	Lscala/PartialFunction;;
Asciz	sendBuffer;
Asciz	Lscala/actors/MQueue;;
Asciz	mailbox;
Asciz	onTimeout;
Asciz	Lscala/Option;;
Asciz	senders;
Asciz	Lscala/collection/immutable/List;;
Asciz	shouldExit;
Asciz	Z;
Asciz	scala$actors$Actor$$exitReason;
Asciz	Ljava/lang/Object;;
Asciz	trapExit;
Asciz	links;
Asciz	scala$actors$Actor$$received;
Asciz	scala$actors$Actor$$isSuspended;
Asciz	scala$actors$Futures$FutureActor$$fun;
Asciz	Lscala/Function1;;
Asciz	scheduler;
Asciz	()Lscala/actors/IScheduler;;
Asciz	Code;
Asciz	LineNumberTable;
Asciz	scala/actors/DaemonActor$class;
class	scala/actors/DaemonActor$class
Asciz	(Lscala/actors/DaemonActor;)Lscala/actors/IScheduler;;
NameAndType	scheduler:(Lscala/actors/DaemonActor;)Lscala/actors/IScheduler;
Method	scala/actors/DaemonActor$class.scheduler:(Lscala/actors/DaemonActor;)Lscala/actors/IScheduler;
Asciz	()Z;
Asciz	scala/actors/Futures$FutureActor;
class	scala/actors/Futures$FutureActor
NameAndType	scala$actors$Actor$$isSuspended:Z
Field	scala/actors/Futures$FutureActor.scala$actors$Actor$$isSuspended:Z
Asciz	scala$actors$Actor$$isSuspended_$eq;
Asciz	(Z)V;
Asciz	()Lscala/Option;;
NameAndType	scala$actors$Actor$$received:Lscala/Option;
Field	scala/actors/Futures$FutureActor.scala$actors$Actor$$received:Lscala/Option;
Asciz	scala$actors$Actor$$received_$eq;
Asciz	(Lscala/Option;)V;
Asciz	scala$actors$Actor$$blocker;
Asciz	()Lscala/actors/Actor$blocker$;;
NameAndType	scala$actors$Actor$$blocker$module:Lscala/actors/Actor$blocker$;
Field	scala/actors/Futures$FutureActor.scala$actors$Actor$$blocker$module:Lscala/actors/Actor$blocker$;
Asciz	scala/actors/Actor$blocker$;
class	scala/actors/Actor$blocker$
Asciz	<init>;
Asciz	(Lscala/actors/Actor;)V;
NameAndType	"<init>":(Lscala/actors/Actor;)V
Method	scala/actors/Actor$blocker$."<init>":(Lscala/actors/Actor;)V
Asciz	()Lscala/collection/immutable/List;;
NameAndType	links:Lscala/collection/immutable/List;
Field	scala/actors/Futures$FutureActor.links:Lscala/collection/immutable/List;
Asciz	links_$eq;
Asciz	(Lscala/collection/immutable/List;)V;
NameAndType	trapExit:Z
Field	scala/actors/Futures$FutureActor.trapExit:Z
Asciz	trapExit_$eq;
Asciz	()Ljava/lang/Object;;
NameAndType	scala$actors$Actor$$exitReason:Ljava/lang/Object;
Field	scala/actors/Futures$FutureActor.scala$actors$Actor$$exitReason:Ljava/lang/Object;
Asciz	scala$actors$Actor$$exitReason_$eq;
Asciz	(Ljava/lang/Object;)V;
NameAndType	shouldExit:Z
Field	scala/actors/Futures$FutureActor.shouldExit:Z
Asciz	shouldExit_$eq;
Asciz	scala$actors$Actor$$super$startSearch;
Asciz	(Ljava/lang/Object;Lscala/actors/OutputChannel;Lscala/PartialFunction;)Lscala/Function0;;
Asciz	scala/actors/Reactor$class;
class	scala/actors/Reactor$class
Asciz	startSearch;
Asciz	(Lscala/actors/Reactor;Ljava/lang/Object;Lscala/actors/OutputChannel;Lscala/PartialFunction;)Lscala/Function0;;
NameAndType	startSearch:(Lscala/actors/Reactor;Ljava/lang/Object;Lscala/actors/OutputChannel;Lscala/PartialFunction;)Lscala/Function0;
Method	scala/actors/Reactor$class.startSearch:(Lscala/actors/Reactor;Ljava/lang/Object;Lscala/actors/OutputChannel;Lscala/PartialFunction;)Lscala/Function0;
Asciz	this;
Asciz	Lscala/actors/Futures$FutureActor;;
Asciz	msg;
Asciz	replyTo;
Asciz	Lscala/actors/OutputChannel;;
Asciz	handler;
Asciz	LocalVariableTable;
Asciz	scala$actors$Actor$$super$react;
Asciz	(Lscala/PartialFunction;)Lscala/runtime/Nothing$;;
Asciz	scala/actors/ReplyReactor$class;
class	scala/actors/ReplyReactor$class
Asciz	react;
Asciz	(Lscala/actors/ReplyReactor;Lscala/PartialFunction;)Lscala/runtime/Nothing$;;
NameAndType	react:(Lscala/actors/ReplyReactor;Lscala/PartialFunction;)Lscala/runtime/Nothing$;
Method	scala/actors/ReplyReactor$class.react:(Lscala/actors/ReplyReactor;Lscala/PartialFunction;)Lscala/runtime/Nothing$;
Asciz	scala$actors$Actor$$super$reactWithin;
Asciz	(JLscala/PartialFunction;)Lscala/runtime/Nothing$;;
Asciz	reactWithin;
Asciz	(Lscala/actors/ReplyReactor;JLscala/PartialFunction;)Lscala/runtime/Nothing$;;
NameAndType	reactWithin:(Lscala/actors/ReplyReactor;JLscala/PartialFunction;)Lscala/runtime/Nothing$;
Method	scala/actors/ReplyReactor$class.reactWithin:(Lscala/actors/ReplyReactor;JLscala/PartialFunction;)Lscala/runtime/Nothing$;
Asciz	msec;
Asciz	J;
Asciz	scala$actors$Actor$$super$getState;
Asciz	()Lscala/Enumeration$Value;;
Asciz	getState;
Asciz	(Lscala/actors/ReplyReactor;)Lscala/Enumeration$Value;;
NameAndType	getState:(Lscala/actors/ReplyReactor;)Lscala/Enumeration$Value;
Method	scala/actors/ReplyReactor$class.getState:(Lscala/actors/ReplyReactor;)Lscala/Enumeration$Value;
Asciz	scala$actors$Actor$$super$exit;
Asciz	()Lscala/runtime/Nothing$;;
Asciz	exit;
Asciz	(Lscala/actors/Reactor;)Lscala/runtime/Nothing$;;
NameAndType	exit:(Lscala/actors/Reactor;)Lscala/runtime/Nothing$;
Method	scala/actors/Reactor$class.exit:(Lscala/actors/Reactor;)Lscala/runtime/Nothing$;
Asciz	scala/actors/Actor$class;
class	scala/actors/Actor$class
Asciz	(Lscala/actors/Actor;Ljava/lang/Object;Lscala/actors/OutputChannel;Lscala/PartialFunction;)Lscala/Function0;;
NameAndType	startSearch:(Lscala/actors/Actor;Ljava/lang/Object;Lscala/actors/OutputChannel;Lscala/PartialFunction;)Lscala/Function0;
Method	scala/actors/Actor$class.startSearch:(Lscala/actors/Actor;Ljava/lang/Object;Lscala/actors/OutputChannel;Lscala/PartialFunction;)Lscala/Function0;
Asciz	makeReaction;
Asciz	(Lscala/Function0;)Ljava/lang/Runnable;;
Asciz	(Lscala/actors/Actor;Lscala/Function0;)Ljava/lang/Runnable;;
NameAndType	makeReaction:(Lscala/actors/Actor;Lscala/Function0;)Ljava/lang/Runnable;
Method	scala/actors/Actor$class.makeReaction:(Lscala/actors/Actor;Lscala/Function0;)Ljava/lang/Runnable;
Asciz	fun;
Asciz	receive;
Asciz	(Lscala/PartialFunction;)Ljava/lang/Object;;
Asciz	(Lscala/actors/Actor;Lscala/PartialFunction;)Ljava/lang/Object;;
NameAndType	receive:(Lscala/actors/Actor;Lscala/PartialFunction;)Ljava/lang/Object;
Method	scala/actors/Actor$class.receive:(Lscala/actors/Actor;Lscala/PartialFunction;)Ljava/lang/Object;
Asciz	f;
Asciz	receiveWithin;
Asciz	(JLscala/PartialFunction;)Ljava/lang/Object;;
Asciz	(Lscala/actors/Actor;JLscala/PartialFunction;)Ljava/lang/Object;;
NameAndType	receiveWithin:(Lscala/actors/Actor;JLscala/PartialFunction;)Ljava/lang/Object;
Method	scala/actors/Actor$class.receiveWithin:(Lscala/actors/Actor;JLscala/PartialFunction;)Ljava/lang/Object;
Asciz	(Lscala/actors/Actor;Lscala/PartialFunction;)Lscala/runtime/Nothing$;;
NameAndType	react:(Lscala/actors/Actor;Lscala/PartialFunction;)Lscala/runtime/Nothing$;
Method	scala/actors/Actor$class.react:(Lscala/actors/Actor;Lscala/PartialFunction;)Lscala/runtime/Nothing$;
Asciz	(Lscala/actors/Actor;JLscala/PartialFunction;)Lscala/runtime/Nothing$;;
NameAndType	reactWithin:(Lscala/actors/Actor;JLscala/PartialFunction;)Lscala/runtime/Nothing$;
Method	scala/actors/Actor$class.reactWithin:(Lscala/actors/Actor;JLscala/PartialFunction;)Lscala/runtime/Nothing$;
Asciz	$qmark;
Asciz	(Lscala/actors/Actor;)Ljava/lang/Object;;
NameAndType	$qmark:(Lscala/actors/Actor;)Ljava/lang/Object;
Method	scala/actors/Actor$class.$qmark:(Lscala/actors/Actor;)Ljava/lang/Object;
Asciz	scheduleActor;
Asciz	(Lscala/PartialFunction;Ljava/lang/Object;)V;
Asciz	(Lscala/actors/Actor;Lscala/PartialFunction;Ljava/lang/Object;)V;
NameAndType	scheduleActor:(Lscala/actors/Actor;Lscala/PartialFunction;Ljava/lang/Object;)V
Method	scala/actors/Actor$class.scheduleActor:(Lscala/actors/Actor;Lscala/PartialFunction;Ljava/lang/Object;)V
Asciz	exiting;
Asciz	(Lscala/actors/Actor;)Z;
NameAndType	exiting:(Lscala/actors/Actor;)Z
Method	scala/actors/Actor$class.exiting:(Lscala/actors/Actor;)Z
Asciz	start;
Asciz	()Lscala/actors/Actor;;
Asciz	(Lscala/actors/Actor;)Lscala/actors/Actor;;
NameAndType	start:(Lscala/actors/Actor;)Lscala/actors/Actor;
Method	scala/actors/Actor$class.start:(Lscala/actors/Actor;)Lscala/actors/Actor;
Asciz	(Lscala/actors/Actor;)Lscala/Enumeration$Value;;
NameAndType	getState:(Lscala/actors/Actor;)Lscala/Enumeration$Value;
Method	scala/actors/Actor$class.getState:(Lscala/actors/Actor;)Lscala/Enumeration$Value;
Asciz	link;
Asciz	(Lscala/actors/AbstractActor;)Lscala/actors/AbstractActor;;
Asciz	(Lscala/actors/Actor;Lscala/actors/AbstractActor;)Lscala/actors/AbstractActor;;
NameAndType	link:(Lscala/actors/Actor;Lscala/actors/AbstractActor;)Lscala/actors/AbstractActor;
Method	scala/actors/Actor$class.link:(Lscala/actors/Actor;Lscala/actors/AbstractActor;)Lscala/actors/AbstractActor;
Asciz	to;
Asciz	Lscala/actors/AbstractActor;;
Asciz	(Lscala/Function0;)Lscala/actors/Actor;;
Asciz	(Lscala/actors/Actor;Lscala/Function0;)Lscala/actors/Actor;;
NameAndType	link:(Lscala/actors/Actor;Lscala/Function0;)Lscala/actors/Actor;
Method	scala/actors/Actor$class.link:(Lscala/actors/Actor;Lscala/Function0;)Lscala/actors/Actor;
Asciz	body;
Asciz	linkTo;
Asciz	(Lscala/actors/AbstractActor;)V;
Asciz	(Lscala/actors/Actor;Lscala/actors/AbstractActor;)V;
NameAndType	linkTo:(Lscala/actors/Actor;Lscala/actors/AbstractActor;)V
Method	scala/actors/Actor$class.linkTo:(Lscala/actors/Actor;Lscala/actors/AbstractActor;)V
Asciz	unlink;
NameAndType	unlink:(Lscala/actors/Actor;Lscala/actors/AbstractActor;)V
Method	scala/actors/Actor$class.unlink:(Lscala/actors/Actor;Lscala/actors/AbstractActor;)V
Asciz	from;
Asciz	unlinkFrom;
NameAndType	unlinkFrom:(Lscala/actors/Actor;Lscala/actors/AbstractActor;)V
Method	scala/actors/Actor$class.unlinkFrom:(Lscala/actors/Actor;Lscala/actors/AbstractActor;)V
Asciz	(Ljava/lang/Object;)Lscala/runtime/Nothing$;;
Asciz	(Lscala/actors/Actor;Ljava/lang/Object;)Lscala/runtime/Nothing$;;
NameAndType	exit:(Lscala/actors/Actor;Ljava/lang/Object;)Lscala/runtime/Nothing$;
Method	scala/actors/Actor$class.exit:(Lscala/actors/Actor;Ljava/lang/Object;)Lscala/runtime/Nothing$;
Asciz	reason;
Asciz	(Lscala/actors/Actor;)Lscala/runtime/Nothing$;;
NameAndType	exit:(Lscala/actors/Actor;)Lscala/runtime/Nothing$;
Method	scala/actors/Actor$class.exit:(Lscala/actors/Actor;)Lscala/runtime/Nothing$;
Asciz	exitLinked;
Asciz	()V;
NameAndType	exitLinked:(Lscala/actors/Actor;)V
Method	scala/actors/Actor$class.exitLinked:(Lscala/actors/Actor;)V
Asciz	(Lscala/actors/Actor;Ljava/lang/Object;)V;
NameAndType	exitLinked:(Lscala/actors/Actor;Ljava/lang/Object;)V
Method	scala/actors/Actor$class.exitLinked:(Lscala/actors/Actor;Ljava/lang/Object;)V
Asciz	(Lscala/actors/AbstractActor;Ljava/lang/Object;)V;
Asciz	(Lscala/actors/Actor;Lscala/actors/AbstractActor;Ljava/lang/Object;)V;
NameAndType	exit:(Lscala/actors/Actor;Lscala/actors/AbstractActor;Ljava/lang/Object;)V
Method	scala/actors/Actor$class.exit:(Lscala/actors/Actor;Lscala/actors/AbstractActor;Ljava/lang/Object;)V
Asciz	onTerminate;
Asciz	(Lscala/Function0;)V;
Asciz	(Lscala/actors/Actor;Lscala/Function0;)V;
NameAndType	onTerminate:(Lscala/actors/Actor;Lscala/Function0;)V
Method	scala/actors/Actor$class.onTerminate:(Lscala/actors/Actor;Lscala/Function0;)V
Asciz	$bang$qmark;
Asciz	(Ljava/lang/Object;)Ljava/lang/Object;;
Asciz	scala/actors/ReplyableActor$class;
class	scala/actors/ReplyableActor$class
Asciz	(Lscala/actors/AbstractActor;Ljava/lang/Object;)Ljava/lang/Object;;
NameAndType	$bang$qmark:(Lscala/actors/AbstractActor;Ljava/lang/Object;)Ljava/lang/Object;
Method	scala/actors/ReplyableActor$class.$bang$qmark:(Lscala/actors/AbstractActor;Ljava/lang/Object;)Ljava/lang/Object;
Asciz	(JLjava/lang/Object;)Lscala/Option;;
Asciz	(Lscala/actors/AbstractActor;JLjava/lang/Object;)Lscala/Option;;
NameAndType	$bang$qmark:(Lscala/actors/AbstractActor;JLjava/lang/Object;)Lscala/Option;
Method	scala/actors/ReplyableActor$class.$bang$qmark:(Lscala/actors/AbstractActor;JLjava/lang/Object;)Lscala/Option;
Asciz	$bang$bang;
Asciz	(Ljava/lang/Object;Lscala/PartialFunction;)Lscala/actors/Future;;
Asciz	(Lscala/actors/AbstractActor;Ljava/lang/Object;Lscala/PartialFunction;)Lscala/actors/Future;;
NameAndType	$bang$bang:(Lscala/actors/AbstractActor;Ljava/lang/Object;Lscala/PartialFunction;)Lscala/actors/Future;
Method	scala/actors/ReplyableActor$class.$bang$bang:(Lscala/actors/AbstractActor;Ljava/lang/Object;Lscala/PartialFunction;)Lscala/actors/Future;
Asciz	(Ljava/lang/Object;)Lscala/actors/Future;;
Asciz	(Lscala/actors/AbstractActor;Ljava/lang/Object;)Lscala/actors/Future;;
NameAndType	$bang$bang:(Lscala/actors/AbstractActor;Ljava/lang/Object;)Lscala/actors/Future;
Method	scala/actors/ReplyableActor$class.$bang$bang:(Lscala/actors/AbstractActor;Ljava/lang/Object;)Lscala/actors/Future;
NameAndType	senders:Lscala/collection/immutable/List;
Field	scala/actors/Futures$FutureActor.senders:Lscala/collection/immutable/List;
Asciz	senders_$eq;
NameAndType	onTimeout:Lscala/Option;
Field	scala/actors/Futures$FutureActor.onTimeout:Lscala/Option;
Asciz	onTimeout_$eq;
Asciz	scala$actors$ReplyReactor$$super$resumeReceiver;
Asciz	(Lscala/Tuple2;Lscala/PartialFunction;Z)V;
Asciz	resumeReceiver;
Asciz	(Lscala/actors/Reactor;Lscala/Tuple2;Lscala/PartialFunction;Z)V;
NameAndType	resumeReceiver:(Lscala/actors/Reactor;Lscala/Tuple2;Lscala/PartialFunction;Z)V
Method	scala/actors/Reactor$class.resumeReceiver:(Lscala/actors/Reactor;Lscala/Tuple2;Lscala/PartialFunction;Z)V
Asciz	item;
Asciz	Lscala/Tuple2;;
Asciz	onSameThread;
Asciz	scala$actors$ReplyReactor$$super$react;
Asciz	(Lscala/actors/Reactor;Lscala/PartialFunction;)Lscala/runtime/Nothing$;;
NameAndType	react:(Lscala/actors/Reactor;Lscala/PartialFunction;)Lscala/runtime/Nothing$;
Method	scala/actors/Reactor$class.react:(Lscala/actors/Reactor;Lscala/PartialFunction;)Lscala/runtime/Nothing$;
Asciz	sender;
Asciz	()Lscala/actors/OutputChannel;;
Asciz	(Lscala/actors/ReplyReactor;)Lscala/actors/OutputChannel;;
NameAndType	sender:(Lscala/actors/ReplyReactor;)Lscala/actors/OutputChannel;
Method	scala/actors/ReplyReactor$class.sender:(Lscala/actors/ReplyReactor;)Lscala/actors/OutputChannel;
Asciz	reply;
Asciz	(Lscala/actors/ReplyReactor;Ljava/lang/Object;)V;
NameAndType	reply:(Lscala/actors/ReplyReactor;Ljava/lang/Object;)V
Method	scala/actors/ReplyReactor$class.reply:(Lscala/actors/ReplyReactor;Ljava/lang/Object;)V
Asciz	$bang;
NameAndType	$bang:(Lscala/actors/ReplyReactor;Ljava/lang/Object;)V
Method	scala/actors/ReplyReactor$class.$bang:(Lscala/actors/ReplyReactor;Ljava/lang/Object;)V
Asciz	forward;
NameAndType	forward:(Lscala/actors/ReplyReactor;Ljava/lang/Object;)V
Method	scala/actors/ReplyReactor$class.forward:(Lscala/actors/ReplyReactor;Ljava/lang/Object;)V
Asciz	(Lscala/actors/ReplyReactor;Lscala/Tuple2;Lscala/PartialFunction;Z)V;
NameAndType	resumeReceiver:(Lscala/actors/ReplyReactor;Lscala/Tuple2;Lscala/PartialFunction;Z)V
Method	scala/actors/ReplyReactor$class.resumeReceiver:(Lscala/actors/ReplyReactor;Lscala/Tuple2;Lscala/PartialFunction;Z)V
Asciz	searchMailbox;
Asciz	(Lscala/actors/MQueue;Lscala/PartialFunction;Z)V;
Asciz	(Lscala/actors/ReplyReactor;Lscala/actors/MQueue;Lscala/PartialFunction;Z)V;
NameAndType	searchMailbox:(Lscala/actors/ReplyReactor;Lscala/actors/MQueue;Lscala/PartialFunction;Z)V
Method	scala/actors/ReplyReactor$class.searchMailbox:(Lscala/actors/ReplyReactor;Lscala/actors/MQueue;Lscala/PartialFunction;Z)V
Asciz	startMbox;
Asciz	resumeOnSameThread;
Asciz	()Lscala/actors/MQueue;;
NameAndType	mailbox:Lscala/actors/MQueue;
Field	scala/actors/Futures$FutureActor.mailbox:Lscala/actors/MQueue;
NameAndType	sendBuffer:Lscala/actors/MQueue;
Field	scala/actors/Futures$FutureActor.sendBuffer:Lscala/actors/MQueue;
Asciz	()Lscala/PartialFunction;;
NameAndType	waitingFor:Lscala/PartialFunction;
Field	scala/actors/Futures$FutureActor.waitingFor:Lscala/PartialFunction;
Asciz	waitingFor_$eq;
Asciz	(Lscala/PartialFunction;)V;
NameAndType	_state:Lscala/Enumeration$Value;
Field	scala/actors/Futures$FutureActor._state:Lscala/Enumeration$Value;
Asciz	_state_$eq;
Asciz	(Lscala/Enumeration$Value;)V;
Asciz	()Lscala/Function0;;
NameAndType	kill:Lscala/Function0;
Field	scala/actors/Futures$FutureActor.kill:Lscala/Function0;
Asciz	kill_$eq;
Asciz	scala$actors$Reactor$_setter_$mailbox_$eq;
Asciz	(Lscala/actors/MQueue;)V;
Asciz	scala$actors$Reactor$_setter_$sendBuffer_$eq;
Asciz	exceptionHandler;
Asciz	(Lscala/actors/Reactor;)Lscala/PartialFunction;;
NameAndType	exceptionHandler:(Lscala/actors/Reactor;)Lscala/PartialFunction;
Method	scala/actors/Reactor$class.exceptionHandler:(Lscala/actors/Reactor;)Lscala/PartialFunction;
Asciz	mailboxSize;
Asciz	()I;
Asciz	(Lscala/actors/Reactor;)I;
NameAndType	mailboxSize:(Lscala/actors/Reactor;)I
Method	scala/actors/Reactor$class.mailboxSize:(Lscala/actors/Reactor;)I
Asciz	send;
Asciz	(Ljava/lang/Object;Lscala/actors/OutputChannel;)V;
Asciz	(Lscala/actors/Reactor;Ljava/lang/Object;Lscala/actors/OutputChannel;)V;
NameAndType	send:(Lscala/actors/Reactor;Ljava/lang/Object;Lscala/actors/OutputChannel;)V
Method	scala/actors/Reactor$class.send:(Lscala/actors/Reactor;Ljava/lang/Object;Lscala/actors/OutputChannel;)V
Asciz	receiver;
Asciz	(Lscala/actors/Reactor;)Lscala/actors/Actor;;
NameAndType	receiver:(Lscala/actors/Reactor;)Lscala/actors/Actor;
Method	scala/actors/Reactor$class.receiver:(Lscala/actors/Reactor;)Lscala/actors/Actor;
Asciz	drainSendBuffer;
Asciz	(Lscala/actors/Reactor;Lscala/actors/MQueue;)V;
NameAndType	drainSendBuffer:(Lscala/actors/Reactor;Lscala/actors/MQueue;)V
Method	scala/actors/Reactor$class.drainSendBuffer:(Lscala/actors/Reactor;Lscala/actors/MQueue;)V
Asciz	mbox;
Asciz	mkBody;
Asciz	(Lscala/Function0;)Lscala/actors/Actor$Body;;
Asciz	(Lscala/actors/Reactor;Lscala/Function0;)Lscala/actors/Actor$Body;;
NameAndType	mkBody:(Lscala/actors/Reactor;Lscala/Function0;)Lscala/actors/Actor$Body;
Method	scala/actors/Reactor$class.mkBody:(Lscala/actors/Reactor;Lscala/Function0;)Lscala/actors/Actor$Body;
Asciz	seq;
Asciz	(Lscala/Function0;Lscala/Function0;)V;
Asciz	(Lscala/actors/Reactor;Lscala/Function0;Lscala/Function0;)V;
NameAndType	seq:(Lscala/actors/Reactor;Lscala/Function0;Lscala/Function0;)V
Method	scala/actors/Reactor$class.seq:(Lscala/actors/Reactor;Lscala/Function0;Lscala/Function0;)V
Asciz	first;
Asciz	next;
Asciz	terminated;
Asciz	(Lscala/actors/Reactor;)V;
NameAndType	terminated:(Lscala/actors/Reactor;)V
Method	scala/actors/Reactor$class.terminated:(Lscala/actors/Reactor;)V
Asciz	loop;
Asciz	scala/actors/Combinators$class;
class	scala/actors/Combinators$class
Asciz	(Lscala/actors/Combinators;Lscala/Function0;)V;
NameAndType	loop:(Lscala/actors/Combinators;Lscala/Function0;)V
Method	scala/actors/Combinators$class.loop:(Lscala/actors/Combinators;Lscala/Function0;)V
Asciz	loopWhile;
Asciz	(Lscala/actors/Combinators;Lscala/Function0;Lscala/Function0;)V;
NameAndType	loopWhile:(Lscala/actors/Combinators;Lscala/Function0;Lscala/Function0;)V
Method	scala/actors/Combinators$class.loopWhile:(Lscala/actors/Combinators;Lscala/Function0;Lscala/Function0;)V
Asciz	cond;
Asciz	continue;
Asciz	(Lscala/actors/Combinators;)V;
NameAndType	continue:(Lscala/actors/Combinators;)V
Method	scala/actors/Combinators$class.continue:(Lscala/actors/Combinators;)V
Asciz	scala$actors$Futures$FutureActor$$super$inputChannel;
Asciz	()Lscala/actors/InputChannel;;
Asciz	scala/actors/Future;
class	scala/actors/Future
Asciz	inputChannel;
NameAndType	inputChannel:()Lscala/actors/InputChannel;
Method	scala/actors/Future.inputChannel:()Lscala/actors/InputChannel;
Asciz	isSet;
Asciz	fvalue;
NameAndType	fvalue:()Lscala/Option;
Method	scala/actors/Futures$FutureActor.fvalue:()Lscala/Option;
Asciz	scala/Option;
class	scala/Option
Asciz	isEmpty;
NameAndType	isEmpty:()Z
Method	scala/Option.isEmpty:()Z
Asciz	apply;
Asciz	scala/actors/Futures$Eval$;
class	scala/actors/Futures$Eval$
Asciz	MODULE$;
Asciz	Lscala/actors/Futures$Eval$;;
NameAndType	MODULE$:Lscala/actors/Futures$Eval$;
Field	scala/actors/Futures$Eval$.MODULE$:Lscala/actors/Futures$Eval$;
Asciz	scala/actors/ReplyableActor;
class	scala/actors/ReplyableActor
NameAndType	$bang$qmark:(Ljava/lang/Object;)Ljava/lang/Object;
InterfaceMethod	scala/actors/ReplyableActor.$bang$qmark:(Ljava/lang/Object;)Ljava/lang/Object;
Asciz	scala/runtime/BoxedUnit;
class	scala/runtime/BoxedUnit
Asciz	UNIT;
Asciz	Lscala/runtime/BoxedUnit;;
NameAndType	UNIT:Lscala/runtime/BoxedUnit;
Field	scala/runtime/BoxedUnit.UNIT:Lscala/runtime/BoxedUnit;
Asciz	fvalueTyped;
NameAndType	fvalueTyped:()Ljava/lang/Object;
Method	scala/actors/Futures$FutureActor.fvalueTyped:()Ljava/lang/Object;
Asciz	()TT;;
Asciz	Signature;
Asciz	respond;
Asciz	(Lscala/Function1;)V;
NameAndType	isSet:()Z
Method	scala/actors/Futures$FutureActor.isSet:()Z
Asciz	scala/Function1;
class	scala/Function1
NameAndType	apply:(Ljava/lang/Object;)Ljava/lang/Object;
InterfaceMethod	scala/Function1.apply:(Ljava/lang/Object;)Ljava/lang/Object;
NameAndType	$bang$bang:(Ljava/lang/Object;)Lscala/actors/Future;
InterfaceMethod	scala/actors/ReplyableActor.$bang$bang:(Ljava/lang/Object;)Lscala/actors/Future;
Asciz	scala/actors/Futures$FutureActor$$anonfun$respond$1;
class	scala/actors/Futures$FutureActor$$anonfun$respond$1
Asciz	(Lscala/actors/Futures$FutureActor;Lscala/Function1;)V;
NameAndType	"<init>":(Lscala/actors/Futures$FutureActor;Lscala/Function1;)V
Method	scala/actors/Futures$FutureActor$$anonfun$respond$1."<init>":(Lscala/actors/Futures$FutureActor;Lscala/Function1;)V
Asciz	scala/actors/InputChannel;
class	scala/actors/InputChannel
NameAndType	react:(Lscala/PartialFunction;)Lscala/runtime/Nothing$;
InterfaceMethod	scala/actors/InputChannel.react:(Lscala/PartialFunction;)Lscala/runtime/Nothing$;
Asciz	k$1;
Asciz	ft;
Asciz	Lscala/actors/Future;;
Asciz	(Lscala/Function1<TT;Ljava/lang/Object;>;)V;
Asciz	act;
Asciz	scala/concurrent/SyncVar;
class	scala/concurrent/SyncVar
NameAndType	"<init>":()V
Method	scala/concurrent/SyncVar."<init>":()V
Asciz	scala/actors/Futures$FutureActor$$anonfun$act$1;
class	scala/actors/Futures$FutureActor$$anonfun$act$1
Asciz	(Lscala/actors/Futures$FutureActor;Lscala/concurrent/SyncVar;)V;
NameAndType	"<init>":(Lscala/actors/Futures$FutureActor;Lscala/concurrent/SyncVar;)V
Method	scala/actors/Futures$FutureActor$$anonfun$act$1."<init>":(Lscala/actors/Futures$FutureActor;Lscala/concurrent/SyncVar;)V
Asciz	scala/actors/Actor$$anon$6;
class	scala/actors/Actor$$anon$6
NameAndType	"<init>":(Lscala/Function0;)V
Method	scala/actors/Actor$$anon$6."<init>":(Lscala/Function0;)V
Asciz	scala/actors/Futures$FutureActor$$anonfun$act$2;
class	scala/actors/Futures$FutureActor$$anonfun$act$2
Method	scala/actors/Futures$FutureActor$$anonfun$act$2."<init>":(Lscala/actors/Futures$FutureActor;Lscala/concurrent/SyncVar;)V
Asciz	scala/actors/Actor$;
class	scala/actors/Actor$
Asciz	Lscala/actors/Actor$;;
NameAndType	MODULE$:Lscala/actors/Actor$;
Field	scala/actors/Actor$.MODULE$:Lscala/actors/Actor$;
Asciz	scala/actors/Scheduler$;
class	scala/actors/Scheduler$
Asciz	Lscala/actors/Scheduler$;;
NameAndType	MODULE$:Lscala/actors/Scheduler$;
Field	scala/actors/Scheduler$.MODULE$:Lscala/actors/Scheduler$;
Asciz	rawSelf;
Asciz	(Lscala/actors/IScheduler;)Lscala/actors/ReplyReactor;;
NameAndType	rawSelf:(Lscala/actors/IScheduler;)Lscala/actors/ReplyReactor;
Method	scala/actors/Actor$.rawSelf:(Lscala/actors/IScheduler;)Lscala/actors/ReplyReactor;
Asciz	scala/actors/Reactor;
class	scala/actors/Reactor
NameAndType	seq:(Lscala/Function0;Lscala/Function0;)V
InterfaceMethod	scala/actors/Reactor.seq:(Lscala/Function0;Lscala/Function0;)V
Asciz	res$1;
Asciz	Lscala/concurrent/SyncVar;;
Asciz	(Ljava/lang/Object;)Lscala/Function0;;
Asciz	(Ljava/lang/Object;Lscala/PartialFunction;)Lscala/Function0;;
NameAndType	$bang$bang:(Ljava/lang/Object;Lscala/PartialFunction;)Lscala/actors/Future;
InterfaceMethod	scala/actors/ReplyableActor.$bang$bang:(Ljava/lang/Object;Lscala/PartialFunction;)Lscala/actors/Future;
Asciz	()Lscala/actors/Reactor;;
Asciz	scala/actors/Actor;
class	scala/actors/Actor
NameAndType	start:()Lscala/actors/Actor;
InterfaceMethod	scala/actors/Actor.start:()Lscala/actors/Actor;
Asciz	(Lscala/Function1;Lscala/actors/Channel;)V;
NameAndType	scala$actors$Futures$FutureActor$$fun:Lscala/Function1;
Field	scala/actors/Futures$FutureActor.scala$actors$Futures$FutureActor$$fun:Lscala/Function1;
Asciz	(Lscala/actors/InputChannel;)V;
NameAndType	"<init>":(Lscala/actors/InputChannel;)V
Method	scala/actors/Future."<init>":(Lscala/actors/InputChannel;)V
Asciz	scala/actors/CanReply$class;
class	scala/actors/CanReply$class
Asciz	$init$;
Asciz	(Lscala/actors/CanReply;)V;
NameAndType	$init$:(Lscala/actors/CanReply;)V
Method	scala/actors/CanReply$class.$init$:(Lscala/actors/CanReply;)V
Asciz	scala/actors/AbstractActor$class;
class	scala/actors/AbstractActor$class
NameAndType	$init$:(Lscala/actors/AbstractActor;)V
Method	scala/actors/AbstractActor$class.$init$:(Lscala/actors/AbstractActor;)V
NameAndType	$init$:(Lscala/actors/Combinators;)V
Method	scala/actors/Combinators$class.$init$:(Lscala/actors/Combinators;)V
NameAndType	$init$:(Lscala/actors/Reactor;)V
Method	scala/actors/Reactor$class.$init$:(Lscala/actors/Reactor;)V
Asciz	scala/actors/ReplyableReactor$class;
class	scala/actors/ReplyableReactor$class
Asciz	(Lscala/actors/ReplyReactor;)V;
NameAndType	$init$:(Lscala/actors/ReplyReactor;)V
Method	scala/actors/ReplyableReactor$class.$init$:(Lscala/actors/ReplyReactor;)V
Method	scala/actors/ReplyReactor$class.$init$:(Lscala/actors/ReplyReactor;)V
Method	scala/actors/ReplyableActor$class.$init$:(Lscala/actors/AbstractActor;)V
NameAndType	$init$:(Lscala/actors/Actor;)V
Method	scala/actors/Actor$class.$init$:(Lscala/actors/Actor;)V
Asciz	(Lscala/actors/DaemonActor;)V;
NameAndType	$init$:(Lscala/actors/DaemonActor;)V
Method	scala/actors/DaemonActor$class.$init$:(Lscala/actors/DaemonActor;)V
Asciz	channel;
Asciz	Lscala/actors/Channel;;
Asciz	(Lscala/Function1<Lscala/concurrent/SyncVar<TT;>;Ljava/lang/Object;>;Lscala/actors/Channel<TT;>;)V;
Asciz	<T:Ljava/lang/Object;>Lscala/actors/Future<TT;>;Lscala/actors/DaemonActor;Lscala/ScalaObject;;
Asciz	Scala;
Asciz	InnerClasses;
Asciz	scala/actors/Actor$Body;
class	scala/actors/Actor$Body
Asciz	Body;
Asciz	$anon$6;
Asciz	scala/Enumeration$Value;
class	scala/Enumeration$Value
Asciz	scala/Enumeration;
class	scala/Enumeration
Asciz	Value;
Asciz	scala/actors/Futures;
class	scala/actors/Futures
Asciz	FutureActor;
Asciz	$anonfun$act$2;
Asciz	$anonfun$act$1;
Asciz	$anonfun$respond$1;
Asciz	scala/actors/DaemonActor;
class	scala/actors/DaemonActor
Asciz	scala/ScalaObject;
class	scala/ScalaObject

{
private scala.actors.Actor$blocker$ scala$actors$Actor$$blocker$module;
  Signature: Lscala/actors/Actor$blocker$;

private volatile scala.Function0 kill;
  Signature: Lscala/Function0;

private scala.Enumeration$Value _state;
  Signature: Lscala/Enumeration$Value;

private scala.PartialFunction waitingFor;
  Signature: Lscala/PartialFunction;

private final scala.actors.MQueue sendBuffer;
  Signature: Lscala/actors/MQueue;

private final scala.actors.MQueue mailbox;
  Signature: Lscala/actors/MQueue;

private scala.Option onTimeout;
  Signature: Lscala/Option;

private volatile scala.collection.immutable.List senders;
  Signature: Lscala/collection/immutable/List;

private boolean shouldExit;
  Signature: Z

private java.lang.Object scala$actors$Actor$$exitReason;
  Signature: Ljava/lang/Object;

private volatile boolean trapExit;
  Signature: Z

private scala.collection.immutable.List links;
  Signature: Lscala/collection/immutable/List;

private volatile scala.Option scala$actors$Actor$$received;
  Signature: Lscala/Option;

private volatile boolean scala$actors$Actor$$isSuspended;
  Signature: Z

public final scala.Function1 scala$actors$Futures$FutureActor$$fun;
  Signature: Lscala/Function1;

public scala.actors.IScheduler scheduler();
  Signature: ()Lscala/actors/IScheduler;
  Code:
   Stack=1, Locals=1, Args_size=1
	aload_0
	invokestatic	Method scala/actors/DaemonActor$class.scheduler:(Lscala/actors/DaemonActor;)Lscala/actors/IScheduler;
	areturn
  Labels:

public final boolean scala$actors$Actor$$isSuspended();
  Signature: ()Z
  Code:
   Stack=1, Locals=1, Args_size=1
	aload_0
	getfield	Field scala$actors$Actor$$isSuspended:Z
	ireturn
  Labels:

public final void scala$actors$Actor$$isSuspended_$eq(boolean);
  Signature: (Z)V
  Code:
   Stack=2, Locals=2, Args_size=2
	aload_0
	iload_1
	putfield	Field scala$actors$Actor$$isSuspended:Z
	return
  Labels:

public final scala.Option scala$actors$Actor$$received();
  Signature: ()Lscala/Option;
  Code:
   Stack=1, Locals=1, Args_size=1
	aload_0
	getfield	Field scala$actors$Actor$$received:Lscala/Option;
	areturn
  Labels:

public final void scala$actors$Actor$$received_$eq(scala.Option);
  Signature: (Lscala/Option;)V
  Code:
   Stack=2, Locals=2, Args_size=2
	aload_0
	aload_1
	putfield	Field scala$actors$Actor$$received:Lscala/Option;
	return
  Labels:

public final scala.actors.Actor$blocker$ scala$actors$Actor$$blocker();
  Signature: ()Lscala/actors/Actor$blocker$;
  Code:
   Stack=4, Locals=1, Args_size=1
	aload_0
	getfield	Field scala$actors$Actor$$blocker$module:Lscala/actors/Actor$blocker$;
	ifnonnull	l1 // aload_0
	aload_0
	new	class scala/actors/Actor$blocker$
	dup
	aload_0
	invokespecial	Method scala/actors/Actor$blocker$."<init>":(Lscala/actors/Actor;)V
	putfield	Field scala$actors$Actor$$blocker$module:Lscala/actors/Actor$blocker$;
l1	aload_0
	getfield	Field scala$actors$Actor$$blocker$module:Lscala/actors/Actor$blocker$;
	areturn
  Labels:
   	l1 = 19 // aload_0

public scala.collection.immutable.List links();
  Signature: ()Lscala/collection/immutable/List;
  Code:
   Stack=1, Locals=1, Args_size=1
	aload_0
	getfield	Field links:Lscala/collection/immutable/List;
	areturn
  Labels:

public void links_$eq(scala.collection.immutable.List);
  Signature: (Lscala/collection/immutable/List;)V
  Code:
   Stack=2, Locals=2, Args_size=2
	aload_0
	aload_1
	putfield	Field links:Lscala/collection/immutable/List;
	return
  Labels:

public boolean trapExit();
  Signature: ()Z
  Code:
   Stack=1, Locals=1, Args_size=1
	aload_0
	getfield	Field trapExit:Z
	ireturn
  Labels:

public void trapExit_$eq(boolean);
  Signature: (Z)V
  Code:
   Stack=2, Locals=2, Args_size=2
	aload_0
	iload_1
	putfield	Field trapExit:Z
	return
  Labels:

public final java.lang.Object scala$actors$Actor$$exitReason();
  Signature: ()Ljava/lang/Object;
  Code:
   Stack=1, Locals=1, Args_size=1
	aload_0
	getfield	Field scala$actors$Actor$$exitReason:Ljava/lang/Object;
	areturn
  Labels:

public final void scala$actors$Actor$$exitReason_$eq(java.lang.Object);
  Signature: (Ljava/lang/Object;)V
  Code:
   Stack=2, Locals=2, Args_size=2
	aload_0
	aload_1
	putfield	Field scala$actors$Actor$$exitReason:Ljava/lang/Object;
	return
  Labels:

public boolean shouldExit();
  Signature: ()Z
  Code:
   Stack=1, Locals=1, Args_size=1
	aload_0
	getfield	Field shouldExit:Z
	ireturn
  Labels:

public void shouldExit_$eq(boolean);
  Signature: (Z)V
  Code:
   Stack=2, Locals=2, Args_size=2
	aload_0
	iload_1
	putfield	Field shouldExit:Z
	return
  Labels:

public final scala.Function0 scala$actors$Actor$$super$startSearch(java.lang.Object, scala.actors.OutputChannel, scala.PartialFunction);
  Signature: (Ljava/lang/Object;Lscala/actors/OutputChannel;Lscala/PartialFunction;)Lscala/Function0;
  Code:
   Stack=4, Locals=4, Args_size=4
	aload_0
	aload_1
	aload_2
	aload_3
	invokestatic	Method scala/actors/Reactor$class.startSearch:(Lscala/actors/Reactor;Ljava/lang/Object;Lscala/actors/OutputChannel;Lscala/PartialFunction;)Lscala/Function0;
	areturn
  Labels:
  LocalVariableTable: 
   Start  Length  Slot  Name   Signature
   0      8      0    this       Lscala/actors/Futures$FutureActor;
   0      8      1    msg       Ljava/lang/Object;
   0      8      2    replyTo       Lscala/actors/OutputChannel;
   0      8      3    handler       Lscala/PartialFunction;


public final scala.runtime.Nothing$ scala$actors$Actor$$super$react(scala.PartialFunction);
  Signature: (Lscala/PartialFunction;)Lscala/runtime/Nothing$;
  Code:
   Stack=2, Locals=2, Args_size=2
	aload_0
	aload_1
	invokestatic	Method scala/actors/ReplyReactor$class.react:(Lscala/actors/ReplyReactor;Lscala/PartialFunction;)Lscala/runtime/Nothing$;
	areturn
  Labels:
  LocalVariableTable: 
   Start  Length  Slot  Name   Signature
   0      6      0    this       Lscala/actors/Futures$FutureActor;
   0      6      1    handler       Lscala/PartialFunction;


public final scala.runtime.Nothing$ scala$actors$Actor$$super$reactWithin(long, scala.PartialFunction);
  Signature: (JLscala/PartialFunction;)Lscala/runtime/Nothing$;
  Code:
   Stack=4, Locals=4, Args_size=3
	aload_0
	lload_1
	aload_3
	invokestatic	Method scala/actors/ReplyReactor$class.reactWithin:(Lscala/actors/ReplyReactor;JLscala/PartialFunction;)Lscala/runtime/Nothing$;
	areturn
  Labels:
  LocalVariableTable: 
   Start  Length  Slot  Name   Signature
   0      7      0    this       Lscala/actors/Futures$FutureActor;
   0      7      1    msec       J
   0      7      3    handler       Lscala/PartialFunction;


public final scala.Enumeration$Value scala$actors$Actor$$super$getState();
  Signature: ()Lscala/Enumeration$Value;
  Code:
   Stack=1, Locals=1, Args_size=1
	aload_0
	invokestatic	Method scala/actors/ReplyReactor$class.getState:(Lscala/actors/ReplyReactor;)Lscala/Enumeration$Value;
	areturn
  Labels:

public final scala.runtime.Nothing$ scala$actors$Actor$$super$exit();
  Signature: ()Lscala/runtime/Nothing$;
  Code:
   Stack=1, Locals=1, Args_size=1
	aload_0
	invokestatic	Method scala/actors/Reactor$class.exit:(Lscala/actors/Reactor;)Lscala/runtime/Nothing$;
	areturn
  Labels:

public scala.Function0 startSearch(java.lang.Object, scala.actors.OutputChannel, scala.PartialFunction);
  Signature: (Ljava/lang/Object;Lscala/actors/OutputChannel;Lscala/PartialFunction;)Lscala/Function0;
  Code:
   Stack=4, Locals=4, Args_size=4
	aload_0
	aload_1
	aload_2
	aload_3
	invokestatic	Method scala/actors/Actor$class.startSearch:(Lscala/actors/Actor;Ljava/lang/Object;Lscala/actors/OutputChannel;Lscala/PartialFunction;)Lscala/Function0;
	areturn
  Labels:
  LocalVariableTable: 
   Start  Length  Slot  Name   Signature
   0      8      0    this       Lscala/actors/Futures$FutureActor;
   0      8      1    msg       Ljava/lang/Object;
   0      8      2    replyTo       Lscala/actors/OutputChannel;
   0      8      3    handler       Lscala/PartialFunction;


public java.lang.Runnable makeReaction(scala.Function0);
  Signature: (Lscala/Function0;)Ljava/lang/Runnable;
  Code:
   Stack=2, Locals=2, Args_size=2
	aload_0
	aload_1
	invokestatic	Method scala/actors/Actor$class.makeReaction:(Lscala/actors/Actor;Lscala/Function0;)Ljava/lang/Runnable;
	areturn
  Labels:
  LocalVariableTable: 
   Start  Length  Slot  Name   Signature
   0      6      0    this       Lscala/actors/Futures$FutureActor;
   0      6      1    fun       Lscala/Function0;


public java.lang.Object receive(scala.PartialFunction);
  Signature: (Lscala/PartialFunction;)Ljava/lang/Object;
  Code:
   Stack=2, Locals=2, Args_size=2
	aload_0
	aload_1
	invokestatic	Method scala/actors/Actor$class.receive:(Lscala/actors/Actor;Lscala/PartialFunction;)Ljava/lang/Object;
	areturn
  Labels:
  LocalVariableTable: 
   Start  Length  Slot  Name   Signature
   0      6      0    this       Lscala/actors/Futures$FutureActor;
   0      6      1    f       Lscala/PartialFunction;


public java.lang.Object receiveWithin(long, scala.PartialFunction);
  Signature: (JLscala/PartialFunction;)Ljava/lang/Object;
  Code:
   Stack=4, Locals=4, Args_size=3
	aload_0
	lload_1
	aload_3
	invokestatic	Method scala/actors/Actor$class.receiveWithin:(Lscala/actors/Actor;JLscala/PartialFunction;)Ljava/lang/Object;
	areturn
  Labels:
  LocalVariableTable: 
   Start  Length  Slot  Name   Signature
   0      7      0    this       Lscala/actors/Futures$FutureActor;
   0      7      1    msec       J
   0      7      3    f       Lscala/PartialFunction;


public scala.runtime.Nothing$ react(scala.PartialFunction);
  Signature: (Lscala/PartialFunction;)Lscala/runtime/Nothing$;
  Code:
   Stack=2, Locals=2, Args_size=2
	aload_0
	aload_1
	invokestatic	Method scala/actors/Actor$class.react:(Lscala/actors/Actor;Lscala/PartialFunction;)Lscala/runtime/Nothing$;
	areturn
  Labels:
  LocalVariableTable: 
   Start  Length  Slot  Name   Signature
   0      6      0    this       Lscala/actors/Futures$FutureActor;
   0      6      1    handler       Lscala/PartialFunction;


public scala.runtime.Nothing$ reactWithin(long, scala.PartialFunction);
  Signature: (JLscala/PartialFunction;)Lscala/runtime/Nothing$;
  Code:
   Stack=4, Locals=4, Args_size=3
	aload_0
	lload_1
	aload_3
	invokestatic	Method scala/actors/Actor$class.reactWithin:(Lscala/actors/Actor;JLscala/PartialFunction;)Lscala/runtime/Nothing$;
	areturn
  Labels:
  LocalVariableTable: 
   Start  Length  Slot  Name   Signature
   0      7      0    this       Lscala/actors/Futures$FutureActor;
   0      7      1    msec       J
   0      7      3    handler       Lscala/PartialFunction;


public java.lang.Object $qmark();
  Signature: ()Ljava/lang/Object;
  Code:
   Stack=1, Locals=1, Args_size=1
	aload_0
	invokestatic	Method scala/actors/Actor$class.$qmark:(Lscala/actors/Actor;)Ljava/lang/Object;
	areturn
  Labels:

public void scheduleActor(scala.PartialFunction, java.lang.Object);
  Signature: (Lscala/PartialFunction;Ljava/lang/Object;)V
  Code:
   Stack=3, Locals=3, Args_size=3
	aload_0
	aload_1
	aload_2
	invokestatic	Method scala/actors/Actor$class.scheduleActor:(Lscala/actors/Actor;Lscala/PartialFunction;Ljava/lang/Object;)V
	return
  Labels:
  LocalVariableTable: 
   Start  Length  Slot  Name   Signature
   0      7      0    this       Lscala/actors/Futures$FutureActor;
   0      7      1    f       Lscala/PartialFunction;
   0      7      2    msg       Ljava/lang/Object;


public boolean exiting();
  Signature: ()Z
  Code:
   Stack=1, Locals=1, Args_size=1
	aload_0
	invokestatic	Method scala/actors/Actor$class.exiting:(Lscala/actors/Actor;)Z
	ireturn
  Labels:

public scala.actors.Actor start();
  Signature: ()Lscala/actors/Actor;
  Code:
   Stack=1, Locals=1, Args_size=1
	aload_0
	invokestatic	Method scala/actors/Actor$class.start:(Lscala/actors/Actor;)Lscala/actors/Actor;
	areturn
  Labels:

public scala.Enumeration$Value getState();
  Signature: ()Lscala/Enumeration$Value;
  Code:
   Stack=1, Locals=1, Args_size=1
	aload_0
	invokestatic	Method scala/actors/Actor$class.getState:(Lscala/actors/Actor;)Lscala/Enumeration$Value;
	areturn
  Labels:

public scala.actors.AbstractActor link(scala.actors.AbstractActor);
  Signature: (Lscala/actors/AbstractActor;)Lscala/actors/AbstractActor;
  Code:
   Stack=2, Locals=2, Args_size=2
	aload_0
	aload_1
	invokestatic	Method scala/actors/Actor$class.link:(Lscala/actors/Actor;Lscala/actors/AbstractActor;)Lscala/actors/AbstractActor;
	areturn
  Labels:
  LocalVariableTable: 
   Start  Length  Slot  Name   Signature
   0      6      0    this       Lscala/actors/Futures$FutureActor;
   0      6      1    to       Lscala/actors/AbstractActor;


public scala.actors.Actor link(scala.Function0);
  Signature: (Lscala/Function0;)Lscala/actors/Actor;
  Code:
   Stack=2, Locals=2, Args_size=2
	aload_0
	aload_1
	invokestatic	Method scala/actors/Actor$class.link:(Lscala/actors/Actor;Lscala/Function0;)Lscala/actors/Actor;
	areturn
  Labels:
  LocalVariableTable: 
   Start  Length  Slot  Name   Signature
   0      6      0    this       Lscala/actors/Futures$FutureActor;
   0      6      1    body       Lscala/Function0;


public void linkTo(scala.actors.AbstractActor);
  Signature: (Lscala/actors/AbstractActor;)V
  Code:
   Stack=2, Locals=2, Args_size=2
	aload_0
	aload_1
	invokestatic	Method scala/actors/Actor$class.linkTo:(Lscala/actors/Actor;Lscala/actors/AbstractActor;)V
	return
  Labels:
  LocalVariableTable: 
   Start  Length  Slot  Name   Signature
   0      6      0    this       Lscala/actors/Futures$FutureActor;
   0      6      1    to       Lscala/actors/AbstractActor;


public void unlink(scala.actors.AbstractActor);
  Signature: (Lscala/actors/AbstractActor;)V
  Code:
   Stack=2, Locals=2, Args_size=2
	aload_0
	aload_1
	invokestatic	Method scala/actors/Actor$class.unlink:(Lscala/actors/Actor;Lscala/actors/AbstractActor;)V
	return
  Labels:
  LocalVariableTable: 
   Start  Length  Slot  Name   Signature
   0      6      0    this       Lscala/actors/Futures$FutureActor;
   0      6      1    from       Lscala/actors/AbstractActor;


public void unlinkFrom(scala.actors.AbstractActor);
  Signature: (Lscala/actors/AbstractActor;)V
  Code:
   Stack=2, Locals=2, Args_size=2
	aload_0
	aload_1
	invokestatic	Method scala/actors/Actor$class.unlinkFrom:(Lscala/actors/Actor;Lscala/actors/AbstractActor;)V
	return
  Labels:
  LocalVariableTable: 
   Start  Length  Slot  Name   Signature
   0      6      0    this       Lscala/actors/Futures$FutureActor;
   0      6      1    from       Lscala/actors/AbstractActor;


public scala.runtime.Nothing$ exit(java.lang.Object);
  Signature: (Ljava/lang/Object;)Lscala/runtime/Nothing$;
  Code:
   Stack=2, Locals=2, Args_size=2
	aload_0
	aload_1
	invokestatic	Method scala/actors/Actor$class.exit:(Lscala/actors/Actor;Ljava/lang/Object;)Lscala/runtime/Nothing$;
	areturn
  Labels:
  LocalVariableTable: 
   Start  Length  Slot  Name   Signature
   0      6      0    this       Lscala/actors/Futures$FutureActor;
   0      6      1    reason       Ljava/lang/Object;


public scala.runtime.Nothing$ exit();
  Signature: ()Lscala/runtime/Nothing$;
  Code:
   Stack=1, Locals=1, Args_size=1
	aload_0
	invokestatic	Method scala/actors/Actor$class.exit:(Lscala/actors/Actor;)Lscala/runtime/Nothing$;
	areturn
  Labels:

public void exitLinked();
  Signature: ()V
  Code:
   Stack=1, Locals=1, Args_size=1
	aload_0
	invokestatic	Method scala/actors/Actor$class.exitLinked:(Lscala/actors/Actor;)V
	return
  Labels:

public void exitLinked(java.lang.Object);
  Signature: (Ljava/lang/Object;)V
  Code:
   Stack=2, Locals=2, Args_size=2
	aload_0
	aload_1
	invokestatic	Method scala/actors/Actor$class.exitLinked:(Lscala/actors/Actor;Ljava/lang/Object;)V
	return
  Labels:
  LocalVariableTable: 
   Start  Length  Slot  Name   Signature
   0      6      0    this       Lscala/actors/Futures$FutureActor;
   0      6      1    reason       Ljava/lang/Object;


public void exit(scala.actors.AbstractActor, java.lang.Object);
  Signature: (Lscala/actors/AbstractActor;Ljava/lang/Object;)V
  Code:
   Stack=3, Locals=3, Args_size=3
	aload_0
	aload_1
	aload_2
	invokestatic	Method scala/actors/Actor$class.exit:(Lscala/actors/Actor;Lscala/actors/AbstractActor;Ljava/lang/Object;)V
	return
  Labels:
  LocalVariableTable: 
   Start  Length  Slot  Name   Signature
   0      7      0    this       Lscala/actors/Futures$FutureActor;
   0      7      1    from       Lscala/actors/AbstractActor;
   0      7      2    reason       Ljava/lang/Object;


public void onTerminate(scala.Function0);
  Signature: (Lscala/Function0;)V
  Code:
   Stack=2, Locals=2, Args_size=2
	aload_0
	aload_1
	invokestatic	Method scala/actors/Actor$class.onTerminate:(Lscala/actors/Actor;Lscala/Function0;)V
	return
  Labels:
  LocalVariableTable: 
   Start  Length  Slot  Name   Signature
   0      6      0    this       Lscala/actors/Futures$FutureActor;
   0      6      1    f       Lscala/Function0;


public java.lang.Object $bang$qmark(java.lang.Object);
  Signature: (Ljava/lang/Object;)Ljava/lang/Object;
  Code:
   Stack=2, Locals=2, Args_size=2
	aload_0
	aload_1
	invokestatic	Method scala/actors/ReplyableActor$class.$bang$qmark:(Lscala/actors/AbstractActor;Ljava/lang/Object;)Ljava/lang/Object;
	areturn
  Labels:
  LocalVariableTable: 
   Start  Length  Slot  Name   Signature
   0      6      0    this       Lscala/actors/Futures$FutureActor;
   0      6      1    msg       Ljava/lang/Object;


public scala.Option $bang$qmark(long, java.lang.Object);
  Signature: (JLjava/lang/Object;)Lscala/Option;
  Code:
   Stack=4, Locals=4, Args_size=3
	aload_0
	lload_1
	aload_3
	invokestatic	Method scala/actors/ReplyableActor$class.$bang$qmark:(Lscala/actors/AbstractActor;JLjava/lang/Object;)Lscala/Option;
	areturn
  Labels:
  LocalVariableTable: 
   Start  Length  Slot  Name   Signature
   0      7      0    this       Lscala/actors/Futures$FutureActor;
   0      7      1    msec       J
   0      7      3    msg       Ljava/lang/Object;


public scala.actors.Future $bang$bang(java.lang.Object, scala.PartialFunction);
  Signature: (Ljava/lang/Object;Lscala/PartialFunction;)Lscala/actors/Future;
  Code:
   Stack=3, Locals=3, Args_size=3
	aload_0
	aload_1
	aload_2
	invokestatic	Method scala/actors/ReplyableActor$class.$bang$bang:(Lscala/actors/AbstractActor;Ljava/lang/Object;Lscala/PartialFunction;)Lscala/actors/Future;
	areturn
  Labels:
  LocalVariableTable: 
   Start  Length  Slot  Name   Signature
   0      7      0    this       Lscala/actors/Futures$FutureActor;
   0      7      1    msg       Ljava/lang/Object;
   0      7      2    handler       Lscala/PartialFunction;


public scala.actors.Future $bang$bang(java.lang.Object);
  Signature: (Ljava/lang/Object;)Lscala/actors/Future;
  Code:
   Stack=2, Locals=2, Args_size=2
	aload_0
	aload_1
	invokestatic	Method scala/actors/ReplyableActor$class.$bang$bang:(Lscala/actors/AbstractActor;Ljava/lang/Object;)Lscala/actors/Future;
	areturn
  Labels:
  LocalVariableTable: 
   Start  Length  Slot  Name   Signature
   0      6      0    this       Lscala/actors/Futures$FutureActor;
   0      6      1    msg       Ljava/lang/Object;


public scala.collection.immutable.List senders();
  Signature: ()Lscala/collection/immutable/List;
  Code:
   Stack=1, Locals=1, Args_size=1
	aload_0
	getfield	Field senders:Lscala/collection/immutable/List;
	areturn
  Labels:

public void senders_$eq(scala.collection.immutable.List);
  Signature: (Lscala/collection/immutable/List;)V
  Code:
   Stack=2, Locals=2, Args_size=2
	aload_0
	aload_1
	putfield	Field senders:Lscala/collection/immutable/List;
	return
  Labels:

public scala.Option onTimeout();
  Signature: ()Lscala/Option;
  Code:
   Stack=1, Locals=1, Args_size=1
	aload_0
	getfield	Field onTimeout:Lscala/Option;
	areturn
  Labels:

public void onTimeout_$eq(scala.Option);
  Signature: (Lscala/Option;)V
  Code:
   Stack=2, Locals=2, Args_size=2
	aload_0
	aload_1
	putfield	Field onTimeout:Lscala/Option;
	return
  Labels:

public final void scala$actors$ReplyReactor$$super$resumeReceiver(scala.Tuple2, scala.PartialFunction, boolean);
  Signature: (Lscala/Tuple2;Lscala/PartialFunction;Z)V
  Code:
   Stack=4, Locals=4, Args_size=4
	aload_0
	aload_1
	aload_2
	iload_3
	invokestatic	Method scala/actors/Reactor$class.resumeReceiver:(Lscala/actors/Reactor;Lscala/Tuple2;Lscala/PartialFunction;Z)V
	return
  Labels:
  LocalVariableTable: 
   Start  Length  Slot  Name   Signature
   0      8      0    this       Lscala/actors/Futures$FutureActor;
   0      8      1    item       Lscala/Tuple2;
   0      8      2    handler       Lscala/PartialFunction;
   0      8      3    onSameThread       Z


public final scala.runtime.Nothing$ scala$actors$ReplyReactor$$super$react(scala.PartialFunction);
  Signature: (Lscala/PartialFunction;)Lscala/runtime/Nothing$;
  Code:
   Stack=2, Locals=2, Args_size=2
	aload_0
	aload_1
	invokestatic	Method scala/actors/Reactor$class.react:(Lscala/actors/Reactor;Lscala/PartialFunction;)Lscala/runtime/Nothing$;
	areturn
  Labels:
  LocalVariableTable: 
   Start  Length  Slot  Name   Signature
   0      6      0    this       Lscala/actors/Futures$FutureActor;
   0      6      1    handler       Lscala/PartialFunction;


public scala.actors.OutputChannel sender();
  Signature: ()Lscala/actors/OutputChannel;
  Code:
   Stack=1, Locals=1, Args_size=1
	aload_0
	invokestatic	Method scala/actors/ReplyReactor$class.sender:(Lscala/actors/ReplyReactor;)Lscala/actors/OutputChannel;
	areturn
  Labels:

public void reply(java.lang.Object);
  Signature: (Ljava/lang/Object;)V
  Code:
   Stack=2, Locals=2, Args_size=2
	aload_0
	aload_1
	invokestatic	Method scala/actors/ReplyReactor$class.reply:(Lscala/actors/ReplyReactor;Ljava/lang/Object;)V
	return
  Labels:
  LocalVariableTable: 
   Start  Length  Slot  Name   Signature
   0      6      0    this       Lscala/actors/Futures$FutureActor;
   0      6      1    msg       Ljava/lang/Object;


public void $bang(java.lang.Object);
  Signature: (Ljava/lang/Object;)V
  Code:
   Stack=2, Locals=2, Args_size=2
	aload_0
	aload_1
	invokestatic	Method scala/actors/ReplyReactor$class.$bang:(Lscala/actors/ReplyReactor;Ljava/lang/Object;)V
	return
  Labels:
  LocalVariableTable: 
   Start  Length  Slot  Name   Signature
   0      6      0    this       Lscala/actors/Futures$FutureActor;
   0      6      1    msg       Ljava/lang/Object;


public void forward(java.lang.Object);
  Signature: (Ljava/lang/Object;)V
  Code:
   Stack=2, Locals=2, Args_size=2
	aload_0
	aload_1
	invokestatic	Method scala/actors/ReplyReactor$class.forward:(Lscala/actors/ReplyReactor;Ljava/lang/Object;)V
	return
  Labels:
  LocalVariableTable: 
   Start  Length  Slot  Name   Signature
   0      6      0    this       Lscala/actors/Futures$FutureActor;
   0      6      1    msg       Ljava/lang/Object;


public void resumeReceiver(scala.Tuple2, scala.PartialFunction, boolean);
  Signature: (Lscala/Tuple2;Lscala/PartialFunction;Z)V
  Code:
   Stack=4, Locals=4, Args_size=4
	aload_0
	aload_1
	aload_2
	iload_3
	invokestatic	Method scala/actors/ReplyReactor$class.resumeReceiver:(Lscala/actors/ReplyReactor;Lscala/Tuple2;Lscala/PartialFunction;Z)V
	return
  Labels:
  LocalVariableTable: 
   Start  Length  Slot  Name   Signature
   0      8      0    this       Lscala/actors/Futures$FutureActor;
   0      8      1    item       Lscala/Tuple2;
   0      8      2    handler       Lscala/PartialFunction;
   0      8      3    onSameThread       Z


public void searchMailbox(scala.actors.MQueue, scala.PartialFunction, boolean);
  Signature: (Lscala/actors/MQueue;Lscala/PartialFunction;Z)V
  Code:
   Stack=4, Locals=4, Args_size=4
	aload_0
	aload_1
	aload_2
	iload_3
	invokestatic	Method scala/actors/ReplyReactor$class.searchMailbox:(Lscala/actors/ReplyReactor;Lscala/actors/MQueue;Lscala/PartialFunction;Z)V
	return
  Labels:
  LocalVariableTable: 
   Start  Length  Slot  Name   Signature
   0      8      0    this       Lscala/actors/Futures$FutureActor;
   0      8      1    startMbox       Lscala/actors/MQueue;
   0      8      2    handler       Lscala/PartialFunction;
   0      8      3    resumeOnSameThread       Z


public scala.actors.MQueue mailbox();
  Signature: ()Lscala/actors/MQueue;
  Code:
   Stack=1, Locals=1, Args_size=1
	aload_0
	getfield	Field mailbox:Lscala/actors/MQueue;
	areturn
  Labels:

public scala.actors.MQueue sendBuffer();
  Signature: ()Lscala/actors/MQueue;
  Code:
   Stack=1, Locals=1, Args_size=1
	aload_0
	getfield	Field sendBuffer:Lscala/actors/MQueue;
	areturn
  Labels:

public scala.PartialFunction waitingFor();
  Signature: ()Lscala/PartialFunction;
  Code:
   Stack=1, Locals=1, Args_size=1
	aload_0
	getfield	Field waitingFor:Lscala/PartialFunction;
	areturn
  Labels:

public void waitingFor_$eq(scala.PartialFunction);
  Signature: (Lscala/PartialFunction;)V
  Code:
   Stack=2, Locals=2, Args_size=2
	aload_0
	aload_1
	putfield	Field waitingFor:Lscala/PartialFunction;
	return
  Labels:

public scala.Enumeration$Value _state();
  Signature: ()Lscala/Enumeration$Value;
  Code:
   Stack=1, Locals=1, Args_size=1
	aload_0
	getfield	Field _state:Lscala/Enumeration$Value;
	areturn
  Labels:

public void _state_$eq(scala.Enumeration$Value);
  Signature: (Lscala/Enumeration$Value;)V
  Code:
   Stack=2, Locals=2, Args_size=2
	aload_0
	aload_1
	putfield	Field _state:Lscala/Enumeration$Value;
	return
  Labels:

public scala.Function0 kill();
  Signature: ()Lscala/Function0;
  Code:
   Stack=1, Locals=1, Args_size=1
	aload_0
	getfield	Field kill:Lscala/Function0;
	areturn
  Labels:

public void kill_$eq(scala.Function0);
  Signature: (Lscala/Function0;)V
  Code:
   Stack=2, Locals=2, Args_size=2
	aload_0
	aload_1
	putfield	Field kill:Lscala/Function0;
	return
  Labels:

public void scala$actors$Reactor$_setter_$mailbox_$eq(scala.actors.MQueue);
  Signature: (Lscala/actors/MQueue;)V
  Code:
   Stack=2, Locals=2, Args_size=2
	aload_0
	aload_1
	putfield	Field mailbox:Lscala/actors/MQueue;
	return
  Labels:

public void scala$actors$Reactor$_setter_$sendBuffer_$eq(scala.actors.MQueue);
  Signature: (Lscala/actors/MQueue;)V
  Code:
   Stack=2, Locals=2, Args_size=2
	aload_0
	aload_1
	putfield	Field sendBuffer:Lscala/actors/MQueue;
	return
  Labels:

public scala.PartialFunction exceptionHandler();
  Signature: ()Lscala/PartialFunction;
  Code:
   Stack=1, Locals=1, Args_size=1
	aload_0
	invokestatic	Method scala/actors/Reactor$class.exceptionHandler:(Lscala/actors/Reactor;)Lscala/PartialFunction;
	areturn
  Labels:

public int mailboxSize();
  Signature: ()I
  Code:
   Stack=1, Locals=1, Args_size=1
	aload_0
	invokestatic	Method scala/actors/Reactor$class.mailboxSize:(Lscala/actors/Reactor;)I
	ireturn
  Labels:

public void send(java.lang.Object, scala.actors.OutputChannel);
  Signature: (Ljava/lang/Object;Lscala/actors/OutputChannel;)V
  Code:
   Stack=3, Locals=3, Args_size=3
	aload_0
	aload_1
	aload_2
	invokestatic	Method scala/actors/Reactor$class.send:(Lscala/actors/Reactor;Ljava/lang/Object;Lscala/actors/OutputChannel;)V
	return
  Labels:
  LocalVariableTable: 
   Start  Length  Slot  Name   Signature
   0      7      0    this       Lscala/actors/Futures$FutureActor;
   0      7      1    msg       Ljava/lang/Object;
   0      7      2    replyTo       Lscala/actors/OutputChannel;


public scala.actors.Actor receiver();
  Signature: ()Lscala/actors/Actor;
  Code:
   Stack=1, Locals=1, Args_size=1
	aload_0
	invokestatic	Method scala/actors/Reactor$class.receiver:(Lscala/actors/Reactor;)Lscala/actors/Actor;
	areturn
  Labels:

public void drainSendBuffer(scala.actors.MQueue);
  Signature: (Lscala/actors/MQueue;)V
  Code:
   Stack=2, Locals=2, Args_size=2
	aload_0
	aload_1
	invokestatic	Method scala/actors/Reactor$class.drainSendBuffer:(Lscala/actors/Reactor;Lscala/actors/MQueue;)V
	return
  Labels:
  LocalVariableTable: 
   Start  Length  Slot  Name   Signature
   0      6      0    this       Lscala/actors/Futures$FutureActor;
   0      6      1    mbox       Lscala/actors/MQueue;


public scala.actors.Actor$Body mkBody(scala.Function0);
  Signature: (Lscala/Function0;)Lscala/actors/Actor$Body;
  Code:
   Stack=2, Locals=2, Args_size=2
	aload_0
	aload_1
	invokestatic	Method scala/actors/Reactor$class.mkBody:(Lscala/actors/Reactor;Lscala/Function0;)Lscala/actors/Actor$Body;
	areturn
  Labels:
  LocalVariableTable: 
   Start  Length  Slot  Name   Signature
   0      6      0    this       Lscala/actors/Futures$FutureActor;
   0      6      1    body       Lscala/Function0;


public void seq(scala.Function0, scala.Function0);
  Signature: (Lscala/Function0;Lscala/Function0;)V
  Code:
   Stack=3, Locals=3, Args_size=3
	aload_0
	aload_1
	aload_2
	invokestatic	Method scala/actors/Reactor$class.seq:(Lscala/actors/Reactor;Lscala/Function0;Lscala/Function0;)V
	return
  Labels:
  LocalVariableTable: 
   Start  Length  Slot  Name   Signature
   0      7      0    this       Lscala/actors/Futures$FutureActor;
   0      7      1    first       Lscala/Function0;
   0      7      2    next       Lscala/Function0;


public void terminated();
  Signature: ()V
  Code:
   Stack=1, Locals=1, Args_size=1
	aload_0
	invokestatic	Method scala/actors/Reactor$class.terminated:(Lscala/actors/Reactor;)V
	return
  Labels:

public void loop(scala.Function0);
  Signature: (Lscala/Function0;)V
  Code:
   Stack=2, Locals=2, Args_size=2
	aload_0
	aload_1
	invokestatic	Method scala/actors/Combinators$class.loop:(Lscala/actors/Combinators;Lscala/Function0;)V
	return
  Labels:
  LocalVariableTable: 
   Start  Length  Slot  Name   Signature
   0      6      0    this       Lscala/actors/Futures$FutureActor;
   0      6      1    body       Lscala/Function0;


public void loopWhile(scala.Function0, scala.Function0);
  Signature: (Lscala/Function0;Lscala/Function0;)V
  Code:
   Stack=3, Locals=3, Args_size=3
	aload_0
	aload_1
	aload_2
	invokestatic	Method scala/actors/Combinators$class.loopWhile:(Lscala/actors/Combinators;Lscala/Function0;Lscala/Function0;)V
	return
  Labels:
  LocalVariableTable: 
   Start  Length  Slot  Name   Signature
   0      7      0    this       Lscala/actors/Futures$FutureActor;
   0      7      1    cond       Lscala/Function0;
   0      7      2    body       Lscala/Function0;


public void continue();
  Signature: ()V
  Code:
   Stack=1, Locals=1, Args_size=1
	aload_0
	invokestatic	Method scala/actors/Combinators$class.continue:(Lscala/actors/Combinators;)V
	return
  Labels:

public final scala.actors.InputChannel scala$actors$Futures$FutureActor$$super$inputChannel();
  Signature: ()Lscala/actors/InputChannel;
  Code:
   Stack=1, Locals=1, Args_size=1
	aload_0
	invokespecial	Method scala/actors/Future.inputChannel:()Lscala/actors/InputChannel;
	areturn
  Labels:

public boolean isSet();
  Signature: ()Z
  Code:
   Stack=1, Locals=1, Args_size=1
	aload_0
	invokevirtual	Method fvalue:()Lscala/Option;
	invokevirtual	Method scala/Option.isEmpty:()Z
	ifeq	l1 // iconst_1
	iconst_0
	goto	l2 // ireturn
l1	iconst_1
l2	ireturn
  Labels:
   	l1 = 14 // iconst_1
   	l2 = 15 // ireturn

public java.lang.Object apply();
  Signature: ()Ljava/lang/Object;
  Code:
   Stack=2, Locals=1, Args_size=1
	aload_0
	invokevirtual	Method fvalue:()Lscala/Option;
	invokevirtual	Method scala/Option.isEmpty:()Z
	ifeq	l1 // getstatic
	aload_0
	getstatic	Field scala/actors/Futures$Eval$.MODULE$:Lscala/actors/Futures$Eval$;
	invokeinterface	InterfaceMethod scala/actors/ReplyableActor.$bang$qmark:(Ljava/lang/Object;)Ljava/lang/Object;
	goto	l2 // pop
l1	getstatic	Field scala/runtime/BoxedUnit.UNIT:Lscala/runtime/BoxedUnit;
l2	pop
	aload_0
	invokevirtual	Method fvalueTyped:()Ljava/lang/Object;
	areturn
  Labels:
   	l1 = 22 // getstatic
   	l2 = 25 // pop
  Signature: length = 0x2
   01 FFFFFF86 

public void respond(scala.Function1);
  Signature: (Lscala/Function1;)V
  Code:
   Stack=5, Locals=3, Args_size=2
	aload_0
	invokevirtual	Method isSet:()Z
	ifeq	l1 // aload_0
	aload_1
	aload_0
	invokevirtual	Method fvalueTyped:()Ljava/lang/Object;
	invokeinterface	InterfaceMethod scala/Function1.apply:(Ljava/lang/Object;)Ljava/lang/Object;
	pop
	return
l1	aload_0
	getstatic	Field scala/actors/Futures$Eval$.MODULE$:Lscala/actors/Futures$Eval$;
	invokeinterface	InterfaceMethod scala/actors/ReplyableActor.$bang$bang:(Ljava/lang/Object;)Lscala/actors/Future;
	astore_2
	aload_2
	invokevirtual	Method scala/actors/Future.inputChannel:()Lscala/actors/InputChannel;
	new	class scala/actors/Futures$FutureActor$$anonfun$respond$1
	dup
	aload_0
	aload_1
	invokespecial	Method scala/actors/Futures$FutureActor$$anonfun$respond$1."<init>":(Lscala/actors/Futures$FutureActor;Lscala/Function1;)V
	invokeinterface	InterfaceMethod scala/actors/InputChannel.react:(Lscala/PartialFunction;)Lscala/runtime/Nothing$;
	athrow
  Labels:
   	l1 = 19 // aload_0
  LocalVariableTable: 
   Start  Length  Slot  Name   Signature
   0      48      0    this       Lscala/actors/Futures$FutureActor;
   0      48      1    k$1       Lscala/Function1;
   29      19      2    ft       Lscala/actors/Future;

  Signature: length = 0x2
   01 FFFFFF9E 

public void act();
  Signature: ()V
  Code:
   Stack=4, Locals=5, Args_size=1
	new	class scala/concurrent/SyncVar
	dup
	invokespecial	Method scala/concurrent/SyncVar."<init>":()V
	astore_1
	new	class scala/actors/Futures$FutureActor$$anonfun$act$1
	dup
	aload_0
	aload_1
	invokespecial	Method scala/actors/Futures$FutureActor$$anonfun$act$1."<init>":(Lscala/actors/Futures$FutureActor;Lscala/concurrent/SyncVar;)V
	astore_3
	new	class scala/actors/Actor$$anon$6
	dup
	aload_3
	invokespecial	Method scala/actors/Actor$$anon$6."<init>":(Lscala/Function0;)V
	pop
	new	class scala/actors/Futures$FutureActor$$anonfun$act$2
	dup
	aload_0
	aload_1
	invokespecial	Method scala/actors/Futures$FutureActor$$anonfun$act$2."<init>":(Lscala/actors/Futures$FutureActor;Lscala/concurrent/SyncVar;)V
	astore	4
	getstatic	Field scala/actors/Actor$.MODULE$:Lscala/actors/Actor$;
	astore_2
	aload_2
	getstatic	Field scala/actors/Scheduler$.MODULE$:Lscala/actors/Scheduler$;
	invokevirtual	Method scala/actors/Actor$.rawSelf:(Lscala/actors/IScheduler;)Lscala/actors/ReplyReactor;
	aload_3
	aload	4
	invokeinterface	InterfaceMethod scala/actors/Reactor.seq:(Lscala/Function0;Lscala/Function0;)V
	return
  Labels:
  LocalVariableTable: 
   Start  Length  Slot  Name   Signature
   0      58      0    this       Lscala/actors/Futures$FutureActor;
   8      49      1    res$1       Lscala/concurrent/SyncVar;


public scala.Function0 $bang$bang(java.lang.Object);
  Signature: (Ljava/lang/Object;)Lscala/Function0;
  Code:
   Stack=2, Locals=2, Args_size=2
	aload_0
	aload_1
	invokeinterface	InterfaceMethod scala/actors/ReplyableActor.$bang$bang:(Ljava/lang/Object;)Lscala/actors/Future;
	areturn
  Labels:
  LocalVariableTable: 
   Start  Length  Slot  Name   Signature
   0      8      0    this       Lscala/actors/Futures$FutureActor;
   0      8      1    msg       Ljava/lang/Object;


public scala.Function0 $bang$bang(java.lang.Object, scala.PartialFunction);
  Signature: (Ljava/lang/Object;Lscala/PartialFunction;)Lscala/Function0;
  Code:
   Stack=3, Locals=3, Args_size=3
	aload_0
	aload_1
	aload_2
	invokeinterface	InterfaceMethod scala/actors/ReplyableActor.$bang$bang:(Ljava/lang/Object;Lscala/PartialFunction;)Lscala/actors/Future;
	areturn
  Labels:
  LocalVariableTable: 
   Start  Length  Slot  Name   Signature
   0      9      0    this       Lscala/actors/Futures$FutureActor;
   0      9      1    msg       Ljava/lang/Object;
   0      9      2    handler       Lscala/PartialFunction;


public scala.actors.Reactor start();
  Signature: ()Lscala/actors/Reactor;
  Code:
   Stack=1, Locals=1, Args_size=1
	aload_0
	invokeinterface	InterfaceMethod scala/actors/Actor.start:()Lscala/actors/Actor;
	areturn
  Labels:

public scala.actors.Futures$FutureActor(scala.Function1, scala.actors.Channel);
  Signature: (Lscala/Function1;Lscala/actors/Channel;)V
  Code:
   Stack=2, Locals=3, Args_size=3
	aload_0
	aload_1
	putfield	Field scala$actors$Futures$FutureActor$$fun:Lscala/Function1;
	aload_0
	aload_2
	invokespecial	Method scala/actors/Future."<init>":(Lscala/actors/InputChannel;)V
	aload_0
	invokestatic	Method scala/actors/CanReply$class.$init$:(Lscala/actors/CanReply;)V
	aload_0
	invokestatic	Method scala/actors/AbstractActor$class.$init$:(Lscala/actors/AbstractActor;)V
	aload_0
	invokestatic	Method scala/actors/Combinators$class.$init$:(Lscala/actors/Combinators;)V
	aload_0
	invokestatic	Method scala/actors/Reactor$class.$init$:(Lscala/actors/Reactor;)V
	aload_0
	invokestatic	Method scala/actors/ReplyableReactor$class.$init$:(Lscala/actors/ReplyReactor;)V
	aload_0
	invokestatic	Method scala/actors/ReplyReactor$class.$init$:(Lscala/actors/ReplyReactor;)V
	aload_0
	invokestatic	Method scala/actors/ReplyableActor$class.$init$:(Lscala/actors/AbstractActor;)V
	aload_0
	invokestatic	Method scala/actors/Actor$class.$init$:(Lscala/actors/Actor;)V
	aload_0
	invokestatic	Method scala/actors/DaemonActor$class.$init$:(Lscala/actors/DaemonActor;)V
	return
  Labels:
  LocalVariableTable: 
   Start  Length  Slot  Name   Signature
   0      47      0    this       Lscala/actors/Futures$FutureActor;
   0      47      1    fun       Lscala/Function1;
   0      47      2    channel       Lscala/actors/Channel;

  Signature: length = 0x2
   01 FFFFFFEF 

}

