Compiled from "Future.scala"
public final class scala.actors.Futures$$anonfun$5 extends scala.runtime.AbstractFunction1 implements java.io.Serializable
  SourceFile: "Future.scala"
  Scala: length = 0x
   
  InnerClass: 
   public final $anonfun$5=class scala/actors/Futures$$anonfun$5 of class scala/actors/Futures
   public final $anonfun$6=class scala/actors/Futures$$anonfun$5$$anonfun$6 of class scala/actors/Futures$$anonfun$5
  minor version: 0
  major version: 49
  Constant pool:
Asciz	SourceFile;
Asciz	Future.scala;
Asciz	<clinit>;
Asciz	()V;
Asciz	Code;
Asciz	serialVersionUID;
Asciz	J;
Asciz	scala/actors/Futures$$anonfun$5;
class	scala/actors/Futures$$anonfun$5
NameAndType	serialVersionUID:J
Field	scala/actors/Futures$$anonfun$5.serialVersionUID:J
Asciz	apply;
Asciz	(Lscala/Tuple2;)Lscala/PartialFunction;;
Asciz	LineNumberTable;
Asciz	scala/Tuple2;
class	scala/Tuple2
Asciz	_2;
Asciz	()Ljava/lang/Object;;
NameAndType	_2:()Ljava/lang/Object;
Method	scala/Tuple2._2:()Ljava/lang/Object;
Asciz	scala/actors/Future;
class	scala/actors/Future
Asciz	inputChannel;
Asciz	()Lscala/actors/InputChannel;;
NameAndType	inputChannel:()Lscala/actors/InputChannel;
Method	scala/actors/Future.inputChannel:()Lscala/actors/InputChannel;
Asciz	scala/actors/Futures$$anonfun$5$$anonfun$6;
class	scala/actors/Futures$$anonfun$5$$anonfun$6
Asciz	<init>;
Asciz	(Lscala/actors/Futures$$anonfun$5;Lscala/Tuple2;Lscala/actors/InputChannel;)V;
NameAndType	"<init>":(Lscala/actors/Futures$$anonfun$5;Lscala/Tuple2;Lscala/actors/InputChannel;)V
Method	scala/actors/Futures$$anonfun$5$$anonfun$6."<init>":(Lscala/actors/Futures$$anonfun$5;Lscala/Tuple2;Lscala/actors/InputChannel;)V
Asciz	this;
Asciz	Lscala/actors/Futures$$anonfun$5;;
Asciz	p$1;
Asciz	Lscala/Tuple2;;
Asciz	FutCh$1;
Asciz	Lscala/actors/InputChannel;;
Asciz	singleCase;
Asciz	Lscala/PartialFunction;;
Asciz	LocalVariableTable;
Asciz	(Lscala/Tuple2<Ljava/lang/Integer;Lscala/actors/Future<Ljava/lang/Object;>;>;)Lscala/PartialFunction<Ljava/lang/Object;Lscala/Tuple2<Ljava/lang/Integer;Ljava/lang/Object;>;>;;
Asciz	Signature;
Asciz	(Ljava/lang/Object;)Ljava/lang/Object;;
NameAndType	apply:(Lscala/Tuple2;)Lscala/PartialFunction;
Method	scala/actors/Futures$$anonfun$5.apply:(Lscala/Tuple2;)Lscala/PartialFunction;
Asciz	v1;
Asciz	Ljava/lang/Object;;
Asciz	scala/runtime/AbstractFunction1;
class	scala/runtime/AbstractFunction1
NameAndType	"<init>":()V
Method	scala/runtime/AbstractFunction1."<init>":()V
Asciz	Scala;
Asciz	InnerClasses;
Asciz	scala/actors/Futures;
class	scala/actors/Futures
Asciz	$anonfun$5;
Asciz	$anonfun$6;
Asciz	java/io/Serializable;
class	java/io/Serializable

{
public static final long serialVersionUID;
  Signature: J

public static {};
  Signature: ()V
  Code:
   Stack=2, Locals=0, Args_size=0
	lconst_0
	putstatic	Field serialVersionUID:J
	return
  Labels:

public final scala.PartialFunction apply(scala.Tuple2);
  Signature: (Lscala/Tuple2;)Lscala/PartialFunction;
  Code:
   Stack=5, Locals=4, Args_size=2
	aload_1
	invokevirtual	Method scala/Tuple2._2:()Ljava/lang/Object;
	checkcast	class scala/actors/Future
	invokevirtual	Method scala/actors/Future.inputChannel:()Lscala/actors/InputChannel;
	astore_2
	new	class scala/actors/Futures$$anonfun$5$$anonfun$6
	dup
	aload_0
	aload_1
	aload_2
	invokespecial	Method scala/actors/Futures$$anonfun$5$$anonfun$6."<init>":(Lscala/actors/Futures$$anonfun$5;Lscala/Tuple2;Lscala/actors/InputChannel;)V
	astore_3
	aload_3
	areturn
  Labels:
  LocalVariableTable: 
   Start  Length  Slot  Name   Signature
   0      24      0    this       Lscala/actors/Futures$$anonfun$5;
   0      24      1    p$1       Lscala/Tuple2;
   11      12      2    FutCh$1       Lscala/actors/InputChannel;
   22      1      3    singleCase       Lscala/PartialFunction;

  Signature: length = 0x2
   00 2A 

public final java.lang.Object apply(java.lang.Object);
  Signature: (Ljava/lang/Object;)Ljava/lang/Object;
  Code:
   Stack=2, Locals=2, Args_size=2
	aload_0
	aload_1
	checkcast	class scala/Tuple2
	invokevirtual	Method apply:(Lscala/Tuple2;)Lscala/PartialFunction;
	areturn
  Labels:
  LocalVariableTable: 
   Start  Length  Slot  Name   Signature
   0      9      0    this       Lscala/actors/Futures$$anonfun$5;
   0      9      1    v1       Ljava/lang/Object;


public scala.actors.Futures$$anonfun$5();
  Signature: ()V
  Code:
   Stack=1, Locals=1, Args_size=1
	aload_0
	invokespecial	Method scala/runtime/AbstractFunction1."<init>":()V
	return
  Labels:

}

