Compiled from "IScheduler.scala"
public abstract class scala.actors.IScheduler$class extends java.lang.Object
  SourceFile: "IScheduler.scala"
  Scala: length = 0x
   
  minor version: 0
  major version: 49
  Constant pool:
const #1 = Asciz	SourceFile;
const #2 = Asciz	IScheduler.scala;
const #3 = Asciz	$init$;
const #4 = Asciz	(Lscala/actors/IScheduler;)V;
const #5 = Asciz	Code;
const #6 = Asciz	LineNumberTable;
const #7 = Asciz	$this;
const #8 = Asciz	Lscala/actors/IScheduler;;
const #9 = Asciz	LocalVariableTable;
const #10 = Asciz	printActorDump;
const #11 = Asciz	Deprecated;
const #12 = Asciz	onLockup;
const #13 = Asciz	(Lscala/actors/IScheduler;ILscala/Function0;)V;
const #14 = Asciz	millis;
const #15 = Asciz	I;
const #16 = Asciz	handler;
const #17 = Asciz	Lscala/Function0;;
const #18 = Asciz	(Lscala/actors/IScheduler;Lscala/Function0;)V;
const #19 = Asciz	tick;
const #20 = Asciz	(Lscala/actors/IScheduler;Lscala/actors/Actor;)V;
const #21 = Asciz	a;
const #22 = Asciz	Lscala/actors/Actor;;
const #23 = Asciz	executeFromActor;
const #24 = Asciz	(Lscala/actors/IScheduler;Ljava/lang/Runnable;)V;
const #25 = Asciz	scala/actors/IScheduler;
const #26 = class	#25;	//  scala/actors/IScheduler
const #27 = Asciz	execute;
const #28 = Asciz	(Ljava/lang/Runnable;)V;
const #29 = NameAndType	#27:#28;//  execute:(Ljava/lang/Runnable;)V
const #30 = InterfaceMethod	#26.#29;	//  scala/actors/IScheduler.execute:(Ljava/lang/Runnable;)V
const #31 = Asciz	task;
const #32 = Asciz	Ljava/lang/Runnable;;
const #33 = Asciz	Scala;
const #34 = Asciz	scala/actors/IScheduler$class;
const #35 = class	#34;	//  scala/actors/IScheduler$class
const #36 = Asciz	java/lang/Object;
const #37 = class	#36;	//  java/lang/Object

{
public static void $init$(scala.actors.IScheduler);
  Code:
   Stack=0, Locals=1, Args_size=1
   0:	return
  LineNumberTable: 
   line 23: 0

  LocalVariableTable: 
   Start  Length  Slot  Name   Signature
   0      1      0    $this       Lscala/actors/IScheduler;


public static void printActorDump(scala.actors.IScheduler);
  Code:
   Stack=0, Locals=1, Args_size=1
   0:	return
  LineNumberTable: 
   line 81: 0

  LocalVariableTable: 
   Start  Length  Slot  Name   Signature
   0      1      0    $this       Lscala/actors/IScheduler;

  Deprecated: true

public static void onLockup(scala.actors.IScheduler, int, scala.Function0);
  Code:
   Stack=0, Locals=3, Args_size=3
   0:	return
  LineNumberTable: 
   line 78: 0

  LocalVariableTable: 
   Start  Length  Slot  Name   Signature
   0      1      0    $this       Lscala/actors/IScheduler;
   0      1      1    millis       I
   0      1      2    handler       Lscala/Function0;

  Deprecated: true

public static void onLockup(scala.actors.IScheduler, scala.Function0);
  Code:
   Stack=0, Locals=2, Args_size=2
   0:	return
  LineNumberTable: 
   line 75: 0

  LocalVariableTable: 
   Start  Length  Slot  Name   Signature
   0      1      0    $this       Lscala/actors/IScheduler;
   0      1      1    handler       Lscala/Function0;

  Deprecated: true

public static void tick(scala.actors.IScheduler, scala.actors.Actor);
  Code:
   Stack=0, Locals=2, Args_size=2
   0:	return
  LineNumberTable: 
   line 72: 0

  LocalVariableTable: 
   Start  Length  Slot  Name   Signature
   0      1      0    $this       Lscala/actors/IScheduler;
   0      1      1    a       Lscala/actors/Actor;

  Deprecated: true

public static void executeFromActor(scala.actors.IScheduler, java.lang.Runnable);
  Code:
   Stack=2, Locals=2, Args_size=2
   0:	aload_0
   1:	aload_1
   2:	invokeinterface	#30,  2; //InterfaceMethod scala/actors/IScheduler.execute:(Ljava/lang/Runnable;)V
   7:	return
  LineNumberTable: 
   line 38: 0

  LocalVariableTable: 
   Start  Length  Slot  Name   Signature
   0      8      0    $this       Lscala/actors/IScheduler;
   0      8      1    task       Ljava/lang/Runnable;


}

