public class scala.actors.LinkedQueue extends java.lang.Object
  minor version: 0
  major version: 49
  Constant pool:
const #1 = Method	#2.#47;	//  java/lang/Object."<init>":()V
const #2 = class	#48;	//  java/lang/Object
const #3 = Field	#22.#49;	//  scala/actors/LinkedQueue.putLock_:Ljava/lang/Object;
const #4 = Field	#22.#50;	//  scala/actors/LinkedQueue.waitingForTake_:I
const #5 = class	#51;	//  scala/actors/LinkedNode
const #6 = Method	#5.#52;	//  scala/actors/LinkedNode."<init>":(Ljava/lang/Object;)V
const #7 = Field	#22.#53;	//  scala/actors/LinkedQueue.head_:Lscala/actors/LinkedNode;
const #8 = Field	#22.#54;	//  scala/actors/LinkedQueue.last_:Lscala/actors/LinkedNode;
const #9 = Field	#5.#55;	//  scala/actors/LinkedNode.next:Lscala/actors/LinkedNode;
const #10 = Method	#2.#56;	//  java/lang/Object.notify:()V
const #11 = Field	#5.#57;	//  scala/actors/LinkedNode.value:Ljava/lang/Object;
const #12 = class	#58;	//  java/lang/IllegalArgumentException
const #13 = Method	#12.#47;	//  java/lang/IllegalArgumentException."<init>":()V
const #14 = Method	#59.#60;	//  java/lang/Thread.interrupted:()Z
const #15 = class	#61;	//  java/lang/InterruptedException
const #16 = Method	#15.#47;	//  java/lang/InterruptedException."<init>":()V
const #17 = Method	#22.#62;	//  scala/actors/LinkedQueue.insert:(Ljava/lang/Object;)V
const #18 = Method	#22.#63;	//  scala/actors/LinkedQueue.extract:()Ljava/lang/Object;
const #19 = Method	#2.#64;	//  java/lang/Object.wait:()V
const #20 = Method	#65.#66;	//  java/lang/System.currentTimeMillis:()J
const #21 = Method	#2.#67;	//  java/lang/Object.wait:(J)V
const #22 = class	#68;	//  scala/actors/LinkedQueue
const #23 = Asciz	head_;
const #24 = Asciz	Lscala/actors/LinkedNode;;
const #25 = Asciz	putLock_;
const #26 = Asciz	Ljava/lang/Object;;
const #27 = Asciz	last_;
const #28 = Asciz	waitingForTake_;
const #29 = Asciz	I;
const #30 = Asciz	<init>;
const #31 = Asciz	()V;
const #32 = Asciz	Code;
const #33 = Asciz	insert;
const #34 = Asciz	(Ljava/lang/Object;)V;
const #35 = Asciz	extract;
const #36 = Asciz	()Ljava/lang/Object;;
const #37 = Asciz	put;
const #38 = Asciz	Exceptions;
const #39 = Asciz	offer;
const #40 = Asciz	(Ljava/lang/Object;J)Z;
const #41 = Asciz	take;
const #42 = Asciz	peek;
const #43 = Asciz	isEmpty;
const #44 = Asciz	()Z;
const #45 = Asciz	poll;
const #46 = Asciz	(J)Ljava/lang/Object;;
const #47 = NameAndType	#30:#31;//  "<init>":()V
const #48 = Asciz	java/lang/Object;
const #49 = NameAndType	#25:#26;//  putLock_:Ljava/lang/Object;
const #50 = NameAndType	#28:#29;//  waitingForTake_:I
const #51 = Asciz	scala/actors/LinkedNode;
const #52 = NameAndType	#30:#34;//  "<init>":(Ljava/lang/Object;)V
const #53 = NameAndType	#23:#24;//  head_:Lscala/actors/LinkedNode;
const #54 = NameAndType	#27:#24;//  last_:Lscala/actors/LinkedNode;
const #55 = NameAndType	#69:#24;//  next:Lscala/actors/LinkedNode;
const #56 = NameAndType	#70:#31;//  notify:()V
const #57 = NameAndType	#71:#26;//  value:Ljava/lang/Object;
const #58 = Asciz	java/lang/IllegalArgumentException;
const #59 = class	#72;	//  java/lang/Thread
const #60 = NameAndType	#73:#44;//  interrupted:()Z
const #61 = Asciz	java/lang/InterruptedException;
const #62 = NameAndType	#33:#34;//  insert:(Ljava/lang/Object;)V
const #63 = NameAndType	#35:#36;//  extract:()Ljava/lang/Object;
const #64 = NameAndType	#74:#31;//  wait:()V
const #65 = class	#75;	//  java/lang/System
const #66 = NameAndType	#76:#77;//  currentTimeMillis:()J
const #67 = NameAndType	#74:#78;//  wait:(J)V
const #68 = Asciz	scala/actors/LinkedQueue;
const #69 = Asciz	next;
const #70 = Asciz	notify;
const #71 = Asciz	value;
const #72 = Asciz	java/lang/Thread;
const #73 = Asciz	interrupted;
const #74 = Asciz	wait;
const #75 = Asciz	java/lang/System;
const #76 = Asciz	currentTimeMillis;
const #77 = Asciz	()J;
const #78 = Asciz	(J)V;

{
protected scala.actors.LinkedNode head_;

protected final java.lang.Object putLock_;

protected scala.actors.LinkedNode last_;

protected int waitingForTake_;

public scala.actors.LinkedQueue();
  Code:
   Stack=4, Locals=1, Args_size=1
   0:	aload_0
   1:	invokespecial	#1; //Method java/lang/Object."<init>":()V
   4:	aload_0
   5:	new	#2; //class java/lang/Object
   8:	dup
   9:	invokespecial	#1; //Method java/lang/Object."<init>":()V
   12:	putfield	#3; //Field putLock_:Ljava/lang/Object;
   15:	aload_0
   16:	iconst_0
   17:	putfield	#4; //Field waitingForTake_:I
   20:	aload_0
   21:	new	#5; //class scala/actors/LinkedNode
   24:	dup
   25:	aconst_null
   26:	invokespecial	#6; //Method scala/actors/LinkedNode."<init>":(Ljava/lang/Object;)V
   29:	putfield	#7; //Field head_:Lscala/actors/LinkedNode;
   32:	aload_0
   33:	aload_0
   34:	getfield	#7; //Field head_:Lscala/actors/LinkedNode;
   37:	putfield	#8; //Field last_:Lscala/actors/LinkedNode;
   40:	return

protected void insert(java.lang.Object);
  Code:
   Stack=3, Locals=7, Args_size=2
   0:	aload_0
   1:	getfield	#3; //Field putLock_:Ljava/lang/Object;
   4:	dup
   5:	astore_2
   6:	monitorenter
   7:	new	#5; //class scala/actors/LinkedNode
   10:	dup
   11:	aload_1
   12:	invokespecial	#6; //Method scala/actors/LinkedNode."<init>":(Ljava/lang/Object;)V
   15:	astore_3
   16:	aload_0
   17:	getfield	#8; //Field last_:Lscala/actors/LinkedNode;
   20:	dup
   21:	astore	4
   23:	monitorenter
   24:	aload_0
   25:	getfield	#8; //Field last_:Lscala/actors/LinkedNode;
   28:	aload_3
   29:	putfield	#9; //Field scala/actors/LinkedNode.next:Lscala/actors/LinkedNode;
   32:	aload_0
   33:	aload_3
   34:	putfield	#8; //Field last_:Lscala/actors/LinkedNode;
   37:	aload	4
   39:	monitorexit
   40:	goto	51
   43:	astore	5
   45:	aload	4
   47:	monitorexit
   48:	aload	5
   50:	athrow
   51:	aload_0
   52:	getfield	#4; //Field waitingForTake_:I
   55:	ifle	65
   58:	aload_0
   59:	getfield	#3; //Field putLock_:Ljava/lang/Object;
   62:	invokevirtual	#10; //Method java/lang/Object.notify:()V
   65:	aload_2
   66:	monitorexit
   67:	goto	77
   70:	astore	6
   72:	aload_2
   73:	monitorexit
   74:	aload	6
   76:	athrow
   77:	return
  Exception table:
   from   to  target type
    24    40    43   any
    43    48    43   any
     7    67    70   any
    70    74    70   any

protected synchronized java.lang.Object extract();
  Code:
   Stack=2, Locals=5, Args_size=1
   0:	aload_0
   1:	getfield	#7; //Field head_:Lscala/actors/LinkedNode;
   4:	dup
   5:	astore_1
   6:	monitorenter
   7:	aconst_null
   8:	astore_2
   9:	aload_0
   10:	getfield	#7; //Field head_:Lscala/actors/LinkedNode;
   13:	getfield	#9; //Field scala/actors/LinkedNode.next:Lscala/actors/LinkedNode;
   16:	astore_3
   17:	aload_3
   18:	ifnull	36
   21:	aload_3
   22:	getfield	#11; //Field scala/actors/LinkedNode.value:Ljava/lang/Object;
   25:	astore_2
   26:	aload_3
   27:	aconst_null
   28:	putfield	#11; //Field scala/actors/LinkedNode.value:Ljava/lang/Object;
   31:	aload_0
   32:	aload_3
   33:	putfield	#7; //Field head_:Lscala/actors/LinkedNode;
   36:	aload_2
   37:	aload_1
   38:	monitorexit
   39:	areturn
   40:	astore	4
   42:	aload_1
   43:	monitorexit
   44:	aload	4
   46:	athrow
  Exception table:
   from   to  target type
     7    39    40   any
    40    44    40   any

public void put(java.lang.Object)   throws java.lang.InterruptedException;
  Code:
   Stack=2, Locals=2, Args_size=2
   0:	aload_1
   1:	ifnonnull	12
   4:	new	#12; //class java/lang/IllegalArgumentException
   7:	dup
   8:	invokespecial	#13; //Method java/lang/IllegalArgumentException."<init>":()V
   11:	athrow
   12:	invokestatic	#14; //Method java/lang/Thread.interrupted:()Z
   15:	ifeq	26
   18:	new	#15; //class java/lang/InterruptedException
   21:	dup
   22:	invokespecial	#16; //Method java/lang/InterruptedException."<init>":()V
   25:	athrow
   26:	aload_0
   27:	aload_1
   28:	invokevirtual	#17; //Method insert:(Ljava/lang/Object;)V
   31:	return
  Exceptions: 
   throws java.lang.InterruptedException
public boolean offer(java.lang.Object, long)   throws java.lang.InterruptedException;
  Code:
   Stack=2, Locals=4, Args_size=3
   0:	aload_1
   1:	ifnonnull	12
   4:	new	#12; //class java/lang/IllegalArgumentException
   7:	dup
   8:	invokespecial	#13; //Method java/lang/IllegalArgumentException."<init>":()V
   11:	athrow
   12:	invokestatic	#14; //Method java/lang/Thread.interrupted:()Z
   15:	ifeq	26
   18:	new	#15; //class java/lang/InterruptedException
   21:	dup
   22:	invokespecial	#16; //Method java/lang/InterruptedException."<init>":()V
   25:	athrow
   26:	aload_0
   27:	aload_1
   28:	invokevirtual	#17; //Method insert:(Ljava/lang/Object;)V
   31:	iconst_1
   32:	ireturn
  Exceptions: 
   throws java.lang.InterruptedException
public java.lang.Object take()   throws java.lang.InterruptedException;
  Code:
   Stack=3, Locals=5, Args_size=1
   0:	invokestatic	#14; //Method java/lang/Thread.interrupted:()Z
   3:	ifeq	14
   6:	new	#15; //class java/lang/InterruptedException
   9:	dup
   10:	invokespecial	#16; //Method java/lang/InterruptedException."<init>":()V
   13:	athrow
   14:	aload_0
   15:	invokevirtual	#18; //Method extract:()Ljava/lang/Object;
   18:	astore_1
   19:	aload_1
   20:	ifnull	25
   23:	aload_1
   24:	areturn
   25:	aload_0
   26:	getfield	#3; //Field putLock_:Ljava/lang/Object;
   29:	dup
   30:	astore_2
   31:	monitorenter
   32:	aload_0
   33:	dup
   34:	getfield	#4; //Field waitingForTake_:I
   37:	iconst_1
   38:	iadd
   39:	putfield	#4; //Field waitingForTake_:I
   42:	aload_0
   43:	invokevirtual	#18; //Method extract:()Ljava/lang/Object;
   46:	astore_1
   47:	aload_1
   48:	ifnull	65
   51:	aload_0
   52:	dup
   53:	getfield	#4; //Field waitingForTake_:I
   56:	iconst_1
   57:	isub
   58:	putfield	#4; //Field waitingForTake_:I
   61:	aload_1
   62:	aload_2
   63:	monitorexit
   64:	areturn
   65:	aload_0
   66:	getfield	#3; //Field putLock_:Ljava/lang/Object;
   69:	invokevirtual	#19; //Method java/lang/Object.wait:()V
   72:	goto	42
   75:	astore_3
   76:	aload_0
   77:	dup
   78:	getfield	#4; //Field waitingForTake_:I
   81:	iconst_1
   82:	isub
   83:	putfield	#4; //Field waitingForTake_:I
   86:	aload_0
   87:	getfield	#3; //Field putLock_:Ljava/lang/Object;
   90:	invokevirtual	#10; //Method java/lang/Object.notify:()V
   93:	aload_3
   94:	athrow
   95:	astore	4
   97:	aload_2
   98:	monitorexit
   99:	aload	4
   101:	athrow
  Exception table:
   from   to  target type
    32    62    75   Class java/lang/InterruptedException

    65    75    75   Class java/lang/InterruptedException

    32    64    95   any
    65    99    95   any
  Exceptions: 
   throws java.lang.InterruptedException
public java.lang.Object peek();
  Code:
   Stack=2, Locals=4, Args_size=1
   0:	aload_0
   1:	getfield	#7; //Field head_:Lscala/actors/LinkedNode;
   4:	dup
   5:	astore_1
   6:	monitorenter
   7:	aload_0
   8:	getfield	#7; //Field head_:Lscala/actors/LinkedNode;
   11:	getfield	#9; //Field scala/actors/LinkedNode.next:Lscala/actors/LinkedNode;
   14:	astore_2
   15:	aload_2
   16:	ifnull	26
   19:	aload_2
   20:	getfield	#11; //Field scala/actors/LinkedNode.value:Ljava/lang/Object;
   23:	aload_1
   24:	monitorexit
   25:	areturn
   26:	aconst_null
   27:	aload_1
   28:	monitorexit
   29:	areturn
   30:	astore_3
   31:	aload_1
   32:	monitorexit
   33:	aload_3
   34:	athrow
  Exception table:
   from   to  target type
     7    25    30   any
    26    29    30   any
    30    33    30   any

public boolean isEmpty();
  Code:
   Stack=2, Locals=3, Args_size=1
   0:	aload_0
   1:	getfield	#7; //Field head_:Lscala/actors/LinkedNode;
   4:	dup
   5:	astore_1
   6:	monitorenter
   7:	aload_0
   8:	getfield	#7; //Field head_:Lscala/actors/LinkedNode;
   11:	getfield	#9; //Field scala/actors/LinkedNode.next:Lscala/actors/LinkedNode;
   14:	ifnonnull	21
   17:	iconst_1
   18:	goto	22
   21:	iconst_0
   22:	aload_1
   23:	monitorexit
   24:	ireturn
   25:	astore_2
   26:	aload_1
   27:	monitorexit
   28:	aload_2
   29:	athrow
  Exception table:
   from   to  target type
     7    24    25   any
    25    28    25   any

public java.lang.Object poll(long)   throws java.lang.InterruptedException;
  Code:
   Stack=6, Locals=10, Args_size=2
   0:	invokestatic	#14; //Method java/lang/Thread.interrupted:()Z
   3:	ifeq	14
   6:	new	#15; //class java/lang/InterruptedException
   9:	dup
   10:	invokespecial	#16; //Method java/lang/InterruptedException."<init>":()V
   13:	athrow
   14:	aload_0
   15:	invokevirtual	#18; //Method extract:()Ljava/lang/Object;
   18:	astore_3
   19:	aload_3
   20:	ifnull	25
   23:	aload_3
   24:	areturn
   25:	aload_0
   26:	getfield	#3; //Field putLock_:Ljava/lang/Object;
   29:	dup
   30:	astore	4
   32:	monitorenter
   33:	lload_1
   34:	lstore	5
   36:	lload_1
   37:	lconst_0
   38:	lcmp
   39:	ifgt	46
   42:	lconst_0
   43:	goto	49
   46:	invokestatic	#20; //Method java/lang/System.currentTimeMillis:()J
   49:	lstore	7
   51:	aload_0
   52:	dup
   53:	getfield	#4; //Field waitingForTake_:I
   56:	iconst_1
   57:	iadd
   58:	putfield	#4; //Field waitingForTake_:I
   61:	aload_0
   62:	invokevirtual	#18; //Method extract:()Ljava/lang/Object;
   65:	astore_3
   66:	aload_3
   67:	ifnonnull	77
   70:	lload	5
   72:	lconst_0
   73:	lcmp
   74:	ifgt	92
   77:	aload_0
   78:	dup
   79:	getfield	#4; //Field waitingForTake_:I
   82:	iconst_1
   83:	isub
   84:	putfield	#4; //Field waitingForTake_:I
   87:	aload_3
   88:	aload	4
   90:	monitorexit
   91:	areturn
   92:	aload_0
   93:	getfield	#3; //Field putLock_:Ljava/lang/Object;
   96:	lload	5
   98:	invokevirtual	#21; //Method java/lang/Object.wait:(J)V
   101:	lload_1
   102:	invokestatic	#20; //Method java/lang/System.currentTimeMillis:()J
   105:	lload	7
   107:	lsub
   108:	lsub
   109:	lstore	5
   111:	goto	61
   114:	astore	5
   116:	aload_0
   117:	dup
   118:	getfield	#4; //Field waitingForTake_:I
   121:	iconst_1
   122:	isub
   123:	putfield	#4; //Field waitingForTake_:I
   126:	aload_0
   127:	getfield	#3; //Field putLock_:Ljava/lang/Object;
   130:	invokevirtual	#10; //Method java/lang/Object.notify:()V
   133:	aload	5
   135:	athrow
   136:	astore	9
   138:	aload	4
   140:	monitorexit
   141:	aload	9
   143:	athrow
  Exception table:
   from   to  target type
    33    88   114   Class java/lang/InterruptedException

    92   114   114   Class java/lang/InterruptedException

    33    91   136   any
    92   141   136   any
  Exceptions: 
   throws java.lang.InterruptedException
}

