public class scala.actors.LinkedNode extends java.lang.Object
  minor version: 0
  major version: 49
  Constant pool:
const #1 = Method	#5.#15;	//  java/lang/Object."<init>":()V
const #2 = Field	#4.#16;	//  scala/actors/LinkedNode.value:Ljava/lang/Object;
const #3 = Field	#4.#17;	//  scala/actors/LinkedNode.next:Lscala/actors/LinkedNode;
const #4 = class	#18;	//  scala/actors/LinkedNode
const #5 = class	#19;	//  java/lang/Object
const #6 = Asciz	value;
const #7 = Asciz	Ljava/lang/Object;;
const #8 = Asciz	next;
const #9 = Asciz	Lscala/actors/LinkedNode;;
const #10 = Asciz	<init>;
const #11 = Asciz	()V;
const #12 = Asciz	Code;
const #13 = Asciz	(Ljava/lang/Object;)V;
const #14 = Asciz	(Ljava/lang/Object;Lscala/actors/LinkedNode;)V;
const #15 = NameAndType	#10:#11;//  "<init>":()V
const #16 = NameAndType	#6:#7;//  value:Ljava/lang/Object;
const #17 = NameAndType	#8:#9;//  next:Lscala/actors/LinkedNode;
const #18 = Asciz	scala/actors/LinkedNode;
const #19 = Asciz	java/lang/Object;

{
public java.lang.Object value;

public scala.actors.LinkedNode next;

public scala.actors.LinkedNode();
  Code:
   Stack=1, Locals=1, Args_size=1
   0:	aload_0
   1:	invokespecial	#1; //Method java/lang/Object."<init>":()V
   4:	return

public scala.actors.LinkedNode(java.lang.Object);
  Code:
   Stack=2, Locals=2, Args_size=2
   0:	aload_0
   1:	invokespecial	#1; //Method java/lang/Object."<init>":()V
   4:	aload_0
   5:	aload_1
   6:	putfield	#2; //Field value:Ljava/lang/Object;
   9:	return

public scala.actors.LinkedNode(java.lang.Object, scala.actors.LinkedNode);
  Code:
   Stack=2, Locals=3, Args_size=3
   0:	aload_0
   1:	invokespecial	#1; //Method java/lang/Object."<init>":()V
   4:	aload_0
   5:	aload_1
   6:	putfield	#2; //Field value:Ljava/lang/Object;
   9:	aload_0
   10:	aload_2
   11:	putfield	#3; //Field next:Lscala/actors/LinkedNode;
   14:	return

}

