Compiled from "Debug.scala"
public class scala.actors.Logger extends java.lang.Object implements scala.ScalaObject
  SourceFile: "Debug.scala"
  ScalaSig: length = 0x3
   05 00 00 
  RuntimeVisibleAnnotations: length = 0xB
   00 01 00 62 00 01 00 63 73 00 64 
  minor version: 0
  major version: 49
  Constant pool:
Asciz	SourceFile;
Asciz	Debug.scala;
Asciz	lev;
Asciz	I;
Asciz	tagString;
Asciz	Ljava/lang/String;;
Asciz	()I;
Asciz	Code;
Asciz	LineNumberTable;
Asciz	scala/actors/Logger;
class	scala/actors/Logger
NameAndType	lev:I
Field	scala/actors/Logger.lev:I
Asciz	lev_$eq;
Asciz	(I)V;
Asciz	level;
NameAndType	lev:()I
Method	scala/actors/Logger.lev:()I
Asciz	level_$eq;
NameAndType	lev_$eq:(I)V
Method	scala/actors/Logger.lev_$eq:(I)V
Asciz	this;
Asciz	Lscala/actors/Logger;;
Asciz	LocalVariableTable;
Asciz	()Ljava/lang/String;;
NameAndType	tagString:Ljava/lang/String;
Field	scala/actors/Logger.tagString:Ljava/lang/String;
Asciz	info;
Asciz	(Ljava/lang/String;)V;
Asciz	java/lang/System;
class	java/lang/System
Asciz	out;
Asciz	Ljava/io/PrintStream;;
NameAndType	out:Ljava/io/PrintStream;
Field	java/lang/System.out:Ljava/io/PrintStream;
Asciz	scala/collection/mutable/StringBuilder;
class	scala/collection/mutable/StringBuilder
Asciz	<init>;
Asciz	()V;
NameAndType	"<init>":()V
Method	scala/collection/mutable/StringBuilder."<init>":()V
Asciz	Info;
String	Info
Asciz	append;
Asciz	(Ljava/lang/Object;)Lscala/collection/mutable/StringBuilder;;
NameAndType	append:(Ljava/lang/Object;)Lscala/collection/mutable/StringBuilder;
Method	scala/collection/mutable/StringBuilder.append:(Ljava/lang/Object;)Lscala/collection/mutable/StringBuilder;
NameAndType	tagString:()Ljava/lang/String;
Method	scala/actors/Logger.tagString:()Ljava/lang/String;
Asciz	: ;
String	: 
Asciz	toString;
NameAndType	toString:()Ljava/lang/String;
Method	scala/collection/mutable/StringBuilder.toString:()Ljava/lang/String;
Asciz	java/io/PrintStream;
class	java/io/PrintStream
Asciz	println;
NameAndType	println:(Ljava/lang/String;)V
Method	java/io/PrintStream.println:(Ljava/lang/String;)V
Asciz	s;
Asciz	warning;
Asciz	err;
NameAndType	err:Ljava/io/PrintStream;
Field	java/lang/System.err:Ljava/io/PrintStream;
Asciz	Warning;
String	Warning
Asciz	error;
Asciz	Error;
String	Error
Asciz	doInfo;
Asciz	(Lscala/Function0;)V;
Asciz	scala/Function0;
class	scala/Function0
Asciz	apply$mcV$sp;
NameAndType	apply$mcV$sp:()V
InterfaceMethod	scala/Function0.apply$mcV$sp:()V
Asciz	b;
Asciz	Lscala/Function0;;
Asciz	(Lscala/Function0<Ljava/lang/Object;>;)V;
Asciz	Signature;
Asciz	doWarning;
Asciz	doError;
Asciz	java/lang/Object;
class	java/lang/Object
Method	java/lang/Object."<init>":()V
Asciz	;
String	
Asciz	equals;
Asciz	(Ljava/lang/Object;)Z;
NameAndType	equals:(Ljava/lang/Object;)Z
Method	java/lang/Object.equals:(Ljava/lang/Object;)Z
Asciz	 [;
String	 [
Asciz	];
String	]
Asciz	tag;
Asciz	ScalaSig;
Asciz	Lscala/reflect/ScalaSignature;;
Asciz	bytes;
Asciz	u3\"\tA\r1{wmZ3s\tA!bGR|'o)1oY1mCNaB!iQ\"A)Y7b]TDU4-\t1qJ6fGR\"E\tI!AM\r\1PE*,7\r\t)\t)A-A/Y4AqC!aI!!\rAX\rZ3g\tYBDTiJLgn3AQA}\taP5oSRtDC#!\t\t!D!R1!1A\n\n1\3w+1C\t(\tACAAJ]RDqAA%1&AmKZ|F%Z91zC\t.\tqCAV]&$b*\rAJq\nBA&a%mKZ\"\t)!7fmd\"\t9!7fmdwJ3r)\taC%kaC;\tIBQwm;sS:<W#!iBA\ny)AyQA/Y4TiJLgn\tA\"\t%tgmY\rCQ!AY\ta\r!\taRoh.8h)\ta\nCEaCK1*AfeJ|'-\")A)a-!)a\nC1Am\%oM>$\")\t\rEkE1Sc\tTY%A\ty\tLh.Y7f}!)aC/IAm\,be:LgnYaCa!U+\".\tYa3pJxNYqCa!U-;
Asciz	RuntimeVisibleAnnotations;
Asciz	scala/ScalaObject;
class	scala/ScalaObject

{
private int lev;
  Signature: I

private final java.lang.String tagString;
  Signature: Ljava/lang/String;

private int lev();
  Signature: ()I
  Code:
   Stack=1, Locals=1, Args_size=1
	aload_0
	getfield	Field lev:I
	ireturn
  Labels:

private void lev_$eq(int);
  Signature: (I)V
  Code:
   Stack=2, Locals=2, Args_size=2
	aload_0
	iload_1
	putfield	Field lev:I
	return
  Labels:

public int level();
  Signature: ()I
  Code:
   Stack=1, Locals=1, Args_size=1
	aload_0
	invokespecial	Method lev:()I
	ireturn
  Labels:

public void level_$eq(int);
  Signature: (I)V
  Code:
   Stack=2, Locals=2, Args_size=2
	aload_0
	iload_1
	invokespecial	Method lev_$eq:(I)V
	return
  Labels:
  LocalVariableTable: 
   Start  Length  Slot  Name   Signature
   0      6      0    this       Lscala/actors/Logger;
   0      6      1    lev       I


private java.lang.String tagString();
  Signature: ()Ljava/lang/String;
  Code:
   Stack=1, Locals=1, Args_size=1
	aload_0
	getfield	Field tagString:Ljava/lang/String;
	areturn
  Labels:

public void info(java.lang.String);
  Signature: (Ljava/lang/String;)V
  Code:
   Stack=3, Locals=2, Args_size=2
	aload_0
	invokespecial	Method lev:()I
	iconst_2
	if_icmple	l1 // return
	getstatic	Field java/lang/System.out:Ljava/io/PrintStream;
	new	class scala/collection/mutable/StringBuilder
	dup
	invokespecial	Method scala/collection/mutable/StringBuilder."<init>":()V
	ldc	String Info
	invokevirtual	Method scala/collection/mutable/StringBuilder.append:(Ljava/lang/Object;)Lscala/collection/mutable/StringBuilder;
	aload_0
	invokespecial	Method tagString:()Ljava/lang/String;
	invokevirtual	Method scala/collection/mutable/StringBuilder.append:(Ljava/lang/Object;)Lscala/collection/mutable/StringBuilder;
	ldc	String : 
	invokevirtual	Method scala/collection/mutable/StringBuilder.append:(Ljava/lang/Object;)Lscala/collection/mutable/StringBuilder;
	aload_1
	invokevirtual	Method scala/collection/mutable/StringBuilder.append:(Ljava/lang/Object;)Lscala/collection/mutable/StringBuilder;
	invokevirtual	Method scala/collection/mutable/StringBuilder.toString:()Ljava/lang/String;
	invokevirtual	Method java/io/PrintStream.println:(Ljava/lang/String;)V
l1	return
  Labels:
   	l1 = 45 // return
  LocalVariableTable: 
   Start  Length  Slot  Name   Signature
   0      46      0    this       Lscala/actors/Logger;
   0      46      1    s       Ljava/lang/String;


public void warning(java.lang.String);
  Signature: (Ljava/lang/String;)V
  Code:
   Stack=3, Locals=2, Args_size=2
	aload_0
	invokespecial	Method lev:()I
	iconst_1
	if_icmple	l1 // return
	getstatic	Field java/lang/System.err:Ljava/io/PrintStream;
	new	class scala/collection/mutable/StringBuilder
	dup
	invokespecial	Method scala/collection/mutable/StringBuilder."<init>":()V
	ldc	String Warning
	invokevirtual	Method scala/collection/mutable/StringBuilder.append:(Ljava/lang/Object;)Lscala/collection/mutable/StringBuilder;
	aload_0
	invokespecial	Method tagString:()Ljava/lang/String;
	invokevirtual	Method scala/collection/mutable/StringBuilder.append:(Ljava/lang/Object;)Lscala/collection/mutable/StringBuilder;
	ldc	String : 
	invokevirtual	Method scala/collection/mutable/StringBuilder.append:(Ljava/lang/Object;)Lscala/collection/mutable/StringBuilder;
	aload_1
	invokevirtual	Method scala/collection/mutable/StringBuilder.append:(Ljava/lang/Object;)Lscala/collection/mutable/StringBuilder;
	invokevirtual	Method scala/collection/mutable/StringBuilder.toString:()Ljava/lang/String;
	invokevirtual	Method java/io/PrintStream.println:(Ljava/lang/String;)V
l1	return
  Labels:
   	l1 = 45 // return
  LocalVariableTable: 
   Start  Length  Slot  Name   Signature
   0      46      0    this       Lscala/actors/Logger;
   0      46      1    s       Ljava/lang/String;


public void error(java.lang.String);
  Signature: (Ljava/lang/String;)V
  Code:
   Stack=3, Locals=2, Args_size=2
	aload_0
	invokespecial	Method lev:()I
	iconst_0
	if_icmple	l1 // return
	getstatic	Field java/lang/System.err:Ljava/io/PrintStream;
	new	class scala/collection/mutable/StringBuilder
	dup
	invokespecial	Method scala/collection/mutable/StringBuilder."<init>":()V
	ldc	String Error
	invokevirtual	Method scala/collection/mutable/StringBuilder.append:(Ljava/lang/Object;)Lscala/collection/mutable/StringBuilder;
	aload_0
	invokespecial	Method tagString:()Ljava/lang/String;
	invokevirtual	Method scala/collection/mutable/StringBuilder.append:(Ljava/lang/Object;)Lscala/collection/mutable/StringBuilder;
	ldc	String : 
	invokevirtual	Method scala/collection/mutable/StringBuilder.append:(Ljava/lang/Object;)Lscala/collection/mutable/StringBuilder;
	aload_1
	invokevirtual	Method scala/collection/mutable/StringBuilder.append:(Ljava/lang/Object;)Lscala/collection/mutable/StringBuilder;
	invokevirtual	Method scala/collection/mutable/StringBuilder.toString:()Ljava/lang/String;
	invokevirtual	Method java/io/PrintStream.println:(Ljava/lang/String;)V
l1	return
  Labels:
   	l1 = 45 // return
  LocalVariableTable: 
   Start  Length  Slot  Name   Signature
   0      46      0    this       Lscala/actors/Logger;
   0      46      1    s       Ljava/lang/String;


public void doInfo(scala.Function0);
  Signature: (Lscala/Function0;)V
  Code:
   Stack=2, Locals=2, Args_size=2
	aload_0
	invokespecial	Method lev:()I
	iconst_2
	if_icmple	l1 // return
	aload_1
	invokeinterface	InterfaceMethod scala/Function0.apply$mcV$sp:()V
l1	return
  Labels:
   	l1 = 14 // return
  LocalVariableTable: 
   Start  Length  Slot  Name   Signature
   0      15      0    this       Lscala/actors/Logger;
   0      15      1    b       Lscala/Function0;

  Signature: length = 0x2
   00 4F 

public void doWarning(scala.Function0);
  Signature: (Lscala/Function0;)V
  Code:
   Stack=2, Locals=2, Args_size=2
	aload_0
	invokespecial	Method lev:()I
	iconst_1
	if_icmple	l1 // return
	aload_1
	invokeinterface	InterfaceMethod scala/Function0.apply$mcV$sp:()V
l1	return
  Labels:
   	l1 = 14 // return
  LocalVariableTable: 
   Start  Length  Slot  Name   Signature
   0      15      0    this       Lscala/actors/Logger;
   0      15      1    b       Lscala/Function0;

  Signature: length = 0x2
   00 4F 

public void doError(scala.Function0);
  Signature: (Lscala/Function0;)V
  Code:
   Stack=2, Locals=2, Args_size=2
	aload_0
	invokespecial	Method lev:()I
	iconst_0
	if_icmple	l1 // return
	aload_1
	invokeinterface	InterfaceMethod scala/Function0.apply$mcV$sp:()V
l1	return
  Labels:
   	l1 = 14 // return
  LocalVariableTable: 
   Start  Length  Slot  Name   Signature
   0      15      0    this       Lscala/actors/Logger;
   0      15      1    b       Lscala/Function0;

  Signature: length = 0x2
   00 4F 

public scala.actors.Logger(java.lang.String);
  Signature: (Ljava/lang/String;)V
  Code:
   Stack=3, Locals=3, Args_size=2
	aload_0
	invokespecial	Method java/lang/Object."<init>":()V
	aload_0
	iconst_2
	putfield	Field lev:I
	aload_0
	aload_1
	ldc	String 
	astore_2
	dup
	ifnonnull	l1 // aload_2
	pop
	aload_2
	ifnull	l2 // ldc
	goto	l3 // new
l1	aload_2
	invokevirtual	Method java/lang/Object.equals:(Ljava/lang/Object;)Z
	ifeq	l3 // new
l2	ldc	String 
	goto	l4 // putfield
l3	new	class scala/collection/mutable/StringBuilder
	dup
	invokespecial	Method scala/collection/mutable/StringBuilder."<init>":()V
	ldc	String  [
	invokevirtual	Method scala/collection/mutable/StringBuilder.append:(Ljava/lang/Object;)Lscala/collection/mutable/StringBuilder;
	aload_1
	invokevirtual	Method scala/collection/mutable/StringBuilder.append:(Ljava/lang/Object;)Lscala/collection/mutable/StringBuilder;
	ldc	String ]
	invokevirtual	Method scala/collection/mutable/StringBuilder.append:(Ljava/lang/Object;)Lscala/collection/mutable/StringBuilder;
	invokevirtual	Method scala/collection/mutable/StringBuilder.toString:()Ljava/lang/String;
l4	putfield	Field tagString:Ljava/lang/String;
	return
  Labels:
   	l1 = 26 // aload_2
   	l2 = 33 // ldc
   	l3 = 38 // new
   	l4 = 62 // putfield
  LocalVariableTable: 
   Start  Length  Slot  Name   Signature
   0      66      0    this       Lscala/actors/Logger;
   0      66      1    tag       Ljava/lang/String;


}

