Compiled from "MessageQueue.scala"
public class scala.actors.MessageQueueElement extends java.lang.Object implements scala.ScalaObject,java.io.Serializable
  SourceFile: "MessageQueue.scala"
  ScalaSig: length = 0x231
   05 00 4E 06 08 01 02 FFFFFF84 FFFFFF80 FFFFFF80 FFFFFF80 00 07 02 13 4D
   65 73 73 61 67 65 51 75 65 75 65 45 6C 65 6D 65
   6E 74 0A 02 03 04 01 06 61 63 74 6F 72 73 0A 01
   05 01 05 73 63 61 6C 61 03 00 13 03 00 08 10 10
   02 09 0E 0D 01 0A 0A 02 0B 0C 01 04 6C 61 6E 67
   0A 01 0D 01 04 6A 61 76 61 09 02 0F 0A 02 06 4F
   62 6A 65 63 74 10 02 11 12 0D 01 04 09 02 13 04
   02 0B 53 63 61 6C 61 4F 62 6A 65 63 74 08 08 15
   00 FFFFFF82 FFFFFFC2 FFFFFF80 FFFFFF84 00 16 01 03 6D 73 67 15 01 17 10
   02 11 18 09 02 19 04 02 03 41 6E 79 08 08 1B 00
   FFFFFF82 FFFFFF80 FFFFFFA0 FFFFFF80 04 17 01 04 6D 73 67 20 08 08 1D 00
   FFFFFF82 FFFFFFC2 FFFFFF80 FFFFFF84 00 1E 01 07 73 65 73 73 69 6F 6E 15
   01 1F 10 03 20 21 17 0D 01 02 09 02 22 02 02 0D
   4F 75 74 70 75 74 43 68 61 6E 6E 65 6C 08 08 24
   00 FFFFFF82 FFFFFF80 FFFFFFA0 FFFFFF80 04 1F 01 08 73 65 73 73 69 6F 6E
   20 08 08 26 00 FFFFFF82 FFFFFFC0 FFFFFF80 FFFFFF84 00 27 01 04 6E 65 78
   74 15 01 28 10 02 20 00 08 08 2A 00 FFFFFF82 FFFFFFC0 FFFFFF80 FFFFFF84
   00 2B 01 08 6E 65 78 74 5F 24 65 71 14 02 2C 2F
   10 02 11 2D 09 02 2E 04 02 04 55 6E 69 74 08 07
   30 29 FFFFFF81 FFFFFF80 FFFFFFC0 00 28 01 03 78 24 31 08 08 32 00
   FFFFFF82 FFFFFF80 FFFFFFA0 FFFFFFA0 04 28 01 05 6E 65 78 74 20 08 05 34
   00 FFFFFF84 00 35 01 06 3C 69 6E 69 74 3E 14 04 28 36
   37 38 08 05 15 33 FFFFFFC0 00 17 08 05 1D 33 FFFFFFC0 00 1F
   08 05 26 33 FFFFFFC0 00 28 08 05 34 00 FFFFFF84 00 3A 14 01
   28 08 05 34 00 FFFFFF84 00 3C 14 03 28 3D 3E 08 05 15
   3B FFFFFFC0 00 17 08 05 1D 3B FFFFFFC0 00 1F 28 03 00 40 43
   10 02 11 41 09 02 42 04 02 0A 64 65 70 72 65 63
   61 74 65 64 21 01 44 01 35 74 68 69 73 20 63 6C
   61 73 73 20 69 73 20 67 6F 69 6E 67 20 74 6F 20
   62 65 20 72 65 6D 6F 76 65 64 20 69 6E 20 61 20
   66 75 74 75 72 65 20 72 65 6C 65 61 73 65 28 03
   00 46 49 10 02 11 47 09 02 48 04 02 10 53 65 72
   69 61 6C 56 65 72 73 69 6F 6E 55 49 44 1E 08 62
   FFFFFFDE FFFFFF85 FFFFFFD4 70 FFFFFFE0 FFFFFFAF 59 28 02 00 4B 10 02 11 4C 09
   02 4D 04 02 0C 73 65 72 69 61 6C 69 7A 61 62 6C
   65 
  minor version: 0
  major version: 49
  Constant pool:
const #1 = Asciz	SourceFile;
const #2 = Asciz	MessageQueue.scala;
const #3 = Asciz	<clinit>;
const #4 = Asciz	()V;
const #5 = Asciz	Code;
const #6 = Asciz	serialVersionUID;
const #7 = Asciz	J;
const #8 = long	7124278808020037465l;
const #10 = Asciz	scala/actors/MessageQueueElement;
const #11 = class	#10;	//  scala/actors/MessageQueueElement
const #12 = NameAndType	#6:#7;//  serialVersionUID:J
const #13 = Field	#11.#12;	//  scala/actors/MessageQueueElement.serialVersionUID:J
const #14 = Asciz	next;
const #15 = Asciz	Lscala/actors/MessageQueueElement;;
const #16 = Asciz	session;
const #17 = Asciz	Lscala/actors/OutputChannel;;
const #18 = Asciz	Lscala/actors/OutputChannel<Ljava/lang/Object;>;;
const #19 = Asciz	Signature;
const #20 = Asciz	msg;
const #21 = Asciz	Ljava/lang/Object;;
const #22 = Asciz	<init>;
const #23 = Asciz	(Ljava/lang/Object;Lscala/actors/OutputChannel;Lscala/actors/MessageQueueElement;)V;
const #24 = Asciz	LineNumberTable;
const #25 = NameAndType	#20:#21;//  msg:Ljava/lang/Object;
const #26 = Field	#11.#25;	//  scala/actors/MessageQueueElement.msg:Ljava/lang/Object;
const #27 = NameAndType	#16:#17;//  session:Lscala/actors/OutputChannel;
const #28 = Field	#11.#27;	//  scala/actors/MessageQueueElement.session:Lscala/actors/OutputChannel;
const #29 = NameAndType	#14:#15;//  next:Lscala/actors/MessageQueueElement;
const #30 = Field	#11.#29;	//  scala/actors/MessageQueueElement.next:Lscala/actors/MessageQueueElement;
const #31 = Asciz	java/lang/Object;
const #32 = class	#31;	//  java/lang/Object
const #33 = NameAndType	#22:#4;//  "<init>":()V
const #34 = Method	#32.#33;	//  java/lang/Object."<init>":()V
const #35 = Asciz	this;
const #36 = Asciz	LocalVariableTable;
const #37 = Asciz	(Ljava/lang/Object;Lscala/actors/OutputChannel<Ljava/lang/Object;>;Lscala/actors/MessageQueueElement;)V;
const #38 = Asciz	(Ljava/lang/Object;Lscala/actors/OutputChannel;)V;
const #39 = NameAndType	#22:#23;//  "<init>":(Ljava/lang/Object;Lscala/actors/OutputChannel;Lscala/actors/MessageQueueElement;)V
const #40 = Method	#11.#39;	//  scala/actors/MessageQueueElement."<init>":(Ljava/lang/Object;Lscala/actors/OutputChannel;Lscala/actors/MessageQueueElement;)V
const #41 = Asciz	(Ljava/lang/Object;Lscala/actors/OutputChannel<Ljava/lang/Object;>;)V;
const #42 = Asciz	next_$eq;
const #43 = Asciz	(Lscala/actors/MessageQueueElement;)V;
const #44 = Asciz	()Lscala/actors/MessageQueueElement;;
const #45 = Asciz	()Lscala/actors/OutputChannel;;
const #46 = Asciz	()Lscala/actors/OutputChannel<Ljava/lang/Object;>;;
const #47 = Asciz	()Ljava/lang/Object;;
const #48 = Asciz	ScalaSig;
const #49 = Asciz	scala/ScalaObject;
const #50 = class	#49;	//  scala/ScalaObject
const #51 = Asciz	java/io/Serializable;
const #52 = class	#51;	//  java/io/Serializable

{
public static final long serialVersionUID;

public static {};
  Code:
   Stack=2, Locals=0, Args_size=0
   0:	ldc2_w	#8; //long 7124278808020037465l
   3:	putstatic	#13; //Field serialVersionUID:J
   6:	return

public scala.actors.MessageQueueElement(java.lang.Object, scala.actors.OutputChannel, scala.actors.MessageQueueElement);
  Code:
   Stack=2, Locals=4, Args_size=4
   0:	aload_0
   1:	aload_1
   2:	putfield	#26; //Field msg:Ljava/lang/Object;
   5:	aload_0
   6:	aload_2
   7:	putfield	#28; //Field session:Lscala/actors/OutputChannel;
   10:	aload_0
   11:	aload_3
   12:	putfield	#30; //Field next:Lscala/actors/MessageQueueElement;
   15:	aload_0
   16:	invokespecial	#34; //Method java/lang/Object."<init>":()V
   19:	return
  LineNumberTable: 
   line 21: 0

  LocalVariableTable: 
   Start  Length  Slot  Name   Signature
   0      20      0    this       Lscala/actors/MessageQueueElement;
   0      20      1    msg       Ljava/lang/Object;
   0      20      2    session       Lscala/actors/OutputChannel;
   0      20      3    next       Lscala/actors/MessageQueueElement;

  Signature: length = 0x2
   00 25 

public scala.actors.MessageQueueElement(java.lang.Object, scala.actors.OutputChannel);
  Code:
   Stack=4, Locals=3, Args_size=3
   0:	aload_0
   1:	aload_1
   2:	aload_2
   3:	aconst_null
   4:	invokespecial	#40; //Method "<init>":(Ljava/lang/Object;Lscala/actors/OutputChannel;Lscala/actors/MessageQueueElement;)V
   7:	return
  LineNumberTable: 
   line 23: 0

  LocalVariableTable: 
   Start  Length  Slot  Name   Signature
   0      8      0    this       Lscala/actors/MessageQueueElement;
   0      8      1    msg       Ljava/lang/Object;
   0      8      2    session       Lscala/actors/OutputChannel;

  Signature: length = 0x2
   00 29 

public scala.actors.MessageQueueElement();
  Code:
   Stack=4, Locals=1, Args_size=1
   0:	aload_0
   1:	aconst_null
   2:	aconst_null
   3:	aconst_null
   4:	invokespecial	#40; //Method "<init>":(Ljava/lang/Object;Lscala/actors/OutputChannel;Lscala/actors/MessageQueueElement;)V
   7:	return
  LineNumberTable: 
   line 22: 0


public void next_$eq(scala.actors.MessageQueueElement);
  Code:
   Stack=2, Locals=2, Args_size=2
   0:	aload_0
   1:	aload_1
   2:	putfield	#30; //Field next:Lscala/actors/MessageQueueElement;
   5:	return
  LineNumberTable: 
   line 21: 0


public scala.actors.MessageQueueElement next();
  Code:
   Stack=1, Locals=1, Args_size=1
   0:	aload_0
   1:	getfield	#30; //Field next:Lscala/actors/MessageQueueElement;
   4:	areturn
  LineNumberTable: 
   line 21: 0


public scala.actors.OutputChannel session();
  Code:
   Stack=1, Locals=1, Args_size=1
   0:	aload_0
   1:	getfield	#28; //Field session:Lscala/actors/OutputChannel;
   4:	areturn
  LineNumberTable: 
   line 21: 0

  Signature: length = 0x2
   00 2E 

public java.lang.Object msg();
  Code:
   Stack=1, Locals=1, Args_size=1
   0:	aload_0
   1:	getfield	#26; //Field msg:Ljava/lang/Object;
   4:	areturn
  LineNumberTable: 
   line 21: 0


}

