Compiled from "MessageQueue.scala"
public final class scala.actors.MessageQueueTracer$ extends java.lang.Object implements scala.ScalaObject
  SourceFile: "MessageQueue.scala"
  Scala: length = 0x
   
  minor version: 0
  major version: 49
  Constant pool:
const #1 = Asciz	SourceFile;
const #2 = Asciz	MessageQueue.scala;
const #3 = Asciz	Scala;
const #4 = Asciz	MODULE$;
const #5 = Asciz	Lscala/actors/MessageQueueTracer$;;
const #6 = Asciz	<clinit>;
const #7 = Asciz	()V;
const #8 = Asciz	Code;
const #9 = Asciz	scala/actors/MessageQueueTracer$;
const #10 = class	#9;	//  scala/actors/MessageQueueTracer$
const #11 = Asciz	<init>;
const #12 = NameAndType	#11:#7;//  "<init>":()V
const #13 = Method	#10.#12;	//  scala/actors/MessageQueueTracer$."<init>":()V
const #14 = Asciz	queueNumberAssigner;
const #15 = Asciz	I;
const #16 = Asciz	LineNumberTable;
const #17 = Asciz	java/lang/Object;
const #18 = class	#17;	//  java/lang/Object
const #19 = Method	#18.#12;	//  java/lang/Object."<init>":()V
const #20 = NameAndType	#4:#5;//  MODULE$:Lscala/actors/MessageQueueTracer$;
const #21 = Field	#10.#20;	//  scala/actors/MessageQueueTracer$.MODULE$:Lscala/actors/MessageQueueTracer$;
const #22 = NameAndType	#14:#15;//  queueNumberAssigner:I
const #23 = Field	#10.#22;	//  scala/actors/MessageQueueTracer$.queueNumberAssigner:I
const #24 = Asciz	scala$actors$MessageQueueTracer$$getQueueNumber;
const #25 = Asciz	()I;
const #26 = NameAndType	#14:#25;//  queueNumberAssigner:()I
const #27 = Method	#10.#26;	//  scala/actors/MessageQueueTracer$.queueNumberAssigner:()I
const #28 = Asciz	queueNumberAssigner_$eq;
const #29 = Asciz	(I)V;
const #30 = NameAndType	#28:#29;//  queueNumberAssigner_$eq:(I)V
const #31 = Method	#10.#30;	//  scala/actors/MessageQueueTracer$.queueNumberAssigner_$eq:(I)V
const #32 = Asciz	scala/ScalaObject;
const #33 = class	#32;	//  scala/ScalaObject

{
public static final scala.actors.MessageQueueTracer$ MODULE$;

public static {};
  Code:
   Stack=1, Locals=0, Args_size=0
   0:	new	#10; //class scala/actors/MessageQueueTracer$
   3:	invokespecial	#13; //Method "<init>":()V
   6:	return

public final int scala$actors$MessageQueueTracer$$getQueueNumber();
  Code:
   Stack=3, Locals=2, Args_size=1
   0:	aload_0
   1:	dup
   2:	pop
   3:	monitorenter
   4:	aload_0
   5:	aload_0
   6:	invokespecial	#27; //Method queueNumberAssigner:()I
   9:	iconst_1
   10:	iadd
   11:	invokespecial	#31; //Method queueNumberAssigner_$eq:(I)V
   14:	aload_0
   15:	invokespecial	#27; //Method queueNumberAssigner:()I
   18:	istore_1
   19:	aload_0
   20:	monitorexit
   21:	iload_1
   22:	ireturn
   23:	aload_0
   24:	monitorexit
   25:	athrow
  Exception table:
   from   to  target type
     4    21    23   any
  LineNumberTable: 
   line 194: 0
   line 195: 4
   line 196: 14
   line 194: 20


}

