Compiled from "MessageQueue.scala"
public class scala.actors.MessageQueue extends java.lang.Object implements scala.ScalaObject,java.io.Serializable
  SourceFile: "MessageQueue.scala"
  ScalaSig: length = 0x4D1
   05 00 FFFFFF81 30 06 08 01 02 FFFFFF84 FFFFFF80 FFFFFF80 FFFFFF80 00 07 02 0C
   4D 65 73 73 61 67 65 51 75 65 75 65 0A 02 03 04
   01 06 61 63 74 6F 72 73 0A 01 05 01 05 73 63 61
   6C 61 03 00 13 03 00 08 10 10 02 09 0E 0D 01 0A
   0A 02 0B 0C 01 04 6C 61 6E 67 0A 01 0D 01 04 6A
   61 76 61 09 02 0F 0A 02 06 4F 62 6A 65 63 74 10
   02 11 12 0D 01 04 09 02 13 04 02 0B 53 63 61 6C
   61 4F 62 6A 65 63 74 08 08 15 00 FFFFFF82 FFFFFFC2 FFFFFF80 FFFFFF84 08
   16 01 05 6C 61 62 65 6C 15 01 17 10 02 18 1B 0E
   02 11 19 09 02 1A 04 01 06 50 72 65 64 65 66 09
   02 1C 1D 02 06 53 74 72 69 6E 67 0A 02 1A 04 08
   08 1F 00 FFFFFF82 FFFFFF80 FFFFFFA0 FFFFFF80 04 17 01 06 6C 61 62 65 6C
   20 08 05 21 00 FFFFFF84 00 22 01 06 3C 69 6E 69 74 3E
   14 02 23 25 10 02 24 00 0D 01 02 08 05 15 20 FFFFFFC0
   00 17 08 07 27 00 FFFFFFC0 FFFFFF80 FFFFFF84 08 28 01 05 66 69 72
   73 74 15 01 29 10 02 24 2A 09 02 2B 02 02 13 4D
   65 73 73 61 67 65 51 75 65 75 65 45 6C 65 6D 65
   6E 74 08 07 2D 00 FFFFFFC0 FFFFFF80 FFFFFF84 08 2E 01 09 66 69 72
   73 74 5F 24 65 71 14 02 2F 32 10 02 11 30 09 02
   31 04 02 04 55 6E 69 74 08 07 33 2C FFFFFF81 FFFFFF80 FFFFFFC0 00
   29 01 03 78 24 31 08 06 35 00 FFFFFFA0 FFFFFFA0 04 29 01 06
   66 69 72 73 74 20 08 07 37 00 FFFFFFC0 FFFFFF80 FFFFFF84 08 28 01
   04 6C 61 73 74 08 07 39 00 FFFFFFC0 FFFFFF80 FFFFFF84 08 3A 01 08
   6C 61 73 74 5F 24 65 71 14 02 2F 3B 08 07 33 38
   FFFFFF81 FFFFFF80 FFFFFFC0 00 29 08 06 3D 00 FFFFFFA0 FFFFFFA0 04 29 01 05 6C
   61 73 74 20 08 07 3F 00 FFFFFFC0 FFFFFF80 FFFFFF84 04 40 01 05 5F
   73 69 7A 65 15 01 41 10 02 11 42 09 02 43 04 02
   03 49 6E 74 08 07 45 00 FFFFFFC0 FFFFFF80 FFFFFF84 04 46 01 09 5F
   73 69 7A 65 5F 24 65 71 14 02 2F 47 08 07 33 44
   FFFFFF81 FFFFFF80 FFFFFFC0 00 41 08 06 49 00 FFFFFFA0 FFFFFFA0 04 41 01 06 5F
   73 69 7A 65 20 08 05 4B 00 FFFFFF84 00 40 01 04 73 69
   7A 65 08 05 4D 00 FFFFFF84 02 4E 01 07 69 73 45 6D 70
   74 79 15 01 4F 10 02 11 50 09 02 51 04 02 07 42
   6F 6F 6C 65 61 6E 08 05 53 00 FFFFFF84 08 54 01 0A 63
   68 61 6E 67 65 53 69 7A 65 14 02 2F 55 08 05 56
   52 FFFFFFC0 00 41 01 04 64 69 66 66 08 05 58 00 FFFFFF84 00
   59 01 06 61 70 70 65 6E 64 14 03 2F 5A 5F 08 05
   5B 57 FFFFFFC0 00 5C 01 03 6D 73 67 10 02 11 5D 09 02
   5E 04 02 03 41 6E 79 08 05 60 57 FFFFFFC0 00 61 01 07
   73 65 73 73 69 6F 6E 10 03 24 62 5C 09 02 63 02
   02 0D 4F 75 74 70 75 74 43 68 61 6E 6E 65 6C 08
   05 65 00 FFFFFF84 00 66 01 07 66 6F 72 65 61 63 68 14
   02 2F 67 08 05 68 64 FFFFFFC0 00 69 01 01 66 10 05 11
   6A 5C 61 2F 09 02 6B 04 02 09 46 75 6E 63 74 69
   6F 6E 32 08 05 6D 00 FFFFFF84 00 6E 01 08 66 6F 6C 64
   4C 65 66 74 15 02 6F 73 14 02 70 7B 14 02 71 79
   10 02 72 73 0C 00 04 08 74 6C FFFFFF84 FFFFFF80 FFFFFF80 FFFFFFC2 00 75
   02 01 42 11 02 76 5C 10 02 11 77 09 02 78 04 02
   07 4E 6F 74 68 69 6E 67 08 05 68 6C FFFFFFC0 00 7A 10
   05 11 6A 71 5C 71 08 05 7C 6C FFFFFFC0 00 71 01 01 7A
   08 05 7E 00 FFFFFF84 00 7F 01 03 67 65 74 14 04 FFFFFF81 00
   FFFFFF81 09 14 04 FFFFFF81 01 FFFFFF81 04 10 04 11 FFFFFF81 02 5C 09 03
   FFFFFF81 03 04 02 06 4F 70 74 69 6F 6E 08 07 FFFFFF81 05 7D
   FFFFFFC0 00 FFFFFF81 06 01 01 70 10 05 11 FFFFFF81 07 5C 4F 09 03
   FFFFFF81 08 04 02 09 46 75 6E 63 74 69 6F 6E 31 08 06
   FFFFFF81 0A 7D FFFFFFC0 00 41 01 01 6E 08 07 FFFFFF81 0C 00 FFFFFF84 00
   FFFFFF81 0D 01 06 72 65 6D 6F 76 65 14 04 FFFFFF81 0E FFFFFF81 15
   14 04 FFFFFF81 0F FFFFFF81 13 10 05 11 FFFFFF81 02 FFFFFF81 10 10 05 11
   FFFFFF81 11 5C 61 09 03 FFFFFF81 12 04 02 06 54 75 70 6C 65
   32 08 08 FFFFFF81 05 FFFFFF81 0B FFFFFFC0 00 FFFFFF81 14 10 05 11 6A 5C
   61 4F 08 07 FFFFFF81 0A FFFFFF81 0B FFFFFFC0 00 41 08 07 FFFFFF81 17 00
   FFFFFF84 00 FFFFFF81 18 01 0C 65 78 74 72 61 63 74 46 69 72
   73 74 14 03 29 FFFFFF81 19 08 08 FFFFFF81 05 FFFFFF81 16 FFFFFFC0 00 FFFFFF81
   14 08 07 FFFFFF81 1B 00 FFFFFF84 04 FFFFFF81 1C 01 0E 72 65 6D 6F
   76 65 49 6E 74 65 72 6E 61 6C 14 04 FFFFFF81 1D FFFFFF81 20
   14 04 FFFFFF81 1E FFFFFF81 1F 10 04 11 FFFFFF81 02 29 08 08 FFFFFF81 05
   FFFFFF81 1A FFFFFFC0 00 FFFFFF81 14 08 07 FFFFFF81 0A FFFFFF81 1A FFFFFFC0 00 41 28
   05 00 FFFFFF81 22 FFFFFF81 25 10 03 11 FFFFFF81 23 09 03 FFFFFF81 24 04
   02 0A 64 65 70 72 65 63 61 74 65 64 21 02 FFFFFF81 26
   01 35 74 68 69 73 20 63 6C 61 73 73 20 69 73 20
   67 6F 69 6E 67 20 74 6F 20 62 65 20 72 65 6D 6F
   76 65 64 20 69 6E 20 61 20 66 75 74 75 72 65 20
   72 65 6C 65 61 73 65 28 05 00 FFFFFF81 28 FFFFFF81 2B 10 03
   11 FFFFFF81 29 09 03 FFFFFF81 2A 04 02 10 53 65 72 69 61 6C
   56 65 72 73 69 6F 6E 55 49 44 1E 08 1E 19 FFFFFF9B FFFFFFAF
   53 FFFFFFDB FFFFFFBB 17 28 03 00 FFFFFF81 2D 10 03 11 FFFFFF81 2E 09 03
   FFFFFF81 2F 04 02 0C 73 65 72 69 61 6C 69 7A 61 62 6C
   65 
  InnerClass: 
   public abstract $less$colon$less=class scala/Predef$$less$colon$less of class scala/Predef
   public final $anonfun$remove$1=class scala/actors/MessageQueue$$anonfun$remove$1 of class scala/actors/MessageQueue
  minor version: 0
  major version: 49
  Constant pool:
Asciz	SourceFile;
Asciz	MessageQueue.scala;
Asciz	<clinit>;
Asciz	()V;
Asciz	Code;
Asciz	serialVersionUID;
Asciz	J;
long	2168935872884095767l;
Asciz	scala/actors/MessageQueue;
class	scala/actors/MessageQueue
NameAndType	serialVersionUID:J
Field	scala/actors/MessageQueue.serialVersionUID:J
Asciz	_size;
Asciz	I;
Asciz	last;
Asciz	Lscala/actors/MessageQueueElement;;
Asciz	first;
Asciz	label;
Asciz	Ljava/lang/String;;
Asciz	<init>;
Asciz	(Ljava/lang/String;)V;
Asciz	LineNumberTable;
NameAndType	label:Ljava/lang/String;
Field	scala/actors/MessageQueue.label:Ljava/lang/String;
Asciz	java/lang/Object;
class	java/lang/Object
NameAndType	"<init>":()V
Method	java/lang/Object."<init>":()V
NameAndType	first:Lscala/actors/MessageQueueElement;
Field	scala/actors/MessageQueue.first:Lscala/actors/MessageQueueElement;
NameAndType	last:Lscala/actors/MessageQueueElement;
Field	scala/actors/MessageQueue.last:Lscala/actors/MessageQueueElement;
NameAndType	_size:I
Field	scala/actors/MessageQueue._size:I
Asciz	this;
Asciz	Lscala/actors/MessageQueue;;
Asciz	LocalVariableTable;
Asciz	test$2;
Asciz	(Ljava/lang/Object;Lscala/actors/OutputChannel;ILscala/Function2;Lscala/runtime/IntRef;)Z;
Asciz	scala/Function2;
class	scala/Function2
Asciz	apply;
Asciz	(Ljava/lang/Object;Ljava/lang/Object;)Ljava/lang/Object;;
NameAndType	apply:(Ljava/lang/Object;Ljava/lang/Object;)Ljava/lang/Object;
InterfaceMethod	scala/Function2.apply:(Ljava/lang/Object;Ljava/lang/Object;)Ljava/lang/Object;
Asciz	scala/runtime/BoxesRunTime;
class	scala/runtime/BoxesRunTime
Asciz	unboxToBoolean;
Asciz	(Ljava/lang/Object;)Z;
NameAndType	unboxToBoolean:(Ljava/lang/Object;)Z
Method	scala/runtime/BoxesRunTime.unboxToBoolean:(Ljava/lang/Object;)Z
Asciz	scala/runtime/IntRef;
class	scala/runtime/IntRef
Asciz	elem;
NameAndType	elem:I
Field	scala/runtime/IntRef.elem:I
Asciz	msg;
Asciz	Ljava/lang/Object;;
Asciz	session;
Asciz	Lscala/actors/OutputChannel;;
Asciz	foundMsg$1;
Asciz	(Lscala/actors/MessageQueueElement;)Lscala/Some;;
Asciz	changeSize;
Asciz	(I)V;
NameAndType	changeSize:(I)V
Method	scala/actors/MessageQueue.changeSize:(I)V
Asciz	scala/Some;
class	scala/Some
Asciz	(Ljava/lang/Object;)V;
NameAndType	"<init>":(Ljava/lang/Object;)V
Method	scala/Some."<init>":(Ljava/lang/Object;)V
Asciz	x;
Asciz	test$1;
Asciz	(Ljava/lang/Object;ILscala/Function1;Lscala/runtime/IntRef;)Z;
Asciz	scala/Function1;
class	scala/Function1
Asciz	(Ljava/lang/Object;)Ljava/lang/Object;;
NameAndType	apply:(Ljava/lang/Object;)Ljava/lang/Object;
InterfaceMethod	scala/Function1.apply:(Ljava/lang/Object;)Ljava/lang/Object;
Asciz	removeInternal;
Asciz	(ILscala/Function2;)Lscala/Option;;
NameAndType	"<init>":(I)V
Method	scala/runtime/IntRef."<init>":(I)V
Asciz	isEmpty;
Asciz	()Z;
NameAndType	isEmpty:()Z
Method	scala/actors/MessageQueue.isEmpty:()Z
Asciz	scala/None$;
class	scala/None$
Asciz	MODULE$;
Asciz	Lscala/None$;;
NameAndType	MODULE$:Lscala/None$;
Field	scala/None$.MODULE$:Lscala/None$;
Asciz	()Lscala/actors/MessageQueueElement;;
NameAndType	first:()Lscala/actors/MessageQueueElement;
Method	scala/actors/MessageQueue.first:()Lscala/actors/MessageQueueElement;
Asciz	scala/actors/MessageQueueElement;
class	scala/actors/MessageQueueElement
Asciz	()Ljava/lang/Object;;
NameAndType	msg:()Ljava/lang/Object;
Method	scala/actors/MessageQueueElement.msg:()Ljava/lang/Object;
Asciz	()Lscala/actors/OutputChannel;;
NameAndType	session:()Lscala/actors/OutputChannel;
Method	scala/actors/MessageQueueElement.session:()Lscala/actors/OutputChannel;
NameAndType	test$2:(Ljava/lang/Object;Lscala/actors/OutputChannel;ILscala/Function2;Lscala/runtime/IntRef;)Z
Method	scala/actors/MessageQueue.test$2:(Ljava/lang/Object;Lscala/actors/OutputChannel;ILscala/Function2;Lscala/runtime/IntRef;)Z
Asciz	next;
NameAndType	next:()Lscala/actors/MessageQueueElement;
Method	scala/actors/MessageQueueElement.next:()Lscala/actors/MessageQueueElement;
Asciz	first_$eq;
Asciz	(Lscala/actors/MessageQueueElement;)V;
NameAndType	first_$eq:(Lscala/actors/MessageQueueElement;)V
Method	scala/actors/MessageQueue.first_$eq:(Lscala/actors/MessageQueueElement;)V
NameAndType	last:()Lscala/actors/MessageQueueElement;
Method	scala/actors/MessageQueue.last:()Lscala/actors/MessageQueueElement;
Asciz	last_$eq;
NameAndType	last_$eq:(Lscala/actors/MessageQueueElement;)V
Method	scala/actors/MessageQueue.last_$eq:(Lscala/actors/MessageQueueElement;)V
NameAndType	foundMsg$1:(Lscala/actors/MessageQueueElement;)Lscala/Some;
Method	scala/actors/MessageQueue.foundMsg$1:(Lscala/actors/MessageQueueElement;)Lscala/Some;
Asciz	equals;
NameAndType	equals:(Ljava/lang/Object;)Z
Method	java/lang/Object.equals:(Ljava/lang/Object;)Z
Asciz	next_$eq;
NameAndType	next_$eq:(Lscala/actors/MessageQueueElement;)V
Method	scala/actors/MessageQueueElement.next_$eq:(Lscala/actors/MessageQueueElement;)V
Asciz	n$2;
Asciz	p$2;
Asciz	Lscala/Function2;;
Asciz	res;
Asciz	pos$2;
Asciz	Lscala/runtime/IntRef;;
Asciz	prev;
Asciz	curr;
Asciz	(ILscala/Function2<Ljava/lang/Object;Lscala/actors/OutputChannel<Ljava/lang/Object;>;Ljava/lang/Boolean;>;)Lscala/Option<Lscala/actors/MessageQueueElement;>;;
Asciz	Signature;
Asciz	extractFirst;
Asciz	(Lscala/Function2;)Lscala/actors/MessageQueueElement;;
NameAndType	removeInternal:(ILscala/Function2;)Lscala/Option;
Method	scala/actors/MessageQueue.removeInternal:(ILscala/Function2;)Lscala/Option;
Asciz	scala/Predef$;
class	scala/Predef$
Asciz	Lscala/Predef$;;
NameAndType	MODULE$:Lscala/Predef$;
Field	scala/Predef$.MODULE$:Lscala/Predef$;
Asciz	conforms;
Asciz	()Lscala/Predef$$less$colon$less;;
NameAndType	conforms:()Lscala/Predef$$less$colon$less;
Method	scala/Predef$.conforms:()Lscala/Predef$$less$colon$less;
Asciz	scala/Option;
class	scala/Option
Asciz	orNull;
Asciz	(Lscala/Predef$$less$colon$less;)Ljava/lang/Object;;
NameAndType	orNull:(Lscala/Predef$$less$colon$less;)Ljava/lang/Object;
Method	scala/Option.orNull:(Lscala/Predef$$less$colon$less;)Ljava/lang/Object;
Asciz	p;
Asciz	(Lscala/Function2<Ljava/lang/Object;Lscala/actors/OutputChannel<Ljava/lang/Object;>;Ljava/lang/Boolean;>;)Lscala/actors/MessageQueueElement;;
Asciz	remove;
Asciz	scala/actors/MessageQueue$$anonfun$remove$1;
class	scala/actors/MessageQueue$$anonfun$remove$1
Asciz	(Lscala/actors/MessageQueue;)V;
NameAndType	"<init>":(Lscala/actors/MessageQueue;)V
Method	scala/actors/MessageQueue$$anonfun$remove$1."<init>":(Lscala/actors/MessageQueue;)V
Asciz	map;
Asciz	(Lscala/Function1;)Lscala/Option;;
NameAndType	map:(Lscala/Function1;)Lscala/Option;
Method	scala/Option.map:(Lscala/Function1;)Lscala/Option;
Asciz	n;
Asciz	(ILscala/Function2<Ljava/lang/Object;Lscala/actors/OutputChannel<Ljava/lang/Object;>;Ljava/lang/Boolean;>;)Lscala/Option<Lscala/Tuple2<Ljava/lang/Object;Lscala/actors/OutputChannel<Ljava/lang/Object;>;>;>;;
Asciz	get;
Asciz	(ILscala/Function1;)Lscala/Option;;
NameAndType	test$1:(Ljava/lang/Object;ILscala/Function1;Lscala/runtime/IntRef;)Z
Method	scala/actors/MessageQueue.test$1:(Ljava/lang/Object;ILscala/Function1;Lscala/runtime/IntRef;)Z
Asciz	n$1;
Asciz	p$1;
Asciz	Lscala/Function1;;
Asciz	pos$1;
Asciz	(ILscala/Function1<Ljava/lang/Object;Ljava/lang/Boolean;>;)Lscala/Option<Ljava/lang/Object;>;;
Asciz	foldLeft;
Asciz	(Ljava/lang/Object;Lscala/Function2;)Ljava/lang/Object;;
Asciz	z;
Asciz	f;
Asciz	acc;
Asciz	<B:Ljava/lang/Object;>(TB;Lscala/Function2<TB;Ljava/lang/Object;TB;>;)TB;;
Asciz	foreach;
Asciz	(Lscala/Function2;)V;
Asciz	(Lscala/Function2<Ljava/lang/Object;Lscala/actors/OutputChannel<Ljava/lang/Object;>;Ljava/lang/Object;>;)V;
Asciz	append;
Asciz	(Ljava/lang/Object;Lscala/actors/OutputChannel;)V;
NameAndType	"<init>":(Ljava/lang/Object;Lscala/actors/OutputChannel;)V
Method	scala/actors/MessageQueueElement."<init>":(Ljava/lang/Object;Lscala/actors/OutputChannel;)V
Asciz	el;
Asciz	(Ljava/lang/Object;Lscala/actors/OutputChannel<Ljava/lang/Object;>;)V;
Asciz	()I;
NameAndType	_size:()I
Method	scala/actors/MessageQueue._size:()I
Asciz	_size_$eq;
NameAndType	_size_$eq:(I)V
Method	scala/actors/MessageQueue._size_$eq:(I)V
Asciz	diff;
Asciz	size;
Asciz	()Ljava/lang/String;;
Asciz	ScalaSig;
Asciz	InnerClasses;
Asciz	scala/Predef$$less$colon$less;
class	scala/Predef$$less$colon$less
Asciz	scala/Predef;
class	scala/Predef
Asciz	$less$colon$less;
Asciz	$anonfun$remove$1;
Asciz	scala/ScalaObject;
class	scala/ScalaObject
Asciz	java/io/Serializable;
class	java/io/Serializable

{
public static final long serialVersionUID;
  Signature: J

private int _size;
  Signature: I

private scala.actors.MessageQueueElement last;
  Signature: Lscala/actors/MessageQueueElement;

private scala.actors.MessageQueueElement first;
  Signature: Lscala/actors/MessageQueueElement;

private final java.lang.String label;
  Signature: Ljava/lang/String;

public static {};
  Signature: ()V
  Code:
   Stack=2, Locals=0, Args_size=0
	ldc2_w	long 2168935872884095767l
	putstatic	Field serialVersionUID:J
	return
  Labels:

public scala.actors.MessageQueue(java.lang.String);
  Signature: (Ljava/lang/String;)V
  Code:
   Stack=2, Locals=2, Args_size=2
	aload_0
	aload_1
	putfield	Field label:Ljava/lang/String;
	aload_0
	invokespecial	Method java/lang/Object."<init>":()V
	aload_0
	aconst_null
	putfield	Field first:Lscala/actors/MessageQueueElement;
	aload_0
	aconst_null
	putfield	Field last:Lscala/actors/MessageQueueElement;
	aload_0
	iconst_0
	putfield	Field _size:I
	return
  Labels:
  LocalVariableTable: 
   Start  Length  Slot  Name   Signature
   0      25      0    this       Lscala/actors/MessageQueue;
   0      25      1    label       Ljava/lang/String;


private final boolean test$2(java.lang.Object, scala.actors.OutputChannel, int, scala.Function2, scala.runtime.IntRef);
  Signature: (Ljava/lang/Object;Lscala/actors/OutputChannel;ILscala/Function2;Lscala/runtime/IntRef;)Z
  Code:
   Stack=3, Locals=6, Args_size=6
	aload	4
	aload_1
	aload_2
	invokeinterface	InterfaceMethod scala/Function2.apply:(Ljava/lang/Object;Ljava/lang/Object;)Ljava/lang/Object;
	invokestatic	Method scala/runtime/BoxesRunTime.unboxToBoolean:(Ljava/lang/Object;)Z
	ifeq	l1 // iconst_0
	aload	5
	getfield	Field scala/runtime/IntRef.elem:I
	iload_3
	if_icmpeq	l2 // iconst_1
	aload	5
	aload	5
	getfield	Field scala/runtime/IntRef.elem:I
	iconst_1
	iadd
	putfield	Field scala/runtime/IntRef.elem:I
	iconst_0
	ifeq	l1 // iconst_0
l2	iconst_1
	goto	l3 // ireturn
l1	iconst_0
l3	ireturn
  Labels:
   	l2 = 40 // iconst_1
   	l1 = 44 // iconst_0
   	l3 = 45 // ireturn
  LocalVariableTable: 
   Start  Length  Slot  Name   Signature
   0      46      0    this       Lscala/actors/MessageQueue;
   0      46      1    msg       Ljava/lang/Object;
   0      46      2    session       Lscala/actors/OutputChannel;


private final scala.Some foundMsg$1(scala.actors.MessageQueueElement);
  Signature: (Lscala/actors/MessageQueueElement;)Lscala/Some;
  Code:
   Stack=3, Locals=2, Args_size=2
	aload_0
	iconst_m1
	invokevirtual	Method changeSize:(I)V
	new	class scala/Some
	dup
	aload_1
	invokespecial	Method scala/Some."<init>":(Ljava/lang/Object;)V
	areturn
  Labels:
  LocalVariableTable: 
   Start  Length  Slot  Name   Signature
   0      14      0    this       Lscala/actors/MessageQueue;
   0      14      1    x       Lscala/actors/MessageQueueElement;


private final boolean test$1(java.lang.Object, int, scala.Function1, scala.runtime.IntRef);
  Signature: (Ljava/lang/Object;ILscala/Function1;Lscala/runtime/IntRef;)Z
  Code:
   Stack=3, Locals=5, Args_size=5
	aload_3
	aload_1
	invokeinterface	InterfaceMethod scala/Function1.apply:(Ljava/lang/Object;)Ljava/lang/Object;
	invokestatic	Method scala/runtime/BoxesRunTime.unboxToBoolean:(Ljava/lang/Object;)Z
	ifeq	l1 // iconst_0
	aload	4
	getfield	Field scala/runtime/IntRef.elem:I
	iload_2
	if_icmpeq	l2 // iconst_1
	aload	4
	aload	4
	getfield	Field scala/runtime/IntRef.elem:I
	iconst_1
	iadd
	putfield	Field scala/runtime/IntRef.elem:I
	iconst_0
	ifeq	l1 // iconst_0
l2	iconst_1
	goto	l3 // ireturn
l1	iconst_0
l3	ireturn
  Labels:
   	l2 = 38 // iconst_1
   	l1 = 42 // iconst_0
   	l3 = 43 // ireturn
  LocalVariableTable: 
   Start  Length  Slot  Name   Signature
   0      44      0    this       Lscala/actors/MessageQueue;
   0      44      1    msg       Ljava/lang/Object;


private scala.Option removeInternal(int, scala.Function2);
  Signature: (ILscala/Function2;)Lscala/Option;
  Code:
   Stack=6, Locals=7, Args_size=3
	new	class scala/runtime/IntRef
	dup
	iconst_0
	invokespecial	Method scala/runtime/IntRef."<init>":(I)V
	astore	4
	aload_0
	invokevirtual	Method isEmpty:()Z
	ifeq	l1 // aload_0
	getstatic	Field scala/None$.MODULE$:Lscala/None$;
	areturn
l1	aload_0
	aload_0
	invokevirtual	Method first:()Lscala/actors/MessageQueueElement;
	invokevirtual	Method scala/actors/MessageQueueElement.msg:()Ljava/lang/Object;
	aload_0
	invokevirtual	Method first:()Lscala/actors/MessageQueueElement;
	invokevirtual	Method scala/actors/MessageQueueElement.session:()Lscala/actors/OutputChannel;
	iload_1
	aload_2
	aload	4
	invokespecial	Method test$2:(Ljava/lang/Object;Lscala/actors/OutputChannel;ILscala/Function2;Lscala/runtime/IntRef;)Z
	ifeq	l2 // aload_0
	aload_0
	invokevirtual	Method first:()Lscala/actors/MessageQueueElement;
	astore_3
	aload_0
	aload_0
	invokevirtual	Method first:()Lscala/actors/MessageQueueElement;
	invokevirtual	Method scala/actors/MessageQueueElement.next:()Lscala/actors/MessageQueueElement;
	invokevirtual	Method first_$eq:(Lscala/actors/MessageQueueElement;)V
	aload_3
	aload_0
	invokevirtual	Method last:()Lscala/actors/MessageQueueElement;
	if_acmpne	l3 // aload_0
	aload_0
	aconst_null
	invokevirtual	Method last_$eq:(Lscala/actors/MessageQueueElement;)V
l3	aload_0
	aload_3
	invokespecial	Method foundMsg$1:(Lscala/actors/MessageQueueElement;)Lscala/Some;
	goto	l4 // areturn
l2	aload_0
	invokevirtual	Method first:()Lscala/actors/MessageQueueElement;
	invokevirtual	Method scala/actors/MessageQueueElement.next:()Lscala/actors/MessageQueueElement;
	astore	6
	aload_0
	invokevirtual	Method first:()Lscala/actors/MessageQueueElement;
	astore	5
l9	aload	6
	dup
	pop
	ifnull	l5 // getstatic
	aload	6
	aconst_null
	invokevirtual	Method java/lang/Object.equals:(Ljava/lang/Object;)Z
	ifeq	l6 // aload_0
l5	getstatic	Field scala/None$.MODULE$:Lscala/None$;
l4	areturn
l6	aload_0
	aload	6
	invokevirtual	Method scala/actors/MessageQueueElement.msg:()Ljava/lang/Object;
	aload	6
	invokevirtual	Method scala/actors/MessageQueueElement.session:()Lscala/actors/OutputChannel;
	iload_1
	aload_2
	aload	4
	invokespecial	Method test$2:(Ljava/lang/Object;Lscala/actors/OutputChannel;ILscala/Function2;Lscala/runtime/IntRef;)Z
	ifeq	l7 // aload
	aload	5
	aload	6
	invokevirtual	Method scala/actors/MessageQueueElement.next:()Lscala/actors/MessageQueueElement;
	invokevirtual	Method scala/actors/MessageQueueElement.next_$eq:(Lscala/actors/MessageQueueElement;)V
	aload	6
	aload_0
	invokevirtual	Method last:()Lscala/actors/MessageQueueElement;
	if_acmpne	l8 // aload_0
	aload_0
	aload	5
	invokevirtual	Method last_$eq:(Lscala/actors/MessageQueueElement;)V
l8	aload_0
	aload	6
	invokespecial	Method foundMsg$1:(Lscala/actors/MessageQueueElement;)Lscala/Some;
	areturn
l7	aload	6
	astore	5
	aload	6
	invokevirtual	Method scala/actors/MessageQueueElement.next:()Lscala/actors/MessageQueueElement;
	astore	6
	goto	l9 // aload
  Labels:
   	l1 = 21 // aload_0
   	l3 = 75 // aload_0
   	l2 = 83 // aload_0
   	l9 = 98 // aload
   	l5 = 114 // getstatic
   	l4 = 117 // areturn
   	l6 = 118 // aload_0
   	l8 = 164 // aload_0
   	l7 = 171 // aload
  LocalVariableTable: 
   Start  Length  Slot  Name   Signature
   0      185      0    this       Lscala/actors/MessageQueue;
   0      185      1    n$2       I
   0      185      2    p$2       Lscala/Function2;
   51      29      3    res       Lscala/actors/MessageQueueElement;
   10      175      4    pos$2       Lscala/runtime/IntRef;
   98      19      5    prev       Lscala/actors/MessageQueueElement;
   118      67      5    prev       Lscala/actors/MessageQueueElement;
   92      25      6    curr       Lscala/actors/MessageQueueElement;
   118      67      6    curr       Lscala/actors/MessageQueueElement;

  Signature: length = 0x2
   00 FFFFFF88 

public scala.actors.MessageQueueElement extractFirst(scala.Function2);
  Signature: (Lscala/Function2;)Lscala/actors/MessageQueueElement;
  Code:
   Stack=3, Locals=2, Args_size=2
	aload_0
	iconst_0
	aload_1
	invokespecial	Method removeInternal:(ILscala/Function2;)Lscala/Option;
	getstatic	Field scala/Predef$.MODULE$:Lscala/Predef$;
	invokevirtual	Method scala/Predef$.conforms:()Lscala/Predef$$less$colon$less;
	invokevirtual	Method scala/Option.orNull:(Lscala/Predef$$less$colon$less;)Ljava/lang/Object;
	checkcast	class scala/actors/MessageQueueElement
	areturn
  Labels:
  LocalVariableTable: 
   Start  Length  Slot  Name   Signature
   0      19      0    this       Lscala/actors/MessageQueue;
   0      19      1    p       Lscala/Function2;

  Signature: length = 0x2
   00 FFFFFF9E 

public scala.Option remove(int, scala.Function2);
  Signature: (ILscala/Function2;)Lscala/Option;
  Code:
   Stack=4, Locals=3, Args_size=3
	aload_0
	iload_1
	aload_2
	invokespecial	Method removeInternal:(ILscala/Function2;)Lscala/Option;
	new	class scala/actors/MessageQueue$$anonfun$remove$1
	dup
	aload_0
	invokespecial	Method scala/actors/MessageQueue$$anonfun$remove$1."<init>":(Lscala/actors/MessageQueue;)V
	invokevirtual	Method scala/Option.map:(Lscala/Function1;)Lscala/Option;
	areturn
  Labels:
  LocalVariableTable: 
   Start  Length  Slot  Name   Signature
   0      18      0    this       Lscala/actors/MessageQueue;
   0      18      1    n       I
   0      18      2    p       Lscala/Function2;

  Signature: length = 0x2
   00 FFFFFFAA 

public scala.Option get(int, scala.Function1);
  Signature: (ILscala/Function1;)Lscala/Option;
  Code:
   Stack=5, Locals=5, Args_size=3
	new	class scala/runtime/IntRef
	dup
	iconst_0
	invokespecial	Method scala/runtime/IntRef."<init>":(I)V
	astore_3
	aload_0
	invokevirtual	Method first:()Lscala/actors/MessageQueueElement;
	astore	4
l4	aload	4
	dup
	pop
	ifnull	l1 // getstatic
	aload	4
	aconst_null
	invokevirtual	Method java/lang/Object.equals:(Ljava/lang/Object;)Z
	ifeq	l2 // aload_0
l1	getstatic	Field scala/None$.MODULE$:Lscala/None$;
	areturn
l2	aload_0
	aload	4
	invokevirtual	Method scala/actors/MessageQueueElement.msg:()Ljava/lang/Object;
	iload_1
	aload_2
	aload_3
	invokespecial	Method test$1:(Ljava/lang/Object;ILscala/Function1;Lscala/runtime/IntRef;)Z
	ifeq	l3 // aload
	new	class scala/Some
	dup
	aload	4
	invokevirtual	Method scala/actors/MessageQueueElement.msg:()Ljava/lang/Object;
	invokespecial	Method scala/Some."<init>":(Ljava/lang/Object;)V
	areturn
l3	aload	4
	invokevirtual	Method scala/actors/MessageQueueElement.next:()Lscala/actors/MessageQueueElement;
	astore	4
	goto	l4 // aload
  Labels:
   	l4 = 15 // aload
   	l1 = 31 // getstatic
   	l2 = 35 // aload_0
   	l3 = 63 // aload
  LocalVariableTable: 
   Start  Length  Slot  Name   Signature
   0      73      0    this       Lscala/actors/MessageQueue;
   0      73      1    n$1       I
   0      73      2    p$1       Lscala/Function1;
   9      25      3    pos$1       Lscala/runtime/IntRef;
   35      38      3    pos$1       Lscala/runtime/IntRef;
   15      19      4    curr       Lscala/actors/MessageQueueElement;
   35      38      4    curr       Lscala/actors/MessageQueueElement;

  Signature: length = 0x2
   00 FFFFFFB3 

public java.lang.Object foldLeft(java.lang.Object, scala.Function2);
  Signature: (Ljava/lang/Object;Lscala/Function2;)Ljava/lang/Object;
  Code:
   Stack=3, Locals=5, Args_size=3
	aload_1
	astore_3
	aload_0
	invokevirtual	Method first:()Lscala/actors/MessageQueueElement;
	astore	4
l3	aload	4
	dup
	pop
	ifnull	l1 // aload_3
	aload	4
	aconst_null
	invokevirtual	Method java/lang/Object.equals:(Ljava/lang/Object;)Z
	ifeq	l2 // aload_2
l1	aload_3
	areturn
l2	aload_2
	aload_3
	aload	4
	invokevirtual	Method scala/actors/MessageQueueElement.msg:()Ljava/lang/Object;
	invokeinterface	InterfaceMethod scala/Function2.apply:(Ljava/lang/Object;Ljava/lang/Object;)Ljava/lang/Object;
	astore_3
	aload	4
	invokevirtual	Method scala/actors/MessageQueueElement.next:()Lscala/actors/MessageQueueElement;
	astore	4
	goto	l3 // aload
  Labels:
   	l3 = 8 // aload
   	l1 = 24 // aload_3
   	l2 = 26 // aload_2
  LocalVariableTable: 
   Start  Length  Slot  Name   Signature
   0      49      0    this       Lscala/actors/MessageQueue;
   0      49      1    z       Ljava/lang/Object;
   0      49      2    f       Lscala/Function2;
   2      23      3    acc       Ljava/lang/Object;
   26      23      3    acc       Ljava/lang/Object;
   8      17      4    curr       Lscala/actors/MessageQueueElement;
   26      23      4    curr       Lscala/actors/MessageQueueElement;

  Signature: length = 0x2
   00 FFFFFFB9 

public void foreach(scala.Function2);
  Signature: (Lscala/Function2;)V
  Code:
   Stack=3, Locals=3, Args_size=2
	aload_0
	invokevirtual	Method first:()Lscala/actors/MessageQueueElement;
	astore_2
l3	aload_2
	dup
	pop
	ifnull	l1 // return
	aload_2
	aconst_null
	invokevirtual	Method java/lang/Object.equals:(Ljava/lang/Object;)Z
	ifeq	l2 // aload_1
l1	return
l2	aload_1
	aload_2
	invokevirtual	Method scala/actors/MessageQueueElement.msg:()Ljava/lang/Object;
	aload_2
	invokevirtual	Method scala/actors/MessageQueueElement.session:()Lscala/actors/OutputChannel;
	invokeinterface	InterfaceMethod scala/Function2.apply:(Ljava/lang/Object;Ljava/lang/Object;)Ljava/lang/Object;
	pop
	aload_2
	invokevirtual	Method scala/actors/MessageQueueElement.next:()Lscala/actors/MessageQueueElement;
	astore_2
	goto	l3 // aload_2
  Labels:
   	l3 = 5 // aload_2
   	l1 = 19 // return
   	l2 = 20 // aload_1
  LocalVariableTable: 
   Start  Length  Slot  Name   Signature
   0      43      0    this       Lscala/actors/MessageQueue;
   0      43      1    f       Lscala/Function2;
   5      38      2    curr       Lscala/actors/MessageQueueElement;

  Signature: length = 0x2
   00 FFFFFFBC 

public void append(java.lang.Object, scala.actors.OutputChannel);
  Signature: (Ljava/lang/Object;Lscala/actors/OutputChannel;)V
  Code:
   Stack=4, Locals=4, Args_size=3
	aload_0
	iconst_1
	invokevirtual	Method changeSize:(I)V
	new	class scala/actors/MessageQueueElement
	dup
	aload_1
	aload_2
	invokespecial	Method scala/actors/MessageQueueElement."<init>":(Ljava/lang/Object;Lscala/actors/OutputChannel;)V
	astore_3
	aload_0
	invokevirtual	Method isEmpty:()Z
	ifeq	l1 // aload_0
	aload_0
	aload_3
	invokevirtual	Method first_$eq:(Lscala/actors/MessageQueueElement;)V
	goto	l2 // aload_0
l1	aload_0
	invokevirtual	Method last:()Lscala/actors/MessageQueueElement;
	aload_3
	invokevirtual	Method scala/actors/MessageQueueElement.next_$eq:(Lscala/actors/MessageQueueElement;)V
l2	aload_0
	aload_3
	invokevirtual	Method last_$eq:(Lscala/actors/MessageQueueElement;)V
	return
  Labels:
   	l1 = 30 // aload_0
   	l2 = 38 // aload_0
  LocalVariableTable: 
   Start  Length  Slot  Name   Signature
   0      44      0    this       Lscala/actors/MessageQueue;
   0      44      1    msg       Ljava/lang/Object;
   0      44      2    session       Lscala/actors/OutputChannel;
   15      28      3    el       Lscala/actors/MessageQueueElement;

  Signature: length = 0x2
   00 FFFFFFC2 

public void changeSize(int);
  Signature: (I)V
  Code:
   Stack=3, Locals=2, Args_size=2
	aload_0
	aload_0
	invokespecial	Method _size:()I
	iload_1
	iadd
	invokespecial	Method _size_$eq:(I)V
	return
  Labels:
  LocalVariableTable: 
   Start  Length  Slot  Name   Signature
   0      11      0    this       Lscala/actors/MessageQueue;
   0      11      1    diff       I


public final boolean isEmpty();
  Signature: ()Z
  Code:
   Stack=1, Locals=1, Args_size=1
	aload_0
	invokevirtual	Method last:()Lscala/actors/MessageQueueElement;
	ifnonnull	l1 // iconst_0
	iconst_1
	goto	l2 // ireturn
l1	iconst_0
l2	ireturn
  Labels:
   	l1 = 11 // iconst_0
   	l2 = 12 // ireturn

public int size();
  Signature: ()I
  Code:
   Stack=1, Locals=1, Args_size=1
	aload_0
	invokespecial	Method _size:()I
	ireturn
  Labels:

private void _size_$eq(int);
  Signature: (I)V
  Code:
   Stack=2, Locals=2, Args_size=2
	aload_0
	iload_1
	putfield	Field _size:I
	return
  Labels:

private int _size();
  Signature: ()I
  Code:
   Stack=1, Locals=1, Args_size=1
	aload_0
	getfield	Field _size:I
	ireturn
  Labels:

public void last_$eq(scala.actors.MessageQueueElement);
  Signature: (Lscala/actors/MessageQueueElement;)V
  Code:
   Stack=2, Locals=2, Args_size=2
	aload_0
	aload_1
	putfield	Field last:Lscala/actors/MessageQueueElement;
	return
  Labels:

public scala.actors.MessageQueueElement last();
  Signature: ()Lscala/actors/MessageQueueElement;
  Code:
   Stack=1, Locals=1, Args_size=1
	aload_0
	getfield	Field last:Lscala/actors/MessageQueueElement;
	areturn
  Labels:

public void first_$eq(scala.actors.MessageQueueElement);
  Signature: (Lscala/actors/MessageQueueElement;)V
  Code:
   Stack=2, Locals=2, Args_size=2
	aload_0
	aload_1
	putfield	Field first:Lscala/actors/MessageQueueElement;
	return
  Labels:

public scala.actors.MessageQueueElement first();
  Signature: ()Lscala/actors/MessageQueueElement;
  Code:
   Stack=1, Locals=1, Args_size=1
	aload_0
	getfield	Field first:Lscala/actors/MessageQueueElement;
	areturn
  Labels:

public java.lang.String label();
  Signature: ()Ljava/lang/String;
  Code:
   Stack=1, Locals=1, Args_size=1
	aload_0
	getfield	Field label:Ljava/lang/String;
	areturn
  Labels:

}

