Compiled from "MessageQueue.scala"
public abstract class scala.actors.MessageQueueTracer$class extends java.lang.Object
  SourceFile: "MessageQueue.scala"
  Scala: length = 0x
   
  minor version: 0
  major version: 49
  Constant pool:
Asciz	SourceFile;
Asciz	MessageQueue.scala;
Asciz	append;
Asciz	(Lscala/actors/MessageQueueTracer;Ljava/lang/Object;Lscala/actors/OutputChannel;)V;
Asciz	Code;
Asciz	LineNumberTable;
Asciz	scala/actors/MessageQueueTracer;
class	scala/actors/MessageQueueTracer
Asciz	scala$actors$MessageQueueTracer$$super$append;
Asciz	(Ljava/lang/Object;Lscala/actors/OutputChannel;)V;
NameAndType	scala$actors$MessageQueueTracer$$super$append:(Ljava/lang/Object;Lscala/actors/OutputChannel;)V
InterfaceMethod	scala/actors/MessageQueueTracer.scala$actors$MessageQueueTracer$$super$append:(Ljava/lang/Object;Lscala/actors/OutputChannel;)V
Asciz	scala/Predef$;
class	scala/Predef$
Asciz	MODULE$;
Asciz	Lscala/Predef$;;
NameAndType	MODULE$:Lscala/Predef$;
Field	scala/Predef$.MODULE$:Lscala/Predef$;
Asciz	APPEND %s;
String	APPEND %s
Asciz	augmentString;
Asciz	(Ljava/lang/String;)Lscala/collection/immutable/StringOps;;
NameAndType	augmentString:(Ljava/lang/String;)Lscala/collection/immutable/StringOps;
Method	scala/Predef$.augmentString:(Ljava/lang/String;)Lscala/collection/immutable/StringOps;
Asciz	java/lang/Object;
class	java/lang/Object
Asciz	genericWrapArray;
Asciz	(Ljava/lang/Object;)Lscala/collection/mutable/WrappedArray;;
NameAndType	genericWrapArray:(Ljava/lang/Object;)Lscala/collection/mutable/WrappedArray;
Method	scala/Predef$.genericWrapArray:(Ljava/lang/Object;)Lscala/collection/mutable/WrappedArray;
Asciz	scala/collection/immutable/StringLike;
class	scala/collection/immutable/StringLike
Asciz	format;
Asciz	(Lscala/collection/Seq;)Ljava/lang/String;;
NameAndType	format:(Lscala/collection/Seq;)Ljava/lang/String;
InterfaceMethod	scala/collection/immutable/StringLike.format:(Lscala/collection/Seq;)Ljava/lang/String;
Asciz	scala/actors/MessageQueueTracer$class;
class	scala/actors/MessageQueueTracer$class
Asciz	printQueue;
Asciz	(Lscala/actors/MessageQueueTracer;Ljava/lang/String;)V;
NameAndType	printQueue:(Lscala/actors/MessageQueueTracer;Ljava/lang/String;)V
Method	scala/actors/MessageQueueTracer$class.printQueue:(Lscala/actors/MessageQueueTracer;Ljava/lang/String;)V
Asciz	$this;
Asciz	Lscala/actors/MessageQueueTracer;;
Asciz	msg;
Asciz	Ljava/lang/Object;;
Asciz	session;
Asciz	Lscala/actors/OutputChannel;;
Asciz	LocalVariableTable;
Asciz	get;
Asciz	(Lscala/actors/MessageQueueTracer;ILscala/Function1;)Lscala/Option;;
Asciz	scala$actors$MessageQueueTracer$$super$get;
Asciz	(ILscala/Function1;)Lscala/Option;;
NameAndType	scala$actors$MessageQueueTracer$$super$get:(ILscala/Function1;)Lscala/Option;
InterfaceMethod	scala/actors/MessageQueueTracer.scala$actors$MessageQueueTracer$$super$get:(ILscala/Function1;)Lscala/Option;
Asciz	GET %s;
String	GET %s
Asciz	n;
Asciz	I;
Asciz	p;
Asciz	Lscala/Function1;;
Asciz	res;
Asciz	Lscala/Option;;
Asciz	remove;
Asciz	(Lscala/actors/MessageQueueTracer;ILscala/Function2;)Lscala/Option;;
Asciz	scala$actors$MessageQueueTracer$$super$remove;
Asciz	(ILscala/Function2;)Lscala/Option;;
NameAndType	scala$actors$MessageQueueTracer$$super$remove:(ILscala/Function2;)Lscala/Option;
InterfaceMethod	scala/actors/MessageQueueTracer.scala$actors$MessageQueueTracer$$super$remove:(ILscala/Function2;)Lscala/Option;
Asciz	REMOVE %s;
String	REMOVE %s
Asciz	Lscala/Function2;;
Asciz	extractFirst;
Asciz	(Lscala/actors/MessageQueueTracer;Lscala/Function2;)Lscala/actors/MQueueElement;;
Asciz	scala$actors$MessageQueueTracer$$super$extractFirst;
Asciz	(Lscala/Function2;)Lscala/actors/MQueueElement;;
NameAndType	scala$actors$MessageQueueTracer$$super$extractFirst:(Lscala/Function2;)Lscala/actors/MQueueElement;
InterfaceMethod	scala/actors/MessageQueueTracer.scala$actors$MessageQueueTracer$$super$extractFirst:(Lscala/Function2;)Lscala/actors/MQueueElement;
Asciz	EXTRACT_FIRST %s;
String	EXTRACT_FIRST %s
Asciz	Lscala/actors/MQueueElement;;
Asciz	[%s size=%d] [%s] first = %s, last = %s;
String	[%s size=%d] [%s] first = %s, last = %s
Asciz	scala/actors/MQueue;
class	scala/actors/MQueue
Asciz	size;
Asciz	()I;
NameAndType	size:()I
Method	scala/actors/MQueue.size:()I
Asciz	scala/runtime/BoxesRunTime;
class	scala/runtime/BoxesRunTime
Asciz	boxToInteger;
Asciz	(I)Ljava/lang/Integer;;
NameAndType	boxToInteger:(I)Ljava/lang/Integer;
Method	scala/runtime/BoxesRunTime.boxToInteger:(I)Ljava/lang/Integer;
Asciz	firstMsg$1;
Asciz	(Lscala/actors/MessageQueueTracer;)Ljava/lang/Object;;
NameAndType	firstMsg$1:(Lscala/actors/MessageQueueTracer;)Ljava/lang/Object;
Method	scala/actors/MessageQueueTracer$class.firstMsg$1:(Lscala/actors/MessageQueueTracer;)Ljava/lang/Object;
Asciz	lastMsg$1;
NameAndType	lastMsg$1:(Lscala/actors/MessageQueueTracer;)Ljava/lang/Object;
Method	scala/actors/MessageQueueTracer$class.lastMsg$1:(Lscala/actors/MessageQueueTracer;)Ljava/lang/Object;
Asciz	println;
Asciz	(Ljava/lang/Object;)V;
NameAndType	println:(Ljava/lang/Object;)V
Method	scala/Predef$.println:(Ljava/lang/Object;)V
Asciz	Ljava/lang/String;;
Asciz	toString;
Asciz	(Lscala/actors/MessageQueueTracer;)Ljava/lang/String;;
Asciz	%s:%d;
String	%s:%d
Asciz	label;
Asciz	()Ljava/lang/String;;
NameAndType	label:()Ljava/lang/String;
Method	scala/actors/MQueue.label:()Ljava/lang/String;
Asciz	scala$actors$MessageQueueTracer$$queueNumber;
NameAndType	scala$actors$MessageQueueTracer$$queueNumber:()I
InterfaceMethod	scala/actors/MessageQueueTracer.scala$actors$MessageQueueTracer$$queueNumber:()I
Asciz	first;
Asciz	()Lscala/actors/MQueueElement;;
NameAndType	first:()Lscala/actors/MQueueElement;
Method	scala/actors/MQueue.first:()Lscala/actors/MQueueElement;
Asciz	null;
String	null
Asciz	scala/actors/MQueueElement;
class	scala/actors/MQueueElement
Asciz	()Ljava/lang/Object;;
NameAndType	msg:()Ljava/lang/Object;
Method	scala/actors/MQueueElement.msg:()Ljava/lang/Object;
Asciz	last;
NameAndType	last:()Lscala/actors/MQueueElement;
Method	scala/actors/MQueue.last:()Lscala/actors/MQueueElement;
Asciz	$init$;
Asciz	(Lscala/actors/MessageQueueTracer;)V;
Asciz	scala/actors/MessageQueueTracer$;
class	scala/actors/MessageQueueTracer$
Asciz	Lscala/actors/MessageQueueTracer$;;
NameAndType	MODULE$:Lscala/actors/MessageQueueTracer$;
Field	scala/actors/MessageQueueTracer$.MODULE$:Lscala/actors/MessageQueueTracer$;
Asciz	scala$actors$MessageQueueTracer$$getQueueNumber;
NameAndType	scala$actors$MessageQueueTracer$$getQueueNumber:()I
Method	scala/actors/MessageQueueTracer$.scala$actors$MessageQueueTracer$$getQueueNumber:()I
Asciz	scala$actors$MessageQueueTracer$_setter_$scala$actors$MessageQueueTracer$$queueNumber_$eq;
Asciz	(I)V;
NameAndType	scala$actors$MessageQueueTracer$_setter_$scala$actors$MessageQueueTracer$$queueNumber_$eq:(I)V
InterfaceMethod	scala/actors/MessageQueueTracer.scala$actors$MessageQueueTracer$_setter_$scala$actors$MessageQueueTracer$$queueNumber_$eq:(I)V
Asciz	Scala;

{
public static void append(scala.actors.MessageQueueTracer, java.lang.Object, scala.actors.OutputChannel);
  Signature: (Lscala/actors/MessageQueueTracer;Ljava/lang/Object;Lscala/actors/OutputChannel;)V
  Code:
   Stack=7, Locals=3, Args_size=3
	aload_0
	aload_1
	aload_2
	invokeinterface	InterfaceMethod scala/actors/MessageQueueTracer.scala$actors$MessageQueueTracer$$super$append:(Ljava/lang/Object;Lscala/actors/OutputChannel;)V
	aload_0
	getstatic	Field scala/Predef$.MODULE$:Lscala/Predef$;
	ldc	String APPEND %s
	invokevirtual	Method scala/Predef$.augmentString:(Ljava/lang/String;)Lscala/collection/immutable/StringOps;
	getstatic	Field scala/Predef$.MODULE$:Lscala/Predef$;
	iconst_1
	anewarray	class java/lang/Object
	dup
	iconst_0
	aload_1
	aastore
	invokevirtual	Method scala/Predef$.genericWrapArray:(Ljava/lang/Object;)Lscala/collection/mutable/WrappedArray;
	invokeinterface	InterfaceMethod scala/collection/immutable/StringLike.format:(Lscala/collection/Seq;)Ljava/lang/String;
	invokestatic	Method printQueue:(Lscala/actors/MessageQueueTracer;Ljava/lang/String;)V
	return
  Labels:
  LocalVariableTable: 
   Start  Length  Slot  Name   Signature
   0      40      0    $this       Lscala/actors/MessageQueueTracer;
   0      40      1    msg       Ljava/lang/Object;
   0      40      2    session       Lscala/actors/OutputChannel;


public static scala.Option get(scala.actors.MessageQueueTracer, int, scala.Function1);
  Signature: (Lscala/actors/MessageQueueTracer;ILscala/Function1;)Lscala/Option;
  Code:
   Stack=7, Locals=4, Args_size=3
	aload_0
	iload_1
	aload_2
	invokeinterface	InterfaceMethod scala/actors/MessageQueueTracer.scala$actors$MessageQueueTracer$$super$get:(ILscala/Function1;)Lscala/Option;
	astore_3
	aload_0
	getstatic	Field scala/Predef$.MODULE$:Lscala/Predef$;
	ldc	String GET %s
	invokevirtual	Method scala/Predef$.augmentString:(Ljava/lang/String;)Lscala/collection/immutable/StringOps;
	getstatic	Field scala/Predef$.MODULE$:Lscala/Predef$;
	iconst_1
	anewarray	class java/lang/Object
	dup
	iconst_0
	aload_3
	aastore
	invokevirtual	Method scala/Predef$.genericWrapArray:(Ljava/lang/Object;)Lscala/collection/mutable/WrappedArray;
	invokeinterface	InterfaceMethod scala/collection/immutable/StringLike.format:(Lscala/collection/Seq;)Ljava/lang/String;
	invokestatic	Method printQueue:(Lscala/actors/MessageQueueTracer;Ljava/lang/String;)V
	aload_3
	areturn
  Labels:
  LocalVariableTable: 
   Start  Length  Slot  Name   Signature
   0      42      0    $this       Lscala/actors/MessageQueueTracer;
   0      42      1    n       I
   0      42      2    p       Lscala/Function1;
   9      32      3    res       Lscala/Option;


public static scala.Option remove(scala.actors.MessageQueueTracer, int, scala.Function2);
  Signature: (Lscala/actors/MessageQueueTracer;ILscala/Function2;)Lscala/Option;
  Code:
   Stack=7, Locals=4, Args_size=3
	aload_0
	iload_1
	aload_2
	invokeinterface	InterfaceMethod scala/actors/MessageQueueTracer.scala$actors$MessageQueueTracer$$super$remove:(ILscala/Function2;)Lscala/Option;
	astore_3
	aload_0
	getstatic	Field scala/Predef$.MODULE$:Lscala/Predef$;
	ldc	String REMOVE %s
	invokevirtual	Method scala/Predef$.augmentString:(Ljava/lang/String;)Lscala/collection/immutable/StringOps;
	getstatic	Field scala/Predef$.MODULE$:Lscala/Predef$;
	iconst_1
	anewarray	class java/lang/Object
	dup
	iconst_0
	aload_3
	aastore
	invokevirtual	Method scala/Predef$.genericWrapArray:(Ljava/lang/Object;)Lscala/collection/mutable/WrappedArray;
	invokeinterface	InterfaceMethod scala/collection/immutable/StringLike.format:(Lscala/collection/Seq;)Ljava/lang/String;
	invokestatic	Method printQueue:(Lscala/actors/MessageQueueTracer;Ljava/lang/String;)V
	aload_3
	areturn
  Labels:
  LocalVariableTable: 
   Start  Length  Slot  Name   Signature
   0      42      0    $this       Lscala/actors/MessageQueueTracer;
   0      42      1    n       I
   0      42      2    p       Lscala/Function2;
   9      32      3    res       Lscala/Option;


public static scala.actors.MQueueElement extractFirst(scala.actors.MessageQueueTracer, scala.Function2);
  Signature: (Lscala/actors/MessageQueueTracer;Lscala/Function2;)Lscala/actors/MQueueElement;
  Code:
   Stack=7, Locals=3, Args_size=2
	aload_0
	aload_1
	invokeinterface	InterfaceMethod scala/actors/MessageQueueTracer.scala$actors$MessageQueueTracer$$super$extractFirst:(Lscala/Function2;)Lscala/actors/MQueueElement;
	astore_2
	aload_0
	getstatic	Field scala/Predef$.MODULE$:Lscala/Predef$;
	ldc	String EXTRACT_FIRST %s
	invokevirtual	Method scala/Predef$.augmentString:(Ljava/lang/String;)Lscala/collection/immutable/StringOps;
	getstatic	Field scala/Predef$.MODULE$:Lscala/Predef$;
	iconst_1
	anewarray	class java/lang/Object
	dup
	iconst_0
	aload_2
	aastore
	invokevirtual	Method scala/Predef$.genericWrapArray:(Ljava/lang/Object;)Lscala/collection/mutable/WrappedArray;
	invokeinterface	InterfaceMethod scala/collection/immutable/StringLike.format:(Lscala/collection/Seq;)Ljava/lang/String;
	invokestatic	Method printQueue:(Lscala/actors/MessageQueueTracer;Ljava/lang/String;)V
	aload_2
	areturn
  Labels:
  LocalVariableTable: 
   Start  Length  Slot  Name   Signature
   0      41      0    $this       Lscala/actors/MessageQueueTracer;
   0      41      1    p       Lscala/Function2;
   8      32      2    res       Lscala/actors/MQueueElement;


private static void printQueue(scala.actors.MessageQueueTracer, java.lang.String);
  Signature: (Lscala/actors/MessageQueueTracer;Ljava/lang/String;)V
  Code:
   Stack=7, Locals=3, Args_size=2
	getstatic	Field scala/Predef$.MODULE$:Lscala/Predef$;
	getstatic	Field scala/Predef$.MODULE$:Lscala/Predef$;
	ldc	String [%s size=%d] [%s] first = %s, last = %s
	invokevirtual	Method scala/Predef$.augmentString:(Ljava/lang/String;)Lscala/collection/immutable/StringOps;
	getstatic	Field scala/Predef$.MODULE$:Lscala/Predef$;
	iconst_5
	anewarray	class java/lang/Object
	dup
	iconst_0
	aload_0
	aastore
	dup
	iconst_1
	aload_0
	checkcast	class scala/actors/MQueue
	invokevirtual	Method scala/actors/MQueue.size:()I
	istore_2
	iload_2
	invokestatic	Method scala/runtime/BoxesRunTime.boxToInteger:(I)Ljava/lang/Integer;
	aastore
	dup
	iconst_2
	aload_1
	aastore
	dup
	iconst_3
	aload_0
	invokestatic	Method firstMsg$1:(Lscala/actors/MessageQueueTracer;)Ljava/lang/Object;
	aastore
	dup
	iconst_4
	aload_0
	invokestatic	Method lastMsg$1:(Lscala/actors/MessageQueueTracer;)Ljava/lang/Object;
	aastore
	invokevirtual	Method scala/Predef$.genericWrapArray:(Ljava/lang/Object;)Lscala/collection/mutable/WrappedArray;
	invokeinterface	InterfaceMethod scala/collection/immutable/StringLike.format:(Lscala/collection/Seq;)Ljava/lang/String;
	invokevirtual	Method scala/Predef$.println:(Ljava/lang/Object;)V
	return
  Labels:
  LocalVariableTable: 
   Start  Length  Slot  Name   Signature
   0      67      0    $this       Lscala/actors/MessageQueueTracer;
   0      67      1    msg       Ljava/lang/String;


public static java.lang.String toString(scala.actors.MessageQueueTracer);
  Signature: (Lscala/actors/MessageQueueTracer;)Ljava/lang/String;
  Code:
   Stack=6, Locals=2, Args_size=1
	getstatic	Field scala/Predef$.MODULE$:Lscala/Predef$;
	ldc	String %s:%d
	invokevirtual	Method scala/Predef$.augmentString:(Ljava/lang/String;)Lscala/collection/immutable/StringOps;
	getstatic	Field scala/Predef$.MODULE$:Lscala/Predef$;
	iconst_2
	anewarray	class java/lang/Object
	dup
	iconst_0
	aload_0
	checkcast	class scala/actors/MQueue
	invokevirtual	Method scala/actors/MQueue.label:()Ljava/lang/String;
	aastore
	dup
	iconst_1
	aload_0
	invokeinterface	InterfaceMethod scala/actors/MessageQueueTracer.scala$actors$MessageQueueTracer$$queueNumber:()I
	istore_1
	iload_1
	invokestatic	Method scala/runtime/BoxesRunTime.boxToInteger:(I)Ljava/lang/Integer;
	aastore
	invokevirtual	Method scala/Predef$.genericWrapArray:(Ljava/lang/Object;)Lscala/collection/mutable/WrappedArray;
	invokeinterface	InterfaceMethod scala/collection/immutable/StringLike.format:(Lscala/collection/Seq;)Ljava/lang/String;
	areturn
  Labels:
  LocalVariableTable: 
   Start  Length  Slot  Name   Signature
   0      48      0    $this       Lscala/actors/MessageQueueTracer;


private static final java.lang.Object firstMsg$1(scala.actors.MessageQueueTracer);
  Signature: (Lscala/actors/MessageQueueTracer;)Ljava/lang/Object;
  Code:
   Stack=1, Locals=1, Args_size=1
	aload_0
	checkcast	class scala/actors/MQueue
	invokevirtual	Method scala/actors/MQueue.first:()Lscala/actors/MQueueElement;
	ifnonnull	l1 // aload_0
	ldc	String null
	goto	l2 // areturn
l1	aload_0
	checkcast	class scala/actors/MQueue
	invokevirtual	Method scala/actors/MQueue.first:()Lscala/actors/MQueueElement;
	invokevirtual	Method scala/actors/MQueueElement.msg:()Ljava/lang/Object;
l2	areturn
  Labels:
   	l1 = 15 // aload_0
   	l2 = 25 // areturn
  LocalVariableTable: 
   Start  Length  Slot  Name   Signature
   0      26      0    $this       Lscala/actors/MessageQueueTracer;


private static final java.lang.Object lastMsg$1(scala.actors.MessageQueueTracer);
  Signature: (Lscala/actors/MessageQueueTracer;)Ljava/lang/Object;
  Code:
   Stack=1, Locals=1, Args_size=1
	aload_0
	checkcast	class scala/actors/MQueue
	invokevirtual	Method scala/actors/MQueue.last:()Lscala/actors/MQueueElement;
	ifnonnull	l1 // aload_0
	ldc	String null
	goto	l2 // areturn
l1	aload_0
	checkcast	class scala/actors/MQueue
	invokevirtual	Method scala/actors/MQueue.last:()Lscala/actors/MQueueElement;
	invokevirtual	Method scala/actors/MQueueElement.msg:()Ljava/lang/Object;
l2	areturn
  Labels:
   	l1 = 15 // aload_0
   	l2 = 25 // areturn
  LocalVariableTable: 
   Start  Length  Slot  Name   Signature
   0      26      0    $this       Lscala/actors/MessageQueueTracer;


public static void $init$(scala.actors.MessageQueueTracer);
  Signature: (Lscala/actors/MessageQueueTracer;)V
  Code:
   Stack=2, Locals=1, Args_size=1
	aload_0
	getstatic	Field scala/actors/MessageQueueTracer$.MODULE$:Lscala/actors/MessageQueueTracer$;
	invokevirtual	Method scala/actors/MessageQueueTracer$.scala$actors$MessageQueueTracer$$getQueueNumber:()I
	invokeinterface	InterfaceMethod scala/actors/MessageQueueTracer.scala$actors$MessageQueueTracer$_setter_$scala$actors$MessageQueueTracer$$queueNumber_$eq:(I)V
	return
  Labels:
  LocalVariableTable: 
   Start  Length  Slot  Name   Signature
   0      13      0    $this       Lscala/actors/MessageQueueTracer;


}

