Compiled from "MessageQueue.scala"
public final class scala.actors.MessageQueueTracer$ extends java.lang.Object implements scala.ScalaObject
  SourceFile: "MessageQueue.scala"
  Scala: length = 0x
   
  minor version: 0
  major version: 49
  Constant pool:
Asciz	SourceFile;
Asciz	MessageQueue.scala;
Asciz	Scala;
Asciz	MODULE$;
Asciz	Lscala/actors/MessageQueueTracer$;;
Asciz	<clinit>;
Asciz	()V;
Asciz	Code;
Asciz	scala/actors/MessageQueueTracer$;
class	scala/actors/MessageQueueTracer$
Asciz	<init>;
NameAndType	"<init>":()V
Method	scala/actors/MessageQueueTracer$."<init>":()V
Asciz	queueNumberAssigner;
Asciz	I;
Asciz	()I;
Asciz	LineNumberTable;
NameAndType	queueNumberAssigner:I
Field	scala/actors/MessageQueueTracer$.queueNumberAssigner:I
Asciz	queueNumberAssigner_$eq;
Asciz	(I)V;
Asciz	scala$actors$MessageQueueTracer$$getQueueNumber;
NameAndType	queueNumberAssigner:()I
Method	scala/actors/MessageQueueTracer$.queueNumberAssigner:()I
NameAndType	queueNumberAssigner_$eq:(I)V
Method	scala/actors/MessageQueueTracer$.queueNumberAssigner_$eq:(I)V
Asciz	scala/runtime/BoxesRunTime;
class	scala/runtime/BoxesRunTime
Asciz	boxToInteger;
Asciz	(I)Ljava/lang/Integer;;
NameAndType	boxToInteger:(I)Ljava/lang/Integer;
Method	scala/runtime/BoxesRunTime.boxToInteger:(I)Ljava/lang/Integer;
Asciz	unboxToInt;
Asciz	(Ljava/lang/Object;)I;
NameAndType	unboxToInt:(Ljava/lang/Object;)I
Method	scala/runtime/BoxesRunTime.unboxToInt:(Ljava/lang/Object;)I
Asciz	java/lang/Object;
class	java/lang/Object
Method	java/lang/Object."<init>":()V
NameAndType	MODULE$:Lscala/actors/MessageQueueTracer$;
Field	scala/actors/MessageQueueTracer$.MODULE$:Lscala/actors/MessageQueueTracer$;
Asciz	scala/ScalaObject;
class	scala/ScalaObject

{
public static final scala.actors.MessageQueueTracer$ MODULE$;
  Signature: Lscala/actors/MessageQueueTracer$;

private int queueNumberAssigner;
  Signature: I

public static {};
  Signature: ()V
  Code:
   Stack=1, Locals=0, Args_size=0
	new	class scala/actors/MessageQueueTracer$
	invokespecial	Method "<init>":()V
	return
  Labels:

private int queueNumberAssigner();
  Signature: ()I
  Code:
   Stack=1, Locals=1, Args_size=1
	aload_0
	getfield	Field queueNumberAssigner:I
	ireturn
  Labels:

private void queueNumberAssigner_$eq(int);
  Signature: (I)V
  Code:
   Stack=2, Locals=2, Args_size=2
	aload_0
	iload_1
	putfield	Field queueNumberAssigner:I
	return
  Labels:

public final int scala$actors$MessageQueueTracer$$getQueueNumber();
  Signature: ()I
  Code:
   Stack=3, Locals=3, Args_size=1
	aload_0
	dup
	astore_1
	monitorenter
	aload_0
	aload_0
	invokespecial	Method queueNumberAssigner:()I
	iconst_1
	iadd
	invokespecial	Method queueNumberAssigner_$eq:(I)V
	aload_0
	invokespecial	Method queueNumberAssigner:()I
	invokestatic	Method scala/runtime/BoxesRunTime.boxToInteger:(I)Ljava/lang/Integer;
	astore_2
	aload_1
	monitorexit
	aload_2
	invokestatic	Method scala/runtime/BoxesRunTime.unboxToInt:(Ljava/lang/Object;)I
	ireturn
	aload_1
	monitorexit
	athrow
  Labels:
  Exception table:
   from   to  target type
     4    24    29   any

private scala.actors.MessageQueueTracer$();
  Signature: ()V
  Code:
   Stack=2, Locals=1, Args_size=1
	aload_0
	invokespecial	Method java/lang/Object."<init>":()V
	aload_0
	putstatic	Field MODULE$:Lscala/actors/MessageQueueTracer$;
	aload_0
	iconst_0
	putfield	Field queueNumberAssigner:I
	return
  Labels:

}

