Compiled from "MessageQueue.scala"
public abstract class scala.actors.MessageQueueTracer$class extends java.lang.Object
  SourceFile: "MessageQueue.scala"
  Scala: length = 0x
   
  minor version: 0
  major version: 49
  Constant pool:
const #1 = Asciz	SourceFile;
const #2 = Asciz	MessageQueue.scala;
const #3 = Asciz	$init$;
const #4 = Asciz	(Lscala/actors/MessageQueueTracer;)V;
const #5 = Asciz	Code;
const #6 = Asciz	LineNumberTable;
const #7 = Asciz	scala/actors/MessageQueueTracer$;
const #8 = class	#7;	//  scala/actors/MessageQueueTracer$
const #9 = Asciz	MODULE$;
const #10 = Asciz	Lscala/actors/MessageQueueTracer$;;
const #11 = NameAndType	#9:#10;//  MODULE$:Lscala/actors/MessageQueueTracer$;
const #12 = Field	#8.#11;	//  scala/actors/MessageQueueTracer$.MODULE$:Lscala/actors/MessageQueueTracer$;
const #13 = Asciz	scala$actors$MessageQueueTracer$$getQueueNumber;
const #14 = Asciz	()I;
const #15 = NameAndType	#13:#14;//  scala$actors$MessageQueueTracer$$getQueueNumber:()I
const #16 = Method	#8.#15;	//  scala/actors/MessageQueueTracer$.scala$actors$MessageQueueTracer$$getQueueNumber:()I
const #17 = Asciz	scala/actors/MessageQueueTracer;
const #18 = class	#17;	//  scala/actors/MessageQueueTracer
const #19 = Asciz	scala$actors$MessageQueueTracer$_setter_$scala$actors$MessageQueueTracer$$queueNumber_$eq;
const #20 = Asciz	(I)V;
const #21 = NameAndType	#19:#20;//  scala$actors$MessageQueueTracer$_setter_$scala$actors$MessageQueueTracer$$queueNumber_$eq:(I)V
const #22 = InterfaceMethod	#18.#21;	//  scala/actors/MessageQueueTracer.scala$actors$MessageQueueTracer$_setter_$scala$actors$MessageQueueTracer$$queueNumber_$eq:(I)V
const #23 = Asciz	$this;
const #24 = Asciz	Lscala/actors/MessageQueueTracer;;
const #25 = Asciz	LocalVariableTable;
const #26 = Asciz	lastMsg$1;
const #27 = Asciz	(Lscala/actors/MessageQueueTracer;)Ljava/lang/Object;;
const #28 = Asciz	scala/actors/MessageQueue;
const #29 = class	#28;	//  scala/actors/MessageQueue
const #30 = Asciz	last;
const #31 = Asciz	()Lscala/actors/MessageQueueElement;;
const #32 = NameAndType	#30:#31;//  last:()Lscala/actors/MessageQueueElement;
const #33 = Method	#29.#32;	//  scala/actors/MessageQueue.last:()Lscala/actors/MessageQueueElement;
const #34 = Asciz	null;
const #35 = String	#34;	//  null
const #36 = Asciz	scala/actors/MessageQueueElement;
const #37 = class	#36;	//  scala/actors/MessageQueueElement
const #38 = Asciz	msg;
const #39 = Asciz	()Ljava/lang/Object;;
const #40 = NameAndType	#38:#39;//  msg:()Ljava/lang/Object;
const #41 = Method	#37.#40;	//  scala/actors/MessageQueueElement.msg:()Ljava/lang/Object;
const #42 = Asciz	firstMsg$1;
const #43 = Asciz	first;
const #44 = NameAndType	#43:#31;//  first:()Lscala/actors/MessageQueueElement;
const #45 = Method	#29.#44;	//  scala/actors/MessageQueue.first:()Lscala/actors/MessageQueueElement;
const #46 = Asciz	toString;
const #47 = Asciz	(Lscala/actors/MessageQueueTracer;)Ljava/lang/String;;
const #48 = Asciz	scala/Predef$;
const #49 = class	#48;	//  scala/Predef$
const #50 = Asciz	Lscala/Predef$;;
const #51 = NameAndType	#9:#50;//  MODULE$:Lscala/Predef$;
const #52 = Field	#49.#51;	//  scala/Predef$.MODULE$:Lscala/Predef$;
const #53 = Asciz	%s:%d;
const #54 = String	#53;	//  %s:%d
const #55 = Asciz	augmentString;
const #56 = Asciz	(Ljava/lang/String;)Lscala/collection/immutable/StringOps;;
const #57 = NameAndType	#55:#56;//  augmentString:(Ljava/lang/String;)Lscala/collection/immutable/StringOps;
const #58 = Method	#49.#57;	//  scala/Predef$.augmentString:(Ljava/lang/String;)Lscala/collection/immutable/StringOps;
const #59 = Asciz	java/lang/Object;
const #60 = class	#59;	//  java/lang/Object
const #61 = Asciz	label;
const #62 = Asciz	()Ljava/lang/String;;
const #63 = NameAndType	#61:#62;//  label:()Ljava/lang/String;
const #64 = Method	#29.#63;	//  scala/actors/MessageQueue.label:()Ljava/lang/String;
const #65 = Asciz	scala$actors$MessageQueueTracer$$queueNumber;
const #66 = NameAndType	#65:#14;//  scala$actors$MessageQueueTracer$$queueNumber:()I
const #67 = InterfaceMethod	#18.#66;	//  scala/actors/MessageQueueTracer.scala$actors$MessageQueueTracer$$queueNumber:()I
const #68 = Asciz	scala/runtime/BoxesRunTime;
const #69 = class	#68;	//  scala/runtime/BoxesRunTime
const #70 = Asciz	boxToInteger;
const #71 = Asciz	(I)Ljava/lang/Integer;;
const #72 = NameAndType	#70:#71;//  boxToInteger:(I)Ljava/lang/Integer;
const #73 = Method	#69.#72;	//  scala/runtime/BoxesRunTime.boxToInteger:(I)Ljava/lang/Integer;
const #74 = Asciz	genericWrapArray;
const #75 = Asciz	(Ljava/lang/Object;)Lscala/collection/mutable/WrappedArray;;
const #76 = NameAndType	#74:#75;//  genericWrapArray:(Ljava/lang/Object;)Lscala/collection/mutable/WrappedArray;
const #77 = Method	#49.#76;	//  scala/Predef$.genericWrapArray:(Ljava/lang/Object;)Lscala/collection/mutable/WrappedArray;
const #78 = Asciz	scala/collection/immutable/StringLike;
const #79 = class	#78;	//  scala/collection/immutable/StringLike
const #80 = Asciz	format;
const #81 = Asciz	(Lscala/collection/Seq;)Ljava/lang/String;;
const #82 = NameAndType	#80:#81;//  format:(Lscala/collection/Seq;)Ljava/lang/String;
const #83 = InterfaceMethod	#79.#82;	//  scala/collection/immutable/StringLike.format:(Lscala/collection/Seq;)Ljava/lang/String;
const #84 = Asciz	printQueue;
const #85 = Asciz	(Lscala/actors/MessageQueueTracer;Ljava/lang/String;)V;
const #86 = Asciz	[%s size=%d] [%s] first = %s, last = %s;
const #87 = String	#86;	//  [%s size=%d] [%s] first = %s, last = %s
const #88 = Asciz	size;
const #89 = NameAndType	#88:#14;//  size:()I
const #90 = Method	#29.#89;	//  scala/actors/MessageQueue.size:()I
const #91 = Asciz	scala/actors/MessageQueueTracer$class;
const #92 = class	#91;	//  scala/actors/MessageQueueTracer$class
const #93 = NameAndType	#42:#27;//  firstMsg$1:(Lscala/actors/MessageQueueTracer;)Ljava/lang/Object;
const #94 = Method	#92.#93;	//  scala/actors/MessageQueueTracer$class.firstMsg$1:(Lscala/actors/MessageQueueTracer;)Ljava/lang/Object;
const #95 = NameAndType	#26:#27;//  lastMsg$1:(Lscala/actors/MessageQueueTracer;)Ljava/lang/Object;
const #96 = Method	#92.#95;	//  scala/actors/MessageQueueTracer$class.lastMsg$1:(Lscala/actors/MessageQueueTracer;)Ljava/lang/Object;
const #97 = Asciz	println;
const #98 = Asciz	(Ljava/lang/Object;)V;
const #99 = NameAndType	#97:#98;//  println:(Ljava/lang/Object;)V
const #100 = Method	#49.#99;	//  scala/Predef$.println:(Ljava/lang/Object;)V
const #101 = Asciz	Ljava/lang/String;;
const #102 = Asciz	extractFirst;
const #103 = Asciz	(Lscala/actors/MessageQueueTracer;Lscala/Function2;)Lscala/actors/MessageQueueElement;;
const #104 = Asciz	scala$actors$MessageQueueTracer$$super$extractFirst;
const #105 = Asciz	(Lscala/Function2;)Lscala/actors/MessageQueueElement;;
const #106 = NameAndType	#104:#105;//  scala$actors$MessageQueueTracer$$super$extractFirst:(Lscala/Function2;)Lscala/actors/MessageQueueElement;
const #107 = InterfaceMethod	#18.#106;	//  scala/actors/MessageQueueTracer.scala$actors$MessageQueueTracer$$super$extractFirst:(Lscala/Function2;)Lscala/actors/MessageQueueElement;
const #108 = Asciz	EXTRACT_FIRST %s;
const #109 = String	#108;	//  EXTRACT_FIRST %s
const #110 = NameAndType	#84:#85;//  printQueue:(Lscala/actors/MessageQueueTracer;Ljava/lang/String;)V
const #111 = Method	#92.#110;	//  scala/actors/MessageQueueTracer$class.printQueue:(Lscala/actors/MessageQueueTracer;Ljava/lang/String;)V
const #112 = Asciz	p;
const #113 = Asciz	Lscala/Function2;;
const #114 = Asciz	res;
const #115 = Asciz	Lscala/actors/MessageQueueElement;;
const #116 = Asciz	remove;
const #117 = Asciz	(Lscala/actors/MessageQueueTracer;ILscala/Function2;)Lscala/Option;;
const #118 = Asciz	scala$actors$MessageQueueTracer$$super$remove;
const #119 = Asciz	(ILscala/Function2;)Lscala/Option;;
const #120 = NameAndType	#118:#119;//  scala$actors$MessageQueueTracer$$super$remove:(ILscala/Function2;)Lscala/Option;
const #121 = InterfaceMethod	#18.#120;	//  scala/actors/MessageQueueTracer.scala$actors$MessageQueueTracer$$super$remove:(ILscala/Function2;)Lscala/Option;
const #122 = Asciz	REMOVE %s;
const #123 = String	#122;	//  REMOVE %s
const #124 = Asciz	n;
const #125 = Asciz	I;
const #126 = Asciz	Lscala/Option;;
const #127 = Asciz	get;
const #128 = Asciz	(Lscala/actors/MessageQueueTracer;ILscala/Function1;)Lscala/Option;;
const #129 = Asciz	scala$actors$MessageQueueTracer$$super$get;
const #130 = Asciz	(ILscala/Function1;)Lscala/Option;;
const #131 = NameAndType	#129:#130;//  scala$actors$MessageQueueTracer$$super$get:(ILscala/Function1;)Lscala/Option;
const #132 = InterfaceMethod	#18.#131;	//  scala/actors/MessageQueueTracer.scala$actors$MessageQueueTracer$$super$get:(ILscala/Function1;)Lscala/Option;
const #133 = Asciz	GET %s;
const #134 = String	#133;	//  GET %s
const #135 = Asciz	Lscala/Function1;;
const #136 = Asciz	append;
const #137 = Asciz	(Lscala/actors/MessageQueueTracer;Ljava/lang/Object;Lscala/actors/OutputChannel;)V;
const #138 = Asciz	scala$actors$MessageQueueTracer$$super$append;
const #139 = Asciz	(Ljava/lang/Object;Lscala/actors/OutputChannel;)V;
const #140 = NameAndType	#138:#139;//  scala$actors$MessageQueueTracer$$super$append:(Ljava/lang/Object;Lscala/actors/OutputChannel;)V
const #141 = InterfaceMethod	#18.#140;	//  scala/actors/MessageQueueTracer.scala$actors$MessageQueueTracer$$super$append:(Ljava/lang/Object;Lscala/actors/OutputChannel;)V
const #142 = Asciz	APPEND %s;
const #143 = String	#142;	//  APPEND %s
const #144 = Asciz	Ljava/lang/Object;;
const #145 = Asciz	session;
const #146 = Asciz	Lscala/actors/OutputChannel;;
const #147 = Asciz	Scala;

{
public static void $init$(scala.actors.MessageQueueTracer);
  Code:
   Stack=2, Locals=1, Args_size=1
   0:	aload_0
   1:	getstatic	#12; //Field scala/actors/MessageQueueTracer$.MODULE$:Lscala/actors/MessageQueueTracer$;
   4:	invokevirtual	#16; //Method scala/actors/MessageQueueTracer$.scala$actors$MessageQueueTracer$$getQueueNumber:()I
   7:	invokeinterface	#22,  2; //InterfaceMethod scala/actors/MessageQueueTracer.scala$actors$MessageQueueTracer$_setter_$scala$actors$MessageQueueTracer$$queueNumber_$eq:(I)V
   12:	return
  LineNumberTable: 
   line 153: 0

  LocalVariableTable: 
   Start  Length  Slot  Name   Signature
   0      13      0    $this       Lscala/actors/MessageQueueTracer;


public static java.lang.String toString(scala.actors.MessageQueueTracer);
  Code:
   Stack=6, Locals=2, Args_size=1
   0:	getstatic	#52; //Field scala/Predef$.MODULE$:Lscala/Predef$;
   3:	ldc	#54; //String %s:%d
   5:	invokevirtual	#58; //Method scala/Predef$.augmentString:(Ljava/lang/String;)Lscala/collection/immutable/StringOps;
   8:	getstatic	#52; //Field scala/Predef$.MODULE$:Lscala/Predef$;
   11:	iconst_2
   12:	anewarray	#60; //class java/lang/Object
   15:	dup
   16:	iconst_0
   17:	aload_0
   18:	checkcast	#29; //class scala/actors/MessageQueue
   21:	invokevirtual	#64; //Method scala/actors/MessageQueue.label:()Ljava/lang/String;
   24:	aastore
   25:	dup
   26:	iconst_1
   27:	aload_0
   28:	invokeinterface	#67,  1; //InterfaceMethod scala/actors/MessageQueueTracer.scala$actors$MessageQueueTracer$$queueNumber:()I
   33:	istore_1
   34:	iload_1
   35:	invokestatic	#73; //Method scala/runtime/BoxesRunTime.boxToInteger:(I)Ljava/lang/Integer;
   38:	aastore
   39:	invokevirtual	#77; //Method scala/Predef$.genericWrapArray:(Ljava/lang/Object;)Lscala/collection/mutable/WrappedArray;
   42:	invokeinterface	#83,  2; //InterfaceMethod scala/collection/immutable/StringLike.format:(Lscala/collection/Seq;)Ljava/lang/String;
   47:	areturn
  LineNumberTable: 
   line 181: 0

  LocalVariableTable: 
   Start  Length  Slot  Name   Signature
   0      48      0    $this       Lscala/actors/MessageQueueTracer;


public static scala.actors.MessageQueueElement extractFirst(scala.actors.MessageQueueTracer, scala.Function2);
  Code:
   Stack=7, Locals=3, Args_size=2
   0:	aload_0
   1:	aload_1
   2:	invokeinterface	#107,  2; //InterfaceMethod scala/actors/MessageQueueTracer.scala$actors$MessageQueueTracer$$super$extractFirst:(Lscala/Function2;)Lscala/actors/MessageQueueElement;
   7:	astore_2
   8:	aload_0
   9:	getstatic	#52; //Field scala/Predef$.MODULE$:Lscala/Predef$;
   12:	ldc	#109; //String EXTRACT_FIRST %s
   14:	invokevirtual	#58; //Method scala/Predef$.augmentString:(Ljava/lang/String;)Lscala/collection/immutable/StringOps;
   17:	getstatic	#52; //Field scala/Predef$.MODULE$:Lscala/Predef$;
   20:	iconst_1
   21:	anewarray	#60; //class java/lang/Object
   24:	dup
   25:	iconst_0
   26:	aload_2
   27:	aastore
   28:	invokevirtual	#77; //Method scala/Predef$.genericWrapArray:(Ljava/lang/Object;)Lscala/collection/mutable/WrappedArray;
   31:	invokeinterface	#83,  2; //InterfaceMethod scala/collection/immutable/StringLike.format:(Lscala/collection/Seq;)Ljava/lang/String;
   36:	invokestatic	#111; //Method printQueue:(Lscala/actors/MessageQueueTracer;Ljava/lang/String;)V
   39:	aload_2
   40:	areturn
  LineNumberTable: 
   line 170: 0
   line 171: 8
   line 172: 39

  LocalVariableTable: 
   Start  Length  Slot  Name   Signature
   0      41      0    $this       Lscala/actors/MessageQueueTracer;
   0      41      1    p       Lscala/Function2;
   8      32      2    res       Lscala/actors/MessageQueueElement;


public static scala.Option remove(scala.actors.MessageQueueTracer, int, scala.Function2);
  Code:
   Stack=7, Locals=4, Args_size=3
   0:	aload_0
   1:	iload_1
   2:	aload_2
   3:	invokeinterface	#121,  3; //InterfaceMethod scala/actors/MessageQueueTracer.scala$actors$MessageQueueTracer$$super$remove:(ILscala/Function2;)Lscala/Option;
   8:	astore_3
   9:	aload_0
   10:	getstatic	#52; //Field scala/Predef$.MODULE$:Lscala/Predef$;
   13:	ldc	#123; //String REMOVE %s
   15:	invokevirtual	#58; //Method scala/Predef$.augmentString:(Ljava/lang/String;)Lscala/collection/immutable/StringOps;
   18:	getstatic	#52; //Field scala/Predef$.MODULE$:Lscala/Predef$;
   21:	iconst_1
   22:	anewarray	#60; //class java/lang/Object
   25:	dup
   26:	iconst_0
   27:	aload_3
   28:	aastore
   29:	invokevirtual	#77; //Method scala/Predef$.genericWrapArray:(Ljava/lang/Object;)Lscala/collection/mutable/WrappedArray;
   32:	invokeinterface	#83,  2; //InterfaceMethod scala/collection/immutable/StringLike.format:(Lscala/collection/Seq;)Ljava/lang/String;
   37:	invokestatic	#111; //Method printQueue:(Lscala/actors/MessageQueueTracer;Ljava/lang/String;)V
   40:	aload_3
   41:	areturn
  LineNumberTable: 
   line 165: 0
   line 166: 9
   line 167: 40

  LocalVariableTable: 
   Start  Length  Slot  Name   Signature
   0      42      0    $this       Lscala/actors/MessageQueueTracer;
   0      42      1    n       I
   0      42      2    p       Lscala/Function2;
   9      32      3    res       Lscala/Option;


public static scala.Option get(scala.actors.MessageQueueTracer, int, scala.Function1);
  Code:
   Stack=7, Locals=4, Args_size=3
   0:	aload_0
   1:	iload_1
   2:	aload_2
   3:	invokeinterface	#132,  3; //InterfaceMethod scala/actors/MessageQueueTracer.scala$actors$MessageQueueTracer$$super$get:(ILscala/Function1;)Lscala/Option;
   8:	astore_3
   9:	aload_0
   10:	getstatic	#52; //Field scala/Predef$.MODULE$:Lscala/Predef$;
   13:	ldc	#134; //String GET %s
   15:	invokevirtual	#58; //Method scala/Predef$.augmentString:(Ljava/lang/String;)Lscala/collection/immutable/StringOps;
   18:	getstatic	#52; //Field scala/Predef$.MODULE$:Lscala/Predef$;
   21:	iconst_1
   22:	anewarray	#60; //class java/lang/Object
   25:	dup
   26:	iconst_0
   27:	aload_3
   28:	aastore
   29:	invokevirtual	#77; //Method scala/Predef$.genericWrapArray:(Ljava/lang/Object;)Lscala/collection/mutable/WrappedArray;
   32:	invokeinterface	#83,  2; //InterfaceMethod scala/collection/immutable/StringLike.format:(Lscala/collection/Seq;)Ljava/lang/String;
   37:	invokestatic	#111; //Method printQueue:(Lscala/actors/MessageQueueTracer;Ljava/lang/String;)V
   40:	aload_3
   41:	areturn
  LineNumberTable: 
   line 160: 0
   line 161: 9
   line 162: 40

  LocalVariableTable: 
   Start  Length  Slot  Name   Signature
   0      42      0    $this       Lscala/actors/MessageQueueTracer;
   0      42      1    n       I
   0      42      2    p       Lscala/Function1;
   9      32      3    res       Lscala/Option;


public static void append(scala.actors.MessageQueueTracer, java.lang.Object, scala.actors.OutputChannel);
  Code:
   Stack=7, Locals=3, Args_size=3
   0:	aload_0
   1:	aload_1
   2:	aload_2
   3:	invokeinterface	#141,  3; //InterfaceMethod scala/actors/MessageQueueTracer.scala$actors$MessageQueueTracer$$super$append:(Ljava/lang/Object;Lscala/actors/OutputChannel;)V
   8:	aload_0
   9:	getstatic	#52; //Field scala/Predef$.MODULE$:Lscala/Predef$;
   12:	ldc	#143; //String APPEND %s
   14:	invokevirtual	#58; //Method scala/Predef$.augmentString:(Ljava/lang/String;)Lscala/collection/immutable/StringOps;
   17:	getstatic	#52; //Field scala/Predef$.MODULE$:Lscala/Predef$;
   20:	iconst_1
   21:	anewarray	#60; //class java/lang/Object
   24:	dup
   25:	iconst_0
   26:	aload_1
   27:	aastore
   28:	invokevirtual	#77; //Method scala/Predef$.genericWrapArray:(Ljava/lang/Object;)Lscala/collection/mutable/WrappedArray;
   31:	invokeinterface	#83,  2; //InterfaceMethod scala/collection/immutable/StringLike.format:(Lscala/collection/Seq;)Ljava/lang/String;
   36:	invokestatic	#111; //Method printQueue:(Lscala/actors/MessageQueueTracer;Ljava/lang/String;)V
   39:	return
  LineNumberTable: 
   line 156: 0
   line 157: 8

  LocalVariableTable: 
   Start  Length  Slot  Name   Signature
   0      40      0    $this       Lscala/actors/MessageQueueTracer;
   0      40      1    msg       Ljava/lang/Object;
   0      40      2    session       Lscala/actors/OutputChannel;


}

