Compiled from "MessageQueue.scala"
public final class scala.actors.MQueue$$anonfun$remove$1 extends scala.runtime.AbstractFunction1 implements java.io.Serializable
  SourceFile: "MessageQueue.scala"
  Scala: length = 0x
   
  InnerClass: 
   public final $anonfun$remove$1=class scala/actors/MQueue$$anonfun$remove$1 of class scala/actors/MQueue
  minor version: 0
  major version: 49
  Constant pool:
Asciz	SourceFile;
Asciz	MessageQueue.scala;
Asciz	<clinit>;
Asciz	()V;
Asciz	Code;
Asciz	serialVersionUID;
Asciz	J;
Asciz	scala/actors/MQueue$$anonfun$remove$1;
class	scala/actors/MQueue$$anonfun$remove$1
NameAndType	serialVersionUID:J
Field	scala/actors/MQueue$$anonfun$remove$1.serialVersionUID:J
Asciz	<init>;
Asciz	(Lscala/actors/MQueue;)V;
Asciz	LineNumberTable;
Asciz	scala/runtime/AbstractFunction1;
class	scala/runtime/AbstractFunction1
NameAndType	"<init>":()V
Method	scala/runtime/AbstractFunction1."<init>":()V
Asciz	this;
Asciz	Lscala/actors/MQueue$$anonfun$remove$1;;
Asciz	$outer;
Asciz	Lscala/actors/MQueue;;
Asciz	LocalVariableTable;
Asciz	apply;
Asciz	(Ljava/lang/Object;)Ljava/lang/Object;;
Asciz	scala/actors/MQueueElement;
class	scala/actors/MQueueElement
Asciz	(Lscala/actors/MQueueElement;)Lscala/Tuple2;;
NameAndType	apply:(Lscala/actors/MQueueElement;)Lscala/Tuple2;
Method	scala/actors/MQueue$$anonfun$remove$1.apply:(Lscala/actors/MQueueElement;)Lscala/Tuple2;
Asciz	v1;
Asciz	Ljava/lang/Object;;
Asciz	scala/Tuple2;
class	scala/Tuple2
Asciz	msg;
Asciz	()Ljava/lang/Object;;
NameAndType	msg:()Ljava/lang/Object;
Method	scala/actors/MQueueElement.msg:()Ljava/lang/Object;
Asciz	session;
Asciz	()Lscala/actors/OutputChannel;;
NameAndType	session:()Lscala/actors/OutputChannel;
Method	scala/actors/MQueueElement.session:()Lscala/actors/OutputChannel;
Asciz	(Ljava/lang/Object;Ljava/lang/Object;)V;
NameAndType	"<init>":(Ljava/lang/Object;Ljava/lang/Object;)V
Method	scala/Tuple2."<init>":(Ljava/lang/Object;Ljava/lang/Object;)V
Asciz	x;
Asciz	Lscala/actors/MQueueElement;;
Asciz	(Lscala/actors/MQueueElement;)Lscala/Tuple2<Ljava/lang/Object;Lscala/actors/OutputChannel<Ljava/lang/Object;>;>;;
Asciz	Signature;
Asciz	Scala;
Asciz	InnerClasses;
Asciz	scala/actors/MQueue;
class	scala/actors/MQueue
Asciz	$anonfun$remove$1;
Asciz	java/io/Serializable;
class	java/io/Serializable

{
public static final long serialVersionUID;
  Signature: J

public static {};
  Signature: ()V
  Code:
   Stack=2, Locals=0, Args_size=0
	lconst_0
	putstatic	Field serialVersionUID:J
	return
  Labels:

public scala.actors.MQueue$$anonfun$remove$1(scala.actors.MQueue);
  Signature: (Lscala/actors/MQueue;)V
  Code:
   Stack=1, Locals=2, Args_size=2
	aload_0
	invokespecial	Method scala/runtime/AbstractFunction1."<init>":()V
	return
  Labels:
  LocalVariableTable: 
   Start  Length  Slot  Name   Signature
   0      5      0    this       Lscala/actors/MQueue$$anonfun$remove$1;
   0      5      1    $outer       Lscala/actors/MQueue;


public final java.lang.Object apply(java.lang.Object);
  Signature: (Ljava/lang/Object;)Ljava/lang/Object;
  Code:
   Stack=2, Locals=2, Args_size=2
	aload_0
	aload_1
	checkcast	class scala/actors/MQueueElement
	invokevirtual	Method apply:(Lscala/actors/MQueueElement;)Lscala/Tuple2;
	areturn
  Labels:
  LocalVariableTable: 
   Start  Length  Slot  Name   Signature
   0      9      0    this       Lscala/actors/MQueue$$anonfun$remove$1;
   0      9      1    v1       Ljava/lang/Object;


public final scala.Tuple2 apply(scala.actors.MQueueElement);
  Signature: (Lscala/actors/MQueueElement;)Lscala/Tuple2;
  Code:
   Stack=4, Locals=2, Args_size=2
	new	class scala/Tuple2
	dup
	aload_1
	invokevirtual	Method scala/actors/MQueueElement.msg:()Ljava/lang/Object;
	aload_1
	invokevirtual	Method scala/actors/MQueueElement.session:()Lscala/actors/OutputChannel;
	invokespecial	Method scala/Tuple2."<init>":(Ljava/lang/Object;Ljava/lang/Object;)V
	areturn
  Labels:
  LocalVariableTable: 
   Start  Length  Slot  Name   Signature
   0      16      0    this       Lscala/actors/MQueue$$anonfun$remove$1;
   0      16      1    x       Lscala/actors/MQueueElement;

  Signature: length = 0x2
   00 30 

}

