Compiled from "MessageQueue.scala"
public class scala.actors.MQueue extends java.lang.Object implements scala.ScalaObject
  SourceFile: "MessageQueue.scala"
  Signature: length = 0x2
   00 FFFFFFD7 
  ScalaSig: length = 0x501
   05 00 FFFFFF81 3D 06 05 01 02 00 02 06 02 06 4D 51 75
   65 75 65 0A 02 03 04 01 06 61 63 74 6F 72 73 0A
   01 05 01 05 73 63 61 6C 61 15 02 07 28 13 03 00
   08 10 10 02 09 0E 0D 01 0A 0A 02 0B 0C 01 04 6C
   61 6E 67 0A 01 0D 01 04 6A 61 76 61 09 02 0F 0A
   02 06 4F 62 6A 65 63 74 10 02 11 12 0D 01 04 09
   02 13 04 02 0B 53 63 61 6C 61 4F 62 6A 65 63 74
   08 08 15 00 FFFFFF82 FFFFFFC2 FFFFFF80 FFFFFF84 08 17 01 05 6C 61 62 65
   6C 03 00 15 01 18 10 02 19 1C 0E 02 11 1A 09 02
   1B 04 01 06 50 72 65 64 65 66 09 02 1D 1E 02 06
   53 74 72 69 6E 67 0A 02 1B 04 08 08 20 00 FFFFFF82 FFFFFF80
   FFFFFFA0 FFFFFF80 04 18 01 06 6C 61 62 65 6C 20 08 05 22 00
   FFFFFF84 00 23 01 06 3C 69 6E 69 74 3E 14 02 24 31 10
   03 25 00 26 0D 01 02 10 02 27 28 0C 00 04 08 29
   00 FFFFFF84 FFFFFF80 FFFFFF80 FFFFFFC2 00 2A 02 03 4D 73 67 11 02 2B 2E
   10 02 11 2C 09 02 2D 04 02 04 4E 75 6C 6C 10 02
   11 2F 09 02 30 04 02 03 41 6E 79 08 05 15 21 FFFFFFC0
   00 18 08 07 33 00 FFFFFFC0 FFFFFF80 FFFFFF84 08 34 01 05 66 69 72
   73 74 15 01 35 10 03 25 36 26 09 02 37 02 02 0D
   4D 51 75 65 75 65 45 6C 65 6D 65 6E 74 08 07 39
   00 FFFFFFC0 FFFFFF80 FFFFFF84 08 3A 01 09 66 69 72 73 74 5F 24 65
   71 14 02 3B 3E 10 02 11 3C 09 02 3D 04 02 04 55
   6E 69 74 08 07 3F 38 FFFFFF81 FFFFFF80 FFFFFFC0 00 35 01 03 78 24
   31 08 06 41 00 FFFFFFA0 FFFFFFA0 04 35 01 06 66 69 72 73 74
   20 08 07 43 00 FFFFFFC0 FFFFFF80 FFFFFF84 08 34 01 04 6C 61 73 74
   08 07 45 00 FFFFFFC0 FFFFFF80 FFFFFF84 08 46 01 08 6C 61 73 74 5F
   24 65 71 14 02 3B 47 08 07 3F 44 FFFFFF81 FFFFFF80 FFFFFFC0 00 35
   08 06 49 00 FFFFFFA0 FFFFFFA0 04 35 01 05 6C 61 73 74 20 08
   07 4B 00 FFFFFFC0 FFFFFF80 FFFFFF84 04 4C 01 05 5F 73 69 7A 65 15
   01 4D 10 02 11 4E 09 02 4F 04 02 03 49 6E 74 08
   07 51 00 FFFFFFC0 FFFFFF80 FFFFFF84 04 52 01 09 5F 73 69 7A 65 5F
   24 65 71 14 02 3B 53 08 07 3F 50 FFFFFF81 FFFFFF80 FFFFFFC0 00 4D
   08 06 55 00 FFFFFFA0 FFFFFFA0 04 4D 01 06 5F 73 69 7A 65 20
   08 05 57 00 FFFFFF84 00 4C 01 04 73 69 7A 65 08 05 59
   00 FFFFFF84 02 5A 01 07 69 73 45 6D 70 74 79 15 01 5B
   10 02 11 5C 09 02 5D 04 02 07 42 6F 6F 6C 65 61
   6E 08 05 5F 00 FFFFFF84 08 60 01 0A 63 68 61 6E 67 65
   53 69 7A 65 14 02 3B 61 08 05 62 5E FFFFFFC0 00 4D 01
   04 64 69 66 66 08 05 64 00 FFFFFF84 00 65 01 06 61 70
   70 65 6E 64 14 03 3B 66 68 08 05 67 63 FFFFFFC0 00 26
   01 03 6D 73 67 08 05 69 63 FFFFFFC0 00 6A 01 07 73 65
   73 73 69 6F 6E 10 03 25 6B 2E 09 02 6C 02 02 0D
   4F 75 74 70 75 74 43 68 61 6E 6E 65 6C 08 05 64
   00 FFFFFF84 00 6E 14 02 3B 6F 08 05 70 6D FFFFFFC0 00 35 01
   02 65 6C 08 05 72 00 FFFFFF84 00 73 01 07 66 6F 72 65
   61 63 68 14 02 3B 74 08 05 75 71 FFFFFFC0 00 76 01 01
   66 10 05 11 77 26 6A 3B 09 02 78 04 02 09 46 75
   6E 63 74 69 6F 6E 32 08 05 7A 00 FFFFFF84 00 7B 01 0D
   66 6F 72 65 61 63 68 41 70 70 65 6E 64 14 02 3B
   7C 08 05 7D 79 FFFFFFC0 00 24 01 06 74 61 72 67 65 74
   08 06 7F 00 FFFFFF84 00 FFFFFF81 00 01 0E 66 6F 72 65 61 63
   68 44 65 71 75 65 75 65 14 03 3B FFFFFF81 01 08 05 7D
   7E FFFFFFC0 00 24 08 07 FFFFFF81 03 00 FFFFFF84 00 FFFFFF81 04 01 08 66
   6F 6C 64 4C 65 66 74 15 04 FFFFFF81 05 FFFFFF81 08 14 04 FFFFFF81
   06 FFFFFF81 10 14 04 FFFFFF81 07 FFFFFF81 0E 10 03 27 FFFFFF81 08 04 0B
   FFFFFF81 09 FFFFFF81 02 FFFFFF84 FFFFFF80 FFFFFF80 FFFFFFC2 00 FFFFFF81 0A 02 01 42 11 03
   FFFFFF81 0B 2E 10 03 11 FFFFFF81 0C 09 03 FFFFFF81 0D 04 02 07 4E
   6F 74 68 69 6E 67 08 07 75 FFFFFF81 02 FFFFFFC0 00 FFFFFF81 0F 10
   07 11 77 FFFFFF81 07 26 FFFFFF81 07 08 08 FFFFFF81 11 FFFFFF81 02 FFFFFFC0 00
   FFFFFF81 07 01 01 7A 08 07 FFFFFF81 13 00 FFFFFF84 00 FFFFFF81 14 01 03
   67 65 74 14 04 FFFFFF81 15 FFFFFF81 1E 14 04 FFFFFF81 16 FFFFFF81 19 10
   04 11 FFFFFF81 17 26 09 03 FFFFFF81 18 04 02 06 4F 70 74 69
   6F 6E 08 08 FFFFFF81 1A FFFFFF81 12 FFFFFFC0 00 FFFFFF81 1B 01 01 70 10
   05 11 FFFFFF81 1C 26 5B 09 03 FFFFFF81 1D 04 02 09 46 75 6E
   63 74 69 6F 6E 31 08 07 FFFFFF81 1F FFFFFF81 12 FFFFFFC0 00 4D 01
   01 6E 08 07 FFFFFF81 21 00 FFFFFF84 00 FFFFFF81 22 01 06 72 65 6D
   6F 76 65 14 04 FFFFFF81 23 FFFFFF81 2A 14 04 FFFFFF81 24 FFFFFF81 28 10
   05 11 FFFFFF81 17 FFFFFF81 25 10 05 11 FFFFFF81 26 26 6A 09 03 FFFFFF81
   27 04 02 06 54 75 70 6C 65 32 08 08 FFFFFF81 1A FFFFFF81 20
   FFFFFFC0 00 FFFFFF81 29 10 05 11 77 26 6A 5B 08 07 FFFFFF81 1F FFFFFF81
   20 FFFFFFC0 00 4D 08 07 FFFFFF81 2C 00 FFFFFF84 00 FFFFFF81 2D 01 0C 65
   78 74 72 61 63 74 46 69 72 73 74 14 03 35 FFFFFF81 2E
   08 08 FFFFFF81 1A FFFFFF81 2B FFFFFFC0 00 FFFFFF81 29 08 07 FFFFFF81 2C 00 FFFFFF84
   00 FFFFFF81 30 14 03 35 FFFFFF81 31 08 08 FFFFFF81 32 FFFFFF81 2F FFFFFFC0 00
   FFFFFF81 33 01 02 70 66 10 05 11 FFFFFF81 34 26 2E 09 03 FFFFFF81
   35 04 02 0F 50 61 72 74 69 61 6C 46 75 6E 63 74
   69 6F 6E 08 07 FFFFFF81 37 00 FFFFFF84 04 FFFFFF81 38 01 0E 72 65
   6D 6F 76 65 49 6E 74 65 72 6E 61 6C 14 04 FFFFFF81 39
   FFFFFF81 3C 14 04 FFFFFF81 3A FFFFFF81 3B 10 04 11 FFFFFF81 17 35 08 08
   FFFFFF81 1A FFFFFF81 36 FFFFFFC0 00 FFFFFF81 29 08 07 FFFFFF81 1F FFFFFF81 36 FFFFFFC0 00
   4D 
  InnerClass: 
   public abstract $less$colon$less=class scala/Predef$$less$colon$less of class scala/Predef
   public final $anonfun$remove$1=class scala/actors/MQueue$$anonfun$remove$1 of class scala/actors/MQueue
  minor version: 0
  major version: 49
  Constant pool:
Asciz	SourceFile;
Asciz	MessageQueue.scala;
Asciz	_size;
Asciz	I;
Asciz	last;
Asciz	Lscala/actors/MQueueElement;;
Asciz	Lscala/actors/MQueueElement<TMsg;>;;
Asciz	Signature;
Asciz	first;
Asciz	label;
Asciz	Ljava/lang/String;;
Asciz	()Ljava/lang/String;;
Asciz	Code;
Asciz	LineNumberTable;
Asciz	scala/actors/MQueue;
class	scala/actors/MQueue
NameAndType	label:Ljava/lang/String;
Field	scala/actors/MQueue.label:Ljava/lang/String;
Asciz	()Lscala/actors/MQueueElement;;
NameAndType	first:Lscala/actors/MQueueElement;
Field	scala/actors/MQueue.first:Lscala/actors/MQueueElement;
Asciz	()Lscala/actors/MQueueElement<TMsg;>;;
Asciz	first_$eq;
Asciz	(Lscala/actors/MQueueElement;)V;
Asciz	(Lscala/actors/MQueueElement<TMsg;>;)V;
NameAndType	last:Lscala/actors/MQueueElement;
Field	scala/actors/MQueue.last:Lscala/actors/MQueueElement;
Asciz	last_$eq;
Asciz	()I;
NameAndType	_size:I
Field	scala/actors/MQueue._size:I
Asciz	_size_$eq;
Asciz	(I)V;
Asciz	size;
NameAndType	_size:()I
Method	scala/actors/MQueue._size:()I
Asciz	isEmpty;
Asciz	()Z;
NameAndType	last:()Lscala/actors/MQueueElement;
Method	scala/actors/MQueue.last:()Lscala/actors/MQueueElement;
Asciz	changeSize;
NameAndType	_size_$eq:(I)V
Method	scala/actors/MQueue._size_$eq:(I)V
Asciz	this;
Asciz	Lscala/actors/MQueue;;
Asciz	diff;
Asciz	LocalVariableTable;
Asciz	append;
Asciz	(Ljava/lang/Object;Lscala/actors/OutputChannel;)V;
NameAndType	changeSize:(I)V
Method	scala/actors/MQueue.changeSize:(I)V
Asciz	scala/actors/MQueueElement;
class	scala/actors/MQueueElement
Asciz	<init>;
NameAndType	"<init>":(Ljava/lang/Object;Lscala/actors/OutputChannel;)V
Method	scala/actors/MQueueElement."<init>":(Ljava/lang/Object;Lscala/actors/OutputChannel;)V
NameAndType	isEmpty:()Z
Method	scala/actors/MQueue.isEmpty:()Z
NameAndType	first_$eq:(Lscala/actors/MQueueElement;)V
Method	scala/actors/MQueue.first_$eq:(Lscala/actors/MQueueElement;)V
Asciz	next_$eq;
NameAndType	next_$eq:(Lscala/actors/MQueueElement;)V
Method	scala/actors/MQueueElement.next_$eq:(Lscala/actors/MQueueElement;)V
NameAndType	last_$eq:(Lscala/actors/MQueueElement;)V
Method	scala/actors/MQueue.last_$eq:(Lscala/actors/MQueueElement;)V
Asciz	msg;
Asciz	Ljava/lang/Object;;
Asciz	session;
Asciz	Lscala/actors/OutputChannel;;
Asciz	el;
Asciz	(TMsg;Lscala/actors/OutputChannel<Ljava/lang/Object;>;)V;
Asciz	foreach;
Asciz	(Lscala/Function2;)V;
NameAndType	first:()Lscala/actors/MQueueElement;
Method	scala/actors/MQueue.first:()Lscala/actors/MQueueElement;
Asciz	java/lang/Object;
class	java/lang/Object
Asciz	equals;
Asciz	(Ljava/lang/Object;)Z;
NameAndType	equals:(Ljava/lang/Object;)Z
Method	java/lang/Object.equals:(Ljava/lang/Object;)Z
Asciz	()Ljava/lang/Object;;
NameAndType	msg:()Ljava/lang/Object;
Method	scala/actors/MQueueElement.msg:()Ljava/lang/Object;
Asciz	()Lscala/actors/OutputChannel;;
NameAndType	session:()Lscala/actors/OutputChannel;
Method	scala/actors/MQueueElement.session:()Lscala/actors/OutputChannel;
Asciz	scala/Function2;
class	scala/Function2
Asciz	apply;
Asciz	(Ljava/lang/Object;Ljava/lang/Object;)Ljava/lang/Object;;
NameAndType	apply:(Ljava/lang/Object;Ljava/lang/Object;)Ljava/lang/Object;
InterfaceMethod	scala/Function2.apply:(Ljava/lang/Object;Ljava/lang/Object;)Ljava/lang/Object;
Asciz	next;
NameAndType	next:()Lscala/actors/MQueueElement;
Method	scala/actors/MQueueElement.next:()Lscala/actors/MQueueElement;
Asciz	f;
Asciz	Lscala/Function2;;
Asciz	curr;
Asciz	(Lscala/Function2<TMsg;Lscala/actors/OutputChannel<Ljava/lang/Object;>;Ljava/lang/Object;>;)V;
Asciz	foreachAppend;
Asciz	(Lscala/actors/MQueue;)V;
NameAndType	append:(Lscala/actors/MQueueElement;)V
Method	scala/actors/MQueue.append:(Lscala/actors/MQueueElement;)V
Asciz	target;
Asciz	(Lscala/actors/MQueue<TMsg;>;)V;
Asciz	foreachDequeue;
Asciz	foldLeft;
Asciz	(Ljava/lang/Object;Lscala/Function2;)Ljava/lang/Object;;
Asciz	z;
Asciz	acc;
Asciz	<B:Ljava/lang/Object;>(TB;Lscala/Function2<TB;TMsg;TB;>;)TB;;
Asciz	get;
Asciz	(ILscala/Function1;)Lscala/Option;;
Asciz	scala/runtime/IntRef;
class	scala/runtime/IntRef
NameAndType	"<init>":(I)V
Method	scala/runtime/IntRef."<init>":(I)V
Asciz	scala/None$;
class	scala/None$
Asciz	MODULE$;
Asciz	Lscala/None$;;
NameAndType	MODULE$:Lscala/None$;
Field	scala/None$.MODULE$:Lscala/None$;
Asciz	test$1;
Asciz	(Ljava/lang/Object;ILscala/Function1;Lscala/runtime/IntRef;)Z;
NameAndType	test$1:(Ljava/lang/Object;ILscala/Function1;Lscala/runtime/IntRef;)Z
Method	scala/actors/MQueue.test$1:(Ljava/lang/Object;ILscala/Function1;Lscala/runtime/IntRef;)Z
Asciz	scala/Some;
class	scala/Some
Asciz	(Ljava/lang/Object;)V;
NameAndType	"<init>":(Ljava/lang/Object;)V
Method	scala/Some."<init>":(Ljava/lang/Object;)V
Asciz	n$1;
Asciz	p$1;
Asciz	Lscala/Function1;;
Asciz	pos$1;
Asciz	Lscala/runtime/IntRef;;
Asciz	(ILscala/Function1<TMsg;Ljava/lang/Boolean;>;)Lscala/Option<TMsg;>;;
Asciz	remove;
Asciz	(ILscala/Function2;)Lscala/Option;;
Asciz	removeInternal;
NameAndType	removeInternal:(ILscala/Function2;)Lscala/Option;
Method	scala/actors/MQueue.removeInternal:(ILscala/Function2;)Lscala/Option;
Asciz	scala/actors/MQueue$$anonfun$remove$1;
class	scala/actors/MQueue$$anonfun$remove$1
NameAndType	"<init>":(Lscala/actors/MQueue;)V
Method	scala/actors/MQueue$$anonfun$remove$1."<init>":(Lscala/actors/MQueue;)V
Asciz	scala/Option;
class	scala/Option
Asciz	map;
Asciz	(Lscala/Function1;)Lscala/Option;;
NameAndType	map:(Lscala/Function1;)Lscala/Option;
Method	scala/Option.map:(Lscala/Function1;)Lscala/Option;
Asciz	n;
Asciz	p;
Asciz	(ILscala/Function2<TMsg;Lscala/actors/OutputChannel<Ljava/lang/Object;>;Ljava/lang/Boolean;>;)Lscala/Option<Lscala/Tuple2<TMsg;Lscala/actors/OutputChannel<Ljava/lang/Object;>;>;>;;
Asciz	extractFirst;
Asciz	(Lscala/Function2;)Lscala/actors/MQueueElement;;
Asciz	scala/Predef$;
class	scala/Predef$
Asciz	Lscala/Predef$;;
NameAndType	MODULE$:Lscala/Predef$;
Field	scala/Predef$.MODULE$:Lscala/Predef$;
Asciz	conforms;
Asciz	()Lscala/Predef$$less$colon$less;;
NameAndType	conforms:()Lscala/Predef$$less$colon$less;
Method	scala/Predef$.conforms:()Lscala/Predef$$less$colon$less;
Asciz	orNull;
Asciz	(Lscala/Predef$$less$colon$less;)Ljava/lang/Object;;
NameAndType	orNull:(Lscala/Predef$$less$colon$less;)Ljava/lang/Object;
Method	scala/Option.orNull:(Lscala/Predef$$less$colon$less;)Ljava/lang/Object;
Asciz	(Lscala/Function2<TMsg;Lscala/actors/OutputChannel<Ljava/lang/Object;>;Ljava/lang/Boolean;>;)Lscala/actors/MQueueElement<TMsg;>;;
Asciz	(Lscala/PartialFunction;)Lscala/actors/MQueueElement;;
Asciz	scala/PartialFunction;
class	scala/PartialFunction
Asciz	isDefinedAt;
NameAndType	isDefinedAt:(Ljava/lang/Object;)Z
InterfaceMethod	scala/PartialFunction.isDefinedAt:(Ljava/lang/Object;)Z
Asciz	pf;
Asciz	Lscala/PartialFunction;;
Asciz	res;
Asciz	prev;
Asciz	(Lscala/PartialFunction<TMsg;Ljava/lang/Object;>;)Lscala/actors/MQueueElement<TMsg;>;;
Asciz	test$2;
Asciz	(Ljava/lang/Object;Lscala/actors/OutputChannel;ILscala/Function2;Lscala/runtime/IntRef;)Z;
NameAndType	test$2:(Ljava/lang/Object;Lscala/actors/OutputChannel;ILscala/Function2;Lscala/runtime/IntRef;)Z
Method	scala/actors/MQueue.test$2:(Ljava/lang/Object;Lscala/actors/OutputChannel;ILscala/Function2;Lscala/runtime/IntRef;)Z
Asciz	foundMsg$1;
Asciz	(Lscala/actors/MQueueElement;)Lscala/Some;;
NameAndType	foundMsg$1:(Lscala/actors/MQueueElement;)Lscala/Some;
Method	scala/actors/MQueue.foundMsg$1:(Lscala/actors/MQueueElement;)Lscala/Some;
Asciz	n$2;
Asciz	p$2;
Asciz	pos$2;
Asciz	(ILscala/Function2<TMsg;Lscala/actors/OutputChannel<Ljava/lang/Object;>;Ljava/lang/Boolean;>;)Lscala/Option<Lscala/actors/MQueueElement<TMsg;>;>;;
Asciz	scala/Function1;
class	scala/Function1
Asciz	(Ljava/lang/Object;)Ljava/lang/Object;;
NameAndType	apply:(Ljava/lang/Object;)Ljava/lang/Object;
InterfaceMethod	scala/Function1.apply:(Ljava/lang/Object;)Ljava/lang/Object;
Asciz	scala/runtime/BoxesRunTime;
class	scala/runtime/BoxesRunTime
Asciz	unboxToBoolean;
NameAndType	unboxToBoolean:(Ljava/lang/Object;)Z
Method	scala/runtime/BoxesRunTime.unboxToBoolean:(Ljava/lang/Object;)Z
Asciz	elem;
NameAndType	elem:I
Field	scala/runtime/IntRef.elem:I
Asciz	x;
Asciz	(Ljava/lang/String;)V;
Asciz	()V;
NameAndType	"<init>":()V
Method	java/lang/Object."<init>":()V
Asciz	<Msg:Ljava/lang/Object;>Ljava/lang/Object;Lscala/ScalaObject;;
Asciz	ScalaSig;
Asciz	InnerClasses;
Asciz	scala/Predef$$less$colon$less;
class	scala/Predef$$less$colon$less
Asciz	scala/Predef;
class	scala/Predef
Asciz	$less$colon$less;
Asciz	$anonfun$remove$1;
Asciz	scala/ScalaObject;
class	scala/ScalaObject

{
private int _size;
  Signature: I

private scala.actors.MQueueElement last;
  Signature: Lscala/actors/MQueueElement;
  Signature: length = 0x2
   00 07 

private scala.actors.MQueueElement first;
  Signature: Lscala/actors/MQueueElement;
  Signature: length = 0x2
   00 07 

private final java.lang.String label;
  Signature: Ljava/lang/String;

public java.lang.String label();
  Signature: ()Ljava/lang/String;
  Code:
   Stack=1, Locals=1, Args_size=1
	aload_0
	getfield	Field label:Ljava/lang/String;
	areturn
  Labels:

public scala.actors.MQueueElement first();
  Signature: ()Lscala/actors/MQueueElement;
  Code:
   Stack=1, Locals=1, Args_size=1
	aload_0
	getfield	Field first:Lscala/actors/MQueueElement;
	areturn
  Labels:
  Signature: length = 0x2
   00 16 

public void first_$eq(scala.actors.MQueueElement);
  Signature: (Lscala/actors/MQueueElement;)V
  Code:
   Stack=2, Locals=2, Args_size=2
	aload_0
	aload_1
	putfield	Field first:Lscala/actors/MQueueElement;
	return
  Labels:
  Signature: length = 0x2
   00 19 

public scala.actors.MQueueElement last();
  Signature: ()Lscala/actors/MQueueElement;
  Code:
   Stack=1, Locals=1, Args_size=1
	aload_0
	getfield	Field last:Lscala/actors/MQueueElement;
	areturn
  Labels:
  Signature: length = 0x2
   00 16 

public void last_$eq(scala.actors.MQueueElement);
  Signature: (Lscala/actors/MQueueElement;)V
  Code:
   Stack=2, Locals=2, Args_size=2
	aload_0
	aload_1
	putfield	Field last:Lscala/actors/MQueueElement;
	return
  Labels:
  Signature: length = 0x2
   00 19 

private int _size();
  Signature: ()I
  Code:
   Stack=1, Locals=1, Args_size=1
	aload_0
	getfield	Field _size:I
	ireturn
  Labels:

private void _size_$eq(int);
  Signature: (I)V
  Code:
   Stack=2, Locals=2, Args_size=2
	aload_0
	iload_1
	putfield	Field _size:I
	return
  Labels:

public int size();
  Signature: ()I
  Code:
   Stack=1, Locals=1, Args_size=1
	aload_0
	invokespecial	Method _size:()I
	ireturn
  Labels:

public final boolean isEmpty();
  Signature: ()Z
  Code:
   Stack=1, Locals=1, Args_size=1
	aload_0
	invokevirtual	Method last:()Lscala/actors/MQueueElement;
	ifnonnull	l1 // iconst_0
	iconst_1
	goto	l2 // ireturn
l1	iconst_0
l2	ireturn
  Labels:
   	l1 = 11 // iconst_0
   	l2 = 12 // ireturn

public void changeSize(int);
  Signature: (I)V
  Code:
   Stack=3, Locals=2, Args_size=2
	aload_0
	aload_0
	invokespecial	Method _size:()I
	iload_1
	iadd
	invokespecial	Method _size_$eq:(I)V
	return
  Labels:
  LocalVariableTable: 
   Start  Length  Slot  Name   Signature
   0      11      0    this       Lscala/actors/MQueue;
   0      11      1    diff       I


public void append(java.lang.Object, scala.actors.OutputChannel);
  Signature: (Ljava/lang/Object;Lscala/actors/OutputChannel;)V
  Code:
   Stack=4, Locals=4, Args_size=3
	aload_0
	iconst_1
	invokevirtual	Method changeSize:(I)V
	new	class scala/actors/MQueueElement
	dup
	aload_1
	aload_2
	invokespecial	Method scala/actors/MQueueElement."<init>":(Ljava/lang/Object;Lscala/actors/OutputChannel;)V
	astore_3
	aload_0
	invokevirtual	Method isEmpty:()Z
	ifeq	l1 // aload_0
	aload_0
	aload_3
	invokevirtual	Method first_$eq:(Lscala/actors/MQueueElement;)V
	goto	l2 // aload_0
l1	aload_0
	invokevirtual	Method last:()Lscala/actors/MQueueElement;
	aload_3
	invokevirtual	Method scala/actors/MQueueElement.next_$eq:(Lscala/actors/MQueueElement;)V
l2	aload_0
	aload_3
	invokevirtual	Method last_$eq:(Lscala/actors/MQueueElement;)V
	return
  Labels:
   	l1 = 30 // aload_0
   	l2 = 38 // aload_0
  LocalVariableTable: 
   Start  Length  Slot  Name   Signature
   0      44      0    this       Lscala/actors/MQueue;
   0      44      1    msg       Ljava/lang/Object;
   0      44      2    session       Lscala/actors/OutputChannel;
   15      28      3    el       Lscala/actors/MQueueElement;

  Signature: length = 0x2
   00 47 

public void append(scala.actors.MQueueElement);
  Signature: (Lscala/actors/MQueueElement;)V
  Code:
   Stack=2, Locals=2, Args_size=2
	aload_0
	iconst_1
	invokevirtual	Method changeSize:(I)V
	aload_0
	invokevirtual	Method isEmpty:()Z
	ifeq	l1 // aload_0
	aload_0
	aload_1
	invokevirtual	Method first_$eq:(Lscala/actors/MQueueElement;)V
	goto	l2 // aload_0
l1	aload_0
	invokevirtual	Method last:()Lscala/actors/MQueueElement;
	aload_1
	invokevirtual	Method scala/actors/MQueueElement.next_$eq:(Lscala/actors/MQueueElement;)V
l2	aload_0
	aload_1
	invokevirtual	Method last_$eq:(Lscala/actors/MQueueElement;)V
	return
  Labels:
   	l1 = 20 // aload_0
   	l2 = 28 // aload_0
  LocalVariableTable: 
   Start  Length  Slot  Name   Signature
   0      34      0    this       Lscala/actors/MQueue;
   0      34      1    el       Lscala/actors/MQueueElement;

  Signature: length = 0x2
   00 19 

public void foreach(scala.Function2);
  Signature: (Lscala/Function2;)V
  Code:
   Stack=3, Locals=3, Args_size=2
	aload_0
	invokevirtual	Method first:()Lscala/actors/MQueueElement;
	astore_2
l3	aload_2
	dup
	pop
	ifnull	l1 // return
	aload_2
	aconst_null
	invokevirtual	Method java/lang/Object.equals:(Ljava/lang/Object;)Z
	ifeq	l2 // aload_1
l1	return
l2	aload_1
	aload_2
	invokevirtual	Method scala/actors/MQueueElement.msg:()Ljava/lang/Object;
	aload_2
	invokevirtual	Method scala/actors/MQueueElement.session:()Lscala/actors/OutputChannel;
	invokeinterface	InterfaceMethod scala/Function2.apply:(Ljava/lang/Object;Ljava/lang/Object;)Ljava/lang/Object;
	pop
	aload_2
	invokevirtual	Method scala/actors/MQueueElement.next:()Lscala/actors/MQueueElement;
	astore_2
	goto	l3 // aload_2
  Labels:
   	l3 = 5 // aload_2
   	l1 = 19 // return
   	l2 = 20 // aload_1
  LocalVariableTable: 
   Start  Length  Slot  Name   Signature
   0      43      0    this       Lscala/actors/MQueue;
   0      43      1    f       Lscala/Function2;
   5      38      2    curr       Lscala/actors/MQueueElement;

  Signature: length = 0x2
   00 64 

public void foreachAppend(scala.actors.MQueue);
  Signature: (Lscala/actors/MQueue;)V
  Code:
   Stack=2, Locals=3, Args_size=2
	aload_0
	invokevirtual	Method first:()Lscala/actors/MQueueElement;
	astore_2
l3	aload_2
	dup
	pop
	ifnull	l1 // return
	aload_2
	aconst_null
	invokevirtual	Method java/lang/Object.equals:(Ljava/lang/Object;)Z
	ifeq	l2 // aload_1
l1	return
l2	aload_1
	aload_2
	invokevirtual	Method append:(Lscala/actors/MQueueElement;)V
	aload_2
	invokevirtual	Method scala/actors/MQueueElement.next:()Lscala/actors/MQueueElement;
	astore_2
	goto	l3 // aload_2
  Labels:
   	l3 = 5 // aload_2
   	l1 = 19 // return
   	l2 = 20 // aload_1
  LocalVariableTable: 
   Start  Length  Slot  Name   Signature
   0      33      0    this       Lscala/actors/MQueue;
   0      33      1    target       Lscala/actors/MQueue;
   5      28      2    curr       Lscala/actors/MQueueElement;

  Signature: length = 0x2
   00 6A 

public void foreachDequeue(scala.actors.MQueue);
  Signature: (Lscala/actors/MQueue;)V
  Code:
   Stack=2, Locals=3, Args_size=2
	aload_0
	invokevirtual	Method first:()Lscala/actors/MQueueElement;
	astore_2
l3	aload_2
	dup
	pop
	ifnull	l1 // aload_0
	aload_2
	aconst_null
	invokevirtual	Method java/lang/Object.equals:(Ljava/lang/Object;)Z
	ifeq	l2 // aload_1
l1	aload_0
	aconst_null
	invokevirtual	Method first_$eq:(Lscala/actors/MQueueElement;)V
	aload_0
	aconst_null
	invokevirtual	Method last_$eq:(Lscala/actors/MQueueElement;)V
	aload_0
	iconst_0
	invokespecial	Method _size_$eq:(I)V
	return
l2	aload_1
	aload_2
	invokevirtual	Method append:(Lscala/actors/MQueueElement;)V
	aload_2
	invokevirtual	Method scala/actors/MQueueElement.next:()Lscala/actors/MQueueElement;
	astore_2
	goto	l3 // aload_2
  Labels:
   	l3 = 5 // aload_2
   	l1 = 19 // aload_0
   	l2 = 35 // aload_1
  LocalVariableTable: 
   Start  Length  Slot  Name   Signature
   0      48      0    this       Lscala/actors/MQueue;
   0      48      1    target       Lscala/actors/MQueue;
   5      29      2    curr       Lscala/actors/MQueueElement;
   35      13      2    curr       Lscala/actors/MQueueElement;

  Signature: length = 0x2
   00 6A 

public java.lang.Object foldLeft(java.lang.Object, scala.Function2);
  Signature: (Ljava/lang/Object;Lscala/Function2;)Ljava/lang/Object;
  Code:
   Stack=3, Locals=5, Args_size=3
	aload_1
	astore_3
	aload_0
	invokevirtual	Method first:()Lscala/actors/MQueueElement;
	astore	4
l3	aload	4
	dup
	pop
	ifnull	l1 // aload_3
	aload	4
	aconst_null
	invokevirtual	Method java/lang/Object.equals:(Ljava/lang/Object;)Z
	ifeq	l2 // aload_2
l1	aload_3
	areturn
l2	aload_2
	aload_3
	aload	4
	invokevirtual	Method scala/actors/MQueueElement.msg:()Ljava/lang/Object;
	invokeinterface	InterfaceMethod scala/Function2.apply:(Ljava/lang/Object;Ljava/lang/Object;)Ljava/lang/Object;
	astore_3
	aload	4
	invokevirtual	Method scala/actors/MQueueElement.next:()Lscala/actors/MQueueElement;
	astore	4
	goto	l3 // aload
  Labels:
   	l3 = 8 // aload
   	l1 = 24 // aload_3
   	l2 = 26 // aload_2
  LocalVariableTable: 
   Start  Length  Slot  Name   Signature
   0      49      0    this       Lscala/actors/MQueue;
   0      49      1    z       Ljava/lang/Object;
   0      49      2    f       Lscala/Function2;
   2      23      3    acc       Ljava/lang/Object;
   26      23      3    acc       Ljava/lang/Object;
   8      17      4    curr       Lscala/actors/MQueueElement;
   26      23      4    curr       Lscala/actors/MQueueElement;

  Signature: length = 0x2
   00 70 

public scala.Option get(int, scala.Function1);
  Signature: (ILscala/Function1;)Lscala/Option;
  Code:
   Stack=5, Locals=5, Args_size=3
	new	class scala/runtime/IntRef
	dup
	iconst_0
	invokespecial	Method scala/runtime/IntRef."<init>":(I)V
	astore_3
	aload_0
	invokevirtual	Method first:()Lscala/actors/MQueueElement;
	astore	4
l4	aload	4
	dup
	pop
	ifnull	l1 // getstatic
	aload	4
	aconst_null
	invokevirtual	Method java/lang/Object.equals:(Ljava/lang/Object;)Z
	ifeq	l2 // aload_0
l1	getstatic	Field scala/None$.MODULE$:Lscala/None$;
	areturn
l2	aload_0
	aload	4
	invokevirtual	Method scala/actors/MQueueElement.msg:()Ljava/lang/Object;
	iload_1
	aload_2
	aload_3
	invokespecial	Method test$1:(Ljava/lang/Object;ILscala/Function1;Lscala/runtime/IntRef;)Z
	ifeq	l3 // aload
	new	class scala/Some
	dup
	aload	4
	invokevirtual	Method scala/actors/MQueueElement.msg:()Ljava/lang/Object;
	invokespecial	Method scala/Some."<init>":(Ljava/lang/Object;)V
	areturn
l3	aload	4
	invokevirtual	Method scala/actors/MQueueElement.next:()Lscala/actors/MQueueElement;
	astore	4
	goto	l4 // aload
  Labels:
   	l4 = 15 // aload
   	l1 = 31 // getstatic
   	l2 = 35 // aload_0
   	l3 = 63 // aload
  LocalVariableTable: 
   Start  Length  Slot  Name   Signature
   0      73      0    this       Lscala/actors/MQueue;
   0      73      1    n$1       I
   0      73      2    p$1       Lscala/Function1;
   9      25      3    pos$1       Lscala/runtime/IntRef;
   35      38      3    pos$1       Lscala/runtime/IntRef;
   15      19      4    curr       Lscala/actors/MQueueElement;
   35      38      4    curr       Lscala/actors/MQueueElement;

  Signature: length = 0x2
   00 FFFFFF8B 

public scala.Option remove(int, scala.Function2);
  Signature: (ILscala/Function2;)Lscala/Option;
  Code:
   Stack=4, Locals=3, Args_size=3
	aload_0
	iload_1
	aload_2
	invokespecial	Method removeInternal:(ILscala/Function2;)Lscala/Option;
	new	class scala/actors/MQueue$$anonfun$remove$1
	dup
	aload_0
	invokespecial	Method scala/actors/MQueue$$anonfun$remove$1."<init>":(Lscala/actors/MQueue;)V
	invokevirtual	Method scala/Option.map:(Lscala/Function1;)Lscala/Option;
	areturn
  Labels:
  LocalVariableTable: 
   Start  Length  Slot  Name   Signature
   0      18      0    this       Lscala/actors/MQueue;
   0      18      1    n       I
   0      18      2    p       Lscala/Function2;

  Signature: length = 0x2
   00 FFFFFF9D 

public scala.actors.MQueueElement extractFirst(scala.Function2);
  Signature: (Lscala/Function2;)Lscala/actors/MQueueElement;
  Code:
   Stack=3, Locals=2, Args_size=2
	aload_0
	iconst_0
	aload_1
	invokespecial	Method removeInternal:(ILscala/Function2;)Lscala/Option;
	getstatic	Field scala/Predef$.MODULE$:Lscala/Predef$;
	invokevirtual	Method scala/Predef$.conforms:()Lscala/Predef$$less$colon$less;
	invokevirtual	Method scala/Option.orNull:(Lscala/Predef$$less$colon$less;)Ljava/lang/Object;
	checkcast	class scala/actors/MQueueElement
	areturn
  Labels:
  LocalVariableTable: 
   Start  Length  Slot  Name   Signature
   0      19      0    this       Lscala/actors/MQueue;
   0      19      1    p       Lscala/Function2;

  Signature: length = 0x2
   00 FFFFFFAD 

public scala.actors.MQueueElement extractFirst(scala.PartialFunction);
  Signature: (Lscala/PartialFunction;)Lscala/actors/MQueueElement;
  Code:
   Stack=2, Locals=5, Args_size=2
	aload_0
	invokevirtual	Method isEmpty:()Z
	ifeq	l1 // aload_1
	aconst_null
	areturn
l1	aload_1
	aload_0
	invokevirtual	Method first:()Lscala/actors/MQueueElement;
	invokevirtual	Method scala/actors/MQueueElement.msg:()Ljava/lang/Object;
	invokeinterface	InterfaceMethod scala/PartialFunction.isDefinedAt:(Ljava/lang/Object;)Z
	ifeq	l2 // aload_0
	aload_0
	invokevirtual	Method first:()Lscala/actors/MQueueElement;
	astore_2
	aload_0
	aload_0
	invokevirtual	Method first:()Lscala/actors/MQueueElement;
	invokevirtual	Method scala/actors/MQueueElement.next:()Lscala/actors/MQueueElement;
	invokevirtual	Method first_$eq:(Lscala/actors/MQueueElement;)V
	aload_2
	aload_0
	invokevirtual	Method last:()Lscala/actors/MQueueElement;
	if_acmpne	l3 // aload_0
	aload_0
	aconst_null
	invokevirtual	Method last_$eq:(Lscala/actors/MQueueElement;)V
l3	aload_0
	iconst_m1
	invokevirtual	Method changeSize:(I)V
	aload_2
	goto	l4 // areturn
l2	aload_0
	invokevirtual	Method first:()Lscala/actors/MQueueElement;
	invokevirtual	Method scala/actors/MQueueElement.next:()Lscala/actors/MQueueElement;
	astore	4
	aload_0
	invokevirtual	Method first:()Lscala/actors/MQueueElement;
	astore_3
l9	aload	4
	dup
	pop
	ifnull	l5 // aconst_null
	aload	4
	aconst_null
	invokevirtual	Method java/lang/Object.equals:(Ljava/lang/Object;)Z
	ifeq	l6 // aload_1
l5	aconst_null
l4	areturn
l6	aload_1
	aload	4
	invokevirtual	Method scala/actors/MQueueElement.msg:()Ljava/lang/Object;
	invokeinterface	InterfaceMethod scala/PartialFunction.isDefinedAt:(Ljava/lang/Object;)Z
	ifeq	l7 // aload
	aload_3
	aload	4
	invokevirtual	Method scala/actors/MQueueElement.next:()Lscala/actors/MQueueElement;
	invokevirtual	Method scala/actors/MQueueElement.next_$eq:(Lscala/actors/MQueueElement;)V
	aload	4
	aload_0
	invokevirtual	Method last:()Lscala/actors/MQueueElement;
	if_acmpne	l8 // aload_0
	aload_0
	aload_3
	invokevirtual	Method last_$eq:(Lscala/actors/MQueueElement;)V
l8	aload_0
	iconst_m1
	invokevirtual	Method changeSize:(I)V
	aload	4
	areturn
l7	aload	4
	astore_3
	aload	4
	invokevirtual	Method scala/actors/MQueueElement.next:()Lscala/actors/MQueueElement;
	astore	4
	goto	l9 // aload
  Labels:
   	l1 = 9 // aload_1
   	l3 = 54 // aload_0
   	l2 = 63 // aload_0
   	l9 = 77 // aload
   	l5 = 93 // aconst_null
   	l4 = 94 // areturn
   	l6 = 95 // aload_1
   	l8 = 132 // aload_0
   	l7 = 140 // aload
  LocalVariableTable: 
   Start  Length  Slot  Name   Signature
   0      153      0    this       Lscala/actors/MQueue;
   0      153      1    pf       Lscala/PartialFunction;
   30      30      2    res       Lscala/actors/MQueueElement;
   77      17      3    prev       Lscala/actors/MQueueElement;
   95      58      3    prev       Lscala/actors/MQueueElement;
   72      22      4    curr       Lscala/actors/MQueueElement;
   95      58      4    curr       Lscala/actors/MQueueElement;

  Signature: length = 0x2
   00 FFFFFFB8 

private scala.Option removeInternal(int, scala.Function2);
  Signature: (ILscala/Function2;)Lscala/Option;
  Code:
   Stack=6, Locals=7, Args_size=3
	new	class scala/runtime/IntRef
	dup
	iconst_0
	invokespecial	Method scala/runtime/IntRef."<init>":(I)V
	astore	4
	aload_0
	invokevirtual	Method isEmpty:()Z
	ifeq	l1 // aload_0
	getstatic	Field scala/None$.MODULE$:Lscala/None$;
	areturn
l1	aload_0
	aload_0
	invokevirtual	Method first:()Lscala/actors/MQueueElement;
	invokevirtual	Method scala/actors/MQueueElement.msg:()Ljava/lang/Object;
	aload_0
	invokevirtual	Method first:()Lscala/actors/MQueueElement;
	invokevirtual	Method scala/actors/MQueueElement.session:()Lscala/actors/OutputChannel;
	iload_1
	aload_2
	aload	4
	invokespecial	Method test$2:(Ljava/lang/Object;Lscala/actors/OutputChannel;ILscala/Function2;Lscala/runtime/IntRef;)Z
	ifeq	l2 // aload_0
	aload_0
	invokevirtual	Method first:()Lscala/actors/MQueueElement;
	astore_3
	aload_0
	aload_0
	invokevirtual	Method first:()Lscala/actors/MQueueElement;
	invokevirtual	Method scala/actors/MQueueElement.next:()Lscala/actors/MQueueElement;
	invokevirtual	Method first_$eq:(Lscala/actors/MQueueElement;)V
	aload_3
	aload_0
	invokevirtual	Method last:()Lscala/actors/MQueueElement;
	if_acmpne	l3 // aload_0
	aload_0
	aconst_null
	invokevirtual	Method last_$eq:(Lscala/actors/MQueueElement;)V
l3	aload_0
	aload_3
	invokespecial	Method foundMsg$1:(Lscala/actors/MQueueElement;)Lscala/Some;
	goto	l4 // areturn
l2	aload_0
	invokevirtual	Method first:()Lscala/actors/MQueueElement;
	invokevirtual	Method scala/actors/MQueueElement.next:()Lscala/actors/MQueueElement;
	astore	6
	aload_0
	invokevirtual	Method first:()Lscala/actors/MQueueElement;
	astore	5
l9	aload	6
	dup
	pop
	ifnull	l5 // getstatic
	aload	6
	aconst_null
	invokevirtual	Method java/lang/Object.equals:(Ljava/lang/Object;)Z
	ifeq	l6 // aload_0
l5	getstatic	Field scala/None$.MODULE$:Lscala/None$;
l4	areturn
l6	aload_0
	aload	6
	invokevirtual	Method scala/actors/MQueueElement.msg:()Ljava/lang/Object;
	aload	6
	invokevirtual	Method scala/actors/MQueueElement.session:()Lscala/actors/OutputChannel;
	iload_1
	aload_2
	aload	4
	invokespecial	Method test$2:(Ljava/lang/Object;Lscala/actors/OutputChannel;ILscala/Function2;Lscala/runtime/IntRef;)Z
	ifeq	l7 // aload
	aload	5
	aload	6
	invokevirtual	Method scala/actors/MQueueElement.next:()Lscala/actors/MQueueElement;
	invokevirtual	Method scala/actors/MQueueElement.next_$eq:(Lscala/actors/MQueueElement;)V
	aload	6
	aload_0
	invokevirtual	Method last:()Lscala/actors/MQueueElement;
	if_acmpne	l8 // aload_0
	aload_0
	aload	5
	invokevirtual	Method last_$eq:(Lscala/actors/MQueueElement;)V
l8	aload_0
	aload	6
	invokespecial	Method foundMsg$1:(Lscala/actors/MQueueElement;)Lscala/Some;
	areturn
l7	aload	6
	astore	5
	aload	6
	invokevirtual	Method scala/actors/MQueueElement.next:()Lscala/actors/MQueueElement;
	astore	6
	goto	l9 // aload
  Labels:
   	l1 = 21 // aload_0
   	l3 = 75 // aload_0
   	l2 = 83 // aload_0
   	l9 = 98 // aload
   	l5 = 114 // getstatic
   	l4 = 117 // areturn
   	l6 = 118 // aload_0
   	l8 = 164 // aload_0
   	l7 = 171 // aload
  LocalVariableTable: 
   Start  Length  Slot  Name   Signature
   0      185      0    this       Lscala/actors/MQueue;
   0      185      1    n$2       I
   0      185      2    p$2       Lscala/Function2;
   51      29      3    res       Lscala/actors/MQueueElement;
   10      175      4    pos$2       Lscala/runtime/IntRef;
   98      19      5    prev       Lscala/actors/MQueueElement;
   118      67      5    prev       Lscala/actors/MQueueElement;
   92      25      6    curr       Lscala/actors/MQueueElement;
   118      67      6    curr       Lscala/actors/MQueueElement;

  Signature: length = 0x2
   00 FFFFFFC4 

private final boolean test$1(java.lang.Object, int, scala.Function1, scala.runtime.IntRef);
  Signature: (Ljava/lang/Object;ILscala/Function1;Lscala/runtime/IntRef;)Z
  Code:
   Stack=3, Locals=5, Args_size=5
	aload_3
	aload_1
	invokeinterface	InterfaceMethod scala/Function1.apply:(Ljava/lang/Object;)Ljava/lang/Object;
	invokestatic	Method scala/runtime/BoxesRunTime.unboxToBoolean:(Ljava/lang/Object;)Z
	ifeq	l1 // iconst_0
	aload	4
	getfield	Field scala/runtime/IntRef.elem:I
	iload_2
	if_icmpeq	l2 // iconst_1
	aload	4
	aload	4
	getfield	Field scala/runtime/IntRef.elem:I
	iconst_1
	iadd
	putfield	Field scala/runtime/IntRef.elem:I
	iconst_0
	ifeq	l1 // iconst_0
l2	iconst_1
	goto	l3 // ireturn
l1	iconst_0
l3	ireturn
  Labels:
   	l2 = 38 // iconst_1
   	l1 = 42 // iconst_0
   	l3 = 43 // ireturn
  LocalVariableTable: 
   Start  Length  Slot  Name   Signature
   0      44      0    this       Lscala/actors/MQueue;
   0      44      1    msg       Ljava/lang/Object;


private final scala.Some foundMsg$1(scala.actors.MQueueElement);
  Signature: (Lscala/actors/MQueueElement;)Lscala/Some;
  Code:
   Stack=3, Locals=2, Args_size=2
	aload_0
	iconst_m1
	invokevirtual	Method changeSize:(I)V
	new	class scala/Some
	dup
	aload_1
	invokespecial	Method scala/Some."<init>":(Ljava/lang/Object;)V
	areturn
  Labels:
  LocalVariableTable: 
   Start  Length  Slot  Name   Signature
   0      14      0    this       Lscala/actors/MQueue;
   0      14      1    x       Lscala/actors/MQueueElement;


private final boolean test$2(java.lang.Object, scala.actors.OutputChannel, int, scala.Function2, scala.runtime.IntRef);
  Signature: (Ljava/lang/Object;Lscala/actors/OutputChannel;ILscala/Function2;Lscala/runtime/IntRef;)Z
  Code:
   Stack=3, Locals=6, Args_size=6
	aload	4
	aload_1
	aload_2
	invokeinterface	InterfaceMethod scala/Function2.apply:(Ljava/lang/Object;Ljava/lang/Object;)Ljava/lang/Object;
	invokestatic	Method scala/runtime/BoxesRunTime.unboxToBoolean:(Ljava/lang/Object;)Z
	ifeq	l1 // iconst_0
	aload	5
	getfield	Field scala/runtime/IntRef.elem:I
	iload_3
	if_icmpeq	l2 // iconst_1
	aload	5
	aload	5
	getfield	Field scala/runtime/IntRef.elem:I
	iconst_1
	iadd
	putfield	Field scala/runtime/IntRef.elem:I
	iconst_0
	ifeq	l1 // iconst_0
l2	iconst_1
	goto	l3 // ireturn
l1	iconst_0
l3	ireturn
  Labels:
   	l2 = 40 // iconst_1
   	l1 = 44 // iconst_0
   	l3 = 45 // ireturn
  LocalVariableTable: 
   Start  Length  Slot  Name   Signature
   0      46      0    this       Lscala/actors/MQueue;
   0      46      1    msg       Ljava/lang/Object;
   0      46      2    session       Lscala/actors/OutputChannel;


public scala.actors.MQueue(java.lang.String);
  Signature: (Ljava/lang/String;)V
  Code:
   Stack=2, Locals=2, Args_size=2
	aload_0
	aload_1
	putfield	Field label:Ljava/lang/String;
	aload_0
	invokespecial	Method java/lang/Object."<init>":()V
	aload_0
	aconst_null
	putfield	Field first:Lscala/actors/MQueueElement;
	aload_0
	aconst_null
	putfield	Field last:Lscala/actors/MQueueElement;
	aload_0
	iconst_0
	putfield	Field _size:I
	return
  Labels:
  LocalVariableTable: 
   Start  Length  Slot  Name   Signature
   0      25      0    this       Lscala/actors/MQueue;
   0      25      1    label       Ljava/lang/String;

  Signature: length = 0x2
   00 FFFFFFD3 

}

