Compiled from "MessageQueue.scala"
public class scala.actors.MQueue extends java.lang.Object implements scala.ScalaObject
  SourceFile: "MessageQueue.scala"
  ScalaSig: length = 0x424
   05 00 FFFFFF81 21 06 09 01 02 FFFFFF84 FFFFFF80 FFFFFF80 FFFFFF80 00 02 06 02
   06 4D 51 75 65 75 65 0A 02 03 04 01 06 61 63 74
   6F 72 73 0A 01 05 01 05 73 63 61 6C 61 13 03 00
   07 0F 10 02 08 0D 0D 01 09 0A 02 0A 0B 01 04 6C
   61 6E 67 0A 01 0C 01 04 6A 61 76 61 09 02 0E 09
   02 06 4F 62 6A 65 63 74 10 02 10 11 0D 01 04 09
   02 12 04 02 0B 53 63 61 6C 61 4F 62 6A 65 63 74
   08 08 14 00 FFFFFF82 FFFFFFC2 FFFFFF80 FFFFFF84 08 16 01 05 6C 61 62 65
   6C 03 00 15 01 17 10 02 18 1B 0E 02 10 19 09 02
   1A 04 01 06 50 72 65 64 65 66 09 02 1C 1D 02 06
   53 74 72 69 6E 67 0A 02 1A 04 08 08 1F 00 FFFFFF82 FFFFFF80
   FFFFFFA0 FFFFFF80 04 17 01 06 6C 61 62 65 6C 20 08 05 21 00
   FFFFFF84 00 22 01 06 3C 69 6E 69 74 3E 14 02 23 25 10
   02 24 00 0D 01 02 08 05 14 20 FFFFFFC0 00 17 08 07 27
   00 FFFFFFC0 FFFFFF80 FFFFFF84 08 28 01 05 66 69 72 73 74 15 01 29
   10 02 24 2A 09 02 2B 02 02 0D 4D 51 75 65 75 65
   45 6C 65 6D 65 6E 74 08 07 2D 00 FFFFFFC0 FFFFFF80 FFFFFF84 08 2E
   01 09 66 69 72 73 74 5F 24 65 71 14 02 2F 32 10
   02 10 30 09 02 31 04 02 04 55 6E 69 74 08 07 33
   2C FFFFFF81 FFFFFF80 FFFFFFC0 00 29 01 03 78 24 31 08 06 35 00 FFFFFFA0
   FFFFFFA0 04 29 01 06 66 69 72 73 74 20 08 07 37 00 FFFFFFC0
   FFFFFF80 FFFFFF84 08 28 01 04 6C 61 73 74 08 07 39 00 FFFFFFC0 FFFFFF80
   FFFFFF84 08 3A 01 08 6C 61 73 74 5F 24 65 71 14 02 2F
   3B 08 07 33 38 FFFFFF81 FFFFFF80 FFFFFFC0 00 29 08 06 3D 00 FFFFFFA0 FFFFFFA0
   04 29 01 05 6C 61 73 74 20 08 07 3F 00 FFFFFFC0 FFFFFF80 FFFFFF84
   04 40 01 05 5F 73 69 7A 65 15 01 41 10 02 10 42
   09 02 43 04 02 03 49 6E 74 08 07 45 00 FFFFFFC0 FFFFFF80 FFFFFF84
   04 46 01 09 5F 73 69 7A 65 5F 24 65 71 14 02 2F
   47 08 07 33 44 FFFFFF81 FFFFFF80 FFFFFFC0 00 41 08 06 49 00 FFFFFFA0 FFFFFFA0
   04 41 01 06 5F 73 69 7A 65 20 08 05 4B 00 FFFFFF84 00
   40 01 04 73 69 7A 65 08 05 4D 00 FFFFFF84 02 4E 01 07
   69 73 45 6D 70 74 79 15 01 4F 10 02 10 50 09 02
   51 04 02 07 42 6F 6F 6C 65 61 6E 08 05 53 00 FFFFFF84
   08 54 01 0A 63 68 61 6E 67 65 53 69 7A 65 14 02
   2F 55 08 05 56 52 FFFFFFC0 00 41 01 04 64 69 66 66 08
   05 58 00 FFFFFF84 00 59 01 06 61 70 70 65 6E 64 14 03
   2F 5A 5F 08 05 5B 57 FFFFFFC0 00 5C 01 03 6D 73 67 10
   02 10 5D 09 02 5E 04 02 03 41 6E 79 08 05 60 57
   FFFFFFC0 00 61 01 07 73 65 73 73 69 6F 6E 10 03 24 62
   5C 09 02 63 02 02 0D 4F 75 74 70 75 74 43 68 61
   6E 6E 65 6C 08 05 65 00 FFFFFF84 00 66 01 07 66 6F 72
   65 61 63 68 14 02 2F 67 08 05 68 64 FFFFFFC0 00 69 01
   01 66 10 05 10 6A 5C 61 2F 09 02 6B 04 02 09 46
   75 6E 63 74 69 6F 6E 32 08 05 6D 00 FFFFFF84 00 6E 01
   08 66 6F 6C 64 4C 65 66 74 15 02 6F 73 14 02 70
   7B 14 02 71 79 10 02 72 73 0C 00 04 08 74 6C FFFFFF84
   FFFFFF80 FFFFFF80 FFFFFFC2 00 75 02 01 42 11 02 76 5C 10 02 10 77
   09 02 78 04 02 07 4E 6F 74 68 69 6E 67 08 05 68
   6C FFFFFFC0 00 7A 10 05 10 6A 71 5C 71 08 05 7C 6C FFFFFFC0
   00 71 01 01 7A 08 05 7E 00 FFFFFF84 00 7F 01 03 67 65
   74 14 04 FFFFFF81 00 FFFFFF81 09 14 04 FFFFFF81 01 FFFFFF81 04 10 04 10
   FFFFFF81 02 5C 09 03 FFFFFF81 03 04 02 06 4F 70 74 69 6F 6E
   08 07 FFFFFF81 05 7D FFFFFFC0 00 FFFFFF81 06 01 01 70 10 05 10 FFFFFF81
   07 5C 4F 09 03 FFFFFF81 08 04 02 09 46 75 6E 63 74 69
   6F 6E 31 08 06 FFFFFF81 0A 7D FFFFFFC0 00 41 01 01 6E 08 07
   FFFFFF81 0C 00 FFFFFF84 00 FFFFFF81 0D 01 06 72 65 6D 6F 76 65 14
   04 FFFFFF81 0E FFFFFF81 15 14 04 FFFFFF81 0F FFFFFF81 13 10 05 10 FFFFFF81 02
   FFFFFF81 10 10 05 10 FFFFFF81 11 5C 61 09 03 FFFFFF81 12 04 02 06
   54 75 70 6C 65 32 08 08 FFFFFF81 05 FFFFFF81 0B FFFFFFC0 00 FFFFFF81 14
   10 05 10 6A 5C 61 4F 08 07 FFFFFF81 0A FFFFFF81 0B FFFFFFC0 00 41
   08 07 FFFFFF81 17 00 FFFFFF84 00 FFFFFF81 18 01 0C 65 78 74 72 61
   63 74 46 69 72 73 74 14 03 29 FFFFFF81 19 08 08 FFFFFF81 05
   FFFFFF81 16 FFFFFFC0 00 FFFFFF81 14 08 07 FFFFFF81 1B 00 FFFFFF84 04 FFFFFF81 1C 01
   0E 72 65 6D 6F 76 65 49 6E 74 65 72 6E 61 6C 14
   04 FFFFFF81 1D FFFFFF81 20 14 04 FFFFFF81 1E FFFFFF81 1F 10 04 10 FFFFFF81 02
   29 08 08 FFFFFF81 05 FFFFFF81 1A FFFFFFC0 00 FFFFFF81 14 08 07 FFFFFF81 0A FFFFFF81
   1A FFFFFFC0 00 41 
  InnerClass: 
   public abstract #203= #200 of #202; //$less$colon$less=class scala/Predef$$less$colon$less of class scala/Predef
   public final #204= #154 of #15; //$anonfun$remove$1=class scala/actors/MQueue$$anonfun$remove$1 of class scala/actors/MQueue
  minor version: 0
  major version: 49
  Constant pool:
const #1 = Asciz	SourceFile;
const #2 = Asciz	MessageQueue.scala;
const #3 = Asciz	_size;
const #4 = Asciz	I;
const #5 = Asciz	last;
const #6 = Asciz	Lscala/actors/MQueueElement;;
const #7 = Asciz	first;
const #8 = Asciz	label;
const #9 = Asciz	Ljava/lang/String;;
const #10 = Asciz	<init>;
const #11 = Asciz	(Ljava/lang/String;)V;
const #12 = Asciz	Code;
const #13 = Asciz	LineNumberTable;
const #14 = Asciz	scala/actors/MQueue;
const #15 = class	#14;	//  scala/actors/MQueue
const #16 = NameAndType	#8:#9;//  label:Ljava/lang/String;
const #17 = Field	#15.#16;	//  scala/actors/MQueue.label:Ljava/lang/String;
const #18 = Asciz	java/lang/Object;
const #19 = class	#18;	//  java/lang/Object
const #20 = Asciz	()V;
const #21 = NameAndType	#10:#20;//  "<init>":()V
const #22 = Method	#19.#21;	//  java/lang/Object."<init>":()V
const #23 = NameAndType	#7:#6;//  first:Lscala/actors/MQueueElement;
const #24 = Field	#15.#23;	//  scala/actors/MQueue.first:Lscala/actors/MQueueElement;
const #25 = NameAndType	#5:#6;//  last:Lscala/actors/MQueueElement;
const #26 = Field	#15.#25;	//  scala/actors/MQueue.last:Lscala/actors/MQueueElement;
const #27 = NameAndType	#3:#4;//  _size:I
const #28 = Field	#15.#27;	//  scala/actors/MQueue._size:I
const #29 = Asciz	this;
const #30 = Asciz	Lscala/actors/MQueue;;
const #31 = Asciz	LocalVariableTable;
const #32 = Asciz	test$2;
const #33 = Asciz	(Ljava/lang/Object;Lscala/actors/OutputChannel;ILscala/Function2;Lscala/runtime/IntRef;)Z;
const #34 = Asciz	scala/Function2;
const #35 = class	#34;	//  scala/Function2
const #36 = Asciz	apply;
const #37 = Asciz	(Ljava/lang/Object;Ljava/lang/Object;)Ljava/lang/Object;;
const #38 = NameAndType	#36:#37;//  apply:(Ljava/lang/Object;Ljava/lang/Object;)Ljava/lang/Object;
const #39 = InterfaceMethod	#35.#38;	//  scala/Function2.apply:(Ljava/lang/Object;Ljava/lang/Object;)Ljava/lang/Object;
const #40 = Asciz	scala/runtime/BoxesRunTime;
const #41 = class	#40;	//  scala/runtime/BoxesRunTime
const #42 = Asciz	unboxToBoolean;
const #43 = Asciz	(Ljava/lang/Object;)Z;
const #44 = NameAndType	#42:#43;//  unboxToBoolean:(Ljava/lang/Object;)Z
const #45 = Method	#41.#44;	//  scala/runtime/BoxesRunTime.unboxToBoolean:(Ljava/lang/Object;)Z
const #46 = Asciz	scala/runtime/IntRef;
const #47 = class	#46;	//  scala/runtime/IntRef
const #48 = Asciz	elem;
const #49 = NameAndType	#48:#4;//  elem:I
const #50 = Field	#47.#49;	//  scala/runtime/IntRef.elem:I
const #51 = Asciz	msg;
const #52 = Asciz	Ljava/lang/Object;;
const #53 = Asciz	session;
const #54 = Asciz	Lscala/actors/OutputChannel;;
const #55 = Asciz	foundMsg$1;
const #56 = Asciz	(Lscala/actors/MQueueElement;)Lscala/Some;;
const #57 = Asciz	changeSize;
const #58 = Asciz	(I)V;
const #59 = NameAndType	#57:#58;//  changeSize:(I)V
const #60 = Method	#15.#59;	//  scala/actors/MQueue.changeSize:(I)V
const #61 = Asciz	scala/Some;
const #62 = class	#61;	//  scala/Some
const #63 = Asciz	(Ljava/lang/Object;)V;
const #64 = NameAndType	#10:#63;//  "<init>":(Ljava/lang/Object;)V
const #65 = Method	#62.#64;	//  scala/Some."<init>":(Ljava/lang/Object;)V
const #66 = Asciz	x;
const #67 = Asciz	test$1;
const #68 = Asciz	(Ljava/lang/Object;ILscala/Function1;Lscala/runtime/IntRef;)Z;
const #69 = Asciz	scala/Function1;
const #70 = class	#69;	//  scala/Function1
const #71 = Asciz	(Ljava/lang/Object;)Ljava/lang/Object;;
const #72 = NameAndType	#36:#71;//  apply:(Ljava/lang/Object;)Ljava/lang/Object;
const #73 = InterfaceMethod	#70.#72;	//  scala/Function1.apply:(Ljava/lang/Object;)Ljava/lang/Object;
const #74 = Asciz	removeInternal;
const #75 = Asciz	(ILscala/Function2;)Lscala/Option;;
const #76 = NameAndType	#10:#58;//  "<init>":(I)V
const #77 = Method	#47.#76;	//  scala/runtime/IntRef."<init>":(I)V
const #78 = Asciz	isEmpty;
const #79 = Asciz	()Z;
const #80 = NameAndType	#78:#79;//  isEmpty:()Z
const #81 = Method	#15.#80;	//  scala/actors/MQueue.isEmpty:()Z
const #82 = Asciz	scala/None$;
const #83 = class	#82;	//  scala/None$
const #84 = Asciz	MODULE$;
const #85 = Asciz	Lscala/None$;;
const #86 = NameAndType	#84:#85;//  MODULE$:Lscala/None$;
const #87 = Field	#83.#86;	//  scala/None$.MODULE$:Lscala/None$;
const #88 = Asciz	()Lscala/actors/MQueueElement;;
const #89 = NameAndType	#7:#88;//  first:()Lscala/actors/MQueueElement;
const #90 = Method	#15.#89;	//  scala/actors/MQueue.first:()Lscala/actors/MQueueElement;
const #91 = Asciz	scala/actors/MQueueElement;
const #92 = class	#91;	//  scala/actors/MQueueElement
const #93 = Asciz	()Ljava/lang/Object;;
const #94 = NameAndType	#51:#93;//  msg:()Ljava/lang/Object;
const #95 = Method	#92.#94;	//  scala/actors/MQueueElement.msg:()Ljava/lang/Object;
const #96 = Asciz	()Lscala/actors/OutputChannel;;
const #97 = NameAndType	#53:#96;//  session:()Lscala/actors/OutputChannel;
const #98 = Method	#92.#97;	//  scala/actors/MQueueElement.session:()Lscala/actors/OutputChannel;
const #99 = NameAndType	#32:#33;//  test$2:(Ljava/lang/Object;Lscala/actors/OutputChannel;ILscala/Function2;Lscala/runtime/IntRef;)Z
const #100 = Method	#15.#99;	//  scala/actors/MQueue.test$2:(Ljava/lang/Object;Lscala/actors/OutputChannel;ILscala/Function2;Lscala/runtime/IntRef;)Z
const #101 = Asciz	next;
const #102 = NameAndType	#101:#88;//  next:()Lscala/actors/MQueueElement;
const #103 = Method	#92.#102;	//  scala/actors/MQueueElement.next:()Lscala/actors/MQueueElement;
const #104 = Asciz	first_$eq;
const #105 = Asciz	(Lscala/actors/MQueueElement;)V;
const #106 = NameAndType	#104:#105;//  first_$eq:(Lscala/actors/MQueueElement;)V
const #107 = Method	#15.#106;	//  scala/actors/MQueue.first_$eq:(Lscala/actors/MQueueElement;)V
const #108 = NameAndType	#5:#88;//  last:()Lscala/actors/MQueueElement;
const #109 = Method	#15.#108;	//  scala/actors/MQueue.last:()Lscala/actors/MQueueElement;
const #110 = Asciz	last_$eq;
const #111 = NameAndType	#110:#105;//  last_$eq:(Lscala/actors/MQueueElement;)V
const #112 = Method	#15.#111;	//  scala/actors/MQueue.last_$eq:(Lscala/actors/MQueueElement;)V
const #113 = NameAndType	#55:#56;//  foundMsg$1:(Lscala/actors/MQueueElement;)Lscala/Some;
const #114 = Method	#15.#113;	//  scala/actors/MQueue.foundMsg$1:(Lscala/actors/MQueueElement;)Lscala/Some;
const #115 = Asciz	equals;
const #116 = NameAndType	#115:#43;//  equals:(Ljava/lang/Object;)Z
const #117 = Method	#19.#116;	//  java/lang/Object.equals:(Ljava/lang/Object;)Z
const #118 = Asciz	next_$eq;
const #119 = NameAndType	#118:#105;//  next_$eq:(Lscala/actors/MQueueElement;)V
const #120 = Method	#92.#119;	//  scala/actors/MQueueElement.next_$eq:(Lscala/actors/MQueueElement;)V
const #121 = Asciz	n$2;
const #122 = Asciz	p$2;
const #123 = Asciz	Lscala/Function2;;
const #124 = Asciz	res;
const #125 = Asciz	pos$2;
const #126 = Asciz	Lscala/runtime/IntRef;;
const #127 = Asciz	prev;
const #128 = Asciz	curr;
const #129 = Asciz	(ILscala/Function2<Ljava/lang/Object;Lscala/actors/OutputChannel<Ljava/lang/Object;>;Ljava/lang/Boolean;>;)Lscala/Option<Lscala/actors/MQueueElement;>;;
const #130 = Asciz	Signature;
const #131 = Asciz	extractFirst;
const #132 = Asciz	(Lscala/Function2;)Lscala/actors/MQueueElement;;
const #133 = NameAndType	#74:#75;//  removeInternal:(ILscala/Function2;)Lscala/Option;
const #134 = Method	#15.#133;	//  scala/actors/MQueue.removeInternal:(ILscala/Function2;)Lscala/Option;
const #135 = Asciz	scala/Predef$;
const #136 = class	#135;	//  scala/Predef$
const #137 = Asciz	Lscala/Predef$;;
const #138 = NameAndType	#84:#137;//  MODULE$:Lscala/Predef$;
const #139 = Field	#136.#138;	//  scala/Predef$.MODULE$:Lscala/Predef$;
const #140 = Asciz	conforms;
const #141 = Asciz	()Lscala/Predef$$less$colon$less;;
const #142 = NameAndType	#140:#141;//  conforms:()Lscala/Predef$$less$colon$less;
const #143 = Method	#136.#142;	//  scala/Predef$.conforms:()Lscala/Predef$$less$colon$less;
const #144 = Asciz	scala/Option;
const #145 = class	#144;	//  scala/Option
const #146 = Asciz	orNull;
const #147 = Asciz	(Lscala/Predef$$less$colon$less;)Ljava/lang/Object;;
const #148 = NameAndType	#146:#147;//  orNull:(Lscala/Predef$$less$colon$less;)Ljava/lang/Object;
const #149 = Method	#145.#148;	//  scala/Option.orNull:(Lscala/Predef$$less$colon$less;)Ljava/lang/Object;
const #150 = Asciz	p;
const #151 = Asciz	(Lscala/Function2<Ljava/lang/Object;Lscala/actors/OutputChannel<Ljava/lang/Object;>;Ljava/lang/Boolean;>;)Lscala/actors/MQueueElement;;
const #152 = Asciz	remove;
const #153 = Asciz	scala/actors/MQueue$$anonfun$remove$1;
const #154 = class	#153;	//  scala/actors/MQueue$$anonfun$remove$1
const #155 = Asciz	(Lscala/actors/MQueue;)V;
const #156 = NameAndType	#10:#155;//  "<init>":(Lscala/actors/MQueue;)V
const #157 = Method	#154.#156;	//  scala/actors/MQueue$$anonfun$remove$1."<init>":(Lscala/actors/MQueue;)V
const #158 = Asciz	map;
const #159 = Asciz	(Lscala/Function1;)Lscala/Option;;
const #160 = NameAndType	#158:#159;//  map:(Lscala/Function1;)Lscala/Option;
const #161 = Method	#145.#160;	//  scala/Option.map:(Lscala/Function1;)Lscala/Option;
const #162 = Asciz	n;
const #163 = Asciz	(ILscala/Function2<Ljava/lang/Object;Lscala/actors/OutputChannel<Ljava/lang/Object;>;Ljava/lang/Boolean;>;)Lscala/Option<Lscala/Tuple2<Ljava/lang/Object;Lscala/actors/OutputChannel<Ljava/lang/Object;>;>;>;;
const #164 = Asciz	get;
const #165 = Asciz	(ILscala/Function1;)Lscala/Option;;
const #166 = NameAndType	#67:#68;//  test$1:(Ljava/lang/Object;ILscala/Function1;Lscala/runtime/IntRef;)Z
const #167 = Method	#15.#166;	//  scala/actors/MQueue.test$1:(Ljava/lang/Object;ILscala/Function1;Lscala/runtime/IntRef;)Z
const #168 = Asciz	n$1;
const #169 = Asciz	p$1;
const #170 = Asciz	Lscala/Function1;;
const #171 = Asciz	pos$1;
const #172 = Asciz	(ILscala/Function1<Ljava/lang/Object;Ljava/lang/Boolean;>;)Lscala/Option<Ljava/lang/Object;>;;
const #173 = Asciz	foldLeft;
const #174 = Asciz	(Ljava/lang/Object;Lscala/Function2;)Ljava/lang/Object;;
const #175 = Asciz	z;
const #176 = Asciz	f;
const #177 = Asciz	acc;
const #178 = Asciz	<B:Ljava/lang/Object;>(TB;Lscala/Function2<TB;Ljava/lang/Object;TB;>;)TB;;
const #179 = Asciz	foreach;
const #180 = Asciz	(Lscala/Function2;)V;
const #181 = Asciz	(Lscala/Function2<Ljava/lang/Object;Lscala/actors/OutputChannel<Ljava/lang/Object;>;Ljava/lang/Object;>;)V;
const #182 = Asciz	append;
const #183 = Asciz	(Ljava/lang/Object;Lscala/actors/OutputChannel;)V;
const #184 = NameAndType	#10:#183;//  "<init>":(Ljava/lang/Object;Lscala/actors/OutputChannel;)V
const #185 = Method	#92.#184;	//  scala/actors/MQueueElement."<init>":(Ljava/lang/Object;Lscala/actors/OutputChannel;)V
const #186 = Asciz	el;
const #187 = Asciz	(Ljava/lang/Object;Lscala/actors/OutputChannel<Ljava/lang/Object;>;)V;
const #188 = Asciz	()I;
const #189 = NameAndType	#3:#188;//  _size:()I
const #190 = Method	#15.#189;	//  scala/actors/MQueue._size:()I
const #191 = Asciz	_size_$eq;
const #192 = NameAndType	#191:#58;//  _size_$eq:(I)V
const #193 = Method	#15.#192;	//  scala/actors/MQueue._size_$eq:(I)V
const #194 = Asciz	diff;
const #195 = Asciz	size;
const #196 = Asciz	()Ljava/lang/String;;
const #197 = Asciz	ScalaSig;
const #198 = Asciz	InnerClasses;
const #199 = Asciz	scala/Predef$$less$colon$less;
const #200 = class	#199;	//  scala/Predef$$less$colon$less
const #201 = Asciz	scala/Predef;
const #202 = class	#201;	//  scala/Predef
const #203 = Asciz	$less$colon$less;
const #204 = Asciz	$anonfun$remove$1;
const #205 = Asciz	scala/ScalaObject;
const #206 = class	#205;	//  scala/ScalaObject

{
public scala.actors.MQueue(java.lang.String);
  Code:
   Stack=2, Locals=2, Args_size=2
   0:	aload_0
   1:	aload_1
   2:	putfield	#17; //Field label:Ljava/lang/String;
   5:	aload_0
   6:	invokespecial	#22; //Method java/lang/Object."<init>":()V
   9:	aload_0
   10:	aconst_null
   11:	putfield	#24; //Field first:Lscala/actors/MQueueElement;
   14:	aload_0
   15:	aconst_null
   16:	putfield	#26; //Field last:Lscala/actors/MQueueElement;
   19:	aload_0
   20:	iconst_0
   21:	putfield	#28; //Field _size:I
   24:	return
  LineNumberTable: 
   line 43: 0
   line 44: 9
   line 45: 14
   line 46: 19

  LocalVariableTable: 
   Start  Length  Slot  Name   Signature
   0      25      0    this       Lscala/actors/MQueue;
   0      25      1    label       Ljava/lang/String;


public scala.actors.MQueueElement extractFirst(scala.Function2);
  Code:
   Stack=3, Locals=2, Args_size=2
   0:	aload_0
   1:	iconst_0
   2:	aload_1
   3:	invokespecial	#134; //Method removeInternal:(ILscala/Function2;)Lscala/Option;
   6:	getstatic	#139; //Field scala/Predef$.MODULE$:Lscala/Predef$;
   9:	invokevirtual	#143; //Method scala/Predef$.conforms:()Lscala/Predef$$less$colon$less;
   12:	invokevirtual	#149; //Method scala/Option.orNull:(Lscala/Predef$$less$colon$less;)Ljava/lang/Object;
   15:	checkcast	#92; //class scala/actors/MQueueElement
   18:	areturn
  LineNumberTable: 
   line 109: 0

  LocalVariableTable: 
   Start  Length  Slot  Name   Signature
   0      19      0    this       Lscala/actors/MQueue;
   0      19      1    p       Lscala/Function2;

  Signature: length = 0x2
   00 FFFFFF97 

public scala.Option remove(int, scala.Function2);
  Code:
   Stack=4, Locals=3, Args_size=3
   0:	aload_0
   1:	iload_1
   2:	aload_2
   3:	invokespecial	#134; //Method removeInternal:(ILscala/Function2;)Lscala/Option;
   6:	new	#154; //class scala/actors/MQueue$$anonfun$remove$1
   9:	dup
   10:	aload_0
   11:	invokespecial	#157; //Method scala/actors/MQueue$$anonfun$remove$1."<init>":(Lscala/actors/MQueue;)V
   14:	invokevirtual	#161; //Method scala/Option.map:(Lscala/Function1;)Lscala/Option;
   17:	areturn
  LineNumberTable: 
   line 103: 0

  LocalVariableTable: 
   Start  Length  Slot  Name   Signature
   0      18      0    this       Lscala/actors/MQueue;
   0      18      1    n       I
   0      18      2    p       Lscala/Function2;

  Signature: length = 0x2
   00 FFFFFFA3 

public scala.Option get(int, scala.Function1);
  Code:
   Stack=5, Locals=5, Args_size=3
   0:	new	#47; //class scala/runtime/IntRef
   3:	dup
   4:	iconst_0
   5:	invokespecial	#77; //Method scala/runtime/IntRef."<init>":(I)V
   8:	astore_3
   9:	aload_0
   10:	invokevirtual	#90; //Method first:()Lscala/actors/MQueueElement;
   13:	astore	4
   15:	aload	4
   17:	dup
   18:	pop
   19:	ifnull	31
   22:	aload	4
   24:	aconst_null
   25:	invokevirtual	#117; //Method java/lang/Object.equals:(Ljava/lang/Object;)Z
   28:	ifeq	35
   31:	getstatic	#87; //Field scala/None$.MODULE$:Lscala/None$;
   34:	areturn
   35:	aload_0
   36:	aload	4
   38:	invokevirtual	#95; //Method scala/actors/MQueueElement.msg:()Ljava/lang/Object;
   41:	iload_1
   42:	aload_2
   43:	aload_3
   44:	invokespecial	#167; //Method test$1:(Ljava/lang/Object;ILscala/Function1;Lscala/runtime/IntRef;)Z
   47:	ifeq	63
   50:	new	#62; //class scala/Some
   53:	dup
   54:	aload	4
   56:	invokevirtual	#95; //Method scala/actors/MQueueElement.msg:()Ljava/lang/Object;
   59:	invokespecial	#65; //Method scala/Some."<init>":(Ljava/lang/Object;)V
   62:	areturn
   63:	aload	4
   65:	invokevirtual	#103; //Method scala/actors/MQueueElement.next:()Lscala/actors/MQueueElement;
   68:	astore	4
   70:	goto	15
  LineNumberTable: 
   line 87: 0
   line 92: 9
   line 93: 15
   line 97: 31
   line 94: 35
   line 95: 63
   line 94: 70

  LocalVariableTable: 
   Start  Length  Slot  Name   Signature
   0      73      0    this       Lscala/actors/MQueue;
   0      73      1    n$1       I
   0      73      2    p$1       Lscala/Function1;
   9      25      3    pos$1       Lscala/runtime/IntRef;
   35      38      3    pos$1       Lscala/runtime/IntRef;
   15      19      4    curr       Lscala/actors/MQueueElement;
   35      38      4    curr       Lscala/actors/MQueueElement;

  Signature: length = 0x2
   00 FFFFFFAC 

public java.lang.Object foldLeft(java.lang.Object, scala.Function2);
  Code:
   Stack=3, Locals=5, Args_size=3
   0:	aload_1
   1:	astore_3
   2:	aload_0
   3:	invokevirtual	#90; //Method first:()Lscala/actors/MQueueElement;
   6:	astore	4
   8:	aload	4
   10:	dup
   11:	pop
   12:	ifnull	24
   15:	aload	4
   17:	aconst_null
   18:	invokevirtual	#117; //Method java/lang/Object.equals:(Ljava/lang/Object;)Z
   21:	ifeq	26
   24:	aload_3
   25:	areturn
   26:	aload_2
   27:	aload_3
   28:	aload	4
   30:	invokevirtual	#95; //Method scala/actors/MQueueElement.msg:()Ljava/lang/Object;
   33:	invokeinterface	#39,  3; //InterfaceMethod scala/Function2.apply:(Ljava/lang/Object;Ljava/lang/Object;)Ljava/lang/Object;
   38:	astore_3
   39:	aload	4
   41:	invokevirtual	#103; //Method scala/actors/MQueueElement.next:()Lscala/actors/MQueueElement;
   44:	astore	4
   46:	goto	8
  LineNumberTable: 
   line 74: 0
   line 75: 2
   line 76: 8
   line 80: 24
   line 77: 26
   line 78: 39

  LocalVariableTable: 
   Start  Length  Slot  Name   Signature
   0      49      0    this       Lscala/actors/MQueue;
   0      49      1    z       Ljava/lang/Object;
   0      49      2    f       Lscala/Function2;
   2      23      3    acc       Ljava/lang/Object;
   26      23      3    acc       Ljava/lang/Object;
   8      17      4    curr       Lscala/actors/MQueueElement;
   26      23      4    curr       Lscala/actors/MQueueElement;

  Signature: length = 0x2
   00 FFFFFFB2 

public void foreach(scala.Function2);
  Code:
   Stack=3, Locals=3, Args_size=2
   0:	aload_0
   1:	invokevirtual	#90; //Method first:()Lscala/actors/MQueueElement;
   4:	astore_2
   5:	aload_2
   6:	dup
   7:	pop
   8:	ifnull	19
   11:	aload_2
   12:	aconst_null
   13:	invokevirtual	#117; //Method java/lang/Object.equals:(Ljava/lang/Object;)Z
   16:	ifeq	20
   19:	return
   20:	aload_1
   21:	aload_2
   22:	invokevirtual	#95; //Method scala/actors/MQueueElement.msg:()Ljava/lang/Object;
   25:	aload_2
   26:	invokevirtual	#98; //Method scala/actors/MQueueElement.session:()Lscala/actors/OutputChannel;
   29:	invokeinterface	#39,  3; //InterfaceMethod scala/Function2.apply:(Ljava/lang/Object;Ljava/lang/Object;)Ljava/lang/Object;
   34:	pop
   35:	aload_2
   36:	invokevirtual	#103; //Method scala/actors/MQueueElement.next:()Lscala/actors/MQueueElement;
   39:	astore_2
   40:	goto	5
  LineNumberTable: 
   line 66: 0
   line 67: 5
   line 65: 19
   line 68: 20
   line 69: 35

  LocalVariableTable: 
   Start  Length  Slot  Name   Signature
   0      43      0    this       Lscala/actors/MQueue;
   0      43      1    f       Lscala/Function2;
   5      38      2    curr       Lscala/actors/MQueueElement;

  Signature: length = 0x2
   00 FFFFFFB5 

public void append(java.lang.Object, scala.actors.OutputChannel);
  Code:
   Stack=4, Locals=4, Args_size=3
   0:	aload_0
   1:	iconst_1
   2:	invokevirtual	#60; //Method changeSize:(I)V
   5:	new	#92; //class scala/actors/MQueueElement
   8:	dup
   9:	aload_1
   10:	aload_2
   11:	invokespecial	#185; //Method scala/actors/MQueueElement."<init>":(Ljava/lang/Object;Lscala/actors/OutputChannel;)V
   14:	astore_3
   15:	aload_0
   16:	invokevirtual	#81; //Method isEmpty:()Z
   19:	ifeq	30
   22:	aload_0
   23:	aload_3
   24:	invokevirtual	#107; //Method first_$eq:(Lscala/actors/MQueueElement;)V
   27:	goto	38
   30:	aload_0
   31:	invokevirtual	#109; //Method last:()Lscala/actors/MQueueElement;
   34:	aload_3
   35:	invokevirtual	#120; //Method scala/actors/MQueueElement.next_$eq:(Lscala/actors/MQueueElement;)V
   38:	aload_0
   39:	aload_3
   40:	invokevirtual	#112; //Method last_$eq:(Lscala/actors/MQueueElement;)V
   43:	return
  LineNumberTable: 
   line 56: 0
   line 57: 5
   line 59: 15
   line 60: 30
   line 62: 38

  LocalVariableTable: 
   Start  Length  Slot  Name   Signature
   0      44      0    this       Lscala/actors/MQueue;
   0      44      1    msg       Ljava/lang/Object;
   0      44      2    session       Lscala/actors/OutputChannel;
   15      28      3    el       Lscala/actors/MQueueElement;

  Signature: length = 0x2
   00 FFFFFFBB 

public void changeSize(int);
  Code:
   Stack=3, Locals=2, Args_size=2
   0:	aload_0
   1:	aload_0
   2:	invokespecial	#190; //Method _size:()I
   5:	iload_1
   6:	iadd
   7:	invokespecial	#193; //Method _size_$eq:(I)V
   10:	return
  LineNumberTable: 
   line 52: 0

  LocalVariableTable: 
   Start  Length  Slot  Name   Signature
   0      11      0    this       Lscala/actors/MQueue;
   0      11      1    diff       I


public final boolean isEmpty();
  Code:
   Stack=1, Locals=1, Args_size=1
   0:	aload_0
   1:	invokevirtual	#109; //Method last:()Lscala/actors/MQueueElement;
   4:	ifnonnull	11
   7:	iconst_1
   8:	goto	12
   11:	iconst_0
   12:	ireturn
  LineNumberTable: 
   line 49: 0


public int size();
  Code:
   Stack=1, Locals=1, Args_size=1
   0:	aload_0
   1:	invokespecial	#190; //Method _size:()I
   4:	ireturn
  LineNumberTable: 
   line 48: 0


public void last_$eq(scala.actors.MQueueElement);
  Code:
   Stack=2, Locals=2, Args_size=2
   0:	aload_0
   1:	aload_1
   2:	putfield	#26; //Field last:Lscala/actors/MQueueElement;
   5:	return
  LineNumberTable: 
   line 45: 0


public scala.actors.MQueueElement last();
  Code:
   Stack=1, Locals=1, Args_size=1
   0:	aload_0
   1:	getfield	#26; //Field last:Lscala/actors/MQueueElement;
   4:	areturn
  LineNumberTable: 
   line 45: 0


public void first_$eq(scala.actors.MQueueElement);
  Code:
   Stack=2, Locals=2, Args_size=2
   0:	aload_0
   1:	aload_1
   2:	putfield	#24; //Field first:Lscala/actors/MQueueElement;
   5:	return
  LineNumberTable: 
   line 44: 0


public scala.actors.MQueueElement first();
  Code:
   Stack=1, Locals=1, Args_size=1
   0:	aload_0
   1:	getfield	#24; //Field first:Lscala/actors/MQueueElement;
   4:	areturn
  LineNumberTable: 
   line 44: 0


public java.lang.String label();
  Code:
   Stack=1, Locals=1, Args_size=1
   0:	aload_0
   1:	getfield	#17; //Field label:Ljava/lang/String;
   4:	areturn
  LineNumberTable: 
   line 43: 0


}

