Compiled from "MessageQueue.scala"
public class scala.actors.MQueueElement extends java.lang.Object implements scala.ScalaObject
  SourceFile: "MessageQueue.scala"
  Signature: length = 0x2
   00 2E 
  ScalaSig: length = 0x1BE
   05 00 48 06 05 01 02 00 02 06 02 0D 4D 51 75 65
   75 65 45 6C 65 6D 65 6E 74 0A 02 03 04 01 06 61
   63 74 6F 72 73 0A 01 05 01 05 73 63 61 6C 61 15
   02 07 1A 13 03 00 08 10 10 02 09 0E 0D 01 0A 0A
   02 0B 0C 01 04 6C 61 6E 67 0A 01 0D 01 04 6A 61
   76 61 09 02 0F 0A 02 06 4F 62 6A 65 63 74 10 02
   11 12 0D 01 04 09 02 13 04 02 0B 53 63 61 6C 61
   4F 62 6A 65 63 74 08 08 15 00 FFFFFF82 FFFFFFC2 FFFFFF80 FFFFFF84 00 17
   01 03 6D 73 67 03 00 15 01 18 10 02 19 1A 0C 00
   04 08 1B 00 FFFFFF84 FFFFFF80 FFFFFF80 FFFFFFC2 00 1C 02 03 4D 73 67 11
   02 1D 20 10 02 11 1E 09 02 1F 04 02 04 4E 75 6C
   6C 10 02 11 21 09 02 22 04 02 03 41 6E 79 08 08
   24 00 FFFFFF82 FFFFFF80 FFFFFFA0 FFFFFF80 04 18 01 04 6D 73 67 20 08 08
   26 00 FFFFFF82 FFFFFFC2 FFFFFF80 FFFFFF84 00 27 01 07 73 65 73 73 69 6F
   6E 15 01 28 10 03 29 2A 20 0D 01 02 09 02 2B 02
   02 0D 4F 75 74 70 75 74 43 68 61 6E 6E 65 6C 08
   08 2D 00 FFFFFF82 FFFFFF80 FFFFFFA0 FFFFFF80 04 28 01 08 73 65 73 73 69
   6F 6E 20 08 08 2F 00 FFFFFF82 FFFFFFC0 FFFFFF80 FFFFFF84 00 30 01 04 6E
   65 78 74 15 01 31 10 03 29 00 18 08 08 33 00 FFFFFF82
   FFFFFFC0 FFFFFF80 FFFFFF84 00 34 01 08 6E 65 78 74 5F 24 65 71 14
   02 35 38 10 02 11 36 09 02 37 04 02 04 55 6E 69
   74 08 07 39 32 FFFFFF81 FFFFFF80 FFFFFFC0 00 31 01 03 78 24 31 08
   08 3B 00 FFFFFF82 FFFFFF80 FFFFFFA0 FFFFFFA0 04 31 01 05 6E 65 78 74 20
   08 05 3D 00 FFFFFF84 00 3E 01 06 3C 69 6E 69 74 3E 14
   04 31 3F 40 41 08 05 15 3C FFFFFFC0 00 18 08 05 26 3C
   FFFFFFC0 00 28 08 05 2F 3C FFFFFFC0 00 31 08 05 3D 00 FFFFFF84 00
   43 14 01 31 08 05 3D 00 FFFFFF84 00 45 14 03 31 46 47
   08 05 15 44 FFFFFFC0 00 18 08 05 26 44 FFFFFFC0 00 28 
  minor version: 0
  major version: 49
  Constant pool:
Asciz	SourceFile;
Asciz	MessageQueue.scala;
Asciz	next;
Asciz	Lscala/actors/MQueueElement;;
Asciz	Lscala/actors/MQueueElement<TMsg;>;;
Asciz	Signature;
Asciz	session;
Asciz	Lscala/actors/OutputChannel;;
Asciz	Lscala/actors/OutputChannel<Ljava/lang/Object;>;;
Asciz	msg;
Asciz	Ljava/lang/Object;;
Asciz	TMsg;;
Asciz	()Ljava/lang/Object;;
Asciz	Code;
Asciz	LineNumberTable;
Asciz	scala/actors/MQueueElement;
class	scala/actors/MQueueElement
NameAndType	msg:Ljava/lang/Object;
Field	scala/actors/MQueueElement.msg:Ljava/lang/Object;
Asciz	()TMsg;;
Asciz	()Lscala/actors/OutputChannel;;
NameAndType	session:Lscala/actors/OutputChannel;
Field	scala/actors/MQueueElement.session:Lscala/actors/OutputChannel;
Asciz	()Lscala/actors/OutputChannel<Ljava/lang/Object;>;;
Asciz	()Lscala/actors/MQueueElement;;
NameAndType	next:Lscala/actors/MQueueElement;
Field	scala/actors/MQueueElement.next:Lscala/actors/MQueueElement;
Asciz	()Lscala/actors/MQueueElement<TMsg;>;;
Asciz	next_$eq;
Asciz	(Lscala/actors/MQueueElement;)V;
Asciz	(Lscala/actors/MQueueElement<TMsg;>;)V;
Asciz	<init>;
Asciz	()V;
Asciz	(Ljava/lang/Object;Lscala/actors/OutputChannel;Lscala/actors/MQueueElement;)V;
NameAndType	"<init>":(Ljava/lang/Object;Lscala/actors/OutputChannel;Lscala/actors/MQueueElement;)V
Method	scala/actors/MQueueElement."<init>":(Ljava/lang/Object;Lscala/actors/OutputChannel;Lscala/actors/MQueueElement;)V
Asciz	(Ljava/lang/Object;Lscala/actors/OutputChannel;)V;
Asciz	this;
Asciz	LocalVariableTable;
Asciz	(TMsg;Lscala/actors/OutputChannel<Ljava/lang/Object;>;)V;
Asciz	java/lang/Object;
class	java/lang/Object
NameAndType	"<init>":()V
Method	java/lang/Object."<init>":()V
Asciz	(TMsg;Lscala/actors/OutputChannel<Ljava/lang/Object;>;Lscala/actors/MQueueElement<TMsg;>;)V;
Asciz	<Msg:Ljava/lang/Object;>Ljava/lang/Object;Lscala/ScalaObject;;
Asciz	ScalaSig;
Asciz	scala/ScalaObject;
class	scala/ScalaObject

{
private scala.actors.MQueueElement next;
  Signature: Lscala/actors/MQueueElement;
  Signature: length = 0x2
   00 05 

private final scala.actors.OutputChannel session;
  Signature: Lscala/actors/OutputChannel;
  Signature: length = 0x2
   00 09 

private final java.lang.Object msg;
  Signature: Ljava/lang/Object;
  Signature: length = 0x2
   00 0C 

public java.lang.Object msg();
  Signature: ()Ljava/lang/Object;
  Code:
   Stack=1, Locals=1, Args_size=1
	aload_0
	getfield	Field msg:Ljava/lang/Object;
	areturn
  Labels:
  Signature: length = 0x2
   00 14 

public scala.actors.OutputChannel session();
  Signature: ()Lscala/actors/OutputChannel;
  Code:
   Stack=1, Locals=1, Args_size=1
	aload_0
	getfield	Field session:Lscala/actors/OutputChannel;
	areturn
  Labels:
  Signature: length = 0x2
   00 18 

public scala.actors.MQueueElement next();
  Signature: ()Lscala/actors/MQueueElement;
  Code:
   Stack=1, Locals=1, Args_size=1
	aload_0
	getfield	Field next:Lscala/actors/MQueueElement;
	areturn
  Labels:
  Signature: length = 0x2
   00 1C 

public void next_$eq(scala.actors.MQueueElement);
  Signature: (Lscala/actors/MQueueElement;)V
  Code:
   Stack=2, Locals=2, Args_size=2
	aload_0
	aload_1
	putfield	Field next:Lscala/actors/MQueueElement;
	return
  Labels:
  Signature: length = 0x2
   00 1F 

public scala.actors.MQueueElement();
  Signature: ()V
  Code:
   Stack=4, Locals=1, Args_size=1
	aload_0
	aconst_null
	pop
	aconst_null
	aconst_null
	pop
	aconst_null
	aconst_null
	pop
	aconst_null
	invokespecial	Method "<init>":(Ljava/lang/Object;Lscala/actors/OutputChannel;Lscala/actors/MQueueElement;)V
	return
  Labels:
  Signature: length = 0x2
   00 21 

public scala.actors.MQueueElement(java.lang.Object, scala.actors.OutputChannel);
  Signature: (Ljava/lang/Object;Lscala/actors/OutputChannel;)V
  Code:
   Stack=4, Locals=3, Args_size=3
	aload_0
	aload_1
	aload_2
	aconst_null
	pop
	aconst_null
	invokespecial	Method "<init>":(Ljava/lang/Object;Lscala/actors/OutputChannel;Lscala/actors/MQueueElement;)V
	return
  Labels:
  LocalVariableTable: 
   Start  Length  Slot  Name   Signature
   0      10      0    this       Lscala/actors/MQueueElement;
   0      10      1    msg       Ljava/lang/Object;
   0      10      2    session       Lscala/actors/OutputChannel;

  Signature: length = 0x2
   00 28 

public scala.actors.MQueueElement(java.lang.Object, scala.actors.OutputChannel, scala.actors.MQueueElement);
  Signature: (Ljava/lang/Object;Lscala/actors/OutputChannel;Lscala/actors/MQueueElement;)V
  Code:
   Stack=2, Locals=4, Args_size=4
	aload_0
	aload_1
	putfield	Field msg:Ljava/lang/Object;
	aload_0
	aload_2
	putfield	Field session:Lscala/actors/OutputChannel;
	aload_0
	aload_3
	putfield	Field next:Lscala/actors/MQueueElement;
	aload_0
	invokespecial	Method java/lang/Object."<init>":()V
	return
  Labels:
  LocalVariableTable: 
   Start  Length  Slot  Name   Signature
   0      20      0    this       Lscala/actors/MQueueElement;
   0      20      1    msg       Ljava/lang/Object;
   0      20      2    session       Lscala/actors/OutputChannel;
   0      20      3    next       Lscala/actors/MQueueElement;

  Signature: length = 0x2
   00 2D 

}

