Compiled from "package.scala"
public final class scala.actors.package$ extends java.lang.Object implements scala.ScalaObject
  SourceFile: "package.scala"
  Scala: length = 0x
   
  minor version: 0
  major version: 49
  Constant pool:
Asciz	SourceFile;
Asciz	package.scala;
Asciz	MODULE$;
Asciz	Lscala/actors/package$;;
Asciz	<clinit>;
Asciz	()V;
Asciz	Code;
Asciz	scala/actors/package$;
class	scala/actors/package$
Asciz	<init>;
NameAndType	"<init>":()V
Method	scala/actors/package$."<init>":()V
Asciz	ActorGC;
Asciz	Lscala/actors/IScheduler;;
Asciz	()Lscala/actors/IScheduler;;
Asciz	LineNumberTable;
NameAndType	ActorGC:Lscala/actors/IScheduler;
Field	scala/actors/package$.ActorGC:Lscala/actors/IScheduler;
Asciz	Deprecated;
Asciz	java/lang/Object;
class	java/lang/Object
Method	java/lang/Object."<init>":()V
NameAndType	MODULE$:Lscala/actors/package$;
Field	scala/actors/package$.MODULE$:Lscala/actors/package$;
Asciz	scala/actors/Scheduler$;
class	scala/actors/Scheduler$
Asciz	Lscala/actors/Scheduler$;;
NameAndType	MODULE$:Lscala/actors/Scheduler$;
Field	scala/actors/Scheduler$.MODULE$:Lscala/actors/Scheduler$;
Asciz	scala/actors/scheduler/DelegatingScheduler;
class	scala/actors/scheduler/DelegatingScheduler
Asciz	impl;
NameAndType	impl:()Lscala/actors/IScheduler;
InterfaceMethod	scala/actors/scheduler/DelegatingScheduler.impl:()Lscala/actors/IScheduler;
Asciz	scala/actors/IScheduler;
class	scala/actors/IScheduler
Asciz	scala/actors/scheduler/ActorGC;
class	scala/actors/scheduler/ActorGC
Asciz	this;
Asciz	temp1;
Asciz	LocalVariableTable;
Asciz	Scala;
Asciz	scala/ScalaObject;
class	scala/ScalaObject

{
public static final scala.actors.package$ MODULE$;
  Signature: Lscala/actors/package$;

private final scala.actors.IScheduler ActorGC;
  Signature: Lscala/actors/IScheduler;

public static {};
  Signature: ()V
  Code:
   Stack=1, Locals=0, Args_size=0
	new	class scala/actors/package$
	invokespecial	Method "<init>":()V
	return
  Labels:

public scala.actors.IScheduler ActorGC();
  Signature: ()Lscala/actors/IScheduler;
  Code:
   Stack=1, Locals=1, Args_size=1
	aload_0
	getfield	Field ActorGC:Lscala/actors/IScheduler;
	areturn
  Labels:
  Deprecated: true

private scala.actors.package$();
  Signature: ()V
  Code:
   Stack=2, Locals=2, Args_size=1
	aload_0
	invokespecial	Method java/lang/Object."<init>":()V
	aload_0
	putstatic	Field MODULE$:Lscala/actors/package$;
	aload_0
	getstatic	Field scala/actors/Scheduler$.MODULE$:Lscala/actors/Scheduler$;
	invokeinterface	InterfaceMethod scala/actors/scheduler/DelegatingScheduler.impl:()Lscala/actors/IScheduler;
	astore_1
	aload_1
	instanceof	class scala/actors/IScheduler
	ifeq	l1 // iconst_0
	aload_1
	instanceof	class scala/actors/scheduler/ActorGC
	ifeq	l1 // iconst_0
	iconst_1
	goto	l2 // ifeq
l1	iconst_0
l2	ifeq	l3 // aconst_null
	aload_1
	goto	l4 // putfield
l3	aconst_null
l4	putfield	Field ActorGC:Lscala/actors/IScheduler;
	return
  Labels:
   	l1 = 36 // iconst_0
   	l2 = 37 // ifeq
   	l3 = 44 // aconst_null
   	l4 = 45 // putfield
  LocalVariableTable: 
   Start  Length  Slot  Name   Signature
   0      49      0    this       Lscala/actors/package$;
   18      31      1    temp1       Lscala/actors/IScheduler;


}

