Compiled from "package.scala"
public final class scala.actors.package$ extends java.lang.Object implements scala.ScalaObject
  SourceFile: "package.scala"
  Scala: length = 0x
   
  minor version: 0
  major version: 49
  Constant pool:
const #1 = Asciz	SourceFile;
const #2 = Asciz	package.scala;
const #3 = Asciz	Scala;
const #4 = Asciz	MODULE$;
const #5 = Asciz	Lscala/actors/package$;;
const #6 = Asciz	<clinit>;
const #7 = Asciz	()V;
const #8 = Asciz	Code;
const #9 = Asciz	scala/actors/package$;
const #10 = class	#9;	//  scala/actors/package$
const #11 = Asciz	<init>;
const #12 = NameAndType	#11:#7;//  "<init>":()V
const #13 = Method	#10.#12;	//  scala/actors/package$."<init>":()V
const #14 = Asciz	ActorGC;
const #15 = Asciz	Lscala/actors/scheduler/ThreadPoolScheduler;;
const #16 = Asciz	LineNumberTable;
const #17 = Asciz	java/lang/Object;
const #18 = class	#17;	//  java/lang/Object
const #19 = Method	#18.#12;	//  java/lang/Object."<init>":()V
const #20 = NameAndType	#4:#5;//  MODULE$:Lscala/actors/package$;
const #21 = Field	#10.#20;	//  scala/actors/package$.MODULE$:Lscala/actors/package$;
const #22 = Asciz	scala/actors/Scheduler$;
const #23 = class	#22;	//  scala/actors/Scheduler$
const #24 = Asciz	Lscala/actors/Scheduler$;;
const #25 = NameAndType	#4:#24;//  MODULE$:Lscala/actors/Scheduler$;
const #26 = Field	#23.#25;	//  scala/actors/Scheduler$.MODULE$:Lscala/actors/Scheduler$;
const #27 = Asciz	scala/actors/scheduler/DelegatingScheduler;
const #28 = class	#27;	//  scala/actors/scheduler/DelegatingScheduler
const #29 = Asciz	impl;
const #30 = Asciz	()Lscala/actors/IScheduler;;
const #31 = NameAndType	#29:#30;//  impl:()Lscala/actors/IScheduler;
const #32 = InterfaceMethod	#28.#31;	//  scala/actors/scheduler/DelegatingScheduler.impl:()Lscala/actors/IScheduler;
const #33 = Asciz	scala/actors/scheduler/ThreadPoolScheduler;
const #34 = class	#33;	//  scala/actors/scheduler/ThreadPoolScheduler
const #35 = NameAndType	#14:#15;//  ActorGC:Lscala/actors/scheduler/ThreadPoolScheduler;
const #36 = Field	#10.#35;	//  scala/actors/package$.ActorGC:Lscala/actors/scheduler/ThreadPoolScheduler;
const #37 = Asciz	()Lscala/actors/scheduler/ThreadPoolScheduler;;
const #38 = Asciz	scala/ScalaObject;
const #39 = class	#38;	//  scala/ScalaObject

{
public static final scala.actors.package$ MODULE$;

public static {};
  Code:
   Stack=1, Locals=0, Args_size=0
   0:	new	#10; //class scala/actors/package$
   3:	invokespecial	#13; //Method "<init>":()V
   6:	return

public scala.actors.scheduler.ThreadPoolScheduler ActorGC();
  Code:
   Stack=1, Locals=1, Args_size=1
   0:	aload_0
   1:	getfield	#36; //Field ActorGC:Lscala/actors/scheduler/ThreadPoolScheduler;
   4:	areturn
  LineNumberTable: 
   line 17: 0


}

