Compiled from "Reactor.scala"
public abstract class scala.actors.Reactor$class extends java.lang.Object
  SourceFile: "Reactor.scala"
  Scala: length = 0x
   
  InnerClass: 
   public final #357= #325 of #16; //$anonfun$2=class scala/actors/Reactor$$anonfun$2 of class scala/actors/Reactor
   public final #358= #194 of #16; //$anonfun$3=class scala/actors/Reactor$$anonfun$3 of class scala/actors/Reactor
   public final #359= #133 of #16; //$anonfun$4=class scala/actors/Reactor$$anonfun$4 of class scala/actors/Reactor
   public final #360= #119 of #16; //$anonfun$5=class scala/actors/Reactor$$anonfun$5 of class scala/actors/Reactor
   public final #361= #50 of #16; //$anonfun$6=class scala/actors/Reactor$$anonfun$6 of class scala/actors/Reactor
   public final #362= #35 of #16; //$anonfun$1=class scala/actors/Reactor$$anonfun$1 of class scala/actors/Reactor
   public final #363= #93 of #16; //$anonfun$seq$1=class scala/actors/Reactor$$anonfun$seq$1 of class scala/actors/Reactor
   public final #364= #183 of #16; //$anonfun$react$2=class scala/actors/Reactor$$anonfun$react$2 of class scala/actors/Reactor
   public final #365= #153 of #16; //$anonfun$react$1=class scala/actors/Reactor$$anonfun$react$1 of class scala/actors/Reactor
   public final #366= #294 of #16; //$anonfun$startSearch$1=class scala/actors/Reactor$$anonfun$startSearch$1 of class scala/actors/Reactor
   public final #367= #203 of #16; //$anonfun$searchMailbox$1=class scala/actors/Reactor$$anonfun$searchMailbox$1 of class scala/actors/Reactor
  minor version: 0
  major version: 49
  Constant pool:
const #1 = Asciz	SourceFile;
const #2 = Asciz	Reactor.scala;
const #3 = Asciz	$init$;
const #4 = Asciz	(Lscala/actors/Reactor;)V;
const #5 = Asciz	Code;
const #6 = Asciz	LineNumberTable;
const #7 = Asciz	scala/actors/MessageQueue;
const #8 = class	#7;	//  scala/actors/MessageQueue
const #9 = Asciz	Reactor;
const #10 = String	#9;	//  Reactor
const #11 = Asciz	<init>;
const #12 = Asciz	(Ljava/lang/String;)V;
const #13 = NameAndType	#11:#12;//  "<init>":(Ljava/lang/String;)V
const #14 = Method	#8.#13;	//  scala/actors/MessageQueue."<init>":(Ljava/lang/String;)V
const #15 = Asciz	scala/actors/Reactor;
const #16 = class	#15;	//  scala/actors/Reactor
const #17 = Asciz	scala$actors$Reactor$_setter_$mailbox_$eq;
const #18 = Asciz	(Lscala/actors/MessageQueue;)V;
const #19 = NameAndType	#17:#18;//  scala$actors$Reactor$_setter_$mailbox_$eq:(Lscala/actors/MessageQueue;)V
const #20 = InterfaceMethod	#16.#19;	//  scala/actors/Reactor.scala$actors$Reactor$_setter_$mailbox_$eq:(Lscala/actors/MessageQueue;)V
const #21 = Asciz	scala/collection/mutable/Queue;
const #22 = class	#21;	//  scala/collection/mutable/Queue
const #23 = Asciz	()V;
const #24 = NameAndType	#11:#23;//  "<init>":()V
const #25 = Method	#22.#24;	//  scala/collection/mutable/Queue."<init>":()V
const #26 = Asciz	scala$actors$Reactor$_setter_$sendBuffer_$eq;
const #27 = Asciz	(Lscala/collection/mutable/Queue;)V;
const #28 = NameAndType	#26:#27;//  scala$actors$Reactor$_setter_$sendBuffer_$eq:(Lscala/collection/mutable/Queue;)V
const #29 = InterfaceMethod	#16.#28;	//  scala/actors/Reactor.scala$actors$Reactor$_setter_$sendBuffer_$eq:(Lscala/collection/mutable/Queue;)V
const #30 = Asciz	continuation_$eq;
const #31 = Asciz	(Lscala/PartialFunction;)V;
const #32 = NameAndType	#30:#31;//  continuation_$eq:(Lscala/PartialFunction;)V
const #33 = InterfaceMethod	#16.#32;	//  scala/actors/Reactor.continuation_$eq:(Lscala/PartialFunction;)V
const #34 = Asciz	scala/actors/Reactor$$anonfun$1;
const #35 = class	#34;	//  scala/actors/Reactor$$anonfun$1
const #36 = NameAndType	#11:#4;//  "<init>":(Lscala/actors/Reactor;)V
const #37 = Method	#35.#36;	//  scala/actors/Reactor$$anonfun$1."<init>":(Lscala/actors/Reactor;)V
const #38 = Asciz	scala$actors$Reactor$_setter_$waitingForNone_$eq;
const #39 = Asciz	(Lscala/Function1;)V;
const #40 = NameAndType	#38:#39;//  scala$actors$Reactor$_setter_$waitingForNone_$eq:(Lscala/Function1;)V
const #41 = InterfaceMethod	#16.#40;	//  scala/actors/Reactor.scala$actors$Reactor$_setter_$waitingForNone_$eq:(Lscala/Function1;)V
const #42 = Asciz	waitingForNone;
const #43 = Asciz	()Lscala/Function1;;
const #44 = NameAndType	#42:#43;//  waitingForNone:()Lscala/Function1;
const #45 = InterfaceMethod	#16.#44;	//  scala/actors/Reactor.waitingForNone:()Lscala/Function1;
const #46 = Asciz	waitingFor_$eq;
const #47 = NameAndType	#46:#39;//  waitingFor_$eq:(Lscala/Function1;)V
const #48 = InterfaceMethod	#16.#47;	//  scala/actors/Reactor.waitingFor_$eq:(Lscala/Function1;)V
const #49 = Asciz	scala/actors/Reactor$$anonfun$6;
const #50 = class	#49;	//  scala/actors/Reactor$$anonfun$6
const #51 = Method	#50.#36;	//  scala/actors/Reactor$$anonfun$6."<init>":(Lscala/actors/Reactor;)V
const #52 = Asciz	kill_$eq;
const #53 = Asciz	(Lscala/Function0;)V;
const #54 = NameAndType	#52:#53;//  kill_$eq:(Lscala/Function0;)V
const #55 = InterfaceMethod	#16.#54;	//  scala/actors/Reactor.kill_$eq:(Lscala/Function0;)V
const #56 = Asciz	$this;
const #57 = Asciz	Lscala/actors/Reactor;;
const #58 = Asciz	LocalVariableTable;
const #59 = Asciz	terminated;
const #60 = Asciz	scheduler;
const #61 = Asciz	()Lscala/actors/IScheduler;;
const #62 = NameAndType	#60:#61;//  scheduler:()Lscala/actors/IScheduler;
const #63 = InterfaceMethod	#16.#62;	//  scala/actors/Reactor.scheduler:()Lscala/actors/IScheduler;
const #64 = Asciz	scala/actors/IScheduler;
const #65 = class	#64;	//  scala/actors/IScheduler
const #66 = NameAndType	#59:#4;//  terminated:(Lscala/actors/Reactor;)V
const #67 = InterfaceMethod	#65.#66;	//  scala/actors/IScheduler.terminated:(Lscala/actors/Reactor;)V
const #68 = Asciz	exit;
const #69 = Asciz	(Lscala/actors/Reactor;)Lscala/runtime/Nothing$;;
const #70 = NameAndType	#59:#23;//  terminated:()V
const #71 = InterfaceMethod	#16.#70;	//  scala/actors/Reactor.terminated:()V
const #72 = Asciz	scala/actors/Actor$;
const #73 = class	#72;	//  scala/actors/Actor$
const #74 = Asciz	MODULE$;
const #75 = Asciz	Lscala/actors/Actor$;;
const #76 = NameAndType	#74:#75;//  MODULE$:Lscala/actors/Actor$;
const #77 = Field	#73.#76;	//  scala/actors/Actor$.MODULE$:Lscala/actors/Actor$;
const #78 = Asciz	suspendException;
const #79 = Asciz	()Lscala/actors/SuspendActorException;;
const #80 = NameAndType	#78:#79;//  suspendException:()Lscala/actors/SuspendActorException;
const #81 = Method	#73.#80;	//  scala/actors/Actor$.suspendException:()Lscala/actors/SuspendActorException;
const #82 = Asciz	seq;
const #83 = Asciz	(Lscala/actors/Reactor;Lscala/Function0;Lscala/Function0;)V;
const #84 = Asciz	rawSelf;
const #85 = Asciz	(Lscala/actors/IScheduler;)Lscala/actors/Reactor;;
const #86 = NameAndType	#84:#85;//  rawSelf:(Lscala/actors/IScheduler;)Lscala/actors/Reactor;
const #87 = Method	#73.#86;	//  scala/actors/Actor$.rawSelf:(Lscala/actors/IScheduler;)Lscala/actors/Reactor;
const #88 = Asciz	kill;
const #89 = Asciz	()Lscala/Function0;;
const #90 = NameAndType	#88:#89;//  kill:()Lscala/Function0;
const #91 = InterfaceMethod	#16.#90;	//  scala/actors/Reactor.kill:()Lscala/Function0;
const #92 = Asciz	scala/actors/Reactor$$anonfun$seq$1;
const #93 = class	#92;	//  scala/actors/Reactor$$anonfun$seq$1
const #94 = Asciz	(Lscala/actors/Reactor;Lscala/Function0;Lscala/actors/Reactor;Lscala/Function0;)V;
const #95 = NameAndType	#11:#94;//  "<init>":(Lscala/actors/Reactor;Lscala/Function0;Lscala/actors/Reactor;Lscala/Function0;)V
const #96 = Method	#93.#95;	//  scala/actors/Reactor$$anonfun$seq$1."<init>":(Lscala/actors/Reactor;Lscala/Function0;Lscala/actors/Reactor;Lscala/Function0;)V
const #97 = Asciz	scala/Function0;
const #98 = class	#97;	//  scala/Function0
const #99 = Asciz	apply;
const #100 = Asciz	()Ljava/lang/Object;;
const #101 = NameAndType	#99:#100;//  apply:()Ljava/lang/Object;
const #102 = InterfaceMethod	#98.#101;	//  scala/Function0.apply:()Ljava/lang/Object;
const #103 = Asciz	scala/actors/KillActorException;
const #104 = class	#103;	//  scala/actors/KillActorException
const #105 = Method	#104.#24;	//  scala/actors/KillActorException."<init>":()V
const #106 = Asciz	first;
const #107 = Asciz	Lscala/Function0;;
const #108 = Asciz	next$1;
const #109 = Asciz	s$1;
const #110 = Asciz	killNext$1;
const #111 = Asciz	start;
const #112 = Asciz	(Lscala/actors/Reactor;)Lscala/actors/Reactor;;
const #113 = Asciz	newActor;
const #114 = NameAndType	#113:#4;//  newActor:(Lscala/actors/Reactor;)V
const #115 = InterfaceMethod	#65.#114;	//  scala/actors/IScheduler.newActor:(Lscala/actors/Reactor;)V
const #116 = Asciz	scala/actors/ReactorTask;
const #117 = class	#116;	//  scala/actors/ReactorTask
const #118 = Asciz	scala/actors/Reactor$$anonfun$5;
const #119 = class	#118;	//  scala/actors/Reactor$$anonfun$5
const #120 = Method	#119.#36;	//  scala/actors/Reactor$$anonfun$5."<init>":(Lscala/actors/Reactor;)V
const #121 = Asciz	(Lscala/actors/Reactor;Lscala/Function0;)V;
const #122 = NameAndType	#11:#121;//  "<init>":(Lscala/actors/Reactor;Lscala/Function0;)V
const #123 = Method	#117.#122;	//  scala/actors/ReactorTask."<init>":(Lscala/actors/Reactor;Lscala/Function0;)V
const #124 = Asciz	execute;
const #125 = Asciz	(Ljava/lang/Runnable;)V;
const #126 = NameAndType	#124:#125;//  execute:(Ljava/lang/Runnable;)V
const #127 = InterfaceMethod	#65.#126;	//  scala/actors/IScheduler.execute:(Ljava/lang/Runnable;)V
const #128 = Asciz	task;
const #129 = Asciz	Lscala/actors/ReactorTask;;
const #130 = Asciz	scheduleActor;
const #131 = Asciz	(Lscala/actors/Reactor;Lscala/PartialFunction;Ljava/lang/Object;)V;
const #132 = Asciz	scala/actors/Reactor$$anonfun$4;
const #133 = class	#132;	//  scala/actors/Reactor$$anonfun$4
const #134 = NameAndType	#11:#131;//  "<init>":(Lscala/actors/Reactor;Lscala/PartialFunction;Ljava/lang/Object;)V
const #135 = Method	#133.#134;	//  scala/actors/Reactor$$anonfun$4."<init>":(Lscala/actors/Reactor;Lscala/PartialFunction;Ljava/lang/Object;)V
const #136 = Asciz	executeFromActor;
const #137 = NameAndType	#136:#125;//  executeFromActor:(Ljava/lang/Runnable;)V
const #138 = InterfaceMethod	#65.#137;	//  scala/actors/IScheduler.executeFromActor:(Ljava/lang/Runnable;)V
const #139 = Asciz	handler$2;
const #140 = Asciz	Lscala/PartialFunction;;
const #141 = Asciz	msg$2;
const #142 = Asciz	Ljava/lang/Object;;
const #143 = Asciz	fun;
const #144 = Asciz	react;
const #145 = Asciz	(Lscala/actors/Reactor;Lscala/PartialFunction;)Lscala/runtime/Nothing$;;
const #146 = Asciz	java/lang/Object;
const #147 = class	#146;	//  java/lang/Object
const #148 = Asciz	equals;
const #149 = Asciz	(Ljava/lang/Object;)Z;
const #150 = NameAndType	#148:#149;//  equals:(Ljava/lang/Object;)Z
const #151 = Method	#147.#150;	//  java/lang/Object.equals:(Ljava/lang/Object;)Z
const #152 = Asciz	scala/actors/Reactor$$anonfun$react$1;
const #153 = class	#152;	//  scala/actors/Reactor$$anonfun$react$1
const #154 = Method	#153.#36;	//  scala/actors/Reactor$$anonfun$react$1."<init>":(Lscala/actors/Reactor;)V
const #155 = Asciz	java/lang/AssertionError;
const #156 = class	#155;	//  java/lang/AssertionError
const #157 = Asciz	scala/collection/mutable/StringBuilder;
const #158 = class	#157;	//  scala/collection/mutable/StringBuilder
const #159 = Method	#158.#24;	//  scala/collection/mutable/StringBuilder."<init>":()V
const #160 = Asciz	assertion failed: ;
const #161 = String	#160;	//  assertion failed: 
const #162 = Asciz	append;
const #163 = Asciz	(Ljava/lang/Object;)Lscala/collection/mutable/StringBuilder;;
const #164 = NameAndType	#162:#163;//  append:(Ljava/lang/Object;)Lscala/collection/mutable/StringBuilder;
const #165 = Method	#158.#164;	//  scala/collection/mutable/StringBuilder.append:(Ljava/lang/Object;)Lscala/collection/mutable/StringBuilder;
const #166 = Asciz	react on channel belonging to other actor;
const #167 = String	#166;	//  react on channel belonging to other actor
const #168 = Asciz	toString;
const #169 = Asciz	()Ljava/lang/String;;
const #170 = NameAndType	#168:#169;//  toString:()Ljava/lang/String;
const #171 = Method	#158.#170;	//  scala/collection/mutable/StringBuilder.toString:()Ljava/lang/String;
const #172 = Asciz	(Ljava/lang/Object;)V;
const #173 = NameAndType	#11:#172;//  "<init>":(Ljava/lang/Object;)V
const #174 = Method	#156.#173;	//  java/lang/AssertionError."<init>":(Ljava/lang/Object;)V
const #175 = Asciz	mailbox;
const #176 = Asciz	()Lscala/actors/MessageQueue;;
const #177 = NameAndType	#175:#176;//  mailbox:()Lscala/actors/MessageQueue;
const #178 = InterfaceMethod	#16.#177;	//  scala/actors/Reactor.mailbox:()Lscala/actors/MessageQueue;
const #179 = Asciz	drainSendBuffer;
const #180 = NameAndType	#179:#18;//  drainSendBuffer:(Lscala/actors/MessageQueue;)V
const #181 = InterfaceMethod	#16.#180;	//  scala/actors/Reactor.drainSendBuffer:(Lscala/actors/MessageQueue;)V
const #182 = Asciz	scala/actors/Reactor$$anonfun$react$2;
const #183 = class	#182;	//  scala/actors/Reactor$$anonfun$react$2
const #184 = Asciz	(Lscala/actors/Reactor;Lscala/PartialFunction;)V;
const #185 = NameAndType	#11:#184;//  "<init>":(Lscala/actors/Reactor;Lscala/PartialFunction;)V
const #186 = Method	#183.#185;	//  scala/actors/Reactor$$anonfun$react$2."<init>":(Lscala/actors/Reactor;Lscala/PartialFunction;)V
const #187 = Asciz	searchMailbox;
const #188 = Asciz	(Lscala/actors/MessageQueue;Lscala/Function1;Z)V;
const #189 = NameAndType	#187:#188;//  searchMailbox:(Lscala/actors/MessageQueue;Lscala/Function1;Z)V
const #190 = InterfaceMethod	#16.#189;	//  scala/actors/Reactor.searchMailbox:(Lscala/actors/MessageQueue;Lscala/Function1;Z)V
const #191 = Asciz	f$1;
const #192 = Asciz	(Lscala/actors/Reactor;Lscala/actors/MessageQueue;Lscala/Function1;Z)V;
const #193 = Asciz	scala/actors/Reactor$$anonfun$3;
const #194 = class	#193;	//  scala/actors/Reactor$$anonfun$3
const #195 = Asciz	(Lscala/actors/Reactor;Lscala/Function1;)V;
const #196 = NameAndType	#11:#195;//  "<init>":(Lscala/actors/Reactor;Lscala/Function1;)V
const #197 = Method	#194.#196;	//  scala/actors/Reactor$$anonfun$3."<init>":(Lscala/actors/Reactor;Lscala/Function1;)V
const #198 = Asciz	extractFirst;
const #199 = Asciz	(Lscala/Function2;)Lscala/actors/MessageQueueElement;;
const #200 = NameAndType	#198:#199;//  extractFirst:(Lscala/Function2;)Lscala/actors/MessageQueueElement;
const #201 = Method	#8.#200;	//  scala/actors/MessageQueue.extractFirst:(Lscala/Function2;)Lscala/actors/MessageQueueElement;
const #202 = Asciz	scala/actors/Reactor$$anonfun$searchMailbox$1;
const #203 = class	#202;	//  scala/actors/Reactor$$anonfun$searchMailbox$1
const #204 = Method	#203.#36;	//  scala/actors/Reactor$$anonfun$searchMailbox$1."<init>":(Lscala/actors/Reactor;)V
const #205 = Asciz	foreach;
const #206 = Asciz	(Lscala/Function2;)V;
const #207 = NameAndType	#205:#206;//  foreach:(Lscala/Function2;)V
const #208 = Method	#8.#207;	//  scala/actors/MessageQueue.foreach:(Lscala/Function2;)V
const #209 = Asciz	sendBuffer;
const #210 = Asciz	()Lscala/collection/mutable/Queue;;
const #211 = NameAndType	#209:#210;//  sendBuffer:()Lscala/collection/mutable/Queue;
const #212 = InterfaceMethod	#16.#211;	//  scala/actors/Reactor.sendBuffer:()Lscala/collection/mutable/Queue;
const #213 = Asciz	isEmpty;
const #214 = Asciz	()Z;
const #215 = NameAndType	#213:#214;//  isEmpty:()Z
const #216 = Method	#22.#215;	//  scala/collection/mutable/Queue.isEmpty:()Z
const #217 = Asciz	Temp;
const #218 = String	#217;	//  Temp
const #219 = Asciz	scala/Tuple2;
const #220 = class	#219;	//  scala/Tuple2
const #221 = Asciz	scala/actors/MessageQueueElement;
const #222 = class	#221;	//  scala/actors/MessageQueueElement
const #223 = Asciz	msg;
const #224 = NameAndType	#223:#100;//  msg:()Ljava/lang/Object;
const #225 = Method	#222.#224;	//  scala/actors/MessageQueueElement.msg:()Ljava/lang/Object;
const #226 = Asciz	session;
const #227 = Asciz	()Lscala/actors/OutputChannel;;
const #228 = NameAndType	#226:#227;//  session:()Lscala/actors/OutputChannel;
const #229 = Method	#222.#228;	//  scala/actors/MessageQueueElement.session:()Lscala/actors/OutputChannel;
const #230 = Asciz	(Ljava/lang/Object;Ljava/lang/Object;)V;
const #231 = NameAndType	#11:#230;//  "<init>":(Ljava/lang/Object;Ljava/lang/Object;)V
const #232 = Method	#220.#231;	//  scala/Tuple2."<init>":(Ljava/lang/Object;Ljava/lang/Object;)V
const #233 = Asciz	resumeReceiver;
const #234 = Asciz	(Lscala/Tuple2;Z)V;
const #235 = NameAndType	#233:#234;//  resumeReceiver:(Lscala/Tuple2;Z)V
const #236 = InterfaceMethod	#16.#235;	//  scala/actors/Reactor.resumeReceiver:(Lscala/Tuple2;Z)V
const #237 = Asciz	startMbox;
const #238 = Asciz	Lscala/actors/MessageQueue;;
const #239 = Asciz	handlesMessage$1;
const #240 = Asciz	Lscala/Function1;;
const #241 = Asciz	resumeOnSameThread;
const #242 = Asciz	Z;
const #243 = Asciz	tmpMbox;
const #244 = Asciz	qel;
const #245 = Asciz	Lscala/actors/MessageQueueElement;;
const #246 = Asciz	done;
const #247 = Asciz	(Lscala/actors/Reactor;Lscala/actors/MessageQueue;)V;
const #248 = Asciz	dequeue;
const #249 = NameAndType	#248:#100;//  dequeue:()Ljava/lang/Object;
const #250 = Method	#22.#249;	//  scala/collection/mutable/Queue.dequeue:()Ljava/lang/Object;
const #251 = Asciz	_1;
const #252 = NameAndType	#251:#100;//  _1:()Ljava/lang/Object;
const #253 = Method	#220.#252;	//  scala/Tuple2._1:()Ljava/lang/Object;
const #254 = Asciz	_2;
const #255 = NameAndType	#254:#100;//  _2:()Ljava/lang/Object;
const #256 = Method	#220.#255;	//  scala/Tuple2._2:()Ljava/lang/Object;
const #257 = Asciz	scala/actors/OutputChannel;
const #258 = class	#257;	//  scala/actors/OutputChannel
const #259 = Asciz	(Ljava/lang/Object;Lscala/actors/OutputChannel;)V;
const #260 = NameAndType	#162:#259;//  append:(Ljava/lang/Object;Lscala/actors/OutputChannel;)V
const #261 = Method	#8.#260;	//  scala/actors/MessageQueue.append:(Ljava/lang/Object;Lscala/actors/OutputChannel;)V
const #262 = Asciz	mbox;
const #263 = Asciz	item;
const #264 = Asciz	Lscala/Tuple2;;
const #265 = Asciz	receiver;
const #266 = Asciz	(Lscala/actors/Reactor;)Lscala/actors/Actor;;
const #267 = Asciz	scala/actors/Actor;
const #268 = class	#267;	//  scala/actors/Actor
const #269 = Asciz	forward;
const #270 = Asciz	(Lscala/actors/Reactor;Ljava/lang/Object;)V;
const #271 = Asciz	send;
const #272 = NameAndType	#271:#259;//  send:(Ljava/lang/Object;Lscala/actors/OutputChannel;)V
const #273 = InterfaceMethod	#16.#272;	//  scala/actors/Reactor.send:(Ljava/lang/Object;Lscala/actors/OutputChannel;)V
const #274 = Asciz	$bang;
const #275 = Asciz	(Lscala/actors/Reactor;Lscala/Tuple2;Z)V;
const #276 = Asciz	continuation;
const #277 = Asciz	()Lscala/PartialFunction;;
const #278 = NameAndType	#276:#277;//  continuation:()Lscala/PartialFunction;
const #279 = InterfaceMethod	#16.#278;	//  scala/actors/Reactor.continuation:()Lscala/PartialFunction;
const #280 = Asciz	scala/Function1;
const #281 = class	#280;	//  scala/Function1
const #282 = Asciz	(Ljava/lang/Object;)Ljava/lang/Object;;
const #283 = NameAndType	#99:#282;//  apply:(Ljava/lang/Object;)Ljava/lang/Object;
const #284 = InterfaceMethod	#281.#283;	//  scala/Function1.apply:(Ljava/lang/Object;)Ljava/lang/Object;
const #285 = Asciz	(Lscala/PartialFunction;Ljava/lang/Object;)V;
const #286 = NameAndType	#130:#285;//  scheduleActor:(Lscala/PartialFunction;Ljava/lang/Object;)V
const #287 = InterfaceMethod	#16.#286;	//  scala/actors/Reactor.scheduleActor:(Lscala/PartialFunction;Ljava/lang/Object;)V
const #288 = Asciz	onSameThread;
const #289 = Asciz	makeReaction;
const #290 = Asciz	(Lscala/actors/Reactor;Lscala/Function0;)Ljava/lang/Runnable;;
const #291 = Asciz	startSearch;
const #292 = Asciz	(Lscala/actors/Reactor;Ljava/lang/Object;Lscala/actors/OutputChannel;Lscala/Function1;)Lscala/Function0;;
const #293 = Asciz	scala/actors/Reactor$$anonfun$startSearch$1;
const #294 = class	#293;	//  scala/actors/Reactor$$anonfun$startSearch$1
const #295 = Asciz	(Lscala/actors/Reactor;Ljava/lang/Object;Lscala/actors/OutputChannel;Lscala/Function1;)V;
const #296 = NameAndType	#11:#295;//  "<init>":(Lscala/actors/Reactor;Ljava/lang/Object;Lscala/actors/OutputChannel;Lscala/Function1;)V
const #297 = Method	#294.#296;	//  scala/actors/Reactor$$anonfun$startSearch$1."<init>":(Lscala/actors/Reactor;Ljava/lang/Object;Lscala/actors/OutputChannel;Lscala/Function1;)V
const #298 = Asciz	msg$1;
const #299 = Asciz	replyTo$1;
const #300 = Asciz	Lscala/actors/OutputChannel;;
const #301 = Asciz	handler$1;
const #302 = Asciz	(Lscala/actors/Reactor;Ljava/lang/Object;Lscala/actors/OutputChannel;)V;
const #303 = Asciz	waitingFor;
const #304 = NameAndType	#303:#43;//  waitingFor:()Lscala/Function1;
const #305 = InterfaceMethod	#16.#304;	//  scala/actors/Reactor.waitingFor:()Lscala/Function1;
const #306 = Asciz	(Ljava/lang/Object;Lscala/actors/OutputChannel;Lscala/Function1;)Lscala/Function0;;
const #307 = NameAndType	#291:#306;//  startSearch:(Ljava/lang/Object;Lscala/actors/OutputChannel;Lscala/Function1;)Lscala/Function0;
const #308 = InterfaceMethod	#16.#307;	//  scala/actors/Reactor.startSearch:(Ljava/lang/Object;Lscala/actors/OutputChannel;Lscala/Function1;)Lscala/Function0;
const #309 = Asciz	scala/Predef$;
const #310 = class	#309;	//  scala/Predef$
const #311 = Asciz	Lscala/Predef$;;
const #312 = NameAndType	#74:#311;//  MODULE$:Lscala/Predef$;
const #313 = Field	#310.#312;	//  scala/Predef$.MODULE$:Lscala/Predef$;
const #314 = Asciz	[Ljava/lang/Object;;
const #315 = class	#314;	//  "[Ljava/lang/Object;"
const #316 = Asciz	wrapRefArray;
const #317 = Asciz	([Ljava/lang/Object;)Lscala/collection/mutable/WrappedArray;;
const #318 = NameAndType	#316:#317;//  wrapRefArray:([Ljava/lang/Object;)Lscala/collection/mutable/WrappedArray;
const #319 = Method	#310.#318;	//  scala/Predef$.wrapRefArray:([Ljava/lang/Object;)Lscala/collection/mutable/WrappedArray;
const #320 = Asciz	enqueue;
const #321 = Asciz	(Lscala/collection/Seq;)V;
const #322 = NameAndType	#320:#321;//  enqueue:(Lscala/collection/Seq;)V
const #323 = Method	#22.#322;	//  scala/collection/mutable/Queue.enqueue:(Lscala/collection/Seq;)V
const #324 = Asciz	scala/actors/Reactor$$anonfun$2;
const #325 = class	#324;	//  scala/actors/Reactor$$anonfun$2
const #326 = Method	#325.#36;	//  scala/actors/Reactor$$anonfun$2."<init>":(Lscala/actors/Reactor;)V
const #327 = Asciz	replyTo;
const #328 = Asciz	savedWaitingFor;
const #329 = Asciz	todo;
const #330 = Asciz	mailboxSize;
const #331 = Asciz	(Lscala/actors/Reactor;)I;
const #332 = Asciz	size;
const #333 = Asciz	()I;
const #334 = NameAndType	#332:#333;//  size:()I
const #335 = Method	#8.#334;	//  scala/actors/MessageQueue.size:()I
const #336 = Asciz	(Lscala/actors/Reactor;)Lscala/actors/IScheduler;;
const #337 = Asciz	scala/actors/Reactor$;
const #338 = class	#337;	//  scala/actors/Reactor$
const #339 = Asciz	Lscala/actors/Reactor$;;
const #340 = NameAndType	#74:#339;//  MODULE$:Lscala/actors/Reactor$;
const #341 = Field	#338.#340;	//  scala/actors/Reactor$.MODULE$:Lscala/actors/Reactor$;
const #342 = NameAndType	#60:#100;//  scheduler:()Ljava/lang/Object;
const #343 = Method	#338.#342;	//  scala/actors/Reactor$.scheduler:()Ljava/lang/Object;
const #344 = Asciz	exceptionHandler;
const #345 = Asciz	(Lscala/actors/Reactor;)Lscala/PartialFunction;;
const #346 = Asciz	Map;
const #347 = Asciz	()Lscala/collection/immutable/Map$;;
const #348 = NameAndType	#346:#347;//  Map:()Lscala/collection/immutable/Map$;
const #349 = Method	#310.#348;	//  scala/Predef$.Map:()Lscala/collection/immutable/Map$;
const #350 = Asciz	scala/collection/immutable/Map$;
const #351 = class	#350;	//  scala/collection/immutable/Map$
const #352 = Asciz	(Lscala/collection/Seq;)Lscala/collection/Map;;
const #353 = NameAndType	#99:#352;//  apply:(Lscala/collection/Seq;)Lscala/collection/Map;
const #354 = Method	#351.#353;	//  scala/collection/immutable/Map$.apply:(Lscala/collection/Seq;)Lscala/collection/Map;
const #355 = Asciz	Scala;
const #356 = Asciz	InnerClasses;
const #357 = Asciz	$anonfun$2;
const #358 = Asciz	$anonfun$3;
const #359 = Asciz	$anonfun$4;
const #360 = Asciz	$anonfun$5;
const #361 = Asciz	$anonfun$6;
const #362 = Asciz	$anonfun$1;
const #363 = Asciz	$anonfun$seq$1;
const #364 = Asciz	$anonfun$react$2;
const #365 = Asciz	$anonfun$react$1;
const #366 = Asciz	$anonfun$startSearch$1;
const #367 = Asciz	$anonfun$searchMailbox$1;
const #368 = Asciz	scala/actors/Reactor$class;
const #369 = class	#368;	//  scala/actors/Reactor$class

{
public static void $init$(scala.actors.Reactor);
  Code:
   Stack=4, Locals=1, Args_size=1
   0:	aload_0
   1:	new	#8; //class scala/actors/MessageQueue
   4:	dup
   5:	ldc	#10; //String Reactor
   7:	invokespecial	#14; //Method scala/actors/MessageQueue."<init>":(Ljava/lang/String;)V
   10:	invokeinterface	#20,  2; //InterfaceMethod scala/actors/Reactor.scala$actors$Reactor$_setter_$mailbox_$eq:(Lscala/actors/MessageQueue;)V
   15:	aload_0
   16:	new	#22; //class scala/collection/mutable/Queue
   19:	dup
   20:	invokespecial	#25; //Method scala/collection/mutable/Queue."<init>":()V
   23:	invokeinterface	#29,  2; //InterfaceMethod scala/actors/Reactor.scala$actors$Reactor$_setter_$sendBuffer_$eq:(Lscala/collection/mutable/Queue;)V
   28:	aload_0
   29:	aconst_null
   30:	invokeinterface	#33,  2; //InterfaceMethod scala/actors/Reactor.continuation_$eq:(Lscala/PartialFunction;)V
   35:	aload_0
   36:	new	#35; //class scala/actors/Reactor$$anonfun$1
   39:	dup
   40:	aload_0
   41:	invokespecial	#37; //Method scala/actors/Reactor$$anonfun$1."<init>":(Lscala/actors/Reactor;)V
   44:	invokeinterface	#41,  2; //InterfaceMethod scala/actors/Reactor.scala$actors$Reactor$_setter_$waitingForNone_$eq:(Lscala/Function1;)V
   49:	aload_0
   50:	aload_0
   51:	invokeinterface	#45,  1; //InterfaceMethod scala/actors/Reactor.waitingForNone:()Lscala/Function1;
   56:	invokeinterface	#48,  2; //InterfaceMethod scala/actors/Reactor.waitingFor_$eq:(Lscala/Function1;)V
   61:	aload_0
   62:	new	#50; //class scala/actors/Reactor$$anonfun$6
   65:	dup
   66:	aload_0
   67:	invokespecial	#51; //Method scala/actors/Reactor$$anonfun$6."<init>":(Lscala/actors/Reactor;)V
   70:	invokeinterface	#55,  2; //InterfaceMethod scala/actors/Reactor.kill_$eq:(Lscala/Function0;)V
   75:	return
  LineNumberTable: 
   line 35: 0
   line 38: 15
   line 44: 28
   line 53: 35
   line 56: 49
   line 193: 61
   line 194: 62
   line 193: 70

  LocalVariableTable: 
   Start  Length  Slot  Name   Signature
   0      76      0    $this       Lscala/actors/Reactor;


public static void terminated(scala.actors.Reactor);
  Code:
   Stack=2, Locals=1, Args_size=1
   0:	aload_0
   1:	invokeinterface	#63,  1; //InterfaceMethod scala/actors/Reactor.scheduler:()Lscala/actors/IScheduler;
   6:	aload_0
   7:	invokeinterface	#67,  2; //InterfaceMethod scala/actors/IScheduler.terminated:(Lscala/actors/Reactor;)V
   12:	return
  LineNumberTable: 
   line 218: 0

  LocalVariableTable: 
   Start  Length  Slot  Name   Signature
   0      13      0    $this       Lscala/actors/Reactor;


public static scala.runtime.Nothing$ exit(scala.actors.Reactor);
  Code:
   Stack=1, Locals=1, Args_size=1
   0:	aload_0
   1:	invokeinterface	#71,  1; //InterfaceMethod scala/actors/Reactor.terminated:()V
   6:	getstatic	#77; //Field scala/actors/Actor$.MODULE$:Lscala/actors/Actor$;
   9:	invokevirtual	#81; //Method scala/actors/Actor$.suspendException:()Lscala/actors/SuspendActorException;
   12:	athrow
  LineNumberTable: 
   line 213: 0
   line 214: 6

  LocalVariableTable: 
   Start  Length  Slot  Name   Signature
   0      13      0    $this       Lscala/actors/Reactor;


public static void seq(scala.actors.Reactor, scala.Function0, scala.Function0);
  Code:
   Stack=7, Locals=5, Args_size=3
   0:	getstatic	#77; //Field scala/actors/Actor$.MODULE$:Lscala/actors/Actor$;
   3:	aload_0
   4:	invokeinterface	#63,  1; //InterfaceMethod scala/actors/Reactor.scheduler:()Lscala/actors/IScheduler;
   9:	invokevirtual	#87; //Method scala/actors/Actor$.rawSelf:(Lscala/actors/IScheduler;)Lscala/actors/Reactor;
   12:	astore_3
   13:	aload_3
   14:	invokeinterface	#91,  1; //InterfaceMethod scala/actors/Reactor.kill:()Lscala/Function0;
   19:	astore	4
   21:	aload_3
   22:	new	#93; //class scala/actors/Reactor$$anonfun$seq$1
   25:	dup
   26:	aload_0
   27:	aload_2
   28:	aload_3
   29:	aload	4
   31:	invokespecial	#96; //Method scala/actors/Reactor$$anonfun$seq$1."<init>":(Lscala/actors/Reactor;Lscala/Function0;Lscala/actors/Reactor;Lscala/Function0;)V
   34:	invokeinterface	#55,  2; //InterfaceMethod scala/actors/Reactor.kill_$eq:(Lscala/Function0;)V
   39:	aload_1
   40:	invokeinterface	#102,  1; //InterfaceMethod scala/Function0.apply:()Ljava/lang/Object;
   45:	pop
   46:	new	#104; //class scala/actors/KillActorException
   49:	dup
   50:	invokespecial	#105; //Method scala/actors/KillActorException."<init>":()V
   53:	athrow
  LineNumberTable: 
   line 197: 0
   line 198: 13
   line 199: 21
   line 208: 39
   line 209: 46

  LocalVariableTable: 
   Start  Length  Slot  Name   Signature
   0      54      0    $this       Lscala/actors/Reactor;
   0      54      1    first       Lscala/Function0;
   0      54      2    next$1       Lscala/Function0;
   13      41      3    s$1       Lscala/actors/Reactor;
   21      33      4    killNext$1       Lscala/Function0;


public static scala.actors.Reactor start(scala.actors.Reactor);
  Code:
   Stack=6, Locals=2, Args_size=1
   0:	aload_0
   1:	invokeinterface	#63,  1; //InterfaceMethod scala/actors/Reactor.scheduler:()Lscala/actors/IScheduler;
   6:	aload_0
   7:	invokeinterface	#115,  2; //InterfaceMethod scala/actors/IScheduler.newActor:(Lscala/actors/Reactor;)V
   12:	new	#117; //class scala/actors/ReactorTask
   15:	dup
   16:	aload_0
   17:	new	#119; //class scala/actors/Reactor$$anonfun$5
   20:	dup
   21:	aload_0
   22:	invokespecial	#120; //Method scala/actors/Reactor$$anonfun$5."<init>":(Lscala/actors/Reactor;)V
   25:	invokespecial	#123; //Method scala/actors/ReactorTask."<init>":(Lscala/actors/Reactor;Lscala/Function0;)V
   28:	astore_1
   29:	aload_0
   30:	invokeinterface	#63,  1; //InterfaceMethod scala/actors/Reactor.scheduler:()Lscala/actors/IScheduler;
   35:	aload_1
   36:	invokeinterface	#127,  2; //InterfaceMethod scala/actors/IScheduler.execute:(Ljava/lang/Runnable;)V
   41:	aload_0
   42:	areturn
  LineNumberTable: 
   line 182: 0
   line 183: 12
   line 184: 29
   line 185: 41

  LocalVariableTable: 
   Start  Length  Slot  Name   Signature
   0      43      0    $this       Lscala/actors/Reactor;
   29      13      1    task       Lscala/actors/ReactorTask;


public static void scheduleActor(scala.actors.Reactor, scala.PartialFunction, java.lang.Object);
  Code:
   Stack=5, Locals=5, Args_size=3
   0:	new	#133; //class scala/actors/Reactor$$anonfun$4
   3:	dup
   4:	aload_0
   5:	aload_1
   6:	aload_2
   7:	invokespecial	#135; //Method scala/actors/Reactor$$anonfun$4."<init>":(Lscala/actors/Reactor;Lscala/PartialFunction;Ljava/lang/Object;)V
   10:	astore_3
   11:	new	#117; //class scala/actors/ReactorTask
   14:	dup
   15:	aload_0
   16:	aload_3
   17:	invokespecial	#123; //Method scala/actors/ReactorTask."<init>":(Lscala/actors/Reactor;Lscala/Function0;)V
   20:	astore	4
   22:	aload_0
   23:	invokeinterface	#63,  1; //InterfaceMethod scala/actors/Reactor.scheduler:()Lscala/actors/IScheduler;
   28:	aload	4
   30:	invokeinterface	#138,  2; //InterfaceMethod scala/actors/IScheduler.executeFromActor:(Ljava/lang/Runnable;)V
   35:	return
  LineNumberTable: 
   line 176: 0
   line 177: 11
   line 178: 22

  LocalVariableTable: 
   Start  Length  Slot  Name   Signature
   0      36      0    $this       Lscala/actors/Reactor;
   0      36      1    handler$2       Lscala/PartialFunction;
   0      36      2    msg$2       Ljava/lang/Object;
   11      24      3    fun       Lscala/Function0;
   22      13      4    task       Lscala/actors/ReactorTask;


public static scala.runtime.Nothing$ react(scala.actors.Reactor, scala.PartialFunction);
  Code:
   Stack=6, Locals=3, Args_size=2
   0:	getstatic	#77; //Field scala/actors/Actor$.MODULE$:Lscala/actors/Actor$;
   3:	aload_0
   4:	invokeinterface	#63,  1; //InterfaceMethod scala/actors/Reactor.scheduler:()Lscala/actors/IScheduler;
   9:	invokevirtual	#87; //Method scala/actors/Actor$.rawSelf:(Lscala/actors/IScheduler;)Lscala/actors/Reactor;
   12:	dup
   13:	ifnonnull	24
   16:	pop
   17:	aload_0
   18:	ifnull	31
   21:	goto	35
   24:	aload_0
   25:	invokevirtual	#151; //Method java/lang/Object.equals:(Ljava/lang/Object;)Z
   28:	ifeq	35
   31:	iconst_1
   32:	goto	36
   35:	iconst_0
   36:	new	#153; //class scala/actors/Reactor$$anonfun$react$1
   39:	dup
   40:	pop
   41:	aload_0
   42:	invokespecial	#154; //Method scala/actors/Reactor$$anonfun$react$1."<init>":(Lscala/actors/Reactor;)V
   45:	istore_2
   46:	iload_2
   47:	ifne	78
   50:	new	#156; //class java/lang/AssertionError
   53:	dup
   54:	new	#158; //class scala/collection/mutable/StringBuilder
   57:	dup
   58:	invokespecial	#159; //Method scala/collection/mutable/StringBuilder."<init>":()V
   61:	ldc	#161; //String assertion failed: 
   63:	invokevirtual	#165; //Method scala/collection/mutable/StringBuilder.append:(Ljava/lang/Object;)Lscala/collection/mutable/StringBuilder;
   66:	ldc	#167; //String react on channel belonging to other actor
   68:	invokevirtual	#165; //Method scala/collection/mutable/StringBuilder.append:(Ljava/lang/Object;)Lscala/collection/mutable/StringBuilder;
   71:	invokevirtual	#171; //Method scala/collection/mutable/StringBuilder.toString:()Ljava/lang/String;
   74:	invokespecial	#174; //Method java/lang/AssertionError."<init>":(Ljava/lang/Object;)V
   77:	athrow
   78:	aload_0
   79:	dup
   80:	pop
   81:	monitorenter
   82:	aload_0
   83:	aload_0
   84:	invokeinterface	#178,  1; //InterfaceMethod scala/actors/Reactor.mailbox:()Lscala/actors/MessageQueue;
   89:	invokeinterface	#181,  2; //InterfaceMethod scala/actors/Reactor.drainSendBuffer:(Lscala/actors/MessageQueue;)V
   94:	aload_0
   95:	monitorexit
   96:	aload_0
   97:	aload_1
   98:	invokeinterface	#33,  2; //InterfaceMethod scala/actors/Reactor.continuation_$eq:(Lscala/PartialFunction;)V
   103:	aload_0
   104:	aload_0
   105:	invokeinterface	#178,  1; //InterfaceMethod scala/actors/Reactor.mailbox:()Lscala/actors/MessageQueue;
   110:	new	#183; //class scala/actors/Reactor$$anonfun$react$2
   113:	dup
   114:	aload_0
   115:	aload_1
   116:	invokespecial	#186; //Method scala/actors/Reactor$$anonfun$react$2."<init>":(Lscala/actors/Reactor;Lscala/PartialFunction;)V
   119:	iconst_0
   120:	invokeinterface	#190,  4; //InterfaceMethod scala/actors/Reactor.searchMailbox:(Lscala/actors/MessageQueue;Lscala/Function1;Z)V
   125:	getstatic	#77; //Field scala/actors/Actor$.MODULE$:Lscala/actors/Actor$;
   128:	invokevirtual	#81; //Method scala/actors/Actor$.suspendException:()Lscala/actors/SuspendActorException;
   131:	athrow
   132:	aload_0
   133:	monitorexit
   134:	athrow
  Exception table:
   from   to  target type
    82    96   132   any
  LineNumberTable: 
   line 163: 0
   line 164: 78
   line 165: 96
   line 166: 103
   line 167: 125
   line 164: 133

  LocalVariableTable: 
   Start  Length  Slot  Name   Signature
   0      135      0    $this       Lscala/actors/Reactor;
   0      135      1    f$1       Lscala/PartialFunction;


public static void searchMailbox(scala.actors.Reactor, scala.actors.MessageQueue, scala.Function1, boolean);
  Code:
   Stack=5, Locals=7, Args_size=4
   0:	aload_1
   1:	astore	4
   3:	iconst_0
   4:	istore	6
   6:	iload	6
   8:	ifeq	12
   11:	return
   12:	aload	4
   14:	new	#194; //class scala/actors/Reactor$$anonfun$3
   17:	dup
   18:	aload_0
   19:	aload_2
   20:	invokespecial	#197; //Method scala/actors/Reactor$$anonfun$3."<init>":(Lscala/actors/Reactor;Lscala/Function1;)V
   23:	invokevirtual	#201; //Method scala/actors/MessageQueue.extractFirst:(Lscala/Function2;)Lscala/actors/MessageQueueElement;
   26:	astore	5
   28:	aload	4
   30:	aload_0
   31:	invokeinterface	#178,  1; //InterfaceMethod scala/actors/Reactor.mailbox:()Lscala/actors/MessageQueue;
   36:	if_acmpeq	52
   39:	aload	4
   41:	new	#203; //class scala/actors/Reactor$$anonfun$searchMailbox$1
   44:	dup
   45:	aload_0
   46:	invokespecial	#204; //Method scala/actors/Reactor$$anonfun$searchMailbox$1."<init>":(Lscala/actors/Reactor;)V
   49:	invokevirtual	#208; //Method scala/actors/MessageQueue.foreach:(Lscala/Function2;)V
   52:	aload	5
   54:	ifnonnull	110
   57:	aload_0
   58:	dup
   59:	pop
   60:	monitorenter
   61:	aload_0
   62:	invokeinterface	#212,  1; //InterfaceMethod scala/actors/Reactor.sendBuffer:()Lscala/collection/mutable/Queue;
   67:	invokevirtual	#216; //Method scala/collection/mutable/Queue.isEmpty:()Z
   70:	ifeq	86
   73:	aload_0
   74:	aload_2
   75:	invokeinterface	#48,  2; //InterfaceMethod scala/actors/Reactor.waitingFor_$eq:(Lscala/Function1;)V
   80:	iconst_1
   81:	istore	6
   83:	goto	105
   86:	new	#8; //class scala/actors/MessageQueue
   89:	dup
   90:	ldc	#218; //String Temp
   92:	invokespecial	#14; //Method scala/actors/MessageQueue."<init>":(Ljava/lang/String;)V
   95:	astore	4
   97:	aload_0
   98:	aload	4
   100:	invokeinterface	#181,  2; //InterfaceMethod scala/actors/Reactor.drainSendBuffer:(Lscala/actors/MessageQueue;)V
   105:	aload_0
   106:	monitorexit
   107:	goto	137
   110:	aload_0
   111:	new	#220; //class scala/Tuple2
   114:	dup
   115:	aload	5
   117:	invokevirtual	#225; //Method scala/actors/MessageQueueElement.msg:()Ljava/lang/Object;
   120:	aload	5
   122:	invokevirtual	#229; //Method scala/actors/MessageQueueElement.session:()Lscala/actors/OutputChannel;
   125:	invokespecial	#232; //Method scala/Tuple2."<init>":(Ljava/lang/Object;Ljava/lang/Object;)V
   128:	iload_3
   129:	invokeinterface	#236,  3; //InterfaceMethod scala/actors/Reactor.resumeReceiver:(Lscala/Tuple2;Z)V
   134:	iconst_1
   135:	istore	6
   137:	goto	6
   140:	aload_0
   141:	monitorexit
   142:	athrow
  Exception table:
   from   to  target type
    61   110   140   any
  LineNumberTable: 
   line 137: 0
   line 138: 3
   line 139: 6
   line 136: 11
   line 140: 12
   line 141: 28
   line 142: 39
   line 143: 52
   line 144: 57
   line 146: 61
   line 151: 73
   line 152: 80
   line 146: 83
   line 147: 86
   line 148: 97
   line 156: 105
   line 144: 106
   line 156: 110
   line 157: 134
   line 143: 137
   line 144: 141

  LocalVariableTable: 
   Start  Length  Slot  Name   Signature
   0      143      0    $this       Lscala/actors/Reactor;
   0      143      1    startMbox       Lscala/actors/MessageQueue;
   0      143      2    handlesMessage$1       Lscala/Function1;
   0      143      3    resumeOnSameThread       Z
   3      140      4    tmpMbox       Lscala/actors/MessageQueue;
   28      109      5    qel       Lscala/actors/MessageQueueElement;
   140      3      5    qel       Lscala/actors/MessageQueueElement;
   6      137      6    done       Z


public static void drainSendBuffer(scala.actors.Reactor, scala.actors.MessageQueue);
  Code:
   Stack=3, Locals=3, Args_size=2
   0:	aload_0
   1:	invokeinterface	#212,  1; //InterfaceMethod scala/actors/Reactor.sendBuffer:()Lscala/collection/mutable/Queue;
   6:	invokevirtual	#216; //Method scala/collection/mutable/Queue.isEmpty:()Z
   9:	ifeq	13
   12:	return
   13:	aload_0
   14:	invokeinterface	#212,  1; //InterfaceMethod scala/actors/Reactor.sendBuffer:()Lscala/collection/mutable/Queue;
   19:	invokevirtual	#250; //Method scala/collection/mutable/Queue.dequeue:()Ljava/lang/Object;
   22:	checkcast	#220; //class scala/Tuple2
   25:	astore_2
   26:	aload_1
   27:	aload_2
   28:	invokevirtual	#253; //Method scala/Tuple2._1:()Ljava/lang/Object;
   31:	aload_2
   32:	invokevirtual	#256; //Method scala/Tuple2._2:()Ljava/lang/Object;
   35:	checkcast	#258; //class scala/actors/OutputChannel
   38:	invokevirtual	#261; //Method scala/actors/MessageQueue.append:(Ljava/lang/Object;Lscala/actors/OutputChannel;)V
   41:	goto	0
  LineNumberTable: 
   line 127: 0
   line 128: 13
   line 129: 26

  LocalVariableTable: 
   Start  Length  Slot  Name   Signature
   0      44      0    $this       Lscala/actors/Reactor;
   0      44      1    mbox       Lscala/actors/MessageQueue;
   26      15      2    item       Lscala/Tuple2;


public static scala.actors.Actor receiver(scala.actors.Reactor);
  Code:
   Stack=1, Locals=1, Args_size=1
   0:	aload_0
   1:	checkcast	#268; //class scala/actors/Actor
   4:	areturn
  LineNumberTable: 
   line 123: 0

  LocalVariableTable: 
   Start  Length  Slot  Name   Signature
   0      5      0    $this       Lscala/actors/Reactor;


public static void forward(scala.actors.Reactor, java.lang.Object);
  Code:
   Stack=3, Locals=2, Args_size=2
   0:	aload_0
   1:	aload_1
   2:	aconst_null
   3:	invokeinterface	#273,  3; //InterfaceMethod scala/actors/Reactor.send:(Ljava/lang/Object;Lscala/actors/OutputChannel;)V
   8:	return
  LineNumberTable: 
   line 120: 0

  LocalVariableTable: 
   Start  Length  Slot  Name   Signature
   0      9      0    $this       Lscala/actors/Reactor;
   0      9      1    msg       Ljava/lang/Object;


public static void $bang(scala.actors.Reactor, java.lang.Object);
  Code:
   Stack=3, Locals=2, Args_size=2
   0:	aload_0
   1:	aload_1
   2:	aconst_null
   3:	invokeinterface	#273,  3; //InterfaceMethod scala/actors/Reactor.send:(Ljava/lang/Object;Lscala/actors/OutputChannel;)V
   8:	return
  LineNumberTable: 
   line 116: 0

  LocalVariableTable: 
   Start  Length  Slot  Name   Signature
   0      9      0    $this       Lscala/actors/Reactor;
   0      9      1    msg       Ljava/lang/Object;


public static void resumeReceiver(scala.actors.Reactor, scala.Tuple2, boolean);
  Code:
   Stack=3, Locals=3, Args_size=3
   0:	iload_2
   1:	ifeq	23
   4:	aload_0
   5:	invokeinterface	#279,  1; //InterfaceMethod scala/actors/Reactor.continuation:()Lscala/PartialFunction;
   10:	aload_1
   11:	invokevirtual	#253; //Method scala/Tuple2._1:()Ljava/lang/Object;
   14:	invokeinterface	#284,  2; //InterfaceMethod scala/Function1.apply:(Ljava/lang/Object;)Ljava/lang/Object;
   19:	pop
   20:	goto	39
   23:	aload_0
   24:	aload_0
   25:	invokeinterface	#279,  1; //InterfaceMethod scala/actors/Reactor.continuation:()Lscala/PartialFunction;
   30:	aload_1
   31:	invokevirtual	#253; //Method scala/Tuple2._1:()Ljava/lang/Object;
   34:	invokeinterface	#287,  3; //InterfaceMethod scala/actors/Reactor.scheduleActor:(Lscala/PartialFunction;Ljava/lang/Object;)V
   39:	return
  LineNumberTable: 
   line 109: 0
   line 110: 4
   line 112: 23
   line 109: 39

  LocalVariableTable: 
   Start  Length  Slot  Name   Signature
   0      40      0    $this       Lscala/actors/Reactor;
   0      40      1    item       Lscala/Tuple2;
   0      40      2    onSameThread       Z


public static java.lang.Runnable makeReaction(scala.actors.Reactor, scala.Function0);
  Code:
   Stack=4, Locals=2, Args_size=2
   0:	new	#117; //class scala/actors/ReactorTask
   3:	dup
   4:	aload_0
   5:	aload_1
   6:	invokespecial	#123; //Method scala/actors/ReactorTask."<init>":(Lscala/actors/Reactor;Lscala/Function0;)V
   9:	areturn
  LineNumberTable: 
   line 102: 0

  LocalVariableTable: 
   Start  Length  Slot  Name   Signature
   0      10      0    $this       Lscala/actors/Reactor;
   0      10      1    fun       Lscala/Function0;


public static scala.Function0 startSearch(scala.actors.Reactor, java.lang.Object, scala.actors.OutputChannel, scala.Function1);
  Code:
   Stack=6, Locals=4, Args_size=4
   0:	new	#294; //class scala/actors/Reactor$$anonfun$startSearch$1
   3:	dup
   4:	aload_0
   5:	aload_1
   6:	aload_2
   7:	aload_3
   8:	invokespecial	#297; //Method scala/actors/Reactor$$anonfun$startSearch$1."<init>":(Lscala/actors/Reactor;Ljava/lang/Object;Lscala/actors/OutputChannel;Lscala/Function1;)V
   11:	areturn
  LineNumberTable: 
   line 95: 0

  LocalVariableTable: 
   Start  Length  Slot  Name   Signature
   0      12      0    $this       Lscala/actors/Reactor;
   0      12      1    msg$1       Ljava/lang/Object;
   0      12      2    replyTo$1       Lscala/actors/OutputChannel;
   0      12      3    handler$1       Lscala/Function1;


public static void send(scala.actors.Reactor, java.lang.Object, scala.actors.OutputChannel);
  Code:
   Stack=9, Locals=5, Args_size=3
   0:	aload_0
   1:	dup
   2:	pop
   3:	monitorenter
   4:	aload_0
   5:	invokeinterface	#305,  1; //InterfaceMethod scala/actors/Reactor.waitingFor:()Lscala/Function1;
   10:	aload_0
   11:	invokeinterface	#45,  1; //InterfaceMethod scala/actors/Reactor.waitingForNone:()Lscala/Function1;
   16:	if_acmpeq	50
   19:	aload_0
   20:	invokeinterface	#305,  1; //InterfaceMethod scala/actors/Reactor.waitingFor:()Lscala/Function1;
   25:	astore_3
   26:	aload_0
   27:	aload_0
   28:	invokeinterface	#45,  1; //InterfaceMethod scala/actors/Reactor.waitingForNone:()Lscala/Function1;
   33:	invokeinterface	#48,  2; //InterfaceMethod scala/actors/Reactor.waitingFor_$eq:(Lscala/Function1;)V
   38:	aload_0
   39:	aload_1
   40:	aload_2
   41:	aload_3
   42:	invokeinterface	#308,  4; //InterfaceMethod scala/actors/Reactor.startSearch:(Ljava/lang/Object;Lscala/actors/OutputChannel;Lscala/Function1;)Lscala/Function0;
   47:	goto	92
   50:	aload_0
   51:	invokeinterface	#212,  1; //InterfaceMethod scala/actors/Reactor.sendBuffer:()Lscala/collection/mutable/Queue;
   56:	getstatic	#313; //Field scala/Predef$.MODULE$:Lscala/Predef$;
   59:	iconst_1
   60:	anewarray	#220; //class scala/Tuple2
   63:	dup
   64:	iconst_0
   65:	new	#220; //class scala/Tuple2
   68:	dup
   69:	aload_1
   70:	aload_2
   71:	invokespecial	#232; //Method scala/Tuple2."<init>":(Ljava/lang/Object;Ljava/lang/Object;)V
   74:	aastore
   75:	checkcast	#315; //class "[Ljava/lang/Object;"
   78:	invokevirtual	#319; //Method scala/Predef$.wrapRefArray:([Ljava/lang/Object;)Lscala/collection/mutable/WrappedArray;
   81:	invokevirtual	#323; //Method scala/collection/mutable/Queue.enqueue:(Lscala/collection/Seq;)V
   84:	new	#325; //class scala/actors/Reactor$$anonfun$2
   87:	dup
   88:	aload_0
   89:	invokespecial	#326; //Method scala/actors/Reactor$$anonfun$2."<init>":(Lscala/actors/Reactor;)V
   92:	aload_0
   93:	monitorexit
   94:	checkcast	#98; //class scala/Function0
   97:	astore	4
   99:	aload	4
   101:	invokeinterface	#102,  1; //InterfaceMethod scala/Function0.apply:()Ljava/lang/Object;
   106:	pop
   107:	return
   108:	aload_0
   109:	monitorexit
   110:	athrow
  Exception table:
   from   to  target type
     4    94   108   any
  LineNumberTable: 
   line 81: 0
   line 82: 4
   line 83: 19
   line 84: 26
   line 85: 38
   line 87: 50
   line 88: 84
   line 81: 93
   line 91: 99
   line 81: 109

  LocalVariableTable: 
   Start  Length  Slot  Name   Signature
   0      111      0    $this       Lscala/actors/Reactor;
   0      111      1    msg       Ljava/lang/Object;
   0      111      2    replyTo       Lscala/actors/OutputChannel;
   26      21      3    savedWaitingFor       Lscala/Function1;
   99      8      4    todo       Lscala/Function0;


public static int mailboxSize(scala.actors.Reactor);
  Code:
   Stack=1, Locals=1, Args_size=1
   0:	aload_0
   1:	invokeinterface	#178,  1; //InterfaceMethod scala/actors/Reactor.mailbox:()Lscala/actors/MessageQueue;
   6:	invokevirtual	#335; //Method scala/actors/MessageQueue.size:()I
   9:	ireturn
  LineNumberTable: 
   line 71: 0

  LocalVariableTable: 
   Start  Length  Slot  Name   Signature
   0      10      0    $this       Lscala/actors/Reactor;


public static scala.actors.IScheduler scheduler(scala.actors.Reactor);
  Code:
   Stack=1, Locals=1, Args_size=1
   0:	getstatic	#341; //Field scala/actors/Reactor$.MODULE$:Lscala/actors/Reactor$;
   3:	invokevirtual	#343; //Method scala/actors/Reactor$.scheduler:()Ljava/lang/Object;
   6:	checkcast	#65; //class scala/actors/IScheduler
   9:	areturn
  LineNumberTable: 
   line 68: 0

  LocalVariableTable: 
   Start  Length  Slot  Name   Signature
   0      10      0    $this       Lscala/actors/Reactor;


public static scala.PartialFunction exceptionHandler(scala.actors.Reactor);
  Code:
   Stack=3, Locals=1, Args_size=1
   0:	getstatic	#313; //Field scala/Predef$.MODULE$:Lscala/Predef$;
   3:	invokevirtual	#349; //Method scala/Predef$.Map:()Lscala/collection/immutable/Map$;
   6:	getstatic	#313; //Field scala/Predef$.MODULE$:Lscala/Predef$;
   9:	iconst_0
   10:	anewarray	#220; //class scala/Tuple2
   13:	checkcast	#315; //class "[Ljava/lang/Object;"
   16:	invokevirtual	#319; //Method scala/Predef$.wrapRefArray:([Ljava/lang/Object;)Lscala/collection/mutable/WrappedArray;
   19:	invokevirtual	#354; //Method scala/collection/immutable/Map$.apply:(Lscala/collection/Seq;)Lscala/collection/Map;
   22:	areturn
  LineNumberTable: 
   line 65: 0

  LocalVariableTable: 
   Start  Length  Slot  Name   Signature
   0      23      0    $this       Lscala/actors/Reactor;


}

