Compiled from "ReactorTask.scala"
public class scala.actors.ReactorTask extends java.lang.Object implements java.util.concurrent.Callable,java.lang.Runnable,scala.ScalaObject
  SourceFile: "ReactorTask.scala"
  Signature: length = 0x2
   00 FFFFFFA5 
  ScalaSig: length = 0x26B
   05 00 63 06 05 01 02 00 02 06 02 0B 52 65 61 63
   74 6F 72 54 61 73 6B 0A 02 03 04 01 06 61 63 74
   6F 72 73 0A 01 05 01 05 73 63 61 6C 61 15 02 07
   28 13 05 00 08 10 1C 1F 10 02 09 0E 0D 01 0A 0A
   02 0B 0C 01 04 6C 61 6E 67 0A 01 0D 01 04 6A 61
   76 61 09 02 0F 0A 02 06 4F 62 6A 65 63 74 10 03
   11 16 18 0D 01 12 0A 02 13 14 01 0A 63 6F 6E 63
   75 72 72 65 6E 74 0A 02 15 0C 01 04 75 74 69 6C
   09 02 17 12 02 08 43 61 6C 6C 61 62 6C 65 10 02
   19 1A 0D 01 04 09 02 1B 04 02 04 55 6E 69 74 10
   02 09 1D 09 02 1E 0A 02 08 52 75 6E 6E 61 62 6C
   65 10 02 19 20 09 02 21 04 02 0B 53 63 61 6C 61
   4F 62 6A 65 63 74 08 08 23 00 FFFFFF82 FFFFFFC0 FFFFFF80 FFFFFF84 00 25
   01 07 72 65 61 63 74 6F 72 03 00 15 01 26 10 02
   27 28 0C 00 04 08 29 00 FFFFFF84 FFFFFF80 FFFFFF80 FFFFFFC2 00 2A 02 01
   54 11 02 2B 2E 10 02 19 2C 09 02 2D 04 02 07 4E
   6F 74 68 69 6E 67 10 02 2F 30 0D 01 02 09 02 31
   02 02 07 52 65 61 63 74 6F 72 08 08 33 00 FFFFFF82 FFFFFFC0
   FFFFFF80 FFFFFF84 00 34 01 0B 72 65 61 63 74 6F 72 5F 24 65
   71 14 02 18 35 08 07 36 32 FFFFFF81 FFFFFF80 FFFFFFC0 00 26 01 03
   78 24 31 08 08 38 00 FFFFFF82 FFFFFF80 FFFFFFA0 FFFFFFA0 04 26 01 08 72
   65 61 63 74 6F 72 20 08 08 3A 00 FFFFFF82 FFFFFFC0 FFFFFF80 FFFFFF84 00
   3B 01 03 66 75 6E 15 01 3C 10 03 19 3D 18 09 02
   3E 04 02 09 46 75 6E 63 74 69 6F 6E 30 08 08 40
   00 FFFFFF82 FFFFFFC0 FFFFFF80 FFFFFF84 00 41 01 07 66 75 6E 5F 24 65 71
   14 02 18 42 08 07 36 3F FFFFFF81 FFFFFF80 FFFFFFC0 00 3C 08 08 44
   00 FFFFFF82 FFFFFF80 FFFFFFA0 FFFFFFA0 04 3C 01 04 66 75 6E 20 08 05 46
   00 FFFFFF84 00 47 01 06 3C 69 6E 69 74 3E 14 03 48 49
   4A 10 03 2F 00 26 08 05 23 45 FFFFFFC0 00 26 08 05 3A
   45 FFFFFFC0 00 3C 08 05 4C 00 FFFFFF84 00 4D 01 03 72 75 6E
   14 01 18 08 05 4F 00 FFFFFF84 00 4D 01 04 63 61 6C 6C
   08 05 51 00 FFFFFF84 08 4D 01 0F 62 65 66 6F 72 65 45
   78 65 63 75 74 69 6E 67 08 05 53 00 FFFFFF84 08 54 01
   0E 61 66 74 65 72 45 78 65 63 75 74 69 6E 67 14
   02 18 55 08 05 56 52 FFFFFFC0 00 57 01 01 65 10 02 58
   60 0E 02 59 5E 0E 02 5A 5D 0D 01 5B 0A 02 5C 24
   01 06 3C 72 6F 6F 74 3E 09 01 05 09 02 5F 04 01
   07 70 61 63 6B 61 67 65 09 02 61 62 02 09 45 78
   63 65 70 74 69 6F 6E 0A 02 5F 04 
  minor version: 0
  major version: 49
  Constant pool:
const #1 = Asciz	SourceFile;
const #2 = Asciz	ReactorTask.scala;
const #3 = Asciz	fun;
const #4 = Asciz	Lscala/Function0;;
const #5 = Asciz	Lscala/Function0<Ljava/lang/Object;>;;
const #6 = Asciz	Signature;
const #7 = Asciz	reactor;
const #8 = Asciz	Lscala/actors/Reactor;;
const #9 = Asciz	TT;;
const #10 = Asciz	<init>;
const #11 = Asciz	(Lscala/actors/Reactor;Lscala/Function0;)V;
const #12 = Asciz	Code;
const #13 = Asciz	LineNumberTable;
const #14 = Asciz	scala/actors/ReactorTask;
const #15 = class	#14;	//  scala/actors/ReactorTask
const #16 = NameAndType	#7:#8;//  reactor:Lscala/actors/Reactor;
const #17 = Field	#15.#16;	//  scala/actors/ReactorTask.reactor:Lscala/actors/Reactor;
const #18 = NameAndType	#3:#4;//  fun:Lscala/Function0;
const #19 = Field	#15.#18;	//  scala/actors/ReactorTask.fun:Lscala/Function0;
const #20 = Asciz	java/lang/Object;
const #21 = class	#20;	//  java/lang/Object
const #22 = Asciz	()V;
const #23 = NameAndType	#10:#22;//  "<init>":()V
const #24 = Method	#21.#23;	//  java/lang/Object."<init>":()V
const #25 = Asciz	this;
const #26 = Asciz	Lscala/actors/ReactorTask;;
const #27 = Asciz	LocalVariableTable;
const #28 = Asciz	(TT;Lscala/Function0<Ljava/lang/Object;>;)V;
const #29 = Asciz	gd1$1;
const #30 = Asciz	(Ljava/lang/Exception;)Z;
const #31 = Asciz	()Lscala/actors/Reactor;;
const #32 = NameAndType	#7:#31;//  reactor:()Lscala/actors/Reactor;
const #33 = Method	#15.#32;	//  scala/actors/ReactorTask.reactor:()Lscala/actors/Reactor;
const #34 = Asciz	scala/actors/Reactor;
const #35 = class	#34;	//  scala/actors/Reactor
const #36 = Asciz	exceptionHandler;
const #37 = Asciz	()Lscala/PartialFunction;;
const #38 = NameAndType	#36:#37;//  exceptionHandler:()Lscala/PartialFunction;
const #39 = InterfaceMethod	#35.#38;	//  scala/actors/Reactor.exceptionHandler:()Lscala/PartialFunction;
const #40 = Asciz	scala/PartialFunction;
const #41 = class	#40;	//  scala/PartialFunction
const #42 = Asciz	isDefinedAt;
const #43 = Asciz	(Ljava/lang/Object;)Z;
const #44 = NameAndType	#42:#43;//  isDefinedAt:(Ljava/lang/Object;)Z
const #45 = InterfaceMethod	#41.#44;	//  scala/PartialFunction.isDefinedAt:(Ljava/lang/Object;)Z
const #46 = Asciz	call;
const #47 = Asciz	()Ljava/lang/Object;;
const #48 = NameAndType	#46:#22;//  call:()V
const #49 = Method	#15.#48;	//  scala/actors/ReactorTask.call:()V
const #50 = Asciz	scala/runtime/BoxedUnit;
const #51 = class	#50;	//  scala/runtime/BoxedUnit
const #52 = Asciz	UNIT;
const #53 = Asciz	Lscala/runtime/BoxedUnit;;
const #54 = NameAndType	#52:#53;//  UNIT:Lscala/runtime/BoxedUnit;
const #55 = Field	#51.#54;	//  scala/runtime/BoxedUnit.UNIT:Lscala/runtime/BoxedUnit;
const #56 = Asciz	afterExecuting;
const #57 = Asciz	(Ljava/lang/Exception;)V;
const #58 = Asciz	e;
const #59 = Asciz	Ljava/lang/Exception;;
const #60 = Asciz	beforeExecuting;
const #61 = Asciz	run;
const #62 = NameAndType	#61:#22;//  run:()V
const #63 = Method	#15.#62;	//  scala/actors/ReactorTask.run:()V
const #64 = Asciz	scala/actors/Actor$;
const #65 = class	#64;	//  scala/actors/Actor$
const #66 = Asciz	MODULE$;
const #67 = Asciz	Lscala/actors/Actor$;;
const #68 = NameAndType	#66:#67;//  MODULE$:Lscala/actors/Actor$;
const #69 = Field	#65.#68;	//  scala/actors/Actor$.MODULE$:Lscala/actors/Actor$;
const #70 = Asciz	tl;
const #71 = Asciz	()Ljava/lang/ThreadLocal;;
const #72 = NameAndType	#70:#71;//  tl:()Ljava/lang/ThreadLocal;
const #73 = Method	#65.#72;	//  scala/actors/Actor$.tl:()Ljava/lang/ThreadLocal;
const #74 = Asciz	java/lang/ThreadLocal;
const #75 = class	#74;	//  java/lang/ThreadLocal
const #76 = Asciz	get;
const #77 = NameAndType	#76:#47;//  get:()Ljava/lang/Object;
const #78 = Method	#75.#77;	//  java/lang/ThreadLocal.get:()Ljava/lang/Object;
const #79 = Asciz	set;
const #80 = Asciz	(Ljava/lang/Object;)V;
const #81 = NameAndType	#79:#80;//  set:(Ljava/lang/Object;)V
const #82 = Method	#75.#81;	//  java/lang/ThreadLocal.set:(Ljava/lang/Object;)V
const #83 = NameAndType	#60:#22;//  beforeExecuting:()V
const #84 = Method	#15.#83;	//  scala/actors/ReactorTask.beforeExecuting:()V
const #85 = Asciz	()Lscala/Function0;;
const #86 = NameAndType	#3:#85;//  fun:()Lscala/Function0;
const #87 = Method	#15.#86;	//  scala/actors/ReactorTask.fun:()Lscala/Function0;
const #88 = Asciz	scala/Function0;
const #89 = class	#88;	//  scala/Function0
const #90 = Asciz	apply;
const #91 = NameAndType	#90:#47;//  apply:()Ljava/lang/Object;
const #92 = InterfaceMethod	#89.#91;	//  scala/Function0.apply:()Ljava/lang/Object;
const #93 = Asciz	java/lang/Exception;
const #94 = class	#93;	//  java/lang/Exception
const #95 = NameAndType	#29:#30;//  gd1$1:(Ljava/lang/Exception;)Z
const #96 = Method	#15.#95;	//  scala/actors/ReactorTask.gd1$1:(Ljava/lang/Exception;)Z
const #97 = Asciz	scala/Function1;
const #98 = class	#97;	//  scala/Function1
const #99 = Asciz	(Ljava/lang/Object;)Ljava/lang/Object;;
const #100 = NameAndType	#90:#99;//  apply:(Ljava/lang/Object;)Ljava/lang/Object;
const #101 = InterfaceMethod	#98.#100;	//  scala/Function1.apply:(Ljava/lang/Object;)Ljava/lang/Object;
const #102 = Asciz	scala/MatchError;
const #103 = class	#102;	//  scala/MatchError
const #104 = Asciz	java/lang/Throwable;
const #105 = class	#104;	//  java/lang/Throwable
const #106 = Asciz	toString;
const #107 = Asciz	()Ljava/lang/String;;
const #108 = NameAndType	#106:#107;//  toString:()Ljava/lang/String;
const #109 = Method	#105.#108;	//  java/lang/Throwable.toString:()Ljava/lang/String;
const #110 = Asciz	(Ljava/lang/String;)V;
const #111 = NameAndType	#10:#110;//  "<init>":(Ljava/lang/String;)V
const #112 = Method	#103.#111;	//  scala/MatchError."<init>":(Ljava/lang/String;)V
const #113 = Asciz	kill;
const #114 = NameAndType	#113:#85;//  kill:()Lscala/Function0;
const #115 = InterfaceMethod	#35.#114;	//  scala/actors/Reactor.kill:()Lscala/Function0;
const #116 = Asciz	reactor_$eq;
const #117 = Asciz	(Lscala/actors/Reactor;)V;
const #118 = NameAndType	#116:#117;//  reactor_$eq:(Lscala/actors/Reactor;)V
const #119 = Method	#15.#118;	//  scala/actors/ReactorTask.reactor_$eq:(Lscala/actors/Reactor;)V
const #120 = Asciz	fun_$eq;
const #121 = Asciz	(Lscala/Function0;)V;
const #122 = NameAndType	#120:#121;//  fun_$eq:(Lscala/Function0;)V
const #123 = Method	#15.#122;	//  scala/actors/ReactorTask.fun_$eq:(Lscala/Function0;)V
const #124 = Asciz	scala/actors/Debug$;
const #125 = class	#124;	//  scala/actors/Debug$
const #126 = Asciz	Lscala/actors/Debug$;;
const #127 = NameAndType	#66:#126;//  MODULE$:Lscala/actors/Debug$;
const #128 = Field	#125.#127;	//  scala/actors/Debug$.MODULE$:Lscala/actors/Debug$;
const #129 = Asciz	scala/collection/mutable/StringBuilder;
const #130 = class	#129;	//  scala/collection/mutable/StringBuilder
const #131 = Method	#130.#23;	//  scala/collection/mutable/StringBuilder."<init>":()V
const #132 = Asciz	scala/runtime/StringAdd;
const #133 = class	#132;	//  scala/runtime/StringAdd
const #134 = NameAndType	#10:#80;//  "<init>":(Ljava/lang/Object;)V
const #135 = Method	#133.#134;	//  scala/runtime/StringAdd."<init>":(Ljava/lang/Object;)V
const #136 = Asciz	: caught ;
const #137 = String	#136;	//  : caught 
const #138 = Asciz	$plus;
const #139 = Asciz	(Ljava/lang/String;)Ljava/lang/String;;
const #140 = NameAndType	#138:#139;//  $plus:(Ljava/lang/String;)Ljava/lang/String;
const #141 = Method	#133.#140;	//  scala/runtime/StringAdd.$plus:(Ljava/lang/String;)Ljava/lang/String;
const #142 = Asciz	append;
const #143 = Asciz	(Ljava/lang/Object;)Lscala/collection/mutable/StringBuilder;;
const #144 = NameAndType	#142:#143;//  append:(Ljava/lang/Object;)Lscala/collection/mutable/StringBuilder;
const #145 = Method	#130.#144;	//  scala/collection/mutable/StringBuilder.append:(Ljava/lang/Object;)Lscala/collection/mutable/StringBuilder;
const #146 = Method	#130.#108;	//  scala/collection/mutable/StringBuilder.toString:()Ljava/lang/String;
const #147 = Asciz	info;
const #148 = NameAndType	#147:#110;//  info:(Ljava/lang/String;)V
const #149 = Method	#125.#148;	//  scala/actors/Debug$.info:(Ljava/lang/String;)V
const #150 = Asciz	terminated;
const #151 = NameAndType	#150:#22;//  terminated:()V
const #152 = InterfaceMethod	#35.#151;	//  scala/actors/Reactor.terminated:()V
const #153 = NameAndType	#56:#57;//  afterExecuting:(Ljava/lang/Exception;)V
const #154 = Method	#15.#153;	//  scala/actors/ReactorTask.afterExecuting:(Ljava/lang/Exception;)V
const #155 = Asciz	scala/actors/KillActorException;
const #156 = class	#155;	//  scala/actors/KillActorException
const #157 = Asciz	scala/actors/SuspendActorException;
const #158 = class	#157;	//  scala/actors/SuspendActorException
const #159 = Asciz	temp2;
const #160 = Asciz	saved;
const #161 = Asciz	(Lscala/Function0<Ljava/lang/Object;>;)V;
const #162 = Asciz	()Lscala/Function0<Ljava/lang/Object;>;;
const #163 = Asciz	(TT;)V;
const #164 = Asciz	()TT;;
const #165 = Asciz	<T::Lscala/actors/Reactor;>Ljava/lang/Object;Ljava/util/concurrent/Callable<Ljava/lang/Object;>;Ljava/lang/Runnable;Lscala/ScalaObject;;
const #166 = Asciz	ScalaSig;
const #167 = Asciz	java/util/concurrent/Callable;
const #168 = class	#167;	//  java/util/concurrent/Callable
const #169 = Asciz	java/lang/Runnable;
const #170 = class	#169;	//  java/lang/Runnable
const #171 = Asciz	scala/ScalaObject;
const #172 = class	#171;	//  scala/ScalaObject

{
public scala.actors.ReactorTask(scala.actors.Reactor, scala.Function0);
  Code:
   Stack=2, Locals=3, Args_size=3
   0:	aload_0
   1:	aload_1
   2:	putfield	#17; //Field reactor:Lscala/actors/Reactor;
   5:	aload_0
   6:	aload_2
   7:	putfield	#19; //Field fun:Lscala/Function0;
   10:	aload_0
   11:	invokespecial	#24; //Method java/lang/Object."<init>":()V
   14:	return
  LineNumberTable: 
   line 23: 0

  LocalVariableTable: 
   Start  Length  Slot  Name   Signature
   0      15      0    this       Lscala/actors/ReactorTask;
   0      15      1    reactor       Lscala/actors/Reactor;
   0      15      2    fun       Lscala/Function0;

  Signature: length = 0x2
   00 1C 

public java.lang.Object call();
  Code:
   Stack=1, Locals=1, Args_size=1
   0:	aload_0
   1:	invokevirtual	#49; //Method call:()V
   4:	getstatic	#55; //Field scala/runtime/BoxedUnit.UNIT:Lscala/runtime/BoxedUnit;
   7:	areturn
  LineNumberTable: 
   line 23: 0


public void afterExecuting(java.lang.Exception);
  Code:
   Stack=0, Locals=2, Args_size=2
   0:	return
  LineNumberTable: 
   line 62: 0

  LocalVariableTable: 
   Start  Length  Slot  Name   Signature
   0      1      0    this       Lscala/actors/ReactorTask;
   0      1      1    e       Ljava/lang/Exception;


public void beforeExecuting();
  Code:
   Stack=0, Locals=1, Args_size=1
   0:	return
  LineNumberTable: 
   line 60: 0


public void call();
  Code:
   Stack=1, Locals=1, Args_size=1
   0:	aload_0
   1:	invokevirtual	#63; //Method run:()V
   4:	return
  LineNumberTable: 
   line 58: 0


public void run();
  Code:
   Stack=5, Locals=7, Args_size=1
   0:	getstatic	#69; //Field scala/actors/Actor$.MODULE$:Lscala/actors/Actor$;
   3:	invokevirtual	#73; //Method scala/actors/Actor$.tl:()Ljava/lang/ThreadLocal;
   6:	invokevirtual	#78; //Method java/lang/ThreadLocal.get:()Ljava/lang/Object;
   9:	checkcast	#35; //class scala/actors/Reactor
   12:	astore	5
   14:	getstatic	#69; //Field scala/actors/Actor$.MODULE$:Lscala/actors/Actor$;
   17:	invokevirtual	#73; //Method scala/actors/Actor$.tl:()Ljava/lang/ThreadLocal;
   20:	aload_0
   21:	invokevirtual	#33; //Method reactor:()Lscala/actors/Reactor;
   24:	invokevirtual	#82; //Method java/lang/ThreadLocal.set:(Ljava/lang/Object;)V
   27:	aload_0
   28:	invokevirtual	#84; //Method beforeExecuting:()V
   31:	aload_0
   32:	invokevirtual	#87; //Method fun:()Lscala/Function0;
   35:	invokeinterface	#92,  1; //InterfaceMethod scala/Function0.apply:()Ljava/lang/Object;
   40:	pop
   41:	goto	81
   44:	astore_2
   45:	aload_2
   46:	instanceof	#94; //class java/lang/Exception
   49:	ifeq	102
   52:	aload_2
   53:	checkcast	#94; //class java/lang/Exception
   56:	astore_1
   57:	aload_0
   58:	aload_1
   59:	invokespecial	#96; //Method gd1$1:(Ljava/lang/Exception;)Z
   62:	ifeq	84
   65:	aload_0
   66:	invokevirtual	#33; //Method reactor:()Lscala/actors/Reactor;
   69:	invokeinterface	#39,  1; //InterfaceMethod scala/actors/Reactor.exceptionHandler:()Lscala/PartialFunction;
   74:	aload_1
   75:	invokeinterface	#101,  2; //InterfaceMethod scala/Function1.apply:(Ljava/lang/Object;)Ljava/lang/Object;
   80:	pop
   81:	goto	121
   84:	iconst_1
   85:	ifeq	90
   88:	aload_2
   89:	athrow
   90:	new	#103; //class scala/MatchError
   93:	dup
   94:	aload_2
   95:	invokevirtual	#109; //Method java/lang/Throwable.toString:()Ljava/lang/String;
   98:	invokespecial	#112; //Method scala/MatchError."<init>":(Ljava/lang/String;)V
   101:	athrow
   102:	iconst_1
   103:	ifeq	108
   106:	aload_2
   107:	athrow
   108:	new	#103; //class scala/MatchError
   111:	dup
   112:	aload_2
   113:	invokevirtual	#109; //Method java/lang/Throwable.toString:()Ljava/lang/String;
   116:	invokespecial	#112; //Method scala/MatchError."<init>":(Ljava/lang/String;)V
   119:	athrow
   120:	pop
   121:	aload_0
   122:	invokevirtual	#33; //Method reactor:()Lscala/actors/Reactor;
   125:	invokeinterface	#115,  1; //InterfaceMethod scala/actors/Reactor.kill:()Lscala/Function0;
   130:	invokeinterface	#92,  1; //InterfaceMethod scala/Function0.apply:()Ljava/lang/Object;
   135:	pop
   136:	getstatic	#69; //Field scala/actors/Actor$.MODULE$:Lscala/actors/Actor$;
   139:	invokevirtual	#73; //Method scala/actors/Actor$.tl:()Ljava/lang/ThreadLocal;
   142:	aload	5
   144:	invokevirtual	#82; //Method java/lang/ThreadLocal.set:(Ljava/lang/Object;)V
   147:	aload_0
   148:	aconst_null
   149:	invokevirtual	#119; //Method reactor_$eq:(Lscala/actors/Reactor;)V
   152:	aload_0
   153:	aconst_null
   154:	invokevirtual	#123; //Method fun_$eq:(Lscala/Function0;)V
   157:	goto	265
   160:	pop
   161:	getstatic	#69; //Field scala/actors/Actor$.MODULE$:Lscala/actors/Actor$;
   164:	invokevirtual	#73; //Method scala/actors/Actor$.tl:()Ljava/lang/ThreadLocal;
   167:	aload	5
   169:	invokevirtual	#82; //Method java/lang/ThreadLocal.set:(Ljava/lang/Object;)V
   172:	aload_0
   173:	aconst_null
   174:	invokevirtual	#119; //Method reactor_$eq:(Lscala/actors/Reactor;)V
   177:	aload_0
   178:	aconst_null
   179:	invokevirtual	#123; //Method fun_$eq:(Lscala/Function0;)V
   182:	goto	265
   185:	astore	4
   187:	getstatic	#128; //Field scala/actors/Debug$.MODULE$:Lscala/actors/Debug$;
   190:	new	#130; //class scala/collection/mutable/StringBuilder
   193:	dup
   194:	invokespecial	#131; //Method scala/collection/mutable/StringBuilder."<init>":()V
   197:	aload_0
   198:	invokevirtual	#33; //Method reactor:()Lscala/actors/Reactor;
   201:	astore_3
   202:	new	#133; //class scala/runtime/StringAdd
   205:	dup
   206:	aload_3
   207:	invokespecial	#135; //Method scala/runtime/StringAdd."<init>":(Ljava/lang/Object;)V
   210:	ldc	#137; //String : caught 
   212:	invokevirtual	#141; //Method scala/runtime/StringAdd.$plus:(Ljava/lang/String;)Ljava/lang/String;
   215:	invokevirtual	#145; //Method scala/collection/mutable/StringBuilder.append:(Ljava/lang/Object;)Lscala/collection/mutable/StringBuilder;
   218:	aload	4
   220:	invokevirtual	#145; //Method scala/collection/mutable/StringBuilder.append:(Ljava/lang/Object;)Lscala/collection/mutable/StringBuilder;
   223:	invokevirtual	#146; //Method scala/collection/mutable/StringBuilder.toString:()Ljava/lang/String;
   226:	invokevirtual	#149; //Method scala/actors/Debug$.info:(Ljava/lang/String;)V
   229:	aload_0
   230:	invokevirtual	#33; //Method reactor:()Lscala/actors/Reactor;
   233:	invokeinterface	#152,  1; //InterfaceMethod scala/actors/Reactor.terminated:()V
   238:	aload_0
   239:	aload	4
   241:	invokevirtual	#154; //Method afterExecuting:(Ljava/lang/Exception;)V
   244:	getstatic	#69; //Field scala/actors/Actor$.MODULE$:Lscala/actors/Actor$;
   247:	invokevirtual	#73; //Method scala/actors/Actor$.tl:()Ljava/lang/ThreadLocal;
   250:	aload	5
   252:	invokevirtual	#82; //Method java/lang/ThreadLocal.set:(Ljava/lang/Object;)V
   255:	aload_0
   256:	aconst_null
   257:	invokevirtual	#119; //Method reactor_$eq:(Lscala/actors/Reactor;)V
   260:	aload_0
   261:	aconst_null
   262:	invokevirtual	#123; //Method fun_$eq:(Lscala/Function0;)V
   265:	return
   266:	astore	6
   268:	getstatic	#69; //Field scala/actors/Actor$.MODULE$:Lscala/actors/Actor$;
   271:	invokevirtual	#73; //Method scala/actors/Actor$.tl:()Ljava/lang/ThreadLocal;
   274:	aload	5
   276:	invokevirtual	#82; //Method java/lang/ThreadLocal.set:(Ljava/lang/Object;)V
   279:	aload_0
   280:	aconst_null
   281:	invokevirtual	#119; //Method reactor_$eq:(Lscala/actors/Reactor;)V
   284:	aload_0
   285:	aconst_null
   286:	invokevirtual	#123; //Method fun_$eq:(Lscala/Function0;)V
   289:	aload	6
   291:	athrow
  Exception table:
   from   to  target type
    31    44    44   Class java/lang/Throwable

    31   120   120   Class scala/actors/KillActorException

    27   136   160   Class scala/actors/SuspendActorException

    27   136   185   Class java/lang/Exception

    27   136   266   any
   160   161   266   any
   185   244   266   any
  LineNumberTable: 
   line 27: 0
   line 28: 14
   line 30: 27
   line 33: 31
   line 32: 44
   line 26: 52
   line 32: 57
   line 36: 65
   line 644: 81
   line 32: 88
   line 644: 102
   line 32: 106
   line 52: 120
   line 41: 121
   line 52: 136
   line 53: 147
   line 54: 152
   line 52: 160
   line 53: 172
   line 54: 177
   line 47: 185
   line 48: 187
   line 49: 229
   line 50: 238
   line 52: 244
   line 53: 255
   line 54: 260
   line 26: 265
   line 52: 268
   line 53: 279
   line 54: 284

  LocalVariableTable: 
   Start  Length  Slot  Name   Signature
   0      292      0    this       Lscala/actors/ReactorTask;
   57      24      1    temp2       Ljava/lang/Exception;
   84      18      1    temp2       Ljava/lang/Exception;
   14      278      5    saved       Lscala/actors/Reactor;


public void fun_$eq(scala.Function0);
  Code:
   Stack=2, Locals=2, Args_size=2
   0:	aload_0
   1:	aload_1
   2:	putfield	#19; //Field fun:Lscala/Function0;
   5:	return
  LineNumberTable: 
   line 23: 0

  Signature: length = 0x2
   00 FFFFFFA1 

public scala.Function0 fun();
  Code:
   Stack=1, Locals=1, Args_size=1
   0:	aload_0
   1:	getfield	#19; //Field fun:Lscala/Function0;
   4:	areturn
  LineNumberTable: 
   line 23: 0

  Signature: length = 0x2
   00 FFFFFFA2 

public void reactor_$eq(scala.actors.Reactor);
  Code:
   Stack=2, Locals=2, Args_size=2
   0:	aload_0
   1:	aload_1
   2:	putfield	#17; //Field reactor:Lscala/actors/Reactor;
   5:	return
  LineNumberTable: 
   line 23: 0

  Signature: length = 0x2
   00 FFFFFFA3 

public scala.actors.Reactor reactor();
  Code:
   Stack=1, Locals=1, Args_size=1
   0:	aload_0
   1:	getfield	#17; //Field reactor:Lscala/actors/Reactor;
   4:	areturn
  LineNumberTable: 
   line 23: 0

  Signature: length = 0x2
   00 FFFFFFA4 

}

