Compiled from "Reactor.scala"
public final class scala.actors.Reactor$$anonfun$4 extends java.lang.Object implements scala.Function0,scala.ScalaObject,java.io.Serializable
  SourceFile: "Reactor.scala"
  Scala: length = 0x
   
  InnerClass: 
   public final $anonfun$4=class scala/actors/Reactor$$anonfun$4 of class scala/actors/Reactor
  minor version: 0
  major version: 49
  Constant pool:
Asciz	SourceFile;
Asciz	Reactor.scala;
Asciz	<clinit>;
Asciz	()V;
Asciz	Code;
Asciz	serialVersionUID;
Asciz	J;
Asciz	scala/actors/Reactor$$anonfun$4;
class	scala/actors/Reactor$$anonfun$4
NameAndType	serialVersionUID:J
Field	scala/actors/Reactor$$anonfun$4.serialVersionUID:J
Asciz	msg$2;
Asciz	Ljava/lang/Object;;
Asciz	handler$2;
Asciz	Lscala/PartialFunction;;
Asciz	<init>;
Asciz	(Lscala/actors/Reactor;Lscala/PartialFunction;Ljava/lang/Object;)V;
Asciz	LineNumberTable;
NameAndType	handler$2:Lscala/PartialFunction;
Field	scala/actors/Reactor$$anonfun$4.handler$2:Lscala/PartialFunction;
NameAndType	msg$2:Ljava/lang/Object;
Field	scala/actors/Reactor$$anonfun$4.msg$2:Ljava/lang/Object;
Asciz	java/lang/Object;
class	java/lang/Object
NameAndType	"<init>":()V
Method	java/lang/Object."<init>":()V
Asciz	scala/Function0$class;
class	scala/Function0$class
Asciz	$init$;
Asciz	(Lscala/Function0;)V;
NameAndType	$init$:(Lscala/Function0;)V
Method	scala/Function0$class.$init$:(Lscala/Function0;)V
Asciz	this;
Asciz	Lscala/actors/Reactor$$anonfun$4;;
Asciz	$outer;
Asciz	Lscala/actors/Reactor;;
Asciz	LocalVariableTable;
Asciz	apply;
Asciz	()Ljava/lang/Object;;
NameAndType	apply:()V
Method	scala/actors/Reactor$$anonfun$4.apply:()V
Asciz	scala/runtime/BoxedUnit;
class	scala/runtime/BoxedUnit
Asciz	UNIT;
Asciz	Lscala/runtime/BoxedUnit;;
NameAndType	UNIT:Lscala/runtime/BoxedUnit;
Field	scala/runtime/BoxedUnit.UNIT:Lscala/runtime/BoxedUnit;
Asciz	scala/Function1;
class	scala/Function1
Asciz	(Ljava/lang/Object;)Ljava/lang/Object;;
NameAndType	apply:(Ljava/lang/Object;)Ljava/lang/Object;
InterfaceMethod	scala/Function1.apply:(Ljava/lang/Object;)Ljava/lang/Object;
Asciz	toString;
Asciz	()Ljava/lang/String;;
Asciz	(Lscala/Function0;)Ljava/lang/String;;
NameAndType	toString:(Lscala/Function0;)Ljava/lang/String;
Method	scala/Function0$class.toString:(Lscala/Function0;)Ljava/lang/String;
Asciz	Scala;
Asciz	InnerClasses;
Asciz	scala/actors/Reactor;
class	scala/actors/Reactor
Asciz	$anonfun$4;
Asciz	scala/Function0;
class	scala/Function0
Asciz	scala/ScalaObject;
class	scala/ScalaObject
Asciz	java/io/Serializable;
class	java/io/Serializable

{
public static final long serialVersionUID;
  Signature: J

private final java.lang.Object msg$2;
  Signature: Ljava/lang/Object;

private final scala.PartialFunction handler$2;
  Signature: Lscala/PartialFunction;

public static {};
  Signature: ()V
  Code:
   Stack=2, Locals=0, Args_size=0
	lconst_0
	putstatic	Field serialVersionUID:J
	return
  Labels:

public scala.actors.Reactor$$anonfun$4(scala.actors.Reactor, scala.PartialFunction, java.lang.Object);
  Signature: (Lscala/actors/Reactor;Lscala/PartialFunction;Ljava/lang/Object;)V
  Code:
   Stack=2, Locals=4, Args_size=4
	aload_0
	aload_2
	putfield	Field handler$2:Lscala/PartialFunction;
	aload_0
	aload_3
	putfield	Field msg$2:Ljava/lang/Object;
	aload_0
	invokespecial	Method java/lang/Object."<init>":()V
	aload_0
	invokestatic	Method scala/Function0$class.$init$:(Lscala/Function0;)V
	return
  Labels:
  LocalVariableTable: 
   Start  Length  Slot  Name   Signature
   0      19      0    this       Lscala/actors/Reactor$$anonfun$4;
   0      19      1    $outer       Lscala/actors/Reactor;


public final java.lang.Object apply();
  Signature: ()Ljava/lang/Object;
  Code:
   Stack=1, Locals=1, Args_size=1
	aload_0
	invokevirtual	Method apply:()V
	getstatic	Field scala/runtime/BoxedUnit.UNIT:Lscala/runtime/BoxedUnit;
	areturn
  Labels:

public final void apply();
  Signature: ()V
  Code:
   Stack=2, Locals=1, Args_size=1
	aload_0
	getfield	Field handler$2:Lscala/PartialFunction;
	aload_0
	getfield	Field msg$2:Ljava/lang/Object;
	invokeinterface	InterfaceMethod scala/Function1.apply:(Ljava/lang/Object;)Ljava/lang/Object;
	pop
	return
  Labels:

public java.lang.String toString();
  Signature: ()Ljava/lang/String;
  Code:
   Stack=1, Locals=1, Args_size=1
	aload_0
	invokestatic	Method scala/Function0$class.toString:(Lscala/Function0;)Ljava/lang/String;
	areturn
  Labels:

}

