Compiled from "Reactor.scala"
public final class scala.actors.Reactor$$anonfun$startSearch$1$$anonfun$apply$mcV$sp$1 extends scala.runtime.AbstractFunction0 implements java.io.Serializable
  SourceFile: "Reactor.scala"
  Scala: length = 0x
   
  InnerClass: 
   public final $anonfun$startSearch$1=class scala/actors/Reactor$$anonfun$startSearch$1 of class scala/actors/Reactor
   public final $anonfun$apply$mcV$sp$1=class scala/actors/Reactor$$anonfun$startSearch$1$$anonfun$apply$mcV$sp$1 of class scala/actors/Reactor$$anonfun$startSearch$1
  minor version: 0
  major version: 49
  Constant pool:
Asciz	SourceFile;
Asciz	Reactor.scala;
Asciz	<clinit>;
Asciz	()V;
Asciz	Code;
Asciz	serialVersionUID;
Asciz	J;
Asciz	scala/actors/Reactor$$anonfun$startSearch$1$$anonfun$apply$mcV$sp$1;
class	scala/actors/Reactor$$anonfun$startSearch$1$$anonfun$apply$mcV$sp$1
NameAndType	serialVersionUID:J
Field	scala/actors/Reactor$$anonfun$startSearch$1$$anonfun$apply$mcV$sp$1.serialVersionUID:J
Asciz	$outer;
Asciz	Lscala/actors/Reactor$$anonfun$startSearch$1;;
Asciz	apply;
Asciz	scala/actors/MQueue;
class	scala/actors/MQueue
Asciz	LineNumberTable;
Asciz	Start;
String	Start
Asciz	<init>;
Asciz	(Ljava/lang/String;)V;
NameAndType	"<init>":(Ljava/lang/String;)V
Method	scala/actors/MQueue."<init>":(Ljava/lang/String;)V
NameAndType	$outer:Lscala/actors/Reactor$$anonfun$startSearch$1;
Field	scala/actors/Reactor$$anonfun$startSearch$1$$anonfun$apply$mcV$sp$1.$outer:Lscala/actors/Reactor$$anonfun$startSearch$1;
Asciz	scala/actors/Reactor$$anonfun$startSearch$1;
class	scala/actors/Reactor$$anonfun$startSearch$1
Asciz	Lscala/actors/Reactor;;
NameAndType	$outer:Lscala/actors/Reactor;
Field	scala/actors/Reactor$$anonfun$startSearch$1.$outer:Lscala/actors/Reactor;
Asciz	msg$1;
Asciz	Ljava/lang/Object;;
NameAndType	msg$1:Ljava/lang/Object;
Field	scala/actors/Reactor$$anonfun$startSearch$1.msg$1:Ljava/lang/Object;
Asciz	replyTo$1;
Asciz	Lscala/actors/OutputChannel;;
NameAndType	replyTo$1:Lscala/actors/OutputChannel;
Field	scala/actors/Reactor$$anonfun$startSearch$1.replyTo$1:Lscala/actors/OutputChannel;
Asciz	append;
Asciz	(Ljava/lang/Object;Lscala/actors/OutputChannel;)V;
NameAndType	append:(Ljava/lang/Object;Lscala/actors/OutputChannel;)V
Method	scala/actors/MQueue.append:(Ljava/lang/Object;Lscala/actors/OutputChannel;)V
Asciz	handler$1;
Asciz	Lscala/PartialFunction;;
NameAndType	handler$1:Lscala/PartialFunction;
Field	scala/actors/Reactor$$anonfun$startSearch$1.handler$1:Lscala/PartialFunction;
Asciz	scala/actors/Reactor;
class	scala/actors/Reactor
Asciz	searchMailbox;
Asciz	(Lscala/actors/MQueue;Lscala/PartialFunction;Z)V;
NameAndType	searchMailbox:(Lscala/actors/MQueue;Lscala/PartialFunction;Z)V
InterfaceMethod	scala/actors/Reactor.searchMailbox:(Lscala/actors/MQueue;Lscala/PartialFunction;Z)V
Asciz	this;
Asciz	Lscala/actors/Reactor$$anonfun$startSearch$1$$anonfun$apply$mcV$sp$1;;
Asciz	startMbox0;
Asciz	Lscala/actors/MQueue;;
Asciz	LocalVariableTable;
Asciz	apply$mcV$sp;
Asciz	startMbox;
Asciz	()Ljava/lang/Object;;
NameAndType	apply:()V
Method	scala/actors/Reactor$$anonfun$startSearch$1$$anonfun$apply$mcV$sp$1.apply:()V
Asciz	scala/runtime/BoxedUnit;
class	scala/runtime/BoxedUnit
Asciz	UNIT;
Asciz	Lscala/runtime/BoxedUnit;;
NameAndType	UNIT:Lscala/runtime/BoxedUnit;
Field	scala/runtime/BoxedUnit.UNIT:Lscala/runtime/BoxedUnit;
Asciz	(Lscala/actors/Reactor$$anonfun$startSearch$1;)V;
Asciz	java/lang/NullPointerException;
class	java/lang/NullPointerException
NameAndType	"<init>":()V
Method	java/lang/NullPointerException."<init>":()V
Asciz	scala/runtime/AbstractFunction0;
class	scala/runtime/AbstractFunction0
Method	scala/runtime/AbstractFunction0."<init>":()V
Asciz	(Lscala/actors/Reactor<TMsg;>.$anonfun$startSearch$1;)V;
Asciz	Signature;
Asciz	Scala;
Asciz	InnerClasses;
Asciz	$anonfun$startSearch$1;
Asciz	$anonfun$apply$mcV$sp$1;
Asciz	java/io/Serializable;
class	java/io/Serializable

{
public static final long serialVersionUID;
  Signature: J

public final scala.actors.Reactor$$anonfun$startSearch$1 $outer;
  Signature: Lscala/actors/Reactor$$anonfun$startSearch$1;

public static {};
  Signature: ()V
  Code:
   Stack=2, Locals=0, Args_size=0
	lconst_0
	putstatic	Field serialVersionUID:J
	return
  Labels:

public final void apply();
  Signature: ()V
  Code:
   Stack=4, Locals=5, Args_size=1
	new	class scala/actors/MQueue
	dup
	ldc	String Start
	invokespecial	Method scala/actors/MQueue."<init>":(Ljava/lang/String;)V
	astore_3
	aload_0
	getfield	Field $outer:Lscala/actors/Reactor$$anonfun$startSearch$1;
	astore_1
	aload_1
	getfield	Field scala/actors/Reactor$$anonfun$startSearch$1.$outer:Lscala/actors/Reactor;
	dup
	astore	4
	monitorenter
	aload_3
	aload_0
	getfield	Field $outer:Lscala/actors/Reactor$$anonfun$startSearch$1;
	getfield	Field scala/actors/Reactor$$anonfun$startSearch$1.msg$1:Ljava/lang/Object;
	aload_0
	getfield	Field $outer:Lscala/actors/Reactor$$anonfun$startSearch$1;
	getfield	Field scala/actors/Reactor$$anonfun$startSearch$1.replyTo$1:Lscala/actors/OutputChannel;
	invokevirtual	Method scala/actors/MQueue.append:(Ljava/lang/Object;Lscala/actors/OutputChannel;)V
	aload	4
	monitorexit
	aload_0
	getfield	Field $outer:Lscala/actors/Reactor$$anonfun$startSearch$1;
	astore_2
	aload_2
	getfield	Field scala/actors/Reactor$$anonfun$startSearch$1.$outer:Lscala/actors/Reactor;
	aload_3
	aload_0
	getfield	Field $outer:Lscala/actors/Reactor$$anonfun$startSearch$1;
	getfield	Field scala/actors/Reactor$$anonfun$startSearch$1.handler$1:Lscala/PartialFunction;
	iconst_1
	invokeinterface	InterfaceMethod scala/actors/Reactor.searchMailbox:(Lscala/actors/MQueue;Lscala/PartialFunction;Z)V
	return
	aload	4
	monitorexit
	athrow
  Labels:
  Exception table:
   from   to  target type
    23    44    68   any
  LocalVariableTable: 
   Start  Length  Slot  Name   Signature
   0      72      0    this       Lscala/actors/Reactor$$anonfun$startSearch$1$$anonfun$apply$mcV$sp$1;
   10      57      3    startMbox0       Lscala/actors/MQueue;
   68      4      3    startMbox0       Lscala/actors/MQueue;


public void apply$mcV$sp();
  Signature: ()V
  Code:
   Stack=4, Locals=5, Args_size=1
	new	class scala/actors/MQueue
	dup
	ldc	String Start
	invokespecial	Method scala/actors/MQueue."<init>":(Ljava/lang/String;)V
	astore_3
	aload_0
	getfield	Field $outer:Lscala/actors/Reactor$$anonfun$startSearch$1;
	astore_1
	aload_1
	getfield	Field scala/actors/Reactor$$anonfun$startSearch$1.$outer:Lscala/actors/Reactor;
	dup
	astore	4
	monitorenter
	aload_3
	aload_0
	getfield	Field $outer:Lscala/actors/Reactor$$anonfun$startSearch$1;
	getfield	Field scala/actors/Reactor$$anonfun$startSearch$1.msg$1:Ljava/lang/Object;
	aload_0
	getfield	Field $outer:Lscala/actors/Reactor$$anonfun$startSearch$1;
	getfield	Field scala/actors/Reactor$$anonfun$startSearch$1.replyTo$1:Lscala/actors/OutputChannel;
	invokevirtual	Method scala/actors/MQueue.append:(Ljava/lang/Object;Lscala/actors/OutputChannel;)V
	aload	4
	monitorexit
	aload_0
	getfield	Field $outer:Lscala/actors/Reactor$$anonfun$startSearch$1;
	astore_2
	aload_2
	getfield	Field scala/actors/Reactor$$anonfun$startSearch$1.$outer:Lscala/actors/Reactor;
	aload_3
	aload_0
	getfield	Field $outer:Lscala/actors/Reactor$$anonfun$startSearch$1;
	getfield	Field scala/actors/Reactor$$anonfun$startSearch$1.handler$1:Lscala/PartialFunction;
	iconst_1
	invokeinterface	InterfaceMethod scala/actors/Reactor.searchMailbox:(Lscala/actors/MQueue;Lscala/PartialFunction;Z)V
	return
	aload	4
	monitorexit
	athrow
  Labels:
  Exception table:
   from   to  target type
    23    44    68   any
  LocalVariableTable: 
   Start  Length  Slot  Name   Signature
   0      72      0    this       Lscala/actors/Reactor$$anonfun$startSearch$1$$anonfun$apply$mcV$sp$1;
   10      57      3    startMbox       Lscala/actors/MQueue;
   68      4      3    startMbox       Lscala/actors/MQueue;


public final java.lang.Object apply();
  Signature: ()Ljava/lang/Object;
  Code:
   Stack=1, Locals=1, Args_size=1
	aload_0
	invokevirtual	Method apply:()V
	getstatic	Field scala/runtime/BoxedUnit.UNIT:Lscala/runtime/BoxedUnit;
	areturn
  Labels:

public scala.actors.Reactor$$anonfun$startSearch$1$$anonfun$apply$mcV$sp$1(scala.actors.Reactor$$anonfun$startSearch$1);
  Signature: (Lscala/actors/Reactor$$anonfun$startSearch$1;)V
  Code:
   Stack=2, Locals=2, Args_size=2
	aload_1
	ifnonnull	l1 // aload_0
	new	class java/lang/NullPointerException
	dup
	invokespecial	Method java/lang/NullPointerException."<init>":()V
	athrow
l1	aload_0
	aload_1
	putfield	Field $outer:Lscala/actors/Reactor$$anonfun$startSearch$1;
	aload_0
	invokespecial	Method scala/runtime/AbstractFunction0."<init>":()V
	return
  Labels:
   	l1 = 12 // aload_0
  LocalVariableTable: 
   Start  Length  Slot  Name   Signature
   0      22      0    this       Lscala/actors/Reactor$$anonfun$startSearch$1$$anonfun$apply$mcV$sp$1;
   0      22      1    $outer       Lscala/actors/Reactor$$anonfun$startSearch$1;

  Signature: length = 0x2
   00 4D 

}

