Compiled from "Reactor.scala"
public abstract class scala.actors.Reactor$class extends java.lang.Object
  SourceFile: "Reactor.scala"
  Scala: length = 0x
   
  InnerClass: 
   public final $anonfun$2=class scala/actors/Reactor$$anonfun$2 of class scala/actors/Reactor
   public final $anonfun$3=class scala/actors/Reactor$$anonfun$3 of class scala/actors/Reactor
   public final $anonfun$4=class scala/actors/Reactor$$anonfun$4 of class scala/actors/Reactor
   public final $anonfun$5=class scala/actors/Reactor$$anonfun$5 of class scala/actors/Reactor
   public final $anonfun$6=class scala/actors/Reactor$$anonfun$6 of class scala/actors/Reactor
   public final $anonfun$1=class scala/actors/Reactor$$anonfun$1 of class scala/actors/Reactor
   public final $anonfun$seq$1=class scala/actors/Reactor$$anonfun$seq$1 of class scala/actors/Reactor
   public final $anonfun$react$2=class scala/actors/Reactor$$anonfun$react$2 of class scala/actors/Reactor
   public final $anonfun$startSearch$1=class scala/actors/Reactor$$anonfun$startSearch$1 of class scala/actors/Reactor
   public final $anonfun$searchMailbox$1=class scala/actors/Reactor$$anonfun$searchMailbox$1 of class scala/actors/Reactor
  minor version: 0
  major version: 49
  Constant pool:
Asciz	SourceFile;
Asciz	Reactor.scala;
Asciz	$init$;
Asciz	(Lscala/actors/Reactor;)V;
Asciz	Code;
Asciz	LineNumberTable;
Asciz	scala/actors/MessageQueue;
class	scala/actors/MessageQueue
Asciz	Reactor;
String	Reactor
Asciz	<init>;
Asciz	(Ljava/lang/String;)V;
NameAndType	"<init>":(Ljava/lang/String;)V
Method	scala/actors/MessageQueue."<init>":(Ljava/lang/String;)V
Asciz	scala/actors/Reactor;
class	scala/actors/Reactor
Asciz	scala$actors$Reactor$_setter_$mailbox_$eq;
Asciz	(Lscala/actors/MessageQueue;)V;
NameAndType	scala$actors$Reactor$_setter_$mailbox_$eq:(Lscala/actors/MessageQueue;)V
InterfaceMethod	scala/actors/Reactor.scala$actors$Reactor$_setter_$mailbox_$eq:(Lscala/actors/MessageQueue;)V
Asciz	scala/collection/mutable/Queue;
class	scala/collection/mutable/Queue
Asciz	()V;
NameAndType	"<init>":()V
Method	scala/collection/mutable/Queue."<init>":()V
Asciz	scala$actors$Reactor$_setter_$sendBuffer_$eq;
Asciz	(Lscala/collection/mutable/Queue;)V;
NameAndType	scala$actors$Reactor$_setter_$sendBuffer_$eq:(Lscala/collection/mutable/Queue;)V
InterfaceMethod	scala/actors/Reactor.scala$actors$Reactor$_setter_$sendBuffer_$eq:(Lscala/collection/mutable/Queue;)V
Asciz	continuation_$eq;
Asciz	(Lscala/PartialFunction;)V;
NameAndType	continuation_$eq:(Lscala/PartialFunction;)V
InterfaceMethod	scala/actors/Reactor.continuation_$eq:(Lscala/PartialFunction;)V
Asciz	scala/actors/Reactor$$anonfun$1;
class	scala/actors/Reactor$$anonfun$1
NameAndType	"<init>":(Lscala/actors/Reactor;)V
Method	scala/actors/Reactor$$anonfun$1."<init>":(Lscala/actors/Reactor;)V
Asciz	scala$actors$Reactor$_setter_$waitingForNone_$eq;
Asciz	(Lscala/Function1;)V;
NameAndType	scala$actors$Reactor$_setter_$waitingForNone_$eq:(Lscala/Function1;)V
InterfaceMethod	scala/actors/Reactor.scala$actors$Reactor$_setter_$waitingForNone_$eq:(Lscala/Function1;)V
Asciz	waitingForNone;
Asciz	()Lscala/Function1;;
NameAndType	waitingForNone:()Lscala/Function1;
InterfaceMethod	scala/actors/Reactor.waitingForNone:()Lscala/Function1;
Asciz	waitingFor_$eq;
NameAndType	waitingFor_$eq:(Lscala/Function1;)V
InterfaceMethod	scala/actors/Reactor.waitingFor_$eq:(Lscala/Function1;)V
Asciz	scala/actors/Reactor$$anonfun$6;
class	scala/actors/Reactor$$anonfun$6
Method	scala/actors/Reactor$$anonfun$6."<init>":(Lscala/actors/Reactor;)V
Asciz	kill_$eq;
Asciz	(Lscala/Function0;)V;
NameAndType	kill_$eq:(Lscala/Function0;)V
InterfaceMethod	scala/actors/Reactor.kill_$eq:(Lscala/Function0;)V
Asciz	$this;
Asciz	Lscala/actors/Reactor;;
Asciz	LocalVariableTable;
Asciz	terminated;
Asciz	scheduler;
Asciz	()Lscala/actors/IScheduler;;
NameAndType	scheduler:()Lscala/actors/IScheduler;
InterfaceMethod	scala/actors/Reactor.scheduler:()Lscala/actors/IScheduler;
Asciz	scala/actors/IScheduler;
class	scala/actors/IScheduler
NameAndType	terminated:(Lscala/actors/Reactor;)V
InterfaceMethod	scala/actors/IScheduler.terminated:(Lscala/actors/Reactor;)V
Asciz	exit;
Asciz	(Lscala/actors/Reactor;)Lscala/runtime/Nothing$;;
NameAndType	terminated:()V
InterfaceMethod	scala/actors/Reactor.terminated:()V
Asciz	scala/actors/Actor$;
class	scala/actors/Actor$
Asciz	MODULE$;
Asciz	Lscala/actors/Actor$;;
NameAndType	MODULE$:Lscala/actors/Actor$;
Field	scala/actors/Actor$.MODULE$:Lscala/actors/Actor$;
Asciz	suspendException;
Asciz	()Lscala/actors/SuspendActorException;;
NameAndType	suspendException:()Lscala/actors/SuspendActorException;
Method	scala/actors/Actor$.suspendException:()Lscala/actors/SuspendActorException;
Asciz	seq;
Asciz	(Lscala/actors/Reactor;Lscala/Function0;Lscala/Function0;)V;
Asciz	rawSelf;
Asciz	(Lscala/actors/IScheduler;)Lscala/actors/Reactor;;
NameAndType	rawSelf:(Lscala/actors/IScheduler;)Lscala/actors/Reactor;
Method	scala/actors/Actor$.rawSelf:(Lscala/actors/IScheduler;)Lscala/actors/Reactor;
Asciz	kill;
Asciz	()Lscala/Function0;;
NameAndType	kill:()Lscala/Function0;
InterfaceMethod	scala/actors/Reactor.kill:()Lscala/Function0;
Asciz	scala/actors/Reactor$$anonfun$seq$1;
class	scala/actors/Reactor$$anonfun$seq$1
Asciz	(Lscala/actors/Reactor;Lscala/Function0;Lscala/actors/Reactor;Lscala/Function0;)V;
NameAndType	"<init>":(Lscala/actors/Reactor;Lscala/Function0;Lscala/actors/Reactor;Lscala/Function0;)V
Method	scala/actors/Reactor$$anonfun$seq$1."<init>":(Lscala/actors/Reactor;Lscala/Function0;Lscala/actors/Reactor;Lscala/Function0;)V
Asciz	scala/Function0;
class	scala/Function0
Asciz	apply;
Asciz	()Ljava/lang/Object;;
NameAndType	apply:()Ljava/lang/Object;
InterfaceMethod	scala/Function0.apply:()Ljava/lang/Object;
Asciz	scala/actors/KillActorException;
class	scala/actors/KillActorException
Method	scala/actors/KillActorException."<init>":()V
Asciz	first;
Asciz	Lscala/Function0;;
Asciz	next$1;
Asciz	s$1;
Asciz	killNext$1;
Asciz	start;
Asciz	(Lscala/actors/Reactor;)Lscala/actors/Reactor;;
Asciz	newActor;
NameAndType	newActor:(Lscala/actors/Reactor;)V
InterfaceMethod	scala/actors/IScheduler.newActor:(Lscala/actors/Reactor;)V
Asciz	scala/actors/ReactorTask;
class	scala/actors/ReactorTask
Asciz	scala/actors/Reactor$$anonfun$5;
class	scala/actors/Reactor$$anonfun$5
Method	scala/actors/Reactor$$anonfun$5."<init>":(Lscala/actors/Reactor;)V
Asciz	(Lscala/actors/Reactor;Lscala/Function0;)V;
NameAndType	"<init>":(Lscala/actors/Reactor;Lscala/Function0;)V
Method	scala/actors/ReactorTask."<init>":(Lscala/actors/Reactor;Lscala/Function0;)V
Asciz	execute;
Asciz	(Ljava/lang/Runnable;)V;
NameAndType	execute:(Ljava/lang/Runnable;)V
InterfaceMethod	scala/actors/IScheduler.execute:(Ljava/lang/Runnable;)V
Asciz	task;
Asciz	Lscala/actors/ReactorTask;;
Asciz	scheduleActor;
Asciz	(Lscala/actors/Reactor;Lscala/PartialFunction;Ljava/lang/Object;)V;
Asciz	scala/actors/Reactor$$anonfun$4;
class	scala/actors/Reactor$$anonfun$4
NameAndType	"<init>":(Lscala/actors/Reactor;Lscala/PartialFunction;Ljava/lang/Object;)V
Method	scala/actors/Reactor$$anonfun$4."<init>":(Lscala/actors/Reactor;Lscala/PartialFunction;Ljava/lang/Object;)V
Asciz	executeFromActor;
NameAndType	executeFromActor:(Ljava/lang/Runnable;)V
InterfaceMethod	scala/actors/IScheduler.executeFromActor:(Ljava/lang/Runnable;)V
Asciz	handler$2;
Asciz	Lscala/PartialFunction;;
Asciz	msg$2;
Asciz	Ljava/lang/Object;;
Asciz	fun;
Asciz	react;
Asciz	(Lscala/actors/Reactor;Lscala/PartialFunction;)Lscala/runtime/Nothing$;;
Asciz	java/lang/Object;
class	java/lang/Object
Asciz	equals;
Asciz	(Ljava/lang/Object;)Z;
NameAndType	equals:(Ljava/lang/Object;)Z
Method	java/lang/Object.equals:(Ljava/lang/Object;)Z
Asciz	java/lang/AssertionError;
class	java/lang/AssertionError
Asciz	scala/collection/mutable/StringBuilder;
class	scala/collection/mutable/StringBuilder
Method	scala/collection/mutable/StringBuilder."<init>":()V
Asciz	assertion failed: ;
String	assertion failed: 
Asciz	append;
Asciz	(Ljava/lang/Object;)Lscala/collection/mutable/StringBuilder;;
NameAndType	append:(Ljava/lang/Object;)Lscala/collection/mutable/StringBuilder;
Method	scala/collection/mutable/StringBuilder.append:(Ljava/lang/Object;)Lscala/collection/mutable/StringBuilder;
Asciz	react on channel belonging to other actor;
String	react on channel belonging to other actor
Asciz	toString;
Asciz	()Ljava/lang/String;;
NameAndType	toString:()Ljava/lang/String;
Method	scala/collection/mutable/StringBuilder.toString:()Ljava/lang/String;
Asciz	(Ljava/lang/Object;)V;
NameAndType	"<init>":(Ljava/lang/Object;)V
Method	java/lang/AssertionError."<init>":(Ljava/lang/Object;)V
Asciz	mailbox;
Asciz	()Lscala/actors/MessageQueue;;
NameAndType	mailbox:()Lscala/actors/MessageQueue;
InterfaceMethod	scala/actors/Reactor.mailbox:()Lscala/actors/MessageQueue;
Asciz	drainSendBuffer;
NameAndType	drainSendBuffer:(Lscala/actors/MessageQueue;)V
InterfaceMethod	scala/actors/Reactor.drainSendBuffer:(Lscala/actors/MessageQueue;)V
Asciz	scala/actors/Reactor$$anonfun$react$2;
class	scala/actors/Reactor$$anonfun$react$2
Asciz	(Lscala/actors/Reactor;Lscala/PartialFunction;)V;
NameAndType	"<init>":(Lscala/actors/Reactor;Lscala/PartialFunction;)V
Method	scala/actors/Reactor$$anonfun$react$2."<init>":(Lscala/actors/Reactor;Lscala/PartialFunction;)V
Asciz	searchMailbox;
Asciz	(Lscala/actors/MessageQueue;Lscala/Function1;Z)V;
NameAndType	searchMailbox:(Lscala/actors/MessageQueue;Lscala/Function1;Z)V
InterfaceMethod	scala/actors/Reactor.searchMailbox:(Lscala/actors/MessageQueue;Lscala/Function1;Z)V
Asciz	f$1;
Asciz	(Lscala/actors/Reactor;Lscala/actors/MessageQueue;Lscala/Function1;Z)V;
Asciz	scala/actors/Reactor$$anonfun$3;
class	scala/actors/Reactor$$anonfun$3
Asciz	(Lscala/actors/Reactor;Lscala/Function1;)V;
NameAndType	"<init>":(Lscala/actors/Reactor;Lscala/Function1;)V
Method	scala/actors/Reactor$$anonfun$3."<init>":(Lscala/actors/Reactor;Lscala/Function1;)V
Asciz	extractFirst;
Asciz	(Lscala/Function2;)Lscala/actors/MessageQueueElement;;
NameAndType	extractFirst:(Lscala/Function2;)Lscala/actors/MessageQueueElement;
Method	scala/actors/MessageQueue.extractFirst:(Lscala/Function2;)Lscala/actors/MessageQueueElement;
Asciz	scala/actors/Reactor$$anonfun$searchMailbox$1;
class	scala/actors/Reactor$$anonfun$searchMailbox$1
Method	scala/actors/Reactor$$anonfun$searchMailbox$1."<init>":(Lscala/actors/Reactor;)V
Asciz	foreach;
Asciz	(Lscala/Function2;)V;
NameAndType	foreach:(Lscala/Function2;)V
Method	scala/actors/MessageQueue.foreach:(Lscala/Function2;)V
Asciz	sendBuffer;
Asciz	()Lscala/collection/mutable/Queue;;
NameAndType	sendBuffer:()Lscala/collection/mutable/Queue;
InterfaceMethod	scala/actors/Reactor.sendBuffer:()Lscala/collection/mutable/Queue;
Asciz	isEmpty;
Asciz	()Z;
NameAndType	isEmpty:()Z
Method	scala/collection/mutable/Queue.isEmpty:()Z
Asciz	Temp;
String	Temp
Asciz	scala/Tuple2;
class	scala/Tuple2
Asciz	scala/actors/MessageQueueElement;
class	scala/actors/MessageQueueElement
Asciz	msg;
NameAndType	msg:()Ljava/lang/Object;
Method	scala/actors/MessageQueueElement.msg:()Ljava/lang/Object;
Asciz	session;
Asciz	()Lscala/actors/OutputChannel;;
NameAndType	session:()Lscala/actors/OutputChannel;
Method	scala/actors/MessageQueueElement.session:()Lscala/actors/OutputChannel;
Asciz	(Ljava/lang/Object;Ljava/lang/Object;)V;
NameAndType	"<init>":(Ljava/lang/Object;Ljava/lang/Object;)V
Method	scala/Tuple2."<init>":(Ljava/lang/Object;Ljava/lang/Object;)V
Asciz	resumeReceiver;
Asciz	(Lscala/Tuple2;Z)V;
NameAndType	resumeReceiver:(Lscala/Tuple2;Z)V
InterfaceMethod	scala/actors/Reactor.resumeReceiver:(Lscala/Tuple2;Z)V
Asciz	startMbox;
Asciz	Lscala/actors/MessageQueue;;
Asciz	handlesMessage$1;
Asciz	Lscala/Function1;;
Asciz	resumeOnSameThread;
Asciz	Z;
Asciz	tmpMbox;
Asciz	qel;
Asciz	Lscala/actors/MessageQueueElement;;
Asciz	done;
Asciz	(Lscala/actors/Reactor;Lscala/actors/MessageQueue;)V;
Asciz	dequeue;
NameAndType	dequeue:()Ljava/lang/Object;
Method	scala/collection/mutable/Queue.dequeue:()Ljava/lang/Object;
Asciz	_1;
NameAndType	_1:()Ljava/lang/Object;
Method	scala/Tuple2._1:()Ljava/lang/Object;
Asciz	_2;
NameAndType	_2:()Ljava/lang/Object;
Method	scala/Tuple2._2:()Ljava/lang/Object;
Asciz	scala/actors/OutputChannel;
class	scala/actors/OutputChannel
Asciz	(Ljava/lang/Object;Lscala/actors/OutputChannel;)V;
NameAndType	append:(Ljava/lang/Object;Lscala/actors/OutputChannel;)V
Method	scala/actors/MessageQueue.append:(Ljava/lang/Object;Lscala/actors/OutputChannel;)V
Asciz	mbox;
Asciz	item;
Asciz	Lscala/Tuple2;;
Asciz	receiver;
Asciz	(Lscala/actors/Reactor;)Lscala/actors/Actor;;
Asciz	scala/actors/Actor;
class	scala/actors/Actor
Asciz	forward;
Asciz	(Lscala/actors/Reactor;Ljava/lang/Object;)V;
Asciz	send;
NameAndType	send:(Ljava/lang/Object;Lscala/actors/OutputChannel;)V
InterfaceMethod	scala/actors/Reactor.send:(Ljava/lang/Object;Lscala/actors/OutputChannel;)V
Asciz	$bang;
Asciz	(Lscala/actors/Reactor;Lscala/Tuple2;Z)V;
Asciz	continuation;
Asciz	()Lscala/PartialFunction;;
NameAndType	continuation:()Lscala/PartialFunction;
InterfaceMethod	scala/actors/Reactor.continuation:()Lscala/PartialFunction;
Asciz	scala/Function1;
class	scala/Function1
Asciz	(Ljava/lang/Object;)Ljava/lang/Object;;
NameAndType	apply:(Ljava/lang/Object;)Ljava/lang/Object;
InterfaceMethod	scala/Function1.apply:(Ljava/lang/Object;)Ljava/lang/Object;
Asciz	(Lscala/PartialFunction;Ljava/lang/Object;)V;
NameAndType	scheduleActor:(Lscala/PartialFunction;Ljava/lang/Object;)V
InterfaceMethod	scala/actors/Reactor.scheduleActor:(Lscala/PartialFunction;Ljava/lang/Object;)V
Asciz	onSameThread;
Asciz	makeReaction;
Asciz	(Lscala/actors/Reactor;Lscala/Function0;)Ljava/lang/Runnable;;
Asciz	startSearch;
Asciz	(Lscala/actors/Reactor;Ljava/lang/Object;Lscala/actors/OutputChannel;Lscala/Function1;)Lscala/Function0;;
Asciz	scala/actors/Reactor$$anonfun$startSearch$1;
class	scala/actors/Reactor$$anonfun$startSearch$1
Asciz	(Lscala/actors/Reactor;Ljava/lang/Object;Lscala/actors/OutputChannel;Lscala/Function1;)V;
NameAndType	"<init>":(Lscala/actors/Reactor;Ljava/lang/Object;Lscala/actors/OutputChannel;Lscala/Function1;)V
Method	scala/actors/Reactor$$anonfun$startSearch$1."<init>":(Lscala/actors/Reactor;Ljava/lang/Object;Lscala/actors/OutputChannel;Lscala/Function1;)V
Asciz	msg$1;
Asciz	replyTo$1;
Asciz	Lscala/actors/OutputChannel;;
Asciz	handler$1;
Asciz	(Lscala/actors/Reactor;Ljava/lang/Object;Lscala/actors/OutputChannel;)V;
Asciz	waitingFor;
NameAndType	waitingFor:()Lscala/Function1;
InterfaceMethod	scala/actors/Reactor.waitingFor:()Lscala/Function1;
Asciz	(Ljava/lang/Object;Lscala/actors/OutputChannel;Lscala/Function1;)Lscala/Function0;;
NameAndType	startSearch:(Ljava/lang/Object;Lscala/actors/OutputChannel;Lscala/Function1;)Lscala/Function0;
InterfaceMethod	scala/actors/Reactor.startSearch:(Ljava/lang/Object;Lscala/actors/OutputChannel;Lscala/Function1;)Lscala/Function0;
Asciz	scala/Predef$;
class	scala/Predef$
Asciz	Lscala/Predef$;;
NameAndType	MODULE$:Lscala/Predef$;
Field	scala/Predef$.MODULE$:Lscala/Predef$;
Asciz	[Ljava/lang/Object;;
class	"[Ljava/lang/Object;"
Asciz	wrapRefArray;
Asciz	([Ljava/lang/Object;)Lscala/collection/mutable/WrappedArray;;
NameAndType	wrapRefArray:([Ljava/lang/Object;)Lscala/collection/mutable/WrappedArray;
Method	scala/Predef$.wrapRefArray:([Ljava/lang/Object;)Lscala/collection/mutable/WrappedArray;
Asciz	enqueue;
Asciz	(Lscala/collection/Seq;)V;
NameAndType	enqueue:(Lscala/collection/Seq;)V
Method	scala/collection/mutable/Queue.enqueue:(Lscala/collection/Seq;)V
Asciz	scala/actors/Reactor$$anonfun$2;
class	scala/actors/Reactor$$anonfun$2
Method	scala/actors/Reactor$$anonfun$2."<init>":(Lscala/actors/Reactor;)V
Asciz	replyTo;
Asciz	savedWaitingFor;
Asciz	todo;
Asciz	mailboxSize;
Asciz	(Lscala/actors/Reactor;)I;
Asciz	size;
Asciz	()I;
NameAndType	size:()I
Method	scala/actors/MessageQueue.size:()I
Asciz	(Lscala/actors/Reactor;)Lscala/actors/IScheduler;;
Asciz	scala/actors/Reactor$;
class	scala/actors/Reactor$
Asciz	Lscala/actors/Reactor$;;
NameAndType	MODULE$:Lscala/actors/Reactor$;
Field	scala/actors/Reactor$.MODULE$:Lscala/actors/Reactor$;
NameAndType	scheduler:()Ljava/lang/Object;
Method	scala/actors/Reactor$.scheduler:()Ljava/lang/Object;
Asciz	exceptionHandler;
Asciz	(Lscala/actors/Reactor;)Lscala/PartialFunction;;
Asciz	Map;
Asciz	()Lscala/collection/immutable/Map$;;
NameAndType	Map:()Lscala/collection/immutable/Map$;
Method	scala/Predef$.Map:()Lscala/collection/immutable/Map$;
Asciz	scala/collection/immutable/Map$;
class	scala/collection/immutable/Map$
Asciz	(Lscala/collection/Seq;)Lscala/collection/Map;;
NameAndType	apply:(Lscala/collection/Seq;)Lscala/collection/Map;
Method	scala/collection/immutable/Map$.apply:(Lscala/collection/Seq;)Lscala/collection/Map;
Asciz	Scala;
Asciz	InnerClasses;
Asciz	$anonfun$2;
Asciz	$anonfun$3;
Asciz	$anonfun$4;
Asciz	$anonfun$5;
Asciz	$anonfun$6;
Asciz	$anonfun$1;
Asciz	$anonfun$seq$1;
Asciz	$anonfun$react$2;
Asciz	$anonfun$startSearch$1;
Asciz	$anonfun$searchMailbox$1;
Asciz	scala/actors/Reactor$class;
class	scala/actors/Reactor$class

{
public static void $init$(scala.actors.Reactor);
  Signature: (Lscala/actors/Reactor;)V
  Code:
   Stack=4, Locals=1, Args_size=1
	aload_0
	new	class scala/actors/MessageQueue
	dup
	ldc	String Reactor
	invokespecial	Method scala/actors/MessageQueue."<init>":(Ljava/lang/String;)V
	invokeinterface	InterfaceMethod scala/actors/Reactor.scala$actors$Reactor$_setter_$mailbox_$eq:(Lscala/actors/MessageQueue;)V
	aload_0
	new	class scala/collection/mutable/Queue
	dup
	invokespecial	Method scala/collection/mutable/Queue."<init>":()V
	invokeinterface	InterfaceMethod scala/actors/Reactor.scala$actors$Reactor$_setter_$sendBuffer_$eq:(Lscala/collection/mutable/Queue;)V
	aload_0
	aconst_null
	invokeinterface	InterfaceMethod scala/actors/Reactor.continuation_$eq:(Lscala/PartialFunction;)V
	aload_0
	new	class scala/actors/Reactor$$anonfun$1
	dup
	aload_0
	invokespecial	Method scala/actors/Reactor$$anonfun$1."<init>":(Lscala/actors/Reactor;)V
	invokeinterface	InterfaceMethod scala/actors/Reactor.scala$actors$Reactor$_setter_$waitingForNone_$eq:(Lscala/Function1;)V
	aload_0
	aload_0
	invokeinterface	InterfaceMethod scala/actors/Reactor.waitingForNone:()Lscala/Function1;
	invokeinterface	InterfaceMethod scala/actors/Reactor.waitingFor_$eq:(Lscala/Function1;)V
	aload_0
	new	class scala/actors/Reactor$$anonfun$6
	dup
	aload_0
	invokespecial	Method scala/actors/Reactor$$anonfun$6."<init>":(Lscala/actors/Reactor;)V
	invokeinterface	InterfaceMethod scala/actors/Reactor.kill_$eq:(Lscala/Function0;)V
	return
  Labels:
  LocalVariableTable: 
   Start  Length  Slot  Name   Signature
   0      76      0    $this       Lscala/actors/Reactor;


public static void terminated(scala.actors.Reactor);
  Signature: (Lscala/actors/Reactor;)V
  Code:
   Stack=2, Locals=1, Args_size=1
	aload_0
	invokeinterface	InterfaceMethod scala/actors/Reactor.scheduler:()Lscala/actors/IScheduler;
	aload_0
	invokeinterface	InterfaceMethod scala/actors/IScheduler.terminated:(Lscala/actors/Reactor;)V
	return
  Labels:
  LocalVariableTable: 
   Start  Length  Slot  Name   Signature
   0      13      0    $this       Lscala/actors/Reactor;


public static scala.runtime.Nothing$ exit(scala.actors.Reactor);
  Signature: (Lscala/actors/Reactor;)Lscala/runtime/Nothing$;
  Code:
   Stack=1, Locals=1, Args_size=1
	aload_0
	invokeinterface	InterfaceMethod scala/actors/Reactor.terminated:()V
	getstatic	Field scala/actors/Actor$.MODULE$:Lscala/actors/Actor$;
	invokevirtual	Method scala/actors/Actor$.suspendException:()Lscala/actors/SuspendActorException;
	athrow
  Labels:
  LocalVariableTable: 
   Start  Length  Slot  Name   Signature
   0      13      0    $this       Lscala/actors/Reactor;


public static void seq(scala.actors.Reactor, scala.Function0, scala.Function0);
  Signature: (Lscala/actors/Reactor;Lscala/Function0;Lscala/Function0;)V
  Code:
   Stack=7, Locals=5, Args_size=3
	getstatic	Field scala/actors/Actor$.MODULE$:Lscala/actors/Actor$;
	aload_0
	invokeinterface	InterfaceMethod scala/actors/Reactor.scheduler:()Lscala/actors/IScheduler;
	invokevirtual	Method scala/actors/Actor$.rawSelf:(Lscala/actors/IScheduler;)Lscala/actors/Reactor;
	astore_3
	aload_3
	invokeinterface	InterfaceMethod scala/actors/Reactor.kill:()Lscala/Function0;
	astore	4
	aload_3
	new	class scala/actors/Reactor$$anonfun$seq$1
	dup
	aload_0
	aload_2
	aload_3
	aload	4
	invokespecial	Method scala/actors/Reactor$$anonfun$seq$1."<init>":(Lscala/actors/Reactor;Lscala/Function0;Lscala/actors/Reactor;Lscala/Function0;)V
	invokeinterface	InterfaceMethod scala/actors/Reactor.kill_$eq:(Lscala/Function0;)V
	aload_1
	invokeinterface	InterfaceMethod scala/Function0.apply:()Ljava/lang/Object;
	pop
	new	class scala/actors/KillActorException
	dup
	invokespecial	Method scala/actors/KillActorException."<init>":()V
	athrow
  Labels:
  LocalVariableTable: 
   Start  Length  Slot  Name   Signature
   0      54      0    $this       Lscala/actors/Reactor;
   0      54      1    first       Lscala/Function0;
   0      54      2    next$1       Lscala/Function0;
   13      41      3    s$1       Lscala/actors/Reactor;
   21      33      4    killNext$1       Lscala/Function0;


public static scala.actors.Reactor start(scala.actors.Reactor);
  Signature: (Lscala/actors/Reactor;)Lscala/actors/Reactor;
  Code:
   Stack=6, Locals=2, Args_size=1
	aload_0
	invokeinterface	InterfaceMethod scala/actors/Reactor.scheduler:()Lscala/actors/IScheduler;
	aload_0
	invokeinterface	InterfaceMethod scala/actors/IScheduler.newActor:(Lscala/actors/Reactor;)V
	new	class scala/actors/ReactorTask
	dup
	aload_0
	new	class scala/actors/Reactor$$anonfun$5
	dup
	aload_0
	invokespecial	Method scala/actors/Reactor$$anonfun$5."<init>":(Lscala/actors/Reactor;)V
	invokespecial	Method scala/actors/ReactorTask."<init>":(Lscala/actors/Reactor;Lscala/Function0;)V
	astore_1
	aload_0
	invokeinterface	InterfaceMethod scala/actors/Reactor.scheduler:()Lscala/actors/IScheduler;
	aload_1
	invokeinterface	InterfaceMethod scala/actors/IScheduler.execute:(Ljava/lang/Runnable;)V
	aload_0
	areturn
  Labels:
  LocalVariableTable: 
   Start  Length  Slot  Name   Signature
   0      43      0    $this       Lscala/actors/Reactor;
   29      13      1    task       Lscala/actors/ReactorTask;


public static void scheduleActor(scala.actors.Reactor, scala.PartialFunction, java.lang.Object);
  Signature: (Lscala/actors/Reactor;Lscala/PartialFunction;Ljava/lang/Object;)V
  Code:
   Stack=5, Locals=5, Args_size=3
	new	class scala/actors/Reactor$$anonfun$4
	dup
	aload_0
	aload_1
	aload_2
	invokespecial	Method scala/actors/Reactor$$anonfun$4."<init>":(Lscala/actors/Reactor;Lscala/PartialFunction;Ljava/lang/Object;)V
	astore_3
	new	class scala/actors/ReactorTask
	dup
	aload_0
	aload_3
	invokespecial	Method scala/actors/ReactorTask."<init>":(Lscala/actors/Reactor;Lscala/Function0;)V
	astore	4
	aload_0
	invokeinterface	InterfaceMethod scala/actors/Reactor.scheduler:()Lscala/actors/IScheduler;
	aload	4
	invokeinterface	InterfaceMethod scala/actors/IScheduler.executeFromActor:(Ljava/lang/Runnable;)V
	return
  Labels:
  LocalVariableTable: 
   Start  Length  Slot  Name   Signature
   0      36      0    $this       Lscala/actors/Reactor;
   0      36      1    handler$2       Lscala/PartialFunction;
   0      36      2    msg$2       Ljava/lang/Object;
   11      24      3    fun       Lscala/Function0;
   22      13      4    task       Lscala/actors/ReactorTask;


public static scala.runtime.Nothing$ react(scala.actors.Reactor, scala.PartialFunction);
  Signature: (Lscala/actors/Reactor;Lscala/PartialFunction;)Lscala/runtime/Nothing$;
  Code:
   Stack=6, Locals=3, Args_size=2
	getstatic	Field scala/actors/Actor$.MODULE$:Lscala/actors/Actor$;
	aload_0
	invokeinterface	InterfaceMethod scala/actors/Reactor.scheduler:()Lscala/actors/IScheduler;
	invokevirtual	Method scala/actors/Actor$.rawSelf:(Lscala/actors/IScheduler;)Lscala/actors/Reactor;
	dup
	ifnonnull	l1 // aload_0
	pop
	aload_0
	ifnull	l2 // iconst_1
	goto	l3 // iconst_0
l1	aload_0
	invokevirtual	Method java/lang/Object.equals:(Ljava/lang/Object;)Z
	ifeq	l3 // iconst_0
l2	iconst_1
	goto	l4 // istore_2
l3	iconst_0
l4	istore_2
	iload_2
	ifne	l5 // aload_0
	new	class java/lang/AssertionError
	dup
	new	class scala/collection/mutable/StringBuilder
	dup
	invokespecial	Method scala/collection/mutable/StringBuilder."<init>":()V
	ldc	String assertion failed: 
	invokevirtual	Method scala/collection/mutable/StringBuilder.append:(Ljava/lang/Object;)Lscala/collection/mutable/StringBuilder;
	ldc	String react on channel belonging to other actor
	invokevirtual	Method scala/collection/mutable/StringBuilder.append:(Ljava/lang/Object;)Lscala/collection/mutable/StringBuilder;
	invokevirtual	Method scala/collection/mutable/StringBuilder.toString:()Ljava/lang/String;
	invokespecial	Method java/lang/AssertionError."<init>":(Ljava/lang/Object;)V
	athrow
l5	aload_0
	dup
	pop
	monitorenter
	aload_0
	aload_0
	invokeinterface	InterfaceMethod scala/actors/Reactor.mailbox:()Lscala/actors/MessageQueue;
	invokeinterface	InterfaceMethod scala/actors/Reactor.drainSendBuffer:(Lscala/actors/MessageQueue;)V
	aload_0
	monitorexit
	aload_0
	aload_1
	invokeinterface	InterfaceMethod scala/actors/Reactor.continuation_$eq:(Lscala/PartialFunction;)V
	aload_0
	aload_0
	invokeinterface	InterfaceMethod scala/actors/Reactor.mailbox:()Lscala/actors/MessageQueue;
	new	class scala/actors/Reactor$$anonfun$react$2
	dup
	aload_0
	aload_1
	invokespecial	Method scala/actors/Reactor$$anonfun$react$2."<init>":(Lscala/actors/Reactor;Lscala/PartialFunction;)V
	iconst_0
	invokeinterface	InterfaceMethod scala/actors/Reactor.searchMailbox:(Lscala/actors/MessageQueue;Lscala/Function1;Z)V
	getstatic	Field scala/actors/Actor$.MODULE$:Lscala/actors/Actor$;
	invokevirtual	Method scala/actors/Actor$.suspendException:()Lscala/actors/SuspendActorException;
	athrow
	aload_0
	monitorexit
	athrow
  Labels:
   	l1 = 24 // aload_0
   	l2 = 31 // iconst_1
   	l3 = 35 // iconst_0
   	l4 = 36 // istore_2
   	l5 = 69 // aload_0
  Exception table:
   from   to  target type
    73    87   123   any
  LocalVariableTable: 
   Start  Length  Slot  Name   Signature
   0      126      0    $this       Lscala/actors/Reactor;
   0      126      1    f$1       Lscala/PartialFunction;


public static void searchMailbox(scala.actors.Reactor, scala.actors.MessageQueue, scala.Function1, boolean);
  Signature: (Lscala/actors/Reactor;Lscala/actors/MessageQueue;Lscala/Function1;Z)V
  Code:
   Stack=5, Locals=7, Args_size=4
	aload_1
	astore	4
	iconst_0
	istore	6
l7	iload	6
	ifeq	l1 // aload
	return
l1	aload	4
	new	class scala/actors/Reactor$$anonfun$3
	dup
	aload_0
	aload_2
	invokespecial	Method scala/actors/Reactor$$anonfun$3."<init>":(Lscala/actors/Reactor;Lscala/Function1;)V
	invokevirtual	Method scala/actors/MessageQueue.extractFirst:(Lscala/Function2;)Lscala/actors/MessageQueueElement;
	astore	5
	aload	4
	aload_0
	invokeinterface	InterfaceMethod scala/actors/Reactor.mailbox:()Lscala/actors/MessageQueue;
	if_acmpeq	l2 // aload
	aload	4
	new	class scala/actors/Reactor$$anonfun$searchMailbox$1
	dup
	aload_0
	invokespecial	Method scala/actors/Reactor$$anonfun$searchMailbox$1."<init>":(Lscala/actors/Reactor;)V
	invokevirtual	Method scala/actors/MessageQueue.foreach:(Lscala/Function2;)V
l2	aload	5
	ifnonnull	l3 // aload_0
	aload_0
	dup
	pop
	monitorenter
	aload_0
	invokeinterface	InterfaceMethod scala/actors/Reactor.sendBuffer:()Lscala/collection/mutable/Queue;
	invokevirtual	Method scala/collection/mutable/Queue.isEmpty:()Z
	ifeq	l4 // new
	aload_0
	aload_2
	invokeinterface	InterfaceMethod scala/actors/Reactor.waitingFor_$eq:(Lscala/Function1;)V
	iconst_1
	istore	6
	goto	l5 // aload_0
l4	new	class scala/actors/MessageQueue
	dup
	ldc	String Temp
	invokespecial	Method scala/actors/MessageQueue."<init>":(Ljava/lang/String;)V
	astore	4
	aload_0
	aload	4
	invokeinterface	InterfaceMethod scala/actors/Reactor.drainSendBuffer:(Lscala/actors/MessageQueue;)V
l5	aload_0
	monitorexit
	goto	l6 // goto
l3	aload_0
	new	class scala/Tuple2
	dup
	aload	5
	invokevirtual	Method scala/actors/MessageQueueElement.msg:()Ljava/lang/Object;
	aload	5
	invokevirtual	Method scala/actors/MessageQueueElement.session:()Lscala/actors/OutputChannel;
	invokespecial	Method scala/Tuple2."<init>":(Ljava/lang/Object;Ljava/lang/Object;)V
	iload_3
	invokeinterface	InterfaceMethod scala/actors/Reactor.resumeReceiver:(Lscala/Tuple2;Z)V
	iconst_1
	istore	6
l6	goto	l7 // iload
	aload_0
	monitorexit
	athrow
  Labels:
   	l7 = 6 // iload
   	l1 = 12 // aload
   	l2 = 52 // aload
   	l4 = 86 // new
   	l5 = 105 // aload_0
   	l3 = 110 // aload_0
   	l6 = 137 // goto
  Exception table:
   from   to  target type
    61   110   140   any
  LocalVariableTable: 
   Start  Length  Slot  Name   Signature
   0      143      0    $this       Lscala/actors/Reactor;
   0      143      1    startMbox       Lscala/actors/MessageQueue;
   0      143      2    handlesMessage$1       Lscala/Function1;
   0      143      3    resumeOnSameThread       Z
   3      140      4    tmpMbox       Lscala/actors/MessageQueue;
   28      109      5    qel       Lscala/actors/MessageQueueElement;
   140      3      5    qel       Lscala/actors/MessageQueueElement;
   6      137      6    done       Z


public static void drainSendBuffer(scala.actors.Reactor, scala.actors.MessageQueue);
  Signature: (Lscala/actors/Reactor;Lscala/actors/MessageQueue;)V
  Code:
   Stack=3, Locals=3, Args_size=2
l2	aload_0
	invokeinterface	InterfaceMethod scala/actors/Reactor.sendBuffer:()Lscala/collection/mutable/Queue;
	invokevirtual	Method scala/collection/mutable/Queue.isEmpty:()Z
	ifeq	l1 // aload_0
	return
l1	aload_0
	invokeinterface	InterfaceMethod scala/actors/Reactor.sendBuffer:()Lscala/collection/mutable/Queue;
	invokevirtual	Method scala/collection/mutable/Queue.dequeue:()Ljava/lang/Object;
	checkcast	class scala/Tuple2
	astore_2
	aload_1
	aload_2
	invokevirtual	Method scala/Tuple2._1:()Ljava/lang/Object;
	aload_2
	invokevirtual	Method scala/Tuple2._2:()Ljava/lang/Object;
	checkcast	class scala/actors/OutputChannel
	invokevirtual	Method scala/actors/MessageQueue.append:(Ljava/lang/Object;Lscala/actors/OutputChannel;)V
	goto	l2 // aload_0
  Labels:
   	l2 = 0 // aload_0
   	l1 = 13 // aload_0
  LocalVariableTable: 
   Start  Length  Slot  Name   Signature
   0      44      0    $this       Lscala/actors/Reactor;
   0      44      1    mbox       Lscala/actors/MessageQueue;
   26      15      2    item       Lscala/Tuple2;


public static scala.actors.Actor receiver(scala.actors.Reactor);
  Signature: (Lscala/actors/Reactor;)Lscala/actors/Actor;
  Code:
   Stack=1, Locals=1, Args_size=1
	aload_0
	checkcast	class scala/actors/Actor
	areturn
  Labels:
  LocalVariableTable: 
   Start  Length  Slot  Name   Signature
   0      5      0    $this       Lscala/actors/Reactor;


public static void forward(scala.actors.Reactor, java.lang.Object);
  Signature: (Lscala/actors/Reactor;Ljava/lang/Object;)V
  Code:
   Stack=3, Locals=2, Args_size=2
	aload_0
	aload_1
	aconst_null
	invokeinterface	InterfaceMethod scala/actors/Reactor.send:(Ljava/lang/Object;Lscala/actors/OutputChannel;)V
	return
  Labels:
  LocalVariableTable: 
   Start  Length  Slot  Name   Signature
   0      9      0    $this       Lscala/actors/Reactor;
   0      9      1    msg       Ljava/lang/Object;


public static void $bang(scala.actors.Reactor, java.lang.Object);
  Signature: (Lscala/actors/Reactor;Ljava/lang/Object;)V
  Code:
   Stack=3, Locals=2, Args_size=2
	aload_0
	aload_1
	aconst_null
	invokeinterface	InterfaceMethod scala/actors/Reactor.send:(Ljava/lang/Object;Lscala/actors/OutputChannel;)V
	return
  Labels:
  LocalVariableTable: 
   Start  Length  Slot  Name   Signature
   0      9      0    $this       Lscala/actors/Reactor;
   0      9      1    msg       Ljava/lang/Object;


public static void resumeReceiver(scala.actors.Reactor, scala.Tuple2, boolean);
  Signature: (Lscala/actors/Reactor;Lscala/Tuple2;Z)V
  Code:
   Stack=3, Locals=3, Args_size=3
	iload_2
	ifeq	l1 // aload_0
	aload_0
	invokeinterface	InterfaceMethod scala/actors/Reactor.continuation:()Lscala/PartialFunction;
	aload_1
	invokevirtual	Method scala/Tuple2._1:()Ljava/lang/Object;
	invokeinterface	InterfaceMethod scala/Function1.apply:(Ljava/lang/Object;)Ljava/lang/Object;
	pop
	goto	l2 // return
l1	aload_0
	aload_0
	invokeinterface	InterfaceMethod scala/actors/Reactor.continuation:()Lscala/PartialFunction;
	aload_1
	invokevirtual	Method scala/Tuple2._1:()Ljava/lang/Object;
	invokeinterface	InterfaceMethod scala/actors/Reactor.scheduleActor:(Lscala/PartialFunction;Ljava/lang/Object;)V
l2	return
  Labels:
   	l1 = 23 // aload_0
   	l2 = 39 // return
  LocalVariableTable: 
   Start  Length  Slot  Name   Signature
   0      40      0    $this       Lscala/actors/Reactor;
   0      40      1    item       Lscala/Tuple2;
   0      40      2    onSameThread       Z


public static java.lang.Runnable makeReaction(scala.actors.Reactor, scala.Function0);
  Signature: (Lscala/actors/Reactor;Lscala/Function0;)Ljava/lang/Runnable;
  Code:
   Stack=4, Locals=2, Args_size=2
	new	class scala/actors/ReactorTask
	dup
	aload_0
	aload_1
	invokespecial	Method scala/actors/ReactorTask."<init>":(Lscala/actors/Reactor;Lscala/Function0;)V
	areturn
  Labels:
  LocalVariableTable: 
   Start  Length  Slot  Name   Signature
   0      10      0    $this       Lscala/actors/Reactor;
   0      10      1    fun       Lscala/Function0;


public static scala.Function0 startSearch(scala.actors.Reactor, java.lang.Object, scala.actors.OutputChannel, scala.Function1);
  Signature: (Lscala/actors/Reactor;Ljava/lang/Object;Lscala/actors/OutputChannel;Lscala/Function1;)Lscala/Function0;
  Code:
   Stack=6, Locals=4, Args_size=4
	new	class scala/actors/Reactor$$anonfun$startSearch$1
	dup
	aload_0
	aload_1
	aload_2
	aload_3
	invokespecial	Method scala/actors/Reactor$$anonfun$startSearch$1."<init>":(Lscala/actors/Reactor;Ljava/lang/Object;Lscala/actors/OutputChannel;Lscala/Function1;)V
	areturn
  Labels:
  LocalVariableTable: 
   Start  Length  Slot  Name   Signature
   0      12      0    $this       Lscala/actors/Reactor;
   0      12      1    msg$1       Ljava/lang/Object;
   0      12      2    replyTo$1       Lscala/actors/OutputChannel;
   0      12      3    handler$1       Lscala/Function1;


public static void send(scala.actors.Reactor, java.lang.Object, scala.actors.OutputChannel);
  Signature: (Lscala/actors/Reactor;Ljava/lang/Object;Lscala/actors/OutputChannel;)V
  Code:
   Stack=9, Locals=5, Args_size=3
	aload_0
	dup
	pop
	monitorenter
	aload_0
	invokeinterface	InterfaceMethod scala/actors/Reactor.waitingFor:()Lscala/Function1;
	aload_0
	invokeinterface	InterfaceMethod scala/actors/Reactor.waitingForNone:()Lscala/Function1;
	if_acmpeq	l1 // aload_0
	aload_0
	invokeinterface	InterfaceMethod scala/actors/Reactor.waitingFor:()Lscala/Function1;
	astore_3
	aload_0
	aload_0
	invokeinterface	InterfaceMethod scala/actors/Reactor.waitingForNone:()Lscala/Function1;
	invokeinterface	InterfaceMethod scala/actors/Reactor.waitingFor_$eq:(Lscala/Function1;)V
	aload_0
	aload_1
	aload_2
	aload_3
	invokeinterface	InterfaceMethod scala/actors/Reactor.startSearch:(Ljava/lang/Object;Lscala/actors/OutputChannel;Lscala/Function1;)Lscala/Function0;
	goto	l2 // aload_0
l1	aload_0
	invokeinterface	InterfaceMethod scala/actors/Reactor.sendBuffer:()Lscala/collection/mutable/Queue;
	getstatic	Field scala/Predef$.MODULE$:Lscala/Predef$;
	iconst_1
	anewarray	class scala/Tuple2
	dup
	iconst_0
	new	class scala/Tuple2
	dup
	aload_1
	aload_2
	invokespecial	Method scala/Tuple2."<init>":(Ljava/lang/Object;Ljava/lang/Object;)V
	aastore
	checkcast	class "[Ljava/lang/Object;"
	invokevirtual	Method scala/Predef$.wrapRefArray:([Ljava/lang/Object;)Lscala/collection/mutable/WrappedArray;
	invokevirtual	Method scala/collection/mutable/Queue.enqueue:(Lscala/collection/Seq;)V
	new	class scala/actors/Reactor$$anonfun$2
	dup
	aload_0
	invokespecial	Method scala/actors/Reactor$$anonfun$2."<init>":(Lscala/actors/Reactor;)V
l2	aload_0
	monitorexit
	checkcast	class scala/Function0
	astore	4
	aload	4
	invokeinterface	InterfaceMethod scala/Function0.apply:()Ljava/lang/Object;
	pop
	return
	aload_0
	monitorexit
	athrow
  Labels:
   	l1 = 50 // aload_0
   	l2 = 92 // aload_0
  Exception table:
   from   to  target type
     4    94   108   any
  LocalVariableTable: 
   Start  Length  Slot  Name   Signature
   0      111      0    $this       Lscala/actors/Reactor;
   0      111      1    msg       Ljava/lang/Object;
   0      111      2    replyTo       Lscala/actors/OutputChannel;
   26      21      3    savedWaitingFor       Lscala/Function1;
   99      8      4    todo       Lscala/Function0;


public static int mailboxSize(scala.actors.Reactor);
  Signature: (Lscala/actors/Reactor;)I
  Code:
   Stack=1, Locals=1, Args_size=1
	aload_0
	invokeinterface	InterfaceMethod scala/actors/Reactor.mailbox:()Lscala/actors/MessageQueue;
	invokevirtual	Method scala/actors/MessageQueue.size:()I
	ireturn
  Labels:
  LocalVariableTable: 
   Start  Length  Slot  Name   Signature
   0      10      0    $this       Lscala/actors/Reactor;


public static scala.actors.IScheduler scheduler(scala.actors.Reactor);
  Signature: (Lscala/actors/Reactor;)Lscala/actors/IScheduler;
  Code:
   Stack=1, Locals=1, Args_size=1
	getstatic	Field scala/actors/Reactor$.MODULE$:Lscala/actors/Reactor$;
	invokevirtual	Method scala/actors/Reactor$.scheduler:()Ljava/lang/Object;
	checkcast	class scala/actors/IScheduler
	areturn
  Labels:
  LocalVariableTable: 
   Start  Length  Slot  Name   Signature
   0      10      0    $this       Lscala/actors/Reactor;


public static scala.PartialFunction exceptionHandler(scala.actors.Reactor);
  Signature: (Lscala/actors/Reactor;)Lscala/PartialFunction;
  Code:
   Stack=3, Locals=1, Args_size=1
	getstatic	Field scala/Predef$.MODULE$:Lscala/Predef$;
	invokevirtual	Method scala/Predef$.Map:()Lscala/collection/immutable/Map$;
	getstatic	Field scala/Predef$.MODULE$:Lscala/Predef$;
	iconst_0
	anewarray	class scala/Tuple2
	checkcast	class "[Ljava/lang/Object;"
	invokevirtual	Method scala/Predef$.wrapRefArray:([Ljava/lang/Object;)Lscala/collection/mutable/WrappedArray;
	invokevirtual	Method scala/collection/immutable/Map$.apply:(Lscala/collection/Seq;)Lscala/collection/Map;
	areturn
  Labels:
  LocalVariableTable: 
   Start  Length  Slot  Name   Signature
   0      23      0    $this       Lscala/actors/Reactor;


}

