Compiled from "Reactor.scala"
public final class scala.actors.Reactor$ extends java.lang.Object implements scala.ScalaObject
  SourceFile: "Reactor.scala"
  Scala: length = 0x
   
  InnerClass: 
   public final #31= #23 of #30; //$anon$1=class scala/actors/Reactor$$anon$1 of class scala/actors/Reactor
   public final #34= #33 of #30; //$anonfun$6=class scala/actors/Reactor$$anonfun$6 of class scala/actors/Reactor
   public final #37= #36 of #30; //$anonfun$5=class scala/actors/Reactor$$anonfun$5 of class scala/actors/Reactor
   public final #40= #39 of #30; //$anonfun$4=class scala/actors/Reactor$$anonfun$4 of class scala/actors/Reactor
   public final #43= #42 of #30; //$anonfun$3=class scala/actors/Reactor$$anonfun$3 of class scala/actors/Reactor
   public final #46= #45 of #30; //$anonfun$2=class scala/actors/Reactor$$anonfun$2 of class scala/actors/Reactor
   public final #49= #48 of #30; //$anonfun$1=class scala/actors/Reactor$$anonfun$1 of class scala/actors/Reactor
   public final #52= #51 of #30; //$anonfun$seq$1=class scala/actors/Reactor$$anonfun$seq$1 of class scala/actors/Reactor
   public final #55= #54 of #30; //$anonfun$react$2=class scala/actors/Reactor$$anonfun$react$2 of class scala/actors/Reactor
   public final #58= #57 of #30; //$anonfun$react$1=class scala/actors/Reactor$$anonfun$react$1 of class scala/actors/Reactor
   public final #61= #60 of #30; //$anonfun$startSearch$1=class scala/actors/Reactor$$anonfun$startSearch$1 of class scala/actors/Reactor
   public final #64= #63 of #30; //$anonfun$searchMailbox$1=class scala/actors/Reactor$$anonfun$searchMailbox$1 of class scala/actors/Reactor
  minor version: 0
  major version: 49
  Constant pool:
const #1 = Asciz	SourceFile;
const #2 = Asciz	Reactor.scala;
const #3 = Asciz	Scala;
const #4 = Asciz	MODULE$;
const #5 = Asciz	Lscala/actors/Reactor$;;
const #6 = Asciz	<clinit>;
const #7 = Asciz	()V;
const #8 = Asciz	Code;
const #9 = Asciz	scala/actors/Reactor$;
const #10 = class	#9;	//  scala/actors/Reactor$
const #11 = Asciz	<init>;
const #12 = NameAndType	#11:#7;//  "<init>":()V
const #13 = Method	#10.#12;	//  scala/actors/Reactor$."<init>":()V
const #14 = Asciz	scheduler;
const #15 = Asciz	Ljava/lang/Object;;
const #16 = Asciz	LineNumberTable;
const #17 = Asciz	java/lang/Object;
const #18 = class	#17;	//  java/lang/Object
const #19 = Method	#18.#12;	//  java/lang/Object."<init>":()V
const #20 = NameAndType	#4:#5;//  MODULE$:Lscala/actors/Reactor$;
const #21 = Field	#10.#20;	//  scala/actors/Reactor$.MODULE$:Lscala/actors/Reactor$;
const #22 = Asciz	scala/actors/Reactor$$anon$1;
const #23 = class	#22;	//  scala/actors/Reactor$$anon$1
const #24 = Method	#23.#12;	//  scala/actors/Reactor$$anon$1."<init>":()V
const #25 = NameAndType	#14:#15;//  scheduler:Ljava/lang/Object;
const #26 = Field	#10.#25;	//  scala/actors/Reactor$.scheduler:Ljava/lang/Object;
const #27 = Asciz	()Ljava/lang/Object;;
const #28 = Asciz	InnerClasses;
const #29 = Asciz	scala/actors/Reactor;
const #30 = class	#29;	//  scala/actors/Reactor
const #31 = Asciz	$anon$1;
const #32 = Asciz	scala/actors/Reactor$$anonfun$6;
const #33 = class	#32;	//  scala/actors/Reactor$$anonfun$6
const #34 = Asciz	$anonfun$6;
const #35 = Asciz	scala/actors/Reactor$$anonfun$5;
const #36 = class	#35;	//  scala/actors/Reactor$$anonfun$5
const #37 = Asciz	$anonfun$5;
const #38 = Asciz	scala/actors/Reactor$$anonfun$4;
const #39 = class	#38;	//  scala/actors/Reactor$$anonfun$4
const #40 = Asciz	$anonfun$4;
const #41 = Asciz	scala/actors/Reactor$$anonfun$3;
const #42 = class	#41;	//  scala/actors/Reactor$$anonfun$3
const #43 = Asciz	$anonfun$3;
const #44 = Asciz	scala/actors/Reactor$$anonfun$2;
const #45 = class	#44;	//  scala/actors/Reactor$$anonfun$2
const #46 = Asciz	$anonfun$2;
const #47 = Asciz	scala/actors/Reactor$$anonfun$1;
const #48 = class	#47;	//  scala/actors/Reactor$$anonfun$1
const #49 = Asciz	$anonfun$1;
const #50 = Asciz	scala/actors/Reactor$$anonfun$seq$1;
const #51 = class	#50;	//  scala/actors/Reactor$$anonfun$seq$1
const #52 = Asciz	$anonfun$seq$1;
const #53 = Asciz	scala/actors/Reactor$$anonfun$react$2;
const #54 = class	#53;	//  scala/actors/Reactor$$anonfun$react$2
const #55 = Asciz	$anonfun$react$2;
const #56 = Asciz	scala/actors/Reactor$$anonfun$react$1;
const #57 = class	#56;	//  scala/actors/Reactor$$anonfun$react$1
const #58 = Asciz	$anonfun$react$1;
const #59 = Asciz	scala/actors/Reactor$$anonfun$startSearch$1;
const #60 = class	#59;	//  scala/actors/Reactor$$anonfun$startSearch$1
const #61 = Asciz	$anonfun$startSearch$1;
const #62 = Asciz	scala/actors/Reactor$$anonfun$searchMailbox$1;
const #63 = class	#62;	//  scala/actors/Reactor$$anonfun$searchMailbox$1
const #64 = Asciz	$anonfun$searchMailbox$1;
const #65 = Asciz	scala/ScalaObject;
const #66 = class	#65;	//  scala/ScalaObject

{
public static final scala.actors.Reactor$ MODULE$;

public static {};
  Code:
   Stack=1, Locals=0, Args_size=0
   0:	new	#10; //class scala/actors/Reactor$
   3:	invokespecial	#13; //Method "<init>":()V
   6:	return

public java.lang.Object scheduler();
  Code:
   Stack=1, Locals=1, Args_size=1
   0:	aload_0
   1:	getfield	#26; //Field scheduler:Ljava/lang/Object;
   4:	areturn
  LineNumberTable: 
   line 17: 0


}

