Compiled from "Reactor.scala"
public final class scala.actors.Reactor$$anon$3 extends java.lang.Object implements scala.actors.Actor$Body
  SourceFile: "Reactor.scala"
  Signature: length = 0x2
   00 28 
  Scala: length = 0x
   
  InnerClass: 
   public abstract Body=class scala/actors/Actor$Body of class scala/actors/Actor
   public final $anon$3=class scala/actors/Reactor$$anon$3 of class scala/actors/Reactor
  minor version: 0
  major version: 49
  Constant pool:
Asciz	SourceFile;
Asciz	Reactor.scala;
Asciz	body$1;
Asciz	Lscala/Function0;;
Asciz	$outer;
Asciz	Lscala/actors/Reactor;;
Asciz	andThen;
Asciz	(Lscala/Function0;)V;
Asciz	Code;
Asciz	LineNumberTable;
Asciz	scala/actors/Reactor$$anon$3;
class	scala/actors/Reactor$$anon$3
NameAndType	$outer:Lscala/actors/Reactor;
Field	scala/actors/Reactor$$anon$3.$outer:Lscala/actors/Reactor;
NameAndType	body$1:Lscala/Function0;
Field	scala/actors/Reactor$$anon$3.body$1:Lscala/Function0;
Asciz	scala/actors/Reactor;
class	scala/actors/Reactor
Asciz	seq;
Asciz	(Lscala/Function0;Lscala/Function0;)V;
NameAndType	seq:(Lscala/Function0;Lscala/Function0;)V
InterfaceMethod	scala/actors/Reactor.seq:(Lscala/Function0;Lscala/Function0;)V
Asciz	this;
Asciz	Lscala/actors/Reactor$$anon$3;;
Asciz	other;
Asciz	LocalVariableTable;
Asciz	<B:Ljava/lang/Object;>(Lscala/Function0<TB;>;)V;
Asciz	Signature;
Asciz	<init>;
Asciz	(Lscala/actors/Reactor;Lscala/Function0;)V;
Asciz	java/lang/NullPointerException;
class	java/lang/NullPointerException
Asciz	()V;
NameAndType	"<init>":()V
Method	java/lang/NullPointerException."<init>":()V
Asciz	java/lang/Object;
class	java/lang/Object
Method	java/lang/Object."<init>":()V
Asciz	(Lscala/actors/Reactor<TMsg;>;)V;
Asciz	Ljava/lang/Object;Lscala/actors/Actor$Body<TA;>;;
Asciz	Scala;
Asciz	InnerClasses;
Asciz	scala/actors/Actor$Body;
class	scala/actors/Actor$Body
Asciz	scala/actors/Actor;
class	scala/actors/Actor
Asciz	Body;
Asciz	$anon$3;

{
private final scala.Function0 body$1;
  Signature: Lscala/Function0;

private final scala.actors.Reactor $outer;
  Signature: Lscala/actors/Reactor;

public void andThen(scala.Function0);
  Signature: (Lscala/Function0;)V
  Code:
   Stack=3, Locals=2, Args_size=2
	aload_0
	getfield	Field $outer:Lscala/actors/Reactor;
	aload_0
	getfield	Field body$1:Lscala/Function0;
	aload_1
	invokeinterface	InterfaceMethod scala/actors/Reactor.seq:(Lscala/Function0;Lscala/Function0;)V
	return
  Labels:
  LocalVariableTable: 
   Start  Length  Slot  Name   Signature
   0      15      0    this       Lscala/actors/Reactor$$anon$3;
   0      15      1    other       Lscala/Function0;

  Signature: length = 0x2
   00 1B 

public scala.actors.Reactor$$anon$3(scala.actors.Reactor, scala.Function0);
  Signature: (Lscala/actors/Reactor;Lscala/Function0;)V
  Code:
   Stack=2, Locals=3, Args_size=3
	aload_1
	ifnonnull	l1 // aload_0
	new	class java/lang/NullPointerException
	dup
	invokespecial	Method java/lang/NullPointerException."<init>":()V
	athrow
l1	aload_0
	aload_1
	putfield	Field $outer:Lscala/actors/Reactor;
	aload_0
	aload_2
	putfield	Field body$1:Lscala/Function0;
	aload_0
	invokespecial	Method java/lang/Object."<init>":()V
	return
  Labels:
   	l1 = 12 // aload_0
  LocalVariableTable: 
   Start  Length  Slot  Name   Signature
   0      27      0    this       Lscala/actors/Reactor$$anon$3;
   0      27      1    $outer       Lscala/actors/Reactor;

  Signature: length = 0x2
   00 27 

}

