Compiled from "Reactor.scala"
public final class scala.actors.Reactor$$anon$2 extends java.lang.Object implements scala.actors.scheduler.DelegatingScheduler
  SourceFile: "Reactor.scala"
  Scala: length = 0x
   
  InnerClass: 
   public final $anon$2=class scala/actors/Reactor$$anon$2 of class scala/actors/Reactor
   public CallerRunsPolicy=class java/util/concurrent/ThreadPoolExecutor$CallerRunsPolicy of class java/util/concurrent/ThreadPoolExecutor
  minor version: 0
  major version: 49
  Constant pool:
Asciz	SourceFile;
Asciz	Reactor.scala;
Asciz	sched;
Asciz	Lscala/actors/IScheduler;;
Asciz	()Lscala/actors/IScheduler;;
Asciz	Code;
Asciz	LineNumberTable;
Asciz	scala/actors/Reactor$$anon$2;
class	scala/actors/Reactor$$anon$2
NameAndType	sched:Lscala/actors/IScheduler;
Field	scala/actors/Reactor$$anon$2.sched:Lscala/actors/IScheduler;
Asciz	sched_$eq;
Asciz	(Lscala/actors/IScheduler;)V;
Asciz	impl;
Asciz	scala/actors/scheduler/DelegatingScheduler$class;
class	scala/actors/scheduler/DelegatingScheduler$class
Asciz	(Lscala/actors/scheduler/DelegatingScheduler;)Lscala/actors/IScheduler;;
NameAndType	impl:(Lscala/actors/scheduler/DelegatingScheduler;)Lscala/actors/IScheduler;
Method	scala/actors/scheduler/DelegatingScheduler$class.impl:(Lscala/actors/scheduler/DelegatingScheduler;)Lscala/actors/IScheduler;
Asciz	impl_$eq;
Asciz	(Lscala/actors/scheduler/DelegatingScheduler;Lscala/actors/IScheduler;)V;
NameAndType	impl_$eq:(Lscala/actors/scheduler/DelegatingScheduler;Lscala/actors/IScheduler;)V
Method	scala/actors/scheduler/DelegatingScheduler$class.impl_$eq:(Lscala/actors/scheduler/DelegatingScheduler;Lscala/actors/IScheduler;)V
Asciz	this;
Asciz	Lscala/actors/Reactor$$anon$2;;
Asciz	scheduler;
Asciz	LocalVariableTable;
Asciz	isActive;
Asciz	()Z;
Asciz	(Lscala/actors/scheduler/DelegatingScheduler;)Z;
NameAndType	isActive:(Lscala/actors/scheduler/DelegatingScheduler;)Z
Method	scala/actors/scheduler/DelegatingScheduler$class.isActive:(Lscala/actors/scheduler/DelegatingScheduler;)Z
Asciz	execute;
Asciz	(Lscala/Function0;)V;
Asciz	(Lscala/actors/scheduler/DelegatingScheduler;Lscala/Function0;)V;
NameAndType	execute:(Lscala/actors/scheduler/DelegatingScheduler;Lscala/Function0;)V
Method	scala/actors/scheduler/DelegatingScheduler$class.execute:(Lscala/actors/scheduler/DelegatingScheduler;Lscala/Function0;)V
Asciz	fun;
Asciz	Lscala/Function0;;
Asciz	(Ljava/lang/Runnable;)V;
Asciz	(Lscala/actors/scheduler/DelegatingScheduler;Ljava/lang/Runnable;)V;
NameAndType	execute:(Lscala/actors/scheduler/DelegatingScheduler;Ljava/lang/Runnable;)V
Method	scala/actors/scheduler/DelegatingScheduler$class.execute:(Lscala/actors/scheduler/DelegatingScheduler;Ljava/lang/Runnable;)V
Asciz	task;
Asciz	Ljava/lang/Runnable;;
Asciz	executeFromActor;
NameAndType	executeFromActor:(Lscala/actors/scheduler/DelegatingScheduler;Ljava/lang/Runnable;)V
Method	scala/actors/scheduler/DelegatingScheduler$class.executeFromActor:(Lscala/actors/scheduler/DelegatingScheduler;Ljava/lang/Runnable;)V
Asciz	shutdown;
Asciz	()V;
Asciz	(Lscala/actors/scheduler/DelegatingScheduler;)V;
NameAndType	shutdown:(Lscala/actors/scheduler/DelegatingScheduler;)V
Method	scala/actors/scheduler/DelegatingScheduler$class.shutdown:(Lscala/actors/scheduler/DelegatingScheduler;)V
Asciz	newActor;
Asciz	(Lscala/actors/Reactor;)V;
Asciz	(Lscala/actors/scheduler/DelegatingScheduler;Lscala/actors/Reactor;)V;
NameAndType	newActor:(Lscala/actors/scheduler/DelegatingScheduler;Lscala/actors/Reactor;)V
Method	scala/actors/scheduler/DelegatingScheduler$class.newActor:(Lscala/actors/scheduler/DelegatingScheduler;Lscala/actors/Reactor;)V
Asciz	actor;
Asciz	Lscala/actors/Reactor;;
Asciz	terminated;
NameAndType	terminated:(Lscala/actors/scheduler/DelegatingScheduler;Lscala/actors/Reactor;)V
Method	scala/actors/scheduler/DelegatingScheduler$class.terminated:(Lscala/actors/scheduler/DelegatingScheduler;Lscala/actors/Reactor;)V
Asciz	onTerminate;
Asciz	(Lscala/actors/Reactor;Lscala/Function0;)V;
Asciz	(Lscala/actors/scheduler/DelegatingScheduler;Lscala/actors/Reactor;Lscala/Function0;)V;
NameAndType	onTerminate:(Lscala/actors/scheduler/DelegatingScheduler;Lscala/actors/Reactor;Lscala/Function0;)V
Method	scala/actors/scheduler/DelegatingScheduler$class.onTerminate:(Lscala/actors/scheduler/DelegatingScheduler;Lscala/actors/Reactor;Lscala/Function0;)V
Asciz	f;
Asciz	managedBlock;
Asciz	(Lscala/concurrent/ManagedBlocker;)V;
Asciz	(Lscala/actors/scheduler/DelegatingScheduler;Lscala/concurrent/ManagedBlocker;)V;
NameAndType	managedBlock:(Lscala/actors/scheduler/DelegatingScheduler;Lscala/concurrent/ManagedBlocker;)V
Method	scala/actors/scheduler/DelegatingScheduler$class.managedBlock:(Lscala/actors/scheduler/DelegatingScheduler;Lscala/concurrent/ManagedBlocker;)V
Asciz	blocker;
Asciz	Lscala/concurrent/ManagedBlocker;;
Asciz	tick;
Asciz	(Lscala/actors/Actor;)V;
Asciz	scala/actors/IScheduler$class;
class	scala/actors/IScheduler$class
Asciz	(Lscala/actors/IScheduler;Lscala/actors/Actor;)V;
NameAndType	tick:(Lscala/actors/IScheduler;Lscala/actors/Actor;)V
Method	scala/actors/IScheduler$class.tick:(Lscala/actors/IScheduler;Lscala/actors/Actor;)V
Asciz	a;
Asciz	Lscala/actors/Actor;;
Asciz	Deprecated;
Asciz	onLockup;
Asciz	(Lscala/actors/IScheduler;Lscala/Function0;)V;
NameAndType	onLockup:(Lscala/actors/IScheduler;Lscala/Function0;)V
Method	scala/actors/IScheduler$class.onLockup:(Lscala/actors/IScheduler;Lscala/Function0;)V
Asciz	handler;
Asciz	(ILscala/Function0;)V;
Asciz	(Lscala/actors/IScheduler;ILscala/Function0;)V;
NameAndType	onLockup:(Lscala/actors/IScheduler;ILscala/Function0;)V
Method	scala/actors/IScheduler$class.onLockup:(Lscala/actors/IScheduler;ILscala/Function0;)V
Asciz	millis;
Asciz	I;
Asciz	printActorDump;
NameAndType	printActorDump:(Lscala/actors/IScheduler;)V
Method	scala/actors/IScheduler$class.printActorDump:(Lscala/actors/IScheduler;)V
Asciz	makeNewScheduler;
Asciz	scala/actors/scheduler/ThreadPoolConfig$;
class	scala/actors/scheduler/ThreadPoolConfig$
Asciz	MODULE$;
Asciz	Lscala/actors/scheduler/ThreadPoolConfig$;;
NameAndType	MODULE$:Lscala/actors/scheduler/ThreadPoolConfig$;
Field	scala/actors/scheduler/ThreadPoolConfig$.MODULE$:Lscala/actors/scheduler/ThreadPoolConfig$;
Asciz	useForkJoin;
NameAndType	useForkJoin:()Z
Method	scala/actors/scheduler/ThreadPoolConfig$.useForkJoin:()Z
Asciz	scala/actors/scheduler/ForkJoinScheduler;
class	scala/actors/scheduler/ForkJoinScheduler
Asciz	corePoolSize;
Asciz	()I;
NameAndType	corePoolSize:()I
Method	scala/actors/scheduler/ThreadPoolConfig$.corePoolSize:()I
Asciz	maxPoolSize;
NameAndType	maxPoolSize:()I
Method	scala/actors/scheduler/ThreadPoolConfig$.maxPoolSize:()I
Asciz	<init>;
Asciz	(IIZZ)V;
NameAndType	"<init>":(IIZZ)V
Method	scala/actors/scheduler/ForkJoinScheduler."<init>":(IIZZ)V
Asciz	start;
NameAndType	start:()V
Method	scala/actors/scheduler/ForkJoinScheduler.start:()V
Asciz	java/util/concurrent/LinkedBlockingQueue;
class	java/util/concurrent/LinkedBlockingQueue
NameAndType	"<init>":()V
Method	java/util/concurrent/LinkedBlockingQueue."<init>":()V
Asciz	scala/actors/scheduler/ExecutorScheduler$;
class	scala/actors/scheduler/ExecutorScheduler$
Asciz	Lscala/actors/scheduler/ExecutorScheduler$;;
NameAndType	MODULE$:Lscala/actors/scheduler/ExecutorScheduler$;
Field	scala/actors/scheduler/ExecutorScheduler$.MODULE$:Lscala/actors/scheduler/ExecutorScheduler$;
Asciz	java/util/concurrent/ThreadPoolExecutor;
class	java/util/concurrent/ThreadPoolExecutor
long	60000l;
Asciz	java/util/concurrent/TimeUnit;
class	java/util/concurrent/TimeUnit
Asciz	MILLISECONDS;
Asciz	Ljava/util/concurrent/TimeUnit;;
NameAndType	MILLISECONDS:Ljava/util/concurrent/TimeUnit;
Field	java/util/concurrent/TimeUnit.MILLISECONDS:Ljava/util/concurrent/TimeUnit;
Asciz	java/util/concurrent/ThreadPoolExecutor$CallerRunsPolicy;
class	java/util/concurrent/ThreadPoolExecutor$CallerRunsPolicy
Method	java/util/concurrent/ThreadPoolExecutor$CallerRunsPolicy."<init>":()V
Asciz	(IIJLjava/util/concurrent/TimeUnit;Ljava/util/concurrent/BlockingQueue;Ljava/util/concurrent/RejectedExecutionHandler;)V;
NameAndType	"<init>":(IIJLjava/util/concurrent/TimeUnit;Ljava/util/concurrent/BlockingQueue;Ljava/util/concurrent/RejectedExecutionHandler;)V
Method	java/util/concurrent/ThreadPoolExecutor."<init>":(IIJLjava/util/concurrent/TimeUnit;Ljava/util/concurrent/BlockingQueue;Ljava/util/concurrent/RejectedExecutionHandler;)V
Asciz	apply;
Asciz	(Ljava/util/concurrent/ExecutorService;)Lscala/actors/scheduler/ExecutorScheduler;;
NameAndType	apply:(Ljava/util/concurrent/ExecutorService;)Lscala/actors/scheduler/ExecutorScheduler;
Method	scala/actors/scheduler/ExecutorScheduler$.apply:(Ljava/util/concurrent/ExecutorService;)Lscala/actors/scheduler/ExecutorScheduler;
Asciz	scala/actors/Debug$;
class	scala/actors/Debug$
Asciz	Lscala/actors/Debug$;;
NameAndType	MODULE$:Lscala/actors/Debug$;
Field	scala/actors/Debug$.MODULE$:Lscala/actors/Debug$;
Asciz	scala/collection/mutable/StringBuilder;
class	scala/collection/mutable/StringBuilder
Method	scala/collection/mutable/StringBuilder."<init>":()V
Asciz	scala/Predef$;
class	scala/Predef$
Asciz	Lscala/Predef$;;
NameAndType	MODULE$:Lscala/Predef$;
Field	scala/Predef$.MODULE$:Lscala/Predef$;
Asciz	any2stringadd;
Asciz	(Ljava/lang/Object;)Lscala/runtime/StringAdd;;
NameAndType	any2stringadd:(Ljava/lang/Object;)Lscala/runtime/StringAdd;
Method	scala/Predef$.any2stringadd:(Ljava/lang/Object;)Lscala/runtime/StringAdd;
Asciz	: starting new ;
String	: starting new 
Asciz	scala/runtime/StringAdd;
class	scala/runtime/StringAdd
Asciz	$plus;
Asciz	(Ljava/lang/String;)Ljava/lang/String;;
NameAndType	$plus:(Ljava/lang/String;)Ljava/lang/String;
Method	scala/runtime/StringAdd.$plus:(Ljava/lang/String;)Ljava/lang/String;
Asciz	append;
Asciz	(Ljava/lang/Object;)Lscala/collection/mutable/StringBuilder;;
NameAndType	append:(Ljava/lang/Object;)Lscala/collection/mutable/StringBuilder;
Method	scala/collection/mutable/StringBuilder.append:(Ljava/lang/Object;)Lscala/collection/mutable/StringBuilder;
Asciz	 [;
String	 [
Asciz	java/lang/Object;
class	java/lang/Object
Asciz	getClass;
Asciz	()Ljava/lang/Class;;
NameAndType	getClass:()Ljava/lang/Class;
Method	java/lang/Object.getClass:()Ljava/lang/Class;
Asciz	];
String	]
Asciz	toString;
Asciz	()Ljava/lang/String;;
NameAndType	toString:()Ljava/lang/String;
Method	scala/collection/mutable/StringBuilder.toString:()Ljava/lang/String;
Asciz	info;
Asciz	(Ljava/lang/String;)V;
NameAndType	info:(Ljava/lang/String;)V
Method	scala/actors/Debug$.info:(Ljava/lang/String;)V
Asciz	workQueue;
Asciz	Ljava/util/concurrent/LinkedBlockingQueue;;
Asciz	s;
Asciz	Lscala/actors/scheduler/ForkJoinScheduler;;
Method	java/lang/Object."<init>":()V
Asciz	$init$;
NameAndType	$init$:(Lscala/actors/IScheduler;)V
Method	scala/actors/IScheduler$class.$init$:(Lscala/actors/IScheduler;)V
NameAndType	$init$:(Lscala/actors/scheduler/DelegatingScheduler;)V
Method	scala/actors/scheduler/DelegatingScheduler$class.$init$:(Lscala/actors/scheduler/DelegatingScheduler;)V
Asciz	Scala;
Asciz	InnerClasses;
Asciz	scala/actors/Reactor;
class	scala/actors/Reactor
Asciz	$anon$2;
Asciz	CallerRunsPolicy;
Asciz	scala/actors/scheduler/DelegatingScheduler;
class	scala/actors/scheduler/DelegatingScheduler

{
private scala.actors.IScheduler sched;
  Signature: Lscala/actors/IScheduler;

public scala.actors.IScheduler sched();
  Signature: ()Lscala/actors/IScheduler;
  Code:
   Stack=1, Locals=1, Args_size=1
	aload_0
	getfield	Field sched:Lscala/actors/IScheduler;
	areturn
  Labels:

public void sched_$eq(scala.actors.IScheduler);
  Signature: (Lscala/actors/IScheduler;)V
  Code:
   Stack=2, Locals=2, Args_size=2
	aload_0
	aload_1
	putfield	Field sched:Lscala/actors/IScheduler;
	return
  Labels:

public final scala.actors.IScheduler impl();
  Signature: ()Lscala/actors/IScheduler;
  Code:
   Stack=1, Locals=1, Args_size=1
	aload_0
	invokestatic	Method scala/actors/scheduler/DelegatingScheduler$class.impl:(Lscala/actors/scheduler/DelegatingScheduler;)Lscala/actors/IScheduler;
	areturn
  Labels:

public final void impl_$eq(scala.actors.IScheduler);
  Signature: (Lscala/actors/IScheduler;)V
  Code:
   Stack=2, Locals=2, Args_size=2
	aload_0
	aload_1
	invokestatic	Method scala/actors/scheduler/DelegatingScheduler$class.impl_$eq:(Lscala/actors/scheduler/DelegatingScheduler;Lscala/actors/IScheduler;)V
	return
  Labels:
  LocalVariableTable: 
   Start  Length  Slot  Name   Signature
   0      6      0    this       Lscala/actors/Reactor$$anon$2;
   0      6      1    scheduler       Lscala/actors/IScheduler;


public boolean isActive();
  Signature: ()Z
  Code:
   Stack=1, Locals=1, Args_size=1
	aload_0
	invokestatic	Method scala/actors/scheduler/DelegatingScheduler$class.isActive:(Lscala/actors/scheduler/DelegatingScheduler;)Z
	ireturn
  Labels:

public void execute(scala.Function0);
  Signature: (Lscala/Function0;)V
  Code:
   Stack=2, Locals=2, Args_size=2
	aload_0
	aload_1
	invokestatic	Method scala/actors/scheduler/DelegatingScheduler$class.execute:(Lscala/actors/scheduler/DelegatingScheduler;Lscala/Function0;)V
	return
  Labels:
  LocalVariableTable: 
   Start  Length  Slot  Name   Signature
   0      6      0    this       Lscala/actors/Reactor$$anon$2;
   0      6      1    fun       Lscala/Function0;


public void execute(java.lang.Runnable);
  Signature: (Ljava/lang/Runnable;)V
  Code:
   Stack=2, Locals=2, Args_size=2
	aload_0
	aload_1
	invokestatic	Method scala/actors/scheduler/DelegatingScheduler$class.execute:(Lscala/actors/scheduler/DelegatingScheduler;Ljava/lang/Runnable;)V
	return
  Labels:
  LocalVariableTable: 
   Start  Length  Slot  Name   Signature
   0      6      0    this       Lscala/actors/Reactor$$anon$2;
   0      6      1    task       Ljava/lang/Runnable;


public void executeFromActor(java.lang.Runnable);
  Signature: (Ljava/lang/Runnable;)V
  Code:
   Stack=2, Locals=2, Args_size=2
	aload_0
	aload_1
	invokestatic	Method scala/actors/scheduler/DelegatingScheduler$class.executeFromActor:(Lscala/actors/scheduler/DelegatingScheduler;Ljava/lang/Runnable;)V
	return
  Labels:
  LocalVariableTable: 
   Start  Length  Slot  Name   Signature
   0      6      0    this       Lscala/actors/Reactor$$anon$2;
   0      6      1    task       Ljava/lang/Runnable;


public void shutdown();
  Signature: ()V
  Code:
   Stack=1, Locals=1, Args_size=1
	aload_0
	invokestatic	Method scala/actors/scheduler/DelegatingScheduler$class.shutdown:(Lscala/actors/scheduler/DelegatingScheduler;)V
	return
  Labels:

public void newActor(scala.actors.Reactor);
  Signature: (Lscala/actors/Reactor;)V
  Code:
   Stack=2, Locals=2, Args_size=2
	aload_0
	aload_1
	invokestatic	Method scala/actors/scheduler/DelegatingScheduler$class.newActor:(Lscala/actors/scheduler/DelegatingScheduler;Lscala/actors/Reactor;)V
	return
  Labels:
  LocalVariableTable: 
   Start  Length  Slot  Name   Signature
   0      6      0    this       Lscala/actors/Reactor$$anon$2;
   0      6      1    actor       Lscala/actors/Reactor;


public void terminated(scala.actors.Reactor);
  Signature: (Lscala/actors/Reactor;)V
  Code:
   Stack=2, Locals=2, Args_size=2
	aload_0
	aload_1
	invokestatic	Method scala/actors/scheduler/DelegatingScheduler$class.terminated:(Lscala/actors/scheduler/DelegatingScheduler;Lscala/actors/Reactor;)V
	return
  Labels:
  LocalVariableTable: 
   Start  Length  Slot  Name   Signature
   0      6      0    this       Lscala/actors/Reactor$$anon$2;
   0      6      1    actor       Lscala/actors/Reactor;


public void onTerminate(scala.actors.Reactor, scala.Function0);
  Signature: (Lscala/actors/Reactor;Lscala/Function0;)V
  Code:
   Stack=3, Locals=3, Args_size=3
	aload_0
	aload_1
	aload_2
	invokestatic	Method scala/actors/scheduler/DelegatingScheduler$class.onTerminate:(Lscala/actors/scheduler/DelegatingScheduler;Lscala/actors/Reactor;Lscala/Function0;)V
	return
  Labels:
  LocalVariableTable: 
   Start  Length  Slot  Name   Signature
   0      7      0    this       Lscala/actors/Reactor$$anon$2;
   0      7      1    actor       Lscala/actors/Reactor;
   0      7      2    f       Lscala/Function0;


public void managedBlock(scala.concurrent.ManagedBlocker);
  Signature: (Lscala/concurrent/ManagedBlocker;)V
  Code:
   Stack=2, Locals=2, Args_size=2
	aload_0
	aload_1
	invokestatic	Method scala/actors/scheduler/DelegatingScheduler$class.managedBlock:(Lscala/actors/scheduler/DelegatingScheduler;Lscala/concurrent/ManagedBlocker;)V
	return
  Labels:
  LocalVariableTable: 
   Start  Length  Slot  Name   Signature
   0      6      0    this       Lscala/actors/Reactor$$anon$2;
   0      6      1    blocker       Lscala/concurrent/ManagedBlocker;


public void tick(scala.actors.Actor);
  Signature: (Lscala/actors/Actor;)V
  Code:
   Stack=2, Locals=2, Args_size=2
	aload_0
	aload_1
	invokestatic	Method scala/actors/IScheduler$class.tick:(Lscala/actors/IScheduler;Lscala/actors/Actor;)V
	return
  Labels:
  LocalVariableTable: 
   Start  Length  Slot  Name   Signature
   0      6      0    this       Lscala/actors/Reactor$$anon$2;
   0      6      1    a       Lscala/actors/Actor;

  Deprecated: true

public void onLockup(scala.Function0);
  Signature: (Lscala/Function0;)V
  Code:
   Stack=2, Locals=2, Args_size=2
	aload_0
	aload_1
	invokestatic	Method scala/actors/IScheduler$class.onLockup:(Lscala/actors/IScheduler;Lscala/Function0;)V
	return
  Labels:
  LocalVariableTable: 
   Start  Length  Slot  Name   Signature
   0      6      0    this       Lscala/actors/Reactor$$anon$2;
   0      6      1    handler       Lscala/Function0;

  Deprecated: true

public void onLockup(int, scala.Function0);
  Signature: (ILscala/Function0;)V
  Code:
   Stack=3, Locals=3, Args_size=3
	aload_0
	iload_1
	aload_2
	invokestatic	Method scala/actors/IScheduler$class.onLockup:(Lscala/actors/IScheduler;ILscala/Function0;)V
	return
  Labels:
  LocalVariableTable: 
   Start  Length  Slot  Name   Signature
   0      7      0    this       Lscala/actors/Reactor$$anon$2;
   0      7      1    millis       I
   0      7      2    handler       Lscala/Function0;

  Deprecated: true

public void printActorDump();
  Signature: ()V
  Code:
   Stack=1, Locals=1, Args_size=1
	aload_0
	invokestatic	Method scala/actors/IScheduler$class.printActorDump:(Lscala/actors/IScheduler;)V
	return
  Labels:
  Deprecated: true

public scala.actors.IScheduler makeNewScheduler();
  Signature: ()Lscala/actors/IScheduler;
  Code:
   Stack=11, Locals=4, Args_size=1
	getstatic	Field scala/actors/scheduler/ThreadPoolConfig$.MODULE$:Lscala/actors/scheduler/ThreadPoolConfig$;
	invokevirtual	Method scala/actors/scheduler/ThreadPoolConfig$.useForkJoin:()Z
	ifeq	l1 // new
	new	class scala/actors/scheduler/ForkJoinScheduler
	dup
	getstatic	Field scala/actors/scheduler/ThreadPoolConfig$.MODULE$:Lscala/actors/scheduler/ThreadPoolConfig$;
	invokevirtual	Method scala/actors/scheduler/ThreadPoolConfig$.corePoolSize:()I
	getstatic	Field scala/actors/scheduler/ThreadPoolConfig$.MODULE$:Lscala/actors/scheduler/ThreadPoolConfig$;
	invokevirtual	Method scala/actors/scheduler/ThreadPoolConfig$.maxPoolSize:()I
	iconst_0
	iconst_0
	invokespecial	Method scala/actors/scheduler/ForkJoinScheduler."<init>":(IIZZ)V
	astore_3
	aload_3
	invokevirtual	Method scala/actors/scheduler/ForkJoinScheduler.start:()V
	aload_3
	goto	l2 // astore_1
l1	new	class java/util/concurrent/LinkedBlockingQueue
	dup
	invokespecial	Method java/util/concurrent/LinkedBlockingQueue."<init>":()V
	astore_2
	getstatic	Field scala/actors/scheduler/ExecutorScheduler$.MODULE$:Lscala/actors/scheduler/ExecutorScheduler$;
	new	class java/util/concurrent/ThreadPoolExecutor
	dup
	getstatic	Field scala/actors/scheduler/ThreadPoolConfig$.MODULE$:Lscala/actors/scheduler/ThreadPoolConfig$;
	invokevirtual	Method scala/actors/scheduler/ThreadPoolConfig$.corePoolSize:()I
	getstatic	Field scala/actors/scheduler/ThreadPoolConfig$.MODULE$:Lscala/actors/scheduler/ThreadPoolConfig$;
	invokevirtual	Method scala/actors/scheduler/ThreadPoolConfig$.maxPoolSize:()I
	ldc2_w	long 60000l
	getstatic	Field java/util/concurrent/TimeUnit.MILLISECONDS:Ljava/util/concurrent/TimeUnit;
	aload_2
	new	class java/util/concurrent/ThreadPoolExecutor$CallerRunsPolicy
	dup
	invokespecial	Method java/util/concurrent/ThreadPoolExecutor$CallerRunsPolicy."<init>":()V
	invokespecial	Method java/util/concurrent/ThreadPoolExecutor."<init>":(IIJLjava/util/concurrent/TimeUnit;Ljava/util/concurrent/BlockingQueue;Ljava/util/concurrent/RejectedExecutionHandler;)V
	invokevirtual	Method scala/actors/scheduler/ExecutorScheduler$.apply:(Ljava/util/concurrent/ExecutorService;)Lscala/actors/scheduler/ExecutorScheduler;
l2	astore_1
	getstatic	Field scala/actors/Debug$.MODULE$:Lscala/actors/Debug$;
	new	class scala/collection/mutable/StringBuilder
	dup
	invokespecial	Method scala/collection/mutable/StringBuilder."<init>":()V
	getstatic	Field scala/Predef$.MODULE$:Lscala/Predef$;
	aload_0
	invokevirtual	Method scala/Predef$.any2stringadd:(Ljava/lang/Object;)Lscala/runtime/StringAdd;
	ldc	String : starting new 
	invokevirtual	Method scala/runtime/StringAdd.$plus:(Ljava/lang/String;)Ljava/lang/String;
	invokevirtual	Method scala/collection/mutable/StringBuilder.append:(Ljava/lang/Object;)Lscala/collection/mutable/StringBuilder;
	aload_1
	invokevirtual	Method scala/collection/mutable/StringBuilder.append:(Ljava/lang/Object;)Lscala/collection/mutable/StringBuilder;
	ldc	String  [
	invokevirtual	Method scala/collection/mutable/StringBuilder.append:(Ljava/lang/Object;)Lscala/collection/mutable/StringBuilder;
	aload_1
	invokevirtual	Method java/lang/Object.getClass:()Ljava/lang/Class;
	invokevirtual	Method scala/collection/mutable/StringBuilder.append:(Ljava/lang/Object;)Lscala/collection/mutable/StringBuilder;
	ldc	String ]
	invokevirtual	Method scala/collection/mutable/StringBuilder.append:(Ljava/lang/Object;)Lscala/collection/mutable/StringBuilder;
	invokevirtual	Method scala/collection/mutable/StringBuilder.toString:()Ljava/lang/String;
	invokevirtual	Method scala/actors/Debug$.info:(Ljava/lang/String;)V
	aload_1
	areturn
  Labels:
   	l1 = 39 // new
   	l2 = 86 // astore_1
  LocalVariableTable: 
   Start  Length  Slot  Name   Signature
   0      141      0    this       Lscala/actors/Reactor$$anon$2;
   87      53      1    sched       Lscala/actors/IScheduler;
   47      39      2    workQueue       Ljava/util/concurrent/LinkedBlockingQueue;
   31      5      3    s       Lscala/actors/scheduler/ForkJoinScheduler;


public scala.actors.Reactor$$anon$2();
  Signature: ()V
  Code:
   Stack=1, Locals=1, Args_size=1
	aload_0
	invokespecial	Method java/lang/Object."<init>":()V
	aload_0
	invokestatic	Method scala/actors/IScheduler$class.$init$:(Lscala/actors/IScheduler;)V
	aload_0
	invokestatic	Method scala/actors/scheduler/DelegatingScheduler$class.$init$:(Lscala/actors/scheduler/DelegatingScheduler;)V
	return
  Labels:

}

