Compiled from "Reactor.scala"
public final class scala.actors.Reactor$$anonfun$searchMailbox$1 extends scala.runtime.AbstractFunction2 implements java.io.Serializable
  SourceFile: "Reactor.scala"
  Scala: length = 0x
   
  InnerClass: 
   public final $anonfun$searchMailbox$1=class scala/actors/Reactor$$anonfun$searchMailbox$1 of class scala/actors/Reactor
  minor version: 0
  major version: 49
  Constant pool:
Asciz	SourceFile;
Asciz	Reactor.scala;
Asciz	<clinit>;
Asciz	()V;
Asciz	Code;
Asciz	serialVersionUID;
Asciz	J;
Asciz	scala/actors/Reactor$$anonfun$searchMailbox$1;
class	scala/actors/Reactor$$anonfun$searchMailbox$1
NameAndType	serialVersionUID:J
Field	scala/actors/Reactor$$anonfun$searchMailbox$1.serialVersionUID:J
Asciz	$outer;
Asciz	Lscala/actors/Reactor;;
Asciz	<init>;
Asciz	(Lscala/actors/Reactor;)V;
Asciz	LineNumberTable;
Asciz	java/lang/NullPointerException;
class	java/lang/NullPointerException
NameAndType	"<init>":()V
Method	java/lang/NullPointerException."<init>":()V
NameAndType	$outer:Lscala/actors/Reactor;
Field	scala/actors/Reactor$$anonfun$searchMailbox$1.$outer:Lscala/actors/Reactor;
Asciz	scala/runtime/AbstractFunction2;
class	scala/runtime/AbstractFunction2
Method	scala/runtime/AbstractFunction2."<init>":()V
Asciz	this;
Asciz	Lscala/actors/Reactor$$anonfun$searchMailbox$1;;
Asciz	LocalVariableTable;
Asciz	apply;
Asciz	(Ljava/lang/Object;Ljava/lang/Object;)Ljava/lang/Object;;
Asciz	scala/actors/OutputChannel;
class	scala/actors/OutputChannel
Asciz	(Ljava/lang/Object;Lscala/actors/OutputChannel;)V;
NameAndType	apply:(Ljava/lang/Object;Lscala/actors/OutputChannel;)V
Method	scala/actors/Reactor$$anonfun$searchMailbox$1.apply:(Ljava/lang/Object;Lscala/actors/OutputChannel;)V
Asciz	scala/runtime/BoxedUnit;
class	scala/runtime/BoxedUnit
Asciz	UNIT;
Asciz	Lscala/runtime/BoxedUnit;;
NameAndType	UNIT:Lscala/runtime/BoxedUnit;
Field	scala/runtime/BoxedUnit.UNIT:Lscala/runtime/BoxedUnit;
Asciz	v1;
Asciz	Ljava/lang/Object;;
Asciz	v2;
Asciz	scala/actors/Reactor;
class	scala/actors/Reactor
Asciz	mailbox;
Asciz	()Lscala/actors/MQueue;;
NameAndType	mailbox:()Lscala/actors/MQueue;
InterfaceMethod	scala/actors/Reactor.mailbox:()Lscala/actors/MQueue;
Asciz	scala/actors/MQueue;
class	scala/actors/MQueue
Asciz	append;
NameAndType	append:(Ljava/lang/Object;Lscala/actors/OutputChannel;)V
Method	scala/actors/MQueue.append:(Ljava/lang/Object;Lscala/actors/OutputChannel;)V
Asciz	m;
Asciz	s;
Asciz	Lscala/actors/OutputChannel;;
Asciz	(Ljava/lang/Object;Lscala/actors/OutputChannel<Ljava/lang/Object;>;)V;
Asciz	Signature;
Asciz	Scala;
Asciz	InnerClasses;
Asciz	$anonfun$searchMailbox$1;
Asciz	java/io/Serializable;
class	java/io/Serializable

{
public static final long serialVersionUID;
  Signature: J

public final scala.actors.Reactor $outer;
  Signature: Lscala/actors/Reactor;

public static {};
  Signature: ()V
  Code:
   Stack=2, Locals=0, Args_size=0
	lconst_0
	putstatic	Field serialVersionUID:J
	return
  Labels:

public scala.actors.Reactor$$anonfun$searchMailbox$1(scala.actors.Reactor);
  Signature: (Lscala/actors/Reactor;)V
  Code:
   Stack=2, Locals=2, Args_size=2
	aload_1
	ifnonnull	l1 // aload_0
	new	class java/lang/NullPointerException
	dup
	invokespecial	Method java/lang/NullPointerException."<init>":()V
	athrow
l1	aload_0
	aload_1
	putfield	Field $outer:Lscala/actors/Reactor;
	aload_0
	invokespecial	Method scala/runtime/AbstractFunction2."<init>":()V
	return
  Labels:
   	l1 = 12 // aload_0
  LocalVariableTable: 
   Start  Length  Slot  Name   Signature
   0      22      0    this       Lscala/actors/Reactor$$anonfun$searchMailbox$1;
   0      22      1    $outer       Lscala/actors/Reactor;


public final java.lang.Object apply(java.lang.Object, java.lang.Object);
  Signature: (Ljava/lang/Object;Ljava/lang/Object;)Ljava/lang/Object;
  Code:
   Stack=3, Locals=3, Args_size=3
	aload_0
	aload_1
	aload_2
	checkcast	class scala/actors/OutputChannel
	invokevirtual	Method apply:(Ljava/lang/Object;Lscala/actors/OutputChannel;)V
	getstatic	Field scala/runtime/BoxedUnit.UNIT:Lscala/runtime/BoxedUnit;
	areturn
  Labels:
  LocalVariableTable: 
   Start  Length  Slot  Name   Signature
   0      13      0    this       Lscala/actors/Reactor$$anonfun$searchMailbox$1;
   0      13      1    v1       Ljava/lang/Object;
   0      13      2    v2       Ljava/lang/Object;


public final void apply(java.lang.Object, scala.actors.OutputChannel);
  Signature: (Ljava/lang/Object;Lscala/actors/OutputChannel;)V
  Code:
   Stack=3, Locals=3, Args_size=3
	aload_0
	getfield	Field $outer:Lscala/actors/Reactor;
	invokeinterface	InterfaceMethod scala/actors/Reactor.mailbox:()Lscala/actors/MQueue;
	aload_1
	aload_2
	invokevirtual	Method scala/actors/MQueue.append:(Ljava/lang/Object;Lscala/actors/OutputChannel;)V
	return
  Labels:
  LocalVariableTable: 
   Start  Length  Slot  Name   Signature
   0      15      0    this       Lscala/actors/Reactor$$anonfun$searchMailbox$1;
   0      15      1    m       Ljava/lang/Object;
   0      15      2    s       Lscala/actors/OutputChannel;

  Signature: length = 0x2
   00 3B 

}

