Compiled from "Reaction.scala"
public final class scala.actors.Reaction$$anonfun$$init$$1 extends scala.runtime.AbstractFunction0 implements java.io.Serializable
  SourceFile: "Reaction.scala"
  Scala: length = 0x
   
  InnerClass: 
   public final $anonfun$$init$$1=class scala/actors/Reaction$$anonfun$$init$$1 of class scala/actors/Reaction
  minor version: 0
  major version: 49
  Constant pool:
Asciz	SourceFile;
Asciz	Reaction.scala;
Asciz	<clinit>;
Asciz	()V;
Asciz	Code;
Asciz	serialVersionUID;
Asciz	J;
Asciz	scala/actors/Reaction$$anonfun$$init$$1;
class	scala/actors/Reaction$$anonfun$$init$$1
NameAndType	serialVersionUID:J
Field	scala/actors/Reaction$$anonfun$$init$$1.serialVersionUID:J
Asciz	msg$1;
Asciz	Ljava/lang/Object;;
Asciz	f$1;
Asciz	Lscala/PartialFunction;;
Asciz	a$1;
Asciz	Lscala/actors/Actor;;
Asciz	apply;
Asciz	LineNumberTable;
NameAndType	f$1:Lscala/PartialFunction;
Field	scala/actors/Reaction$$anonfun$$init$$1.f$1:Lscala/PartialFunction;
Asciz	java/lang/Object;
class	java/lang/Object
Asciz	equals;
Asciz	(Ljava/lang/Object;)Z;
NameAndType	equals:(Ljava/lang/Object;)Z
Method	java/lang/Object.equals:(Ljava/lang/Object;)Z
NameAndType	a$1:Lscala/actors/Actor;
Field	scala/actors/Reaction$$anonfun$$init$$1.a$1:Lscala/actors/Actor;
Asciz	scala/actors/Reactor;
class	scala/actors/Reactor
Asciz	act;
NameAndType	act:()V
InterfaceMethod	scala/actors/Reactor.act:()V
NameAndType	msg$1:Ljava/lang/Object;
Field	scala/actors/Reaction$$anonfun$$init$$1.msg$1:Ljava/lang/Object;
Asciz	scala/Function1;
class	scala/Function1
Asciz	(Ljava/lang/Object;)Ljava/lang/Object;;
NameAndType	apply:(Ljava/lang/Object;)Ljava/lang/Object;
InterfaceMethod	scala/Function1.apply:(Ljava/lang/Object;)Ljava/lang/Object;
Asciz	()Ljava/lang/Object;;
NameAndType	apply:()V
Method	scala/actors/Reaction$$anonfun$$init$$1.apply:()V
Asciz	scala/runtime/BoxedUnit;
class	scala/runtime/BoxedUnit
Asciz	UNIT;
Asciz	Lscala/runtime/BoxedUnit;;
NameAndType	UNIT:Lscala/runtime/BoxedUnit;
Field	scala/runtime/BoxedUnit.UNIT:Lscala/runtime/BoxedUnit;
Asciz	<init>;
Asciz	(Lscala/actors/Actor;Lscala/PartialFunction;Ljava/lang/Object;)V;
Asciz	scala/runtime/AbstractFunction0;
class	scala/runtime/AbstractFunction0
NameAndType	"<init>":()V
Method	scala/runtime/AbstractFunction0."<init>":()V
Asciz	Scala;
Asciz	InnerClasses;
Asciz	scala/actors/Reaction;
class	scala/actors/Reaction
Asciz	$anonfun$$init$$1;
Asciz	java/io/Serializable;
class	java/io/Serializable

{
public static final long serialVersionUID;
  Signature: J

private final java.lang.Object msg$1;
  Signature: Ljava/lang/Object;

private final scala.PartialFunction f$1;
  Signature: Lscala/PartialFunction;

private final scala.actors.Actor a$1;
  Signature: Lscala/actors/Actor;

public static {};
  Signature: ()V
  Code:
   Stack=2, Locals=0, Args_size=0
	lconst_0
	putstatic	Field serialVersionUID:J
	return
  Labels:

public final void apply();
  Signature: ()V
  Code:
   Stack=2, Locals=2, Args_size=1
	aload_0
	getfield	Field f$1:Lscala/PartialFunction;
	dup
	astore_1
	ifnull	l1 // aload_0
	aload_1
	aconst_null
	invokevirtual	Method java/lang/Object.equals:(Ljava/lang/Object;)Z
	ifeq	l2 // aload_0
l1	aload_0
	getfield	Field a$1:Lscala/actors/Actor;
	invokeinterface	InterfaceMethod scala/actors/Reactor.act:()V
	goto	l3 // return
l2	aload_0
	getfield	Field f$1:Lscala/PartialFunction;
	aload_0
	getfield	Field msg$1:Ljava/lang/Object;
	invokeinterface	InterfaceMethod scala/Function1.apply:(Ljava/lang/Object;)Ljava/lang/Object;
	pop
l3	return
  Labels:
   	l1 = 17 // aload_0
   	l2 = 29 // aload_0
   	l3 = 43 // return

public final java.lang.Object apply();
  Signature: ()Ljava/lang/Object;
  Code:
   Stack=1, Locals=1, Args_size=1
	aload_0
	invokevirtual	Method apply:()V
	getstatic	Field scala/runtime/BoxedUnit.UNIT:Lscala/runtime/BoxedUnit;
	areturn
  Labels:

public scala.actors.Reaction$$anonfun$$init$$1(scala.actors.Actor, scala.PartialFunction, java.lang.Object);
  Signature: (Lscala/actors/Actor;Lscala/PartialFunction;Ljava/lang/Object;)V
  Code:
   Stack=2, Locals=4, Args_size=4
	aload_0
	aload_1
	putfield	Field a$1:Lscala/actors/Actor;
	aload_0
	aload_2
	putfield	Field f$1:Lscala/PartialFunction;
	aload_0
	aload_3
	putfield	Field msg$1:Ljava/lang/Object;
	aload_0
	invokespecial	Method scala/runtime/AbstractFunction0."<init>":()V
	return
  Labels:

}

