Compiled from "Reaction.scala"
public final class scala.actors.Reaction$$anonfun$$init$$1 extends java.lang.Object implements scala.Function0,scala.ScalaObject,java.io.Serializable
  SourceFile: "Reaction.scala"
  Scala: length = 0x
   
  InnerClass: 
   public final #70= #9 of #69; //$anonfun$$init$$1=class scala/actors/Reaction$$anonfun$$init$$1 of class scala/actors/Reaction
  minor version: 0
  major version: 49
  Constant pool:
const #1 = Asciz	SourceFile;
const #2 = Asciz	Reaction.scala;
const #3 = Asciz	<clinit>;
const #4 = Asciz	()V;
const #5 = Asciz	Code;
const #6 = Asciz	serialVersionUID;
const #7 = Asciz	J;
const #8 = Asciz	scala/actors/Reaction$$anonfun$$init$$1;
const #9 = class	#8;	//  scala/actors/Reaction$$anonfun$$init$$1
const #10 = NameAndType	#6:#7;//  serialVersionUID:J
const #11 = Field	#9.#10;	//  scala/actors/Reaction$$anonfun$$init$$1.serialVersionUID:J
const #12 = Asciz	msg$1;
const #13 = Asciz	Ljava/lang/Object;;
const #14 = Asciz	f$1;
const #15 = Asciz	Lscala/PartialFunction;;
const #16 = Asciz	a$1;
const #17 = Asciz	Lscala/actors/Actor;;
const #18 = Asciz	<init>;
const #19 = Asciz	(Lscala/actors/Actor;Lscala/PartialFunction;Ljava/lang/Object;)V;
const #20 = Asciz	LineNumberTable;
const #21 = NameAndType	#16:#17;//  a$1:Lscala/actors/Actor;
const #22 = Field	#9.#21;	//  scala/actors/Reaction$$anonfun$$init$$1.a$1:Lscala/actors/Actor;
const #23 = NameAndType	#14:#15;//  f$1:Lscala/PartialFunction;
const #24 = Field	#9.#23;	//  scala/actors/Reaction$$anonfun$$init$$1.f$1:Lscala/PartialFunction;
const #25 = NameAndType	#12:#13;//  msg$1:Ljava/lang/Object;
const #26 = Field	#9.#25;	//  scala/actors/Reaction$$anonfun$$init$$1.msg$1:Ljava/lang/Object;
const #27 = Asciz	java/lang/Object;
const #28 = class	#27;	//  java/lang/Object
const #29 = NameAndType	#18:#4;//  "<init>":()V
const #30 = Method	#28.#29;	//  java/lang/Object."<init>":()V
const #31 = Asciz	scala/Function0$class;
const #32 = class	#31;	//  scala/Function0$class
const #33 = Asciz	$init$;
const #34 = Asciz	(Lscala/Function0;)V;
const #35 = NameAndType	#33:#34;//  $init$:(Lscala/Function0;)V
const #36 = Method	#32.#35;	//  scala/Function0$class.$init$:(Lscala/Function0;)V
const #37 = Asciz	apply;
const #38 = Asciz	()Ljava/lang/Object;;
const #39 = NameAndType	#37:#4;//  apply:()V
const #40 = Method	#9.#39;	//  scala/actors/Reaction$$anonfun$$init$$1.apply:()V
const #41 = Asciz	scala/runtime/BoxedUnit;
const #42 = class	#41;	//  scala/runtime/BoxedUnit
const #43 = Asciz	UNIT;
const #44 = Asciz	Lscala/runtime/BoxedUnit;;
const #45 = NameAndType	#43:#44;//  UNIT:Lscala/runtime/BoxedUnit;
const #46 = Field	#42.#45;	//  scala/runtime/BoxedUnit.UNIT:Lscala/runtime/BoxedUnit;
const #47 = Asciz	equals;
const #48 = Asciz	(Ljava/lang/Object;)Z;
const #49 = NameAndType	#47:#48;//  equals:(Ljava/lang/Object;)Z
const #50 = Method	#28.#49;	//  java/lang/Object.equals:(Ljava/lang/Object;)Z
const #51 = Asciz	scala/actors/Reactor;
const #52 = class	#51;	//  scala/actors/Reactor
const #53 = Asciz	act;
const #54 = NameAndType	#53:#4;//  act:()V
const #55 = InterfaceMethod	#52.#54;	//  scala/actors/Reactor.act:()V
const #56 = Asciz	scala/Function1;
const #57 = class	#56;	//  scala/Function1
const #58 = Asciz	(Ljava/lang/Object;)Ljava/lang/Object;;
const #59 = NameAndType	#37:#58;//  apply:(Ljava/lang/Object;)Ljava/lang/Object;
const #60 = InterfaceMethod	#57.#59;	//  scala/Function1.apply:(Ljava/lang/Object;)Ljava/lang/Object;
const #61 = Asciz	toString;
const #62 = Asciz	()Ljava/lang/String;;
const #63 = Asciz	(Lscala/Function0;)Ljava/lang/String;;
const #64 = NameAndType	#61:#63;//  toString:(Lscala/Function0;)Ljava/lang/String;
const #65 = Method	#32.#64;	//  scala/Function0$class.toString:(Lscala/Function0;)Ljava/lang/String;
const #66 = Asciz	Scala;
const #67 = Asciz	InnerClasses;
const #68 = Asciz	scala/actors/Reaction;
const #69 = class	#68;	//  scala/actors/Reaction
const #70 = Asciz	$anonfun$$init$$1;
const #71 = Asciz	scala/Function0;
const #72 = class	#71;	//  scala/Function0
const #73 = Asciz	scala/ScalaObject;
const #74 = class	#73;	//  scala/ScalaObject
const #75 = Asciz	java/io/Serializable;
const #76 = class	#75;	//  java/io/Serializable

{
public static final long serialVersionUID;

public static {};
  Code:
   Stack=2, Locals=0, Args_size=0
   0:	lconst_0
   1:	putstatic	#11; //Field serialVersionUID:J
   4:	return

public scala.actors.Reaction$$anonfun$$init$$1(scala.actors.Actor, scala.PartialFunction, java.lang.Object);
  Code:
   Stack=2, Locals=4, Args_size=4
   0:	aload_0
   1:	aload_1
   2:	putfield	#22; //Field a$1:Lscala/actors/Actor;
   5:	aload_0
   6:	aload_2
   7:	putfield	#24; //Field f$1:Lscala/PartialFunction;
   10:	aload_0
   11:	aload_3
   12:	putfield	#26; //Field msg$1:Ljava/lang/Object;
   15:	aload_0
   16:	invokespecial	#30; //Method java/lang/Object."<init>":()V
   19:	aload_0
   20:	invokestatic	#36; //Method scala/Function0$class.$init$:(Lscala/Function0;)V
   23:	return
  LineNumberTable: 
   line 29: 0


public final java.lang.Object apply();
  Code:
   Stack=1, Locals=1, Args_size=1
   0:	aload_0
   1:	invokevirtual	#40; //Method apply:()V
   4:	getstatic	#46; //Field scala/runtime/BoxedUnit.UNIT:Lscala/runtime/BoxedUnit;
   7:	areturn
  LineNumberTable: 
   line 29: 0


public final void apply();
  Code:
   Stack=2, Locals=2, Args_size=1
   0:	aload_0
   1:	getfield	#24; //Field f$1:Lscala/PartialFunction;
   4:	dup
   5:	astore_1
   6:	ifnull	17
   9:	aload_1
   10:	aconst_null
   11:	invokevirtual	#50; //Method java/lang/Object.equals:(Ljava/lang/Object;)Z
   14:	ifeq	29
   17:	aload_0
   18:	getfield	#22; //Field a$1:Lscala/actors/Actor;
   21:	invokeinterface	#55,  1; //InterfaceMethod scala/actors/Reactor.act:()V
   26:	goto	43
   29:	aload_0
   30:	getfield	#24; //Field f$1:Lscala/PartialFunction;
   33:	aload_0
   34:	getfield	#26; //Field msg$1:Ljava/lang/Object;
   37:	invokeinterface	#60,  2; //InterfaceMethod scala/Function1.apply:(Ljava/lang/Object;)Ljava/lang/Object;
   42:	pop
   43:	return
  LineNumberTable: 
   line 30: 0
   line 31: 17
   line 33: 29
   line 30: 43


public java.lang.String toString();
  Code:
   Stack=1, Locals=1, Args_size=1
   0:	aload_0
   1:	invokestatic	#65; //Method scala/Function0$class.toString:(Lscala/Function0;)Ljava/lang/String;
   4:	areturn
  LineNumberTable: 
   line 29: 0


}

