Compiled from "Reactor.scala"
public final class scala.actors.Reactor$$anonfun$2 extends scala.runtime.AbstractFunction0 implements java.io.Serializable
  SourceFile: "Reactor.scala"
  Scala: length = 0x
   
  InnerClass: 
   public final $anonfun$2=class scala/actors/Reactor$$anonfun$2 of class scala/actors/Reactor
  minor version: 0
  major version: 49
  Constant pool:
Asciz	SourceFile;
Asciz	Reactor.scala;
Asciz	<clinit>;
Asciz	()V;
Asciz	Code;
Asciz	serialVersionUID;
Asciz	J;
Asciz	scala/actors/Reactor$$anonfun$2;
class	scala/actors/Reactor$$anonfun$2
NameAndType	serialVersionUID:J
Field	scala/actors/Reactor$$anonfun$2.serialVersionUID:J
Asciz	msg$2;
Asciz	Ljava/lang/Object;;
Asciz	handler$2;
Asciz	Lscala/PartialFunction;;
Asciz	apply;
Asciz	LineNumberTable;
NameAndType	handler$2:Lscala/PartialFunction;
Field	scala/actors/Reactor$$anonfun$2.handler$2:Lscala/PartialFunction;
NameAndType	msg$2:Ljava/lang/Object;
Field	scala/actors/Reactor$$anonfun$2.msg$2:Ljava/lang/Object;
Asciz	scala/Function1;
class	scala/Function1
Asciz	(Ljava/lang/Object;)Ljava/lang/Object;;
NameAndType	apply:(Ljava/lang/Object;)Ljava/lang/Object;
InterfaceMethod	scala/Function1.apply:(Ljava/lang/Object;)Ljava/lang/Object;
Asciz	()Ljava/lang/Object;;
NameAndType	apply:()V
Method	scala/actors/Reactor$$anonfun$2.apply:()V
Asciz	scala/runtime/BoxedUnit;
class	scala/runtime/BoxedUnit
Asciz	UNIT;
Asciz	Lscala/runtime/BoxedUnit;;
NameAndType	UNIT:Lscala/runtime/BoxedUnit;
Field	scala/runtime/BoxedUnit.UNIT:Lscala/runtime/BoxedUnit;
Asciz	<init>;
Asciz	(Lscala/actors/Reactor;Lscala/PartialFunction;Ljava/lang/Object;)V;
Asciz	scala/runtime/AbstractFunction0;
class	scala/runtime/AbstractFunction0
NameAndType	"<init>":()V
Method	scala/runtime/AbstractFunction0."<init>":()V
Asciz	this;
Asciz	Lscala/actors/Reactor$$anonfun$2;;
Asciz	$outer;
Asciz	Lscala/actors/Reactor;;
Asciz	LocalVariableTable;
Asciz	(Lscala/actors/Reactor<TMsg;>;)V;
Asciz	Signature;
Asciz	Scala;
Asciz	InnerClasses;
Asciz	scala/actors/Reactor;
class	scala/actors/Reactor
Asciz	$anonfun$2;
Asciz	java/io/Serializable;
class	java/io/Serializable

{
public static final long serialVersionUID;
  Signature: J

public final java.lang.Object msg$2;
  Signature: Ljava/lang/Object;

public final scala.PartialFunction handler$2;
  Signature: Lscala/PartialFunction;

public static {};
  Signature: ()V
  Code:
   Stack=2, Locals=0, Args_size=0
	lconst_0
	putstatic	Field serialVersionUID:J
	return
  Labels:

public final void apply();
  Signature: ()V
  Code:
   Stack=2, Locals=1, Args_size=1
	aload_0
	getfield	Field handler$2:Lscala/PartialFunction;
	aload_0
	getfield	Field msg$2:Ljava/lang/Object;
	invokeinterface	InterfaceMethod scala/Function1.apply:(Ljava/lang/Object;)Ljava/lang/Object;
	pop
	return
  Labels:

public final java.lang.Object apply();
  Signature: ()Ljava/lang/Object;
  Code:
   Stack=1, Locals=1, Args_size=1
	aload_0
	invokevirtual	Method apply:()V
	getstatic	Field scala/runtime/BoxedUnit.UNIT:Lscala/runtime/BoxedUnit;
	areturn
  Labels:

public scala.actors.Reactor$$anonfun$2(scala.actors.Reactor, scala.PartialFunction, java.lang.Object);
  Signature: (Lscala/actors/Reactor;Lscala/PartialFunction;Ljava/lang/Object;)V
  Code:
   Stack=2, Locals=4, Args_size=4
	aload_0
	aload_2
	putfield	Field handler$2:Lscala/PartialFunction;
	aload_0
	aload_3
	putfield	Field msg$2:Ljava/lang/Object;
	aload_0
	invokespecial	Method scala/runtime/AbstractFunction0."<init>":()V
	return
  Labels:
  LocalVariableTable: 
   Start  Length  Slot  Name   Signature
   0      15      0    this       Lscala/actors/Reactor$$anonfun$2;
   0      15      1    $outer       Lscala/actors/Reactor;

  Signature: length = 0x2
   00 2F 

}

