Compiled from "ReactChannel.scala"
public final class scala.actors.ReactChannel$SendToReactor$ extends java.lang.Object implements scala.Function2,scala.ScalaObject
  SourceFile: "ReactChannel.scala"
  Scala: length = 0x
   
  InnerClass: 
   public SendToReactor=class scala/actors/ReactChannel$SendToReactor of class scala/actors/ReactChannel
  minor version: 0
  major version: 49
  Constant pool:
Asciz	SourceFile;
Asciz	ReactChannel.scala;
Asciz	Scala;
Asciz	$outer;
Asciz	Lscala/actors/ReactChannel;;
Asciz	toString;
Asciz	()Ljava/lang/String;;
Asciz	Code;
Asciz	LineNumberTable;
Asciz	scala/Function2$class;
class	scala/Function2$class
Asciz	(Lscala/Function2;)Ljava/lang/String;;
NameAndType	toString:(Lscala/Function2;)Ljava/lang/String;
Method	scala/Function2$class.toString:(Lscala/Function2;)Ljava/lang/String;
Asciz	curried;
Asciz	()Lscala/Function1;;
Asciz	(Lscala/Function2;)Lscala/Function1;;
NameAndType	curried:(Lscala/Function2;)Lscala/Function1;
Method	scala/Function2$class.curried:(Lscala/Function2;)Lscala/Function1;
Asciz	curry;
NameAndType	curry:(Lscala/Function2;)Lscala/Function1;
Method	scala/Function2$class.curry:(Lscala/Function2;)Lscala/Function1;
Asciz	Deprecated;
Asciz	tupled;
NameAndType	tupled:(Lscala/Function2;)Lscala/Function1;
Method	scala/Function2$class.tupled:(Lscala/Function2;)Lscala/Function1;
Asciz	unapply;
Asciz	(Lscala/actors/ReactChannel$SendToReactor;)Lscala/Option;;
Asciz	java/lang/Object;
class	java/lang/Object
Asciz	equals;
Asciz	(Ljava/lang/Object;)Z;
NameAndType	equals:(Ljava/lang/Object;)Z
Method	java/lang/Object.equals:(Ljava/lang/Object;)Z
Asciz	scala/None$;
class	scala/None$
Asciz	MODULE$;
Asciz	Lscala/None$;;
NameAndType	MODULE$:Lscala/None$;
Field	scala/None$.MODULE$:Lscala/None$;
Asciz	scala/Some;
class	scala/Some
Asciz	scala/Tuple2;
class	scala/Tuple2
Asciz	scala/actors/ReactChannel$SendToReactor;
class	scala/actors/ReactChannel$SendToReactor
Asciz	channel;
Asciz	()Lscala/actors/ReactChannel;;
NameAndType	channel:()Lscala/actors/ReactChannel;
Method	scala/actors/ReactChannel$SendToReactor.channel:()Lscala/actors/ReactChannel;
Asciz	msg;
Asciz	()Ljava/lang/Object;;
NameAndType	msg:()Ljava/lang/Object;
Method	scala/actors/ReactChannel$SendToReactor.msg:()Ljava/lang/Object;
Asciz	<init>;
Asciz	(Ljava/lang/Object;Ljava/lang/Object;)V;
NameAndType	"<init>":(Ljava/lang/Object;Ljava/lang/Object;)V
Method	scala/Tuple2."<init>":(Ljava/lang/Object;Ljava/lang/Object;)V
Asciz	(Ljava/lang/Object;)V;
NameAndType	"<init>":(Ljava/lang/Object;)V
Method	scala/Some."<init>":(Ljava/lang/Object;)V
Asciz	this;
Asciz	Lscala/actors/ReactChannel$SendToReactor$;;
Asciz	x$0;
Asciz	Lscala/actors/ReactChannel$SendToReactor;;
Asciz	LocalVariableTable;
Asciz	apply;
Asciz	(Lscala/actors/ReactChannel;Ljava/lang/Object;)Lscala/actors/ReactChannel$SendToReactor;;
Asciz	scala/actors/ReactChannel$SendToReactor$;
class	scala/actors/ReactChannel$SendToReactor$
NameAndType	$outer:Lscala/actors/ReactChannel;
Field	scala/actors/ReactChannel$SendToReactor$.$outer:Lscala/actors/ReactChannel;
Asciz	(Lscala/actors/ReactChannel;Lscala/actors/ReactChannel;Ljava/lang/Object;)V;
NameAndType	"<init>":(Lscala/actors/ReactChannel;Lscala/actors/ReactChannel;Ljava/lang/Object;)V
Method	scala/actors/ReactChannel$SendToReactor."<init>":(Lscala/actors/ReactChannel;Lscala/actors/ReactChannel;Ljava/lang/Object;)V
Asciz	Ljava/lang/Object;;
Asciz	(Ljava/lang/Object;Ljava/lang/Object;)Ljava/lang/Object;;
Asciz	scala/actors/ReactChannel;
class	scala/actors/ReactChannel
NameAndType	apply:(Lscala/actors/ReactChannel;Ljava/lang/Object;)Lscala/actors/ReactChannel$SendToReactor;
Method	scala/actors/ReactChannel$SendToReactor$.apply:(Lscala/actors/ReactChannel;Ljava/lang/Object;)Lscala/actors/ReactChannel$SendToReactor;
Asciz	v1;
Asciz	v2;
Asciz	(Lscala/actors/ReactChannel;)V;
Asciz	java/lang/NullPointerException;
class	java/lang/NullPointerException
Asciz	()V;
NameAndType	"<init>":()V
Method	java/lang/NullPointerException."<init>":()V
Method	java/lang/Object."<init>":()V
Asciz	$init$;
Asciz	(Lscala/Function2;)V;
NameAndType	$init$:(Lscala/Function2;)V
Method	scala/Function2$class.$init$:(Lscala/Function2;)V
Asciz	(Lscala/actors/ReactChannel<TMsg;>;)V;
Asciz	Signature;
Asciz	InnerClasses;
Asciz	SendToReactor;
Asciz	scala/Function2;
class	scala/Function2
Asciz	scala/ScalaObject;
class	scala/ScalaObject

{
private final scala.actors.ReactChannel $outer;
  Signature: Lscala/actors/ReactChannel;

public java.lang.String toString();
  Signature: ()Ljava/lang/String;
  Code:
   Stack=1, Locals=1, Args_size=1
	aload_0
	invokestatic	Method scala/Function2$class.toString:(Lscala/Function2;)Ljava/lang/String;
	areturn
  Labels:

public scala.Function1 curried();
  Signature: ()Lscala/Function1;
  Code:
   Stack=1, Locals=1, Args_size=1
	aload_0
	invokestatic	Method scala/Function2$class.curried:(Lscala/Function2;)Lscala/Function1;
	areturn
  Labels:

public scala.Function1 curry();
  Signature: ()Lscala/Function1;
  Code:
   Stack=1, Locals=1, Args_size=1
	aload_0
	invokestatic	Method scala/Function2$class.curry:(Lscala/Function2;)Lscala/Function1;
	areturn
  Labels:
  Deprecated: true

public scala.Function1 tupled();
  Signature: ()Lscala/Function1;
  Code:
   Stack=1, Locals=1, Args_size=1
	aload_0
	invokestatic	Method scala/Function2$class.tupled:(Lscala/Function2;)Lscala/Function1;
	areturn
  Labels:

public scala.Option unapply(scala.actors.ReactChannel$SendToReactor);
  Signature: (Lscala/actors/ReactChannel$SendToReactor;)Lscala/Option;
  Code:
   Stack=6, Locals=3, Args_size=2
	aload_1
	dup
	astore_2
	ifnull	l1 // getstatic
	aload_2
	aconst_null
	invokevirtual	Method java/lang/Object.equals:(Ljava/lang/Object;)Z
	ifeq	l2 // new
l1	getstatic	Field scala/None$.MODULE$:Lscala/None$;
	goto	l3 // areturn
l2	new	class scala/Some
	dup
	new	class scala/Tuple2
	dup
	aload_1
	invokevirtual	Method scala/actors/ReactChannel$SendToReactor.channel:()Lscala/actors/ReactChannel;
	aload_1
	invokevirtual	Method scala/actors/ReactChannel$SendToReactor.msg:()Ljava/lang/Object;
	invokespecial	Method scala/Tuple2."<init>":(Ljava/lang/Object;Ljava/lang/Object;)V
	invokespecial	Method scala/Some."<init>":(Ljava/lang/Object;)V
l3	areturn
  Labels:
   	l1 = 14 // getstatic
   	l2 = 20 // new
   	l3 = 42 // areturn
  LocalVariableTable: 
   Start  Length  Slot  Name   Signature
   0      43      0    this       Lscala/actors/ReactChannel$SendToReactor$;
   0      43      1    x$0       Lscala/actors/ReactChannel$SendToReactor;


public scala.actors.ReactChannel$SendToReactor apply(scala.actors.ReactChannel, java.lang.Object);
  Signature: (Lscala/actors/ReactChannel;Ljava/lang/Object;)Lscala/actors/ReactChannel$SendToReactor;
  Code:
   Stack=5, Locals=4, Args_size=3
	aload_0
	getfield	Field $outer:Lscala/actors/ReactChannel;
	astore_3
	new	class scala/actors/ReactChannel$SendToReactor
	dup
	aload_0
	getfield	Field $outer:Lscala/actors/ReactChannel;
	aload_1
	aload_2
	invokespecial	Method scala/actors/ReactChannel$SendToReactor."<init>":(Lscala/actors/ReactChannel;Lscala/actors/ReactChannel;Ljava/lang/Object;)V
	areturn
  Labels:
  LocalVariableTable: 
   Start  Length  Slot  Name   Signature
   0      19      0    this       Lscala/actors/ReactChannel$SendToReactor$;
   5      14      1    channel       Lscala/actors/ReactChannel;
   5      14      2    msg       Ljava/lang/Object;


public java.lang.Object apply(java.lang.Object, java.lang.Object);
  Signature: (Ljava/lang/Object;Ljava/lang/Object;)Ljava/lang/Object;
  Code:
   Stack=3, Locals=4, Args_size=3
	aload_0
	getfield	Field $outer:Lscala/actors/ReactChannel;
	astore_3
	aload_0
	aload_1
	checkcast	class scala/actors/ReactChannel
	aload_2
	invokevirtual	Method apply:(Lscala/actors/ReactChannel;Ljava/lang/Object;)Lscala/actors/ReactChannel$SendToReactor;
	areturn
  Labels:
  LocalVariableTable: 
   Start  Length  Slot  Name   Signature
   0      15      0    this       Lscala/actors/ReactChannel$SendToReactor$;
   5      10      1    v1       Ljava/lang/Object;
   5      10      2    v2       Ljava/lang/Object;


public scala.actors.ReactChannel$SendToReactor$(scala.actors.ReactChannel);
  Signature: (Lscala/actors/ReactChannel;)V
  Code:
   Stack=2, Locals=2, Args_size=2
	aload_1
	ifnonnull	l1 // aload_0
	new	class java/lang/NullPointerException
	dup
	invokespecial	Method java/lang/NullPointerException."<init>":()V
	athrow
l1	aload_0
	aload_1
	putfield	Field $outer:Lscala/actors/ReactChannel;
	aload_0
	invokespecial	Method java/lang/Object."<init>":()V
	aload_0
	invokestatic	Method scala/Function2$class.$init$:(Lscala/Function2;)V
	return
  Labels:
   	l1 = 12 // aload_0
  LocalVariableTable: 
   Start  Length  Slot  Name   Signature
   0      26      0    this       Lscala/actors/ReactChannel$SendToReactor$;
   0      26      1    $outer       Lscala/actors/ReactChannel;

  Signature: length = 0x2
   00 5F 

}

