Compiled from "Reactor.scala"
public final class scala.actors.Reactor$$anonfun$3 extends java.lang.Object implements scala.Function2,scala.ScalaObject,java.io.Serializable
  SourceFile: "Reactor.scala"
  Scala: length = 0x
   
  InnerClass: 
   public final $anonfun$3=class scala/actors/Reactor$$anonfun$3 of class scala/actors/Reactor
  minor version: 0
  major version: 49
  Constant pool:
Asciz	SourceFile;
Asciz	Reactor.scala;
Asciz	<clinit>;
Asciz	()V;
Asciz	Code;
Asciz	serialVersionUID;
Asciz	J;
Asciz	scala/actors/Reactor$$anonfun$3;
class	scala/actors/Reactor$$anonfun$3
NameAndType	serialVersionUID:J
Field	scala/actors/Reactor$$anonfun$3.serialVersionUID:J
Asciz	handlesMessage$1;
Asciz	Lscala/Function1;;
Asciz	<init>;
Asciz	(Lscala/actors/Reactor;Lscala/Function1;)V;
Asciz	LineNumberTable;
NameAndType	handlesMessage$1:Lscala/Function1;
Field	scala/actors/Reactor$$anonfun$3.handlesMessage$1:Lscala/Function1;
Asciz	java/lang/Object;
class	java/lang/Object
NameAndType	"<init>":()V
Method	java/lang/Object."<init>":()V
Asciz	scala/Function2$class;
class	scala/Function2$class
Asciz	$init$;
Asciz	(Lscala/Function2;)V;
NameAndType	$init$:(Lscala/Function2;)V
Method	scala/Function2$class.$init$:(Lscala/Function2;)V
Asciz	this;
Asciz	Lscala/actors/Reactor$$anonfun$3;;
Asciz	$outer;
Asciz	Lscala/actors/Reactor;;
Asciz	LocalVariableTable;
Asciz	apply;
Asciz	(Ljava/lang/Object;Ljava/lang/Object;)Ljava/lang/Object;;
Asciz	scala/actors/OutputChannel;
class	scala/actors/OutputChannel
Asciz	(Ljava/lang/Object;Lscala/actors/OutputChannel;)Z;
NameAndType	apply:(Ljava/lang/Object;Lscala/actors/OutputChannel;)Z
Method	scala/actors/Reactor$$anonfun$3.apply:(Ljava/lang/Object;Lscala/actors/OutputChannel;)Z
Asciz	scala/runtime/BoxesRunTime;
class	scala/runtime/BoxesRunTime
Asciz	boxToBoolean;
Asciz	(Z)Ljava/lang/Boolean;;
NameAndType	boxToBoolean:(Z)Ljava/lang/Boolean;
Method	scala/runtime/BoxesRunTime.boxToBoolean:(Z)Ljava/lang/Boolean;
Asciz	v1;
Asciz	Ljava/lang/Object;;
Asciz	v2;
Asciz	scala/Function1;
class	scala/Function1
Asciz	(Ljava/lang/Object;)Ljava/lang/Object;;
NameAndType	apply:(Ljava/lang/Object;)Ljava/lang/Object;
InterfaceMethod	scala/Function1.apply:(Ljava/lang/Object;)Ljava/lang/Object;
Asciz	unboxToBoolean;
Asciz	(Ljava/lang/Object;)Z;
NameAndType	unboxToBoolean:(Ljava/lang/Object;)Z
Method	scala/runtime/BoxesRunTime.unboxToBoolean:(Ljava/lang/Object;)Z
Asciz	msg;
Asciz	replyTo;
Asciz	Lscala/actors/OutputChannel;;
Asciz	(Ljava/lang/Object;Lscala/actors/OutputChannel<Ljava/lang/Object;>;)Z;
Asciz	Signature;
Asciz	curry;
Asciz	()Lscala/Function1;;
Asciz	(Lscala/Function2;)Lscala/Function1;;
NameAndType	curry:(Lscala/Function2;)Lscala/Function1;
Method	scala/Function2$class.curry:(Lscala/Function2;)Lscala/Function1;
Asciz	toString;
Asciz	()Ljava/lang/String;;
Asciz	(Lscala/Function2;)Ljava/lang/String;;
NameAndType	toString:(Lscala/Function2;)Ljava/lang/String;
Method	scala/Function2$class.toString:(Lscala/Function2;)Ljava/lang/String;
Asciz	Scala;
Asciz	InnerClasses;
Asciz	scala/actors/Reactor;
class	scala/actors/Reactor
Asciz	$anonfun$3;
Asciz	scala/Function2;
class	scala/Function2
Asciz	scala/ScalaObject;
class	scala/ScalaObject
Asciz	java/io/Serializable;
class	java/io/Serializable

{
public static final long serialVersionUID;
  Signature: J

private final scala.Function1 handlesMessage$1;
  Signature: Lscala/Function1;

public static {};
  Signature: ()V
  Code:
   Stack=2, Locals=0, Args_size=0
	lconst_0
	putstatic	Field serialVersionUID:J
	return
  Labels:

public scala.actors.Reactor$$anonfun$3(scala.actors.Reactor, scala.Function1);
  Signature: (Lscala/actors/Reactor;Lscala/Function1;)V
  Code:
   Stack=2, Locals=3, Args_size=3
	aload_0
	aload_2
	putfield	Field handlesMessage$1:Lscala/Function1;
	aload_0
	invokespecial	Method java/lang/Object."<init>":()V
	aload_0
	invokestatic	Method scala/Function2$class.$init$:(Lscala/Function2;)V
	return
  Labels:
  LocalVariableTable: 
   Start  Length  Slot  Name   Signature
   0      14      0    this       Lscala/actors/Reactor$$anonfun$3;
   0      14      1    $outer       Lscala/actors/Reactor;


public final java.lang.Object apply(java.lang.Object, java.lang.Object);
  Signature: (Ljava/lang/Object;Ljava/lang/Object;)Ljava/lang/Object;
  Code:
   Stack=3, Locals=4, Args_size=3
	aload_0
	aload_1
	aload_2
	checkcast	class scala/actors/OutputChannel
	invokevirtual	Method apply:(Ljava/lang/Object;Lscala/actors/OutputChannel;)Z
	istore_3
	iload_3
	invokestatic	Method scala/runtime/BoxesRunTime.boxToBoolean:(Z)Ljava/lang/Boolean;
	areturn
  Labels:
  LocalVariableTable: 
   Start  Length  Slot  Name   Signature
   0      15      0    this       Lscala/actors/Reactor$$anonfun$3;
   0      15      1    v1       Ljava/lang/Object;
   0      15      2    v2       Ljava/lang/Object;


public final boolean apply(java.lang.Object, scala.actors.OutputChannel);
  Signature: (Ljava/lang/Object;Lscala/actors/OutputChannel;)Z
  Code:
   Stack=2, Locals=3, Args_size=3
	aload_0
	getfield	Field handlesMessage$1:Lscala/Function1;
	aload_1
	invokeinterface	InterfaceMethod scala/Function1.apply:(Ljava/lang/Object;)Ljava/lang/Object;
	invokestatic	Method scala/runtime/BoxesRunTime.unboxToBoolean:(Ljava/lang/Object;)Z
	ireturn
  Labels:
  LocalVariableTable: 
   Start  Length  Slot  Name   Signature
   0      14      0    this       Lscala/actors/Reactor$$anonfun$3;
   0      14      1    msg       Ljava/lang/Object;
   0      14      2    replyTo       Lscala/actors/OutputChannel;

  Signature: length = 0x2
   00 3E 

public scala.Function1 curry();
  Signature: ()Lscala/Function1;
  Code:
   Stack=1, Locals=1, Args_size=1
	aload_0
	invokestatic	Method scala/Function2$class.curry:(Lscala/Function2;)Lscala/Function1;
	areturn
  Labels:

public java.lang.String toString();
  Signature: ()Ljava/lang/String;
  Code:
   Stack=1, Locals=1, Args_size=1
	aload_0
	invokestatic	Method scala/Function2$class.toString:(Lscala/Function2;)Ljava/lang/String;
	areturn
  Labels:

}

