Compiled from "ReactorCanReply.scala"
public final class scala.actors.ReactorCanReply$$anon$3 extends java.lang.Object implements scala.actors.OutputChannel
  SourceFile: "ReactorCanReply.scala"
  Scala: length = 0x
   
  Signature: length = 0x2
   00 46 
  InnerClass: 
   public final $anon$3=class scala/actors/ReactorCanReply$$anon$3 of class scala/actors/ReactorCanReply
  minor version: 0
  major version: 49
  Constant pool:
Asciz	SourceFile;
Asciz	ReactorCanReply.scala;
Asciz	handler$1;
Asciz	Lscala/PartialFunction;;
Asciz	myself$2;
Asciz	Lscala/actors/ReplyReactor;;
Asciz	ftch$1;
Asciz	Lscala/actors/ReactChannel;;
Asciz	res$2;
Asciz	Lscala/concurrent/SyncVar;;
Asciz	$bang;
Asciz	(Ljava/lang/Object;)V;
Asciz	Code;
Asciz	LineNumberTable;
Asciz	scala/actors/ReactorCanReply$$anon$3;
class	scala/actors/ReactorCanReply$$anon$3
NameAndType	handler$1:Lscala/PartialFunction;
Field	scala/actors/ReactorCanReply$$anon$3.handler$1:Lscala/PartialFunction;
Asciz	scala/Function1;
class	scala/Function1
Asciz	apply;
Asciz	(Ljava/lang/Object;)Ljava/lang/Object;;
NameAndType	apply:(Ljava/lang/Object;)Ljava/lang/Object;
InterfaceMethod	scala/Function1.apply:(Ljava/lang/Object;)Ljava/lang/Object;
NameAndType	ftch$1:Lscala/actors/ReactChannel;
Field	scala/actors/ReactorCanReply$$anon$3.ftch$1:Lscala/actors/ReactChannel;
Asciz	scala/actors/ReactChannel;
class	scala/actors/ReactChannel
NameAndType	$bang:(Ljava/lang/Object;)V
Method	scala/actors/ReactChannel.$bang:(Ljava/lang/Object;)V
NameAndType	res$2:Lscala/concurrent/SyncVar;
Field	scala/actors/ReactorCanReply$$anon$3.res$2:Lscala/concurrent/SyncVar;
Asciz	scala/concurrent/SyncVar;
class	scala/concurrent/SyncVar
Asciz	set;
NameAndType	set:(Ljava/lang/Object;)V
Method	scala/concurrent/SyncVar.set:(Ljava/lang/Object;)V
Asciz	this;
Asciz	Lscala/actors/ReactorCanReply$$anon$3;;
Asciz	msg;
Asciz	Ljava/lang/Object;;
Asciz	msg1;
Asciz	LocalVariableTable;
Asciz	send;
Asciz	(Ljava/lang/Object;Lscala/actors/OutputChannel;)V;
NameAndType	send:(Ljava/lang/Object;Lscala/actors/OutputChannel;)V
Method	scala/actors/ReactChannel.send:(Ljava/lang/Object;Lscala/actors/OutputChannel;)V
Asciz	replyTo;
Asciz	Lscala/actors/OutputChannel;;
Asciz	(Ljava/lang/Object;Lscala/actors/OutputChannel<Ljava/lang/Object;>;)V;
Asciz	Signature;
Asciz	forward;
NameAndType	forward:(Ljava/lang/Object;)V
Method	scala/actors/ReactChannel.forward:(Ljava/lang/Object;)V
Asciz	receiver;
Asciz	()Lscala/actors/Actor;;
NameAndType	myself$2:Lscala/actors/ReplyReactor;
Field	scala/actors/ReactorCanReply$$anon$3.myself$2:Lscala/actors/ReplyReactor;
Asciz	scala/actors/Actor;
class	scala/actors/Actor
Asciz	<init>;
Asciz	(Lscala/actors/ReplyReactor;Lscala/PartialFunction;Lscala/actors/ReplyReactor;Lscala/actors/ReactChannel;Lscala/concurrent/SyncVar;)V;
Asciz	java/lang/Object;
class	java/lang/Object
Asciz	()V;
NameAndType	"<init>":()V
Method	java/lang/Object."<init>":()V
Asciz	$outer;
Asciz	Scala;
Asciz	Ljava/lang/Object;Lscala/actors/OutputChannel<Ljava/lang/Object;>;;
Asciz	InnerClasses;
Asciz	scala/actors/ReactorCanReply;
class	scala/actors/ReactorCanReply
Asciz	$anon$3;
Asciz	scala/actors/OutputChannel;
class	scala/actors/OutputChannel

{
private final scala.PartialFunction handler$1;
  Signature: Lscala/PartialFunction;

private final scala.actors.ReplyReactor myself$2;
  Signature: Lscala/actors/ReplyReactor;

private final scala.actors.ReactChannel ftch$1;
  Signature: Lscala/actors/ReactChannel;

private final scala.concurrent.SyncVar res$2;
  Signature: Lscala/concurrent/SyncVar;

public void $bang(java.lang.Object);
  Signature: (Ljava/lang/Object;)V
  Code:
   Stack=2, Locals=3, Args_size=2
	aload_0
	getfield	Field handler$1:Lscala/PartialFunction;
	aload_1
	invokeinterface	InterfaceMethod scala/Function1.apply:(Ljava/lang/Object;)Ljava/lang/Object;
	astore_2
	aload_0
	getfield	Field ftch$1:Lscala/actors/ReactChannel;
	aload_2
	invokevirtual	Method scala/actors/ReactChannel.$bang:(Ljava/lang/Object;)V
	aload_0
	getfield	Field res$2:Lscala/concurrent/SyncVar;
	aload_2
	invokevirtual	Method scala/concurrent/SyncVar.set:(Ljava/lang/Object;)V
	return
  Labels:
  LocalVariableTable: 
   Start  Length  Slot  Name   Signature
   0      28      0    this       Lscala/actors/ReactorCanReply$$anon$3;
   0      28      1    msg       Ljava/lang/Object;
   11      16      2    msg1       Ljava/lang/Object;


public void send(java.lang.Object, scala.actors.OutputChannel);
  Signature: (Ljava/lang/Object;Lscala/actors/OutputChannel;)V
  Code:
   Stack=3, Locals=4, Args_size=3
	aload_0
	getfield	Field handler$1:Lscala/PartialFunction;
	aload_1
	invokeinterface	InterfaceMethod scala/Function1.apply:(Ljava/lang/Object;)Ljava/lang/Object;
	astore_3
	aload_0
	getfield	Field ftch$1:Lscala/actors/ReactChannel;
	aload_3
	aload_2
	invokevirtual	Method scala/actors/ReactChannel.send:(Ljava/lang/Object;Lscala/actors/OutputChannel;)V
	aload_0
	getfield	Field res$2:Lscala/concurrent/SyncVar;
	aload_3
	invokevirtual	Method scala/concurrent/SyncVar.set:(Ljava/lang/Object;)V
	return
  Labels:
  LocalVariableTable: 
   Start  Length  Slot  Name   Signature
   0      29      0    this       Lscala/actors/ReactorCanReply$$anon$3;
   0      29      1    msg       Ljava/lang/Object;
   0      29      2    replyTo       Lscala/actors/OutputChannel;
   11      17      3    msg1       Ljava/lang/Object;

  Signature: length = 0x2
   00 32 

public void forward(java.lang.Object);
  Signature: (Ljava/lang/Object;)V
  Code:
   Stack=2, Locals=3, Args_size=2
	aload_0
	getfield	Field handler$1:Lscala/PartialFunction;
	aload_1
	invokeinterface	InterfaceMethod scala/Function1.apply:(Ljava/lang/Object;)Ljava/lang/Object;
	astore_2
	aload_0
	getfield	Field ftch$1:Lscala/actors/ReactChannel;
	aload_2
	invokevirtual	Method scala/actors/ReactChannel.forward:(Ljava/lang/Object;)V
	aload_0
	getfield	Field res$2:Lscala/concurrent/SyncVar;
	aload_2
	invokevirtual	Method scala/concurrent/SyncVar.set:(Ljava/lang/Object;)V
	return
  Labels:
  LocalVariableTable: 
   Start  Length  Slot  Name   Signature
   0      28      0    this       Lscala/actors/ReactorCanReply$$anon$3;
   0      28      1    msg       Ljava/lang/Object;
   11      16      2    msg1       Ljava/lang/Object;


public scala.actors.Actor receiver();
  Signature: ()Lscala/actors/Actor;
  Code:
   Stack=1, Locals=1, Args_size=1
	aload_0
	getfield	Field myself$2:Lscala/actors/ReplyReactor;
	checkcast	class scala/actors/Actor
	areturn
  Labels:

public scala.actors.ReactorCanReply$$anon$3(scala.actors.ReplyReactor, scala.PartialFunction, scala.actors.ReplyReactor, scala.actors.ReactChannel, scala.concurrent.SyncVar);
  Signature: (Lscala/actors/ReplyReactor;Lscala/PartialFunction;Lscala/actors/ReplyReactor;Lscala/actors/ReactChannel;Lscala/concurrent/SyncVar;)V
  Code:
   Stack=2, Locals=6, Args_size=6
	aload_0
	aload_2
	putfield	Field handler$1:Lscala/PartialFunction;
	aload_0
	aload_3
	putfield	Field myself$2:Lscala/actors/ReplyReactor;
	aload_0
	aload	4
	putfield	Field ftch$1:Lscala/actors/ReactChannel;
	aload_0
	aload	5
	putfield	Field res$2:Lscala/concurrent/SyncVar;
	aload_0
	invokespecial	Method java/lang/Object."<init>":()V
	return
  Labels:
  LocalVariableTable: 
   Start  Length  Slot  Name   Signature
   0      27      0    this       Lscala/actors/ReactorCanReply$$anon$3;
   0      27      1    $outer       Lscala/actors/ReplyReactor;


}

