Compiled from "Reactor.scala"
public final class scala.actors.Reactor$$anonfun$react$2 extends scala.runtime.AbstractFunction1 implements java.io.Serializable
  SourceFile: "Reactor.scala"
  Scala: length = 0x
   
  InnerClass: 
   public final $anonfun$react$2=class scala/actors/Reactor$$anonfun$react$2 of class scala/actors/Reactor
  minor version: 0
  major version: 49
  Constant pool:
Asciz	SourceFile;
Asciz	Reactor.scala;
Asciz	<clinit>;
Asciz	()V;
Asciz	Code;
Asciz	serialVersionUID;
Asciz	J;
Asciz	scala/actors/Reactor$$anonfun$react$2;
class	scala/actors/Reactor$$anonfun$react$2
NameAndType	serialVersionUID:J
Field	scala/actors/Reactor$$anonfun$react$2.serialVersionUID:J
Asciz	f$1;
Asciz	Lscala/PartialFunction;;
Asciz	<init>;
Asciz	(Lscala/actors/Reactor;Lscala/PartialFunction;)V;
Asciz	LineNumberTable;
NameAndType	f$1:Lscala/PartialFunction;
Field	scala/actors/Reactor$$anonfun$react$2.f$1:Lscala/PartialFunction;
Asciz	scala/runtime/AbstractFunction1;
class	scala/runtime/AbstractFunction1
NameAndType	"<init>":()V
Method	scala/runtime/AbstractFunction1."<init>":()V
Asciz	this;
Asciz	Lscala/actors/Reactor$$anonfun$react$2;;
Asciz	$outer;
Asciz	Lscala/actors/Reactor;;
Asciz	LocalVariableTable;
Asciz	apply;
Asciz	(Ljava/lang/Object;)Ljava/lang/Object;;
Asciz	(Ljava/lang/Object;)Z;
NameAndType	apply:(Ljava/lang/Object;)Z
Method	scala/actors/Reactor$$anonfun$react$2.apply:(Ljava/lang/Object;)Z
Asciz	scala/runtime/BoxesRunTime;
class	scala/runtime/BoxesRunTime
Asciz	boxToBoolean;
Asciz	(Z)Ljava/lang/Boolean;;
NameAndType	boxToBoolean:(Z)Ljava/lang/Boolean;
Method	scala/runtime/BoxesRunTime.boxToBoolean:(Z)Ljava/lang/Boolean;
Asciz	v1;
Asciz	Ljava/lang/Object;;
Asciz	scala/PartialFunction;
class	scala/PartialFunction
Asciz	isDefinedAt;
NameAndType	isDefinedAt:(Ljava/lang/Object;)Z
InterfaceMethod	scala/PartialFunction.isDefinedAt:(Ljava/lang/Object;)Z
Asciz	Scala;
Asciz	InnerClasses;
Asciz	scala/actors/Reactor;
class	scala/actors/Reactor
Asciz	$anonfun$react$2;
Asciz	java/io/Serializable;
class	java/io/Serializable

{
public static final long serialVersionUID;
  Signature: J

public final scala.PartialFunction f$1;
  Signature: Lscala/PartialFunction;

public static {};
  Signature: ()V
  Code:
   Stack=2, Locals=0, Args_size=0
	lconst_0
	putstatic	Field serialVersionUID:J
	return
  Labels:

public scala.actors.Reactor$$anonfun$react$2(scala.actors.Reactor, scala.PartialFunction);
  Signature: (Lscala/actors/Reactor;Lscala/PartialFunction;)V
  Code:
   Stack=2, Locals=3, Args_size=3
	aload_0
	aload_2
	putfield	Field f$1:Lscala/PartialFunction;
	aload_0
	invokespecial	Method scala/runtime/AbstractFunction1."<init>":()V
	return
  Labels:
  LocalVariableTable: 
   Start  Length  Slot  Name   Signature
   0      10      0    this       Lscala/actors/Reactor$$anonfun$react$2;
   0      10      1    $outer       Lscala/actors/Reactor;


public final java.lang.Object apply(java.lang.Object);
  Signature: (Ljava/lang/Object;)Ljava/lang/Object;
  Code:
   Stack=2, Locals=3, Args_size=2
	aload_0
	aload_1
	invokevirtual	Method apply:(Ljava/lang/Object;)Z
	istore_2
	iload_2
	invokestatic	Method scala/runtime/BoxesRunTime.boxToBoolean:(Z)Ljava/lang/Boolean;
	areturn
  Labels:
  LocalVariableTable: 
   Start  Length  Slot  Name   Signature
   0      11      0    this       Lscala/actors/Reactor$$anonfun$react$2;
   0      11      1    v1       Ljava/lang/Object;


public final boolean apply(java.lang.Object);
  Signature: (Ljava/lang/Object;)Z
  Code:
   Stack=2, Locals=2, Args_size=2
	aload_0
	getfield	Field f$1:Lscala/PartialFunction;
	aload_1
	invokeinterface	InterfaceMethod scala/PartialFunction.isDefinedAt:(Ljava/lang/Object;)Z
	ireturn
  Labels:

}

