Compiled from "Reaction.scala"
public class scala.actors.Reaction extends scala.actors.ActorTask implements scala.ScalaObject
  SourceFile: "Reaction.scala"
  ScalaSig: length = 0x12F
   05 00 32 06 08 01 02 FFFFFF84 FFFFFF80 FFFFFF80 FFFFFF80 00 07 02 08 52
   65 61 63 74 69 6F 6E 0A 02 03 04 01 06 61 63 74
   6F 72 73 0A 01 05 01 05 73 63 61 6C 61 03 00 13
   03 00 08 0C 10 02 09 0A 0D 01 02 09 02 0B 02 02
   09 41 63 74 6F 72 54 61 73 6B 10 02 0D 0E 0D 01
   04 09 02 0F 04 02 0B 53 63 61 6C 61 4F 62 6A 65
   63 74 08 08 11 00 FFFFFF82 FFFFFF80 FFFFFFA0 FFFFFF80 04 12 01 01 61 10
   02 09 13 09 02 14 02 02 05 41 63 74 6F 72 08 08
   16 00 FFFFFF82 FFFFFF80 FFFFFFA0 FFFFFF80 04 17 01 01 66 10 04 18 20 23
   23 0E 02 19 1E 0E 02 1A 1D 0D 01 1B 0A 02 1C 06
   01 06 3C 72 6F 6F 74 3E 09 01 05 09 02 1F 04 01
   07 70 61 63 6B 61 67 65 09 02 21 22 02 11 24 65
   71 24 67 72 65 61 74 65 72 24 71 6D 61 72 6B 0A
   02 1F 04 10 02 0D 24 09 02 25 04 02 03 41 6E 79
   08 08 27 00 FFFFFF82 FFFFFF80 FFFFFFA0 FFFFFF80 04 23 01 03 6D 73 67 08
   05 29 00 FFFFFF84 00 2A 01 06 3C 69 6E 69 74 3E 14 04
   2B 2C 2D 2E 10 02 09 00 08 05 11 28 FFFFFFC0 00 12 08
   05 16 28 FFFFFFC0 00 17 08 05 27 28 FFFFFFC0 00 23 08 05 29
   00 FFFFFF84 00 30 14 02 2B 31 08 05 11 2F FFFFFFC0 00 12 
  InnerClass: 
   public final $anonfun$$init$$1=class scala/actors/Reaction$$anonfun$$init$$1 of class scala/actors/Reaction
  minor version: 0
  major version: 49
  Constant pool:
Asciz	SourceFile;
Asciz	Reaction.scala;
Asciz	<init>;
Asciz	(Lscala/actors/Actor;Lscala/PartialFunction;Ljava/lang/Object;)V;
Asciz	Code;
Asciz	LineNumberTable;
Asciz	scala/actors/Reaction$$anonfun$$init$$1;
class	scala/actors/Reaction$$anonfun$$init$$1
NameAndType	"<init>":(Lscala/actors/Actor;Lscala/PartialFunction;Ljava/lang/Object;)V
Method	scala/actors/Reaction$$anonfun$$init$$1."<init>":(Lscala/actors/Actor;Lscala/PartialFunction;Ljava/lang/Object;)V
Asciz	scala/actors/ActorTask;
class	scala/actors/ActorTask
Asciz	(Lscala/actors/Actor;Lscala/Function0;)V;
NameAndType	"<init>":(Lscala/actors/Actor;Lscala/Function0;)V
Method	scala/actors/ActorTask."<init>":(Lscala/actors/Actor;Lscala/Function0;)V
Asciz	this;
Asciz	Lscala/actors/Reaction;;
Asciz	a$1;
Asciz	Lscala/actors/Actor;;
Asciz	f$1;
Asciz	Lscala/PartialFunction;;
Asciz	msg$1;
Asciz	Ljava/lang/Object;;
Asciz	LocalVariableTable;
Asciz	(Lscala/actors/Actor;Lscala/PartialFunction<Ljava/lang/Object;Ljava/lang/Object;>;Ljava/lang/Object;)V;
Asciz	Signature;
Asciz	(Lscala/actors/Actor;)V;
Asciz	scala/actors/Reaction;
class	scala/actors/Reaction
Method	scala/actors/Reaction."<init>":(Lscala/actors/Actor;Lscala/PartialFunction;Ljava/lang/Object;)V
Asciz	a;
Asciz	ScalaSig;
Asciz	InnerClasses;
Asciz	$anonfun$$init$$1;
Asciz	scala/ScalaObject;
class	scala/ScalaObject

{
public scala.actors.Reaction(scala.actors.Actor, scala.PartialFunction, java.lang.Object);
  Signature: (Lscala/actors/Actor;Lscala/PartialFunction;Ljava/lang/Object;)V
  Code:
   Stack=7, Locals=4, Args_size=4
	aload_0
	aload_1
	new	class scala/actors/Reaction$$anonfun$$init$$1
	dup
	aload_1
	aload_2
	aload_3
	invokespecial	Method scala/actors/Reaction$$anonfun$$init$$1."<init>":(Lscala/actors/Actor;Lscala/PartialFunction;Ljava/lang/Object;)V
	invokespecial	Method scala/actors/ActorTask."<init>":(Lscala/actors/Actor;Lscala/Function0;)V
	return
  Labels:
  LocalVariableTable: 
   Start  Length  Slot  Name   Signature
   0      16      0    this       Lscala/actors/Reaction;
   0      16      1    a$1       Lscala/actors/Actor;
   0      16      2    f$1       Lscala/PartialFunction;
   0      16      3    msg$1       Ljava/lang/Object;

  Signature: length = 0x2
   00 19 

public scala.actors.Reaction(scala.actors.Actor);
  Signature: (Lscala/actors/Actor;)V
  Code:
   Stack=4, Locals=2, Args_size=2
	aload_0
	aload_1
	aconst_null
	aconst_null
	invokespecial	Method "<init>":(Lscala/actors/Actor;Lscala/PartialFunction;Ljava/lang/Object;)V
	return
  Labels:
  LocalVariableTable: 
   Start  Length  Slot  Name   Signature
   0      8      0    this       Lscala/actors/Reaction;
   0      8      1    a       Lscala/actors/Actor;


}

