Compiled from "Reactor.scala"
public final class scala.actors.Reactor$$anonfun$startSearch$1$$anonfun$apply$2 extends java.lang.Object implements scala.Function0,scala.ScalaObject,java.io.Serializable
  SourceFile: "Reactor.scala"
  Scala: length = 0x
   
  InnerClass: 
   public final $anonfun$startSearch$1=class scala/actors/Reactor$$anonfun$startSearch$1 of class scala/actors/Reactor
   public final $anonfun$apply$2=class scala/actors/Reactor$$anonfun$startSearch$1$$anonfun$apply$2 of class scala/actors/Reactor$$anonfun$startSearch$1
  minor version: 0
  major version: 49
  Constant pool:
Asciz	SourceFile;
Asciz	Reactor.scala;
Asciz	<clinit>;
Asciz	()V;
Asciz	Code;
Asciz	serialVersionUID;
Asciz	J;
Asciz	scala/actors/Reactor$$anonfun$startSearch$1$$anonfun$apply$2;
class	scala/actors/Reactor$$anonfun$startSearch$1$$anonfun$apply$2
NameAndType	serialVersionUID:J
Field	scala/actors/Reactor$$anonfun$startSearch$1$$anonfun$apply$2.serialVersionUID:J
Asciz	$outer;
Asciz	Lscala/actors/Reactor$$anonfun$startSearch$1;;
Asciz	<init>;
Asciz	(Lscala/actors/Reactor$$anonfun$startSearch$1;)V;
Asciz	LineNumberTable;
Asciz	java/lang/NullPointerException;
class	java/lang/NullPointerException
NameAndType	"<init>":()V
Method	java/lang/NullPointerException."<init>":()V
NameAndType	$outer:Lscala/actors/Reactor$$anonfun$startSearch$1;
Field	scala/actors/Reactor$$anonfun$startSearch$1$$anonfun$apply$2.$outer:Lscala/actors/Reactor$$anonfun$startSearch$1;
Asciz	java/lang/Object;
class	java/lang/Object
Method	java/lang/Object."<init>":()V
Asciz	scala/Function0$class;
class	scala/Function0$class
Asciz	$init$;
Asciz	(Lscala/Function0;)V;
NameAndType	$init$:(Lscala/Function0;)V
Method	scala/Function0$class.$init$:(Lscala/Function0;)V
Asciz	this;
Asciz	Lscala/actors/Reactor$$anonfun$startSearch$1$$anonfun$apply$2;;
Asciz	LocalVariableTable;
Asciz	apply;
Asciz	()Ljava/lang/Object;;
NameAndType	apply:()V
Method	scala/actors/Reactor$$anonfun$startSearch$1$$anonfun$apply$2.apply:()V
Asciz	scala/runtime/BoxedUnit;
class	scala/runtime/BoxedUnit
Asciz	UNIT;
Asciz	Lscala/runtime/BoxedUnit;;
NameAndType	UNIT:Lscala/runtime/BoxedUnit;
Field	scala/runtime/BoxedUnit.UNIT:Lscala/runtime/BoxedUnit;
Asciz	scala/actors/MessageQueue;
class	scala/actors/MessageQueue
Asciz	Start;
String	Start
Asciz	(Ljava/lang/String;)V;
NameAndType	"<init>":(Ljava/lang/String;)V
Method	scala/actors/MessageQueue."<init>":(Ljava/lang/String;)V
Asciz	scala/actors/Reactor$$anonfun$startSearch$1;
class	scala/actors/Reactor$$anonfun$startSearch$1
Asciz	Lscala/actors/Reactor;;
NameAndType	$outer:Lscala/actors/Reactor;
Field	scala/actors/Reactor$$anonfun$startSearch$1.$outer:Lscala/actors/Reactor;
Asciz	msg$1;
Asciz	Ljava/lang/Object;;
NameAndType	msg$1:Ljava/lang/Object;
Field	scala/actors/Reactor$$anonfun$startSearch$1.msg$1:Ljava/lang/Object;
Asciz	replyTo$1;
Asciz	Lscala/actors/OutputChannel;;
NameAndType	replyTo$1:Lscala/actors/OutputChannel;
Field	scala/actors/Reactor$$anonfun$startSearch$1.replyTo$1:Lscala/actors/OutputChannel;
Asciz	append;
Asciz	(Ljava/lang/Object;Lscala/actors/OutputChannel;)V;
NameAndType	append:(Ljava/lang/Object;Lscala/actors/OutputChannel;)V
Method	scala/actors/MessageQueue.append:(Ljava/lang/Object;Lscala/actors/OutputChannel;)V
Asciz	handler$1;
Asciz	Lscala/Function1;;
NameAndType	handler$1:Lscala/Function1;
Field	scala/actors/Reactor$$anonfun$startSearch$1.handler$1:Lscala/Function1;
Asciz	scala/actors/Reactor;
class	scala/actors/Reactor
Asciz	searchMailbox;
Asciz	(Lscala/actors/MessageQueue;Lscala/Function1;Z)V;
NameAndType	searchMailbox:(Lscala/actors/MessageQueue;Lscala/Function1;Z)V
InterfaceMethod	scala/actors/Reactor.searchMailbox:(Lscala/actors/MessageQueue;Lscala/Function1;Z)V
Asciz	startMbox;
Asciz	Lscala/actors/MessageQueue;;
Asciz	toString;
Asciz	()Ljava/lang/String;;
Asciz	(Lscala/Function0;)Ljava/lang/String;;
NameAndType	toString:(Lscala/Function0;)Ljava/lang/String;
Method	scala/Function0$class.toString:(Lscala/Function0;)Ljava/lang/String;
Asciz	Scala;
Asciz	InnerClasses;
Asciz	$anonfun$startSearch$1;
Asciz	$anonfun$apply$2;
Asciz	scala/Function0;
class	scala/Function0
Asciz	scala/ScalaObject;
class	scala/ScalaObject
Asciz	java/io/Serializable;
class	java/io/Serializable

{
public static final long serialVersionUID;
  Signature: J

private final scala.actors.Reactor$$anonfun$startSearch$1 $outer;
  Signature: Lscala/actors/Reactor$$anonfun$startSearch$1;

public static {};
  Signature: ()V
  Code:
   Stack=2, Locals=0, Args_size=0
	lconst_0
	putstatic	Field serialVersionUID:J
	return
  Labels:

public scala.actors.Reactor$$anonfun$startSearch$1$$anonfun$apply$2(scala.actors.Reactor$$anonfun$startSearch$1);
  Signature: (Lscala/actors/Reactor$$anonfun$startSearch$1;)V
  Code:
   Stack=2, Locals=2, Args_size=2
	aload_1
	ifnonnull	l1 // aload_0
	new	class java/lang/NullPointerException
	dup
	invokespecial	Method java/lang/NullPointerException."<init>":()V
	athrow
l1	aload_0
	aload_1
	putfield	Field $outer:Lscala/actors/Reactor$$anonfun$startSearch$1;
	aload_0
	invokespecial	Method java/lang/Object."<init>":()V
	aload_0
	invokestatic	Method scala/Function0$class.$init$:(Lscala/Function0;)V
	return
  Labels:
   	l1 = 12 // aload_0
  LocalVariableTable: 
   Start  Length  Slot  Name   Signature
   0      26      0    this       Lscala/actors/Reactor$$anonfun$startSearch$1$$anonfun$apply$2;
   0      26      1    $outer       Lscala/actors/Reactor$$anonfun$startSearch$1;


public final java.lang.Object apply();
  Signature: ()Ljava/lang/Object;
  Code:
   Stack=1, Locals=2, Args_size=1
	aload_0
	getfield	Field $outer:Lscala/actors/Reactor$$anonfun$startSearch$1;
	astore_1
	aload_0
	invokevirtual	Method apply:()V
	getstatic	Field scala/runtime/BoxedUnit.UNIT:Lscala/runtime/BoxedUnit;
	areturn
  Labels:
  LocalVariableTable: 
   Start  Length  Slot  Name   Signature
   0      13      0    this       Lscala/actors/Reactor$$anonfun$startSearch$1$$anonfun$apply$2;


public final void apply();
  Signature: ()V
  Code:
   Stack=4, Locals=6, Args_size=1
	aload_0
	getfield	Field $outer:Lscala/actors/Reactor$$anonfun$startSearch$1;
	astore	5
	new	class scala/actors/MessageQueue
	dup
	ldc	String Start
	invokespecial	Method scala/actors/MessageQueue."<init>":(Ljava/lang/String;)V
	astore_3
	aload_0
	getfield	Field $outer:Lscala/actors/Reactor$$anonfun$startSearch$1;
	astore_1
	aload_1
	getfield	Field scala/actors/Reactor$$anonfun$startSearch$1.$outer:Lscala/actors/Reactor;
	dup
	astore	4
	monitorenter
	aload_3
	aload_0
	getfield	Field $outer:Lscala/actors/Reactor$$anonfun$startSearch$1;
	getfield	Field scala/actors/Reactor$$anonfun$startSearch$1.msg$1:Ljava/lang/Object;
	aload_0
	getfield	Field $outer:Lscala/actors/Reactor$$anonfun$startSearch$1;
	getfield	Field scala/actors/Reactor$$anonfun$startSearch$1.replyTo$1:Lscala/actors/OutputChannel;
	invokevirtual	Method scala/actors/MessageQueue.append:(Ljava/lang/Object;Lscala/actors/OutputChannel;)V
	aload	4
	monitorexit
	aload_0
	getfield	Field $outer:Lscala/actors/Reactor$$anonfun$startSearch$1;
	astore_2
	aload_2
	getfield	Field scala/actors/Reactor$$anonfun$startSearch$1.$outer:Lscala/actors/Reactor;
	aload_3
	aload_0
	getfield	Field $outer:Lscala/actors/Reactor$$anonfun$startSearch$1;
	getfield	Field scala/actors/Reactor$$anonfun$startSearch$1.handler$1:Lscala/Function1;
	iconst_1
	invokeinterface	InterfaceMethod scala/actors/Reactor.searchMailbox:(Lscala/actors/MessageQueue;Lscala/Function1;Z)V
	return
	aload	4
	monitorexit
	athrow
  Labels:
  Exception table:
   from   to  target type
    29    50    74   any
  LocalVariableTable: 
   Start  Length  Slot  Name   Signature
   0      78      0    this       Lscala/actors/Reactor$$anonfun$startSearch$1$$anonfun$apply$2;
   16      57      3    startMbox       Lscala/actors/MessageQueue;
   74      4      3    startMbox       Lscala/actors/MessageQueue;


public java.lang.String toString();
  Signature: ()Ljava/lang/String;
  Code:
   Stack=1, Locals=1, Args_size=1
	aload_0
	invokestatic	Method scala/Function0$class.toString:(Lscala/Function0;)Ljava/lang/String;
	areturn
  Labels:

}

