Compiled from "Reactor.scala"
public final class scala.actors.Reactor$$anonfun$startSearch$1$$anonfun$apply$2 extends java.lang.Object implements scala.Function0,scala.ScalaObject,java.io.Serializable
  SourceFile: "Reactor.scala"
  Scala: length = 0x
   
  InnerClass: 
   public final #88= #53 of #74; //$anonfun$startSearch$1=class scala/actors/Reactor$$anonfun$startSearch$1 of class scala/actors/Reactor
   public final #89= #9 of #53; //$anonfun$apply$2=class scala/actors/Reactor$$anonfun$startSearch$1$$anonfun$apply$2 of class scala/actors/Reactor$$anonfun$startSearch$1
  minor version: 0
  major version: 49
  Constant pool:
const #1 = Asciz	SourceFile;
const #2 = Asciz	Reactor.scala;
const #3 = Asciz	<clinit>;
const #4 = Asciz	()V;
const #5 = Asciz	Code;
const #6 = Asciz	serialVersionUID;
const #7 = Asciz	J;
const #8 = Asciz	scala/actors/Reactor$$anonfun$startSearch$1$$anonfun$apply$2;
const #9 = class	#8;	//  scala/actors/Reactor$$anonfun$startSearch$1$$anonfun$apply$2
const #10 = NameAndType	#6:#7;//  serialVersionUID:J
const #11 = Field	#9.#10;	//  scala/actors/Reactor$$anonfun$startSearch$1$$anonfun$apply$2.serialVersionUID:J
const #12 = Asciz	$outer;
const #13 = Asciz	Lscala/actors/Reactor$$anonfun$startSearch$1;;
const #14 = Asciz	<init>;
const #15 = Asciz	(Lscala/actors/Reactor$$anonfun$startSearch$1;)V;
const #16 = Asciz	LineNumberTable;
const #17 = Asciz	java/lang/NullPointerException;
const #18 = class	#17;	//  java/lang/NullPointerException
const #19 = NameAndType	#14:#4;//  "<init>":()V
const #20 = Method	#18.#19;	//  java/lang/NullPointerException."<init>":()V
const #21 = NameAndType	#12:#13;//  $outer:Lscala/actors/Reactor$$anonfun$startSearch$1;
const #22 = Field	#9.#21;	//  scala/actors/Reactor$$anonfun$startSearch$1$$anonfun$apply$2.$outer:Lscala/actors/Reactor$$anonfun$startSearch$1;
const #23 = Asciz	java/lang/Object;
const #24 = class	#23;	//  java/lang/Object
const #25 = Method	#24.#19;	//  java/lang/Object."<init>":()V
const #26 = Asciz	scala/Function0$class;
const #27 = class	#26;	//  scala/Function0$class
const #28 = Asciz	$init$;
const #29 = Asciz	(Lscala/Function0;)V;
const #30 = NameAndType	#28:#29;//  $init$:(Lscala/Function0;)V
const #31 = Method	#27.#30;	//  scala/Function0$class.$init$:(Lscala/Function0;)V
const #32 = Asciz	this;
const #33 = Asciz	Lscala/actors/Reactor$$anonfun$startSearch$1$$anonfun$apply$2;;
const #34 = Asciz	LocalVariableTable;
const #35 = Asciz	apply;
const #36 = Asciz	()Ljava/lang/Object;;
const #37 = NameAndType	#35:#4;//  apply:()V
const #38 = Method	#9.#37;	//  scala/actors/Reactor$$anonfun$startSearch$1$$anonfun$apply$2.apply:()V
const #39 = Asciz	scala/runtime/BoxedUnit;
const #40 = class	#39;	//  scala/runtime/BoxedUnit
const #41 = Asciz	UNIT;
const #42 = Asciz	Lscala/runtime/BoxedUnit;;
const #43 = NameAndType	#41:#42;//  UNIT:Lscala/runtime/BoxedUnit;
const #44 = Field	#40.#43;	//  scala/runtime/BoxedUnit.UNIT:Lscala/runtime/BoxedUnit;
const #45 = Asciz	scala/actors/MessageQueue;
const #46 = class	#45;	//  scala/actors/MessageQueue
const #47 = Asciz	Start;
const #48 = String	#47;	//  Start
const #49 = Asciz	(Ljava/lang/String;)V;
const #50 = NameAndType	#14:#49;//  "<init>":(Ljava/lang/String;)V
const #51 = Method	#46.#50;	//  scala/actors/MessageQueue."<init>":(Ljava/lang/String;)V
const #52 = Asciz	scala/actors/Reactor$$anonfun$startSearch$1;
const #53 = class	#52;	//  scala/actors/Reactor$$anonfun$startSearch$1
const #54 = Asciz	Lscala/actors/Reactor;;
const #55 = NameAndType	#12:#54;//  $outer:Lscala/actors/Reactor;
const #56 = Field	#53.#55;	//  scala/actors/Reactor$$anonfun$startSearch$1.$outer:Lscala/actors/Reactor;
const #57 = Asciz	msg$1;
const #58 = Asciz	Ljava/lang/Object;;
const #59 = NameAndType	#57:#58;//  msg$1:Ljava/lang/Object;
const #60 = Field	#53.#59;	//  scala/actors/Reactor$$anonfun$startSearch$1.msg$1:Ljava/lang/Object;
const #61 = Asciz	replyTo$1;
const #62 = Asciz	Lscala/actors/OutputChannel;;
const #63 = NameAndType	#61:#62;//  replyTo$1:Lscala/actors/OutputChannel;
const #64 = Field	#53.#63;	//  scala/actors/Reactor$$anonfun$startSearch$1.replyTo$1:Lscala/actors/OutputChannel;
const #65 = Asciz	append;
const #66 = Asciz	(Ljava/lang/Object;Lscala/actors/OutputChannel;)V;
const #67 = NameAndType	#65:#66;//  append:(Ljava/lang/Object;Lscala/actors/OutputChannel;)V
const #68 = Method	#46.#67;	//  scala/actors/MessageQueue.append:(Ljava/lang/Object;Lscala/actors/OutputChannel;)V
const #69 = Asciz	handler$1;
const #70 = Asciz	Lscala/Function1;;
const #71 = NameAndType	#69:#70;//  handler$1:Lscala/Function1;
const #72 = Field	#53.#71;	//  scala/actors/Reactor$$anonfun$startSearch$1.handler$1:Lscala/Function1;
const #73 = Asciz	scala/actors/Reactor;
const #74 = class	#73;	//  scala/actors/Reactor
const #75 = Asciz	searchMailbox;
const #76 = Asciz	(Lscala/actors/MessageQueue;Lscala/Function1;Z)V;
const #77 = NameAndType	#75:#76;//  searchMailbox:(Lscala/actors/MessageQueue;Lscala/Function1;Z)V
const #78 = InterfaceMethod	#74.#77;	//  scala/actors/Reactor.searchMailbox:(Lscala/actors/MessageQueue;Lscala/Function1;Z)V
const #79 = Asciz	startMbox;
const #80 = Asciz	Lscala/actors/MessageQueue;;
const #81 = Asciz	toString;
const #82 = Asciz	()Ljava/lang/String;;
const #83 = Asciz	(Lscala/Function0;)Ljava/lang/String;;
const #84 = NameAndType	#81:#83;//  toString:(Lscala/Function0;)Ljava/lang/String;
const #85 = Method	#27.#84;	//  scala/Function0$class.toString:(Lscala/Function0;)Ljava/lang/String;
const #86 = Asciz	Scala;
const #87 = Asciz	InnerClasses;
const #88 = Asciz	$anonfun$startSearch$1;
const #89 = Asciz	$anonfun$apply$2;
const #90 = Asciz	scala/Function0;
const #91 = class	#90;	//  scala/Function0
const #92 = Asciz	scala/ScalaObject;
const #93 = class	#92;	//  scala/ScalaObject
const #94 = Asciz	java/io/Serializable;
const #95 = class	#94;	//  java/io/Serializable

{
public static final long serialVersionUID;

public static {};
  Code:
   Stack=2, Locals=0, Args_size=0
   0:	lconst_0
   1:	putstatic	#11; //Field serialVersionUID:J
   4:	return

public scala.actors.Reactor$$anonfun$startSearch$1$$anonfun$apply$2(scala.actors.Reactor$$anonfun$startSearch$1);
  Code:
   Stack=2, Locals=2, Args_size=2
   0:	aload_1
   1:	ifnonnull	12
   4:	new	#18; //class java/lang/NullPointerException
   7:	dup
   8:	invokespecial	#20; //Method java/lang/NullPointerException."<init>":()V
   11:	athrow
   12:	aload_0
   13:	aload_1
   14:	putfield	#22; //Field $outer:Lscala/actors/Reactor$$anonfun$startSearch$1;
   17:	aload_0
   18:	invokespecial	#25; //Method java/lang/Object."<init>":()V
   21:	aload_0
   22:	invokestatic	#31; //Method scala/Function0$class.$init$:(Lscala/Function0;)V
   25:	return
  LineNumberTable: 
   line 95: 0

  LocalVariableTable: 
   Start  Length  Slot  Name   Signature
   0      26      0    this       Lscala/actors/Reactor$$anonfun$startSearch$1$$anonfun$apply$2;
   0      26      1    $outer       Lscala/actors/Reactor$$anonfun$startSearch$1;


public final java.lang.Object apply();
  Code:
   Stack=1, Locals=2, Args_size=1
   0:	aload_0
   1:	getfield	#22; //Field $outer:Lscala/actors/Reactor$$anonfun$startSearch$1;
   4:	astore_1
   5:	aload_0
   6:	invokevirtual	#38; //Method apply:()V
   9:	getstatic	#44; //Field scala/runtime/BoxedUnit.UNIT:Lscala/runtime/BoxedUnit;
   12:	areturn
  LineNumberTable: 
   line 95: 0

  LocalVariableTable: 
   Start  Length  Slot  Name   Signature
   0      13      0    this       Lscala/actors/Reactor$$anonfun$startSearch$1$$anonfun$apply$2;


public final void apply();
  Code:
   Stack=4, Locals=6, Args_size=1
   0:	aload_0
   1:	getfield	#22; //Field $outer:Lscala/actors/Reactor$$anonfun$startSearch$1;
   4:	astore	5
   6:	new	#46; //class scala/actors/MessageQueue
   9:	dup
   10:	ldc	#48; //String Start
   12:	invokespecial	#51; //Method scala/actors/MessageQueue."<init>":(Ljava/lang/String;)V
   15:	astore_3
   16:	aload_0
   17:	getfield	#22; //Field $outer:Lscala/actors/Reactor$$anonfun$startSearch$1;
   20:	astore_1
   21:	aload_1
   22:	getfield	#56; //Field scala/actors/Reactor$$anonfun$startSearch$1.$outer:Lscala/actors/Reactor;
   25:	dup
   26:	astore	4
   28:	monitorenter
   29:	aload_3
   30:	aload_0
   31:	getfield	#22; //Field $outer:Lscala/actors/Reactor$$anonfun$startSearch$1;
   34:	getfield	#60; //Field scala/actors/Reactor$$anonfun$startSearch$1.msg$1:Ljava/lang/Object;
   37:	aload_0
   38:	getfield	#22; //Field $outer:Lscala/actors/Reactor$$anonfun$startSearch$1;
   41:	getfield	#64; //Field scala/actors/Reactor$$anonfun$startSearch$1.replyTo$1:Lscala/actors/OutputChannel;
   44:	invokevirtual	#68; //Method scala/actors/MessageQueue.append:(Ljava/lang/Object;Lscala/actors/OutputChannel;)V
   47:	aload	4
   49:	monitorexit
   50:	aload_0
   51:	getfield	#22; //Field $outer:Lscala/actors/Reactor$$anonfun$startSearch$1;
   54:	astore_2
   55:	aload_2
   56:	getfield	#56; //Field scala/actors/Reactor$$anonfun$startSearch$1.$outer:Lscala/actors/Reactor;
   59:	aload_3
   60:	aload_0
   61:	getfield	#22; //Field $outer:Lscala/actors/Reactor$$anonfun$startSearch$1;
   64:	getfield	#72; //Field scala/actors/Reactor$$anonfun$startSearch$1.handler$1:Lscala/Function1;
   67:	iconst_1
   68:	invokeinterface	#78,  4; //InterfaceMethod scala/actors/Reactor.searchMailbox:(Lscala/actors/MessageQueue;Lscala/Function1;Z)V
   73:	return
   74:	aload	4
   76:	monitorexit
   77:	athrow
  Exception table:
   from   to  target type
    29    50    74   any
  LineNumberTable: 
   line 96: 0
   line 97: 16
   line 98: 50
   line 97: 76

  LocalVariableTable: 
   Start  Length  Slot  Name   Signature
   0      78      0    this       Lscala/actors/Reactor$$anonfun$startSearch$1$$anonfun$apply$2;
   16      57      3    startMbox       Lscala/actors/MessageQueue;
   74      4      3    startMbox       Lscala/actors/MessageQueue;


public java.lang.String toString();
  Code:
   Stack=1, Locals=1, Args_size=1
   0:	aload_0
   1:	invokestatic	#85; //Method scala/Function0$class.toString:(Lscala/Function0;)Ljava/lang/String;
   4:	areturn
  LineNumberTable: 
   line 95: 0


}

