Compiled from "Reactor.scala"
public final class scala.actors.Reactor$$anonfun$seq$1 extends java.lang.Object implements scala.Function0,scala.ScalaObject,java.io.Serializable
  SourceFile: "Reactor.scala"
  Scala: length = 0x
   
  InnerClass: 
   public final $anonfun$seq$1=class scala/actors/Reactor$$anonfun$seq$1 of class scala/actors/Reactor
   public final $anonfun$apply$1=class scala/actors/Reactor$$anonfun$seq$1$$anonfun$apply$1 of class scala/actors/Reactor$$anonfun$seq$1
  minor version: 0
  major version: 49
  Constant pool:
Asciz	SourceFile;
Asciz	Reactor.scala;
Asciz	<clinit>;
Asciz	()V;
Asciz	Code;
Asciz	serialVersionUID;
Asciz	J;
Asciz	scala/actors/Reactor$$anonfun$seq$1;
class	scala/actors/Reactor$$anonfun$seq$1
NameAndType	serialVersionUID:J
Field	scala/actors/Reactor$$anonfun$seq$1.serialVersionUID:J
Asciz	killNext$1;
Asciz	Lscala/Function0;;
Asciz	s$1;
Asciz	Lscala/actors/Reactor;;
Asciz	next$1;
Asciz	$outer;
Asciz	<init>;
Asciz	(Lscala/actors/Reactor;Lscala/Function0;Lscala/actors/Reactor;Lscala/Function0;)V;
Asciz	LineNumberTable;
Asciz	java/lang/NullPointerException;
class	java/lang/NullPointerException
NameAndType	"<init>":()V
Method	java/lang/NullPointerException."<init>":()V
NameAndType	$outer:Lscala/actors/Reactor;
Field	scala/actors/Reactor$$anonfun$seq$1.$outer:Lscala/actors/Reactor;
NameAndType	next$1:Lscala/Function0;
Field	scala/actors/Reactor$$anonfun$seq$1.next$1:Lscala/Function0;
NameAndType	s$1:Lscala/actors/Reactor;
Field	scala/actors/Reactor$$anonfun$seq$1.s$1:Lscala/actors/Reactor;
NameAndType	killNext$1:Lscala/Function0;
Field	scala/actors/Reactor$$anonfun$seq$1.killNext$1:Lscala/Function0;
Asciz	java/lang/Object;
class	java/lang/Object
Method	java/lang/Object."<init>":()V
Asciz	scala/Function0$class;
class	scala/Function0$class
Asciz	$init$;
Asciz	(Lscala/Function0;)V;
NameAndType	$init$:(Lscala/Function0;)V
Method	scala/Function0$class.$init$:(Lscala/Function0;)V
Asciz	this;
Asciz	Lscala/actors/Reactor$$anonfun$seq$1;;
Asciz	LocalVariableTable;
Asciz	apply;
Asciz	()Ljava/lang/Object;;
Asciz	()Lscala/runtime/Nothing$;;
NameAndType	apply:()Lscala/runtime/Nothing$;
Method	scala/actors/Reactor$$anonfun$seq$1.apply:()Lscala/runtime/Nothing$;
Asciz	scala/actors/Reactor;
class	scala/actors/Reactor
Asciz	kill_$eq;
NameAndType	kill_$eq:(Lscala/Function0;)V
InterfaceMethod	scala/actors/Reactor.kill_$eq:(Lscala/Function0;)V
Asciz	scala/actors/Reactor$$anonfun$seq$1$$anonfun$apply$1;
class	scala/actors/Reactor$$anonfun$seq$1$$anonfun$apply$1
Asciz	(Lscala/actors/Reactor$$anonfun$seq$1;)V;
NameAndType	"<init>":(Lscala/actors/Reactor$$anonfun$seq$1;)V
Method	scala/actors/Reactor$$anonfun$seq$1$$anonfun$apply$1."<init>":(Lscala/actors/Reactor$$anonfun$seq$1;)V
Asciz	scala/runtime/BoxesRunTime;
class	scala/runtime/BoxesRunTime
Asciz	boxToInteger;
Asciz	(I)Ljava/lang/Integer;;
NameAndType	boxToInteger:(I)Ljava/lang/Integer;
Method	scala/runtime/BoxesRunTime.boxToInteger:(I)Ljava/lang/Integer;
Asciz	scheduleActor;
Asciz	(Lscala/PartialFunction;Ljava/lang/Object;)V;
NameAndType	scheduleActor:(Lscala/PartialFunction;Ljava/lang/Object;)V
InterfaceMethod	scala/actors/Reactor.scheduleActor:(Lscala/PartialFunction;Ljava/lang/Object;)V
Asciz	scala/actors/Actor$;
class	scala/actors/Actor$
Asciz	MODULE$;
Asciz	Lscala/actors/Actor$;;
NameAndType	MODULE$:Lscala/actors/Actor$;
Field	scala/actors/Actor$.MODULE$:Lscala/actors/Actor$;
Asciz	suspendException;
Asciz	()Lscala/actors/SuspendActorException;;
NameAndType	suspendException:()Lscala/actors/SuspendActorException;
Method	scala/actors/Actor$.suspendException:()Lscala/actors/SuspendActorException;
Asciz	toString;
Asciz	()Ljava/lang/String;;
Asciz	(Lscala/Function0;)Ljava/lang/String;;
NameAndType	toString:(Lscala/Function0;)Ljava/lang/String;
Method	scala/Function0$class.toString:(Lscala/Function0;)Ljava/lang/String;
Asciz	Scala;
Asciz	InnerClasses;
Asciz	$anonfun$seq$1;
Asciz	$anonfun$apply$1;
Asciz	scala/Function0;
class	scala/Function0
Asciz	scala/ScalaObject;
class	scala/ScalaObject
Asciz	java/io/Serializable;
class	java/io/Serializable

{
public static final long serialVersionUID;
  Signature: J

private final scala.Function0 killNext$1;
  Signature: Lscala/Function0;

private final scala.actors.Reactor s$1;
  Signature: Lscala/actors/Reactor;

public final scala.Function0 next$1;
  Signature: Lscala/Function0;

private final scala.actors.Reactor $outer;
  Signature: Lscala/actors/Reactor;

public static {};
  Signature: ()V
  Code:
   Stack=2, Locals=0, Args_size=0
	lconst_0
	putstatic	Field serialVersionUID:J
	return
  Labels:

public scala.actors.Reactor$$anonfun$seq$1(scala.actors.Reactor, scala.Function0, scala.actors.Reactor, scala.Function0);
  Signature: (Lscala/actors/Reactor;Lscala/Function0;Lscala/actors/Reactor;Lscala/Function0;)V
  Code:
   Stack=2, Locals=5, Args_size=5
	aload_1
	ifnonnull	l1 // aload_0
	new	class java/lang/NullPointerException
	dup
	invokespecial	Method java/lang/NullPointerException."<init>":()V
	athrow
l1	aload_0
	aload_1
	putfield	Field $outer:Lscala/actors/Reactor;
	aload_0
	aload_2
	putfield	Field next$1:Lscala/Function0;
	aload_0
	aload_3
	putfield	Field s$1:Lscala/actors/Reactor;
	aload_0
	aload	4
	putfield	Field killNext$1:Lscala/Function0;
	aload_0
	invokespecial	Method java/lang/Object."<init>":()V
	aload_0
	invokestatic	Method scala/Function0$class.$init$:(Lscala/Function0;)V
	return
  Labels:
   	l1 = 12 // aload_0
  LocalVariableTable: 
   Start  Length  Slot  Name   Signature
   0      42      0    this       Lscala/actors/Reactor$$anonfun$seq$1;
   0      42      1    $outer       Lscala/actors/Reactor;


public final java.lang.Object apply();
  Signature: ()Ljava/lang/Object;
  Code:
   Stack=1, Locals=2, Args_size=1
	aload_0
	getfield	Field $outer:Lscala/actors/Reactor;
	astore_1
	aload_0
	invokevirtual	Method apply:()Lscala/runtime/Nothing$;
	athrow
  Labels:
  LocalVariableTable: 
   Start  Length  Slot  Name   Signature
   0      10      0    this       Lscala/actors/Reactor$$anonfun$seq$1;


public final scala.runtime.Nothing$ apply();
  Signature: ()Lscala/runtime/Nothing$;
  Code:
   Stack=4, Locals=3, Args_size=1
	aload_0
	getfield	Field $outer:Lscala/actors/Reactor;
	astore_2
	aload_0
	getfield	Field s$1:Lscala/actors/Reactor;
	aload_0
	getfield	Field killNext$1:Lscala/Function0;
	invokeinterface	InterfaceMethod scala/actors/Reactor.kill_$eq:(Lscala/Function0;)V
	aload_0
	getfield	Field $outer:Lscala/actors/Reactor;
	new	class scala/actors/Reactor$$anonfun$seq$1$$anonfun$apply$1
	dup
	aload_0
	invokespecial	Method scala/actors/Reactor$$anonfun$seq$1$$anonfun$apply$1."<init>":(Lscala/actors/Reactor$$anonfun$seq$1;)V
	iconst_1
	istore_1
	iload_1
	invokestatic	Method scala/runtime/BoxesRunTime.boxToInteger:(I)Ljava/lang/Integer;
	invokeinterface	InterfaceMethod scala/actors/Reactor.scheduleActor:(Lscala/PartialFunction;Ljava/lang/Object;)V
	getstatic	Field scala/actors/Actor$.MODULE$:Lscala/actors/Actor$;
	invokevirtual	Method scala/actors/Actor$.suspendException:()Lscala/actors/SuspendActorException;
	athrow
  Labels:
  LocalVariableTable: 
   Start  Length  Slot  Name   Signature
   0      48      0    this       Lscala/actors/Reactor$$anonfun$seq$1;


public java.lang.String toString();
  Signature: ()Ljava/lang/String;
  Code:
   Stack=1, Locals=1, Args_size=1
	aload_0
	invokestatic	Method scala/Function0$class.toString:(Lscala/Function0;)Ljava/lang/String;
	areturn
  Labels:

}

