Compiled from "Reactor.scala"
public final class scala.actors.Reactor$$anonfun$6 extends java.lang.Object implements scala.Function0,scala.ScalaObject,java.io.Serializable
  SourceFile: "Reactor.scala"
  Scala: length = 0x
   
  InnerClass: 
   public final $anonfun$6=class scala/actors/Reactor$$anonfun$6 of class scala/actors/Reactor
  minor version: 0
  major version: 49
  Constant pool:
Asciz	SourceFile;
Asciz	Reactor.scala;
Asciz	<clinit>;
Asciz	()V;
Asciz	Code;
Asciz	serialVersionUID;
Asciz	J;
Asciz	scala/actors/Reactor$$anonfun$6;
class	scala/actors/Reactor$$anonfun$6
NameAndType	serialVersionUID:J
Field	scala/actors/Reactor$$anonfun$6.serialVersionUID:J
Asciz	$outer;
Asciz	Lscala/actors/Reactor;;
Asciz	<init>;
Asciz	(Lscala/actors/Reactor;)V;
Asciz	LineNumberTable;
Asciz	java/lang/NullPointerException;
class	java/lang/NullPointerException
NameAndType	"<init>":()V
Method	java/lang/NullPointerException."<init>":()V
NameAndType	$outer:Lscala/actors/Reactor;
Field	scala/actors/Reactor$$anonfun$6.$outer:Lscala/actors/Reactor;
Asciz	java/lang/Object;
class	java/lang/Object
Method	java/lang/Object."<init>":()V
Asciz	scala/Function0$class;
class	scala/Function0$class
Asciz	$init$;
Asciz	(Lscala/Function0;)V;
NameAndType	$init$:(Lscala/Function0;)V
Method	scala/Function0$class.$init$:(Lscala/Function0;)V
Asciz	this;
Asciz	Lscala/actors/Reactor$$anonfun$6;;
Asciz	LocalVariableTable;
Asciz	apply;
Asciz	()Ljava/lang/Object;;
Asciz	()Lscala/runtime/Nothing$;;
NameAndType	apply:()Lscala/runtime/Nothing$;
Method	scala/actors/Reactor$$anonfun$6.apply:()Lscala/runtime/Nothing$;
Asciz	scala/actors/Reactor;
class	scala/actors/Reactor
Asciz	exit;
NameAndType	exit:()Lscala/runtime/Nothing$;
InterfaceMethod	scala/actors/Reactor.exit:()Lscala/runtime/Nothing$;
Asciz	toString;
Asciz	()Ljava/lang/String;;
Asciz	(Lscala/Function0;)Ljava/lang/String;;
NameAndType	toString:(Lscala/Function0;)Ljava/lang/String;
Method	scala/Function0$class.toString:(Lscala/Function0;)Ljava/lang/String;
Asciz	Scala;
Asciz	InnerClasses;
Asciz	$anonfun$6;
Asciz	scala/Function0;
class	scala/Function0
Asciz	scala/ScalaObject;
class	scala/ScalaObject
Asciz	java/io/Serializable;
class	java/io/Serializable

{
public static final long serialVersionUID;
  Signature: J

private final scala.actors.Reactor $outer;
  Signature: Lscala/actors/Reactor;

public static {};
  Signature: ()V
  Code:
   Stack=2, Locals=0, Args_size=0
	lconst_0
	putstatic	Field serialVersionUID:J
	return
  Labels:

public scala.actors.Reactor$$anonfun$6(scala.actors.Reactor);
  Signature: (Lscala/actors/Reactor;)V
  Code:
   Stack=2, Locals=2, Args_size=2
	aload_1
	ifnonnull	l1 // aload_0
	new	class java/lang/NullPointerException
	dup
	invokespecial	Method java/lang/NullPointerException."<init>":()V
	athrow
l1	aload_0
	aload_1
	putfield	Field $outer:Lscala/actors/Reactor;
	aload_0
	invokespecial	Method java/lang/Object."<init>":()V
	aload_0
	invokestatic	Method scala/Function0$class.$init$:(Lscala/Function0;)V
	return
  Labels:
   	l1 = 12 // aload_0
  LocalVariableTable: 
   Start  Length  Slot  Name   Signature
   0      26      0    this       Lscala/actors/Reactor$$anonfun$6;
   0      26      1    $outer       Lscala/actors/Reactor;


public final java.lang.Object apply();
  Signature: ()Ljava/lang/Object;
  Code:
   Stack=1, Locals=2, Args_size=1
	aload_0
	getfield	Field $outer:Lscala/actors/Reactor;
	astore_1
	aload_0
	invokevirtual	Method apply:()Lscala/runtime/Nothing$;
	athrow
  Labels:
  LocalVariableTable: 
   Start  Length  Slot  Name   Signature
   0      10      0    this       Lscala/actors/Reactor$$anonfun$6;


public final scala.runtime.Nothing$ apply();
  Signature: ()Lscala/runtime/Nothing$;
  Code:
   Stack=1, Locals=2, Args_size=1
	aload_0
	getfield	Field $outer:Lscala/actors/Reactor;
	astore_1
	aload_0
	getfield	Field $outer:Lscala/actors/Reactor;
	invokeinterface	InterfaceMethod scala/actors/Reactor.exit:()Lscala/runtime/Nothing$;
	areturn
  Labels:
  LocalVariableTable: 
   Start  Length  Slot  Name   Signature
   0      15      0    this       Lscala/actors/Reactor$$anonfun$6;


public java.lang.String toString();
  Signature: ()Ljava/lang/String;
  Code:
   Stack=1, Locals=1, Args_size=1
	aload_0
	invokestatic	Method scala/Function0$class.toString:(Lscala/Function0;)Ljava/lang/String;
	areturn
  Labels:

}

