Compiled from "Reactor.scala"
public final class scala.actors.Reactor$$anonfun$startSearch$1 extends java.lang.Object implements scala.Function0,scala.ScalaObject,java.io.Serializable
  SourceFile: "Reactor.scala"
  Scala: length = 0x
   
  InnerClass: 
   public final $anonfun$startSearch$1=class scala/actors/Reactor$$anonfun$startSearch$1 of class scala/actors/Reactor
   public final $anonfun$apply$2=class scala/actors/Reactor$$anonfun$startSearch$1$$anonfun$apply$2 of class scala/actors/Reactor$$anonfun$startSearch$1
  minor version: 0
  major version: 49
  Constant pool:
Asciz	SourceFile;
Asciz	Reactor.scala;
Asciz	<clinit>;
Asciz	()V;
Asciz	Code;
Asciz	serialVersionUID;
Asciz	J;
Asciz	scala/actors/Reactor$$anonfun$startSearch$1;
class	scala/actors/Reactor$$anonfun$startSearch$1
NameAndType	serialVersionUID:J
Field	scala/actors/Reactor$$anonfun$startSearch$1.serialVersionUID:J
Asciz	handler$1;
Asciz	Lscala/Function1;;
Asciz	replyTo$1;
Asciz	Lscala/actors/OutputChannel;;
Asciz	msg$1;
Asciz	Ljava/lang/Object;;
Asciz	$outer;
Asciz	Lscala/actors/Reactor;;
Asciz	<init>;
Asciz	(Lscala/actors/Reactor;Ljava/lang/Object;Lscala/actors/OutputChannel;Lscala/Function1;)V;
Asciz	LineNumberTable;
Asciz	java/lang/NullPointerException;
class	java/lang/NullPointerException
NameAndType	"<init>":()V
Method	java/lang/NullPointerException."<init>":()V
NameAndType	$outer:Lscala/actors/Reactor;
Field	scala/actors/Reactor$$anonfun$startSearch$1.$outer:Lscala/actors/Reactor;
NameAndType	msg$1:Ljava/lang/Object;
Field	scala/actors/Reactor$$anonfun$startSearch$1.msg$1:Ljava/lang/Object;
NameAndType	replyTo$1:Lscala/actors/OutputChannel;
Field	scala/actors/Reactor$$anonfun$startSearch$1.replyTo$1:Lscala/actors/OutputChannel;
NameAndType	handler$1:Lscala/Function1;
Field	scala/actors/Reactor$$anonfun$startSearch$1.handler$1:Lscala/Function1;
Asciz	java/lang/Object;
class	java/lang/Object
Method	java/lang/Object."<init>":()V
Asciz	scala/Function0$class;
class	scala/Function0$class
Asciz	$init$;
Asciz	(Lscala/Function0;)V;
NameAndType	$init$:(Lscala/Function0;)V
Method	scala/Function0$class.$init$:(Lscala/Function0;)V
Asciz	this;
Asciz	Lscala/actors/Reactor$$anonfun$startSearch$1;;
Asciz	LocalVariableTable;
Asciz	apply;
Asciz	()Ljava/lang/Object;;
NameAndType	apply:()V
Method	scala/actors/Reactor$$anonfun$startSearch$1.apply:()V
Asciz	scala/runtime/BoxedUnit;
class	scala/runtime/BoxedUnit
Asciz	UNIT;
Asciz	Lscala/runtime/BoxedUnit;;
NameAndType	UNIT:Lscala/runtime/BoxedUnit;
Field	scala/runtime/BoxedUnit.UNIT:Lscala/runtime/BoxedUnit;
Asciz	scala$actors$Reactor$$anonfun$$$outer;
Asciz	()Lscala/actors/Reactor;;
Asciz	scala/actors/Reactor;
class	scala/actors/Reactor
Asciz	scheduler;
Asciz	()Lscala/actors/IScheduler;;
NameAndType	scheduler:()Lscala/actors/IScheduler;
InterfaceMethod	scala/actors/Reactor.scheduler:()Lscala/actors/IScheduler;
Asciz	scala/actors/Reactor$$anonfun$startSearch$1$$anonfun$apply$2;
class	scala/actors/Reactor$$anonfun$startSearch$1$$anonfun$apply$2
Asciz	(Lscala/actors/Reactor$$anonfun$startSearch$1;)V;
NameAndType	"<init>":(Lscala/actors/Reactor$$anonfun$startSearch$1;)V
Method	scala/actors/Reactor$$anonfun$startSearch$1$$anonfun$apply$2."<init>":(Lscala/actors/Reactor$$anonfun$startSearch$1;)V
Asciz	makeReaction;
Asciz	(Lscala/Function0;)Ljava/lang/Runnable;;
NameAndType	makeReaction:(Lscala/Function0;)Ljava/lang/Runnable;
InterfaceMethod	scala/actors/Reactor.makeReaction:(Lscala/Function0;)Ljava/lang/Runnable;
Asciz	scala/actors/IScheduler;
class	scala/actors/IScheduler
Asciz	execute;
Asciz	(Ljava/lang/Runnable;)V;
NameAndType	execute:(Ljava/lang/Runnable;)V
InterfaceMethod	scala/actors/IScheduler.execute:(Ljava/lang/Runnable;)V
Asciz	toString;
Asciz	()Ljava/lang/String;;
Asciz	(Lscala/Function0;)Ljava/lang/String;;
NameAndType	toString:(Lscala/Function0;)Ljava/lang/String;
Method	scala/Function0$class.toString:(Lscala/Function0;)Ljava/lang/String;
Asciz	Scala;
Asciz	InnerClasses;
Asciz	$anonfun$startSearch$1;
Asciz	$anonfun$apply$2;
Asciz	scala/Function0;
class	scala/Function0
Asciz	scala/ScalaObject;
class	scala/ScalaObject
Asciz	java/io/Serializable;
class	java/io/Serializable

{
public static final long serialVersionUID;
  Signature: J

public final scala.Function1 handler$1;
  Signature: Lscala/Function1;

public final scala.actors.OutputChannel replyTo$1;
  Signature: Lscala/actors/OutputChannel;

public final java.lang.Object msg$1;
  Signature: Ljava/lang/Object;

public final scala.actors.Reactor $outer;
  Signature: Lscala/actors/Reactor;

public static {};
  Signature: ()V
  Code:
   Stack=2, Locals=0, Args_size=0
	lconst_0
	putstatic	Field serialVersionUID:J
	return
  Labels:

public scala.actors.Reactor$$anonfun$startSearch$1(scala.actors.Reactor, java.lang.Object, scala.actors.OutputChannel, scala.Function1);
  Signature: (Lscala/actors/Reactor;Ljava/lang/Object;Lscala/actors/OutputChannel;Lscala/Function1;)V
  Code:
   Stack=2, Locals=5, Args_size=5
	aload_1
	ifnonnull	l1 // aload_0
	new	class java/lang/NullPointerException
	dup
	invokespecial	Method java/lang/NullPointerException."<init>":()V
	athrow
l1	aload_0
	aload_1
	putfield	Field $outer:Lscala/actors/Reactor;
	aload_0
	aload_2
	putfield	Field msg$1:Ljava/lang/Object;
	aload_0
	aload_3
	putfield	Field replyTo$1:Lscala/actors/OutputChannel;
	aload_0
	aload	4
	putfield	Field handler$1:Lscala/Function1;
	aload_0
	invokespecial	Method java/lang/Object."<init>":()V
	aload_0
	invokestatic	Method scala/Function0$class.$init$:(Lscala/Function0;)V
	return
  Labels:
   	l1 = 12 // aload_0
  LocalVariableTable: 
   Start  Length  Slot  Name   Signature
   0      42      0    this       Lscala/actors/Reactor$$anonfun$startSearch$1;
   0      42      1    $outer       Lscala/actors/Reactor;


public final java.lang.Object apply();
  Signature: ()Ljava/lang/Object;
  Code:
   Stack=1, Locals=2, Args_size=1
	aload_0
	getfield	Field $outer:Lscala/actors/Reactor;
	astore_1
	aload_0
	invokevirtual	Method apply:()V
	getstatic	Field scala/runtime/BoxedUnit.UNIT:Lscala/runtime/BoxedUnit;
	areturn
  Labels:
  LocalVariableTable: 
   Start  Length  Slot  Name   Signature
   0      13      0    this       Lscala/actors/Reactor$$anonfun$startSearch$1;


public scala.actors.Reactor scala$actors$Reactor$$anonfun$$$outer();
  Signature: ()Lscala/actors/Reactor;
  Code:
   Stack=1, Locals=1, Args_size=1
	aload_0
	getfield	Field $outer:Lscala/actors/Reactor;
	areturn
  Labels:

public final void apply();
  Signature: ()V
  Code:
   Stack=5, Locals=2, Args_size=1
	aload_0
	getfield	Field $outer:Lscala/actors/Reactor;
	astore_1
	aload_0
	getfield	Field $outer:Lscala/actors/Reactor;
	invokeinterface	InterfaceMethod scala/actors/Reactor.scheduler:()Lscala/actors/IScheduler;
	aload_0
	getfield	Field $outer:Lscala/actors/Reactor;
	new	class scala/actors/Reactor$$anonfun$startSearch$1$$anonfun$apply$2
	dup
	aload_0
	invokespecial	Method scala/actors/Reactor$$anonfun$startSearch$1$$anonfun$apply$2."<init>":(Lscala/actors/Reactor$$anonfun$startSearch$1;)V
	invokeinterface	InterfaceMethod scala/actors/Reactor.makeReaction:(Lscala/Function0;)Ljava/lang/Runnable;
	invokeinterface	InterfaceMethod scala/actors/IScheduler.execute:(Ljava/lang/Runnable;)V
	return
  Labels:
  LocalVariableTable: 
   Start  Length  Slot  Name   Signature
   0      37      0    this       Lscala/actors/Reactor$$anonfun$startSearch$1;


public java.lang.String toString();
  Signature: ()Ljava/lang/String;
  Code:
   Stack=1, Locals=1, Args_size=1
	aload_0
	invokestatic	Method scala/Function0$class.toString:(Lscala/Function0;)Ljava/lang/String;
	areturn
  Labels:

}

