Compiled from "ReactChannel.scala"
public class scala.actors.ReactChannel extends java.lang.Object implements scala.actors.InputChannel,scala.ScalaObject
  SourceFile: "ReactChannel.scala"
  Signature: length = 0x2
   00 6D 
  ScalaSig: length = 0x662
   05 00 FFFFFF81 60 06 05 01 02 00 02 06 02 0C 52 65 61
   63 74 43 68 61 6E 6E 65 6C 0A 02 03 04 01 06 61
   63 74 6F 72 73 0A 01 05 01 05 73 63 61 6C 61 15
   02 07 16 13 04 00 08 10 21 10 02 09 0E 0D 01 0A
   0A 02 0B 0C 01 04 6C 61 6E 67 0A 01 0D 01 04 6A
   61 76 61 09 02 0F 0A 02 06 4F 62 6A 65 63 74 10
   03 11 12 14 0D 01 02 09 02 13 02 02 0C 49 6E 70
   75 74 43 68 61 6E 6E 65 6C 10 02 15 16 0C 00 04
   08 17 00 FFFFFF84 FFFFFF80 FFFFFF80 FFFFFFC2 00 19 02 03 4D 73 67 03 00
   11 02 1A 1E 10 02 1B 1C 0D 01 04 09 02 1D 04 02
   07 4E 6F 74 68 69 6E 67 10 02 1B 1F 09 02 20 04
   02 03 41 6E 79 10 02 1B 22 09 02 23 04 02 0B 53
   63 61 6C 61 4F 62 6A 65 63 74 08 08 25 00 FFFFFF82 FFFFFF80
   FFFFFFA0 FFFFFF80 04 26 01 08 72 65 63 65 69 76 65 72 10 02
   11 27 09 02 28 02 02 07 52 65 61 63 74 6F 72 08
   05 2A 00 FFFFFF84 00 2B 01 06 3C 69 6E 69 74 3E 14 02
   2C 2D 10 03 11 00 14 08 05 25 29 FFFFFFC0 00 26 06 08
   2F 00 FFFFFF84 FFFFFF80 FFFFFF80 FFFFFF80 44 30 02 0D 53 65 6E 64 54 6F
   52 65 61 63 74 6F 72 13 04 2E 08 21 31 10 02 1B
   32 09 02 33 04 02 07 50 72 6F 64 75 63 74 08 08
   35 2E FFFFFF82 FFFFFFCA FFFFFF80 FFFFFF84 00 36 01 07 63 68 61 6E 6E 65
   6C 15 01 2C 08 08 38 2E FFFFFF82 FFFFFF88 FFFFFFA0 FFFFFF80 04 2C 01 08
   63 68 61 6E 6E 65 6C 20 08 08 3A 2E FFFFFF82 FFFFFFCA FFFFFF80 FFFFFF84
   00 3B 01 03 6D 73 67 15 01 14 08 08 3D 2E FFFFFF82 FFFFFF88
   FFFFFFA0 FFFFFF80 04 14 01 04 6D 73 67 20 08 05 2A 2E FFFFFF84 00
   3F 14 03 40 42 43 10 02 41 2E 0D 01 00 08 05 35
   3E FFFFFFC0 00 2C 08 05 3A 3E FFFFFFC0 00 14 08 07 45 2E FFFFFF81
   FFFFFF80 FFFFFF84 00 46 01 04 63 6F 70 79 14 03 40 47 48 08
   07 35 44 FFFFFF90 FFFFFF80 FFFFFFC0 00 2C 08 07 3A 44 FFFFFF90 FFFFFF80 FFFFFFC0 00
   14 08 07 4A 2E FFFFFF91 FFFFFF80 FFFFFF84 00 4B 01 0E 63 6F 70 79
   24 64 65 66 61 75 6C 74 24 31 15 01 4C 2A 02 2C
   4D 2B 01 4E 10 02 4F 54 0D 01 50 0A 02 51 52 01
   09 75 6E 63 68 65 63 6B 65 64 0A 02 53 04 01 0A
   61 6E 6E 6F 74 61 74 69 6F 6E 09 02 55 50 02 11
   75 6E 63 68 65 63 6B 65 64 56 61 72 69 61 6E 63
   65 08 07 57 2E FFFFFF91 FFFFFF80 FFFFFF84 00 58 01 0E 63 6F 70 79
   24 64 65 66 61 75 6C 74 24 32 15 01 59 2A 02 14
   4D 08 08 5B 2E FFFFFF84 FFFFFF80 FFFFFF80 FFFFFF84 20 5C 01 08 68 61 73
   68 43 6F 64 65 14 01 5D 10 02 1B 5E 09 02 5F 04
   02 03 49 6E 74 08 08 61 2E FFFFFF84 FFFFFF80 FFFFFF80 FFFFFF84 20 62 01
   08 74 6F 53 74 72 69 6E 67 14 01 63 10 02 64 67
   0E 02 1B 65 09 02 66 04 01 06 50 72 65 64 65 66
   09 02 68 69 02 06 53 74 72 69 6E 67 0A 02 66 04
   08 08 6B 2E FFFFFF84 FFFFFF80 FFFFFF80 FFFFFF84 20 6C 01 06 65 71 75 61
   6C 73 14 02 6D 70 10 02 1B 6E 09 02 6F 04 02 07
   42 6F 6F 6C 65 61 6E 08 07 71 6A FFFFFF81 FFFFFF80 FFFFFFC0 00 1E
   01 03 78 24 31 08 08 73 2E FFFFFF84 FFFFFF80 FFFFFF80 FFFFFF84 20 74 01
   0D 70 72 6F 64 75 63 74 50 72 65 66 69 78 15 01
   75 10 02 09 76 09 02 68 0A 08 08 78 2E FFFFFF84 FFFFFF80 FFFFFF80
   FFFFFF84 20 79 01 0C 70 72 6F 64 75 63 74 41 72 69 74
   79 15 01 5D 08 08 7B 2E FFFFFF84 FFFFFF80 FFFFFF80 FFFFFF84 20 7C 01 0E
   70 72 6F 64 75 63 74 45 6C 65 6D 65 6E 74 14 02
   1E 7D 08 07 71 7A FFFFFF81 FFFFFF80 FFFFFFC0 00 5D 08 09 7F 2E FFFFFF84
   FFFFFF80 FFFFFF80 FFFFFF84 20 FFFFFF81 00 01 12 70 72 6F 64 75 63 74 45
   6C 65 6D 65 6E 74 4E 61 6D 65 14 03 75 FFFFFF81 01 08
   07 71 7E FFFFFF81 FFFFFF80 FFFFFFC0 00 5D 08 0A FFFFFF81 03 2E FFFFFF84 FFFFFF80 FFFFFF80
   FFFFFF84 20 FFFFFF81 04 01 08 63 61 6E 45 71 75 61 6C 14 03
   6D FFFFFF81 05 08 08 71 FFFFFF81 02 FFFFFF81 FFFFFF80 FFFFFFC0 00 1E 28 03 2E
   FFFFFF81 07 10 03 1B FFFFFF81 08 09 03 FFFFFF81 09 04 02 0C 73 65
   72 69 61 6C 69 7A 61 62 6C 65 07 09 FFFFFF81 0B 00 FFFFFF81
   FFFFFF80 FFFFFF88 06 FFFFFF81 0C 01 0D 53 65 6E 64 54 6F 52 65 61
   63 74 6F 72 10 03 41 FFFFFF81 0D 06 09 2F 00 FFFFFF84 FFFFFF81 FFFFFF80
   FFFFFF88 06 FFFFFF81 0E 13 06 FFFFFF81 0D 08 FFFFFF81 0F 21 10 06 1B FFFFFF81
   10 2C 14 40 09 03 FFFFFF81 11 04 02 09 46 75 6E 63 74
   69 6F 6E 32 08 07 2A FFFFFF81 0D FFFFFF84 00 FFFFFF81 13 14 02 FFFFFF81
   0C 08 0A FFFFFF81 15 FFFFFF81 0D FFFFFF81 FFFFFF80 FFFFFF84 40 FFFFFF81 16 01 05 61
   70 70 6C 79 14 05 40 FFFFFF81 17 FFFFFF81 18 08 06 35 FFFFFF81 14
   FFFFFFC0 00 2C 08 06 3A FFFFFF81 14 FFFFFFC0 00 14 08 0A FFFFFF81 1A FFFFFF81
   0D FFFFFF81 FFFFFF80 FFFFFF84 40 FFFFFF81 1B 01 07 75 6E 61 70 70 6C 79
   14 04 FFFFFF81 1C FFFFFF81 22 10 05 1B FFFFFF81 1D FFFFFF81 1F 09 03 FFFFFF81
   1E 04 02 04 53 6F 6D 65 10 05 1B FFFFFF81 20 2C 14 09
   03 FFFFFF81 21 04 02 06 54 75 70 6C 65 32 08 07 FFFFFF81 23
   FFFFFF81 19 FFFFFFC0 00 40 01 03 78 24 30 08 07 FFFFFF81 25 00 FFFFFF84
   00 FFFFFF81 26 01 05 24 62 61 6E 67 14 04 FFFFFF81 27 FFFFFF81 2A
   10 03 1B FFFFFF81 28 09 03 FFFFFF81 29 04 02 04 55 6E 69 74
   08 06 3A FFFFFF81 24 FFFFFFC0 00 14 08 07 FFFFFF81 2C 00 FFFFFF84 00 FFFFFF81
   2D 01 04 73 65 6E 64 14 06 FFFFFF81 27 FFFFFF81 2E FFFFFF81 2F 08
   06 3A FFFFFF81 2B FFFFFFC0 00 14 08 08 FFFFFF81 30 FFFFFF81 2B FFFFFFC0 00 FFFFFF81
   31 01 07 72 65 70 6C 79 54 6F 10 04 11 FFFFFF81 32 1E
   09 03 FFFFFF81 33 02 02 0D 4F 75 74 70 75 74 43 68 61
   6E 6E 65 6C 08 07 FFFFFF81 35 00 FFFFFF84 00 FFFFFF81 36 01 07 66
   6F 72 77 61 72 64 14 04 FFFFFF81 27 FFFFFF81 37 08 06 3A FFFFFF81
   34 FFFFFFC0 00 14 08 07 FFFFFF81 39 00 FFFFFF84 00 FFFFFF81 3A 01 05 72
   65 61 63 74 14 03 1A FFFFFF81 3B 08 08 FFFFFF81 3C FFFFFF81 38 FFFFFFC0
   00 FFFFFF81 3D 01 01 66 10 06 1B FFFFFF81 3E 14 FFFFFF81 27 09 03
   FFFFFF81 3F 04 02 0F 50 61 72 74 69 61 6C 46 75 6E 63
   74 69 6F 6E 08 07 FFFFFF81 41 00 FFFFFF84 00 FFFFFF81 42 01 0B 72
   65 61 63 74 57 69 74 68 69 6E 14 04 FFFFFF81 43 FFFFFF81 46
   14 03 1A FFFFFF81 44 08 08 FFFFFF81 3C FFFFFF81 40 FFFFFFC0 00 FFFFFF81 45 10
   06 1B FFFFFF81 3E 1E FFFFFF81 27 08 08 FFFFFF81 47 FFFFFF81 40 FFFFFFC0 00 FFFFFF81
   48 01 04 6D 73 65 63 10 03 1B FFFFFF81 49 09 03 FFFFFF81 4A
   04 02 04 4C 6F 6E 67 08 07 FFFFFF81 4C 00 FFFFFF84 00 FFFFFF81 4D
   01 07 72 65 63 65 69 76 65 15 04 FFFFFF81 4E FFFFFF81 50 14
   04 FFFFFF81 4F FFFFFF81 52 10 03 15 FFFFFF81 50 04 0A FFFFFF81 51 FFFFFF81 4B
   FFFFFF84 FFFFFF80 FFFFFF80 FFFFFFC2 00 19 02 01 52 08 08 FFFFFF81 3C FFFFFF81 4B FFFFFFC0
   00 FFFFFF81 53 10 06 1B FFFFFF81 3E 14 FFFFFF81 4F 08 07 FFFFFF81 55 00
   FFFFFF84 00 FFFFFF81 56 01 0D 72 65 63 65 69 76 65 57 69 74
   68 69 6E 15 04 FFFFFF81 57 FFFFFF81 5A 14 04 FFFFFF81 58 FFFFFF81 5D 14
   04 FFFFFF81 59 FFFFFF81 5B 10 03 15 FFFFFF81 5A 04 0A FFFFFF81 51 FFFFFF81 54
   FFFFFF84 FFFFFF80 FFFFFF80 FFFFFFC2 00 19 08 08 FFFFFF81 3C FFFFFF81 54 FFFFFFC0 00 FFFFFF81 5C
   10 06 1B FFFFFF81 3E 1E FFFFFF81 59 08 08 FFFFFF81 47 FFFFFF81 54 FFFFFFC0 00
   FFFFFF81 48 08 06 FFFFFF81 5F 00 FFFFFF84 00 3B 01 06 24 71 6D 61
   72 6B 
  InnerClass: 
   public SendToReactor=class scala/actors/ReactChannel$SendToReactor of class scala/actors/ReactChannel
   public final $anonfun$react$1=class scala/actors/ReactChannel$$anonfun$react$1 of class scala/actors/ReactChannel
   public final $anonfun$$qmark$1=class scala/actors/ReactChannel$$anonfun$$qmark$1 of class scala/actors/ReactChannel
   public final $anonfun$receive$1=class scala/actors/ReactChannel$$anonfun$receive$1 of class scala/actors/ReactChannel
   public final $anonfun$reactWithin$1=class scala/actors/ReactChannel$$anonfun$reactWithin$1 of class scala/actors/ReactChannel
   public final $anonfun$receiveWithin$1=class scala/actors/ReactChannel$$anonfun$receiveWithin$1 of class scala/actors/ReactChannel
  minor version: 0
  major version: 49
  Constant pool:
Asciz	SourceFile;
Asciz	ReactChannel.scala;
Asciz	SendToReactor$module;
Asciz	Lscala/actors/ReactChannel$SendToReactor$;;
Asciz	receiver;
Asciz	Lscala/actors/Reactor;;
Asciz	$bang;
Asciz	(Ljava/lang/Object;)V;
Asciz	Code;
Asciz	LineNumberTable;
Asciz	scala/actors/ReactChannel;
class	scala/actors/ReactChannel
NameAndType	receiver:Lscala/actors/Reactor;
Field	scala/actors/ReactChannel.receiver:Lscala/actors/Reactor;
Asciz	scala/actors/ReactChannel$SendToReactor;
class	scala/actors/ReactChannel$SendToReactor
Asciz	<init>;
Asciz	(Lscala/actors/ReactChannel;Lscala/actors/ReactChannel;Ljava/lang/Object;)V;
NameAndType	"<init>":(Lscala/actors/ReactChannel;Lscala/actors/ReactChannel;Ljava/lang/Object;)V
Method	scala/actors/ReactChannel$SendToReactor."<init>":(Lscala/actors/ReactChannel;Lscala/actors/ReactChannel;Ljava/lang/Object;)V
Asciz	scala/actors/Reactor;
class	scala/actors/Reactor
NameAndType	$bang:(Ljava/lang/Object;)V
InterfaceMethod	scala/actors/Reactor.$bang:(Ljava/lang/Object;)V
Asciz	this;
Asciz	Lscala/actors/ReactChannel;;
Asciz	msg;
Asciz	Ljava/lang/Object;;
Asciz	LocalVariableTable;
Asciz	(TMsg;)V;
Asciz	Signature;
Asciz	send;
Asciz	(Ljava/lang/Object;Lscala/actors/OutputChannel;)V;
NameAndType	send:(Ljava/lang/Object;Lscala/actors/OutputChannel;)V
InterfaceMethod	scala/actors/Reactor.send:(Ljava/lang/Object;Lscala/actors/OutputChannel;)V
Asciz	replyTo;
Asciz	Lscala/actors/OutputChannel;;
Asciz	(TMsg;Lscala/actors/OutputChannel<Ljava/lang/Object;>;)V;
Asciz	forward;
NameAndType	forward:(Ljava/lang/Object;)V
InterfaceMethod	scala/actors/Reactor.forward:(Ljava/lang/Object;)V
Asciz	react;
Asciz	(Lscala/PartialFunction;)Lscala/runtime/Nothing$;;
Asciz	scala/actors/ReactChannel$$anonfun$react$1;
class	scala/actors/ReactChannel$$anonfun$react$1
Asciz	(Lscala/actors/ReactChannel;Lscala/PartialFunction;Lscala/actors/ReactChannel;)V;
NameAndType	"<init>":(Lscala/actors/ReactChannel;Lscala/PartialFunction;Lscala/actors/ReactChannel;)V
Method	scala/actors/ReactChannel$$anonfun$react$1."<init>":(Lscala/actors/ReactChannel;Lscala/PartialFunction;Lscala/actors/ReactChannel;)V
NameAndType	react:(Lscala/PartialFunction;)Lscala/runtime/Nothing$;
InterfaceMethod	scala/actors/Reactor.react:(Lscala/PartialFunction;)Lscala/runtime/Nothing$;
Asciz	f$1;
Asciz	Lscala/PartialFunction;;
Asciz	(Lscala/PartialFunction<TMsg;Ljava/lang/Object;>;)Lscala/runtime/Nothing$;;
Asciz	reactWithin;
Asciz	(JLscala/PartialFunction;)Lscala/runtime/Nothing$;;
Asciz	scala/actors/Actor;
class	scala/actors/Actor
Asciz	scala/actors/ReactChannel$$anonfun$reactWithin$1;
class	scala/actors/ReactChannel$$anonfun$reactWithin$1
Method	scala/actors/ReactChannel$$anonfun$reactWithin$1."<init>":(Lscala/actors/ReactChannel;Lscala/PartialFunction;Lscala/actors/ReactChannel;)V
NameAndType	reactWithin:(JLscala/PartialFunction;)Lscala/runtime/Nothing$;
InterfaceMethod	scala/actors/Actor.reactWithin:(JLscala/PartialFunction;)Lscala/runtime/Nothing$;
Asciz	msec;
Asciz	J;
Asciz	f$2;
Asciz	recvActor;
Asciz	Lscala/actors/Actor;;
Asciz	(JLscala/PartialFunction<Ljava/lang/Object;Ljava/lang/Object;>;)Lscala/runtime/Nothing$;;
Asciz	receive;
Asciz	(Lscala/PartialFunction;)Ljava/lang/Object;;
Asciz	scala/actors/ReactChannel$$anonfun$receive$1;
class	scala/actors/ReactChannel$$anonfun$receive$1
Method	scala/actors/ReactChannel$$anonfun$receive$1."<init>":(Lscala/actors/ReactChannel;Lscala/PartialFunction;Lscala/actors/ReactChannel;)V
NameAndType	receive:(Lscala/PartialFunction;)Ljava/lang/Object;
InterfaceMethod	scala/actors/Actor.receive:(Lscala/PartialFunction;)Ljava/lang/Object;
Asciz	f$3;
Asciz	<R:Ljava/lang/Object;>(Lscala/PartialFunction<TMsg;TR;>;)TR;;
Asciz	receiveWithin;
Asciz	(JLscala/PartialFunction;)Ljava/lang/Object;;
Asciz	scala/actors/ReactChannel$$anonfun$receiveWithin$1;
class	scala/actors/ReactChannel$$anonfun$receiveWithin$1
Method	scala/actors/ReactChannel$$anonfun$receiveWithin$1."<init>":(Lscala/actors/ReactChannel;Lscala/PartialFunction;Lscala/actors/ReactChannel;)V
NameAndType	receiveWithin:(JLscala/PartialFunction;)Ljava/lang/Object;
InterfaceMethod	scala/actors/Actor.receiveWithin:(JLscala/PartialFunction;)Ljava/lang/Object;
Asciz	f$4;
Asciz	<R:Ljava/lang/Object;>(JLscala/PartialFunction<Ljava/lang/Object;TR;>;)TR;;
Asciz	$qmark;
Asciz	()Ljava/lang/Object;;
Asciz	scala/actors/ReactChannel$$anonfun$$qmark$1;
class	scala/actors/ReactChannel$$anonfun$$qmark$1
Asciz	(Lscala/actors/ReactChannel;)V;
NameAndType	"<init>":(Lscala/actors/ReactChannel;)V
Method	scala/actors/ReactChannel$$anonfun$$qmark$1."<init>":(Lscala/actors/ReactChannel;)V
Method	scala/actors/ReactChannel.receive:(Lscala/PartialFunction;)Ljava/lang/Object;
Asciz	()TMsg;;
Asciz	SendToReactor;
Asciz	()Lscala/actors/ReactChannel$SendToReactor$;;
NameAndType	SendToReactor$module:Lscala/actors/ReactChannel$SendToReactor$;
Field	scala/actors/ReactChannel.SendToReactor$module:Lscala/actors/ReactChannel$SendToReactor$;
Asciz	scala/actors/ReactChannel$SendToReactor$;
class	scala/actors/ReactChannel$SendToReactor$
Method	scala/actors/ReactChannel$SendToReactor$."<init>":(Lscala/actors/ReactChannel;)V
Asciz	(Lscala/actors/Reactor;)V;
Asciz	java/lang/Object;
class	java/lang/Object
Asciz	()V;
NameAndType	"<init>":()V
Method	java/lang/Object."<init>":()V
Asciz	<Msg:Ljava/lang/Object;>Ljava/lang/Object;Lscala/actors/InputChannel<TMsg;>;Lscala/ScalaObject;;
Asciz	ScalaSig;
Asciz	InnerClasses;
Asciz	$anonfun$react$1;
Asciz	$anonfun$$qmark$1;
Asciz	$anonfun$receive$1;
Asciz	$anonfun$reactWithin$1;
Asciz	$anonfun$receiveWithin$1;
Asciz	scala/actors/InputChannel;
class	scala/actors/InputChannel
Asciz	scala/ScalaObject;
class	scala/ScalaObject

{
private scala.actors.ReactChannel$SendToReactor$ SendToReactor$module;
  Signature: Lscala/actors/ReactChannel$SendToReactor$;

private final scala.actors.Reactor receiver;
  Signature: Lscala/actors/Reactor;

public void $bang(java.lang.Object);
  Signature: (Ljava/lang/Object;)V
  Code:
   Stack=6, Locals=2, Args_size=2
	aload_0
	getfield	Field receiver:Lscala/actors/Reactor;
	new	class scala/actors/ReactChannel$SendToReactor
	dup
	aload_0
	aload_0
	aload_1
	invokespecial	Method scala/actors/ReactChannel$SendToReactor."<init>":(Lscala/actors/ReactChannel;Lscala/actors/ReactChannel;Ljava/lang/Object;)V
	invokeinterface	InterfaceMethod scala/actors/Reactor.$bang:(Ljava/lang/Object;)V
	return
  Labels:
  LocalVariableTable: 
   Start  Length  Slot  Name   Signature
   0      20      0    this       Lscala/actors/ReactChannel;
   0      20      1    msg       Ljava/lang/Object;

  Signature: length = 0x2
   00 1E 

public void send(java.lang.Object, scala.actors.OutputChannel);
  Signature: (Ljava/lang/Object;Lscala/actors/OutputChannel;)V
  Code:
   Stack=6, Locals=3, Args_size=3
	aload_0
	getfield	Field receiver:Lscala/actors/Reactor;
	new	class scala/actors/ReactChannel$SendToReactor
	dup
	aload_0
	aload_0
	aload_1
	invokespecial	Method scala/actors/ReactChannel$SendToReactor."<init>":(Lscala/actors/ReactChannel;Lscala/actors/ReactChannel;Ljava/lang/Object;)V
	aload_2
	invokeinterface	InterfaceMethod scala/actors/Reactor.send:(Ljava/lang/Object;Lscala/actors/OutputChannel;)V
	return
  Labels:
  LocalVariableTable: 
   Start  Length  Slot  Name   Signature
   0      21      0    this       Lscala/actors/ReactChannel;
   0      21      1    msg       Ljava/lang/Object;
   0      21      2    replyTo       Lscala/actors/OutputChannel;

  Signature: length = 0x2
   00 26 

public void forward(java.lang.Object);
  Signature: (Ljava/lang/Object;)V
  Code:
   Stack=6, Locals=2, Args_size=2
	aload_0
	getfield	Field receiver:Lscala/actors/Reactor;
	new	class scala/actors/ReactChannel$SendToReactor
	dup
	aload_0
	aload_0
	aload_1
	invokespecial	Method scala/actors/ReactChannel$SendToReactor."<init>":(Lscala/actors/ReactChannel;Lscala/actors/ReactChannel;Ljava/lang/Object;)V
	invokeinterface	InterfaceMethod scala/actors/Reactor.forward:(Ljava/lang/Object;)V
	return
  Labels:
  LocalVariableTable: 
   Start  Length  Slot  Name   Signature
   0      20      0    this       Lscala/actors/ReactChannel;
   0      20      1    msg       Ljava/lang/Object;

  Signature: length = 0x2
   00 1E 

public scala.runtime.Nothing$ react(scala.PartialFunction);
  Signature: (Lscala/PartialFunction;)Lscala/runtime/Nothing$;
  Code:
   Stack=6, Locals=2, Args_size=2
	aload_0
	getfield	Field receiver:Lscala/actors/Reactor;
	new	class scala/actors/ReactChannel$$anonfun$react$1
	dup
	aload_0
	aload_1
	aload_0
	invokespecial	Method scala/actors/ReactChannel$$anonfun$react$1."<init>":(Lscala/actors/ReactChannel;Lscala/PartialFunction;Lscala/actors/ReactChannel;)V
	invokeinterface	InterfaceMethod scala/actors/Reactor.react:(Lscala/PartialFunction;)Lscala/runtime/Nothing$;
	areturn
  Labels:
  LocalVariableTable: 
   Start  Length  Slot  Name   Signature
   0      20      0    this       Lscala/actors/ReactChannel;
   0      20      1    f$1       Lscala/PartialFunction;

  Signature: length = 0x2
   00 35 

public scala.runtime.Nothing$ reactWithin(long, scala.PartialFunction);
  Signature: (JLscala/PartialFunction;)Lscala/runtime/Nothing$;
  Code:
   Stack=8, Locals=5, Args_size=3
	aload_0
	getfield	Field receiver:Lscala/actors/Reactor;
	checkcast	class scala/actors/Actor
	astore	4
	aload	4
	lload_1
	new	class scala/actors/ReactChannel$$anonfun$reactWithin$1
	dup
	aload_0
	aload_3
	aload_0
	invokespecial	Method scala/actors/ReactChannel$$anonfun$reactWithin$1."<init>":(Lscala/actors/ReactChannel;Lscala/PartialFunction;Lscala/actors/ReactChannel;)V
	invokeinterface	InterfaceMethod scala/actors/Actor.reactWithin:(JLscala/PartialFunction;)Lscala/runtime/Nothing$;
	areturn
  Labels:
  LocalVariableTable: 
   Start  Length  Slot  Name   Signature
   0      28      0    this       Lscala/actors/ReactChannel;
   0      28      1    msec       J
   0      28      3    f$2       Lscala/PartialFunction;
   9      18      4    recvActor       Lscala/actors/Actor;

  Signature: length = 0x2
   00 44 

public java.lang.Object receive(scala.PartialFunction);
  Signature: (Lscala/PartialFunction;)Ljava/lang/Object;
  Code:
   Stack=6, Locals=3, Args_size=2
	aload_0
	getfield	Field receiver:Lscala/actors/Reactor;
	checkcast	class scala/actors/Actor
	astore_2
	aload_2
	new	class scala/actors/ReactChannel$$anonfun$receive$1
	dup
	aload_0
	aload_1
	aload_0
	invokespecial	Method scala/actors/ReactChannel$$anonfun$receive$1."<init>":(Lscala/actors/ReactChannel;Lscala/PartialFunction;Lscala/actors/ReactChannel;)V
	invokeinterface	InterfaceMethod scala/actors/Actor.receive:(Lscala/PartialFunction;)Ljava/lang/Object;
	areturn
  Labels:
  LocalVariableTable: 
   Start  Length  Slot  Name   Signature
   0      25      0    this       Lscala/actors/ReactChannel;
   0      25      1    f$3       Lscala/PartialFunction;
   8      16      2    recvActor       Lscala/actors/Actor;

  Signature: length = 0x2
   00 4D 

public java.lang.Object receiveWithin(long, scala.PartialFunction);
  Signature: (JLscala/PartialFunction;)Ljava/lang/Object;
  Code:
   Stack=8, Locals=5, Args_size=3
	aload_0
	getfield	Field receiver:Lscala/actors/Reactor;
	checkcast	class scala/actors/Actor
	astore	4
	aload	4
	lload_1
	new	class scala/actors/ReactChannel$$anonfun$receiveWithin$1
	dup
	aload_0
	aload_3
	aload_0
	invokespecial	Method scala/actors/ReactChannel$$anonfun$receiveWithin$1."<init>":(Lscala/actors/ReactChannel;Lscala/PartialFunction;Lscala/actors/ReactChannel;)V
	invokeinterface	InterfaceMethod scala/actors/Actor.receiveWithin:(JLscala/PartialFunction;)Ljava/lang/Object;
	areturn
  Labels:
  LocalVariableTable: 
   Start  Length  Slot  Name   Signature
   0      28      0    this       Lscala/actors/ReactChannel;
   0      28      1    msec       J
   0      28      3    f$4       Lscala/PartialFunction;
   9      18      4    recvActor       Lscala/actors/Actor;

  Signature: length = 0x2
   00 56 

public java.lang.Object $qmark();
  Signature: ()Ljava/lang/Object;
  Code:
   Stack=4, Locals=1, Args_size=1
	aload_0
	new	class scala/actors/ReactChannel$$anonfun$$qmark$1
	dup
	aload_0
	invokespecial	Method scala/actors/ReactChannel$$anonfun$$qmark$1."<init>":(Lscala/actors/ReactChannel;)V
	invokevirtual	Method receive:(Lscala/PartialFunction;)Ljava/lang/Object;
	areturn
  Labels:
  Signature: length = 0x2
   00 5F 

private final scala.actors.ReactChannel$SendToReactor$ SendToReactor();
  Signature: ()Lscala/actors/ReactChannel$SendToReactor$;
  Code:
   Stack=4, Locals=1, Args_size=1
	aload_0
	getfield	Field SendToReactor$module:Lscala/actors/ReactChannel$SendToReactor$;
	ifnonnull	l1 // aload_0
	aload_0
	new	class scala/actors/ReactChannel$SendToReactor$
	dup
	aload_0
	invokespecial	Method scala/actors/ReactChannel$SendToReactor$."<init>":(Lscala/actors/ReactChannel;)V
	putfield	Field SendToReactor$module:Lscala/actors/ReactChannel$SendToReactor$;
l1	aload_0
	getfield	Field SendToReactor$module:Lscala/actors/ReactChannel$SendToReactor$;
	areturn
  Labels:
   	l1 = 19 // aload_0

public scala.actors.ReactChannel(scala.actors.Reactor);
  Signature: (Lscala/actors/Reactor;)V
  Code:
   Stack=2, Locals=2, Args_size=2
	aload_0
	aload_1
	putfield	Field receiver:Lscala/actors/Reactor;
	aload_0
	invokespecial	Method java/lang/Object."<init>":()V
	return
  Labels:
  LocalVariableTable: 
   Start  Length  Slot  Name   Signature
   0      10      0    this       Lscala/actors/ReactChannel;
   0      10      1    receiver       Lscala/actors/Reactor;

  Signature: length = 0x2
   00 67 

}

