Compiled from "ReactChannel.scala"
public class scala.actors.ReactChannel$SendToReactor extends java.lang.Object implements scala.ScalaObject,scala.Product,java.io.Serializable
  SourceFile: "ReactChannel.scala"
  Scala: length = 0x
   
  InnerClass: 
   public SendToReactor=class scala/actors/ReactChannel$SendToReactor of class scala/actors/ReactChannel
  minor version: 0
  major version: 49
  Constant pool:
Asciz	SourceFile;
Asciz	ReactChannel.scala;
Asciz	$outer;
Asciz	Lscala/actors/ReactChannel;;
Asciz	msg;
Asciz	Ljava/lang/Object;;
Asciz	TMsg;;
Asciz	Signature;
Asciz	channel;
Asciz	Lscala/actors/ReactChannel<TMsg;>;;
Asciz	productElementName;
Asciz	(I)Ljava/lang/String;;
Asciz	Code;
Asciz	LineNumberTable;
Asciz	scala/Product$class;
class	scala/Product$class
Asciz	(Lscala/Product;I)Ljava/lang/String;;
NameAndType	productElementName:(Lscala/Product;I)Ljava/lang/String;
Method	scala/Product$class.productElementName:(Lscala/Product;I)Ljava/lang/String;
Asciz	this;
Asciz	Lscala/actors/ReactChannel$SendToReactor;;
Asciz	n;
Asciz	I;
Asciz	LocalVariableTable;
Asciz	productIterator;
Asciz	()Lscala/collection/Iterator;;
Asciz	(Lscala/Product;)Lscala/collection/Iterator;;
NameAndType	productIterator:(Lscala/Product;)Lscala/collection/Iterator;
Method	scala/Product$class.productIterator:(Lscala/Product;)Lscala/collection/Iterator;
Asciz	productElements;
NameAndType	productElements:(Lscala/Product;)Lscala/collection/Iterator;
Method	scala/Product$class.productElements:(Lscala/Product;)Lscala/collection/Iterator;
Asciz	Deprecated;
Asciz	copy$default$2;
Asciz	()Ljava/lang/Object;;
Asciz	scala/actors/ReactChannel$SendToReactor;
class	scala/actors/ReactChannel$SendToReactor
NameAndType	msg:()Ljava/lang/Object;
Method	scala/actors/ReactChannel$SendToReactor.msg:()Ljava/lang/Object;
Asciz	copy$default$1;
Asciz	()Lscala/actors/ReactChannel;;
NameAndType	channel:()Lscala/actors/ReactChannel;
Method	scala/actors/ReactChannel$SendToReactor.channel:()Lscala/actors/ReactChannel;
NameAndType	channel:Lscala/actors/ReactChannel;
Field	scala/actors/ReactChannel$SendToReactor.channel:Lscala/actors/ReactChannel;
Asciz	()Lscala/actors/ReactChannel<TMsg;>;;
NameAndType	msg:Ljava/lang/Object;
Field	scala/actors/ReactChannel$SendToReactor.msg:Ljava/lang/Object;
Asciz	()TMsg;;
Asciz	copy;
Asciz	(Lscala/actors/ReactChannel;Ljava/lang/Object;)Lscala/actors/ReactChannel$SendToReactor;;
Asciz	scala$actors$ReactChannel$SendToReactor$$$outer;
NameAndType	scala$actors$ReactChannel$SendToReactor$$$outer:()Lscala/actors/ReactChannel;
Method	scala/actors/ReactChannel$SendToReactor.scala$actors$ReactChannel$SendToReactor$$$outer:()Lscala/actors/ReactChannel;
Asciz	<init>;
Asciz	(Lscala/actors/ReactChannel;Lscala/actors/ReactChannel;Ljava/lang/Object;)V;
NameAndType	"<init>":(Lscala/actors/ReactChannel;Lscala/actors/ReactChannel;Ljava/lang/Object;)V
Method	scala/actors/ReactChannel$SendToReactor."<init>":(Lscala/actors/ReactChannel;Lscala/actors/ReactChannel;Ljava/lang/Object;)V
Asciz	hashCode;
Asciz	()I;
Asciz	scala/runtime/ScalaRunTime$;
class	scala/runtime/ScalaRunTime$
Asciz	MODULE$;
Asciz	Lscala/runtime/ScalaRunTime$;;
NameAndType	MODULE$:Lscala/runtime/ScalaRunTime$;
Field	scala/runtime/ScalaRunTime$.MODULE$:Lscala/runtime/ScalaRunTime$;
Asciz	_hashCode;
Asciz	(Lscala/Product;)I;
NameAndType	_hashCode:(Lscala/Product;)I
Method	scala/runtime/ScalaRunTime$._hashCode:(Lscala/Product;)I
Asciz	toString;
Asciz	()Ljava/lang/String;;
Asciz	_toString;
Asciz	(Lscala/Product;)Ljava/lang/String;;
NameAndType	_toString:(Lscala/Product;)Ljava/lang/String;
Method	scala/runtime/ScalaRunTime$._toString:(Lscala/Product;)Ljava/lang/String;
Asciz	equals;
Asciz	(Ljava/lang/Object;)Z;
Asciz	gd1$1;
Asciz	(Lscala/actors/ReactChannel;Ljava/lang/Object;)Z;
NameAndType	gd1$1:(Lscala/actors/ReactChannel;Ljava/lang/Object;)Z
Method	scala/actors/ReactChannel$SendToReactor.gd1$1:(Lscala/actors/ReactChannel;Ljava/lang/Object;)Z
Asciz	scala/Equals;
class	scala/Equals
Asciz	canEqual;
NameAndType	canEqual:(Ljava/lang/Object;)Z
InterfaceMethod	scala/Equals.canEqual:(Ljava/lang/Object;)Z
Asciz	temp2;
Asciz	temp3;
Asciz	temp4;
Asciz	productPrefix;
Asciz	SendToReactor;
String	SendToReactor
Asciz	productArity;
Asciz	productElement;
Asciz	(I)Ljava/lang/Object;;
Asciz	java/lang/IndexOutOfBoundsException;
class	java/lang/IndexOutOfBoundsException
Asciz	scala/runtime/BoxesRunTime;
class	scala/runtime/BoxesRunTime
Asciz	boxToInteger;
Asciz	(I)Ljava/lang/Integer;;
NameAndType	boxToInteger:(I)Ljava/lang/Integer;
Method	scala/runtime/BoxesRunTime.boxToInteger:(I)Ljava/lang/Integer;
Asciz	java/lang/Object;
class	java/lang/Object
NameAndType	toString:()Ljava/lang/String;
Method	java/lang/Object.toString:()Ljava/lang/String;
Asciz	(Ljava/lang/String;)V;
NameAndType	"<init>":(Ljava/lang/String;)V
Method	java/lang/IndexOutOfBoundsException."<init>":(Ljava/lang/String;)V
NameAndType	$outer:Lscala/actors/ReactChannel;
Field	scala/actors/ReactChannel$SendToReactor.$outer:Lscala/actors/ReactChannel;
NameAndType	equals:(Ljava/lang/Object;)Z
Method	java/lang/Object.equals:(Ljava/lang/Object;)Z
Asciz	java/lang/Number;
class	java/lang/Number
Asciz	java/lang/Character;
class	java/lang/Character
Asciz	equalsCharObject;
Asciz	(Ljava/lang/Character;Ljava/lang/Object;)Z;
NameAndType	equalsCharObject:(Ljava/lang/Character;Ljava/lang/Object;)Z
Method	scala/runtime/BoxesRunTime.equalsCharObject:(Ljava/lang/Character;Ljava/lang/Object;)Z
Asciz	equalsNumObject;
Asciz	(Ljava/lang/Number;Ljava/lang/Object;)Z;
NameAndType	equalsNumObject:(Ljava/lang/Number;Ljava/lang/Object;)Z
Method	scala/runtime/BoxesRunTime.equalsNumObject:(Ljava/lang/Number;Ljava/lang/Object;)Z
Asciz	java/lang/NullPointerException;
class	java/lang/NullPointerException
Asciz	()V;
NameAndType	"<init>":()V
Method	java/lang/NullPointerException."<init>":()V
Method	java/lang/Object."<init>":()V
Asciz	$init$;
Asciz	(Lscala/Product;)V;
NameAndType	$init$:(Lscala/Product;)V
Method	scala/Product$class.$init$:(Lscala/Product;)V
Asciz	(Lscala/actors/ReactChannel<TMsg;>;Lscala/actors/ReactChannel<TMsg;>;TMsg;)V;
Asciz	Scala;
Asciz	InnerClasses;
Asciz	scala/actors/ReactChannel;
class	scala/actors/ReactChannel
Asciz	scala/ScalaObject;
class	scala/ScalaObject
Asciz	scala/Product;
class	scala/Product
Asciz	java/io/Serializable;
class	java/io/Serializable

{
public final scala.actors.ReactChannel $outer;
  Signature: Lscala/actors/ReactChannel;

private final java.lang.Object msg;
  Signature: Ljava/lang/Object;
  Signature: length = 0x2
   00 07 

private final scala.actors.ReactChannel channel;
  Signature: Lscala/actors/ReactChannel;
  Signature: length = 0x2
   00 0A 

public java.lang.String productElementName(int);
  Signature: (I)Ljava/lang/String;
  Code:
   Stack=2, Locals=2, Args_size=2
	aload_0
	iload_1
	invokestatic	Method scala/Product$class.productElementName:(Lscala/Product;I)Ljava/lang/String;
	areturn
  Labels:
  LocalVariableTable: 
   Start  Length  Slot  Name   Signature
   0      6      0    this       Lscala/actors/ReactChannel$SendToReactor;
   0      6      1    n       I


public scala.collection.Iterator productIterator();
  Signature: ()Lscala/collection/Iterator;
  Code:
   Stack=1, Locals=1, Args_size=1
	aload_0
	invokestatic	Method scala/Product$class.productIterator:(Lscala/Product;)Lscala/collection/Iterator;
	areturn
  Labels:

public scala.collection.Iterator productElements();
  Signature: ()Lscala/collection/Iterator;
  Code:
   Stack=1, Locals=1, Args_size=1
	aload_0
	invokestatic	Method scala/Product$class.productElements:(Lscala/Product;)Lscala/collection/Iterator;
	areturn
  Labels:
  Deprecated: true

public java.lang.Object copy$default$2();
  Signature: ()Ljava/lang/Object;
  Code:
   Stack=1, Locals=1, Args_size=1
	aload_0
	invokevirtual	Method msg:()Ljava/lang/Object;
	areturn
  Labels:

public scala.actors.ReactChannel copy$default$1();
  Signature: ()Lscala/actors/ReactChannel;
  Code:
   Stack=1, Locals=1, Args_size=1
	aload_0
	invokevirtual	Method channel:()Lscala/actors/ReactChannel;
	areturn
  Labels:

public scala.actors.ReactChannel channel();
  Signature: ()Lscala/actors/ReactChannel;
  Code:
   Stack=1, Locals=1, Args_size=1
	aload_0
	getfield	Field channel:Lscala/actors/ReactChannel;
	areturn
  Labels:
  Signature: length = 0x2
   00 2E 

public java.lang.Object msg();
  Signature: ()Ljava/lang/Object;
  Code:
   Stack=1, Locals=1, Args_size=1
	aload_0
	getfield	Field msg:Ljava/lang/Object;
	areturn
  Labels:
  Signature: length = 0x2
   00 31 

public scala.actors.ReactChannel$SendToReactor copy(scala.actors.ReactChannel, java.lang.Object);
  Signature: (Lscala/actors/ReactChannel;Ljava/lang/Object;)Lscala/actors/ReactChannel$SendToReactor;
  Code:
   Stack=5, Locals=3, Args_size=3
	new	class scala/actors/ReactChannel$SendToReactor
	dup
	aload_0
	invokevirtual	Method scala$actors$ReactChannel$SendToReactor$$$outer:()Lscala/actors/ReactChannel;
	aload_1
	aload_2
	invokespecial	Method "<init>":(Lscala/actors/ReactChannel;Lscala/actors/ReactChannel;Ljava/lang/Object;)V
	areturn
  Labels:
  LocalVariableTable: 
   Start  Length  Slot  Name   Signature
   0      14      0    this       Lscala/actors/ReactChannel$SendToReactor;
   0      14      1    channel       Lscala/actors/ReactChannel;
   0      14      2    msg       Ljava/lang/Object;


public int hashCode();
  Signature: ()I
  Code:
   Stack=2, Locals=1, Args_size=1
	getstatic	Field scala/runtime/ScalaRunTime$.MODULE$:Lscala/runtime/ScalaRunTime$;
	aload_0
	invokevirtual	Method scala/runtime/ScalaRunTime$._hashCode:(Lscala/Product;)I
	ireturn
  Labels:

public java.lang.String toString();
  Signature: ()Ljava/lang/String;
  Code:
   Stack=2, Locals=1, Args_size=1
	getstatic	Field scala/runtime/ScalaRunTime$.MODULE$:Lscala/runtime/ScalaRunTime$;
	aload_0
	invokevirtual	Method scala/runtime/ScalaRunTime$._toString:(Lscala/Product;)Ljava/lang/String;
	areturn
  Labels:

public boolean equals(java.lang.Object);
  Signature: (Ljava/lang/Object;)Z
  Code:
   Stack=3, Locals=5, Args_size=2
	aload_0
	aload_1
	if_acmpeq	l1 // iconst_1
	aload_1
	instanceof	class scala/actors/ReactChannel$SendToReactor
	ifeq	l2 // iconst_0
	aload_1
	checkcast	class scala/actors/ReactChannel$SendToReactor
	invokevirtual	Method scala$actors$ReactChannel$SendToReactor$$$outer:()Lscala/actors/ReactChannel;
	aload_0
	invokevirtual	Method scala$actors$ReactChannel$SendToReactor$$$outer:()Lscala/actors/ReactChannel;
	if_acmpne	l2 // iconst_0
	aload_1
	checkcast	class scala/actors/ReactChannel$SendToReactor
	astore_2
	aload_2
	invokevirtual	Method channel:()Lscala/actors/ReactChannel;
	astore_3
	aload_2
	invokevirtual	Method msg:()Ljava/lang/Object;
	astore	4
	aload_0
	aload_3
	aload	4
	invokespecial	Method gd1$1:(Lscala/actors/ReactChannel;Ljava/lang/Object;)Z
	ifeq	l3 // iconst_0
	aload_1
	checkcast	class scala/actors/ReactChannel$SendToReactor
	aload_0
	invokeinterface	InterfaceMethod scala/Equals.canEqual:(Ljava/lang/Object;)Z
	goto	l4 // ifeq
l3	iconst_0
	goto	l4 // ifeq
l2	iconst_0
l4	ifeq	l5 // iconst_0
l1	iconst_1
	goto	l6 // ireturn
l5	iconst_0
l6	ireturn
  Labels:
   	l3 = 65 // iconst_0
   	l2 = 69 // iconst_0
   	l4 = 70 // ifeq
   	l1 = 73 // iconst_1
   	l5 = 77 // iconst_0
   	l6 = 78 // ireturn
  LocalVariableTable: 
   Start  Length  Slot  Name   Signature
   0      79      0    this       Lscala/actors/ReactChannel$SendToReactor;
   31      38      2    temp2       Lscala/actors/ReactChannel$SendToReactor;
   36      33      3    temp3       Lscala/actors/ReactChannel;
   42      27      4    temp4       Ljava/lang/Object;


public java.lang.String productPrefix();
  Signature: ()Ljava/lang/String;
  Code:
   Stack=1, Locals=1, Args_size=1
	ldc	String SendToReactor
	areturn
  Labels:

public int productArity();
  Signature: ()I
  Code:
   Stack=1, Locals=1, Args_size=1
	iconst_2
	ireturn
  Labels:

public java.lang.Object productElement(int);
  Signature: (I)Ljava/lang/Object;
  Code:
   Stack=3, Locals=2, Args_size=2
	iload_1
	tableswitch{ //0 to 1
		0: 46;
		1: 39;
		default: 24 }
	new	class java/lang/IndexOutOfBoundsException
	dup
	iload_1
	invokestatic	Method scala/runtime/BoxesRunTime.boxToInteger:(I)Ljava/lang/Integer;
	invokevirtual	Method java/lang/Object.toString:()Ljava/lang/String;
	invokespecial	Method java/lang/IndexOutOfBoundsException."<init>":(Ljava/lang/String;)V
	athrow
	aload_0
	invokevirtual	Method msg:()Ljava/lang/Object;
	goto	l1 // areturn
	aload_0
	invokevirtual	Method channel:()Lscala/actors/ReactChannel;
l1	areturn
  Labels:
   	l1 = 50 // areturn

public boolean canEqual(java.lang.Object);
  Signature: (Ljava/lang/Object;)Z
  Code:
   Stack=1, Locals=2, Args_size=2
	aload_1
	instanceof	class scala/actors/ReactChannel$SendToReactor
	ireturn
  Labels:

public scala.actors.ReactChannel scala$actors$ReactChannel$SendToReactor$$$outer();
  Signature: ()Lscala/actors/ReactChannel;
  Code:
   Stack=1, Locals=1, Args_size=1
	aload_0
	getfield	Field $outer:Lscala/actors/ReactChannel;
	areturn
  Labels:

private final boolean gd1$1(scala.actors.ReactChannel, java.lang.Object);
  Signature: (Lscala/actors/ReactChannel;Ljava/lang/Object;)Z
  Code:
   Stack=2, Locals=5, Args_size=3
	aload_1
	aload_0
	invokevirtual	Method channel:()Lscala/actors/ReactChannel;
	astore_3
	dup
	ifnonnull	l1 // aload_3
	pop
	aload_3
	ifnull	l2 // aload_0
	goto	l3 // iconst_0
l1	aload_3
	invokevirtual	Method java/lang/Object.equals:(Ljava/lang/Object;)Z
	ifeq	l3 // iconst_0
l2	aload_0
	invokevirtual	Method msg:()Ljava/lang/Object;
	astore	4
	aload_2
	aload	4
	if_acmpeq	l4 // iconst_1
	aload_2
	ifnull	l5 // iconst_0
	aload_2
	instanceof	class java/lang/Number
	ifne	l6 // aload_2
	aload_2
	instanceof	class java/lang/Character
	ifne	l7 // aload_2
	aload_2
	aload	4
	invokevirtual	Method java/lang/Object.equals:(Ljava/lang/Object;)Z
	goto	l8 // ifeq
l7	aload_2
	checkcast	class java/lang/Character
	aload	4
	invokestatic	Method scala/runtime/BoxesRunTime.equalsCharObject:(Ljava/lang/Character;Ljava/lang/Object;)Z
	goto	l8 // ifeq
l6	aload_2
	checkcast	class java/lang/Number
	aload	4
	invokestatic	Method scala/runtime/BoxesRunTime.equalsNumObject:(Ljava/lang/Number;Ljava/lang/Object;)Z
	goto	l8 // ifeq
l5	iconst_0
	goto	l8 // ifeq
l4	iconst_1
l8	ifeq	l3 // iconst_0
	iconst_1
	goto	l9 // ireturn
l3	iconst_0
l9	ireturn
  Labels:
   	l1 = 18 // aload_3
   	l2 = 25 // aload_0
   	l7 = 64 // aload_2
   	l6 = 76 // aload_2
   	l5 = 88 // iconst_0
   	l4 = 92 // iconst_1
   	l8 = 93 // ifeq
   	l3 = 100 // iconst_0
   	l9 = 101 // ireturn
  LocalVariableTable: 
   Start  Length  Slot  Name   Signature
   0      102      0    this       Lscala/actors/ReactChannel$SendToReactor;


public scala.actors.ReactChannel$SendToReactor(scala.actors.ReactChannel, scala.actors.ReactChannel, java.lang.Object);
  Signature: (Lscala/actors/ReactChannel;Lscala/actors/ReactChannel;Ljava/lang/Object;)V
  Code:
   Stack=2, Locals=4, Args_size=4
	aload_0
	aload_2
	putfield	Field channel:Lscala/actors/ReactChannel;
	aload_0
	aload_3
	putfield	Field msg:Ljava/lang/Object;
	aload_1
	ifnonnull	l1 // aload_0
	new	class java/lang/NullPointerException
	dup
	invokespecial	Method java/lang/NullPointerException."<init>":()V
	athrow
l1	aload_0
	aload_1
	putfield	Field $outer:Lscala/actors/ReactChannel;
	aload_0
	invokespecial	Method java/lang/Object."<init>":()V
	aload_0
	invokestatic	Method scala/Product$class.$init$:(Lscala/Product;)V
	return
  Labels:
   	l1 = 22 // aload_0
  LocalVariableTable: 
   Start  Length  Slot  Name   Signature
   0      36      0    this       Lscala/actors/ReactChannel$SendToReactor;
   0      36      1    $outer       Lscala/actors/ReactChannel;
   0      36      2    channel       Lscala/actors/ReactChannel;
   0      36      3    msg       Ljava/lang/Object;

  Signature: length = 0x2
   00 FFFFFF8A 

}

