Compiled from "Reaction.scala"
public class scala.actors.Reaction extends scala.actors.ActorTask implements scala.ScalaObject
  SourceFile: "Reaction.scala"
  ScalaSig: length = 0x110
   05 00 2C 06 08 01 02 FFFFFF84 FFFFFF80 FFFFFF80 FFFFFF80 00 07 02 08 52
   65 61 63 74 69 6F 6E 0A 02 03 04 01 06 61 63 74
   6F 72 73 0A 01 05 01 05 73 63 61 6C 61 03 00 13
   03 00 08 0C 10 02 09 0A 0D 01 02 09 02 0B 02 02
   09 41 63 74 6F 72 54 61 73 6B 10 02 0D 0E 0D 01
   04 09 02 0F 04 02 0B 53 63 61 6C 61 4F 62 6A 65
   63 74 08 08 11 00 FFFFFF82 FFFFFF80 FFFFFFA0 FFFFFF80 04 12 01 01 61 10
   02 09 13 09 02 14 02 02 05 41 63 74 6F 72 08 08
   16 00 FFFFFF82 FFFFFF80 FFFFFFA0 FFFFFF80 04 17 01 01 66 10 04 0D 18 1A
   1D 09 02 19 04 02 0F 50 61 72 74 69 61 6C 46 75
   6E 63 74 69 6F 6E 10 02 0D 1B 09 02 1C 04 02 03
   41 6E 79 10 02 0D 1E 09 02 1F 04 02 04 55 6E 69
   74 08 08 21 00 FFFFFF82 FFFFFF80 FFFFFFA0 FFFFFF80 04 1A 01 03 6D 73 67
   08 05 23 00 FFFFFF84 00 24 01 06 3C 69 6E 69 74 3E 14
   04 25 26 27 28 10 02 09 00 08 05 11 22 FFFFFFC0 00 12
   08 05 16 22 FFFFFFC0 00 17 08 05 21 22 FFFFFFC0 00 1A 08 05
   23 00 FFFFFF84 00 2A 14 02 25 2B 08 05 11 29 FFFFFFC0 00 12
   
  InnerClass: 
   public final #34= #8 of #29; //$anonfun$$init$$1=class scala/actors/Reaction$$anonfun$$init$$1 of class scala/actors/Reaction
  minor version: 0
  major version: 49
  Constant pool:
const #1 = Asciz	SourceFile;
const #2 = Asciz	Reaction.scala;
const #3 = Asciz	<init>;
const #4 = Asciz	(Lscala/actors/Actor;Lscala/PartialFunction;Ljava/lang/Object;)V;
const #5 = Asciz	Code;
const #6 = Asciz	LineNumberTable;
const #7 = Asciz	scala/actors/Reaction$$anonfun$$init$$1;
const #8 = class	#7;	//  scala/actors/Reaction$$anonfun$$init$$1
const #9 = NameAndType	#3:#4;//  "<init>":(Lscala/actors/Actor;Lscala/PartialFunction;Ljava/lang/Object;)V
const #10 = Method	#8.#9;	//  scala/actors/Reaction$$anonfun$$init$$1."<init>":(Lscala/actors/Actor;Lscala/PartialFunction;Ljava/lang/Object;)V
const #11 = Asciz	scala/actors/ActorTask;
const #12 = class	#11;	//  scala/actors/ActorTask
const #13 = Asciz	(Lscala/actors/Actor;Lscala/Function0;)V;
const #14 = NameAndType	#3:#13;//  "<init>":(Lscala/actors/Actor;Lscala/Function0;)V
const #15 = Method	#12.#14;	//  scala/actors/ActorTask."<init>":(Lscala/actors/Actor;Lscala/Function0;)V
const #16 = Asciz	this;
const #17 = Asciz	Lscala/actors/Reaction;;
const #18 = Asciz	a$1;
const #19 = Asciz	Lscala/actors/Actor;;
const #20 = Asciz	f$1;
const #21 = Asciz	Lscala/PartialFunction;;
const #22 = Asciz	msg$1;
const #23 = Asciz	Ljava/lang/Object;;
const #24 = Asciz	LocalVariableTable;
const #25 = Asciz	(Lscala/actors/Actor;Lscala/PartialFunction<Ljava/lang/Object;Ljava/lang/Object;>;Ljava/lang/Object;)V;
const #26 = Asciz	Signature;
const #27 = Asciz	(Lscala/actors/Actor;)V;
const #28 = Asciz	scala/actors/Reaction;
const #29 = class	#28;	//  scala/actors/Reaction
const #30 = Method	#29.#9;	//  scala/actors/Reaction."<init>":(Lscala/actors/Actor;Lscala/PartialFunction;Ljava/lang/Object;)V
const #31 = Asciz	a;
const #32 = Asciz	ScalaSig;
const #33 = Asciz	InnerClasses;
const #34 = Asciz	$anonfun$$init$$1;
const #35 = Asciz	scala/ScalaObject;
const #36 = class	#35;	//  scala/ScalaObject

{
public scala.actors.Reaction(scala.actors.Actor, scala.PartialFunction, java.lang.Object);
  Code:
   Stack=7, Locals=4, Args_size=4
   0:	aload_0
   1:	aload_1
   2:	new	#8; //class scala/actors/Reaction$$anonfun$$init$$1
   5:	dup
   6:	aload_1
   7:	aload_2
   8:	aload_3
   9:	invokespecial	#10; //Method scala/actors/Reaction$$anonfun$$init$$1."<init>":(Lscala/actors/Actor;Lscala/PartialFunction;Ljava/lang/Object;)V
   12:	invokespecial	#15; //Method scala/actors/ActorTask."<init>":(Lscala/actors/Actor;Lscala/Function0;)V
   15:	return
  LineNumberTable: 
   line 29: 0

  LocalVariableTable: 
   Start  Length  Slot  Name   Signature
   0      16      0    this       Lscala/actors/Reaction;
   0      16      1    a$1       Lscala/actors/Actor;
   0      16      2    f$1       Lscala/PartialFunction;
   0      16      3    msg$1       Ljava/lang/Object;

  Signature: length = 0x2
   00 19 

public scala.actors.Reaction(scala.actors.Actor);
  Code:
   Stack=4, Locals=2, Args_size=2
   0:	aload_0
   1:	aload_1
   2:	aconst_null
   3:	aconst_null
   4:	invokespecial	#30; //Method "<init>":(Lscala/actors/Actor;Lscala/PartialFunction;Ljava/lang/Object;)V
   7:	return
  LineNumberTable: 
   line 36: 0

  LocalVariableTable: 
   Start  Length  Slot  Name   Signature
   0      8      0    this       Lscala/actors/Reaction;
   0      8      1    a       Lscala/actors/Actor;


}

