Compiled from "Reactor.scala"
public final class scala.actors.Reactor$$anonfun$startSearch$1 extends java.lang.Object implements scala.Function0,scala.ScalaObject,java.io.Serializable
  SourceFile: "Reactor.scala"
  Scala: length = 0x
   
  InnerClass: 
   public final #87= #9 of #60; //$anonfun$startSearch$1=class scala/actors/Reactor$$anonfun$startSearch$1 of class scala/actors/Reactor
   public final #88= #66 of #9; //$anonfun$apply$2=class scala/actors/Reactor$$anonfun$startSearch$1$$anonfun$apply$2 of class scala/actors/Reactor$$anonfun$startSearch$1
  minor version: 0
  major version: 49
  Constant pool:
const #1 = Asciz	SourceFile;
const #2 = Asciz	Reactor.scala;
const #3 = Asciz	<clinit>;
const #4 = Asciz	()V;
const #5 = Asciz	Code;
const #6 = Asciz	serialVersionUID;
const #7 = Asciz	J;
const #8 = Asciz	scala/actors/Reactor$$anonfun$startSearch$1;
const #9 = class	#8;	//  scala/actors/Reactor$$anonfun$startSearch$1
const #10 = NameAndType	#6:#7;//  serialVersionUID:J
const #11 = Field	#9.#10;	//  scala/actors/Reactor$$anonfun$startSearch$1.serialVersionUID:J
const #12 = Asciz	handler$1;
const #13 = Asciz	Lscala/Function1;;
const #14 = Asciz	replyTo$1;
const #15 = Asciz	Lscala/actors/OutputChannel;;
const #16 = Asciz	msg$1;
const #17 = Asciz	Ljava/lang/Object;;
const #18 = Asciz	$outer;
const #19 = Asciz	Lscala/actors/Reactor;;
const #20 = Asciz	<init>;
const #21 = Asciz	(Lscala/actors/Reactor;Ljava/lang/Object;Lscala/actors/OutputChannel;Lscala/Function1;)V;
const #22 = Asciz	LineNumberTable;
const #23 = Asciz	java/lang/NullPointerException;
const #24 = class	#23;	//  java/lang/NullPointerException
const #25 = NameAndType	#20:#4;//  "<init>":()V
const #26 = Method	#24.#25;	//  java/lang/NullPointerException."<init>":()V
const #27 = NameAndType	#18:#19;//  $outer:Lscala/actors/Reactor;
const #28 = Field	#9.#27;	//  scala/actors/Reactor$$anonfun$startSearch$1.$outer:Lscala/actors/Reactor;
const #29 = NameAndType	#16:#17;//  msg$1:Ljava/lang/Object;
const #30 = Field	#9.#29;	//  scala/actors/Reactor$$anonfun$startSearch$1.msg$1:Ljava/lang/Object;
const #31 = NameAndType	#14:#15;//  replyTo$1:Lscala/actors/OutputChannel;
const #32 = Field	#9.#31;	//  scala/actors/Reactor$$anonfun$startSearch$1.replyTo$1:Lscala/actors/OutputChannel;
const #33 = NameAndType	#12:#13;//  handler$1:Lscala/Function1;
const #34 = Field	#9.#33;	//  scala/actors/Reactor$$anonfun$startSearch$1.handler$1:Lscala/Function1;
const #35 = Asciz	java/lang/Object;
const #36 = class	#35;	//  java/lang/Object
const #37 = Method	#36.#25;	//  java/lang/Object."<init>":()V
const #38 = Asciz	scala/Function0$class;
const #39 = class	#38;	//  scala/Function0$class
const #40 = Asciz	$init$;
const #41 = Asciz	(Lscala/Function0;)V;
const #42 = NameAndType	#40:#41;//  $init$:(Lscala/Function0;)V
const #43 = Method	#39.#42;	//  scala/Function0$class.$init$:(Lscala/Function0;)V
const #44 = Asciz	this;
const #45 = Asciz	Lscala/actors/Reactor$$anonfun$startSearch$1;;
const #46 = Asciz	LocalVariableTable;
const #47 = Asciz	apply;
const #48 = Asciz	()Ljava/lang/Object;;
const #49 = NameAndType	#47:#4;//  apply:()V
const #50 = Method	#9.#49;	//  scala/actors/Reactor$$anonfun$startSearch$1.apply:()V
const #51 = Asciz	scala/runtime/BoxedUnit;
const #52 = class	#51;	//  scala/runtime/BoxedUnit
const #53 = Asciz	UNIT;
const #54 = Asciz	Lscala/runtime/BoxedUnit;;
const #55 = NameAndType	#53:#54;//  UNIT:Lscala/runtime/BoxedUnit;
const #56 = Field	#52.#55;	//  scala/runtime/BoxedUnit.UNIT:Lscala/runtime/BoxedUnit;
const #57 = Asciz	scala$actors$Reactor$$anonfun$$$outer;
const #58 = Asciz	()Lscala/actors/Reactor;;
const #59 = Asciz	scala/actors/Reactor;
const #60 = class	#59;	//  scala/actors/Reactor
const #61 = Asciz	scheduler;
const #62 = Asciz	()Lscala/actors/IScheduler;;
const #63 = NameAndType	#61:#62;//  scheduler:()Lscala/actors/IScheduler;
const #64 = InterfaceMethod	#60.#63;	//  scala/actors/Reactor.scheduler:()Lscala/actors/IScheduler;
const #65 = Asciz	scala/actors/Reactor$$anonfun$startSearch$1$$anonfun$apply$2;
const #66 = class	#65;	//  scala/actors/Reactor$$anonfun$startSearch$1$$anonfun$apply$2
const #67 = Asciz	(Lscala/actors/Reactor$$anonfun$startSearch$1;)V;
const #68 = NameAndType	#20:#67;//  "<init>":(Lscala/actors/Reactor$$anonfun$startSearch$1;)V
const #69 = Method	#66.#68;	//  scala/actors/Reactor$$anonfun$startSearch$1$$anonfun$apply$2."<init>":(Lscala/actors/Reactor$$anonfun$startSearch$1;)V
const #70 = Asciz	makeReaction;
const #71 = Asciz	(Lscala/Function0;)Ljava/lang/Runnable;;
const #72 = NameAndType	#70:#71;//  makeReaction:(Lscala/Function0;)Ljava/lang/Runnable;
const #73 = InterfaceMethod	#60.#72;	//  scala/actors/Reactor.makeReaction:(Lscala/Function0;)Ljava/lang/Runnable;
const #74 = Asciz	scala/actors/IScheduler;
const #75 = class	#74;	//  scala/actors/IScheduler
const #76 = Asciz	execute;
const #77 = Asciz	(Ljava/lang/Runnable;)V;
const #78 = NameAndType	#76:#77;//  execute:(Ljava/lang/Runnable;)V
const #79 = InterfaceMethod	#75.#78;	//  scala/actors/IScheduler.execute:(Ljava/lang/Runnable;)V
const #80 = Asciz	toString;
const #81 = Asciz	()Ljava/lang/String;;
const #82 = Asciz	(Lscala/Function0;)Ljava/lang/String;;
const #83 = NameAndType	#80:#82;//  toString:(Lscala/Function0;)Ljava/lang/String;
const #84 = Method	#39.#83;	//  scala/Function0$class.toString:(Lscala/Function0;)Ljava/lang/String;
const #85 = Asciz	Scala;
const #86 = Asciz	InnerClasses;
const #87 = Asciz	$anonfun$startSearch$1;
const #88 = Asciz	$anonfun$apply$2;
const #89 = Asciz	scala/Function0;
const #90 = class	#89;	//  scala/Function0
const #91 = Asciz	scala/ScalaObject;
const #92 = class	#91;	//  scala/ScalaObject
const #93 = Asciz	java/io/Serializable;
const #94 = class	#93;	//  java/io/Serializable

{
public static final long serialVersionUID;

public final scala.Function1 handler$1;

public final scala.actors.OutputChannel replyTo$1;

public final java.lang.Object msg$1;

public final scala.actors.Reactor $outer;

public static {};
  Code:
   Stack=2, Locals=0, Args_size=0
   0:	lconst_0
   1:	putstatic	#11; //Field serialVersionUID:J
   4:	return

public scala.actors.Reactor$$anonfun$startSearch$1(scala.actors.Reactor, java.lang.Object, scala.actors.OutputChannel, scala.Function1);
  Code:
   Stack=2, Locals=5, Args_size=5
   0:	aload_1
   1:	ifnonnull	12
   4:	new	#24; //class java/lang/NullPointerException
   7:	dup
   8:	invokespecial	#26; //Method java/lang/NullPointerException."<init>":()V
   11:	athrow
   12:	aload_0
   13:	aload_1
   14:	putfield	#28; //Field $outer:Lscala/actors/Reactor;
   17:	aload_0
   18:	aload_2
   19:	putfield	#30; //Field msg$1:Ljava/lang/Object;
   22:	aload_0
   23:	aload_3
   24:	putfield	#32; //Field replyTo$1:Lscala/actors/OutputChannel;
   27:	aload_0
   28:	aload	4
   30:	putfield	#34; //Field handler$1:Lscala/Function1;
   33:	aload_0
   34:	invokespecial	#37; //Method java/lang/Object."<init>":()V
   37:	aload_0
   38:	invokestatic	#43; //Method scala/Function0$class.$init$:(Lscala/Function0;)V
   41:	return
  LineNumberTable: 
   line 95: 0

  LocalVariableTable: 
   Start  Length  Slot  Name   Signature
   0      42      0    this       Lscala/actors/Reactor$$anonfun$startSearch$1;
   0      42      1    $outer       Lscala/actors/Reactor;


public final java.lang.Object apply();
  Code:
   Stack=1, Locals=2, Args_size=1
   0:	aload_0
   1:	getfield	#28; //Field $outer:Lscala/actors/Reactor;
   4:	astore_1
   5:	aload_0
   6:	invokevirtual	#50; //Method apply:()V
   9:	getstatic	#56; //Field scala/runtime/BoxedUnit.UNIT:Lscala/runtime/BoxedUnit;
   12:	areturn
  LineNumberTable: 
   line 95: 0

  LocalVariableTable: 
   Start  Length  Slot  Name   Signature
   0      13      0    this       Lscala/actors/Reactor$$anonfun$startSearch$1;


public scala.actors.Reactor scala$actors$Reactor$$anonfun$$$outer();
  Code:
   Stack=1, Locals=1, Args_size=1
   0:	aload_0
   1:	getfield	#28; //Field $outer:Lscala/actors/Reactor;
   4:	areturn
  LineNumberTable: 
   line 95: 0


public final void apply();
  Code:
   Stack=5, Locals=2, Args_size=1
   0:	aload_0
   1:	getfield	#28; //Field $outer:Lscala/actors/Reactor;
   4:	astore_1
   5:	aload_0
   6:	getfield	#28; //Field $outer:Lscala/actors/Reactor;
   9:	invokeinterface	#64,  1; //InterfaceMethod scala/actors/Reactor.scheduler:()Lscala/actors/IScheduler;
   14:	aload_0
   15:	getfield	#28; //Field $outer:Lscala/actors/Reactor;
   18:	new	#66; //class scala/actors/Reactor$$anonfun$startSearch$1$$anonfun$apply$2
   21:	dup
   22:	aload_0
   23:	invokespecial	#69; //Method scala/actors/Reactor$$anonfun$startSearch$1$$anonfun$apply$2."<init>":(Lscala/actors/Reactor$$anonfun$startSearch$1;)V
   26:	invokeinterface	#73,  2; //InterfaceMethod scala/actors/Reactor.makeReaction:(Lscala/Function0;)Ljava/lang/Runnable;
   31:	invokeinterface	#79,  2; //InterfaceMethod scala/actors/IScheduler.execute:(Ljava/lang/Runnable;)V
   36:	return
  LineNumberTable: 
   line 95: 0

  LocalVariableTable: 
   Start  Length  Slot  Name   Signature
   0      37      0    this       Lscala/actors/Reactor$$anonfun$startSearch$1;


public java.lang.String toString();
  Code:
   Stack=1, Locals=1, Args_size=1
   0:	aload_0
   1:	invokestatic	#84; //Method scala/Function0$class.toString:(Lscala/Function0;)Ljava/lang/String;
   4:	areturn
  LineNumberTable: 
   line 95: 0


}

