Compiled from "ReactorTask.scala"
public class scala.actors.ReactorTask extends scala.concurrent.forkjoin.RecursiveAction implements java.util.concurrent.Callable,java.lang.Runnable,scala.ScalaObject
  SourceFile: "ReactorTask.scala"
  ScalaSig: length = 0x3
   05 00 00 
  Signature: length = 0x2
   00 FFFFFFB2 
  RuntimeVisibleAnnotations: length = 0xB
   00 01 00 FFFFFFB3 00 01 00 FFFFFFB4 73 00 FFFFFFB5 
  InnerClass: 
   public final $anonfun$run$1=class scala/actors/ReactorTask$$anonfun$run$1 of class scala/actors/ReactorTask
  minor version: 0
  major version: 49
  Constant pool:
Asciz	SourceFile;
Asciz	ReactorTask.scala;
Asciz	reactor;
Asciz	Lscala/actors/Reactor;;
Asciz	Lscala/actors/Reactor<TMsg;>;;
Asciz	Signature;
Asciz	fun;
Asciz	Lscala/Function0;;
Asciz	Lscala/Function0<Ljava/lang/Object;>;;
Asciz	handler;
Asciz	Lscala/PartialFunction;;
Asciz	Lscala/PartialFunction<TMsg;Ljava/lang/Object;>;;
Asciz	msg;
Asciz	Ljava/lang/Object;;
Asciz	TMsg;;
Asciz	()Lscala/actors/Reactor;;
Asciz	Code;
Asciz	LineNumberTable;
Asciz	scala/actors/ReactorTask;
class	scala/actors/ReactorTask
NameAndType	reactor:Lscala/actors/Reactor;
Field	scala/actors/ReactorTask.reactor:Lscala/actors/Reactor;
Asciz	()Lscala/actors/Reactor<TMsg;>;;
Asciz	reactor_$eq;
Asciz	(Lscala/actors/Reactor;)V;
Asciz	(Lscala/actors/Reactor<TMsg;>;)V;
Asciz	()Lscala/Function0;;
NameAndType	fun:Lscala/Function0;
Field	scala/actors/ReactorTask.fun:Lscala/Function0;
Asciz	()Lscala/Function0<Ljava/lang/Object;>;;
Asciz	fun_$eq;
Asciz	(Lscala/Function0;)V;
Asciz	(Lscala/Function0<Ljava/lang/Object;>;)V;
Asciz	()Lscala/PartialFunction;;
NameAndType	handler:Lscala/PartialFunction;
Field	scala/actors/ReactorTask.handler:Lscala/PartialFunction;
Asciz	()Lscala/PartialFunction<TMsg;Ljava/lang/Object;>;;
Asciz	handler_$eq;
Asciz	(Lscala/PartialFunction;)V;
Asciz	(Lscala/PartialFunction<TMsg;Ljava/lang/Object;>;)V;
Asciz	()Ljava/lang/Object;;
NameAndType	msg:Ljava/lang/Object;
Field	scala/actors/ReactorTask.msg:Ljava/lang/Object;
Asciz	()TMsg;;
Asciz	msg_$eq;
Asciz	(Ljava/lang/Object;)V;
Asciz	(TMsg;)V;
Asciz	run;
Asciz	()V;
Asciz	beginExecution;
NameAndType	beginExecution:()V
Method	scala/actors/ReactorTask.beginExecution:()V
NameAndType	fun:()Lscala/Function0;
Method	scala/actors/ReactorTask.fun:()Lscala/Function0;
NameAndType	handler:()Lscala/PartialFunction;
Method	scala/actors/ReactorTask.handler:()Lscala/PartialFunction;
NameAndType	msg:()Ljava/lang/Object;
Method	scala/actors/ReactorTask.msg:()Ljava/lang/Object;
Asciz	scala/Function1;
class	scala/Function1
Asciz	apply;
Asciz	(Ljava/lang/Object;)Ljava/lang/Object;;
NameAndType	apply:(Ljava/lang/Object;)Ljava/lang/Object;
InterfaceMethod	scala/Function1.apply:(Ljava/lang/Object;)Ljava/lang/Object;
Asciz	scala/Function0;
class	scala/Function0
NameAndType	apply:()Ljava/lang/Object;
InterfaceMethod	scala/Function0.apply:()Ljava/lang/Object;
Asciz	java/lang/Exception;
class	java/lang/Exception
Asciz	gd1$1;
Asciz	(Ljava/lang/Exception;)Z;
NameAndType	gd1$1:(Ljava/lang/Exception;)Z
Method	scala/actors/ReactorTask.gd1$1:(Ljava/lang/Exception;)Z
NameAndType	reactor:()Lscala/actors/Reactor;
Method	scala/actors/ReactorTask.reactor:()Lscala/actors/Reactor;
Asciz	scala/actors/Reactor;
class	scala/actors/Reactor
Asciz	exceptionHandler;
NameAndType	exceptionHandler:()Lscala/PartialFunction;
InterfaceMethod	scala/actors/Reactor.exceptionHandler:()Lscala/PartialFunction;
Asciz	kill;
NameAndType	kill:()Lscala/Function0;
InterfaceMethod	scala/actors/Reactor.kill:()Lscala/Function0;
Asciz	apply$mcV$sp;
NameAndType	apply$mcV$sp:()V
InterfaceMethod	scala/Function0.apply$mcV$sp:()V
Asciz	suspendExecution;
NameAndType	suspendExecution:()V
Method	scala/actors/ReactorTask.suspendExecution:()V
NameAndType	reactor_$eq:(Lscala/actors/Reactor;)V
Method	scala/actors/ReactorTask.reactor_$eq:(Lscala/actors/Reactor;)V
NameAndType	fun_$eq:(Lscala/Function0;)V
Method	scala/actors/ReactorTask.fun_$eq:(Lscala/Function0;)V
NameAndType	handler_$eq:(Lscala/PartialFunction;)V
Method	scala/actors/ReactorTask.handler_$eq:(Lscala/PartialFunction;)V
NameAndType	msg_$eq:(Ljava/lang/Object;)V
Method	scala/actors/ReactorTask.msg_$eq:(Ljava/lang/Object;)V
Asciz	scala/collection/mutable/StringBuilder;
class	scala/collection/mutable/StringBuilder
Asciz	<init>;
NameAndType	"<init>":()V
Method	scala/collection/mutable/StringBuilder."<init>":()V
Asciz	Uncaught exception in ;
String	Uncaught exception in 
Asciz	append;
Asciz	(Ljava/lang/Object;)Lscala/collection/mutable/StringBuilder;;
NameAndType	append:(Ljava/lang/Object;)Lscala/collection/mutable/StringBuilder;
Method	scala/collection/mutable/StringBuilder.append:(Ljava/lang/Object;)Lscala/collection/mutable/StringBuilder;
Asciz	\n;
String	\n
Asciz	toString;
Asciz	()Ljava/lang/String;;
NameAndType	toString:()Ljava/lang/String;
Method	scala/collection/mutable/StringBuilder.toString:()Ljava/lang/String;
Asciz	;
String	
Asciz	Message: ;
String	Message: 
Asciz	scala/actors/Debug$;
class	scala/actors/Debug$
Asciz	MODULE$;
Asciz	Lscala/actors/Debug$;;
NameAndType	MODULE$:Lscala/actors/Debug$;
Field	scala/actors/Debug$.MODULE$:Lscala/actors/Debug$;
Asciz	scala/actors/ReactorTask$$anonfun$run$1;
class	scala/actors/ReactorTask$$anonfun$run$1
Asciz	(Lscala/actors/ReactorTask;Ljava/lang/Exception;Ljava/lang/String;Ljava/lang/String;)V;
NameAndType	"<init>":(Lscala/actors/ReactorTask;Ljava/lang/Exception;Ljava/lang/String;Ljava/lang/String;)V
Method	scala/actors/ReactorTask$$anonfun$run$1."<init>":(Lscala/actors/ReactorTask;Ljava/lang/Exception;Ljava/lang/String;Ljava/lang/String;)V
Asciz	doWarning;
NameAndType	doWarning:(Lscala/Function0;)V
Method	scala/actors/Debug$.doWarning:(Lscala/Function0;)V
Asciz	terminateExecution;
Asciz	(Ljava/lang/Exception;)V;
NameAndType	terminateExecution:(Ljava/lang/Exception;)V
Method	scala/actors/ReactorTask.terminateExecution:(Ljava/lang/Exception;)V
Asciz	terminated;
NameAndType	terminated:()V
InterfaceMethod	scala/actors/Reactor.terminated:()V
Asciz	scala/actors/KillActorControl;
class	scala/actors/KillActorControl
Asciz	scala/actors/SuspendActorControl;
class	scala/actors/SuspendActorControl
Asciz	this;
Asciz	Lscala/actors/ReactorTask;;
Asciz	temp2;
Asciz	Ljava/lang/Exception;;
Asciz	msgException$1;
Asciz	Ljava/lang/String;;
Asciz	msgMessage$1;
Asciz	LocalVariableTable;
Asciz	call;
NameAndType	run:()V
Method	scala/actors/ReactorTask.run:()V
Asciz	compute;
Asciz	e;
NameAndType	call:()V
Method	scala/actors/ReactorTask.call:()V
Asciz	scala/runtime/BoxedUnit;
class	scala/runtime/BoxedUnit
Asciz	UNIT;
Asciz	Lscala/runtime/BoxedUnit;;
NameAndType	UNIT:Lscala/runtime/BoxedUnit;
Field	scala/runtime/BoxedUnit.UNIT:Lscala/runtime/BoxedUnit;
Asciz	scala/PartialFunction;
class	scala/PartialFunction
Asciz	isDefinedAt;
Asciz	(Ljava/lang/Object;)Z;
NameAndType	isDefinedAt:(Ljava/lang/Object;)Z
InterfaceMethod	scala/PartialFunction.isDefinedAt:(Ljava/lang/Object;)Z
Asciz	(Lscala/actors/Reactor;Lscala/Function0;Lscala/PartialFunction;Ljava/lang/Object;)V;
Asciz	scala/concurrent/forkjoin/RecursiveAction;
class	scala/concurrent/forkjoin/RecursiveAction
Method	scala/concurrent/forkjoin/RecursiveAction."<init>":()V
Asciz	(Lscala/actors/Reactor<TMsg;>;Lscala/Function0<Ljava/lang/Object;>;Lscala/PartialFunction<TMsg;Ljava/lang/Object;>;TMsg;)V;
Asciz	ScalaSig;
Asciz	<Msg:Ljava/lang/Object;>Lscala/concurrent/forkjoin/RecursiveAction;Ljava/util/concurrent/Callable<Ljava/lang/Object;>;Ljava/lang/Runnable;Lscala/ScalaObject;;
Asciz	Lscala/reflect/ScalaSignature;;
Asciz	bytes;
Asciz	-a!B\t1!a*fC$xN+bg.T!a\rGo:t)!B:dC2WCA1'E$!\tIa\"D\tYA\"g_J\'n\5o\tiA!d_:WO:f]RL!aI+7-:tSZ,i;j_:2!E\"BA\t!R#vi&d'\"\t)g/Y1IbQ1mYG.\t5miB9A!8jiBa$I?)%FYtw-#?\tA!+8oC\ndW\rI%Q'G.Y(cUG(\t\r\"*X-Y2u_J!F+!\rYCFL%QF%7\r^8s!\tyEA!ACI1!T:h#\tdi%QVdGo%:LIAI,m;pe~#S-3qBq!P!&AyIEBbKAK\te7\r^8sA!A\tBA!)Agk:,a\t53BA#%1UO\2uS>tH\t\r\"I1WO\0%KF$\"!G%\tu2!a\"A1\nBB&1)gk:C'I(!g7feV\tq\n!:2BA)=M;jC24UO\2uS>tC*I+!g7fe~#S-3UCq!*q\nX\t\t)P!AM3mKJC-I.5x-F/!aA!a\niaB7tO~#S-3yCq!P.aa\t\t)/i7o\t\tAA2\rqJg.;?)!WMZ4i!\rYAO\rA\ra\ra3\rAU!\ta[eVtG#A\r\t5AA6\t\rG_!\ta[G>l/;f\t\"l9WmZ5ob,7-;j_:DQa-c];tatG-=fGV$n8\tUA<%Q,'/\5oCR,W\t_3dkRLwN3]DQ;Ae!\tuabA>9Ap`{*aKyI|w \nI1!amY6bOLA!a\n\tIQ\t_2faRLwN!;
Asciz	RuntimeVisibleAnnotations;
Asciz	InnerClasses;
Asciz	$anonfun$run$1;
Asciz	java/util/concurrent/Callable;
class	java/util/concurrent/Callable
Asciz	java/lang/Runnable;
class	java/lang/Runnable
Asciz	scala/ScalaObject;
class	scala/ScalaObject

{
private scala.actors.Reactor reactor;
  Signature: Lscala/actors/Reactor;
  Signature: length = 0x2
   00 05 

private scala.Function0 fun;
  Signature: Lscala/Function0;
  Signature: length = 0x2
   00 09 

private scala.PartialFunction handler;
  Signature: Lscala/PartialFunction;
  Signature: length = 0x2
   00 0C 

private java.lang.Object msg;
  Signature: Ljava/lang/Object;
  Signature: length = 0x2
   00 0F 

public scala.actors.Reactor reactor();
  Signature: ()Lscala/actors/Reactor;
  Code:
   Stack=1, Locals=1, Args_size=1
	aload_0
	getfield	Field reactor:Lscala/actors/Reactor;
	areturn
  Labels:
  Signature: length = 0x2
   00 17 

public void reactor_$eq(scala.actors.Reactor);
  Signature: (Lscala/actors/Reactor;)V
  Code:
   Stack=2, Locals=2, Args_size=2
	aload_0
	aload_1
	putfield	Field reactor:Lscala/actors/Reactor;
	return
  Labels:
  Signature: length = 0x2
   00 1A 

public scala.Function0 fun();
  Signature: ()Lscala/Function0;
  Code:
   Stack=1, Locals=1, Args_size=1
	aload_0
	getfield	Field fun:Lscala/Function0;
	areturn
  Labels:
  Signature: length = 0x2
   00 1E 

public void fun_$eq(scala.Function0);
  Signature: (Lscala/Function0;)V
  Code:
   Stack=2, Locals=2, Args_size=2
	aload_0
	aload_1
	putfield	Field fun:Lscala/Function0;
	return
  Labels:
  Signature: length = 0x2
   00 21 

public scala.PartialFunction handler();
  Signature: ()Lscala/PartialFunction;
  Code:
   Stack=1, Locals=1, Args_size=1
	aload_0
	getfield	Field handler:Lscala/PartialFunction;
	areturn
  Labels:
  Signature: length = 0x2
   00 25 

public void handler_$eq(scala.PartialFunction);
  Signature: (Lscala/PartialFunction;)V
  Code:
   Stack=2, Locals=2, Args_size=2
	aload_0
	aload_1
	putfield	Field handler:Lscala/PartialFunction;
	return
  Labels:
  Signature: length = 0x2
   00 28 

public java.lang.Object msg();
  Signature: ()Ljava/lang/Object;
  Code:
   Stack=1, Locals=1, Args_size=1
	aload_0
	getfield	Field msg:Ljava/lang/Object;
	areturn
  Labels:
  Signature: length = 0x2
   00 2C 

public void msg_$eq(java.lang.Object);
  Signature: (Ljava/lang/Object;)V
  Code:
   Stack=2, Locals=2, Args_size=2
	aload_0
	aload_1
	putfield	Field msg:Ljava/lang/Object;
	return
  Labels:
  Signature: length = 0x2
   00 2F 

public void run();
  Signature: ()V
  Code:
   Stack=7, Locals=7, Args_size=1
	aload_0
	invokevirtual	Method beginExecution:()V
	aload_0
	invokevirtual	Method fun:()Lscala/Function0;
	ifnonnull	l1 // aload_0
	aload_0
	invokevirtual	Method handler:()Lscala/PartialFunction;
	aload_0
	invokevirtual	Method msg:()Ljava/lang/Object;
	invokeinterface	InterfaceMethod scala/Function1.apply:(Ljava/lang/Object;)Ljava/lang/Object;
	pop
	goto	l2 // goto
l1	aload_0
	invokevirtual	Method fun:()Lscala/Function0;
	invokeinterface	InterfaceMethod scala/Function0.apply:()Ljava/lang/Object;
	pop
l2	goto	l3 // goto
	astore_2
	aload_2
	instanceof	class java/lang/Exception
	ifeq	l4 // aload_2
	aload_2
	checkcast	class java/lang/Exception
	astore_1
	aload_0
	aload_1
	invokespecial	Method gd1$1:(Ljava/lang/Exception;)Z
	ifeq	l5 // aload_2
	aload_0
	invokevirtual	Method reactor:()Lscala/actors/Reactor;
	invokeinterface	InterfaceMethod scala/actors/Reactor.exceptionHandler:()Lscala/PartialFunction;
	aload_1
	invokeinterface	InterfaceMethod scala/Function1.apply:(Ljava/lang/Object;)Ljava/lang/Object;
	pop
l3	goto	l6 // aload_0
l5	aload_2
	athrow
l4	aload_2
	athrow
	pop
l6	aload_0
	invokevirtual	Method reactor:()Lscala/actors/Reactor;
	invokeinterface	InterfaceMethod scala/actors/Reactor.kill:()Lscala/Function0;
	invokeinterface	InterfaceMethod scala/Function0.apply$mcV$sp:()V
	aload_0
	invokevirtual	Method suspendExecution:()V
	aload_0
	aconst_null
	invokevirtual	Method reactor_$eq:(Lscala/actors/Reactor;)V
	aload_0
	aconst_null
	invokevirtual	Method fun_$eq:(Lscala/Function0;)V
	aload_0
	aconst_null
	invokevirtual	Method handler_$eq:(Lscala/PartialFunction;)V
	aload_0
	aconst_null
	invokevirtual	Method msg_$eq:(Ljava/lang/Object;)V
	goto	l7 // return
	pop
	aload_0
	invokevirtual	Method suspendExecution:()V
	aload_0
	aconst_null
	invokevirtual	Method reactor_$eq:(Lscala/actors/Reactor;)V
	aload_0
	aconst_null
	invokevirtual	Method fun_$eq:(Lscala/Function0;)V
	aload_0
	aconst_null
	invokevirtual	Method handler_$eq:(Lscala/PartialFunction;)V
	aload_0
	aconst_null
	invokevirtual	Method msg_$eq:(Ljava/lang/Object;)V
	goto	l7 // return
	astore	5
	new	class scala/collection/mutable/StringBuilder
	dup
	invokespecial	Method scala/collection/mutable/StringBuilder."<init>":()V
	ldc	String Uncaught exception in 
	invokevirtual	Method scala/collection/mutable/StringBuilder.append:(Ljava/lang/Object;)Lscala/collection/mutable/StringBuilder;
	aload_0
	invokevirtual	Method reactor:()Lscala/actors/Reactor;
	invokevirtual	Method scala/collection/mutable/StringBuilder.append:(Ljava/lang/Object;)Lscala/collection/mutable/StringBuilder;
	ldc	String \n
	invokevirtual	Method scala/collection/mutable/StringBuilder.append:(Ljava/lang/Object;)Lscala/collection/mutable/StringBuilder;
	invokevirtual	Method scala/collection/mutable/StringBuilder.toString:()Ljava/lang/String;
	astore_3
	aload_0
	invokevirtual	Method msg:()Ljava/lang/Object;
	ifnonnull	l8 // new
	ldc	String 
	goto	l9 // astore
l8	new	class scala/collection/mutable/StringBuilder
	dup
	invokespecial	Method scala/collection/mutable/StringBuilder."<init>":()V
	ldc	String Message: 
	invokevirtual	Method scala/collection/mutable/StringBuilder.append:(Ljava/lang/Object;)Lscala/collection/mutable/StringBuilder;
	aload_0
	invokevirtual	Method msg:()Ljava/lang/Object;
	invokevirtual	Method scala/collection/mutable/StringBuilder.append:(Ljava/lang/Object;)Lscala/collection/mutable/StringBuilder;
	ldc	String \n
	invokevirtual	Method scala/collection/mutable/StringBuilder.append:(Ljava/lang/Object;)Lscala/collection/mutable/StringBuilder;
	invokevirtual	Method scala/collection/mutable/StringBuilder.toString:()Ljava/lang/String;
l9	astore	4
	getstatic	Field scala/actors/Debug$.MODULE$:Lscala/actors/Debug$;
	new	class scala/actors/ReactorTask$$anonfun$run$1
	dup
	aload_0
	aload	5
	aload_3
	aload	4
	invokespecial	Method scala/actors/ReactorTask$$anonfun$run$1."<init>":(Lscala/actors/ReactorTask;Ljava/lang/Exception;Ljava/lang/String;Ljava/lang/String;)V
	invokevirtual	Method scala/actors/Debug$.doWarning:(Lscala/Function0;)V
	aload_0
	aload	5
	invokevirtual	Method terminateExecution:(Ljava/lang/Exception;)V
	aload_0
	invokevirtual	Method reactor:()Lscala/actors/Reactor;
	invokeinterface	InterfaceMethod scala/actors/Reactor.terminated:()V
	aload_0
	invokevirtual	Method suspendExecution:()V
	aload_0
	aconst_null
	invokevirtual	Method reactor_$eq:(Lscala/actors/Reactor;)V
	aload_0
	aconst_null
	invokevirtual	Method fun_$eq:(Lscala/Function0;)V
	aload_0
	aconst_null
	invokevirtual	Method handler_$eq:(Lscala/PartialFunction;)V
	aload_0
	aconst_null
	invokevirtual	Method msg_$eq:(Ljava/lang/Object;)V
l7	return
	astore	6
	aload_0
	invokevirtual	Method suspendExecution:()V
	aload_0
	aconst_null
	invokevirtual	Method reactor_$eq:(Lscala/actors/Reactor;)V
	aload_0
	aconst_null
	invokevirtual	Method fun_$eq:(Lscala/Function0;)V
	aload_0
	aconst_null
	invokevirtual	Method handler_$eq:(Lscala/PartialFunction;)V
	aload_0
	aconst_null
	invokevirtual	Method msg_$eq:(Ljava/lang/Object;)V
	aload	6
	athrow
  Labels:
   	l1 = 28 // aload_0
   	l2 = 38 // goto
   	l3 = 78 // goto
   	l5 = 81 // aload_2
   	l4 = 83 // aload_2
   	l6 = 86 // aload_0
   	l8 = 197 // new
   	l9 = 224 // astore
   	l7 = 284 // return
  Exception table:
   from   to  target type
     4    41    41   any
     4    85    85   Class scala/actors/KillActorControl

     0   100   127   Class scala/actors/SuspendActorControl

     0   100   155   Class java/lang/Exception

     0   100   285   any
   127   128   285   any
   155   260   285   any
  LocalVariableTable: 
   Start  Length  Slot  Name   Signature
   0      314      0    this       Lscala/actors/ReactorTask;
   54      24      1    temp2       Ljava/lang/Exception;
   81      2      1    temp2       Ljava/lang/Exception;
   185      75      3    msgException$1       Ljava/lang/String;
   226      34      4    msgMessage$1       Ljava/lang/String;


public void call();
  Signature: ()V
  Code:
   Stack=1, Locals=1, Args_size=1
	aload_0
	invokevirtual	Method run:()V
	return
  Labels:

public void compute();
  Signature: ()V
  Code:
   Stack=1, Locals=1, Args_size=1
	aload_0
	invokevirtual	Method run:()V
	return
  Labels:

public void beginExecution();
  Signature: ()V
  Code:
   Stack=0, Locals=1, Args_size=1
	return
  Labels:

public void suspendExecution();
  Signature: ()V
  Code:
   Stack=0, Locals=1, Args_size=1
	return
  Labels:

public void terminateExecution(java.lang.Exception);
  Signature: (Ljava/lang/Exception;)V
  Code:
   Stack=0, Locals=2, Args_size=2
	return
  Labels:
  LocalVariableTable: 
   Start  Length  Slot  Name   Signature
   0      1      0    this       Lscala/actors/ReactorTask;
   0      1      1    e       Ljava/lang/Exception;


public java.lang.Object call();
  Signature: ()Ljava/lang/Object;
  Code:
   Stack=1, Locals=1, Args_size=1
	aload_0
	invokevirtual	Method call:()V
	getstatic	Field scala/runtime/BoxedUnit.UNIT:Lscala/runtime/BoxedUnit;
	areturn
  Labels:

private final boolean gd1$1(java.lang.Exception);
  Signature: (Ljava/lang/Exception;)Z
  Code:
   Stack=2, Locals=2, Args_size=2
	aload_0
	invokevirtual	Method reactor:()Lscala/actors/Reactor;
	invokeinterface	InterfaceMethod scala/actors/Reactor.exceptionHandler:()Lscala/PartialFunction;
	aload_1
	invokeinterface	InterfaceMethod scala/PartialFunction.isDefinedAt:(Ljava/lang/Object;)Z
	ireturn
  Labels:

public scala.actors.ReactorTask(scala.actors.Reactor, scala.Function0, scala.PartialFunction, java.lang.Object);
  Signature: (Lscala/actors/Reactor;Lscala/Function0;Lscala/PartialFunction;Ljava/lang/Object;)V
  Code:
   Stack=2, Locals=5, Args_size=5
	aload_0
	aload_1
	putfield	Field reactor:Lscala/actors/Reactor;
	aload_0
	aload_2
	putfield	Field fun:Lscala/Function0;
	aload_0
	aload_3
	putfield	Field handler:Lscala/PartialFunction;
	aload_0
	aload	4
	putfield	Field msg:Ljava/lang/Object;
	aload_0
	invokespecial	Method scala/concurrent/forkjoin/RecursiveAction."<init>":()V
	return
  Labels:
  LocalVariableTable: 
   Start  Length  Slot  Name   Signature
   0      26      0    this       Lscala/actors/ReactorTask;
   0      26      1    reactor       Lscala/actors/Reactor;
   0      26      2    fun       Lscala/Function0;
   0      26      3    handler       Lscala/PartialFunction;
   0      26      4    msg       Ljava/lang/Object;

  Signature: length = 0x2
   00 FFFFFFB0 

}

