Compiled from "ReactorTask.scala"
public final class scala.actors.ReactorTask$$anonfun$run$1 extends scala.runtime.AbstractFunction0$mcV$sp implements java.io.Serializable
  SourceFile: "ReactorTask.scala"
  Scala: length = 0x
   
  InnerClass: 
   public final $anonfun$run$1=class scala/actors/ReactorTask$$anonfun$run$1 of class scala/actors/ReactorTask
  minor version: 0
  major version: 49
  Constant pool:
Asciz	SourceFile;
Asciz	ReactorTask.scala;
Asciz	<clinit>;
Asciz	()V;
Asciz	Code;
Asciz	serialVersionUID;
Asciz	J;
Asciz	scala/actors/ReactorTask$$anonfun$run$1;
class	scala/actors/ReactorTask$$anonfun$run$1
NameAndType	serialVersionUID:J
Field	scala/actors/ReactorTask$$anonfun$run$1.serialVersionUID:J
Asciz	e$1;
Asciz	Ljava/lang/Exception;;
Asciz	msgException$1;
Asciz	Ljava/lang/String;;
Asciz	msgMessage$1;
Asciz	apply;
Asciz	scala/Console$;
class	scala/Console$
Asciz	MODULE$;
Asciz	Lscala/Console$;;
NameAndType	MODULE$:Lscala/Console$;
Field	scala/Console$.MODULE$:Lscala/Console$;
Asciz	LineNumberTable;
Asciz	err;
Asciz	()Ljava/io/PrintStream;;
NameAndType	err:()Ljava/io/PrintStream;
Method	scala/Console$.err:()Ljava/io/PrintStream;
Asciz	scala/collection/mutable/StringBuilder;
class	scala/collection/mutable/StringBuilder
Asciz	<init>;
NameAndType	"<init>":()V
Method	scala/collection/mutable/StringBuilder."<init>":()V
NameAndType	msgException$1:Ljava/lang/String;
Field	scala/actors/ReactorTask$$anonfun$run$1.msgException$1:Ljava/lang/String;
Asciz	append;
Asciz	(Ljava/lang/Object;)Lscala/collection/mutable/StringBuilder;;
NameAndType	append:(Ljava/lang/Object;)Lscala/collection/mutable/StringBuilder;
Method	scala/collection/mutable/StringBuilder.append:(Ljava/lang/Object;)Lscala/collection/mutable/StringBuilder;
NameAndType	msgMessage$1:Ljava/lang/String;
Field	scala/actors/ReactorTask$$anonfun$run$1.msgMessage$1:Ljava/lang/String;
Asciz	toString;
Asciz	()Ljava/lang/String;;
NameAndType	toString:()Ljava/lang/String;
Method	scala/collection/mutable/StringBuilder.toString:()Ljava/lang/String;
Asciz	java/io/PrintStream;
class	java/io/PrintStream
Asciz	print;
Asciz	(Ljava/lang/String;)V;
NameAndType	print:(Ljava/lang/String;)V
Method	java/io/PrintStream.print:(Ljava/lang/String;)V
NameAndType	e$1:Ljava/lang/Exception;
Field	scala/actors/ReactorTask$$anonfun$run$1.e$1:Ljava/lang/Exception;
Asciz	java/lang/Exception;
class	java/lang/Exception
Asciz	printStackTrace;
NameAndType	printStackTrace:()V
Method	java/lang/Exception.printStackTrace:()V
Asciz	apply$mcV$sp;
Asciz	()Ljava/lang/Object;;
NameAndType	apply:()V
Method	scala/actors/ReactorTask$$anonfun$run$1.apply:()V
Asciz	scala/runtime/BoxedUnit;
class	scala/runtime/BoxedUnit
Asciz	UNIT;
Asciz	Lscala/runtime/BoxedUnit;;
NameAndType	UNIT:Lscala/runtime/BoxedUnit;
Field	scala/runtime/BoxedUnit.UNIT:Lscala/runtime/BoxedUnit;
Asciz	(Lscala/actors/ReactorTask;Ljava/lang/Exception;Ljava/lang/String;Ljava/lang/String;)V;
Asciz	scala/runtime/AbstractFunction0$mcV$sp;
class	scala/runtime/AbstractFunction0$mcV$sp
Method	scala/runtime/AbstractFunction0$mcV$sp."<init>":()V
Asciz	this;
Asciz	Lscala/actors/ReactorTask$$anonfun$run$1;;
Asciz	$outer;
Asciz	Lscala/actors/ReactorTask;;
Asciz	LocalVariableTable;
Asciz	(Lscala/actors/ReactorTask<TMsg;>;)V;
Asciz	Signature;
Asciz	Scala;
Asciz	InnerClasses;
Asciz	scala/actors/ReactorTask;
class	scala/actors/ReactorTask
Asciz	$anonfun$run$1;
Asciz	java/io/Serializable;
class	java/io/Serializable

{
public static final long serialVersionUID;
  Signature: J

public final java.lang.Exception e$1;
  Signature: Ljava/lang/Exception;

public final java.lang.String msgException$1;
  Signature: Ljava/lang/String;

public final java.lang.String msgMessage$1;
  Signature: Ljava/lang/String;

public static {};
  Signature: ()V
  Code:
   Stack=2, Locals=0, Args_size=0
	lconst_0
	putstatic	Field serialVersionUID:J
	return
  Labels:

public final void apply();
  Signature: ()V
  Code:
   Stack=3, Locals=1, Args_size=1
	getstatic	Field scala/Console$.MODULE$:Lscala/Console$;
	invokevirtual	Method scala/Console$.err:()Ljava/io/PrintStream;
	new	class scala/collection/mutable/StringBuilder
	dup
	invokespecial	Method scala/collection/mutable/StringBuilder."<init>":()V
	aload_0
	getfield	Field msgException$1:Ljava/lang/String;
	invokevirtual	Method scala/collection/mutable/StringBuilder.append:(Ljava/lang/Object;)Lscala/collection/mutable/StringBuilder;
	aload_0
	getfield	Field msgMessage$1:Ljava/lang/String;
	invokevirtual	Method scala/collection/mutable/StringBuilder.append:(Ljava/lang/Object;)Lscala/collection/mutable/StringBuilder;
	invokevirtual	Method scala/collection/mutable/StringBuilder.toString:()Ljava/lang/String;
	invokevirtual	Method java/io/PrintStream.print:(Ljava/lang/String;)V
	aload_0
	getfield	Field e$1:Ljava/lang/Exception;
	invokevirtual	Method java/lang/Exception.printStackTrace:()V
	return
  Labels:

public void apply$mcV$sp();
  Signature: ()V
  Code:
   Stack=3, Locals=1, Args_size=1
	getstatic	Field scala/Console$.MODULE$:Lscala/Console$;
	invokevirtual	Method scala/Console$.err:()Ljava/io/PrintStream;
	new	class scala/collection/mutable/StringBuilder
	dup
	invokespecial	Method scala/collection/mutable/StringBuilder."<init>":()V
	aload_0
	getfield	Field msgException$1:Ljava/lang/String;
	invokevirtual	Method scala/collection/mutable/StringBuilder.append:(Ljava/lang/Object;)Lscala/collection/mutable/StringBuilder;
	aload_0
	getfield	Field msgMessage$1:Ljava/lang/String;
	invokevirtual	Method scala/collection/mutable/StringBuilder.append:(Ljava/lang/Object;)Lscala/collection/mutable/StringBuilder;
	invokevirtual	Method scala/collection/mutable/StringBuilder.toString:()Ljava/lang/String;
	invokevirtual	Method java/io/PrintStream.print:(Ljava/lang/String;)V
	aload_0
	getfield	Field e$1:Ljava/lang/Exception;
	invokevirtual	Method java/lang/Exception.printStackTrace:()V
	return
  Labels:

public final java.lang.Object apply();
  Signature: ()Ljava/lang/Object;
  Code:
   Stack=1, Locals=1, Args_size=1
	aload_0
	invokevirtual	Method apply:()V
	getstatic	Field scala/runtime/BoxedUnit.UNIT:Lscala/runtime/BoxedUnit;
	areturn
  Labels:

public scala.actors.ReactorTask$$anonfun$run$1(scala.actors.ReactorTask, java.lang.Exception, java.lang.String, java.lang.String);
  Signature: (Lscala/actors/ReactorTask;Ljava/lang/Exception;Ljava/lang/String;Ljava/lang/String;)V
  Code:
   Stack=2, Locals=5, Args_size=5
	aload_0
	aload_2
	putfield	Field e$1:Ljava/lang/Exception;
	aload_0
	aload_3
	putfield	Field msgException$1:Ljava/lang/String;
	aload_0
	aload	4
	putfield	Field msgMessage$1:Ljava/lang/String;
	aload_0
	invokespecial	Method scala/runtime/AbstractFunction0$mcV$sp."<init>":()V
	return
  Labels:
  LocalVariableTable: 
   Start  Length  Slot  Name   Signature
   0      21      0    this       Lscala/actors/ReactorTask$$anonfun$run$1;
   0      21      1    $outer       Lscala/actors/ReactorTask;

  Signature: length = 0x2
   00 4E 

}

