Compiled from "ReactChannel.scala"
public final class scala.actors.ReactChannel$$anonfun$react$1 extends java.lang.Object implements scala.PartialFunction,java.io.Serializable
  SourceFile: "ReactChannel.scala"
  Scala: length = 0x
   
  InnerClass: 
   public SendToReactor=class scala/actors/ReactChannel$SendToReactor of class scala/actors/ReactChannel
   public final $anonfun$react$1=class scala/actors/ReactChannel$$anonfun$react$1 of class scala/actors/ReactChannel
  minor version: 0
  major version: 49
  Constant pool:
Asciz	SourceFile;
Asciz	ReactChannel.scala;
Asciz	<clinit>;
Asciz	()V;
Asciz	Code;
Asciz	serialVersionUID;
Asciz	J;
Asciz	scala/actors/ReactChannel$$anonfun$react$1;
class	scala/actors/ReactChannel$$anonfun$react$1
NameAndType	serialVersionUID:J
Field	scala/actors/ReactChannel$$anonfun$react$1.serialVersionUID:J
Asciz	C$1;
Asciz	Lscala/actors/ReactChannel;;
Asciz	f$1;
Asciz	Lscala/PartialFunction;;
Asciz	$outer;
Asciz	<init>;
Asciz	(Lscala/actors/ReactChannel;Lscala/PartialFunction;Lscala/actors/ReactChannel;)V;
Asciz	LineNumberTable;
Asciz	java/lang/NullPointerException;
class	java/lang/NullPointerException
NameAndType	"<init>":()V
Method	java/lang/NullPointerException."<init>":()V
NameAndType	$outer:Lscala/actors/ReactChannel;
Field	scala/actors/ReactChannel$$anonfun$react$1.$outer:Lscala/actors/ReactChannel;
NameAndType	f$1:Lscala/PartialFunction;
Field	scala/actors/ReactChannel$$anonfun$react$1.f$1:Lscala/PartialFunction;
NameAndType	C$1:Lscala/actors/ReactChannel;
Field	scala/actors/ReactChannel$$anonfun$react$1.C$1:Lscala/actors/ReactChannel;
Asciz	java/lang/Object;
class	java/lang/Object
Method	java/lang/Object."<init>":()V
Asciz	scala/Function1$class;
class	scala/Function1$class
Asciz	$init$;
Asciz	(Lscala/Function1;)V;
NameAndType	$init$:(Lscala/Function1;)V
Method	scala/Function1$class.$init$:(Lscala/Function1;)V
Asciz	scala/PartialFunction$class;
class	scala/PartialFunction$class
Asciz	(Lscala/PartialFunction;)V;
NameAndType	$init$:(Lscala/PartialFunction;)V
Method	scala/PartialFunction$class.$init$:(Lscala/PartialFunction;)V
Asciz	this;
Asciz	Lscala/actors/ReactChannel$$anonfun$react$1;;
Asciz	LocalVariableTable;
Asciz	(Lscala/actors/ReactChannel<TMsg;>;)V;
Asciz	Signature;
Asciz	gd3$1;
Asciz	(Ljava/lang/Object;)Z;
Asciz	scala/PartialFunction;
class	scala/PartialFunction
Asciz	isDefinedAt;
NameAndType	isDefinedAt:(Ljava/lang/Object;)Z
InterfaceMethod	scala/PartialFunction.isDefinedAt:(Ljava/lang/Object;)Z
Asciz	gd2$1;
Asciz	apply;
Asciz	(Ljava/lang/Object;)Ljava/lang/Object;;
Asciz	(Ljava/lang/Object;)V;
NameAndType	apply:(Ljava/lang/Object;)V
Method	scala/actors/ReactChannel$$anonfun$react$1.apply:(Ljava/lang/Object;)V
Asciz	scala/runtime/BoxedUnit;
class	scala/runtime/BoxedUnit
Asciz	UNIT;
Asciz	Lscala/runtime/BoxedUnit;;
NameAndType	UNIT:Lscala/runtime/BoxedUnit;
Field	scala/runtime/BoxedUnit.UNIT:Lscala/runtime/BoxedUnit;
Asciz	v1;
Asciz	Ljava/lang/Object;;
Asciz	andThen;
Asciz	(Lscala/Function1;)Lscala/Function1;;
Asciz	(Lscala/Function1;)Lscala/PartialFunction;;
NameAndType	andThen:(Lscala/Function1;)Lscala/PartialFunction;
InterfaceMethod	scala/PartialFunction.andThen:(Lscala/Function1;)Lscala/PartialFunction;
Asciz	g;
Asciz	Lscala/Function1;;
Asciz	scala/actors/ReactChannel$SendToReactor;
class	scala/actors/ReactChannel$SendToReactor
Asciz	scala$actors$ReactChannel$SendToReactor$$$outer;
Asciz	()Lscala/actors/ReactChannel;;
NameAndType	scala$actors$ReactChannel$SendToReactor$$$outer:()Lscala/actors/ReactChannel;
Method	scala/actors/ReactChannel$SendToReactor.scala$actors$ReactChannel$SendToReactor$$$outer:()Lscala/actors/ReactChannel;
Asciz	channel;
NameAndType	channel:()Lscala/actors/ReactChannel;
Method	scala/actors/ReactChannel$SendToReactor.channel:()Lscala/actors/ReactChannel;
Asciz	equals;
NameAndType	equals:(Ljava/lang/Object;)Z
Method	java/lang/Object.equals:(Ljava/lang/Object;)Z
Asciz	msg;
Asciz	()Ljava/lang/Object;;
NameAndType	msg:()Ljava/lang/Object;
Method	scala/actors/ReactChannel$SendToReactor.msg:()Ljava/lang/Object;
NameAndType	gd3$1:(Ljava/lang/Object;)Z
Method	scala/actors/ReactChannel$$anonfun$react$1.gd3$1:(Ljava/lang/Object;)Z
Asciz	scala/MatchError;
class	scala/MatchError
Asciz	toString;
Asciz	()Ljava/lang/String;;
NameAndType	toString:()Ljava/lang/String;
Method	java/lang/Object.toString:()Ljava/lang/String;
Asciz	(Ljava/lang/String;)V;
NameAndType	"<init>":(Ljava/lang/String;)V
Method	scala/MatchError."<init>":(Ljava/lang/String;)V
Asciz	temp12;
Asciz	Lscala/actors/ReactChannel$SendToReactor;;
NameAndType	gd2$1:(Ljava/lang/Object;)Z
Method	scala/actors/ReactChannel$$anonfun$react$1.gd2$1:(Ljava/lang/Object;)Z
Asciz	scala/Function1;
class	scala/Function1
NameAndType	apply:(Ljava/lang/Object;)Ljava/lang/Object;
InterfaceMethod	scala/Function1.apply:(Ljava/lang/Object;)Ljava/lang/Object;
Asciz	temp7;
Asciz	temp9;
Asciz	compose;
Asciz	(Lscala/Function1;Lscala/Function1;)Lscala/Function1;;
NameAndType	compose:(Lscala/Function1;Lscala/Function1;)Lscala/Function1;
Method	scala/Function1$class.compose:(Lscala/Function1;Lscala/Function1;)Lscala/Function1;
Asciz	(Lscala/Function1;)Ljava/lang/String;;
NameAndType	toString:(Lscala/Function1;)Ljava/lang/String;
Method	scala/Function1$class.toString:(Lscala/Function1;)Ljava/lang/String;
Asciz	(Lscala/PartialFunction;Lscala/Function1;)Lscala/PartialFunction;;
NameAndType	andThen:(Lscala/PartialFunction;Lscala/Function1;)Lscala/PartialFunction;
Method	scala/PartialFunction$class.andThen:(Lscala/PartialFunction;Lscala/Function1;)Lscala/PartialFunction;
Asciz	k;
Asciz	orElse;
Asciz	(Lscala/PartialFunction;)Lscala/PartialFunction;;
Asciz	(Lscala/PartialFunction;Lscala/PartialFunction;)Lscala/PartialFunction;;
NameAndType	orElse:(Lscala/PartialFunction;Lscala/PartialFunction;)Lscala/PartialFunction;
Method	scala/PartialFunction$class.orElse:(Lscala/PartialFunction;Lscala/PartialFunction;)Lscala/PartialFunction;
Asciz	that;
Asciz	Scala;
Asciz	InnerClasses;
Asciz	scala/actors/ReactChannel;
class	scala/actors/ReactChannel
Asciz	SendToReactor;
Asciz	$anonfun$react$1;
Asciz	java/io/Serializable;
class	java/io/Serializable

{
public static final long serialVersionUID;
  Signature: J

private final scala.actors.ReactChannel C$1;
  Signature: Lscala/actors/ReactChannel;

private final scala.PartialFunction f$1;
  Signature: Lscala/PartialFunction;

private final scala.actors.ReactChannel $outer;
  Signature: Lscala/actors/ReactChannel;

public static {};
  Signature: ()V
  Code:
   Stack=2, Locals=0, Args_size=0
	lconst_0
	putstatic	Field serialVersionUID:J
	return
  Labels:

public scala.actors.ReactChannel$$anonfun$react$1(scala.actors.ReactChannel, scala.PartialFunction, scala.actors.ReactChannel);
  Signature: (Lscala/actors/ReactChannel;Lscala/PartialFunction;Lscala/actors/ReactChannel;)V
  Code:
   Stack=2, Locals=4, Args_size=4
	aload_1
	ifnonnull	l1 // aload_0
	new	class java/lang/NullPointerException
	dup
	invokespecial	Method java/lang/NullPointerException."<init>":()V
	athrow
l1	aload_0
	aload_1
	putfield	Field $outer:Lscala/actors/ReactChannel;
	aload_0
	aload_2
	putfield	Field f$1:Lscala/PartialFunction;
	aload_0
	aload_3
	putfield	Field C$1:Lscala/actors/ReactChannel;
	aload_0
	invokespecial	Method java/lang/Object."<init>":()V
	aload_0
	invokestatic	Method scala/Function1$class.$init$:(Lscala/Function1;)V
	aload_0
	invokestatic	Method scala/PartialFunction$class.$init$:(Lscala/PartialFunction;)V
	return
  Labels:
   	l1 = 12 // aload_0
  LocalVariableTable: 
   Start  Length  Slot  Name   Signature
   0      40      0    this       Lscala/actors/ReactChannel$$anonfun$react$1;
   0      40      1    $outer       Lscala/actors/ReactChannel;

  Signature: length = 0x2
   00 2F 

private final boolean gd3$1(java.lang.Object);
  Signature: (Ljava/lang/Object;)Z
  Code:
   Stack=2, Locals=2, Args_size=2
	aload_0
	getfield	Field f$1:Lscala/PartialFunction;
	aload_1
	invokeinterface	InterfaceMethod scala/PartialFunction.isDefinedAt:(Ljava/lang/Object;)Z
	ireturn
  Labels:

private final boolean gd2$1(java.lang.Object);
  Signature: (Ljava/lang/Object;)Z
  Code:
   Stack=2, Locals=2, Args_size=2
	aload_0
	getfield	Field f$1:Lscala/PartialFunction;
	aload_1
	invokeinterface	InterfaceMethod scala/PartialFunction.isDefinedAt:(Ljava/lang/Object;)Z
	ireturn
  Labels:

public final java.lang.Object apply(java.lang.Object);
  Signature: (Ljava/lang/Object;)Ljava/lang/Object;
  Code:
   Stack=2, Locals=2, Args_size=2
	aload_0
	aload_1
	invokevirtual	Method apply:(Ljava/lang/Object;)V
	getstatic	Field scala/runtime/BoxedUnit.UNIT:Lscala/runtime/BoxedUnit;
	areturn
  Labels:
  LocalVariableTable: 
   Start  Length  Slot  Name   Signature
   0      9      0    this       Lscala/actors/ReactChannel$$anonfun$react$1;
   0      9      1    v1       Ljava/lang/Object;


public scala.Function1 andThen(scala.Function1);
  Signature: (Lscala/Function1;)Lscala/Function1;
  Code:
   Stack=2, Locals=2, Args_size=2
	aload_0
	aload_1
	invokeinterface	InterfaceMethod scala/PartialFunction.andThen:(Lscala/Function1;)Lscala/PartialFunction;
	areturn
  Labels:
  LocalVariableTable: 
   Start  Length  Slot  Name   Signature
   0      8      0    this       Lscala/actors/ReactChannel$$anonfun$react$1;
   0      8      1    g       Lscala/Function1;


public final boolean isDefinedAt(java.lang.Object);
  Signature: (Ljava/lang/Object;)Z
  Code:
   Stack=3, Locals=4, Args_size=2
	aload_1
	instanceof	class scala/actors/ReactChannel$SendToReactor
	ifeq	l1 // iconst_1
	aload_1
	checkcast	class scala/actors/ReactChannel$SendToReactor
	invokevirtual	Method scala/actors/ReactChannel$SendToReactor.scala$actors$ReactChannel$SendToReactor$$$outer:()Lscala/actors/ReactChannel;
	aload_0
	getfield	Field $outer:Lscala/actors/ReactChannel;
	if_acmpne	l1 // iconst_1
	aload_1
	checkcast	class scala/actors/ReactChannel$SendToReactor
	astore_3
	aload_0
	getfield	Field C$1:Lscala/actors/ReactChannel;
	aload_3
	invokevirtual	Method scala/actors/ReactChannel$SendToReactor.channel:()Lscala/actors/ReactChannel;
	astore_2
	dup
	ifnonnull	l2 // aload_2
	pop
	aload_2
	ifnull	l3 // aload_0
	goto	l4 // iconst_1
l2	aload_2
	invokevirtual	Method java/lang/Object.equals:(Ljava/lang/Object;)Z
	ifeq	l4 // iconst_1
l3	aload_0
	aload_3
	invokevirtual	Method scala/actors/ReactChannel$SendToReactor.msg:()Ljava/lang/Object;
	invokespecial	Method gd3$1:(Ljava/lang/Object;)Z
	ifeq	l5 // iconst_1
	iconst_1
	goto	l6 // ireturn
l5	iconst_1
	ifeq	l7 // new
	iconst_0
	goto	l6 // ireturn
l7	new	class scala/MatchError
	dup
	aload_1
	invokevirtual	Method java/lang/Object.toString:()Ljava/lang/String;
	invokespecial	Method scala/MatchError."<init>":(Ljava/lang/String;)V
	athrow
l4	iconst_1
	ifeq	l8 // new
	iconst_0
	goto	l6 // ireturn
l8	new	class scala/MatchError
	dup
	aload_1
	invokevirtual	Method java/lang/Object.toString:()Ljava/lang/String;
	invokespecial	Method scala/MatchError."<init>":(Ljava/lang/String;)V
	athrow
l1	iconst_1
	ifeq	l9 // new
	iconst_0
l6	ireturn
l9	new	class scala/MatchError
	dup
	aload_1
	invokevirtual	Method java/lang/Object.toString:()Ljava/lang/String;
	invokespecial	Method scala/MatchError."<init>":(Ljava/lang/String;)V
	athrow
  Labels:
   	l2 = 47 // aload_2
   	l3 = 54 // aload_0
   	l5 = 69 // iconst_1
   	l7 = 77 // new
   	l4 = 89 // iconst_1
   	l8 = 97 // new
   	l1 = 109 // iconst_1
   	l6 = 114 // ireturn
   	l9 = 115 // new
  LocalVariableTable: 
   Start  Length  Slot  Name   Signature
   0      127      0    this       Lscala/actors/ReactChannel$$anonfun$react$1;
   26      83      3    temp12       Lscala/actors/ReactChannel$SendToReactor;


public final void apply(java.lang.Object);
  Signature: (Ljava/lang/Object;)V
  Code:
   Stack=3, Locals=5, Args_size=2
	aload_1
	instanceof	class scala/actors/ReactChannel$SendToReactor
	ifeq	l1 // new
	aload_1
	checkcast	class scala/actors/ReactChannel$SendToReactor
	invokevirtual	Method scala/actors/ReactChannel$SendToReactor.scala$actors$ReactChannel$SendToReactor$$$outer:()Lscala/actors/ReactChannel;
	aload_0
	getfield	Field $outer:Lscala/actors/ReactChannel;
	if_acmpne	l1 // new
	aload_1
	checkcast	class scala/actors/ReactChannel$SendToReactor
	astore_2
	aload_2
	invokevirtual	Method scala/actors/ReactChannel$SendToReactor.msg:()Ljava/lang/Object;
	astore	4
	aload_0
	getfield	Field C$1:Lscala/actors/ReactChannel;
	aload_2
	invokevirtual	Method scala/actors/ReactChannel$SendToReactor.channel:()Lscala/actors/ReactChannel;
	astore_3
	dup
	ifnonnull	l2 // aload_3
	pop
	aload_3
	ifnull	l3 // aload_0
	goto	l4 // new
l2	aload_3
	invokevirtual	Method java/lang/Object.equals:(Ljava/lang/Object;)Z
	ifeq	l4 // new
l3	aload_0
	aload	4
	invokespecial	Method gd2$1:(Ljava/lang/Object;)Z
	ifeq	l5 // new
	aload_0
	getfield	Field f$1:Lscala/PartialFunction;
	aload	4
	invokeinterface	InterfaceMethod scala/Function1.apply:(Ljava/lang/Object;)Ljava/lang/Object;
	pop
	return
l5	new	class scala/MatchError
	dup
	aload_1
	invokevirtual	Method java/lang/Object.toString:()Ljava/lang/String;
	invokespecial	Method scala/MatchError."<init>":(Ljava/lang/String;)V
	athrow
l4	new	class scala/MatchError
	dup
	aload_1
	invokevirtual	Method java/lang/Object.toString:()Ljava/lang/String;
	invokespecial	Method scala/MatchError."<init>":(Ljava/lang/String;)V
	athrow
l1	new	class scala/MatchError
	dup
	aload_1
	invokevirtual	Method java/lang/Object.toString:()Ljava/lang/String;
	invokespecial	Method scala/MatchError."<init>":(Ljava/lang/String;)V
	athrow
  Labels:
   	l2 = 53 // aload_3
   	l3 = 60 // aload_0
   	l5 = 82 // new
   	l4 = 94 // new
   	l1 = 106 // new
  LocalVariableTable: 
   Start  Length  Slot  Name   Signature
   0      118      0    this       Lscala/actors/ReactChannel$$anonfun$react$1;
   26      80      2    temp7       Lscala/actors/ReactChannel$SendToReactor;
   32      74      4    temp9       Ljava/lang/Object;


public scala.Function1 compose(scala.Function1);
  Signature: (Lscala/Function1;)Lscala/Function1;
  Code:
   Stack=2, Locals=2, Args_size=2
	aload_0
	aload_1
	invokestatic	Method scala/Function1$class.compose:(Lscala/Function1;Lscala/Function1;)Lscala/Function1;
	areturn
  Labels:
  LocalVariableTable: 
   Start  Length  Slot  Name   Signature
   0      6      0    this       Lscala/actors/ReactChannel$$anonfun$react$1;
   0      6      1    g       Lscala/Function1;


public java.lang.String toString();
  Signature: ()Ljava/lang/String;
  Code:
   Stack=1, Locals=1, Args_size=1
	aload_0
	invokestatic	Method scala/Function1$class.toString:(Lscala/Function1;)Ljava/lang/String;
	areturn
  Labels:

public scala.PartialFunction andThen(scala.Function1);
  Signature: (Lscala/Function1;)Lscala/PartialFunction;
  Code:
   Stack=2, Locals=2, Args_size=2
	aload_0
	aload_1
	invokestatic	Method scala/PartialFunction$class.andThen:(Lscala/PartialFunction;Lscala/Function1;)Lscala/PartialFunction;
	areturn
  Labels:
  LocalVariableTable: 
   Start  Length  Slot  Name   Signature
   0      6      0    this       Lscala/actors/ReactChannel$$anonfun$react$1;
   0      6      1    k       Lscala/Function1;


public scala.PartialFunction orElse(scala.PartialFunction);
  Signature: (Lscala/PartialFunction;)Lscala/PartialFunction;
  Code:
   Stack=2, Locals=2, Args_size=2
	aload_0
	aload_1
	invokestatic	Method scala/PartialFunction$class.orElse:(Lscala/PartialFunction;Lscala/PartialFunction;)Lscala/PartialFunction;
	areturn
  Labels:
  LocalVariableTable: 
   Start  Length  Slot  Name   Signature
   0      6      0    this       Lscala/actors/ReactChannel$$anonfun$react$1;
   0      6      1    that       Lscala/PartialFunction;


}

