Compiled from "ReactChannel.scala"
public final class scala.actors.ReactChannel$$anonfun$react$1 extends java.lang.Object implements scala.PartialFunction,java.io.Serializable
  SourceFile: "ReactChannel.scala"
  Scala: length = 0x
   
  InnerClass: 
   public #140= #78 of #139; //SendToReactor=class scala/actors/ReactChannel$SendToReactor of class scala/actors/ReactChannel
   public final #141= #9 of #139; //$anonfun$react$1=class scala/actors/ReactChannel$$anonfun$react$1 of class scala/actors/ReactChannel
  minor version: 0
  major version: 49
  Constant pool:
const #1 = Asciz	SourceFile;
const #2 = Asciz	ReactChannel.scala;
const #3 = Asciz	<clinit>;
const #4 = Asciz	()V;
const #5 = Asciz	Code;
const #6 = Asciz	serialVersionUID;
const #7 = Asciz	J;
const #8 = Asciz	scala/actors/ReactChannel$$anonfun$react$1;
const #9 = class	#8;	//  scala/actors/ReactChannel$$anonfun$react$1
const #10 = NameAndType	#6:#7;//  serialVersionUID:J
const #11 = Field	#9.#10;	//  scala/actors/ReactChannel$$anonfun$react$1.serialVersionUID:J
const #12 = Asciz	C$1;
const #13 = Asciz	Lscala/actors/ReactChannel;;
const #14 = Asciz	f$1;
const #15 = Asciz	Lscala/PartialFunction;;
const #16 = Asciz	$outer;
const #17 = Asciz	<init>;
const #18 = Asciz	(Lscala/actors/ReactChannel;Lscala/PartialFunction;Lscala/actors/ReactChannel;)V;
const #19 = Asciz	LineNumberTable;
const #20 = Asciz	java/lang/NullPointerException;
const #21 = class	#20;	//  java/lang/NullPointerException
const #22 = NameAndType	#17:#4;//  "<init>":()V
const #23 = Method	#21.#22;	//  java/lang/NullPointerException."<init>":()V
const #24 = NameAndType	#16:#13;//  $outer:Lscala/actors/ReactChannel;
const #25 = Field	#9.#24;	//  scala/actors/ReactChannel$$anonfun$react$1.$outer:Lscala/actors/ReactChannel;
const #26 = NameAndType	#14:#15;//  f$1:Lscala/PartialFunction;
const #27 = Field	#9.#26;	//  scala/actors/ReactChannel$$anonfun$react$1.f$1:Lscala/PartialFunction;
const #28 = NameAndType	#12:#13;//  C$1:Lscala/actors/ReactChannel;
const #29 = Field	#9.#28;	//  scala/actors/ReactChannel$$anonfun$react$1.C$1:Lscala/actors/ReactChannel;
const #30 = Asciz	java/lang/Object;
const #31 = class	#30;	//  java/lang/Object
const #32 = Method	#31.#22;	//  java/lang/Object."<init>":()V
const #33 = Asciz	scala/Function1$class;
const #34 = class	#33;	//  scala/Function1$class
const #35 = Asciz	$init$;
const #36 = Asciz	(Lscala/Function1;)V;
const #37 = NameAndType	#35:#36;//  $init$:(Lscala/Function1;)V
const #38 = Method	#34.#37;	//  scala/Function1$class.$init$:(Lscala/Function1;)V
const #39 = Asciz	scala/PartialFunction$class;
const #40 = class	#39;	//  scala/PartialFunction$class
const #41 = Asciz	(Lscala/PartialFunction;)V;
const #42 = NameAndType	#35:#41;//  $init$:(Lscala/PartialFunction;)V
const #43 = Method	#40.#42;	//  scala/PartialFunction$class.$init$:(Lscala/PartialFunction;)V
const #44 = Asciz	this;
const #45 = Asciz	Lscala/actors/ReactChannel$$anonfun$react$1;;
const #46 = Asciz	LocalVariableTable;
const #47 = Asciz	(Lscala/actors/ReactChannel<TMsg;>;)V;
const #48 = Asciz	Signature;
const #49 = Asciz	gd3$1;
const #50 = Asciz	(Ljava/lang/Object;)Z;
const #51 = Asciz	scala/PartialFunction;
const #52 = class	#51;	//  scala/PartialFunction
const #53 = Asciz	isDefinedAt;
const #54 = NameAndType	#53:#50;//  isDefinedAt:(Ljava/lang/Object;)Z
const #55 = InterfaceMethod	#52.#54;	//  scala/PartialFunction.isDefinedAt:(Ljava/lang/Object;)Z
const #56 = Asciz	gd2$1;
const #57 = Asciz	apply;
const #58 = Asciz	(Ljava/lang/Object;)Ljava/lang/Object;;
const #59 = Asciz	(Ljava/lang/Object;)V;
const #60 = NameAndType	#57:#59;//  apply:(Ljava/lang/Object;)V
const #61 = Method	#9.#60;	//  scala/actors/ReactChannel$$anonfun$react$1.apply:(Ljava/lang/Object;)V
const #62 = Asciz	scala/runtime/BoxedUnit;
const #63 = class	#62;	//  scala/runtime/BoxedUnit
const #64 = Asciz	UNIT;
const #65 = Asciz	Lscala/runtime/BoxedUnit;;
const #66 = NameAndType	#64:#65;//  UNIT:Lscala/runtime/BoxedUnit;
const #67 = Field	#63.#66;	//  scala/runtime/BoxedUnit.UNIT:Lscala/runtime/BoxedUnit;
const #68 = Asciz	v1;
const #69 = Asciz	Ljava/lang/Object;;
const #70 = Asciz	andThen;
const #71 = Asciz	(Lscala/Function1;)Lscala/Function1;;
const #72 = Asciz	(Lscala/Function1;)Lscala/PartialFunction;;
const #73 = NameAndType	#70:#72;//  andThen:(Lscala/Function1;)Lscala/PartialFunction;
const #74 = InterfaceMethod	#52.#73;	//  scala/PartialFunction.andThen:(Lscala/Function1;)Lscala/PartialFunction;
const #75 = Asciz	g;
const #76 = Asciz	Lscala/Function1;;
const #77 = Asciz	scala/actors/ReactChannel$SendToReactor;
const #78 = class	#77;	//  scala/actors/ReactChannel$SendToReactor
const #79 = Asciz	scala$actors$ReactChannel$SendToReactor$$$outer;
const #80 = Asciz	()Lscala/actors/ReactChannel;;
const #81 = NameAndType	#79:#80;//  scala$actors$ReactChannel$SendToReactor$$$outer:()Lscala/actors/ReactChannel;
const #82 = Method	#78.#81;	//  scala/actors/ReactChannel$SendToReactor.scala$actors$ReactChannel$SendToReactor$$$outer:()Lscala/actors/ReactChannel;
const #83 = Asciz	channel;
const #84 = NameAndType	#83:#80;//  channel:()Lscala/actors/ReactChannel;
const #85 = Method	#78.#84;	//  scala/actors/ReactChannel$SendToReactor.channel:()Lscala/actors/ReactChannel;
const #86 = Asciz	equals;
const #87 = NameAndType	#86:#50;//  equals:(Ljava/lang/Object;)Z
const #88 = Method	#31.#87;	//  java/lang/Object.equals:(Ljava/lang/Object;)Z
const #89 = Asciz	msg;
const #90 = Asciz	()Ljava/lang/Object;;
const #91 = NameAndType	#89:#90;//  msg:()Ljava/lang/Object;
const #92 = Method	#78.#91;	//  scala/actors/ReactChannel$SendToReactor.msg:()Ljava/lang/Object;
const #93 = NameAndType	#49:#50;//  gd3$1:(Ljava/lang/Object;)Z
const #94 = Method	#9.#93;	//  scala/actors/ReactChannel$$anonfun$react$1.gd3$1:(Ljava/lang/Object;)Z
const #95 = Asciz	scala/MatchError;
const #96 = class	#95;	//  scala/MatchError
const #97 = Asciz	toString;
const #98 = Asciz	()Ljava/lang/String;;
const #99 = NameAndType	#97:#98;//  toString:()Ljava/lang/String;
const #100 = Method	#31.#99;	//  java/lang/Object.toString:()Ljava/lang/String;
const #101 = Asciz	(Ljava/lang/String;)V;
const #102 = NameAndType	#17:#101;//  "<init>":(Ljava/lang/String;)V
const #103 = Method	#96.#102;	//  scala/MatchError."<init>":(Ljava/lang/String;)V
const #104 = Asciz	temp12;
const #105 = Asciz	Lscala/actors/ReactChannel$SendToReactor;;
const #106 = NameAndType	#56:#50;//  gd2$1:(Ljava/lang/Object;)Z
const #107 = Method	#9.#106;	//  scala/actors/ReactChannel$$anonfun$react$1.gd2$1:(Ljava/lang/Object;)Z
const #108 = Asciz	scala/Function1;
const #109 = class	#108;	//  scala/Function1
const #110 = NameAndType	#57:#58;//  apply:(Ljava/lang/Object;)Ljava/lang/Object;
const #111 = InterfaceMethod	#109.#110;	//  scala/Function1.apply:(Ljava/lang/Object;)Ljava/lang/Object;
const #112 = Asciz	temp7;
const #113 = Asciz	temp9;
const #114 = Asciz	compose;
const #115 = Asciz	(Lscala/Function1;Lscala/Function1;)Lscala/Function1;;
const #116 = NameAndType	#114:#115;//  compose:(Lscala/Function1;Lscala/Function1;)Lscala/Function1;
const #117 = Method	#34.#116;	//  scala/Function1$class.compose:(Lscala/Function1;Lscala/Function1;)Lscala/Function1;
const #118 = Asciz	(Lscala/Function1;)Ljava/lang/String;;
const #119 = NameAndType	#97:#118;//  toString:(Lscala/Function1;)Ljava/lang/String;
const #120 = Method	#34.#119;	//  scala/Function1$class.toString:(Lscala/Function1;)Ljava/lang/String;
const #121 = Asciz	lift;
const #122 = Asciz	()Lscala/Function1;;
const #123 = Asciz	(Lscala/PartialFunction;)Lscala/Function1;;
const #124 = NameAndType	#121:#123;//  lift:(Lscala/PartialFunction;)Lscala/Function1;
const #125 = Method	#40.#124;	//  scala/PartialFunction$class.lift:(Lscala/PartialFunction;)Lscala/Function1;
const #126 = Asciz	(Lscala/PartialFunction;Lscala/Function1;)Lscala/PartialFunction;;
const #127 = NameAndType	#70:#126;//  andThen:(Lscala/PartialFunction;Lscala/Function1;)Lscala/PartialFunction;
const #128 = Method	#40.#127;	//  scala/PartialFunction$class.andThen:(Lscala/PartialFunction;Lscala/Function1;)Lscala/PartialFunction;
const #129 = Asciz	k;
const #130 = Asciz	orElse;
const #131 = Asciz	(Lscala/PartialFunction;)Lscala/PartialFunction;;
const #132 = Asciz	(Lscala/PartialFunction;Lscala/PartialFunction;)Lscala/PartialFunction;;
const #133 = NameAndType	#130:#132;//  orElse:(Lscala/PartialFunction;Lscala/PartialFunction;)Lscala/PartialFunction;
const #134 = Method	#40.#133;	//  scala/PartialFunction$class.orElse:(Lscala/PartialFunction;Lscala/PartialFunction;)Lscala/PartialFunction;
const #135 = Asciz	that;
const #136 = Asciz	Scala;
const #137 = Asciz	InnerClasses;
const #138 = Asciz	scala/actors/ReactChannel;
const #139 = class	#138;	//  scala/actors/ReactChannel
const #140 = Asciz	SendToReactor;
const #141 = Asciz	$anonfun$react$1;
const #142 = Asciz	java/io/Serializable;
const #143 = class	#142;	//  java/io/Serializable

{
public static final long serialVersionUID;

public static {};
  Code:
   Stack=2, Locals=0, Args_size=0
   0:	lconst_0
   1:	putstatic	#11; //Field serialVersionUID:J
   4:	return

public scala.actors.ReactChannel$$anonfun$react$1(scala.actors.ReactChannel, scala.PartialFunction, scala.actors.ReactChannel);
  Code:
   Stack=2, Locals=4, Args_size=4
   0:	aload_1
   1:	ifnonnull	12
   4:	new	#21; //class java/lang/NullPointerException
   7:	dup
   8:	invokespecial	#23; //Method java/lang/NullPointerException."<init>":()V
   11:	athrow
   12:	aload_0
   13:	aload_1
   14:	putfield	#25; //Field $outer:Lscala/actors/ReactChannel;
   17:	aload_0
   18:	aload_2
   19:	putfield	#27; //Field f$1:Lscala/PartialFunction;
   22:	aload_0
   23:	aload_3
   24:	putfield	#29; //Field C$1:Lscala/actors/ReactChannel;
   27:	aload_0
   28:	invokespecial	#32; //Method java/lang/Object."<init>":()V
   31:	aload_0
   32:	invokestatic	#38; //Method scala/Function1$class.$init$:(Lscala/Function1;)V
   35:	aload_0
   36:	invokestatic	#43; //Method scala/PartialFunction$class.$init$:(Lscala/PartialFunction;)V
   39:	return
  LineNumberTable: 
   line 60: 0

  LocalVariableTable: 
   Start  Length  Slot  Name   Signature
   0      40      0    this       Lscala/actors/ReactChannel$$anonfun$react$1;
   0      40      1    $outer       Lscala/actors/ReactChannel;

  Signature: length = 0x2
   00 2F 

public final java.lang.Object apply(java.lang.Object);
  Code:
   Stack=2, Locals=2, Args_size=2
   0:	aload_0
   1:	aload_1
   2:	invokevirtual	#61; //Method apply:(Ljava/lang/Object;)V
   5:	getstatic	#67; //Field scala/runtime/BoxedUnit.UNIT:Lscala/runtime/BoxedUnit;
   8:	areturn
  LineNumberTable: 
   line 60: 0

  LocalVariableTable: 
   Start  Length  Slot  Name   Signature
   0      9      0    this       Lscala/actors/ReactChannel$$anonfun$react$1;
   0      9      1    v1       Ljava/lang/Object;


public scala.Function1 andThen(scala.Function1);
  Code:
   Stack=2, Locals=2, Args_size=2
   0:	aload_0
   1:	aload_1
   2:	invokeinterface	#74,  2; //InterfaceMethod scala/PartialFunction.andThen:(Lscala/Function1;)Lscala/PartialFunction;
   7:	areturn
  LineNumberTable: 
   line 60: 0

  LocalVariableTable: 
   Start  Length  Slot  Name   Signature
   0      8      0    this       Lscala/actors/ReactChannel$$anonfun$react$1;
   0      8      1    g       Lscala/Function1;


public final boolean isDefinedAt(java.lang.Object);
  Code:
   Stack=3, Locals=4, Args_size=2
   0:	aload_1
   1:	instanceof	#78; //class scala/actors/ReactChannel$SendToReactor
   4:	ifeq	109
   7:	aload_1
   8:	checkcast	#78; //class scala/actors/ReactChannel$SendToReactor
   11:	invokevirtual	#82; //Method scala/actors/ReactChannel$SendToReactor.scala$actors$ReactChannel$SendToReactor$$$outer:()Lscala/actors/ReactChannel;
   14:	aload_0
   15:	getfield	#25; //Field $outer:Lscala/actors/ReactChannel;
   18:	if_acmpne	109
   21:	aload_1
   22:	checkcast	#78; //class scala/actors/ReactChannel$SendToReactor
   25:	astore_3
   26:	aload_0
   27:	getfield	#29; //Field C$1:Lscala/actors/ReactChannel;
   30:	aload_3
   31:	invokevirtual	#85; //Method scala/actors/ReactChannel$SendToReactor.channel:()Lscala/actors/ReactChannel;
   34:	astore_2
   35:	dup
   36:	ifnonnull	47
   39:	pop
   40:	aload_2
   41:	ifnull	54
   44:	goto	89
   47:	aload_2
   48:	invokevirtual	#88; //Method java/lang/Object.equals:(Ljava/lang/Object;)Z
   51:	ifeq	89
   54:	aload_0
   55:	aload_3
   56:	invokevirtual	#92; //Method scala/actors/ReactChannel$SendToReactor.msg:()Ljava/lang/Object;
   59:	invokespecial	#94; //Method gd3$1:(Ljava/lang/Object;)Z
   62:	ifeq	69
   65:	iconst_1
   66:	goto	114
   69:	iconst_1
   70:	ifeq	77
   73:	iconst_0
   74:	goto	114
   77:	new	#96; //class scala/MatchError
   80:	dup
   81:	aload_1
   82:	invokevirtual	#100; //Method java/lang/Object.toString:()Ljava/lang/String;
   85:	invokespecial	#103; //Method scala/MatchError."<init>":(Ljava/lang/String;)V
   88:	athrow
   89:	iconst_1
   90:	ifeq	97
   93:	iconst_0
   94:	goto	114
   97:	new	#96; //class scala/MatchError
   100:	dup
   101:	aload_1
   102:	invokevirtual	#100; //Method java/lang/Object.toString:()Ljava/lang/String;
   105:	invokespecial	#103; //Method scala/MatchError."<init>":(Ljava/lang/String;)V
   108:	athrow
   109:	iconst_1
   110:	ifeq	115
   113:	iconst_0
   114:	ireturn
   115:	new	#96; //class scala/MatchError
   118:	dup
   119:	aload_1
   120:	invokevirtual	#100; //Method java/lang/Object.toString:()Ljava/lang/String;
   123:	invokespecial	#103; //Method scala/MatchError."<init>":(Ljava/lang/String;)V
   126:	athrow
  LineNumberTable: 
   line 60: 0
   line 644: 69
   line 60: 73
   line 644: 89
   line 60: 93
   line 644: 109
   line 60: 113

  LocalVariableTable: 
   Start  Length  Slot  Name   Signature
   0      127      0    this       Lscala/actors/ReactChannel$$anonfun$react$1;
   26      83      3    temp12       Lscala/actors/ReactChannel$SendToReactor;


public final void apply(java.lang.Object);
  Code:
   Stack=3, Locals=5, Args_size=2
   0:	aload_1
   1:	instanceof	#78; //class scala/actors/ReactChannel$SendToReactor
   4:	ifeq	106
   7:	aload_1
   8:	checkcast	#78; //class scala/actors/ReactChannel$SendToReactor
   11:	invokevirtual	#82; //Method scala/actors/ReactChannel$SendToReactor.scala$actors$ReactChannel$SendToReactor$$$outer:()Lscala/actors/ReactChannel;
   14:	aload_0
   15:	getfield	#25; //Field $outer:Lscala/actors/ReactChannel;
   18:	if_acmpne	106
   21:	aload_1
   22:	checkcast	#78; //class scala/actors/ReactChannel$SendToReactor
   25:	astore_2
   26:	aload_2
   27:	invokevirtual	#92; //Method scala/actors/ReactChannel$SendToReactor.msg:()Ljava/lang/Object;
   30:	astore	4
   32:	aload_0
   33:	getfield	#29; //Field C$1:Lscala/actors/ReactChannel;
   36:	aload_2
   37:	invokevirtual	#85; //Method scala/actors/ReactChannel$SendToReactor.channel:()Lscala/actors/ReactChannel;
   40:	astore_3
   41:	dup
   42:	ifnonnull	53
   45:	pop
   46:	aload_3
   47:	ifnull	60
   50:	goto	94
   53:	aload_3
   54:	invokevirtual	#88; //Method java/lang/Object.equals:(Ljava/lang/Object;)Z
   57:	ifeq	94
   60:	aload_0
   61:	aload	4
   63:	invokespecial	#107; //Method gd2$1:(Ljava/lang/Object;)Z
   66:	ifeq	82
   69:	aload_0
   70:	getfield	#27; //Field f$1:Lscala/PartialFunction;
   73:	aload	4
   75:	invokeinterface	#111,  2; //InterfaceMethod scala/Function1.apply:(Ljava/lang/Object;)Ljava/lang/Object;
   80:	pop
   81:	return
   82:	new	#96; //class scala/MatchError
   85:	dup
   86:	aload_1
   87:	invokevirtual	#100; //Method java/lang/Object.toString:()Ljava/lang/String;
   90:	invokespecial	#103; //Method scala/MatchError."<init>":(Ljava/lang/String;)V
   93:	athrow
   94:	new	#96; //class scala/MatchError
   97:	dup
   98:	aload_1
   99:	invokevirtual	#100; //Method java/lang/Object.toString:()Ljava/lang/String;
   102:	invokespecial	#103; //Method scala/MatchError."<init>":(Ljava/lang/String;)V
   105:	athrow
   106:	new	#96; //class scala/MatchError
   109:	dup
   110:	aload_1
   111:	invokevirtual	#100; //Method java/lang/Object.toString:()Ljava/lang/String;
   114:	invokespecial	#103; //Method scala/MatchError."<init>":(Ljava/lang/String;)V
   117:	athrow
  LineNumberTable: 
   line 60: 0
   line 62: 69
   line 60: 81

  LocalVariableTable: 
   Start  Length  Slot  Name   Signature
   0      118      0    this       Lscala/actors/ReactChannel$$anonfun$react$1;
   26      80      2    temp7       Lscala/actors/ReactChannel$SendToReactor;
   32      74      4    temp9       Ljava/lang/Object;


public scala.Function1 compose(scala.Function1);
  Code:
   Stack=2, Locals=2, Args_size=2
   0:	aload_0
   1:	aload_1
   2:	invokestatic	#117; //Method scala/Function1$class.compose:(Lscala/Function1;Lscala/Function1;)Lscala/Function1;
   5:	areturn
  LineNumberTable: 
   line 60: 0

  LocalVariableTable: 
   Start  Length  Slot  Name   Signature
   0      6      0    this       Lscala/actors/ReactChannel$$anonfun$react$1;
   0      6      1    g       Lscala/Function1;


public java.lang.String toString();
  Code:
   Stack=1, Locals=1, Args_size=1
   0:	aload_0
   1:	invokestatic	#120; //Method scala/Function1$class.toString:(Lscala/Function1;)Ljava/lang/String;
   4:	areturn
  LineNumberTable: 
   line 60: 0


public scala.Function1 lift();
  Code:
   Stack=1, Locals=1, Args_size=1
   0:	aload_0
   1:	invokestatic	#125; //Method scala/PartialFunction$class.lift:(Lscala/PartialFunction;)Lscala/Function1;
   4:	areturn
  LineNumberTable: 
   line 60: 0


public scala.PartialFunction andThen(scala.Function1);
  Code:
   Stack=2, Locals=2, Args_size=2
   0:	aload_0
   1:	aload_1
   2:	invokestatic	#128; //Method scala/PartialFunction$class.andThen:(Lscala/PartialFunction;Lscala/Function1;)Lscala/PartialFunction;
   5:	areturn
  LineNumberTable: 
   line 60: 0

  LocalVariableTable: 
   Start  Length  Slot  Name   Signature
   0      6      0    this       Lscala/actors/ReactChannel$$anonfun$react$1;
   0      6      1    k       Lscala/Function1;


public scala.PartialFunction orElse(scala.PartialFunction);
  Code:
   Stack=2, Locals=2, Args_size=2
   0:	aload_0
   1:	aload_1
   2:	invokestatic	#134; //Method scala/PartialFunction$class.orElse:(Lscala/PartialFunction;Lscala/PartialFunction;)Lscala/PartialFunction;
   5:	areturn
  LineNumberTable: 
   line 60: 0

  LocalVariableTable: 
   Start  Length  Slot  Name   Signature
   0      6      0    this       Lscala/actors/ReactChannel$$anonfun$react$1;
   0      6      1    that       Lscala/PartialFunction;


}

