Compiled from "ReplyableReactor.scala"
public final class scala.actors.ReplyableReactor$$anon$1 extends scala.actors.Future
  SourceFile: "ReplyableReactor.scala"
  Signature: length = 0x2
   00 50 
  Scala: length = 0x
   
  InnerClass: 
   public final #85= #10 of #84; //$anon$1=class scala/actors/ReplyableReactor$$anon$1 of class scala/actors/ReplyableReactor
   public final #86= #53 of #10; //$anonfun$respond$1=class scala/actors/ReplyableReactor$$anon$1$$anonfun$respond$1 of class scala/actors/ReplyableReactor$$anon$1
  minor version: 0
  major version: 49
  Constant pool:
const #1 = Asciz	SourceFile;
const #2 = Asciz	ReplyableReactor.scala;
const #3 = Asciz	res$2;
const #4 = Asciz	Lscala/concurrent/SyncVar;;
const #5 = Asciz	<init>;
const #6 = Asciz	(Lscala/actors/ReplyReactor;Lscala/actors/ReactChannel;Lscala/concurrent/SyncVar;)V;
const #7 = Asciz	Code;
const #8 = Asciz	LineNumberTable;
const #9 = Asciz	scala/actors/ReplyableReactor$$anon$1;
const #10 = class	#9;	//  scala/actors/ReplyableReactor$$anon$1
const #11 = NameAndType	#3:#4;//  res$2:Lscala/concurrent/SyncVar;
const #12 = Field	#10.#11;	//  scala/actors/ReplyableReactor$$anon$1.res$2:Lscala/concurrent/SyncVar;
const #13 = Asciz	scala/actors/Future;
const #14 = class	#13;	//  scala/actors/Future
const #15 = Asciz	(Lscala/actors/InputChannel;)V;
const #16 = NameAndType	#5:#15;//  "<init>":(Lscala/actors/InputChannel;)V
const #17 = Method	#14.#16;	//  scala/actors/Future."<init>":(Lscala/actors/InputChannel;)V
const #18 = Asciz	this;
const #19 = Asciz	Lscala/actors/ReplyableReactor$$anon$1;;
const #20 = Asciz	$outer;
const #21 = Asciz	Lscala/actors/ReplyReactor;;
const #22 = Asciz	LocalVariableTable;
const #23 = Asciz	isSet;
const #24 = Asciz	()Z;
const #25 = Asciz	value;
const #26 = Asciz	()Lscala/Option;;
const #27 = NameAndType	#25:#26;//  value:()Lscala/Option;
const #28 = Method	#10.#27;	//  scala/actors/ReplyableReactor$$anon$1.value:()Lscala/Option;
const #29 = Asciz	scala/Option;
const #30 = class	#29;	//  scala/Option
const #31 = Asciz	isEmpty;
const #32 = NameAndType	#31:#24;//  isEmpty:()Z
const #33 = Method	#30.#32;	//  scala/Option.isEmpty:()Z
const #34 = Asciz	respond;
const #35 = Asciz	(Lscala/Function1;)V;
const #36 = NameAndType	#23:#24;//  isSet:()Z
const #37 = Method	#10.#36;	//  scala/actors/ReplyableReactor$$anon$1.isSet:()Z
const #38 = Asciz	get;
const #39 = Asciz	()Ljava/lang/Object;;
const #40 = NameAndType	#38:#39;//  get:()Ljava/lang/Object;
const #41 = Method	#30.#40;	//  scala/Option.get:()Ljava/lang/Object;
const #42 = Asciz	scala/Function1;
const #43 = class	#42;	//  scala/Function1
const #44 = Asciz	apply;
const #45 = Asciz	(Ljava/lang/Object;)Ljava/lang/Object;;
const #46 = NameAndType	#44:#45;//  apply:(Ljava/lang/Object;)Ljava/lang/Object;
const #47 = InterfaceMethod	#43.#46;	//  scala/Function1.apply:(Ljava/lang/Object;)Ljava/lang/Object;
const #48 = Asciz	inputChannel;
const #49 = Asciz	()Lscala/actors/InputChannel;;
const #50 = NameAndType	#48:#49;//  inputChannel:()Lscala/actors/InputChannel;
const #51 = Method	#10.#50;	//  scala/actors/ReplyableReactor$$anon$1.inputChannel:()Lscala/actors/InputChannel;
const #52 = Asciz	scala/actors/ReplyableReactor$$anon$1$$anonfun$respond$1;
const #53 = class	#52;	//  scala/actors/ReplyableReactor$$anon$1$$anonfun$respond$1
const #54 = Asciz	(Lscala/actors/ReplyableReactor$$anon$1;Lscala/Function1;)V;
const #55 = NameAndType	#5:#54;//  "<init>":(Lscala/actors/ReplyableReactor$$anon$1;Lscala/Function1;)V
const #56 = Method	#53.#55;	//  scala/actors/ReplyableReactor$$anon$1$$anonfun$respond$1."<init>":(Lscala/actors/ReplyableReactor$$anon$1;Lscala/Function1;)V
const #57 = Asciz	scala/actors/InputChannel;
const #58 = class	#57;	//  scala/actors/InputChannel
const #59 = Asciz	react;
const #60 = Asciz	(Lscala/PartialFunction;)Lscala/runtime/Nothing$;;
const #61 = NameAndType	#59:#60;//  react:(Lscala/PartialFunction;)Lscala/runtime/Nothing$;
const #62 = InterfaceMethod	#58.#61;	//  scala/actors/InputChannel.react:(Lscala/PartialFunction;)Lscala/runtime/Nothing$;
const #63 = Asciz	k$1;
const #64 = Asciz	Lscala/Function1;;
const #65 = Asciz	(Lscala/Function1<TA;Ljava/lang/Object;>;)V;
const #66 = Asciz	Signature;
const #67 = Asciz	scala/Some;
const #68 = class	#67;	//  scala/Some
const #69 = Asciz	scala/concurrent/SyncVar;
const #70 = class	#69;	//  scala/concurrent/SyncVar
const #71 = Method	#70.#40;	//  scala/concurrent/SyncVar.get:()Ljava/lang/Object;
const #72 = Asciz	(Ljava/lang/Object;)V;
const #73 = NameAndType	#5:#72;//  "<init>":(Ljava/lang/Object;)V
const #74 = Method	#68.#73;	//  scala/Some."<init>":(Ljava/lang/Object;)V
const #75 = Asciz	value_$eq;
const #76 = Asciz	(Lscala/Option;)V;
const #77 = NameAndType	#75:#76;//  value_$eq:(Lscala/Option;)V
const #78 = Method	#10.#77;	//  scala/actors/ReplyableReactor$$anon$1.value_$eq:(Lscala/Option;)V
const #79 = Asciz	()TA;;
const #80 = Asciz	Lscala/actors/Future<TA;>;;
const #81 = Asciz	Scala;
const #82 = Asciz	InnerClasses;
const #83 = Asciz	scala/actors/ReplyableReactor;
const #84 = class	#83;	//  scala/actors/ReplyableReactor
const #85 = Asciz	$anon$1;
const #86 = Asciz	$anonfun$respond$1;

{
public scala.actors.ReplyableReactor$$anon$1(scala.actors.ReplyReactor, scala.actors.ReactChannel, scala.concurrent.SyncVar);
  Code:
   Stack=2, Locals=4, Args_size=4
   0:	aload_0
   1:	aload_3
   2:	putfield	#12; //Field res$2:Lscala/concurrent/SyncVar;
   5:	aload_0
   6:	aload_2
   7:	invokespecial	#17; //Method scala/actors/Future."<init>":(Lscala/actors/InputChannel;)V
   10:	return
  LineNumberTable: 
   line 100: 0

  LocalVariableTable: 
   Start  Length  Slot  Name   Signature
   0      11      0    this       Lscala/actors/ReplyableReactor$$anon$1;
   0      11      1    $outer       Lscala/actors/ReplyReactor;


public boolean isSet();
  Code:
   Stack=1, Locals=1, Args_size=1
   0:	aload_0
   1:	invokevirtual	#28; //Method value:()Lscala/Option;
   4:	invokevirtual	#33; //Method scala/Option.isEmpty:()Z
   7:	ifeq	14
   10:	iconst_0
   11:	goto	15
   14:	iconst_1
   15:	ireturn
  LineNumberTable: 
   line 113: 0


public void respond(scala.Function1);
  Code:
   Stack=5, Locals=2, Args_size=2
   0:	aload_0
   1:	invokevirtual	#37; //Method isSet:()Z
   4:	ifeq	22
   7:	aload_1
   8:	aload_0
   9:	invokevirtual	#28; //Method value:()Lscala/Option;
   12:	invokevirtual	#41; //Method scala/Option.get:()Ljava/lang/Object;
   15:	invokeinterface	#47,  2; //InterfaceMethod scala/Function1.apply:(Ljava/lang/Object;)Ljava/lang/Object;
   20:	pop
   21:	return
   22:	aload_0
   23:	invokevirtual	#51; //Method inputChannel:()Lscala/actors/InputChannel;
   26:	new	#53; //class scala/actors/ReplyableReactor$$anon$1$$anonfun$respond$1
   29:	dup
   30:	aload_0
   31:	aload_1
   32:	invokespecial	#56; //Method scala/actors/ReplyableReactor$$anon$1$$anonfun$respond$1."<init>":(Lscala/actors/ReplyableReactor$$anon$1;Lscala/Function1;)V
   35:	invokeinterface	#62,  2; //InterfaceMethod scala/actors/InputChannel.react:(Lscala/PartialFunction;)Lscala/runtime/Nothing$;
   40:	athrow
  LineNumberTable: 
   line 108: 0
   line 109: 22

  LocalVariableTable: 
   Start  Length  Slot  Name   Signature
   0      41      0    this       Lscala/actors/ReplyableReactor$$anon$1;
   0      41      1    k$1       Lscala/Function1;

  Signature: length = 0x2
   00 41 

public java.lang.Object apply();
  Code:
   Stack=4, Locals=1, Args_size=1
   0:	aload_0
   1:	invokevirtual	#37; //Method isSet:()Z
   4:	ifeq	17
   7:	aload_0
   8:	invokevirtual	#28; //Method value:()Lscala/Option;
   11:	invokevirtual	#41; //Method scala/Option.get:()Ljava/lang/Object;
   14:	goto	42
   17:	aload_0
   18:	new	#68; //class scala/Some
   21:	dup
   22:	aload_0
   23:	getfield	#12; //Field res$2:Lscala/concurrent/SyncVar;
   26:	invokevirtual	#71; //Method scala/concurrent/SyncVar.get:()Ljava/lang/Object;
   29:	invokespecial	#74; //Method scala/Some."<init>":(Ljava/lang/Object;)V
   32:	invokevirtual	#78; //Method value_$eq:(Lscala/Option;)V
   35:	aload_0
   36:	invokevirtual	#28; //Method value:()Lscala/Option;
   39:	invokevirtual	#41; //Method scala/Option.get:()Ljava/lang/Object;
   42:	areturn
  LineNumberTable: 
   line 102: 0
   line 104: 17
   line 105: 35
   line 102: 42

  Signature: length = 0x2
   00 4F 

}

