Compiled from "ReplyableActor.scala"
public final class scala.actors.ReplyableActor$$anon$2 extends scala.actors.Future
  SourceFile: "ReplyableActor.scala"
  Signature: length = 0x2
   00 FFFFFFA1 
  Scala: length = 0x
   
  InnerClass: 
   public final $anon$2=class scala/actors/ReplyableActor$$anon$2 of class scala/actors/ReplyableActor
   public final $anonfun$3=class scala/actors/ReplyableActor$$anon$2$$anonfun$3 of class scala/actors/ReplyableActor$$anon$2
   public final $anonfun$2=class scala/actors/ReplyableActor$$anon$2$$anonfun$2 of class scala/actors/ReplyableActor$$anon$2
   public final $anonfun$1=class scala/actors/ReplyableActor$$anon$2$$anonfun$1 of class scala/actors/ReplyableActor$$anon$2
   public final $anonfun$apply$1=class scala/actors/ReplyableActor$$anon$2$$anonfun$apply$1 of class scala/actors/ReplyableActor$$anon$2
   public final $anonfun$respond$1=class scala/actors/ReplyableActor$$anon$2$$anonfun$respond$1 of class scala/actors/ReplyableActor$$anon$2
  minor version: 0
  major version: 49
  Constant pool:
Asciz	SourceFile;
Asciz	ReplyableActor.scala;
Asciz	handleReply;
Asciz	Lscala/PartialFunction;;
Asciz	Lscala/PartialFunction<Ljava/lang/Object;Ljava/lang/Object;>;;
Asciz	Signature;
Asciz	scala$actors$ReplyableActor$$anon$$exitReason;
Asciz	Lscala/Option;;
Asciz	<init>;
Asciz	(Lscala/actors/ReplyableActor;Lscala/actors/Channel;)V;
Asciz	Code;
Asciz	LineNumberTable;
Asciz	scala/actors/Future;
class	scala/actors/Future
Asciz	(Lscala/actors/InputChannel;)V;
NameAndType	"<init>":(Lscala/actors/InputChannel;)V
Method	scala/actors/Future."<init>":(Lscala/actors/InputChannel;)V
Asciz	scala/None$;
class	scala/None$
Asciz	MODULE$;
Asciz	Lscala/None$;;
NameAndType	MODULE$:Lscala/None$;
Field	scala/None$.MODULE$:Lscala/None$;
Asciz	scala/actors/ReplyableActor$$anon$2;
class	scala/actors/ReplyableActor$$anon$2
NameAndType	scala$actors$ReplyableActor$$anon$$exitReason:Lscala/Option;
Field	scala/actors/ReplyableActor$$anon$2.scala$actors$ReplyableActor$$anon$$exitReason:Lscala/Option;
Asciz	scala/actors/ReplyableActor$$anon$2$$anonfun$1;
class	scala/actors/ReplyableActor$$anon$2$$anonfun$1
Asciz	(Lscala/actors/ReplyableActor$$anon$2;)V;
NameAndType	"<init>":(Lscala/actors/ReplyableActor$$anon$2;)V
Method	scala/actors/ReplyableActor$$anon$2$$anonfun$1."<init>":(Lscala/actors/ReplyableActor$$anon$2;)V
NameAndType	handleReply:Lscala/PartialFunction;
Field	scala/actors/ReplyableActor$$anon$2.handleReply:Lscala/PartialFunction;
Asciz	this;
Asciz	Lscala/actors/ReplyableActor$$anon$2;;
Asciz	$outer;
Asciz	Lscala/actors/ReplyableActor;;
Asciz	LocalVariableTable;
Asciz	isSet;
Asciz	()Z;
Asciz	fvalue;
Asciz	()Lscala/Option;;
NameAndType	fvalue:()Lscala/Option;
Method	scala/actors/ReplyableActor$$anon$2.fvalue:()Lscala/Option;
Asciz	java/lang/Object;
class	java/lang/Object
Asciz	equals;
Asciz	(Ljava/lang/Object;)Z;
NameAndType	equals:(Ljava/lang/Object;)Z
Method	java/lang/Object.equals:(Ljava/lang/Object;)Z
Asciz	scala/actors/ReplyableActor$$anon$2$$anonfun$2;
class	scala/actors/ReplyableActor$$anon$2$$anonfun$2
Method	scala/actors/ReplyableActor$$anon$2$$anonfun$2."<init>":(Lscala/actors/ReplyableActor$$anon$2;)V
Asciz	()Lscala/PartialFunction;;
NameAndType	handleReply:()Lscala/PartialFunction;
Method	scala/actors/ReplyableActor$$anon$2.handleReply:()Lscala/PartialFunction;
Asciz	scala/actors/ReplyableActor$$anon$2$$anonfun$3;
class	scala/actors/ReplyableActor$$anon$2$$anonfun$3
Method	scala/actors/ReplyableActor$$anon$2$$anonfun$3."<init>":(Lscala/actors/ReplyableActor$$anon$2;)V
Asciz	scala/PartialFunction;
class	scala/PartialFunction
Asciz	andThen;
Asciz	(Lscala/Function1;)Lscala/PartialFunction;;
NameAndType	andThen:(Lscala/Function1;)Lscala/PartialFunction;
InterfaceMethod	scala/PartialFunction.andThen:(Lscala/Function1;)Lscala/PartialFunction;
Asciz	scala/PartialFunction$class;
class	scala/PartialFunction$class
Asciz	orElse;
Asciz	(Lscala/PartialFunction;Lscala/PartialFunction;)Lscala/PartialFunction;;
NameAndType	orElse:(Lscala/PartialFunction;Lscala/PartialFunction;)Lscala/PartialFunction;
Method	scala/PartialFunction$class.orElse:(Lscala/PartialFunction;Lscala/PartialFunction;)Lscala/PartialFunction;
Asciz	inputChannel;
Asciz	()Lscala/actors/InputChannel;;
NameAndType	inputChannel:()Lscala/actors/InputChannel;
Method	scala/actors/ReplyableActor$$anon$2.inputChannel:()Lscala/actors/InputChannel;
Asciz	scala/actors/InputChannel;
class	scala/actors/InputChannel
Asciz	receiveWithin;
Asciz	(JLscala/PartialFunction;)Ljava/lang/Object;;
NameAndType	receiveWithin:(JLscala/PartialFunction;)Ljava/lang/Object;
InterfaceMethod	scala/actors/InputChannel.receiveWithin:(JLscala/PartialFunction;)Ljava/lang/Object;
Asciz	scala/runtime/BoxesRunTime;
class	scala/runtime/BoxesRunTime
Asciz	unboxToBoolean;
NameAndType	unboxToBoolean:(Ljava/lang/Object;)Z
Method	scala/runtime/BoxesRunTime.unboxToBoolean:(Ljava/lang/Object;)Z
Asciz	scala/MatchError;
class	scala/MatchError
Asciz	scala/Option;
class	scala/Option
Asciz	toString;
Asciz	()Ljava/lang/String;;
NameAndType	toString:()Ljava/lang/String;
Method	scala/Option.toString:()Ljava/lang/String;
Asciz	(Ljava/lang/String;)V;
NameAndType	"<init>":(Ljava/lang/String;)V
Method	scala/MatchError."<init>":(Ljava/lang/String;)V
Asciz	scala/Some;
class	scala/Some
NameAndType	scala$actors$ReplyableActor$$anon$$exitReason:()Lscala/Option;
Method	scala/actors/ReplyableActor$$anon$2.scala$actors$ReplyableActor$$anon$$exitReason:()Lscala/Option;
Asciz	isEmpty;
NameAndType	isEmpty:()Z
Method	scala/Option.isEmpty:()Z
Asciz	handleTimeout;
Asciz	whatToDo;
Asciz	temp12;
Asciz	respond;
Asciz	(Lscala/Function1;)V;
NameAndType	isSet:()Z
Method	scala/actors/ReplyableActor$$anon$2.isSet:()Z
Asciz	apply;
Asciz	()Ljava/lang/Object;;
NameAndType	apply:()Ljava/lang/Object;
Method	scala/actors/ReplyableActor$$anon$2.apply:()Ljava/lang/Object;
Asciz	scala/actors/ReplyableActor$$anon$2$$anonfun$respond$1;
class	scala/actors/ReplyableActor$$anon$2$$anonfun$respond$1
Asciz	(Lscala/actors/ReplyableActor$$anon$2;Lscala/Function1;)V;
NameAndType	"<init>":(Lscala/actors/ReplyableActor$$anon$2;Lscala/Function1;)V
Method	scala/actors/ReplyableActor$$anon$2$$anonfun$respond$1."<init>":(Lscala/actors/ReplyableActor$$anon$2;Lscala/Function1;)V
Asciz	react;
Asciz	(Lscala/PartialFunction;)Lscala/runtime/Nothing$;;
NameAndType	react:(Lscala/PartialFunction;)Lscala/runtime/Nothing$;
InterfaceMethod	scala/actors/InputChannel.react:(Lscala/PartialFunction;)Lscala/runtime/Nothing$;
Asciz	k$1;
Asciz	Lscala/Function1;;
Asciz	(Lscala/Function1<Ljava/lang/Object;Ljava/lang/Object;>;)V;
Asciz	scala/runtime/BoxedUnit;
class	scala/runtime/BoxedUnit
Asciz	UNIT;
Asciz	Lscala/runtime/BoxedUnit;;
NameAndType	UNIT:Lscala/runtime/BoxedUnit;
Field	scala/runtime/BoxedUnit.UNIT:Lscala/runtime/BoxedUnit;
Asciz	get;
NameAndType	get:()Ljava/lang/Object;
Method	scala/Option.get:()Ljava/lang/Object;
Asciz	java/lang/Throwable;
class	java/lang/Throwable
Asciz	java/util/concurrent/ExecutionException;
class	java/util/concurrent/ExecutionException
Asciz	(Ljava/lang/Throwable;)V;
NameAndType	"<init>":(Ljava/lang/Throwable;)V
Method	java/util/concurrent/ExecutionException."<init>":(Ljava/lang/Throwable;)V
Asciz	java/lang/Exception;
class	java/lang/Exception
Method	java/lang/Object.toString:()Ljava/lang/String;
Method	java/lang/Exception."<init>":(Ljava/lang/String;)V
Asciz	scala/actors/ReplyableActor$$anon$2$$anonfun$apply$1;
class	scala/actors/ReplyableActor$$anon$2$$anonfun$apply$1
Method	scala/actors/ReplyableActor$$anon$2$$anonfun$apply$1."<init>":(Lscala/actors/ReplyableActor$$anon$2;)V
Asciz	receive;
Asciz	(Lscala/PartialFunction;)Ljava/lang/Object;;
NameAndType	receive:(Lscala/PartialFunction;)Ljava/lang/Object;
InterfaceMethod	scala/actors/InputChannel.receive:(Lscala/PartialFunction;)Ljava/lang/Object;
Asciz	reason;
Asciz	Ljava/lang/Object;;
Asciz	()Lscala/PartialFunction<Ljava/lang/Object;Ljava/lang/Object;>;;
Asciz	scala$actors$ReplyableActor$$anon$$exitReason_$eq;
Asciz	(Lscala/Option;)V;
Asciz	Lscala/actors/Future<Ljava/lang/Object;>;;
Asciz	Scala;
Asciz	InnerClasses;
Asciz	scala/actors/ReplyableActor;
class	scala/actors/ReplyableActor
Asciz	$anon$2;
Asciz	$anonfun$3;
Asciz	$anonfun$2;
Asciz	$anonfun$1;
Asciz	$anonfun$apply$1;
Asciz	$anonfun$respond$1;

{
private final scala.PartialFunction handleReply;
  Signature: Lscala/PartialFunction;
  Signature: length = 0x2
   00 05 

private scala.Option scala$actors$ReplyableActor$$anon$$exitReason;
  Signature: Lscala/Option;

public scala.actors.ReplyableActor$$anon$2(scala.actors.ReplyableActor, scala.actors.Channel);
  Signature: (Lscala/actors/ReplyableActor;Lscala/actors/Channel;)V
  Code:
   Stack=4, Locals=3, Args_size=3
	aload_0
	aload_2
	invokespecial	Method scala/actors/Future."<init>":(Lscala/actors/InputChannel;)V
	aload_0
	getstatic	Field scala/None$.MODULE$:Lscala/None$;
	putfield	Field scala$actors$ReplyableActor$$anon$$exitReason:Lscala/Option;
	aload_0
	new	class scala/actors/ReplyableActor$$anon$2$$anonfun$1
	dup
	aload_0
	invokespecial	Method scala/actors/ReplyableActor$$anon$2$$anonfun$1."<init>":(Lscala/actors/ReplyableActor$$anon$2;)V
	putfield	Field handleReply:Lscala/PartialFunction;
	return
  Labels:
  LocalVariableTable: 
   Start  Length  Slot  Name   Signature
   0      25      0    this       Lscala/actors/ReplyableActor$$anon$2;
   0      25      1    $outer       Lscala/actors/ReplyableActor;


public boolean isSet();
  Signature: ()Z
  Code:
   Stack=4, Locals=5, Args_size=1
	aload_0
	invokevirtual	Method fvalue:()Lscala/Option;
	astore	4
	getstatic	Field scala/None$.MODULE$:Lscala/None$;
	dup
	ifnonnull	l1 // aload
	pop
	aload	4
	ifnull	l2 // iconst_1
	goto	l3 // aload
l1	aload	4
	invokevirtual	Method java/lang/Object.equals:(Ljava/lang/Object;)Z
	ifeq	l3 // aload
l2	iconst_1
	ifeq	l4 // new
	new	class scala/actors/ReplyableActor$$anon$2$$anonfun$2
	dup
	aload_0
	invokespecial	Method scala/actors/ReplyableActor$$anon$2$$anonfun$2."<init>":(Lscala/actors/ReplyableActor$$anon$2;)V
	astore_1
	aload_0
	invokespecial	Method handleReply:()Lscala/PartialFunction;
	new	class scala/actors/ReplyableActor$$anon$2$$anonfun$3
	dup
	aload_0
	invokespecial	Method scala/actors/ReplyableActor$$anon$2$$anonfun$3."<init>":(Lscala/actors/ReplyableActor$$anon$2;)V
	invokeinterface	InterfaceMethod scala/PartialFunction.andThen:(Lscala/Function1;)Lscala/PartialFunction;
	astore_2
	aload_1
	aload_2
	invokestatic	Method scala/PartialFunction$class.orElse:(Lscala/PartialFunction;Lscala/PartialFunction;)Lscala/PartialFunction;
	astore_3
	aload_0
	invokevirtual	Method inputChannel:()Lscala/actors/InputChannel;
	lconst_0
	aload_3
	invokeinterface	InterfaceMethod scala/actors/InputChannel.receiveWithin:(JLscala/PartialFunction;)Ljava/lang/Object;
	invokestatic	Method scala/runtime/BoxesRunTime.unboxToBoolean:(Ljava/lang/Object;)Z
	goto	l5 // ifne
l4	new	class scala/MatchError
	dup
	aload	4
	invokevirtual	Method scala/Option.toString:()Ljava/lang/String;
	invokespecial	Method scala/MatchError."<init>":(Ljava/lang/String;)V
	athrow
l3	aload	4
	instanceof	class scala/Some
	ifeq	l6 // new
	iconst_1
	ifeq	l7 // new
	iconst_1
l5	ifne	l8 // iconst_1
	aload_0
	invokespecial	Method scala$actors$ReplyableActor$$anon$$exitReason:()Lscala/Option;
	invokevirtual	Method scala/Option.isEmpty:()Z
	ifeq	l8 // iconst_1
	iconst_0
	goto	l9 // ireturn
l8	iconst_1
l9	ireturn
l7	new	class scala/MatchError
	dup
	aload	4
	invokevirtual	Method scala/Option.toString:()Ljava/lang/String;
	invokespecial	Method scala/MatchError."<init>":(Ljava/lang/String;)V
	athrow
l6	new	class scala/MatchError
	dup
	aload	4
	invokevirtual	Method scala/Option.toString:()Ljava/lang/String;
	invokespecial	Method scala/MatchError."<init>":(Ljava/lang/String;)V
	athrow
  Labels:
   	l1 = 22 // aload
   	l2 = 30 // iconst_1
   	l4 = 84 // new
   	l3 = 97 // aload
   	l5 = 110 // ifne
   	l8 = 127 // iconst_1
   	l9 = 128 // ireturn
   	l7 = 129 // new
   	l6 = 142 // new
  LocalVariableTable: 
   Start  Length  Slot  Name   Signature
   0      155      0    this       Lscala/actors/ReplyableActor$$anon$2;
   43      38      1    handleTimeout       Lscala/PartialFunction;
   67      14      3    whatToDo       Lscala/PartialFunction;
   6      107      4    temp12       Lscala/Option;
   129      26      4    temp12       Lscala/Option;


public void respond(scala.Function1);
  Signature: (Lscala/Function1;)V
  Code:
   Stack=6, Locals=2, Args_size=2
	aload_0
	invokevirtual	Method isSet:()Z
	ifeq	l1 // aload_0
	aload_0
	invokevirtual	Method apply:()Ljava/lang/Object;
	pop
	return
l1	aload_0
	invokevirtual	Method inputChannel:()Lscala/actors/InputChannel;
	aload_0
	invokespecial	Method handleReply:()Lscala/PartialFunction;
	new	class scala/actors/ReplyableActor$$anon$2$$anonfun$respond$1
	dup
	aload_0
	aload_1
	invokespecial	Method scala/actors/ReplyableActor$$anon$2$$anonfun$respond$1."<init>":(Lscala/actors/ReplyableActor$$anon$2;Lscala/Function1;)V
	invokeinterface	InterfaceMethod scala/PartialFunction.andThen:(Lscala/Function1;)Lscala/PartialFunction;
	invokeinterface	InterfaceMethod scala/actors/InputChannel.react:(Lscala/PartialFunction;)Lscala/runtime/Nothing$;
	athrow
  Labels:
   	l1 = 13 // aload_0
  LocalVariableTable: 
   Start  Length  Slot  Name   Signature
   0      41      0    this       Lscala/actors/ReplyableActor$$anon$2;
   0      41      1    k$1       Lscala/Function1;

  Signature: length = 0x2
   00 FFFFFF80 

public java.lang.Object apply();
  Signature: ()Ljava/lang/Object;
  Code:
   Stack=5, Locals=2, Args_size=1
	aload_0
	invokevirtual	Method isSet:()Z
	ifeq	l1 // aload_0
	aload_0
	invokevirtual	Method fvalue:()Lscala/Option;
	invokevirtual	Method scala/Option.isEmpty:()Z
	ifeq	l2 // aload_0
	aload_0
	invokespecial	Method scala$actors$ReplyableActor$$anon$$exitReason:()Lscala/Option;
	invokevirtual	Method scala/Option.isEmpty:()Z
	ifeq	l3 // aload_0
	getstatic	Field scala/runtime/BoxedUnit.UNIT:Lscala/runtime/BoxedUnit;
	goto	l4 // areturn
l3	aload_0
	invokespecial	Method scala$actors$ReplyableActor$$anon$$exitReason:()Lscala/Option;
	invokevirtual	Method scala/Option.get:()Ljava/lang/Object;
	astore_1
	aload_1
	instanceof	class java/lang/Throwable
	ifeq	l5 // new
	new	class java/util/concurrent/ExecutionException
	dup
	aload_1
	checkcast	class java/lang/Throwable
	invokespecial	Method java/util/concurrent/ExecutionException."<init>":(Ljava/lang/Throwable;)V
	athrow
l5	new	class java/util/concurrent/ExecutionException
	dup
	new	class java/lang/Exception
	dup
	aload_1
	invokevirtual	Method java/lang/Object.toString:()Ljava/lang/String;
	invokespecial	Method java/lang/Exception."<init>":(Ljava/lang/String;)V
	invokespecial	Method java/util/concurrent/ExecutionException."<init>":(Ljava/lang/Throwable;)V
	athrow
l2	aload_0
	invokevirtual	Method fvalue:()Lscala/Option;
	invokevirtual	Method scala/Option.get:()Ljava/lang/Object;
	goto	l4 // areturn
l1	aload_0
	invokevirtual	Method inputChannel:()Lscala/actors/InputChannel;
	aload_0
	invokespecial	Method handleReply:()Lscala/PartialFunction;
	new	class scala/actors/ReplyableActor$$anon$2$$anonfun$apply$1
	dup
	aload_0
	invokespecial	Method scala/actors/ReplyableActor$$anon$2$$anonfun$apply$1."<init>":(Lscala/actors/ReplyableActor$$anon$2;)V
	invokeinterface	InterfaceMethod scala/PartialFunction.andThen:(Lscala/Function1;)Lscala/PartialFunction;
	invokeinterface	InterfaceMethod scala/actors/InputChannel.receive:(Lscala/PartialFunction;)Ljava/lang/Object;
l4	areturn
  Labels:
   	l3 = 33 // aload_0
   	l5 = 60 // new
   	l2 = 79 // aload_0
   	l1 = 89 // aload_0
   	l4 = 115 // areturn
  LocalVariableTable: 
   Start  Length  Slot  Name   Signature
   0      116      0    this       Lscala/actors/ReplyableActor$$anon$2;
   41      38      1    reason       Ljava/lang/Object;


private scala.PartialFunction handleReply();
  Signature: ()Lscala/PartialFunction;
  Code:
   Stack=1, Locals=1, Args_size=1
	aload_0
	getfield	Field handleReply:Lscala/PartialFunction;
	areturn
  Labels:
  Signature: length = 0x2
   00 FFFFFF9E 

public final void scala$actors$ReplyableActor$$anon$$exitReason_$eq(scala.Option);
  Signature: (Lscala/Option;)V
  Code:
   Stack=2, Locals=2, Args_size=2
	aload_0
	aload_1
	putfield	Field scala$actors$ReplyableActor$$anon$$exitReason:Lscala/Option;
	return
  Labels:

private scala.Option scala$actors$ReplyableActor$$anon$$exitReason();
  Signature: ()Lscala/Option;
  Code:
   Stack=1, Locals=1, Args_size=1
	aload_0
	getfield	Field scala$actors$ReplyableActor$$anon$$exitReason:Lscala/Option;
	areturn
  Labels:

}

