Compiled from "Replyable.scala"
public abstract class scala.actors.Replyable$class extends java.lang.Object
  SourceFile: "Replyable.scala"
  Scala: length = 0x
   
  InnerClass: 
   public final #33= #24 of #32; //$anonfun$$bang$bang$1=class scala/actors/Replyable$$anonfun$$bang$bang$1 of class scala/actors/Replyable
   public final #34= #13 of #32; //$anonfun$$bang$bang$2=class scala/actors/Replyable$$anonfun$$bang$bang$2 of class scala/actors/Replyable
  minor version: 0
  major version: 49
  Constant pool:
const #1 = Asciz	SourceFile;
const #2 = Asciz	Replyable.scala;
const #3 = Asciz	$init$;
const #4 = Asciz	(Lscala/actors/Replyable;)V;
const #5 = Asciz	Code;
const #6 = Asciz	LineNumberTable;
const #7 = Asciz	$this;
const #8 = Asciz	Lscala/actors/Replyable;;
const #9 = Asciz	LocalVariableTable;
const #10 = Asciz	$bang$bang;
const #11 = Asciz	(Lscala/actors/Replyable;Ljava/lang/Object;Lscala/PartialFunction;)Lscala/Function0;;
const #12 = Asciz	scala/actors/Replyable$$anonfun$$bang$bang$2;
const #13 = class	#12;	//  scala/actors/Replyable$$anonfun$$bang$bang$2
const #14 = Asciz	<init>;
const #15 = Asciz	(Lscala/actors/Replyable;Ljava/lang/Object;Lscala/PartialFunction;)V;
const #16 = NameAndType	#14:#15;//  "<init>":(Lscala/actors/Replyable;Ljava/lang/Object;Lscala/PartialFunction;)V
const #17 = Method	#13.#16;	//  scala/actors/Replyable$$anonfun$$bang$bang$2."<init>":(Lscala/actors/Replyable;Ljava/lang/Object;Lscala/PartialFunction;)V
const #18 = Asciz	msg$1;
const #19 = Asciz	Ljava/lang/Object;;
const #20 = Asciz	f$1;
const #21 = Asciz	Lscala/PartialFunction;;
const #22 = Asciz	(Lscala/actors/Replyable;Ljava/lang/Object;)Lscala/Function0;;
const #23 = Asciz	scala/actors/Replyable$$anonfun$$bang$bang$1;
const #24 = class	#23;	//  scala/actors/Replyable$$anonfun$$bang$bang$1
const #25 = Asciz	(Lscala/actors/Replyable;Ljava/lang/Object;)V;
const #26 = NameAndType	#14:#25;//  "<init>":(Lscala/actors/Replyable;Ljava/lang/Object;)V
const #27 = Method	#24.#26;	//  scala/actors/Replyable$$anonfun$$bang$bang$1."<init>":(Lscala/actors/Replyable;Ljava/lang/Object;)V
const #28 = Asciz	msg$2;
const #29 = Asciz	Scala;
const #30 = Asciz	InnerClasses;
const #31 = Asciz	scala/actors/Replyable;
const #32 = class	#31;	//  scala/actors/Replyable
const #33 = Asciz	$anonfun$$bang$bang$1;
const #34 = Asciz	$anonfun$$bang$bang$2;
const #35 = Asciz	scala/actors/Replyable$class;
const #36 = class	#35;	//  scala/actors/Replyable$class
const #37 = Asciz	java/lang/Object;
const #38 = class	#37;	//  java/lang/Object

{
public static void $init$(scala.actors.Replyable);
  Code:
   Stack=0, Locals=1, Args_size=1
   0:	return
  LineNumberTable: 
   line 19: 0

  LocalVariableTable: 
   Start  Length  Slot  Name   Signature
   0      1      0    $this       Lscala/actors/Replyable;


public static scala.Function0 $bang$bang(scala.actors.Replyable, java.lang.Object, scala.PartialFunction);
  Code:
   Stack=5, Locals=3, Args_size=3
   0:	new	#13; //class scala/actors/Replyable$$anonfun$$bang$bang$2
   3:	dup
   4:	aload_0
   5:	aload_1
   6:	aload_2
   7:	invokespecial	#17; //Method scala/actors/Replyable$$anonfun$$bang$bang$2."<init>":(Lscala/actors/Replyable;Ljava/lang/Object;Lscala/PartialFunction;)V
   10:	areturn
  LineNumberTable: 
   line 63: 0

  LocalVariableTable: 
   Start  Length  Slot  Name   Signature
   0      11      0    $this       Lscala/actors/Replyable;
   0      11      1    msg$1       Ljava/lang/Object;
   0      11      2    f$1       Lscala/PartialFunction;


public static scala.Function0 $bang$bang(scala.actors.Replyable, java.lang.Object);
  Code:
   Stack=4, Locals=2, Args_size=2
   0:	new	#24; //class scala/actors/Replyable$$anonfun$$bang$bang$1
   3:	dup
   4:	aload_0
   5:	aload_1
   6:	invokespecial	#27; //Method scala/actors/Replyable$$anonfun$$bang$bang$1."<init>":(Lscala/actors/Replyable;Ljava/lang/Object;)V
   9:	areturn
  LineNumberTable: 
   line 49: 0

  LocalVariableTable: 
   Start  Length  Slot  Name   Signature
   0      10      0    $this       Lscala/actors/Replyable;
   0      10      1    msg$2       Ljava/lang/Object;


}

