Compiled from "ReplyReactor.scala"
public final class scala.actors.ReplyReactor$$anonfun$1 extends java.lang.Object implements scala.Function2,scala.ScalaObject,java.io.Serializable
  SourceFile: "ReplyReactor.scala"
  Scala: length = 0x
   
  InnerClass: 
   public final #107= #9 of #76; //$anonfun$1=class scala/actors/ReplyReactor$$anonfun$1 of class scala/actors/ReplyReactor
  minor version: 0
  major version: 49
  Constant pool:
const #1 = Asciz	SourceFile;
const #2 = Asciz	ReplyReactor.scala;
const #3 = Asciz	<clinit>;
const #4 = Asciz	()V;
const #5 = Asciz	Code;
const #6 = Asciz	serialVersionUID;
const #7 = Asciz	J;
const #8 = Asciz	scala/actors/ReplyReactor$$anonfun$1;
const #9 = class	#8;	//  scala/actors/ReplyReactor$$anonfun$1
const #10 = NameAndType	#6:#7;//  serialVersionUID:J
const #11 = Field	#9.#10;	//  scala/actors/ReplyReactor$$anonfun$1.serialVersionUID:J
const #12 = Asciz	handlesMessage$1;
const #13 = Asciz	Lscala/Function1;;
const #14 = Asciz	$outer;
const #15 = Asciz	Lscala/actors/ReplyReactor;;
const #16 = Asciz	<init>;
const #17 = Asciz	(Lscala/actors/ReplyReactor;Lscala/Function1;)V;
const #18 = Asciz	LineNumberTable;
const #19 = Asciz	java/lang/NullPointerException;
const #20 = class	#19;	//  java/lang/NullPointerException
const #21 = NameAndType	#16:#4;//  "<init>":()V
const #22 = Method	#20.#21;	//  java/lang/NullPointerException."<init>":()V
const #23 = NameAndType	#14:#15;//  $outer:Lscala/actors/ReplyReactor;
const #24 = Field	#9.#23;	//  scala/actors/ReplyReactor$$anonfun$1.$outer:Lscala/actors/ReplyReactor;
const #25 = NameAndType	#12:#13;//  handlesMessage$1:Lscala/Function1;
const #26 = Field	#9.#25;	//  scala/actors/ReplyReactor$$anonfun$1.handlesMessage$1:Lscala/Function1;
const #27 = Asciz	java/lang/Object;
const #28 = class	#27;	//  java/lang/Object
const #29 = Method	#28.#21;	//  java/lang/Object."<init>":()V
const #30 = Asciz	scala/Function2$class;
const #31 = class	#30;	//  scala/Function2$class
const #32 = Asciz	$init$;
const #33 = Asciz	(Lscala/Function2;)V;
const #34 = NameAndType	#32:#33;//  $init$:(Lscala/Function2;)V
const #35 = Method	#31.#34;	//  scala/Function2$class.$init$:(Lscala/Function2;)V
const #36 = Asciz	this;
const #37 = Asciz	Lscala/actors/ReplyReactor$$anonfun$1;;
const #38 = Asciz	LocalVariableTable;
const #39 = Asciz	apply;
const #40 = Asciz	(Ljava/lang/Object;Ljava/lang/Object;)Ljava/lang/Object;;
const #41 = Asciz	scala/actors/OutputChannel;
const #42 = class	#41;	//  scala/actors/OutputChannel
const #43 = Asciz	(Ljava/lang/Object;Lscala/actors/OutputChannel;)Z;
const #44 = NameAndType	#39:#43;//  apply:(Ljava/lang/Object;Lscala/actors/OutputChannel;)Z
const #45 = Method	#9.#44;	//  scala/actors/ReplyReactor$$anonfun$1.apply:(Ljava/lang/Object;Lscala/actors/OutputChannel;)Z
const #46 = Asciz	scala/runtime/BoxesRunTime;
const #47 = class	#46;	//  scala/runtime/BoxesRunTime
const #48 = Asciz	boxToBoolean;
const #49 = Asciz	(Z)Ljava/lang/Boolean;;
const #50 = NameAndType	#48:#49;//  boxToBoolean:(Z)Ljava/lang/Boolean;
const #51 = Method	#47.#50;	//  scala/runtime/BoxesRunTime.boxToBoolean:(Z)Ljava/lang/Boolean;
const #52 = Asciz	v1;
const #53 = Asciz	Ljava/lang/Object;;
const #54 = Asciz	v2;
const #55 = Asciz	scala/collection/immutable/List$;
const #56 = class	#55;	//  scala/collection/immutable/List$
const #57 = Asciz	MODULE$;
const #58 = Asciz	Lscala/collection/immutable/List$;;
const #59 = NameAndType	#57:#58;//  MODULE$:Lscala/collection/immutable/List$;
const #60 = Field	#56.#59;	//  scala/collection/immutable/List$.MODULE$:Lscala/collection/immutable/List$;
const #61 = Asciz	scala/Predef$;
const #62 = class	#61;	//  scala/Predef$
const #63 = Asciz	Lscala/Predef$;;
const #64 = NameAndType	#57:#63;//  MODULE$:Lscala/Predef$;
const #65 = Field	#62.#64;	//  scala/Predef$.MODULE$:Lscala/Predef$;
const #66 = Asciz	[Ljava/lang/Object;;
const #67 = class	#66;	//  "[Ljava/lang/Object;"
const #68 = Asciz	wrapRefArray;
const #69 = Asciz	([Ljava/lang/Object;)Lscala/collection/mutable/WrappedArray;;
const #70 = NameAndType	#68:#69;//  wrapRefArray:([Ljava/lang/Object;)Lscala/collection/mutable/WrappedArray;
const #71 = Method	#62.#70;	//  scala/Predef$.wrapRefArray:([Ljava/lang/Object;)Lscala/collection/mutable/WrappedArray;
const #72 = Asciz	(Lscala/collection/Seq;)Lscala/collection/immutable/List;;
const #73 = NameAndType	#39:#72;//  apply:(Lscala/collection/Seq;)Lscala/collection/immutable/List;
const #74 = Method	#56.#73;	//  scala/collection/immutable/List$.apply:(Lscala/collection/Seq;)Lscala/collection/immutable/List;
const #75 = Asciz	scala/actors/ReplyReactor;
const #76 = class	#75;	//  scala/actors/ReplyReactor
const #77 = Asciz	senders_$eq;
const #78 = Asciz	(Lscala/collection/immutable/List;)V;
const #79 = NameAndType	#77:#78;//  senders_$eq:(Lscala/collection/immutable/List;)V
const #80 = InterfaceMethod	#76.#79;	//  scala/actors/ReplyReactor.senders_$eq:(Lscala/collection/immutable/List;)V
const #81 = Asciz	scala/Function1;
const #82 = class	#81;	//  scala/Function1
const #83 = Asciz	(Ljava/lang/Object;)Ljava/lang/Object;;
const #84 = NameAndType	#39:#83;//  apply:(Ljava/lang/Object;)Ljava/lang/Object;
const #85 = InterfaceMethod	#82.#84;	//  scala/Function1.apply:(Ljava/lang/Object;)Ljava/lang/Object;
const #86 = Asciz	unboxToBoolean;
const #87 = Asciz	(Ljava/lang/Object;)Z;
const #88 = NameAndType	#86:#87;//  unboxToBoolean:(Ljava/lang/Object;)Z
const #89 = Method	#47.#88;	//  scala/runtime/BoxesRunTime.unboxToBoolean:(Ljava/lang/Object;)Z
const #90 = Asciz	msg;
const #91 = Asciz	replyTo;
const #92 = Asciz	Lscala/actors/OutputChannel;;
const #93 = Asciz	(Ljava/lang/Object;Lscala/actors/OutputChannel<Ljava/lang/Object;>;)Z;
const #94 = Asciz	Signature;
const #95 = Asciz	curry;
const #96 = Asciz	()Lscala/Function1;;
const #97 = Asciz	(Lscala/Function2;)Lscala/Function1;;
const #98 = NameAndType	#95:#97;//  curry:(Lscala/Function2;)Lscala/Function1;
const #99 = Method	#31.#98;	//  scala/Function2$class.curry:(Lscala/Function2;)Lscala/Function1;
const #100 = Asciz	toString;
const #101 = Asciz	()Ljava/lang/String;;
const #102 = Asciz	(Lscala/Function2;)Ljava/lang/String;;
const #103 = NameAndType	#100:#102;//  toString:(Lscala/Function2;)Ljava/lang/String;
const #104 = Method	#31.#103;	//  scala/Function2$class.toString:(Lscala/Function2;)Ljava/lang/String;
const #105 = Asciz	Scala;
const #106 = Asciz	InnerClasses;
const #107 = Asciz	$anonfun$1;
const #108 = Asciz	scala/Function2;
const #109 = class	#108;	//  scala/Function2
const #110 = Asciz	scala/ScalaObject;
const #111 = class	#110;	//  scala/ScalaObject
const #112 = Asciz	java/io/Serializable;
const #113 = class	#112;	//  java/io/Serializable

{
public static final long serialVersionUID;

public static {};
  Code:
   Stack=2, Locals=0, Args_size=0
   0:	lconst_0
   1:	putstatic	#11; //Field serialVersionUID:J
   4:	return

public scala.actors.ReplyReactor$$anonfun$1(scala.actors.ReplyReactor, scala.Function1);
  Code:
   Stack=2, Locals=3, Args_size=3
   0:	aload_1
   1:	ifnonnull	12
   4:	new	#20; //class java/lang/NullPointerException
   7:	dup
   8:	invokespecial	#22; //Method java/lang/NullPointerException."<init>":()V
   11:	athrow
   12:	aload_0
   13:	aload_1
   14:	putfield	#24; //Field $outer:Lscala/actors/ReplyReactor;
   17:	aload_0
   18:	aload_2
   19:	putfield	#26; //Field handlesMessage$1:Lscala/Function1;
   22:	aload_0
   23:	invokespecial	#29; //Method java/lang/Object."<init>":()V
   26:	aload_0
   27:	invokestatic	#35; //Method scala/Function2$class.$init$:(Lscala/Function2;)V
   30:	return
  LineNumberTable: 
   line 71: 0

  LocalVariableTable: 
   Start  Length  Slot  Name   Signature
   0      31      0    this       Lscala/actors/ReplyReactor$$anonfun$1;
   0      31      1    $outer       Lscala/actors/ReplyReactor;


public final java.lang.Object apply(java.lang.Object, java.lang.Object);
  Code:
   Stack=3, Locals=5, Args_size=3
   0:	aload_0
   1:	getfield	#24; //Field $outer:Lscala/actors/ReplyReactor;
   4:	astore	4
   6:	aload_0
   7:	aload_1
   8:	aload_2
   9:	checkcast	#42; //class scala/actors/OutputChannel
   12:	invokevirtual	#45; //Method apply:(Ljava/lang/Object;Lscala/actors/OutputChannel;)Z
   15:	istore_3
   16:	iload_3
   17:	invokestatic	#51; //Method scala/runtime/BoxesRunTime.boxToBoolean:(Z)Ljava/lang/Boolean;
   20:	areturn
  LineNumberTable: 
   line 71: 0

  LocalVariableTable: 
   Start  Length  Slot  Name   Signature
   0      21      0    this       Lscala/actors/ReplyReactor$$anonfun$1;
   6      15      1    v1       Ljava/lang/Object;
   6      15      2    v2       Ljava/lang/Object;


public final boolean apply(java.lang.Object, scala.actors.OutputChannel);
  Code:
   Stack=7, Locals=4, Args_size=3
   0:	aload_0
   1:	getfield	#24; //Field $outer:Lscala/actors/ReplyReactor;
   4:	astore_3
   5:	aload_0
   6:	getfield	#24; //Field $outer:Lscala/actors/ReplyReactor;
   9:	getstatic	#60; //Field scala/collection/immutable/List$.MODULE$:Lscala/collection/immutable/List$;
   12:	getstatic	#65; //Field scala/Predef$.MODULE$:Lscala/Predef$;
   15:	iconst_1
   16:	anewarray	#42; //class scala/actors/OutputChannel
   19:	dup
   20:	iconst_0
   21:	aload_2
   22:	aastore
   23:	checkcast	#67; //class "[Ljava/lang/Object;"
   26:	invokevirtual	#71; //Method scala/Predef$.wrapRefArray:([Ljava/lang/Object;)Lscala/collection/mutable/WrappedArray;
   29:	invokevirtual	#74; //Method scala/collection/immutable/List$.apply:(Lscala/collection/Seq;)Lscala/collection/immutable/List;
   32:	invokeinterface	#80,  2; //InterfaceMethod scala/actors/ReplyReactor.senders_$eq:(Lscala/collection/immutable/List;)V
   37:	aload_0
   38:	getfield	#26; //Field handlesMessage$1:Lscala/Function1;
   41:	aload_1
   42:	invokeinterface	#85,  2; //InterfaceMethod scala/Function1.apply:(Ljava/lang/Object;)Ljava/lang/Object;
   47:	invokestatic	#89; //Method scala/runtime/BoxesRunTime.unboxToBoolean:(Ljava/lang/Object;)Z
   50:	ireturn
  LineNumberTable: 
   line 72: 0
   line 73: 37

  LocalVariableTable: 
   Start  Length  Slot  Name   Signature
   0      51      0    this       Lscala/actors/ReplyReactor$$anonfun$1;
   5      46      1    msg       Ljava/lang/Object;
   5      46      2    replyTo       Lscala/actors/OutputChannel;

  Signature: length = 0x2
   00 5D 

public scala.Function1 curry();
  Code:
   Stack=1, Locals=1, Args_size=1
   0:	aload_0
   1:	invokestatic	#99; //Method scala/Function2$class.curry:(Lscala/Function2;)Lscala/Function1;
   4:	areturn
  LineNumberTable: 
   line 71: 0


public java.lang.String toString();
  Code:
   Stack=1, Locals=1, Args_size=1
   0:	aload_0
   1:	invokestatic	#104; //Method scala/Function2$class.toString:(Lscala/Function2;)Ljava/lang/String;
   4:	areturn
  LineNumberTable: 
   line 71: 0


}

