Compiled from "ReplyableActor.scala"
public final class scala.actors.ReplyableActor$$anon$1 extends java.lang.Object implements scala.actors.AbstractActor
  SourceFile: "ReplyableActor.scala"
  Scala: length = 0x
   
  InnerClass: 
   public final $anon$1=class scala/actors/ReplyableActor$$anon$1 of class scala/actors/ReplyableActor
  minor version: 0
  major version: 49
  Constant pool:
Asciz	SourceFile;
Asciz	ReplyableActor.scala;
Asciz	exiting;
Asciz	Z;
Asciz	ftch$2;
Asciz	Lscala/actors/Channel;;
Asciz	$outer;
Asciz	Lscala/actors/AbstractActor;;
Asciz	<init>;
Asciz	(Lscala/actors/AbstractActor;Lscala/actors/Channel;)V;
Asciz	Code;
Asciz	LineNumberTable;
Asciz	java/lang/NullPointerException;
class	java/lang/NullPointerException
Asciz	()V;
NameAndType	"<init>":()V
Method	java/lang/NullPointerException."<init>":()V
Asciz	scala/actors/ReplyableActor$$anon$1;
class	scala/actors/ReplyableActor$$anon$1
NameAndType	$outer:Lscala/actors/AbstractActor;
Field	scala/actors/ReplyableActor$$anon$1.$outer:Lscala/actors/AbstractActor;
NameAndType	ftch$2:Lscala/actors/Channel;
Field	scala/actors/ReplyableActor$$anon$1.ftch$2:Lscala/actors/Channel;
Asciz	java/lang/Object;
class	java/lang/Object
Method	java/lang/Object."<init>":()V
Asciz	scala/actors/Replyable$class;
class	scala/actors/Replyable$class
Asciz	$init$;
Asciz	(Lscala/actors/Replyable;)V;
NameAndType	$init$:(Lscala/actors/Replyable;)V
Method	scala/actors/Replyable$class.$init$:(Lscala/actors/Replyable;)V
Asciz	scala/actors/AbstractActor$class;
class	scala/actors/AbstractActor$class
Asciz	(Lscala/actors/AbstractActor;)V;
NameAndType	$init$:(Lscala/actors/AbstractActor;)V
Method	scala/actors/AbstractActor$class.$init$:(Lscala/actors/AbstractActor;)V
Asciz	this;
Asciz	Lscala/actors/ReplyableActor$$anon$1;;
Asciz	LocalVariableTable;
Asciz	$bang$bang;
Asciz	(Ljava/lang/Object;)Lscala/Function0;;
Asciz	(Ljava/lang/Object;)Lscala/actors/Future;;
NameAndType	$bang$bang:(Ljava/lang/Object;)Lscala/actors/Future;
Method	scala/actors/ReplyableActor$$anon$1.$bang$bang:(Ljava/lang/Object;)Lscala/actors/Future;
Asciz	msg;
Asciz	Ljava/lang/Object;;
Asciz	(Ljava/lang/Object;Lscala/PartialFunction;)Lscala/Function0;;
Asciz	(Ljava/lang/Object;Lscala/PartialFunction;)Lscala/actors/Future;;
NameAndType	$bang$bang:(Ljava/lang/Object;Lscala/PartialFunction;)Lscala/actors/Future;
Method	scala/actors/ReplyableActor$$anon$1.$bang$bang:(Ljava/lang/Object;Lscala/PartialFunction;)Lscala/actors/Future;
Asciz	f;
Asciz	Lscala/PartialFunction;;
Asciz	scala/actors/Channel;
class	scala/actors/Channel
Asciz	scala/actors/Actor$;
class	scala/actors/Actor$
Asciz	MODULE$;
Asciz	Lscala/actors/Actor$;;
NameAndType	MODULE$:Lscala/actors/Actor$;
Field	scala/actors/Actor$.MODULE$:Lscala/actors/Actor$;
Asciz	scala/actors/Reactor;
class	scala/actors/Reactor
Asciz	scheduler;
Asciz	()Lscala/actors/IScheduler;;
NameAndType	scheduler:()Lscala/actors/IScheduler;
InterfaceMethod	scala/actors/Reactor.scheduler:()Lscala/actors/IScheduler;
Asciz	self;
Asciz	(Lscala/actors/IScheduler;)Lscala/actors/Actor;;
NameAndType	self:(Lscala/actors/IScheduler;)Lscala/actors/Actor;
Method	scala/actors/Actor$.self:(Lscala/actors/IScheduler;)Lscala/actors/Actor;
Asciz	(Lscala/actors/Actor;)V;
NameAndType	"<init>":(Lscala/actors/Actor;)V
Method	scala/actors/Channel."<init>":(Lscala/actors/Actor;)V
Asciz	scala/actors/Futures$;
class	scala/actors/Futures$
Asciz	Lscala/actors/Futures$;;
NameAndType	MODULE$:Lscala/actors/Futures$;
Field	scala/actors/Futures$.MODULE$:Lscala/actors/Futures$;
Asciz	fromInputChannel;
Asciz	(Lscala/actors/InputChannel;)Lscala/actors/Future;;
NameAndType	fromInputChannel:(Lscala/actors/InputChannel;)Lscala/actors/Future;
Method	scala/actors/Futures$.fromInputChannel:(Lscala/actors/InputChannel;)Lscala/actors/Future;
Asciz	someChan;
Asciz	<A:Ljava/lang/Object;>(Ljava/lang/Object;Lscala/PartialFunction<Ljava/lang/Object;TA;>;)Lscala/actors/Future<TA;>;;
Asciz	Signature;
Asciz	(Ljava/lang/Object;)Lscala/actors/Future<Ljava/lang/Object;>;;
Asciz	$bang$qmark;
Asciz	(JLjava/lang/Object;)Lscala/Option;;
Asciz	scala/Some;
class	scala/Some
Asciz	(Ljava/lang/Object;)V;
NameAndType	"<init>":(Ljava/lang/Object;)V
Method	scala/Some."<init>":(Ljava/lang/Object;)V
Asciz	msec;
Asciz	J;
Asciz	(JLjava/lang/Object;)Lscala/Option<Ljava/lang/Object;>;;
Asciz	(Ljava/lang/Object;)Ljava/lang/Object;;
Asciz	exit;
Asciz	(Lscala/actors/AbstractActor;Ljava/lang/Object;)V;
Asciz	scala/actors/Exit;
class	scala/actors/Exit
NameAndType	"<init>":(Lscala/actors/AbstractActor;Ljava/lang/Object;)V
Method	scala/actors/Exit."<init>":(Lscala/actors/AbstractActor;Ljava/lang/Object;)V
Asciz	send;
Asciz	(Ljava/lang/Object;Lscala/actors/OutputChannel;)V;
NameAndType	send:(Ljava/lang/Object;Lscala/actors/OutputChannel;)V
Method	scala/actors/Channel.send:(Ljava/lang/Object;Lscala/actors/OutputChannel;)V
Asciz	from;
Asciz	reason;
Asciz	unlinkFrom;
Asciz	linkTo;
Asciz	to;
Asciz	receiver;
Asciz	()Lscala/actors/Actor;;
NameAndType	receiver:()Lscala/actors/Actor;
Method	scala/actors/Channel.receiver:()Lscala/actors/Actor;
Asciz	forward;
NameAndType	forward:(Ljava/lang/Object;)V
Method	scala/actors/Channel.forward:(Ljava/lang/Object;)V
Asciz	replyTo;
Asciz	Lscala/actors/OutputChannel;;
Asciz	(Ljava/lang/Object;Lscala/actors/OutputChannel<Ljava/lang/Object;>;)V;
Asciz	$bang;
NameAndType	$bang:(Ljava/lang/Object;)V
Method	scala/actors/Channel.$bang:(Ljava/lang/Object;)V
Asciz	exiting_$eq;
Asciz	(Z)V;
NameAndType	exiting:Z
Field	scala/actors/ReplyableActor$$anon$1.exiting:Z
Asciz	()Z;
Asciz	Scala;
Asciz	InnerClasses;
Asciz	scala/actors/ReplyableActor;
class	scala/actors/ReplyableActor
Asciz	$anon$1;
Asciz	scala/actors/AbstractActor;
class	scala/actors/AbstractActor

{
private boolean exiting;
  Signature: Z

private final scala.actors.Channel ftch$2;
  Signature: Lscala/actors/Channel;

public final scala.actors.AbstractActor $outer;
  Signature: Lscala/actors/AbstractActor;

public scala.actors.ReplyableActor$$anon$1(scala.actors.AbstractActor, scala.actors.Channel);
  Signature: (Lscala/actors/AbstractActor;Lscala/actors/Channel;)V
  Code:
   Stack=2, Locals=3, Args_size=3
	aload_1
	ifnonnull	l1 // aload_0
	new	class java/lang/NullPointerException
	dup
	invokespecial	Method java/lang/NullPointerException."<init>":()V
	athrow
l1	aload_0
	aload_1
	putfield	Field $outer:Lscala/actors/AbstractActor;
	aload_0
	aload_2
	putfield	Field ftch$2:Lscala/actors/Channel;
	aload_0
	invokespecial	Method java/lang/Object."<init>":()V
	aload_0
	invokestatic	Method scala/actors/Replyable$class.$init$:(Lscala/actors/Replyable;)V
	aload_0
	invokestatic	Method scala/actors/AbstractActor$class.$init$:(Lscala/actors/AbstractActor;)V
	return
  Labels:
   	l1 = 12 // aload_0
  LocalVariableTable: 
   Start  Length  Slot  Name   Signature
   0      35      0    this       Lscala/actors/ReplyableActor$$anon$1;
   0      35      1    $outer       Lscala/actors/AbstractActor;


public scala.Function0 $bang$bang(java.lang.Object);
  Signature: (Ljava/lang/Object;)Lscala/Function0;
  Code:
   Stack=2, Locals=2, Args_size=2
	aload_0
	aload_1
	invokevirtual	Method $bang$bang:(Ljava/lang/Object;)Lscala/actors/Future;
	areturn
  Labels:
  LocalVariableTable: 
   Start  Length  Slot  Name   Signature
   0      6      0    this       Lscala/actors/ReplyableActor$$anon$1;
   0      6      1    msg       Ljava/lang/Object;


public scala.Function0 $bang$bang(java.lang.Object, scala.PartialFunction);
  Signature: (Ljava/lang/Object;Lscala/PartialFunction;)Lscala/Function0;
  Code:
   Stack=3, Locals=3, Args_size=3
	aload_0
	aload_1
	aload_2
	invokevirtual	Method $bang$bang:(Ljava/lang/Object;Lscala/PartialFunction;)Lscala/actors/Future;
	areturn
  Labels:
  LocalVariableTable: 
   Start  Length  Slot  Name   Signature
   0      7      0    this       Lscala/actors/ReplyableActor$$anon$1;
   0      7      1    msg       Ljava/lang/Object;
   0      7      2    f       Lscala/PartialFunction;


public scala.actors.Future $bang$bang(java.lang.Object, scala.PartialFunction);
  Signature: (Ljava/lang/Object;Lscala/PartialFunction;)Lscala/actors/Future;
  Code:
   Stack=4, Locals=4, Args_size=3
	new	class scala/actors/Channel
	dup
	getstatic	Field scala/actors/Actor$.MODULE$:Lscala/actors/Actor$;
	aload_0
	getfield	Field $outer:Lscala/actors/AbstractActor;
	checkcast	class scala/actors/Reactor
	invokeinterface	InterfaceMethod scala/actors/Reactor.scheduler:()Lscala/actors/IScheduler;
	invokevirtual	Method scala/actors/Actor$.self:(Lscala/actors/IScheduler;)Lscala/actors/Actor;
	invokespecial	Method scala/actors/Channel."<init>":(Lscala/actors/Actor;)V
	astore_3
	getstatic	Field scala/actors/Futures$.MODULE$:Lscala/actors/Futures$;
	aload_3
	invokevirtual	Method scala/actors/Futures$.fromInputChannel:(Lscala/actors/InputChannel;)Lscala/actors/Future;
	areturn
  Labels:
  LocalVariableTable: 
   Start  Length  Slot  Name   Signature
   0      34      0    this       Lscala/actors/ReplyableActor$$anon$1;
   0      34      1    msg       Ljava/lang/Object;
   0      34      2    f       Lscala/PartialFunction;
   26      7      3    someChan       Lscala/actors/Channel;

  Signature: length = 0x2
   00 55 

public scala.actors.Future $bang$bang(java.lang.Object);
  Signature: (Ljava/lang/Object;)Lscala/actors/Future;
  Code:
   Stack=4, Locals=3, Args_size=2
	new	class scala/actors/Channel
	dup
	getstatic	Field scala/actors/Actor$.MODULE$:Lscala/actors/Actor$;
	aload_0
	getfield	Field $outer:Lscala/actors/AbstractActor;
	checkcast	class scala/actors/Reactor
	invokeinterface	InterfaceMethod scala/actors/Reactor.scheduler:()Lscala/actors/IScheduler;
	invokevirtual	Method scala/actors/Actor$.self:(Lscala/actors/IScheduler;)Lscala/actors/Actor;
	invokespecial	Method scala/actors/Channel."<init>":(Lscala/actors/Actor;)V
	astore_2
	getstatic	Field scala/actors/Futures$.MODULE$:Lscala/actors/Futures$;
	aload_2
	invokevirtual	Method scala/actors/Futures$.fromInputChannel:(Lscala/actors/InputChannel;)Lscala/actors/Future;
	areturn
  Labels:
  LocalVariableTable: 
   Start  Length  Slot  Name   Signature
   0      34      0    this       Lscala/actors/ReplyableActor$$anon$1;
   0      34      1    msg       Ljava/lang/Object;
   26      7      2    someChan       Lscala/actors/Channel;

  Signature: length = 0x2
   00 57 

public scala.Option $bang$qmark(long, java.lang.Object);
  Signature: (JLjava/lang/Object;)Lscala/Option;
  Code:
   Stack=3, Locals=4, Args_size=3
	new	class scala/Some
	dup
	aload_3
	invokespecial	Method scala/Some."<init>":(Ljava/lang/Object;)V
	areturn
  Labels:
  LocalVariableTable: 
   Start  Length  Slot  Name   Signature
   0      9      0    this       Lscala/actors/ReplyableActor$$anon$1;
   0      9      1    msec       J
   0      9      3    msg       Ljava/lang/Object;

  Signature: length = 0x2
   00 61 

public java.lang.Object $bang$qmark(java.lang.Object);
  Signature: (Ljava/lang/Object;)Ljava/lang/Object;
  Code:
   Stack=1, Locals=2, Args_size=2
	aload_1
	areturn
  Labels:
  LocalVariableTable: 
   Start  Length  Slot  Name   Signature
   0      2      0    this       Lscala/actors/ReplyableActor$$anon$1;
   0      2      1    msg       Ljava/lang/Object;


public void exit(scala.actors.AbstractActor, java.lang.Object);
  Signature: (Lscala/actors/AbstractActor;Ljava/lang/Object;)V
  Code:
   Stack=5, Locals=3, Args_size=3
	aload_0
	getfield	Field ftch$2:Lscala/actors/Channel;
	new	class scala/actors/Exit
	dup
	aload_1
	aload_2
	invokespecial	Method scala/actors/Exit."<init>":(Lscala/actors/AbstractActor;Ljava/lang/Object;)V
	aload_0
	getfield	Field $outer:Lscala/actors/AbstractActor;
	invokevirtual	Method scala/actors/Channel.send:(Ljava/lang/Object;Lscala/actors/OutputChannel;)V
	return
  Labels:
  LocalVariableTable: 
   Start  Length  Slot  Name   Signature
   0      21      0    this       Lscala/actors/ReplyableActor$$anon$1;
   0      21      1    from       Lscala/actors/AbstractActor;
   0      21      2    reason       Ljava/lang/Object;


public void unlinkFrom(scala.actors.AbstractActor);
  Signature: (Lscala/actors/AbstractActor;)V
  Code:
   Stack=0, Locals=2, Args_size=2
	return
  Labels:
  LocalVariableTable: 
   Start  Length  Slot  Name   Signature
   0      1      0    this       Lscala/actors/ReplyableActor$$anon$1;
   0      1      1    from       Lscala/actors/AbstractActor;


public void linkTo(scala.actors.AbstractActor);
  Signature: (Lscala/actors/AbstractActor;)V
  Code:
   Stack=0, Locals=2, Args_size=2
	return
  Labels:
  LocalVariableTable: 
   Start  Length  Slot  Name   Signature
   0      1      0    this       Lscala/actors/ReplyableActor$$anon$1;
   0      1      1    to       Lscala/actors/AbstractActor;


public scala.actors.Actor receiver();
  Signature: ()Lscala/actors/Actor;
  Code:
   Stack=1, Locals=1, Args_size=1
	aload_0
	getfield	Field ftch$2:Lscala/actors/Channel;
	invokevirtual	Method scala/actors/Channel.receiver:()Lscala/actors/Actor;
	areturn
  Labels:

public void forward(java.lang.Object);
  Signature: (Ljava/lang/Object;)V
  Code:
   Stack=2, Locals=2, Args_size=2
	aload_0
	getfield	Field ftch$2:Lscala/actors/Channel;
	aload_1
	invokevirtual	Method scala/actors/Channel.forward:(Ljava/lang/Object;)V
	return
  Labels:
  LocalVariableTable: 
   Start  Length  Slot  Name   Signature
   0      9      0    this       Lscala/actors/ReplyableActor$$anon$1;
   0      9      1    msg       Ljava/lang/Object;


public void send(java.lang.Object, scala.actors.OutputChannel);
  Signature: (Ljava/lang/Object;Lscala/actors/OutputChannel;)V
  Code:
   Stack=3, Locals=3, Args_size=3
	aload_0
	getfield	Field ftch$2:Lscala/actors/Channel;
	aload_1
	aload_2
	invokevirtual	Method scala/actors/Channel.send:(Ljava/lang/Object;Lscala/actors/OutputChannel;)V
	return
  Labels:
  LocalVariableTable: 
   Start  Length  Slot  Name   Signature
   0      10      0    this       Lscala/actors/ReplyableActor$$anon$1;
   0      10      1    msg       Ljava/lang/Object;
   0      10      2    replyTo       Lscala/actors/OutputChannel;

  Signature: length = 0x2
   00 7B 

public void $bang(java.lang.Object);
  Signature: (Ljava/lang/Object;)V
  Code:
   Stack=2, Locals=2, Args_size=2
	aload_0
	getfield	Field ftch$2:Lscala/actors/Channel;
	aload_1
	invokevirtual	Method scala/actors/Channel.$bang:(Ljava/lang/Object;)V
	return
  Labels:
  LocalVariableTable: 
   Start  Length  Slot  Name   Signature
   0      9      0    this       Lscala/actors/ReplyableActor$$anon$1;
   0      9      1    msg       Ljava/lang/Object;


public void exiting_$eq(boolean);
  Signature: (Z)V
  Code:
   Stack=2, Locals=2, Args_size=2
	aload_0
	iload_1
	putfield	Field exiting:Z
	return
  Labels:

public boolean exiting();
  Signature: ()Z
  Code:
   Stack=1, Locals=1, Args_size=1
	aload_0
	getfield	Field exiting:Z
	ireturn
  Labels:

}

