Compiled from "ReplyableReactor.scala"
public final class scala.actors.ReplyableReactor$$anon$3 extends java.lang.Object implements scala.actors.OutputChannel
  SourceFile: "ReplyableReactor.scala"
  Signature: length = 0x2
   00 43 
  Scala: length = 0x
   
  InnerClass: 
   public final #72= #16 of #71; //$anon$3=class scala/actors/ReplyableReactor$$anon$3 of class scala/actors/ReplyableReactor
  minor version: 0
  major version: 49
  Constant pool:
const #1 = Asciz	SourceFile;
const #2 = Asciz	ReplyableReactor.scala;
const #3 = Asciz	res$2;
const #4 = Asciz	Lscala/concurrent/SyncVar;;
const #5 = Asciz	ftch$1;
const #6 = Asciz	Lscala/actors/Channel;;
const #7 = Asciz	myself$2;
const #8 = Asciz	Lscala/actors/Reactor;;
const #9 = Asciz	f$1;
const #10 = Asciz	Lscala/PartialFunction;;
const #11 = Asciz	<init>;
const #12 = Asciz	(Lscala/actors/ReplyableReactor;Lscala/PartialFunction;Lscala/actors/Reactor;Lscala/actors/Channel;Lscala/concurrent/SyncVar;)V;
const #13 = Asciz	Code;
const #14 = Asciz	LineNumberTable;
const #15 = Asciz	scala/actors/ReplyableReactor$$anon$3;
const #16 = class	#15;	//  scala/actors/ReplyableReactor$$anon$3
const #17 = NameAndType	#9:#10;//  f$1:Lscala/PartialFunction;
const #18 = Field	#16.#17;	//  scala/actors/ReplyableReactor$$anon$3.f$1:Lscala/PartialFunction;
const #19 = NameAndType	#7:#8;//  myself$2:Lscala/actors/Reactor;
const #20 = Field	#16.#19;	//  scala/actors/ReplyableReactor$$anon$3.myself$2:Lscala/actors/Reactor;
const #21 = NameAndType	#5:#6;//  ftch$1:Lscala/actors/Channel;
const #22 = Field	#16.#21;	//  scala/actors/ReplyableReactor$$anon$3.ftch$1:Lscala/actors/Channel;
const #23 = NameAndType	#3:#4;//  res$2:Lscala/concurrent/SyncVar;
const #24 = Field	#16.#23;	//  scala/actors/ReplyableReactor$$anon$3.res$2:Lscala/concurrent/SyncVar;
const #25 = Asciz	java/lang/Object;
const #26 = class	#25;	//  java/lang/Object
const #27 = Asciz	()V;
const #28 = NameAndType	#11:#27;//  "<init>":()V
const #29 = Method	#26.#28;	//  java/lang/Object."<init>":()V
const #30 = Asciz	this;
const #31 = Asciz	Lscala/actors/ReplyableReactor$$anon$3;;
const #32 = Asciz	$outer;
const #33 = Asciz	Lscala/actors/ReplyableReactor;;
const #34 = Asciz	LocalVariableTable;
const #35 = Asciz	receiver;
const #36 = Asciz	()Lscala/actors/Reactor;;
const #37 = Asciz	forward;
const #38 = Asciz	(Ljava/lang/Object;)V;
const #39 = Asciz	scala/Function1;
const #40 = class	#39;	//  scala/Function1
const #41 = Asciz	apply;
const #42 = Asciz	(Ljava/lang/Object;)Ljava/lang/Object;;
const #43 = NameAndType	#41:#42;//  apply:(Ljava/lang/Object;)Ljava/lang/Object;
const #44 = InterfaceMethod	#40.#43;	//  scala/Function1.apply:(Ljava/lang/Object;)Ljava/lang/Object;
const #45 = Asciz	scala/actors/Channel;
const #46 = class	#45;	//  scala/actors/Channel
const #47 = NameAndType	#37:#38;//  forward:(Ljava/lang/Object;)V
const #48 = Method	#46.#47;	//  scala/actors/Channel.forward:(Ljava/lang/Object;)V
const #49 = Asciz	scala/concurrent/SyncVar;
const #50 = class	#49;	//  scala/concurrent/SyncVar
const #51 = Asciz	set;
const #52 = NameAndType	#51:#38;//  set:(Ljava/lang/Object;)V
const #53 = Method	#50.#52;	//  scala/concurrent/SyncVar.set:(Ljava/lang/Object;)V
const #54 = Asciz	msg;
const #55 = Asciz	Ljava/lang/Object;;
const #56 = Asciz	send;
const #57 = Asciz	(Ljava/lang/Object;Lscala/actors/OutputChannel;)V;
const #58 = NameAndType	#56:#57;//  send:(Ljava/lang/Object;Lscala/actors/OutputChannel;)V
const #59 = Method	#46.#58;	//  scala/actors/Channel.send:(Ljava/lang/Object;Lscala/actors/OutputChannel;)V
const #60 = Asciz	replyTo;
const #61 = Asciz	Lscala/actors/OutputChannel;;
const #62 = Asciz	(Ljava/lang/Object;Lscala/actors/OutputChannel<Ljava/lang/Object;>;)V;
const #63 = Asciz	Signature;
const #64 = Asciz	$bang;
const #65 = NameAndType	#64:#38;//  $bang:(Ljava/lang/Object;)V
const #66 = Method	#46.#65;	//  scala/actors/Channel.$bang:(Ljava/lang/Object;)V
const #67 = Asciz	Ljava/lang/Object;Lscala/actors/OutputChannel<Ljava/lang/Object;>;;
const #68 = Asciz	Scala;
const #69 = Asciz	InnerClasses;
const #70 = Asciz	scala/actors/ReplyableReactor;
const #71 = class	#70;	//  scala/actors/ReplyableReactor
const #72 = Asciz	$anon$3;
const #73 = Asciz	scala/actors/OutputChannel;
const #74 = class	#73;	//  scala/actors/OutputChannel

{
public scala.actors.ReplyableReactor$$anon$3(scala.actors.ReplyableReactor, scala.PartialFunction, scala.actors.Reactor, scala.actors.Channel, scala.concurrent.SyncVar);
  Code:
   Stack=2, Locals=6, Args_size=6
   0:	aload_0
   1:	aload_2
   2:	putfield	#18; //Field f$1:Lscala/PartialFunction;
   5:	aload_0
   6:	aload_3
   7:	putfield	#20; //Field myself$2:Lscala/actors/Reactor;
   10:	aload_0
   11:	aload	4
   13:	putfield	#22; //Field ftch$1:Lscala/actors/Channel;
   16:	aload_0
   17:	aload	5
   19:	putfield	#24; //Field res$2:Lscala/concurrent/SyncVar;
   22:	aload_0
   23:	invokespecial	#29; //Method java/lang/Object."<init>":()V
   26:	return
  LineNumberTable: 
   line 78: 0

  LocalVariableTable: 
   Start  Length  Slot  Name   Signature
   0      27      0    this       Lscala/actors/ReplyableReactor$$anon$3;
   0      27      1    $outer       Lscala/actors/ReplyableReactor;


public scala.actors.Reactor receiver();
  Code:
   Stack=1, Locals=1, Args_size=1
   0:	aload_0
   1:	getfield	#20; //Field myself$2:Lscala/actors/Reactor;
   4:	areturn
  LineNumberTable: 
   line 92: 0


public void forward(java.lang.Object);
  Code:
   Stack=3, Locals=2, Args_size=2
   0:	aload_0
   1:	getfield	#22; //Field ftch$1:Lscala/actors/Channel;
   4:	aload_0
   5:	getfield	#18; //Field f$1:Lscala/PartialFunction;
   8:	aload_1
   9:	invokeinterface	#44,  2; //InterfaceMethod scala/Function1.apply:(Ljava/lang/Object;)Ljava/lang/Object;
   14:	invokevirtual	#48; //Method scala/actors/Channel.forward:(Ljava/lang/Object;)V
   17:	aload_0
   18:	getfield	#24; //Field res$2:Lscala/concurrent/SyncVar;
   21:	aload_0
   22:	getfield	#18; //Field f$1:Lscala/PartialFunction;
   25:	aload_1
   26:	invokeinterface	#44,  2; //InterfaceMethod scala/Function1.apply:(Ljava/lang/Object;)Ljava/lang/Object;
   31:	invokevirtual	#53; //Method scala/concurrent/SyncVar.set:(Ljava/lang/Object;)V
   34:	return
  LineNumberTable: 
   line 88: 0
   line 89: 17

  LocalVariableTable: 
   Start  Length  Slot  Name   Signature
   0      35      0    this       Lscala/actors/ReplyableReactor$$anon$3;
   0      35      1    msg       Ljava/lang/Object;


public void send(java.lang.Object, scala.actors.OutputChannel);
  Code:
   Stack=3, Locals=3, Args_size=3
   0:	aload_0
   1:	getfield	#22; //Field ftch$1:Lscala/actors/Channel;
   4:	aload_0
   5:	getfield	#18; //Field f$1:Lscala/PartialFunction;
   8:	aload_1
   9:	invokeinterface	#44,  2; //InterfaceMethod scala/Function1.apply:(Ljava/lang/Object;)Ljava/lang/Object;
   14:	aload_2
   15:	invokevirtual	#59; //Method scala/actors/Channel.send:(Ljava/lang/Object;Lscala/actors/OutputChannel;)V
   18:	aload_0
   19:	getfield	#24; //Field res$2:Lscala/concurrent/SyncVar;
   22:	aload_0
   23:	getfield	#18; //Field f$1:Lscala/PartialFunction;
   26:	aload_1
   27:	invokeinterface	#44,  2; //InterfaceMethod scala/Function1.apply:(Ljava/lang/Object;)Ljava/lang/Object;
   32:	invokevirtual	#53; //Method scala/concurrent/SyncVar.set:(Ljava/lang/Object;)V
   35:	return
  LineNumberTable: 
   line 84: 0
   line 85: 18

  LocalVariableTable: 
   Start  Length  Slot  Name   Signature
   0      36      0    this       Lscala/actors/ReplyableReactor$$anon$3;
   0      36      1    msg       Ljava/lang/Object;
   0      36      2    replyTo       Lscala/actors/OutputChannel;

  Signature: length = 0x2
   00 3E 

public void $bang(java.lang.Object);
  Code:
   Stack=3, Locals=2, Args_size=2
   0:	aload_0
   1:	getfield	#22; //Field ftch$1:Lscala/actors/Channel;
   4:	aload_0
   5:	getfield	#18; //Field f$1:Lscala/PartialFunction;
   8:	aload_1
   9:	invokeinterface	#44,  2; //InterfaceMethod scala/Function1.apply:(Ljava/lang/Object;)Ljava/lang/Object;
   14:	invokevirtual	#66; //Method scala/actors/Channel.$bang:(Ljava/lang/Object;)V
   17:	aload_0
   18:	getfield	#24; //Field res$2:Lscala/concurrent/SyncVar;
   21:	aload_0
   22:	getfield	#18; //Field f$1:Lscala/PartialFunction;
   25:	aload_1
   26:	invokeinterface	#44,  2; //InterfaceMethod scala/Function1.apply:(Ljava/lang/Object;)Ljava/lang/Object;
   31:	invokevirtual	#53; //Method scala/concurrent/SyncVar.set:(Ljava/lang/Object;)V
   34:	return
  LineNumberTable: 
   line 80: 0
   line 81: 17

  LocalVariableTable: 
   Start  Length  Slot  Name   Signature
   0      35      0    this       Lscala/actors/ReplyableReactor$$anon$3;
   0      35      1    msg       Ljava/lang/Object;


}

