Compiled from "Replyable.scala"
public final class scala.actors.Replyable$$anonfun$$bang$bang$2 extends java.lang.Object implements scala.Function0,scala.ScalaObject,java.io.Serializable
  SourceFile: "Replyable.scala"
  Scala: length = 0x
   
  InnerClass: 
   public final $anonfun$$bang$bang$2=class scala/actors/Replyable$$anonfun$$bang$bang$2 of class scala/actors/Replyable
  minor version: 0
  major version: 49
  Constant pool:
Asciz	SourceFile;
Asciz	Replyable.scala;
Asciz	<clinit>;
Asciz	()V;
Asciz	Code;
Asciz	serialVersionUID;
Asciz	J;
Asciz	scala/actors/Replyable$$anonfun$$bang$bang$2;
class	scala/actors/Replyable$$anonfun$$bang$bang$2
NameAndType	serialVersionUID:J
Field	scala/actors/Replyable$$anonfun$$bang$bang$2.serialVersionUID:J
Asciz	f$1;
Asciz	Lscala/PartialFunction;;
Asciz	msg$1;
Asciz	Ljava/lang/Object;;
Asciz	$outer;
Asciz	Lscala/actors/Replyable;;
Asciz	<init>;
Asciz	(Lscala/actors/Replyable;Ljava/lang/Object;Lscala/PartialFunction;)V;
Asciz	LineNumberTable;
Asciz	java/lang/NullPointerException;
class	java/lang/NullPointerException
NameAndType	"<init>":()V
Method	java/lang/NullPointerException."<init>":()V
NameAndType	$outer:Lscala/actors/Replyable;
Field	scala/actors/Replyable$$anonfun$$bang$bang$2.$outer:Lscala/actors/Replyable;
NameAndType	msg$1:Ljava/lang/Object;
Field	scala/actors/Replyable$$anonfun$$bang$bang$2.msg$1:Ljava/lang/Object;
NameAndType	f$1:Lscala/PartialFunction;
Field	scala/actors/Replyable$$anonfun$$bang$bang$2.f$1:Lscala/PartialFunction;
Asciz	java/lang/Object;
class	java/lang/Object
Method	java/lang/Object."<init>":()V
Asciz	scala/Function0$class;
class	scala/Function0$class
Asciz	$init$;
Asciz	(Lscala/Function0;)V;
NameAndType	$init$:(Lscala/Function0;)V
Method	scala/Function0$class.$init$:(Lscala/Function0;)V
Asciz	this;
Asciz	Lscala/actors/Replyable$$anonfun$$bang$bang$2;;
Asciz	LocalVariableTable;
Asciz	(Lscala/actors/Replyable<TT;TR;>;)V;
Asciz	Signature;
Asciz	apply;
Asciz	()Ljava/lang/Object;;
Asciz	scala/actors/Replyable;
class	scala/actors/Replyable
Asciz	$bang$qmark;
Asciz	(Ljava/lang/Object;)Ljava/lang/Object;;
NameAndType	$bang$qmark:(Ljava/lang/Object;)Ljava/lang/Object;
InterfaceMethod	scala/actors/Replyable.$bang$qmark:(Ljava/lang/Object;)Ljava/lang/Object;
Asciz	scala/Function1;
class	scala/Function1
NameAndType	apply:(Ljava/lang/Object;)Ljava/lang/Object;
InterfaceMethod	scala/Function1.apply:(Ljava/lang/Object;)Ljava/lang/Object;
Asciz	()TP;;
Asciz	toString;
Asciz	()Ljava/lang/String;;
Asciz	(Lscala/Function0;)Ljava/lang/String;;
NameAndType	toString:(Lscala/Function0;)Ljava/lang/String;
Method	scala/Function0$class.toString:(Lscala/Function0;)Ljava/lang/String;
Asciz	Scala;
Asciz	InnerClasses;
Asciz	$anonfun$$bang$bang$2;
Asciz	scala/Function0;
class	scala/Function0
Asciz	scala/ScalaObject;
class	scala/ScalaObject
Asciz	java/io/Serializable;
class	java/io/Serializable

{
public static final long serialVersionUID;
  Signature: J

private final scala.PartialFunction f$1;
  Signature: Lscala/PartialFunction;

private final java.lang.Object msg$1;
  Signature: Ljava/lang/Object;

private final scala.actors.Replyable $outer;
  Signature: Lscala/actors/Replyable;

public static {};
  Signature: ()V
  Code:
   Stack=2, Locals=0, Args_size=0
	lconst_0
	putstatic	Field serialVersionUID:J
	return
  Labels:

public scala.actors.Replyable$$anonfun$$bang$bang$2(scala.actors.Replyable, java.lang.Object, scala.PartialFunction);
  Signature: (Lscala/actors/Replyable;Ljava/lang/Object;Lscala/PartialFunction;)V
  Code:
   Stack=2, Locals=4, Args_size=4
	aload_1
	ifnonnull	l1 // aload_0
	new	class java/lang/NullPointerException
	dup
	invokespecial	Method java/lang/NullPointerException."<init>":()V
	athrow
l1	aload_0
	aload_1
	putfield	Field $outer:Lscala/actors/Replyable;
	aload_0
	aload_2
	putfield	Field msg$1:Ljava/lang/Object;
	aload_0
	aload_3
	putfield	Field f$1:Lscala/PartialFunction;
	aload_0
	invokespecial	Method java/lang/Object."<init>":()V
	aload_0
	invokestatic	Method scala/Function0$class.$init$:(Lscala/Function0;)V
	return
  Labels:
   	l1 = 12 // aload_0
  LocalVariableTable: 
   Start  Length  Slot  Name   Signature
   0      36      0    this       Lscala/actors/Replyable$$anonfun$$bang$bang$2;
   0      36      1    $outer       Lscala/actors/Replyable;

  Signature: length = 0x2
   00 2B 

public final java.lang.Object apply();
  Signature: ()Ljava/lang/Object;
  Code:
   Stack=3, Locals=2, Args_size=1
	aload_0
	getfield	Field $outer:Lscala/actors/Replyable;
	astore_1
	aload_0
	getfield	Field f$1:Lscala/PartialFunction;
	aload_0
	getfield	Field $outer:Lscala/actors/Replyable;
	aload_0
	getfield	Field msg$1:Ljava/lang/Object;
	invokeinterface	InterfaceMethod scala/actors/Replyable.$bang$qmark:(Ljava/lang/Object;)Ljava/lang/Object;
	invokeinterface	InterfaceMethod scala/Function1.apply:(Ljava/lang/Object;)Ljava/lang/Object;
	areturn
  Labels:
  LocalVariableTable: 
   Start  Length  Slot  Name   Signature
   0      28      0    this       Lscala/actors/Replyable$$anonfun$$bang$bang$2;

  Signature: length = 0x2
   00 39 

public java.lang.String toString();
  Signature: ()Ljava/lang/String;
  Code:
   Stack=1, Locals=1, Args_size=1
	aload_0
	invokestatic	Method scala/Function0$class.toString:(Lscala/Function0;)Ljava/lang/String;
	areturn
  Labels:

}

