Compiled from "ReplyableActor.scala"
public abstract class scala.actors.ReplyableActor$class extends java.lang.Object
  SourceFile: "ReplyableActor.scala"
  Scala: length = 0x
   
  InnerClass: 
   public final $anon$3=class scala/actors/ReplyableActor$$anon$3 of class scala/actors/ReplyableActor
   public final $anon$2=class scala/actors/ReplyableActor$$anon$2 of class scala/actors/ReplyableActor
   public final $anon$1=class scala/actors/ReplyableActor$$anon$1 of class scala/actors/ReplyableActor
   public final $anonfun$$bang$qmark$1=class scala/actors/ReplyableActor$$anonfun$$bang$qmark$1 of class scala/actors/ReplyableActor
   public final $anonfun$$bang$qmark$2=class scala/actors/ReplyableActor$$anonfun$$bang$qmark$2 of class scala/actors/ReplyableActor
  minor version: 0
  major version: 49
  Constant pool:
Asciz	SourceFile;
Asciz	ReplyableActor.scala;
Asciz	$init$;
Asciz	(Lscala/actors/AbstractActor;)V;
Asciz	Code;
Asciz	LineNumberTable;
Asciz	$this;
Asciz	Lscala/actors/AbstractActor;;
Asciz	LocalVariableTable;
Asciz	$bang$bang;
Asciz	(Lscala/actors/AbstractActor;Ljava/lang/Object;)Lscala/actors/Future;;
Asciz	scala/actors/Channel;
class	scala/actors/Channel
Asciz	scala/actors/Actor$;
class	scala/actors/Actor$
Asciz	MODULE$;
Asciz	Lscala/actors/Actor$;;
NameAndType	MODULE$:Lscala/actors/Actor$;
Field	scala/actors/Actor$.MODULE$:Lscala/actors/Actor$;
Asciz	scala/actors/Reactor;
class	scala/actors/Reactor
Asciz	scheduler;
Asciz	()Lscala/actors/IScheduler;;
NameAndType	scheduler:()Lscala/actors/IScheduler;
InterfaceMethod	scala/actors/Reactor.scheduler:()Lscala/actors/IScheduler;
Asciz	self;
Asciz	(Lscala/actors/IScheduler;)Lscala/actors/Actor;;
NameAndType	self:(Lscala/actors/IScheduler;)Lscala/actors/Actor;
Method	scala/actors/Actor$.self:(Lscala/actors/IScheduler;)Lscala/actors/Actor;
Asciz	<init>;
Asciz	(Lscala/actors/Actor;)V;
NameAndType	"<init>":(Lscala/actors/Actor;)V
Method	scala/actors/Channel."<init>":(Lscala/actors/Actor;)V
Asciz	scala/actors/ReplyableActor$$anon$1;
class	scala/actors/ReplyableActor$$anon$1
Asciz	(Lscala/actors/AbstractActor;Lscala/actors/Channel;)V;
NameAndType	"<init>":(Lscala/actors/AbstractActor;Lscala/actors/Channel;)V
Method	scala/actors/ReplyableActor$$anon$1."<init>":(Lscala/actors/AbstractActor;Lscala/actors/Channel;)V
Asciz	scala/actors/AbstractActor;
class	scala/actors/AbstractActor
Asciz	linkTo;
NameAndType	linkTo:(Lscala/actors/AbstractActor;)V
InterfaceMethod	scala/actors/AbstractActor.linkTo:(Lscala/actors/AbstractActor;)V
Asciz	send;
Asciz	(Ljava/lang/Object;Lscala/actors/OutputChannel;)V;
NameAndType	send:(Ljava/lang/Object;Lscala/actors/OutputChannel;)V
InterfaceMethod	scala/actors/Reactor.send:(Ljava/lang/Object;Lscala/actors/OutputChannel;)V
Asciz	scala/actors/ReplyableActor$$anon$2;
class	scala/actors/ReplyableActor$$anon$2
Method	scala/actors/ReplyableActor$$anon$2."<init>":(Lscala/actors/AbstractActor;Lscala/actors/Channel;)V
Asciz	msg;
Asciz	Ljava/lang/Object;;
Asciz	ftch$2;
Asciz	Lscala/actors/Channel;;
Asciz	linkedChannel;
Asciz	(Lscala/actors/AbstractActor;Ljava/lang/Object;Lscala/PartialFunction;)Lscala/actors/Future;;
Asciz	scala/actors/ReplyableActor$$anon$3;
class	scala/actors/ReplyableActor$$anon$3
Asciz	(Lscala/actors/AbstractActor;Lscala/PartialFunction;Lscala/actors/Channel;)V;
NameAndType	"<init>":(Lscala/actors/AbstractActor;Lscala/PartialFunction;Lscala/actors/Channel;)V
Method	scala/actors/ReplyableActor$$anon$3."<init>":(Lscala/actors/AbstractActor;Lscala/PartialFunction;Lscala/actors/Channel;)V
Asciz	scala/actors/Futures$;
class	scala/actors/Futures$
Asciz	Lscala/actors/Futures$;;
NameAndType	MODULE$:Lscala/actors/Futures$;
Field	scala/actors/Futures$.MODULE$:Lscala/actors/Futures$;
Asciz	fromInputChannel;
Asciz	(Lscala/actors/InputChannel;)Lscala/actors/Future;;
NameAndType	fromInputChannel:(Lscala/actors/InputChannel;)Lscala/actors/Future;
Method	scala/actors/Futures$.fromInputChannel:(Lscala/actors/InputChannel;)Lscala/actors/Future;
Asciz	f$1;
Asciz	Lscala/PartialFunction;;
Asciz	ftch$1;
Asciz	$bang$qmark;
Asciz	(Lscala/actors/AbstractActor;JLjava/lang/Object;)Lscala/Option;;
Asciz	scala/actors/ReplyableActor$$anonfun$$bang$qmark$2;
class	scala/actors/ReplyableActor$$anonfun$$bang$qmark$2
NameAndType	"<init>":(Lscala/actors/AbstractActor;)V
Method	scala/actors/ReplyableActor$$anonfun$$bang$qmark$2."<init>":(Lscala/actors/AbstractActor;)V
Asciz	receiveWithin;
Asciz	(JLscala/PartialFunction;)Ljava/lang/Object;;
NameAndType	receiveWithin:(JLscala/PartialFunction;)Ljava/lang/Object;
Method	scala/actors/Channel.receiveWithin:(JLscala/PartialFunction;)Ljava/lang/Object;
Asciz	scala/Option;
class	scala/Option
Asciz	msec;
Asciz	J;
Asciz	replyCh;
Asciz	(Lscala/actors/AbstractActor;Ljava/lang/Object;)Ljava/lang/Object;;
Asciz	scala/actors/ReplyableActor$$anonfun$$bang$qmark$1;
class	scala/actors/ReplyableActor$$anonfun$$bang$qmark$1
Method	scala/actors/ReplyableActor$$anonfun$$bang$qmark$1."<init>":(Lscala/actors/AbstractActor;)V
Asciz	receive;
Asciz	(Lscala/PartialFunction;)Ljava/lang/Object;;
NameAndType	receive:(Lscala/PartialFunction;)Ljava/lang/Object;
Method	scala/actors/Channel.receive:(Lscala/PartialFunction;)Ljava/lang/Object;
Asciz	Scala;
Asciz	InnerClasses;
Asciz	scala/actors/ReplyableActor;
class	scala/actors/ReplyableActor
Asciz	$anon$3;
Asciz	$anon$2;
Asciz	$anon$1;
Asciz	$anonfun$$bang$qmark$1;
Asciz	$anonfun$$bang$qmark$2;
Asciz	scala/actors/ReplyableActor$class;
class	scala/actors/ReplyableActor$class
Asciz	java/lang/Object;
class	java/lang/Object

{
public static void $init$(scala.actors.AbstractActor);
  Signature: (Lscala/actors/AbstractActor;)V
  Code:
   Stack=0, Locals=1, Args_size=1
	return
  Labels:
  LocalVariableTable: 
   Start  Length  Slot  Name   Signature
   0      1      0    $this       Lscala/actors/AbstractActor;


public static scala.actors.Future $bang$bang(scala.actors.AbstractActor, java.lang.Object);
  Signature: (Lscala/actors/AbstractActor;Ljava/lang/Object;)Lscala/actors/Future;
  Code:
   Stack=4, Locals=4, Args_size=2
	new	class scala/actors/Channel
	dup
	getstatic	Field scala/actors/Actor$.MODULE$:Lscala/actors/Actor$;
	aload_0
	checkcast	class scala/actors/Reactor
	invokeinterface	InterfaceMethod scala/actors/Reactor.scheduler:()Lscala/actors/IScheduler;
	invokevirtual	Method scala/actors/Actor$.self:(Lscala/actors/IScheduler;)Lscala/actors/Actor;
	invokespecial	Method scala/actors/Channel."<init>":(Lscala/actors/Actor;)V
	astore_2
	new	class scala/actors/ReplyableActor$$anon$1
	dup
	aload_0
	aload_2
	invokespecial	Method scala/actors/ReplyableActor$$anon$1."<init>":(Lscala/actors/AbstractActor;Lscala/actors/Channel;)V
	astore_3
	aload_0
	aload_3
	invokeinterface	InterfaceMethod scala/actors/AbstractActor.linkTo:(Lscala/actors/AbstractActor;)V
	aload_0
	checkcast	class scala/actors/Reactor
	aload_1
	aload_3
	invokeinterface	InterfaceMethod scala/actors/Reactor.send:(Ljava/lang/Object;Lscala/actors/OutputChannel;)V
	new	class scala/actors/ReplyableActor$$anon$2
	dup
	aload_0
	aload_2
	invokespecial	Method scala/actors/ReplyableActor$$anon$2."<init>":(Lscala/actors/AbstractActor;Lscala/actors/Channel;)V
	areturn
  Labels:
  LocalVariableTable: 
   Start  Length  Slot  Name   Signature
   0      61      0    $this       Lscala/actors/AbstractActor;
   0      61      1    msg       Ljava/lang/Object;
   23      37      2    ftch$2       Lscala/actors/Channel;
   33      27      3    linkedChannel       Lscala/actors/AbstractActor;


public static scala.actors.Future $bang$bang(scala.actors.AbstractActor, java.lang.Object, scala.PartialFunction);
  Signature: (Lscala/actors/AbstractActor;Ljava/lang/Object;Lscala/PartialFunction;)Lscala/actors/Future;
  Code:
   Stack=7, Locals=4, Args_size=3
	new	class scala/actors/Channel
	dup
	getstatic	Field scala/actors/Actor$.MODULE$:Lscala/actors/Actor$;
	aload_0
	checkcast	class scala/actors/Reactor
	invokeinterface	InterfaceMethod scala/actors/Reactor.scheduler:()Lscala/actors/IScheduler;
	invokevirtual	Method scala/actors/Actor$.self:(Lscala/actors/IScheduler;)Lscala/actors/Actor;
	invokespecial	Method scala/actors/Channel."<init>":(Lscala/actors/Actor;)V
	astore_3
	aload_0
	checkcast	class scala/actors/Reactor
	aload_1
	new	class scala/actors/ReplyableActor$$anon$3
	dup
	aload_0
	aload_2
	aload_3
	invokespecial	Method scala/actors/ReplyableActor$$anon$3."<init>":(Lscala/actors/AbstractActor;Lscala/PartialFunction;Lscala/actors/Channel;)V
	invokeinterface	InterfaceMethod scala/actors/Reactor.send:(Ljava/lang/Object;Lscala/actors/OutputChannel;)V
	getstatic	Field scala/actors/Futures$.MODULE$:Lscala/actors/Futures$;
	aload_3
	invokevirtual	Method scala/actors/Futures$.fromInputChannel:(Lscala/actors/InputChannel;)Lscala/actors/Future;
	areturn
  Labels:
  LocalVariableTable: 
   Start  Length  Slot  Name   Signature
   0      51      0    $this       Lscala/actors/AbstractActor;
   0      51      1    msg       Ljava/lang/Object;
   0      51      2    f$1       Lscala/PartialFunction;
   23      27      3    ftch$1       Lscala/actors/Channel;


public static scala.Option $bang$qmark(scala.actors.AbstractActor, long, java.lang.Object);
  Signature: (Lscala/actors/AbstractActor;JLjava/lang/Object;)Lscala/Option;
  Code:
   Stack=6, Locals=5, Args_size=3
	new	class scala/actors/Channel
	dup
	getstatic	Field scala/actors/Actor$.MODULE$:Lscala/actors/Actor$;
	aload_0
	checkcast	class scala/actors/Reactor
	invokeinterface	InterfaceMethod scala/actors/Reactor.scheduler:()Lscala/actors/IScheduler;
	invokevirtual	Method scala/actors/Actor$.self:(Lscala/actors/IScheduler;)Lscala/actors/Actor;
	invokespecial	Method scala/actors/Channel."<init>":(Lscala/actors/Actor;)V
	astore	4
	aload_0
	checkcast	class scala/actors/Reactor
	aload_3
	aload	4
	invokeinterface	InterfaceMethod scala/actors/Reactor.send:(Ljava/lang/Object;Lscala/actors/OutputChannel;)V
	aload	4
	lload_1
	new	class scala/actors/ReplyableActor$$anonfun$$bang$qmark$2
	dup
	aload_0
	invokespecial	Method scala/actors/ReplyableActor$$anonfun$$bang$qmark$2."<init>":(Lscala/actors/AbstractActor;)V
	invokevirtual	Method scala/actors/Channel.receiveWithin:(JLscala/PartialFunction;)Ljava/lang/Object;
	checkcast	class scala/Option
	areturn
  Labels:
  LocalVariableTable: 
   Start  Length  Slot  Name   Signature
   0      54      0    $this       Lscala/actors/AbstractActor;
   0      54      1    msec       J
   0      54      3    msg       Ljava/lang/Object;
   24      29      4    replyCh       Lscala/actors/Channel;


public static java.lang.Object $bang$qmark(scala.actors.AbstractActor, java.lang.Object);
  Signature: (Lscala/actors/AbstractActor;Ljava/lang/Object;)Ljava/lang/Object;
  Code:
   Stack=4, Locals=3, Args_size=2
	new	class scala/actors/Channel
	dup
	getstatic	Field scala/actors/Actor$.MODULE$:Lscala/actors/Actor$;
	aload_0
	checkcast	class scala/actors/Reactor
	invokeinterface	InterfaceMethod scala/actors/Reactor.scheduler:()Lscala/actors/IScheduler;
	invokevirtual	Method scala/actors/Actor$.self:(Lscala/actors/IScheduler;)Lscala/actors/Actor;
	invokespecial	Method scala/actors/Channel."<init>":(Lscala/actors/Actor;)V
	astore_2
	aload_0
	checkcast	class scala/actors/Reactor
	aload_1
	aload_2
	invokeinterface	InterfaceMethod scala/actors/Reactor.send:(Ljava/lang/Object;Lscala/actors/OutputChannel;)V
	aload_2
	new	class scala/actors/ReplyableActor$$anonfun$$bang$qmark$1
	dup
	aload_0
	invokespecial	Method scala/actors/ReplyableActor$$anonfun$$bang$qmark$1."<init>":(Lscala/actors/AbstractActor;)V
	invokevirtual	Method scala/actors/Channel.receive:(Lscala/PartialFunction;)Ljava/lang/Object;
	areturn
  Labels:
  LocalVariableTable: 
   Start  Length  Slot  Name   Signature
   0      47      0    $this       Lscala/actors/AbstractActor;
   0      47      1    msg       Ljava/lang/Object;
   23      23      2    replyCh       Lscala/actors/Channel;


}

