Compiled from "ReplyReactorTask.scala"
public class scala.actors.ReplyReactorTask extends scala.actors.ReactorTask implements scala.ScalaObject
  SourceFile: "ReplyReactorTask.scala"
  Signature: length = 0x2
   00 3E 
  ScalaSig: length = 0x1A1
   05 00 3E 06 05 01 02 00 02 06 02 10 52 65 70 6C
   79 52 65 61 63 74 6F 72 54 61 73 6B 0A 02 03 04
   01 06 61 63 74 6F 72 73 0A 01 05 01 05 73 63 61
   6C 61 15 02 07 18 13 03 00 08 0F 10 03 09 0A 0C
   0D 01 02 09 02 0B 02 02 0B 52 65 61 63 74 6F 72
   54 61 73 6B 10 02 09 0D 09 02 0E 02 02 0C 52 65
   70 6C 79 52 65 61 63 74 6F 72 10 02 10 11 0D 01
   04 09 02 12 04 02 0B 53 63 61 6C 61 4F 62 6A 65
   63 74 08 08 14 00 FFFFFF82 FFFFFF80 FFFFFFA0 FFFFFF80 04 16 01 07 72 65
   61 63 74 6F 72 03 00 10 02 17 18 0C 00 04 08 19
   00 FFFFFF84 FFFFFF80 FFFFFF80 FFFFFFC2 00 1A 02 01 54 11 02 1B 0C 10 02
   10 1C 09 02 1D 04 02 04 4E 75 6C 6C 08 08 1F 00
   FFFFFF82 FFFFFF80 FFFFFFA0 FFFFFF80 04 20 01 03 66 75 6E 10 03 10 21 23
   09 02 22 04 02 09 46 75 6E 63 74 69 6F 6E 30 10
   02 10 24 09 02 25 04 02 04 55 6E 69 74 08 05 27
   00 FFFFFF84 00 28 01 06 3C 69 6E 69 74 3E 14 03 29 2A
   2B 10 03 09 00 16 08 05 14 26 FFFFFFC0 00 16 08 05 1F
   26 FFFFFFC0 00 20 08 07 2D 00 FFFFFFC0 FFFFFF80 FFFFFF84 00 2E 01 05 73
   61 76 65 64 15 01 2F 10 02 09 30 09 02 31 02 02
   07 52 65 61 63 74 6F 72 08 07 33 00 FFFFFFC0 FFFFFF80 FFFFFF84 00
   34 01 09 73 61 76 65 64 5F 24 65 71 14 02 23 35
   08 07 36 32 FFFFFF81 FFFFFF80 FFFFFFC0 00 2F 01 03 78 24 31 08 06
   38 00 FFFFFFA0 FFFFFFA0 04 2F 01 06 73 61 76 65 64 20 08 05
   3A 00 FFFFFF84 28 3B 01 0E 62 65 67 69 6E 45 78 65 63
   75 74 69 6F 6E 14 01 23 08 05 3D 00 FFFFFF84 28 3B 01
   10 73 75 73 70 65 6E 64 45 78 65 63 75 74 69 6F
   6E 
  minor version: 0
  major version: 49
  Constant pool:
Asciz	SourceFile;
Asciz	ReplyReactorTask.scala;
Asciz	saved;
Asciz	Lscala/actors/Reactor;;
Asciz	reactor;
Asciz	Lscala/actors/ReplyReactor;;
Asciz	TT;;
Asciz	Signature;
Asciz	()Lscala/actors/Reactor;;
Asciz	Code;
Asciz	LineNumberTable;
Asciz	scala/actors/ReplyReactorTask;
class	scala/actors/ReplyReactorTask
NameAndType	saved:Lscala/actors/Reactor;
Field	scala/actors/ReplyReactorTask.saved:Lscala/actors/Reactor;
Asciz	saved_$eq;
Asciz	(Lscala/actors/Reactor;)V;
Asciz	beginExecution;
Asciz	()V;
Asciz	scala/actors/Actor$;
class	scala/actors/Actor$
Asciz	MODULE$;
Asciz	Lscala/actors/Actor$;;
NameAndType	MODULE$:Lscala/actors/Actor$;
Field	scala/actors/Actor$.MODULE$:Lscala/actors/Actor$;
Asciz	tl;
Asciz	()Ljava/lang/ThreadLocal;;
NameAndType	tl:()Ljava/lang/ThreadLocal;
Method	scala/actors/Actor$.tl:()Ljava/lang/ThreadLocal;
Asciz	java/lang/ThreadLocal;
class	java/lang/ThreadLocal
Asciz	get;
Asciz	()Ljava/lang/Object;;
NameAndType	get:()Ljava/lang/Object;
Method	java/lang/ThreadLocal.get:()Ljava/lang/Object;
Asciz	scala/actors/Reactor;
class	scala/actors/Reactor
NameAndType	saved_$eq:(Lscala/actors/Reactor;)V
Method	scala/actors/ReplyReactorTask.saved_$eq:(Lscala/actors/Reactor;)V
NameAndType	reactor:Lscala/actors/ReplyReactor;
Field	scala/actors/ReplyReactorTask.reactor:Lscala/actors/ReplyReactor;
Asciz	set;
Asciz	(Ljava/lang/Object;)V;
NameAndType	set:(Ljava/lang/Object;)V
Method	java/lang/ThreadLocal.set:(Ljava/lang/Object;)V
Asciz	suspendExecution;
NameAndType	saved:()Lscala/actors/Reactor;
Method	scala/actors/ReplyReactorTask.saved:()Lscala/actors/Reactor;
Asciz	<init>;
Asciz	(Lscala/actors/ReplyReactor;Lscala/Function0;)V;
Asciz	scala/actors/ReactorTask;
class	scala/actors/ReactorTask
Asciz	(Lscala/actors/Reactor;Lscala/Function0;)V;
NameAndType	"<init>":(Lscala/actors/Reactor;Lscala/Function0;)V
Method	scala/actors/ReactorTask."<init>":(Lscala/actors/Reactor;Lscala/Function0;)V
Asciz	this;
Asciz	Lscala/actors/ReplyReactorTask;;
Asciz	fun;
Asciz	Lscala/Function0;;
Asciz	LocalVariableTable;
Asciz	(TT;Lscala/Function0<Ljava/lang/Object;>;)V;
Asciz	<T::Lscala/actors/ReplyReactor;>Lscala/actors/ReactorTask<Lscala/actors/ReplyReactor;>;Lscala/ScalaObject;;
Asciz	ScalaSig;
Asciz	scala/ScalaObject;
class	scala/ScalaObject

{
private scala.actors.Reactor saved;
  Signature: Lscala/actors/Reactor;

private final scala.actors.ReplyReactor reactor;
  Signature: Lscala/actors/ReplyReactor;
  Signature: length = 0x2
   00 07 

public scala.actors.Reactor saved();
  Signature: ()Lscala/actors/Reactor;
  Code:
   Stack=1, Locals=1, Args_size=1
	aload_0
	getfield	Field saved:Lscala/actors/Reactor;
	areturn
  Labels:

public void saved_$eq(scala.actors.Reactor);
  Signature: (Lscala/actors/Reactor;)V
  Code:
   Stack=2, Locals=2, Args_size=2
	aload_0
	aload_1
	putfield	Field saved:Lscala/actors/Reactor;
	return
  Labels:

public void beginExecution();
  Signature: ()V
  Code:
   Stack=2, Locals=1, Args_size=1
	aload_0
	getstatic	Field scala/actors/Actor$.MODULE$:Lscala/actors/Actor$;
	invokevirtual	Method scala/actors/Actor$.tl:()Ljava/lang/ThreadLocal;
	invokevirtual	Method java/lang/ThreadLocal.get:()Ljava/lang/Object;
	checkcast	class scala/actors/Reactor
	invokevirtual	Method saved_$eq:(Lscala/actors/Reactor;)V
	getstatic	Field scala/actors/Actor$.MODULE$:Lscala/actors/Actor$;
	invokevirtual	Method scala/actors/Actor$.tl:()Ljava/lang/ThreadLocal;
	aload_0
	getfield	Field reactor:Lscala/actors/ReplyReactor;
	invokevirtual	Method java/lang/ThreadLocal.set:(Ljava/lang/Object;)V
	return
  Labels:

public void suspendExecution();
  Signature: ()V
  Code:
   Stack=2, Locals=1, Args_size=1
	getstatic	Field scala/actors/Actor$.MODULE$:Lscala/actors/Actor$;
	invokevirtual	Method scala/actors/Actor$.tl:()Ljava/lang/ThreadLocal;
	aload_0
	invokevirtual	Method saved:()Lscala/actors/Reactor;
	invokevirtual	Method java/lang/ThreadLocal.set:(Ljava/lang/Object;)V
	return
  Labels:

public scala.actors.ReplyReactorTask(scala.actors.ReplyReactor, scala.Function0);
  Signature: (Lscala/actors/ReplyReactor;Lscala/Function0;)V
  Code:
   Stack=3, Locals=3, Args_size=3
	aload_0
	aload_1
	putfield	Field reactor:Lscala/actors/ReplyReactor;
	aload_0
	aload_1
	aload_2
	invokespecial	Method scala/actors/ReactorTask."<init>":(Lscala/actors/Reactor;Lscala/Function0;)V
	return
  Labels:
  LocalVariableTable: 
   Start  Length  Slot  Name   Signature
   0      12      0    this       Lscala/actors/ReplyReactorTask;
   0      12      1    reactor       Lscala/actors/ReplyReactor;
   0      12      2    fun       Lscala/Function0;

  Signature: length = 0x2
   00 3D 

}

