Compiled from "ReplyableReactor.scala"
public final class scala.actors.ReplyableReactor$$anon$2 extends java.lang.Object implements scala.actors.OutputChannel
  SourceFile: "ReplyableReactor.scala"
  Signature: length = 0x2
   00 2F 
  Scala: length = 0x
   
  InnerClass: 
   public final $anon$2=class scala/actors/ReplyableReactor$$anon$2 of class scala/actors/ReplyableReactor
  minor version: 0
  major version: 49
  Constant pool:
Asciz	SourceFile;
Asciz	ReplyableReactor.scala;
Asciz	res$1;
Asciz	Lscala/concurrent/SyncVar;;
Asciz	myself$1;
Asciz	Lscala/actors/Reactor;;
Asciz	<init>;
Asciz	(Lscala/actors/ReplyReactor;Lscala/actors/Reactor;Lscala/concurrent/SyncVar;)V;
Asciz	Code;
Asciz	LineNumberTable;
Asciz	scala/actors/ReplyableReactor$$anon$2;
class	scala/actors/ReplyableReactor$$anon$2
NameAndType	myself$1:Lscala/actors/Reactor;
Field	scala/actors/ReplyableReactor$$anon$2.myself$1:Lscala/actors/Reactor;
NameAndType	res$1:Lscala/concurrent/SyncVar;
Field	scala/actors/ReplyableReactor$$anon$2.res$1:Lscala/concurrent/SyncVar;
Asciz	java/lang/Object;
class	java/lang/Object
Asciz	()V;
NameAndType	"<init>":()V
Method	java/lang/Object."<init>":()V
Asciz	this;
Asciz	Lscala/actors/ReplyableReactor$$anon$2;;
Asciz	$outer;
Asciz	Lscala/actors/ReplyReactor;;
Asciz	LocalVariableTable;
Asciz	receiver;
Asciz	()Lscala/actors/Actor;;
Asciz	scala/actors/Actor;
class	scala/actors/Actor
Asciz	forward;
Asciz	(Ljava/lang/Object;)V;
Asciz	scala/concurrent/SyncVar;
class	scala/concurrent/SyncVar
Asciz	set;
NameAndType	set:(Ljava/lang/Object;)V
Method	scala/concurrent/SyncVar.set:(Ljava/lang/Object;)V
Asciz	msg;
Asciz	Ljava/lang/Object;;
Asciz	send;
Asciz	(Ljava/lang/Object;Lscala/actors/OutputChannel;)V;
Asciz	replyTo;
Asciz	Lscala/actors/OutputChannel;;
Asciz	(Ljava/lang/Object;Lscala/actors/OutputChannel<Ljava/lang/Object;>;)V;
Asciz	Signature;
Asciz	$bang;
Asciz	Ljava/lang/Object;Lscala/actors/OutputChannel<Ljava/lang/Object;>;;
Asciz	Scala;
Asciz	InnerClasses;
Asciz	scala/actors/ReplyableReactor;
class	scala/actors/ReplyableReactor
Asciz	$anon$2;
Asciz	scala/actors/OutputChannel;
class	scala/actors/OutputChannel

{
private final scala.concurrent.SyncVar res$1;
  Signature: Lscala/concurrent/SyncVar;

private final scala.actors.Reactor myself$1;
  Signature: Lscala/actors/Reactor;

public scala.actors.ReplyableReactor$$anon$2(scala.actors.ReplyReactor, scala.actors.Reactor, scala.concurrent.SyncVar);
  Signature: (Lscala/actors/ReplyReactor;Lscala/actors/Reactor;Lscala/concurrent/SyncVar;)V
  Code:
   Stack=2, Locals=4, Args_size=4
	aload_0
	aload_2
	putfield	Field myself$1:Lscala/actors/Reactor;
	aload_0
	aload_3
	putfield	Field res$1:Lscala/concurrent/SyncVar;
	aload_0
	invokespecial	Method java/lang/Object."<init>":()V
	return
  Labels:
  LocalVariableTable: 
   Start  Length  Slot  Name   Signature
   0      15      0    this       Lscala/actors/ReplyableReactor$$anon$2;
   0      15      1    $outer       Lscala/actors/ReplyReactor;


public scala.actors.Actor receiver();
  Signature: ()Lscala/actors/Actor;
  Code:
   Stack=1, Locals=1, Args_size=1
	aload_0
	getfield	Field myself$1:Lscala/actors/Reactor;
	checkcast	class scala/actors/Actor
	areturn
  Labels:

public void forward(java.lang.Object);
  Signature: (Ljava/lang/Object;)V
  Code:
   Stack=2, Locals=2, Args_size=2
	aload_0
	getfield	Field res$1:Lscala/concurrent/SyncVar;
	aload_1
	invokevirtual	Method scala/concurrent/SyncVar.set:(Ljava/lang/Object;)V
	return
  Labels:
  LocalVariableTable: 
   Start  Length  Slot  Name   Signature
   0      9      0    this       Lscala/actors/ReplyableReactor$$anon$2;
   0      9      1    msg       Ljava/lang/Object;


public void send(java.lang.Object, scala.actors.OutputChannel);
  Signature: (Ljava/lang/Object;Lscala/actors/OutputChannel;)V
  Code:
   Stack=2, Locals=3, Args_size=3
	aload_0
	getfield	Field res$1:Lscala/concurrent/SyncVar;
	aload_1
	invokevirtual	Method scala/concurrent/SyncVar.set:(Ljava/lang/Object;)V
	return
  Labels:
  LocalVariableTable: 
   Start  Length  Slot  Name   Signature
   0      9      0    this       Lscala/actors/ReplyableReactor$$anon$2;
   0      9      1    msg       Ljava/lang/Object;
   0      9      2    replyTo       Lscala/actors/OutputChannel;

  Signature: length = 0x2
   00 2C 

public void $bang(java.lang.Object);
  Signature: (Ljava/lang/Object;)V
  Code:
   Stack=2, Locals=2, Args_size=2
	aload_0
	getfield	Field res$1:Lscala/concurrent/SyncVar;
	aload_1
	invokevirtual	Method scala/concurrent/SyncVar.set:(Ljava/lang/Object;)V
	return
  Labels:
  LocalVariableTable: 
   Start  Length  Slot  Name   Signature
   0      9      0    this       Lscala/actors/ReplyableReactor$$anon$2;
   0      9      1    msg       Ljava/lang/Object;


}

