Compiled from "ReplyableActor.scala"
public final class scala.actors.ReplyableActor$$anon$2$$anonfun$respond$1 extends java.lang.Object implements scala.Function1,scala.ScalaObject,java.io.Serializable
  SourceFile: "ReplyableActor.scala"
  Scala: length = 0x
   
  InnerClass: 
   public final $anon$2=class scala/actors/ReplyableActor$$anon$2 of class scala/actors/ReplyableActor
   public final $anonfun$respond$1=class scala/actors/ReplyableActor$$anon$2$$anonfun$respond$1 of class scala/actors/ReplyableActor$$anon$2
  minor version: 0
  major version: 49
  Constant pool:
Asciz	SourceFile;
Asciz	ReplyableActor.scala;
Asciz	<clinit>;
Asciz	()V;
Asciz	Code;
Asciz	serialVersionUID;
Asciz	J;
Asciz	scala/actors/ReplyableActor$$anon$2$$anonfun$respond$1;
class	scala/actors/ReplyableActor$$anon$2$$anonfun$respond$1
NameAndType	serialVersionUID:J
Field	scala/actors/ReplyableActor$$anon$2$$anonfun$respond$1.serialVersionUID:J
Asciz	k$1;
Asciz	Lscala/Function1;;
Asciz	$outer;
Asciz	Lscala/actors/ReplyableActor$$anon$2;;
Asciz	<init>;
Asciz	(Lscala/actors/ReplyableActor$$anon$2;Lscala/Function1;)V;
Asciz	LineNumberTable;
Asciz	java/lang/NullPointerException;
class	java/lang/NullPointerException
NameAndType	"<init>":()V
Method	java/lang/NullPointerException."<init>":()V
NameAndType	$outer:Lscala/actors/ReplyableActor$$anon$2;
Field	scala/actors/ReplyableActor$$anon$2$$anonfun$respond$1.$outer:Lscala/actors/ReplyableActor$$anon$2;
NameAndType	k$1:Lscala/Function1;
Field	scala/actors/ReplyableActor$$anon$2$$anonfun$respond$1.k$1:Lscala/Function1;
Asciz	java/lang/Object;
class	java/lang/Object
Method	java/lang/Object."<init>":()V
Asciz	scala/Function1$class;
class	scala/Function1$class
Asciz	$init$;
Asciz	(Lscala/Function1;)V;
NameAndType	$init$:(Lscala/Function1;)V
Method	scala/Function1$class.$init$:(Lscala/Function1;)V
Asciz	this;
Asciz	Lscala/actors/ReplyableActor$$anon$2$$anonfun$respond$1;;
Asciz	LocalVariableTable;
Asciz	apply;
Asciz	(Ljava/lang/Object;)Ljava/lang/Object;;
Asciz	scala/runtime/BoxedUnit;
class	scala/runtime/BoxedUnit
Asciz	(Lscala/runtime/BoxedUnit;)V;
NameAndType	apply:(Lscala/runtime/BoxedUnit;)V
Method	scala/actors/ReplyableActor$$anon$2$$anonfun$respond$1.apply:(Lscala/runtime/BoxedUnit;)V
Asciz	UNIT;
Asciz	Lscala/runtime/BoxedUnit;;
NameAndType	UNIT:Lscala/runtime/BoxedUnit;
Field	scala/runtime/BoxedUnit.UNIT:Lscala/runtime/BoxedUnit;
Asciz	v1;
Asciz	Ljava/lang/Object;;
Asciz	scala/actors/ReplyableActor$$anon$2;
class	scala/actors/ReplyableActor$$anon$2
Asciz	()Ljava/lang/Object;;
NameAndType	apply:()Ljava/lang/Object;
Method	scala/actors/ReplyableActor$$anon$2.apply:()Ljava/lang/Object;
Asciz	scala/Function1;
class	scala/Function1
NameAndType	apply:(Ljava/lang/Object;)Ljava/lang/Object;
InterfaceMethod	scala/Function1.apply:(Ljava/lang/Object;)Ljava/lang/Object;
Asciz	x;
Asciz	andThen;
Asciz	(Lscala/Function1;)Lscala/Function1;;
Asciz	(Lscala/Function1;Lscala/Function1;)Lscala/Function1;;
NameAndType	andThen:(Lscala/Function1;Lscala/Function1;)Lscala/Function1;
Method	scala/Function1$class.andThen:(Lscala/Function1;Lscala/Function1;)Lscala/Function1;
Asciz	g;
Asciz	compose;
NameAndType	compose:(Lscala/Function1;Lscala/Function1;)Lscala/Function1;
Method	scala/Function1$class.compose:(Lscala/Function1;Lscala/Function1;)Lscala/Function1;
Asciz	toString;
Asciz	()Ljava/lang/String;;
Asciz	(Lscala/Function1;)Ljava/lang/String;;
NameAndType	toString:(Lscala/Function1;)Ljava/lang/String;
Method	scala/Function1$class.toString:(Lscala/Function1;)Ljava/lang/String;
Asciz	Scala;
Asciz	InnerClasses;
Asciz	scala/actors/ReplyableActor;
class	scala/actors/ReplyableActor
Asciz	$anon$2;
Asciz	$anonfun$respond$1;
Asciz	scala/ScalaObject;
class	scala/ScalaObject
Asciz	java/io/Serializable;
class	java/io/Serializable

{
public static final long serialVersionUID;
  Signature: J

private final scala.Function1 k$1;
  Signature: Lscala/Function1;

private final scala.actors.ReplyableActor$$anon$2 $outer;
  Signature: Lscala/actors/ReplyableActor$$anon$2;

public static {};
  Signature: ()V
  Code:
   Stack=2, Locals=0, Args_size=0
	lconst_0
	putstatic	Field serialVersionUID:J
	return
  Labels:

public scala.actors.ReplyableActor$$anon$2$$anonfun$respond$1(scala.actors.ReplyableActor$$anon$2, scala.Function1);
  Signature: (Lscala/actors/ReplyableActor$$anon$2;Lscala/Function1;)V
  Code:
   Stack=2, Locals=3, Args_size=3
	aload_1
	ifnonnull	l1 // aload_0
	new	class java/lang/NullPointerException
	dup
	invokespecial	Method java/lang/NullPointerException."<init>":()V
	athrow
l1	aload_0
	aload_1
	putfield	Field $outer:Lscala/actors/ReplyableActor$$anon$2;
	aload_0
	aload_2
	putfield	Field k$1:Lscala/Function1;
	aload_0
	invokespecial	Method java/lang/Object."<init>":()V
	aload_0
	invokestatic	Method scala/Function1$class.$init$:(Lscala/Function1;)V
	return
  Labels:
   	l1 = 12 // aload_0
  LocalVariableTable: 
   Start  Length  Slot  Name   Signature
   0      31      0    this       Lscala/actors/ReplyableActor$$anon$2$$anonfun$respond$1;
   0      31      1    $outer       Lscala/actors/ReplyableActor$$anon$2;


public final java.lang.Object apply(java.lang.Object);
  Signature: (Ljava/lang/Object;)Ljava/lang/Object;
  Code:
   Stack=2, Locals=3, Args_size=2
	aload_0
	getfield	Field $outer:Lscala/actors/ReplyableActor$$anon$2;
	astore_2
	aload_0
	aload_1
	checkcast	class scala/runtime/BoxedUnit
	invokevirtual	Method apply:(Lscala/runtime/BoxedUnit;)V
	getstatic	Field scala/runtime/BoxedUnit.UNIT:Lscala/runtime/BoxedUnit;
	areturn
  Labels:
  LocalVariableTable: 
   Start  Length  Slot  Name   Signature
   0      17      0    this       Lscala/actors/ReplyableActor$$anon$2$$anonfun$respond$1;
   5      12      1    v1       Ljava/lang/Object;


public final void apply(scala.runtime.BoxedUnit);
  Signature: (Lscala/runtime/BoxedUnit;)V
  Code:
   Stack=2, Locals=3, Args_size=2
	aload_0
	getfield	Field $outer:Lscala/actors/ReplyableActor$$anon$2;
	astore_2
	aload_0
	getfield	Field k$1:Lscala/Function1;
	aload_0
	getfield	Field $outer:Lscala/actors/ReplyableActor$$anon$2;
	invokevirtual	Method scala/actors/ReplyableActor$$anon$2.apply:()Ljava/lang/Object;
	invokeinterface	InterfaceMethod scala/Function1.apply:(Ljava/lang/Object;)Ljava/lang/Object;
	pop
	return
  Labels:
  LocalVariableTable: 
   Start  Length  Slot  Name   Signature
   0      23      0    this       Lscala/actors/ReplyableActor$$anon$2$$anonfun$respond$1;
   5      18      1    x       Lscala/runtime/BoxedUnit;


public scala.Function1 andThen(scala.Function1);
  Signature: (Lscala/Function1;)Lscala/Function1;
  Code:
   Stack=2, Locals=2, Args_size=2
	aload_0
	aload_1
	invokestatic	Method scala/Function1$class.andThen:(Lscala/Function1;Lscala/Function1;)Lscala/Function1;
	areturn
  Labels:
  LocalVariableTable: 
   Start  Length  Slot  Name   Signature
   0      6      0    this       Lscala/actors/ReplyableActor$$anon$2$$anonfun$respond$1;
   0      6      1    g       Lscala/Function1;


public scala.Function1 compose(scala.Function1);
  Signature: (Lscala/Function1;)Lscala/Function1;
  Code:
   Stack=2, Locals=2, Args_size=2
	aload_0
	aload_1
	invokestatic	Method scala/Function1$class.compose:(Lscala/Function1;Lscala/Function1;)Lscala/Function1;
	areturn
  Labels:
  LocalVariableTable: 
   Start  Length  Slot  Name   Signature
   0      6      0    this       Lscala/actors/ReplyableActor$$anon$2$$anonfun$respond$1;
   0      6      1    g       Lscala/Function1;


public java.lang.String toString();
  Signature: ()Ljava/lang/String;
  Code:
   Stack=1, Locals=1, Args_size=1
	aload_0
	invokestatic	Method scala/Function1$class.toString:(Lscala/Function1;)Ljava/lang/String;
	areturn
  Labels:

}

