Compiled from "ReplyableActor.scala"
public final class scala.actors.ReplyableActor$$anon$2 extends scala.actors.Future
  SourceFile: "ReplyableActor.scala"
  Signature: length = 0x2
   00 FFFFFFA1 
  Scala: length = 0x
   
  InnerClass: 
   public final #166= #25 of #165; //$anon$2=class scala/actors/ReplyableActor$$anon$2 of class scala/actors/ReplyableActor
   public final #167= #59 of #25; //$anonfun$3=class scala/actors/ReplyableActor$$anon$2$$anonfun$3 of class scala/actors/ReplyableActor$$anon$2
   public final #168= #53 of #25; //$anonfun$2=class scala/actors/ReplyableActor$$anon$2$$anonfun$2 of class scala/actors/ReplyableActor$$anon$2
   public final #169= #29 of #25; //$anonfun$1=class scala/actors/ReplyableActor$$anon$2$$anonfun$1 of class scala/actors/ReplyableActor$$anon$2
   public final #170= #150 of #25; //$anonfun$apply$1=class scala/actors/ReplyableActor$$anon$2$$anonfun$apply$1 of class scala/actors/ReplyableActor$$anon$2
   public final #171= #118 of #25; //$anonfun$respond$1=class scala/actors/ReplyableActor$$anon$2$$anonfun$respond$1 of class scala/actors/ReplyableActor$$anon$2
  minor version: 0
  major version: 49
  Constant pool:
const #1 = Asciz	SourceFile;
const #2 = Asciz	ReplyableActor.scala;
const #3 = Asciz	handleReply;
const #4 = Asciz	Lscala/PartialFunction;;
const #5 = Asciz	Lscala/PartialFunction<Ljava/lang/Object;Ljava/lang/Object;>;;
const #6 = Asciz	Signature;
const #7 = Asciz	scala$actors$ReplyableActor$$anon$$exitReason;
const #8 = Asciz	Lscala/Option;;
const #9 = Asciz	<init>;
const #10 = Asciz	(Lscala/actors/ReplyableActor;Lscala/actors/Channel;)V;
const #11 = Asciz	Code;
const #12 = Asciz	LineNumberTable;
const #13 = Asciz	scala/actors/Future;
const #14 = class	#13;	//  scala/actors/Future
const #15 = Asciz	(Lscala/actors/InputChannel;)V;
const #16 = NameAndType	#9:#15;//  "<init>":(Lscala/actors/InputChannel;)V
const #17 = Method	#14.#16;	//  scala/actors/Future."<init>":(Lscala/actors/InputChannel;)V
const #18 = Asciz	scala/None$;
const #19 = class	#18;	//  scala/None$
const #20 = Asciz	MODULE$;
const #21 = Asciz	Lscala/None$;;
const #22 = NameAndType	#20:#21;//  MODULE$:Lscala/None$;
const #23 = Field	#19.#22;	//  scala/None$.MODULE$:Lscala/None$;
const #24 = Asciz	scala/actors/ReplyableActor$$anon$2;
const #25 = class	#24;	//  scala/actors/ReplyableActor$$anon$2
const #26 = NameAndType	#7:#8;//  scala$actors$ReplyableActor$$anon$$exitReason:Lscala/Option;
const #27 = Field	#25.#26;	//  scala/actors/ReplyableActor$$anon$2.scala$actors$ReplyableActor$$anon$$exitReason:Lscala/Option;
const #28 = Asciz	scala/actors/ReplyableActor$$anon$2$$anonfun$1;
const #29 = class	#28;	//  scala/actors/ReplyableActor$$anon$2$$anonfun$1
const #30 = Asciz	(Lscala/actors/ReplyableActor$$anon$2;)V;
const #31 = NameAndType	#9:#30;//  "<init>":(Lscala/actors/ReplyableActor$$anon$2;)V
const #32 = Method	#29.#31;	//  scala/actors/ReplyableActor$$anon$2$$anonfun$1."<init>":(Lscala/actors/ReplyableActor$$anon$2;)V
const #33 = NameAndType	#3:#4;//  handleReply:Lscala/PartialFunction;
const #34 = Field	#25.#33;	//  scala/actors/ReplyableActor$$anon$2.handleReply:Lscala/PartialFunction;
const #35 = Asciz	this;
const #36 = Asciz	Lscala/actors/ReplyableActor$$anon$2;;
const #37 = Asciz	$outer;
const #38 = Asciz	Lscala/actors/ReplyableActor;;
const #39 = Asciz	LocalVariableTable;
const #40 = Asciz	isSet;
const #41 = Asciz	()Z;
const #42 = Asciz	fvalue;
const #43 = Asciz	()Lscala/Option;;
const #44 = NameAndType	#42:#43;//  fvalue:()Lscala/Option;
const #45 = Method	#25.#44;	//  scala/actors/ReplyableActor$$anon$2.fvalue:()Lscala/Option;
const #46 = Asciz	java/lang/Object;
const #47 = class	#46;	//  java/lang/Object
const #48 = Asciz	equals;
const #49 = Asciz	(Ljava/lang/Object;)Z;
const #50 = NameAndType	#48:#49;//  equals:(Ljava/lang/Object;)Z
const #51 = Method	#47.#50;	//  java/lang/Object.equals:(Ljava/lang/Object;)Z
const #52 = Asciz	scala/actors/ReplyableActor$$anon$2$$anonfun$2;
const #53 = class	#52;	//  scala/actors/ReplyableActor$$anon$2$$anonfun$2
const #54 = Method	#53.#31;	//  scala/actors/ReplyableActor$$anon$2$$anonfun$2."<init>":(Lscala/actors/ReplyableActor$$anon$2;)V
const #55 = Asciz	()Lscala/PartialFunction;;
const #56 = NameAndType	#3:#55;//  handleReply:()Lscala/PartialFunction;
const #57 = Method	#25.#56;	//  scala/actors/ReplyableActor$$anon$2.handleReply:()Lscala/PartialFunction;
const #58 = Asciz	scala/actors/ReplyableActor$$anon$2$$anonfun$3;
const #59 = class	#58;	//  scala/actors/ReplyableActor$$anon$2$$anonfun$3
const #60 = Method	#59.#31;	//  scala/actors/ReplyableActor$$anon$2$$anonfun$3."<init>":(Lscala/actors/ReplyableActor$$anon$2;)V
const #61 = Asciz	scala/PartialFunction;
const #62 = class	#61;	//  scala/PartialFunction
const #63 = Asciz	andThen;
const #64 = Asciz	(Lscala/Function1;)Lscala/PartialFunction;;
const #65 = NameAndType	#63:#64;//  andThen:(Lscala/Function1;)Lscala/PartialFunction;
const #66 = InterfaceMethod	#62.#65;	//  scala/PartialFunction.andThen:(Lscala/Function1;)Lscala/PartialFunction;
const #67 = Asciz	scala/PartialFunction$class;
const #68 = class	#67;	//  scala/PartialFunction$class
const #69 = Asciz	orElse;
const #70 = Asciz	(Lscala/PartialFunction;Lscala/PartialFunction;)Lscala/PartialFunction;;
const #71 = NameAndType	#69:#70;//  orElse:(Lscala/PartialFunction;Lscala/PartialFunction;)Lscala/PartialFunction;
const #72 = Method	#68.#71;	//  scala/PartialFunction$class.orElse:(Lscala/PartialFunction;Lscala/PartialFunction;)Lscala/PartialFunction;
const #73 = Asciz	inputChannel;
const #74 = Asciz	()Lscala/actors/InputChannel;;
const #75 = NameAndType	#73:#74;//  inputChannel:()Lscala/actors/InputChannel;
const #76 = Method	#25.#75;	//  scala/actors/ReplyableActor$$anon$2.inputChannel:()Lscala/actors/InputChannel;
const #77 = Asciz	scala/actors/InputChannel;
const #78 = class	#77;	//  scala/actors/InputChannel
const #79 = Asciz	receiveWithin;
const #80 = Asciz	(JLscala/PartialFunction;)Ljava/lang/Object;;
const #81 = NameAndType	#79:#80;//  receiveWithin:(JLscala/PartialFunction;)Ljava/lang/Object;
const #82 = InterfaceMethod	#78.#81;	//  scala/actors/InputChannel.receiveWithin:(JLscala/PartialFunction;)Ljava/lang/Object;
const #83 = Asciz	scala/runtime/BoxesRunTime;
const #84 = class	#83;	//  scala/runtime/BoxesRunTime
const #85 = Asciz	unboxToBoolean;
const #86 = NameAndType	#85:#49;//  unboxToBoolean:(Ljava/lang/Object;)Z
const #87 = Method	#84.#86;	//  scala/runtime/BoxesRunTime.unboxToBoolean:(Ljava/lang/Object;)Z
const #88 = Asciz	scala/MatchError;
const #89 = class	#88;	//  scala/MatchError
const #90 = Asciz	scala/Option;
const #91 = class	#90;	//  scala/Option
const #92 = Asciz	toString;
const #93 = Asciz	()Ljava/lang/String;;
const #94 = NameAndType	#92:#93;//  toString:()Ljava/lang/String;
const #95 = Method	#91.#94;	//  scala/Option.toString:()Ljava/lang/String;
const #96 = Asciz	(Ljava/lang/String;)V;
const #97 = NameAndType	#9:#96;//  "<init>":(Ljava/lang/String;)V
const #98 = Method	#89.#97;	//  scala/MatchError."<init>":(Ljava/lang/String;)V
const #99 = Asciz	scala/Some;
const #100 = class	#99;	//  scala/Some
const #101 = NameAndType	#7:#43;//  scala$actors$ReplyableActor$$anon$$exitReason:()Lscala/Option;
const #102 = Method	#25.#101;	//  scala/actors/ReplyableActor$$anon$2.scala$actors$ReplyableActor$$anon$$exitReason:()Lscala/Option;
const #103 = Asciz	isEmpty;
const #104 = NameAndType	#103:#41;//  isEmpty:()Z
const #105 = Method	#91.#104;	//  scala/Option.isEmpty:()Z
const #106 = Asciz	handleTimeout;
const #107 = Asciz	whatToDo;
const #108 = Asciz	temp12;
const #109 = Asciz	respond;
const #110 = Asciz	(Lscala/Function1;)V;
const #111 = NameAndType	#40:#41;//  isSet:()Z
const #112 = Method	#25.#111;	//  scala/actors/ReplyableActor$$anon$2.isSet:()Z
const #113 = Asciz	apply;
const #114 = Asciz	()Ljava/lang/Object;;
const #115 = NameAndType	#113:#114;//  apply:()Ljava/lang/Object;
const #116 = Method	#25.#115;	//  scala/actors/ReplyableActor$$anon$2.apply:()Ljava/lang/Object;
const #117 = Asciz	scala/actors/ReplyableActor$$anon$2$$anonfun$respond$1;
const #118 = class	#117;	//  scala/actors/ReplyableActor$$anon$2$$anonfun$respond$1
const #119 = Asciz	(Lscala/actors/ReplyableActor$$anon$2;Lscala/Function1;)V;
const #120 = NameAndType	#9:#119;//  "<init>":(Lscala/actors/ReplyableActor$$anon$2;Lscala/Function1;)V
const #121 = Method	#118.#120;	//  scala/actors/ReplyableActor$$anon$2$$anonfun$respond$1."<init>":(Lscala/actors/ReplyableActor$$anon$2;Lscala/Function1;)V
const #122 = Asciz	react;
const #123 = Asciz	(Lscala/PartialFunction;)Lscala/runtime/Nothing$;;
const #124 = NameAndType	#122:#123;//  react:(Lscala/PartialFunction;)Lscala/runtime/Nothing$;
const #125 = InterfaceMethod	#78.#124;	//  scala/actors/InputChannel.react:(Lscala/PartialFunction;)Lscala/runtime/Nothing$;
const #126 = Asciz	k$1;
const #127 = Asciz	Lscala/Function1;;
const #128 = Asciz	(Lscala/Function1<Ljava/lang/Object;Ljava/lang/Object;>;)V;
const #129 = Asciz	scala/runtime/BoxedUnit;
const #130 = class	#129;	//  scala/runtime/BoxedUnit
const #131 = Asciz	UNIT;
const #132 = Asciz	Lscala/runtime/BoxedUnit;;
const #133 = NameAndType	#131:#132;//  UNIT:Lscala/runtime/BoxedUnit;
const #134 = Field	#130.#133;	//  scala/runtime/BoxedUnit.UNIT:Lscala/runtime/BoxedUnit;
const #135 = Asciz	get;
const #136 = NameAndType	#135:#114;//  get:()Ljava/lang/Object;
const #137 = Method	#91.#136;	//  scala/Option.get:()Ljava/lang/Object;
const #138 = Asciz	java/lang/Throwable;
const #139 = class	#138;	//  java/lang/Throwable
const #140 = Asciz	java/util/concurrent/ExecutionException;
const #141 = class	#140;	//  java/util/concurrent/ExecutionException
const #142 = Asciz	(Ljava/lang/Throwable;)V;
const #143 = NameAndType	#9:#142;//  "<init>":(Ljava/lang/Throwable;)V
const #144 = Method	#141.#143;	//  java/util/concurrent/ExecutionException."<init>":(Ljava/lang/Throwable;)V
const #145 = Asciz	java/lang/Exception;
const #146 = class	#145;	//  java/lang/Exception
const #147 = Method	#47.#94;	//  java/lang/Object.toString:()Ljava/lang/String;
const #148 = Method	#146.#97;	//  java/lang/Exception."<init>":(Ljava/lang/String;)V
const #149 = Asciz	scala/actors/ReplyableActor$$anon$2$$anonfun$apply$1;
const #150 = class	#149;	//  scala/actors/ReplyableActor$$anon$2$$anonfun$apply$1
const #151 = Method	#150.#31;	//  scala/actors/ReplyableActor$$anon$2$$anonfun$apply$1."<init>":(Lscala/actors/ReplyableActor$$anon$2;)V
const #152 = Asciz	receive;
const #153 = Asciz	(Lscala/PartialFunction;)Ljava/lang/Object;;
const #154 = NameAndType	#152:#153;//  receive:(Lscala/PartialFunction;)Ljava/lang/Object;
const #155 = InterfaceMethod	#78.#154;	//  scala/actors/InputChannel.receive:(Lscala/PartialFunction;)Ljava/lang/Object;
const #156 = Asciz	reason;
const #157 = Asciz	Ljava/lang/Object;;
const #158 = Asciz	()Lscala/PartialFunction<Ljava/lang/Object;Ljava/lang/Object;>;;
const #159 = Asciz	scala$actors$ReplyableActor$$anon$$exitReason_$eq;
const #160 = Asciz	(Lscala/Option;)V;
const #161 = Asciz	Lscala/actors/Future<Ljava/lang/Object;>;;
const #162 = Asciz	Scala;
const #163 = Asciz	InnerClasses;
const #164 = Asciz	scala/actors/ReplyableActor;
const #165 = class	#164;	//  scala/actors/ReplyableActor
const #166 = Asciz	$anon$2;
const #167 = Asciz	$anonfun$3;
const #168 = Asciz	$anonfun$2;
const #169 = Asciz	$anonfun$1;
const #170 = Asciz	$anonfun$apply$1;
const #171 = Asciz	$anonfun$respond$1;

{
public scala.actors.ReplyableActor$$anon$2(scala.actors.ReplyableActor, scala.actors.Channel);
  Code:
   Stack=4, Locals=3, Args_size=3
   0:	aload_0
   1:	aload_2
   2:	invokespecial	#17; //Method scala/actors/Future."<init>":(Lscala/actors/InputChannel;)V
   5:	aload_0
   6:	getstatic	#23; //Field scala/None$.MODULE$:Lscala/None$;
   9:	putfield	#27; //Field scala$actors$ReplyableActor$$anon$$exitReason:Lscala/Option;
   12:	aload_0
   13:	new	#29; //class scala/actors/ReplyableActor$$anon$2$$anonfun$1
   16:	dup
   17:	aload_0
   18:	invokespecial	#32; //Method scala/actors/ReplyableActor$$anon$2$$anonfun$1."<init>":(Lscala/actors/ReplyableActor$$anon$2;)V
   21:	putfield	#34; //Field handleReply:Lscala/PartialFunction;
   24:	return
  LineNumberTable: 
   line 118: 0
   line 119: 5
   line 120: 12

  LocalVariableTable: 
   Start  Length  Slot  Name   Signature
   0      25      0    this       Lscala/actors/ReplyableActor$$anon$2;
   0      25      1    $outer       Lscala/actors/ReplyableActor;


public boolean isSet();
  Code:
   Stack=4, Locals=5, Args_size=1
   0:	aload_0
   1:	invokevirtual	#45; //Method fvalue:()Lscala/Option;
   4:	astore	4
   6:	getstatic	#23; //Field scala/None$.MODULE$:Lscala/None$;
   9:	dup
   10:	ifnonnull	22
   13:	pop
   14:	aload	4
   16:	ifnull	30
   19:	goto	97
   22:	aload	4
   24:	invokevirtual	#51; //Method java/lang/Object.equals:(Ljava/lang/Object;)Z
   27:	ifeq	97
   30:	iconst_1
   31:	ifeq	84
   34:	new	#53; //class scala/actors/ReplyableActor$$anon$2$$anonfun$2
   37:	dup
   38:	aload_0
   39:	invokespecial	#54; //Method scala/actors/ReplyableActor$$anon$2$$anonfun$2."<init>":(Lscala/actors/ReplyableActor$$anon$2;)V
   42:	astore_1
   43:	aload_0
   44:	invokespecial	#57; //Method handleReply:()Lscala/PartialFunction;
   47:	new	#59; //class scala/actors/ReplyableActor$$anon$2$$anonfun$3
   50:	dup
   51:	aload_0
   52:	invokespecial	#60; //Method scala/actors/ReplyableActor$$anon$2$$anonfun$3."<init>":(Lscala/actors/ReplyableActor$$anon$2;)V
   55:	invokeinterface	#66,  2; //InterfaceMethod scala/PartialFunction.andThen:(Lscala/Function1;)Lscala/PartialFunction;
   60:	astore_2
   61:	aload_1
   62:	aload_2
   63:	invokestatic	#72; //Method scala/PartialFunction$class.orElse:(Lscala/PartialFunction;Lscala/PartialFunction;)Lscala/PartialFunction;
   66:	astore_3
   67:	aload_0
   68:	invokevirtual	#76; //Method inputChannel:()Lscala/actors/InputChannel;
   71:	lconst_0
   72:	aload_3
   73:	invokeinterface	#82,  4; //InterfaceMethod scala/actors/InputChannel.receiveWithin:(JLscala/PartialFunction;)Ljava/lang/Object;
   78:	invokestatic	#87; //Method scala/runtime/BoxesRunTime.unboxToBoolean:(Ljava/lang/Object;)Z
   81:	goto	110
   84:	new	#89; //class scala/MatchError
   87:	dup
   88:	aload	4
   90:	invokevirtual	#95; //Method scala/Option.toString:()Ljava/lang/String;
   93:	invokespecial	#98; //Method scala/MatchError."<init>":(Ljava/lang/String;)V
   96:	athrow
   97:	aload	4
   99:	instanceof	#100; //class scala/Some
   102:	ifeq	142
   105:	iconst_1
   106:	ifeq	129
   109:	iconst_1
   110:	ifne	127
   113:	aload_0
   114:	invokespecial	#102; //Method scala$actors$ReplyableActor$$anon$$exitReason:()Lscala/Option;
   117:	invokevirtual	#105; //Method scala/Option.isEmpty:()Z
   120:	ifeq	127
   123:	iconst_0
   124:	goto	128
   127:	iconst_1
   128:	ireturn
   129:	new	#89; //class scala/MatchError
   132:	dup
   133:	aload	4
   135:	invokevirtual	#95; //Method scala/Option.toString:()Ljava/lang/String;
   138:	invokespecial	#98; //Method scala/MatchError."<init>":(Ljava/lang/String;)V
   141:	athrow
   142:	new	#89; //class scala/MatchError
   145:	dup
   146:	aload	4
   148:	invokevirtual	#95; //Method scala/Option.toString:()Ljava/lang/String;
   151:	invokespecial	#98; //Method scala/MatchError."<init>":(Ljava/lang/String;)V
   154:	athrow
  LineNumberTable: 
   line 146: 0
   line 644: 30
   line 148: 34
   line 153: 43
   line 152: 66
   line 154: 67
   line 146: 84
   line 644: 105
   line 155: 109
   line 146: 110
   line 156: 113
   line 146: 129

  LocalVariableTable: 
   Start  Length  Slot  Name   Signature
   0      155      0    this       Lscala/actors/ReplyableActor$$anon$2;
   43      38      1    handleTimeout       Lscala/PartialFunction;
   67      14      3    whatToDo       Lscala/PartialFunction;
   6      107      4    temp12       Lscala/Option;
   129      26      4    temp12       Lscala/Option;


public void respond(scala.Function1);
  Code:
   Stack=6, Locals=2, Args_size=2
   0:	aload_0
   1:	invokevirtual	#112; //Method isSet:()Z
   4:	ifeq	13
   7:	aload_0
   8:	invokevirtual	#116; //Method apply:()Ljava/lang/Object;
   11:	pop
   12:	return
   13:	aload_0
   14:	invokevirtual	#76; //Method inputChannel:()Lscala/actors/InputChannel;
   17:	aload_0
   18:	invokespecial	#57; //Method handleReply:()Lscala/PartialFunction;
   21:	new	#118; //class scala/actors/ReplyableActor$$anon$2$$anonfun$respond$1
   24:	dup
   25:	aload_0
   26:	aload_1
   27:	invokespecial	#121; //Method scala/actors/ReplyableActor$$anon$2$$anonfun$respond$1."<init>":(Lscala/actors/ReplyableActor$$anon$2;Lscala/Function1;)V
   30:	invokeinterface	#66,  2; //InterfaceMethod scala/PartialFunction.andThen:(Lscala/Function1;)Lscala/PartialFunction;
   35:	invokeinterface	#125,  2; //InterfaceMethod scala/actors/InputChannel.react:(Lscala/PartialFunction;)Lscala/runtime/Nothing$;
   40:	athrow
  LineNumberTable: 
   line 141: 0
   line 142: 7
   line 141: 12
   line 144: 13

  LocalVariableTable: 
   Start  Length  Slot  Name   Signature
   0      41      0    this       Lscala/actors/ReplyableActor$$anon$2;
   0      41      1    k$1       Lscala/Function1;

  Signature: length = 0x2
   00 FFFFFF80 

public java.lang.Object apply();
  Code:
   Stack=5, Locals=2, Args_size=1
   0:	aload_0
   1:	invokevirtual	#112; //Method isSet:()Z
   4:	ifeq	89
   7:	aload_0
   8:	invokevirtual	#45; //Method fvalue:()Lscala/Option;
   11:	invokevirtual	#105; //Method scala/Option.isEmpty:()Z
   14:	ifeq	79
   17:	aload_0
   18:	invokespecial	#102; //Method scala$actors$ReplyableActor$$anon$$exitReason:()Lscala/Option;
   21:	invokevirtual	#105; //Method scala/Option.isEmpty:()Z
   24:	ifeq	33
   27:	getstatic	#134; //Field scala/runtime/BoxedUnit.UNIT:Lscala/runtime/BoxedUnit;
   30:	goto	115
   33:	aload_0
   34:	invokespecial	#102; //Method scala$actors$ReplyableActor$$anon$$exitReason:()Lscala/Option;
   37:	invokevirtual	#137; //Method scala/Option.get:()Ljava/lang/Object;
   40:	astore_1
   41:	aload_1
   42:	instanceof	#139; //class java/lang/Throwable
   45:	ifeq	60
   48:	new	#141; //class java/util/concurrent/ExecutionException
   51:	dup
   52:	aload_1
   53:	checkcast	#139; //class java/lang/Throwable
   56:	invokespecial	#144; //Method java/util/concurrent/ExecutionException."<init>":(Ljava/lang/Throwable;)V
   59:	athrow
   60:	new	#141; //class java/util/concurrent/ExecutionException
   63:	dup
   64:	new	#146; //class java/lang/Exception
   67:	dup
   68:	aload_1
   69:	invokevirtual	#147; //Method java/lang/Object.toString:()Ljava/lang/String;
   72:	invokespecial	#148; //Method java/lang/Exception."<init>":(Ljava/lang/String;)V
   75:	invokespecial	#144; //Method java/util/concurrent/ExecutionException."<init>":(Ljava/lang/Throwable;)V
   78:	athrow
   79:	aload_0
   80:	invokevirtual	#45; //Method fvalue:()Lscala/Option;
   83:	invokevirtual	#137; //Method scala/Option.get:()Ljava/lang/Object;
   86:	goto	115
   89:	aload_0
   90:	invokevirtual	#76; //Method inputChannel:()Lscala/actors/InputChannel;
   93:	aload_0
   94:	invokespecial	#57; //Method handleReply:()Lscala/PartialFunction;
   97:	new	#150; //class scala/actors/ReplyableActor$$anon$2$$anonfun$apply$1
   100:	dup
   101:	aload_0
   102:	invokespecial	#151; //Method scala/actors/ReplyableActor$$anon$2$$anonfun$apply$1."<init>":(Lscala/actors/ReplyableActor$$anon$2;)V
   105:	invokeinterface	#66,  2; //InterfaceMethod scala/PartialFunction.andThen:(Lscala/Function1;)Lscala/PartialFunction;
   110:	invokeinterface	#155,  2; //InterfaceMethod scala/actors/InputChannel.receive:(Lscala/PartialFunction;)Ljava/lang/Object;
   115:	areturn
  LineNumberTable: 
   line 128: 0
   line 129: 7
   line 131: 17
   line 132: 33
   line 133: 41
   line 134: 48
   line 136: 60
   line 130: 79
   line 138: 89
   line 128: 115

  LocalVariableTable: 
   Start  Length  Slot  Name   Signature
   0      116      0    this       Lscala/actors/ReplyableActor$$anon$2;
   41      38      1    reason       Ljava/lang/Object;


public final void scala$actors$ReplyableActor$$anon$$exitReason_$eq(scala.Option);
  Code:
   Stack=2, Locals=2, Args_size=2
   0:	aload_0
   1:	aload_1
   2:	putfield	#27; //Field scala$actors$ReplyableActor$$anon$$exitReason:Lscala/Option;
   5:	return
  LineNumberTable: 
   line 119: 0


}

