Compiled from "ReplyableReactor.scala"
public final class scala.actors.ReplyableReactor$$anon$1 extends scala.actors.Future
  SourceFile: "ReplyableReactor.scala"
  Signature: length = 0x2
   00 50 
  Scala: length = 0x
   
  InnerClass: 
   public final $anon$1=class scala/actors/ReplyableReactor$$anon$1 of class scala/actors/ReplyableReactor
   public final $anonfun$respond$1=class scala/actors/ReplyableReactor$$anon$1$$anonfun$respond$1 of class scala/actors/ReplyableReactor$$anon$1
  minor version: 0
  major version: 49
  Constant pool:
Asciz	SourceFile;
Asciz	ReplyableReactor.scala;
Asciz	res$2;
Asciz	Lscala/concurrent/SyncVar;;
Asciz	<init>;
Asciz	(Lscala/actors/ReplyReactor;Lscala/actors/ReactChannel;Lscala/concurrent/SyncVar;)V;
Asciz	Code;
Asciz	LineNumberTable;
Asciz	scala/actors/ReplyableReactor$$anon$1;
class	scala/actors/ReplyableReactor$$anon$1
NameAndType	res$2:Lscala/concurrent/SyncVar;
Field	scala/actors/ReplyableReactor$$anon$1.res$2:Lscala/concurrent/SyncVar;
Asciz	scala/actors/Future;
class	scala/actors/Future
Asciz	(Lscala/actors/InputChannel;)V;
NameAndType	"<init>":(Lscala/actors/InputChannel;)V
Method	scala/actors/Future."<init>":(Lscala/actors/InputChannel;)V
Asciz	this;
Asciz	Lscala/actors/ReplyableReactor$$anon$1;;
Asciz	$outer;
Asciz	Lscala/actors/ReplyReactor;;
Asciz	LocalVariableTable;
Asciz	isSet;
Asciz	()Z;
Asciz	value;
Asciz	()Lscala/Option;;
NameAndType	value:()Lscala/Option;
Method	scala/actors/ReplyableReactor$$anon$1.value:()Lscala/Option;
Asciz	scala/Option;
class	scala/Option
Asciz	isEmpty;
NameAndType	isEmpty:()Z
Method	scala/Option.isEmpty:()Z
Asciz	respond;
Asciz	(Lscala/Function1;)V;
NameAndType	isSet:()Z
Method	scala/actors/ReplyableReactor$$anon$1.isSet:()Z
Asciz	get;
Asciz	()Ljava/lang/Object;;
NameAndType	get:()Ljava/lang/Object;
Method	scala/Option.get:()Ljava/lang/Object;
Asciz	scala/Function1;
class	scala/Function1
Asciz	apply;
Asciz	(Ljava/lang/Object;)Ljava/lang/Object;;
NameAndType	apply:(Ljava/lang/Object;)Ljava/lang/Object;
InterfaceMethod	scala/Function1.apply:(Ljava/lang/Object;)Ljava/lang/Object;
Asciz	inputChannel;
Asciz	()Lscala/actors/InputChannel;;
NameAndType	inputChannel:()Lscala/actors/InputChannel;
Method	scala/actors/ReplyableReactor$$anon$1.inputChannel:()Lscala/actors/InputChannel;
Asciz	scala/actors/ReplyableReactor$$anon$1$$anonfun$respond$1;
class	scala/actors/ReplyableReactor$$anon$1$$anonfun$respond$1
Asciz	(Lscala/actors/ReplyableReactor$$anon$1;Lscala/Function1;)V;
NameAndType	"<init>":(Lscala/actors/ReplyableReactor$$anon$1;Lscala/Function1;)V
Method	scala/actors/ReplyableReactor$$anon$1$$anonfun$respond$1."<init>":(Lscala/actors/ReplyableReactor$$anon$1;Lscala/Function1;)V
Asciz	scala/actors/InputChannel;
class	scala/actors/InputChannel
Asciz	react;
Asciz	(Lscala/PartialFunction;)Lscala/runtime/Nothing$;;
NameAndType	react:(Lscala/PartialFunction;)Lscala/runtime/Nothing$;
InterfaceMethod	scala/actors/InputChannel.react:(Lscala/PartialFunction;)Lscala/runtime/Nothing$;
Asciz	k$1;
Asciz	Lscala/Function1;;
Asciz	(Lscala/Function1<TA;Ljava/lang/Object;>;)V;
Asciz	Signature;
Asciz	scala/Some;
class	scala/Some
Asciz	scala/concurrent/SyncVar;
class	scala/concurrent/SyncVar
Method	scala/concurrent/SyncVar.get:()Ljava/lang/Object;
Asciz	(Ljava/lang/Object;)V;
NameAndType	"<init>":(Ljava/lang/Object;)V
Method	scala/Some."<init>":(Ljava/lang/Object;)V
Asciz	value_$eq;
Asciz	(Lscala/Option;)V;
NameAndType	value_$eq:(Lscala/Option;)V
Method	scala/actors/ReplyableReactor$$anon$1.value_$eq:(Lscala/Option;)V
Asciz	()TA;;
Asciz	Lscala/actors/Future<TA;>;;
Asciz	Scala;
Asciz	InnerClasses;
Asciz	scala/actors/ReplyableReactor;
class	scala/actors/ReplyableReactor
Asciz	$anon$1;
Asciz	$anonfun$respond$1;

{
private final scala.concurrent.SyncVar res$2;
  Signature: Lscala/concurrent/SyncVar;

public scala.actors.ReplyableReactor$$anon$1(scala.actors.ReplyReactor, scala.actors.ReactChannel, scala.concurrent.SyncVar);
  Signature: (Lscala/actors/ReplyReactor;Lscala/actors/ReactChannel;Lscala/concurrent/SyncVar;)V
  Code:
   Stack=2, Locals=4, Args_size=4
	aload_0
	aload_3
	putfield	Field res$2:Lscala/concurrent/SyncVar;
	aload_0
	aload_2
	invokespecial	Method scala/actors/Future."<init>":(Lscala/actors/InputChannel;)V
	return
  Labels:
  LocalVariableTable: 
   Start  Length  Slot  Name   Signature
   0      11      0    this       Lscala/actors/ReplyableReactor$$anon$1;
   0      11      1    $outer       Lscala/actors/ReplyReactor;


public boolean isSet();
  Signature: ()Z
  Code:
   Stack=1, Locals=1, Args_size=1
	aload_0
	invokevirtual	Method value:()Lscala/Option;
	invokevirtual	Method scala/Option.isEmpty:()Z
	ifeq	l1 // iconst_1
	iconst_0
	goto	l2 // ireturn
l1	iconst_1
l2	ireturn
  Labels:
   	l1 = 14 // iconst_1
   	l2 = 15 // ireturn

public void respond(scala.Function1);
  Signature: (Lscala/Function1;)V
  Code:
   Stack=5, Locals=2, Args_size=2
	aload_0
	invokevirtual	Method isSet:()Z
	ifeq	l1 // aload_0
	aload_1
	aload_0
	invokevirtual	Method value:()Lscala/Option;
	invokevirtual	Method scala/Option.get:()Ljava/lang/Object;
	invokeinterface	InterfaceMethod scala/Function1.apply:(Ljava/lang/Object;)Ljava/lang/Object;
	pop
	return
l1	aload_0
	invokevirtual	Method inputChannel:()Lscala/actors/InputChannel;
	new	class scala/actors/ReplyableReactor$$anon$1$$anonfun$respond$1
	dup
	aload_0
	aload_1
	invokespecial	Method scala/actors/ReplyableReactor$$anon$1$$anonfun$respond$1."<init>":(Lscala/actors/ReplyableReactor$$anon$1;Lscala/Function1;)V
	invokeinterface	InterfaceMethod scala/actors/InputChannel.react:(Lscala/PartialFunction;)Lscala/runtime/Nothing$;
	athrow
  Labels:
   	l1 = 22 // aload_0
  LocalVariableTable: 
   Start  Length  Slot  Name   Signature
   0      41      0    this       Lscala/actors/ReplyableReactor$$anon$1;
   0      41      1    k$1       Lscala/Function1;

  Signature: length = 0x2
   00 41 

public java.lang.Object apply();
  Signature: ()Ljava/lang/Object;
  Code:
   Stack=4, Locals=1, Args_size=1
	aload_0
	invokevirtual	Method isSet:()Z
	ifeq	l1 // aload_0
	aload_0
	invokevirtual	Method value:()Lscala/Option;
	invokevirtual	Method scala/Option.get:()Ljava/lang/Object;
	goto	l2 // areturn
l1	aload_0
	new	class scala/Some
	dup
	aload_0
	getfield	Field res$2:Lscala/concurrent/SyncVar;
	invokevirtual	Method scala/concurrent/SyncVar.get:()Ljava/lang/Object;
	invokespecial	Method scala/Some."<init>":(Ljava/lang/Object;)V
	invokevirtual	Method value_$eq:(Lscala/Option;)V
	aload_0
	invokevirtual	Method value:()Lscala/Option;
	invokevirtual	Method scala/Option.get:()Ljava/lang/Object;
l2	areturn
  Labels:
   	l1 = 17 // aload_0
   	l2 = 42 // areturn
  Signature: length = 0x2
   00 4F 

}

