Compiled from "ReplyReactor.scala"
public abstract class scala.actors.ReplyReactor$class extends java.lang.Object
  SourceFile: "ReplyReactor.scala"
  Scala: length = 0x
   
  InnerClass: 
   public final #190= #25 of #14; //$anonfun$1=class scala/actors/ReplyReactor$$anonfun$1 of class scala/actors/ReplyReactor
   public final #191= #43 of #14; //$anonfun$searchMailbox$1=class scala/actors/ReplyReactor$$anonfun$searchMailbox$1 of class scala/actors/ReplyReactor
  minor version: 0
  major version: 49
  Constant pool:
const #1 = Asciz	SourceFile;
const #2 = Asciz	ReplyReactor.scala;
const #3 = Asciz	$init$;
const #4 = Asciz	(Lscala/actors/ReplyReactor;)V;
const #5 = Asciz	Code;
const #6 = Asciz	LineNumberTable;
const #7 = Asciz	scala/collection/immutable/Nil$;
const #8 = class	#7;	//  scala/collection/immutable/Nil$
const #9 = Asciz	MODULE$;
const #10 = Asciz	Lscala/collection/immutable/Nil$;;
const #11 = NameAndType	#9:#10;//  MODULE$:Lscala/collection/immutable/Nil$;
const #12 = Field	#8.#11;	//  scala/collection/immutable/Nil$.MODULE$:Lscala/collection/immutable/Nil$;
const #13 = Asciz	scala/actors/ReplyReactor;
const #14 = class	#13;	//  scala/actors/ReplyReactor
const #15 = Asciz	senders_$eq;
const #16 = Asciz	(Lscala/collection/immutable/List;)V;
const #17 = NameAndType	#15:#16;//  senders_$eq:(Lscala/collection/immutable/List;)V
const #18 = InterfaceMethod	#14.#17;	//  scala/actors/ReplyReactor.senders_$eq:(Lscala/collection/immutable/List;)V
const #19 = Asciz	$this;
const #20 = Asciz	Lscala/actors/ReplyReactor;;
const #21 = Asciz	LocalVariableTable;
const #22 = Asciz	searchMailbox;
const #23 = Asciz	(Lscala/actors/ReplyReactor;Lscala/actors/MessageQueue;Lscala/Function1;Z)V;
const #24 = Asciz	scala/actors/ReplyReactor$$anonfun$1;
const #25 = class	#24;	//  scala/actors/ReplyReactor$$anonfun$1
const #26 = Asciz	<init>;
const #27 = Asciz	(Lscala/actors/ReplyReactor;Lscala/Function1;)V;
const #28 = NameAndType	#26:#27;//  "<init>":(Lscala/actors/ReplyReactor;Lscala/Function1;)V
const #29 = Method	#25.#28;	//  scala/actors/ReplyReactor$$anonfun$1."<init>":(Lscala/actors/ReplyReactor;Lscala/Function1;)V
const #30 = Asciz	scala/actors/MessageQueue;
const #31 = class	#30;	//  scala/actors/MessageQueue
const #32 = Asciz	extractFirst;
const #33 = Asciz	(Lscala/Function2;)Lscala/actors/MessageQueueElement;;
const #34 = NameAndType	#32:#33;//  extractFirst:(Lscala/Function2;)Lscala/actors/MessageQueueElement;
const #35 = Method	#31.#34;	//  scala/actors/MessageQueue.extractFirst:(Lscala/Function2;)Lscala/actors/MessageQueueElement;
const #36 = Asciz	scala/actors/Reactor;
const #37 = class	#36;	//  scala/actors/Reactor
const #38 = Asciz	mailbox;
const #39 = Asciz	()Lscala/actors/MessageQueue;;
const #40 = NameAndType	#38:#39;//  mailbox:()Lscala/actors/MessageQueue;
const #41 = InterfaceMethod	#37.#40;	//  scala/actors/Reactor.mailbox:()Lscala/actors/MessageQueue;
const #42 = Asciz	scala/actors/ReplyReactor$$anonfun$searchMailbox$1;
const #43 = class	#42;	//  scala/actors/ReplyReactor$$anonfun$searchMailbox$1
const #44 = NameAndType	#26:#4;//  "<init>":(Lscala/actors/ReplyReactor;)V
const #45 = Method	#43.#44;	//  scala/actors/ReplyReactor$$anonfun$searchMailbox$1."<init>":(Lscala/actors/ReplyReactor;)V
const #46 = Asciz	foreach;
const #47 = Asciz	(Lscala/Function2;)V;
const #48 = NameAndType	#46:#47;//  foreach:(Lscala/Function2;)V
const #49 = Method	#31.#48;	//  scala/actors/MessageQueue.foreach:(Lscala/Function2;)V
const #50 = Asciz	sendBuffer;
const #51 = Asciz	()Lscala/collection/mutable/Queue;;
const #52 = NameAndType	#50:#51;//  sendBuffer:()Lscala/collection/mutable/Queue;
const #53 = InterfaceMethod	#37.#52;	//  scala/actors/Reactor.sendBuffer:()Lscala/collection/mutable/Queue;
const #54 = Asciz	scala/collection/mutable/Queue;
const #55 = class	#54;	//  scala/collection/mutable/Queue
const #56 = Asciz	isEmpty;
const #57 = Asciz	()Z;
const #58 = NameAndType	#56:#57;//  isEmpty:()Z
const #59 = Method	#55.#58;	//  scala/collection/mutable/Queue.isEmpty:()Z
const #60 = Asciz	waitingFor_$eq;
const #61 = Asciz	(Lscala/Function1;)V;
const #62 = NameAndType	#60:#61;//  waitingFor_$eq:(Lscala/Function1;)V
const #63 = InterfaceMethod	#37.#62;	//  scala/actors/Reactor.waitingFor_$eq:(Lscala/Function1;)V
const #64 = Asciz	Temp;
const #65 = String	#64;	//  Temp
const #66 = Asciz	(Ljava/lang/String;)V;
const #67 = NameAndType	#26:#66;//  "<init>":(Ljava/lang/String;)V
const #68 = Method	#31.#67;	//  scala/actors/MessageQueue."<init>":(Ljava/lang/String;)V
const #69 = Asciz	drainSendBuffer;
const #70 = Asciz	(Lscala/actors/MessageQueue;)V;
const #71 = NameAndType	#69:#70;//  drainSendBuffer:(Lscala/actors/MessageQueue;)V
const #72 = InterfaceMethod	#37.#71;	//  scala/actors/Reactor.drainSendBuffer:(Lscala/actors/MessageQueue;)V
const #73 = Asciz	scala/Tuple2;
const #74 = class	#73;	//  scala/Tuple2
const #75 = Asciz	scala/actors/MessageQueueElement;
const #76 = class	#75;	//  scala/actors/MessageQueueElement
const #77 = Asciz	msg;
const #78 = Asciz	()Ljava/lang/Object;;
const #79 = NameAndType	#77:#78;//  msg:()Ljava/lang/Object;
const #80 = Method	#76.#79;	//  scala/actors/MessageQueueElement.msg:()Ljava/lang/Object;
const #81 = Asciz	session;
const #82 = Asciz	()Lscala/actors/OutputChannel;;
const #83 = NameAndType	#81:#82;//  session:()Lscala/actors/OutputChannel;
const #84 = Method	#76.#83;	//  scala/actors/MessageQueueElement.session:()Lscala/actors/OutputChannel;
const #85 = Asciz	(Ljava/lang/Object;Ljava/lang/Object;)V;
const #86 = NameAndType	#26:#85;//  "<init>":(Ljava/lang/Object;Ljava/lang/Object;)V
const #87 = Method	#74.#86;	//  scala/Tuple2."<init>":(Ljava/lang/Object;Ljava/lang/Object;)V
const #88 = Asciz	resumeReceiver;
const #89 = Asciz	(Lscala/Tuple2;Z)V;
const #90 = NameAndType	#88:#89;//  resumeReceiver:(Lscala/Tuple2;Z)V
const #91 = InterfaceMethod	#14.#90;	//  scala/actors/ReplyReactor.resumeReceiver:(Lscala/Tuple2;Z)V
const #92 = Asciz	java/lang/Throwable;
const #93 = class	#92;	//  java/lang/Throwable
const #94 = Asciz	startMbox;
const #95 = Asciz	Lscala/actors/MessageQueue;;
const #96 = Asciz	handlesMessage$1;
const #97 = Asciz	Lscala/Function1;;
const #98 = Asciz	resumeOnSameThread;
const #99 = Asciz	Z;
const #100 = Asciz	tmpMbox;
const #101 = Asciz	qel;
const #102 = Asciz	Lscala/actors/MessageQueueElement;;
const #103 = Asciz	done;
const #104 = Asciz	(Lscala/actors/ReplyReactor;Lscala/Tuple2;Z)V;
const #105 = Asciz	scala/collection/immutable/List$;
const #106 = class	#105;	//  scala/collection/immutable/List$
const #107 = Asciz	Lscala/collection/immutable/List$;;
const #108 = NameAndType	#9:#107;//  MODULE$:Lscala/collection/immutable/List$;
const #109 = Field	#106.#108;	//  scala/collection/immutable/List$.MODULE$:Lscala/collection/immutable/List$;
const #110 = Asciz	scala/Predef$;
const #111 = class	#110;	//  scala/Predef$
const #112 = Asciz	Lscala/Predef$;;
const #113 = NameAndType	#9:#112;//  MODULE$:Lscala/Predef$;
const #114 = Field	#111.#113;	//  scala/Predef$.MODULE$:Lscala/Predef$;
const #115 = Asciz	scala/actors/OutputChannel;
const #116 = class	#115;	//  scala/actors/OutputChannel
const #117 = Asciz	_2;
const #118 = NameAndType	#117:#78;//  _2:()Ljava/lang/Object;
const #119 = Method	#74.#118;	//  scala/Tuple2._2:()Ljava/lang/Object;
const #120 = Asciz	[Ljava/lang/Object;;
const #121 = class	#120;	//  "[Ljava/lang/Object;"
const #122 = Asciz	wrapRefArray;
const #123 = Asciz	([Ljava/lang/Object;)Lscala/collection/mutable/WrappedArray;;
const #124 = NameAndType	#122:#123;//  wrapRefArray:([Ljava/lang/Object;)Lscala/collection/mutable/WrappedArray;
const #125 = Method	#111.#124;	//  scala/Predef$.wrapRefArray:([Ljava/lang/Object;)Lscala/collection/mutable/WrappedArray;
const #126 = Asciz	apply;
const #127 = Asciz	(Lscala/collection/Seq;)Lscala/collection/immutable/List;;
const #128 = NameAndType	#126:#127;//  apply:(Lscala/collection/Seq;)Lscala/collection/immutable/List;
const #129 = Method	#106.#128;	//  scala/collection/immutable/List$.apply:(Lscala/collection/Seq;)Lscala/collection/immutable/List;
const #130 = Asciz	continuation;
const #131 = Asciz	()Lscala/PartialFunction;;
const #132 = NameAndType	#130:#131;//  continuation:()Lscala/PartialFunction;
const #133 = InterfaceMethod	#37.#132;	//  scala/actors/Reactor.continuation:()Lscala/PartialFunction;
const #134 = Asciz	_1;
const #135 = NameAndType	#134:#78;//  _1:()Ljava/lang/Object;
const #136 = Method	#74.#135;	//  scala/Tuple2._1:()Ljava/lang/Object;
const #137 = Asciz	scala/Function1;
const #138 = class	#137;	//  scala/Function1
const #139 = Asciz	(Ljava/lang/Object;)Ljava/lang/Object;;
const #140 = NameAndType	#126:#139;//  apply:(Ljava/lang/Object;)Ljava/lang/Object;
const #141 = InterfaceMethod	#138.#140;	//  scala/Function1.apply:(Ljava/lang/Object;)Ljava/lang/Object;
const #142 = Asciz	scheduleActor;
const #143 = Asciz	(Lscala/PartialFunction;Ljava/lang/Object;)V;
const #144 = NameAndType	#142:#143;//  scheduleActor:(Lscala/PartialFunction;Ljava/lang/Object;)V
const #145 = InterfaceMethod	#37.#144;	//  scala/actors/Reactor.scheduleActor:(Lscala/PartialFunction;Ljava/lang/Object;)V
const #146 = Asciz	item;
const #147 = Asciz	Lscala/Tuple2;;
const #148 = Asciz	onSameThread;
const #149 = Asciz	forward;
const #150 = Asciz	(Lscala/actors/ReplyReactor;Ljava/lang/Object;)V;
const #151 = Asciz	scala/actors/Actor$;
const #152 = class	#151;	//  scala/actors/Actor$
const #153 = Asciz	Lscala/actors/Actor$;;
const #154 = NameAndType	#9:#153;//  MODULE$:Lscala/actors/Actor$;
const #155 = Field	#152.#154;	//  scala/actors/Actor$.MODULE$:Lscala/actors/Actor$;
const #156 = Asciz	sender;
const #157 = NameAndType	#156:#82;//  sender:()Lscala/actors/OutputChannel;
const #158 = Method	#152.#157;	//  scala/actors/Actor$.sender:()Lscala/actors/OutputChannel;
const #159 = Asciz	send;
const #160 = Asciz	(Ljava/lang/Object;Lscala/actors/OutputChannel;)V;
const #161 = NameAndType	#159:#160;//  send:(Ljava/lang/Object;Lscala/actors/OutputChannel;)V
const #162 = InterfaceMethod	#37.#161;	//  scala/actors/Reactor.send:(Ljava/lang/Object;Lscala/actors/OutputChannel;)V
const #163 = Asciz	Ljava/lang/Object;;
const #164 = Asciz	$bang;
const #165 = Asciz	scheduler;
const #166 = Asciz	()Lscala/actors/IScheduler;;
const #167 = NameAndType	#165:#166;//  scheduler:()Lscala/actors/IScheduler;
const #168 = InterfaceMethod	#37.#167;	//  scala/actors/Reactor.scheduler:()Lscala/actors/IScheduler;
const #169 = Asciz	rawSelf;
const #170 = Asciz	(Lscala/actors/IScheduler;)Lscala/actors/Reactor;;
const #171 = NameAndType	#169:#170;//  rawSelf:(Lscala/actors/IScheduler;)Lscala/actors/Reactor;
const #172 = Method	#152.#171;	//  scala/actors/Actor$.rawSelf:(Lscala/actors/IScheduler;)Lscala/actors/Reactor;
const #173 = Asciz	reply;
const #174 = InterfaceMethod	#14.#157;	//  scala/actors/ReplyReactor.sender:()Lscala/actors/OutputChannel;
const #175 = Asciz	(Ljava/lang/Object;)V;
const #176 = NameAndType	#164:#175;//  $bang:(Ljava/lang/Object;)V
const #177 = InterfaceMethod	#116.#176;	//  scala/actors/OutputChannel.$bang:(Ljava/lang/Object;)V
const #178 = Asciz	(Lscala/actors/ReplyReactor;)Lscala/actors/OutputChannel;;
const #179 = Asciz	senders;
const #180 = Asciz	()Lscala/collection/immutable/List;;
const #181 = NameAndType	#179:#180;//  senders:()Lscala/collection/immutable/List;
const #182 = InterfaceMethod	#14.#181;	//  scala/actors/ReplyReactor.senders:()Lscala/collection/immutable/List;
const #183 = Asciz	scala/collection/IterableLike;
const #184 = class	#183;	//  scala/collection/IterableLike
const #185 = Asciz	head;
const #186 = NameAndType	#185:#78;//  head:()Ljava/lang/Object;
const #187 = InterfaceMethod	#184.#186;	//  scala/collection/IterableLike.head:()Ljava/lang/Object;
const #188 = Asciz	Scala;
const #189 = Asciz	InnerClasses;
const #190 = Asciz	$anonfun$1;
const #191 = Asciz	$anonfun$searchMailbox$1;
const #192 = Asciz	scala/actors/ReplyReactor$class;
const #193 = class	#192;	//  scala/actors/ReplyReactor$class
const #194 = Asciz	java/lang/Object;
const #195 = class	#194;	//  java/lang/Object

{
public static void $init$(scala.actors.ReplyReactor);
  Code:
   Stack=2, Locals=1, Args_size=1
   0:	aload_0
   1:	getstatic	#12; //Field scala/collection/immutable/Nil$.MODULE$:Lscala/collection/immutable/Nil$;
   4:	invokeinterface	#18,  2; //InterfaceMethod scala/actors/ReplyReactor.senders_$eq:(Lscala/collection/immutable/List;)V
   9:	return
  LineNumberTable: 
   line 28: 0
   line 29: 1
   line 28: 4

  LocalVariableTable: 
   Start  Length  Slot  Name   Signature
   0      10      0    $this       Lscala/actors/ReplyReactor;


public static void searchMailbox(scala.actors.ReplyReactor, scala.actors.MessageQueue, scala.Function1, boolean);
  Code:
   Stack=5, Locals=7, Args_size=4
   0:	aload_1
   1:	astore	4
   3:	iconst_0
   4:	istore	6
   6:	iload	6
   8:	ifeq	12
   11:	return
   12:	aload	4
   14:	new	#25; //class scala/actors/ReplyReactor$$anonfun$1
   17:	dup
   18:	aload_0
   19:	aload_2
   20:	invokespecial	#29; //Method scala/actors/ReplyReactor$$anonfun$1."<init>":(Lscala/actors/ReplyReactor;Lscala/Function1;)V
   23:	invokevirtual	#35; //Method scala/actors/MessageQueue.extractFirst:(Lscala/Function2;)Lscala/actors/MessageQueueElement;
   26:	astore	5
   28:	aload	4
   30:	aload_0
   31:	invokeinterface	#41,  1; //InterfaceMethod scala/actors/Reactor.mailbox:()Lscala/actors/MessageQueue;
   36:	if_acmpeq	52
   39:	aload	4
   41:	new	#43; //class scala/actors/ReplyReactor$$anonfun$searchMailbox$1
   44:	dup
   45:	aload_0
   46:	invokespecial	#45; //Method scala/actors/ReplyReactor$$anonfun$searchMailbox$1."<init>":(Lscala/actors/ReplyReactor;)V
   49:	invokevirtual	#49; //Method scala/actors/MessageQueue.foreach:(Lscala/Function2;)V
   52:	aload	5
   54:	ifnonnull	110
   57:	aload_0
   58:	dup
   59:	pop
   60:	monitorenter
   61:	aload_0
   62:	invokeinterface	#53,  1; //InterfaceMethod scala/actors/Reactor.sendBuffer:()Lscala/collection/mutable/Queue;
   67:	invokevirtual	#59; //Method scala/collection/mutable/Queue.isEmpty:()Z
   70:	ifeq	86
   73:	aload_0
   74:	aload_2
   75:	invokeinterface	#63,  2; //InterfaceMethod scala/actors/Reactor.waitingFor_$eq:(Lscala/Function1;)V
   80:	iconst_1
   81:	istore	6
   83:	goto	105
   86:	new	#31; //class scala/actors/MessageQueue
   89:	dup
   90:	ldc	#65; //String Temp
   92:	invokespecial	#68; //Method scala/actors/MessageQueue."<init>":(Ljava/lang/String;)V
   95:	astore	4
   97:	aload_0
   98:	aload	4
   100:	invokeinterface	#72,  2; //InterfaceMethod scala/actors/Reactor.drainSendBuffer:(Lscala/actors/MessageQueue;)V
   105:	aload_0
   106:	monitorexit
   107:	goto	137
   110:	aload_0
   111:	new	#74; //class scala/Tuple2
   114:	dup
   115:	aload	5
   117:	invokevirtual	#80; //Method scala/actors/MessageQueueElement.msg:()Ljava/lang/Object;
   120:	aload	5
   122:	invokevirtual	#84; //Method scala/actors/MessageQueueElement.session:()Lscala/actors/OutputChannel;
   125:	invokespecial	#87; //Method scala/Tuple2."<init>":(Ljava/lang/Object;Ljava/lang/Object;)V
   128:	iload_3
   129:	invokeinterface	#91,  3; //InterfaceMethod scala/actors/ReplyReactor.resumeReceiver:(Lscala/Tuple2;Z)V
   134:	iconst_1
   135:	istore	6
   137:	goto	6
   140:	aload_0
   141:	monitorexit
   142:	athrow
  Exception table:
   from   to  target type
    61   110   140   Class java/lang/Throwable

  LineNumberTable: 
   line 68: 0
   line 69: 3
   line 70: 6
   line 67: 11
   line 71: 12
   line 75: 28
   line 76: 39
   line 77: 52
   line 78: 57
   line 80: 61
   line 85: 73
   line 86: 80
   line 80: 83
   line 81: 86
   line 82: 97
   line 90: 105
   line 78: 106
   line 90: 110
   line 91: 134
   line 77: 137
   line 78: 141

  LocalVariableTable: 
   Start  Length  Slot  Name   Signature
   0      143      0    $this       Lscala/actors/ReplyReactor;
   0      143      1    startMbox       Lscala/actors/MessageQueue;
   0      143      2    handlesMessage$1       Lscala/Function1;
   0      143      3    resumeOnSameThread       Z
   3      140      4    tmpMbox       Lscala/actors/MessageQueue;
   28      109      5    qel       Lscala/actors/MessageQueueElement;
   140      3      5    qel       Lscala/actors/MessageQueueElement;
   6      137      6    done       Z


public static void resumeReceiver(scala.actors.ReplyReactor, scala.Tuple2, boolean);
  Code:
   Stack=7, Locals=3, Args_size=3
   0:	aload_0
   1:	getstatic	#109; //Field scala/collection/immutable/List$.MODULE$:Lscala/collection/immutable/List$;
   4:	getstatic	#114; //Field scala/Predef$.MODULE$:Lscala/Predef$;
   7:	iconst_1
   8:	anewarray	#116; //class scala/actors/OutputChannel
   11:	dup
   12:	iconst_0
   13:	aload_1
   14:	invokevirtual	#119; //Method scala/Tuple2._2:()Ljava/lang/Object;
   17:	checkcast	#116; //class scala/actors/OutputChannel
   20:	aastore
   21:	checkcast	#121; //class "[Ljava/lang/Object;"
   24:	invokevirtual	#125; //Method scala/Predef$.wrapRefArray:([Ljava/lang/Object;)Lscala/collection/mutable/WrappedArray;
   27:	invokevirtual	#129; //Method scala/collection/immutable/List$.apply:(Lscala/collection/Seq;)Lscala/collection/immutable/List;
   30:	invokeinterface	#18,  2; //InterfaceMethod scala/actors/ReplyReactor.senders_$eq:(Lscala/collection/immutable/List;)V
   35:	iload_2
   36:	ifeq	58
   39:	aload_0
   40:	invokeinterface	#133,  1; //InterfaceMethod scala/actors/Reactor.continuation:()Lscala/PartialFunction;
   45:	aload_1
   46:	invokevirtual	#136; //Method scala/Tuple2._1:()Ljava/lang/Object;
   49:	invokeinterface	#141,  2; //InterfaceMethod scala/Function1.apply:(Ljava/lang/Object;)Ljava/lang/Object;
   54:	pop
   55:	goto	74
   58:	aload_0
   59:	aload_0
   60:	invokeinterface	#133,  1; //InterfaceMethod scala/actors/Reactor.continuation:()Lscala/PartialFunction;
   65:	aload_1
   66:	invokevirtual	#136; //Method scala/Tuple2._1:()Ljava/lang/Object;
   69:	invokeinterface	#145,  3; //InterfaceMethod scala/actors/Reactor.scheduleActor:(Lscala/PartialFunction;Ljava/lang/Object;)V
   74:	return
  LineNumberTable: 
   line 56: 0
   line 58: 35
   line 59: 39
   line 61: 58
   line 55: 74

  LocalVariableTable: 
   Start  Length  Slot  Name   Signature
   0      75      0    $this       Lscala/actors/ReplyReactor;
   0      75      1    item       Lscala/Tuple2;
   0      75      2    onSameThread       Z


public static void forward(scala.actors.ReplyReactor, java.lang.Object);
  Code:
   Stack=3, Locals=2, Args_size=2
   0:	aload_0
   1:	aload_1
   2:	getstatic	#155; //Field scala/actors/Actor$.MODULE$:Lscala/actors/Actor$;
   5:	invokevirtual	#158; //Method scala/actors/Actor$.sender:()Lscala/actors/OutputChannel;
   8:	invokeinterface	#162,  3; //InterfaceMethod scala/actors/Reactor.send:(Ljava/lang/Object;Lscala/actors/OutputChannel;)V
   13:	return
  LineNumberTable: 
   line 52: 0

  LocalVariableTable: 
   Start  Length  Slot  Name   Signature
   0      14      0    $this       Lscala/actors/ReplyReactor;
   0      14      1    msg       Ljava/lang/Object;


public static void $bang(scala.actors.ReplyReactor, java.lang.Object);
  Code:
   Stack=4, Locals=2, Args_size=2
   0:	aload_0
   1:	aload_1
   2:	getstatic	#155; //Field scala/actors/Actor$.MODULE$:Lscala/actors/Actor$;
   5:	aload_0
   6:	invokeinterface	#168,  1; //InterfaceMethod scala/actors/Reactor.scheduler:()Lscala/actors/IScheduler;
   11:	invokevirtual	#172; //Method scala/actors/Actor$.rawSelf:(Lscala/actors/IScheduler;)Lscala/actors/Reactor;
   14:	invokeinterface	#162,  3; //InterfaceMethod scala/actors/Reactor.send:(Ljava/lang/Object;Lscala/actors/OutputChannel;)V
   19:	return
  LineNumberTable: 
   line 45: 0

  LocalVariableTable: 
   Start  Length  Slot  Name   Signature
   0      20      0    $this       Lscala/actors/ReplyReactor;
   0      20      1    msg       Ljava/lang/Object;


public static void reply(scala.actors.ReplyReactor, java.lang.Object);
  Code:
   Stack=2, Locals=2, Args_size=2
   0:	aload_0
   1:	invokeinterface	#174,  1; //InterfaceMethod scala/actors/ReplyReactor.sender:()Lscala/actors/OutputChannel;
   6:	aload_1
   7:	invokeinterface	#177,  2; //InterfaceMethod scala/actors/OutputChannel.$bang:(Ljava/lang/Object;)V
   12:	return
  LineNumberTable: 
   line 38: 0

  LocalVariableTable: 
   Start  Length  Slot  Name   Signature
   0      13      0    $this       Lscala/actors/ReplyReactor;
   0      13      1    msg       Ljava/lang/Object;


public static scala.actors.OutputChannel sender(scala.actors.ReplyReactor);
  Code:
   Stack=1, Locals=1, Args_size=1
   0:	aload_0
   1:	invokeinterface	#182,  1; //InterfaceMethod scala/actors/ReplyReactor.senders:()Lscala/collection/immutable/List;
   6:	invokeinterface	#187,  1; //InterfaceMethod scala/collection/IterableLike.head:()Ljava/lang/Object;
   11:	checkcast	#116; //class scala/actors/OutputChannel
   14:	areturn
  LineNumberTable: 
   line 32: 0

  LocalVariableTable: 
   Start  Length  Slot  Name   Signature
   0      15      0    $this       Lscala/actors/ReplyReactor;


}

