Compiled from "ReplyableReactor.scala"
public abstract class scala.actors.ReplyableReactor$class extends java.lang.Object
  SourceFile: "ReplyableReactor.scala"
  Scala: length = 0x
   
  InnerClass: 
   public final #103= #40 of #72; //$anon$3=class scala/actors/ReplyableReactor$$anon$3 of class scala/actors/ReplyableReactor
   public final #104= #51 of #72; //$anon$1=class scala/actors/ReplyableReactor$$anon$1 of class scala/actors/ReplyableReactor
   public final #105= #79 of #72; //$anon$2=class scala/actors/ReplyableReactor$$anon$2 of class scala/actors/ReplyableReactor
   public final #106= #68 of #72; //$anonfun$$bang$bang$1=class scala/actors/ReplyableReactor$$anonfun$$bang$bang$1 of class scala/actors/ReplyableReactor
  minor version: 0
  major version: 49
  Constant pool:
const #1 = Asciz	SourceFile;
const #2 = Asciz	ReplyableReactor.scala;
const #3 = Asciz	$init$;
const #4 = Asciz	(Lscala/actors/ReplyableReactor;)V;
const #5 = Asciz	Code;
const #6 = Asciz	LineNumberTable;
const #7 = Asciz	$this;
const #8 = Asciz	Lscala/actors/ReplyableReactor;;
const #9 = Asciz	LocalVariableTable;
const #10 = Asciz	$bang$bang;
const #11 = Asciz	(Lscala/actors/ReplyableReactor;Ljava/lang/Object;Lscala/PartialFunction;)Lscala/actors/Future;;
const #12 = Asciz	scala/actors/Actor$;
const #13 = class	#12;	//  scala/actors/Actor$
const #14 = Asciz	MODULE$;
const #15 = Asciz	Lscala/actors/Actor$;;
const #16 = NameAndType	#14:#15;//  MODULE$:Lscala/actors/Actor$;
const #17 = Field	#13.#16;	//  scala/actors/Actor$.MODULE$:Lscala/actors/Actor$;
const #18 = Asciz	scala/actors/Reactor;
const #19 = class	#18;	//  scala/actors/Reactor
const #20 = Asciz	scheduler;
const #21 = Asciz	()Lscala/actors/IScheduler;;
const #22 = NameAndType	#20:#21;//  scheduler:()Lscala/actors/IScheduler;
const #23 = InterfaceMethod	#19.#22;	//  scala/actors/Reactor.scheduler:()Lscala/actors/IScheduler;
const #24 = Asciz	rawSelf;
const #25 = Asciz	(Lscala/actors/IScheduler;)Lscala/actors/Reactor;;
const #26 = NameAndType	#24:#25;//  rawSelf:(Lscala/actors/IScheduler;)Lscala/actors/Reactor;
const #27 = Method	#13.#26;	//  scala/actors/Actor$.rawSelf:(Lscala/actors/IScheduler;)Lscala/actors/Reactor;
const #28 = Asciz	scala/actors/Channel;
const #29 = class	#28;	//  scala/actors/Channel
const #30 = Asciz	<init>;
const #31 = Asciz	(Lscala/actors/Reactor;)V;
const #32 = NameAndType	#30:#31;//  "<init>":(Lscala/actors/Reactor;)V
const #33 = Method	#29.#32;	//  scala/actors/Channel."<init>":(Lscala/actors/Reactor;)V
const #34 = Asciz	scala/concurrent/SyncVar;
const #35 = class	#34;	//  scala/concurrent/SyncVar
const #36 = Asciz	()V;
const #37 = NameAndType	#30:#36;//  "<init>":()V
const #38 = Method	#35.#37;	//  scala/concurrent/SyncVar."<init>":()V
const #39 = Asciz	scala/actors/ReplyableReactor$$anon$3;
const #40 = class	#39;	//  scala/actors/ReplyableReactor$$anon$3
const #41 = Asciz	(Lscala/actors/ReplyableReactor;Lscala/PartialFunction;Lscala/actors/Reactor;Lscala/actors/Channel;Lscala/concurrent/SyncVar;)V;
const #42 = NameAndType	#30:#41;//  "<init>":(Lscala/actors/ReplyableReactor;Lscala/PartialFunction;Lscala/actors/Reactor;Lscala/actors/Channel;Lscala/concurrent/SyncVar;)V
const #43 = Method	#40.#42;	//  scala/actors/ReplyableReactor$$anon$3."<init>":(Lscala/actors/ReplyableReactor;Lscala/PartialFunction;Lscala/actors/Reactor;Lscala/actors/Channel;Lscala/concurrent/SyncVar;)V
const #44 = Asciz	scala/actors/OutputChannel;
const #45 = class	#44;	//  scala/actors/OutputChannel
const #46 = Asciz	send;
const #47 = Asciz	(Ljava/lang/Object;Lscala/actors/OutputChannel;)V;
const #48 = NameAndType	#46:#47;//  send:(Ljava/lang/Object;Lscala/actors/OutputChannel;)V
const #49 = InterfaceMethod	#19.#48;	//  scala/actors/Reactor.send:(Ljava/lang/Object;Lscala/actors/OutputChannel;)V
const #50 = Asciz	scala/actors/ReplyableReactor$$anon$1;
const #51 = class	#50;	//  scala/actors/ReplyableReactor$$anon$1
const #52 = Asciz	(Lscala/actors/ReplyableReactor;Lscala/actors/Channel;Lscala/concurrent/SyncVar;)V;
const #53 = NameAndType	#30:#52;//  "<init>":(Lscala/actors/ReplyableReactor;Lscala/actors/Channel;Lscala/concurrent/SyncVar;)V
const #54 = Method	#51.#53;	//  scala/actors/ReplyableReactor$$anon$1."<init>":(Lscala/actors/ReplyableReactor;Lscala/actors/Channel;Lscala/concurrent/SyncVar;)V
const #55 = Asciz	msg;
const #56 = Asciz	Ljava/lang/Object;;
const #57 = Asciz	f$1;
const #58 = Asciz	Lscala/PartialFunction;;
const #59 = Asciz	myself$2;
const #60 = Asciz	Lscala/actors/Reactor;;
const #61 = Asciz	ftch$1;
const #62 = Asciz	Lscala/actors/Channel;;
const #63 = Asciz	res$2;
const #64 = Asciz	Lscala/concurrent/SyncVar;;
const #65 = Asciz	out;
const #66 = Asciz	(Lscala/actors/ReplyableReactor;Ljava/lang/Object;)Lscala/actors/Future;;
const #67 = Asciz	scala/actors/ReplyableReactor$$anonfun$$bang$bang$1;
const #68 = class	#67;	//  scala/actors/ReplyableReactor$$anonfun$$bang$bang$1
const #69 = NameAndType	#30:#4;//  "<init>":(Lscala/actors/ReplyableReactor;)V
const #70 = Method	#68.#69;	//  scala/actors/ReplyableReactor$$anonfun$$bang$bang$1."<init>":(Lscala/actors/ReplyableReactor;)V
const #71 = Asciz	scala/actors/ReplyableReactor;
const #72 = class	#71;	//  scala/actors/ReplyableReactor
const #73 = Asciz	(Ljava/lang/Object;Lscala/PartialFunction;)Lscala/actors/Future;;
const #74 = NameAndType	#10:#73;//  $bang$bang:(Ljava/lang/Object;Lscala/PartialFunction;)Lscala/actors/Future;
const #75 = InterfaceMethod	#72.#74;	//  scala/actors/ReplyableReactor.$bang$bang:(Ljava/lang/Object;Lscala/PartialFunction;)Lscala/actors/Future;
const #76 = Asciz	$bang$qmark;
const #77 = Asciz	(Lscala/actors/ReplyableReactor;JLjava/lang/Object;)Lscala/Option;;
const #78 = Asciz	scala/actors/ReplyableReactor$$anon$2;
const #79 = class	#78;	//  scala/actors/ReplyableReactor$$anon$2
const #80 = Asciz	(Lscala/actors/ReplyableReactor;Lscala/actors/Reactor;Lscala/concurrent/SyncVar;)V;
const #81 = NameAndType	#30:#80;//  "<init>":(Lscala/actors/ReplyableReactor;Lscala/actors/Reactor;Lscala/concurrent/SyncVar;)V
const #82 = Method	#79.#81;	//  scala/actors/ReplyableReactor$$anon$2."<init>":(Lscala/actors/ReplyableReactor;Lscala/actors/Reactor;Lscala/concurrent/SyncVar;)V
const #83 = Asciz	get;
const #84 = Asciz	(J)Lscala/Option;;
const #85 = NameAndType	#83:#84;//  get:(J)Lscala/Option;
const #86 = Method	#35.#85;	//  scala/concurrent/SyncVar.get:(J)Lscala/Option;
const #87 = Asciz	msec;
const #88 = Asciz	J;
const #89 = Asciz	myself$1;
const #90 = Asciz	res$1;
const #91 = Asciz	(Lscala/actors/ReplyableReactor;Ljava/lang/Object;)Ljava/lang/Object;;
const #92 = Asciz	(Ljava/lang/Object;)Lscala/actors/Future;;
const #93 = NameAndType	#10:#92;//  $bang$bang:(Ljava/lang/Object;)Lscala/actors/Future;
const #94 = InterfaceMethod	#72.#93;	//  scala/actors/ReplyableReactor.$bang$bang:(Ljava/lang/Object;)Lscala/actors/Future;
const #95 = Asciz	scala/Function0;
const #96 = class	#95;	//  scala/Function0
const #97 = Asciz	apply;
const #98 = Asciz	()Ljava/lang/Object;;
const #99 = NameAndType	#97:#98;//  apply:()Ljava/lang/Object;
const #100 = InterfaceMethod	#96.#99;	//  scala/Function0.apply:()Ljava/lang/Object;
const #101 = Asciz	Scala;
const #102 = Asciz	InnerClasses;
const #103 = Asciz	$anon$3;
const #104 = Asciz	$anon$1;
const #105 = Asciz	$anon$2;
const #106 = Asciz	$anonfun$$bang$bang$1;
const #107 = Asciz	scala/actors/ReplyableReactor$class;
const #108 = class	#107;	//  scala/actors/ReplyableReactor$class
const #109 = Asciz	java/lang/Object;
const #110 = class	#109;	//  java/lang/Object

{
public static void $init$(scala.actors.ReplyableReactor);
  Code:
   Stack=0, Locals=1, Args_size=1
   0:	return
  LineNumberTable: 
   line 20: 0

  LocalVariableTable: 
   Start  Length  Slot  Name   Signature
   0      1      0    $this       Lscala/actors/ReplyableReactor;


public static scala.actors.Future $bang$bang(scala.actors.ReplyableReactor, java.lang.Object, scala.PartialFunction);
  Code:
   Stack=7, Locals=7, Args_size=3
   0:	getstatic	#17; //Field scala/actors/Actor$.MODULE$:Lscala/actors/Actor$;
   3:	aload_0
   4:	checkcast	#19; //class scala/actors/Reactor
   7:	invokeinterface	#23,  1; //InterfaceMethod scala/actors/Reactor.scheduler:()Lscala/actors/IScheduler;
   12:	invokevirtual	#27; //Method scala/actors/Actor$.rawSelf:(Lscala/actors/IScheduler;)Lscala/actors/Reactor;
   15:	astore_3
   16:	new	#29; //class scala/actors/Channel
   19:	dup
   20:	aload_3
   21:	invokespecial	#33; //Method scala/actors/Channel."<init>":(Lscala/actors/Reactor;)V
   24:	astore	4
   26:	new	#35; //class scala/concurrent/SyncVar
   29:	dup
   30:	invokespecial	#38; //Method scala/concurrent/SyncVar."<init>":()V
   33:	astore	5
   35:	new	#40; //class scala/actors/ReplyableReactor$$anon$3
   38:	dup
   39:	aload_0
   40:	aload_2
   41:	aload_3
   42:	aload	4
   44:	aload	5
   46:	invokespecial	#43; //Method scala/actors/ReplyableReactor$$anon$3."<init>":(Lscala/actors/ReplyableReactor;Lscala/PartialFunction;Lscala/actors/Reactor;Lscala/actors/Channel;Lscala/concurrent/SyncVar;)V
   49:	astore	6
   51:	aload_0
   52:	checkcast	#19; //class scala/actors/Reactor
   55:	aload_1
   56:	aload	6
   58:	checkcast	#45; //class scala/actors/OutputChannel
   61:	invokeinterface	#49,  3; //InterfaceMethod scala/actors/Reactor.send:(Ljava/lang/Object;Lscala/actors/OutputChannel;)V
   66:	new	#51; //class scala/actors/ReplyableReactor$$anon$1
   69:	dup
   70:	aload_0
   71:	aload	4
   73:	aload	5
   75:	invokespecial	#54; //Method scala/actors/ReplyableReactor$$anon$1."<init>":(Lscala/actors/ReplyableReactor;Lscala/actors/Channel;Lscala/concurrent/SyncVar;)V
   78:	areturn
  LineNumberTable: 
   line 74: 0
   line 75: 16
   line 76: 26
   line 78: 35
   line 95: 51
   line 97: 66

  LocalVariableTable: 
   Start  Length  Slot  Name   Signature
   0      79      0    $this       Lscala/actors/ReplyableReactor;
   0      79      1    msg       Ljava/lang/Object;
   0      79      2    f$1       Lscala/PartialFunction;
   16      62      3    myself$2       Lscala/actors/Reactor;
   26      52      4    ftch$1       Lscala/actors/Channel;
   35      43      5    res$2       Lscala/concurrent/SyncVar;
   51      27      6    out       Ljava/lang/Object;


public static scala.actors.Future $bang$bang(scala.actors.ReplyableReactor, java.lang.Object);
  Code:
   Stack=5, Locals=2, Args_size=2
   0:	aload_0
   1:	aload_1
   2:	new	#68; //class scala/actors/ReplyableReactor$$anonfun$$bang$bang$1
   5:	dup
   6:	aload_0
   7:	invokespecial	#70; //Method scala/actors/ReplyableReactor$$anonfun$$bang$bang$1."<init>":(Lscala/actors/ReplyableReactor;)V
   10:	invokeinterface	#75,  3; //InterfaceMethod scala/actors/ReplyableReactor.$bang$bang:(Ljava/lang/Object;Lscala/PartialFunction;)Lscala/actors/Future;
   15:	areturn
  LineNumberTable: 
   line 64: 0

  LocalVariableTable: 
   Start  Length  Slot  Name   Signature
   0      16      0    $this       Lscala/actors/ReplyableReactor;
   0      16      1    msg       Ljava/lang/Object;


public static scala.Option $bang$qmark(scala.actors.ReplyableReactor, long, java.lang.Object);
  Code:
   Stack=5, Locals=7, Args_size=3
   0:	getstatic	#17; //Field scala/actors/Actor$.MODULE$:Lscala/actors/Actor$;
   3:	aload_0
   4:	checkcast	#19; //class scala/actors/Reactor
   7:	invokeinterface	#23,  1; //InterfaceMethod scala/actors/Reactor.scheduler:()Lscala/actors/IScheduler;
   12:	invokevirtual	#27; //Method scala/actors/Actor$.rawSelf:(Lscala/actors/IScheduler;)Lscala/actors/Reactor;
   15:	astore	4
   17:	new	#35; //class scala/concurrent/SyncVar
   20:	dup
   21:	invokespecial	#38; //Method scala/concurrent/SyncVar."<init>":()V
   24:	astore	5
   26:	new	#79; //class scala/actors/ReplyableReactor$$anon$2
   29:	dup
   30:	aload_0
   31:	aload	4
   33:	aload	5
   35:	invokespecial	#82; //Method scala/actors/ReplyableReactor$$anon$2."<init>":(Lscala/actors/ReplyableReactor;Lscala/actors/Reactor;Lscala/concurrent/SyncVar;)V
   38:	astore	6
   40:	aload_0
   41:	checkcast	#19; //class scala/actors/Reactor
   44:	aload_3
   45:	aload	6
   47:	checkcast	#45; //class scala/actors/OutputChannel
   50:	invokeinterface	#49,  3; //InterfaceMethod scala/actors/Reactor.send:(Ljava/lang/Object;Lscala/actors/OutputChannel;)V
   55:	aload	5
   57:	lload_1
   58:	invokevirtual	#86; //Method scala/concurrent/SyncVar.get:(J)Lscala/Option;
   61:	areturn
  LineNumberTable: 
   line 43: 0
   line 44: 17
   line 45: 26
   line 55: 40
   line 56: 55

  LocalVariableTable: 
   Start  Length  Slot  Name   Signature
   0      62      0    $this       Lscala/actors/ReplyableReactor;
   0      62      1    msec       J
   0      62      3    msg       Ljava/lang/Object;
   17      44      4    myself$1       Lscala/actors/Reactor;
   26      35      5    res$1       Lscala/concurrent/SyncVar;
   40      21      6    out       Ljava/lang/Object;


public static java.lang.Object $bang$qmark(scala.actors.ReplyableReactor, java.lang.Object);
  Code:
   Stack=2, Locals=2, Args_size=2
   0:	aload_0
   1:	aload_1
   2:	invokeinterface	#94,  2; //InterfaceMethod scala/actors/ReplyableReactor.$bang$bang:(Ljava/lang/Object;)Lscala/actors/Future;
   7:	invokeinterface	#100,  1; //InterfaceMethod scala/Function0.apply:()Ljava/lang/Object;
   12:	areturn
  LineNumberTable: 
   line 31: 0

  LocalVariableTable: 
   Start  Length  Slot  Name   Signature
   0      13      0    $this       Lscala/actors/ReplyableReactor;
   0      13      1    msg       Ljava/lang/Object;


}

