Compiled from "ReplyReactor.scala"
public final class scala.actors.ReplyReactor$$anonfun$1 extends java.lang.Object implements scala.Function2,scala.ScalaObject,java.io.Serializable
  SourceFile: "ReplyReactor.scala"
  Scala: length = 0x
   
  InnerClass: 
   public final $anonfun$1=class scala/actors/ReplyReactor$$anonfun$1 of class scala/actors/ReplyReactor
  minor version: 0
  major version: 49
  Constant pool:
Asciz	SourceFile;
Asciz	ReplyReactor.scala;
Asciz	<clinit>;
Asciz	()V;
Asciz	Code;
Asciz	serialVersionUID;
Asciz	J;
Asciz	scala/actors/ReplyReactor$$anonfun$1;
class	scala/actors/ReplyReactor$$anonfun$1
NameAndType	serialVersionUID:J
Field	scala/actors/ReplyReactor$$anonfun$1.serialVersionUID:J
Asciz	handlesMessage$1;
Asciz	Lscala/Function1;;
Asciz	$outer;
Asciz	Lscala/actors/ReplyReactor;;
Asciz	<init>;
Asciz	(Lscala/actors/ReplyReactor;Lscala/Function1;)V;
Asciz	LineNumberTable;
Asciz	java/lang/NullPointerException;
class	java/lang/NullPointerException
NameAndType	"<init>":()V
Method	java/lang/NullPointerException."<init>":()V
NameAndType	$outer:Lscala/actors/ReplyReactor;
Field	scala/actors/ReplyReactor$$anonfun$1.$outer:Lscala/actors/ReplyReactor;
NameAndType	handlesMessage$1:Lscala/Function1;
Field	scala/actors/ReplyReactor$$anonfun$1.handlesMessage$1:Lscala/Function1;
Asciz	java/lang/Object;
class	java/lang/Object
Method	java/lang/Object."<init>":()V
Asciz	scala/Function2$class;
class	scala/Function2$class
Asciz	$init$;
Asciz	(Lscala/Function2;)V;
NameAndType	$init$:(Lscala/Function2;)V
Method	scala/Function2$class.$init$:(Lscala/Function2;)V
Asciz	this;
Asciz	Lscala/actors/ReplyReactor$$anonfun$1;;
Asciz	LocalVariableTable;
Asciz	apply;
Asciz	(Ljava/lang/Object;Ljava/lang/Object;)Ljava/lang/Object;;
Asciz	scala/actors/OutputChannel;
class	scala/actors/OutputChannel
Asciz	(Ljava/lang/Object;Lscala/actors/OutputChannel;)Z;
NameAndType	apply:(Ljava/lang/Object;Lscala/actors/OutputChannel;)Z
Method	scala/actors/ReplyReactor$$anonfun$1.apply:(Ljava/lang/Object;Lscala/actors/OutputChannel;)Z
Asciz	scala/runtime/BoxesRunTime;
class	scala/runtime/BoxesRunTime
Asciz	boxToBoolean;
Asciz	(Z)Ljava/lang/Boolean;;
NameAndType	boxToBoolean:(Z)Ljava/lang/Boolean;
Method	scala/runtime/BoxesRunTime.boxToBoolean:(Z)Ljava/lang/Boolean;
Asciz	v1;
Asciz	Ljava/lang/Object;;
Asciz	v2;
Asciz	scala/collection/immutable/List$;
class	scala/collection/immutable/List$
Asciz	MODULE$;
Asciz	Lscala/collection/immutable/List$;;
NameAndType	MODULE$:Lscala/collection/immutable/List$;
Field	scala/collection/immutable/List$.MODULE$:Lscala/collection/immutable/List$;
Asciz	scala/Predef$;
class	scala/Predef$
Asciz	Lscala/Predef$;;
NameAndType	MODULE$:Lscala/Predef$;
Field	scala/Predef$.MODULE$:Lscala/Predef$;
Asciz	[Ljava/lang/Object;;
class	"[Ljava/lang/Object;"
Asciz	wrapRefArray;
Asciz	([Ljava/lang/Object;)Lscala/collection/mutable/WrappedArray;;
NameAndType	wrapRefArray:([Ljava/lang/Object;)Lscala/collection/mutable/WrappedArray;
Method	scala/Predef$.wrapRefArray:([Ljava/lang/Object;)Lscala/collection/mutable/WrappedArray;
Asciz	(Lscala/collection/Seq;)Lscala/collection/immutable/List;;
NameAndType	apply:(Lscala/collection/Seq;)Lscala/collection/immutable/List;
Method	scala/collection/immutable/List$.apply:(Lscala/collection/Seq;)Lscala/collection/immutable/List;
Asciz	scala/actors/ReplyReactor;
class	scala/actors/ReplyReactor
Asciz	senders_$eq;
Asciz	(Lscala/collection/immutable/List;)V;
NameAndType	senders_$eq:(Lscala/collection/immutable/List;)V
InterfaceMethod	scala/actors/ReplyReactor.senders_$eq:(Lscala/collection/immutable/List;)V
Asciz	scala/Function1;
class	scala/Function1
Asciz	(Ljava/lang/Object;)Ljava/lang/Object;;
NameAndType	apply:(Ljava/lang/Object;)Ljava/lang/Object;
InterfaceMethod	scala/Function1.apply:(Ljava/lang/Object;)Ljava/lang/Object;
Asciz	unboxToBoolean;
Asciz	(Ljava/lang/Object;)Z;
NameAndType	unboxToBoolean:(Ljava/lang/Object;)Z
Method	scala/runtime/BoxesRunTime.unboxToBoolean:(Ljava/lang/Object;)Z
Asciz	msg;
Asciz	replyTo;
Asciz	Lscala/actors/OutputChannel;;
Asciz	(Ljava/lang/Object;Lscala/actors/OutputChannel<Ljava/lang/Object;>;)Z;
Asciz	Signature;
Asciz	curry;
Asciz	()Lscala/Function1;;
Asciz	(Lscala/Function2;)Lscala/Function1;;
NameAndType	curry:(Lscala/Function2;)Lscala/Function1;
Method	scala/Function2$class.curry:(Lscala/Function2;)Lscala/Function1;
Asciz	toString;
Asciz	()Ljava/lang/String;;
Asciz	(Lscala/Function2;)Ljava/lang/String;;
NameAndType	toString:(Lscala/Function2;)Ljava/lang/String;
Method	scala/Function2$class.toString:(Lscala/Function2;)Ljava/lang/String;
Asciz	Scala;
Asciz	InnerClasses;
Asciz	$anonfun$1;
Asciz	scala/Function2;
class	scala/Function2
Asciz	scala/ScalaObject;
class	scala/ScalaObject
Asciz	java/io/Serializable;
class	java/io/Serializable

{
public static final long serialVersionUID;
  Signature: J

private final scala.Function1 handlesMessage$1;
  Signature: Lscala/Function1;

private final scala.actors.ReplyReactor $outer;
  Signature: Lscala/actors/ReplyReactor;

public static {};
  Signature: ()V
  Code:
   Stack=2, Locals=0, Args_size=0
	lconst_0
	putstatic	Field serialVersionUID:J
	return
  Labels:

public scala.actors.ReplyReactor$$anonfun$1(scala.actors.ReplyReactor, scala.Function1);
  Signature: (Lscala/actors/ReplyReactor;Lscala/Function1;)V
  Code:
   Stack=2, Locals=3, Args_size=3
	aload_1
	ifnonnull	l1 // aload_0
	new	class java/lang/NullPointerException
	dup
	invokespecial	Method java/lang/NullPointerException."<init>":()V
	athrow
l1	aload_0
	aload_1
	putfield	Field $outer:Lscala/actors/ReplyReactor;
	aload_0
	aload_2
	putfield	Field handlesMessage$1:Lscala/Function1;
	aload_0
	invokespecial	Method java/lang/Object."<init>":()V
	aload_0
	invokestatic	Method scala/Function2$class.$init$:(Lscala/Function2;)V
	return
  Labels:
   	l1 = 12 // aload_0
  LocalVariableTable: 
   Start  Length  Slot  Name   Signature
   0      31      0    this       Lscala/actors/ReplyReactor$$anonfun$1;
   0      31      1    $outer       Lscala/actors/ReplyReactor;


public final java.lang.Object apply(java.lang.Object, java.lang.Object);
  Signature: (Ljava/lang/Object;Ljava/lang/Object;)Ljava/lang/Object;
  Code:
   Stack=3, Locals=5, Args_size=3
	aload_0
	getfield	Field $outer:Lscala/actors/ReplyReactor;
	astore	4
	aload_0
	aload_1
	aload_2
	checkcast	class scala/actors/OutputChannel
	invokevirtual	Method apply:(Ljava/lang/Object;Lscala/actors/OutputChannel;)Z
	istore_3
	iload_3
	invokestatic	Method scala/runtime/BoxesRunTime.boxToBoolean:(Z)Ljava/lang/Boolean;
	areturn
  Labels:
  LocalVariableTable: 
   Start  Length  Slot  Name   Signature
   0      21      0    this       Lscala/actors/ReplyReactor$$anonfun$1;
   6      15      1    v1       Ljava/lang/Object;
   6      15      2    v2       Ljava/lang/Object;


public final boolean apply(java.lang.Object, scala.actors.OutputChannel);
  Signature: (Ljava/lang/Object;Lscala/actors/OutputChannel;)Z
  Code:
   Stack=7, Locals=4, Args_size=3
	aload_0
	getfield	Field $outer:Lscala/actors/ReplyReactor;
	astore_3
	aload_0
	getfield	Field $outer:Lscala/actors/ReplyReactor;
	getstatic	Field scala/collection/immutable/List$.MODULE$:Lscala/collection/immutable/List$;
	getstatic	Field scala/Predef$.MODULE$:Lscala/Predef$;
	iconst_1
	anewarray	class scala/actors/OutputChannel
	dup
	iconst_0
	aload_2
	aastore
	checkcast	class "[Ljava/lang/Object;"
	invokevirtual	Method scala/Predef$.wrapRefArray:([Ljava/lang/Object;)Lscala/collection/mutable/WrappedArray;
	invokevirtual	Method scala/collection/immutable/List$.apply:(Lscala/collection/Seq;)Lscala/collection/immutable/List;
	invokeinterface	InterfaceMethod scala/actors/ReplyReactor.senders_$eq:(Lscala/collection/immutable/List;)V
	aload_0
	getfield	Field handlesMessage$1:Lscala/Function1;
	aload_1
	invokeinterface	InterfaceMethod scala/Function1.apply:(Ljava/lang/Object;)Ljava/lang/Object;
	invokestatic	Method scala/runtime/BoxesRunTime.unboxToBoolean:(Ljava/lang/Object;)Z
	ireturn
  Labels:
  LocalVariableTable: 
   Start  Length  Slot  Name   Signature
   0      51      0    this       Lscala/actors/ReplyReactor$$anonfun$1;
   5      46      1    msg       Ljava/lang/Object;
   5      46      2    replyTo       Lscala/actors/OutputChannel;

  Signature: length = 0x2
   00 5D 

public scala.Function1 curry();
  Signature: ()Lscala/Function1;
  Code:
   Stack=1, Locals=1, Args_size=1
	aload_0
	invokestatic	Method scala/Function2$class.curry:(Lscala/Function2;)Lscala/Function1;
	areturn
  Labels:

public java.lang.String toString();
  Signature: ()Ljava/lang/String;
  Code:
   Stack=1, Locals=1, Args_size=1
	aload_0
	invokestatic	Method scala/Function2$class.toString:(Lscala/Function2;)Ljava/lang/String;
	areturn
  Labels:

}

