Compiled from "ReplyableActor.scala"
public final class scala.actors.ReplyableActor$$anon$1 extends java.lang.Object implements scala.actors.AbstractActor
  SourceFile: "ReplyableActor.scala"
  Scala: length = 0x
   
  InnerClass: 
   public final #139= #19 of #138; //$anon$1=class scala/actors/ReplyableActor$$anon$1 of class scala/actors/ReplyableActor
  minor version: 0
  major version: 49
  Constant pool:
const #1 = Asciz	SourceFile;
const #2 = Asciz	ReplyableActor.scala;
const #3 = Asciz	exiting;
const #4 = Asciz	Z;
const #5 = Asciz	ftch$2;
const #6 = Asciz	Lscala/actors/Channel;;
const #7 = Asciz	$outer;
const #8 = Asciz	Lscala/actors/ReplyableActor;;
const #9 = Asciz	<init>;
const #10 = Asciz	(Lscala/actors/ReplyableActor;Lscala/actors/Channel;)V;
const #11 = Asciz	Code;
const #12 = Asciz	LineNumberTable;
const #13 = Asciz	java/lang/NullPointerException;
const #14 = class	#13;	//  java/lang/NullPointerException
const #15 = Asciz	()V;
const #16 = NameAndType	#9:#15;//  "<init>":()V
const #17 = Method	#14.#16;	//  java/lang/NullPointerException."<init>":()V
const #18 = Asciz	scala/actors/ReplyableActor$$anon$1;
const #19 = class	#18;	//  scala/actors/ReplyableActor$$anon$1
const #20 = NameAndType	#7:#8;//  $outer:Lscala/actors/ReplyableActor;
const #21 = Field	#19.#20;	//  scala/actors/ReplyableActor$$anon$1.$outer:Lscala/actors/ReplyableActor;
const #22 = NameAndType	#5:#6;//  ftch$2:Lscala/actors/Channel;
const #23 = Field	#19.#22;	//  scala/actors/ReplyableActor$$anon$1.ftch$2:Lscala/actors/Channel;
const #24 = Asciz	java/lang/Object;
const #25 = class	#24;	//  java/lang/Object
const #26 = Method	#25.#16;	//  java/lang/Object."<init>":()V
const #27 = Asciz	scala/actors/Replyable$class;
const #28 = class	#27;	//  scala/actors/Replyable$class
const #29 = Asciz	$init$;
const #30 = Asciz	(Lscala/actors/Replyable;)V;
const #31 = NameAndType	#29:#30;//  $init$:(Lscala/actors/Replyable;)V
const #32 = Method	#28.#31;	//  scala/actors/Replyable$class.$init$:(Lscala/actors/Replyable;)V
const #33 = Asciz	scala/actors/AbstractActor$class;
const #34 = class	#33;	//  scala/actors/AbstractActor$class
const #35 = Asciz	(Lscala/actors/AbstractActor;)V;
const #36 = NameAndType	#29:#35;//  $init$:(Lscala/actors/AbstractActor;)V
const #37 = Method	#34.#36;	//  scala/actors/AbstractActor$class.$init$:(Lscala/actors/AbstractActor;)V
const #38 = Asciz	this;
const #39 = Asciz	Lscala/actors/ReplyableActor$$anon$1;;
const #40 = Asciz	LocalVariableTable;
const #41 = Asciz	$bang$bang;
const #42 = Asciz	(Ljava/lang/Object;)Lscala/Function0;;
const #43 = Asciz	(Ljava/lang/Object;)Lscala/actors/Future;;
const #44 = NameAndType	#41:#43;//  $bang$bang:(Ljava/lang/Object;)Lscala/actors/Future;
const #45 = Method	#19.#44;	//  scala/actors/ReplyableActor$$anon$1.$bang$bang:(Ljava/lang/Object;)Lscala/actors/Future;
const #46 = Asciz	msg;
const #47 = Asciz	Ljava/lang/Object;;
const #48 = Asciz	(Ljava/lang/Object;Lscala/PartialFunction;)Lscala/Function0;;
const #49 = Asciz	(Ljava/lang/Object;Lscala/PartialFunction;)Lscala/actors/Future;;
const #50 = NameAndType	#41:#49;//  $bang$bang:(Ljava/lang/Object;Lscala/PartialFunction;)Lscala/actors/Future;
const #51 = Method	#19.#50;	//  scala/actors/ReplyableActor$$anon$1.$bang$bang:(Ljava/lang/Object;Lscala/PartialFunction;)Lscala/actors/Future;
const #52 = Asciz	f;
const #53 = Asciz	Lscala/PartialFunction;;
const #54 = Asciz	scala/actors/Channel;
const #55 = class	#54;	//  scala/actors/Channel
const #56 = Asciz	scala/actors/Actor$;
const #57 = class	#56;	//  scala/actors/Actor$
const #58 = Asciz	MODULE$;
const #59 = Asciz	Lscala/actors/Actor$;;
const #60 = NameAndType	#58:#59;//  MODULE$:Lscala/actors/Actor$;
const #61 = Field	#57.#60;	//  scala/actors/Actor$.MODULE$:Lscala/actors/Actor$;
const #62 = Asciz	scala/actors/Reactor;
const #63 = class	#62;	//  scala/actors/Reactor
const #64 = Asciz	scheduler;
const #65 = Asciz	()Lscala/actors/IScheduler;;
const #66 = NameAndType	#64:#65;//  scheduler:()Lscala/actors/IScheduler;
const #67 = InterfaceMethod	#63.#66;	//  scala/actors/Reactor.scheduler:()Lscala/actors/IScheduler;
const #68 = Asciz	self;
const #69 = Asciz	(Lscala/actors/IScheduler;)Lscala/actors/Actor;;
const #70 = NameAndType	#68:#69;//  self:(Lscala/actors/IScheduler;)Lscala/actors/Actor;
const #71 = Method	#57.#70;	//  scala/actors/Actor$.self:(Lscala/actors/IScheduler;)Lscala/actors/Actor;
const #72 = Asciz	(Lscala/actors/Actor;)V;
const #73 = NameAndType	#9:#72;//  "<init>":(Lscala/actors/Actor;)V
const #74 = Method	#55.#73;	//  scala/actors/Channel."<init>":(Lscala/actors/Actor;)V
const #75 = Asciz	scala/actors/Futures$;
const #76 = class	#75;	//  scala/actors/Futures$
const #77 = Asciz	Lscala/actors/Futures$;;
const #78 = NameAndType	#58:#77;//  MODULE$:Lscala/actors/Futures$;
const #79 = Field	#76.#78;	//  scala/actors/Futures$.MODULE$:Lscala/actors/Futures$;
const #80 = Asciz	fromInputChannel;
const #81 = Asciz	(Lscala/actors/InputChannel;)Lscala/actors/Future;;
const #82 = NameAndType	#80:#81;//  fromInputChannel:(Lscala/actors/InputChannel;)Lscala/actors/Future;
const #83 = Method	#76.#82;	//  scala/actors/Futures$.fromInputChannel:(Lscala/actors/InputChannel;)Lscala/actors/Future;
const #84 = Asciz	someChan;
const #85 = Asciz	<A:Ljava/lang/Object;>(Ljava/lang/Object;Lscala/PartialFunction<Ljava/lang/Object;TA;>;)Lscala/actors/Future<TA;>;;
const #86 = Asciz	Signature;
const #87 = Asciz	(Ljava/lang/Object;)Lscala/actors/Future<Ljava/lang/Object;>;;
const #88 = Asciz	$bang$qmark;
const #89 = Asciz	(JLjava/lang/Object;)Lscala/Option;;
const #90 = Asciz	scala/Some;
const #91 = class	#90;	//  scala/Some
const #92 = Asciz	(Ljava/lang/Object;)V;
const #93 = NameAndType	#9:#92;//  "<init>":(Ljava/lang/Object;)V
const #94 = Method	#91.#93;	//  scala/Some."<init>":(Ljava/lang/Object;)V
const #95 = Asciz	msec;
const #96 = Asciz	J;
const #97 = Asciz	(JLjava/lang/Object;)Lscala/Option<Ljava/lang/Object;>;;
const #98 = Asciz	(Ljava/lang/Object;)Ljava/lang/Object;;
const #99 = Asciz	exit;
const #100 = Asciz	(Lscala/actors/AbstractActor;Ljava/lang/Object;)V;
const #101 = Asciz	scala/actors/Exit;
const #102 = class	#101;	//  scala/actors/Exit
const #103 = NameAndType	#9:#100;//  "<init>":(Lscala/actors/AbstractActor;Ljava/lang/Object;)V
const #104 = Method	#102.#103;	//  scala/actors/Exit."<init>":(Lscala/actors/AbstractActor;Ljava/lang/Object;)V
const #105 = Asciz	scala/actors/OutputChannel;
const #106 = class	#105;	//  scala/actors/OutputChannel
const #107 = Asciz	send;
const #108 = Asciz	(Ljava/lang/Object;Lscala/actors/OutputChannel;)V;
const #109 = NameAndType	#107:#108;//  send:(Ljava/lang/Object;Lscala/actors/OutputChannel;)V
const #110 = Method	#55.#109;	//  scala/actors/Channel.send:(Ljava/lang/Object;Lscala/actors/OutputChannel;)V
const #111 = Asciz	from;
const #112 = Asciz	Lscala/actors/AbstractActor;;
const #113 = Asciz	reason;
const #114 = Asciz	unlinkFrom;
const #115 = Asciz	linkTo;
const #116 = Asciz	to;
const #117 = Asciz	receiver;
const #118 = Asciz	()Lscala/actors/Actor;;
const #119 = NameAndType	#117:#118;//  receiver:()Lscala/actors/Actor;
const #120 = Method	#55.#119;	//  scala/actors/Channel.receiver:()Lscala/actors/Actor;
const #121 = Asciz	forward;
const #122 = NameAndType	#121:#92;//  forward:(Ljava/lang/Object;)V
const #123 = Method	#55.#122;	//  scala/actors/Channel.forward:(Ljava/lang/Object;)V
const #124 = Asciz	replyTo;
const #125 = Asciz	Lscala/actors/OutputChannel;;
const #126 = Asciz	(Ljava/lang/Object;Lscala/actors/OutputChannel<Ljava/lang/Object;>;)V;
const #127 = Asciz	$bang;
const #128 = NameAndType	#127:#92;//  $bang:(Ljava/lang/Object;)V
const #129 = Method	#55.#128;	//  scala/actors/Channel.$bang:(Ljava/lang/Object;)V
const #130 = Asciz	exiting_$eq;
const #131 = Asciz	(Z)V;
const #132 = NameAndType	#3:#4;//  exiting:Z
const #133 = Field	#19.#132;	//  scala/actors/ReplyableActor$$anon$1.exiting:Z
const #134 = Asciz	()Z;
const #135 = Asciz	Scala;
const #136 = Asciz	InnerClasses;
const #137 = Asciz	scala/actors/ReplyableActor;
const #138 = class	#137;	//  scala/actors/ReplyableActor
const #139 = Asciz	$anon$1;
const #140 = Asciz	scala/actors/AbstractActor;
const #141 = class	#140;	//  scala/actors/AbstractActor

{
public scala.actors.ReplyableActor$$anon$1(scala.actors.ReplyableActor, scala.actors.Channel);
  Code:
   Stack=2, Locals=3, Args_size=3
   0:	aload_1
   1:	ifnonnull	12
   4:	new	#14; //class java/lang/NullPointerException
   7:	dup
   8:	invokespecial	#17; //Method java/lang/NullPointerException."<init>":()V
   11:	athrow
   12:	aload_0
   13:	aload_1
   14:	putfield	#21; //Field $outer:Lscala/actors/ReplyableActor;
   17:	aload_0
   18:	aload_2
   19:	putfield	#23; //Field ftch$2:Lscala/actors/Channel;
   22:	aload_0
   23:	invokespecial	#26; //Method java/lang/Object."<init>":()V
   26:	aload_0
   27:	invokestatic	#32; //Method scala/actors/Replyable$class.$init$:(Lscala/actors/Replyable;)V
   30:	aload_0
   31:	invokestatic	#37; //Method scala/actors/AbstractActor$class.$init$:(Lscala/actors/AbstractActor;)V
   34:	return
  LineNumberTable: 
   line 86: 0

  LocalVariableTable: 
   Start  Length  Slot  Name   Signature
   0      35      0    this       Lscala/actors/ReplyableActor$$anon$1;
   0      35      1    $outer       Lscala/actors/ReplyableActor;


public scala.Function0 $bang$bang(java.lang.Object);
  Code:
   Stack=2, Locals=2, Args_size=2
   0:	aload_0
   1:	aload_1
   2:	invokevirtual	#45; //Method $bang$bang:(Ljava/lang/Object;)Lscala/actors/Future;
   5:	areturn
  LineNumberTable: 
   line 86: 0

  LocalVariableTable: 
   Start  Length  Slot  Name   Signature
   0      6      0    this       Lscala/actors/ReplyableActor$$anon$1;
   0      6      1    msg       Ljava/lang/Object;


public scala.Function0 $bang$bang(java.lang.Object, scala.PartialFunction);
  Code:
   Stack=3, Locals=3, Args_size=3
   0:	aload_0
   1:	aload_1
   2:	aload_2
   3:	invokevirtual	#51; //Method $bang$bang:(Ljava/lang/Object;Lscala/PartialFunction;)Lscala/actors/Future;
   6:	areturn
  LineNumberTable: 
   line 86: 0

  LocalVariableTable: 
   Start  Length  Slot  Name   Signature
   0      7      0    this       Lscala/actors/ReplyableActor$$anon$1;
   0      7      1    msg       Ljava/lang/Object;
   0      7      2    f       Lscala/PartialFunction;


public scala.actors.Future $bang$bang(java.lang.Object, scala.PartialFunction);
  Code:
   Stack=4, Locals=4, Args_size=3
   0:	new	#55; //class scala/actors/Channel
   3:	dup
   4:	getstatic	#61; //Field scala/actors/Actor$.MODULE$:Lscala/actors/Actor$;
   7:	aload_0
   8:	getfield	#21; //Field $outer:Lscala/actors/ReplyableActor;
   11:	checkcast	#63; //class scala/actors/Reactor
   14:	invokeinterface	#67,  1; //InterfaceMethod scala/actors/Reactor.scheduler:()Lscala/actors/IScheduler;
   19:	invokevirtual	#71; //Method scala/actors/Actor$.self:(Lscala/actors/IScheduler;)Lscala/actors/Actor;
   22:	invokespecial	#74; //Method scala/actors/Channel."<init>":(Lscala/actors/Actor;)V
   25:	astore_3
   26:	getstatic	#79; //Field scala/actors/Futures$.MODULE$:Lscala/actors/Futures$;
   29:	aload_3
   30:	invokevirtual	#83; //Method scala/actors/Futures$.fromInputChannel:(Lscala/actors/InputChannel;)Lscala/actors/Future;
   33:	areturn
  LineNumberTable: 
   line 112: 0
   line 113: 26

  LocalVariableTable: 
   Start  Length  Slot  Name   Signature
   0      34      0    this       Lscala/actors/ReplyableActor$$anon$1;
   0      34      1    msg       Ljava/lang/Object;
   0      34      2    f       Lscala/PartialFunction;
   26      7      3    someChan       Lscala/actors/Channel;

  Signature: length = 0x2
   00 55 

public scala.actors.Future $bang$bang(java.lang.Object);
  Code:
   Stack=4, Locals=3, Args_size=2
   0:	new	#55; //class scala/actors/Channel
   3:	dup
   4:	getstatic	#61; //Field scala/actors/Actor$.MODULE$:Lscala/actors/Actor$;
   7:	aload_0
   8:	getfield	#21; //Field $outer:Lscala/actors/ReplyableActor;
   11:	checkcast	#63; //class scala/actors/Reactor
   14:	invokeinterface	#67,  1; //InterfaceMethod scala/actors/Reactor.scheduler:()Lscala/actors/IScheduler;
   19:	invokevirtual	#71; //Method scala/actors/Actor$.self:(Lscala/actors/IScheduler;)Lscala/actors/Actor;
   22:	invokespecial	#74; //Method scala/actors/Channel."<init>":(Lscala/actors/Actor;)V
   25:	astore_2
   26:	getstatic	#79; //Field scala/actors/Futures$.MODULE$:Lscala/actors/Futures$;
   29:	aload_2
   30:	invokevirtual	#83; //Method scala/actors/Futures$.fromInputChannel:(Lscala/actors/InputChannel;)Lscala/actors/Future;
   33:	areturn
  LineNumberTable: 
   line 107: 0
   line 108: 26

  LocalVariableTable: 
   Start  Length  Slot  Name   Signature
   0      34      0    this       Lscala/actors/ReplyableActor$$anon$1;
   0      34      1    msg       Ljava/lang/Object;
   26      7      2    someChan       Lscala/actors/Channel;

  Signature: length = 0x2
   00 57 

public scala.Option $bang$qmark(long, java.lang.Object);
  Code:
   Stack=3, Locals=4, Args_size=3
   0:	new	#91; //class scala/Some
   3:	dup
   4:	aload_3
   5:	invokespecial	#94; //Method scala/Some."<init>":(Ljava/lang/Object;)V
   8:	areturn
  LineNumberTable: 
   line 104: 0

  LocalVariableTable: 
   Start  Length  Slot  Name   Signature
   0      9      0    this       Lscala/actors/ReplyableActor$$anon$1;
   0      9      1    msec       J
   0      9      3    msg       Ljava/lang/Object;

  Signature: length = 0x2
   00 61 

public java.lang.Object $bang$qmark(java.lang.Object);
  Code:
   Stack=1, Locals=2, Args_size=2
   0:	aload_1
   1:	areturn
  LineNumberTable: 
   line 102: 0

  LocalVariableTable: 
   Start  Length  Slot  Name   Signature
   0      2      0    this       Lscala/actors/ReplyableActor$$anon$1;
   0      2      1    msg       Ljava/lang/Object;


public void exit(scala.actors.AbstractActor, java.lang.Object);
  Code:
   Stack=5, Locals=3, Args_size=3
   0:	aload_0
   1:	getfield	#23; //Field ftch$2:Lscala/actors/Channel;
   4:	new	#102; //class scala/actors/Exit
   7:	dup
   8:	aload_1
   9:	aload_2
   10:	invokespecial	#104; //Method scala/actors/Exit."<init>":(Lscala/actors/AbstractActor;Ljava/lang/Object;)V
   13:	aload_0
   14:	getfield	#21; //Field $outer:Lscala/actors/ReplyableActor;
   17:	checkcast	#106; //class scala/actors/OutputChannel
   20:	invokevirtual	#110; //Method scala/actors/Channel.send:(Ljava/lang/Object;Lscala/actors/OutputChannel;)V
   23:	return
  LineNumberTable: 
   line 99: 0

  LocalVariableTable: 
   Start  Length  Slot  Name   Signature
   0      24      0    this       Lscala/actors/ReplyableActor$$anon$1;
   0      24      1    from       Lscala/actors/AbstractActor;
   0      24      2    reason       Ljava/lang/Object;


public void unlinkFrom(scala.actors.AbstractActor);
  Code:
   Stack=0, Locals=2, Args_size=2
   0:	return
  LineNumberTable: 
   line 97: 0

  LocalVariableTable: 
   Start  Length  Slot  Name   Signature
   0      1      0    this       Lscala/actors/ReplyableActor$$anon$1;
   0      1      1    from       Lscala/actors/AbstractActor;


public void linkTo(scala.actors.AbstractActor);
  Code:
   Stack=0, Locals=2, Args_size=2
   0:	return
  LineNumberTable: 
   line 96: 0

  LocalVariableTable: 
   Start  Length  Slot  Name   Signature
   0      1      0    this       Lscala/actors/ReplyableActor$$anon$1;
   0      1      1    to       Lscala/actors/AbstractActor;


public scala.actors.Actor receiver();
  Code:
   Stack=1, Locals=1, Args_size=1
   0:	aload_0
   1:	getfield	#23; //Field ftch$2:Lscala/actors/Channel;
   4:	invokevirtual	#120; //Method scala/actors/Channel.receiver:()Lscala/actors/Actor;
   7:	areturn
  LineNumberTable: 
   line 95: 0


public void forward(java.lang.Object);
  Code:
   Stack=2, Locals=2, Args_size=2
   0:	aload_0
   1:	getfield	#23; //Field ftch$2:Lscala/actors/Channel;
   4:	aload_1
   5:	invokevirtual	#123; //Method scala/actors/Channel.forward:(Ljava/lang/Object;)V
   8:	return
  LineNumberTable: 
   line 93: 0

  LocalVariableTable: 
   Start  Length  Slot  Name   Signature
   0      9      0    this       Lscala/actors/ReplyableActor$$anon$1;
   0      9      1    msg       Ljava/lang/Object;


public void send(java.lang.Object, scala.actors.OutputChannel);
  Code:
   Stack=3, Locals=3, Args_size=3
   0:	aload_0
   1:	getfield	#23; //Field ftch$2:Lscala/actors/Channel;
   4:	aload_1
   5:	aload_2
   6:	invokevirtual	#110; //Method scala/actors/Channel.send:(Ljava/lang/Object;Lscala/actors/OutputChannel;)V
   9:	return
  LineNumberTable: 
   line 91: 0

  LocalVariableTable: 
   Start  Length  Slot  Name   Signature
   0      10      0    this       Lscala/actors/ReplyableActor$$anon$1;
   0      10      1    msg       Ljava/lang/Object;
   0      10      2    replyTo       Lscala/actors/OutputChannel;

  Signature: length = 0x2
   00 7E 

public void $bang(java.lang.Object);
  Code:
   Stack=2, Locals=2, Args_size=2
   0:	aload_0
   1:	getfield	#23; //Field ftch$2:Lscala/actors/Channel;
   4:	aload_1
   5:	invokevirtual	#129; //Method scala/actors/Channel.$bang:(Ljava/lang/Object;)V
   8:	return
  LineNumberTable: 
   line 89: 0

  LocalVariableTable: 
   Start  Length  Slot  Name   Signature
   0      9      0    this       Lscala/actors/ReplyableActor$$anon$1;
   0      9      1    msg       Ljava/lang/Object;


public void exiting_$eq(boolean);
  Code:
   Stack=2, Locals=2, Args_size=2
   0:	aload_0
   1:	iload_1
   2:	putfield	#133; //Field exiting:Z
   5:	return
  LineNumberTable: 
   line 86: 0


public boolean exiting();
  Code:
   Stack=1, Locals=1, Args_size=1
   0:	aload_0
   1:	getfield	#133; //Field exiting:Z
   4:	ireturn
  LineNumberTable: 
   line 86: 0


}

