Compiled from "ReplyableActor.scala"
public final class scala.actors.ReplyableActor$$anon$3 extends java.lang.Object implements scala.actors.OutputChannel
  SourceFile: "ReplyableActor.scala"
  Signature: length = 0x2
   00 38 
  Scala: length = 0x
   
  InnerClass: 
   public final $anon$3=class scala/actors/ReplyableActor$$anon$3 of class scala/actors/ReplyableActor
  minor version: 0
  major version: 49
  Constant pool:
Asciz	SourceFile;
Asciz	ReplyableActor.scala;
Asciz	ftch$1;
Asciz	Lscala/actors/Channel;;
Asciz	f$1;
Asciz	Lscala/PartialFunction;;
Asciz	<init>;
Asciz	(Lscala/actors/ReplyableActor;Lscala/PartialFunction;Lscala/actors/Channel;)V;
Asciz	Code;
Asciz	LineNumberTable;
Asciz	scala/actors/ReplyableActor$$anon$3;
class	scala/actors/ReplyableActor$$anon$3
NameAndType	f$1:Lscala/PartialFunction;
Field	scala/actors/ReplyableActor$$anon$3.f$1:Lscala/PartialFunction;
NameAndType	ftch$1:Lscala/actors/Channel;
Field	scala/actors/ReplyableActor$$anon$3.ftch$1:Lscala/actors/Channel;
Asciz	java/lang/Object;
class	java/lang/Object
Asciz	()V;
NameAndType	"<init>":()V
Method	java/lang/Object."<init>":()V
Asciz	this;
Asciz	Lscala/actors/ReplyableActor$$anon$3;;
Asciz	$outer;
Asciz	Lscala/actors/ReplyableActor;;
Asciz	LocalVariableTable;
Asciz	receiver;
Asciz	()Lscala/actors/Actor;;
Asciz	scala/actors/Channel;
class	scala/actors/Channel
NameAndType	receiver:()Lscala/actors/Actor;
Method	scala/actors/Channel.receiver:()Lscala/actors/Actor;
Asciz	forward;
Asciz	(Ljava/lang/Object;)V;
Asciz	scala/Function1;
class	scala/Function1
Asciz	apply;
Asciz	(Ljava/lang/Object;)Ljava/lang/Object;;
NameAndType	apply:(Ljava/lang/Object;)Ljava/lang/Object;
InterfaceMethod	scala/Function1.apply:(Ljava/lang/Object;)Ljava/lang/Object;
NameAndType	forward:(Ljava/lang/Object;)V
Method	scala/actors/Channel.forward:(Ljava/lang/Object;)V
Asciz	msg;
Asciz	Ljava/lang/Object;;
Asciz	send;
Asciz	(Ljava/lang/Object;Lscala/actors/OutputChannel;)V;
NameAndType	send:(Ljava/lang/Object;Lscala/actors/OutputChannel;)V
Method	scala/actors/Channel.send:(Ljava/lang/Object;Lscala/actors/OutputChannel;)V
Asciz	replyTo;
Asciz	Lscala/actors/OutputChannel;;
Asciz	(Ljava/lang/Object;Lscala/actors/OutputChannel<Ljava/lang/Object;>;)V;
Asciz	Signature;
Asciz	$bang;
NameAndType	$bang:(Ljava/lang/Object;)V
Method	scala/actors/Channel.$bang:(Ljava/lang/Object;)V
Asciz	Ljava/lang/Object;Lscala/actors/OutputChannel<Ljava/lang/Object;>;;
Asciz	Scala;
Asciz	InnerClasses;
Asciz	scala/actors/ReplyableActor;
class	scala/actors/ReplyableActor
Asciz	$anon$3;
Asciz	scala/actors/OutputChannel;
class	scala/actors/OutputChannel

{
private final scala.actors.Channel ftch$1;
  Signature: Lscala/actors/Channel;

private final scala.PartialFunction f$1;
  Signature: Lscala/PartialFunction;

public scala.actors.ReplyableActor$$anon$3(scala.actors.ReplyableActor, scala.PartialFunction, scala.actors.Channel);
  Signature: (Lscala/actors/ReplyableActor;Lscala/PartialFunction;Lscala/actors/Channel;)V
  Code:
   Stack=2, Locals=4, Args_size=4
	aload_0
	aload_2
	putfield	Field f$1:Lscala/PartialFunction;
	aload_0
	aload_3
	putfield	Field ftch$1:Lscala/actors/Channel;
	aload_0
	invokespecial	Method java/lang/Object."<init>":()V
	return
  Labels:
  LocalVariableTable: 
   Start  Length  Slot  Name   Signature
   0      15      0    this       Lscala/actors/ReplyableActor$$anon$3;
   0      15      1    $outer       Lscala/actors/ReplyableActor;


public scala.actors.Actor receiver();
  Signature: ()Lscala/actors/Actor;
  Code:
   Stack=1, Locals=1, Args_size=1
	aload_0
	getfield	Field ftch$1:Lscala/actors/Channel;
	invokevirtual	Method scala/actors/Channel.receiver:()Lscala/actors/Actor;
	areturn
  Labels:

public void forward(java.lang.Object);
  Signature: (Ljava/lang/Object;)V
  Code:
   Stack=3, Locals=2, Args_size=2
	aload_0
	getfield	Field ftch$1:Lscala/actors/Channel;
	aload_0
	getfield	Field f$1:Lscala/PartialFunction;
	aload_1
	invokeinterface	InterfaceMethod scala/Function1.apply:(Ljava/lang/Object;)Ljava/lang/Object;
	invokevirtual	Method scala/actors/Channel.forward:(Ljava/lang/Object;)V
	return
  Labels:
  LocalVariableTable: 
   Start  Length  Slot  Name   Signature
   0      18      0    this       Lscala/actors/ReplyableActor$$anon$3;
   0      18      1    msg       Ljava/lang/Object;


public void send(java.lang.Object, scala.actors.OutputChannel);
  Signature: (Ljava/lang/Object;Lscala/actors/OutputChannel;)V
  Code:
   Stack=3, Locals=3, Args_size=3
	aload_0
	getfield	Field ftch$1:Lscala/actors/Channel;
	aload_0
	getfield	Field f$1:Lscala/PartialFunction;
	aload_1
	invokeinterface	InterfaceMethod scala/Function1.apply:(Ljava/lang/Object;)Ljava/lang/Object;
	aload_2
	invokevirtual	Method scala/actors/Channel.send:(Ljava/lang/Object;Lscala/actors/OutputChannel;)V
	return
  Labels:
  LocalVariableTable: 
   Start  Length  Slot  Name   Signature
   0      19      0    this       Lscala/actors/ReplyableActor$$anon$3;
   0      19      1    msg       Ljava/lang/Object;
   0      19      2    replyTo       Lscala/actors/OutputChannel;

  Signature: length = 0x2
   00 33 

public void $bang(java.lang.Object);
  Signature: (Ljava/lang/Object;)V
  Code:
   Stack=3, Locals=2, Args_size=2
	aload_0
	getfield	Field ftch$1:Lscala/actors/Channel;
	aload_0
	getfield	Field f$1:Lscala/PartialFunction;
	aload_1
	invokeinterface	InterfaceMethod scala/Function1.apply:(Ljava/lang/Object;)Ljava/lang/Object;
	invokevirtual	Method scala/actors/Channel.$bang:(Ljava/lang/Object;)V
	return
  Labels:
  LocalVariableTable: 
   Start  Length  Slot  Name   Signature
   0      18      0    this       Lscala/actors/ReplyableActor$$anon$3;
   0      18      1    msg       Ljava/lang/Object;


}

