Compiled from "ReplyableReactor.scala"
public abstract class scala.actors.ReplyableReactor$class extends java.lang.Object
  SourceFile: "ReplyableReactor.scala"
  Scala: length = 0x
   
  InnerClass: 
   public final $anon$2=class scala/actors/ReplyableReactor$$anon$2 of class scala/actors/ReplyableReactor
   public final $anon$1=class scala/actors/ReplyableReactor$$anon$1 of class scala/actors/ReplyableReactor
   public final $anon$3=class scala/actors/ReplyableReactor$$anon$3 of class scala/actors/ReplyableReactor
   public final $anonfun$$bang$bang$1=class scala/actors/ReplyableReactor$$anonfun$$bang$bang$1 of class scala/actors/ReplyableReactor
  minor version: 0
  major version: 49
  Constant pool:
Asciz	SourceFile;
Asciz	ReplyableReactor.scala;
Asciz	$init$;
Asciz	(Lscala/actors/ReplyReactor;)V;
Asciz	Code;
Asciz	LineNumberTable;
Asciz	$this;
Asciz	Lscala/actors/ReplyReactor;;
Asciz	LocalVariableTable;
Asciz	$bang$bang;
Asciz	(Lscala/actors/ReplyReactor;Ljava/lang/Object;Lscala/PartialFunction;)Lscala/actors/Future;;
Asciz	scala/actors/Actor$;
class	scala/actors/Actor$
Asciz	MODULE$;
Asciz	Lscala/actors/Actor$;;
NameAndType	MODULE$:Lscala/actors/Actor$;
Field	scala/actors/Actor$.MODULE$:Lscala/actors/Actor$;
Asciz	scala/actors/Reactor;
class	scala/actors/Reactor
Asciz	scheduler;
Asciz	()Lscala/actors/IScheduler;;
NameAndType	scheduler:()Lscala/actors/IScheduler;
InterfaceMethod	scala/actors/Reactor.scheduler:()Lscala/actors/IScheduler;
Asciz	rawSelf;
Asciz	(Lscala/actors/IScheduler;)Lscala/actors/Reactor;;
NameAndType	rawSelf:(Lscala/actors/IScheduler;)Lscala/actors/Reactor;
Method	scala/actors/Actor$.rawSelf:(Lscala/actors/IScheduler;)Lscala/actors/Reactor;
Asciz	scala/actors/ReactChannel;
class	scala/actors/ReactChannel
Asciz	<init>;
Asciz	(Lscala/actors/Reactor;)V;
NameAndType	"<init>":(Lscala/actors/Reactor;)V
Method	scala/actors/ReactChannel."<init>":(Lscala/actors/Reactor;)V
Asciz	scala/concurrent/SyncVar;
class	scala/concurrent/SyncVar
Asciz	()V;
NameAndType	"<init>":()V
Method	scala/concurrent/SyncVar."<init>":()V
Asciz	scala/actors/ReplyableReactor$$anon$3;
class	scala/actors/ReplyableReactor$$anon$3
Asciz	(Lscala/actors/ReplyReactor;Lscala/PartialFunction;Lscala/actors/Reactor;Lscala/actors/ReactChannel;Lscala/concurrent/SyncVar;)V;
NameAndType	"<init>":(Lscala/actors/ReplyReactor;Lscala/PartialFunction;Lscala/actors/Reactor;Lscala/actors/ReactChannel;Lscala/concurrent/SyncVar;)V
Method	scala/actors/ReplyableReactor$$anon$3."<init>":(Lscala/actors/ReplyReactor;Lscala/PartialFunction;Lscala/actors/Reactor;Lscala/actors/ReactChannel;Lscala/concurrent/SyncVar;)V
Asciz	scala/actors/OutputChannel;
class	scala/actors/OutputChannel
Asciz	send;
Asciz	(Ljava/lang/Object;Lscala/actors/OutputChannel;)V;
NameAndType	send:(Ljava/lang/Object;Lscala/actors/OutputChannel;)V
InterfaceMethod	scala/actors/Reactor.send:(Ljava/lang/Object;Lscala/actors/OutputChannel;)V
Asciz	scala/actors/ReplyableReactor$$anon$1;
class	scala/actors/ReplyableReactor$$anon$1
Asciz	(Lscala/actors/ReplyReactor;Lscala/actors/ReactChannel;Lscala/concurrent/SyncVar;)V;
NameAndType	"<init>":(Lscala/actors/ReplyReactor;Lscala/actors/ReactChannel;Lscala/concurrent/SyncVar;)V
Method	scala/actors/ReplyableReactor$$anon$1."<init>":(Lscala/actors/ReplyReactor;Lscala/actors/ReactChannel;Lscala/concurrent/SyncVar;)V
Asciz	msg;
Asciz	Ljava/lang/Object;;
Asciz	f$1;
Asciz	Lscala/PartialFunction;;
Asciz	myself$2;
Asciz	Lscala/actors/Reactor;;
Asciz	ftch$1;
Asciz	Lscala/actors/ReactChannel;;
Asciz	res$2;
Asciz	Lscala/concurrent/SyncVar;;
Asciz	out;
Asciz	(Lscala/actors/ReplyReactor;Ljava/lang/Object;)Lscala/actors/Future;;
Asciz	scala/actors/ReplyableReactor$$anonfun$$bang$bang$1;
class	scala/actors/ReplyableReactor$$anonfun$$bang$bang$1
NameAndType	"<init>":(Lscala/actors/ReplyReactor;)V
Method	scala/actors/ReplyableReactor$$anonfun$$bang$bang$1."<init>":(Lscala/actors/ReplyReactor;)V
Asciz	scala/actors/ReplyableReactor;
class	scala/actors/ReplyableReactor
Asciz	(Ljava/lang/Object;Lscala/PartialFunction;)Lscala/actors/Future;;
NameAndType	$bang$bang:(Ljava/lang/Object;Lscala/PartialFunction;)Lscala/actors/Future;
InterfaceMethod	scala/actors/ReplyableReactor.$bang$bang:(Ljava/lang/Object;Lscala/PartialFunction;)Lscala/actors/Future;
Asciz	$bang$qmark;
Asciz	(Lscala/actors/ReplyReactor;JLjava/lang/Object;)Lscala/Option;;
Asciz	scala/actors/ReplyableReactor$$anon$2;
class	scala/actors/ReplyableReactor$$anon$2
Asciz	(Lscala/actors/ReplyReactor;Lscala/actors/Reactor;Lscala/concurrent/SyncVar;)V;
NameAndType	"<init>":(Lscala/actors/ReplyReactor;Lscala/actors/Reactor;Lscala/concurrent/SyncVar;)V
Method	scala/actors/ReplyableReactor$$anon$2."<init>":(Lscala/actors/ReplyReactor;Lscala/actors/Reactor;Lscala/concurrent/SyncVar;)V
Asciz	get;
Asciz	(J)Lscala/Option;;
NameAndType	get:(J)Lscala/Option;
Method	scala/concurrent/SyncVar.get:(J)Lscala/Option;
Asciz	msec;
Asciz	J;
Asciz	myself$1;
Asciz	res$1;
Asciz	(Lscala/actors/ReplyReactor;Ljava/lang/Object;)Ljava/lang/Object;;
Asciz	(Ljava/lang/Object;)Lscala/actors/Future;;
NameAndType	$bang$bang:(Ljava/lang/Object;)Lscala/actors/Future;
InterfaceMethod	scala/actors/ReplyableReactor.$bang$bang:(Ljava/lang/Object;)Lscala/actors/Future;
Asciz	scala/Function0;
class	scala/Function0
Asciz	apply;
Asciz	()Ljava/lang/Object;;
NameAndType	apply:()Ljava/lang/Object;
InterfaceMethod	scala/Function0.apply:()Ljava/lang/Object;
Asciz	Scala;
Asciz	InnerClasses;
Asciz	$anon$2;
Asciz	$anon$1;
Asciz	$anon$3;
Asciz	$anonfun$$bang$bang$1;
Asciz	scala/actors/ReplyableReactor$class;
class	scala/actors/ReplyableReactor$class
Asciz	java/lang/Object;
class	java/lang/Object

{
public static void $init$(scala.actors.ReplyReactor);
  Signature: (Lscala/actors/ReplyReactor;)V
  Code:
   Stack=0, Locals=1, Args_size=1
	return
  Labels:
  LocalVariableTable: 
   Start  Length  Slot  Name   Signature
   0      1      0    $this       Lscala/actors/ReplyReactor;


public static scala.actors.Future $bang$bang(scala.actors.ReplyReactor, java.lang.Object, scala.PartialFunction);
  Signature: (Lscala/actors/ReplyReactor;Ljava/lang/Object;Lscala/PartialFunction;)Lscala/actors/Future;
  Code:
   Stack=7, Locals=7, Args_size=3
	getstatic	Field scala/actors/Actor$.MODULE$:Lscala/actors/Actor$;
	aload_0
	invokeinterface	InterfaceMethod scala/actors/Reactor.scheduler:()Lscala/actors/IScheduler;
	invokevirtual	Method scala/actors/Actor$.rawSelf:(Lscala/actors/IScheduler;)Lscala/actors/Reactor;
	astore_3
	new	class scala/actors/ReactChannel
	dup
	aload_3
	invokespecial	Method scala/actors/ReactChannel."<init>":(Lscala/actors/Reactor;)V
	astore	4
	new	class scala/concurrent/SyncVar
	dup
	invokespecial	Method scala/concurrent/SyncVar."<init>":()V
	astore	5
	new	class scala/actors/ReplyableReactor$$anon$3
	dup
	aload_0
	aload_2
	aload_3
	aload	4
	aload	5
	invokespecial	Method scala/actors/ReplyableReactor$$anon$3."<init>":(Lscala/actors/ReplyReactor;Lscala/PartialFunction;Lscala/actors/Reactor;Lscala/actors/ReactChannel;Lscala/concurrent/SyncVar;)V
	astore	6
	aload_0
	aload_1
	aload	6
	checkcast	class scala/actors/OutputChannel
	invokeinterface	InterfaceMethod scala/actors/Reactor.send:(Ljava/lang/Object;Lscala/actors/OutputChannel;)V
	new	class scala/actors/ReplyableReactor$$anon$1
	dup
	aload_0
	aload	4
	aload	5
	invokespecial	Method scala/actors/ReplyableReactor$$anon$1."<init>":(Lscala/actors/ReplyReactor;Lscala/actors/ReactChannel;Lscala/concurrent/SyncVar;)V
	areturn
  Labels:
  LocalVariableTable: 
   Start  Length  Slot  Name   Signature
   0      73      0    $this       Lscala/actors/ReplyReactor;
   0      73      1    msg       Ljava/lang/Object;
   0      73      2    f$1       Lscala/PartialFunction;
   13      59      3    myself$2       Lscala/actors/Reactor;
   23      49      4    ftch$1       Lscala/actors/ReactChannel;
   32      40      5    res$2       Lscala/concurrent/SyncVar;
   48      24      6    out       Ljava/lang/Object;


public static scala.actors.Future $bang$bang(scala.actors.ReplyReactor, java.lang.Object);
  Signature: (Lscala/actors/ReplyReactor;Ljava/lang/Object;)Lscala/actors/Future;
  Code:
   Stack=5, Locals=2, Args_size=2
	aload_0
	aload_1
	new	class scala/actors/ReplyableReactor$$anonfun$$bang$bang$1
	dup
	aload_0
	invokespecial	Method scala/actors/ReplyableReactor$$anonfun$$bang$bang$1."<init>":(Lscala/actors/ReplyReactor;)V
	invokeinterface	InterfaceMethod scala/actors/ReplyableReactor.$bang$bang:(Ljava/lang/Object;Lscala/PartialFunction;)Lscala/actors/Future;
	areturn
  Labels:
  LocalVariableTable: 
   Start  Length  Slot  Name   Signature
   0      16      0    $this       Lscala/actors/ReplyReactor;
   0      16      1    msg       Ljava/lang/Object;


public static scala.Option $bang$qmark(scala.actors.ReplyReactor, long, java.lang.Object);
  Signature: (Lscala/actors/ReplyReactor;JLjava/lang/Object;)Lscala/Option;
  Code:
   Stack=5, Locals=7, Args_size=3
	getstatic	Field scala/actors/Actor$.MODULE$:Lscala/actors/Actor$;
	aload_0
	invokeinterface	InterfaceMethod scala/actors/Reactor.scheduler:()Lscala/actors/IScheduler;
	invokevirtual	Method scala/actors/Actor$.rawSelf:(Lscala/actors/IScheduler;)Lscala/actors/Reactor;
	astore	4
	new	class scala/concurrent/SyncVar
	dup
	invokespecial	Method scala/concurrent/SyncVar."<init>":()V
	astore	5
	new	class scala/actors/ReplyableReactor$$anon$2
	dup
	aload_0
	aload	4
	aload	5
	invokespecial	Method scala/actors/ReplyableReactor$$anon$2."<init>":(Lscala/actors/ReplyReactor;Lscala/actors/Reactor;Lscala/concurrent/SyncVar;)V
	astore	6
	aload_0
	aload_3
	aload	6
	checkcast	class scala/actors/OutputChannel
	invokeinterface	InterfaceMethod scala/actors/Reactor.send:(Ljava/lang/Object;Lscala/actors/OutputChannel;)V
	aload	5
	lload_1
	invokevirtual	Method scala/concurrent/SyncVar.get:(J)Lscala/Option;
	areturn
  Labels:
  LocalVariableTable: 
   Start  Length  Slot  Name   Signature
   0      56      0    $this       Lscala/actors/ReplyReactor;
   0      56      1    msec       J
   0      56      3    msg       Ljava/lang/Object;
   14      41      4    myself$1       Lscala/actors/Reactor;
   23      32      5    res$1       Lscala/concurrent/SyncVar;
   37      18      6    out       Ljava/lang/Object;


public static java.lang.Object $bang$qmark(scala.actors.ReplyReactor, java.lang.Object);
  Signature: (Lscala/actors/ReplyReactor;Ljava/lang/Object;)Ljava/lang/Object;
  Code:
   Stack=2, Locals=2, Args_size=2
	aload_0
	aload_1
	invokeinterface	InterfaceMethod scala/actors/ReplyableReactor.$bang$bang:(Ljava/lang/Object;)Lscala/actors/Future;
	invokeinterface	InterfaceMethod scala/Function0.apply:()Ljava/lang/Object;
	areturn
  Labels:
  LocalVariableTable: 
   Start  Length  Slot  Name   Signature
   0      13      0    $this       Lscala/actors/ReplyReactor;
   0      13      1    msg       Ljava/lang/Object;


}

