Compiled from "ReplyableReactor.scala"
public final class scala.actors.ReplyableReactor$$anon$2 extends java.lang.Object implements scala.actors.OutputChannel
  SourceFile: "ReplyableReactor.scala"
  Signature: length = 0x2
   00 2F 
  Scala: length = 0x
   
  InnerClass: 
   public final #52= #12 of #51; //$anon$2=class scala/actors/ReplyableReactor$$anon$2 of class scala/actors/ReplyableReactor
  minor version: 0
  major version: 49
  Constant pool:
const #1 = Asciz	SourceFile;
const #2 = Asciz	ReplyableReactor.scala;
const #3 = Asciz	res$1;
const #4 = Asciz	Lscala/concurrent/SyncVar;;
const #5 = Asciz	myself$1;
const #6 = Asciz	Lscala/actors/Reactor;;
const #7 = Asciz	<init>;
const #8 = Asciz	(Lscala/actors/ReplyReactor;Lscala/actors/Reactor;Lscala/concurrent/SyncVar;)V;
const #9 = Asciz	Code;
const #10 = Asciz	LineNumberTable;
const #11 = Asciz	scala/actors/ReplyableReactor$$anon$2;
const #12 = class	#11;	//  scala/actors/ReplyableReactor$$anon$2
const #13 = NameAndType	#5:#6;//  myself$1:Lscala/actors/Reactor;
const #14 = Field	#12.#13;	//  scala/actors/ReplyableReactor$$anon$2.myself$1:Lscala/actors/Reactor;
const #15 = NameAndType	#3:#4;//  res$1:Lscala/concurrent/SyncVar;
const #16 = Field	#12.#15;	//  scala/actors/ReplyableReactor$$anon$2.res$1:Lscala/concurrent/SyncVar;
const #17 = Asciz	java/lang/Object;
const #18 = class	#17;	//  java/lang/Object
const #19 = Asciz	()V;
const #20 = NameAndType	#7:#19;//  "<init>":()V
const #21 = Method	#18.#20;	//  java/lang/Object."<init>":()V
const #22 = Asciz	this;
const #23 = Asciz	Lscala/actors/ReplyableReactor$$anon$2;;
const #24 = Asciz	$outer;
const #25 = Asciz	Lscala/actors/ReplyReactor;;
const #26 = Asciz	LocalVariableTable;
const #27 = Asciz	receiver;
const #28 = Asciz	()Lscala/actors/Actor;;
const #29 = Asciz	scala/actors/Actor;
const #30 = class	#29;	//  scala/actors/Actor
const #31 = Asciz	forward;
const #32 = Asciz	(Ljava/lang/Object;)V;
const #33 = Asciz	scala/concurrent/SyncVar;
const #34 = class	#33;	//  scala/concurrent/SyncVar
const #35 = Asciz	set;
const #36 = NameAndType	#35:#32;//  set:(Ljava/lang/Object;)V
const #37 = Method	#34.#36;	//  scala/concurrent/SyncVar.set:(Ljava/lang/Object;)V
const #38 = Asciz	msg;
const #39 = Asciz	Ljava/lang/Object;;
const #40 = Asciz	send;
const #41 = Asciz	(Ljava/lang/Object;Lscala/actors/OutputChannel;)V;
const #42 = Asciz	replyTo;
const #43 = Asciz	Lscala/actors/OutputChannel;;
const #44 = Asciz	(Ljava/lang/Object;Lscala/actors/OutputChannel<Ljava/lang/Object;>;)V;
const #45 = Asciz	Signature;
const #46 = Asciz	$bang;
const #47 = Asciz	Ljava/lang/Object;Lscala/actors/OutputChannel<Ljava/lang/Object;>;;
const #48 = Asciz	Scala;
const #49 = Asciz	InnerClasses;
const #50 = Asciz	scala/actors/ReplyableReactor;
const #51 = class	#50;	//  scala/actors/ReplyableReactor
const #52 = Asciz	$anon$2;
const #53 = Asciz	scala/actors/OutputChannel;
const #54 = class	#53;	//  scala/actors/OutputChannel

{
public scala.actors.ReplyableReactor$$anon$2(scala.actors.ReplyReactor, scala.actors.Reactor, scala.concurrent.SyncVar);
  Code:
   Stack=2, Locals=4, Args_size=4
   0:	aload_0
   1:	aload_2
   2:	putfield	#14; //Field myself$1:Lscala/actors/Reactor;
   5:	aload_0
   6:	aload_3
   7:	putfield	#16; //Field res$1:Lscala/concurrent/SyncVar;
   10:	aload_0
   11:	invokespecial	#21; //Method java/lang/Object."<init>":()V
   14:	return
  LineNumberTable: 
   line 45: 0

  LocalVariableTable: 
   Start  Length  Slot  Name   Signature
   0      15      0    this       Lscala/actors/ReplyableReactor$$anon$2;
   0      15      1    $outer       Lscala/actors/ReplyReactor;


public scala.actors.Actor receiver();
  Code:
   Stack=1, Locals=1, Args_size=1
   0:	aload_0
   1:	getfield	#14; //Field myself$1:Lscala/actors/Reactor;
   4:	checkcast	#30; //class scala/actors/Actor
   7:	areturn
  LineNumberTable: 
   line 53: 0


public void forward(java.lang.Object);
  Code:
   Stack=2, Locals=2, Args_size=2
   0:	aload_0
   1:	getfield	#16; //Field res$1:Lscala/concurrent/SyncVar;
   4:	aload_1
   5:	invokevirtual	#37; //Method scala/concurrent/SyncVar.set:(Ljava/lang/Object;)V
   8:	return
  LineNumberTable: 
   line 51: 0

  LocalVariableTable: 
   Start  Length  Slot  Name   Signature
   0      9      0    this       Lscala/actors/ReplyableReactor$$anon$2;
   0      9      1    msg       Ljava/lang/Object;


public void send(java.lang.Object, scala.actors.OutputChannel);
  Code:
   Stack=2, Locals=3, Args_size=3
   0:	aload_0
   1:	getfield	#16; //Field res$1:Lscala/concurrent/SyncVar;
   4:	aload_1
   5:	invokevirtual	#37; //Method scala/concurrent/SyncVar.set:(Ljava/lang/Object;)V
   8:	return
  LineNumberTable: 
   line 49: 0

  LocalVariableTable: 
   Start  Length  Slot  Name   Signature
   0      9      0    this       Lscala/actors/ReplyableReactor$$anon$2;
   0      9      1    msg       Ljava/lang/Object;
   0      9      2    replyTo       Lscala/actors/OutputChannel;

  Signature: length = 0x2
   00 2C 

public void $bang(java.lang.Object);
  Code:
   Stack=2, Locals=2, Args_size=2
   0:	aload_0
   1:	getfield	#16; //Field res$1:Lscala/concurrent/SyncVar;
   4:	aload_1
   5:	invokevirtual	#37; //Method scala/concurrent/SyncVar.set:(Ljava/lang/Object;)V
   8:	return
  LineNumberTable: 
   line 47: 0

  LocalVariableTable: 
   Start  Length  Slot  Name   Signature
   0      9      0    this       Lscala/actors/ReplyableReactor$$anon$2;
   0      9      1    msg       Ljava/lang/Object;


}

