Compiled from "ReplyableReactor.scala"
public final class scala.actors.ReplyableReactor$$anon$1$$anonfun$respond$1 extends java.lang.Object implements scala.PartialFunction,scala.ScalaObject,java.io.Serializable
  SourceFile: "ReplyableReactor.scala"
  Scala: length = 0x
   
  InnerClass: 
   public final $anon$1=class scala/actors/ReplyableReactor$$anon$1 of class scala/actors/ReplyableReactor
   public final $anonfun$respond$1=class scala/actors/ReplyableReactor$$anon$1$$anonfun$respond$1 of class scala/actors/ReplyableReactor$$anon$1
  minor version: 0
  major version: 49
  Constant pool:
Asciz	SourceFile;
Asciz	ReplyableReactor.scala;
Asciz	<clinit>;
Asciz	()V;
Asciz	Code;
Asciz	serialVersionUID;
Asciz	J;
Asciz	scala/actors/ReplyableReactor$$anon$1$$anonfun$respond$1;
class	scala/actors/ReplyableReactor$$anon$1$$anonfun$respond$1
NameAndType	serialVersionUID:J
Field	scala/actors/ReplyableReactor$$anon$1$$anonfun$respond$1.serialVersionUID:J
Asciz	k$1;
Asciz	Lscala/Function1;;
Asciz	$outer;
Asciz	Lscala/actors/ReplyableReactor$$anon$1;;
Asciz	<init>;
Asciz	(Lscala/actors/ReplyableReactor$$anon$1;Lscala/Function1;)V;
Asciz	LineNumberTable;
Asciz	java/lang/NullPointerException;
class	java/lang/NullPointerException
NameAndType	"<init>":()V
Method	java/lang/NullPointerException."<init>":()V
NameAndType	$outer:Lscala/actors/ReplyableReactor$$anon$1;
Field	scala/actors/ReplyableReactor$$anon$1$$anonfun$respond$1.$outer:Lscala/actors/ReplyableReactor$$anon$1;
NameAndType	k$1:Lscala/Function1;
Field	scala/actors/ReplyableReactor$$anon$1$$anonfun$respond$1.k$1:Lscala/Function1;
Asciz	java/lang/Object;
class	java/lang/Object
Method	java/lang/Object."<init>":()V
Asciz	scala/Function1$class;
class	scala/Function1$class
Asciz	$init$;
Asciz	(Lscala/Function1;)V;
NameAndType	$init$:(Lscala/Function1;)V
Method	scala/Function1$class.$init$:(Lscala/Function1;)V
Asciz	scala/PartialFunction$class;
class	scala/PartialFunction$class
Asciz	(Lscala/PartialFunction;)V;
NameAndType	$init$:(Lscala/PartialFunction;)V
Method	scala/PartialFunction$class.$init$:(Lscala/PartialFunction;)V
Asciz	this;
Asciz	Lscala/actors/ReplyableReactor$$anon$1$$anonfun$respond$1;;
Asciz	LocalVariableTable;
Asciz	apply;
Asciz	(Ljava/lang/Object;)Ljava/lang/Object;;
Asciz	(Ljava/lang/Object;)V;
NameAndType	apply:(Ljava/lang/Object;)V
Method	scala/actors/ReplyableReactor$$anon$1$$anonfun$respond$1.apply:(Ljava/lang/Object;)V
Asciz	scala/runtime/BoxedUnit;
class	scala/runtime/BoxedUnit
Asciz	UNIT;
Asciz	Lscala/runtime/BoxedUnit;;
NameAndType	UNIT:Lscala/runtime/BoxedUnit;
Field	scala/runtime/BoxedUnit.UNIT:Lscala/runtime/BoxedUnit;
Asciz	v1;
Asciz	Ljava/lang/Object;;
Asciz	andThen;
Asciz	(Lscala/Function1;)Lscala/Function1;;
Asciz	scala/PartialFunction;
class	scala/PartialFunction
Asciz	(Lscala/Function1;)Lscala/PartialFunction;;
NameAndType	andThen:(Lscala/Function1;)Lscala/PartialFunction;
InterfaceMethod	scala/PartialFunction.andThen:(Lscala/Function1;)Lscala/PartialFunction;
Asciz	g;
Asciz	isDefinedAt;
Asciz	(Ljava/lang/Object;)Z;
Asciz	(TA;)Z;
Asciz	Signature;
Asciz	scala/Some;
class	scala/Some
NameAndType	"<init>":(Ljava/lang/Object;)V
Method	scala/Some."<init>":(Ljava/lang/Object;)V
Asciz	scala/actors/ReplyableReactor$$anon$1;
class	scala/actors/ReplyableReactor$$anon$1
Asciz	value_$eq;
Asciz	(Lscala/Option;)V;
NameAndType	value_$eq:(Lscala/Option;)V
Method	scala/actors/ReplyableReactor$$anon$1.value_$eq:(Lscala/Option;)V
Asciz	value;
Asciz	()Lscala/Option;;
NameAndType	value:()Lscala/Option;
Method	scala/actors/ReplyableReactor$$anon$1.value:()Lscala/Option;
Asciz	scala/Option;
class	scala/Option
Asciz	get;
Asciz	()Ljava/lang/Object;;
NameAndType	get:()Ljava/lang/Object;
Method	scala/Option.get:()Ljava/lang/Object;
Asciz	scala/Function1;
class	scala/Function1
NameAndType	apply:(Ljava/lang/Object;)Ljava/lang/Object;
InterfaceMethod	scala/Function1.apply:(Ljava/lang/Object;)Ljava/lang/Object;
Asciz	scala/MatchError;
class	scala/MatchError
Asciz	toString;
Asciz	()Ljava/lang/String;;
NameAndType	toString:()Ljava/lang/String;
Method	java/lang/Object.toString:()Ljava/lang/String;
Asciz	(Ljava/lang/String;)V;
NameAndType	"<init>":(Ljava/lang/String;)V
Method	scala/MatchError."<init>":(Ljava/lang/String;)V
Asciz	(TA;)V;
Asciz	compose;
Asciz	(Lscala/Function1;Lscala/Function1;)Lscala/Function1;;
NameAndType	compose:(Lscala/Function1;Lscala/Function1;)Lscala/Function1;
Method	scala/Function1$class.compose:(Lscala/Function1;Lscala/Function1;)Lscala/Function1;
Asciz	(Lscala/Function1;)Ljava/lang/String;;
NameAndType	toString:(Lscala/Function1;)Ljava/lang/String;
Method	scala/Function1$class.toString:(Lscala/Function1;)Ljava/lang/String;
Asciz	(Lscala/PartialFunction;Lscala/Function1;)Lscala/PartialFunction;;
NameAndType	andThen:(Lscala/PartialFunction;Lscala/Function1;)Lscala/PartialFunction;
Method	scala/PartialFunction$class.andThen:(Lscala/PartialFunction;Lscala/Function1;)Lscala/PartialFunction;
Asciz	k;
Asciz	orElse;
Asciz	(Lscala/PartialFunction;)Lscala/PartialFunction;;
Asciz	(Lscala/PartialFunction;Lscala/PartialFunction;)Lscala/PartialFunction;;
NameAndType	orElse:(Lscala/PartialFunction;Lscala/PartialFunction;)Lscala/PartialFunction;
Method	scala/PartialFunction$class.orElse:(Lscala/PartialFunction;Lscala/PartialFunction;)Lscala/PartialFunction;
Asciz	that;
Asciz	Lscala/PartialFunction;;
Asciz	Scala;
Asciz	InnerClasses;
Asciz	scala/actors/ReplyableReactor;
class	scala/actors/ReplyableReactor
Asciz	$anon$1;
Asciz	$anonfun$respond$1;
Asciz	scala/ScalaObject;
class	scala/ScalaObject
Asciz	java/io/Serializable;
class	java/io/Serializable

{
public static final long serialVersionUID;
  Signature: J

private final scala.Function1 k$1;
  Signature: Lscala/Function1;

private final scala.actors.ReplyableReactor$$anon$1 $outer;
  Signature: Lscala/actors/ReplyableReactor$$anon$1;

public static {};
  Signature: ()V
  Code:
   Stack=2, Locals=0, Args_size=0
	lconst_0
	putstatic	Field serialVersionUID:J
	return
  Labels:

public scala.actors.ReplyableReactor$$anon$1$$anonfun$respond$1(scala.actors.ReplyableReactor$$anon$1, scala.Function1);
  Signature: (Lscala/actors/ReplyableReactor$$anon$1;Lscala/Function1;)V
  Code:
   Stack=2, Locals=3, Args_size=3
	aload_1
	ifnonnull	l1 // aload_0
	new	class java/lang/NullPointerException
	dup
	invokespecial	Method java/lang/NullPointerException."<init>":()V
	athrow
l1	aload_0
	aload_1
	putfield	Field $outer:Lscala/actors/ReplyableReactor$$anon$1;
	aload_0
	aload_2
	putfield	Field k$1:Lscala/Function1;
	aload_0
	invokespecial	Method java/lang/Object."<init>":()V
	aload_0
	invokestatic	Method scala/Function1$class.$init$:(Lscala/Function1;)V
	aload_0
	invokestatic	Method scala/PartialFunction$class.$init$:(Lscala/PartialFunction;)V
	return
  Labels:
   	l1 = 12 // aload_0
  LocalVariableTable: 
   Start  Length  Slot  Name   Signature
   0      35      0    this       Lscala/actors/ReplyableReactor$$anon$1$$anonfun$respond$1;
   0      35      1    $outer       Lscala/actors/ReplyableReactor$$anon$1;


public final java.lang.Object apply(java.lang.Object);
  Signature: (Ljava/lang/Object;)Ljava/lang/Object;
  Code:
   Stack=2, Locals=2, Args_size=2
	aload_0
	aload_1
	invokevirtual	Method apply:(Ljava/lang/Object;)V
	getstatic	Field scala/runtime/BoxedUnit.UNIT:Lscala/runtime/BoxedUnit;
	areturn
  Labels:
  LocalVariableTable: 
   Start  Length  Slot  Name   Signature
   0      9      0    this       Lscala/actors/ReplyableReactor$$anon$1$$anonfun$respond$1;
   0      9      1    v1       Ljava/lang/Object;


public scala.Function1 andThen(scala.Function1);
  Signature: (Lscala/Function1;)Lscala/Function1;
  Code:
   Stack=2, Locals=2, Args_size=2
	aload_0
	aload_1
	invokeinterface	InterfaceMethod scala/PartialFunction.andThen:(Lscala/Function1;)Lscala/PartialFunction;
	areturn
  Labels:
  LocalVariableTable: 
   Start  Length  Slot  Name   Signature
   0      8      0    this       Lscala/actors/ReplyableReactor$$anon$1$$anonfun$respond$1;
   0      8      1    g       Lscala/Function1;


public final boolean isDefinedAt(java.lang.Object);
  Signature: (Ljava/lang/Object;)Z
  Code:
   Stack=1, Locals=2, Args_size=2
	iconst_1
	ireturn
  Labels:
  Signature: length = 0x2
   00 43 

public final void apply(java.lang.Object);
  Signature: (Ljava/lang/Object;)V
  Code:
   Stack=4, Locals=2, Args_size=2
	iconst_1
	ifeq	l1 // new
	aload_0
	getfield	Field $outer:Lscala/actors/ReplyableReactor$$anon$1;
	new	class scala/Some
	dup
	aload_1
	invokespecial	Method scala/Some."<init>":(Ljava/lang/Object;)V
	invokevirtual	Method scala/actors/ReplyableReactor$$anon$1.value_$eq:(Lscala/Option;)V
	aload_0
	getfield	Field k$1:Lscala/Function1;
	aload_0
	getfield	Field $outer:Lscala/actors/ReplyableReactor$$anon$1;
	invokevirtual	Method scala/actors/ReplyableReactor$$anon$1.value:()Lscala/Option;
	invokevirtual	Method scala/Option.get:()Ljava/lang/Object;
	invokeinterface	InterfaceMethod scala/Function1.apply:(Ljava/lang/Object;)Ljava/lang/Object;
	pop
	return
l1	new	class scala/MatchError
	dup
	aload_1
	invokevirtual	Method java/lang/Object.toString:()Ljava/lang/String;
	invokespecial	Method scala/MatchError."<init>":(Ljava/lang/String;)V
	athrow
  Labels:
   	l1 = 40 // new
  Signature: length = 0x2
   00 66 

public scala.Function1 compose(scala.Function1);
  Signature: (Lscala/Function1;)Lscala/Function1;
  Code:
   Stack=2, Locals=2, Args_size=2
	aload_0
	aload_1
	invokestatic	Method scala/Function1$class.compose:(Lscala/Function1;Lscala/Function1;)Lscala/Function1;
	areturn
  Labels:
  LocalVariableTable: 
   Start  Length  Slot  Name   Signature
   0      6      0    this       Lscala/actors/ReplyableReactor$$anon$1$$anonfun$respond$1;
   0      6      1    g       Lscala/Function1;


public java.lang.String toString();
  Signature: ()Ljava/lang/String;
  Code:
   Stack=1, Locals=1, Args_size=1
	aload_0
	invokestatic	Method scala/Function1$class.toString:(Lscala/Function1;)Ljava/lang/String;
	areturn
  Labels:

public scala.PartialFunction andThen(scala.Function1);
  Signature: (Lscala/Function1;)Lscala/PartialFunction;
  Code:
   Stack=2, Locals=2, Args_size=2
	aload_0
	aload_1
	invokestatic	Method scala/PartialFunction$class.andThen:(Lscala/PartialFunction;Lscala/Function1;)Lscala/PartialFunction;
	areturn
  Labels:
  LocalVariableTable: 
   Start  Length  Slot  Name   Signature
   0      6      0    this       Lscala/actors/ReplyableReactor$$anon$1$$anonfun$respond$1;
   0      6      1    k       Lscala/Function1;


public scala.PartialFunction orElse(scala.PartialFunction);
  Signature: (Lscala/PartialFunction;)Lscala/PartialFunction;
  Code:
   Stack=2, Locals=2, Args_size=2
	aload_0
	aload_1
	invokestatic	Method scala/PartialFunction$class.orElse:(Lscala/PartialFunction;Lscala/PartialFunction;)Lscala/PartialFunction;
	areturn
  Labels:
  LocalVariableTable: 
   Start  Length  Slot  Name   Signature
   0      6      0    this       Lscala/actors/ReplyableReactor$$anon$1$$anonfun$respond$1;
   0      6      1    that       Lscala/PartialFunction;


}

