Compiled from "ReplyableActor.scala"
public abstract class scala.actors.ReplyableActor$class extends java.lang.Object
  SourceFile: "ReplyableActor.scala"
  Scala: length = 0x
   
  InnerClass: 
   public final #104= #61 of #103; //$anon$3=class scala/actors/ReplyableActor$$anon$3 of class scala/actors/ReplyableActor
   public final #105= #52 of #103; //$anon$2=class scala/actors/ReplyableActor$$anon$2 of class scala/actors/ReplyableActor
   public final #106= #35 of #103; //$anon$1=class scala/actors/ReplyableActor$$anon$1 of class scala/actors/ReplyableActor
   public final #107= #94 of #103; //$anonfun$$bang$qmark$1=class scala/actors/ReplyableActor$$anonfun$$bang$qmark$1 of class scala/actors/ReplyableActor
   public final #108= #80 of #103; //$anonfun$$bang$qmark$2=class scala/actors/ReplyableActor$$anonfun$$bang$qmark$2 of class scala/actors/ReplyableActor
  minor version: 0
  major version: 49
  Constant pool:
const #1 = Asciz	SourceFile;
const #2 = Asciz	ReplyableActor.scala;
const #3 = Asciz	$init$;
const #4 = Asciz	(Lscala/actors/ReplyableActor;)V;
const #5 = Asciz	Code;
const #6 = Asciz	LineNumberTable;
const #7 = Asciz	$this;
const #8 = Asciz	Lscala/actors/ReplyableActor;;
const #9 = Asciz	LocalVariableTable;
const #10 = Asciz	$bang$bang;
const #11 = Asciz	(Lscala/actors/ReplyableActor;Ljava/lang/Object;)Lscala/actors/Future;;
const #12 = Asciz	scala/actors/Channel;
const #13 = class	#12;	//  scala/actors/Channel
const #14 = Asciz	scala/actors/Actor$;
const #15 = class	#14;	//  scala/actors/Actor$
const #16 = Asciz	MODULE$;
const #17 = Asciz	Lscala/actors/Actor$;;
const #18 = NameAndType	#16:#17;//  MODULE$:Lscala/actors/Actor$;
const #19 = Field	#15.#18;	//  scala/actors/Actor$.MODULE$:Lscala/actors/Actor$;
const #20 = Asciz	scala/actors/Reactor;
const #21 = class	#20;	//  scala/actors/Reactor
const #22 = Asciz	scheduler;
const #23 = Asciz	()Lscala/actors/IScheduler;;
const #24 = NameAndType	#22:#23;//  scheduler:()Lscala/actors/IScheduler;
const #25 = InterfaceMethod	#21.#24;	//  scala/actors/Reactor.scheduler:()Lscala/actors/IScheduler;
const #26 = Asciz	self;
const #27 = Asciz	(Lscala/actors/IScheduler;)Lscala/actors/Actor;;
const #28 = NameAndType	#26:#27;//  self:(Lscala/actors/IScheduler;)Lscala/actors/Actor;
const #29 = Method	#15.#28;	//  scala/actors/Actor$.self:(Lscala/actors/IScheduler;)Lscala/actors/Actor;
const #30 = Asciz	<init>;
const #31 = Asciz	(Lscala/actors/Actor;)V;
const #32 = NameAndType	#30:#31;//  "<init>":(Lscala/actors/Actor;)V
const #33 = Method	#13.#32;	//  scala/actors/Channel."<init>":(Lscala/actors/Actor;)V
const #34 = Asciz	scala/actors/ReplyableActor$$anon$1;
const #35 = class	#34;	//  scala/actors/ReplyableActor$$anon$1
const #36 = Asciz	(Lscala/actors/ReplyableActor;Lscala/actors/Channel;)V;
const #37 = NameAndType	#30:#36;//  "<init>":(Lscala/actors/ReplyableActor;Lscala/actors/Channel;)V
const #38 = Method	#35.#37;	//  scala/actors/ReplyableActor$$anon$1."<init>":(Lscala/actors/ReplyableActor;Lscala/actors/Channel;)V
const #39 = Asciz	scala/actors/AbstractActor;
const #40 = class	#39;	//  scala/actors/AbstractActor
const #41 = Asciz	linkTo;
const #42 = Asciz	(Lscala/actors/AbstractActor;)V;
const #43 = NameAndType	#41:#42;//  linkTo:(Lscala/actors/AbstractActor;)V
const #44 = InterfaceMethod	#40.#43;	//  scala/actors/AbstractActor.linkTo:(Lscala/actors/AbstractActor;)V
const #45 = Asciz	scala/actors/OutputChannel;
const #46 = class	#45;	//  scala/actors/OutputChannel
const #47 = Asciz	send;
const #48 = Asciz	(Ljava/lang/Object;Lscala/actors/OutputChannel;)V;
const #49 = NameAndType	#47:#48;//  send:(Ljava/lang/Object;Lscala/actors/OutputChannel;)V
const #50 = InterfaceMethod	#21.#49;	//  scala/actors/Reactor.send:(Ljava/lang/Object;Lscala/actors/OutputChannel;)V
const #51 = Asciz	scala/actors/ReplyableActor$$anon$2;
const #52 = class	#51;	//  scala/actors/ReplyableActor$$anon$2
const #53 = Method	#52.#37;	//  scala/actors/ReplyableActor$$anon$2."<init>":(Lscala/actors/ReplyableActor;Lscala/actors/Channel;)V
const #54 = Asciz	msg;
const #55 = Asciz	Ljava/lang/Object;;
const #56 = Asciz	ftch$2;
const #57 = Asciz	Lscala/actors/Channel;;
const #58 = Asciz	linkedChannel;
const #59 = Asciz	(Lscala/actors/ReplyableActor;Ljava/lang/Object;Lscala/PartialFunction;)Lscala/actors/Future;;
const #60 = Asciz	scala/actors/ReplyableActor$$anon$3;
const #61 = class	#60;	//  scala/actors/ReplyableActor$$anon$3
const #62 = Asciz	(Lscala/actors/ReplyableActor;Lscala/PartialFunction;Lscala/actors/Channel;)V;
const #63 = NameAndType	#30:#62;//  "<init>":(Lscala/actors/ReplyableActor;Lscala/PartialFunction;Lscala/actors/Channel;)V
const #64 = Method	#61.#63;	//  scala/actors/ReplyableActor$$anon$3."<init>":(Lscala/actors/ReplyableActor;Lscala/PartialFunction;Lscala/actors/Channel;)V
const #65 = Asciz	scala/actors/Futures$;
const #66 = class	#65;	//  scala/actors/Futures$
const #67 = Asciz	Lscala/actors/Futures$;;
const #68 = NameAndType	#16:#67;//  MODULE$:Lscala/actors/Futures$;
const #69 = Field	#66.#68;	//  scala/actors/Futures$.MODULE$:Lscala/actors/Futures$;
const #70 = Asciz	fromInputChannel;
const #71 = Asciz	(Lscala/actors/InputChannel;)Lscala/actors/Future;;
const #72 = NameAndType	#70:#71;//  fromInputChannel:(Lscala/actors/InputChannel;)Lscala/actors/Future;
const #73 = Method	#66.#72;	//  scala/actors/Futures$.fromInputChannel:(Lscala/actors/InputChannel;)Lscala/actors/Future;
const #74 = Asciz	f$1;
const #75 = Asciz	Lscala/PartialFunction;;
const #76 = Asciz	ftch$1;
const #77 = Asciz	$bang$qmark;
const #78 = Asciz	(Lscala/actors/ReplyableActor;JLjava/lang/Object;)Lscala/Option;;
const #79 = Asciz	scala/actors/ReplyableActor$$anonfun$$bang$qmark$2;
const #80 = class	#79;	//  scala/actors/ReplyableActor$$anonfun$$bang$qmark$2
const #81 = NameAndType	#30:#4;//  "<init>":(Lscala/actors/ReplyableActor;)V
const #82 = Method	#80.#81;	//  scala/actors/ReplyableActor$$anonfun$$bang$qmark$2."<init>":(Lscala/actors/ReplyableActor;)V
const #83 = Asciz	receiveWithin;
const #84 = Asciz	(JLscala/PartialFunction;)Ljava/lang/Object;;
const #85 = NameAndType	#83:#84;//  receiveWithin:(JLscala/PartialFunction;)Ljava/lang/Object;
const #86 = Method	#13.#85;	//  scala/actors/Channel.receiveWithin:(JLscala/PartialFunction;)Ljava/lang/Object;
const #87 = Asciz	scala/Option;
const #88 = class	#87;	//  scala/Option
const #89 = Asciz	msec;
const #90 = Asciz	J;
const #91 = Asciz	replyCh;
const #92 = Asciz	(Lscala/actors/ReplyableActor;Ljava/lang/Object;)Ljava/lang/Object;;
const #93 = Asciz	scala/actors/ReplyableActor$$anonfun$$bang$qmark$1;
const #94 = class	#93;	//  scala/actors/ReplyableActor$$anonfun$$bang$qmark$1
const #95 = Method	#94.#81;	//  scala/actors/ReplyableActor$$anonfun$$bang$qmark$1."<init>":(Lscala/actors/ReplyableActor;)V
const #96 = Asciz	receive;
const #97 = Asciz	(Lscala/PartialFunction;)Ljava/lang/Object;;
const #98 = NameAndType	#96:#97;//  receive:(Lscala/PartialFunction;)Ljava/lang/Object;
const #99 = Method	#13.#98;	//  scala/actors/Channel.receive:(Lscala/PartialFunction;)Ljava/lang/Object;
const #100 = Asciz	Scala;
const #101 = Asciz	InnerClasses;
const #102 = Asciz	scala/actors/ReplyableActor;
const #103 = class	#102;	//  scala/actors/ReplyableActor
const #104 = Asciz	$anon$3;
const #105 = Asciz	$anon$2;
const #106 = Asciz	$anon$1;
const #107 = Asciz	$anonfun$$bang$qmark$1;
const #108 = Asciz	$anonfun$$bang$qmark$2;
const #109 = Asciz	scala/actors/ReplyableActor$class;
const #110 = class	#109;	//  scala/actors/ReplyableActor$class
const #111 = Asciz	java/lang/Object;
const #112 = class	#111;	//  java/lang/Object

{
public static void $init$(scala.actors.ReplyableActor);
  Code:
   Stack=0, Locals=1, Args_size=1
   0:	return
  LineNumberTable: 
   line 22: 0

  LocalVariableTable: 
   Start  Length  Slot  Name   Signature
   0      1      0    $this       Lscala/actors/ReplyableActor;


public static scala.actors.Future $bang$bang(scala.actors.ReplyableActor, java.lang.Object);
  Code:
   Stack=4, Locals=4, Args_size=2
   0:	new	#13; //class scala/actors/Channel
   3:	dup
   4:	getstatic	#19; //Field scala/actors/Actor$.MODULE$:Lscala/actors/Actor$;
   7:	aload_0
   8:	checkcast	#21; //class scala/actors/Reactor
   11:	invokeinterface	#25,  1; //InterfaceMethod scala/actors/Reactor.scheduler:()Lscala/actors/IScheduler;
   16:	invokevirtual	#29; //Method scala/actors/Actor$.self:(Lscala/actors/IScheduler;)Lscala/actors/Actor;
   19:	invokespecial	#33; //Method scala/actors/Channel."<init>":(Lscala/actors/Actor;)V
   22:	astore_2
   23:	new	#35; //class scala/actors/ReplyableActor$$anon$1
   26:	dup
   27:	aload_0
   28:	aload_2
   29:	invokespecial	#38; //Method scala/actors/ReplyableActor$$anon$1."<init>":(Lscala/actors/ReplyableActor;Lscala/actors/Channel;)V
   32:	astore_3
   33:	aload_0
   34:	checkcast	#40; //class scala/actors/AbstractActor
   37:	aload_3
   38:	checkcast	#40; //class scala/actors/AbstractActor
   41:	invokeinterface	#44,  2; //InterfaceMethod scala/actors/AbstractActor.linkTo:(Lscala/actors/AbstractActor;)V
   46:	aload_0
   47:	checkcast	#21; //class scala/actors/Reactor
   50:	aload_1
   51:	aload_3
   52:	checkcast	#46; //class scala/actors/OutputChannel
   55:	invokeinterface	#50,  3; //InterfaceMethod scala/actors/Reactor.send:(Ljava/lang/Object;Lscala/actors/OutputChannel;)V
   60:	new	#52; //class scala/actors/ReplyableActor$$anon$2
   63:	dup
   64:	aload_0
   65:	aload_2
   66:	invokespecial	#53; //Method scala/actors/ReplyableActor$$anon$2."<init>":(Lscala/actors/ReplyableActor;Lscala/actors/Channel;)V
   69:	areturn
  LineNumberTable: 
   line 85: 0
   line 86: 23
   line 118: 28
   line 86: 29
   line 116: 33
   line 117: 37
   line 116: 38
   line 117: 46
   line 118: 60

  LocalVariableTable: 
   Start  Length  Slot  Name   Signature
   0      70      0    $this       Lscala/actors/ReplyableActor;
   0      70      1    msg       Ljava/lang/Object;
   23      46      2    ftch$2       Lscala/actors/Channel;
   33      36      3    linkedChannel       Ljava/lang/Object;


public static scala.actors.Future $bang$bang(scala.actors.ReplyableActor, java.lang.Object, scala.PartialFunction);
  Code:
   Stack=7, Locals=4, Args_size=3
   0:	new	#13; //class scala/actors/Channel
   3:	dup
   4:	getstatic	#19; //Field scala/actors/Actor$.MODULE$:Lscala/actors/Actor$;
   7:	aload_0
   8:	checkcast	#21; //class scala/actors/Reactor
   11:	invokeinterface	#25,  1; //InterfaceMethod scala/actors/Reactor.scheduler:()Lscala/actors/IScheduler;
   16:	invokevirtual	#29; //Method scala/actors/Actor$.self:(Lscala/actors/IScheduler;)Lscala/actors/Actor;
   19:	invokespecial	#33; //Method scala/actors/Channel."<init>":(Lscala/actors/Actor;)V
   22:	astore_3
   23:	aload_0
   24:	checkcast	#21; //class scala/actors/Reactor
   27:	aload_1
   28:	new	#61; //class scala/actors/ReplyableActor$$anon$3
   31:	dup
   32:	aload_0
   33:	aload_2
   34:	aload_3
   35:	invokespecial	#64; //Method scala/actors/ReplyableActor$$anon$3."<init>":(Lscala/actors/ReplyableActor;Lscala/PartialFunction;Lscala/actors/Channel;)V
   38:	invokeinterface	#50,  3; //InterfaceMethod scala/actors/Reactor.send:(Ljava/lang/Object;Lscala/actors/OutputChannel;)V
   43:	getstatic	#69; //Field scala/actors/Futures$.MODULE$:Lscala/actors/Futures$;
   46:	aload_3
   47:	invokevirtual	#73; //Method scala/actors/Futures$.fromInputChannel:(Lscala/actors/InputChannel;)Lscala/actors/Future;
   50:	areturn
  LineNumberTable: 
   line 66: 0
   line 67: 23
   line 77: 34
   line 67: 35
   line 77: 43

  LocalVariableTable: 
   Start  Length  Slot  Name   Signature
   0      51      0    $this       Lscala/actors/ReplyableActor;
   0      51      1    msg       Ljava/lang/Object;
   0      51      2    f$1       Lscala/PartialFunction;
   23      27      3    ftch$1       Lscala/actors/Channel;


public static scala.Option $bang$qmark(scala.actors.ReplyableActor, long, java.lang.Object);
  Code:
   Stack=6, Locals=5, Args_size=3
   0:	new	#13; //class scala/actors/Channel
   3:	dup
   4:	getstatic	#19; //Field scala/actors/Actor$.MODULE$:Lscala/actors/Actor$;
   7:	aload_0
   8:	checkcast	#21; //class scala/actors/Reactor
   11:	invokeinterface	#25,  1; //InterfaceMethod scala/actors/Reactor.scheduler:()Lscala/actors/IScheduler;
   16:	invokevirtual	#29; //Method scala/actors/Actor$.self:(Lscala/actors/IScheduler;)Lscala/actors/Actor;
   19:	invokespecial	#33; //Method scala/actors/Channel."<init>":(Lscala/actors/Actor;)V
   22:	astore	4
   24:	aload_0
   25:	checkcast	#21; //class scala/actors/Reactor
   28:	aload_3
   29:	aload	4
   31:	invokeinterface	#50,  3; //InterfaceMethod scala/actors/Reactor.send:(Ljava/lang/Object;Lscala/actors/OutputChannel;)V
   36:	aload	4
   38:	lload_1
   39:	new	#80; //class scala/actors/ReplyableActor$$anonfun$$bang$qmark$2
   42:	dup
   43:	aload_0
   44:	invokespecial	#82; //Method scala/actors/ReplyableActor$$anonfun$$bang$qmark$2."<init>":(Lscala/actors/ReplyableActor;)V
   47:	invokevirtual	#86; //Method scala/actors/Channel.receiveWithin:(JLscala/PartialFunction;)Ljava/lang/Object;
   50:	checkcast	#88; //class scala/Option
   53:	areturn
  LineNumberTable: 
   line 50: 0
   line 51: 24
   line 52: 29
   line 51: 31
   line 52: 36

  LocalVariableTable: 
   Start  Length  Slot  Name   Signature
   0      54      0    $this       Lscala/actors/ReplyableActor;
   0      54      1    msec       J
   0      54      3    msg       Ljava/lang/Object;
   24      29      4    replyCh       Lscala/actors/Channel;


public static java.lang.Object $bang$qmark(scala.actors.ReplyableActor, java.lang.Object);
  Code:
   Stack=4, Locals=3, Args_size=2
   0:	new	#13; //class scala/actors/Channel
   3:	dup
   4:	getstatic	#19; //Field scala/actors/Actor$.MODULE$:Lscala/actors/Actor$;
   7:	aload_0
   8:	checkcast	#21; //class scala/actors/Reactor
   11:	invokeinterface	#25,  1; //InterfaceMethod scala/actors/Reactor.scheduler:()Lscala/actors/IScheduler;
   16:	invokevirtual	#29; //Method scala/actors/Actor$.self:(Lscala/actors/IScheduler;)Lscala/actors/Actor;
   19:	invokespecial	#33; //Method scala/actors/Channel."<init>":(Lscala/actors/Actor;)V
   22:	astore_2
   23:	aload_0
   24:	checkcast	#21; //class scala/actors/Reactor
   27:	aload_1
   28:	aload_2
   29:	invokeinterface	#50,  3; //InterfaceMethod scala/actors/Reactor.send:(Ljava/lang/Object;Lscala/actors/OutputChannel;)V
   34:	aload_2
   35:	new	#94; //class scala/actors/ReplyableActor$$anonfun$$bang$qmark$1
   38:	dup
   39:	aload_0
   40:	invokespecial	#95; //Method scala/actors/ReplyableActor$$anonfun$$bang$qmark$1."<init>":(Lscala/actors/ReplyableActor;)V
   43:	invokevirtual	#99; //Method scala/actors/Channel.receive:(Lscala/PartialFunction;)Ljava/lang/Object;
   46:	areturn
  LineNumberTable: 
   line 33: 0
   line 34: 23
   line 35: 28
   line 34: 29
   line 35: 34

  LocalVariableTable: 
   Start  Length  Slot  Name   Signature
   0      47      0    $this       Lscala/actors/ReplyableActor;
   0      47      1    msg       Ljava/lang/Object;
   23      23      2    replyCh       Lscala/actors/Channel;


}

