Compiled from "Scheduler.scala"
public final class scala.actors.Scheduler$ extends java.lang.Object implements scala.actors.scheduler.DelegatingScheduler,scala.ScalaObject
  SourceFile: "Scheduler.scala"
  Scala: length = 0x
   
  minor version: 0
  major version: 49
  Constant pool:
Asciz	SourceFile;
Asciz	Scheduler.scala;
Asciz	Scala;
Asciz	MODULE$;
Asciz	Lscala/actors/Scheduler$;;
Asciz	<clinit>;
Asciz	()V;
Asciz	Code;
Asciz	scala/actors/Scheduler$;
class	scala/actors/Scheduler$
Asciz	<init>;
NameAndType	"<init>":()V
Method	scala/actors/Scheduler$."<init>":()V
Asciz	sched;
Asciz	Lscala/actors/IScheduler;;
Asciz	LineNumberTable;
Asciz	java/lang/Object;
class	java/lang/Object
Method	java/lang/Object."<init>":()V
NameAndType	MODULE$:Lscala/actors/Scheduler$;
Field	scala/actors/Scheduler$.MODULE$:Lscala/actors/Scheduler$;
Asciz	scala/actors/IScheduler$class;
class	scala/actors/IScheduler$class
Asciz	$init$;
Asciz	(Lscala/actors/IScheduler;)V;
NameAndType	$init$:(Lscala/actors/IScheduler;)V
Method	scala/actors/IScheduler$class.$init$:(Lscala/actors/IScheduler;)V
Asciz	scala/actors/scheduler/DelegatingScheduler$class;
class	scala/actors/scheduler/DelegatingScheduler$class
Asciz	(Lscala/actors/scheduler/DelegatingScheduler;)V;
NameAndType	$init$:(Lscala/actors/scheduler/DelegatingScheduler;)V
Method	scala/actors/scheduler/DelegatingScheduler$class.$init$:(Lscala/actors/scheduler/DelegatingScheduler;)V
Asciz	scala/actors/Debug$;
class	scala/actors/Debug$
Asciz	Lscala/actors/Debug$;;
NameAndType	MODULE$:Lscala/actors/Debug$;
Field	scala/actors/Debug$.MODULE$:Lscala/actors/Debug$;
Asciz	scala/collection/mutable/StringBuilder;
class	scala/collection/mutable/StringBuilder
Method	scala/collection/mutable/StringBuilder."<init>":()V
Asciz	initializing ;
String	initializing 
Asciz	append;
Asciz	(Ljava/lang/Object;)Lscala/collection/mutable/StringBuilder;;
NameAndType	append:(Ljava/lang/Object;)Lscala/collection/mutable/StringBuilder;
Method	scala/collection/mutable/StringBuilder.append:(Ljava/lang/Object;)Lscala/collection/mutable/StringBuilder;
Asciz	...;
String	...
Asciz	toString;
Asciz	()Ljava/lang/String;;
NameAndType	toString:()Ljava/lang/String;
Method	scala/collection/mutable/StringBuilder.toString:()Ljava/lang/String;
Asciz	info;
Asciz	(Ljava/lang/String;)V;
NameAndType	info:(Ljava/lang/String;)V
Method	scala/actors/Debug$.info:(Ljava/lang/String;)V
Asciz	restart;
NameAndType	sched:Lscala/actors/IScheduler;
Field	scala/actors/Scheduler$.sched:Lscala/actors/IScheduler;
Asciz	scala/actors/scheduler/ForkJoinScheduler;
class	scala/actors/scheduler/ForkJoinScheduler
NameAndType	restart:()V
Method	scala/actors/scheduler/ForkJoinScheduler.restart:()V
Asciz	scheduler does not implement restart;
String	scheduler does not implement restart
Asciz	java/lang/RuntimeException;
class	java/lang/RuntimeException
NameAndType	"<init>":(Ljava/lang/String;)V
Method	java/lang/RuntimeException."<init>":(Ljava/lang/String;)V
Asciz	this;
Asciz	LocalVariableTable;
Asciz	snapshot;
NameAndType	snapshot:()V
Method	scala/actors/scheduler/ForkJoinScheduler.snapshot:()V
Asciz	scheduler does not implement snapshot;
String	scheduler does not implement snapshot
Asciz	makeNewScheduler;
Asciz	()Lscala/actors/IScheduler;;
Asciz	java.vm.vendor;
String	java.vm.vendor
Asciz	java/lang/System;
class	java/lang/System
Asciz	getProperty;
Asciz	(Ljava/lang/String;)Ljava/lang/String;;
NameAndType	getProperty:(Ljava/lang/String;)Ljava/lang/String;
Method	java/lang/System.getProperty:(Ljava/lang/String;)Ljava/lang/String;
Asciz	IBM;
String	IBM
Asciz	java/lang/String;
class	java/lang/String
Asciz	indexOf;
Asciz	(Ljava/lang/String;)I;
NameAndType	indexOf:(Ljava/lang/String;)I
Method	java/lang/String.indexOf:(Ljava/lang/String;)I
Asciz	scala/runtime/StringAdd;
class	scala/runtime/StringAdd
Asciz	(Ljava/lang/Object;)V;
NameAndType	"<init>":(Ljava/lang/Object;)V
Method	scala/runtime/StringAdd."<init>":(Ljava/lang/Object;)V
Asciz	: running on a ;
String	: running on a 
Asciz	$plus;
NameAndType	$plus:(Ljava/lang/String;)Ljava/lang/String;
Method	scala/runtime/StringAdd.$plus:(Ljava/lang/String;)Ljava/lang/String;
Asciz	 JVM;
String	 JVM
Asciz	scala/actors/scheduler/ResizableThreadPoolScheduler;
class	scala/actors/scheduler/ResizableThreadPoolScheduler
Asciz	(Z)V;
NameAndType	"<init>":(Z)V
Method	scala/actors/scheduler/ResizableThreadPoolScheduler."<init>":(Z)V
Asciz	start;
NameAndType	start:()V
Method	scala/actors/scheduler/ResizableThreadPoolScheduler.start:()V
Method	scala/actors/scheduler/ForkJoinScheduler."<init>":()V
Method	scala/actors/scheduler/ForkJoinScheduler.start:()V
Asciz	: starting new ;
String	: starting new 
Asciz	 [;
String	 [
Asciz	getClass;
Asciz	()Ljava/lang/Class;;
NameAndType	getClass:()Ljava/lang/Class;
Method	java/lang/Object.getClass:()Ljava/lang/Class;
Asciz	];
String	]
Asciz	jvmVendor;
Asciz	Ljava/lang/String;;
Asciz	s;
Asciz	Lscala/actors/scheduler/ResizableThreadPoolScheduler;;
Asciz	Lscala/actors/scheduler/ForkJoinScheduler;;
Asciz	printActorDump;
NameAndType	printActorDump:(Lscala/actors/IScheduler;)V
Method	scala/actors/IScheduler$class.printActorDump:(Lscala/actors/IScheduler;)V
Asciz	onLockup;
Asciz	(ILscala/Function0;)V;
Asciz	(Lscala/actors/IScheduler;ILscala/Function0;)V;
NameAndType	onLockup:(Lscala/actors/IScheduler;ILscala/Function0;)V
Method	scala/actors/IScheduler$class.onLockup:(Lscala/actors/IScheduler;ILscala/Function0;)V
Asciz	millis;
Asciz	I;
Asciz	handler;
Asciz	Lscala/Function0;;
Asciz	(Lscala/Function0;)V;
Asciz	(Lscala/actors/IScheduler;Lscala/Function0;)V;
NameAndType	onLockup:(Lscala/actors/IScheduler;Lscala/Function0;)V
Method	scala/actors/IScheduler$class.onLockup:(Lscala/actors/IScheduler;Lscala/Function0;)V
Asciz	tick;
Asciz	(Lscala/actors/Actor;)V;
Asciz	(Lscala/actors/IScheduler;Lscala/actors/Actor;)V;
NameAndType	tick:(Lscala/actors/IScheduler;Lscala/actors/Actor;)V
Method	scala/actors/IScheduler$class.tick:(Lscala/actors/IScheduler;Lscala/actors/Actor;)V
Asciz	a;
Asciz	Lscala/actors/Actor;;
Asciz	managedBlock;
Asciz	(Lscala/concurrent/ManagedBlocker;)V;
Asciz	(Lscala/actors/scheduler/DelegatingScheduler;Lscala/concurrent/ManagedBlocker;)V;
NameAndType	managedBlock:(Lscala/actors/scheduler/DelegatingScheduler;Lscala/concurrent/ManagedBlocker;)V
Method	scala/actors/scheduler/DelegatingScheduler$class.managedBlock:(Lscala/actors/scheduler/DelegatingScheduler;Lscala/concurrent/ManagedBlocker;)V
Asciz	blocker;
Asciz	Lscala/concurrent/ManagedBlocker;;
Asciz	onTerminate;
Asciz	(Lscala/actors/Reactor;Lscala/Function0;)V;
Asciz	(Lscala/actors/scheduler/DelegatingScheduler;Lscala/actors/Reactor;Lscala/Function0;)V;
NameAndType	onTerminate:(Lscala/actors/scheduler/DelegatingScheduler;Lscala/actors/Reactor;Lscala/Function0;)V
Method	scala/actors/scheduler/DelegatingScheduler$class.onTerminate:(Lscala/actors/scheduler/DelegatingScheduler;Lscala/actors/Reactor;Lscala/Function0;)V
Asciz	actor;
Asciz	Lscala/actors/Reactor;;
Asciz	f;
Asciz	terminated;
Asciz	(Lscala/actors/Reactor;)V;
Asciz	(Lscala/actors/scheduler/DelegatingScheduler;Lscala/actors/Reactor;)V;
NameAndType	terminated:(Lscala/actors/scheduler/DelegatingScheduler;Lscala/actors/Reactor;)V
Method	scala/actors/scheduler/DelegatingScheduler$class.terminated:(Lscala/actors/scheduler/DelegatingScheduler;Lscala/actors/Reactor;)V
Asciz	newActor;
NameAndType	newActor:(Lscala/actors/scheduler/DelegatingScheduler;Lscala/actors/Reactor;)V
Method	scala/actors/scheduler/DelegatingScheduler$class.newActor:(Lscala/actors/scheduler/DelegatingScheduler;Lscala/actors/Reactor;)V
Asciz	shutdown;
NameAndType	shutdown:(Lscala/actors/scheduler/DelegatingScheduler;)V
Method	scala/actors/scheduler/DelegatingScheduler$class.shutdown:(Lscala/actors/scheduler/DelegatingScheduler;)V
Asciz	executeFromActor;
Asciz	(Ljava/lang/Runnable;)V;
Asciz	(Lscala/actors/scheduler/DelegatingScheduler;Ljava/lang/Runnable;)V;
NameAndType	executeFromActor:(Lscala/actors/scheduler/DelegatingScheduler;Ljava/lang/Runnable;)V
Method	scala/actors/scheduler/DelegatingScheduler$class.executeFromActor:(Lscala/actors/scheduler/DelegatingScheduler;Ljava/lang/Runnable;)V
Asciz	task;
Asciz	Ljava/lang/Runnable;;
Asciz	execute;
NameAndType	execute:(Lscala/actors/scheduler/DelegatingScheduler;Ljava/lang/Runnable;)V
Method	scala/actors/scheduler/DelegatingScheduler$class.execute:(Lscala/actors/scheduler/DelegatingScheduler;Ljava/lang/Runnable;)V
Asciz	(Lscala/actors/scheduler/DelegatingScheduler;Lscala/Function0;)V;
NameAndType	execute:(Lscala/actors/scheduler/DelegatingScheduler;Lscala/Function0;)V
Method	scala/actors/scheduler/DelegatingScheduler$class.execute:(Lscala/actors/scheduler/DelegatingScheduler;Lscala/Function0;)V
Asciz	fun;
Asciz	isActive;
Asciz	()Z;
Asciz	(Lscala/actors/scheduler/DelegatingScheduler;)Z;
NameAndType	isActive:(Lscala/actors/scheduler/DelegatingScheduler;)Z
Method	scala/actors/scheduler/DelegatingScheduler$class.isActive:(Lscala/actors/scheduler/DelegatingScheduler;)Z
Asciz	impl_$eq;
Asciz	(Lscala/actors/scheduler/DelegatingScheduler;Lscala/actors/IScheduler;)V;
NameAndType	impl_$eq:(Lscala/actors/scheduler/DelegatingScheduler;Lscala/actors/IScheduler;)V
Method	scala/actors/scheduler/DelegatingScheduler$class.impl_$eq:(Lscala/actors/scheduler/DelegatingScheduler;Lscala/actors/IScheduler;)V
Asciz	scheduler;
Asciz	impl;
Asciz	(Lscala/actors/scheduler/DelegatingScheduler;)Lscala/actors/IScheduler;;
NameAndType	impl:(Lscala/actors/scheduler/DelegatingScheduler;)Lscala/actors/IScheduler;
Method	scala/actors/scheduler/DelegatingScheduler$class.impl:(Lscala/actors/scheduler/DelegatingScheduler;)Lscala/actors/IScheduler;
Asciz	sched_$eq;
Asciz	scala/actors/scheduler/DelegatingScheduler;
class	scala/actors/scheduler/DelegatingScheduler
Asciz	scala/ScalaObject;
class	scala/ScalaObject

{
public static final scala.actors.Scheduler$ MODULE$;
  Signature: Lscala/actors/Scheduler$;

private scala.actors.IScheduler sched;
  Signature: Lscala/actors/IScheduler;

public static {};
  Signature: ()V
  Code:
   Stack=1, Locals=0, Args_size=0
	new	class scala/actors/Scheduler$
	invokespecial	Method "<init>":()V
	return
  Labels:

private scala.actors.Scheduler$();
  Signature: ()V
  Code:
   Stack=3, Locals=1, Args_size=1
	aload_0
	invokespecial	Method java/lang/Object."<init>":()V
	aload_0
	putstatic	Field MODULE$:Lscala/actors/Scheduler$;
	aload_0
	invokestatic	Method scala/actors/IScheduler$class.$init$:(Lscala/actors/IScheduler;)V
	aload_0
	invokestatic	Method scala/actors/scheduler/DelegatingScheduler$class.$init$:(Lscala/actors/scheduler/DelegatingScheduler;)V
	getstatic	Field scala/actors/Debug$.MODULE$:Lscala/actors/Debug$;
	new	class scala/collection/mutable/StringBuilder
	dup
	invokespecial	Method scala/collection/mutable/StringBuilder."<init>":()V
	ldc	String initializing 
	invokevirtual	Method scala/collection/mutable/StringBuilder.append:(Ljava/lang/Object;)Lscala/collection/mutable/StringBuilder;
	aload_0
	invokevirtual	Method scala/collection/mutable/StringBuilder.append:(Ljava/lang/Object;)Lscala/collection/mutable/StringBuilder;
	ldc	String ...
	invokevirtual	Method scala/collection/mutable/StringBuilder.append:(Ljava/lang/Object;)Lscala/collection/mutable/StringBuilder;
	invokevirtual	Method scala/collection/mutable/StringBuilder.toString:()Ljava/lang/String;
	invokevirtual	Method scala/actors/Debug$.info:(Ljava/lang/String;)V
	return
  Labels:

public void restart();
  Signature: ()V
  Code:
   Stack=3, Locals=2, Args_size=1
	aload_0
	getfield	Field sched:Lscala/actors/IScheduler;
	instanceof	class scala/actors/scheduler/ForkJoinScheduler
	ifeq	l1 // ldc
	aload_0
	getfield	Field sched:Lscala/actors/IScheduler;
	checkcast	class scala/actors/scheduler/ForkJoinScheduler
	invokevirtual	Method scala/actors/scheduler/ForkJoinScheduler.restart:()V
	return
l1	ldc	String scheduler does not implement restart
	astore_1
	new	class java/lang/RuntimeException
	dup
	aload_1
	invokespecial	Method java/lang/RuntimeException."<init>":(Ljava/lang/String;)V
	athrow
  Labels:
   	l1 = 21 // ldc
  LocalVariableTable: 
   Start  Length  Slot  Name   Signature
   0      33      0    this       Lscala/actors/Scheduler$;


public void snapshot();
  Signature: ()V
  Code:
   Stack=3, Locals=2, Args_size=1
	aload_0
	getfield	Field sched:Lscala/actors/IScheduler;
	instanceof	class scala/actors/scheduler/ForkJoinScheduler
	ifeq	l1 // ldc
	aload_0
	getfield	Field sched:Lscala/actors/IScheduler;
	checkcast	class scala/actors/scheduler/ForkJoinScheduler
	invokevirtual	Method scala/actors/scheduler/ForkJoinScheduler.snapshot:()V
	return
l1	ldc	String scheduler does not implement snapshot
	astore_1
	new	class java/lang/RuntimeException
	dup
	aload_1
	invokespecial	Method java/lang/RuntimeException."<init>":(Ljava/lang/String;)V
	athrow
  Labels:
   	l1 = 21 // ldc
  LocalVariableTable: 
   Start  Length  Slot  Name   Signature
   0      33      0    this       Lscala/actors/Scheduler$;


public scala.actors.IScheduler makeNewScheduler();
  Signature: ()Lscala/actors/IScheduler;
  Code:
   Stack=5, Locals=5, Args_size=1
	ldc	String java.vm.vendor
	invokestatic	Method java/lang/System.getProperty:(Ljava/lang/String;)Ljava/lang/String;
	astore_1
	aload_1
	ldc	String IBM
	invokevirtual	Method java/lang/String.indexOf:(Ljava/lang/String;)I
	iconst_m1
	if_icmpeq	l1 // new
	getstatic	Field scala/actors/Debug$.MODULE$:Lscala/actors/Debug$;
	new	class scala/collection/mutable/StringBuilder
	dup
	invokespecial	Method scala/collection/mutable/StringBuilder."<init>":()V
	new	class scala/runtime/StringAdd
	dup
	aload_0
	invokespecial	Method scala/runtime/StringAdd."<init>":(Ljava/lang/Object;)V
	ldc	String : running on a 
	invokevirtual	Method scala/runtime/StringAdd.$plus:(Ljava/lang/String;)Ljava/lang/String;
	invokevirtual	Method scala/collection/mutable/StringBuilder.append:(Ljava/lang/Object;)Lscala/collection/mutable/StringBuilder;
	aload_1
	invokevirtual	Method scala/collection/mutable/StringBuilder.append:(Ljava/lang/Object;)Lscala/collection/mutable/StringBuilder;
	ldc	String  JVM
	invokevirtual	Method scala/collection/mutable/StringBuilder.append:(Ljava/lang/Object;)Lscala/collection/mutable/StringBuilder;
	invokevirtual	Method scala/collection/mutable/StringBuilder.toString:()Ljava/lang/String;
	invokevirtual	Method scala/actors/Debug$.info:(Ljava/lang/String;)V
	new	class scala/actors/scheduler/ResizableThreadPoolScheduler
	dup
	iconst_0
	invokespecial	Method scala/actors/scheduler/ResizableThreadPoolScheduler."<init>":(Z)V
	astore_2
	aload_2
	invokevirtual	Method scala/actors/scheduler/ResizableThreadPoolScheduler.start:()V
	aload_2
	goto	l2 // astore
l1	new	class scala/actors/scheduler/ForkJoinScheduler
	dup
	invokespecial	Method scala/actors/scheduler/ForkJoinScheduler."<init>":()V
	astore_3
	aload_3
	invokevirtual	Method scala/actors/scheduler/ForkJoinScheduler.start:()V
	aload_3
l2	astore	4
	getstatic	Field scala/actors/Debug$.MODULE$:Lscala/actors/Debug$;
	new	class scala/collection/mutable/StringBuilder
	dup
	invokespecial	Method scala/collection/mutable/StringBuilder."<init>":()V
	new	class scala/runtime/StringAdd
	dup
	aload_0
	invokespecial	Method scala/runtime/StringAdd."<init>":(Ljava/lang/Object;)V
	ldc	String : starting new 
	invokevirtual	Method scala/runtime/StringAdd.$plus:(Ljava/lang/String;)Ljava/lang/String;
	invokevirtual	Method scala/collection/mutable/StringBuilder.append:(Ljava/lang/Object;)Lscala/collection/mutable/StringBuilder;
	aload	4
	invokevirtual	Method scala/collection/mutable/StringBuilder.append:(Ljava/lang/Object;)Lscala/collection/mutable/StringBuilder;
	ldc	String  [
	invokevirtual	Method scala/collection/mutable/StringBuilder.append:(Ljava/lang/Object;)Lscala/collection/mutable/StringBuilder;
	aload	4
	invokevirtual	Method java/lang/Object.getClass:()Ljava/lang/Class;
	invokevirtual	Method scala/collection/mutable/StringBuilder.append:(Ljava/lang/Object;)Lscala/collection/mutable/StringBuilder;
	ldc	String ]
	invokevirtual	Method scala/collection/mutable/StringBuilder.append:(Ljava/lang/Object;)Lscala/collection/mutable/StringBuilder;
	invokevirtual	Method scala/collection/mutable/StringBuilder.toString:()Ljava/lang/String;
	invokevirtual	Method scala/actors/Debug$.info:(Ljava/lang/String;)V
	aload	4
	areturn
  Labels:
   	l1 = 74 // new
   	l2 = 87 // astore
  LocalVariableTable: 
   Start  Length  Slot  Name   Signature
   0      147      0    this       Lscala/actors/Scheduler$;
   6      140      1    jvmVendor       Ljava/lang/String;
   66      5      2    s       Lscala/actors/scheduler/ResizableThreadPoolScheduler;
   82      5      3    s       Lscala/actors/scheduler/ForkJoinScheduler;
   89      57      4    sched       Lscala/actors/IScheduler;


public void printActorDump();
  Signature: ()V
  Code:
   Stack=1, Locals=1, Args_size=1
	aload_0
	invokestatic	Method scala/actors/IScheduler$class.printActorDump:(Lscala/actors/IScheduler;)V
	return
  Labels:

public void onLockup(int, scala.Function0);
  Signature: (ILscala/Function0;)V
  Code:
   Stack=3, Locals=3, Args_size=3
	aload_0
	iload_1
	aload_2
	invokestatic	Method scala/actors/IScheduler$class.onLockup:(Lscala/actors/IScheduler;ILscala/Function0;)V
	return
  Labels:
  LocalVariableTable: 
   Start  Length  Slot  Name   Signature
   0      7      0    this       Lscala/actors/Scheduler$;
   0      7      1    millis       I
   0      7      2    handler       Lscala/Function0;


public void onLockup(scala.Function0);
  Signature: (Lscala/Function0;)V
  Code:
   Stack=2, Locals=2, Args_size=2
	aload_0
	aload_1
	invokestatic	Method scala/actors/IScheduler$class.onLockup:(Lscala/actors/IScheduler;Lscala/Function0;)V
	return
  Labels:
  LocalVariableTable: 
   Start  Length  Slot  Name   Signature
   0      6      0    this       Lscala/actors/Scheduler$;
   0      6      1    handler       Lscala/Function0;


public void tick(scala.actors.Actor);
  Signature: (Lscala/actors/Actor;)V
  Code:
   Stack=2, Locals=2, Args_size=2
	aload_0
	aload_1
	invokestatic	Method scala/actors/IScheduler$class.tick:(Lscala/actors/IScheduler;Lscala/actors/Actor;)V
	return
  Labels:
  LocalVariableTable: 
   Start  Length  Slot  Name   Signature
   0      6      0    this       Lscala/actors/Scheduler$;
   0      6      1    a       Lscala/actors/Actor;


public void managedBlock(scala.concurrent.ManagedBlocker);
  Signature: (Lscala/concurrent/ManagedBlocker;)V
  Code:
   Stack=2, Locals=2, Args_size=2
	aload_0
	aload_1
	invokestatic	Method scala/actors/scheduler/DelegatingScheduler$class.managedBlock:(Lscala/actors/scheduler/DelegatingScheduler;Lscala/concurrent/ManagedBlocker;)V
	return
  Labels:
  LocalVariableTable: 
   Start  Length  Slot  Name   Signature
   0      6      0    this       Lscala/actors/Scheduler$;
   0      6      1    blocker       Lscala/concurrent/ManagedBlocker;


public void onTerminate(scala.actors.Reactor, scala.Function0);
  Signature: (Lscala/actors/Reactor;Lscala/Function0;)V
  Code:
   Stack=3, Locals=3, Args_size=3
	aload_0
	aload_1
	aload_2
	invokestatic	Method scala/actors/scheduler/DelegatingScheduler$class.onTerminate:(Lscala/actors/scheduler/DelegatingScheduler;Lscala/actors/Reactor;Lscala/Function0;)V
	return
  Labels:
  LocalVariableTable: 
   Start  Length  Slot  Name   Signature
   0      7      0    this       Lscala/actors/Scheduler$;
   0      7      1    actor       Lscala/actors/Reactor;
   0      7      2    f       Lscala/Function0;


public void terminated(scala.actors.Reactor);
  Signature: (Lscala/actors/Reactor;)V
  Code:
   Stack=2, Locals=2, Args_size=2
	aload_0
	aload_1
	invokestatic	Method scala/actors/scheduler/DelegatingScheduler$class.terminated:(Lscala/actors/scheduler/DelegatingScheduler;Lscala/actors/Reactor;)V
	return
  Labels:
  LocalVariableTable: 
   Start  Length  Slot  Name   Signature
   0      6      0    this       Lscala/actors/Scheduler$;
   0      6      1    actor       Lscala/actors/Reactor;


public void newActor(scala.actors.Reactor);
  Signature: (Lscala/actors/Reactor;)V
  Code:
   Stack=2, Locals=2, Args_size=2
	aload_0
	aload_1
	invokestatic	Method scala/actors/scheduler/DelegatingScheduler$class.newActor:(Lscala/actors/scheduler/DelegatingScheduler;Lscala/actors/Reactor;)V
	return
  Labels:
  LocalVariableTable: 
   Start  Length  Slot  Name   Signature
   0      6      0    this       Lscala/actors/Scheduler$;
   0      6      1    actor       Lscala/actors/Reactor;


public void shutdown();
  Signature: ()V
  Code:
   Stack=1, Locals=1, Args_size=1
	aload_0
	invokestatic	Method scala/actors/scheduler/DelegatingScheduler$class.shutdown:(Lscala/actors/scheduler/DelegatingScheduler;)V
	return
  Labels:

public void executeFromActor(java.lang.Runnable);
  Signature: (Ljava/lang/Runnable;)V
  Code:
   Stack=2, Locals=2, Args_size=2
	aload_0
	aload_1
	invokestatic	Method scala/actors/scheduler/DelegatingScheduler$class.executeFromActor:(Lscala/actors/scheduler/DelegatingScheduler;Ljava/lang/Runnable;)V
	return
  Labels:
  LocalVariableTable: 
   Start  Length  Slot  Name   Signature
   0      6      0    this       Lscala/actors/Scheduler$;
   0      6      1    task       Ljava/lang/Runnable;


public void execute(java.lang.Runnable);
  Signature: (Ljava/lang/Runnable;)V
  Code:
   Stack=2, Locals=2, Args_size=2
	aload_0
	aload_1
	invokestatic	Method scala/actors/scheduler/DelegatingScheduler$class.execute:(Lscala/actors/scheduler/DelegatingScheduler;Ljava/lang/Runnable;)V
	return
  Labels:
  LocalVariableTable: 
   Start  Length  Slot  Name   Signature
   0      6      0    this       Lscala/actors/Scheduler$;
   0      6      1    task       Ljava/lang/Runnable;


public void execute(scala.Function0);
  Signature: (Lscala/Function0;)V
  Code:
   Stack=2, Locals=2, Args_size=2
	aload_0
	aload_1
	invokestatic	Method scala/actors/scheduler/DelegatingScheduler$class.execute:(Lscala/actors/scheduler/DelegatingScheduler;Lscala/Function0;)V
	return
  Labels:
  LocalVariableTable: 
   Start  Length  Slot  Name   Signature
   0      6      0    this       Lscala/actors/Scheduler$;
   0      6      1    fun       Lscala/Function0;


public boolean isActive();
  Signature: ()Z
  Code:
   Stack=1, Locals=1, Args_size=1
	aload_0
	invokestatic	Method scala/actors/scheduler/DelegatingScheduler$class.isActive:(Lscala/actors/scheduler/DelegatingScheduler;)Z
	ireturn
  Labels:

public final void impl_$eq(scala.actors.IScheduler);
  Signature: (Lscala/actors/IScheduler;)V
  Code:
   Stack=2, Locals=2, Args_size=2
	aload_0
	aload_1
	invokestatic	Method scala/actors/scheduler/DelegatingScheduler$class.impl_$eq:(Lscala/actors/scheduler/DelegatingScheduler;Lscala/actors/IScheduler;)V
	return
  Labels:
  LocalVariableTable: 
   Start  Length  Slot  Name   Signature
   0      6      0    this       Lscala/actors/Scheduler$;
   0      6      1    scheduler       Lscala/actors/IScheduler;


public final scala.actors.IScheduler impl();
  Signature: ()Lscala/actors/IScheduler;
  Code:
   Stack=1, Locals=1, Args_size=1
	aload_0
	invokestatic	Method scala/actors/scheduler/DelegatingScheduler$class.impl:(Lscala/actors/scheduler/DelegatingScheduler;)Lscala/actors/IScheduler;
	areturn
  Labels:

public void sched_$eq(scala.actors.IScheduler);
  Signature: (Lscala/actors/IScheduler;)V
  Code:
   Stack=2, Locals=2, Args_size=2
	aload_0
	aload_1
	putfield	Field sched:Lscala/actors/IScheduler;
	return
  Labels:

public scala.actors.IScheduler sched();
  Signature: ()Lscala/actors/IScheduler;
  Code:
   Stack=1, Locals=1, Args_size=1
	aload_0
	getfield	Field sched:Lscala/actors/IScheduler;
	areturn
  Labels:

}

