Compiled from "SchedulerAdapter.scala"
public abstract class scala.actors.SchedulerAdapter$class extends java.lang.Object
  SourceFile: "SchedulerAdapter.scala"
  Scala: length = 0x
   
  InnerClass: 
   public final #71= #56 of #70; //$anonfun$execute$1=class scala/actors/SchedulerAdapter$$anonfun$execute$1 of class scala/actors/SchedulerAdapter
  minor version: 0
  major version: 49
  Constant pool:
const #1 = Asciz	SourceFile;
const #2 = Asciz	SchedulerAdapter.scala;
const #3 = Asciz	$init$;
const #4 = Asciz	(Lscala/actors/SchedulerAdapter;)V;
const #5 = Asciz	Code;
const #6 = Asciz	LineNumberTable;
const #7 = Asciz	$this;
const #8 = Asciz	Lscala/actors/SchedulerAdapter;;
const #9 = Asciz	LocalVariableTable;
const #10 = Asciz	managedBlock;
const #11 = Asciz	(Lscala/actors/SchedulerAdapter;Lscala/concurrent/ManagedBlocker;)V;
const #12 = Asciz	scala/concurrent/ManagedBlocker;
const #13 = class	#12;	//  scala/concurrent/ManagedBlocker
const #14 = Asciz	block;
const #15 = Asciz	()Z;
const #16 = NameAndType	#14:#15;//  block:()Z
const #17 = InterfaceMethod	#13.#16;	//  scala/concurrent/ManagedBlocker.block:()Z
const #18 = Asciz	blocker;
const #19 = Asciz	Lscala/concurrent/ManagedBlocker;;
const #20 = Asciz	onTerminate;
const #21 = Asciz	(Lscala/actors/SchedulerAdapter;Lscala/actors/Reactor;Lscala/Function0;)V;
const #22 = Asciz	scala/actors/Scheduler$;
const #23 = class	#22;	//  scala/actors/Scheduler$
const #24 = Asciz	MODULE$;
const #25 = Asciz	Lscala/actors/Scheduler$;;
const #26 = NameAndType	#24:#25;//  MODULE$:Lscala/actors/Scheduler$;
const #27 = Field	#23.#26;	//  scala/actors/Scheduler$.MODULE$:Lscala/actors/Scheduler$;
const #28 = Asciz	scala/actors/scheduler/DelegatingScheduler;
const #29 = class	#28;	//  scala/actors/scheduler/DelegatingScheduler
const #30 = Asciz	(Lscala/actors/Reactor;Lscala/Function0;)V;
const #31 = NameAndType	#20:#30;//  onTerminate:(Lscala/actors/Reactor;Lscala/Function0;)V
const #32 = InterfaceMethod	#29.#31;	//  scala/actors/scheduler/DelegatingScheduler.onTerminate:(Lscala/actors/Reactor;Lscala/Function0;)V
const #33 = Asciz	a;
const #34 = Asciz	Lscala/actors/Reactor;;
const #35 = Asciz	f;
const #36 = Asciz	Lscala/Function0;;
const #37 = Asciz	terminated;
const #38 = Asciz	(Lscala/actors/SchedulerAdapter;Lscala/actors/Reactor;)V;
const #39 = Asciz	(Lscala/actors/Reactor;)V;
const #40 = NameAndType	#37:#39;//  terminated:(Lscala/actors/Reactor;)V
const #41 = InterfaceMethod	#29.#40;	//  scala/actors/scheduler/DelegatingScheduler.terminated:(Lscala/actors/Reactor;)V
const #42 = Asciz	newActor;
const #43 = NameAndType	#42:#39;//  newActor:(Lscala/actors/Reactor;)V
const #44 = InterfaceMethod	#29.#43;	//  scala/actors/scheduler/DelegatingScheduler.newActor:(Lscala/actors/Reactor;)V
const #45 = Asciz	isActive;
const #46 = Asciz	(Lscala/actors/SchedulerAdapter;)Z;
const #47 = NameAndType	#45:#15;//  isActive:()Z
const #48 = InterfaceMethod	#29.#47;	//  scala/actors/scheduler/DelegatingScheduler.isActive:()Z
const #49 = Asciz	shutdown;
const #50 = Asciz	()V;
const #51 = NameAndType	#49:#50;//  shutdown:()V
const #52 = InterfaceMethod	#29.#51;	//  scala/actors/scheduler/DelegatingScheduler.shutdown:()V
const #53 = Asciz	execute;
const #54 = Asciz	(Lscala/actors/SchedulerAdapter;Ljava/lang/Runnable;)V;
const #55 = Asciz	scala/actors/SchedulerAdapter$$anonfun$execute$1;
const #56 = class	#55;	//  scala/actors/SchedulerAdapter$$anonfun$execute$1
const #57 = Asciz	<init>;
const #58 = NameAndType	#57:#54;//  "<init>":(Lscala/actors/SchedulerAdapter;Ljava/lang/Runnable;)V
const #59 = Method	#56.#58;	//  scala/actors/SchedulerAdapter$$anonfun$execute$1."<init>":(Lscala/actors/SchedulerAdapter;Ljava/lang/Runnable;)V
const #60 = Asciz	scala/actors/IScheduler;
const #61 = class	#60;	//  scala/actors/IScheduler
const #62 = Asciz	(Lscala/Function0;)V;
const #63 = NameAndType	#53:#62;//  execute:(Lscala/Function0;)V
const #64 = InterfaceMethod	#61.#63;	//  scala/actors/IScheduler.execute:(Lscala/Function0;)V
const #65 = Asciz	task$1;
const #66 = Asciz	Ljava/lang/Runnable;;
const #67 = Asciz	Scala;
const #68 = Asciz	InnerClasses;
const #69 = Asciz	scala/actors/SchedulerAdapter;
const #70 = class	#69;	//  scala/actors/SchedulerAdapter
const #71 = Asciz	$anonfun$execute$1;
const #72 = Asciz	scala/actors/SchedulerAdapter$class;
const #73 = class	#72;	//  scala/actors/SchedulerAdapter$class
const #74 = Asciz	java/lang/Object;
const #75 = class	#74;	//  java/lang/Object

{
public static void $init$(scala.actors.SchedulerAdapter);
  Code:
   Stack=0, Locals=1, Args_size=1
   0:	return
  LineNumberTable: 
   line 22: 0

  LocalVariableTable: 
   Start  Length  Slot  Name   Signature
   0      1      0    $this       Lscala/actors/SchedulerAdapter;


public static void managedBlock(scala.actors.SchedulerAdapter, scala.concurrent.ManagedBlocker);
  Code:
   Stack=1, Locals=2, Args_size=2
   0:	aload_1
   1:	invokeinterface	#17,  1; //InterfaceMethod scala/concurrent/ManagedBlocker.block:()Z
   6:	pop
   7:	return
  LineNumberTable: 
   line 66: 0

  LocalVariableTable: 
   Start  Length  Slot  Name   Signature
   0      8      0    $this       Lscala/actors/SchedulerAdapter;
   0      8      1    blocker       Lscala/concurrent/ManagedBlocker;


public static void onTerminate(scala.actors.SchedulerAdapter, scala.actors.Reactor, scala.Function0);
  Code:
   Stack=3, Locals=3, Args_size=3
   0:	getstatic	#27; //Field scala/actors/Scheduler$.MODULE$:Lscala/actors/Scheduler$;
   3:	aload_1
   4:	aload_2
   5:	invokeinterface	#32,  3; //InterfaceMethod scala/actors/scheduler/DelegatingScheduler.onTerminate:(Lscala/actors/Reactor;Lscala/Function0;)V
   10:	return
  LineNumberTable: 
   line 63: 0

  LocalVariableTable: 
   Start  Length  Slot  Name   Signature
   0      11      0    $this       Lscala/actors/SchedulerAdapter;
   0      11      1    a       Lscala/actors/Reactor;
   0      11      2    f       Lscala/Function0;


public static void terminated(scala.actors.SchedulerAdapter, scala.actors.Reactor);
  Code:
   Stack=2, Locals=2, Args_size=2
   0:	getstatic	#27; //Field scala/actors/Scheduler$.MODULE$:Lscala/actors/Scheduler$;
   3:	aload_1
   4:	invokeinterface	#41,  2; //InterfaceMethod scala/actors/scheduler/DelegatingScheduler.terminated:(Lscala/actors/Reactor;)V
   9:	return
  LineNumberTable: 
   line 54: 0

  LocalVariableTable: 
   Start  Length  Slot  Name   Signature
   0      10      0    $this       Lscala/actors/SchedulerAdapter;
   0      10      1    a       Lscala/actors/Reactor;


public static void newActor(scala.actors.SchedulerAdapter, scala.actors.Reactor);
  Code:
   Stack=2, Locals=2, Args_size=2
   0:	getstatic	#27; //Field scala/actors/Scheduler$.MODULE$:Lscala/actors/Scheduler$;
   3:	aload_1
   4:	invokeinterface	#44,  2; //InterfaceMethod scala/actors/scheduler/DelegatingScheduler.newActor:(Lscala/actors/Reactor;)V
   9:	return
  LineNumberTable: 
   line 46: 0

  LocalVariableTable: 
   Start  Length  Slot  Name   Signature
   0      10      0    $this       Lscala/actors/SchedulerAdapter;
   0      10      1    a       Lscala/actors/Reactor;


public static boolean isActive(scala.actors.SchedulerAdapter);
  Code:
   Stack=1, Locals=1, Args_size=1
   0:	getstatic	#27; //Field scala/actors/Scheduler$.MODULE$:Lscala/actors/Scheduler$;
   3:	invokeinterface	#48,  1; //InterfaceMethod scala/actors/scheduler/DelegatingScheduler.isActive:()Z
   8:	ireturn
  LineNumberTable: 
   line 39: 0

  LocalVariableTable: 
   Start  Length  Slot  Name   Signature
   0      9      0    $this       Lscala/actors/SchedulerAdapter;


public static void shutdown(scala.actors.SchedulerAdapter);
  Code:
   Stack=1, Locals=1, Args_size=1
   0:	getstatic	#27; //Field scala/actors/Scheduler$.MODULE$:Lscala/actors/Scheduler$;
   3:	invokeinterface	#52,  1; //InterfaceMethod scala/actors/scheduler/DelegatingScheduler.shutdown:()V
   8:	return
  LineNumberTable: 
   line 34: 0

  LocalVariableTable: 
   Start  Length  Slot  Name   Signature
   0      9      0    $this       Lscala/actors/SchedulerAdapter;


public static void execute(scala.actors.SchedulerAdapter, java.lang.Runnable);
  Code:
   Stack=5, Locals=2, Args_size=2
   0:	aload_0
   1:	new	#56; //class scala/actors/SchedulerAdapter$$anonfun$execute$1
   4:	dup
   5:	aload_0
   6:	aload_1
   7:	invokespecial	#59; //Method scala/actors/SchedulerAdapter$$anonfun$execute$1."<init>":(Lscala/actors/SchedulerAdapter;Ljava/lang/Runnable;)V
   10:	invokeinterface	#64,  2; //InterfaceMethod scala/actors/IScheduler.execute:(Lscala/Function0;)V
   15:	return
  LineNumberTable: 
   line 29: 0

  LocalVariableTable: 
   Start  Length  Slot  Name   Signature
   0      16      0    $this       Lscala/actors/SchedulerAdapter;
   0      16      1    task$1       Ljava/lang/Runnable;


}

