Compiled from "SchedulerAdapter.scala"
public final class scala.actors.SchedulerAdapter$$anonfun$execute$1 extends java.lang.Object implements scala.Function0,scala.ScalaObject,java.io.Serializable
  SourceFile: "SchedulerAdapter.scala"
  Scala: length = 0x
   
  InnerClass: 
   public final $anonfun$execute$1=class scala/actors/SchedulerAdapter$$anonfun$execute$1 of class scala/actors/SchedulerAdapter
  minor version: 0
  major version: 49
  Constant pool:
Asciz	SourceFile;
Asciz	SchedulerAdapter.scala;
Asciz	<clinit>;
Asciz	()V;
Asciz	Code;
Asciz	serialVersionUID;
Asciz	J;
Asciz	scala/actors/SchedulerAdapter$$anonfun$execute$1;
class	scala/actors/SchedulerAdapter$$anonfun$execute$1
NameAndType	serialVersionUID:J
Field	scala/actors/SchedulerAdapter$$anonfun$execute$1.serialVersionUID:J
Asciz	task$1;
Asciz	Ljava/lang/Runnable;;
Asciz	<init>;
Asciz	(Lscala/actors/SchedulerAdapter;Ljava/lang/Runnable;)V;
Asciz	LineNumberTable;
NameAndType	task$1:Ljava/lang/Runnable;
Field	scala/actors/SchedulerAdapter$$anonfun$execute$1.task$1:Ljava/lang/Runnable;
Asciz	java/lang/Object;
class	java/lang/Object
NameAndType	"<init>":()V
Method	java/lang/Object."<init>":()V
Asciz	scala/Function0$class;
class	scala/Function0$class
Asciz	$init$;
Asciz	(Lscala/Function0;)V;
NameAndType	$init$:(Lscala/Function0;)V
Method	scala/Function0$class.$init$:(Lscala/Function0;)V
Asciz	this;
Asciz	Lscala/actors/SchedulerAdapter$$anonfun$execute$1;;
Asciz	$outer;
Asciz	Lscala/actors/SchedulerAdapter;;
Asciz	LocalVariableTable;
Asciz	apply;
Asciz	()Ljava/lang/Object;;
NameAndType	apply:()V
Method	scala/actors/SchedulerAdapter$$anonfun$execute$1.apply:()V
Asciz	scala/runtime/BoxedUnit;
class	scala/runtime/BoxedUnit
Asciz	UNIT;
Asciz	Lscala/runtime/BoxedUnit;;
NameAndType	UNIT:Lscala/runtime/BoxedUnit;
Field	scala/runtime/BoxedUnit.UNIT:Lscala/runtime/BoxedUnit;
Asciz	java/lang/Runnable;
class	java/lang/Runnable
Asciz	run;
NameAndType	run:()V
InterfaceMethod	java/lang/Runnable.run:()V
Asciz	toString;
Asciz	()Ljava/lang/String;;
Asciz	(Lscala/Function0;)Ljava/lang/String;;
NameAndType	toString:(Lscala/Function0;)Ljava/lang/String;
Method	scala/Function0$class.toString:(Lscala/Function0;)Ljava/lang/String;
Asciz	Scala;
Asciz	InnerClasses;
Asciz	scala/actors/SchedulerAdapter;
class	scala/actors/SchedulerAdapter
Asciz	$anonfun$execute$1;
Asciz	scala/Function0;
class	scala/Function0
Asciz	scala/ScalaObject;
class	scala/ScalaObject
Asciz	java/io/Serializable;
class	java/io/Serializable

{
public static final long serialVersionUID;
  Signature: J

private final java.lang.Runnable task$1;
  Signature: Ljava/lang/Runnable;

public static {};
  Signature: ()V
  Code:
   Stack=2, Locals=0, Args_size=0
	lconst_0
	putstatic	Field serialVersionUID:J
	return
  Labels:

public scala.actors.SchedulerAdapter$$anonfun$execute$1(scala.actors.SchedulerAdapter, java.lang.Runnable);
  Signature: (Lscala/actors/SchedulerAdapter;Ljava/lang/Runnable;)V
  Code:
   Stack=2, Locals=3, Args_size=3
	aload_0
	aload_2
	putfield	Field task$1:Ljava/lang/Runnable;
	aload_0
	invokespecial	Method java/lang/Object."<init>":()V
	aload_0
	invokestatic	Method scala/Function0$class.$init$:(Lscala/Function0;)V
	return
  Labels:
  LocalVariableTable: 
   Start  Length  Slot  Name   Signature
   0      14      0    this       Lscala/actors/SchedulerAdapter$$anonfun$execute$1;
   0      14      1    $outer       Lscala/actors/SchedulerAdapter;


public final java.lang.Object apply();
  Signature: ()Ljava/lang/Object;
  Code:
   Stack=1, Locals=1, Args_size=1
	aload_0
	invokevirtual	Method apply:()V
	getstatic	Field scala/runtime/BoxedUnit.UNIT:Lscala/runtime/BoxedUnit;
	areturn
  Labels:

public final void apply();
  Signature: ()V
  Code:
   Stack=1, Locals=1, Args_size=1
	aload_0
	getfield	Field task$1:Ljava/lang/Runnable;
	invokeinterface	InterfaceMethod java/lang/Runnable.run:()V
	return
  Labels:

public java.lang.String toString();
  Signature: ()Ljava/lang/String;
  Code:
   Stack=1, Locals=1, Args_size=1
	aload_0
	invokestatic	Method scala/Function0$class.toString:(Lscala/Function0;)Ljava/lang/String;
	areturn
  Labels:

}

