Compiled from "Scheduler.scala"
public final class scala.actors.Scheduler extends java.lang.Object
  SourceFile: "Scheduler.scala"
  ScalaSig: length = 0x187
   05 00 38 07 05 01 02 FFFFFF88 02 07 01 09 53 63 68 65
   64 75 6C 65 72 0A 02 03 04 01 06 61 63 74 6F 72
   73 0A 01 05 01 05 73 63 61 6C 61 03 00 10 02 08
   09 0D 01 02 06 08 0A 02 FFFFFF84 FFFFFF80 FFFFFF80 FFFFFF88 02 0B 02 09
   53 63 68 65 64 75 6C 65 72 13 04 09 0C 14 1A 10
   02 0D 12 0D 01 0E 0A 02 0F 10 01 04 6C 61 6E 67
   0A 01 11 01 04 6A 61 76 61 09 02 13 0E 02 06 4F
   62 6A 65 63 74 10 02 15 18 0D 01 16 0A 02 17 02
   01 09 73 63 68 65 64 75 6C 65 72 09 02 19 16 02
   13 44 65 6C 65 67 61 74 69 6E 67 53 63 68 65 64
   75 6C 65 72 10 02 1B 1C 0D 01 04 09 02 1D 04 02
   0B 53 63 61 6C 61 4F 62 6A 65 63 74 08 05 1F 09
   FFFFFF84 00 20 01 06 3C 69 6E 69 74 3E 14 01 07 08 05
   22 09 FFFFFF84 00 23 01 10 6D 61 6B 65 4E 65 77 53 63
   68 65 64 75 6C 65 72 14 01 24 10 02 08 25 09 02
   26 02 02 0A 49 53 63 68 65 64 75 6C 65 72 08 05
   28 09 FFFFFF84 00 29 01 08 73 6E 61 70 73 68 6F 74 14
   01 2A 10 02 1B 2B 09 02 2C 04 02 04 55 6E 69 74
   28 03 27 2E 31 10 02 1B 2F 09 02 30 04 02 0A 64
   65 70 72 65 63 61 74 65 64 21 01 32 01 18 73 6E
   61 70 73 68 6F 74 20 77 69 6C 6C 20 62 65 20 72
   65 6D 6F 76 65 64 08 05 34 09 FFFFFF84 00 29 01 07 72
   65 73 74 61 72 74 28 03 33 2E 36 21 01 37 01 17
   72 65 73 74 61 72 74 20 77 69 6C 6C 20 62 65 20
   72 65 6D 6F 76 65 64 
  minor version: 0
  major version: 49
  Constant pool:
const #1 = Asciz	SourceFile;
const #2 = Asciz	Scheduler.scala;
const #3 = Asciz	printActorDump;
const #4 = Asciz	()V;
const #5 = Asciz	Code;
const #6 = Asciz	scala/actors/Scheduler$;
const #7 = class	#6;	//  scala/actors/Scheduler$
const #8 = Asciz	MODULE$;
const #9 = Asciz	Lscala/actors/Scheduler$;;
const #10 = NameAndType	#8:#9;//  MODULE$:Lscala/actors/Scheduler$;
const #11 = Field	#7.#10;	//  scala/actors/Scheduler$.MODULE$:Lscala/actors/Scheduler$;
const #12 = NameAndType	#3:#4;//  printActorDump:()V
const #13 = Method	#7.#12;	//  scala/actors/Scheduler$.printActorDump:()V
const #14 = Asciz	Deprecated;
const #15 = Asciz	onLockup;
const #16 = Asciz	(ILscala/Function0;)V;
const #17 = NameAndType	#15:#16;//  onLockup:(ILscala/Function0;)V
const #18 = Method	#7.#17;	//  scala/actors/Scheduler$.onLockup:(ILscala/Function0;)V
const #19 = Asciz	(Lscala/Function0;)V;
const #20 = NameAndType	#15:#19;//  onLockup:(Lscala/Function0;)V
const #21 = Method	#7.#20;	//  scala/actors/Scheduler$.onLockup:(Lscala/Function0;)V
const #22 = Asciz	tick;
const #23 = Asciz	(Lscala/actors/Actor;)V;
const #24 = NameAndType	#22:#23;//  tick:(Lscala/actors/Actor;)V
const #25 = Method	#7.#24;	//  scala/actors/Scheduler$.tick:(Lscala/actors/Actor;)V
const #26 = Asciz	managedBlock;
const #27 = Asciz	(Lscala/concurrent/ManagedBlocker;)V;
const #28 = NameAndType	#26:#27;//  managedBlock:(Lscala/concurrent/ManagedBlocker;)V
const #29 = Method	#7.#28;	//  scala/actors/Scheduler$.managedBlock:(Lscala/concurrent/ManagedBlocker;)V
const #30 = Asciz	onTerminate;
const #31 = Asciz	(Lscala/actors/Reactor;Lscala/Function0;)V;
const #32 = NameAndType	#30:#31;//  onTerminate:(Lscala/actors/Reactor;Lscala/Function0;)V
const #33 = Method	#7.#32;	//  scala/actors/Scheduler$.onTerminate:(Lscala/actors/Reactor;Lscala/Function0;)V
const #34 = Asciz	terminated;
const #35 = Asciz	(Lscala/actors/Reactor;)V;
const #36 = NameAndType	#34:#35;//  terminated:(Lscala/actors/Reactor;)V
const #37 = Method	#7.#36;	//  scala/actors/Scheduler$.terminated:(Lscala/actors/Reactor;)V
const #38 = Asciz	newActor;
const #39 = NameAndType	#38:#35;//  newActor:(Lscala/actors/Reactor;)V
const #40 = Method	#7.#39;	//  scala/actors/Scheduler$.newActor:(Lscala/actors/Reactor;)V
const #41 = Asciz	shutdown;
const #42 = NameAndType	#41:#4;//  shutdown:()V
const #43 = Method	#7.#42;	//  scala/actors/Scheduler$.shutdown:()V
const #44 = Asciz	executeFromActor;
const #45 = Asciz	(Ljava/lang/Runnable;)V;
const #46 = NameAndType	#44:#45;//  executeFromActor:(Ljava/lang/Runnable;)V
const #47 = Method	#7.#46;	//  scala/actors/Scheduler$.executeFromActor:(Ljava/lang/Runnable;)V
const #48 = Asciz	execute;
const #49 = NameAndType	#48:#45;//  execute:(Ljava/lang/Runnable;)V
const #50 = Method	#7.#49;	//  scala/actors/Scheduler$.execute:(Ljava/lang/Runnable;)V
const #51 = NameAndType	#48:#19;//  execute:(Lscala/Function0;)V
const #52 = Method	#7.#51;	//  scala/actors/Scheduler$.execute:(Lscala/Function0;)V
const #53 = Asciz	isActive;
const #54 = Asciz	()Z;
const #55 = NameAndType	#53:#54;//  isActive:()Z
const #56 = Method	#7.#55;	//  scala/actors/Scheduler$.isActive:()Z
const #57 = Asciz	impl_$eq;
const #58 = Asciz	(Lscala/actors/IScheduler;)V;
const #59 = NameAndType	#57:#58;//  impl_$eq:(Lscala/actors/IScheduler;)V
const #60 = Method	#7.#59;	//  scala/actors/Scheduler$.impl_$eq:(Lscala/actors/IScheduler;)V
const #61 = Asciz	impl;
const #62 = Asciz	()Lscala/actors/IScheduler;;
const #63 = NameAndType	#61:#62;//  impl:()Lscala/actors/IScheduler;
const #64 = Method	#7.#63;	//  scala/actors/Scheduler$.impl:()Lscala/actors/IScheduler;
const #65 = Asciz	restart;
const #66 = NameAndType	#65:#4;//  restart:()V
const #67 = Method	#7.#66;	//  scala/actors/Scheduler$.restart:()V
const #68 = Asciz	snapshot;
const #69 = NameAndType	#68:#4;//  snapshot:()V
const #70 = Method	#7.#69;	//  scala/actors/Scheduler$.snapshot:()V
const #71 = Asciz	makeNewScheduler;
const #72 = NameAndType	#71:#62;//  makeNewScheduler:()Lscala/actors/IScheduler;
const #73 = Method	#7.#72;	//  scala/actors/Scheduler$.makeNewScheduler:()Lscala/actors/IScheduler;
const #74 = Asciz	ScalaSig;
const #75 = Asciz	scala/actors/Scheduler;
const #76 = class	#75;	//  scala/actors/Scheduler
const #77 = Asciz	java/lang/Object;
const #78 = class	#77;	//  java/lang/Object

{
public static final void printActorDump();
  Code:
   Stack=1, Locals=0, Args_size=0
   0:	getstatic	#11; //Field scala/actors/Scheduler$.MODULE$:Lscala/actors/Scheduler$;
   3:	invokevirtual	#13; //Method scala/actors/Scheduler$.printActorDump:()V
   6:	return
  Deprecated: true

public static final void onLockup(int, scala.Function0);
  Code:
   Stack=3, Locals=2, Args_size=2
   0:	getstatic	#11; //Field scala/actors/Scheduler$.MODULE$:Lscala/actors/Scheduler$;
   3:	iload_0
   4:	aload_1
   5:	invokevirtual	#18; //Method scala/actors/Scheduler$.onLockup:(ILscala/Function0;)V
   8:	return
  Deprecated: true

public static final void onLockup(scala.Function0);
  Code:
   Stack=2, Locals=1, Args_size=1
   0:	getstatic	#11; //Field scala/actors/Scheduler$.MODULE$:Lscala/actors/Scheduler$;
   3:	aload_0
   4:	invokevirtual	#21; //Method scala/actors/Scheduler$.onLockup:(Lscala/Function0;)V
   7:	return
  Deprecated: true

public static final void tick(scala.actors.Actor);
  Code:
   Stack=2, Locals=1, Args_size=1
   0:	getstatic	#11; //Field scala/actors/Scheduler$.MODULE$:Lscala/actors/Scheduler$;
   3:	aload_0
   4:	invokevirtual	#25; //Method scala/actors/Scheduler$.tick:(Lscala/actors/Actor;)V
   7:	return
  Deprecated: true

public static final void managedBlock(scala.concurrent.ManagedBlocker);
  Code:
   Stack=2, Locals=1, Args_size=1
   0:	getstatic	#11; //Field scala/actors/Scheduler$.MODULE$:Lscala/actors/Scheduler$;
   3:	aload_0
   4:	invokevirtual	#29; //Method scala/actors/Scheduler$.managedBlock:(Lscala/concurrent/ManagedBlocker;)V
   7:	return

public static final void onTerminate(scala.actors.Reactor, scala.Function0);
  Code:
   Stack=3, Locals=2, Args_size=2
   0:	getstatic	#11; //Field scala/actors/Scheduler$.MODULE$:Lscala/actors/Scheduler$;
   3:	aload_0
   4:	aload_1
   5:	invokevirtual	#33; //Method scala/actors/Scheduler$.onTerminate:(Lscala/actors/Reactor;Lscala/Function0;)V
   8:	return

public static final void terminated(scala.actors.Reactor);
  Code:
   Stack=2, Locals=1, Args_size=1
   0:	getstatic	#11; //Field scala/actors/Scheduler$.MODULE$:Lscala/actors/Scheduler$;
   3:	aload_0
   4:	invokevirtual	#37; //Method scala/actors/Scheduler$.terminated:(Lscala/actors/Reactor;)V
   7:	return

public static final void newActor(scala.actors.Reactor);
  Code:
   Stack=2, Locals=1, Args_size=1
   0:	getstatic	#11; //Field scala/actors/Scheduler$.MODULE$:Lscala/actors/Scheduler$;
   3:	aload_0
   4:	invokevirtual	#40; //Method scala/actors/Scheduler$.newActor:(Lscala/actors/Reactor;)V
   7:	return

public static final void shutdown();
  Code:
   Stack=1, Locals=0, Args_size=0
   0:	getstatic	#11; //Field scala/actors/Scheduler$.MODULE$:Lscala/actors/Scheduler$;
   3:	invokevirtual	#43; //Method scala/actors/Scheduler$.shutdown:()V
   6:	return

public static final void executeFromActor(java.lang.Runnable);
  Code:
   Stack=2, Locals=1, Args_size=1
   0:	getstatic	#11; //Field scala/actors/Scheduler$.MODULE$:Lscala/actors/Scheduler$;
   3:	aload_0
   4:	invokevirtual	#47; //Method scala/actors/Scheduler$.executeFromActor:(Ljava/lang/Runnable;)V
   7:	return

public static final void execute(java.lang.Runnable);
  Code:
   Stack=2, Locals=1, Args_size=1
   0:	getstatic	#11; //Field scala/actors/Scheduler$.MODULE$:Lscala/actors/Scheduler$;
   3:	aload_0
   4:	invokevirtual	#50; //Method scala/actors/Scheduler$.execute:(Ljava/lang/Runnable;)V
   7:	return

public static final void execute(scala.Function0);
  Code:
   Stack=2, Locals=1, Args_size=1
   0:	getstatic	#11; //Field scala/actors/Scheduler$.MODULE$:Lscala/actors/Scheduler$;
   3:	aload_0
   4:	invokevirtual	#52; //Method scala/actors/Scheduler$.execute:(Lscala/Function0;)V
   7:	return

public static final boolean isActive();
  Code:
   Stack=1, Locals=0, Args_size=0
   0:	getstatic	#11; //Field scala/actors/Scheduler$.MODULE$:Lscala/actors/Scheduler$;
   3:	invokevirtual	#56; //Method scala/actors/Scheduler$.isActive:()Z
   6:	ireturn

public static final void impl_$eq(scala.actors.IScheduler);
  Code:
   Stack=2, Locals=1, Args_size=1
   0:	getstatic	#11; //Field scala/actors/Scheduler$.MODULE$:Lscala/actors/Scheduler$;
   3:	aload_0
   4:	invokevirtual	#60; //Method scala/actors/Scheduler$.impl_$eq:(Lscala/actors/IScheduler;)V
   7:	return

public static final scala.actors.IScheduler impl();
  Code:
   Stack=1, Locals=0, Args_size=0
   0:	getstatic	#11; //Field scala/actors/Scheduler$.MODULE$:Lscala/actors/Scheduler$;
   3:	invokevirtual	#64; //Method scala/actors/Scheduler$.impl:()Lscala/actors/IScheduler;
   6:	areturn

public static final void restart();
  Code:
   Stack=1, Locals=0, Args_size=0
   0:	getstatic	#11; //Field scala/actors/Scheduler$.MODULE$:Lscala/actors/Scheduler$;
   3:	invokevirtual	#67; //Method scala/actors/Scheduler$.restart:()V
   6:	return
  Deprecated: true

public static final void snapshot();
  Code:
   Stack=1, Locals=0, Args_size=0
   0:	getstatic	#11; //Field scala/actors/Scheduler$.MODULE$:Lscala/actors/Scheduler$;
   3:	invokevirtual	#70; //Method scala/actors/Scheduler$.snapshot:()V
   6:	return
  Deprecated: true

public static final scala.actors.IScheduler makeNewScheduler();
  Code:
   Stack=1, Locals=0, Args_size=0
   0:	getstatic	#11; //Field scala/actors/Scheduler$.MODULE$:Lscala/actors/Scheduler$;
   3:	invokevirtual	#73; //Method scala/actors/Scheduler$.makeNewScheduler:()Lscala/actors/IScheduler;
   6:	areturn

}

