Compiled from "SchedulerAdapter.scala"
public abstract class scala.actors.SchedulerAdapter$class extends java.lang.Object
  SourceFile: "SchedulerAdapter.scala"
  Scala: length = 0x
   
  InnerClass: 
   public final $anonfun$execute$1=class scala/actors/SchedulerAdapter$$anonfun$execute$1 of class scala/actors/SchedulerAdapter
  minor version: 0
  major version: 49
  Constant pool:
Asciz	SourceFile;
Asciz	SchedulerAdapter.scala;
Asciz	$init$;
Asciz	(Lscala/actors/SchedulerAdapter;)V;
Asciz	Code;
Asciz	LineNumberTable;
Asciz	$this;
Asciz	Lscala/actors/SchedulerAdapter;;
Asciz	LocalVariableTable;
Asciz	managedBlock;
Asciz	(Lscala/actors/SchedulerAdapter;Lscala/concurrent/ManagedBlocker;)V;
Asciz	scala/concurrent/ManagedBlocker;
class	scala/concurrent/ManagedBlocker
Asciz	block;
Asciz	()Z;
NameAndType	block:()Z
InterfaceMethod	scala/concurrent/ManagedBlocker.block:()Z
Asciz	blocker;
Asciz	Lscala/concurrent/ManagedBlocker;;
Asciz	onTerminate;
Asciz	(Lscala/actors/SchedulerAdapter;Lscala/actors/Reactor;Lscala/Function0;)V;
Asciz	scala/actors/Scheduler$;
class	scala/actors/Scheduler$
Asciz	MODULE$;
Asciz	Lscala/actors/Scheduler$;;
NameAndType	MODULE$:Lscala/actors/Scheduler$;
Field	scala/actors/Scheduler$.MODULE$:Lscala/actors/Scheduler$;
Asciz	scala/actors/scheduler/DelegatingScheduler;
class	scala/actors/scheduler/DelegatingScheduler
Asciz	(Lscala/actors/Reactor;Lscala/Function0;)V;
NameAndType	onTerminate:(Lscala/actors/Reactor;Lscala/Function0;)V
InterfaceMethod	scala/actors/scheduler/DelegatingScheduler.onTerminate:(Lscala/actors/Reactor;Lscala/Function0;)V
Asciz	a;
Asciz	Lscala/actors/Reactor;;
Asciz	f;
Asciz	Lscala/Function0;;
Asciz	terminated;
Asciz	(Lscala/actors/SchedulerAdapter;Lscala/actors/Reactor;)V;
Asciz	(Lscala/actors/Reactor;)V;
NameAndType	terminated:(Lscala/actors/Reactor;)V
InterfaceMethod	scala/actors/scheduler/DelegatingScheduler.terminated:(Lscala/actors/Reactor;)V
Asciz	newActor;
NameAndType	newActor:(Lscala/actors/Reactor;)V
InterfaceMethod	scala/actors/scheduler/DelegatingScheduler.newActor:(Lscala/actors/Reactor;)V
Asciz	isActive;
Asciz	(Lscala/actors/SchedulerAdapter;)Z;
NameAndType	isActive:()Z
InterfaceMethod	scala/actors/scheduler/DelegatingScheduler.isActive:()Z
Asciz	shutdown;
Asciz	()V;
NameAndType	shutdown:()V
InterfaceMethod	scala/actors/scheduler/DelegatingScheduler.shutdown:()V
Asciz	execute;
Asciz	(Lscala/actors/SchedulerAdapter;Ljava/lang/Runnable;)V;
Asciz	scala/actors/SchedulerAdapter$$anonfun$execute$1;
class	scala/actors/SchedulerAdapter$$anonfun$execute$1
Asciz	<init>;
NameAndType	"<init>":(Lscala/actors/SchedulerAdapter;Ljava/lang/Runnable;)V
Method	scala/actors/SchedulerAdapter$$anonfun$execute$1."<init>":(Lscala/actors/SchedulerAdapter;Ljava/lang/Runnable;)V
Asciz	scala/actors/IScheduler;
class	scala/actors/IScheduler
Asciz	(Lscala/Function0;)V;
NameAndType	execute:(Lscala/Function0;)V
InterfaceMethod	scala/actors/IScheduler.execute:(Lscala/Function0;)V
Asciz	task$1;
Asciz	Ljava/lang/Runnable;;
Asciz	Scala;
Asciz	InnerClasses;
Asciz	scala/actors/SchedulerAdapter;
class	scala/actors/SchedulerAdapter
Asciz	$anonfun$execute$1;
Asciz	scala/actors/SchedulerAdapter$class;
class	scala/actors/SchedulerAdapter$class
Asciz	java/lang/Object;
class	java/lang/Object

{
public static void $init$(scala.actors.SchedulerAdapter);
  Signature: (Lscala/actors/SchedulerAdapter;)V
  Code:
   Stack=0, Locals=1, Args_size=1
	return
  Labels:
  LocalVariableTable: 
   Start  Length  Slot  Name   Signature
   0      1      0    $this       Lscala/actors/SchedulerAdapter;


public static void managedBlock(scala.actors.SchedulerAdapter, scala.concurrent.ManagedBlocker);
  Signature: (Lscala/actors/SchedulerAdapter;Lscala/concurrent/ManagedBlocker;)V
  Code:
   Stack=1, Locals=2, Args_size=2
	aload_1
	invokeinterface	InterfaceMethod scala/concurrent/ManagedBlocker.block:()Z
	pop
	return
  Labels:
  LocalVariableTable: 
   Start  Length  Slot  Name   Signature
   0      8      0    $this       Lscala/actors/SchedulerAdapter;
   0      8      1    blocker       Lscala/concurrent/ManagedBlocker;


public static void onTerminate(scala.actors.SchedulerAdapter, scala.actors.Reactor, scala.Function0);
  Signature: (Lscala/actors/SchedulerAdapter;Lscala/actors/Reactor;Lscala/Function0;)V
  Code:
   Stack=3, Locals=3, Args_size=3
	getstatic	Field scala/actors/Scheduler$.MODULE$:Lscala/actors/Scheduler$;
	aload_1
	aload_2
	invokeinterface	InterfaceMethod scala/actors/scheduler/DelegatingScheduler.onTerminate:(Lscala/actors/Reactor;Lscala/Function0;)V
	return
  Labels:
  LocalVariableTable: 
   Start  Length  Slot  Name   Signature
   0      11      0    $this       Lscala/actors/SchedulerAdapter;
   0      11      1    a       Lscala/actors/Reactor;
   0      11      2    f       Lscala/Function0;


public static void terminated(scala.actors.SchedulerAdapter, scala.actors.Reactor);
  Signature: (Lscala/actors/SchedulerAdapter;Lscala/actors/Reactor;)V
  Code:
   Stack=2, Locals=2, Args_size=2
	getstatic	Field scala/actors/Scheduler$.MODULE$:Lscala/actors/Scheduler$;
	aload_1
	invokeinterface	InterfaceMethod scala/actors/scheduler/DelegatingScheduler.terminated:(Lscala/actors/Reactor;)V
	return
  Labels:
  LocalVariableTable: 
   Start  Length  Slot  Name   Signature
   0      10      0    $this       Lscala/actors/SchedulerAdapter;
   0      10      1    a       Lscala/actors/Reactor;


public static void newActor(scala.actors.SchedulerAdapter, scala.actors.Reactor);
  Signature: (Lscala/actors/SchedulerAdapter;Lscala/actors/Reactor;)V
  Code:
   Stack=2, Locals=2, Args_size=2
	getstatic	Field scala/actors/Scheduler$.MODULE$:Lscala/actors/Scheduler$;
	aload_1
	invokeinterface	InterfaceMethod scala/actors/scheduler/DelegatingScheduler.newActor:(Lscala/actors/Reactor;)V
	return
  Labels:
  LocalVariableTable: 
   Start  Length  Slot  Name   Signature
   0      10      0    $this       Lscala/actors/SchedulerAdapter;
   0      10      1    a       Lscala/actors/Reactor;


public static boolean isActive(scala.actors.SchedulerAdapter);
  Signature: (Lscala/actors/SchedulerAdapter;)Z
  Code:
   Stack=1, Locals=1, Args_size=1
	getstatic	Field scala/actors/Scheduler$.MODULE$:Lscala/actors/Scheduler$;
	invokeinterface	InterfaceMethod scala/actors/scheduler/DelegatingScheduler.isActive:()Z
	ireturn
  Labels:
  LocalVariableTable: 
   Start  Length  Slot  Name   Signature
   0      9      0    $this       Lscala/actors/SchedulerAdapter;


public static void shutdown(scala.actors.SchedulerAdapter);
  Signature: (Lscala/actors/SchedulerAdapter;)V
  Code:
   Stack=1, Locals=1, Args_size=1
	getstatic	Field scala/actors/Scheduler$.MODULE$:Lscala/actors/Scheduler$;
	invokeinterface	InterfaceMethod scala/actors/scheduler/DelegatingScheduler.shutdown:()V
	return
  Labels:
  LocalVariableTable: 
   Start  Length  Slot  Name   Signature
   0      9      0    $this       Lscala/actors/SchedulerAdapter;


public static void execute(scala.actors.SchedulerAdapter, java.lang.Runnable);
  Signature: (Lscala/actors/SchedulerAdapter;Ljava/lang/Runnable;)V
  Code:
   Stack=5, Locals=2, Args_size=2
	aload_0
	new	class scala/actors/SchedulerAdapter$$anonfun$execute$1
	dup
	aload_0
	aload_1
	invokespecial	Method scala/actors/SchedulerAdapter$$anonfun$execute$1."<init>":(Lscala/actors/SchedulerAdapter;Ljava/lang/Runnable;)V
	invokeinterface	InterfaceMethod scala/actors/IScheduler.execute:(Lscala/Function0;)V
	return
  Labels:
  LocalVariableTable: 
   Start  Length  Slot  Name   Signature
   0      16      0    $this       Lscala/actors/SchedulerAdapter;
   0      16      1    task$1       Ljava/lang/Runnable;


}

