Compiled from "Actor.scala"
public final class scala.actors.TIMEOUT extends java.lang.Object
  SourceFile: "Actor.scala"
  ScalaSig: length = 0x1E1
   05 00 47 07 05 01 02 FFFFFF88 42 07 01 07 54 49 4D 45
   4F 55 54 0A 02 03 04 01 06 61 63 74 6F 72 73 0A
   01 05 01 05 73 63 61 6C 61 03 00 10 02 08 09 0D
   01 02 06 08 0A 02 FFFFFF84 FFFFFF80 FFFFFF80 FFFFFF88 42 0B 02 07 54 49
   4D 45 4F 55 54 13 04 09 0C 14 18 10 02 0D 12 0D
   01 0E 0A 02 0F 10 01 04 6C 61 6E 67 0A 01 11 01
   04 6A 61 76 61 09 02 13 0E 02 06 4F 62 6A 65 63
   74 10 02 15 16 0D 01 04 09 02 17 04 02 0B 53 63
   61 6C 61 4F 62 6A 65 63 74 10 02 15 19 09 02 1A
   04 02 07 50 72 6F 64 75 63 74 08 05 1C 09 FFFFFF84 00
   1D 01 06 3C 69 6E 69 74 3E 14 01 07 08 08 1F 09
   FFFFFF84 FFFFFF80 FFFFFF80 FFFFFF84 22 20 01 08 74 6F 53 74 72 69 6E 67
   14 01 21 10 02 0D 22 09 02 23 0E 02 06 53 74 72
   69 6E 67 08 08 25 09 FFFFFF84 FFFFFF80 FFFFFF80 FFFFFF84 20 26 01 0D 70
   72 6F 64 75 63 74 50 72 65 66 69 78 15 01 21 08
   08 28 09 FFFFFF84 FFFFFF80 FFFFFF80 FFFFFF84 20 29 01 0C 70 72 6F 64 75
   63 74 41 72 69 74 79 15 01 2A 10 02 15 2B 09 02
   2C 04 02 03 49 6E 74 08 08 2E 09 FFFFFF84 FFFFFF80 FFFFFF80 FFFFFF84 20
   2F 01 0E 70 72 6F 64 75 63 74 45 6C 65 6D 65 6E
   74 14 02 30 33 10 02 15 31 09 02 32 04 02 03 41
   6E 79 08 07 34 2D FFFFFF81 FFFFFF80 FFFFFFC0 00 2A 01 03 78 24 31
   08 08 36 09 FFFFFF84 FFFFFF80 FFFFFF80 FFFFFF84 20 37 01 12 70 72 6F 64
   75 63 74 45 6C 65 6D 65 6E 74 4E 61 6D 65 14 02
   21 38 08 07 34 35 FFFFFF81 FFFFFF80 FFFFFFC0 00 2A 08 08 3A 09 FFFFFF84
   FFFFFF80 FFFFFF80 FFFFFF84 20 3B 01 08 63 61 6E 45 71 75 61 6C 14
   02 3C 3F 10 02 15 3D 09 02 3E 04 02 07 42 6F 6F
   6C 65 61 6E 08 07 34 39 FFFFFF81 FFFFFF80 FFFFFFC0 00 30 08 08 41
   09 FFFFFF84 FFFFFF80 FFFFFF80 FFFFFF84 08 42 01 0B 72 65 61 64 52 65 73
   6F 6C 76 65 14 01 0C 28 02 09 44 10 02 15 45 09
   02 46 04 02 0C 73 65 72 69 61 6C 69 7A 61 62 6C
   65 
  minor version: 0
  major version: 49
  Constant pool:
Asciz	SourceFile;
Asciz	Actor.scala;
Asciz	productElements;
Asciz	()Lscala/collection/Iterator;;
Asciz	Code;
Asciz	scala/actors/TIMEOUT$;
class	scala/actors/TIMEOUT$
Asciz	MODULE$;
Asciz	Lscala/actors/TIMEOUT$;;
NameAndType	MODULE$:Lscala/actors/TIMEOUT$;
Field	scala/actors/TIMEOUT$.MODULE$:Lscala/actors/TIMEOUT$;
NameAndType	productElements:()Lscala/collection/Iterator;
Method	scala/actors/TIMEOUT$.productElements:()Lscala/collection/Iterator;
Asciz	Deprecated;
Asciz	productIterator;
NameAndType	productIterator:()Lscala/collection/Iterator;
Method	scala/actors/TIMEOUT$.productIterator:()Lscala/collection/Iterator;
Asciz	canEqual;
Asciz	(Ljava/lang/Object;)Z;
NameAndType	canEqual:(Ljava/lang/Object;)Z
Method	scala/actors/TIMEOUT$.canEqual:(Ljava/lang/Object;)Z
Asciz	productElementName;
Asciz	(I)Ljava/lang/String;;
NameAndType	productElementName:(I)Ljava/lang/String;
Method	scala/actors/TIMEOUT$.productElementName:(I)Ljava/lang/String;
Asciz	productElement;
Asciz	(I)Ljava/lang/Object;;
NameAndType	productElement:(I)Ljava/lang/Object;
Method	scala/actors/TIMEOUT$.productElement:(I)Ljava/lang/Object;
Asciz	productArity;
Asciz	()I;
NameAndType	productArity:()I
Method	scala/actors/TIMEOUT$.productArity:()I
Asciz	productPrefix;
Asciz	()Ljava/lang/String;;
NameAndType	productPrefix:()Ljava/lang/String;
Method	scala/actors/TIMEOUT$.productPrefix:()Ljava/lang/String;
Asciz	ScalaSig;
Asciz	scala/actors/TIMEOUT;
class	scala/actors/TIMEOUT
Asciz	java/lang/Object;
class	java/lang/Object

{
public static final scala.collection.Iterator productElements();
  Signature: ()Lscala/collection/Iterator;
  Code:
   Stack=1, Locals=0, Args_size=0
	getstatic	Field scala/actors/TIMEOUT$.MODULE$:Lscala/actors/TIMEOUT$;
	invokevirtual	Method scala/actors/TIMEOUT$.productElements:()Lscala/collection/Iterator;
	areturn
  Labels:
  Deprecated: true

public static final scala.collection.Iterator productIterator();
  Signature: ()Lscala/collection/Iterator;
  Code:
   Stack=1, Locals=0, Args_size=0
	getstatic	Field scala/actors/TIMEOUT$.MODULE$:Lscala/actors/TIMEOUT$;
	invokevirtual	Method scala/actors/TIMEOUT$.productIterator:()Lscala/collection/Iterator;
	areturn
  Labels:

public static final boolean canEqual(java.lang.Object);
  Signature: (Ljava/lang/Object;)Z
  Code:
   Stack=2, Locals=1, Args_size=1
	getstatic	Field scala/actors/TIMEOUT$.MODULE$:Lscala/actors/TIMEOUT$;
	aload_0
	invokevirtual	Method scala/actors/TIMEOUT$.canEqual:(Ljava/lang/Object;)Z
	ireturn
  Labels:

public static final java.lang.String productElementName(int);
  Signature: (I)Ljava/lang/String;
  Code:
   Stack=2, Locals=1, Args_size=1
	getstatic	Field scala/actors/TIMEOUT$.MODULE$:Lscala/actors/TIMEOUT$;
	iload_0
	invokevirtual	Method scala/actors/TIMEOUT$.productElementName:(I)Ljava/lang/String;
	areturn
  Labels:

public static final java.lang.Object productElement(int);
  Signature: (I)Ljava/lang/Object;
  Code:
   Stack=2, Locals=1, Args_size=1
	getstatic	Field scala/actors/TIMEOUT$.MODULE$:Lscala/actors/TIMEOUT$;
	iload_0
	invokevirtual	Method scala/actors/TIMEOUT$.productElement:(I)Ljava/lang/Object;
	areturn
  Labels:

public static final int productArity();
  Signature: ()I
  Code:
   Stack=1, Locals=0, Args_size=0
	getstatic	Field scala/actors/TIMEOUT$.MODULE$:Lscala/actors/TIMEOUT$;
	invokevirtual	Method scala/actors/TIMEOUT$.productArity:()I
	ireturn
  Labels:

public static final java.lang.String productPrefix();
  Signature: ()Ljava/lang/String;
  Code:
   Stack=1, Locals=0, Args_size=0
	getstatic	Field scala/actors/TIMEOUT$.MODULE$:Lscala/actors/TIMEOUT$;
	invokevirtual	Method scala/actors/TIMEOUT$.productPrefix:()Ljava/lang/String;
	areturn
  Labels:

}

