class scala.actors.threadpool.locks.FIFOCondVar extends scala.actors.threadpool.locks.CondVar implements scala.actors.threadpool.locks.Condition,java.io.Serializable
  InnerClass: 
   public abstract QueuedSync=class scala/actors/threadpool/helpers/WaitQueue$QueuedSync of class scala/actors/threadpool/helpers/WaitQueue
   abstract ExclusiveLock=class scala/actors/threadpool/locks/CondVar$ExclusiveLock of class scala/actors/threadpool/locks/CondVar
   public WaitNode=class scala/actors/threadpool/helpers/WaitQueue$WaitNode of class scala/actors/threadpool/helpers/WaitQueue
   class scala/actors/threadpool/locks/FIFOCondVar$1
  minor version: 0
  major version: 49
  Constant pool:
Method	scala/actors/threadpool/locks/CondVar."<init>":(Lscala/actors/threadpool/locks/CondVar$ExclusiveLock;)V
class	scala/actors/threadpool/helpers/FIFOWaitQueue
Method	scala/actors/threadpool/helpers/FIFOWaitQueue."<init>":()V
Field	scala/actors/threadpool/locks/FIFOCondVar.wq:Lscala/actors/threadpool/helpers/WaitQueue;
Field	scala/actors/threadpool/locks/FIFOCondVar.lock:Lscala/actors/threadpool/locks/CondVar$ExclusiveLock;
InterfaceMethod	scala/actors/threadpool/locks/CondVar$ExclusiveLock.getHoldCount:()I
class	java/lang/IllegalMonitorStateException
Method	java/lang/IllegalMonitorStateException."<init>":()V
class	scala/actors/threadpool/helpers/WaitQueue$WaitNode
Method	scala/actors/threadpool/helpers/WaitQueue$WaitNode."<init>":()V
Method	scala/actors/threadpool/helpers/WaitQueue.insert:(Lscala/actors/threadpool/helpers/WaitQueue$WaitNode;)V
InterfaceMethod	scala/actors/threadpool/locks/CondVar$ExclusiveLock.unlock:()V
Field	scala/actors/threadpool/locks/FIFOCondVar.sync:Lscala/actors/threadpool/helpers/WaitQueue$QueuedSync;
Method	scala/actors/threadpool/helpers/WaitQueue$WaitNode.doWaitUninterruptibly:(Lscala/actors/threadpool/helpers/WaitQueue$QueuedSync;)V
InterfaceMethod	scala/actors/threadpool/locks/CondVar$ExclusiveLock.lock:()V
Method	java/lang/Thread.interrupted:()Z
class	java/lang/InterruptedException
Method	java/lang/InterruptedException."<init>":()V
Method	scala/actors/threadpool/helpers/WaitQueue$WaitNode.doWait:(Lscala/actors/threadpool/helpers/WaitQueue$QueuedSync;)V
Method	scala/actors/threadpool/TimeUnit.toNanos:(J)J
Method	scala/actors/threadpool/helpers/WaitQueue$WaitNode.doTimedWait:(Lscala/actors/threadpool/helpers/WaitQueue$QueuedSync;J)Z
class	java/lang/NullPointerException
Method	java/lang/NullPointerException."<init>":()V
Method	java/util/Date.getTime:()J
Method	java/lang/System.currentTimeMillis:()J
Field	scala/actors/threadpool/TimeUnit.MILLISECONDS:Lscala/actors/threadpool/TimeUnit;
Method	scala/actors/threadpool/locks/FIFOCondVar.await:(JLscala/actors/threadpool/TimeUnit;)Z
InterfaceMethod	scala/actors/threadpool/locks/CondVar$ExclusiveLock.isHeldByCurrentThread:()Z
Method	scala/actors/threadpool/helpers/WaitQueue.extract:()Lscala/actors/threadpool/helpers/WaitQueue$WaitNode;
Method	scala/actors/threadpool/helpers/WaitQueue$WaitNode.signal:(Lscala/actors/threadpool/helpers/WaitQueue$QueuedSync;)Z
Method	scala/actors/threadpool/helpers/WaitQueue.hasNodes:()Z
Method	scala/actors/threadpool/helpers/WaitQueue.getLength:()I
Method	scala/actors/threadpool/helpers/WaitQueue.getWaitingThreads:()Ljava/util/Collection;
class	scala/actors/threadpool/locks/FIFOCondVar$1
Method	scala/actors/threadpool/locks/FIFOCondVar$1."<init>":()V
class	scala/actors/threadpool/locks/FIFOCondVar
class	scala/actors/threadpool/locks/CondVar
class	scala/actors/threadpool/locks/Condition
class	java/io/Serializable
Asciz	sync;
class	scala/actors/threadpool/helpers/WaitQueue$QueuedSync
Asciz	QueuedSync;
Asciz	InnerClasses;
Asciz	Lscala/actors/threadpool/helpers/WaitQueue$QueuedSync;;
Asciz	wq;
Asciz	Lscala/actors/threadpool/helpers/WaitQueue;;
Asciz	<init>;
class	scala/actors/threadpool/locks/CondVar$ExclusiveLock
Asciz	ExclusiveLock;
Asciz	(Lscala/actors/threadpool/locks/CondVar$ExclusiveLock;)V;
Asciz	Code;
Asciz	awaitUninterruptibly;
Asciz	()V;
Asciz	await;
Asciz	Exceptions;
Asciz	(JLscala/actors/threadpool/TimeUnit;)Z;
Asciz	awaitUntil;
Asciz	(Ljava/util/Date;)Z;
Asciz	signal;
Asciz	signalAll;
Asciz	hasWaiters;
Asciz	()Z;
Asciz	getWaitQueueLength;
Asciz	()I;
Asciz	getWaitingThreads;
Asciz	()Ljava/util/Collection;;
Asciz	<clinit>;
NameAndType	"<init>":(Lscala/actors/threadpool/locks/CondVar$ExclusiveLock;)V
Asciz	scala/actors/threadpool/helpers/FIFOWaitQueue;
NameAndType	"<init>":()V
NameAndType	wq:Lscala/actors/threadpool/helpers/WaitQueue;
NameAndType	lock:Lscala/actors/threadpool/locks/CondVar$ExclusiveLock;
NameAndType	getHoldCount:()I
Asciz	java/lang/IllegalMonitorStateException;
class	scala/actors/threadpool/helpers/WaitQueue
Asciz	scala/actors/threadpool/helpers/WaitQueue$WaitNode;
Asciz	WaitNode;
NameAndType	insert:(Lscala/actors/threadpool/helpers/WaitQueue$WaitNode;)V
NameAndType	unlock:()V
NameAndType	sync:Lscala/actors/threadpool/helpers/WaitQueue$QueuedSync;
NameAndType	doWaitUninterruptibly:(Lscala/actors/threadpool/helpers/WaitQueue$QueuedSync;)V
NameAndType	lock:()V
class	java/lang/Thread
NameAndType	interrupted:()Z
Asciz	java/lang/InterruptedException;
NameAndType	doWait:(Lscala/actors/threadpool/helpers/WaitQueue$QueuedSync;)V
class	scala/actors/threadpool/TimeUnit
NameAndType	toNanos:(J)J
NameAndType	doTimedWait:(Lscala/actors/threadpool/helpers/WaitQueue$QueuedSync;J)Z
Asciz	java/lang/NullPointerException;
class	java/util/Date
NameAndType	getTime:()J
class	java/lang/System
NameAndType	currentTimeMillis:()J
NameAndType	MILLISECONDS:Lscala/actors/threadpool/TimeUnit;
NameAndType	await:(JLscala/actors/threadpool/TimeUnit;)Z
NameAndType	isHeldByCurrentThread:()Z
NameAndType	extract:()Lscala/actors/threadpool/helpers/WaitQueue$WaitNode;
NameAndType	signal:(Lscala/actors/threadpool/helpers/WaitQueue$QueuedSync;)Z
NameAndType	hasNodes:()Z
NameAndType	getLength:()I
NameAndType	getWaitingThreads:()Ljava/util/Collection;
Asciz	scala/actors/threadpool/locks/FIFOCondVar$1;
Asciz	;
Asciz	scala/actors/threadpool/locks/FIFOCondVar;
Asciz	scala/actors/threadpool/locks/CondVar;
Asciz	scala/actors/threadpool/locks/Condition;
Asciz	java/io/Serializable;
Asciz	scala/actors/threadpool/helpers/WaitQueue$QueuedSync;
Asciz	scala/actors/threadpool/locks/CondVar$ExclusiveLock;
Asciz	lock;
Asciz	Lscala/actors/threadpool/locks/CondVar$ExclusiveLock;;
Asciz	getHoldCount;
Asciz	scala/actors/threadpool/helpers/WaitQueue;
Asciz	insert;
Asciz	(Lscala/actors/threadpool/helpers/WaitQueue$WaitNode;)V;
Asciz	unlock;
Asciz	doWaitUninterruptibly;
Asciz	(Lscala/actors/threadpool/helpers/WaitQueue$QueuedSync;)V;
Asciz	java/lang/Thread;
Asciz	interrupted;
Asciz	doWait;
Asciz	scala/actors/threadpool/TimeUnit;
Asciz	toNanos;
Asciz	(J)J;
Asciz	doTimedWait;
Asciz	(Lscala/actors/threadpool/helpers/WaitQueue$QueuedSync;J)Z;
Asciz	java/util/Date;
Asciz	getTime;
Asciz	()J;
Asciz	java/lang/System;
Asciz	currentTimeMillis;
Asciz	MILLISECONDS;
Asciz	Lscala/actors/threadpool/TimeUnit;;
Asciz	isHeldByCurrentThread;
Asciz	extract;
Asciz	()Lscala/actors/threadpool/helpers/WaitQueue$WaitNode;;
Asciz	(Lscala/actors/threadpool/helpers/WaitQueue$QueuedSync;)Z;
Asciz	hasNodes;
Asciz	getLength;

{
private static final scala.actors.threadpool.helpers.WaitQueue$QueuedSync sync;
  Signature: Lscala/actors/threadpool/helpers/WaitQueue$QueuedSync;

private final scala.actors.threadpool.helpers.WaitQueue wq;
  Signature: Lscala/actors/threadpool/helpers/WaitQueue;

scala.actors.threadpool.locks.FIFOCondVar(scala.actors.threadpool.locks.CondVar$ExclusiveLock);
  Signature: (Lscala/actors/threadpool/locks/CondVar$ExclusiveLock;)V
  Code:
   Stack=3, Locals=2, Args_size=2
	aload_0
	aload_1
	invokespecial	Method scala/actors/threadpool/locks/CondVar."<init>":(Lscala/actors/threadpool/locks/CondVar$ExclusiveLock;)V
	aload_0
	new	class scala/actors/threadpool/helpers/FIFOWaitQueue
	dup
	invokespecial	Method scala/actors/threadpool/helpers/FIFOWaitQueue."<init>":()V
	putfield	Field wq:Lscala/actors/threadpool/helpers/WaitQueue;
	return
  Labels:

public void awaitUninterruptibly();
  Signature: ()V
  Code:
   Stack=2, Locals=6, Args_size=1
	aload_0
	getfield	Field lock:Lscala/actors/threadpool/locks/CondVar$ExclusiveLock;
	invokeinterface	InterfaceMethod scala/actors/threadpool/locks/CondVar$ExclusiveLock.getHoldCount:()I
	istore_1
	iload_1
	ifne	l1 // new
	new	class java/lang/IllegalMonitorStateException
	dup
	invokespecial	Method java/lang/IllegalMonitorStateException."<init>":()V
	athrow
l1	new	class scala/actors/threadpool/helpers/WaitQueue$WaitNode
	dup
	invokespecial	Method scala/actors/threadpool/helpers/WaitQueue$WaitNode."<init>":()V
	astore_2
	aload_0
	getfield	Field wq:Lscala/actors/threadpool/helpers/WaitQueue;
	aload_2
	invokevirtual	Method scala/actors/threadpool/helpers/WaitQueue.insert:(Lscala/actors/threadpool/helpers/WaitQueue$WaitNode;)V
	iload_1
	istore_3
l3	iload_3
	ifle	l2 // aload_2
	aload_0
	getfield	Field lock:Lscala/actors/threadpool/locks/CondVar$ExclusiveLock;
	invokeinterface	InterfaceMethod scala/actors/threadpool/locks/CondVar$ExclusiveLock.unlock:()V
	iinc	3, -1
	goto	l3 // iload_3
l2	aload_2
	getstatic	Field sync:Lscala/actors/threadpool/helpers/WaitQueue$QueuedSync;
	invokevirtual	Method scala/actors/threadpool/helpers/WaitQueue$WaitNode.doWaitUninterruptibly:(Lscala/actors/threadpool/helpers/WaitQueue$QueuedSync;)V
	iload_1
	istore_3
l5	iload_3
	ifle	l4 // goto
	aload_0
	getfield	Field lock:Lscala/actors/threadpool/locks/CondVar$ExclusiveLock;
	invokeinterface	InterfaceMethod scala/actors/threadpool/locks/CondVar$ExclusiveLock.lock:()V
	iinc	3, -1
	goto	l5 // iload_3
l4	goto	l6 // return
	astore	4
	iload_1
	istore	5
l8	iload	5
	ifle	l7 // aload
	aload_0
	getfield	Field lock:Lscala/actors/threadpool/locks/CondVar$ExclusiveLock;
	invokeinterface	InterfaceMethod scala/actors/threadpool/locks/CondVar$ExclusiveLock.lock:()V
	iinc	5, -1
	goto	l8 // iload
l7	aload	4
	athrow
l6	return
  Labels:
   	l1 = 22 // new
   	l3 = 40 // iload_3
   	l2 = 59 // aload_2
   	l5 = 68 // iload_3
   	l4 = 87 // goto
   	l8 = 95 // iload
   	l7 = 115 // aload
   	l6 = 118 // return
  Exception table:
   from   to  target type
    59    66    90   any
    90    92    90   any

public void await()   throws java.lang.InterruptedException;
  Signature: ()V
  Code:
   Stack=2, Locals=6, Args_size=1
	aload_0
	getfield	Field lock:Lscala/actors/threadpool/locks/CondVar$ExclusiveLock;
	invokeinterface	InterfaceMethod scala/actors/threadpool/locks/CondVar$ExclusiveLock.getHoldCount:()I
	istore_1
	iload_1
	ifne	l1 // invokestatic
	new	class java/lang/IllegalMonitorStateException
	dup
	invokespecial	Method java/lang/IllegalMonitorStateException."<init>":()V
	athrow
l1	invokestatic	Method java/lang/Thread.interrupted:()Z
	ifeq	l2 // new
	new	class java/lang/InterruptedException
	dup
	invokespecial	Method java/lang/InterruptedException."<init>":()V
	athrow
l2	new	class scala/actors/threadpool/helpers/WaitQueue$WaitNode
	dup
	invokespecial	Method scala/actors/threadpool/helpers/WaitQueue$WaitNode."<init>":()V
	astore_2
	aload_0
	getfield	Field wq:Lscala/actors/threadpool/helpers/WaitQueue;
	aload_2
	invokevirtual	Method scala/actors/threadpool/helpers/WaitQueue.insert:(Lscala/actors/threadpool/helpers/WaitQueue$WaitNode;)V
	iload_1
	istore_3
l4	iload_3
	ifle	l3 // aload_2
	aload_0
	getfield	Field lock:Lscala/actors/threadpool/locks/CondVar$ExclusiveLock;
	invokeinterface	InterfaceMethod scala/actors/threadpool/locks/CondVar$ExclusiveLock.unlock:()V
	iinc	3, -1
	goto	l4 // iload_3
l3	aload_2
	getstatic	Field sync:Lscala/actors/threadpool/helpers/WaitQueue$QueuedSync;
	invokevirtual	Method scala/actors/threadpool/helpers/WaitQueue$WaitNode.doWait:(Lscala/actors/threadpool/helpers/WaitQueue$QueuedSync;)V
	iload_1
	istore_3
l6	iload_3
	ifle	l5 // goto
	aload_0
	getfield	Field lock:Lscala/actors/threadpool/locks/CondVar$ExclusiveLock;
	invokeinterface	InterfaceMethod scala/actors/threadpool/locks/CondVar$ExclusiveLock.lock:()V
	iinc	3, -1
	goto	l6 // iload_3
l5	goto	l7 // return
	astore	4
	iload_1
	istore	5
l9	iload	5
	ifle	l8 // aload
	aload_0
	getfield	Field lock:Lscala/actors/threadpool/locks/CondVar$ExclusiveLock;
	invokeinterface	InterfaceMethod scala/actors/threadpool/locks/CondVar$ExclusiveLock.lock:()V
	iinc	5, -1
	goto	l9 // iload
l8	aload	4
	athrow
l7	return
  Labels:
   	l1 = 22 // invokestatic
   	l2 = 36 // new
   	l4 = 54 // iload_3
   	l3 = 73 // aload_2
   	l6 = 82 // iload_3
   	l5 = 101 // goto
   	l9 = 109 // iload
   	l8 = 129 // aload
   	l7 = 132 // return
  Exception table:
   from   to  target type
    73    80   104   any
   104   106   104   any
  Exceptions: 
   throws java.lang.InterruptedException
public boolean await(long, scala.actors.threadpool.TimeUnit)   throws java.lang.InterruptedException;
  Signature: (JLscala/actors/threadpool/TimeUnit;)Z
  Code:
   Stack=4, Locals=12, Args_size=3
	aload_0
	getfield	Field lock:Lscala/actors/threadpool/locks/CondVar$ExclusiveLock;
	invokeinterface	InterfaceMethod scala/actors/threadpool/locks/CondVar$ExclusiveLock.getHoldCount:()I
	istore	4
	iload	4
	ifne	l1 // invokestatic
	new	class java/lang/IllegalMonitorStateException
	dup
	invokespecial	Method java/lang/IllegalMonitorStateException."<init>":()V
	athrow
l1	invokestatic	Method java/lang/Thread.interrupted:()Z
	ifeq	l2 // aload_3
	new	class java/lang/InterruptedException
	dup
	invokespecial	Method java/lang/InterruptedException."<init>":()V
	athrow
l2	aload_3
	lload_1
	invokevirtual	Method scala/actors/threadpool/TimeUnit.toNanos:(J)J
	lstore	5
	new	class scala/actors/threadpool/helpers/WaitQueue$WaitNode
	dup
	invokespecial	Method scala/actors/threadpool/helpers/WaitQueue$WaitNode."<init>":()V
	astore	7
	aload_0
	getfield	Field wq:Lscala/actors/threadpool/helpers/WaitQueue;
	aload	7
	invokevirtual	Method scala/actors/threadpool/helpers/WaitQueue.insert:(Lscala/actors/threadpool/helpers/WaitQueue$WaitNode;)V
	iconst_0
	istore	8
	iload	4
	istore	9
l4	iload	9
	ifle	l3 // aload
	aload_0
	getfield	Field lock:Lscala/actors/threadpool/locks/CondVar$ExclusiveLock;
	invokeinterface	InterfaceMethod scala/actors/threadpool/locks/CondVar$ExclusiveLock.unlock:()V
	iinc	9, -1
	goto	l4 // iload
l3	aload	7
	getstatic	Field sync:Lscala/actors/threadpool/helpers/WaitQueue$QueuedSync;
	lload	5
	invokevirtual	Method scala/actors/threadpool/helpers/WaitQueue$WaitNode.doTimedWait:(Lscala/actors/threadpool/helpers/WaitQueue$QueuedSync;J)Z
	istore	8
	iload	4
	istore	9
l6	iload	9
	ifle	l5 // goto
	aload_0
	getfield	Field lock:Lscala/actors/threadpool/locks/CondVar$ExclusiveLock;
	invokeinterface	InterfaceMethod scala/actors/threadpool/locks/CondVar$ExclusiveLock.lock:()V
	iinc	9, -1
	goto	l6 // iload
l5	goto	l7 // iload
	astore	10
	iload	4
	istore	11
l9	iload	11
	ifle	l8 // aload
	aload_0
	getfield	Field lock:Lscala/actors/threadpool/locks/CondVar$ExclusiveLock;
	invokeinterface	InterfaceMethod scala/actors/threadpool/locks/CondVar$ExclusiveLock.lock:()V
	iinc	11, -1
	goto	l9 // iload
l8	aload	10
	athrow
l7	iload	8
	ireturn
  Labels:
   	l1 = 24 // invokestatic
   	l2 = 38 // aload_3
   	l4 = 70 // iload
   	l3 = 90 // aload
   	l6 = 106 // iload
   	l5 = 126 // goto
   	l9 = 135 // iload
   	l8 = 155 // aload
   	l7 = 158 // iload
  Exception table:
   from   to  target type
    90   102   129   any
   129   131   129   any
  Exceptions: 
   throws java.lang.InterruptedException
public boolean awaitUntil(java.util.Date)   throws java.lang.InterruptedException;
  Signature: (Ljava/util/Date;)Z
  Code:
   Stack=4, Locals=8, Args_size=2
	aload_1
	ifnonnull	l1 // aload_1
	new	class java/lang/NullPointerException
	dup
	invokespecial	Method java/lang/NullPointerException."<init>":()V
	athrow
l1	aload_1
	invokevirtual	Method java/util/Date.getTime:()J
	lstore_2
	invokestatic	Method java/lang/System.currentTimeMillis:()J
	lstore	4
	lload_2
	lload	4
	lsub
	lstore	6
	aload_0
	lload	6
	getstatic	Field scala/actors/threadpool/TimeUnit.MILLISECONDS:Lscala/actors/threadpool/TimeUnit;
	invokevirtual	Method await:(JLscala/actors/threadpool/TimeUnit;)Z
	ireturn
  Labels:
   	l1 = 12 // aload_1
  Exceptions: 
   throws java.lang.InterruptedException
public void signal();
  Signature: ()V
  Code:
   Stack=2, Locals=2, Args_size=1
	aload_0
	getfield	Field lock:Lscala/actors/threadpool/locks/CondVar$ExclusiveLock;
	invokeinterface	InterfaceMethod scala/actors/threadpool/locks/CondVar$ExclusiveLock.isHeldByCurrentThread:()Z
	ifne	l1 // aload_0
	new	class java/lang/IllegalMonitorStateException
	dup
	invokespecial	Method java/lang/IllegalMonitorStateException."<init>":()V
	athrow
l1	aload_0
	getfield	Field wq:Lscala/actors/threadpool/helpers/WaitQueue;
	invokevirtual	Method scala/actors/threadpool/helpers/WaitQueue.extract:()Lscala/actors/threadpool/helpers/WaitQueue$WaitNode;
	astore_1
	aload_1
	ifnonnull	l2 // aload_1
	return
l2	aload_1
	getstatic	Field sync:Lscala/actors/threadpool/helpers/WaitQueue$QueuedSync;
	invokevirtual	Method scala/actors/threadpool/helpers/WaitQueue$WaitNode.signal:(Lscala/actors/threadpool/helpers/WaitQueue$QueuedSync;)Z
	ifeq	l3 // goto
	return
l3	goto	l1 // aload_0
  Labels:
   	l1 = 20 // aload_0
   	l2 = 33 // aload_1
   	l3 = 44 // goto

public void signalAll();
  Signature: ()V
  Code:
   Stack=2, Locals=2, Args_size=1
	aload_0
	getfield	Field lock:Lscala/actors/threadpool/locks/CondVar$ExclusiveLock;
	invokeinterface	InterfaceMethod scala/actors/threadpool/locks/CondVar$ExclusiveLock.isHeldByCurrentThread:()Z
	ifne	l1 // aload_0
	new	class java/lang/IllegalMonitorStateException
	dup
	invokespecial	Method java/lang/IllegalMonitorStateException."<init>":()V
	athrow
l1	aload_0
	getfield	Field wq:Lscala/actors/threadpool/helpers/WaitQueue;
	invokevirtual	Method scala/actors/threadpool/helpers/WaitQueue.extract:()Lscala/actors/threadpool/helpers/WaitQueue$WaitNode;
	astore_1
	aload_1
	ifnonnull	l2 // aload_1
	return
l2	aload_1
	getstatic	Field sync:Lscala/actors/threadpool/helpers/WaitQueue$QueuedSync;
	invokevirtual	Method scala/actors/threadpool/helpers/WaitQueue$WaitNode.signal:(Lscala/actors/threadpool/helpers/WaitQueue$QueuedSync;)Z
	pop
	goto	l1 // aload_0
  Labels:
   	l1 = 20 // aload_0
   	l2 = 33 // aload_1

protected boolean hasWaiters();
  Signature: ()Z
  Code:
   Stack=2, Locals=1, Args_size=1
	aload_0
	getfield	Field lock:Lscala/actors/threadpool/locks/CondVar$ExclusiveLock;
	invokeinterface	InterfaceMethod scala/actors/threadpool/locks/CondVar$ExclusiveLock.isHeldByCurrentThread:()Z
	ifne	l1 // aload_0
	new	class java/lang/IllegalMonitorStateException
	dup
	invokespecial	Method java/lang/IllegalMonitorStateException."<init>":()V
	athrow
l1	aload_0
	getfield	Field wq:Lscala/actors/threadpool/helpers/WaitQueue;
	invokevirtual	Method scala/actors/threadpool/helpers/WaitQueue.hasNodes:()Z
	ireturn
  Labels:
   	l1 = 20 // aload_0

protected int getWaitQueueLength();
  Signature: ()I
  Code:
   Stack=2, Locals=1, Args_size=1
	aload_0
	getfield	Field lock:Lscala/actors/threadpool/locks/CondVar$ExclusiveLock;
	invokeinterface	InterfaceMethod scala/actors/threadpool/locks/CondVar$ExclusiveLock.isHeldByCurrentThread:()Z
	ifne	l1 // aload_0
	new	class java/lang/IllegalMonitorStateException
	dup
	invokespecial	Method java/lang/IllegalMonitorStateException."<init>":()V
	athrow
l1	aload_0
	getfield	Field wq:Lscala/actors/threadpool/helpers/WaitQueue;
	invokevirtual	Method scala/actors/threadpool/helpers/WaitQueue.getLength:()I
	ireturn
  Labels:
   	l1 = 20 // aload_0

protected java.util.Collection getWaitingThreads();
  Signature: ()Ljava/util/Collection;
  Code:
   Stack=2, Locals=1, Args_size=1
	aload_0
	getfield	Field lock:Lscala/actors/threadpool/locks/CondVar$ExclusiveLock;
	invokeinterface	InterfaceMethod scala/actors/threadpool/locks/CondVar$ExclusiveLock.isHeldByCurrentThread:()Z
	ifne	l1 // aload_0
	new	class java/lang/IllegalMonitorStateException
	dup
	invokespecial	Method java/lang/IllegalMonitorStateException."<init>":()V
	athrow
l1	aload_0
	getfield	Field wq:Lscala/actors/threadpool/helpers/WaitQueue;
	invokevirtual	Method scala/actors/threadpool/helpers/WaitQueue.getWaitingThreads:()Ljava/util/Collection;
	areturn
  Labels:
   	l1 = 20 // aload_0

static {};
  Signature: ()V
  Code:
   Stack=2, Locals=0, Args_size=0
	new	class scala/actors/threadpool/locks/FIFOCondVar$1
	dup
	invokespecial	Method scala/actors/threadpool/locks/FIFOCondVar$1."<init>":()V
	putstatic	Field sync:Lscala/actors/threadpool/helpers/WaitQueue$QueuedSync;
	return
  Labels:

}

