public class scala.actors.threadpool.locks.ReentrantReadWriteLock$WriteLock extends java.lang.Object implements scala.actors.threadpool.locks.Lock,scala.actors.threadpool.locks.CondVar$ExclusiveLock,java.io.Serializable
  InnerClass: 
   public WriteLock=class scala/actors/threadpool/locks/ReentrantReadWriteLock$WriteLock of class scala/actors/threadpool/locks/ReentrantReadWriteLock
   abstract ExclusiveLock=class scala/actors/threadpool/locks/CondVar$ExclusiveLock of class scala/actors/threadpool/locks/CondVar
   abstract Sync=class scala/actors/threadpool/locks/ReentrantReadWriteLock$Sync of class scala/actors/threadpool/locks/ReentrantReadWriteLock
   public ReadLock=class scala/actors/threadpool/locks/ReentrantReadWriteLock$ReadLock of class scala/actors/threadpool/locks/ReentrantReadWriteLock
  minor version: 0
  major version: 49
  Constant pool:
Method	java/lang/Object."<init>":()V
class	java/lang/NullPointerException
Method	java/lang/NullPointerException."<init>":()V
Field	scala/actors/threadpool/locks/ReentrantReadWriteLock$WriteLock.lock:Lscala/actors/threadpool/locks/ReentrantReadWriteLock;
Field	scala/actors/threadpool/locks/ReentrantReadWriteLock.sync:Lscala/actors/threadpool/locks/ReentrantReadWriteLock$Sync;
Method	scala/actors/threadpool/locks/ReentrantReadWriteLock$Sync.startWriteFromNewWriter:()Z
Method	java/lang/Thread.interrupted:()Z
Method	java/lang/Object.wait:()V
class	java/lang/InterruptedException
Method	scala/actors/threadpool/locks/ReentrantReadWriteLock$Sync.startWriteFromWaitingWriter:()Z
Method	java/lang/Thread.currentThread:()Ljava/lang/Thread;
Method	java/lang/Thread.interrupt:()V
Method	java/lang/InterruptedException."<init>":()V
Method	scala/actors/threadpool/locks/ReentrantReadWriteLock$Sync.cancelledWaitingWriter:()V
Method	java/lang/Object.notify:()V
Field	scala/actors/threadpool/locks/ReentrantReadWriteLock.readerLock_:Lscala/actors/threadpool/locks/ReentrantReadWriteLock$ReadLock;
Method	scala/actors/threadpool/locks/ReentrantReadWriteLock$ReadLock.signalWaiters:()V
Method	scala/actors/threadpool/locks/ReentrantReadWriteLock$Sync.startWrite:()Z
Method	scala/actors/threadpool/TimeUnit.toNanos:(J)J
Method	scala/actors/threadpool/helpers/Utils.nanoTime:()J
Field	scala/actors/threadpool/TimeUnit.NANOSECONDS:Lscala/actors/threadpool/TimeUnit;
Method	scala/actors/threadpool/TimeUnit.timedWait:(Ljava/lang/Object;J)V
Method	scala/actors/threadpool/locks/ReentrantReadWriteLock$Sync.endWrite:()I
Field	scala/actors/threadpool/locks/ReentrantReadWriteLock.writerLock_:Lscala/actors/threadpool/locks/ReentrantReadWriteLock$WriteLock;
Method	scala/actors/threadpool/locks/ReentrantReadWriteLock$WriteLock.signalWaiters:()V
class	scala/actors/threadpool/locks/CondVar
Method	scala/actors/threadpool/locks/CondVar."<init>":(Lscala/actors/threadpool/locks/CondVar$ExclusiveLock;)V
Method	scala/actors/threadpool/locks/ReentrantReadWriteLock.getOwner:()Ljava/lang/Thread;
class	java/lang/StringBuilder
Method	java/lang/StringBuilder."<init>":()V
Method	java/lang/Object.toString:()Ljava/lang/String;
Method	java/lang/StringBuilder.append:(Ljava/lang/String;)Ljava/lang/StringBuilder;
String	[Unlocked]
String	[Locked by thread 
Method	java/lang/Thread.getName:()Ljava/lang/String;
String	]
Method	java/lang/StringBuilder.toString:()Ljava/lang/String;
Method	scala/actors/threadpool/locks/ReentrantReadWriteLock$Sync.isWriteLockedByCurrentThread:()Z
Method	scala/actors/threadpool/locks/ReentrantReadWriteLock$Sync.getWriteHoldCount:()I
class	scala/actors/threadpool/locks/ReentrantReadWriteLock$WriteLock
class	java/lang/Object
class	scala/actors/threadpool/locks/Lock
class	scala/actors/threadpool/locks/CondVar$ExclusiveLock
class	java/io/Serializable
Asciz	serialVersionUID;
Asciz	J;
Asciz	ConstantValue;
long	-4992448646407690164l;
Asciz	lock;
Asciz	Lscala/actors/threadpool/locks/ReentrantReadWriteLock;;
Asciz	<init>;
Asciz	(Lscala/actors/threadpool/locks/ReentrantReadWriteLock;)V;
Asciz	Code;
Asciz	()V;
Asciz	lockInterruptibly;
Asciz	Exceptions;
Asciz	tryLock;
Asciz	()Z;
Asciz	(JLscala/actors/threadpool/TimeUnit;)Z;
Asciz	unlock;
Asciz	newCondition;
Asciz	()Lscala/actors/threadpool/locks/Condition;;
Asciz	signalWaiters;
Asciz	toString;
Asciz	()Ljava/lang/String;;
Asciz	isHeldByCurrentThread;
Asciz	getHoldCount;
Asciz	()I;
NameAndType	"<init>":()V
Asciz	java/lang/NullPointerException;
NameAndType	lock:Lscala/actors/threadpool/locks/ReentrantReadWriteLock;
class	scala/actors/threadpool/locks/ReentrantReadWriteLock
NameAndType	sync:Lscala/actors/threadpool/locks/ReentrantReadWriteLock$Sync;
class	scala/actors/threadpool/locks/ReentrantReadWriteLock$Sync
NameAndType	startWriteFromNewWriter:()Z
class	java/lang/Thread
NameAndType	interrupted:()Z
NameAndType	wait:()V
Asciz	java/lang/InterruptedException;
NameAndType	startWriteFromWaitingWriter:()Z
NameAndType	currentThread:()Ljava/lang/Thread;
NameAndType	interrupt:()V
NameAndType	cancelledWaitingWriter:()V
NameAndType	notify:()V
NameAndType	readerLock_:Lscala/actors/threadpool/locks/ReentrantReadWriteLock$ReadLock;
class	scala/actors/threadpool/locks/ReentrantReadWriteLock$ReadLock
NameAndType	signalWaiters:()V
NameAndType	startWrite:()Z
class	scala/actors/threadpool/TimeUnit
NameAndType	toNanos:(J)J
class	scala/actors/threadpool/helpers/Utils
NameAndType	nanoTime:()J
NameAndType	NANOSECONDS:Lscala/actors/threadpool/TimeUnit;
NameAndType	timedWait:(Ljava/lang/Object;J)V
NameAndType	endWrite:()I
NameAndType	writerLock_:Lscala/actors/threadpool/locks/ReentrantReadWriteLock$WriteLock;
Asciz	scala/actors/threadpool/locks/CondVar;
NameAndType	"<init>":(Lscala/actors/threadpool/locks/CondVar$ExclusiveLock;)V
NameAndType	getOwner:()Ljava/lang/Thread;
Asciz	java/lang/StringBuilder;
NameAndType	toString:()Ljava/lang/String;
NameAndType	append:(Ljava/lang/String;)Ljava/lang/StringBuilder;
Asciz	[Unlocked];
Asciz	[Locked by thread ;
NameAndType	getName:()Ljava/lang/String;
Asciz	];
NameAndType	isWriteLockedByCurrentThread:()Z
NameAndType	getWriteHoldCount:()I
Asciz	scala/actors/threadpool/locks/ReentrantReadWriteLock$WriteLock;
Asciz	WriteLock;
Asciz	InnerClasses;
Asciz	java/lang/Object;
Asciz	scala/actors/threadpool/locks/Lock;
Asciz	scala/actors/threadpool/locks/CondVar$ExclusiveLock;
Asciz	ExclusiveLock;
Asciz	java/io/Serializable;
Asciz	scala/actors/threadpool/locks/ReentrantReadWriteLock;
Asciz	sync;
Asciz	Sync;
Asciz	Lscala/actors/threadpool/locks/ReentrantReadWriteLock$Sync;;
Asciz	scala/actors/threadpool/locks/ReentrantReadWriteLock$Sync;
Asciz	startWriteFromNewWriter;
Asciz	java/lang/Thread;
Asciz	interrupted;
Asciz	wait;
Asciz	startWriteFromWaitingWriter;
Asciz	currentThread;
Asciz	()Ljava/lang/Thread;;
Asciz	interrupt;
Asciz	cancelledWaitingWriter;
Asciz	notify;
Asciz	readerLock_;
Asciz	ReadLock;
Asciz	Lscala/actors/threadpool/locks/ReentrantReadWriteLock$ReadLock;;
Asciz	scala/actors/threadpool/locks/ReentrantReadWriteLock$ReadLock;
Asciz	startWrite;
Asciz	scala/actors/threadpool/TimeUnit;
Asciz	toNanos;
Asciz	(J)J;
Asciz	scala/actors/threadpool/helpers/Utils;
Asciz	nanoTime;
Asciz	()J;
Asciz	NANOSECONDS;
Asciz	Lscala/actors/threadpool/TimeUnit;;
Asciz	timedWait;
Asciz	(Ljava/lang/Object;J)V;
Asciz	endWrite;
Asciz	writerLock_;
Asciz	Lscala/actors/threadpool/locks/ReentrantReadWriteLock$WriteLock;;
Asciz	(Lscala/actors/threadpool/locks/CondVar$ExclusiveLock;)V;
Asciz	getOwner;
Asciz	append;
Asciz	(Ljava/lang/String;)Ljava/lang/StringBuilder;;
Asciz	getName;
Asciz	isWriteLockedByCurrentThread;
Asciz	getWriteHoldCount;

{
private static final long serialVersionUID;
  Signature: J
  Constant value: long -4992448646407690164l
final scala.actors.threadpool.locks.ReentrantReadWriteLock lock;
  Signature: Lscala/actors/threadpool/locks/ReentrantReadWriteLock;

protected scala.actors.threadpool.locks.ReentrantReadWriteLock$WriteLock(scala.actors.threadpool.locks.ReentrantReadWriteLock);
  Signature: (Lscala/actors/threadpool/locks/ReentrantReadWriteLock;)V
  Code:
   Stack=2, Locals=2, Args_size=2
	aload_0
	invokespecial	Method java/lang/Object."<init>":()V
	aload_1
	ifnonnull	l1 // aload_0
	new	class java/lang/NullPointerException
	dup
	invokespecial	Method java/lang/NullPointerException."<init>":()V
	athrow
l1	aload_0
	aload_1
	putfield	Field lock:Lscala/actors/threadpool/locks/ReentrantReadWriteLock;
	return
  Labels:
   	l1 = 16 // aload_0

public void lock();
  Signature: ()V
  Code:
   Stack=2, Locals=6, Args_size=1
	aload_0
	dup
	astore_1
	monitorenter
	aload_0
	getfield	Field lock:Lscala/actors/threadpool/locks/ReentrantReadWriteLock;
	getfield	Field scala/actors/threadpool/locks/ReentrantReadWriteLock.sync:Lscala/actors/threadpool/locks/ReentrantReadWriteLock$Sync;
	invokevirtual	Method scala/actors/threadpool/locks/ReentrantReadWriteLock$Sync.startWriteFromNewWriter:()Z
	ifeq	l1 // invokestatic
	aload_1
	monitorexit
	return
l1	invokestatic	Method java/lang/Thread.interrupted:()Z
	istore_2
l3	aload_0
	invokevirtual	Method java/lang/Object.wait:()V
	goto	l2 // aload_0
	astore_3
	iconst_1
	istore_2
l2	aload_0
	getfield	Field lock:Lscala/actors/threadpool/locks/ReentrantReadWriteLock;
	getfield	Field scala/actors/threadpool/locks/ReentrantReadWriteLock.sync:Lscala/actors/threadpool/locks/ReentrantReadWriteLock$Sync;
	invokevirtual	Method scala/actors/threadpool/locks/ReentrantReadWriteLock$Sync.startWriteFromWaitingWriter:()Z
	ifeq	l3 // aload_0
	iload_2
	ifeq	l4 // aload_1
	invokestatic	Method java/lang/Thread.currentThread:()Ljava/lang/Thread;
	invokevirtual	Method java/lang/Thread.interrupt:()V
l4	aload_1
	monitorexit
	return
	astore	4
	iload_2
	ifeq	l5 // aload
	invokestatic	Method java/lang/Thread.currentThread:()Ljava/lang/Thread;
	invokevirtual	Method java/lang/Thread.interrupt:()V
l5	aload	4
	athrow
	astore	5
	aload_1
	monitorexit
	aload	5
	athrow
  Labels:
   	l1 = 20 // invokestatic
   	l3 = 24 // aload_0
   	l2 = 34 // aload_0
   	l4 = 57 // aload_1
   	l5 = 72 // aload
  Exception table:
   from   to  target type
    24    28    31   Class java/lang/InterruptedException

    24    47    60   any
    60    62    60   any
     4    19    75   any
    20    59    75   any
    60    79    75   any

public void lockInterruptibly()   throws java.lang.InterruptedException;
  Signature: ()V
  Code:
   Stack=2, Locals=5, Args_size=1
	invokestatic	Method java/lang/Thread.interrupted:()Z
	ifeq	l1 // aconst_null
	new	class java/lang/InterruptedException
	dup
	invokespecial	Method java/lang/InterruptedException."<init>":()V
	athrow
l1	aconst_null
	astore_1
	aload_0
	dup
	astore_2
	monitorenter
	aload_0
	getfield	Field lock:Lscala/actors/threadpool/locks/ReentrantReadWriteLock;
	getfield	Field scala/actors/threadpool/locks/ReentrantReadWriteLock.sync:Lscala/actors/threadpool/locks/ReentrantReadWriteLock$Sync;
	invokevirtual	Method scala/actors/threadpool/locks/ReentrantReadWriteLock$Sync.startWriteFromNewWriter:()Z
	ifne	l2 // aload_2
l4	aload_0
	invokevirtual	Method java/lang/Object.wait:()V
	aload_0
	getfield	Field lock:Lscala/actors/threadpool/locks/ReentrantReadWriteLock;
	getfield	Field scala/actors/threadpool/locks/ReentrantReadWriteLock.sync:Lscala/actors/threadpool/locks/ReentrantReadWriteLock$Sync;
	invokevirtual	Method scala/actors/threadpool/locks/ReentrantReadWriteLock$Sync.startWriteFromWaitingWriter:()Z
	ifeq	l3 // goto
	aload_2
	monitorexit
	return
l3	goto	l4 // aload_0
	astore_3
	aload_0
	getfield	Field lock:Lscala/actors/threadpool/locks/ReentrantReadWriteLock;
	getfield	Field scala/actors/threadpool/locks/ReentrantReadWriteLock.sync:Lscala/actors/threadpool/locks/ReentrantReadWriteLock$Sync;
	invokevirtual	Method scala/actors/threadpool/locks/ReentrantReadWriteLock$Sync.cancelledWaitingWriter:()V
	aload_0
	invokevirtual	Method java/lang/Object.notify:()V
	aload_3
	astore_1
	goto	l2 // aload_2
l2	aload_2
	monitorexit
	goto	l5 // aload_1
	astore	4
	aload_2
	monitorexit
	aload	4
	athrow
l5	aload_1
	ifnull	l6 // return
	aload_0
	getfield	Field lock:Lscala/actors/threadpool/locks/ReentrantReadWriteLock;
	getfield	Field scala/actors/threadpool/locks/ReentrantReadWriteLock.readerLock_:Lscala/actors/threadpool/locks/ReentrantReadWriteLock$ReadLock;
	invokevirtual	Method scala/actors/threadpool/locks/ReentrantReadWriteLock$ReadLock.signalWaiters:()V
	aload_1
	athrow
l6	return
  Labels:
   	l1 = 14 // aconst_null
   	l4 = 33 // aload_0
   	l3 = 53 // goto
   	l2 = 76 // aload_2
   	l5 = 88 // aload_1
   	l6 = 104 // return
  Exception table:
   from   to  target type
    33    50    56   Class java/lang/InterruptedException

    20    52    81   any
    53    78    81   any
    81    85    81   any
  Exceptions: 
   throws java.lang.InterruptedException
public boolean tryLock();
  Signature: ()Z
  Code:
   Stack=1, Locals=1, Args_size=1
	aload_0
	getfield	Field lock:Lscala/actors/threadpool/locks/ReentrantReadWriteLock;
	getfield	Field scala/actors/threadpool/locks/ReentrantReadWriteLock.sync:Lscala/actors/threadpool/locks/ReentrantReadWriteLock$Sync;
	invokevirtual	Method scala/actors/threadpool/locks/ReentrantReadWriteLock$Sync.startWrite:()Z
	ireturn
  Labels:

public boolean tryLock(long, scala.actors.threadpool.TimeUnit)   throws java.lang.InterruptedException;
  Signature: (JLscala/actors/threadpool/TimeUnit;)Z
  Code:
   Stack=4, Locals=12, Args_size=3
	invokestatic	Method java/lang/Thread.interrupted:()Z
	ifeq	l1 // aconst_null
	new	class java/lang/InterruptedException
	dup
	invokespecial	Method java/lang/InterruptedException."<init>":()V
	athrow
l1	aconst_null
	astore	4
	aload_3
	lload_1
	invokevirtual	Method scala/actors/threadpool/TimeUnit.toNanos:(J)J
	lstore	5
	aload_0
	dup
	astore	7
	monitorenter
	lload	5
	lconst_0
	lcmp
	ifgt	l2 // aload_0
	aload_0
	getfield	Field lock:Lscala/actors/threadpool/locks/ReentrantReadWriteLock;
	getfield	Field scala/actors/threadpool/locks/ReentrantReadWriteLock.sync:Lscala/actors/threadpool/locks/ReentrantReadWriteLock$Sync;
	invokevirtual	Method scala/actors/threadpool/locks/ReentrantReadWriteLock$Sync.startWrite:()Z
	aload	7
	monitorexit
	ireturn
l2	aload_0
	getfield	Field lock:Lscala/actors/threadpool/locks/ReentrantReadWriteLock;
	getfield	Field scala/actors/threadpool/locks/ReentrantReadWriteLock.sync:Lscala/actors/threadpool/locks/ReentrantReadWriteLock$Sync;
	invokevirtual	Method scala/actors/threadpool/locks/ReentrantReadWriteLock$Sync.startWriteFromNewWriter:()Z
	ifeq	l3 // invokestatic
	iconst_1
	aload	7
	monitorexit
	ireturn
l3	invokestatic	Method scala/actors/threadpool/helpers/Utils.nanoTime:()J
	lload	5
	ladd
	lstore	8
l7	getstatic	Field scala/actors/threadpool/TimeUnit.NANOSECONDS:Lscala/actors/threadpool/TimeUnit;
	aload_0
	lload	5
	invokevirtual	Method scala/actors/threadpool/TimeUnit.timedWait:(Ljava/lang/Object;J)V
	goto	l4 // aload_0
	astore	10
	aload_0
	getfield	Field lock:Lscala/actors/threadpool/locks/ReentrantReadWriteLock;
	getfield	Field scala/actors/threadpool/locks/ReentrantReadWriteLock.sync:Lscala/actors/threadpool/locks/ReentrantReadWriteLock$Sync;
	invokevirtual	Method scala/actors/threadpool/locks/ReentrantReadWriteLock$Sync.cancelledWaitingWriter:()V
	aload_0
	invokevirtual	Method java/lang/Object.notify:()V
	aload	10
	astore	4
	goto	l5 // aload
l4	aload_0
	getfield	Field lock:Lscala/actors/threadpool/locks/ReentrantReadWriteLock;
	getfield	Field scala/actors/threadpool/locks/ReentrantReadWriteLock.sync:Lscala/actors/threadpool/locks/ReentrantReadWriteLock$Sync;
	invokevirtual	Method scala/actors/threadpool/locks/ReentrantReadWriteLock$Sync.startWriteFromWaitingWriter:()Z
	ifeq	l6 // lload
	iconst_1
	aload	7
	monitorexit
	ireturn
l6	lload	8
	invokestatic	Method scala/actors/threadpool/helpers/Utils.nanoTime:()J
	lsub
	lstore	5
	lload	5
	lconst_0
	lcmp
	ifgt	l7 // getstatic
	aload_0
	getfield	Field lock:Lscala/actors/threadpool/locks/ReentrantReadWriteLock;
	getfield	Field scala/actors/threadpool/locks/ReentrantReadWriteLock.sync:Lscala/actors/threadpool/locks/ReentrantReadWriteLock$Sync;
	invokevirtual	Method scala/actors/threadpool/locks/ReentrantReadWriteLock$Sync.cancelledWaitingWriter:()V
	aload_0
	invokevirtual	Method java/lang/Object.notify:()V
	goto	l5 // aload
l5	aload	7
	monitorexit
	goto	l8 // aload_0
	astore	11
	aload	7
	monitorexit
	aload	11
	athrow
l8	aload_0
	getfield	Field lock:Lscala/actors/threadpool/locks/ReentrantReadWriteLock;
	getfield	Field scala/actors/threadpool/locks/ReentrantReadWriteLock.readerLock_:Lscala/actors/threadpool/locks/ReentrantReadWriteLock$ReadLock;
	invokevirtual	Method scala/actors/threadpool/locks/ReentrantReadWriteLock$ReadLock.signalWaiters:()V
	aload	4
	ifnull	l9 // iconst_0
	aload	4
	athrow
l9	iconst_0
	ireturn
  Labels:
   	l1 = 14 // aconst_null
   	l2 = 50 // aload_0
   	l3 = 68 // invokestatic
   	l7 = 76 // getstatic
   	l4 = 111 // aload_0
   	l6 = 129 // lload
   	l5 = 161 // aload
   	l8 = 175 // aload_0
   	l9 = 193 // iconst_0
  Exception table:
   from   to  target type
    76    85    88   Class java/lang/InterruptedException

    29    49   167   any
    50    67   167   any
    68   128   167   any
   129   164   167   any
   167   172   167   any
  Exceptions: 
   throws java.lang.InterruptedException
public void unlock();
  Signature: ()V
  Code:
   Stack=1, Locals=1, Args_size=1
	aload_0
	getfield	Field lock:Lscala/actors/threadpool/locks/ReentrantReadWriteLock;
	getfield	Field scala/actors/threadpool/locks/ReentrantReadWriteLock.sync:Lscala/actors/threadpool/locks/ReentrantReadWriteLock$Sync;
	invokevirtual	Method scala/actors/threadpool/locks/ReentrantReadWriteLock$Sync.endWrite:()I
	tableswitch{ //0 to 2
		0: 36;
		1: 37;
		2: 48;
		default: 59 }
	return
	aload_0
	getfield	Field lock:Lscala/actors/threadpool/locks/ReentrantReadWriteLock;
	getfield	Field scala/actors/threadpool/locks/ReentrantReadWriteLock.readerLock_:Lscala/actors/threadpool/locks/ReentrantReadWriteLock$ReadLock;
	invokevirtual	Method scala/actors/threadpool/locks/ReentrantReadWriteLock$ReadLock.signalWaiters:()V
	return
	aload_0
	getfield	Field lock:Lscala/actors/threadpool/locks/ReentrantReadWriteLock;
	getfield	Field scala/actors/threadpool/locks/ReentrantReadWriteLock.writerLock_:Lscala/actors/threadpool/locks/ReentrantReadWriteLock$WriteLock;
	invokevirtual	Method signalWaiters:()V
	return
	return
  Labels:

public scala.actors.threadpool.locks.Condition newCondition();
  Signature: ()Lscala/actors/threadpool/locks/Condition;
  Code:
   Stack=3, Locals=1, Args_size=1
	new	class scala/actors/threadpool/locks/CondVar
	dup
	aload_0
	invokespecial	Method scala/actors/threadpool/locks/CondVar."<init>":(Lscala/actors/threadpool/locks/CondVar$ExclusiveLock;)V
	areturn
  Labels:

synchronized void signalWaiters();
  Signature: ()V
  Code:
   Stack=1, Locals=1, Args_size=1
	aload_0
	invokevirtual	Method java/lang/Object.notify:()V
	return
  Labels:

public java.lang.String toString();
  Signature: ()Ljava/lang/String;
  Code:
   Stack=3, Locals=2, Args_size=1
	aload_0
	getfield	Field lock:Lscala/actors/threadpool/locks/ReentrantReadWriteLock;
	invokevirtual	Method scala/actors/threadpool/locks/ReentrantReadWriteLock.getOwner:()Ljava/lang/Thread;
	astore_1
	new	class java/lang/StringBuilder
	dup
	invokespecial	Method java/lang/StringBuilder."<init>":()V
	aload_0
	invokespecial	Method java/lang/Object.toString:()Ljava/lang/String;
	invokevirtual	Method java/lang/StringBuilder.append:(Ljava/lang/String;)Ljava/lang/StringBuilder;
	aload_1
	ifnonnull	l1 // new
	ldc	String [Unlocked]
	goto	l2 // invokevirtual
l1	new	class java/lang/StringBuilder
	dup
	invokespecial	Method java/lang/StringBuilder."<init>":()V
	ldc	String [Locked by thread 
	invokevirtual	Method java/lang/StringBuilder.append:(Ljava/lang/String;)Ljava/lang/StringBuilder;
	aload_1
	invokevirtual	Method java/lang/Thread.getName:()Ljava/lang/String;
	invokevirtual	Method java/lang/StringBuilder.append:(Ljava/lang/String;)Ljava/lang/StringBuilder;
	ldc	String ]
	invokevirtual	Method java/lang/StringBuilder.append:(Ljava/lang/String;)Ljava/lang/StringBuilder;
	invokevirtual	Method java/lang/StringBuilder.toString:()Ljava/lang/String;
l2	invokevirtual	Method java/lang/StringBuilder.append:(Ljava/lang/String;)Ljava/lang/StringBuilder;
	invokevirtual	Method java/lang/StringBuilder.toString:()Ljava/lang/String;
	areturn
  Labels:
   	l1 = 31 // new
   	l2 = 58 // invokevirtual

public boolean isHeldByCurrentThread();
  Signature: ()Z
  Code:
   Stack=1, Locals=1, Args_size=1
	aload_0
	getfield	Field lock:Lscala/actors/threadpool/locks/ReentrantReadWriteLock;
	getfield	Field scala/actors/threadpool/locks/ReentrantReadWriteLock.sync:Lscala/actors/threadpool/locks/ReentrantReadWriteLock$Sync;
	invokevirtual	Method scala/actors/threadpool/locks/ReentrantReadWriteLock$Sync.isWriteLockedByCurrentThread:()Z
	ireturn
  Labels:

public int getHoldCount();
  Signature: ()I
  Code:
   Stack=1, Locals=1, Args_size=1
	aload_0
	getfield	Field lock:Lscala/actors/threadpool/locks/ReentrantReadWriteLock;
	getfield	Field scala/actors/threadpool/locks/ReentrantReadWriteLock.sync:Lscala/actors/threadpool/locks/ReentrantReadWriteLock$Sync;
	invokevirtual	Method scala/actors/threadpool/locks/ReentrantReadWriteLock$Sync.getWriteHoldCount:()I
	ireturn
  Labels:

}

