final class scala.actors.threadpool.locks.ReentrantLock$FairSync extends scala.actors.threadpool.locks.ReentrantLock$Sync implements scala.actors.threadpool.helpers.WaitQueue$QueuedSync
  InnerClass: 
   public WaitNode=class scala/actors/threadpool/helpers/WaitQueue$WaitNode of class scala/actors/threadpool/helpers/WaitQueue
   final FairSync=class scala/actors/threadpool/locks/ReentrantLock$FairSync of class scala/actors/threadpool/locks/ReentrantLock
   abstract Sync=class scala/actors/threadpool/locks/ReentrantLock$Sync of class scala/actors/threadpool/locks/ReentrantLock
   public abstract QueuedSync=class scala/actors/threadpool/helpers/WaitQueue$QueuedSync of class scala/actors/threadpool/helpers/WaitQueue
  minor version: 0
  major version: 49
  Constant pool:
Method	scala/actors/threadpool/locks/ReentrantLock$Sync."<init>":()V
class	scala/actors/threadpool/helpers/FIFOWaitQueue
Method	scala/actors/threadpool/helpers/FIFOWaitQueue."<init>":()V
Field	scala/actors/threadpool/locks/ReentrantLock$FairSync.wq_:Lscala/actors/threadpool/helpers/WaitQueue;
Method	java/lang/Thread.currentThread:()Ljava/lang/Thread;
Field	scala/actors/threadpool/locks/ReentrantLock$FairSync.owner_:Ljava/lang/Thread;
Field	scala/actors/threadpool/locks/ReentrantLock$FairSync.holds_:I
Method	scala/actors/threadpool/locks/ReentrantLock$FairSync.incHolds:()V
Method	scala/actors/threadpool/helpers/WaitQueue.insert:(Lscala/actors/threadpool/helpers/WaitQueue$WaitNode;)V
Method	scala/actors/threadpool/helpers/WaitQueue$WaitNode.getOwner:()Ljava/lang/Thread;
class	scala/actors/threadpool/helpers/WaitQueue$WaitNode
Method	scala/actors/threadpool/helpers/WaitQueue$WaitNode."<init>":()V
Method	scala/actors/threadpool/helpers/WaitQueue$WaitNode.doWaitUninterruptibly:(Lscala/actors/threadpool/helpers/WaitQueue$QueuedSync;)V
Method	java/lang/Thread.interrupted:()Z
class	java/lang/InterruptedException
Method	java/lang/InterruptedException."<init>":()V
Method	scala/actors/threadpool/helpers/WaitQueue$WaitNode.doWait:(Lscala/actors/threadpool/helpers/WaitQueue$QueuedSync;)V
Method	scala/actors/threadpool/helpers/WaitQueue$WaitNode.doTimedWait:(Lscala/actors/threadpool/helpers/WaitQueue$QueuedSync;J)Z
class	java/lang/IllegalMonitorStateException
String	Not owner
Method	java/lang/IllegalMonitorStateException."<init>":(Ljava/lang/String;)V
Method	scala/actors/threadpool/helpers/WaitQueue.extract:()Lscala/actors/threadpool/helpers/WaitQueue$WaitNode;
Method	scala/actors/threadpool/locks/ReentrantLock$FairSync.getSignallee:(Ljava/lang/Thread;)Lscala/actors/threadpool/helpers/WaitQueue$WaitNode;
Method	scala/actors/threadpool/helpers/WaitQueue$WaitNode.signal:(Lscala/actors/threadpool/helpers/WaitQueue$QueuedSync;)Z
Method	scala/actors/threadpool/helpers/WaitQueue.hasNodes:()Z
Method	scala/actors/threadpool/helpers/WaitQueue.getLength:()I
Method	scala/actors/threadpool/helpers/WaitQueue.getWaitingThreads:()Ljava/util/Collection;
Method	scala/actors/threadpool/helpers/WaitQueue.isWaiting:(Ljava/lang/Thread;)Z
Method	java/io/ObjectInputStream.defaultReadObject:()V
class	scala/actors/threadpool/locks/ReentrantLock$FairSync
class	scala/actors/threadpool/locks/ReentrantLock$Sync
class	scala/actors/threadpool/helpers/WaitQueue$QueuedSync
Asciz	serialVersionUID;
Asciz	J;
Asciz	ConstantValue;
long	-3000897897090466540l;
Asciz	wq_;
Asciz	Lscala/actors/threadpool/helpers/WaitQueue;;
Asciz	<init>;
Asciz	()V;
Asciz	Code;
Asciz	recheck;
Asciz	WaitNode;
Asciz	InnerClasses;
Asciz	(Lscala/actors/threadpool/helpers/WaitQueue$WaitNode;)Z;
Asciz	takeOver;
Asciz	(Lscala/actors/threadpool/helpers/WaitQueue$WaitNode;)V;
Asciz	lock;
Asciz	lockInterruptibly;
Asciz	Exceptions;
Asciz	tryLock;
Asciz	(J)Z;
Asciz	getSignallee;
Asciz	(Ljava/lang/Thread;)Lscala/actors/threadpool/helpers/WaitQueue$WaitNode;;
Asciz	unlock;
Asciz	isFair;
Asciz	()Z;
Asciz	hasQueuedThreads;
Asciz	getQueueLength;
Asciz	()I;
Asciz	getQueuedThreads;
Asciz	()Ljava/util/Collection;;
Asciz	isQueued;
Asciz	(Ljava/lang/Thread;)Z;
Asciz	readObject;
Asciz	(Ljava/io/ObjectInputStream;)V;
class	java/io/IOException
class	java/lang/ClassNotFoundException
NameAndType	"<init>":()V
Asciz	scala/actors/threadpool/helpers/FIFOWaitQueue;
NameAndType	wq_:Lscala/actors/threadpool/helpers/WaitQueue;
class	java/lang/Thread
NameAndType	currentThread:()Ljava/lang/Thread;
NameAndType	owner_:Ljava/lang/Thread;
NameAndType	holds_:I
NameAndType	incHolds:()V
class	scala/actors/threadpool/helpers/WaitQueue
NameAndType	insert:(Lscala/actors/threadpool/helpers/WaitQueue$WaitNode;)V
NameAndType	getOwner:()Ljava/lang/Thread;
Asciz	scala/actors/threadpool/helpers/WaitQueue$WaitNode;
NameAndType	doWaitUninterruptibly:(Lscala/actors/threadpool/helpers/WaitQueue$QueuedSync;)V
NameAndType	interrupted:()Z
Asciz	java/lang/InterruptedException;
NameAndType	doWait:(Lscala/actors/threadpool/helpers/WaitQueue$QueuedSync;)V
NameAndType	doTimedWait:(Lscala/actors/threadpool/helpers/WaitQueue$QueuedSync;J)Z
Asciz	java/lang/IllegalMonitorStateException;
Asciz	Not owner;
NameAndType	"<init>":(Ljava/lang/String;)V
NameAndType	extract:()Lscala/actors/threadpool/helpers/WaitQueue$WaitNode;
NameAndType	getSignallee:(Ljava/lang/Thread;)Lscala/actors/threadpool/helpers/WaitQueue$WaitNode;
NameAndType	signal:(Lscala/actors/threadpool/helpers/WaitQueue$QueuedSync;)Z
NameAndType	hasNodes:()Z
NameAndType	getLength:()I
NameAndType	getWaitingThreads:()Ljava/util/Collection;
NameAndType	isWaiting:(Ljava/lang/Thread;)Z
class	java/io/ObjectInputStream
NameAndType	defaultReadObject:()V
class	scala/actors/threadpool/locks/ReentrantLock
Asciz	scala/actors/threadpool/locks/ReentrantLock$FairSync;
Asciz	FairSync;
Asciz	scala/actors/threadpool/locks/ReentrantLock$Sync;
Asciz	Sync;
Asciz	scala/actors/threadpool/helpers/WaitQueue$QueuedSync;
Asciz	QueuedSync;
Asciz	java/io/IOException;
Asciz	java/lang/ClassNotFoundException;
Asciz	java/lang/Thread;
Asciz	currentThread;
Asciz	()Ljava/lang/Thread;;
Asciz	owner_;
Asciz	Ljava/lang/Thread;;
Asciz	holds_;
Asciz	I;
Asciz	incHolds;
Asciz	scala/actors/threadpool/helpers/WaitQueue;
Asciz	insert;
Asciz	getOwner;
Asciz	doWaitUninterruptibly;
Asciz	(Lscala/actors/threadpool/helpers/WaitQueue$QueuedSync;)V;
Asciz	interrupted;
Asciz	doWait;
Asciz	doTimedWait;
Asciz	(Lscala/actors/threadpool/helpers/WaitQueue$QueuedSync;J)Z;
Asciz	(Ljava/lang/String;)V;
Asciz	extract;
Asciz	()Lscala/actors/threadpool/helpers/WaitQueue$WaitNode;;
Asciz	signal;
Asciz	(Lscala/actors/threadpool/helpers/WaitQueue$QueuedSync;)Z;
Asciz	hasNodes;
Asciz	getLength;
Asciz	getWaitingThreads;
Asciz	isWaiting;
Asciz	java/io/ObjectInputStream;
Asciz	defaultReadObject;
Asciz	scala/actors/threadpool/locks/ReentrantLock;

{
private static final long serialVersionUID;
  Signature: J
  Constant value: long -3000897897090466540l
private transient scala.actors.threadpool.helpers.WaitQueue wq_;
  Signature: Lscala/actors/threadpool/helpers/WaitQueue;

scala.actors.threadpool.locks.ReentrantLock$FairSync();
  Signature: ()V
  Code:
   Stack=3, Locals=1, Args_size=1
	aload_0
	invokespecial	Method scala/actors/threadpool/locks/ReentrantLock$Sync."<init>":()V
	aload_0
	new	class scala/actors/threadpool/helpers/FIFOWaitQueue
	dup
	invokespecial	Method scala/actors/threadpool/helpers/FIFOWaitQueue."<init>":()V
	putfield	Field wq_:Lscala/actors/threadpool/helpers/WaitQueue;
	return
  Labels:

public synchronized boolean recheck(scala.actors.threadpool.helpers.WaitQueue$WaitNode);
  Signature: (Lscala/actors/threadpool/helpers/WaitQueue$WaitNode;)Z
  Code:
   Stack=2, Locals=3, Args_size=2
	invokestatic	Method java/lang/Thread.currentThread:()Ljava/lang/Thread;
	astore_2
	aload_0
	getfield	Field owner_:Ljava/lang/Thread;
	ifnonnull	l1 // aload_2
	aload_0
	aload_2
	putfield	Field owner_:Ljava/lang/Thread;
	aload_0
	iconst_1
	putfield	Field holds_:I
	iconst_1
	ireturn
l1	aload_2
	aload_0
	getfield	Field owner_:Ljava/lang/Thread;
	if_acmpne	l2 // aload_0
	aload_0
	invokevirtual	Method incHolds:()V
	iconst_1
	ireturn
l2	aload_0
	getfield	Field wq_:Lscala/actors/threadpool/helpers/WaitQueue;
	aload_1
	invokevirtual	Method scala/actors/threadpool/helpers/WaitQueue.insert:(Lscala/actors/threadpool/helpers/WaitQueue$WaitNode;)V
	iconst_0
	ireturn
  Labels:
   	l1 = 23 // aload_2
   	l2 = 37 // aload_0

public synchronized void takeOver(scala.actors.threadpool.helpers.WaitQueue$WaitNode);
  Signature: (Lscala/actors/threadpool/helpers/WaitQueue$WaitNode;)V
  Code:
   Stack=2, Locals=2, Args_size=2
	aload_0
	aload_1
	invokevirtual	Method scala/actors/threadpool/helpers/WaitQueue$WaitNode.getOwner:()Ljava/lang/Thread;
	putfield	Field owner_:Ljava/lang/Thread;
	return
  Labels:

public void lock();
  Signature: ()V
  Code:
   Stack=2, Locals=4, Args_size=1
	invokestatic	Method java/lang/Thread.currentThread:()Ljava/lang/Thread;
	astore_1
	aload_0
	dup
	astore_2
	monitorenter
	aload_0
	getfield	Field owner_:Ljava/lang/Thread;
	ifnonnull	l1 // aload_1
	aload_0
	aload_1
	putfield	Field owner_:Ljava/lang/Thread;
	aload_0
	iconst_1
	putfield	Field holds_:I
	aload_2
	monitorexit
	return
l1	aload_1
	aload_0
	getfield	Field owner_:Ljava/lang/Thread;
	if_acmpne	l2 // aload_2
	aload_0
	invokevirtual	Method incHolds:()V
	aload_2
	monitorexit
	return
l2	aload_2
	monitorexit
	goto	l3 // new
	astore_3
	aload_2
	monitorexit
	aload_3
	athrow
l3	new	class scala/actors/threadpool/helpers/WaitQueue$WaitNode
	dup
	invokespecial	Method scala/actors/threadpool/helpers/WaitQueue$WaitNode."<init>":()V
	astore_2
	aload_2
	aload_0
	invokevirtual	Method scala/actors/threadpool/helpers/WaitQueue$WaitNode.doWaitUninterruptibly:(Lscala/actors/threadpool/helpers/WaitQueue$QueuedSync;)V
	return
  Labels:
   	l1 = 28 // aload_1
   	l2 = 43 // aload_2
   	l3 = 53 // new
  Exception table:
   from   to  target type
     8    27    48   any
    28    42    48   any
    43    45    48   any
    48    51    48   any

public void lockInterruptibly()   throws java.lang.InterruptedException;
  Signature: ()V
  Code:
   Stack=2, Locals=4, Args_size=1
	invokestatic	Method java/lang/Thread.interrupted:()Z
	ifeq	l1 // invokestatic
	new	class java/lang/InterruptedException
	dup
	invokespecial	Method java/lang/InterruptedException."<init>":()V
	athrow
l1	invokestatic	Method java/lang/Thread.currentThread:()Ljava/lang/Thread;
	astore_1
	aload_0
	dup
	astore_2
	monitorenter
	aload_0
	getfield	Field owner_:Ljava/lang/Thread;
	ifnonnull	l2 // aload_1
	aload_0
	aload_1
	putfield	Field owner_:Ljava/lang/Thread;
	aload_0
	iconst_1
	putfield	Field holds_:I
	aload_2
	monitorexit
	return
l2	aload_1
	aload_0
	getfield	Field owner_:Ljava/lang/Thread;
	if_acmpne	l3 // aload_2
	aload_0
	invokevirtual	Method incHolds:()V
	aload_2
	monitorexit
	return
l3	aload_2
	monitorexit
	goto	l4 // new
	astore_3
	aload_2
	monitorexit
	aload_3
	athrow
l4	new	class scala/actors/threadpool/helpers/WaitQueue$WaitNode
	dup
	invokespecial	Method scala/actors/threadpool/helpers/WaitQueue$WaitNode."<init>":()V
	astore_2
	aload_2
	aload_0
	invokevirtual	Method scala/actors/threadpool/helpers/WaitQueue$WaitNode.doWait:(Lscala/actors/threadpool/helpers/WaitQueue$QueuedSync;)V
	return
  Labels:
   	l1 = 14 // invokestatic
   	l2 = 42 // aload_1
   	l3 = 57 // aload_2
   	l4 = 67 // new
  Exception table:
   from   to  target type
    22    41    62   any
    42    56    62   any
    57    59    62   any
    62    65    62   any
  Exceptions: 
   throws java.lang.InterruptedException
public boolean tryLock(long)   throws java.lang.InterruptedException;
  Signature: (J)Z
  Code:
   Stack=4, Locals=6, Args_size=2
	invokestatic	Method java/lang/Thread.interrupted:()Z
	ifeq	l1 // invokestatic
	new	class java/lang/InterruptedException
	dup
	invokespecial	Method java/lang/InterruptedException."<init>":()V
	athrow
l1	invokestatic	Method java/lang/Thread.currentThread:()Ljava/lang/Thread;
	astore_3
	aload_0
	dup
	astore	4
	monitorenter
	aload_0
	getfield	Field owner_:Ljava/lang/Thread;
	ifnonnull	l2 // aload_3
	aload_0
	aload_3
	putfield	Field owner_:Ljava/lang/Thread;
	aload_0
	iconst_1
	putfield	Field holds_:I
	iconst_1
	aload	4
	monitorexit
	ireturn
l2	aload_3
	aload_0
	getfield	Field owner_:Ljava/lang/Thread;
	if_acmpne	l3 // aload
	aload_0
	invokevirtual	Method incHolds:()V
	iconst_1
	aload	4
	monitorexit
	ireturn
l3	aload	4
	monitorexit
	goto	l4 // new
	astore	5
	aload	4
	monitorexit
	aload	5
	athrow
l4	new	class scala/actors/threadpool/helpers/WaitQueue$WaitNode
	dup
	invokespecial	Method scala/actors/threadpool/helpers/WaitQueue$WaitNode."<init>":()V
	astore	4
	aload	4
	aload_0
	lload_1
	invokevirtual	Method scala/actors/threadpool/helpers/WaitQueue$WaitNode.doTimedWait:(Lscala/actors/threadpool/helpers/WaitQueue$QueuedSync;J)Z
	ireturn
  Labels:
   	l1 = 14 // invokestatic
   	l2 = 45 // aload_3
   	l3 = 62 // aload
   	l4 = 76 // new
  Exception table:
   from   to  target type
    23    44    68   any
    45    61    68   any
    62    65    68   any
    68    73    68   any
  Exceptions: 
   throws java.lang.InterruptedException
protected synchronized scala.actors.threadpool.helpers.WaitQueue$WaitNode getSignallee(java.lang.Thread);
  Signature: (Ljava/lang/Thread;)Lscala/actors/threadpool/helpers/WaitQueue$WaitNode;
  Code:
   Stack=3, Locals=3, Args_size=2
	aload_1
	aload_0
	getfield	Field owner_:Ljava/lang/Thread;
	if_acmpeq	l1 // aload_0
	new	class java/lang/IllegalMonitorStateException
	dup
	ldc	String Not owner
	invokespecial	Method java/lang/IllegalMonitorStateException."<init>":(Ljava/lang/String;)V
	athrow
l1	aload_0
	getfield	Field holds_:I
	iconst_2
	if_icmplt	l2 // aload_0
	aload_0
	dup
	getfield	Field holds_:I
	iconst_1
	isub
	putfield	Field holds_:I
	aconst_null
	areturn
l2	aload_0
	getfield	Field wq_:Lscala/actors/threadpool/helpers/WaitQueue;
	invokevirtual	Method scala/actors/threadpool/helpers/WaitQueue.extract:()Lscala/actors/threadpool/helpers/WaitQueue$WaitNode;
	astore_2
	aload_2
	ifnonnull	l3 // aload_2
	aload_0
	aconst_null
	putfield	Field owner_:Ljava/lang/Thread;
	aload_0
	iconst_0
	putfield	Field holds_:I
l3	aload_2
	areturn
  Labels:
   	l1 = 18 // aload_0
   	l2 = 38 // aload_0
   	l3 = 60 // aload_2

public void unlock();
  Signature: ()V
  Code:
   Stack=2, Locals=3, Args_size=1
	invokestatic	Method java/lang/Thread.currentThread:()Ljava/lang/Thread;
	astore_1
l3	aload_0
	aload_1
	invokevirtual	Method getSignallee:(Ljava/lang/Thread;)Lscala/actors/threadpool/helpers/WaitQueue$WaitNode;
	astore_2
	aload_2
	ifnonnull	l1 // aload_2
	return
l1	aload_2
	aload_0
	invokevirtual	Method scala/actors/threadpool/helpers/WaitQueue$WaitNode.signal:(Lscala/actors/threadpool/helpers/WaitQueue$QueuedSync;)Z
	ifeq	l2 // goto
	return
l2	goto	l3 // aload_0
  Labels:
   	l3 = 4 // aload_0
   	l1 = 15 // aload_2
   	l2 = 24 // goto

public final boolean isFair();
  Signature: ()Z
  Code:
   Stack=1, Locals=1, Args_size=1
	iconst_1
	ireturn
  Labels:

public synchronized boolean hasQueuedThreads();
  Signature: ()Z
  Code:
   Stack=1, Locals=1, Args_size=1
	aload_0
	getfield	Field wq_:Lscala/actors/threadpool/helpers/WaitQueue;
	invokevirtual	Method scala/actors/threadpool/helpers/WaitQueue.hasNodes:()Z
	ireturn
  Labels:

public synchronized int getQueueLength();
  Signature: ()I
  Code:
   Stack=1, Locals=1, Args_size=1
	aload_0
	getfield	Field wq_:Lscala/actors/threadpool/helpers/WaitQueue;
	invokevirtual	Method scala/actors/threadpool/helpers/WaitQueue.getLength:()I
	ireturn
  Labels:

public synchronized java.util.Collection getQueuedThreads();
  Signature: ()Ljava/util/Collection;
  Code:
   Stack=1, Locals=1, Args_size=1
	aload_0
	getfield	Field wq_:Lscala/actors/threadpool/helpers/WaitQueue;
	invokevirtual	Method scala/actors/threadpool/helpers/WaitQueue.getWaitingThreads:()Ljava/util/Collection;
	areturn
  Labels:

public synchronized boolean isQueued(java.lang.Thread);
  Signature: (Ljava/lang/Thread;)Z
  Code:
   Stack=2, Locals=2, Args_size=2
	aload_0
	getfield	Field wq_:Lscala/actors/threadpool/helpers/WaitQueue;
	aload_1
	invokevirtual	Method scala/actors/threadpool/helpers/WaitQueue.isWaiting:(Ljava/lang/Thread;)Z
	ireturn
  Labels:

private void readObject(java.io.ObjectInputStream)   throws java.io.IOException, java.lang.ClassNotFoundException;
  Signature: (Ljava/io/ObjectInputStream;)V
  Code:
   Stack=3, Locals=4, Args_size=2
	aload_1
	invokevirtual	Method java/io/ObjectInputStream.defaultReadObject:()V
	aload_0
	dup
	astore_2
	monitorenter
	aload_0
	new	class scala/actors/threadpool/helpers/FIFOWaitQueue
	dup
	invokespecial	Method scala/actors/threadpool/helpers/FIFOWaitQueue."<init>":()V
	putfield	Field wq_:Lscala/actors/threadpool/helpers/WaitQueue;
	aload_2
	monitorexit
	goto	l1 // return
	astore_3
	aload_2
	monitorexit
	aload_3
	athrow
l1	return
  Labels:
   	l1 = 29 // return
  Exception table:
   from   to  target type
     8    21    24   any
    24    27    24   any
  Exceptions: 
   throws java.io.IOException, java.lang.ClassNotFoundException
}

