public class scala.actors.threadpool.locks.ReentrantLock extends java.lang.Object implements scala.actors.threadpool.locks.Lock,java.io.Serializable,scala.actors.threadpool.locks.CondVar$ExclusiveLock
  InnerClass: 
   final #52= #5 of #47; //FairSync=class scala/actors/threadpool/locks/ReentrantLock$FairSync of class scala/actors/threadpool/locks/ReentrantLock
   final #54= #2 of #47; //NonfairSync=class scala/actors/threadpool/locks/ReentrantLock$NonfairSync of class scala/actors/threadpool/locks/ReentrantLock
   abstract #56= #55 of #47; //Sync=class scala/actors/threadpool/locks/ReentrantLock$Sync of class scala/actors/threadpool/locks/ReentrantLock
   abstract #146= #51 of #16; //ExclusiveLock=class scala/actors/threadpool/locks/CondVar$ExclusiveLock of class scala/actors/threadpool/locks/CondVar
  minor version: 0
  major version: 49
  Constant pool:
const #1 = Method	#48.#101;	//  java/lang/Object."<init>":()V
const #2 = class	#102;	//  scala/actors/threadpool/locks/ReentrantLock$NonfairSync
const #3 = Method	#2.#101;	//  scala/actors/threadpool/locks/ReentrantLock$NonfairSync."<init>":()V
const #4 = Field	#47.#103;	//  scala/actors/threadpool/locks/ReentrantLock.sync:Lscala/actors/threadpool/locks/ReentrantLock$Sync;
const #5 = class	#104;	//  scala/actors/threadpool/locks/ReentrantLock$FairSync
const #6 = Method	#5.#101;	//  scala/actors/threadpool/locks/ReentrantLock$FairSync."<init>":()V
const #7 = Method	#55.#105;	//  scala/actors/threadpool/locks/ReentrantLock$Sync.lock:()V
const #8 = Method	#55.#106;	//  scala/actors/threadpool/locks/ReentrantLock$Sync.lockInterruptibly:()V
const #9 = Method	#55.#107;	//  scala/actors/threadpool/locks/ReentrantLock$Sync.tryLock:()Z
const #10 = Method	#108.#109;	//  scala/actors/threadpool/TimeUnit.toNanos:(J)J
const #11 = Method	#55.#110;	//  scala/actors/threadpool/locks/ReentrantLock$Sync.tryLock:(J)Z
const #12 = Method	#55.#111;	//  scala/actors/threadpool/locks/ReentrantLock$Sync.unlock:()V
const #13 = Method	#47.#112;	//  scala/actors/threadpool/locks/ReentrantLock.isFair:()Z
const #14 = class	#113;	//  scala/actors/threadpool/locks/FIFOCondVar
const #15 = Method	#14.#114;	//  scala/actors/threadpool/locks/FIFOCondVar."<init>":(Lscala/actors/threadpool/locks/CondVar$ExclusiveLock;)V
const #16 = class	#115;	//  scala/actors/threadpool/locks/CondVar
const #17 = Method	#16.#114;	//  scala/actors/threadpool/locks/CondVar."<init>":(Lscala/actors/threadpool/locks/CondVar$ExclusiveLock;)V
const #18 = Method	#55.#116;	//  scala/actors/threadpool/locks/ReentrantLock$Sync.getHoldCount:()I
const #19 = Method	#55.#117;	//  scala/actors/threadpool/locks/ReentrantLock$Sync.isHeldByCurrentThread:()Z
const #20 = Method	#55.#118;	//  scala/actors/threadpool/locks/ReentrantLock$Sync.isLocked:()Z
const #21 = Method	#55.#112;	//  scala/actors/threadpool/locks/ReentrantLock$Sync.isFair:()Z
const #22 = Method	#55.#119;	//  scala/actors/threadpool/locks/ReentrantLock$Sync.getOwner:()Ljava/lang/Thread;
const #23 = Method	#55.#120;	//  scala/actors/threadpool/locks/ReentrantLock$Sync.hasQueuedThreads:()Z
const #24 = Method	#55.#121;	//  scala/actors/threadpool/locks/ReentrantLock$Sync.isQueued:(Ljava/lang/Thread;)Z
const #25 = Method	#55.#122;	//  scala/actors/threadpool/locks/ReentrantLock$Sync.getQueueLength:()I
const #26 = Method	#55.#123;	//  scala/actors/threadpool/locks/ReentrantLock$Sync.getQueuedThreads:()Ljava/util/Collection;
const #27 = Method	#47.#124;	//  scala/actors/threadpool/locks/ReentrantLock.asCondVar:(Lscala/actors/threadpool/locks/Condition;)Lscala/actors/threadpool/locks/CondVar;
const #28 = Method	#16.#125;	//  scala/actors/threadpool/locks/CondVar.hasWaiters:()Z
const #29 = Method	#16.#126;	//  scala/actors/threadpool/locks/CondVar.getWaitQueueLength:()I
const #30 = Method	#16.#127;	//  scala/actors/threadpool/locks/CondVar.getWaitingThreads:()Ljava/util/Collection;
const #31 = Method	#47.#119;	//  scala/actors/threadpool/locks/ReentrantLock.getOwner:()Ljava/lang/Thread;
const #32 = class	#128;	//  java/lang/StringBuilder
const #33 = Method	#32.#101;	//  java/lang/StringBuilder."<init>":()V
const #34 = Method	#48.#129;	//  java/lang/Object.toString:()Ljava/lang/String;
const #35 = Method	#32.#130;	//  java/lang/StringBuilder.append:(Ljava/lang/String;)Ljava/lang/StringBuilder;
const #36 = String	#131;	//  [Unlocked]
const #37 = String	#132;	//  [Locked by thread 
const #38 = Method	#133.#134;	//  java/lang/Thread.getName:()Ljava/lang/String;
const #39 = String	#135;	//  ]
const #40 = Method	#32.#129;	//  java/lang/StringBuilder.toString:()Ljava/lang/String;
const #41 = class	#136;	//  java/lang/NullPointerException
const #42 = Method	#41.#101;	//  java/lang/NullPointerException."<init>":()V
const #43 = class	#137;	//  java/lang/IllegalArgumentException
const #44 = String	#138;	//  not owner
const #45 = Method	#43.#139;	//  java/lang/IllegalArgumentException."<init>":(Ljava/lang/String;)V
const #46 = Field	#16.#140;	//  scala/actors/threadpool/locks/CondVar.lock:Lscala/actors/threadpool/locks/CondVar$ExclusiveLock;
const #47 = class	#141;	//  scala/actors/threadpool/locks/ReentrantLock
const #48 = class	#142;	//  java/lang/Object
const #49 = class	#143;	//  scala/actors/threadpool/locks/Lock
const #50 = class	#144;	//  java/io/Serializable
const #51 = class	#145;	//  scala/actors/threadpool/locks/CondVar$ExclusiveLock
const #52 = Asciz	FairSync;
const #53 = Asciz	InnerClasses;
const #54 = Asciz	NonfairSync;
const #55 = class	#147;	//  scala/actors/threadpool/locks/ReentrantLock$Sync
const #56 = Asciz	Sync;
const #57 = Asciz	serialVersionUID;
const #58 = Asciz	J;
const #59 = Asciz	ConstantValue;
const #60 = long	7373984872572414699l;
const #62 = Asciz	sync;
const #63 = Asciz	Lscala/actors/threadpool/locks/ReentrantLock$Sync;;
const #64 = Asciz	<init>;
const #65 = Asciz	()V;
const #66 = Asciz	Code;
const #67 = Asciz	(Z)V;
const #68 = Asciz	lock;
const #69 = Asciz	lockInterruptibly;
const #70 = Asciz	Exceptions;
const #71 = class	#148;	//  java/lang/InterruptedException
const #72 = Asciz	tryLock;
const #73 = Asciz	()Z;
const #74 = Asciz	(JLscala/actors/threadpool/TimeUnit;)Z;
const #75 = Asciz	unlock;
const #76 = Asciz	newCondition;
const #77 = Asciz	()Lscala/actors/threadpool/locks/Condition;;
const #78 = Asciz	getHoldCount;
const #79 = Asciz	()I;
const #80 = Asciz	isHeldByCurrentThread;
const #81 = Asciz	isLocked;
const #82 = Asciz	isFair;
const #83 = Asciz	getOwner;
const #84 = Asciz	()Ljava/lang/Thread;;
const #85 = Asciz	hasQueuedThreads;
const #86 = Asciz	hasQueuedThread;
const #87 = Asciz	(Ljava/lang/Thread;)Z;
const #88 = Asciz	getQueueLength;
const #89 = Asciz	getQueuedThreads;
const #90 = Asciz	()Ljava/util/Collection;;
const #91 = Asciz	hasWaiters;
const #92 = Asciz	(Lscala/actors/threadpool/locks/Condition;)Z;
const #93 = Asciz	getWaitQueueLength;
const #94 = Asciz	(Lscala/actors/threadpool/locks/Condition;)I;
const #95 = Asciz	getWaitingThreads;
const #96 = Asciz	(Lscala/actors/threadpool/locks/Condition;)Ljava/util/Collection;;
const #97 = Asciz	toString;
const #98 = Asciz	()Ljava/lang/String;;
const #99 = Asciz	asCondVar;
const #100 = Asciz	(Lscala/actors/threadpool/locks/Condition;)Lscala/actors/threadpool/locks/CondVar;;
const #101 = NameAndType	#64:#65;//  "<init>":()V
const #102 = Asciz	scala/actors/threadpool/locks/ReentrantLock$NonfairSync;
const #103 = NameAndType	#62:#63;//  sync:Lscala/actors/threadpool/locks/ReentrantLock$Sync;
const #104 = Asciz	scala/actors/threadpool/locks/ReentrantLock$FairSync;
const #105 = NameAndType	#68:#65;//  lock:()V
const #106 = NameAndType	#69:#65;//  lockInterruptibly:()V
const #107 = NameAndType	#72:#73;//  tryLock:()Z
const #108 = class	#149;	//  scala/actors/threadpool/TimeUnit
const #109 = NameAndType	#150:#151;//  toNanos:(J)J
const #110 = NameAndType	#72:#152;//  tryLock:(J)Z
const #111 = NameAndType	#75:#65;//  unlock:()V
const #112 = NameAndType	#82:#73;//  isFair:()Z
const #113 = Asciz	scala/actors/threadpool/locks/FIFOCondVar;
const #114 = NameAndType	#64:#153;//  "<init>":(Lscala/actors/threadpool/locks/CondVar$ExclusiveLock;)V
const #115 = Asciz	scala/actors/threadpool/locks/CondVar;
const #116 = NameAndType	#78:#79;//  getHoldCount:()I
const #117 = NameAndType	#80:#73;//  isHeldByCurrentThread:()Z
const #118 = NameAndType	#81:#73;//  isLocked:()Z
const #119 = NameAndType	#83:#84;//  getOwner:()Ljava/lang/Thread;
const #120 = NameAndType	#85:#73;//  hasQueuedThreads:()Z
const #121 = NameAndType	#154:#87;//  isQueued:(Ljava/lang/Thread;)Z
const #122 = NameAndType	#88:#79;//  getQueueLength:()I
const #123 = NameAndType	#89:#90;//  getQueuedThreads:()Ljava/util/Collection;
const #124 = NameAndType	#99:#100;//  asCondVar:(Lscala/actors/threadpool/locks/Condition;)Lscala/actors/threadpool/locks/CondVar;
const #125 = NameAndType	#91:#73;//  hasWaiters:()Z
const #126 = NameAndType	#93:#79;//  getWaitQueueLength:()I
const #127 = NameAndType	#95:#90;//  getWaitingThreads:()Ljava/util/Collection;
const #128 = Asciz	java/lang/StringBuilder;
const #129 = NameAndType	#97:#98;//  toString:()Ljava/lang/String;
const #130 = NameAndType	#155:#156;//  append:(Ljava/lang/String;)Ljava/lang/StringBuilder;
const #131 = Asciz	[Unlocked];
const #132 = Asciz	[Locked by thread ;
const #133 = class	#157;	//  java/lang/Thread
const #134 = NameAndType	#158:#98;//  getName:()Ljava/lang/String;
const #135 = Asciz	];
const #136 = Asciz	java/lang/NullPointerException;
const #137 = Asciz	java/lang/IllegalArgumentException;
const #138 = Asciz	not owner;
const #139 = NameAndType	#64:#159;//  "<init>":(Ljava/lang/String;)V
const #140 = NameAndType	#68:#160;//  lock:Lscala/actors/threadpool/locks/CondVar$ExclusiveLock;
const #141 = Asciz	scala/actors/threadpool/locks/ReentrantLock;
const #142 = Asciz	java/lang/Object;
const #143 = Asciz	scala/actors/threadpool/locks/Lock;
const #144 = Asciz	java/io/Serializable;
const #145 = Asciz	scala/actors/threadpool/locks/CondVar$ExclusiveLock;
const #146 = Asciz	ExclusiveLock;
const #147 = Asciz	scala/actors/threadpool/locks/ReentrantLock$Sync;
const #148 = Asciz	java/lang/InterruptedException;
const #149 = Asciz	scala/actors/threadpool/TimeUnit;
const #150 = Asciz	toNanos;
const #151 = Asciz	(J)J;
const #152 = Asciz	(J)Z;
const #153 = Asciz	(Lscala/actors/threadpool/locks/CondVar$ExclusiveLock;)V;
const #154 = Asciz	isQueued;
const #155 = Asciz	append;
const #156 = Asciz	(Ljava/lang/String;)Ljava/lang/StringBuilder;;
const #157 = Asciz	java/lang/Thread;
const #158 = Asciz	getName;
const #159 = Asciz	(Ljava/lang/String;)V;
const #160 = Asciz	Lscala/actors/threadpool/locks/CondVar$ExclusiveLock;;

{
public scala.actors.threadpool.locks.ReentrantLock();
  Code:
   Stack=3, Locals=1, Args_size=1
   0:	aload_0
   1:	invokespecial	#1; //Method java/lang/Object."<init>":()V
   4:	aload_0
   5:	new	#2; //class scala/actors/threadpool/locks/ReentrantLock$NonfairSync
   8:	dup
   9:	invokespecial	#3; //Method scala/actors/threadpool/locks/ReentrantLock$NonfairSync."<init>":()V
   12:	putfield	#4; //Field sync:Lscala/actors/threadpool/locks/ReentrantLock$Sync;
   15:	return

public scala.actors.threadpool.locks.ReentrantLock(boolean);
  Code:
   Stack=3, Locals=2, Args_size=2
   0:	aload_0
   1:	invokespecial	#1; //Method java/lang/Object."<init>":()V
   4:	aload_0
   5:	iload_1
   6:	ifeq	19
   9:	new	#5; //class scala/actors/threadpool/locks/ReentrantLock$FairSync
   12:	dup
   13:	invokespecial	#6; //Method scala/actors/threadpool/locks/ReentrantLock$FairSync."<init>":()V
   16:	goto	26
   19:	new	#2; //class scala/actors/threadpool/locks/ReentrantLock$NonfairSync
   22:	dup
   23:	invokespecial	#3; //Method scala/actors/threadpool/locks/ReentrantLock$NonfairSync."<init>":()V
   26:	putfield	#4; //Field sync:Lscala/actors/threadpool/locks/ReentrantLock$Sync;
   29:	return

public void lock();
  Code:
   Stack=1, Locals=1, Args_size=1
   0:	aload_0
   1:	getfield	#4; //Field sync:Lscala/actors/threadpool/locks/ReentrantLock$Sync;
   4:	invokevirtual	#7; //Method scala/actors/threadpool/locks/ReentrantLock$Sync.lock:()V
   7:	return

public void lockInterruptibly()   throws java.lang.InterruptedException;
  Code:
   Stack=1, Locals=1, Args_size=1
   0:	aload_0
   1:	getfield	#4; //Field sync:Lscala/actors/threadpool/locks/ReentrantLock$Sync;
   4:	invokevirtual	#8; //Method scala/actors/threadpool/locks/ReentrantLock$Sync.lockInterruptibly:()V
   7:	return
  Exceptions: 
   throws java.lang.InterruptedException
public boolean tryLock();
  Code:
   Stack=1, Locals=1, Args_size=1
   0:	aload_0
   1:	getfield	#4; //Field sync:Lscala/actors/threadpool/locks/ReentrantLock$Sync;
   4:	invokevirtual	#9; //Method scala/actors/threadpool/locks/ReentrantLock$Sync.tryLock:()Z
   7:	ireturn

public boolean tryLock(long, scala.actors.threadpool.TimeUnit)   throws java.lang.InterruptedException;
  Code:
   Stack=4, Locals=4, Args_size=3
   0:	aload_0
   1:	getfield	#4; //Field sync:Lscala/actors/threadpool/locks/ReentrantLock$Sync;
   4:	aload_3
   5:	lload_1
   6:	invokevirtual	#10; //Method scala/actors/threadpool/TimeUnit.toNanos:(J)J
   9:	invokevirtual	#11; //Method scala/actors/threadpool/locks/ReentrantLock$Sync.tryLock:(J)Z
   12:	ireturn
  Exceptions: 
   throws java.lang.InterruptedException
public void unlock();
  Code:
   Stack=1, Locals=1, Args_size=1
   0:	aload_0
   1:	getfield	#4; //Field sync:Lscala/actors/threadpool/locks/ReentrantLock$Sync;
   4:	invokevirtual	#12; //Method scala/actors/threadpool/locks/ReentrantLock$Sync.unlock:()V
   7:	return

public scala.actors.threadpool.locks.Condition newCondition();
  Code:
   Stack=3, Locals=1, Args_size=1
   0:	aload_0
   1:	invokevirtual	#13; //Method isFair:()Z
   4:	ifeq	18
   7:	new	#14; //class scala/actors/threadpool/locks/FIFOCondVar
   10:	dup
   11:	aload_0
   12:	invokespecial	#15; //Method scala/actors/threadpool/locks/FIFOCondVar."<init>":(Lscala/actors/threadpool/locks/CondVar$ExclusiveLock;)V
   15:	goto	26
   18:	new	#16; //class scala/actors/threadpool/locks/CondVar
   21:	dup
   22:	aload_0
   23:	invokespecial	#17; //Method scala/actors/threadpool/locks/CondVar."<init>":(Lscala/actors/threadpool/locks/CondVar$ExclusiveLock;)V
   26:	areturn

public int getHoldCount();
  Code:
   Stack=1, Locals=1, Args_size=1
   0:	aload_0
   1:	getfield	#4; //Field sync:Lscala/actors/threadpool/locks/ReentrantLock$Sync;
   4:	invokevirtual	#18; //Method scala/actors/threadpool/locks/ReentrantLock$Sync.getHoldCount:()I
   7:	ireturn

public boolean isHeldByCurrentThread();
  Code:
   Stack=1, Locals=1, Args_size=1
   0:	aload_0
   1:	getfield	#4; //Field sync:Lscala/actors/threadpool/locks/ReentrantLock$Sync;
   4:	invokevirtual	#19; //Method scala/actors/threadpool/locks/ReentrantLock$Sync.isHeldByCurrentThread:()Z
   7:	ireturn

public boolean isLocked();
  Code:
   Stack=1, Locals=1, Args_size=1
   0:	aload_0
   1:	getfield	#4; //Field sync:Lscala/actors/threadpool/locks/ReentrantLock$Sync;
   4:	invokevirtual	#20; //Method scala/actors/threadpool/locks/ReentrantLock$Sync.isLocked:()Z
   7:	ireturn

public final boolean isFair();
  Code:
   Stack=1, Locals=1, Args_size=1
   0:	aload_0
   1:	getfield	#4; //Field sync:Lscala/actors/threadpool/locks/ReentrantLock$Sync;
   4:	invokevirtual	#21; //Method scala/actors/threadpool/locks/ReentrantLock$Sync.isFair:()Z
   7:	ireturn

protected java.lang.Thread getOwner();
  Code:
   Stack=1, Locals=1, Args_size=1
   0:	aload_0
   1:	getfield	#4; //Field sync:Lscala/actors/threadpool/locks/ReentrantLock$Sync;
   4:	invokevirtual	#22; //Method scala/actors/threadpool/locks/ReentrantLock$Sync.getOwner:()Ljava/lang/Thread;
   7:	areturn

public final boolean hasQueuedThreads();
  Code:
   Stack=1, Locals=1, Args_size=1
   0:	aload_0
   1:	getfield	#4; //Field sync:Lscala/actors/threadpool/locks/ReentrantLock$Sync;
   4:	invokevirtual	#23; //Method scala/actors/threadpool/locks/ReentrantLock$Sync.hasQueuedThreads:()Z
   7:	ireturn

public final boolean hasQueuedThread(java.lang.Thread);
  Code:
   Stack=2, Locals=2, Args_size=2
   0:	aload_0
   1:	getfield	#4; //Field sync:Lscala/actors/threadpool/locks/ReentrantLock$Sync;
   4:	aload_1
   5:	invokevirtual	#24; //Method scala/actors/threadpool/locks/ReentrantLock$Sync.isQueued:(Ljava/lang/Thread;)Z
   8:	ireturn

public final int getQueueLength();
  Code:
   Stack=1, Locals=1, Args_size=1
   0:	aload_0
   1:	getfield	#4; //Field sync:Lscala/actors/threadpool/locks/ReentrantLock$Sync;
   4:	invokevirtual	#25; //Method scala/actors/threadpool/locks/ReentrantLock$Sync.getQueueLength:()I
   7:	ireturn

protected java.util.Collection getQueuedThreads();
  Code:
   Stack=1, Locals=1, Args_size=1
   0:	aload_0
   1:	getfield	#4; //Field sync:Lscala/actors/threadpool/locks/ReentrantLock$Sync;
   4:	invokevirtual	#26; //Method scala/actors/threadpool/locks/ReentrantLock$Sync.getQueuedThreads:()Ljava/util/Collection;
   7:	areturn

public boolean hasWaiters(scala.actors.threadpool.locks.Condition);
  Code:
   Stack=2, Locals=2, Args_size=2
   0:	aload_0
   1:	aload_1
   2:	invokespecial	#27; //Method asCondVar:(Lscala/actors/threadpool/locks/Condition;)Lscala/actors/threadpool/locks/CondVar;
   5:	invokevirtual	#28; //Method scala/actors/threadpool/locks/CondVar.hasWaiters:()Z
   8:	ireturn

public int getWaitQueueLength(scala.actors.threadpool.locks.Condition);
  Code:
   Stack=2, Locals=2, Args_size=2
   0:	aload_0
   1:	aload_1
   2:	invokespecial	#27; //Method asCondVar:(Lscala/actors/threadpool/locks/Condition;)Lscala/actors/threadpool/locks/CondVar;
   5:	invokevirtual	#29; //Method scala/actors/threadpool/locks/CondVar.getWaitQueueLength:()I
   8:	ireturn

protected java.util.Collection getWaitingThreads(scala.actors.threadpool.locks.Condition);
  Code:
   Stack=2, Locals=2, Args_size=2
   0:	aload_0
   1:	aload_1
   2:	invokespecial	#27; //Method asCondVar:(Lscala/actors/threadpool/locks/Condition;)Lscala/actors/threadpool/locks/CondVar;
   5:	invokevirtual	#30; //Method scala/actors/threadpool/locks/CondVar.getWaitingThreads:()Ljava/util/Collection;
   8:	areturn

public java.lang.String toString();
  Code:
   Stack=3, Locals=2, Args_size=1
   0:	aload_0
   1:	invokevirtual	#31; //Method getOwner:()Ljava/lang/Thread;
   4:	astore_1
   5:	new	#32; //class java/lang/StringBuilder
   8:	dup
   9:	invokespecial	#33; //Method java/lang/StringBuilder."<init>":()V
   12:	aload_0
   13:	invokespecial	#34; //Method java/lang/Object.toString:()Ljava/lang/String;
   16:	invokevirtual	#35; //Method java/lang/StringBuilder.append:(Ljava/lang/String;)Ljava/lang/StringBuilder;
   19:	aload_1
   20:	ifnonnull	28
   23:	ldc	#36; //String [Unlocked]
   25:	goto	55
   28:	new	#32; //class java/lang/StringBuilder
   31:	dup
   32:	invokespecial	#33; //Method java/lang/StringBuilder."<init>":()V
   35:	ldc	#37; //String [Locked by thread 
   37:	invokevirtual	#35; //Method java/lang/StringBuilder.append:(Ljava/lang/String;)Ljava/lang/StringBuilder;
   40:	aload_1
   41:	invokevirtual	#38; //Method java/lang/Thread.getName:()Ljava/lang/String;
   44:	invokevirtual	#35; //Method java/lang/StringBuilder.append:(Ljava/lang/String;)Ljava/lang/StringBuilder;
   47:	ldc	#39; //String ]
   49:	invokevirtual	#35; //Method java/lang/StringBuilder.append:(Ljava/lang/String;)Ljava/lang/StringBuilder;
   52:	invokevirtual	#40; //Method java/lang/StringBuilder.toString:()Ljava/lang/String;
   55:	invokevirtual	#35; //Method java/lang/StringBuilder.append:(Ljava/lang/String;)Ljava/lang/StringBuilder;
   58:	invokevirtual	#40; //Method java/lang/StringBuilder.toString:()Ljava/lang/String;
   61:	areturn

}

