public class scala.actors.threadpool.locks.ReentrantReadWriteLock extends java.lang.Object implements scala.actors.threadpool.locks.ReadWriteLock,java.io.Serializable
  InnerClass: 
   public WriteLock=class scala/actors/threadpool/locks/ReentrantReadWriteLock$WriteLock of class scala/actors/threadpool/locks/ReentrantReadWriteLock
   public ReadLock=class scala/actors/threadpool/locks/ReentrantReadWriteLock$ReadLock of class scala/actors/threadpool/locks/ReentrantReadWriteLock
   NonfairSync=class scala/actors/threadpool/locks/ReentrantReadWriteLock$NonfairSync of class scala/actors/threadpool/locks/ReentrantReadWriteLock
   abstract Sync=class scala/actors/threadpool/locks/ReentrantReadWriteLock$Sync of class scala/actors/threadpool/locks/ReentrantReadWriteLock
  minor version: 0
  major version: 49
  Constant pool:
Method	java/lang/Object."<init>":()V
class	scala/actors/threadpool/locks/ReentrantReadWriteLock$ReadLock
Method	scala/actors/threadpool/locks/ReentrantReadWriteLock$ReadLock."<init>":(Lscala/actors/threadpool/locks/ReentrantReadWriteLock;)V
Field	scala/actors/threadpool/locks/ReentrantReadWriteLock.readerLock_:Lscala/actors/threadpool/locks/ReentrantReadWriteLock$ReadLock;
class	scala/actors/threadpool/locks/ReentrantReadWriteLock$WriteLock
Method	scala/actors/threadpool/locks/ReentrantReadWriteLock$WriteLock."<init>":(Lscala/actors/threadpool/locks/ReentrantReadWriteLock;)V
Field	scala/actors/threadpool/locks/ReentrantReadWriteLock.writerLock_:Lscala/actors/threadpool/locks/ReentrantReadWriteLock$WriteLock;
class	scala/actors/threadpool/locks/ReentrantReadWriteLock$NonfairSync
Method	scala/actors/threadpool/locks/ReentrantReadWriteLock$NonfairSync."<init>":()V
Field	scala/actors/threadpool/locks/ReentrantReadWriteLock.sync:Lscala/actors/threadpool/locks/ReentrantReadWriteLock$Sync;
Method	scala/actors/threadpool/locks/ReentrantReadWriteLock$Sync.getOwner:()Ljava/lang/Thread;
Method	scala/actors/threadpool/locks/ReentrantReadWriteLock$Sync.getReadLockCount:()I
Method	scala/actors/threadpool/locks/ReentrantReadWriteLock$Sync.isWriteLocked:()Z
Method	scala/actors/threadpool/locks/ReentrantReadWriteLock$Sync.isWriteLockedByCurrentThread:()Z
Method	scala/actors/threadpool/locks/ReentrantReadWriteLock$Sync.getWriteHoldCount:()I
Method	scala/actors/threadpool/locks/ReentrantReadWriteLock$Sync.getReadHoldCount:()I
Method	scala/actors/threadpool/locks/ReentrantReadWriteLock$Sync.hasQueuedThreads:()Z
Method	scala/actors/threadpool/locks/ReentrantReadWriteLock$Sync.getQueueLength:()I
class	java/lang/StringBuilder
Method	java/lang/StringBuilder."<init>":()V
Method	java/lang/Object.toString:()Ljava/lang/String;
Method	java/lang/StringBuilder.append:(Ljava/lang/String;)Ljava/lang/StringBuilder;
String	[Write locks = 
Method	scala/actors/threadpool/locks/ReentrantReadWriteLock.getWriteHoldCount:()I
Method	java/lang/StringBuilder.append:(I)Ljava/lang/StringBuilder;
String	, Read locks = 
Method	scala/actors/threadpool/locks/ReentrantReadWriteLock.getReadLockCount:()I
String	]
Method	java/lang/StringBuilder.toString:()Ljava/lang/String;
class	scala/actors/threadpool/locks/ReentrantReadWriteLock
class	java/lang/Object
class	scala/actors/threadpool/locks/ReadWriteLock
class	java/io/Serializable
Asciz	WriteLock;
Asciz	InnerClasses;
Asciz	ReadLock;
Asciz	NonfairSync;
class	scala/actors/threadpool/locks/ReentrantReadWriteLock$Sync
Asciz	Sync;
Asciz	serialVersionUID;
Asciz	J;
Asciz	ConstantValue;
long	-3463448656717690166l;
Asciz	readerLock_;
Asciz	Lscala/actors/threadpool/locks/ReentrantReadWriteLock$ReadLock;;
Asciz	writerLock_;
Asciz	Lscala/actors/threadpool/locks/ReentrantReadWriteLock$WriteLock;;
Asciz	sync;
Asciz	Lscala/actors/threadpool/locks/ReentrantReadWriteLock$Sync;;
Asciz	<init>;
Asciz	()V;
Asciz	Code;
Asciz	writeLock;
Asciz	()Lscala/actors/threadpool/locks/Lock;;
Asciz	readLock;
Asciz	isFair;
Asciz	()Z;
Asciz	getOwner;
Asciz	()Ljava/lang/Thread;;
Asciz	getReadLockCount;
Asciz	()I;
Asciz	isWriteLocked;
Asciz	isWriteLockedByCurrentThread;
Asciz	getWriteHoldCount;
Asciz	getReadHoldCount;
Asciz	hasQueuedThreads;
Asciz	getQueueLength;
Asciz	toString;
Asciz	()Ljava/lang/String;;
NameAndType	"<init>":()V
Asciz	scala/actors/threadpool/locks/ReentrantReadWriteLock$ReadLock;
NameAndType	"<init>":(Lscala/actors/threadpool/locks/ReentrantReadWriteLock;)V
NameAndType	readerLock_:Lscala/actors/threadpool/locks/ReentrantReadWriteLock$ReadLock;
Asciz	scala/actors/threadpool/locks/ReentrantReadWriteLock$WriteLock;
NameAndType	writerLock_:Lscala/actors/threadpool/locks/ReentrantReadWriteLock$WriteLock;
Asciz	scala/actors/threadpool/locks/ReentrantReadWriteLock$NonfairSync;
NameAndType	sync:Lscala/actors/threadpool/locks/ReentrantReadWriteLock$Sync;
NameAndType	getOwner:()Ljava/lang/Thread;
NameAndType	getReadLockCount:()I
NameAndType	isWriteLocked:()Z
NameAndType	isWriteLockedByCurrentThread:()Z
NameAndType	getWriteHoldCount:()I
NameAndType	getReadHoldCount:()I
NameAndType	hasQueuedThreads:()Z
NameAndType	getQueueLength:()I
Asciz	java/lang/StringBuilder;
NameAndType	toString:()Ljava/lang/String;
NameAndType	append:(Ljava/lang/String;)Ljava/lang/StringBuilder;
Asciz	[Write locks = ;
NameAndType	append:(I)Ljava/lang/StringBuilder;
Asciz	, Read locks = ;
Asciz	];
Asciz	scala/actors/threadpool/locks/ReentrantReadWriteLock;
Asciz	java/lang/Object;
Asciz	scala/actors/threadpool/locks/ReadWriteLock;
Asciz	java/io/Serializable;
Asciz	scala/actors/threadpool/locks/ReentrantReadWriteLock$Sync;
Asciz	(Lscala/actors/threadpool/locks/ReentrantReadWriteLock;)V;
Asciz	append;
Asciz	(Ljava/lang/String;)Ljava/lang/StringBuilder;;
Asciz	(I)Ljava/lang/StringBuilder;;

{
private static final long serialVersionUID;
  Signature: J
  Constant value: long -3463448656717690166l
final scala.actors.threadpool.locks.ReentrantReadWriteLock$ReadLock readerLock_;
  Signature: Lscala/actors/threadpool/locks/ReentrantReadWriteLock$ReadLock;

final scala.actors.threadpool.locks.ReentrantReadWriteLock$WriteLock writerLock_;
  Signature: Lscala/actors/threadpool/locks/ReentrantReadWriteLock$WriteLock;

final scala.actors.threadpool.locks.ReentrantReadWriteLock$Sync sync;
  Signature: Lscala/actors/threadpool/locks/ReentrantReadWriteLock$Sync;

public scala.actors.threadpool.locks.ReentrantReadWriteLock();
  Signature: ()V
  Code:
   Stack=4, Locals=1, Args_size=1
	aload_0
	invokespecial	Method java/lang/Object."<init>":()V
	aload_0
	new	class scala/actors/threadpool/locks/ReentrantReadWriteLock$ReadLock
	dup
	aload_0
	invokespecial	Method scala/actors/threadpool/locks/ReentrantReadWriteLock$ReadLock."<init>":(Lscala/actors/threadpool/locks/ReentrantReadWriteLock;)V
	putfield	Field readerLock_:Lscala/actors/threadpool/locks/ReentrantReadWriteLock$ReadLock;
	aload_0
	new	class scala/actors/threadpool/locks/ReentrantReadWriteLock$WriteLock
	dup
	aload_0
	invokespecial	Method scala/actors/threadpool/locks/ReentrantReadWriteLock$WriteLock."<init>":(Lscala/actors/threadpool/locks/ReentrantReadWriteLock;)V
	putfield	Field writerLock_:Lscala/actors/threadpool/locks/ReentrantReadWriteLock$WriteLock;
	aload_0
	new	class scala/actors/threadpool/locks/ReentrantReadWriteLock$NonfairSync
	dup
	invokespecial	Method scala/actors/threadpool/locks/ReentrantReadWriteLock$NonfairSync."<init>":()V
	putfield	Field sync:Lscala/actors/threadpool/locks/ReentrantReadWriteLock$Sync;
	return
  Labels:

public scala.actors.threadpool.locks.Lock writeLock();
  Signature: ()Lscala/actors/threadpool/locks/Lock;
  Code:
   Stack=1, Locals=1, Args_size=1
	aload_0
	getfield	Field writerLock_:Lscala/actors/threadpool/locks/ReentrantReadWriteLock$WriteLock;
	areturn
  Labels:

public scala.actors.threadpool.locks.Lock readLock();
  Signature: ()Lscala/actors/threadpool/locks/Lock;
  Code:
   Stack=1, Locals=1, Args_size=1
	aload_0
	getfield	Field readerLock_:Lscala/actors/threadpool/locks/ReentrantReadWriteLock$ReadLock;
	areturn
  Labels:

public final boolean isFair();
  Signature: ()Z
  Code:
   Stack=1, Locals=1, Args_size=1
	iconst_0
	ireturn
  Labels:

protected java.lang.Thread getOwner();
  Signature: ()Ljava/lang/Thread;
  Code:
   Stack=1, Locals=1, Args_size=1
	aload_0
	getfield	Field sync:Lscala/actors/threadpool/locks/ReentrantReadWriteLock$Sync;
	invokevirtual	Method scala/actors/threadpool/locks/ReentrantReadWriteLock$Sync.getOwner:()Ljava/lang/Thread;
	areturn
  Labels:

public int getReadLockCount();
  Signature: ()I
  Code:
   Stack=1, Locals=1, Args_size=1
	aload_0
	getfield	Field sync:Lscala/actors/threadpool/locks/ReentrantReadWriteLock$Sync;
	invokevirtual	Method scala/actors/threadpool/locks/ReentrantReadWriteLock$Sync.getReadLockCount:()I
	ireturn
  Labels:

public boolean isWriteLocked();
  Signature: ()Z
  Code:
   Stack=1, Locals=1, Args_size=1
	aload_0
	getfield	Field sync:Lscala/actors/threadpool/locks/ReentrantReadWriteLock$Sync;
	invokevirtual	Method scala/actors/threadpool/locks/ReentrantReadWriteLock$Sync.isWriteLocked:()Z
	ireturn
  Labels:

public boolean isWriteLockedByCurrentThread();
  Signature: ()Z
  Code:
   Stack=1, Locals=1, Args_size=1
	aload_0
	getfield	Field sync:Lscala/actors/threadpool/locks/ReentrantReadWriteLock$Sync;
	invokevirtual	Method scala/actors/threadpool/locks/ReentrantReadWriteLock$Sync.isWriteLockedByCurrentThread:()Z
	ireturn
  Labels:

public int getWriteHoldCount();
  Signature: ()I
  Code:
   Stack=1, Locals=1, Args_size=1
	aload_0
	getfield	Field sync:Lscala/actors/threadpool/locks/ReentrantReadWriteLock$Sync;
	invokevirtual	Method scala/actors/threadpool/locks/ReentrantReadWriteLock$Sync.getWriteHoldCount:()I
	ireturn
  Labels:

public int getReadHoldCount();
  Signature: ()I
  Code:
   Stack=1, Locals=1, Args_size=1
	aload_0
	getfield	Field sync:Lscala/actors/threadpool/locks/ReentrantReadWriteLock$Sync;
	invokevirtual	Method scala/actors/threadpool/locks/ReentrantReadWriteLock$Sync.getReadHoldCount:()I
	ireturn
  Labels:

public final boolean hasQueuedThreads();
  Signature: ()Z
  Code:
   Stack=1, Locals=1, Args_size=1
	aload_0
	getfield	Field sync:Lscala/actors/threadpool/locks/ReentrantReadWriteLock$Sync;
	invokevirtual	Method scala/actors/threadpool/locks/ReentrantReadWriteLock$Sync.hasQueuedThreads:()Z
	ireturn
  Labels:

public final int getQueueLength();
  Signature: ()I
  Code:
   Stack=1, Locals=1, Args_size=1
	aload_0
	getfield	Field sync:Lscala/actors/threadpool/locks/ReentrantReadWriteLock$Sync;
	invokevirtual	Method scala/actors/threadpool/locks/ReentrantReadWriteLock$Sync.getQueueLength:()I
	ireturn
  Labels:

public java.lang.String toString();
  Signature: ()Ljava/lang/String;
  Code:
   Stack=2, Locals=1, Args_size=1
	new	class java/lang/StringBuilder
	dup
	invokespecial	Method java/lang/StringBuilder."<init>":()V
	aload_0
	invokespecial	Method java/lang/Object.toString:()Ljava/lang/String;
	invokevirtual	Method java/lang/StringBuilder.append:(Ljava/lang/String;)Ljava/lang/StringBuilder;
	ldc	String [Write locks = 
	invokevirtual	Method java/lang/StringBuilder.append:(Ljava/lang/String;)Ljava/lang/StringBuilder;
	aload_0
	invokevirtual	Method getWriteHoldCount:()I
	invokevirtual	Method java/lang/StringBuilder.append:(I)Ljava/lang/StringBuilder;
	ldc	String , Read locks = 
	invokevirtual	Method java/lang/StringBuilder.append:(Ljava/lang/String;)Ljava/lang/StringBuilder;
	aload_0
	invokevirtual	Method getReadLockCount:()I
	invokevirtual	Method java/lang/StringBuilder.append:(I)Ljava/lang/StringBuilder;
	ldc	String ]
	invokevirtual	Method java/lang/StringBuilder.append:(Ljava/lang/String;)Ljava/lang/StringBuilder;
	invokevirtual	Method java/lang/StringBuilder.toString:()Ljava/lang/String;
	areturn
  Labels:

}

