public class scala.actors.threadpool.locks.ReentrantReadWriteLock extends java.lang.Object implements scala.actors.threadpool.locks.ReadWriteLock,java.io.Serializable
  InnerClass: 
   public #34= #5 of #30; //WriteLock=class scala/actors/threadpool/locks/ReentrantReadWriteLock$WriteLock of class scala/actors/threadpool/locks/ReentrantReadWriteLock
   public #36= #2 of #30; //ReadLock=class scala/actors/threadpool/locks/ReentrantReadWriteLock$ReadLock of class scala/actors/threadpool/locks/ReentrantReadWriteLock
   #37= #8 of #30; //NonfairSync=class scala/actors/threadpool/locks/ReentrantReadWriteLock$NonfairSync of class scala/actors/threadpool/locks/ReentrantReadWriteLock
   abstract #39= #38 of #30; //Sync=class scala/actors/threadpool/locks/ReentrantReadWriteLock$Sync of class scala/actors/threadpool/locks/ReentrantReadWriteLock
  minor version: 0
  major version: 49
  Constant pool:
const #1 = Method	#31.#71;	//  java/lang/Object."<init>":()V
const #2 = class	#72;	//  scala/actors/threadpool/locks/ReentrantReadWriteLock$ReadLock
const #3 = Method	#2.#73;	//  scala/actors/threadpool/locks/ReentrantReadWriteLock$ReadLock."<init>":(Lscala/actors/threadpool/locks/ReentrantReadWriteLock;)V
const #4 = Field	#30.#74;	//  scala/actors/threadpool/locks/ReentrantReadWriteLock.readerLock_:Lscala/actors/threadpool/locks/ReentrantReadWriteLock$ReadLock;
const #5 = class	#75;	//  scala/actors/threadpool/locks/ReentrantReadWriteLock$WriteLock
const #6 = Method	#5.#73;	//  scala/actors/threadpool/locks/ReentrantReadWriteLock$WriteLock."<init>":(Lscala/actors/threadpool/locks/ReentrantReadWriteLock;)V
const #7 = Field	#30.#76;	//  scala/actors/threadpool/locks/ReentrantReadWriteLock.writerLock_:Lscala/actors/threadpool/locks/ReentrantReadWriteLock$WriteLock;
const #8 = class	#77;	//  scala/actors/threadpool/locks/ReentrantReadWriteLock$NonfairSync
const #9 = Method	#8.#71;	//  scala/actors/threadpool/locks/ReentrantReadWriteLock$NonfairSync."<init>":()V
const #10 = Field	#30.#78;	//  scala/actors/threadpool/locks/ReentrantReadWriteLock.sync:Lscala/actors/threadpool/locks/ReentrantReadWriteLock$Sync;
const #11 = Method	#38.#79;	//  scala/actors/threadpool/locks/ReentrantReadWriteLock$Sync.getOwner:()Ljava/lang/Thread;
const #12 = Method	#38.#80;	//  scala/actors/threadpool/locks/ReentrantReadWriteLock$Sync.getReadLockCount:()I
const #13 = Method	#38.#81;	//  scala/actors/threadpool/locks/ReentrantReadWriteLock$Sync.isWriteLocked:()Z
const #14 = Method	#38.#82;	//  scala/actors/threadpool/locks/ReentrantReadWriteLock$Sync.isWriteLockedByCurrentThread:()Z
const #15 = Method	#38.#83;	//  scala/actors/threadpool/locks/ReentrantReadWriteLock$Sync.getWriteHoldCount:()I
const #16 = Method	#38.#84;	//  scala/actors/threadpool/locks/ReentrantReadWriteLock$Sync.getReadHoldCount:()I
const #17 = Method	#38.#85;	//  scala/actors/threadpool/locks/ReentrantReadWriteLock$Sync.hasQueuedThreads:()Z
const #18 = Method	#38.#86;	//  scala/actors/threadpool/locks/ReentrantReadWriteLock$Sync.getQueueLength:()I
const #19 = class	#87;	//  java/lang/StringBuilder
const #20 = Method	#19.#71;	//  java/lang/StringBuilder."<init>":()V
const #21 = Method	#31.#88;	//  java/lang/Object.toString:()Ljava/lang/String;
const #22 = Method	#19.#89;	//  java/lang/StringBuilder.append:(Ljava/lang/String;)Ljava/lang/StringBuilder;
const #23 = String	#90;	//  [Write locks = 
const #24 = Method	#30.#83;	//  scala/actors/threadpool/locks/ReentrantReadWriteLock.getWriteHoldCount:()I
const #25 = Method	#19.#91;	//  java/lang/StringBuilder.append:(I)Ljava/lang/StringBuilder;
const #26 = String	#92;	//  , Read locks = 
const #27 = Method	#30.#80;	//  scala/actors/threadpool/locks/ReentrantReadWriteLock.getReadLockCount:()I
const #28 = String	#93;	//  ]
const #29 = Method	#19.#88;	//  java/lang/StringBuilder.toString:()Ljava/lang/String;
const #30 = class	#94;	//  scala/actors/threadpool/locks/ReentrantReadWriteLock
const #31 = class	#95;	//  java/lang/Object
const #32 = class	#96;	//  scala/actors/threadpool/locks/ReadWriteLock
const #33 = class	#97;	//  java/io/Serializable
const #34 = Asciz	WriteLock;
const #35 = Asciz	InnerClasses;
const #36 = Asciz	ReadLock;
const #37 = Asciz	NonfairSync;
const #38 = class	#98;	//  scala/actors/threadpool/locks/ReentrantReadWriteLock$Sync
const #39 = Asciz	Sync;
const #40 = Asciz	serialVersionUID;
const #41 = Asciz	J;
const #42 = Asciz	ConstantValue;
const #43 = long	-3463448656717690166l;
const #45 = Asciz	readerLock_;
const #46 = Asciz	Lscala/actors/threadpool/locks/ReentrantReadWriteLock$ReadLock;;
const #47 = Asciz	writerLock_;
const #48 = Asciz	Lscala/actors/threadpool/locks/ReentrantReadWriteLock$WriteLock;;
const #49 = Asciz	sync;
const #50 = Asciz	Lscala/actors/threadpool/locks/ReentrantReadWriteLock$Sync;;
const #51 = Asciz	<init>;
const #52 = Asciz	()V;
const #53 = Asciz	Code;
const #54 = Asciz	writeLock;
const #55 = Asciz	()Lscala/actors/threadpool/locks/Lock;;
const #56 = Asciz	readLock;
const #57 = Asciz	isFair;
const #58 = Asciz	()Z;
const #59 = Asciz	getOwner;
const #60 = Asciz	()Ljava/lang/Thread;;
const #61 = Asciz	getReadLockCount;
const #62 = Asciz	()I;
const #63 = Asciz	isWriteLocked;
const #64 = Asciz	isWriteLockedByCurrentThread;
const #65 = Asciz	getWriteHoldCount;
const #66 = Asciz	getReadHoldCount;
const #67 = Asciz	hasQueuedThreads;
const #68 = Asciz	getQueueLength;
const #69 = Asciz	toString;
const #70 = Asciz	()Ljava/lang/String;;
const #71 = NameAndType	#51:#52;//  "<init>":()V
const #72 = Asciz	scala/actors/threadpool/locks/ReentrantReadWriteLock$ReadLock;
const #73 = NameAndType	#51:#99;//  "<init>":(Lscala/actors/threadpool/locks/ReentrantReadWriteLock;)V
const #74 = NameAndType	#45:#46;//  readerLock_:Lscala/actors/threadpool/locks/ReentrantReadWriteLock$ReadLock;
const #75 = Asciz	scala/actors/threadpool/locks/ReentrantReadWriteLock$WriteLock;
const #76 = NameAndType	#47:#48;//  writerLock_:Lscala/actors/threadpool/locks/ReentrantReadWriteLock$WriteLock;
const #77 = Asciz	scala/actors/threadpool/locks/ReentrantReadWriteLock$NonfairSync;
const #78 = NameAndType	#49:#50;//  sync:Lscala/actors/threadpool/locks/ReentrantReadWriteLock$Sync;
const #79 = NameAndType	#59:#60;//  getOwner:()Ljava/lang/Thread;
const #80 = NameAndType	#61:#62;//  getReadLockCount:()I
const #81 = NameAndType	#63:#58;//  isWriteLocked:()Z
const #82 = NameAndType	#64:#58;//  isWriteLockedByCurrentThread:()Z
const #83 = NameAndType	#65:#62;//  getWriteHoldCount:()I
const #84 = NameAndType	#66:#62;//  getReadHoldCount:()I
const #85 = NameAndType	#67:#58;//  hasQueuedThreads:()Z
const #86 = NameAndType	#68:#62;//  getQueueLength:()I
const #87 = Asciz	java/lang/StringBuilder;
const #88 = NameAndType	#69:#70;//  toString:()Ljava/lang/String;
const #89 = NameAndType	#100:#101;//  append:(Ljava/lang/String;)Ljava/lang/StringBuilder;
const #90 = Asciz	[Write locks = ;
const #91 = NameAndType	#100:#102;//  append:(I)Ljava/lang/StringBuilder;
const #92 = Asciz	, Read locks = ;
const #93 = Asciz	];
const #94 = Asciz	scala/actors/threadpool/locks/ReentrantReadWriteLock;
const #95 = Asciz	java/lang/Object;
const #96 = Asciz	scala/actors/threadpool/locks/ReadWriteLock;
const #97 = Asciz	java/io/Serializable;
const #98 = Asciz	scala/actors/threadpool/locks/ReentrantReadWriteLock$Sync;
const #99 = Asciz	(Lscala/actors/threadpool/locks/ReentrantReadWriteLock;)V;
const #100 = Asciz	append;
const #101 = Asciz	(Ljava/lang/String;)Ljava/lang/StringBuilder;;
const #102 = Asciz	(I)Ljava/lang/StringBuilder;;

{
final scala.actors.threadpool.locks.ReentrantReadWriteLock$ReadLock readerLock_;

final scala.actors.threadpool.locks.ReentrantReadWriteLock$WriteLock writerLock_;

final scala.actors.threadpool.locks.ReentrantReadWriteLock$Sync sync;

public scala.actors.threadpool.locks.ReentrantReadWriteLock();
  Code:
   Stack=4, Locals=1, Args_size=1
   0:	aload_0
   1:	invokespecial	#1; //Method java/lang/Object."<init>":()V
   4:	aload_0
   5:	new	#2; //class scala/actors/threadpool/locks/ReentrantReadWriteLock$ReadLock
   8:	dup
   9:	aload_0
   10:	invokespecial	#3; //Method scala/actors/threadpool/locks/ReentrantReadWriteLock$ReadLock."<init>":(Lscala/actors/threadpool/locks/ReentrantReadWriteLock;)V
   13:	putfield	#4; //Field readerLock_:Lscala/actors/threadpool/locks/ReentrantReadWriteLock$ReadLock;
   16:	aload_0
   17:	new	#5; //class scala/actors/threadpool/locks/ReentrantReadWriteLock$WriteLock
   20:	dup
   21:	aload_0
   22:	invokespecial	#6; //Method scala/actors/threadpool/locks/ReentrantReadWriteLock$WriteLock."<init>":(Lscala/actors/threadpool/locks/ReentrantReadWriteLock;)V
   25:	putfield	#7; //Field writerLock_:Lscala/actors/threadpool/locks/ReentrantReadWriteLock$WriteLock;
   28:	aload_0
   29:	new	#8; //class scala/actors/threadpool/locks/ReentrantReadWriteLock$NonfairSync
   32:	dup
   33:	invokespecial	#9; //Method scala/actors/threadpool/locks/ReentrantReadWriteLock$NonfairSync."<init>":()V
   36:	putfield	#10; //Field sync:Lscala/actors/threadpool/locks/ReentrantReadWriteLock$Sync;
   39:	return

public scala.actors.threadpool.locks.Lock writeLock();
  Code:
   Stack=1, Locals=1, Args_size=1
   0:	aload_0
   1:	getfield	#7; //Field writerLock_:Lscala/actors/threadpool/locks/ReentrantReadWriteLock$WriteLock;
   4:	areturn

public scala.actors.threadpool.locks.Lock readLock();
  Code:
   Stack=1, Locals=1, Args_size=1
   0:	aload_0
   1:	getfield	#4; //Field readerLock_:Lscala/actors/threadpool/locks/ReentrantReadWriteLock$ReadLock;
   4:	areturn

public final boolean isFair();
  Code:
   Stack=1, Locals=1, Args_size=1
   0:	iconst_0
   1:	ireturn

protected java.lang.Thread getOwner();
  Code:
   Stack=1, Locals=1, Args_size=1
   0:	aload_0
   1:	getfield	#10; //Field sync:Lscala/actors/threadpool/locks/ReentrantReadWriteLock$Sync;
   4:	invokevirtual	#11; //Method scala/actors/threadpool/locks/ReentrantReadWriteLock$Sync.getOwner:()Ljava/lang/Thread;
   7:	areturn

public int getReadLockCount();
  Code:
   Stack=1, Locals=1, Args_size=1
   0:	aload_0
   1:	getfield	#10; //Field sync:Lscala/actors/threadpool/locks/ReentrantReadWriteLock$Sync;
   4:	invokevirtual	#12; //Method scala/actors/threadpool/locks/ReentrantReadWriteLock$Sync.getReadLockCount:()I
   7:	ireturn

public boolean isWriteLocked();
  Code:
   Stack=1, Locals=1, Args_size=1
   0:	aload_0
   1:	getfield	#10; //Field sync:Lscala/actors/threadpool/locks/ReentrantReadWriteLock$Sync;
   4:	invokevirtual	#13; //Method scala/actors/threadpool/locks/ReentrantReadWriteLock$Sync.isWriteLocked:()Z
   7:	ireturn

public boolean isWriteLockedByCurrentThread();
  Code:
   Stack=1, Locals=1, Args_size=1
   0:	aload_0
   1:	getfield	#10; //Field sync:Lscala/actors/threadpool/locks/ReentrantReadWriteLock$Sync;
   4:	invokevirtual	#14; //Method scala/actors/threadpool/locks/ReentrantReadWriteLock$Sync.isWriteLockedByCurrentThread:()Z
   7:	ireturn

public int getWriteHoldCount();
  Code:
   Stack=1, Locals=1, Args_size=1
   0:	aload_0
   1:	getfield	#10; //Field sync:Lscala/actors/threadpool/locks/ReentrantReadWriteLock$Sync;
   4:	invokevirtual	#15; //Method scala/actors/threadpool/locks/ReentrantReadWriteLock$Sync.getWriteHoldCount:()I
   7:	ireturn

public int getReadHoldCount();
  Code:
   Stack=1, Locals=1, Args_size=1
   0:	aload_0
   1:	getfield	#10; //Field sync:Lscala/actors/threadpool/locks/ReentrantReadWriteLock$Sync;
   4:	invokevirtual	#16; //Method scala/actors/threadpool/locks/ReentrantReadWriteLock$Sync.getReadHoldCount:()I
   7:	ireturn

public final boolean hasQueuedThreads();
  Code:
   Stack=1, Locals=1, Args_size=1
   0:	aload_0
   1:	getfield	#10; //Field sync:Lscala/actors/threadpool/locks/ReentrantReadWriteLock$Sync;
   4:	invokevirtual	#17; //Method scala/actors/threadpool/locks/ReentrantReadWriteLock$Sync.hasQueuedThreads:()Z
   7:	ireturn

public final int getQueueLength();
  Code:
   Stack=1, Locals=1, Args_size=1
   0:	aload_0
   1:	getfield	#10; //Field sync:Lscala/actors/threadpool/locks/ReentrantReadWriteLock$Sync;
   4:	invokevirtual	#18; //Method scala/actors/threadpool/locks/ReentrantReadWriteLock$Sync.getQueueLength:()I
   7:	ireturn

public java.lang.String toString();
  Code:
   Stack=2, Locals=1, Args_size=1
   0:	new	#19; //class java/lang/StringBuilder
   3:	dup
   4:	invokespecial	#20; //Method java/lang/StringBuilder."<init>":()V
   7:	aload_0
   8:	invokespecial	#21; //Method java/lang/Object.toString:()Ljava/lang/String;
   11:	invokevirtual	#22; //Method java/lang/StringBuilder.append:(Ljava/lang/String;)Ljava/lang/StringBuilder;
   14:	ldc	#23; //String [Write locks = 
   16:	invokevirtual	#22; //Method java/lang/StringBuilder.append:(Ljava/lang/String;)Ljava/lang/StringBuilder;
   19:	aload_0
   20:	invokevirtual	#24; //Method getWriteHoldCount:()I
   23:	invokevirtual	#25; //Method java/lang/StringBuilder.append:(I)Ljava/lang/StringBuilder;
   26:	ldc	#26; //String , Read locks = 
   28:	invokevirtual	#22; //Method java/lang/StringBuilder.append:(Ljava/lang/String;)Ljava/lang/StringBuilder;
   31:	aload_0
   32:	invokevirtual	#27; //Method getReadLockCount:()I
   35:	invokevirtual	#25; //Method java/lang/StringBuilder.append:(I)Ljava/lang/StringBuilder;
   38:	ldc	#28; //String ]
   40:	invokevirtual	#22; //Method java/lang/StringBuilder.append:(Ljava/lang/String;)Ljava/lang/StringBuilder;
   43:	invokevirtual	#29; //Method java/lang/StringBuilder.toString:()Ljava/lang/String;
   46:	areturn

}

