Compiled from "HedgeRHS.scala"
public final class scala.util.grammar.AnyHedgeRHS extends java.lang.Object
  SourceFile: "HedgeRHS.scala"
  ScalaSig: length = 0x3
   05 00 00 
  RuntimeVisibleAnnotations: length = 0xB
   00 01 00 27 00 01 00 28 73 00 29 
  minor version: 0
  major version: 49
  Constant pool:
Asciz	SourceFile;
Asciz	HedgeRHS.scala;
Asciz	productElements;
Asciz	()Lscala/collection/Iterator;;
Asciz	Code;
Asciz	scala/util/grammar/AnyHedgeRHS$;
class	scala/util/grammar/AnyHedgeRHS$
Asciz	MODULE$;
Asciz	Lscala/util/grammar/AnyHedgeRHS$;;
NameAndType	MODULE$:Lscala/util/grammar/AnyHedgeRHS$;
Field	scala/util/grammar/AnyHedgeRHS$.MODULE$:Lscala/util/grammar/AnyHedgeRHS$;
NameAndType	productElements:()Lscala/collection/Iterator;
Method	scala/util/grammar/AnyHedgeRHS$.productElements:()Lscala/collection/Iterator;
Asciz	Deprecated;
Asciz	productIterator;
NameAndType	productIterator:()Lscala/collection/Iterator;
Method	scala/util/grammar/AnyHedgeRHS$.productIterator:()Lscala/collection/Iterator;
Asciz	productElementName;
Asciz	(I)Ljava/lang/String;;
NameAndType	productElementName:(I)Ljava/lang/String;
Method	scala/util/grammar/AnyHedgeRHS$.productElementName:(I)Ljava/lang/String;
Asciz	canEqual;
Asciz	(Ljava/lang/Object;)Z;
NameAndType	canEqual:(Ljava/lang/Object;)Z
Method	scala/util/grammar/AnyHedgeRHS$.canEqual:(Ljava/lang/Object;)Z
Asciz	productElement;
Asciz	(I)Ljava/lang/Object;;
NameAndType	productElement:(I)Ljava/lang/Object;
Method	scala/util/grammar/AnyHedgeRHS$.productElement:(I)Ljava/lang/Object;
Asciz	productArity;
Asciz	()I;
NameAndType	productArity:()I
Method	scala/util/grammar/AnyHedgeRHS$.productArity:()I
Asciz	productPrefix;
Asciz	()Ljava/lang/String;;
NameAndType	productPrefix:()Ljava/lang/String;
Method	scala/util/grammar/AnyHedgeRHS$.productPrefix:()Ljava/lang/String;
Asciz	ScalaSig;
Asciz	Lscala/reflect/ScalaSignature;;
Asciz	bytes;
Asciz	!;Q!\t&\t1\"8z$w-*I'*1BOJW.\1s\t)a!vi&d'\"AM\r\1A!bCAABC#UBAB]fDU\rZ4f%\"6B#U\"AC\nA!%fI,'S*IR\"\nQ1!aC*dC2wJ6fGR\"A\n]1!a)s_,8\r3-!\tAGy%t %AH%)%H\ti>FO]5oOR\ta I5\tE\"E!A.8h6bmL!!\n\rM#(/8h!93\"A\nB!9s_,8\r)sKL0F!Q3\"A\nZ9s_,8\r^!sSRLX#IiB\rIe\ta-!\t!C!cqO]8ek$X\t\3nK:$HC6!\t2'5\r\tI\=\tYz!aYJ\taZA!ABe\nbY1oF,\ruu\"AE\nq2!a\"p_2,Mm]\n\t13!y4\"A\n#a:fCVm]8mm$!\t?\tK!a\r='.Z2uQ\tYQ\t\r&qI\rg.7juG.;
Asciz	RuntimeVisibleAnnotations;
Asciz	scala/util/grammar/AnyHedgeRHS;
class	scala/util/grammar/AnyHedgeRHS
Asciz	java/lang/Object;
class	java/lang/Object

{
public static final scala.collection.Iterator productElements();
  Signature: ()Lscala/collection/Iterator;
  Code:
   Stack=1, Locals=0, Args_size=0
	getstatic	Field scala/util/grammar/AnyHedgeRHS$.MODULE$:Lscala/util/grammar/AnyHedgeRHS$;
	invokevirtual	Method scala/util/grammar/AnyHedgeRHS$.productElements:()Lscala/collection/Iterator;
	areturn
  Labels:
  Deprecated: true

public static final scala.collection.Iterator productIterator();
  Signature: ()Lscala/collection/Iterator;
  Code:
   Stack=1, Locals=0, Args_size=0
	getstatic	Field scala/util/grammar/AnyHedgeRHS$.MODULE$:Lscala/util/grammar/AnyHedgeRHS$;
	invokevirtual	Method scala/util/grammar/AnyHedgeRHS$.productIterator:()Lscala/collection/Iterator;
	areturn
  Labels:

public static final java.lang.String productElementName(int);
  Signature: (I)Ljava/lang/String;
  Code:
   Stack=2, Locals=1, Args_size=1
	getstatic	Field scala/util/grammar/AnyHedgeRHS$.MODULE$:Lscala/util/grammar/AnyHedgeRHS$;
	iload_0
	invokevirtual	Method scala/util/grammar/AnyHedgeRHS$.productElementName:(I)Ljava/lang/String;
	areturn
  Labels:

public static final boolean canEqual(java.lang.Object);
  Signature: (Ljava/lang/Object;)Z
  Code:
   Stack=2, Locals=1, Args_size=1
	getstatic	Field scala/util/grammar/AnyHedgeRHS$.MODULE$:Lscala/util/grammar/AnyHedgeRHS$;
	aload_0
	invokevirtual	Method scala/util/grammar/AnyHedgeRHS$.canEqual:(Ljava/lang/Object;)Z
	ireturn
  Labels:

public static final java.lang.Object productElement(int);
  Signature: (I)Ljava/lang/Object;
  Code:
   Stack=2, Locals=1, Args_size=1
	getstatic	Field scala/util/grammar/AnyHedgeRHS$.MODULE$:Lscala/util/grammar/AnyHedgeRHS$;
	iload_0
	invokevirtual	Method scala/util/grammar/AnyHedgeRHS$.productElement:(I)Ljava/lang/Object;
	areturn
  Labels:

public static final int productArity();
  Signature: ()I
  Code:
   Stack=1, Locals=0, Args_size=0
	getstatic	Field scala/util/grammar/AnyHedgeRHS$.MODULE$:Lscala/util/grammar/AnyHedgeRHS$;
	invokevirtual	Method scala/util/grammar/AnyHedgeRHS$.productArity:()I
	ireturn
  Labels:

public static final java.lang.String productPrefix();
  Signature: ()Ljava/lang/String;
  Code:
   Stack=1, Locals=0, Args_size=0
	getstatic	Field scala/util/grammar/AnyHedgeRHS$.MODULE$:Lscala/util/grammar/AnyHedgeRHS$;
	invokevirtual	Method scala/util/grammar/AnyHedgeRHS$.productPrefix:()Ljava/lang/String;
	areturn
  Labels:

}

