Compiled from "HedgeRHS.scala"
public class scala.util.grammar.ConsRHS extends scala.util.grammar.HedgeRHS implements scala.ScalaObject,scala.Product,java.io.Serializable
  SourceFile: "HedgeRHS.scala"
  ScalaSig: length = 0x39F
   05 00 FFFFFF81 08 06 08 01 02 FFFFFF84 FFFFFF80 FFFFFF80 FFFFFF80 40 09 02 07
   43 6F 6E 73 52 48 53 0A 02 03 04 01 07 67 72 61
   6D 6D 61 72 0A 02 05 06 01 04 75 74 69 6C 0A 01
   07 01 05 73 63 61 6C 61 03 00 13 04 00 0A 0E 12
   10 02 0B 0C 0D 01 02 09 02 0D 02 02 08 48 65 64
   67 65 52 48 53 10 02 0F 10 0D 01 06 09 02 11 06
   02 0B 53 63 61 6C 61 4F 62 6A 65 63 74 10 02 0F
   13 09 02 14 06 02 07 50 72 6F 64 75 63 74 08 08
   16 00 FFFFFF82 FFFFFFCA FFFFFF80 FFFFFF84 00 17 01 03 74 6E 74 15 01 18
   10 02 0F 19 09 02 1A 06 02 03 49 6E 74 08 08 1C
   00 FFFFFF82 FFFFFF88 FFFFFFA0 FFFFFF80 04 18 01 04 74 6E 74 20 08 08 1E
   00 FFFFFF82 FFFFFFCA FFFFFF80 FFFFFF84 00 17 01 03 68 6E 74 08 08 20 00
   FFFFFF82 FFFFFF88 FFFFFFA0 FFFFFF80 04 18 01 04 68 6E 74 20 08 05 22 00
   FFFFFF84 00 23 01 06 3C 69 6E 69 74 3E 14 03 24 25 26
   10 02 0B 00 08 05 16 21 FFFFFFC0 00 18 08 05 1E 21 FFFFFFC0
   00 18 08 07 28 00 FFFFFF81 FFFFFF80 FFFFFF84 00 29 01 04 63 6F 70
   79 14 03 24 2A 38 08 08 2B 16 27 FFFFFF90 FFFFFF80 FFFFFFC0 00 18
   08 07 2C 00 FFFFFF91 FFFFFF80 FFFFFF84 00 2D 01 0E 63 6F 70 79 24
   64 65 66 61 75 6C 74 24 31 15 01 2E 2A 02 18 2F
   2B 01 30 10 02 31 36 0D 01 32 0A 02 33 34 01 09
   75 6E 63 68 65 63 6B 65 64 0A 02 35 06 01 0A 61
   6E 6E 6F 74 61 74 69 6F 6E 09 02 37 32 02 11 75
   6E 63 68 65 63 6B 65 64 56 61 72 69 61 6E 63 65
   08 08 39 1E 27 FFFFFF90 FFFFFF80 FFFFFFC0 00 18 08 07 3A 00 FFFFFF91 FFFFFF80
   FFFFFF84 00 2D 01 0E 63 6F 70 79 24 64 65 66 61 75 6C
   74 24 32 08 08 3C 00 FFFFFF84 FFFFFF80 FFFFFF80 FFFFFF84 20 3D 01 08 68
   61 73 68 43 6F 64 65 14 01 18 08 08 3F 00 FFFFFF84 FFFFFF80
   FFFFFF80 FFFFFF84 20 40 01 08 74 6F 53 74 72 69 6E 67 14 01
   41 10 02 42 45 0E 02 0F 43 09 02 44 06 01 06 50
   72 65 64 65 66 09 02 46 47 02 06 53 74 72 69 6E
   67 0A 02 44 06 08 08 49 00 FFFFFF84 FFFFFF80 FFFFFF80 FFFFFF84 20 4A 01
   06 65 71 75 61 6C 73 14 02 4B 4E 10 02 0F 4C 09
   02 4D 06 02 07 42 6F 6F 6C 65 61 6E 08 07 4F 48
   FFFFFF81 FFFFFF80 FFFFFFC0 00 50 01 03 78 24 31 10 02 0F 51 09 02
   52 06 02 03 41 6E 79 08 08 54 00 FFFFFF84 FFFFFF80 FFFFFF80 FFFFFF84 20
   55 01 0D 70 72 6F 64 75 63 74 50 72 65 66 69 78
   15 01 56 10 02 57 5C 0D 01 58 0A 02 59 5A 01 04
   6C 61 6E 67 0A 01 5B 01 04 6A 61 76 61 09 02 46
   58 08 08 5E 00 FFFFFF84 FFFFFF80 FFFFFF80 FFFFFF84 20 17 01 0C 70 72 6F
   64 75 63 74 41 72 69 74 79 08 08 60 00 FFFFFF84 FFFFFF80 FFFFFF80
   FFFFFF84 20 61 01 0E 70 72 6F 64 75 63 74 45 6C 65 6D
   65 6E 74 14 02 50 62 08 07 4F 5F FFFFFF81 FFFFFF80 FFFFFFC0 00 18
   08 08 64 00 FFFFFF84 FFFFFF80 FFFFFF80 FFFFFF84 20 65 01 08 63 61 6E 45
   71 75 61 6C 14 02 4B 66 08 07 4F 63 FFFFFF81 FFFFFF80 FFFFFFC0 00
   50 28 02 00 68 10 02 0F 69 09 02 6A 06 02 0C 73
   65 72 69 61 6C 69 7A 61 62 6C 65 07 07 6C 02 FFFFFF81
   FFFFFF80 FFFFFF88 02 6D 01 07 43 6F 6E 73 52 48 53 10 02 0B
   6E 06 08 01 02 FFFFFF84 FFFFFF81 FFFFFF80 FFFFFF88 02 6F 13 04 6E 70 73
   0E 10 02 57 71 09 02 72 58 02 06 4F 62 6A 65 63
   74 10 05 0F 74 18 18 24 09 02 75 06 02 09 46 75
   6E 63 74 69 6F 6E 32 08 05 22 6E FFFFFF84 00 77 14 01
   6D 08 07 79 6E FFFFFF81 FFFFFF80 FFFFFF84 40 7A 01 05 61 70 70 6C
   79 14 03 24 7B 7C 08 05 16 78 FFFFFFC0 00 18 08 05 1E
   78 FFFFFFC0 00 18 08 07 7E 6E FFFFFF81 FFFFFF80 FFFFFF84 40 7F 01 07 75
   6E 61 70 70 6C 79 14 04 FFFFFF81 00 FFFFFF81 06 10 05 0F FFFFFF81
   01 FFFFFF81 03 09 03 FFFFFF81 02 06 02 04 53 6F 6D 65 10 05
   0F FFFFFF81 04 18 18 09 03 FFFFFF81 05 06 02 06 54 75 70 6C
   65 32 08 06 FFFFFF81 07 7D FFFFFFC0 00 24 01 03 78 24 30 
  minor version: 0
  major version: 49
  Constant pool:
Asciz	SourceFile;
Asciz	HedgeRHS.scala;
Asciz	tupled;
Asciz	()Lscala/Function1;;
Asciz	Code;
Asciz	scala/util/grammar/ConsRHS$;
class	scala/util/grammar/ConsRHS$
Asciz	MODULE$;
Asciz	Lscala/util/grammar/ConsRHS$;;
NameAndType	MODULE$:Lscala/util/grammar/ConsRHS$;
Field	scala/util/grammar/ConsRHS$.MODULE$:Lscala/util/grammar/ConsRHS$;
NameAndType	tupled:()Lscala/Function1;
Method	scala/util/grammar/ConsRHS$.tupled:()Lscala/Function1;
Asciz	curry;
NameAndType	curry:()Lscala/Function1;
Method	scala/util/grammar/ConsRHS$.curry:()Lscala/Function1;
Asciz	Deprecated;
Asciz	curried;
NameAndType	curried:()Lscala/Function1;
Method	scala/util/grammar/ConsRHS$.curried:()Lscala/Function1;
Asciz	hnt;
Asciz	I;
Asciz	tnt;
Asciz	<init>;
Asciz	(II)V;
Asciz	LineNumberTable;
Asciz	scala/util/grammar/ConsRHS;
class	scala/util/grammar/ConsRHS
NameAndType	tnt:I
Field	scala/util/grammar/ConsRHS.tnt:I
NameAndType	hnt:I
Field	scala/util/grammar/ConsRHS.hnt:I
Asciz	scala/util/grammar/HedgeRHS;
class	scala/util/grammar/HedgeRHS
Asciz	()V;
NameAndType	"<init>":()V
Method	scala/util/grammar/HedgeRHS."<init>":()V
Asciz	scala/Product$class;
class	scala/Product$class
Asciz	$init$;
Asciz	(Lscala/Product;)V;
NameAndType	$init$:(Lscala/Product;)V
Method	scala/Product$class.$init$:(Lscala/Product;)V
Asciz	this;
Asciz	Lscala/util/grammar/ConsRHS;;
Asciz	LocalVariableTable;
Asciz	gd1$1;
Asciz	(II)Z;
Asciz	()I;
NameAndType	tnt:()I
Method	scala/util/grammar/ConsRHS.tnt:()I
NameAndType	hnt:()I
Method	scala/util/grammar/ConsRHS.hnt:()I
Asciz	canEqual;
Asciz	(Ljava/lang/Object;)Z;
Asciz	productElement;
Asciz	(I)Ljava/lang/Object;;
Asciz	java/lang/IndexOutOfBoundsException;
class	java/lang/IndexOutOfBoundsException
Asciz	scala/runtime/BoxesRunTime;
class	scala/runtime/BoxesRunTime
Asciz	boxToInteger;
Asciz	(I)Ljava/lang/Integer;;
NameAndType	boxToInteger:(I)Ljava/lang/Integer;
Method	scala/runtime/BoxesRunTime.boxToInteger:(I)Ljava/lang/Integer;
Asciz	java/lang/Object;
class	java/lang/Object
Asciz	toString;
Asciz	()Ljava/lang/String;;
NameAndType	toString:()Ljava/lang/String;
Method	java/lang/Object.toString:()Ljava/lang/String;
Asciz	(Ljava/lang/String;)V;
NameAndType	"<init>":(Ljava/lang/String;)V
Method	java/lang/IndexOutOfBoundsException."<init>":(Ljava/lang/String;)V
Asciz	productArity;
Asciz	productPrefix;
Asciz	ConsRHS;
String	ConsRHS
Asciz	equals;
NameAndType	gd1$1:(II)Z
Method	scala/util/grammar/ConsRHS.gd1$1:(II)Z
Asciz	scala/Equals;
class	scala/Equals
NameAndType	canEqual:(Ljava/lang/Object;)Z
InterfaceMethod	scala/Equals.canEqual:(Ljava/lang/Object;)Z
Asciz	temp2;
Asciz	temp3;
Asciz	temp4;
Asciz	scala/runtime/ScalaRunTime$;
class	scala/runtime/ScalaRunTime$
Asciz	Lscala/runtime/ScalaRunTime$;;
NameAndType	MODULE$:Lscala/runtime/ScalaRunTime$;
Field	scala/runtime/ScalaRunTime$.MODULE$:Lscala/runtime/ScalaRunTime$;
Asciz	_toString;
Asciz	(Lscala/Product;)Ljava/lang/String;;
NameAndType	_toString:(Lscala/Product;)Ljava/lang/String;
Method	scala/runtime/ScalaRunTime$._toString:(Lscala/Product;)Ljava/lang/String;
Asciz	hashCode;
Asciz	_hashCode;
Asciz	(Lscala/Product;)I;
NameAndType	_hashCode:(Lscala/Product;)I
Method	scala/runtime/ScalaRunTime$._hashCode:(Lscala/Product;)I
Asciz	copy;
Asciz	(II)Lscala/util/grammar/ConsRHS;;
NameAndType	"<init>":(II)V
Method	scala/util/grammar/ConsRHS."<init>":(II)V
Asciz	copy$default$1;
Asciz	copy$default$2;
Asciz	productElements;
Asciz	()Lscala/collection/Iterator;;
Asciz	(Lscala/Product;)Lscala/collection/Iterator;;
NameAndType	productElements:(Lscala/Product;)Lscala/collection/Iterator;
Method	scala/Product$class.productElements:(Lscala/Product;)Lscala/collection/Iterator;
Asciz	productIterator;
NameAndType	productIterator:(Lscala/Product;)Lscala/collection/Iterator;
Method	scala/Product$class.productIterator:(Lscala/Product;)Lscala/collection/Iterator;
Asciz	ScalaSig;
Asciz	scala/ScalaObject;
class	scala/ScalaObject
Asciz	scala/Product;
class	scala/Product
Asciz	java/io/Serializable;
class	java/io/Serializable

{
private final int hnt;
  Signature: I

private final int tnt;
  Signature: I

public static final scala.Function1 tupled();
  Signature: ()Lscala/Function1;
  Code:
   Stack=1, Locals=0, Args_size=0
	getstatic	Field scala/util/grammar/ConsRHS$.MODULE$:Lscala/util/grammar/ConsRHS$;
	invokevirtual	Method scala/util/grammar/ConsRHS$.tupled:()Lscala/Function1;
	areturn
  Labels:

public static final scala.Function1 curry();
  Signature: ()Lscala/Function1;
  Code:
   Stack=1, Locals=0, Args_size=0
	getstatic	Field scala/util/grammar/ConsRHS$.MODULE$:Lscala/util/grammar/ConsRHS$;
	invokevirtual	Method scala/util/grammar/ConsRHS$.curry:()Lscala/Function1;
	areturn
  Labels:
  Deprecated: true

public static final scala.Function1 curried();
  Signature: ()Lscala/Function1;
  Code:
   Stack=1, Locals=0, Args_size=0
	getstatic	Field scala/util/grammar/ConsRHS$.MODULE$:Lscala/util/grammar/ConsRHS$;
	invokevirtual	Method scala/util/grammar/ConsRHS$.curried:()Lscala/Function1;
	areturn
  Labels:

public scala.util.grammar.ConsRHS(int, int);
  Signature: (II)V
  Code:
   Stack=2, Locals=3, Args_size=3
	aload_0
	iload_1
	putfield	Field tnt:I
	aload_0
	iload_2
	putfield	Field hnt:I
	aload_0
	invokespecial	Method scala/util/grammar/HedgeRHS."<init>":()V
	aload_0
	invokestatic	Method scala/Product$class.$init$:(Lscala/Product;)V
	return
  Labels:
  LocalVariableTable: 
   Start  Length  Slot  Name   Signature
   0      19      0    this       Lscala/util/grammar/ConsRHS;
   0      19      1    tnt       I
   0      19      2    hnt       I


private final boolean gd1$1(int, int);
  Signature: (II)Z
  Code:
   Stack=2, Locals=3, Args_size=3
	iload_1
	aload_0
	invokevirtual	Method tnt:()I
	if_icmpne	l1 // iconst_0
	iload_2
	aload_0
	invokevirtual	Method hnt:()I
	if_icmpne	l1 // iconst_0
	iconst_1
	goto	l2 // ireturn
l1	iconst_0
l2	ireturn
  Labels:
   	l1 = 20 // iconst_0
   	l2 = 21 // ireturn

public boolean canEqual(java.lang.Object);
  Signature: (Ljava/lang/Object;)Z
  Code:
   Stack=1, Locals=2, Args_size=2
	aload_1
	instanceof	class scala/util/grammar/ConsRHS
	ireturn
  Labels:

public java.lang.Object productElement(int);
  Signature: (I)Ljava/lang/Object;
  Code:
   Stack=3, Locals=4, Args_size=2
	iload_1
	tableswitch{ //0 to 1
		0: 51;
		1: 39;
		default: 24 }
	new	class java/lang/IndexOutOfBoundsException
	dup
	iload_1
	invokestatic	Method scala/runtime/BoxesRunTime.boxToInteger:(I)Ljava/lang/Integer;
	invokevirtual	Method java/lang/Object.toString:()Ljava/lang/String;
	invokespecial	Method java/lang/IndexOutOfBoundsException."<init>":(Ljava/lang/String;)V
	athrow
	aload_0
	invokevirtual	Method hnt:()I
	istore_2
	iload_2
	invokestatic	Method scala/runtime/BoxesRunTime.boxToInteger:(I)Ljava/lang/Integer;
	goto	l1 // areturn
	aload_0
	invokevirtual	Method tnt:()I
	istore_3
	iload_3
	invokestatic	Method scala/runtime/BoxesRunTime.boxToInteger:(I)Ljava/lang/Integer;
l1	areturn
  Labels:
   	l1 = 60 // areturn

public int productArity();
  Signature: ()I
  Code:
   Stack=1, Locals=1, Args_size=1
	iconst_2
	ireturn
  Labels:

public java.lang.String productPrefix();
  Signature: ()Ljava/lang/String;
  Code:
   Stack=1, Locals=1, Args_size=1
	ldc	String ConsRHS
	areturn
  Labels:

public boolean equals(java.lang.Object);
  Signature: (Ljava/lang/Object;)Z
  Code:
   Stack=3, Locals=5, Args_size=2
	aload_0
	aload_1
	if_acmpeq	l1 // iconst_1
	aload_1
	instanceof	class scala/util/grammar/ConsRHS
	ifeq	l2 // iconst_0
	aload_1
	checkcast	class scala/util/grammar/ConsRHS
	astore_2
	aload_2
	invokevirtual	Method tnt:()I
	istore_3
	aload_2
	invokevirtual	Method hnt:()I
	istore	4
	aload_0
	iload_3
	iload	4
	invokespecial	Method gd1$1:(II)Z
	ifeq	l3 // iconst_0
	aload_1
	checkcast	class scala/util/grammar/ConsRHS
	aload_0
	invokeinterface	InterfaceMethod scala/Equals.canEqual:(Ljava/lang/Object;)Z
	goto	l4 // ifeq
l3	iconst_0
	goto	l4 // ifeq
l2	iconst_0
l4	ifeq	l5 // iconst_0
l1	iconst_1
	goto	l6 // ireturn
l5	iconst_0
l6	ireturn
  Labels:
   	l3 = 51 // iconst_0
   	l2 = 55 // iconst_0
   	l4 = 56 // ifeq
   	l1 = 59 // iconst_1
   	l5 = 63 // iconst_0
   	l6 = 64 // ireturn
  LocalVariableTable: 
   Start  Length  Slot  Name   Signature
   0      65      0    this       Lscala/util/grammar/ConsRHS;
   17      38      2    temp2       Lscala/util/grammar/ConsRHS;
   22      33      3    temp3       I
   28      27      4    temp4       I


public java.lang.String toString();
  Signature: ()Ljava/lang/String;
  Code:
   Stack=2, Locals=1, Args_size=1
	getstatic	Field scala/runtime/ScalaRunTime$.MODULE$:Lscala/runtime/ScalaRunTime$;
	aload_0
	invokevirtual	Method scala/runtime/ScalaRunTime$._toString:(Lscala/Product;)Ljava/lang/String;
	areturn
  Labels:

public int hashCode();
  Signature: ()I
  Code:
   Stack=2, Locals=1, Args_size=1
	getstatic	Field scala/runtime/ScalaRunTime$.MODULE$:Lscala/runtime/ScalaRunTime$;
	aload_0
	invokevirtual	Method scala/runtime/ScalaRunTime$._hashCode:(Lscala/Product;)I
	ireturn
  Labels:

public scala.util.grammar.ConsRHS copy(int, int);
  Signature: (II)Lscala/util/grammar/ConsRHS;
  Code:
   Stack=4, Locals=3, Args_size=3
	new	class scala/util/grammar/ConsRHS
	dup
	iload_1
	iload_2
	invokespecial	Method "<init>":(II)V
	areturn
  Labels:
  LocalVariableTable: 
   Start  Length  Slot  Name   Signature
   0      10      0    this       Lscala/util/grammar/ConsRHS;
   0      10      1    tnt       I
   0      10      2    hnt       I


public int hnt();
  Signature: ()I
  Code:
   Stack=1, Locals=1, Args_size=1
	aload_0
	getfield	Field hnt:I
	ireturn
  Labels:

public int tnt();
  Signature: ()I
  Code:
   Stack=1, Locals=1, Args_size=1
	aload_0
	getfield	Field tnt:I
	ireturn
  Labels:

public int copy$default$1();
  Signature: ()I
  Code:
   Stack=1, Locals=1, Args_size=1
	aload_0
	invokevirtual	Method tnt:()I
	ireturn
  Labels:

public int copy$default$2();
  Signature: ()I
  Code:
   Stack=1, Locals=1, Args_size=1
	aload_0
	invokevirtual	Method hnt:()I
	ireturn
  Labels:

public scala.collection.Iterator productElements();
  Signature: ()Lscala/collection/Iterator;
  Code:
   Stack=1, Locals=1, Args_size=1
	aload_0
	invokestatic	Method scala/Product$class.productElements:(Lscala/Product;)Lscala/collection/Iterator;
	areturn
  Labels:
  Deprecated: true

public scala.collection.Iterator productIterator();
  Signature: ()Lscala/collection/Iterator;
  Code:
   Stack=1, Locals=1, Args_size=1
	aload_0
	invokestatic	Method scala/Product$class.productIterator:(Lscala/Product;)Lscala/collection/Iterator;
	areturn
  Labels:

}

