Compiled from "HedgeRHS.scala"
public final class scala.util.grammar.EmptyHedgeRHS extends java.lang.Object
  SourceFile: "HedgeRHS.scala"
  ScalaSig: length = 0x3
   05 00 00 
  RuntimeVisibleAnnotations: length = 0xB
   00 01 00 27 00 01 00 28 73 00 29 
  minor version: 0
  major version: 49
  Constant pool:
Asciz	SourceFile;
Asciz	HedgeRHS.scala;
Asciz	productElements;
Asciz	()Lscala/collection/Iterator;;
Asciz	Code;
Asciz	scala/util/grammar/EmptyHedgeRHS$;
class	scala/util/grammar/EmptyHedgeRHS$
Asciz	MODULE$;
Asciz	Lscala/util/grammar/EmptyHedgeRHS$;;
NameAndType	MODULE$:Lscala/util/grammar/EmptyHedgeRHS$;
Field	scala/util/grammar/EmptyHedgeRHS$.MODULE$:Lscala/util/grammar/EmptyHedgeRHS$;
NameAndType	productElements:()Lscala/collection/Iterator;
Method	scala/util/grammar/EmptyHedgeRHS$.productElements:()Lscala/collection/Iterator;
Asciz	Deprecated;
Asciz	productIterator;
NameAndType	productIterator:()Lscala/collection/Iterator;
Method	scala/util/grammar/EmptyHedgeRHS$.productIterator:()Lscala/collection/Iterator;
Asciz	productElementName;
Asciz	(I)Ljava/lang/String;;
NameAndType	productElementName:(I)Ljava/lang/String;
Method	scala/util/grammar/EmptyHedgeRHS$.productElementName:(I)Ljava/lang/String;
Asciz	canEqual;
Asciz	(Ljava/lang/Object;)Z;
NameAndType	canEqual:(Ljava/lang/Object;)Z
Method	scala/util/grammar/EmptyHedgeRHS$.canEqual:(Ljava/lang/Object;)Z
Asciz	productElement;
Asciz	(I)Ljava/lang/Object;;
NameAndType	productElement:(I)Ljava/lang/Object;
Method	scala/util/grammar/EmptyHedgeRHS$.productElement:(I)Ljava/lang/Object;
Asciz	productArity;
Asciz	()I;
NameAndType	productArity:()I
Method	scala/util/grammar/EmptyHedgeRHS$.productArity:()I
Asciz	productPrefix;
Asciz	()Ljava/lang/String;;
NameAndType	productPrefix:()Ljava/lang/String;
Method	scala/util/grammar/EmptyHedgeRHS$.productPrefix:()Ljava/lang/String;
Asciz	ScalaSig;
Asciz	Lscala/reflect/ScalaSignature;;
Asciz	bytes;
Asciz	!;Q!\t&\tQ\"R7qifDU\rZ4f%\"&BA9'/Y7nCJT!!\tU$)1oY1mCCa\t\tRQk^=IK<WM%T'Ya\"E)yB\t!AU\rZ4f%\"C\n1B-6-7b\nTWm;I1BA&o3vGRDQ!Gi\taP5oSRtD#A\tqYA!AFu\t^8TiJLgn=AqJA)EIYtwMC$QM^1\n#AB*ue&tw\r(\t\")5(o3vGR&/4jqV\ta+\t\",1(o3vGR%/;z+aC\n.\tqcAAJ]RDM%\t%MaJ|G-^2u2,W.8u)\tTg%AG:Lb0\rLq\n\tII\rg.R9vC2$\"AOIYBun7fC:DqAN!@\t\"A-X-3SKN|GN^3\"a\"\n\r#AB(cUGB!CRAb]3sSdN_1cY;
Asciz	RuntimeVisibleAnnotations;
Asciz	scala/util/grammar/EmptyHedgeRHS;
class	scala/util/grammar/EmptyHedgeRHS
Asciz	java/lang/Object;
class	java/lang/Object

{
public static final scala.collection.Iterator productElements();
  Signature: ()Lscala/collection/Iterator;
  Code:
   Stack=1, Locals=0, Args_size=0
	getstatic	Field scala/util/grammar/EmptyHedgeRHS$.MODULE$:Lscala/util/grammar/EmptyHedgeRHS$;
	invokevirtual	Method scala/util/grammar/EmptyHedgeRHS$.productElements:()Lscala/collection/Iterator;
	areturn
  Labels:
  Deprecated: true

public static final scala.collection.Iterator productIterator();
  Signature: ()Lscala/collection/Iterator;
  Code:
   Stack=1, Locals=0, Args_size=0
	getstatic	Field scala/util/grammar/EmptyHedgeRHS$.MODULE$:Lscala/util/grammar/EmptyHedgeRHS$;
	invokevirtual	Method scala/util/grammar/EmptyHedgeRHS$.productIterator:()Lscala/collection/Iterator;
	areturn
  Labels:

public static final java.lang.String productElementName(int);
  Signature: (I)Ljava/lang/String;
  Code:
   Stack=2, Locals=1, Args_size=1
	getstatic	Field scala/util/grammar/EmptyHedgeRHS$.MODULE$:Lscala/util/grammar/EmptyHedgeRHS$;
	iload_0
	invokevirtual	Method scala/util/grammar/EmptyHedgeRHS$.productElementName:(I)Ljava/lang/String;
	areturn
  Labels:

public static final boolean canEqual(java.lang.Object);
  Signature: (Ljava/lang/Object;)Z
  Code:
   Stack=2, Locals=1, Args_size=1
	getstatic	Field scala/util/grammar/EmptyHedgeRHS$.MODULE$:Lscala/util/grammar/EmptyHedgeRHS$;
	aload_0
	invokevirtual	Method scala/util/grammar/EmptyHedgeRHS$.canEqual:(Ljava/lang/Object;)Z
	ireturn
  Labels:

public static final java.lang.Object productElement(int);
  Signature: (I)Ljava/lang/Object;
  Code:
   Stack=2, Locals=1, Args_size=1
	getstatic	Field scala/util/grammar/EmptyHedgeRHS$.MODULE$:Lscala/util/grammar/EmptyHedgeRHS$;
	iload_0
	invokevirtual	Method scala/util/grammar/EmptyHedgeRHS$.productElement:(I)Ljava/lang/Object;
	areturn
  Labels:

public static final int productArity();
  Signature: ()I
  Code:
   Stack=1, Locals=0, Args_size=0
	getstatic	Field scala/util/grammar/EmptyHedgeRHS$.MODULE$:Lscala/util/grammar/EmptyHedgeRHS$;
	invokevirtual	Method scala/util/grammar/EmptyHedgeRHS$.productArity:()I
	ireturn
  Labels:

public static final java.lang.String productPrefix();
  Signature: ()Ljava/lang/String;
  Code:
   Stack=1, Locals=0, Args_size=0
	getstatic	Field scala/util/grammar/EmptyHedgeRHS$.MODULE$:Lscala/util/grammar/EmptyHedgeRHS$;
	invokevirtual	Method scala/util/grammar/EmptyHedgeRHS$.productPrefix:()Ljava/lang/String;
	areturn
  Labels:

}

