Compiled from "TreeRHS.scala"
public class scala.util.grammar.LabelledRHS extends scala.util.grammar.TreeRHS implements scala.ScalaObject,scala.Product,java.io.Serializable
  SourceFile: "TreeRHS.scala"
  Signature: length = 0x2
   00 7B 
  ScalaSig: length = 0x471
   05 00 FFFFFF81 23 06 04 01 02 40 09 02 0B 4C 61 62 65
   6C 6C 65 64 52 48 53 0A 02 03 04 01 07 67 72 61
   6D 6D 61 72 0A 02 05 06 01 04 75 74 69 6C 0A 01
   07 01 05 73 63 61 6C 61 03 00 15 02 0A 1B 13 04
   00 0B 0F 13 10 02 0C 0D 0D 01 02 09 02 0E 02 02
   07 54 72 65 65 52 48 53 10 02 10 11 0D 01 06 09
   02 12 06 02 0B 53 63 61 6C 61 4F 62 6A 65 63 74
   10 02 10 14 09 02 15 06 02 07 50 72 6F 64 75 63
   74 08 08 17 00 FFFFFF82 FFFFFFCA FFFFFF80 FFFFFF84 00 18 01 05 6C 61 62
   65 6C 15 01 19 10 02 1A 1B 0C 00 04 08 1C 00 FFFFFF84
   FFFFFF80 FFFFFF80 FFFFFFC2 00 1D 02 01 41 11 02 1E 21 10 02 10 1F
   09 02 20 06 02 07 4E 6F 74 68 69 6E 67 10 02 10
   22 09 02 23 06 02 03 41 6E 79 08 08 25 00 FFFFFF82 FFFFFF88
   FFFFFFA0 FFFFFF80 04 19 01 06 6C 61 62 65 6C 20 08 08 27 00
   FFFFFF82 FFFFFFCA FFFFFF80 FFFFFF84 00 28 01 03 68 6E 74 15 01 29 10 02
   10 2A 09 02 2B 06 02 03 49 6E 74 08 08 2D 00 FFFFFF82
   FFFFFF88 FFFFFFA0 FFFFFF80 04 29 01 04 68 6E 74 20 08 05 2F 00 FFFFFF84
   00 30 01 06 3C 69 6E 69 74 3E 14 03 31 32 33 10
   03 0C 00 19 08 05 17 2E FFFFFFC0 00 19 08 05 27 2E FFFFFFC0
   00 29 08 07 35 00 FFFFFF81 FFFFFF80 FFFFFF84 00 36 01 04 63 6F 70
   79 15 02 37 3A 14 03 38 3B 3C 10 03 0C 00 39 10
   02 1A 3A 04 08 1C 34 FFFFFF84 FFFFFF80 FFFFFF80 FFFFFFC2 00 1D 08 07 17
   34 FFFFFF90 FFFFFF80 FFFFFFC0 00 39 08 07 27 34 FFFFFF90 FFFFFF80 FFFFFFC0 00 29 08
   07 3E 00 FFFFFF91 FFFFFF80 FFFFFF84 00 3F 01 0E 63 6F 70 79 24 64
   65 66 61 75 6C 74 24 31 15 02 40 4A 2A 02 19 41
   2B 01 42 10 02 43 48 0D 01 44 0A 02 45 46 01 09
   75 6E 63 68 65 63 6B 65 64 0A 02 47 06 01 0A 61
   6E 6E 6F 74 61 74 69 6F 6E 09 02 49 44 02 11 75
   6E 63 68 65 63 6B 65 64 56 61 72 69 61 6E 63 65
   04 08 1C 3D FFFFFF84 FFFFFF80 FFFFFF80 FFFFFFC2 00 1D 08 07 4C 00 FFFFFF91 FFFFFF80
   FFFFFF84 00 4D 01 0E 63 6F 70 79 24 64 65 66 61 75 6C
   74 24 32 15 02 4E 4F 2A 02 29 41 04 08 1C 4B FFFFFF84
   FFFFFF80 FFFFFF80 FFFFFFC2 00 1D 08 08 51 00 FFFFFF84 FFFFFF80 FFFFFF80 FFFFFF84 20 52 01
   08 68 61 73 68 43 6F 64 65 14 01 29 08 08 54 00
   FFFFFF84 FFFFFF80 FFFFFF80 FFFFFF84 20 55 01 08 74 6F 53 74 72 69 6E 67
   14 01 56 10 02 57 5A 0E 02 10 58 09 02 59 06 01
   06 50 72 65 64 65 66 09 02 5B 5C 02 06 53 74 72
   69 6E 67 0A 02 59 06 08 08 5E 00 FFFFFF84 FFFFFF80 FFFFFF80 FFFFFF84 20
   5F 01 06 65 71 75 61 6C 73 14 02 60 63 10 02 10
   61 09 02 62 06 02 07 42 6F 6F 6C 65 61 6E 08 07
   64 5D FFFFFF81 FFFFFF80 FFFFFFC0 00 21 01 03 78 24 31 08 08 66 00
   FFFFFF84 FFFFFF80 FFFFFF80 FFFFFF84 20 67 01 0D 70 72 6F 64 75 63 74 50
   72 65 66 69 78 15 01 68 10 02 69 6E 0D 01 6A 0A
   02 6B 6C 01 04 6C 61 6E 67 0A 01 6D 01 04 6A 61
   76 61 09 02 5B 6A 08 08 70 00 FFFFFF84 FFFFFF80 FFFFFF80 FFFFFF84 20 28
   01 0C 70 72 6F 64 75 63 74 41 72 69 74 79 08 08
   72 00 FFFFFF84 FFFFFF80 FFFFFF80 FFFFFF84 20 73 01 0E 70 72 6F 64 75 63
   74 45 6C 65 6D 65 6E 74 14 02 21 74 08 07 64 71
   FFFFFF81 FFFFFF80 FFFFFFC0 00 29 08 08 76 00 FFFFFF84 FFFFFF80 FFFFFF80 FFFFFF84 20 77 01
   12 70 72 6F 64 75 63 74 45 6C 65 6D 65 6E 74 4E
   61 6D 65 14 02 68 78 08 07 64 75 FFFFFF81 FFFFFF80 FFFFFFC0 00 29
   08 08 7A 00 FFFFFF84 FFFFFF80 FFFFFF80 FFFFFF84 20 7B 01 08 63 61 6E 45
   71 75 61 6C 14 02 60 7C 08 07 64 79 FFFFFF81 FFFFFF80 FFFFFFC0 00
   21 28 02 00 7E 10 02 10 7F 09 03 FFFFFF81 00 06 02 0C
   73 65 72 69 61 6C 69 7A 61 62 6C 65 07 09 FFFFFF81 02
   02 FFFFFF81 FFFFFF80 FFFFFF88 02 FFFFFF81 03 01 0B 4C 61 62 65 6C 6C 65
   64 52 48 53 10 03 0C FFFFFF81 04 06 09 01 02 FFFFFF84 FFFFFF81 FFFFFF80
   FFFFFF88 02 FFFFFF81 05 13 05 FFFFFF81 04 FFFFFF81 06 0F 10 03 69 FFFFFF81 07
   09 03 FFFFFF81 08 6A 02 06 4F 62 6A 65 63 74 08 07 2F
   FFFFFF81 04 FFFFFF84 00 FFFFFF81 0A 14 02 FFFFFF81 03 08 0A FFFFFF81 0C FFFFFF81 04
   FFFFFF81 FFFFFF80 FFFFFF84 40 FFFFFF81 0D 01 05 61 70 70 6C 79 15 04 FFFFFF81
   0E FFFFFF81 11 14 06 FFFFFF81 0F FFFFFF81 12 FFFFFF81 13 10 04 0C 00 FFFFFF81
   10 10 03 1A FFFFFF81 11 04 09 1C FFFFFF81 0B FFFFFF84 FFFFFF80 FFFFFF80 FFFFFFC2 00
   1D 08 07 17 FFFFFF81 0B FFFFFFC0 00 FFFFFF81 10 08 06 27 FFFFFF81 0B FFFFFFC0
   00 29 08 0A FFFFFF81 15 FFFFFF81 04 FFFFFF81 FFFFFF80 FFFFFF84 40 FFFFFF81 16 01 07
   75 6E 61 70 70 6C 79 15 04 FFFFFF81 17 FFFFFF81 1F 14 04 FFFFFF81
   18 FFFFFF81 20 10 05 10 FFFFFF81 19 FFFFFF81 1B 09 03 FFFFFF81 1A 06 02
   06 4F 70 74 69 6F 6E 10 06 10 FFFFFF81 1C FFFFFF81 1E 29 09
   03 FFFFFF81 1D 06 02 06 54 75 70 6C 65 32 10 03 1A FFFFFF81
   1F 04 09 1C FFFFFF81 14 FFFFFF84 FFFFFF80 FFFFFF80 FFFFFFC2 00 1D 08 08 FFFFFF81 21
   FFFFFF81 14 FFFFFFC0 00 FFFFFF81 22 01 03 78 24 30 10 04 0C 00 FFFFFF81
   1E 
  minor version: 0
  major version: 49
  Constant pool:
Asciz	SourceFile;
Asciz	TreeRHS.scala;
Asciz	hnt;
Asciz	I;
Asciz	label;
Asciz	Ljava/lang/Object;;
Asciz	TA;;
Asciz	Signature;
Asciz	productIterator;
Asciz	()Lscala/collection/Iterator;;
Asciz	Code;
Asciz	LineNumberTable;
Asciz	scala/Product$class;
class	scala/Product$class
Asciz	(Lscala/Product;)Lscala/collection/Iterator;;
NameAndType	productIterator:(Lscala/Product;)Lscala/collection/Iterator;
Method	scala/Product$class.productIterator:(Lscala/Product;)Lscala/collection/Iterator;
Asciz	productElements;
NameAndType	productElements:(Lscala/Product;)Lscala/collection/Iterator;
Method	scala/Product$class.productElements:(Lscala/Product;)Lscala/collection/Iterator;
Asciz	Deprecated;
Asciz	copy$default$2;
Asciz	()I;
Asciz	scala/util/grammar/LabelledRHS;
class	scala/util/grammar/LabelledRHS
NameAndType	hnt:()I
Method	scala/util/grammar/LabelledRHS.hnt:()I
Asciz	copy$default$1;
Asciz	()Ljava/lang/Object;;
NameAndType	label:()Ljava/lang/Object;
Method	scala/util/grammar/LabelledRHS.label:()Ljava/lang/Object;
NameAndType	label:Ljava/lang/Object;
Field	scala/util/grammar/LabelledRHS.label:Ljava/lang/Object;
Asciz	()TA;;
NameAndType	hnt:I
Field	scala/util/grammar/LabelledRHS.hnt:I
Asciz	copy;
Asciz	(Ljava/lang/Object;I)Lscala/util/grammar/LabelledRHS;;
Asciz	<init>;
Asciz	(Ljava/lang/Object;I)V;
NameAndType	"<init>":(Ljava/lang/Object;I)V
Method	scala/util/grammar/LabelledRHS."<init>":(Ljava/lang/Object;I)V
Asciz	this;
Asciz	Lscala/util/grammar/LabelledRHS;;
Asciz	LocalVariableTable;
Asciz	hashCode;
Asciz	scala/runtime/ScalaRunTime$;
class	scala/runtime/ScalaRunTime$
Asciz	MODULE$;
Asciz	Lscala/runtime/ScalaRunTime$;;
NameAndType	MODULE$:Lscala/runtime/ScalaRunTime$;
Field	scala/runtime/ScalaRunTime$.MODULE$:Lscala/runtime/ScalaRunTime$;
Asciz	_hashCode;
Asciz	(Lscala/Product;)I;
NameAndType	_hashCode:(Lscala/Product;)I
Method	scala/runtime/ScalaRunTime$._hashCode:(Lscala/Product;)I
Asciz	toString;
Asciz	()Ljava/lang/String;;
Asciz	_toString;
Asciz	(Lscala/Product;)Ljava/lang/String;;
NameAndType	_toString:(Lscala/Product;)Ljava/lang/String;
Method	scala/runtime/ScalaRunTime$._toString:(Lscala/Product;)Ljava/lang/String;
Asciz	equals;
Asciz	(Ljava/lang/Object;)Z;
Asciz	gd1$1;
Asciz	(Ljava/lang/Object;I)Z;
NameAndType	gd1$1:(Ljava/lang/Object;I)Z
Method	scala/util/grammar/LabelledRHS.gd1$1:(Ljava/lang/Object;I)Z
Asciz	scala/Equals;
class	scala/Equals
Asciz	canEqual;
NameAndType	canEqual:(Ljava/lang/Object;)Z
InterfaceMethod	scala/Equals.canEqual:(Ljava/lang/Object;)Z
Asciz	temp2;
Asciz	temp3;
Asciz	temp4;
Asciz	productPrefix;
Asciz	LabelledRHS;
String	LabelledRHS
Asciz	productArity;
Asciz	productElement;
Asciz	(I)Ljava/lang/Object;;
Asciz	java/lang/IndexOutOfBoundsException;
class	java/lang/IndexOutOfBoundsException
Asciz	scala/runtime/BoxesRunTime;
class	scala/runtime/BoxesRunTime
Asciz	boxToInteger;
Asciz	(I)Ljava/lang/Integer;;
NameAndType	boxToInteger:(I)Ljava/lang/Integer;
Method	scala/runtime/BoxesRunTime.boxToInteger:(I)Ljava/lang/Integer;
Asciz	java/lang/Object;
class	java/lang/Object
NameAndType	toString:()Ljava/lang/String;
Method	java/lang/Object.toString:()Ljava/lang/String;
Asciz	(Ljava/lang/String;)V;
NameAndType	"<init>":(Ljava/lang/String;)V
Method	java/lang/IndexOutOfBoundsException."<init>":(Ljava/lang/String;)V
Asciz	productElementName;
Asciz	(I)Ljava/lang/String;;
String	hnt
String	label
Asciz	java/lang/Number;
class	java/lang/Number
Asciz	java/lang/Character;
class	java/lang/Character
Asciz	equals2;
Asciz	(Ljava/lang/Object;Ljava/lang/Object;)Z;
NameAndType	equals2:(Ljava/lang/Object;Ljava/lang/Object;)Z
Method	scala/runtime/BoxesRunTime.equals2:(Ljava/lang/Object;Ljava/lang/Object;)Z
NameAndType	equals:(Ljava/lang/Object;)Z
Method	java/lang/Object.equals:(Ljava/lang/Object;)Z
Asciz	y0;
Asciz	scala/util/grammar/TreeRHS;
class	scala/util/grammar/TreeRHS
Asciz	()V;
NameAndType	"<init>":()V
Method	scala/util/grammar/TreeRHS."<init>":()V
Asciz	$init$;
Asciz	(Lscala/Product;)V;
NameAndType	$init$:(Lscala/Product;)V
Method	scala/Product$class.$init$:(Lscala/Product;)V
Asciz	(TA;I)V;
Asciz	<A:Ljava/lang/Object;>Lscala/util/grammar/TreeRHS;Lscala/ScalaObject;Lscala/Product;;
Asciz	ScalaSig;
Asciz	scala/ScalaObject;
class	scala/ScalaObject
Asciz	scala/Product;
class	scala/Product
Asciz	java/io/Serializable;
class	java/io/Serializable

{
private final int hnt;
  Signature: I

private final java.lang.Object label;
  Signature: Ljava/lang/Object;
  Signature: length = 0x2
   00 07 

public scala.collection.Iterator productIterator();
  Signature: ()Lscala/collection/Iterator;
  Code:
   Stack=1, Locals=1, Args_size=1
	aload_0
	invokestatic	Method scala/Product$class.productIterator:(Lscala/Product;)Lscala/collection/Iterator;
	areturn
  Labels:

public scala.collection.Iterator productElements();
  Signature: ()Lscala/collection/Iterator;
  Code:
   Stack=1, Locals=1, Args_size=1
	aload_0
	invokestatic	Method scala/Product$class.productElements:(Lscala/Product;)Lscala/collection/Iterator;
	areturn
  Labels:
  Deprecated: true

public int copy$default$2();
  Signature: ()I
  Code:
   Stack=1, Locals=1, Args_size=1
	aload_0
	invokevirtual	Method hnt:()I
	ireturn
  Labels:

public java.lang.Object copy$default$1();
  Signature: ()Ljava/lang/Object;
  Code:
   Stack=1, Locals=1, Args_size=1
	aload_0
	invokevirtual	Method label:()Ljava/lang/Object;
	areturn
  Labels:

public java.lang.Object label();
  Signature: ()Ljava/lang/Object;
  Code:
   Stack=1, Locals=1, Args_size=1
	aload_0
	getfield	Field label:Ljava/lang/Object;
	areturn
  Labels:
  Signature: length = 0x2
   00 22 

public int hnt();
  Signature: ()I
  Code:
   Stack=1, Locals=1, Args_size=1
	aload_0
	getfield	Field hnt:I
	ireturn
  Labels:

public scala.util.grammar.LabelledRHS copy(java.lang.Object, int);
  Signature: (Ljava/lang/Object;I)Lscala/util/grammar/LabelledRHS;
  Code:
   Stack=4, Locals=3, Args_size=3
	new	class scala/util/grammar/LabelledRHS
	dup
	aload_1
	iload_2
	invokespecial	Method "<init>":(Ljava/lang/Object;I)V
	areturn
  Labels:
  LocalVariableTable: 
   Start  Length  Slot  Name   Signature
   0      10      0    this       Lscala/util/grammar/LabelledRHS;
   0      10      1    label       Ljava/lang/Object;
   0      10      2    hnt       I


public int hashCode();
  Signature: ()I
  Code:
   Stack=2, Locals=1, Args_size=1
	getstatic	Field scala/runtime/ScalaRunTime$.MODULE$:Lscala/runtime/ScalaRunTime$;
	aload_0
	invokevirtual	Method scala/runtime/ScalaRunTime$._hashCode:(Lscala/Product;)I
	ireturn
  Labels:

public java.lang.String toString();
  Signature: ()Ljava/lang/String;
  Code:
   Stack=2, Locals=1, Args_size=1
	getstatic	Field scala/runtime/ScalaRunTime$.MODULE$:Lscala/runtime/ScalaRunTime$;
	aload_0
	invokevirtual	Method scala/runtime/ScalaRunTime$._toString:(Lscala/Product;)Ljava/lang/String;
	areturn
  Labels:

public boolean equals(java.lang.Object);
  Signature: (Ljava/lang/Object;)Z
  Code:
   Stack=3, Locals=5, Args_size=2
	aload_0
	aload_1
	if_acmpeq	l1 // iconst_1
	aload_1
	instanceof	class scala/util/grammar/LabelledRHS
	ifeq	l2 // iconst_0
	aload_1
	checkcast	class scala/util/grammar/LabelledRHS
	astore_2
	aload_2
	invokevirtual	Method label:()Ljava/lang/Object;
	astore_3
	aload_2
	invokevirtual	Method hnt:()I
	istore	4
	aload_0
	aload_3
	iload	4
	invokespecial	Method gd1$1:(Ljava/lang/Object;I)Z
	ifeq	l3 // iconst_0
	aload_1
	checkcast	class scala/util/grammar/LabelledRHS
	aload_0
	invokeinterface	InterfaceMethod scala/Equals.canEqual:(Ljava/lang/Object;)Z
	goto	l4 // ifeq
l3	iconst_0
	goto	l4 // ifeq
l2	iconst_0
l4	ifeq	l5 // iconst_0
l1	iconst_1
	goto	l6 // ireturn
l5	iconst_0
l6	ireturn
  Labels:
   	l3 = 51 // iconst_0
   	l2 = 55 // iconst_0
   	l4 = 56 // ifeq
   	l1 = 59 // iconst_1
   	l5 = 63 // iconst_0
   	l6 = 64 // ireturn
  LocalVariableTable: 
   Start  Length  Slot  Name   Signature
   0      65      0    this       Lscala/util/grammar/LabelledRHS;
   17      38      2    temp2       Lscala/util/grammar/LabelledRHS;
   22      33      3    temp3       Ljava/lang/Object;
   28      27      4    temp4       I


public java.lang.String productPrefix();
  Signature: ()Ljava/lang/String;
  Code:
   Stack=1, Locals=1, Args_size=1
	ldc	String LabelledRHS
	areturn
  Labels:

public int productArity();
  Signature: ()I
  Code:
   Stack=1, Locals=1, Args_size=1
	iconst_2
	ireturn
  Labels:

public java.lang.Object productElement(int);
  Signature: (I)Ljava/lang/Object;
  Code:
   Stack=3, Locals=3, Args_size=2
	iload_1
	tableswitch{ //0 to 1
		0: 51;
		1: 39;
		default: 24 }
	new	class java/lang/IndexOutOfBoundsException
	dup
	iload_1
	invokestatic	Method scala/runtime/BoxesRunTime.boxToInteger:(I)Ljava/lang/Integer;
	invokevirtual	Method java/lang/Object.toString:()Ljava/lang/String;
	invokespecial	Method java/lang/IndexOutOfBoundsException."<init>":(Ljava/lang/String;)V
	athrow
	aload_0
	invokevirtual	Method hnt:()I
	istore_2
	iload_2
	invokestatic	Method scala/runtime/BoxesRunTime.boxToInteger:(I)Ljava/lang/Integer;
	goto	l1 // areturn
	aload_0
	invokevirtual	Method label:()Ljava/lang/Object;
l1	areturn
  Labels:
   	l1 = 55 // areturn

public java.lang.String productElementName(int);
  Signature: (I)Ljava/lang/String;
  Code:
   Stack=3, Locals=2, Args_size=2
	iload_1
	tableswitch{ //0 to 1
		0: 44;
		1: 39;
		default: 24 }
	new	class java/lang/IndexOutOfBoundsException
	dup
	iload_1
	invokestatic	Method scala/runtime/BoxesRunTime.boxToInteger:(I)Ljava/lang/Integer;
	invokevirtual	Method java/lang/Object.toString:()Ljava/lang/String;
	invokespecial	Method java/lang/IndexOutOfBoundsException."<init>":(Ljava/lang/String;)V
	athrow
	ldc	String hnt
	goto	l1 // areturn
	ldc	String label
l1	areturn
  Labels:
   	l1 = 46 // areturn

public boolean canEqual(java.lang.Object);
  Signature: (Ljava/lang/Object;)Z
  Code:
   Stack=1, Locals=2, Args_size=2
	aload_1
	instanceof	class scala/util/grammar/LabelledRHS
	ireturn
  Labels:

private final boolean gd1$1(java.lang.Object, int);
  Signature: (Ljava/lang/Object;I)Z
  Code:
   Stack=2, Locals=4, Args_size=3
	aload_0
	invokevirtual	Method label:()Ljava/lang/Object;
	astore_3
	aload_1
	aload_3
	if_acmpne	l1 // aload_1
	iconst_1
	goto	l2 // ifeq
l1	aload_1
	ifnonnull	l3 // aload_1
	iconst_0
	goto	l2 // ifeq
l3	aload_1
	instanceof	class java/lang/Number
	ifne	l4 // aload_1
	aload_1
	instanceof	class java/lang/Character
	ifeq	l5 // aload_1
l4	aload_1
	aload_3
	invokestatic	Method scala/runtime/BoxesRunTime.equals2:(Ljava/lang/Object;Ljava/lang/Object;)Z
	goto	l2 // ifeq
l5	aload_1
	aload_3
	invokevirtual	Method java/lang/Object.equals:(Ljava/lang/Object;)Z
l2	ifeq	l6 // iconst_0
	iload_2
	aload_0
	invokevirtual	Method hnt:()I
	if_icmpne	l6 // iconst_0
	iconst_1
	goto	l7 // ireturn
l6	iconst_0
l7	ireturn
  Labels:
   	l1 = 14 // aload_1
   	l3 = 22 // aload_1
   	l4 = 36 // aload_1
   	l5 = 44 // aload_1
   	l2 = 49 // ifeq
   	l6 = 64 // iconst_0
   	l7 = 65 // ireturn
  LocalVariableTable: 
   Start  Length  Slot  Name   Signature
   0      66      0    this       Lscala/util/grammar/LabelledRHS;
   10      42      3    y0       Ljava/lang/Object;


public scala.util.grammar.LabelledRHS(java.lang.Object, int);
  Signature: (Ljava/lang/Object;I)V
  Code:
   Stack=2, Locals=3, Args_size=3
	aload_0
	aload_1
	putfield	Field label:Ljava/lang/Object;
	aload_0
	iload_2
	putfield	Field hnt:I
	aload_0
	invokespecial	Method scala/util/grammar/TreeRHS."<init>":()V
	aload_0
	invokestatic	Method scala/Product$class.$init$:(Lscala/Product;)V
	return
  Labels:
  LocalVariableTable: 
   Start  Length  Slot  Name   Signature
   0      19      0    this       Lscala/util/grammar/LabelledRHS;
   0      19      1    label       Ljava/lang/Object;
   0      19      2    hnt       I

  Signature: length = 0x2
   00 7A 

}

