Compiled from "TreeRHS.scala"
public final class scala.util.grammar.LabelledRHS$ extends java.lang.Object implements scala.ScalaObject
  SourceFile: "TreeRHS.scala"
  Scala: length = 0x
   
  minor version: 0
  major version: 49
  Constant pool:
const #1 = Asciz	SourceFile;
const #2 = Asciz	TreeRHS.scala;
const #3 = Asciz	Scala;
const #4 = Asciz	MODULE$;
const #5 = Asciz	Lscala/util/grammar/LabelledRHS$;;
const #6 = Asciz	<clinit>;
const #7 = Asciz	()V;
const #8 = Asciz	Code;
const #9 = Asciz	scala/util/grammar/LabelledRHS$;
const #10 = class	#9;	//  scala/util/grammar/LabelledRHS$
const #11 = Asciz	<init>;
const #12 = NameAndType	#11:#7;//  "<init>":()V
const #13 = Method	#10.#12;	//  scala/util/grammar/LabelledRHS$."<init>":()V
const #14 = Asciz	LineNumberTable;
const #15 = Asciz	java/lang/Object;
const #16 = class	#15;	//  java/lang/Object
const #17 = Method	#16.#12;	//  java/lang/Object."<init>":()V
const #18 = NameAndType	#4:#5;//  MODULE$:Lscala/util/grammar/LabelledRHS$;
const #19 = Field	#10.#18;	//  scala/util/grammar/LabelledRHS$.MODULE$:Lscala/util/grammar/LabelledRHS$;
const #20 = Asciz	apply;
const #21 = Asciz	(Ljava/lang/Object;I)Lscala/util/grammar/LabelledRHS;;
const #22 = Asciz	scala/util/grammar/LabelledRHS;
const #23 = class	#22;	//  scala/util/grammar/LabelledRHS
const #24 = Asciz	(Ljava/lang/Object;I)V;
const #25 = NameAndType	#11:#24;//  "<init>":(Ljava/lang/Object;I)V
const #26 = Method	#23.#25;	//  scala/util/grammar/LabelledRHS."<init>":(Ljava/lang/Object;I)V
const #27 = Asciz	this;
const #28 = Asciz	label;
const #29 = Asciz	Ljava/lang/Object;;
const #30 = Asciz	hnt;
const #31 = Asciz	I;
const #32 = Asciz	LocalVariableTable;
const #33 = Asciz	unapply;
const #34 = Asciz	(Lscala/util/grammar/LabelledRHS;)Lscala/Some;;
const #35 = Asciz	scala/Some;
const #36 = class	#35;	//  scala/Some
const #37 = Asciz	scala/Tuple2;
const #38 = class	#37;	//  scala/Tuple2
const #39 = Asciz	()Ljava/lang/Object;;
const #40 = NameAndType	#28:#39;//  label:()Ljava/lang/Object;
const #41 = Method	#23.#40;	//  scala/util/grammar/LabelledRHS.label:()Ljava/lang/Object;
const #42 = Asciz	()I;
const #43 = NameAndType	#30:#42;//  hnt:()I
const #44 = Method	#23.#43;	//  scala/util/grammar/LabelledRHS.hnt:()I
const #45 = Asciz	scala/runtime/BoxesRunTime;
const #46 = class	#45;	//  scala/runtime/BoxesRunTime
const #47 = Asciz	boxToInteger;
const #48 = Asciz	(I)Ljava/lang/Integer;;
const #49 = NameAndType	#47:#48;//  boxToInteger:(I)Ljava/lang/Integer;
const #50 = Method	#46.#49;	//  scala/runtime/BoxesRunTime.boxToInteger:(I)Ljava/lang/Integer;
const #51 = Asciz	(Ljava/lang/Object;Ljava/lang/Object;)V;
const #52 = NameAndType	#11:#51;//  "<init>":(Ljava/lang/Object;Ljava/lang/Object;)V
const #53 = Method	#38.#52;	//  scala/Tuple2."<init>":(Ljava/lang/Object;Ljava/lang/Object;)V
const #54 = Asciz	(Ljava/lang/Object;)V;
const #55 = NameAndType	#11:#54;//  "<init>":(Ljava/lang/Object;)V
const #56 = Method	#36.#55;	//  scala/Some."<init>":(Ljava/lang/Object;)V
const #57 = Asciz	x$0;
const #58 = Asciz	Lscala/util/grammar/LabelledRHS;;
const #59 = Asciz	scala/ScalaObject;
const #60 = class	#59;	//  scala/ScalaObject

{
public static final scala.util.grammar.LabelledRHS$ MODULE$;

public static {};
  Code:
   Stack=1, Locals=0, Args_size=0
   0:	new	#10; //class scala/util/grammar/LabelledRHS$
   3:	invokespecial	#13; //Method "<init>":()V
   6:	return

public scala.util.grammar.LabelledRHS apply(java.lang.Object, int);
  Code:
   Stack=4, Locals=3, Args_size=3
   0:	new	#23; //class scala/util/grammar/LabelledRHS
   3:	dup
   4:	aload_1
   5:	iload_2
   6:	invokespecial	#26; //Method scala/util/grammar/LabelledRHS."<init>":(Ljava/lang/Object;I)V
   9:	areturn
  LineNumberTable: 
   line 18: 0

  LocalVariableTable: 
   Start  Length  Slot  Name   Signature
   0      10      0    this       Lscala/util/grammar/LabelledRHS$;
   0      10      1    label       Ljava/lang/Object;
   0      10      2    hnt       I


public scala.Some unapply(scala.util.grammar.LabelledRHS);
  Code:
   Stack=6, Locals=2, Args_size=2
   0:	new	#36; //class scala/Some
   3:	dup
   4:	new	#38; //class scala/Tuple2
   7:	dup
   8:	aload_1
   9:	invokevirtual	#41; //Method scala/util/grammar/LabelledRHS.label:()Ljava/lang/Object;
   12:	aload_1
   13:	invokevirtual	#44; //Method scala/util/grammar/LabelledRHS.hnt:()I
   16:	invokestatic	#50; //Method scala/runtime/BoxesRunTime.boxToInteger:(I)Ljava/lang/Integer;
   19:	invokespecial	#53; //Method scala/Tuple2."<init>":(Ljava/lang/Object;Ljava/lang/Object;)V
   22:	invokespecial	#56; //Method scala/Some."<init>":(Ljava/lang/Object;)V
   25:	areturn
  LineNumberTable: 
   line 18: 0

  LocalVariableTable: 
   Start  Length  Slot  Name   Signature
   0      26      0    this       Lscala/util/grammar/LabelledRHS$;
   0      26      1    x$0       Lscala/util/grammar/LabelledRHS;


}

