Compiled from "TreeRHS.scala"
public final class scala.util.grammar.LabelledRHS$ extends java.lang.Object implements scala.ScalaObject
  SourceFile: "TreeRHS.scala"
  Scala: length = 0x
   
  minor version: 0
  major version: 49
  Constant pool:
Asciz	SourceFile;
Asciz	TreeRHS.scala;
Asciz	Scala;
Asciz	MODULE$;
Asciz	Lscala/util/grammar/LabelledRHS$;;
Asciz	<clinit>;
Asciz	()V;
Asciz	Code;
Asciz	scala/util/grammar/LabelledRHS$;
class	scala/util/grammar/LabelledRHS$
Asciz	<init>;
NameAndType	"<init>":()V
Method	scala/util/grammar/LabelledRHS$."<init>":()V
Asciz	unapply;
Asciz	(Lscala/util/grammar/LabelledRHS;)Lscala/Option;;
Asciz	LineNumberTable;
Asciz	java/lang/Object;
class	java/lang/Object
Asciz	equals;
Asciz	(Ljava/lang/Object;)Z;
NameAndType	equals:(Ljava/lang/Object;)Z
Method	java/lang/Object.equals:(Ljava/lang/Object;)Z
Asciz	scala/None$;
class	scala/None$
Asciz	Lscala/None$;;
NameAndType	MODULE$:Lscala/None$;
Field	scala/None$.MODULE$:Lscala/None$;
Asciz	scala/Some;
class	scala/Some
Asciz	scala/Tuple2;
class	scala/Tuple2
Asciz	scala/util/grammar/LabelledRHS;
class	scala/util/grammar/LabelledRHS
Asciz	label;
Asciz	()Ljava/lang/Object;;
NameAndType	label:()Ljava/lang/Object;
Method	scala/util/grammar/LabelledRHS.label:()Ljava/lang/Object;
Asciz	hnt;
Asciz	()I;
NameAndType	hnt:()I
Method	scala/util/grammar/LabelledRHS.hnt:()I
Asciz	scala/runtime/BoxesRunTime;
class	scala/runtime/BoxesRunTime
Asciz	boxToInteger;
Asciz	(I)Ljava/lang/Integer;;
NameAndType	boxToInteger:(I)Ljava/lang/Integer;
Method	scala/runtime/BoxesRunTime.boxToInteger:(I)Ljava/lang/Integer;
Asciz	(Ljava/lang/Object;Ljava/lang/Object;)V;
NameAndType	"<init>":(Ljava/lang/Object;Ljava/lang/Object;)V
Method	scala/Tuple2."<init>":(Ljava/lang/Object;Ljava/lang/Object;)V
Asciz	(Ljava/lang/Object;)V;
NameAndType	"<init>":(Ljava/lang/Object;)V
Method	scala/Some."<init>":(Ljava/lang/Object;)V
Asciz	this;
Asciz	x$0;
Asciz	Lscala/util/grammar/LabelledRHS;;
Asciz	LocalVariableTable;
Asciz	apply;
Asciz	(Ljava/lang/Object;I)Lscala/util/grammar/LabelledRHS;;
Asciz	(Ljava/lang/Object;I)V;
NameAndType	"<init>":(Ljava/lang/Object;I)V
Method	scala/util/grammar/LabelledRHS."<init>":(Ljava/lang/Object;I)V
Asciz	Ljava/lang/Object;;
Asciz	I;
Method	java/lang/Object."<init>":()V
NameAndType	MODULE$:Lscala/util/grammar/LabelledRHS$;
Field	scala/util/grammar/LabelledRHS$.MODULE$:Lscala/util/grammar/LabelledRHS$;
Asciz	scala/ScalaObject;
class	scala/ScalaObject

{
public static final scala.util.grammar.LabelledRHS$ MODULE$;
  Signature: Lscala/util/grammar/LabelledRHS$;

public static {};
  Signature: ()V
  Code:
   Stack=1, Locals=0, Args_size=0
	new	class scala/util/grammar/LabelledRHS$
	invokespecial	Method "<init>":()V
	return
  Labels:

public scala.Option unapply(scala.util.grammar.LabelledRHS);
  Signature: (Lscala/util/grammar/LabelledRHS;)Lscala/Option;
  Code:
   Stack=6, Locals=3, Args_size=2
	aload_1
	dup
	astore_2
	ifnull	l1 // getstatic
	aload_2
	aconst_null
	invokevirtual	Method java/lang/Object.equals:(Ljava/lang/Object;)Z
	ifeq	l2 // new
l1	getstatic	Field scala/None$.MODULE$:Lscala/None$;
	goto	l3 // areturn
l2	new	class scala/Some
	dup
	new	class scala/Tuple2
	dup
	aload_1
	invokevirtual	Method scala/util/grammar/LabelledRHS.label:()Ljava/lang/Object;
	aload_1
	invokevirtual	Method scala/util/grammar/LabelledRHS.hnt:()I
	invokestatic	Method scala/runtime/BoxesRunTime.boxToInteger:(I)Ljava/lang/Integer;
	invokespecial	Method scala/Tuple2."<init>":(Ljava/lang/Object;Ljava/lang/Object;)V
	invokespecial	Method scala/Some."<init>":(Ljava/lang/Object;)V
l3	areturn
  Labels:
   	l1 = 14 // getstatic
   	l2 = 20 // new
   	l3 = 45 // areturn
  LocalVariableTable: 
   Start  Length  Slot  Name   Signature
   0      46      0    this       Lscala/util/grammar/LabelledRHS$;
   0      46      1    x$0       Lscala/util/grammar/LabelledRHS;


public scala.util.grammar.LabelledRHS apply(java.lang.Object, int);
  Signature: (Ljava/lang/Object;I)Lscala/util/grammar/LabelledRHS;
  Code:
   Stack=4, Locals=3, Args_size=3
	new	class scala/util/grammar/LabelledRHS
	dup
	aload_1
	iload_2
	invokespecial	Method scala/util/grammar/LabelledRHS."<init>":(Ljava/lang/Object;I)V
	areturn
  Labels:
  LocalVariableTable: 
   Start  Length  Slot  Name   Signature
   0      10      0    this       Lscala/util/grammar/LabelledRHS$;
   0      10      1    label       Ljava/lang/Object;
   0      10      2    hnt       I


private scala.util.grammar.LabelledRHS$();
  Signature: ()V
  Code:
   Stack=1, Locals=1, Args_size=1
	aload_0
	invokespecial	Method java/lang/Object."<init>":()V
	aload_0
	putstatic	Field MODULE$:Lscala/util/grammar/LabelledRHS$;
	return
  Labels:

}

