Compiled from "AddingBuilder.scala"
public class scala.collection.mutable.AddingBuilder extends java.lang.Object implements scala.collection.mutable.Builder,scala.ScalaObject
  SourceFile: "AddingBuilder.scala"
  ScalaSig: length = 0x3
   05 00 00 
  Signature: length = 0x2
   00 5F 
  RuntimeVisibleAnnotations: length = 0xB
   00 01 00 60 00 01 00 61 73 00 62 
  minor version: 0
  major version: 49
  Constant pool:
Asciz	SourceFile;
Asciz	AddingBuilder.scala;
Asciz	empty;
Asciz	Lscala/collection/generic/Addable;;
Asciz	TTo;;
Asciz	Signature;
Asciz	elems;
Asciz	sizeHint;
Asciz	(I)V;
Asciz	Code;
Asciz	LineNumberTable;
Asciz	scala/collection/mutable/Builder$class;
class	scala/collection/mutable/Builder$class
Asciz	(Lscala/collection/mutable/Builder;I)V;
NameAndType	sizeHint:(Lscala/collection/mutable/Builder;I)V
Method	scala/collection/mutable/Builder$class.sizeHint:(Lscala/collection/mutable/Builder;I)V
Asciz	this;
Asciz	Lscala/collection/mutable/AddingBuilder;;
Asciz	size;
Asciz	I;
Asciz	LocalVariableTable;
Asciz	mapResult;
Asciz	(Lscala/Function1;)Lscala/collection/mutable/Builder;;
Asciz	(Lscala/collection/mutable/Builder;Lscala/Function1;)Lscala/collection/mutable/Builder;;
NameAndType	mapResult:(Lscala/collection/mutable/Builder;Lscala/Function1;)Lscala/collection/mutable/Builder;
Method	scala/collection/mutable/Builder$class.mapResult:(Lscala/collection/mutable/Builder;Lscala/Function1;)Lscala/collection/mutable/Builder;
Asciz	f;
Asciz	Lscala/Function1;;
Asciz	$plus$eq;
Asciz	(Ljava/lang/Object;Ljava/lang/Object;Lscala/collection/Seq;)Lscala/collection/generic/Growable;;
Asciz	scala/collection/generic/Growable$class;
class	scala/collection/generic/Growable$class
Asciz	(Lscala/collection/generic/Growable;Ljava/lang/Object;Ljava/lang/Object;Lscala/collection/Seq;)Lscala/collection/generic/Growable;;
NameAndType	$plus$eq:(Lscala/collection/generic/Growable;Ljava/lang/Object;Ljava/lang/Object;Lscala/collection/Seq;)Lscala/collection/generic/Growable;
Method	scala/collection/generic/Growable$class.$plus$eq:(Lscala/collection/generic/Growable;Ljava/lang/Object;Ljava/lang/Object;Lscala/collection/Seq;)Lscala/collection/generic/Growable;
Asciz	elem1;
Asciz	Ljava/lang/Object;;
Asciz	elem2;
Asciz	Lscala/collection/Seq;;
Asciz	$plus$plus$eq;
Asciz	(Lscala/collection/TraversableOnce;)Lscala/collection/generic/Growable;;
Asciz	(Lscala/collection/generic/Growable;Lscala/collection/TraversableOnce;)Lscala/collection/generic/Growable;;
NameAndType	$plus$plus$eq:(Lscala/collection/generic/Growable;Lscala/collection/TraversableOnce;)Lscala/collection/generic/Growable;
Method	scala/collection/generic/Growable$class.$plus$plus$eq:(Lscala/collection/generic/Growable;Lscala/collection/TraversableOnce;)Lscala/collection/generic/Growable;
Asciz	xs;
Asciz	Lscala/collection/TraversableOnce;;
Asciz	()Lscala/collection/generic/Addable;;
Asciz	scala/collection/mutable/AddingBuilder;
class	scala/collection/mutable/AddingBuilder
NameAndType	elems:Lscala/collection/generic/Addable;
Field	scala/collection/mutable/AddingBuilder.elems:Lscala/collection/generic/Addable;
Asciz	()TTo;;
Asciz	elems_$eq;
Asciz	(Lscala/collection/generic/Addable;)V;
Asciz	(TTo;)V;
Asciz	(Ljava/lang/Object;)Lscala/collection/mutable/AddingBuilder;;
NameAndType	elems:()Lscala/collection/generic/Addable;
Method	scala/collection/mutable/AddingBuilder.elems:()Lscala/collection/generic/Addable;
Asciz	scala/collection/generic/Addable;
class	scala/collection/generic/Addable
Asciz	$plus;
Asciz	(Ljava/lang/Object;)Lscala/collection/generic/Addable;;
NameAndType	$plus:(Ljava/lang/Object;)Lscala/collection/generic/Addable;
InterfaceMethod	scala/collection/generic/Addable.$plus:(Ljava/lang/Object;)Lscala/collection/generic/Addable;
NameAndType	elems_$eq:(Lscala/collection/generic/Addable;)V
Method	scala/collection/mutable/AddingBuilder.elems_$eq:(Lscala/collection/generic/Addable;)V
Asciz	x;
Asciz	(TElem;)Lscala/collection/mutable/AddingBuilder<TElem;TTo;>;;
Asciz	clear;
Asciz	()V;
NameAndType	empty:Lscala/collection/generic/Addable;
Field	scala/collection/mutable/AddingBuilder.empty:Lscala/collection/generic/Addable;
Asciz	result;
Asciz	()Ljava/lang/Object;;
NameAndType	result:()Lscala/collection/generic/Addable;
Method	scala/collection/mutable/AddingBuilder.result:()Lscala/collection/generic/Addable;
Asciz	(Ljava/lang/Object;)Lscala/collection/generic/Growable;;
NameAndType	$plus$eq:(Ljava/lang/Object;)Lscala/collection/mutable/AddingBuilder;
Method	scala/collection/mutable/AddingBuilder.$plus$eq:(Ljava/lang/Object;)Lscala/collection/mutable/AddingBuilder;
Asciz	elem;
Asciz	(Ljava/lang/Object;)Lscala/collection/mutable/Builder;;
Asciz	<init>;
Asciz	java/lang/Object;
class	java/lang/Object
NameAndType	"<init>":()V
Method	java/lang/Object."<init>":()V
Asciz	$init$;
Asciz	(Lscala/collection/generic/Growable;)V;
NameAndType	$init$:(Lscala/collection/generic/Growable;)V
Method	scala/collection/generic/Growable$class.$init$:(Lscala/collection/generic/Growable;)V
Asciz	(Lscala/collection/mutable/Builder;)V;
NameAndType	$init$:(Lscala/collection/mutable/Builder;)V
Method	scala/collection/mutable/Builder$class.$init$:(Lscala/collection/mutable/Builder;)V
Asciz	ScalaSig;
Asciz	<Elem:Ljava/lang/Object;To::Lscala/collection/generic/Addable<TElem;TTo;>;:Lscala/collection/Iterable<TElem;>;:Lscala/collection/IterableLike<TElem;TTo;>;>Ljava/lang/Object;Lscala/collection/mutable/Builder<TElem;TTo;>;Lscala/ScalaObject;;
Asciz	Lscala/reflect/ScalaSignature;;
Asciz	bytes;
Asciz	i3A!\ti\t3j]U/7eKJT!a5,H/2mK*QABG>dG.Z2uS>t'\"AM\r\1U!\"\tY1c\tEi!=\tA\1oO*\t#kCZB\ny%M[3diB!A#F$BU/7eKJ\"G\r\rA!C1DFYlC!!\tib$D\tybAAO_RDN\4u\tB\r\te.\t1\"\"\n\rA\n)>\"H\t!R\tS!\t!AO\taAH]3gS:,W.8u}A!1FL$a#BA9WM\3sSL!a#G-2mKBGMI!a\r%#XM]1cYB!MG%a\rR,'/2mK2K7.\t;aJ!!M\r\1PE*,7\r\tw\t)AG)Q-9us\")QC}1A(8jiz\"\"a!\tQqc\twq\ra\t\r\"D)G.Z7t+bB#%\tBR\nK2,Wn]0%KF$\"a&uABA%)f.;\t-#!aGJ\t\r5)$)G.Z7tA!)q\nC!AA7vg*R%6\tCTq#Ay)\"WG.Z1s)9\"-\tIA:fgVdGF$;
Asciz	RuntimeVisibleAnnotations;
Asciz	scala/collection/mutable/Builder;
class	scala/collection/mutable/Builder
Asciz	scala/ScalaObject;
class	scala/ScalaObject

{
private final scala.collection.generic.Addable empty;
  Signature: Lscala/collection/generic/Addable;
  Signature: length = 0x2
   00 05 

private scala.collection.generic.Addable elems;
  Signature: Lscala/collection/generic/Addable;
  Signature: length = 0x2
   00 05 

public void sizeHint(int);
  Signature: (I)V
  Code:
   Stack=2, Locals=2, Args_size=2
	aload_0
	iload_1
	invokestatic	Method scala/collection/mutable/Builder$class.sizeHint:(Lscala/collection/mutable/Builder;I)V
	return
  Labels:
  LocalVariableTable: 
   Start  Length  Slot  Name   Signature
   0      6      0    this       Lscala/collection/mutable/AddingBuilder;
   0      6      1    size       I


public scala.collection.mutable.Builder mapResult(scala.Function1);
  Signature: (Lscala/Function1;)Lscala/collection/mutable/Builder;
  Code:
   Stack=2, Locals=2, Args_size=2
	aload_0
	aload_1
	invokestatic	Method scala/collection/mutable/Builder$class.mapResult:(Lscala/collection/mutable/Builder;Lscala/Function1;)Lscala/collection/mutable/Builder;
	areturn
  Labels:
  LocalVariableTable: 
   Start  Length  Slot  Name   Signature
   0      6      0    this       Lscala/collection/mutable/AddingBuilder;
   0      6      1    f       Lscala/Function1;


public scala.collection.generic.Growable $plus$eq(java.lang.Object, java.lang.Object, scala.collection.Seq);
  Signature: (Ljava/lang/Object;Ljava/lang/Object;Lscala/collection/Seq;)Lscala/collection/generic/Growable;
  Code:
   Stack=4, Locals=4, Args_size=4
	aload_0
	aload_1
	aload_2
	aload_3
	invokestatic	Method scala/collection/generic/Growable$class.$plus$eq:(Lscala/collection/generic/Growable;Ljava/lang/Object;Ljava/lang/Object;Lscala/collection/Seq;)Lscala/collection/generic/Growable;
	areturn
  Labels:
  LocalVariableTable: 
   Start  Length  Slot  Name   Signature
   0      8      0    this       Lscala/collection/mutable/AddingBuilder;
   0      8      1    elem1       Ljava/lang/Object;
   0      8      2    elem2       Ljava/lang/Object;
   0      8      3    elems       Lscala/collection/Seq;


public scala.collection.generic.Growable $plus$plus$eq(scala.collection.TraversableOnce);
  Signature: (Lscala/collection/TraversableOnce;)Lscala/collection/generic/Growable;
  Code:
   Stack=2, Locals=2, Args_size=2
	aload_0
	aload_1
	invokestatic	Method scala/collection/generic/Growable$class.$plus$plus$eq:(Lscala/collection/generic/Growable;Lscala/collection/TraversableOnce;)Lscala/collection/generic/Growable;
	areturn
  Labels:
  LocalVariableTable: 
   Start  Length  Slot  Name   Signature
   0      6      0    this       Lscala/collection/mutable/AddingBuilder;
   0      6      1    xs       Lscala/collection/TraversableOnce;


public scala.collection.generic.Addable elems();
  Signature: ()Lscala/collection/generic/Addable;
  Code:
   Stack=1, Locals=1, Args_size=1
	aload_0
	getfield	Field elems:Lscala/collection/generic/Addable;
	areturn
  Labels:
  Signature: length = 0x2
   00 34 

public void elems_$eq(scala.collection.generic.Addable);
  Signature: (Lscala/collection/generic/Addable;)V
  Code:
   Stack=2, Locals=2, Args_size=2
	aload_0
	aload_1
	putfield	Field elems:Lscala/collection/generic/Addable;
	return
  Labels:
  Signature: length = 0x2
   00 37 

public scala.collection.mutable.AddingBuilder $plus$eq(java.lang.Object);
  Signature: (Ljava/lang/Object;)Lscala/collection/mutable/AddingBuilder;
  Code:
   Stack=3, Locals=2, Args_size=2
	aload_0
	aload_0
	invokevirtual	Method elems:()Lscala/collection/generic/Addable;
	aload_1
	invokeinterface	InterfaceMethod scala/collection/generic/Addable.$plus:(Ljava/lang/Object;)Lscala/collection/generic/Addable;
	invokevirtual	Method elems_$eq:(Lscala/collection/generic/Addable;)V
	aload_0
	areturn
  Labels:
  LocalVariableTable: 
   Start  Length  Slot  Name   Signature
   0      16      0    this       Lscala/collection/mutable/AddingBuilder;
   0      16      1    x       Ljava/lang/Object;

  Signature: length = 0x2
   00 44 

public void clear();
  Signature: ()V
  Code:
   Stack=2, Locals=1, Args_size=1
	aload_0
	aload_0
	getfield	Field empty:Lscala/collection/generic/Addable;
	invokevirtual	Method elems_$eq:(Lscala/collection/generic/Addable;)V
	return
  Labels:

public scala.collection.generic.Addable result();
  Signature: ()Lscala/collection/generic/Addable;
  Code:
   Stack=1, Locals=1, Args_size=1
	aload_0
	invokevirtual	Method elems:()Lscala/collection/generic/Addable;
	areturn
  Labels:
  Signature: length = 0x2
   00 34 

public java.lang.Object result();
  Signature: ()Ljava/lang/Object;
  Code:
   Stack=1, Locals=1, Args_size=1
	aload_0
	invokevirtual	Method result:()Lscala/collection/generic/Addable;
	areturn
  Labels:

public scala.collection.generic.Growable $plus$eq(java.lang.Object);
  Signature: (Ljava/lang/Object;)Lscala/collection/generic/Growable;
  Code:
   Stack=2, Locals=2, Args_size=2
	aload_0
	aload_1
	invokevirtual	Method $plus$eq:(Ljava/lang/Object;)Lscala/collection/mutable/AddingBuilder;
	areturn
  Labels:
  LocalVariableTable: 
   Start  Length  Slot  Name   Signature
   0      6      0    this       Lscala/collection/mutable/AddingBuilder;
   0      6      1    elem       Ljava/lang/Object;


public scala.collection.mutable.Builder $plus$eq(java.lang.Object);
  Signature: (Ljava/lang/Object;)Lscala/collection/mutable/Builder;
  Code:
   Stack=2, Locals=2, Args_size=2
	aload_0
	aload_1
	invokevirtual	Method $plus$eq:(Ljava/lang/Object;)Lscala/collection/mutable/AddingBuilder;
	areturn
  Labels:
  LocalVariableTable: 
   Start  Length  Slot  Name   Signature
   0      6      0    this       Lscala/collection/mutable/AddingBuilder;
   0      6      1    elem       Ljava/lang/Object;


public scala.collection.mutable.AddingBuilder(scala.collection.generic.Addable);
  Signature: (Lscala/collection/generic/Addable;)V
  Code:
   Stack=2, Locals=2, Args_size=2
	aload_0
	aload_1
	putfield	Field empty:Lscala/collection/generic/Addable;
	aload_0
	invokespecial	Method java/lang/Object."<init>":()V
	aload_0
	invokestatic	Method scala/collection/generic/Growable$class.$init$:(Lscala/collection/generic/Growable;)V
	aload_0
	invokestatic	Method scala/collection/mutable/Builder$class.$init$:(Lscala/collection/mutable/Builder;)V
	aload_0
	aload_1
	putfield	Field elems:Lscala/collection/generic/Addable;
	return
  Labels:
  LocalVariableTable: 
   Start  Length  Slot  Name   Signature
   0      23      0    this       Lscala/collection/mutable/AddingBuilder;
   0      23      1    empty       Lscala/collection/generic/Addable;

  Signature: length = 0x2
   00 37 

}

