Compiled from "ArrayBuffer.scala"
public class scala.collection.mutable.ArrayBuffer extends java.lang.Object implements scala.collection.mutable.Buffer,scala.collection.generic.GenericTraversableTemplate,scala.collection.mutable.BufferLike,scala.collection.mutable.IndexedSeqLike,scala.collection.mutable.Builder,scala.collection.mutable.ResizableArray,scala.ScalaObject,java.io.Serializable
  SourceFile: "ArrayBuffer.scala"
  Signature: length = 0x2
   04 FFFFFF85 
  ScalaSig: length = 0x4FB
   05 00 FFFFFF81 35 06 04 01 02 00 09 02 0B 41 72 72 61
   79 42 75 66 66 65 72 0A 02 03 04 01 07 6D 75 74
   61 62 6C 65 0A 02 05 06 01 0A 63 6F 6C 6C 65 63
   74 69 6F 6E 0A 01 07 01 05 73 63 61 6C 61 03 00
   15 02 0A 19 13 09 00 0B 13 23 2A 2E 31 34 37 10
   02 0C 11 0D 01 0D 0A 02 0E 0F 01 04 6C 61 6E 67
   0A 01 10 01 04 6A 61 76 61 09 02 12 0D 02 06 4F
   62 6A 65 63 74 10 03 14 15 17 0D 01 02 09 02 16
   02 02 06 42 75 66 66 65 72 10 02 18 19 0C 00 04
   08 1A 00 FFFFFF84 FFFFFF80 FFFFFF80 FFFFFFC2 00 1B 02 01 41 11 02 1C 20
   10 02 1D 1E 0D 01 06 09 02 1F 06 02 07 4E 6F 74
   68 69 6E 67 10 02 1D 21 09 02 22 06 02 03 41 6E
   79 10 04 24 27 17 29 0D 01 25 0A 02 26 04 01 07
   67 65 6E 65 72 69 63 09 02 28 25 02 1A 47 65 6E
   65 72 69 63 54 72 61 76 65 72 73 61 62 6C 65 54
   65 6D 70 6C 61 74 65 10 02 14 00 10 04 14 2B 17
   2D 09 02 2C 02 02 0A 42 75 66 66 65 72 4C 69 6B
   65 10 03 14 00 17 10 04 14 2F 17 2D 09 02 30 02
   02 0E 49 6E 64 65 78 65 64 53 65 71 4C 69 6B 65
   10 04 14 32 17 2D 09 02 33 02 02 07 42 75 69 6C
   64 65 72 10 03 14 35 17 09 02 36 02 02 0E 52 65
   73 69 7A 61 62 6C 65 41 72 72 61 79 10 02 1D 38
   09 02 39 06 02 0B 53 63 61 6C 61 4F 62 6A 65 63
   74 08 08 3B 00 FFFFFF82 FFFFFFC2 FFFFFF80 FFFFFF84 28 3C 01 0B 69 6E 69
   74 69 61 6C 53 69 7A 65 15 01 3D 10 02 1D 3E 09
   02 3F 06 02 03 49 6E 74 08 08 41 00 FFFFFF82 FFFFFF80 FFFFFFA0 FFFFFF80
   04 3D 01 0C 69 6E 69 74 69 61 6C 53 69 7A 65 20
   08 05 43 00 FFFFFF84 00 44 01 06 3C 69 6E 69 74 3E 14
   02 2D 45 08 05 3B 42 FFFFFFC0 00 3D 08 05 47 00 FFFFFF84 20
   48 01 09 63 6F 6D 70 61 6E 69 6F 6E 15 01 49 10
   03 24 4A 29 09 02 4B 25 02 10 47 65 6E 65 72 69
   63 43 6F 6D 70 61 6E 69 6F 6E 08 05 43 00 FFFFFF84 00
   4D 14 01 2D 08 05 4F 00 FFFFFF84 00 50 01 05 63 6C 65
   61 72 14 01 51 10 02 1D 52 09 02 53 06 02 04 55
   6E 69 74 08 05 55 00 FFFFFF84 20 56 01 08 73 69 7A 65
   48 69 6E 74 14 02 51 57 08 05 58 54 FFFFFFC0 00 3D 01
   03 6C 65 6E 08 05 5A 00 FFFFFF84 00 5B 01 08 24 70 6C
   75 73 24 65 71 14 02 5C 5D 0D 01 00 08 05 5E 59
   FFFFFFC0 00 17 01 04 65 6C 65 6D 08 05 60 00 FFFFFF84 20 61
   01 0D 24 70 6C 75 73 24 70 6C 75 73 24 65 71 14
   02 5C 62 08 05 63 5F FFFFFFC0 00 64 01 04 69 74 65 72
   10 03 65 66 17 0D 01 04 09 02 67 04 02 0B 54 72
   61 76 65 72 73 61 62 6C 65 08 05 69 00 FFFFFF84 00 6A
   01 0E 24 70 6C 75 73 24 65 71 24 63 6F 6C 6F 6E
   14 02 5C 6B 08 05 5E 68 FFFFFFC0 00 17 08 05 6D 00 FFFFFF84
   20 6E 01 13 24 70 6C 75 73 24 70 6C 75 73 24 65
   71 24 63 6F 6C 6F 6E 14 02 5C 6F 08 05 63 6C FFFFFFC0
   00 64 08 05 71 00 FFFFFF84 00 72 01 09 69 6E 73 65 72
   74 41 6C 6C 14 03 51 73 75 08 05 74 70 FFFFFFC0 00 3D
   01 01 6E 08 05 76 70 FFFFFFC0 00 64 01 03 73 65 71 08
   05 78 00 FFFFFF84 20 79 01 06 72 65 6D 6F 76 65 14 03
   51 7A 7B 08 05 74 77 FFFFFFC0 00 3D 08 05 7C 77 FFFFFFC0 00
   3D 01 05 63 6F 75 6E 74 08 05 78 00 FFFFFF84 00 7E 14
   02 17 7F 08 05 74 7D FFFFFFC0 00 3D 08 06 FFFFFF81 01 00 FFFFFF84
   20 4D 01 05 63 6C 6F 6E 65 08 06 FFFFFF81 03 00 FFFFFF84 00
   4D 01 06 72 65 73 75 6C 74 08 07 FFFFFF81 05 00 FFFFFF84 20
   FFFFFF81 06 01 0C 73 74 72 69 6E 67 50 72 65 66 69 78
   15 02 FFFFFF81 07 10 04 FFFFFF81 08 FFFFFF81 0B 0E 03 1D FFFFFF81 09 09
   03 FFFFFF81 0A 06 01 06 50 72 65 64 65 66 09 04 FFFFFF81 0C
   FFFFFF81 0D 02 06 53 74 72 69 6E 67 0A 03 FFFFFF81 0A 06 28
   05 00 FFFFFF81 0F FFFFFF81 12 10 03 1D FFFFFF81 10 09 03 FFFFFF81 11 06
   02 10 53 65 72 69 61 6C 56 65 72 73 69 6F 6E 55
   49 44 1E 08 15 38 FFFFFFB0 53 FFFFFF83 FFFFFF82 FFFFFF8E 73 28 03 00 FFFFFF81
   14 10 03 1D FFFFFF81 15 09 03 FFFFFF81 16 06 02 0C 73 65 72
   69 61 6C 69 7A 61 62 6C 65 07 07 FFFFFF81 18 02 FFFFFF88 02
   FFFFFF81 19 01 0B 41 72 72 61 79 42 75 66 66 65 72 10
   03 14 FFFFFF81 1A 06 09 01 02 FFFFFF84 FFFFFF80 FFFFFF80 FFFFFF88 02 FFFFFF81 1B 13
   05 FFFFFF81 1A FFFFFF81 1C 37 10 04 24 FFFFFF81 1D 29 09 03 FFFFFF81 1E
   25 02 0A 53 65 71 46 61 63 74 6F 72 79 08 07 43
   FFFFFF81 1A FFFFFF84 00 FFFFFF81 20 14 02 FFFFFF81 19 08 08 FFFFFF81 22 FFFFFF81 1A
   FFFFFF84 01 FFFFFF81 23 01 0C 63 61 6E 42 75 69 6C 64 46 72
   6F 6D 15 04 FFFFFF81 24 FFFFFF81 2C 10 09 24 FFFFFF81 25 FFFFFF81 27 FFFFFF81
   2B FFFFFF81 2D 09 03 FFFFFF81 26 25 02 0C 43 61 6E 42 75 69
   6C 64 46 72 6F 6D 10 04 FFFFFF81 28 FFFFFF81 29 0D 02 FFFFFF81 1A
   09 03 FFFFFF81 2A 4A 02 04 43 6F 6C 6C 10 03 18 FFFFFF81 2C
   04 09 1A FFFFFF81 21 FFFFFF84 FFFFFF80 FFFFFF80 FFFFFFC2 00 1B 10 04 14 00 FFFFFF81
   2B 08 08 FFFFFF81 2F FFFFFF81 1A FFFFFF84 00 FFFFFF81 30 01 0A 6E 65 77
   42 75 69 6C 64 65 72 15 04 FFFFFF81 31 FFFFFF81 33 10 06 14
   32 FFFFFF81 32 FFFFFF81 34 10 03 18 FFFFFF81 33 04 09 1A FFFFFF81 2E FFFFFF84
   FFFFFF80 FFFFFF80 FFFFFFC2 00 1B 10 04 14 00 FFFFFF81 32 
  InnerClass: 
   public #1162= #1161 of #292; //WithFilter=class scala/collection/TraversableLike$WithFilter of class scala/collection/TraversableLike
   public final #1163= #313 of #11; //$anonfun$remove$1=class scala/collection/mutable/ArrayBuffer$$anonfun$remove$1 of class scala/collection/mutable/ArrayBuffer
  minor version: 0
  major version: 49
  Constant pool:
const #1 = Asciz	SourceFile;
const #2 = Asciz	ArrayBuffer.scala;
const #3 = Asciz	<clinit>;
const #4 = Asciz	()V;
const #5 = Asciz	Code;
const #6 = Asciz	serialVersionUID;
const #7 = Asciz	J;
const #8 = long	1529165946227428979l;
const #10 = Asciz	scala/collection/mutable/ArrayBuffer;
const #11 = class	#10;	//  scala/collection/mutable/ArrayBuffer
const #12 = NameAndType	#6:#7;//  serialVersionUID:J
const #13 = Field	#11.#12;	//  scala/collection/mutable/ArrayBuffer.serialVersionUID:J
const #14 = Asciz	size0;
const #15 = Asciz	I;
const #16 = Asciz	array;
const #17 = Asciz	[Ljava/lang/Object;;
const #18 = Asciz	initialSize;
const #19 = Asciz	<init>;
const #20 = Asciz	(I)V;
const #21 = Asciz	LineNumberTable;
const #22 = NameAndType	#18:#15;//  initialSize:I
const #23 = Field	#11.#22;	//  scala/collection/mutable/ArrayBuffer.initialSize:I
const #24 = Asciz	java/lang/Object;
const #25 = class	#24;	//  java/lang/Object
const #26 = NameAndType	#19:#4;//  "<init>":()V
const #27 = Method	#25.#26;	//  java/lang/Object."<init>":()V
const #28 = Asciz	scala/collection/TraversableLike$class;
const #29 = class	#28;	//  scala/collection/TraversableLike$class
const #30 = Asciz	$init$;
const #31 = Asciz	(Lscala/collection/TraversableLike;)V;
const #32 = NameAndType	#30:#31;//  $init$:(Lscala/collection/TraversableLike;)V
const #33 = Method	#29.#32;	//  scala/collection/TraversableLike$class.$init$:(Lscala/collection/TraversableLike;)V
const #34 = Asciz	scala/collection/generic/GenericTraversableTemplate$class;
const #35 = class	#34;	//  scala/collection/generic/GenericTraversableTemplate$class
const #36 = Asciz	(Lscala/collection/generic/GenericTraversableTemplate;)V;
const #37 = NameAndType	#30:#36;//  $init$:(Lscala/collection/generic/GenericTraversableTemplate;)V
const #38 = Method	#35.#37;	//  scala/collection/generic/GenericTraversableTemplate$class.$init$:(Lscala/collection/generic/GenericTraversableTemplate;)V
const #39 = Asciz	scala/collection/Traversable$class;
const #40 = class	#39;	//  scala/collection/Traversable$class
const #41 = Asciz	(Lscala/collection/Traversable;)V;
const #42 = NameAndType	#30:#41;//  $init$:(Lscala/collection/Traversable;)V
const #43 = Method	#40.#42;	//  scala/collection/Traversable$class.$init$:(Lscala/collection/Traversable;)V
const #44 = Asciz	scala/collection/mutable/Traversable$class;
const #45 = class	#44;	//  scala/collection/mutable/Traversable$class
const #46 = Asciz	(Lscala/collection/mutable/Traversable;)V;
const #47 = NameAndType	#30:#46;//  $init$:(Lscala/collection/mutable/Traversable;)V
const #48 = Method	#45.#47;	//  scala/collection/mutable/Traversable$class.$init$:(Lscala/collection/mutable/Traversable;)V
const #49 = Asciz	scala/collection/IterableLike$class;
const #50 = class	#49;	//  scala/collection/IterableLike$class
const #51 = Asciz	(Lscala/collection/IterableLike;)V;
const #52 = NameAndType	#30:#51;//  $init$:(Lscala/collection/IterableLike;)V
const #53 = Method	#50.#52;	//  scala/collection/IterableLike$class.$init$:(Lscala/collection/IterableLike;)V
const #54 = Asciz	scala/collection/Iterable$class;
const #55 = class	#54;	//  scala/collection/Iterable$class
const #56 = Asciz	(Lscala/collection/Iterable;)V;
const #57 = NameAndType	#30:#56;//  $init$:(Lscala/collection/Iterable;)V
const #58 = Method	#55.#57;	//  scala/collection/Iterable$class.$init$:(Lscala/collection/Iterable;)V
const #59 = Asciz	scala/collection/mutable/Iterable$class;
const #60 = class	#59;	//  scala/collection/mutable/Iterable$class
const #61 = Asciz	(Lscala/collection/mutable/Iterable;)V;
const #62 = NameAndType	#30:#61;//  $init$:(Lscala/collection/mutable/Iterable;)V
const #63 = Method	#60.#62;	//  scala/collection/mutable/Iterable$class.$init$:(Lscala/collection/mutable/Iterable;)V
const #64 = Asciz	scala/Function1$class;
const #65 = class	#64;	//  scala/Function1$class
const #66 = Asciz	(Lscala/Function1;)V;
const #67 = NameAndType	#30:#66;//  $init$:(Lscala/Function1;)V
const #68 = Method	#65.#67;	//  scala/Function1$class.$init$:(Lscala/Function1;)V
const #69 = Asciz	scala/PartialFunction$class;
const #70 = class	#69;	//  scala/PartialFunction$class
const #71 = Asciz	(Lscala/PartialFunction;)V;
const #72 = NameAndType	#30:#71;//  $init$:(Lscala/PartialFunction;)V
const #73 = Method	#70.#72;	//  scala/PartialFunction$class.$init$:(Lscala/PartialFunction;)V
const #74 = Asciz	scala/collection/SeqLike$class;
const #75 = class	#74;	//  scala/collection/SeqLike$class
const #76 = Asciz	(Lscala/collection/SeqLike;)V;
const #77 = NameAndType	#30:#76;//  $init$:(Lscala/collection/SeqLike;)V
const #78 = Method	#75.#77;	//  scala/collection/SeqLike$class.$init$:(Lscala/collection/SeqLike;)V
const #79 = Asciz	scala/collection/Seq$class;
const #80 = class	#79;	//  scala/collection/Seq$class
const #81 = Asciz	(Lscala/collection/Seq;)V;
const #82 = NameAndType	#30:#81;//  $init$:(Lscala/collection/Seq;)V
const #83 = Method	#80.#82;	//  scala/collection/Seq$class.$init$:(Lscala/collection/Seq;)V
const #84 = Asciz	scala/collection/mutable/Seq$class;
const #85 = class	#84;	//  scala/collection/mutable/Seq$class
const #86 = Asciz	(Lscala/collection/mutable/Seq;)V;
const #87 = NameAndType	#30:#86;//  $init$:(Lscala/collection/mutable/Seq;)V
const #88 = Method	#85.#87;	//  scala/collection/mutable/Seq$class.$init$:(Lscala/collection/mutable/Seq;)V
const #89 = Asciz	scala/collection/generic/Growable$class;
const #90 = class	#89;	//  scala/collection/generic/Growable$class
const #91 = Asciz	(Lscala/collection/generic/Growable;)V;
const #92 = NameAndType	#30:#91;//  $init$:(Lscala/collection/generic/Growable;)V
const #93 = Method	#90.#92;	//  scala/collection/generic/Growable$class.$init$:(Lscala/collection/generic/Growable;)V
const #94 = Asciz	scala/collection/generic/Shrinkable$class;
const #95 = class	#94;	//  scala/collection/generic/Shrinkable$class
const #96 = Asciz	(Lscala/collection/generic/Shrinkable;)V;
const #97 = NameAndType	#30:#96;//  $init$:(Lscala/collection/generic/Shrinkable;)V
const #98 = Method	#95.#97;	//  scala/collection/generic/Shrinkable$class.$init$:(Lscala/collection/generic/Shrinkable;)V
const #99 = Asciz	scala/collection/generic/Addable$class;
const #100 = class	#99;	//  scala/collection/generic/Addable$class
const #101 = Asciz	(Lscala/collection/generic/Addable;)V;
const #102 = NameAndType	#30:#101;//  $init$:(Lscala/collection/generic/Addable;)V
const #103 = Method	#100.#102;	//  scala/collection/generic/Addable$class.$init$:(Lscala/collection/generic/Addable;)V
const #104 = Asciz	scala/collection/generic/Subtractable$class;
const #105 = class	#104;	//  scala/collection/generic/Subtractable$class
const #106 = Asciz	(Lscala/collection/generic/Subtractable;)V;
const #107 = NameAndType	#30:#106;//  $init$:(Lscala/collection/generic/Subtractable;)V
const #108 = Method	#105.#107;	//  scala/collection/generic/Subtractable$class.$init$:(Lscala/collection/generic/Subtractable;)V
const #109 = Asciz	scala/collection/mutable/Cloneable$class;
const #110 = class	#109;	//  scala/collection/mutable/Cloneable$class
const #111 = Asciz	(Lscala/collection/mutable/Cloneable;)V;
const #112 = NameAndType	#30:#111;//  $init$:(Lscala/collection/mutable/Cloneable;)V
const #113 = Method	#110.#112;	//  scala/collection/mutable/Cloneable$class.$init$:(Lscala/collection/mutable/Cloneable;)V
const #114 = Asciz	scala/collection/mutable/BufferLike$class;
const #115 = class	#114;	//  scala/collection/mutable/BufferLike$class
const #116 = Asciz	(Lscala/collection/mutable/BufferLike;)V;
const #117 = NameAndType	#30:#116;//  $init$:(Lscala/collection/mutable/BufferLike;)V
const #118 = Method	#115.#117;	//  scala/collection/mutable/BufferLike$class.$init$:(Lscala/collection/mutable/BufferLike;)V
const #119 = Asciz	scala/collection/mutable/Buffer$class;
const #120 = class	#119;	//  scala/collection/mutable/Buffer$class
const #121 = Asciz	(Lscala/collection/mutable/Buffer;)V;
const #122 = NameAndType	#30:#121;//  $init$:(Lscala/collection/mutable/Buffer;)V
const #123 = Method	#120.#122;	//  scala/collection/mutable/Buffer$class.$init$:(Lscala/collection/mutable/Buffer;)V
const #124 = Asciz	scala/collection/IndexedSeqLike$class;
const #125 = class	#124;	//  scala/collection/IndexedSeqLike$class
const #126 = Asciz	(Lscala/collection/IndexedSeqLike;)V;
const #127 = NameAndType	#30:#126;//  $init$:(Lscala/collection/IndexedSeqLike;)V
const #128 = Method	#125.#127;	//  scala/collection/IndexedSeqLike$class.$init$:(Lscala/collection/IndexedSeqLike;)V
const #129 = Asciz	scala/collection/mutable/IndexedSeqLike$class;
const #130 = class	#129;	//  scala/collection/mutable/IndexedSeqLike$class
const #131 = Asciz	(Lscala/collection/mutable/IndexedSeqLike;)V;
const #132 = NameAndType	#30:#131;//  $init$:(Lscala/collection/mutable/IndexedSeqLike;)V
const #133 = Method	#130.#132;	//  scala/collection/mutable/IndexedSeqLike$class.$init$:(Lscala/collection/mutable/IndexedSeqLike;)V
const #134 = Asciz	scala/collection/mutable/Builder$class;
const #135 = class	#134;	//  scala/collection/mutable/Builder$class
const #136 = Asciz	(Lscala/collection/mutable/Builder;)V;
const #137 = NameAndType	#30:#136;//  $init$:(Lscala/collection/mutable/Builder;)V
const #138 = Method	#135.#137;	//  scala/collection/mutable/Builder$class.$init$:(Lscala/collection/mutable/Builder;)V
const #139 = Asciz	scala/collection/IndexedSeq$class;
const #140 = class	#139;	//  scala/collection/IndexedSeq$class
const #141 = Asciz	(Lscala/collection/IndexedSeq;)V;
const #142 = NameAndType	#30:#141;//  $init$:(Lscala/collection/IndexedSeq;)V
const #143 = Method	#140.#142;	//  scala/collection/IndexedSeq$class.$init$:(Lscala/collection/IndexedSeq;)V
const #144 = Asciz	scala/collection/mutable/IndexedSeq$class;
const #145 = class	#144;	//  scala/collection/mutable/IndexedSeq$class
const #146 = Asciz	(Lscala/collection/mutable/IndexedSeq;)V;
const #147 = NameAndType	#30:#146;//  $init$:(Lscala/collection/mutable/IndexedSeq;)V
const #148 = Method	#145.#147;	//  scala/collection/mutable/IndexedSeq$class.$init$:(Lscala/collection/mutable/IndexedSeq;)V
const #149 = Asciz	scala/collection/mutable/ResizableArray$class;
const #150 = class	#149;	//  scala/collection/mutable/ResizableArray$class
const #151 = Asciz	(Lscala/collection/mutable/ResizableArray;)V;
const #152 = NameAndType	#30:#151;//  $init$:(Lscala/collection/mutable/ResizableArray;)V
const #153 = Method	#150.#152;	//  scala/collection/mutable/ResizableArray$class.$init$:(Lscala/collection/mutable/ResizableArray;)V
const #154 = Asciz	this;
const #155 = Asciz	Lscala/collection/mutable/ArrayBuffer;;
const #156 = Asciz	LocalVariableTable;
const #157 = Asciz	Signature;
const #158 = Asciz	$plus$eq;
const #159 = Asciz	(Ljava/lang/Object;)Lscala/collection/mutable/Builder;;
const #160 = Asciz	(Ljava/lang/Object;)Lscala/collection/mutable/ArrayBuffer;;
const #161 = NameAndType	#158:#160;//  $plus$eq:(Ljava/lang/Object;)Lscala/collection/mutable/ArrayBuffer;
const #162 = Method	#11.#161;	//  scala/collection/mutable/ArrayBuffer.$plus$eq:(Ljava/lang/Object;)Lscala/collection/mutable/ArrayBuffer;
const #163 = Asciz	elem;
const #164 = Asciz	Ljava/lang/Object;;
const #165 = Asciz	(Ljava/lang/Object;)Lscala/collection/mutable/BufferLike;;
const #166 = Asciz	(Ljava/lang/Object;)Lscala/collection/generic/Growable;;
const #167 = Asciz	$plus$plus$eq;
const #168 = Asciz	(Lscala/collection/Traversable;)Lscala/collection/generic/Growable;;
const #169 = Asciz	(Lscala/collection/Traversable;)Lscala/collection/mutable/ArrayBuffer;;
const #170 = NameAndType	#167:#169;//  $plus$plus$eq:(Lscala/collection/Traversable;)Lscala/collection/mutable/ArrayBuffer;
const #171 = Method	#11.#170;	//  scala/collection/mutable/ArrayBuffer.$plus$plus$eq:(Lscala/collection/Traversable;)Lscala/collection/mutable/ArrayBuffer;
const #172 = Asciz	elems;
const #173 = Asciz	Lscala/collection/Traversable;;
const #174 = Asciz	$plus$eq$colon;
const #175 = NameAndType	#174:#160;//  $plus$eq$colon:(Ljava/lang/Object;)Lscala/collection/mutable/ArrayBuffer;
const #176 = Method	#11.#175;	//  scala/collection/mutable/ArrayBuffer.$plus$eq$colon:(Ljava/lang/Object;)Lscala/collection/mutable/ArrayBuffer;
const #177 = Asciz	$plus$plus$eq$colon;
const #178 = Asciz	(Lscala/collection/Traversable;)Lscala/collection/mutable/BufferLike;;
const #179 = NameAndType	#177:#169;//  $plus$plus$eq$colon:(Lscala/collection/Traversable;)Lscala/collection/mutable/ArrayBuffer;
const #180 = Method	#11.#179;	//  scala/collection/mutable/ArrayBuffer.$plus$plus$eq$colon:(Lscala/collection/Traversable;)Lscala/collection/mutable/ArrayBuffer;
const #181 = Asciz	clone;
const #182 = Asciz	()Ljava/lang/Object;;
const #183 = Asciz	()Lscala/collection/mutable/ArrayBuffer;;
const #184 = NameAndType	#181:#183;//  clone:()Lscala/collection/mutable/ArrayBuffer;
const #185 = Method	#11.#184;	//  scala/collection/mutable/ArrayBuffer.clone:()Lscala/collection/mutable/ArrayBuffer;
const #186 = Asciz	result;
const #187 = NameAndType	#186:#183;//  result:()Lscala/collection/mutable/ArrayBuffer;
const #188 = Method	#11.#187;	//  scala/collection/mutable/ArrayBuffer.result:()Lscala/collection/mutable/ArrayBuffer;
const #189 = Asciz	apply;
const #190 = Asciz	(Ljava/lang/Object;)Ljava/lang/Object;;
const #191 = Asciz	scala/runtime/BoxesRunTime;
const #192 = class	#191;	//  scala/runtime/BoxesRunTime
const #193 = Asciz	unboxToInt;
const #194 = Asciz	(Ljava/lang/Object;)I;
const #195 = NameAndType	#193:#194;//  unboxToInt:(Ljava/lang/Object;)I
const #196 = Method	#192.#195;	//  scala/runtime/BoxesRunTime.unboxToInt:(Ljava/lang/Object;)I
const #197 = Asciz	scala/collection/mutable/ResizableArray;
const #198 = class	#197;	//  scala/collection/mutable/ResizableArray
const #199 = Asciz	(I)Ljava/lang/Object;;
const #200 = NameAndType	#189:#199;//  apply:(I)Ljava/lang/Object;
const #201 = InterfaceMethod	#198.#200;	//  scala/collection/mutable/ResizableArray.apply:(I)Ljava/lang/Object;
const #202 = Asciz	v1;
const #203 = Asciz	thisCollection;
const #204 = Asciz	()Lscala/collection/IndexedSeq;;
const #205 = Asciz	scala/collection/mutable/IndexedSeqLike;
const #206 = class	#205;	//  scala/collection/mutable/IndexedSeqLike
const #207 = Asciz	()Lscala/collection/mutable/IndexedSeq;;
const #208 = NameAndType	#203:#207;//  thisCollection:()Lscala/collection/mutable/IndexedSeq;
const #209 = InterfaceMethod	#206.#208;	//  scala/collection/mutable/IndexedSeqLike.thisCollection:()Lscala/collection/mutable/IndexedSeq;
const #210 = Asciz	()Lscala/collection/Seq;;
const #211 = Asciz	()Lscala/collection/Iterable;;
const #212 = Asciz	()Lscala/collection/Traversable;;
const #213 = Asciz	toCollection;
const #214 = Asciz	(Ljava/lang/Object;)Lscala/collection/IndexedSeq;;
const #215 = Asciz	(Ljava/lang/Object;)Lscala/collection/mutable/IndexedSeq;;
const #216 = NameAndType	#213:#215;//  toCollection:(Ljava/lang/Object;)Lscala/collection/mutable/IndexedSeq;
const #217 = InterfaceMethod	#206.#216;	//  scala/collection/mutable/IndexedSeqLike.toCollection:(Ljava/lang/Object;)Lscala/collection/mutable/IndexedSeq;
const #218 = Asciz	repr;
const #219 = Asciz	(Ljava/lang/Object;)Lscala/collection/Seq;;
const #220 = Asciz	(Ljava/lang/Object;)Lscala/collection/Iterable;;
const #221 = Asciz	(Ljava/lang/Object;)Lscala/collection/Traversable;;
const #222 = Asciz	view;
const #223 = Asciz	(II)Lscala/collection/IndexedSeqView;;
const #224 = Asciz	(II)Lscala/collection/mutable/IndexedSeqView;;
const #225 = NameAndType	#222:#224;//  view:(II)Lscala/collection/mutable/IndexedSeqView;
const #226 = InterfaceMethod	#206.#225;	//  scala/collection/mutable/IndexedSeqLike.view:(II)Lscala/collection/mutable/IndexedSeqView;
const #227 = Asciz	from;
const #228 = Asciz	until;
const #229 = Asciz	(II)Lscala/collection/SeqView;;
const #230 = Asciz	(II)Lscala/collection/IterableView;;
const #231 = Asciz	(II)Lscala/collection/TraversableView;;
const #232 = Asciz	$minus$eq;
const #233 = Asciz	(Ljava/lang/Object;)Lscala/collection/generic/Shrinkable;;
const #234 = Asciz	scala/collection/mutable/BufferLike;
const #235 = class	#234;	//  scala/collection/mutable/BufferLike
const #236 = NameAndType	#232:#165;//  $minus$eq:(Ljava/lang/Object;)Lscala/collection/mutable/BufferLike;
const #237 = InterfaceMethod	#235.#236;	//  scala/collection/mutable/BufferLike.$minus$eq:(Ljava/lang/Object;)Lscala/collection/mutable/BufferLike;
const #238 = Asciz	$plus;
const #239 = Asciz	(Ljava/lang/Object;)Lscala/collection/generic/Addable;;
const #240 = NameAndType	#238:#165;//  $plus:(Ljava/lang/Object;)Lscala/collection/mutable/BufferLike;
const #241 = InterfaceMethod	#235.#240;	//  scala/collection/mutable/BufferLike.$plus:(Ljava/lang/Object;)Lscala/collection/mutable/BufferLike;
const #242 = Asciz	(Ljava/lang/Object;Ljava/lang/Object;Lscala/collection/Seq;)Lscala/collection/generic/Addable;;
const #243 = Asciz	(Ljava/lang/Object;Ljava/lang/Object;Lscala/collection/Seq;)Lscala/collection/mutable/BufferLike;;
const #244 = NameAndType	#238:#243;//  $plus:(Ljava/lang/Object;Ljava/lang/Object;Lscala/collection/Seq;)Lscala/collection/mutable/BufferLike;
const #245 = InterfaceMethod	#235.#244;	//  scala/collection/mutable/BufferLike.$plus:(Ljava/lang/Object;Ljava/lang/Object;Lscala/collection/Seq;)Lscala/collection/mutable/BufferLike;
const #246 = Asciz	elem1;
const #247 = Asciz	elem2;
const #248 = Asciz	Lscala/collection/Seq;;
const #249 = Asciz	$plus$plus;
const #250 = Asciz	(Lscala/collection/Traversable;)Lscala/collection/generic/Addable;;
const #251 = NameAndType	#249:#178;//  $plus$plus:(Lscala/collection/Traversable;)Lscala/collection/mutable/BufferLike;
const #252 = InterfaceMethod	#235.#251;	//  scala/collection/mutable/BufferLike.$plus$plus:(Lscala/collection/Traversable;)Lscala/collection/mutable/BufferLike;
const #253 = Asciz	(Lscala/collection/Iterator;)Lscala/collection/generic/Addable;;
const #254 = Asciz	(Lscala/collection/Iterator;)Lscala/collection/mutable/BufferLike;;
const #255 = NameAndType	#249:#254;//  $plus$plus:(Lscala/collection/Iterator;)Lscala/collection/mutable/BufferLike;
const #256 = InterfaceMethod	#235.#255;	//  scala/collection/mutable/BufferLike.$plus$plus:(Lscala/collection/Iterator;)Lscala/collection/mutable/BufferLike;
const #257 = Asciz	iter;
const #258 = Asciz	Lscala/collection/Iterator;;
const #259 = Asciz	$minus;
const #260 = Asciz	(Ljava/lang/Object;)Lscala/collection/generic/Subtractable;;
const #261 = NameAndType	#259:#165;//  $minus:(Ljava/lang/Object;)Lscala/collection/mutable/BufferLike;
const #262 = InterfaceMethod	#235.#261;	//  scala/collection/mutable/BufferLike.$minus:(Ljava/lang/Object;)Lscala/collection/mutable/BufferLike;
const #263 = Asciz	(Ljava/lang/Object;Ljava/lang/Object;Lscala/collection/Seq;)Lscala/collection/generic/Subtractable;;
const #264 = NameAndType	#259:#243;//  $minus:(Ljava/lang/Object;Ljava/lang/Object;Lscala/collection/Seq;)Lscala/collection/mutable/BufferLike;
const #265 = InterfaceMethod	#235.#264;	//  scala/collection/mutable/BufferLike.$minus:(Ljava/lang/Object;Ljava/lang/Object;Lscala/collection/Seq;)Lscala/collection/mutable/BufferLike;
const #266 = Asciz	$minus$minus;
const #267 = Asciz	(Lscala/collection/Traversable;)Lscala/collection/generic/Subtractable;;
const #268 = NameAndType	#266:#178;//  $minus$minus:(Lscala/collection/Traversable;)Lscala/collection/mutable/BufferLike;
const #269 = InterfaceMethod	#235.#268;	//  scala/collection/mutable/BufferLike.$minus$minus:(Lscala/collection/Traversable;)Lscala/collection/mutable/BufferLike;
const #270 = Asciz	(Lscala/collection/Iterator;)Lscala/collection/generic/Subtractable;;
const #271 = NameAndType	#266:#254;//  $minus$minus:(Lscala/collection/Iterator;)Lscala/collection/mutable/BufferLike;
const #272 = InterfaceMethod	#235.#271;	//  scala/collection/mutable/BufferLike.$minus$minus:(Lscala/collection/Iterator;)Lscala/collection/mutable/BufferLike;
const #273 = Asciz	isDefinedAt;
const #274 = Asciz	(Ljava/lang/Object;)Z;
const #275 = Asciz	scala/collection/SeqLike;
const #276 = class	#275;	//  scala/collection/SeqLike
const #277 = Asciz	(I)Z;
const #278 = NameAndType	#273:#277;//  isDefinedAt:(I)Z
const #279 = InterfaceMethod	#276.#278;	//  scala/collection/SeqLike.isDefinedAt:(I)Z
const #280 = Asciz	x;
const #281 = Asciz	andThen;
const #282 = Asciz	(Lscala/Function1;)Lscala/Function1;;
const #283 = Asciz	scala/PartialFunction;
const #284 = class	#283;	//  scala/PartialFunction
const #285 = Asciz	(Lscala/Function1;)Lscala/PartialFunction;;
const #286 = NameAndType	#281:#285;//  andThen:(Lscala/Function1;)Lscala/PartialFunction;
const #287 = InterfaceMethod	#284.#286;	//  scala/PartialFunction.andThen:(Lscala/Function1;)Lscala/PartialFunction;
const #288 = Asciz	g;
const #289 = Asciz	Lscala/Function1;;
const #290 = Asciz	()Lscala/collection/generic/Subtractable;;
const #291 = Asciz	scala/collection/TraversableLike;
const #292 = class	#291;	//  scala/collection/TraversableLike
const #293 = NameAndType	#218:#182;//  repr:()Ljava/lang/Object;
const #294 = InterfaceMethod	#292.#293;	//  scala/collection/TraversableLike.repr:()Ljava/lang/Object;
const #295 = Asciz	scala/collection/generic/Subtractable;
const #296 = class	#295;	//  scala/collection/generic/Subtractable
const #297 = Asciz	()Lscala/collection/generic/Addable;;
const #298 = Asciz	scala/collection/generic/Addable;
const #299 = class	#298;	//  scala/collection/generic/Addable
const #300 = Asciz	stringPrefix;
const #301 = Asciz	()Ljava/lang/String;;
const #302 = Asciz	ArrayBuffer;
const #303 = String	#302;	//  ArrayBuffer
const #304 = Asciz	()Lscala/collection/mutable/ArrayBuffer<TA;>;;
const #305 = Method	#11.#26;	//  scala/collection/mutable/ArrayBuffer."<init>":()V
const #306 = Asciz	remove;
const #307 = Asciz	(II)V;
const #308 = NameAndType	#306:#307;//  remove:(II)V
const #309 = Method	#11.#308;	//  scala/collection/mutable/ArrayBuffer.remove:(II)V
const #310 = Asciz	n;
const #311 = Asciz	(I)TA;;
const #312 = Asciz	scala/collection/mutable/ArrayBuffer$$anonfun$remove$1;
const #313 = class	#312;	//  scala/collection/mutable/ArrayBuffer$$anonfun$remove$1
const #314 = Asciz	(Lscala/collection/mutable/ArrayBuffer;)V;
const #315 = NameAndType	#19:#314;//  "<init>":(Lscala/collection/mutable/ArrayBuffer;)V
const #316 = Method	#313.#315;	//  scala/collection/mutable/ArrayBuffer$$anonfun$remove$1."<init>":(Lscala/collection/mutable/ArrayBuffer;)V
const #317 = Asciz	()I;
const #318 = NameAndType	#14:#317;//  size0:()I
const #319 = InterfaceMethod	#198.#318;	//  scala/collection/mutable/ResizableArray.size0:()I
const #320 = Asciz	java/lang/IndexOutOfBoundsException;
const #321 = class	#320;	//  java/lang/IndexOutOfBoundsException
const #322 = Asciz	boxToInteger;
const #323 = Asciz	(I)Ljava/lang/Integer;;
const #324 = NameAndType	#322:#323;//  boxToInteger:(I)Ljava/lang/Integer;
const #325 = Method	#192.#324;	//  scala/runtime/BoxesRunTime.boxToInteger:(I)Ljava/lang/Integer;
const #326 = Asciz	toString;
const #327 = NameAndType	#326:#301;//  toString:()Ljava/lang/String;
const #328 = Method	#25.#327;	//  java/lang/Object.toString:()Ljava/lang/String;
const #329 = Asciz	(Ljava/lang/String;)V;
const #330 = NameAndType	#19:#329;//  "<init>":(Ljava/lang/String;)V
const #331 = Method	#321.#330;	//  java/lang/IndexOutOfBoundsException."<init>":(Ljava/lang/String;)V
const #332 = Asciz	copy;
const #333 = Asciz	(III)V;
const #334 = NameAndType	#332:#333;//  copy:(III)V
const #335 = InterfaceMethod	#198.#334;	//  scala/collection/mutable/ResizableArray.copy:(III)V
const #336 = Asciz	size0_$eq;
const #337 = NameAndType	#336:#20;//  size0_$eq:(I)V
const #338 = InterfaceMethod	#198.#337;	//  scala/collection/mutable/ResizableArray.size0_$eq:(I)V
const #339 = Asciz	java/lang/IllegalArgumentException;
const #340 = class	#339;	//  java/lang/IllegalArgumentException
const #341 = Asciz	scala/collection/mutable/StringBuilder;
const #342 = class	#341;	//  scala/collection/mutable/StringBuilder
const #343 = Method	#342.#26;	//  scala/collection/mutable/StringBuilder."<init>":()V
const #344 = Asciz	requirement failed: ;
const #345 = String	#344;	//  requirement failed: 
const #346 = Asciz	append;
const #347 = Asciz	(Ljava/lang/Object;)Lscala/collection/mutable/StringBuilder;;
const #348 = NameAndType	#346:#347;//  append:(Ljava/lang/Object;)Lscala/collection/mutable/StringBuilder;
const #349 = Method	#342.#348;	//  scala/collection/mutable/StringBuilder.append:(Ljava/lang/Object;)Lscala/collection/mutable/StringBuilder;
const #350 = Asciz	removing negative number of elements;
const #351 = String	#350;	//  removing negative number of elements
const #352 = Method	#342.#327;	//  scala/collection/mutable/StringBuilder.toString:()Ljava/lang/String;
const #353 = Method	#340.#330;	//  java/lang/IllegalArgumentException."<init>":(Ljava/lang/String;)V
const #354 = Asciz	count;
const #355 = Asciz	requirement0;
const #356 = Asciz	Z;
const #357 = Asciz	insertAll;
const #358 = Asciz	(ILscala/collection/Traversable;)V;
const #359 = Asciz	toList;
const #360 = Asciz	()Lscala/collection/immutable/List;;
const #361 = NameAndType	#359:#360;//  toList:()Lscala/collection/immutable/List;
const #362 = InterfaceMethod	#292.#361;	//  scala/collection/TraversableLike.toList:()Lscala/collection/immutable/List;
const #363 = Asciz	scala/collection/LinearSeqLike;
const #364 = class	#363;	//  scala/collection/LinearSeqLike
const #365 = Asciz	length;
const #366 = NameAndType	#365:#317;//  length:()I
const #367 = InterfaceMethod	#364.#366;	//  scala/collection/LinearSeqLike.length:()I
const #368 = Asciz	ensureSize;
const #369 = NameAndType	#368:#20;//  ensureSize:(I)V
const #370 = InterfaceMethod	#198.#369;	//  scala/collection/mutable/ResizableArray.ensureSize:(I)V
const #371 = Asciz	()[Ljava/lang/Object;;
const #372 = NameAndType	#16:#371;//  array:()[Ljava/lang/Object;
const #373 = InterfaceMethod	#198.#372;	//  scala/collection/mutable/ResizableArray.array:()[Ljava/lang/Object;
const #374 = Asciz	copyToArray;
const #375 = Asciz	(Ljava/lang/Object;I)V;
const #376 = NameAndType	#374:#375;//  copyToArray:(Ljava/lang/Object;I)V
const #377 = InterfaceMethod	#292.#376;	//  scala/collection/TraversableLike.copyToArray:(Ljava/lang/Object;I)V
const #378 = Asciz	seq;
const #379 = Asciz	xs;
const #380 = Asciz	Lscala/collection/immutable/List;;
const #381 = Asciz	len;
const #382 = Asciz	(ILscala/collection/Traversable<TA;>;)V;
const #383 = NameAndType	#357:#358;//  insertAll:(ILscala/collection/Traversable;)V
const #384 = Method	#11.#383;	//  scala/collection/mutable/ArrayBuffer.insertAll:(ILscala/collection/Traversable;)V
const #385 = Asciz	(Lscala/collection/Traversable<TA;>;)Lscala/collection/mutable/ArrayBuffer<TA;>;;
const #386 = Asciz	(TA;)Lscala/collection/mutable/ArrayBuffer<TA;>;;
const #387 = Asciz	scala/collection/mutable/IndexedSeq;
const #388 = class	#387;	//  scala/collection/mutable/IndexedSeq
const #389 = InterfaceMethod	#276.#366;	//  scala/collection/SeqLike.length:()I
const #390 = Asciz	scala/collection/IndexedSeqLike;
const #391 = class	#390;	//  scala/collection/IndexedSeqLike
const #392 = Asciz	(Ljava/lang/Object;II)V;
const #393 = NameAndType	#374:#392;//  copyToArray:(Ljava/lang/Object;II)V
const #394 = InterfaceMethod	#391.#393;	//  scala/collection/IndexedSeqLike.copyToArray:(Ljava/lang/Object;II)V
const #395 = Asciz	scala/MatchError;
const #396 = class	#395;	//  scala/MatchError
const #397 = InterfaceMethod	#292.#327;	//  scala/collection/TraversableLike.toString:()Ljava/lang/String;
const #398 = Method	#396.#330;	//  scala/MatchError."<init>":(Ljava/lang/String;)V
const #399 = Asciz	(Lscala/collection/generic/Growable;Lscala/collection/Traversable;)Lscala/collection/generic/Growable;;
const #400 = NameAndType	#167:#399;//  $plus$plus$eq:(Lscala/collection/generic/Growable;Lscala/collection/Traversable;)Lscala/collection/generic/Growable;
const #401 = Method	#90.#400;	//  scala/collection/generic/Growable$class.$plus$plus$eq:(Lscala/collection/generic/Growable;Lscala/collection/Traversable;)Lscala/collection/generic/Growable;
const #402 = Asciz	temp2;
const #403 = Asciz	Lscala/collection/mutable/IndexedSeq;;
const #404 = Asciz	sizeHint;
const #405 = Asciz	size;
const #406 = NameAndType	#405:#317;//  size:()I
const #407 = InterfaceMethod	#276.#406;	//  scala/collection/SeqLike.size:()I
const #408 = Asciz	scala/runtime/RichInt;
const #409 = class	#408;	//  scala/runtime/RichInt
const #410 = NameAndType	#19:#20;//  "<init>":(I)V
const #411 = Method	#409.#410;	//  scala/runtime/RichInt."<init>":(I)V
const #412 = Asciz	min;
const #413 = Asciz	(I)I;
const #414 = NameAndType	#412:#413;//  min:(I)I
const #415 = Method	#409.#414;	//  scala/runtime/RichInt.min:(I)I
const #416 = Asciz	scala/Array$;
const #417 = class	#416;	//  scala/Array$
const #418 = Asciz	MODULE$;
const #419 = Asciz	Lscala/Array$;;
const #420 = NameAndType	#418:#419;//  MODULE$:Lscala/Array$;
const #421 = Field	#417.#420;	//  scala/Array$.MODULE$:Lscala/Array$;
const #422 = Asciz	(Ljava/lang/Object;ILjava/lang/Object;II)V;
const #423 = NameAndType	#332:#422;//  copy:(Ljava/lang/Object;ILjava/lang/Object;II)V
const #424 = Method	#417.#423;	//  scala/Array$.copy:(Ljava/lang/Object;ILjava/lang/Object;II)V
const #425 = Asciz	array_$eq;
const #426 = Asciz	([Ljava/lang/Object;)V;
const #427 = NameAndType	#425:#426;//  array_$eq:([Ljava/lang/Object;)V
const #428 = InterfaceMethod	#198.#427;	//  scala/collection/mutable/ResizableArray.array_$eq:([Ljava/lang/Object;)V
const #429 = Asciz	newarray;
const #430 = Asciz	clear;
const #431 = Asciz	reduceToSize;
const #432 = NameAndType	#431:#20;//  reduceToSize:(I)V
const #433 = InterfaceMethod	#198.#432;	//  scala/collection/mutable/ResizableArray.reduceToSize:(I)V
const #434 = int	16;
const #435 = Method	#11.#410;	//  scala/collection/mutable/ArrayBuffer."<init>":(I)V
const #436 = Asciz	companion;
const #437 = Asciz	()Lscala/collection/generic/GenericCompanion;;
const #438 = Asciz	scala/collection/mutable/ArrayBuffer$;
const #439 = class	#438;	//  scala/collection/mutable/ArrayBuffer$
const #440 = Asciz	Lscala/collection/mutable/ArrayBuffer$;;
const #441 = NameAndType	#418:#440;//  MODULE$:Lscala/collection/mutable/ArrayBuffer$;
const #442 = Field	#439.#441;	//  scala/collection/mutable/ArrayBuffer$.MODULE$:Lscala/collection/mutable/ArrayBuffer$;
const #443 = Asciz	()Lscala/collection/generic/GenericCompanion<Lscala/collection/mutable/ArrayBuffer;>;;
const #444 = Asciz	withFilter;
const #445 = Asciz	(Lscala/Function1;)Lscala/collection/TraversableLike$WithFilter;;
const #446 = Asciz	(Lscala/collection/TraversableLike;Lscala/Function1;)Lscala/collection/TraversableLike$WithFilter;;
const #447 = NameAndType	#444:#446;//  withFilter:(Lscala/collection/TraversableLike;Lscala/Function1;)Lscala/collection/TraversableLike$WithFilter;
const #448 = Method	#29.#447;	//  scala/collection/TraversableLike$class.withFilter:(Lscala/collection/TraversableLike;Lscala/Function1;)Lscala/collection/TraversableLike$WithFilter;
const #449 = Asciz	p;
const #450 = Asciz	addString;
const #451 = Asciz	(Lscala/collection/mutable/StringBuilder;)Lscala/collection/mutable/StringBuilder;;
const #452 = Asciz	(Lscala/collection/TraversableLike;Lscala/collection/mutable/StringBuilder;)Lscala/collection/mutable/StringBuilder;;
const #453 = NameAndType	#450:#452;//  addString:(Lscala/collection/TraversableLike;Lscala/collection/mutable/StringBuilder;)Lscala/collection/mutable/StringBuilder;
const #454 = Method	#29.#453;	//  scala/collection/TraversableLike$class.addString:(Lscala/collection/TraversableLike;Lscala/collection/mutable/StringBuilder;)Lscala/collection/mutable/StringBuilder;
const #455 = Asciz	b;
const #456 = Asciz	Lscala/collection/mutable/StringBuilder;;
const #457 = Asciz	(Lscala/collection/mutable/StringBuilder;Ljava/lang/String;)Lscala/collection/mutable/StringBuilder;;
const #458 = Asciz	(Lscala/collection/TraversableLike;Lscala/collection/mutable/StringBuilder;Ljava/lang/String;)Lscala/collection/mutable/StringBuilder;;
const #459 = NameAndType	#450:#458;//  addString:(Lscala/collection/TraversableLike;Lscala/collection/mutable/StringBuilder;Ljava/lang/String;)Lscala/collection/mutable/StringBuilder;
const #460 = Method	#29.#459;	//  scala/collection/TraversableLike$class.addString:(Lscala/collection/TraversableLike;Lscala/collection/mutable/StringBuilder;Ljava/lang/String;)Lscala/collection/mutable/StringBuilder;
const #461 = Asciz	sep;
const #462 = Asciz	Ljava/lang/String;;
const #463 = Asciz	(Lscala/collection/mutable/StringBuilder;Ljava/lang/String;Ljava/lang/String;Ljava/lang/String;)Lscala/collection/mutable/StringBuilder;;
const #464 = Asciz	(Lscala/collection/TraversableLike;Lscala/collection/mutable/StringBuilder;Ljava/lang/String;Ljava/lang/String;Ljava/lang/String;)Lscala/collection/mutable/StringBuilder;;
const #465 = NameAndType	#450:#464;//  addString:(Lscala/collection/TraversableLike;Lscala/collection/mutable/StringBuilder;Ljava/lang/String;Ljava/lang/String;Ljava/lang/String;)Lscala/collection/mutable/StringBuilder;
const #466 = Method	#29.#465;	//  scala/collection/TraversableLike$class.addString:(Lscala/collection/TraversableLike;Lscala/collection/mutable/StringBuilder;Ljava/lang/String;Ljava/lang/String;Ljava/lang/String;)Lscala/collection/mutable/StringBuilder;
const #467 = Asciz	start;
const #468 = Asciz	end;
const #469 = Asciz	mkString;
const #470 = Asciz	(Lscala/collection/TraversableLike;)Ljava/lang/String;;
const #471 = NameAndType	#469:#470;//  mkString:(Lscala/collection/TraversableLike;)Ljava/lang/String;
const #472 = Method	#29.#471;	//  scala/collection/TraversableLike$class.mkString:(Lscala/collection/TraversableLike;)Ljava/lang/String;
const #473 = Asciz	(Ljava/lang/String;)Ljava/lang/String;;
const #474 = Asciz	(Lscala/collection/TraversableLike;Ljava/lang/String;)Ljava/lang/String;;
const #475 = NameAndType	#469:#474;//  mkString:(Lscala/collection/TraversableLike;Ljava/lang/String;)Ljava/lang/String;
const #476 = Method	#29.#475;	//  scala/collection/TraversableLike$class.mkString:(Lscala/collection/TraversableLike;Ljava/lang/String;)Ljava/lang/String;
const #477 = Asciz	(Ljava/lang/String;Ljava/lang/String;Ljava/lang/String;)Ljava/lang/String;;
const #478 = Asciz	(Lscala/collection/TraversableLike;Ljava/lang/String;Ljava/lang/String;Ljava/lang/String;)Ljava/lang/String;;
const #479 = NameAndType	#469:#478;//  mkString:(Lscala/collection/TraversableLike;Ljava/lang/String;Ljava/lang/String;Ljava/lang/String;)Ljava/lang/String;
const #480 = Method	#29.#479;	//  scala/collection/TraversableLike$class.mkString:(Lscala/collection/TraversableLike;Ljava/lang/String;Ljava/lang/String;Ljava/lang/String;)Ljava/lang/String;
const #481 = Asciz	toSet;
const #482 = Asciz	()Lscala/collection/immutable/Set;;
const #483 = Asciz	(Lscala/collection/TraversableLike;)Lscala/collection/immutable/Set;;
const #484 = NameAndType	#481:#483;//  toSet:(Lscala/collection/TraversableLike;)Lscala/collection/immutable/Set;
const #485 = Method	#29.#484;	//  scala/collection/TraversableLike$class.toSet:(Lscala/collection/TraversableLike;)Lscala/collection/immutable/Set;
const #486 = Asciz	toIndexedSeq;
const #487 = Asciz	(Lscala/collection/TraversableLike;)Lscala/collection/mutable/IndexedSeq;;
const #488 = NameAndType	#486:#487;//  toIndexedSeq:(Lscala/collection/TraversableLike;)Lscala/collection/mutable/IndexedSeq;
const #489 = Method	#29.#488;	//  scala/collection/TraversableLike$class.toIndexedSeq:(Lscala/collection/TraversableLike;)Lscala/collection/mutable/IndexedSeq;
const #490 = Asciz	(Lscala/collection/TraversableLike;)Lscala/collection/immutable/List;;
const #491 = NameAndType	#359:#490;//  toList:(Lscala/collection/TraversableLike;)Lscala/collection/immutable/List;
const #492 = Method	#29.#491;	//  scala/collection/TraversableLike$class.toList:(Lscala/collection/TraversableLike;)Lscala/collection/immutable/List;
const #493 = Asciz	toArray;
const #494 = Asciz	(Lscala/reflect/ClassManifest;)Ljava/lang/Object;;
const #495 = Asciz	(Lscala/collection/TraversableLike;Lscala/reflect/ClassManifest;)Ljava/lang/Object;;
const #496 = NameAndType	#493:#495;//  toArray:(Lscala/collection/TraversableLike;Lscala/reflect/ClassManifest;)Ljava/lang/Object;
const #497 = Method	#29.#496;	//  scala/collection/TraversableLike$class.toArray:(Lscala/collection/TraversableLike;Lscala/reflect/ClassManifest;)Ljava/lang/Object;
const #498 = Asciz	evidence$1;
const #499 = Asciz	Lscala/reflect/ClassManifest;;
const #500 = Asciz	(Ljava/lang/Object;)V;
const #501 = Asciz	(Lscala/collection/TraversableLike;Ljava/lang/Object;)V;
const #502 = NameAndType	#374:#501;//  copyToArray:(Lscala/collection/TraversableLike;Ljava/lang/Object;)V
const #503 = Method	#29.#502;	//  scala/collection/TraversableLike$class.copyToArray:(Lscala/collection/TraversableLike;Ljava/lang/Object;)V
const #504 = Asciz	(Lscala/collection/TraversableLike;Ljava/lang/Object;I)V;
const #505 = NameAndType	#374:#504;//  copyToArray:(Lscala/collection/TraversableLike;Ljava/lang/Object;I)V
const #506 = Method	#29.#505;	//  scala/collection/TraversableLike$class.copyToArray:(Lscala/collection/TraversableLike;Ljava/lang/Object;I)V
const #507 = Asciz	copyToBuffer;
const #508 = Asciz	(Lscala/collection/TraversableLike;Lscala/collection/mutable/Buffer;)V;
const #509 = NameAndType	#507:#508;//  copyToBuffer:(Lscala/collection/TraversableLike;Lscala/collection/mutable/Buffer;)V
const #510 = Method	#29.#509;	//  scala/collection/TraversableLike$class.copyToBuffer:(Lscala/collection/TraversableLike;Lscala/collection/mutable/Buffer;)V
const #511 = Asciz	dest;
const #512 = Asciz	Lscala/collection/mutable/Buffer;;
const #513 = Asciz	lastOption;
const #514 = Asciz	()Lscala/Option;;
const #515 = Asciz	(Lscala/collection/TraversableLike;)Lscala/Option;;
const #516 = NameAndType	#513:#515;//  lastOption:(Lscala/collection/TraversableLike;)Lscala/Option;
const #517 = Method	#29.#516;	//  scala/collection/TraversableLike$class.lastOption:(Lscala/collection/TraversableLike;)Lscala/Option;
const #518 = Asciz	headOption;
const #519 = NameAndType	#518:#515;//  headOption:(Lscala/collection/TraversableLike;)Lscala/Option;
const #520 = Method	#29.#519;	//  scala/collection/TraversableLike$class.headOption:(Lscala/collection/TraversableLike;)Lscala/Option;
const #521 = Asciz	max;
const #522 = Asciz	(Lscala/math/Ordering;)Ljava/lang/Object;;
const #523 = Asciz	(Lscala/collection/TraversableLike;Lscala/math/Ordering;)Ljava/lang/Object;;
const #524 = NameAndType	#521:#523;//  max:(Lscala/collection/TraversableLike;Lscala/math/Ordering;)Ljava/lang/Object;
const #525 = Method	#29.#524;	//  scala/collection/TraversableLike$class.max:(Lscala/collection/TraversableLike;Lscala/math/Ordering;)Ljava/lang/Object;
const #526 = Asciz	cmp;
const #527 = Asciz	Lscala/math/Ordering;;
const #528 = NameAndType	#412:#523;//  min:(Lscala/collection/TraversableLike;Lscala/math/Ordering;)Ljava/lang/Object;
const #529 = Method	#29.#528;	//  scala/collection/TraversableLike$class.min:(Lscala/collection/TraversableLike;Lscala/math/Ordering;)Ljava/lang/Object;
const #530 = Asciz	product;
const #531 = Asciz	(Lscala/math/Numeric;)Ljava/lang/Object;;
const #532 = Asciz	(Lscala/collection/TraversableLike;Lscala/math/Numeric;)Ljava/lang/Object;;
const #533 = NameAndType	#530:#532;//  product:(Lscala/collection/TraversableLike;Lscala/math/Numeric;)Ljava/lang/Object;
const #534 = Method	#29.#533;	//  scala/collection/TraversableLike$class.product:(Lscala/collection/TraversableLike;Lscala/math/Numeric;)Ljava/lang/Object;
const #535 = Asciz	num;
const #536 = Asciz	Lscala/math/Numeric;;
const #537 = Asciz	sum;
const #538 = NameAndType	#537:#532;//  sum:(Lscala/collection/TraversableLike;Lscala/math/Numeric;)Ljava/lang/Object;
const #539 = Method	#29.#538;	//  scala/collection/TraversableLike$class.sum:(Lscala/collection/TraversableLike;Lscala/math/Numeric;)Ljava/lang/Object;
const #540 = Asciz	reduceRightOption;
const #541 = Asciz	(Lscala/Function2;)Lscala/Option;;
const #542 = Asciz	(Lscala/collection/TraversableLike;Lscala/Function2;)Lscala/Option;;
const #543 = NameAndType	#540:#542;//  reduceRightOption:(Lscala/collection/TraversableLike;Lscala/Function2;)Lscala/Option;
const #544 = Method	#29.#543;	//  scala/collection/TraversableLike$class.reduceRightOption:(Lscala/collection/TraversableLike;Lscala/Function2;)Lscala/Option;
const #545 = Asciz	op;
const #546 = Asciz	Lscala/Function2;;
const #547 = Asciz	reduceLeftOption;
const #548 = NameAndType	#547:#542;//  reduceLeftOption:(Lscala/collection/TraversableLike;Lscala/Function2;)Lscala/Option;
const #549 = Method	#29.#548;	//  scala/collection/TraversableLike$class.reduceLeftOption:(Lscala/collection/TraversableLike;Lscala/Function2;)Lscala/Option;
const #550 = Asciz	$colon$bslash;
const #551 = Asciz	(Ljava/lang/Object;Lscala/Function2;)Ljava/lang/Object;;
const #552 = Asciz	(Lscala/collection/TraversableLike;Ljava/lang/Object;Lscala/Function2;)Ljava/lang/Object;;
const #553 = NameAndType	#550:#552;//  $colon$bslash:(Lscala/collection/TraversableLike;Ljava/lang/Object;Lscala/Function2;)Ljava/lang/Object;
const #554 = Method	#29.#553;	//  scala/collection/TraversableLike$class.$colon$bslash:(Lscala/collection/TraversableLike;Ljava/lang/Object;Lscala/Function2;)Ljava/lang/Object;
const #555 = Asciz	z;
const #556 = Asciz	$div$colon;
const #557 = NameAndType	#556:#552;//  $div$colon:(Lscala/collection/TraversableLike;Ljava/lang/Object;Lscala/Function2;)Ljava/lang/Object;
const #558 = Method	#29.#557;	//  scala/collection/TraversableLike$class.$div$colon:(Lscala/collection/TraversableLike;Ljava/lang/Object;Lscala/Function2;)Ljava/lang/Object;
const #559 = Asciz	(Lscala/Function1;)I;
const #560 = Asciz	(Lscala/collection/TraversableLike;Lscala/Function1;)I;
const #561 = NameAndType	#354:#560;//  count:(Lscala/collection/TraversableLike;Lscala/Function1;)I
const #562 = Method	#29.#561;	//  scala/collection/TraversableLike$class.count:(Lscala/collection/TraversableLike;Lscala/Function1;)I
const #563 = Asciz	groupBy;
const #564 = Asciz	(Lscala/Function1;)Lscala/collection/Map;;
const #565 = Asciz	(Lscala/collection/TraversableLike;Lscala/Function1;)Lscala/collection/Map;;
const #566 = NameAndType	#563:#565;//  groupBy:(Lscala/collection/TraversableLike;Lscala/Function1;)Lscala/collection/Map;
const #567 = Method	#29.#566;	//  scala/collection/TraversableLike$class.groupBy:(Lscala/collection/TraversableLike;Lscala/Function1;)Lscala/collection/Map;
const #568 = Asciz	f;
const #569 = Asciz	partition;
const #570 = Asciz	(Lscala/Function1;)Lscala/Tuple2;;
const #571 = Asciz	(Lscala/collection/TraversableLike;Lscala/Function1;)Lscala/Tuple2;;
const #572 = NameAndType	#569:#571;//  partition:(Lscala/collection/TraversableLike;Lscala/Function1;)Lscala/Tuple2;
const #573 = Method	#29.#572;	//  scala/collection/TraversableLike$class.partition:(Lscala/collection/TraversableLike;Lscala/Function1;)Lscala/Tuple2;
const #574 = Asciz	partialMap;
const #575 = Asciz	(Lscala/PartialFunction;Lscala/collection/generic/CanBuildFrom;)Ljava/lang/Object;;
const #576 = Asciz	(Lscala/collection/TraversableLike;Lscala/PartialFunction;Lscala/collection/generic/CanBuildFrom;)Ljava/lang/Object;;
const #577 = NameAndType	#574:#576;//  partialMap:(Lscala/collection/TraversableLike;Lscala/PartialFunction;Lscala/collection/generic/CanBuildFrom;)Ljava/lang/Object;
const #578 = Method	#29.#577;	//  scala/collection/TraversableLike$class.partialMap:(Lscala/collection/TraversableLike;Lscala/PartialFunction;Lscala/collection/generic/CanBuildFrom;)Ljava/lang/Object;
const #579 = Asciz	pf;
const #580 = Asciz	Lscala/PartialFunction;;
const #581 = Asciz	bf;
const #582 = Asciz	Lscala/collection/generic/CanBuildFrom;;
const #583 = Asciz	filterNot;
const #584 = Asciz	(Lscala/Function1;)Ljava/lang/Object;;
const #585 = Asciz	(Lscala/collection/TraversableLike;Lscala/Function1;)Ljava/lang/Object;;
const #586 = NameAndType	#583:#585;//  filterNot:(Lscala/collection/TraversableLike;Lscala/Function1;)Ljava/lang/Object;
const #587 = Method	#29.#586;	//  scala/collection/TraversableLike$class.filterNot:(Lscala/collection/TraversableLike;Lscala/Function1;)Ljava/lang/Object;
const #588 = Asciz	filter;
const #589 = NameAndType	#588:#585;//  filter:(Lscala/collection/TraversableLike;Lscala/Function1;)Ljava/lang/Object;
const #590 = Method	#29.#589;	//  scala/collection/TraversableLike$class.filter:(Lscala/collection/TraversableLike;Lscala/Function1;)Ljava/lang/Object;
const #591 = Asciz	flatMap;
const #592 = Asciz	(Lscala/Function1;Lscala/collection/generic/CanBuildFrom;)Ljava/lang/Object;;
const #593 = Asciz	(Lscala/collection/TraversableLike;Lscala/Function1;Lscala/collection/generic/CanBuildFrom;)Ljava/lang/Object;;
const #594 = NameAndType	#591:#593;//  flatMap:(Lscala/collection/TraversableLike;Lscala/Function1;Lscala/collection/generic/CanBuildFrom;)Ljava/lang/Object;
const #595 = Method	#29.#594;	//  scala/collection/TraversableLike$class.flatMap:(Lscala/collection/TraversableLike;Lscala/Function1;Lscala/collection/generic/CanBuildFrom;)Ljava/lang/Object;
const #596 = Asciz	map;
const #597 = NameAndType	#596:#593;//  map:(Lscala/collection/TraversableLike;Lscala/Function1;Lscala/collection/generic/CanBuildFrom;)Ljava/lang/Object;
const #598 = Method	#29.#597;	//  scala/collection/TraversableLike$class.map:(Lscala/collection/TraversableLike;Lscala/Function1;Lscala/collection/generic/CanBuildFrom;)Ljava/lang/Object;
const #599 = Asciz	(Lscala/collection/Iterator;Lscala/collection/generic/CanBuildFrom;)Ljava/lang/Object;;
const #600 = Asciz	(Lscala/collection/TraversableLike;Lscala/collection/Iterator;Lscala/collection/generic/CanBuildFrom;)Ljava/lang/Object;;
const #601 = NameAndType	#249:#600;//  $plus$plus:(Lscala/collection/TraversableLike;Lscala/collection/Iterator;Lscala/collection/generic/CanBuildFrom;)Ljava/lang/Object;
const #602 = Method	#29.#601;	//  scala/collection/TraversableLike$class.$plus$plus:(Lscala/collection/TraversableLike;Lscala/collection/Iterator;Lscala/collection/generic/CanBuildFrom;)Ljava/lang/Object;
const #603 = Asciz	that;
const #604 = Asciz	(Lscala/collection/Traversable;Lscala/collection/generic/CanBuildFrom;)Ljava/lang/Object;;
const #605 = Asciz	(Lscala/collection/TraversableLike;Lscala/collection/Traversable;Lscala/collection/generic/CanBuildFrom;)Ljava/lang/Object;;
const #606 = NameAndType	#249:#605;//  $plus$plus:(Lscala/collection/TraversableLike;Lscala/collection/Traversable;Lscala/collection/generic/CanBuildFrom;)Ljava/lang/Object;
const #607 = Method	#29.#606;	//  scala/collection/TraversableLike$class.$plus$plus:(Lscala/collection/TraversableLike;Lscala/collection/Traversable;Lscala/collection/generic/CanBuildFrom;)Ljava/lang/Object;
const #608 = Asciz	hasDefiniteSize;
const #609 = Asciz	()Z;
const #610 = Asciz	(Lscala/collection/TraversableLike;)Z;
const #611 = NameAndType	#608:#610;//  hasDefiniteSize:(Lscala/collection/TraversableLike;)Z
const #612 = Method	#29.#611;	//  scala/collection/TraversableLike$class.hasDefiniteSize:(Lscala/collection/TraversableLike;)Z
const #613 = Asciz	nonEmpty;
const #614 = NameAndType	#613:#610;//  nonEmpty:(Lscala/collection/TraversableLike;)Z
const #615 = Method	#29.#614;	//  scala/collection/TraversableLike$class.nonEmpty:(Lscala/collection/TraversableLike;)Z
const #616 = Asciz	(Lscala/collection/TraversableLike;)Ljava/lang/Object;;
const #617 = NameAndType	#218:#616;//  repr:(Lscala/collection/TraversableLike;)Ljava/lang/Object;
const #618 = Method	#29.#617;	//  scala/collection/TraversableLike$class.repr:(Lscala/collection/TraversableLike;)Ljava/lang/Object;
const #619 = Asciz	transpose;
const #620 = Asciz	(Lscala/Function1;)Lscala/collection/Traversable;;
const #621 = Asciz	(Lscala/collection/generic/GenericTraversableTemplate;Lscala/Function1;)Lscala/collection/Traversable;;
const #622 = NameAndType	#619:#621;//  transpose:(Lscala/collection/generic/GenericTraversableTemplate;Lscala/Function1;)Lscala/collection/Traversable;
const #623 = Method	#35.#622;	//  scala/collection/generic/GenericTraversableTemplate$class.transpose:(Lscala/collection/generic/GenericTraversableTemplate;Lscala/Function1;)Lscala/collection/Traversable;
const #624 = Asciz	asTraversable;
const #625 = Asciz	flatten;
const #626 = NameAndType	#625:#621;//  flatten:(Lscala/collection/generic/GenericTraversableTemplate;Lscala/Function1;)Lscala/collection/Traversable;
const #627 = Method	#35.#626;	//  scala/collection/generic/GenericTraversableTemplate$class.flatten:(Lscala/collection/generic/GenericTraversableTemplate;Lscala/Function1;)Lscala/collection/Traversable;
const #628 = Asciz	unzip;
const #629 = Asciz	(Lscala/collection/generic/GenericTraversableTemplate;Lscala/Function1;)Lscala/Tuple2;;
const #630 = NameAndType	#628:#629;//  unzip:(Lscala/collection/generic/GenericTraversableTemplate;Lscala/Function1;)Lscala/Tuple2;
const #631 = Method	#35.#630;	//  scala/collection/generic/GenericTraversableTemplate$class.unzip:(Lscala/collection/generic/GenericTraversableTemplate;Lscala/Function1;)Lscala/Tuple2;
const #632 = Asciz	asPair;
const #633 = Asciz	genericBuilder;
const #634 = Asciz	()Lscala/collection/mutable/Builder;;
const #635 = Asciz	(Lscala/collection/generic/GenericTraversableTemplate;)Lscala/collection/mutable/Builder;;
const #636 = NameAndType	#633:#635;//  genericBuilder:(Lscala/collection/generic/GenericTraversableTemplate;)Lscala/collection/mutable/Builder;
const #637 = Method	#35.#636;	//  scala/collection/generic/GenericTraversableTemplate$class.genericBuilder:(Lscala/collection/generic/GenericTraversableTemplate;)Lscala/collection/mutable/Builder;
const #638 = Asciz	newBuilder;
const #639 = NameAndType	#638:#635;//  newBuilder:(Lscala/collection/generic/GenericTraversableTemplate;)Lscala/collection/mutable/Builder;
const #640 = Method	#35.#639;	//  scala/collection/generic/GenericTraversableTemplate$class.newBuilder:(Lscala/collection/generic/GenericTraversableTemplate;)Lscala/collection/mutable/Builder;
const #641 = Asciz	firstOption;
const #642 = Asciz	(Lscala/collection/IterableLike;)Lscala/Option;;
const #643 = NameAndType	#641:#642;//  firstOption:(Lscala/collection/IterableLike;)Lscala/Option;
const #644 = Method	#50.#643;	//  scala/collection/IterableLike$class.firstOption:(Lscala/collection/IterableLike;)Lscala/Option;
const #645 = Asciz	Deprecated;
const #646 = Asciz	first;
const #647 = Asciz	(Lscala/collection/IterableLike;)Ljava/lang/Object;;
const #648 = NameAndType	#646:#647;//  first:(Lscala/collection/IterableLike;)Ljava/lang/Object;
const #649 = Method	#50.#648;	//  scala/collection/IterableLike$class.first:(Lscala/collection/IterableLike;)Ljava/lang/Object;
const #650 = Asciz	canEqual;
const #651 = Asciz	(Lscala/collection/IterableLike;Ljava/lang/Object;)Z;
const #652 = NameAndType	#650:#651;//  canEqual:(Lscala/collection/IterableLike;Ljava/lang/Object;)Z
const #653 = Method	#50.#652;	//  scala/collection/IterableLike$class.canEqual:(Lscala/collection/IterableLike;Ljava/lang/Object;)Z
const #654 = Asciz	toStream;
const #655 = Asciz	()Lscala/collection/immutable/Stream;;
const #656 = Asciz	(Lscala/collection/IterableLike;)Lscala/collection/immutable/Stream;;
const #657 = NameAndType	#654:#656;//  toStream:(Lscala/collection/IterableLike;)Lscala/collection/immutable/Stream;
const #658 = Method	#50.#657;	//  scala/collection/IterableLike$class.toStream:(Lscala/collection/IterableLike;)Lscala/collection/immutable/Stream;
const #659 = Asciz	zipAll;
const #660 = Asciz	(Lscala/collection/Iterable;Ljava/lang/Object;Ljava/lang/Object;Lscala/collection/generic/CanBuildFrom;)Ljava/lang/Object;;
const #661 = Asciz	(Lscala/collection/IterableLike;Lscala/collection/Iterable;Ljava/lang/Object;Ljava/lang/Object;Lscala/collection/generic/CanBuildFrom;)Ljava/lang/Object;;
const #662 = NameAndType	#659:#661;//  zipAll:(Lscala/collection/IterableLike;Lscala/collection/Iterable;Ljava/lang/Object;Ljava/lang/Object;Lscala/collection/generic/CanBuildFrom;)Ljava/lang/Object;
const #663 = Method	#50.#662;	//  scala/collection/IterableLike$class.zipAll:(Lscala/collection/IterableLike;Lscala/collection/Iterable;Ljava/lang/Object;Ljava/lang/Object;Lscala/collection/generic/CanBuildFrom;)Ljava/lang/Object;
const #664 = Asciz	Lscala/collection/Iterable;;
const #665 = Asciz	thisElem;
const #666 = Asciz	thatElem;
const #667 = Asciz	toIterable;
const #668 = Asciz	(Lscala/collection/IterableLike;)Lscala/collection/Iterable;;
const #669 = NameAndType	#667:#668;//  toIterable:(Lscala/collection/IterableLike;)Lscala/collection/Iterable;
const #670 = Method	#50.#669;	//  scala/collection/IterableLike$class.toIterable:(Lscala/collection/IterableLike;)Lscala/collection/Iterable;
const #671 = Asciz	elements;
const #672 = Asciz	()Lscala/collection/Iterator;;
const #673 = Asciz	(Lscala/collection/IterableLike;)Lscala/collection/Iterator;;
const #674 = NameAndType	#671:#673;//  elements:(Lscala/collection/IterableLike;)Lscala/collection/Iterator;
const #675 = Method	#50.#674;	//  scala/collection/IterableLike$class.elements:(Lscala/collection/IterableLike;)Lscala/collection/Iterator;
const #676 = Asciz	compose;
const #677 = Asciz	(Lscala/Function1;Lscala/Function1;)Lscala/Function1;;
const #678 = NameAndType	#676:#677;//  compose:(Lscala/Function1;Lscala/Function1;)Lscala/Function1;
const #679 = Method	#65.#678;	//  scala/Function1$class.compose:(Lscala/Function1;Lscala/Function1;)Lscala/Function1;
const #680 = Asciz	lift;
const #681 = Asciz	()Lscala/Function1;;
const #682 = Asciz	(Lscala/PartialFunction;)Lscala/Function1;;
const #683 = NameAndType	#680:#682;//  lift:(Lscala/PartialFunction;)Lscala/Function1;
const #684 = Method	#70.#683;	//  scala/PartialFunction$class.lift:(Lscala/PartialFunction;)Lscala/Function1;
const #685 = Asciz	(Lscala/PartialFunction;Lscala/Function1;)Lscala/PartialFunction;;
const #686 = NameAndType	#281:#685;//  andThen:(Lscala/PartialFunction;Lscala/Function1;)Lscala/PartialFunction;
const #687 = Method	#70.#686;	//  scala/PartialFunction$class.andThen:(Lscala/PartialFunction;Lscala/Function1;)Lscala/PartialFunction;
const #688 = Asciz	k;
const #689 = Asciz	orElse;
const #690 = Asciz	(Lscala/PartialFunction;)Lscala/PartialFunction;;
const #691 = Asciz	(Lscala/PartialFunction;Lscala/PartialFunction;)Lscala/PartialFunction;;
const #692 = NameAndType	#689:#691;//  orElse:(Lscala/PartialFunction;Lscala/PartialFunction;)Lscala/PartialFunction;
const #693 = Method	#70.#692;	//  scala/PartialFunction$class.orElse:(Lscala/PartialFunction;Lscala/PartialFunction;)Lscala/PartialFunction;
const #694 = Asciz	projection;
const #695 = Asciz	(Lscala/collection/SeqLike;)Ljava/lang/Object;;
const #696 = NameAndType	#694:#695;//  projection:(Lscala/collection/SeqLike;)Ljava/lang/Object;
const #697 = Method	#75.#696;	//  scala/collection/SeqLike$class.projection:(Lscala/collection/SeqLike;)Ljava/lang/Object;
const #698 = Asciz	equalsWith;
const #699 = Asciz	(Lscala/collection/Seq;Lscala/Function2;)Z;
const #700 = Asciz	(Lscala/collection/SeqLike;Lscala/collection/Seq;Lscala/Function2;)Z;
const #701 = NameAndType	#698:#700;//  equalsWith:(Lscala/collection/SeqLike;Lscala/collection/Seq;Lscala/Function2;)Z
const #702 = Method	#75.#701;	//  scala/collection/SeqLike$class.equalsWith:(Lscala/collection/SeqLike;Lscala/collection/Seq;Lscala/Function2;)Z
const #703 = Asciz	findLastIndexOf;
const #704 = Asciz	(Lscala/collection/SeqLike;Lscala/Function1;)I;
const #705 = NameAndType	#703:#704;//  findLastIndexOf:(Lscala/collection/SeqLike;Lscala/Function1;)I
const #706 = Method	#75.#705;	//  scala/collection/SeqLike$class.findLastIndexOf:(Lscala/collection/SeqLike;Lscala/Function1;)I
const #707 = Asciz	(Lscala/collection/SeqLike;)Ljava/lang/String;;
const #708 = NameAndType	#326:#707;//  toString:(Lscala/collection/SeqLike;)Ljava/lang/String;
const #709 = Method	#75.#708;	//  scala/collection/SeqLike$class.toString:(Lscala/collection/SeqLike;)Ljava/lang/String;
const #710 = Asciz	equals;
const #711 = Asciz	(Lscala/collection/SeqLike;Ljava/lang/Object;)Z;
const #712 = NameAndType	#710:#711;//  equals:(Lscala/collection/SeqLike;Ljava/lang/Object;)Z
const #713 = Method	#75.#712;	//  scala/collection/SeqLike$class.equals:(Lscala/collection/SeqLike;Ljava/lang/Object;)Z
const #714 = Asciz	hashCode;
const #715 = Asciz	(Lscala/collection/SeqLike;)I;
const #716 = NameAndType	#714:#715;//  hashCode:(Lscala/collection/SeqLike;)I
const #717 = Method	#75.#716;	//  scala/collection/SeqLike$class.hashCode:(Lscala/collection/SeqLike;)I
const #718 = Asciz	indices;
const #719 = Asciz	()Lscala/collection/immutable/Range;;
const #720 = Asciz	(Lscala/collection/SeqLike;)Lscala/collection/immutable/Range;;
const #721 = NameAndType	#718:#720;//  indices:(Lscala/collection/SeqLike;)Lscala/collection/immutable/Range;
const #722 = Method	#75.#721;	//  scala/collection/SeqLike$class.indices:(Lscala/collection/SeqLike;)Lscala/collection/immutable/Range;
const #723 = Asciz	toSeq;
const #724 = Asciz	(Lscala/collection/SeqLike;)Lscala/collection/Seq;;
const #725 = NameAndType	#723:#724;//  toSeq:(Lscala/collection/SeqLike;)Lscala/collection/Seq;
const #726 = Method	#75.#725;	//  scala/collection/SeqLike$class.toSeq:(Lscala/collection/SeqLike;)Lscala/collection/Seq;
const #727 = Asciz	sortBy;
const #728 = Asciz	(Lscala/Function1;Lscala/math/Ordering;)Ljava/lang/Object;;
const #729 = Asciz	(Lscala/collection/SeqLike;Lscala/Function1;Lscala/math/Ordering;)Ljava/lang/Object;;
const #730 = NameAndType	#727:#729;//  sortBy:(Lscala/collection/SeqLike;Lscala/Function1;Lscala/math/Ordering;)Ljava/lang/Object;
const #731 = Method	#75.#730;	//  scala/collection/SeqLike$class.sortBy:(Lscala/collection/SeqLike;Lscala/Function1;Lscala/math/Ordering;)Ljava/lang/Object;
const #732 = Asciz	ord;
const #733 = Asciz	sortWith;
const #734 = Asciz	(Lscala/collection/SeqLike;Lscala/math/Ordering;)Ljava/lang/Object;;
const #735 = NameAndType	#733:#734;//  sortWith:(Lscala/collection/SeqLike;Lscala/math/Ordering;)Ljava/lang/Object;
const #736 = Method	#75.#735;	//  scala/collection/SeqLike$class.sortWith:(Lscala/collection/SeqLike;Lscala/math/Ordering;)Ljava/lang/Object;
const #737 = Asciz	(Lscala/Function2;)Ljava/lang/Object;;
const #738 = Asciz	(Lscala/collection/SeqLike;Lscala/Function2;)Ljava/lang/Object;;
const #739 = NameAndType	#733:#738;//  sortWith:(Lscala/collection/SeqLike;Lscala/Function2;)Ljava/lang/Object;
const #740 = Method	#75.#739;	//  scala/collection/SeqLike$class.sortWith:(Lscala/collection/SeqLike;Lscala/Function2;)Ljava/lang/Object;
const #741 = Asciz	lt;
const #742 = Asciz	corresponds;
const #743 = NameAndType	#742:#700;//  corresponds:(Lscala/collection/SeqLike;Lscala/collection/Seq;Lscala/Function2;)Z
const #744 = Method	#75.#743;	//  scala/collection/SeqLike$class.corresponds:(Lscala/collection/SeqLike;Lscala/collection/Seq;Lscala/Function2;)Z
const #745 = Asciz	padTo;
const #746 = Asciz	(ILjava/lang/Object;Lscala/collection/generic/CanBuildFrom;)Ljava/lang/Object;;
const #747 = Asciz	(Lscala/collection/SeqLike;ILjava/lang/Object;Lscala/collection/generic/CanBuildFrom;)Ljava/lang/Object;;
const #748 = NameAndType	#745:#747;//  padTo:(Lscala/collection/SeqLike;ILjava/lang/Object;Lscala/collection/generic/CanBuildFrom;)Ljava/lang/Object;
const #749 = Method	#75.#748;	//  scala/collection/SeqLike$class.padTo:(Lscala/collection/SeqLike;ILjava/lang/Object;Lscala/collection/generic/CanBuildFrom;)Ljava/lang/Object;
const #750 = Asciz	$colon$plus;
const #751 = Asciz	(Ljava/lang/Object;Lscala/collection/generic/CanBuildFrom;)Ljava/lang/Object;;
const #752 = Asciz	(Lscala/collection/SeqLike;Ljava/lang/Object;Lscala/collection/generic/CanBuildFrom;)Ljava/lang/Object;;
const #753 = NameAndType	#750:#752;//  $colon$plus:(Lscala/collection/SeqLike;Ljava/lang/Object;Lscala/collection/generic/CanBuildFrom;)Ljava/lang/Object;
const #754 = Method	#75.#753;	//  scala/collection/SeqLike$class.$colon$plus:(Lscala/collection/SeqLike;Ljava/lang/Object;Lscala/collection/generic/CanBuildFrom;)Ljava/lang/Object;
const #755 = Asciz	$plus$colon;
const #756 = NameAndType	#755:#752;//  $plus$colon:(Lscala/collection/SeqLike;Ljava/lang/Object;Lscala/collection/generic/CanBuildFrom;)Ljava/lang/Object;
const #757 = Method	#75.#756;	//  scala/collection/SeqLike$class.$plus$colon:(Lscala/collection/SeqLike;Ljava/lang/Object;Lscala/collection/generic/CanBuildFrom;)Ljava/lang/Object;
const #758 = Asciz	updated;
const #759 = NameAndType	#758:#747;//  updated:(Lscala/collection/SeqLike;ILjava/lang/Object;Lscala/collection/generic/CanBuildFrom;)Ljava/lang/Object;
const #760 = Method	#75.#759;	//  scala/collection/SeqLike$class.updated:(Lscala/collection/SeqLike;ILjava/lang/Object;Lscala/collection/generic/CanBuildFrom;)Ljava/lang/Object;
const #761 = Asciz	index;
const #762 = Asciz	patch;
const #763 = Asciz	(ILscala/collection/Seq;ILscala/collection/generic/CanBuildFrom;)Ljava/lang/Object;;
const #764 = Asciz	(Lscala/collection/SeqLike;ILscala/collection/Seq;ILscala/collection/generic/CanBuildFrom;)Ljava/lang/Object;;
const #765 = NameAndType	#762:#764;//  patch:(Lscala/collection/SeqLike;ILscala/collection/Seq;ILscala/collection/generic/CanBuildFrom;)Ljava/lang/Object;
const #766 = Method	#75.#765;	//  scala/collection/SeqLike$class.patch:(Lscala/collection/SeqLike;ILscala/collection/Seq;ILscala/collection/generic/CanBuildFrom;)Ljava/lang/Object;
const #767 = Asciz	replaced;
const #768 = Asciz	removeDuplicates;
const #769 = NameAndType	#768:#695;//  removeDuplicates:(Lscala/collection/SeqLike;)Ljava/lang/Object;
const #770 = Method	#75.#769;	//  scala/collection/SeqLike$class.removeDuplicates:(Lscala/collection/SeqLike;)Ljava/lang/Object;
const #771 = Asciz	intersect;
const #772 = Asciz	(Lscala/collection/Seq;)Ljava/lang/Object;;
const #773 = Asciz	(Lscala/collection/SeqLike;Lscala/collection/Seq;)Ljava/lang/Object;;
const #774 = NameAndType	#771:#773;//  intersect:(Lscala/collection/SeqLike;Lscala/collection/Seq;)Ljava/lang/Object;
const #775 = Method	#75.#774;	//  scala/collection/SeqLike$class.intersect:(Lscala/collection/SeqLike;Lscala/collection/Seq;)Ljava/lang/Object;
const #776 = Asciz	diff;
const #777 = NameAndType	#776:#773;//  diff:(Lscala/collection/SeqLike;Lscala/collection/Seq;)Ljava/lang/Object;
const #778 = Method	#75.#777;	//  scala/collection/SeqLike$class.diff:(Lscala/collection/SeqLike;Lscala/collection/Seq;)Ljava/lang/Object;
const #779 = Asciz	union;
const #780 = Asciz	(Lscala/collection/Seq;Lscala/collection/generic/CanBuildFrom;)Ljava/lang/Object;;
const #781 = Asciz	(Lscala/collection/SeqLike;Lscala/collection/Seq;Lscala/collection/generic/CanBuildFrom;)Ljava/lang/Object;;
const #782 = NameAndType	#779:#781;//  union:(Lscala/collection/SeqLike;Lscala/collection/Seq;Lscala/collection/generic/CanBuildFrom;)Ljava/lang/Object;
const #783 = Method	#75.#782;	//  scala/collection/SeqLike$class.union:(Lscala/collection/SeqLike;Lscala/collection/Seq;Lscala/collection/generic/CanBuildFrom;)Ljava/lang/Object;
const #784 = Asciz	contains;
const #785 = NameAndType	#784:#711;//  contains:(Lscala/collection/SeqLike;Ljava/lang/Object;)Z
const #786 = Method	#75.#785;	//  scala/collection/SeqLike$class.contains:(Lscala/collection/SeqLike;Ljava/lang/Object;)Z
const #787 = Asciz	containsSlice;
const #788 = Asciz	(Lscala/collection/Seq;)Z;
const #789 = Asciz	(Lscala/collection/SeqLike;Lscala/collection/Seq;)Z;
const #790 = NameAndType	#787:#789;//  containsSlice:(Lscala/collection/SeqLike;Lscala/collection/Seq;)Z
const #791 = Method	#75.#790;	//  scala/collection/SeqLike$class.containsSlice:(Lscala/collection/SeqLike;Lscala/collection/Seq;)Z
const #792 = Asciz	lastIndexOfSlice;
const #793 = Asciz	(Lscala/collection/Seq;I)I;
const #794 = Asciz	(Lscala/collection/SeqLike;Lscala/collection/Seq;I)I;
const #795 = NameAndType	#792:#794;//  lastIndexOfSlice:(Lscala/collection/SeqLike;Lscala/collection/Seq;I)I
const #796 = Method	#75.#795;	//  scala/collection/SeqLike$class.lastIndexOfSlice:(Lscala/collection/SeqLike;Lscala/collection/Seq;I)I
const #797 = Asciz	(Lscala/collection/Seq;)I;
const #798 = Asciz	(Lscala/collection/SeqLike;Lscala/collection/Seq;)I;
const #799 = NameAndType	#792:#798;//  lastIndexOfSlice:(Lscala/collection/SeqLike;Lscala/collection/Seq;)I
const #800 = Method	#75.#799;	//  scala/collection/SeqLike$class.lastIndexOfSlice:(Lscala/collection/SeqLike;Lscala/collection/Seq;)I
const #801 = Asciz	indexOfSlice;
const #802 = NameAndType	#801:#794;//  indexOfSlice:(Lscala/collection/SeqLike;Lscala/collection/Seq;I)I
const #803 = Method	#75.#802;	//  scala/collection/SeqLike$class.indexOfSlice:(Lscala/collection/SeqLike;Lscala/collection/Seq;I)I
const #804 = NameAndType	#801:#798;//  indexOfSlice:(Lscala/collection/SeqLike;Lscala/collection/Seq;)I
const #805 = Method	#75.#804;	//  scala/collection/SeqLike$class.indexOfSlice:(Lscala/collection/SeqLike;Lscala/collection/Seq;)I
const #806 = Asciz	startsWith;
const #807 = NameAndType	#806:#789;//  startsWith:(Lscala/collection/SeqLike;Lscala/collection/Seq;)Z
const #808 = Method	#75.#807;	//  scala/collection/SeqLike$class.startsWith:(Lscala/collection/SeqLike;Lscala/collection/Seq;)Z
const #809 = Asciz	reversedElements;
const #810 = Asciz	(Lscala/collection/SeqLike;)Lscala/collection/Iterator;;
const #811 = NameAndType	#809:#810;//  reversedElements:(Lscala/collection/SeqLike;)Lscala/collection/Iterator;
const #812 = Method	#75.#811;	//  scala/collection/SeqLike$class.reversedElements:(Lscala/collection/SeqLike;)Lscala/collection/Iterator;
const #813 = Asciz	reverseMap;
const #814 = Asciz	(Lscala/collection/SeqLike;Lscala/Function1;Lscala/collection/generic/CanBuildFrom;)Ljava/lang/Object;;
const #815 = NameAndType	#813:#814;//  reverseMap:(Lscala/collection/SeqLike;Lscala/Function1;Lscala/collection/generic/CanBuildFrom;)Ljava/lang/Object;
const #816 = Method	#75.#815;	//  scala/collection/SeqLike$class.reverseMap:(Lscala/collection/SeqLike;Lscala/Function1;Lscala/collection/generic/CanBuildFrom;)Ljava/lang/Object;
const #817 = Asciz	lastIndexWhere;
const #818 = NameAndType	#817:#704;//  lastIndexWhere:(Lscala/collection/SeqLike;Lscala/Function1;)I
const #819 = Method	#75.#818;	//  scala/collection/SeqLike$class.lastIndexWhere:(Lscala/collection/SeqLike;Lscala/Function1;)I
const #820 = Asciz	lastIndexOf;
const #821 = Asciz	(Ljava/lang/Object;I)I;
const #822 = Asciz	(Lscala/collection/SeqLike;Ljava/lang/Object;I)I;
const #823 = NameAndType	#820:#822;//  lastIndexOf:(Lscala/collection/SeqLike;Ljava/lang/Object;I)I
const #824 = Method	#75.#823;	//  scala/collection/SeqLike$class.lastIndexOf:(Lscala/collection/SeqLike;Ljava/lang/Object;I)I
const #825 = Asciz	(Lscala/collection/SeqLike;Ljava/lang/Object;)I;
const #826 = NameAndType	#820:#825;//  lastIndexOf:(Lscala/collection/SeqLike;Ljava/lang/Object;)I
const #827 = Method	#75.#826;	//  scala/collection/SeqLike$class.lastIndexOf:(Lscala/collection/SeqLike;Ljava/lang/Object;)I
const #828 = Asciz	indexOf;
const #829 = NameAndType	#828:#822;//  indexOf:(Lscala/collection/SeqLike;Ljava/lang/Object;I)I
const #830 = Method	#75.#829;	//  scala/collection/SeqLike$class.indexOf:(Lscala/collection/SeqLike;Ljava/lang/Object;I)I
const #831 = NameAndType	#828:#825;//  indexOf:(Lscala/collection/SeqLike;Ljava/lang/Object;)I
const #832 = Method	#75.#831;	//  scala/collection/SeqLike$class.indexOf:(Lscala/collection/SeqLike;Ljava/lang/Object;)I
const #833 = Asciz	findIndexOf;
const #834 = NameAndType	#833:#704;//  findIndexOf:(Lscala/collection/SeqLike;Lscala/Function1;)I
const #835 = Method	#75.#834;	//  scala/collection/SeqLike$class.findIndexOf:(Lscala/collection/SeqLike;Lscala/Function1;)I
const #836 = Asciz	indexWhere;
const #837 = NameAndType	#836:#704;//  indexWhere:(Lscala/collection/SeqLike;Lscala/Function1;)I
const #838 = Method	#75.#837;	//  scala/collection/SeqLike$class.indexWhere:(Lscala/collection/SeqLike;Lscala/Function1;)I
const #839 = Asciz	prefixLength;
const #840 = NameAndType	#839:#704;//  prefixLength:(Lscala/collection/SeqLike;Lscala/Function1;)I
const #841 = Method	#75.#840;	//  scala/collection/SeqLike$class.prefixLength:(Lscala/collection/SeqLike;Lscala/Function1;)I
const #842 = Asciz	(Lscala/collection/SeqLike;I)Z;
const #843 = NameAndType	#273:#842;//  isDefinedAt:(Lscala/collection/SeqLike;I)Z
const #844 = Method	#75.#843;	//  scala/collection/SeqLike$class.isDefinedAt:(Lscala/collection/SeqLike;I)Z
const #845 = Asciz	idx;
const #846 = NameAndType	#405:#715;//  size:(Lscala/collection/SeqLike;)I
const #847 = Method	#75.#846;	//  scala/collection/SeqLike$class.size:(Lscala/collection/SeqLike;)I
const #848 = Asciz	(Lscala/collection/Iterator;)Lscala/collection/generic/Growable;;
const #849 = Asciz	(Lscala/collection/generic/Growable;Lscala/collection/Iterator;)Lscala/collection/generic/Growable;;
const #850 = NameAndType	#167:#849;//  $plus$plus$eq:(Lscala/collection/generic/Growable;Lscala/collection/Iterator;)Lscala/collection/generic/Growable;
const #851 = Method	#90.#850;	//  scala/collection/generic/Growable$class.$plus$plus$eq:(Lscala/collection/generic/Growable;Lscala/collection/Iterator;)Lscala/collection/generic/Growable;
const #852 = Asciz	(Ljava/lang/Object;Ljava/lang/Object;Lscala/collection/Seq;)Lscala/collection/generic/Growable;;
const #853 = Asciz	(Lscala/collection/generic/Growable;Ljava/lang/Object;Ljava/lang/Object;Lscala/collection/Seq;)Lscala/collection/generic/Growable;;
const #854 = NameAndType	#158:#853;//  $plus$eq:(Lscala/collection/generic/Growable;Ljava/lang/Object;Ljava/lang/Object;Lscala/collection/Seq;)Lscala/collection/generic/Growable;
const #855 = Method	#90.#854;	//  scala/collection/generic/Growable$class.$plus$eq:(Lscala/collection/generic/Growable;Ljava/lang/Object;Ljava/lang/Object;Lscala/collection/Seq;)Lscala/collection/generic/Growable;
const #856 = Asciz	$minus$minus$eq;
const #857 = Asciz	(Lscala/collection/Traversable;)Lscala/collection/generic/Shrinkable;;
const #858 = Asciz	(Lscala/collection/generic/Shrinkable;Lscala/collection/Traversable;)Lscala/collection/generic/Shrinkable;;
const #859 = NameAndType	#856:#858;//  $minus$minus$eq:(Lscala/collection/generic/Shrinkable;Lscala/collection/Traversable;)Lscala/collection/generic/Shrinkable;
const #860 = Method	#95.#859;	//  scala/collection/generic/Shrinkable$class.$minus$minus$eq:(Lscala/collection/generic/Shrinkable;Lscala/collection/Traversable;)Lscala/collection/generic/Shrinkable;
const #861 = Asciz	(Lscala/collection/Iterator;)Lscala/collection/generic/Shrinkable;;
const #862 = Asciz	(Lscala/collection/generic/Shrinkable;Lscala/collection/Iterator;)Lscala/collection/generic/Shrinkable;;
const #863 = NameAndType	#856:#862;//  $minus$minus$eq:(Lscala/collection/generic/Shrinkable;Lscala/collection/Iterator;)Lscala/collection/generic/Shrinkable;
const #864 = Method	#95.#863;	//  scala/collection/generic/Shrinkable$class.$minus$minus$eq:(Lscala/collection/generic/Shrinkable;Lscala/collection/Iterator;)Lscala/collection/generic/Shrinkable;
const #865 = Asciz	(Ljava/lang/Object;Ljava/lang/Object;Lscala/collection/Seq;)Lscala/collection/generic/Shrinkable;;
const #866 = Asciz	(Lscala/collection/generic/Shrinkable;Ljava/lang/Object;Ljava/lang/Object;Lscala/collection/Seq;)Lscala/collection/generic/Shrinkable;;
const #867 = NameAndType	#232:#866;//  $minus$eq:(Lscala/collection/generic/Shrinkable;Ljava/lang/Object;Ljava/lang/Object;Lscala/collection/Seq;)Lscala/collection/generic/Shrinkable;
const #868 = Method	#95.#867;	//  scala/collection/generic/Shrinkable$class.$minus$eq:(Lscala/collection/generic/Shrinkable;Ljava/lang/Object;Ljava/lang/Object;Lscala/collection/Seq;)Lscala/collection/generic/Shrinkable;
const #869 = Asciz	scala$collection$mutable$Cloneable$$super$clone;
const #870 = NameAndType	#181:#182;//  clone:()Ljava/lang/Object;
const #871 = Method	#25.#870;	//  java/lang/Object.clone:()Ljava/lang/Object;
const #872 = Asciz	(Lscala/collection/mutable/BufferLike;Lscala/collection/Iterator;)Lscala/collection/mutable/BufferLike;;
const #873 = NameAndType	#266:#872;//  $minus$minus:(Lscala/collection/mutable/BufferLike;Lscala/collection/Iterator;)Lscala/collection/mutable/BufferLike;
const #874 = Method	#115.#873;	//  scala/collection/mutable/BufferLike$class.$minus$minus:(Lscala/collection/mutable/BufferLike;Lscala/collection/Iterator;)Lscala/collection/mutable/BufferLike;
const #875 = Asciz	(Lscala/collection/mutable/BufferLike;Ljava/lang/Object;)Lscala/collection/mutable/BufferLike;;
const #876 = NameAndType	#755:#875;//  $plus$colon:(Lscala/collection/mutable/BufferLike;Ljava/lang/Object;)Lscala/collection/mutable/BufferLike;
const #877 = Method	#115.#876;	//  scala/collection/mutable/BufferLike$class.$plus$colon:(Lscala/collection/mutable/BufferLike;Ljava/lang/Object;)Lscala/collection/mutable/BufferLike;
const #878 = Asciz	(Lscala/collection/mutable/BufferLike;Lscala/collection/Traversable;)Lscala/collection/mutable/BufferLike;;
const #879 = NameAndType	#266:#878;//  $minus$minus:(Lscala/collection/mutable/BufferLike;Lscala/collection/Traversable;)Lscala/collection/mutable/BufferLike;
const #880 = Method	#115.#879;	//  scala/collection/mutable/BufferLike$class.$minus$minus:(Lscala/collection/mutable/BufferLike;Lscala/collection/Traversable;)Lscala/collection/mutable/BufferLike;
const #881 = Asciz	(Lscala/collection/mutable/BufferLike;Ljava/lang/Object;Ljava/lang/Object;Lscala/collection/Seq;)Lscala/collection/mutable/BufferLike;;
const #882 = NameAndType	#259:#881;//  $minus:(Lscala/collection/mutable/BufferLike;Ljava/lang/Object;Ljava/lang/Object;Lscala/collection/Seq;)Lscala/collection/mutable/BufferLike;
const #883 = Method	#115.#882;	//  scala/collection/mutable/BufferLike$class.$minus:(Lscala/collection/mutable/BufferLike;Ljava/lang/Object;Ljava/lang/Object;Lscala/collection/Seq;)Lscala/collection/mutable/BufferLike;
const #884 = NameAndType	#259:#875;//  $minus:(Lscala/collection/mutable/BufferLike;Ljava/lang/Object;)Lscala/collection/mutable/BufferLike;
const #885 = Method	#115.#884;	//  scala/collection/mutable/BufferLike$class.$minus:(Lscala/collection/mutable/BufferLike;Ljava/lang/Object;)Lscala/collection/mutable/BufferLike;
const #886 = NameAndType	#249:#872;//  $plus$plus:(Lscala/collection/mutable/BufferLike;Lscala/collection/Iterator;)Lscala/collection/mutable/BufferLike;
const #887 = Method	#115.#886;	//  scala/collection/mutable/BufferLike$class.$plus$plus:(Lscala/collection/mutable/BufferLike;Lscala/collection/Iterator;)Lscala/collection/mutable/BufferLike;
const #888 = NameAndType	#249:#878;//  $plus$plus:(Lscala/collection/mutable/BufferLike;Lscala/collection/Traversable;)Lscala/collection/mutable/BufferLike;
const #889 = Method	#115.#888;	//  scala/collection/mutable/BufferLike$class.$plus$plus:(Lscala/collection/mutable/BufferLike;Lscala/collection/Traversable;)Lscala/collection/mutable/BufferLike;
const #890 = NameAndType	#238:#881;//  $plus:(Lscala/collection/mutable/BufferLike;Ljava/lang/Object;Ljava/lang/Object;Lscala/collection/Seq;)Lscala/collection/mutable/BufferLike;
const #891 = Method	#115.#890;	//  scala/collection/mutable/BufferLike$class.$plus:(Lscala/collection/mutable/BufferLike;Ljava/lang/Object;Ljava/lang/Object;Lscala/collection/Seq;)Lscala/collection/mutable/BufferLike;
const #892 = NameAndType	#238:#875;//  $plus:(Lscala/collection/mutable/BufferLike;Ljava/lang/Object;)Lscala/collection/mutable/BufferLike;
const #893 = Method	#115.#892;	//  scala/collection/mutable/BufferLike$class.$plus:(Lscala/collection/mutable/BufferLike;Ljava/lang/Object;)Lscala/collection/mutable/BufferLike;
const #894 = Asciz	$plus$plus$colon;
const #895 = NameAndType	#894:#878;//  $plus$plus$colon:(Lscala/collection/mutable/BufferLike;Lscala/collection/Traversable;)Lscala/collection/mutable/BufferLike;
const #896 = Method	#115.#895;	//  scala/collection/mutable/BufferLike$class.$plus$plus$colon:(Lscala/collection/mutable/BufferLike;Lscala/collection/Traversable;)Lscala/collection/mutable/BufferLike;
const #897 = Asciz	(Lscala/collection/mutable/BufferLike;Ljava/lang/Object;II)V;
const #898 = NameAndType	#167:#897;//  $plus$plus$eq:(Lscala/collection/mutable/BufferLike;Ljava/lang/Object;II)V
const #899 = Method	#115.#898;	//  scala/collection/mutable/BufferLike$class.$plus$plus$eq:(Lscala/collection/mutable/BufferLike;Ljava/lang/Object;II)V
const #900 = Asciz	src;
const #901 = Asciz	readOnly;
const #902 = Asciz	(Lscala/collection/mutable/BufferLike;)Lscala/collection/Seq;;
const #903 = NameAndType	#901:#902;//  readOnly:(Lscala/collection/mutable/BufferLike;)Lscala/collection/Seq;
const #904 = Method	#115.#903;	//  scala/collection/mutable/BufferLike$class.readOnly:(Lscala/collection/mutable/BufferLike;)Lscala/collection/Seq;
const #905 = Asciz	$less$less;
const #906 = Asciz	(Lscala/collection/script/Message;)V;
const #907 = Asciz	(Lscala/collection/mutable/BufferLike;Lscala/collection/script/Message;)V;
const #908 = NameAndType	#905:#907;//  $less$less:(Lscala/collection/mutable/BufferLike;Lscala/collection/script/Message;)V
const #909 = Method	#115.#908;	//  scala/collection/mutable/BufferLike$class.$less$less:(Lscala/collection/mutable/BufferLike;Lscala/collection/script/Message;)V
const #910 = Asciz	cmd;
const #911 = Asciz	Lscala/collection/script/Message;;
const #912 = Asciz	trimEnd;
const #913 = Asciz	(Lscala/collection/mutable/BufferLike;I)V;
const #914 = NameAndType	#912:#913;//  trimEnd:(Lscala/collection/mutable/BufferLike;I)V
const #915 = Method	#115.#914;	//  scala/collection/mutable/BufferLike$class.trimEnd:(Lscala/collection/mutable/BufferLike;I)V
const #916 = Asciz	trimStart;
const #917 = NameAndType	#916:#913;//  trimStart:(Lscala/collection/mutable/BufferLike;I)V
const #918 = Method	#115.#917;	//  scala/collection/mutable/BufferLike$class.trimStart:(Lscala/collection/mutable/BufferLike;I)V
const #919 = Asciz	insert;
const #920 = Asciz	(ILscala/collection/Seq;)V;
const #921 = Asciz	(Lscala/collection/mutable/BufferLike;ILscala/collection/Seq;)V;
const #922 = NameAndType	#919:#921;//  insert:(Lscala/collection/mutable/BufferLike;ILscala/collection/Seq;)V
const #923 = Method	#115.#922;	//  scala/collection/mutable/BufferLike$class.insert:(Lscala/collection/mutable/BufferLike;ILscala/collection/Seq;)V
const #924 = Asciz	prependAll;
const #925 = Asciz	(Lscala/collection/Iterator;)V;
const #926 = Asciz	(Lscala/collection/mutable/BufferLike;Lscala/collection/Iterator;)V;
const #927 = NameAndType	#924:#926;//  prependAll:(Lscala/collection/mutable/BufferLike;Lscala/collection/Iterator;)V
const #928 = Method	#115.#927;	//  scala/collection/mutable/BufferLike$class.prependAll:(Lscala/collection/mutable/BufferLike;Lscala/collection/Iterator;)V
const #929 = Asciz	(Lscala/collection/mutable/BufferLike;Lscala/collection/Traversable;)V;
const #930 = NameAndType	#924:#929;//  prependAll:(Lscala/collection/mutable/BufferLike;Lscala/collection/Traversable;)V
const #931 = Method	#115.#930;	//  scala/collection/mutable/BufferLike$class.prependAll:(Lscala/collection/mutable/BufferLike;Lscala/collection/Traversable;)V
const #932 = Asciz	prepend;
const #933 = Asciz	(Lscala/collection/mutable/BufferLike;Lscala/collection/Seq;)V;
const #934 = NameAndType	#932:#933;//  prepend:(Lscala/collection/mutable/BufferLike;Lscala/collection/Seq;)V
const #935 = Method	#115.#934;	//  scala/collection/mutable/BufferLike$class.prepend:(Lscala/collection/mutable/BufferLike;Lscala/collection/Seq;)V
const #936 = Asciz	appendAll;
const #937 = NameAndType	#936:#926;//  appendAll:(Lscala/collection/mutable/BufferLike;Lscala/collection/Iterator;)V
const #938 = Method	#115.#937;	//  scala/collection/mutable/BufferLike$class.appendAll:(Lscala/collection/mutable/BufferLike;Lscala/collection/Iterator;)V
const #939 = NameAndType	#936:#929;//  appendAll:(Lscala/collection/mutable/BufferLike;Lscala/collection/Traversable;)V
const #940 = Method	#115.#939;	//  scala/collection/mutable/BufferLike$class.appendAll:(Lscala/collection/mutable/BufferLike;Lscala/collection/Traversable;)V
const #941 = NameAndType	#346:#933;//  append:(Lscala/collection/mutable/BufferLike;Lscala/collection/Seq;)V
const #942 = Method	#115.#941;	//  scala/collection/mutable/BufferLike$class.append:(Lscala/collection/mutable/BufferLike;Lscala/collection/Seq;)V
const #943 = NameAndType	#177:#872;//  $plus$plus$eq$colon:(Lscala/collection/mutable/BufferLike;Lscala/collection/Iterator;)Lscala/collection/mutable/BufferLike;
const #944 = Method	#115.#943;	//  scala/collection/mutable/BufferLike$class.$plus$plus$eq$colon:(Lscala/collection/mutable/BufferLike;Lscala/collection/Iterator;)Lscala/collection/mutable/BufferLike;
const #945 = NameAndType	#232:#875;//  $minus$eq:(Lscala/collection/mutable/BufferLike;Ljava/lang/Object;)Lscala/collection/mutable/BufferLike;
const #946 = Method	#115.#945;	//  scala/collection/mutable/BufferLike$class.$minus$eq:(Lscala/collection/mutable/BufferLike;Ljava/lang/Object;)Lscala/collection/mutable/BufferLike;
const #947 = Asciz	endsWith;
const #948 = Asciz	(Lscala/collection/IndexedSeqLike;Lscala/collection/Seq;)Z;
const #949 = NameAndType	#947:#948;//  endsWith:(Lscala/collection/IndexedSeqLike;Lscala/collection/Seq;)Z
const #950 = Method	#125.#949;	//  scala/collection/IndexedSeqLike$class.endsWith:(Lscala/collection/IndexedSeqLike;Lscala/collection/Seq;)Z
const #951 = Asciz	(Lscala/collection/Seq;I)Z;
const #952 = Asciz	(Lscala/collection/IndexedSeqLike;Lscala/collection/Seq;I)Z;
const #953 = NameAndType	#806:#952;//  startsWith:(Lscala/collection/IndexedSeqLike;Lscala/collection/Seq;I)Z
const #954 = Method	#125.#953;	//  scala/collection/IndexedSeqLike$class.startsWith:(Lscala/collection/IndexedSeqLike;Lscala/collection/Seq;I)Z
const #955 = Asciz	offset;
const #956 = Asciz	reverseIterator;
const #957 = Asciz	(Lscala/collection/IndexedSeqLike;)Lscala/collection/Iterator;;
const #958 = NameAndType	#956:#957;//  reverseIterator:(Lscala/collection/IndexedSeqLike;)Lscala/collection/Iterator;
const #959 = Method	#125.#958;	//  scala/collection/IndexedSeqLike$class.reverseIterator:(Lscala/collection/IndexedSeqLike;)Lscala/collection/Iterator;
const #960 = Asciz	reverse;
const #961 = Asciz	(Lscala/collection/IndexedSeqLike;)Ljava/lang/Object;;
const #962 = NameAndType	#960:#961;//  reverse:(Lscala/collection/IndexedSeqLike;)Ljava/lang/Object;
const #963 = Method	#125.#962;	//  scala/collection/IndexedSeqLike$class.reverse:(Lscala/collection/IndexedSeqLike;)Ljava/lang/Object;
const #964 = Asciz	(Lscala/Function1;I)I;
const #965 = Asciz	(Lscala/collection/IndexedSeqLike;Lscala/Function1;I)I;
const #966 = NameAndType	#817:#965;//  lastIndexWhere:(Lscala/collection/IndexedSeqLike;Lscala/Function1;I)I
const #967 = Method	#125.#966;	//  scala/collection/IndexedSeqLike$class.lastIndexWhere:(Lscala/collection/IndexedSeqLike;Lscala/Function1;I)I
const #968 = NameAndType	#836:#965;//  indexWhere:(Lscala/collection/IndexedSeqLike;Lscala/Function1;I)I
const #969 = Method	#125.#968;	//  scala/collection/IndexedSeqLike$class.indexWhere:(Lscala/collection/IndexedSeqLike;Lscala/Function1;I)I
const #970 = Asciz	segmentLength;
const #971 = NameAndType	#970:#965;//  segmentLength:(Lscala/collection/IndexedSeqLike;Lscala/Function1;I)I
const #972 = Method	#125.#971;	//  scala/collection/IndexedSeqLike$class.segmentLength:(Lscala/collection/IndexedSeqLike;Lscala/Function1;I)I
const #973 = Asciz	lengthCompare;
const #974 = Asciz	(Lscala/collection/IndexedSeqLike;I)I;
const #975 = NameAndType	#973:#974;//  lengthCompare:(Lscala/collection/IndexedSeqLike;I)I
const #976 = Method	#125.#975;	//  scala/collection/IndexedSeqLike$class.lengthCompare:(Lscala/collection/IndexedSeqLike;I)I
const #977 = Asciz	sameElements;
const #978 = Asciz	(Lscala/collection/Iterable;)Z;
const #979 = Asciz	(Lscala/collection/IndexedSeqLike;Lscala/collection/Iterable;)Z;
const #980 = NameAndType	#977:#979;//  sameElements:(Lscala/collection/IndexedSeqLike;Lscala/collection/Iterable;)Z
const #981 = Method	#125.#980;	//  scala/collection/IndexedSeqLike$class.sameElements:(Lscala/collection/IndexedSeqLike;Lscala/collection/Iterable;)Z
const #982 = Asciz	span;
const #983 = Asciz	(Lscala/collection/IndexedSeqLike;Lscala/Function1;)Lscala/Tuple2;;
const #984 = NameAndType	#982:#983;//  span:(Lscala/collection/IndexedSeqLike;Lscala/Function1;)Lscala/Tuple2;
const #985 = Method	#125.#984;	//  scala/collection/IndexedSeqLike$class.span:(Lscala/collection/IndexedSeqLike;Lscala/Function1;)Lscala/Tuple2;
const #986 = Asciz	dropWhile;
const #987 = Asciz	(Lscala/collection/IndexedSeqLike;Lscala/Function1;)Ljava/lang/Object;;
const #988 = NameAndType	#986:#987;//  dropWhile:(Lscala/collection/IndexedSeqLike;Lscala/Function1;)Ljava/lang/Object;
const #989 = Method	#125.#988;	//  scala/collection/IndexedSeqLike$class.dropWhile:(Lscala/collection/IndexedSeqLike;Lscala/Function1;)Ljava/lang/Object;
const #990 = Asciz	takeWhile;
const #991 = NameAndType	#990:#987;//  takeWhile:(Lscala/collection/IndexedSeqLike;Lscala/Function1;)Ljava/lang/Object;
const #992 = Method	#125.#991;	//  scala/collection/IndexedSeqLike$class.takeWhile:(Lscala/collection/IndexedSeqLike;Lscala/Function1;)Ljava/lang/Object;
const #993 = Asciz	splitAt;
const #994 = Asciz	(I)Lscala/Tuple2;;
const #995 = Asciz	(Lscala/collection/IndexedSeqLike;I)Lscala/Tuple2;;
const #996 = NameAndType	#993:#995;//  splitAt:(Lscala/collection/IndexedSeqLike;I)Lscala/Tuple2;
const #997 = Method	#125.#996;	//  scala/collection/IndexedSeqLike$class.splitAt:(Lscala/collection/IndexedSeqLike;I)Lscala/Tuple2;
const #998 = Asciz	dropRight;
const #999 = Asciz	(Lscala/collection/IndexedSeqLike;I)Ljava/lang/Object;;
const #1000 = NameAndType	#998:#999;//  dropRight:(Lscala/collection/IndexedSeqLike;I)Ljava/lang/Object;
const #1001 = Method	#125.#1000;	//  scala/collection/IndexedSeqLike$class.dropRight:(Lscala/collection/IndexedSeqLike;I)Ljava/lang/Object;
const #1002 = Asciz	takeRight;
const #1003 = NameAndType	#1002:#999;//  takeRight:(Lscala/collection/IndexedSeqLike;I)Ljava/lang/Object;
const #1004 = Method	#125.#1003;	//  scala/collection/IndexedSeqLike$class.takeRight:(Lscala/collection/IndexedSeqLike;I)Ljava/lang/Object;
const #1005 = Asciz	drop;
const #1006 = NameAndType	#1005:#999;//  drop:(Lscala/collection/IndexedSeqLike;I)Ljava/lang/Object;
const #1007 = Method	#125.#1006;	//  scala/collection/IndexedSeqLike$class.drop:(Lscala/collection/IndexedSeqLike;I)Ljava/lang/Object;
const #1008 = Asciz	take;
const #1009 = NameAndType	#1008:#999;//  take:(Lscala/collection/IndexedSeqLike;I)Ljava/lang/Object;
const #1010 = Method	#125.#1009;	//  scala/collection/IndexedSeqLike$class.take:(Lscala/collection/IndexedSeqLike;I)Ljava/lang/Object;
const #1011 = Asciz	init;
const #1012 = NameAndType	#1011:#961;//  init:(Lscala/collection/IndexedSeqLike;)Ljava/lang/Object;
const #1013 = Method	#125.#1012;	//  scala/collection/IndexedSeqLike$class.init:(Lscala/collection/IndexedSeqLike;)Ljava/lang/Object;
const #1014 = Asciz	last;
const #1015 = NameAndType	#1014:#961;//  last:(Lscala/collection/IndexedSeqLike;)Ljava/lang/Object;
const #1016 = Method	#125.#1015;	//  scala/collection/IndexedSeqLike$class.last:(Lscala/collection/IndexedSeqLike;)Ljava/lang/Object;
const #1017 = Asciz	tail;
const #1018 = NameAndType	#1017:#961;//  tail:(Lscala/collection/IndexedSeqLike;)Ljava/lang/Object;
const #1019 = Method	#125.#1018;	//  scala/collection/IndexedSeqLike$class.tail:(Lscala/collection/IndexedSeqLike;)Ljava/lang/Object;
const #1020 = Asciz	head;
const #1021 = NameAndType	#1020:#961;//  head:(Lscala/collection/IndexedSeqLike;)Ljava/lang/Object;
const #1022 = Method	#125.#1021;	//  scala/collection/IndexedSeqLike$class.head:(Lscala/collection/IndexedSeqLike;)Ljava/lang/Object;
const #1023 = Asciz	slice;
const #1024 = Asciz	(II)Ljava/lang/Object;;
const #1025 = Asciz	(Lscala/collection/IndexedSeqLike;II)Ljava/lang/Object;;
const #1026 = NameAndType	#1023:#1025;//  slice:(Lscala/collection/IndexedSeqLike;II)Ljava/lang/Object;
const #1027 = Method	#125.#1026;	//  scala/collection/IndexedSeqLike$class.slice:(Lscala/collection/IndexedSeqLike;II)Ljava/lang/Object;
const #1028 = Asciz	zipWithIndex;
const #1029 = Asciz	(Lscala/collection/generic/CanBuildFrom;)Ljava/lang/Object;;
const #1030 = Asciz	(Lscala/collection/IndexedSeqLike;Lscala/collection/generic/CanBuildFrom;)Ljava/lang/Object;;
const #1031 = NameAndType	#1028:#1030;//  zipWithIndex:(Lscala/collection/IndexedSeqLike;Lscala/collection/generic/CanBuildFrom;)Ljava/lang/Object;
const #1032 = Method	#125.#1031;	//  scala/collection/IndexedSeqLike$class.zipWithIndex:(Lscala/collection/IndexedSeqLike;Lscala/collection/generic/CanBuildFrom;)Ljava/lang/Object;
const #1033 = Asciz	zip;
const #1034 = Asciz	(Lscala/collection/Iterable;Lscala/collection/generic/CanBuildFrom;)Ljava/lang/Object;;
const #1035 = Asciz	(Lscala/collection/IndexedSeqLike;Lscala/collection/Iterable;Lscala/collection/generic/CanBuildFrom;)Ljava/lang/Object;;
const #1036 = NameAndType	#1033:#1035;//  zip:(Lscala/collection/IndexedSeqLike;Lscala/collection/Iterable;Lscala/collection/generic/CanBuildFrom;)Ljava/lang/Object;
const #1037 = Method	#125.#1036;	//  scala/collection/IndexedSeqLike$class.zip:(Lscala/collection/IndexedSeqLike;Lscala/collection/Iterable;Lscala/collection/generic/CanBuildFrom;)Ljava/lang/Object;
const #1038 = Asciz	reduceRight;
const #1039 = Asciz	(Lscala/collection/IndexedSeqLike;Lscala/Function2;)Ljava/lang/Object;;
const #1040 = NameAndType	#1038:#1039;//  reduceRight:(Lscala/collection/IndexedSeqLike;Lscala/Function2;)Ljava/lang/Object;
const #1041 = Method	#125.#1040;	//  scala/collection/IndexedSeqLike$class.reduceRight:(Lscala/collection/IndexedSeqLike;Lscala/Function2;)Ljava/lang/Object;
const #1042 = Asciz	reduceLeft;
const #1043 = NameAndType	#1042:#1039;//  reduceLeft:(Lscala/collection/IndexedSeqLike;Lscala/Function2;)Ljava/lang/Object;
const #1044 = Method	#125.#1043;	//  scala/collection/IndexedSeqLike$class.reduceLeft:(Lscala/collection/IndexedSeqLike;Lscala/Function2;)Ljava/lang/Object;
const #1045 = Asciz	foldRight;
const #1046 = Asciz	(Lscala/collection/IndexedSeqLike;Ljava/lang/Object;Lscala/Function2;)Ljava/lang/Object;;
const #1047 = NameAndType	#1045:#1046;//  foldRight:(Lscala/collection/IndexedSeqLike;Ljava/lang/Object;Lscala/Function2;)Ljava/lang/Object;
const #1048 = Method	#125.#1047;	//  scala/collection/IndexedSeqLike$class.foldRight:(Lscala/collection/IndexedSeqLike;Ljava/lang/Object;Lscala/Function2;)Ljava/lang/Object;
const #1049 = Asciz	foldLeft;
const #1050 = NameAndType	#1049:#1046;//  foldLeft:(Lscala/collection/IndexedSeqLike;Ljava/lang/Object;Lscala/Function2;)Ljava/lang/Object;
const #1051 = Method	#125.#1050;	//  scala/collection/IndexedSeqLike$class.foldLeft:(Lscala/collection/IndexedSeqLike;Ljava/lang/Object;Lscala/Function2;)Ljava/lang/Object;
const #1052 = Asciz	find;
const #1053 = Asciz	(Lscala/Function1;)Lscala/Option;;
const #1054 = Asciz	(Lscala/collection/IndexedSeqLike;Lscala/Function1;)Lscala/Option;;
const #1055 = NameAndType	#1052:#1054;//  find:(Lscala/collection/IndexedSeqLike;Lscala/Function1;)Lscala/Option;
const #1056 = Method	#125.#1055;	//  scala/collection/IndexedSeqLike$class.find:(Lscala/collection/IndexedSeqLike;Lscala/Function1;)Lscala/Option;
const #1057 = Asciz	exists;
const #1058 = Asciz	(Lscala/Function1;)Z;
const #1059 = Asciz	(Lscala/collection/IndexedSeqLike;Lscala/Function1;)Z;
const #1060 = NameAndType	#1057:#1059;//  exists:(Lscala/collection/IndexedSeqLike;Lscala/Function1;)Z
const #1061 = Method	#125.#1060;	//  scala/collection/IndexedSeqLike$class.exists:(Lscala/collection/IndexedSeqLike;Lscala/Function1;)Z
const #1062 = Asciz	forall;
const #1063 = NameAndType	#1062:#1059;//  forall:(Lscala/collection/IndexedSeqLike;Lscala/Function1;)Z
const #1064 = Method	#125.#1063;	//  scala/collection/IndexedSeqLike$class.forall:(Lscala/collection/IndexedSeqLike;Lscala/Function1;)Z
const #1065 = Asciz	isEmpty;
const #1066 = Asciz	(Lscala/collection/IndexedSeqLike;)Z;
const #1067 = NameAndType	#1065:#1066;//  isEmpty:(Lscala/collection/IndexedSeqLike;)Z
const #1068 = Method	#125.#1067;	//  scala/collection/IndexedSeqLike$class.isEmpty:(Lscala/collection/IndexedSeqLike;)Z
const #1069 = Asciz	iterator;
const #1070 = NameAndType	#1069:#957;//  iterator:(Lscala/collection/IndexedSeqLike;)Lscala/collection/Iterator;
const #1071 = Method	#125.#1070;	//  scala/collection/IndexedSeqLike$class.iterator:(Lscala/collection/IndexedSeqLike;)Lscala/collection/Iterator;
const #1072 = Asciz	scala$collection$IndexedSeqLike$$super$endsWith;
const #1073 = NameAndType	#947:#789;//  endsWith:(Lscala/collection/SeqLike;Lscala/collection/Seq;)Z
const #1074 = Method	#75.#1073;	//  scala/collection/SeqLike$class.endsWith:(Lscala/collection/SeqLike;Lscala/collection/Seq;)Z
const #1075 = Asciz	scala$collection$IndexedSeqLike$$super$sameElements;
const #1076 = Asciz	(Lscala/collection/IterableLike;Lscala/collection/Iterable;)Z;
const #1077 = NameAndType	#977:#1076;//  sameElements:(Lscala/collection/IterableLike;Lscala/collection/Iterable;)Z
const #1078 = Method	#50.#1077;	//  scala/collection/IterableLike$class.sameElements:(Lscala/collection/IterableLike;Lscala/collection/Iterable;)Z
const #1079 = Asciz	scala$collection$IndexedSeqLike$$super$init;
const #1080 = NameAndType	#1011:#616;//  init:(Lscala/collection/TraversableLike;)Ljava/lang/Object;
const #1081 = Method	#29.#1080;	//  scala/collection/TraversableLike$class.init:(Lscala/collection/TraversableLike;)Ljava/lang/Object;
const #1082 = Asciz	scala$collection$IndexedSeqLike$$super$last;
const #1083 = NameAndType	#1014:#616;//  last:(Lscala/collection/TraversableLike;)Ljava/lang/Object;
const #1084 = Method	#29.#1083;	//  scala/collection/TraversableLike$class.last:(Lscala/collection/TraversableLike;)Ljava/lang/Object;
const #1085 = Asciz	scala$collection$IndexedSeqLike$$super$tail;
const #1086 = NameAndType	#1017:#616;//  tail:(Lscala/collection/TraversableLike;)Ljava/lang/Object;
const #1087 = Method	#29.#1086;	//  scala/collection/TraversableLike$class.tail:(Lscala/collection/TraversableLike;)Ljava/lang/Object;
const #1088 = Asciz	scala$collection$IndexedSeqLike$$super$head;
const #1089 = NameAndType	#1020:#647;//  head:(Lscala/collection/IterableLike;)Ljava/lang/Object;
const #1090 = Method	#50.#1089;	//  scala/collection/IterableLike$class.head:(Lscala/collection/IterableLike;)Ljava/lang/Object;
const #1091 = Asciz	scala$collection$IndexedSeqLike$$super$zip;
const #1092 = Asciz	(Lscala/collection/IterableLike;Lscala/collection/Iterable;Lscala/collection/generic/CanBuildFrom;)Ljava/lang/Object;;
const #1093 = NameAndType	#1033:#1092;//  zip:(Lscala/collection/IterableLike;Lscala/collection/Iterable;Lscala/collection/generic/CanBuildFrom;)Ljava/lang/Object;
const #1094 = Method	#50.#1093;	//  scala/collection/IterableLike$class.zip:(Lscala/collection/IterableLike;Lscala/collection/Iterable;Lscala/collection/generic/CanBuildFrom;)Ljava/lang/Object;
const #1095 = Asciz	scala$collection$IndexedSeqLike$$super$reduceRight;
const #1096 = Asciz	(Lscala/collection/IterableLike;Lscala/Function2;)Ljava/lang/Object;;
const #1097 = NameAndType	#1038:#1096;//  reduceRight:(Lscala/collection/IterableLike;Lscala/Function2;)Ljava/lang/Object;
const #1098 = Method	#50.#1097;	//  scala/collection/IterableLike$class.reduceRight:(Lscala/collection/IterableLike;Lscala/Function2;)Ljava/lang/Object;
const #1099 = Asciz	scala$collection$IndexedSeqLike$$super$reduceLeft;
const #1100 = Asciz	(Lscala/collection/TraversableLike;Lscala/Function2;)Ljava/lang/Object;;
const #1101 = NameAndType	#1042:#1100;//  reduceLeft:(Lscala/collection/TraversableLike;Lscala/Function2;)Ljava/lang/Object;
const #1102 = Method	#29.#1101;	//  scala/collection/TraversableLike$class.reduceLeft:(Lscala/collection/TraversableLike;Lscala/Function2;)Ljava/lang/Object;
const #1103 = Asciz	(Lscala/collection/mutable/IndexedSeqLike;II)Lscala/collection/mutable/IndexedSeqView;;
const #1104 = NameAndType	#222:#1103;//  view:(Lscala/collection/mutable/IndexedSeqLike;II)Lscala/collection/mutable/IndexedSeqView;
const #1105 = Method	#130.#1104;	//  scala/collection/mutable/IndexedSeqLike$class.view:(Lscala/collection/mutable/IndexedSeqLike;II)Lscala/collection/mutable/IndexedSeqView;
const #1106 = Asciz	(Lscala/collection/mutable/IndexedSeqLike;)Ljava/lang/Object;;
const #1107 = NameAndType	#222:#1106;//  view:(Lscala/collection/mutable/IndexedSeqLike;)Ljava/lang/Object;
const #1108 = Method	#130.#1107;	//  scala/collection/mutable/IndexedSeqLike$class.view:(Lscala/collection/mutable/IndexedSeqLike;)Ljava/lang/Object;
const #1109 = Asciz	(Lscala/collection/mutable/IndexedSeqLike;Ljava/lang/Object;)Lscala/collection/mutable/IndexedSeq;;
const #1110 = NameAndType	#213:#1109;//  toCollection:(Lscala/collection/mutable/IndexedSeqLike;Ljava/lang/Object;)Lscala/collection/mutable/IndexedSeq;
const #1111 = Method	#130.#1110;	//  scala/collection/mutable/IndexedSeqLike$class.toCollection:(Lscala/collection/mutable/IndexedSeqLike;Ljava/lang/Object;)Lscala/collection/mutable/IndexedSeq;
const #1112 = Asciz	(Lscala/collection/mutable/IndexedSeqLike;)Lscala/collection/mutable/IndexedSeq;;
const #1113 = NameAndType	#203:#1112;//  thisCollection:(Lscala/collection/mutable/IndexedSeqLike;)Lscala/collection/mutable/IndexedSeq;
const #1114 = Method	#130.#1113;	//  scala/collection/mutable/IndexedSeqLike$class.thisCollection:(Lscala/collection/mutable/IndexedSeqLike;)Lscala/collection/mutable/IndexedSeq;
const #1115 = Asciz	mapResult;
const #1116 = Asciz	(Lscala/Function1;)Lscala/collection/mutable/Builder;;
const #1117 = Asciz	(Lscala/collection/mutable/Builder;Lscala/Function1;)Lscala/collection/mutable/Builder;;
const #1118 = NameAndType	#1115:#1117;//  mapResult:(Lscala/collection/mutable/Builder;Lscala/Function1;)Lscala/collection/mutable/Builder;
const #1119 = Method	#135.#1118;	//  scala/collection/mutable/Builder$class.mapResult:(Lscala/collection/mutable/Builder;Lscala/Function1;)Lscala/collection/mutable/Builder;
const #1120 = Asciz	(Lscala/collection/mutable/ResizableArray;III)V;
const #1121 = NameAndType	#332:#1120;//  copy:(Lscala/collection/mutable/ResizableArray;III)V
const #1122 = Method	#150.#1121;	//  scala/collection/mutable/ResizableArray$class.copy:(Lscala/collection/mutable/ResizableArray;III)V
const #1123 = Asciz	m;
const #1124 = Asciz	swap;
const #1125 = Asciz	(Lscala/collection/mutable/ResizableArray;II)V;
const #1126 = NameAndType	#1124:#1125;//  swap:(Lscala/collection/mutable/ResizableArray;II)V
const #1127 = Method	#150.#1126;	//  scala/collection/mutable/ResizableArray$class.swap:(Lscala/collection/mutable/ResizableArray;II)V
const #1128 = Asciz	a;
const #1129 = Asciz	(Lscala/collection/mutable/ResizableArray;I)V;
const #1130 = NameAndType	#368:#1129;//  ensureSize:(Lscala/collection/mutable/ResizableArray;I)V
const #1131 = Method	#150.#1130;	//  scala/collection/mutable/ResizableArray$class.ensureSize:(Lscala/collection/mutable/ResizableArray;I)V
const #1132 = NameAndType	#431:#1129;//  reduceToSize:(Lscala/collection/mutable/ResizableArray;I)V
const #1133 = Method	#150.#1132;	//  scala/collection/mutable/ResizableArray$class.reduceToSize:(Lscala/collection/mutable/ResizableArray;I)V
const #1134 = Asciz	sz;
const #1135 = Asciz	(Lscala/collection/mutable/ResizableArray;Ljava/lang/Object;II)V;
const #1136 = NameAndType	#374:#1135;//  copyToArray:(Lscala/collection/mutable/ResizableArray;Ljava/lang/Object;II)V
const #1137 = Method	#150.#1136;	//  scala/collection/mutable/ResizableArray$class.copyToArray:(Lscala/collection/mutable/ResizableArray;Ljava/lang/Object;II)V
const #1138 = Asciz	foreach;
const #1139 = Asciz	(Lscala/collection/mutable/ResizableArray;Lscala/Function1;)V;
const #1140 = NameAndType	#1138:#1139;//  foreach:(Lscala/collection/mutable/ResizableArray;Lscala/Function1;)V
const #1141 = Method	#150.#1140;	//  scala/collection/mutable/ResizableArray$class.foreach:(Lscala/collection/mutable/ResizableArray;Lscala/Function1;)V
const #1142 = Asciz	update;
const #1143 = Asciz	(ILjava/lang/Object;)V;
const #1144 = Asciz	(Lscala/collection/mutable/ResizableArray;ILjava/lang/Object;)V;
const #1145 = NameAndType	#1142:#1144;//  update:(Lscala/collection/mutable/ResizableArray;ILjava/lang/Object;)V
const #1146 = Method	#150.#1145;	//  scala/collection/mutable/ResizableArray$class.update:(Lscala/collection/mutable/ResizableArray;ILjava/lang/Object;)V
const #1147 = Asciz	(Lscala/collection/mutable/ResizableArray;I)Ljava/lang/Object;;
const #1148 = NameAndType	#189:#1147;//  apply:(Lscala/collection/mutable/ResizableArray;I)Ljava/lang/Object;
const #1149 = Method	#150.#1148;	//  scala/collection/mutable/ResizableArray$class.apply:(Lscala/collection/mutable/ResizableArray;I)Ljava/lang/Object;
const #1150 = Asciz	(Lscala/collection/mutable/ResizableArray;)I;
const #1151 = NameAndType	#365:#1150;//  length:(Lscala/collection/mutable/ResizableArray;)I
const #1152 = Method	#150.#1151;	//  scala/collection/mutable/ResizableArray$class.length:(Lscala/collection/mutable/ResizableArray;)I
const #1153 = NameAndType	#14:#15;//  size0:I
const #1154 = Field	#11.#1153;	//  scala/collection/mutable/ArrayBuffer.size0:I
const #1155 = NameAndType	#16:#17;//  array:[Ljava/lang/Object;
const #1156 = Field	#11.#1155;	//  scala/collection/mutable/ArrayBuffer.array:[Ljava/lang/Object;
const #1157 = Asciz	<A:Ljava/lang/Object;>Ljava/lang/Object;Lscala/collection/mutable/Buffer<TA;>;Lscala/collection/generic/GenericTraversableTemplate<TA;Lscala/collection/mutable/ArrayBuffer;>;Lscala/collection/mutable/BufferLike<TA;Lscala/collection/mutable/ArrayBuffer<TA;>;>;Lscala/collection/mutable/IndexedSeqLike<TA;Lscala/collection/mutable/ArrayBuffer<TA;>;>;Lscala/collection/mutable/Builder<TA;Lscala/collection/mutable/ArrayBuffer<TA;>;>;Lscala/collection/mutable/ResizableArray<TA;>;Lscala/ScalaObject;;
const #1158 = Asciz	ScalaSig;
const #1159 = Asciz	InnerClasses;
const #1160 = Asciz	scala/collection/TraversableLike$WithFilter;
const #1161 = class	#1160;	//  scala/collection/TraversableLike$WithFilter
const #1162 = Asciz	WithFilter;
const #1163 = Asciz	$anonfun$remove$1;
const #1164 = Asciz	scala/collection/mutable/Buffer;
const #1165 = class	#1164;	//  scala/collection/mutable/Buffer
const #1166 = Asciz	scala/collection/generic/GenericTraversableTemplate;
const #1167 = class	#1166;	//  scala/collection/generic/GenericTraversableTemplate
const #1168 = Asciz	scala/collection/mutable/Builder;
const #1169 = class	#1168;	//  scala/collection/mutable/Builder
const #1170 = Asciz	scala/ScalaObject;
const #1171 = class	#1170;	//  scala/ScalaObject
const #1172 = Asciz	java/io/Serializable;
const #1173 = class	#1172;	//  java/io/Serializable

{
public static final long serialVersionUID;

public static {};
  Code:
   Stack=2, Locals=0, Args_size=0
   0:	ldc2_w	#8; //long 1529165946227428979l
   3:	putstatic	#13; //Field serialVersionUID:J
   6:	return

public scala.collection.mutable.ArrayBuffer(int);
  Code:
   Stack=2, Locals=2, Args_size=2
   0:	aload_0
   1:	iload_1
   2:	putfield	#23; //Field initialSize:I
   5:	aload_0
   6:	invokespecial	#27; //Method java/lang/Object."<init>":()V
   9:	aload_0
   10:	invokestatic	#33; //Method scala/collection/TraversableLike$class.$init$:(Lscala/collection/TraversableLike;)V
   13:	aload_0
   14:	invokestatic	#38; //Method scala/collection/generic/GenericTraversableTemplate$class.$init$:(Lscala/collection/generic/GenericTraversableTemplate;)V
   17:	aload_0
   18:	invokestatic	#43; //Method scala/collection/Traversable$class.$init$:(Lscala/collection/Traversable;)V
   21:	aload_0
   22:	invokestatic	#48; //Method scala/collection/mutable/Traversable$class.$init$:(Lscala/collection/mutable/Traversable;)V
   25:	aload_0
   26:	invokestatic	#53; //Method scala/collection/IterableLike$class.$init$:(Lscala/collection/IterableLike;)V
   29:	aload_0
   30:	invokestatic	#58; //Method scala/collection/Iterable$class.$init$:(Lscala/collection/Iterable;)V
   33:	aload_0
   34:	invokestatic	#63; //Method scala/collection/mutable/Iterable$class.$init$:(Lscala/collection/mutable/Iterable;)V
   37:	aload_0
   38:	invokestatic	#68; //Method scala/Function1$class.$init$:(Lscala/Function1;)V
   41:	aload_0
   42:	invokestatic	#73; //Method scala/PartialFunction$class.$init$:(Lscala/PartialFunction;)V
   45:	aload_0
   46:	invokestatic	#78; //Method scala/collection/SeqLike$class.$init$:(Lscala/collection/SeqLike;)V
   49:	aload_0
   50:	invokestatic	#83; //Method scala/collection/Seq$class.$init$:(Lscala/collection/Seq;)V
   53:	aload_0
   54:	invokestatic	#88; //Method scala/collection/mutable/Seq$class.$init$:(Lscala/collection/mutable/Seq;)V
   57:	aload_0
   58:	invokestatic	#93; //Method scala/collection/generic/Growable$class.$init$:(Lscala/collection/generic/Growable;)V
   61:	aload_0
   62:	invokestatic	#98; //Method scala/collection/generic/Shrinkable$class.$init$:(Lscala/collection/generic/Shrinkable;)V
   65:	aload_0
   66:	invokestatic	#103; //Method scala/collection/generic/Addable$class.$init$:(Lscala/collection/generic/Addable;)V
   69:	aload_0
   70:	invokestatic	#108; //Method scala/collection/generic/Subtractable$class.$init$:(Lscala/collection/generic/Subtractable;)V
   73:	aload_0
   74:	invokestatic	#113; //Method scala/collection/mutable/Cloneable$class.$init$:(Lscala/collection/mutable/Cloneable;)V
   77:	aload_0
   78:	invokestatic	#118; //Method scala/collection/mutable/BufferLike$class.$init$:(Lscala/collection/mutable/BufferLike;)V
   81:	aload_0
   82:	invokestatic	#123; //Method scala/collection/mutable/Buffer$class.$init$:(Lscala/collection/mutable/Buffer;)V
   85:	aload_0
   86:	invokestatic	#128; //Method scala/collection/IndexedSeqLike$class.$init$:(Lscala/collection/IndexedSeqLike;)V
   89:	aload_0
   90:	invokestatic	#133; //Method scala/collection/mutable/IndexedSeqLike$class.$init$:(Lscala/collection/mutable/IndexedSeqLike;)V
   93:	aload_0
   94:	invokestatic	#138; //Method scala/collection/mutable/Builder$class.$init$:(Lscala/collection/mutable/Builder;)V
   97:	aload_0
   98:	invokestatic	#143; //Method scala/collection/IndexedSeq$class.$init$:(Lscala/collection/IndexedSeq;)V
   101:	aload_0
   102:	invokestatic	#148; //Method scala/collection/mutable/IndexedSeq$class.$init$:(Lscala/collection/mutable/IndexedSeq;)V
   105:	aload_0
   106:	invokestatic	#153; //Method scala/collection/mutable/ResizableArray$class.$init$:(Lscala/collection/mutable/ResizableArray;)V
   109:	return
  LineNumberTable: 
   line 28: 0

  LocalVariableTable: 
   Start  Length  Slot  Name   Signature
   0      110      0    this       Lscala/collection/mutable/ArrayBuffer;
   0      110      1    initialSize       I

  Signature: length = 0x2
   00 14 

public scala.collection.mutable.Builder $plus$eq(java.lang.Object);
  Code:
   Stack=2, Locals=2, Args_size=2
   0:	aload_0
   1:	aload_1
   2:	invokevirtual	#162; //Method $plus$eq:(Ljava/lang/Object;)Lscala/collection/mutable/ArrayBuffer;
   5:	areturn
  LineNumberTable: 
   line 28: 0

  LocalVariableTable: 
   Start  Length  Slot  Name   Signature
   0      6      0    this       Lscala/collection/mutable/ArrayBuffer;
   0      6      1    elem       Ljava/lang/Object;


public scala.collection.mutable.BufferLike $plus$eq(java.lang.Object);
  Code:
   Stack=2, Locals=2, Args_size=2
   0:	aload_0
   1:	aload_1
   2:	invokevirtual	#162; //Method $plus$eq:(Ljava/lang/Object;)Lscala/collection/mutable/ArrayBuffer;
   5:	areturn
  LineNumberTable: 
   line 28: 0

  LocalVariableTable: 
   Start  Length  Slot  Name   Signature
   0      6      0    this       Lscala/collection/mutable/ArrayBuffer;
   0      6      1    elem       Ljava/lang/Object;


public scala.collection.generic.Growable $plus$eq(java.lang.Object);
  Code:
   Stack=2, Locals=2, Args_size=2
   0:	aload_0
   1:	aload_1
   2:	invokevirtual	#162; //Method $plus$eq:(Ljava/lang/Object;)Lscala/collection/mutable/ArrayBuffer;
   5:	areturn
  LineNumberTable: 
   line 28: 0

  LocalVariableTable: 
   Start  Length  Slot  Name   Signature
   0      6      0    this       Lscala/collection/mutable/ArrayBuffer;
   0      6      1    elem       Ljava/lang/Object;


public scala.collection.generic.Growable $plus$plus$eq(scala.collection.Traversable);
  Code:
   Stack=2, Locals=2, Args_size=2
   0:	aload_0
   1:	aload_1
   2:	invokevirtual	#171; //Method $plus$plus$eq:(Lscala/collection/Traversable;)Lscala/collection/mutable/ArrayBuffer;
   5:	areturn
  LineNumberTable: 
   line 28: 0

  LocalVariableTable: 
   Start  Length  Slot  Name   Signature
   0      6      0    this       Lscala/collection/mutable/ArrayBuffer;
   0      6      1    elems       Lscala/collection/Traversable;


public scala.collection.mutable.BufferLike $plus$eq$colon(java.lang.Object);
  Code:
   Stack=2, Locals=2, Args_size=2
   0:	aload_0
   1:	aload_1
   2:	invokevirtual	#176; //Method $plus$eq$colon:(Ljava/lang/Object;)Lscala/collection/mutable/ArrayBuffer;
   5:	areturn
  LineNumberTable: 
   line 28: 0

  LocalVariableTable: 
   Start  Length  Slot  Name   Signature
   0      6      0    this       Lscala/collection/mutable/ArrayBuffer;
   0      6      1    elem       Ljava/lang/Object;


public scala.collection.mutable.BufferLike $plus$plus$eq$colon(scala.collection.Traversable);
  Code:
   Stack=2, Locals=2, Args_size=2
   0:	aload_0
   1:	aload_1
   2:	invokevirtual	#180; //Method $plus$plus$eq$colon:(Lscala/collection/Traversable;)Lscala/collection/mutable/ArrayBuffer;
   5:	areturn
  LineNumberTable: 
   line 28: 0

  LocalVariableTable: 
   Start  Length  Slot  Name   Signature
   0      6      0    this       Lscala/collection/mutable/ArrayBuffer;
   0      6      1    elems       Lscala/collection/Traversable;


public java.lang.Object clone();
  Code:
   Stack=1, Locals=1, Args_size=1
   0:	aload_0
   1:	invokevirtual	#185; //Method clone:()Lscala/collection/mutable/ArrayBuffer;
   4:	areturn
  LineNumberTable: 
   line 28: 0


public java.lang.Object result();
  Code:
   Stack=1, Locals=1, Args_size=1
   0:	aload_0
   1:	invokevirtual	#188; //Method result:()Lscala/collection/mutable/ArrayBuffer;
   4:	areturn
  LineNumberTable: 
   line 28: 0


public java.lang.Object apply(java.lang.Object);
  Code:
   Stack=2, Locals=2, Args_size=2
   0:	aload_0
   1:	aload_1
   2:	invokestatic	#196; //Method scala/runtime/BoxesRunTime.unboxToInt:(Ljava/lang/Object;)I
   5:	invokeinterface	#201,  2; //InterfaceMethod scala/collection/mutable/ResizableArray.apply:(I)Ljava/lang/Object;
   10:	areturn
  LineNumberTable: 
   line 28: 0

  LocalVariableTable: 
   Start  Length  Slot  Name   Signature
   0      11      0    this       Lscala/collection/mutable/ArrayBuffer;
   0      11      1    v1       Ljava/lang/Object;


public scala.collection.IndexedSeq thisCollection();
  Code:
   Stack=1, Locals=1, Args_size=1
   0:	aload_0
   1:	invokeinterface	#209,  1; //InterfaceMethod scala/collection/mutable/IndexedSeqLike.thisCollection:()Lscala/collection/mutable/IndexedSeq;
   6:	areturn
  LineNumberTable: 
   line 28: 0


public scala.collection.Seq thisCollection();
  Code:
   Stack=1, Locals=1, Args_size=1
   0:	aload_0
   1:	invokeinterface	#209,  1; //InterfaceMethod scala/collection/mutable/IndexedSeqLike.thisCollection:()Lscala/collection/mutable/IndexedSeq;
   6:	areturn
  LineNumberTable: 
   line 28: 0


public scala.collection.Iterable thisCollection();
  Code:
   Stack=1, Locals=1, Args_size=1
   0:	aload_0
   1:	invokeinterface	#209,  1; //InterfaceMethod scala/collection/mutable/IndexedSeqLike.thisCollection:()Lscala/collection/mutable/IndexedSeq;
   6:	areturn
  LineNumberTable: 
   line 28: 0


public scala.collection.Traversable thisCollection();
  Code:
   Stack=1, Locals=1, Args_size=1
   0:	aload_0
   1:	invokeinterface	#209,  1; //InterfaceMethod scala/collection/mutable/IndexedSeqLike.thisCollection:()Lscala/collection/mutable/IndexedSeq;
   6:	areturn
  LineNumberTable: 
   line 28: 0


public scala.collection.IndexedSeq toCollection(java.lang.Object);
  Code:
   Stack=2, Locals=2, Args_size=2
   0:	aload_0
   1:	aload_1
   2:	invokeinterface	#217,  2; //InterfaceMethod scala/collection/mutable/IndexedSeqLike.toCollection:(Ljava/lang/Object;)Lscala/collection/mutable/IndexedSeq;
   7:	areturn
  LineNumberTable: 
   line 28: 0

  LocalVariableTable: 
   Start  Length  Slot  Name   Signature
   0      8      0    this       Lscala/collection/mutable/ArrayBuffer;
   0      8      1    repr       Ljava/lang/Object;


public scala.collection.Seq toCollection(java.lang.Object);
  Code:
   Stack=2, Locals=2, Args_size=2
   0:	aload_0
   1:	aload_1
   2:	invokeinterface	#217,  2; //InterfaceMethod scala/collection/mutable/IndexedSeqLike.toCollection:(Ljava/lang/Object;)Lscala/collection/mutable/IndexedSeq;
   7:	areturn
  LineNumberTable: 
   line 28: 0

  LocalVariableTable: 
   Start  Length  Slot  Name   Signature
   0      8      0    this       Lscala/collection/mutable/ArrayBuffer;
   0      8      1    repr       Ljava/lang/Object;


public scala.collection.Iterable toCollection(java.lang.Object);
  Code:
   Stack=2, Locals=2, Args_size=2
   0:	aload_0
   1:	aload_1
   2:	invokeinterface	#217,  2; //InterfaceMethod scala/collection/mutable/IndexedSeqLike.toCollection:(Ljava/lang/Object;)Lscala/collection/mutable/IndexedSeq;
   7:	areturn
  LineNumberTable: 
   line 28: 0

  LocalVariableTable: 
   Start  Length  Slot  Name   Signature
   0      8      0    this       Lscala/collection/mutable/ArrayBuffer;
   0      8      1    repr       Ljava/lang/Object;


public scala.collection.Traversable toCollection(java.lang.Object);
  Code:
   Stack=2, Locals=2, Args_size=2
   0:	aload_0
   1:	aload_1
   2:	invokeinterface	#217,  2; //InterfaceMethod scala/collection/mutable/IndexedSeqLike.toCollection:(Ljava/lang/Object;)Lscala/collection/mutable/IndexedSeq;
   7:	areturn
  LineNumberTable: 
   line 28: 0

  LocalVariableTable: 
   Start  Length  Slot  Name   Signature
   0      8      0    this       Lscala/collection/mutable/ArrayBuffer;
   0      8      1    repr       Ljava/lang/Object;


public scala.collection.IndexedSeqView view(int, int);
  Code:
   Stack=3, Locals=3, Args_size=3
   0:	aload_0
   1:	iload_1
   2:	iload_2
   3:	invokeinterface	#226,  3; //InterfaceMethod scala/collection/mutable/IndexedSeqLike.view:(II)Lscala/collection/mutable/IndexedSeqView;
   8:	areturn
  LineNumberTable: 
   line 28: 0

  LocalVariableTable: 
   Start  Length  Slot  Name   Signature
   0      9      0    this       Lscala/collection/mutable/ArrayBuffer;
   0      9      1    from       I
   0      9      2    until       I


public scala.collection.SeqView view(int, int);
  Code:
   Stack=3, Locals=3, Args_size=3
   0:	aload_0
   1:	iload_1
   2:	iload_2
   3:	invokeinterface	#226,  3; //InterfaceMethod scala/collection/mutable/IndexedSeqLike.view:(II)Lscala/collection/mutable/IndexedSeqView;
   8:	areturn
  LineNumberTable: 
   line 28: 0

  LocalVariableTable: 
   Start  Length  Slot  Name   Signature
   0      9      0    this       Lscala/collection/mutable/ArrayBuffer;
   0      9      1    from       I
   0      9      2    until       I


public scala.collection.IterableView view(int, int);
  Code:
   Stack=3, Locals=3, Args_size=3
   0:	aload_0
   1:	iload_1
   2:	iload_2
   3:	invokeinterface	#226,  3; //InterfaceMethod scala/collection/mutable/IndexedSeqLike.view:(II)Lscala/collection/mutable/IndexedSeqView;
   8:	areturn
  LineNumberTable: 
   line 28: 0

  LocalVariableTable: 
   Start  Length  Slot  Name   Signature
   0      9      0    this       Lscala/collection/mutable/ArrayBuffer;
   0      9      1    from       I
   0      9      2    until       I


public scala.collection.TraversableView view(int, int);
  Code:
   Stack=3, Locals=3, Args_size=3
   0:	aload_0
   1:	iload_1
   2:	iload_2
   3:	invokeinterface	#226,  3; //InterfaceMethod scala/collection/mutable/IndexedSeqLike.view:(II)Lscala/collection/mutable/IndexedSeqView;
   8:	areturn
  LineNumberTable: 
   line 28: 0

  LocalVariableTable: 
   Start  Length  Slot  Name   Signature
   0      9      0    this       Lscala/collection/mutable/ArrayBuffer;
   0      9      1    from       I
   0      9      2    until       I


public scala.collection.generic.Shrinkable $minus$eq(java.lang.Object);
  Code:
   Stack=2, Locals=2, Args_size=2
   0:	aload_0
   1:	aload_1
   2:	invokeinterface	#237,  2; //InterfaceMethod scala/collection/mutable/BufferLike.$minus$eq:(Ljava/lang/Object;)Lscala/collection/mutable/BufferLike;
   7:	areturn
  LineNumberTable: 
   line 28: 0

  LocalVariableTable: 
   Start  Length  Slot  Name   Signature
   0      8      0    this       Lscala/collection/mutable/ArrayBuffer;
   0      8      1    elem       Ljava/lang/Object;


public scala.collection.generic.Addable $plus(java.lang.Object);
  Code:
   Stack=2, Locals=2, Args_size=2
   0:	aload_0
   1:	aload_1
   2:	invokeinterface	#241,  2; //InterfaceMethod scala/collection/mutable/BufferLike.$plus:(Ljava/lang/Object;)Lscala/collection/mutable/BufferLike;
   7:	areturn
  LineNumberTable: 
   line 28: 0

  LocalVariableTable: 
   Start  Length  Slot  Name   Signature
   0      8      0    this       Lscala/collection/mutable/ArrayBuffer;
   0      8      1    elem       Ljava/lang/Object;


public scala.collection.generic.Addable $plus(java.lang.Object, java.lang.Object, scala.collection.Seq);
  Code:
   Stack=4, Locals=4, Args_size=4
   0:	aload_0
   1:	aload_1
   2:	aload_2
   3:	aload_3
   4:	invokeinterface	#245,  4; //InterfaceMethod scala/collection/mutable/BufferLike.$plus:(Ljava/lang/Object;Ljava/lang/Object;Lscala/collection/Seq;)Lscala/collection/mutable/BufferLike;
   9:	areturn
  LineNumberTable: 
   line 28: 0

  LocalVariableTable: 
   Start  Length  Slot  Name   Signature
   0      10      0    this       Lscala/collection/mutable/ArrayBuffer;
   0      10      1    elem1       Ljava/lang/Object;
   0      10      2    elem2       Ljava/lang/Object;
   0      10      3    elems       Lscala/collection/Seq;


public scala.collection.generic.Addable $plus$plus(scala.collection.Traversable);
  Code:
   Stack=2, Locals=2, Args_size=2
   0:	aload_0
   1:	aload_1
   2:	invokeinterface	#252,  2; //InterfaceMethod scala/collection/mutable/BufferLike.$plus$plus:(Lscala/collection/Traversable;)Lscala/collection/mutable/BufferLike;
   7:	areturn
  LineNumberTable: 
   line 28: 0

  LocalVariableTable: 
   Start  Length  Slot  Name   Signature
   0      8      0    this       Lscala/collection/mutable/ArrayBuffer;
   0      8      1    elems       Lscala/collection/Traversable;


public scala.collection.generic.Addable $plus$plus(scala.collection.Iterator);
  Code:
   Stack=2, Locals=2, Args_size=2
   0:	aload_0
   1:	aload_1
   2:	invokeinterface	#256,  2; //InterfaceMethod scala/collection/mutable/BufferLike.$plus$plus:(Lscala/collection/Iterator;)Lscala/collection/mutable/BufferLike;
   7:	areturn
  LineNumberTable: 
   line 28: 0

  LocalVariableTable: 
   Start  Length  Slot  Name   Signature
   0      8      0    this       Lscala/collection/mutable/ArrayBuffer;
   0      8      1    iter       Lscala/collection/Iterator;


public scala.collection.generic.Subtractable $minus(java.lang.Object);
  Code:
   Stack=2, Locals=2, Args_size=2
   0:	aload_0
   1:	aload_1
   2:	invokeinterface	#262,  2; //InterfaceMethod scala/collection/mutable/BufferLike.$minus:(Ljava/lang/Object;)Lscala/collection/mutable/BufferLike;
   7:	areturn
  LineNumberTable: 
   line 28: 0

  LocalVariableTable: 
   Start  Length  Slot  Name   Signature
   0      8      0    this       Lscala/collection/mutable/ArrayBuffer;
   0      8      1    elem       Ljava/lang/Object;


public scala.collection.generic.Subtractable $minus(java.lang.Object, java.lang.Object, scala.collection.Seq);
  Code:
   Stack=4, Locals=4, Args_size=4
   0:	aload_0
   1:	aload_1
   2:	aload_2
   3:	aload_3
   4:	invokeinterface	#265,  4; //InterfaceMethod scala/collection/mutable/BufferLike.$minus:(Ljava/lang/Object;Ljava/lang/Object;Lscala/collection/Seq;)Lscala/collection/mutable/BufferLike;
   9:	areturn
  LineNumberTable: 
   line 28: 0

  LocalVariableTable: 
   Start  Length  Slot  Name   Signature
   0      10      0    this       Lscala/collection/mutable/ArrayBuffer;
   0      10      1    elem1       Ljava/lang/Object;
   0      10      2    elem2       Ljava/lang/Object;
   0      10      3    elems       Lscala/collection/Seq;


public scala.collection.generic.Subtractable $minus$minus(scala.collection.Traversable);
  Code:
   Stack=2, Locals=2, Args_size=2
   0:	aload_0
   1:	aload_1
   2:	invokeinterface	#269,  2; //InterfaceMethod scala/collection/mutable/BufferLike.$minus$minus:(Lscala/collection/Traversable;)Lscala/collection/mutable/BufferLike;
   7:	areturn
  LineNumberTable: 
   line 28: 0

  LocalVariableTable: 
   Start  Length  Slot  Name   Signature
   0      8      0    this       Lscala/collection/mutable/ArrayBuffer;
   0      8      1    elems       Lscala/collection/Traversable;


public scala.collection.generic.Subtractable $minus$minus(scala.collection.Iterator);
  Code:
   Stack=2, Locals=2, Args_size=2
   0:	aload_0
   1:	aload_1
   2:	invokeinterface	#272,  2; //InterfaceMethod scala/collection/mutable/BufferLike.$minus$minus:(Lscala/collection/Iterator;)Lscala/collection/mutable/BufferLike;
   7:	areturn
  LineNumberTable: 
   line 28: 0

  LocalVariableTable: 
   Start  Length  Slot  Name   Signature
   0      8      0    this       Lscala/collection/mutable/ArrayBuffer;
   0      8      1    iter       Lscala/collection/Iterator;


public boolean isDefinedAt(java.lang.Object);
  Code:
   Stack=2, Locals=2, Args_size=2
   0:	aload_0
   1:	aload_1
   2:	invokestatic	#196; //Method scala/runtime/BoxesRunTime.unboxToInt:(Ljava/lang/Object;)I
   5:	invokeinterface	#279,  2; //InterfaceMethod scala/collection/SeqLike.isDefinedAt:(I)Z
   10:	ireturn
  LineNumberTable: 
   line 28: 0

  LocalVariableTable: 
   Start  Length  Slot  Name   Signature
   0      11      0    this       Lscala/collection/mutable/ArrayBuffer;
   0      11      1    x       Ljava/lang/Object;


public scala.Function1 andThen(scala.Function1);
  Code:
   Stack=2, Locals=2, Args_size=2
   0:	aload_0
   1:	aload_1
   2:	invokeinterface	#287,  2; //InterfaceMethod scala/PartialFunction.andThen:(Lscala/Function1;)Lscala/PartialFunction;
   7:	areturn
  LineNumberTable: 
   line 28: 0

  LocalVariableTable: 
   Start  Length  Slot  Name   Signature
   0      8      0    this       Lscala/collection/mutable/ArrayBuffer;
   0      8      1    g       Lscala/Function1;


public scala.collection.generic.Subtractable repr();
  Code:
   Stack=1, Locals=1, Args_size=1
   0:	aload_0
   1:	invokeinterface	#294,  1; //InterfaceMethod scala/collection/TraversableLike.repr:()Ljava/lang/Object;
   6:	checkcast	#296; //class scala/collection/generic/Subtractable
   9:	areturn
  LineNumberTable: 
   line 28: 0


public scala.collection.generic.Addable repr();
  Code:
   Stack=1, Locals=1, Args_size=1
   0:	aload_0
   1:	invokeinterface	#294,  1; //InterfaceMethod scala/collection/TraversableLike.repr:()Ljava/lang/Object;
   6:	checkcast	#299; //class scala/collection/generic/Addable
   9:	areturn
  LineNumberTable: 
   line 28: 0


public java.lang.String stringPrefix();
  Code:
   Stack=1, Locals=1, Args_size=1
   0:	ldc_w	#303; //String ArrayBuffer
   3:	areturn
  LineNumberTable: 
   line 159: 0


public scala.collection.mutable.ArrayBuffer result();
  Code:
   Stack=1, Locals=1, Args_size=1
   0:	aload_0
   1:	areturn
  LineNumberTable: 
   line 155: 0

  Signature: length = 0x2
   01 30 

public scala.collection.mutable.ArrayBuffer clone();
  Code:
   Stack=2, Locals=1, Args_size=1
   0:	new	#11; //class scala/collection/mutable/ArrayBuffer
   3:	dup
   4:	invokespecial	#305; //Method "<init>":()V
   7:	aload_0
   8:	invokevirtual	#171; //Method $plus$plus$eq:(Lscala/collection/Traversable;)Lscala/collection/mutable/ArrayBuffer;
   11:	areturn
  LineNumberTable: 
   line 153: 0

  Signature: length = 0x2
   01 30 

public java.lang.Object remove(int);
  Code:
   Stack=3, Locals=3, Args_size=2
   0:	aload_0
   1:	iload_1
   2:	invokeinterface	#201,  2; //InterfaceMethod scala/collection/mutable/ResizableArray.apply:(I)Ljava/lang/Object;
   7:	astore_2
   8:	aload_0
   9:	iload_1
   10:	iconst_1
   11:	invokevirtual	#309; //Method remove:(II)V
   14:	aload_2
   15:	areturn
  LineNumberTable: 
   line 144: 0
   line 145: 8
   line 146: 14

  LocalVariableTable: 
   Start  Length  Slot  Name   Signature
   0      16      0    this       Lscala/collection/mutable/ArrayBuffer;
   0      16      1    n       I
   8      7      2    result       Ljava/lang/Object;

  Signature: length = 0x2
   01 37 

public void remove(int, int);
  Code:
   Stack=6, Locals=4, Args_size=3
   0:	iload_2
   1:	iconst_0
   2:	if_icmplt	9
   5:	iconst_1
   6:	goto	10
   9:	iconst_0
   10:	new	#313; //class scala/collection/mutable/ArrayBuffer$$anonfun$remove$1
   13:	dup
   14:	pop
   15:	aload_0
   16:	invokespecial	#316; //Method scala/collection/mutable/ArrayBuffer$$anonfun$remove$1."<init>":(Lscala/collection/mutable/ArrayBuffer;)V
   19:	istore_3
   20:	iload_3
   21:	ifeq	91
   24:	iload_1
   25:	iconst_0
   26:	if_icmplt	41
   29:	iload_1
   30:	aload_0
   31:	invokeinterface	#319,  1; //InterfaceMethod scala/collection/mutable/ResizableArray.size0:()I
   36:	iload_2
   37:	isub
   38:	if_icmple	56
   41:	new	#321; //class java/lang/IndexOutOfBoundsException
   44:	dup
   45:	iload_1
   46:	invokestatic	#325; //Method scala/runtime/BoxesRunTime.boxToInteger:(I)Ljava/lang/Integer;
   49:	invokevirtual	#328; //Method java/lang/Object.toString:()Ljava/lang/String;
   52:	invokespecial	#331; //Method java/lang/IndexOutOfBoundsException."<init>":(Ljava/lang/String;)V
   55:	athrow
   56:	aload_0
   57:	iload_1
   58:	iload_2
   59:	iadd
   60:	iload_1
   61:	aload_0
   62:	invokeinterface	#319,  1; //InterfaceMethod scala/collection/mutable/ResizableArray.size0:()I
   67:	iload_1
   68:	iload_2
   69:	iadd
   70:	isub
   71:	invokeinterface	#335,  4; //InterfaceMethod scala/collection/mutable/ResizableArray.copy:(III)V
   76:	aload_0
   77:	aload_0
   78:	invokeinterface	#319,  1; //InterfaceMethod scala/collection/mutable/ResizableArray.size0:()I
   83:	iload_2
   84:	isub
   85:	invokeinterface	#338,  2; //InterfaceMethod scala/collection/mutable/ResizableArray.size0_$eq:(I)V
   90:	return
   91:	new	#340; //class java/lang/IllegalArgumentException
   94:	dup
   95:	new	#342; //class scala/collection/mutable/StringBuilder
   98:	dup
   99:	invokespecial	#343; //Method scala/collection/mutable/StringBuilder."<init>":()V
   102:	ldc_w	#345; //String requirement failed: 
   105:	invokevirtual	#349; //Method scala/collection/mutable/StringBuilder.append:(Ljava/lang/Object;)Lscala/collection/mutable/StringBuilder;
   108:	ldc_w	#351; //String removing negative number of elements
   111:	invokevirtual	#349; //Method scala/collection/mutable/StringBuilder.append:(Ljava/lang/Object;)Lscala/collection/mutable/StringBuilder;
   114:	invokevirtual	#352; //Method scala/collection/mutable/StringBuilder.toString:()Ljava/lang/String;
   117:	invokespecial	#353; //Method java/lang/IllegalArgumentException."<init>":(Ljava/lang/String;)V
   120:	athrow
  LineNumberTable: 
   line 132: 0
   line 133: 24
   line 134: 56
   line 135: 76
   line 132: 91

  LocalVariableTable: 
   Start  Length  Slot  Name   Signature
   0      121      0    this       Lscala/collection/mutable/ArrayBuffer;
   0      121      1    n       I
   0      121      2    count       I
   24      5      3    requirement0       Z
   91      30      3    requirement0       Z


public void insertAll(int, scala.collection.Traversable);
  Code:
   Stack=5, Locals=5, Args_size=3
   0:	iload_1
   1:	iconst_0
   2:	if_icmplt	15
   5:	iload_1
   6:	aload_0
   7:	invokeinterface	#319,  1; //InterfaceMethod scala/collection/mutable/ResizableArray.size0:()I
   12:	if_icmple	30
   15:	new	#321; //class java/lang/IndexOutOfBoundsException
   18:	dup
   19:	iload_1
   20:	invokestatic	#325; //Method scala/runtime/BoxesRunTime.boxToInteger:(I)Ljava/lang/Integer;
   23:	invokevirtual	#328; //Method java/lang/Object.toString:()Ljava/lang/String;
   26:	invokespecial	#331; //Method java/lang/IndexOutOfBoundsException."<init>":(Ljava/lang/String;)V
   29:	athrow
   30:	aload_2
   31:	invokeinterface	#362,  1; //InterfaceMethod scala/collection/TraversableLike.toList:()Lscala/collection/immutable/List;
   36:	astore_3
   37:	aload_3
   38:	invokeinterface	#367,  1; //InterfaceMethod scala/collection/LinearSeqLike.length:()I
   43:	istore	4
   45:	aload_0
   46:	aload_0
   47:	invokeinterface	#319,  1; //InterfaceMethod scala/collection/mutable/ResizableArray.size0:()I
   52:	iload	4
   54:	iadd
   55:	invokeinterface	#370,  2; //InterfaceMethod scala/collection/mutable/ResizableArray.ensureSize:(I)V
   60:	aload_0
   61:	iload_1
   62:	iload_1
   63:	iload	4
   65:	iadd
   66:	aload_0
   67:	invokeinterface	#319,  1; //InterfaceMethod scala/collection/mutable/ResizableArray.size0:()I
   72:	iload_1
   73:	isub
   74:	invokeinterface	#335,  4; //InterfaceMethod scala/collection/mutable/ResizableArray.copy:(III)V
   79:	aload_3
   80:	aload_0
   81:	invokeinterface	#373,  1; //InterfaceMethod scala/collection/mutable/ResizableArray.array:()[Ljava/lang/Object;
   86:	iload_1
   87:	invokeinterface	#377,  3; //InterfaceMethod scala/collection/TraversableLike.copyToArray:(Ljava/lang/Object;I)V
   92:	aload_0
   93:	aload_0
   94:	invokeinterface	#319,  1; //InterfaceMethod scala/collection/mutable/ResizableArray.size0:()I
   99:	iload	4
   101:	iadd
   102:	invokeinterface	#338,  2; //InterfaceMethod scala/collection/mutable/ResizableArray.size0_$eq:(I)V
   107:	return
  LineNumberTable: 
   line 115: 0
   line 116: 30
   line 117: 37
   line 118: 45
   line 119: 60
   line 120: 79
   line 121: 92

  LocalVariableTable: 
   Start  Length  Slot  Name   Signature
   0      108      0    this       Lscala/collection/mutable/ArrayBuffer;
   0      108      1    n       I
   0      108      2    seq       Lscala/collection/Traversable;
   37      70      3    xs       Lscala/collection/immutable/List;
   45      62      4    len       I

  Signature: length = 0x2
   01 7E 

public scala.collection.mutable.ArrayBuffer $plus$plus$eq$colon(scala.collection.Traversable);
  Code:
   Stack=3, Locals=2, Args_size=2
   0:	aload_0
   1:	iconst_0
   2:	aload_1
   3:	invokevirtual	#384; //Method insertAll:(ILscala/collection/Traversable;)V
   6:	aload_0
   7:	areturn
  LineNumberTable: 
   line 104: 0

  LocalVariableTable: 
   Start  Length  Slot  Name   Signature
   0      8      0    this       Lscala/collection/mutable/ArrayBuffer;
   0      8      1    iter       Lscala/collection/Traversable;

  Signature: length = 0x2
   01 FFFFFF81 

public scala.collection.mutable.ArrayBuffer $plus$eq$colon(java.lang.Object);
  Code:
   Stack=4, Locals=2, Args_size=2
   0:	aload_0
   1:	aload_0
   2:	invokeinterface	#319,  1; //InterfaceMethod scala/collection/mutable/ResizableArray.size0:()I
   7:	iconst_1
   8:	iadd
   9:	invokeinterface	#370,  2; //InterfaceMethod scala/collection/mutable/ResizableArray.ensureSize:(I)V
   14:	aload_0
   15:	iconst_0
   16:	iconst_1
   17:	aload_0
   18:	invokeinterface	#319,  1; //InterfaceMethod scala/collection/mutable/ResizableArray.size0:()I
   23:	invokeinterface	#335,  4; //InterfaceMethod scala/collection/mutable/ResizableArray.copy:(III)V
   28:	aload_0
   29:	invokeinterface	#373,  1; //InterfaceMethod scala/collection/mutable/ResizableArray.array:()[Ljava/lang/Object;
   34:	iconst_0
   35:	aload_1
   36:	aastore
   37:	aload_0
   38:	aload_0
   39:	invokeinterface	#319,  1; //InterfaceMethod scala/collection/mutable/ResizableArray.size0:()I
   44:	iconst_1
   45:	iadd
   46:	invokeinterface	#338,  2; //InterfaceMethod scala/collection/mutable/ResizableArray.size0_$eq:(I)V
   51:	aload_0
   52:	areturn
  LineNumberTable: 
   line 90: 0
   line 91: 14
   line 92: 28
   line 93: 37
   line 94: 51

  LocalVariableTable: 
   Start  Length  Slot  Name   Signature
   0      53      0    this       Lscala/collection/mutable/ArrayBuffer;
   0      53      1    elem       Ljava/lang/Object;

  Signature: length = 0x2
   01 FFFFFF82 

public scala.collection.mutable.ArrayBuffer $plus$plus$eq(scala.collection.Traversable);
  Code:
   Stack=4, Locals=4, Args_size=2
   0:	aload_1
   1:	instanceof	#388; //class scala/collection/mutable/IndexedSeq
   4:	ifeq	88
   7:	aload_1
   8:	checkcast	#388; //class scala/collection/mutable/IndexedSeq
   11:	astore_2
   12:	iconst_1
   13:	ifeq	74
   16:	aload_2
   17:	invokeinterface	#389,  1; //InterfaceMethod scala/collection/SeqLike.length:()I
   22:	istore_3
   23:	aload_0
   24:	aload_0
   25:	invokeinterface	#319,  1; //InterfaceMethod scala/collection/mutable/ResizableArray.size0:()I
   30:	iload_3
   31:	iadd
   32:	invokeinterface	#370,  2; //InterfaceMethod scala/collection/mutable/ResizableArray.ensureSize:(I)V
   37:	aload_2
   38:	aload_0
   39:	invokeinterface	#373,  1; //InterfaceMethod scala/collection/mutable/ResizableArray.array:()[Ljava/lang/Object;
   44:	aload_0
   45:	invokeinterface	#319,  1; //InterfaceMethod scala/collection/mutable/ResizableArray.size0:()I
   50:	iload_3
   51:	invokeinterface	#394,  4; //InterfaceMethod scala/collection/IndexedSeqLike.copyToArray:(Ljava/lang/Object;II)V
   56:	aload_0
   57:	aload_0
   58:	invokeinterface	#319,  1; //InterfaceMethod scala/collection/mutable/ResizableArray.size0:()I
   63:	iload_3
   64:	iadd
   65:	invokeinterface	#338,  2; //InterfaceMethod scala/collection/mutable/ResizableArray.size0_$eq:(I)V
   70:	aload_0
   71:	goto	100
   74:	new	#396; //class scala/MatchError
   77:	dup
   78:	aload_1
   79:	invokeinterface	#397,  1; //InterfaceMethod scala/collection/TraversableLike.toString:()Ljava/lang/String;
   84:	invokespecial	#398; //Method scala/MatchError."<init>":(Ljava/lang/String;)V
   87:	athrow
   88:	iconst_1
   89:	ifeq	101
   92:	aload_0
   93:	aload_1
   94:	invokestatic	#401; //Method scala/collection/generic/Growable$class.$plus$plus$eq:(Lscala/collection/generic/Growable;Lscala/collection/Traversable;)Lscala/collection/generic/Growable;
   97:	checkcast	#11; //class scala/collection/mutable/ArrayBuffer
   100:	areturn
   101:	new	#396; //class scala/MatchError
   104:	dup
   105:	aload_1
   106:	invokeinterface	#397,  1; //InterfaceMethod scala/collection/TraversableLike.toString:()Ljava/lang/String;
   111:	invokespecial	#398; //Method scala/MatchError."<init>":(Ljava/lang/String;)V
   114:	athrow
  LineNumberTable: 
   line 71: 0
   line 21: 12
   line 73: 16
   line 74: 23
   line 75: 37
   line 76: 56
   line 77: 70
   line 71: 74
   line 21: 88
   line 79: 92
   line 71: 100

  LocalVariableTable: 
   Start  Length  Slot  Name   Signature
   0      115      0    this       Lscala/collection/mutable/ArrayBuffer;
   0      115      1    iter       Lscala/collection/Traversable;
   12      76      2    temp2       Lscala/collection/mutable/IndexedSeq;
   23      48      3    n       I

  Signature: length = 0x2
   01 FFFFFF81 

public scala.collection.mutable.ArrayBuffer $plus$eq(java.lang.Object);
  Code:
   Stack=3, Locals=2, Args_size=2
   0:	aload_0
   1:	aload_0
   2:	invokeinterface	#319,  1; //InterfaceMethod scala/collection/mutable/ResizableArray.size0:()I
   7:	iconst_1
   8:	iadd
   9:	invokeinterface	#370,  2; //InterfaceMethod scala/collection/mutable/ResizableArray.ensureSize:(I)V
   14:	aload_0
   15:	invokeinterface	#373,  1; //InterfaceMethod scala/collection/mutable/ResizableArray.array:()[Ljava/lang/Object;
   20:	aload_0
   21:	invokeinterface	#319,  1; //InterfaceMethod scala/collection/mutable/ResizableArray.size0:()I
   26:	aload_1
   27:	aastore
   28:	aload_0
   29:	aload_0
   30:	invokeinterface	#319,  1; //InterfaceMethod scala/collection/mutable/ResizableArray.size0:()I
   35:	iconst_1
   36:	iadd
   37:	invokeinterface	#338,  2; //InterfaceMethod scala/collection/mutable/ResizableArray.size0_$eq:(I)V
   42:	aload_0
   43:	areturn
  LineNumberTable: 
   line 58: 0
   line 59: 14
   line 60: 28
   line 61: 42

  LocalVariableTable: 
   Start  Length  Slot  Name   Signature
   0      44      0    this       Lscala/collection/mutable/ArrayBuffer;
   0      44      1    elem       Ljava/lang/Object;

  Signature: length = 0x2
   01 FFFFFF82 

public void sizeHint(int);
  Code:
   Stack=6, Locals=3, Args_size=2
   0:	iload_1
   1:	aload_0
   2:	invokeinterface	#407,  1; //InterfaceMethod scala/collection/SeqLike.size:()I
   7:	if_icmple	59
   10:	iload_1
   11:	iconst_1
   12:	if_icmplt	59
   15:	new	#409; //class scala/runtime/RichInt
   18:	dup
   19:	iload_1
   20:	invokespecial	#411; //Method scala/runtime/RichInt."<init>":(I)V
   23:	iconst_1
   24:	invokevirtual	#415; //Method scala/runtime/RichInt.min:(I)I
   27:	anewarray	#25; //class java/lang/Object
   30:	astore_2
   31:	getstatic	#421; //Field scala/Array$.MODULE$:Lscala/Array$;
   34:	aload_0
   35:	invokeinterface	#373,  1; //InterfaceMethod scala/collection/mutable/ResizableArray.array:()[Ljava/lang/Object;
   40:	iconst_0
   41:	aload_2
   42:	iconst_0
   43:	aload_0
   44:	invokeinterface	#319,  1; //InterfaceMethod scala/collection/mutable/ResizableArray.size0:()I
   49:	invokevirtual	#424; //Method scala/Array$.copy:(Ljava/lang/Object;ILjava/lang/Object;II)V
   52:	aload_0
   53:	aload_2
   54:	invokeinterface	#428,  2; //InterfaceMethod scala/collection/mutable/ResizableArray.array_$eq:([Ljava/lang/Object;)V
   59:	return
  LineNumberTable: 
   line 45: 0
   line 46: 15
   line 47: 31
   line 48: 52
   line 45: 59

  LocalVariableTable: 
   Start  Length  Slot  Name   Signature
   0      60      0    this       Lscala/collection/mutable/ArrayBuffer;
   0      60      1    len       I
   31      28      2    newarray       [Ljava/lang/Object;


public void clear();
  Code:
   Stack=2, Locals=1, Args_size=1
   0:	aload_0
   1:	iconst_0
   2:	invokeinterface	#433,  2; //InterfaceMethod scala/collection/mutable/ResizableArray.reduceToSize:(I)V
   7:	return
  LineNumberTable: 
   line 42: 0


public scala.collection.mutable.ArrayBuffer();
  Code:
   Stack=2, Locals=1, Args_size=1
   0:	aload_0
   1:	ldc_w	#434; //int 16
   4:	invokespecial	#435; //Method "<init>":(I)V
   7:	return
  LineNumberTable: 
   line 40: 0

  Signature: length = 0x2
   00 04 

public scala.collection.generic.GenericCompanion companion();
  Code:
   Stack=1, Locals=1, Args_size=1
   0:	getstatic	#442; //Field scala/collection/mutable/ArrayBuffer$.MODULE$:Lscala/collection/mutable/ArrayBuffer$;
   3:	areturn
  LineNumberTable: 
   line 36: 0

  Signature: length = 0x2
   01 FFFFFFBB 

public int initialSize();
  Code:
   Stack=1, Locals=1, Args_size=1
   0:	aload_0
   1:	getfield	#23; //Field initialSize:I
   4:	ireturn
  LineNumberTable: 
   line 28: 0


public scala.collection.TraversableLike$WithFilter withFilter(scala.Function1);
  Code:
   Stack=2, Locals=2, Args_size=2
   0:	aload_0
   1:	aload_1
   2:	invokestatic	#448; //Method scala/collection/TraversableLike$class.withFilter:(Lscala/collection/TraversableLike;Lscala/Function1;)Lscala/collection/TraversableLike$WithFilter;
   5:	areturn
  LineNumberTable: 
   line 28: 0

  LocalVariableTable: 
   Start  Length  Slot  Name   Signature
   0      6      0    this       Lscala/collection/mutable/ArrayBuffer;
   0      6      1    p       Lscala/Function1;

  Signature: length = 0x2
   01 FFFFFFBD 

public scala.collection.mutable.StringBuilder addString(scala.collection.mutable.StringBuilder);
  Code:
   Stack=2, Locals=2, Args_size=2
   0:	aload_0
   1:	aload_1
   2:	invokestatic	#454; //Method scala/collection/TraversableLike$class.addString:(Lscala/collection/TraversableLike;Lscala/collection/mutable/StringBuilder;)Lscala/collection/mutable/StringBuilder;
   5:	areturn
  LineNumberTable: 
   line 28: 0

  LocalVariableTable: 
   Start  Length  Slot  Name   Signature
   0      6      0    this       Lscala/collection/mutable/ArrayBuffer;
   0      6      1    b       Lscala/collection/mutable/StringBuilder;


public scala.collection.mutable.StringBuilder addString(scala.collection.mutable.StringBuilder, java.lang.String);
  Code:
   Stack=3, Locals=3, Args_size=3
   0:	aload_0
   1:	aload_1
   2:	aload_2
   3:	invokestatic	#460; //Method scala/collection/TraversableLike$class.addString:(Lscala/collection/TraversableLike;Lscala/collection/mutable/StringBuilder;Ljava/lang/String;)Lscala/collection/mutable/StringBuilder;
   6:	areturn
  LineNumberTable: 
   line 28: 0

  LocalVariableTable: 
   Start  Length  Slot  Name   Signature
   0      7      0    this       Lscala/collection/mutable/ArrayBuffer;
   0      7      1    b       Lscala/collection/mutable/StringBuilder;
   0      7      2    sep       Ljava/lang/String;


public scala.collection.mutable.StringBuilder addString(scala.collection.mutable.StringBuilder, java.lang.String, java.lang.String, java.lang.String);
  Code:
   Stack=5, Locals=5, Args_size=5
   0:	aload_0
   1:	aload_1
   2:	aload_2
   3:	aload_3
   4:	aload	4
   6:	invokestatic	#466; //Method scala/collection/TraversableLike$class.addString:(Lscala/collection/TraversableLike;Lscala/collection/mutable/StringBuilder;Ljava/lang/String;Ljava/lang/String;Ljava/lang/String;)Lscala/collection/mutable/StringBuilder;
   9:	areturn
  LineNumberTable: 
   line 28: 0

  LocalVariableTable: 
   Start  Length  Slot  Name   Signature
   0      10      0    this       Lscala/collection/mutable/ArrayBuffer;
   0      10      1    b       Lscala/collection/mutable/StringBuilder;
   0      10      2    start       Ljava/lang/String;
   0      10      3    sep       Ljava/lang/String;
   0      10      4    end       Ljava/lang/String;


public java.lang.String mkString();
  Code:
   Stack=1, Locals=1, Args_size=1
   0:	aload_0
   1:	invokestatic	#472; //Method scala/collection/TraversableLike$class.mkString:(Lscala/collection/TraversableLike;)Ljava/lang/String;
   4:	areturn
  LineNumberTable: 
   line 28: 0


public java.lang.String mkString(java.lang.String);
  Code:
   Stack=2, Locals=2, Args_size=2
   0:	aload_0
   1:	aload_1
   2:	invokestatic	#476; //Method scala/collection/TraversableLike$class.mkString:(Lscala/collection/TraversableLike;Ljava/lang/String;)Ljava/lang/String;
   5:	areturn
  LineNumberTable: 
   line 28: 0

  LocalVariableTable: 
   Start  Length  Slot  Name   Signature
   0      6      0    this       Lscala/collection/mutable/ArrayBuffer;
   0      6      1    sep       Ljava/lang/String;


public java.lang.String mkString(java.lang.String, java.lang.String, java.lang.String);
  Code:
   Stack=4, Locals=4, Args_size=4
   0:	aload_0
   1:	aload_1
   2:	aload_2
   3:	aload_3
   4:	invokestatic	#480; //Method scala/collection/TraversableLike$class.mkString:(Lscala/collection/TraversableLike;Ljava/lang/String;Ljava/lang/String;Ljava/lang/String;)Ljava/lang/String;
   7:	areturn
  LineNumberTable: 
   line 28: 0

  LocalVariableTable: 
   Start  Length  Slot  Name   Signature
   0      8      0    this       Lscala/collection/mutable/ArrayBuffer;
   0      8      1    start       Ljava/lang/String;
   0      8      2    sep       Ljava/lang/String;
   0      8      3    end       Ljava/lang/String;


public scala.collection.immutable.Set toSet();
  Code:
   Stack=1, Locals=1, Args_size=1
   0:	aload_0
   1:	invokestatic	#485; //Method scala/collection/TraversableLike$class.toSet:(Lscala/collection/TraversableLike;)Lscala/collection/immutable/Set;
   4:	areturn
  LineNumberTable: 
   line 28: 0


public scala.collection.mutable.IndexedSeq toIndexedSeq();
  Code:
   Stack=1, Locals=1, Args_size=1
   0:	aload_0
   1:	invokestatic	#489; //Method scala/collection/TraversableLike$class.toIndexedSeq:(Lscala/collection/TraversableLike;)Lscala/collection/mutable/IndexedSeq;
   4:	areturn
  LineNumberTable: 
   line 28: 0


public scala.collection.immutable.List toList();
  Code:
   Stack=1, Locals=1, Args_size=1
   0:	aload_0
   1:	invokestatic	#492; //Method scala/collection/TraversableLike$class.toList:(Lscala/collection/TraversableLike;)Lscala/collection/immutable/List;
   4:	areturn
  LineNumberTable: 
   line 28: 0


public java.lang.Object toArray(scala.reflect.ClassManifest);
  Code:
   Stack=2, Locals=2, Args_size=2
   0:	aload_0
   1:	aload_1
   2:	invokestatic	#497; //Method scala/collection/TraversableLike$class.toArray:(Lscala/collection/TraversableLike;Lscala/reflect/ClassManifest;)Ljava/lang/Object;
   5:	areturn
  LineNumberTable: 
   line 28: 0

  LocalVariableTable: 
   Start  Length  Slot  Name   Signature
   0      6      0    this       Lscala/collection/mutable/ArrayBuffer;
   0      6      1    evidence$1       Lscala/reflect/ClassManifest;


public void copyToArray(java.lang.Object);
  Code:
   Stack=2, Locals=2, Args_size=2
   0:	aload_0
   1:	aload_1
   2:	invokestatic	#503; //Method scala/collection/TraversableLike$class.copyToArray:(Lscala/collection/TraversableLike;Ljava/lang/Object;)V
   5:	return
  LineNumberTable: 
   line 28: 0

  LocalVariableTable: 
   Start  Length  Slot  Name   Signature
   0      6      0    this       Lscala/collection/mutable/ArrayBuffer;
   0      6      1    xs       Ljava/lang/Object;


public void copyToArray(java.lang.Object, int);
  Code:
   Stack=3, Locals=3, Args_size=3
   0:	aload_0
   1:	aload_1
   2:	iload_2
   3:	invokestatic	#506; //Method scala/collection/TraversableLike$class.copyToArray:(Lscala/collection/TraversableLike;Ljava/lang/Object;I)V
   6:	return
  LineNumberTable: 
   line 28: 0

  LocalVariableTable: 
   Start  Length  Slot  Name   Signature
   0      7      0    this       Lscala/collection/mutable/ArrayBuffer;
   0      7      1    xs       Ljava/lang/Object;
   0      7      2    start       I


public void copyToBuffer(scala.collection.mutable.Buffer);
  Code:
   Stack=2, Locals=2, Args_size=2
   0:	aload_0
   1:	aload_1
   2:	invokestatic	#510; //Method scala/collection/TraversableLike$class.copyToBuffer:(Lscala/collection/TraversableLike;Lscala/collection/mutable/Buffer;)V
   5:	return
  LineNumberTable: 
   line 28: 0

  LocalVariableTable: 
   Start  Length  Slot  Name   Signature
   0      6      0    this       Lscala/collection/mutable/ArrayBuffer;
   0      6      1    dest       Lscala/collection/mutable/Buffer;


public scala.Option lastOption();
  Code:
   Stack=1, Locals=1, Args_size=1
   0:	aload_0
   1:	invokestatic	#517; //Method scala/collection/TraversableLike$class.lastOption:(Lscala/collection/TraversableLike;)Lscala/Option;
   4:	areturn
  LineNumberTable: 
   line 28: 0


public scala.Option headOption();
  Code:
   Stack=1, Locals=1, Args_size=1
   0:	aload_0
   1:	invokestatic	#520; //Method scala/collection/TraversableLike$class.headOption:(Lscala/collection/TraversableLike;)Lscala/Option;
   4:	areturn
  LineNumberTable: 
   line 28: 0


public java.lang.Object max(scala.math.Ordering);
  Code:
   Stack=2, Locals=2, Args_size=2
   0:	aload_0
   1:	aload_1
   2:	invokestatic	#525; //Method scala/collection/TraversableLike$class.max:(Lscala/collection/TraversableLike;Lscala/math/Ordering;)Ljava/lang/Object;
   5:	areturn
  LineNumberTable: 
   line 28: 0

  LocalVariableTable: 
   Start  Length  Slot  Name   Signature
   0      6      0    this       Lscala/collection/mutable/ArrayBuffer;
   0      6      1    cmp       Lscala/math/Ordering;


public java.lang.Object min(scala.math.Ordering);
  Code:
   Stack=2, Locals=2, Args_size=2
   0:	aload_0
   1:	aload_1
   2:	invokestatic	#529; //Method scala/collection/TraversableLike$class.min:(Lscala/collection/TraversableLike;Lscala/math/Ordering;)Ljava/lang/Object;
   5:	areturn
  LineNumberTable: 
   line 28: 0

  LocalVariableTable: 
   Start  Length  Slot  Name   Signature
   0      6      0    this       Lscala/collection/mutable/ArrayBuffer;
   0      6      1    cmp       Lscala/math/Ordering;


public java.lang.Object product(scala.math.Numeric);
  Code:
   Stack=2, Locals=2, Args_size=2
   0:	aload_0
   1:	aload_1
   2:	invokestatic	#534; //Method scala/collection/TraversableLike$class.product:(Lscala/collection/TraversableLike;Lscala/math/Numeric;)Ljava/lang/Object;
   5:	areturn
  LineNumberTable: 
   line 28: 0

  LocalVariableTable: 
   Start  Length  Slot  Name   Signature
   0      6      0    this       Lscala/collection/mutable/ArrayBuffer;
   0      6      1    num       Lscala/math/Numeric;


public java.lang.Object sum(scala.math.Numeric);
  Code:
   Stack=2, Locals=2, Args_size=2
   0:	aload_0
   1:	aload_1
   2:	invokestatic	#539; //Method scala/collection/TraversableLike$class.sum:(Lscala/collection/TraversableLike;Lscala/math/Numeric;)Ljava/lang/Object;
   5:	areturn
  LineNumberTable: 
   line 28: 0

  LocalVariableTable: 
   Start  Length  Slot  Name   Signature
   0      6      0    this       Lscala/collection/mutable/ArrayBuffer;
   0      6      1    num       Lscala/math/Numeric;


public scala.Option reduceRightOption(scala.Function2);
  Code:
   Stack=2, Locals=2, Args_size=2
   0:	aload_0
   1:	aload_1
   2:	invokestatic	#544; //Method scala/collection/TraversableLike$class.reduceRightOption:(Lscala/collection/TraversableLike;Lscala/Function2;)Lscala/Option;
   5:	areturn
  LineNumberTable: 
   line 28: 0

  LocalVariableTable: 
   Start  Length  Slot  Name   Signature
   0      6      0    this       Lscala/collection/mutable/ArrayBuffer;
   0      6      1    op       Lscala/Function2;


public scala.Option reduceLeftOption(scala.Function2);
  Code:
   Stack=2, Locals=2, Args_size=2
   0:	aload_0
   1:	aload_1
   2:	invokestatic	#549; //Method scala/collection/TraversableLike$class.reduceLeftOption:(Lscala/collection/TraversableLike;Lscala/Function2;)Lscala/Option;
   5:	areturn
  LineNumberTable: 
   line 28: 0

  LocalVariableTable: 
   Start  Length  Slot  Name   Signature
   0      6      0    this       Lscala/collection/mutable/ArrayBuffer;
   0      6      1    op       Lscala/Function2;


public java.lang.Object $colon$bslash(java.lang.Object, scala.Function2);
  Code:
   Stack=3, Locals=3, Args_size=3
   0:	aload_0
   1:	aload_1
   2:	aload_2
   3:	invokestatic	#554; //Method scala/collection/TraversableLike$class.$colon$bslash:(Lscala/collection/TraversableLike;Ljava/lang/Object;Lscala/Function2;)Ljava/lang/Object;
   6:	areturn
  LineNumberTable: 
   line 28: 0

  LocalVariableTable: 
   Start  Length  Slot  Name   Signature
   0      7      0    this       Lscala/collection/mutable/ArrayBuffer;
   0      7      1    z       Ljava/lang/Object;
   0      7      2    op       Lscala/Function2;


public java.lang.Object $div$colon(java.lang.Object, scala.Function2);
  Code:
   Stack=3, Locals=3, Args_size=3
   0:	aload_0
   1:	aload_1
   2:	aload_2
   3:	invokestatic	#558; //Method scala/collection/TraversableLike$class.$div$colon:(Lscala/collection/TraversableLike;Ljava/lang/Object;Lscala/Function2;)Ljava/lang/Object;
   6:	areturn
  LineNumberTable: 
   line 28: 0

  LocalVariableTable: 
   Start  Length  Slot  Name   Signature
   0      7      0    this       Lscala/collection/mutable/ArrayBuffer;
   0      7      1    z       Ljava/lang/Object;
   0      7      2    op       Lscala/Function2;


public int count(scala.Function1);
  Code:
   Stack=2, Locals=2, Args_size=2
   0:	aload_0
   1:	aload_1
   2:	invokestatic	#562; //Method scala/collection/TraversableLike$class.count:(Lscala/collection/TraversableLike;Lscala/Function1;)I
   5:	ireturn
  LineNumberTable: 
   line 28: 0

  LocalVariableTable: 
   Start  Length  Slot  Name   Signature
   0      6      0    this       Lscala/collection/mutable/ArrayBuffer;
   0      6      1    p       Lscala/Function1;


public scala.collection.Map groupBy(scala.Function1);
  Code:
   Stack=2, Locals=2, Args_size=2
   0:	aload_0
   1:	aload_1
   2:	invokestatic	#567; //Method scala/collection/TraversableLike$class.groupBy:(Lscala/collection/TraversableLike;Lscala/Function1;)Lscala/collection/Map;
   5:	areturn
  LineNumberTable: 
   line 28: 0

  LocalVariableTable: 
   Start  Length  Slot  Name   Signature
   0      6      0    this       Lscala/collection/mutable/ArrayBuffer;
   0      6      1    f       Lscala/Function1;


public scala.Tuple2 partition(scala.Function1);
  Code:
   Stack=2, Locals=2, Args_size=2
   0:	aload_0
   1:	aload_1
   2:	invokestatic	#573; //Method scala/collection/TraversableLike$class.partition:(Lscala/collection/TraversableLike;Lscala/Function1;)Lscala/Tuple2;
   5:	areturn
  LineNumberTable: 
   line 28: 0

  LocalVariableTable: 
   Start  Length  Slot  Name   Signature
   0      6      0    this       Lscala/collection/mutable/ArrayBuffer;
   0      6      1    p       Lscala/Function1;


public java.lang.Object partialMap(scala.PartialFunction, scala.collection.generic.CanBuildFrom);
  Code:
   Stack=3, Locals=3, Args_size=3
   0:	aload_0
   1:	aload_1
   2:	aload_2
   3:	invokestatic	#578; //Method scala/collection/TraversableLike$class.partialMap:(Lscala/collection/TraversableLike;Lscala/PartialFunction;Lscala/collection/generic/CanBuildFrom;)Ljava/lang/Object;
   6:	areturn
  LineNumberTable: 
   line 28: 0

  LocalVariableTable: 
   Start  Length  Slot  Name   Signature
   0      7      0    this       Lscala/collection/mutable/ArrayBuffer;
   0      7      1    pf       Lscala/PartialFunction;
   0      7      2    bf       Lscala/collection/generic/CanBuildFrom;


public java.lang.Object filterNot(scala.Function1);
  Code:
   Stack=2, Locals=2, Args_size=2
   0:	aload_0
   1:	aload_1
   2:	invokestatic	#587; //Method scala/collection/TraversableLike$class.filterNot:(Lscala/collection/TraversableLike;Lscala/Function1;)Ljava/lang/Object;
   5:	areturn
  LineNumberTable: 
   line 28: 0

  LocalVariableTable: 
   Start  Length  Slot  Name   Signature
   0      6      0    this       Lscala/collection/mutable/ArrayBuffer;
   0      6      1    p       Lscala/Function1;


public java.lang.Object filter(scala.Function1);
  Code:
   Stack=2, Locals=2, Args_size=2
   0:	aload_0
   1:	aload_1
   2:	invokestatic	#590; //Method scala/collection/TraversableLike$class.filter:(Lscala/collection/TraversableLike;Lscala/Function1;)Ljava/lang/Object;
   5:	areturn
  LineNumberTable: 
   line 28: 0

  LocalVariableTable: 
   Start  Length  Slot  Name   Signature
   0      6      0    this       Lscala/collection/mutable/ArrayBuffer;
   0      6      1    p       Lscala/Function1;


public java.lang.Object flatMap(scala.Function1, scala.collection.generic.CanBuildFrom);
  Code:
   Stack=3, Locals=3, Args_size=3
   0:	aload_0
   1:	aload_1
   2:	aload_2
   3:	invokestatic	#595; //Method scala/collection/TraversableLike$class.flatMap:(Lscala/collection/TraversableLike;Lscala/Function1;Lscala/collection/generic/CanBuildFrom;)Ljava/lang/Object;
   6:	areturn
  LineNumberTable: 
   line 28: 0

  LocalVariableTable: 
   Start  Length  Slot  Name   Signature
   0      7      0    this       Lscala/collection/mutable/ArrayBuffer;
   0      7      1    f       Lscala/Function1;
   0      7      2    bf       Lscala/collection/generic/CanBuildFrom;


public java.lang.Object map(scala.Function1, scala.collection.generic.CanBuildFrom);
  Code:
   Stack=3, Locals=3, Args_size=3
   0:	aload_0
   1:	aload_1
   2:	aload_2
   3:	invokestatic	#598; //Method scala/collection/TraversableLike$class.map:(Lscala/collection/TraversableLike;Lscala/Function1;Lscala/collection/generic/CanBuildFrom;)Ljava/lang/Object;
   6:	areturn
  LineNumberTable: 
   line 28: 0

  LocalVariableTable: 
   Start  Length  Slot  Name   Signature
   0      7      0    this       Lscala/collection/mutable/ArrayBuffer;
   0      7      1    f       Lscala/Function1;
   0      7      2    bf       Lscala/collection/generic/CanBuildFrom;


public java.lang.Object $plus$plus(scala.collection.Iterator, scala.collection.generic.CanBuildFrom);
  Code:
   Stack=3, Locals=3, Args_size=3
   0:	aload_0
   1:	aload_1
   2:	aload_2
   3:	invokestatic	#602; //Method scala/collection/TraversableLike$class.$plus$plus:(Lscala/collection/TraversableLike;Lscala/collection/Iterator;Lscala/collection/generic/CanBuildFrom;)Ljava/lang/Object;
   6:	areturn
  LineNumberTable: 
   line 28: 0

  LocalVariableTable: 
   Start  Length  Slot  Name   Signature
   0      7      0    this       Lscala/collection/mutable/ArrayBuffer;
   0      7      1    that       Lscala/collection/Iterator;
   0      7      2    bf       Lscala/collection/generic/CanBuildFrom;


public java.lang.Object $plus$plus(scala.collection.Traversable, scala.collection.generic.CanBuildFrom);
  Code:
   Stack=3, Locals=3, Args_size=3
   0:	aload_0
   1:	aload_1
   2:	aload_2
   3:	invokestatic	#607; //Method scala/collection/TraversableLike$class.$plus$plus:(Lscala/collection/TraversableLike;Lscala/collection/Traversable;Lscala/collection/generic/CanBuildFrom;)Ljava/lang/Object;
   6:	areturn
  LineNumberTable: 
   line 28: 0

  LocalVariableTable: 
   Start  Length  Slot  Name   Signature
   0      7      0    this       Lscala/collection/mutable/ArrayBuffer;
   0      7      1    that       Lscala/collection/Traversable;
   0      7      2    bf       Lscala/collection/generic/CanBuildFrom;


public boolean hasDefiniteSize();
  Code:
   Stack=1, Locals=1, Args_size=1
   0:	aload_0
   1:	invokestatic	#612; //Method scala/collection/TraversableLike$class.hasDefiniteSize:(Lscala/collection/TraversableLike;)Z
   4:	ireturn
  LineNumberTable: 
   line 28: 0


public boolean nonEmpty();
  Code:
   Stack=1, Locals=1, Args_size=1
   0:	aload_0
   1:	invokestatic	#615; //Method scala/collection/TraversableLike$class.nonEmpty:(Lscala/collection/TraversableLike;)Z
   4:	ireturn
  LineNumberTable: 
   line 28: 0


public java.lang.Object repr();
  Code:
   Stack=1, Locals=1, Args_size=1
   0:	aload_0
   1:	invokestatic	#618; //Method scala/collection/TraversableLike$class.repr:(Lscala/collection/TraversableLike;)Ljava/lang/Object;
   4:	areturn
  LineNumberTable: 
   line 28: 0


public scala.collection.Traversable transpose(scala.Function1);
  Code:
   Stack=2, Locals=2, Args_size=2
   0:	aload_0
   1:	aload_1
   2:	invokestatic	#623; //Method scala/collection/generic/GenericTraversableTemplate$class.transpose:(Lscala/collection/generic/GenericTraversableTemplate;Lscala/Function1;)Lscala/collection/Traversable;
   5:	areturn
  LineNumberTable: 
   line 28: 0

  LocalVariableTable: 
   Start  Length  Slot  Name   Signature
   0      6      0    this       Lscala/collection/mutable/ArrayBuffer;
   0      6      1    asTraversable       Lscala/Function1;


public scala.collection.Traversable flatten(scala.Function1);
  Code:
   Stack=2, Locals=2, Args_size=2
   0:	aload_0
   1:	aload_1
   2:	invokestatic	#627; //Method scala/collection/generic/GenericTraversableTemplate$class.flatten:(Lscala/collection/generic/GenericTraversableTemplate;Lscala/Function1;)Lscala/collection/Traversable;
   5:	areturn
  LineNumberTable: 
   line 28: 0

  LocalVariableTable: 
   Start  Length  Slot  Name   Signature
   0      6      0    this       Lscala/collection/mutable/ArrayBuffer;
   0      6      1    asTraversable       Lscala/Function1;


public scala.Tuple2 unzip(scala.Function1);
  Code:
   Stack=2, Locals=2, Args_size=2
   0:	aload_0
   1:	aload_1
   2:	invokestatic	#631; //Method scala/collection/generic/GenericTraversableTemplate$class.unzip:(Lscala/collection/generic/GenericTraversableTemplate;Lscala/Function1;)Lscala/Tuple2;
   5:	areturn
  LineNumberTable: 
   line 28: 0

  LocalVariableTable: 
   Start  Length  Slot  Name   Signature
   0      6      0    this       Lscala/collection/mutable/ArrayBuffer;
   0      6      1    asPair       Lscala/Function1;


public scala.collection.mutable.Builder genericBuilder();
  Code:
   Stack=1, Locals=1, Args_size=1
   0:	aload_0
   1:	invokestatic	#637; //Method scala/collection/generic/GenericTraversableTemplate$class.genericBuilder:(Lscala/collection/generic/GenericTraversableTemplate;)Lscala/collection/mutable/Builder;
   4:	areturn
  LineNumberTable: 
   line 28: 0


public scala.collection.mutable.Builder newBuilder();
  Code:
   Stack=1, Locals=1, Args_size=1
   0:	aload_0
   1:	invokestatic	#640; //Method scala/collection/generic/GenericTraversableTemplate$class.newBuilder:(Lscala/collection/generic/GenericTraversableTemplate;)Lscala/collection/mutable/Builder;
   4:	areturn
  LineNumberTable: 
   line 28: 0


public scala.Option firstOption();
  Code:
   Stack=1, Locals=1, Args_size=1
   0:	aload_0
   1:	invokestatic	#644; //Method scala/collection/IterableLike$class.firstOption:(Lscala/collection/IterableLike;)Lscala/Option;
   4:	areturn
  LineNumberTable: 
   line 28: 0

  Deprecated: true

public java.lang.Object first();
  Code:
   Stack=1, Locals=1, Args_size=1
   0:	aload_0
   1:	invokestatic	#649; //Method scala/collection/IterableLike$class.first:(Lscala/collection/IterableLike;)Ljava/lang/Object;
   4:	areturn
  LineNumberTable: 
   line 28: 0

  Deprecated: true

public boolean canEqual(java.lang.Object);
  Code:
   Stack=2, Locals=2, Args_size=2
   0:	aload_0
   1:	aload_1
   2:	invokestatic	#653; //Method scala/collection/IterableLike$class.canEqual:(Lscala/collection/IterableLike;Ljava/lang/Object;)Z
   5:	ireturn
  LineNumberTable: 
   line 28: 0

  LocalVariableTable: 
   Start  Length  Slot  Name   Signature
   0      6      0    this       Lscala/collection/mutable/ArrayBuffer;
   0      6      1    that       Ljava/lang/Object;


public scala.collection.immutable.Stream toStream();
  Code:
   Stack=1, Locals=1, Args_size=1
   0:	aload_0
   1:	invokestatic	#658; //Method scala/collection/IterableLike$class.toStream:(Lscala/collection/IterableLike;)Lscala/collection/immutable/Stream;
   4:	areturn
  LineNumberTable: 
   line 28: 0


public java.lang.Object zipAll(scala.collection.Iterable, java.lang.Object, java.lang.Object, scala.collection.generic.CanBuildFrom);
  Code:
   Stack=5, Locals=5, Args_size=5
   0:	aload_0
   1:	aload_1
   2:	aload_2
   3:	aload_3
   4:	aload	4
   6:	invokestatic	#663; //Method scala/collection/IterableLike$class.zipAll:(Lscala/collection/IterableLike;Lscala/collection/Iterable;Ljava/lang/Object;Ljava/lang/Object;Lscala/collection/generic/CanBuildFrom;)Ljava/lang/Object;
   9:	areturn
  LineNumberTable: 
   line 28: 0

  LocalVariableTable: 
   Start  Length  Slot  Name   Signature
   0      10      0    this       Lscala/collection/mutable/ArrayBuffer;
   0      10      1    that       Lscala/collection/Iterable;
   0      10      2    thisElem       Ljava/lang/Object;
   0      10      3    thatElem       Ljava/lang/Object;
   0      10      4    bf       Lscala/collection/generic/CanBuildFrom;


public scala.collection.Iterable toIterable();
  Code:
   Stack=1, Locals=1, Args_size=1
   0:	aload_0
   1:	invokestatic	#670; //Method scala/collection/IterableLike$class.toIterable:(Lscala/collection/IterableLike;)Lscala/collection/Iterable;
   4:	areturn
  LineNumberTable: 
   line 28: 0


public scala.collection.Iterator elements();
  Code:
   Stack=1, Locals=1, Args_size=1
   0:	aload_0
   1:	invokestatic	#675; //Method scala/collection/IterableLike$class.elements:(Lscala/collection/IterableLike;)Lscala/collection/Iterator;
   4:	areturn
  LineNumberTable: 
   line 28: 0

  Deprecated: true

public scala.Function1 compose(scala.Function1);
  Code:
   Stack=2, Locals=2, Args_size=2
   0:	aload_0
   1:	aload_1
   2:	invokestatic	#679; //Method scala/Function1$class.compose:(Lscala/Function1;Lscala/Function1;)Lscala/Function1;
   5:	areturn
  LineNumberTable: 
   line 28: 0

  LocalVariableTable: 
   Start  Length  Slot  Name   Signature
   0      6      0    this       Lscala/collection/mutable/ArrayBuffer;
   0      6      1    g       Lscala/Function1;


public scala.Function1 lift();
  Code:
   Stack=1, Locals=1, Args_size=1
   0:	aload_0
   1:	invokestatic	#684; //Method scala/PartialFunction$class.lift:(Lscala/PartialFunction;)Lscala/Function1;
   4:	areturn
  LineNumberTable: 
   line 28: 0


public scala.PartialFunction andThen(scala.Function1);
  Code:
   Stack=2, Locals=2, Args_size=2
   0:	aload_0
   1:	aload_1
   2:	invokestatic	#687; //Method scala/PartialFunction$class.andThen:(Lscala/PartialFunction;Lscala/Function1;)Lscala/PartialFunction;
   5:	areturn
  LineNumberTable: 
   line 28: 0

  LocalVariableTable: 
   Start  Length  Slot  Name   Signature
   0      6      0    this       Lscala/collection/mutable/ArrayBuffer;
   0      6      1    k       Lscala/Function1;


public scala.PartialFunction orElse(scala.PartialFunction);
  Code:
   Stack=2, Locals=2, Args_size=2
   0:	aload_0
   1:	aload_1
   2:	invokestatic	#693; //Method scala/PartialFunction$class.orElse:(Lscala/PartialFunction;Lscala/PartialFunction;)Lscala/PartialFunction;
   5:	areturn
  LineNumberTable: 
   line 28: 0

  LocalVariableTable: 
   Start  Length  Slot  Name   Signature
   0      6      0    this       Lscala/collection/mutable/ArrayBuffer;
   0      6      1    that       Lscala/PartialFunction;


public java.lang.Object projection();
  Code:
   Stack=1, Locals=1, Args_size=1
   0:	aload_0
   1:	invokestatic	#697; //Method scala/collection/SeqLike$class.projection:(Lscala/collection/SeqLike;)Ljava/lang/Object;
   4:	areturn
  LineNumberTable: 
   line 28: 0

  Deprecated: true

public boolean equalsWith(scala.collection.Seq, scala.Function2);
  Code:
   Stack=3, Locals=3, Args_size=3
   0:	aload_0
   1:	aload_1
   2:	aload_2
   3:	invokestatic	#702; //Method scala/collection/SeqLike$class.equalsWith:(Lscala/collection/SeqLike;Lscala/collection/Seq;Lscala/Function2;)Z
   6:	ireturn
  LineNumberTable: 
   line 28: 0

  LocalVariableTable: 
   Start  Length  Slot  Name   Signature
   0      7      0    this       Lscala/collection/mutable/ArrayBuffer;
   0      7      1    that       Lscala/collection/Seq;
   0      7      2    f       Lscala/Function2;

  Deprecated: true

public int findLastIndexOf(scala.Function1);
  Code:
   Stack=2, Locals=2, Args_size=2
   0:	aload_0
   1:	aload_1
   2:	invokestatic	#706; //Method scala/collection/SeqLike$class.findLastIndexOf:(Lscala/collection/SeqLike;Lscala/Function1;)I
   5:	ireturn
  LineNumberTable: 
   line 28: 0

  LocalVariableTable: 
   Start  Length  Slot  Name   Signature
   0      6      0    this       Lscala/collection/mutable/ArrayBuffer;
   0      6      1    p       Lscala/Function1;


public java.lang.String toString();
  Code:
   Stack=1, Locals=1, Args_size=1
   0:	aload_0
   1:	invokestatic	#709; //Method scala/collection/SeqLike$class.toString:(Lscala/collection/SeqLike;)Ljava/lang/String;
   4:	areturn
  LineNumberTable: 
   line 28: 0


public boolean equals(java.lang.Object);
  Code:
   Stack=2, Locals=2, Args_size=2
   0:	aload_0
   1:	aload_1
   2:	invokestatic	#713; //Method scala/collection/SeqLike$class.equals:(Lscala/collection/SeqLike;Ljava/lang/Object;)Z
   5:	ireturn
  LineNumberTable: 
   line 28: 0

  LocalVariableTable: 
   Start  Length  Slot  Name   Signature
   0      6      0    this       Lscala/collection/mutable/ArrayBuffer;
   0      6      1    that       Ljava/lang/Object;


public int hashCode();
  Code:
   Stack=1, Locals=1, Args_size=1
   0:	aload_0
   1:	invokestatic	#717; //Method scala/collection/SeqLike$class.hashCode:(Lscala/collection/SeqLike;)I
   4:	ireturn
  LineNumberTable: 
   line 28: 0


public scala.collection.immutable.Range indices();
  Code:
   Stack=1, Locals=1, Args_size=1
   0:	aload_0
   1:	invokestatic	#722; //Method scala/collection/SeqLike$class.indices:(Lscala/collection/SeqLike;)Lscala/collection/immutable/Range;
   4:	areturn
  LineNumberTable: 
   line 28: 0


public scala.collection.Seq toSeq();
  Code:
   Stack=1, Locals=1, Args_size=1
   0:	aload_0
   1:	invokestatic	#726; //Method scala/collection/SeqLike$class.toSeq:(Lscala/collection/SeqLike;)Lscala/collection/Seq;
   4:	areturn
  LineNumberTable: 
   line 28: 0


public java.lang.Object sortBy(scala.Function1, scala.math.Ordering);
  Code:
   Stack=3, Locals=3, Args_size=3
   0:	aload_0
   1:	aload_1
   2:	aload_2
   3:	invokestatic	#731; //Method scala/collection/SeqLike$class.sortBy:(Lscala/collection/SeqLike;Lscala/Function1;Lscala/math/Ordering;)Ljava/lang/Object;
   6:	areturn
  LineNumberTable: 
   line 28: 0

  LocalVariableTable: 
   Start  Length  Slot  Name   Signature
   0      7      0    this       Lscala/collection/mutable/ArrayBuffer;
   0      7      1    f       Lscala/Function1;
   0      7      2    ord       Lscala/math/Ordering;


public java.lang.Object sortWith(scala.math.Ordering);
  Code:
   Stack=2, Locals=2, Args_size=2
   0:	aload_0
   1:	aload_1
   2:	invokestatic	#736; //Method scala/collection/SeqLike$class.sortWith:(Lscala/collection/SeqLike;Lscala/math/Ordering;)Ljava/lang/Object;
   5:	areturn
  LineNumberTable: 
   line 28: 0

  LocalVariableTable: 
   Start  Length  Slot  Name   Signature
   0      6      0    this       Lscala/collection/mutable/ArrayBuffer;
   0      6      1    ord       Lscala/math/Ordering;


public java.lang.Object sortWith(scala.Function2);
  Code:
   Stack=2, Locals=2, Args_size=2
   0:	aload_0
   1:	aload_1
   2:	invokestatic	#740; //Method scala/collection/SeqLike$class.sortWith:(Lscala/collection/SeqLike;Lscala/Function2;)Ljava/lang/Object;
   5:	areturn
  LineNumberTable: 
   line 28: 0

  LocalVariableTable: 
   Start  Length  Slot  Name   Signature
   0      6      0    this       Lscala/collection/mutable/ArrayBuffer;
   0      6      1    lt       Lscala/Function2;


public boolean corresponds(scala.collection.Seq, scala.Function2);
  Code:
   Stack=3, Locals=3, Args_size=3
   0:	aload_0
   1:	aload_1
   2:	aload_2
   3:	invokestatic	#744; //Method scala/collection/SeqLike$class.corresponds:(Lscala/collection/SeqLike;Lscala/collection/Seq;Lscala/Function2;)Z
   6:	ireturn
  LineNumberTable: 
   line 28: 0

  LocalVariableTable: 
   Start  Length  Slot  Name   Signature
   0      7      0    this       Lscala/collection/mutable/ArrayBuffer;
   0      7      1    that       Lscala/collection/Seq;
   0      7      2    p       Lscala/Function2;


public java.lang.Object padTo(int, java.lang.Object, scala.collection.generic.CanBuildFrom);
  Code:
   Stack=4, Locals=4, Args_size=4
   0:	aload_0
   1:	iload_1
   2:	aload_2
   3:	aload_3
   4:	invokestatic	#749; //Method scala/collection/SeqLike$class.padTo:(Lscala/collection/SeqLike;ILjava/lang/Object;Lscala/collection/generic/CanBuildFrom;)Ljava/lang/Object;
   7:	areturn
  LineNumberTable: 
   line 28: 0

  LocalVariableTable: 
   Start  Length  Slot  Name   Signature
   0      8      0    this       Lscala/collection/mutable/ArrayBuffer;
   0      8      1    len       I
   0      8      2    elem       Ljava/lang/Object;
   0      8      3    bf       Lscala/collection/generic/CanBuildFrom;


public java.lang.Object $colon$plus(java.lang.Object, scala.collection.generic.CanBuildFrom);
  Code:
   Stack=3, Locals=3, Args_size=3
   0:	aload_0
   1:	aload_1
   2:	aload_2
   3:	invokestatic	#754; //Method scala/collection/SeqLike$class.$colon$plus:(Lscala/collection/SeqLike;Ljava/lang/Object;Lscala/collection/generic/CanBuildFrom;)Ljava/lang/Object;
   6:	areturn
  LineNumberTable: 
   line 28: 0

  LocalVariableTable: 
   Start  Length  Slot  Name   Signature
   0      7      0    this       Lscala/collection/mutable/ArrayBuffer;
   0      7      1    elem       Ljava/lang/Object;
   0      7      2    bf       Lscala/collection/generic/CanBuildFrom;


public java.lang.Object $plus$colon(java.lang.Object, scala.collection.generic.CanBuildFrom);
  Code:
   Stack=3, Locals=3, Args_size=3
   0:	aload_0
   1:	aload_1
   2:	aload_2
   3:	invokestatic	#757; //Method scala/collection/SeqLike$class.$plus$colon:(Lscala/collection/SeqLike;Ljava/lang/Object;Lscala/collection/generic/CanBuildFrom;)Ljava/lang/Object;
   6:	areturn
  LineNumberTable: 
   line 28: 0

  LocalVariableTable: 
   Start  Length  Slot  Name   Signature
   0      7      0    this       Lscala/collection/mutable/ArrayBuffer;
   0      7      1    elem       Ljava/lang/Object;
   0      7      2    bf       Lscala/collection/generic/CanBuildFrom;


public java.lang.Object updated(int, java.lang.Object, scala.collection.generic.CanBuildFrom);
  Code:
   Stack=4, Locals=4, Args_size=4
   0:	aload_0
   1:	iload_1
   2:	aload_2
   3:	aload_3
   4:	invokestatic	#760; //Method scala/collection/SeqLike$class.updated:(Lscala/collection/SeqLike;ILjava/lang/Object;Lscala/collection/generic/CanBuildFrom;)Ljava/lang/Object;
   7:	areturn
  LineNumberTable: 
   line 28: 0

  LocalVariableTable: 
   Start  Length  Slot  Name   Signature
   0      8      0    this       Lscala/collection/mutable/ArrayBuffer;
   0      8      1    index       I
   0      8      2    elem       Ljava/lang/Object;
   0      8      3    bf       Lscala/collection/generic/CanBuildFrom;


public java.lang.Object patch(int, scala.collection.Seq, int, scala.collection.generic.CanBuildFrom);
  Code:
   Stack=5, Locals=5, Args_size=5
   0:	aload_0
   1:	iload_1
   2:	aload_2
   3:	iload_3
   4:	aload	4
   6:	invokestatic	#766; //Method scala/collection/SeqLike$class.patch:(Lscala/collection/SeqLike;ILscala/collection/Seq;ILscala/collection/generic/CanBuildFrom;)Ljava/lang/Object;
   9:	areturn
  LineNumberTable: 
   line 28: 0

  LocalVariableTable: 
   Start  Length  Slot  Name   Signature
   0      10      0    this       Lscala/collection/mutable/ArrayBuffer;
   0      10      1    from       I
   0      10      2    patch       Lscala/collection/Seq;
   0      10      3    replaced       I
   0      10      4    bf       Lscala/collection/generic/CanBuildFrom;


public java.lang.Object removeDuplicates();
  Code:
   Stack=1, Locals=1, Args_size=1
   0:	aload_0
   1:	invokestatic	#770; //Method scala/collection/SeqLike$class.removeDuplicates:(Lscala/collection/SeqLike;)Ljava/lang/Object;
   4:	areturn
  LineNumberTable: 
   line 28: 0


public java.lang.Object intersect(scala.collection.Seq);
  Code:
   Stack=2, Locals=2, Args_size=2
   0:	aload_0
   1:	aload_1
   2:	invokestatic	#775; //Method scala/collection/SeqLike$class.intersect:(Lscala/collection/SeqLike;Lscala/collection/Seq;)Ljava/lang/Object;
   5:	areturn
  LineNumberTable: 
   line 28: 0

  LocalVariableTable: 
   Start  Length  Slot  Name   Signature
   0      6      0    this       Lscala/collection/mutable/ArrayBuffer;
   0      6      1    that       Lscala/collection/Seq;


public java.lang.Object diff(scala.collection.Seq);
  Code:
   Stack=2, Locals=2, Args_size=2
   0:	aload_0
   1:	aload_1
   2:	invokestatic	#778; //Method scala/collection/SeqLike$class.diff:(Lscala/collection/SeqLike;Lscala/collection/Seq;)Ljava/lang/Object;
   5:	areturn
  LineNumberTable: 
   line 28: 0

  LocalVariableTable: 
   Start  Length  Slot  Name   Signature
   0      6      0    this       Lscala/collection/mutable/ArrayBuffer;
   0      6      1    that       Lscala/collection/Seq;


public java.lang.Object union(scala.collection.Seq, scala.collection.generic.CanBuildFrom);
  Code:
   Stack=3, Locals=3, Args_size=3
   0:	aload_0
   1:	aload_1
   2:	aload_2
   3:	invokestatic	#783; //Method scala/collection/SeqLike$class.union:(Lscala/collection/SeqLike;Lscala/collection/Seq;Lscala/collection/generic/CanBuildFrom;)Ljava/lang/Object;
   6:	areturn
  LineNumberTable: 
   line 28: 0

  LocalVariableTable: 
   Start  Length  Slot  Name   Signature
   0      7      0    this       Lscala/collection/mutable/ArrayBuffer;
   0      7      1    that       Lscala/collection/Seq;
   0      7      2    bf       Lscala/collection/generic/CanBuildFrom;


public boolean contains(java.lang.Object);
  Code:
   Stack=2, Locals=2, Args_size=2
   0:	aload_0
   1:	aload_1
   2:	invokestatic	#786; //Method scala/collection/SeqLike$class.contains:(Lscala/collection/SeqLike;Ljava/lang/Object;)Z
   5:	ireturn
  LineNumberTable: 
   line 28: 0

  LocalVariableTable: 
   Start  Length  Slot  Name   Signature
   0      6      0    this       Lscala/collection/mutable/ArrayBuffer;
   0      6      1    elem       Ljava/lang/Object;


public boolean containsSlice(scala.collection.Seq);
  Code:
   Stack=2, Locals=2, Args_size=2
   0:	aload_0
   1:	aload_1
   2:	invokestatic	#791; //Method scala/collection/SeqLike$class.containsSlice:(Lscala/collection/SeqLike;Lscala/collection/Seq;)Z
   5:	ireturn
  LineNumberTable: 
   line 28: 0

  LocalVariableTable: 
   Start  Length  Slot  Name   Signature
   0      6      0    this       Lscala/collection/mutable/ArrayBuffer;
   0      6      1    that       Lscala/collection/Seq;


public int lastIndexOfSlice(scala.collection.Seq, int);
  Code:
   Stack=3, Locals=3, Args_size=3
   0:	aload_0
   1:	aload_1
   2:	iload_2
   3:	invokestatic	#796; //Method scala/collection/SeqLike$class.lastIndexOfSlice:(Lscala/collection/SeqLike;Lscala/collection/Seq;I)I
   6:	ireturn
  LineNumberTable: 
   line 28: 0

  LocalVariableTable: 
   Start  Length  Slot  Name   Signature
   0      7      0    this       Lscala/collection/mutable/ArrayBuffer;
   0      7      1    that       Lscala/collection/Seq;
   0      7      2    end       I


public int lastIndexOfSlice(scala.collection.Seq);
  Code:
   Stack=2, Locals=2, Args_size=2
   0:	aload_0
   1:	aload_1
   2:	invokestatic	#800; //Method scala/collection/SeqLike$class.lastIndexOfSlice:(Lscala/collection/SeqLike;Lscala/collection/Seq;)I
   5:	ireturn
  LineNumberTable: 
   line 28: 0

  LocalVariableTable: 
   Start  Length  Slot  Name   Signature
   0      6      0    this       Lscala/collection/mutable/ArrayBuffer;
   0      6      1    that       Lscala/collection/Seq;


public int indexOfSlice(scala.collection.Seq, int);
  Code:
   Stack=3, Locals=3, Args_size=3
   0:	aload_0
   1:	aload_1
   2:	iload_2
   3:	invokestatic	#803; //Method scala/collection/SeqLike$class.indexOfSlice:(Lscala/collection/SeqLike;Lscala/collection/Seq;I)I
   6:	ireturn
  LineNumberTable: 
   line 28: 0

  LocalVariableTable: 
   Start  Length  Slot  Name   Signature
   0      7      0    this       Lscala/collection/mutable/ArrayBuffer;
   0      7      1    that       Lscala/collection/Seq;
   0      7      2    from       I


public int indexOfSlice(scala.collection.Seq);
  Code:
   Stack=2, Locals=2, Args_size=2
   0:	aload_0
   1:	aload_1
   2:	invokestatic	#805; //Method scala/collection/SeqLike$class.indexOfSlice:(Lscala/collection/SeqLike;Lscala/collection/Seq;)I
   5:	ireturn
  LineNumberTable: 
   line 28: 0

  LocalVariableTable: 
   Start  Length  Slot  Name   Signature
   0      6      0    this       Lscala/collection/mutable/ArrayBuffer;
   0      6      1    that       Lscala/collection/Seq;


public boolean startsWith(scala.collection.Seq);
  Code:
   Stack=2, Locals=2, Args_size=2
   0:	aload_0
   1:	aload_1
   2:	invokestatic	#808; //Method scala/collection/SeqLike$class.startsWith:(Lscala/collection/SeqLike;Lscala/collection/Seq;)Z
   5:	ireturn
  LineNumberTable: 
   line 28: 0

  LocalVariableTable: 
   Start  Length  Slot  Name   Signature
   0      6      0    this       Lscala/collection/mutable/ArrayBuffer;
   0      6      1    that       Lscala/collection/Seq;


public scala.collection.Iterator reversedElements();
  Code:
   Stack=1, Locals=1, Args_size=1
   0:	aload_0
   1:	invokestatic	#812; //Method scala/collection/SeqLike$class.reversedElements:(Lscala/collection/SeqLike;)Lscala/collection/Iterator;
   4:	areturn
  LineNumberTable: 
   line 28: 0

  Deprecated: true

public java.lang.Object reverseMap(scala.Function1, scala.collection.generic.CanBuildFrom);
  Code:
   Stack=3, Locals=3, Args_size=3
   0:	aload_0
   1:	aload_1
   2:	aload_2
   3:	invokestatic	#816; //Method scala/collection/SeqLike$class.reverseMap:(Lscala/collection/SeqLike;Lscala/Function1;Lscala/collection/generic/CanBuildFrom;)Ljava/lang/Object;
   6:	areturn
  LineNumberTable: 
   line 28: 0

  LocalVariableTable: 
   Start  Length  Slot  Name   Signature
   0      7      0    this       Lscala/collection/mutable/ArrayBuffer;
   0      7      1    f       Lscala/Function1;
   0      7      2    bf       Lscala/collection/generic/CanBuildFrom;


public int lastIndexWhere(scala.Function1);
  Code:
   Stack=2, Locals=2, Args_size=2
   0:	aload_0
   1:	aload_1
   2:	invokestatic	#819; //Method scala/collection/SeqLike$class.lastIndexWhere:(Lscala/collection/SeqLike;Lscala/Function1;)I
   5:	ireturn
  LineNumberTable: 
   line 28: 0

  LocalVariableTable: 
   Start  Length  Slot  Name   Signature
   0      6      0    this       Lscala/collection/mutable/ArrayBuffer;
   0      6      1    p       Lscala/Function1;


public int lastIndexOf(java.lang.Object, int);
  Code:
   Stack=3, Locals=3, Args_size=3
   0:	aload_0
   1:	aload_1
   2:	iload_2
   3:	invokestatic	#824; //Method scala/collection/SeqLike$class.lastIndexOf:(Lscala/collection/SeqLike;Ljava/lang/Object;I)I
   6:	ireturn
  LineNumberTable: 
   line 28: 0

  LocalVariableTable: 
   Start  Length  Slot  Name   Signature
   0      7      0    this       Lscala/collection/mutable/ArrayBuffer;
   0      7      1    elem       Ljava/lang/Object;
   0      7      2    end       I


public int lastIndexOf(java.lang.Object);
  Code:
   Stack=2, Locals=2, Args_size=2
   0:	aload_0
   1:	aload_1
   2:	invokestatic	#827; //Method scala/collection/SeqLike$class.lastIndexOf:(Lscala/collection/SeqLike;Ljava/lang/Object;)I
   5:	ireturn
  LineNumberTable: 
   line 28: 0

  LocalVariableTable: 
   Start  Length  Slot  Name   Signature
   0      6      0    this       Lscala/collection/mutable/ArrayBuffer;
   0      6      1    elem       Ljava/lang/Object;


public int indexOf(java.lang.Object, int);
  Code:
   Stack=3, Locals=3, Args_size=3
   0:	aload_0
   1:	aload_1
   2:	iload_2
   3:	invokestatic	#830; //Method scala/collection/SeqLike$class.indexOf:(Lscala/collection/SeqLike;Ljava/lang/Object;I)I
   6:	ireturn
  LineNumberTable: 
   line 28: 0

  LocalVariableTable: 
   Start  Length  Slot  Name   Signature
   0      7      0    this       Lscala/collection/mutable/ArrayBuffer;
   0      7      1    elem       Ljava/lang/Object;
   0      7      2    from       I


public int indexOf(java.lang.Object);
  Code:
   Stack=2, Locals=2, Args_size=2
   0:	aload_0
   1:	aload_1
   2:	invokestatic	#832; //Method scala/collection/SeqLike$class.indexOf:(Lscala/collection/SeqLike;Ljava/lang/Object;)I
   5:	ireturn
  LineNumberTable: 
   line 28: 0

  LocalVariableTable: 
   Start  Length  Slot  Name   Signature
   0      6      0    this       Lscala/collection/mutable/ArrayBuffer;
   0      6      1    elem       Ljava/lang/Object;


public int findIndexOf(scala.Function1);
  Code:
   Stack=2, Locals=2, Args_size=2
   0:	aload_0
   1:	aload_1
   2:	invokestatic	#835; //Method scala/collection/SeqLike$class.findIndexOf:(Lscala/collection/SeqLike;Lscala/Function1;)I
   5:	ireturn
  LineNumberTable: 
   line 28: 0

  LocalVariableTable: 
   Start  Length  Slot  Name   Signature
   0      6      0    this       Lscala/collection/mutable/ArrayBuffer;
   0      6      1    p       Lscala/Function1;


public int indexWhere(scala.Function1);
  Code:
   Stack=2, Locals=2, Args_size=2
   0:	aload_0
   1:	aload_1
   2:	invokestatic	#838; //Method scala/collection/SeqLike$class.indexWhere:(Lscala/collection/SeqLike;Lscala/Function1;)I
   5:	ireturn
  LineNumberTable: 
   line 28: 0

  LocalVariableTable: 
   Start  Length  Slot  Name   Signature
   0      6      0    this       Lscala/collection/mutable/ArrayBuffer;
   0      6      1    p       Lscala/Function1;


public int prefixLength(scala.Function1);
  Code:
   Stack=2, Locals=2, Args_size=2
   0:	aload_0
   1:	aload_1
   2:	invokestatic	#841; //Method scala/collection/SeqLike$class.prefixLength:(Lscala/collection/SeqLike;Lscala/Function1;)I
   5:	ireturn
  LineNumberTable: 
   line 28: 0

  LocalVariableTable: 
   Start  Length  Slot  Name   Signature
   0      6      0    this       Lscala/collection/mutable/ArrayBuffer;
   0      6      1    p       Lscala/Function1;


public boolean isDefinedAt(int);
  Code:
   Stack=2, Locals=2, Args_size=2
   0:	aload_0
   1:	iload_1
   2:	invokestatic	#844; //Method scala/collection/SeqLike$class.isDefinedAt:(Lscala/collection/SeqLike;I)Z
   5:	ireturn
  LineNumberTable: 
   line 28: 0

  LocalVariableTable: 
   Start  Length  Slot  Name   Signature
   0      6      0    this       Lscala/collection/mutable/ArrayBuffer;
   0      6      1    idx       I


public int size();
  Code:
   Stack=1, Locals=1, Args_size=1
   0:	aload_0
   1:	invokestatic	#847; //Method scala/collection/SeqLike$class.size:(Lscala/collection/SeqLike;)I
   4:	ireturn
  LineNumberTable: 
   line 28: 0


public scala.collection.generic.Growable $plus$plus$eq(scala.collection.Iterator);
  Code:
   Stack=2, Locals=2, Args_size=2
   0:	aload_0
   1:	aload_1
   2:	invokestatic	#851; //Method scala/collection/generic/Growable$class.$plus$plus$eq:(Lscala/collection/generic/Growable;Lscala/collection/Iterator;)Lscala/collection/generic/Growable;
   5:	areturn
  LineNumberTable: 
   line 28: 0

  LocalVariableTable: 
   Start  Length  Slot  Name   Signature
   0      6      0    this       Lscala/collection/mutable/ArrayBuffer;
   0      6      1    iter       Lscala/collection/Iterator;


public scala.collection.generic.Growable $plus$eq(java.lang.Object, java.lang.Object, scala.collection.Seq);
  Code:
   Stack=4, Locals=4, Args_size=4
   0:	aload_0
   1:	aload_1
   2:	aload_2
   3:	aload_3
   4:	invokestatic	#855; //Method scala/collection/generic/Growable$class.$plus$eq:(Lscala/collection/generic/Growable;Ljava/lang/Object;Ljava/lang/Object;Lscala/collection/Seq;)Lscala/collection/generic/Growable;
   7:	areturn
  LineNumberTable: 
   line 28: 0

  LocalVariableTable: 
   Start  Length  Slot  Name   Signature
   0      8      0    this       Lscala/collection/mutable/ArrayBuffer;
   0      8      1    elem1       Ljava/lang/Object;
   0      8      2    elem2       Ljava/lang/Object;
   0      8      3    elems       Lscala/collection/Seq;


public scala.collection.generic.Shrinkable $minus$minus$eq(scala.collection.Traversable);
  Code:
   Stack=2, Locals=2, Args_size=2
   0:	aload_0
   1:	aload_1
   2:	invokestatic	#860; //Method scala/collection/generic/Shrinkable$class.$minus$minus$eq:(Lscala/collection/generic/Shrinkable;Lscala/collection/Traversable;)Lscala/collection/generic/Shrinkable;
   5:	areturn
  LineNumberTable: 
   line 28: 0

  LocalVariableTable: 
   Start  Length  Slot  Name   Signature
   0      6      0    this       Lscala/collection/mutable/ArrayBuffer;
   0      6      1    iter       Lscala/collection/Traversable;


public scala.collection.generic.Shrinkable $minus$minus$eq(scala.collection.Iterator);
  Code:
   Stack=2, Locals=2, Args_size=2
   0:	aload_0
   1:	aload_1
   2:	invokestatic	#864; //Method scala/collection/generic/Shrinkable$class.$minus$minus$eq:(Lscala/collection/generic/Shrinkable;Lscala/collection/Iterator;)Lscala/collection/generic/Shrinkable;
   5:	areturn
  LineNumberTable: 
   line 28: 0

  LocalVariableTable: 
   Start  Length  Slot  Name   Signature
   0      6      0    this       Lscala/collection/mutable/ArrayBuffer;
   0      6      1    iter       Lscala/collection/Iterator;


public scala.collection.generic.Shrinkable $minus$eq(java.lang.Object, java.lang.Object, scala.collection.Seq);
  Code:
   Stack=4, Locals=4, Args_size=4
   0:	aload_0
   1:	aload_1
   2:	aload_2
   3:	aload_3
   4:	invokestatic	#868; //Method scala/collection/generic/Shrinkable$class.$minus$eq:(Lscala/collection/generic/Shrinkable;Ljava/lang/Object;Ljava/lang/Object;Lscala/collection/Seq;)Lscala/collection/generic/Shrinkable;
   7:	areturn
  LineNumberTable: 
   line 28: 0

  LocalVariableTable: 
   Start  Length  Slot  Name   Signature
   0      8      0    this       Lscala/collection/mutable/ArrayBuffer;
   0      8      1    elem1       Ljava/lang/Object;
   0      8      2    elem2       Ljava/lang/Object;
   0      8      3    elems       Lscala/collection/Seq;


public final java.lang.Object scala$collection$mutable$Cloneable$$super$clone();
  Code:
   Stack=1, Locals=1, Args_size=1
   0:	aload_0
   1:	invokespecial	#871; //Method java/lang/Object.clone:()Ljava/lang/Object;
   4:	areturn
  LineNumberTable: 
   line 28: 0


public scala.collection.mutable.BufferLike $minus$minus(scala.collection.Iterator);
  Code:
   Stack=2, Locals=2, Args_size=2
   0:	aload_0
   1:	aload_1
   2:	invokestatic	#874; //Method scala/collection/mutable/BufferLike$class.$minus$minus:(Lscala/collection/mutable/BufferLike;Lscala/collection/Iterator;)Lscala/collection/mutable/BufferLike;
   5:	areturn
  LineNumberTable: 
   line 28: 0

  LocalVariableTable: 
   Start  Length  Slot  Name   Signature
   0      6      0    this       Lscala/collection/mutable/ArrayBuffer;
   0      6      1    iter       Lscala/collection/Iterator;

  Deprecated: true

public final scala.collection.mutable.BufferLike $plus$colon(java.lang.Object);
  Code:
   Stack=2, Locals=2, Args_size=2
   0:	aload_0
   1:	aload_1
   2:	invokestatic	#877; //Method scala/collection/mutable/BufferLike$class.$plus$colon:(Lscala/collection/mutable/BufferLike;Ljava/lang/Object;)Lscala/collection/mutable/BufferLike;
   5:	areturn
  LineNumberTable: 
   line 28: 0

  LocalVariableTable: 
   Start  Length  Slot  Name   Signature
   0      6      0    this       Lscala/collection/mutable/ArrayBuffer;
   0      6      1    elem       Ljava/lang/Object;

  Deprecated: true

public scala.collection.mutable.BufferLike $minus$minus(scala.collection.Traversable);
  Code:
   Stack=2, Locals=2, Args_size=2
   0:	aload_0
   1:	aload_1
   2:	invokestatic	#880; //Method scala/collection/mutable/BufferLike$class.$minus$minus:(Lscala/collection/mutable/BufferLike;Lscala/collection/Traversable;)Lscala/collection/mutable/BufferLike;
   5:	areturn
  LineNumberTable: 
   line 28: 0

  LocalVariableTable: 
   Start  Length  Slot  Name   Signature
   0      6      0    this       Lscala/collection/mutable/ArrayBuffer;
   0      6      1    iter       Lscala/collection/Traversable;

  Deprecated: true

public scala.collection.mutable.BufferLike $minus(java.lang.Object, java.lang.Object, scala.collection.Seq);
  Code:
   Stack=4, Locals=4, Args_size=4
   0:	aload_0
   1:	aload_1
   2:	aload_2
   3:	aload_3
   4:	invokestatic	#883; //Method scala/collection/mutable/BufferLike$class.$minus:(Lscala/collection/mutable/BufferLike;Ljava/lang/Object;Ljava/lang/Object;Lscala/collection/Seq;)Lscala/collection/mutable/BufferLike;
   7:	areturn
  LineNumberTable: 
   line 28: 0

  LocalVariableTable: 
   Start  Length  Slot  Name   Signature
   0      8      0    this       Lscala/collection/mutable/ArrayBuffer;
   0      8      1    elem1       Ljava/lang/Object;
   0      8      2    elem2       Ljava/lang/Object;
   0      8      3    elems       Lscala/collection/Seq;

  Deprecated: true

public scala.collection.mutable.BufferLike $minus(java.lang.Object);
  Code:
   Stack=2, Locals=2, Args_size=2
   0:	aload_0
   1:	aload_1
   2:	invokestatic	#885; //Method scala/collection/mutable/BufferLike$class.$minus:(Lscala/collection/mutable/BufferLike;Ljava/lang/Object;)Lscala/collection/mutable/BufferLike;
   5:	areturn
  LineNumberTable: 
   line 28: 0

  LocalVariableTable: 
   Start  Length  Slot  Name   Signature
   0      6      0    this       Lscala/collection/mutable/ArrayBuffer;
   0      6      1    elem       Ljava/lang/Object;

  Deprecated: true

public scala.collection.mutable.BufferLike $plus$plus(scala.collection.Iterator);
  Code:
   Stack=2, Locals=2, Args_size=2
   0:	aload_0
   1:	aload_1
   2:	invokestatic	#887; //Method scala/collection/mutable/BufferLike$class.$plus$plus:(Lscala/collection/mutable/BufferLike;Lscala/collection/Iterator;)Lscala/collection/mutable/BufferLike;
   5:	areturn
  LineNumberTable: 
   line 28: 0

  LocalVariableTable: 
   Start  Length  Slot  Name   Signature
   0      6      0    this       Lscala/collection/mutable/ArrayBuffer;
   0      6      1    iter       Lscala/collection/Iterator;

  Deprecated: true

public scala.collection.mutable.BufferLike $plus$plus(scala.collection.Traversable);
  Code:
   Stack=2, Locals=2, Args_size=2
   0:	aload_0
   1:	aload_1
   2:	invokestatic	#889; //Method scala/collection/mutable/BufferLike$class.$plus$plus:(Lscala/collection/mutable/BufferLike;Lscala/collection/Traversable;)Lscala/collection/mutable/BufferLike;
   5:	areturn
  LineNumberTable: 
   line 28: 0

  LocalVariableTable: 
   Start  Length  Slot  Name   Signature
   0      6      0    this       Lscala/collection/mutable/ArrayBuffer;
   0      6      1    iter       Lscala/collection/Traversable;

  Deprecated: true

public scala.collection.mutable.BufferLike $plus(java.lang.Object, java.lang.Object, scala.collection.Seq);
  Code:
   Stack=4, Locals=4, Args_size=4
   0:	aload_0
   1:	aload_1
   2:	aload_2
   3:	aload_3
   4:	invokestatic	#891; //Method scala/collection/mutable/BufferLike$class.$plus:(Lscala/collection/mutable/BufferLike;Ljava/lang/Object;Ljava/lang/Object;Lscala/collection/Seq;)Lscala/collection/mutable/BufferLike;
   7:	areturn
  LineNumberTable: 
   line 28: 0

  LocalVariableTable: 
   Start  Length  Slot  Name   Signature
   0      8      0    this       Lscala/collection/mutable/ArrayBuffer;
   0      8      1    elem1       Ljava/lang/Object;
   0      8      2    elem2       Ljava/lang/Object;
   0      8      3    elems       Lscala/collection/Seq;

  Deprecated: true

public scala.collection.mutable.BufferLike $plus(java.lang.Object);
  Code:
   Stack=2, Locals=2, Args_size=2
   0:	aload_0
   1:	aload_1
   2:	invokestatic	#893; //Method scala/collection/mutable/BufferLike$class.$plus:(Lscala/collection/mutable/BufferLike;Ljava/lang/Object;)Lscala/collection/mutable/BufferLike;
   5:	areturn
  LineNumberTable: 
   line 28: 0

  LocalVariableTable: 
   Start  Length  Slot  Name   Signature
   0      6      0    this       Lscala/collection/mutable/ArrayBuffer;
   0      6      1    elem       Ljava/lang/Object;

  Deprecated: true

public final scala.collection.mutable.BufferLike $plus$plus$colon(scala.collection.Traversable);
  Code:
   Stack=2, Locals=2, Args_size=2
   0:	aload_0
   1:	aload_1
   2:	invokestatic	#896; //Method scala/collection/mutable/BufferLike$class.$plus$plus$colon:(Lscala/collection/mutable/BufferLike;Lscala/collection/Traversable;)Lscala/collection/mutable/BufferLike;
   5:	areturn
  LineNumberTable: 
   line 28: 0

  LocalVariableTable: 
   Start  Length  Slot  Name   Signature
   0      6      0    this       Lscala/collection/mutable/ArrayBuffer;
   0      6      1    iter       Lscala/collection/Traversable;

  Deprecated: true

public void $plus$plus$eq(java.lang.Object, int, int);
  Code:
   Stack=4, Locals=4, Args_size=4
   0:	aload_0
   1:	aload_1
   2:	iload_2
   3:	iload_3
   4:	invokestatic	#899; //Method scala/collection/mutable/BufferLike$class.$plus$plus$eq:(Lscala/collection/mutable/BufferLike;Ljava/lang/Object;II)V
   7:	return
  LineNumberTable: 
   line 28: 0

  LocalVariableTable: 
   Start  Length  Slot  Name   Signature
   0      8      0    this       Lscala/collection/mutable/ArrayBuffer;
   0      8      1    src       Ljava/lang/Object;
   0      8      2    start       I
   0      8      3    len       I

  Deprecated: true

public scala.collection.Seq readOnly();
  Code:
   Stack=1, Locals=1, Args_size=1
   0:	aload_0
   1:	invokestatic	#904; //Method scala/collection/mutable/BufferLike$class.readOnly:(Lscala/collection/mutable/BufferLike;)Lscala/collection/Seq;
   4:	areturn
  LineNumberTable: 
   line 28: 0


public void $less$less(scala.collection.script.Message);
  Code:
   Stack=2, Locals=2, Args_size=2
   0:	aload_0
   1:	aload_1
   2:	invokestatic	#909; //Method scala/collection/mutable/BufferLike$class.$less$less:(Lscala/collection/mutable/BufferLike;Lscala/collection/script/Message;)V
   5:	return
  LineNumberTable: 
   line 28: 0

  LocalVariableTable: 
   Start  Length  Slot  Name   Signature
   0      6      0    this       Lscala/collection/mutable/ArrayBuffer;
   0      6      1    cmd       Lscala/collection/script/Message;


public void trimEnd(int);
  Code:
   Stack=2, Locals=2, Args_size=2
   0:	aload_0
   1:	iload_1
   2:	invokestatic	#915; //Method scala/collection/mutable/BufferLike$class.trimEnd:(Lscala/collection/mutable/BufferLike;I)V
   5:	return
  LineNumberTable: 
   line 28: 0

  LocalVariableTable: 
   Start  Length  Slot  Name   Signature
   0      6      0    this       Lscala/collection/mutable/ArrayBuffer;
   0      6      1    n       I


public void trimStart(int);
  Code:
   Stack=2, Locals=2, Args_size=2
   0:	aload_0
   1:	iload_1
   2:	invokestatic	#918; //Method scala/collection/mutable/BufferLike$class.trimStart:(Lscala/collection/mutable/BufferLike;I)V
   5:	return
  LineNumberTable: 
   line 28: 0

  LocalVariableTable: 
   Start  Length  Slot  Name   Signature
   0      6      0    this       Lscala/collection/mutable/ArrayBuffer;
   0      6      1    n       I


public void insert(int, scala.collection.Seq);
  Code:
   Stack=3, Locals=3, Args_size=3
   0:	aload_0
   1:	iload_1
   2:	aload_2
   3:	invokestatic	#923; //Method scala/collection/mutable/BufferLike$class.insert:(Lscala/collection/mutable/BufferLike;ILscala/collection/Seq;)V
   6:	return
  LineNumberTable: 
   line 28: 0

  LocalVariableTable: 
   Start  Length  Slot  Name   Signature
   0      7      0    this       Lscala/collection/mutable/ArrayBuffer;
   0      7      1    n       I
   0      7      2    elems       Lscala/collection/Seq;


public void prependAll(scala.collection.Iterator);
  Code:
   Stack=2, Locals=2, Args_size=2
   0:	aload_0
   1:	aload_1
   2:	invokestatic	#928; //Method scala/collection/mutable/BufferLike$class.prependAll:(Lscala/collection/mutable/BufferLike;Lscala/collection/Iterator;)V
   5:	return
  LineNumberTable: 
   line 28: 0

  LocalVariableTable: 
   Start  Length  Slot  Name   Signature
   0      6      0    this       Lscala/collection/mutable/ArrayBuffer;
   0      6      1    iter       Lscala/collection/Iterator;


public void prependAll(scala.collection.Traversable);
  Code:
   Stack=2, Locals=2, Args_size=2
   0:	aload_0
   1:	aload_1
   2:	invokestatic	#931; //Method scala/collection/mutable/BufferLike$class.prependAll:(Lscala/collection/mutable/BufferLike;Lscala/collection/Traversable;)V
   5:	return
  LineNumberTable: 
   line 28: 0

  LocalVariableTable: 
   Start  Length  Slot  Name   Signature
   0      6      0    this       Lscala/collection/mutable/ArrayBuffer;
   0      6      1    iter       Lscala/collection/Traversable;


public void prepend(scala.collection.Seq);
  Code:
   Stack=2, Locals=2, Args_size=2
   0:	aload_0
   1:	aload_1
   2:	invokestatic	#935; //Method scala/collection/mutable/BufferLike$class.prepend:(Lscala/collection/mutable/BufferLike;Lscala/collection/Seq;)V
   5:	return
  LineNumberTable: 
   line 28: 0

  LocalVariableTable: 
   Start  Length  Slot  Name   Signature
   0      6      0    this       Lscala/collection/mutable/ArrayBuffer;
   0      6      1    elems       Lscala/collection/Seq;


public void appendAll(scala.collection.Iterator);
  Code:
   Stack=2, Locals=2, Args_size=2
   0:	aload_0
   1:	aload_1
   2:	invokestatic	#938; //Method scala/collection/mutable/BufferLike$class.appendAll:(Lscala/collection/mutable/BufferLike;Lscala/collection/Iterator;)V
   5:	return
  LineNumberTable: 
   line 28: 0

  LocalVariableTable: 
   Start  Length  Slot  Name   Signature
   0      6      0    this       Lscala/collection/mutable/ArrayBuffer;
   0      6      1    iter       Lscala/collection/Iterator;


public void appendAll(scala.collection.Traversable);
  Code:
   Stack=2, Locals=2, Args_size=2
   0:	aload_0
   1:	aload_1
   2:	invokestatic	#940; //Method scala/collection/mutable/BufferLike$class.appendAll:(Lscala/collection/mutable/BufferLike;Lscala/collection/Traversable;)V
   5:	return
  LineNumberTable: 
   line 28: 0

  LocalVariableTable: 
   Start  Length  Slot  Name   Signature
   0      6      0    this       Lscala/collection/mutable/ArrayBuffer;
   0      6      1    elems       Lscala/collection/Traversable;


public void append(scala.collection.Seq);
  Code:
   Stack=2, Locals=2, Args_size=2
   0:	aload_0
   1:	aload_1
   2:	invokestatic	#942; //Method scala/collection/mutable/BufferLike$class.append:(Lscala/collection/mutable/BufferLike;Lscala/collection/Seq;)V
   5:	return
  LineNumberTable: 
   line 28: 0

  LocalVariableTable: 
   Start  Length  Slot  Name   Signature
   0      6      0    this       Lscala/collection/mutable/ArrayBuffer;
   0      6      1    elems       Lscala/collection/Seq;


public scala.collection.mutable.BufferLike $plus$plus$eq$colon(scala.collection.Iterator);
  Code:
   Stack=2, Locals=2, Args_size=2
   0:	aload_0
   1:	aload_1
   2:	invokestatic	#944; //Method scala/collection/mutable/BufferLike$class.$plus$plus$eq$colon:(Lscala/collection/mutable/BufferLike;Lscala/collection/Iterator;)Lscala/collection/mutable/BufferLike;
   5:	areturn
  LineNumberTable: 
   line 28: 0

  LocalVariableTable: 
   Start  Length  Slot  Name   Signature
   0      6      0    this       Lscala/collection/mutable/ArrayBuffer;
   0      6      1    iter       Lscala/collection/Iterator;


public scala.collection.mutable.BufferLike $minus$eq(java.lang.Object);
  Code:
   Stack=2, Locals=2, Args_size=2
   0:	aload_0
   1:	aload_1
   2:	invokestatic	#946; //Method scala/collection/mutable/BufferLike$class.$minus$eq:(Lscala/collection/mutable/BufferLike;Ljava/lang/Object;)Lscala/collection/mutable/BufferLike;
   5:	areturn
  LineNumberTable: 
   line 28: 0

  LocalVariableTable: 
   Start  Length  Slot  Name   Signature
   0      6      0    this       Lscala/collection/mutable/ArrayBuffer;
   0      6      1    x       Ljava/lang/Object;


public boolean endsWith(scala.collection.Seq);
  Code:
   Stack=2, Locals=2, Args_size=2
   0:	aload_0
   1:	aload_1
   2:	invokestatic	#950; //Method scala/collection/IndexedSeqLike$class.endsWith:(Lscala/collection/IndexedSeqLike;Lscala/collection/Seq;)Z
   5:	ireturn
  LineNumberTable: 
   line 28: 0

  LocalVariableTable: 
   Start  Length  Slot  Name   Signature
   0      6      0    this       Lscala/collection/mutable/ArrayBuffer;
   0      6      1    that       Lscala/collection/Seq;


public boolean startsWith(scala.collection.Seq, int);
  Code:
   Stack=3, Locals=3, Args_size=3
   0:	aload_0
   1:	aload_1
   2:	iload_2
   3:	invokestatic	#954; //Method scala/collection/IndexedSeqLike$class.startsWith:(Lscala/collection/IndexedSeqLike;Lscala/collection/Seq;I)Z
   6:	ireturn
  LineNumberTable: 
   line 28: 0

  LocalVariableTable: 
   Start  Length  Slot  Name   Signature
   0      7      0    this       Lscala/collection/mutable/ArrayBuffer;
   0      7      1    that       Lscala/collection/Seq;
   0      7      2    offset       I


public scala.collection.Iterator reverseIterator();
  Code:
   Stack=1, Locals=1, Args_size=1
   0:	aload_0
   1:	invokestatic	#959; //Method scala/collection/IndexedSeqLike$class.reverseIterator:(Lscala/collection/IndexedSeqLike;)Lscala/collection/Iterator;
   4:	areturn
  LineNumberTable: 
   line 28: 0


public java.lang.Object reverse();
  Code:
   Stack=1, Locals=1, Args_size=1
   0:	aload_0
   1:	invokestatic	#963; //Method scala/collection/IndexedSeqLike$class.reverse:(Lscala/collection/IndexedSeqLike;)Ljava/lang/Object;
   4:	areturn
  LineNumberTable: 
   line 28: 0


public int lastIndexWhere(scala.Function1, int);
  Code:
   Stack=3, Locals=3, Args_size=3
   0:	aload_0
   1:	aload_1
   2:	iload_2
   3:	invokestatic	#967; //Method scala/collection/IndexedSeqLike$class.lastIndexWhere:(Lscala/collection/IndexedSeqLike;Lscala/Function1;I)I
   6:	ireturn
  LineNumberTable: 
   line 28: 0

  LocalVariableTable: 
   Start  Length  Slot  Name   Signature
   0      7      0    this       Lscala/collection/mutable/ArrayBuffer;
   0      7      1    p       Lscala/Function1;
   0      7      2    end       I


public int indexWhere(scala.Function1, int);
  Code:
   Stack=3, Locals=3, Args_size=3
   0:	aload_0
   1:	aload_1
   2:	iload_2
   3:	invokestatic	#969; //Method scala/collection/IndexedSeqLike$class.indexWhere:(Lscala/collection/IndexedSeqLike;Lscala/Function1;I)I
   6:	ireturn
  LineNumberTable: 
   line 28: 0

  LocalVariableTable: 
   Start  Length  Slot  Name   Signature
   0      7      0    this       Lscala/collection/mutable/ArrayBuffer;
   0      7      1    p       Lscala/Function1;
   0      7      2    from       I


public int segmentLength(scala.Function1, int);
  Code:
   Stack=3, Locals=3, Args_size=3
   0:	aload_0
   1:	aload_1
   2:	iload_2
   3:	invokestatic	#972; //Method scala/collection/IndexedSeqLike$class.segmentLength:(Lscala/collection/IndexedSeqLike;Lscala/Function1;I)I
   6:	ireturn
  LineNumberTable: 
   line 28: 0

  LocalVariableTable: 
   Start  Length  Slot  Name   Signature
   0      7      0    this       Lscala/collection/mutable/ArrayBuffer;
   0      7      1    p       Lscala/Function1;
   0      7      2    from       I


public int lengthCompare(int);
  Code:
   Stack=2, Locals=2, Args_size=2
   0:	aload_0
   1:	iload_1
   2:	invokestatic	#976; //Method scala/collection/IndexedSeqLike$class.lengthCompare:(Lscala/collection/IndexedSeqLike;I)I
   5:	ireturn
  LineNumberTable: 
   line 28: 0

  LocalVariableTable: 
   Start  Length  Slot  Name   Signature
   0      6      0    this       Lscala/collection/mutable/ArrayBuffer;
   0      6      1    len       I


public boolean sameElements(scala.collection.Iterable);
  Code:
   Stack=2, Locals=2, Args_size=2
   0:	aload_0
   1:	aload_1
   2:	invokestatic	#981; //Method scala/collection/IndexedSeqLike$class.sameElements:(Lscala/collection/IndexedSeqLike;Lscala/collection/Iterable;)Z
   5:	ireturn
  LineNumberTable: 
   line 28: 0

  LocalVariableTable: 
   Start  Length  Slot  Name   Signature
   0      6      0    this       Lscala/collection/mutable/ArrayBuffer;
   0      6      1    that       Lscala/collection/Iterable;


public scala.Tuple2 span(scala.Function1);
  Code:
   Stack=2, Locals=2, Args_size=2
   0:	aload_0
   1:	aload_1
   2:	invokestatic	#985; //Method scala/collection/IndexedSeqLike$class.span:(Lscala/collection/IndexedSeqLike;Lscala/Function1;)Lscala/Tuple2;
   5:	areturn
  LineNumberTable: 
   line 28: 0

  LocalVariableTable: 
   Start  Length  Slot  Name   Signature
   0      6      0    this       Lscala/collection/mutable/ArrayBuffer;
   0      6      1    p       Lscala/Function1;


public java.lang.Object dropWhile(scala.Function1);
  Code:
   Stack=2, Locals=2, Args_size=2
   0:	aload_0
   1:	aload_1
   2:	invokestatic	#989; //Method scala/collection/IndexedSeqLike$class.dropWhile:(Lscala/collection/IndexedSeqLike;Lscala/Function1;)Ljava/lang/Object;
   5:	areturn
  LineNumberTable: 
   line 28: 0

  LocalVariableTable: 
   Start  Length  Slot  Name   Signature
   0      6      0    this       Lscala/collection/mutable/ArrayBuffer;
   0      6      1    p       Lscala/Function1;


public java.lang.Object takeWhile(scala.Function1);
  Code:
   Stack=2, Locals=2, Args_size=2
   0:	aload_0
   1:	aload_1
   2:	invokestatic	#992; //Method scala/collection/IndexedSeqLike$class.takeWhile:(Lscala/collection/IndexedSeqLike;Lscala/Function1;)Ljava/lang/Object;
   5:	areturn
  LineNumberTable: 
   line 28: 0

  LocalVariableTable: 
   Start  Length  Slot  Name   Signature
   0      6      0    this       Lscala/collection/mutable/ArrayBuffer;
   0      6      1    p       Lscala/Function1;


public scala.Tuple2 splitAt(int);
  Code:
   Stack=2, Locals=2, Args_size=2
   0:	aload_0
   1:	iload_1
   2:	invokestatic	#997; //Method scala/collection/IndexedSeqLike$class.splitAt:(Lscala/collection/IndexedSeqLike;I)Lscala/Tuple2;
   5:	areturn
  LineNumberTable: 
   line 28: 0

  LocalVariableTable: 
   Start  Length  Slot  Name   Signature
   0      6      0    this       Lscala/collection/mutable/ArrayBuffer;
   0      6      1    n       I


public java.lang.Object dropRight(int);
  Code:
   Stack=2, Locals=2, Args_size=2
   0:	aload_0
   1:	iload_1
   2:	invokestatic	#1001; //Method scala/collection/IndexedSeqLike$class.dropRight:(Lscala/collection/IndexedSeqLike;I)Ljava/lang/Object;
   5:	areturn
  LineNumberTable: 
   line 28: 0

  LocalVariableTable: 
   Start  Length  Slot  Name   Signature
   0      6      0    this       Lscala/collection/mutable/ArrayBuffer;
   0      6      1    n       I


public java.lang.Object takeRight(int);
  Code:
   Stack=2, Locals=2, Args_size=2
   0:	aload_0
   1:	iload_1
   2:	invokestatic	#1004; //Method scala/collection/IndexedSeqLike$class.takeRight:(Lscala/collection/IndexedSeqLike;I)Ljava/lang/Object;
   5:	areturn
  LineNumberTable: 
   line 28: 0

  LocalVariableTable: 
   Start  Length  Slot  Name   Signature
   0      6      0    this       Lscala/collection/mutable/ArrayBuffer;
   0      6      1    n       I


public java.lang.Object drop(int);
  Code:
   Stack=2, Locals=2, Args_size=2
   0:	aload_0
   1:	iload_1
   2:	invokestatic	#1007; //Method scala/collection/IndexedSeqLike$class.drop:(Lscala/collection/IndexedSeqLike;I)Ljava/lang/Object;
   5:	areturn
  LineNumberTable: 
   line 28: 0

  LocalVariableTable: 
   Start  Length  Slot  Name   Signature
   0      6      0    this       Lscala/collection/mutable/ArrayBuffer;
   0      6      1    n       I


public java.lang.Object take(int);
  Code:
   Stack=2, Locals=2, Args_size=2
   0:	aload_0
   1:	iload_1
   2:	invokestatic	#1010; //Method scala/collection/IndexedSeqLike$class.take:(Lscala/collection/IndexedSeqLike;I)Ljava/lang/Object;
   5:	areturn
  LineNumberTable: 
   line 28: 0

  LocalVariableTable: 
   Start  Length  Slot  Name   Signature
   0      6      0    this       Lscala/collection/mutable/ArrayBuffer;
   0      6      1    n       I


public java.lang.Object init();
  Code:
   Stack=1, Locals=1, Args_size=1
   0:	aload_0
   1:	invokestatic	#1013; //Method scala/collection/IndexedSeqLike$class.init:(Lscala/collection/IndexedSeqLike;)Ljava/lang/Object;
   4:	areturn
  LineNumberTable: 
   line 28: 0


public java.lang.Object last();
  Code:
   Stack=1, Locals=1, Args_size=1
   0:	aload_0
   1:	invokestatic	#1016; //Method scala/collection/IndexedSeqLike$class.last:(Lscala/collection/IndexedSeqLike;)Ljava/lang/Object;
   4:	areturn
  LineNumberTable: 
   line 28: 0


public java.lang.Object tail();
  Code:
   Stack=1, Locals=1, Args_size=1
   0:	aload_0
   1:	invokestatic	#1019; //Method scala/collection/IndexedSeqLike$class.tail:(Lscala/collection/IndexedSeqLike;)Ljava/lang/Object;
   4:	areturn
  LineNumberTable: 
   line 28: 0


public java.lang.Object head();
  Code:
   Stack=1, Locals=1, Args_size=1
   0:	aload_0
   1:	invokestatic	#1022; //Method scala/collection/IndexedSeqLike$class.head:(Lscala/collection/IndexedSeqLike;)Ljava/lang/Object;
   4:	areturn
  LineNumberTable: 
   line 28: 0


public java.lang.Object slice(int, int);
  Code:
   Stack=3, Locals=3, Args_size=3
   0:	aload_0
   1:	iload_1
   2:	iload_2
   3:	invokestatic	#1027; //Method scala/collection/IndexedSeqLike$class.slice:(Lscala/collection/IndexedSeqLike;II)Ljava/lang/Object;
   6:	areturn
  LineNumberTable: 
   line 28: 0

  LocalVariableTable: 
   Start  Length  Slot  Name   Signature
   0      7      0    this       Lscala/collection/mutable/ArrayBuffer;
   0      7      1    from       I
   0      7      2    until       I


public java.lang.Object zipWithIndex(scala.collection.generic.CanBuildFrom);
  Code:
   Stack=2, Locals=2, Args_size=2
   0:	aload_0
   1:	aload_1
   2:	invokestatic	#1032; //Method scala/collection/IndexedSeqLike$class.zipWithIndex:(Lscala/collection/IndexedSeqLike;Lscala/collection/generic/CanBuildFrom;)Ljava/lang/Object;
   5:	areturn
  LineNumberTable: 
   line 28: 0

  LocalVariableTable: 
   Start  Length  Slot  Name   Signature
   0      6      0    this       Lscala/collection/mutable/ArrayBuffer;
   0      6      1    bf       Lscala/collection/generic/CanBuildFrom;


public java.lang.Object zip(scala.collection.Iterable, scala.collection.generic.CanBuildFrom);
  Code:
   Stack=3, Locals=3, Args_size=3
   0:	aload_0
   1:	aload_1
   2:	aload_2
   3:	invokestatic	#1037; //Method scala/collection/IndexedSeqLike$class.zip:(Lscala/collection/IndexedSeqLike;Lscala/collection/Iterable;Lscala/collection/generic/CanBuildFrom;)Ljava/lang/Object;
   6:	areturn
  LineNumberTable: 
   line 28: 0

  LocalVariableTable: 
   Start  Length  Slot  Name   Signature
   0      7      0    this       Lscala/collection/mutable/ArrayBuffer;
   0      7      1    that       Lscala/collection/Iterable;
   0      7      2    bf       Lscala/collection/generic/CanBuildFrom;


public java.lang.Object reduceRight(scala.Function2);
  Code:
   Stack=2, Locals=2, Args_size=2
   0:	aload_0
   1:	aload_1
   2:	invokestatic	#1041; //Method scala/collection/IndexedSeqLike$class.reduceRight:(Lscala/collection/IndexedSeqLike;Lscala/Function2;)Ljava/lang/Object;
   5:	areturn
  LineNumberTable: 
   line 28: 0

  LocalVariableTable: 
   Start  Length  Slot  Name   Signature
   0      6      0    this       Lscala/collection/mutable/ArrayBuffer;
   0      6      1    op       Lscala/Function2;


public java.lang.Object reduceLeft(scala.Function2);
  Code:
   Stack=2, Locals=2, Args_size=2
   0:	aload_0
   1:	aload_1
   2:	invokestatic	#1044; //Method scala/collection/IndexedSeqLike$class.reduceLeft:(Lscala/collection/IndexedSeqLike;Lscala/Function2;)Ljava/lang/Object;
   5:	areturn
  LineNumberTable: 
   line 28: 0

  LocalVariableTable: 
   Start  Length  Slot  Name   Signature
   0      6      0    this       Lscala/collection/mutable/ArrayBuffer;
   0      6      1    op       Lscala/Function2;


public java.lang.Object foldRight(java.lang.Object, scala.Function2);
  Code:
   Stack=3, Locals=3, Args_size=3
   0:	aload_0
   1:	aload_1
   2:	aload_2
   3:	invokestatic	#1048; //Method scala/collection/IndexedSeqLike$class.foldRight:(Lscala/collection/IndexedSeqLike;Ljava/lang/Object;Lscala/Function2;)Ljava/lang/Object;
   6:	areturn
  LineNumberTable: 
   line 28: 0

  LocalVariableTable: 
   Start  Length  Slot  Name   Signature
   0      7      0    this       Lscala/collection/mutable/ArrayBuffer;
   0      7      1    z       Ljava/lang/Object;
   0      7      2    op       Lscala/Function2;


public java.lang.Object foldLeft(java.lang.Object, scala.Function2);
  Code:
   Stack=3, Locals=3, Args_size=3
   0:	aload_0
   1:	aload_1
   2:	aload_2
   3:	invokestatic	#1051; //Method scala/collection/IndexedSeqLike$class.foldLeft:(Lscala/collection/IndexedSeqLike;Ljava/lang/Object;Lscala/Function2;)Ljava/lang/Object;
   6:	areturn
  LineNumberTable: 
   line 28: 0

  LocalVariableTable: 
   Start  Length  Slot  Name   Signature
   0      7      0    this       Lscala/collection/mutable/ArrayBuffer;
   0      7      1    z       Ljava/lang/Object;
   0      7      2    op       Lscala/Function2;


public scala.Option find(scala.Function1);
  Code:
   Stack=2, Locals=2, Args_size=2
   0:	aload_0
   1:	aload_1
   2:	invokestatic	#1056; //Method scala/collection/IndexedSeqLike$class.find:(Lscala/collection/IndexedSeqLike;Lscala/Function1;)Lscala/Option;
   5:	areturn
  LineNumberTable: 
   line 28: 0

  LocalVariableTable: 
   Start  Length  Slot  Name   Signature
   0      6      0    this       Lscala/collection/mutable/ArrayBuffer;
   0      6      1    p       Lscala/Function1;


public boolean exists(scala.Function1);
  Code:
   Stack=2, Locals=2, Args_size=2
   0:	aload_0
   1:	aload_1
   2:	invokestatic	#1061; //Method scala/collection/IndexedSeqLike$class.exists:(Lscala/collection/IndexedSeqLike;Lscala/Function1;)Z
   5:	ireturn
  LineNumberTable: 
   line 28: 0

  LocalVariableTable: 
   Start  Length  Slot  Name   Signature
   0      6      0    this       Lscala/collection/mutable/ArrayBuffer;
   0      6      1    p       Lscala/Function1;


public boolean forall(scala.Function1);
  Code:
   Stack=2, Locals=2, Args_size=2
   0:	aload_0
   1:	aload_1
   2:	invokestatic	#1064; //Method scala/collection/IndexedSeqLike$class.forall:(Lscala/collection/IndexedSeqLike;Lscala/Function1;)Z
   5:	ireturn
  LineNumberTable: 
   line 28: 0

  LocalVariableTable: 
   Start  Length  Slot  Name   Signature
   0      6      0    this       Lscala/collection/mutable/ArrayBuffer;
   0      6      1    p       Lscala/Function1;


public boolean isEmpty();
  Code:
   Stack=1, Locals=1, Args_size=1
   0:	aload_0
   1:	invokestatic	#1068; //Method scala/collection/IndexedSeqLike$class.isEmpty:(Lscala/collection/IndexedSeqLike;)Z
   4:	ireturn
  LineNumberTable: 
   line 28: 0


public scala.collection.Iterator iterator();
  Code:
   Stack=1, Locals=1, Args_size=1
   0:	aload_0
   1:	invokestatic	#1071; //Method scala/collection/IndexedSeqLike$class.iterator:(Lscala/collection/IndexedSeqLike;)Lscala/collection/Iterator;
   4:	areturn
  LineNumberTable: 
   line 28: 0


public final boolean scala$collection$IndexedSeqLike$$super$endsWith(scala.collection.Seq);
  Code:
   Stack=2, Locals=2, Args_size=2
   0:	aload_0
   1:	aload_1
   2:	invokestatic	#1074; //Method scala/collection/SeqLike$class.endsWith:(Lscala/collection/SeqLike;Lscala/collection/Seq;)Z
   5:	ireturn
  LineNumberTable: 
   line 28: 0

  LocalVariableTable: 
   Start  Length  Slot  Name   Signature
   0      6      0    this       Lscala/collection/mutable/ArrayBuffer;
   0      6      1    that       Lscala/collection/Seq;


public final boolean scala$collection$IndexedSeqLike$$super$sameElements(scala.collection.Iterable);
  Code:
   Stack=2, Locals=2, Args_size=2
   0:	aload_0
   1:	aload_1
   2:	invokestatic	#1078; //Method scala/collection/IterableLike$class.sameElements:(Lscala/collection/IterableLike;Lscala/collection/Iterable;)Z
   5:	ireturn
  LineNumberTable: 
   line 28: 0

  LocalVariableTable: 
   Start  Length  Slot  Name   Signature
   0      6      0    this       Lscala/collection/mutable/ArrayBuffer;
   0      6      1    that       Lscala/collection/Iterable;


public final java.lang.Object scala$collection$IndexedSeqLike$$super$init();
  Code:
   Stack=1, Locals=1, Args_size=1
   0:	aload_0
   1:	invokestatic	#1081; //Method scala/collection/TraversableLike$class.init:(Lscala/collection/TraversableLike;)Ljava/lang/Object;
   4:	areturn
  LineNumberTable: 
   line 28: 0


public final java.lang.Object scala$collection$IndexedSeqLike$$super$last();
  Code:
   Stack=1, Locals=1, Args_size=1
   0:	aload_0
   1:	invokestatic	#1084; //Method scala/collection/TraversableLike$class.last:(Lscala/collection/TraversableLike;)Ljava/lang/Object;
   4:	areturn
  LineNumberTable: 
   line 28: 0


public final java.lang.Object scala$collection$IndexedSeqLike$$super$tail();
  Code:
   Stack=1, Locals=1, Args_size=1
   0:	aload_0
   1:	invokestatic	#1087; //Method scala/collection/TraversableLike$class.tail:(Lscala/collection/TraversableLike;)Ljava/lang/Object;
   4:	areturn
  LineNumberTable: 
   line 28: 0


public final java.lang.Object scala$collection$IndexedSeqLike$$super$head();
  Code:
   Stack=1, Locals=1, Args_size=1
   0:	aload_0
   1:	invokestatic	#1090; //Method scala/collection/IterableLike$class.head:(Lscala/collection/IterableLike;)Ljava/lang/Object;
   4:	areturn
  LineNumberTable: 
   line 28: 0


public final java.lang.Object scala$collection$IndexedSeqLike$$super$zip(scala.collection.Iterable, scala.collection.generic.CanBuildFrom);
  Code:
   Stack=3, Locals=3, Args_size=3
   0:	aload_0
   1:	aload_1
   2:	aload_2
   3:	invokestatic	#1094; //Method scala/collection/IterableLike$class.zip:(Lscala/collection/IterableLike;Lscala/collection/Iterable;Lscala/collection/generic/CanBuildFrom;)Ljava/lang/Object;
   6:	areturn
  LineNumberTable: 
   line 28: 0

  LocalVariableTable: 
   Start  Length  Slot  Name   Signature
   0      7      0    this       Lscala/collection/mutable/ArrayBuffer;
   0      7      1    that       Lscala/collection/Iterable;
   0      7      2    bf       Lscala/collection/generic/CanBuildFrom;


public final java.lang.Object scala$collection$IndexedSeqLike$$super$reduceRight(scala.Function2);
  Code:
   Stack=2, Locals=2, Args_size=2
   0:	aload_0
   1:	aload_1
   2:	invokestatic	#1098; //Method scala/collection/IterableLike$class.reduceRight:(Lscala/collection/IterableLike;Lscala/Function2;)Ljava/lang/Object;
   5:	areturn
  LineNumberTable: 
   line 28: 0

  LocalVariableTable: 
   Start  Length  Slot  Name   Signature
   0      6      0    this       Lscala/collection/mutable/ArrayBuffer;
   0      6      1    op       Lscala/Function2;


public final java.lang.Object scala$collection$IndexedSeqLike$$super$reduceLeft(scala.Function2);
  Code:
   Stack=2, Locals=2, Args_size=2
   0:	aload_0
   1:	aload_1
   2:	invokestatic	#1102; //Method scala/collection/TraversableLike$class.reduceLeft:(Lscala/collection/TraversableLike;Lscala/Function2;)Ljava/lang/Object;
   5:	areturn
  LineNumberTable: 
   line 28: 0

  LocalVariableTable: 
   Start  Length  Slot  Name   Signature
   0      6      0    this       Lscala/collection/mutable/ArrayBuffer;
   0      6      1    op       Lscala/Function2;


public scala.collection.mutable.IndexedSeqView view(int, int);
  Code:
   Stack=3, Locals=3, Args_size=3
   0:	aload_0
   1:	iload_1
   2:	iload_2
   3:	invokestatic	#1105; //Method scala/collection/mutable/IndexedSeqLike$class.view:(Lscala/collection/mutable/IndexedSeqLike;II)Lscala/collection/mutable/IndexedSeqView;
   6:	areturn
  LineNumberTable: 
   line 28: 0

  LocalVariableTable: 
   Start  Length  Slot  Name   Signature
   0      7      0    this       Lscala/collection/mutable/ArrayBuffer;
   0      7      1    from       I
   0      7      2    until       I


public java.lang.Object view();
  Code:
   Stack=1, Locals=1, Args_size=1
   0:	aload_0
   1:	invokestatic	#1108; //Method scala/collection/mutable/IndexedSeqLike$class.view:(Lscala/collection/mutable/IndexedSeqLike;)Ljava/lang/Object;
   4:	areturn
  LineNumberTable: 
   line 28: 0


public scala.collection.mutable.IndexedSeq toCollection(java.lang.Object);
  Code:
   Stack=2, Locals=2, Args_size=2
   0:	aload_0
   1:	aload_1
   2:	invokestatic	#1111; //Method scala/collection/mutable/IndexedSeqLike$class.toCollection:(Lscala/collection/mutable/IndexedSeqLike;Ljava/lang/Object;)Lscala/collection/mutable/IndexedSeq;
   5:	areturn
  LineNumberTable: 
   line 28: 0

  LocalVariableTable: 
   Start  Length  Slot  Name   Signature
   0      6      0    this       Lscala/collection/mutable/ArrayBuffer;
   0      6      1    repr       Ljava/lang/Object;


public scala.collection.mutable.IndexedSeq thisCollection();
  Code:
   Stack=1, Locals=1, Args_size=1
   0:	aload_0
   1:	invokestatic	#1114; //Method scala/collection/mutable/IndexedSeqLike$class.thisCollection:(Lscala/collection/mutable/IndexedSeqLike;)Lscala/collection/mutable/IndexedSeq;
   4:	areturn
  LineNumberTable: 
   line 28: 0


public scala.collection.mutable.Builder mapResult(scala.Function1);
  Code:
   Stack=2, Locals=2, Args_size=2
   0:	aload_0
   1:	aload_1
   2:	invokestatic	#1119; //Method scala/collection/mutable/Builder$class.mapResult:(Lscala/collection/mutable/Builder;Lscala/Function1;)Lscala/collection/mutable/Builder;
   5:	areturn
  LineNumberTable: 
   line 28: 0

  LocalVariableTable: 
   Start  Length  Slot  Name   Signature
   0      6      0    this       Lscala/collection/mutable/ArrayBuffer;
   0      6      1    f       Lscala/Function1;


public void copy(int, int, int);
  Code:
   Stack=4, Locals=4, Args_size=4
   0:	aload_0
   1:	iload_1
   2:	iload_2
   3:	iload_3
   4:	invokestatic	#1122; //Method scala/collection/mutable/ResizableArray$class.copy:(Lscala/collection/mutable/ResizableArray;III)V
   7:	return
  LineNumberTable: 
   line 28: 0

  LocalVariableTable: 
   Start  Length  Slot  Name   Signature
   0      8      0    this       Lscala/collection/mutable/ArrayBuffer;
   0      8      1    m       I
   0      8      2    n       I
   0      8      3    len       I


public void swap(int, int);
  Code:
   Stack=3, Locals=3, Args_size=3
   0:	aload_0
   1:	iload_1
   2:	iload_2
   3:	invokestatic	#1127; //Method scala/collection/mutable/ResizableArray$class.swap:(Lscala/collection/mutable/ResizableArray;II)V
   6:	return
  LineNumberTable: 
   line 28: 0

  LocalVariableTable: 
   Start  Length  Slot  Name   Signature
   0      7      0    this       Lscala/collection/mutable/ArrayBuffer;
   0      7      1    a       I
   0      7      2    b       I


public void ensureSize(int);
  Code:
   Stack=2, Locals=2, Args_size=2
   0:	aload_0
   1:	iload_1
   2:	invokestatic	#1131; //Method scala/collection/mutable/ResizableArray$class.ensureSize:(Lscala/collection/mutable/ResizableArray;I)V
   5:	return
  LineNumberTable: 
   line 28: 0

  LocalVariableTable: 
   Start  Length  Slot  Name   Signature
   0      6      0    this       Lscala/collection/mutable/ArrayBuffer;
   0      6      1    n       I


public void reduceToSize(int);
  Code:
   Stack=2, Locals=2, Args_size=2
   0:	aload_0
   1:	iload_1
   2:	invokestatic	#1133; //Method scala/collection/mutable/ResizableArray$class.reduceToSize:(Lscala/collection/mutable/ResizableArray;I)V
   5:	return
  LineNumberTable: 
   line 28: 0

  LocalVariableTable: 
   Start  Length  Slot  Name   Signature
   0      6      0    this       Lscala/collection/mutable/ArrayBuffer;
   0      6      1    sz       I


public void copyToArray(java.lang.Object, int, int);
  Code:
   Stack=4, Locals=4, Args_size=4
   0:	aload_0
   1:	aload_1
   2:	iload_2
   3:	iload_3
   4:	invokestatic	#1137; //Method scala/collection/mutable/ResizableArray$class.copyToArray:(Lscala/collection/mutable/ResizableArray;Ljava/lang/Object;II)V
   7:	return
  LineNumberTable: 
   line 28: 0

  LocalVariableTable: 
   Start  Length  Slot  Name   Signature
   0      8      0    this       Lscala/collection/mutable/ArrayBuffer;
   0      8      1    xs       Ljava/lang/Object;
   0      8      2    start       I
   0      8      3    len       I


public void foreach(scala.Function1);
  Code:
   Stack=2, Locals=2, Args_size=2
   0:	aload_0
   1:	aload_1
   2:	invokestatic	#1141; //Method scala/collection/mutable/ResizableArray$class.foreach:(Lscala/collection/mutable/ResizableArray;Lscala/Function1;)V
   5:	return
  LineNumberTable: 
   line 28: 0

  LocalVariableTable: 
   Start  Length  Slot  Name   Signature
   0      6      0    this       Lscala/collection/mutable/ArrayBuffer;
   0      6      1    f       Lscala/Function1;


public void update(int, java.lang.Object);
  Code:
   Stack=3, Locals=3, Args_size=3
   0:	aload_0
   1:	iload_1
   2:	aload_2
   3:	invokestatic	#1146; //Method scala/collection/mutable/ResizableArray$class.update:(Lscala/collection/mutable/ResizableArray;ILjava/lang/Object;)V
   6:	return
  LineNumberTable: 
   line 28: 0

  LocalVariableTable: 
   Start  Length  Slot  Name   Signature
   0      7      0    this       Lscala/collection/mutable/ArrayBuffer;
   0      7      1    idx       I
   0      7      2    elem       Ljava/lang/Object;


public java.lang.Object apply(int);
  Code:
   Stack=2, Locals=2, Args_size=2
   0:	aload_0
   1:	iload_1
   2:	invokestatic	#1149; //Method scala/collection/mutable/ResizableArray$class.apply:(Lscala/collection/mutable/ResizableArray;I)Ljava/lang/Object;
   5:	areturn
  LineNumberTable: 
   line 28: 0

  LocalVariableTable: 
   Start  Length  Slot  Name   Signature
   0      6      0    this       Lscala/collection/mutable/ArrayBuffer;
   0      6      1    idx       I


public int length();
  Code:
   Stack=1, Locals=1, Args_size=1
   0:	aload_0
   1:	invokestatic	#1152; //Method scala/collection/mutable/ResizableArray$class.length:(Lscala/collection/mutable/ResizableArray;)I
   4:	ireturn
  LineNumberTable: 
   line 28: 0


public void size0_$eq(int);
  Code:
   Stack=2, Locals=2, Args_size=2
   0:	aload_0
   1:	iload_1
   2:	putfield	#1154; //Field size0:I
   5:	return
  LineNumberTable: 
   line 28: 0


public int size0();
  Code:
   Stack=1, Locals=1, Args_size=1
   0:	aload_0
   1:	getfield	#1154; //Field size0:I
   4:	ireturn
  LineNumberTable: 
   line 28: 0


public void array_$eq(java.lang.Object[]);
  Code:
   Stack=2, Locals=2, Args_size=2
   0:	aload_0
   1:	aload_1
   2:	putfield	#1156; //Field array:[Ljava/lang/Object;
   5:	return
  LineNumberTable: 
   line 28: 0


public java.lang.Object[] array();
  Code:
   Stack=1, Locals=1, Args_size=1
   0:	aload_0
   1:	getfield	#1156; //Field array:[Ljava/lang/Object;
   4:	areturn
  LineNumberTable: 
   line 28: 0


}

