Compiled from "ArrayOps.scala"
public class scala.collection.mutable.ArrayOps$ofBoolean extends scala.collection.mutable.ArrayOps implements scala.collection.mutable.ArrayLike,scala.ScalaObject
  SourceFile: "ArrayOps.scala"
  Signature: length = 0x2
   00 57 
  Scala: length = 0x
   
  InnerClass: 
   public ofBoolean=class scala/collection/mutable/ArrayOps$ofBoolean of class scala/collection/mutable/ArrayOps
   public final ofBoolean=class scala/collection/mutable/WrappedArray$ofBoolean of class scala/collection/mutable/WrappedArray
   public ofBoolean=class scala/collection/mutable/ArrayBuilder$ofBoolean of class scala/collection/mutable/ArrayBuilder
  minor version: 0
  major version: 49
  Constant pool:
Asciz	SourceFile;
Asciz	ArrayOps.scala;
Asciz	repr;
Asciz	[Z;
Asciz	<init>;
Asciz	([Z)V;
Asciz	Code;
Asciz	LineNumberTable;
Asciz	scala/collection/mutable/ArrayOps$ofBoolean;
class	scala/collection/mutable/ArrayOps$ofBoolean
NameAndType	repr:[Z
Field	scala/collection/mutable/ArrayOps$ofBoolean.repr:[Z
Asciz	scala/collection/mutable/ArrayOps;
class	scala/collection/mutable/ArrayOps
Asciz	()V;
NameAndType	"<init>":()V
Method	scala/collection/mutable/ArrayOps."<init>":()V
Asciz	this;
Asciz	Lscala/collection/mutable/ArrayOps$ofBoolean;;
Asciz	LocalVariableTable;
Asciz	()Ljava/lang/Object;;
Asciz	()[Z;
NameAndType	repr:()[Z
Method	scala/collection/mutable/ArrayOps$ofBoolean.repr:()[Z
Asciz	thisCollection;
Asciz	()Lscala/collection/mutable/IndexedSeq;;
Asciz	()Lscala/collection/mutable/WrappedArray;;
NameAndType	thisCollection:()Lscala/collection/mutable/WrappedArray;
Method	scala/collection/mutable/ArrayOps$ofBoolean.thisCollection:()Lscala/collection/mutable/WrappedArray;
Asciz	()Lscala/collection/IndexedSeq;;
Asciz	()Lscala/collection/Seq;;
Asciz	()Lscala/collection/Iterable;;
Asciz	()Lscala/collection/Traversable;;
Asciz	toCollection;
Asciz	(Ljava/lang/Object;)Lscala/collection/mutable/IndexedSeq;;
class	"[Z"
Asciz	([Z)Lscala/collection/mutable/WrappedArray;;
NameAndType	toCollection:([Z)Lscala/collection/mutable/WrappedArray;
Method	scala/collection/mutable/ArrayOps$ofBoolean.toCollection:([Z)Lscala/collection/mutable/WrappedArray;
Asciz	Ljava/lang/Object;;
Asciz	(Ljava/lang/Object;)Lscala/collection/IndexedSeq;;
Asciz	(Ljava/lang/Object;)Lscala/collection/Seq;;
Asciz	(Ljava/lang/Object;)Lscala/collection/Iterable;;
Asciz	(Ljava/lang/Object;)Lscala/collection/Traversable;;
Asciz	newBuilder;
Asciz	()Lscala/collection/mutable/Builder;;
Asciz	()Lscala/collection/mutable/ArrayBuilder$ofBoolean;;
NameAndType	newBuilder:()Lscala/collection/mutable/ArrayBuilder$ofBoolean;
Method	scala/collection/mutable/ArrayOps$ofBoolean.newBuilder:()Lscala/collection/mutable/ArrayBuilder$ofBoolean;
Asciz	apply;
Asciz	(I)Ljava/lang/Object;;
Asciz	(I)Z;
NameAndType	apply:(I)Z
Method	scala/collection/mutable/ArrayOps$ofBoolean.apply:(I)Z
Asciz	scala/runtime/BoxesRunTime;
class	scala/runtime/BoxesRunTime
Asciz	boxToBoolean;
Asciz	(Z)Ljava/lang/Boolean;;
NameAndType	boxToBoolean:(Z)Ljava/lang/Boolean;
Method	scala/runtime/BoxesRunTime.boxToBoolean:(Z)Ljava/lang/Boolean;
Asciz	idx;
Asciz	I;
Asciz	update;
Asciz	(ILjava/lang/Object;)V;
Asciz	unboxToBoolean;
Asciz	(Ljava/lang/Object;)Z;
NameAndType	unboxToBoolean:(Ljava/lang/Object;)Z
Method	scala/runtime/BoxesRunTime.unboxToBoolean:(Ljava/lang/Object;)Z
Asciz	(IZ)V;
NameAndType	update:(IZ)V
Method	scala/collection/mutable/ArrayOps$ofBoolean.update:(IZ)V
Asciz	elem;
Asciz	index;
Asciz	Z;
Asciz	length;
Asciz	()I;
Asciz	scala/collection/mutable/ArrayBuilder$ofBoolean;
class	scala/collection/mutable/ArrayBuilder$ofBoolean
Method	scala/collection/mutable/ArrayBuilder$ofBoolean."<init>":()V
Asciz	scala/collection/mutable/WrappedArray$ofBoolean;
class	scala/collection/mutable/WrappedArray$ofBoolean
NameAndType	"<init>":([Z)V
Method	scala/collection/mutable/WrappedArray$ofBoolean."<init>":([Z)V
Asciz	([Z)Lscala/collection/mutable/WrappedArray<Ljava/lang/Boolean;>;;
Asciz	Signature;
Asciz	()Lscala/collection/mutable/WrappedArray<Ljava/lang/Boolean;>;;
Asciz	Lscala/collection/mutable/ArrayOps<Ljava/lang/Boolean;>;Lscala/collection/mutable/ArrayLike<Ljava/lang/Boolean;[Z>;Lscala/ScalaObject;;
Asciz	Scala;
Asciz	InnerClasses;
Asciz	ofBoolean;
Asciz	scala/collection/mutable/WrappedArray;
class	scala/collection/mutable/WrappedArray
Asciz	scala/collection/mutable/ArrayBuilder;
class	scala/collection/mutable/ArrayBuilder
Asciz	scala/collection/mutable/ArrayLike;
class	scala/collection/mutable/ArrayLike
Asciz	scala/ScalaObject;
class	scala/ScalaObject

{
private final boolean[] repr;
  Signature: [Z

public scala.collection.mutable.ArrayOps$ofBoolean(boolean[]);
  Signature: ([Z)V
  Code:
   Stack=2, Locals=2, Args_size=2
	aload_0
	aload_1
	putfield	Field repr:[Z
	aload_0
	invokespecial	Method scala/collection/mutable/ArrayOps."<init>":()V
	return
  Labels:
  LocalVariableTable: 
   Start  Length  Slot  Name   Signature
   0      10      0    this       Lscala/collection/mutable/ArrayOps$ofBoolean;
   0      10      1    repr       [Z


public java.lang.Object repr();
  Signature: ()Ljava/lang/Object;
  Code:
   Stack=1, Locals=1, Args_size=1
	aload_0
	invokevirtual	Method repr:()[Z
	areturn
  Labels:

public scala.collection.mutable.IndexedSeq thisCollection();
  Signature: ()Lscala/collection/mutable/IndexedSeq;
  Code:
   Stack=1, Locals=1, Args_size=1
	aload_0
	invokevirtual	Method thisCollection:()Lscala/collection/mutable/WrappedArray;
	areturn
  Labels:

public scala.collection.IndexedSeq thisCollection();
  Signature: ()Lscala/collection/IndexedSeq;
  Code:
   Stack=1, Locals=1, Args_size=1
	aload_0
	invokevirtual	Method thisCollection:()Lscala/collection/mutable/WrappedArray;
	areturn
  Labels:

public scala.collection.Seq thisCollection();
  Signature: ()Lscala/collection/Seq;
  Code:
   Stack=1, Locals=1, Args_size=1
	aload_0
	invokevirtual	Method thisCollection:()Lscala/collection/mutable/WrappedArray;
	areturn
  Labels:

public scala.collection.Iterable thisCollection();
  Signature: ()Lscala/collection/Iterable;
  Code:
   Stack=1, Locals=1, Args_size=1
	aload_0
	invokevirtual	Method thisCollection:()Lscala/collection/mutable/WrappedArray;
	areturn
  Labels:

public scala.collection.Traversable thisCollection();
  Signature: ()Lscala/collection/Traversable;
  Code:
   Stack=1, Locals=1, Args_size=1
	aload_0
	invokevirtual	Method thisCollection:()Lscala/collection/mutable/WrappedArray;
	areturn
  Labels:

public scala.collection.mutable.IndexedSeq toCollection(java.lang.Object);
  Signature: (Ljava/lang/Object;)Lscala/collection/mutable/IndexedSeq;
  Code:
   Stack=2, Locals=2, Args_size=2
	aload_0
	aload_1
	checkcast	class "[Z"
	invokevirtual	Method toCollection:([Z)Lscala/collection/mutable/WrappedArray;
	areturn
  Labels:
  LocalVariableTable: 
   Start  Length  Slot  Name   Signature
   0      9      0    this       Lscala/collection/mutable/ArrayOps$ofBoolean;
   0      9      1    repr       Ljava/lang/Object;


public scala.collection.IndexedSeq toCollection(java.lang.Object);
  Signature: (Ljava/lang/Object;)Lscala/collection/IndexedSeq;
  Code:
   Stack=2, Locals=2, Args_size=2
	aload_0
	aload_1
	checkcast	class "[Z"
	invokevirtual	Method toCollection:([Z)Lscala/collection/mutable/WrappedArray;
	areturn
  Labels:
  LocalVariableTable: 
   Start  Length  Slot  Name   Signature
   0      9      0    this       Lscala/collection/mutable/ArrayOps$ofBoolean;
   0      9      1    repr       Ljava/lang/Object;


public scala.collection.Seq toCollection(java.lang.Object);
  Signature: (Ljava/lang/Object;)Lscala/collection/Seq;
  Code:
   Stack=2, Locals=2, Args_size=2
	aload_0
	aload_1
	checkcast	class "[Z"
	invokevirtual	Method toCollection:([Z)Lscala/collection/mutable/WrappedArray;
	areturn
  Labels:
  LocalVariableTable: 
   Start  Length  Slot  Name   Signature
   0      9      0    this       Lscala/collection/mutable/ArrayOps$ofBoolean;
   0      9      1    repr       Ljava/lang/Object;


public scala.collection.Iterable toCollection(java.lang.Object);
  Signature: (Ljava/lang/Object;)Lscala/collection/Iterable;
  Code:
   Stack=2, Locals=2, Args_size=2
	aload_0
	aload_1
	checkcast	class "[Z"
	invokevirtual	Method toCollection:([Z)Lscala/collection/mutable/WrappedArray;
	areturn
  Labels:
  LocalVariableTable: 
   Start  Length  Slot  Name   Signature
   0      9      0    this       Lscala/collection/mutable/ArrayOps$ofBoolean;
   0      9      1    repr       Ljava/lang/Object;


public scala.collection.Traversable toCollection(java.lang.Object);
  Signature: (Ljava/lang/Object;)Lscala/collection/Traversable;
  Code:
   Stack=2, Locals=2, Args_size=2
	aload_0
	aload_1
	checkcast	class "[Z"
	invokevirtual	Method toCollection:([Z)Lscala/collection/mutable/WrappedArray;
	areturn
  Labels:
  LocalVariableTable: 
   Start  Length  Slot  Name   Signature
   0      9      0    this       Lscala/collection/mutable/ArrayOps$ofBoolean;
   0      9      1    repr       Ljava/lang/Object;


public scala.collection.mutable.Builder newBuilder();
  Signature: ()Lscala/collection/mutable/Builder;
  Code:
   Stack=1, Locals=1, Args_size=1
	aload_0
	invokevirtual	Method newBuilder:()Lscala/collection/mutable/ArrayBuilder$ofBoolean;
	areturn
  Labels:

public java.lang.Object apply(int);
  Signature: (I)Ljava/lang/Object;
  Code:
   Stack=2, Locals=3, Args_size=2
	aload_0
	iload_1
	invokevirtual	Method apply:(I)Z
	istore_2
	iload_2
	invokestatic	Method scala/runtime/BoxesRunTime.boxToBoolean:(Z)Ljava/lang/Boolean;
	areturn
  Labels:
  LocalVariableTable: 
   Start  Length  Slot  Name   Signature
   0      11      0    this       Lscala/collection/mutable/ArrayOps$ofBoolean;
   0      11      1    idx       I


public void update(int, java.lang.Object);
  Signature: (ILjava/lang/Object;)V
  Code:
   Stack=3, Locals=3, Args_size=3
	aload_0
	iload_1
	aload_2
	invokestatic	Method scala/runtime/BoxesRunTime.unboxToBoolean:(Ljava/lang/Object;)Z
	invokevirtual	Method update:(IZ)V
	return
  Labels:
  LocalVariableTable: 
   Start  Length  Slot  Name   Signature
   0      10      0    this       Lscala/collection/mutable/ArrayOps$ofBoolean;
   0      10      1    idx       I
   0      10      2    elem       Ljava/lang/Object;


public void update(int, boolean);
  Signature: (IZ)V
  Code:
   Stack=3, Locals=3, Args_size=3
	aload_0
	invokevirtual	Method repr:()[Z
	iload_1
	iload_2
	bastore
	return
  Labels:
  LocalVariableTable: 
   Start  Length  Slot  Name   Signature
   0      8      0    this       Lscala/collection/mutable/ArrayOps$ofBoolean;
   0      8      1    index       I
   0      8      2    elem       Z


public boolean apply(int);
  Signature: (I)Z
  Code:
   Stack=2, Locals=2, Args_size=2
	aload_0
	invokevirtual	Method repr:()[Z
	iload_1
	baload
	ireturn
  Labels:
  LocalVariableTable: 
   Start  Length  Slot  Name   Signature
   0      7      0    this       Lscala/collection/mutable/ArrayOps$ofBoolean;
   0      7      1    index       I


public int length();
  Signature: ()I
  Code:
   Stack=1, Locals=1, Args_size=1
	aload_0
	invokevirtual	Method repr:()[Z
	arraylength
	ireturn
  Labels:

public scala.collection.mutable.ArrayBuilder$ofBoolean newBuilder();
  Signature: ()Lscala/collection/mutable/ArrayBuilder$ofBoolean;
  Code:
   Stack=2, Locals=1, Args_size=1
	new	class scala/collection/mutable/ArrayBuilder$ofBoolean
	dup
	invokespecial	Method scala/collection/mutable/ArrayBuilder$ofBoolean."<init>":()V
	areturn
  Labels:

public scala.collection.mutable.WrappedArray toCollection(boolean[]);
  Signature: ([Z)Lscala/collection/mutable/WrappedArray;
  Code:
   Stack=3, Locals=2, Args_size=2
	new	class scala/collection/mutable/WrappedArray$ofBoolean
	dup
	aload_1
	invokespecial	Method scala/collection/mutable/WrappedArray$ofBoolean."<init>":([Z)V
	areturn
  Labels:
  LocalVariableTable: 
   Start  Length  Slot  Name   Signature
   0      9      0    this       Lscala/collection/mutable/ArrayOps$ofBoolean;
   0      9      1    repr       [Z

  Signature: length = 0x2
   00 54 

public scala.collection.mutable.WrappedArray thisCollection();
  Signature: ()Lscala/collection/mutable/WrappedArray;
  Code:
   Stack=3, Locals=1, Args_size=1
	new	class scala/collection/mutable/WrappedArray$ofBoolean
	dup
	aload_0
	invokevirtual	Method repr:()[Z
	invokespecial	Method scala/collection/mutable/WrappedArray$ofBoolean."<init>":([Z)V
	areturn
  Labels:
  Signature: length = 0x2
   00 56 

public boolean[] repr();
  Signature: ()[Z
  Code:
   Stack=1, Locals=1, Args_size=1
	aload_0
	getfield	Field repr:[Z
	areturn
  Labels:

}

