Compiled from "ArrayOps.scala"
public class scala.collection.mutable.ArrayOps$ofLong extends scala.collection.mutable.ArrayOps implements scala.collection.mutable.ArrayLike,scala.ScalaObject
  SourceFile: "ArrayOps.scala"
  Signature: length = 0x2
   00 57 
  Scala: length = 0x
   
  InnerClass: 
   public ofLong=class scala/collection/mutable/ArrayOps$ofLong of class scala/collection/mutable/ArrayOps
   public final ofLong=class scala/collection/mutable/WrappedArray$ofLong of class scala/collection/mutable/WrappedArray
   public ofLong=class scala/collection/mutable/ArrayBuilder$ofLong of class scala/collection/mutable/ArrayBuilder
  minor version: 0
  major version: 49
  Constant pool:
Asciz	SourceFile;
Asciz	ArrayOps.scala;
Asciz	repr;
Asciz	[J;
Asciz	<init>;
Asciz	([J)V;
Asciz	Code;
Asciz	LineNumberTable;
Asciz	scala/collection/mutable/ArrayOps$ofLong;
class	scala/collection/mutable/ArrayOps$ofLong
NameAndType	repr:[J
Field	scala/collection/mutable/ArrayOps$ofLong.repr:[J
Asciz	scala/collection/mutable/ArrayOps;
class	scala/collection/mutable/ArrayOps
Asciz	()V;
NameAndType	"<init>":()V
Method	scala/collection/mutable/ArrayOps."<init>":()V
Asciz	this;
Asciz	Lscala/collection/mutable/ArrayOps$ofLong;;
Asciz	LocalVariableTable;
Asciz	()Ljava/lang/Object;;
Asciz	()[J;
NameAndType	repr:()[J
Method	scala/collection/mutable/ArrayOps$ofLong.repr:()[J
Asciz	thisCollection;
Asciz	()Lscala/collection/mutable/IndexedSeq;;
Asciz	()Lscala/collection/mutable/WrappedArray;;
NameAndType	thisCollection:()Lscala/collection/mutable/WrappedArray;
Method	scala/collection/mutable/ArrayOps$ofLong.thisCollection:()Lscala/collection/mutable/WrappedArray;
Asciz	()Lscala/collection/IndexedSeq;;
Asciz	()Lscala/collection/Seq;;
Asciz	()Lscala/collection/Iterable;;
Asciz	()Lscala/collection/Traversable;;
Asciz	toCollection;
Asciz	(Ljava/lang/Object;)Lscala/collection/mutable/IndexedSeq;;
class	"[J"
Asciz	([J)Lscala/collection/mutable/WrappedArray;;
NameAndType	toCollection:([J)Lscala/collection/mutable/WrappedArray;
Method	scala/collection/mutable/ArrayOps$ofLong.toCollection:([J)Lscala/collection/mutable/WrappedArray;
Asciz	Ljava/lang/Object;;
Asciz	(Ljava/lang/Object;)Lscala/collection/IndexedSeq;;
Asciz	(Ljava/lang/Object;)Lscala/collection/Seq;;
Asciz	(Ljava/lang/Object;)Lscala/collection/Iterable;;
Asciz	(Ljava/lang/Object;)Lscala/collection/Traversable;;
Asciz	newBuilder;
Asciz	()Lscala/collection/mutable/Builder;;
Asciz	()Lscala/collection/mutable/ArrayBuilder$ofLong;;
NameAndType	newBuilder:()Lscala/collection/mutable/ArrayBuilder$ofLong;
Method	scala/collection/mutable/ArrayOps$ofLong.newBuilder:()Lscala/collection/mutable/ArrayBuilder$ofLong;
Asciz	apply;
Asciz	(I)Ljava/lang/Object;;
Asciz	(I)J;
NameAndType	apply:(I)J
Method	scala/collection/mutable/ArrayOps$ofLong.apply:(I)J
Asciz	scala/runtime/BoxesRunTime;
class	scala/runtime/BoxesRunTime
Asciz	boxToLong;
Asciz	(J)Ljava/lang/Long;;
NameAndType	boxToLong:(J)Ljava/lang/Long;
Method	scala/runtime/BoxesRunTime.boxToLong:(J)Ljava/lang/Long;
Asciz	idx;
Asciz	I;
Asciz	update;
Asciz	(ILjava/lang/Object;)V;
Asciz	unboxToLong;
Asciz	(Ljava/lang/Object;)J;
NameAndType	unboxToLong:(Ljava/lang/Object;)J
Method	scala/runtime/BoxesRunTime.unboxToLong:(Ljava/lang/Object;)J
Asciz	(IJ)V;
NameAndType	update:(IJ)V
Method	scala/collection/mutable/ArrayOps$ofLong.update:(IJ)V
Asciz	elem;
Asciz	index;
Asciz	J;
Asciz	length;
Asciz	()I;
Asciz	scala/collection/mutable/ArrayBuilder$ofLong;
class	scala/collection/mutable/ArrayBuilder$ofLong
Method	scala/collection/mutable/ArrayBuilder$ofLong."<init>":()V
Asciz	scala/collection/mutable/WrappedArray$ofLong;
class	scala/collection/mutable/WrappedArray$ofLong
NameAndType	"<init>":([J)V
Method	scala/collection/mutable/WrappedArray$ofLong."<init>":([J)V
Asciz	([J)Lscala/collection/mutable/WrappedArray<Ljava/lang/Long;>;;
Asciz	Signature;
Asciz	()Lscala/collection/mutable/WrappedArray<Ljava/lang/Long;>;;
Asciz	Lscala/collection/mutable/ArrayOps<Ljava/lang/Long;>;Lscala/collection/mutable/ArrayLike<Ljava/lang/Long;[J>;Lscala/ScalaObject;;
Asciz	Scala;
Asciz	InnerClasses;
Asciz	ofLong;
Asciz	scala/collection/mutable/WrappedArray;
class	scala/collection/mutable/WrappedArray
Asciz	scala/collection/mutable/ArrayBuilder;
class	scala/collection/mutable/ArrayBuilder
Asciz	scala/collection/mutable/ArrayLike;
class	scala/collection/mutable/ArrayLike
Asciz	scala/ScalaObject;
class	scala/ScalaObject

{
private final long[] repr;
  Signature: [J

public scala.collection.mutable.ArrayOps$ofLong(long[]);
  Signature: ([J)V
  Code:
   Stack=2, Locals=2, Args_size=2
	aload_0
	aload_1
	putfield	Field repr:[J
	aload_0
	invokespecial	Method scala/collection/mutable/ArrayOps."<init>":()V
	return
  Labels:
  LocalVariableTable: 
   Start  Length  Slot  Name   Signature
   0      10      0    this       Lscala/collection/mutable/ArrayOps$ofLong;
   0      10      1    repr       [J


public java.lang.Object repr();
  Signature: ()Ljava/lang/Object;
  Code:
   Stack=1, Locals=1, Args_size=1
	aload_0
	invokevirtual	Method repr:()[J
	areturn
  Labels:

public scala.collection.mutable.IndexedSeq thisCollection();
  Signature: ()Lscala/collection/mutable/IndexedSeq;
  Code:
   Stack=1, Locals=1, Args_size=1
	aload_0
	invokevirtual	Method thisCollection:()Lscala/collection/mutable/WrappedArray;
	areturn
  Labels:

public scala.collection.IndexedSeq thisCollection();
  Signature: ()Lscala/collection/IndexedSeq;
  Code:
   Stack=1, Locals=1, Args_size=1
	aload_0
	invokevirtual	Method thisCollection:()Lscala/collection/mutable/WrappedArray;
	areturn
  Labels:

public scala.collection.Seq thisCollection();
  Signature: ()Lscala/collection/Seq;
  Code:
   Stack=1, Locals=1, Args_size=1
	aload_0
	invokevirtual	Method thisCollection:()Lscala/collection/mutable/WrappedArray;
	areturn
  Labels:

public scala.collection.Iterable thisCollection();
  Signature: ()Lscala/collection/Iterable;
  Code:
   Stack=1, Locals=1, Args_size=1
	aload_0
	invokevirtual	Method thisCollection:()Lscala/collection/mutable/WrappedArray;
	areturn
  Labels:

public scala.collection.Traversable thisCollection();
  Signature: ()Lscala/collection/Traversable;
  Code:
   Stack=1, Locals=1, Args_size=1
	aload_0
	invokevirtual	Method thisCollection:()Lscala/collection/mutable/WrappedArray;
	areturn
  Labels:

public scala.collection.mutable.IndexedSeq toCollection(java.lang.Object);
  Signature: (Ljava/lang/Object;)Lscala/collection/mutable/IndexedSeq;
  Code:
   Stack=2, Locals=2, Args_size=2
	aload_0
	aload_1
	checkcast	class "[J"
	invokevirtual	Method toCollection:([J)Lscala/collection/mutable/WrappedArray;
	areturn
  Labels:
  LocalVariableTable: 
   Start  Length  Slot  Name   Signature
   0      9      0    this       Lscala/collection/mutable/ArrayOps$ofLong;
   0      9      1    repr       Ljava/lang/Object;


public scala.collection.IndexedSeq toCollection(java.lang.Object);
  Signature: (Ljava/lang/Object;)Lscala/collection/IndexedSeq;
  Code:
   Stack=2, Locals=2, Args_size=2
	aload_0
	aload_1
	checkcast	class "[J"
	invokevirtual	Method toCollection:([J)Lscala/collection/mutable/WrappedArray;
	areturn
  Labels:
  LocalVariableTable: 
   Start  Length  Slot  Name   Signature
   0      9      0    this       Lscala/collection/mutable/ArrayOps$ofLong;
   0      9      1    repr       Ljava/lang/Object;


public scala.collection.Seq toCollection(java.lang.Object);
  Signature: (Ljava/lang/Object;)Lscala/collection/Seq;
  Code:
   Stack=2, Locals=2, Args_size=2
	aload_0
	aload_1
	checkcast	class "[J"
	invokevirtual	Method toCollection:([J)Lscala/collection/mutable/WrappedArray;
	areturn
  Labels:
  LocalVariableTable: 
   Start  Length  Slot  Name   Signature
   0      9      0    this       Lscala/collection/mutable/ArrayOps$ofLong;
   0      9      1    repr       Ljava/lang/Object;


public scala.collection.Iterable toCollection(java.lang.Object);
  Signature: (Ljava/lang/Object;)Lscala/collection/Iterable;
  Code:
   Stack=2, Locals=2, Args_size=2
	aload_0
	aload_1
	checkcast	class "[J"
	invokevirtual	Method toCollection:([J)Lscala/collection/mutable/WrappedArray;
	areturn
  Labels:
  LocalVariableTable: 
   Start  Length  Slot  Name   Signature
   0      9      0    this       Lscala/collection/mutable/ArrayOps$ofLong;
   0      9      1    repr       Ljava/lang/Object;


public scala.collection.Traversable toCollection(java.lang.Object);
  Signature: (Ljava/lang/Object;)Lscala/collection/Traversable;
  Code:
   Stack=2, Locals=2, Args_size=2
	aload_0
	aload_1
	checkcast	class "[J"
	invokevirtual	Method toCollection:([J)Lscala/collection/mutable/WrappedArray;
	areturn
  Labels:
  LocalVariableTable: 
   Start  Length  Slot  Name   Signature
   0      9      0    this       Lscala/collection/mutable/ArrayOps$ofLong;
   0      9      1    repr       Ljava/lang/Object;


public scala.collection.mutable.Builder newBuilder();
  Signature: ()Lscala/collection/mutable/Builder;
  Code:
   Stack=1, Locals=1, Args_size=1
	aload_0
	invokevirtual	Method newBuilder:()Lscala/collection/mutable/ArrayBuilder$ofLong;
	areturn
  Labels:

public java.lang.Object apply(int);
  Signature: (I)Ljava/lang/Object;
  Code:
   Stack=2, Locals=4, Args_size=2
	aload_0
	iload_1
	invokevirtual	Method apply:(I)J
	lstore_2
	lload_2
	invokestatic	Method scala/runtime/BoxesRunTime.boxToLong:(J)Ljava/lang/Long;
	areturn
  Labels:
  LocalVariableTable: 
   Start  Length  Slot  Name   Signature
   0      11      0    this       Lscala/collection/mutable/ArrayOps$ofLong;
   0      11      1    idx       I


public void update(int, java.lang.Object);
  Signature: (ILjava/lang/Object;)V
  Code:
   Stack=4, Locals=3, Args_size=3
	aload_0
	iload_1
	aload_2
	invokestatic	Method scala/runtime/BoxesRunTime.unboxToLong:(Ljava/lang/Object;)J
	invokevirtual	Method update:(IJ)V
	return
  Labels:
  LocalVariableTable: 
   Start  Length  Slot  Name   Signature
   0      10      0    this       Lscala/collection/mutable/ArrayOps$ofLong;
   0      10      1    idx       I
   0      10      2    elem       Ljava/lang/Object;


public void update(int, long);
  Signature: (IJ)V
  Code:
   Stack=4, Locals=4, Args_size=3
	aload_0
	invokevirtual	Method repr:()[J
	iload_1
	lload_2
	lastore
	return
  Labels:
  LocalVariableTable: 
   Start  Length  Slot  Name   Signature
   0      8      0    this       Lscala/collection/mutable/ArrayOps$ofLong;
   0      8      1    index       I
   0      8      2    elem       J


public long apply(int);
  Signature: (I)J
  Code:
   Stack=2, Locals=2, Args_size=2
	aload_0
	invokevirtual	Method repr:()[J
	iload_1
	laload
	lreturn
  Labels:
  LocalVariableTable: 
   Start  Length  Slot  Name   Signature
   0      7      0    this       Lscala/collection/mutable/ArrayOps$ofLong;
   0      7      1    index       I


public int length();
  Signature: ()I
  Code:
   Stack=1, Locals=1, Args_size=1
	aload_0
	invokevirtual	Method repr:()[J
	arraylength
	ireturn
  Labels:

public scala.collection.mutable.ArrayBuilder$ofLong newBuilder();
  Signature: ()Lscala/collection/mutable/ArrayBuilder$ofLong;
  Code:
   Stack=2, Locals=1, Args_size=1
	new	class scala/collection/mutable/ArrayBuilder$ofLong
	dup
	invokespecial	Method scala/collection/mutable/ArrayBuilder$ofLong."<init>":()V
	areturn
  Labels:

public scala.collection.mutable.WrappedArray toCollection(long[]);
  Signature: ([J)Lscala/collection/mutable/WrappedArray;
  Code:
   Stack=3, Locals=2, Args_size=2
	new	class scala/collection/mutable/WrappedArray$ofLong
	dup
	aload_1
	invokespecial	Method scala/collection/mutable/WrappedArray$ofLong."<init>":([J)V
	areturn
  Labels:
  LocalVariableTable: 
   Start  Length  Slot  Name   Signature
   0      9      0    this       Lscala/collection/mutable/ArrayOps$ofLong;
   0      9      1    repr       [J

  Signature: length = 0x2
   00 54 

public scala.collection.mutable.WrappedArray thisCollection();
  Signature: ()Lscala/collection/mutable/WrappedArray;
  Code:
   Stack=3, Locals=1, Args_size=1
	new	class scala/collection/mutable/WrappedArray$ofLong
	dup
	aload_0
	invokevirtual	Method repr:()[J
	invokespecial	Method scala/collection/mutable/WrappedArray$ofLong."<init>":([J)V
	areturn
  Labels:
  Signature: length = 0x2
   00 56 

public long[] repr();
  Signature: ()[J
  Code:
   Stack=1, Locals=1, Args_size=1
	aload_0
	getfield	Field repr:[J
	areturn
  Labels:

}

