Compiled from "ArrayOps.scala"
public class scala.collection.mutable.ArrayOps$ofDouble extends scala.collection.mutable.ArrayOps implements scala.collection.mutable.ArrayLike,scala.ScalaObject
  SourceFile: "ArrayOps.scala"
  Signature: length = 0x2
   00 57 
  Scala: length = 0x
   
  InnerClass: 
   public #90= #10 of #14; //ofDouble=class scala/collection/mutable/ArrayOps$ofDouble of class scala/collection/mutable/ArrayOps
   public final #90= #81 of #92; //ofDouble=class scala/collection/mutable/WrappedArray$ofDouble of class scala/collection/mutable/WrappedArray
   public #90= #78 of #94; //ofDouble=class scala/collection/mutable/ArrayBuilder$ofDouble of class scala/collection/mutable/ArrayBuilder
  minor version: 0
  major version: 49
  Constant pool:
const #1 = Asciz	SourceFile;
const #2 = Asciz	ArrayOps.scala;
const #3 = Asciz	repr;
const #4 = Asciz	[D;
const #5 = Asciz	<init>;
const #6 = Asciz	([D)V;
const #7 = Asciz	Code;
const #8 = Asciz	LineNumberTable;
const #9 = Asciz	scala/collection/mutable/ArrayOps$ofDouble;
const #10 = class	#9;	//  scala/collection/mutable/ArrayOps$ofDouble
const #11 = NameAndType	#3:#4;//  repr:[D
const #12 = Field	#10.#11;	//  scala/collection/mutable/ArrayOps$ofDouble.repr:[D
const #13 = Asciz	scala/collection/mutable/ArrayOps;
const #14 = class	#13;	//  scala/collection/mutable/ArrayOps
const #15 = Asciz	()V;
const #16 = NameAndType	#5:#15;//  "<init>":()V
const #17 = Method	#14.#16;	//  scala/collection/mutable/ArrayOps."<init>":()V
const #18 = Asciz	this;
const #19 = Asciz	Lscala/collection/mutable/ArrayOps$ofDouble;;
const #20 = Asciz	LocalVariableTable;
const #21 = Asciz	()Ljava/lang/Object;;
const #22 = Asciz	()[D;
const #23 = NameAndType	#3:#22;//  repr:()[D
const #24 = Method	#10.#23;	//  scala/collection/mutable/ArrayOps$ofDouble.repr:()[D
const #25 = Asciz	thisCollection;
const #26 = Asciz	()Lscala/collection/mutable/IndexedSeq;;
const #27 = Asciz	()Lscala/collection/mutable/WrappedArray;;
const #28 = NameAndType	#25:#27;//  thisCollection:()Lscala/collection/mutable/WrappedArray;
const #29 = Method	#10.#28;	//  scala/collection/mutable/ArrayOps$ofDouble.thisCollection:()Lscala/collection/mutable/WrappedArray;
const #30 = Asciz	()Lscala/collection/IndexedSeq;;
const #31 = Asciz	()Lscala/collection/Seq;;
const #32 = Asciz	()Lscala/collection/Iterable;;
const #33 = Asciz	()Lscala/collection/Traversable;;
const #34 = Asciz	toCollection;
const #35 = Asciz	(Ljava/lang/Object;)Lscala/collection/mutable/IndexedSeq;;
const #36 = class	#4;	//  "[D"
const #37 = Asciz	([D)Lscala/collection/mutable/WrappedArray;;
const #38 = NameAndType	#34:#37;//  toCollection:([D)Lscala/collection/mutable/WrappedArray;
const #39 = Method	#10.#38;	//  scala/collection/mutable/ArrayOps$ofDouble.toCollection:([D)Lscala/collection/mutable/WrappedArray;
const #40 = Asciz	Ljava/lang/Object;;
const #41 = Asciz	(Ljava/lang/Object;)Lscala/collection/IndexedSeq;;
const #42 = Asciz	(Ljava/lang/Object;)Lscala/collection/Seq;;
const #43 = Asciz	(Ljava/lang/Object;)Lscala/collection/Iterable;;
const #44 = Asciz	(Ljava/lang/Object;)Lscala/collection/Traversable;;
const #45 = Asciz	newBuilder;
const #46 = Asciz	()Lscala/collection/mutable/Builder;;
const #47 = Asciz	()Lscala/collection/mutable/ArrayBuilder$ofDouble;;
const #48 = NameAndType	#45:#47;//  newBuilder:()Lscala/collection/mutable/ArrayBuilder$ofDouble;
const #49 = Method	#10.#48;	//  scala/collection/mutable/ArrayOps$ofDouble.newBuilder:()Lscala/collection/mutable/ArrayBuilder$ofDouble;
const #50 = Asciz	apply;
const #51 = Asciz	(I)Ljava/lang/Object;;
const #52 = Asciz	(I)D;
const #53 = NameAndType	#50:#52;//  apply:(I)D
const #54 = Method	#10.#53;	//  scala/collection/mutable/ArrayOps$ofDouble.apply:(I)D
const #55 = Asciz	scala/runtime/BoxesRunTime;
const #56 = class	#55;	//  scala/runtime/BoxesRunTime
const #57 = Asciz	boxToDouble;
const #58 = Asciz	(D)Ljava/lang/Double;;
const #59 = NameAndType	#57:#58;//  boxToDouble:(D)Ljava/lang/Double;
const #60 = Method	#56.#59;	//  scala/runtime/BoxesRunTime.boxToDouble:(D)Ljava/lang/Double;
const #61 = Asciz	idx;
const #62 = Asciz	I;
const #63 = Asciz	update;
const #64 = Asciz	(ILjava/lang/Object;)V;
const #65 = Asciz	unboxToDouble;
const #66 = Asciz	(Ljava/lang/Object;)D;
const #67 = NameAndType	#65:#66;//  unboxToDouble:(Ljava/lang/Object;)D
const #68 = Method	#56.#67;	//  scala/runtime/BoxesRunTime.unboxToDouble:(Ljava/lang/Object;)D
const #69 = Asciz	(ID)V;
const #70 = NameAndType	#63:#69;//  update:(ID)V
const #71 = Method	#10.#70;	//  scala/collection/mutable/ArrayOps$ofDouble.update:(ID)V
const #72 = Asciz	elem;
const #73 = Asciz	index;
const #74 = Asciz	D;
const #75 = Asciz	length;
const #76 = Asciz	()I;
const #77 = Asciz	scala/collection/mutable/ArrayBuilder$ofDouble;
const #78 = class	#77;	//  scala/collection/mutable/ArrayBuilder$ofDouble
const #79 = Method	#78.#16;	//  scala/collection/mutable/ArrayBuilder$ofDouble."<init>":()V
const #80 = Asciz	scala/collection/mutable/WrappedArray$ofDouble;
const #81 = class	#80;	//  scala/collection/mutable/WrappedArray$ofDouble
const #82 = NameAndType	#5:#6;//  "<init>":([D)V
const #83 = Method	#81.#82;	//  scala/collection/mutable/WrappedArray$ofDouble."<init>":([D)V
const #84 = Asciz	([D)Lscala/collection/mutable/WrappedArray<Ljava/lang/Double;>;;
const #85 = Asciz	Signature;
const #86 = Asciz	()Lscala/collection/mutable/WrappedArray<Ljava/lang/Double;>;;
const #87 = Asciz	Lscala/collection/mutable/ArrayOps<Ljava/lang/Double;>;Lscala/collection/mutable/ArrayLike<Ljava/lang/Double;[D>;Lscala/ScalaObject;;
const #88 = Asciz	Scala;
const #89 = Asciz	InnerClasses;
const #90 = Asciz	ofDouble;
const #91 = Asciz	scala/collection/mutable/WrappedArray;
const #92 = class	#91;	//  scala/collection/mutable/WrappedArray
const #93 = Asciz	scala/collection/mutable/ArrayBuilder;
const #94 = class	#93;	//  scala/collection/mutable/ArrayBuilder
const #95 = Asciz	scala/collection/mutable/ArrayLike;
const #96 = class	#95;	//  scala/collection/mutable/ArrayLike
const #97 = Asciz	scala/ScalaObject;
const #98 = class	#97;	//  scala/ScalaObject

{
public scala.collection.mutable.ArrayOps$ofDouble(double[]);
  Code:
   Stack=2, Locals=2, Args_size=2
   0:	aload_0
   1:	aload_1
   2:	putfield	#12; //Field repr:[D
   5:	aload_0
   6:	invokespecial	#17; //Method scala/collection/mutable/ArrayOps."<init>":()V
   9:	return
  LineNumberTable: 
   line 139: 0

  LocalVariableTable: 
   Start  Length  Slot  Name   Signature
   0      10      0    this       Lscala/collection/mutable/ArrayOps$ofDouble;
   0      10      1    repr       [D


public java.lang.Object repr();
  Code:
   Stack=1, Locals=1, Args_size=1
   0:	aload_0
   1:	invokevirtual	#24; //Method repr:()[D
   4:	areturn
  LineNumberTable: 
   line 139: 0


public scala.collection.mutable.IndexedSeq thisCollection();
  Code:
   Stack=1, Locals=1, Args_size=1
   0:	aload_0
   1:	invokevirtual	#29; //Method thisCollection:()Lscala/collection/mutable/WrappedArray;
   4:	areturn
  LineNumberTable: 
   line 139: 0


public scala.collection.IndexedSeq thisCollection();
  Code:
   Stack=1, Locals=1, Args_size=1
   0:	aload_0
   1:	invokevirtual	#29; //Method thisCollection:()Lscala/collection/mutable/WrappedArray;
   4:	areturn
  LineNumberTable: 
   line 139: 0


public scala.collection.Seq thisCollection();
  Code:
   Stack=1, Locals=1, Args_size=1
   0:	aload_0
   1:	invokevirtual	#29; //Method thisCollection:()Lscala/collection/mutable/WrappedArray;
   4:	areturn
  LineNumberTable: 
   line 139: 0


public scala.collection.Iterable thisCollection();
  Code:
   Stack=1, Locals=1, Args_size=1
   0:	aload_0
   1:	invokevirtual	#29; //Method thisCollection:()Lscala/collection/mutable/WrappedArray;
   4:	areturn
  LineNumberTable: 
   line 139: 0


public scala.collection.Traversable thisCollection();
  Code:
   Stack=1, Locals=1, Args_size=1
   0:	aload_0
   1:	invokevirtual	#29; //Method thisCollection:()Lscala/collection/mutable/WrappedArray;
   4:	areturn
  LineNumberTable: 
   line 139: 0


public scala.collection.mutable.IndexedSeq toCollection(java.lang.Object);
  Code:
   Stack=2, Locals=2, Args_size=2
   0:	aload_0
   1:	aload_1
   2:	checkcast	#36; //class "[D"
   5:	invokevirtual	#39; //Method toCollection:([D)Lscala/collection/mutable/WrappedArray;
   8:	areturn
  LineNumberTable: 
   line 139: 0

  LocalVariableTable: 
   Start  Length  Slot  Name   Signature
   0      9      0    this       Lscala/collection/mutable/ArrayOps$ofDouble;
   0      9      1    repr       Ljava/lang/Object;


public scala.collection.IndexedSeq toCollection(java.lang.Object);
  Code:
   Stack=2, Locals=2, Args_size=2
   0:	aload_0
   1:	aload_1
   2:	checkcast	#36; //class "[D"
   5:	invokevirtual	#39; //Method toCollection:([D)Lscala/collection/mutable/WrappedArray;
   8:	areturn
  LineNumberTable: 
   line 139: 0

  LocalVariableTable: 
   Start  Length  Slot  Name   Signature
   0      9      0    this       Lscala/collection/mutable/ArrayOps$ofDouble;
   0      9      1    repr       Ljava/lang/Object;


public scala.collection.Seq toCollection(java.lang.Object);
  Code:
   Stack=2, Locals=2, Args_size=2
   0:	aload_0
   1:	aload_1
   2:	checkcast	#36; //class "[D"
   5:	invokevirtual	#39; //Method toCollection:([D)Lscala/collection/mutable/WrappedArray;
   8:	areturn
  LineNumberTable: 
   line 139: 0

  LocalVariableTable: 
   Start  Length  Slot  Name   Signature
   0      9      0    this       Lscala/collection/mutable/ArrayOps$ofDouble;
   0      9      1    repr       Ljava/lang/Object;


public scala.collection.Iterable toCollection(java.lang.Object);
  Code:
   Stack=2, Locals=2, Args_size=2
   0:	aload_0
   1:	aload_1
   2:	checkcast	#36; //class "[D"
   5:	invokevirtual	#39; //Method toCollection:([D)Lscala/collection/mutable/WrappedArray;
   8:	areturn
  LineNumberTable: 
   line 139: 0

  LocalVariableTable: 
   Start  Length  Slot  Name   Signature
   0      9      0    this       Lscala/collection/mutable/ArrayOps$ofDouble;
   0      9      1    repr       Ljava/lang/Object;


public scala.collection.Traversable toCollection(java.lang.Object);
  Code:
   Stack=2, Locals=2, Args_size=2
   0:	aload_0
   1:	aload_1
   2:	checkcast	#36; //class "[D"
   5:	invokevirtual	#39; //Method toCollection:([D)Lscala/collection/mutable/WrappedArray;
   8:	areturn
  LineNumberTable: 
   line 139: 0

  LocalVariableTable: 
   Start  Length  Slot  Name   Signature
   0      9      0    this       Lscala/collection/mutable/ArrayOps$ofDouble;
   0      9      1    repr       Ljava/lang/Object;


public scala.collection.mutable.Builder newBuilder();
  Code:
   Stack=1, Locals=1, Args_size=1
   0:	aload_0
   1:	invokevirtual	#49; //Method newBuilder:()Lscala/collection/mutable/ArrayBuilder$ofDouble;
   4:	areturn
  LineNumberTable: 
   line 139: 0


public java.lang.Object apply(int);
  Code:
   Stack=2, Locals=4, Args_size=2
   0:	aload_0
   1:	iload_1
   2:	invokevirtual	#54; //Method apply:(I)D
   5:	dstore_2
   6:	dload_2
   7:	invokestatic	#60; //Method scala/runtime/BoxesRunTime.boxToDouble:(D)Ljava/lang/Double;
   10:	areturn
  LineNumberTable: 
   line 139: 0

  LocalVariableTable: 
   Start  Length  Slot  Name   Signature
   0      11      0    this       Lscala/collection/mutable/ArrayOps$ofDouble;
   0      11      1    idx       I


public void update(int, java.lang.Object);
  Code:
   Stack=4, Locals=3, Args_size=3
   0:	aload_0
   1:	iload_1
   2:	aload_2
   3:	invokestatic	#68; //Method scala/runtime/BoxesRunTime.unboxToDouble:(Ljava/lang/Object;)D
   6:	invokevirtual	#71; //Method update:(ID)V
   9:	return
  LineNumberTable: 
   line 139: 0

  LocalVariableTable: 
   Start  Length  Slot  Name   Signature
   0      10      0    this       Lscala/collection/mutable/ArrayOps$ofDouble;
   0      10      1    idx       I
   0      10      2    elem       Ljava/lang/Object;


public void update(int, double);
  Code:
   Stack=4, Locals=4, Args_size=3
   0:	aload_0
   1:	invokevirtual	#24; //Method repr:()[D
   4:	iload_1
   5:	dload_2
   6:	dastore
   7:	return
  LineNumberTable: 
   line 147: 0

  LocalVariableTable: 
   Start  Length  Slot  Name   Signature
   0      8      0    this       Lscala/collection/mutable/ArrayOps$ofDouble;
   0      8      1    index       I
   0      8      2    elem       D


public double apply(int);
  Code:
   Stack=2, Locals=2, Args_size=2
   0:	aload_0
   1:	invokevirtual	#24; //Method repr:()[D
   4:	iload_1
   5:	daload
   6:	dreturn
  LineNumberTable: 
   line 146: 0

  LocalVariableTable: 
   Start  Length  Slot  Name   Signature
   0      7      0    this       Lscala/collection/mutable/ArrayOps$ofDouble;
   0      7      1    index       I


public int length();
  Code:
   Stack=1, Locals=1, Args_size=1
   0:	aload_0
   1:	invokevirtual	#24; //Method repr:()[D
   4:	arraylength
   5:	ireturn
  LineNumberTable: 
   line 145: 0


public scala.collection.mutable.ArrayBuilder$ofDouble newBuilder();
  Code:
   Stack=2, Locals=1, Args_size=1
   0:	new	#78; //class scala/collection/mutable/ArrayBuilder$ofDouble
   3:	dup
   4:	invokespecial	#79; //Method scala/collection/mutable/ArrayBuilder$ofDouble."<init>":()V
   7:	areturn
  LineNumberTable: 
   line 143: 0


public scala.collection.mutable.WrappedArray toCollection(double[]);
  Code:
   Stack=3, Locals=2, Args_size=2
   0:	new	#81; //class scala/collection/mutable/WrappedArray$ofDouble
   3:	dup
   4:	aload_1
   5:	invokespecial	#83; //Method scala/collection/mutable/WrappedArray$ofDouble."<init>":([D)V
   8:	areturn
  LineNumberTable: 
   line 142: 0

  LocalVariableTable: 
   Start  Length  Slot  Name   Signature
   0      9      0    this       Lscala/collection/mutable/ArrayOps$ofDouble;
   0      9      1    repr       [D

  Signature: length = 0x2
   00 54 

public scala.collection.mutable.WrappedArray thisCollection();
  Code:
   Stack=3, Locals=1, Args_size=1
   0:	new	#81; //class scala/collection/mutable/WrappedArray$ofDouble
   3:	dup
   4:	aload_0
   5:	invokevirtual	#24; //Method repr:()[D
   8:	invokespecial	#83; //Method scala/collection/mutable/WrappedArray$ofDouble."<init>":([D)V
   11:	areturn
  LineNumberTable: 
   line 141: 0

  Signature: length = 0x2
   00 56 

public double[] repr();
  Code:
   Stack=1, Locals=1, Args_size=1
   0:	aload_0
   1:	getfield	#12; //Field repr:[D
   4:	areturn
  LineNumberTable: 
   line 139: 0


}

