Compiled from "ArrayOps.scala"
public class scala.collection.mutable.ArrayOps$ofDouble extends scala.collection.mutable.ArrayOps implements scala.collection.mutable.ArrayLike,scala.ScalaObject
  SourceFile: "ArrayOps.scala"
  Signature: length = 0x2
   00 57 
  Scala: length = 0x
   
  InnerClass: 
   public ofDouble=class scala/collection/mutable/ArrayOps$ofDouble of class scala/collection/mutable/ArrayOps
   public final ofDouble=class scala/collection/mutable/WrappedArray$ofDouble of class scala/collection/mutable/WrappedArray
   public ofDouble=class scala/collection/mutable/ArrayBuilder$ofDouble of class scala/collection/mutable/ArrayBuilder
  minor version: 0
  major version: 49
  Constant pool:
Asciz	SourceFile;
Asciz	ArrayOps.scala;
Asciz	repr;
Asciz	[D;
Asciz	<init>;
Asciz	([D)V;
Asciz	Code;
Asciz	LineNumberTable;
Asciz	scala/collection/mutable/ArrayOps$ofDouble;
class	scala/collection/mutable/ArrayOps$ofDouble
NameAndType	repr:[D
Field	scala/collection/mutable/ArrayOps$ofDouble.repr:[D
Asciz	scala/collection/mutable/ArrayOps;
class	scala/collection/mutable/ArrayOps
Asciz	()V;
NameAndType	"<init>":()V
Method	scala/collection/mutable/ArrayOps."<init>":()V
Asciz	this;
Asciz	Lscala/collection/mutable/ArrayOps$ofDouble;;
Asciz	LocalVariableTable;
Asciz	()Ljava/lang/Object;;
Asciz	()[D;
NameAndType	repr:()[D
Method	scala/collection/mutable/ArrayOps$ofDouble.repr:()[D
Asciz	thisCollection;
Asciz	()Lscala/collection/mutable/IndexedSeq;;
Asciz	()Lscala/collection/mutable/WrappedArray;;
NameAndType	thisCollection:()Lscala/collection/mutable/WrappedArray;
Method	scala/collection/mutable/ArrayOps$ofDouble.thisCollection:()Lscala/collection/mutable/WrappedArray;
Asciz	()Lscala/collection/IndexedSeq;;
Asciz	()Lscala/collection/Seq;;
Asciz	()Lscala/collection/Iterable;;
Asciz	()Lscala/collection/Traversable;;
Asciz	toCollection;
Asciz	(Ljava/lang/Object;)Lscala/collection/mutable/IndexedSeq;;
class	"[D"
Asciz	([D)Lscala/collection/mutable/WrappedArray;;
NameAndType	toCollection:([D)Lscala/collection/mutable/WrappedArray;
Method	scala/collection/mutable/ArrayOps$ofDouble.toCollection:([D)Lscala/collection/mutable/WrappedArray;
Asciz	Ljava/lang/Object;;
Asciz	(Ljava/lang/Object;)Lscala/collection/IndexedSeq;;
Asciz	(Ljava/lang/Object;)Lscala/collection/Seq;;
Asciz	(Ljava/lang/Object;)Lscala/collection/Iterable;;
Asciz	(Ljava/lang/Object;)Lscala/collection/Traversable;;
Asciz	newBuilder;
Asciz	()Lscala/collection/mutable/Builder;;
Asciz	()Lscala/collection/mutable/ArrayBuilder$ofDouble;;
NameAndType	newBuilder:()Lscala/collection/mutable/ArrayBuilder$ofDouble;
Method	scala/collection/mutable/ArrayOps$ofDouble.newBuilder:()Lscala/collection/mutable/ArrayBuilder$ofDouble;
Asciz	apply;
Asciz	(I)Ljava/lang/Object;;
Asciz	(I)D;
NameAndType	apply:(I)D
Method	scala/collection/mutable/ArrayOps$ofDouble.apply:(I)D
Asciz	scala/runtime/BoxesRunTime;
class	scala/runtime/BoxesRunTime
Asciz	boxToDouble;
Asciz	(D)Ljava/lang/Double;;
NameAndType	boxToDouble:(D)Ljava/lang/Double;
Method	scala/runtime/BoxesRunTime.boxToDouble:(D)Ljava/lang/Double;
Asciz	idx;
Asciz	I;
Asciz	update;
Asciz	(ILjava/lang/Object;)V;
Asciz	unboxToDouble;
Asciz	(Ljava/lang/Object;)D;
NameAndType	unboxToDouble:(Ljava/lang/Object;)D
Method	scala/runtime/BoxesRunTime.unboxToDouble:(Ljava/lang/Object;)D
Asciz	(ID)V;
NameAndType	update:(ID)V
Method	scala/collection/mutable/ArrayOps$ofDouble.update:(ID)V
Asciz	elem;
Asciz	index;
Asciz	D;
Asciz	length;
Asciz	()I;
Asciz	scala/collection/mutable/ArrayBuilder$ofDouble;
class	scala/collection/mutable/ArrayBuilder$ofDouble
Method	scala/collection/mutable/ArrayBuilder$ofDouble."<init>":()V
Asciz	scala/collection/mutable/WrappedArray$ofDouble;
class	scala/collection/mutable/WrappedArray$ofDouble
NameAndType	"<init>":([D)V
Method	scala/collection/mutable/WrappedArray$ofDouble."<init>":([D)V
Asciz	([D)Lscala/collection/mutable/WrappedArray<Ljava/lang/Double;>;;
Asciz	Signature;
Asciz	()Lscala/collection/mutable/WrappedArray<Ljava/lang/Double;>;;
Asciz	Lscala/collection/mutable/ArrayOps<Ljava/lang/Double;>;Lscala/collection/mutable/ArrayLike<Ljava/lang/Double;[D>;Lscala/ScalaObject;;
Asciz	Scala;
Asciz	InnerClasses;
Asciz	ofDouble;
Asciz	scala/collection/mutable/WrappedArray;
class	scala/collection/mutable/WrappedArray
Asciz	scala/collection/mutable/ArrayBuilder;
class	scala/collection/mutable/ArrayBuilder
Asciz	scala/collection/mutable/ArrayLike;
class	scala/collection/mutable/ArrayLike
Asciz	scala/ScalaObject;
class	scala/ScalaObject

{
private final double[] repr;
  Signature: [D

public scala.collection.mutable.ArrayOps$ofDouble(double[]);
  Signature: ([D)V
  Code:
   Stack=2, Locals=2, Args_size=2
	aload_0
	aload_1
	putfield	Field repr:[D
	aload_0
	invokespecial	Method scala/collection/mutable/ArrayOps."<init>":()V
	return
  Labels:
  LocalVariableTable: 
   Start  Length  Slot  Name   Signature
   0      10      0    this       Lscala/collection/mutable/ArrayOps$ofDouble;
   0      10      1    repr       [D


public java.lang.Object repr();
  Signature: ()Ljava/lang/Object;
  Code:
   Stack=1, Locals=1, Args_size=1
	aload_0
	invokevirtual	Method repr:()[D
	areturn
  Labels:

public scala.collection.mutable.IndexedSeq thisCollection();
  Signature: ()Lscala/collection/mutable/IndexedSeq;
  Code:
   Stack=1, Locals=1, Args_size=1
	aload_0
	invokevirtual	Method thisCollection:()Lscala/collection/mutable/WrappedArray;
	areturn
  Labels:

public scala.collection.IndexedSeq thisCollection();
  Signature: ()Lscala/collection/IndexedSeq;
  Code:
   Stack=1, Locals=1, Args_size=1
	aload_0
	invokevirtual	Method thisCollection:()Lscala/collection/mutable/WrappedArray;
	areturn
  Labels:

public scala.collection.Seq thisCollection();
  Signature: ()Lscala/collection/Seq;
  Code:
   Stack=1, Locals=1, Args_size=1
	aload_0
	invokevirtual	Method thisCollection:()Lscala/collection/mutable/WrappedArray;
	areturn
  Labels:

public scala.collection.Iterable thisCollection();
  Signature: ()Lscala/collection/Iterable;
  Code:
   Stack=1, Locals=1, Args_size=1
	aload_0
	invokevirtual	Method thisCollection:()Lscala/collection/mutable/WrappedArray;
	areturn
  Labels:

public scala.collection.Traversable thisCollection();
  Signature: ()Lscala/collection/Traversable;
  Code:
   Stack=1, Locals=1, Args_size=1
	aload_0
	invokevirtual	Method thisCollection:()Lscala/collection/mutable/WrappedArray;
	areturn
  Labels:

public scala.collection.mutable.IndexedSeq toCollection(java.lang.Object);
  Signature: (Ljava/lang/Object;)Lscala/collection/mutable/IndexedSeq;
  Code:
   Stack=2, Locals=2, Args_size=2
	aload_0
	aload_1
	checkcast	class "[D"
	invokevirtual	Method toCollection:([D)Lscala/collection/mutable/WrappedArray;
	areturn
  Labels:
  LocalVariableTable: 
   Start  Length  Slot  Name   Signature
   0      9      0    this       Lscala/collection/mutable/ArrayOps$ofDouble;
   0      9      1    repr       Ljava/lang/Object;


public scala.collection.IndexedSeq toCollection(java.lang.Object);
  Signature: (Ljava/lang/Object;)Lscala/collection/IndexedSeq;
  Code:
   Stack=2, Locals=2, Args_size=2
	aload_0
	aload_1
	checkcast	class "[D"
	invokevirtual	Method toCollection:([D)Lscala/collection/mutable/WrappedArray;
	areturn
  Labels:
  LocalVariableTable: 
   Start  Length  Slot  Name   Signature
   0      9      0    this       Lscala/collection/mutable/ArrayOps$ofDouble;
   0      9      1    repr       Ljava/lang/Object;


public scala.collection.Seq toCollection(java.lang.Object);
  Signature: (Ljava/lang/Object;)Lscala/collection/Seq;
  Code:
   Stack=2, Locals=2, Args_size=2
	aload_0
	aload_1
	checkcast	class "[D"
	invokevirtual	Method toCollection:([D)Lscala/collection/mutable/WrappedArray;
	areturn
  Labels:
  LocalVariableTable: 
   Start  Length  Slot  Name   Signature
   0      9      0    this       Lscala/collection/mutable/ArrayOps$ofDouble;
   0      9      1    repr       Ljava/lang/Object;


public scala.collection.Iterable toCollection(java.lang.Object);
  Signature: (Ljava/lang/Object;)Lscala/collection/Iterable;
  Code:
   Stack=2, Locals=2, Args_size=2
	aload_0
	aload_1
	checkcast	class "[D"
	invokevirtual	Method toCollection:([D)Lscala/collection/mutable/WrappedArray;
	areturn
  Labels:
  LocalVariableTable: 
   Start  Length  Slot  Name   Signature
   0      9      0    this       Lscala/collection/mutable/ArrayOps$ofDouble;
   0      9      1    repr       Ljava/lang/Object;


public scala.collection.Traversable toCollection(java.lang.Object);
  Signature: (Ljava/lang/Object;)Lscala/collection/Traversable;
  Code:
   Stack=2, Locals=2, Args_size=2
	aload_0
	aload_1
	checkcast	class "[D"
	invokevirtual	Method toCollection:([D)Lscala/collection/mutable/WrappedArray;
	areturn
  Labels:
  LocalVariableTable: 
   Start  Length  Slot  Name   Signature
   0      9      0    this       Lscala/collection/mutable/ArrayOps$ofDouble;
   0      9      1    repr       Ljava/lang/Object;


public scala.collection.mutable.Builder newBuilder();
  Signature: ()Lscala/collection/mutable/Builder;
  Code:
   Stack=1, Locals=1, Args_size=1
	aload_0
	invokevirtual	Method newBuilder:()Lscala/collection/mutable/ArrayBuilder$ofDouble;
	areturn
  Labels:

public java.lang.Object apply(int);
  Signature: (I)Ljava/lang/Object;
  Code:
   Stack=2, Locals=4, Args_size=2
	aload_0
	iload_1
	invokevirtual	Method apply:(I)D
	dstore_2
	dload_2
	invokestatic	Method scala/runtime/BoxesRunTime.boxToDouble:(D)Ljava/lang/Double;
	areturn
  Labels:
  LocalVariableTable: 
   Start  Length  Slot  Name   Signature
   0      11      0    this       Lscala/collection/mutable/ArrayOps$ofDouble;
   0      11      1    idx       I


public void update(int, java.lang.Object);
  Signature: (ILjava/lang/Object;)V
  Code:
   Stack=4, Locals=3, Args_size=3
	aload_0
	iload_1
	aload_2
	invokestatic	Method scala/runtime/BoxesRunTime.unboxToDouble:(Ljava/lang/Object;)D
	invokevirtual	Method update:(ID)V
	return
  Labels:
  LocalVariableTable: 
   Start  Length  Slot  Name   Signature
   0      10      0    this       Lscala/collection/mutable/ArrayOps$ofDouble;
   0      10      1    idx       I
   0      10      2    elem       Ljava/lang/Object;


public void update(int, double);
  Signature: (ID)V
  Code:
   Stack=4, Locals=4, Args_size=3
	aload_0
	invokevirtual	Method repr:()[D
	iload_1
	dload_2
	dastore
	return
  Labels:
  LocalVariableTable: 
   Start  Length  Slot  Name   Signature
   0      8      0    this       Lscala/collection/mutable/ArrayOps$ofDouble;
   0      8      1    index       I
   0      8      2    elem       D


public double apply(int);
  Signature: (I)D
  Code:
   Stack=2, Locals=2, Args_size=2
	aload_0
	invokevirtual	Method repr:()[D
	iload_1
	daload
	dreturn
  Labels:
  LocalVariableTable: 
   Start  Length  Slot  Name   Signature
   0      7      0    this       Lscala/collection/mutable/ArrayOps$ofDouble;
   0      7      1    index       I


public int length();
  Signature: ()I
  Code:
   Stack=1, Locals=1, Args_size=1
	aload_0
	invokevirtual	Method repr:()[D
	arraylength
	ireturn
  Labels:

public scala.collection.mutable.ArrayBuilder$ofDouble newBuilder();
  Signature: ()Lscala/collection/mutable/ArrayBuilder$ofDouble;
  Code:
   Stack=2, Locals=1, Args_size=1
	new	class scala/collection/mutable/ArrayBuilder$ofDouble
	dup
	invokespecial	Method scala/collection/mutable/ArrayBuilder$ofDouble."<init>":()V
	areturn
  Labels:

public scala.collection.mutable.WrappedArray toCollection(double[]);
  Signature: ([D)Lscala/collection/mutable/WrappedArray;
  Code:
   Stack=3, Locals=2, Args_size=2
	new	class scala/collection/mutable/WrappedArray$ofDouble
	dup
	aload_1
	invokespecial	Method scala/collection/mutable/WrappedArray$ofDouble."<init>":([D)V
	areturn
  Labels:
  LocalVariableTable: 
   Start  Length  Slot  Name   Signature
   0      9      0    this       Lscala/collection/mutable/ArrayOps$ofDouble;
   0      9      1    repr       [D

  Signature: length = 0x2
   00 54 

public scala.collection.mutable.WrappedArray thisCollection();
  Signature: ()Lscala/collection/mutable/WrappedArray;
  Code:
   Stack=3, Locals=1, Args_size=1
	new	class scala/collection/mutable/WrappedArray$ofDouble
	dup
	aload_0
	invokevirtual	Method repr:()[D
	invokespecial	Method scala/collection/mutable/WrappedArray$ofDouble."<init>":([D)V
	areturn
  Labels:
  Signature: length = 0x2
   00 56 

public double[] repr();
  Signature: ()[D
  Code:
   Stack=1, Locals=1, Args_size=1
	aload_0
	getfield	Field repr:[D
	areturn
  Labels:

}

