Compiled from "ArrayOps.scala"
public class scala.collection.mutable.ArrayOps$ofUnit extends scala.collection.mutable.ArrayOps implements scala.collection.mutable.ArrayLike,scala.ScalaObject
  SourceFile: "ArrayOps.scala"
  Signature: length = 0x2
   00 52 
  Scala: length = 0x
   
  InnerClass: 
   public ofUnit=class scala/collection/mutable/ArrayOps$ofUnit of class scala/collection/mutable/ArrayOps
   public ofUnit=class scala/collection/mutable/ArrayBuilder$ofUnit of class scala/collection/mutable/ArrayBuilder
   public final ofUnit=class scala/collection/mutable/WrappedArray$ofUnit of class scala/collection/mutable/WrappedArray
  minor version: 0
  major version: 49
  Constant pool:
Asciz	SourceFile;
Asciz	ArrayOps.scala;
Asciz	repr;
Asciz	[Lscala/runtime/BoxedUnit;;
Asciz	()[Lscala/runtime/BoxedUnit;;
Asciz	Code;
Asciz	LineNumberTable;
Asciz	scala/collection/mutable/ArrayOps$ofUnit;
class	scala/collection/mutable/ArrayOps$ofUnit
NameAndType	repr:[Lscala/runtime/BoxedUnit;
Field	scala/collection/mutable/ArrayOps$ofUnit.repr:[Lscala/runtime/BoxedUnit;
Asciz	thisCollection;
Asciz	()Lscala/collection/mutable/WrappedArray;;
Asciz	scala/collection/mutable/WrappedArray$ofUnit;
class	scala/collection/mutable/WrappedArray$ofUnit
NameAndType	repr:()[Lscala/runtime/BoxedUnit;
Method	scala/collection/mutable/ArrayOps$ofUnit.repr:()[Lscala/runtime/BoxedUnit;
Asciz	<init>;
Asciz	([Lscala/runtime/BoxedUnit;)V;
NameAndType	"<init>":([Lscala/runtime/BoxedUnit;)V
Method	scala/collection/mutable/WrappedArray$ofUnit."<init>":([Lscala/runtime/BoxedUnit;)V
Asciz	()Lscala/collection/mutable/WrappedArray<Ljava/lang/Object;>;;
Asciz	Signature;
Asciz	toCollection;
Asciz	([Lscala/runtime/BoxedUnit;)Lscala/collection/mutable/WrappedArray;;
Asciz	this;
Asciz	Lscala/collection/mutable/ArrayOps$ofUnit;;
Asciz	LocalVariableTable;
Asciz	([Lscala/runtime/BoxedUnit;)Lscala/collection/mutable/WrappedArray<Ljava/lang/Object;>;;
Asciz	newBuilder;
Asciz	()Lscala/collection/mutable/ArrayBuilder$ofUnit;;
Asciz	scala/collection/mutable/ArrayBuilder$ofUnit;
class	scala/collection/mutable/ArrayBuilder$ofUnit
Asciz	()V;
NameAndType	"<init>":()V
Method	scala/collection/mutable/ArrayBuilder$ofUnit."<init>":()V
Asciz	length;
Asciz	()I;
Asciz	apply;
Asciz	(I)V;
Asciz	index;
Asciz	I;
Asciz	update;
Asciz	(ILscala/runtime/BoxedUnit;)V;
Asciz	elem;
Asciz	Lscala/runtime/BoxedUnit;;
Asciz	(ILjava/lang/Object;)V;
Asciz	scala/runtime/BoxedUnit;
class	scala/runtime/BoxedUnit
NameAndType	update:(ILscala/runtime/BoxedUnit;)V
Method	scala/collection/mutable/ArrayOps$ofUnit.update:(ILscala/runtime/BoxedUnit;)V
Asciz	idx;
Asciz	Ljava/lang/Object;;
Asciz	(I)Ljava/lang/Object;;
NameAndType	apply:(I)V
Method	scala/collection/mutable/ArrayOps$ofUnit.apply:(I)V
Asciz	UNIT;
NameAndType	UNIT:Lscala/runtime/BoxedUnit;
Field	scala/runtime/BoxedUnit.UNIT:Lscala/runtime/BoxedUnit;
Asciz	()Lscala/collection/mutable/Builder;;
NameAndType	newBuilder:()Lscala/collection/mutable/ArrayBuilder$ofUnit;
Method	scala/collection/mutable/ArrayOps$ofUnit.newBuilder:()Lscala/collection/mutable/ArrayBuilder$ofUnit;
Asciz	(Ljava/lang/Object;)Lscala/collection/Traversable;;
class	"[Lscala/runtime/BoxedUnit;"
NameAndType	toCollection:([Lscala/runtime/BoxedUnit;)Lscala/collection/mutable/WrappedArray;
Method	scala/collection/mutable/ArrayOps$ofUnit.toCollection:([Lscala/runtime/BoxedUnit;)Lscala/collection/mutable/WrappedArray;
Asciz	(Ljava/lang/Object;)Lscala/collection/Iterable;;
Asciz	(Ljava/lang/Object;)Lscala/collection/Seq;;
Asciz	(Ljava/lang/Object;)Lscala/collection/IndexedSeq;;
Asciz	(Ljava/lang/Object;)Lscala/collection/mutable/IndexedSeq;;
Asciz	()Lscala/collection/Traversable;;
NameAndType	thisCollection:()Lscala/collection/mutable/WrappedArray;
Method	scala/collection/mutable/ArrayOps$ofUnit.thisCollection:()Lscala/collection/mutable/WrappedArray;
Asciz	()Lscala/collection/Iterable;;
Asciz	()Lscala/collection/Seq;;
Asciz	()Lscala/collection/IndexedSeq;;
Asciz	()Lscala/collection/mutable/IndexedSeq;;
Asciz	()Ljava/lang/Object;;
Asciz	scala/collection/mutable/ArrayOps;
class	scala/collection/mutable/ArrayOps
Method	scala/collection/mutable/ArrayOps."<init>":()V
Asciz	Lscala/collection/mutable/ArrayOps<Ljava/lang/Object;>;Lscala/collection/mutable/ArrayLike<Ljava/lang/Object;[Lscala/runtime/BoxedUnit;>;Lscala/ScalaObject;;
Asciz	Scala;
Asciz	InnerClasses;
Asciz	ofUnit;
Asciz	scala/collection/mutable/ArrayBuilder;
class	scala/collection/mutable/ArrayBuilder
Asciz	scala/collection/mutable/WrappedArray;
class	scala/collection/mutable/WrappedArray
Asciz	scala/collection/mutable/ArrayLike;
class	scala/collection/mutable/ArrayLike
Asciz	scala/ScalaObject;
class	scala/ScalaObject

{
private final scala.runtime.BoxedUnit[] repr;
  Signature: [Lscala/runtime/BoxedUnit;

public scala.runtime.BoxedUnit[] repr();
  Signature: ()[Lscala/runtime/BoxedUnit;
  Code:
   Stack=1, Locals=1, Args_size=1
	aload_0
	getfield	Field repr:[Lscala/runtime/BoxedUnit;
	areturn
  Labels:

public scala.collection.mutable.WrappedArray thisCollection();
  Signature: ()Lscala/collection/mutable/WrappedArray;
  Code:
   Stack=3, Locals=1, Args_size=1
	new	class scala/collection/mutable/WrappedArray$ofUnit
	dup
	aload_0
	invokevirtual	Method repr:()[Lscala/runtime/BoxedUnit;
	invokespecial	Method scala/collection/mutable/WrappedArray$ofUnit."<init>":([Lscala/runtime/BoxedUnit;)V
	areturn
  Labels:
  Signature: length = 0x2
   00 16 

public scala.collection.mutable.WrappedArray toCollection(scala.runtime.BoxedUnit[]);
  Signature: ([Lscala/runtime/BoxedUnit;)Lscala/collection/mutable/WrappedArray;
  Code:
   Stack=3, Locals=2, Args_size=2
	new	class scala/collection/mutable/WrappedArray$ofUnit
	dup
	aload_1
	invokespecial	Method scala/collection/mutable/WrappedArray$ofUnit."<init>":([Lscala/runtime/BoxedUnit;)V
	areturn
  Labels:
  LocalVariableTable: 
   Start  Length  Slot  Name   Signature
   0      9      0    this       Lscala/collection/mutable/ArrayOps$ofUnit;
   0      9      1    repr       [Lscala/runtime/BoxedUnit;

  Signature: length = 0x2
   00 1D 

public scala.collection.mutable.ArrayBuilder$ofUnit newBuilder();
  Signature: ()Lscala/collection/mutable/ArrayBuilder$ofUnit;
  Code:
   Stack=2, Locals=1, Args_size=1
	new	class scala/collection/mutable/ArrayBuilder$ofUnit
	dup
	invokespecial	Method scala/collection/mutable/ArrayBuilder$ofUnit."<init>":()V
	areturn
  Labels:

public int length();
  Signature: ()I
  Code:
   Stack=1, Locals=1, Args_size=1
	aload_0
	invokevirtual	Method repr:()[Lscala/runtime/BoxedUnit;
	arraylength
	ireturn
  Labels:

public void apply(int);
  Signature: (I)V
  Code:
   Stack=2, Locals=2, Args_size=2
	aload_0
	invokevirtual	Method repr:()[Lscala/runtime/BoxedUnit;
	iload_1
	aaload
	pop
	return
  Labels:
  LocalVariableTable: 
   Start  Length  Slot  Name   Signature
   0      8      0    this       Lscala/collection/mutable/ArrayOps$ofUnit;
   0      8      1    index       I


public void update(int, scala.runtime.BoxedUnit);
  Signature: (ILscala/runtime/BoxedUnit;)V
  Code:
   Stack=3, Locals=3, Args_size=3
	aload_0
	invokevirtual	Method repr:()[Lscala/runtime/BoxedUnit;
	iload_1
	aload_2
	aastore
	return
  Labels:
  LocalVariableTable: 
   Start  Length  Slot  Name   Signature
   0      8      0    this       Lscala/collection/mutable/ArrayOps$ofUnit;
   0      8      1    index       I
   0      8      2    elem       Lscala/runtime/BoxedUnit;


public void update(int, java.lang.Object);
  Signature: (ILjava/lang/Object;)V
  Code:
   Stack=3, Locals=3, Args_size=3
	aload_0
	iload_1
	aload_2
	checkcast	class scala/runtime/BoxedUnit
	invokevirtual	Method update:(ILscala/runtime/BoxedUnit;)V
	return
  Labels:
  LocalVariableTable: 
   Start  Length  Slot  Name   Signature
   0      10      0    this       Lscala/collection/mutable/ArrayOps$ofUnit;
   0      10      1    idx       I
   0      10      2    elem       Ljava/lang/Object;


public java.lang.Object apply(int);
  Signature: (I)Ljava/lang/Object;
  Code:
   Stack=2, Locals=2, Args_size=2
	aload_0
	iload_1
	invokevirtual	Method apply:(I)V
	getstatic	Field scala/runtime/BoxedUnit.UNIT:Lscala/runtime/BoxedUnit;
	areturn
  Labels:
  LocalVariableTable: 
   Start  Length  Slot  Name   Signature
   0      9      0    this       Lscala/collection/mutable/ArrayOps$ofUnit;
   0      9      1    idx       I


public scala.collection.mutable.Builder newBuilder();
  Signature: ()Lscala/collection/mutable/Builder;
  Code:
   Stack=1, Locals=1, Args_size=1
	aload_0
	invokevirtual	Method newBuilder:()Lscala/collection/mutable/ArrayBuilder$ofUnit;
	areturn
  Labels:

public scala.collection.Traversable toCollection(java.lang.Object);
  Signature: (Ljava/lang/Object;)Lscala/collection/Traversable;
  Code:
   Stack=2, Locals=2, Args_size=2
	aload_0
	aload_1
	checkcast	class "[Lscala/runtime/BoxedUnit;"
	invokevirtual	Method toCollection:([Lscala/runtime/BoxedUnit;)Lscala/collection/mutable/WrappedArray;
	areturn
  Labels:
  LocalVariableTable: 
   Start  Length  Slot  Name   Signature
   0      9      0    this       Lscala/collection/mutable/ArrayOps$ofUnit;
   0      9      1    repr       Ljava/lang/Object;


public scala.collection.Iterable toCollection(java.lang.Object);
  Signature: (Ljava/lang/Object;)Lscala/collection/Iterable;
  Code:
   Stack=2, Locals=2, Args_size=2
	aload_0
	aload_1
	checkcast	class "[Lscala/runtime/BoxedUnit;"
	invokevirtual	Method toCollection:([Lscala/runtime/BoxedUnit;)Lscala/collection/mutable/WrappedArray;
	areturn
  Labels:
  LocalVariableTable: 
   Start  Length  Slot  Name   Signature
   0      9      0    this       Lscala/collection/mutable/ArrayOps$ofUnit;
   0      9      1    repr       Ljava/lang/Object;


public scala.collection.Seq toCollection(java.lang.Object);
  Signature: (Ljava/lang/Object;)Lscala/collection/Seq;
  Code:
   Stack=2, Locals=2, Args_size=2
	aload_0
	aload_1
	checkcast	class "[Lscala/runtime/BoxedUnit;"
	invokevirtual	Method toCollection:([Lscala/runtime/BoxedUnit;)Lscala/collection/mutable/WrappedArray;
	areturn
  Labels:
  LocalVariableTable: 
   Start  Length  Slot  Name   Signature
   0      9      0    this       Lscala/collection/mutable/ArrayOps$ofUnit;
   0      9      1    repr       Ljava/lang/Object;


public scala.collection.IndexedSeq toCollection(java.lang.Object);
  Signature: (Ljava/lang/Object;)Lscala/collection/IndexedSeq;
  Code:
   Stack=2, Locals=2, Args_size=2
	aload_0
	aload_1
	checkcast	class "[Lscala/runtime/BoxedUnit;"
	invokevirtual	Method toCollection:([Lscala/runtime/BoxedUnit;)Lscala/collection/mutable/WrappedArray;
	areturn
  Labels:
  LocalVariableTable: 
   Start  Length  Slot  Name   Signature
   0      9      0    this       Lscala/collection/mutable/ArrayOps$ofUnit;
   0      9      1    repr       Ljava/lang/Object;


public scala.collection.mutable.IndexedSeq toCollection(java.lang.Object);
  Signature: (Ljava/lang/Object;)Lscala/collection/mutable/IndexedSeq;
  Code:
   Stack=2, Locals=2, Args_size=2
	aload_0
	aload_1
	checkcast	class "[Lscala/runtime/BoxedUnit;"
	invokevirtual	Method toCollection:([Lscala/runtime/BoxedUnit;)Lscala/collection/mutable/WrappedArray;
	areturn
  Labels:
  LocalVariableTable: 
   Start  Length  Slot  Name   Signature
   0      9      0    this       Lscala/collection/mutable/ArrayOps$ofUnit;
   0      9      1    repr       Ljava/lang/Object;


public scala.collection.Traversable thisCollection();
  Signature: ()Lscala/collection/Traversable;
  Code:
   Stack=1, Locals=1, Args_size=1
	aload_0
	invokevirtual	Method thisCollection:()Lscala/collection/mutable/WrappedArray;
	areturn
  Labels:

public scala.collection.Iterable thisCollection();
  Signature: ()Lscala/collection/Iterable;
  Code:
   Stack=1, Locals=1, Args_size=1
	aload_0
	invokevirtual	Method thisCollection:()Lscala/collection/mutable/WrappedArray;
	areturn
  Labels:

public scala.collection.Seq thisCollection();
  Signature: ()Lscala/collection/Seq;
  Code:
   Stack=1, Locals=1, Args_size=1
	aload_0
	invokevirtual	Method thisCollection:()Lscala/collection/mutable/WrappedArray;
	areturn
  Labels:

public scala.collection.IndexedSeq thisCollection();
  Signature: ()Lscala/collection/IndexedSeq;
  Code:
   Stack=1, Locals=1, Args_size=1
	aload_0
	invokevirtual	Method thisCollection:()Lscala/collection/mutable/WrappedArray;
	areturn
  Labels:

public scala.collection.mutable.IndexedSeq thisCollection();
  Signature: ()Lscala/collection/mutable/IndexedSeq;
  Code:
   Stack=1, Locals=1, Args_size=1
	aload_0
	invokevirtual	Method thisCollection:()Lscala/collection/mutable/WrappedArray;
	areturn
  Labels:

public java.lang.Object repr();
  Signature: ()Ljava/lang/Object;
  Code:
   Stack=1, Locals=1, Args_size=1
	aload_0
	invokevirtual	Method repr:()[Lscala/runtime/BoxedUnit;
	areturn
  Labels:

public scala.collection.mutable.ArrayOps$ofUnit(scala.runtime.BoxedUnit[]);
  Signature: ([Lscala/runtime/BoxedUnit;)V
  Code:
   Stack=2, Locals=2, Args_size=2
	aload_0
	aload_1
	putfield	Field repr:[Lscala/runtime/BoxedUnit;
	aload_0
	invokespecial	Method scala/collection/mutable/ArrayOps."<init>":()V
	return
  Labels:
  LocalVariableTable: 
   Start  Length  Slot  Name   Signature
   0      10      0    this       Lscala/collection/mutable/ArrayOps$ofUnit;
   0      10      1    repr       [Lscala/runtime/BoxedUnit;


}

