Compiled from "ArrayStack.scala"
public final class scala.collection.mutable.ArrayStack$$anonfun$$plus$plus$eq$2 extends scala.runtime.AbstractFunction1 implements java.io.Serializable
  SourceFile: "ArrayStack.scala"
  Scala: length = 0x
   
  InnerClass: 
   public final $anonfun$$plus$plus$eq$2=class scala/collection/mutable/ArrayStack$$anonfun$$plus$plus$eq$2 of class scala/collection/mutable/ArrayStack
  minor version: 0
  major version: 49
  Constant pool:
Asciz	SourceFile;
Asciz	ArrayStack.scala;
Asciz	<clinit>;
Asciz	()V;
Asciz	Code;
Asciz	serialVersionUID;
Asciz	J;
Asciz	scala/collection/mutable/ArrayStack$$anonfun$$plus$plus$eq$2;
class	scala/collection/mutable/ArrayStack$$anonfun$$plus$plus$eq$2
NameAndType	serialVersionUID:J
Field	scala/collection/mutable/ArrayStack$$anonfun$$plus$plus$eq$2.serialVersionUID:J
Asciz	$outer;
Asciz	Lscala/collection/mutable/ArrayStack;;
Asciz	apply;
Asciz	(Ljava/lang/Object;)Lscala/collection/mutable/ArrayStack;;
Asciz	LineNumberTable;
NameAndType	$outer:Lscala/collection/mutable/ArrayStack;
Field	scala/collection/mutable/ArrayStack$$anonfun$$plus$plus$eq$2.$outer:Lscala/collection/mutable/ArrayStack;
Asciz	scala/collection/mutable/ArrayStack;
class	scala/collection/mutable/ArrayStack
Asciz	$plus$eq;
NameAndType	$plus$eq:(Ljava/lang/Object;)Lscala/collection/mutable/ArrayStack;
Method	scala/collection/mutable/ArrayStack.$plus$eq:(Ljava/lang/Object;)Lscala/collection/mutable/ArrayStack;
Asciz	(TT;)Lscala/collection/mutable/ArrayStack<TT;>;;
Asciz	Signature;
Asciz	(Ljava/lang/Object;)Ljava/lang/Object;;
NameAndType	apply:(Ljava/lang/Object;)Lscala/collection/mutable/ArrayStack;
Method	scala/collection/mutable/ArrayStack$$anonfun$$plus$plus$eq$2.apply:(Ljava/lang/Object;)Lscala/collection/mutable/ArrayStack;
Asciz	this;
Asciz	Lscala/collection/mutable/ArrayStack$$anonfun$$plus$plus$eq$2;;
Asciz	v1;
Asciz	Ljava/lang/Object;;
Asciz	LocalVariableTable;
Asciz	<init>;
Asciz	(Lscala/collection/mutable/ArrayStack;)V;
Asciz	java/lang/NullPointerException;
class	java/lang/NullPointerException
NameAndType	"<init>":()V
Method	java/lang/NullPointerException."<init>":()V
Asciz	scala/runtime/AbstractFunction1;
class	scala/runtime/AbstractFunction1
Method	scala/runtime/AbstractFunction1."<init>":()V
Asciz	(Lscala/collection/mutable/ArrayStack<TT;>;)V;
Asciz	Scala;
Asciz	InnerClasses;
Asciz	$anonfun$$plus$plus$eq$2;
Asciz	java/io/Serializable;
class	java/io/Serializable

{
public static final long serialVersionUID;
  Signature: J

private final scala.collection.mutable.ArrayStack $outer;
  Signature: Lscala/collection/mutable/ArrayStack;

public static {};
  Signature: ()V
  Code:
   Stack=2, Locals=0, Args_size=0
	lconst_0
	putstatic	Field serialVersionUID:J
	return
  Labels:

public final scala.collection.mutable.ArrayStack apply(java.lang.Object);
  Signature: (Ljava/lang/Object;)Lscala/collection/mutable/ArrayStack;
  Code:
   Stack=2, Locals=2, Args_size=2
	aload_0
	getfield	Field $outer:Lscala/collection/mutable/ArrayStack;
	aload_1
	invokevirtual	Method scala/collection/mutable/ArrayStack.$plus$eq:(Ljava/lang/Object;)Lscala/collection/mutable/ArrayStack;
	areturn
  Labels:
  Signature: length = 0x2
   00 18 

public final java.lang.Object apply(java.lang.Object);
  Signature: (Ljava/lang/Object;)Ljava/lang/Object;
  Code:
   Stack=2, Locals=2, Args_size=2
	aload_0
	aload_1
	invokevirtual	Method apply:(Ljava/lang/Object;)Lscala/collection/mutable/ArrayStack;
	areturn
  Labels:
  LocalVariableTable: 
   Start  Length  Slot  Name   Signature
   0      6      0    this       Lscala/collection/mutable/ArrayStack$$anonfun$$plus$plus$eq$2;
   0      6      1    v1       Ljava/lang/Object;


public scala.collection.mutable.ArrayStack$$anonfun$$plus$plus$eq$2(scala.collection.mutable.ArrayStack);
  Signature: (Lscala/collection/mutable/ArrayStack;)V
  Code:
   Stack=2, Locals=2, Args_size=2
	aload_1
	ifnonnull	l1 // aload_0
	new	class java/lang/NullPointerException
	dup
	invokespecial	Method java/lang/NullPointerException."<init>":()V
	athrow
l1	aload_0
	aload_1
	putfield	Field $outer:Lscala/collection/mutable/ArrayStack;
	aload_0
	invokespecial	Method scala/runtime/AbstractFunction1."<init>":()V
	return
  Labels:
   	l1 = 12 // aload_0
  LocalVariableTable: 
   Start  Length  Slot  Name   Signature
   0      22      0    this       Lscala/collection/mutable/ArrayStack$$anonfun$$plus$plus$eq$2;
   0      22      1    $outer       Lscala/collection/mutable/ArrayStack;

  Signature: length = 0x2
   00 2B 

}

