Compiled from "ArrayOps.scala"
public abstract class scala.collection.mutable.ArrayOps extends java.lang.Object implements scala.collection.mutable.ArrayLike,scala.ScalaObject
  SourceFile: "ArrayOps.scala"
  Signature: length = 0x2
   03 2E 
  ScalaSig: length = 0xCCB
   05 00 FFFFFF83 3E 06 05 01 02 FFFFFF81 00 09 02 08 41 72 72
   61 79 4F 70 73 0A 02 03 04 01 07 6D 75 74 61 62
   6C 65 0A 02 05 06 01 0A 63 6F 6C 6C 65 63 74 69
   6F 6E 0A 01 07 01 05 73 63 61 6C 61 03 00 15 02
   0A 19 13 04 00 0B 13 26 10 02 0C 11 0D 01 0D 0A
   02 0E 0F 01 04 6C 61 6E 67 0A 01 10 01 04 6A 61
   76 61 09 02 12 0D 02 06 4F 62 6A 65 63 74 10 04
   14 15 17 23 0D 01 02 09 02 16 02 02 09 41 72 72
   61 79 4C 69 6B 65 10 02 18 19 0C 00 04 08 1A 00
   FFFFFF84 FFFFFF80 FFFFFF80 FFFFFFC2 00 1B 02 01 54 11 02 1C 20 10 02 1D
   1E 0D 01 06 09 02 1F 06 02 07 4E 6F 74 68 69 6E
   67 10 02 1D 21 09 02 22 06 02 03 41 6E 79 10 03
   1D 24 17 09 02 25 06 02 05 41 72 72 61 79 10 02
   1D 27 09 02 28 06 02 0B 53 63 61 6C 61 4F 62 6A
   65 63 74 08 05 2A 00 FFFFFF84 00 2B 01 06 3C 69 6E 69
   74 3E 14 01 2C 10 03 14 00 17 08 05 2E 00 FFFFFF84 04
   2F 01 0A 72 6F 77 42 75 69 6C 64 65 72 15 02 30
   34 10 04 14 31 33 36 09 02 32 02 02 07 42 75 69
   6C 64 65 72 10 02 18 34 04 08 35 2D FFFFFF84 FFFFFF80 FFFFFF80 FFFFFFC2
   00 1B 02 01 55 10 03 1D 24 33 08 05 38 00 FFFFFF84 00
   39 01 07 66 6C 61 74 74 65 6E 15 02 3A 3D 16 02
   3B 3E 10 03 1D 24 3C 10 02 18 3D 04 08 35 37 FFFFFF84
   FFFFFF80 FFFFFF80 FFFFFFC2 00 1B 08 05 3F 37 FFFFFFC0 01 40 01 07 61 73
   41 72 72 61 79 10 04 1D 41 17 3B 09 02 42 06 02
   09 46 75 6E 63 74 69 6F 6E 31 08 05 44 00 FFFFFF84 00
   45 01 09 74 72 61 6E 73 70 6F 73 65 15 02 46 4A
   16 02 47 4B 10 03 1D 24 48 10 03 1D 24 49 10 02
   18 4A 04 08 35 43 FFFFFF84 FFFFFF80 FFFFFF80 FFFFFFC2 00 1B 08 05 3F 43
   FFFFFFC0 01 4C 10 04 1D 41 17 48 07 05 4E 02 FFFFFF88 02 4F
   01 08 41 72 72 61 79 4F 70 73 10 02 14 50 06 08
   01 02 FFFFFF84 FFFFFF80 FFFFFF80 FFFFFF88 02 51 13 03 50 0B 26 08 05 2A
   50 FFFFFF84 00 53 14 01 4F 06 04 55 50 00 56 02 05 6F
   66 52 65 66 15 02 57 5A 13 04 54 58 5F 26 10 03
   14 00 59 10 02 18 5A 04 08 1A 54 FFFFFF84 FFFFFF80 FFFFFF80 FFFFFFC2 00
   5B 11 02 1C 5C 10 02 1D 5D 09 02 5E 06 02 06 41
   6E 79 52 65 66 10 04 14 15 59 60 10 03 1D 24 59
   08 08 62 54 FFFFFF82 FFFFFFC2 FFFFFF80 FFFFFF84 20 63 01 04 72 65 70 72
   15 01 60 08 08 65 54 FFFFFF82 FFFFFF80 FFFFFFA0 FFFFFF80 04 60 01 05 72
   65 70 72 20 08 05 2A 54 FFFFFF84 00 67 14 02 68 6A 10
   03 69 54 59 0D 01 50 08 05 62 66 FFFFFFC0 00 60 08 06
   6C 54 FFFFFFA0 FFFFFF84 28 6D 01 0E 74 68 69 73 43 6F 6C 6C
   65 63 74 69 6F 6E 15 01 6E 10 03 14 6F 59 09 02
   70 02 02 0C 57 72 61 70 70 65 64 41 72 72 61 79
   08 06 72 54 FFFFFFA0 FFFFFF84 28 73 01 0C 74 6F 43 6F 6C 6C
   65 63 74 69 6F 6E 14 02 6E 74 08 05 62 71 FFFFFFC0 00
   60 08 06 76 54 FFFFFFA0 FFFFFF84 28 77 01 0A 6E 65 77 42 75
   69 6C 64 65 72 15 01 78 10 03 79 7C 59 0E 02 14
   7A 09 02 7B 02 01 0C 41 72 72 61 79 42 75 69 6C
   64 65 72 09 02 55 7D 0A 02 7B 02 08 06 7F 54 FFFFFF84
   00 FFFFFF81 00 01 06 6C 65 6E 67 74 68 15 02 FFFFFF81 01 10
   03 1D FFFFFF81 02 09 03 FFFFFF81 03 06 02 03 49 6E 74 08 07
   FFFFFF81 05 54 FFFFFF84 00 FFFFFF81 06 01 05 61 70 70 6C 79 14 03
   59 FFFFFF81 07 08 08 FFFFFF81 08 FFFFFF81 04 FFFFFFC0 00 FFFFFF81 01 01 05 69
   6E 64 65 78 08 07 FFFFFF81 0A 54 FFFFFF84 00 FFFFFF81 0B 01 06 75
   70 64 61 74 65 14 06 FFFFFF81 0C FFFFFF81 0F FFFFFF81 10 10 03 1D
   FFFFFF81 0D 09 03 FFFFFF81 0E 06 02 04 55 6E 69 74 08 08 FFFFFF81
   08 FFFFFF81 09 FFFFFFC0 00 FFFFFF81 01 08 07 FFFFFF81 11 FFFFFF81 09 FFFFFFC0 00 59
   01 04 65 6C 65 6D 06 0A FFFFFF81 13 50 FFFFFF84 FFFFFF80 FFFFFF80 FFFFFF80 00
   FFFFFF81 14 02 06 6F 66 42 79 74 65 13 07 FFFFFF81 12 FFFFFF81 15
   FFFFFF81 19 26 10 04 14 00 FFFFFF81 16 10 03 1D FFFFFF81 17 09 03
   FFFFFF81 18 06 02 04 42 79 74 65 10 06 14 15 FFFFFF81 16 FFFFFF81
   1A 10 04 1D 24 FFFFFF81 16 08 0A 62 FFFFFF81 12 FFFFFF82 FFFFFFC2 FFFFFF80 FFFFFF84
   20 FFFFFF81 1C 15 02 FFFFFF81 1A 08 0A 65 FFFFFF81 12 FFFFFF82 FFFFFF80 FFFFFFA0 FFFFFF80
   04 FFFFFF81 1A 08 07 2A FFFFFF81 12 FFFFFF84 00 FFFFFF81 1F 14 04 FFFFFF81 20
   FFFFFF81 21 10 03 69 FFFFFF81 12 08 07 62 FFFFFF81 1E FFFFFFC0 00 FFFFFF81 1A
   08 08 6C FFFFFF81 12 FFFFFFA0 FFFFFF84 28 FFFFFF81 23 15 02 FFFFFF81 24 10 04
   14 6F FFFFFF81 16 08 08 72 FFFFFF81 12 FFFFFFA0 FFFFFF84 28 FFFFFF81 26 14 04
   FFFFFF81 24 FFFFFF81 27 08 07 62 FFFFFF81 25 FFFFFFC0 00 FFFFFF81 1A 08 08 76
   FFFFFF81 12 FFFFFFA0 FFFFFF84 28 FFFFFF81 29 15 02 FFFFFF81 2A 10 03 79 FFFFFF81 2B
   09 03 FFFFFF81 13 7D 08 07 7F FFFFFF81 12 FFFFFF84 00 FFFFFF81 00 08 08
   FFFFFF81 05 FFFFFF81 12 FFFFFF84 00 FFFFFF81 2E 14 04 FFFFFF81 16 FFFFFF81 2F 08 08
   FFFFFF81 08 FFFFFF81 2D FFFFFFC0 00 FFFFFF81 01 08 08 FFFFFF81 0A FFFFFF81 12 FFFFFF84 00
   FFFFFF81 31 14 06 FFFFFF81 0C FFFFFF81 32 FFFFFF81 33 08 08 FFFFFF81 08 FFFFFF81 30
   FFFFFFC0 00 FFFFFF81 01 08 08 FFFFFF81 11 FFFFFF81 30 FFFFFFC0 00 FFFFFF81 16 06 0A
   FFFFFF81 35 50 FFFFFF84 FFFFFF80 FFFFFF80 FFFFFF80 00 FFFFFF81 36 02 07 6F 66 53 68
   6F 72 74 13 07 FFFFFF81 34 FFFFFF81 37 FFFFFF81 3B 26 10 04 14 00
   FFFFFF81 38 10 03 1D FFFFFF81 39 09 03 FFFFFF81 3A 06 02 05 53 68
   6F 72 74 10 06 14 15 FFFFFF81 38 FFFFFF81 3C 10 04 1D 24 FFFFFF81
   38 08 0A 62 FFFFFF81 34 FFFFFF82 FFFFFFC2 FFFFFF80 FFFFFF84 20 FFFFFF81 3E 15 02 FFFFFF81
   3C 08 0A 65 FFFFFF81 34 FFFFFF82 FFFFFF80 FFFFFFA0 FFFFFF80 04 FFFFFF81 3C 08 07 2A
   FFFFFF81 34 FFFFFF84 00 FFFFFF81 41 14 04 FFFFFF81 42 FFFFFF81 43 10 03 69 FFFFFF81
   34 08 07 62 FFFFFF81 40 FFFFFFC0 00 FFFFFF81 3C 08 08 6C FFFFFF81 34 FFFFFFA0
   FFFFFF84 28 FFFFFF81 45 15 02 FFFFFF81 46 10 04 14 6F FFFFFF81 38 08 08
   72 FFFFFF81 34 FFFFFFA0 FFFFFF84 28 FFFFFF81 48 14 04 FFFFFF81 46 FFFFFF81 49 08 07
   62 FFFFFF81 47 FFFFFFC0 00 FFFFFF81 3C 08 08 76 FFFFFF81 34 FFFFFFA0 FFFFFF84 28 FFFFFF81
   4B 15 02 FFFFFF81 4C 10 03 79 FFFFFF81 4D 09 03 FFFFFF81 35 7D 08
   07 7F FFFFFF81 34 FFFFFF84 00 FFFFFF81 00 08 08 FFFFFF81 05 FFFFFF81 34 FFFFFF84 00
   FFFFFF81 50 14 04 FFFFFF81 38 FFFFFF81 51 08 08 FFFFFF81 08 FFFFFF81 4F FFFFFFC0 00
   FFFFFF81 01 08 08 FFFFFF81 0A FFFFFF81 34 FFFFFF84 00 FFFFFF81 53 14 06 FFFFFF81 0C
   FFFFFF81 54 FFFFFF81 55 08 08 FFFFFF81 08 FFFFFF81 52 FFFFFFC0 00 FFFFFF81 01 08 08
   FFFFFF81 11 FFFFFF81 52 FFFFFFC0 00 FFFFFF81 38 06 0A FFFFFF81 57 50 FFFFFF84 FFFFFF80 FFFFFF80
   FFFFFF80 00 FFFFFF81 58 02 06 6F 66 43 68 61 72 13 07 FFFFFF81 56
   FFFFFF81 59 FFFFFF81 5D 26 10 04 14 00 FFFFFF81 5A 10 03 1D FFFFFF81 5B
   09 03 FFFFFF81 5C 06 02 04 43 68 61 72 10 06 14 15 FFFFFF81
   5A FFFFFF81 5E 10 04 1D 24 FFFFFF81 5A 08 0A 62 FFFFFF81 56 FFFFFF82 FFFFFFC2
   FFFFFF80 FFFFFF84 20 FFFFFF81 60 15 02 FFFFFF81 5E 08 0A 65 FFFFFF81 56 FFFFFF82 FFFFFF80
   FFFFFFA0 FFFFFF80 04 FFFFFF81 5E 08 07 2A FFFFFF81 56 FFFFFF84 00 FFFFFF81 63 14 04
   FFFFFF81 64 FFFFFF81 65 10 03 69 FFFFFF81 56 08 07 62 FFFFFF81 62 FFFFFFC0 00
   FFFFFF81 5E 08 08 6C FFFFFF81 56 FFFFFFA0 FFFFFF84 28 FFFFFF81 67 15 02 FFFFFF81 68
   10 04 14 6F FFFFFF81 5A 08 08 72 FFFFFF81 56 FFFFFFA0 FFFFFF84 28 FFFFFF81 6A
   14 04 FFFFFF81 68 FFFFFF81 6B 08 07 62 FFFFFF81 69 FFFFFFC0 00 FFFFFF81 5E 08
   08 76 FFFFFF81 56 FFFFFFA0 FFFFFF84 28 FFFFFF81 6D 15 02 FFFFFF81 6E 10 03 79
   FFFFFF81 6F 09 03 FFFFFF81 57 7D 08 07 7F FFFFFF81 56 FFFFFF84 00 FFFFFF81 00
   08 08 FFFFFF81 05 FFFFFF81 56 FFFFFF84 00 FFFFFF81 72 14 04 FFFFFF81 5A FFFFFF81 73
   08 08 FFFFFF81 08 FFFFFF81 71 FFFFFFC0 00 FFFFFF81 01 08 08 FFFFFF81 0A FFFFFF81 56
   FFFFFF84 00 FFFFFF81 75 14 06 FFFFFF81 0C FFFFFF81 76 FFFFFF81 77 08 08 FFFFFF81 08
   FFFFFF81 74 FFFFFFC0 00 FFFFFF81 01 08 08 FFFFFF81 11 FFFFFF81 74 FFFFFFC0 00 FFFFFF81 5A
   06 0A FFFFFF81 79 50 FFFFFF84 FFFFFF80 FFFFFF80 FFFFFF80 00 FFFFFF81 7A 02 05 6F 66
   49 6E 74 13 07 FFFFFF81 78 FFFFFF81 7B FFFFFF81 7C 26 10 04 14 00
   FFFFFF81 01 10 06 14 15 FFFFFF81 01 FFFFFF81 7D 10 04 1D 24 FFFFFF81 01
   08 0A 62 FFFFFF81 78 FFFFFF82 FFFFFFC2 FFFFFF80 FFFFFF84 20 FFFFFF81 7F 15 02 FFFFFF81 7D
   08 0A 65 FFFFFF81 78 FFFFFF82 FFFFFF80 FFFFFFA0 FFFFFF80 04 FFFFFF81 7D 08 07 2A FFFFFF81
   78 FFFFFF84 00 FFFFFF82 02 14 04 FFFFFF82 03 FFFFFF82 04 10 03 69 FFFFFF81 78
   08 07 62 FFFFFF82 01 FFFFFFC0 00 FFFFFF81 7D 08 08 6C FFFFFF81 78 FFFFFFA0 FFFFFF84
   28 FFFFFF82 06 15 02 FFFFFF82 07 10 04 14 6F FFFFFF81 01 08 08 72
   FFFFFF81 78 FFFFFFA0 FFFFFF84 28 FFFFFF82 09 14 04 FFFFFF82 07 FFFFFF82 0A 08 07 62
   FFFFFF82 08 FFFFFFC0 00 FFFFFF81 7D 08 08 76 FFFFFF81 78 FFFFFFA0 FFFFFF84 28 FFFFFF82 0C
   15 02 FFFFFF82 0D 10 03 79 FFFFFF82 0E 09 03 FFFFFF81 79 7D 08 07
   7F FFFFFF81 78 FFFFFF84 00 FFFFFF81 00 08 08 FFFFFF81 05 FFFFFF81 78 FFFFFF84 00 FFFFFF82
   11 14 04 FFFFFF81 01 FFFFFF82 12 08 08 FFFFFF81 08 FFFFFF82 10 FFFFFFC0 00 FFFFFF81
   01 08 08 FFFFFF81 0A FFFFFF81 78 FFFFFF84 00 FFFFFF82 14 14 06 FFFFFF81 0C FFFFFF82
   15 FFFFFF82 16 08 08 FFFFFF81 08 FFFFFF82 13 FFFFFFC0 00 FFFFFF81 01 08 08 FFFFFF81
   11 FFFFFF82 13 FFFFFFC0 00 FFFFFF81 01 06 0A FFFFFF82 18 50 FFFFFF84 FFFFFF80 FFFFFF80 FFFFFF80
   00 FFFFFF82 19 02 06 6F 66 4C 6F 6E 67 13 07 FFFFFF82 17 FFFFFF82
   1A FFFFFF82 1E 26 10 04 14 00 FFFFFF82 1B 10 03 1D FFFFFF82 1C 09
   03 FFFFFF82 1D 06 02 04 4C 6F 6E 67 10 06 14 15 FFFFFF82 1B
   FFFFFF82 1F 10 04 1D 24 FFFFFF82 1B 08 0A 62 FFFFFF82 17 FFFFFF82 FFFFFFC2 FFFFFF80
   FFFFFF84 20 FFFFFF82 21 15 02 FFFFFF82 1F 08 0A 65 FFFFFF82 17 FFFFFF82 FFFFFF80 FFFFFFA0
   FFFFFF80 04 FFFFFF82 1F 08 07 2A FFFFFF82 17 FFFFFF84 00 FFFFFF82 24 14 04 FFFFFF82
   25 FFFFFF82 26 10 03 69 FFFFFF82 17 08 07 62 FFFFFF82 23 FFFFFFC0 00 FFFFFF82
   1F 08 08 6C FFFFFF82 17 FFFFFFA0 FFFFFF84 28 FFFFFF82 28 15 02 FFFFFF82 29 10
   04 14 6F FFFFFF82 1B 08 08 72 FFFFFF82 17 FFFFFFA0 FFFFFF84 28 FFFFFF82 2B 14
   04 FFFFFF82 29 FFFFFF82 2C 08 07 62 FFFFFF82 2A FFFFFFC0 00 FFFFFF82 1F 08 08
   76 FFFFFF82 17 FFFFFFA0 FFFFFF84 28 FFFFFF82 2E 15 02 FFFFFF82 2F 10 03 79 FFFFFF82
   30 09 03 FFFFFF82 18 7D 08 07 7F FFFFFF82 17 FFFFFF84 00 FFFFFF81 00 08
   08 FFFFFF81 05 FFFFFF82 17 FFFFFF84 00 FFFFFF82 33 14 04 FFFFFF82 1B FFFFFF82 34 08
   08 FFFFFF81 08 FFFFFF82 32 FFFFFFC0 00 FFFFFF81 01 08 08 FFFFFF81 0A FFFFFF82 17 FFFFFF84
   00 FFFFFF82 36 14 06 FFFFFF81 0C FFFFFF82 37 FFFFFF82 38 08 08 FFFFFF81 08 FFFFFF82
   35 FFFFFFC0 00 FFFFFF81 01 08 08 FFFFFF81 11 FFFFFF82 35 FFFFFFC0 00 FFFFFF82 1B 06
   0A FFFFFF82 3A 50 FFFFFF84 FFFFFF80 FFFFFF80 FFFFFF80 00 FFFFFF82 3B 02 07 6F 66 46
   6C 6F 61 74 13 07 FFFFFF82 39 FFFFFF82 3C FFFFFF82 40 26 10 04 14
   00 FFFFFF82 3D 10 03 1D FFFFFF82 3E 09 03 FFFFFF82 3F 06 02 05 46
   6C 6F 61 74 10 06 14 15 FFFFFF82 3D FFFFFF82 41 10 04 1D 24
   FFFFFF82 3D 08 0A 62 FFFFFF82 39 FFFFFF82 FFFFFFC2 FFFFFF80 FFFFFF84 20 FFFFFF82 43 15 02
   FFFFFF82 41 08 0A 65 FFFFFF82 39 FFFFFF82 FFFFFF80 FFFFFFA0 FFFFFF80 04 FFFFFF82 41 08 07
   2A FFFFFF82 39 FFFFFF84 00 FFFFFF82 46 14 04 FFFFFF82 47 FFFFFF82 48 10 03 69
   FFFFFF82 39 08 07 62 FFFFFF82 45 FFFFFFC0 00 FFFFFF82 41 08 08 6C FFFFFF82 39
   FFFFFFA0 FFFFFF84 28 FFFFFF82 4A 15 02 FFFFFF82 4B 10 04 14 6F FFFFFF82 3D 08
   08 72 FFFFFF82 39 FFFFFFA0 FFFFFF84 28 FFFFFF82 4D 14 04 FFFFFF82 4B FFFFFF82 4E 08
   07 62 FFFFFF82 4C FFFFFFC0 00 FFFFFF82 41 08 08 76 FFFFFF82 39 FFFFFFA0 FFFFFF84 28
   FFFFFF82 50 15 02 FFFFFF82 51 10 03 79 FFFFFF82 52 09 03 FFFFFF82 3A 7D
   08 07 7F FFFFFF82 39 FFFFFF84 00 FFFFFF81 00 08 08 FFFFFF81 05 FFFFFF82 39 FFFFFF84
   00 FFFFFF82 55 14 04 FFFFFF82 3D FFFFFF82 56 08 08 FFFFFF81 08 FFFFFF82 54 FFFFFFC0
   00 FFFFFF81 01 08 08 FFFFFF81 0A FFFFFF82 39 FFFFFF84 00 FFFFFF82 58 14 06 FFFFFF81
   0C FFFFFF82 59 FFFFFF82 5A 08 08 FFFFFF81 08 FFFFFF82 57 FFFFFFC0 00 FFFFFF81 01 08
   08 FFFFFF81 11 FFFFFF82 57 FFFFFFC0 00 FFFFFF82 3D 06 0A FFFFFF82 5C 50 FFFFFF84 FFFFFF80
   FFFFFF80 FFFFFF80 00 FFFFFF82 5D 02 08 6F 66 44 6F 75 62 6C 65 13
   07 FFFFFF82 5B FFFFFF82 5E FFFFFF82 62 26 10 04 14 00 FFFFFF82 5F 10 03
   1D FFFFFF82 60 09 03 FFFFFF82 61 06 02 06 44 6F 75 62 6C 65
   10 06 14 15 FFFFFF82 5F FFFFFF82 63 10 04 1D 24 FFFFFF82 5F 08 0A
   62 FFFFFF82 5B FFFFFF82 FFFFFFC2 FFFFFF80 FFFFFF84 20 FFFFFF82 65 15 02 FFFFFF82 63 08 0A
   65 FFFFFF82 5B FFFFFF82 FFFFFF80 FFFFFFA0 FFFFFF80 04 FFFFFF82 63 08 07 2A FFFFFF82 5B FFFFFF84
   00 FFFFFF82 68 14 04 FFFFFF82 69 FFFFFF82 6A 10 03 69 FFFFFF82 5B 08 07
   62 FFFFFF82 67 FFFFFFC0 00 FFFFFF82 63 08 08 6C FFFFFF82 5B FFFFFFA0 FFFFFF84 28 FFFFFF82
   6C 15 02 FFFFFF82 6D 10 04 14 6F FFFFFF82 5F 08 08 72 FFFFFF82 5B
   FFFFFFA0 FFFFFF84 28 FFFFFF82 6F 14 04 FFFFFF82 6D FFFFFF82 70 08 07 62 FFFFFF82 6E
   FFFFFFC0 00 FFFFFF82 63 08 08 76 FFFFFF82 5B FFFFFFA0 FFFFFF84 28 FFFFFF82 72 15 02
   FFFFFF82 73 10 03 79 FFFFFF82 74 09 03 FFFFFF82 5C 7D 08 07 7F FFFFFF82
   5B FFFFFF84 00 FFFFFF81 00 08 08 FFFFFF81 05 FFFFFF82 5B FFFFFF84 00 FFFFFF82 77 14
   04 FFFFFF82 5F FFFFFF82 78 08 08 FFFFFF81 08 FFFFFF82 76 FFFFFFC0 00 FFFFFF81 01 08
   08 FFFFFF81 0A FFFFFF82 5B FFFFFF84 00 FFFFFF82 7A 14 06 FFFFFF81 0C FFFFFF82 7B FFFFFF82
   7C 08 08 FFFFFF81 08 FFFFFF82 79 FFFFFFC0 00 FFFFFF81 01 08 08 FFFFFF81 11 FFFFFF82
   79 FFFFFFC0 00 FFFFFF82 5F 06 0A FFFFFF82 7E 50 FFFFFF84 FFFFFF80 FFFFFF80 FFFFFF80 00 FFFFFF82
   7F 02 09 6F 66 42 6F 6F 6C 65 61 6E 13 07 FFFFFF82 7D
   FFFFFF83 00 FFFFFF83 04 26 10 04 14 00 FFFFFF83 01 10 03 1D FFFFFF83 02
   09 03 FFFFFF83 03 06 02 07 42 6F 6F 6C 65 61 6E 10 06
   14 15 FFFFFF83 01 FFFFFF83 05 10 04 1D 24 FFFFFF83 01 08 0A 62 FFFFFF82
   7D FFFFFF82 FFFFFFC2 FFFFFF80 FFFFFF84 20 FFFFFF83 07 15 02 FFFFFF83 05 08 0A 65 FFFFFF82
   7D FFFFFF82 FFFFFF80 FFFFFFA0 FFFFFF80 04 FFFFFF83 05 08 07 2A FFFFFF82 7D FFFFFF84 00 FFFFFF83
   0A 14 04 FFFFFF83 0B FFFFFF83 0C 10 03 69 FFFFFF82 7D 08 07 62 FFFFFF83
   09 FFFFFFC0 00 FFFFFF83 05 08 08 6C FFFFFF82 7D FFFFFFA0 FFFFFF84 28 FFFFFF83 0E 15
   02 FFFFFF83 0F 10 04 14 6F FFFFFF83 01 08 08 72 FFFFFF82 7D FFFFFFA0 FFFFFF84
   28 FFFFFF83 11 14 04 FFFFFF83 0F FFFFFF83 12 08 07 62 FFFFFF83 10 FFFFFFC0 00
   FFFFFF83 05 08 08 76 FFFFFF82 7D FFFFFFA0 FFFFFF84 28 FFFFFF83 14 15 02 FFFFFF83 15
   10 03 79 FFFFFF83 16 09 03 FFFFFF82 7E 7D 08 07 7F FFFFFF82 7D FFFFFF84
   00 FFFFFF81 00 08 08 FFFFFF81 05 FFFFFF82 7D FFFFFF84 00 FFFFFF83 19 14 04 FFFFFF83
   01 FFFFFF83 1A 08 08 FFFFFF81 08 FFFFFF83 18 FFFFFFC0 00 FFFFFF81 01 08 08 FFFFFF81
   0A FFFFFF82 7D FFFFFF84 00 FFFFFF83 1C 14 06 FFFFFF81 0C FFFFFF83 1D FFFFFF83 1E 08
   08 FFFFFF81 08 FFFFFF83 1B FFFFFFC0 00 FFFFFF81 01 08 08 FFFFFF81 11 FFFFFF83 1B FFFFFFC0
   00 FFFFFF83 01 06 0A FFFFFF83 20 50 FFFFFF84 FFFFFF80 FFFFFF80 FFFFFF80 00 FFFFFF83 21 02
   06 6F 66 55 6E 69 74 13 07 FFFFFF83 1F FFFFFF83 22 FFFFFF83 23 26
   10 04 14 00 FFFFFF81 0C 10 06 14 15 FFFFFF81 0C FFFFFF83 24 10 04
   1D 24 FFFFFF81 0C 08 0A 62 FFFFFF83 1F FFFFFF82 FFFFFFC2 FFFFFF80 FFFFFF84 20 FFFFFF83 26
   15 02 FFFFFF83 24 08 0A 65 FFFFFF83 1F FFFFFF82 FFFFFF80 FFFFFFA0 FFFFFF80 04 FFFFFF83 24
   08 07 2A FFFFFF83 1F FFFFFF84 00 FFFFFF83 29 14 04 FFFFFF83 2A FFFFFF83 2B 10
   03 69 FFFFFF83 1F 08 07 62 FFFFFF83 28 FFFFFFC0 00 FFFFFF83 24 08 08 6C
   FFFFFF83 1F FFFFFFA0 FFFFFF84 28 FFFFFF83 2D 15 02 FFFFFF83 2E 10 04 14 6F FFFFFF81
   0C 08 08 72 FFFFFF83 1F FFFFFFA0 FFFFFF84 28 FFFFFF83 30 14 04 FFFFFF83 2E FFFFFF83
   31 08 07 62 FFFFFF83 2F FFFFFFC0 00 FFFFFF83 24 08 08 76 FFFFFF83 1F FFFFFFA0
   FFFFFF84 28 FFFFFF83 33 15 02 FFFFFF83 34 10 03 79 FFFFFF83 35 09 03 FFFFFF83
   20 7D 08 07 7F FFFFFF83 1F FFFFFF84 00 FFFFFF81 00 08 08 FFFFFF81 05 FFFFFF83
   1F FFFFFF84 00 FFFFFF83 38 14 04 FFFFFF81 0C FFFFFF83 39 08 08 FFFFFF81 08 FFFFFF83
   37 FFFFFFC0 00 FFFFFF81 01 08 08 FFFFFF81 0A FFFFFF83 1F FFFFFF84 00 FFFFFF83 3B 14
   06 FFFFFF81 0C FFFFFF83 3C FFFFFF83 3D 08 08 FFFFFF81 08 FFFFFF83 3A FFFFFFC0 00 FFFFFF81
   01 08 08 FFFFFF81 11 FFFFFF83 3A FFFFFFC0 00 FFFFFF81 0C 
  InnerClass: 
   public ofInt=class scala/collection/mutable/ArrayOps$ofInt of class scala/collection/mutable/ArrayOps
   public ofRef=class scala/collection/mutable/ArrayOps$ofRef of class scala/collection/mutable/ArrayOps
   public ofUnit=class scala/collection/mutable/ArrayOps$ofUnit of class scala/collection/mutable/ArrayOps
   public ofLong=class scala/collection/mutable/ArrayOps$ofLong of class scala/collection/mutable/ArrayOps
   public ofChar=class scala/collection/mutable/ArrayOps$ofChar of class scala/collection/mutable/ArrayOps
   public ofByte=class scala/collection/mutable/ArrayOps$ofByte of class scala/collection/mutable/ArrayOps
   public ofFloat=class scala/collection/mutable/ArrayOps$ofFloat of class scala/collection/mutable/ArrayOps
   public ofShort=class scala/collection/mutable/ArrayOps$ofShort of class scala/collection/mutable/ArrayOps
   public ofDouble=class scala/collection/mutable/ArrayOps$ofDouble of class scala/collection/mutable/ArrayOps
   public ofBoolean=class scala/collection/mutable/ArrayOps$ofBoolean of class scala/collection/mutable/ArrayOps
   public final $anonfun$1=class scala/collection/mutable/ArrayOps$$anonfun$1 of class scala/collection/mutable/ArrayOps
   public abstract $less$colon$less=class scala/Predef$$less$colon$less of class scala/Predef
   public WithFilter=class scala/collection/TraversableLike$WithFilter of class scala/collection/TraversableLike
   public final $anonfun$flatten$1=class scala/collection/mutable/ArrayOps$$anonfun$flatten$1 of class scala/collection/mutable/ArrayOps
   public final $anonfun$transpose$2=class scala/collection/mutable/ArrayOps$$anonfun$transpose$2 of class scala/collection/mutable/ArrayOps
   public final $anonfun$transpose$1=class scala/collection/mutable/ArrayOps$$anonfun$transpose$1 of class scala/collection/mutable/ArrayOps
  minor version: 0
  major version: 49
  Constant pool:
Asciz	SourceFile;
Asciz	ArrayOps.scala;
Asciz	<init>;
Asciz	()V;
Asciz	Code;
Asciz	LineNumberTable;
Asciz	java/lang/Object;
class	java/lang/Object
NameAndType	"<init>":()V
Method	java/lang/Object."<init>":()V
Asciz	scala/collection/TraversableLike$class;
class	scala/collection/TraversableLike$class
Asciz	$init$;
Asciz	(Lscala/collection/TraversableLike;)V;
NameAndType	$init$:(Lscala/collection/TraversableLike;)V
Method	scala/collection/TraversableLike$class.$init$:(Lscala/collection/TraversableLike;)V
Asciz	scala/collection/IterableLike$class;
class	scala/collection/IterableLike$class
Asciz	(Lscala/collection/IterableLike;)V;
NameAndType	$init$:(Lscala/collection/IterableLike;)V
Method	scala/collection/IterableLike$class.$init$:(Lscala/collection/IterableLike;)V
Asciz	scala/collection/SeqLike$class;
class	scala/collection/SeqLike$class
Asciz	(Lscala/collection/SeqLike;)V;
NameAndType	$init$:(Lscala/collection/SeqLike;)V
Method	scala/collection/SeqLike$class.$init$:(Lscala/collection/SeqLike;)V
Asciz	scala/collection/IndexedSeqLike$class;
class	scala/collection/IndexedSeqLike$class
Asciz	(Lscala/collection/IndexedSeqLike;)V;
NameAndType	$init$:(Lscala/collection/IndexedSeqLike;)V
Method	scala/collection/IndexedSeqLike$class.$init$:(Lscala/collection/IndexedSeqLike;)V
Asciz	scala/collection/mutable/IndexedSeqLike$class;
class	scala/collection/mutable/IndexedSeqLike$class
Asciz	(Lscala/collection/mutable/IndexedSeqLike;)V;
NameAndType	$init$:(Lscala/collection/mutable/IndexedSeqLike;)V
Method	scala/collection/mutable/IndexedSeqLike$class.$init$:(Lscala/collection/mutable/IndexedSeqLike;)V
Asciz	scala/collection/mutable/ArrayLike$class;
class	scala/collection/mutable/ArrayLike$class
Asciz	(Lscala/collection/mutable/ArrayLike;)V;
NameAndType	$init$:(Lscala/collection/mutable/ArrayLike;)V
Method	scala/collection/mutable/ArrayLike$class.$init$:(Lscala/collection/mutable/ArrayLike;)V
Asciz	Signature;
Asciz	thisCollection;
Asciz	()Lscala/collection/IndexedSeq;;
Asciz	scala/collection/mutable/IndexedSeqLike;
class	scala/collection/mutable/IndexedSeqLike
Asciz	()Lscala/collection/mutable/IndexedSeq;;
NameAndType	thisCollection:()Lscala/collection/mutable/IndexedSeq;
InterfaceMethod	scala/collection/mutable/IndexedSeqLike.thisCollection:()Lscala/collection/mutable/IndexedSeq;
Asciz	()Lscala/collection/Seq;;
Asciz	()Lscala/collection/Iterable;;
Asciz	()Lscala/collection/Traversable;;
Asciz	toCollection;
Asciz	(Ljava/lang/Object;)Lscala/collection/IndexedSeq;;
Asciz	(Ljava/lang/Object;)Lscala/collection/mutable/IndexedSeq;;
NameAndType	toCollection:(Ljava/lang/Object;)Lscala/collection/mutable/IndexedSeq;
InterfaceMethod	scala/collection/mutable/IndexedSeqLike.toCollection:(Ljava/lang/Object;)Lscala/collection/mutable/IndexedSeq;
Asciz	this;
Asciz	Lscala/collection/mutable/ArrayOps;;
Asciz	repr;
Asciz	Ljava/lang/Object;;
Asciz	LocalVariableTable;
Asciz	(Ljava/lang/Object;)Lscala/collection/Seq;;
Asciz	(Ljava/lang/Object;)Lscala/collection/Iterable;;
Asciz	(Ljava/lang/Object;)Lscala/collection/Traversable;;
Asciz	view;
Asciz	()Lscala/collection/IndexedSeqView;;
Asciz	()Lscala/collection/mutable/IndexedSeqView;;
NameAndType	view:()Lscala/collection/mutable/IndexedSeqView;
InterfaceMethod	scala/collection/mutable/IndexedSeqLike.view:()Lscala/collection/mutable/IndexedSeqView;
Asciz	()Lscala/collection/SeqView;;
Asciz	()Lscala/collection/IterableView;;
Asciz	()Lscala/collection/TraversableView;;
Asciz	(II)Lscala/collection/IndexedSeqView;;
Asciz	(II)Lscala/collection/mutable/IndexedSeqView;;
NameAndType	view:(II)Lscala/collection/mutable/IndexedSeqView;
InterfaceMethod	scala/collection/mutable/IndexedSeqLike.view:(II)Lscala/collection/mutable/IndexedSeqView;
Asciz	from;
Asciz	I;
Asciz	until;
Asciz	(II)Lscala/collection/SeqView;;
Asciz	(II)Lscala/collection/IterableView;;
Asciz	(II)Lscala/collection/TraversableView;;
Asciz	projection;
Asciz	scala/collection/SeqLike;
class	scala/collection/SeqLike
NameAndType	projection:()Lscala/collection/SeqView;
InterfaceMethod	scala/collection/SeqLike.projection:()Lscala/collection/SeqView;
Asciz	transpose;
Asciz	(Lscala/Function1;)[Ljava/lang/Object;;
Asciz	scala/Predef$;
class	scala/Predef$
Asciz	MODULE$;
Asciz	Lscala/Predef$;;
NameAndType	MODULE$:Lscala/Predef$;
Field	scala/Predef$.MODULE$:Lscala/Predef$;
Asciz	scala/collection/IndexedSeqLike;
class	scala/collection/IndexedSeqLike
Asciz	head;
Asciz	()Ljava/lang/Object;;
NameAndType	head:()Ljava/lang/Object;
InterfaceMethod	scala/collection/IndexedSeqLike.head:()Ljava/lang/Object;
Asciz	scala/Function1;
class	scala/Function1
Asciz	apply;
Asciz	(Ljava/lang/Object;)Ljava/lang/Object;;
NameAndType	apply:(Ljava/lang/Object;)Ljava/lang/Object;
InterfaceMethod	scala/Function1.apply:(Ljava/lang/Object;)Ljava/lang/Object;
Asciz	genericArrayOps;
Asciz	(Ljava/lang/Object;)Lscala/collection/mutable/ArrayOps;;
NameAndType	genericArrayOps:(Ljava/lang/Object;)Lscala/collection/mutable/ArrayOps;
Method	scala/Predef$.genericArrayOps:(Ljava/lang/Object;)Lscala/collection/mutable/ArrayOps;
Asciz	scala/collection/mutable/ArrayOps$$anonfun$1;
class	scala/collection/mutable/ArrayOps$$anonfun$1
Asciz	(Lscala/collection/mutable/ArrayOps;)V;
NameAndType	"<init>":(Lscala/collection/mutable/ArrayOps;)V
Method	scala/collection/mutable/ArrayOps$$anonfun$1."<init>":(Lscala/collection/mutable/ArrayOps;)V
Asciz	scala/Array$;
class	scala/Array$
Asciz	Lscala/Array$;;
NameAndType	MODULE$:Lscala/Array$;
Field	scala/Array$.MODULE$:Lscala/Array$;
Asciz	scala/reflect/ClassManifest$;
class	scala/reflect/ClassManifest$
Asciz	Lscala/reflect/ClassManifest$;;
NameAndType	MODULE$:Lscala/reflect/ClassManifest$;
Field	scala/reflect/ClassManifest$.MODULE$:Lscala/reflect/ClassManifest$;
Asciz	scala/collection/mutable/Builder;
class	scala/collection/mutable/Builder
Asciz	scala/reflect/NoManifest$;
class	scala/reflect/NoManifest$
Asciz	Lscala/reflect/NoManifest$;;
NameAndType	MODULE$:Lscala/reflect/NoManifest$;
Field	scala/reflect/NoManifest$.MODULE$:Lscala/reflect/NoManifest$;
Asciz	scala/reflect/OptManifest;
class	scala/reflect/OptManifest
Asciz	arrayType;
Asciz	(Lscala/reflect/OptManifest;)Lscala/reflect/ClassManifest;;
NameAndType	arrayType:(Lscala/reflect/OptManifest;)Lscala/reflect/ClassManifest;
Method	scala/reflect/ClassManifest$.arrayType:(Lscala/reflect/OptManifest;)Lscala/reflect/ClassManifest;
Asciz	[Ljava/lang/Object;;
class	"[Ljava/lang/Object;"
Asciz	wrapRefArray;
Asciz	([Ljava/lang/Object;)Lscala/collection/mutable/WrappedArray;;
NameAndType	wrapRefArray:([Ljava/lang/Object;)Lscala/collection/mutable/WrappedArray;
Method	scala/Predef$.wrapRefArray:([Ljava/lang/Object;)Lscala/collection/mutable/WrappedArray;
Asciz	classType;
Asciz	(Ljava/lang/Class;Lscala/reflect/OptManifest;Lscala/collection/Seq;)Lscala/reflect/ClassManifest;;
NameAndType	classType:(Ljava/lang/Class;Lscala/reflect/OptManifest;Lscala/collection/Seq;)Lscala/reflect/ClassManifest;
Method	scala/reflect/ClassManifest$.classType:(Ljava/lang/Class;Lscala/reflect/OptManifest;Lscala/collection/Seq;)Lscala/reflect/ClassManifest;
Asciz	canBuildFrom;
Asciz	(Lscala/reflect/ClassManifest;)Lscala/collection/generic/CanBuildFrom;;
NameAndType	canBuildFrom:(Lscala/reflect/ClassManifest;)Lscala/collection/generic/CanBuildFrom;
Method	scala/Array$.canBuildFrom:(Lscala/reflect/ClassManifest;)Lscala/collection/generic/CanBuildFrom;
Asciz	scala/collection/TraversableLike;
class	scala/collection/TraversableLike
Asciz	map;
Asciz	(Lscala/Function1;Lscala/collection/generic/CanBuildFrom;)Ljava/lang/Object;;
NameAndType	map:(Lscala/Function1;Lscala/collection/generic/CanBuildFrom;)Ljava/lang/Object;
InterfaceMethod	scala/collection/TraversableLike.map:(Lscala/Function1;Lscala/collection/generic/CanBuildFrom;)Ljava/lang/Object;
Asciz	[Lscala/collection/mutable/Builder;;
class	"[Lscala/collection/mutable/Builder;"
Asciz	scala/collection/mutable/ArrayOps$$anonfun$transpose$1;
class	scala/collection/mutable/ArrayOps$$anonfun$transpose$1
Asciz	(Lscala/collection/mutable/ArrayOps;Lscala/Function1;[Lscala/collection/mutable/Builder;)V;
NameAndType	"<init>":(Lscala/collection/mutable/ArrayOps;Lscala/Function1;[Lscala/collection/mutable/Builder;)V
Method	scala/collection/mutable/ArrayOps$$anonfun$transpose$1."<init>":(Lscala/collection/mutable/ArrayOps;Lscala/Function1;[Lscala/collection/mutable/Builder;)V
Asciz	foreach;
Asciz	(Lscala/Function1;)V;
NameAndType	foreach:(Lscala/Function1;)V
InterfaceMethod	scala/collection/IndexedSeqLike.foreach:(Lscala/Function1;)V
NameAndType	repr:()Ljava/lang/Object;
InterfaceMethod	scala/collection/TraversableLike.repr:()Ljava/lang/Object;
Asciz	getClass;
Asciz	()Ljava/lang/Class;;
NameAndType	getClass:()Ljava/lang/Class;
Method	java/lang/Object.getClass:()Ljava/lang/Class;
Asciz	java/lang/Class;
class	java/lang/Class
Asciz	getComponentType;
NameAndType	getComponentType:()Ljava/lang/Class;
Method	java/lang/Class.getComponentType:()Ljava/lang/Class;
Asciz	fromClass;
Asciz	(Ljava/lang/Class;)Lscala/reflect/ClassManifest;;
NameAndType	fromClass:(Ljava/lang/Class;)Lscala/reflect/ClassManifest;
Method	scala/reflect/ClassManifest$.fromClass:(Ljava/lang/Class;)Lscala/reflect/ClassManifest;
Asciz	newBuilder;
Asciz	(Lscala/reflect/ClassManifest;)Lscala/collection/mutable/ArrayBuilder;;
NameAndType	newBuilder:(Lscala/reflect/ClassManifest;)Lscala/collection/mutable/ArrayBuilder;
Method	scala/Array$.newBuilder:(Lscala/reflect/ClassManifest;)Lscala/collection/mutable/ArrayBuilder;
Asciz	refArrayOps;
Asciz	([Ljava/lang/Object;)Lscala/collection/mutable/ArrayOps;;
NameAndType	refArrayOps:([Ljava/lang/Object;)Lscala/collection/mutable/ArrayOps;
Method	scala/Predef$.refArrayOps:([Ljava/lang/Object;)Lscala/collection/mutable/ArrayOps;
Asciz	scala/collection/mutable/ArrayOps$$anonfun$transpose$2;
class	scala/collection/mutable/ArrayOps$$anonfun$transpose$2
Asciz	(Lscala/collection/mutable/ArrayOps;Lscala/collection/mutable/Builder;)V;
NameAndType	"<init>":(Lscala/collection/mutable/ArrayOps;Lscala/collection/mutable/Builder;)V
Method	scala/collection/mutable/ArrayOps$$anonfun$transpose$2."<init>":(Lscala/collection/mutable/ArrayOps;Lscala/collection/mutable/Builder;)V
Asciz	result;
NameAndType	result:()Ljava/lang/Object;
InterfaceMethod	scala/collection/mutable/Builder.result:()Ljava/lang/Object;
Asciz	asArray$2;
Asciz	Lscala/Function1;;
Asciz	bs$1;
Asciz	bb$1;
Asciz	Lscala/collection/mutable/Builder;;
Asciz	<U:Ljava/lang/Object;>(Lscala/Function1<TT;[TU;>;)[[TU;;
Asciz	flatten;
Asciz	(Lscala/Function1;)Ljava/lang/Object;;
Asciz	scala/collection/mutable/ArrayOps;
class	scala/collection/mutable/ArrayOps
Asciz	scala$collection$mutable$ArrayOps$$rowBuilder;
Asciz	()Lscala/collection/mutable/Builder;;
NameAndType	scala$collection$mutable$ArrayOps$$rowBuilder:()Lscala/collection/mutable/Builder;
Method	scala/collection/mutable/ArrayOps.scala$collection$mutable$ArrayOps$$rowBuilder:()Lscala/collection/mutable/Builder;
Asciz	scala/collection/mutable/ArrayOps$$anonfun$flatten$1;
class	scala/collection/mutable/ArrayOps$$anonfun$flatten$1
Asciz	(Lscala/collection/mutable/ArrayOps;Lscala/Function1;Lscala/collection/mutable/Builder;)V;
NameAndType	"<init>":(Lscala/collection/mutable/ArrayOps;Lscala/Function1;Lscala/collection/mutable/Builder;)V
Method	scala/collection/mutable/ArrayOps$$anonfun$flatten$1."<init>":(Lscala/collection/mutable/ArrayOps;Lscala/Function1;Lscala/collection/mutable/Builder;)V
Asciz	asArray$1;
Asciz	b$1;
Asciz	<U:Ljava/lang/Object;>(Lscala/Function1<TT;[TU;>;)[TU;;
Asciz	withFilter;
Asciz	(Lscala/Function1;)Lscala/collection/TraversableLike$WithFilter;;
Asciz	(Lscala/collection/TraversableLike;Lscala/Function1;)Lscala/collection/TraversableLike$WithFilter;;
NameAndType	withFilter:(Lscala/collection/TraversableLike;Lscala/Function1;)Lscala/collection/TraversableLike$WithFilter;
Method	scala/collection/TraversableLike$class.withFilter:(Lscala/collection/TraversableLike;Lscala/Function1;)Lscala/collection/TraversableLike$WithFilter;
Asciz	p;
Asciz	stringPrefix;
Asciz	()Ljava/lang/String;;
Asciz	(Lscala/collection/TraversableLike;)Ljava/lang/String;;
NameAndType	stringPrefix:(Lscala/collection/TraversableLike;)Ljava/lang/String;
Method	scala/collection/TraversableLike$class.stringPrefix:(Lscala/collection/TraversableLike;)Ljava/lang/String;
Asciz	addString;
Asciz	(Lscala/collection/mutable/StringBuilder;)Lscala/collection/mutable/StringBuilder;;
Asciz	(Lscala/collection/TraversableLike;Lscala/collection/mutable/StringBuilder;)Lscala/collection/mutable/StringBuilder;;
NameAndType	addString:(Lscala/collection/TraversableLike;Lscala/collection/mutable/StringBuilder;)Lscala/collection/mutable/StringBuilder;
Method	scala/collection/TraversableLike$class.addString:(Lscala/collection/TraversableLike;Lscala/collection/mutable/StringBuilder;)Lscala/collection/mutable/StringBuilder;
Asciz	b;
Asciz	Lscala/collection/mutable/StringBuilder;;
Asciz	(Lscala/collection/mutable/StringBuilder;Ljava/lang/String;)Lscala/collection/mutable/StringBuilder;;
Asciz	(Lscala/collection/TraversableLike;Lscala/collection/mutable/StringBuilder;Ljava/lang/String;)Lscala/collection/mutable/StringBuilder;;
NameAndType	addString:(Lscala/collection/TraversableLike;Lscala/collection/mutable/StringBuilder;Ljava/lang/String;)Lscala/collection/mutable/StringBuilder;
Method	scala/collection/TraversableLike$class.addString:(Lscala/collection/TraversableLike;Lscala/collection/mutable/StringBuilder;Ljava/lang/String;)Lscala/collection/mutable/StringBuilder;
Asciz	sep;
Asciz	Ljava/lang/String;;
Asciz	(Lscala/collection/mutable/StringBuilder;Ljava/lang/String;Ljava/lang/String;Ljava/lang/String;)Lscala/collection/mutable/StringBuilder;;
Asciz	(Lscala/collection/TraversableLike;Lscala/collection/mutable/StringBuilder;Ljava/lang/String;Ljava/lang/String;Ljava/lang/String;)Lscala/collection/mutable/StringBuilder;;
NameAndType	addString:(Lscala/collection/TraversableLike;Lscala/collection/mutable/StringBuilder;Ljava/lang/String;Ljava/lang/String;Ljava/lang/String;)Lscala/collection/mutable/StringBuilder;
Method	scala/collection/TraversableLike$class.addString:(Lscala/collection/TraversableLike;Lscala/collection/mutable/StringBuilder;Ljava/lang/String;Ljava/lang/String;Ljava/lang/String;)Lscala/collection/mutable/StringBuilder;
Asciz	start;
Asciz	end;
Asciz	mkString;
NameAndType	mkString:(Lscala/collection/TraversableLike;)Ljava/lang/String;
Method	scala/collection/TraversableLike$class.mkString:(Lscala/collection/TraversableLike;)Ljava/lang/String;
Asciz	(Ljava/lang/String;)Ljava/lang/String;;
Asciz	(Lscala/collection/TraversableLike;Ljava/lang/String;)Ljava/lang/String;;
NameAndType	mkString:(Lscala/collection/TraversableLike;Ljava/lang/String;)Ljava/lang/String;
Method	scala/collection/TraversableLike$class.mkString:(Lscala/collection/TraversableLike;Ljava/lang/String;)Ljava/lang/String;
Asciz	(Ljava/lang/String;Ljava/lang/String;Ljava/lang/String;)Ljava/lang/String;;
Asciz	(Lscala/collection/TraversableLike;Ljava/lang/String;Ljava/lang/String;Ljava/lang/String;)Ljava/lang/String;;
NameAndType	mkString:(Lscala/collection/TraversableLike;Ljava/lang/String;Ljava/lang/String;Ljava/lang/String;)Ljava/lang/String;
Method	scala/collection/TraversableLike$class.mkString:(Lscala/collection/TraversableLike;Ljava/lang/String;Ljava/lang/String;Ljava/lang/String;)Ljava/lang/String;
Asciz	toMap;
Asciz	(Lscala/Predef$$less$colon$less;)Lscala/collection/immutable/Map;;
Asciz	(Lscala/collection/TraversableLike;Lscala/Predef$$less$colon$less;)Lscala/collection/immutable/Map;;
NameAndType	toMap:(Lscala/collection/TraversableLike;Lscala/Predef$$less$colon$less;)Lscala/collection/immutable/Map;
Method	scala/collection/TraversableLike$class.toMap:(Lscala/collection/TraversableLike;Lscala/Predef$$less$colon$less;)Lscala/collection/immutable/Map;
Asciz	ev;
Asciz	Lscala/Predef$$less$colon$less;;
Asciz	toSet;
Asciz	()Lscala/collection/immutable/Set;;
Asciz	(Lscala/collection/TraversableLike;)Lscala/collection/immutable/Set;;
NameAndType	toSet:(Lscala/collection/TraversableLike;)Lscala/collection/immutable/Set;
Method	scala/collection/TraversableLike$class.toSet:(Lscala/collection/TraversableLike;)Lscala/collection/immutable/Set;
Asciz	toIndexedSeq;
Asciz	(Lscala/collection/TraversableLike;)Lscala/collection/mutable/IndexedSeq;;
NameAndType	toIndexedSeq:(Lscala/collection/TraversableLike;)Lscala/collection/mutable/IndexedSeq;
Method	scala/collection/TraversableLike$class.toIndexedSeq:(Lscala/collection/TraversableLike;)Lscala/collection/mutable/IndexedSeq;
Asciz	toList;
Asciz	()Lscala/collection/immutable/List;;
Asciz	(Lscala/collection/TraversableLike;)Lscala/collection/immutable/List;;
NameAndType	toList:(Lscala/collection/TraversableLike;)Lscala/collection/immutable/List;
Method	scala/collection/TraversableLike$class.toList:(Lscala/collection/TraversableLike;)Lscala/collection/immutable/List;
Asciz	toArray;
Asciz	(Lscala/reflect/ClassManifest;)Ljava/lang/Object;;
Asciz	(Lscala/collection/TraversableLike;Lscala/reflect/ClassManifest;)Ljava/lang/Object;;
NameAndType	toArray:(Lscala/collection/TraversableLike;Lscala/reflect/ClassManifest;)Ljava/lang/Object;
Method	scala/collection/TraversableLike$class.toArray:(Lscala/collection/TraversableLike;Lscala/reflect/ClassManifest;)Ljava/lang/Object;
Asciz	evidence$1;
Asciz	Lscala/reflect/ClassManifest;;
Asciz	copyToArray;
Asciz	(Ljava/lang/Object;)V;
Asciz	(Lscala/collection/TraversableLike;Ljava/lang/Object;)V;
NameAndType	copyToArray:(Lscala/collection/TraversableLike;Ljava/lang/Object;)V
Method	scala/collection/TraversableLike$class.copyToArray:(Lscala/collection/TraversableLike;Ljava/lang/Object;)V
Asciz	xs;
Asciz	(Ljava/lang/Object;I)V;
Asciz	(Lscala/collection/TraversableLike;Ljava/lang/Object;I)V;
NameAndType	copyToArray:(Lscala/collection/TraversableLike;Ljava/lang/Object;I)V
Method	scala/collection/TraversableLike$class.copyToArray:(Lscala/collection/TraversableLike;Ljava/lang/Object;I)V
Asciz	copyToBuffer;
Asciz	(Lscala/collection/mutable/Buffer;)V;
Asciz	(Lscala/collection/TraversableLike;Lscala/collection/mutable/Buffer;)V;
NameAndType	copyToBuffer:(Lscala/collection/TraversableLike;Lscala/collection/mutable/Buffer;)V
Method	scala/collection/TraversableLike$class.copyToBuffer:(Lscala/collection/TraversableLike;Lscala/collection/mutable/Buffer;)V
Asciz	dest;
Asciz	Lscala/collection/mutable/Buffer;;
Asciz	lastOption;
Asciz	()Lscala/Option;;
Asciz	(Lscala/collection/TraversableLike;)Lscala/Option;;
NameAndType	lastOption:(Lscala/collection/TraversableLike;)Lscala/Option;
Method	scala/collection/TraversableLike$class.lastOption:(Lscala/collection/TraversableLike;)Lscala/Option;
Asciz	headOption;
NameAndType	headOption:(Lscala/collection/TraversableLike;)Lscala/Option;
Method	scala/collection/TraversableLike$class.headOption:(Lscala/collection/TraversableLike;)Lscala/Option;
Asciz	max;
Asciz	(Lscala/math/Ordering;)Ljava/lang/Object;;
Asciz	(Lscala/collection/TraversableLike;Lscala/math/Ordering;)Ljava/lang/Object;;
NameAndType	max:(Lscala/collection/TraversableLike;Lscala/math/Ordering;)Ljava/lang/Object;
Method	scala/collection/TraversableLike$class.max:(Lscala/collection/TraversableLike;Lscala/math/Ordering;)Ljava/lang/Object;
Asciz	cmp;
Asciz	Lscala/math/Ordering;;
Asciz	min;
NameAndType	min:(Lscala/collection/TraversableLike;Lscala/math/Ordering;)Ljava/lang/Object;
Method	scala/collection/TraversableLike$class.min:(Lscala/collection/TraversableLike;Lscala/math/Ordering;)Ljava/lang/Object;
Asciz	product;
Asciz	(Lscala/math/Numeric;)Ljava/lang/Object;;
Asciz	(Lscala/collection/TraversableLike;Lscala/math/Numeric;)Ljava/lang/Object;;
NameAndType	product:(Lscala/collection/TraversableLike;Lscala/math/Numeric;)Ljava/lang/Object;
Method	scala/collection/TraversableLike$class.product:(Lscala/collection/TraversableLike;Lscala/math/Numeric;)Ljava/lang/Object;
Asciz	num;
Asciz	Lscala/math/Numeric;;
Asciz	sum;
NameAndType	sum:(Lscala/collection/TraversableLike;Lscala/math/Numeric;)Ljava/lang/Object;
Method	scala/collection/TraversableLike$class.sum:(Lscala/collection/TraversableLike;Lscala/math/Numeric;)Ljava/lang/Object;
Asciz	reduceRightOption;
Asciz	(Lscala/Function2;)Lscala/Option;;
Asciz	(Lscala/collection/TraversableLike;Lscala/Function2;)Lscala/Option;;
NameAndType	reduceRightOption:(Lscala/collection/TraversableLike;Lscala/Function2;)Lscala/Option;
Method	scala/collection/TraversableLike$class.reduceRightOption:(Lscala/collection/TraversableLike;Lscala/Function2;)Lscala/Option;
Asciz	op;
Asciz	Lscala/Function2;;
Asciz	reduceLeftOption;
NameAndType	reduceLeftOption:(Lscala/collection/TraversableLike;Lscala/Function2;)Lscala/Option;
Method	scala/collection/TraversableLike$class.reduceLeftOption:(Lscala/collection/TraversableLike;Lscala/Function2;)Lscala/Option;
Asciz	$colon$bslash;
Asciz	(Ljava/lang/Object;Lscala/Function2;)Ljava/lang/Object;;
Asciz	(Lscala/collection/TraversableLike;Ljava/lang/Object;Lscala/Function2;)Ljava/lang/Object;;
NameAndType	$colon$bslash:(Lscala/collection/TraversableLike;Ljava/lang/Object;Lscala/Function2;)Ljava/lang/Object;
Method	scala/collection/TraversableLike$class.$colon$bslash:(Lscala/collection/TraversableLike;Ljava/lang/Object;Lscala/Function2;)Ljava/lang/Object;
Asciz	z;
Asciz	$div$colon;
NameAndType	$div$colon:(Lscala/collection/TraversableLike;Ljava/lang/Object;Lscala/Function2;)Ljava/lang/Object;
Method	scala/collection/TraversableLike$class.$div$colon:(Lscala/collection/TraversableLike;Ljava/lang/Object;Lscala/Function2;)Ljava/lang/Object;
Asciz	count;
Asciz	(Lscala/Function1;)I;
Asciz	(Lscala/collection/TraversableLike;Lscala/Function1;)I;
NameAndType	count:(Lscala/collection/TraversableLike;Lscala/Function1;)I
Method	scala/collection/TraversableLike$class.count:(Lscala/collection/TraversableLike;Lscala/Function1;)I
Asciz	groupBy;
Asciz	(Lscala/Function1;)Lscala/collection/Map;;
Asciz	(Lscala/collection/TraversableLike;Lscala/Function1;)Lscala/collection/Map;;
NameAndType	groupBy:(Lscala/collection/TraversableLike;Lscala/Function1;)Lscala/collection/Map;
Method	scala/collection/TraversableLike$class.groupBy:(Lscala/collection/TraversableLike;Lscala/Function1;)Lscala/collection/Map;
Asciz	f;
Asciz	partition;
Asciz	(Lscala/Function1;)Lscala/Tuple2;;
Asciz	(Lscala/collection/TraversableLike;Lscala/Function1;)Lscala/Tuple2;;
NameAndType	partition:(Lscala/collection/TraversableLike;Lscala/Function1;)Lscala/Tuple2;
Method	scala/collection/TraversableLike$class.partition:(Lscala/collection/TraversableLike;Lscala/Function1;)Lscala/Tuple2;
Asciz	partialMap;
Asciz	(Lscala/PartialFunction;Lscala/collection/generic/CanBuildFrom;)Ljava/lang/Object;;
Asciz	(Lscala/collection/TraversableLike;Lscala/PartialFunction;Lscala/collection/generic/CanBuildFrom;)Ljava/lang/Object;;
NameAndType	partialMap:(Lscala/collection/TraversableLike;Lscala/PartialFunction;Lscala/collection/generic/CanBuildFrom;)Ljava/lang/Object;
Method	scala/collection/TraversableLike$class.partialMap:(Lscala/collection/TraversableLike;Lscala/PartialFunction;Lscala/collection/generic/CanBuildFrom;)Ljava/lang/Object;
Asciz	pf;
Asciz	Lscala/PartialFunction;;
Asciz	bf;
Asciz	Lscala/collection/generic/CanBuildFrom;;
Asciz	filterNot;
Asciz	(Lscala/collection/TraversableLike;Lscala/Function1;)Ljava/lang/Object;;
NameAndType	filterNot:(Lscala/collection/TraversableLike;Lscala/Function1;)Ljava/lang/Object;
Method	scala/collection/TraversableLike$class.filterNot:(Lscala/collection/TraversableLike;Lscala/Function1;)Ljava/lang/Object;
Asciz	filter;
NameAndType	filter:(Lscala/collection/TraversableLike;Lscala/Function1;)Ljava/lang/Object;
Method	scala/collection/TraversableLike$class.filter:(Lscala/collection/TraversableLike;Lscala/Function1;)Ljava/lang/Object;
Asciz	flatMap;
Asciz	(Lscala/collection/TraversableLike;Lscala/Function1;Lscala/collection/generic/CanBuildFrom;)Ljava/lang/Object;;
NameAndType	flatMap:(Lscala/collection/TraversableLike;Lscala/Function1;Lscala/collection/generic/CanBuildFrom;)Ljava/lang/Object;
Method	scala/collection/TraversableLike$class.flatMap:(Lscala/collection/TraversableLike;Lscala/Function1;Lscala/collection/generic/CanBuildFrom;)Ljava/lang/Object;
NameAndType	map:(Lscala/collection/TraversableLike;Lscala/Function1;Lscala/collection/generic/CanBuildFrom;)Ljava/lang/Object;
Method	scala/collection/TraversableLike$class.map:(Lscala/collection/TraversableLike;Lscala/Function1;Lscala/collection/generic/CanBuildFrom;)Ljava/lang/Object;
Asciz	$plus$plus;
Asciz	(Lscala/collection/Iterator;Lscala/collection/generic/CanBuildFrom;)Ljava/lang/Object;;
Asciz	(Lscala/collection/TraversableLike;Lscala/collection/Iterator;Lscala/collection/generic/CanBuildFrom;)Ljava/lang/Object;;
NameAndType	$plus$plus:(Lscala/collection/TraversableLike;Lscala/collection/Iterator;Lscala/collection/generic/CanBuildFrom;)Ljava/lang/Object;
Method	scala/collection/TraversableLike$class.$plus$plus:(Lscala/collection/TraversableLike;Lscala/collection/Iterator;Lscala/collection/generic/CanBuildFrom;)Ljava/lang/Object;
Asciz	that;
Asciz	Lscala/collection/Iterator;;
Asciz	(Lscala/collection/Traversable;Lscala/collection/generic/CanBuildFrom;)Ljava/lang/Object;;
Asciz	(Lscala/collection/TraversableLike;Lscala/collection/Traversable;Lscala/collection/generic/CanBuildFrom;)Ljava/lang/Object;;
NameAndType	$plus$plus:(Lscala/collection/TraversableLike;Lscala/collection/Traversable;Lscala/collection/generic/CanBuildFrom;)Ljava/lang/Object;
Method	scala/collection/TraversableLike$class.$plus$plus:(Lscala/collection/TraversableLike;Lscala/collection/Traversable;Lscala/collection/generic/CanBuildFrom;)Ljava/lang/Object;
Asciz	Lscala/collection/Traversable;;
Asciz	hasDefiniteSize;
Asciz	()Z;
Asciz	(Lscala/collection/TraversableLike;)Z;
NameAndType	hasDefiniteSize:(Lscala/collection/TraversableLike;)Z
Method	scala/collection/TraversableLike$class.hasDefiniteSize:(Lscala/collection/TraversableLike;)Z
Asciz	nonEmpty;
NameAndType	nonEmpty:(Lscala/collection/TraversableLike;)Z
Method	scala/collection/TraversableLike$class.nonEmpty:(Lscala/collection/TraversableLike;)Z
Asciz	(Lscala/collection/TraversableLike;)Ljava/lang/Object;;
NameAndType	repr:(Lscala/collection/TraversableLike;)Ljava/lang/Object;
Method	scala/collection/TraversableLike$class.repr:(Lscala/collection/TraversableLike;)Ljava/lang/Object;
Asciz	firstOption;
Asciz	(Lscala/collection/IterableLike;)Lscala/Option;;
NameAndType	firstOption:(Lscala/collection/IterableLike;)Lscala/Option;
Method	scala/collection/IterableLike$class.firstOption:(Lscala/collection/IterableLike;)Lscala/Option;
Asciz	Deprecated;
Asciz	first;
Asciz	(Lscala/collection/IterableLike;)Ljava/lang/Object;;
NameAndType	first:(Lscala/collection/IterableLike;)Ljava/lang/Object;
Method	scala/collection/IterableLike$class.first:(Lscala/collection/IterableLike;)Ljava/lang/Object;
Asciz	canEqual;
Asciz	(Ljava/lang/Object;)Z;
Asciz	(Lscala/collection/IterableLike;Ljava/lang/Object;)Z;
NameAndType	canEqual:(Lscala/collection/IterableLike;Ljava/lang/Object;)Z
Method	scala/collection/IterableLike$class.canEqual:(Lscala/collection/IterableLike;Ljava/lang/Object;)Z
Asciz	toStream;
Asciz	()Lscala/collection/immutable/Stream;;
Asciz	(Lscala/collection/IterableLike;)Lscala/collection/immutable/Stream;;
NameAndType	toStream:(Lscala/collection/IterableLike;)Lscala/collection/immutable/Stream;
Method	scala/collection/IterableLike$class.toStream:(Lscala/collection/IterableLike;)Lscala/collection/immutable/Stream;
Asciz	zipAll;
Asciz	(Lscala/collection/Iterable;Ljava/lang/Object;Ljava/lang/Object;Lscala/collection/generic/CanBuildFrom;)Ljava/lang/Object;;
Asciz	(Lscala/collection/IterableLike;Lscala/collection/Iterable;Ljava/lang/Object;Ljava/lang/Object;Lscala/collection/generic/CanBuildFrom;)Ljava/lang/Object;;
NameAndType	zipAll:(Lscala/collection/IterableLike;Lscala/collection/Iterable;Ljava/lang/Object;Ljava/lang/Object;Lscala/collection/generic/CanBuildFrom;)Ljava/lang/Object;
Method	scala/collection/IterableLike$class.zipAll:(Lscala/collection/IterableLike;Lscala/collection/Iterable;Ljava/lang/Object;Ljava/lang/Object;Lscala/collection/generic/CanBuildFrom;)Ljava/lang/Object;
Asciz	Lscala/collection/Iterable;;
Asciz	thisElem;
Asciz	thatElem;
Asciz	toIterable;
Asciz	(Lscala/collection/IterableLike;)Lscala/collection/Iterable;;
NameAndType	toIterable:(Lscala/collection/IterableLike;)Lscala/collection/Iterable;
Method	scala/collection/IterableLike$class.toIterable:(Lscala/collection/IterableLike;)Lscala/collection/Iterable;
Asciz	elements;
Asciz	()Lscala/collection/Iterator;;
Asciz	(Lscala/collection/IterableLike;)Lscala/collection/Iterator;;
NameAndType	elements:(Lscala/collection/IterableLike;)Lscala/collection/Iterator;
Method	scala/collection/IterableLike$class.elements:(Lscala/collection/IterableLike;)Lscala/collection/Iterator;
Asciz	(Lscala/collection/SeqLike;)Lscala/collection/SeqView;;
NameAndType	projection:(Lscala/collection/SeqLike;)Lscala/collection/SeqView;
Method	scala/collection/SeqLike$class.projection:(Lscala/collection/SeqLike;)Lscala/collection/SeqView;
Asciz	equalsWith;
Asciz	(Lscala/collection/Seq;Lscala/Function2;)Z;
Asciz	(Lscala/collection/SeqLike;Lscala/collection/Seq;Lscala/Function2;)Z;
NameAndType	equalsWith:(Lscala/collection/SeqLike;Lscala/collection/Seq;Lscala/Function2;)Z
Method	scala/collection/SeqLike$class.equalsWith:(Lscala/collection/SeqLike;Lscala/collection/Seq;Lscala/Function2;)Z
Asciz	Lscala/collection/Seq;;
Asciz	findLastIndexOf;
Asciz	(Lscala/collection/SeqLike;Lscala/Function1;)I;
NameAndType	findLastIndexOf:(Lscala/collection/SeqLike;Lscala/Function1;)I
Method	scala/collection/SeqLike$class.findLastIndexOf:(Lscala/collection/SeqLike;Lscala/Function1;)I
Asciz	toString;
Asciz	(Lscala/collection/SeqLike;)Ljava/lang/String;;
NameAndType	toString:(Lscala/collection/SeqLike;)Ljava/lang/String;
Method	scala/collection/SeqLike$class.toString:(Lscala/collection/SeqLike;)Ljava/lang/String;
Asciz	equals;
Asciz	(Lscala/collection/SeqLike;Ljava/lang/Object;)Z;
NameAndType	equals:(Lscala/collection/SeqLike;Ljava/lang/Object;)Z
Method	scala/collection/SeqLike$class.equals:(Lscala/collection/SeqLike;Ljava/lang/Object;)Z
Asciz	hashCode;
Asciz	()I;
Asciz	(Lscala/collection/SeqLike;)I;
NameAndType	hashCode:(Lscala/collection/SeqLike;)I
Method	scala/collection/SeqLike$class.hashCode:(Lscala/collection/SeqLike;)I
Asciz	indices;
Asciz	()Lscala/collection/immutable/Range;;
Asciz	(Lscala/collection/SeqLike;)Lscala/collection/immutable/Range;;
NameAndType	indices:(Lscala/collection/SeqLike;)Lscala/collection/immutable/Range;
Method	scala/collection/SeqLike$class.indices:(Lscala/collection/SeqLike;)Lscala/collection/immutable/Range;
Asciz	toSeq;
Asciz	(Lscala/collection/SeqLike;)Lscala/collection/Seq;;
NameAndType	toSeq:(Lscala/collection/SeqLike;)Lscala/collection/Seq;
Method	scala/collection/SeqLike$class.toSeq:(Lscala/collection/SeqLike;)Lscala/collection/Seq;
Asciz	sortBy;
Asciz	(Lscala/Function1;Lscala/math/Ordering;)Ljava/lang/Object;;
Asciz	(Lscala/collection/SeqLike;Lscala/Function1;Lscala/math/Ordering;)Ljava/lang/Object;;
NameAndType	sortBy:(Lscala/collection/SeqLike;Lscala/Function1;Lscala/math/Ordering;)Ljava/lang/Object;
Method	scala/collection/SeqLike$class.sortBy:(Lscala/collection/SeqLike;Lscala/Function1;Lscala/math/Ordering;)Ljava/lang/Object;
Asciz	ord;
Asciz	sortWith;
Asciz	(Lscala/collection/SeqLike;Lscala/math/Ordering;)Ljava/lang/Object;;
NameAndType	sortWith:(Lscala/collection/SeqLike;Lscala/math/Ordering;)Ljava/lang/Object;
Method	scala/collection/SeqLike$class.sortWith:(Lscala/collection/SeqLike;Lscala/math/Ordering;)Ljava/lang/Object;
Asciz	(Lscala/Function2;)Ljava/lang/Object;;
Asciz	(Lscala/collection/SeqLike;Lscala/Function2;)Ljava/lang/Object;;
NameAndType	sortWith:(Lscala/collection/SeqLike;Lscala/Function2;)Ljava/lang/Object;
Method	scala/collection/SeqLike$class.sortWith:(Lscala/collection/SeqLike;Lscala/Function2;)Ljava/lang/Object;
Asciz	lt;
Asciz	corresponds;
NameAndType	corresponds:(Lscala/collection/SeqLike;Lscala/collection/Seq;Lscala/Function2;)Z
Method	scala/collection/SeqLike$class.corresponds:(Lscala/collection/SeqLike;Lscala/collection/Seq;Lscala/Function2;)Z
Asciz	padTo;
Asciz	(ILjava/lang/Object;Lscala/collection/generic/CanBuildFrom;)Ljava/lang/Object;;
Asciz	(Lscala/collection/SeqLike;ILjava/lang/Object;Lscala/collection/generic/CanBuildFrom;)Ljava/lang/Object;;
NameAndType	padTo:(Lscala/collection/SeqLike;ILjava/lang/Object;Lscala/collection/generic/CanBuildFrom;)Ljava/lang/Object;
Method	scala/collection/SeqLike$class.padTo:(Lscala/collection/SeqLike;ILjava/lang/Object;Lscala/collection/generic/CanBuildFrom;)Ljava/lang/Object;
Asciz	len;
Asciz	elem;
Asciz	$colon$plus;
Asciz	(Ljava/lang/Object;Lscala/collection/generic/CanBuildFrom;)Ljava/lang/Object;;
Asciz	(Lscala/collection/SeqLike;Ljava/lang/Object;Lscala/collection/generic/CanBuildFrom;)Ljava/lang/Object;;
NameAndType	$colon$plus:(Lscala/collection/SeqLike;Ljava/lang/Object;Lscala/collection/generic/CanBuildFrom;)Ljava/lang/Object;
Method	scala/collection/SeqLike$class.$colon$plus:(Lscala/collection/SeqLike;Ljava/lang/Object;Lscala/collection/generic/CanBuildFrom;)Ljava/lang/Object;
Asciz	$plus$colon;
NameAndType	$plus$colon:(Lscala/collection/SeqLike;Ljava/lang/Object;Lscala/collection/generic/CanBuildFrom;)Ljava/lang/Object;
Method	scala/collection/SeqLike$class.$plus$colon:(Lscala/collection/SeqLike;Ljava/lang/Object;Lscala/collection/generic/CanBuildFrom;)Ljava/lang/Object;
Asciz	updated;
NameAndType	updated:(Lscala/collection/SeqLike;ILjava/lang/Object;Lscala/collection/generic/CanBuildFrom;)Ljava/lang/Object;
Method	scala/collection/SeqLike$class.updated:(Lscala/collection/SeqLike;ILjava/lang/Object;Lscala/collection/generic/CanBuildFrom;)Ljava/lang/Object;
Asciz	index;
Asciz	patch;
Asciz	(ILscala/collection/Seq;ILscala/collection/generic/CanBuildFrom;)Ljava/lang/Object;;
Asciz	(Lscala/collection/SeqLike;ILscala/collection/Seq;ILscala/collection/generic/CanBuildFrom;)Ljava/lang/Object;;
NameAndType	patch:(Lscala/collection/SeqLike;ILscala/collection/Seq;ILscala/collection/generic/CanBuildFrom;)Ljava/lang/Object;
Method	scala/collection/SeqLike$class.patch:(Lscala/collection/SeqLike;ILscala/collection/Seq;ILscala/collection/generic/CanBuildFrom;)Ljava/lang/Object;
Asciz	replaced;
Asciz	removeDuplicates;
Asciz	(Lscala/collection/SeqLike;)Ljava/lang/Object;;
NameAndType	removeDuplicates:(Lscala/collection/SeqLike;)Ljava/lang/Object;
Method	scala/collection/SeqLike$class.removeDuplicates:(Lscala/collection/SeqLike;)Ljava/lang/Object;
Asciz	intersect;
Asciz	(Lscala/collection/Seq;)Ljava/lang/Object;;
Asciz	(Lscala/collection/SeqLike;Lscala/collection/Seq;)Ljava/lang/Object;;
NameAndType	intersect:(Lscala/collection/SeqLike;Lscala/collection/Seq;)Ljava/lang/Object;
Method	scala/collection/SeqLike$class.intersect:(Lscala/collection/SeqLike;Lscala/collection/Seq;)Ljava/lang/Object;
Asciz	diff;
NameAndType	diff:(Lscala/collection/SeqLike;Lscala/collection/Seq;)Ljava/lang/Object;
Method	scala/collection/SeqLike$class.diff:(Lscala/collection/SeqLike;Lscala/collection/Seq;)Ljava/lang/Object;
Asciz	union;
Asciz	(Lscala/collection/Seq;Lscala/collection/generic/CanBuildFrom;)Ljava/lang/Object;;
Asciz	(Lscala/collection/SeqLike;Lscala/collection/Seq;Lscala/collection/generic/CanBuildFrom;)Ljava/lang/Object;;
NameAndType	union:(Lscala/collection/SeqLike;Lscala/collection/Seq;Lscala/collection/generic/CanBuildFrom;)Ljava/lang/Object;
Method	scala/collection/SeqLike$class.union:(Lscala/collection/SeqLike;Lscala/collection/Seq;Lscala/collection/generic/CanBuildFrom;)Ljava/lang/Object;
Asciz	contains;
NameAndType	contains:(Lscala/collection/SeqLike;Ljava/lang/Object;)Z
Method	scala/collection/SeqLike$class.contains:(Lscala/collection/SeqLike;Ljava/lang/Object;)Z
Asciz	containsSlice;
Asciz	(Lscala/collection/Seq;)Z;
Asciz	(Lscala/collection/SeqLike;Lscala/collection/Seq;)Z;
NameAndType	containsSlice:(Lscala/collection/SeqLike;Lscala/collection/Seq;)Z
Method	scala/collection/SeqLike$class.containsSlice:(Lscala/collection/SeqLike;Lscala/collection/Seq;)Z
Asciz	lastIndexOfSlice;
Asciz	(Lscala/collection/Seq;I)I;
Asciz	(Lscala/collection/SeqLike;Lscala/collection/Seq;I)I;
NameAndType	lastIndexOfSlice:(Lscala/collection/SeqLike;Lscala/collection/Seq;I)I
Method	scala/collection/SeqLike$class.lastIndexOfSlice:(Lscala/collection/SeqLike;Lscala/collection/Seq;I)I
Asciz	(Lscala/collection/Seq;)I;
Asciz	(Lscala/collection/SeqLike;Lscala/collection/Seq;)I;
NameAndType	lastIndexOfSlice:(Lscala/collection/SeqLike;Lscala/collection/Seq;)I
Method	scala/collection/SeqLike$class.lastIndexOfSlice:(Lscala/collection/SeqLike;Lscala/collection/Seq;)I
Asciz	indexOfSlice;
NameAndType	indexOfSlice:(Lscala/collection/SeqLike;Lscala/collection/Seq;I)I
Method	scala/collection/SeqLike$class.indexOfSlice:(Lscala/collection/SeqLike;Lscala/collection/Seq;I)I
NameAndType	indexOfSlice:(Lscala/collection/SeqLike;Lscala/collection/Seq;)I
Method	scala/collection/SeqLike$class.indexOfSlice:(Lscala/collection/SeqLike;Lscala/collection/Seq;)I
Asciz	startsWith;
NameAndType	startsWith:(Lscala/collection/SeqLike;Lscala/collection/Seq;)Z
Method	scala/collection/SeqLike$class.startsWith:(Lscala/collection/SeqLike;Lscala/collection/Seq;)Z
Asciz	reversedElements;
Asciz	(Lscala/collection/SeqLike;)Lscala/collection/Iterator;;
NameAndType	reversedElements:(Lscala/collection/SeqLike;)Lscala/collection/Iterator;
Method	scala/collection/SeqLike$class.reversedElements:(Lscala/collection/SeqLike;)Lscala/collection/Iterator;
Asciz	reverseMap;
Asciz	(Lscala/collection/SeqLike;Lscala/Function1;Lscala/collection/generic/CanBuildFrom;)Ljava/lang/Object;;
NameAndType	reverseMap:(Lscala/collection/SeqLike;Lscala/Function1;Lscala/collection/generic/CanBuildFrom;)Ljava/lang/Object;
Method	scala/collection/SeqLike$class.reverseMap:(Lscala/collection/SeqLike;Lscala/Function1;Lscala/collection/generic/CanBuildFrom;)Ljava/lang/Object;
Asciz	lastIndexWhere;
NameAndType	lastIndexWhere:(Lscala/collection/SeqLike;Lscala/Function1;)I
Method	scala/collection/SeqLike$class.lastIndexWhere:(Lscala/collection/SeqLike;Lscala/Function1;)I
Asciz	lastIndexOf;
Asciz	(Ljava/lang/Object;I)I;
Asciz	(Lscala/collection/SeqLike;Ljava/lang/Object;I)I;
NameAndType	lastIndexOf:(Lscala/collection/SeqLike;Ljava/lang/Object;I)I
Method	scala/collection/SeqLike$class.lastIndexOf:(Lscala/collection/SeqLike;Ljava/lang/Object;I)I
Asciz	(Ljava/lang/Object;)I;
Asciz	(Lscala/collection/SeqLike;Ljava/lang/Object;)I;
NameAndType	lastIndexOf:(Lscala/collection/SeqLike;Ljava/lang/Object;)I
Method	scala/collection/SeqLike$class.lastIndexOf:(Lscala/collection/SeqLike;Ljava/lang/Object;)I
Asciz	indexOf;
NameAndType	indexOf:(Lscala/collection/SeqLike;Ljava/lang/Object;I)I
Method	scala/collection/SeqLike$class.indexOf:(Lscala/collection/SeqLike;Ljava/lang/Object;I)I
NameAndType	indexOf:(Lscala/collection/SeqLike;Ljava/lang/Object;)I
Method	scala/collection/SeqLike$class.indexOf:(Lscala/collection/SeqLike;Ljava/lang/Object;)I
Asciz	findIndexOf;
NameAndType	findIndexOf:(Lscala/collection/SeqLike;Lscala/Function1;)I
Method	scala/collection/SeqLike$class.findIndexOf:(Lscala/collection/SeqLike;Lscala/Function1;)I
Asciz	indexWhere;
NameAndType	indexWhere:(Lscala/collection/SeqLike;Lscala/Function1;)I
Method	scala/collection/SeqLike$class.indexWhere:(Lscala/collection/SeqLike;Lscala/Function1;)I
Asciz	prefixLength;
NameAndType	prefixLength:(Lscala/collection/SeqLike;Lscala/Function1;)I
Method	scala/collection/SeqLike$class.prefixLength:(Lscala/collection/SeqLike;Lscala/Function1;)I
Asciz	isDefinedAt;
Asciz	(I)Z;
Asciz	(Lscala/collection/SeqLike;I)Z;
NameAndType	isDefinedAt:(Lscala/collection/SeqLike;I)Z
Method	scala/collection/SeqLike$class.isDefinedAt:(Lscala/collection/SeqLike;I)Z
Asciz	idx;
Asciz	size;
NameAndType	size:(Lscala/collection/SeqLike;)I
Method	scala/collection/SeqLike$class.size:(Lscala/collection/SeqLike;)I
Asciz	endsWith;
Asciz	(Lscala/collection/IndexedSeqLike;Lscala/collection/Seq;)Z;
NameAndType	endsWith:(Lscala/collection/IndexedSeqLike;Lscala/collection/Seq;)Z
Method	scala/collection/IndexedSeqLike$class.endsWith:(Lscala/collection/IndexedSeqLike;Lscala/collection/Seq;)Z
Asciz	(Lscala/collection/Seq;I)Z;
Asciz	(Lscala/collection/IndexedSeqLike;Lscala/collection/Seq;I)Z;
NameAndType	startsWith:(Lscala/collection/IndexedSeqLike;Lscala/collection/Seq;I)Z
Method	scala/collection/IndexedSeqLike$class.startsWith:(Lscala/collection/IndexedSeqLike;Lscala/collection/Seq;I)Z
Asciz	offset;
Asciz	reverseIterator;
Asciz	(Lscala/collection/IndexedSeqLike;)Lscala/collection/Iterator;;
NameAndType	reverseIterator:(Lscala/collection/IndexedSeqLike;)Lscala/collection/Iterator;
Method	scala/collection/IndexedSeqLike$class.reverseIterator:(Lscala/collection/IndexedSeqLike;)Lscala/collection/Iterator;
Asciz	reverse;
Asciz	(Lscala/collection/IndexedSeqLike;)Ljava/lang/Object;;
NameAndType	reverse:(Lscala/collection/IndexedSeqLike;)Ljava/lang/Object;
Method	scala/collection/IndexedSeqLike$class.reverse:(Lscala/collection/IndexedSeqLike;)Ljava/lang/Object;
Asciz	(Lscala/Function1;I)I;
Asciz	(Lscala/collection/IndexedSeqLike;Lscala/Function1;I)I;
NameAndType	lastIndexWhere:(Lscala/collection/IndexedSeqLike;Lscala/Function1;I)I
Method	scala/collection/IndexedSeqLike$class.lastIndexWhere:(Lscala/collection/IndexedSeqLike;Lscala/Function1;I)I
NameAndType	indexWhere:(Lscala/collection/IndexedSeqLike;Lscala/Function1;I)I
Method	scala/collection/IndexedSeqLike$class.indexWhere:(Lscala/collection/IndexedSeqLike;Lscala/Function1;I)I
Asciz	segmentLength;
NameAndType	segmentLength:(Lscala/collection/IndexedSeqLike;Lscala/Function1;I)I
Method	scala/collection/IndexedSeqLike$class.segmentLength:(Lscala/collection/IndexedSeqLike;Lscala/Function1;I)I
Asciz	lengthCompare;
Asciz	(I)I;
Asciz	(Lscala/collection/IndexedSeqLike;I)I;
NameAndType	lengthCompare:(Lscala/collection/IndexedSeqLike;I)I
Method	scala/collection/IndexedSeqLike$class.lengthCompare:(Lscala/collection/IndexedSeqLike;I)I
Asciz	(Ljava/lang/Object;II)V;
Asciz	(Lscala/collection/IndexedSeqLike;Ljava/lang/Object;II)V;
NameAndType	copyToArray:(Lscala/collection/IndexedSeqLike;Ljava/lang/Object;II)V
Method	scala/collection/IndexedSeqLike$class.copyToArray:(Lscala/collection/IndexedSeqLike;Ljava/lang/Object;II)V
Asciz	sameElements;
Asciz	(Lscala/collection/Iterable;)Z;
Asciz	(Lscala/collection/IndexedSeqLike;Lscala/collection/Iterable;)Z;
NameAndType	sameElements:(Lscala/collection/IndexedSeqLike;Lscala/collection/Iterable;)Z
Method	scala/collection/IndexedSeqLike$class.sameElements:(Lscala/collection/IndexedSeqLike;Lscala/collection/Iterable;)Z
Asciz	span;
Asciz	(Lscala/collection/IndexedSeqLike;Lscala/Function1;)Lscala/Tuple2;;
NameAndType	span:(Lscala/collection/IndexedSeqLike;Lscala/Function1;)Lscala/Tuple2;
Method	scala/collection/IndexedSeqLike$class.span:(Lscala/collection/IndexedSeqLike;Lscala/Function1;)Lscala/Tuple2;
Asciz	dropWhile;
Asciz	(Lscala/collection/IndexedSeqLike;Lscala/Function1;)Ljava/lang/Object;;
NameAndType	dropWhile:(Lscala/collection/IndexedSeqLike;Lscala/Function1;)Ljava/lang/Object;
Method	scala/collection/IndexedSeqLike$class.dropWhile:(Lscala/collection/IndexedSeqLike;Lscala/Function1;)Ljava/lang/Object;
Asciz	takeWhile;
NameAndType	takeWhile:(Lscala/collection/IndexedSeqLike;Lscala/Function1;)Ljava/lang/Object;
Method	scala/collection/IndexedSeqLike$class.takeWhile:(Lscala/collection/IndexedSeqLike;Lscala/Function1;)Ljava/lang/Object;
Asciz	splitAt;
Asciz	(I)Lscala/Tuple2;;
Asciz	(Lscala/collection/IndexedSeqLike;I)Lscala/Tuple2;;
NameAndType	splitAt:(Lscala/collection/IndexedSeqLike;I)Lscala/Tuple2;
Method	scala/collection/IndexedSeqLike$class.splitAt:(Lscala/collection/IndexedSeqLike;I)Lscala/Tuple2;
Asciz	n;
Asciz	dropRight;
Asciz	(I)Ljava/lang/Object;;
Asciz	(Lscala/collection/IndexedSeqLike;I)Ljava/lang/Object;;
NameAndType	dropRight:(Lscala/collection/IndexedSeqLike;I)Ljava/lang/Object;
Method	scala/collection/IndexedSeqLike$class.dropRight:(Lscala/collection/IndexedSeqLike;I)Ljava/lang/Object;
Asciz	takeRight;
NameAndType	takeRight:(Lscala/collection/IndexedSeqLike;I)Ljava/lang/Object;
Method	scala/collection/IndexedSeqLike$class.takeRight:(Lscala/collection/IndexedSeqLike;I)Ljava/lang/Object;
Asciz	drop;
NameAndType	drop:(Lscala/collection/IndexedSeqLike;I)Ljava/lang/Object;
Method	scala/collection/IndexedSeqLike$class.drop:(Lscala/collection/IndexedSeqLike;I)Ljava/lang/Object;
Asciz	take;
NameAndType	take:(Lscala/collection/IndexedSeqLike;I)Ljava/lang/Object;
Method	scala/collection/IndexedSeqLike$class.take:(Lscala/collection/IndexedSeqLike;I)Ljava/lang/Object;
Asciz	init;
NameAndType	init:(Lscala/collection/IndexedSeqLike;)Ljava/lang/Object;
Method	scala/collection/IndexedSeqLike$class.init:(Lscala/collection/IndexedSeqLike;)Ljava/lang/Object;
Asciz	last;
NameAndType	last:(Lscala/collection/IndexedSeqLike;)Ljava/lang/Object;
Method	scala/collection/IndexedSeqLike$class.last:(Lscala/collection/IndexedSeqLike;)Ljava/lang/Object;
Asciz	tail;
NameAndType	tail:(Lscala/collection/IndexedSeqLike;)Ljava/lang/Object;
Method	scala/collection/IndexedSeqLike$class.tail:(Lscala/collection/IndexedSeqLike;)Ljava/lang/Object;
NameAndType	head:(Lscala/collection/IndexedSeqLike;)Ljava/lang/Object;
Method	scala/collection/IndexedSeqLike$class.head:(Lscala/collection/IndexedSeqLike;)Ljava/lang/Object;
Asciz	slice;
Asciz	(II)Ljava/lang/Object;;
Asciz	(Lscala/collection/IndexedSeqLike;II)Ljava/lang/Object;;
NameAndType	slice:(Lscala/collection/IndexedSeqLike;II)Ljava/lang/Object;
Method	scala/collection/IndexedSeqLike$class.slice:(Lscala/collection/IndexedSeqLike;II)Ljava/lang/Object;
Asciz	zipWithIndex;
Asciz	(Lscala/collection/generic/CanBuildFrom;)Ljava/lang/Object;;
Asciz	(Lscala/collection/IndexedSeqLike;Lscala/collection/generic/CanBuildFrom;)Ljava/lang/Object;;
NameAndType	zipWithIndex:(Lscala/collection/IndexedSeqLike;Lscala/collection/generic/CanBuildFrom;)Ljava/lang/Object;
Method	scala/collection/IndexedSeqLike$class.zipWithIndex:(Lscala/collection/IndexedSeqLike;Lscala/collection/generic/CanBuildFrom;)Ljava/lang/Object;
Asciz	zip;
Asciz	(Lscala/collection/Iterable;Lscala/collection/generic/CanBuildFrom;)Ljava/lang/Object;;
Asciz	(Lscala/collection/IndexedSeqLike;Lscala/collection/Iterable;Lscala/collection/generic/CanBuildFrom;)Ljava/lang/Object;;
NameAndType	zip:(Lscala/collection/IndexedSeqLike;Lscala/collection/Iterable;Lscala/collection/generic/CanBuildFrom;)Ljava/lang/Object;
Method	scala/collection/IndexedSeqLike$class.zip:(Lscala/collection/IndexedSeqLike;Lscala/collection/Iterable;Lscala/collection/generic/CanBuildFrom;)Ljava/lang/Object;
Asciz	reduceRight;
Asciz	(Lscala/collection/IndexedSeqLike;Lscala/Function2;)Ljava/lang/Object;;
NameAndType	reduceRight:(Lscala/collection/IndexedSeqLike;Lscala/Function2;)Ljava/lang/Object;
Method	scala/collection/IndexedSeqLike$class.reduceRight:(Lscala/collection/IndexedSeqLike;Lscala/Function2;)Ljava/lang/Object;
Asciz	reduceLeft;
NameAndType	reduceLeft:(Lscala/collection/IndexedSeqLike;Lscala/Function2;)Ljava/lang/Object;
Method	scala/collection/IndexedSeqLike$class.reduceLeft:(Lscala/collection/IndexedSeqLike;Lscala/Function2;)Ljava/lang/Object;
Asciz	foldRight;
Asciz	(Lscala/collection/IndexedSeqLike;Ljava/lang/Object;Lscala/Function2;)Ljava/lang/Object;;
NameAndType	foldRight:(Lscala/collection/IndexedSeqLike;Ljava/lang/Object;Lscala/Function2;)Ljava/lang/Object;
Method	scala/collection/IndexedSeqLike$class.foldRight:(Lscala/collection/IndexedSeqLike;Ljava/lang/Object;Lscala/Function2;)Ljava/lang/Object;
Asciz	foldLeft;
NameAndType	foldLeft:(Lscala/collection/IndexedSeqLike;Ljava/lang/Object;Lscala/Function2;)Ljava/lang/Object;
Method	scala/collection/IndexedSeqLike$class.foldLeft:(Lscala/collection/IndexedSeqLike;Ljava/lang/Object;Lscala/Function2;)Ljava/lang/Object;
Asciz	find;
Asciz	(Lscala/Function1;)Lscala/Option;;
Asciz	(Lscala/collection/IndexedSeqLike;Lscala/Function1;)Lscala/Option;;
NameAndType	find:(Lscala/collection/IndexedSeqLike;Lscala/Function1;)Lscala/Option;
Method	scala/collection/IndexedSeqLike$class.find:(Lscala/collection/IndexedSeqLike;Lscala/Function1;)Lscala/Option;
Asciz	exists;
Asciz	(Lscala/Function1;)Z;
Asciz	(Lscala/collection/IndexedSeqLike;Lscala/Function1;)Z;
NameAndType	exists:(Lscala/collection/IndexedSeqLike;Lscala/Function1;)Z
Method	scala/collection/IndexedSeqLike$class.exists:(Lscala/collection/IndexedSeqLike;Lscala/Function1;)Z
Asciz	forall;
NameAndType	forall:(Lscala/collection/IndexedSeqLike;Lscala/Function1;)Z
Method	scala/collection/IndexedSeqLike$class.forall:(Lscala/collection/IndexedSeqLike;Lscala/Function1;)Z
Asciz	(Lscala/collection/IndexedSeqLike;Lscala/Function1;)V;
NameAndType	foreach:(Lscala/collection/IndexedSeqLike;Lscala/Function1;)V
Method	scala/collection/IndexedSeqLike$class.foreach:(Lscala/collection/IndexedSeqLike;Lscala/Function1;)V
Asciz	isEmpty;
Asciz	(Lscala/collection/IndexedSeqLike;)Z;
NameAndType	isEmpty:(Lscala/collection/IndexedSeqLike;)Z
Method	scala/collection/IndexedSeqLike$class.isEmpty:(Lscala/collection/IndexedSeqLike;)Z
Asciz	iterator;
NameAndType	iterator:(Lscala/collection/IndexedSeqLike;)Lscala/collection/Iterator;
Method	scala/collection/IndexedSeqLike$class.iterator:(Lscala/collection/IndexedSeqLike;)Lscala/collection/Iterator;
Asciz	scala$collection$IndexedSeqLike$$super$endsWith;
NameAndType	endsWith:(Lscala/collection/SeqLike;Lscala/collection/Seq;)Z
Method	scala/collection/SeqLike$class.endsWith:(Lscala/collection/SeqLike;Lscala/collection/Seq;)Z
Asciz	scala$collection$IndexedSeqLike$$super$sameElements;
Asciz	(Lscala/collection/IterableLike;Lscala/collection/Iterable;)Z;
NameAndType	sameElements:(Lscala/collection/IterableLike;Lscala/collection/Iterable;)Z
Method	scala/collection/IterableLike$class.sameElements:(Lscala/collection/IterableLike;Lscala/collection/Iterable;)Z
Asciz	scala$collection$IndexedSeqLike$$super$init;
NameAndType	init:(Lscala/collection/TraversableLike;)Ljava/lang/Object;
Method	scala/collection/TraversableLike$class.init:(Lscala/collection/TraversableLike;)Ljava/lang/Object;
Asciz	scala$collection$IndexedSeqLike$$super$last;
NameAndType	last:(Lscala/collection/TraversableLike;)Ljava/lang/Object;
Method	scala/collection/TraversableLike$class.last:(Lscala/collection/TraversableLike;)Ljava/lang/Object;
Asciz	scala$collection$IndexedSeqLike$$super$tail;
NameAndType	tail:(Lscala/collection/TraversableLike;)Ljava/lang/Object;
Method	scala/collection/TraversableLike$class.tail:(Lscala/collection/TraversableLike;)Ljava/lang/Object;
Asciz	scala$collection$IndexedSeqLike$$super$head;
NameAndType	head:(Lscala/collection/IterableLike;)Ljava/lang/Object;
Method	scala/collection/IterableLike$class.head:(Lscala/collection/IterableLike;)Ljava/lang/Object;
Asciz	scala$collection$IndexedSeqLike$$super$zip;
Asciz	(Lscala/collection/IterableLike;Lscala/collection/Iterable;Lscala/collection/generic/CanBuildFrom;)Ljava/lang/Object;;
NameAndType	zip:(Lscala/collection/IterableLike;Lscala/collection/Iterable;Lscala/collection/generic/CanBuildFrom;)Ljava/lang/Object;
Method	scala/collection/IterableLike$class.zip:(Lscala/collection/IterableLike;Lscala/collection/Iterable;Lscala/collection/generic/CanBuildFrom;)Ljava/lang/Object;
Asciz	scala$collection$IndexedSeqLike$$super$reduceRight;
Asciz	(Lscala/collection/IterableLike;Lscala/Function2;)Ljava/lang/Object;;
NameAndType	reduceRight:(Lscala/collection/IterableLike;Lscala/Function2;)Ljava/lang/Object;
Method	scala/collection/IterableLike$class.reduceRight:(Lscala/collection/IterableLike;Lscala/Function2;)Ljava/lang/Object;
Asciz	scala$collection$IndexedSeqLike$$super$reduceLeft;
Asciz	(Lscala/collection/TraversableLike;Lscala/Function2;)Ljava/lang/Object;;
NameAndType	reduceLeft:(Lscala/collection/TraversableLike;Lscala/Function2;)Ljava/lang/Object;
Method	scala/collection/TraversableLike$class.reduceLeft:(Lscala/collection/TraversableLike;Lscala/Function2;)Ljava/lang/Object;
Asciz	(Lscala/collection/mutable/IndexedSeqLike;II)Lscala/collection/mutable/IndexedSeqView;;
NameAndType	view:(Lscala/collection/mutable/IndexedSeqLike;II)Lscala/collection/mutable/IndexedSeqView;
Method	scala/collection/mutable/IndexedSeqLike$class.view:(Lscala/collection/mutable/IndexedSeqLike;II)Lscala/collection/mutable/IndexedSeqView;
Asciz	(Lscala/collection/mutable/IndexedSeqLike;)Lscala/collection/mutable/IndexedSeqView;;
NameAndType	view:(Lscala/collection/mutable/IndexedSeqLike;)Lscala/collection/mutable/IndexedSeqView;
Method	scala/collection/mutable/IndexedSeqLike$class.view:(Lscala/collection/mutable/IndexedSeqLike;)Lscala/collection/mutable/IndexedSeqView;
Asciz	(Lscala/collection/mutable/IndexedSeqLike;Ljava/lang/Object;)Lscala/collection/mutable/IndexedSeq;;
NameAndType	toCollection:(Lscala/collection/mutable/IndexedSeqLike;Ljava/lang/Object;)Lscala/collection/mutable/IndexedSeq;
Method	scala/collection/mutable/IndexedSeqLike$class.toCollection:(Lscala/collection/mutable/IndexedSeqLike;Ljava/lang/Object;)Lscala/collection/mutable/IndexedSeq;
Asciz	(Lscala/collection/mutable/IndexedSeqLike;)Lscala/collection/mutable/IndexedSeq;;
NameAndType	thisCollection:(Lscala/collection/mutable/IndexedSeqLike;)Lscala/collection/mutable/IndexedSeq;
Method	scala/collection/mutable/IndexedSeqLike$class.thisCollection:(Lscala/collection/mutable/IndexedSeqLike;)Lscala/collection/mutable/IndexedSeq;
Asciz	deepEquals;
Asciz	(Lscala/collection/mutable/ArrayLike;Ljava/lang/Object;)Z;
NameAndType	deepEquals:(Lscala/collection/mutable/ArrayLike;Ljava/lang/Object;)Z
Method	scala/collection/mutable/ArrayLike$class.deepEquals:(Lscala/collection/mutable/ArrayLike;Ljava/lang/Object;)Z
Asciz	deepMkString;
Asciz	(Lscala/collection/mutable/ArrayLike;Ljava/lang/String;)Ljava/lang/String;;
NameAndType	deepMkString:(Lscala/collection/mutable/ArrayLike;Ljava/lang/String;)Ljava/lang/String;
Method	scala/collection/mutable/ArrayLike$class.deepMkString:(Lscala/collection/mutable/ArrayLike;Ljava/lang/String;)Ljava/lang/String;
Asciz	(Lscala/collection/mutable/ArrayLike;Ljava/lang/String;Ljava/lang/String;Ljava/lang/String;)Ljava/lang/String;;
NameAndType	deepMkString:(Lscala/collection/mutable/ArrayLike;Ljava/lang/String;Ljava/lang/String;Ljava/lang/String;)Ljava/lang/String;
Method	scala/collection/mutable/ArrayLike$class.deepMkString:(Lscala/collection/mutable/ArrayLike;Ljava/lang/String;Ljava/lang/String;Ljava/lang/String;)Ljava/lang/String;
Asciz	deepToString;
Asciz	(Lscala/collection/mutable/ArrayLike;)Ljava/lang/String;;
NameAndType	deepToString:(Lscala/collection/mutable/ArrayLike;)Ljava/lang/String;
Method	scala/collection/mutable/ArrayLike$class.deepToString:(Lscala/collection/mutable/ArrayLike;)Ljava/lang/String;
Asciz	deep;
Asciz	(Lscala/collection/mutable/ArrayLike;)Lscala/collection/IndexedSeq;;
NameAndType	deep:(Lscala/collection/mutable/ArrayLike;)Lscala/collection/IndexedSeq;
Method	scala/collection/mutable/ArrayLike$class.deep:(Lscala/collection/mutable/ArrayLike;)Lscala/collection/IndexedSeq;
Asciz	<T:Ljava/lang/Object;>Ljava/lang/Object;Lscala/collection/mutable/ArrayLike<TT;[TT;>;Lscala/ScalaObject;;
Asciz	ScalaSig;
Asciz	InnerClasses;
Asciz	scala/collection/mutable/ArrayOps$ofInt;
class	scala/collection/mutable/ArrayOps$ofInt
Asciz	ofInt;
Asciz	scala/collection/mutable/ArrayOps$ofRef;
class	scala/collection/mutable/ArrayOps$ofRef
Asciz	ofRef;
Asciz	scala/collection/mutable/ArrayOps$ofUnit;
class	scala/collection/mutable/ArrayOps$ofUnit
Asciz	ofUnit;
Asciz	scala/collection/mutable/ArrayOps$ofLong;
class	scala/collection/mutable/ArrayOps$ofLong
Asciz	ofLong;
Asciz	scala/collection/mutable/ArrayOps$ofChar;
class	scala/collection/mutable/ArrayOps$ofChar
Asciz	ofChar;
Asciz	scala/collection/mutable/ArrayOps$ofByte;
class	scala/collection/mutable/ArrayOps$ofByte
Asciz	ofByte;
Asciz	scala/collection/mutable/ArrayOps$ofFloat;
class	scala/collection/mutable/ArrayOps$ofFloat
Asciz	ofFloat;
Asciz	scala/collection/mutable/ArrayOps$ofShort;
class	scala/collection/mutable/ArrayOps$ofShort
Asciz	ofShort;
Asciz	scala/collection/mutable/ArrayOps$ofDouble;
class	scala/collection/mutable/ArrayOps$ofDouble
Asciz	ofDouble;
Asciz	scala/collection/mutable/ArrayOps$ofBoolean;
class	scala/collection/mutable/ArrayOps$ofBoolean
Asciz	ofBoolean;
Asciz	$anonfun$1;
Asciz	scala/Predef$$less$colon$less;
class	scala/Predef$$less$colon$less
Asciz	scala/Predef;
class	scala/Predef
Asciz	$less$colon$less;
Asciz	scala/collection/TraversableLike$WithFilter;
class	scala/collection/TraversableLike$WithFilter
Asciz	WithFilter;
Asciz	$anonfun$flatten$1;
Asciz	$anonfun$transpose$2;
Asciz	$anonfun$transpose$1;
Asciz	scala/collection/mutable/ArrayLike;
class	scala/collection/mutable/ArrayLike
Asciz	scala/ScalaObject;
class	scala/ScalaObject

{
public scala.collection.mutable.ArrayOps();
  Signature: ()V
  Code:
   Stack=1, Locals=1, Args_size=1
	aload_0
	invokespecial	Method java/lang/Object."<init>":()V
	aload_0
	invokestatic	Method scala/collection/TraversableLike$class.$init$:(Lscala/collection/TraversableLike;)V
	aload_0
	invokestatic	Method scala/collection/IterableLike$class.$init$:(Lscala/collection/IterableLike;)V
	aload_0
	invokestatic	Method scala/collection/SeqLike$class.$init$:(Lscala/collection/SeqLike;)V
	aload_0
	invokestatic	Method scala/collection/IndexedSeqLike$class.$init$:(Lscala/collection/IndexedSeqLike;)V
	aload_0
	invokestatic	Method scala/collection/mutable/IndexedSeqLike$class.$init$:(Lscala/collection/mutable/IndexedSeqLike;)V
	aload_0
	invokestatic	Method scala/collection/mutable/ArrayLike$class.$init$:(Lscala/collection/mutable/ArrayLike;)V
	return
  Labels:
  Signature: length = 0x2
   00 04 

public scala.collection.IndexedSeq thisCollection();
  Signature: ()Lscala/collection/IndexedSeq;
  Code:
   Stack=1, Locals=1, Args_size=1
	aload_0
	invokeinterface	InterfaceMethod scala/collection/mutable/IndexedSeqLike.thisCollection:()Lscala/collection/mutable/IndexedSeq;
	areturn
  Labels:

public scala.collection.Seq thisCollection();
  Signature: ()Lscala/collection/Seq;
  Code:
   Stack=1, Locals=1, Args_size=1
	aload_0
	invokeinterface	InterfaceMethod scala/collection/mutable/IndexedSeqLike.thisCollection:()Lscala/collection/mutable/IndexedSeq;
	areturn
  Labels:

public scala.collection.Iterable thisCollection();
  Signature: ()Lscala/collection/Iterable;
  Code:
   Stack=1, Locals=1, Args_size=1
	aload_0
	invokeinterface	InterfaceMethod scala/collection/mutable/IndexedSeqLike.thisCollection:()Lscala/collection/mutable/IndexedSeq;
	areturn
  Labels:

public scala.collection.Traversable thisCollection();
  Signature: ()Lscala/collection/Traversable;
  Code:
   Stack=1, Locals=1, Args_size=1
	aload_0
	invokeinterface	InterfaceMethod scala/collection/mutable/IndexedSeqLike.thisCollection:()Lscala/collection/mutable/IndexedSeq;
	areturn
  Labels:

public scala.collection.IndexedSeq toCollection(java.lang.Object);
  Signature: (Ljava/lang/Object;)Lscala/collection/IndexedSeq;
  Code:
   Stack=2, Locals=2, Args_size=2
	aload_0
	aload_1
	invokeinterface	InterfaceMethod scala/collection/mutable/IndexedSeqLike.toCollection:(Ljava/lang/Object;)Lscala/collection/mutable/IndexedSeq;
	areturn
  Labels:
  LocalVariableTable: 
   Start  Length  Slot  Name   Signature
   0      8      0    this       Lscala/collection/mutable/ArrayOps;
   0      8      1    repr       Ljava/lang/Object;


public scala.collection.Seq toCollection(java.lang.Object);
  Signature: (Ljava/lang/Object;)Lscala/collection/Seq;
  Code:
   Stack=2, Locals=2, Args_size=2
	aload_0
	aload_1
	invokeinterface	InterfaceMethod scala/collection/mutable/IndexedSeqLike.toCollection:(Ljava/lang/Object;)Lscala/collection/mutable/IndexedSeq;
	areturn
  Labels:
  LocalVariableTable: 
   Start  Length  Slot  Name   Signature
   0      8      0    this       Lscala/collection/mutable/ArrayOps;
   0      8      1    repr       Ljava/lang/Object;


public scala.collection.Iterable toCollection(java.lang.Object);
  Signature: (Ljava/lang/Object;)Lscala/collection/Iterable;
  Code:
   Stack=2, Locals=2, Args_size=2
	aload_0
	aload_1
	invokeinterface	InterfaceMethod scala/collection/mutable/IndexedSeqLike.toCollection:(Ljava/lang/Object;)Lscala/collection/mutable/IndexedSeq;
	areturn
  Labels:
  LocalVariableTable: 
   Start  Length  Slot  Name   Signature
   0      8      0    this       Lscala/collection/mutable/ArrayOps;
   0      8      1    repr       Ljava/lang/Object;


public scala.collection.Traversable toCollection(java.lang.Object);
  Signature: (Ljava/lang/Object;)Lscala/collection/Traversable;
  Code:
   Stack=2, Locals=2, Args_size=2
	aload_0
	aload_1
	invokeinterface	InterfaceMethod scala/collection/mutable/IndexedSeqLike.toCollection:(Ljava/lang/Object;)Lscala/collection/mutable/IndexedSeq;
	areturn
  Labels:
  LocalVariableTable: 
   Start  Length  Slot  Name   Signature
   0      8      0    this       Lscala/collection/mutable/ArrayOps;
   0      8      1    repr       Ljava/lang/Object;


public scala.collection.IndexedSeqView view();
  Signature: ()Lscala/collection/IndexedSeqView;
  Code:
   Stack=1, Locals=1, Args_size=1
	aload_0
	invokeinterface	InterfaceMethod scala/collection/mutable/IndexedSeqLike.view:()Lscala/collection/mutable/IndexedSeqView;
	areturn
  Labels:

public scala.collection.SeqView view();
  Signature: ()Lscala/collection/SeqView;
  Code:
   Stack=1, Locals=1, Args_size=1
	aload_0
	invokeinterface	InterfaceMethod scala/collection/mutable/IndexedSeqLike.view:()Lscala/collection/mutable/IndexedSeqView;
	areturn
  Labels:

public scala.collection.IterableView view();
  Signature: ()Lscala/collection/IterableView;
  Code:
   Stack=1, Locals=1, Args_size=1
	aload_0
	invokeinterface	InterfaceMethod scala/collection/mutable/IndexedSeqLike.view:()Lscala/collection/mutable/IndexedSeqView;
	areturn
  Labels:

public scala.collection.TraversableView view();
  Signature: ()Lscala/collection/TraversableView;
  Code:
   Stack=1, Locals=1, Args_size=1
	aload_0
	invokeinterface	InterfaceMethod scala/collection/mutable/IndexedSeqLike.view:()Lscala/collection/mutable/IndexedSeqView;
	areturn
  Labels:

public scala.collection.IndexedSeqView view(int, int);
  Signature: (II)Lscala/collection/IndexedSeqView;
  Code:
   Stack=3, Locals=3, Args_size=3
	aload_0
	iload_1
	iload_2
	invokeinterface	InterfaceMethod scala/collection/mutable/IndexedSeqLike.view:(II)Lscala/collection/mutable/IndexedSeqView;
	areturn
  Labels:
  LocalVariableTable: 
   Start  Length  Slot  Name   Signature
   0      9      0    this       Lscala/collection/mutable/ArrayOps;
   0      9      1    from       I
   0      9      2    until       I


public scala.collection.SeqView view(int, int);
  Signature: (II)Lscala/collection/SeqView;
  Code:
   Stack=3, Locals=3, Args_size=3
	aload_0
	iload_1
	iload_2
	invokeinterface	InterfaceMethod scala/collection/mutable/IndexedSeqLike.view:(II)Lscala/collection/mutable/IndexedSeqView;
	areturn
  Labels:
  LocalVariableTable: 
   Start  Length  Slot  Name   Signature
   0      9      0    this       Lscala/collection/mutable/ArrayOps;
   0      9      1    from       I
   0      9      2    until       I


public scala.collection.IterableView view(int, int);
  Signature: (II)Lscala/collection/IterableView;
  Code:
   Stack=3, Locals=3, Args_size=3
	aload_0
	iload_1
	iload_2
	invokeinterface	InterfaceMethod scala/collection/mutable/IndexedSeqLike.view:(II)Lscala/collection/mutable/IndexedSeqView;
	areturn
  Labels:
  LocalVariableTable: 
   Start  Length  Slot  Name   Signature
   0      9      0    this       Lscala/collection/mutable/ArrayOps;
   0      9      1    from       I
   0      9      2    until       I


public scala.collection.TraversableView view(int, int);
  Signature: (II)Lscala/collection/TraversableView;
  Code:
   Stack=3, Locals=3, Args_size=3
	aload_0
	iload_1
	iload_2
	invokeinterface	InterfaceMethod scala/collection/mutable/IndexedSeqLike.view:(II)Lscala/collection/mutable/IndexedSeqView;
	areturn
  Labels:
  LocalVariableTable: 
   Start  Length  Slot  Name   Signature
   0      9      0    this       Lscala/collection/mutable/ArrayOps;
   0      9      1    from       I
   0      9      2    until       I


public scala.collection.IterableView projection();
  Signature: ()Lscala/collection/IterableView;
  Code:
   Stack=1, Locals=1, Args_size=1
	aload_0
	invokeinterface	InterfaceMethod scala/collection/SeqLike.projection:()Lscala/collection/SeqView;
	areturn
  Labels:

public java.lang.Object[] transpose(scala.Function1);
  Signature: (Lscala/Function1;)[Ljava/lang/Object;
  Code:
   Stack=12, Locals=4, Args_size=2
	getstatic	Field scala/Predef$.MODULE$:Lscala/Predef$;
	aload_1
	aload_0
	invokeinterface	InterfaceMethod scala/collection/IndexedSeqLike.head:()Ljava/lang/Object;
	invokeinterface	InterfaceMethod scala/Function1.apply:(Ljava/lang/Object;)Ljava/lang/Object;
	invokevirtual	Method scala/Predef$.genericArrayOps:(Ljava/lang/Object;)Lscala/collection/mutable/ArrayOps;
	new	class scala/collection/mutable/ArrayOps$$anonfun$1
	dup
	aload_0
	invokespecial	Method scala/collection/mutable/ArrayOps$$anonfun$1."<init>":(Lscala/collection/mutable/ArrayOps;)V
	getstatic	Field scala/Array$.MODULE$:Lscala/Array$;
	getstatic	Field scala/reflect/ClassManifest$.MODULE$:Lscala/reflect/ClassManifest$;
	ldc	class scala/collection/mutable/Builder
	getstatic	Field scala/reflect/NoManifest$.MODULE$:Lscala/reflect/NoManifest$;
	getstatic	Field scala/Predef$.MODULE$:Lscala/Predef$;
	iconst_1
	anewarray	class scala/reflect/OptManifest
	dup
	iconst_0
	getstatic	Field scala/reflect/ClassManifest$.MODULE$:Lscala/reflect/ClassManifest$;
	getstatic	Field scala/reflect/NoManifest$.MODULE$:Lscala/reflect/NoManifest$;
	invokevirtual	Method scala/reflect/ClassManifest$.arrayType:(Lscala/reflect/OptManifest;)Lscala/reflect/ClassManifest;
	aastore
	checkcast	class "[Ljava/lang/Object;"
	invokevirtual	Method scala/Predef$.wrapRefArray:([Ljava/lang/Object;)Lscala/collection/mutable/WrappedArray;
	invokevirtual	Method scala/reflect/ClassManifest$.classType:(Ljava/lang/Class;Lscala/reflect/OptManifest;Lscala/collection/Seq;)Lscala/reflect/ClassManifest;
	invokevirtual	Method scala/Array$.canBuildFrom:(Lscala/reflect/ClassManifest;)Lscala/collection/generic/CanBuildFrom;
	invokeinterface	InterfaceMethod scala/collection/TraversableLike.map:(Lscala/Function1;Lscala/collection/generic/CanBuildFrom;)Ljava/lang/Object;
	checkcast	class "[Lscala/collection/mutable/Builder;"
	astore_2
	aload_0
	new	class scala/collection/mutable/ArrayOps$$anonfun$transpose$1
	dup
	aload_0
	aload_1
	aload_2
	invokespecial	Method scala/collection/mutable/ArrayOps$$anonfun$transpose$1."<init>":(Lscala/collection/mutable/ArrayOps;Lscala/Function1;[Lscala/collection/mutable/Builder;)V
	invokeinterface	InterfaceMethod scala/collection/IndexedSeqLike.foreach:(Lscala/Function1;)V
	getstatic	Field scala/Array$.MODULE$:Lscala/Array$;
	getstatic	Field scala/reflect/ClassManifest$.MODULE$:Lscala/reflect/ClassManifest$;
	aload_0
	invokeinterface	InterfaceMethod scala/collection/TraversableLike.repr:()Ljava/lang/Object;
	invokevirtual	Method java/lang/Object.getClass:()Ljava/lang/Class;
	invokevirtual	Method java/lang/Class.getComponentType:()Ljava/lang/Class;
	invokevirtual	Method scala/reflect/ClassManifest$.fromClass:(Ljava/lang/Class;)Lscala/reflect/ClassManifest;
	invokevirtual	Method scala/Array$.newBuilder:(Lscala/reflect/ClassManifest;)Lscala/collection/mutable/ArrayBuilder;
	astore_3
	getstatic	Field scala/Predef$.MODULE$:Lscala/Predef$;
	aload_2
	checkcast	class "[Ljava/lang/Object;"
	invokevirtual	Method scala/Predef$.refArrayOps:([Ljava/lang/Object;)Lscala/collection/mutable/ArrayOps;
	new	class scala/collection/mutable/ArrayOps$$anonfun$transpose$2
	dup
	aload_0
	aload_3
	invokespecial	Method scala/collection/mutable/ArrayOps$$anonfun$transpose$2."<init>":(Lscala/collection/mutable/ArrayOps;Lscala/collection/mutable/Builder;)V
	invokeinterface	InterfaceMethod scala/collection/IndexedSeqLike.foreach:(Lscala/Function1;)V
	aload_3
	invokeinterface	InterfaceMethod scala/collection/mutable/Builder.result:()Ljava/lang/Object;
	checkcast	class "[Ljava/lang/Object;"
	areturn
  Labels:
  LocalVariableTable: 
   Start  Length  Slot  Name   Signature
   0      152      0    this       Lscala/collection/mutable/ArrayOps;
   0      152      1    asArray$2       Lscala/Function1;
   77      74      2    bs$1       [Lscala/collection/mutable/Builder;
   118      33      3    bb$1       Lscala/collection/mutable/Builder;

  Signature: length = 0x2
   00 FFFFFFD0 

public java.lang.Object flatten(scala.Function1);
  Signature: (Lscala/Function1;)Ljava/lang/Object;
  Code:
   Stack=6, Locals=3, Args_size=2
	aload_0
	invokevirtual	Method scala$collection$mutable$ArrayOps$$rowBuilder:()Lscala/collection/mutable/Builder;
	astore_2
	aload_0
	new	class scala/collection/mutable/ArrayOps$$anonfun$flatten$1
	dup
	aload_0
	aload_1
	aload_2
	invokespecial	Method scala/collection/mutable/ArrayOps$$anonfun$flatten$1."<init>":(Lscala/collection/mutable/ArrayOps;Lscala/Function1;Lscala/collection/mutable/Builder;)V
	invokeinterface	InterfaceMethod scala/collection/IndexedSeqLike.foreach:(Lscala/Function1;)V
	aload_2
	invokeinterface	InterfaceMethod scala/collection/mutable/Builder.result:()Ljava/lang/Object;
	areturn
  Labels:
  LocalVariableTable: 
   Start  Length  Slot  Name   Signature
   0      28      0    this       Lscala/collection/mutable/ArrayOps;
   0      28      1    asArray$1       Lscala/Function1;
   5      22      2    b$1       Lscala/collection/mutable/Builder;

  Signature: length = 0x2
   00 FFFFFFE0 

public final scala.collection.mutable.Builder scala$collection$mutable$ArrayOps$$rowBuilder();
  Signature: ()Lscala/collection/mutable/Builder;
  Code:
   Stack=3, Locals=1, Args_size=1
	getstatic	Field scala/Array$.MODULE$:Lscala/Array$;
	getstatic	Field scala/reflect/ClassManifest$.MODULE$:Lscala/reflect/ClassManifest$;
	aload_0
	invokeinterface	InterfaceMethod scala/collection/TraversableLike.repr:()Ljava/lang/Object;
	invokevirtual	Method java/lang/Object.getClass:()Ljava/lang/Class;
	invokevirtual	Method java/lang/Class.getComponentType:()Ljava/lang/Class;
	invokevirtual	Method java/lang/Class.getComponentType:()Ljava/lang/Class;
	invokevirtual	Method scala/reflect/ClassManifest$.fromClass:(Ljava/lang/Class;)Lscala/reflect/ClassManifest;
	invokevirtual	Method scala/Array$.newBuilder:(Lscala/reflect/ClassManifest;)Lscala/collection/mutable/ArrayBuilder;
	areturn
  Labels:

public scala.collection.TraversableLike$WithFilter withFilter(scala.Function1);
  Signature: (Lscala/Function1;)Lscala/collection/TraversableLike$WithFilter;
  Code:
   Stack=2, Locals=2, Args_size=2
	aload_0
	aload_1
	invokestatic	Method scala/collection/TraversableLike$class.withFilter:(Lscala/collection/TraversableLike;Lscala/Function1;)Lscala/collection/TraversableLike$WithFilter;
	areturn
  Labels:
  LocalVariableTable: 
   Start  Length  Slot  Name   Signature
   0      6      0    this       Lscala/collection/mutable/ArrayOps;
   0      6      1    p       Lscala/Function1;

  Signature: length = 0x2
   00 FFFFFFE2 

public java.lang.String stringPrefix();
  Signature: ()Ljava/lang/String;
  Code:
   Stack=1, Locals=1, Args_size=1
	aload_0
	invokestatic	Method scala/collection/TraversableLike$class.stringPrefix:(Lscala/collection/TraversableLike;)Ljava/lang/String;
	areturn
  Labels:

public scala.collection.mutable.StringBuilder addString(scala.collection.mutable.StringBuilder);
  Signature: (Lscala/collection/mutable/StringBuilder;)Lscala/collection/mutable/StringBuilder;
  Code:
   Stack=2, Locals=2, Args_size=2
	aload_0
	aload_1
	invokestatic	Method scala/collection/TraversableLike$class.addString:(Lscala/collection/TraversableLike;Lscala/collection/mutable/StringBuilder;)Lscala/collection/mutable/StringBuilder;
	areturn
  Labels:
  LocalVariableTable: 
   Start  Length  Slot  Name   Signature
   0      6      0    this       Lscala/collection/mutable/ArrayOps;
   0      6      1    b       Lscala/collection/mutable/StringBuilder;


public scala.collection.mutable.StringBuilder addString(scala.collection.mutable.StringBuilder, java.lang.String);
  Signature: (Lscala/collection/mutable/StringBuilder;Ljava/lang/String;)Lscala/collection/mutable/StringBuilder;
  Code:
   Stack=3, Locals=3, Args_size=3
	aload_0
	aload_1
	aload_2
	invokestatic	Method scala/collection/TraversableLike$class.addString:(Lscala/collection/TraversableLike;Lscala/collection/mutable/StringBuilder;Ljava/lang/String;)Lscala/collection/mutable/StringBuilder;
	areturn
  Labels:
  LocalVariableTable: 
   Start  Length  Slot  Name   Signature
   0      7      0    this       Lscala/collection/mutable/ArrayOps;
   0      7      1    b       Lscala/collection/mutable/StringBuilder;
   0      7      2    sep       Ljava/lang/String;


public scala.collection.mutable.StringBuilder addString(scala.collection.mutable.StringBuilder, java.lang.String, java.lang.String, java.lang.String);
  Signature: (Lscala/collection/mutable/StringBuilder;Ljava/lang/String;Ljava/lang/String;Ljava/lang/String;)Lscala/collection/mutable/StringBuilder;
  Code:
   Stack=5, Locals=5, Args_size=5
	aload_0
	aload_1
	aload_2
	aload_3
	aload	4
	invokestatic	Method scala/collection/TraversableLike$class.addString:(Lscala/collection/TraversableLike;Lscala/collection/mutable/StringBuilder;Ljava/lang/String;Ljava/lang/String;Ljava/lang/String;)Lscala/collection/mutable/StringBuilder;
	areturn
  Labels:
  LocalVariableTable: 
   Start  Length  Slot  Name   Signature
   0      10      0    this       Lscala/collection/mutable/ArrayOps;
   0      10      1    b       Lscala/collection/mutable/StringBuilder;
   0      10      2    start       Ljava/lang/String;
   0      10      3    sep       Ljava/lang/String;
   0      10      4    end       Ljava/lang/String;


public java.lang.String mkString();
  Signature: ()Ljava/lang/String;
  Code:
   Stack=1, Locals=1, Args_size=1
	aload_0
	invokestatic	Method scala/collection/TraversableLike$class.mkString:(Lscala/collection/TraversableLike;)Ljava/lang/String;
	areturn
  Labels:

public java.lang.String mkString(java.lang.String);
  Signature: (Ljava/lang/String;)Ljava/lang/String;
  Code:
   Stack=2, Locals=2, Args_size=2
	aload_0
	aload_1
	invokestatic	Method scala/collection/TraversableLike$class.mkString:(Lscala/collection/TraversableLike;Ljava/lang/String;)Ljava/lang/String;
	areturn
  Labels:
  LocalVariableTable: 
   Start  Length  Slot  Name   Signature
   0      6      0    this       Lscala/collection/mutable/ArrayOps;
   0      6      1    sep       Ljava/lang/String;


public java.lang.String mkString(java.lang.String, java.lang.String, java.lang.String);
  Signature: (Ljava/lang/String;Ljava/lang/String;Ljava/lang/String;)Ljava/lang/String;
  Code:
   Stack=4, Locals=4, Args_size=4
	aload_0
	aload_1
	aload_2
	aload_3
	invokestatic	Method scala/collection/TraversableLike$class.mkString:(Lscala/collection/TraversableLike;Ljava/lang/String;Ljava/lang/String;Ljava/lang/String;)Ljava/lang/String;
	areturn
  Labels:
  LocalVariableTable: 
   Start  Length  Slot  Name   Signature
   0      8      0    this       Lscala/collection/mutable/ArrayOps;
   0      8      1    start       Ljava/lang/String;
   0      8      2    sep       Ljava/lang/String;
   0      8      3    end       Ljava/lang/String;


public scala.collection.immutable.Map toMap(scala.Predef$$less$colon$less);
  Signature: (Lscala/Predef$$less$colon$less;)Lscala/collection/immutable/Map;
  Code:
   Stack=2, Locals=2, Args_size=2
	aload_0
	aload_1
	invokestatic	Method scala/collection/TraversableLike$class.toMap:(Lscala/collection/TraversableLike;Lscala/Predef$$less$colon$less;)Lscala/collection/immutable/Map;
	areturn
  Labels:
  LocalVariableTable: 
   Start  Length  Slot  Name   Signature
   0      6      0    this       Lscala/collection/mutable/ArrayOps;
   0      6      1    ev       Lscala/Predef$$less$colon$less;


public scala.collection.immutable.Set toSet();
  Signature: ()Lscala/collection/immutable/Set;
  Code:
   Stack=1, Locals=1, Args_size=1
	aload_0
	invokestatic	Method scala/collection/TraversableLike$class.toSet:(Lscala/collection/TraversableLike;)Lscala/collection/immutable/Set;
	areturn
  Labels:

public scala.collection.mutable.IndexedSeq toIndexedSeq();
  Signature: ()Lscala/collection/mutable/IndexedSeq;
  Code:
   Stack=1, Locals=1, Args_size=1
	aload_0
	invokestatic	Method scala/collection/TraversableLike$class.toIndexedSeq:(Lscala/collection/TraversableLike;)Lscala/collection/mutable/IndexedSeq;
	areturn
  Labels:

public scala.collection.immutable.List toList();
  Signature: ()Lscala/collection/immutable/List;
  Code:
   Stack=1, Locals=1, Args_size=1
	aload_0
	invokestatic	Method scala/collection/TraversableLike$class.toList:(Lscala/collection/TraversableLike;)Lscala/collection/immutable/List;
	areturn
  Labels:

public java.lang.Object toArray(scala.reflect.ClassManifest);
  Signature: (Lscala/reflect/ClassManifest;)Ljava/lang/Object;
  Code:
   Stack=2, Locals=2, Args_size=2
	aload_0
	aload_1
	invokestatic	Method scala/collection/TraversableLike$class.toArray:(Lscala/collection/TraversableLike;Lscala/reflect/ClassManifest;)Ljava/lang/Object;
	areturn
  Labels:
  LocalVariableTable: 
   Start  Length  Slot  Name   Signature
   0      6      0    this       Lscala/collection/mutable/ArrayOps;
   0      6      1    evidence$1       Lscala/reflect/ClassManifest;


public void copyToArray(java.lang.Object);
  Signature: (Ljava/lang/Object;)V
  Code:
   Stack=2, Locals=2, Args_size=2
	aload_0
	aload_1
	invokestatic	Method scala/collection/TraversableLike$class.copyToArray:(Lscala/collection/TraversableLike;Ljava/lang/Object;)V
	return
  Labels:
  LocalVariableTable: 
   Start  Length  Slot  Name   Signature
   0      6      0    this       Lscala/collection/mutable/ArrayOps;
   0      6      1    xs       Ljava/lang/Object;


public void copyToArray(java.lang.Object, int);
  Signature: (Ljava/lang/Object;I)V
  Code:
   Stack=3, Locals=3, Args_size=3
	aload_0
	aload_1
	iload_2
	invokestatic	Method scala/collection/TraversableLike$class.copyToArray:(Lscala/collection/TraversableLike;Ljava/lang/Object;I)V
	return
  Labels:
  LocalVariableTable: 
   Start  Length  Slot  Name   Signature
   0      7      0    this       Lscala/collection/mutable/ArrayOps;
   0      7      1    xs       Ljava/lang/Object;
   0      7      2    start       I


public void copyToBuffer(scala.collection.mutable.Buffer);
  Signature: (Lscala/collection/mutable/Buffer;)V
  Code:
   Stack=2, Locals=2, Args_size=2
	aload_0
	aload_1
	invokestatic	Method scala/collection/TraversableLike$class.copyToBuffer:(Lscala/collection/TraversableLike;Lscala/collection/mutable/Buffer;)V
	return
  Labels:
  LocalVariableTable: 
   Start  Length  Slot  Name   Signature
   0      6      0    this       Lscala/collection/mutable/ArrayOps;
   0      6      1    dest       Lscala/collection/mutable/Buffer;


public scala.Option lastOption();
  Signature: ()Lscala/Option;
  Code:
   Stack=1, Locals=1, Args_size=1
	aload_0
	invokestatic	Method scala/collection/TraversableLike$class.lastOption:(Lscala/collection/TraversableLike;)Lscala/Option;
	areturn
  Labels:

public scala.Option headOption();
  Signature: ()Lscala/Option;
  Code:
   Stack=1, Locals=1, Args_size=1
	aload_0
	invokestatic	Method scala/collection/TraversableLike$class.headOption:(Lscala/collection/TraversableLike;)Lscala/Option;
	areturn
  Labels:

public java.lang.Object max(scala.math.Ordering);
  Signature: (Lscala/math/Ordering;)Ljava/lang/Object;
  Code:
   Stack=2, Locals=2, Args_size=2
	aload_0
	aload_1
	invokestatic	Method scala/collection/TraversableLike$class.max:(Lscala/collection/TraversableLike;Lscala/math/Ordering;)Ljava/lang/Object;
	areturn
  Labels:
  LocalVariableTable: 
   Start  Length  Slot  Name   Signature
   0      6      0    this       Lscala/collection/mutable/ArrayOps;
   0      6      1    cmp       Lscala/math/Ordering;


public java.lang.Object min(scala.math.Ordering);
  Signature: (Lscala/math/Ordering;)Ljava/lang/Object;
  Code:
   Stack=2, Locals=2, Args_size=2
	aload_0
	aload_1
	invokestatic	Method scala/collection/TraversableLike$class.min:(Lscala/collection/TraversableLike;Lscala/math/Ordering;)Ljava/lang/Object;
	areturn
  Labels:
  LocalVariableTable: 
   Start  Length  Slot  Name   Signature
   0      6      0    this       Lscala/collection/mutable/ArrayOps;
   0      6      1    cmp       Lscala/math/Ordering;


public java.lang.Object product(scala.math.Numeric);
  Signature: (Lscala/math/Numeric;)Ljava/lang/Object;
  Code:
   Stack=2, Locals=2, Args_size=2
	aload_0
	aload_1
	invokestatic	Method scala/collection/TraversableLike$class.product:(Lscala/collection/TraversableLike;Lscala/math/Numeric;)Ljava/lang/Object;
	areturn
  Labels:
  LocalVariableTable: 
   Start  Length  Slot  Name   Signature
   0      6      0    this       Lscala/collection/mutable/ArrayOps;
   0      6      1    num       Lscala/math/Numeric;


public java.lang.Object sum(scala.math.Numeric);
  Signature: (Lscala/math/Numeric;)Ljava/lang/Object;
  Code:
   Stack=2, Locals=2, Args_size=2
	aload_0
	aload_1
	invokestatic	Method scala/collection/TraversableLike$class.sum:(Lscala/collection/TraversableLike;Lscala/math/Numeric;)Ljava/lang/Object;
	areturn
  Labels:
  LocalVariableTable: 
   Start  Length  Slot  Name   Signature
   0      6      0    this       Lscala/collection/mutable/ArrayOps;
   0      6      1    num       Lscala/math/Numeric;


public scala.Option reduceRightOption(scala.Function2);
  Signature: (Lscala/Function2;)Lscala/Option;
  Code:
   Stack=2, Locals=2, Args_size=2
	aload_0
	aload_1
	invokestatic	Method scala/collection/TraversableLike$class.reduceRightOption:(Lscala/collection/TraversableLike;Lscala/Function2;)Lscala/Option;
	areturn
  Labels:
  LocalVariableTable: 
   Start  Length  Slot  Name   Signature
   0      6      0    this       Lscala/collection/mutable/ArrayOps;
   0      6      1    op       Lscala/Function2;


public scala.Option reduceLeftOption(scala.Function2);
  Signature: (Lscala/Function2;)Lscala/Option;
  Code:
   Stack=2, Locals=2, Args_size=2
	aload_0
	aload_1
	invokestatic	Method scala/collection/TraversableLike$class.reduceLeftOption:(Lscala/collection/TraversableLike;Lscala/Function2;)Lscala/Option;
	areturn
  Labels:
  LocalVariableTable: 
   Start  Length  Slot  Name   Signature
   0      6      0    this       Lscala/collection/mutable/ArrayOps;
   0      6      1    op       Lscala/Function2;


public java.lang.Object $colon$bslash(java.lang.Object, scala.Function2);
  Signature: (Ljava/lang/Object;Lscala/Function2;)Ljava/lang/Object;
  Code:
   Stack=3, Locals=3, Args_size=3
	aload_0
	aload_1
	aload_2
	invokestatic	Method scala/collection/TraversableLike$class.$colon$bslash:(Lscala/collection/TraversableLike;Ljava/lang/Object;Lscala/Function2;)Ljava/lang/Object;
	areturn
  Labels:
  LocalVariableTable: 
   Start  Length  Slot  Name   Signature
   0      7      0    this       Lscala/collection/mutable/ArrayOps;
   0      7      1    z       Ljava/lang/Object;
   0      7      2    op       Lscala/Function2;


public java.lang.Object $div$colon(java.lang.Object, scala.Function2);
  Signature: (Ljava/lang/Object;Lscala/Function2;)Ljava/lang/Object;
  Code:
   Stack=3, Locals=3, Args_size=3
	aload_0
	aload_1
	aload_2
	invokestatic	Method scala/collection/TraversableLike$class.$div$colon:(Lscala/collection/TraversableLike;Ljava/lang/Object;Lscala/Function2;)Ljava/lang/Object;
	areturn
  Labels:
  LocalVariableTable: 
   Start  Length  Slot  Name   Signature
   0      7      0    this       Lscala/collection/mutable/ArrayOps;
   0      7      1    z       Ljava/lang/Object;
   0      7      2    op       Lscala/Function2;


public int count(scala.Function1);
  Signature: (Lscala/Function1;)I
  Code:
   Stack=2, Locals=2, Args_size=2
	aload_0
	aload_1
	invokestatic	Method scala/collection/TraversableLike$class.count:(Lscala/collection/TraversableLike;Lscala/Function1;)I
	ireturn
  Labels:
  LocalVariableTable: 
   Start  Length  Slot  Name   Signature
   0      6      0    this       Lscala/collection/mutable/ArrayOps;
   0      6      1    p       Lscala/Function1;


public scala.collection.Map groupBy(scala.Function1);
  Signature: (Lscala/Function1;)Lscala/collection/Map;
  Code:
   Stack=2, Locals=2, Args_size=2
	aload_0
	aload_1
	invokestatic	Method scala/collection/TraversableLike$class.groupBy:(Lscala/collection/TraversableLike;Lscala/Function1;)Lscala/collection/Map;
	areturn
  Labels:
  LocalVariableTable: 
   Start  Length  Slot  Name   Signature
   0      6      0    this       Lscala/collection/mutable/ArrayOps;
   0      6      1    f       Lscala/Function1;


public scala.Tuple2 partition(scala.Function1);
  Signature: (Lscala/Function1;)Lscala/Tuple2;
  Code:
   Stack=2, Locals=2, Args_size=2
	aload_0
	aload_1
	invokestatic	Method scala/collection/TraversableLike$class.partition:(Lscala/collection/TraversableLike;Lscala/Function1;)Lscala/Tuple2;
	areturn
  Labels:
  LocalVariableTable: 
   Start  Length  Slot  Name   Signature
   0      6      0    this       Lscala/collection/mutable/ArrayOps;
   0      6      1    p       Lscala/Function1;


public java.lang.Object partialMap(scala.PartialFunction, scala.collection.generic.CanBuildFrom);
  Signature: (Lscala/PartialFunction;Lscala/collection/generic/CanBuildFrom;)Ljava/lang/Object;
  Code:
   Stack=3, Locals=3, Args_size=3
	aload_0
	aload_1
	aload_2
	invokestatic	Method scala/collection/TraversableLike$class.partialMap:(Lscala/collection/TraversableLike;Lscala/PartialFunction;Lscala/collection/generic/CanBuildFrom;)Ljava/lang/Object;
	areturn
  Labels:
  LocalVariableTable: 
   Start  Length  Slot  Name   Signature
   0      7      0    this       Lscala/collection/mutable/ArrayOps;
   0      7      1    pf       Lscala/PartialFunction;
   0      7      2    bf       Lscala/collection/generic/CanBuildFrom;


public java.lang.Object filterNot(scala.Function1);
  Signature: (Lscala/Function1;)Ljava/lang/Object;
  Code:
   Stack=2, Locals=2, Args_size=2
	aload_0
	aload_1
	invokestatic	Method scala/collection/TraversableLike$class.filterNot:(Lscala/collection/TraversableLike;Lscala/Function1;)Ljava/lang/Object;
	areturn
  Labels:
  LocalVariableTable: 
   Start  Length  Slot  Name   Signature
   0      6      0    this       Lscala/collection/mutable/ArrayOps;
   0      6      1    p       Lscala/Function1;


public java.lang.Object filter(scala.Function1);
  Signature: (Lscala/Function1;)Ljava/lang/Object;
  Code:
   Stack=2, Locals=2, Args_size=2
	aload_0
	aload_1
	invokestatic	Method scala/collection/TraversableLike$class.filter:(Lscala/collection/TraversableLike;Lscala/Function1;)Ljava/lang/Object;
	areturn
  Labels:
  LocalVariableTable: 
   Start  Length  Slot  Name   Signature
   0      6      0    this       Lscala/collection/mutable/ArrayOps;
   0      6      1    p       Lscala/Function1;


public java.lang.Object flatMap(scala.Function1, scala.collection.generic.CanBuildFrom);
  Signature: (Lscala/Function1;Lscala/collection/generic/CanBuildFrom;)Ljava/lang/Object;
  Code:
   Stack=3, Locals=3, Args_size=3
	aload_0
	aload_1
	aload_2
	invokestatic	Method scala/collection/TraversableLike$class.flatMap:(Lscala/collection/TraversableLike;Lscala/Function1;Lscala/collection/generic/CanBuildFrom;)Ljava/lang/Object;
	areturn
  Labels:
  LocalVariableTable: 
   Start  Length  Slot  Name   Signature
   0      7      0    this       Lscala/collection/mutable/ArrayOps;
   0      7      1    f       Lscala/Function1;
   0      7      2    bf       Lscala/collection/generic/CanBuildFrom;


public java.lang.Object map(scala.Function1, scala.collection.generic.CanBuildFrom);
  Signature: (Lscala/Function1;Lscala/collection/generic/CanBuildFrom;)Ljava/lang/Object;
  Code:
   Stack=3, Locals=3, Args_size=3
	aload_0
	aload_1
	aload_2
	invokestatic	Method scala/collection/TraversableLike$class.map:(Lscala/collection/TraversableLike;Lscala/Function1;Lscala/collection/generic/CanBuildFrom;)Ljava/lang/Object;
	areturn
  Labels:
  LocalVariableTable: 
   Start  Length  Slot  Name   Signature
   0      7      0    this       Lscala/collection/mutable/ArrayOps;
   0      7      1    f       Lscala/Function1;
   0      7      2    bf       Lscala/collection/generic/CanBuildFrom;


public java.lang.Object $plus$plus(scala.collection.Iterator, scala.collection.generic.CanBuildFrom);
  Signature: (Lscala/collection/Iterator;Lscala/collection/generic/CanBuildFrom;)Ljava/lang/Object;
  Code:
   Stack=3, Locals=3, Args_size=3
	aload_0
	aload_1
	aload_2
	invokestatic	Method scala/collection/TraversableLike$class.$plus$plus:(Lscala/collection/TraversableLike;Lscala/collection/Iterator;Lscala/collection/generic/CanBuildFrom;)Ljava/lang/Object;
	areturn
  Labels:
  LocalVariableTable: 
   Start  Length  Slot  Name   Signature
   0      7      0    this       Lscala/collection/mutable/ArrayOps;
   0      7      1    that       Lscala/collection/Iterator;
   0      7      2    bf       Lscala/collection/generic/CanBuildFrom;


public java.lang.Object $plus$plus(scala.collection.Traversable, scala.collection.generic.CanBuildFrom);
  Signature: (Lscala/collection/Traversable;Lscala/collection/generic/CanBuildFrom;)Ljava/lang/Object;
  Code:
   Stack=3, Locals=3, Args_size=3
	aload_0
	aload_1
	aload_2
	invokestatic	Method scala/collection/TraversableLike$class.$plus$plus:(Lscala/collection/TraversableLike;Lscala/collection/Traversable;Lscala/collection/generic/CanBuildFrom;)Ljava/lang/Object;
	areturn
  Labels:
  LocalVariableTable: 
   Start  Length  Slot  Name   Signature
   0      7      0    this       Lscala/collection/mutable/ArrayOps;
   0      7      1    that       Lscala/collection/Traversable;
   0      7      2    bf       Lscala/collection/generic/CanBuildFrom;


public boolean hasDefiniteSize();
  Signature: ()Z
  Code:
   Stack=1, Locals=1, Args_size=1
	aload_0
	invokestatic	Method scala/collection/TraversableLike$class.hasDefiniteSize:(Lscala/collection/TraversableLike;)Z
	ireturn
  Labels:

public boolean nonEmpty();
  Signature: ()Z
  Code:
   Stack=1, Locals=1, Args_size=1
	aload_0
	invokestatic	Method scala/collection/TraversableLike$class.nonEmpty:(Lscala/collection/TraversableLike;)Z
	ireturn
  Labels:

public java.lang.Object repr();
  Signature: ()Ljava/lang/Object;
  Code:
   Stack=1, Locals=1, Args_size=1
	aload_0
	invokestatic	Method scala/collection/TraversableLike$class.repr:(Lscala/collection/TraversableLike;)Ljava/lang/Object;
	areturn
  Labels:

public scala.Option firstOption();
  Signature: ()Lscala/Option;
  Code:
   Stack=1, Locals=1, Args_size=1
	aload_0
	invokestatic	Method scala/collection/IterableLike$class.firstOption:(Lscala/collection/IterableLike;)Lscala/Option;
	areturn
  Labels:
  Deprecated: true

public java.lang.Object first();
  Signature: ()Ljava/lang/Object;
  Code:
   Stack=1, Locals=1, Args_size=1
	aload_0
	invokestatic	Method scala/collection/IterableLike$class.first:(Lscala/collection/IterableLike;)Ljava/lang/Object;
	areturn
  Labels:
  Deprecated: true

public boolean canEqual(java.lang.Object);
  Signature: (Ljava/lang/Object;)Z
  Code:
   Stack=2, Locals=2, Args_size=2
	aload_0
	aload_1
	invokestatic	Method scala/collection/IterableLike$class.canEqual:(Lscala/collection/IterableLike;Ljava/lang/Object;)Z
	ireturn
  Labels:
  LocalVariableTable: 
   Start  Length  Slot  Name   Signature
   0      6      0    this       Lscala/collection/mutable/ArrayOps;
   0      6      1    that       Ljava/lang/Object;


public scala.collection.immutable.Stream toStream();
  Signature: ()Lscala/collection/immutable/Stream;
  Code:
   Stack=1, Locals=1, Args_size=1
	aload_0
	invokestatic	Method scala/collection/IterableLike$class.toStream:(Lscala/collection/IterableLike;)Lscala/collection/immutable/Stream;
	areturn
  Labels:

public java.lang.Object zipAll(scala.collection.Iterable, java.lang.Object, java.lang.Object, scala.collection.generic.CanBuildFrom);
  Signature: (Lscala/collection/Iterable;Ljava/lang/Object;Ljava/lang/Object;Lscala/collection/generic/CanBuildFrom;)Ljava/lang/Object;
  Code:
   Stack=5, Locals=5, Args_size=5
	aload_0
	aload_1
	aload_2
	aload_3
	aload	4
	invokestatic	Method scala/collection/IterableLike$class.zipAll:(Lscala/collection/IterableLike;Lscala/collection/Iterable;Ljava/lang/Object;Ljava/lang/Object;Lscala/collection/generic/CanBuildFrom;)Ljava/lang/Object;
	areturn
  Labels:
  LocalVariableTable: 
   Start  Length  Slot  Name   Signature
   0      10      0    this       Lscala/collection/mutable/ArrayOps;
   0      10      1    that       Lscala/collection/Iterable;
   0      10      2    thisElem       Ljava/lang/Object;
   0      10      3    thatElem       Ljava/lang/Object;
   0      10      4    bf       Lscala/collection/generic/CanBuildFrom;


public scala.collection.Iterable toIterable();
  Signature: ()Lscala/collection/Iterable;
  Code:
   Stack=1, Locals=1, Args_size=1
	aload_0
	invokestatic	Method scala/collection/IterableLike$class.toIterable:(Lscala/collection/IterableLike;)Lscala/collection/Iterable;
	areturn
  Labels:

public scala.collection.Iterator elements();
  Signature: ()Lscala/collection/Iterator;
  Code:
   Stack=1, Locals=1, Args_size=1
	aload_0
	invokestatic	Method scala/collection/IterableLike$class.elements:(Lscala/collection/IterableLike;)Lscala/collection/Iterator;
	areturn
  Labels:
  Deprecated: true

public scala.collection.SeqView projection();
  Signature: ()Lscala/collection/SeqView;
  Code:
   Stack=1, Locals=1, Args_size=1
	aload_0
	invokestatic	Method scala/collection/SeqLike$class.projection:(Lscala/collection/SeqLike;)Lscala/collection/SeqView;
	areturn
  Labels:
  Deprecated: true

public boolean equalsWith(scala.collection.Seq, scala.Function2);
  Signature: (Lscala/collection/Seq;Lscala/Function2;)Z
  Code:
   Stack=3, Locals=3, Args_size=3
	aload_0
	aload_1
	aload_2
	invokestatic	Method scala/collection/SeqLike$class.equalsWith:(Lscala/collection/SeqLike;Lscala/collection/Seq;Lscala/Function2;)Z
	ireturn
  Labels:
  LocalVariableTable: 
   Start  Length  Slot  Name   Signature
   0      7      0    this       Lscala/collection/mutable/ArrayOps;
   0      7      1    that       Lscala/collection/Seq;
   0      7      2    f       Lscala/Function2;

  Deprecated: true

public int findLastIndexOf(scala.Function1);
  Signature: (Lscala/Function1;)I
  Code:
   Stack=2, Locals=2, Args_size=2
	aload_0
	aload_1
	invokestatic	Method scala/collection/SeqLike$class.findLastIndexOf:(Lscala/collection/SeqLike;Lscala/Function1;)I
	ireturn
  Labels:
  LocalVariableTable: 
   Start  Length  Slot  Name   Signature
   0      6      0    this       Lscala/collection/mutable/ArrayOps;
   0      6      1    p       Lscala/Function1;


public java.lang.String toString();
  Signature: ()Ljava/lang/String;
  Code:
   Stack=1, Locals=1, Args_size=1
	aload_0
	invokestatic	Method scala/collection/SeqLike$class.toString:(Lscala/collection/SeqLike;)Ljava/lang/String;
	areturn
  Labels:

public boolean equals(java.lang.Object);
  Signature: (Ljava/lang/Object;)Z
  Code:
   Stack=2, Locals=2, Args_size=2
	aload_0
	aload_1
	invokestatic	Method scala/collection/SeqLike$class.equals:(Lscala/collection/SeqLike;Ljava/lang/Object;)Z
	ireturn
  Labels:
  LocalVariableTable: 
   Start  Length  Slot  Name   Signature
   0      6      0    this       Lscala/collection/mutable/ArrayOps;
   0      6      1    that       Ljava/lang/Object;


public int hashCode();
  Signature: ()I
  Code:
   Stack=1, Locals=1, Args_size=1
	aload_0
	invokestatic	Method scala/collection/SeqLike$class.hashCode:(Lscala/collection/SeqLike;)I
	ireturn
  Labels:

public scala.collection.immutable.Range indices();
  Signature: ()Lscala/collection/immutable/Range;
  Code:
   Stack=1, Locals=1, Args_size=1
	aload_0
	invokestatic	Method scala/collection/SeqLike$class.indices:(Lscala/collection/SeqLike;)Lscala/collection/immutable/Range;
	areturn
  Labels:

public scala.collection.Seq toSeq();
  Signature: ()Lscala/collection/Seq;
  Code:
   Stack=1, Locals=1, Args_size=1
	aload_0
	invokestatic	Method scala/collection/SeqLike$class.toSeq:(Lscala/collection/SeqLike;)Lscala/collection/Seq;
	areturn
  Labels:

public java.lang.Object sortBy(scala.Function1, scala.math.Ordering);
  Signature: (Lscala/Function1;Lscala/math/Ordering;)Ljava/lang/Object;
  Code:
   Stack=3, Locals=3, Args_size=3
	aload_0
	aload_1
	aload_2
	invokestatic	Method scala/collection/SeqLike$class.sortBy:(Lscala/collection/SeqLike;Lscala/Function1;Lscala/math/Ordering;)Ljava/lang/Object;
	areturn
  Labels:
  LocalVariableTable: 
   Start  Length  Slot  Name   Signature
   0      7      0    this       Lscala/collection/mutable/ArrayOps;
   0      7      1    f       Lscala/Function1;
   0      7      2    ord       Lscala/math/Ordering;


public java.lang.Object sortWith(scala.math.Ordering);
  Signature: (Lscala/math/Ordering;)Ljava/lang/Object;
  Code:
   Stack=2, Locals=2, Args_size=2
	aload_0
	aload_1
	invokestatic	Method scala/collection/SeqLike$class.sortWith:(Lscala/collection/SeqLike;Lscala/math/Ordering;)Ljava/lang/Object;
	areturn
  Labels:
  LocalVariableTable: 
   Start  Length  Slot  Name   Signature
   0      6      0    this       Lscala/collection/mutable/ArrayOps;
   0      6      1    ord       Lscala/math/Ordering;


public java.lang.Object sortWith(scala.Function2);
  Signature: (Lscala/Function2;)Ljava/lang/Object;
  Code:
   Stack=2, Locals=2, Args_size=2
	aload_0
	aload_1
	invokestatic	Method scala/collection/SeqLike$class.sortWith:(Lscala/collection/SeqLike;Lscala/Function2;)Ljava/lang/Object;
	areturn
  Labels:
  LocalVariableTable: 
   Start  Length  Slot  Name   Signature
   0      6      0    this       Lscala/collection/mutable/ArrayOps;
   0      6      1    lt       Lscala/Function2;


public boolean corresponds(scala.collection.Seq, scala.Function2);
  Signature: (Lscala/collection/Seq;Lscala/Function2;)Z
  Code:
   Stack=3, Locals=3, Args_size=3
	aload_0
	aload_1
	aload_2
	invokestatic	Method scala/collection/SeqLike$class.corresponds:(Lscala/collection/SeqLike;Lscala/collection/Seq;Lscala/Function2;)Z
	ireturn
  Labels:
  LocalVariableTable: 
   Start  Length  Slot  Name   Signature
   0      7      0    this       Lscala/collection/mutable/ArrayOps;
   0      7      1    that       Lscala/collection/Seq;
   0      7      2    p       Lscala/Function2;


public java.lang.Object padTo(int, java.lang.Object, scala.collection.generic.CanBuildFrom);
  Signature: (ILjava/lang/Object;Lscala/collection/generic/CanBuildFrom;)Ljava/lang/Object;
  Code:
   Stack=4, Locals=4, Args_size=4
	aload_0
	iload_1
	aload_2
	aload_3
	invokestatic	Method scala/collection/SeqLike$class.padTo:(Lscala/collection/SeqLike;ILjava/lang/Object;Lscala/collection/generic/CanBuildFrom;)Ljava/lang/Object;
	areturn
  Labels:
  LocalVariableTable: 
   Start  Length  Slot  Name   Signature
   0      8      0    this       Lscala/collection/mutable/ArrayOps;
   0      8      1    len       I
   0      8      2    elem       Ljava/lang/Object;
   0      8      3    bf       Lscala/collection/generic/CanBuildFrom;


public java.lang.Object $colon$plus(java.lang.Object, scala.collection.generic.CanBuildFrom);
  Signature: (Ljava/lang/Object;Lscala/collection/generic/CanBuildFrom;)Ljava/lang/Object;
  Code:
   Stack=3, Locals=3, Args_size=3
	aload_0
	aload_1
	aload_2
	invokestatic	Method scala/collection/SeqLike$class.$colon$plus:(Lscala/collection/SeqLike;Ljava/lang/Object;Lscala/collection/generic/CanBuildFrom;)Ljava/lang/Object;
	areturn
  Labels:
  LocalVariableTable: 
   Start  Length  Slot  Name   Signature
   0      7      0    this       Lscala/collection/mutable/ArrayOps;
   0      7      1    elem       Ljava/lang/Object;
   0      7      2    bf       Lscala/collection/generic/CanBuildFrom;


public java.lang.Object $plus$colon(java.lang.Object, scala.collection.generic.CanBuildFrom);
  Signature: (Ljava/lang/Object;Lscala/collection/generic/CanBuildFrom;)Ljava/lang/Object;
  Code:
   Stack=3, Locals=3, Args_size=3
	aload_0
	aload_1
	aload_2
	invokestatic	Method scala/collection/SeqLike$class.$plus$colon:(Lscala/collection/SeqLike;Ljava/lang/Object;Lscala/collection/generic/CanBuildFrom;)Ljava/lang/Object;
	areturn
  Labels:
  LocalVariableTable: 
   Start  Length  Slot  Name   Signature
   0      7      0    this       Lscala/collection/mutable/ArrayOps;
   0      7      1    elem       Ljava/lang/Object;
   0      7      2    bf       Lscala/collection/generic/CanBuildFrom;


public java.lang.Object updated(int, java.lang.Object, scala.collection.generic.CanBuildFrom);
  Signature: (ILjava/lang/Object;Lscala/collection/generic/CanBuildFrom;)Ljava/lang/Object;
  Code:
   Stack=4, Locals=4, Args_size=4
	aload_0
	iload_1
	aload_2
	aload_3
	invokestatic	Method scala/collection/SeqLike$class.updated:(Lscala/collection/SeqLike;ILjava/lang/Object;Lscala/collection/generic/CanBuildFrom;)Ljava/lang/Object;
	areturn
  Labels:
  LocalVariableTable: 
   Start  Length  Slot  Name   Signature
   0      8      0    this       Lscala/collection/mutable/ArrayOps;
   0      8      1    index       I
   0      8      2    elem       Ljava/lang/Object;
   0      8      3    bf       Lscala/collection/generic/CanBuildFrom;


public java.lang.Object patch(int, scala.collection.Seq, int, scala.collection.generic.CanBuildFrom);
  Signature: (ILscala/collection/Seq;ILscala/collection/generic/CanBuildFrom;)Ljava/lang/Object;
  Code:
   Stack=5, Locals=5, Args_size=5
	aload_0
	iload_1
	aload_2
	iload_3
	aload	4
	invokestatic	Method scala/collection/SeqLike$class.patch:(Lscala/collection/SeqLike;ILscala/collection/Seq;ILscala/collection/generic/CanBuildFrom;)Ljava/lang/Object;
	areturn
  Labels:
  LocalVariableTable: 
   Start  Length  Slot  Name   Signature
   0      10      0    this       Lscala/collection/mutable/ArrayOps;
   0      10      1    from       I
   0      10      2    patch       Lscala/collection/Seq;
   0      10      3    replaced       I
   0      10      4    bf       Lscala/collection/generic/CanBuildFrom;


public java.lang.Object removeDuplicates();
  Signature: ()Ljava/lang/Object;
  Code:
   Stack=1, Locals=1, Args_size=1
	aload_0
	invokestatic	Method scala/collection/SeqLike$class.removeDuplicates:(Lscala/collection/SeqLike;)Ljava/lang/Object;
	areturn
  Labels:

public java.lang.Object intersect(scala.collection.Seq);
  Signature: (Lscala/collection/Seq;)Ljava/lang/Object;
  Code:
   Stack=2, Locals=2, Args_size=2
	aload_0
	aload_1
	invokestatic	Method scala/collection/SeqLike$class.intersect:(Lscala/collection/SeqLike;Lscala/collection/Seq;)Ljava/lang/Object;
	areturn
  Labels:
  LocalVariableTable: 
   Start  Length  Slot  Name   Signature
   0      6      0    this       Lscala/collection/mutable/ArrayOps;
   0      6      1    that       Lscala/collection/Seq;


public java.lang.Object diff(scala.collection.Seq);
  Signature: (Lscala/collection/Seq;)Ljava/lang/Object;
  Code:
   Stack=2, Locals=2, Args_size=2
	aload_0
	aload_1
	invokestatic	Method scala/collection/SeqLike$class.diff:(Lscala/collection/SeqLike;Lscala/collection/Seq;)Ljava/lang/Object;
	areturn
  Labels:
  LocalVariableTable: 
   Start  Length  Slot  Name   Signature
   0      6      0    this       Lscala/collection/mutable/ArrayOps;
   0      6      1    that       Lscala/collection/Seq;


public java.lang.Object union(scala.collection.Seq, scala.collection.generic.CanBuildFrom);
  Signature: (Lscala/collection/Seq;Lscala/collection/generic/CanBuildFrom;)Ljava/lang/Object;
  Code:
   Stack=3, Locals=3, Args_size=3
	aload_0
	aload_1
	aload_2
	invokestatic	Method scala/collection/SeqLike$class.union:(Lscala/collection/SeqLike;Lscala/collection/Seq;Lscala/collection/generic/CanBuildFrom;)Ljava/lang/Object;
	areturn
  Labels:
  LocalVariableTable: 
   Start  Length  Slot  Name   Signature
   0      7      0    this       Lscala/collection/mutable/ArrayOps;
   0      7      1    that       Lscala/collection/Seq;
   0      7      2    bf       Lscala/collection/generic/CanBuildFrom;


public boolean contains(java.lang.Object);
  Signature: (Ljava/lang/Object;)Z
  Code:
   Stack=2, Locals=2, Args_size=2
	aload_0
	aload_1
	invokestatic	Method scala/collection/SeqLike$class.contains:(Lscala/collection/SeqLike;Ljava/lang/Object;)Z
	ireturn
  Labels:
  LocalVariableTable: 
   Start  Length  Slot  Name   Signature
   0      6      0    this       Lscala/collection/mutable/ArrayOps;
   0      6      1    elem       Ljava/lang/Object;


public boolean containsSlice(scala.collection.Seq);
  Signature: (Lscala/collection/Seq;)Z
  Code:
   Stack=2, Locals=2, Args_size=2
	aload_0
	aload_1
	invokestatic	Method scala/collection/SeqLike$class.containsSlice:(Lscala/collection/SeqLike;Lscala/collection/Seq;)Z
	ireturn
  Labels:
  LocalVariableTable: 
   Start  Length  Slot  Name   Signature
   0      6      0    this       Lscala/collection/mutable/ArrayOps;
   0      6      1    that       Lscala/collection/Seq;


public int lastIndexOfSlice(scala.collection.Seq, int);
  Signature: (Lscala/collection/Seq;I)I
  Code:
   Stack=3, Locals=3, Args_size=3
	aload_0
	aload_1
	iload_2
	invokestatic	Method scala/collection/SeqLike$class.lastIndexOfSlice:(Lscala/collection/SeqLike;Lscala/collection/Seq;I)I
	ireturn
  Labels:
  LocalVariableTable: 
   Start  Length  Slot  Name   Signature
   0      7      0    this       Lscala/collection/mutable/ArrayOps;
   0      7      1    that       Lscala/collection/Seq;
   0      7      2    end       I


public int lastIndexOfSlice(scala.collection.Seq);
  Signature: (Lscala/collection/Seq;)I
  Code:
   Stack=2, Locals=2, Args_size=2
	aload_0
	aload_1
	invokestatic	Method scala/collection/SeqLike$class.lastIndexOfSlice:(Lscala/collection/SeqLike;Lscala/collection/Seq;)I
	ireturn
  Labels:
  LocalVariableTable: 
   Start  Length  Slot  Name   Signature
   0      6      0    this       Lscala/collection/mutable/ArrayOps;
   0      6      1    that       Lscala/collection/Seq;


public int indexOfSlice(scala.collection.Seq, int);
  Signature: (Lscala/collection/Seq;I)I
  Code:
   Stack=3, Locals=3, Args_size=3
	aload_0
	aload_1
	iload_2
	invokestatic	Method scala/collection/SeqLike$class.indexOfSlice:(Lscala/collection/SeqLike;Lscala/collection/Seq;I)I
	ireturn
  Labels:
  LocalVariableTable: 
   Start  Length  Slot  Name   Signature
   0      7      0    this       Lscala/collection/mutable/ArrayOps;
   0      7      1    that       Lscala/collection/Seq;
   0      7      2    from       I


public int indexOfSlice(scala.collection.Seq);
  Signature: (Lscala/collection/Seq;)I
  Code:
   Stack=2, Locals=2, Args_size=2
	aload_0
	aload_1
	invokestatic	Method scala/collection/SeqLike$class.indexOfSlice:(Lscala/collection/SeqLike;Lscala/collection/Seq;)I
	ireturn
  Labels:
  LocalVariableTable: 
   Start  Length  Slot  Name   Signature
   0      6      0    this       Lscala/collection/mutable/ArrayOps;
   0      6      1    that       Lscala/collection/Seq;


public boolean startsWith(scala.collection.Seq);
  Signature: (Lscala/collection/Seq;)Z
  Code:
   Stack=2, Locals=2, Args_size=2
	aload_0
	aload_1
	invokestatic	Method scala/collection/SeqLike$class.startsWith:(Lscala/collection/SeqLike;Lscala/collection/Seq;)Z
	ireturn
  Labels:
  LocalVariableTable: 
   Start  Length  Slot  Name   Signature
   0      6      0    this       Lscala/collection/mutable/ArrayOps;
   0      6      1    that       Lscala/collection/Seq;


public scala.collection.Iterator reversedElements();
  Signature: ()Lscala/collection/Iterator;
  Code:
   Stack=1, Locals=1, Args_size=1
	aload_0
	invokestatic	Method scala/collection/SeqLike$class.reversedElements:(Lscala/collection/SeqLike;)Lscala/collection/Iterator;
	areturn
  Labels:
  Deprecated: true

public java.lang.Object reverseMap(scala.Function1, scala.collection.generic.CanBuildFrom);
  Signature: (Lscala/Function1;Lscala/collection/generic/CanBuildFrom;)Ljava/lang/Object;
  Code:
   Stack=3, Locals=3, Args_size=3
	aload_0
	aload_1
	aload_2
	invokestatic	Method scala/collection/SeqLike$class.reverseMap:(Lscala/collection/SeqLike;Lscala/Function1;Lscala/collection/generic/CanBuildFrom;)Ljava/lang/Object;
	areturn
  Labels:
  LocalVariableTable: 
   Start  Length  Slot  Name   Signature
   0      7      0    this       Lscala/collection/mutable/ArrayOps;
   0      7      1    f       Lscala/Function1;
   0      7      2    bf       Lscala/collection/generic/CanBuildFrom;


public int lastIndexWhere(scala.Function1);
  Signature: (Lscala/Function1;)I
  Code:
   Stack=2, Locals=2, Args_size=2
	aload_0
	aload_1
	invokestatic	Method scala/collection/SeqLike$class.lastIndexWhere:(Lscala/collection/SeqLike;Lscala/Function1;)I
	ireturn
  Labels:
  LocalVariableTable: 
   Start  Length  Slot  Name   Signature
   0      6      0    this       Lscala/collection/mutable/ArrayOps;
   0      6      1    p       Lscala/Function1;


public int lastIndexOf(java.lang.Object, int);
  Signature: (Ljava/lang/Object;I)I
  Code:
   Stack=3, Locals=3, Args_size=3
	aload_0
	aload_1
	iload_2
	invokestatic	Method scala/collection/SeqLike$class.lastIndexOf:(Lscala/collection/SeqLike;Ljava/lang/Object;I)I
	ireturn
  Labels:
  LocalVariableTable: 
   Start  Length  Slot  Name   Signature
   0      7      0    this       Lscala/collection/mutable/ArrayOps;
   0      7      1    elem       Ljava/lang/Object;
   0      7      2    end       I


public int lastIndexOf(java.lang.Object);
  Signature: (Ljava/lang/Object;)I
  Code:
   Stack=2, Locals=2, Args_size=2
	aload_0
	aload_1
	invokestatic	Method scala/collection/SeqLike$class.lastIndexOf:(Lscala/collection/SeqLike;Ljava/lang/Object;)I
	ireturn
  Labels:
  LocalVariableTable: 
   Start  Length  Slot  Name   Signature
   0      6      0    this       Lscala/collection/mutable/ArrayOps;
   0      6      1    elem       Ljava/lang/Object;


public int indexOf(java.lang.Object, int);
  Signature: (Ljava/lang/Object;I)I
  Code:
   Stack=3, Locals=3, Args_size=3
	aload_0
	aload_1
	iload_2
	invokestatic	Method scala/collection/SeqLike$class.indexOf:(Lscala/collection/SeqLike;Ljava/lang/Object;I)I
	ireturn
  Labels:
  LocalVariableTable: 
   Start  Length  Slot  Name   Signature
   0      7      0    this       Lscala/collection/mutable/ArrayOps;
   0      7      1    elem       Ljava/lang/Object;
   0      7      2    from       I


public int indexOf(java.lang.Object);
  Signature: (Ljava/lang/Object;)I
  Code:
   Stack=2, Locals=2, Args_size=2
	aload_0
	aload_1
	invokestatic	Method scala/collection/SeqLike$class.indexOf:(Lscala/collection/SeqLike;Ljava/lang/Object;)I
	ireturn
  Labels:
  LocalVariableTable: 
   Start  Length  Slot  Name   Signature
   0      6      0    this       Lscala/collection/mutable/ArrayOps;
   0      6      1    elem       Ljava/lang/Object;


public int findIndexOf(scala.Function1);
  Signature: (Lscala/Function1;)I
  Code:
   Stack=2, Locals=2, Args_size=2
	aload_0
	aload_1
	invokestatic	Method scala/collection/SeqLike$class.findIndexOf:(Lscala/collection/SeqLike;Lscala/Function1;)I
	ireturn
  Labels:
  LocalVariableTable: 
   Start  Length  Slot  Name   Signature
   0      6      0    this       Lscala/collection/mutable/ArrayOps;
   0      6      1    p       Lscala/Function1;


public int indexWhere(scala.Function1);
  Signature: (Lscala/Function1;)I
  Code:
   Stack=2, Locals=2, Args_size=2
	aload_0
	aload_1
	invokestatic	Method scala/collection/SeqLike$class.indexWhere:(Lscala/collection/SeqLike;Lscala/Function1;)I
	ireturn
  Labels:
  LocalVariableTable: 
   Start  Length  Slot  Name   Signature
   0      6      0    this       Lscala/collection/mutable/ArrayOps;
   0      6      1    p       Lscala/Function1;


public int prefixLength(scala.Function1);
  Signature: (Lscala/Function1;)I
  Code:
   Stack=2, Locals=2, Args_size=2
	aload_0
	aload_1
	invokestatic	Method scala/collection/SeqLike$class.prefixLength:(Lscala/collection/SeqLike;Lscala/Function1;)I
	ireturn
  Labels:
  LocalVariableTable: 
   Start  Length  Slot  Name   Signature
   0      6      0    this       Lscala/collection/mutable/ArrayOps;
   0      6      1    p       Lscala/Function1;


public boolean isDefinedAt(int);
  Signature: (I)Z
  Code:
   Stack=2, Locals=2, Args_size=2
	aload_0
	iload_1
	invokestatic	Method scala/collection/SeqLike$class.isDefinedAt:(Lscala/collection/SeqLike;I)Z
	ireturn
  Labels:
  LocalVariableTable: 
   Start  Length  Slot  Name   Signature
   0      6      0    this       Lscala/collection/mutable/ArrayOps;
   0      6      1    idx       I


public int size();
  Signature: ()I
  Code:
   Stack=1, Locals=1, Args_size=1
	aload_0
	invokestatic	Method scala/collection/SeqLike$class.size:(Lscala/collection/SeqLike;)I
	ireturn
  Labels:

public boolean endsWith(scala.collection.Seq);
  Signature: (Lscala/collection/Seq;)Z
  Code:
   Stack=2, Locals=2, Args_size=2
	aload_0
	aload_1
	invokestatic	Method scala/collection/IndexedSeqLike$class.endsWith:(Lscala/collection/IndexedSeqLike;Lscala/collection/Seq;)Z
	ireturn
  Labels:
  LocalVariableTable: 
   Start  Length  Slot  Name   Signature
   0      6      0    this       Lscala/collection/mutable/ArrayOps;
   0      6      1    that       Lscala/collection/Seq;


public boolean startsWith(scala.collection.Seq, int);
  Signature: (Lscala/collection/Seq;I)Z
  Code:
   Stack=3, Locals=3, Args_size=3
	aload_0
	aload_1
	iload_2
	invokestatic	Method scala/collection/IndexedSeqLike$class.startsWith:(Lscala/collection/IndexedSeqLike;Lscala/collection/Seq;I)Z
	ireturn
  Labels:
  LocalVariableTable: 
   Start  Length  Slot  Name   Signature
   0      7      0    this       Lscala/collection/mutable/ArrayOps;
   0      7      1    that       Lscala/collection/Seq;
   0      7      2    offset       I


public scala.collection.Iterator reverseIterator();
  Signature: ()Lscala/collection/Iterator;
  Code:
   Stack=1, Locals=1, Args_size=1
	aload_0
	invokestatic	Method scala/collection/IndexedSeqLike$class.reverseIterator:(Lscala/collection/IndexedSeqLike;)Lscala/collection/Iterator;
	areturn
  Labels:

public java.lang.Object reverse();
  Signature: ()Ljava/lang/Object;
  Code:
   Stack=1, Locals=1, Args_size=1
	aload_0
	invokestatic	Method scala/collection/IndexedSeqLike$class.reverse:(Lscala/collection/IndexedSeqLike;)Ljava/lang/Object;
	areturn
  Labels:

public int lastIndexWhere(scala.Function1, int);
  Signature: (Lscala/Function1;I)I
  Code:
   Stack=3, Locals=3, Args_size=3
	aload_0
	aload_1
	iload_2
	invokestatic	Method scala/collection/IndexedSeqLike$class.lastIndexWhere:(Lscala/collection/IndexedSeqLike;Lscala/Function1;I)I
	ireturn
  Labels:
  LocalVariableTable: 
   Start  Length  Slot  Name   Signature
   0      7      0    this       Lscala/collection/mutable/ArrayOps;
   0      7      1    p       Lscala/Function1;
   0      7      2    end       I


public int indexWhere(scala.Function1, int);
  Signature: (Lscala/Function1;I)I
  Code:
   Stack=3, Locals=3, Args_size=3
	aload_0
	aload_1
	iload_2
	invokestatic	Method scala/collection/IndexedSeqLike$class.indexWhere:(Lscala/collection/IndexedSeqLike;Lscala/Function1;I)I
	ireturn
  Labels:
  LocalVariableTable: 
   Start  Length  Slot  Name   Signature
   0      7      0    this       Lscala/collection/mutable/ArrayOps;
   0      7      1    p       Lscala/Function1;
   0      7      2    from       I


public int segmentLength(scala.Function1, int);
  Signature: (Lscala/Function1;I)I
  Code:
   Stack=3, Locals=3, Args_size=3
	aload_0
	aload_1
	iload_2
	invokestatic	Method scala/collection/IndexedSeqLike$class.segmentLength:(Lscala/collection/IndexedSeqLike;Lscala/Function1;I)I
	ireturn
  Labels:
  LocalVariableTable: 
   Start  Length  Slot  Name   Signature
   0      7      0    this       Lscala/collection/mutable/ArrayOps;
   0      7      1    p       Lscala/Function1;
   0      7      2    from       I


public int lengthCompare(int);
  Signature: (I)I
  Code:
   Stack=2, Locals=2, Args_size=2
	aload_0
	iload_1
	invokestatic	Method scala/collection/IndexedSeqLike$class.lengthCompare:(Lscala/collection/IndexedSeqLike;I)I
	ireturn
  Labels:
  LocalVariableTable: 
   Start  Length  Slot  Name   Signature
   0      6      0    this       Lscala/collection/mutable/ArrayOps;
   0      6      1    len       I


public void copyToArray(java.lang.Object, int, int);
  Signature: (Ljava/lang/Object;II)V
  Code:
   Stack=4, Locals=4, Args_size=4
	aload_0
	aload_1
	iload_2
	iload_3
	invokestatic	Method scala/collection/IndexedSeqLike$class.copyToArray:(Lscala/collection/IndexedSeqLike;Ljava/lang/Object;II)V
	return
  Labels:
  LocalVariableTable: 
   Start  Length  Slot  Name   Signature
   0      8      0    this       Lscala/collection/mutable/ArrayOps;
   0      8      1    xs       Ljava/lang/Object;
   0      8      2    start       I
   0      8      3    len       I


public boolean sameElements(scala.collection.Iterable);
  Signature: (Lscala/collection/Iterable;)Z
  Code:
   Stack=2, Locals=2, Args_size=2
	aload_0
	aload_1
	invokestatic	Method scala/collection/IndexedSeqLike$class.sameElements:(Lscala/collection/IndexedSeqLike;Lscala/collection/Iterable;)Z
	ireturn
  Labels:
  LocalVariableTable: 
   Start  Length  Slot  Name   Signature
   0      6      0    this       Lscala/collection/mutable/ArrayOps;
   0      6      1    that       Lscala/collection/Iterable;


public scala.Tuple2 span(scala.Function1);
  Signature: (Lscala/Function1;)Lscala/Tuple2;
  Code:
   Stack=2, Locals=2, Args_size=2
	aload_0
	aload_1
	invokestatic	Method scala/collection/IndexedSeqLike$class.span:(Lscala/collection/IndexedSeqLike;Lscala/Function1;)Lscala/Tuple2;
	areturn
  Labels:
  LocalVariableTable: 
   Start  Length  Slot  Name   Signature
   0      6      0    this       Lscala/collection/mutable/ArrayOps;
   0      6      1    p       Lscala/Function1;


public java.lang.Object dropWhile(scala.Function1);
  Signature: (Lscala/Function1;)Ljava/lang/Object;
  Code:
   Stack=2, Locals=2, Args_size=2
	aload_0
	aload_1
	invokestatic	Method scala/collection/IndexedSeqLike$class.dropWhile:(Lscala/collection/IndexedSeqLike;Lscala/Function1;)Ljava/lang/Object;
	areturn
  Labels:
  LocalVariableTable: 
   Start  Length  Slot  Name   Signature
   0      6      0    this       Lscala/collection/mutable/ArrayOps;
   0      6      1    p       Lscala/Function1;


public java.lang.Object takeWhile(scala.Function1);
  Signature: (Lscala/Function1;)Ljava/lang/Object;
  Code:
   Stack=2, Locals=2, Args_size=2
	aload_0
	aload_1
	invokestatic	Method scala/collection/IndexedSeqLike$class.takeWhile:(Lscala/collection/IndexedSeqLike;Lscala/Function1;)Ljava/lang/Object;
	areturn
  Labels:
  LocalVariableTable: 
   Start  Length  Slot  Name   Signature
   0      6      0    this       Lscala/collection/mutable/ArrayOps;
   0      6      1    p       Lscala/Function1;


public scala.Tuple2 splitAt(int);
  Signature: (I)Lscala/Tuple2;
  Code:
   Stack=2, Locals=2, Args_size=2
	aload_0
	iload_1
	invokestatic	Method scala/collection/IndexedSeqLike$class.splitAt:(Lscala/collection/IndexedSeqLike;I)Lscala/Tuple2;
	areturn
  Labels:
  LocalVariableTable: 
   Start  Length  Slot  Name   Signature
   0      6      0    this       Lscala/collection/mutable/ArrayOps;
   0      6      1    n       I


public java.lang.Object dropRight(int);
  Signature: (I)Ljava/lang/Object;
  Code:
   Stack=2, Locals=2, Args_size=2
	aload_0
	iload_1
	invokestatic	Method scala/collection/IndexedSeqLike$class.dropRight:(Lscala/collection/IndexedSeqLike;I)Ljava/lang/Object;
	areturn
  Labels:
  LocalVariableTable: 
   Start  Length  Slot  Name   Signature
   0      6      0    this       Lscala/collection/mutable/ArrayOps;
   0      6      1    n       I


public java.lang.Object takeRight(int);
  Signature: (I)Ljava/lang/Object;
  Code:
   Stack=2, Locals=2, Args_size=2
	aload_0
	iload_1
	invokestatic	Method scala/collection/IndexedSeqLike$class.takeRight:(Lscala/collection/IndexedSeqLike;I)Ljava/lang/Object;
	areturn
  Labels:
  LocalVariableTable: 
   Start  Length  Slot  Name   Signature
   0      6      0    this       Lscala/collection/mutable/ArrayOps;
   0      6      1    n       I


public java.lang.Object drop(int);
  Signature: (I)Ljava/lang/Object;
  Code:
   Stack=2, Locals=2, Args_size=2
	aload_0
	iload_1
	invokestatic	Method scala/collection/IndexedSeqLike$class.drop:(Lscala/collection/IndexedSeqLike;I)Ljava/lang/Object;
	areturn
  Labels:
  LocalVariableTable: 
   Start  Length  Slot  Name   Signature
   0      6      0    this       Lscala/collection/mutable/ArrayOps;
   0      6      1    n       I


public java.lang.Object take(int);
  Signature: (I)Ljava/lang/Object;
  Code:
   Stack=2, Locals=2, Args_size=2
	aload_0
	iload_1
	invokestatic	Method scala/collection/IndexedSeqLike$class.take:(Lscala/collection/IndexedSeqLike;I)Ljava/lang/Object;
	areturn
  Labels:
  LocalVariableTable: 
   Start  Length  Slot  Name   Signature
   0      6      0    this       Lscala/collection/mutable/ArrayOps;
   0      6      1    n       I


public java.lang.Object init();
  Signature: ()Ljava/lang/Object;
  Code:
   Stack=1, Locals=1, Args_size=1
	aload_0
	invokestatic	Method scala/collection/IndexedSeqLike$class.init:(Lscala/collection/IndexedSeqLike;)Ljava/lang/Object;
	areturn
  Labels:

public java.lang.Object last();
  Signature: ()Ljava/lang/Object;
  Code:
   Stack=1, Locals=1, Args_size=1
	aload_0
	invokestatic	Method scala/collection/IndexedSeqLike$class.last:(Lscala/collection/IndexedSeqLike;)Ljava/lang/Object;
	areturn
  Labels:

public java.lang.Object tail();
  Signature: ()Ljava/lang/Object;
  Code:
   Stack=1, Locals=1, Args_size=1
	aload_0
	invokestatic	Method scala/collection/IndexedSeqLike$class.tail:(Lscala/collection/IndexedSeqLike;)Ljava/lang/Object;
	areturn
  Labels:

public java.lang.Object head();
  Signature: ()Ljava/lang/Object;
  Code:
   Stack=1, Locals=1, Args_size=1
	aload_0
	invokestatic	Method scala/collection/IndexedSeqLike$class.head:(Lscala/collection/IndexedSeqLike;)Ljava/lang/Object;
	areturn
  Labels:

public java.lang.Object slice(int, int);
  Signature: (II)Ljava/lang/Object;
  Code:
   Stack=3, Locals=3, Args_size=3
	aload_0
	iload_1
	iload_2
	invokestatic	Method scala/collection/IndexedSeqLike$class.slice:(Lscala/collection/IndexedSeqLike;II)Ljava/lang/Object;
	areturn
  Labels:
  LocalVariableTable: 
   Start  Length  Slot  Name   Signature
   0      7      0    this       Lscala/collection/mutable/ArrayOps;
   0      7      1    from       I
   0      7      2    until       I


public java.lang.Object zipWithIndex(scala.collection.generic.CanBuildFrom);
  Signature: (Lscala/collection/generic/CanBuildFrom;)Ljava/lang/Object;
  Code:
   Stack=2, Locals=2, Args_size=2
	aload_0
	aload_1
	invokestatic	Method scala/collection/IndexedSeqLike$class.zipWithIndex:(Lscala/collection/IndexedSeqLike;Lscala/collection/generic/CanBuildFrom;)Ljava/lang/Object;
	areturn
  Labels:
  LocalVariableTable: 
   Start  Length  Slot  Name   Signature
   0      6      0    this       Lscala/collection/mutable/ArrayOps;
   0      6      1    bf       Lscala/collection/generic/CanBuildFrom;


public java.lang.Object zip(scala.collection.Iterable, scala.collection.generic.CanBuildFrom);
  Signature: (Lscala/collection/Iterable;Lscala/collection/generic/CanBuildFrom;)Ljava/lang/Object;
  Code:
   Stack=3, Locals=3, Args_size=3
	aload_0
	aload_1
	aload_2
	invokestatic	Method scala/collection/IndexedSeqLike$class.zip:(Lscala/collection/IndexedSeqLike;Lscala/collection/Iterable;Lscala/collection/generic/CanBuildFrom;)Ljava/lang/Object;
	areturn
  Labels:
  LocalVariableTable: 
   Start  Length  Slot  Name   Signature
   0      7      0    this       Lscala/collection/mutable/ArrayOps;
   0      7      1    that       Lscala/collection/Iterable;
   0      7      2    bf       Lscala/collection/generic/CanBuildFrom;


public java.lang.Object reduceRight(scala.Function2);
  Signature: (Lscala/Function2;)Ljava/lang/Object;
  Code:
   Stack=2, Locals=2, Args_size=2
	aload_0
	aload_1
	invokestatic	Method scala/collection/IndexedSeqLike$class.reduceRight:(Lscala/collection/IndexedSeqLike;Lscala/Function2;)Ljava/lang/Object;
	areturn
  Labels:
  LocalVariableTable: 
   Start  Length  Slot  Name   Signature
   0      6      0    this       Lscala/collection/mutable/ArrayOps;
   0      6      1    op       Lscala/Function2;


public java.lang.Object reduceLeft(scala.Function2);
  Signature: (Lscala/Function2;)Ljava/lang/Object;
  Code:
   Stack=2, Locals=2, Args_size=2
	aload_0
	aload_1
	invokestatic	Method scala/collection/IndexedSeqLike$class.reduceLeft:(Lscala/collection/IndexedSeqLike;Lscala/Function2;)Ljava/lang/Object;
	areturn
  Labels:
  LocalVariableTable: 
   Start  Length  Slot  Name   Signature
   0      6      0    this       Lscala/collection/mutable/ArrayOps;
   0      6      1    op       Lscala/Function2;


public java.lang.Object foldRight(java.lang.Object, scala.Function2);
  Signature: (Ljava/lang/Object;Lscala/Function2;)Ljava/lang/Object;
  Code:
   Stack=3, Locals=3, Args_size=3
	aload_0
	aload_1
	aload_2
	invokestatic	Method scala/collection/IndexedSeqLike$class.foldRight:(Lscala/collection/IndexedSeqLike;Ljava/lang/Object;Lscala/Function2;)Ljava/lang/Object;
	areturn
  Labels:
  LocalVariableTable: 
   Start  Length  Slot  Name   Signature
   0      7      0    this       Lscala/collection/mutable/ArrayOps;
   0      7      1    z       Ljava/lang/Object;
   0      7      2    op       Lscala/Function2;


public java.lang.Object foldLeft(java.lang.Object, scala.Function2);
  Signature: (Ljava/lang/Object;Lscala/Function2;)Ljava/lang/Object;
  Code:
   Stack=3, Locals=3, Args_size=3
	aload_0
	aload_1
	aload_2
	invokestatic	Method scala/collection/IndexedSeqLike$class.foldLeft:(Lscala/collection/IndexedSeqLike;Ljava/lang/Object;Lscala/Function2;)Ljava/lang/Object;
	areturn
  Labels:
  LocalVariableTable: 
   Start  Length  Slot  Name   Signature
   0      7      0    this       Lscala/collection/mutable/ArrayOps;
   0      7      1    z       Ljava/lang/Object;
   0      7      2    op       Lscala/Function2;


public scala.Option find(scala.Function1);
  Signature: (Lscala/Function1;)Lscala/Option;
  Code:
   Stack=2, Locals=2, Args_size=2
	aload_0
	aload_1
	invokestatic	Method scala/collection/IndexedSeqLike$class.find:(Lscala/collection/IndexedSeqLike;Lscala/Function1;)Lscala/Option;
	areturn
  Labels:
  LocalVariableTable: 
   Start  Length  Slot  Name   Signature
   0      6      0    this       Lscala/collection/mutable/ArrayOps;
   0      6      1    p       Lscala/Function1;


public boolean exists(scala.Function1);
  Signature: (Lscala/Function1;)Z
  Code:
   Stack=2, Locals=2, Args_size=2
	aload_0
	aload_1
	invokestatic	Method scala/collection/IndexedSeqLike$class.exists:(Lscala/collection/IndexedSeqLike;Lscala/Function1;)Z
	ireturn
  Labels:
  LocalVariableTable: 
   Start  Length  Slot  Name   Signature
   0      6      0    this       Lscala/collection/mutable/ArrayOps;
   0      6      1    p       Lscala/Function1;


public boolean forall(scala.Function1);
  Signature: (Lscala/Function1;)Z
  Code:
   Stack=2, Locals=2, Args_size=2
	aload_0
	aload_1
	invokestatic	Method scala/collection/IndexedSeqLike$class.forall:(Lscala/collection/IndexedSeqLike;Lscala/Function1;)Z
	ireturn
  Labels:
  LocalVariableTable: 
   Start  Length  Slot  Name   Signature
   0      6      0    this       Lscala/collection/mutable/ArrayOps;
   0      6      1    p       Lscala/Function1;


public void foreach(scala.Function1);
  Signature: (Lscala/Function1;)V
  Code:
   Stack=2, Locals=2, Args_size=2
	aload_0
	aload_1
	invokestatic	Method scala/collection/IndexedSeqLike$class.foreach:(Lscala/collection/IndexedSeqLike;Lscala/Function1;)V
	return
  Labels:
  LocalVariableTable: 
   Start  Length  Slot  Name   Signature
   0      6      0    this       Lscala/collection/mutable/ArrayOps;
   0      6      1    f       Lscala/Function1;


public boolean isEmpty();
  Signature: ()Z
  Code:
   Stack=1, Locals=1, Args_size=1
	aload_0
	invokestatic	Method scala/collection/IndexedSeqLike$class.isEmpty:(Lscala/collection/IndexedSeqLike;)Z
	ireturn
  Labels:

public scala.collection.Iterator iterator();
  Signature: ()Lscala/collection/Iterator;
  Code:
   Stack=1, Locals=1, Args_size=1
	aload_0
	invokestatic	Method scala/collection/IndexedSeqLike$class.iterator:(Lscala/collection/IndexedSeqLike;)Lscala/collection/Iterator;
	areturn
  Labels:

public final boolean scala$collection$IndexedSeqLike$$super$endsWith(scala.collection.Seq);
  Signature: (Lscala/collection/Seq;)Z
  Code:
   Stack=2, Locals=2, Args_size=2
	aload_0
	aload_1
	invokestatic	Method scala/collection/SeqLike$class.endsWith:(Lscala/collection/SeqLike;Lscala/collection/Seq;)Z
	ireturn
  Labels:
  LocalVariableTable: 
   Start  Length  Slot  Name   Signature
   0      6      0    this       Lscala/collection/mutable/ArrayOps;
   0      6      1    that       Lscala/collection/Seq;


public final boolean scala$collection$IndexedSeqLike$$super$sameElements(scala.collection.Iterable);
  Signature: (Lscala/collection/Iterable;)Z
  Code:
   Stack=2, Locals=2, Args_size=2
	aload_0
	aload_1
	invokestatic	Method scala/collection/IterableLike$class.sameElements:(Lscala/collection/IterableLike;Lscala/collection/Iterable;)Z
	ireturn
  Labels:
  LocalVariableTable: 
   Start  Length  Slot  Name   Signature
   0      6      0    this       Lscala/collection/mutable/ArrayOps;
   0      6      1    that       Lscala/collection/Iterable;


public final java.lang.Object scala$collection$IndexedSeqLike$$super$init();
  Signature: ()Ljava/lang/Object;
  Code:
   Stack=1, Locals=1, Args_size=1
	aload_0
	invokestatic	Method scala/collection/TraversableLike$class.init:(Lscala/collection/TraversableLike;)Ljava/lang/Object;
	areturn
  Labels:

public final java.lang.Object scala$collection$IndexedSeqLike$$super$last();
  Signature: ()Ljava/lang/Object;
  Code:
   Stack=1, Locals=1, Args_size=1
	aload_0
	invokestatic	Method scala/collection/TraversableLike$class.last:(Lscala/collection/TraversableLike;)Ljava/lang/Object;
	areturn
  Labels:

public final java.lang.Object scala$collection$IndexedSeqLike$$super$tail();
  Signature: ()Ljava/lang/Object;
  Code:
   Stack=1, Locals=1, Args_size=1
	aload_0
	invokestatic	Method scala/collection/TraversableLike$class.tail:(Lscala/collection/TraversableLike;)Ljava/lang/Object;
	areturn
  Labels:

public final java.lang.Object scala$collection$IndexedSeqLike$$super$head();
  Signature: ()Ljava/lang/Object;
  Code:
   Stack=1, Locals=1, Args_size=1
	aload_0
	invokestatic	Method scala/collection/IterableLike$class.head:(Lscala/collection/IterableLike;)Ljava/lang/Object;
	areturn
  Labels:

public final java.lang.Object scala$collection$IndexedSeqLike$$super$zip(scala.collection.Iterable, scala.collection.generic.CanBuildFrom);
  Signature: (Lscala/collection/Iterable;Lscala/collection/generic/CanBuildFrom;)Ljava/lang/Object;
  Code:
   Stack=3, Locals=3, Args_size=3
	aload_0
	aload_1
	aload_2
	invokestatic	Method scala/collection/IterableLike$class.zip:(Lscala/collection/IterableLike;Lscala/collection/Iterable;Lscala/collection/generic/CanBuildFrom;)Ljava/lang/Object;
	areturn
  Labels:
  LocalVariableTable: 
   Start  Length  Slot  Name   Signature
   0      7      0    this       Lscala/collection/mutable/ArrayOps;
   0      7      1    that       Lscala/collection/Iterable;
   0      7      2    bf       Lscala/collection/generic/CanBuildFrom;


public final java.lang.Object scala$collection$IndexedSeqLike$$super$reduceRight(scala.Function2);
  Signature: (Lscala/Function2;)Ljava/lang/Object;
  Code:
   Stack=2, Locals=2, Args_size=2
	aload_0
	aload_1
	invokestatic	Method scala/collection/IterableLike$class.reduceRight:(Lscala/collection/IterableLike;Lscala/Function2;)Ljava/lang/Object;
	areturn
  Labels:
  LocalVariableTable: 
   Start  Length  Slot  Name   Signature
   0      6      0    this       Lscala/collection/mutable/ArrayOps;
   0      6      1    op       Lscala/Function2;


public final java.lang.Object scala$collection$IndexedSeqLike$$super$reduceLeft(scala.Function2);
  Signature: (Lscala/Function2;)Ljava/lang/Object;
  Code:
   Stack=2, Locals=2, Args_size=2
	aload_0
	aload_1
	invokestatic	Method scala/collection/TraversableLike$class.reduceLeft:(Lscala/collection/TraversableLike;Lscala/Function2;)Ljava/lang/Object;
	areturn
  Labels:
  LocalVariableTable: 
   Start  Length  Slot  Name   Signature
   0      6      0    this       Lscala/collection/mutable/ArrayOps;
   0      6      1    op       Lscala/Function2;


public scala.collection.mutable.IndexedSeqView view(int, int);
  Signature: (II)Lscala/collection/mutable/IndexedSeqView;
  Code:
   Stack=3, Locals=3, Args_size=3
	aload_0
	iload_1
	iload_2
	invokestatic	Method scala/collection/mutable/IndexedSeqLike$class.view:(Lscala/collection/mutable/IndexedSeqLike;II)Lscala/collection/mutable/IndexedSeqView;
	areturn
  Labels:
  LocalVariableTable: 
   Start  Length  Slot  Name   Signature
   0      7      0    this       Lscala/collection/mutable/ArrayOps;
   0      7      1    from       I
   0      7      2    until       I


public scala.collection.mutable.IndexedSeqView view();
  Signature: ()Lscala/collection/mutable/IndexedSeqView;
  Code:
   Stack=1, Locals=1, Args_size=1
	aload_0
	invokestatic	Method scala/collection/mutable/IndexedSeqLike$class.view:(Lscala/collection/mutable/IndexedSeqLike;)Lscala/collection/mutable/IndexedSeqView;
	areturn
  Labels:

public scala.collection.mutable.IndexedSeq toCollection(java.lang.Object);
  Signature: (Ljava/lang/Object;)Lscala/collection/mutable/IndexedSeq;
  Code:
   Stack=2, Locals=2, Args_size=2
	aload_0
	aload_1
	invokestatic	Method scala/collection/mutable/IndexedSeqLike$class.toCollection:(Lscala/collection/mutable/IndexedSeqLike;Ljava/lang/Object;)Lscala/collection/mutable/IndexedSeq;
	areturn
  Labels:
  LocalVariableTable: 
   Start  Length  Slot  Name   Signature
   0      6      0    this       Lscala/collection/mutable/ArrayOps;
   0      6      1    repr       Ljava/lang/Object;


public scala.collection.mutable.IndexedSeq thisCollection();
  Signature: ()Lscala/collection/mutable/IndexedSeq;
  Code:
   Stack=1, Locals=1, Args_size=1
	aload_0
	invokestatic	Method scala/collection/mutable/IndexedSeqLike$class.thisCollection:(Lscala/collection/mutable/IndexedSeqLike;)Lscala/collection/mutable/IndexedSeq;
	areturn
  Labels:

public final boolean deepEquals(java.lang.Object);
  Signature: (Ljava/lang/Object;)Z
  Code:
   Stack=2, Locals=2, Args_size=2
	aload_0
	aload_1
	invokestatic	Method scala/collection/mutable/ArrayLike$class.deepEquals:(Lscala/collection/mutable/ArrayLike;Ljava/lang/Object;)Z
	ireturn
  Labels:
  LocalVariableTable: 
   Start  Length  Slot  Name   Signature
   0      6      0    this       Lscala/collection/mutable/ArrayOps;
   0      6      1    that       Ljava/lang/Object;

  Deprecated: true

public final java.lang.String deepMkString(java.lang.String);
  Signature: (Ljava/lang/String;)Ljava/lang/String;
  Code:
   Stack=2, Locals=2, Args_size=2
	aload_0
	aload_1
	invokestatic	Method scala/collection/mutable/ArrayLike$class.deepMkString:(Lscala/collection/mutable/ArrayLike;Ljava/lang/String;)Ljava/lang/String;
	areturn
  Labels:
  LocalVariableTable: 
   Start  Length  Slot  Name   Signature
   0      6      0    this       Lscala/collection/mutable/ArrayOps;
   0      6      1    sep       Ljava/lang/String;

  Deprecated: true

public final java.lang.String deepMkString(java.lang.String, java.lang.String, java.lang.String);
  Signature: (Ljava/lang/String;Ljava/lang/String;Ljava/lang/String;)Ljava/lang/String;
  Code:
   Stack=4, Locals=4, Args_size=4
	aload_0
	aload_1
	aload_2
	aload_3
	invokestatic	Method scala/collection/mutable/ArrayLike$class.deepMkString:(Lscala/collection/mutable/ArrayLike;Ljava/lang/String;Ljava/lang/String;Ljava/lang/String;)Ljava/lang/String;
	areturn
  Labels:
  LocalVariableTable: 
   Start  Length  Slot  Name   Signature
   0      8      0    this       Lscala/collection/mutable/ArrayOps;
   0      8      1    start       Ljava/lang/String;
   0      8      2    sep       Ljava/lang/String;
   0      8      3    end       Ljava/lang/String;

  Deprecated: true

public final java.lang.String deepToString();
  Signature: ()Ljava/lang/String;
  Code:
   Stack=1, Locals=1, Args_size=1
	aload_0
	invokestatic	Method scala/collection/mutable/ArrayLike$class.deepToString:(Lscala/collection/mutable/ArrayLike;)Ljava/lang/String;
	areturn
  Labels:
  Deprecated: true

public scala.collection.IndexedSeq deep();
  Signature: ()Lscala/collection/IndexedSeq;
  Code:
   Stack=1, Locals=1, Args_size=1
	aload_0
	invokestatic	Method scala/collection/mutable/ArrayLike$class.deep:(Lscala/collection/mutable/ArrayLike;)Lscala/collection/IndexedSeq;
	areturn
  Labels:

}

