Compiled from "ArrayOps.scala"
public class scala.collection.mutable.ArrayOps$ofBoolean extends scala.collection.mutable.ArrayOps implements scala.collection.mutable.ArrayLike,scala.ScalaObject
  SourceFile: "ArrayOps.scala"
  Signature: length = 0x2
   00 57 
  Scala: length = 0x
   
  InnerClass: 
   public #90= #10 of #14; //ofBoolean=class scala/collection/mutable/ArrayOps$ofBoolean of class scala/collection/mutable/ArrayOps
   public final #90= #81 of #92; //ofBoolean=class scala/collection/mutable/WrappedArray$ofBoolean of class scala/collection/mutable/WrappedArray
   public #90= #78 of #94; //ofBoolean=class scala/collection/mutable/ArrayBuilder$ofBoolean of class scala/collection/mutable/ArrayBuilder
  minor version: 0
  major version: 49
  Constant pool:
const #1 = Asciz	SourceFile;
const #2 = Asciz	ArrayOps.scala;
const #3 = Asciz	repr;
const #4 = Asciz	[Z;
const #5 = Asciz	<init>;
const #6 = Asciz	([Z)V;
const #7 = Asciz	Code;
const #8 = Asciz	LineNumberTable;
const #9 = Asciz	scala/collection/mutable/ArrayOps$ofBoolean;
const #10 = class	#9;	//  scala/collection/mutable/ArrayOps$ofBoolean
const #11 = NameAndType	#3:#4;//  repr:[Z
const #12 = Field	#10.#11;	//  scala/collection/mutable/ArrayOps$ofBoolean.repr:[Z
const #13 = Asciz	scala/collection/mutable/ArrayOps;
const #14 = class	#13;	//  scala/collection/mutable/ArrayOps
const #15 = Asciz	()V;
const #16 = NameAndType	#5:#15;//  "<init>":()V
const #17 = Method	#14.#16;	//  scala/collection/mutable/ArrayOps."<init>":()V
const #18 = Asciz	this;
const #19 = Asciz	Lscala/collection/mutable/ArrayOps$ofBoolean;;
const #20 = Asciz	LocalVariableTable;
const #21 = Asciz	()Ljava/lang/Object;;
const #22 = Asciz	()[Z;
const #23 = NameAndType	#3:#22;//  repr:()[Z
const #24 = Method	#10.#23;	//  scala/collection/mutable/ArrayOps$ofBoolean.repr:()[Z
const #25 = Asciz	thisCollection;
const #26 = Asciz	()Lscala/collection/mutable/IndexedSeq;;
const #27 = Asciz	()Lscala/collection/mutable/WrappedArray;;
const #28 = NameAndType	#25:#27;//  thisCollection:()Lscala/collection/mutable/WrappedArray;
const #29 = Method	#10.#28;	//  scala/collection/mutable/ArrayOps$ofBoolean.thisCollection:()Lscala/collection/mutable/WrappedArray;
const #30 = Asciz	()Lscala/collection/IndexedSeq;;
const #31 = Asciz	()Lscala/collection/Seq;;
const #32 = Asciz	()Lscala/collection/Iterable;;
const #33 = Asciz	()Lscala/collection/Traversable;;
const #34 = Asciz	toCollection;
const #35 = Asciz	(Ljava/lang/Object;)Lscala/collection/mutable/IndexedSeq;;
const #36 = class	#4;	//  "[Z"
const #37 = Asciz	([Z)Lscala/collection/mutable/WrappedArray;;
const #38 = NameAndType	#34:#37;//  toCollection:([Z)Lscala/collection/mutable/WrappedArray;
const #39 = Method	#10.#38;	//  scala/collection/mutable/ArrayOps$ofBoolean.toCollection:([Z)Lscala/collection/mutable/WrappedArray;
const #40 = Asciz	Ljava/lang/Object;;
const #41 = Asciz	(Ljava/lang/Object;)Lscala/collection/IndexedSeq;;
const #42 = Asciz	(Ljava/lang/Object;)Lscala/collection/Seq;;
const #43 = Asciz	(Ljava/lang/Object;)Lscala/collection/Iterable;;
const #44 = Asciz	(Ljava/lang/Object;)Lscala/collection/Traversable;;
const #45 = Asciz	newBuilder;
const #46 = Asciz	()Lscala/collection/mutable/Builder;;
const #47 = Asciz	()Lscala/collection/mutable/ArrayBuilder$ofBoolean;;
const #48 = NameAndType	#45:#47;//  newBuilder:()Lscala/collection/mutable/ArrayBuilder$ofBoolean;
const #49 = Method	#10.#48;	//  scala/collection/mutable/ArrayOps$ofBoolean.newBuilder:()Lscala/collection/mutable/ArrayBuilder$ofBoolean;
const #50 = Asciz	apply;
const #51 = Asciz	(I)Ljava/lang/Object;;
const #52 = Asciz	(I)Z;
const #53 = NameAndType	#50:#52;//  apply:(I)Z
const #54 = Method	#10.#53;	//  scala/collection/mutable/ArrayOps$ofBoolean.apply:(I)Z
const #55 = Asciz	scala/runtime/BoxesRunTime;
const #56 = class	#55;	//  scala/runtime/BoxesRunTime
const #57 = Asciz	boxToBoolean;
const #58 = Asciz	(Z)Ljava/lang/Boolean;;
const #59 = NameAndType	#57:#58;//  boxToBoolean:(Z)Ljava/lang/Boolean;
const #60 = Method	#56.#59;	//  scala/runtime/BoxesRunTime.boxToBoolean:(Z)Ljava/lang/Boolean;
const #61 = Asciz	idx;
const #62 = Asciz	I;
const #63 = Asciz	update;
const #64 = Asciz	(ILjava/lang/Object;)V;
const #65 = Asciz	unboxToBoolean;
const #66 = Asciz	(Ljava/lang/Object;)Z;
const #67 = NameAndType	#65:#66;//  unboxToBoolean:(Ljava/lang/Object;)Z
const #68 = Method	#56.#67;	//  scala/runtime/BoxesRunTime.unboxToBoolean:(Ljava/lang/Object;)Z
const #69 = Asciz	(IZ)V;
const #70 = NameAndType	#63:#69;//  update:(IZ)V
const #71 = Method	#10.#70;	//  scala/collection/mutable/ArrayOps$ofBoolean.update:(IZ)V
const #72 = Asciz	elem;
const #73 = Asciz	index;
const #74 = Asciz	Z;
const #75 = Asciz	length;
const #76 = Asciz	()I;
const #77 = Asciz	scala/collection/mutable/ArrayBuilder$ofBoolean;
const #78 = class	#77;	//  scala/collection/mutable/ArrayBuilder$ofBoolean
const #79 = Method	#78.#16;	//  scala/collection/mutable/ArrayBuilder$ofBoolean."<init>":()V
const #80 = Asciz	scala/collection/mutable/WrappedArray$ofBoolean;
const #81 = class	#80;	//  scala/collection/mutable/WrappedArray$ofBoolean
const #82 = NameAndType	#5:#6;//  "<init>":([Z)V
const #83 = Method	#81.#82;	//  scala/collection/mutable/WrappedArray$ofBoolean."<init>":([Z)V
const #84 = Asciz	([Z)Lscala/collection/mutable/WrappedArray<Ljava/lang/Boolean;>;;
const #85 = Asciz	Signature;
const #86 = Asciz	()Lscala/collection/mutable/WrappedArray<Ljava/lang/Boolean;>;;
const #87 = Asciz	Lscala/collection/mutable/ArrayOps<Ljava/lang/Boolean;>;Lscala/collection/mutable/ArrayLike<Ljava/lang/Boolean;[Z>;Lscala/ScalaObject;;
const #88 = Asciz	Scala;
const #89 = Asciz	InnerClasses;
const #90 = Asciz	ofBoolean;
const #91 = Asciz	scala/collection/mutable/WrappedArray;
const #92 = class	#91;	//  scala/collection/mutable/WrappedArray
const #93 = Asciz	scala/collection/mutable/ArrayBuilder;
const #94 = class	#93;	//  scala/collection/mutable/ArrayBuilder
const #95 = Asciz	scala/collection/mutable/ArrayLike;
const #96 = class	#95;	//  scala/collection/mutable/ArrayLike
const #97 = Asciz	scala/ScalaObject;
const #98 = class	#97;	//  scala/ScalaObject

{
public scala.collection.mutable.ArrayOps$ofBoolean(boolean[]);
  Code:
   Stack=2, Locals=2, Args_size=2
   0:	aload_0
   1:	aload_1
   2:	putfield	#12; //Field repr:[Z
   5:	aload_0
   6:	invokespecial	#17; //Method scala/collection/mutable/ArrayOps."<init>":()V
   9:	return
  LineNumberTable: 
   line 150: 0

  LocalVariableTable: 
   Start  Length  Slot  Name   Signature
   0      10      0    this       Lscala/collection/mutable/ArrayOps$ofBoolean;
   0      10      1    repr       [Z


public java.lang.Object repr();
  Code:
   Stack=1, Locals=1, Args_size=1
   0:	aload_0
   1:	invokevirtual	#24; //Method repr:()[Z
   4:	areturn
  LineNumberTable: 
   line 150: 0


public scala.collection.mutable.IndexedSeq thisCollection();
  Code:
   Stack=1, Locals=1, Args_size=1
   0:	aload_0
   1:	invokevirtual	#29; //Method thisCollection:()Lscala/collection/mutable/WrappedArray;
   4:	areturn
  LineNumberTable: 
   line 150: 0


public scala.collection.IndexedSeq thisCollection();
  Code:
   Stack=1, Locals=1, Args_size=1
   0:	aload_0
   1:	invokevirtual	#29; //Method thisCollection:()Lscala/collection/mutable/WrappedArray;
   4:	areturn
  LineNumberTable: 
   line 150: 0


public scala.collection.Seq thisCollection();
  Code:
   Stack=1, Locals=1, Args_size=1
   0:	aload_0
   1:	invokevirtual	#29; //Method thisCollection:()Lscala/collection/mutable/WrappedArray;
   4:	areturn
  LineNumberTable: 
   line 150: 0


public scala.collection.Iterable thisCollection();
  Code:
   Stack=1, Locals=1, Args_size=1
   0:	aload_0
   1:	invokevirtual	#29; //Method thisCollection:()Lscala/collection/mutable/WrappedArray;
   4:	areturn
  LineNumberTable: 
   line 150: 0


public scala.collection.Traversable thisCollection();
  Code:
   Stack=1, Locals=1, Args_size=1
   0:	aload_0
   1:	invokevirtual	#29; //Method thisCollection:()Lscala/collection/mutable/WrappedArray;
   4:	areturn
  LineNumberTable: 
   line 150: 0


public scala.collection.mutable.IndexedSeq toCollection(java.lang.Object);
  Code:
   Stack=2, Locals=2, Args_size=2
   0:	aload_0
   1:	aload_1
   2:	checkcast	#36; //class "[Z"
   5:	invokevirtual	#39; //Method toCollection:([Z)Lscala/collection/mutable/WrappedArray;
   8:	areturn
  LineNumberTable: 
   line 150: 0

  LocalVariableTable: 
   Start  Length  Slot  Name   Signature
   0      9      0    this       Lscala/collection/mutable/ArrayOps$ofBoolean;
   0      9      1    repr       Ljava/lang/Object;


public scala.collection.IndexedSeq toCollection(java.lang.Object);
  Code:
   Stack=2, Locals=2, Args_size=2
   0:	aload_0
   1:	aload_1
   2:	checkcast	#36; //class "[Z"
   5:	invokevirtual	#39; //Method toCollection:([Z)Lscala/collection/mutable/WrappedArray;
   8:	areturn
  LineNumberTable: 
   line 150: 0

  LocalVariableTable: 
   Start  Length  Slot  Name   Signature
   0      9      0    this       Lscala/collection/mutable/ArrayOps$ofBoolean;
   0      9      1    repr       Ljava/lang/Object;


public scala.collection.Seq toCollection(java.lang.Object);
  Code:
   Stack=2, Locals=2, Args_size=2
   0:	aload_0
   1:	aload_1
   2:	checkcast	#36; //class "[Z"
   5:	invokevirtual	#39; //Method toCollection:([Z)Lscala/collection/mutable/WrappedArray;
   8:	areturn
  LineNumberTable: 
   line 150: 0

  LocalVariableTable: 
   Start  Length  Slot  Name   Signature
   0      9      0    this       Lscala/collection/mutable/ArrayOps$ofBoolean;
   0      9      1    repr       Ljava/lang/Object;


public scala.collection.Iterable toCollection(java.lang.Object);
  Code:
   Stack=2, Locals=2, Args_size=2
   0:	aload_0
   1:	aload_1
   2:	checkcast	#36; //class "[Z"
   5:	invokevirtual	#39; //Method toCollection:([Z)Lscala/collection/mutable/WrappedArray;
   8:	areturn
  LineNumberTable: 
   line 150: 0

  LocalVariableTable: 
   Start  Length  Slot  Name   Signature
   0      9      0    this       Lscala/collection/mutable/ArrayOps$ofBoolean;
   0      9      1    repr       Ljava/lang/Object;


public scala.collection.Traversable toCollection(java.lang.Object);
  Code:
   Stack=2, Locals=2, Args_size=2
   0:	aload_0
   1:	aload_1
   2:	checkcast	#36; //class "[Z"
   5:	invokevirtual	#39; //Method toCollection:([Z)Lscala/collection/mutable/WrappedArray;
   8:	areturn
  LineNumberTable: 
   line 150: 0

  LocalVariableTable: 
   Start  Length  Slot  Name   Signature
   0      9      0    this       Lscala/collection/mutable/ArrayOps$ofBoolean;
   0      9      1    repr       Ljava/lang/Object;


public scala.collection.mutable.Builder newBuilder();
  Code:
   Stack=1, Locals=1, Args_size=1
   0:	aload_0
   1:	invokevirtual	#49; //Method newBuilder:()Lscala/collection/mutable/ArrayBuilder$ofBoolean;
   4:	areturn
  LineNumberTable: 
   line 150: 0


public java.lang.Object apply(int);
  Code:
   Stack=2, Locals=3, Args_size=2
   0:	aload_0
   1:	iload_1
   2:	invokevirtual	#54; //Method apply:(I)Z
   5:	istore_2
   6:	iload_2
   7:	invokestatic	#60; //Method scala/runtime/BoxesRunTime.boxToBoolean:(Z)Ljava/lang/Boolean;
   10:	areturn
  LineNumberTable: 
   line 150: 0

  LocalVariableTable: 
   Start  Length  Slot  Name   Signature
   0      11      0    this       Lscala/collection/mutable/ArrayOps$ofBoolean;
   0      11      1    idx       I


public void update(int, java.lang.Object);
  Code:
   Stack=3, Locals=3, Args_size=3
   0:	aload_0
   1:	iload_1
   2:	aload_2
   3:	invokestatic	#68; //Method scala/runtime/BoxesRunTime.unboxToBoolean:(Ljava/lang/Object;)Z
   6:	invokevirtual	#71; //Method update:(IZ)V
   9:	return
  LineNumberTable: 
   line 150: 0

  LocalVariableTable: 
   Start  Length  Slot  Name   Signature
   0      10      0    this       Lscala/collection/mutable/ArrayOps$ofBoolean;
   0      10      1    idx       I
   0      10      2    elem       Ljava/lang/Object;


public void update(int, boolean);
  Code:
   Stack=3, Locals=3, Args_size=3
   0:	aload_0
   1:	invokevirtual	#24; //Method repr:()[Z
   4:	iload_1
   5:	iload_2
   6:	bastore
   7:	return
  LineNumberTable: 
   line 158: 0

  LocalVariableTable: 
   Start  Length  Slot  Name   Signature
   0      8      0    this       Lscala/collection/mutable/ArrayOps$ofBoolean;
   0      8      1    index       I
   0      8      2    elem       Z


public boolean apply(int);
  Code:
   Stack=2, Locals=2, Args_size=2
   0:	aload_0
   1:	invokevirtual	#24; //Method repr:()[Z
   4:	iload_1
   5:	baload
   6:	ireturn
  LineNumberTable: 
   line 157: 0

  LocalVariableTable: 
   Start  Length  Slot  Name   Signature
   0      7      0    this       Lscala/collection/mutable/ArrayOps$ofBoolean;
   0      7      1    index       I


public int length();
  Code:
   Stack=1, Locals=1, Args_size=1
   0:	aload_0
   1:	invokevirtual	#24; //Method repr:()[Z
   4:	arraylength
   5:	ireturn
  LineNumberTable: 
   line 156: 0


public scala.collection.mutable.ArrayBuilder$ofBoolean newBuilder();
  Code:
   Stack=2, Locals=1, Args_size=1
   0:	new	#78; //class scala/collection/mutable/ArrayBuilder$ofBoolean
   3:	dup
   4:	invokespecial	#79; //Method scala/collection/mutable/ArrayBuilder$ofBoolean."<init>":()V
   7:	areturn
  LineNumberTable: 
   line 154: 0


public scala.collection.mutable.WrappedArray toCollection(boolean[]);
  Code:
   Stack=3, Locals=2, Args_size=2
   0:	new	#81; //class scala/collection/mutable/WrappedArray$ofBoolean
   3:	dup
   4:	aload_1
   5:	invokespecial	#83; //Method scala/collection/mutable/WrappedArray$ofBoolean."<init>":([Z)V
   8:	areturn
  LineNumberTable: 
   line 153: 0

  LocalVariableTable: 
   Start  Length  Slot  Name   Signature
   0      9      0    this       Lscala/collection/mutable/ArrayOps$ofBoolean;
   0      9      1    repr       [Z

  Signature: length = 0x2
   00 54 

public scala.collection.mutable.WrappedArray thisCollection();
  Code:
   Stack=3, Locals=1, Args_size=1
   0:	new	#81; //class scala/collection/mutable/WrappedArray$ofBoolean
   3:	dup
   4:	aload_0
   5:	invokevirtual	#24; //Method repr:()[Z
   8:	invokespecial	#83; //Method scala/collection/mutable/WrappedArray$ofBoolean."<init>":([Z)V
   11:	areturn
  LineNumberTable: 
   line 152: 0

  Signature: length = 0x2
   00 56 

public boolean[] repr();
  Code:
   Stack=1, Locals=1, Args_size=1
   0:	aload_0
   1:	getfield	#12; //Field repr:[Z
   4:	areturn
  LineNumberTable: 
   line 150: 0


}

