Compiled from "ArrayBuilder.scala"
public class scala.collection.mutable.ArrayBuilder$ofShort extends scala.collection.mutable.ArrayBuilder implements scala.ScalaObject
  SourceFile: "ArrayBuilder.scala"
  Signature: length = 0x2
   00 FFFFFF85 
  Scala: length = 0x
   
  InnerClass: 
   public final #138= #84 of #137; //ofShort=class scala/collection/mutable/WrappedArray$ofShort of class scala/collection/mutable/WrappedArray
   public #138= #17 of #13; //ofShort=class scala/collection/mutable/ArrayBuilder$ofShort of class scala/collection/mutable/ArrayBuilder
  minor version: 0
  major version: 49
  Constant pool:
const #1 = Asciz	SourceFile;
const #2 = Asciz	ArrayBuilder.scala;
const #3 = Asciz	size;
const #4 = Asciz	I;
const #5 = Asciz	capacity;
const #6 = Asciz	elems;
const #7 = Asciz	[S;
const #8 = Asciz	<init>;
const #9 = Asciz	()V;
const #10 = Asciz	Code;
const #11 = Asciz	LineNumberTable;
const #12 = Asciz	scala/collection/mutable/ArrayBuilder;
const #13 = class	#12;	//  scala/collection/mutable/ArrayBuilder
const #14 = NameAndType	#8:#9;//  "<init>":()V
const #15 = Method	#13.#14;	//  scala/collection/mutable/ArrayBuilder."<init>":()V
const #16 = Asciz	scala/collection/mutable/ArrayBuilder$ofShort;
const #17 = class	#16;	//  scala/collection/mutable/ArrayBuilder$ofShort
const #18 = NameAndType	#5:#4;//  capacity:I
const #19 = Field	#17.#18;	//  scala/collection/mutable/ArrayBuilder$ofShort.capacity:I
const #20 = NameAndType	#3:#4;//  size:I
const #21 = Field	#17.#20;	//  scala/collection/mutable/ArrayBuilder$ofShort.size:I
const #22 = Asciz	$plus$eq;
const #23 = Asciz	(Ljava/lang/Object;)Lscala/collection/mutable/Builder;;
const #24 = Asciz	scala/runtime/BoxesRunTime;
const #25 = class	#24;	//  scala/runtime/BoxesRunTime
const #26 = Asciz	unboxToShort;
const #27 = Asciz	(Ljava/lang/Object;)S;
const #28 = NameAndType	#26:#27;//  unboxToShort:(Ljava/lang/Object;)S
const #29 = Method	#25.#28;	//  scala/runtime/BoxesRunTime.unboxToShort:(Ljava/lang/Object;)S
const #30 = Asciz	(S)Lscala/collection/mutable/ArrayBuilder$ofShort;;
const #31 = NameAndType	#22:#30;//  $plus$eq:(S)Lscala/collection/mutable/ArrayBuilder$ofShort;
const #32 = Method	#17.#31;	//  scala/collection/mutable/ArrayBuilder$ofShort.$plus$eq:(S)Lscala/collection/mutable/ArrayBuilder$ofShort;
const #33 = Asciz	this;
const #34 = Asciz	Lscala/collection/mutable/ArrayBuilder$ofShort;;
const #35 = Asciz	elem;
const #36 = Asciz	Ljava/lang/Object;;
const #37 = Asciz	LocalVariableTable;
const #38 = Asciz	(Ljava/lang/Object;)Lscala/collection/generic/Growable;;
const #39 = Asciz	$plus$plus$eq;
const #40 = Asciz	(Lscala/collection/Traversable;)Lscala/collection/generic/Growable;;
const #41 = Asciz	(Lscala/collection/Traversable;)Lscala/collection/mutable/ArrayBuilder$ofShort;;
const #42 = NameAndType	#39:#41;//  $plus$plus$eq:(Lscala/collection/Traversable;)Lscala/collection/mutable/ArrayBuilder$ofShort;
const #43 = Method	#17.#42;	//  scala/collection/mutable/ArrayBuilder$ofShort.$plus$plus$eq:(Lscala/collection/Traversable;)Lscala/collection/mutable/ArrayBuilder$ofShort;
const #44 = Asciz	Lscala/collection/Traversable;;
const #45 = Asciz	result;
const #46 = Asciz	()Ljava/lang/Object;;
const #47 = Asciz	()[S;
const #48 = NameAndType	#45:#47;//  result:()[S
const #49 = Method	#17.#48;	//  scala/collection/mutable/ArrayBuilder$ofShort.result:()[S
const #50 = Asciz	toString;
const #51 = Asciz	()Ljava/lang/String;;
const #52 = Asciz	ArrayBuilder.ofShort;
const #53 = String	#52;	//  ArrayBuilder.ofShort
const #54 = Asciz	equals;
const #55 = Asciz	(Ljava/lang/Object;)Z;
const #56 = Asciz	()I;
const #57 = NameAndType	#3:#56;//  size:()I
const #58 = Method	#17.#57;	//  scala/collection/mutable/ArrayBuilder$ofShort.size:()I
const #59 = NameAndType	#6:#47;//  elems:()[S
const #60 = Method	#17.#59;	//  scala/collection/mutable/ArrayBuilder$ofShort.elems:()[S
const #61 = Asciz	scala/MatchError;
const #62 = class	#61;	//  scala/MatchError
const #63 = Asciz	java/lang/Object;
const #64 = class	#63;	//  java/lang/Object
const #65 = NameAndType	#50:#51;//  toString:()Ljava/lang/String;
const #66 = Method	#64.#65;	//  java/lang/Object.toString:()Ljava/lang/String;
const #67 = Asciz	(Ljava/lang/String;)V;
const #68 = NameAndType	#8:#67;//  "<init>":(Ljava/lang/String;)V
const #69 = Method	#62.#68;	//  scala/MatchError."<init>":(Ljava/lang/String;)V
const #70 = Asciz	other;
const #71 = Asciz	temp12;
const #72 = NameAndType	#5:#56;//  capacity:()I
const #73 = Method	#17.#72;	//  scala/collection/mutable/ArrayBuilder$ofShort.capacity:()I
const #74 = Asciz	mkArray;
const #75 = Asciz	(I)[S;
const #76 = NameAndType	#74:#75;//  mkArray:(I)[S
const #77 = Method	#17.#76;	//  scala/collection/mutable/ArrayBuilder$ofShort.mkArray:(I)[S
const #78 = Asciz	clear;
const #79 = Asciz	size_$eq;
const #80 = Asciz	(I)V;
const #81 = NameAndType	#79:#80;//  size_$eq:(I)V
const #82 = Method	#17.#81;	//  scala/collection/mutable/ArrayBuilder$ofShort.size_$eq:(I)V
const #83 = Asciz	scala/collection/mutable/WrappedArray$ofShort;
const #84 = class	#83;	//  scala/collection/mutable/WrappedArray$ofShort
const #85 = Asciz	array;
const #86 = NameAndType	#85:#7;//  array:[S
const #87 = Field	#84.#86;	//  scala/collection/mutable/WrappedArray$ofShort.array:[S
const #88 = Asciz	ensureSize;
const #89 = NameAndType	#88:#80;//  ensureSize:(I)V
const #90 = Method	#17.#89;	//  scala/collection/mutable/ArrayBuilder$ofShort.ensureSize:(I)V
const #91 = Asciz	scala/Array$;
const #92 = class	#91;	//  scala/Array$
const #93 = Asciz	MODULE$;
const #94 = Asciz	Lscala/Array$;;
const #95 = NameAndType	#93:#94;//  MODULE$:Lscala/Array$;
const #96 = Field	#92.#95;	//  scala/Array$.MODULE$:Lscala/Array$;
const #97 = Asciz	copy;
const #98 = Asciz	(Ljava/lang/Object;ILjava/lang/Object;II)V;
const #99 = NameAndType	#97:#98;//  copy:(Ljava/lang/Object;ILjava/lang/Object;II)V
const #100 = Method	#92.#99;	//  scala/Array$.copy:(Ljava/lang/Object;ILjava/lang/Object;II)V
const #101 = NameAndType	#85:#47;//  array:()[S
const #102 = Method	#84.#101;	//  scala/collection/mutable/WrappedArray$ofShort.array:()[S
const #103 = Asciz	scala/collection/TraversableLike;
const #104 = class	#103;	//  scala/collection/TraversableLike
const #105 = InterfaceMethod	#104.#65;	//  scala/collection/TraversableLike.toString:()Ljava/lang/String;
const #106 = Asciz	scala/collection/generic/Growable$class;
const #107 = class	#106;	//  scala/collection/generic/Growable$class
const #108 = Asciz	(Lscala/collection/generic/Growable;Lscala/collection/Traversable;)Lscala/collection/generic/Growable;;
const #109 = NameAndType	#39:#108;//  $plus$plus$eq:(Lscala/collection/generic/Growable;Lscala/collection/Traversable;)Lscala/collection/generic/Growable;
const #110 = Method	#107.#109;	//  scala/collection/generic/Growable$class.$plus$plus$eq:(Lscala/collection/generic/Growable;Lscala/collection/Traversable;)Lscala/collection/generic/Growable;
const #111 = Asciz	xs;
const #112 = Asciz	temp10;
const #113 = Asciz	Lscala/collection/mutable/WrappedArray$ofShort;;
const #114 = Asciz	(Lscala/collection/Traversable<Ljava/lang/Short;>;)Lscala/collection/mutable/ArrayBuilder$ofShort;;
const #115 = Asciz	Signature;
const #116 = Asciz	S;
const #117 = int	16;
const #118 = Asciz	resize;
const #119 = NameAndType	#118:#80;//  resize:(I)V
const #120 = Method	#17.#119;	//  scala/collection/mutable/ArrayBuilder$ofShort.resize:(I)V
const #121 = Asciz	newsize;
const #122 = Asciz	sizeHint;
const #123 = Asciz	elems_$eq;
const #124 = Asciz	([S)V;
const #125 = NameAndType	#123:#124;//  elems_$eq:([S)V
const #126 = Method	#17.#125;	//  scala/collection/mutable/ArrayBuilder$ofShort.elems_$eq:([S)V
const #127 = Asciz	capacity_$eq;
const #128 = NameAndType	#127:#80;//  capacity_$eq:(I)V
const #129 = Method	#17.#128;	//  scala/collection/mutable/ArrayBuilder$ofShort.capacity_$eq:(I)V
const #130 = Asciz	newelems;
const #131 = NameAndType	#6:#7;//  elems:[S
const #132 = Field	#17.#131;	//  scala/collection/mutable/ArrayBuilder$ofShort.elems:[S
const #133 = Asciz	Lscala/collection/mutable/ArrayBuilder<Ljava/lang/Short;>;Lscala/ScalaObject;;
const #134 = Asciz	Scala;
const #135 = Asciz	InnerClasses;
const #136 = Asciz	scala/collection/mutable/WrappedArray;
const #137 = class	#136;	//  scala/collection/mutable/WrappedArray
const #138 = Asciz	ofShort;
const #139 = Asciz	scala/ScalaObject;
const #140 = class	#139;	//  scala/ScalaObject

{
public scala.collection.mutable.ArrayBuilder$ofShort();
  Code:
   Stack=2, Locals=1, Args_size=1
   0:	aload_0
   1:	invokespecial	#15; //Method scala/collection/mutable/ArrayBuilder."<init>":()V
   4:	aload_0
   5:	iconst_0
   6:	putfield	#19; //Field capacity:I
   9:	aload_0
   10:	iconst_0
   11:	putfield	#21; //Field size:I
   14:	return
  LineNumberTable: 
   line 161: 0
   line 164: 4
   line 165: 9


public scala.collection.mutable.Builder $plus$eq(java.lang.Object);
  Code:
   Stack=2, Locals=2, Args_size=2
   0:	aload_0
   1:	aload_1
   2:	invokestatic	#29; //Method scala/runtime/BoxesRunTime.unboxToShort:(Ljava/lang/Object;)S
   5:	invokevirtual	#32; //Method $plus$eq:(S)Lscala/collection/mutable/ArrayBuilder$ofShort;
   8:	areturn
  LineNumberTable: 
   line 161: 0

  LocalVariableTable: 
   Start  Length  Slot  Name   Signature
   0      9      0    this       Lscala/collection/mutable/ArrayBuilder$ofShort;
   0      9      1    elem       Ljava/lang/Object;


public scala.collection.generic.Growable $plus$eq(java.lang.Object);
  Code:
   Stack=2, Locals=2, Args_size=2
   0:	aload_0
   1:	aload_1
   2:	invokestatic	#29; //Method scala/runtime/BoxesRunTime.unboxToShort:(Ljava/lang/Object;)S
   5:	invokevirtual	#32; //Method $plus$eq:(S)Lscala/collection/mutable/ArrayBuilder$ofShort;
   8:	areturn
  LineNumberTable: 
   line 161: 0

  LocalVariableTable: 
   Start  Length  Slot  Name   Signature
   0      9      0    this       Lscala/collection/mutable/ArrayBuilder$ofShort;
   0      9      1    elem       Ljava/lang/Object;


public scala.collection.generic.Growable $plus$plus$eq(scala.collection.Traversable);
  Code:
   Stack=2, Locals=2, Args_size=2
   0:	aload_0
   1:	aload_1
   2:	invokevirtual	#43; //Method $plus$plus$eq:(Lscala/collection/Traversable;)Lscala/collection/mutable/ArrayBuilder$ofShort;
   5:	areturn
  LineNumberTable: 
   line 161: 0

  LocalVariableTable: 
   Start  Length  Slot  Name   Signature
   0      6      0    this       Lscala/collection/mutable/ArrayBuilder$ofShort;
   0      6      1    elems       Lscala/collection/Traversable;


public java.lang.Object result();
  Code:
   Stack=1, Locals=1, Args_size=1
   0:	aload_0
   1:	invokevirtual	#49; //Method result:()[S
   4:	areturn
  LineNumberTable: 
   line 161: 0


public java.lang.String toString();
  Code:
   Stack=1, Locals=1, Args_size=1
   0:	ldc	#53; //String ArrayBuilder.ofShort
   2:	areturn
  LineNumberTable: 
   line 222: 0


public boolean equals(java.lang.Object);
  Code:
   Stack=3, Locals=3, Args_size=2
   0:	aload_1
   1:	instanceof	#17; //class scala/collection/mutable/ArrayBuilder$ofShort
   4:	ifeq	58
   7:	aload_1
   8:	checkcast	#17; //class scala/collection/mutable/ArrayBuilder$ofShort
   11:	astore_2
   12:	iconst_1
   13:	ifeq	46
   16:	aload_0
   17:	invokespecial	#58; //Method size:()I
   20:	aload_2
   21:	invokespecial	#58; //Method size:()I
   24:	if_icmpne	42
   27:	aload_0
   28:	invokespecial	#60; //Method elems:()[S
   31:	aload_2
   32:	invokespecial	#60; //Method elems:()[S
   35:	if_acmpne	42
   38:	iconst_1
   39:	goto	63
   42:	iconst_0
   43:	goto	63
   46:	new	#62; //class scala/MatchError
   49:	dup
   50:	aload_1
   51:	invokevirtual	#66; //Method java/lang/Object.toString:()Ljava/lang/String;
   54:	invokespecial	#69; //Method scala/MatchError."<init>":(Ljava/lang/String;)V
   57:	athrow
   58:	iconst_1
   59:	ifeq	64
   62:	iconst_0
   63:	ireturn
   64:	new	#62; //class scala/MatchError
   67:	dup
   68:	aload_1
   69:	invokevirtual	#66; //Method java/lang/Object.toString:()Ljava/lang/String;
   72:	invokespecial	#69; //Method scala/MatchError."<init>":(Ljava/lang/String;)V
   75:	athrow
  LineNumberTable: 
   line 217: 0
   line 21: 12
   line 218: 16
   line 217: 46
   line 21: 58
   line 219: 62
   line 217: 63

  LocalVariableTable: 
   Start  Length  Slot  Name   Signature
   0      76      0    this       Lscala/collection/mutable/ArrayBuilder$ofShort;
   0      76      1    other       Ljava/lang/Object;
   12      46      2    temp12       Lscala/collection/mutable/ArrayBuilder$ofShort;


public short[] result();
  Code:
   Stack=2, Locals=1, Args_size=1
   0:	aload_0
   1:	invokespecial	#73; //Method capacity:()I
   4:	iconst_0
   5:	if_icmpeq	26
   8:	aload_0
   9:	invokespecial	#73; //Method capacity:()I
   12:	aload_0
   13:	invokespecial	#58; //Method size:()I
   16:	if_icmpne	26
   19:	aload_0
   20:	invokespecial	#60; //Method elems:()[S
   23:	goto	34
   26:	aload_0
   27:	aload_0
   28:	invokespecial	#58; //Method size:()I
   31:	invokespecial	#77; //Method mkArray:(I)[S
   34:	areturn
  LineNumberTable: 
   line 213: 0
   line 214: 26
   line 213: 34


public void clear();
  Code:
   Stack=2, Locals=1, Args_size=1
   0:	aload_0
   1:	iconst_0
   2:	invokespecial	#82; //Method size_$eq:(I)V
   5:	return
  LineNumberTable: 
   line 209: 0


public scala.collection.mutable.ArrayBuilder$ofShort $plus$plus$eq(scala.collection.Traversable);
  Code:
   Stack=6, Locals=3, Args_size=2
   0:	aload_1
   1:	instanceof	#84; //class scala/collection/mutable/WrappedArray$ofShort
   4:	ifeq	86
   7:	aload_1
   8:	checkcast	#84; //class scala/collection/mutable/WrappedArray$ofShort
   11:	astore_2
   12:	iconst_1
   13:	ifeq	72
   16:	aload_0
   17:	aload_0
   18:	invokespecial	#58; //Method size:()I
   21:	aload_2
   22:	getfield	#87; //Field scala/collection/mutable/WrappedArray$ofShort.array:[S
   25:	arraylength
   26:	iadd
   27:	invokespecial	#90; //Method ensureSize:(I)V
   30:	getstatic	#96; //Field scala/Array$.MODULE$:Lscala/Array$;
   33:	aload_2
   34:	getfield	#87; //Field scala/collection/mutable/WrappedArray$ofShort.array:[S
   37:	iconst_0
   38:	aload_0
   39:	invokespecial	#60; //Method elems:()[S
   42:	aload_0
   43:	invokespecial	#58; //Method size:()I
   46:	aload_2
   47:	getfield	#87; //Field scala/collection/mutable/WrappedArray$ofShort.array:[S
   50:	arraylength
   51:	invokevirtual	#100; //Method scala/Array$.copy:(Ljava/lang/Object;ILjava/lang/Object;II)V
   54:	aload_0
   55:	aload_0
   56:	invokespecial	#58; //Method size:()I
   59:	aload_2
   60:	invokevirtual	#102; //Method scala/collection/mutable/WrappedArray$ofShort.array:()[S
   63:	arraylength
   64:	iadd
   65:	invokespecial	#82; //Method size_$eq:(I)V
   68:	aload_0
   69:	goto	98
   72:	new	#62; //class scala/MatchError
   75:	dup
   76:	aload_1
   77:	invokeinterface	#105,  1; //InterfaceMethod scala/collection/TraversableLike.toString:()Ljava/lang/String;
   82:	invokespecial	#69; //Method scala/MatchError."<init>":(Ljava/lang/String;)V
   85:	athrow
   86:	iconst_1
   87:	ifeq	99
   90:	aload_0
   91:	aload_1
   92:	invokestatic	#110; //Method scala/collection/generic/Growable$class.$plus$plus$eq:(Lscala/collection/generic/Growable;Lscala/collection/Traversable;)Lscala/collection/generic/Growable;
   95:	checkcast	#17; //class scala/collection/mutable/ArrayBuilder$ofShort
   98:	areturn
   99:	new	#62; //class scala/MatchError
   102:	dup
   103:	aload_1
   104:	invokeinterface	#105,  1; //InterfaceMethod scala/collection/TraversableLike.toString:()Ljava/lang/String;
   109:	invokespecial	#69; //Method scala/MatchError."<init>":(Ljava/lang/String;)V
   112:	athrow
  LineNumberTable: 
   line 198: 0
   line 21: 12
   line 200: 16
   line 201: 30
   line 202: 54
   line 203: 68
   line 198: 72
   line 21: 86
   line 205: 90
   line 198: 98

  LocalVariableTable: 
   Start  Length  Slot  Name   Signature
   0      113      0    this       Lscala/collection/mutable/ArrayBuilder$ofShort;
   0      113      1    xs       Lscala/collection/Traversable;
   12      74      2    temp10       Lscala/collection/mutable/WrappedArray$ofShort;

  Signature: length = 0x2
   00 72 

public scala.collection.mutable.ArrayBuilder$ofShort $plus$eq(short);
  Code:
   Stack=3, Locals=2, Args_size=2
   0:	aload_0
   1:	aload_0
   2:	invokespecial	#58; //Method size:()I
   5:	iconst_1
   6:	iadd
   7:	invokespecial	#90; //Method ensureSize:(I)V
   10:	aload_0
   11:	invokespecial	#60; //Method elems:()[S
   14:	aload_0
   15:	invokespecial	#58; //Method size:()I
   18:	iload_1
   19:	sastore
   20:	aload_0
   21:	aload_0
   22:	invokespecial	#58; //Method size:()I
   25:	iconst_1
   26:	iadd
   27:	invokespecial	#82; //Method size_$eq:(I)V
   30:	aload_0
   31:	areturn
  LineNumberTable: 
   line 192: 0
   line 193: 10
   line 194: 20
   line 195: 30

  LocalVariableTable: 
   Start  Length  Slot  Name   Signature
   0      32      0    this       Lscala/collection/mutable/ArrayBuilder$ofShort;
   0      32      1    elem       S


public void sizeHint(int);
  Code:
   Stack=2, Locals=2, Args_size=2
   0:	aload_0
   1:	invokespecial	#73; //Method capacity:()I
   4:	iload_1
   5:	if_icmpge	13
   8:	aload_0
   9:	iload_1
   10:	invokespecial	#120; //Method resize:(I)V
   13:	return
  LineNumberTable: 
   line 179: 0

  LocalVariableTable: 
   Start  Length  Slot  Name   Signature
   0      14      0    this       Lscala/collection/mutable/ArrayBuilder$ofShort;
   0      14      1    size       I


}

