Compiled from "ArrayOps.scala"
public class scala.collection.mutable.ArrayOps$ofFloat extends scala.collection.mutable.ArrayOps implements scala.collection.mutable.ArrayLike,scala.ScalaObject
  SourceFile: "ArrayOps.scala"
  Signature: length = 0x2
   00 57 
  Scala: length = 0x
   
  InnerClass: 
   public #90= #10 of #14; //ofFloat=class scala/collection/mutable/ArrayOps$ofFloat of class scala/collection/mutable/ArrayOps
   public final #90= #81 of #92; //ofFloat=class scala/collection/mutable/WrappedArray$ofFloat of class scala/collection/mutable/WrappedArray
   public #90= #78 of #94; //ofFloat=class scala/collection/mutable/ArrayBuilder$ofFloat of class scala/collection/mutable/ArrayBuilder
  minor version: 0
  major version: 49
  Constant pool:
const #1 = Asciz	SourceFile;
const #2 = Asciz	ArrayOps.scala;
const #3 = Asciz	repr;
const #4 = Asciz	[F;
const #5 = Asciz	<init>;
const #6 = Asciz	([F)V;
const #7 = Asciz	Code;
const #8 = Asciz	LineNumberTable;
const #9 = Asciz	scala/collection/mutable/ArrayOps$ofFloat;
const #10 = class	#9;	//  scala/collection/mutable/ArrayOps$ofFloat
const #11 = NameAndType	#3:#4;//  repr:[F
const #12 = Field	#10.#11;	//  scala/collection/mutable/ArrayOps$ofFloat.repr:[F
const #13 = Asciz	scala/collection/mutable/ArrayOps;
const #14 = class	#13;	//  scala/collection/mutable/ArrayOps
const #15 = Asciz	()V;
const #16 = NameAndType	#5:#15;//  "<init>":()V
const #17 = Method	#14.#16;	//  scala/collection/mutable/ArrayOps."<init>":()V
const #18 = Asciz	this;
const #19 = Asciz	Lscala/collection/mutable/ArrayOps$ofFloat;;
const #20 = Asciz	LocalVariableTable;
const #21 = Asciz	()Ljava/lang/Object;;
const #22 = Asciz	()[F;
const #23 = NameAndType	#3:#22;//  repr:()[F
const #24 = Method	#10.#23;	//  scala/collection/mutable/ArrayOps$ofFloat.repr:()[F
const #25 = Asciz	thisCollection;
const #26 = Asciz	()Lscala/collection/mutable/IndexedSeq;;
const #27 = Asciz	()Lscala/collection/mutable/WrappedArray;;
const #28 = NameAndType	#25:#27;//  thisCollection:()Lscala/collection/mutable/WrappedArray;
const #29 = Method	#10.#28;	//  scala/collection/mutable/ArrayOps$ofFloat.thisCollection:()Lscala/collection/mutable/WrappedArray;
const #30 = Asciz	()Lscala/collection/IndexedSeq;;
const #31 = Asciz	()Lscala/collection/Seq;;
const #32 = Asciz	()Lscala/collection/Iterable;;
const #33 = Asciz	()Lscala/collection/Traversable;;
const #34 = Asciz	toCollection;
const #35 = Asciz	(Ljava/lang/Object;)Lscala/collection/mutable/IndexedSeq;;
const #36 = class	#4;	//  "[F"
const #37 = Asciz	([F)Lscala/collection/mutable/WrappedArray;;
const #38 = NameAndType	#34:#37;//  toCollection:([F)Lscala/collection/mutable/WrappedArray;
const #39 = Method	#10.#38;	//  scala/collection/mutable/ArrayOps$ofFloat.toCollection:([F)Lscala/collection/mutable/WrappedArray;
const #40 = Asciz	Ljava/lang/Object;;
const #41 = Asciz	(Ljava/lang/Object;)Lscala/collection/IndexedSeq;;
const #42 = Asciz	(Ljava/lang/Object;)Lscala/collection/Seq;;
const #43 = Asciz	(Ljava/lang/Object;)Lscala/collection/Iterable;;
const #44 = Asciz	(Ljava/lang/Object;)Lscala/collection/Traversable;;
const #45 = Asciz	newBuilder;
const #46 = Asciz	()Lscala/collection/mutable/Builder;;
const #47 = Asciz	()Lscala/collection/mutable/ArrayBuilder$ofFloat;;
const #48 = NameAndType	#45:#47;//  newBuilder:()Lscala/collection/mutable/ArrayBuilder$ofFloat;
const #49 = Method	#10.#48;	//  scala/collection/mutable/ArrayOps$ofFloat.newBuilder:()Lscala/collection/mutable/ArrayBuilder$ofFloat;
const #50 = Asciz	apply;
const #51 = Asciz	(I)Ljava/lang/Object;;
const #52 = Asciz	(I)F;
const #53 = NameAndType	#50:#52;//  apply:(I)F
const #54 = Method	#10.#53;	//  scala/collection/mutable/ArrayOps$ofFloat.apply:(I)F
const #55 = Asciz	scala/runtime/BoxesRunTime;
const #56 = class	#55;	//  scala/runtime/BoxesRunTime
const #57 = Asciz	boxToFloat;
const #58 = Asciz	(F)Ljava/lang/Float;;
const #59 = NameAndType	#57:#58;//  boxToFloat:(F)Ljava/lang/Float;
const #60 = Method	#56.#59;	//  scala/runtime/BoxesRunTime.boxToFloat:(F)Ljava/lang/Float;
const #61 = Asciz	idx;
const #62 = Asciz	I;
const #63 = Asciz	update;
const #64 = Asciz	(ILjava/lang/Object;)V;
const #65 = Asciz	unboxToFloat;
const #66 = Asciz	(Ljava/lang/Object;)F;
const #67 = NameAndType	#65:#66;//  unboxToFloat:(Ljava/lang/Object;)F
const #68 = Method	#56.#67;	//  scala/runtime/BoxesRunTime.unboxToFloat:(Ljava/lang/Object;)F
const #69 = Asciz	(IF)V;
const #70 = NameAndType	#63:#69;//  update:(IF)V
const #71 = Method	#10.#70;	//  scala/collection/mutable/ArrayOps$ofFloat.update:(IF)V
const #72 = Asciz	elem;
const #73 = Asciz	index;
const #74 = Asciz	F;
const #75 = Asciz	length;
const #76 = Asciz	()I;
const #77 = Asciz	scala/collection/mutable/ArrayBuilder$ofFloat;
const #78 = class	#77;	//  scala/collection/mutable/ArrayBuilder$ofFloat
const #79 = Method	#78.#16;	//  scala/collection/mutable/ArrayBuilder$ofFloat."<init>":()V
const #80 = Asciz	scala/collection/mutable/WrappedArray$ofFloat;
const #81 = class	#80;	//  scala/collection/mutable/WrappedArray$ofFloat
const #82 = NameAndType	#5:#6;//  "<init>":([F)V
const #83 = Method	#81.#82;	//  scala/collection/mutable/WrappedArray$ofFloat."<init>":([F)V
const #84 = Asciz	([F)Lscala/collection/mutable/WrappedArray<Ljava/lang/Float;>;;
const #85 = Asciz	Signature;
const #86 = Asciz	()Lscala/collection/mutable/WrappedArray<Ljava/lang/Float;>;;
const #87 = Asciz	Lscala/collection/mutable/ArrayOps<Ljava/lang/Float;>;Lscala/collection/mutable/ArrayLike<Ljava/lang/Float;[F>;Lscala/ScalaObject;;
const #88 = Asciz	Scala;
const #89 = Asciz	InnerClasses;
const #90 = Asciz	ofFloat;
const #91 = Asciz	scala/collection/mutable/WrappedArray;
const #92 = class	#91;	//  scala/collection/mutable/WrappedArray
const #93 = Asciz	scala/collection/mutable/ArrayBuilder;
const #94 = class	#93;	//  scala/collection/mutable/ArrayBuilder
const #95 = Asciz	scala/collection/mutable/ArrayLike;
const #96 = class	#95;	//  scala/collection/mutable/ArrayLike
const #97 = Asciz	scala/ScalaObject;
const #98 = class	#97;	//  scala/ScalaObject

{
public scala.collection.mutable.ArrayOps$ofFloat(float[]);
  Code:
   Stack=2, Locals=2, Args_size=2
   0:	aload_0
   1:	aload_1
   2:	putfield	#12; //Field repr:[F
   5:	aload_0
   6:	invokespecial	#17; //Method scala/collection/mutable/ArrayOps."<init>":()V
   9:	return
  LineNumberTable: 
   line 128: 0

  LocalVariableTable: 
   Start  Length  Slot  Name   Signature
   0      10      0    this       Lscala/collection/mutable/ArrayOps$ofFloat;
   0      10      1    repr       [F


public java.lang.Object repr();
  Code:
   Stack=1, Locals=1, Args_size=1
   0:	aload_0
   1:	invokevirtual	#24; //Method repr:()[F
   4:	areturn
  LineNumberTable: 
   line 128: 0


public scala.collection.mutable.IndexedSeq thisCollection();
  Code:
   Stack=1, Locals=1, Args_size=1
   0:	aload_0
   1:	invokevirtual	#29; //Method thisCollection:()Lscala/collection/mutable/WrappedArray;
   4:	areturn
  LineNumberTable: 
   line 128: 0


public scala.collection.IndexedSeq thisCollection();
  Code:
   Stack=1, Locals=1, Args_size=1
   0:	aload_0
   1:	invokevirtual	#29; //Method thisCollection:()Lscala/collection/mutable/WrappedArray;
   4:	areturn
  LineNumberTable: 
   line 128: 0


public scala.collection.Seq thisCollection();
  Code:
   Stack=1, Locals=1, Args_size=1
   0:	aload_0
   1:	invokevirtual	#29; //Method thisCollection:()Lscala/collection/mutable/WrappedArray;
   4:	areturn
  LineNumberTable: 
   line 128: 0


public scala.collection.Iterable thisCollection();
  Code:
   Stack=1, Locals=1, Args_size=1
   0:	aload_0
   1:	invokevirtual	#29; //Method thisCollection:()Lscala/collection/mutable/WrappedArray;
   4:	areturn
  LineNumberTable: 
   line 128: 0


public scala.collection.Traversable thisCollection();
  Code:
   Stack=1, Locals=1, Args_size=1
   0:	aload_0
   1:	invokevirtual	#29; //Method thisCollection:()Lscala/collection/mutable/WrappedArray;
   4:	areturn
  LineNumberTable: 
   line 128: 0


public scala.collection.mutable.IndexedSeq toCollection(java.lang.Object);
  Code:
   Stack=2, Locals=2, Args_size=2
   0:	aload_0
   1:	aload_1
   2:	checkcast	#36; //class "[F"
   5:	invokevirtual	#39; //Method toCollection:([F)Lscala/collection/mutable/WrappedArray;
   8:	areturn
  LineNumberTable: 
   line 128: 0

  LocalVariableTable: 
   Start  Length  Slot  Name   Signature
   0      9      0    this       Lscala/collection/mutable/ArrayOps$ofFloat;
   0      9      1    repr       Ljava/lang/Object;


public scala.collection.IndexedSeq toCollection(java.lang.Object);
  Code:
   Stack=2, Locals=2, Args_size=2
   0:	aload_0
   1:	aload_1
   2:	checkcast	#36; //class "[F"
   5:	invokevirtual	#39; //Method toCollection:([F)Lscala/collection/mutable/WrappedArray;
   8:	areturn
  LineNumberTable: 
   line 128: 0

  LocalVariableTable: 
   Start  Length  Slot  Name   Signature
   0      9      0    this       Lscala/collection/mutable/ArrayOps$ofFloat;
   0      9      1    repr       Ljava/lang/Object;


public scala.collection.Seq toCollection(java.lang.Object);
  Code:
   Stack=2, Locals=2, Args_size=2
   0:	aload_0
   1:	aload_1
   2:	checkcast	#36; //class "[F"
   5:	invokevirtual	#39; //Method toCollection:([F)Lscala/collection/mutable/WrappedArray;
   8:	areturn
  LineNumberTable: 
   line 128: 0

  LocalVariableTable: 
   Start  Length  Slot  Name   Signature
   0      9      0    this       Lscala/collection/mutable/ArrayOps$ofFloat;
   0      9      1    repr       Ljava/lang/Object;


public scala.collection.Iterable toCollection(java.lang.Object);
  Code:
   Stack=2, Locals=2, Args_size=2
   0:	aload_0
   1:	aload_1
   2:	checkcast	#36; //class "[F"
   5:	invokevirtual	#39; //Method toCollection:([F)Lscala/collection/mutable/WrappedArray;
   8:	areturn
  LineNumberTable: 
   line 128: 0

  LocalVariableTable: 
   Start  Length  Slot  Name   Signature
   0      9      0    this       Lscala/collection/mutable/ArrayOps$ofFloat;
   0      9      1    repr       Ljava/lang/Object;


public scala.collection.Traversable toCollection(java.lang.Object);
  Code:
   Stack=2, Locals=2, Args_size=2
   0:	aload_0
   1:	aload_1
   2:	checkcast	#36; //class "[F"
   5:	invokevirtual	#39; //Method toCollection:([F)Lscala/collection/mutable/WrappedArray;
   8:	areturn
  LineNumberTable: 
   line 128: 0

  LocalVariableTable: 
   Start  Length  Slot  Name   Signature
   0      9      0    this       Lscala/collection/mutable/ArrayOps$ofFloat;
   0      9      1    repr       Ljava/lang/Object;


public scala.collection.mutable.Builder newBuilder();
  Code:
   Stack=1, Locals=1, Args_size=1
   0:	aload_0
   1:	invokevirtual	#49; //Method newBuilder:()Lscala/collection/mutable/ArrayBuilder$ofFloat;
   4:	areturn
  LineNumberTable: 
   line 128: 0


public java.lang.Object apply(int);
  Code:
   Stack=2, Locals=3, Args_size=2
   0:	aload_0
   1:	iload_1
   2:	invokevirtual	#54; //Method apply:(I)F
   5:	fstore_2
   6:	fload_2
   7:	invokestatic	#60; //Method scala/runtime/BoxesRunTime.boxToFloat:(F)Ljava/lang/Float;
   10:	areturn
  LineNumberTable: 
   line 128: 0

  LocalVariableTable: 
   Start  Length  Slot  Name   Signature
   0      11      0    this       Lscala/collection/mutable/ArrayOps$ofFloat;
   0      11      1    idx       I


public void update(int, java.lang.Object);
  Code:
   Stack=3, Locals=3, Args_size=3
   0:	aload_0
   1:	iload_1
   2:	aload_2
   3:	invokestatic	#68; //Method scala/runtime/BoxesRunTime.unboxToFloat:(Ljava/lang/Object;)F
   6:	invokevirtual	#71; //Method update:(IF)V
   9:	return
  LineNumberTable: 
   line 128: 0

  LocalVariableTable: 
   Start  Length  Slot  Name   Signature
   0      10      0    this       Lscala/collection/mutable/ArrayOps$ofFloat;
   0      10      1    idx       I
   0      10      2    elem       Ljava/lang/Object;


public void update(int, float);
  Code:
   Stack=3, Locals=3, Args_size=3
   0:	aload_0
   1:	invokevirtual	#24; //Method repr:()[F
   4:	iload_1
   5:	fload_2
   6:	fastore
   7:	return
  LineNumberTable: 
   line 136: 0

  LocalVariableTable: 
   Start  Length  Slot  Name   Signature
   0      8      0    this       Lscala/collection/mutable/ArrayOps$ofFloat;
   0      8      1    index       I
   0      8      2    elem       F


public float apply(int);
  Code:
   Stack=2, Locals=2, Args_size=2
   0:	aload_0
   1:	invokevirtual	#24; //Method repr:()[F
   4:	iload_1
   5:	faload
   6:	freturn
  LineNumberTable: 
   line 135: 0

  LocalVariableTable: 
   Start  Length  Slot  Name   Signature
   0      7      0    this       Lscala/collection/mutable/ArrayOps$ofFloat;
   0      7      1    index       I


public int length();
  Code:
   Stack=1, Locals=1, Args_size=1
   0:	aload_0
   1:	invokevirtual	#24; //Method repr:()[F
   4:	arraylength
   5:	ireturn
  LineNumberTable: 
   line 134: 0


public scala.collection.mutable.ArrayBuilder$ofFloat newBuilder();
  Code:
   Stack=2, Locals=1, Args_size=1
   0:	new	#78; //class scala/collection/mutable/ArrayBuilder$ofFloat
   3:	dup
   4:	invokespecial	#79; //Method scala/collection/mutable/ArrayBuilder$ofFloat."<init>":()V
   7:	areturn
  LineNumberTable: 
   line 132: 0


public scala.collection.mutable.WrappedArray toCollection(float[]);
  Code:
   Stack=3, Locals=2, Args_size=2
   0:	new	#81; //class scala/collection/mutable/WrappedArray$ofFloat
   3:	dup
   4:	aload_1
   5:	invokespecial	#83; //Method scala/collection/mutable/WrappedArray$ofFloat."<init>":([F)V
   8:	areturn
  LineNumberTable: 
   line 131: 0

  LocalVariableTable: 
   Start  Length  Slot  Name   Signature
   0      9      0    this       Lscala/collection/mutable/ArrayOps$ofFloat;
   0      9      1    repr       [F

  Signature: length = 0x2
   00 54 

public scala.collection.mutable.WrappedArray thisCollection();
  Code:
   Stack=3, Locals=1, Args_size=1
   0:	new	#81; //class scala/collection/mutable/WrappedArray$ofFloat
   3:	dup
   4:	aload_0
   5:	invokevirtual	#24; //Method repr:()[F
   8:	invokespecial	#83; //Method scala/collection/mutable/WrappedArray$ofFloat."<init>":([F)V
   11:	areturn
  LineNumberTable: 
   line 130: 0

  Signature: length = 0x2
   00 56 

public float[] repr();
  Code:
   Stack=1, Locals=1, Args_size=1
   0:	aload_0
   1:	getfield	#12; //Field repr:[F
   4:	areturn
  LineNumberTable: 
   line 128: 0


}

