Compiled from "ArrayOps.scala"
public class scala.collection.mutable.ArrayOps$ofChar extends scala.collection.mutable.ArrayOps implements scala.collection.mutable.ArrayLike,scala.ScalaObject
  SourceFile: "ArrayOps.scala"
  Signature: length = 0x2
   00 57 
  Scala: length = 0x
   
  InnerClass: 
   public ofChar=class scala/collection/mutable/ArrayOps$ofChar of class scala/collection/mutable/ArrayOps
   public final ofChar=class scala/collection/mutable/WrappedArray$ofChar of class scala/collection/mutable/WrappedArray
   public ofChar=class scala/collection/mutable/ArrayBuilder$ofChar of class scala/collection/mutable/ArrayBuilder
  minor version: 0
  major version: 49
  Constant pool:
Asciz	SourceFile;
Asciz	ArrayOps.scala;
Asciz	repr;
Asciz	[C;
Asciz	<init>;
Asciz	([C)V;
Asciz	Code;
Asciz	LineNumberTable;
Asciz	scala/collection/mutable/ArrayOps$ofChar;
class	scala/collection/mutable/ArrayOps$ofChar
NameAndType	repr:[C
Field	scala/collection/mutable/ArrayOps$ofChar.repr:[C
Asciz	scala/collection/mutable/ArrayOps;
class	scala/collection/mutable/ArrayOps
Asciz	()V;
NameAndType	"<init>":()V
Method	scala/collection/mutable/ArrayOps."<init>":()V
Asciz	this;
Asciz	Lscala/collection/mutable/ArrayOps$ofChar;;
Asciz	LocalVariableTable;
Asciz	()Ljava/lang/Object;;
Asciz	()[C;
NameAndType	repr:()[C
Method	scala/collection/mutable/ArrayOps$ofChar.repr:()[C
Asciz	thisCollection;
Asciz	()Lscala/collection/mutable/IndexedSeq;;
Asciz	()Lscala/collection/mutable/WrappedArray;;
NameAndType	thisCollection:()Lscala/collection/mutable/WrappedArray;
Method	scala/collection/mutable/ArrayOps$ofChar.thisCollection:()Lscala/collection/mutable/WrappedArray;
Asciz	()Lscala/collection/IndexedSeq;;
Asciz	()Lscala/collection/Seq;;
Asciz	()Lscala/collection/Iterable;;
Asciz	()Lscala/collection/Traversable;;
Asciz	toCollection;
Asciz	(Ljava/lang/Object;)Lscala/collection/mutable/IndexedSeq;;
class	"[C"
Asciz	([C)Lscala/collection/mutable/WrappedArray;;
NameAndType	toCollection:([C)Lscala/collection/mutable/WrappedArray;
Method	scala/collection/mutable/ArrayOps$ofChar.toCollection:([C)Lscala/collection/mutable/WrappedArray;
Asciz	Ljava/lang/Object;;
Asciz	(Ljava/lang/Object;)Lscala/collection/IndexedSeq;;
Asciz	(Ljava/lang/Object;)Lscala/collection/Seq;;
Asciz	(Ljava/lang/Object;)Lscala/collection/Iterable;;
Asciz	(Ljava/lang/Object;)Lscala/collection/Traversable;;
Asciz	newBuilder;
Asciz	()Lscala/collection/mutable/Builder;;
Asciz	()Lscala/collection/mutable/ArrayBuilder$ofChar;;
NameAndType	newBuilder:()Lscala/collection/mutable/ArrayBuilder$ofChar;
Method	scala/collection/mutable/ArrayOps$ofChar.newBuilder:()Lscala/collection/mutable/ArrayBuilder$ofChar;
Asciz	apply;
Asciz	(I)Ljava/lang/Object;;
Asciz	(I)C;
NameAndType	apply:(I)C
Method	scala/collection/mutable/ArrayOps$ofChar.apply:(I)C
Asciz	scala/runtime/BoxesRunTime;
class	scala/runtime/BoxesRunTime
Asciz	boxToCharacter;
Asciz	(C)Ljava/lang/Character;;
NameAndType	boxToCharacter:(C)Ljava/lang/Character;
Method	scala/runtime/BoxesRunTime.boxToCharacter:(C)Ljava/lang/Character;
Asciz	idx;
Asciz	I;
Asciz	update;
Asciz	(ILjava/lang/Object;)V;
Asciz	unboxToChar;
Asciz	(Ljava/lang/Object;)C;
NameAndType	unboxToChar:(Ljava/lang/Object;)C
Method	scala/runtime/BoxesRunTime.unboxToChar:(Ljava/lang/Object;)C
Asciz	(IC)V;
NameAndType	update:(IC)V
Method	scala/collection/mutable/ArrayOps$ofChar.update:(IC)V
Asciz	elem;
Asciz	index;
Asciz	C;
Asciz	length;
Asciz	()I;
Asciz	scala/collection/mutable/ArrayBuilder$ofChar;
class	scala/collection/mutable/ArrayBuilder$ofChar
Method	scala/collection/mutable/ArrayBuilder$ofChar."<init>":()V
Asciz	scala/collection/mutable/WrappedArray$ofChar;
class	scala/collection/mutable/WrappedArray$ofChar
NameAndType	"<init>":([C)V
Method	scala/collection/mutable/WrappedArray$ofChar."<init>":([C)V
Asciz	([C)Lscala/collection/mutable/WrappedArray<Ljava/lang/Character;>;;
Asciz	Signature;
Asciz	()Lscala/collection/mutable/WrappedArray<Ljava/lang/Character;>;;
Asciz	Lscala/collection/mutable/ArrayOps<Ljava/lang/Character;>;Lscala/collection/mutable/ArrayLike<Ljava/lang/Character;[C>;Lscala/ScalaObject;;
Asciz	Scala;
Asciz	InnerClasses;
Asciz	ofChar;
Asciz	scala/collection/mutable/WrappedArray;
class	scala/collection/mutable/WrappedArray
Asciz	scala/collection/mutable/ArrayBuilder;
class	scala/collection/mutable/ArrayBuilder
Asciz	scala/collection/mutable/ArrayLike;
class	scala/collection/mutable/ArrayLike
Asciz	scala/ScalaObject;
class	scala/ScalaObject

{
private final char[] repr;
  Signature: [C

public scala.collection.mutable.ArrayOps$ofChar(char[]);
  Signature: ([C)V
  Code:
   Stack=2, Locals=2, Args_size=2
	aload_0
	aload_1
	putfield	Field repr:[C
	aload_0
	invokespecial	Method scala/collection/mutable/ArrayOps."<init>":()V
	return
  Labels:
  LocalVariableTable: 
   Start  Length  Slot  Name   Signature
   0      10      0    this       Lscala/collection/mutable/ArrayOps$ofChar;
   0      10      1    repr       [C


public java.lang.Object repr();
  Signature: ()Ljava/lang/Object;
  Code:
   Stack=1, Locals=1, Args_size=1
	aload_0
	invokevirtual	Method repr:()[C
	areturn
  Labels:

public scala.collection.mutable.IndexedSeq thisCollection();
  Signature: ()Lscala/collection/mutable/IndexedSeq;
  Code:
   Stack=1, Locals=1, Args_size=1
	aload_0
	invokevirtual	Method thisCollection:()Lscala/collection/mutable/WrappedArray;
	areturn
  Labels:

public scala.collection.IndexedSeq thisCollection();
  Signature: ()Lscala/collection/IndexedSeq;
  Code:
   Stack=1, Locals=1, Args_size=1
	aload_0
	invokevirtual	Method thisCollection:()Lscala/collection/mutable/WrappedArray;
	areturn
  Labels:

public scala.collection.Seq thisCollection();
  Signature: ()Lscala/collection/Seq;
  Code:
   Stack=1, Locals=1, Args_size=1
	aload_0
	invokevirtual	Method thisCollection:()Lscala/collection/mutable/WrappedArray;
	areturn
  Labels:

public scala.collection.Iterable thisCollection();
  Signature: ()Lscala/collection/Iterable;
  Code:
   Stack=1, Locals=1, Args_size=1
	aload_0
	invokevirtual	Method thisCollection:()Lscala/collection/mutable/WrappedArray;
	areturn
  Labels:

public scala.collection.Traversable thisCollection();
  Signature: ()Lscala/collection/Traversable;
  Code:
   Stack=1, Locals=1, Args_size=1
	aload_0
	invokevirtual	Method thisCollection:()Lscala/collection/mutable/WrappedArray;
	areturn
  Labels:

public scala.collection.mutable.IndexedSeq toCollection(java.lang.Object);
  Signature: (Ljava/lang/Object;)Lscala/collection/mutable/IndexedSeq;
  Code:
   Stack=2, Locals=2, Args_size=2
	aload_0
	aload_1
	checkcast	class "[C"
	invokevirtual	Method toCollection:([C)Lscala/collection/mutable/WrappedArray;
	areturn
  Labels:
  LocalVariableTable: 
   Start  Length  Slot  Name   Signature
   0      9      0    this       Lscala/collection/mutable/ArrayOps$ofChar;
   0      9      1    repr       Ljava/lang/Object;


public scala.collection.IndexedSeq toCollection(java.lang.Object);
  Signature: (Ljava/lang/Object;)Lscala/collection/IndexedSeq;
  Code:
   Stack=2, Locals=2, Args_size=2
	aload_0
	aload_1
	checkcast	class "[C"
	invokevirtual	Method toCollection:([C)Lscala/collection/mutable/WrappedArray;
	areturn
  Labels:
  LocalVariableTable: 
   Start  Length  Slot  Name   Signature
   0      9      0    this       Lscala/collection/mutable/ArrayOps$ofChar;
   0      9      1    repr       Ljava/lang/Object;


public scala.collection.Seq toCollection(java.lang.Object);
  Signature: (Ljava/lang/Object;)Lscala/collection/Seq;
  Code:
   Stack=2, Locals=2, Args_size=2
	aload_0
	aload_1
	checkcast	class "[C"
	invokevirtual	Method toCollection:([C)Lscala/collection/mutable/WrappedArray;
	areturn
  Labels:
  LocalVariableTable: 
   Start  Length  Slot  Name   Signature
   0      9      0    this       Lscala/collection/mutable/ArrayOps$ofChar;
   0      9      1    repr       Ljava/lang/Object;


public scala.collection.Iterable toCollection(java.lang.Object);
  Signature: (Ljava/lang/Object;)Lscala/collection/Iterable;
  Code:
   Stack=2, Locals=2, Args_size=2
	aload_0
	aload_1
	checkcast	class "[C"
	invokevirtual	Method toCollection:([C)Lscala/collection/mutable/WrappedArray;
	areturn
  Labels:
  LocalVariableTable: 
   Start  Length  Slot  Name   Signature
   0      9      0    this       Lscala/collection/mutable/ArrayOps$ofChar;
   0      9      1    repr       Ljava/lang/Object;


public scala.collection.Traversable toCollection(java.lang.Object);
  Signature: (Ljava/lang/Object;)Lscala/collection/Traversable;
  Code:
   Stack=2, Locals=2, Args_size=2
	aload_0
	aload_1
	checkcast	class "[C"
	invokevirtual	Method toCollection:([C)Lscala/collection/mutable/WrappedArray;
	areturn
  Labels:
  LocalVariableTable: 
   Start  Length  Slot  Name   Signature
   0      9      0    this       Lscala/collection/mutable/ArrayOps$ofChar;
   0      9      1    repr       Ljava/lang/Object;


public scala.collection.mutable.Builder newBuilder();
  Signature: ()Lscala/collection/mutable/Builder;
  Code:
   Stack=1, Locals=1, Args_size=1
	aload_0
	invokevirtual	Method newBuilder:()Lscala/collection/mutable/ArrayBuilder$ofChar;
	areturn
  Labels:

public java.lang.Object apply(int);
  Signature: (I)Ljava/lang/Object;
  Code:
   Stack=2, Locals=3, Args_size=2
	aload_0
	iload_1
	invokevirtual	Method apply:(I)C
	istore_2
	iload_2
	invokestatic	Method scala/runtime/BoxesRunTime.boxToCharacter:(C)Ljava/lang/Character;
	areturn
  Labels:
  LocalVariableTable: 
   Start  Length  Slot  Name   Signature
   0      11      0    this       Lscala/collection/mutable/ArrayOps$ofChar;
   0      11      1    idx       I


public void update(int, java.lang.Object);
  Signature: (ILjava/lang/Object;)V
  Code:
   Stack=3, Locals=3, Args_size=3
	aload_0
	iload_1
	aload_2
	invokestatic	Method scala/runtime/BoxesRunTime.unboxToChar:(Ljava/lang/Object;)C
	invokevirtual	Method update:(IC)V
	return
  Labels:
  LocalVariableTable: 
   Start  Length  Slot  Name   Signature
   0      10      0    this       Lscala/collection/mutable/ArrayOps$ofChar;
   0      10      1    idx       I
   0      10      2    elem       Ljava/lang/Object;


public void update(int, char);
  Signature: (IC)V
  Code:
   Stack=3, Locals=3, Args_size=3
	aload_0
	invokevirtual	Method repr:()[C
	iload_1
	iload_2
	castore
	return
  Labels:
  LocalVariableTable: 
   Start  Length  Slot  Name   Signature
   0      8      0    this       Lscala/collection/mutable/ArrayOps$ofChar;
   0      8      1    index       I
   0      8      2    elem       C


public char apply(int);
  Signature: (I)C
  Code:
   Stack=2, Locals=2, Args_size=2
	aload_0
	invokevirtual	Method repr:()[C
	iload_1
	caload
	ireturn
  Labels:
  LocalVariableTable: 
   Start  Length  Slot  Name   Signature
   0      7      0    this       Lscala/collection/mutable/ArrayOps$ofChar;
   0      7      1    index       I


public int length();
  Signature: ()I
  Code:
   Stack=1, Locals=1, Args_size=1
	aload_0
	invokevirtual	Method repr:()[C
	arraylength
	ireturn
  Labels:

public scala.collection.mutable.ArrayBuilder$ofChar newBuilder();
  Signature: ()Lscala/collection/mutable/ArrayBuilder$ofChar;
  Code:
   Stack=2, Locals=1, Args_size=1
	new	class scala/collection/mutable/ArrayBuilder$ofChar
	dup
	invokespecial	Method scala/collection/mutable/ArrayBuilder$ofChar."<init>":()V
	areturn
  Labels:

public scala.collection.mutable.WrappedArray toCollection(char[]);
  Signature: ([C)Lscala/collection/mutable/WrappedArray;
  Code:
   Stack=3, Locals=2, Args_size=2
	new	class scala/collection/mutable/WrappedArray$ofChar
	dup
	aload_1
	invokespecial	Method scala/collection/mutable/WrappedArray$ofChar."<init>":([C)V
	areturn
  Labels:
  LocalVariableTable: 
   Start  Length  Slot  Name   Signature
   0      9      0    this       Lscala/collection/mutable/ArrayOps$ofChar;
   0      9      1    repr       [C

  Signature: length = 0x2
   00 54 

public scala.collection.mutable.WrappedArray thisCollection();
  Signature: ()Lscala/collection/mutable/WrappedArray;
  Code:
   Stack=3, Locals=1, Args_size=1
	new	class scala/collection/mutable/WrappedArray$ofChar
	dup
	aload_0
	invokevirtual	Method repr:()[C
	invokespecial	Method scala/collection/mutable/WrappedArray$ofChar."<init>":([C)V
	areturn
  Labels:
  Signature: length = 0x2
   00 56 

public char[] repr();
  Signature: ()[C
  Code:
   Stack=1, Locals=1, Args_size=1
	aload_0
	getfield	Field repr:[C
	areturn
  Labels:

}

