Compiled from "ArrayOps.scala"
public class scala.collection.mutable.ArrayOps$ofInt extends scala.collection.mutable.ArrayOps implements scala.collection.mutable.ArrayLike,scala.ScalaObject
  SourceFile: "ArrayOps.scala"
  Scala: length = 0x
   
  Signature: length = 0x2
   00 57 
  InnerClass: 
   public ofInt=class scala/collection/mutable/ArrayOps$ofInt of class scala/collection/mutable/ArrayOps
   public ofInt=class scala/collection/mutable/ArrayBuilder$ofInt of class scala/collection/mutable/ArrayBuilder
   public final ofInt=class scala/collection/mutable/WrappedArray$ofInt of class scala/collection/mutable/WrappedArray
  minor version: 0
  major version: 49
  Constant pool:
Asciz	SourceFile;
Asciz	ArrayOps.scala;
Asciz	repr;
Asciz	[I;
Asciz	()[I;
Asciz	Code;
Asciz	LineNumberTable;
Asciz	scala/collection/mutable/ArrayOps$ofInt;
class	scala/collection/mutable/ArrayOps$ofInt
NameAndType	repr:[I
Field	scala/collection/mutable/ArrayOps$ofInt.repr:[I
Asciz	thisCollection;
Asciz	()Lscala/collection/mutable/WrappedArray;;
Asciz	scala/collection/mutable/WrappedArray$ofInt;
class	scala/collection/mutable/WrappedArray$ofInt
NameAndType	repr:()[I
Method	scala/collection/mutable/ArrayOps$ofInt.repr:()[I
Asciz	<init>;
Asciz	([I)V;
NameAndType	"<init>":([I)V
Method	scala/collection/mutable/WrappedArray$ofInt."<init>":([I)V
Asciz	()Lscala/collection/mutable/WrappedArray<Ljava/lang/Integer;>;;
Asciz	Signature;
Asciz	toCollection;
Asciz	([I)Lscala/collection/mutable/WrappedArray;;
Asciz	this;
Asciz	Lscala/collection/mutable/ArrayOps$ofInt;;
Asciz	LocalVariableTable;
Asciz	([I)Lscala/collection/mutable/WrappedArray<Ljava/lang/Integer;>;;
Asciz	newBuilder;
Asciz	()Lscala/collection/mutable/ArrayBuilder$ofInt;;
Asciz	scala/collection/mutable/ArrayBuilder$ofInt;
class	scala/collection/mutable/ArrayBuilder$ofInt
Asciz	()V;
NameAndType	"<init>":()V
Method	scala/collection/mutable/ArrayBuilder$ofInt."<init>":()V
Asciz	length;
Asciz	()I;
Asciz	apply;
Asciz	(I)I;
Asciz	index;
Asciz	I;
Asciz	update;
Asciz	(II)V;
Asciz	elem;
Asciz	(ILjava/lang/Object;)V;
Asciz	scala/runtime/BoxesRunTime;
class	scala/runtime/BoxesRunTime
Asciz	unboxToInt;
Asciz	(Ljava/lang/Object;)I;
NameAndType	unboxToInt:(Ljava/lang/Object;)I
Method	scala/runtime/BoxesRunTime.unboxToInt:(Ljava/lang/Object;)I
NameAndType	update:(II)V
Method	scala/collection/mutable/ArrayOps$ofInt.update:(II)V
Asciz	idx;
Asciz	Ljava/lang/Object;;
Asciz	(I)Ljava/lang/Object;;
NameAndType	apply:(I)I
Method	scala/collection/mutable/ArrayOps$ofInt.apply:(I)I
Asciz	boxToInteger;
Asciz	(I)Ljava/lang/Integer;;
NameAndType	boxToInteger:(I)Ljava/lang/Integer;
Method	scala/runtime/BoxesRunTime.boxToInteger:(I)Ljava/lang/Integer;
Asciz	()Lscala/collection/mutable/Builder;;
NameAndType	newBuilder:()Lscala/collection/mutable/ArrayBuilder$ofInt;
Method	scala/collection/mutable/ArrayOps$ofInt.newBuilder:()Lscala/collection/mutable/ArrayBuilder$ofInt;
Asciz	(Ljava/lang/Object;)Lscala/collection/Traversable;;
class	"[I"
NameAndType	toCollection:([I)Lscala/collection/mutable/WrappedArray;
Method	scala/collection/mutable/ArrayOps$ofInt.toCollection:([I)Lscala/collection/mutable/WrappedArray;
Asciz	(Ljava/lang/Object;)Lscala/collection/Iterable;;
Asciz	(Ljava/lang/Object;)Lscala/collection/Seq;;
Asciz	(Ljava/lang/Object;)Lscala/collection/IndexedSeq;;
Asciz	(Ljava/lang/Object;)Lscala/collection/mutable/IndexedSeq;;
Asciz	()Lscala/collection/Traversable;;
NameAndType	thisCollection:()Lscala/collection/mutable/WrappedArray;
Method	scala/collection/mutable/ArrayOps$ofInt.thisCollection:()Lscala/collection/mutable/WrappedArray;
Asciz	()Lscala/collection/Iterable;;
Asciz	()Lscala/collection/Seq;;
Asciz	()Lscala/collection/IndexedSeq;;
Asciz	()Lscala/collection/mutable/IndexedSeq;;
Asciz	()Ljava/lang/Object;;
Asciz	scala/collection/mutable/ArrayOps;
class	scala/collection/mutable/ArrayOps
Method	scala/collection/mutable/ArrayOps."<init>":()V
Asciz	Scala;
Asciz	Lscala/collection/mutable/ArrayOps<Ljava/lang/Integer;>;Lscala/collection/mutable/ArrayLike<Ljava/lang/Integer;[I>;Lscala/ScalaObject;;
Asciz	InnerClasses;
Asciz	ofInt;
Asciz	scala/collection/mutable/ArrayBuilder;
class	scala/collection/mutable/ArrayBuilder
Asciz	scala/collection/mutable/WrappedArray;
class	scala/collection/mutable/WrappedArray
Asciz	scala/collection/mutable/ArrayLike;
class	scala/collection/mutable/ArrayLike
Asciz	scala/ScalaObject;
class	scala/ScalaObject

{
private final int[] repr;
  Signature: [I

public int[] repr();
  Signature: ()[I
  Code:
   Stack=1, Locals=1, Args_size=1
	aload_0
	getfield	Field repr:[I
	areturn
  Labels:

public scala.collection.mutable.WrappedArray thisCollection();
  Signature: ()Lscala/collection/mutable/WrappedArray;
  Code:
   Stack=3, Locals=1, Args_size=1
	new	class scala/collection/mutable/WrappedArray$ofInt
	dup
	aload_0
	invokevirtual	Method repr:()[I
	invokespecial	Method scala/collection/mutable/WrappedArray$ofInt."<init>":([I)V
	areturn
  Labels:
  Signature: length = 0x2
   00 16 

public scala.collection.mutable.WrappedArray toCollection(int[]);
  Signature: ([I)Lscala/collection/mutable/WrappedArray;
  Code:
   Stack=3, Locals=2, Args_size=2
	new	class scala/collection/mutable/WrappedArray$ofInt
	dup
	aload_1
	invokespecial	Method scala/collection/mutable/WrappedArray$ofInt."<init>":([I)V
	areturn
  Labels:
  LocalVariableTable: 
   Start  Length  Slot  Name   Signature
   0      9      0    this       Lscala/collection/mutable/ArrayOps$ofInt;
   0      9      1    repr       [I

  Signature: length = 0x2
   00 1D 

public scala.collection.mutable.ArrayBuilder$ofInt newBuilder();
  Signature: ()Lscala/collection/mutable/ArrayBuilder$ofInt;
  Code:
   Stack=2, Locals=1, Args_size=1
	new	class scala/collection/mutable/ArrayBuilder$ofInt
	dup
	invokespecial	Method scala/collection/mutable/ArrayBuilder$ofInt."<init>":()V
	areturn
  Labels:

public int length();
  Signature: ()I
  Code:
   Stack=1, Locals=1, Args_size=1
	aload_0
	invokevirtual	Method repr:()[I
	arraylength
	ireturn
  Labels:

public int apply(int);
  Signature: (I)I
  Code:
   Stack=2, Locals=2, Args_size=2
	aload_0
	invokevirtual	Method repr:()[I
	iload_1
	iaload
	ireturn
  Labels:
  LocalVariableTable: 
   Start  Length  Slot  Name   Signature
   0      7      0    this       Lscala/collection/mutable/ArrayOps$ofInt;
   0      7      1    index       I


public void update(int, int);
  Signature: (II)V
  Code:
   Stack=3, Locals=3, Args_size=3
	aload_0
	invokevirtual	Method repr:()[I
	iload_1
	iload_2
	iastore
	return
  Labels:
  LocalVariableTable: 
   Start  Length  Slot  Name   Signature
   0      8      0    this       Lscala/collection/mutable/ArrayOps$ofInt;
   0      8      1    index       I
   0      8      2    elem       I


public void update(int, java.lang.Object);
  Signature: (ILjava/lang/Object;)V
  Code:
   Stack=3, Locals=3, Args_size=3
	aload_0
	iload_1
	aload_2
	invokestatic	Method scala/runtime/BoxesRunTime.unboxToInt:(Ljava/lang/Object;)I
	invokevirtual	Method update:(II)V
	return
  Labels:
  LocalVariableTable: 
   Start  Length  Slot  Name   Signature
   0      10      0    this       Lscala/collection/mutable/ArrayOps$ofInt;
   0      10      1    idx       I
   0      10      2    elem       Ljava/lang/Object;


public java.lang.Object apply(int);
  Signature: (I)Ljava/lang/Object;
  Code:
   Stack=2, Locals=3, Args_size=2
	aload_0
	iload_1
	invokevirtual	Method apply:(I)I
	istore_2
	iload_2
	invokestatic	Method scala/runtime/BoxesRunTime.boxToInteger:(I)Ljava/lang/Integer;
	areturn
  Labels:
  LocalVariableTable: 
   Start  Length  Slot  Name   Signature
   0      11      0    this       Lscala/collection/mutable/ArrayOps$ofInt;
   0      11      1    idx       I


public scala.collection.mutable.Builder newBuilder();
  Signature: ()Lscala/collection/mutable/Builder;
  Code:
   Stack=1, Locals=1, Args_size=1
	aload_0
	invokevirtual	Method newBuilder:()Lscala/collection/mutable/ArrayBuilder$ofInt;
	areturn
  Labels:

public scala.collection.Traversable toCollection(java.lang.Object);
  Signature: (Ljava/lang/Object;)Lscala/collection/Traversable;
  Code:
   Stack=2, Locals=2, Args_size=2
	aload_0
	aload_1
	checkcast	class "[I"
	invokevirtual	Method toCollection:([I)Lscala/collection/mutable/WrappedArray;
	areturn
  Labels:
  LocalVariableTable: 
   Start  Length  Slot  Name   Signature
   0      9      0    this       Lscala/collection/mutable/ArrayOps$ofInt;
   0      9      1    repr       Ljava/lang/Object;


public scala.collection.Iterable toCollection(java.lang.Object);
  Signature: (Ljava/lang/Object;)Lscala/collection/Iterable;
  Code:
   Stack=2, Locals=2, Args_size=2
	aload_0
	aload_1
	checkcast	class "[I"
	invokevirtual	Method toCollection:([I)Lscala/collection/mutable/WrappedArray;
	areturn
  Labels:
  LocalVariableTable: 
   Start  Length  Slot  Name   Signature
   0      9      0    this       Lscala/collection/mutable/ArrayOps$ofInt;
   0      9      1    repr       Ljava/lang/Object;


public scala.collection.Seq toCollection(java.lang.Object);
  Signature: (Ljava/lang/Object;)Lscala/collection/Seq;
  Code:
   Stack=2, Locals=2, Args_size=2
	aload_0
	aload_1
	checkcast	class "[I"
	invokevirtual	Method toCollection:([I)Lscala/collection/mutable/WrappedArray;
	areturn
  Labels:
  LocalVariableTable: 
   Start  Length  Slot  Name   Signature
   0      9      0    this       Lscala/collection/mutable/ArrayOps$ofInt;
   0      9      1    repr       Ljava/lang/Object;


public scala.collection.IndexedSeq toCollection(java.lang.Object);
  Signature: (Ljava/lang/Object;)Lscala/collection/IndexedSeq;
  Code:
   Stack=2, Locals=2, Args_size=2
	aload_0
	aload_1
	checkcast	class "[I"
	invokevirtual	Method toCollection:([I)Lscala/collection/mutable/WrappedArray;
	areturn
  Labels:
  LocalVariableTable: 
   Start  Length  Slot  Name   Signature
   0      9      0    this       Lscala/collection/mutable/ArrayOps$ofInt;
   0      9      1    repr       Ljava/lang/Object;


public scala.collection.mutable.IndexedSeq toCollection(java.lang.Object);
  Signature: (Ljava/lang/Object;)Lscala/collection/mutable/IndexedSeq;
  Code:
   Stack=2, Locals=2, Args_size=2
	aload_0
	aload_1
	checkcast	class "[I"
	invokevirtual	Method toCollection:([I)Lscala/collection/mutable/WrappedArray;
	areturn
  Labels:
  LocalVariableTable: 
   Start  Length  Slot  Name   Signature
   0      9      0    this       Lscala/collection/mutable/ArrayOps$ofInt;
   0      9      1    repr       Ljava/lang/Object;


public scala.collection.Traversable thisCollection();
  Signature: ()Lscala/collection/Traversable;
  Code:
   Stack=1, Locals=1, Args_size=1
	aload_0
	invokevirtual	Method thisCollection:()Lscala/collection/mutable/WrappedArray;
	areturn
  Labels:

public scala.collection.Iterable thisCollection();
  Signature: ()Lscala/collection/Iterable;
  Code:
   Stack=1, Locals=1, Args_size=1
	aload_0
	invokevirtual	Method thisCollection:()Lscala/collection/mutable/WrappedArray;
	areturn
  Labels:

public scala.collection.Seq thisCollection();
  Signature: ()Lscala/collection/Seq;
  Code:
   Stack=1, Locals=1, Args_size=1
	aload_0
	invokevirtual	Method thisCollection:()Lscala/collection/mutable/WrappedArray;
	areturn
  Labels:

public scala.collection.IndexedSeq thisCollection();
  Signature: ()Lscala/collection/IndexedSeq;
  Code:
   Stack=1, Locals=1, Args_size=1
	aload_0
	invokevirtual	Method thisCollection:()Lscala/collection/mutable/WrappedArray;
	areturn
  Labels:

public scala.collection.mutable.IndexedSeq thisCollection();
  Signature: ()Lscala/collection/mutable/IndexedSeq;
  Code:
   Stack=1, Locals=1, Args_size=1
	aload_0
	invokevirtual	Method thisCollection:()Lscala/collection/mutable/WrappedArray;
	areturn
  Labels:

public java.lang.Object repr();
  Signature: ()Ljava/lang/Object;
  Code:
   Stack=1, Locals=1, Args_size=1
	aload_0
	invokevirtual	Method repr:()[I
	areturn
  Labels:

public scala.collection.mutable.ArrayOps$ofInt(int[]);
  Signature: ([I)V
  Code:
   Stack=2, Locals=2, Args_size=2
	aload_0
	aload_1
	putfield	Field repr:[I
	aload_0
	invokespecial	Method scala/collection/mutable/ArrayOps."<init>":()V
	return
  Labels:
  LocalVariableTable: 
   Start  Length  Slot  Name   Signature
   0      10      0    this       Lscala/collection/mutable/ArrayOps$ofInt;
   0      10      1    repr       [I


}

