Compiled from "ArrayOps.scala"
public final class scala.collection.mutable.ArrayOps$ extends java.lang.Object implements scala.ScalaObject
  SourceFile: "ArrayOps.scala"
  Scala: length = 0x
   
  InnerClass: 
   public #25= #22 of #24; //ofInt=class scala/collection/mutable/ArrayOps$ofInt of class scala/collection/mutable/ArrayOps
   public #28= #27 of #24; //ofRef=class scala/collection/mutable/ArrayOps$ofRef of class scala/collection/mutable/ArrayOps
   public #31= #30 of #24; //ofUnit=class scala/collection/mutable/ArrayOps$ofUnit of class scala/collection/mutable/ArrayOps
   public #34= #33 of #24; //ofLong=class scala/collection/mutable/ArrayOps$ofLong of class scala/collection/mutable/ArrayOps
   public #37= #36 of #24; //ofChar=class scala/collection/mutable/ArrayOps$ofChar of class scala/collection/mutable/ArrayOps
   public #40= #39 of #24; //ofByte=class scala/collection/mutable/ArrayOps$ofByte of class scala/collection/mutable/ArrayOps
   public #43= #42 of #24; //ofFloat=class scala/collection/mutable/ArrayOps$ofFloat of class scala/collection/mutable/ArrayOps
   public #46= #45 of #24; //ofShort=class scala/collection/mutable/ArrayOps$ofShort of class scala/collection/mutable/ArrayOps
   public #49= #48 of #24; //ofDouble=class scala/collection/mutable/ArrayOps$ofDouble of class scala/collection/mutable/ArrayOps
   public #52= #51 of #24; //ofBoolean=class scala/collection/mutable/ArrayOps$ofBoolean of class scala/collection/mutable/ArrayOps
   public final #55= #54 of #24; //$anonfun$1=class scala/collection/mutable/ArrayOps$$anonfun$1 of class scala/collection/mutable/ArrayOps
   public final #58= #57 of #24; //$anonfun$flatten$1=class scala/collection/mutable/ArrayOps$$anonfun$flatten$1 of class scala/collection/mutable/ArrayOps
   public final #61= #60 of #24; //$anonfun$transpose$2=class scala/collection/mutable/ArrayOps$$anonfun$transpose$2 of class scala/collection/mutable/ArrayOps
   public final #64= #63 of #24; //$anonfun$transpose$1=class scala/collection/mutable/ArrayOps$$anonfun$transpose$1 of class scala/collection/mutable/ArrayOps
  minor version: 0
  major version: 49
  Constant pool:
const #1 = Asciz	SourceFile;
const #2 = Asciz	ArrayOps.scala;
const #3 = Asciz	Scala;
const #4 = Asciz	MODULE$;
const #5 = Asciz	Lscala/collection/mutable/ArrayOps$;;
const #6 = Asciz	<clinit>;
const #7 = Asciz	()V;
const #8 = Asciz	Code;
const #9 = Asciz	scala/collection/mutable/ArrayOps$;
const #10 = class	#9;	//  scala/collection/mutable/ArrayOps$
const #11 = Asciz	<init>;
const #12 = NameAndType	#11:#7;//  "<init>":()V
const #13 = Method	#10.#12;	//  scala/collection/mutable/ArrayOps$."<init>":()V
const #14 = Asciz	LineNumberTable;
const #15 = Asciz	java/lang/Object;
const #16 = class	#15;	//  java/lang/Object
const #17 = Method	#16.#12;	//  java/lang/Object."<init>":()V
const #18 = NameAndType	#4:#5;//  MODULE$:Lscala/collection/mutable/ArrayOps$;
const #19 = Field	#10.#18;	//  scala/collection/mutable/ArrayOps$.MODULE$:Lscala/collection/mutable/ArrayOps$;
const #20 = Asciz	InnerClasses;
const #21 = Asciz	scala/collection/mutable/ArrayOps$ofInt;
const #22 = class	#21;	//  scala/collection/mutable/ArrayOps$ofInt
const #23 = Asciz	scala/collection/mutable/ArrayOps;
const #24 = class	#23;	//  scala/collection/mutable/ArrayOps
const #25 = Asciz	ofInt;
const #26 = Asciz	scala/collection/mutable/ArrayOps$ofRef;
const #27 = class	#26;	//  scala/collection/mutable/ArrayOps$ofRef
const #28 = Asciz	ofRef;
const #29 = Asciz	scala/collection/mutable/ArrayOps$ofUnit;
const #30 = class	#29;	//  scala/collection/mutable/ArrayOps$ofUnit
const #31 = Asciz	ofUnit;
const #32 = Asciz	scala/collection/mutable/ArrayOps$ofLong;
const #33 = class	#32;	//  scala/collection/mutable/ArrayOps$ofLong
const #34 = Asciz	ofLong;
const #35 = Asciz	scala/collection/mutable/ArrayOps$ofChar;
const #36 = class	#35;	//  scala/collection/mutable/ArrayOps$ofChar
const #37 = Asciz	ofChar;
const #38 = Asciz	scala/collection/mutable/ArrayOps$ofByte;
const #39 = class	#38;	//  scala/collection/mutable/ArrayOps$ofByte
const #40 = Asciz	ofByte;
const #41 = Asciz	scala/collection/mutable/ArrayOps$ofFloat;
const #42 = class	#41;	//  scala/collection/mutable/ArrayOps$ofFloat
const #43 = Asciz	ofFloat;
const #44 = Asciz	scala/collection/mutable/ArrayOps$ofShort;
const #45 = class	#44;	//  scala/collection/mutable/ArrayOps$ofShort
const #46 = Asciz	ofShort;
const #47 = Asciz	scala/collection/mutable/ArrayOps$ofDouble;
const #48 = class	#47;	//  scala/collection/mutable/ArrayOps$ofDouble
const #49 = Asciz	ofDouble;
const #50 = Asciz	scala/collection/mutable/ArrayOps$ofBoolean;
const #51 = class	#50;	//  scala/collection/mutable/ArrayOps$ofBoolean
const #52 = Asciz	ofBoolean;
const #53 = Asciz	scala/collection/mutable/ArrayOps$$anonfun$1;
const #54 = class	#53;	//  scala/collection/mutable/ArrayOps$$anonfun$1
const #55 = Asciz	$anonfun$1;
const #56 = Asciz	scala/collection/mutable/ArrayOps$$anonfun$flatten$1;
const #57 = class	#56;	//  scala/collection/mutable/ArrayOps$$anonfun$flatten$1
const #58 = Asciz	$anonfun$flatten$1;
const #59 = Asciz	scala/collection/mutable/ArrayOps$$anonfun$transpose$2;
const #60 = class	#59;	//  scala/collection/mutable/ArrayOps$$anonfun$transpose$2
const #61 = Asciz	$anonfun$transpose$2;
const #62 = Asciz	scala/collection/mutable/ArrayOps$$anonfun$transpose$1;
const #63 = class	#62;	//  scala/collection/mutable/ArrayOps$$anonfun$transpose$1
const #64 = Asciz	$anonfun$transpose$1;
const #65 = Asciz	scala/ScalaObject;
const #66 = class	#65;	//  scala/ScalaObject

{
public static final scala.collection.mutable.ArrayOps$ MODULE$;

public static {};
  Code:
   Stack=1, Locals=0, Args_size=0
   0:	new	#10; //class scala/collection/mutable/ArrayOps$
   3:	invokespecial	#13; //Method "<init>":()V
   6:	return

}

