Compiled from "ArrayOps.scala"
public class scala.collection.mutable.ArrayOps$ofShort extends scala.collection.mutable.ArrayOps implements scala.collection.mutable.ArrayLike,scala.ScalaObject
  SourceFile: "ArrayOps.scala"
  Signature: length = 0x2
   00 57 
  Scala: length = 0x
   
  InnerClass: 
   public ofShort=class scala/collection/mutable/ArrayOps$ofShort of class scala/collection/mutable/ArrayOps
   public ofShort=class scala/collection/mutable/ArrayBuilder$ofShort of class scala/collection/mutable/ArrayBuilder
   public final ofShort=class scala/collection/mutable/WrappedArray$ofShort of class scala/collection/mutable/WrappedArray
  minor version: 0
  major version: 49
  Constant pool:
Asciz	SourceFile;
Asciz	ArrayOps.scala;
Asciz	repr;
Asciz	[S;
Asciz	()[S;
Asciz	Code;
Asciz	LineNumberTable;
Asciz	scala/collection/mutable/ArrayOps$ofShort;
class	scala/collection/mutable/ArrayOps$ofShort
NameAndType	repr:[S
Field	scala/collection/mutable/ArrayOps$ofShort.repr:[S
Asciz	thisCollection;
Asciz	()Lscala/collection/mutable/WrappedArray;;
Asciz	scala/collection/mutable/WrappedArray$ofShort;
class	scala/collection/mutable/WrappedArray$ofShort
NameAndType	repr:()[S
Method	scala/collection/mutable/ArrayOps$ofShort.repr:()[S
Asciz	<init>;
Asciz	([S)V;
NameAndType	"<init>":([S)V
Method	scala/collection/mutable/WrappedArray$ofShort."<init>":([S)V
Asciz	()Lscala/collection/mutable/WrappedArray<Ljava/lang/Short;>;;
Asciz	Signature;
Asciz	toCollection;
Asciz	([S)Lscala/collection/mutable/WrappedArray;;
Asciz	this;
Asciz	Lscala/collection/mutable/ArrayOps$ofShort;;
Asciz	LocalVariableTable;
Asciz	([S)Lscala/collection/mutable/WrappedArray<Ljava/lang/Short;>;;
Asciz	newBuilder;
Asciz	()Lscala/collection/mutable/ArrayBuilder$ofShort;;
Asciz	scala/collection/mutable/ArrayBuilder$ofShort;
class	scala/collection/mutable/ArrayBuilder$ofShort
Asciz	()V;
NameAndType	"<init>":()V
Method	scala/collection/mutable/ArrayBuilder$ofShort."<init>":()V
Asciz	length;
Asciz	()I;
Asciz	apply;
Asciz	(I)S;
Asciz	index;
Asciz	I;
Asciz	update;
Asciz	(IS)V;
Asciz	elem;
Asciz	S;
Asciz	(ILjava/lang/Object;)V;
Asciz	scala/runtime/BoxesRunTime;
class	scala/runtime/BoxesRunTime
Asciz	unboxToShort;
Asciz	(Ljava/lang/Object;)S;
NameAndType	unboxToShort:(Ljava/lang/Object;)S
Method	scala/runtime/BoxesRunTime.unboxToShort:(Ljava/lang/Object;)S
NameAndType	update:(IS)V
Method	scala/collection/mutable/ArrayOps$ofShort.update:(IS)V
Asciz	idx;
Asciz	Ljava/lang/Object;;
Asciz	(I)Ljava/lang/Object;;
NameAndType	apply:(I)S
Method	scala/collection/mutable/ArrayOps$ofShort.apply:(I)S
Asciz	boxToShort;
Asciz	(S)Ljava/lang/Short;;
NameAndType	boxToShort:(S)Ljava/lang/Short;
Method	scala/runtime/BoxesRunTime.boxToShort:(S)Ljava/lang/Short;
Asciz	()Lscala/collection/mutable/Builder;;
NameAndType	newBuilder:()Lscala/collection/mutable/ArrayBuilder$ofShort;
Method	scala/collection/mutable/ArrayOps$ofShort.newBuilder:()Lscala/collection/mutable/ArrayBuilder$ofShort;
Asciz	(Ljava/lang/Object;)Lscala/collection/Traversable;;
class	"[S"
NameAndType	toCollection:([S)Lscala/collection/mutable/WrappedArray;
Method	scala/collection/mutable/ArrayOps$ofShort.toCollection:([S)Lscala/collection/mutable/WrappedArray;
Asciz	(Ljava/lang/Object;)Lscala/collection/Iterable;;
Asciz	(Ljava/lang/Object;)Lscala/collection/Seq;;
Asciz	(Ljava/lang/Object;)Lscala/collection/IndexedSeq;;
Asciz	(Ljava/lang/Object;)Lscala/collection/mutable/IndexedSeq;;
Asciz	()Lscala/collection/Traversable;;
NameAndType	thisCollection:()Lscala/collection/mutable/WrappedArray;
Method	scala/collection/mutable/ArrayOps$ofShort.thisCollection:()Lscala/collection/mutable/WrappedArray;
Asciz	()Lscala/collection/Iterable;;
Asciz	()Lscala/collection/Seq;;
Asciz	()Lscala/collection/IndexedSeq;;
Asciz	()Lscala/collection/mutable/IndexedSeq;;
Asciz	()Ljava/lang/Object;;
Asciz	scala/collection/mutable/ArrayOps;
class	scala/collection/mutable/ArrayOps
Method	scala/collection/mutable/ArrayOps."<init>":()V
Asciz	Lscala/collection/mutable/ArrayOps<Ljava/lang/Short;>;Lscala/collection/mutable/ArrayLike<Ljava/lang/Short;[S>;Lscala/ScalaObject;;
Asciz	Scala;
Asciz	InnerClasses;
Asciz	ofShort;
Asciz	scala/collection/mutable/ArrayBuilder;
class	scala/collection/mutable/ArrayBuilder
Asciz	scala/collection/mutable/WrappedArray;
class	scala/collection/mutable/WrappedArray
Asciz	scala/collection/mutable/ArrayLike;
class	scala/collection/mutable/ArrayLike
Asciz	scala/ScalaObject;
class	scala/ScalaObject

{
private final short[] repr;
  Signature: [S

public short[] repr();
  Signature: ()[S
  Code:
   Stack=1, Locals=1, Args_size=1
	aload_0
	getfield	Field repr:[S
	areturn
  Labels:

public scala.collection.mutable.WrappedArray thisCollection();
  Signature: ()Lscala/collection/mutable/WrappedArray;
  Code:
   Stack=3, Locals=1, Args_size=1
	new	class scala/collection/mutable/WrappedArray$ofShort
	dup
	aload_0
	invokevirtual	Method repr:()[S
	invokespecial	Method scala/collection/mutable/WrappedArray$ofShort."<init>":([S)V
	areturn
  Labels:
  Signature: length = 0x2
   00 16 

public scala.collection.mutable.WrappedArray toCollection(short[]);
  Signature: ([S)Lscala/collection/mutable/WrappedArray;
  Code:
   Stack=3, Locals=2, Args_size=2
	new	class scala/collection/mutable/WrappedArray$ofShort
	dup
	aload_1
	invokespecial	Method scala/collection/mutable/WrappedArray$ofShort."<init>":([S)V
	areturn
  Labels:
  LocalVariableTable: 
   Start  Length  Slot  Name   Signature
   0      9      0    this       Lscala/collection/mutable/ArrayOps$ofShort;
   0      9      1    repr       [S

  Signature: length = 0x2
   00 1D 

public scala.collection.mutable.ArrayBuilder$ofShort newBuilder();
  Signature: ()Lscala/collection/mutable/ArrayBuilder$ofShort;
  Code:
   Stack=2, Locals=1, Args_size=1
	new	class scala/collection/mutable/ArrayBuilder$ofShort
	dup
	invokespecial	Method scala/collection/mutable/ArrayBuilder$ofShort."<init>":()V
	areturn
  Labels:

public int length();
  Signature: ()I
  Code:
   Stack=1, Locals=1, Args_size=1
	aload_0
	invokevirtual	Method repr:()[S
	arraylength
	ireturn
  Labels:

public short apply(int);
  Signature: (I)S
  Code:
   Stack=2, Locals=2, Args_size=2
	aload_0
	invokevirtual	Method repr:()[S
	iload_1
	saload
	ireturn
  Labels:
  LocalVariableTable: 
   Start  Length  Slot  Name   Signature
   0      7      0    this       Lscala/collection/mutable/ArrayOps$ofShort;
   0      7      1    index       I


public void update(int, short);
  Signature: (IS)V
  Code:
   Stack=3, Locals=3, Args_size=3
	aload_0
	invokevirtual	Method repr:()[S
	iload_1
	iload_2
	sastore
	return
  Labels:
  LocalVariableTable: 
   Start  Length  Slot  Name   Signature
   0      8      0    this       Lscala/collection/mutable/ArrayOps$ofShort;
   0      8      1    index       I
   0      8      2    elem       S


public void update(int, java.lang.Object);
  Signature: (ILjava/lang/Object;)V
  Code:
   Stack=3, Locals=3, Args_size=3
	aload_0
	iload_1
	aload_2
	invokestatic	Method scala/runtime/BoxesRunTime.unboxToShort:(Ljava/lang/Object;)S
	invokevirtual	Method update:(IS)V
	return
  Labels:
  LocalVariableTable: 
   Start  Length  Slot  Name   Signature
   0      10      0    this       Lscala/collection/mutable/ArrayOps$ofShort;
   0      10      1    idx       I
   0      10      2    elem       Ljava/lang/Object;


public java.lang.Object apply(int);
  Signature: (I)Ljava/lang/Object;
  Code:
   Stack=2, Locals=3, Args_size=2
	aload_0
	iload_1
	invokevirtual	Method apply:(I)S
	istore_2
	iload_2
	invokestatic	Method scala/runtime/BoxesRunTime.boxToShort:(S)Ljava/lang/Short;
	areturn
  Labels:
  LocalVariableTable: 
   Start  Length  Slot  Name   Signature
   0      11      0    this       Lscala/collection/mutable/ArrayOps$ofShort;
   0      11      1    idx       I


public scala.collection.mutable.Builder newBuilder();
  Signature: ()Lscala/collection/mutable/Builder;
  Code:
   Stack=1, Locals=1, Args_size=1
	aload_0
	invokevirtual	Method newBuilder:()Lscala/collection/mutable/ArrayBuilder$ofShort;
	areturn
  Labels:

public scala.collection.Traversable toCollection(java.lang.Object);
  Signature: (Ljava/lang/Object;)Lscala/collection/Traversable;
  Code:
   Stack=2, Locals=2, Args_size=2
	aload_0
	aload_1
	checkcast	class "[S"
	invokevirtual	Method toCollection:([S)Lscala/collection/mutable/WrappedArray;
	areturn
  Labels:
  LocalVariableTable: 
   Start  Length  Slot  Name   Signature
   0      9      0    this       Lscala/collection/mutable/ArrayOps$ofShort;
   0      9      1    repr       Ljava/lang/Object;


public scala.collection.Iterable toCollection(java.lang.Object);
  Signature: (Ljava/lang/Object;)Lscala/collection/Iterable;
  Code:
   Stack=2, Locals=2, Args_size=2
	aload_0
	aload_1
	checkcast	class "[S"
	invokevirtual	Method toCollection:([S)Lscala/collection/mutable/WrappedArray;
	areturn
  Labels:
  LocalVariableTable: 
   Start  Length  Slot  Name   Signature
   0      9      0    this       Lscala/collection/mutable/ArrayOps$ofShort;
   0      9      1    repr       Ljava/lang/Object;


public scala.collection.Seq toCollection(java.lang.Object);
  Signature: (Ljava/lang/Object;)Lscala/collection/Seq;
  Code:
   Stack=2, Locals=2, Args_size=2
	aload_0
	aload_1
	checkcast	class "[S"
	invokevirtual	Method toCollection:([S)Lscala/collection/mutable/WrappedArray;
	areturn
  Labels:
  LocalVariableTable: 
   Start  Length  Slot  Name   Signature
   0      9      0    this       Lscala/collection/mutable/ArrayOps$ofShort;
   0      9      1    repr       Ljava/lang/Object;


public scala.collection.IndexedSeq toCollection(java.lang.Object);
  Signature: (Ljava/lang/Object;)Lscala/collection/IndexedSeq;
  Code:
   Stack=2, Locals=2, Args_size=2
	aload_0
	aload_1
	checkcast	class "[S"
	invokevirtual	Method toCollection:([S)Lscala/collection/mutable/WrappedArray;
	areturn
  Labels:
  LocalVariableTable: 
   Start  Length  Slot  Name   Signature
   0      9      0    this       Lscala/collection/mutable/ArrayOps$ofShort;
   0      9      1    repr       Ljava/lang/Object;


public scala.collection.mutable.IndexedSeq toCollection(java.lang.Object);
  Signature: (Ljava/lang/Object;)Lscala/collection/mutable/IndexedSeq;
  Code:
   Stack=2, Locals=2, Args_size=2
	aload_0
	aload_1
	checkcast	class "[S"
	invokevirtual	Method toCollection:([S)Lscala/collection/mutable/WrappedArray;
	areturn
  Labels:
  LocalVariableTable: 
   Start  Length  Slot  Name   Signature
   0      9      0    this       Lscala/collection/mutable/ArrayOps$ofShort;
   0      9      1    repr       Ljava/lang/Object;


public scala.collection.Traversable thisCollection();
  Signature: ()Lscala/collection/Traversable;
  Code:
   Stack=1, Locals=1, Args_size=1
	aload_0
	invokevirtual	Method thisCollection:()Lscala/collection/mutable/WrappedArray;
	areturn
  Labels:

public scala.collection.Iterable thisCollection();
  Signature: ()Lscala/collection/Iterable;
  Code:
   Stack=1, Locals=1, Args_size=1
	aload_0
	invokevirtual	Method thisCollection:()Lscala/collection/mutable/WrappedArray;
	areturn
  Labels:

public scala.collection.Seq thisCollection();
  Signature: ()Lscala/collection/Seq;
  Code:
   Stack=1, Locals=1, Args_size=1
	aload_0
	invokevirtual	Method thisCollection:()Lscala/collection/mutable/WrappedArray;
	areturn
  Labels:

public scala.collection.IndexedSeq thisCollection();
  Signature: ()Lscala/collection/IndexedSeq;
  Code:
   Stack=1, Locals=1, Args_size=1
	aload_0
	invokevirtual	Method thisCollection:()Lscala/collection/mutable/WrappedArray;
	areturn
  Labels:

public scala.collection.mutable.IndexedSeq thisCollection();
  Signature: ()Lscala/collection/mutable/IndexedSeq;
  Code:
   Stack=1, Locals=1, Args_size=1
	aload_0
	invokevirtual	Method thisCollection:()Lscala/collection/mutable/WrappedArray;
	areturn
  Labels:

public java.lang.Object repr();
  Signature: ()Ljava/lang/Object;
  Code:
   Stack=1, Locals=1, Args_size=1
	aload_0
	invokevirtual	Method repr:()[S
	areturn
  Labels:

public scala.collection.mutable.ArrayOps$ofShort(short[]);
  Signature: ([S)V
  Code:
   Stack=2, Locals=2, Args_size=2
	aload_0
	aload_1
	putfield	Field repr:[S
	aload_0
	invokespecial	Method scala/collection/mutable/ArrayOps."<init>":()V
	return
  Labels:
  LocalVariableTable: 
   Start  Length  Slot  Name   Signature
   0      10      0    this       Lscala/collection/mutable/ArrayOps$ofShort;
   0      10      1    repr       [S


}

