Compiled from "ArrayOps.scala"
public class scala.collection.mutable.ArrayOps$ofRef extends scala.collection.mutable.ArrayOps implements scala.collection.mutable.ArrayLike,scala.ScalaObject
  SourceFile: "ArrayOps.scala"
  Signature: length = 0x2
   00 62 
  Scala: length = 0x
   
  InnerClass: 
   public ofRef=class scala/collection/mutable/ArrayOps$ofRef of class scala/collection/mutable/ArrayOps
   public final ofRef=class scala/collection/mutable/WrappedArray$ofRef of class scala/collection/mutable/WrappedArray
   public ofRef=class scala/collection/mutable/ArrayBuilder$ofRef of class scala/collection/mutable/ArrayBuilder
  minor version: 0
  major version: 49
  Constant pool:
Asciz	SourceFile;
Asciz	ArrayOps.scala;
Asciz	repr;
Asciz	[Ljava/lang/Object;;
Asciz	[TT;;
Asciz	Signature;
Asciz	<init>;
Asciz	([Ljava/lang/Object;)V;
Asciz	Code;
Asciz	LineNumberTable;
Asciz	scala/collection/mutable/ArrayOps$ofRef;
class	scala/collection/mutable/ArrayOps$ofRef
NameAndType	repr:[Ljava/lang/Object;
Field	scala/collection/mutable/ArrayOps$ofRef.repr:[Ljava/lang/Object;
Asciz	scala/collection/mutable/ArrayOps;
class	scala/collection/mutable/ArrayOps
Asciz	()V;
NameAndType	"<init>":()V
Method	scala/collection/mutable/ArrayOps."<init>":()V
Asciz	this;
Asciz	Lscala/collection/mutable/ArrayOps$ofRef;;
Asciz	LocalVariableTable;
Asciz	([TT;)V;
Asciz	()Ljava/lang/Object;;
Asciz	()[Ljava/lang/Object;;
NameAndType	repr:()[Ljava/lang/Object;
Method	scala/collection/mutable/ArrayOps$ofRef.repr:()[Ljava/lang/Object;
Asciz	thisCollection;
Asciz	()Lscala/collection/mutable/IndexedSeq;;
Asciz	()Lscala/collection/mutable/WrappedArray;;
NameAndType	thisCollection:()Lscala/collection/mutable/WrappedArray;
Method	scala/collection/mutable/ArrayOps$ofRef.thisCollection:()Lscala/collection/mutable/WrappedArray;
Asciz	()Lscala/collection/IndexedSeq;;
Asciz	()Lscala/collection/Seq;;
Asciz	()Lscala/collection/Iterable;;
Asciz	()Lscala/collection/Traversable;;
Asciz	toCollection;
Asciz	(Ljava/lang/Object;)Lscala/collection/mutable/IndexedSeq;;
class	"[Ljava/lang/Object;"
Asciz	([Ljava/lang/Object;)Lscala/collection/mutable/WrappedArray;;
NameAndType	toCollection:([Ljava/lang/Object;)Lscala/collection/mutable/WrappedArray;
Method	scala/collection/mutable/ArrayOps$ofRef.toCollection:([Ljava/lang/Object;)Lscala/collection/mutable/WrappedArray;
Asciz	Ljava/lang/Object;;
Asciz	(Ljava/lang/Object;)Lscala/collection/IndexedSeq;;
Asciz	(Ljava/lang/Object;)Lscala/collection/Seq;;
Asciz	(Ljava/lang/Object;)Lscala/collection/Iterable;;
Asciz	(Ljava/lang/Object;)Lscala/collection/Traversable;;
Asciz	newBuilder;
Asciz	()Lscala/collection/mutable/Builder;;
Asciz	()Lscala/collection/mutable/ArrayBuilder$ofRef;;
NameAndType	newBuilder:()Lscala/collection/mutable/ArrayBuilder$ofRef;
Method	scala/collection/mutable/ArrayOps$ofRef.newBuilder:()Lscala/collection/mutable/ArrayBuilder$ofRef;
Asciz	update;
Asciz	(ILjava/lang/Object;)V;
Asciz	index;
Asciz	I;
Asciz	elem;
Asciz	(ITT;)V;
Asciz	apply;
Asciz	(I)Ljava/lang/Object;;
Asciz	(I)TT;;
Asciz	length;
Asciz	()I;
Asciz	scala/collection/mutable/ArrayBuilder$ofRef;
class	scala/collection/mutable/ArrayBuilder$ofRef
Asciz	scala/reflect/ClassManifest$;
class	scala/reflect/ClassManifest$
Asciz	MODULE$;
Asciz	Lscala/reflect/ClassManifest$;;
NameAndType	MODULE$:Lscala/reflect/ClassManifest$;
Field	scala/reflect/ClassManifest$.MODULE$:Lscala/reflect/ClassManifest$;
Asciz	java/lang/Object;
class	java/lang/Object
Asciz	getClass;
Asciz	()Ljava/lang/Class;;
NameAndType	getClass:()Ljava/lang/Class;
Method	java/lang/Object.getClass:()Ljava/lang/Class;
Asciz	java/lang/Class;
class	java/lang/Class
Asciz	getComponentType;
NameAndType	getComponentType:()Ljava/lang/Class;
Method	java/lang/Class.getComponentType:()Ljava/lang/Class;
Asciz	classType;
Asciz	(Ljava/lang/Class;)Lscala/reflect/ClassManifest;;
NameAndType	classType:(Ljava/lang/Class;)Lscala/reflect/ClassManifest;
Method	scala/reflect/ClassManifest$.classType:(Ljava/lang/Class;)Lscala/reflect/ClassManifest;
Asciz	(Lscala/reflect/ClassManifest;)V;
NameAndType	"<init>":(Lscala/reflect/ClassManifest;)V
Method	scala/collection/mutable/ArrayBuilder$ofRef."<init>":(Lscala/reflect/ClassManifest;)V
Asciz	()Lscala/collection/mutable/ArrayBuilder$ofRef<TT;>;;
Asciz	scala/collection/mutable/WrappedArray$ofRef;
class	scala/collection/mutable/WrappedArray$ofRef
NameAndType	"<init>":([Ljava/lang/Object;)V
Method	scala/collection/mutable/WrappedArray$ofRef."<init>":([Ljava/lang/Object;)V
Asciz	([TT;)Lscala/collection/mutable/WrappedArray<TT;>;;
Asciz	()Lscala/collection/mutable/WrappedArray<TT;>;;
Asciz	()[TT;;
Asciz	<T:Ljava/lang/Object;>Lscala/collection/mutable/ArrayOps<TT;>;Lscala/collection/mutable/ArrayLike<TT;[TT;>;Lscala/ScalaObject;;
Asciz	Scala;
Asciz	InnerClasses;
Asciz	ofRef;
Asciz	scala/collection/mutable/WrappedArray;
class	scala/collection/mutable/WrappedArray
Asciz	scala/collection/mutable/ArrayBuilder;
class	scala/collection/mutable/ArrayBuilder
Asciz	scala/collection/mutable/ArrayLike;
class	scala/collection/mutable/ArrayLike
Asciz	scala/ScalaObject;
class	scala/ScalaObject

{
private final java.lang.Object[] repr;
  Signature: [Ljava/lang/Object;
  Signature: length = 0x2
   00 05 

public scala.collection.mutable.ArrayOps$ofRef(java.lang.Object[]);
  Signature: ([Ljava/lang/Object;)V
  Code:
   Stack=2, Locals=2, Args_size=2
	aload_0
	aload_1
	putfield	Field repr:[Ljava/lang/Object;
	aload_0
	invokespecial	Method scala/collection/mutable/ArrayOps."<init>":()V
	return
  Labels:
  LocalVariableTable: 
   Start  Length  Slot  Name   Signature
   0      10      0    this       Lscala/collection/mutable/ArrayOps$ofRef;
   0      10      1    repr       [Ljava/lang/Object;

  Signature: length = 0x2
   00 17 

public java.lang.Object repr();
  Signature: ()Ljava/lang/Object;
  Code:
   Stack=1, Locals=1, Args_size=1
	aload_0
	invokevirtual	Method repr:()[Ljava/lang/Object;
	areturn
  Labels:

public scala.collection.mutable.IndexedSeq thisCollection();
  Signature: ()Lscala/collection/mutable/IndexedSeq;
  Code:
   Stack=1, Locals=1, Args_size=1
	aload_0
	invokevirtual	Method thisCollection:()Lscala/collection/mutable/WrappedArray;
	areturn
  Labels:

public scala.collection.IndexedSeq thisCollection();
  Signature: ()Lscala/collection/IndexedSeq;
  Code:
   Stack=1, Locals=1, Args_size=1
	aload_0
	invokevirtual	Method thisCollection:()Lscala/collection/mutable/WrappedArray;
	areturn
  Labels:

public scala.collection.Seq thisCollection();
  Signature: ()Lscala/collection/Seq;
  Code:
   Stack=1, Locals=1, Args_size=1
	aload_0
	invokevirtual	Method thisCollection:()Lscala/collection/mutable/WrappedArray;
	areturn
  Labels:

public scala.collection.Iterable thisCollection();
  Signature: ()Lscala/collection/Iterable;
  Code:
   Stack=1, Locals=1, Args_size=1
	aload_0
	invokevirtual	Method thisCollection:()Lscala/collection/mutable/WrappedArray;
	areturn
  Labels:

public scala.collection.Traversable thisCollection();
  Signature: ()Lscala/collection/Traversable;
  Code:
   Stack=1, Locals=1, Args_size=1
	aload_0
	invokevirtual	Method thisCollection:()Lscala/collection/mutable/WrappedArray;
	areturn
  Labels:

public scala.collection.mutable.IndexedSeq toCollection(java.lang.Object);
  Signature: (Ljava/lang/Object;)Lscala/collection/mutable/IndexedSeq;
  Code:
   Stack=2, Locals=2, Args_size=2
	aload_0
	aload_1
	checkcast	class "[Ljava/lang/Object;"
	invokevirtual	Method toCollection:([Ljava/lang/Object;)Lscala/collection/mutable/WrappedArray;
	areturn
  Labels:
  LocalVariableTable: 
   Start  Length  Slot  Name   Signature
   0      9      0    this       Lscala/collection/mutable/ArrayOps$ofRef;
   0      9      1    repr       Ljava/lang/Object;


public scala.collection.IndexedSeq toCollection(java.lang.Object);
  Signature: (Ljava/lang/Object;)Lscala/collection/IndexedSeq;
  Code:
   Stack=2, Locals=2, Args_size=2
	aload_0
	aload_1
	checkcast	class "[Ljava/lang/Object;"
	invokevirtual	Method toCollection:([Ljava/lang/Object;)Lscala/collection/mutable/WrappedArray;
	areturn
  Labels:
  LocalVariableTable: 
   Start  Length  Slot  Name   Signature
   0      9      0    this       Lscala/collection/mutable/ArrayOps$ofRef;
   0      9      1    repr       Ljava/lang/Object;


public scala.collection.Seq toCollection(java.lang.Object);
  Signature: (Ljava/lang/Object;)Lscala/collection/Seq;
  Code:
   Stack=2, Locals=2, Args_size=2
	aload_0
	aload_1
	checkcast	class "[Ljava/lang/Object;"
	invokevirtual	Method toCollection:([Ljava/lang/Object;)Lscala/collection/mutable/WrappedArray;
	areturn
  Labels:
  LocalVariableTable: 
   Start  Length  Slot  Name   Signature
   0      9      0    this       Lscala/collection/mutable/ArrayOps$ofRef;
   0      9      1    repr       Ljava/lang/Object;


public scala.collection.Iterable toCollection(java.lang.Object);
  Signature: (Ljava/lang/Object;)Lscala/collection/Iterable;
  Code:
   Stack=2, Locals=2, Args_size=2
	aload_0
	aload_1
	checkcast	class "[Ljava/lang/Object;"
	invokevirtual	Method toCollection:([Ljava/lang/Object;)Lscala/collection/mutable/WrappedArray;
	areturn
  Labels:
  LocalVariableTable: 
   Start  Length  Slot  Name   Signature
   0      9      0    this       Lscala/collection/mutable/ArrayOps$ofRef;
   0      9      1    repr       Ljava/lang/Object;


public scala.collection.Traversable toCollection(java.lang.Object);
  Signature: (Ljava/lang/Object;)Lscala/collection/Traversable;
  Code:
   Stack=2, Locals=2, Args_size=2
	aload_0
	aload_1
	checkcast	class "[Ljava/lang/Object;"
	invokevirtual	Method toCollection:([Ljava/lang/Object;)Lscala/collection/mutable/WrappedArray;
	areturn
  Labels:
  LocalVariableTable: 
   Start  Length  Slot  Name   Signature
   0      9      0    this       Lscala/collection/mutable/ArrayOps$ofRef;
   0      9      1    repr       Ljava/lang/Object;


public scala.collection.mutable.Builder newBuilder();
  Signature: ()Lscala/collection/mutable/Builder;
  Code:
   Stack=1, Locals=1, Args_size=1
	aload_0
	invokevirtual	Method newBuilder:()Lscala/collection/mutable/ArrayBuilder$ofRef;
	areturn
  Labels:

public void update(int, java.lang.Object);
  Signature: (ILjava/lang/Object;)V
  Code:
   Stack=3, Locals=3, Args_size=3
	aload_0
	invokevirtual	Method repr:()[Ljava/lang/Object;
	iload_1
	aload_2
	aastore
	return
  Labels:
  LocalVariableTable: 
   Start  Length  Slot  Name   Signature
   0      8      0    this       Lscala/collection/mutable/ArrayOps$ofRef;
   0      8      1    index       I
   0      8      2    elem       Ljava/lang/Object;

  Signature: length = 0x2
   00 3A 

public java.lang.Object apply(int);
  Signature: (I)Ljava/lang/Object;
  Code:
   Stack=2, Locals=2, Args_size=2
	aload_0
	invokevirtual	Method repr:()[Ljava/lang/Object;
	iload_1
	aaload
	areturn
  Labels:
  LocalVariableTable: 
   Start  Length  Slot  Name   Signature
   0      7      0    this       Lscala/collection/mutable/ArrayOps$ofRef;
   0      7      1    index       I

  Signature: length = 0x2
   00 3D 

public int length();
  Signature: ()I
  Code:
   Stack=1, Locals=1, Args_size=1
	aload_0
	invokevirtual	Method repr:()[Ljava/lang/Object;
	arraylength
	ireturn
  Labels:

public scala.collection.mutable.ArrayBuilder$ofRef newBuilder();
  Signature: ()Lscala/collection/mutable/ArrayBuilder$ofRef;
  Code:
   Stack=4, Locals=1, Args_size=1
	new	class scala/collection/mutable/ArrayBuilder$ofRef
	dup
	getstatic	Field scala/reflect/ClassManifest$.MODULE$:Lscala/reflect/ClassManifest$;
	aload_0
	invokevirtual	Method repr:()[Ljava/lang/Object;
	invokevirtual	Method java/lang/Object.getClass:()Ljava/lang/Class;
	invokevirtual	Method java/lang/Class.getComponentType:()Ljava/lang/Class;
	invokevirtual	Method scala/reflect/ClassManifest$.classType:(Ljava/lang/Class;)Lscala/reflect/ClassManifest;
	invokespecial	Method scala/collection/mutable/ArrayBuilder$ofRef."<init>":(Lscala/reflect/ClassManifest;)V
	areturn
  Labels:
  Signature: length = 0x2
   00 5A 

public scala.collection.mutable.WrappedArray toCollection(java.lang.Object[]);
  Signature: ([Ljava/lang/Object;)Lscala/collection/mutable/WrappedArray;
  Code:
   Stack=3, Locals=2, Args_size=2
	new	class scala/collection/mutable/WrappedArray$ofRef
	dup
	aload_1
	invokespecial	Method scala/collection/mutable/WrappedArray$ofRef."<init>":([Ljava/lang/Object;)V
	areturn
  Labels:
  LocalVariableTable: 
   Start  Length  Slot  Name   Signature
   0      9      0    this       Lscala/collection/mutable/ArrayOps$ofRef;
   0      9      1    repr       [Ljava/lang/Object;

  Signature: length = 0x2
   00 5F 

public scala.collection.mutable.WrappedArray thisCollection();
  Signature: ()Lscala/collection/mutable/WrappedArray;
  Code:
   Stack=3, Locals=1, Args_size=1
	new	class scala/collection/mutable/WrappedArray$ofRef
	dup
	aload_0
	invokevirtual	Method repr:()[Ljava/lang/Object;
	invokespecial	Method scala/collection/mutable/WrappedArray$ofRef."<init>":([Ljava/lang/Object;)V
	areturn
  Labels:
  Signature: length = 0x2
   00 60 

public java.lang.Object[] repr();
  Signature: ()[Ljava/lang/Object;
  Code:
   Stack=1, Locals=1, Args_size=1
	aload_0
	getfield	Field repr:[Ljava/lang/Object;
	areturn
  Labels:
  Signature: length = 0x2
   00 61 

}

