Compiled from "ArrayLike.scala"
public abstract class scala.collection.mutable.ArrayLike$class extends java.lang.Object
  SourceFile: "ArrayLike.scala"
  Scala: length = 0x
   
  InnerClass: 
   public final #91= #86 of #30; //$anon$1=class scala/collection/mutable/ArrayLike$$anon$1 of class scala/collection/mutable/ArrayLike
  minor version: 0
  major version: 49
  Constant pool:
const #1 = Asciz	SourceFile;
const #2 = Asciz	ArrayLike.scala;
const #3 = Asciz	$init$;
const #4 = Asciz	(Lscala/collection/mutable/ArrayLike;)V;
const #5 = Asciz	Code;
const #6 = Asciz	LineNumberTable;
const #7 = Asciz	$this;
const #8 = Asciz	Lscala/collection/mutable/ArrayLike;;
const #9 = Asciz	LocalVariableTable;
const #10 = Asciz	gd2$1;
const #11 = Asciz	(Lscala/collection/mutable/ArrayLike;Ljava/lang/Object;)Z;
const #12 = Asciz	java/lang/Object;
const #13 = class	#12;	//  java/lang/Object
const #14 = Asciz	getClass;
const #15 = Asciz	()Ljava/lang/Class;;
const #16 = NameAndType	#14:#15;//  getClass:()Ljava/lang/Class;
const #17 = Method	#13.#16;	//  java/lang/Object.getClass:()Ljava/lang/Class;
const #18 = Asciz	java/lang/Class;
const #19 = class	#18;	//  java/lang/Class
const #20 = Asciz	isArray;
const #21 = Asciz	()Z;
const #22 = NameAndType	#20:#21;//  isArray:()Z
const #23 = Method	#19.#22;	//  java/lang/Class.isArray:()Z
const #24 = Asciz	deepEquals;
const #25 = Asciz	scala/collection/mutable/ArrayLike$class;
const #26 = class	#25;	//  scala/collection/mutable/ArrayLike$class
const #27 = NameAndType	#10:#11;//  gd2$1:(Lscala/collection/mutable/ArrayLike;Ljava/lang/Object;)Z
const #28 = Method	#26.#27;	//  scala/collection/mutable/ArrayLike$class.gd2$1:(Lscala/collection/mutable/ArrayLike;Ljava/lang/Object;)Z
const #29 = Asciz	scala/collection/mutable/ArrayLike;
const #30 = class	#29;	//  scala/collection/mutable/ArrayLike
const #31 = Asciz	deep;
const #32 = Asciz	()Lscala/collection/IndexedSeq;;
const #33 = NameAndType	#31:#32;//  deep:()Lscala/collection/IndexedSeq;
const #34 = InterfaceMethod	#30.#33;	//  scala/collection/mutable/ArrayLike.deep:()Lscala/collection/IndexedSeq;
const #35 = Asciz	scala/collection/mutable/WrappedArray$;
const #36 = class	#35;	//  scala/collection/mutable/WrappedArray$
const #37 = Asciz	MODULE$;
const #38 = Asciz	Lscala/collection/mutable/WrappedArray$;;
const #39 = NameAndType	#37:#38;//  MODULE$:Lscala/collection/mutable/WrappedArray$;
const #40 = Field	#36.#39;	//  scala/collection/mutable/WrappedArray$.MODULE$:Lscala/collection/mutable/WrappedArray$;
const #41 = Asciz	make;
const #42 = Asciz	(Ljava/lang/Object;)Lscala/collection/mutable/WrappedArray;;
const #43 = NameAndType	#41:#42;//  make:(Ljava/lang/Object;)Lscala/collection/mutable/WrappedArray;
const #44 = Method	#36.#43;	//  scala/collection/mutable/WrappedArray$.make:(Ljava/lang/Object;)Lscala/collection/mutable/WrappedArray;
const #45 = Asciz	scala/collection/SeqLike;
const #46 = class	#45;	//  scala/collection/SeqLike
const #47 = Asciz	equals;
const #48 = Asciz	(Ljava/lang/Object;)Z;
const #49 = NameAndType	#47:#48;//  equals:(Ljava/lang/Object;)Z
const #50 = InterfaceMethod	#46.#49;	//  scala/collection/SeqLike.equals:(Ljava/lang/Object;)Z
const #51 = Asciz	scala/MatchError;
const #52 = class	#51;	//  scala/MatchError
const #53 = Asciz	toString;
const #54 = Asciz	()Ljava/lang/String;;
const #55 = NameAndType	#53:#54;//  toString:()Ljava/lang/String;
const #56 = Method	#13.#55;	//  java/lang/Object.toString:()Ljava/lang/String;
const #57 = Asciz	<init>;
const #58 = Asciz	(Ljava/lang/String;)V;
const #59 = NameAndType	#57:#58;//  "<init>":(Ljava/lang/String;)V
const #60 = Method	#52.#59;	//  scala/MatchError."<init>":(Ljava/lang/String;)V
const #61 = Asciz	that;
const #62 = Asciz	Ljava/lang/Object;;
const #63 = Asciz	Deprecated;
const #64 = Asciz	deepMkString;
const #65 = Asciz	(Lscala/collection/mutable/ArrayLike;Ljava/lang/String;)Ljava/lang/String;;
const #66 = Asciz	;
const #67 = String	#66;	//  
const #68 = Asciz	(Ljava/lang/String;Ljava/lang/String;Ljava/lang/String;)Ljava/lang/String;;
const #69 = NameAndType	#64:#68;//  deepMkString:(Ljava/lang/String;Ljava/lang/String;Ljava/lang/String;)Ljava/lang/String;
const #70 = InterfaceMethod	#30.#69;	//  scala/collection/mutable/ArrayLike.deepMkString:(Ljava/lang/String;Ljava/lang/String;Ljava/lang/String;)Ljava/lang/String;
const #71 = Asciz	sep;
const #72 = Asciz	Ljava/lang/String;;
const #73 = Asciz	(Lscala/collection/mutable/ArrayLike;Ljava/lang/String;Ljava/lang/String;Ljava/lang/String;)Ljava/lang/String;;
const #74 = Asciz	scala/collection/TraversableLike;
const #75 = class	#74;	//  scala/collection/TraversableLike
const #76 = Asciz	mkString;
const #77 = NameAndType	#76:#68;//  mkString:(Ljava/lang/String;Ljava/lang/String;Ljava/lang/String;)Ljava/lang/String;
const #78 = InterfaceMethod	#75.#77;	//  scala/collection/TraversableLike.mkString:(Ljava/lang/String;Ljava/lang/String;Ljava/lang/String;)Ljava/lang/String;
const #79 = Asciz	start;
const #80 = Asciz	end;
const #81 = Asciz	deepToString;
const #82 = Asciz	(Lscala/collection/mutable/ArrayLike;)Ljava/lang/String;;
const #83 = InterfaceMethod	#46.#55;	//  scala/collection/SeqLike.toString:()Ljava/lang/String;
const #84 = Asciz	(Lscala/collection/mutable/ArrayLike;)Lscala/collection/IndexedSeq;;
const #85 = Asciz	scala/collection/mutable/ArrayLike$$anon$1;
const #86 = class	#85;	//  scala/collection/mutable/ArrayLike$$anon$1
const #87 = NameAndType	#57:#4;//  "<init>":(Lscala/collection/mutable/ArrayLike;)V
const #88 = Method	#86.#87;	//  scala/collection/mutable/ArrayLike$$anon$1."<init>":(Lscala/collection/mutable/ArrayLike;)V
const #89 = Asciz	Scala;
const #90 = Asciz	InnerClasses;
const #91 = Asciz	$anon$1;

{
public static void $init$(scala.collection.mutable.ArrayLike);
  Code:
   Stack=0, Locals=1, Args_size=1
   0:	return
  LineNumberTable: 
   line 21: 0

  LocalVariableTable: 
   Start  Length  Slot  Name   Signature
   0      1      0    $this       Lscala/collection/mutable/ArrayLike;


public static final boolean deepEquals(scala.collection.mutable.ArrayLike, java.lang.Object);
  Code:
   Stack=3, Locals=2, Args_size=2
   0:	aload_1
   1:	instanceof	#13; //class java/lang/Object
   4:	ifeq	61
   7:	aload_0
   8:	aload_1
   9:	invokestatic	#28; //Method gd2$1:(Lscala/collection/mutable/ArrayLike;Ljava/lang/Object;)Z
   12:	ifeq	41
   15:	aload_0
   16:	invokeinterface	#34,  1; //InterfaceMethod scala/collection/mutable/ArrayLike.deep:()Lscala/collection/IndexedSeq;
   21:	getstatic	#40; //Field scala/collection/mutable/WrappedArray$.MODULE$:Lscala/collection/mutable/WrappedArray$;
   24:	aload_1
   25:	invokevirtual	#44; //Method scala/collection/mutable/WrappedArray$.make:(Ljava/lang/Object;)Lscala/collection/mutable/WrappedArray;
   28:	invokeinterface	#34,  1; //InterfaceMethod scala/collection/mutable/ArrayLike.deep:()Lscala/collection/IndexedSeq;
   33:	invokeinterface	#50,  2; //InterfaceMethod scala/collection/SeqLike.equals:(Ljava/lang/Object;)Z
   38:	goto	66
   41:	iconst_1
   42:	ifeq	49
   45:	iconst_0
   46:	goto	66
   49:	new	#52; //class scala/MatchError
   52:	dup
   53:	aload_1
   54:	invokevirtual	#56; //Method java/lang/Object.toString:()Ljava/lang/String;
   57:	invokespecial	#60; //Method scala/MatchError."<init>":(Ljava/lang/String;)V
   60:	athrow
   61:	iconst_1
   62:	ifeq	67
   65:	iconst_0
   66:	ireturn
   67:	new	#52; //class scala/MatchError
   70:	dup
   71:	aload_1
   72:	invokevirtual	#56; //Method java/lang/Object.toString:()Ljava/lang/String;
   75:	invokespecial	#60; //Method scala/MatchError."<init>":(Ljava/lang/String;)V
   78:	athrow
  LineNumberTable: 
   line 54: 0
   line 55: 15
   line 21: 41
   line 56: 45
   line 54: 49
   line 21: 61
   line 56: 65
   line 54: 66

  LocalVariableTable: 
   Start  Length  Slot  Name   Signature
   0      79      0    $this       Lscala/collection/mutable/ArrayLike;
   0      79      1    that       Ljava/lang/Object;

  Deprecated: true

public static final java.lang.String deepMkString(scala.collection.mutable.ArrayLike, java.lang.String);
  Code:
   Stack=4, Locals=2, Args_size=2
   0:	aload_0
   1:	ldc	#67; //String 
   3:	aload_1
   4:	ldc	#67; //String 
   6:	invokeinterface	#70,  4; //InterfaceMethod scala/collection/mutable/ArrayLike.deepMkString:(Ljava/lang/String;Ljava/lang/String;Ljava/lang/String;)Ljava/lang/String;
   11:	areturn
  LineNumberTable: 
   line 51: 0

  LocalVariableTable: 
   Start  Length  Slot  Name   Signature
   0      12      0    $this       Lscala/collection/mutable/ArrayLike;
   0      12      1    sep       Ljava/lang/String;

  Deprecated: true

public static final java.lang.String deepMkString(scala.collection.mutable.ArrayLike, java.lang.String, java.lang.String, java.lang.String);
  Code:
   Stack=4, Locals=4, Args_size=4
   0:	aload_0
   1:	invokeinterface	#34,  1; //InterfaceMethod scala/collection/mutable/ArrayLike.deep:()Lscala/collection/IndexedSeq;
   6:	aload_1
   7:	aload_2
   8:	aload_3
   9:	invokeinterface	#78,  4; //InterfaceMethod scala/collection/TraversableLike.mkString:(Ljava/lang/String;Ljava/lang/String;Ljava/lang/String;)Ljava/lang/String;
   14:	areturn
  LineNumberTable: 
   line 47: 0

  LocalVariableTable: 
   Start  Length  Slot  Name   Signature
   0      15      0    $this       Lscala/collection/mutable/ArrayLike;
   0      15      1    start       Ljava/lang/String;
   0      15      2    sep       Ljava/lang/String;
   0      15      3    end       Ljava/lang/String;

  Deprecated: true

public static final java.lang.String deepToString(scala.collection.mutable.ArrayLike);
  Code:
   Stack=1, Locals=1, Args_size=1
   0:	aload_0
   1:	invokeinterface	#34,  1; //InterfaceMethod scala/collection/mutable/ArrayLike.deep:()Lscala/collection/IndexedSeq;
   6:	invokeinterface	#83,  1; //InterfaceMethod scala/collection/SeqLike.toString:()Ljava/lang/String;
   11:	areturn
  LineNumberTable: 
   line 43: 0

  LocalVariableTable: 
   Start  Length  Slot  Name   Signature
   0      12      0    $this       Lscala/collection/mutable/ArrayLike;

  Deprecated: true

public static scala.collection.IndexedSeq deep(scala.collection.mutable.ArrayLike);
  Code:
   Stack=3, Locals=1, Args_size=1
   0:	new	#86; //class scala/collection/mutable/ArrayLike$$anon$1
   3:	dup
   4:	aload_0
   5:	invokespecial	#88; //Method scala/collection/mutable/ArrayLike$$anon$1."<init>":(Lscala/collection/mutable/ArrayLike;)V
   8:	areturn
  LineNumberTable: 
   line 32: 0

  LocalVariableTable: 
   Start  Length  Slot  Name   Signature
   0      9      0    $this       Lscala/collection/mutable/ArrayLike;


}

