Compiled from "ArrayOps.scala"
public class scala.collection.mutable.ArrayOps$ofByte extends scala.collection.mutable.ArrayOps implements scala.collection.mutable.ArrayLike,scala.ScalaObject
  SourceFile: "ArrayOps.scala"
  Scala: length = 0x
   
  Signature: length = 0x2
   00 58 
  InnerClass: 
   public ofByte=class scala/collection/mutable/ArrayOps$ofByte of class scala/collection/mutable/ArrayOps
   public ofByte=class scala/collection/mutable/ArrayBuilder$ofByte of class scala/collection/mutable/ArrayBuilder
   public final ofByte=class scala/collection/mutable/WrappedArray$ofByte of class scala/collection/mutable/WrappedArray
  minor version: 0
  major version: 49
  Constant pool:
Asciz	SourceFile;
Asciz	ArrayOps.scala;
Asciz	repr;
Asciz	[B;
Asciz	()[B;
Asciz	Code;
Asciz	LineNumberTable;
Asciz	scala/collection/mutable/ArrayOps$ofByte;
class	scala/collection/mutable/ArrayOps$ofByte
NameAndType	repr:[B
Field	scala/collection/mutable/ArrayOps$ofByte.repr:[B
Asciz	thisCollection;
Asciz	()Lscala/collection/mutable/WrappedArray;;
Asciz	scala/collection/mutable/WrappedArray$ofByte;
class	scala/collection/mutable/WrappedArray$ofByte
NameAndType	repr:()[B
Method	scala/collection/mutable/ArrayOps$ofByte.repr:()[B
Asciz	<init>;
Asciz	([B)V;
NameAndType	"<init>":([B)V
Method	scala/collection/mutable/WrappedArray$ofByte."<init>":([B)V
Asciz	()Lscala/collection/mutable/WrappedArray<Ljava/lang/Byte;>;;
Asciz	Signature;
Asciz	toCollection;
Asciz	([B)Lscala/collection/mutable/WrappedArray;;
Asciz	this;
Asciz	Lscala/collection/mutable/ArrayOps$ofByte;;
Asciz	LocalVariableTable;
Asciz	([B)Lscala/collection/mutable/WrappedArray<Ljava/lang/Byte;>;;
Asciz	newBuilder;
Asciz	()Lscala/collection/mutable/ArrayBuilder$ofByte;;
Asciz	scala/collection/mutable/ArrayBuilder$ofByte;
class	scala/collection/mutable/ArrayBuilder$ofByte
Asciz	()V;
NameAndType	"<init>":()V
Method	scala/collection/mutable/ArrayBuilder$ofByte."<init>":()V
Asciz	length;
Asciz	()I;
Asciz	apply;
Asciz	(I)B;
Asciz	index;
Asciz	I;
Asciz	update;
Asciz	(IB)V;
Asciz	elem;
Asciz	B;
Asciz	(ILjava/lang/Object;)V;
Asciz	scala/runtime/BoxesRunTime;
class	scala/runtime/BoxesRunTime
Asciz	unboxToByte;
Asciz	(Ljava/lang/Object;)B;
NameAndType	unboxToByte:(Ljava/lang/Object;)B
Method	scala/runtime/BoxesRunTime.unboxToByte:(Ljava/lang/Object;)B
NameAndType	update:(IB)V
Method	scala/collection/mutable/ArrayOps$ofByte.update:(IB)V
Asciz	idx;
Asciz	Ljava/lang/Object;;
Asciz	(I)Ljava/lang/Object;;
NameAndType	apply:(I)B
Method	scala/collection/mutable/ArrayOps$ofByte.apply:(I)B
Asciz	boxToByte;
Asciz	(B)Ljava/lang/Byte;;
NameAndType	boxToByte:(B)Ljava/lang/Byte;
Method	scala/runtime/BoxesRunTime.boxToByte:(B)Ljava/lang/Byte;
Asciz	()Lscala/collection/mutable/Builder;;
NameAndType	newBuilder:()Lscala/collection/mutable/ArrayBuilder$ofByte;
Method	scala/collection/mutable/ArrayOps$ofByte.newBuilder:()Lscala/collection/mutable/ArrayBuilder$ofByte;
Asciz	(Ljava/lang/Object;)Lscala/collection/Traversable;;
class	"[B"
NameAndType	toCollection:([B)Lscala/collection/mutable/WrappedArray;
Method	scala/collection/mutable/ArrayOps$ofByte.toCollection:([B)Lscala/collection/mutable/WrappedArray;
Asciz	(Ljava/lang/Object;)Lscala/collection/Iterable;;
Asciz	(Ljava/lang/Object;)Lscala/collection/Seq;;
Asciz	(Ljava/lang/Object;)Lscala/collection/IndexedSeq;;
Asciz	(Ljava/lang/Object;)Lscala/collection/mutable/IndexedSeq;;
Asciz	()Lscala/collection/Traversable;;
NameAndType	thisCollection:()Lscala/collection/mutable/WrappedArray;
Method	scala/collection/mutable/ArrayOps$ofByte.thisCollection:()Lscala/collection/mutable/WrappedArray;
Asciz	()Lscala/collection/Iterable;;
Asciz	()Lscala/collection/Seq;;
Asciz	()Lscala/collection/IndexedSeq;;
Asciz	()Lscala/collection/mutable/IndexedSeq;;
Asciz	()Ljava/lang/Object;;
Asciz	scala/collection/mutable/ArrayOps;
class	scala/collection/mutable/ArrayOps
Method	scala/collection/mutable/ArrayOps."<init>":()V
Asciz	Scala;
Asciz	Lscala/collection/mutable/ArrayOps<Ljava/lang/Byte;>;Lscala/collection/mutable/ArrayLike<Ljava/lang/Byte;[B>;Lscala/ScalaObject;;
Asciz	InnerClasses;
Asciz	ofByte;
Asciz	scala/collection/mutable/ArrayBuilder;
class	scala/collection/mutable/ArrayBuilder
Asciz	scala/collection/mutable/WrappedArray;
class	scala/collection/mutable/WrappedArray
Asciz	scala/collection/mutable/ArrayLike;
class	scala/collection/mutable/ArrayLike
Asciz	scala/ScalaObject;
class	scala/ScalaObject

{
private final byte[] repr;
  Signature: [B

public byte[] repr();
  Signature: ()[B
  Code:
   Stack=1, Locals=1, Args_size=1
	aload_0
	getfield	Field repr:[B
	areturn
  Labels:

public scala.collection.mutable.WrappedArray thisCollection();
  Signature: ()Lscala/collection/mutable/WrappedArray;
  Code:
   Stack=3, Locals=1, Args_size=1
	new	class scala/collection/mutable/WrappedArray$ofByte
	dup
	aload_0
	invokevirtual	Method repr:()[B
	invokespecial	Method scala/collection/mutable/WrappedArray$ofByte."<init>":([B)V
	areturn
  Labels:
  Signature: length = 0x2
   00 16 

public scala.collection.mutable.WrappedArray toCollection(byte[]);
  Signature: ([B)Lscala/collection/mutable/WrappedArray;
  Code:
   Stack=3, Locals=2, Args_size=2
	new	class scala/collection/mutable/WrappedArray$ofByte
	dup
	aload_1
	invokespecial	Method scala/collection/mutable/WrappedArray$ofByte."<init>":([B)V
	areturn
  Labels:
  LocalVariableTable: 
   Start  Length  Slot  Name   Signature
   0      9      0    this       Lscala/collection/mutable/ArrayOps$ofByte;
   0      9      1    repr       [B

  Signature: length = 0x2
   00 1D 

public scala.collection.mutable.ArrayBuilder$ofByte newBuilder();
  Signature: ()Lscala/collection/mutable/ArrayBuilder$ofByte;
  Code:
   Stack=2, Locals=1, Args_size=1
	new	class scala/collection/mutable/ArrayBuilder$ofByte
	dup
	invokespecial	Method scala/collection/mutable/ArrayBuilder$ofByte."<init>":()V
	areturn
  Labels:

public int length();
  Signature: ()I
  Code:
   Stack=1, Locals=1, Args_size=1
	aload_0
	invokevirtual	Method repr:()[B
	arraylength
	ireturn
  Labels:

public byte apply(int);
  Signature: (I)B
  Code:
   Stack=2, Locals=2, Args_size=2
	aload_0
	invokevirtual	Method repr:()[B
	iload_1
	baload
	ireturn
  Labels:
  LocalVariableTable: 
   Start  Length  Slot  Name   Signature
   0      7      0    this       Lscala/collection/mutable/ArrayOps$ofByte;
   0      7      1    index       I


public void update(int, byte);
  Signature: (IB)V
  Code:
   Stack=3, Locals=3, Args_size=3
	aload_0
	invokevirtual	Method repr:()[B
	iload_1
	iload_2
	bastore
	return
  Labels:
  LocalVariableTable: 
   Start  Length  Slot  Name   Signature
   0      8      0    this       Lscala/collection/mutable/ArrayOps$ofByte;
   0      8      1    index       I
   0      8      2    elem       B


public void update(int, java.lang.Object);
  Signature: (ILjava/lang/Object;)V
  Code:
   Stack=3, Locals=3, Args_size=3
	aload_0
	iload_1
	aload_2
	invokestatic	Method scala/runtime/BoxesRunTime.unboxToByte:(Ljava/lang/Object;)B
	invokevirtual	Method update:(IB)V
	return
  Labels:
  LocalVariableTable: 
   Start  Length  Slot  Name   Signature
   0      10      0    this       Lscala/collection/mutable/ArrayOps$ofByte;
   0      10      1    idx       I
   0      10      2    elem       Ljava/lang/Object;


public java.lang.Object apply(int);
  Signature: (I)Ljava/lang/Object;
  Code:
   Stack=2, Locals=3, Args_size=2
	aload_0
	iload_1
	invokevirtual	Method apply:(I)B
	istore_2
	iload_2
	invokestatic	Method scala/runtime/BoxesRunTime.boxToByte:(B)Ljava/lang/Byte;
	areturn
  Labels:
  LocalVariableTable: 
   Start  Length  Slot  Name   Signature
   0      11      0    this       Lscala/collection/mutable/ArrayOps$ofByte;
   0      11      1    idx       I


public scala.collection.mutable.Builder newBuilder();
  Signature: ()Lscala/collection/mutable/Builder;
  Code:
   Stack=1, Locals=1, Args_size=1
	aload_0
	invokevirtual	Method newBuilder:()Lscala/collection/mutable/ArrayBuilder$ofByte;
	areturn
  Labels:

public scala.collection.Traversable toCollection(java.lang.Object);
  Signature: (Ljava/lang/Object;)Lscala/collection/Traversable;
  Code:
   Stack=2, Locals=2, Args_size=2
	aload_0
	aload_1
	checkcast	class "[B"
	invokevirtual	Method toCollection:([B)Lscala/collection/mutable/WrappedArray;
	areturn
  Labels:
  LocalVariableTable: 
   Start  Length  Slot  Name   Signature
   0      9      0    this       Lscala/collection/mutable/ArrayOps$ofByte;
   0      9      1    repr       Ljava/lang/Object;


public scala.collection.Iterable toCollection(java.lang.Object);
  Signature: (Ljava/lang/Object;)Lscala/collection/Iterable;
  Code:
   Stack=2, Locals=2, Args_size=2
	aload_0
	aload_1
	checkcast	class "[B"
	invokevirtual	Method toCollection:([B)Lscala/collection/mutable/WrappedArray;
	areturn
  Labels:
  LocalVariableTable: 
   Start  Length  Slot  Name   Signature
   0      9      0    this       Lscala/collection/mutable/ArrayOps$ofByte;
   0      9      1    repr       Ljava/lang/Object;


public scala.collection.Seq toCollection(java.lang.Object);
  Signature: (Ljava/lang/Object;)Lscala/collection/Seq;
  Code:
   Stack=2, Locals=2, Args_size=2
	aload_0
	aload_1
	checkcast	class "[B"
	invokevirtual	Method toCollection:([B)Lscala/collection/mutable/WrappedArray;
	areturn
  Labels:
  LocalVariableTable: 
   Start  Length  Slot  Name   Signature
   0      9      0    this       Lscala/collection/mutable/ArrayOps$ofByte;
   0      9      1    repr       Ljava/lang/Object;


public scala.collection.IndexedSeq toCollection(java.lang.Object);
  Signature: (Ljava/lang/Object;)Lscala/collection/IndexedSeq;
  Code:
   Stack=2, Locals=2, Args_size=2
	aload_0
	aload_1
	checkcast	class "[B"
	invokevirtual	Method toCollection:([B)Lscala/collection/mutable/WrappedArray;
	areturn
  Labels:
  LocalVariableTable: 
   Start  Length  Slot  Name   Signature
   0      9      0    this       Lscala/collection/mutable/ArrayOps$ofByte;
   0      9      1    repr       Ljava/lang/Object;


public scala.collection.mutable.IndexedSeq toCollection(java.lang.Object);
  Signature: (Ljava/lang/Object;)Lscala/collection/mutable/IndexedSeq;
  Code:
   Stack=2, Locals=2, Args_size=2
	aload_0
	aload_1
	checkcast	class "[B"
	invokevirtual	Method toCollection:([B)Lscala/collection/mutable/WrappedArray;
	areturn
  Labels:
  LocalVariableTable: 
   Start  Length  Slot  Name   Signature
   0      9      0    this       Lscala/collection/mutable/ArrayOps$ofByte;
   0      9      1    repr       Ljava/lang/Object;


public scala.collection.Traversable thisCollection();
  Signature: ()Lscala/collection/Traversable;
  Code:
   Stack=1, Locals=1, Args_size=1
	aload_0
	invokevirtual	Method thisCollection:()Lscala/collection/mutable/WrappedArray;
	areturn
  Labels:

public scala.collection.Iterable thisCollection();
  Signature: ()Lscala/collection/Iterable;
  Code:
   Stack=1, Locals=1, Args_size=1
	aload_0
	invokevirtual	Method thisCollection:()Lscala/collection/mutable/WrappedArray;
	areturn
  Labels:

public scala.collection.Seq thisCollection();
  Signature: ()Lscala/collection/Seq;
  Code:
   Stack=1, Locals=1, Args_size=1
	aload_0
	invokevirtual	Method thisCollection:()Lscala/collection/mutable/WrappedArray;
	areturn
  Labels:

public scala.collection.IndexedSeq thisCollection();
  Signature: ()Lscala/collection/IndexedSeq;
  Code:
   Stack=1, Locals=1, Args_size=1
	aload_0
	invokevirtual	Method thisCollection:()Lscala/collection/mutable/WrappedArray;
	areturn
  Labels:

public scala.collection.mutable.IndexedSeq thisCollection();
  Signature: ()Lscala/collection/mutable/IndexedSeq;
  Code:
   Stack=1, Locals=1, Args_size=1
	aload_0
	invokevirtual	Method thisCollection:()Lscala/collection/mutable/WrappedArray;
	areturn
  Labels:

public java.lang.Object repr();
  Signature: ()Ljava/lang/Object;
  Code:
   Stack=1, Locals=1, Args_size=1
	aload_0
	invokevirtual	Method repr:()[B
	areturn
  Labels:

public scala.collection.mutable.ArrayOps$ofByte(byte[]);
  Signature: ([B)V
  Code:
   Stack=2, Locals=2, Args_size=2
	aload_0
	aload_1
	putfield	Field repr:[B
	aload_0
	invokespecial	Method scala/collection/mutable/ArrayOps."<init>":()V
	return
  Labels:
  LocalVariableTable: 
   Start  Length  Slot  Name   Signature
   0      10      0    this       Lscala/collection/mutable/ArrayOps$ofByte;
   0      10      1    repr       [B


}

