Compiled from "BitSet.scala"
public class scala.collection.mutable.BitSet extends java.lang.Object implements scala.collection.mutable.Set,scala.collection.BitSet,scala.collection.BitSetLike,scala.collection.mutable.SetLike,scala.ScalaObject,java.io.Serializable
  SourceFile: "BitSet.scala"
  Signature: length = 0x2
   03 FFFFFF81 
  ScalaSig: length = 0x3E1
   05 00 FFFFFF81 19 06 08 01 02 FFFFFF84 FFFFFF80 FFFFFF80 FFFFFF80 00 09 02 06
   42 69 74 53 65 74 0A 02 03 04 01 07 6D 75 74 61
   62 6C 65 0A 02 05 06 01 0A 63 6F 6C 6C 65 63 74
   69 6F 6E 0A 01 07 01 05 73 63 61 6C 61 03 00 13
   07 00 0A 12 1A 1D 21 24 10 02 0B 10 0D 01 0C 0A
   02 0D 0E 01 04 6C 61 6E 67 0A 01 0F 01 04 6A 61
   76 61 09 02 11 0C 02 06 4F 62 6A 65 63 74 10 03
   13 14 16 0D 01 02 09 02 15 02 02 03 53 65 74 10
   02 17 18 0D 01 06 09 02 19 06 02 03 49 6E 74 10
   02 1B 1C 0D 01 04 09 02 01 04 10 03 1B 1E 20 09
   02 1F 04 02 0A 42 69 74 53 65 74 4C 69 6B 65 10
   02 13 00 10 04 13 22 16 20 09 02 23 02 02 07 53
   65 74 4C 69 6B 65 10 02 17 25 09 02 26 06 02 0B
   53 63 61 6C 61 4F 62 6A 65 63 74 08 08 28 00 FFFFFF82
   FFFFFFC0 FFFFFF80 FFFFFF84 08 29 01 05 65 6C 65 6D 73 15 01 2A 10
   03 17 2B 2D 09 02 2C 06 02 05 41 72 72 61 79 10
   02 17 2E 09 02 2F 06 02 04 4C 6F 6E 67 08 08 31
   00 FFFFFF82 FFFFFFC0 FFFFFF80 FFFFFF84 08 32 01 09 65 6C 65 6D 73 5F 24
   65 71 14 02 33 36 10 02 17 34 09 02 35 06 02 04
   55 6E 69 74 08 07 37 30 FFFFFF81 FFFFFF80 FFFFFFC0 00 2A 01 03 78
   24 31 08 08 39 00 FFFFFF82 FFFFFF80 FFFFFFA0 FFFFFFA0 04 2A 01 06 65 6C
   65 6D 73 20 08 05 3B 00 FFFFFF84 00 3C 01 06 3C 69 6E
   69 74 3E 14 02 20 3D 08 05 28 3A FFFFFFC0 00 2A 08 05
   3F 00 FFFFFF84 20 40 01 05 65 6D 70 74 79 15 01 20 08
   05 3B 00 FFFFFF84 00 42 14 02 20 43 08 05 44 41 FFFFFFC0 00
   16 01 08 69 6E 69 74 53 69 7A 65 08 05 3B 00 FFFFFF84
   00 46 14 01 20 08 05 48 00 FFFFFF84 08 49 01 06 6E 77
   6F 72 64 73 15 01 16 08 05 4B 00 FFFFFF84 08 4C 01 04
   77 6F 72 64 14 02 2D 4D 08 05 4E 4A FFFFFFC0 00 16 01
   03 69 64 78 08 05 50 00 FFFFFF84 04 51 01 0A 75 70 64
   61 74 65 57 6F 72 64 14 03 33 52 53 08 05 4E 4F
   FFFFFFC0 00 16 08 05 54 4F FFFFFFC0 00 2D 01 01 77 08 05 56
   00 FFFFFF84 08 57 01 09 66 72 6F 6D 41 72 72 61 79 14
   02 20 58 08 05 59 55 FFFFFFC0 00 2A 01 05 77 6F 72 64
   73 08 05 5B 00 FFFFFF84 20 5C 01 03 61 64 64 14 02 5D
   60 10 02 17 5E 09 02 5F 06 02 07 42 6F 6F 6C 65
   61 6E 08 05 61 5A FFFFFFC0 00 16 01 04 65 6C 65 6D 08
   05 63 00 FFFFFF84 20 64 01 06 72 65 6D 6F 76 65 14 02
   5D 65 08 05 61 62 FFFFFFC0 00 16 08 05 67 00 FFFFFF84 00 68
   01 08 24 70 6C 75 73 24 65 71 14 02 69 6A 0D 01
   00 08 05 61 66 FFFFFFC0 00 16 08 05 6C 00 FFFFFF84 00 6D 01
   09 24 6D 69 6E 75 73 24 65 71 14 02 69 6E 08 05
   61 6B FFFFFFC0 00 16 08 05 70 00 FFFFFF84 20 71 01 05 63 6C
   65 61 72 14 01 33 08 05 73 00 FFFFFF84 00 74 01 0B 74
   6F 49 6D 6D 75 74 61 62 6C 65 15 01 75 10 02 76
   79 0D 01 77 0A 02 78 04 01 09 69 6D 6D 75 74 61
   62 6C 65 09 02 01 77 08 05 7B 00 FFFFFF84 20 46 01 05
   63 6C 6F 6E 65 28 04 00 7D FFFFFF81 00 10 02 17 7E 09
   02 7F 06 02 10 53 65 72 69 61 6C 56 65 72 73 69
   6F 6E 55 49 44 1E 08 75 FFFFFFBA 10 FFFFFFEB 2D 44 1B FFFFFFB3 28
   03 00 FFFFFF81 02 10 03 17 FFFFFF81 03 09 03 FFFFFF81 04 06 02 0C
   73 65 72 69 61 6C 69 7A 61 62 6C 65 07 07 FFFFFF81 06
   02 FFFFFF88 02 FFFFFF81 07 01 06 42 69 74 53 65 74 10 03 13
   FFFFFF81 08 06 09 01 02 FFFFFF84 FFFFFF80 FFFFFF80 FFFFFF88 02 FFFFFF81 09 13 06 FFFFFF81
   08 0A FFFFFF81 0A 24 10 05 FFFFFF81 0B FFFFFF81 0E 20 0D 02 FFFFFF81 0C
   0A 03 FFFFFF81 0D 04 01 07 67 65 6E 65 72 69 63 09 04
   FFFFFF81 0F FFFFFF81 0C 02 0D 42 69 74 53 65 74 46 61 63 74
   6F 72 79 08 07 3B FFFFFF81 08 FFFFFF84 00 FFFFFF81 11 14 02 FFFFFF81 07
   08 06 3F FFFFFF81 08 FFFFFF84 00 40 08 08 FFFFFF81 14 FFFFFF81 08 FFFFFF84 01
   FFFFFF81 15 01 0C 63 61 6E 42 75 69 6C 64 46 72 6F 6D
   15 02 FFFFFF81 16 10 07 FFFFFF81 0B FFFFFF81 17 20 16 20 09 04 FFFFFF81
   18 FFFFFF81 0C 02 0C 43 61 6E 42 75 69 6C 64 46 72 6F
   6D 
  InnerClass: 
   public #902= #901 of #268; //WithFilter=class scala/collection/TraversableLike$WithFilter of class scala/collection/TraversableLike
  minor version: 0
  major version: 49
  Constant pool:
const #1 = Asciz	SourceFile;
const #2 = Asciz	BitSet.scala;
const #3 = Asciz	<clinit>;
const #4 = Asciz	()V;
const #5 = Asciz	Code;
const #6 = Asciz	serialVersionUID;
const #7 = Asciz	J;
const #8 = long	8483111450368547763l;
const #10 = Asciz	scala/collection/mutable/BitSet;
const #11 = class	#10;	//  scala/collection/mutable/BitSet
const #12 = NameAndType	#6:#7;//  serialVersionUID:J
const #13 = Field	#11.#12;	//  scala/collection/mutable/BitSet.serialVersionUID:J
const #14 = Asciz	elems;
const #15 = Asciz	[J;
const #16 = Asciz	<init>;
const #17 = Asciz	([J)V;
const #18 = Asciz	LineNumberTable;
const #19 = NameAndType	#14:#15;//  elems:[J
const #20 = Field	#11.#19;	//  scala/collection/mutable/BitSet.elems:[J
const #21 = Asciz	java/lang/Object;
const #22 = class	#21;	//  java/lang/Object
const #23 = NameAndType	#16:#4;//  "<init>":()V
const #24 = Method	#22.#23;	//  java/lang/Object."<init>":()V
const #25 = Asciz	scala/collection/TraversableLike$class;
const #26 = class	#25;	//  scala/collection/TraversableLike$class
const #27 = Asciz	$init$;
const #28 = Asciz	(Lscala/collection/TraversableLike;)V;
const #29 = NameAndType	#27:#28;//  $init$:(Lscala/collection/TraversableLike;)V
const #30 = Method	#26.#29;	//  scala/collection/TraversableLike$class.$init$:(Lscala/collection/TraversableLike;)V
const #31 = Asciz	scala/collection/generic/GenericTraversableTemplate$class;
const #32 = class	#31;	//  scala/collection/generic/GenericTraversableTemplate$class
const #33 = Asciz	(Lscala/collection/generic/GenericTraversableTemplate;)V;
const #34 = NameAndType	#27:#33;//  $init$:(Lscala/collection/generic/GenericTraversableTemplate;)V
const #35 = Method	#32.#34;	//  scala/collection/generic/GenericTraversableTemplate$class.$init$:(Lscala/collection/generic/GenericTraversableTemplate;)V
const #36 = Asciz	scala/collection/Traversable$class;
const #37 = class	#36;	//  scala/collection/Traversable$class
const #38 = Asciz	(Lscala/collection/Traversable;)V;
const #39 = NameAndType	#27:#38;//  $init$:(Lscala/collection/Traversable;)V
const #40 = Method	#37.#39;	//  scala/collection/Traversable$class.$init$:(Lscala/collection/Traversable;)V
const #41 = Asciz	scala/collection/mutable/Traversable$class;
const #42 = class	#41;	//  scala/collection/mutable/Traversable$class
const #43 = Asciz	(Lscala/collection/mutable/Traversable;)V;
const #44 = NameAndType	#27:#43;//  $init$:(Lscala/collection/mutable/Traversable;)V
const #45 = Method	#42.#44;	//  scala/collection/mutable/Traversable$class.$init$:(Lscala/collection/mutable/Traversable;)V
const #46 = Asciz	scala/collection/IterableLike$class;
const #47 = class	#46;	//  scala/collection/IterableLike$class
const #48 = Asciz	(Lscala/collection/IterableLike;)V;
const #49 = NameAndType	#27:#48;//  $init$:(Lscala/collection/IterableLike;)V
const #50 = Method	#47.#49;	//  scala/collection/IterableLike$class.$init$:(Lscala/collection/IterableLike;)V
const #51 = Asciz	scala/collection/Iterable$class;
const #52 = class	#51;	//  scala/collection/Iterable$class
const #53 = Asciz	(Lscala/collection/Iterable;)V;
const #54 = NameAndType	#27:#53;//  $init$:(Lscala/collection/Iterable;)V
const #55 = Method	#52.#54;	//  scala/collection/Iterable$class.$init$:(Lscala/collection/Iterable;)V
const #56 = Asciz	scala/collection/mutable/Iterable$class;
const #57 = class	#56;	//  scala/collection/mutable/Iterable$class
const #58 = Asciz	(Lscala/collection/mutable/Iterable;)V;
const #59 = NameAndType	#27:#58;//  $init$:(Lscala/collection/mutable/Iterable;)V
const #60 = Method	#57.#59;	//  scala/collection/mutable/Iterable$class.$init$:(Lscala/collection/mutable/Iterable;)V
const #61 = Asciz	scala/Function1$class;
const #62 = class	#61;	//  scala/Function1$class
const #63 = Asciz	(Lscala/Function1;)V;
const #64 = NameAndType	#27:#63;//  $init$:(Lscala/Function1;)V
const #65 = Method	#62.#64;	//  scala/Function1$class.$init$:(Lscala/Function1;)V
const #66 = Asciz	scala/collection/generic/GenericSetTemplate$class;
const #67 = class	#66;	//  scala/collection/generic/GenericSetTemplate$class
const #68 = Asciz	(Lscala/collection/generic/GenericSetTemplate;)V;
const #69 = NameAndType	#27:#68;//  $init$:(Lscala/collection/generic/GenericSetTemplate;)V
const #70 = Method	#67.#69;	//  scala/collection/generic/GenericSetTemplate$class.$init$:(Lscala/collection/generic/GenericSetTemplate;)V
const #71 = Asciz	scala/collection/generic/Addable$class;
const #72 = class	#71;	//  scala/collection/generic/Addable$class
const #73 = Asciz	(Lscala/collection/generic/Addable;)V;
const #74 = NameAndType	#27:#73;//  $init$:(Lscala/collection/generic/Addable;)V
const #75 = Method	#72.#74;	//  scala/collection/generic/Addable$class.$init$:(Lscala/collection/generic/Addable;)V
const #76 = Asciz	scala/collection/generic/Subtractable$class;
const #77 = class	#76;	//  scala/collection/generic/Subtractable$class
const #78 = Asciz	(Lscala/collection/generic/Subtractable;)V;
const #79 = NameAndType	#27:#78;//  $init$:(Lscala/collection/generic/Subtractable;)V
const #80 = Method	#77.#79;	//  scala/collection/generic/Subtractable$class.$init$:(Lscala/collection/generic/Subtractable;)V
const #81 = Asciz	scala/collection/SetLike$class;
const #82 = class	#81;	//  scala/collection/SetLike$class
const #83 = Asciz	(Lscala/collection/SetLike;)V;
const #84 = NameAndType	#27:#83;//  $init$:(Lscala/collection/SetLike;)V
const #85 = Method	#82.#84;	//  scala/collection/SetLike$class.$init$:(Lscala/collection/SetLike;)V
const #86 = Asciz	scala/collection/Set$class;
const #87 = class	#86;	//  scala/collection/Set$class
const #88 = Asciz	(Lscala/collection/Set;)V;
const #89 = NameAndType	#27:#88;//  $init$:(Lscala/collection/Set;)V
const #90 = Method	#87.#89;	//  scala/collection/Set$class.$init$:(Lscala/collection/Set;)V
const #91 = Asciz	scala/collection/generic/Growable$class;
const #92 = class	#91;	//  scala/collection/generic/Growable$class
const #93 = Asciz	(Lscala/collection/generic/Growable;)V;
const #94 = NameAndType	#27:#93;//  $init$:(Lscala/collection/generic/Growable;)V
const #95 = Method	#92.#94;	//  scala/collection/generic/Growable$class.$init$:(Lscala/collection/generic/Growable;)V
const #96 = Asciz	scala/collection/mutable/Builder$class;
const #97 = class	#96;	//  scala/collection/mutable/Builder$class
const #98 = Asciz	(Lscala/collection/mutable/Builder;)V;
const #99 = NameAndType	#27:#98;//  $init$:(Lscala/collection/mutable/Builder;)V
const #100 = Method	#97.#99;	//  scala/collection/mutable/Builder$class.$init$:(Lscala/collection/mutable/Builder;)V
const #101 = Asciz	scala/collection/generic/Shrinkable$class;
const #102 = class	#101;	//  scala/collection/generic/Shrinkable$class
const #103 = Asciz	(Lscala/collection/generic/Shrinkable;)V;
const #104 = NameAndType	#27:#103;//  $init$:(Lscala/collection/generic/Shrinkable;)V
const #105 = Method	#102.#104;	//  scala/collection/generic/Shrinkable$class.$init$:(Lscala/collection/generic/Shrinkable;)V
const #106 = Asciz	scala/collection/mutable/Cloneable$class;
const #107 = class	#106;	//  scala/collection/mutable/Cloneable$class
const #108 = Asciz	(Lscala/collection/mutable/Cloneable;)V;
const #109 = NameAndType	#27:#108;//  $init$:(Lscala/collection/mutable/Cloneable;)V
const #110 = Method	#107.#109;	//  scala/collection/mutable/Cloneable$class.$init$:(Lscala/collection/mutable/Cloneable;)V
const #111 = Asciz	scala/collection/mutable/SetLike$class;
const #112 = class	#111;	//  scala/collection/mutable/SetLike$class
const #113 = Asciz	(Lscala/collection/mutable/SetLike;)V;
const #114 = NameAndType	#27:#113;//  $init$:(Lscala/collection/mutable/SetLike;)V
const #115 = Method	#112.#114;	//  scala/collection/mutable/SetLike$class.$init$:(Lscala/collection/mutable/SetLike;)V
const #116 = Asciz	scala/collection/mutable/Set$class;
const #117 = class	#116;	//  scala/collection/mutable/Set$class
const #118 = Asciz	(Lscala/collection/mutable/Set;)V;
const #119 = NameAndType	#27:#118;//  $init$:(Lscala/collection/mutable/Set;)V
const #120 = Method	#117.#119;	//  scala/collection/mutable/Set$class.$init$:(Lscala/collection/mutable/Set;)V
const #121 = Asciz	scala/collection/BitSetLike$class;
const #122 = class	#121;	//  scala/collection/BitSetLike$class
const #123 = Asciz	(Lscala/collection/BitSetLike;)V;
const #124 = NameAndType	#27:#123;//  $init$:(Lscala/collection/BitSetLike;)V
const #125 = Method	#122.#124;	//  scala/collection/BitSetLike$class.$init$:(Lscala/collection/BitSetLike;)V
const #126 = Asciz	scala/collection/BitSet$class;
const #127 = class	#126;	//  scala/collection/BitSet$class
const #128 = Asciz	(Lscala/collection/BitSet;)V;
const #129 = NameAndType	#27:#128;//  $init$:(Lscala/collection/BitSet;)V
const #130 = Method	#127.#129;	//  scala/collection/BitSet$class.$init$:(Lscala/collection/BitSet;)V
const #131 = Asciz	this;
const #132 = Asciz	Lscala/collection/mutable/BitSet;;
const #133 = Asciz	LocalVariableTable;
const #134 = Asciz	empty;
const #135 = Asciz	()Lscala/collection/BitSet;;
const #136 = Asciz	()Lscala/collection/mutable/BitSet;;
const #137 = NameAndType	#134:#136;//  empty:()Lscala/collection/mutable/BitSet;
const #138 = Method	#11.#137;	//  scala/collection/mutable/BitSet.empty:()Lscala/collection/mutable/BitSet;
const #139 = Asciz	()Lscala/collection/Set;;
const #140 = Asciz	()Lscala/collection/BitSetLike;;
const #141 = Asciz	()Lscala/collection/SetLike;;
const #142 = Asciz	fromArray;
const #143 = Asciz	([J)Lscala/collection/BitSetLike;;
const #144 = Asciz	([J)Lscala/collection/mutable/BitSet;;
const #145 = NameAndType	#142:#144;//  fromArray:([J)Lscala/collection/mutable/BitSet;
const #146 = Method	#11.#145;	//  scala/collection/mutable/BitSet.fromArray:([J)Lscala/collection/mutable/BitSet;
const #147 = Asciz	add;
const #148 = Asciz	(Ljava/lang/Object;)Z;
const #149 = Asciz	scala/runtime/BoxesRunTime;
const #150 = class	#149;	//  scala/runtime/BoxesRunTime
const #151 = Asciz	unboxToInt;
const #152 = Asciz	(Ljava/lang/Object;)I;
const #153 = NameAndType	#151:#152;//  unboxToInt:(Ljava/lang/Object;)I
const #154 = Method	#150.#153;	//  scala/runtime/BoxesRunTime.unboxToInt:(Ljava/lang/Object;)I
const #155 = Asciz	(I)Z;
const #156 = NameAndType	#147:#155;//  add:(I)Z
const #157 = Method	#11.#156;	//  scala/collection/mutable/BitSet.add:(I)Z
const #158 = Asciz	elem;
const #159 = Asciz	Ljava/lang/Object;;
const #160 = Asciz	remove;
const #161 = NameAndType	#160:#155;//  remove:(I)Z
const #162 = Method	#11.#161;	//  scala/collection/mutable/BitSet.remove:(I)Z
const #163 = Asciz	$plus$eq;
const #164 = Asciz	(Ljava/lang/Object;)Lscala/collection/mutable/SetLike;;
const #165 = Asciz	(I)Lscala/collection/mutable/BitSet;;
const #166 = NameAndType	#163:#165;//  $plus$eq:(I)Lscala/collection/mutable/BitSet;
const #167 = Method	#11.#166;	//  scala/collection/mutable/BitSet.$plus$eq:(I)Lscala/collection/mutable/BitSet;
const #168 = Asciz	(Ljava/lang/Object;)Lscala/collection/mutable/Builder;;
const #169 = Asciz	(Ljava/lang/Object;)Lscala/collection/generic/Growable;;
const #170 = Asciz	$minus$eq;
const #171 = NameAndType	#170:#165;//  $minus$eq:(I)Lscala/collection/mutable/BitSet;
const #172 = Method	#11.#171;	//  scala/collection/mutable/BitSet.$minus$eq:(I)Lscala/collection/mutable/BitSet;
const #173 = Asciz	(Ljava/lang/Object;)Lscala/collection/generic/Shrinkable;;
const #174 = Asciz	clone;
const #175 = Asciz	()Lscala/collection/mutable/Set;;
const #176 = NameAndType	#174:#136;//  clone:()Lscala/collection/mutable/BitSet;
const #177 = Method	#11.#176;	//  scala/collection/mutable/BitSet.clone:()Lscala/collection/mutable/BitSet;
const #178 = Asciz	()Ljava/lang/Object;;
const #179 = Asciz	iterator;
const #180 = Asciz	()Lscala/collection/Iterator;;
const #181 = Asciz	scala/collection/BitSetLike;
const #182 = class	#181;	//  scala/collection/BitSetLike
const #183 = NameAndType	#179:#178;//  iterator:()Ljava/lang/Object;
const #184 = InterfaceMethod	#182.#183;	//  scala/collection/BitSetLike.iterator:()Ljava/lang/Object;
const #185 = Asciz	scala/collection/Iterator;
const #186 = class	#185;	//  scala/collection/Iterator
const #187 = Asciz	contains;
const #188 = NameAndType	#187:#155;//  contains:(I)Z
const #189 = InterfaceMethod	#182.#188;	//  scala/collection/BitSetLike.contains:(I)Z
const #190 = Asciz	result;
const #191 = Asciz	scala/collection/mutable/SetLike;
const #192 = class	#191;	//  scala/collection/mutable/SetLike
const #193 = Asciz	()Lscala/collection/mutable/SetLike;;
const #194 = NameAndType	#190:#193;//  result:()Lscala/collection/mutable/SetLike;
const #195 = InterfaceMethod	#192.#194;	//  scala/collection/mutable/SetLike.result:()Lscala/collection/mutable/SetLike;
const #196 = Asciz	$plus;
const #197 = Asciz	(Ljava/lang/Object;)Lscala/collection/SetLike;;
const #198 = NameAndType	#196:#164;//  $plus:(Ljava/lang/Object;)Lscala/collection/mutable/SetLike;
const #199 = InterfaceMethod	#192.#198;	//  scala/collection/mutable/SetLike.$plus:(Ljava/lang/Object;)Lscala/collection/mutable/SetLike;
const #200 = Asciz	(Ljava/lang/Object;)Lscala/collection/generic/Addable;;
const #201 = Asciz	(Ljava/lang/Object;Ljava/lang/Object;Lscala/collection/Seq;)Lscala/collection/generic/Addable;;
const #202 = Asciz	(Ljava/lang/Object;Ljava/lang/Object;Lscala/collection/Seq;)Lscala/collection/mutable/SetLike;;
const #203 = NameAndType	#196:#202;//  $plus:(Ljava/lang/Object;Ljava/lang/Object;Lscala/collection/Seq;)Lscala/collection/mutable/SetLike;
const #204 = InterfaceMethod	#192.#203;	//  scala/collection/mutable/SetLike.$plus:(Ljava/lang/Object;Ljava/lang/Object;Lscala/collection/Seq;)Lscala/collection/mutable/SetLike;
const #205 = Asciz	elem1;
const #206 = Asciz	elem2;
const #207 = Asciz	Lscala/collection/Seq;;
const #208 = Asciz	$plus$plus;
const #209 = Asciz	(Lscala/collection/Traversable;)Lscala/collection/generic/Addable;;
const #210 = Asciz	(Lscala/collection/Traversable;)Lscala/collection/mutable/SetLike;;
const #211 = NameAndType	#208:#210;//  $plus$plus:(Lscala/collection/Traversable;)Lscala/collection/mutable/SetLike;
const #212 = InterfaceMethod	#192.#211;	//  scala/collection/mutable/SetLike.$plus$plus:(Lscala/collection/Traversable;)Lscala/collection/mutable/SetLike;
const #213 = Asciz	Lscala/collection/Traversable;;
const #214 = Asciz	(Lscala/collection/Iterator;)Lscala/collection/generic/Addable;;
const #215 = Asciz	(Lscala/collection/Iterator;)Lscala/collection/mutable/SetLike;;
const #216 = NameAndType	#208:#215;//  $plus$plus:(Lscala/collection/Iterator;)Lscala/collection/mutable/SetLike;
const #217 = InterfaceMethod	#192.#216;	//  scala/collection/mutable/SetLike.$plus$plus:(Lscala/collection/Iterator;)Lscala/collection/mutable/SetLike;
const #218 = Asciz	iter;
const #219 = Asciz	Lscala/collection/Iterator;;
const #220 = Asciz	$minus;
const #221 = NameAndType	#220:#164;//  $minus:(Ljava/lang/Object;)Lscala/collection/mutable/SetLike;
const #222 = InterfaceMethod	#192.#221;	//  scala/collection/mutable/SetLike.$minus:(Ljava/lang/Object;)Lscala/collection/mutable/SetLike;
const #223 = Asciz	(Ljava/lang/Object;)Lscala/collection/generic/Subtractable;;
const #224 = Asciz	(Ljava/lang/Object;Ljava/lang/Object;Lscala/collection/Seq;)Lscala/collection/generic/Subtractable;;
const #225 = NameAndType	#220:#202;//  $minus:(Ljava/lang/Object;Ljava/lang/Object;Lscala/collection/Seq;)Lscala/collection/mutable/SetLike;
const #226 = InterfaceMethod	#192.#225;	//  scala/collection/mutable/SetLike.$minus:(Ljava/lang/Object;Ljava/lang/Object;Lscala/collection/Seq;)Lscala/collection/mutable/SetLike;
const #227 = Asciz	$minus$minus;
const #228 = Asciz	(Lscala/collection/Traversable;)Lscala/collection/generic/Subtractable;;
const #229 = NameAndType	#227:#210;//  $minus$minus:(Lscala/collection/Traversable;)Lscala/collection/mutable/SetLike;
const #230 = InterfaceMethod	#192.#229;	//  scala/collection/mutable/SetLike.$minus$minus:(Lscala/collection/Traversable;)Lscala/collection/mutable/SetLike;
const #231 = Asciz	(Lscala/collection/Iterator;)Lscala/collection/generic/Subtractable;;
const #232 = NameAndType	#227:#215;//  $minus$minus:(Lscala/collection/Iterator;)Lscala/collection/mutable/SetLike;
const #233 = InterfaceMethod	#192.#232;	//  scala/collection/mutable/SetLike.$minus$minus:(Lscala/collection/Iterator;)Lscala/collection/mutable/SetLike;
const #234 = Asciz	apply;
const #235 = Asciz	(Ljava/lang/Object;)Ljava/lang/Object;;
const #236 = Asciz	scala/collection/SetLike;
const #237 = class	#236;	//  scala/collection/SetLike
const #238 = NameAndType	#234:#148;//  apply:(Ljava/lang/Object;)Z
const #239 = InterfaceMethod	#237.#238;	//  scala/collection/SetLike.apply:(Ljava/lang/Object;)Z
const #240 = Asciz	boxToBoolean;
const #241 = Asciz	(Z)Ljava/lang/Boolean;;
const #242 = NameAndType	#240:#241;//  boxToBoolean:(Z)Ljava/lang/Boolean;
const #243 = Method	#150.#242;	//  scala/runtime/BoxesRunTime.boxToBoolean:(Z)Ljava/lang/Boolean;
const #244 = Asciz	v1;
const #245 = Asciz	thisCollection;
const #246 = Asciz	()Lscala/collection/Traversable;;
const #247 = Asciz	scala/collection/IterableLike;
const #248 = class	#247;	//  scala/collection/IterableLike
const #249 = Asciz	()Lscala/collection/Iterable;;
const #250 = NameAndType	#245:#249;//  thisCollection:()Lscala/collection/Iterable;
const #251 = InterfaceMethod	#248.#250;	//  scala/collection/IterableLike.thisCollection:()Lscala/collection/Iterable;
const #252 = Asciz	toCollection;
const #253 = Asciz	(Ljava/lang/Object;)Lscala/collection/Traversable;;
const #254 = Asciz	(Ljava/lang/Object;)Lscala/collection/Iterable;;
const #255 = NameAndType	#252:#254;//  toCollection:(Ljava/lang/Object;)Lscala/collection/Iterable;
const #256 = InterfaceMethod	#248.#255;	//  scala/collection/IterableLike.toCollection:(Ljava/lang/Object;)Lscala/collection/Iterable;
const #257 = Asciz	repr;
const #258 = Asciz	view;
const #259 = Asciz	(II)Lscala/collection/TraversableView;;
const #260 = Asciz	(II)Lscala/collection/IterableView;;
const #261 = NameAndType	#258:#260;//  view:(II)Lscala/collection/IterableView;
const #262 = InterfaceMethod	#248.#261;	//  scala/collection/IterableLike.view:(II)Lscala/collection/IterableView;
const #263 = Asciz	from;
const #264 = Asciz	I;
const #265 = Asciz	until;
const #266 = Asciz	()Lscala/collection/generic/Subtractable;;
const #267 = Asciz	scala/collection/TraversableLike;
const #268 = class	#267;	//  scala/collection/TraversableLike
const #269 = NameAndType	#257:#178;//  repr:()Ljava/lang/Object;
const #270 = InterfaceMethod	#268.#269;	//  scala/collection/TraversableLike.repr:()Ljava/lang/Object;
const #271 = Asciz	scala/collection/generic/Subtractable;
const #272 = class	#271;	//  scala/collection/generic/Subtractable
const #273 = Asciz	()Lscala/collection/generic/Addable;;
const #274 = Asciz	scala/collection/generic/Addable;
const #275 = class	#274;	//  scala/collection/generic/Addable
const #276 = Asciz	()[J;
const #277 = NameAndType	#14:#276;//  elems:()[J
const #278 = Method	#11.#277;	//  scala/collection/mutable/BitSet.elems:()[J
const #279 = Asciz	scala/Array$;
const #280 = class	#279;	//  scala/Array$
const #281 = Asciz	MODULE$;
const #282 = Asciz	Lscala/Array$;;
const #283 = NameAndType	#281:#282;//  MODULE$:Lscala/Array$;
const #284 = Field	#280.#283;	//  scala/Array$.MODULE$:Lscala/Array$;
const #285 = Asciz	copy;
const #286 = Asciz	(Ljava/lang/Object;ILjava/lang/Object;II)V;
const #287 = NameAndType	#285:#286;//  copy:(Ljava/lang/Object;ILjava/lang/Object;II)V
const #288 = Method	#280.#287;	//  scala/Array$.copy:(Ljava/lang/Object;ILjava/lang/Object;II)V
const #289 = NameAndType	#16:#17;//  "<init>":([J)V
const #290 = Method	#11.#289;	//  scala/collection/mutable/BitSet."<init>":([J)V
const #291 = Asciz	elems1;
const #292 = Asciz	toImmutable;
const #293 = Asciz	()Lscala/collection/immutable/BitSet;;
const #294 = Asciz	scala/collection/immutable/BitSet$;
const #295 = class	#294;	//  scala/collection/immutable/BitSet$
const #296 = Asciz	Lscala/collection/immutable/BitSet$;;
const #297 = NameAndType	#281:#296;//  MODULE$:Lscala/collection/immutable/BitSet$;
const #298 = Field	#295.#297;	//  scala/collection/immutable/BitSet$.MODULE$:Lscala/collection/immutable/BitSet$;
const #299 = Asciz	([J)Lscala/collection/immutable/BitSet;;
const #300 = NameAndType	#142:#299;//  fromArray:([J)Lscala/collection/immutable/BitSet;
const #301 = Method	#295.#300;	//  scala/collection/immutable/BitSet$.fromArray:([J)Lscala/collection/immutable/BitSet;
const #302 = Asciz	clear;
const #303 = Asciz	elems_$eq;
const #304 = NameAndType	#303:#17;//  elems_$eq:([J)V
const #305 = Method	#11.#304;	//  scala/collection/mutable/BitSet.elems_$eq:([J)V
const #306 = Asciz	scala/Predef$;
const #307 = class	#306;	//  scala/Predef$
const #308 = Asciz	Lscala/Predef$;;
const #309 = NameAndType	#281:#308;//  MODULE$:Lscala/Predef$;
const #310 = Field	#307.#309;	//  scala/Predef$.MODULE$:Lscala/Predef$;
const #311 = Asciz	require;
const #312 = Asciz	(Z)V;
const #313 = NameAndType	#311:#312;//  require:(Z)V
const #314 = Method	#307.#313;	//  scala/Predef$.require:(Z)V
const #315 = Asciz	scala/collection/BitSetLike$;
const #316 = class	#315;	//  scala/collection/BitSetLike$
const #317 = Asciz	Lscala/collection/BitSetLike$;;
const #318 = NameAndType	#281:#317;//  MODULE$:Lscala/collection/BitSetLike$;
const #319 = Field	#316.#318;	//  scala/collection/BitSetLike$.MODULE$:Lscala/collection/BitSetLike$;
const #320 = Asciz	LogWL;
const #321 = Asciz	()I;
const #322 = NameAndType	#320:#321;//  LogWL:()I
const #323 = Method	#316.#322;	//  scala/collection/BitSetLike$.LogWL:()I
const #324 = Asciz	word;
const #325 = Asciz	(I)J;
const #326 = NameAndType	#324:#325;//  word:(I)J
const #327 = Method	#11.#326;	//  scala/collection/mutable/BitSet.word:(I)J
const #328 = long	-1l;
const #330 = Asciz	updateWord;
const #331 = Asciz	(IJ)V;
const #332 = NameAndType	#330:#331;//  updateWord:(IJ)V
const #333 = Method	#11.#332;	//  scala/collection/mutable/BitSet.updateWord:(IJ)V
const #334 = Asciz	idx;
const #335 = Asciz	words;
const #336 = Asciz	nwords;
const #337 = NameAndType	#336:#321;//  nwords:()I
const #338 = Method	#11.#337;	//  scala/collection/mutable/BitSet.nwords:()I
const #339 = Asciz	w;
const #340 = Asciz	newlen;
const #341 = Asciz	(I)V;
const #342 = NameAndType	#16:#341;//  "<init>":(I)V
const #343 = Method	#11.#342;	//  scala/collection/mutable/BitSet."<init>":(I)V
const #344 = int	63;
const #345 = int	6;
const #346 = Asciz	intWrapper;
const #347 = Asciz	(I)Lscala/runtime/RichInt;;
const #348 = NameAndType	#346:#347;//  intWrapper:(I)Lscala/runtime/RichInt;
const #349 = Method	#307.#348;	//  scala/Predef$.intWrapper:(I)Lscala/runtime/RichInt;
const #350 = Asciz	scala/runtime/RichInt;
const #351 = class	#350;	//  scala/runtime/RichInt
const #352 = Asciz	max;
const #353 = Asciz	(I)I;
const #354 = NameAndType	#352:#353;//  max:(I)I
const #355 = Method	#351.#354;	//  scala/runtime/RichInt.max:(I)I
const #356 = Asciz	initSize;
const #357 = Asciz	scala/collection/mutable/BitSet$;
const #358 = class	#357;	//  scala/collection/mutable/BitSet$
const #359 = Asciz	Lscala/collection/mutable/BitSet$;;
const #360 = NameAndType	#281:#359;//  MODULE$:Lscala/collection/mutable/BitSet$;
const #361 = Field	#358.#360;	//  scala/collection/mutable/BitSet$.MODULE$:Lscala/collection/mutable/BitSet$;
const #362 = Method	#358.#137;	//  scala/collection/mutable/BitSet$.empty:()Lscala/collection/mutable/BitSet;
const #363 = Asciz	withFilter;
const #364 = Asciz	(Lscala/Function1;)Lscala/collection/TraversableLike$WithFilter;;
const #365 = Asciz	(Lscala/collection/TraversableLike;Lscala/Function1;)Lscala/collection/TraversableLike$WithFilter;;
const #366 = NameAndType	#363:#365;//  withFilter:(Lscala/collection/TraversableLike;Lscala/Function1;)Lscala/collection/TraversableLike$WithFilter;
const #367 = Method	#26.#366;	//  scala/collection/TraversableLike$class.withFilter:(Lscala/collection/TraversableLike;Lscala/Function1;)Lscala/collection/TraversableLike$WithFilter;
const #368 = Asciz	p;
const #369 = Asciz	Lscala/Function1;;
const #370 = Asciz	Signature;
const #371 = Asciz	addString;
const #372 = Asciz	(Lscala/collection/mutable/StringBuilder;)Lscala/collection/mutable/StringBuilder;;
const #373 = Asciz	(Lscala/collection/TraversableLike;Lscala/collection/mutable/StringBuilder;)Lscala/collection/mutable/StringBuilder;;
const #374 = NameAndType	#371:#373;//  addString:(Lscala/collection/TraversableLike;Lscala/collection/mutable/StringBuilder;)Lscala/collection/mutable/StringBuilder;
const #375 = Method	#26.#374;	//  scala/collection/TraversableLike$class.addString:(Lscala/collection/TraversableLike;Lscala/collection/mutable/StringBuilder;)Lscala/collection/mutable/StringBuilder;
const #376 = Asciz	b;
const #377 = Asciz	Lscala/collection/mutable/StringBuilder;;
const #378 = Asciz	(Lscala/collection/mutable/StringBuilder;Ljava/lang/String;)Lscala/collection/mutable/StringBuilder;;
const #379 = Asciz	(Lscala/collection/TraversableLike;Lscala/collection/mutable/StringBuilder;Ljava/lang/String;)Lscala/collection/mutable/StringBuilder;;
const #380 = NameAndType	#371:#379;//  addString:(Lscala/collection/TraversableLike;Lscala/collection/mutable/StringBuilder;Ljava/lang/String;)Lscala/collection/mutable/StringBuilder;
const #381 = Method	#26.#380;	//  scala/collection/TraversableLike$class.addString:(Lscala/collection/TraversableLike;Lscala/collection/mutable/StringBuilder;Ljava/lang/String;)Lscala/collection/mutable/StringBuilder;
const #382 = Asciz	sep;
const #383 = Asciz	Ljava/lang/String;;
const #384 = Asciz	mkString;
const #385 = Asciz	()Ljava/lang/String;;
const #386 = Asciz	(Lscala/collection/TraversableLike;)Ljava/lang/String;;
const #387 = NameAndType	#384:#386;//  mkString:(Lscala/collection/TraversableLike;)Ljava/lang/String;
const #388 = Method	#26.#387;	//  scala/collection/TraversableLike$class.mkString:(Lscala/collection/TraversableLike;)Ljava/lang/String;
const #389 = Asciz	(Ljava/lang/String;)Ljava/lang/String;;
const #390 = Asciz	(Lscala/collection/TraversableLike;Ljava/lang/String;)Ljava/lang/String;;
const #391 = NameAndType	#384:#390;//  mkString:(Lscala/collection/TraversableLike;Ljava/lang/String;)Ljava/lang/String;
const #392 = Method	#26.#391;	//  scala/collection/TraversableLike$class.mkString:(Lscala/collection/TraversableLike;Ljava/lang/String;)Ljava/lang/String;
const #393 = Asciz	(Ljava/lang/String;Ljava/lang/String;Ljava/lang/String;)Ljava/lang/String;;
const #394 = Asciz	(Lscala/collection/TraversableLike;Ljava/lang/String;Ljava/lang/String;Ljava/lang/String;)Ljava/lang/String;;
const #395 = NameAndType	#384:#394;//  mkString:(Lscala/collection/TraversableLike;Ljava/lang/String;Ljava/lang/String;Ljava/lang/String;)Ljava/lang/String;
const #396 = Method	#26.#395;	//  scala/collection/TraversableLike$class.mkString:(Lscala/collection/TraversableLike;Ljava/lang/String;Ljava/lang/String;Ljava/lang/String;)Ljava/lang/String;
const #397 = Asciz	start;
const #398 = Asciz	end;
const #399 = Asciz	toSet;
const #400 = Asciz	()Lscala/collection/immutable/Set;;
const #401 = Asciz	(Lscala/collection/TraversableLike;)Lscala/collection/immutable/Set;;
const #402 = NameAndType	#399:#401;//  toSet:(Lscala/collection/TraversableLike;)Lscala/collection/immutable/Set;
const #403 = Method	#26.#402;	//  scala/collection/TraversableLike$class.toSet:(Lscala/collection/TraversableLike;)Lscala/collection/immutable/Set;
const #404 = Asciz	toIndexedSeq;
const #405 = Asciz	()Lscala/collection/mutable/IndexedSeq;;
const #406 = Asciz	(Lscala/collection/TraversableLike;)Lscala/collection/mutable/IndexedSeq;;
const #407 = NameAndType	#404:#406;//  toIndexedSeq:(Lscala/collection/TraversableLike;)Lscala/collection/mutable/IndexedSeq;
const #408 = Method	#26.#407;	//  scala/collection/TraversableLike$class.toIndexedSeq:(Lscala/collection/TraversableLike;)Lscala/collection/mutable/IndexedSeq;
const #409 = Asciz	toSeq;
const #410 = Asciz	()Lscala/collection/Seq;;
const #411 = Asciz	(Lscala/collection/TraversableLike;)Lscala/collection/Seq;;
const #412 = NameAndType	#409:#411;//  toSeq:(Lscala/collection/TraversableLike;)Lscala/collection/Seq;
const #413 = Method	#26.#412;	//  scala/collection/TraversableLike$class.toSeq:(Lscala/collection/TraversableLike;)Lscala/collection/Seq;
const #414 = Asciz	toList;
const #415 = Asciz	()Lscala/collection/immutable/List;;
const #416 = Asciz	(Lscala/collection/TraversableLike;)Lscala/collection/immutable/List;;
const #417 = NameAndType	#414:#416;//  toList:(Lscala/collection/TraversableLike;)Lscala/collection/immutable/List;
const #418 = Method	#26.#417;	//  scala/collection/TraversableLike$class.toList:(Lscala/collection/TraversableLike;)Lscala/collection/immutable/List;
const #419 = Asciz	toArray;
const #420 = Asciz	(Lscala/reflect/ClassManifest;)Ljava/lang/Object;;
const #421 = Asciz	(Lscala/collection/TraversableLike;Lscala/reflect/ClassManifest;)Ljava/lang/Object;;
const #422 = NameAndType	#419:#421;//  toArray:(Lscala/collection/TraversableLike;Lscala/reflect/ClassManifest;)Ljava/lang/Object;
const #423 = Method	#26.#422;	//  scala/collection/TraversableLike$class.toArray:(Lscala/collection/TraversableLike;Lscala/reflect/ClassManifest;)Ljava/lang/Object;
const #424 = Asciz	evidence$1;
const #425 = Asciz	Lscala/reflect/ClassManifest;;
const #426 = Asciz	copyToArray;
const #427 = Asciz	(Ljava/lang/Object;)V;
const #428 = Asciz	(Lscala/collection/TraversableLike;Ljava/lang/Object;)V;
const #429 = NameAndType	#426:#428;//  copyToArray:(Lscala/collection/TraversableLike;Ljava/lang/Object;)V
const #430 = Method	#26.#429;	//  scala/collection/TraversableLike$class.copyToArray:(Lscala/collection/TraversableLike;Ljava/lang/Object;)V
const #431 = Asciz	xs;
const #432 = Asciz	(Ljava/lang/Object;I)V;
const #433 = Asciz	(Lscala/collection/TraversableLike;Ljava/lang/Object;I)V;
const #434 = NameAndType	#426:#433;//  copyToArray:(Lscala/collection/TraversableLike;Ljava/lang/Object;I)V
const #435 = Method	#26.#434;	//  scala/collection/TraversableLike$class.copyToArray:(Lscala/collection/TraversableLike;Ljava/lang/Object;I)V
const #436 = Asciz	copyToBuffer;
const #437 = Asciz	(Lscala/collection/mutable/Buffer;)V;
const #438 = Asciz	(Lscala/collection/TraversableLike;Lscala/collection/mutable/Buffer;)V;
const #439 = NameAndType	#436:#438;//  copyToBuffer:(Lscala/collection/TraversableLike;Lscala/collection/mutable/Buffer;)V
const #440 = Method	#26.#439;	//  scala/collection/TraversableLike$class.copyToBuffer:(Lscala/collection/TraversableLike;Lscala/collection/mutable/Buffer;)V
const #441 = Asciz	dest;
const #442 = Asciz	Lscala/collection/mutable/Buffer;;
const #443 = Asciz	splitAt;
const #444 = Asciz	(I)Lscala/Tuple2;;
const #445 = Asciz	(Lscala/collection/TraversableLike;I)Lscala/Tuple2;;
const #446 = NameAndType	#443:#445;//  splitAt:(Lscala/collection/TraversableLike;I)Lscala/Tuple2;
const #447 = Method	#26.#446;	//  scala/collection/TraversableLike$class.splitAt:(Lscala/collection/TraversableLike;I)Lscala/Tuple2;
const #448 = Asciz	n;
const #449 = Asciz	span;
const #450 = Asciz	(Lscala/Function1;)Lscala/Tuple2;;
const #451 = Asciz	(Lscala/collection/TraversableLike;Lscala/Function1;)Lscala/Tuple2;;
const #452 = NameAndType	#449:#451;//  span:(Lscala/collection/TraversableLike;Lscala/Function1;)Lscala/Tuple2;
const #453 = Method	#26.#452;	//  scala/collection/TraversableLike$class.span:(Lscala/collection/TraversableLike;Lscala/Function1;)Lscala/Tuple2;
const #454 = Asciz	dropWhile;
const #455 = Asciz	(Lscala/Function1;)Ljava/lang/Object;;
const #456 = Asciz	(Lscala/collection/TraversableLike;Lscala/Function1;)Ljava/lang/Object;;
const #457 = NameAndType	#454:#456;//  dropWhile:(Lscala/collection/TraversableLike;Lscala/Function1;)Ljava/lang/Object;
const #458 = Method	#26.#457;	//  scala/collection/TraversableLike$class.dropWhile:(Lscala/collection/TraversableLike;Lscala/Function1;)Ljava/lang/Object;
const #459 = Asciz	drop;
const #460 = Asciz	(I)Ljava/lang/Object;;
const #461 = Asciz	(Lscala/collection/TraversableLike;I)Ljava/lang/Object;;
const #462 = NameAndType	#459:#461;//  drop:(Lscala/collection/TraversableLike;I)Ljava/lang/Object;
const #463 = Method	#26.#462;	//  scala/collection/TraversableLike$class.drop:(Lscala/collection/TraversableLike;I)Ljava/lang/Object;
const #464 = Asciz	init;
const #465 = Asciz	(Lscala/collection/TraversableLike;)Ljava/lang/Object;;
const #466 = NameAndType	#464:#465;//  init:(Lscala/collection/TraversableLike;)Ljava/lang/Object;
const #467 = Method	#26.#466;	//  scala/collection/TraversableLike$class.init:(Lscala/collection/TraversableLike;)Ljava/lang/Object;
const #468 = Asciz	lastOption;
const #469 = Asciz	()Lscala/Option;;
const #470 = Asciz	(Lscala/collection/TraversableLike;)Lscala/Option;;
const #471 = NameAndType	#468:#470;//  lastOption:(Lscala/collection/TraversableLike;)Lscala/Option;
const #472 = Method	#26.#471;	//  scala/collection/TraversableLike$class.lastOption:(Lscala/collection/TraversableLike;)Lscala/Option;
const #473 = Asciz	last;
const #474 = NameAndType	#473:#465;//  last:(Lscala/collection/TraversableLike;)Ljava/lang/Object;
const #475 = Method	#26.#474;	//  scala/collection/TraversableLike$class.last:(Lscala/collection/TraversableLike;)Ljava/lang/Object;
const #476 = Asciz	tail;
const #477 = NameAndType	#476:#465;//  tail:(Lscala/collection/TraversableLike;)Ljava/lang/Object;
const #478 = Method	#26.#477;	//  scala/collection/TraversableLike$class.tail:(Lscala/collection/TraversableLike;)Ljava/lang/Object;
const #479 = Asciz	headOption;
const #480 = NameAndType	#479:#470;//  headOption:(Lscala/collection/TraversableLike;)Lscala/Option;
const #481 = Method	#26.#480;	//  scala/collection/TraversableLike$class.headOption:(Lscala/collection/TraversableLike;)Lscala/Option;
const #482 = Asciz	(Lscala/math/Ordering;)Ljava/lang/Object;;
const #483 = Asciz	(Lscala/collection/TraversableLike;Lscala/math/Ordering;)Ljava/lang/Object;;
const #484 = NameAndType	#352:#483;//  max:(Lscala/collection/TraversableLike;Lscala/math/Ordering;)Ljava/lang/Object;
const #485 = Method	#26.#484;	//  scala/collection/TraversableLike$class.max:(Lscala/collection/TraversableLike;Lscala/math/Ordering;)Ljava/lang/Object;
const #486 = Asciz	cmp;
const #487 = Asciz	Lscala/math/Ordering;;
const #488 = Asciz	min;
const #489 = NameAndType	#488:#483;//  min:(Lscala/collection/TraversableLike;Lscala/math/Ordering;)Ljava/lang/Object;
const #490 = Method	#26.#489;	//  scala/collection/TraversableLike$class.min:(Lscala/collection/TraversableLike;Lscala/math/Ordering;)Ljava/lang/Object;
const #491 = Asciz	product;
const #492 = Asciz	(Lscala/math/Numeric;)Ljava/lang/Object;;
const #493 = Asciz	(Lscala/collection/TraversableLike;Lscala/math/Numeric;)Ljava/lang/Object;;
const #494 = NameAndType	#491:#493;//  product:(Lscala/collection/TraversableLike;Lscala/math/Numeric;)Ljava/lang/Object;
const #495 = Method	#26.#494;	//  scala/collection/TraversableLike$class.product:(Lscala/collection/TraversableLike;Lscala/math/Numeric;)Ljava/lang/Object;
const #496 = Asciz	num;
const #497 = Asciz	Lscala/math/Numeric;;
const #498 = Asciz	sum;
const #499 = NameAndType	#498:#493;//  sum:(Lscala/collection/TraversableLike;Lscala/math/Numeric;)Ljava/lang/Object;
const #500 = Method	#26.#499;	//  scala/collection/TraversableLike$class.sum:(Lscala/collection/TraversableLike;Lscala/math/Numeric;)Ljava/lang/Object;
const #501 = Asciz	reduceRightOption;
const #502 = Asciz	(Lscala/Function2;)Lscala/Option;;
const #503 = Asciz	(Lscala/collection/TraversableLike;Lscala/Function2;)Lscala/Option;;
const #504 = NameAndType	#501:#503;//  reduceRightOption:(Lscala/collection/TraversableLike;Lscala/Function2;)Lscala/Option;
const #505 = Method	#26.#504;	//  scala/collection/TraversableLike$class.reduceRightOption:(Lscala/collection/TraversableLike;Lscala/Function2;)Lscala/Option;
const #506 = Asciz	op;
const #507 = Asciz	Lscala/Function2;;
const #508 = Asciz	reduceLeftOption;
const #509 = NameAndType	#508:#503;//  reduceLeftOption:(Lscala/collection/TraversableLike;Lscala/Function2;)Lscala/Option;
const #510 = Method	#26.#509;	//  scala/collection/TraversableLike$class.reduceLeftOption:(Lscala/collection/TraversableLike;Lscala/Function2;)Lscala/Option;
const #511 = Asciz	reduceLeft;
const #512 = Asciz	(Lscala/Function2;)Ljava/lang/Object;;
const #513 = Asciz	(Lscala/collection/TraversableLike;Lscala/Function2;)Ljava/lang/Object;;
const #514 = NameAndType	#511:#513;//  reduceLeft:(Lscala/collection/TraversableLike;Lscala/Function2;)Ljava/lang/Object;
const #515 = Method	#26.#514;	//  scala/collection/TraversableLike$class.reduceLeft:(Lscala/collection/TraversableLike;Lscala/Function2;)Ljava/lang/Object;
const #516 = Asciz	$colon$bslash;
const #517 = Asciz	(Ljava/lang/Object;Lscala/Function2;)Ljava/lang/Object;;
const #518 = Asciz	(Lscala/collection/TraversableLike;Ljava/lang/Object;Lscala/Function2;)Ljava/lang/Object;;
const #519 = NameAndType	#516:#518;//  $colon$bslash:(Lscala/collection/TraversableLike;Ljava/lang/Object;Lscala/Function2;)Ljava/lang/Object;
const #520 = Method	#26.#519;	//  scala/collection/TraversableLike$class.$colon$bslash:(Lscala/collection/TraversableLike;Ljava/lang/Object;Lscala/Function2;)Ljava/lang/Object;
const #521 = Asciz	z;
const #522 = Asciz	$div$colon;
const #523 = NameAndType	#522:#518;//  $div$colon:(Lscala/collection/TraversableLike;Ljava/lang/Object;Lscala/Function2;)Ljava/lang/Object;
const #524 = Method	#26.#523;	//  scala/collection/TraversableLike$class.$div$colon:(Lscala/collection/TraversableLike;Ljava/lang/Object;Lscala/Function2;)Ljava/lang/Object;
const #525 = Asciz	foldLeft;
const #526 = NameAndType	#525:#518;//  foldLeft:(Lscala/collection/TraversableLike;Ljava/lang/Object;Lscala/Function2;)Ljava/lang/Object;
const #527 = Method	#26.#526;	//  scala/collection/TraversableLike$class.foldLeft:(Lscala/collection/TraversableLike;Ljava/lang/Object;Lscala/Function2;)Ljava/lang/Object;
const #528 = Asciz	count;
const #529 = Asciz	(Lscala/Function1;)I;
const #530 = Asciz	(Lscala/collection/TraversableLike;Lscala/Function1;)I;
const #531 = NameAndType	#528:#530;//  count:(Lscala/collection/TraversableLike;Lscala/Function1;)I
const #532 = Method	#26.#531;	//  scala/collection/TraversableLike$class.count:(Lscala/collection/TraversableLike;Lscala/Function1;)I
const #533 = Asciz	groupBy;
const #534 = Asciz	(Lscala/Function1;)Lscala/collection/Map;;
const #535 = Asciz	(Lscala/collection/TraversableLike;Lscala/Function1;)Lscala/collection/Map;;
const #536 = NameAndType	#533:#535;//  groupBy:(Lscala/collection/TraversableLike;Lscala/Function1;)Lscala/collection/Map;
const #537 = Method	#26.#536;	//  scala/collection/TraversableLike$class.groupBy:(Lscala/collection/TraversableLike;Lscala/Function1;)Lscala/collection/Map;
const #538 = Asciz	f;
const #539 = Asciz	partition;
const #540 = NameAndType	#539:#451;//  partition:(Lscala/collection/TraversableLike;Lscala/Function1;)Lscala/Tuple2;
const #541 = Method	#26.#540;	//  scala/collection/TraversableLike$class.partition:(Lscala/collection/TraversableLike;Lscala/Function1;)Lscala/Tuple2;
const #542 = Asciz	partialMap;
const #543 = Asciz	(Lscala/PartialFunction;Lscala/collection/generic/CanBuildFrom;)Ljava/lang/Object;;
const #544 = Asciz	(Lscala/collection/TraversableLike;Lscala/PartialFunction;Lscala/collection/generic/CanBuildFrom;)Ljava/lang/Object;;
const #545 = NameAndType	#542:#544;//  partialMap:(Lscala/collection/TraversableLike;Lscala/PartialFunction;Lscala/collection/generic/CanBuildFrom;)Ljava/lang/Object;
const #546 = Method	#26.#545;	//  scala/collection/TraversableLike$class.partialMap:(Lscala/collection/TraversableLike;Lscala/PartialFunction;Lscala/collection/generic/CanBuildFrom;)Ljava/lang/Object;
const #547 = Asciz	pf;
const #548 = Asciz	Lscala/PartialFunction;;
const #549 = Asciz	bf;
const #550 = Asciz	Lscala/collection/generic/CanBuildFrom;;
const #551 = Asciz	filterNot;
const #552 = NameAndType	#551:#456;//  filterNot:(Lscala/collection/TraversableLike;Lscala/Function1;)Ljava/lang/Object;
const #553 = Method	#26.#552;	//  scala/collection/TraversableLike$class.filterNot:(Lscala/collection/TraversableLike;Lscala/Function1;)Ljava/lang/Object;
const #554 = Asciz	filter;
const #555 = NameAndType	#554:#456;//  filter:(Lscala/collection/TraversableLike;Lscala/Function1;)Ljava/lang/Object;
const #556 = Method	#26.#555;	//  scala/collection/TraversableLike$class.filter:(Lscala/collection/TraversableLike;Lscala/Function1;)Ljava/lang/Object;
const #557 = Asciz	flatMap;
const #558 = Asciz	(Lscala/Function1;Lscala/collection/generic/CanBuildFrom;)Ljava/lang/Object;;
const #559 = Asciz	(Lscala/collection/TraversableLike;Lscala/Function1;Lscala/collection/generic/CanBuildFrom;)Ljava/lang/Object;;
const #560 = NameAndType	#557:#559;//  flatMap:(Lscala/collection/TraversableLike;Lscala/Function1;Lscala/collection/generic/CanBuildFrom;)Ljava/lang/Object;
const #561 = Method	#26.#560;	//  scala/collection/TraversableLike$class.flatMap:(Lscala/collection/TraversableLike;Lscala/Function1;Lscala/collection/generic/CanBuildFrom;)Ljava/lang/Object;
const #562 = Asciz	map;
const #563 = NameAndType	#562:#559;//  map:(Lscala/collection/TraversableLike;Lscala/Function1;Lscala/collection/generic/CanBuildFrom;)Ljava/lang/Object;
const #564 = Method	#26.#563;	//  scala/collection/TraversableLike$class.map:(Lscala/collection/TraversableLike;Lscala/Function1;Lscala/collection/generic/CanBuildFrom;)Ljava/lang/Object;
const #565 = Asciz	(Lscala/collection/Iterator;Lscala/collection/generic/CanBuildFrom;)Ljava/lang/Object;;
const #566 = Asciz	(Lscala/collection/TraversableLike;Lscala/collection/Iterator;Lscala/collection/generic/CanBuildFrom;)Ljava/lang/Object;;
const #567 = NameAndType	#208:#566;//  $plus$plus:(Lscala/collection/TraversableLike;Lscala/collection/Iterator;Lscala/collection/generic/CanBuildFrom;)Ljava/lang/Object;
const #568 = Method	#26.#567;	//  scala/collection/TraversableLike$class.$plus$plus:(Lscala/collection/TraversableLike;Lscala/collection/Iterator;Lscala/collection/generic/CanBuildFrom;)Ljava/lang/Object;
const #569 = Asciz	that;
const #570 = Asciz	(Lscala/collection/Traversable;Lscala/collection/generic/CanBuildFrom;)Ljava/lang/Object;;
const #571 = Asciz	(Lscala/collection/TraversableLike;Lscala/collection/Traversable;Lscala/collection/generic/CanBuildFrom;)Ljava/lang/Object;;
const #572 = NameAndType	#208:#571;//  $plus$plus:(Lscala/collection/TraversableLike;Lscala/collection/Traversable;Lscala/collection/generic/CanBuildFrom;)Ljava/lang/Object;
const #573 = Method	#26.#572;	//  scala/collection/TraversableLike$class.$plus$plus:(Lscala/collection/TraversableLike;Lscala/collection/Traversable;Lscala/collection/generic/CanBuildFrom;)Ljava/lang/Object;
const #574 = Asciz	hasDefiniteSize;
const #575 = Asciz	()Z;
const #576 = Asciz	(Lscala/collection/TraversableLike;)Z;
const #577 = NameAndType	#574:#576;//  hasDefiniteSize:(Lscala/collection/TraversableLike;)Z
const #578 = Method	#26.#577;	//  scala/collection/TraversableLike$class.hasDefiniteSize:(Lscala/collection/TraversableLike;)Z
const #579 = Asciz	nonEmpty;
const #580 = NameAndType	#579:#576;//  nonEmpty:(Lscala/collection/TraversableLike;)Z
const #581 = Method	#26.#580;	//  scala/collection/TraversableLike$class.nonEmpty:(Lscala/collection/TraversableLike;)Z
const #582 = NameAndType	#257:#465;//  repr:(Lscala/collection/TraversableLike;)Ljava/lang/Object;
const #583 = Method	#26.#582;	//  scala/collection/TraversableLike$class.repr:(Lscala/collection/TraversableLike;)Ljava/lang/Object;
const #584 = Asciz	transpose;
const #585 = Asciz	(Lscala/Function1;)Lscala/collection/Traversable;;
const #586 = Asciz	(Lscala/collection/generic/GenericTraversableTemplate;Lscala/Function1;)Lscala/collection/Traversable;;
const #587 = NameAndType	#584:#586;//  transpose:(Lscala/collection/generic/GenericTraversableTemplate;Lscala/Function1;)Lscala/collection/Traversable;
const #588 = Method	#32.#587;	//  scala/collection/generic/GenericTraversableTemplate$class.transpose:(Lscala/collection/generic/GenericTraversableTemplate;Lscala/Function1;)Lscala/collection/Traversable;
const #589 = Asciz	asTraversable;
const #590 = Asciz	flatten;
const #591 = NameAndType	#590:#586;//  flatten:(Lscala/collection/generic/GenericTraversableTemplate;Lscala/Function1;)Lscala/collection/Traversable;
const #592 = Method	#32.#591;	//  scala/collection/generic/GenericTraversableTemplate$class.flatten:(Lscala/collection/generic/GenericTraversableTemplate;Lscala/Function1;)Lscala/collection/Traversable;
const #593 = Asciz	unzip;
const #594 = Asciz	(Lscala/collection/generic/GenericTraversableTemplate;Lscala/Function1;)Lscala/Tuple2;;
const #595 = NameAndType	#593:#594;//  unzip:(Lscala/collection/generic/GenericTraversableTemplate;Lscala/Function1;)Lscala/Tuple2;
const #596 = Method	#32.#595;	//  scala/collection/generic/GenericTraversableTemplate$class.unzip:(Lscala/collection/generic/GenericTraversableTemplate;Lscala/Function1;)Lscala/Tuple2;
const #597 = Asciz	asPair;
const #598 = Asciz	genericBuilder;
const #599 = Asciz	()Lscala/collection/mutable/Builder;;
const #600 = Asciz	(Lscala/collection/generic/GenericTraversableTemplate;)Lscala/collection/mutable/Builder;;
const #601 = NameAndType	#598:#600;//  genericBuilder:(Lscala/collection/generic/GenericTraversableTemplate;)Lscala/collection/mutable/Builder;
const #602 = Method	#32.#601;	//  scala/collection/generic/GenericTraversableTemplate$class.genericBuilder:(Lscala/collection/generic/GenericTraversableTemplate;)Lscala/collection/mutable/Builder;
const #603 = Asciz	projection;
const #604 = Asciz	(Lscala/collection/IterableLike;)Ljava/lang/Object;;
const #605 = NameAndType	#603:#604;//  projection:(Lscala/collection/IterableLike;)Ljava/lang/Object;
const #606 = Method	#47.#605;	//  scala/collection/IterableLike$class.projection:(Lscala/collection/IterableLike;)Ljava/lang/Object;
const #607 = Asciz	Deprecated;
const #608 = Asciz	firstOption;
const #609 = Asciz	(Lscala/collection/IterableLike;)Lscala/Option;;
const #610 = NameAndType	#608:#609;//  firstOption:(Lscala/collection/IterableLike;)Lscala/Option;
const #611 = Method	#47.#610;	//  scala/collection/IterableLike$class.firstOption:(Lscala/collection/IterableLike;)Lscala/Option;
const #612 = Asciz	first;
const #613 = NameAndType	#612:#604;//  first:(Lscala/collection/IterableLike;)Ljava/lang/Object;
const #614 = Method	#47.#613;	//  scala/collection/IterableLike$class.first:(Lscala/collection/IterableLike;)Ljava/lang/Object;
const #615 = Asciz	(Lscala/collection/IterableLike;II)Lscala/collection/IterableView;;
const #616 = NameAndType	#258:#615;//  view:(Lscala/collection/IterableLike;II)Lscala/collection/IterableView;
const #617 = Method	#47.#616;	//  scala/collection/IterableLike$class.view:(Lscala/collection/IterableLike;II)Lscala/collection/IterableView;
const #618 = NameAndType	#258:#604;//  view:(Lscala/collection/IterableLike;)Ljava/lang/Object;
const #619 = Method	#47.#618;	//  scala/collection/IterableLike$class.view:(Lscala/collection/IterableLike;)Ljava/lang/Object;
const #620 = Asciz	canEqual;
const #621 = Asciz	(Lscala/collection/IterableLike;Ljava/lang/Object;)Z;
const #622 = NameAndType	#620:#621;//  canEqual:(Lscala/collection/IterableLike;Ljava/lang/Object;)Z
const #623 = Method	#47.#622;	//  scala/collection/IterableLike$class.canEqual:(Lscala/collection/IterableLike;Ljava/lang/Object;)Z
const #624 = Asciz	toStream;
const #625 = Asciz	()Lscala/collection/immutable/Stream;;
const #626 = Asciz	(Lscala/collection/IterableLike;)Lscala/collection/immutable/Stream;;
const #627 = NameAndType	#624:#626;//  toStream:(Lscala/collection/IterableLike;)Lscala/collection/immutable/Stream;
const #628 = Method	#47.#627;	//  scala/collection/IterableLike$class.toStream:(Lscala/collection/IterableLike;)Lscala/collection/immutable/Stream;
const #629 = Asciz	sameElements;
const #630 = Asciz	(Lscala/collection/Iterable;)Z;
const #631 = Asciz	(Lscala/collection/IterableLike;Lscala/collection/Iterable;)Z;
const #632 = NameAndType	#629:#631;//  sameElements:(Lscala/collection/IterableLike;Lscala/collection/Iterable;)Z
const #633 = Method	#47.#632;	//  scala/collection/IterableLike$class.sameElements:(Lscala/collection/IterableLike;Lscala/collection/Iterable;)Z
const #634 = Asciz	Lscala/collection/Iterable;;
const #635 = Asciz	zipWithIndex;
const #636 = Asciz	(Lscala/collection/generic/CanBuildFrom;)Ljava/lang/Object;;
const #637 = Asciz	(Lscala/collection/IterableLike;Lscala/collection/generic/CanBuildFrom;)Ljava/lang/Object;;
const #638 = NameAndType	#635:#637;//  zipWithIndex:(Lscala/collection/IterableLike;Lscala/collection/generic/CanBuildFrom;)Ljava/lang/Object;
const #639 = Method	#47.#638;	//  scala/collection/IterableLike$class.zipWithIndex:(Lscala/collection/IterableLike;Lscala/collection/generic/CanBuildFrom;)Ljava/lang/Object;
const #640 = Asciz	zipAll;
const #641 = Asciz	(Lscala/collection/Iterable;Ljava/lang/Object;Ljava/lang/Object;Lscala/collection/generic/CanBuildFrom;)Ljava/lang/Object;;
const #642 = Asciz	(Lscala/collection/IterableLike;Lscala/collection/Iterable;Ljava/lang/Object;Ljava/lang/Object;Lscala/collection/generic/CanBuildFrom;)Ljava/lang/Object;;
const #643 = NameAndType	#640:#642;//  zipAll:(Lscala/collection/IterableLike;Lscala/collection/Iterable;Ljava/lang/Object;Ljava/lang/Object;Lscala/collection/generic/CanBuildFrom;)Ljava/lang/Object;
const #644 = Method	#47.#643;	//  scala/collection/IterableLike$class.zipAll:(Lscala/collection/IterableLike;Lscala/collection/Iterable;Ljava/lang/Object;Ljava/lang/Object;Lscala/collection/generic/CanBuildFrom;)Ljava/lang/Object;
const #645 = Asciz	thisElem;
const #646 = Asciz	thatElem;
const #647 = Asciz	zip;
const #648 = Asciz	(Lscala/collection/Iterable;Lscala/collection/generic/CanBuildFrom;)Ljava/lang/Object;;
const #649 = Asciz	(Lscala/collection/IterableLike;Lscala/collection/Iterable;Lscala/collection/generic/CanBuildFrom;)Ljava/lang/Object;;
const #650 = NameAndType	#647:#649;//  zip:(Lscala/collection/IterableLike;Lscala/collection/Iterable;Lscala/collection/generic/CanBuildFrom;)Ljava/lang/Object;
const #651 = Method	#47.#650;	//  scala/collection/IterableLike$class.zip:(Lscala/collection/IterableLike;Lscala/collection/Iterable;Lscala/collection/generic/CanBuildFrom;)Ljava/lang/Object;
const #652 = Asciz	(Ljava/lang/Object;II)V;
const #653 = Asciz	(Lscala/collection/IterableLike;Ljava/lang/Object;II)V;
const #654 = NameAndType	#426:#653;//  copyToArray:(Lscala/collection/IterableLike;Ljava/lang/Object;II)V
const #655 = Method	#47.#654;	//  scala/collection/IterableLike$class.copyToArray:(Lscala/collection/IterableLike;Ljava/lang/Object;II)V
const #656 = Asciz	len;
const #657 = Asciz	dropRight;
const #658 = Asciz	(Lscala/collection/IterableLike;I)Ljava/lang/Object;;
const #659 = NameAndType	#657:#658;//  dropRight:(Lscala/collection/IterableLike;I)Ljava/lang/Object;
const #660 = Method	#47.#659;	//  scala/collection/IterableLike$class.dropRight:(Lscala/collection/IterableLike;I)Ljava/lang/Object;
const #661 = Asciz	takeRight;
const #662 = NameAndType	#661:#658;//  takeRight:(Lscala/collection/IterableLike;I)Ljava/lang/Object;
const #663 = Method	#47.#662;	//  scala/collection/IterableLike$class.takeRight:(Lscala/collection/IterableLike;I)Ljava/lang/Object;
const #664 = Asciz	takeWhile;
const #665 = Asciz	(Lscala/collection/IterableLike;Lscala/Function1;)Ljava/lang/Object;;
const #666 = NameAndType	#664:#665;//  takeWhile:(Lscala/collection/IterableLike;Lscala/Function1;)Ljava/lang/Object;
const #667 = Method	#47.#666;	//  scala/collection/IterableLike$class.takeWhile:(Lscala/collection/IterableLike;Lscala/Function1;)Ljava/lang/Object;
const #668 = Asciz	slice;
const #669 = Asciz	(II)Ljava/lang/Object;;
const #670 = Asciz	(Lscala/collection/IterableLike;II)Ljava/lang/Object;;
const #671 = NameAndType	#668:#670;//  slice:(Lscala/collection/IterableLike;II)Ljava/lang/Object;
const #672 = Method	#47.#671;	//  scala/collection/IterableLike$class.slice:(Lscala/collection/IterableLike;II)Ljava/lang/Object;
const #673 = Asciz	take;
const #674 = NameAndType	#673:#658;//  take:(Lscala/collection/IterableLike;I)Ljava/lang/Object;
const #675 = Method	#47.#674;	//  scala/collection/IterableLike$class.take:(Lscala/collection/IterableLike;I)Ljava/lang/Object;
const #676 = Asciz	head;
const #677 = NameAndType	#676:#604;//  head:(Lscala/collection/IterableLike;)Ljava/lang/Object;
const #678 = Method	#47.#677;	//  scala/collection/IterableLike$class.head:(Lscala/collection/IterableLike;)Ljava/lang/Object;
const #679 = Asciz	toIterable;
const #680 = Asciz	(Lscala/collection/IterableLike;)Lscala/collection/Iterable;;
const #681 = NameAndType	#679:#680;//  toIterable:(Lscala/collection/IterableLike;)Lscala/collection/Iterable;
const #682 = Method	#47.#681;	//  scala/collection/IterableLike$class.toIterable:(Lscala/collection/IterableLike;)Lscala/collection/Iterable;
const #683 = Asciz	reduceRight;
const #684 = Asciz	(Lscala/collection/IterableLike;Lscala/Function2;)Ljava/lang/Object;;
const #685 = NameAndType	#683:#684;//  reduceRight:(Lscala/collection/IterableLike;Lscala/Function2;)Ljava/lang/Object;
const #686 = Method	#47.#685;	//  scala/collection/IterableLike$class.reduceRight:(Lscala/collection/IterableLike;Lscala/Function2;)Ljava/lang/Object;
const #687 = Asciz	foldRight;
const #688 = Asciz	(Lscala/collection/IterableLike;Ljava/lang/Object;Lscala/Function2;)Ljava/lang/Object;;
const #689 = NameAndType	#687:#688;//  foldRight:(Lscala/collection/IterableLike;Ljava/lang/Object;Lscala/Function2;)Ljava/lang/Object;
const #690 = Method	#47.#689;	//  scala/collection/IterableLike$class.foldRight:(Lscala/collection/IterableLike;Ljava/lang/Object;Lscala/Function2;)Ljava/lang/Object;
const #691 = Asciz	find;
const #692 = Asciz	(Lscala/Function1;)Lscala/Option;;
const #693 = Asciz	(Lscala/collection/IterableLike;Lscala/Function1;)Lscala/Option;;
const #694 = NameAndType	#691:#693;//  find:(Lscala/collection/IterableLike;Lscala/Function1;)Lscala/Option;
const #695 = Method	#47.#694;	//  scala/collection/IterableLike$class.find:(Lscala/collection/IterableLike;Lscala/Function1;)Lscala/Option;
const #696 = Asciz	exists;
const #697 = Asciz	(Lscala/Function1;)Z;
const #698 = Asciz	(Lscala/collection/IterableLike;Lscala/Function1;)Z;
const #699 = NameAndType	#696:#698;//  exists:(Lscala/collection/IterableLike;Lscala/Function1;)Z
const #700 = Method	#47.#699;	//  scala/collection/IterableLike$class.exists:(Lscala/collection/IterableLike;Lscala/Function1;)Z
const #701 = Asciz	forall;
const #702 = NameAndType	#701:#698;//  forall:(Lscala/collection/IterableLike;Lscala/Function1;)Z
const #703 = Method	#47.#702;	//  scala/collection/IterableLike$class.forall:(Lscala/collection/IterableLike;Lscala/Function1;)Z
const #704 = Asciz	elements;
const #705 = Asciz	(Lscala/collection/IterableLike;)Lscala/collection/Iterator;;
const #706 = NameAndType	#704:#705;//  elements:(Lscala/collection/IterableLike;)Lscala/collection/Iterator;
const #707 = Method	#47.#706;	//  scala/collection/IterableLike$class.elements:(Lscala/collection/IterableLike;)Lscala/collection/Iterator;
const #708 = Asciz	(Lscala/collection/IterableLike;Ljava/lang/Object;)Lscala/collection/Iterable;;
const #709 = NameAndType	#252:#708;//  toCollection:(Lscala/collection/IterableLike;Ljava/lang/Object;)Lscala/collection/Iterable;
const #710 = Method	#47.#709;	//  scala/collection/IterableLike$class.toCollection:(Lscala/collection/IterableLike;Ljava/lang/Object;)Lscala/collection/Iterable;
const #711 = NameAndType	#245:#680;//  thisCollection:(Lscala/collection/IterableLike;)Lscala/collection/Iterable;
const #712 = Method	#47.#711;	//  scala/collection/IterableLike$class.thisCollection:(Lscala/collection/IterableLike;)Lscala/collection/Iterable;
const #713 = Asciz	andThen;
const #714 = Asciz	(Lscala/Function1;)Lscala/Function1;;
const #715 = Asciz	(Lscala/Function1;Lscala/Function1;)Lscala/Function1;;
const #716 = NameAndType	#713:#715;//  andThen:(Lscala/Function1;Lscala/Function1;)Lscala/Function1;
const #717 = Method	#62.#716;	//  scala/Function1$class.andThen:(Lscala/Function1;Lscala/Function1;)Lscala/Function1;
const #718 = Asciz	g;
const #719 = Asciz	compose;
const #720 = NameAndType	#719:#715;//  compose:(Lscala/Function1;Lscala/Function1;)Lscala/Function1;
const #721 = Method	#62.#720;	//  scala/Function1$class.compose:(Lscala/Function1;Lscala/Function1;)Lscala/Function1;
const #722 = Asciz	equals;
const #723 = Asciz	(Lscala/collection/SetLike;Ljava/lang/Object;)Z;
const #724 = NameAndType	#722:#723;//  equals:(Lscala/collection/SetLike;Ljava/lang/Object;)Z
const #725 = Method	#82.#724;	//  scala/collection/SetLike$class.equals:(Lscala/collection/SetLike;Ljava/lang/Object;)Z
const #726 = Asciz	hashCode;
const #727 = Asciz	(Lscala/collection/SetLike;)I;
const #728 = NameAndType	#726:#727;//  hashCode:(Lscala/collection/SetLike;)I
const #729 = Method	#82.#728;	//  scala/collection/SetLike$class.hashCode:(Lscala/collection/SetLike;)I
const #730 = Asciz	toString;
const #731 = Asciz	(Lscala/collection/SetLike;)Ljava/lang/String;;
const #732 = NameAndType	#730:#731;//  toString:(Lscala/collection/SetLike;)Ljava/lang/String;
const #733 = Method	#82.#732;	//  scala/collection/SetLike$class.toString:(Lscala/collection/SetLike;)Ljava/lang/String;
const #734 = Asciz	subsetOf;
const #735 = Asciz	(Lscala/collection/Set;)Z;
const #736 = Asciz	(Lscala/collection/SetLike;Lscala/collection/Set;)Z;
const #737 = NameAndType	#734:#736;//  subsetOf:(Lscala/collection/SetLike;Lscala/collection/Set;)Z
const #738 = Method	#82.#737;	//  scala/collection/SetLike$class.subsetOf:(Lscala/collection/SetLike;Lscala/collection/Set;)Z
const #739 = Asciz	Lscala/collection/Set;;
const #740 = Asciz	$amp$tilde;
const #741 = Asciz	(Lscala/collection/Set;)Lscala/collection/SetLike;;
const #742 = Asciz	(Lscala/collection/SetLike;Lscala/collection/Set;)Lscala/collection/SetLike;;
const #743 = NameAndType	#740:#742;//  $amp$tilde:(Lscala/collection/SetLike;Lscala/collection/Set;)Lscala/collection/SetLike;
const #744 = Method	#82.#743;	//  scala/collection/SetLike$class.$amp$tilde:(Lscala/collection/SetLike;Lscala/collection/Set;)Lscala/collection/SetLike;
const #745 = Asciz	diff;
const #746 = NameAndType	#745:#742;//  diff:(Lscala/collection/SetLike;Lscala/collection/Set;)Lscala/collection/SetLike;
const #747 = Method	#82.#746;	//  scala/collection/SetLike$class.diff:(Lscala/collection/SetLike;Lscala/collection/Set;)Lscala/collection/SetLike;
const #748 = Asciz	$bar;
const #749 = NameAndType	#748:#742;//  $bar:(Lscala/collection/SetLike;Lscala/collection/Set;)Lscala/collection/SetLike;
const #750 = Method	#82.#749;	//  scala/collection/SetLike$class.$bar:(Lscala/collection/SetLike;Lscala/collection/Set;)Lscala/collection/SetLike;
const #751 = Asciz	union;
const #752 = NameAndType	#751:#742;//  union:(Lscala/collection/SetLike;Lscala/collection/Set;)Lscala/collection/SetLike;
const #753 = Method	#82.#752;	//  scala/collection/SetLike$class.union:(Lscala/collection/SetLike;Lscala/collection/Set;)Lscala/collection/SetLike;
const #754 = Asciz	$times$times;
const #755 = NameAndType	#754:#742;//  $times$times:(Lscala/collection/SetLike;Lscala/collection/Set;)Lscala/collection/SetLike;
const #756 = Method	#82.#755;	//  scala/collection/SetLike$class.$times$times:(Lscala/collection/SetLike;Lscala/collection/Set;)Lscala/collection/SetLike;
const #757 = Asciz	$amp;
const #758 = NameAndType	#757:#742;//  $amp:(Lscala/collection/SetLike;Lscala/collection/Set;)Lscala/collection/SetLike;
const #759 = Method	#82.#758;	//  scala/collection/SetLike$class.$amp:(Lscala/collection/SetLike;Lscala/collection/Set;)Lscala/collection/SetLike;
const #760 = Asciz	intersect;
const #761 = NameAndType	#760:#742;//  intersect:(Lscala/collection/SetLike;Lscala/collection/Set;)Lscala/collection/SetLike;
const #762 = Method	#82.#761;	//  scala/collection/SetLike$class.intersect:(Lscala/collection/SetLike;Lscala/collection/Set;)Lscala/collection/SetLike;
const #763 = NameAndType	#234:#723;//  apply:(Lscala/collection/SetLike;Ljava/lang/Object;)Z
const #764 = Method	#82.#763;	//  scala/collection/SetLike$class.apply:(Lscala/collection/SetLike;Ljava/lang/Object;)Z
const #765 = Asciz	isEmpty;
const #766 = Asciz	(Lscala/collection/SetLike;)Z;
const #767 = NameAndType	#765:#766;//  isEmpty:(Lscala/collection/SetLike;)Z
const #768 = Method	#82.#767;	//  scala/collection/SetLike$class.isEmpty:(Lscala/collection/SetLike;)Z
const #769 = Asciz	$plus$plus$eq;
const #770 = Asciz	(Lscala/collection/Traversable;)Lscala/collection/generic/Growable;;
const #771 = Asciz	(Lscala/collection/generic/Growable;Lscala/collection/Traversable;)Lscala/collection/generic/Growable;;
const #772 = NameAndType	#769:#771;//  $plus$plus$eq:(Lscala/collection/generic/Growable;Lscala/collection/Traversable;)Lscala/collection/generic/Growable;
const #773 = Method	#92.#772;	//  scala/collection/generic/Growable$class.$plus$plus$eq:(Lscala/collection/generic/Growable;Lscala/collection/Traversable;)Lscala/collection/generic/Growable;
const #774 = Asciz	(Lscala/collection/Iterator;)Lscala/collection/generic/Growable;;
const #775 = Asciz	(Lscala/collection/generic/Growable;Lscala/collection/Iterator;)Lscala/collection/generic/Growable;;
const #776 = NameAndType	#769:#775;//  $plus$plus$eq:(Lscala/collection/generic/Growable;Lscala/collection/Iterator;)Lscala/collection/generic/Growable;
const #777 = Method	#92.#776;	//  scala/collection/generic/Growable$class.$plus$plus$eq:(Lscala/collection/generic/Growable;Lscala/collection/Iterator;)Lscala/collection/generic/Growable;
const #778 = Asciz	(Ljava/lang/Object;Ljava/lang/Object;Lscala/collection/Seq;)Lscala/collection/generic/Growable;;
const #779 = Asciz	(Lscala/collection/generic/Growable;Ljava/lang/Object;Ljava/lang/Object;Lscala/collection/Seq;)Lscala/collection/generic/Growable;;
const #780 = NameAndType	#163:#779;//  $plus$eq:(Lscala/collection/generic/Growable;Ljava/lang/Object;Ljava/lang/Object;Lscala/collection/Seq;)Lscala/collection/generic/Growable;
const #781 = Method	#92.#780;	//  scala/collection/generic/Growable$class.$plus$eq:(Lscala/collection/generic/Growable;Ljava/lang/Object;Ljava/lang/Object;Lscala/collection/Seq;)Lscala/collection/generic/Growable;
const #782 = Asciz	mapResult;
const #783 = Asciz	(Lscala/Function1;)Lscala/collection/mutable/Builder;;
const #784 = Asciz	(Lscala/collection/mutable/Builder;Lscala/Function1;)Lscala/collection/mutable/Builder;;
const #785 = NameAndType	#782:#784;//  mapResult:(Lscala/collection/mutable/Builder;Lscala/Function1;)Lscala/collection/mutable/Builder;
const #786 = Method	#97.#785;	//  scala/collection/mutable/Builder$class.mapResult:(Lscala/collection/mutable/Builder;Lscala/Function1;)Lscala/collection/mutable/Builder;
const #787 = Asciz	sizeHint;
const #788 = Asciz	(Lscala/collection/mutable/Builder;I)V;
const #789 = NameAndType	#787:#788;//  sizeHint:(Lscala/collection/mutable/Builder;I)V
const #790 = Method	#97.#789;	//  scala/collection/mutable/Builder$class.sizeHint:(Lscala/collection/mutable/Builder;I)V
const #791 = Asciz	size;
const #792 = Asciz	$minus$minus$eq;
const #793 = Asciz	(Lscala/collection/Traversable;)Lscala/collection/generic/Shrinkable;;
const #794 = Asciz	(Lscala/collection/generic/Shrinkable;Lscala/collection/Traversable;)Lscala/collection/generic/Shrinkable;;
const #795 = NameAndType	#792:#794;//  $minus$minus$eq:(Lscala/collection/generic/Shrinkable;Lscala/collection/Traversable;)Lscala/collection/generic/Shrinkable;
const #796 = Method	#102.#795;	//  scala/collection/generic/Shrinkable$class.$minus$minus$eq:(Lscala/collection/generic/Shrinkable;Lscala/collection/Traversable;)Lscala/collection/generic/Shrinkable;
const #797 = Asciz	(Lscala/collection/Iterator;)Lscala/collection/generic/Shrinkable;;
const #798 = Asciz	(Lscala/collection/generic/Shrinkable;Lscala/collection/Iterator;)Lscala/collection/generic/Shrinkable;;
const #799 = NameAndType	#792:#798;//  $minus$minus$eq:(Lscala/collection/generic/Shrinkable;Lscala/collection/Iterator;)Lscala/collection/generic/Shrinkable;
const #800 = Method	#102.#799;	//  scala/collection/generic/Shrinkable$class.$minus$minus$eq:(Lscala/collection/generic/Shrinkable;Lscala/collection/Iterator;)Lscala/collection/generic/Shrinkable;
const #801 = Asciz	(Ljava/lang/Object;Ljava/lang/Object;Lscala/collection/Seq;)Lscala/collection/generic/Shrinkable;;
const #802 = Asciz	(Lscala/collection/generic/Shrinkable;Ljava/lang/Object;Ljava/lang/Object;Lscala/collection/Seq;)Lscala/collection/generic/Shrinkable;;
const #803 = NameAndType	#170:#802;//  $minus$eq:(Lscala/collection/generic/Shrinkable;Ljava/lang/Object;Ljava/lang/Object;Lscala/collection/Seq;)Lscala/collection/generic/Shrinkable;
const #804 = Method	#102.#803;	//  scala/collection/generic/Shrinkable$class.$minus$eq:(Lscala/collection/generic/Shrinkable;Ljava/lang/Object;Ljava/lang/Object;Lscala/collection/Seq;)Lscala/collection/generic/Shrinkable;
const #805 = Asciz	scala$collection$mutable$Cloneable$$super$clone;
const #806 = NameAndType	#174:#178;//  clone:()Ljava/lang/Object;
const #807 = Method	#22.#806;	//  java/lang/Object.clone:()Ljava/lang/Object;
const #808 = Asciz	$less$less;
const #809 = Asciz	(Lscala/collection/script/Message;)V;
const #810 = Asciz	(Lscala/collection/mutable/SetLike;Lscala/collection/script/Message;)V;
const #811 = NameAndType	#808:#810;//  $less$less:(Lscala/collection/mutable/SetLike;Lscala/collection/script/Message;)V
const #812 = Method	#112.#811;	//  scala/collection/mutable/SetLike$class.$less$less:(Lscala/collection/mutable/SetLike;Lscala/collection/script/Message;)V
const #813 = Asciz	cmd;
const #814 = Asciz	Lscala/collection/script/Message;;
const #815 = Asciz	(Lscala/collection/mutable/SetLike;Lscala/collection/Iterator;)Lscala/collection/mutable/SetLike;;
const #816 = NameAndType	#227:#815;//  $minus$minus:(Lscala/collection/mutable/SetLike;Lscala/collection/Iterator;)Lscala/collection/mutable/SetLike;
const #817 = Method	#112.#816;	//  scala/collection/mutable/SetLike$class.$minus$minus:(Lscala/collection/mutable/SetLike;Lscala/collection/Iterator;)Lscala/collection/mutable/SetLike;
const #818 = Asciz	(Lscala/collection/mutable/SetLike;Lscala/collection/Traversable;)Lscala/collection/mutable/SetLike;;
const #819 = NameAndType	#227:#818;//  $minus$minus:(Lscala/collection/mutable/SetLike;Lscala/collection/Traversable;)Lscala/collection/mutable/SetLike;
const #820 = Method	#112.#819;	//  scala/collection/mutable/SetLike$class.$minus$minus:(Lscala/collection/mutable/SetLike;Lscala/collection/Traversable;)Lscala/collection/mutable/SetLike;
const #821 = Asciz	(Lscala/collection/mutable/SetLike;Ljava/lang/Object;Ljava/lang/Object;Lscala/collection/Seq;)Lscala/collection/mutable/SetLike;;
const #822 = NameAndType	#220:#821;//  $minus:(Lscala/collection/mutable/SetLike;Ljava/lang/Object;Ljava/lang/Object;Lscala/collection/Seq;)Lscala/collection/mutable/SetLike;
const #823 = Method	#112.#822;	//  scala/collection/mutable/SetLike$class.$minus:(Lscala/collection/mutable/SetLike;Ljava/lang/Object;Ljava/lang/Object;Lscala/collection/Seq;)Lscala/collection/mutable/SetLike;
const #824 = Asciz	(Lscala/collection/mutable/SetLike;Ljava/lang/Object;)Lscala/collection/mutable/SetLike;;
const #825 = NameAndType	#220:#824;//  $minus:(Lscala/collection/mutable/SetLike;Ljava/lang/Object;)Lscala/collection/mutable/SetLike;
const #826 = Method	#112.#825;	//  scala/collection/mutable/SetLike$class.$minus:(Lscala/collection/mutable/SetLike;Ljava/lang/Object;)Lscala/collection/mutable/SetLike;
const #827 = NameAndType	#208:#815;//  $plus$plus:(Lscala/collection/mutable/SetLike;Lscala/collection/Iterator;)Lscala/collection/mutable/SetLike;
const #828 = Method	#112.#827;	//  scala/collection/mutable/SetLike$class.$plus$plus:(Lscala/collection/mutable/SetLike;Lscala/collection/Iterator;)Lscala/collection/mutable/SetLike;
const #829 = NameAndType	#208:#818;//  $plus$plus:(Lscala/collection/mutable/SetLike;Lscala/collection/Traversable;)Lscala/collection/mutable/SetLike;
const #830 = Method	#112.#829;	//  scala/collection/mutable/SetLike$class.$plus$plus:(Lscala/collection/mutable/SetLike;Lscala/collection/Traversable;)Lscala/collection/mutable/SetLike;
const #831 = NameAndType	#196:#821;//  $plus:(Lscala/collection/mutable/SetLike;Ljava/lang/Object;Ljava/lang/Object;Lscala/collection/Seq;)Lscala/collection/mutable/SetLike;
const #832 = Method	#112.#831;	//  scala/collection/mutable/SetLike$class.$plus:(Lscala/collection/mutable/SetLike;Ljava/lang/Object;Ljava/lang/Object;Lscala/collection/Seq;)Lscala/collection/mutable/SetLike;
const #833 = NameAndType	#196:#824;//  $plus:(Lscala/collection/mutable/SetLike;Ljava/lang/Object;)Lscala/collection/mutable/SetLike;
const #834 = Method	#112.#833;	//  scala/collection/mutable/SetLike$class.$plus:(Lscala/collection/mutable/SetLike;Ljava/lang/Object;)Lscala/collection/mutable/SetLike;
const #835 = Asciz	(Lscala/collection/mutable/SetLike;)Lscala/collection/mutable/SetLike;;
const #836 = NameAndType	#190:#835;//  result:(Lscala/collection/mutable/SetLike;)Lscala/collection/mutable/SetLike;
const #837 = Method	#112.#836;	//  scala/collection/mutable/SetLike$class.result:(Lscala/collection/mutable/SetLike;)Lscala/collection/mutable/SetLike;
const #838 = Asciz	retain;
const #839 = Asciz	(Lscala/collection/mutable/SetLike;Lscala/Function1;)V;
const #840 = NameAndType	#838:#839;//  retain:(Lscala/collection/mutable/SetLike;Lscala/Function1;)V
const #841 = Method	#112.#840;	//  scala/collection/mutable/SetLike$class.retain:(Lscala/collection/mutable/SetLike;Lscala/Function1;)V
const #842 = Asciz	update;
const #843 = Asciz	(Ljava/lang/Object;Z)V;
const #844 = Asciz	(Lscala/collection/mutable/SetLike;Ljava/lang/Object;Z)V;
const #845 = NameAndType	#842:#844;//  update:(Lscala/collection/mutable/SetLike;Ljava/lang/Object;Z)V
const #846 = Method	#112.#845;	//  scala/collection/mutable/SetLike$class.update:(Lscala/collection/mutable/SetLike;Ljava/lang/Object;Z)V
const #847 = Asciz	included;
const #848 = Asciz	Z;
const #849 = Asciz	newBuilder;
const #850 = Asciz	(Lscala/collection/mutable/SetLike;)Lscala/collection/mutable/Builder;;
const #851 = NameAndType	#849:#850;//  newBuilder:(Lscala/collection/mutable/SetLike;)Lscala/collection/mutable/Builder;
const #852 = Method	#112.#851;	//  scala/collection/mutable/SetLike$class.newBuilder:(Lscala/collection/mutable/SetLike;)Lscala/collection/mutable/Builder;
const #853 = Asciz	companion;
const #854 = Asciz	()Lscala/collection/generic/GenericCompanion;;
const #855 = Asciz	(Lscala/collection/mutable/Set;)Lscala/collection/generic/GenericCompanion;;
const #856 = NameAndType	#853:#855;//  companion:(Lscala/collection/mutable/Set;)Lscala/collection/generic/GenericCompanion;
const #857 = Method	#117.#856;	//  scala/collection/mutable/Set$class.companion:(Lscala/collection/mutable/Set;)Lscala/collection/generic/GenericCompanion;
const #858 = Asciz	stringPrefix;
const #859 = Asciz	(Lscala/collection/BitSetLike;)Ljava/lang/String;;
const #860 = NameAndType	#858:#859;//  stringPrefix:(Lscala/collection/BitSetLike;)Ljava/lang/String;
const #861 = Method	#122.#860;	//  scala/collection/BitSetLike$class.stringPrefix:(Lscala/collection/BitSetLike;)Ljava/lang/String;
const #862 = Asciz	(Lscala/collection/mutable/StringBuilder;Ljava/lang/String;Ljava/lang/String;Ljava/lang/String;)Lscala/collection/mutable/StringBuilder;;
const #863 = Asciz	(Lscala/collection/BitSetLike;Lscala/collection/mutable/StringBuilder;Ljava/lang/String;Ljava/lang/String;Ljava/lang/String;)Lscala/collection/mutable/StringBuilder;;
const #864 = NameAndType	#371:#863;//  addString:(Lscala/collection/BitSetLike;Lscala/collection/mutable/StringBuilder;Ljava/lang/String;Ljava/lang/String;Ljava/lang/String;)Lscala/collection/mutable/StringBuilder;
const #865 = Method	#122.#864;	//  scala/collection/BitSetLike$class.addString:(Lscala/collection/BitSetLike;Lscala/collection/mutable/StringBuilder;Ljava/lang/String;Ljava/lang/String;Ljava/lang/String;)Lscala/collection/mutable/StringBuilder;
const #866 = Asciz	sb;
const #867 = Asciz	(Lscala/collection/BitSet;)Z;
const #868 = Asciz	(Lscala/collection/BitSetLike;Lscala/collection/BitSet;)Z;
const #869 = NameAndType	#734:#868;//  subsetOf:(Lscala/collection/BitSetLike;Lscala/collection/BitSet;)Z
const #870 = Method	#122.#869;	//  scala/collection/BitSetLike$class.subsetOf:(Lscala/collection/BitSetLike;Lscala/collection/BitSet;)Z
const #871 = Asciz	other;
const #872 = Asciz	Lscala/collection/BitSet;;
const #873 = Asciz	(Lscala/collection/BitSetLike;I)Z;
const #874 = NameAndType	#187:#873;//  contains:(Lscala/collection/BitSetLike;I)Z
const #875 = Method	#122.#874;	//  scala/collection/BitSetLike$class.contains:(Lscala/collection/BitSetLike;I)Z
const #876 = Asciz	$up;
const #877 = Asciz	(Lscala/collection/BitSet;)Lscala/collection/BitSetLike;;
const #878 = Asciz	(Lscala/collection/BitSetLike;Lscala/collection/BitSet;)Lscala/collection/BitSetLike;;
const #879 = NameAndType	#876:#878;//  $up:(Lscala/collection/BitSetLike;Lscala/collection/BitSet;)Lscala/collection/BitSetLike;
const #880 = Method	#122.#879;	//  scala/collection/BitSetLike$class.$up:(Lscala/collection/BitSetLike;Lscala/collection/BitSet;)Lscala/collection/BitSetLike;
const #881 = NameAndType	#740:#878;//  $amp$tilde:(Lscala/collection/BitSetLike;Lscala/collection/BitSet;)Lscala/collection/BitSetLike;
const #882 = Method	#122.#881;	//  scala/collection/BitSetLike$class.$amp$tilde:(Lscala/collection/BitSetLike;Lscala/collection/BitSet;)Lscala/collection/BitSetLike;
const #883 = NameAndType	#757:#878;//  $amp:(Lscala/collection/BitSetLike;Lscala/collection/BitSet;)Lscala/collection/BitSetLike;
const #884 = Method	#122.#883;	//  scala/collection/BitSetLike$class.$amp:(Lscala/collection/BitSetLike;Lscala/collection/BitSet;)Lscala/collection/BitSetLike;
const #885 = NameAndType	#748:#878;//  $bar:(Lscala/collection/BitSetLike;Lscala/collection/BitSet;)Lscala/collection/BitSetLike;
const #886 = Method	#122.#885;	//  scala/collection/BitSetLike$class.$bar:(Lscala/collection/BitSetLike;Lscala/collection/BitSet;)Lscala/collection/BitSetLike;
const #887 = Asciz	foreach;
const #888 = Asciz	(Lscala/collection/BitSetLike;Lscala/Function1;)V;
const #889 = NameAndType	#887:#888;//  foreach:(Lscala/collection/BitSetLike;Lscala/Function1;)V
const #890 = Method	#122.#889;	//  scala/collection/BitSetLike$class.foreach:(Lscala/collection/BitSetLike;Lscala/Function1;)V
const #891 = Asciz	(Lscala/collection/BitSetLike;)Ljava/lang/Object;;
const #892 = NameAndType	#179:#891;//  iterator:(Lscala/collection/BitSetLike;)Ljava/lang/Object;
const #893 = Method	#122.#892;	//  scala/collection/BitSetLike$class.iterator:(Lscala/collection/BitSetLike;)Ljava/lang/Object;
const #894 = Asciz	(Lscala/collection/BitSetLike;)I;
const #895 = NameAndType	#791:#894;//  size:(Lscala/collection/BitSetLike;)I
const #896 = Method	#122.#895;	//  scala/collection/BitSetLike$class.size:(Lscala/collection/BitSetLike;)I
const #897 = Asciz	Ljava/lang/Object;Lscala/collection/mutable/Set<Ljava/lang/Integer;>;Lscala/collection/BitSet;Lscala/collection/BitSetLike<Lscala/collection/mutable/BitSet;>;Lscala/collection/mutable/SetLike<Ljava/lang/Integer;Lscala/collection/mutable/BitSet;>;Lscala/ScalaObject;;
const #898 = Asciz	ScalaSig;
const #899 = Asciz	InnerClasses;
const #900 = Asciz	scala/collection/TraversableLike$WithFilter;
const #901 = class	#900;	//  scala/collection/TraversableLike$WithFilter
const #902 = Asciz	WithFilter;
const #903 = Asciz	scala/collection/mutable/Set;
const #904 = class	#903;	//  scala/collection/mutable/Set
const #905 = Asciz	scala/collection/BitSet;
const #906 = class	#905;	//  scala/collection/BitSet
const #907 = Asciz	scala/ScalaObject;
const #908 = class	#907;	//  scala/ScalaObject
const #909 = Asciz	java/io/Serializable;
const #910 = class	#909;	//  java/io/Serializable

{
public static final long serialVersionUID;

public static {};
  Code:
   Stack=2, Locals=0, Args_size=0
   0:	ldc2_w	#8; //long 8483111450368547763l
   3:	putstatic	#13; //Field serialVersionUID:J
   6:	return

public scala.collection.mutable.BitSet(long[]);
  Code:
   Stack=2, Locals=2, Args_size=2
   0:	aload_0
   1:	aload_1
   2:	putfield	#20; //Field elems:[J
   5:	aload_0
   6:	invokespecial	#24; //Method java/lang/Object."<init>":()V
   9:	aload_0
   10:	invokestatic	#30; //Method scala/collection/TraversableLike$class.$init$:(Lscala/collection/TraversableLike;)V
   13:	aload_0
   14:	invokestatic	#35; //Method scala/collection/generic/GenericTraversableTemplate$class.$init$:(Lscala/collection/generic/GenericTraversableTemplate;)V
   17:	aload_0
   18:	invokestatic	#40; //Method scala/collection/Traversable$class.$init$:(Lscala/collection/Traversable;)V
   21:	aload_0
   22:	invokestatic	#45; //Method scala/collection/mutable/Traversable$class.$init$:(Lscala/collection/mutable/Traversable;)V
   25:	aload_0
   26:	invokestatic	#50; //Method scala/collection/IterableLike$class.$init$:(Lscala/collection/IterableLike;)V
   29:	aload_0
   30:	invokestatic	#55; //Method scala/collection/Iterable$class.$init$:(Lscala/collection/Iterable;)V
   33:	aload_0
   34:	invokestatic	#60; //Method scala/collection/mutable/Iterable$class.$init$:(Lscala/collection/mutable/Iterable;)V
   37:	aload_0
   38:	invokestatic	#65; //Method scala/Function1$class.$init$:(Lscala/Function1;)V
   41:	aload_0
   42:	invokestatic	#70; //Method scala/collection/generic/GenericSetTemplate$class.$init$:(Lscala/collection/generic/GenericSetTemplate;)V
   45:	aload_0
   46:	invokestatic	#75; //Method scala/collection/generic/Addable$class.$init$:(Lscala/collection/generic/Addable;)V
   49:	aload_0
   50:	invokestatic	#80; //Method scala/collection/generic/Subtractable$class.$init$:(Lscala/collection/generic/Subtractable;)V
   53:	aload_0
   54:	invokestatic	#85; //Method scala/collection/SetLike$class.$init$:(Lscala/collection/SetLike;)V
   57:	aload_0
   58:	invokestatic	#90; //Method scala/collection/Set$class.$init$:(Lscala/collection/Set;)V
   61:	aload_0
   62:	invokestatic	#95; //Method scala/collection/generic/Growable$class.$init$:(Lscala/collection/generic/Growable;)V
   65:	aload_0
   66:	invokestatic	#100; //Method scala/collection/mutable/Builder$class.$init$:(Lscala/collection/mutable/Builder;)V
   69:	aload_0
   70:	invokestatic	#105; //Method scala/collection/generic/Shrinkable$class.$init$:(Lscala/collection/generic/Shrinkable;)V
   73:	aload_0
   74:	invokestatic	#110; //Method scala/collection/mutable/Cloneable$class.$init$:(Lscala/collection/mutable/Cloneable;)V
   77:	aload_0
   78:	invokestatic	#115; //Method scala/collection/mutable/SetLike$class.$init$:(Lscala/collection/mutable/SetLike;)V
   81:	aload_0
   82:	invokestatic	#120; //Method scala/collection/mutable/Set$class.$init$:(Lscala/collection/mutable/Set;)V
   85:	aload_0
   86:	invokestatic	#125; //Method scala/collection/BitSetLike$class.$init$:(Lscala/collection/BitSetLike;)V
   89:	aload_0
   90:	invokestatic	#130; //Method scala/collection/BitSet$class.$init$:(Lscala/collection/BitSet;)V
   93:	return
  LineNumberTable: 
   line 26: 0

  LocalVariableTable: 
   Start  Length  Slot  Name   Signature
   0      94      0    this       Lscala/collection/mutable/BitSet;
   0      94      1    elems       [J


public scala.collection.BitSet empty();
  Code:
   Stack=1, Locals=1, Args_size=1
   0:	aload_0
   1:	invokevirtual	#138; //Method empty:()Lscala/collection/mutable/BitSet;
   4:	areturn
  LineNumberTable: 
   line 26: 0


public scala.collection.Set empty();
  Code:
   Stack=1, Locals=1, Args_size=1
   0:	aload_0
   1:	invokevirtual	#138; //Method empty:()Lscala/collection/mutable/BitSet;
   4:	areturn
  LineNumberTable: 
   line 26: 0


public scala.collection.BitSetLike empty();
  Code:
   Stack=1, Locals=1, Args_size=1
   0:	aload_0
   1:	invokevirtual	#138; //Method empty:()Lscala/collection/mutable/BitSet;
   4:	areturn
  LineNumberTable: 
   line 26: 0


public scala.collection.SetLike empty();
  Code:
   Stack=1, Locals=1, Args_size=1
   0:	aload_0
   1:	invokevirtual	#138; //Method empty:()Lscala/collection/mutable/BitSet;
   4:	areturn
  LineNumberTable: 
   line 26: 0


public scala.collection.BitSetLike fromArray(long[]);
  Code:
   Stack=2, Locals=2, Args_size=2
   0:	aload_0
   1:	aload_1
   2:	invokevirtual	#146; //Method fromArray:([J)Lscala/collection/mutable/BitSet;
   5:	areturn
  LineNumberTable: 
   line 26: 0

  LocalVariableTable: 
   Start  Length  Slot  Name   Signature
   0      6      0    this       Lscala/collection/mutable/BitSet;
   0      6      1    elems       [J


public boolean add(java.lang.Object);
  Code:
   Stack=2, Locals=2, Args_size=2
   0:	aload_0
   1:	aload_1
   2:	invokestatic	#154; //Method scala/runtime/BoxesRunTime.unboxToInt:(Ljava/lang/Object;)I
   5:	invokevirtual	#157; //Method add:(I)Z
   8:	ireturn
  LineNumberTable: 
   line 26: 0

  LocalVariableTable: 
   Start  Length  Slot  Name   Signature
   0      9      0    this       Lscala/collection/mutable/BitSet;
   0      9      1    elem       Ljava/lang/Object;


public boolean remove(java.lang.Object);
  Code:
   Stack=2, Locals=2, Args_size=2
   0:	aload_0
   1:	aload_1
   2:	invokestatic	#154; //Method scala/runtime/BoxesRunTime.unboxToInt:(Ljava/lang/Object;)I
   5:	invokevirtual	#162; //Method remove:(I)Z
   8:	ireturn
  LineNumberTable: 
   line 26: 0

  LocalVariableTable: 
   Start  Length  Slot  Name   Signature
   0      9      0    this       Lscala/collection/mutable/BitSet;
   0      9      1    elem       Ljava/lang/Object;


public scala.collection.mutable.SetLike $plus$eq(java.lang.Object);
  Code:
   Stack=2, Locals=2, Args_size=2
   0:	aload_0
   1:	aload_1
   2:	invokestatic	#154; //Method scala/runtime/BoxesRunTime.unboxToInt:(Ljava/lang/Object;)I
   5:	invokevirtual	#167; //Method $plus$eq:(I)Lscala/collection/mutable/BitSet;
   8:	areturn
  LineNumberTable: 
   line 26: 0

  LocalVariableTable: 
   Start  Length  Slot  Name   Signature
   0      9      0    this       Lscala/collection/mutable/BitSet;
   0      9      1    elem       Ljava/lang/Object;


public scala.collection.mutable.Builder $plus$eq(java.lang.Object);
  Code:
   Stack=2, Locals=2, Args_size=2
   0:	aload_0
   1:	aload_1
   2:	invokestatic	#154; //Method scala/runtime/BoxesRunTime.unboxToInt:(Ljava/lang/Object;)I
   5:	invokevirtual	#167; //Method $plus$eq:(I)Lscala/collection/mutable/BitSet;
   8:	areturn
  LineNumberTable: 
   line 26: 0

  LocalVariableTable: 
   Start  Length  Slot  Name   Signature
   0      9      0    this       Lscala/collection/mutable/BitSet;
   0      9      1    elem       Ljava/lang/Object;


public scala.collection.generic.Growable $plus$eq(java.lang.Object);
  Code:
   Stack=2, Locals=2, Args_size=2
   0:	aload_0
   1:	aload_1
   2:	invokestatic	#154; //Method scala/runtime/BoxesRunTime.unboxToInt:(Ljava/lang/Object;)I
   5:	invokevirtual	#167; //Method $plus$eq:(I)Lscala/collection/mutable/BitSet;
   8:	areturn
  LineNumberTable: 
   line 26: 0

  LocalVariableTable: 
   Start  Length  Slot  Name   Signature
   0      9      0    this       Lscala/collection/mutable/BitSet;
   0      9      1    elem       Ljava/lang/Object;


public scala.collection.mutable.SetLike $minus$eq(java.lang.Object);
  Code:
   Stack=2, Locals=2, Args_size=2
   0:	aload_0
   1:	aload_1
   2:	invokestatic	#154; //Method scala/runtime/BoxesRunTime.unboxToInt:(Ljava/lang/Object;)I
   5:	invokevirtual	#172; //Method $minus$eq:(I)Lscala/collection/mutable/BitSet;
   8:	areturn
  LineNumberTable: 
   line 26: 0

  LocalVariableTable: 
   Start  Length  Slot  Name   Signature
   0      9      0    this       Lscala/collection/mutable/BitSet;
   0      9      1    elem       Ljava/lang/Object;


public scala.collection.generic.Shrinkable $minus$eq(java.lang.Object);
  Code:
   Stack=2, Locals=2, Args_size=2
   0:	aload_0
   1:	aload_1
   2:	invokestatic	#154; //Method scala/runtime/BoxesRunTime.unboxToInt:(Ljava/lang/Object;)I
   5:	invokevirtual	#172; //Method $minus$eq:(I)Lscala/collection/mutable/BitSet;
   8:	areturn
  LineNumberTable: 
   line 26: 0

  LocalVariableTable: 
   Start  Length  Slot  Name   Signature
   0      9      0    this       Lscala/collection/mutable/BitSet;
   0      9      1    elem       Ljava/lang/Object;


public scala.collection.mutable.Set clone();
  Code:
   Stack=1, Locals=1, Args_size=1
   0:	aload_0
   1:	invokevirtual	#177; //Method clone:()Lscala/collection/mutable/BitSet;
   4:	areturn
  LineNumberTable: 
   line 26: 0


public java.lang.Object clone();
  Code:
   Stack=1, Locals=1, Args_size=1
   0:	aload_0
   1:	invokevirtual	#177; //Method clone:()Lscala/collection/mutable/BitSet;
   4:	areturn
  LineNumberTable: 
   line 26: 0


public scala.collection.Iterator iterator();
  Code:
   Stack=1, Locals=1, Args_size=1
   0:	aload_0
   1:	invokeinterface	#184,  1; //InterfaceMethod scala/collection/BitSetLike.iterator:()Ljava/lang/Object;
   6:	checkcast	#186; //class scala/collection/Iterator
   9:	areturn
  LineNumberTable: 
   line 26: 0


public boolean contains(java.lang.Object);
  Code:
   Stack=2, Locals=2, Args_size=2
   0:	aload_0
   1:	aload_1
   2:	invokestatic	#154; //Method scala/runtime/BoxesRunTime.unboxToInt:(Ljava/lang/Object;)I
   5:	invokeinterface	#189,  2; //InterfaceMethod scala/collection/BitSetLike.contains:(I)Z
   10:	ireturn
  LineNumberTable: 
   line 26: 0

  LocalVariableTable: 
   Start  Length  Slot  Name   Signature
   0      11      0    this       Lscala/collection/mutable/BitSet;
   0      11      1    elem       Ljava/lang/Object;


public java.lang.Object result();
  Code:
   Stack=1, Locals=1, Args_size=1
   0:	aload_0
   1:	invokeinterface	#195,  1; //InterfaceMethod scala/collection/mutable/SetLike.result:()Lscala/collection/mutable/SetLike;
   6:	areturn
  LineNumberTable: 
   line 26: 0


public scala.collection.SetLike $plus(java.lang.Object);
  Code:
   Stack=2, Locals=2, Args_size=2
   0:	aload_0
   1:	aload_1
   2:	invokeinterface	#199,  2; //InterfaceMethod scala/collection/mutable/SetLike.$plus:(Ljava/lang/Object;)Lscala/collection/mutable/SetLike;
   7:	areturn
  LineNumberTable: 
   line 26: 0

  LocalVariableTable: 
   Start  Length  Slot  Name   Signature
   0      8      0    this       Lscala/collection/mutable/BitSet;
   0      8      1    elem       Ljava/lang/Object;


public scala.collection.generic.Addable $plus(java.lang.Object);
  Code:
   Stack=2, Locals=2, Args_size=2
   0:	aload_0
   1:	aload_1
   2:	invokeinterface	#199,  2; //InterfaceMethod scala/collection/mutable/SetLike.$plus:(Ljava/lang/Object;)Lscala/collection/mutable/SetLike;
   7:	areturn
  LineNumberTable: 
   line 26: 0

  LocalVariableTable: 
   Start  Length  Slot  Name   Signature
   0      8      0    this       Lscala/collection/mutable/BitSet;
   0      8      1    elem       Ljava/lang/Object;


public scala.collection.generic.Addable $plus(java.lang.Object, java.lang.Object, scala.collection.Seq);
  Code:
   Stack=4, Locals=4, Args_size=4
   0:	aload_0
   1:	aload_1
   2:	aload_2
   3:	aload_3
   4:	invokeinterface	#204,  4; //InterfaceMethod scala/collection/mutable/SetLike.$plus:(Ljava/lang/Object;Ljava/lang/Object;Lscala/collection/Seq;)Lscala/collection/mutable/SetLike;
   9:	areturn
  LineNumberTable: 
   line 26: 0

  LocalVariableTable: 
   Start  Length  Slot  Name   Signature
   0      10      0    this       Lscala/collection/mutable/BitSet;
   0      10      1    elem1       Ljava/lang/Object;
   0      10      2    elem2       Ljava/lang/Object;
   0      10      3    elems       Lscala/collection/Seq;


public scala.collection.generic.Addable $plus$plus(scala.collection.Traversable);
  Code:
   Stack=2, Locals=2, Args_size=2
   0:	aload_0
   1:	aload_1
   2:	invokeinterface	#212,  2; //InterfaceMethod scala/collection/mutable/SetLike.$plus$plus:(Lscala/collection/Traversable;)Lscala/collection/mutable/SetLike;
   7:	areturn
  LineNumberTable: 
   line 26: 0

  LocalVariableTable: 
   Start  Length  Slot  Name   Signature
   0      8      0    this       Lscala/collection/mutable/BitSet;
   0      8      1    elems       Lscala/collection/Traversable;


public scala.collection.generic.Addable $plus$plus(scala.collection.Iterator);
  Code:
   Stack=2, Locals=2, Args_size=2
   0:	aload_0
   1:	aload_1
   2:	invokeinterface	#217,  2; //InterfaceMethod scala/collection/mutable/SetLike.$plus$plus:(Lscala/collection/Iterator;)Lscala/collection/mutable/SetLike;
   7:	areturn
  LineNumberTable: 
   line 26: 0

  LocalVariableTable: 
   Start  Length  Slot  Name   Signature
   0      8      0    this       Lscala/collection/mutable/BitSet;
   0      8      1    iter       Lscala/collection/Iterator;


public scala.collection.SetLike $minus(java.lang.Object);
  Code:
   Stack=2, Locals=2, Args_size=2
   0:	aload_0
   1:	aload_1
   2:	invokeinterface	#222,  2; //InterfaceMethod scala/collection/mutable/SetLike.$minus:(Ljava/lang/Object;)Lscala/collection/mutable/SetLike;
   7:	areturn
  LineNumberTable: 
   line 26: 0

  LocalVariableTable: 
   Start  Length  Slot  Name   Signature
   0      8      0    this       Lscala/collection/mutable/BitSet;
   0      8      1    elem       Ljava/lang/Object;


public scala.collection.generic.Subtractable $minus(java.lang.Object);
  Code:
   Stack=2, Locals=2, Args_size=2
   0:	aload_0
   1:	aload_1
   2:	invokeinterface	#222,  2; //InterfaceMethod scala/collection/mutable/SetLike.$minus:(Ljava/lang/Object;)Lscala/collection/mutable/SetLike;
   7:	areturn
  LineNumberTable: 
   line 26: 0

  LocalVariableTable: 
   Start  Length  Slot  Name   Signature
   0      8      0    this       Lscala/collection/mutable/BitSet;
   0      8      1    elem       Ljava/lang/Object;


public scala.collection.generic.Subtractable $minus(java.lang.Object, java.lang.Object, scala.collection.Seq);
  Code:
   Stack=4, Locals=4, Args_size=4
   0:	aload_0
   1:	aload_1
   2:	aload_2
   3:	aload_3
   4:	invokeinterface	#226,  4; //InterfaceMethod scala/collection/mutable/SetLike.$minus:(Ljava/lang/Object;Ljava/lang/Object;Lscala/collection/Seq;)Lscala/collection/mutable/SetLike;
   9:	areturn
  LineNumberTable: 
   line 26: 0

  LocalVariableTable: 
   Start  Length  Slot  Name   Signature
   0      10      0    this       Lscala/collection/mutable/BitSet;
   0      10      1    elem1       Ljava/lang/Object;
   0      10      2    elem2       Ljava/lang/Object;
   0      10      3    elems       Lscala/collection/Seq;


public scala.collection.generic.Subtractable $minus$minus(scala.collection.Traversable);
  Code:
   Stack=2, Locals=2, Args_size=2
   0:	aload_0
   1:	aload_1
   2:	invokeinterface	#230,  2; //InterfaceMethod scala/collection/mutable/SetLike.$minus$minus:(Lscala/collection/Traversable;)Lscala/collection/mutable/SetLike;
   7:	areturn
  LineNumberTable: 
   line 26: 0

  LocalVariableTable: 
   Start  Length  Slot  Name   Signature
   0      8      0    this       Lscala/collection/mutable/BitSet;
   0      8      1    elems       Lscala/collection/Traversable;


public scala.collection.generic.Subtractable $minus$minus(scala.collection.Iterator);
  Code:
   Stack=2, Locals=2, Args_size=2
   0:	aload_0
   1:	aload_1
   2:	invokeinterface	#233,  2; //InterfaceMethod scala/collection/mutable/SetLike.$minus$minus:(Lscala/collection/Iterator;)Lscala/collection/mutable/SetLike;
   7:	areturn
  LineNumberTable: 
   line 26: 0

  LocalVariableTable: 
   Start  Length  Slot  Name   Signature
   0      8      0    this       Lscala/collection/mutable/BitSet;
   0      8      1    iter       Lscala/collection/Iterator;


public java.lang.Object apply(java.lang.Object);
  Code:
   Stack=2, Locals=3, Args_size=2
   0:	aload_0
   1:	aload_1
   2:	invokeinterface	#239,  2; //InterfaceMethod scala/collection/SetLike.apply:(Ljava/lang/Object;)Z
   7:	istore_2
   8:	iload_2
   9:	invokestatic	#243; //Method scala/runtime/BoxesRunTime.boxToBoolean:(Z)Ljava/lang/Boolean;
   12:	areturn
  LineNumberTable: 
   line 26: 0

  LocalVariableTable: 
   Start  Length  Slot  Name   Signature
   0      13      0    this       Lscala/collection/mutable/BitSet;
   0      13      1    v1       Ljava/lang/Object;


public scala.collection.Traversable thisCollection();
  Code:
   Stack=1, Locals=1, Args_size=1
   0:	aload_0
   1:	invokeinterface	#251,  1; //InterfaceMethod scala/collection/IterableLike.thisCollection:()Lscala/collection/Iterable;
   6:	areturn
  LineNumberTable: 
   line 26: 0


public scala.collection.Traversable toCollection(java.lang.Object);
  Code:
   Stack=2, Locals=2, Args_size=2
   0:	aload_0
   1:	aload_1
   2:	invokeinterface	#256,  2; //InterfaceMethod scala/collection/IterableLike.toCollection:(Ljava/lang/Object;)Lscala/collection/Iterable;
   7:	areturn
  LineNumberTable: 
   line 26: 0

  LocalVariableTable: 
   Start  Length  Slot  Name   Signature
   0      8      0    this       Lscala/collection/mutable/BitSet;
   0      8      1    repr       Ljava/lang/Object;


public scala.collection.TraversableView view(int, int);
  Code:
   Stack=3, Locals=3, Args_size=3
   0:	aload_0
   1:	iload_1
   2:	iload_2
   3:	invokeinterface	#262,  3; //InterfaceMethod scala/collection/IterableLike.view:(II)Lscala/collection/IterableView;
   8:	areturn
  LineNumberTable: 
   line 26: 0

  LocalVariableTable: 
   Start  Length  Slot  Name   Signature
   0      9      0    this       Lscala/collection/mutable/BitSet;
   0      9      1    from       I
   0      9      2    until       I


public scala.collection.generic.Subtractable repr();
  Code:
   Stack=1, Locals=1, Args_size=1
   0:	aload_0
   1:	invokeinterface	#270,  1; //InterfaceMethod scala/collection/TraversableLike.repr:()Ljava/lang/Object;
   6:	checkcast	#272; //class scala/collection/generic/Subtractable
   9:	areturn
  LineNumberTable: 
   line 26: 0


public scala.collection.generic.Addable repr();
  Code:
   Stack=1, Locals=1, Args_size=1
   0:	aload_0
   1:	invokeinterface	#270,  1; //InterfaceMethod scala/collection/TraversableLike.repr:()Ljava/lang/Object;
   6:	checkcast	#275; //class scala/collection/generic/Addable
   9:	areturn
  LineNumberTable: 
   line 26: 0


public scala.collection.mutable.BitSet clone();
  Code:
   Stack=6, Locals=2, Args_size=1
   0:	aload_0
   1:	invokevirtual	#278; //Method elems:()[J
   4:	arraylength
   5:	newarray long
   7:	astore_1
   8:	getstatic	#284; //Field scala/Array$.MODULE$:Lscala/Array$;
   11:	aload_0
   12:	invokevirtual	#278; //Method elems:()[J
   15:	iconst_0
   16:	aload_1
   17:	iconst_0
   18:	aload_0
   19:	invokevirtual	#278; //Method elems:()[J
   22:	arraylength
   23:	invokevirtual	#288; //Method scala/Array$.copy:(Ljava/lang/Object;ILjava/lang/Object;II)V
   26:	new	#11; //class scala/collection/mutable/BitSet
   29:	dup
   30:	aload_1
   31:	invokespecial	#290; //Method "<init>":([J)V
   34:	areturn
  LineNumberTable: 
   line 87: 0
   line 88: 8
   line 89: 26

  LocalVariableTable: 
   Start  Length  Slot  Name   Signature
   0      35      0    this       Lscala/collection/mutable/BitSet;
   8      26      1    elems1       [J


public scala.collection.immutable.BitSet toImmutable();
  Code:
   Stack=2, Locals=1, Args_size=1
   0:	getstatic	#298; //Field scala/collection/immutable/BitSet$.MODULE$:Lscala/collection/immutable/BitSet$;
   3:	aload_0
   4:	invokevirtual	#278; //Method elems:()[J
   7:	invokevirtual	#301; //Method scala/collection/immutable/BitSet$.fromArray:([J)Lscala/collection/immutable/BitSet;
   10:	areturn
  LineNumberTable: 
   line 84: 0


public void clear();
  Code:
   Stack=2, Locals=1, Args_size=1
   0:	aload_0
   1:	aload_0
   2:	invokevirtual	#278; //Method elems:()[J
   5:	arraylength
   6:	newarray long
   8:	invokevirtual	#305; //Method elems_$eq:([J)V
   11:	return
  LineNumberTable: 
   line 77: 0


public scala.collection.mutable.BitSet $minus$eq(int);
  Code:
   Stack=2, Locals=2, Args_size=2
   0:	aload_0
   1:	iload_1
   2:	invokevirtual	#162; //Method remove:(I)Z
   5:	pop
   6:	aload_0
   7:	areturn
  LineNumberTable: 
   line 74: 0

  LocalVariableTable: 
   Start  Length  Slot  Name   Signature
   0      8      0    this       Lscala/collection/mutable/BitSet;
   0      8      1    elem       I


public scala.collection.mutable.BitSet $plus$eq(int);
  Code:
   Stack=2, Locals=2, Args_size=2
   0:	aload_0
   1:	iload_1
   2:	invokevirtual	#157; //Method add:(I)Z
   5:	pop
   6:	aload_0
   7:	areturn
  LineNumberTable: 
   line 73: 0

  LocalVariableTable: 
   Start  Length  Slot  Name   Signature
   0      8      0    this       Lscala/collection/mutable/BitSet;
   0      8      1    elem       I


public boolean remove(int);
  Code:
   Stack=8, Locals=3, Args_size=2
   0:	getstatic	#310; //Field scala/Predef$.MODULE$:Lscala/Predef$;
   3:	iload_1
   4:	iconst_0
   5:	if_icmplt	12
   8:	iconst_1
   9:	goto	13
   12:	iconst_0
   13:	invokevirtual	#314; //Method scala/Predef$.require:(Z)V
   16:	aload_0
   17:	iload_1
   18:	invokeinterface	#189,  2; //InterfaceMethod scala/collection/BitSetLike.contains:(I)Z
   23:	ifeq	57
   26:	iload_1
   27:	getstatic	#319; //Field scala/collection/BitSetLike$.MODULE$:Lscala/collection/BitSetLike$;
   30:	invokevirtual	#323; //Method scala/collection/BitSetLike$.LogWL:()I
   33:	ishr
   34:	istore_2
   35:	aload_0
   36:	iload_2
   37:	aload_0
   38:	iload_2
   39:	invokevirtual	#327; //Method word:(I)J
   42:	lconst_1
   43:	iload_1
   44:	lshl
   45:	ldc2_w	#328; //long -1l
   48:	lxor
   49:	land
   50:	invokespecial	#333; //Method updateWord:(IJ)V
   53:	iconst_1
   54:	goto	58
   57:	iconst_0
   58:	ireturn
  LineNumberTable: 
   line 65: 0
   line 66: 16
   line 67: 26
   line 68: 35
   line 69: 53
   line 70: 57
   line 64: 58

  LocalVariableTable: 
   Start  Length  Slot  Name   Signature
   0      59      0    this       Lscala/collection/mutable/BitSet;
   0      59      1    elem       I
   35      19      2    idx       I


public boolean add(int);
  Code:
   Stack=7, Locals=3, Args_size=2
   0:	getstatic	#310; //Field scala/Predef$.MODULE$:Lscala/Predef$;
   3:	iload_1
   4:	iconst_0
   5:	if_icmplt	12
   8:	iconst_1
   9:	goto	13
   12:	iconst_0
   13:	invokevirtual	#314; //Method scala/Predef$.require:(Z)V
   16:	aload_0
   17:	iload_1
   18:	invokeinterface	#189,  2; //InterfaceMethod scala/collection/BitSetLike.contains:(I)Z
   23:	ifeq	30
   26:	iconst_0
   27:	goto	54
   30:	iload_1
   31:	getstatic	#319; //Field scala/collection/BitSetLike$.MODULE$:Lscala/collection/BitSetLike$;
   34:	invokevirtual	#323; //Method scala/collection/BitSetLike$.LogWL:()I
   37:	ishr
   38:	istore_2
   39:	aload_0
   40:	iload_2
   41:	aload_0
   42:	iload_2
   43:	invokevirtual	#327; //Method word:(I)J
   46:	lconst_1
   47:	iload_1
   48:	lshl
   49:	lor
   50:	invokespecial	#333; //Method updateWord:(IJ)V
   53:	iconst_1
   54:	ireturn
  LineNumberTable: 
   line 55: 0
   line 56: 16
   line 58: 30
   line 59: 39
   line 60: 53
   line 54: 54

  LocalVariableTable: 
   Start  Length  Slot  Name   Signature
   0      55      0    this       Lscala/collection/mutable/BitSet;
   0      55      1    elem       I
   39      15      2    idx       I


public scala.collection.mutable.BitSet fromArray(long[]);
  Code:
   Stack=3, Locals=2, Args_size=2
   0:	new	#11; //class scala/collection/mutable/BitSet
   3:	dup
   4:	aload_1
   5:	invokespecial	#290; //Method "<init>":([J)V
   8:	areturn
  LineNumberTable: 
   line 52: 0

  LocalVariableTable: 
   Start  Length  Slot  Name   Signature
   0      9      0    this       Lscala/collection/mutable/BitSet;
   0      9      1    words       [J


public long word(int);
  Code:
   Stack=2, Locals=2, Args_size=2
   0:	iload_1
   1:	aload_0
   2:	invokevirtual	#338; //Method nwords:()I
   5:	if_icmpge	17
   8:	aload_0
   9:	invokevirtual	#278; //Method elems:()[J
   12:	iload_1
   13:	laload
   14:	goto	18
   17:	lconst_0
   18:	lreturn
  LineNumberTable: 
   line 39: 0

  LocalVariableTable: 
   Start  Length  Slot  Name   Signature
   0      19      0    this       Lscala/collection/mutable/BitSet;
   0      19      1    idx       I


public int nwords();
  Code:
   Stack=1, Locals=1, Args_size=1
   0:	aload_0
   1:	invokevirtual	#278; //Method elems:()[J
   4:	arraylength
   5:	ireturn
  LineNumberTable: 
   line 37: 0


public scala.collection.mutable.BitSet();
  Code:
   Stack=2, Locals=1, Args_size=1
   0:	aload_0
   1:	iconst_0
   2:	invokespecial	#343; //Method "<init>":(I)V
   5:	return
  LineNumberTable: 
   line 35: 0


public scala.collection.mutable.BitSet(int);
  Code:
   Stack=4, Locals=2, Args_size=2
   0:	aload_0
   1:	getstatic	#310; //Field scala/Predef$.MODULE$:Lscala/Predef$;
   4:	iload_1
   5:	ldc_w	#344; //int 63
   8:	iadd
   9:	ldc_w	#345; //int 6
   12:	ishr
   13:	invokevirtual	#349; //Method scala/Predef$.intWrapper:(I)Lscala/runtime/RichInt;
   16:	iconst_1
   17:	invokevirtual	#355; //Method scala/runtime/RichInt.max:(I)I
   20:	newarray long
   22:	invokespecial	#290; //Method "<init>":([J)V
   25:	return
  LineNumberTable: 
   line 33: 0

  LocalVariableTable: 
   Start  Length  Slot  Name   Signature
   0      26      0    this       Lscala/collection/mutable/BitSet;
   0      26      1    initSize       I


public scala.collection.mutable.BitSet empty();
  Code:
   Stack=1, Locals=1, Args_size=1
   0:	getstatic	#361; //Field scala/collection/mutable/BitSet$.MODULE$:Lscala/collection/mutable/BitSet$;
   3:	invokevirtual	#362; //Method scala/collection/mutable/BitSet$.empty:()Lscala/collection/mutable/BitSet;
   6:	areturn
  LineNumberTable: 
   line 31: 0


public void elems_$eq(long[]);
  Code:
   Stack=2, Locals=2, Args_size=2
   0:	aload_0
   1:	aload_1
   2:	putfield	#20; //Field elems:[J
   5:	return
  LineNumberTable: 
   line 26: 0


public long[] elems();
  Code:
   Stack=1, Locals=1, Args_size=1
   0:	aload_0
   1:	getfield	#20; //Field elems:[J
   4:	areturn
  LineNumberTable: 
   line 26: 0


public scala.collection.TraversableLike$WithFilter withFilter(scala.Function1);
  Code:
   Stack=2, Locals=2, Args_size=2
   0:	aload_0
   1:	aload_1
   2:	invokestatic	#367; //Method scala/collection/TraversableLike$class.withFilter:(Lscala/collection/TraversableLike;Lscala/Function1;)Lscala/collection/TraversableLike$WithFilter;
   5:	areturn
  LineNumberTable: 
   line 26: 0

  LocalVariableTable: 
   Start  Length  Slot  Name   Signature
   0      6      0    this       Lscala/collection/mutable/BitSet;
   0      6      1    p       Lscala/Function1;

  Signature: length = 0x2
   01 6C 

public scala.collection.mutable.StringBuilder addString(scala.collection.mutable.StringBuilder);
  Code:
   Stack=2, Locals=2, Args_size=2
   0:	aload_0
   1:	aload_1
   2:	invokestatic	#375; //Method scala/collection/TraversableLike$class.addString:(Lscala/collection/TraversableLike;Lscala/collection/mutable/StringBuilder;)Lscala/collection/mutable/StringBuilder;
   5:	areturn
  LineNumberTable: 
   line 26: 0

  LocalVariableTable: 
   Start  Length  Slot  Name   Signature
   0      6      0    this       Lscala/collection/mutable/BitSet;
   0      6      1    b       Lscala/collection/mutable/StringBuilder;


public scala.collection.mutable.StringBuilder addString(scala.collection.mutable.StringBuilder, java.lang.String);
  Code:
   Stack=3, Locals=3, Args_size=3
   0:	aload_0
   1:	aload_1
   2:	aload_2
   3:	invokestatic	#381; //Method scala/collection/TraversableLike$class.addString:(Lscala/collection/TraversableLike;Lscala/collection/mutable/StringBuilder;Ljava/lang/String;)Lscala/collection/mutable/StringBuilder;
   6:	areturn
  LineNumberTable: 
   line 26: 0

  LocalVariableTable: 
   Start  Length  Slot  Name   Signature
   0      7      0    this       Lscala/collection/mutable/BitSet;
   0      7      1    b       Lscala/collection/mutable/StringBuilder;
   0      7      2    sep       Ljava/lang/String;


public java.lang.String mkString();
  Code:
   Stack=1, Locals=1, Args_size=1
   0:	aload_0
   1:	invokestatic	#388; //Method scala/collection/TraversableLike$class.mkString:(Lscala/collection/TraversableLike;)Ljava/lang/String;
   4:	areturn
  LineNumberTable: 
   line 26: 0


public java.lang.String mkString(java.lang.String);
  Code:
   Stack=2, Locals=2, Args_size=2
   0:	aload_0
   1:	aload_1
   2:	invokestatic	#392; //Method scala/collection/TraversableLike$class.mkString:(Lscala/collection/TraversableLike;Ljava/lang/String;)Ljava/lang/String;
   5:	areturn
  LineNumberTable: 
   line 26: 0

  LocalVariableTable: 
   Start  Length  Slot  Name   Signature
   0      6      0    this       Lscala/collection/mutable/BitSet;
   0      6      1    sep       Ljava/lang/String;


public java.lang.String mkString(java.lang.String, java.lang.String, java.lang.String);
  Code:
   Stack=4, Locals=4, Args_size=4
   0:	aload_0
   1:	aload_1
   2:	aload_2
   3:	aload_3
   4:	invokestatic	#396; //Method scala/collection/TraversableLike$class.mkString:(Lscala/collection/TraversableLike;Ljava/lang/String;Ljava/lang/String;Ljava/lang/String;)Ljava/lang/String;
   7:	areturn
  LineNumberTable: 
   line 26: 0

  LocalVariableTable: 
   Start  Length  Slot  Name   Signature
   0      8      0    this       Lscala/collection/mutable/BitSet;
   0      8      1    start       Ljava/lang/String;
   0      8      2    sep       Ljava/lang/String;
   0      8      3    end       Ljava/lang/String;


public scala.collection.immutable.Set toSet();
  Code:
   Stack=1, Locals=1, Args_size=1
   0:	aload_0
   1:	invokestatic	#403; //Method scala/collection/TraversableLike$class.toSet:(Lscala/collection/TraversableLike;)Lscala/collection/immutable/Set;
   4:	areturn
  LineNumberTable: 
   line 26: 0


public scala.collection.mutable.IndexedSeq toIndexedSeq();
  Code:
   Stack=1, Locals=1, Args_size=1
   0:	aload_0
   1:	invokestatic	#408; //Method scala/collection/TraversableLike$class.toIndexedSeq:(Lscala/collection/TraversableLike;)Lscala/collection/mutable/IndexedSeq;
   4:	areturn
  LineNumberTable: 
   line 26: 0


public scala.collection.Seq toSeq();
  Code:
   Stack=1, Locals=1, Args_size=1
   0:	aload_0
   1:	invokestatic	#413; //Method scala/collection/TraversableLike$class.toSeq:(Lscala/collection/TraversableLike;)Lscala/collection/Seq;
   4:	areturn
  LineNumberTable: 
   line 26: 0


public scala.collection.immutable.List toList();
  Code:
   Stack=1, Locals=1, Args_size=1
   0:	aload_0
   1:	invokestatic	#418; //Method scala/collection/TraversableLike$class.toList:(Lscala/collection/TraversableLike;)Lscala/collection/immutable/List;
   4:	areturn
  LineNumberTable: 
   line 26: 0


public java.lang.Object toArray(scala.reflect.ClassManifest);
  Code:
   Stack=2, Locals=2, Args_size=2
   0:	aload_0
   1:	aload_1
   2:	invokestatic	#423; //Method scala/collection/TraversableLike$class.toArray:(Lscala/collection/TraversableLike;Lscala/reflect/ClassManifest;)Ljava/lang/Object;
   5:	areturn
  LineNumberTable: 
   line 26: 0

  LocalVariableTable: 
   Start  Length  Slot  Name   Signature
   0      6      0    this       Lscala/collection/mutable/BitSet;
   0      6      1    evidence$1       Lscala/reflect/ClassManifest;


public void copyToArray(java.lang.Object);
  Code:
   Stack=2, Locals=2, Args_size=2
   0:	aload_0
   1:	aload_1
   2:	invokestatic	#430; //Method scala/collection/TraversableLike$class.copyToArray:(Lscala/collection/TraversableLike;Ljava/lang/Object;)V
   5:	return
  LineNumberTable: 
   line 26: 0

  LocalVariableTable: 
   Start  Length  Slot  Name   Signature
   0      6      0    this       Lscala/collection/mutable/BitSet;
   0      6      1    xs       Ljava/lang/Object;


public void copyToArray(java.lang.Object, int);
  Code:
   Stack=3, Locals=3, Args_size=3
   0:	aload_0
   1:	aload_1
   2:	iload_2
   3:	invokestatic	#435; //Method scala/collection/TraversableLike$class.copyToArray:(Lscala/collection/TraversableLike;Ljava/lang/Object;I)V
   6:	return
  LineNumberTable: 
   line 26: 0

  LocalVariableTable: 
   Start  Length  Slot  Name   Signature
   0      7      0    this       Lscala/collection/mutable/BitSet;
   0      7      1    xs       Ljava/lang/Object;
   0      7      2    start       I


public void copyToBuffer(scala.collection.mutable.Buffer);
  Code:
   Stack=2, Locals=2, Args_size=2
   0:	aload_0
   1:	aload_1
   2:	invokestatic	#440; //Method scala/collection/TraversableLike$class.copyToBuffer:(Lscala/collection/TraversableLike;Lscala/collection/mutable/Buffer;)V
   5:	return
  LineNumberTable: 
   line 26: 0

  LocalVariableTable: 
   Start  Length  Slot  Name   Signature
   0      6      0    this       Lscala/collection/mutable/BitSet;
   0      6      1    dest       Lscala/collection/mutable/Buffer;


public scala.Tuple2 splitAt(int);
  Code:
   Stack=2, Locals=2, Args_size=2
   0:	aload_0
   1:	iload_1
   2:	invokestatic	#447; //Method scala/collection/TraversableLike$class.splitAt:(Lscala/collection/TraversableLike;I)Lscala/Tuple2;
   5:	areturn
  LineNumberTable: 
   line 26: 0

  LocalVariableTable: 
   Start  Length  Slot  Name   Signature
   0      6      0    this       Lscala/collection/mutable/BitSet;
   0      6      1    n       I


public scala.Tuple2 span(scala.Function1);
  Code:
   Stack=2, Locals=2, Args_size=2
   0:	aload_0
   1:	aload_1
   2:	invokestatic	#453; //Method scala/collection/TraversableLike$class.span:(Lscala/collection/TraversableLike;Lscala/Function1;)Lscala/Tuple2;
   5:	areturn
  LineNumberTable: 
   line 26: 0

  LocalVariableTable: 
   Start  Length  Slot  Name   Signature
   0      6      0    this       Lscala/collection/mutable/BitSet;
   0      6      1    p       Lscala/Function1;


public java.lang.Object dropWhile(scala.Function1);
  Code:
   Stack=2, Locals=2, Args_size=2
   0:	aload_0
   1:	aload_1
   2:	invokestatic	#458; //Method scala/collection/TraversableLike$class.dropWhile:(Lscala/collection/TraversableLike;Lscala/Function1;)Ljava/lang/Object;
   5:	areturn
  LineNumberTable: 
   line 26: 0

  LocalVariableTable: 
   Start  Length  Slot  Name   Signature
   0      6      0    this       Lscala/collection/mutable/BitSet;
   0      6      1    p       Lscala/Function1;


public java.lang.Object drop(int);
  Code:
   Stack=2, Locals=2, Args_size=2
   0:	aload_0
   1:	iload_1
   2:	invokestatic	#463; //Method scala/collection/TraversableLike$class.drop:(Lscala/collection/TraversableLike;I)Ljava/lang/Object;
   5:	areturn
  LineNumberTable: 
   line 26: 0

  LocalVariableTable: 
   Start  Length  Slot  Name   Signature
   0      6      0    this       Lscala/collection/mutable/BitSet;
   0      6      1    n       I


public java.lang.Object init();
  Code:
   Stack=1, Locals=1, Args_size=1
   0:	aload_0
   1:	invokestatic	#467; //Method scala/collection/TraversableLike$class.init:(Lscala/collection/TraversableLike;)Ljava/lang/Object;
   4:	areturn
  LineNumberTable: 
   line 26: 0


public scala.Option lastOption();
  Code:
   Stack=1, Locals=1, Args_size=1
   0:	aload_0
   1:	invokestatic	#472; //Method scala/collection/TraversableLike$class.lastOption:(Lscala/collection/TraversableLike;)Lscala/Option;
   4:	areturn
  LineNumberTable: 
   line 26: 0


public java.lang.Object last();
  Code:
   Stack=1, Locals=1, Args_size=1
   0:	aload_0
   1:	invokestatic	#475; //Method scala/collection/TraversableLike$class.last:(Lscala/collection/TraversableLike;)Ljava/lang/Object;
   4:	areturn
  LineNumberTable: 
   line 26: 0


public java.lang.Object tail();
  Code:
   Stack=1, Locals=1, Args_size=1
   0:	aload_0
   1:	invokestatic	#478; //Method scala/collection/TraversableLike$class.tail:(Lscala/collection/TraversableLike;)Ljava/lang/Object;
   4:	areturn
  LineNumberTable: 
   line 26: 0


public scala.Option headOption();
  Code:
   Stack=1, Locals=1, Args_size=1
   0:	aload_0
   1:	invokestatic	#481; //Method scala/collection/TraversableLike$class.headOption:(Lscala/collection/TraversableLike;)Lscala/Option;
   4:	areturn
  LineNumberTable: 
   line 26: 0


public java.lang.Object max(scala.math.Ordering);
  Code:
   Stack=2, Locals=2, Args_size=2
   0:	aload_0
   1:	aload_1
   2:	invokestatic	#485; //Method scala/collection/TraversableLike$class.max:(Lscala/collection/TraversableLike;Lscala/math/Ordering;)Ljava/lang/Object;
   5:	areturn
  LineNumberTable: 
   line 26: 0

  LocalVariableTable: 
   Start  Length  Slot  Name   Signature
   0      6      0    this       Lscala/collection/mutable/BitSet;
   0      6      1    cmp       Lscala/math/Ordering;


public java.lang.Object min(scala.math.Ordering);
  Code:
   Stack=2, Locals=2, Args_size=2
   0:	aload_0
   1:	aload_1
   2:	invokestatic	#490; //Method scala/collection/TraversableLike$class.min:(Lscala/collection/TraversableLike;Lscala/math/Ordering;)Ljava/lang/Object;
   5:	areturn
  LineNumberTable: 
   line 26: 0

  LocalVariableTable: 
   Start  Length  Slot  Name   Signature
   0      6      0    this       Lscala/collection/mutable/BitSet;
   0      6      1    cmp       Lscala/math/Ordering;


public java.lang.Object product(scala.math.Numeric);
  Code:
   Stack=2, Locals=2, Args_size=2
   0:	aload_0
   1:	aload_1
   2:	invokestatic	#495; //Method scala/collection/TraversableLike$class.product:(Lscala/collection/TraversableLike;Lscala/math/Numeric;)Ljava/lang/Object;
   5:	areturn
  LineNumberTable: 
   line 26: 0

  LocalVariableTable: 
   Start  Length  Slot  Name   Signature
   0      6      0    this       Lscala/collection/mutable/BitSet;
   0      6      1    num       Lscala/math/Numeric;


public java.lang.Object sum(scala.math.Numeric);
  Code:
   Stack=2, Locals=2, Args_size=2
   0:	aload_0
   1:	aload_1
   2:	invokestatic	#500; //Method scala/collection/TraversableLike$class.sum:(Lscala/collection/TraversableLike;Lscala/math/Numeric;)Ljava/lang/Object;
   5:	areturn
  LineNumberTable: 
   line 26: 0

  LocalVariableTable: 
   Start  Length  Slot  Name   Signature
   0      6      0    this       Lscala/collection/mutable/BitSet;
   0      6      1    num       Lscala/math/Numeric;


public scala.Option reduceRightOption(scala.Function2);
  Code:
   Stack=2, Locals=2, Args_size=2
   0:	aload_0
   1:	aload_1
   2:	invokestatic	#505; //Method scala/collection/TraversableLike$class.reduceRightOption:(Lscala/collection/TraversableLike;Lscala/Function2;)Lscala/Option;
   5:	areturn
  LineNumberTable: 
   line 26: 0

  LocalVariableTable: 
   Start  Length  Slot  Name   Signature
   0      6      0    this       Lscala/collection/mutable/BitSet;
   0      6      1    op       Lscala/Function2;


public scala.Option reduceLeftOption(scala.Function2);
  Code:
   Stack=2, Locals=2, Args_size=2
   0:	aload_0
   1:	aload_1
   2:	invokestatic	#510; //Method scala/collection/TraversableLike$class.reduceLeftOption:(Lscala/collection/TraversableLike;Lscala/Function2;)Lscala/Option;
   5:	areturn
  LineNumberTable: 
   line 26: 0

  LocalVariableTable: 
   Start  Length  Slot  Name   Signature
   0      6      0    this       Lscala/collection/mutable/BitSet;
   0      6      1    op       Lscala/Function2;


public java.lang.Object reduceLeft(scala.Function2);
  Code:
   Stack=2, Locals=2, Args_size=2
   0:	aload_0
   1:	aload_1
   2:	invokestatic	#515; //Method scala/collection/TraversableLike$class.reduceLeft:(Lscala/collection/TraversableLike;Lscala/Function2;)Ljava/lang/Object;
   5:	areturn
  LineNumberTable: 
   line 26: 0

  LocalVariableTable: 
   Start  Length  Slot  Name   Signature
   0      6      0    this       Lscala/collection/mutable/BitSet;
   0      6      1    op       Lscala/Function2;


public java.lang.Object $colon$bslash(java.lang.Object, scala.Function2);
  Code:
   Stack=3, Locals=3, Args_size=3
   0:	aload_0
   1:	aload_1
   2:	aload_2
   3:	invokestatic	#520; //Method scala/collection/TraversableLike$class.$colon$bslash:(Lscala/collection/TraversableLike;Ljava/lang/Object;Lscala/Function2;)Ljava/lang/Object;
   6:	areturn
  LineNumberTable: 
   line 26: 0

  LocalVariableTable: 
   Start  Length  Slot  Name   Signature
   0      7      0    this       Lscala/collection/mutable/BitSet;
   0      7      1    z       Ljava/lang/Object;
   0      7      2    op       Lscala/Function2;


public java.lang.Object $div$colon(java.lang.Object, scala.Function2);
  Code:
   Stack=3, Locals=3, Args_size=3
   0:	aload_0
   1:	aload_1
   2:	aload_2
   3:	invokestatic	#524; //Method scala/collection/TraversableLike$class.$div$colon:(Lscala/collection/TraversableLike;Ljava/lang/Object;Lscala/Function2;)Ljava/lang/Object;
   6:	areturn
  LineNumberTable: 
   line 26: 0

  LocalVariableTable: 
   Start  Length  Slot  Name   Signature
   0      7      0    this       Lscala/collection/mutable/BitSet;
   0      7      1    z       Ljava/lang/Object;
   0      7      2    op       Lscala/Function2;


public java.lang.Object foldLeft(java.lang.Object, scala.Function2);
  Code:
   Stack=3, Locals=3, Args_size=3
   0:	aload_0
   1:	aload_1
   2:	aload_2
   3:	invokestatic	#527; //Method scala/collection/TraversableLike$class.foldLeft:(Lscala/collection/TraversableLike;Ljava/lang/Object;Lscala/Function2;)Ljava/lang/Object;
   6:	areturn
  LineNumberTable: 
   line 26: 0

  LocalVariableTable: 
   Start  Length  Slot  Name   Signature
   0      7      0    this       Lscala/collection/mutable/BitSet;
   0      7      1    z       Ljava/lang/Object;
   0      7      2    op       Lscala/Function2;


public int count(scala.Function1);
  Code:
   Stack=2, Locals=2, Args_size=2
   0:	aload_0
   1:	aload_1
   2:	invokestatic	#532; //Method scala/collection/TraversableLike$class.count:(Lscala/collection/TraversableLike;Lscala/Function1;)I
   5:	ireturn
  LineNumberTable: 
   line 26: 0

  LocalVariableTable: 
   Start  Length  Slot  Name   Signature
   0      6      0    this       Lscala/collection/mutable/BitSet;
   0      6      1    p       Lscala/Function1;


public scala.collection.Map groupBy(scala.Function1);
  Code:
   Stack=2, Locals=2, Args_size=2
   0:	aload_0
   1:	aload_1
   2:	invokestatic	#537; //Method scala/collection/TraversableLike$class.groupBy:(Lscala/collection/TraversableLike;Lscala/Function1;)Lscala/collection/Map;
   5:	areturn
  LineNumberTable: 
   line 26: 0

  LocalVariableTable: 
   Start  Length  Slot  Name   Signature
   0      6      0    this       Lscala/collection/mutable/BitSet;
   0      6      1    f       Lscala/Function1;


public scala.Tuple2 partition(scala.Function1);
  Code:
   Stack=2, Locals=2, Args_size=2
   0:	aload_0
   1:	aload_1
   2:	invokestatic	#541; //Method scala/collection/TraversableLike$class.partition:(Lscala/collection/TraversableLike;Lscala/Function1;)Lscala/Tuple2;
   5:	areturn
  LineNumberTable: 
   line 26: 0

  LocalVariableTable: 
   Start  Length  Slot  Name   Signature
   0      6      0    this       Lscala/collection/mutable/BitSet;
   0      6      1    p       Lscala/Function1;


public java.lang.Object partialMap(scala.PartialFunction, scala.collection.generic.CanBuildFrom);
  Code:
   Stack=3, Locals=3, Args_size=3
   0:	aload_0
   1:	aload_1
   2:	aload_2
   3:	invokestatic	#546; //Method scala/collection/TraversableLike$class.partialMap:(Lscala/collection/TraversableLike;Lscala/PartialFunction;Lscala/collection/generic/CanBuildFrom;)Ljava/lang/Object;
   6:	areturn
  LineNumberTable: 
   line 26: 0

  LocalVariableTable: 
   Start  Length  Slot  Name   Signature
   0      7      0    this       Lscala/collection/mutable/BitSet;
   0      7      1    pf       Lscala/PartialFunction;
   0      7      2    bf       Lscala/collection/generic/CanBuildFrom;


public java.lang.Object filterNot(scala.Function1);
  Code:
   Stack=2, Locals=2, Args_size=2
   0:	aload_0
   1:	aload_1
   2:	invokestatic	#553; //Method scala/collection/TraversableLike$class.filterNot:(Lscala/collection/TraversableLike;Lscala/Function1;)Ljava/lang/Object;
   5:	areturn
  LineNumberTable: 
   line 26: 0

  LocalVariableTable: 
   Start  Length  Slot  Name   Signature
   0      6      0    this       Lscala/collection/mutable/BitSet;
   0      6      1    p       Lscala/Function1;


public java.lang.Object filter(scala.Function1);
  Code:
   Stack=2, Locals=2, Args_size=2
   0:	aload_0
   1:	aload_1
   2:	invokestatic	#556; //Method scala/collection/TraversableLike$class.filter:(Lscala/collection/TraversableLike;Lscala/Function1;)Ljava/lang/Object;
   5:	areturn
  LineNumberTable: 
   line 26: 0

  LocalVariableTable: 
   Start  Length  Slot  Name   Signature
   0      6      0    this       Lscala/collection/mutable/BitSet;
   0      6      1    p       Lscala/Function1;


public java.lang.Object flatMap(scala.Function1, scala.collection.generic.CanBuildFrom);
  Code:
   Stack=3, Locals=3, Args_size=3
   0:	aload_0
   1:	aload_1
   2:	aload_2
   3:	invokestatic	#561; //Method scala/collection/TraversableLike$class.flatMap:(Lscala/collection/TraversableLike;Lscala/Function1;Lscala/collection/generic/CanBuildFrom;)Ljava/lang/Object;
   6:	areturn
  LineNumberTable: 
   line 26: 0

  LocalVariableTable: 
   Start  Length  Slot  Name   Signature
   0      7      0    this       Lscala/collection/mutable/BitSet;
   0      7      1    f       Lscala/Function1;
   0      7      2    bf       Lscala/collection/generic/CanBuildFrom;


public java.lang.Object map(scala.Function1, scala.collection.generic.CanBuildFrom);
  Code:
   Stack=3, Locals=3, Args_size=3
   0:	aload_0
   1:	aload_1
   2:	aload_2
   3:	invokestatic	#564; //Method scala/collection/TraversableLike$class.map:(Lscala/collection/TraversableLike;Lscala/Function1;Lscala/collection/generic/CanBuildFrom;)Ljava/lang/Object;
   6:	areturn
  LineNumberTable: 
   line 26: 0

  LocalVariableTable: 
   Start  Length  Slot  Name   Signature
   0      7      0    this       Lscala/collection/mutable/BitSet;
   0      7      1    f       Lscala/Function1;
   0      7      2    bf       Lscala/collection/generic/CanBuildFrom;


public java.lang.Object $plus$plus(scala.collection.Iterator, scala.collection.generic.CanBuildFrom);
  Code:
   Stack=3, Locals=3, Args_size=3
   0:	aload_0
   1:	aload_1
   2:	aload_2
   3:	invokestatic	#568; //Method scala/collection/TraversableLike$class.$plus$plus:(Lscala/collection/TraversableLike;Lscala/collection/Iterator;Lscala/collection/generic/CanBuildFrom;)Ljava/lang/Object;
   6:	areturn
  LineNumberTable: 
   line 26: 0

  LocalVariableTable: 
   Start  Length  Slot  Name   Signature
   0      7      0    this       Lscala/collection/mutable/BitSet;
   0      7      1    that       Lscala/collection/Iterator;
   0      7      2    bf       Lscala/collection/generic/CanBuildFrom;


public java.lang.Object $plus$plus(scala.collection.Traversable, scala.collection.generic.CanBuildFrom);
  Code:
   Stack=3, Locals=3, Args_size=3
   0:	aload_0
   1:	aload_1
   2:	aload_2
   3:	invokestatic	#573; //Method scala/collection/TraversableLike$class.$plus$plus:(Lscala/collection/TraversableLike;Lscala/collection/Traversable;Lscala/collection/generic/CanBuildFrom;)Ljava/lang/Object;
   6:	areturn
  LineNumberTable: 
   line 26: 0

  LocalVariableTable: 
   Start  Length  Slot  Name   Signature
   0      7      0    this       Lscala/collection/mutable/BitSet;
   0      7      1    that       Lscala/collection/Traversable;
   0      7      2    bf       Lscala/collection/generic/CanBuildFrom;


public boolean hasDefiniteSize();
  Code:
   Stack=1, Locals=1, Args_size=1
   0:	aload_0
   1:	invokestatic	#578; //Method scala/collection/TraversableLike$class.hasDefiniteSize:(Lscala/collection/TraversableLike;)Z
   4:	ireturn
  LineNumberTable: 
   line 26: 0


public boolean nonEmpty();
  Code:
   Stack=1, Locals=1, Args_size=1
   0:	aload_0
   1:	invokestatic	#581; //Method scala/collection/TraversableLike$class.nonEmpty:(Lscala/collection/TraversableLike;)Z
   4:	ireturn
  LineNumberTable: 
   line 26: 0


public java.lang.Object repr();
  Code:
   Stack=1, Locals=1, Args_size=1
   0:	aload_0
   1:	invokestatic	#583; //Method scala/collection/TraversableLike$class.repr:(Lscala/collection/TraversableLike;)Ljava/lang/Object;
   4:	areturn
  LineNumberTable: 
   line 26: 0


public scala.collection.Traversable transpose(scala.Function1);
  Code:
   Stack=2, Locals=2, Args_size=2
   0:	aload_0
   1:	aload_1
   2:	invokestatic	#588; //Method scala/collection/generic/GenericTraversableTemplate$class.transpose:(Lscala/collection/generic/GenericTraversableTemplate;Lscala/Function1;)Lscala/collection/Traversable;
   5:	areturn
  LineNumberTable: 
   line 26: 0

  LocalVariableTable: 
   Start  Length  Slot  Name   Signature
   0      6      0    this       Lscala/collection/mutable/BitSet;
   0      6      1    asTraversable       Lscala/Function1;


public scala.collection.Traversable flatten(scala.Function1);
  Code:
   Stack=2, Locals=2, Args_size=2
   0:	aload_0
   1:	aload_1
   2:	invokestatic	#592; //Method scala/collection/generic/GenericTraversableTemplate$class.flatten:(Lscala/collection/generic/GenericTraversableTemplate;Lscala/Function1;)Lscala/collection/Traversable;
   5:	areturn
  LineNumberTable: 
   line 26: 0

  LocalVariableTable: 
   Start  Length  Slot  Name   Signature
   0      6      0    this       Lscala/collection/mutable/BitSet;
   0      6      1    asTraversable       Lscala/Function1;


public scala.Tuple2 unzip(scala.Function1);
  Code:
   Stack=2, Locals=2, Args_size=2
   0:	aload_0
   1:	aload_1
   2:	invokestatic	#596; //Method scala/collection/generic/GenericTraversableTemplate$class.unzip:(Lscala/collection/generic/GenericTraversableTemplate;Lscala/Function1;)Lscala/Tuple2;
   5:	areturn
  LineNumberTable: 
   line 26: 0

  LocalVariableTable: 
   Start  Length  Slot  Name   Signature
   0      6      0    this       Lscala/collection/mutable/BitSet;
   0      6      1    asPair       Lscala/Function1;


public scala.collection.mutable.Builder genericBuilder();
  Code:
   Stack=1, Locals=1, Args_size=1
   0:	aload_0
   1:	invokestatic	#602; //Method scala/collection/generic/GenericTraversableTemplate$class.genericBuilder:(Lscala/collection/generic/GenericTraversableTemplate;)Lscala/collection/mutable/Builder;
   4:	areturn
  LineNumberTable: 
   line 26: 0


public java.lang.Object projection();
  Code:
   Stack=1, Locals=1, Args_size=1
   0:	aload_0
   1:	invokestatic	#606; //Method scala/collection/IterableLike$class.projection:(Lscala/collection/IterableLike;)Ljava/lang/Object;
   4:	areturn
  LineNumberTable: 
   line 26: 0

  Deprecated: true

public scala.Option firstOption();
  Code:
   Stack=1, Locals=1, Args_size=1
   0:	aload_0
   1:	invokestatic	#611; //Method scala/collection/IterableLike$class.firstOption:(Lscala/collection/IterableLike;)Lscala/Option;
   4:	areturn
  LineNumberTable: 
   line 26: 0

  Deprecated: true

public java.lang.Object first();
  Code:
   Stack=1, Locals=1, Args_size=1
   0:	aload_0
   1:	invokestatic	#614; //Method scala/collection/IterableLike$class.first:(Lscala/collection/IterableLike;)Ljava/lang/Object;
   4:	areturn
  LineNumberTable: 
   line 26: 0

  Deprecated: true

public scala.collection.IterableView view(int, int);
  Code:
   Stack=3, Locals=3, Args_size=3
   0:	aload_0
   1:	iload_1
   2:	iload_2
   3:	invokestatic	#617; //Method scala/collection/IterableLike$class.view:(Lscala/collection/IterableLike;II)Lscala/collection/IterableView;
   6:	areturn
  LineNumberTable: 
   line 26: 0

  LocalVariableTable: 
   Start  Length  Slot  Name   Signature
   0      7      0    this       Lscala/collection/mutable/BitSet;
   0      7      1    from       I
   0      7      2    until       I


public java.lang.Object view();
  Code:
   Stack=1, Locals=1, Args_size=1
   0:	aload_0
   1:	invokestatic	#619; //Method scala/collection/IterableLike$class.view:(Lscala/collection/IterableLike;)Ljava/lang/Object;
   4:	areturn
  LineNumberTable: 
   line 26: 0


public boolean canEqual(java.lang.Object);
  Code:
   Stack=2, Locals=2, Args_size=2
   0:	aload_0
   1:	aload_1
   2:	invokestatic	#623; //Method scala/collection/IterableLike$class.canEqual:(Lscala/collection/IterableLike;Ljava/lang/Object;)Z
   5:	ireturn
  LineNumberTable: 
   line 26: 0

  LocalVariableTable: 
   Start  Length  Slot  Name   Signature
   0      6      0    this       Lscala/collection/mutable/BitSet;
   0      6      1    that       Ljava/lang/Object;


public scala.collection.immutable.Stream toStream();
  Code:
   Stack=1, Locals=1, Args_size=1
   0:	aload_0
   1:	invokestatic	#628; //Method scala/collection/IterableLike$class.toStream:(Lscala/collection/IterableLike;)Lscala/collection/immutable/Stream;
   4:	areturn
  LineNumberTable: 
   line 26: 0


public boolean sameElements(scala.collection.Iterable);
  Code:
   Stack=2, Locals=2, Args_size=2
   0:	aload_0
   1:	aload_1
   2:	invokestatic	#633; //Method scala/collection/IterableLike$class.sameElements:(Lscala/collection/IterableLike;Lscala/collection/Iterable;)Z
   5:	ireturn
  LineNumberTable: 
   line 26: 0

  LocalVariableTable: 
   Start  Length  Slot  Name   Signature
   0      6      0    this       Lscala/collection/mutable/BitSet;
   0      6      1    that       Lscala/collection/Iterable;


public java.lang.Object zipWithIndex(scala.collection.generic.CanBuildFrom);
  Code:
   Stack=2, Locals=2, Args_size=2
   0:	aload_0
   1:	aload_1
   2:	invokestatic	#639; //Method scala/collection/IterableLike$class.zipWithIndex:(Lscala/collection/IterableLike;Lscala/collection/generic/CanBuildFrom;)Ljava/lang/Object;
   5:	areturn
  LineNumberTable: 
   line 26: 0

  LocalVariableTable: 
   Start  Length  Slot  Name   Signature
   0      6      0    this       Lscala/collection/mutable/BitSet;
   0      6      1    bf       Lscala/collection/generic/CanBuildFrom;


public java.lang.Object zipAll(scala.collection.Iterable, java.lang.Object, java.lang.Object, scala.collection.generic.CanBuildFrom);
  Code:
   Stack=5, Locals=5, Args_size=5
   0:	aload_0
   1:	aload_1
   2:	aload_2
   3:	aload_3
   4:	aload	4
   6:	invokestatic	#644; //Method scala/collection/IterableLike$class.zipAll:(Lscala/collection/IterableLike;Lscala/collection/Iterable;Ljava/lang/Object;Ljava/lang/Object;Lscala/collection/generic/CanBuildFrom;)Ljava/lang/Object;
   9:	areturn
  LineNumberTable: 
   line 26: 0

  LocalVariableTable: 
   Start  Length  Slot  Name   Signature
   0      10      0    this       Lscala/collection/mutable/BitSet;
   0      10      1    that       Lscala/collection/Iterable;
   0      10      2    thisElem       Ljava/lang/Object;
   0      10      3    thatElem       Ljava/lang/Object;
   0      10      4    bf       Lscala/collection/generic/CanBuildFrom;


public java.lang.Object zip(scala.collection.Iterable, scala.collection.generic.CanBuildFrom);
  Code:
   Stack=3, Locals=3, Args_size=3
   0:	aload_0
   1:	aload_1
   2:	aload_2
   3:	invokestatic	#651; //Method scala/collection/IterableLike$class.zip:(Lscala/collection/IterableLike;Lscala/collection/Iterable;Lscala/collection/generic/CanBuildFrom;)Ljava/lang/Object;
   6:	areturn
  LineNumberTable: 
   line 26: 0

  LocalVariableTable: 
   Start  Length  Slot  Name   Signature
   0      7      0    this       Lscala/collection/mutable/BitSet;
   0      7      1    that       Lscala/collection/Iterable;
   0      7      2    bf       Lscala/collection/generic/CanBuildFrom;


public void copyToArray(java.lang.Object, int, int);
  Code:
   Stack=4, Locals=4, Args_size=4
   0:	aload_0
   1:	aload_1
   2:	iload_2
   3:	iload_3
   4:	invokestatic	#655; //Method scala/collection/IterableLike$class.copyToArray:(Lscala/collection/IterableLike;Ljava/lang/Object;II)V
   7:	return
  LineNumberTable: 
   line 26: 0

  LocalVariableTable: 
   Start  Length  Slot  Name   Signature
   0      8      0    this       Lscala/collection/mutable/BitSet;
   0      8      1    xs       Ljava/lang/Object;
   0      8      2    start       I
   0      8      3    len       I


public java.lang.Object dropRight(int);
  Code:
   Stack=2, Locals=2, Args_size=2
   0:	aload_0
   1:	iload_1
   2:	invokestatic	#660; //Method scala/collection/IterableLike$class.dropRight:(Lscala/collection/IterableLike;I)Ljava/lang/Object;
   5:	areturn
  LineNumberTable: 
   line 26: 0

  LocalVariableTable: 
   Start  Length  Slot  Name   Signature
   0      6      0    this       Lscala/collection/mutable/BitSet;
   0      6      1    n       I


public java.lang.Object takeRight(int);
  Code:
   Stack=2, Locals=2, Args_size=2
   0:	aload_0
   1:	iload_1
   2:	invokestatic	#663; //Method scala/collection/IterableLike$class.takeRight:(Lscala/collection/IterableLike;I)Ljava/lang/Object;
   5:	areturn
  LineNumberTable: 
   line 26: 0

  LocalVariableTable: 
   Start  Length  Slot  Name   Signature
   0      6      0    this       Lscala/collection/mutable/BitSet;
   0      6      1    n       I


public java.lang.Object takeWhile(scala.Function1);
  Code:
   Stack=2, Locals=2, Args_size=2
   0:	aload_0
   1:	aload_1
   2:	invokestatic	#667; //Method scala/collection/IterableLike$class.takeWhile:(Lscala/collection/IterableLike;Lscala/Function1;)Ljava/lang/Object;
   5:	areturn
  LineNumberTable: 
   line 26: 0

  LocalVariableTable: 
   Start  Length  Slot  Name   Signature
   0      6      0    this       Lscala/collection/mutable/BitSet;
   0      6      1    p       Lscala/Function1;


public java.lang.Object slice(int, int);
  Code:
   Stack=3, Locals=3, Args_size=3
   0:	aload_0
   1:	iload_1
   2:	iload_2
   3:	invokestatic	#672; //Method scala/collection/IterableLike$class.slice:(Lscala/collection/IterableLike;II)Ljava/lang/Object;
   6:	areturn
  LineNumberTable: 
   line 26: 0

  LocalVariableTable: 
   Start  Length  Slot  Name   Signature
   0      7      0    this       Lscala/collection/mutable/BitSet;
   0      7      1    from       I
   0      7      2    until       I


public java.lang.Object take(int);
  Code:
   Stack=2, Locals=2, Args_size=2
   0:	aload_0
   1:	iload_1
   2:	invokestatic	#675; //Method scala/collection/IterableLike$class.take:(Lscala/collection/IterableLike;I)Ljava/lang/Object;
   5:	areturn
  LineNumberTable: 
   line 26: 0

  LocalVariableTable: 
   Start  Length  Slot  Name   Signature
   0      6      0    this       Lscala/collection/mutable/BitSet;
   0      6      1    n       I


public java.lang.Object head();
  Code:
   Stack=1, Locals=1, Args_size=1
   0:	aload_0
   1:	invokestatic	#678; //Method scala/collection/IterableLike$class.head:(Lscala/collection/IterableLike;)Ljava/lang/Object;
   4:	areturn
  LineNumberTable: 
   line 26: 0


public scala.collection.Iterable toIterable();
  Code:
   Stack=1, Locals=1, Args_size=1
   0:	aload_0
   1:	invokestatic	#682; //Method scala/collection/IterableLike$class.toIterable:(Lscala/collection/IterableLike;)Lscala/collection/Iterable;
   4:	areturn
  LineNumberTable: 
   line 26: 0


public java.lang.Object reduceRight(scala.Function2);
  Code:
   Stack=2, Locals=2, Args_size=2
   0:	aload_0
   1:	aload_1
   2:	invokestatic	#686; //Method scala/collection/IterableLike$class.reduceRight:(Lscala/collection/IterableLike;Lscala/Function2;)Ljava/lang/Object;
   5:	areturn
  LineNumberTable: 
   line 26: 0

  LocalVariableTable: 
   Start  Length  Slot  Name   Signature
   0      6      0    this       Lscala/collection/mutable/BitSet;
   0      6      1    op       Lscala/Function2;


public java.lang.Object foldRight(java.lang.Object, scala.Function2);
  Code:
   Stack=3, Locals=3, Args_size=3
   0:	aload_0
   1:	aload_1
   2:	aload_2
   3:	invokestatic	#690; //Method scala/collection/IterableLike$class.foldRight:(Lscala/collection/IterableLike;Ljava/lang/Object;Lscala/Function2;)Ljava/lang/Object;
   6:	areturn
  LineNumberTable: 
   line 26: 0

  LocalVariableTable: 
   Start  Length  Slot  Name   Signature
   0      7      0    this       Lscala/collection/mutable/BitSet;
   0      7      1    z       Ljava/lang/Object;
   0      7      2    op       Lscala/Function2;


public scala.Option find(scala.Function1);
  Code:
   Stack=2, Locals=2, Args_size=2
   0:	aload_0
   1:	aload_1
   2:	invokestatic	#695; //Method scala/collection/IterableLike$class.find:(Lscala/collection/IterableLike;Lscala/Function1;)Lscala/Option;
   5:	areturn
  LineNumberTable: 
   line 26: 0

  LocalVariableTable: 
   Start  Length  Slot  Name   Signature
   0      6      0    this       Lscala/collection/mutable/BitSet;
   0      6      1    p       Lscala/Function1;


public boolean exists(scala.Function1);
  Code:
   Stack=2, Locals=2, Args_size=2
   0:	aload_0
   1:	aload_1
   2:	invokestatic	#700; //Method scala/collection/IterableLike$class.exists:(Lscala/collection/IterableLike;Lscala/Function1;)Z
   5:	ireturn
  LineNumberTable: 
   line 26: 0

  LocalVariableTable: 
   Start  Length  Slot  Name   Signature
   0      6      0    this       Lscala/collection/mutable/BitSet;
   0      6      1    p       Lscala/Function1;


public boolean forall(scala.Function1);
  Code:
   Stack=2, Locals=2, Args_size=2
   0:	aload_0
   1:	aload_1
   2:	invokestatic	#703; //Method scala/collection/IterableLike$class.forall:(Lscala/collection/IterableLike;Lscala/Function1;)Z
   5:	ireturn
  LineNumberTable: 
   line 26: 0

  LocalVariableTable: 
   Start  Length  Slot  Name   Signature
   0      6      0    this       Lscala/collection/mutable/BitSet;
   0      6      1    p       Lscala/Function1;


public scala.collection.Iterator elements();
  Code:
   Stack=1, Locals=1, Args_size=1
   0:	aload_0
   1:	invokestatic	#707; //Method scala/collection/IterableLike$class.elements:(Lscala/collection/IterableLike;)Lscala/collection/Iterator;
   4:	areturn
  LineNumberTable: 
   line 26: 0

  Deprecated: true

public scala.collection.Iterable toCollection(java.lang.Object);
  Code:
   Stack=2, Locals=2, Args_size=2
   0:	aload_0
   1:	aload_1
   2:	invokestatic	#710; //Method scala/collection/IterableLike$class.toCollection:(Lscala/collection/IterableLike;Ljava/lang/Object;)Lscala/collection/Iterable;
   5:	areturn
  LineNumberTable: 
   line 26: 0

  LocalVariableTable: 
   Start  Length  Slot  Name   Signature
   0      6      0    this       Lscala/collection/mutable/BitSet;
   0      6      1    repr       Ljava/lang/Object;


public scala.collection.Iterable thisCollection();
  Code:
   Stack=1, Locals=1, Args_size=1
   0:	aload_0
   1:	invokestatic	#712; //Method scala/collection/IterableLike$class.thisCollection:(Lscala/collection/IterableLike;)Lscala/collection/Iterable;
   4:	areturn
  LineNumberTable: 
   line 26: 0


public scala.Function1 andThen(scala.Function1);
  Code:
   Stack=2, Locals=2, Args_size=2
   0:	aload_0
   1:	aload_1
   2:	invokestatic	#717; //Method scala/Function1$class.andThen:(Lscala/Function1;Lscala/Function1;)Lscala/Function1;
   5:	areturn
  LineNumberTable: 
   line 26: 0

  LocalVariableTable: 
   Start  Length  Slot  Name   Signature
   0      6      0    this       Lscala/collection/mutable/BitSet;
   0      6      1    g       Lscala/Function1;


public scala.Function1 compose(scala.Function1);
  Code:
   Stack=2, Locals=2, Args_size=2
   0:	aload_0
   1:	aload_1
   2:	invokestatic	#721; //Method scala/Function1$class.compose:(Lscala/Function1;Lscala/Function1;)Lscala/Function1;
   5:	areturn
  LineNumberTable: 
   line 26: 0

  LocalVariableTable: 
   Start  Length  Slot  Name   Signature
   0      6      0    this       Lscala/collection/mutable/BitSet;
   0      6      1    g       Lscala/Function1;


public boolean equals(java.lang.Object);
  Code:
   Stack=2, Locals=2, Args_size=2
   0:	aload_0
   1:	aload_1
   2:	invokestatic	#725; //Method scala/collection/SetLike$class.equals:(Lscala/collection/SetLike;Ljava/lang/Object;)Z
   5:	ireturn
  LineNumberTable: 
   line 26: 0

  LocalVariableTable: 
   Start  Length  Slot  Name   Signature
   0      6      0    this       Lscala/collection/mutable/BitSet;
   0      6      1    that       Ljava/lang/Object;


public int hashCode();
  Code:
   Stack=1, Locals=1, Args_size=1
   0:	aload_0
   1:	invokestatic	#729; //Method scala/collection/SetLike$class.hashCode:(Lscala/collection/SetLike;)I
   4:	ireturn
  LineNumberTable: 
   line 26: 0


public java.lang.String toString();
  Code:
   Stack=1, Locals=1, Args_size=1
   0:	aload_0
   1:	invokestatic	#733; //Method scala/collection/SetLike$class.toString:(Lscala/collection/SetLike;)Ljava/lang/String;
   4:	areturn
  LineNumberTable: 
   line 26: 0


public boolean subsetOf(scala.collection.Set);
  Code:
   Stack=2, Locals=2, Args_size=2
   0:	aload_0
   1:	aload_1
   2:	invokestatic	#738; //Method scala/collection/SetLike$class.subsetOf:(Lscala/collection/SetLike;Lscala/collection/Set;)Z
   5:	ireturn
  LineNumberTable: 
   line 26: 0

  LocalVariableTable: 
   Start  Length  Slot  Name   Signature
   0      6      0    this       Lscala/collection/mutable/BitSet;
   0      6      1    that       Lscala/collection/Set;


public scala.collection.SetLike $amp$tilde(scala.collection.Set);
  Code:
   Stack=2, Locals=2, Args_size=2
   0:	aload_0
   1:	aload_1
   2:	invokestatic	#744; //Method scala/collection/SetLike$class.$amp$tilde:(Lscala/collection/SetLike;Lscala/collection/Set;)Lscala/collection/SetLike;
   5:	areturn
  LineNumberTable: 
   line 26: 0

  LocalVariableTable: 
   Start  Length  Slot  Name   Signature
   0      6      0    this       Lscala/collection/mutable/BitSet;
   0      6      1    that       Lscala/collection/Set;


public scala.collection.SetLike diff(scala.collection.Set);
  Code:
   Stack=2, Locals=2, Args_size=2
   0:	aload_0
   1:	aload_1
   2:	invokestatic	#747; //Method scala/collection/SetLike$class.diff:(Lscala/collection/SetLike;Lscala/collection/Set;)Lscala/collection/SetLike;
   5:	areturn
  LineNumberTable: 
   line 26: 0

  LocalVariableTable: 
   Start  Length  Slot  Name   Signature
   0      6      0    this       Lscala/collection/mutable/BitSet;
   0      6      1    that       Lscala/collection/Set;


public scala.collection.SetLike $bar(scala.collection.Set);
  Code:
   Stack=2, Locals=2, Args_size=2
   0:	aload_0
   1:	aload_1
   2:	invokestatic	#750; //Method scala/collection/SetLike$class.$bar:(Lscala/collection/SetLike;Lscala/collection/Set;)Lscala/collection/SetLike;
   5:	areturn
  LineNumberTable: 
   line 26: 0

  LocalVariableTable: 
   Start  Length  Slot  Name   Signature
   0      6      0    this       Lscala/collection/mutable/BitSet;
   0      6      1    that       Lscala/collection/Set;


public scala.collection.SetLike union(scala.collection.Set);
  Code:
   Stack=2, Locals=2, Args_size=2
   0:	aload_0
   1:	aload_1
   2:	invokestatic	#753; //Method scala/collection/SetLike$class.union:(Lscala/collection/SetLike;Lscala/collection/Set;)Lscala/collection/SetLike;
   5:	areturn
  LineNumberTable: 
   line 26: 0

  LocalVariableTable: 
   Start  Length  Slot  Name   Signature
   0      6      0    this       Lscala/collection/mutable/BitSet;
   0      6      1    that       Lscala/collection/Set;


public scala.collection.SetLike $times$times(scala.collection.Set);
  Code:
   Stack=2, Locals=2, Args_size=2
   0:	aload_0
   1:	aload_1
   2:	invokestatic	#756; //Method scala/collection/SetLike$class.$times$times:(Lscala/collection/SetLike;Lscala/collection/Set;)Lscala/collection/SetLike;
   5:	areturn
  LineNumberTable: 
   line 26: 0

  LocalVariableTable: 
   Start  Length  Slot  Name   Signature
   0      6      0    this       Lscala/collection/mutable/BitSet;
   0      6      1    that       Lscala/collection/Set;

  Deprecated: true

public scala.collection.SetLike $amp(scala.collection.Set);
  Code:
   Stack=2, Locals=2, Args_size=2
   0:	aload_0
   1:	aload_1
   2:	invokestatic	#759; //Method scala/collection/SetLike$class.$amp:(Lscala/collection/SetLike;Lscala/collection/Set;)Lscala/collection/SetLike;
   5:	areturn
  LineNumberTable: 
   line 26: 0

  LocalVariableTable: 
   Start  Length  Slot  Name   Signature
   0      6      0    this       Lscala/collection/mutable/BitSet;
   0      6      1    that       Lscala/collection/Set;


public scala.collection.SetLike intersect(scala.collection.Set);
  Code:
   Stack=2, Locals=2, Args_size=2
   0:	aload_0
   1:	aload_1
   2:	invokestatic	#762; //Method scala/collection/SetLike$class.intersect:(Lscala/collection/SetLike;Lscala/collection/Set;)Lscala/collection/SetLike;
   5:	areturn
  LineNumberTable: 
   line 26: 0

  LocalVariableTable: 
   Start  Length  Slot  Name   Signature
   0      6      0    this       Lscala/collection/mutable/BitSet;
   0      6      1    that       Lscala/collection/Set;


public boolean apply(java.lang.Object);
  Code:
   Stack=2, Locals=2, Args_size=2
   0:	aload_0
   1:	aload_1
   2:	invokestatic	#764; //Method scala/collection/SetLike$class.apply:(Lscala/collection/SetLike;Ljava/lang/Object;)Z
   5:	ireturn
  LineNumberTable: 
   line 26: 0

  LocalVariableTable: 
   Start  Length  Slot  Name   Signature
   0      6      0    this       Lscala/collection/mutable/BitSet;
   0      6      1    elem       Ljava/lang/Object;


public boolean isEmpty();
  Code:
   Stack=1, Locals=1, Args_size=1
   0:	aload_0
   1:	invokestatic	#768; //Method scala/collection/SetLike$class.isEmpty:(Lscala/collection/SetLike;)Z
   4:	ireturn
  LineNumberTable: 
   line 26: 0


public scala.collection.generic.Growable $plus$plus$eq(scala.collection.Traversable);
  Code:
   Stack=2, Locals=2, Args_size=2
   0:	aload_0
   1:	aload_1
   2:	invokestatic	#773; //Method scala/collection/generic/Growable$class.$plus$plus$eq:(Lscala/collection/generic/Growable;Lscala/collection/Traversable;)Lscala/collection/generic/Growable;
   5:	areturn
  LineNumberTable: 
   line 26: 0

  LocalVariableTable: 
   Start  Length  Slot  Name   Signature
   0      6      0    this       Lscala/collection/mutable/BitSet;
   0      6      1    elems       Lscala/collection/Traversable;


public scala.collection.generic.Growable $plus$plus$eq(scala.collection.Iterator);
  Code:
   Stack=2, Locals=2, Args_size=2
   0:	aload_0
   1:	aload_1
   2:	invokestatic	#777; //Method scala/collection/generic/Growable$class.$plus$plus$eq:(Lscala/collection/generic/Growable;Lscala/collection/Iterator;)Lscala/collection/generic/Growable;
   5:	areturn
  LineNumberTable: 
   line 26: 0

  LocalVariableTable: 
   Start  Length  Slot  Name   Signature
   0      6      0    this       Lscala/collection/mutable/BitSet;
   0      6      1    iter       Lscala/collection/Iterator;


public scala.collection.generic.Growable $plus$eq(java.lang.Object, java.lang.Object, scala.collection.Seq);
  Code:
   Stack=4, Locals=4, Args_size=4
   0:	aload_0
   1:	aload_1
   2:	aload_2
   3:	aload_3
   4:	invokestatic	#781; //Method scala/collection/generic/Growable$class.$plus$eq:(Lscala/collection/generic/Growable;Ljava/lang/Object;Ljava/lang/Object;Lscala/collection/Seq;)Lscala/collection/generic/Growable;
   7:	areturn
  LineNumberTable: 
   line 26: 0

  LocalVariableTable: 
   Start  Length  Slot  Name   Signature
   0      8      0    this       Lscala/collection/mutable/BitSet;
   0      8      1    elem1       Ljava/lang/Object;
   0      8      2    elem2       Ljava/lang/Object;
   0      8      3    elems       Lscala/collection/Seq;


public scala.collection.mutable.Builder mapResult(scala.Function1);
  Code:
   Stack=2, Locals=2, Args_size=2
   0:	aload_0
   1:	aload_1
   2:	invokestatic	#786; //Method scala/collection/mutable/Builder$class.mapResult:(Lscala/collection/mutable/Builder;Lscala/Function1;)Lscala/collection/mutable/Builder;
   5:	areturn
  LineNumberTable: 
   line 26: 0

  LocalVariableTable: 
   Start  Length  Slot  Name   Signature
   0      6      0    this       Lscala/collection/mutable/BitSet;
   0      6      1    f       Lscala/Function1;


public void sizeHint(int);
  Code:
   Stack=2, Locals=2, Args_size=2
   0:	aload_0
   1:	iload_1
   2:	invokestatic	#790; //Method scala/collection/mutable/Builder$class.sizeHint:(Lscala/collection/mutable/Builder;I)V
   5:	return
  LineNumberTable: 
   line 26: 0

  LocalVariableTable: 
   Start  Length  Slot  Name   Signature
   0      6      0    this       Lscala/collection/mutable/BitSet;
   0      6      1    size       I


public scala.collection.generic.Shrinkable $minus$minus$eq(scala.collection.Traversable);
  Code:
   Stack=2, Locals=2, Args_size=2
   0:	aload_0
   1:	aload_1
   2:	invokestatic	#796; //Method scala/collection/generic/Shrinkable$class.$minus$minus$eq:(Lscala/collection/generic/Shrinkable;Lscala/collection/Traversable;)Lscala/collection/generic/Shrinkable;
   5:	areturn
  LineNumberTable: 
   line 26: 0

  LocalVariableTable: 
   Start  Length  Slot  Name   Signature
   0      6      0    this       Lscala/collection/mutable/BitSet;
   0      6      1    iter       Lscala/collection/Traversable;


public scala.collection.generic.Shrinkable $minus$minus$eq(scala.collection.Iterator);
  Code:
   Stack=2, Locals=2, Args_size=2
   0:	aload_0
   1:	aload_1
   2:	invokestatic	#800; //Method scala/collection/generic/Shrinkable$class.$minus$minus$eq:(Lscala/collection/generic/Shrinkable;Lscala/collection/Iterator;)Lscala/collection/generic/Shrinkable;
   5:	areturn
  LineNumberTable: 
   line 26: 0

  LocalVariableTable: 
   Start  Length  Slot  Name   Signature
   0      6      0    this       Lscala/collection/mutable/BitSet;
   0      6      1    iter       Lscala/collection/Iterator;


public scala.collection.generic.Shrinkable $minus$eq(java.lang.Object, java.lang.Object, scala.collection.Seq);
  Code:
   Stack=4, Locals=4, Args_size=4
   0:	aload_0
   1:	aload_1
   2:	aload_2
   3:	aload_3
   4:	invokestatic	#804; //Method scala/collection/generic/Shrinkable$class.$minus$eq:(Lscala/collection/generic/Shrinkable;Ljava/lang/Object;Ljava/lang/Object;Lscala/collection/Seq;)Lscala/collection/generic/Shrinkable;
   7:	areturn
  LineNumberTable: 
   line 26: 0

  LocalVariableTable: 
   Start  Length  Slot  Name   Signature
   0      8      0    this       Lscala/collection/mutable/BitSet;
   0      8      1    elem1       Ljava/lang/Object;
   0      8      2    elem2       Ljava/lang/Object;
   0      8      3    elems       Lscala/collection/Seq;


public final java.lang.Object scala$collection$mutable$Cloneable$$super$clone();
  Code:
   Stack=1, Locals=1, Args_size=1
   0:	aload_0
   1:	invokespecial	#807; //Method java/lang/Object.clone:()Ljava/lang/Object;
   4:	areturn
  LineNumberTable: 
   line 26: 0


public void $less$less(scala.collection.script.Message);
  Code:
   Stack=2, Locals=2, Args_size=2
   0:	aload_0
   1:	aload_1
   2:	invokestatic	#812; //Method scala/collection/mutable/SetLike$class.$less$less:(Lscala/collection/mutable/SetLike;Lscala/collection/script/Message;)V
   5:	return
  LineNumberTable: 
   line 26: 0

  LocalVariableTable: 
   Start  Length  Slot  Name   Signature
   0      6      0    this       Lscala/collection/mutable/BitSet;
   0      6      1    cmd       Lscala/collection/script/Message;


public scala.collection.mutable.SetLike $minus$minus(scala.collection.Iterator);
  Code:
   Stack=2, Locals=2, Args_size=2
   0:	aload_0
   1:	aload_1
   2:	invokestatic	#817; //Method scala/collection/mutable/SetLike$class.$minus$minus:(Lscala/collection/mutable/SetLike;Lscala/collection/Iterator;)Lscala/collection/mutable/SetLike;
   5:	areturn
  LineNumberTable: 
   line 26: 0

  LocalVariableTable: 
   Start  Length  Slot  Name   Signature
   0      6      0    this       Lscala/collection/mutable/BitSet;
   0      6      1    iter       Lscala/collection/Iterator;

  Deprecated: true

public scala.collection.mutable.SetLike $minus$minus(scala.collection.Traversable);
  Code:
   Stack=2, Locals=2, Args_size=2
   0:	aload_0
   1:	aload_1
   2:	invokestatic	#820; //Method scala/collection/mutable/SetLike$class.$minus$minus:(Lscala/collection/mutable/SetLike;Lscala/collection/Traversable;)Lscala/collection/mutable/SetLike;
   5:	areturn
  LineNumberTable: 
   line 26: 0

  LocalVariableTable: 
   Start  Length  Slot  Name   Signature
   0      6      0    this       Lscala/collection/mutable/BitSet;
   0      6      1    iter       Lscala/collection/Traversable;

  Deprecated: true

public scala.collection.mutable.SetLike $minus(java.lang.Object, java.lang.Object, scala.collection.Seq);
  Code:
   Stack=4, Locals=4, Args_size=4
   0:	aload_0
   1:	aload_1
   2:	aload_2
   3:	aload_3
   4:	invokestatic	#823; //Method scala/collection/mutable/SetLike$class.$minus:(Lscala/collection/mutable/SetLike;Ljava/lang/Object;Ljava/lang/Object;Lscala/collection/Seq;)Lscala/collection/mutable/SetLike;
   7:	areturn
  LineNumberTable: 
   line 26: 0

  LocalVariableTable: 
   Start  Length  Slot  Name   Signature
   0      8      0    this       Lscala/collection/mutable/BitSet;
   0      8      1    elem1       Ljava/lang/Object;
   0      8      2    elem2       Ljava/lang/Object;
   0      8      3    elems       Lscala/collection/Seq;

  Deprecated: true

public scala.collection.mutable.SetLike $minus(java.lang.Object);
  Code:
   Stack=2, Locals=2, Args_size=2
   0:	aload_0
   1:	aload_1
   2:	invokestatic	#826; //Method scala/collection/mutable/SetLike$class.$minus:(Lscala/collection/mutable/SetLike;Ljava/lang/Object;)Lscala/collection/mutable/SetLike;
   5:	areturn
  LineNumberTable: 
   line 26: 0

  LocalVariableTable: 
   Start  Length  Slot  Name   Signature
   0      6      0    this       Lscala/collection/mutable/BitSet;
   0      6      1    elem       Ljava/lang/Object;

  Deprecated: true

public scala.collection.mutable.SetLike $plus$plus(scala.collection.Iterator);
  Code:
   Stack=2, Locals=2, Args_size=2
   0:	aload_0
   1:	aload_1
   2:	invokestatic	#828; //Method scala/collection/mutable/SetLike$class.$plus$plus:(Lscala/collection/mutable/SetLike;Lscala/collection/Iterator;)Lscala/collection/mutable/SetLike;
   5:	areturn
  LineNumberTable: 
   line 26: 0

  LocalVariableTable: 
   Start  Length  Slot  Name   Signature
   0      6      0    this       Lscala/collection/mutable/BitSet;
   0      6      1    iter       Lscala/collection/Iterator;

  Deprecated: true

public scala.collection.mutable.SetLike $plus$plus(scala.collection.Traversable);
  Code:
   Stack=2, Locals=2, Args_size=2
   0:	aload_0
   1:	aload_1
   2:	invokestatic	#830; //Method scala/collection/mutable/SetLike$class.$plus$plus:(Lscala/collection/mutable/SetLike;Lscala/collection/Traversable;)Lscala/collection/mutable/SetLike;
   5:	areturn
  LineNumberTable: 
   line 26: 0

  LocalVariableTable: 
   Start  Length  Slot  Name   Signature
   0      6      0    this       Lscala/collection/mutable/BitSet;
   0      6      1    iter       Lscala/collection/Traversable;

  Deprecated: true

public scala.collection.mutable.SetLike $plus(java.lang.Object, java.lang.Object, scala.collection.Seq);
  Code:
   Stack=4, Locals=4, Args_size=4
   0:	aload_0
   1:	aload_1
   2:	aload_2
   3:	aload_3
   4:	invokestatic	#832; //Method scala/collection/mutable/SetLike$class.$plus:(Lscala/collection/mutable/SetLike;Ljava/lang/Object;Ljava/lang/Object;Lscala/collection/Seq;)Lscala/collection/mutable/SetLike;
   7:	areturn
  LineNumberTable: 
   line 26: 0

  LocalVariableTable: 
   Start  Length  Slot  Name   Signature
   0      8      0    this       Lscala/collection/mutable/BitSet;
   0      8      1    elem1       Ljava/lang/Object;
   0      8      2    elem2       Ljava/lang/Object;
   0      8      3    elems       Lscala/collection/Seq;

  Deprecated: true

public scala.collection.mutable.SetLike $plus(java.lang.Object);
  Code:
   Stack=2, Locals=2, Args_size=2
   0:	aload_0
   1:	aload_1
   2:	invokestatic	#834; //Method scala/collection/mutable/SetLike$class.$plus:(Lscala/collection/mutable/SetLike;Ljava/lang/Object;)Lscala/collection/mutable/SetLike;
   5:	areturn
  LineNumberTable: 
   line 26: 0

  LocalVariableTable: 
   Start  Length  Slot  Name   Signature
   0      6      0    this       Lscala/collection/mutable/BitSet;
   0      6      1    elem       Ljava/lang/Object;

  Deprecated: true

public scala.collection.mutable.SetLike result();
  Code:
   Stack=1, Locals=1, Args_size=1
   0:	aload_0
   1:	invokestatic	#837; //Method scala/collection/mutable/SetLike$class.result:(Lscala/collection/mutable/SetLike;)Lscala/collection/mutable/SetLike;
   4:	areturn
  LineNumberTable: 
   line 26: 0


public void retain(scala.Function1);
  Code:
   Stack=2, Locals=2, Args_size=2
   0:	aload_0
   1:	aload_1
   2:	invokestatic	#841; //Method scala/collection/mutable/SetLike$class.retain:(Lscala/collection/mutable/SetLike;Lscala/Function1;)V
   5:	return
  LineNumberTable: 
   line 26: 0

  LocalVariableTable: 
   Start  Length  Slot  Name   Signature
   0      6      0    this       Lscala/collection/mutable/BitSet;
   0      6      1    p       Lscala/Function1;


public void update(java.lang.Object, boolean);
  Code:
   Stack=3, Locals=3, Args_size=3
   0:	aload_0
   1:	aload_1
   2:	iload_2
   3:	invokestatic	#846; //Method scala/collection/mutable/SetLike$class.update:(Lscala/collection/mutable/SetLike;Ljava/lang/Object;Z)V
   6:	return
  LineNumberTable: 
   line 26: 0

  LocalVariableTable: 
   Start  Length  Slot  Name   Signature
   0      7      0    this       Lscala/collection/mutable/BitSet;
   0      7      1    elem       Ljava/lang/Object;
   0      7      2    included       Z


public scala.collection.mutable.Builder newBuilder();
  Code:
   Stack=1, Locals=1, Args_size=1
   0:	aload_0
   1:	invokestatic	#852; //Method scala/collection/mutable/SetLike$class.newBuilder:(Lscala/collection/mutable/SetLike;)Lscala/collection/mutable/Builder;
   4:	areturn
  LineNumberTable: 
   line 26: 0


public scala.collection.generic.GenericCompanion companion();
  Code:
   Stack=1, Locals=1, Args_size=1
   0:	aload_0
   1:	invokestatic	#857; //Method scala/collection/mutable/Set$class.companion:(Lscala/collection/mutable/Set;)Lscala/collection/generic/GenericCompanion;
   4:	areturn
  LineNumberTable: 
   line 26: 0


public java.lang.String stringPrefix();
  Code:
   Stack=1, Locals=1, Args_size=1
   0:	aload_0
   1:	invokestatic	#861; //Method scala/collection/BitSetLike$class.stringPrefix:(Lscala/collection/BitSetLike;)Ljava/lang/String;
   4:	areturn
  LineNumberTable: 
   line 26: 0


public scala.collection.mutable.StringBuilder addString(scala.collection.mutable.StringBuilder, java.lang.String, java.lang.String, java.lang.String);
  Code:
   Stack=5, Locals=5, Args_size=5
   0:	aload_0
   1:	aload_1
   2:	aload_2
   3:	aload_3
   4:	aload	4
   6:	invokestatic	#865; //Method scala/collection/BitSetLike$class.addString:(Lscala/collection/BitSetLike;Lscala/collection/mutable/StringBuilder;Ljava/lang/String;Ljava/lang/String;Ljava/lang/String;)Lscala/collection/mutable/StringBuilder;
   9:	areturn
  LineNumberTable: 
   line 26: 0

  LocalVariableTable: 
   Start  Length  Slot  Name   Signature
   0      10      0    this       Lscala/collection/mutable/BitSet;
   0      10      1    sb       Lscala/collection/mutable/StringBuilder;
   0      10      2    start       Ljava/lang/String;
   0      10      3    sep       Ljava/lang/String;
   0      10      4    end       Ljava/lang/String;


public boolean subsetOf(scala.collection.BitSet);
  Code:
   Stack=2, Locals=2, Args_size=2
   0:	aload_0
   1:	aload_1
   2:	invokestatic	#870; //Method scala/collection/BitSetLike$class.subsetOf:(Lscala/collection/BitSetLike;Lscala/collection/BitSet;)Z
   5:	ireturn
  LineNumberTable: 
   line 26: 0

  LocalVariableTable: 
   Start  Length  Slot  Name   Signature
   0      6      0    this       Lscala/collection/mutable/BitSet;
   0      6      1    other       Lscala/collection/BitSet;


public boolean contains(int);
  Code:
   Stack=2, Locals=2, Args_size=2
   0:	aload_0
   1:	iload_1
   2:	invokestatic	#875; //Method scala/collection/BitSetLike$class.contains:(Lscala/collection/BitSetLike;I)Z
   5:	ireturn
  LineNumberTable: 
   line 26: 0

  LocalVariableTable: 
   Start  Length  Slot  Name   Signature
   0      6      0    this       Lscala/collection/mutable/BitSet;
   0      6      1    elem       I


public scala.collection.BitSetLike $up(scala.collection.BitSet);
  Code:
   Stack=2, Locals=2, Args_size=2
   0:	aload_0
   1:	aload_1
   2:	invokestatic	#880; //Method scala/collection/BitSetLike$class.$up:(Lscala/collection/BitSetLike;Lscala/collection/BitSet;)Lscala/collection/BitSetLike;
   5:	areturn
  LineNumberTable: 
   line 26: 0

  LocalVariableTable: 
   Start  Length  Slot  Name   Signature
   0      6      0    this       Lscala/collection/mutable/BitSet;
   0      6      1    other       Lscala/collection/BitSet;


public scala.collection.BitSetLike $amp$tilde(scala.collection.BitSet);
  Code:
   Stack=2, Locals=2, Args_size=2
   0:	aload_0
   1:	aload_1
   2:	invokestatic	#882; //Method scala/collection/BitSetLike$class.$amp$tilde:(Lscala/collection/BitSetLike;Lscala/collection/BitSet;)Lscala/collection/BitSetLike;
   5:	areturn
  LineNumberTable: 
   line 26: 0

  LocalVariableTable: 
   Start  Length  Slot  Name   Signature
   0      6      0    this       Lscala/collection/mutable/BitSet;
   0      6      1    other       Lscala/collection/BitSet;


public scala.collection.BitSetLike $amp(scala.collection.BitSet);
  Code:
   Stack=2, Locals=2, Args_size=2
   0:	aload_0
   1:	aload_1
   2:	invokestatic	#884; //Method scala/collection/BitSetLike$class.$amp:(Lscala/collection/BitSetLike;Lscala/collection/BitSet;)Lscala/collection/BitSetLike;
   5:	areturn
  LineNumberTable: 
   line 26: 0

  LocalVariableTable: 
   Start  Length  Slot  Name   Signature
   0      6      0    this       Lscala/collection/mutable/BitSet;
   0      6      1    other       Lscala/collection/BitSet;


public scala.collection.BitSetLike $bar(scala.collection.BitSet);
  Code:
   Stack=2, Locals=2, Args_size=2
   0:	aload_0
   1:	aload_1
   2:	invokestatic	#886; //Method scala/collection/BitSetLike$class.$bar:(Lscala/collection/BitSetLike;Lscala/collection/BitSet;)Lscala/collection/BitSetLike;
   5:	areturn
  LineNumberTable: 
   line 26: 0

  LocalVariableTable: 
   Start  Length  Slot  Name   Signature
   0      6      0    this       Lscala/collection/mutable/BitSet;
   0      6      1    other       Lscala/collection/BitSet;


public void foreach(scala.Function1);
  Code:
   Stack=2, Locals=2, Args_size=2
   0:	aload_0
   1:	aload_1
   2:	invokestatic	#890; //Method scala/collection/BitSetLike$class.foreach:(Lscala/collection/BitSetLike;Lscala/Function1;)V
   5:	return
  LineNumberTable: 
   line 26: 0

  LocalVariableTable: 
   Start  Length  Slot  Name   Signature
   0      6      0    this       Lscala/collection/mutable/BitSet;
   0      6      1    f       Lscala/Function1;


public java.lang.Object iterator();
  Code:
   Stack=1, Locals=1, Args_size=1
   0:	aload_0
   1:	invokestatic	#893; //Method scala/collection/BitSetLike$class.iterator:(Lscala/collection/BitSetLike;)Ljava/lang/Object;
   4:	areturn
  LineNumberTable: 
   line 26: 0


public int size();
  Code:
   Stack=1, Locals=1, Args_size=1
   0:	aload_0
   1:	invokestatic	#896; //Method scala/collection/BitSetLike$class.size:(Lscala/collection/BitSetLike;)I
   4:	ireturn
  LineNumberTable: 
   line 26: 0


}

