Compiled from "BufferLike.scala"
public final class scala.collection.mutable.BufferLike$$anonfun$$minus$minus$1 extends scala.runtime.AbstractFunction1 implements java.io.Serializable
  SourceFile: "BufferLike.scala"
  Scala: length = 0x
   
  InnerClass: 
   public final #47= #9 of #39; //$anonfun$$minus$minus$1=class scala/collection/mutable/BufferLike$$anonfun$$minus$minus$1 of class scala/collection/mutable/BufferLike
  minor version: 0
  major version: 49
  Constant pool:
const #1 = Asciz	SourceFile;
const #2 = Asciz	BufferLike.scala;
const #3 = Asciz	<clinit>;
const #4 = Asciz	()V;
const #5 = Asciz	Code;
const #6 = Asciz	serialVersionUID;
const #7 = Asciz	J;
const #8 = Asciz	scala/collection/mutable/BufferLike$$anonfun$$minus$minus$1;
const #9 = class	#8;	//  scala/collection/mutable/BufferLike$$anonfun$$minus$minus$1
const #10 = NameAndType	#6:#7;//  serialVersionUID:J
const #11 = Field	#9.#10;	//  scala/collection/mutable/BufferLike$$anonfun$$minus$minus$1.serialVersionUID:J
const #12 = Asciz	$outer;
const #13 = Asciz	Lscala/collection/mutable/BufferLike;;
const #14 = Asciz	<init>;
const #15 = Asciz	(Lscala/collection/mutable/BufferLike;)V;
const #16 = Asciz	LineNumberTable;
const #17 = Asciz	java/lang/NullPointerException;
const #18 = class	#17;	//  java/lang/NullPointerException
const #19 = NameAndType	#14:#4;//  "<init>":()V
const #20 = Method	#18.#19;	//  java/lang/NullPointerException."<init>":()V
const #21 = NameAndType	#12:#13;//  $outer:Lscala/collection/mutable/BufferLike;
const #22 = Field	#9.#21;	//  scala/collection/mutable/BufferLike$$anonfun$$minus$minus$1.$outer:Lscala/collection/mutable/BufferLike;
const #23 = Asciz	scala/runtime/AbstractFunction1;
const #24 = class	#23;	//  scala/runtime/AbstractFunction1
const #25 = Method	#24.#19;	//  scala/runtime/AbstractFunction1."<init>":()V
const #26 = Asciz	this;
const #27 = Asciz	Lscala/collection/mutable/BufferLike$$anonfun$$minus$minus$1;;
const #28 = Asciz	LocalVariableTable;
const #29 = Asciz	(TThis;)V;
const #30 = Asciz	Signature;
const #31 = Asciz	apply;
const #32 = Asciz	(Ljava/lang/Object;)Ljava/lang/Object;;
const #33 = Asciz	(Ljava/lang/Object;)Lscala/collection/mutable/BufferLike;;
const #34 = NameAndType	#31:#33;//  apply:(Ljava/lang/Object;)Lscala/collection/mutable/BufferLike;
const #35 = Method	#9.#34;	//  scala/collection/mutable/BufferLike$$anonfun$$minus$minus$1.apply:(Ljava/lang/Object;)Lscala/collection/mutable/BufferLike;
const #36 = Asciz	v1;
const #37 = Asciz	Ljava/lang/Object;;
const #38 = Asciz	scala/collection/mutable/BufferLike;
const #39 = class	#38;	//  scala/collection/mutable/BufferLike
const #40 = Asciz	$minus$eq;
const #41 = NameAndType	#40:#33;//  $minus$eq:(Ljava/lang/Object;)Lscala/collection/mutable/BufferLike;
const #42 = InterfaceMethod	#39.#41;	//  scala/collection/mutable/BufferLike.$minus$eq:(Ljava/lang/Object;)Lscala/collection/mutable/BufferLike;
const #43 = Asciz	elem;
const #44 = Asciz	(TA;)TThis;;
const #45 = Asciz	Scala;
const #46 = Asciz	InnerClasses;
const #47 = Asciz	$anonfun$$minus$minus$1;
const #48 = Asciz	java/io/Serializable;
const #49 = class	#48;	//  java/io/Serializable

{
public static final long serialVersionUID;

public static {};
  Code:
   Stack=2, Locals=0, Args_size=0
   0:	lconst_0
   1:	putstatic	#11; //Field serialVersionUID:J
   4:	return

public scala.collection.mutable.BufferLike$$anonfun$$minus$minus$1(scala.collection.mutable.BufferLike);
  Code:
   Stack=2, Locals=2, Args_size=2
   0:	aload_1
   1:	ifnonnull	12
   4:	new	#18; //class java/lang/NullPointerException
   7:	dup
   8:	invokespecial	#20; //Method java/lang/NullPointerException."<init>":()V
   11:	athrow
   12:	aload_0
   13:	aload_1
   14:	putfield	#22; //Field $outer:Lscala/collection/mutable/BufferLike;
   17:	aload_0
   18:	invokespecial	#25; //Method scala/runtime/AbstractFunction1."<init>":()V
   21:	return
  LineNumberTable: 
   line 321: 0

  LocalVariableTable: 
   Start  Length  Slot  Name   Signature
   0      22      0    this       Lscala/collection/mutable/BufferLike$$anonfun$$minus$minus$1;
   0      22      1    $outer       Lscala/collection/mutable/BufferLike;

  Signature: length = 0x2
   00 1D 

public final java.lang.Object apply(java.lang.Object);
  Code:
   Stack=2, Locals=2, Args_size=2
   0:	aload_0
   1:	aload_1
   2:	invokevirtual	#35; //Method apply:(Ljava/lang/Object;)Lscala/collection/mutable/BufferLike;
   5:	areturn
  LineNumberTable: 
   line 321: 0

  LocalVariableTable: 
   Start  Length  Slot  Name   Signature
   0      6      0    this       Lscala/collection/mutable/BufferLike$$anonfun$$minus$minus$1;
   0      6      1    v1       Ljava/lang/Object;


public final scala.collection.mutable.BufferLike apply(java.lang.Object);
  Code:
   Stack=2, Locals=2, Args_size=2
   0:	aload_0
   1:	getfield	#22; //Field $outer:Lscala/collection/mutable/BufferLike;
   4:	aload_1
   5:	invokeinterface	#42,  2; //InterfaceMethod scala/collection/mutable/BufferLike.$minus$eq:(Ljava/lang/Object;)Lscala/collection/mutable/BufferLike;
   10:	areturn
  LineNumberTable: 
   line 321: 0

  LocalVariableTable: 
   Start  Length  Slot  Name   Signature
   0      11      0    this       Lscala/collection/mutable/BufferLike$$anonfun$$minus$minus$1;
   0      11      1    elem       Ljava/lang/Object;

  Signature: length = 0x2
   00 2C 

}

