Compiled from "BufferLike.scala"
public final class scala.collection.mutable.BufferLike$$anonfun$$less$less$1 extends scala.runtime.AbstractFunction1 implements java.io.Serializable
  SourceFile: "BufferLike.scala"
  Scala: length = 0x
   
  InnerClass: 
   public final $anonfun$$less$less$1=class scala/collection/mutable/BufferLike$$anonfun$$less$less$1 of class scala/collection/mutable/BufferLike
  minor version: 0
  major version: 49
  Constant pool:
Asciz	SourceFile;
Asciz	BufferLike.scala;
Asciz	<clinit>;
Asciz	()V;
Asciz	Code;
Asciz	serialVersionUID;
Asciz	J;
Asciz	scala/collection/mutable/BufferLike$$anonfun$$less$less$1;
class	scala/collection/mutable/BufferLike$$anonfun$$less$less$1
NameAndType	serialVersionUID:J
Field	scala/collection/mutable/BufferLike$$anonfun$$less$less$1.serialVersionUID:J
Asciz	$outer;
Asciz	Lscala/collection/mutable/Buffer;;
Asciz	apply;
Asciz	(Lscala/collection/script/Message;)V;
Asciz	LineNumberTable;
NameAndType	$outer:Lscala/collection/mutable/Buffer;
Field	scala/collection/mutable/BufferLike$$anonfun$$less$less$1.$outer:Lscala/collection/mutable/Buffer;
Asciz	scala/collection/mutable/BufferLike;
class	scala/collection/mutable/BufferLike
Asciz	$less$less;
NameAndType	$less$less:(Lscala/collection/script/Message;)V
InterfaceMethod	scala/collection/mutable/BufferLike.$less$less:(Lscala/collection/script/Message;)V
Asciz	(Lscala/collection/script/Message<TA;>;)V;
Asciz	Signature;
Asciz	(Ljava/lang/Object;)Ljava/lang/Object;;
Asciz	scala/collection/script/Message;
class	scala/collection/script/Message
NameAndType	apply:(Lscala/collection/script/Message;)V
Method	scala/collection/mutable/BufferLike$$anonfun$$less$less$1.apply:(Lscala/collection/script/Message;)V
Asciz	scala/runtime/BoxedUnit;
class	scala/runtime/BoxedUnit
Asciz	UNIT;
Asciz	Lscala/runtime/BoxedUnit;;
NameAndType	UNIT:Lscala/runtime/BoxedUnit;
Field	scala/runtime/BoxedUnit.UNIT:Lscala/runtime/BoxedUnit;
Asciz	this;
Asciz	Lscala/collection/mutable/BufferLike$$anonfun$$less$less$1;;
Asciz	v1;
Asciz	Ljava/lang/Object;;
Asciz	LocalVariableTable;
Asciz	<init>;
Asciz	(Lscala/collection/mutable/Buffer;)V;
Asciz	java/lang/NullPointerException;
class	java/lang/NullPointerException
NameAndType	"<init>":()V
Method	java/lang/NullPointerException."<init>":()V
Asciz	scala/runtime/AbstractFunction1;
class	scala/runtime/AbstractFunction1
Method	scala/runtime/AbstractFunction1."<init>":()V
Asciz	(TThis;)V;
Asciz	Scala;
Asciz	InnerClasses;
Asciz	$anonfun$$less$less$1;
Asciz	java/io/Serializable;
class	java/io/Serializable

{
public static final long serialVersionUID;
  Signature: J

private final scala.collection.mutable.Buffer $outer;
  Signature: Lscala/collection/mutable/Buffer;

public static {};
  Signature: ()V
  Code:
   Stack=2, Locals=0, Args_size=0
	lconst_0
	putstatic	Field serialVersionUID:J
	return
  Labels:

public final void apply(scala.collection.script.Message);
  Signature: (Lscala/collection/script/Message;)V
  Code:
   Stack=2, Locals=2, Args_size=2
	aload_0
	getfield	Field $outer:Lscala/collection/mutable/Buffer;
	aload_1
	invokeinterface	InterfaceMethod scala/collection/mutable/BufferLike.$less$less:(Lscala/collection/script/Message;)V
	return
  Labels:
  Signature: length = 0x2
   00 18 

public final java.lang.Object apply(java.lang.Object);
  Signature: (Ljava/lang/Object;)Ljava/lang/Object;
  Code:
   Stack=2, Locals=2, Args_size=2
	aload_0
	aload_1
	checkcast	class scala/collection/script/Message
	invokevirtual	Method apply:(Lscala/collection/script/Message;)V
	getstatic	Field scala/runtime/BoxedUnit.UNIT:Lscala/runtime/BoxedUnit;
	areturn
  Labels:
  LocalVariableTable: 
   Start  Length  Slot  Name   Signature
   0      12      0    this       Lscala/collection/mutable/BufferLike$$anonfun$$less$less$1;
   0      12      1    v1       Ljava/lang/Object;


public scala.collection.mutable.BufferLike$$anonfun$$less$less$1(scala.collection.mutable.Buffer);
  Signature: (Lscala/collection/mutable/Buffer;)V
  Code:
   Stack=2, Locals=2, Args_size=2
	aload_1
	ifnonnull	l1 // aload_0
	new	class java/lang/NullPointerException
	dup
	invokespecial	Method java/lang/NullPointerException."<init>":()V
	athrow
l1	aload_0
	aload_1
	putfield	Field $outer:Lscala/collection/mutable/Buffer;
	aload_0
	invokespecial	Method scala/runtime/AbstractFunction1."<init>":()V
	return
  Labels:
   	l1 = 12 // aload_0
  LocalVariableTable: 
   Start  Length  Slot  Name   Signature
   0      22      0    this       Lscala/collection/mutable/BufferLike$$anonfun$$less$less$1;
   0      22      1    $outer       Lscala/collection/mutable/Buffer;

  Signature: length = 0x2
   00 33 

}

