Compiled from "Buffer.scala"
public final class scala.collection.mutable.Buffer$$anonfun$$plus$plus$eq$1 extends java.lang.Object implements java.io.Serializable,scala.Function1
  InnerClass: 
   public final $anonfun$$plus$plus$eq$1=class scala/collection/mutable/Buffer$$anonfun$$plus$plus$eq$1 of class scala/collection/mutable/Buffer
  Scala: length = 0x
   
  SourceFile: "Buffer.scala"
  minor version: 0
  major version: 49
  Constant pool:
class	java/io/Serializable
class	java/lang/NullPointerException
class	java/lang/Object
class	scala/Function1
class	scala/Function1$class
class	scala/collection/mutable/Buffer
class	scala/collection/mutable/Buffer$$anonfun$$plus$plus$eq$1
class	scala/runtime/BoxedUnit
Field	scala/collection/mutable/Buffer$$anonfun$$plus$plus$eq$1.$outer:Lscala/collection/mutable/Buffer;
Field	scala/runtime/BoxedUnit.UNIT:Lscala/runtime/BoxedUnit;
Method	java/lang/NullPointerException."<init>":()V
Method	java/lang/Object."<init>":()V
Method	scala/Function1$class.$init$:(Lscala/Function1;)V
Method	scala/Function1$class.toString:(Lscala/Function1;)Ljava/lang/String;
Method	scala/collection/mutable/Buffer$$anonfun$$plus$plus$eq$1.apply:(Ljava/lang/Object;)V
InterfaceMethod	scala/collection/mutable/Buffer.$plus$eq:(Ljava/lang/Object;)V
NameAndType	$init$:(Lscala/Function1;)V
NameAndType	$outer:Lscala/collection/mutable/Buffer;
NameAndType	$plus$eq:(Ljava/lang/Object;)V
NameAndType	"<init>":()V
NameAndType	UNIT:Lscala/runtime/BoxedUnit;
NameAndType	apply:(Ljava/lang/Object;)V
NameAndType	toString:(Lscala/Function1;)Ljava/lang/String;
Asciz	$anonfun$$plus$plus$eq$1;
Asciz	$init$;
Asciz	$outer;
Asciz	$plus$eq;
Asciz	()Ljava/lang/String;;
Asciz	()V;
Asciz	(Ljava/lang/Object;)Ljava/lang/Object;;
Asciz	(Ljava/lang/Object;)V;
Asciz	(Lscala/Function1;)Ljava/lang/String;;
Asciz	(Lscala/Function1;)V;
Asciz	(Lscala/collection/mutable/Buffer;)V;
Asciz	(Lscala/collection/mutable/Buffer<TA;>;)V;
Asciz	(TA;)V;
Asciz	<init>;
Asciz	Buffer.scala;
Asciz	Code;
Asciz	InnerClasses;
Asciz	LineNumberTable;
Asciz	Ljava/lang/Object;;
Asciz	LocalVariableTable;
Asciz	Lscala/collection/mutable/Buffer$$anonfun$$plus$plus$eq$1;;
Asciz	Lscala/collection/mutable/Buffer;;
Asciz	Lscala/runtime/BoxedUnit;;
Asciz	Scala;
Asciz	Signature;
Asciz	SourceFile;
Asciz	UNIT;
Asciz	apply;
Asciz	java/io/Serializable;
Asciz	java/lang/NullPointerException;
Asciz	java/lang/Object;
Asciz	scala/Function1;
Asciz	scala/Function1$class;
Asciz	scala/collection/mutable/Buffer;
Asciz	scala/collection/mutable/Buffer$$anonfun$$plus$plus$eq$1;
Asciz	scala/runtime/BoxedUnit;
Asciz	this;
Asciz	toString;
Asciz	x$1;

{
private final scala.collection.mutable.Buffer $outer;
  Signature: Lscala/collection/mutable/Buffer;

public scala.collection.mutable.Buffer$$anonfun$$plus$plus$eq$1(scala.collection.mutable.Buffer);
  Signature: (Lscala/collection/mutable/Buffer;)V
  Code:
   Stack=2, Locals=2, Args_size=2
	aload_1
	ifnonnull	l1 // aload_0
	new	class java/lang/NullPointerException
	dup
	invokespecial	Method java/lang/NullPointerException."<init>":()V
	athrow
l1	aload_0
	aload_1
	putfield	Field $outer:Lscala/collection/mutable/Buffer;
	aload_0
	invokespecial	Method java/lang/Object."<init>":()V
	aload_0
	invokestatic	Method scala/Function1$class.$init$:(Lscala/Function1;)V
	return
  Labels:
   	l1 = 12 // aload_0
  LocalVariableTable: 
   Start  Length  Slot  Name   Signature
   0      26      0    this       Lscala/collection/mutable/Buffer$$anonfun$$plus$plus$eq$1;
   0      26      1    $outer       Lscala/collection/mutable/Buffer;

  Signature: length = 0x2
   00 23 

public final java.lang.Object apply(java.lang.Object);
  Signature: (Ljava/lang/Object;)Ljava/lang/Object;
  Code:
   Stack=2, Locals=3, Args_size=2
	aload_0
	getfield	Field $outer:Lscala/collection/mutable/Buffer;
	astore_2
	aload_0
	aload_1
	invokevirtual	Method apply:(Ljava/lang/Object;)V
	getstatic	Field scala/runtime/BoxedUnit.UNIT:Lscala/runtime/BoxedUnit;
	areturn
  Labels:
  LocalVariableTable: 
   Start  Length  Slot  Name   Signature
   0      14      0    this       Lscala/collection/mutable/Buffer$$anonfun$$plus$plus$eq$1;
   5      9      1    x$1       Ljava/lang/Object;


public final void apply(java.lang.Object);
  Signature: (Ljava/lang/Object;)V
  Code:
   Stack=2, Locals=3, Args_size=2
	aload_0
	getfield	Field $outer:Lscala/collection/mutable/Buffer;
	astore_2
	aload_0
	getfield	Field $outer:Lscala/collection/mutable/Buffer;
	aload_1
	invokeinterface	InterfaceMethod scala/collection/mutable/Buffer.$plus$eq:(Ljava/lang/Object;)V
	return
  Labels:
  LocalVariableTable: 
   Start  Length  Slot  Name   Signature
   0      16      0    this       Lscala/collection/mutable/Buffer$$anonfun$$plus$plus$eq$1;

  Signature: length = 0x2
   00 24 

public java.lang.String toString();
  Signature: ()Ljava/lang/String;
  Code:
   Stack=1, Locals=1, Args_size=1
	aload_0
	invokestatic	Method scala/Function1$class.toString:(Lscala/Function1;)Ljava/lang/String;
	areturn
  Labels:

}

