Compiled from "Buffer.scala"
public abstract class scala.collection.mutable.Buffer$class extends java.lang.Object
  InnerClass: 
   public final $anonfun$$plus$plus$eq$1=class scala/collection/mutable/Buffer$$anonfun$$plus$plus$eq$1 of class scala/collection/mutable/Buffer
  Scala: length = 0x
   
  SourceFile: "Buffer.scala"
  minor version: 0
  major version: 49
  Constant pool:
String	unsuitable as hash key
class	java/lang/Object
class	java/lang/UnsupportedOperationException
class	scala/Iterable
class	scala/Iterator
class	scala/collection/mutable/Buffer
class	scala/collection/mutable/Buffer$$anonfun$$plus$plus$eq$1
class	scala/collection/mutable/Buffer$class
Method	java/lang/UnsupportedOperationException."<init>":(Ljava/lang/String;)V
Method	scala/collection/mutable/Buffer$$anonfun$$plus$plus$eq$1."<init>":(Lscala/collection/mutable/Buffer;)V
InterfaceMethod	scala/Iterable.elements:()Lscala/Iterator;
InterfaceMethod	scala/Iterator.foreach:(Lscala/Function1;)V
InterfaceMethod	scala/collection/mutable/Buffer.$plus$plus$eq:(Lscala/Iterable;)V
InterfaceMethod	scala/collection/mutable/Buffer.$plus$plus$eq:(Lscala/Iterator;)V
NameAndType	$plus$plus$eq:(Lscala/Iterable;)V
NameAndType	$plus$plus$eq:(Lscala/Iterator;)V
NameAndType	"<init>":(Ljava/lang/String;)V
NameAndType	"<init>":(Lscala/collection/mutable/Buffer;)V
NameAndType	elements:()Lscala/Iterator;
NameAndType	foreach:(Lscala/Function1;)V
Asciz	$anonfun$$plus$plus$eq$1;
Asciz	$init$;
Asciz	$plus$plus;
Asciz	$plus$plus$eq;
Asciz	$this;
Asciz	()Lscala/Iterator;;
Asciz	(Ljava/lang/String;)V;
Asciz	(Lscala/Function1;)V;
Asciz	(Lscala/Iterable;)V;
Asciz	(Lscala/Iterator;)V;
Asciz	(Lscala/collection/mutable/Buffer;)I;
Asciz	(Lscala/collection/mutable/Buffer;)V;
Asciz	(Lscala/collection/mutable/Buffer;Lscala/Iterable;)Lscala/collection/mutable/Buffer;;
Asciz	(Lscala/collection/mutable/Buffer;Lscala/Iterable;)V;
Asciz	(Lscala/collection/mutable/Buffer;Lscala/Iterator;)V;
Asciz	<init>;
Asciz	Buffer.scala;
Asciz	Code;
Asciz	InnerClasses;
Asciz	LineNumberTable;
Asciz	LocalVariableTable;
Asciz	Lscala/Iterable;;
Asciz	Lscala/Iterator;;
Asciz	Lscala/collection/mutable/Buffer;;
Asciz	Scala;
Asciz	SourceFile;
Asciz	elements;
Asciz	foreach;
Asciz	hashCode;
Asciz	iter;
Asciz	java/lang/Object;
Asciz	java/lang/UnsupportedOperationException;
Asciz	scala/Iterable;
Asciz	scala/Iterator;
Asciz	scala/collection/mutable/Buffer;
Asciz	scala/collection/mutable/Buffer$$anonfun$$plus$plus$eq$1;
Asciz	scala/collection/mutable/Buffer$class;
Asciz	unsuitable as hash key;

{
public static void $init$(scala.collection.mutable.Buffer);
  Signature: (Lscala/collection/mutable/Buffer;)V
  Code:
   Stack=0, Locals=1, Args_size=1
	return
  Labels:
  LocalVariableTable: 
   Start  Length  Slot  Name   Signature
   0      1      0    $this       Lscala/collection/mutable/Buffer;


public static int hashCode(scala.collection.mutable.Buffer);
  Signature: (Lscala/collection/mutable/Buffer;)I
  Code:
   Stack=3, Locals=1, Args_size=1
	new	class java/lang/UnsupportedOperationException
	dup
	ldc	String unsuitable as hash key
	invokespecial	Method java/lang/UnsupportedOperationException."<init>":(Ljava/lang/String;)V
	athrow
  Labels:
  LocalVariableTable: 
   Start  Length  Slot  Name   Signature
   0      10      0    $this       Lscala/collection/mutable/Buffer;


public static scala.collection.mutable.Buffer $plus$plus(scala.collection.mutable.Buffer, scala.Iterable);
  Signature: (Lscala/collection/mutable/Buffer;Lscala/Iterable;)Lscala/collection/mutable/Buffer;
  Code:
   Stack=2, Locals=2, Args_size=2
	aload_0
	aload_1
	invokeinterface	InterfaceMethod scala/collection/mutable/Buffer.$plus$plus$eq:(Lscala/Iterable;)V
	aload_0
	areturn
  Labels:
  LocalVariableTable: 
   Start  Length  Slot  Name   Signature
   0      9      0    $this       Lscala/collection/mutable/Buffer;
   0      9      1    iter       Lscala/Iterable;


public static void $plus$plus$eq(scala.collection.mutable.Buffer, scala.Iterable);
  Signature: (Lscala/collection/mutable/Buffer;Lscala/Iterable;)V
  Code:
   Stack=2, Locals=2, Args_size=2
	aload_0
	aload_1
	invokeinterface	InterfaceMethod scala/Iterable.elements:()Lscala/Iterator;
	invokeinterface	InterfaceMethod scala/collection/mutable/Buffer.$plus$plus$eq:(Lscala/Iterator;)V
	return
  Labels:
  LocalVariableTable: 
   Start  Length  Slot  Name   Signature
   0      13      0    $this       Lscala/collection/mutable/Buffer;
   0      13      1    iter       Lscala/Iterable;


public static void $plus$plus$eq(scala.collection.mutable.Buffer, scala.Iterator);
  Signature: (Lscala/collection/mutable/Buffer;Lscala/Iterator;)V
  Code:
   Stack=4, Locals=2, Args_size=2
	aload_1
	new	class scala/collection/mutable/Buffer$$anonfun$$plus$plus$eq$1
	dup
	aload_0
	invokespecial	Method scala/collection/mutable/Buffer$$anonfun$$plus$plus$eq$1."<init>":(Lscala/collection/mutable/Buffer;)V
	invokeinterface	InterfaceMethod scala/Iterator.foreach:(Lscala/Function1;)V
	return
  Labels:
  LocalVariableTable: 
   Start  Length  Slot  Name   Signature
   0      15      0    $this       Lscala/collection/mutable/Buffer;
   0      15      1    iter       Lscala/Iterator;


}

