Compiled from "BufferProxy.scala"
public abstract class scala.collection.mutable.BufferProxy$class extends java.lang.Object
  SourceFile: "BufferProxy.scala"
  Scala: length = 0x
   
  InnerClass: 
   public final #132= #13 of #20; //$anon$1=class scala/collection/mutable/BufferProxy$$anon$1 of class scala/collection/mutable/BufferProxy
  minor version: 0
  major version: 49
  Constant pool:
const #1 = Asciz	SourceFile;
const #2 = Asciz	BufferProxy.scala;
const #3 = Asciz	$init$;
const #4 = Asciz	(Lscala/collection/mutable/BufferProxy;)V;
const #5 = Asciz	Code;
const #6 = Asciz	LineNumberTable;
const #7 = Asciz	$this;
const #8 = Asciz	Lscala/collection/mutable/BufferProxy;;
const #9 = Asciz	LocalVariableTable;
const #10 = Asciz	clone;
const #11 = Asciz	(Lscala/collection/mutable/BufferProxy;)Lscala/collection/mutable/Buffer;;
const #12 = Asciz	scala/collection/mutable/BufferProxy$$anon$1;
const #13 = class	#12;	//  scala/collection/mutable/BufferProxy$$anon$1
const #14 = Asciz	<init>;
const #15 = NameAndType	#14:#4;//  "<init>":(Lscala/collection/mutable/BufferProxy;)V
const #16 = Method	#13.#15;	//  scala/collection/mutable/BufferProxy$$anon$1."<init>":(Lscala/collection/mutable/BufferProxy;)V
const #17 = Asciz	$less$less;
const #18 = Asciz	(Lscala/collection/mutable/BufferProxy;Lscala/collection/script/Message;)V;
const #19 = Asciz	scala/collection/mutable/BufferProxy;
const #20 = class	#19;	//  scala/collection/mutable/BufferProxy
const #21 = Asciz	self;
const #22 = Asciz	()Lscala/collection/mutable/Buffer;;
const #23 = NameAndType	#21:#22;//  self:()Lscala/collection/mutable/Buffer;
const #24 = InterfaceMethod	#20.#23;	//  scala/collection/mutable/BufferProxy.self:()Lscala/collection/mutable/Buffer;
const #25 = Asciz	scala/collection/mutable/BufferLike;
const #26 = class	#25;	//  scala/collection/mutable/BufferLike
const #27 = Asciz	(Lscala/collection/script/Message;)V;
const #28 = NameAndType	#17:#27;//  $less$less:(Lscala/collection/script/Message;)V
const #29 = InterfaceMethod	#26.#28;	//  scala/collection/mutable/BufferLike.$less$less:(Lscala/collection/script/Message;)V
const #30 = Asciz	cmd;
const #31 = Asciz	Lscala/collection/script/Message;;
const #32 = Asciz	clear;
const #33 = Asciz	()V;
const #34 = NameAndType	#32:#33;//  clear:()V
const #35 = InterfaceMethod	#26.#34;	//  scala/collection/mutable/BufferLike.clear:()V
const #36 = Asciz	remove;
const #37 = Asciz	(Lscala/collection/mutable/BufferProxy;I)Ljava/lang/Object;;
const #38 = Asciz	(I)Ljava/lang/Object;;
const #39 = NameAndType	#36:#38;//  remove:(I)Ljava/lang/Object;
const #40 = InterfaceMethod	#26.#39;	//  scala/collection/mutable/BufferLike.remove:(I)Ljava/lang/Object;
const #41 = Asciz	n;
const #42 = Asciz	I;
const #43 = Asciz	update;
const #44 = Asciz	(Lscala/collection/mutable/BufferProxy;ILjava/lang/Object;)V;
const #45 = Asciz	(ILjava/lang/Object;)V;
const #46 = NameAndType	#43:#45;//  update:(ILjava/lang/Object;)V
const #47 = InterfaceMethod	#26.#46;	//  scala/collection/mutable/BufferLike.update:(ILjava/lang/Object;)V
const #48 = Asciz	newelem;
const #49 = Asciz	Ljava/lang/Object;;
const #50 = Asciz	insertAll;
const #51 = Asciz	(Lscala/collection/mutable/BufferProxy;ILscala/collection/Traversable;)V;
const #52 = Asciz	(ILscala/collection/Traversable;)V;
const #53 = NameAndType	#50:#52;//  insertAll:(ILscala/collection/Traversable;)V
const #54 = InterfaceMethod	#26.#53;	//  scala/collection/mutable/BufferLike.insertAll:(ILscala/collection/Traversable;)V
const #55 = Asciz	iter;
const #56 = Asciz	Lscala/collection/Traversable;;
const #57 = Asciz	(Lscala/collection/mutable/BufferProxy;ILscala/collection/Iterable;)V;
const #58 = Asciz	Lscala/collection/Iterable;;
const #59 = Asciz	insert;
const #60 = Asciz	(Lscala/collection/mutable/BufferProxy;ILscala/collection/Seq;)V;
const #61 = Asciz	elems;
const #62 = Asciz	Lscala/collection/Seq;;
const #63 = Asciz	prependAll;
const #64 = Asciz	(Lscala/collection/mutable/BufferProxy;Lscala/collection/Iterable;)V;
const #65 = Asciz	(Lscala/collection/Traversable;)V;
const #66 = NameAndType	#63:#65;//  prependAll:(Lscala/collection/Traversable;)V
const #67 = InterfaceMethod	#26.#66;	//  scala/collection/mutable/BufferLike.prependAll:(Lscala/collection/Traversable;)V
const #68 = Asciz	prepend;
const #69 = Asciz	(Lscala/collection/mutable/BufferProxy;Lscala/collection/Seq;)V;
const #70 = Asciz	$plus$plus$eq$colon;
const #71 = Asciz	(Lscala/collection/mutable/BufferProxy;Lscala/collection/Iterator;)Lscala/collection/mutable/BufferProxy;;
const #72 = Asciz	(Lscala/collection/Iterator;)Lscala/collection/mutable/BufferLike;;
const #73 = NameAndType	#70:#72;//  $plus$plus$eq$colon:(Lscala/collection/Iterator;)Lscala/collection/mutable/BufferLike;
const #74 = InterfaceMethod	#26.#73;	//  scala/collection/mutable/BufferLike.$plus$plus$eq$colon:(Lscala/collection/Iterator;)Lscala/collection/mutable/BufferLike;
const #75 = Asciz	Lscala/collection/Iterator;;
const #76 = Asciz	(Lscala/collection/mutable/BufferProxy;Lscala/collection/Traversable;)Lscala/collection/mutable/BufferProxy;;
const #77 = Asciz	(Lscala/collection/Traversable;)Lscala/collection/mutable/BufferLike;;
const #78 = NameAndType	#70:#77;//  $plus$plus$eq$colon:(Lscala/collection/Traversable;)Lscala/collection/mutable/BufferLike;
const #79 = InterfaceMethod	#26.#78;	//  scala/collection/mutable/BufferLike.$plus$plus$eq$colon:(Lscala/collection/Traversable;)Lscala/collection/mutable/BufferLike;
const #80 = Asciz	$plus$eq$colon;
const #81 = Asciz	(Lscala/collection/mutable/BufferProxy;Ljava/lang/Object;)Lscala/collection/mutable/BufferProxy;;
const #82 = Asciz	(Ljava/lang/Object;)Lscala/collection/mutable/BufferLike;;
const #83 = NameAndType	#80:#82;//  $plus$eq$colon:(Ljava/lang/Object;)Lscala/collection/mutable/BufferLike;
const #84 = InterfaceMethod	#26.#83;	//  scala/collection/mutable/BufferLike.$plus$eq$colon:(Ljava/lang/Object;)Lscala/collection/mutable/BufferLike;
const #85 = Asciz	elem;
const #86 = Asciz	appendAll;
const #87 = NameAndType	#86:#65;//  appendAll:(Lscala/collection/Traversable;)V
const #88 = InterfaceMethod	#26.#87;	//  scala/collection/mutable/BufferLike.appendAll:(Lscala/collection/Traversable;)V
const #89 = Asciz	append;
const #90 = Asciz	scala/collection/generic/Growable;
const #91 = class	#90;	//  scala/collection/generic/Growable
const #92 = Asciz	$plus$plus$eq;
const #93 = Asciz	(Lscala/collection/Traversable;)Lscala/collection/generic/Growable;;
const #94 = NameAndType	#92:#93;//  $plus$plus$eq:(Lscala/collection/Traversable;)Lscala/collection/generic/Growable;
const #95 = InterfaceMethod	#91.#94;	//  scala/collection/generic/Growable.$plus$plus$eq:(Lscala/collection/Traversable;)Lscala/collection/generic/Growable;
const #96 = Asciz	(Lscala/collection/mutable/BufferProxy;Lscala/collection/Iterable;)Lscala/collection/mutable/BufferProxy;;
const #97 = Asciz	$plus$plus;
const #98 = Asciz	(Lscala/collection/mutable/BufferProxy;Lscala/collection/Iterable;)Lscala/collection/mutable/Buffer;;
const #99 = NameAndType	#97:#77;//  $plus$plus:(Lscala/collection/Traversable;)Lscala/collection/mutable/BufferLike;
const #100 = InterfaceMethod	#26.#99;	//  scala/collection/mutable/BufferLike.$plus$plus:(Lscala/collection/Traversable;)Lscala/collection/mutable/BufferLike;
const #101 = Asciz	scala/collection/mutable/Buffer;
const #102 = class	#101;	//  scala/collection/mutable/Buffer
const #103 = Asciz	readOnly;
const #104 = Asciz	(Lscala/collection/mutable/BufferProxy;)Lscala/collection/Seq;;
const #105 = Asciz	()Lscala/collection/Seq;;
const #106 = NameAndType	#103:#105;//  readOnly:()Lscala/collection/Seq;
const #107 = InterfaceMethod	#26.#106;	//  scala/collection/mutable/BufferLike.readOnly:()Lscala/collection/Seq;
const #108 = Asciz	$plus$eq;
const #109 = NameAndType	#108:#82;//  $plus$eq:(Ljava/lang/Object;)Lscala/collection/mutable/BufferLike;
const #110 = InterfaceMethod	#26.#109;	//  scala/collection/mutable/BufferLike.$plus$eq:(Ljava/lang/Object;)Lscala/collection/mutable/BufferLike;
const #111 = Asciz	$plus;
const #112 = Asciz	(Lscala/collection/mutable/BufferProxy;Ljava/lang/Object;)Lscala/collection/mutable/Buffer;;
const #113 = NameAndType	#111:#82;//  $plus:(Ljava/lang/Object;)Lscala/collection/mutable/BufferLike;
const #114 = InterfaceMethod	#26.#113;	//  scala/collection/mutable/BufferLike.$plus:(Ljava/lang/Object;)Lscala/collection/mutable/BufferLike;
const #115 = Asciz	apply;
const #116 = NameAndType	#115:#38;//  apply:(I)Ljava/lang/Object;
const #117 = InterfaceMethod	#26.#116;	//  scala/collection/mutable/BufferLike.apply:(I)Ljava/lang/Object;
const #118 = Asciz	iterator;
const #119 = Asciz	(Lscala/collection/mutable/BufferProxy;)Lscala/collection/Iterator;;
const #120 = Asciz	scala/collection/IterableLike;
const #121 = class	#120;	//  scala/collection/IterableLike
const #122 = Asciz	()Lscala/collection/Iterator;;
const #123 = NameAndType	#118:#122;//  iterator:()Lscala/collection/Iterator;
const #124 = InterfaceMethod	#121.#123;	//  scala/collection/IterableLike.iterator:()Lscala/collection/Iterator;
const #125 = Asciz	length;
const #126 = Asciz	(Lscala/collection/mutable/BufferProxy;)I;
const #127 = Asciz	()I;
const #128 = NameAndType	#125:#127;//  length:()I
const #129 = InterfaceMethod	#26.#128;	//  scala/collection/mutable/BufferLike.length:()I
const #130 = Asciz	Scala;
const #131 = Asciz	InnerClasses;
const #132 = Asciz	$anon$1;
const #133 = Asciz	scala/collection/mutable/BufferProxy$class;
const #134 = class	#133;	//  scala/collection/mutable/BufferProxy$class
const #135 = Asciz	java/lang/Object;
const #136 = class	#135;	//  java/lang/Object

{
public static void $init$(scala.collection.mutable.BufferProxy);
  Code:
   Stack=0, Locals=1, Args_size=1
   0:	return
  LineNumberTable: 
   line 27: 0

  LocalVariableTable: 
   Start  Length  Slot  Name   Signature
   0      1      0    $this       Lscala/collection/mutable/BufferProxy;


public static scala.collection.mutable.Buffer clone(scala.collection.mutable.BufferProxy);
  Code:
   Stack=3, Locals=1, Args_size=1
   0:	new	#13; //class scala/collection/mutable/BufferProxy$$anon$1
   3:	dup
   4:	aload_0
   5:	invokespecial	#16; //Method scala/collection/mutable/BufferProxy$$anon$1."<init>":(Lscala/collection/mutable/BufferProxy;)V
   8:	areturn
  LineNumberTable: 
   line 158: 0

  LocalVariableTable: 
   Start  Length  Slot  Name   Signature
   0      9      0    $this       Lscala/collection/mutable/BufferProxy;


public static void $less$less(scala.collection.mutable.BufferProxy, scala.collection.script.Message);
  Code:
   Stack=2, Locals=2, Args_size=2
   0:	aload_0
   1:	invokeinterface	#24,  1; //InterfaceMethod scala/collection/mutable/BufferProxy.self:()Lscala/collection/mutable/Buffer;
   6:	aload_1
   7:	invokeinterface	#29,  2; //InterfaceMethod scala/collection/mutable/BufferLike.$less$less:(Lscala/collection/script/Message;)V
   12:	return
  LineNumberTable: 
   line 152: 0

  LocalVariableTable: 
   Start  Length  Slot  Name   Signature
   0      13      0    $this       Lscala/collection/mutable/BufferProxy;
   0      13      1    cmd       Lscala/collection/script/Message;


public static void clear(scala.collection.mutable.BufferProxy);
  Code:
   Stack=1, Locals=1, Args_size=1
   0:	aload_0
   1:	invokeinterface	#24,  1; //InterfaceMethod scala/collection/mutable/BufferProxy.self:()Lscala/collection/mutable/Buffer;
   6:	invokeinterface	#35,  1; //InterfaceMethod scala/collection/mutable/BufferLike.clear:()V
   11:	return
  LineNumberTable: 
   line 146: 0

  LocalVariableTable: 
   Start  Length  Slot  Name   Signature
   0      12      0    $this       Lscala/collection/mutable/BufferProxy;


public static java.lang.Object remove(scala.collection.mutable.BufferProxy, int);
  Code:
   Stack=2, Locals=2, Args_size=2
   0:	aload_0
   1:	invokeinterface	#24,  1; //InterfaceMethod scala/collection/mutable/BufferProxy.self:()Lscala/collection/mutable/Buffer;
   6:	iload_1
   7:	invokeinterface	#40,  2; //InterfaceMethod scala/collection/mutable/BufferLike.remove:(I)Ljava/lang/Object;
   12:	areturn
  LineNumberTable: 
   line 142: 0

  LocalVariableTable: 
   Start  Length  Slot  Name   Signature
   0      13      0    $this       Lscala/collection/mutable/BufferProxy;
   0      13      1    n       I


public static void update(scala.collection.mutable.BufferProxy, int, java.lang.Object);
  Code:
   Stack=3, Locals=3, Args_size=3
   0:	aload_0
   1:	invokeinterface	#24,  1; //InterfaceMethod scala/collection/mutable/BufferProxy.self:()Lscala/collection/mutable/Buffer;
   6:	iload_1
   7:	aload_2
   8:	invokeinterface	#47,  3; //InterfaceMethod scala/collection/mutable/BufferLike.update:(ILjava/lang/Object;)V
   13:	return
  LineNumberTable: 
   line 136: 0

  LocalVariableTable: 
   Start  Length  Slot  Name   Signature
   0      14      0    $this       Lscala/collection/mutable/BufferProxy;
   0      14      1    n       I
   0      14      2    newelem       Ljava/lang/Object;


public static void insertAll(scala.collection.mutable.BufferProxy, int, scala.collection.Traversable);
  Code:
   Stack=3, Locals=3, Args_size=3
   0:	aload_0
   1:	invokeinterface	#24,  1; //InterfaceMethod scala/collection/mutable/BufferProxy.self:()Lscala/collection/mutable/Buffer;
   6:	iload_1
   7:	aload_2
   8:	invokeinterface	#54,  3; //InterfaceMethod scala/collection/mutable/BufferLike.insertAll:(ILscala/collection/Traversable;)V
   13:	return
  LineNumberTable: 
   line 128: 0

  LocalVariableTable: 
   Start  Length  Slot  Name   Signature
   0      14      0    $this       Lscala/collection/mutable/BufferProxy;
   0      14      1    n       I
   0      14      2    iter       Lscala/collection/Traversable;


public static void insertAll(scala.collection.mutable.BufferProxy, int, scala.collection.Iterable);
  Code:
   Stack=3, Locals=3, Args_size=3
   0:	aload_0
   1:	invokeinterface	#24,  1; //InterfaceMethod scala/collection/mutable/BufferProxy.self:()Lscala/collection/mutable/Buffer;
   6:	iload_1
   7:	aload_2
   8:	invokeinterface	#54,  3; //InterfaceMethod scala/collection/mutable/BufferLike.insertAll:(ILscala/collection/Traversable;)V
   13:	return
  LineNumberTable: 
   line 126: 0

  LocalVariableTable: 
   Start  Length  Slot  Name   Signature
   0      14      0    $this       Lscala/collection/mutable/BufferProxy;
   0      14      1    n       I
   0      14      2    iter       Lscala/collection/Iterable;


public static void insert(scala.collection.mutable.BufferProxy, int, scala.collection.Seq);
  Code:
   Stack=3, Locals=3, Args_size=3
   0:	aload_0
   1:	invokeinterface	#24,  1; //InterfaceMethod scala/collection/mutable/BufferProxy.self:()Lscala/collection/mutable/Buffer;
   6:	iload_1
   7:	aload_2
   8:	invokeinterface	#54,  3; //InterfaceMethod scala/collection/mutable/BufferLike.insertAll:(ILscala/collection/Traversable;)V
   13:	return
  LineNumberTable: 
   line 117: 0

  LocalVariableTable: 
   Start  Length  Slot  Name   Signature
   0      14      0    $this       Lscala/collection/mutable/BufferProxy;
   0      14      1    n       I
   0      14      2    elems       Lscala/collection/Seq;


public static void prependAll(scala.collection.mutable.BufferProxy, scala.collection.Iterable);
  Code:
   Stack=2, Locals=2, Args_size=2
   0:	aload_0
   1:	invokeinterface	#24,  1; //InterfaceMethod scala/collection/mutable/BufferProxy.self:()Lscala/collection/mutable/Buffer;
   6:	aload_1
   7:	invokeinterface	#67,  2; //InterfaceMethod scala/collection/mutable/BufferLike.prependAll:(Lscala/collection/Traversable;)V
   12:	return
  LineNumberTable: 
   line 108: 0

  LocalVariableTable: 
   Start  Length  Slot  Name   Signature
   0      13      0    $this       Lscala/collection/mutable/BufferProxy;
   0      13      1    elems       Lscala/collection/Iterable;


public static void prepend(scala.collection.mutable.BufferProxy, scala.collection.Seq);
  Code:
   Stack=2, Locals=2, Args_size=2
   0:	aload_0
   1:	invokeinterface	#24,  1; //InterfaceMethod scala/collection/mutable/BufferProxy.self:()Lscala/collection/mutable/Buffer;
   6:	aload_1
   7:	invokeinterface	#67,  2; //InterfaceMethod scala/collection/mutable/BufferLike.prependAll:(Lscala/collection/Traversable;)V
   12:	return
  LineNumberTable: 
   line 100: 0

  LocalVariableTable: 
   Start  Length  Slot  Name   Signature
   0      13      0    $this       Lscala/collection/mutable/BufferProxy;
   0      13      1    elems       Lscala/collection/Seq;


public static scala.collection.mutable.BufferProxy $plus$plus$eq$colon(scala.collection.mutable.BufferProxy, scala.collection.Iterator);
  Code:
   Stack=2, Locals=2, Args_size=2
   0:	aload_0
   1:	invokeinterface	#24,  1; //InterfaceMethod scala/collection/mutable/BufferProxy.self:()Lscala/collection/mutable/Buffer;
   6:	aload_1
   7:	invokeinterface	#74,  2; //InterfaceMethod scala/collection/mutable/BufferLike.$plus$plus$eq$colon:(Lscala/collection/Iterator;)Lscala/collection/mutable/BufferLike;
   12:	pop
   13:	aload_0
   14:	areturn
  LineNumberTable: 
   line 94: 0

  LocalVariableTable: 
   Start  Length  Slot  Name   Signature
   0      15      0    $this       Lscala/collection/mutable/BufferProxy;
   0      15      1    iter       Lscala/collection/Iterator;


public static scala.collection.mutable.BufferProxy $plus$plus$eq$colon(scala.collection.mutable.BufferProxy, scala.collection.Traversable);
  Code:
   Stack=2, Locals=2, Args_size=2
   0:	aload_0
   1:	invokeinterface	#24,  1; //InterfaceMethod scala/collection/mutable/BufferProxy.self:()Lscala/collection/mutable/Buffer;
   6:	aload_1
   7:	invokeinterface	#79,  2; //InterfaceMethod scala/collection/mutable/BufferLike.$plus$plus$eq$colon:(Lscala/collection/Traversable;)Lscala/collection/mutable/BufferLike;
   12:	pop
   13:	aload_0
   14:	areturn
  LineNumberTable: 
   line 93: 0

  LocalVariableTable: 
   Start  Length  Slot  Name   Signature
   0      15      0    $this       Lscala/collection/mutable/BufferProxy;
   0      15      1    iter       Lscala/collection/Traversable;


public static scala.collection.mutable.BufferProxy $plus$eq$colon(scala.collection.mutable.BufferProxy, java.lang.Object);
  Code:
   Stack=2, Locals=2, Args_size=2
   0:	aload_0
   1:	invokeinterface	#24,  1; //InterfaceMethod scala/collection/mutable/BufferProxy.self:()Lscala/collection/mutable/Buffer;
   6:	aload_1
   7:	invokeinterface	#84,  2; //InterfaceMethod scala/collection/mutable/BufferLike.$plus$eq$colon:(Ljava/lang/Object;)Lscala/collection/mutable/BufferLike;
   12:	pop
   13:	aload_0
   14:	areturn
  LineNumberTable: 
   line 91: 0

  LocalVariableTable: 
   Start  Length  Slot  Name   Signature
   0      15      0    $this       Lscala/collection/mutable/BufferProxy;
   0      15      1    elem       Ljava/lang/Object;


public static void appendAll(scala.collection.mutable.BufferProxy, scala.collection.Iterable);
  Code:
   Stack=2, Locals=2, Args_size=2
   0:	aload_0
   1:	invokeinterface	#24,  1; //InterfaceMethod scala/collection/mutable/BufferProxy.self:()Lscala/collection/mutable/Buffer;
   6:	aload_1
   7:	invokeinterface	#88,  2; //InterfaceMethod scala/collection/mutable/BufferLike.appendAll:(Lscala/collection/Traversable;)V
   12:	return
  LineNumberTable: 
   line 84: 0

  LocalVariableTable: 
   Start  Length  Slot  Name   Signature
   0      13      0    $this       Lscala/collection/mutable/BufferProxy;
   0      13      1    iter       Lscala/collection/Iterable;


public static void append(scala.collection.mutable.BufferProxy, scala.collection.Seq);
  Code:
   Stack=2, Locals=2, Args_size=2
   0:	aload_0
   1:	invokeinterface	#24,  1; //InterfaceMethod scala/collection/mutable/BufferProxy.self:()Lscala/collection/mutable/Buffer;
   6:	aload_1
   7:	invokeinterface	#95,  2; //InterfaceMethod scala/collection/generic/Growable.$plus$plus$eq:(Lscala/collection/Traversable;)Lscala/collection/generic/Growable;
   12:	pop
   13:	return
  LineNumberTable: 
   line 77: 0

  LocalVariableTable: 
   Start  Length  Slot  Name   Signature
   0      14      0    $this       Lscala/collection/mutable/BufferProxy;
   0      14      1    elems       Lscala/collection/Seq;


public static scala.collection.mutable.BufferProxy $plus$plus$eq(scala.collection.mutable.BufferProxy, scala.collection.Iterable);
  Code:
   Stack=2, Locals=2, Args_size=2
   0:	aload_0
   1:	invokeinterface	#24,  1; //InterfaceMethod scala/collection/mutable/BufferProxy.self:()Lscala/collection/mutable/Buffer;
   6:	aload_1
   7:	invokeinterface	#95,  2; //InterfaceMethod scala/collection/generic/Growable.$plus$plus$eq:(Lscala/collection/Traversable;)Lscala/collection/generic/Growable;
   12:	pop
   13:	aload_0
   14:	areturn
  LineNumberTable: 
   line 71: 0

  LocalVariableTable: 
   Start  Length  Slot  Name   Signature
   0      15      0    $this       Lscala/collection/mutable/BufferProxy;
   0      15      1    iter       Lscala/collection/Iterable;


public static scala.collection.mutable.Buffer $plus$plus(scala.collection.mutable.BufferProxy, scala.collection.Iterable);
  Code:
   Stack=2, Locals=2, Args_size=2
   0:	aload_0
   1:	invokeinterface	#24,  1; //InterfaceMethod scala/collection/mutable/BufferProxy.self:()Lscala/collection/mutable/Buffer;
   6:	aload_1
   7:	invokeinterface	#100,  2; //InterfaceMethod scala/collection/mutable/BufferLike.$plus$plus:(Lscala/collection/Traversable;)Lscala/collection/mutable/BufferLike;
   12:	checkcast	#102; //class scala/collection/mutable/Buffer
   15:	areturn
  LineNumberTable: 
   line 64: 0

  LocalVariableTable: 
   Start  Length  Slot  Name   Signature
   0      16      0    $this       Lscala/collection/mutable/BufferProxy;
   0      16      1    iter       Lscala/collection/Iterable;


public static scala.collection.Seq readOnly(scala.collection.mutable.BufferProxy);
  Code:
   Stack=1, Locals=1, Args_size=1
   0:	aload_0
   1:	invokeinterface	#24,  1; //InterfaceMethod scala/collection/mutable/BufferProxy.self:()Lscala/collection/mutable/Buffer;
   6:	invokeinterface	#107,  1; //InterfaceMethod scala/collection/mutable/BufferLike.readOnly:()Lscala/collection/Seq;
   11:	areturn
  LineNumberTable: 
   line 53: 0

  LocalVariableTable: 
   Start  Length  Slot  Name   Signature
   0      12      0    $this       Lscala/collection/mutable/BufferProxy;


public static scala.collection.mutable.BufferProxy $plus$eq(scala.collection.mutable.BufferProxy, java.lang.Object);
  Code:
   Stack=2, Locals=2, Args_size=2
   0:	aload_0
   1:	invokeinterface	#24,  1; //InterfaceMethod scala/collection/mutable/BufferProxy.self:()Lscala/collection/mutable/Buffer;
   6:	aload_1
   7:	invokeinterface	#110,  2; //InterfaceMethod scala/collection/mutable/BufferLike.$plus$eq:(Ljava/lang/Object;)Lscala/collection/mutable/BufferLike;
   12:	pop
   13:	aload_0
   14:	areturn
  LineNumberTable: 
   line 51: 0

  LocalVariableTable: 
   Start  Length  Slot  Name   Signature
   0      15      0    $this       Lscala/collection/mutable/BufferProxy;
   0      15      1    elem       Ljava/lang/Object;


public static scala.collection.mutable.Buffer $plus(scala.collection.mutable.BufferProxy, java.lang.Object);
  Code:
   Stack=2, Locals=2, Args_size=2
   0:	aload_0
   1:	invokeinterface	#24,  1; //InterfaceMethod scala/collection/mutable/BufferProxy.self:()Lscala/collection/mutable/Buffer;
   6:	aload_1
   7:	invokeinterface	#114,  2; //InterfaceMethod scala/collection/mutable/BufferLike.$plus:(Ljava/lang/Object;)Lscala/collection/mutable/BufferLike;
   12:	checkcast	#102; //class scala/collection/mutable/Buffer
   15:	areturn
  LineNumberTable: 
   line 45: 0

  LocalVariableTable: 
   Start  Length  Slot  Name   Signature
   0      16      0    $this       Lscala/collection/mutable/BufferProxy;
   0      16      1    elem       Ljava/lang/Object;


public static java.lang.Object apply(scala.collection.mutable.BufferProxy, int);
  Code:
   Stack=2, Locals=2, Args_size=2
   0:	aload_0
   1:	invokeinterface	#24,  1; //InterfaceMethod scala/collection/mutable/BufferProxy.self:()Lscala/collection/mutable/Buffer;
   6:	iload_1
   7:	invokeinterface	#117,  2; //InterfaceMethod scala/collection/mutable/BufferLike.apply:(I)Ljava/lang/Object;
   12:	areturn
  LineNumberTable: 
   line 35: 0

  LocalVariableTable: 
   Start  Length  Slot  Name   Signature
   0      13      0    $this       Lscala/collection/mutable/BufferProxy;
   0      13      1    n       I


public static scala.collection.Iterator iterator(scala.collection.mutable.BufferProxy);
  Code:
   Stack=1, Locals=1, Args_size=1
   0:	aload_0
   1:	invokeinterface	#24,  1; //InterfaceMethod scala/collection/mutable/BufferProxy.self:()Lscala/collection/mutable/Buffer;
   6:	invokeinterface	#124,  1; //InterfaceMethod scala/collection/IterableLike.iterator:()Lscala/collection/Iterator;
   11:	areturn
  LineNumberTable: 
   line 33: 0

  LocalVariableTable: 
   Start  Length  Slot  Name   Signature
   0      12      0    $this       Lscala/collection/mutable/BufferProxy;


public static int length(scala.collection.mutable.BufferProxy);
  Code:
   Stack=1, Locals=1, Args_size=1
   0:	aload_0
   1:	invokeinterface	#24,  1; //InterfaceMethod scala/collection/mutable/BufferProxy.self:()Lscala/collection/mutable/Buffer;
   6:	invokeinterface	#129,  1; //InterfaceMethod scala/collection/mutable/BufferLike.length:()I
   11:	ireturn
  LineNumberTable: 
   line 31: 0

  LocalVariableTable: 
   Start  Length  Slot  Name   Signature
   0      12      0    $this       Lscala/collection/mutable/BufferProxy;


}

