Compiled from "CloneableCollection.scala"
public abstract class scala.collection.mutable.CloneableCollection$class extends java.lang.Object
  SourceFile: "CloneableCollection.scala"
  Scala: length = 0x
   
  minor version: 0
  major version: 49
  Constant pool:
const #1 = Asciz	SourceFile;
const #2 = Asciz	CloneableCollection.scala;
const #3 = Asciz	$init$;
const #4 = Asciz	(Lscala/collection/mutable/CloneableCollection;)V;
const #5 = Asciz	Code;
const #6 = Asciz	LineNumberTable;
const #7 = Asciz	$this;
const #8 = Asciz	Lscala/collection/mutable/CloneableCollection;;
const #9 = Asciz	LocalVariableTable;
const #10 = Asciz	clone;
const #11 = Asciz	(Lscala/collection/mutable/CloneableCollection;)Ljava/lang/Object;;
const #12 = Asciz	scala/collection/mutable/CloneableCollection;
const #13 = class	#12;	//  scala/collection/mutable/CloneableCollection
const #14 = Asciz	scala$collection$mutable$CloneableCollection$$super$clone;
const #15 = Asciz	()Ljava/lang/Object;;
const #16 = NameAndType	#14:#15;//  scala$collection$mutable$CloneableCollection$$super$clone:()Ljava/lang/Object;
const #17 = InterfaceMethod	#13.#16;	//  scala/collection/mutable/CloneableCollection.scala$collection$mutable$CloneableCollection$$super$clone:()Ljava/lang/Object;
const #18 = Asciz	Scala;
const #19 = Asciz	scala/collection/mutable/CloneableCollection$class;
const #20 = class	#19;	//  scala/collection/mutable/CloneableCollection$class
const #21 = Asciz	java/lang/Object;
const #22 = class	#21;	//  java/lang/Object

{
public static void $init$(scala.collection.mutable.CloneableCollection);
  Code:
   Stack=0, Locals=1, Args_size=1
   0:	return
  LineNumberTable: 
   line 21: 0

  LocalVariableTable: 
   Start  Length  Slot  Name   Signature
   0      1      0    $this       Lscala/collection/mutable/CloneableCollection;


public static java.lang.Object clone(scala.collection.mutable.CloneableCollection);
  Code:
   Stack=1, Locals=1, Args_size=1
   0:	aload_0
   1:	invokeinterface	#17,  1; //InterfaceMethod scala/collection/mutable/CloneableCollection.scala$collection$mutable$CloneableCollection$$super$clone:()Ljava/lang/Object;
   6:	areturn
  LineNumberTable: 
   line 22: 0

  LocalVariableTable: 
   Start  Length  Slot  Name   Signature
   0      7      0    $this       Lscala/collection/mutable/CloneableCollection;


}

