Compiled from "DefaultMapModel.scala"
public final class scala.collection.mutable.DefaultMapModel$$anonfun$iterator$1 extends java.lang.Object implements scala.Function1,scala.ScalaObject,java.io.Serializable
  SourceFile: "DefaultMapModel.scala"
  Scala: length = 0x
   
  InnerClass: 
   public final $anonfun$iterator$1=class scala/collection/mutable/DefaultMapModel$$anonfun$iterator$1 of class scala/collection/mutable/DefaultMapModel
  minor version: 0
  major version: 49
  Constant pool:
Asciz	SourceFile;
Asciz	DefaultMapModel.scala;
Asciz	<clinit>;
Asciz	()V;
Asciz	Code;
Asciz	serialVersionUID;
Asciz	J;
Asciz	scala/collection/mutable/DefaultMapModel$$anonfun$iterator$1;
class	scala/collection/mutable/DefaultMapModel$$anonfun$iterator$1
NameAndType	serialVersionUID:J
Field	scala/collection/mutable/DefaultMapModel$$anonfun$iterator$1.serialVersionUID:J
Asciz	<init>;
Asciz	(Lscala/collection/mutable/DefaultMapModel;)V;
Asciz	LineNumberTable;
Asciz	java/lang/Object;
class	java/lang/Object
NameAndType	"<init>":()V
Method	java/lang/Object."<init>":()V
Asciz	scala/Function1$class;
class	scala/Function1$class
Asciz	$init$;
Asciz	(Lscala/Function1;)V;
NameAndType	$init$:(Lscala/Function1;)V
Method	scala/Function1$class.$init$:(Lscala/Function1;)V
Asciz	this;
Asciz	Lscala/collection/mutable/DefaultMapModel$$anonfun$iterator$1;;
Asciz	$outer;
Asciz	Lscala/collection/mutable/DefaultMapModel;;
Asciz	LocalVariableTable;
Asciz	(Lscala/collection/mutable/DefaultMapModel<TA;TB;>;)V;
Asciz	Signature;
Asciz	apply;
Asciz	(Ljava/lang/Object;)Ljava/lang/Object;;
Asciz	scala/collection/mutable/DefaultEntry;
class	scala/collection/mutable/DefaultEntry
Asciz	(Lscala/collection/mutable/DefaultEntry;)Lscala/Tuple2;;
NameAndType	apply:(Lscala/collection/mutable/DefaultEntry;)Lscala/Tuple2;
Method	scala/collection/mutable/DefaultMapModel$$anonfun$iterator$1.apply:(Lscala/collection/mutable/DefaultEntry;)Lscala/Tuple2;
Asciz	v1;
Asciz	Ljava/lang/Object;;
Asciz	scala/Tuple2;
class	scala/Tuple2
Asciz	key;
Asciz	()Ljava/lang/Object;;
NameAndType	key:()Ljava/lang/Object;
Method	scala/collection/mutable/DefaultEntry.key:()Ljava/lang/Object;
Asciz	value;
NameAndType	value:()Ljava/lang/Object;
Method	scala/collection/mutable/DefaultEntry.value:()Ljava/lang/Object;
Asciz	(Ljava/lang/Object;Ljava/lang/Object;)V;
NameAndType	"<init>":(Ljava/lang/Object;Ljava/lang/Object;)V
Method	scala/Tuple2."<init>":(Ljava/lang/Object;Ljava/lang/Object;)V
Asciz	e;
Asciz	Lscala/collection/mutable/DefaultEntry;;
Asciz	(Lscala/collection/mutable/DefaultEntry<TA;TB;>;)Lscala/Tuple2<TA;TB;>;;
Asciz	andThen;
Asciz	(Lscala/Function1;)Lscala/Function1;;
Asciz	(Lscala/Function1;Lscala/Function1;)Lscala/Function1;;
NameAndType	andThen:(Lscala/Function1;Lscala/Function1;)Lscala/Function1;
Method	scala/Function1$class.andThen:(Lscala/Function1;Lscala/Function1;)Lscala/Function1;
Asciz	g;
Asciz	Lscala/Function1;;
Asciz	compose;
NameAndType	compose:(Lscala/Function1;Lscala/Function1;)Lscala/Function1;
Method	scala/Function1$class.compose:(Lscala/Function1;Lscala/Function1;)Lscala/Function1;
Asciz	toString;
Asciz	()Ljava/lang/String;;
Asciz	(Lscala/Function1;)Ljava/lang/String;;
NameAndType	toString:(Lscala/Function1;)Ljava/lang/String;
Method	scala/Function1$class.toString:(Lscala/Function1;)Ljava/lang/String;
Asciz	Scala;
Asciz	InnerClasses;
Asciz	scala/collection/mutable/DefaultMapModel;
class	scala/collection/mutable/DefaultMapModel
Asciz	$anonfun$iterator$1;
Asciz	scala/Function1;
class	scala/Function1
Asciz	scala/ScalaObject;
class	scala/ScalaObject
Asciz	java/io/Serializable;
class	java/io/Serializable

{
public static final long serialVersionUID;
  Signature: J

public static {};
  Signature: ()V
  Code:
   Stack=2, Locals=0, Args_size=0
	lconst_0
	putstatic	Field serialVersionUID:J
	return
  Labels:

public scala.collection.mutable.DefaultMapModel$$anonfun$iterator$1(scala.collection.mutable.DefaultMapModel);
  Signature: (Lscala/collection/mutable/DefaultMapModel;)V
  Code:
   Stack=1, Locals=2, Args_size=2
	aload_0
	invokespecial	Method java/lang/Object."<init>":()V
	aload_0
	invokestatic	Method scala/Function1$class.$init$:(Lscala/Function1;)V
	return
  Labels:
  LocalVariableTable: 
   Start  Length  Slot  Name   Signature
   0      9      0    this       Lscala/collection/mutable/DefaultMapModel$$anonfun$iterator$1;
   0      9      1    $outer       Lscala/collection/mutable/DefaultMapModel;

  Signature: length = 0x2
   00 1E 

public final java.lang.Object apply(java.lang.Object);
  Signature: (Ljava/lang/Object;)Ljava/lang/Object;
  Code:
   Stack=2, Locals=2, Args_size=2
	aload_0
	aload_1
	checkcast	class scala/collection/mutable/DefaultEntry
	invokevirtual	Method apply:(Lscala/collection/mutable/DefaultEntry;)Lscala/Tuple2;
	areturn
  Labels:
  LocalVariableTable: 
   Start  Length  Slot  Name   Signature
   0      9      0    this       Lscala/collection/mutable/DefaultMapModel$$anonfun$iterator$1;
   0      9      1    v1       Ljava/lang/Object;


public final scala.Tuple2 apply(scala.collection.mutable.DefaultEntry);
  Signature: (Lscala/collection/mutable/DefaultEntry;)Lscala/Tuple2;
  Code:
   Stack=4, Locals=2, Args_size=2
	new	class scala/Tuple2
	dup
	aload_1
	invokevirtual	Method scala/collection/mutable/DefaultEntry.key:()Ljava/lang/Object;
	aload_1
	invokevirtual	Method scala/collection/mutable/DefaultEntry.value:()Ljava/lang/Object;
	invokespecial	Method scala/Tuple2."<init>":(Ljava/lang/Object;Ljava/lang/Object;)V
	areturn
  Labels:
  LocalVariableTable: 
   Start  Length  Slot  Name   Signature
   0      16      0    this       Lscala/collection/mutable/DefaultMapModel$$anonfun$iterator$1;
   0      16      1    e       Lscala/collection/mutable/DefaultEntry;

  Signature: length = 0x2
   00 37 

public scala.Function1 andThen(scala.Function1);
  Signature: (Lscala/Function1;)Lscala/Function1;
  Code:
   Stack=2, Locals=2, Args_size=2
	aload_0
	aload_1
	invokestatic	Method scala/Function1$class.andThen:(Lscala/Function1;Lscala/Function1;)Lscala/Function1;
	areturn
  Labels:
  LocalVariableTable: 
   Start  Length  Slot  Name   Signature
   0      6      0    this       Lscala/collection/mutable/DefaultMapModel$$anonfun$iterator$1;
   0      6      1    g       Lscala/Function1;


public scala.Function1 compose(scala.Function1);
  Signature: (Lscala/Function1;)Lscala/Function1;
  Code:
   Stack=2, Locals=2, Args_size=2
	aload_0
	aload_1
	invokestatic	Method scala/Function1$class.compose:(Lscala/Function1;Lscala/Function1;)Lscala/Function1;
	areturn
  Labels:
  LocalVariableTable: 
   Start  Length  Slot  Name   Signature
   0      6      0    this       Lscala/collection/mutable/DefaultMapModel$$anonfun$iterator$1;
   0      6      1    g       Lscala/Function1;


public java.lang.String toString();
  Signature: ()Ljava/lang/String;
  Code:
   Stack=1, Locals=1, Args_size=1
	aload_0
	invokestatic	Method scala/Function1$class.toString:(Lscala/Function1;)Ljava/lang/String;
	areturn
  Labels:

}

