Compiled from "DoubleLinkedList.scala"
public final class scala.collection.mutable.DoubleLinkedList$$anon$1 extends java.lang.Object implements scala.collection.mutable.Builder
  SourceFile: "DoubleLinkedList.scala"
  Signature: length = 0x2
   00 6A 
  Scala: length = 0x
   
  InnerClass: 
   public final #109= #29 of #53; //$anon$1=class scala/collection/mutable/DoubleLinkedList$$anon$1 of class scala/collection/mutable/DoubleLinkedList
  minor version: 0
  major version: 49
  Constant pool:
const #1 = Asciz	SourceFile;
const #2 = Asciz	DoubleLinkedList.scala;
const #3 = Asciz	current;
const #4 = Asciz	Lscala/collection/mutable/DoubleLinkedList;;
const #5 = Asciz	Lscala/collection/mutable/DoubleLinkedList<TA;>;;
const #6 = Asciz	Signature;
const #7 = Asciz	<init>;
const #8 = Asciz	()V;
const #9 = Asciz	Code;
const #10 = Asciz	LineNumberTable;
const #11 = Asciz	java/lang/Object;
const #12 = class	#11;	//  java/lang/Object
const #13 = NameAndType	#7:#8;//  "<init>":()V
const #14 = Method	#12.#13;	//  java/lang/Object."<init>":()V
const #15 = Asciz	scala/collection/generic/Growable$class;
const #16 = class	#15;	//  scala/collection/generic/Growable$class
const #17 = Asciz	$init$;
const #18 = Asciz	(Lscala/collection/generic/Growable;)V;
const #19 = NameAndType	#17:#18;//  $init$:(Lscala/collection/generic/Growable;)V
const #20 = Method	#16.#19;	//  scala/collection/generic/Growable$class.$init$:(Lscala/collection/generic/Growable;)V
const #21 = Asciz	scala/collection/mutable/Builder$class;
const #22 = class	#21;	//  scala/collection/mutable/Builder$class
const #23 = Asciz	(Lscala/collection/mutable/Builder;)V;
const #24 = NameAndType	#17:#23;//  $init$:(Lscala/collection/mutable/Builder;)V
const #25 = Method	#22.#24;	//  scala/collection/mutable/Builder$class.$init$:(Lscala/collection/mutable/Builder;)V
const #26 = Asciz	$plus$eq;
const #27 = Asciz	(Ljava/lang/Object;)Lscala/collection/mutable/Builder;;
const #28 = Asciz	scala/collection/mutable/DoubleLinkedList$$anon$1;
const #29 = class	#28;	//  scala/collection/mutable/DoubleLinkedList$$anon$1
const #30 = Asciz	(Ljava/lang/Object;)Lscala/collection/mutable/DoubleLinkedList$$anon$1;;
const #31 = NameAndType	#26:#30;//  $plus$eq:(Ljava/lang/Object;)Lscala/collection/mutable/DoubleLinkedList$$anon$1;
const #32 = Method	#29.#31;	//  scala/collection/mutable/DoubleLinkedList$$anon$1.$plus$eq:(Ljava/lang/Object;)Lscala/collection/mutable/DoubleLinkedList$$anon$1;
const #33 = Asciz	this;
const #34 = Asciz	Lscala/collection/mutable/DoubleLinkedList$$anon$1;;
const #35 = Asciz	elem;
const #36 = Asciz	Ljava/lang/Object;;
const #37 = Asciz	LocalVariableTable;
const #38 = Asciz	(Ljava/lang/Object;)Lscala/collection/generic/Growable;;
const #39 = Asciz	result;
const #40 = Asciz	()Ljava/lang/Object;;
const #41 = Asciz	()Lscala/collection/mutable/DoubleLinkedList;;
const #42 = NameAndType	#39:#41;//  result:()Lscala/collection/mutable/DoubleLinkedList;
const #43 = Method	#29.#42;	//  scala/collection/mutable/DoubleLinkedList$$anon$1.result:()Lscala/collection/mutable/DoubleLinkedList;
const #44 = NameAndType	#3:#41;//  current:()Lscala/collection/mutable/DoubleLinkedList;
const #45 = Method	#29.#44;	//  scala/collection/mutable/DoubleLinkedList$$anon$1.current:()Lscala/collection/mutable/DoubleLinkedList;
const #46 = Asciz	()Lscala/collection/mutable/DoubleLinkedList<TA;>;;
const #47 = Asciz	clear;
const #48 = Asciz	current_$eq;
const #49 = Asciz	(Lscala/collection/mutable/DoubleLinkedList;)V;
const #50 = NameAndType	#48:#49;//  current_$eq:(Lscala/collection/mutable/DoubleLinkedList;)V
const #51 = Method	#29.#50;	//  scala/collection/mutable/DoubleLinkedList$$anon$1.current_$eq:(Lscala/collection/mutable/DoubleLinkedList;)V
const #52 = Asciz	scala/collection/mutable/DoubleLinkedList;
const #53 = class	#52;	//  scala/collection/mutable/DoubleLinkedList
const #54 = Asciz	(Ljava/lang/Object;Lscala/collection/mutable/DoubleLinkedList;)V;
const #55 = NameAndType	#7:#54;//  "<init>":(Ljava/lang/Object;Lscala/collection/mutable/DoubleLinkedList;)V
const #56 = Method	#53.#55;	//  scala/collection/mutable/DoubleLinkedList."<init>":(Ljava/lang/Object;Lscala/collection/mutable/DoubleLinkedList;)V
const #57 = Asciz	equals;
const #58 = Asciz	(Ljava/lang/Object;)Z;
const #59 = NameAndType	#57:#58;//  equals:(Ljava/lang/Object;)Z
const #60 = Method	#12.#59;	//  java/lang/Object.equals:(Ljava/lang/Object;)Z
const #61 = Asciz	scala/collection/mutable/DoubleLinkedListLike;
const #62 = class	#61;	//  scala/collection/mutable/DoubleLinkedListLike
const #63 = Asciz	insert;
const #64 = Asciz	(Lscala/collection/mutable/Seq;)V;
const #65 = NameAndType	#63:#64;//  insert:(Lscala/collection/mutable/Seq;)V
const #66 = InterfaceMethod	#62.#65;	//  scala/collection/mutable/DoubleLinkedListLike.insert:(Lscala/collection/mutable/Seq;)V
const #67 = Asciz	tmp;
const #68 = Asciz	(TA;)Lscala/collection/mutable/DoubleLinkedList$$anon$1;;
const #69 = NameAndType	#3:#4;//  current:Lscala/collection/mutable/DoubleLinkedList;
const #70 = Field	#29.#69;	//  scala/collection/mutable/DoubleLinkedList$$anon$1.current:Lscala/collection/mutable/DoubleLinkedList;
const #71 = Asciz	(Lscala/collection/mutable/DoubleLinkedList<TA;>;)V;
const #72 = Asciz	$plus$plus$eq;
const #73 = Asciz	(Lscala/collection/Traversable;)Lscala/collection/generic/Growable;;
const #74 = Asciz	(Lscala/collection/generic/Growable;Lscala/collection/Traversable;)Lscala/collection/generic/Growable;;
const #75 = NameAndType	#72:#74;//  $plus$plus$eq:(Lscala/collection/generic/Growable;Lscala/collection/Traversable;)Lscala/collection/generic/Growable;
const #76 = Method	#16.#75;	//  scala/collection/generic/Growable$class.$plus$plus$eq:(Lscala/collection/generic/Growable;Lscala/collection/Traversable;)Lscala/collection/generic/Growable;
const #77 = Asciz	iter;
const #78 = Asciz	Lscala/collection/Traversable;;
const #79 = Asciz	(Lscala/collection/Iterator;)Lscala/collection/generic/Growable;;
const #80 = Asciz	(Lscala/collection/generic/Growable;Lscala/collection/Iterator;)Lscala/collection/generic/Growable;;
const #81 = NameAndType	#72:#80;//  $plus$plus$eq:(Lscala/collection/generic/Growable;Lscala/collection/Iterator;)Lscala/collection/generic/Growable;
const #82 = Method	#16.#81;	//  scala/collection/generic/Growable$class.$plus$plus$eq:(Lscala/collection/generic/Growable;Lscala/collection/Iterator;)Lscala/collection/generic/Growable;
const #83 = Asciz	Lscala/collection/Iterator;;
const #84 = Asciz	(Ljava/lang/Object;Ljava/lang/Object;Lscala/collection/Seq;)Lscala/collection/generic/Growable;;
const #85 = Asciz	(Lscala/collection/generic/Growable;Ljava/lang/Object;Ljava/lang/Object;Lscala/collection/Seq;)Lscala/collection/generic/Growable;;
const #86 = NameAndType	#26:#85;//  $plus$eq:(Lscala/collection/generic/Growable;Ljava/lang/Object;Ljava/lang/Object;Lscala/collection/Seq;)Lscala/collection/generic/Growable;
const #87 = Method	#16.#86;	//  scala/collection/generic/Growable$class.$plus$eq:(Lscala/collection/generic/Growable;Ljava/lang/Object;Ljava/lang/Object;Lscala/collection/Seq;)Lscala/collection/generic/Growable;
const #88 = Asciz	elem1;
const #89 = Asciz	elem2;
const #90 = Asciz	elems;
const #91 = Asciz	Lscala/collection/Seq;;
const #92 = Asciz	mapResult;
const #93 = Asciz	(Lscala/Function1;)Lscala/collection/mutable/Builder;;
const #94 = Asciz	(Lscala/collection/mutable/Builder;Lscala/Function1;)Lscala/collection/mutable/Builder;;
const #95 = NameAndType	#92:#94;//  mapResult:(Lscala/collection/mutable/Builder;Lscala/Function1;)Lscala/collection/mutable/Builder;
const #96 = Method	#22.#95;	//  scala/collection/mutable/Builder$class.mapResult:(Lscala/collection/mutable/Builder;Lscala/Function1;)Lscala/collection/mutable/Builder;
const #97 = Asciz	f;
const #98 = Asciz	Lscala/Function1;;
const #99 = Asciz	sizeHint;
const #100 = Asciz	(I)V;
const #101 = Asciz	(Lscala/collection/mutable/Builder;I)V;
const #102 = NameAndType	#99:#101;//  sizeHint:(Lscala/collection/mutable/Builder;I)V
const #103 = Method	#22.#102;	//  scala/collection/mutable/Builder$class.sizeHint:(Lscala/collection/mutable/Builder;I)V
const #104 = Asciz	size;
const #105 = Asciz	I;
const #106 = Asciz	Ljava/lang/Object;Lscala/collection/mutable/Builder<TA;Lscala/collection/mutable/DoubleLinkedList<TA;>;>;;
const #107 = Asciz	Scala;
const #108 = Asciz	InnerClasses;
const #109 = Asciz	$anon$1;
const #110 = Asciz	scala/collection/mutable/Builder;
const #111 = class	#110;	//  scala/collection/mutable/Builder

{
public scala.collection.mutable.DoubleLinkedList$$anon$1();
  Code:
   Stack=1, Locals=1, Args_size=1
   0:	aload_0
   1:	invokespecial	#14; //Method java/lang/Object."<init>":()V
   4:	aload_0
   5:	invokestatic	#20; //Method scala/collection/generic/Growable$class.$init$:(Lscala/collection/generic/Growable;)V
   8:	aload_0
   9:	invokestatic	#25; //Method scala/collection/mutable/Builder$class.$init$:(Lscala/collection/mutable/Builder;)V
   12:	return
  LineNumberTable: 
   line 45: 0


public scala.collection.mutable.Builder $plus$eq(java.lang.Object);
  Code:
   Stack=2, Locals=2, Args_size=2
   0:	aload_0
   1:	aload_1
   2:	invokevirtual	#32; //Method $plus$eq:(Ljava/lang/Object;)Lscala/collection/mutable/DoubleLinkedList$$anon$1;
   5:	areturn
  LineNumberTable: 
   line 45: 0

  LocalVariableTable: 
   Start  Length  Slot  Name   Signature
   0      6      0    this       Lscala/collection/mutable/DoubleLinkedList$$anon$1;
   0      6      1    elem       Ljava/lang/Object;


public scala.collection.generic.Growable $plus$eq(java.lang.Object);
  Code:
   Stack=2, Locals=2, Args_size=2
   0:	aload_0
   1:	aload_1
   2:	invokevirtual	#32; //Method $plus$eq:(Ljava/lang/Object;)Lscala/collection/mutable/DoubleLinkedList$$anon$1;
   5:	areturn
  LineNumberTable: 
   line 45: 0

  LocalVariableTable: 
   Start  Length  Slot  Name   Signature
   0      6      0    this       Lscala/collection/mutable/DoubleLinkedList$$anon$1;
   0      6      1    elem       Ljava/lang/Object;


public java.lang.Object result();
  Code:
   Stack=1, Locals=1, Args_size=1
   0:	aload_0
   1:	invokevirtual	#43; //Method result:()Lscala/collection/mutable/DoubleLinkedList;
   4:	areturn
  LineNumberTable: 
   line 45: 0


public scala.collection.mutable.DoubleLinkedList result();
  Code:
   Stack=1, Locals=1, Args_size=1
   0:	aload_0
   1:	invokespecial	#45; //Method current:()Lscala/collection/mutable/DoubleLinkedList;
   4:	areturn
  LineNumberTable: 
   line 56: 0

  Signature: length = 0x2
   00 2E 

public void clear();
  Code:
   Stack=2, Locals=1, Args_size=1
   0:	aload_0
   1:	aconst_null
   2:	invokespecial	#51; //Method current_$eq:(Lscala/collection/mutable/DoubleLinkedList;)V
   5:	return
  LineNumberTable: 
   line 55: 0


public scala.collection.mutable.DoubleLinkedList$$anon$1 $plus$eq(java.lang.Object);
  Code:
   Stack=4, Locals=4, Args_size=2
   0:	new	#53; //class scala/collection/mutable/DoubleLinkedList
   3:	dup
   4:	aload_1
   5:	aconst_null
   6:	invokespecial	#56; //Method scala/collection/mutable/DoubleLinkedList."<init>":(Ljava/lang/Object;Lscala/collection/mutable/DoubleLinkedList;)V
   9:	astore_2
   10:	aload_0
   11:	invokespecial	#45; //Method current:()Lscala/collection/mutable/DoubleLinkedList;
   14:	dup
   15:	astore_3
   16:	ifnull	27
   19:	aload_3
   20:	aconst_null
   21:	invokevirtual	#60; //Method java/lang/Object.equals:(Ljava/lang/Object;)Z
   24:	ifeq	35
   27:	aload_0
   28:	aload_2
   29:	invokespecial	#51; //Method current_$eq:(Lscala/collection/mutable/DoubleLinkedList;)V
   32:	goto	45
   35:	aload_0
   36:	invokespecial	#45; //Method current:()Lscala/collection/mutable/DoubleLinkedList;
   39:	aload_2
   40:	invokeinterface	#66,  2; //InterfaceMethod scala/collection/mutable/DoubleLinkedListLike.insert:(Lscala/collection/mutable/Seq;)V
   45:	aload_0
   46:	areturn
  LineNumberTable: 
   line 48: 0
   line 49: 10
   line 52: 27
   line 49: 32
   line 50: 35
   line 53: 45

  LocalVariableTable: 
   Start  Length  Slot  Name   Signature
   0      47      0    this       Lscala/collection/mutable/DoubleLinkedList$$anon$1;
   0      47      1    elem       Ljava/lang/Object;
   10      36      2    tmp       Lscala/collection/mutable/DoubleLinkedList;

  Signature: length = 0x2
   00 44 

public scala.collection.generic.Growable $plus$plus$eq(scala.collection.Traversable);
  Code:
   Stack=2, Locals=2, Args_size=2
   0:	aload_0
   1:	aload_1
   2:	invokestatic	#76; //Method scala/collection/generic/Growable$class.$plus$plus$eq:(Lscala/collection/generic/Growable;Lscala/collection/Traversable;)Lscala/collection/generic/Growable;
   5:	areturn
  LineNumberTable: 
   line 45: 0

  LocalVariableTable: 
   Start  Length  Slot  Name   Signature
   0      6      0    this       Lscala/collection/mutable/DoubleLinkedList$$anon$1;
   0      6      1    iter       Lscala/collection/Traversable;


public scala.collection.generic.Growable $plus$plus$eq(scala.collection.Iterator);
  Code:
   Stack=2, Locals=2, Args_size=2
   0:	aload_0
   1:	aload_1
   2:	invokestatic	#82; //Method scala/collection/generic/Growable$class.$plus$plus$eq:(Lscala/collection/generic/Growable;Lscala/collection/Iterator;)Lscala/collection/generic/Growable;
   5:	areturn
  LineNumberTable: 
   line 45: 0

  LocalVariableTable: 
   Start  Length  Slot  Name   Signature
   0      6      0    this       Lscala/collection/mutable/DoubleLinkedList$$anon$1;
   0      6      1    iter       Lscala/collection/Iterator;


public scala.collection.generic.Growable $plus$eq(java.lang.Object, java.lang.Object, scala.collection.Seq);
  Code:
   Stack=4, Locals=4, Args_size=4
   0:	aload_0
   1:	aload_1
   2:	aload_2
   3:	aload_3
   4:	invokestatic	#87; //Method scala/collection/generic/Growable$class.$plus$eq:(Lscala/collection/generic/Growable;Ljava/lang/Object;Ljava/lang/Object;Lscala/collection/Seq;)Lscala/collection/generic/Growable;
   7:	areturn
  LineNumberTable: 
   line 45: 0

  LocalVariableTable: 
   Start  Length  Slot  Name   Signature
   0      8      0    this       Lscala/collection/mutable/DoubleLinkedList$$anon$1;
   0      8      1    elem1       Ljava/lang/Object;
   0      8      2    elem2       Ljava/lang/Object;
   0      8      3    elems       Lscala/collection/Seq;


public scala.collection.mutable.Builder mapResult(scala.Function1);
  Code:
   Stack=2, Locals=2, Args_size=2
   0:	aload_0
   1:	aload_1
   2:	invokestatic	#96; //Method scala/collection/mutable/Builder$class.mapResult:(Lscala/collection/mutable/Builder;Lscala/Function1;)Lscala/collection/mutable/Builder;
   5:	areturn
  LineNumberTable: 
   line 45: 0

  LocalVariableTable: 
   Start  Length  Slot  Name   Signature
   0      6      0    this       Lscala/collection/mutable/DoubleLinkedList$$anon$1;
   0      6      1    f       Lscala/Function1;


public void sizeHint(int);
  Code:
   Stack=2, Locals=2, Args_size=2
   0:	aload_0
   1:	iload_1
   2:	invokestatic	#103; //Method scala/collection/mutable/Builder$class.sizeHint:(Lscala/collection/mutable/Builder;I)V
   5:	return
  LineNumberTable: 
   line 45: 0

  LocalVariableTable: 
   Start  Length  Slot  Name   Signature
   0      6      0    this       Lscala/collection/mutable/DoubleLinkedList$$anon$1;
   0      6      1    size       I


}

