Compiled from "FlatHashTable.scala"
public final class scala.collection.mutable.FlatHashTable$$anonfun$checkConsistent$1$$anonfun$apply$1 extends scala.runtime.AbstractFunction0 implements java.io.Serializable
  SourceFile: "FlatHashTable.scala"
  Scala: length = 0x
   
  InnerClass: 
   public final $anonfun$checkConsistent$1=class scala/collection/mutable/FlatHashTable$$anonfun$checkConsistent$1 of class scala/collection/mutable/FlatHashTable
   public final $anonfun$apply$1=class scala/collection/mutable/FlatHashTable$$anonfun$checkConsistent$1$$anonfun$apply$1 of class scala/collection/mutable/FlatHashTable$$anonfun$checkConsistent$1
  minor version: 0
  major version: 49
  Constant pool:
Asciz	SourceFile;
Asciz	FlatHashTable.scala;
Asciz	<clinit>;
Asciz	()V;
Asciz	Code;
Asciz	serialVersionUID;
Asciz	J;
Asciz	scala/collection/mutable/FlatHashTable$$anonfun$checkConsistent$1$$anonfun$apply$1;
class	scala/collection/mutable/FlatHashTable$$anonfun$checkConsistent$1$$anonfun$apply$1
NameAndType	serialVersionUID:J
Field	scala/collection/mutable/FlatHashTable$$anonfun$checkConsistent$1$$anonfun$apply$1.serialVersionUID:J
Asciz	i$1;
Asciz	I;
Asciz	$outer;
Asciz	Lscala/collection/mutable/FlatHashTable$$anonfun$checkConsistent$1;;
Asciz	<init>;
Asciz	(Lscala/collection/mutable/FlatHashTable$$anonfun$checkConsistent$1;I)V;
Asciz	LineNumberTable;
Asciz	java/lang/NullPointerException;
class	java/lang/NullPointerException
NameAndType	"<init>":()V
Method	java/lang/NullPointerException."<init>":()V
NameAndType	$outer:Lscala/collection/mutable/FlatHashTable$$anonfun$checkConsistent$1;
Field	scala/collection/mutable/FlatHashTable$$anonfun$checkConsistent$1$$anonfun$apply$1.$outer:Lscala/collection/mutable/FlatHashTable$$anonfun$checkConsistent$1;
NameAndType	i$1:I
Field	scala/collection/mutable/FlatHashTable$$anonfun$checkConsistent$1$$anonfun$apply$1.i$1:I
Asciz	scala/runtime/AbstractFunction0;
class	scala/runtime/AbstractFunction0
Method	scala/runtime/AbstractFunction0."<init>":()V
Asciz	this;
Asciz	Lscala/collection/mutable/FlatHashTable$$anonfun$checkConsistent$1$$anonfun$apply$1;;
Asciz	LocalVariableTable;
Asciz	(Lscala/collection/mutable/FlatHashTable<TA;>.$anonfun$checkConsistent$1;)V;
Asciz	Signature;
Asciz	apply;
Asciz	()Ljava/lang/Object;;
Asciz	()Ljava/lang/String;;
NameAndType	apply:()Ljava/lang/String;
Method	scala/collection/mutable/FlatHashTable$$anonfun$checkConsistent$1$$anonfun$apply$1.apply:()Ljava/lang/String;
Asciz	scala/collection/mutable/StringBuilder;
class	scala/collection/mutable/StringBuilder
Method	scala/collection/mutable/StringBuilder."<init>":()V
Asciz	append;
Asciz	(I)Lscala/collection/mutable/StringBuilder;;
NameAndType	append:(I)Lscala/collection/mutable/StringBuilder;
Method	scala/collection/mutable/StringBuilder.append:(I)Lscala/collection/mutable/StringBuilder;
Asciz	 ;
String	 
Asciz	(Ljava/lang/Object;)Lscala/collection/mutable/StringBuilder;;
NameAndType	append:(Ljava/lang/Object;)Lscala/collection/mutable/StringBuilder;
Method	scala/collection/mutable/StringBuilder.append:(Ljava/lang/Object;)Lscala/collection/mutable/StringBuilder;
Asciz	scala/collection/mutable/FlatHashTable$$anonfun$checkConsistent$1;
class	scala/collection/mutable/FlatHashTable$$anonfun$checkConsistent$1
Asciz	scala$collection$mutable$FlatHashTable$$anonfun$$$outer;
Asciz	()Lscala/collection/mutable/FlatHashTable;;
NameAndType	scala$collection$mutable$FlatHashTable$$anonfun$$$outer:()Lscala/collection/mutable/FlatHashTable;
Method	scala/collection/mutable/FlatHashTable$$anonfun$checkConsistent$1.scala$collection$mutable$FlatHashTable$$anonfun$$$outer:()Lscala/collection/mutable/FlatHashTable;
Asciz	scala/collection/mutable/FlatHashTable;
class	scala/collection/mutable/FlatHashTable
Asciz	table;
Asciz	()[Ljava/lang/Object;;
NameAndType	table:()[Ljava/lang/Object;
InterfaceMethod	scala/collection/mutable/FlatHashTable.table:()[Ljava/lang/Object;
Asciz	scala/Predef$;
class	scala/Predef$
Asciz	MODULE$;
Asciz	Lscala/Predef$;;
NameAndType	MODULE$:Lscala/Predef$;
Field	scala/Predef$.MODULE$:Lscala/Predef$;
Asciz	refArrayOps;
Asciz	([Ljava/lang/Object;)Lscala/collection/mutable/ArrayOps;;
NameAndType	refArrayOps:([Ljava/lang/Object;)Lscala/collection/mutable/ArrayOps;
Method	scala/Predef$.refArrayOps:([Ljava/lang/Object;)Lscala/collection/mutable/ArrayOps;
Asciz	scala/collection/TraversableLike;
class	scala/collection/TraversableLike
Asciz	mkString;
NameAndType	mkString:()Ljava/lang/String;
InterfaceMethod	scala/collection/TraversableLike.mkString:()Ljava/lang/String;
Asciz	toString;
NameAndType	toString:()Ljava/lang/String;
Method	scala/collection/mutable/StringBuilder.toString:()Ljava/lang/String;
Asciz	Scala;
Asciz	InnerClasses;
Asciz	$anonfun$checkConsistent$1;
Asciz	$anonfun$apply$1;
Asciz	java/io/Serializable;
class	java/io/Serializable

{
public static final long serialVersionUID;
  Signature: J

public final int i$1;
  Signature: I

public final scala.collection.mutable.FlatHashTable$$anonfun$checkConsistent$1 $outer;
  Signature: Lscala/collection/mutable/FlatHashTable$$anonfun$checkConsistent$1;

public static {};
  Signature: ()V
  Code:
   Stack=2, Locals=0, Args_size=0
	lconst_0
	putstatic	Field serialVersionUID:J
	return
  Labels:

public scala.collection.mutable.FlatHashTable$$anonfun$checkConsistent$1$$anonfun$apply$1(scala.collection.mutable.FlatHashTable$$anonfun$checkConsistent$1, int);
  Signature: (Lscala/collection/mutable/FlatHashTable$$anonfun$checkConsistent$1;I)V
  Code:
   Stack=2, Locals=3, Args_size=3
	aload_1
	ifnonnull	l1 // aload_0
	new	class java/lang/NullPointerException
	dup
	invokespecial	Method java/lang/NullPointerException."<init>":()V
	athrow
l1	aload_0
	aload_1
	putfield	Field $outer:Lscala/collection/mutable/FlatHashTable$$anonfun$checkConsistent$1;
	aload_0
	iload_2
	putfield	Field i$1:I
	aload_0
	invokespecial	Method scala/runtime/AbstractFunction0."<init>":()V
	return
  Labels:
   	l1 = 12 // aload_0
  LocalVariableTable: 
   Start  Length  Slot  Name   Signature
   0      27      0    this       Lscala/collection/mutable/FlatHashTable$$anonfun$checkConsistent$1$$anonfun$apply$1;
   0      27      1    $outer       Lscala/collection/mutable/FlatHashTable$$anonfun$checkConsistent$1;

  Signature: length = 0x2
   00 21 

public final java.lang.Object apply();
  Signature: ()Ljava/lang/Object;
  Code:
   Stack=1, Locals=1, Args_size=1
	aload_0
	invokevirtual	Method apply:()Ljava/lang/String;
	areturn
  Labels:

public final java.lang.String apply();
  Signature: ()Ljava/lang/String;
  Code:
   Stack=3, Locals=1, Args_size=1
	new	class scala/collection/mutable/StringBuilder
	dup
	invokespecial	Method scala/collection/mutable/StringBuilder."<init>":()V
	aload_0
	getfield	Field i$1:I
	invokevirtual	Method scala/collection/mutable/StringBuilder.append:(I)Lscala/collection/mutable/StringBuilder;
	ldc	String  
	invokevirtual	Method scala/collection/mutable/StringBuilder.append:(Ljava/lang/Object;)Lscala/collection/mutable/StringBuilder;
	aload_0
	getfield	Field $outer:Lscala/collection/mutable/FlatHashTable$$anonfun$checkConsistent$1;
	invokevirtual	Method scala/collection/mutable/FlatHashTable$$anonfun$checkConsistent$1.scala$collection$mutable$FlatHashTable$$anonfun$$$outer:()Lscala/collection/mutable/FlatHashTable;
	invokeinterface	InterfaceMethod scala/collection/mutable/FlatHashTable.table:()[Ljava/lang/Object;
	aload_0
	getfield	Field i$1:I
	aaload
	invokevirtual	Method scala/collection/mutable/StringBuilder.append:(Ljava/lang/Object;)Lscala/collection/mutable/StringBuilder;
	ldc	String  
	invokevirtual	Method scala/collection/mutable/StringBuilder.append:(Ljava/lang/Object;)Lscala/collection/mutable/StringBuilder;
	getstatic	Field scala/Predef$.MODULE$:Lscala/Predef$;
	aload_0
	getfield	Field $outer:Lscala/collection/mutable/FlatHashTable$$anonfun$checkConsistent$1;
	invokevirtual	Method scala/collection/mutable/FlatHashTable$$anonfun$checkConsistent$1.scala$collection$mutable$FlatHashTable$$anonfun$$$outer:()Lscala/collection/mutable/FlatHashTable;
	invokeinterface	InterfaceMethod scala/collection/mutable/FlatHashTable.table:()[Ljava/lang/Object;
	invokevirtual	Method scala/Predef$.refArrayOps:([Ljava/lang/Object;)Lscala/collection/mutable/ArrayOps;
	invokeinterface	InterfaceMethod scala/collection/TraversableLike.mkString:()Ljava/lang/String;
	invokevirtual	Method scala/collection/mutable/StringBuilder.append:(Ljava/lang/Object;)Lscala/collection/mutable/StringBuilder;
	invokevirtual	Method scala/collection/mutable/StringBuilder.toString:()Ljava/lang/String;
	areturn
  Labels:

}

