Compiled from "FlatHashTable.scala"
public final class scala.collection.mutable.FlatHashTable$$anonfun$checkConsistent$1$$anonfun$apply$1 extends java.lang.Object implements scala.Function0,scala.ScalaObject,java.io.Serializable
  SourceFile: "FlatHashTable.scala"
  Scala: length = 0x
   
  InnerClass: 
   public final #86= #54 of #60; //$anonfun$checkConsistent$1=class scala/collection/mutable/FlatHashTable$$anonfun$checkConsistent$1 of class scala/collection/mutable/FlatHashTable
   public final #87= #17 of #54; //$anonfun$apply$1=class scala/collection/mutable/FlatHashTable$$anonfun$checkConsistent$1$$anonfun$apply$1 of class scala/collection/mutable/FlatHashTable$$anonfun$checkConsistent$1
  minor version: 0
  major version: 49
  Constant pool:
const #1 = Asciz	SourceFile;
const #2 = Asciz	FlatHashTable.scala;
const #3 = Asciz	i$1;
const #4 = Asciz	I;
const #5 = Asciz	$outer;
const #6 = Asciz	Lscala/collection/mutable/FlatHashTable$$anonfun$checkConsistent$1;;
const #7 = Asciz	<init>;
const #8 = Asciz	(Lscala/collection/mutable/FlatHashTable$$anonfun$checkConsistent$1;I)V;
const #9 = Asciz	Code;
const #10 = Asciz	LineNumberTable;
const #11 = Asciz	java/lang/NullPointerException;
const #12 = class	#11;	//  java/lang/NullPointerException
const #13 = Asciz	()V;
const #14 = NameAndType	#7:#13;//  "<init>":()V
const #15 = Method	#12.#14;	//  java/lang/NullPointerException."<init>":()V
const #16 = Asciz	scala/collection/mutable/FlatHashTable$$anonfun$checkConsistent$1$$anonfun$apply$1;
const #17 = class	#16;	//  scala/collection/mutable/FlatHashTable$$anonfun$checkConsistent$1$$anonfun$apply$1
const #18 = NameAndType	#5:#6;//  $outer:Lscala/collection/mutable/FlatHashTable$$anonfun$checkConsistent$1;
const #19 = Field	#17.#18;	//  scala/collection/mutable/FlatHashTable$$anonfun$checkConsistent$1$$anonfun$apply$1.$outer:Lscala/collection/mutable/FlatHashTable$$anonfun$checkConsistent$1;
const #20 = NameAndType	#3:#4;//  i$1:I
const #21 = Field	#17.#20;	//  scala/collection/mutable/FlatHashTable$$anonfun$checkConsistent$1$$anonfun$apply$1.i$1:I
const #22 = Asciz	java/lang/Object;
const #23 = class	#22;	//  java/lang/Object
const #24 = Method	#23.#14;	//  java/lang/Object."<init>":()V
const #25 = Asciz	scala/Function0$class;
const #26 = class	#25;	//  scala/Function0$class
const #27 = Asciz	$init$;
const #28 = Asciz	(Lscala/Function0;)V;
const #29 = NameAndType	#27:#28;//  $init$:(Lscala/Function0;)V
const #30 = Method	#26.#29;	//  scala/Function0$class.$init$:(Lscala/Function0;)V
const #31 = Asciz	this;
const #32 = Asciz	Lscala/collection/mutable/FlatHashTable$$anonfun$checkConsistent$1$$anonfun$apply$1;;
const #33 = Asciz	LocalVariableTable;
const #34 = Asciz	(Lscala/collection/mutable/FlatHashTable<TA;>.$anonfun$checkConsistent$1;)V;
const #35 = Asciz	Signature;
const #36 = Asciz	apply;
const #37 = Asciz	()Ljava/lang/Object;;
const #38 = Asciz	()Ljava/lang/String;;
const #39 = NameAndType	#36:#38;//  apply:()Ljava/lang/String;
const #40 = Method	#17.#39;	//  scala/collection/mutable/FlatHashTable$$anonfun$checkConsistent$1$$anonfun$apply$1.apply:()Ljava/lang/String;
const #41 = Asciz	scala/collection/mutable/StringBuilder;
const #42 = class	#41;	//  scala/collection/mutable/StringBuilder
const #43 = Method	#42.#14;	//  scala/collection/mutable/StringBuilder."<init>":()V
const #44 = Asciz	append;
const #45 = Asciz	(I)Lscala/collection/mutable/StringBuilder;;
const #46 = NameAndType	#44:#45;//  append:(I)Lscala/collection/mutable/StringBuilder;
const #47 = Method	#42.#46;	//  scala/collection/mutable/StringBuilder.append:(I)Lscala/collection/mutable/StringBuilder;
const #48 = Asciz	 ;
const #49 = String	#48;	//   
const #50 = Asciz	(Ljava/lang/Object;)Lscala/collection/mutable/StringBuilder;;
const #51 = NameAndType	#44:#50;//  append:(Ljava/lang/Object;)Lscala/collection/mutable/StringBuilder;
const #52 = Method	#42.#51;	//  scala/collection/mutable/StringBuilder.append:(Ljava/lang/Object;)Lscala/collection/mutable/StringBuilder;
const #53 = Asciz	scala/collection/mutable/FlatHashTable$$anonfun$checkConsistent$1;
const #54 = class	#53;	//  scala/collection/mutable/FlatHashTable$$anonfun$checkConsistent$1
const #55 = Asciz	scala$collection$mutable$FlatHashTable$$anonfun$$$outer;
const #56 = Asciz	()Lscala/collection/mutable/FlatHashTable;;
const #57 = NameAndType	#55:#56;//  scala$collection$mutable$FlatHashTable$$anonfun$$$outer:()Lscala/collection/mutable/FlatHashTable;
const #58 = Method	#54.#57;	//  scala/collection/mutable/FlatHashTable$$anonfun$checkConsistent$1.scala$collection$mutable$FlatHashTable$$anonfun$$$outer:()Lscala/collection/mutable/FlatHashTable;
const #59 = Asciz	scala/collection/mutable/FlatHashTable;
const #60 = class	#59;	//  scala/collection/mutable/FlatHashTable
const #61 = Asciz	table;
const #62 = Asciz	()[Ljava/lang/Object;;
const #63 = NameAndType	#61:#62;//  table:()[Ljava/lang/Object;
const #64 = InterfaceMethod	#60.#63;	//  scala/collection/mutable/FlatHashTable.table:()[Ljava/lang/Object;
const #65 = Asciz	scala/runtime/ScalaRunTime$;
const #66 = class	#65;	//  scala/runtime/ScalaRunTime$
const #67 = Asciz	MODULE$;
const #68 = Asciz	Lscala/runtime/ScalaRunTime$;;
const #69 = NameAndType	#67:#68;//  MODULE$:Lscala/runtime/ScalaRunTime$;
const #70 = Field	#66.#69;	//  scala/runtime/ScalaRunTime$.MODULE$:Lscala/runtime/ScalaRunTime$;
const #71 = Asciz	boxArray;
const #72 = Asciz	(Ljava/lang/Object;)Lscala/runtime/BoxedArray;;
const #73 = NameAndType	#71:#72;//  boxArray:(Ljava/lang/Object;)Lscala/runtime/BoxedArray;
const #74 = Method	#66.#73;	//  scala/runtime/ScalaRunTime$.boxArray:(Ljava/lang/Object;)Lscala/runtime/BoxedArray;
const #75 = Asciz	scala/collection/generic/SequenceTemplate;
const #76 = class	#75;	//  scala/collection/generic/SequenceTemplate
const #77 = Asciz	toString;
const #78 = NameAndType	#77:#38;//  toString:()Ljava/lang/String;
const #79 = InterfaceMethod	#76.#78;	//  scala/collection/generic/SequenceTemplate.toString:()Ljava/lang/String;
const #80 = Method	#42.#78;	//  scala/collection/mutable/StringBuilder.toString:()Ljava/lang/String;
const #81 = Asciz	(Lscala/Function0;)Ljava/lang/String;;
const #82 = NameAndType	#77:#81;//  toString:(Lscala/Function0;)Ljava/lang/String;
const #83 = Method	#26.#82;	//  scala/Function0$class.toString:(Lscala/Function0;)Ljava/lang/String;
const #84 = Asciz	Scala;
const #85 = Asciz	InnerClasses;
const #86 = Asciz	$anonfun$checkConsistent$1;
const #87 = Asciz	$anonfun$apply$1;
const #88 = Asciz	scala/Function0;
const #89 = class	#88;	//  scala/Function0
const #90 = Asciz	scala/ScalaObject;
const #91 = class	#90;	//  scala/ScalaObject
const #92 = Asciz	java/io/Serializable;
const #93 = class	#92;	//  java/io/Serializable

{
public scala.collection.mutable.FlatHashTable$$anonfun$checkConsistent$1$$anonfun$apply$1(scala.collection.mutable.FlatHashTable$$anonfun$checkConsistent$1, int);
  Code:
   Stack=2, Locals=3, Args_size=3
   0:	aload_1
   1:	ifnonnull	12
   4:	new	#12; //class java/lang/NullPointerException
   7:	dup
   8:	invokespecial	#15; //Method java/lang/NullPointerException."<init>":()V
   11:	athrow
   12:	aload_0
   13:	aload_1
   14:	putfield	#19; //Field $outer:Lscala/collection/mutable/FlatHashTable$$anonfun$checkConsistent$1;
   17:	aload_0
   18:	iload_2
   19:	putfield	#21; //Field i$1:I
   22:	aload_0
   23:	invokespecial	#24; //Method java/lang/Object."<init>":()V
   26:	aload_0
   27:	invokestatic	#30; //Method scala/Function0$class.$init$:(Lscala/Function0;)V
   30:	return
  LineNumberTable: 
   line 144: 0

  LocalVariableTable: 
   Start  Length  Slot  Name   Signature
   0      31      0    this       Lscala/collection/mutable/FlatHashTable$$anonfun$checkConsistent$1$$anonfun$apply$1;
   0      31      1    $outer       Lscala/collection/mutable/FlatHashTable$$anonfun$checkConsistent$1;

  Signature: length = 0x2
   00 22 

public final java.lang.Object apply();
  Code:
   Stack=1, Locals=2, Args_size=1
   0:	aload_0
   1:	getfield	#19; //Field $outer:Lscala/collection/mutable/FlatHashTable$$anonfun$checkConsistent$1;
   4:	astore_1
   5:	aload_0
   6:	invokevirtual	#40; //Method apply:()Ljava/lang/String;
   9:	areturn
  LineNumberTable: 
   line 144: 0

  LocalVariableTable: 
   Start  Length  Slot  Name   Signature
   0      10      0    this       Lscala/collection/mutable/FlatHashTable$$anonfun$checkConsistent$1$$anonfun$apply$1;


public final java.lang.String apply();
  Code:
   Stack=3, Locals=2, Args_size=1
   0:	aload_0
   1:	getfield	#19; //Field $outer:Lscala/collection/mutable/FlatHashTable$$anonfun$checkConsistent$1;
   4:	astore_1
   5:	new	#42; //class scala/collection/mutable/StringBuilder
   8:	dup
   9:	invokespecial	#43; //Method scala/collection/mutable/StringBuilder."<init>":()V
   12:	aload_0
   13:	getfield	#21; //Field i$1:I
   16:	invokevirtual	#47; //Method scala/collection/mutable/StringBuilder.append:(I)Lscala/collection/mutable/StringBuilder;
   19:	ldc	#49; //String  
   21:	invokevirtual	#52; //Method scala/collection/mutable/StringBuilder.append:(Ljava/lang/Object;)Lscala/collection/mutable/StringBuilder;
   24:	aload_0
   25:	getfield	#19; //Field $outer:Lscala/collection/mutable/FlatHashTable$$anonfun$checkConsistent$1;
   28:	invokevirtual	#58; //Method scala/collection/mutable/FlatHashTable$$anonfun$checkConsistent$1.scala$collection$mutable$FlatHashTable$$anonfun$$$outer:()Lscala/collection/mutable/FlatHashTable;
   31:	invokeinterface	#64,  1; //InterfaceMethod scala/collection/mutable/FlatHashTable.table:()[Ljava/lang/Object;
   36:	aload_0
   37:	getfield	#21; //Field i$1:I
   40:	aaload
   41:	invokevirtual	#52; //Method scala/collection/mutable/StringBuilder.append:(Ljava/lang/Object;)Lscala/collection/mutable/StringBuilder;
   44:	ldc	#49; //String  
   46:	invokevirtual	#52; //Method scala/collection/mutable/StringBuilder.append:(Ljava/lang/Object;)Lscala/collection/mutable/StringBuilder;
   49:	getstatic	#70; //Field scala/runtime/ScalaRunTime$.MODULE$:Lscala/runtime/ScalaRunTime$;
   52:	aload_0
   53:	getfield	#19; //Field $outer:Lscala/collection/mutable/FlatHashTable$$anonfun$checkConsistent$1;
   56:	invokevirtual	#58; //Method scala/collection/mutable/FlatHashTable$$anonfun$checkConsistent$1.scala$collection$mutable$FlatHashTable$$anonfun$$$outer:()Lscala/collection/mutable/FlatHashTable;
   59:	invokeinterface	#64,  1; //InterfaceMethod scala/collection/mutable/FlatHashTable.table:()[Ljava/lang/Object;
   64:	invokevirtual	#74; //Method scala/runtime/ScalaRunTime$.boxArray:(Ljava/lang/Object;)Lscala/runtime/BoxedArray;
   67:	invokeinterface	#79,  1; //InterfaceMethod scala/collection/generic/SequenceTemplate.toString:()Ljava/lang/String;
   72:	invokevirtual	#52; //Method scala/collection/mutable/StringBuilder.append:(Ljava/lang/Object;)Lscala/collection/mutable/StringBuilder;
   75:	invokevirtual	#80; //Method scala/collection/mutable/StringBuilder.toString:()Ljava/lang/String;
   78:	areturn
  LineNumberTable: 
   line 144: 0

  LocalVariableTable: 
   Start  Length  Slot  Name   Signature
   0      79      0    this       Lscala/collection/mutable/FlatHashTable$$anonfun$checkConsistent$1$$anonfun$apply$1;


public java.lang.String toString();
  Code:
   Stack=1, Locals=1, Args_size=1
   0:	aload_0
   1:	invokestatic	#83; //Method scala/Function0$class.toString:(Lscala/Function0;)Ljava/lang/String;
   4:	areturn
  LineNumberTable: 
   line 144: 0


}

