Compiled from "FlatHashTable.scala"
public abstract class scala.collection.mutable.FlatHashTable$class extends java.lang.Object
  SourceFile: "FlatHashTable.scala"
  Scala: length = 0x
   
  InnerClass: 
   public abstract ByOne=class scala/collection/immutable/Range$ByOne of class scala/collection/immutable/Range
   public ofRef=class scala/collection/mutable/ArrayOps$ofRef of class scala/collection/mutable/ArrayOps
   public final $anon$1=class scala/collection/mutable/FlatHashTable$$anon$1 of class scala/collection/mutable/FlatHashTable
   public final $anonfun$serializeTo$1=class scala/collection/mutable/FlatHashTable$$anonfun$serializeTo$1 of class scala/collection/mutable/FlatHashTable
   public final $anonfun$newThreshold$1=class scala/collection/mutable/FlatHashTable$$anonfun$newThreshold$1 of class scala/collection/mutable/FlatHashTable
   public final $anonfun$checkConsistent$1=class scala/collection/mutable/FlatHashTable$$anonfun$checkConsistent$1 of class scala/collection/mutable/FlatHashTable
  minor version: 0
  major version: 49
  Constant pool:
Asciz	SourceFile;
Asciz	FlatHashTable.scala;
Asciz	$init$;
Asciz	(Lscala/collection/mutable/FlatHashTable;)V;
Asciz	Code;
Asciz	LineNumberTable;
Asciz	scala/collection/mutable/FlatHashTable;
class	scala/collection/mutable/FlatHashTable
Asciz	loadFactor;
Asciz	()I;
NameAndType	loadFactor:()I
InterfaceMethod	scala/collection/mutable/FlatHashTable.loadFactor:()I
Asciz	_loadFactor_$eq;
Asciz	(I)V;
NameAndType	_loadFactor_$eq:(I)V
InterfaceMethod	scala/collection/mutable/FlatHashTable._loadFactor_$eq:(I)V
Asciz	scala/collection/mutable/FlatHashTable$class;
class	scala/collection/mutable/FlatHashTable$class
Asciz	initialCapacity;
Asciz	(Lscala/collection/mutable/FlatHashTable;)I;
NameAndType	initialCapacity:(Lscala/collection/mutable/FlatHashTable;)I
Method	scala/collection/mutable/FlatHashTable$class.initialCapacity:(Lscala/collection/mutable/FlatHashTable;)I
Asciz	java/lang/Object;
class	java/lang/Object
Asciz	table_$eq;
Asciz	([Ljava/lang/Object;)V;
NameAndType	table_$eq:([Ljava/lang/Object;)V
InterfaceMethod	scala/collection/mutable/FlatHashTable.table_$eq:([Ljava/lang/Object;)V
Asciz	tableSize_$eq;
NameAndType	tableSize_$eq:(I)V
InterfaceMethod	scala/collection/mutable/FlatHashTable.tableSize_$eq:(I)V
Asciz	newThreshold;
Asciz	(Lscala/collection/mutable/FlatHashTable;I)I;
NameAndType	newThreshold:(Lscala/collection/mutable/FlatHashTable;I)I
Method	scala/collection/mutable/FlatHashTable$class.newThreshold:(Lscala/collection/mutable/FlatHashTable;I)I
Asciz	threshold_$eq;
NameAndType	threshold_$eq:(I)V
InterfaceMethod	scala/collection/mutable/FlatHashTable.threshold_$eq:(I)V
Asciz	$this;
Asciz	Lscala/collection/mutable/FlatHashTable;;
Asciz	LocalVariableTable;
Asciz	precedes$1;
Asciz	(Lscala/collection/mutable/FlatHashTable;II)Z;
Asciz	table;
Asciz	()[Ljava/lang/Object;;
NameAndType	table:()[Ljava/lang/Object;
InterfaceMethod	scala/collection/mutable/FlatHashTable.table:()[Ljava/lang/Object;
Asciz	i;
Asciz	I;
Asciz	j;
Asciz	d;
Asciz	clearTable;
Asciz	_loadFactor;
NameAndType	_loadFactor:()I
InterfaceMethod	scala/collection/mutable/FlatHashTable._loadFactor:()I
Asciz	loadFactorDenum;
NameAndType	loadFactorDenum:()I
InterfaceMethod	scala/collection/mutable/FlatHashTable.loadFactorDenum:()I
Asciz	scala/collection/mutable/FlatHashTable$$anonfun$newThreshold$1;
class	scala/collection/mutable/FlatHashTable$$anonfun$newThreshold$1
Asciz	<init>;
NameAndType	"<init>":(Lscala/collection/mutable/FlatHashTable;)V
Method	scala/collection/mutable/FlatHashTable$$anonfun$newThreshold$1."<init>":(Lscala/collection/mutable/FlatHashTable;)V
Asciz	java/lang/AssertionError;
class	java/lang/AssertionError
Asciz	scala/collection/mutable/StringBuilder;
class	scala/collection/mutable/StringBuilder
Asciz	()V;
NameAndType	"<init>":()V
Method	scala/collection/mutable/StringBuilder."<init>":()V
Asciz	assertion failed: ;
String	assertion failed: 
Asciz	append;
Asciz	(Ljava/lang/Object;)Lscala/collection/mutable/StringBuilder;;
NameAndType	append:(Ljava/lang/Object;)Lscala/collection/mutable/StringBuilder;
Method	scala/collection/mutable/StringBuilder.append:(Ljava/lang/Object;)Lscala/collection/mutable/StringBuilder;
Asciz	loadFactor too large; must be < 0.5;
String	loadFactor too large; must be < 0.5
Asciz	toString;
Asciz	()Ljava/lang/String;;
NameAndType	toString:()Ljava/lang/String;
Method	scala/collection/mutable/StringBuilder.toString:()Ljava/lang/String;
Asciz	(Ljava/lang/Object;)V;
NameAndType	"<init>":(Ljava/lang/Object;)V
Method	java/lang/AssertionError."<init>":(Ljava/lang/Object;)V
Asciz	size;
Asciz	assertion0;
Asciz	Z;
Asciz	lf;
Asciz	index;
Asciz	improve;
Asciz	(I)I;
NameAndType	improve:(I)I
InterfaceMethod	scala/collection/mutable/FlatHashTable.improve:(I)I
Asciz	hcode;
int	9;
int	14;
int	10;
Asciz	h;
Asciz	elemHashCode;
Asciz	(Lscala/collection/mutable/FlatHashTable;Ljava/lang/Object;)I;
Asciz	equals;
Asciz	(Ljava/lang/Object;)Z;
NameAndType	equals:(Ljava/lang/Object;)Z
Method	java/lang/Object.equals:(Ljava/lang/Object;)Z
Asciz	hashCode;
NameAndType	hashCode:()I
Method	java/lang/Object.hashCode:()I
Asciz	elem;
Asciz	Ljava/lang/Object;;
Asciz	checkConsistent;
Asciz	scala/Predef$;
class	scala/Predef$
Asciz	MODULE$;
Asciz	Lscala/Predef$;;
NameAndType	MODULE$:Lscala/Predef$;
Field	scala/Predef$.MODULE$:Lscala/Predef$;
Asciz	intWrapper;
Asciz	(I)Lscala/runtime/RichInt;;
NameAndType	intWrapper:(I)Lscala/runtime/RichInt;
Method	scala/Predef$.intWrapper:(I)Lscala/runtime/RichInt;
Asciz	scala/runtime/RichInt;
class	scala/runtime/RichInt
Asciz	until;
Asciz	(I)Lscala/collection/immutable/Range;;
NameAndType	until:(I)Lscala/collection/immutable/Range;
Method	scala/runtime/RichInt.until:(I)Lscala/collection/immutable/Range;
Asciz	scala/collection/immutable/Range$ByOne;
class	scala/collection/immutable/Range$ByOne
Asciz	scala/collection/mutable/FlatHashTable$$anonfun$checkConsistent$1;
class	scala/collection/mutable/FlatHashTable$$anonfun$checkConsistent$1
Method	scala/collection/mutable/FlatHashTable$$anonfun$checkConsistent$1."<init>":(Lscala/collection/mutable/FlatHashTable;)V
Asciz	foreach;
Asciz	(Lscala/Function1;)V;
NameAndType	foreach:(Lscala/Function1;)V
InterfaceMethod	scala/collection/immutable/Range$ByOne.foreach:(Lscala/Function1;)V
Asciz	growTable;
Asciz	addEntry;
NameAndType	addEntry:(Ljava/lang/Object;)Z
InterfaceMethod	scala/collection/mutable/FlatHashTable.addEntry:(Ljava/lang/Object;)Z
Asciz	oldtable;
Asciz	[Ljava/lang/Object;;
Asciz	entry;
Asciz	iterator;
Asciz	(Lscala/collection/mutable/FlatHashTable;)Ljava/lang/Object;;
Asciz	scala/collection/mutable/FlatHashTable$$anon$1;
class	scala/collection/mutable/FlatHashTable$$anon$1
Method	scala/collection/mutable/FlatHashTable$$anon$1."<init>":(Lscala/collection/mutable/FlatHashTable;)V
Asciz	removeEntry;
Asciz	(Lscala/collection/mutable/FlatHashTable;Ljava/lang/Object;)Lscala/Option;;
Asciz	(Ljava/lang/Object;)I;
NameAndType	elemHashCode:(Ljava/lang/Object;)I
InterfaceMethod	scala/collection/mutable/FlatHashTable.elemHashCode:(Ljava/lang/Object;)I
NameAndType	index:(I)I
InterfaceMethod	scala/collection/mutable/FlatHashTable.index:(I)I
Asciz	scala/None$;
class	scala/None$
Asciz	Lscala/None$;;
NameAndType	MODULE$:Lscala/None$;
Field	scala/None$.MODULE$:Lscala/None$;
Asciz	java/lang/Number;
class	java/lang/Number
Asciz	java/lang/Character;
class	java/lang/Character
Asciz	scala/runtime/BoxesRunTime;
class	scala/runtime/BoxesRunTime
Asciz	equals2;
Asciz	(Ljava/lang/Object;Ljava/lang/Object;)Z;
NameAndType	equals2:(Ljava/lang/Object;Ljava/lang/Object;)Z
Method	scala/runtime/BoxesRunTime.equals2:(Ljava/lang/Object;Ljava/lang/Object;)Z
Asciz	tableSize;
NameAndType	tableSize:()I
InterfaceMethod	scala/collection/mutable/FlatHashTable.tableSize:()I
Asciz	scala/Some;
class	scala/Some
Method	scala/Some."<init>":(Ljava/lang/Object;)V
NameAndType	precedes$1:(Lscala/collection/mutable/FlatHashTable;II)Z
Method	scala/collection/mutable/FlatHashTable$class.precedes$1:(Lscala/collection/mutable/FlatHashTable;II)Z
Asciz	h2;
Asciz	h0;
Asciz	h1;
Asciz	(Lscala/collection/mutable/FlatHashTable;Ljava/lang/Object;)Z;
Asciz	threshold;
NameAndType	threshold:()I
InterfaceMethod	scala/collection/mutable/FlatHashTable.threshold:()I
NameAndType	growTable:(Lscala/collection/mutable/FlatHashTable;)V
Method	scala/collection/mutable/FlatHashTable$class.growTable:(Lscala/collection/mutable/FlatHashTable;)V
Asciz	containsEntry;
Asciz	findEntry;
Asciz	serializeTo;
Asciz	(Lscala/collection/mutable/FlatHashTable;Ljava/io/ObjectOutputStream;)V;
Asciz	java/io/ObjectOutputStream;
class	java/io/ObjectOutputStream
Asciz	defaultWriteObject;
NameAndType	defaultWriteObject:()V
Method	java/io/ObjectOutputStream.defaultWriteObject:()V
Asciz	writeInt;
NameAndType	writeInt:(I)V
Method	java/io/ObjectOutputStream.writeInt:(I)V
Asciz	()Ljava/lang/Object;;
NameAndType	iterator:()Ljava/lang/Object;
InterfaceMethod	scala/collection/mutable/FlatHashTable.iterator:()Ljava/lang/Object;
Asciz	scala/collection/Iterator;
class	scala/collection/Iterator
Asciz	scala/collection/mutable/FlatHashTable$$anonfun$serializeTo$1;
class	scala/collection/mutable/FlatHashTable$$anonfun$serializeTo$1
NameAndType	"<init>":(Lscala/collection/mutable/FlatHashTable;Ljava/io/ObjectOutputStream;)V
Method	scala/collection/mutable/FlatHashTable$$anonfun$serializeTo$1."<init>":(Lscala/collection/mutable/FlatHashTable;Ljava/io/ObjectOutputStream;)V
InterfaceMethod	scala/collection/Iterator.foreach:(Lscala/Function1;)V
Asciz	out$1;
Asciz	Ljava/io/ObjectOutputStream;;
Asciz	init;
Asciz	(Lscala/collection/mutable/FlatHashTable;Ljava/io/ObjectInputStream;Lscala/Function1;)V;
Asciz	java/io/ObjectInputStream;
class	java/io/ObjectInputStream
Asciz	defaultReadObject;
NameAndType	defaultReadObject:()V
Method	java/io/ObjectInputStream.defaultReadObject:()V
Asciz	readInt;
NameAndType	readInt:()I
Method	java/io/ObjectInputStream.readInt:()I
Asciz	assert;
Asciz	(Z)V;
NameAndType	assert:(Z)V
Method	scala/Predef$.assert:(Z)V
Asciz	capacity;
NameAndType	capacity:(Lscala/collection/mutable/FlatHashTable;I)I
Method	scala/collection/mutable/FlatHashTable$class.capacity:(Lscala/collection/mutable/FlatHashTable;I)I
Asciz	scala/collection/mutable/ArrayOps$ofRef;
class	scala/collection/mutable/ArrayOps$ofRef
NameAndType	"<init>":([Ljava/lang/Object;)V
Method	scala/collection/mutable/ArrayOps$ofRef."<init>":([Ljava/lang/Object;)V
Asciz	scala/collection/SeqLike;
class	scala/collection/SeqLike
NameAndType	size:()I
InterfaceMethod	scala/collection/SeqLike.size:()I
Asciz	readObject;
NameAndType	readObject:()Ljava/lang/Object;
Method	java/io/ObjectInputStream.readObject:()Ljava/lang/Object;
Asciz	scala/Function1;
class	scala/Function1
Asciz	apply;
Asciz	(Ljava/lang/Object;)Ljava/lang/Object;;
NameAndType	apply:(Ljava/lang/Object;)Ljava/lang/Object;
InterfaceMethod	scala/Function1.apply:(Ljava/lang/Object;)Ljava/lang/Object;
Asciz	in;
Asciz	Ljava/io/ObjectInputStream;;
Asciz	f;
Asciz	Lscala/Function1;;
Asciz	initialSize;
NameAndType	initialSize:()I
InterfaceMethod	scala/collection/mutable/FlatHashTable.initialSize:()I
int	8;
int	16;
Asciz	expectedSize;
Asciz	c0;
int	1000;
int	450;
Asciz	Scala;
Asciz	InnerClasses;
Asciz	scala/collection/immutable/Range;
class	scala/collection/immutable/Range
Asciz	ByOne;
Asciz	scala/collection/mutable/ArrayOps;
class	scala/collection/mutable/ArrayOps
Asciz	ofRef;
Asciz	$anon$1;
Asciz	$anonfun$serializeTo$1;
Asciz	$anonfun$newThreshold$1;
Asciz	$anonfun$checkConsistent$1;

{
public static void $init$(scala.collection.mutable.FlatHashTable);
  Signature: (Lscala/collection/mutable/FlatHashTable;)V
  Code:
   Stack=3, Locals=1, Args_size=1
	aload_0
	aload_0
	invokeinterface	InterfaceMethod scala/collection/mutable/FlatHashTable.loadFactor:()I
	invokeinterface	InterfaceMethod scala/collection/mutable/FlatHashTable._loadFactor_$eq:(I)V
	aload_0
	aload_0
	invokestatic	Method initialCapacity:(Lscala/collection/mutable/FlatHashTable;)I
	anewarray	class java/lang/Object
	invokeinterface	InterfaceMethod scala/collection/mutable/FlatHashTable.table_$eq:([Ljava/lang/Object;)V
	aload_0
	iconst_0
	invokeinterface	InterfaceMethod scala/collection/mutable/FlatHashTable.tableSize_$eq:(I)V
	aload_0
	aload_0
	aload_0
	invokestatic	Method initialCapacity:(Lscala/collection/mutable/FlatHashTable;)I
	invokestatic	Method newThreshold:(Lscala/collection/mutable/FlatHashTable;I)I
	invokeinterface	InterfaceMethod scala/collection/mutable/FlatHashTable.threshold_$eq:(I)V
	return
  Labels:
  LocalVariableTable: 
   Start  Length  Slot  Name   Signature
   0      47      0    $this       Lscala/collection/mutable/FlatHashTable;


private static final boolean precedes$1(scala.collection.mutable.FlatHashTable, int, int);
  Signature: (Lscala/collection/mutable/FlatHashTable;II)Z
  Code:
   Stack=2, Locals=4, Args_size=3
	aload_0
	invokeinterface	InterfaceMethod scala/collection/mutable/FlatHashTable.table:()[Ljava/lang/Object;
	arraylength
	iconst_1
	ishr
	istore_3
	iload_1
	iload_2
	if_icmpgt	l1 // iload_1
	iload_2
	iload_1
	isub
	iload_3
	if_icmpge	l2 // iconst_0
	iconst_1
	goto	l3 // ireturn
l2	iconst_0
	goto	l3 // ireturn
l1	iload_1
	iload_2
	isub
	iload_3
	if_icmple	l4 // iconst_0
	iconst_1
	goto	l3 // ireturn
l4	iconst_0
l3	ireturn
  Labels:
   	l2 = 26 // iconst_0
   	l1 = 30 // iload_1
   	l4 = 41 // iconst_0
   	l3 = 42 // ireturn
  LocalVariableTable: 
   Start  Length  Slot  Name   Signature
   0      43      0    $this       Lscala/collection/mutable/FlatHashTable;
   0      43      1    i       I
   0      43      2    j       I
   10      33      3    d       I


public static void clearTable(scala.collection.mutable.FlatHashTable);
  Signature: (Lscala/collection/mutable/FlatHashTable;)V
  Code:
   Stack=3, Locals=2, Args_size=1
	aload_0
	invokeinterface	InterfaceMethod scala/collection/mutable/FlatHashTable.table:()[Ljava/lang/Object;
	arraylength
	iconst_1
	isub
	istore_1
l2	iload_1
	iconst_0
	if_icmplt	l1 // aload_0
	aload_0
	invokeinterface	InterfaceMethod scala/collection/mutable/FlatHashTable.table:()[Ljava/lang/Object;
	iload_1
	aconst_null
	aastore
	iload_1
	iconst_1
	isub
	istore_1
	goto	l2 // iload_1
l1	aload_0
	iconst_0
	invokeinterface	InterfaceMethod scala/collection/mutable/FlatHashTable.tableSize_$eq:(I)V
	return
  Labels:
   	l2 = 10 // iload_1
   	l1 = 31 // aload_0
  LocalVariableTable: 
   Start  Length  Slot  Name   Signature
   0      39      0    $this       Lscala/collection/mutable/FlatHashTable;
   10      28      1    i       I


private static int newThreshold(scala.collection.mutable.FlatHashTable, int);
  Signature: (Lscala/collection/mutable/FlatHashTable;I)I
  Code:
   Stack=4, Locals=4, Args_size=2
	aload_0
	invokeinterface	InterfaceMethod scala/collection/mutable/FlatHashTable._loadFactor:()I
	istore_3
	iload_3
	aload_0
	invokeinterface	InterfaceMethod scala/collection/mutable/FlatHashTable.loadFactorDenum:()I
	iconst_2
	idiv
	if_icmpge	l1 // iconst_0
	iconst_1
	goto	l2 // new
l1	iconst_0
l2	new	class scala/collection/mutable/FlatHashTable$$anonfun$newThreshold$1
	dup
	pop
	aload_0
	invokespecial	Method scala/collection/mutable/FlatHashTable$$anonfun$newThreshold$1."<init>":(Lscala/collection/mutable/FlatHashTable;)V
	istore_2
	iload_2
	ifeq	l3 // new
	iload_1
	i2l
	iload_3
	i2l
	lmul
	aload_0
	invokeinterface	InterfaceMethod scala/collection/mutable/FlatHashTable.loadFactorDenum:()I
	i2l
	ldiv
	l2i
	ireturn
l3	new	class java/lang/AssertionError
	dup
	new	class scala/collection/mutable/StringBuilder
	dup
	invokespecial	Method scala/collection/mutable/StringBuilder."<init>":()V
	ldc	String assertion failed: 
	invokevirtual	Method scala/collection/mutable/StringBuilder.append:(Ljava/lang/Object;)Lscala/collection/mutable/StringBuilder;
	ldc	String loadFactor too large; must be < 0.5
	invokevirtual	Method scala/collection/mutable/StringBuilder.append:(Ljava/lang/Object;)Lscala/collection/mutable/StringBuilder;
	invokevirtual	Method scala/collection/mutable/StringBuilder.toString:()Ljava/lang/String;
	invokespecial	Method java/lang/AssertionError."<init>":(Ljava/lang/Object;)V
	athrow
  Labels:
   	l1 = 23 // iconst_0
   	l2 = 24 // new
   	l3 = 53 // new
  LocalVariableTable: 
   Start  Length  Slot  Name   Signature
   0      81      0    $this       Lscala/collection/mutable/FlatHashTable;
   0      81      1    size       I
   38      43      2    assertion0       Z
   7      45      3    lf       I
   53      28      3    lf       I


public static final int index(scala.collection.mutable.FlatHashTable, int);
  Signature: (Lscala/collection/mutable/FlatHashTable;I)I
  Code:
   Stack=3, Locals=2, Args_size=2
	aload_0
	iload_1
	invokeinterface	InterfaceMethod scala/collection/mutable/FlatHashTable.improve:(I)I
	aload_0
	invokeinterface	InterfaceMethod scala/collection/mutable/FlatHashTable.table:()[Ljava/lang/Object;
	arraylength
	iconst_1
	isub
	iand
	ireturn
  Labels:
  LocalVariableTable: 
   Start  Length  Slot  Name   Signature
   0      18      0    $this       Lscala/collection/mutable/FlatHashTable;
   0      18      1    hcode       I


public static final int improve(scala.collection.mutable.FlatHashTable, int);
  Signature: (Lscala/collection/mutable/FlatHashTable;I)I
  Code:
   Stack=3, Locals=3, Args_size=2
	iload_1
	iload_1
	ldc	int 9
	ishl
	iconst_m1
	ixor
	iadd
	istore_2
	iload_2
	iload_2
	ldc	int 14
	iushr
	ixor
	istore_2
	iload_2
	iload_2
	iconst_4
	ishl
	iadd
	istore_2
	iload_2
	iload_2
	ldc	int 10
	iushr
	ixor
	ireturn
  Labels:
  LocalVariableTable: 
   Start  Length  Slot  Name   Signature
   0      29      0    $this       Lscala/collection/mutable/FlatHashTable;
   0      29      1    hcode       I
   9      19      2    h       I


public static int elemHashCode(scala.collection.mutable.FlatHashTable, java.lang.Object);
  Signature: (Lscala/collection/mutable/FlatHashTable;Ljava/lang/Object;)I
  Code:
   Stack=2, Locals=2, Args_size=2
	aload_1
	dup
	pop
	ifnull	l1 // iconst_0
	aload_1
	aconst_null
	invokevirtual	Method java/lang/Object.equals:(Ljava/lang/Object;)Z
	ifeq	l2 // aload_1
l1	iconst_0
	goto	l3 // ireturn
l2	aload_1
	invokevirtual	Method java/lang/Object.hashCode:()I
l3	ireturn
  Labels:
   	l1 = 14 // iconst_0
   	l2 = 18 // aload_1
   	l3 = 22 // ireturn
  LocalVariableTable: 
   Start  Length  Slot  Name   Signature
   0      23      0    $this       Lscala/collection/mutable/FlatHashTable;
   0      23      1    elem       Ljava/lang/Object;


private static void checkConsistent(scala.collection.mutable.FlatHashTable);
  Signature: (Lscala/collection/mutable/FlatHashTable;)V
  Code:
   Stack=4, Locals=1, Args_size=1
	getstatic	Field scala/Predef$.MODULE$:Lscala/Predef$;
	iconst_0
	invokevirtual	Method scala/Predef$.intWrapper:(I)Lscala/runtime/RichInt;
	aload_0
	invokeinterface	InterfaceMethod scala/collection/mutable/FlatHashTable.table:()[Ljava/lang/Object;
	arraylength
	invokevirtual	Method scala/runtime/RichInt.until:(I)Lscala/collection/immutable/Range;
	checkcast	class scala/collection/immutable/Range$ByOne
	new	class scala/collection/mutable/FlatHashTable$$anonfun$checkConsistent$1
	dup
	aload_0
	invokespecial	Method scala/collection/mutable/FlatHashTable$$anonfun$checkConsistent$1."<init>":(Lscala/collection/mutable/FlatHashTable;)V
	invokeinterface	InterfaceMethod scala/collection/immutable/Range$ByOne.foreach:(Lscala/Function1;)V
	return
  Labels:
  LocalVariableTable: 
   Start  Length  Slot  Name   Signature
   0      34      0    $this       Lscala/collection/mutable/FlatHashTable;


private static void growTable(scala.collection.mutable.FlatHashTable);
  Signature: (Lscala/collection/mutable/FlatHashTable;)V
  Code:
   Stack=3, Locals=4, Args_size=1
	aload_0
	invokeinterface	InterfaceMethod scala/collection/mutable/FlatHashTable.table:()[Ljava/lang/Object;
	astore_1
	aload_0
	aload_0
	invokeinterface	InterfaceMethod scala/collection/mutable/FlatHashTable.table:()[Ljava/lang/Object;
	arraylength
	iconst_2
	imul
	anewarray	class java/lang/Object
	invokeinterface	InterfaceMethod scala/collection/mutable/FlatHashTable.table_$eq:([Ljava/lang/Object;)V
	aload_0
	iconst_0
	invokeinterface	InterfaceMethod scala/collection/mutable/FlatHashTable.tableSize_$eq:(I)V
	aload_0
	aload_0
	aload_0
	invokeinterface	InterfaceMethod scala/collection/mutable/FlatHashTable.table:()[Ljava/lang/Object;
	arraylength
	invokestatic	Method newThreshold:(Lscala/collection/mutable/FlatHashTable;I)I
	invokeinterface	InterfaceMethod scala/collection/mutable/FlatHashTable.threshold_$eq:(I)V
	iconst_0
	istore_3
l4	iload_3
	aload_1
	arraylength
	if_icmpge	l1 // return
	aload_1
	iload_3
	aaload
	astore_2
	aload_2
	ifnonnull	l2 // aload_0
	goto	l3 // iload_3
l2	aload_0
	aload_2
	invokeinterface	InterfaceMethod scala/collection/mutable/FlatHashTable.addEntry:(Ljava/lang/Object;)Z
	pop
l3	iload_3
	iconst_1
	iadd
	istore_3
	goto	l4 // iload_3
l1	return
  Labels:
   	l4 = 51 // iload_3
   	l2 = 68 // aload_0
   	l3 = 76 // iload_3
   	l1 = 83 // return
  LocalVariableTable: 
   Start  Length  Slot  Name   Signature
   0      84      0    $this       Lscala/collection/mutable/FlatHashTable;
   7      77      1    oldtable       [Ljava/lang/Object;
   61      19      2    entry       Ljava/lang/Object;
   51      33      3    i       I


public static java.lang.Object iterator(scala.collection.mutable.FlatHashTable);
  Signature: (Lscala/collection/mutable/FlatHashTable;)Ljava/lang/Object;
  Code:
   Stack=3, Locals=1, Args_size=1
	new	class scala/collection/mutable/FlatHashTable$$anon$1
	dup
	aload_0
	invokespecial	Method scala/collection/mutable/FlatHashTable$$anon$1."<init>":(Lscala/collection/mutable/FlatHashTable;)V
	areturn
  Labels:
  LocalVariableTable: 
   Start  Length  Slot  Name   Signature
   0      9      0    $this       Lscala/collection/mutable/FlatHashTable;


public static scala.Option removeEntry(scala.collection.mutable.FlatHashTable, java.lang.Object);
  Signature: (Lscala/collection/mutable/FlatHashTable;Ljava/lang/Object;)Lscala/Option;
  Code:
   Stack=4, Locals=7, Args_size=2
	aload_0
	aload_0
	aload_1
	invokeinterface	InterfaceMethod scala/collection/mutable/FlatHashTable.elemHashCode:(Ljava/lang/Object;)I
	invokeinterface	InterfaceMethod scala/collection/mutable/FlatHashTable.index:(I)I
	istore	5
	aload_0
	invokeinterface	InterfaceMethod scala/collection/mutable/FlatHashTable.table:()[Ljava/lang/Object;
	iload	5
	aaload
	astore	6
l11	aload	6
	ifnonnull	l1 // aload
	getstatic	Field scala/None$.MODULE$:Lscala/None$;
	areturn
l1	aload	6
	aload_1
	if_acmpne	l2 // aload
	iconst_1
	goto	l3 // ifeq
l2	aload	6
	ifnonnull	l4 // aload
	iconst_0
	goto	l3 // ifeq
l4	aload	6
	instanceof	class java/lang/Number
	ifne	l5 // aload
	aload	6
	instanceof	class java/lang/Character
	ifeq	l6 // aload
l5	aload	6
	aload_1
	invokestatic	Method scala/runtime/BoxesRunTime.equals2:(Ljava/lang/Object;Ljava/lang/Object;)Z
	goto	l3 // ifeq
l6	aload	6
	aload_1
	invokevirtual	Method java/lang/Object.equals:(Ljava/lang/Object;)Z
l3	ifeq	l7 // iload
	iload	5
	istore_3
	iload	5
	iconst_1
	iadd
	aload_0
	invokeinterface	InterfaceMethod scala/collection/mutable/FlatHashTable.table:()[Ljava/lang/Object;
	arraylength
	irem
	istore	4
l10	aload_0
	invokeinterface	InterfaceMethod scala/collection/mutable/FlatHashTable.table:()[Ljava/lang/Object;
	iload	4
	aaload
	ifnonnull	l8 // aload_0
	aload_0
	invokeinterface	InterfaceMethod scala/collection/mutable/FlatHashTable.table:()[Ljava/lang/Object;
	iload_3
	aconst_null
	aastore
	aload_0
	aload_0
	invokeinterface	InterfaceMethod scala/collection/mutable/FlatHashTable.tableSize:()I
	iconst_1
	isub
	invokeinterface	InterfaceMethod scala/collection/mutable/FlatHashTable.tableSize_$eq:(I)V
	new	class scala/Some
	dup
	aload	6
	invokespecial	Method scala/Some."<init>":(Ljava/lang/Object;)V
	areturn
l8	aload_0
	aload_0
	aload_0
	invokeinterface	InterfaceMethod scala/collection/mutable/FlatHashTable.table:()[Ljava/lang/Object;
	iload	4
	aaload
	invokeinterface	InterfaceMethod scala/collection/mutable/FlatHashTable.elemHashCode:(Ljava/lang/Object;)I
	invokeinterface	InterfaceMethod scala/collection/mutable/FlatHashTable.index:(I)I
	istore_2
	iload_2
	iload	4
	if_icmpeq	l9 // iload
	aload_0
	iload_2
	iload_3
	invokestatic	Method precedes$1:(Lscala/collection/mutable/FlatHashTable;II)Z
	ifeq	l9 // iload
	aload_0
	invokeinterface	InterfaceMethod scala/collection/mutable/FlatHashTable.table:()[Ljava/lang/Object;
	iload_3
	aload_0
	invokeinterface	InterfaceMethod scala/collection/mutable/FlatHashTable.table:()[Ljava/lang/Object;
	iload	4
	aaload
	aastore
	iload	4
	istore_3
l9	iload	4
	iconst_1
	iadd
	aload_0
	invokeinterface	InterfaceMethod scala/collection/mutable/FlatHashTable.table:()[Ljava/lang/Object;
	arraylength
	irem
	istore	4
	goto	l10 // aload_0
l7	iload	5
	iconst_1
	iadd
	aload_0
	invokeinterface	InterfaceMethod scala/collection/mutable/FlatHashTable.table:()[Ljava/lang/Object;
	arraylength
	irem
	istore	5
	aload_0
	invokeinterface	InterfaceMethod scala/collection/mutable/FlatHashTable.table:()[Ljava/lang/Object;
	iload	5
	aaload
	astore	6
	goto	l11 // aload
  Labels:
   	l11 = 26 // aload
   	l1 = 35 // aload
   	l2 = 45 // aload
   	l4 = 54 // aload
   	l5 = 70 // aload
   	l6 = 79 // aload
   	l3 = 85 // ifeq
   	l10 = 105 // aload_0
   	l8 = 150 // aload_0
   	l9 = 207 // iload
   	l7 = 224 // iload
  LocalVariableTable: 
   Start  Length  Slot  Name   Signature
   0      252      0    $this       Lscala/collection/mutable/FlatHashTable;
   0      252      1    elem       Ljava/lang/Object;
   172      49      2    h2       I
   91      133      3    h0       I
   105      119      4    h1       I
   15      19      5    h       I
   35      217      5    h       I
   26      8      6    entry       Ljava/lang/Object;
   35      217      6    entry       Ljava/lang/Object;


public static boolean addEntry(scala.collection.mutable.FlatHashTable, java.lang.Object);
  Signature: (Lscala/collection/mutable/FlatHashTable;Ljava/lang/Object;)Z
  Code:
   Stack=3, Locals=4, Args_size=2
	aload_0
	aload_0
	aload_1
	invokeinterface	InterfaceMethod scala/collection/mutable/FlatHashTable.elemHashCode:(Ljava/lang/Object;)I
	invokeinterface	InterfaceMethod scala/collection/mutable/FlatHashTable.index:(I)I
	istore_2
	aload_0
	invokeinterface	InterfaceMethod scala/collection/mutable/FlatHashTable.table:()[Ljava/lang/Object;
	iload_2
	aaload
	astore_3
l9	aload_3
	ifnonnull	l1 // aload_3
	aload_0
	invokeinterface	InterfaceMethod scala/collection/mutable/FlatHashTable.table:()[Ljava/lang/Object;
	iload_2
	aload_1
	aastore
	aload_0
	aload_0
	invokeinterface	InterfaceMethod scala/collection/mutable/FlatHashTable.tableSize:()I
	iconst_1
	iadd
	invokeinterface	InterfaceMethod scala/collection/mutable/FlatHashTable.tableSize_$eq:(I)V
	aload_0
	invokeinterface	InterfaceMethod scala/collection/mutable/FlatHashTable.tableSize:()I
	aload_0
	invokeinterface	InterfaceMethod scala/collection/mutable/FlatHashTable.threshold:()I
	if_icmplt	l2 // iconst_1
	aload_0
	invokestatic	Method growTable:(Lscala/collection/mutable/FlatHashTable;)V
l2	iconst_1
	ireturn
l1	aload_3
	aload_1
	if_acmpne	l3 // aload_3
	iconst_1
	goto	l4 // ifeq
l3	aload_3
	ifnonnull	l5 // aload_3
	iconst_0
	goto	l4 // ifeq
l5	aload_3
	instanceof	class java/lang/Number
	ifne	l6 // aload_3
	aload_3
	instanceof	class java/lang/Character
	ifeq	l7 // aload_3
l6	aload_3
	aload_1
	invokestatic	Method scala/runtime/BoxesRunTime.equals2:(Ljava/lang/Object;Ljava/lang/Object;)Z
	goto	l4 // ifeq
l7	aload_3
	aload_1
	invokevirtual	Method java/lang/Object.equals:(Ljava/lang/Object;)Z
l4	ifeq	l8 // iload_2
	iconst_0
	ireturn
l8	iload_2
	iconst_1
	iadd
	aload_0
	invokeinterface	InterfaceMethod scala/collection/mutable/FlatHashTable.table:()[Ljava/lang/Object;
	arraylength
	irem
	istore_2
	aload_0
	invokeinterface	InterfaceMethod scala/collection/mutable/FlatHashTable.table:()[Ljava/lang/Object;
	iload_2
	aaload
	astore_3
	goto	l9 // aload_3
  Labels:
   	l9 = 23 // aload_3
   	l2 = 69 // iconst_1
   	l1 = 71 // aload_3
   	l3 = 80 // aload_3
   	l5 = 88 // aload_3
   	l6 = 102 // aload_3
   	l7 = 110 // aload_3
   	l4 = 115 // ifeq
   	l8 = 120 // iload_2
  LocalVariableTable: 
   Start  Length  Slot  Name   Signature
   0      144      0    $this       Lscala/collection/mutable/FlatHashTable;
   0      144      1    elem       Ljava/lang/Object;
   14      56      2    h       I
   71      73      2    h       I
   23      47      3    entry       Ljava/lang/Object;
   71      73      3    entry       Ljava/lang/Object;


public static boolean containsEntry(scala.collection.mutable.FlatHashTable, java.lang.Object);
  Signature: (Lscala/collection/mutable/FlatHashTable;Ljava/lang/Object;)Z
  Code:
   Stack=3, Locals=4, Args_size=2
	aload_0
	aload_0
	aload_1
	invokeinterface	InterfaceMethod scala/collection/mutable/FlatHashTable.elemHashCode:(Ljava/lang/Object;)I
	invokeinterface	InterfaceMethod scala/collection/mutable/FlatHashTable.index:(I)I
	istore_2
	aload_0
	invokeinterface	InterfaceMethod scala/collection/mutable/FlatHashTable.table:()[Ljava/lang/Object;
	iload_2
	aaload
	astore_3
l10	aload_3
	ifnull	l1 // aload_3
	aload_3
	aload_1
	if_acmpne	l2 // aload_3
	iconst_1
	goto	l3 // ifeq
l2	aload_3
	ifnonnull	l4 // aload_3
	iconst_0
	goto	l3 // ifeq
l4	aload_3
	instanceof	class java/lang/Number
	ifne	l5 // aload_3
	aload_3
	instanceof	class java/lang/Character
	ifeq	l6 // aload_3
l5	aload_3
	aload_1
	invokestatic	Method scala/runtime/BoxesRunTime.equals2:(Ljava/lang/Object;Ljava/lang/Object;)Z
	goto	l3 // ifeq
l6	aload_3
	aload_1
	invokevirtual	Method java/lang/Object.equals:(Ljava/lang/Object;)Z
l3	ifeq	l7 // iload_2
l1	aload_3
	ifnonnull	l8 // iconst_1
	iconst_0
	goto	l9 // ireturn
l8	iconst_1
l9	ireturn
l7	iload_2
	iconst_1
	iadd
	aload_0
	invokeinterface	InterfaceMethod scala/collection/mutable/FlatHashTable.table:()[Ljava/lang/Object;
	arraylength
	irem
	istore_2
	aload_0
	invokeinterface	InterfaceMethod scala/collection/mutable/FlatHashTable.table:()[Ljava/lang/Object;
	iload_2
	aaload
	astore_3
	goto	l10 // aload_3
  Labels:
   	l10 = 23 // aload_3
   	l2 = 36 // aload_3
   	l4 = 44 // aload_3
   	l5 = 58 // aload_3
   	l6 = 66 // aload_3
   	l3 = 71 // ifeq
   	l1 = 74 // aload_3
   	l8 = 82 // iconst_1
   	l9 = 83 // ireturn
   	l7 = 84 // iload_2
  LocalVariableTable: 
   Start  Length  Slot  Name   Signature
   0      108      0    $this       Lscala/collection/mutable/FlatHashTable;
   0      108      1    elem       Ljava/lang/Object;
   14      94      2    h       I
   23      85      3    entry       Ljava/lang/Object;


public static scala.Option findEntry(scala.collection.mutable.FlatHashTable, java.lang.Object);
  Signature: (Lscala/collection/mutable/FlatHashTable;Ljava/lang/Object;)Lscala/Option;
  Code:
   Stack=3, Locals=4, Args_size=2
	aload_0
	aload_0
	aload_1
	invokeinterface	InterfaceMethod scala/collection/mutable/FlatHashTable.elemHashCode:(Ljava/lang/Object;)I
	invokeinterface	InterfaceMethod scala/collection/mutable/FlatHashTable.index:(I)I
	istore_2
	aload_0
	invokeinterface	InterfaceMethod scala/collection/mutable/FlatHashTable.table:()[Ljava/lang/Object;
	iload_2
	aaload
	astore_3
l10	aload_3
	ifnull	l1 // aload_3
	aload_3
	aload_1
	if_acmpne	l2 // aload_3
	iconst_1
	goto	l3 // ifeq
l2	aload_3
	ifnonnull	l4 // aload_3
	iconst_0
	goto	l3 // ifeq
l4	aload_3
	instanceof	class java/lang/Number
	ifne	l5 // aload_3
	aload_3
	instanceof	class java/lang/Character
	ifeq	l6 // aload_3
l5	aload_3
	aload_1
	invokestatic	Method scala/runtime/BoxesRunTime.equals2:(Ljava/lang/Object;Ljava/lang/Object;)Z
	goto	l3 // ifeq
l6	aload_3
	aload_1
	invokevirtual	Method java/lang/Object.equals:(Ljava/lang/Object;)Z
l3	ifeq	l7 // iload_2
l1	aload_3
	ifnonnull	l8 // new
	getstatic	Field scala/None$.MODULE$:Lscala/None$;
	goto	l9 // areturn
l8	new	class scala/Some
	dup
	aload_3
	invokespecial	Method scala/Some."<init>":(Ljava/lang/Object;)V
l9	areturn
l7	iload_2
	iconst_1
	iadd
	aload_0
	invokeinterface	InterfaceMethod scala/collection/mutable/FlatHashTable.table:()[Ljava/lang/Object;
	arraylength
	irem
	istore_2
	aload_0
	invokeinterface	InterfaceMethod scala/collection/mutable/FlatHashTable.table:()[Ljava/lang/Object;
	iload_2
	aaload
	astore_3
	goto	l10 // aload_3
  Labels:
   	l10 = 23 // aload_3
   	l2 = 36 // aload_3
   	l4 = 44 // aload_3
   	l5 = 58 // aload_3
   	l6 = 66 // aload_3
   	l3 = 71 // ifeq
   	l1 = 74 // aload_3
   	l8 = 84 // new
   	l9 = 92 // areturn
   	l7 = 93 // iload_2
  LocalVariableTable: 
   Start  Length  Slot  Name   Signature
   0      117      0    $this       Lscala/collection/mutable/FlatHashTable;
   0      117      1    elem       Ljava/lang/Object;
   14      103      2    h       I
   23      94      3    entry       Ljava/lang/Object;


public static void serializeTo(scala.collection.mutable.FlatHashTable, java.io.ObjectOutputStream);
  Signature: (Lscala/collection/mutable/FlatHashTable;Ljava/io/ObjectOutputStream;)V
  Code:
   Stack=5, Locals=2, Args_size=2
	aload_1
	invokevirtual	Method java/io/ObjectOutputStream.defaultWriteObject:()V
	aload_1
	aload_0
	invokeinterface	InterfaceMethod scala/collection/mutable/FlatHashTable._loadFactor:()I
	invokevirtual	Method java/io/ObjectOutputStream.writeInt:(I)V
	aload_1
	aload_0
	invokeinterface	InterfaceMethod scala/collection/mutable/FlatHashTable.tableSize:()I
	invokevirtual	Method java/io/ObjectOutputStream.writeInt:(I)V
	aload_0
	invokeinterface	InterfaceMethod scala/collection/mutable/FlatHashTable.iterator:()Ljava/lang/Object;
	checkcast	class scala/collection/Iterator
	new	class scala/collection/mutable/FlatHashTable$$anonfun$serializeTo$1
	dup
	aload_0
	aload_1
	invokespecial	Method scala/collection/mutable/FlatHashTable$$anonfun$serializeTo$1."<init>":(Lscala/collection/mutable/FlatHashTable;Ljava/io/ObjectOutputStream;)V
	invokeinterface	InterfaceMethod scala/collection/Iterator.foreach:(Lscala/Function1;)V
	return
  Labels:
  LocalVariableTable: 
   Start  Length  Slot  Name   Signature
   0      48      0    $this       Lscala/collection/mutable/FlatHashTable;
   0      48      1    out$1       Ljava/io/ObjectOutputStream;


public static void init(scala.collection.mutable.FlatHashTable, java.io.ObjectInputStream, scala.Function1);
  Signature: (Lscala/collection/mutable/FlatHashTable;Ljava/io/ObjectInputStream;Lscala/Function1;)V
  Code:
   Stack=5, Locals=7, Args_size=3
	aload_1
	invokevirtual	Method java/io/ObjectInputStream.defaultReadObject:()V
	aload_0
	aload_1
	invokevirtual	Method java/io/ObjectInputStream.readInt:()I
	invokeinterface	InterfaceMethod scala/collection/mutable/FlatHashTable._loadFactor_$eq:(I)V
	getstatic	Field scala/Predef$.MODULE$:Lscala/Predef$;
	aload_0
	invokeinterface	InterfaceMethod scala/collection/mutable/FlatHashTable._loadFactor:()I
	iconst_0
	if_icmple	l1 // iconst_0
	iconst_1
	goto	l2 // invokevirtual
l1	iconst_0
l2	invokevirtual	Method scala/Predef$.assert:(Z)V
	aload_1
	invokevirtual	Method java/io/ObjectInputStream.readInt:()I
	istore	4
	getstatic	Field scala/Predef$.MODULE$:Lscala/Predef$;
	iload	4
	iconst_0
	if_icmplt	l3 // iconst_0
	iconst_1
	goto	l4 // invokevirtual
l3	iconst_0
l4	invokevirtual	Method scala/Predef$.assert:(Z)V
	aload_0
	aload_0
	iload	4
	aload_0
	invokeinterface	InterfaceMethod scala/collection/mutable/FlatHashTable.loadFactorDenum:()I
	imul
	aload_0
	invokeinterface	InterfaceMethod scala/collection/mutable/FlatHashTable._loadFactor:()I
	idiv
	invokestatic	Method capacity:(Lscala/collection/mutable/FlatHashTable;I)I
	anewarray	class java/lang/Object
	invokeinterface	InterfaceMethod scala/collection/mutable/FlatHashTable.table_$eq:([Ljava/lang/Object;)V
	aload_0
	aload_0
	aload_0
	invokeinterface	InterfaceMethod scala/collection/mutable/FlatHashTable.table:()[Ljava/lang/Object;
	astore_3
	new	class scala/collection/mutable/ArrayOps$ofRef
	dup
	aload_3
	invokespecial	Method scala/collection/mutable/ArrayOps$ofRef."<init>":([Ljava/lang/Object;)V
	invokeinterface	InterfaceMethod scala/collection/SeqLike.size:()I
	invokestatic	Method newThreshold:(Lscala/collection/mutable/FlatHashTable;I)I
	invokeinterface	InterfaceMethod scala/collection/mutable/FlatHashTable.threshold_$eq:(I)V
	iconst_0
	istore	6
l6	iload	6
	iload	4
	if_icmpge	l5 // return
	aload_1
	invokevirtual	Method java/io/ObjectInputStream.readObject:()Ljava/lang/Object;
	astore	5
	aload_2
	aload	5
	invokeinterface	InterfaceMethod scala/Function1.apply:(Ljava/lang/Object;)Ljava/lang/Object;
	pop
	aload_0
	aload	5
	invokeinterface	InterfaceMethod scala/collection/mutable/FlatHashTable.addEntry:(Ljava/lang/Object;)Z
	pop
	iload	6
	iconst_1
	iadd
	istore	6
	goto	l6 // iload
l5	return
  Labels:
   	l1 = 31 // iconst_0
   	l2 = 32 // invokevirtual
   	l3 = 54 // iconst_0
   	l4 = 55 // invokevirtual
   	l6 = 120 // iload
   	l5 = 160 // return
  LocalVariableTable: 
   Start  Length  Slot  Name   Signature
   0      161      0    $this       Lscala/collection/mutable/FlatHashTable;
   0      161      1    in       Ljava/io/ObjectInputStream;
   0      161      2    f       Lscala/Function1;
   41      120      4    size       I
   133      24      5    elem       Ljava/lang/Object;
   120      41      6    index       I


private static int initialCapacity(scala.collection.mutable.FlatHashTable);
  Signature: (Lscala/collection/mutable/FlatHashTable;)I
  Code:
   Stack=2, Locals=1, Args_size=1
	aload_0
	aload_0
	invokeinterface	InterfaceMethod scala/collection/mutable/FlatHashTable.initialSize:()I
	invokestatic	Method capacity:(Lscala/collection/mutable/FlatHashTable;I)I
	ireturn
  Labels:
  LocalVariableTable: 
   Start  Length  Slot  Name   Signature
   0      11      0    $this       Lscala/collection/mutable/FlatHashTable;


private static int capacity(scala.collection.mutable.FlatHashTable, int);
  Signature: (Lscala/collection/mutable/FlatHashTable;I)I
  Code:
   Stack=3, Locals=3, Args_size=2
	iload_1
	iconst_0
	if_icmpne	l1 // iload_1
	iconst_1
	goto	l2 // ireturn
l1	iload_1
	iconst_1
	isub
	istore_2
	iload_2
	iload_2
	iconst_1
	iushr
	ior
	istore_2
	iload_2
	iload_2
	iconst_2
	iushr
	ior
	istore_2
	iload_2
	iload_2
	iconst_4
	iushr
	ior
	istore_2
	iload_2
	iload_2
	ldc	int 8
	iushr
	ior
	istore_2
	iload_2
	iload_2
	ldc	int 16
	iushr
	ior
	istore_2
	iload_2
	iconst_1
	iadd
l2	ireturn
  Labels:
   	l1 = 9 // iload_1
   	l2 = 48 // ireturn
  LocalVariableTable: 
   Start  Length  Slot  Name   Signature
   0      49      0    $this       Lscala/collection/mutable/FlatHashTable;
   0      49      1    expectedSize       I
   13      35      2    c0       I


public static int initialSize(scala.collection.mutable.FlatHashTable);
  Signature: (Lscala/collection/mutable/FlatHashTable;)I
  Code:
   Stack=1, Locals=1, Args_size=1
	ldc	int 16
	ireturn
  Labels:
  LocalVariableTable: 
   Start  Length  Slot  Name   Signature
   0      3      0    $this       Lscala/collection/mutable/FlatHashTable;


public static final int loadFactorDenum(scala.collection.mutable.FlatHashTable);
  Signature: (Lscala/collection/mutable/FlatHashTable;)I
  Code:
   Stack=1, Locals=1, Args_size=1
	ldc_w	int 1000
	ireturn
  Labels:
  LocalVariableTable: 
   Start  Length  Slot  Name   Signature
   0      4      0    $this       Lscala/collection/mutable/FlatHashTable;


public static int loadFactor(scala.collection.mutable.FlatHashTable);
  Signature: (Lscala/collection/mutable/FlatHashTable;)I
  Code:
   Stack=1, Locals=1, Args_size=1
	ldc_w	int 450
	ireturn
  Labels:
  LocalVariableTable: 
   Start  Length  Slot  Name   Signature
   0      4      0    $this       Lscala/collection/mutable/FlatHashTable;


}

