Compiled from "FlatHashTable.scala"
public final class scala.collection.mutable.FlatHashTable$$anonfun$newThreshold$1 extends scala.runtime.AbstractFunction0 implements java.io.Serializable
  SourceFile: "FlatHashTable.scala"
  Scala: length = 0x
   
  InnerClass: 
   public final #37= #9 of #36; //$anonfun$newThreshold$1=class scala/collection/mutable/FlatHashTable$$anonfun$newThreshold$1 of class scala/collection/mutable/FlatHashTable
  minor version: 0
  major version: 49
  Constant pool:
const #1 = Asciz	SourceFile;
const #2 = Asciz	FlatHashTable.scala;
const #3 = Asciz	<clinit>;
const #4 = Asciz	()V;
const #5 = Asciz	Code;
const #6 = Asciz	serialVersionUID;
const #7 = Asciz	J;
const #8 = Asciz	scala/collection/mutable/FlatHashTable$$anonfun$newThreshold$1;
const #9 = class	#8;	//  scala/collection/mutable/FlatHashTable$$anonfun$newThreshold$1
const #10 = NameAndType	#6:#7;//  serialVersionUID:J
const #11 = Field	#9.#10;	//  scala/collection/mutable/FlatHashTable$$anonfun$newThreshold$1.serialVersionUID:J
const #12 = Asciz	<init>;
const #13 = Asciz	(Lscala/collection/mutable/FlatHashTable;)V;
const #14 = Asciz	LineNumberTable;
const #15 = Asciz	scala/runtime/AbstractFunction0;
const #16 = class	#15;	//  scala/runtime/AbstractFunction0
const #17 = NameAndType	#12:#4;//  "<init>":()V
const #18 = Method	#16.#17;	//  scala/runtime/AbstractFunction0."<init>":()V
const #19 = Asciz	this;
const #20 = Asciz	Lscala/collection/mutable/FlatHashTable$$anonfun$newThreshold$1;;
const #21 = Asciz	$outer;
const #22 = Asciz	Lscala/collection/mutable/FlatHashTable;;
const #23 = Asciz	LocalVariableTable;
const #24 = Asciz	(Lscala/collection/mutable/FlatHashTable$class;)V;
const #25 = Asciz	Signature;
const #26 = Asciz	apply;
const #27 = Asciz	()Ljava/lang/Object;;
const #28 = Asciz	()Ljava/lang/String;;
const #29 = NameAndType	#26:#28;//  apply:()Ljava/lang/String;
const #30 = Method	#9.#29;	//  scala/collection/mutable/FlatHashTable$$anonfun$newThreshold$1.apply:()Ljava/lang/String;
const #31 = Asciz	loadFactor too large; must be < 0.5;
const #32 = String	#31;	//  loadFactor too large; must be < 0.5
const #33 = Asciz	Scala;
const #34 = Asciz	InnerClasses;
const #35 = Asciz	scala/collection/mutable/FlatHashTable;
const #36 = class	#35;	//  scala/collection/mutable/FlatHashTable
const #37 = Asciz	$anonfun$newThreshold$1;
const #38 = Asciz	java/io/Serializable;
const #39 = class	#38;	//  java/io/Serializable

{
public static final long serialVersionUID;

public static {};
  Code:
   Stack=2, Locals=0, Args_size=0
   0:	lconst_0
   1:	putstatic	#11; //Field serialVersionUID:J
   4:	return

public scala.collection.mutable.FlatHashTable$$anonfun$newThreshold$1(scala.collection.mutable.FlatHashTable);
  Code:
   Stack=1, Locals=2, Args_size=2
   0:	aload_0
   1:	invokespecial	#18; //Method scala/runtime/AbstractFunction0."<init>":()V
   4:	return
  LineNumberTable: 
   line 203: 0

  LocalVariableTable: 
   Start  Length  Slot  Name   Signature
   0      5      0    this       Lscala/collection/mutable/FlatHashTable$$anonfun$newThreshold$1;
   0      5      1    $outer       Lscala/collection/mutable/FlatHashTable;

  Signature: length = 0x2
   00 18 

public final java.lang.Object apply();
  Code:
   Stack=1, Locals=1, Args_size=1
   0:	aload_0
   1:	invokevirtual	#30; //Method apply:()Ljava/lang/String;
   4:	areturn
  LineNumberTable: 
   line 203: 0


public final java.lang.String apply();
  Code:
   Stack=1, Locals=1, Args_size=1
   0:	ldc	#32; //String loadFactor too large; must be < 0.5
   2:	areturn
  LineNumberTable: 
   line 203: 0


}

