Compiled from "GenericArray.scala"
public class scala.collection.mutable.GenericArray extends java.lang.Object implements scala.collection.mutable.IndexedSeq,scala.collection.generic.GenericTraversableTemplate,scala.collection.mutable.IndexedSeqLike,scala.ScalaObject
  SourceFile: "GenericArray.scala"
  Signature: length = 0x2
   03 FFFFFF9B 
  ScalaSig: length = 0x3E1
   05 00 FFFFFF81 17 06 04 01 02 00 09 02 0C 47 65 6E 65
   72 69 63 41 72 72 61 79 0A 02 03 04 01 07 6D 75
   74 61 62 6C 65 0A 02 05 06 01 0A 63 6F 6C 6C 65
   63 74 69 6F 6E 0A 01 07 01 05 73 63 61 6C 61 03
   00 15 02 0A 19 13 06 00 0B 13 23 2A 2E 10 02 0C
   11 0D 01 0D 0A 02 0E 0F 01 04 6C 61 6E 67 0A 01
   10 01 04 6A 61 76 61 09 02 12 0D 02 06 4F 62 6A
   65 63 74 10 03 14 15 17 0D 01 02 09 02 16 02 02
   0A 49 6E 64 65 78 65 64 53 65 71 10 02 18 19 0C
   00 04 08 1A 00 FFFFFF84 FFFFFF80 FFFFFF80 FFFFFFC2 00 1B 02 01 41 11 02
   1C 20 10 02 1D 1E 0D 01 06 09 02 1F 06 02 07 4E
   6F 74 68 69 6E 67 10 02 1D 21 09 02 22 06 02 03
   41 6E 79 10 04 24 27 17 29 0D 01 25 0A 02 26 04
   01 07 67 65 6E 65 72 69 63 09 02 28 25 02 1A 47
   65 6E 65 72 69 63 54 72 61 76 65 72 73 61 62 6C
   65 54 65 6D 70 6C 61 74 65 10 02 14 00 10 04 14
   2B 17 2D 09 02 2C 02 02 0E 49 6E 64 65 78 65 64
   53 65 71 4C 69 6B 65 10 03 14 00 17 10 02 1D 2F
   09 02 30 06 02 0B 53 63 61 6C 61 4F 62 6A 65 63
   74 08 08 32 00 FFFFFF82 FFFFFFC2 FFFFFF80 FFFFFF84 20 33 01 06 6C 65 6E
   67 74 68 15 01 34 10 02 1D 35 09 02 36 06 02 03
   49 6E 74 08 08 38 00 FFFFFF82 FFFFFF80 FFFFFFA0 FFFFFF80 04 34 01 07 6C
   65 6E 67 74 68 20 08 05 3A 00 FFFFFF84 00 3B 01 06 3C
   69 6E 69 74 3E 14 02 2D 3C 08 05 32 39 FFFFFFC0 00 34
   08 05 3E 00 FFFFFF84 20 3F 01 09 63 6F 6D 70 61 6E 69
   6F 6E 15 01 40 10 03 24 41 29 09 02 42 25 02 10
   47 65 6E 65 72 69 63 43 6F 6D 70 61 6E 69 6F 6E
   08 07 44 00 FFFFFFC2 FFFFFF80 FFFFFF84 00 45 01 05 61 72 72 61 79
   15 01 46 10 03 1D 47 49 09 02 48 06 02 05 41 72
   72 61 79 10 02 1D 4A 09 02 4B 06 02 06 41 6E 79
   52 65 66 08 06 4D 00 FFFFFFA0 FFFFFF80 04 46 01 06 61 72 72
   61 79 20 08 05 4F 00 FFFFFF84 00 50 01 05 61 70 70 6C
   79 14 02 17 51 08 05 52 4E FFFFFFC0 00 34 01 03 69 64
   78 08 05 54 00 FFFFFF84 00 55 01 06 75 70 64 61 74 65
   14 03 56 59 5A 10 02 1D 57 09 02 58 06 02 04 55
   6E 69 74 08 05 52 53 FFFFFFC0 00 34 08 05 5B 53 FFFFFFC0 00
   17 01 04 65 6C 65 6D 08 05 5D 00 FFFFFF84 20 5E 01 07
   66 6F 72 65 61 63 68 15 02 5F 66 14 02 56 60 08
   05 61 5C FFFFFFC0 00 62 01 01 66 10 04 1D 63 17 65 09
   02 64 06 02 09 46 75 6E 63 74 69 6F 6E 31 10 02
   18 66 04 08 67 5C FFFFFF84 FFFFFF80 FFFFFF80 FFFFFFC2 00 1B 02 01 55 08
   05 69 00 FFFFFF84 20 6A 01 0B 63 6F 70 79 54 6F 41 72
   72 61 79 15 02 6B 70 14 04 56 6C 73 75 08 05 6D
   68 FFFFFFC0 00 6E 01 02 78 73 10 03 1D 47 6F 10 02 18
   70 04 08 71 68 FFFFFF84 FFFFFF80 FFFFFF80 FFFFFFC2 00 72 02 01 42 11 02
   17 20 08 05 74 68 FFFFFFC0 00 34 01 05 73 74 61 72 74
   08 05 76 68 FFFFFFC0 00 34 01 03 6C 65 6E 07 05 78 02
   FFFFFF88 02 79 01 0C 47 65 6E 65 72 69 63 41 72 72 61
   79 10 02 14 7A 06 08 01 02 FFFFFF84 FFFFFF80 FFFFFF80 FFFFFF88 02 7B 13
   03 7A 7C 2E 10 03 24 7D 29 09 02 7E 25 02 0A 53
   65 71 46 61 63 74 6F 72 79 08 06 3A 7A FFFFFF84 00 FFFFFF81
   00 14 01 79 08 07 FFFFFF81 02 7A FFFFFF84 01 FFFFFF81 03 01 0C 63
   61 6E 42 75 69 6C 64 46 72 6F 6D 15 04 FFFFFF81 04 FFFFFF81
   0C 10 09 24 FFFFFF81 05 FFFFFF81 07 FFFFFF81 0B FFFFFF81 0D 09 03 FFFFFF81 06
   25 02 0C 43 61 6E 42 75 69 6C 64 46 72 6F 6D 10
   04 FFFFFF81 08 FFFFFF81 09 0D 01 7A 09 03 FFFFFF81 0A 41 02 04 43
   6F 6C 6C 10 03 18 FFFFFF81 0C 04 09 1A FFFFFF81 01 FFFFFF84 FFFFFF80 FFFFFF80
   FFFFFFC2 00 1B 10 04 14 00 FFFFFF81 0B 08 07 FFFFFF81 0F 7A FFFFFF84 00
   FFFFFF81 10 01 0A 6E 65 77 42 75 69 6C 64 65 72 15 04
   FFFFFF81 11 FFFFFF81 15 10 07 14 FFFFFF81 12 FFFFFF81 14 FFFFFF81 16 09 03 FFFFFF81
   13 02 02 07 42 75 69 6C 64 65 72 10 03 18 FFFFFF81 15
   04 09 1A FFFFFF81 0E FFFFFF84 FFFFFF80 FFFFFF80 FFFFFFC2 00 1B 10 04 14 00 FFFFFF81
   14 
  InnerClass: 
   public abstract $less$colon$less=class scala/Predef$$less$colon$less of class scala/Predef
   public WithFilter=class scala/collection/TraversableLike$WithFilter of class scala/collection/TraversableLike
   public final $anonfun$newBuilder$1=class scala/collection/mutable/GenericArray$$anonfun$newBuilder$1 of class scala/collection/mutable/GenericArray
  minor version: 0
  major version: 49
  Constant pool:
Asciz	SourceFile;
Asciz	GenericArray.scala;
Asciz	canBuildFrom;
Asciz	()Lscala/collection/generic/CanBuildFrom;;
Asciz	Code;
Asciz	scala/collection/mutable/GenericArray$;
class	scala/collection/mutable/GenericArray$
Asciz	MODULE$;
Asciz	Lscala/collection/mutable/GenericArray$;;
NameAndType	MODULE$:Lscala/collection/mutable/GenericArray$;
Field	scala/collection/mutable/GenericArray$.MODULE$:Lscala/collection/mutable/GenericArray$;
NameAndType	canBuildFrom:()Lscala/collection/generic/CanBuildFrom;
Method	scala/collection/mutable/GenericArray$.canBuildFrom:()Lscala/collection/generic/CanBuildFrom;
Asciz	<A:Ljava/lang/Object;>()Lscala/collection/generic/CanBuildFrom<Lscala/collection/mutable/GenericArray<*>;TA;Lscala/collection/mutable/GenericArray<TA;>;>;;
Asciz	Signature;
Asciz	unapplySeq;
Asciz	(Lscala/collection/Seq;)Lscala/Some;;
NameAndType	unapplySeq:(Lscala/collection/Seq;)Lscala/Some;
Method	scala/collection/mutable/GenericArray$.unapplySeq:(Lscala/collection/Seq;)Lscala/Some;
Asciz	<A:Ljava/lang/Object;>(Lscala/collection/mutable/GenericArray<TA;>;)Lscala/Some<Lscala/collection/mutable/GenericArray<TA;>;>;;
Asciz	iterate;
Asciz	(Ljava/lang/Object;ILscala/Function1;)Lscala/collection/Traversable;;
NameAndType	iterate:(Ljava/lang/Object;ILscala/Function1;)Lscala/collection/Traversable;
Method	scala/collection/mutable/GenericArray$.iterate:(Ljava/lang/Object;ILscala/Function1;)Lscala/collection/Traversable;
Asciz	<A:Ljava/lang/Object;>(TA;ILscala/Function1<TA;TA;>;)Lscala/collection/mutable/GenericArray<TA;>;;
Asciz	range;
Asciz	(III)Lscala/collection/Traversable;;
NameAndType	range:(III)Lscala/collection/Traversable;
Method	scala/collection/mutable/GenericArray$.range:(III)Lscala/collection/Traversable;
Asciz	(III)Lscala/collection/mutable/GenericArray<Ljava/lang/Integer;>;;
Asciz	(II)Lscala/collection/Traversable;;
NameAndType	range:(II)Lscala/collection/Traversable;
Method	scala/collection/mutable/GenericArray$.range:(II)Lscala/collection/Traversable;
Asciz	(II)Lscala/collection/mutable/GenericArray<Ljava/lang/Integer;>;;
Asciz	tabulate;
Asciz	(IIIIILscala/Function5;)Lscala/collection/Traversable;;
NameAndType	tabulate:(IIIIILscala/Function5;)Lscala/collection/Traversable;
Method	scala/collection/mutable/GenericArray$.tabulate:(IIIIILscala/Function5;)Lscala/collection/Traversable;
Asciz	<A:Ljava/lang/Object;>(IIIIILscala/Function5<Ljava/lang/Integer;Ljava/lang/Integer;Ljava/lang/Integer;Ljava/lang/Integer;Ljava/lang/Integer;TA;>;)Lscala/collection/mutable/GenericArray<Lscala/collection/mutable/GenericArray<Lscala/collection/mutable/GenericArray<Lscala/collection/mutable/GenericArray<Lscala/collection/mutable/GenericArray<TA;>;>;>;>;>;;
Asciz	(IIIILscala/Function4;)Lscala/collection/Traversable;;
NameAndType	tabulate:(IIIILscala/Function4;)Lscala/collection/Traversable;
Method	scala/collection/mutable/GenericArray$.tabulate:(IIIILscala/Function4;)Lscala/collection/Traversable;
Asciz	<A:Ljava/lang/Object;>(IIIILscala/Function4<Ljava/lang/Integer;Ljava/lang/Integer;Ljava/lang/Integer;Ljava/lang/Integer;TA;>;)Lscala/collection/mutable/GenericArray<Lscala/collection/mutable/GenericArray<Lscala/collection/mutable/GenericArray<Lscala/collection/mutable/GenericArray<TA;>;>;>;>;;
Asciz	(IIILscala/Function3;)Lscala/collection/Traversable;;
NameAndType	tabulate:(IIILscala/Function3;)Lscala/collection/Traversable;
Method	scala/collection/mutable/GenericArray$.tabulate:(IIILscala/Function3;)Lscala/collection/Traversable;
Asciz	<A:Ljava/lang/Object;>(IIILscala/Function3<Ljava/lang/Integer;Ljava/lang/Integer;Ljava/lang/Integer;TA;>;)Lscala/collection/mutable/GenericArray<Lscala/collection/mutable/GenericArray<Lscala/collection/mutable/GenericArray<TA;>;>;>;;
Asciz	(IILscala/Function2;)Lscala/collection/Traversable;;
NameAndType	tabulate:(IILscala/Function2;)Lscala/collection/Traversable;
Method	scala/collection/mutable/GenericArray$.tabulate:(IILscala/Function2;)Lscala/collection/Traversable;
Asciz	<A:Ljava/lang/Object;>(IILscala/Function2<Ljava/lang/Integer;Ljava/lang/Integer;TA;>;)Lscala/collection/mutable/GenericArray<Lscala/collection/mutable/GenericArray<TA;>;>;;
Asciz	(ILscala/Function1;)Lscala/collection/Traversable;;
NameAndType	tabulate:(ILscala/Function1;)Lscala/collection/Traversable;
Method	scala/collection/mutable/GenericArray$.tabulate:(ILscala/Function1;)Lscala/collection/Traversable;
Asciz	<A:Ljava/lang/Object;>(ILscala/Function1<Ljava/lang/Integer;TA;>;)Lscala/collection/mutable/GenericArray<TA;>;;
Asciz	fill;
Asciz	(IIIIILscala/Function0;)Lscala/collection/Traversable;;
NameAndType	fill:(IIIIILscala/Function0;)Lscala/collection/Traversable;
Method	scala/collection/mutable/GenericArray$.fill:(IIIIILscala/Function0;)Lscala/collection/Traversable;
Asciz	<A:Ljava/lang/Object;>(IIIIILscala/Function0<TA;>;)Lscala/collection/mutable/GenericArray<Lscala/collection/mutable/GenericArray<Lscala/collection/mutable/GenericArray<Lscala/collection/mutable/GenericArray<Lscala/collection/mutable/GenericArray<TA;>;>;>;>;>;;
Asciz	(IIIILscala/Function0;)Lscala/collection/Traversable;;
NameAndType	fill:(IIIILscala/Function0;)Lscala/collection/Traversable;
Method	scala/collection/mutable/GenericArray$.fill:(IIIILscala/Function0;)Lscala/collection/Traversable;
Asciz	<A:Ljava/lang/Object;>(IIIILscala/Function0<TA;>;)Lscala/collection/mutable/GenericArray<Lscala/collection/mutable/GenericArray<Lscala/collection/mutable/GenericArray<Lscala/collection/mutable/GenericArray<TA;>;>;>;>;;
Asciz	(IIILscala/Function0;)Lscala/collection/Traversable;;
NameAndType	fill:(IIILscala/Function0;)Lscala/collection/Traversable;
Method	scala/collection/mutable/GenericArray$.fill:(IIILscala/Function0;)Lscala/collection/Traversable;
Asciz	<A:Ljava/lang/Object;>(IIILscala/Function0<TA;>;)Lscala/collection/mutable/GenericArray<Lscala/collection/mutable/GenericArray<Lscala/collection/mutable/GenericArray<TA;>;>;>;;
Asciz	(IILscala/Function0;)Lscala/collection/Traversable;;
NameAndType	fill:(IILscala/Function0;)Lscala/collection/Traversable;
Method	scala/collection/mutable/GenericArray$.fill:(IILscala/Function0;)Lscala/collection/Traversable;
Asciz	<A:Ljava/lang/Object;>(IILscala/Function0<TA;>;)Lscala/collection/mutable/GenericArray<Lscala/collection/mutable/GenericArray<TA;>;>;;
Asciz	(ILscala/Function0;)Lscala/collection/Traversable;;
NameAndType	fill:(ILscala/Function0;)Lscala/collection/Traversable;
Method	scala/collection/mutable/GenericArray$.fill:(ILscala/Function0;)Lscala/collection/Traversable;
Asciz	<A:Ljava/lang/Object;>(ILscala/Function0<TA;>;)Lscala/collection/mutable/GenericArray<TA;>;;
Asciz	concat;
Asciz	(Lscala/collection/Seq;)Lscala/collection/Traversable;;
NameAndType	concat:(Lscala/collection/Seq;)Lscala/collection/Traversable;
Method	scala/collection/mutable/GenericArray$.concat:(Lscala/collection/Seq;)Lscala/collection/Traversable;
Asciz	<A:Ljava/lang/Object;>(Lscala/collection/Seq<Lscala/collection/Traversable<TA;>;>;)Lscala/collection/mutable/GenericArray<TA;>;;
Asciz	empty;
Asciz	()Lscala/collection/Traversable;;
NameAndType	empty:()Lscala/collection/Traversable;
Method	scala/collection/mutable/GenericArray$.empty:()Lscala/collection/Traversable;
Asciz	<A:Ljava/lang/Object;>()Lscala/collection/mutable/GenericArray<TA;>;;
Asciz	array;
Asciz	[Ljava/lang/Object;;
Asciz	length;
Asciz	I;
Asciz	<init>;
Asciz	(I)V;
Asciz	LineNumberTable;
Asciz	scala/collection/mutable/GenericArray;
class	scala/collection/mutable/GenericArray
NameAndType	length:I
Field	scala/collection/mutable/GenericArray.length:I
Asciz	java/lang/Object;
class	java/lang/Object
Asciz	()V;
NameAndType	"<init>":()V
Method	java/lang/Object."<init>":()V
Asciz	scala/collection/TraversableLike$class;
class	scala/collection/TraversableLike$class
Asciz	$init$;
Asciz	(Lscala/collection/TraversableLike;)V;
NameAndType	$init$:(Lscala/collection/TraversableLike;)V
Method	scala/collection/TraversableLike$class.$init$:(Lscala/collection/TraversableLike;)V
Asciz	scala/collection/generic/GenericTraversableTemplate$class;
class	scala/collection/generic/GenericTraversableTemplate$class
Asciz	(Lscala/collection/generic/GenericTraversableTemplate;)V;
NameAndType	$init$:(Lscala/collection/generic/GenericTraversableTemplate;)V
Method	scala/collection/generic/GenericTraversableTemplate$class.$init$:(Lscala/collection/generic/GenericTraversableTemplate;)V
Asciz	scala/collection/Traversable$class;
class	scala/collection/Traversable$class
Asciz	(Lscala/collection/Traversable;)V;
NameAndType	$init$:(Lscala/collection/Traversable;)V
Method	scala/collection/Traversable$class.$init$:(Lscala/collection/Traversable;)V
Asciz	scala/collection/mutable/Traversable$class;
class	scala/collection/mutable/Traversable$class
Asciz	(Lscala/collection/mutable/Traversable;)V;
NameAndType	$init$:(Lscala/collection/mutable/Traversable;)V
Method	scala/collection/mutable/Traversable$class.$init$:(Lscala/collection/mutable/Traversable;)V
Asciz	scala/collection/IterableLike$class;
class	scala/collection/IterableLike$class
Asciz	(Lscala/collection/IterableLike;)V;
NameAndType	$init$:(Lscala/collection/IterableLike;)V
Method	scala/collection/IterableLike$class.$init$:(Lscala/collection/IterableLike;)V
Asciz	scala/collection/Iterable$class;
class	scala/collection/Iterable$class
Asciz	(Lscala/collection/Iterable;)V;
NameAndType	$init$:(Lscala/collection/Iterable;)V
Method	scala/collection/Iterable$class.$init$:(Lscala/collection/Iterable;)V
Asciz	scala/collection/mutable/Iterable$class;
class	scala/collection/mutable/Iterable$class
Asciz	(Lscala/collection/mutable/Iterable;)V;
NameAndType	$init$:(Lscala/collection/mutable/Iterable;)V
Method	scala/collection/mutable/Iterable$class.$init$:(Lscala/collection/mutable/Iterable;)V
Asciz	scala/Function1$class;
class	scala/Function1$class
Asciz	(Lscala/Function1;)V;
NameAndType	$init$:(Lscala/Function1;)V
Method	scala/Function1$class.$init$:(Lscala/Function1;)V
Asciz	scala/PartialFunction$class;
class	scala/PartialFunction$class
Asciz	(Lscala/PartialFunction;)V;
NameAndType	$init$:(Lscala/PartialFunction;)V
Method	scala/PartialFunction$class.$init$:(Lscala/PartialFunction;)V
Asciz	scala/collection/SeqLike$class;
class	scala/collection/SeqLike$class
Asciz	(Lscala/collection/SeqLike;)V;
NameAndType	$init$:(Lscala/collection/SeqLike;)V
Method	scala/collection/SeqLike$class.$init$:(Lscala/collection/SeqLike;)V
Asciz	scala/collection/Seq$class;
class	scala/collection/Seq$class
Asciz	(Lscala/collection/Seq;)V;
NameAndType	$init$:(Lscala/collection/Seq;)V
Method	scala/collection/Seq$class.$init$:(Lscala/collection/Seq;)V
Asciz	scala/collection/mutable/Seq$class;
class	scala/collection/mutable/Seq$class
Asciz	(Lscala/collection/mutable/Seq;)V;
NameAndType	$init$:(Lscala/collection/mutable/Seq;)V
Method	scala/collection/mutable/Seq$class.$init$:(Lscala/collection/mutable/Seq;)V
Asciz	scala/collection/IndexedSeqLike$class;
class	scala/collection/IndexedSeqLike$class
Asciz	(Lscala/collection/IndexedSeqLike;)V;
NameAndType	$init$:(Lscala/collection/IndexedSeqLike;)V
Method	scala/collection/IndexedSeqLike$class.$init$:(Lscala/collection/IndexedSeqLike;)V
Asciz	scala/collection/IndexedSeq$class;
class	scala/collection/IndexedSeq$class
Asciz	(Lscala/collection/IndexedSeq;)V;
NameAndType	$init$:(Lscala/collection/IndexedSeq;)V
Method	scala/collection/IndexedSeq$class.$init$:(Lscala/collection/IndexedSeq;)V
Asciz	scala/collection/mutable/IndexedSeqLike$class;
class	scala/collection/mutable/IndexedSeqLike$class
Asciz	(Lscala/collection/mutable/IndexedSeqLike;)V;
NameAndType	$init$:(Lscala/collection/mutable/IndexedSeqLike;)V
Method	scala/collection/mutable/IndexedSeqLike$class.$init$:(Lscala/collection/mutable/IndexedSeqLike;)V
Asciz	scala/collection/mutable/IndexedSeq$class;
class	scala/collection/mutable/IndexedSeq$class
Asciz	(Lscala/collection/mutable/IndexedSeq;)V;
NameAndType	$init$:(Lscala/collection/mutable/IndexedSeq;)V
Method	scala/collection/mutable/IndexedSeq$class.$init$:(Lscala/collection/mutable/IndexedSeq;)V
NameAndType	array:[Ljava/lang/Object;
Field	scala/collection/mutable/GenericArray.array:[Ljava/lang/Object;
Asciz	this;
Asciz	Lscala/collection/mutable/GenericArray;;
Asciz	LocalVariableTable;
Asciz	apply;
Asciz	(Ljava/lang/Object;)Ljava/lang/Object;;
Asciz	scala/runtime/BoxesRunTime;
class	scala/runtime/BoxesRunTime
Asciz	unboxToInt;
Asciz	(Ljava/lang/Object;)I;
NameAndType	unboxToInt:(Ljava/lang/Object;)I
Method	scala/runtime/BoxesRunTime.unboxToInt:(Ljava/lang/Object;)I
Asciz	(I)Ljava/lang/Object;;
NameAndType	apply:(I)Ljava/lang/Object;
Method	scala/collection/mutable/GenericArray.apply:(I)Ljava/lang/Object;
Asciz	v1;
Asciz	Ljava/lang/Object;;
Asciz	thisCollection;
Asciz	()Lscala/collection/IndexedSeq;;
Asciz	scala/collection/mutable/IndexedSeqLike;
class	scala/collection/mutable/IndexedSeqLike
Asciz	()Lscala/collection/mutable/IndexedSeq;;
NameAndType	thisCollection:()Lscala/collection/mutable/IndexedSeq;
InterfaceMethod	scala/collection/mutable/IndexedSeqLike.thisCollection:()Lscala/collection/mutable/IndexedSeq;
Asciz	()Lscala/collection/Seq;;
Asciz	()Lscala/collection/Iterable;;
Asciz	toCollection;
Asciz	(Ljava/lang/Object;)Lscala/collection/IndexedSeq;;
Asciz	(Ljava/lang/Object;)Lscala/collection/mutable/IndexedSeq;;
NameAndType	toCollection:(Ljava/lang/Object;)Lscala/collection/mutable/IndexedSeq;
InterfaceMethod	scala/collection/mutable/IndexedSeqLike.toCollection:(Ljava/lang/Object;)Lscala/collection/mutable/IndexedSeq;
Asciz	repr;
Asciz	(Ljava/lang/Object;)Lscala/collection/Seq;;
Asciz	(Ljava/lang/Object;)Lscala/collection/Iterable;;
Asciz	(Ljava/lang/Object;)Lscala/collection/Traversable;;
Asciz	view;
Asciz	()Lscala/collection/IndexedSeqView;;
Asciz	()Lscala/collection/mutable/IndexedSeqView;;
NameAndType	view:()Lscala/collection/mutable/IndexedSeqView;
InterfaceMethod	scala/collection/mutable/IndexedSeqLike.view:()Lscala/collection/mutable/IndexedSeqView;
Asciz	()Lscala/collection/SeqView;;
Asciz	()Lscala/collection/IterableView;;
Asciz	()Lscala/collection/TraversableView;;
Asciz	(II)Lscala/collection/IndexedSeqView;;
Asciz	(II)Lscala/collection/mutable/IndexedSeqView;;
NameAndType	view:(II)Lscala/collection/mutable/IndexedSeqView;
InterfaceMethod	scala/collection/mutable/IndexedSeqLike.view:(II)Lscala/collection/mutable/IndexedSeqView;
Asciz	from;
Asciz	until;
Asciz	(II)Lscala/collection/SeqView;;
Asciz	(II)Lscala/collection/IterableView;;
Asciz	(II)Lscala/collection/TraversableView;;
Asciz	isDefinedAt;
Asciz	(Ljava/lang/Object;)Z;
Asciz	scala/collection/SeqLike;
class	scala/collection/SeqLike
Asciz	(I)Z;
NameAndType	isDefinedAt:(I)Z
InterfaceMethod	scala/collection/SeqLike.isDefinedAt:(I)Z
Asciz	x;
Asciz	projection;
NameAndType	projection:()Lscala/collection/SeqView;
InterfaceMethod	scala/collection/SeqLike.projection:()Lscala/collection/SeqView;
Asciz	andThen;
Asciz	(Lscala/Function1;)Lscala/Function1;;
Asciz	scala/PartialFunction;
class	scala/PartialFunction
Asciz	(Lscala/Function1;)Lscala/PartialFunction;;
NameAndType	andThen:(Lscala/Function1;)Lscala/PartialFunction;
InterfaceMethod	scala/PartialFunction.andThen:(Lscala/Function1;)Lscala/PartialFunction;
Asciz	g;
Asciz	Lscala/Function1;;
Asciz	copyToArray;
Asciz	(Ljava/lang/Object;II)V;
Asciz	scala/Predef$;
class	scala/Predef$
Asciz	Lscala/Predef$;;
NameAndType	MODULE$:Lscala/Predef$;
Field	scala/Predef$.MODULE$:Lscala/Predef$;
Asciz	intWrapper;
Asciz	(I)Lscala/runtime/RichInt;;
NameAndType	intWrapper:(I)Lscala/runtime/RichInt;
Method	scala/Predef$.intWrapper:(I)Lscala/runtime/RichInt;
Asciz	scala/runtime/ScalaRunTime$;
class	scala/runtime/ScalaRunTime$
Asciz	Lscala/runtime/ScalaRunTime$;;
NameAndType	MODULE$:Lscala/runtime/ScalaRunTime$;
Field	scala/runtime/ScalaRunTime$.MODULE$:Lscala/runtime/ScalaRunTime$;
Asciz	array_length;
NameAndType	array_length:(Ljava/lang/Object;)I
Method	scala/runtime/ScalaRunTime$.array_length:(Ljava/lang/Object;)I
Asciz	scala/runtime/RichInt;
class	scala/runtime/RichInt
Asciz	min;
Asciz	(I)I;
NameAndType	min:(I)I
Method	scala/runtime/RichInt.min:(I)I
Asciz	()I;
NameAndType	length:()I
Method	scala/collection/mutable/GenericArray.length:()I
Asciz	scala/Array$;
class	scala/Array$
Asciz	Lscala/Array$;;
NameAndType	MODULE$:Lscala/Array$;
Field	scala/Array$.MODULE$:Lscala/Array$;
Asciz	()[Ljava/lang/Object;;
NameAndType	array:()[Ljava/lang/Object;
Method	scala/collection/mutable/GenericArray.array:()[Ljava/lang/Object;
Asciz	copy;
Asciz	(Ljava/lang/Object;ILjava/lang/Object;II)V;
NameAndType	copy:(Ljava/lang/Object;ILjava/lang/Object;II)V
Method	scala/Array$.copy:(Ljava/lang/Object;ILjava/lang/Object;II)V
Asciz	xs;
Asciz	start;
Asciz	len;
Asciz	len1;
Asciz	<B:Ljava/lang/Object;>([TB;II)V;
Asciz	foreach;
Asciz	scala/Function1;
class	scala/Function1
NameAndType	apply:(Ljava/lang/Object;)Ljava/lang/Object;
InterfaceMethod	scala/Function1.apply:(Ljava/lang/Object;)Ljava/lang/Object;
Asciz	f;
Asciz	i;
Asciz	<U:Ljava/lang/Object;>(Lscala/Function1<TA;TU;>;)V;
Asciz	update;
Asciz	(ILjava/lang/Object;)V;
Asciz	java/lang/IndexOutOfBoundsException;
class	java/lang/IndexOutOfBoundsException
Asciz	boxToInteger;
Asciz	(I)Ljava/lang/Integer;;
NameAndType	boxToInteger:(I)Ljava/lang/Integer;
Method	scala/runtime/BoxesRunTime.boxToInteger:(I)Ljava/lang/Integer;
Asciz	toString;
Asciz	()Ljava/lang/String;;
NameAndType	toString:()Ljava/lang/String;
Method	java/lang/Object.toString:()Ljava/lang/String;
Asciz	(Ljava/lang/String;)V;
NameAndType	"<init>":(Ljava/lang/String;)V
Method	java/lang/IndexOutOfBoundsException."<init>":(Ljava/lang/String;)V
Asciz	idx;
Asciz	elem;
Asciz	(ITA;)V;
Asciz	(I)TA;;
Asciz	companion;
Asciz	()Lscala/collection/generic/GenericCompanion;;
Asciz	()Lscala/collection/generic/GenericCompanion<Lscala/collection/mutable/GenericArray;>;;
Asciz	withFilter;
Asciz	(Lscala/Function1;)Lscala/collection/TraversableLike$WithFilter;;
Asciz	(Lscala/collection/TraversableLike;Lscala/Function1;)Lscala/collection/TraversableLike$WithFilter;;
NameAndType	withFilter:(Lscala/collection/TraversableLike;Lscala/Function1;)Lscala/collection/TraversableLike$WithFilter;
Method	scala/collection/TraversableLike$class.withFilter:(Lscala/collection/TraversableLike;Lscala/Function1;)Lscala/collection/TraversableLike$WithFilter;
Asciz	p;
Asciz	stringPrefix;
Asciz	(Lscala/collection/TraversableLike;)Ljava/lang/String;;
NameAndType	stringPrefix:(Lscala/collection/TraversableLike;)Ljava/lang/String;
Method	scala/collection/TraversableLike$class.stringPrefix:(Lscala/collection/TraversableLike;)Ljava/lang/String;
Asciz	addString;
Asciz	(Lscala/collection/mutable/StringBuilder;)Lscala/collection/mutable/StringBuilder;;
Asciz	(Lscala/collection/TraversableLike;Lscala/collection/mutable/StringBuilder;)Lscala/collection/mutable/StringBuilder;;
NameAndType	addString:(Lscala/collection/TraversableLike;Lscala/collection/mutable/StringBuilder;)Lscala/collection/mutable/StringBuilder;
Method	scala/collection/TraversableLike$class.addString:(Lscala/collection/TraversableLike;Lscala/collection/mutable/StringBuilder;)Lscala/collection/mutable/StringBuilder;
Asciz	b;
Asciz	Lscala/collection/mutable/StringBuilder;;
Asciz	(Lscala/collection/mutable/StringBuilder;Ljava/lang/String;)Lscala/collection/mutable/StringBuilder;;
Asciz	(Lscala/collection/TraversableLike;Lscala/collection/mutable/StringBuilder;Ljava/lang/String;)Lscala/collection/mutable/StringBuilder;;
NameAndType	addString:(Lscala/collection/TraversableLike;Lscala/collection/mutable/StringBuilder;Ljava/lang/String;)Lscala/collection/mutable/StringBuilder;
Method	scala/collection/TraversableLike$class.addString:(Lscala/collection/TraversableLike;Lscala/collection/mutable/StringBuilder;Ljava/lang/String;)Lscala/collection/mutable/StringBuilder;
Asciz	sep;
Asciz	Ljava/lang/String;;
Asciz	(Lscala/collection/mutable/StringBuilder;Ljava/lang/String;Ljava/lang/String;Ljava/lang/String;)Lscala/collection/mutable/StringBuilder;;
Asciz	(Lscala/collection/TraversableLike;Lscala/collection/mutable/StringBuilder;Ljava/lang/String;Ljava/lang/String;Ljava/lang/String;)Lscala/collection/mutable/StringBuilder;;
NameAndType	addString:(Lscala/collection/TraversableLike;Lscala/collection/mutable/StringBuilder;Ljava/lang/String;Ljava/lang/String;Ljava/lang/String;)Lscala/collection/mutable/StringBuilder;
Method	scala/collection/TraversableLike$class.addString:(Lscala/collection/TraversableLike;Lscala/collection/mutable/StringBuilder;Ljava/lang/String;Ljava/lang/String;Ljava/lang/String;)Lscala/collection/mutable/StringBuilder;
Asciz	end;
Asciz	mkString;
NameAndType	mkString:(Lscala/collection/TraversableLike;)Ljava/lang/String;
Method	scala/collection/TraversableLike$class.mkString:(Lscala/collection/TraversableLike;)Ljava/lang/String;
Asciz	(Ljava/lang/String;)Ljava/lang/String;;
Asciz	(Lscala/collection/TraversableLike;Ljava/lang/String;)Ljava/lang/String;;
NameAndType	mkString:(Lscala/collection/TraversableLike;Ljava/lang/String;)Ljava/lang/String;
Method	scala/collection/TraversableLike$class.mkString:(Lscala/collection/TraversableLike;Ljava/lang/String;)Ljava/lang/String;
Asciz	(Ljava/lang/String;Ljava/lang/String;Ljava/lang/String;)Ljava/lang/String;;
Asciz	(Lscala/collection/TraversableLike;Ljava/lang/String;Ljava/lang/String;Ljava/lang/String;)Ljava/lang/String;;
NameAndType	mkString:(Lscala/collection/TraversableLike;Ljava/lang/String;Ljava/lang/String;Ljava/lang/String;)Ljava/lang/String;
Method	scala/collection/TraversableLike$class.mkString:(Lscala/collection/TraversableLike;Ljava/lang/String;Ljava/lang/String;Ljava/lang/String;)Ljava/lang/String;
Asciz	toMap;
Asciz	(Lscala/Predef$$less$colon$less;)Lscala/collection/immutable/Map;;
Asciz	(Lscala/collection/TraversableLike;Lscala/Predef$$less$colon$less;)Lscala/collection/immutable/Map;;
NameAndType	toMap:(Lscala/collection/TraversableLike;Lscala/Predef$$less$colon$less;)Lscala/collection/immutable/Map;
Method	scala/collection/TraversableLike$class.toMap:(Lscala/collection/TraversableLike;Lscala/Predef$$less$colon$less;)Lscala/collection/immutable/Map;
Asciz	ev;
Asciz	Lscala/Predef$$less$colon$less;;
Asciz	toSet;
Asciz	()Lscala/collection/immutable/Set;;
Asciz	(Lscala/collection/TraversableLike;)Lscala/collection/immutable/Set;;
NameAndType	toSet:(Lscala/collection/TraversableLike;)Lscala/collection/immutable/Set;
Method	scala/collection/TraversableLike$class.toSet:(Lscala/collection/TraversableLike;)Lscala/collection/immutable/Set;
Asciz	toIndexedSeq;
Asciz	(Lscala/collection/TraversableLike;)Lscala/collection/mutable/IndexedSeq;;
NameAndType	toIndexedSeq:(Lscala/collection/TraversableLike;)Lscala/collection/mutable/IndexedSeq;
Method	scala/collection/TraversableLike$class.toIndexedSeq:(Lscala/collection/TraversableLike;)Lscala/collection/mutable/IndexedSeq;
Asciz	toList;
Asciz	()Lscala/collection/immutable/List;;
Asciz	(Lscala/collection/TraversableLike;)Lscala/collection/immutable/List;;
NameAndType	toList:(Lscala/collection/TraversableLike;)Lscala/collection/immutable/List;
Method	scala/collection/TraversableLike$class.toList:(Lscala/collection/TraversableLike;)Lscala/collection/immutable/List;
Asciz	toArray;
Asciz	(Lscala/reflect/ClassManifest;)Ljava/lang/Object;;
Asciz	(Lscala/collection/TraversableLike;Lscala/reflect/ClassManifest;)Ljava/lang/Object;;
NameAndType	toArray:(Lscala/collection/TraversableLike;Lscala/reflect/ClassManifest;)Ljava/lang/Object;
Method	scala/collection/TraversableLike$class.toArray:(Lscala/collection/TraversableLike;Lscala/reflect/ClassManifest;)Ljava/lang/Object;
Asciz	evidence$1;
Asciz	Lscala/reflect/ClassManifest;;
Asciz	(Ljava/lang/Object;)V;
Asciz	(Lscala/collection/TraversableLike;Ljava/lang/Object;)V;
NameAndType	copyToArray:(Lscala/collection/TraversableLike;Ljava/lang/Object;)V
Method	scala/collection/TraversableLike$class.copyToArray:(Lscala/collection/TraversableLike;Ljava/lang/Object;)V
Asciz	(Ljava/lang/Object;I)V;
Asciz	(Lscala/collection/TraversableLike;Ljava/lang/Object;I)V;
NameAndType	copyToArray:(Lscala/collection/TraversableLike;Ljava/lang/Object;I)V
Method	scala/collection/TraversableLike$class.copyToArray:(Lscala/collection/TraversableLike;Ljava/lang/Object;I)V
Asciz	copyToBuffer;
Asciz	(Lscala/collection/mutable/Buffer;)V;
Asciz	(Lscala/collection/TraversableLike;Lscala/collection/mutable/Buffer;)V;
NameAndType	copyToBuffer:(Lscala/collection/TraversableLike;Lscala/collection/mutable/Buffer;)V
Method	scala/collection/TraversableLike$class.copyToBuffer:(Lscala/collection/TraversableLike;Lscala/collection/mutable/Buffer;)V
Asciz	dest;
Asciz	Lscala/collection/mutable/Buffer;;
Asciz	lastOption;
Asciz	()Lscala/Option;;
Asciz	(Lscala/collection/TraversableLike;)Lscala/Option;;
NameAndType	lastOption:(Lscala/collection/TraversableLike;)Lscala/Option;
Method	scala/collection/TraversableLike$class.lastOption:(Lscala/collection/TraversableLike;)Lscala/Option;
Asciz	headOption;
NameAndType	headOption:(Lscala/collection/TraversableLike;)Lscala/Option;
Method	scala/collection/TraversableLike$class.headOption:(Lscala/collection/TraversableLike;)Lscala/Option;
Asciz	max;
Asciz	(Lscala/math/Ordering;)Ljava/lang/Object;;
Asciz	(Lscala/collection/TraversableLike;Lscala/math/Ordering;)Ljava/lang/Object;;
NameAndType	max:(Lscala/collection/TraversableLike;Lscala/math/Ordering;)Ljava/lang/Object;
Method	scala/collection/TraversableLike$class.max:(Lscala/collection/TraversableLike;Lscala/math/Ordering;)Ljava/lang/Object;
Asciz	cmp;
Asciz	Lscala/math/Ordering;;
NameAndType	min:(Lscala/collection/TraversableLike;Lscala/math/Ordering;)Ljava/lang/Object;
Method	scala/collection/TraversableLike$class.min:(Lscala/collection/TraversableLike;Lscala/math/Ordering;)Ljava/lang/Object;
Asciz	product;
Asciz	(Lscala/math/Numeric;)Ljava/lang/Object;;
Asciz	(Lscala/collection/TraversableLike;Lscala/math/Numeric;)Ljava/lang/Object;;
NameAndType	product:(Lscala/collection/TraversableLike;Lscala/math/Numeric;)Ljava/lang/Object;
Method	scala/collection/TraversableLike$class.product:(Lscala/collection/TraversableLike;Lscala/math/Numeric;)Ljava/lang/Object;
Asciz	num;
Asciz	Lscala/math/Numeric;;
Asciz	sum;
NameAndType	sum:(Lscala/collection/TraversableLike;Lscala/math/Numeric;)Ljava/lang/Object;
Method	scala/collection/TraversableLike$class.sum:(Lscala/collection/TraversableLike;Lscala/math/Numeric;)Ljava/lang/Object;
Asciz	reduceRightOption;
Asciz	(Lscala/Function2;)Lscala/Option;;
Asciz	(Lscala/collection/TraversableLike;Lscala/Function2;)Lscala/Option;;
NameAndType	reduceRightOption:(Lscala/collection/TraversableLike;Lscala/Function2;)Lscala/Option;
Method	scala/collection/TraversableLike$class.reduceRightOption:(Lscala/collection/TraversableLike;Lscala/Function2;)Lscala/Option;
Asciz	op;
Asciz	Lscala/Function2;;
Asciz	reduceLeftOption;
NameAndType	reduceLeftOption:(Lscala/collection/TraversableLike;Lscala/Function2;)Lscala/Option;
Method	scala/collection/TraversableLike$class.reduceLeftOption:(Lscala/collection/TraversableLike;Lscala/Function2;)Lscala/Option;
Asciz	$colon$bslash;
Asciz	(Ljava/lang/Object;Lscala/Function2;)Ljava/lang/Object;;
Asciz	(Lscala/collection/TraversableLike;Ljava/lang/Object;Lscala/Function2;)Ljava/lang/Object;;
NameAndType	$colon$bslash:(Lscala/collection/TraversableLike;Ljava/lang/Object;Lscala/Function2;)Ljava/lang/Object;
Method	scala/collection/TraversableLike$class.$colon$bslash:(Lscala/collection/TraversableLike;Ljava/lang/Object;Lscala/Function2;)Ljava/lang/Object;
Asciz	z;
Asciz	$div$colon;
NameAndType	$div$colon:(Lscala/collection/TraversableLike;Ljava/lang/Object;Lscala/Function2;)Ljava/lang/Object;
Method	scala/collection/TraversableLike$class.$div$colon:(Lscala/collection/TraversableLike;Ljava/lang/Object;Lscala/Function2;)Ljava/lang/Object;
Asciz	count;
Asciz	(Lscala/Function1;)I;
Asciz	(Lscala/collection/TraversableLike;Lscala/Function1;)I;
NameAndType	count:(Lscala/collection/TraversableLike;Lscala/Function1;)I
Method	scala/collection/TraversableLike$class.count:(Lscala/collection/TraversableLike;Lscala/Function1;)I
Asciz	groupBy;
Asciz	(Lscala/Function1;)Lscala/collection/Map;;
Asciz	(Lscala/collection/TraversableLike;Lscala/Function1;)Lscala/collection/Map;;
NameAndType	groupBy:(Lscala/collection/TraversableLike;Lscala/Function1;)Lscala/collection/Map;
Method	scala/collection/TraversableLike$class.groupBy:(Lscala/collection/TraversableLike;Lscala/Function1;)Lscala/collection/Map;
Asciz	partition;
Asciz	(Lscala/Function1;)Lscala/Tuple2;;
Asciz	(Lscala/collection/TraversableLike;Lscala/Function1;)Lscala/Tuple2;;
NameAndType	partition:(Lscala/collection/TraversableLike;Lscala/Function1;)Lscala/Tuple2;
Method	scala/collection/TraversableLike$class.partition:(Lscala/collection/TraversableLike;Lscala/Function1;)Lscala/Tuple2;
Asciz	partialMap;
Asciz	(Lscala/PartialFunction;Lscala/collection/generic/CanBuildFrom;)Ljava/lang/Object;;
Asciz	(Lscala/collection/TraversableLike;Lscala/PartialFunction;Lscala/collection/generic/CanBuildFrom;)Ljava/lang/Object;;
NameAndType	partialMap:(Lscala/collection/TraversableLike;Lscala/PartialFunction;Lscala/collection/generic/CanBuildFrom;)Ljava/lang/Object;
Method	scala/collection/TraversableLike$class.partialMap:(Lscala/collection/TraversableLike;Lscala/PartialFunction;Lscala/collection/generic/CanBuildFrom;)Ljava/lang/Object;
Asciz	pf;
Asciz	Lscala/PartialFunction;;
Asciz	bf;
Asciz	Lscala/collection/generic/CanBuildFrom;;
Asciz	filterNot;
Asciz	(Lscala/Function1;)Ljava/lang/Object;;
Asciz	(Lscala/collection/TraversableLike;Lscala/Function1;)Ljava/lang/Object;;
NameAndType	filterNot:(Lscala/collection/TraversableLike;Lscala/Function1;)Ljava/lang/Object;
Method	scala/collection/TraversableLike$class.filterNot:(Lscala/collection/TraversableLike;Lscala/Function1;)Ljava/lang/Object;
Asciz	filter;
NameAndType	filter:(Lscala/collection/TraversableLike;Lscala/Function1;)Ljava/lang/Object;
Method	scala/collection/TraversableLike$class.filter:(Lscala/collection/TraversableLike;Lscala/Function1;)Ljava/lang/Object;
Asciz	flatMap;
Asciz	(Lscala/Function1;Lscala/collection/generic/CanBuildFrom;)Ljava/lang/Object;;
Asciz	(Lscala/collection/TraversableLike;Lscala/Function1;Lscala/collection/generic/CanBuildFrom;)Ljava/lang/Object;;
NameAndType	flatMap:(Lscala/collection/TraversableLike;Lscala/Function1;Lscala/collection/generic/CanBuildFrom;)Ljava/lang/Object;
Method	scala/collection/TraversableLike$class.flatMap:(Lscala/collection/TraversableLike;Lscala/Function1;Lscala/collection/generic/CanBuildFrom;)Ljava/lang/Object;
Asciz	map;
NameAndType	map:(Lscala/collection/TraversableLike;Lscala/Function1;Lscala/collection/generic/CanBuildFrom;)Ljava/lang/Object;
Method	scala/collection/TraversableLike$class.map:(Lscala/collection/TraversableLike;Lscala/Function1;Lscala/collection/generic/CanBuildFrom;)Ljava/lang/Object;
Asciz	$plus$plus;
Asciz	(Lscala/collection/Iterator;Lscala/collection/generic/CanBuildFrom;)Ljava/lang/Object;;
Asciz	(Lscala/collection/TraversableLike;Lscala/collection/Iterator;Lscala/collection/generic/CanBuildFrom;)Ljava/lang/Object;;
NameAndType	$plus$plus:(Lscala/collection/TraversableLike;Lscala/collection/Iterator;Lscala/collection/generic/CanBuildFrom;)Ljava/lang/Object;
Method	scala/collection/TraversableLike$class.$plus$plus:(Lscala/collection/TraversableLike;Lscala/collection/Iterator;Lscala/collection/generic/CanBuildFrom;)Ljava/lang/Object;
Asciz	that;
Asciz	Lscala/collection/Iterator;;
Asciz	(Lscala/collection/Traversable;Lscala/collection/generic/CanBuildFrom;)Ljava/lang/Object;;
Asciz	(Lscala/collection/TraversableLike;Lscala/collection/Traversable;Lscala/collection/generic/CanBuildFrom;)Ljava/lang/Object;;
NameAndType	$plus$plus:(Lscala/collection/TraversableLike;Lscala/collection/Traversable;Lscala/collection/generic/CanBuildFrom;)Ljava/lang/Object;
Method	scala/collection/TraversableLike$class.$plus$plus:(Lscala/collection/TraversableLike;Lscala/collection/Traversable;Lscala/collection/generic/CanBuildFrom;)Ljava/lang/Object;
Asciz	Lscala/collection/Traversable;;
Asciz	hasDefiniteSize;
Asciz	()Z;
Asciz	(Lscala/collection/TraversableLike;)Z;
NameAndType	hasDefiniteSize:(Lscala/collection/TraversableLike;)Z
Method	scala/collection/TraversableLike$class.hasDefiniteSize:(Lscala/collection/TraversableLike;)Z
Asciz	nonEmpty;
NameAndType	nonEmpty:(Lscala/collection/TraversableLike;)Z
Method	scala/collection/TraversableLike$class.nonEmpty:(Lscala/collection/TraversableLike;)Z
Asciz	()Ljava/lang/Object;;
Asciz	(Lscala/collection/TraversableLike;)Ljava/lang/Object;;
NameAndType	repr:(Lscala/collection/TraversableLike;)Ljava/lang/Object;
Method	scala/collection/TraversableLike$class.repr:(Lscala/collection/TraversableLike;)Ljava/lang/Object;
Asciz	transpose;
Asciz	(Lscala/Function1;)Lscala/collection/Traversable;;
Asciz	(Lscala/collection/generic/GenericTraversableTemplate;Lscala/Function1;)Lscala/collection/Traversable;;
NameAndType	transpose:(Lscala/collection/generic/GenericTraversableTemplate;Lscala/Function1;)Lscala/collection/Traversable;
Method	scala/collection/generic/GenericTraversableTemplate$class.transpose:(Lscala/collection/generic/GenericTraversableTemplate;Lscala/Function1;)Lscala/collection/Traversable;
Asciz	asTraversable;
Asciz	flatten;
NameAndType	flatten:(Lscala/collection/generic/GenericTraversableTemplate;Lscala/Function1;)Lscala/collection/Traversable;
Method	scala/collection/generic/GenericTraversableTemplate$class.flatten:(Lscala/collection/generic/GenericTraversableTemplate;Lscala/Function1;)Lscala/collection/Traversable;
Asciz	unzip;
Asciz	(Lscala/collection/generic/GenericTraversableTemplate;Lscala/Function1;)Lscala/Tuple2;;
NameAndType	unzip:(Lscala/collection/generic/GenericTraversableTemplate;Lscala/Function1;)Lscala/Tuple2;
Method	scala/collection/generic/GenericTraversableTemplate$class.unzip:(Lscala/collection/generic/GenericTraversableTemplate;Lscala/Function1;)Lscala/Tuple2;
Asciz	asPair;
Asciz	genericBuilder;
Asciz	()Lscala/collection/mutable/Builder;;
Asciz	(Lscala/collection/generic/GenericTraversableTemplate;)Lscala/collection/mutable/Builder;;
NameAndType	genericBuilder:(Lscala/collection/generic/GenericTraversableTemplate;)Lscala/collection/mutable/Builder;
Method	scala/collection/generic/GenericTraversableTemplate$class.genericBuilder:(Lscala/collection/generic/GenericTraversableTemplate;)Lscala/collection/mutable/Builder;
Asciz	newBuilder;
NameAndType	newBuilder:(Lscala/collection/generic/GenericTraversableTemplate;)Lscala/collection/mutable/Builder;
Method	scala/collection/generic/GenericTraversableTemplate$class.newBuilder:(Lscala/collection/generic/GenericTraversableTemplate;)Lscala/collection/mutable/Builder;
Asciz	firstOption;
Asciz	(Lscala/collection/IterableLike;)Lscala/Option;;
NameAndType	firstOption:(Lscala/collection/IterableLike;)Lscala/Option;
Method	scala/collection/IterableLike$class.firstOption:(Lscala/collection/IterableLike;)Lscala/Option;
Asciz	Deprecated;
Asciz	first;
Asciz	(Lscala/collection/IterableLike;)Ljava/lang/Object;;
NameAndType	first:(Lscala/collection/IterableLike;)Ljava/lang/Object;
Method	scala/collection/IterableLike$class.first:(Lscala/collection/IterableLike;)Ljava/lang/Object;
Asciz	canEqual;
Asciz	(Lscala/collection/IterableLike;Ljava/lang/Object;)Z;
NameAndType	canEqual:(Lscala/collection/IterableLike;Ljava/lang/Object;)Z
Method	scala/collection/IterableLike$class.canEqual:(Lscala/collection/IterableLike;Ljava/lang/Object;)Z
Asciz	toStream;
Asciz	()Lscala/collection/immutable/Stream;;
Asciz	(Lscala/collection/IterableLike;)Lscala/collection/immutable/Stream;;
NameAndType	toStream:(Lscala/collection/IterableLike;)Lscala/collection/immutable/Stream;
Method	scala/collection/IterableLike$class.toStream:(Lscala/collection/IterableLike;)Lscala/collection/immutable/Stream;
Asciz	zipAll;
Asciz	(Lscala/collection/Iterable;Ljava/lang/Object;Ljava/lang/Object;Lscala/collection/generic/CanBuildFrom;)Ljava/lang/Object;;
Asciz	(Lscala/collection/IterableLike;Lscala/collection/Iterable;Ljava/lang/Object;Ljava/lang/Object;Lscala/collection/generic/CanBuildFrom;)Ljava/lang/Object;;
NameAndType	zipAll:(Lscala/collection/IterableLike;Lscala/collection/Iterable;Ljava/lang/Object;Ljava/lang/Object;Lscala/collection/generic/CanBuildFrom;)Ljava/lang/Object;
Method	scala/collection/IterableLike$class.zipAll:(Lscala/collection/IterableLike;Lscala/collection/Iterable;Ljava/lang/Object;Ljava/lang/Object;Lscala/collection/generic/CanBuildFrom;)Ljava/lang/Object;
Asciz	Lscala/collection/Iterable;;
Asciz	thisElem;
Asciz	thatElem;
Asciz	toIterable;
Asciz	(Lscala/collection/IterableLike;)Lscala/collection/Iterable;;
NameAndType	toIterable:(Lscala/collection/IterableLike;)Lscala/collection/Iterable;
Method	scala/collection/IterableLike$class.toIterable:(Lscala/collection/IterableLike;)Lscala/collection/Iterable;
Asciz	elements;
Asciz	()Lscala/collection/Iterator;;
Asciz	(Lscala/collection/IterableLike;)Lscala/collection/Iterator;;
NameAndType	elements:(Lscala/collection/IterableLike;)Lscala/collection/Iterator;
Method	scala/collection/IterableLike$class.elements:(Lscala/collection/IterableLike;)Lscala/collection/Iterator;
Asciz	compose;
Asciz	(Lscala/Function1;Lscala/Function1;)Lscala/Function1;;
NameAndType	compose:(Lscala/Function1;Lscala/Function1;)Lscala/Function1;
Method	scala/Function1$class.compose:(Lscala/Function1;Lscala/Function1;)Lscala/Function1;
Asciz	lift;
Asciz	()Lscala/Function1;;
Asciz	(Lscala/PartialFunction;)Lscala/Function1;;
NameAndType	lift:(Lscala/PartialFunction;)Lscala/Function1;
Method	scala/PartialFunction$class.lift:(Lscala/PartialFunction;)Lscala/Function1;
Asciz	(Lscala/PartialFunction;Lscala/Function1;)Lscala/PartialFunction;;
NameAndType	andThen:(Lscala/PartialFunction;Lscala/Function1;)Lscala/PartialFunction;
Method	scala/PartialFunction$class.andThen:(Lscala/PartialFunction;Lscala/Function1;)Lscala/PartialFunction;
Asciz	k;
Asciz	orElse;
Asciz	(Lscala/PartialFunction;)Lscala/PartialFunction;;
Asciz	(Lscala/PartialFunction;Lscala/PartialFunction;)Lscala/PartialFunction;;
NameAndType	orElse:(Lscala/PartialFunction;Lscala/PartialFunction;)Lscala/PartialFunction;
Method	scala/PartialFunction$class.orElse:(Lscala/PartialFunction;Lscala/PartialFunction;)Lscala/PartialFunction;
Asciz	(Lscala/collection/SeqLike;)Lscala/collection/SeqView;;
NameAndType	projection:(Lscala/collection/SeqLike;)Lscala/collection/SeqView;
Method	scala/collection/SeqLike$class.projection:(Lscala/collection/SeqLike;)Lscala/collection/SeqView;
Asciz	equalsWith;
Asciz	(Lscala/collection/Seq;Lscala/Function2;)Z;
Asciz	(Lscala/collection/SeqLike;Lscala/collection/Seq;Lscala/Function2;)Z;
NameAndType	equalsWith:(Lscala/collection/SeqLike;Lscala/collection/Seq;Lscala/Function2;)Z
Method	scala/collection/SeqLike$class.equalsWith:(Lscala/collection/SeqLike;Lscala/collection/Seq;Lscala/Function2;)Z
Asciz	Lscala/collection/Seq;;
Asciz	findLastIndexOf;
Asciz	(Lscala/collection/SeqLike;Lscala/Function1;)I;
NameAndType	findLastIndexOf:(Lscala/collection/SeqLike;Lscala/Function1;)I
Method	scala/collection/SeqLike$class.findLastIndexOf:(Lscala/collection/SeqLike;Lscala/Function1;)I
Asciz	(Lscala/collection/SeqLike;)Ljava/lang/String;;
NameAndType	toString:(Lscala/collection/SeqLike;)Ljava/lang/String;
Method	scala/collection/SeqLike$class.toString:(Lscala/collection/SeqLike;)Ljava/lang/String;
Asciz	equals;
Asciz	(Lscala/collection/SeqLike;Ljava/lang/Object;)Z;
NameAndType	equals:(Lscala/collection/SeqLike;Ljava/lang/Object;)Z
Method	scala/collection/SeqLike$class.equals:(Lscala/collection/SeqLike;Ljava/lang/Object;)Z
Asciz	hashCode;
Asciz	(Lscala/collection/SeqLike;)I;
NameAndType	hashCode:(Lscala/collection/SeqLike;)I
Method	scala/collection/SeqLike$class.hashCode:(Lscala/collection/SeqLike;)I
Asciz	indices;
Asciz	()Lscala/collection/immutable/Range;;
Asciz	(Lscala/collection/SeqLike;)Lscala/collection/immutable/Range;;
NameAndType	indices:(Lscala/collection/SeqLike;)Lscala/collection/immutable/Range;
Method	scala/collection/SeqLike$class.indices:(Lscala/collection/SeqLike;)Lscala/collection/immutable/Range;
Asciz	toSeq;
Asciz	(Lscala/collection/SeqLike;)Lscala/collection/Seq;;
NameAndType	toSeq:(Lscala/collection/SeqLike;)Lscala/collection/Seq;
Method	scala/collection/SeqLike$class.toSeq:(Lscala/collection/SeqLike;)Lscala/collection/Seq;
Asciz	sortBy;
Asciz	(Lscala/Function1;Lscala/math/Ordering;)Ljava/lang/Object;;
Asciz	(Lscala/collection/SeqLike;Lscala/Function1;Lscala/math/Ordering;)Ljava/lang/Object;;
NameAndType	sortBy:(Lscala/collection/SeqLike;Lscala/Function1;Lscala/math/Ordering;)Ljava/lang/Object;
Method	scala/collection/SeqLike$class.sortBy:(Lscala/collection/SeqLike;Lscala/Function1;Lscala/math/Ordering;)Ljava/lang/Object;
Asciz	ord;
Asciz	sortWith;
Asciz	(Lscala/collection/SeqLike;Lscala/math/Ordering;)Ljava/lang/Object;;
NameAndType	sortWith:(Lscala/collection/SeqLike;Lscala/math/Ordering;)Ljava/lang/Object;
Method	scala/collection/SeqLike$class.sortWith:(Lscala/collection/SeqLike;Lscala/math/Ordering;)Ljava/lang/Object;
Asciz	(Lscala/Function2;)Ljava/lang/Object;;
Asciz	(Lscala/collection/SeqLike;Lscala/Function2;)Ljava/lang/Object;;
NameAndType	sortWith:(Lscala/collection/SeqLike;Lscala/Function2;)Ljava/lang/Object;
Method	scala/collection/SeqLike$class.sortWith:(Lscala/collection/SeqLike;Lscala/Function2;)Ljava/lang/Object;
Asciz	lt;
Asciz	corresponds;
NameAndType	corresponds:(Lscala/collection/SeqLike;Lscala/collection/Seq;Lscala/Function2;)Z
Method	scala/collection/SeqLike$class.corresponds:(Lscala/collection/SeqLike;Lscala/collection/Seq;Lscala/Function2;)Z
Asciz	padTo;
Asciz	(ILjava/lang/Object;Lscala/collection/generic/CanBuildFrom;)Ljava/lang/Object;;
Asciz	(Lscala/collection/SeqLike;ILjava/lang/Object;Lscala/collection/generic/CanBuildFrom;)Ljava/lang/Object;;
NameAndType	padTo:(Lscala/collection/SeqLike;ILjava/lang/Object;Lscala/collection/generic/CanBuildFrom;)Ljava/lang/Object;
Method	scala/collection/SeqLike$class.padTo:(Lscala/collection/SeqLike;ILjava/lang/Object;Lscala/collection/generic/CanBuildFrom;)Ljava/lang/Object;
Asciz	$colon$plus;
Asciz	(Ljava/lang/Object;Lscala/collection/generic/CanBuildFrom;)Ljava/lang/Object;;
Asciz	(Lscala/collection/SeqLike;Ljava/lang/Object;Lscala/collection/generic/CanBuildFrom;)Ljava/lang/Object;;
NameAndType	$colon$plus:(Lscala/collection/SeqLike;Ljava/lang/Object;Lscala/collection/generic/CanBuildFrom;)Ljava/lang/Object;
Method	scala/collection/SeqLike$class.$colon$plus:(Lscala/collection/SeqLike;Ljava/lang/Object;Lscala/collection/generic/CanBuildFrom;)Ljava/lang/Object;
Asciz	$plus$colon;
NameAndType	$plus$colon:(Lscala/collection/SeqLike;Ljava/lang/Object;Lscala/collection/generic/CanBuildFrom;)Ljava/lang/Object;
Method	scala/collection/SeqLike$class.$plus$colon:(Lscala/collection/SeqLike;Ljava/lang/Object;Lscala/collection/generic/CanBuildFrom;)Ljava/lang/Object;
Asciz	updated;
NameAndType	updated:(Lscala/collection/SeqLike;ILjava/lang/Object;Lscala/collection/generic/CanBuildFrom;)Ljava/lang/Object;
Method	scala/collection/SeqLike$class.updated:(Lscala/collection/SeqLike;ILjava/lang/Object;Lscala/collection/generic/CanBuildFrom;)Ljava/lang/Object;
Asciz	index;
Asciz	patch;
Asciz	(ILscala/collection/Seq;ILscala/collection/generic/CanBuildFrom;)Ljava/lang/Object;;
Asciz	(Lscala/collection/SeqLike;ILscala/collection/Seq;ILscala/collection/generic/CanBuildFrom;)Ljava/lang/Object;;
NameAndType	patch:(Lscala/collection/SeqLike;ILscala/collection/Seq;ILscala/collection/generic/CanBuildFrom;)Ljava/lang/Object;
Method	scala/collection/SeqLike$class.patch:(Lscala/collection/SeqLike;ILscala/collection/Seq;ILscala/collection/generic/CanBuildFrom;)Ljava/lang/Object;
Asciz	replaced;
Asciz	removeDuplicates;
Asciz	(Lscala/collection/SeqLike;)Ljava/lang/Object;;
NameAndType	removeDuplicates:(Lscala/collection/SeqLike;)Ljava/lang/Object;
Method	scala/collection/SeqLike$class.removeDuplicates:(Lscala/collection/SeqLike;)Ljava/lang/Object;
Asciz	intersect;
Asciz	(Lscala/collection/Seq;)Ljava/lang/Object;;
Asciz	(Lscala/collection/SeqLike;Lscala/collection/Seq;)Ljava/lang/Object;;
NameAndType	intersect:(Lscala/collection/SeqLike;Lscala/collection/Seq;)Ljava/lang/Object;
Method	scala/collection/SeqLike$class.intersect:(Lscala/collection/SeqLike;Lscala/collection/Seq;)Ljava/lang/Object;
Asciz	diff;
NameAndType	diff:(Lscala/collection/SeqLike;Lscala/collection/Seq;)Ljava/lang/Object;
Method	scala/collection/SeqLike$class.diff:(Lscala/collection/SeqLike;Lscala/collection/Seq;)Ljava/lang/Object;
Asciz	union;
Asciz	(Lscala/collection/Seq;Lscala/collection/generic/CanBuildFrom;)Ljava/lang/Object;;
Asciz	(Lscala/collection/SeqLike;Lscala/collection/Seq;Lscala/collection/generic/CanBuildFrom;)Ljava/lang/Object;;
NameAndType	union:(Lscala/collection/SeqLike;Lscala/collection/Seq;Lscala/collection/generic/CanBuildFrom;)Ljava/lang/Object;
Method	scala/collection/SeqLike$class.union:(Lscala/collection/SeqLike;Lscala/collection/Seq;Lscala/collection/generic/CanBuildFrom;)Ljava/lang/Object;
Asciz	contains;
NameAndType	contains:(Lscala/collection/SeqLike;Ljava/lang/Object;)Z
Method	scala/collection/SeqLike$class.contains:(Lscala/collection/SeqLike;Ljava/lang/Object;)Z
Asciz	containsSlice;
Asciz	(Lscala/collection/Seq;)Z;
Asciz	(Lscala/collection/SeqLike;Lscala/collection/Seq;)Z;
NameAndType	containsSlice:(Lscala/collection/SeqLike;Lscala/collection/Seq;)Z
Method	scala/collection/SeqLike$class.containsSlice:(Lscala/collection/SeqLike;Lscala/collection/Seq;)Z
Asciz	lastIndexOfSlice;
Asciz	(Lscala/collection/Seq;I)I;
Asciz	(Lscala/collection/SeqLike;Lscala/collection/Seq;I)I;
NameAndType	lastIndexOfSlice:(Lscala/collection/SeqLike;Lscala/collection/Seq;I)I
Method	scala/collection/SeqLike$class.lastIndexOfSlice:(Lscala/collection/SeqLike;Lscala/collection/Seq;I)I
Asciz	(Lscala/collection/Seq;)I;
Asciz	(Lscala/collection/SeqLike;Lscala/collection/Seq;)I;
NameAndType	lastIndexOfSlice:(Lscala/collection/SeqLike;Lscala/collection/Seq;)I
Method	scala/collection/SeqLike$class.lastIndexOfSlice:(Lscala/collection/SeqLike;Lscala/collection/Seq;)I
Asciz	indexOfSlice;
NameAndType	indexOfSlice:(Lscala/collection/SeqLike;Lscala/collection/Seq;I)I
Method	scala/collection/SeqLike$class.indexOfSlice:(Lscala/collection/SeqLike;Lscala/collection/Seq;I)I
NameAndType	indexOfSlice:(Lscala/collection/SeqLike;Lscala/collection/Seq;)I
Method	scala/collection/SeqLike$class.indexOfSlice:(Lscala/collection/SeqLike;Lscala/collection/Seq;)I
Asciz	startsWith;
NameAndType	startsWith:(Lscala/collection/SeqLike;Lscala/collection/Seq;)Z
Method	scala/collection/SeqLike$class.startsWith:(Lscala/collection/SeqLike;Lscala/collection/Seq;)Z
Asciz	reversedElements;
Asciz	(Lscala/collection/SeqLike;)Lscala/collection/Iterator;;
NameAndType	reversedElements:(Lscala/collection/SeqLike;)Lscala/collection/Iterator;
Method	scala/collection/SeqLike$class.reversedElements:(Lscala/collection/SeqLike;)Lscala/collection/Iterator;
Asciz	reverseMap;
Asciz	(Lscala/collection/SeqLike;Lscala/Function1;Lscala/collection/generic/CanBuildFrom;)Ljava/lang/Object;;
NameAndType	reverseMap:(Lscala/collection/SeqLike;Lscala/Function1;Lscala/collection/generic/CanBuildFrom;)Ljava/lang/Object;
Method	scala/collection/SeqLike$class.reverseMap:(Lscala/collection/SeqLike;Lscala/Function1;Lscala/collection/generic/CanBuildFrom;)Ljava/lang/Object;
Asciz	lastIndexWhere;
NameAndType	lastIndexWhere:(Lscala/collection/SeqLike;Lscala/Function1;)I
Method	scala/collection/SeqLike$class.lastIndexWhere:(Lscala/collection/SeqLike;Lscala/Function1;)I
Asciz	lastIndexOf;
Asciz	(Ljava/lang/Object;I)I;
Asciz	(Lscala/collection/SeqLike;Ljava/lang/Object;I)I;
NameAndType	lastIndexOf:(Lscala/collection/SeqLike;Ljava/lang/Object;I)I
Method	scala/collection/SeqLike$class.lastIndexOf:(Lscala/collection/SeqLike;Ljava/lang/Object;I)I
Asciz	(Lscala/collection/SeqLike;Ljava/lang/Object;)I;
NameAndType	lastIndexOf:(Lscala/collection/SeqLike;Ljava/lang/Object;)I
Method	scala/collection/SeqLike$class.lastIndexOf:(Lscala/collection/SeqLike;Ljava/lang/Object;)I
Asciz	indexOf;
NameAndType	indexOf:(Lscala/collection/SeqLike;Ljava/lang/Object;I)I
Method	scala/collection/SeqLike$class.indexOf:(Lscala/collection/SeqLike;Ljava/lang/Object;I)I
NameAndType	indexOf:(Lscala/collection/SeqLike;Ljava/lang/Object;)I
Method	scala/collection/SeqLike$class.indexOf:(Lscala/collection/SeqLike;Ljava/lang/Object;)I
Asciz	findIndexOf;
NameAndType	findIndexOf:(Lscala/collection/SeqLike;Lscala/Function1;)I
Method	scala/collection/SeqLike$class.findIndexOf:(Lscala/collection/SeqLike;Lscala/Function1;)I
Asciz	indexWhere;
NameAndType	indexWhere:(Lscala/collection/SeqLike;Lscala/Function1;)I
Method	scala/collection/SeqLike$class.indexWhere:(Lscala/collection/SeqLike;Lscala/Function1;)I
Asciz	prefixLength;
NameAndType	prefixLength:(Lscala/collection/SeqLike;Lscala/Function1;)I
Method	scala/collection/SeqLike$class.prefixLength:(Lscala/collection/SeqLike;Lscala/Function1;)I
Asciz	(Lscala/collection/SeqLike;I)Z;
NameAndType	isDefinedAt:(Lscala/collection/SeqLike;I)Z
Method	scala/collection/SeqLike$class.isDefinedAt:(Lscala/collection/SeqLike;I)Z
Asciz	size;
NameAndType	size:(Lscala/collection/SeqLike;)I
Method	scala/collection/SeqLike$class.size:(Lscala/collection/SeqLike;)I
Asciz	endsWith;
Asciz	(Lscala/collection/IndexedSeqLike;Lscala/collection/Seq;)Z;
NameAndType	endsWith:(Lscala/collection/IndexedSeqLike;Lscala/collection/Seq;)Z
Method	scala/collection/IndexedSeqLike$class.endsWith:(Lscala/collection/IndexedSeqLike;Lscala/collection/Seq;)Z
Asciz	(Lscala/collection/Seq;I)Z;
Asciz	(Lscala/collection/IndexedSeqLike;Lscala/collection/Seq;I)Z;
NameAndType	startsWith:(Lscala/collection/IndexedSeqLike;Lscala/collection/Seq;I)Z
Method	scala/collection/IndexedSeqLike$class.startsWith:(Lscala/collection/IndexedSeqLike;Lscala/collection/Seq;I)Z
Asciz	offset;
Asciz	reverseIterator;
Asciz	(Lscala/collection/IndexedSeqLike;)Lscala/collection/Iterator;;
NameAndType	reverseIterator:(Lscala/collection/IndexedSeqLike;)Lscala/collection/Iterator;
Method	scala/collection/IndexedSeqLike$class.reverseIterator:(Lscala/collection/IndexedSeqLike;)Lscala/collection/Iterator;
Asciz	reverse;
Asciz	(Lscala/collection/IndexedSeqLike;)Ljava/lang/Object;;
NameAndType	reverse:(Lscala/collection/IndexedSeqLike;)Ljava/lang/Object;
Method	scala/collection/IndexedSeqLike$class.reverse:(Lscala/collection/IndexedSeqLike;)Ljava/lang/Object;
Asciz	(Lscala/Function1;I)I;
Asciz	(Lscala/collection/IndexedSeqLike;Lscala/Function1;I)I;
NameAndType	lastIndexWhere:(Lscala/collection/IndexedSeqLike;Lscala/Function1;I)I
Method	scala/collection/IndexedSeqLike$class.lastIndexWhere:(Lscala/collection/IndexedSeqLike;Lscala/Function1;I)I
NameAndType	indexWhere:(Lscala/collection/IndexedSeqLike;Lscala/Function1;I)I
Method	scala/collection/IndexedSeqLike$class.indexWhere:(Lscala/collection/IndexedSeqLike;Lscala/Function1;I)I
Asciz	segmentLength;
NameAndType	segmentLength:(Lscala/collection/IndexedSeqLike;Lscala/Function1;I)I
Method	scala/collection/IndexedSeqLike$class.segmentLength:(Lscala/collection/IndexedSeqLike;Lscala/Function1;I)I
Asciz	lengthCompare;
Asciz	(Lscala/collection/IndexedSeqLike;I)I;
NameAndType	lengthCompare:(Lscala/collection/IndexedSeqLike;I)I
Method	scala/collection/IndexedSeqLike$class.lengthCompare:(Lscala/collection/IndexedSeqLike;I)I
Asciz	sameElements;
Asciz	(Lscala/collection/Iterable;)Z;
Asciz	(Lscala/collection/IndexedSeqLike;Lscala/collection/Iterable;)Z;
NameAndType	sameElements:(Lscala/collection/IndexedSeqLike;Lscala/collection/Iterable;)Z
Method	scala/collection/IndexedSeqLike$class.sameElements:(Lscala/collection/IndexedSeqLike;Lscala/collection/Iterable;)Z
Asciz	span;
Asciz	(Lscala/collection/IndexedSeqLike;Lscala/Function1;)Lscala/Tuple2;;
NameAndType	span:(Lscala/collection/IndexedSeqLike;Lscala/Function1;)Lscala/Tuple2;
Method	scala/collection/IndexedSeqLike$class.span:(Lscala/collection/IndexedSeqLike;Lscala/Function1;)Lscala/Tuple2;
Asciz	dropWhile;
Asciz	(Lscala/collection/IndexedSeqLike;Lscala/Function1;)Ljava/lang/Object;;
NameAndType	dropWhile:(Lscala/collection/IndexedSeqLike;Lscala/Function1;)Ljava/lang/Object;
Method	scala/collection/IndexedSeqLike$class.dropWhile:(Lscala/collection/IndexedSeqLike;Lscala/Function1;)Ljava/lang/Object;
Asciz	takeWhile;
NameAndType	takeWhile:(Lscala/collection/IndexedSeqLike;Lscala/Function1;)Ljava/lang/Object;
Method	scala/collection/IndexedSeqLike$class.takeWhile:(Lscala/collection/IndexedSeqLike;Lscala/Function1;)Ljava/lang/Object;
Asciz	splitAt;
Asciz	(I)Lscala/Tuple2;;
Asciz	(Lscala/collection/IndexedSeqLike;I)Lscala/Tuple2;;
NameAndType	splitAt:(Lscala/collection/IndexedSeqLike;I)Lscala/Tuple2;
Method	scala/collection/IndexedSeqLike$class.splitAt:(Lscala/collection/IndexedSeqLike;I)Lscala/Tuple2;
Asciz	n;
Asciz	dropRight;
Asciz	(Lscala/collection/IndexedSeqLike;I)Ljava/lang/Object;;
NameAndType	dropRight:(Lscala/collection/IndexedSeqLike;I)Ljava/lang/Object;
Method	scala/collection/IndexedSeqLike$class.dropRight:(Lscala/collection/IndexedSeqLike;I)Ljava/lang/Object;
Asciz	takeRight;
NameAndType	takeRight:(Lscala/collection/IndexedSeqLike;I)Ljava/lang/Object;
Method	scala/collection/IndexedSeqLike$class.takeRight:(Lscala/collection/IndexedSeqLike;I)Ljava/lang/Object;
Asciz	drop;
NameAndType	drop:(Lscala/collection/IndexedSeqLike;I)Ljava/lang/Object;
Method	scala/collection/IndexedSeqLike$class.drop:(Lscala/collection/IndexedSeqLike;I)Ljava/lang/Object;
Asciz	take;
NameAndType	take:(Lscala/collection/IndexedSeqLike;I)Ljava/lang/Object;
Method	scala/collection/IndexedSeqLike$class.take:(Lscala/collection/IndexedSeqLike;I)Ljava/lang/Object;
Asciz	init;
NameAndType	init:(Lscala/collection/IndexedSeqLike;)Ljava/lang/Object;
Method	scala/collection/IndexedSeqLike$class.init:(Lscala/collection/IndexedSeqLike;)Ljava/lang/Object;
Asciz	last;
NameAndType	last:(Lscala/collection/IndexedSeqLike;)Ljava/lang/Object;
Method	scala/collection/IndexedSeqLike$class.last:(Lscala/collection/IndexedSeqLike;)Ljava/lang/Object;
Asciz	tail;
NameAndType	tail:(Lscala/collection/IndexedSeqLike;)Ljava/lang/Object;
Method	scala/collection/IndexedSeqLike$class.tail:(Lscala/collection/IndexedSeqLike;)Ljava/lang/Object;
Asciz	head;
NameAndType	head:(Lscala/collection/IndexedSeqLike;)Ljava/lang/Object;
Method	scala/collection/IndexedSeqLike$class.head:(Lscala/collection/IndexedSeqLike;)Ljava/lang/Object;
Asciz	slice;
Asciz	(II)Ljava/lang/Object;;
Asciz	(Lscala/collection/IndexedSeqLike;II)Ljava/lang/Object;;
NameAndType	slice:(Lscala/collection/IndexedSeqLike;II)Ljava/lang/Object;
Method	scala/collection/IndexedSeqLike$class.slice:(Lscala/collection/IndexedSeqLike;II)Ljava/lang/Object;
Asciz	zipWithIndex;
Asciz	(Lscala/collection/generic/CanBuildFrom;)Ljava/lang/Object;;
Asciz	(Lscala/collection/IndexedSeqLike;Lscala/collection/generic/CanBuildFrom;)Ljava/lang/Object;;
NameAndType	zipWithIndex:(Lscala/collection/IndexedSeqLike;Lscala/collection/generic/CanBuildFrom;)Ljava/lang/Object;
Method	scala/collection/IndexedSeqLike$class.zipWithIndex:(Lscala/collection/IndexedSeqLike;Lscala/collection/generic/CanBuildFrom;)Ljava/lang/Object;
Asciz	zip;
Asciz	(Lscala/collection/Iterable;Lscala/collection/generic/CanBuildFrom;)Ljava/lang/Object;;
Asciz	(Lscala/collection/IndexedSeqLike;Lscala/collection/Iterable;Lscala/collection/generic/CanBuildFrom;)Ljava/lang/Object;;
NameAndType	zip:(Lscala/collection/IndexedSeqLike;Lscala/collection/Iterable;Lscala/collection/generic/CanBuildFrom;)Ljava/lang/Object;
Method	scala/collection/IndexedSeqLike$class.zip:(Lscala/collection/IndexedSeqLike;Lscala/collection/Iterable;Lscala/collection/generic/CanBuildFrom;)Ljava/lang/Object;
Asciz	reduceRight;
Asciz	(Lscala/collection/IndexedSeqLike;Lscala/Function2;)Ljava/lang/Object;;
NameAndType	reduceRight:(Lscala/collection/IndexedSeqLike;Lscala/Function2;)Ljava/lang/Object;
Method	scala/collection/IndexedSeqLike$class.reduceRight:(Lscala/collection/IndexedSeqLike;Lscala/Function2;)Ljava/lang/Object;
Asciz	reduceLeft;
NameAndType	reduceLeft:(Lscala/collection/IndexedSeqLike;Lscala/Function2;)Ljava/lang/Object;
Method	scala/collection/IndexedSeqLike$class.reduceLeft:(Lscala/collection/IndexedSeqLike;Lscala/Function2;)Ljava/lang/Object;
Asciz	foldRight;
Asciz	(Lscala/collection/IndexedSeqLike;Ljava/lang/Object;Lscala/Function2;)Ljava/lang/Object;;
NameAndType	foldRight:(Lscala/collection/IndexedSeqLike;Ljava/lang/Object;Lscala/Function2;)Ljava/lang/Object;
Method	scala/collection/IndexedSeqLike$class.foldRight:(Lscala/collection/IndexedSeqLike;Ljava/lang/Object;Lscala/Function2;)Ljava/lang/Object;
Asciz	foldLeft;
NameAndType	foldLeft:(Lscala/collection/IndexedSeqLike;Ljava/lang/Object;Lscala/Function2;)Ljava/lang/Object;
Method	scala/collection/IndexedSeqLike$class.foldLeft:(Lscala/collection/IndexedSeqLike;Ljava/lang/Object;Lscala/Function2;)Ljava/lang/Object;
Asciz	find;
Asciz	(Lscala/Function1;)Lscala/Option;;
Asciz	(Lscala/collection/IndexedSeqLike;Lscala/Function1;)Lscala/Option;;
NameAndType	find:(Lscala/collection/IndexedSeqLike;Lscala/Function1;)Lscala/Option;
Method	scala/collection/IndexedSeqLike$class.find:(Lscala/collection/IndexedSeqLike;Lscala/Function1;)Lscala/Option;
Asciz	exists;
Asciz	(Lscala/Function1;)Z;
Asciz	(Lscala/collection/IndexedSeqLike;Lscala/Function1;)Z;
NameAndType	exists:(Lscala/collection/IndexedSeqLike;Lscala/Function1;)Z
Method	scala/collection/IndexedSeqLike$class.exists:(Lscala/collection/IndexedSeqLike;Lscala/Function1;)Z
Asciz	forall;
NameAndType	forall:(Lscala/collection/IndexedSeqLike;Lscala/Function1;)Z
Method	scala/collection/IndexedSeqLike$class.forall:(Lscala/collection/IndexedSeqLike;Lscala/Function1;)Z
Asciz	isEmpty;
Asciz	(Lscala/collection/IndexedSeqLike;)Z;
NameAndType	isEmpty:(Lscala/collection/IndexedSeqLike;)Z
Method	scala/collection/IndexedSeqLike$class.isEmpty:(Lscala/collection/IndexedSeqLike;)Z
Asciz	iterator;
NameAndType	iterator:(Lscala/collection/IndexedSeqLike;)Lscala/collection/Iterator;
Method	scala/collection/IndexedSeqLike$class.iterator:(Lscala/collection/IndexedSeqLike;)Lscala/collection/Iterator;
Asciz	scala$collection$IndexedSeqLike$$super$endsWith;
NameAndType	endsWith:(Lscala/collection/SeqLike;Lscala/collection/Seq;)Z
Method	scala/collection/SeqLike$class.endsWith:(Lscala/collection/SeqLike;Lscala/collection/Seq;)Z
Asciz	scala$collection$IndexedSeqLike$$super$sameElements;
Asciz	(Lscala/collection/IterableLike;Lscala/collection/Iterable;)Z;
NameAndType	sameElements:(Lscala/collection/IterableLike;Lscala/collection/Iterable;)Z
Method	scala/collection/IterableLike$class.sameElements:(Lscala/collection/IterableLike;Lscala/collection/Iterable;)Z
Asciz	scala$collection$IndexedSeqLike$$super$init;
NameAndType	init:(Lscala/collection/TraversableLike;)Ljava/lang/Object;
Method	scala/collection/TraversableLike$class.init:(Lscala/collection/TraversableLike;)Ljava/lang/Object;
Asciz	scala$collection$IndexedSeqLike$$super$last;
NameAndType	last:(Lscala/collection/TraversableLike;)Ljava/lang/Object;
Method	scala/collection/TraversableLike$class.last:(Lscala/collection/TraversableLike;)Ljava/lang/Object;
Asciz	scala$collection$IndexedSeqLike$$super$tail;
NameAndType	tail:(Lscala/collection/TraversableLike;)Ljava/lang/Object;
Method	scala/collection/TraversableLike$class.tail:(Lscala/collection/TraversableLike;)Ljava/lang/Object;
Asciz	scala$collection$IndexedSeqLike$$super$head;
NameAndType	head:(Lscala/collection/IterableLike;)Ljava/lang/Object;
Method	scala/collection/IterableLike$class.head:(Lscala/collection/IterableLike;)Ljava/lang/Object;
Asciz	scala$collection$IndexedSeqLike$$super$zip;
Asciz	(Lscala/collection/IterableLike;Lscala/collection/Iterable;Lscala/collection/generic/CanBuildFrom;)Ljava/lang/Object;;
NameAndType	zip:(Lscala/collection/IterableLike;Lscala/collection/Iterable;Lscala/collection/generic/CanBuildFrom;)Ljava/lang/Object;
Method	scala/collection/IterableLike$class.zip:(Lscala/collection/IterableLike;Lscala/collection/Iterable;Lscala/collection/generic/CanBuildFrom;)Ljava/lang/Object;
Asciz	scala$collection$IndexedSeqLike$$super$reduceRight;
Asciz	(Lscala/collection/IterableLike;Lscala/Function2;)Ljava/lang/Object;;
NameAndType	reduceRight:(Lscala/collection/IterableLike;Lscala/Function2;)Ljava/lang/Object;
Method	scala/collection/IterableLike$class.reduceRight:(Lscala/collection/IterableLike;Lscala/Function2;)Ljava/lang/Object;
Asciz	scala$collection$IndexedSeqLike$$super$reduceLeft;
Asciz	(Lscala/collection/TraversableLike;Lscala/Function2;)Ljava/lang/Object;;
NameAndType	reduceLeft:(Lscala/collection/TraversableLike;Lscala/Function2;)Ljava/lang/Object;
Method	scala/collection/TraversableLike$class.reduceLeft:(Lscala/collection/TraversableLike;Lscala/Function2;)Ljava/lang/Object;
Asciz	(Lscala/collection/mutable/IndexedSeqLike;II)Lscala/collection/mutable/IndexedSeqView;;
NameAndType	view:(Lscala/collection/mutable/IndexedSeqLike;II)Lscala/collection/mutable/IndexedSeqView;
Method	scala/collection/mutable/IndexedSeqLike$class.view:(Lscala/collection/mutable/IndexedSeqLike;II)Lscala/collection/mutable/IndexedSeqView;
Asciz	(Lscala/collection/mutable/IndexedSeqLike;)Lscala/collection/mutable/IndexedSeqView;;
NameAndType	view:(Lscala/collection/mutable/IndexedSeqLike;)Lscala/collection/mutable/IndexedSeqView;
Method	scala/collection/mutable/IndexedSeqLike$class.view:(Lscala/collection/mutable/IndexedSeqLike;)Lscala/collection/mutable/IndexedSeqView;
Asciz	(Lscala/collection/mutable/IndexedSeqLike;Ljava/lang/Object;)Lscala/collection/mutable/IndexedSeq;;
NameAndType	toCollection:(Lscala/collection/mutable/IndexedSeqLike;Ljava/lang/Object;)Lscala/collection/mutable/IndexedSeq;
Method	scala/collection/mutable/IndexedSeqLike$class.toCollection:(Lscala/collection/mutable/IndexedSeqLike;Ljava/lang/Object;)Lscala/collection/mutable/IndexedSeq;
Asciz	(Lscala/collection/mutable/IndexedSeqLike;)Lscala/collection/mutable/IndexedSeq;;
NameAndType	thisCollection:(Lscala/collection/mutable/IndexedSeqLike;)Lscala/collection/mutable/IndexedSeq;
Method	scala/collection/mutable/IndexedSeqLike$class.thisCollection:(Lscala/collection/mutable/IndexedSeqLike;)Lscala/collection/mutable/IndexedSeq;
Asciz	<A:Ljava/lang/Object;>Ljava/lang/Object;Lscala/collection/mutable/IndexedSeq<TA;>;Lscala/collection/generic/GenericTraversableTemplate<TA;Lscala/collection/mutable/GenericArray;>;Lscala/collection/mutable/IndexedSeqLike<TA;Lscala/collection/mutable/GenericArray<TA;>;>;Lscala/ScalaObject;;
Asciz	ScalaSig;
Asciz	InnerClasses;
Asciz	scala/Predef$$less$colon$less;
class	scala/Predef$$less$colon$less
Asciz	scala/Predef;
class	scala/Predef
Asciz	$less$colon$less;
Asciz	scala/collection/TraversableLike$WithFilter;
class	scala/collection/TraversableLike$WithFilter
Asciz	scala/collection/TraversableLike;
class	scala/collection/TraversableLike
Asciz	WithFilter;
Asciz	scala/collection/mutable/GenericArray$$anonfun$newBuilder$1;
class	scala/collection/mutable/GenericArray$$anonfun$newBuilder$1
Asciz	$anonfun$newBuilder$1;
Asciz	scala/collection/mutable/IndexedSeq;
class	scala/collection/mutable/IndexedSeq
Asciz	scala/collection/generic/GenericTraversableTemplate;
class	scala/collection/generic/GenericTraversableTemplate
Asciz	scala/ScalaObject;
class	scala/ScalaObject

{
private final java.lang.Object[] array;
  Signature: [Ljava/lang/Object;

private final int length;
  Signature: I

public static final scala.collection.generic.CanBuildFrom canBuildFrom();
  Signature: ()Lscala/collection/generic/CanBuildFrom;
  Code:
   Stack=1, Locals=0, Args_size=0
	getstatic	Field scala/collection/mutable/GenericArray$.MODULE$:Lscala/collection/mutable/GenericArray$;
	invokevirtual	Method scala/collection/mutable/GenericArray$.canBuildFrom:()Lscala/collection/generic/CanBuildFrom;
	areturn
  Labels:
  Signature: length = 0x2
   00 0E 

public static final scala.Some unapplySeq(scala.collection.Seq);
  Signature: (Lscala/collection/Seq;)Lscala/Some;
  Code:
   Stack=2, Locals=1, Args_size=1
	getstatic	Field scala/collection/mutable/GenericArray$.MODULE$:Lscala/collection/mutable/GenericArray$;
	aload_0
	invokevirtual	Method scala/collection/mutable/GenericArray$.unapplySeq:(Lscala/collection/Seq;)Lscala/Some;
	areturn
  Labels:
  Signature: length = 0x2
   00 14 

public static final scala.collection.Traversable iterate(java.lang.Object, int, scala.Function1);
  Signature: (Ljava/lang/Object;ILscala/Function1;)Lscala/collection/Traversable;
  Code:
   Stack=4, Locals=3, Args_size=3
	getstatic	Field scala/collection/mutable/GenericArray$.MODULE$:Lscala/collection/mutable/GenericArray$;
	aload_0
	iload_1
	aload_2
	invokevirtual	Method scala/collection/mutable/GenericArray$.iterate:(Ljava/lang/Object;ILscala/Function1;)Lscala/collection/Traversable;
	areturn
  Labels:
  Signature: length = 0x2
   00 19 

public static final scala.collection.Traversable range(int, int, int);
  Signature: (III)Lscala/collection/Traversable;
  Code:
   Stack=4, Locals=3, Args_size=3
	getstatic	Field scala/collection/mutable/GenericArray$.MODULE$:Lscala/collection/mutable/GenericArray$;
	iload_0
	iload_1
	iload_2
	invokevirtual	Method scala/collection/mutable/GenericArray$.range:(III)Lscala/collection/Traversable;
	areturn
  Labels:
  Signature: length = 0x2
   00 1E 

public static final scala.collection.Traversable range(int, int);
  Signature: (II)Lscala/collection/Traversable;
  Code:
   Stack=3, Locals=2, Args_size=2
	getstatic	Field scala/collection/mutable/GenericArray$.MODULE$:Lscala/collection/mutable/GenericArray$;
	iload_0
	iload_1
	invokevirtual	Method scala/collection/mutable/GenericArray$.range:(II)Lscala/collection/Traversable;
	areturn
  Labels:
  Signature: length = 0x2
   00 22 

public static final scala.collection.Traversable tabulate(int, int, int, int, int, scala.Function5);
  Signature: (IIIIILscala/Function5;)Lscala/collection/Traversable;
  Code:
   Stack=7, Locals=6, Args_size=6
	getstatic	Field scala/collection/mutable/GenericArray$.MODULE$:Lscala/collection/mutable/GenericArray$;
	iload_0
	iload_1
	iload_2
	iload_3
	iload	4
	aload	5
	invokevirtual	Method scala/collection/mutable/GenericArray$.tabulate:(IIIIILscala/Function5;)Lscala/collection/Traversable;
	areturn
  Labels:
  Signature: length = 0x2
   00 27 

public static final scala.collection.Traversable tabulate(int, int, int, int, scala.Function4);
  Signature: (IIIILscala/Function4;)Lscala/collection/Traversable;
  Code:
   Stack=6, Locals=5, Args_size=5
	getstatic	Field scala/collection/mutable/GenericArray$.MODULE$:Lscala/collection/mutable/GenericArray$;
	iload_0
	iload_1
	iload_2
	iload_3
	aload	4
	invokevirtual	Method scala/collection/mutable/GenericArray$.tabulate:(IIIILscala/Function4;)Lscala/collection/Traversable;
	areturn
  Labels:
  Signature: length = 0x2
   00 2B 

public static final scala.collection.Traversable tabulate(int, int, int, scala.Function3);
  Signature: (IIILscala/Function3;)Lscala/collection/Traversable;
  Code:
   Stack=5, Locals=4, Args_size=4
	getstatic	Field scala/collection/mutable/GenericArray$.MODULE$:Lscala/collection/mutable/GenericArray$;
	iload_0
	iload_1
	iload_2
	aload_3
	invokevirtual	Method scala/collection/mutable/GenericArray$.tabulate:(IIILscala/Function3;)Lscala/collection/Traversable;
	areturn
  Labels:
  Signature: length = 0x2
   00 2F 

public static final scala.collection.Traversable tabulate(int, int, scala.Function2);
  Signature: (IILscala/Function2;)Lscala/collection/Traversable;
  Code:
   Stack=4, Locals=3, Args_size=3
	getstatic	Field scala/collection/mutable/GenericArray$.MODULE$:Lscala/collection/mutable/GenericArray$;
	iload_0
	iload_1
	aload_2
	invokevirtual	Method scala/collection/mutable/GenericArray$.tabulate:(IILscala/Function2;)Lscala/collection/Traversable;
	areturn
  Labels:
  Signature: length = 0x2
   00 33 

public static final scala.collection.Traversable tabulate(int, scala.Function1);
  Signature: (ILscala/Function1;)Lscala/collection/Traversable;
  Code:
   Stack=3, Locals=2, Args_size=2
	getstatic	Field scala/collection/mutable/GenericArray$.MODULE$:Lscala/collection/mutable/GenericArray$;
	iload_0
	aload_1
	invokevirtual	Method scala/collection/mutable/GenericArray$.tabulate:(ILscala/Function1;)Lscala/collection/Traversable;
	areturn
  Labels:
  Signature: length = 0x2
   00 37 

public static final scala.collection.Traversable fill(int, int, int, int, int, scala.Function0);
  Signature: (IIIIILscala/Function0;)Lscala/collection/Traversable;
  Code:
   Stack=7, Locals=6, Args_size=6
	getstatic	Field scala/collection/mutable/GenericArray$.MODULE$:Lscala/collection/mutable/GenericArray$;
	iload_0
	iload_1
	iload_2
	iload_3
	iload	4
	aload	5
	invokevirtual	Method scala/collection/mutable/GenericArray$.fill:(IIIIILscala/Function0;)Lscala/collection/Traversable;
	areturn
  Labels:
  Signature: length = 0x2
   00 3C 

public static final scala.collection.Traversable fill(int, int, int, int, scala.Function0);
  Signature: (IIIILscala/Function0;)Lscala/collection/Traversable;
  Code:
   Stack=6, Locals=5, Args_size=5
	getstatic	Field scala/collection/mutable/GenericArray$.MODULE$:Lscala/collection/mutable/GenericArray$;
	iload_0
	iload_1
	iload_2
	iload_3
	aload	4
	invokevirtual	Method scala/collection/mutable/GenericArray$.fill:(IIIILscala/Function0;)Lscala/collection/Traversable;
	areturn
  Labels:
  Signature: length = 0x2
   00 40 

public static final scala.collection.Traversable fill(int, int, int, scala.Function0);
  Signature: (IIILscala/Function0;)Lscala/collection/Traversable;
  Code:
   Stack=5, Locals=4, Args_size=4
	getstatic	Field scala/collection/mutable/GenericArray$.MODULE$:Lscala/collection/mutable/GenericArray$;
	iload_0
	iload_1
	iload_2
	aload_3
	invokevirtual	Method scala/collection/mutable/GenericArray$.fill:(IIILscala/Function0;)Lscala/collection/Traversable;
	areturn
  Labels:
  Signature: length = 0x2
   00 44 

public static final scala.collection.Traversable fill(int, int, scala.Function0);
  Signature: (IILscala/Function0;)Lscala/collection/Traversable;
  Code:
   Stack=4, Locals=3, Args_size=3
	getstatic	Field scala/collection/mutable/GenericArray$.MODULE$:Lscala/collection/mutable/GenericArray$;
	iload_0
	iload_1
	aload_2
	invokevirtual	Method scala/collection/mutable/GenericArray$.fill:(IILscala/Function0;)Lscala/collection/Traversable;
	areturn
  Labels:
  Signature: length = 0x2
   00 48 

public static final scala.collection.Traversable fill(int, scala.Function0);
  Signature: (ILscala/Function0;)Lscala/collection/Traversable;
  Code:
   Stack=3, Locals=2, Args_size=2
	getstatic	Field scala/collection/mutable/GenericArray$.MODULE$:Lscala/collection/mutable/GenericArray$;
	iload_0
	aload_1
	invokevirtual	Method scala/collection/mutable/GenericArray$.fill:(ILscala/Function0;)Lscala/collection/Traversable;
	areturn
  Labels:
  Signature: length = 0x2
   00 4C 

public static final scala.collection.Traversable concat(scala.collection.Seq);
  Signature: (Lscala/collection/Seq;)Lscala/collection/Traversable;
  Code:
   Stack=2, Locals=1, Args_size=1
	getstatic	Field scala/collection/mutable/GenericArray$.MODULE$:Lscala/collection/mutable/GenericArray$;
	aload_0
	invokevirtual	Method scala/collection/mutable/GenericArray$.concat:(Lscala/collection/Seq;)Lscala/collection/Traversable;
	areturn
  Labels:
  Signature: length = 0x2
   00 51 

public static final scala.collection.Traversable empty();
  Signature: ()Lscala/collection/Traversable;
  Code:
   Stack=1, Locals=0, Args_size=0
	getstatic	Field scala/collection/mutable/GenericArray$.MODULE$:Lscala/collection/mutable/GenericArray$;
	invokevirtual	Method scala/collection/mutable/GenericArray$.empty:()Lscala/collection/Traversable;
	areturn
  Labels:
  Signature: length = 0x2
   00 56 

public scala.collection.mutable.GenericArray(int);
  Signature: (I)V
  Code:
   Stack=2, Locals=2, Args_size=2
	aload_0
	iload_1
	putfield	Field length:I
	aload_0
	invokespecial	Method java/lang/Object."<init>":()V
	aload_0
	invokestatic	Method scala/collection/TraversableLike$class.$init$:(Lscala/collection/TraversableLike;)V
	aload_0
	invokestatic	Method scala/collection/generic/GenericTraversableTemplate$class.$init$:(Lscala/collection/generic/GenericTraversableTemplate;)V
	aload_0
	invokestatic	Method scala/collection/Traversable$class.$init$:(Lscala/collection/Traversable;)V
	aload_0
	invokestatic	Method scala/collection/mutable/Traversable$class.$init$:(Lscala/collection/mutable/Traversable;)V
	aload_0
	invokestatic	Method scala/collection/IterableLike$class.$init$:(Lscala/collection/IterableLike;)V
	aload_0
	invokestatic	Method scala/collection/Iterable$class.$init$:(Lscala/collection/Iterable;)V
	aload_0
	invokestatic	Method scala/collection/mutable/Iterable$class.$init$:(Lscala/collection/mutable/Iterable;)V
	aload_0
	invokestatic	Method scala/Function1$class.$init$:(Lscala/Function1;)V
	aload_0
	invokestatic	Method scala/PartialFunction$class.$init$:(Lscala/PartialFunction;)V
	aload_0
	invokestatic	Method scala/collection/SeqLike$class.$init$:(Lscala/collection/SeqLike;)V
	aload_0
	invokestatic	Method scala/collection/Seq$class.$init$:(Lscala/collection/Seq;)V
	aload_0
	invokestatic	Method scala/collection/mutable/Seq$class.$init$:(Lscala/collection/mutable/Seq;)V
	aload_0
	invokestatic	Method scala/collection/IndexedSeqLike$class.$init$:(Lscala/collection/IndexedSeqLike;)V
	aload_0
	invokestatic	Method scala/collection/IndexedSeq$class.$init$:(Lscala/collection/IndexedSeq;)V
	aload_0
	invokestatic	Method scala/collection/mutable/IndexedSeqLike$class.$init$:(Lscala/collection/mutable/IndexedSeqLike;)V
	aload_0
	invokestatic	Method scala/collection/mutable/IndexedSeq$class.$init$:(Lscala/collection/mutable/IndexedSeq;)V
	aload_0
	iload_1
	anewarray	class java/lang/Object
	putfield	Field array:[Ljava/lang/Object;
	return
  Labels:
  LocalVariableTable: 
   Start  Length  Slot  Name   Signature
   0      82      0    this       Lscala/collection/mutable/GenericArray;
   0      82      1    length       I

  Signature: length = 0x2
   00 5C 

public java.lang.Object apply(java.lang.Object);
  Signature: (Ljava/lang/Object;)Ljava/lang/Object;
  Code:
   Stack=2, Locals=2, Args_size=2
	aload_0
	aload_1
	invokestatic	Method scala/runtime/BoxesRunTime.unboxToInt:(Ljava/lang/Object;)I
	invokevirtual	Method apply:(I)Ljava/lang/Object;
	areturn
  Labels:
  LocalVariableTable: 
   Start  Length  Slot  Name   Signature
   0      9      0    this       Lscala/collection/mutable/GenericArray;
   0      9      1    v1       Ljava/lang/Object;


public scala.collection.IndexedSeq thisCollection();
  Signature: ()Lscala/collection/IndexedSeq;
  Code:
   Stack=1, Locals=1, Args_size=1
	aload_0
	invokeinterface	InterfaceMethod scala/collection/mutable/IndexedSeqLike.thisCollection:()Lscala/collection/mutable/IndexedSeq;
	areturn
  Labels:

public scala.collection.Seq thisCollection();
  Signature: ()Lscala/collection/Seq;
  Code:
   Stack=1, Locals=1, Args_size=1
	aload_0
	invokeinterface	InterfaceMethod scala/collection/mutable/IndexedSeqLike.thisCollection:()Lscala/collection/mutable/IndexedSeq;
	areturn
  Labels:

public scala.collection.Iterable thisCollection();
  Signature: ()Lscala/collection/Iterable;
  Code:
   Stack=1, Locals=1, Args_size=1
	aload_0
	invokeinterface	InterfaceMethod scala/collection/mutable/IndexedSeqLike.thisCollection:()Lscala/collection/mutable/IndexedSeq;
	areturn
  Labels:

public scala.collection.Traversable thisCollection();
  Signature: ()Lscala/collection/Traversable;
  Code:
   Stack=1, Locals=1, Args_size=1
	aload_0
	invokeinterface	InterfaceMethod scala/collection/mutable/IndexedSeqLike.thisCollection:()Lscala/collection/mutable/IndexedSeq;
	areturn
  Labels:

public scala.collection.IndexedSeq toCollection(java.lang.Object);
  Signature: (Ljava/lang/Object;)Lscala/collection/IndexedSeq;
  Code:
   Stack=2, Locals=2, Args_size=2
	aload_0
	aload_1
	invokeinterface	InterfaceMethod scala/collection/mutable/IndexedSeqLike.toCollection:(Ljava/lang/Object;)Lscala/collection/mutable/IndexedSeq;
	areturn
  Labels:
  LocalVariableTable: 
   Start  Length  Slot  Name   Signature
   0      8      0    this       Lscala/collection/mutable/GenericArray;
   0      8      1    repr       Ljava/lang/Object;


public scala.collection.Seq toCollection(java.lang.Object);
  Signature: (Ljava/lang/Object;)Lscala/collection/Seq;
  Code:
   Stack=2, Locals=2, Args_size=2
	aload_0
	aload_1
	invokeinterface	InterfaceMethod scala/collection/mutable/IndexedSeqLike.toCollection:(Ljava/lang/Object;)Lscala/collection/mutable/IndexedSeq;
	areturn
  Labels:
  LocalVariableTable: 
   Start  Length  Slot  Name   Signature
   0      8      0    this       Lscala/collection/mutable/GenericArray;
   0      8      1    repr       Ljava/lang/Object;


public scala.collection.Iterable toCollection(java.lang.Object);
  Signature: (Ljava/lang/Object;)Lscala/collection/Iterable;
  Code:
   Stack=2, Locals=2, Args_size=2
	aload_0
	aload_1
	invokeinterface	InterfaceMethod scala/collection/mutable/IndexedSeqLike.toCollection:(Ljava/lang/Object;)Lscala/collection/mutable/IndexedSeq;
	areturn
  Labels:
  LocalVariableTable: 
   Start  Length  Slot  Name   Signature
   0      8      0    this       Lscala/collection/mutable/GenericArray;
   0      8      1    repr       Ljava/lang/Object;


public scala.collection.Traversable toCollection(java.lang.Object);
  Signature: (Ljava/lang/Object;)Lscala/collection/Traversable;
  Code:
   Stack=2, Locals=2, Args_size=2
	aload_0
	aload_1
	invokeinterface	InterfaceMethod scala/collection/mutable/IndexedSeqLike.toCollection:(Ljava/lang/Object;)Lscala/collection/mutable/IndexedSeq;
	areturn
  Labels:
  LocalVariableTable: 
   Start  Length  Slot  Name   Signature
   0      8      0    this       Lscala/collection/mutable/GenericArray;
   0      8      1    repr       Ljava/lang/Object;


public scala.collection.IndexedSeqView view();
  Signature: ()Lscala/collection/IndexedSeqView;
  Code:
   Stack=1, Locals=1, Args_size=1
	aload_0
	invokeinterface	InterfaceMethod scala/collection/mutable/IndexedSeqLike.view:()Lscala/collection/mutable/IndexedSeqView;
	areturn
  Labels:

public scala.collection.SeqView view();
  Signature: ()Lscala/collection/SeqView;
  Code:
   Stack=1, Locals=1, Args_size=1
	aload_0
	invokeinterface	InterfaceMethod scala/collection/mutable/IndexedSeqLike.view:()Lscala/collection/mutable/IndexedSeqView;
	areturn
  Labels:

public scala.collection.IterableView view();
  Signature: ()Lscala/collection/IterableView;
  Code:
   Stack=1, Locals=1, Args_size=1
	aload_0
	invokeinterface	InterfaceMethod scala/collection/mutable/IndexedSeqLike.view:()Lscala/collection/mutable/IndexedSeqView;
	areturn
  Labels:

public scala.collection.TraversableView view();
  Signature: ()Lscala/collection/TraversableView;
  Code:
   Stack=1, Locals=1, Args_size=1
	aload_0
	invokeinterface	InterfaceMethod scala/collection/mutable/IndexedSeqLike.view:()Lscala/collection/mutable/IndexedSeqView;
	areturn
  Labels:

public scala.collection.IndexedSeqView view(int, int);
  Signature: (II)Lscala/collection/IndexedSeqView;
  Code:
   Stack=3, Locals=3, Args_size=3
	aload_0
	iload_1
	iload_2
	invokeinterface	InterfaceMethod scala/collection/mutable/IndexedSeqLike.view:(II)Lscala/collection/mutable/IndexedSeqView;
	areturn
  Labels:
  LocalVariableTable: 
   Start  Length  Slot  Name   Signature
   0      9      0    this       Lscala/collection/mutable/GenericArray;
   0      9      1    from       I
   0      9      2    until       I


public scala.collection.SeqView view(int, int);
  Signature: (II)Lscala/collection/SeqView;
  Code:
   Stack=3, Locals=3, Args_size=3
	aload_0
	iload_1
	iload_2
	invokeinterface	InterfaceMethod scala/collection/mutable/IndexedSeqLike.view:(II)Lscala/collection/mutable/IndexedSeqView;
	areturn
  Labels:
  LocalVariableTable: 
   Start  Length  Slot  Name   Signature
   0      9      0    this       Lscala/collection/mutable/GenericArray;
   0      9      1    from       I
   0      9      2    until       I


public scala.collection.IterableView view(int, int);
  Signature: (II)Lscala/collection/IterableView;
  Code:
   Stack=3, Locals=3, Args_size=3
	aload_0
	iload_1
	iload_2
	invokeinterface	InterfaceMethod scala/collection/mutable/IndexedSeqLike.view:(II)Lscala/collection/mutable/IndexedSeqView;
	areturn
  Labels:
  LocalVariableTable: 
   Start  Length  Slot  Name   Signature
   0      9      0    this       Lscala/collection/mutable/GenericArray;
   0      9      1    from       I
   0      9      2    until       I


public scala.collection.TraversableView view(int, int);
  Signature: (II)Lscala/collection/TraversableView;
  Code:
   Stack=3, Locals=3, Args_size=3
	aload_0
	iload_1
	iload_2
	invokeinterface	InterfaceMethod scala/collection/mutable/IndexedSeqLike.view:(II)Lscala/collection/mutable/IndexedSeqView;
	areturn
  Labels:
  LocalVariableTable: 
   Start  Length  Slot  Name   Signature
   0      9      0    this       Lscala/collection/mutable/GenericArray;
   0      9      1    from       I
   0      9      2    until       I


public boolean isDefinedAt(java.lang.Object);
  Signature: (Ljava/lang/Object;)Z
  Code:
   Stack=2, Locals=2, Args_size=2
	aload_0
	aload_1
	invokestatic	Method scala/runtime/BoxesRunTime.unboxToInt:(Ljava/lang/Object;)I
	invokeinterface	InterfaceMethod scala/collection/SeqLike.isDefinedAt:(I)Z
	ireturn
  Labels:
  LocalVariableTable: 
   Start  Length  Slot  Name   Signature
   0      11      0    this       Lscala/collection/mutable/GenericArray;
   0      11      1    x       Ljava/lang/Object;


public scala.collection.IterableView projection();
  Signature: ()Lscala/collection/IterableView;
  Code:
   Stack=1, Locals=1, Args_size=1
	aload_0
	invokeinterface	InterfaceMethod scala/collection/SeqLike.projection:()Lscala/collection/SeqView;
	areturn
  Labels:

public scala.Function1 andThen(scala.Function1);
  Signature: (Lscala/Function1;)Lscala/Function1;
  Code:
   Stack=2, Locals=2, Args_size=2
	aload_0
	aload_1
	invokeinterface	InterfaceMethod scala/PartialFunction.andThen:(Lscala/Function1;)Lscala/PartialFunction;
	areturn
  Labels:
  LocalVariableTable: 
   Start  Length  Slot  Name   Signature
   0      8      0    this       Lscala/collection/mutable/GenericArray;
   0      8      1    g       Lscala/Function1;


public void copyToArray(java.lang.Object, int, int);
  Signature: (Ljava/lang/Object;II)V
  Code:
   Stack=6, Locals=5, Args_size=4
	getstatic	Field scala/Predef$.MODULE$:Lscala/Predef$;
	getstatic	Field scala/Predef$.MODULE$:Lscala/Predef$;
	iload_3
	invokevirtual	Method scala/Predef$.intWrapper:(I)Lscala/runtime/RichInt;
	getstatic	Field scala/runtime/ScalaRunTime$.MODULE$:Lscala/runtime/ScalaRunTime$;
	aload_1
	invokevirtual	Method scala/runtime/ScalaRunTime$.array_length:(Ljava/lang/Object;)I
	iload_2
	isub
	invokevirtual	Method scala/runtime/RichInt.min:(I)I
	invokevirtual	Method scala/Predef$.intWrapper:(I)Lscala/runtime/RichInt;
	aload_0
	invokevirtual	Method length:()I
	invokevirtual	Method scala/runtime/RichInt.min:(I)I
	istore	4
	getstatic	Field scala/Array$.MODULE$:Lscala/Array$;
	aload_0
	invokevirtual	Method array:()[Ljava/lang/Object;
	iconst_0
	aload_1
	iload_2
	iload	4
	invokevirtual	Method scala/Array$.copy:(Ljava/lang/Object;ILjava/lang/Object;II)V
	return
  Labels:
  LocalVariableTable: 
   Start  Length  Slot  Name   Signature
   0      50      0    this       Lscala/collection/mutable/GenericArray;
   0      50      1    xs       Ljava/lang/Object;
   0      50      2    start       I
   0      50      3    len       I
   34      15      4    len1       I

  Signature: length = 0x2
   01 2D 

public void foreach(scala.Function1);
  Signature: (Lscala/Function1;)V
  Code:
   Stack=3, Locals=3, Args_size=2
	iconst_0
	istore_2
l2	iload_2
	aload_0
	invokevirtual	Method length:()I
	if_icmpge	l1 // return
	aload_1
	aload_0
	invokevirtual	Method array:()[Ljava/lang/Object;
	iload_2
	aaload
	invokeinterface	InterfaceMethod scala/Function1.apply:(Ljava/lang/Object;)Ljava/lang/Object;
	pop
	iload_2
	iconst_1
	iadd
	istore_2
	goto	l2 // iload_2
l1	return
  Labels:
   	l2 = 2 // iload_2
   	l1 = 30 // return
  LocalVariableTable: 
   Start  Length  Slot  Name   Signature
   0      31      0    this       Lscala/collection/mutable/GenericArray;
   0      31      1    f       Lscala/Function1;
   2      29      2    i       I

  Signature: length = 0x2
   01 35 

public void update(int, java.lang.Object);
  Signature: (ILjava/lang/Object;)V
  Code:
   Stack=3, Locals=3, Args_size=3
	iload_1
	aload_0
	invokevirtual	Method length:()I
	if_icmplt	l1 // aload_0
	new	class java/lang/IndexOutOfBoundsException
	dup
	iload_1
	invokestatic	Method scala/runtime/BoxesRunTime.boxToInteger:(I)Ljava/lang/Integer;
	invokevirtual	Method java/lang/Object.toString:()Ljava/lang/String;
	invokespecial	Method java/lang/IndexOutOfBoundsException."<init>":(Ljava/lang/String;)V
	athrow
l1	aload_0
	invokevirtual	Method array:()[Ljava/lang/Object;
	iload_1
	aload_2
	aastore
	return
  Labels:
   	l1 = 23 // aload_0
  LocalVariableTable: 
   Start  Length  Slot  Name   Signature
   0      31      0    this       Lscala/collection/mutable/GenericArray;
   0      31      1    idx       I
   0      31      2    elem       Ljava/lang/Object;

  Signature: length = 0x2
   01 47 

public java.lang.Object apply(int);
  Signature: (I)Ljava/lang/Object;
  Code:
   Stack=3, Locals=2, Args_size=2
	iload_1
	aload_0
	invokevirtual	Method length:()I
	if_icmplt	l1 // aload_0
	new	class java/lang/IndexOutOfBoundsException
	dup
	iload_1
	invokestatic	Method scala/runtime/BoxesRunTime.boxToInteger:(I)Ljava/lang/Integer;
	invokevirtual	Method java/lang/Object.toString:()Ljava/lang/String;
	invokespecial	Method java/lang/IndexOutOfBoundsException."<init>":(Ljava/lang/String;)V
	athrow
l1	aload_0
	invokevirtual	Method array:()[Ljava/lang/Object;
	iload_1
	aaload
	areturn
  Labels:
   	l1 = 23 // aload_0
  LocalVariableTable: 
   Start  Length  Slot  Name   Signature
   0      30      0    this       Lscala/collection/mutable/GenericArray;
   0      30      1    idx       I

  Signature: length = 0x2
   01 48 

public java.lang.Object[] array();
  Signature: ()[Ljava/lang/Object;
  Code:
   Stack=1, Locals=1, Args_size=1
	aload_0
	getfield	Field array:[Ljava/lang/Object;
	areturn
  Labels:

public scala.collection.generic.GenericCompanion companion();
  Signature: ()Lscala/collection/generic/GenericCompanion;
  Code:
   Stack=1, Locals=1, Args_size=1
	getstatic	Field scala/collection/mutable/GenericArray$.MODULE$:Lscala/collection/mutable/GenericArray$;
	areturn
  Labels:
  Signature: length = 0x2
   01 4B 

public int length();
  Signature: ()I
  Code:
   Stack=1, Locals=1, Args_size=1
	aload_0
	getfield	Field length:I
	ireturn
  Labels:

public scala.collection.TraversableLike$WithFilter withFilter(scala.Function1);
  Signature: (Lscala/Function1;)Lscala/collection/TraversableLike$WithFilter;
  Code:
   Stack=2, Locals=2, Args_size=2
	aload_0
	aload_1
	invokestatic	Method scala/collection/TraversableLike$class.withFilter:(Lscala/collection/TraversableLike;Lscala/Function1;)Lscala/collection/TraversableLike$WithFilter;
	areturn
  Labels:
  LocalVariableTable: 
   Start  Length  Slot  Name   Signature
   0      6      0    this       Lscala/collection/mutable/GenericArray;
   0      6      1    p       Lscala/Function1;

  Signature: length = 0x2
   01 4D 

public java.lang.String stringPrefix();
  Signature: ()Ljava/lang/String;
  Code:
   Stack=1, Locals=1, Args_size=1
	aload_0
	invokestatic	Method scala/collection/TraversableLike$class.stringPrefix:(Lscala/collection/TraversableLike;)Ljava/lang/String;
	areturn
  Labels:

public scala.collection.mutable.StringBuilder addString(scala.collection.mutable.StringBuilder);
  Signature: (Lscala/collection/mutable/StringBuilder;)Lscala/collection/mutable/StringBuilder;
  Code:
   Stack=2, Locals=2, Args_size=2
	aload_0
	aload_1
	invokestatic	Method scala/collection/TraversableLike$class.addString:(Lscala/collection/TraversableLike;Lscala/collection/mutable/StringBuilder;)Lscala/collection/mutable/StringBuilder;
	areturn
  Labels:
  LocalVariableTable: 
   Start  Length  Slot  Name   Signature
   0      6      0    this       Lscala/collection/mutable/GenericArray;
   0      6      1    b       Lscala/collection/mutable/StringBuilder;


public scala.collection.mutable.StringBuilder addString(scala.collection.mutable.StringBuilder, java.lang.String);
  Signature: (Lscala/collection/mutable/StringBuilder;Ljava/lang/String;)Lscala/collection/mutable/StringBuilder;
  Code:
   Stack=3, Locals=3, Args_size=3
	aload_0
	aload_1
	aload_2
	invokestatic	Method scala/collection/TraversableLike$class.addString:(Lscala/collection/TraversableLike;Lscala/collection/mutable/StringBuilder;Ljava/lang/String;)Lscala/collection/mutable/StringBuilder;
	areturn
  Labels:
  LocalVariableTable: 
   Start  Length  Slot  Name   Signature
   0      7      0    this       Lscala/collection/mutable/GenericArray;
   0      7      1    b       Lscala/collection/mutable/StringBuilder;
   0      7      2    sep       Ljava/lang/String;


public scala.collection.mutable.StringBuilder addString(scala.collection.mutable.StringBuilder, java.lang.String, java.lang.String, java.lang.String);
  Signature: (Lscala/collection/mutable/StringBuilder;Ljava/lang/String;Ljava/lang/String;Ljava/lang/String;)Lscala/collection/mutable/StringBuilder;
  Code:
   Stack=5, Locals=5, Args_size=5
	aload_0
	aload_1
	aload_2
	aload_3
	aload	4
	invokestatic	Method scala/collection/TraversableLike$class.addString:(Lscala/collection/TraversableLike;Lscala/collection/mutable/StringBuilder;Ljava/lang/String;Ljava/lang/String;Ljava/lang/String;)Lscala/collection/mutable/StringBuilder;
	areturn
  Labels:
  LocalVariableTable: 
   Start  Length  Slot  Name   Signature
   0      10      0    this       Lscala/collection/mutable/GenericArray;
   0      10      1    b       Lscala/collection/mutable/StringBuilder;
   0      10      2    start       Ljava/lang/String;
   0      10      3    sep       Ljava/lang/String;
   0      10      4    end       Ljava/lang/String;


public java.lang.String mkString();
  Signature: ()Ljava/lang/String;
  Code:
   Stack=1, Locals=1, Args_size=1
	aload_0
	invokestatic	Method scala/collection/TraversableLike$class.mkString:(Lscala/collection/TraversableLike;)Ljava/lang/String;
	areturn
  Labels:

public java.lang.String mkString(java.lang.String);
  Signature: (Ljava/lang/String;)Ljava/lang/String;
  Code:
   Stack=2, Locals=2, Args_size=2
	aload_0
	aload_1
	invokestatic	Method scala/collection/TraversableLike$class.mkString:(Lscala/collection/TraversableLike;Ljava/lang/String;)Ljava/lang/String;
	areturn
  Labels:
  LocalVariableTable: 
   Start  Length  Slot  Name   Signature
   0      6      0    this       Lscala/collection/mutable/GenericArray;
   0      6      1    sep       Ljava/lang/String;


public java.lang.String mkString(java.lang.String, java.lang.String, java.lang.String);
  Signature: (Ljava/lang/String;Ljava/lang/String;Ljava/lang/String;)Ljava/lang/String;
  Code:
   Stack=4, Locals=4, Args_size=4
	aload_0
	aload_1
	aload_2
	aload_3
	invokestatic	Method scala/collection/TraversableLike$class.mkString:(Lscala/collection/TraversableLike;Ljava/lang/String;Ljava/lang/String;Ljava/lang/String;)Ljava/lang/String;
	areturn
  Labels:
  LocalVariableTable: 
   Start  Length  Slot  Name   Signature
   0      8      0    this       Lscala/collection/mutable/GenericArray;
   0      8      1    start       Ljava/lang/String;
   0      8      2    sep       Ljava/lang/String;
   0      8      3    end       Ljava/lang/String;


public scala.collection.immutable.Map toMap(scala.Predef$$less$colon$less);
  Signature: (Lscala/Predef$$less$colon$less;)Lscala/collection/immutable/Map;
  Code:
   Stack=2, Locals=2, Args_size=2
	aload_0
	aload_1
	invokestatic	Method scala/collection/TraversableLike$class.toMap:(Lscala/collection/TraversableLike;Lscala/Predef$$less$colon$less;)Lscala/collection/immutable/Map;
	areturn
  Labels:
  LocalVariableTable: 
   Start  Length  Slot  Name   Signature
   0      6      0    this       Lscala/collection/mutable/GenericArray;
   0      6      1    ev       Lscala/Predef$$less$colon$less;


public scala.collection.immutable.Set toSet();
  Signature: ()Lscala/collection/immutable/Set;
  Code:
   Stack=1, Locals=1, Args_size=1
	aload_0
	invokestatic	Method scala/collection/TraversableLike$class.toSet:(Lscala/collection/TraversableLike;)Lscala/collection/immutable/Set;
	areturn
  Labels:

public scala.collection.mutable.IndexedSeq toIndexedSeq();
  Signature: ()Lscala/collection/mutable/IndexedSeq;
  Code:
   Stack=1, Locals=1, Args_size=1
	aload_0
	invokestatic	Method scala/collection/TraversableLike$class.toIndexedSeq:(Lscala/collection/TraversableLike;)Lscala/collection/mutable/IndexedSeq;
	areturn
  Labels:

public scala.collection.immutable.List toList();
  Signature: ()Lscala/collection/immutable/List;
  Code:
   Stack=1, Locals=1, Args_size=1
	aload_0
	invokestatic	Method scala/collection/TraversableLike$class.toList:(Lscala/collection/TraversableLike;)Lscala/collection/immutable/List;
	areturn
  Labels:

public java.lang.Object toArray(scala.reflect.ClassManifest);
  Signature: (Lscala/reflect/ClassManifest;)Ljava/lang/Object;
  Code:
   Stack=2, Locals=2, Args_size=2
	aload_0
	aload_1
	invokestatic	Method scala/collection/TraversableLike$class.toArray:(Lscala/collection/TraversableLike;Lscala/reflect/ClassManifest;)Ljava/lang/Object;
	areturn
  Labels:
  LocalVariableTable: 
   Start  Length  Slot  Name   Signature
   0      6      0    this       Lscala/collection/mutable/GenericArray;
   0      6      1    evidence$1       Lscala/reflect/ClassManifest;


public void copyToArray(java.lang.Object);
  Signature: (Ljava/lang/Object;)V
  Code:
   Stack=2, Locals=2, Args_size=2
	aload_0
	aload_1
	invokestatic	Method scala/collection/TraversableLike$class.copyToArray:(Lscala/collection/TraversableLike;Ljava/lang/Object;)V
	return
  Labels:
  LocalVariableTable: 
   Start  Length  Slot  Name   Signature
   0      6      0    this       Lscala/collection/mutable/GenericArray;
   0      6      1    xs       Ljava/lang/Object;


public void copyToArray(java.lang.Object, int);
  Signature: (Ljava/lang/Object;I)V
  Code:
   Stack=3, Locals=3, Args_size=3
	aload_0
	aload_1
	iload_2
	invokestatic	Method scala/collection/TraversableLike$class.copyToArray:(Lscala/collection/TraversableLike;Ljava/lang/Object;I)V
	return
  Labels:
  LocalVariableTable: 
   Start  Length  Slot  Name   Signature
   0      7      0    this       Lscala/collection/mutable/GenericArray;
   0      7      1    xs       Ljava/lang/Object;
   0      7      2    start       I


public void copyToBuffer(scala.collection.mutable.Buffer);
  Signature: (Lscala/collection/mutable/Buffer;)V
  Code:
   Stack=2, Locals=2, Args_size=2
	aload_0
	aload_1
	invokestatic	Method scala/collection/TraversableLike$class.copyToBuffer:(Lscala/collection/TraversableLike;Lscala/collection/mutable/Buffer;)V
	return
  Labels:
  LocalVariableTable: 
   Start  Length  Slot  Name   Signature
   0      6      0    this       Lscala/collection/mutable/GenericArray;
   0      6      1    dest       Lscala/collection/mutable/Buffer;


public scala.Option lastOption();
  Signature: ()Lscala/Option;
  Code:
   Stack=1, Locals=1, Args_size=1
	aload_0
	invokestatic	Method scala/collection/TraversableLike$class.lastOption:(Lscala/collection/TraversableLike;)Lscala/Option;
	areturn
  Labels:

public scala.Option headOption();
  Signature: ()Lscala/Option;
  Code:
   Stack=1, Locals=1, Args_size=1
	aload_0
	invokestatic	Method scala/collection/TraversableLike$class.headOption:(Lscala/collection/TraversableLike;)Lscala/Option;
	areturn
  Labels:

public java.lang.Object max(scala.math.Ordering);
  Signature: (Lscala/math/Ordering;)Ljava/lang/Object;
  Code:
   Stack=2, Locals=2, Args_size=2
	aload_0
	aload_1
	invokestatic	Method scala/collection/TraversableLike$class.max:(Lscala/collection/TraversableLike;Lscala/math/Ordering;)Ljava/lang/Object;
	areturn
  Labels:
  LocalVariableTable: 
   Start  Length  Slot  Name   Signature
   0      6      0    this       Lscala/collection/mutable/GenericArray;
   0      6      1    cmp       Lscala/math/Ordering;


public java.lang.Object min(scala.math.Ordering);
  Signature: (Lscala/math/Ordering;)Ljava/lang/Object;
  Code:
   Stack=2, Locals=2, Args_size=2
	aload_0
	aload_1
	invokestatic	Method scala/collection/TraversableLike$class.min:(Lscala/collection/TraversableLike;Lscala/math/Ordering;)Ljava/lang/Object;
	areturn
  Labels:
  LocalVariableTable: 
   Start  Length  Slot  Name   Signature
   0      6      0    this       Lscala/collection/mutable/GenericArray;
   0      6      1    cmp       Lscala/math/Ordering;


public java.lang.Object product(scala.math.Numeric);
  Signature: (Lscala/math/Numeric;)Ljava/lang/Object;
  Code:
   Stack=2, Locals=2, Args_size=2
	aload_0
	aload_1
	invokestatic	Method scala/collection/TraversableLike$class.product:(Lscala/collection/TraversableLike;Lscala/math/Numeric;)Ljava/lang/Object;
	areturn
  Labels:
  LocalVariableTable: 
   Start  Length  Slot  Name   Signature
   0      6      0    this       Lscala/collection/mutable/GenericArray;
   0      6      1    num       Lscala/math/Numeric;


public java.lang.Object sum(scala.math.Numeric);
  Signature: (Lscala/math/Numeric;)Ljava/lang/Object;
  Code:
   Stack=2, Locals=2, Args_size=2
	aload_0
	aload_1
	invokestatic	Method scala/collection/TraversableLike$class.sum:(Lscala/collection/TraversableLike;Lscala/math/Numeric;)Ljava/lang/Object;
	areturn
  Labels:
  LocalVariableTable: 
   Start  Length  Slot  Name   Signature
   0      6      0    this       Lscala/collection/mutable/GenericArray;
   0      6      1    num       Lscala/math/Numeric;


public scala.Option reduceRightOption(scala.Function2);
  Signature: (Lscala/Function2;)Lscala/Option;
  Code:
   Stack=2, Locals=2, Args_size=2
	aload_0
	aload_1
	invokestatic	Method scala/collection/TraversableLike$class.reduceRightOption:(Lscala/collection/TraversableLike;Lscala/Function2;)Lscala/Option;
	areturn
  Labels:
  LocalVariableTable: 
   Start  Length  Slot  Name   Signature
   0      6      0    this       Lscala/collection/mutable/GenericArray;
   0      6      1    op       Lscala/Function2;


public scala.Option reduceLeftOption(scala.Function2);
  Signature: (Lscala/Function2;)Lscala/Option;
  Code:
   Stack=2, Locals=2, Args_size=2
	aload_0
	aload_1
	invokestatic	Method scala/collection/TraversableLike$class.reduceLeftOption:(Lscala/collection/TraversableLike;Lscala/Function2;)Lscala/Option;
	areturn
  Labels:
  LocalVariableTable: 
   Start  Length  Slot  Name   Signature
   0      6      0    this       Lscala/collection/mutable/GenericArray;
   0      6      1    op       Lscala/Function2;


public java.lang.Object $colon$bslash(java.lang.Object, scala.Function2);
  Signature: (Ljava/lang/Object;Lscala/Function2;)Ljava/lang/Object;
  Code:
   Stack=3, Locals=3, Args_size=3
	aload_0
	aload_1
	aload_2
	invokestatic	Method scala/collection/TraversableLike$class.$colon$bslash:(Lscala/collection/TraversableLike;Ljava/lang/Object;Lscala/Function2;)Ljava/lang/Object;
	areturn
  Labels:
  LocalVariableTable: 
   Start  Length  Slot  Name   Signature
   0      7      0    this       Lscala/collection/mutable/GenericArray;
   0      7      1    z       Ljava/lang/Object;
   0      7      2    op       Lscala/Function2;


public java.lang.Object $div$colon(java.lang.Object, scala.Function2);
  Signature: (Ljava/lang/Object;Lscala/Function2;)Ljava/lang/Object;
  Code:
   Stack=3, Locals=3, Args_size=3
	aload_0
	aload_1
	aload_2
	invokestatic	Method scala/collection/TraversableLike$class.$div$colon:(Lscala/collection/TraversableLike;Ljava/lang/Object;Lscala/Function2;)Ljava/lang/Object;
	areturn
  Labels:
  LocalVariableTable: 
   Start  Length  Slot  Name   Signature
   0      7      0    this       Lscala/collection/mutable/GenericArray;
   0      7      1    z       Ljava/lang/Object;
   0      7      2    op       Lscala/Function2;


public int count(scala.Function1);
  Signature: (Lscala/Function1;)I
  Code:
   Stack=2, Locals=2, Args_size=2
	aload_0
	aload_1
	invokestatic	Method scala/collection/TraversableLike$class.count:(Lscala/collection/TraversableLike;Lscala/Function1;)I
	ireturn
  Labels:
  LocalVariableTable: 
   Start  Length  Slot  Name   Signature
   0      6      0    this       Lscala/collection/mutable/GenericArray;
   0      6      1    p       Lscala/Function1;


public scala.collection.Map groupBy(scala.Function1);
  Signature: (Lscala/Function1;)Lscala/collection/Map;
  Code:
   Stack=2, Locals=2, Args_size=2
	aload_0
	aload_1
	invokestatic	Method scala/collection/TraversableLike$class.groupBy:(Lscala/collection/TraversableLike;Lscala/Function1;)Lscala/collection/Map;
	areturn
  Labels:
  LocalVariableTable: 
   Start  Length  Slot  Name   Signature
   0      6      0    this       Lscala/collection/mutable/GenericArray;
   0      6      1    f       Lscala/Function1;


public scala.Tuple2 partition(scala.Function1);
  Signature: (Lscala/Function1;)Lscala/Tuple2;
  Code:
   Stack=2, Locals=2, Args_size=2
	aload_0
	aload_1
	invokestatic	Method scala/collection/TraversableLike$class.partition:(Lscala/collection/TraversableLike;Lscala/Function1;)Lscala/Tuple2;
	areturn
  Labels:
  LocalVariableTable: 
   Start  Length  Slot  Name   Signature
   0      6      0    this       Lscala/collection/mutable/GenericArray;
   0      6      1    p       Lscala/Function1;


public java.lang.Object partialMap(scala.PartialFunction, scala.collection.generic.CanBuildFrom);
  Signature: (Lscala/PartialFunction;Lscala/collection/generic/CanBuildFrom;)Ljava/lang/Object;
  Code:
   Stack=3, Locals=3, Args_size=3
	aload_0
	aload_1
	aload_2
	invokestatic	Method scala/collection/TraversableLike$class.partialMap:(Lscala/collection/TraversableLike;Lscala/PartialFunction;Lscala/collection/generic/CanBuildFrom;)Ljava/lang/Object;
	areturn
  Labels:
  LocalVariableTable: 
   Start  Length  Slot  Name   Signature
   0      7      0    this       Lscala/collection/mutable/GenericArray;
   0      7      1    pf       Lscala/PartialFunction;
   0      7      2    bf       Lscala/collection/generic/CanBuildFrom;


public java.lang.Object filterNot(scala.Function1);
  Signature: (Lscala/Function1;)Ljava/lang/Object;
  Code:
   Stack=2, Locals=2, Args_size=2
	aload_0
	aload_1
	invokestatic	Method scala/collection/TraversableLike$class.filterNot:(Lscala/collection/TraversableLike;Lscala/Function1;)Ljava/lang/Object;
	areturn
  Labels:
  LocalVariableTable: 
   Start  Length  Slot  Name   Signature
   0      6      0    this       Lscala/collection/mutable/GenericArray;
   0      6      1    p       Lscala/Function1;


public java.lang.Object filter(scala.Function1);
  Signature: (Lscala/Function1;)Ljava/lang/Object;
  Code:
   Stack=2, Locals=2, Args_size=2
	aload_0
	aload_1
	invokestatic	Method scala/collection/TraversableLike$class.filter:(Lscala/collection/TraversableLike;Lscala/Function1;)Ljava/lang/Object;
	areturn
  Labels:
  LocalVariableTable: 
   Start  Length  Slot  Name   Signature
   0      6      0    this       Lscala/collection/mutable/GenericArray;
   0      6      1    p       Lscala/Function1;


public java.lang.Object flatMap(scala.Function1, scala.collection.generic.CanBuildFrom);
  Signature: (Lscala/Function1;Lscala/collection/generic/CanBuildFrom;)Ljava/lang/Object;
  Code:
   Stack=3, Locals=3, Args_size=3
	aload_0
	aload_1
	aload_2
	invokestatic	Method scala/collection/TraversableLike$class.flatMap:(Lscala/collection/TraversableLike;Lscala/Function1;Lscala/collection/generic/CanBuildFrom;)Ljava/lang/Object;
	areturn
  Labels:
  LocalVariableTable: 
   Start  Length  Slot  Name   Signature
   0      7      0    this       Lscala/collection/mutable/GenericArray;
   0      7      1    f       Lscala/Function1;
   0      7      2    bf       Lscala/collection/generic/CanBuildFrom;


public java.lang.Object map(scala.Function1, scala.collection.generic.CanBuildFrom);
  Signature: (Lscala/Function1;Lscala/collection/generic/CanBuildFrom;)Ljava/lang/Object;
  Code:
   Stack=3, Locals=3, Args_size=3
	aload_0
	aload_1
	aload_2
	invokestatic	Method scala/collection/TraversableLike$class.map:(Lscala/collection/TraversableLike;Lscala/Function1;Lscala/collection/generic/CanBuildFrom;)Ljava/lang/Object;
	areturn
  Labels:
  LocalVariableTable: 
   Start  Length  Slot  Name   Signature
   0      7      0    this       Lscala/collection/mutable/GenericArray;
   0      7      1    f       Lscala/Function1;
   0      7      2    bf       Lscala/collection/generic/CanBuildFrom;


public java.lang.Object $plus$plus(scala.collection.Iterator, scala.collection.generic.CanBuildFrom);
  Signature: (Lscala/collection/Iterator;Lscala/collection/generic/CanBuildFrom;)Ljava/lang/Object;
  Code:
   Stack=3, Locals=3, Args_size=3
	aload_0
	aload_1
	aload_2
	invokestatic	Method scala/collection/TraversableLike$class.$plus$plus:(Lscala/collection/TraversableLike;Lscala/collection/Iterator;Lscala/collection/generic/CanBuildFrom;)Ljava/lang/Object;
	areturn
  Labels:
  LocalVariableTable: 
   Start  Length  Slot  Name   Signature
   0      7      0    this       Lscala/collection/mutable/GenericArray;
   0      7      1    that       Lscala/collection/Iterator;
   0      7      2    bf       Lscala/collection/generic/CanBuildFrom;


public java.lang.Object $plus$plus(scala.collection.Traversable, scala.collection.generic.CanBuildFrom);
  Signature: (Lscala/collection/Traversable;Lscala/collection/generic/CanBuildFrom;)Ljava/lang/Object;
  Code:
   Stack=3, Locals=3, Args_size=3
	aload_0
	aload_1
	aload_2
	invokestatic	Method scala/collection/TraversableLike$class.$plus$plus:(Lscala/collection/TraversableLike;Lscala/collection/Traversable;Lscala/collection/generic/CanBuildFrom;)Ljava/lang/Object;
	areturn
  Labels:
  LocalVariableTable: 
   Start  Length  Slot  Name   Signature
   0      7      0    this       Lscala/collection/mutable/GenericArray;
   0      7      1    that       Lscala/collection/Traversable;
   0      7      2    bf       Lscala/collection/generic/CanBuildFrom;


public boolean hasDefiniteSize();
  Signature: ()Z
  Code:
   Stack=1, Locals=1, Args_size=1
	aload_0
	invokestatic	Method scala/collection/TraversableLike$class.hasDefiniteSize:(Lscala/collection/TraversableLike;)Z
	ireturn
  Labels:

public boolean nonEmpty();
  Signature: ()Z
  Code:
   Stack=1, Locals=1, Args_size=1
	aload_0
	invokestatic	Method scala/collection/TraversableLike$class.nonEmpty:(Lscala/collection/TraversableLike;)Z
	ireturn
  Labels:

public java.lang.Object repr();
  Signature: ()Ljava/lang/Object;
  Code:
   Stack=1, Locals=1, Args_size=1
	aload_0
	invokestatic	Method scala/collection/TraversableLike$class.repr:(Lscala/collection/TraversableLike;)Ljava/lang/Object;
	areturn
  Labels:

public scala.collection.Traversable transpose(scala.Function1);
  Signature: (Lscala/Function1;)Lscala/collection/Traversable;
  Code:
   Stack=2, Locals=2, Args_size=2
	aload_0
	aload_1
	invokestatic	Method scala/collection/generic/GenericTraversableTemplate$class.transpose:(Lscala/collection/generic/GenericTraversableTemplate;Lscala/Function1;)Lscala/collection/Traversable;
	areturn
  Labels:
  LocalVariableTable: 
   Start  Length  Slot  Name   Signature
   0      6      0    this       Lscala/collection/mutable/GenericArray;
   0      6      1    asTraversable       Lscala/Function1;


public scala.collection.Traversable flatten(scala.Function1);
  Signature: (Lscala/Function1;)Lscala/collection/Traversable;
  Code:
   Stack=2, Locals=2, Args_size=2
	aload_0
	aload_1
	invokestatic	Method scala/collection/generic/GenericTraversableTemplate$class.flatten:(Lscala/collection/generic/GenericTraversableTemplate;Lscala/Function1;)Lscala/collection/Traversable;
	areturn
  Labels:
  LocalVariableTable: 
   Start  Length  Slot  Name   Signature
   0      6      0    this       Lscala/collection/mutable/GenericArray;
   0      6      1    asTraversable       Lscala/Function1;


public scala.Tuple2 unzip(scala.Function1);
  Signature: (Lscala/Function1;)Lscala/Tuple2;
  Code:
   Stack=2, Locals=2, Args_size=2
	aload_0
	aload_1
	invokestatic	Method scala/collection/generic/GenericTraversableTemplate$class.unzip:(Lscala/collection/generic/GenericTraversableTemplate;Lscala/Function1;)Lscala/Tuple2;
	areturn
  Labels:
  LocalVariableTable: 
   Start  Length  Slot  Name   Signature
   0      6      0    this       Lscala/collection/mutable/GenericArray;
   0      6      1    asPair       Lscala/Function1;


public scala.collection.mutable.Builder genericBuilder();
  Signature: ()Lscala/collection/mutable/Builder;
  Code:
   Stack=1, Locals=1, Args_size=1
	aload_0
	invokestatic	Method scala/collection/generic/GenericTraversableTemplate$class.genericBuilder:(Lscala/collection/generic/GenericTraversableTemplate;)Lscala/collection/mutable/Builder;
	areturn
  Labels:

public scala.collection.mutable.Builder newBuilder();
  Signature: ()Lscala/collection/mutable/Builder;
  Code:
   Stack=1, Locals=1, Args_size=1
	aload_0
	invokestatic	Method scala/collection/generic/GenericTraversableTemplate$class.newBuilder:(Lscala/collection/generic/GenericTraversableTemplate;)Lscala/collection/mutable/Builder;
	areturn
  Labels:

public scala.Option firstOption();
  Signature: ()Lscala/Option;
  Code:
   Stack=1, Locals=1, Args_size=1
	aload_0
	invokestatic	Method scala/collection/IterableLike$class.firstOption:(Lscala/collection/IterableLike;)Lscala/Option;
	areturn
  Labels:
  Deprecated: true

public java.lang.Object first();
  Signature: ()Ljava/lang/Object;
  Code:
   Stack=1, Locals=1, Args_size=1
	aload_0
	invokestatic	Method scala/collection/IterableLike$class.first:(Lscala/collection/IterableLike;)Ljava/lang/Object;
	areturn
  Labels:
  Deprecated: true

public boolean canEqual(java.lang.Object);
  Signature: (Ljava/lang/Object;)Z
  Code:
   Stack=2, Locals=2, Args_size=2
	aload_0
	aload_1
	invokestatic	Method scala/collection/IterableLike$class.canEqual:(Lscala/collection/IterableLike;Ljava/lang/Object;)Z
	ireturn
  Labels:
  LocalVariableTable: 
   Start  Length  Slot  Name   Signature
   0      6      0    this       Lscala/collection/mutable/GenericArray;
   0      6      1    that       Ljava/lang/Object;


public scala.collection.immutable.Stream toStream();
  Signature: ()Lscala/collection/immutable/Stream;
  Code:
   Stack=1, Locals=1, Args_size=1
	aload_0
	invokestatic	Method scala/collection/IterableLike$class.toStream:(Lscala/collection/IterableLike;)Lscala/collection/immutable/Stream;
	areturn
  Labels:

public java.lang.Object zipAll(scala.collection.Iterable, java.lang.Object, java.lang.Object, scala.collection.generic.CanBuildFrom);
  Signature: (Lscala/collection/Iterable;Ljava/lang/Object;Ljava/lang/Object;Lscala/collection/generic/CanBuildFrom;)Ljava/lang/Object;
  Code:
   Stack=5, Locals=5, Args_size=5
	aload_0
	aload_1
	aload_2
	aload_3
	aload	4
	invokestatic	Method scala/collection/IterableLike$class.zipAll:(Lscala/collection/IterableLike;Lscala/collection/Iterable;Ljava/lang/Object;Ljava/lang/Object;Lscala/collection/generic/CanBuildFrom;)Ljava/lang/Object;
	areturn
  Labels:
  LocalVariableTable: 
   Start  Length  Slot  Name   Signature
   0      10      0    this       Lscala/collection/mutable/GenericArray;
   0      10      1    that       Lscala/collection/Iterable;
   0      10      2    thisElem       Ljava/lang/Object;
   0      10      3    thatElem       Ljava/lang/Object;
   0      10      4    bf       Lscala/collection/generic/CanBuildFrom;


public scala.collection.Iterable toIterable();
  Signature: ()Lscala/collection/Iterable;
  Code:
   Stack=1, Locals=1, Args_size=1
	aload_0
	invokestatic	Method scala/collection/IterableLike$class.toIterable:(Lscala/collection/IterableLike;)Lscala/collection/Iterable;
	areturn
  Labels:

public scala.collection.Iterator elements();
  Signature: ()Lscala/collection/Iterator;
  Code:
   Stack=1, Locals=1, Args_size=1
	aload_0
	invokestatic	Method scala/collection/IterableLike$class.elements:(Lscala/collection/IterableLike;)Lscala/collection/Iterator;
	areturn
  Labels:
  Deprecated: true

public scala.Function1 compose(scala.Function1);
  Signature: (Lscala/Function1;)Lscala/Function1;
  Code:
   Stack=2, Locals=2, Args_size=2
	aload_0
	aload_1
	invokestatic	Method scala/Function1$class.compose:(Lscala/Function1;Lscala/Function1;)Lscala/Function1;
	areturn
  Labels:
  LocalVariableTable: 
   Start  Length  Slot  Name   Signature
   0      6      0    this       Lscala/collection/mutable/GenericArray;
   0      6      1    g       Lscala/Function1;


public scala.Function1 lift();
  Signature: ()Lscala/Function1;
  Code:
   Stack=1, Locals=1, Args_size=1
	aload_0
	invokestatic	Method scala/PartialFunction$class.lift:(Lscala/PartialFunction;)Lscala/Function1;
	areturn
  Labels:

public scala.PartialFunction andThen(scala.Function1);
  Signature: (Lscala/Function1;)Lscala/PartialFunction;
  Code:
   Stack=2, Locals=2, Args_size=2
	aload_0
	aload_1
	invokestatic	Method scala/PartialFunction$class.andThen:(Lscala/PartialFunction;Lscala/Function1;)Lscala/PartialFunction;
	areturn
  Labels:
  LocalVariableTable: 
   Start  Length  Slot  Name   Signature
   0      6      0    this       Lscala/collection/mutable/GenericArray;
   0      6      1    k       Lscala/Function1;


public scala.PartialFunction orElse(scala.PartialFunction);
  Signature: (Lscala/PartialFunction;)Lscala/PartialFunction;
  Code:
   Stack=2, Locals=2, Args_size=2
	aload_0
	aload_1
	invokestatic	Method scala/PartialFunction$class.orElse:(Lscala/PartialFunction;Lscala/PartialFunction;)Lscala/PartialFunction;
	areturn
  Labels:
  LocalVariableTable: 
   Start  Length  Slot  Name   Signature
   0      6      0    this       Lscala/collection/mutable/GenericArray;
   0      6      1    that       Lscala/PartialFunction;


public scala.collection.SeqView projection();
  Signature: ()Lscala/collection/SeqView;
  Code:
   Stack=1, Locals=1, Args_size=1
	aload_0
	invokestatic	Method scala/collection/SeqLike$class.projection:(Lscala/collection/SeqLike;)Lscala/collection/SeqView;
	areturn
  Labels:
  Deprecated: true

public boolean equalsWith(scala.collection.Seq, scala.Function2);
  Signature: (Lscala/collection/Seq;Lscala/Function2;)Z
  Code:
   Stack=3, Locals=3, Args_size=3
	aload_0
	aload_1
	aload_2
	invokestatic	Method scala/collection/SeqLike$class.equalsWith:(Lscala/collection/SeqLike;Lscala/collection/Seq;Lscala/Function2;)Z
	ireturn
  Labels:
  LocalVariableTable: 
   Start  Length  Slot  Name   Signature
   0      7      0    this       Lscala/collection/mutable/GenericArray;
   0      7      1    that       Lscala/collection/Seq;
   0      7      2    f       Lscala/Function2;

  Deprecated: true

public int findLastIndexOf(scala.Function1);
  Signature: (Lscala/Function1;)I
  Code:
   Stack=2, Locals=2, Args_size=2
	aload_0
	aload_1
	invokestatic	Method scala/collection/SeqLike$class.findLastIndexOf:(Lscala/collection/SeqLike;Lscala/Function1;)I
	ireturn
  Labels:
  LocalVariableTable: 
   Start  Length  Slot  Name   Signature
   0      6      0    this       Lscala/collection/mutable/GenericArray;
   0      6      1    p       Lscala/Function1;


public java.lang.String toString();
  Signature: ()Ljava/lang/String;
  Code:
   Stack=1, Locals=1, Args_size=1
	aload_0
	invokestatic	Method scala/collection/SeqLike$class.toString:(Lscala/collection/SeqLike;)Ljava/lang/String;
	areturn
  Labels:

public boolean equals(java.lang.Object);
  Signature: (Ljava/lang/Object;)Z
  Code:
   Stack=2, Locals=2, Args_size=2
	aload_0
	aload_1
	invokestatic	Method scala/collection/SeqLike$class.equals:(Lscala/collection/SeqLike;Ljava/lang/Object;)Z
	ireturn
  Labels:
  LocalVariableTable: 
   Start  Length  Slot  Name   Signature
   0      6      0    this       Lscala/collection/mutable/GenericArray;
   0      6      1    that       Ljava/lang/Object;


public int hashCode();
  Signature: ()I
  Code:
   Stack=1, Locals=1, Args_size=1
	aload_0
	invokestatic	Method scala/collection/SeqLike$class.hashCode:(Lscala/collection/SeqLike;)I
	ireturn
  Labels:

public scala.collection.immutable.Range indices();
  Signature: ()Lscala/collection/immutable/Range;
  Code:
   Stack=1, Locals=1, Args_size=1
	aload_0
	invokestatic	Method scala/collection/SeqLike$class.indices:(Lscala/collection/SeqLike;)Lscala/collection/immutable/Range;
	areturn
  Labels:

public scala.collection.Seq toSeq();
  Signature: ()Lscala/collection/Seq;
  Code:
   Stack=1, Locals=1, Args_size=1
	aload_0
	invokestatic	Method scala/collection/SeqLike$class.toSeq:(Lscala/collection/SeqLike;)Lscala/collection/Seq;
	areturn
  Labels:

public java.lang.Object sortBy(scala.Function1, scala.math.Ordering);
  Signature: (Lscala/Function1;Lscala/math/Ordering;)Ljava/lang/Object;
  Code:
   Stack=3, Locals=3, Args_size=3
	aload_0
	aload_1
	aload_2
	invokestatic	Method scala/collection/SeqLike$class.sortBy:(Lscala/collection/SeqLike;Lscala/Function1;Lscala/math/Ordering;)Ljava/lang/Object;
	areturn
  Labels:
  LocalVariableTable: 
   Start  Length  Slot  Name   Signature
   0      7      0    this       Lscala/collection/mutable/GenericArray;
   0      7      1    f       Lscala/Function1;
   0      7      2    ord       Lscala/math/Ordering;


public java.lang.Object sortWith(scala.math.Ordering);
  Signature: (Lscala/math/Ordering;)Ljava/lang/Object;
  Code:
   Stack=2, Locals=2, Args_size=2
	aload_0
	aload_1
	invokestatic	Method scala/collection/SeqLike$class.sortWith:(Lscala/collection/SeqLike;Lscala/math/Ordering;)Ljava/lang/Object;
	areturn
  Labels:
  LocalVariableTable: 
   Start  Length  Slot  Name   Signature
   0      6      0    this       Lscala/collection/mutable/GenericArray;
   0      6      1    ord       Lscala/math/Ordering;


public java.lang.Object sortWith(scala.Function2);
  Signature: (Lscala/Function2;)Ljava/lang/Object;
  Code:
   Stack=2, Locals=2, Args_size=2
	aload_0
	aload_1
	invokestatic	Method scala/collection/SeqLike$class.sortWith:(Lscala/collection/SeqLike;Lscala/Function2;)Ljava/lang/Object;
	areturn
  Labels:
  LocalVariableTable: 
   Start  Length  Slot  Name   Signature
   0      6      0    this       Lscala/collection/mutable/GenericArray;
   0      6      1    lt       Lscala/Function2;


public boolean corresponds(scala.collection.Seq, scala.Function2);
  Signature: (Lscala/collection/Seq;Lscala/Function2;)Z
  Code:
   Stack=3, Locals=3, Args_size=3
	aload_0
	aload_1
	aload_2
	invokestatic	Method scala/collection/SeqLike$class.corresponds:(Lscala/collection/SeqLike;Lscala/collection/Seq;Lscala/Function2;)Z
	ireturn
  Labels:
  LocalVariableTable: 
   Start  Length  Slot  Name   Signature
   0      7      0    this       Lscala/collection/mutable/GenericArray;
   0      7      1    that       Lscala/collection/Seq;
   0      7      2    p       Lscala/Function2;


public java.lang.Object padTo(int, java.lang.Object, scala.collection.generic.CanBuildFrom);
  Signature: (ILjava/lang/Object;Lscala/collection/generic/CanBuildFrom;)Ljava/lang/Object;
  Code:
   Stack=4, Locals=4, Args_size=4
	aload_0
	iload_1
	aload_2
	aload_3
	invokestatic	Method scala/collection/SeqLike$class.padTo:(Lscala/collection/SeqLike;ILjava/lang/Object;Lscala/collection/generic/CanBuildFrom;)Ljava/lang/Object;
	areturn
  Labels:
  LocalVariableTable: 
   Start  Length  Slot  Name   Signature
   0      8      0    this       Lscala/collection/mutable/GenericArray;
   0      8      1    len       I
   0      8      2    elem       Ljava/lang/Object;
   0      8      3    bf       Lscala/collection/generic/CanBuildFrom;


public java.lang.Object $colon$plus(java.lang.Object, scala.collection.generic.CanBuildFrom);
  Signature: (Ljava/lang/Object;Lscala/collection/generic/CanBuildFrom;)Ljava/lang/Object;
  Code:
   Stack=3, Locals=3, Args_size=3
	aload_0
	aload_1
	aload_2
	invokestatic	Method scala/collection/SeqLike$class.$colon$plus:(Lscala/collection/SeqLike;Ljava/lang/Object;Lscala/collection/generic/CanBuildFrom;)Ljava/lang/Object;
	areturn
  Labels:
  LocalVariableTable: 
   Start  Length  Slot  Name   Signature
   0      7      0    this       Lscala/collection/mutable/GenericArray;
   0      7      1    elem       Ljava/lang/Object;
   0      7      2    bf       Lscala/collection/generic/CanBuildFrom;


public java.lang.Object $plus$colon(java.lang.Object, scala.collection.generic.CanBuildFrom);
  Signature: (Ljava/lang/Object;Lscala/collection/generic/CanBuildFrom;)Ljava/lang/Object;
  Code:
   Stack=3, Locals=3, Args_size=3
	aload_0
	aload_1
	aload_2
	invokestatic	Method scala/collection/SeqLike$class.$plus$colon:(Lscala/collection/SeqLike;Ljava/lang/Object;Lscala/collection/generic/CanBuildFrom;)Ljava/lang/Object;
	areturn
  Labels:
  LocalVariableTable: 
   Start  Length  Slot  Name   Signature
   0      7      0    this       Lscala/collection/mutable/GenericArray;
   0      7      1    elem       Ljava/lang/Object;
   0      7      2    bf       Lscala/collection/generic/CanBuildFrom;


public java.lang.Object updated(int, java.lang.Object, scala.collection.generic.CanBuildFrom);
  Signature: (ILjava/lang/Object;Lscala/collection/generic/CanBuildFrom;)Ljava/lang/Object;
  Code:
   Stack=4, Locals=4, Args_size=4
	aload_0
	iload_1
	aload_2
	aload_3
	invokestatic	Method scala/collection/SeqLike$class.updated:(Lscala/collection/SeqLike;ILjava/lang/Object;Lscala/collection/generic/CanBuildFrom;)Ljava/lang/Object;
	areturn
  Labels:
  LocalVariableTable: 
   Start  Length  Slot  Name   Signature
   0      8      0    this       Lscala/collection/mutable/GenericArray;
   0      8      1    index       I
   0      8      2    elem       Ljava/lang/Object;
   0      8      3    bf       Lscala/collection/generic/CanBuildFrom;


public java.lang.Object patch(int, scala.collection.Seq, int, scala.collection.generic.CanBuildFrom);
  Signature: (ILscala/collection/Seq;ILscala/collection/generic/CanBuildFrom;)Ljava/lang/Object;
  Code:
   Stack=5, Locals=5, Args_size=5
	aload_0
	iload_1
	aload_2
	iload_3
	aload	4
	invokestatic	Method scala/collection/SeqLike$class.patch:(Lscala/collection/SeqLike;ILscala/collection/Seq;ILscala/collection/generic/CanBuildFrom;)Ljava/lang/Object;
	areturn
  Labels:
  LocalVariableTable: 
   Start  Length  Slot  Name   Signature
   0      10      0    this       Lscala/collection/mutable/GenericArray;
   0      10      1    from       I
   0      10      2    patch       Lscala/collection/Seq;
   0      10      3    replaced       I
   0      10      4    bf       Lscala/collection/generic/CanBuildFrom;


public java.lang.Object removeDuplicates();
  Signature: ()Ljava/lang/Object;
  Code:
   Stack=1, Locals=1, Args_size=1
	aload_0
	invokestatic	Method scala/collection/SeqLike$class.removeDuplicates:(Lscala/collection/SeqLike;)Ljava/lang/Object;
	areturn
  Labels:

public java.lang.Object intersect(scala.collection.Seq);
  Signature: (Lscala/collection/Seq;)Ljava/lang/Object;
  Code:
   Stack=2, Locals=2, Args_size=2
	aload_0
	aload_1
	invokestatic	Method scala/collection/SeqLike$class.intersect:(Lscala/collection/SeqLike;Lscala/collection/Seq;)Ljava/lang/Object;
	areturn
  Labels:
  LocalVariableTable: 
   Start  Length  Slot  Name   Signature
   0      6      0    this       Lscala/collection/mutable/GenericArray;
   0      6      1    that       Lscala/collection/Seq;


public java.lang.Object diff(scala.collection.Seq);
  Signature: (Lscala/collection/Seq;)Ljava/lang/Object;
  Code:
   Stack=2, Locals=2, Args_size=2
	aload_0
	aload_1
	invokestatic	Method scala/collection/SeqLike$class.diff:(Lscala/collection/SeqLike;Lscala/collection/Seq;)Ljava/lang/Object;
	areturn
  Labels:
  LocalVariableTable: 
   Start  Length  Slot  Name   Signature
   0      6      0    this       Lscala/collection/mutable/GenericArray;
   0      6      1    that       Lscala/collection/Seq;


public java.lang.Object union(scala.collection.Seq, scala.collection.generic.CanBuildFrom);
  Signature: (Lscala/collection/Seq;Lscala/collection/generic/CanBuildFrom;)Ljava/lang/Object;
  Code:
   Stack=3, Locals=3, Args_size=3
	aload_0
	aload_1
	aload_2
	invokestatic	Method scala/collection/SeqLike$class.union:(Lscala/collection/SeqLike;Lscala/collection/Seq;Lscala/collection/generic/CanBuildFrom;)Ljava/lang/Object;
	areturn
  Labels:
  LocalVariableTable: 
   Start  Length  Slot  Name   Signature
   0      7      0    this       Lscala/collection/mutable/GenericArray;
   0      7      1    that       Lscala/collection/Seq;
   0      7      2    bf       Lscala/collection/generic/CanBuildFrom;


public boolean contains(java.lang.Object);
  Signature: (Ljava/lang/Object;)Z
  Code:
   Stack=2, Locals=2, Args_size=2
	aload_0
	aload_1
	invokestatic	Method scala/collection/SeqLike$class.contains:(Lscala/collection/SeqLike;Ljava/lang/Object;)Z
	ireturn
  Labels:
  LocalVariableTable: 
   Start  Length  Slot  Name   Signature
   0      6      0    this       Lscala/collection/mutable/GenericArray;
   0      6      1    elem       Ljava/lang/Object;


public boolean containsSlice(scala.collection.Seq);
  Signature: (Lscala/collection/Seq;)Z
  Code:
   Stack=2, Locals=2, Args_size=2
	aload_0
	aload_1
	invokestatic	Method scala/collection/SeqLike$class.containsSlice:(Lscala/collection/SeqLike;Lscala/collection/Seq;)Z
	ireturn
  Labels:
  LocalVariableTable: 
   Start  Length  Slot  Name   Signature
   0      6      0    this       Lscala/collection/mutable/GenericArray;
   0      6      1    that       Lscala/collection/Seq;


public int lastIndexOfSlice(scala.collection.Seq, int);
  Signature: (Lscala/collection/Seq;I)I
  Code:
   Stack=3, Locals=3, Args_size=3
	aload_0
	aload_1
	iload_2
	invokestatic	Method scala/collection/SeqLike$class.lastIndexOfSlice:(Lscala/collection/SeqLike;Lscala/collection/Seq;I)I
	ireturn
  Labels:
  LocalVariableTable: 
   Start  Length  Slot  Name   Signature
   0      7      0    this       Lscala/collection/mutable/GenericArray;
   0      7      1    that       Lscala/collection/Seq;
   0      7      2    end       I


public int lastIndexOfSlice(scala.collection.Seq);
  Signature: (Lscala/collection/Seq;)I
  Code:
   Stack=2, Locals=2, Args_size=2
	aload_0
	aload_1
	invokestatic	Method scala/collection/SeqLike$class.lastIndexOfSlice:(Lscala/collection/SeqLike;Lscala/collection/Seq;)I
	ireturn
  Labels:
  LocalVariableTable: 
   Start  Length  Slot  Name   Signature
   0      6      0    this       Lscala/collection/mutable/GenericArray;
   0      6      1    that       Lscala/collection/Seq;


public int indexOfSlice(scala.collection.Seq, int);
  Signature: (Lscala/collection/Seq;I)I
  Code:
   Stack=3, Locals=3, Args_size=3
	aload_0
	aload_1
	iload_2
	invokestatic	Method scala/collection/SeqLike$class.indexOfSlice:(Lscala/collection/SeqLike;Lscala/collection/Seq;I)I
	ireturn
  Labels:
  LocalVariableTable: 
   Start  Length  Slot  Name   Signature
   0      7      0    this       Lscala/collection/mutable/GenericArray;
   0      7      1    that       Lscala/collection/Seq;
   0      7      2    from       I


public int indexOfSlice(scala.collection.Seq);
  Signature: (Lscala/collection/Seq;)I
  Code:
   Stack=2, Locals=2, Args_size=2
	aload_0
	aload_1
	invokestatic	Method scala/collection/SeqLike$class.indexOfSlice:(Lscala/collection/SeqLike;Lscala/collection/Seq;)I
	ireturn
  Labels:
  LocalVariableTable: 
   Start  Length  Slot  Name   Signature
   0      6      0    this       Lscala/collection/mutable/GenericArray;
   0      6      1    that       Lscala/collection/Seq;


public boolean startsWith(scala.collection.Seq);
  Signature: (Lscala/collection/Seq;)Z
  Code:
   Stack=2, Locals=2, Args_size=2
	aload_0
	aload_1
	invokestatic	Method scala/collection/SeqLike$class.startsWith:(Lscala/collection/SeqLike;Lscala/collection/Seq;)Z
	ireturn
  Labels:
  LocalVariableTable: 
   Start  Length  Slot  Name   Signature
   0      6      0    this       Lscala/collection/mutable/GenericArray;
   0      6      1    that       Lscala/collection/Seq;


public scala.collection.Iterator reversedElements();
  Signature: ()Lscala/collection/Iterator;
  Code:
   Stack=1, Locals=1, Args_size=1
	aload_0
	invokestatic	Method scala/collection/SeqLike$class.reversedElements:(Lscala/collection/SeqLike;)Lscala/collection/Iterator;
	areturn
  Labels:
  Deprecated: true

public java.lang.Object reverseMap(scala.Function1, scala.collection.generic.CanBuildFrom);
  Signature: (Lscala/Function1;Lscala/collection/generic/CanBuildFrom;)Ljava/lang/Object;
  Code:
   Stack=3, Locals=3, Args_size=3
	aload_0
	aload_1
	aload_2
	invokestatic	Method scala/collection/SeqLike$class.reverseMap:(Lscala/collection/SeqLike;Lscala/Function1;Lscala/collection/generic/CanBuildFrom;)Ljava/lang/Object;
	areturn
  Labels:
  LocalVariableTable: 
   Start  Length  Slot  Name   Signature
   0      7      0    this       Lscala/collection/mutable/GenericArray;
   0      7      1    f       Lscala/Function1;
   0      7      2    bf       Lscala/collection/generic/CanBuildFrom;


public int lastIndexWhere(scala.Function1);
  Signature: (Lscala/Function1;)I
  Code:
   Stack=2, Locals=2, Args_size=2
	aload_0
	aload_1
	invokestatic	Method scala/collection/SeqLike$class.lastIndexWhere:(Lscala/collection/SeqLike;Lscala/Function1;)I
	ireturn
  Labels:
  LocalVariableTable: 
   Start  Length  Slot  Name   Signature
   0      6      0    this       Lscala/collection/mutable/GenericArray;
   0      6      1    p       Lscala/Function1;


public int lastIndexOf(java.lang.Object, int);
  Signature: (Ljava/lang/Object;I)I
  Code:
   Stack=3, Locals=3, Args_size=3
	aload_0
	aload_1
	iload_2
	invokestatic	Method scala/collection/SeqLike$class.lastIndexOf:(Lscala/collection/SeqLike;Ljava/lang/Object;I)I
	ireturn
  Labels:
  LocalVariableTable: 
   Start  Length  Slot  Name   Signature
   0      7      0    this       Lscala/collection/mutable/GenericArray;
   0      7      1    elem       Ljava/lang/Object;
   0      7      2    end       I


public int lastIndexOf(java.lang.Object);
  Signature: (Ljava/lang/Object;)I
  Code:
   Stack=2, Locals=2, Args_size=2
	aload_0
	aload_1
	invokestatic	Method scala/collection/SeqLike$class.lastIndexOf:(Lscala/collection/SeqLike;Ljava/lang/Object;)I
	ireturn
  Labels:
  LocalVariableTable: 
   Start  Length  Slot  Name   Signature
   0      6      0    this       Lscala/collection/mutable/GenericArray;
   0      6      1    elem       Ljava/lang/Object;


public int indexOf(java.lang.Object, int);
  Signature: (Ljava/lang/Object;I)I
  Code:
   Stack=3, Locals=3, Args_size=3
	aload_0
	aload_1
	iload_2
	invokestatic	Method scala/collection/SeqLike$class.indexOf:(Lscala/collection/SeqLike;Ljava/lang/Object;I)I
	ireturn
  Labels:
  LocalVariableTable: 
   Start  Length  Slot  Name   Signature
   0      7      0    this       Lscala/collection/mutable/GenericArray;
   0      7      1    elem       Ljava/lang/Object;
   0      7      2    from       I


public int indexOf(java.lang.Object);
  Signature: (Ljava/lang/Object;)I
  Code:
   Stack=2, Locals=2, Args_size=2
	aload_0
	aload_1
	invokestatic	Method scala/collection/SeqLike$class.indexOf:(Lscala/collection/SeqLike;Ljava/lang/Object;)I
	ireturn
  Labels:
  LocalVariableTable: 
   Start  Length  Slot  Name   Signature
   0      6      0    this       Lscala/collection/mutable/GenericArray;
   0      6      1    elem       Ljava/lang/Object;


public int findIndexOf(scala.Function1);
  Signature: (Lscala/Function1;)I
  Code:
   Stack=2, Locals=2, Args_size=2
	aload_0
	aload_1
	invokestatic	Method scala/collection/SeqLike$class.findIndexOf:(Lscala/collection/SeqLike;Lscala/Function1;)I
	ireturn
  Labels:
  LocalVariableTable: 
   Start  Length  Slot  Name   Signature
   0      6      0    this       Lscala/collection/mutable/GenericArray;
   0      6      1    p       Lscala/Function1;


public int indexWhere(scala.Function1);
  Signature: (Lscala/Function1;)I
  Code:
   Stack=2, Locals=2, Args_size=2
	aload_0
	aload_1
	invokestatic	Method scala/collection/SeqLike$class.indexWhere:(Lscala/collection/SeqLike;Lscala/Function1;)I
	ireturn
  Labels:
  LocalVariableTable: 
   Start  Length  Slot  Name   Signature
   0      6      0    this       Lscala/collection/mutable/GenericArray;
   0      6      1    p       Lscala/Function1;


public int prefixLength(scala.Function1);
  Signature: (Lscala/Function1;)I
  Code:
   Stack=2, Locals=2, Args_size=2
	aload_0
	aload_1
	invokestatic	Method scala/collection/SeqLike$class.prefixLength:(Lscala/collection/SeqLike;Lscala/Function1;)I
	ireturn
  Labels:
  LocalVariableTable: 
   Start  Length  Slot  Name   Signature
   0      6      0    this       Lscala/collection/mutable/GenericArray;
   0      6      1    p       Lscala/Function1;


public boolean isDefinedAt(int);
  Signature: (I)Z
  Code:
   Stack=2, Locals=2, Args_size=2
	aload_0
	iload_1
	invokestatic	Method scala/collection/SeqLike$class.isDefinedAt:(Lscala/collection/SeqLike;I)Z
	ireturn
  Labels:
  LocalVariableTable: 
   Start  Length  Slot  Name   Signature
   0      6      0    this       Lscala/collection/mutable/GenericArray;
   0      6      1    idx       I


public int size();
  Signature: ()I
  Code:
   Stack=1, Locals=1, Args_size=1
	aload_0
	invokestatic	Method scala/collection/SeqLike$class.size:(Lscala/collection/SeqLike;)I
	ireturn
  Labels:

public boolean endsWith(scala.collection.Seq);
  Signature: (Lscala/collection/Seq;)Z
  Code:
   Stack=2, Locals=2, Args_size=2
	aload_0
	aload_1
	invokestatic	Method scala/collection/IndexedSeqLike$class.endsWith:(Lscala/collection/IndexedSeqLike;Lscala/collection/Seq;)Z
	ireturn
  Labels:
  LocalVariableTable: 
   Start  Length  Slot  Name   Signature
   0      6      0    this       Lscala/collection/mutable/GenericArray;
   0      6      1    that       Lscala/collection/Seq;


public boolean startsWith(scala.collection.Seq, int);
  Signature: (Lscala/collection/Seq;I)Z
  Code:
   Stack=3, Locals=3, Args_size=3
	aload_0
	aload_1
	iload_2
	invokestatic	Method scala/collection/IndexedSeqLike$class.startsWith:(Lscala/collection/IndexedSeqLike;Lscala/collection/Seq;I)Z
	ireturn
  Labels:
  LocalVariableTable: 
   Start  Length  Slot  Name   Signature
   0      7      0    this       Lscala/collection/mutable/GenericArray;
   0      7      1    that       Lscala/collection/Seq;
   0      7      2    offset       I


public scala.collection.Iterator reverseIterator();
  Signature: ()Lscala/collection/Iterator;
  Code:
   Stack=1, Locals=1, Args_size=1
	aload_0
	invokestatic	Method scala/collection/IndexedSeqLike$class.reverseIterator:(Lscala/collection/IndexedSeqLike;)Lscala/collection/Iterator;
	areturn
  Labels:

public java.lang.Object reverse();
  Signature: ()Ljava/lang/Object;
  Code:
   Stack=1, Locals=1, Args_size=1
	aload_0
	invokestatic	Method scala/collection/IndexedSeqLike$class.reverse:(Lscala/collection/IndexedSeqLike;)Ljava/lang/Object;
	areturn
  Labels:

public int lastIndexWhere(scala.Function1, int);
  Signature: (Lscala/Function1;I)I
  Code:
   Stack=3, Locals=3, Args_size=3
	aload_0
	aload_1
	iload_2
	invokestatic	Method scala/collection/IndexedSeqLike$class.lastIndexWhere:(Lscala/collection/IndexedSeqLike;Lscala/Function1;I)I
	ireturn
  Labels:
  LocalVariableTable: 
   Start  Length  Slot  Name   Signature
   0      7      0    this       Lscala/collection/mutable/GenericArray;
   0      7      1    p       Lscala/Function1;
   0      7      2    end       I


public int indexWhere(scala.Function1, int);
  Signature: (Lscala/Function1;I)I
  Code:
   Stack=3, Locals=3, Args_size=3
	aload_0
	aload_1
	iload_2
	invokestatic	Method scala/collection/IndexedSeqLike$class.indexWhere:(Lscala/collection/IndexedSeqLike;Lscala/Function1;I)I
	ireturn
  Labels:
  LocalVariableTable: 
   Start  Length  Slot  Name   Signature
   0      7      0    this       Lscala/collection/mutable/GenericArray;
   0      7      1    p       Lscala/Function1;
   0      7      2    from       I


public int segmentLength(scala.Function1, int);
  Signature: (Lscala/Function1;I)I
  Code:
   Stack=3, Locals=3, Args_size=3
	aload_0
	aload_1
	iload_2
	invokestatic	Method scala/collection/IndexedSeqLike$class.segmentLength:(Lscala/collection/IndexedSeqLike;Lscala/Function1;I)I
	ireturn
  Labels:
  LocalVariableTable: 
   Start  Length  Slot  Name   Signature
   0      7      0    this       Lscala/collection/mutable/GenericArray;
   0      7      1    p       Lscala/Function1;
   0      7      2    from       I


public int lengthCompare(int);
  Signature: (I)I
  Code:
   Stack=2, Locals=2, Args_size=2
	aload_0
	iload_1
	invokestatic	Method scala/collection/IndexedSeqLike$class.lengthCompare:(Lscala/collection/IndexedSeqLike;I)I
	ireturn
  Labels:
  LocalVariableTable: 
   Start  Length  Slot  Name   Signature
   0      6      0    this       Lscala/collection/mutable/GenericArray;
   0      6      1    len       I


public boolean sameElements(scala.collection.Iterable);
  Signature: (Lscala/collection/Iterable;)Z
  Code:
   Stack=2, Locals=2, Args_size=2
	aload_0
	aload_1
	invokestatic	Method scala/collection/IndexedSeqLike$class.sameElements:(Lscala/collection/IndexedSeqLike;Lscala/collection/Iterable;)Z
	ireturn
  Labels:
  LocalVariableTable: 
   Start  Length  Slot  Name   Signature
   0      6      0    this       Lscala/collection/mutable/GenericArray;
   0      6      1    that       Lscala/collection/Iterable;


public scala.Tuple2 span(scala.Function1);
  Signature: (Lscala/Function1;)Lscala/Tuple2;
  Code:
   Stack=2, Locals=2, Args_size=2
	aload_0
	aload_1
	invokestatic	Method scala/collection/IndexedSeqLike$class.span:(Lscala/collection/IndexedSeqLike;Lscala/Function1;)Lscala/Tuple2;
	areturn
  Labels:
  LocalVariableTable: 
   Start  Length  Slot  Name   Signature
   0      6      0    this       Lscala/collection/mutable/GenericArray;
   0      6      1    p       Lscala/Function1;


public java.lang.Object dropWhile(scala.Function1);
  Signature: (Lscala/Function1;)Ljava/lang/Object;
  Code:
   Stack=2, Locals=2, Args_size=2
	aload_0
	aload_1
	invokestatic	Method scala/collection/IndexedSeqLike$class.dropWhile:(Lscala/collection/IndexedSeqLike;Lscala/Function1;)Ljava/lang/Object;
	areturn
  Labels:
  LocalVariableTable: 
   Start  Length  Slot  Name   Signature
   0      6      0    this       Lscala/collection/mutable/GenericArray;
   0      6      1    p       Lscala/Function1;


public java.lang.Object takeWhile(scala.Function1);
  Signature: (Lscala/Function1;)Ljava/lang/Object;
  Code:
   Stack=2, Locals=2, Args_size=2
	aload_0
	aload_1
	invokestatic	Method scala/collection/IndexedSeqLike$class.takeWhile:(Lscala/collection/IndexedSeqLike;Lscala/Function1;)Ljava/lang/Object;
	areturn
  Labels:
  LocalVariableTable: 
   Start  Length  Slot  Name   Signature
   0      6      0    this       Lscala/collection/mutable/GenericArray;
   0      6      1    p       Lscala/Function1;


public scala.Tuple2 splitAt(int);
  Signature: (I)Lscala/Tuple2;
  Code:
   Stack=2, Locals=2, Args_size=2
	aload_0
	iload_1
	invokestatic	Method scala/collection/IndexedSeqLike$class.splitAt:(Lscala/collection/IndexedSeqLike;I)Lscala/Tuple2;
	areturn
  Labels:
  LocalVariableTable: 
   Start  Length  Slot  Name   Signature
   0      6      0    this       Lscala/collection/mutable/GenericArray;
   0      6      1    n       I


public java.lang.Object dropRight(int);
  Signature: (I)Ljava/lang/Object;
  Code:
   Stack=2, Locals=2, Args_size=2
	aload_0
	iload_1
	invokestatic	Method scala/collection/IndexedSeqLike$class.dropRight:(Lscala/collection/IndexedSeqLike;I)Ljava/lang/Object;
	areturn
  Labels:
  LocalVariableTable: 
   Start  Length  Slot  Name   Signature
   0      6      0    this       Lscala/collection/mutable/GenericArray;
   0      6      1    n       I


public java.lang.Object takeRight(int);
  Signature: (I)Ljava/lang/Object;
  Code:
   Stack=2, Locals=2, Args_size=2
	aload_0
	iload_1
	invokestatic	Method scala/collection/IndexedSeqLike$class.takeRight:(Lscala/collection/IndexedSeqLike;I)Ljava/lang/Object;
	areturn
  Labels:
  LocalVariableTable: 
   Start  Length  Slot  Name   Signature
   0      6      0    this       Lscala/collection/mutable/GenericArray;
   0      6      1    n       I


public java.lang.Object drop(int);
  Signature: (I)Ljava/lang/Object;
  Code:
   Stack=2, Locals=2, Args_size=2
	aload_0
	iload_1
	invokestatic	Method scala/collection/IndexedSeqLike$class.drop:(Lscala/collection/IndexedSeqLike;I)Ljava/lang/Object;
	areturn
  Labels:
  LocalVariableTable: 
   Start  Length  Slot  Name   Signature
   0      6      0    this       Lscala/collection/mutable/GenericArray;
   0      6      1    n       I


public java.lang.Object take(int);
  Signature: (I)Ljava/lang/Object;
  Code:
   Stack=2, Locals=2, Args_size=2
	aload_0
	iload_1
	invokestatic	Method scala/collection/IndexedSeqLike$class.take:(Lscala/collection/IndexedSeqLike;I)Ljava/lang/Object;
	areturn
  Labels:
  LocalVariableTable: 
   Start  Length  Slot  Name   Signature
   0      6      0    this       Lscala/collection/mutable/GenericArray;
   0      6      1    n       I


public java.lang.Object init();
  Signature: ()Ljava/lang/Object;
  Code:
   Stack=1, Locals=1, Args_size=1
	aload_0
	invokestatic	Method scala/collection/IndexedSeqLike$class.init:(Lscala/collection/IndexedSeqLike;)Ljava/lang/Object;
	areturn
  Labels:

public java.lang.Object last();
  Signature: ()Ljava/lang/Object;
  Code:
   Stack=1, Locals=1, Args_size=1
	aload_0
	invokestatic	Method scala/collection/IndexedSeqLike$class.last:(Lscala/collection/IndexedSeqLike;)Ljava/lang/Object;
	areturn
  Labels:

public java.lang.Object tail();
  Signature: ()Ljava/lang/Object;
  Code:
   Stack=1, Locals=1, Args_size=1
	aload_0
	invokestatic	Method scala/collection/IndexedSeqLike$class.tail:(Lscala/collection/IndexedSeqLike;)Ljava/lang/Object;
	areturn
  Labels:

public java.lang.Object head();
  Signature: ()Ljava/lang/Object;
  Code:
   Stack=1, Locals=1, Args_size=1
	aload_0
	invokestatic	Method scala/collection/IndexedSeqLike$class.head:(Lscala/collection/IndexedSeqLike;)Ljava/lang/Object;
	areturn
  Labels:

public java.lang.Object slice(int, int);
  Signature: (II)Ljava/lang/Object;
  Code:
   Stack=3, Locals=3, Args_size=3
	aload_0
	iload_1
	iload_2
	invokestatic	Method scala/collection/IndexedSeqLike$class.slice:(Lscala/collection/IndexedSeqLike;II)Ljava/lang/Object;
	areturn
  Labels:
  LocalVariableTable: 
   Start  Length  Slot  Name   Signature
   0      7      0    this       Lscala/collection/mutable/GenericArray;
   0      7      1    from       I
   0      7      2    until       I


public java.lang.Object zipWithIndex(scala.collection.generic.CanBuildFrom);
  Signature: (Lscala/collection/generic/CanBuildFrom;)Ljava/lang/Object;
  Code:
   Stack=2, Locals=2, Args_size=2
	aload_0
	aload_1
	invokestatic	Method scala/collection/IndexedSeqLike$class.zipWithIndex:(Lscala/collection/IndexedSeqLike;Lscala/collection/generic/CanBuildFrom;)Ljava/lang/Object;
	areturn
  Labels:
  LocalVariableTable: 
   Start  Length  Slot  Name   Signature
   0      6      0    this       Lscala/collection/mutable/GenericArray;
   0      6      1    bf       Lscala/collection/generic/CanBuildFrom;


public java.lang.Object zip(scala.collection.Iterable, scala.collection.generic.CanBuildFrom);
  Signature: (Lscala/collection/Iterable;Lscala/collection/generic/CanBuildFrom;)Ljava/lang/Object;
  Code:
   Stack=3, Locals=3, Args_size=3
	aload_0
	aload_1
	aload_2
	invokestatic	Method scala/collection/IndexedSeqLike$class.zip:(Lscala/collection/IndexedSeqLike;Lscala/collection/Iterable;Lscala/collection/generic/CanBuildFrom;)Ljava/lang/Object;
	areturn
  Labels:
  LocalVariableTable: 
   Start  Length  Slot  Name   Signature
   0      7      0    this       Lscala/collection/mutable/GenericArray;
   0      7      1    that       Lscala/collection/Iterable;
   0      7      2    bf       Lscala/collection/generic/CanBuildFrom;


public java.lang.Object reduceRight(scala.Function2);
  Signature: (Lscala/Function2;)Ljava/lang/Object;
  Code:
   Stack=2, Locals=2, Args_size=2
	aload_0
	aload_1
	invokestatic	Method scala/collection/IndexedSeqLike$class.reduceRight:(Lscala/collection/IndexedSeqLike;Lscala/Function2;)Ljava/lang/Object;
	areturn
  Labels:
  LocalVariableTable: 
   Start  Length  Slot  Name   Signature
   0      6      0    this       Lscala/collection/mutable/GenericArray;
   0      6      1    op       Lscala/Function2;


public java.lang.Object reduceLeft(scala.Function2);
  Signature: (Lscala/Function2;)Ljava/lang/Object;
  Code:
   Stack=2, Locals=2, Args_size=2
	aload_0
	aload_1
	invokestatic	Method scala/collection/IndexedSeqLike$class.reduceLeft:(Lscala/collection/IndexedSeqLike;Lscala/Function2;)Ljava/lang/Object;
	areturn
  Labels:
  LocalVariableTable: 
   Start  Length  Slot  Name   Signature
   0      6      0    this       Lscala/collection/mutable/GenericArray;
   0      6      1    op       Lscala/Function2;


public java.lang.Object foldRight(java.lang.Object, scala.Function2);
  Signature: (Ljava/lang/Object;Lscala/Function2;)Ljava/lang/Object;
  Code:
   Stack=3, Locals=3, Args_size=3
	aload_0
	aload_1
	aload_2
	invokestatic	Method scala/collection/IndexedSeqLike$class.foldRight:(Lscala/collection/IndexedSeqLike;Ljava/lang/Object;Lscala/Function2;)Ljava/lang/Object;
	areturn
  Labels:
  LocalVariableTable: 
   Start  Length  Slot  Name   Signature
   0      7      0    this       Lscala/collection/mutable/GenericArray;
   0      7      1    z       Ljava/lang/Object;
   0      7      2    op       Lscala/Function2;


public java.lang.Object foldLeft(java.lang.Object, scala.Function2);
  Signature: (Ljava/lang/Object;Lscala/Function2;)Ljava/lang/Object;
  Code:
   Stack=3, Locals=3, Args_size=3
	aload_0
	aload_1
	aload_2
	invokestatic	Method scala/collection/IndexedSeqLike$class.foldLeft:(Lscala/collection/IndexedSeqLike;Ljava/lang/Object;Lscala/Function2;)Ljava/lang/Object;
	areturn
  Labels:
  LocalVariableTable: 
   Start  Length  Slot  Name   Signature
   0      7      0    this       Lscala/collection/mutable/GenericArray;
   0      7      1    z       Ljava/lang/Object;
   0      7      2    op       Lscala/Function2;


public scala.Option find(scala.Function1);
  Signature: (Lscala/Function1;)Lscala/Option;
  Code:
   Stack=2, Locals=2, Args_size=2
	aload_0
	aload_1
	invokestatic	Method scala/collection/IndexedSeqLike$class.find:(Lscala/collection/IndexedSeqLike;Lscala/Function1;)Lscala/Option;
	areturn
  Labels:
  LocalVariableTable: 
   Start  Length  Slot  Name   Signature
   0      6      0    this       Lscala/collection/mutable/GenericArray;
   0      6      1    p       Lscala/Function1;


public boolean exists(scala.Function1);
  Signature: (Lscala/Function1;)Z
  Code:
   Stack=2, Locals=2, Args_size=2
	aload_0
	aload_1
	invokestatic	Method scala/collection/IndexedSeqLike$class.exists:(Lscala/collection/IndexedSeqLike;Lscala/Function1;)Z
	ireturn
  Labels:
  LocalVariableTable: 
   Start  Length  Slot  Name   Signature
   0      6      0    this       Lscala/collection/mutable/GenericArray;
   0      6      1    p       Lscala/Function1;


public boolean forall(scala.Function1);
  Signature: (Lscala/Function1;)Z
  Code:
   Stack=2, Locals=2, Args_size=2
	aload_0
	aload_1
	invokestatic	Method scala/collection/IndexedSeqLike$class.forall:(Lscala/collection/IndexedSeqLike;Lscala/Function1;)Z
	ireturn
  Labels:
  LocalVariableTable: 
   Start  Length  Slot  Name   Signature
   0      6      0    this       Lscala/collection/mutable/GenericArray;
   0      6      1    p       Lscala/Function1;


public boolean isEmpty();
  Signature: ()Z
  Code:
   Stack=1, Locals=1, Args_size=1
	aload_0
	invokestatic	Method scala/collection/IndexedSeqLike$class.isEmpty:(Lscala/collection/IndexedSeqLike;)Z
	ireturn
  Labels:

public scala.collection.Iterator iterator();
  Signature: ()Lscala/collection/Iterator;
  Code:
   Stack=1, Locals=1, Args_size=1
	aload_0
	invokestatic	Method scala/collection/IndexedSeqLike$class.iterator:(Lscala/collection/IndexedSeqLike;)Lscala/collection/Iterator;
	areturn
  Labels:

public final boolean scala$collection$IndexedSeqLike$$super$endsWith(scala.collection.Seq);
  Signature: (Lscala/collection/Seq;)Z
  Code:
   Stack=2, Locals=2, Args_size=2
	aload_0
	aload_1
	invokestatic	Method scala/collection/SeqLike$class.endsWith:(Lscala/collection/SeqLike;Lscala/collection/Seq;)Z
	ireturn
  Labels:
  LocalVariableTable: 
   Start  Length  Slot  Name   Signature
   0      6      0    this       Lscala/collection/mutable/GenericArray;
   0      6      1    that       Lscala/collection/Seq;


public final boolean scala$collection$IndexedSeqLike$$super$sameElements(scala.collection.Iterable);
  Signature: (Lscala/collection/Iterable;)Z
  Code:
   Stack=2, Locals=2, Args_size=2
	aload_0
	aload_1
	invokestatic	Method scala/collection/IterableLike$class.sameElements:(Lscala/collection/IterableLike;Lscala/collection/Iterable;)Z
	ireturn
  Labels:
  LocalVariableTable: 
   Start  Length  Slot  Name   Signature
   0      6      0    this       Lscala/collection/mutable/GenericArray;
   0      6      1    that       Lscala/collection/Iterable;


public final java.lang.Object scala$collection$IndexedSeqLike$$super$init();
  Signature: ()Ljava/lang/Object;
  Code:
   Stack=1, Locals=1, Args_size=1
	aload_0
	invokestatic	Method scala/collection/TraversableLike$class.init:(Lscala/collection/TraversableLike;)Ljava/lang/Object;
	areturn
  Labels:

public final java.lang.Object scala$collection$IndexedSeqLike$$super$last();
  Signature: ()Ljava/lang/Object;
  Code:
   Stack=1, Locals=1, Args_size=1
	aload_0
	invokestatic	Method scala/collection/TraversableLike$class.last:(Lscala/collection/TraversableLike;)Ljava/lang/Object;
	areturn
  Labels:

public final java.lang.Object scala$collection$IndexedSeqLike$$super$tail();
  Signature: ()Ljava/lang/Object;
  Code:
   Stack=1, Locals=1, Args_size=1
	aload_0
	invokestatic	Method scala/collection/TraversableLike$class.tail:(Lscala/collection/TraversableLike;)Ljava/lang/Object;
	areturn
  Labels:

public final java.lang.Object scala$collection$IndexedSeqLike$$super$head();
  Signature: ()Ljava/lang/Object;
  Code:
   Stack=1, Locals=1, Args_size=1
	aload_0
	invokestatic	Method scala/collection/IterableLike$class.head:(Lscala/collection/IterableLike;)Ljava/lang/Object;
	areturn
  Labels:

public final java.lang.Object scala$collection$IndexedSeqLike$$super$zip(scala.collection.Iterable, scala.collection.generic.CanBuildFrom);
  Signature: (Lscala/collection/Iterable;Lscala/collection/generic/CanBuildFrom;)Ljava/lang/Object;
  Code:
   Stack=3, Locals=3, Args_size=3
	aload_0
	aload_1
	aload_2
	invokestatic	Method scala/collection/IterableLike$class.zip:(Lscala/collection/IterableLike;Lscala/collection/Iterable;Lscala/collection/generic/CanBuildFrom;)Ljava/lang/Object;
	areturn
  Labels:
  LocalVariableTable: 
   Start  Length  Slot  Name   Signature
   0      7      0    this       Lscala/collection/mutable/GenericArray;
   0      7      1    that       Lscala/collection/Iterable;
   0      7      2    bf       Lscala/collection/generic/CanBuildFrom;


public final java.lang.Object scala$collection$IndexedSeqLike$$super$reduceRight(scala.Function2);
  Signature: (Lscala/Function2;)Ljava/lang/Object;
  Code:
   Stack=2, Locals=2, Args_size=2
	aload_0
	aload_1
	invokestatic	Method scala/collection/IterableLike$class.reduceRight:(Lscala/collection/IterableLike;Lscala/Function2;)Ljava/lang/Object;
	areturn
  Labels:
  LocalVariableTable: 
   Start  Length  Slot  Name   Signature
   0      6      0    this       Lscala/collection/mutable/GenericArray;
   0      6      1    op       Lscala/Function2;


public final java.lang.Object scala$collection$IndexedSeqLike$$super$reduceLeft(scala.Function2);
  Signature: (Lscala/Function2;)Ljava/lang/Object;
  Code:
   Stack=2, Locals=2, Args_size=2
	aload_0
	aload_1
	invokestatic	Method scala/collection/TraversableLike$class.reduceLeft:(Lscala/collection/TraversableLike;Lscala/Function2;)Ljava/lang/Object;
	areturn
  Labels:
  LocalVariableTable: 
   Start  Length  Slot  Name   Signature
   0      6      0    this       Lscala/collection/mutable/GenericArray;
   0      6      1    op       Lscala/Function2;


public scala.collection.mutable.IndexedSeqView view(int, int);
  Signature: (II)Lscala/collection/mutable/IndexedSeqView;
  Code:
   Stack=3, Locals=3, Args_size=3
	aload_0
	iload_1
	iload_2
	invokestatic	Method scala/collection/mutable/IndexedSeqLike$class.view:(Lscala/collection/mutable/IndexedSeqLike;II)Lscala/collection/mutable/IndexedSeqView;
	areturn
  Labels:
  LocalVariableTable: 
   Start  Length  Slot  Name   Signature
   0      7      0    this       Lscala/collection/mutable/GenericArray;
   0      7      1    from       I
   0      7      2    until       I


public scala.collection.mutable.IndexedSeqView view();
  Signature: ()Lscala/collection/mutable/IndexedSeqView;
  Code:
   Stack=1, Locals=1, Args_size=1
	aload_0
	invokestatic	Method scala/collection/mutable/IndexedSeqLike$class.view:(Lscala/collection/mutable/IndexedSeqLike;)Lscala/collection/mutable/IndexedSeqView;
	areturn
  Labels:

public scala.collection.mutable.IndexedSeq toCollection(java.lang.Object);
  Signature: (Ljava/lang/Object;)Lscala/collection/mutable/IndexedSeq;
  Code:
   Stack=2, Locals=2, Args_size=2
	aload_0
	aload_1
	invokestatic	Method scala/collection/mutable/IndexedSeqLike$class.toCollection:(Lscala/collection/mutable/IndexedSeqLike;Ljava/lang/Object;)Lscala/collection/mutable/IndexedSeq;
	areturn
  Labels:
  LocalVariableTable: 
   Start  Length  Slot  Name   Signature
   0      6      0    this       Lscala/collection/mutable/GenericArray;
   0      6      1    repr       Ljava/lang/Object;


public scala.collection.mutable.IndexedSeq thisCollection();
  Signature: ()Lscala/collection/mutable/IndexedSeq;
  Code:
   Stack=1, Locals=1, Args_size=1
	aload_0
	invokestatic	Method scala/collection/mutable/IndexedSeqLike$class.thisCollection:(Lscala/collection/mutable/IndexedSeqLike;)Lscala/collection/mutable/IndexedSeq;
	areturn
  Labels:

}

