Compiled from "HashMap.scala"
public final class scala.collection.mutable.HashMap$$anonfun$foreach$1 extends scala.runtime.AbstractFunction1 implements java.io.Serializable
  SourceFile: "HashMap.scala"
  Scala: length = 0x
   
  InnerClass: 
   public final $anonfun$foreach$1=class scala/collection/mutable/HashMap$$anonfun$foreach$1 of class scala/collection/mutable/HashMap
  minor version: 0
  major version: 49
  Constant pool:
Asciz	SourceFile;
Asciz	HashMap.scala;
Asciz	<clinit>;
Asciz	()V;
Asciz	Code;
Asciz	serialVersionUID;
Asciz	J;
Asciz	scala/collection/mutable/HashMap$$anonfun$foreach$1;
class	scala/collection/mutable/HashMap$$anonfun$foreach$1
NameAndType	serialVersionUID:J
Field	scala/collection/mutable/HashMap$$anonfun$foreach$1.serialVersionUID:J
Asciz	f$1;
Asciz	Lscala/Function1;;
Asciz	<init>;
Asciz	(Lscala/collection/mutable/HashMap;Lscala/Function1;)V;
Asciz	LineNumberTable;
NameAndType	f$1:Lscala/Function1;
Field	scala/collection/mutable/HashMap$$anonfun$foreach$1.f$1:Lscala/Function1;
Asciz	scala/runtime/AbstractFunction1;
class	scala/runtime/AbstractFunction1
NameAndType	"<init>":()V
Method	scala/runtime/AbstractFunction1."<init>":()V
Asciz	this;
Asciz	Lscala/collection/mutable/HashMap$$anonfun$foreach$1;;
Asciz	$outer;
Asciz	Lscala/collection/mutable/HashMap;;
Asciz	LocalVariableTable;
Asciz	(Lscala/collection/mutable/HashMap<TA;TB;>;)V;
Asciz	Signature;
Asciz	apply;
Asciz	(Ljava/lang/Object;)Ljava/lang/Object;;
Asciz	scala/collection/mutable/DefaultEntry;
class	scala/collection/mutable/DefaultEntry
Asciz	(Lscala/collection/mutable/DefaultEntry;)Ljava/lang/Object;;
NameAndType	apply:(Lscala/collection/mutable/DefaultEntry;)Ljava/lang/Object;
Method	scala/collection/mutable/HashMap$$anonfun$foreach$1.apply:(Lscala/collection/mutable/DefaultEntry;)Ljava/lang/Object;
Asciz	v1;
Asciz	Ljava/lang/Object;;
Asciz	scala/Tuple2;
class	scala/Tuple2
Asciz	key;
Asciz	()Ljava/lang/Object;;
NameAndType	key:()Ljava/lang/Object;
Method	scala/collection/mutable/DefaultEntry.key:()Ljava/lang/Object;
Asciz	value;
NameAndType	value:()Ljava/lang/Object;
Method	scala/collection/mutable/DefaultEntry.value:()Ljava/lang/Object;
Asciz	(Ljava/lang/Object;Ljava/lang/Object;)V;
NameAndType	"<init>":(Ljava/lang/Object;Ljava/lang/Object;)V
Method	scala/Tuple2."<init>":(Ljava/lang/Object;Ljava/lang/Object;)V
Asciz	scala/Function1;
class	scala/Function1
NameAndType	apply:(Ljava/lang/Object;)Ljava/lang/Object;
InterfaceMethod	scala/Function1.apply:(Ljava/lang/Object;)Ljava/lang/Object;
Asciz	e;
Asciz	Lscala/collection/mutable/DefaultEntry;;
Asciz	(Lscala/collection/mutable/DefaultEntry<TA;TB;>;)TC;;
Asciz	Scala;
Asciz	InnerClasses;
Asciz	scala/collection/mutable/HashMap;
class	scala/collection/mutable/HashMap
Asciz	$anonfun$foreach$1;
Asciz	java/io/Serializable;
class	java/io/Serializable

{
public static final long serialVersionUID;
  Signature: J

private final scala.Function1 f$1;
  Signature: Lscala/Function1;

public static {};
  Signature: ()V
  Code:
   Stack=2, Locals=0, Args_size=0
	lconst_0
	putstatic	Field serialVersionUID:J
	return
  Labels:

public scala.collection.mutable.HashMap$$anonfun$foreach$1(scala.collection.mutable.HashMap, scala.Function1);
  Signature: (Lscala/collection/mutable/HashMap;Lscala/Function1;)V
  Code:
   Stack=2, Locals=3, Args_size=3
	aload_0
	aload_2
	putfield	Field f$1:Lscala/Function1;
	aload_0
	invokespecial	Method scala/runtime/AbstractFunction1."<init>":()V
	return
  Labels:
  LocalVariableTable: 
   Start  Length  Slot  Name   Signature
   0      10      0    this       Lscala/collection/mutable/HashMap$$anonfun$foreach$1;
   0      10      1    $outer       Lscala/collection/mutable/HashMap;

  Signature: length = 0x2
   00 1C 

public final java.lang.Object apply(java.lang.Object);
  Signature: (Ljava/lang/Object;)Ljava/lang/Object;
  Code:
   Stack=2, Locals=2, Args_size=2
	aload_0
	aload_1
	checkcast	class scala/collection/mutable/DefaultEntry
	invokevirtual	Method apply:(Lscala/collection/mutable/DefaultEntry;)Ljava/lang/Object;
	areturn
  Labels:
  LocalVariableTable: 
   Start  Length  Slot  Name   Signature
   0      9      0    this       Lscala/collection/mutable/HashMap$$anonfun$foreach$1;
   0      9      1    v1       Ljava/lang/Object;


public final java.lang.Object apply(scala.collection.mutable.DefaultEntry);
  Signature: (Lscala/collection/mutable/DefaultEntry;)Ljava/lang/Object;
  Code:
   Stack=5, Locals=2, Args_size=2
	aload_0
	getfield	Field f$1:Lscala/Function1;
	new	class scala/Tuple2
	dup
	aload_1
	invokevirtual	Method scala/collection/mutable/DefaultEntry.key:()Ljava/lang/Object;
	aload_1
	invokevirtual	Method scala/collection/mutable/DefaultEntry.value:()Ljava/lang/Object;
	invokespecial	Method scala/Tuple2."<init>":(Ljava/lang/Object;Ljava/lang/Object;)V
	invokeinterface	InterfaceMethod scala/Function1.apply:(Ljava/lang/Object;)Ljava/lang/Object;
	areturn
  Labels:
  LocalVariableTable: 
   Start  Length  Slot  Name   Signature
   0      25      0    this       Lscala/collection/mutable/HashMap$$anonfun$foreach$1;
   0      25      1    e       Lscala/collection/mutable/DefaultEntry;

  Signature: length = 0x2
   00 39 

}

