Compiled from "HashMap.scala"
public final class scala.collection.mutable.HashMap$$anon$1$$anonfun$foreach$2 extends java.lang.Object implements scala.Function1,scala.ScalaObject,java.io.Serializable
  SourceFile: "HashMap.scala"
  Scala: length = 0x
   
  InnerClass: 
   public final $anon$1=class scala/collection/mutable/HashMap$$anon$1 of class scala/collection/mutable/HashMap
   public final $anonfun$foreach$2=class scala/collection/mutable/HashMap$$anon$1$$anonfun$foreach$2 of class scala/collection/mutable/HashMap$$anon$1
  minor version: 0
  major version: 49
  Constant pool:
Asciz	SourceFile;
Asciz	HashMap.scala;
Asciz	<clinit>;
Asciz	()V;
Asciz	Code;
Asciz	serialVersionUID;
Asciz	J;
Asciz	scala/collection/mutable/HashMap$$anon$1$$anonfun$foreach$2;
class	scala/collection/mutable/HashMap$$anon$1$$anonfun$foreach$2
NameAndType	serialVersionUID:J
Field	scala/collection/mutable/HashMap$$anon$1$$anonfun$foreach$2.serialVersionUID:J
Asciz	f$2;
Asciz	Lscala/Function1;;
Asciz	<init>;
Asciz	(Lscala/collection/mutable/HashMap$$anon$1;Lscala/Function1;)V;
Asciz	LineNumberTable;
NameAndType	f$2:Lscala/Function1;
Field	scala/collection/mutable/HashMap$$anon$1$$anonfun$foreach$2.f$2:Lscala/Function1;
Asciz	java/lang/Object;
class	java/lang/Object
NameAndType	"<init>":()V
Method	java/lang/Object."<init>":()V
Asciz	scala/Function1$class;
class	scala/Function1$class
Asciz	$init$;
Asciz	(Lscala/Function1;)V;
NameAndType	$init$:(Lscala/Function1;)V
Method	scala/Function1$class.$init$:(Lscala/Function1;)V
Asciz	this;
Asciz	Lscala/collection/mutable/HashMap$$anon$1$$anonfun$foreach$2;;
Asciz	$outer;
Asciz	Lscala/collection/mutable/HashMap$$anon$1;;
Asciz	LocalVariableTable;
Asciz	(Lscala/collection/mutable/HashMap<TA;TB;>.$anon$1;)V;
Asciz	Signature;
Asciz	apply;
Asciz	(Ljava/lang/Object;)Ljava/lang/Object;;
Asciz	scala/collection/mutable/DefaultEntry;
class	scala/collection/mutable/DefaultEntry
Asciz	(Lscala/collection/mutable/DefaultEntry;)Ljava/lang/Object;;
NameAndType	apply:(Lscala/collection/mutable/DefaultEntry;)Ljava/lang/Object;
Method	scala/collection/mutable/HashMap$$anon$1$$anonfun$foreach$2.apply:(Lscala/collection/mutable/DefaultEntry;)Ljava/lang/Object;
Asciz	v1;
Asciz	Ljava/lang/Object;;
Asciz	key;
Asciz	()Ljava/lang/Object;;
NameAndType	key:()Ljava/lang/Object;
Method	scala/collection/mutable/DefaultEntry.key:()Ljava/lang/Object;
Asciz	scala/Function1;
class	scala/Function1
NameAndType	apply:(Ljava/lang/Object;)Ljava/lang/Object;
InterfaceMethod	scala/Function1.apply:(Ljava/lang/Object;)Ljava/lang/Object;
Asciz	e;
Asciz	Lscala/collection/mutable/DefaultEntry;;
Asciz	(Lscala/collection/mutable/DefaultEntry<TA;TB;>;)TC;;
Asciz	andThen;
Asciz	(Lscala/Function1;)Lscala/Function1;;
Asciz	(Lscala/Function1;Lscala/Function1;)Lscala/Function1;;
NameAndType	andThen:(Lscala/Function1;Lscala/Function1;)Lscala/Function1;
Method	scala/Function1$class.andThen:(Lscala/Function1;Lscala/Function1;)Lscala/Function1;
Asciz	g;
Asciz	compose;
NameAndType	compose:(Lscala/Function1;Lscala/Function1;)Lscala/Function1;
Method	scala/Function1$class.compose:(Lscala/Function1;Lscala/Function1;)Lscala/Function1;
Asciz	toString;
Asciz	()Ljava/lang/String;;
Asciz	(Lscala/Function1;)Ljava/lang/String;;
NameAndType	toString:(Lscala/Function1;)Ljava/lang/String;
Method	scala/Function1$class.toString:(Lscala/Function1;)Ljava/lang/String;
Asciz	Scala;
Asciz	InnerClasses;
Asciz	scala/collection/mutable/HashMap$$anon$1;
class	scala/collection/mutable/HashMap$$anon$1
Asciz	scala/collection/mutable/HashMap;
class	scala/collection/mutable/HashMap
Asciz	$anon$1;
Asciz	$anonfun$foreach$2;
Asciz	scala/ScalaObject;
class	scala/ScalaObject
Asciz	java/io/Serializable;
class	java/io/Serializable

{
public static final long serialVersionUID;
  Signature: J

private final scala.Function1 f$2;
  Signature: Lscala/Function1;

public static {};
  Signature: ()V
  Code:
   Stack=2, Locals=0, Args_size=0
	lconst_0
	putstatic	Field serialVersionUID:J
	return
  Labels:

public scala.collection.mutable.HashMap$$anon$1$$anonfun$foreach$2(scala.collection.mutable.HashMap$$anon$1, scala.Function1);
  Signature: (Lscala/collection/mutable/HashMap$$anon$1;Lscala/Function1;)V
  Code:
   Stack=2, Locals=3, Args_size=3
	aload_0
	aload_2
	putfield	Field f$2:Lscala/Function1;
	aload_0
	invokespecial	Method java/lang/Object."<init>":()V
	aload_0
	invokestatic	Method scala/Function1$class.$init$:(Lscala/Function1;)V
	return
  Labels:
  LocalVariableTable: 
   Start  Length  Slot  Name   Signature
   0      14      0    this       Lscala/collection/mutable/HashMap$$anon$1$$anonfun$foreach$2;
   0      14      1    $outer       Lscala/collection/mutable/HashMap$$anon$1;

  Signature: length = 0x2
   00 22 

public final java.lang.Object apply(java.lang.Object);
  Signature: (Ljava/lang/Object;)Ljava/lang/Object;
  Code:
   Stack=2, Locals=2, Args_size=2
	aload_0
	aload_1
	checkcast	class scala/collection/mutable/DefaultEntry
	invokevirtual	Method apply:(Lscala/collection/mutable/DefaultEntry;)Ljava/lang/Object;
	areturn
  Labels:
  LocalVariableTable: 
   Start  Length  Slot  Name   Signature
   0      9      0    this       Lscala/collection/mutable/HashMap$$anon$1$$anonfun$foreach$2;
   0      9      1    v1       Ljava/lang/Object;


public final java.lang.Object apply(scala.collection.mutable.DefaultEntry);
  Signature: (Lscala/collection/mutable/DefaultEntry;)Ljava/lang/Object;
  Code:
   Stack=2, Locals=2, Args_size=2
	aload_0
	getfield	Field f$2:Lscala/Function1;
	aload_1
	invokevirtual	Method scala/collection/mutable/DefaultEntry.key:()Ljava/lang/Object;
	invokeinterface	InterfaceMethod scala/Function1.apply:(Ljava/lang/Object;)Ljava/lang/Object;
	areturn
  Labels:
  LocalVariableTable: 
   Start  Length  Slot  Name   Signature
   0      14      0    this       Lscala/collection/mutable/HashMap$$anon$1$$anonfun$foreach$2;
   0      14      1    e       Lscala/collection/mutable/DefaultEntry;

  Signature: length = 0x2
   00 37 

public scala.Function1 andThen(scala.Function1);
  Signature: (Lscala/Function1;)Lscala/Function1;
  Code:
   Stack=2, Locals=2, Args_size=2
	aload_0
	aload_1
	invokestatic	Method scala/Function1$class.andThen:(Lscala/Function1;Lscala/Function1;)Lscala/Function1;
	areturn
  Labels:
  LocalVariableTable: 
   Start  Length  Slot  Name   Signature
   0      6      0    this       Lscala/collection/mutable/HashMap$$anon$1$$anonfun$foreach$2;
   0      6      1    g       Lscala/Function1;


public scala.Function1 compose(scala.Function1);
  Signature: (Lscala/Function1;)Lscala/Function1;
  Code:
   Stack=2, Locals=2, Args_size=2
	aload_0
	aload_1
	invokestatic	Method scala/Function1$class.compose:(Lscala/Function1;Lscala/Function1;)Lscala/Function1;
	areturn
  Labels:
  LocalVariableTable: 
   Start  Length  Slot  Name   Signature
   0      6      0    this       Lscala/collection/mutable/HashMap$$anon$1$$anonfun$foreach$2;
   0      6      1    g       Lscala/Function1;


public java.lang.String toString();
  Signature: ()Ljava/lang/String;
  Code:
   Stack=1, Locals=1, Args_size=1
	aload_0
	invokestatic	Method scala/Function1$class.toString:(Lscala/Function1;)Ljava/lang/String;
	areturn
  Labels:

}

