Compiled from "HashTable.scala"
public final class scala.collection.mutable.HashTable$$anonfun$serializeTo$1 extends scala.runtime.AbstractFunction1 implements java.io.Serializable
  SourceFile: "HashTable.scala"
  Scala: length = 0x
   
  InnerClass: 
   public final #69= #9 of #68; //$anonfun$serializeTo$1=class scala/collection/mutable/HashTable$$anonfun$serializeTo$1 of class scala/collection/mutable/HashTable
  minor version: 0
  major version: 49
  Constant pool:
const #1 = Asciz	SourceFile;
const #2 = Asciz	HashTable.scala;
const #3 = Asciz	<clinit>;
const #4 = Asciz	()V;
const #5 = Asciz	Code;
const #6 = Asciz	serialVersionUID;
const #7 = Asciz	J;
const #8 = Asciz	scala/collection/mutable/HashTable$$anonfun$serializeTo$1;
const #9 = class	#8;	//  scala/collection/mutable/HashTable$$anonfun$serializeTo$1
const #10 = NameAndType	#6:#7;//  serialVersionUID:J
const #11 = Field	#9.#10;	//  scala/collection/mutable/HashTable$$anonfun$serializeTo$1.serialVersionUID:J
const #12 = Asciz	value$1;
const #13 = Asciz	Lscala/Function1;;
const #14 = Asciz	out$1;
const #15 = Asciz	Ljava/io/ObjectOutputStream;;
const #16 = Asciz	<init>;
const #17 = Asciz	(Lscala/collection/mutable/HashTable;Ljava/io/ObjectOutputStream;Lscala/Function1;)V;
const #18 = Asciz	LineNumberTable;
const #19 = NameAndType	#14:#15;//  out$1:Ljava/io/ObjectOutputStream;
const #20 = Field	#9.#19;	//  scala/collection/mutable/HashTable$$anonfun$serializeTo$1.out$1:Ljava/io/ObjectOutputStream;
const #21 = NameAndType	#12:#13;//  value$1:Lscala/Function1;
const #22 = Field	#9.#21;	//  scala/collection/mutable/HashTable$$anonfun$serializeTo$1.value$1:Lscala/Function1;
const #23 = Asciz	scala/runtime/AbstractFunction1;
const #24 = class	#23;	//  scala/runtime/AbstractFunction1
const #25 = NameAndType	#16:#4;//  "<init>":()V
const #26 = Method	#24.#25;	//  scala/runtime/AbstractFunction1."<init>":()V
const #27 = Asciz	this;
const #28 = Asciz	Lscala/collection/mutable/HashTable$$anonfun$serializeTo$1;;
const #29 = Asciz	$outer;
const #30 = Asciz	Lscala/collection/mutable/HashTable;;
const #31 = Asciz	LocalVariableTable;
const #32 = Asciz	(Lscala/collection/mutable/HashTable<TA;>;)V;
const #33 = Asciz	Signature;
const #34 = Asciz	apply;
const #35 = Asciz	(Ljava/lang/Object;)Ljava/lang/Object;;
const #36 = Asciz	scala/collection/mutable/HashEntry;
const #37 = class	#36;	//  scala/collection/mutable/HashEntry
const #38 = Asciz	(Lscala/collection/mutable/HashEntry;)V;
const #39 = NameAndType	#34:#38;//  apply:(Lscala/collection/mutable/HashEntry;)V
const #40 = Method	#9.#39;	//  scala/collection/mutable/HashTable$$anonfun$serializeTo$1.apply:(Lscala/collection/mutable/HashEntry;)V
const #41 = Asciz	scala/runtime/BoxedUnit;
const #42 = class	#41;	//  scala/runtime/BoxedUnit
const #43 = Asciz	UNIT;
const #44 = Asciz	Lscala/runtime/BoxedUnit;;
const #45 = NameAndType	#43:#44;//  UNIT:Lscala/runtime/BoxedUnit;
const #46 = Field	#42.#45;	//  scala/runtime/BoxedUnit.UNIT:Lscala/runtime/BoxedUnit;
const #47 = Asciz	v1;
const #48 = Asciz	Ljava/lang/Object;;
const #49 = Asciz	key;
const #50 = Asciz	()Ljava/lang/Object;;
const #51 = NameAndType	#49:#50;//  key:()Ljava/lang/Object;
const #52 = InterfaceMethod	#37.#51;	//  scala/collection/mutable/HashEntry.key:()Ljava/lang/Object;
const #53 = Asciz	java/io/ObjectOutputStream;
const #54 = class	#53;	//  java/io/ObjectOutputStream
const #55 = Asciz	writeObject;
const #56 = Asciz	(Ljava/lang/Object;)V;
const #57 = NameAndType	#55:#56;//  writeObject:(Ljava/lang/Object;)V
const #58 = Method	#54.#57;	//  java/io/ObjectOutputStream.writeObject:(Ljava/lang/Object;)V
const #59 = Asciz	scala/Function1;
const #60 = class	#59;	//  scala/Function1
const #61 = NameAndType	#34:#35;//  apply:(Ljava/lang/Object;)Ljava/lang/Object;
const #62 = InterfaceMethod	#60.#61;	//  scala/Function1.apply:(Ljava/lang/Object;)Ljava/lang/Object;
const #63 = Asciz	entry;
const #64 = Asciz	Lscala/collection/mutable/HashEntry;;
const #65 = Asciz	Scala;
const #66 = Asciz	InnerClasses;
const #67 = Asciz	scala/collection/mutable/HashTable;
const #68 = class	#67;	//  scala/collection/mutable/HashTable
const #69 = Asciz	$anonfun$serializeTo$1;
const #70 = Asciz	java/io/Serializable;
const #71 = class	#70;	//  java/io/Serializable

{
public static final long serialVersionUID;

public static {};
  Code:
   Stack=2, Locals=0, Args_size=0
   0:	lconst_0
   1:	putstatic	#11; //Field serialVersionUID:J
   4:	return

public scala.collection.mutable.HashTable$$anonfun$serializeTo$1(scala.collection.mutable.HashTable, java.io.ObjectOutputStream, scala.Function1);
  Code:
   Stack=2, Locals=4, Args_size=4
   0:	aload_0
   1:	aload_2
   2:	putfield	#20; //Field out$1:Ljava/io/ObjectOutputStream;
   5:	aload_0
   6:	aload_3
   7:	putfield	#22; //Field value$1:Lscala/Function1;
   10:	aload_0
   11:	invokespecial	#26; //Method scala/runtime/AbstractFunction1."<init>":()V
   14:	return
  LineNumberTable: 
   line 103: 0

  LocalVariableTable: 
   Start  Length  Slot  Name   Signature
   0      15      0    this       Lscala/collection/mutable/HashTable$$anonfun$serializeTo$1;
   0      15      1    $outer       Lscala/collection/mutable/HashTable;

  Signature: length = 0x2
   00 20 

public final java.lang.Object apply(java.lang.Object);
  Code:
   Stack=2, Locals=2, Args_size=2
   0:	aload_0
   1:	aload_1
   2:	checkcast	#37; //class scala/collection/mutable/HashEntry
   5:	invokevirtual	#40; //Method apply:(Lscala/collection/mutable/HashEntry;)V
   8:	getstatic	#46; //Field scala/runtime/BoxedUnit.UNIT:Lscala/runtime/BoxedUnit;
   11:	areturn
  LineNumberTable: 
   line 103: 0

  LocalVariableTable: 
   Start  Length  Slot  Name   Signature
   0      12      0    this       Lscala/collection/mutable/HashTable$$anonfun$serializeTo$1;
   0      12      1    v1       Ljava/lang/Object;


public final void apply(scala.collection.mutable.HashEntry);
  Code:
   Stack=3, Locals=2, Args_size=2
   0:	aload_0
   1:	getfield	#20; //Field out$1:Ljava/io/ObjectOutputStream;
   4:	aload_1
   5:	invokeinterface	#52,  1; //InterfaceMethod scala/collection/mutable/HashEntry.key:()Ljava/lang/Object;
   10:	invokevirtual	#58; //Method java/io/ObjectOutputStream.writeObject:(Ljava/lang/Object;)V
   13:	aload_0
   14:	getfield	#20; //Field out$1:Ljava/io/ObjectOutputStream;
   17:	aload_0
   18:	getfield	#22; //Field value$1:Lscala/Function1;
   21:	aload_1
   22:	invokeinterface	#62,  2; //InterfaceMethod scala/Function1.apply:(Ljava/lang/Object;)Ljava/lang/Object;
   27:	invokevirtual	#58; //Method java/io/ObjectOutputStream.writeObject:(Ljava/lang/Object;)V
   30:	return
  LineNumberTable: 
   line 104: 0
   line 105: 13

  LocalVariableTable: 
   Start  Length  Slot  Name   Signature
   0      31      0    this       Lscala/collection/mutable/HashTable$$anonfun$serializeTo$1;
   0      31      1    entry       Lscala/collection/mutable/HashEntry;

  Signature: length = 0x2
   00 26 

}

