Compiled from "HashTable.scala"
public final class scala.collection.mutable.HashTable$$anonfun$serializeTo$1 extends scala.runtime.AbstractFunction1 implements java.io.Serializable
  SourceFile: "HashTable.scala"
  Scala: length = 0x
   
  InnerClass: 
   public final $anonfun$serializeTo$1=class scala/collection/mutable/HashTable$$anonfun$serializeTo$1 of class scala/collection/mutable/HashTable
  minor version: 0
  major version: 49
  Constant pool:
Asciz	SourceFile;
Asciz	HashTable.scala;
Asciz	<clinit>;
Asciz	()V;
Asciz	Code;
Asciz	serialVersionUID;
Asciz	J;
Asciz	scala/collection/mutable/HashTable$$anonfun$serializeTo$1;
class	scala/collection/mutable/HashTable$$anonfun$serializeTo$1
NameAndType	serialVersionUID:J
Field	scala/collection/mutable/HashTable$$anonfun$serializeTo$1.serialVersionUID:J
Asciz	value$1;
Asciz	Lscala/Function1;;
Asciz	out$1;
Asciz	Ljava/io/ObjectOutputStream;;
Asciz	<init>;
Asciz	(Lscala/collection/mutable/HashTable;Ljava/io/ObjectOutputStream;Lscala/Function1;)V;
Asciz	LineNumberTable;
NameAndType	out$1:Ljava/io/ObjectOutputStream;
Field	scala/collection/mutable/HashTable$$anonfun$serializeTo$1.out$1:Ljava/io/ObjectOutputStream;
NameAndType	value$1:Lscala/Function1;
Field	scala/collection/mutable/HashTable$$anonfun$serializeTo$1.value$1:Lscala/Function1;
Asciz	scala/runtime/AbstractFunction1;
class	scala/runtime/AbstractFunction1
NameAndType	"<init>":()V
Method	scala/runtime/AbstractFunction1."<init>":()V
Asciz	this;
Asciz	Lscala/collection/mutable/HashTable$$anonfun$serializeTo$1;;
Asciz	$outer;
Asciz	Lscala/collection/mutable/HashTable;;
Asciz	LocalVariableTable;
Asciz	(Lscala/collection/mutable/HashTable<TA;>;)V;
Asciz	Signature;
Asciz	apply;
Asciz	(Ljava/lang/Object;)Ljava/lang/Object;;
Asciz	scala/collection/mutable/HashEntry;
class	scala/collection/mutable/HashEntry
Asciz	(Lscala/collection/mutable/HashEntry;)V;
NameAndType	apply:(Lscala/collection/mutable/HashEntry;)V
Method	scala/collection/mutable/HashTable$$anonfun$serializeTo$1.apply:(Lscala/collection/mutable/HashEntry;)V
Asciz	scala/runtime/BoxedUnit;
class	scala/runtime/BoxedUnit
Asciz	UNIT;
Asciz	Lscala/runtime/BoxedUnit;;
NameAndType	UNIT:Lscala/runtime/BoxedUnit;
Field	scala/runtime/BoxedUnit.UNIT:Lscala/runtime/BoxedUnit;
Asciz	v1;
Asciz	Ljava/lang/Object;;
Asciz	key;
Asciz	()Ljava/lang/Object;;
NameAndType	key:()Ljava/lang/Object;
InterfaceMethod	scala/collection/mutable/HashEntry.key:()Ljava/lang/Object;
Asciz	java/io/ObjectOutputStream;
class	java/io/ObjectOutputStream
Asciz	writeObject;
Asciz	(Ljava/lang/Object;)V;
NameAndType	writeObject:(Ljava/lang/Object;)V
Method	java/io/ObjectOutputStream.writeObject:(Ljava/lang/Object;)V
Asciz	scala/Function1;
class	scala/Function1
NameAndType	apply:(Ljava/lang/Object;)Ljava/lang/Object;
InterfaceMethod	scala/Function1.apply:(Ljava/lang/Object;)Ljava/lang/Object;
Asciz	entry;
Asciz	Lscala/collection/mutable/HashEntry;;
Asciz	Scala;
Asciz	InnerClasses;
Asciz	scala/collection/mutable/HashTable;
class	scala/collection/mutable/HashTable
Asciz	$anonfun$serializeTo$1;
Asciz	java/io/Serializable;
class	java/io/Serializable

{
public static final long serialVersionUID;
  Signature: J

private final scala.Function1 value$1;
  Signature: Lscala/Function1;

private final java.io.ObjectOutputStream out$1;
  Signature: Ljava/io/ObjectOutputStream;

public static {};
  Signature: ()V
  Code:
   Stack=2, Locals=0, Args_size=0
	lconst_0
	putstatic	Field serialVersionUID:J
	return
  Labels:

public scala.collection.mutable.HashTable$$anonfun$serializeTo$1(scala.collection.mutable.HashTable, java.io.ObjectOutputStream, scala.Function1);
  Signature: (Lscala/collection/mutable/HashTable;Ljava/io/ObjectOutputStream;Lscala/Function1;)V
  Code:
   Stack=2, Locals=4, Args_size=4
	aload_0
	aload_2
	putfield	Field out$1:Ljava/io/ObjectOutputStream;
	aload_0
	aload_3
	putfield	Field value$1:Lscala/Function1;
	aload_0
	invokespecial	Method scala/runtime/AbstractFunction1."<init>":()V
	return
  Labels:
  LocalVariableTable: 
   Start  Length  Slot  Name   Signature
   0      15      0    this       Lscala/collection/mutable/HashTable$$anonfun$serializeTo$1;
   0      15      1    $outer       Lscala/collection/mutable/HashTable;

  Signature: length = 0x2
   00 20 

public final java.lang.Object apply(java.lang.Object);
  Signature: (Ljava/lang/Object;)Ljava/lang/Object;
  Code:
   Stack=2, Locals=2, Args_size=2
	aload_0
	aload_1
	checkcast	class scala/collection/mutable/HashEntry
	invokevirtual	Method apply:(Lscala/collection/mutable/HashEntry;)V
	getstatic	Field scala/runtime/BoxedUnit.UNIT:Lscala/runtime/BoxedUnit;
	areturn
  Labels:
  LocalVariableTable: 
   Start  Length  Slot  Name   Signature
   0      12      0    this       Lscala/collection/mutable/HashTable$$anonfun$serializeTo$1;
   0      12      1    v1       Ljava/lang/Object;


public final void apply(scala.collection.mutable.HashEntry);
  Signature: (Lscala/collection/mutable/HashEntry;)V
  Code:
   Stack=3, Locals=2, Args_size=2
	aload_0
	getfield	Field out$1:Ljava/io/ObjectOutputStream;
	aload_1
	invokeinterface	InterfaceMethod scala/collection/mutable/HashEntry.key:()Ljava/lang/Object;
	invokevirtual	Method java/io/ObjectOutputStream.writeObject:(Ljava/lang/Object;)V
	aload_0
	getfield	Field out$1:Ljava/io/ObjectOutputStream;
	aload_0
	getfield	Field value$1:Lscala/Function1;
	aload_1
	invokeinterface	InterfaceMethod scala/Function1.apply:(Ljava/lang/Object;)Ljava/lang/Object;
	invokevirtual	Method java/io/ObjectOutputStream.writeObject:(Ljava/lang/Object;)V
	return
  Labels:
  LocalVariableTable: 
   Start  Length  Slot  Name   Signature
   0      31      0    this       Lscala/collection/mutable/HashTable$$anonfun$serializeTo$1;
   0      31      1    entry       Lscala/collection/mutable/HashEntry;

  Signature: length = 0x2
   00 26 

}

