Compiled from "IndexedSeqView.scala"
public final class scala.collection.mutable.IndexedSeqView$$anon$3 extends java.lang.Object implements scala.collection.mutable.IndexedSeqView$DroppedWhile
  SourceFile: "IndexedSeqView.scala"
  Signature: length = 0x2
   03 FFFFFFD1 
  Scala: length = 0x
   
  InnerClass: 
   public final #980= #24 of #164; //$anon$3=class scala/collection/mutable/IndexedSeqView$$anon$3 of class scala/collection/mutable/IndexedSeqView
   public abstract #985= #982 of #984; //Transformed=class scala/collection/SeqViewLike$Transformed of class scala/collection/SeqViewLike
   public abstract #986= #156 of #984; //DroppedWhile=class scala/collection/SeqViewLike$DroppedWhile of class scala/collection/SeqViewLike
   public #991= #988 of #990; //WithFilter=class scala/collection/TraversableLike$WithFilter of class scala/collection/TraversableLike
   public abstract #985= #993 of #164; //Transformed=class scala/collection/mutable/IndexedSeqView$Transformed of class scala/collection/mutable/IndexedSeqView
   public abstract #986= #995 of #164; //DroppedWhile=class scala/collection/mutable/IndexedSeqView$DroppedWhile of class scala/collection/mutable/IndexedSeqView
   public abstract #985= #997 of #999; //Transformed=class scala/collection/IterableViewLike$Transformed of class scala/collection/IterableViewLike
   public abstract #986= #1001 of #999; //DroppedWhile=class scala/collection/IterableViewLike$DroppedWhile of class scala/collection/IterableViewLike
   public abstract #985= #1003 of #236; //Transformed=class scala/collection/IndexedSeqViewLike$Transformed of class scala/collection/IndexedSeqViewLike
   public abstract #986= #1005 of #236; //DroppedWhile=class scala/collection/IndexedSeqViewLike$DroppedWhile of class scala/collection/IndexedSeqViewLike
   public abstract #985= #1007 of #1009; //Transformed=class scala/collection/TraversableViewLike$Transformed of class scala/collection/TraversableViewLike
   public abstract #986= #1011 of #1009; //DroppedWhile=class scala/collection/TraversableViewLike$DroppedWhile of class scala/collection/TraversableViewLike
  minor version: 0
  major version: 49
  Constant pool:
const #1 = Asciz	SourceFile;
const #2 = Asciz	IndexedSeqView.scala;
const #3 = Asciz	bitmap$0;
const #4 = Asciz	I;
const #5 = Asciz	underlying;
const #6 = Asciz	Ljava/lang/Object;;
const #7 = Asciz	start;
const #8 = Asciz	$outer;
const #9 = Asciz	Lscala/collection/mutable/IndexedSeqView;;
const #10 = Asciz	pred;
const #11 = Asciz	Lscala/Function1;;
const #12 = Asciz	Lscala/Function1<TA;Ljava/lang/Boolean;>;;
const #13 = Asciz	Signature;
const #14 = Asciz	<init>;
const #15 = Asciz	(Lscala/collection/mutable/IndexedSeqView;Lscala/Function1;)V;
const #16 = Asciz	Code;
const #17 = Asciz	LineNumberTable;
const #18 = Asciz	java/lang/NullPointerException;
const #19 = class	#18;	//  java/lang/NullPointerException
const #20 = Asciz	()V;
const #21 = NameAndType	#14:#20;//  "<init>":()V
const #22 = Method	#19.#21;	//  java/lang/NullPointerException."<init>":()V
const #23 = Asciz	scala/collection/mutable/IndexedSeqView$$anon$3;
const #24 = class	#23;	//  scala/collection/mutable/IndexedSeqView$$anon$3
const #25 = NameAndType	#8:#9;//  $outer:Lscala/collection/mutable/IndexedSeqView;
const #26 = Field	#24.#25;	//  scala/collection/mutable/IndexedSeqView$$anon$3.$outer:Lscala/collection/mutable/IndexedSeqView;
const #27 = Asciz	java/lang/Object;
const #28 = class	#27;	//  java/lang/Object
const #29 = Method	#28.#21;	//  java/lang/Object."<init>":()V
const #30 = Asciz	scala/Function1$class;
const #31 = class	#30;	//  scala/Function1$class
const #32 = Asciz	$init$;
const #33 = Asciz	(Lscala/Function1;)V;
const #34 = NameAndType	#32:#33;//  $init$:(Lscala/Function1;)V
const #35 = Method	#31.#34;	//  scala/Function1$class.$init$:(Lscala/Function1;)V
const #36 = Asciz	scala/PartialFunction$class;
const #37 = class	#36;	//  scala/PartialFunction$class
const #38 = Asciz	(Lscala/PartialFunction;)V;
const #39 = NameAndType	#32:#38;//  $init$:(Lscala/PartialFunction;)V
const #40 = Method	#37.#39;	//  scala/PartialFunction$class.$init$:(Lscala/PartialFunction;)V
const #41 = Asciz	scala/collection/TraversableLike$class;
const #42 = class	#41;	//  scala/collection/TraversableLike$class
const #43 = Asciz	(Lscala/collection/TraversableLike;)V;
const #44 = NameAndType	#32:#43;//  $init$:(Lscala/collection/TraversableLike;)V
const #45 = Method	#42.#44;	//  scala/collection/TraversableLike$class.$init$:(Lscala/collection/TraversableLike;)V
const #46 = Asciz	scala/collection/generic/GenericTraversableTemplate$class;
const #47 = class	#46;	//  scala/collection/generic/GenericTraversableTemplate$class
const #48 = Asciz	(Lscala/collection/generic/GenericTraversableTemplate;)V;
const #49 = NameAndType	#32:#48;//  $init$:(Lscala/collection/generic/GenericTraversableTemplate;)V
const #50 = Method	#47.#49;	//  scala/collection/generic/GenericTraversableTemplate$class.$init$:(Lscala/collection/generic/GenericTraversableTemplate;)V
const #51 = Asciz	scala/collection/Traversable$class;
const #52 = class	#51;	//  scala/collection/Traversable$class
const #53 = Asciz	(Lscala/collection/Traversable;)V;
const #54 = NameAndType	#32:#53;//  $init$:(Lscala/collection/Traversable;)V
const #55 = Method	#52.#54;	//  scala/collection/Traversable$class.$init$:(Lscala/collection/Traversable;)V
const #56 = Asciz	scala/collection/IterableLike$class;
const #57 = class	#56;	//  scala/collection/IterableLike$class
const #58 = Asciz	(Lscala/collection/IterableLike;)V;
const #59 = NameAndType	#32:#58;//  $init$:(Lscala/collection/IterableLike;)V
const #60 = Method	#57.#59;	//  scala/collection/IterableLike$class.$init$:(Lscala/collection/IterableLike;)V
const #61 = Asciz	scala/collection/Iterable$class;
const #62 = class	#61;	//  scala/collection/Iterable$class
const #63 = Asciz	(Lscala/collection/Iterable;)V;
const #64 = NameAndType	#32:#63;//  $init$:(Lscala/collection/Iterable;)V
const #65 = Method	#62.#64;	//  scala/collection/Iterable$class.$init$:(Lscala/collection/Iterable;)V
const #66 = Asciz	scala/collection/SeqLike$class;
const #67 = class	#66;	//  scala/collection/SeqLike$class
const #68 = Asciz	(Lscala/collection/SeqLike;)V;
const #69 = NameAndType	#32:#68;//  $init$:(Lscala/collection/SeqLike;)V
const #70 = Method	#67.#69;	//  scala/collection/SeqLike$class.$init$:(Lscala/collection/SeqLike;)V
const #71 = Asciz	scala/collection/Seq$class;
const #72 = class	#71;	//  scala/collection/Seq$class
const #73 = Asciz	(Lscala/collection/Seq;)V;
const #74 = NameAndType	#32:#73;//  $init$:(Lscala/collection/Seq;)V
const #75 = Method	#72.#74;	//  scala/collection/Seq$class.$init$:(Lscala/collection/Seq;)V
const #76 = Asciz	scala/collection/IndexedSeqLike$class;
const #77 = class	#76;	//  scala/collection/IndexedSeqLike$class
const #78 = Asciz	(Lscala/collection/IndexedSeqLike;)V;
const #79 = NameAndType	#32:#78;//  $init$:(Lscala/collection/IndexedSeqLike;)V
const #80 = Method	#77.#79;	//  scala/collection/IndexedSeqLike$class.$init$:(Lscala/collection/IndexedSeqLike;)V
const #81 = Asciz	scala/collection/IndexedSeq$class;
const #82 = class	#81;	//  scala/collection/IndexedSeq$class
const #83 = Asciz	(Lscala/collection/IndexedSeq;)V;
const #84 = NameAndType	#32:#83;//  $init$:(Lscala/collection/IndexedSeq;)V
const #85 = Method	#82.#84;	//  scala/collection/IndexedSeq$class.$init$:(Lscala/collection/IndexedSeq;)V
const #86 = Asciz	scala/collection/TraversableViewLike$class;
const #87 = class	#86;	//  scala/collection/TraversableViewLike$class
const #88 = Asciz	(Lscala/collection/TraversableViewLike;)V;
const #89 = NameAndType	#32:#88;//  $init$:(Lscala/collection/TraversableViewLike;)V
const #90 = Method	#87.#89;	//  scala/collection/TraversableViewLike$class.$init$:(Lscala/collection/TraversableViewLike;)V
const #91 = Asciz	scala/collection/IterableViewLike$class;
const #92 = class	#91;	//  scala/collection/IterableViewLike$class
const #93 = Asciz	(Lscala/collection/IterableViewLike;)V;
const #94 = NameAndType	#32:#93;//  $init$:(Lscala/collection/IterableViewLike;)V
const #95 = Method	#92.#94;	//  scala/collection/IterableViewLike$class.$init$:(Lscala/collection/IterableViewLike;)V
const #96 = Asciz	scala/collection/SeqViewLike$class;
const #97 = class	#96;	//  scala/collection/SeqViewLike$class
const #98 = Asciz	(Lscala/collection/SeqViewLike;)V;
const #99 = NameAndType	#32:#98;//  $init$:(Lscala/collection/SeqViewLike;)V
const #100 = Method	#97.#99;	//  scala/collection/SeqViewLike$class.$init$:(Lscala/collection/SeqViewLike;)V
const #101 = Asciz	scala/collection/IndexedSeqViewLike$class;
const #102 = class	#101;	//  scala/collection/IndexedSeqViewLike$class
const #103 = Asciz	(Lscala/collection/IndexedSeqViewLike;)V;
const #104 = NameAndType	#32:#103;//  $init$:(Lscala/collection/IndexedSeqViewLike;)V
const #105 = Method	#102.#104;	//  scala/collection/IndexedSeqViewLike$class.$init$:(Lscala/collection/IndexedSeqViewLike;)V
const #106 = Asciz	scala/collection/mutable/IndexedSeqView$class;
const #107 = class	#106;	//  scala/collection/mutable/IndexedSeqView$class
const #108 = Asciz	(Lscala/collection/mutable/IndexedSeqView;)V;
const #109 = NameAndType	#32:#108;//  $init$:(Lscala/collection/mutable/IndexedSeqView;)V
const #110 = Method	#107.#109;	//  scala/collection/mutable/IndexedSeqView$class.$init$:(Lscala/collection/mutable/IndexedSeqView;)V
const #111 = Asciz	scala/collection/TraversableViewLike$Transformed$class;
const #112 = class	#111;	//  scala/collection/TraversableViewLike$Transformed$class
const #113 = Asciz	(Lscala/collection/TraversableViewLike$Transformed;)V;
const #114 = NameAndType	#32:#113;//  $init$:(Lscala/collection/TraversableViewLike$Transformed;)V
const #115 = Method	#112.#114;	//  scala/collection/TraversableViewLike$Transformed$class.$init$:(Lscala/collection/TraversableViewLike$Transformed;)V
const #116 = Asciz	scala/collection/TraversableViewLike$DroppedWhile$class;
const #117 = class	#116;	//  scala/collection/TraversableViewLike$DroppedWhile$class
const #118 = Asciz	(Lscala/collection/TraversableViewLike$DroppedWhile;)V;
const #119 = NameAndType	#32:#118;//  $init$:(Lscala/collection/TraversableViewLike$DroppedWhile;)V
const #120 = Method	#117.#119;	//  scala/collection/TraversableViewLike$DroppedWhile$class.$init$:(Lscala/collection/TraversableViewLike$DroppedWhile;)V
const #121 = Asciz	scala/collection/IterableViewLike$DroppedWhile$class;
const #122 = class	#121;	//  scala/collection/IterableViewLike$DroppedWhile$class
const #123 = Asciz	(Lscala/collection/IterableViewLike$DroppedWhile;)V;
const #124 = NameAndType	#32:#123;//  $init$:(Lscala/collection/IterableViewLike$DroppedWhile;)V
const #125 = Method	#122.#124;	//  scala/collection/IterableViewLike$DroppedWhile$class.$init$:(Lscala/collection/IterableViewLike$DroppedWhile;)V
const #126 = Asciz	scala/collection/SeqViewLike$DroppedWhile$class;
const #127 = class	#126;	//  scala/collection/SeqViewLike$DroppedWhile$class
const #128 = Asciz	(Lscala/collection/SeqViewLike$DroppedWhile;)V;
const #129 = NameAndType	#32:#128;//  $init$:(Lscala/collection/SeqViewLike$DroppedWhile;)V
const #130 = Method	#127.#129;	//  scala/collection/SeqViewLike$DroppedWhile$class.$init$:(Lscala/collection/SeqViewLike$DroppedWhile;)V
const #131 = Asciz	scala/collection/IndexedSeqViewLike$DroppedWhile$class;
const #132 = class	#131;	//  scala/collection/IndexedSeqViewLike$DroppedWhile$class
const #133 = Asciz	(Lscala/collection/IndexedSeqViewLike$DroppedWhile;)V;
const #134 = NameAndType	#32:#133;//  $init$:(Lscala/collection/IndexedSeqViewLike$DroppedWhile;)V
const #135 = Method	#132.#134;	//  scala/collection/IndexedSeqViewLike$DroppedWhile$class.$init$:(Lscala/collection/IndexedSeqViewLike$DroppedWhile;)V
const #136 = Asciz	scala/collection/mutable/IndexedSeqView$DroppedWhile$class;
const #137 = class	#136;	//  scala/collection/mutable/IndexedSeqView$DroppedWhile$class
const #138 = Asciz	(Lscala/collection/mutable/IndexedSeqView$DroppedWhile;)V;
const #139 = NameAndType	#32:#138;//  $init$:(Lscala/collection/mutable/IndexedSeqView$DroppedWhile;)V
const #140 = Method	#137.#139;	//  scala/collection/mutable/IndexedSeqView$DroppedWhile$class.$init$:(Lscala/collection/mutable/IndexedSeqView$DroppedWhile;)V
const #141 = NameAndType	#10:#11;//  pred:Lscala/Function1;
const #142 = Field	#24.#141;	//  scala/collection/mutable/IndexedSeqView$$anon$3.pred:Lscala/Function1;
const #143 = Asciz	this;
const #144 = Asciz	Lscala/collection/mutable/IndexedSeqView$$anon$3;;
const #145 = Asciz	LocalVariableTable;
const #146 = Asciz	(Lscala/collection/mutable/IndexedSeqView<TA;TColl;>;)V;
const #147 = Asciz	apply;
const #148 = Asciz	(Ljava/lang/Object;)Ljava/lang/Object;;
const #149 = Asciz	scala/runtime/BoxesRunTime;
const #150 = class	#149;	//  scala/runtime/BoxesRunTime
const #151 = Asciz	unboxToInt;
const #152 = Asciz	(Ljava/lang/Object;)I;
const #153 = NameAndType	#151:#152;//  unboxToInt:(Ljava/lang/Object;)I
const #154 = Method	#150.#153;	//  scala/runtime/BoxesRunTime.unboxToInt:(Ljava/lang/Object;)I
const #155 = Asciz	scala/collection/SeqViewLike$DroppedWhile;
const #156 = class	#155;	//  scala/collection/SeqViewLike$DroppedWhile
const #157 = Asciz	(I)Ljava/lang/Object;;
const #158 = NameAndType	#147:#157;//  apply:(I)Ljava/lang/Object;
const #159 = InterfaceMethod	#156.#158;	//  scala/collection/SeqViewLike$DroppedWhile.apply:(I)Ljava/lang/Object;
const #160 = Asciz	v1;
const #161 = Asciz	newFiltered;
const #162 = Asciz	(Lscala/Function1;)Lscala/collection/IndexedSeqViewLike$Transformed;;
const #163 = Asciz	scala/collection/mutable/IndexedSeqView;
const #164 = class	#163;	//  scala/collection/mutable/IndexedSeqView
const #165 = Asciz	(Lscala/Function1;)Lscala/collection/mutable/IndexedSeqView$Transformed;;
const #166 = NameAndType	#161:#165;//  newFiltered:(Lscala/Function1;)Lscala/collection/mutable/IndexedSeqView$Transformed;
const #167 = InterfaceMethod	#164.#166;	//  scala/collection/mutable/IndexedSeqView.newFiltered:(Lscala/Function1;)Lscala/collection/mutable/IndexedSeqView$Transformed;
const #168 = Asciz	p;
const #169 = Asciz	(Lscala/Function1;)Lscala/collection/SeqViewLike$Transformed;;
const #170 = Asciz	(Lscala/Function1;)Lscala/collection/IterableViewLike$Transformed;;
const #171 = Asciz	(Lscala/Function1;)Lscala/collection/TraversableViewLike$Transformed;;
const #172 = Asciz	newSliced;
const #173 = Asciz	(II)Lscala/collection/IndexedSeqViewLike$Transformed;;
const #174 = Asciz	(II)Lscala/collection/mutable/IndexedSeqView$Transformed;;
const #175 = NameAndType	#172:#174;//  newSliced:(II)Lscala/collection/mutable/IndexedSeqView$Transformed;
const #176 = InterfaceMethod	#164.#175;	//  scala/collection/mutable/IndexedSeqView.newSliced:(II)Lscala/collection/mutable/IndexedSeqView$Transformed;
const #177 = Asciz	_from;
const #178 = Asciz	_until;
const #179 = Asciz	(II)Lscala/collection/SeqViewLike$Transformed;;
const #180 = Asciz	(II)Lscala/collection/IterableViewLike$Transformed;;
const #181 = Asciz	(II)Lscala/collection/TraversableViewLike$Transformed;;
const #182 = Asciz	newDroppedWhile;
const #183 = NameAndType	#182:#165;//  newDroppedWhile:(Lscala/Function1;)Lscala/collection/mutable/IndexedSeqView$Transformed;
const #184 = InterfaceMethod	#164.#183;	//  scala/collection/mutable/IndexedSeqView.newDroppedWhile:(Lscala/Function1;)Lscala/collection/mutable/IndexedSeqView$Transformed;
const #185 = Asciz	newTakenWhile;
const #186 = NameAndType	#185:#165;//  newTakenWhile:(Lscala/Function1;)Lscala/collection/mutable/IndexedSeqView$Transformed;
const #187 = InterfaceMethod	#164.#186;	//  scala/collection/mutable/IndexedSeqView.newTakenWhile:(Lscala/Function1;)Lscala/collection/mutable/IndexedSeqView$Transformed;
const #188 = Asciz	newReversed;
const #189 = Asciz	()Lscala/collection/IndexedSeqViewLike$Transformed;;
const #190 = Asciz	()Lscala/collection/mutable/IndexedSeqView$Transformed;;
const #191 = NameAndType	#188:#190;//  newReversed:()Lscala/collection/mutable/IndexedSeqView$Transformed;
const #192 = InterfaceMethod	#164.#191;	//  scala/collection/mutable/IndexedSeqView.newReversed:()Lscala/collection/mutable/IndexedSeqView$Transformed;
const #193 = Asciz	()Lscala/collection/SeqViewLike$Transformed;;
const #194 = Asciz	filter;
const #195 = Asciz	(Lscala/Function1;)Lscala/collection/TraversableView;;
const #196 = Asciz	(Lscala/Function1;)Lscala/collection/mutable/IndexedSeqView;;
const #197 = NameAndType	#194:#196;//  filter:(Lscala/Function1;)Lscala/collection/mutable/IndexedSeqView;
const #198 = InterfaceMethod	#164.#197;	//  scala/collection/mutable/IndexedSeqView.filter:(Lscala/Function1;)Lscala/collection/mutable/IndexedSeqView;
const #199 = Asciz	(Lscala/Function1;)Ljava/lang/Object;;
const #200 = Asciz	init;
const #201 = Asciz	()Lscala/collection/TraversableView;;
const #202 = Asciz	()Lscala/collection/mutable/IndexedSeqView;;
const #203 = NameAndType	#200:#202;//  init:()Lscala/collection/mutable/IndexedSeqView;
const #204 = InterfaceMethod	#164.#203;	//  scala/collection/mutable/IndexedSeqView.init:()Lscala/collection/mutable/IndexedSeqView;
const #205 = Asciz	()Ljava/lang/Object;;
const #206 = Asciz	drop;
const #207 = Asciz	(I)Lscala/collection/TraversableView;;
const #208 = Asciz	(I)Lscala/collection/mutable/IndexedSeqView;;
const #209 = NameAndType	#206:#208;//  drop:(I)Lscala/collection/mutable/IndexedSeqView;
const #210 = InterfaceMethod	#164.#209;	//  scala/collection/mutable/IndexedSeqView.drop:(I)Lscala/collection/mutable/IndexedSeqView;
const #211 = Asciz	n;
const #212 = Asciz	take;
const #213 = NameAndType	#212:#208;//  take:(I)Lscala/collection/mutable/IndexedSeqView;
const #214 = InterfaceMethod	#164.#213;	//  scala/collection/mutable/IndexedSeqView.take:(I)Lscala/collection/mutable/IndexedSeqView;
const #215 = Asciz	slice;
const #216 = Asciz	(II)Lscala/collection/TraversableView;;
const #217 = Asciz	(II)Lscala/collection/mutable/IndexedSeqView;;
const #218 = NameAndType	#215:#217;//  slice:(II)Lscala/collection/mutable/IndexedSeqView;
const #219 = InterfaceMethod	#164.#218;	//  scala/collection/mutable/IndexedSeqView.slice:(II)Lscala/collection/mutable/IndexedSeqView;
const #220 = Asciz	from;
const #221 = Asciz	until;
const #222 = Asciz	(II)Ljava/lang/Object;;
const #223 = Asciz	dropWhile;
const #224 = NameAndType	#223:#196;//  dropWhile:(Lscala/Function1;)Lscala/collection/mutable/IndexedSeqView;
const #225 = InterfaceMethod	#164.#224;	//  scala/collection/mutable/IndexedSeqView.dropWhile:(Lscala/Function1;)Lscala/collection/mutable/IndexedSeqView;
const #226 = Asciz	takeWhile;
const #227 = NameAndType	#226:#196;//  takeWhile:(Lscala/Function1;)Lscala/collection/mutable/IndexedSeqView;
const #228 = InterfaceMethod	#164.#227;	//  scala/collection/mutable/IndexedSeqView.takeWhile:(Lscala/Function1;)Lscala/collection/mutable/IndexedSeqView;
const #229 = Asciz	reverse;
const #230 = Asciz	()Lscala/collection/SeqView;;
const #231 = NameAndType	#229:#202;//  reverse:()Lscala/collection/mutable/IndexedSeqView;
const #232 = InterfaceMethod	#164.#231;	//  scala/collection/mutable/IndexedSeqView.reverse:()Lscala/collection/mutable/IndexedSeqView;
const #233 = Asciz	newAppended;
const #234 = Asciz	(Lscala/collection/Traversable;)Lscala/collection/SeqViewLike$Transformed;;
const #235 = Asciz	scala/collection/IndexedSeqViewLike;
const #236 = class	#235;	//  scala/collection/IndexedSeqViewLike
const #237 = Asciz	(Lscala/collection/Traversable;)Lscala/collection/IndexedSeqViewLike$Transformed;;
const #238 = NameAndType	#233:#237;//  newAppended:(Lscala/collection/Traversable;)Lscala/collection/IndexedSeqViewLike$Transformed;
const #239 = InterfaceMethod	#236.#238;	//  scala/collection/IndexedSeqViewLike.newAppended:(Lscala/collection/Traversable;)Lscala/collection/IndexedSeqViewLike$Transformed;
const #240 = Asciz	that;
const #241 = Asciz	Lscala/collection/Traversable;;
const #242 = Asciz	(Lscala/collection/Traversable;)Lscala/collection/IterableViewLike$Transformed;;
const #243 = Asciz	(Lscala/collection/Traversable;)Lscala/collection/TraversableViewLike$Transformed;;
const #244 = Asciz	newMapped;
const #245 = NameAndType	#244:#162;//  newMapped:(Lscala/Function1;)Lscala/collection/IndexedSeqViewLike$Transformed;
const #246 = InterfaceMethod	#236.#245;	//  scala/collection/IndexedSeqViewLike.newMapped:(Lscala/Function1;)Lscala/collection/IndexedSeqViewLike$Transformed;
const #247 = Asciz	f;
const #248 = Asciz	newFlatMapped;
const #249 = NameAndType	#248:#162;//  newFlatMapped:(Lscala/Function1;)Lscala/collection/IndexedSeqViewLike$Transformed;
const #250 = InterfaceMethod	#236.#249;	//  scala/collection/IndexedSeqViewLike.newFlatMapped:(Lscala/Function1;)Lscala/collection/IndexedSeqViewLike$Transformed;
const #251 = Asciz	newZipped;
const #252 = Asciz	(Lscala/collection/Iterable;)Lscala/collection/SeqViewLike$Transformed;;
const #253 = Asciz	(Lscala/collection/Iterable;)Lscala/collection/IndexedSeqViewLike$Transformed;;
const #254 = NameAndType	#251:#253;//  newZipped:(Lscala/collection/Iterable;)Lscala/collection/IndexedSeqViewLike$Transformed;
const #255 = InterfaceMethod	#236.#254;	//  scala/collection/IndexedSeqViewLike.newZipped:(Lscala/collection/Iterable;)Lscala/collection/IndexedSeqViewLike$Transformed;
const #256 = Asciz	Lscala/collection/Iterable;;
const #257 = Asciz	(Lscala/collection/Iterable;)Lscala/collection/IterableViewLike$Transformed;;
const #258 = Asciz	newZippedAll;
const #259 = Asciz	(Lscala/collection/Iterable;Ljava/lang/Object;Ljava/lang/Object;)Lscala/collection/SeqViewLike$Transformed;;
const #260 = Asciz	(Lscala/collection/Iterable;Ljava/lang/Object;Ljava/lang/Object;)Lscala/collection/IndexedSeqViewLike$Transformed;;
const #261 = NameAndType	#258:#260;//  newZippedAll:(Lscala/collection/Iterable;Ljava/lang/Object;Ljava/lang/Object;)Lscala/collection/IndexedSeqViewLike$Transformed;
const #262 = InterfaceMethod	#236.#261;	//  scala/collection/IndexedSeqViewLike.newZippedAll:(Lscala/collection/Iterable;Ljava/lang/Object;Ljava/lang/Object;)Lscala/collection/IndexedSeqViewLike$Transformed;
const #263 = Asciz	_thisElem;
const #264 = Asciz	_thatElem;
const #265 = Asciz	(Lscala/collection/Iterable;Ljava/lang/Object;Ljava/lang/Object;)Lscala/collection/IterableViewLike$Transformed;;
const #266 = Asciz	newPatched;
const #267 = Asciz	(ILscala/collection/Seq;I)Lscala/collection/SeqViewLike$Transformed;;
const #268 = Asciz	(ILscala/collection/Seq;I)Lscala/collection/IndexedSeqViewLike$Transformed;;
const #269 = NameAndType	#266:#268;//  newPatched:(ILscala/collection/Seq;I)Lscala/collection/IndexedSeqViewLike$Transformed;
const #270 = InterfaceMethod	#236.#269;	//  scala/collection/IndexedSeqViewLike.newPatched:(ILscala/collection/Seq;I)Lscala/collection/IndexedSeqViewLike$Transformed;
const #271 = Asciz	_patch;
const #272 = Asciz	Lscala/collection/Seq;;
const #273 = Asciz	_replaced;
const #274 = Asciz	thisCollection;
const #275 = Asciz	()Lscala/collection/Seq;;
const #276 = Asciz	scala/collection/IndexedSeqLike;
const #277 = class	#276;	//  scala/collection/IndexedSeqLike
const #278 = Asciz	()Lscala/collection/IndexedSeq;;
const #279 = NameAndType	#274:#278;//  thisCollection:()Lscala/collection/IndexedSeq;
const #280 = InterfaceMethod	#277.#279;	//  scala/collection/IndexedSeqLike.thisCollection:()Lscala/collection/IndexedSeq;
const #281 = Asciz	()Lscala/collection/Iterable;;
const #282 = Asciz	()Lscala/collection/Traversable;;
const #283 = Asciz	toCollection;
const #284 = Asciz	(Ljava/lang/Object;)Lscala/collection/Seq;;
const #285 = Asciz	(Ljava/lang/Object;)Lscala/collection/IndexedSeq;;
const #286 = NameAndType	#283:#285;//  toCollection:(Ljava/lang/Object;)Lscala/collection/IndexedSeq;
const #287 = InterfaceMethod	#277.#286;	//  scala/collection/IndexedSeqLike.toCollection:(Ljava/lang/Object;)Lscala/collection/IndexedSeq;
const #288 = Asciz	repr;
const #289 = Asciz	(Ljava/lang/Object;)Lscala/collection/Iterable;;
const #290 = Asciz	(Ljava/lang/Object;)Lscala/collection/Traversable;;
const #291 = Asciz	view;
const #292 = Asciz	(II)Lscala/collection/SeqView;;
const #293 = Asciz	(II)Lscala/collection/IndexedSeqView;;
const #294 = NameAndType	#291:#293;//  view:(II)Lscala/collection/IndexedSeqView;
const #295 = InterfaceMethod	#277.#294;	//  scala/collection/IndexedSeqLike.view:(II)Lscala/collection/IndexedSeqView;
const #296 = Asciz	(II)Lscala/collection/IterableView;;
const #297 = Asciz	isDefinedAt;
const #298 = Asciz	(Ljava/lang/Object;)Z;
const #299 = Asciz	scala/collection/SeqLike;
const #300 = class	#299;	//  scala/collection/SeqLike
const #301 = Asciz	(I)Z;
const #302 = NameAndType	#297:#301;//  isDefinedAt:(I)Z
const #303 = InterfaceMethod	#300.#302;	//  scala/collection/SeqLike.isDefinedAt:(I)Z
const #304 = Asciz	x;
const #305 = Asciz	andThen;
const #306 = Asciz	(Lscala/Function1;)Lscala/Function1;;
const #307 = Asciz	scala/PartialFunction;
const #308 = class	#307;	//  scala/PartialFunction
const #309 = Asciz	(Lscala/Function1;)Lscala/PartialFunction;;
const #310 = NameAndType	#305:#309;//  andThen:(Lscala/Function1;)Lscala/PartialFunction;
const #311 = InterfaceMethod	#308.#310;	//  scala/PartialFunction.andThen:(Lscala/Function1;)Lscala/PartialFunction;
const #312 = Asciz	g;
const #313 = Asciz	scala$collection$TraversableViewLike$Transformed$$$outer;
const #314 = Asciz	()Lscala/collection/TraversableViewLike;;
const #315 = Asciz	scala$collection$TraversableViewLike$DroppedWhile$$$outer;
const #316 = Asciz	scala$collection$IterableViewLike$DroppedWhile$$$outer;
const #317 = Asciz	()Lscala/collection/IterableViewLike;;
const #318 = Asciz	scala$collection$SeqViewLike$DroppedWhile$$$outer;
const #319 = Asciz	()Lscala/collection/SeqViewLike;;
const #320 = Asciz	scala$collection$IndexedSeqViewLike$DroppedWhile$$$outer;
const #321 = Asciz	()Lscala/collection/IndexedSeqViewLike;;
const #322 = Asciz	scala$collection$mutable$IndexedSeqView$DroppedWhile$$$outer;
const #323 = Asciz	()Lscala/Function1;;
const #324 = Asciz	()Lscala/Function1<TA;Ljava/lang/Boolean;>;;
const #325 = Asciz	compose;
const #326 = Asciz	(Lscala/Function1;Lscala/Function1;)Lscala/Function1;;
const #327 = NameAndType	#325:#326;//  compose:(Lscala/Function1;Lscala/Function1;)Lscala/Function1;
const #328 = Method	#31.#327;	//  scala/Function1$class.compose:(Lscala/Function1;Lscala/Function1;)Lscala/Function1;
const #329 = Asciz	lift;
const #330 = Asciz	(Lscala/PartialFunction;)Lscala/Function1;;
const #331 = NameAndType	#329:#330;//  lift:(Lscala/PartialFunction;)Lscala/Function1;
const #332 = Method	#37.#331;	//  scala/PartialFunction$class.lift:(Lscala/PartialFunction;)Lscala/Function1;
const #333 = Asciz	(Lscala/PartialFunction;Lscala/Function1;)Lscala/PartialFunction;;
const #334 = NameAndType	#305:#333;//  andThen:(Lscala/PartialFunction;Lscala/Function1;)Lscala/PartialFunction;
const #335 = Method	#37.#334;	//  scala/PartialFunction$class.andThen:(Lscala/PartialFunction;Lscala/Function1;)Lscala/PartialFunction;
const #336 = Asciz	k;
const #337 = Asciz	orElse;
const #338 = Asciz	(Lscala/PartialFunction;)Lscala/PartialFunction;;
const #339 = Asciz	(Lscala/PartialFunction;Lscala/PartialFunction;)Lscala/PartialFunction;;
const #340 = NameAndType	#337:#339;//  orElse:(Lscala/PartialFunction;Lscala/PartialFunction;)Lscala/PartialFunction;
const #341 = Method	#37.#340;	//  scala/PartialFunction$class.orElse:(Lscala/PartialFunction;Lscala/PartialFunction;)Lscala/PartialFunction;
const #342 = Asciz	Lscala/PartialFunction;;
const #343 = Asciz	withFilter;
const #344 = Asciz	(Lscala/Function1;)Lscala/collection/TraversableLike$WithFilter;;
const #345 = Asciz	(Lscala/collection/TraversableLike;Lscala/Function1;)Lscala/collection/TraversableLike$WithFilter;;
const #346 = NameAndType	#343:#345;//  withFilter:(Lscala/collection/TraversableLike;Lscala/Function1;)Lscala/collection/TraversableLike$WithFilter;
const #347 = Method	#42.#346;	//  scala/collection/TraversableLike$class.withFilter:(Lscala/collection/TraversableLike;Lscala/Function1;)Lscala/collection/TraversableLike$WithFilter;
const #348 = Asciz	addString;
const #349 = Asciz	(Lscala/collection/mutable/StringBuilder;)Lscala/collection/mutable/StringBuilder;;
const #350 = Asciz	(Lscala/collection/TraversableLike;Lscala/collection/mutable/StringBuilder;)Lscala/collection/mutable/StringBuilder;;
const #351 = NameAndType	#348:#350;//  addString:(Lscala/collection/TraversableLike;Lscala/collection/mutable/StringBuilder;)Lscala/collection/mutable/StringBuilder;
const #352 = Method	#42.#351;	//  scala/collection/TraversableLike$class.addString:(Lscala/collection/TraversableLike;Lscala/collection/mutable/StringBuilder;)Lscala/collection/mutable/StringBuilder;
const #353 = Asciz	b;
const #354 = Asciz	Lscala/collection/mutable/StringBuilder;;
const #355 = Asciz	(Lscala/collection/mutable/StringBuilder;Ljava/lang/String;)Lscala/collection/mutable/StringBuilder;;
const #356 = Asciz	(Lscala/collection/TraversableLike;Lscala/collection/mutable/StringBuilder;Ljava/lang/String;)Lscala/collection/mutable/StringBuilder;;
const #357 = NameAndType	#348:#356;//  addString:(Lscala/collection/TraversableLike;Lscala/collection/mutable/StringBuilder;Ljava/lang/String;)Lscala/collection/mutable/StringBuilder;
const #358 = Method	#42.#357;	//  scala/collection/TraversableLike$class.addString:(Lscala/collection/TraversableLike;Lscala/collection/mutable/StringBuilder;Ljava/lang/String;)Lscala/collection/mutable/StringBuilder;
const #359 = Asciz	sep;
const #360 = Asciz	Ljava/lang/String;;
const #361 = Asciz	(Lscala/collection/mutable/StringBuilder;Ljava/lang/String;Ljava/lang/String;Ljava/lang/String;)Lscala/collection/mutable/StringBuilder;;
const #362 = Asciz	(Lscala/collection/TraversableLike;Lscala/collection/mutable/StringBuilder;Ljava/lang/String;Ljava/lang/String;Ljava/lang/String;)Lscala/collection/mutable/StringBuilder;;
const #363 = NameAndType	#348:#362;//  addString:(Lscala/collection/TraversableLike;Lscala/collection/mutable/StringBuilder;Ljava/lang/String;Ljava/lang/String;Ljava/lang/String;)Lscala/collection/mutable/StringBuilder;
const #364 = Method	#42.#363;	//  scala/collection/TraversableLike$class.addString:(Lscala/collection/TraversableLike;Lscala/collection/mutable/StringBuilder;Ljava/lang/String;Ljava/lang/String;Ljava/lang/String;)Lscala/collection/mutable/StringBuilder;
const #365 = Asciz	end;
const #366 = Asciz	mkString;
const #367 = Asciz	()Ljava/lang/String;;
const #368 = Asciz	(Lscala/collection/TraversableLike;)Ljava/lang/String;;
const #369 = NameAndType	#366:#368;//  mkString:(Lscala/collection/TraversableLike;)Ljava/lang/String;
const #370 = Method	#42.#369;	//  scala/collection/TraversableLike$class.mkString:(Lscala/collection/TraversableLike;)Ljava/lang/String;
const #371 = Asciz	(Ljava/lang/String;)Ljava/lang/String;;
const #372 = Asciz	(Lscala/collection/TraversableLike;Ljava/lang/String;)Ljava/lang/String;;
const #373 = NameAndType	#366:#372;//  mkString:(Lscala/collection/TraversableLike;Ljava/lang/String;)Ljava/lang/String;
const #374 = Method	#42.#373;	//  scala/collection/TraversableLike$class.mkString:(Lscala/collection/TraversableLike;Ljava/lang/String;)Ljava/lang/String;
const #375 = Asciz	(Ljava/lang/String;Ljava/lang/String;Ljava/lang/String;)Ljava/lang/String;;
const #376 = Asciz	(Lscala/collection/TraversableLike;Ljava/lang/String;Ljava/lang/String;Ljava/lang/String;)Ljava/lang/String;;
const #377 = NameAndType	#366:#376;//  mkString:(Lscala/collection/TraversableLike;Ljava/lang/String;Ljava/lang/String;Ljava/lang/String;)Ljava/lang/String;
const #378 = Method	#42.#377;	//  scala/collection/TraversableLike$class.mkString:(Lscala/collection/TraversableLike;Ljava/lang/String;Ljava/lang/String;Ljava/lang/String;)Ljava/lang/String;
const #379 = Asciz	toSet;
const #380 = Asciz	()Lscala/collection/immutable/Set;;
const #381 = Asciz	(Lscala/collection/TraversableLike;)Lscala/collection/immutable/Set;;
const #382 = NameAndType	#379:#381;//  toSet:(Lscala/collection/TraversableLike;)Lscala/collection/immutable/Set;
const #383 = Method	#42.#382;	//  scala/collection/TraversableLike$class.toSet:(Lscala/collection/TraversableLike;)Lscala/collection/immutable/Set;
const #384 = Asciz	toIndexedSeq;
const #385 = Asciz	()Lscala/collection/mutable/IndexedSeq;;
const #386 = Asciz	(Lscala/collection/TraversableLike;)Lscala/collection/mutable/IndexedSeq;;
const #387 = NameAndType	#384:#386;//  toIndexedSeq:(Lscala/collection/TraversableLike;)Lscala/collection/mutable/IndexedSeq;
const #388 = Method	#42.#387;	//  scala/collection/TraversableLike$class.toIndexedSeq:(Lscala/collection/TraversableLike;)Lscala/collection/mutable/IndexedSeq;
const #389 = Asciz	toList;
const #390 = Asciz	()Lscala/collection/immutable/List;;
const #391 = Asciz	(Lscala/collection/TraversableLike;)Lscala/collection/immutable/List;;
const #392 = NameAndType	#389:#391;//  toList:(Lscala/collection/TraversableLike;)Lscala/collection/immutable/List;
const #393 = Method	#42.#392;	//  scala/collection/TraversableLike$class.toList:(Lscala/collection/TraversableLike;)Lscala/collection/immutable/List;
const #394 = Asciz	toArray;
const #395 = Asciz	(Lscala/reflect/ClassManifest;)Ljava/lang/Object;;
const #396 = Asciz	(Lscala/collection/TraversableLike;Lscala/reflect/ClassManifest;)Ljava/lang/Object;;
const #397 = NameAndType	#394:#396;//  toArray:(Lscala/collection/TraversableLike;Lscala/reflect/ClassManifest;)Ljava/lang/Object;
const #398 = Method	#42.#397;	//  scala/collection/TraversableLike$class.toArray:(Lscala/collection/TraversableLike;Lscala/reflect/ClassManifest;)Ljava/lang/Object;
const #399 = Asciz	evidence$1;
const #400 = Asciz	Lscala/reflect/ClassManifest;;
const #401 = Asciz	copyToArray;
const #402 = Asciz	(Ljava/lang/Object;)V;
const #403 = Asciz	(Lscala/collection/TraversableLike;Ljava/lang/Object;)V;
const #404 = NameAndType	#401:#403;//  copyToArray:(Lscala/collection/TraversableLike;Ljava/lang/Object;)V
const #405 = Method	#42.#404;	//  scala/collection/TraversableLike$class.copyToArray:(Lscala/collection/TraversableLike;Ljava/lang/Object;)V
const #406 = Asciz	xs;
const #407 = Asciz	(Ljava/lang/Object;I)V;
const #408 = Asciz	(Lscala/collection/TraversableLike;Ljava/lang/Object;I)V;
const #409 = NameAndType	#401:#408;//  copyToArray:(Lscala/collection/TraversableLike;Ljava/lang/Object;I)V
const #410 = Method	#42.#409;	//  scala/collection/TraversableLike$class.copyToArray:(Lscala/collection/TraversableLike;Ljava/lang/Object;I)V
const #411 = Asciz	copyToBuffer;
const #412 = Asciz	(Lscala/collection/mutable/Buffer;)V;
const #413 = Asciz	(Lscala/collection/TraversableLike;Lscala/collection/mutable/Buffer;)V;
const #414 = NameAndType	#411:#413;//  copyToBuffer:(Lscala/collection/TraversableLike;Lscala/collection/mutable/Buffer;)V
const #415 = Method	#42.#414;	//  scala/collection/TraversableLike$class.copyToBuffer:(Lscala/collection/TraversableLike;Lscala/collection/mutable/Buffer;)V
const #416 = Asciz	dest;
const #417 = Asciz	Lscala/collection/mutable/Buffer;;
const #418 = Asciz	lastOption;
const #419 = Asciz	()Lscala/Option;;
const #420 = Asciz	(Lscala/collection/TraversableLike;)Lscala/Option;;
const #421 = NameAndType	#418:#420;//  lastOption:(Lscala/collection/TraversableLike;)Lscala/Option;
const #422 = Method	#42.#421;	//  scala/collection/TraversableLike$class.lastOption:(Lscala/collection/TraversableLike;)Lscala/Option;
const #423 = Asciz	headOption;
const #424 = NameAndType	#423:#420;//  headOption:(Lscala/collection/TraversableLike;)Lscala/Option;
const #425 = Method	#42.#424;	//  scala/collection/TraversableLike$class.headOption:(Lscala/collection/TraversableLike;)Lscala/Option;
const #426 = Asciz	max;
const #427 = Asciz	(Lscala/math/Ordering;)Ljava/lang/Object;;
const #428 = Asciz	(Lscala/collection/TraversableLike;Lscala/math/Ordering;)Ljava/lang/Object;;
const #429 = NameAndType	#426:#428;//  max:(Lscala/collection/TraversableLike;Lscala/math/Ordering;)Ljava/lang/Object;
const #430 = Method	#42.#429;	//  scala/collection/TraversableLike$class.max:(Lscala/collection/TraversableLike;Lscala/math/Ordering;)Ljava/lang/Object;
const #431 = Asciz	cmp;
const #432 = Asciz	Lscala/math/Ordering;;
const #433 = Asciz	min;
const #434 = NameAndType	#433:#428;//  min:(Lscala/collection/TraversableLike;Lscala/math/Ordering;)Ljava/lang/Object;
const #435 = Method	#42.#434;	//  scala/collection/TraversableLike$class.min:(Lscala/collection/TraversableLike;Lscala/math/Ordering;)Ljava/lang/Object;
const #436 = Asciz	product;
const #437 = Asciz	(Lscala/math/Numeric;)Ljava/lang/Object;;
const #438 = Asciz	(Lscala/collection/TraversableLike;Lscala/math/Numeric;)Ljava/lang/Object;;
const #439 = NameAndType	#436:#438;//  product:(Lscala/collection/TraversableLike;Lscala/math/Numeric;)Ljava/lang/Object;
const #440 = Method	#42.#439;	//  scala/collection/TraversableLike$class.product:(Lscala/collection/TraversableLike;Lscala/math/Numeric;)Ljava/lang/Object;
const #441 = Asciz	num;
const #442 = Asciz	Lscala/math/Numeric;;
const #443 = Asciz	sum;
const #444 = NameAndType	#443:#438;//  sum:(Lscala/collection/TraversableLike;Lscala/math/Numeric;)Ljava/lang/Object;
const #445 = Method	#42.#444;	//  scala/collection/TraversableLike$class.sum:(Lscala/collection/TraversableLike;Lscala/math/Numeric;)Ljava/lang/Object;
const #446 = Asciz	reduceRightOption;
const #447 = Asciz	(Lscala/Function2;)Lscala/Option;;
const #448 = Asciz	(Lscala/collection/TraversableLike;Lscala/Function2;)Lscala/Option;;
const #449 = NameAndType	#446:#448;//  reduceRightOption:(Lscala/collection/TraversableLike;Lscala/Function2;)Lscala/Option;
const #450 = Method	#42.#449;	//  scala/collection/TraversableLike$class.reduceRightOption:(Lscala/collection/TraversableLike;Lscala/Function2;)Lscala/Option;
const #451 = Asciz	op;
const #452 = Asciz	Lscala/Function2;;
const #453 = Asciz	reduceLeftOption;
const #454 = NameAndType	#453:#448;//  reduceLeftOption:(Lscala/collection/TraversableLike;Lscala/Function2;)Lscala/Option;
const #455 = Method	#42.#454;	//  scala/collection/TraversableLike$class.reduceLeftOption:(Lscala/collection/TraversableLike;Lscala/Function2;)Lscala/Option;
const #456 = Asciz	$colon$bslash;
const #457 = Asciz	(Ljava/lang/Object;Lscala/Function2;)Ljava/lang/Object;;
const #458 = Asciz	(Lscala/collection/TraversableLike;Ljava/lang/Object;Lscala/Function2;)Ljava/lang/Object;;
const #459 = NameAndType	#456:#458;//  $colon$bslash:(Lscala/collection/TraversableLike;Ljava/lang/Object;Lscala/Function2;)Ljava/lang/Object;
const #460 = Method	#42.#459;	//  scala/collection/TraversableLike$class.$colon$bslash:(Lscala/collection/TraversableLike;Ljava/lang/Object;Lscala/Function2;)Ljava/lang/Object;
const #461 = Asciz	z;
const #462 = Asciz	$div$colon;
const #463 = NameAndType	#462:#458;//  $div$colon:(Lscala/collection/TraversableLike;Ljava/lang/Object;Lscala/Function2;)Ljava/lang/Object;
const #464 = Method	#42.#463;	//  scala/collection/TraversableLike$class.$div$colon:(Lscala/collection/TraversableLike;Ljava/lang/Object;Lscala/Function2;)Ljava/lang/Object;
const #465 = Asciz	count;
const #466 = Asciz	(Lscala/Function1;)I;
const #467 = Asciz	(Lscala/collection/TraversableLike;Lscala/Function1;)I;
const #468 = NameAndType	#465:#467;//  count:(Lscala/collection/TraversableLike;Lscala/Function1;)I
const #469 = Method	#42.#468;	//  scala/collection/TraversableLike$class.count:(Lscala/collection/TraversableLike;Lscala/Function1;)I
const #470 = Asciz	groupBy;
const #471 = Asciz	(Lscala/Function1;)Lscala/collection/Map;;
const #472 = Asciz	(Lscala/collection/TraversableLike;Lscala/Function1;)Lscala/collection/Map;;
const #473 = NameAndType	#470:#472;//  groupBy:(Lscala/collection/TraversableLike;Lscala/Function1;)Lscala/collection/Map;
const #474 = Method	#42.#473;	//  scala/collection/TraversableLike$class.groupBy:(Lscala/collection/TraversableLike;Lscala/Function1;)Lscala/collection/Map;
const #475 = Asciz	partition;
const #476 = Asciz	(Lscala/Function1;)Lscala/Tuple2;;
const #477 = Asciz	(Lscala/collection/TraversableLike;Lscala/Function1;)Lscala/Tuple2;;
const #478 = NameAndType	#475:#477;//  partition:(Lscala/collection/TraversableLike;Lscala/Function1;)Lscala/Tuple2;
const #479 = Method	#42.#478;	//  scala/collection/TraversableLike$class.partition:(Lscala/collection/TraversableLike;Lscala/Function1;)Lscala/Tuple2;
const #480 = Asciz	partialMap;
const #481 = Asciz	(Lscala/PartialFunction;Lscala/collection/generic/CanBuildFrom;)Ljava/lang/Object;;
const #482 = Asciz	(Lscala/collection/TraversableLike;Lscala/PartialFunction;Lscala/collection/generic/CanBuildFrom;)Ljava/lang/Object;;
const #483 = NameAndType	#480:#482;//  partialMap:(Lscala/collection/TraversableLike;Lscala/PartialFunction;Lscala/collection/generic/CanBuildFrom;)Ljava/lang/Object;
const #484 = Method	#42.#483;	//  scala/collection/TraversableLike$class.partialMap:(Lscala/collection/TraversableLike;Lscala/PartialFunction;Lscala/collection/generic/CanBuildFrom;)Ljava/lang/Object;
const #485 = Asciz	pf;
const #486 = Asciz	bf;
const #487 = Asciz	Lscala/collection/generic/CanBuildFrom;;
const #488 = Asciz	filterNot;
const #489 = Asciz	(Lscala/collection/TraversableLike;Lscala/Function1;)Ljava/lang/Object;;
const #490 = NameAndType	#488:#489;//  filterNot:(Lscala/collection/TraversableLike;Lscala/Function1;)Ljava/lang/Object;
const #491 = Method	#42.#490;	//  scala/collection/TraversableLike$class.filterNot:(Lscala/collection/TraversableLike;Lscala/Function1;)Ljava/lang/Object;
const #492 = Asciz	hasDefiniteSize;
const #493 = Asciz	()Z;
const #494 = Asciz	(Lscala/collection/TraversableLike;)Z;
const #495 = NameAndType	#492:#494;//  hasDefiniteSize:(Lscala/collection/TraversableLike;)Z
const #496 = Method	#42.#495;	//  scala/collection/TraversableLike$class.hasDefiniteSize:(Lscala/collection/TraversableLike;)Z
const #497 = Asciz	nonEmpty;
const #498 = NameAndType	#497:#494;//  nonEmpty:(Lscala/collection/TraversableLike;)Z
const #499 = Method	#42.#498;	//  scala/collection/TraversableLike$class.nonEmpty:(Lscala/collection/TraversableLike;)Z
const #500 = Asciz	(Lscala/collection/TraversableLike;)Ljava/lang/Object;;
const #501 = NameAndType	#288:#500;//  repr:(Lscala/collection/TraversableLike;)Ljava/lang/Object;
const #502 = Method	#42.#501;	//  scala/collection/TraversableLike$class.repr:(Lscala/collection/TraversableLike;)Ljava/lang/Object;
const #503 = Asciz	transpose;
const #504 = Asciz	(Lscala/Function1;)Lscala/collection/Traversable;;
const #505 = Asciz	(Lscala/collection/generic/GenericTraversableTemplate;Lscala/Function1;)Lscala/collection/Traversable;;
const #506 = NameAndType	#503:#505;//  transpose:(Lscala/collection/generic/GenericTraversableTemplate;Lscala/Function1;)Lscala/collection/Traversable;
const #507 = Method	#47.#506;	//  scala/collection/generic/GenericTraversableTemplate$class.transpose:(Lscala/collection/generic/GenericTraversableTemplate;Lscala/Function1;)Lscala/collection/Traversable;
const #508 = Asciz	asTraversable;
const #509 = Asciz	flatten;
const #510 = NameAndType	#509:#505;//  flatten:(Lscala/collection/generic/GenericTraversableTemplate;Lscala/Function1;)Lscala/collection/Traversable;
const #511 = Method	#47.#510;	//  scala/collection/generic/GenericTraversableTemplate$class.flatten:(Lscala/collection/generic/GenericTraversableTemplate;Lscala/Function1;)Lscala/collection/Traversable;
const #512 = Asciz	unzip;
const #513 = Asciz	(Lscala/collection/generic/GenericTraversableTemplate;Lscala/Function1;)Lscala/Tuple2;;
const #514 = NameAndType	#512:#513;//  unzip:(Lscala/collection/generic/GenericTraversableTemplate;Lscala/Function1;)Lscala/Tuple2;
const #515 = Method	#47.#514;	//  scala/collection/generic/GenericTraversableTemplate$class.unzip:(Lscala/collection/generic/GenericTraversableTemplate;Lscala/Function1;)Lscala/Tuple2;
const #516 = Asciz	asPair;
const #517 = Asciz	genericBuilder;
const #518 = Asciz	()Lscala/collection/mutable/Builder;;
const #519 = Asciz	(Lscala/collection/generic/GenericTraversableTemplate;)Lscala/collection/mutable/Builder;;
const #520 = NameAndType	#517:#519;//  genericBuilder:(Lscala/collection/generic/GenericTraversableTemplate;)Lscala/collection/mutable/Builder;
const #521 = Method	#47.#520;	//  scala/collection/generic/GenericTraversableTemplate$class.genericBuilder:(Lscala/collection/generic/GenericTraversableTemplate;)Lscala/collection/mutable/Builder;
const #522 = Asciz	firstOption;
const #523 = Asciz	(Lscala/collection/IterableLike;)Lscala/Option;;
const #524 = NameAndType	#522:#523;//  firstOption:(Lscala/collection/IterableLike;)Lscala/Option;
const #525 = Method	#57.#524;	//  scala/collection/IterableLike$class.firstOption:(Lscala/collection/IterableLike;)Lscala/Option;
const #526 = Asciz	Deprecated;
const #527 = Asciz	first;
const #528 = Asciz	(Lscala/collection/IterableLike;)Ljava/lang/Object;;
const #529 = NameAndType	#527:#528;//  first:(Lscala/collection/IterableLike;)Ljava/lang/Object;
const #530 = Method	#57.#529;	//  scala/collection/IterableLike$class.first:(Lscala/collection/IterableLike;)Ljava/lang/Object;
const #531 = Asciz	canEqual;
const #532 = Asciz	(Lscala/collection/IterableLike;Ljava/lang/Object;)Z;
const #533 = NameAndType	#531:#532;//  canEqual:(Lscala/collection/IterableLike;Ljava/lang/Object;)Z
const #534 = Method	#57.#533;	//  scala/collection/IterableLike$class.canEqual:(Lscala/collection/IterableLike;Ljava/lang/Object;)Z
const #535 = Asciz	toStream;
const #536 = Asciz	()Lscala/collection/immutable/Stream;;
const #537 = Asciz	(Lscala/collection/IterableLike;)Lscala/collection/immutable/Stream;;
const #538 = NameAndType	#535:#537;//  toStream:(Lscala/collection/IterableLike;)Lscala/collection/immutable/Stream;
const #539 = Method	#57.#538;	//  scala/collection/IterableLike$class.toStream:(Lscala/collection/IterableLike;)Lscala/collection/immutable/Stream;
const #540 = Asciz	toIterable;
const #541 = Asciz	(Lscala/collection/IterableLike;)Lscala/collection/Iterable;;
const #542 = NameAndType	#540:#541;//  toIterable:(Lscala/collection/IterableLike;)Lscala/collection/Iterable;
const #543 = Method	#57.#542;	//  scala/collection/IterableLike$class.toIterable:(Lscala/collection/IterableLike;)Lscala/collection/Iterable;
const #544 = Asciz	elements;
const #545 = Asciz	()Lscala/collection/Iterator;;
const #546 = Asciz	(Lscala/collection/IterableLike;)Lscala/collection/Iterator;;
const #547 = NameAndType	#544:#546;//  elements:(Lscala/collection/IterableLike;)Lscala/collection/Iterator;
const #548 = Method	#57.#547;	//  scala/collection/IterableLike$class.elements:(Lscala/collection/IterableLike;)Lscala/collection/Iterator;
const #549 = Asciz	projection;
const #550 = Asciz	(Lscala/collection/SeqLike;)Ljava/lang/Object;;
const #551 = NameAndType	#549:#550;//  projection:(Lscala/collection/SeqLike;)Ljava/lang/Object;
const #552 = Method	#67.#551;	//  scala/collection/SeqLike$class.projection:(Lscala/collection/SeqLike;)Ljava/lang/Object;
const #553 = Asciz	equalsWith;
const #554 = Asciz	(Lscala/collection/Seq;Lscala/Function2;)Z;
const #555 = Asciz	(Lscala/collection/SeqLike;Lscala/collection/Seq;Lscala/Function2;)Z;
const #556 = NameAndType	#553:#555;//  equalsWith:(Lscala/collection/SeqLike;Lscala/collection/Seq;Lscala/Function2;)Z
const #557 = Method	#67.#556;	//  scala/collection/SeqLike$class.equalsWith:(Lscala/collection/SeqLike;Lscala/collection/Seq;Lscala/Function2;)Z
const #558 = Asciz	findLastIndexOf;
const #559 = Asciz	(Lscala/collection/SeqLike;Lscala/Function1;)I;
const #560 = NameAndType	#558:#559;//  findLastIndexOf:(Lscala/collection/SeqLike;Lscala/Function1;)I
const #561 = Method	#67.#560;	//  scala/collection/SeqLike$class.findLastIndexOf:(Lscala/collection/SeqLike;Lscala/Function1;)I
const #562 = Asciz	toString;
const #563 = Asciz	(Lscala/collection/SeqLike;)Ljava/lang/String;;
const #564 = NameAndType	#562:#563;//  toString:(Lscala/collection/SeqLike;)Ljava/lang/String;
const #565 = Method	#67.#564;	//  scala/collection/SeqLike$class.toString:(Lscala/collection/SeqLike;)Ljava/lang/String;
const #566 = Asciz	equals;
const #567 = Asciz	(Lscala/collection/SeqLike;Ljava/lang/Object;)Z;
const #568 = NameAndType	#566:#567;//  equals:(Lscala/collection/SeqLike;Ljava/lang/Object;)Z
const #569 = Method	#67.#568;	//  scala/collection/SeqLike$class.equals:(Lscala/collection/SeqLike;Ljava/lang/Object;)Z
const #570 = Asciz	hashCode;
const #571 = Asciz	()I;
const #572 = Asciz	(Lscala/collection/SeqLike;)I;
const #573 = NameAndType	#570:#572;//  hashCode:(Lscala/collection/SeqLike;)I
const #574 = Method	#67.#573;	//  scala/collection/SeqLike$class.hashCode:(Lscala/collection/SeqLike;)I
const #575 = Asciz	indices;
const #576 = Asciz	()Lscala/collection/immutable/Range;;
const #577 = Asciz	(Lscala/collection/SeqLike;)Lscala/collection/immutable/Range;;
const #578 = NameAndType	#575:#577;//  indices:(Lscala/collection/SeqLike;)Lscala/collection/immutable/Range;
const #579 = Method	#67.#578;	//  scala/collection/SeqLike$class.indices:(Lscala/collection/SeqLike;)Lscala/collection/immutable/Range;
const #580 = Asciz	toSeq;
const #581 = Asciz	(Lscala/collection/SeqLike;)Lscala/collection/Seq;;
const #582 = NameAndType	#580:#581;//  toSeq:(Lscala/collection/SeqLike;)Lscala/collection/Seq;
const #583 = Method	#67.#582;	//  scala/collection/SeqLike$class.toSeq:(Lscala/collection/SeqLike;)Lscala/collection/Seq;
const #584 = Asciz	sortBy;
const #585 = Asciz	(Lscala/Function1;Lscala/math/Ordering;)Ljava/lang/Object;;
const #586 = Asciz	(Lscala/collection/SeqLike;Lscala/Function1;Lscala/math/Ordering;)Ljava/lang/Object;;
const #587 = NameAndType	#584:#586;//  sortBy:(Lscala/collection/SeqLike;Lscala/Function1;Lscala/math/Ordering;)Ljava/lang/Object;
const #588 = Method	#67.#587;	//  scala/collection/SeqLike$class.sortBy:(Lscala/collection/SeqLike;Lscala/Function1;Lscala/math/Ordering;)Ljava/lang/Object;
const #589 = Asciz	ord;
const #590 = Asciz	sortWith;
const #591 = Asciz	(Lscala/collection/SeqLike;Lscala/math/Ordering;)Ljava/lang/Object;;
const #592 = NameAndType	#590:#591;//  sortWith:(Lscala/collection/SeqLike;Lscala/math/Ordering;)Ljava/lang/Object;
const #593 = Method	#67.#592;	//  scala/collection/SeqLike$class.sortWith:(Lscala/collection/SeqLike;Lscala/math/Ordering;)Ljava/lang/Object;
const #594 = Asciz	(Lscala/Function2;)Ljava/lang/Object;;
const #595 = Asciz	(Lscala/collection/SeqLike;Lscala/Function2;)Ljava/lang/Object;;
const #596 = NameAndType	#590:#595;//  sortWith:(Lscala/collection/SeqLike;Lscala/Function2;)Ljava/lang/Object;
const #597 = Method	#67.#596;	//  scala/collection/SeqLike$class.sortWith:(Lscala/collection/SeqLike;Lscala/Function2;)Ljava/lang/Object;
const #598 = Asciz	lt;
const #599 = Asciz	corresponds;
const #600 = NameAndType	#599:#555;//  corresponds:(Lscala/collection/SeqLike;Lscala/collection/Seq;Lscala/Function2;)Z
const #601 = Method	#67.#600;	//  scala/collection/SeqLike$class.corresponds:(Lscala/collection/SeqLike;Lscala/collection/Seq;Lscala/Function2;)Z
const #602 = Asciz	$colon$plus;
const #603 = Asciz	(Ljava/lang/Object;Lscala/collection/generic/CanBuildFrom;)Ljava/lang/Object;;
const #604 = Asciz	(Lscala/collection/SeqLike;Ljava/lang/Object;Lscala/collection/generic/CanBuildFrom;)Ljava/lang/Object;;
const #605 = NameAndType	#602:#604;//  $colon$plus:(Lscala/collection/SeqLike;Ljava/lang/Object;Lscala/collection/generic/CanBuildFrom;)Ljava/lang/Object;
const #606 = Method	#67.#605;	//  scala/collection/SeqLike$class.$colon$plus:(Lscala/collection/SeqLike;Ljava/lang/Object;Lscala/collection/generic/CanBuildFrom;)Ljava/lang/Object;
const #607 = Asciz	elem;
const #608 = Asciz	$plus$colon;
const #609 = NameAndType	#608:#604;//  $plus$colon:(Lscala/collection/SeqLike;Ljava/lang/Object;Lscala/collection/generic/CanBuildFrom;)Ljava/lang/Object;
const #610 = Method	#67.#609;	//  scala/collection/SeqLike$class.$plus$colon:(Lscala/collection/SeqLike;Ljava/lang/Object;Lscala/collection/generic/CanBuildFrom;)Ljava/lang/Object;
const #611 = Asciz	updated;
const #612 = Asciz	(ILjava/lang/Object;Lscala/collection/generic/CanBuildFrom;)Ljava/lang/Object;;
const #613 = Asciz	(Lscala/collection/SeqLike;ILjava/lang/Object;Lscala/collection/generic/CanBuildFrom;)Ljava/lang/Object;;
const #614 = NameAndType	#611:#613;//  updated:(Lscala/collection/SeqLike;ILjava/lang/Object;Lscala/collection/generic/CanBuildFrom;)Ljava/lang/Object;
const #615 = Method	#67.#614;	//  scala/collection/SeqLike$class.updated:(Lscala/collection/SeqLike;ILjava/lang/Object;Lscala/collection/generic/CanBuildFrom;)Ljava/lang/Object;
const #616 = Asciz	index;
const #617 = Asciz	removeDuplicates;
const #618 = NameAndType	#617:#550;//  removeDuplicates:(Lscala/collection/SeqLike;)Ljava/lang/Object;
const #619 = Method	#67.#618;	//  scala/collection/SeqLike$class.removeDuplicates:(Lscala/collection/SeqLike;)Ljava/lang/Object;
const #620 = Asciz	intersect;
const #621 = Asciz	(Lscala/collection/Seq;)Ljava/lang/Object;;
const #622 = Asciz	(Lscala/collection/SeqLike;Lscala/collection/Seq;)Ljava/lang/Object;;
const #623 = NameAndType	#620:#622;//  intersect:(Lscala/collection/SeqLike;Lscala/collection/Seq;)Ljava/lang/Object;
const #624 = Method	#67.#623;	//  scala/collection/SeqLike$class.intersect:(Lscala/collection/SeqLike;Lscala/collection/Seq;)Ljava/lang/Object;
const #625 = Asciz	diff;
const #626 = NameAndType	#625:#622;//  diff:(Lscala/collection/SeqLike;Lscala/collection/Seq;)Ljava/lang/Object;
const #627 = Method	#67.#626;	//  scala/collection/SeqLike$class.diff:(Lscala/collection/SeqLike;Lscala/collection/Seq;)Ljava/lang/Object;
const #628 = Asciz	union;
const #629 = Asciz	(Lscala/collection/Seq;Lscala/collection/generic/CanBuildFrom;)Ljava/lang/Object;;
const #630 = Asciz	(Lscala/collection/SeqLike;Lscala/collection/Seq;Lscala/collection/generic/CanBuildFrom;)Ljava/lang/Object;;
const #631 = NameAndType	#628:#630;//  union:(Lscala/collection/SeqLike;Lscala/collection/Seq;Lscala/collection/generic/CanBuildFrom;)Ljava/lang/Object;
const #632 = Method	#67.#631;	//  scala/collection/SeqLike$class.union:(Lscala/collection/SeqLike;Lscala/collection/Seq;Lscala/collection/generic/CanBuildFrom;)Ljava/lang/Object;
const #633 = Asciz	contains;
const #634 = NameAndType	#633:#567;//  contains:(Lscala/collection/SeqLike;Ljava/lang/Object;)Z
const #635 = Method	#67.#634;	//  scala/collection/SeqLike$class.contains:(Lscala/collection/SeqLike;Ljava/lang/Object;)Z
const #636 = Asciz	containsSlice;
const #637 = Asciz	(Lscala/collection/Seq;)Z;
const #638 = Asciz	(Lscala/collection/SeqLike;Lscala/collection/Seq;)Z;
const #639 = NameAndType	#636:#638;//  containsSlice:(Lscala/collection/SeqLike;Lscala/collection/Seq;)Z
const #640 = Method	#67.#639;	//  scala/collection/SeqLike$class.containsSlice:(Lscala/collection/SeqLike;Lscala/collection/Seq;)Z
const #641 = Asciz	lastIndexOfSlice;
const #642 = Asciz	(Lscala/collection/Seq;I)I;
const #643 = Asciz	(Lscala/collection/SeqLike;Lscala/collection/Seq;I)I;
const #644 = NameAndType	#641:#643;//  lastIndexOfSlice:(Lscala/collection/SeqLike;Lscala/collection/Seq;I)I
const #645 = Method	#67.#644;	//  scala/collection/SeqLike$class.lastIndexOfSlice:(Lscala/collection/SeqLike;Lscala/collection/Seq;I)I
const #646 = Asciz	(Lscala/collection/Seq;)I;
const #647 = Asciz	(Lscala/collection/SeqLike;Lscala/collection/Seq;)I;
const #648 = NameAndType	#641:#647;//  lastIndexOfSlice:(Lscala/collection/SeqLike;Lscala/collection/Seq;)I
const #649 = Method	#67.#648;	//  scala/collection/SeqLike$class.lastIndexOfSlice:(Lscala/collection/SeqLike;Lscala/collection/Seq;)I
const #650 = Asciz	indexOfSlice;
const #651 = NameAndType	#650:#643;//  indexOfSlice:(Lscala/collection/SeqLike;Lscala/collection/Seq;I)I
const #652 = Method	#67.#651;	//  scala/collection/SeqLike$class.indexOfSlice:(Lscala/collection/SeqLike;Lscala/collection/Seq;I)I
const #653 = NameAndType	#650:#647;//  indexOfSlice:(Lscala/collection/SeqLike;Lscala/collection/Seq;)I
const #654 = Method	#67.#653;	//  scala/collection/SeqLike$class.indexOfSlice:(Lscala/collection/SeqLike;Lscala/collection/Seq;)I
const #655 = Asciz	startsWith;
const #656 = NameAndType	#655:#638;//  startsWith:(Lscala/collection/SeqLike;Lscala/collection/Seq;)Z
const #657 = Method	#67.#656;	//  scala/collection/SeqLike$class.startsWith:(Lscala/collection/SeqLike;Lscala/collection/Seq;)Z
const #658 = Asciz	reversedElements;
const #659 = Asciz	(Lscala/collection/SeqLike;)Lscala/collection/Iterator;;
const #660 = NameAndType	#658:#659;//  reversedElements:(Lscala/collection/SeqLike;)Lscala/collection/Iterator;
const #661 = Method	#67.#660;	//  scala/collection/SeqLike$class.reversedElements:(Lscala/collection/SeqLike;)Lscala/collection/Iterator;
const #662 = Asciz	reverseMap;
const #663 = Asciz	(Lscala/Function1;Lscala/collection/generic/CanBuildFrom;)Ljava/lang/Object;;
const #664 = Asciz	(Lscala/collection/SeqLike;Lscala/Function1;Lscala/collection/generic/CanBuildFrom;)Ljava/lang/Object;;
const #665 = NameAndType	#662:#664;//  reverseMap:(Lscala/collection/SeqLike;Lscala/Function1;Lscala/collection/generic/CanBuildFrom;)Ljava/lang/Object;
const #666 = Method	#67.#665;	//  scala/collection/SeqLike$class.reverseMap:(Lscala/collection/SeqLike;Lscala/Function1;Lscala/collection/generic/CanBuildFrom;)Ljava/lang/Object;
const #667 = Asciz	lastIndexWhere;
const #668 = NameAndType	#667:#559;//  lastIndexWhere:(Lscala/collection/SeqLike;Lscala/Function1;)I
const #669 = Method	#67.#668;	//  scala/collection/SeqLike$class.lastIndexWhere:(Lscala/collection/SeqLike;Lscala/Function1;)I
const #670 = Asciz	lastIndexOf;
const #671 = Asciz	(Ljava/lang/Object;I)I;
const #672 = Asciz	(Lscala/collection/SeqLike;Ljava/lang/Object;I)I;
const #673 = NameAndType	#670:#672;//  lastIndexOf:(Lscala/collection/SeqLike;Ljava/lang/Object;I)I
const #674 = Method	#67.#673;	//  scala/collection/SeqLike$class.lastIndexOf:(Lscala/collection/SeqLike;Ljava/lang/Object;I)I
const #675 = Asciz	(Lscala/collection/SeqLike;Ljava/lang/Object;)I;
const #676 = NameAndType	#670:#675;//  lastIndexOf:(Lscala/collection/SeqLike;Ljava/lang/Object;)I
const #677 = Method	#67.#676;	//  scala/collection/SeqLike$class.lastIndexOf:(Lscala/collection/SeqLike;Ljava/lang/Object;)I
const #678 = Asciz	indexOf;
const #679 = NameAndType	#678:#672;//  indexOf:(Lscala/collection/SeqLike;Ljava/lang/Object;I)I
const #680 = Method	#67.#679;	//  scala/collection/SeqLike$class.indexOf:(Lscala/collection/SeqLike;Ljava/lang/Object;I)I
const #681 = NameAndType	#678:#675;//  indexOf:(Lscala/collection/SeqLike;Ljava/lang/Object;)I
const #682 = Method	#67.#681;	//  scala/collection/SeqLike$class.indexOf:(Lscala/collection/SeqLike;Ljava/lang/Object;)I
const #683 = Asciz	findIndexOf;
const #684 = NameAndType	#683:#559;//  findIndexOf:(Lscala/collection/SeqLike;Lscala/Function1;)I
const #685 = Method	#67.#684;	//  scala/collection/SeqLike$class.findIndexOf:(Lscala/collection/SeqLike;Lscala/Function1;)I
const #686 = Asciz	indexWhere;
const #687 = NameAndType	#686:#559;//  indexWhere:(Lscala/collection/SeqLike;Lscala/Function1;)I
const #688 = Method	#67.#687;	//  scala/collection/SeqLike$class.indexWhere:(Lscala/collection/SeqLike;Lscala/Function1;)I
const #689 = Asciz	prefixLength;
const #690 = NameAndType	#689:#559;//  prefixLength:(Lscala/collection/SeqLike;Lscala/Function1;)I
const #691 = Method	#67.#690;	//  scala/collection/SeqLike$class.prefixLength:(Lscala/collection/SeqLike;Lscala/Function1;)I
const #692 = Asciz	(Lscala/collection/SeqLike;I)Z;
const #693 = NameAndType	#297:#692;//  isDefinedAt:(Lscala/collection/SeqLike;I)Z
const #694 = Method	#67.#693;	//  scala/collection/SeqLike$class.isDefinedAt:(Lscala/collection/SeqLike;I)Z
const #695 = Asciz	idx;
const #696 = Asciz	size;
const #697 = NameAndType	#696:#572;//  size:(Lscala/collection/SeqLike;)I
const #698 = Method	#67.#697;	//  scala/collection/SeqLike$class.size:(Lscala/collection/SeqLike;)I
const #699 = Asciz	(Lscala/collection/IndexedSeqLike;II)Lscala/collection/IndexedSeqView;;
const #700 = NameAndType	#291:#699;//  view:(Lscala/collection/IndexedSeqLike;II)Lscala/collection/IndexedSeqView;
const #701 = Method	#77.#700;	//  scala/collection/IndexedSeqLike$class.view:(Lscala/collection/IndexedSeqLike;II)Lscala/collection/IndexedSeqView;
const #702 = Asciz	(Lscala/collection/IndexedSeqLike;)Ljava/lang/Object;;
const #703 = NameAndType	#291:#702;//  view:(Lscala/collection/IndexedSeqLike;)Ljava/lang/Object;
const #704 = Method	#77.#703;	//  scala/collection/IndexedSeqLike$class.view:(Lscala/collection/IndexedSeqLike;)Ljava/lang/Object;
const #705 = Asciz	endsWith;
const #706 = Asciz	(Lscala/collection/IndexedSeqLike;Lscala/collection/Seq;)Z;
const #707 = NameAndType	#705:#706;//  endsWith:(Lscala/collection/IndexedSeqLike;Lscala/collection/Seq;)Z
const #708 = Method	#77.#707;	//  scala/collection/IndexedSeqLike$class.endsWith:(Lscala/collection/IndexedSeqLike;Lscala/collection/Seq;)Z
const #709 = Asciz	(Lscala/collection/Seq;I)Z;
const #710 = Asciz	(Lscala/collection/IndexedSeqLike;Lscala/collection/Seq;I)Z;
const #711 = NameAndType	#655:#710;//  startsWith:(Lscala/collection/IndexedSeqLike;Lscala/collection/Seq;I)Z
const #712 = Method	#77.#711;	//  scala/collection/IndexedSeqLike$class.startsWith:(Lscala/collection/IndexedSeqLike;Lscala/collection/Seq;I)Z
const #713 = Asciz	offset;
const #714 = Asciz	reverseIterator;
const #715 = Asciz	(Lscala/collection/IndexedSeqLike;)Lscala/collection/Iterator;;
const #716 = NameAndType	#714:#715;//  reverseIterator:(Lscala/collection/IndexedSeqLike;)Lscala/collection/Iterator;
const #717 = Method	#77.#716;	//  scala/collection/IndexedSeqLike$class.reverseIterator:(Lscala/collection/IndexedSeqLike;)Lscala/collection/Iterator;
const #718 = Asciz	(Lscala/Function1;I)I;
const #719 = Asciz	(Lscala/collection/IndexedSeqLike;Lscala/Function1;I)I;
const #720 = NameAndType	#667:#719;//  lastIndexWhere:(Lscala/collection/IndexedSeqLike;Lscala/Function1;I)I
const #721 = Method	#77.#720;	//  scala/collection/IndexedSeqLike$class.lastIndexWhere:(Lscala/collection/IndexedSeqLike;Lscala/Function1;I)I
const #722 = NameAndType	#686:#719;//  indexWhere:(Lscala/collection/IndexedSeqLike;Lscala/Function1;I)I
const #723 = Method	#77.#722;	//  scala/collection/IndexedSeqLike$class.indexWhere:(Lscala/collection/IndexedSeqLike;Lscala/Function1;I)I
const #724 = Asciz	segmentLength;
const #725 = NameAndType	#724:#719;//  segmentLength:(Lscala/collection/IndexedSeqLike;Lscala/Function1;I)I
const #726 = Method	#77.#725;	//  scala/collection/IndexedSeqLike$class.segmentLength:(Lscala/collection/IndexedSeqLike;Lscala/Function1;I)I
const #727 = Asciz	lengthCompare;
const #728 = Asciz	(I)I;
const #729 = Asciz	(Lscala/collection/IndexedSeqLike;I)I;
const #730 = NameAndType	#727:#729;//  lengthCompare:(Lscala/collection/IndexedSeqLike;I)I
const #731 = Method	#77.#730;	//  scala/collection/IndexedSeqLike$class.lengthCompare:(Lscala/collection/IndexedSeqLike;I)I
const #732 = Asciz	len;
const #733 = Asciz	(Ljava/lang/Object;II)V;
const #734 = Asciz	(Lscala/collection/IndexedSeqLike;Ljava/lang/Object;II)V;
const #735 = NameAndType	#401:#734;//  copyToArray:(Lscala/collection/IndexedSeqLike;Ljava/lang/Object;II)V
const #736 = Method	#77.#735;	//  scala/collection/IndexedSeqLike$class.copyToArray:(Lscala/collection/IndexedSeqLike;Ljava/lang/Object;II)V
const #737 = Asciz	sameElements;
const #738 = Asciz	(Lscala/collection/Iterable;)Z;
const #739 = Asciz	(Lscala/collection/IndexedSeqLike;Lscala/collection/Iterable;)Z;
const #740 = NameAndType	#737:#739;//  sameElements:(Lscala/collection/IndexedSeqLike;Lscala/collection/Iterable;)Z
const #741 = Method	#77.#740;	//  scala/collection/IndexedSeqLike$class.sameElements:(Lscala/collection/IndexedSeqLike;Lscala/collection/Iterable;)Z
const #742 = Asciz	dropRight;
const #743 = Asciz	(Lscala/collection/IndexedSeqLike;I)Ljava/lang/Object;;
const #744 = NameAndType	#742:#743;//  dropRight:(Lscala/collection/IndexedSeqLike;I)Ljava/lang/Object;
const #745 = Method	#77.#744;	//  scala/collection/IndexedSeqLike$class.dropRight:(Lscala/collection/IndexedSeqLike;I)Ljava/lang/Object;
const #746 = Asciz	takeRight;
const #747 = NameAndType	#746:#743;//  takeRight:(Lscala/collection/IndexedSeqLike;I)Ljava/lang/Object;
const #748 = Method	#77.#747;	//  scala/collection/IndexedSeqLike$class.takeRight:(Lscala/collection/IndexedSeqLike;I)Ljava/lang/Object;
const #749 = Asciz	last;
const #750 = NameAndType	#749:#702;//  last:(Lscala/collection/IndexedSeqLike;)Ljava/lang/Object;
const #751 = Method	#77.#750;	//  scala/collection/IndexedSeqLike$class.last:(Lscala/collection/IndexedSeqLike;)Ljava/lang/Object;
const #752 = Asciz	tail;
const #753 = NameAndType	#752:#702;//  tail:(Lscala/collection/IndexedSeqLike;)Ljava/lang/Object;
const #754 = Method	#77.#753;	//  scala/collection/IndexedSeqLike$class.tail:(Lscala/collection/IndexedSeqLike;)Ljava/lang/Object;
const #755 = Asciz	head;
const #756 = NameAndType	#755:#702;//  head:(Lscala/collection/IndexedSeqLike;)Ljava/lang/Object;
const #757 = Method	#77.#756;	//  scala/collection/IndexedSeqLike$class.head:(Lscala/collection/IndexedSeqLike;)Ljava/lang/Object;
const #758 = Asciz	reduceRight;
const #759 = Asciz	(Lscala/collection/IndexedSeqLike;Lscala/Function2;)Ljava/lang/Object;;
const #760 = NameAndType	#758:#759;//  reduceRight:(Lscala/collection/IndexedSeqLike;Lscala/Function2;)Ljava/lang/Object;
const #761 = Method	#77.#760;	//  scala/collection/IndexedSeqLike$class.reduceRight:(Lscala/collection/IndexedSeqLike;Lscala/Function2;)Ljava/lang/Object;
const #762 = Asciz	reduceLeft;
const #763 = NameAndType	#762:#759;//  reduceLeft:(Lscala/collection/IndexedSeqLike;Lscala/Function2;)Ljava/lang/Object;
const #764 = Method	#77.#763;	//  scala/collection/IndexedSeqLike$class.reduceLeft:(Lscala/collection/IndexedSeqLike;Lscala/Function2;)Ljava/lang/Object;
const #765 = Asciz	foldRight;
const #766 = Asciz	(Lscala/collection/IndexedSeqLike;Ljava/lang/Object;Lscala/Function2;)Ljava/lang/Object;;
const #767 = NameAndType	#765:#766;//  foldRight:(Lscala/collection/IndexedSeqLike;Ljava/lang/Object;Lscala/Function2;)Ljava/lang/Object;
const #768 = Method	#77.#767;	//  scala/collection/IndexedSeqLike$class.foldRight:(Lscala/collection/IndexedSeqLike;Ljava/lang/Object;Lscala/Function2;)Ljava/lang/Object;
const #769 = Asciz	foldLeft;
const #770 = NameAndType	#769:#766;//  foldLeft:(Lscala/collection/IndexedSeqLike;Ljava/lang/Object;Lscala/Function2;)Ljava/lang/Object;
const #771 = Method	#77.#770;	//  scala/collection/IndexedSeqLike$class.foldLeft:(Lscala/collection/IndexedSeqLike;Ljava/lang/Object;Lscala/Function2;)Ljava/lang/Object;
const #772 = Asciz	find;
const #773 = Asciz	(Lscala/Function1;)Lscala/Option;;
const #774 = Asciz	(Lscala/collection/IndexedSeqLike;Lscala/Function1;)Lscala/Option;;
const #775 = NameAndType	#772:#774;//  find:(Lscala/collection/IndexedSeqLike;Lscala/Function1;)Lscala/Option;
const #776 = Method	#77.#775;	//  scala/collection/IndexedSeqLike$class.find:(Lscala/collection/IndexedSeqLike;Lscala/Function1;)Lscala/Option;
const #777 = Asciz	exists;
const #778 = Asciz	(Lscala/Function1;)Z;
const #779 = Asciz	(Lscala/collection/IndexedSeqLike;Lscala/Function1;)Z;
const #780 = NameAndType	#777:#779;//  exists:(Lscala/collection/IndexedSeqLike;Lscala/Function1;)Z
const #781 = Method	#77.#780;	//  scala/collection/IndexedSeqLike$class.exists:(Lscala/collection/IndexedSeqLike;Lscala/Function1;)Z
const #782 = Asciz	forall;
const #783 = NameAndType	#782:#779;//  forall:(Lscala/collection/IndexedSeqLike;Lscala/Function1;)Z
const #784 = Method	#77.#783;	//  scala/collection/IndexedSeqLike$class.forall:(Lscala/collection/IndexedSeqLike;Lscala/Function1;)Z
const #785 = Asciz	isEmpty;
const #786 = Asciz	(Lscala/collection/IndexedSeqLike;)Z;
const #787 = NameAndType	#785:#786;//  isEmpty:(Lscala/collection/IndexedSeqLike;)Z
const #788 = Method	#77.#787;	//  scala/collection/IndexedSeqLike$class.isEmpty:(Lscala/collection/IndexedSeqLike;)Z
const #789 = Asciz	(Lscala/collection/IndexedSeqLike;Ljava/lang/Object;)Lscala/collection/IndexedSeq;;
const #790 = NameAndType	#283:#789;//  toCollection:(Lscala/collection/IndexedSeqLike;Ljava/lang/Object;)Lscala/collection/IndexedSeq;
const #791 = Method	#77.#790;	//  scala/collection/IndexedSeqLike$class.toCollection:(Lscala/collection/IndexedSeqLike;Ljava/lang/Object;)Lscala/collection/IndexedSeq;
const #792 = Asciz	(Lscala/collection/IndexedSeqLike;)Lscala/collection/IndexedSeq;;
const #793 = NameAndType	#274:#792;//  thisCollection:(Lscala/collection/IndexedSeqLike;)Lscala/collection/IndexedSeq;
const #794 = Method	#77.#793;	//  scala/collection/IndexedSeqLike$class.thisCollection:(Lscala/collection/IndexedSeqLike;)Lscala/collection/IndexedSeq;
const #795 = Asciz	scala$collection$IndexedSeqLike$$super$endsWith;
const #796 = NameAndType	#705:#638;//  endsWith:(Lscala/collection/SeqLike;Lscala/collection/Seq;)Z
const #797 = Method	#67.#796;	//  scala/collection/SeqLike$class.endsWith:(Lscala/collection/SeqLike;Lscala/collection/Seq;)Z
const #798 = Asciz	scala$collection$IndexedSeqLike$$super$sameElements;
const #799 = Asciz	(Lscala/collection/IterableLike;Lscala/collection/Iterable;)Z;
const #800 = NameAndType	#737:#799;//  sameElements:(Lscala/collection/IterableLike;Lscala/collection/Iterable;)Z
const #801 = Method	#57.#800;	//  scala/collection/IterableLike$class.sameElements:(Lscala/collection/IterableLike;Lscala/collection/Iterable;)Z
const #802 = Asciz	scala$collection$IndexedSeqLike$$super$init;
const #803 = NameAndType	#200:#500;//  init:(Lscala/collection/TraversableLike;)Ljava/lang/Object;
const #804 = Method	#42.#803;	//  scala/collection/TraversableLike$class.init:(Lscala/collection/TraversableLike;)Ljava/lang/Object;
const #805 = Asciz	scala$collection$IndexedSeqLike$$super$last;
const #806 = NameAndType	#749:#500;//  last:(Lscala/collection/TraversableLike;)Ljava/lang/Object;
const #807 = Method	#42.#806;	//  scala/collection/TraversableLike$class.last:(Lscala/collection/TraversableLike;)Ljava/lang/Object;
const #808 = Asciz	scala$collection$IndexedSeqLike$$super$tail;
const #809 = NameAndType	#752:#500;//  tail:(Lscala/collection/TraversableLike;)Ljava/lang/Object;
const #810 = Method	#42.#809;	//  scala/collection/TraversableLike$class.tail:(Lscala/collection/TraversableLike;)Ljava/lang/Object;
const #811 = Asciz	scala$collection$IndexedSeqLike$$super$head;
const #812 = NameAndType	#755:#528;//  head:(Lscala/collection/IterableLike;)Ljava/lang/Object;
const #813 = Method	#57.#812;	//  scala/collection/IterableLike$class.head:(Lscala/collection/IterableLike;)Ljava/lang/Object;
const #814 = Asciz	scala$collection$IndexedSeqLike$$super$zip;
const #815 = Asciz	(Lscala/collection/Iterable;Lscala/collection/generic/CanBuildFrom;)Ljava/lang/Object;;
const #816 = Asciz	zip;
const #817 = Asciz	(Lscala/collection/IterableLike;Lscala/collection/Iterable;Lscala/collection/generic/CanBuildFrom;)Ljava/lang/Object;;
const #818 = NameAndType	#816:#817;//  zip:(Lscala/collection/IterableLike;Lscala/collection/Iterable;Lscala/collection/generic/CanBuildFrom;)Ljava/lang/Object;
const #819 = Method	#57.#818;	//  scala/collection/IterableLike$class.zip:(Lscala/collection/IterableLike;Lscala/collection/Iterable;Lscala/collection/generic/CanBuildFrom;)Ljava/lang/Object;
const #820 = Asciz	scala$collection$IndexedSeqLike$$super$reduceRight;
const #821 = Asciz	(Lscala/collection/IterableLike;Lscala/Function2;)Ljava/lang/Object;;
const #822 = NameAndType	#758:#821;//  reduceRight:(Lscala/collection/IterableLike;Lscala/Function2;)Ljava/lang/Object;
const #823 = Method	#57.#822;	//  scala/collection/IterableLike$class.reduceRight:(Lscala/collection/IterableLike;Lscala/Function2;)Ljava/lang/Object;
const #824 = Asciz	scala$collection$IndexedSeqLike$$super$reduceLeft;
const #825 = Asciz	(Lscala/collection/TraversableLike;Lscala/Function2;)Ljava/lang/Object;;
const #826 = NameAndType	#762:#825;//  reduceLeft:(Lscala/collection/TraversableLike;Lscala/Function2;)Ljava/lang/Object;
const #827 = Method	#42.#826;	//  scala/collection/TraversableLike$class.reduceLeft:(Lscala/collection/TraversableLike;Lscala/Function2;)Ljava/lang/Object;
const #828 = Asciz	companion;
const #829 = Asciz	()Lscala/collection/generic/GenericCompanion;;
const #830 = Asciz	(Lscala/collection/IndexedSeq;)Lscala/collection/generic/GenericCompanion;;
const #831 = NameAndType	#828:#830;//  companion:(Lscala/collection/IndexedSeq;)Lscala/collection/generic/GenericCompanion;
const #832 = Method	#82.#831;	//  scala/collection/IndexedSeq$class.companion:(Lscala/collection/IndexedSeq;)Lscala/collection/generic/GenericCompanion;
const #833 = Asciz	flatMap;
const #834 = Asciz	(Lscala/collection/TraversableViewLike;Lscala/Function1;Lscala/collection/generic/CanBuildFrom;)Ljava/lang/Object;;
const #835 = NameAndType	#833:#834;//  flatMap:(Lscala/collection/TraversableViewLike;Lscala/Function1;Lscala/collection/generic/CanBuildFrom;)Ljava/lang/Object;
const #836 = Method	#87.#835;	//  scala/collection/TraversableViewLike$class.flatMap:(Lscala/collection/TraversableViewLike;Lscala/Function1;Lscala/collection/generic/CanBuildFrom;)Ljava/lang/Object;
const #837 = Asciz	map;
const #838 = NameAndType	#837:#834;//  map:(Lscala/collection/TraversableViewLike;Lscala/Function1;Lscala/collection/generic/CanBuildFrom;)Ljava/lang/Object;
const #839 = Method	#87.#838;	//  scala/collection/TraversableViewLike$class.map:(Lscala/collection/TraversableViewLike;Lscala/Function1;Lscala/collection/generic/CanBuildFrom;)Ljava/lang/Object;
const #840 = Asciz	$plus$plus;
const #841 = Asciz	(Lscala/collection/Iterator;Lscala/collection/generic/CanBuildFrom;)Ljava/lang/Object;;
const #842 = Asciz	(Lscala/collection/TraversableViewLike;Lscala/collection/Iterator;Lscala/collection/generic/CanBuildFrom;)Ljava/lang/Object;;
const #843 = NameAndType	#840:#842;//  $plus$plus:(Lscala/collection/TraversableViewLike;Lscala/collection/Iterator;Lscala/collection/generic/CanBuildFrom;)Ljava/lang/Object;
const #844 = Method	#87.#843;	//  scala/collection/TraversableViewLike$class.$plus$plus:(Lscala/collection/TraversableViewLike;Lscala/collection/Iterator;Lscala/collection/generic/CanBuildFrom;)Ljava/lang/Object;
const #845 = Asciz	Lscala/collection/Iterator;;
const #846 = Asciz	(Lscala/collection/Traversable;Lscala/collection/generic/CanBuildFrom;)Ljava/lang/Object;;
const #847 = Asciz	(Lscala/collection/TraversableViewLike;Lscala/collection/Traversable;Lscala/collection/generic/CanBuildFrom;)Ljava/lang/Object;;
const #848 = NameAndType	#840:#847;//  $plus$plus:(Lscala/collection/TraversableViewLike;Lscala/collection/Traversable;Lscala/collection/generic/CanBuildFrom;)Ljava/lang/Object;
const #849 = Method	#87.#848;	//  scala/collection/TraversableViewLike$class.$plus$plus:(Lscala/collection/TraversableViewLike;Lscala/collection/Traversable;Lscala/collection/generic/CanBuildFrom;)Ljava/lang/Object;
const #850 = Asciz	force;
const #851 = Asciz	(Lscala/collection/generic/CanBuildFrom;)Ljava/lang/Object;;
const #852 = Asciz	(Lscala/collection/TraversableViewLike;Lscala/collection/generic/CanBuildFrom;)Ljava/lang/Object;;
const #853 = NameAndType	#850:#852;//  force:(Lscala/collection/TraversableViewLike;Lscala/collection/generic/CanBuildFrom;)Ljava/lang/Object;
const #854 = Method	#87.#853;	//  scala/collection/TraversableViewLike$class.force:(Lscala/collection/TraversableViewLike;Lscala/collection/generic/CanBuildFrom;)Ljava/lang/Object;
const #855 = Asciz	newBuilder;
const #856 = Asciz	(Lscala/collection/TraversableViewLike;)Lscala/collection/mutable/Builder;;
const #857 = NameAndType	#855:#856;//  newBuilder:(Lscala/collection/TraversableViewLike;)Lscala/collection/mutable/Builder;
const #858 = Method	#87.#857;	//  scala/collection/TraversableViewLike$class.newBuilder:(Lscala/collection/TraversableViewLike;)Lscala/collection/mutable/Builder;
const #859 = Asciz	zipAll;
const #860 = Asciz	(Lscala/collection/Iterable;Ljava/lang/Object;Ljava/lang/Object;Lscala/collection/generic/CanBuildFrom;)Ljava/lang/Object;;
const #861 = Asciz	(Lscala/collection/IterableViewLike;Lscala/collection/Iterable;Ljava/lang/Object;Ljava/lang/Object;Lscala/collection/generic/CanBuildFrom;)Ljava/lang/Object;;
const #862 = NameAndType	#859:#861;//  zipAll:(Lscala/collection/IterableViewLike;Lscala/collection/Iterable;Ljava/lang/Object;Ljava/lang/Object;Lscala/collection/generic/CanBuildFrom;)Ljava/lang/Object;
const #863 = Method	#92.#862;	//  scala/collection/IterableViewLike$class.zipAll:(Lscala/collection/IterableViewLike;Lscala/collection/Iterable;Ljava/lang/Object;Ljava/lang/Object;Lscala/collection/generic/CanBuildFrom;)Ljava/lang/Object;
const #864 = Asciz	thisElem;
const #865 = Asciz	thatElem;
const #866 = Asciz	zipWithIndex;
const #867 = Asciz	(Lscala/collection/IterableViewLike;Lscala/collection/generic/CanBuildFrom;)Ljava/lang/Object;;
const #868 = NameAndType	#866:#867;//  zipWithIndex:(Lscala/collection/IterableViewLike;Lscala/collection/generic/CanBuildFrom;)Ljava/lang/Object;
const #869 = Method	#92.#868;	//  scala/collection/IterableViewLike$class.zipWithIndex:(Lscala/collection/IterableViewLike;Lscala/collection/generic/CanBuildFrom;)Ljava/lang/Object;
const #870 = Asciz	(Lscala/collection/IterableViewLike;Lscala/collection/Iterable;Lscala/collection/generic/CanBuildFrom;)Ljava/lang/Object;;
const #871 = NameAndType	#816:#870;//  zip:(Lscala/collection/IterableViewLike;Lscala/collection/Iterable;Lscala/collection/generic/CanBuildFrom;)Ljava/lang/Object;
const #872 = Method	#92.#871;	//  scala/collection/IterableViewLike$class.zip:(Lscala/collection/IterableViewLike;Lscala/collection/Iterable;Lscala/collection/generic/CanBuildFrom;)Ljava/lang/Object;
const #873 = Asciz	padTo;
const #874 = Asciz	(Lscala/collection/SeqViewLike;ILjava/lang/Object;Lscala/collection/generic/CanBuildFrom;)Ljava/lang/Object;;
const #875 = NameAndType	#873:#874;//  padTo:(Lscala/collection/SeqViewLike;ILjava/lang/Object;Lscala/collection/generic/CanBuildFrom;)Ljava/lang/Object;
const #876 = Method	#97.#875;	//  scala/collection/SeqViewLike$class.padTo:(Lscala/collection/SeqViewLike;ILjava/lang/Object;Lscala/collection/generic/CanBuildFrom;)Ljava/lang/Object;
const #877 = Asciz	patch;
const #878 = Asciz	(ILscala/collection/Seq;ILscala/collection/generic/CanBuildFrom;)Ljava/lang/Object;;
const #879 = Asciz	(Lscala/collection/SeqViewLike;ILscala/collection/Seq;ILscala/collection/generic/CanBuildFrom;)Ljava/lang/Object;;
const #880 = NameAndType	#877:#879;//  patch:(Lscala/collection/SeqViewLike;ILscala/collection/Seq;ILscala/collection/generic/CanBuildFrom;)Ljava/lang/Object;
const #881 = Method	#97.#880;	//  scala/collection/SeqViewLike$class.patch:(Lscala/collection/SeqViewLike;ILscala/collection/Seq;ILscala/collection/generic/CanBuildFrom;)Ljava/lang/Object;
const #882 = Asciz	replaced;
const #883 = Asciz	(Lscala/collection/IndexedSeqViewLike;ILscala/collection/Seq;I)Lscala/collection/IndexedSeqViewLike$Transformed;;
const #884 = NameAndType	#266:#883;//  newPatched:(Lscala/collection/IndexedSeqViewLike;ILscala/collection/Seq;I)Lscala/collection/IndexedSeqViewLike$Transformed;
const #885 = Method	#102.#884;	//  scala/collection/IndexedSeqViewLike$class.newPatched:(Lscala/collection/IndexedSeqViewLike;ILscala/collection/Seq;I)Lscala/collection/IndexedSeqViewLike$Transformed;
const #886 = Asciz	(Lscala/collection/IndexedSeqViewLike;Lscala/collection/Iterable;Ljava/lang/Object;Ljava/lang/Object;)Lscala/collection/IndexedSeqViewLike$Transformed;;
const #887 = NameAndType	#258:#886;//  newZippedAll:(Lscala/collection/IndexedSeqViewLike;Lscala/collection/Iterable;Ljava/lang/Object;Ljava/lang/Object;)Lscala/collection/IndexedSeqViewLike$Transformed;
const #888 = Method	#102.#887;	//  scala/collection/IndexedSeqViewLike$class.newZippedAll:(Lscala/collection/IndexedSeqViewLike;Lscala/collection/Iterable;Ljava/lang/Object;Ljava/lang/Object;)Lscala/collection/IndexedSeqViewLike$Transformed;
const #889 = Asciz	(Lscala/collection/IndexedSeqViewLike;Lscala/collection/Iterable;)Lscala/collection/IndexedSeqViewLike$Transformed;;
const #890 = NameAndType	#251:#889;//  newZipped:(Lscala/collection/IndexedSeqViewLike;Lscala/collection/Iterable;)Lscala/collection/IndexedSeqViewLike$Transformed;
const #891 = Method	#102.#890;	//  scala/collection/IndexedSeqViewLike$class.newZipped:(Lscala/collection/IndexedSeqViewLike;Lscala/collection/Iterable;)Lscala/collection/IndexedSeqViewLike$Transformed;
const #892 = Asciz	(Lscala/collection/IndexedSeqViewLike;Lscala/Function1;)Lscala/collection/IndexedSeqViewLike$Transformed;;
const #893 = NameAndType	#248:#892;//  newFlatMapped:(Lscala/collection/IndexedSeqViewLike;Lscala/Function1;)Lscala/collection/IndexedSeqViewLike$Transformed;
const #894 = Method	#102.#893;	//  scala/collection/IndexedSeqViewLike$class.newFlatMapped:(Lscala/collection/IndexedSeqViewLike;Lscala/Function1;)Lscala/collection/IndexedSeqViewLike$Transformed;
const #895 = NameAndType	#244:#892;//  newMapped:(Lscala/collection/IndexedSeqViewLike;Lscala/Function1;)Lscala/collection/IndexedSeqViewLike$Transformed;
const #896 = Method	#102.#895;	//  scala/collection/IndexedSeqViewLike$class.newMapped:(Lscala/collection/IndexedSeqViewLike;Lscala/Function1;)Lscala/collection/IndexedSeqViewLike$Transformed;
const #897 = Asciz	(Lscala/collection/IndexedSeqViewLike;Lscala/collection/Traversable;)Lscala/collection/IndexedSeqViewLike$Transformed;;
const #898 = NameAndType	#233:#897;//  newAppended:(Lscala/collection/IndexedSeqViewLike;Lscala/collection/Traversable;)Lscala/collection/IndexedSeqViewLike$Transformed;
const #899 = Method	#102.#898;	//  scala/collection/IndexedSeqViewLike$class.newAppended:(Lscala/collection/IndexedSeqViewLike;Lscala/collection/Traversable;)Lscala/collection/IndexedSeqViewLike$Transformed;
const #900 = Asciz	(Lscala/collection/mutable/IndexedSeqView;)Lscala/collection/mutable/IndexedSeqView;;
const #901 = NameAndType	#229:#900;//  reverse:(Lscala/collection/mutable/IndexedSeqView;)Lscala/collection/mutable/IndexedSeqView;
const #902 = Method	#107.#901;	//  scala/collection/mutable/IndexedSeqView$class.reverse:(Lscala/collection/mutable/IndexedSeqView;)Lscala/collection/mutable/IndexedSeqView;
const #903 = Asciz	splitAt;
const #904 = Asciz	(I)Lscala/Tuple2;;
const #905 = Asciz	(Lscala/collection/mutable/IndexedSeqView;I)Lscala/Tuple2;;
const #906 = NameAndType	#903:#905;//  splitAt:(Lscala/collection/mutable/IndexedSeqView;I)Lscala/Tuple2;
const #907 = Method	#107.#906;	//  scala/collection/mutable/IndexedSeqView$class.splitAt:(Lscala/collection/mutable/IndexedSeqView;I)Lscala/Tuple2;
const #908 = Asciz	span;
const #909 = Asciz	(Lscala/collection/mutable/IndexedSeqView;Lscala/Function1;)Lscala/Tuple2;;
const #910 = NameAndType	#908:#909;//  span:(Lscala/collection/mutable/IndexedSeqView;Lscala/Function1;)Lscala/Tuple2;
const #911 = Method	#107.#910;	//  scala/collection/mutable/IndexedSeqView$class.span:(Lscala/collection/mutable/IndexedSeqView;Lscala/Function1;)Lscala/Tuple2;
const #912 = Asciz	(Lscala/collection/mutable/IndexedSeqView;Lscala/Function1;)Lscala/collection/mutable/IndexedSeqView;;
const #913 = NameAndType	#226:#912;//  takeWhile:(Lscala/collection/mutable/IndexedSeqView;Lscala/Function1;)Lscala/collection/mutable/IndexedSeqView;
const #914 = Method	#107.#913;	//  scala/collection/mutable/IndexedSeqView$class.takeWhile:(Lscala/collection/mutable/IndexedSeqView;Lscala/Function1;)Lscala/collection/mutable/IndexedSeqView;
const #915 = NameAndType	#223:#912;//  dropWhile:(Lscala/collection/mutable/IndexedSeqView;Lscala/Function1;)Lscala/collection/mutable/IndexedSeqView;
const #916 = Method	#107.#915;	//  scala/collection/mutable/IndexedSeqView$class.dropWhile:(Lscala/collection/mutable/IndexedSeqView;Lscala/Function1;)Lscala/collection/mutable/IndexedSeqView;
const #917 = Asciz	(Lscala/collection/mutable/IndexedSeqView;II)Lscala/collection/mutable/IndexedSeqView;;
const #918 = NameAndType	#215:#917;//  slice:(Lscala/collection/mutable/IndexedSeqView;II)Lscala/collection/mutable/IndexedSeqView;
const #919 = Method	#107.#918;	//  scala/collection/mutable/IndexedSeqView$class.slice:(Lscala/collection/mutable/IndexedSeqView;II)Lscala/collection/mutable/IndexedSeqView;
const #920 = Asciz	(Lscala/collection/mutable/IndexedSeqView;I)Lscala/collection/mutable/IndexedSeqView;;
const #921 = NameAndType	#212:#920;//  take:(Lscala/collection/mutable/IndexedSeqView;I)Lscala/collection/mutable/IndexedSeqView;
const #922 = Method	#107.#921;	//  scala/collection/mutable/IndexedSeqView$class.take:(Lscala/collection/mutable/IndexedSeqView;I)Lscala/collection/mutable/IndexedSeqView;
const #923 = NameAndType	#206:#920;//  drop:(Lscala/collection/mutable/IndexedSeqView;I)Lscala/collection/mutable/IndexedSeqView;
const #924 = Method	#107.#923;	//  scala/collection/mutable/IndexedSeqView$class.drop:(Lscala/collection/mutable/IndexedSeqView;I)Lscala/collection/mutable/IndexedSeqView;
const #925 = NameAndType	#200:#900;//  init:(Lscala/collection/mutable/IndexedSeqView;)Lscala/collection/mutable/IndexedSeqView;
const #926 = Method	#107.#925;	//  scala/collection/mutable/IndexedSeqView$class.init:(Lscala/collection/mutable/IndexedSeqView;)Lscala/collection/mutable/IndexedSeqView;
const #927 = NameAndType	#194:#912;//  filter:(Lscala/collection/mutable/IndexedSeqView;Lscala/Function1;)Lscala/collection/mutable/IndexedSeqView;
const #928 = Method	#107.#927;	//  scala/collection/mutable/IndexedSeqView$class.filter:(Lscala/collection/mutable/IndexedSeqView;Lscala/Function1;)Lscala/collection/mutable/IndexedSeqView;
const #929 = Asciz	(Lscala/collection/mutable/IndexedSeqView;)Lscala/collection/mutable/IndexedSeqView$Transformed;;
const #930 = NameAndType	#188:#929;//  newReversed:(Lscala/collection/mutable/IndexedSeqView;)Lscala/collection/mutable/IndexedSeqView$Transformed;
const #931 = Method	#107.#930;	//  scala/collection/mutable/IndexedSeqView$class.newReversed:(Lscala/collection/mutable/IndexedSeqView;)Lscala/collection/mutable/IndexedSeqView$Transformed;
const #932 = Asciz	(Lscala/collection/mutable/IndexedSeqView;Lscala/Function1;)Lscala/collection/mutable/IndexedSeqView$Transformed;;
const #933 = NameAndType	#185:#932;//  newTakenWhile:(Lscala/collection/mutable/IndexedSeqView;Lscala/Function1;)Lscala/collection/mutable/IndexedSeqView$Transformed;
const #934 = Method	#107.#933;	//  scala/collection/mutable/IndexedSeqView$class.newTakenWhile:(Lscala/collection/mutable/IndexedSeqView;Lscala/Function1;)Lscala/collection/mutable/IndexedSeqView$Transformed;
const #935 = NameAndType	#182:#932;//  newDroppedWhile:(Lscala/collection/mutable/IndexedSeqView;Lscala/Function1;)Lscala/collection/mutable/IndexedSeqView$Transformed;
const #936 = Method	#107.#935;	//  scala/collection/mutable/IndexedSeqView$class.newDroppedWhile:(Lscala/collection/mutable/IndexedSeqView;Lscala/Function1;)Lscala/collection/mutable/IndexedSeqView$Transformed;
const #937 = Asciz	(Lscala/collection/mutable/IndexedSeqView;II)Lscala/collection/mutable/IndexedSeqView$Transformed;;
const #938 = NameAndType	#172:#937;//  newSliced:(Lscala/collection/mutable/IndexedSeqView;II)Lscala/collection/mutable/IndexedSeqView$Transformed;
const #939 = Method	#107.#938;	//  scala/collection/mutable/IndexedSeqView$class.newSliced:(Lscala/collection/mutable/IndexedSeqView;II)Lscala/collection/mutable/IndexedSeqView$Transformed;
const #940 = NameAndType	#161:#932;//  newFiltered:(Lscala/collection/mutable/IndexedSeqView;Lscala/Function1;)Lscala/collection/mutable/IndexedSeqView$Transformed;
const #941 = Method	#107.#940;	//  scala/collection/mutable/IndexedSeqView$class.newFiltered:(Lscala/collection/mutable/IndexedSeqView;Lscala/Function1;)Lscala/collection/mutable/IndexedSeqView$Transformed;
const #942 = NameAndType	#3:#4;//  bitmap$0:I
const #943 = Field	#24.#942;	//  scala/collection/mutable/IndexedSeqView$$anon$3.bitmap$0:I
const #944 = Asciz	(Lscala/collection/TraversableViewLike$Transformed;)Ljava/lang/Object;;
const #945 = NameAndType	#5:#944;//  underlying:(Lscala/collection/TraversableViewLike$Transformed;)Ljava/lang/Object;
const #946 = Method	#112.#945;	//  scala/collection/TraversableViewLike$Transformed$class.underlying:(Lscala/collection/TraversableViewLike$Transformed;)Ljava/lang/Object;
const #947 = NameAndType	#5:#6;//  underlying:Ljava/lang/Object;
const #948 = Field	#24.#947;	//  scala/collection/mutable/IndexedSeqView$$anon$3.underlying:Ljava/lang/Object;
const #949 = Asciz	stringPrefix;
const #950 = Asciz	(Lscala/collection/TraversableViewLike$DroppedWhile;)Ljava/lang/String;;
const #951 = NameAndType	#949:#950;//  stringPrefix:(Lscala/collection/TraversableViewLike$DroppedWhile;)Ljava/lang/String;
const #952 = Method	#117.#951;	//  scala/collection/TraversableViewLike$DroppedWhile$class.stringPrefix:(Lscala/collection/TraversableViewLike$DroppedWhile;)Ljava/lang/String;
const #953 = Asciz	iterator;
const #954 = Asciz	(Lscala/collection/IterableViewLike$DroppedWhile;)Lscala/collection/Iterator;;
const #955 = NameAndType	#953:#954;//  iterator:(Lscala/collection/IterableViewLike$DroppedWhile;)Lscala/collection/Iterator;
const #956 = Method	#122.#955;	//  scala/collection/IterableViewLike$DroppedWhile$class.iterator:(Lscala/collection/IterableViewLike$DroppedWhile;)Lscala/collection/Iterator;
const #957 = Asciz	(Lscala/collection/SeqViewLike$DroppedWhile;I)Ljava/lang/Object;;
const #958 = NameAndType	#147:#957;//  apply:(Lscala/collection/SeqViewLike$DroppedWhile;I)Ljava/lang/Object;
const #959 = Method	#127.#958;	//  scala/collection/SeqViewLike$DroppedWhile$class.apply:(Lscala/collection/SeqViewLike$DroppedWhile;I)Ljava/lang/Object;
const #960 = Asciz	length;
const #961 = Asciz	(Lscala/collection/SeqViewLike$DroppedWhile;)I;
const #962 = NameAndType	#960:#961;//  length:(Lscala/collection/SeqViewLike$DroppedWhile;)I
const #963 = Method	#127.#962;	//  scala/collection/SeqViewLike$DroppedWhile$class.length:(Lscala/collection/SeqViewLike$DroppedWhile;)I
const #964 = NameAndType	#7:#961;//  start:(Lscala/collection/SeqViewLike$DroppedWhile;)I
const #965 = Method	#127.#964;	//  scala/collection/SeqViewLike$DroppedWhile$class.start:(Lscala/collection/SeqViewLike$DroppedWhile;)I
const #966 = NameAndType	#7:#4;//  start:I
const #967 = Field	#24.#966;	//  scala/collection/mutable/IndexedSeqView$$anon$3.start:I
const #968 = Asciz	foreach;
const #969 = Asciz	(Lscala/collection/IndexedSeqViewLike$DroppedWhile;Lscala/Function1;)V;
const #970 = NameAndType	#968:#969;//  foreach:(Lscala/collection/IndexedSeqViewLike$DroppedWhile;Lscala/Function1;)V
const #971 = Method	#132.#970;	//  scala/collection/IndexedSeqViewLike$DroppedWhile$class.foreach:(Lscala/collection/IndexedSeqViewLike$DroppedWhile;Lscala/Function1;)V
const #972 = Asciz	update;
const #973 = Asciz	(ILjava/lang/Object;)V;
const #974 = Asciz	(Lscala/collection/mutable/IndexedSeqView$DroppedWhile;ILjava/lang/Object;)V;
const #975 = NameAndType	#972:#974;//  update:(Lscala/collection/mutable/IndexedSeqView$DroppedWhile;ILjava/lang/Object;)V
const #976 = Method	#137.#975;	//  scala/collection/mutable/IndexedSeqView$DroppedWhile$class.update:(Lscala/collection/mutable/IndexedSeqView$DroppedWhile;ILjava/lang/Object;)V
const #977 = Asciz	Ljava/lang/Object;Lscala/collection/mutable/IndexedSeqView<TA;TColl;>.DroppedWhile;;
const #978 = Asciz	Scala;
const #979 = Asciz	InnerClasses;
const #980 = Asciz	$anon$3;
const #981 = Asciz	scala/collection/SeqViewLike$Transformed;
const #982 = class	#981;	//  scala/collection/SeqViewLike$Transformed
const #983 = Asciz	scala/collection/SeqViewLike;
const #984 = class	#983;	//  scala/collection/SeqViewLike
const #985 = Asciz	Transformed;
const #986 = Asciz	DroppedWhile;
const #987 = Asciz	scala/collection/TraversableLike$WithFilter;
const #988 = class	#987;	//  scala/collection/TraversableLike$WithFilter
const #989 = Asciz	scala/collection/TraversableLike;
const #990 = class	#989;	//  scala/collection/TraversableLike
const #991 = Asciz	WithFilter;
const #992 = Asciz	scala/collection/mutable/IndexedSeqView$Transformed;
const #993 = class	#992;	//  scala/collection/mutable/IndexedSeqView$Transformed
const #994 = Asciz	scala/collection/mutable/IndexedSeqView$DroppedWhile;
const #995 = class	#994;	//  scala/collection/mutable/IndexedSeqView$DroppedWhile
const #996 = Asciz	scala/collection/IterableViewLike$Transformed;
const #997 = class	#996;	//  scala/collection/IterableViewLike$Transformed
const #998 = Asciz	scala/collection/IterableViewLike;
const #999 = class	#998;	//  scala/collection/IterableViewLike
const #1000 = Asciz	scala/collection/IterableViewLike$DroppedWhile;
const #1001 = class	#1000;	//  scala/collection/IterableViewLike$DroppedWhile
const #1002 = Asciz	scala/collection/IndexedSeqViewLike$Transformed;
const #1003 = class	#1002;	//  scala/collection/IndexedSeqViewLike$Transformed
const #1004 = Asciz	scala/collection/IndexedSeqViewLike$DroppedWhile;
const #1005 = class	#1004;	//  scala/collection/IndexedSeqViewLike$DroppedWhile
const #1006 = Asciz	scala/collection/TraversableViewLike$Transformed;
const #1007 = class	#1006;	//  scala/collection/TraversableViewLike$Transformed
const #1008 = Asciz	scala/collection/TraversableViewLike;
const #1009 = class	#1008;	//  scala/collection/TraversableViewLike
const #1010 = Asciz	scala/collection/TraversableViewLike$DroppedWhile;
const #1011 = class	#1010;	//  scala/collection/TraversableViewLike$DroppedWhile

{
public volatile int bitmap$0;

public scala.collection.mutable.IndexedSeqView$$anon$3(scala.collection.mutable.IndexedSeqView, scala.Function1);
  Code:
   Stack=2, Locals=3, Args_size=3
   0:	aload_1
   1:	ifnonnull	12
   4:	new	#19; //class java/lang/NullPointerException
   7:	dup
   8:	invokespecial	#22; //Method java/lang/NullPointerException."<init>":()V
   11:	athrow
   12:	aload_0
   13:	aload_1
   14:	putfield	#26; //Field $outer:Lscala/collection/mutable/IndexedSeqView;
   17:	aload_0
   18:	invokespecial	#29; //Method java/lang/Object."<init>":()V
   21:	aload_0
   22:	invokestatic	#35; //Method scala/Function1$class.$init$:(Lscala/Function1;)V
   25:	aload_0
   26:	invokestatic	#40; //Method scala/PartialFunction$class.$init$:(Lscala/PartialFunction;)V
   29:	aload_0
   30:	invokestatic	#45; //Method scala/collection/TraversableLike$class.$init$:(Lscala/collection/TraversableLike;)V
   33:	aload_0
   34:	invokestatic	#50; //Method scala/collection/generic/GenericTraversableTemplate$class.$init$:(Lscala/collection/generic/GenericTraversableTemplate;)V
   37:	aload_0
   38:	invokestatic	#55; //Method scala/collection/Traversable$class.$init$:(Lscala/collection/Traversable;)V
   41:	aload_0
   42:	invokestatic	#60; //Method scala/collection/IterableLike$class.$init$:(Lscala/collection/IterableLike;)V
   45:	aload_0
   46:	invokestatic	#65; //Method scala/collection/Iterable$class.$init$:(Lscala/collection/Iterable;)V
   49:	aload_0
   50:	invokestatic	#70; //Method scala/collection/SeqLike$class.$init$:(Lscala/collection/SeqLike;)V
   53:	aload_0
   54:	invokestatic	#75; //Method scala/collection/Seq$class.$init$:(Lscala/collection/Seq;)V
   57:	aload_0
   58:	invokestatic	#80; //Method scala/collection/IndexedSeqLike$class.$init$:(Lscala/collection/IndexedSeqLike;)V
   61:	aload_0
   62:	invokestatic	#85; //Method scala/collection/IndexedSeq$class.$init$:(Lscala/collection/IndexedSeq;)V
   65:	aload_0
   66:	invokestatic	#90; //Method scala/collection/TraversableViewLike$class.$init$:(Lscala/collection/TraversableViewLike;)V
   69:	aload_0
   70:	invokestatic	#95; //Method scala/collection/IterableViewLike$class.$init$:(Lscala/collection/IterableViewLike;)V
   73:	aload_0
   74:	invokestatic	#100; //Method scala/collection/SeqViewLike$class.$init$:(Lscala/collection/SeqViewLike;)V
   77:	aload_0
   78:	invokestatic	#105; //Method scala/collection/IndexedSeqViewLike$class.$init$:(Lscala/collection/IndexedSeqViewLike;)V
   81:	aload_0
   82:	invokestatic	#110; //Method scala/collection/mutable/IndexedSeqView$class.$init$:(Lscala/collection/mutable/IndexedSeqView;)V
   85:	aload_0
   86:	invokestatic	#115; //Method scala/collection/TraversableViewLike$Transformed$class.$init$:(Lscala/collection/TraversableViewLike$Transformed;)V
   89:	aload_0
   90:	invokestatic	#120; //Method scala/collection/TraversableViewLike$DroppedWhile$class.$init$:(Lscala/collection/TraversableViewLike$DroppedWhile;)V
   93:	aload_0
   94:	invokestatic	#125; //Method scala/collection/IterableViewLike$DroppedWhile$class.$init$:(Lscala/collection/IterableViewLike$DroppedWhile;)V
   97:	aload_0
   98:	invokestatic	#130; //Method scala/collection/SeqViewLike$DroppedWhile$class.$init$:(Lscala/collection/SeqViewLike$DroppedWhile;)V
   101:	aload_0
   102:	invokestatic	#135; //Method scala/collection/IndexedSeqViewLike$DroppedWhile$class.$init$:(Lscala/collection/IndexedSeqViewLike$DroppedWhile;)V
   105:	aload_0
   106:	invokestatic	#140; //Method scala/collection/mutable/IndexedSeqView$DroppedWhile$class.$init$:(Lscala/collection/mutable/IndexedSeqView$DroppedWhile;)V
   109:	aload_0
   110:	aload_2
   111:	putfield	#142; //Field pred:Lscala/Function1;
   114:	return
  LineNumberTable: 
   line 70: 0

  LocalVariableTable: 
   Start  Length  Slot  Name   Signature
   0      115      0    this       Lscala/collection/mutable/IndexedSeqView$$anon$3;
   0      115      1    $outer       Lscala/collection/mutable/IndexedSeqView;

  Signature: length = 0x2
   00 FFFFFF92 

public java.lang.Object apply(java.lang.Object);
  Code:
   Stack=2, Locals=2, Args_size=2
   0:	aload_0
   1:	aload_1
   2:	invokestatic	#154; //Method scala/runtime/BoxesRunTime.unboxToInt:(Ljava/lang/Object;)I
   5:	invokeinterface	#159,  2; //InterfaceMethod scala/collection/SeqViewLike$DroppedWhile.apply:(I)Ljava/lang/Object;
   10:	areturn
  LineNumberTable: 
   line 70: 0

  LocalVariableTable: 
   Start  Length  Slot  Name   Signature
   0      11      0    this       Lscala/collection/mutable/IndexedSeqView$$anon$3;
   0      11      1    v1       Ljava/lang/Object;


public scala.collection.IndexedSeqViewLike$Transformed newFiltered(scala.Function1);
  Code:
   Stack=2, Locals=2, Args_size=2
   0:	aload_0
   1:	aload_1
   2:	invokeinterface	#167,  2; //InterfaceMethod scala/collection/mutable/IndexedSeqView.newFiltered:(Lscala/Function1;)Lscala/collection/mutable/IndexedSeqView$Transformed;
   7:	areturn
  LineNumberTable: 
   line 70: 0

  LocalVariableTable: 
   Start  Length  Slot  Name   Signature
   0      8      0    this       Lscala/collection/mutable/IndexedSeqView$$anon$3;
   0      8      1    p       Lscala/Function1;

  Signature: length = 0x2
   00 FFFFFFA2 

public scala.collection.SeqViewLike$Transformed newFiltered(scala.Function1);
  Code:
   Stack=2, Locals=2, Args_size=2
   0:	aload_0
   1:	aload_1
   2:	invokeinterface	#167,  2; //InterfaceMethod scala/collection/mutable/IndexedSeqView.newFiltered:(Lscala/Function1;)Lscala/collection/mutable/IndexedSeqView$Transformed;
   7:	areturn
  LineNumberTable: 
   line 70: 0

  LocalVariableTable: 
   Start  Length  Slot  Name   Signature
   0      8      0    this       Lscala/collection/mutable/IndexedSeqView$$anon$3;
   0      8      1    p       Lscala/Function1;

  Signature: length = 0x2
   00 FFFFFFA9 

public scala.collection.IterableViewLike$Transformed newFiltered(scala.Function1);
  Code:
   Stack=2, Locals=2, Args_size=2
   0:	aload_0
   1:	aload_1
   2:	invokeinterface	#167,  2; //InterfaceMethod scala/collection/mutable/IndexedSeqView.newFiltered:(Lscala/Function1;)Lscala/collection/mutable/IndexedSeqView$Transformed;
   7:	areturn
  LineNumberTable: 
   line 70: 0

  LocalVariableTable: 
   Start  Length  Slot  Name   Signature
   0      8      0    this       Lscala/collection/mutable/IndexedSeqView$$anon$3;
   0      8      1    p       Lscala/Function1;

  Signature: length = 0x2
   00 FFFFFFAA 

public scala.collection.TraversableViewLike$Transformed newFiltered(scala.Function1);
  Code:
   Stack=2, Locals=2, Args_size=2
   0:	aload_0
   1:	aload_1
   2:	invokeinterface	#167,  2; //InterfaceMethod scala/collection/mutable/IndexedSeqView.newFiltered:(Lscala/Function1;)Lscala/collection/mutable/IndexedSeqView$Transformed;
   7:	areturn
  LineNumberTable: 
   line 70: 0

  LocalVariableTable: 
   Start  Length  Slot  Name   Signature
   0      8      0    this       Lscala/collection/mutable/IndexedSeqView$$anon$3;
   0      8      1    p       Lscala/Function1;

  Signature: length = 0x2
   00 FFFFFFAB 

public scala.collection.IndexedSeqViewLike$Transformed newSliced(int, int);
  Code:
   Stack=3, Locals=3, Args_size=3
   0:	aload_0
   1:	iload_1
   2:	iload_2
   3:	invokeinterface	#176,  3; //InterfaceMethod scala/collection/mutable/IndexedSeqView.newSliced:(II)Lscala/collection/mutable/IndexedSeqView$Transformed;
   8:	areturn
  LineNumberTable: 
   line 70: 0

  LocalVariableTable: 
   Start  Length  Slot  Name   Signature
   0      9      0    this       Lscala/collection/mutable/IndexedSeqView$$anon$3;
   0      9      1    _from       I
   0      9      2    _until       I

  Signature: length = 0x2
   00 FFFFFFAD 

public scala.collection.SeqViewLike$Transformed newSliced(int, int);
  Code:
   Stack=3, Locals=3, Args_size=3
   0:	aload_0
   1:	iload_1
   2:	iload_2
   3:	invokeinterface	#176,  3; //InterfaceMethod scala/collection/mutable/IndexedSeqView.newSliced:(II)Lscala/collection/mutable/IndexedSeqView$Transformed;
   8:	areturn
  LineNumberTable: 
   line 70: 0

  LocalVariableTable: 
   Start  Length  Slot  Name   Signature
   0      9      0    this       Lscala/collection/mutable/IndexedSeqView$$anon$3;
   0      9      1    _from       I
   0      9      2    _until       I

  Signature: length = 0x2
   00 FFFFFFB3 

public scala.collection.IterableViewLike$Transformed newSliced(int, int);
  Code:
   Stack=3, Locals=3, Args_size=3
   0:	aload_0
   1:	iload_1
   2:	iload_2
   3:	invokeinterface	#176,  3; //InterfaceMethod scala/collection/mutable/IndexedSeqView.newSliced:(II)Lscala/collection/mutable/IndexedSeqView$Transformed;
   8:	areturn
  LineNumberTable: 
   line 70: 0

  LocalVariableTable: 
   Start  Length  Slot  Name   Signature
   0      9      0    this       Lscala/collection/mutable/IndexedSeqView$$anon$3;
   0      9      1    _from       I
   0      9      2    _until       I

  Signature: length = 0x2
   00 FFFFFFB4 

public scala.collection.TraversableViewLike$Transformed newSliced(int, int);
  Code:
   Stack=3, Locals=3, Args_size=3
   0:	aload_0
   1:	iload_1
   2:	iload_2
   3:	invokeinterface	#176,  3; //InterfaceMethod scala/collection/mutable/IndexedSeqView.newSliced:(II)Lscala/collection/mutable/IndexedSeqView$Transformed;
   8:	areturn
  LineNumberTable: 
   line 70: 0

  LocalVariableTable: 
   Start  Length  Slot  Name   Signature
   0      9      0    this       Lscala/collection/mutable/IndexedSeqView$$anon$3;
   0      9      1    _from       I
   0      9      2    _until       I

  Signature: length = 0x2
   00 FFFFFFB5 

public scala.collection.IndexedSeqViewLike$Transformed newDroppedWhile(scala.Function1);
  Code:
   Stack=2, Locals=2, Args_size=2
   0:	aload_0
   1:	aload_1
   2:	invokeinterface	#184,  2; //InterfaceMethod scala/collection/mutable/IndexedSeqView.newDroppedWhile:(Lscala/Function1;)Lscala/collection/mutable/IndexedSeqView$Transformed;
   7:	areturn
  LineNumberTable: 
   line 70: 0

  LocalVariableTable: 
   Start  Length  Slot  Name   Signature
   0      8      0    this       Lscala/collection/mutable/IndexedSeqView$$anon$3;
   0      8      1    p       Lscala/Function1;

  Signature: length = 0x2
   00 FFFFFFA2 

public scala.collection.SeqViewLike$Transformed newDroppedWhile(scala.Function1);
  Code:
   Stack=2, Locals=2, Args_size=2
   0:	aload_0
   1:	aload_1
   2:	invokeinterface	#184,  2; //InterfaceMethod scala/collection/mutable/IndexedSeqView.newDroppedWhile:(Lscala/Function1;)Lscala/collection/mutable/IndexedSeqView$Transformed;
   7:	areturn
  LineNumberTable: 
   line 70: 0

  LocalVariableTable: 
   Start  Length  Slot  Name   Signature
   0      8      0    this       Lscala/collection/mutable/IndexedSeqView$$anon$3;
   0      8      1    p       Lscala/Function1;

  Signature: length = 0x2
   00 FFFFFFA9 

public scala.collection.IterableViewLike$Transformed newDroppedWhile(scala.Function1);
  Code:
   Stack=2, Locals=2, Args_size=2
   0:	aload_0
   1:	aload_1
   2:	invokeinterface	#184,  2; //InterfaceMethod scala/collection/mutable/IndexedSeqView.newDroppedWhile:(Lscala/Function1;)Lscala/collection/mutable/IndexedSeqView$Transformed;
   7:	areturn
  LineNumberTable: 
   line 70: 0

  LocalVariableTable: 
   Start  Length  Slot  Name   Signature
   0      8      0    this       Lscala/collection/mutable/IndexedSeqView$$anon$3;
   0      8      1    p       Lscala/Function1;

  Signature: length = 0x2
   00 FFFFFFAA 

public scala.collection.TraversableViewLike$Transformed newDroppedWhile(scala.Function1);
  Code:
   Stack=2, Locals=2, Args_size=2
   0:	aload_0
   1:	aload_1
   2:	invokeinterface	#184,  2; //InterfaceMethod scala/collection/mutable/IndexedSeqView.newDroppedWhile:(Lscala/Function1;)Lscala/collection/mutable/IndexedSeqView$Transformed;
   7:	areturn
  LineNumberTable: 
   line 70: 0

  LocalVariableTable: 
   Start  Length  Slot  Name   Signature
   0      8      0    this       Lscala/collection/mutable/IndexedSeqView$$anon$3;
   0      8      1    p       Lscala/Function1;

  Signature: length = 0x2
   00 FFFFFFAB 

public scala.collection.IndexedSeqViewLike$Transformed newTakenWhile(scala.Function1);
  Code:
   Stack=2, Locals=2, Args_size=2
   0:	aload_0
   1:	aload_1
   2:	invokeinterface	#187,  2; //InterfaceMethod scala/collection/mutable/IndexedSeqView.newTakenWhile:(Lscala/Function1;)Lscala/collection/mutable/IndexedSeqView$Transformed;
   7:	areturn
  LineNumberTable: 
   line 70: 0

  LocalVariableTable: 
   Start  Length  Slot  Name   Signature
   0      8      0    this       Lscala/collection/mutable/IndexedSeqView$$anon$3;
   0      8      1    p       Lscala/Function1;

  Signature: length = 0x2
   00 FFFFFFA2 

public scala.collection.SeqViewLike$Transformed newTakenWhile(scala.Function1);
  Code:
   Stack=2, Locals=2, Args_size=2
   0:	aload_0
   1:	aload_1
   2:	invokeinterface	#187,  2; //InterfaceMethod scala/collection/mutable/IndexedSeqView.newTakenWhile:(Lscala/Function1;)Lscala/collection/mutable/IndexedSeqView$Transformed;
   7:	areturn
  LineNumberTable: 
   line 70: 0

  LocalVariableTable: 
   Start  Length  Slot  Name   Signature
   0      8      0    this       Lscala/collection/mutable/IndexedSeqView$$anon$3;
   0      8      1    p       Lscala/Function1;

  Signature: length = 0x2
   00 FFFFFFA9 

public scala.collection.IterableViewLike$Transformed newTakenWhile(scala.Function1);
  Code:
   Stack=2, Locals=2, Args_size=2
   0:	aload_0
   1:	aload_1
   2:	invokeinterface	#187,  2; //InterfaceMethod scala/collection/mutable/IndexedSeqView.newTakenWhile:(Lscala/Function1;)Lscala/collection/mutable/IndexedSeqView$Transformed;
   7:	areturn
  LineNumberTable: 
   line 70: 0

  LocalVariableTable: 
   Start  Length  Slot  Name   Signature
   0      8      0    this       Lscala/collection/mutable/IndexedSeqView$$anon$3;
   0      8      1    p       Lscala/Function1;

  Signature: length = 0x2
   00 FFFFFFAA 

public scala.collection.TraversableViewLike$Transformed newTakenWhile(scala.Function1);
  Code:
   Stack=2, Locals=2, Args_size=2
   0:	aload_0
   1:	aload_1
   2:	invokeinterface	#187,  2; //InterfaceMethod scala/collection/mutable/IndexedSeqView.newTakenWhile:(Lscala/Function1;)Lscala/collection/mutable/IndexedSeqView$Transformed;
   7:	areturn
  LineNumberTable: 
   line 70: 0

  LocalVariableTable: 
   Start  Length  Slot  Name   Signature
   0      8      0    this       Lscala/collection/mutable/IndexedSeqView$$anon$3;
   0      8      1    p       Lscala/Function1;

  Signature: length = 0x2
   00 FFFFFFAB 

public scala.collection.IndexedSeqViewLike$Transformed newReversed();
  Code:
   Stack=1, Locals=1, Args_size=1
   0:	aload_0
   1:	invokeinterface	#192,  1; //InterfaceMethod scala/collection/mutable/IndexedSeqView.newReversed:()Lscala/collection/mutable/IndexedSeqView$Transformed;
   6:	areturn
  LineNumberTable: 
   line 70: 0

  Signature: length = 0x2
   00 FFFFFFBD 

public scala.collection.SeqViewLike$Transformed newReversed();
  Code:
   Stack=1, Locals=1, Args_size=1
   0:	aload_0
   1:	invokeinterface	#192,  1; //InterfaceMethod scala/collection/mutable/IndexedSeqView.newReversed:()Lscala/collection/mutable/IndexedSeqView$Transformed;
   6:	areturn
  LineNumberTable: 
   line 70: 0

  Signature: length = 0x2
   00 FFFFFFC1 

public scala.collection.TraversableView filter(scala.Function1);
  Code:
   Stack=2, Locals=2, Args_size=2
   0:	aload_0
   1:	aload_1
   2:	invokeinterface	#198,  2; //InterfaceMethod scala/collection/mutable/IndexedSeqView.filter:(Lscala/Function1;)Lscala/collection/mutable/IndexedSeqView;
   7:	areturn
  LineNumberTable: 
   line 70: 0

  LocalVariableTable: 
   Start  Length  Slot  Name   Signature
   0      8      0    this       Lscala/collection/mutable/IndexedSeqView$$anon$3;
   0      8      1    p       Lscala/Function1;


public java.lang.Object filter(scala.Function1);
  Code:
   Stack=2, Locals=2, Args_size=2
   0:	aload_0
   1:	aload_1
   2:	invokeinterface	#198,  2; //InterfaceMethod scala/collection/mutable/IndexedSeqView.filter:(Lscala/Function1;)Lscala/collection/mutable/IndexedSeqView;
   7:	areturn
  LineNumberTable: 
   line 70: 0

  LocalVariableTable: 
   Start  Length  Slot  Name   Signature
   0      8      0    this       Lscala/collection/mutable/IndexedSeqView$$anon$3;
   0      8      1    p       Lscala/Function1;


public scala.collection.TraversableView init();
  Code:
   Stack=1, Locals=1, Args_size=1
   0:	aload_0
   1:	invokeinterface	#204,  1; //InterfaceMethod scala/collection/mutable/IndexedSeqView.init:()Lscala/collection/mutable/IndexedSeqView;
   6:	areturn
  LineNumberTable: 
   line 70: 0


public java.lang.Object init();
  Code:
   Stack=1, Locals=1, Args_size=1
   0:	aload_0
   1:	invokeinterface	#204,  1; //InterfaceMethod scala/collection/mutable/IndexedSeqView.init:()Lscala/collection/mutable/IndexedSeqView;
   6:	areturn
  LineNumberTable: 
   line 70: 0


public scala.collection.TraversableView drop(int);
  Code:
   Stack=2, Locals=2, Args_size=2
   0:	aload_0
   1:	iload_1
   2:	invokeinterface	#210,  2; //InterfaceMethod scala/collection/mutable/IndexedSeqView.drop:(I)Lscala/collection/mutable/IndexedSeqView;
   7:	areturn
  LineNumberTable: 
   line 70: 0

  LocalVariableTable: 
   Start  Length  Slot  Name   Signature
   0      8      0    this       Lscala/collection/mutable/IndexedSeqView$$anon$3;
   0      8      1    n       I


public java.lang.Object drop(int);
  Code:
   Stack=2, Locals=2, Args_size=2
   0:	aload_0
   1:	iload_1
   2:	invokeinterface	#210,  2; //InterfaceMethod scala/collection/mutable/IndexedSeqView.drop:(I)Lscala/collection/mutable/IndexedSeqView;
   7:	areturn
  LineNumberTable: 
   line 70: 0

  LocalVariableTable: 
   Start  Length  Slot  Name   Signature
   0      8      0    this       Lscala/collection/mutable/IndexedSeqView$$anon$3;
   0      8      1    n       I


public scala.collection.TraversableView take(int);
  Code:
   Stack=2, Locals=2, Args_size=2
   0:	aload_0
   1:	iload_1
   2:	invokeinterface	#214,  2; //InterfaceMethod scala/collection/mutable/IndexedSeqView.take:(I)Lscala/collection/mutable/IndexedSeqView;
   7:	areturn
  LineNumberTable: 
   line 70: 0

  LocalVariableTable: 
   Start  Length  Slot  Name   Signature
   0      8      0    this       Lscala/collection/mutable/IndexedSeqView$$anon$3;
   0      8      1    n       I


public java.lang.Object take(int);
  Code:
   Stack=2, Locals=2, Args_size=2
   0:	aload_0
   1:	iload_1
   2:	invokeinterface	#214,  2; //InterfaceMethod scala/collection/mutable/IndexedSeqView.take:(I)Lscala/collection/mutable/IndexedSeqView;
   7:	areturn
  LineNumberTable: 
   line 70: 0

  LocalVariableTable: 
   Start  Length  Slot  Name   Signature
   0      8      0    this       Lscala/collection/mutable/IndexedSeqView$$anon$3;
   0      8      1    n       I


public scala.collection.TraversableView slice(int, int);
  Code:
   Stack=3, Locals=3, Args_size=3
   0:	aload_0
   1:	iload_1
   2:	iload_2
   3:	invokeinterface	#219,  3; //InterfaceMethod scala/collection/mutable/IndexedSeqView.slice:(II)Lscala/collection/mutable/IndexedSeqView;
   8:	areturn
  LineNumberTable: 
   line 70: 0

  LocalVariableTable: 
   Start  Length  Slot  Name   Signature
   0      9      0    this       Lscala/collection/mutable/IndexedSeqView$$anon$3;
   0      9      1    from       I
   0      9      2    until       I


public java.lang.Object slice(int, int);
  Code:
   Stack=3, Locals=3, Args_size=3
   0:	aload_0
   1:	iload_1
   2:	iload_2
   3:	invokeinterface	#219,  3; //InterfaceMethod scala/collection/mutable/IndexedSeqView.slice:(II)Lscala/collection/mutable/IndexedSeqView;
   8:	areturn
  LineNumberTable: 
   line 70: 0

  LocalVariableTable: 
   Start  Length  Slot  Name   Signature
   0      9      0    this       Lscala/collection/mutable/IndexedSeqView$$anon$3;
   0      9      1    from       I
   0      9      2    until       I


public scala.collection.TraversableView dropWhile(scala.Function1);
  Code:
   Stack=2, Locals=2, Args_size=2
   0:	aload_0
   1:	aload_1
   2:	invokeinterface	#225,  2; //InterfaceMethod scala/collection/mutable/IndexedSeqView.dropWhile:(Lscala/Function1;)Lscala/collection/mutable/IndexedSeqView;
   7:	areturn
  LineNumberTable: 
   line 70: 0

  LocalVariableTable: 
   Start  Length  Slot  Name   Signature
   0      8      0    this       Lscala/collection/mutable/IndexedSeqView$$anon$3;
   0      8      1    p       Lscala/Function1;


public java.lang.Object dropWhile(scala.Function1);
  Code:
   Stack=2, Locals=2, Args_size=2
   0:	aload_0
   1:	aload_1
   2:	invokeinterface	#225,  2; //InterfaceMethod scala/collection/mutable/IndexedSeqView.dropWhile:(Lscala/Function1;)Lscala/collection/mutable/IndexedSeqView;
   7:	areturn
  LineNumberTable: 
   line 70: 0

  LocalVariableTable: 
   Start  Length  Slot  Name   Signature
   0      8      0    this       Lscala/collection/mutable/IndexedSeqView$$anon$3;
   0      8      1    p       Lscala/Function1;


public scala.collection.TraversableView takeWhile(scala.Function1);
  Code:
   Stack=2, Locals=2, Args_size=2
   0:	aload_0
   1:	aload_1
   2:	invokeinterface	#228,  2; //InterfaceMethod scala/collection/mutable/IndexedSeqView.takeWhile:(Lscala/Function1;)Lscala/collection/mutable/IndexedSeqView;
   7:	areturn
  LineNumberTable: 
   line 70: 0

  LocalVariableTable: 
   Start  Length  Slot  Name   Signature
   0      8      0    this       Lscala/collection/mutable/IndexedSeqView$$anon$3;
   0      8      1    p       Lscala/Function1;


public java.lang.Object takeWhile(scala.Function1);
  Code:
   Stack=2, Locals=2, Args_size=2
   0:	aload_0
   1:	aload_1
   2:	invokeinterface	#228,  2; //InterfaceMethod scala/collection/mutable/IndexedSeqView.takeWhile:(Lscala/Function1;)Lscala/collection/mutable/IndexedSeqView;
   7:	areturn
  LineNumberTable: 
   line 70: 0

  LocalVariableTable: 
   Start  Length  Slot  Name   Signature
   0      8      0    this       Lscala/collection/mutable/IndexedSeqView$$anon$3;
   0      8      1    p       Lscala/Function1;


public scala.collection.SeqView reverse();
  Code:
   Stack=1, Locals=1, Args_size=1
   0:	aload_0
   1:	invokeinterface	#232,  1; //InterfaceMethod scala/collection/mutable/IndexedSeqView.reverse:()Lscala/collection/mutable/IndexedSeqView;
   6:	areturn
  LineNumberTable: 
   line 70: 0


public java.lang.Object reverse();
  Code:
   Stack=1, Locals=1, Args_size=1
   0:	aload_0
   1:	invokeinterface	#232,  1; //InterfaceMethod scala/collection/mutable/IndexedSeqView.reverse:()Lscala/collection/mutable/IndexedSeqView;
   6:	areturn
  LineNumberTable: 
   line 70: 0


public scala.collection.SeqViewLike$Transformed newAppended(scala.collection.Traversable);
  Code:
   Stack=2, Locals=2, Args_size=2
   0:	aload_0
   1:	aload_1
   2:	invokeinterface	#239,  2; //InterfaceMethod scala/collection/IndexedSeqViewLike.newAppended:(Lscala/collection/Traversable;)Lscala/collection/IndexedSeqViewLike$Transformed;
   7:	areturn
  LineNumberTable: 
   line 70: 0

  LocalVariableTable: 
   Start  Length  Slot  Name   Signature
   0      8      0    this       Lscala/collection/mutable/IndexedSeqView$$anon$3;
   0      8      1    that       Lscala/collection/Traversable;

  Signature: length = 0x2
   00 FFFFFFEA 

public scala.collection.IterableViewLike$Transformed newAppended(scala.collection.Traversable);
  Code:
   Stack=2, Locals=2, Args_size=2
   0:	aload_0
   1:	aload_1
   2:	invokeinterface	#239,  2; //InterfaceMethod scala/collection/IndexedSeqViewLike.newAppended:(Lscala/collection/Traversable;)Lscala/collection/IndexedSeqViewLike$Transformed;
   7:	areturn
  LineNumberTable: 
   line 70: 0

  LocalVariableTable: 
   Start  Length  Slot  Name   Signature
   0      8      0    this       Lscala/collection/mutable/IndexedSeqView$$anon$3;
   0      8      1    that       Lscala/collection/Traversable;

  Signature: length = 0x2
   00 FFFFFFF2 

public scala.collection.TraversableViewLike$Transformed newAppended(scala.collection.Traversable);
  Code:
   Stack=2, Locals=2, Args_size=2
   0:	aload_0
   1:	aload_1
   2:	invokeinterface	#239,  2; //InterfaceMethod scala/collection/IndexedSeqViewLike.newAppended:(Lscala/collection/Traversable;)Lscala/collection/IndexedSeqViewLike$Transformed;
   7:	areturn
  LineNumberTable: 
   line 70: 0

  LocalVariableTable: 
   Start  Length  Slot  Name   Signature
   0      8      0    this       Lscala/collection/mutable/IndexedSeqView$$anon$3;
   0      8      1    that       Lscala/collection/Traversable;

  Signature: length = 0x2
   00 FFFFFFF3 

public scala.collection.SeqViewLike$Transformed newMapped(scala.Function1);
  Code:
   Stack=2, Locals=2, Args_size=2
   0:	aload_0
   1:	aload_1
   2:	invokeinterface	#246,  2; //InterfaceMethod scala/collection/IndexedSeqViewLike.newMapped:(Lscala/Function1;)Lscala/collection/IndexedSeqViewLike$Transformed;
   7:	areturn
  LineNumberTable: 
   line 70: 0

  LocalVariableTable: 
   Start  Length  Slot  Name   Signature
   0      8      0    this       Lscala/collection/mutable/IndexedSeqView$$anon$3;
   0      8      1    f       Lscala/Function1;

  Signature: length = 0x2
   00 FFFFFFA9 

public scala.collection.IterableViewLike$Transformed newMapped(scala.Function1);
  Code:
   Stack=2, Locals=2, Args_size=2
   0:	aload_0
   1:	aload_1
   2:	invokeinterface	#246,  2; //InterfaceMethod scala/collection/IndexedSeqViewLike.newMapped:(Lscala/Function1;)Lscala/collection/IndexedSeqViewLike$Transformed;
   7:	areturn
  LineNumberTable: 
   line 70: 0

  LocalVariableTable: 
   Start  Length  Slot  Name   Signature
   0      8      0    this       Lscala/collection/mutable/IndexedSeqView$$anon$3;
   0      8      1    f       Lscala/Function1;

  Signature: length = 0x2
   00 FFFFFFAA 

public scala.collection.TraversableViewLike$Transformed newMapped(scala.Function1);
  Code:
   Stack=2, Locals=2, Args_size=2
   0:	aload_0
   1:	aload_1
   2:	invokeinterface	#246,  2; //InterfaceMethod scala/collection/IndexedSeqViewLike.newMapped:(Lscala/Function1;)Lscala/collection/IndexedSeqViewLike$Transformed;
   7:	areturn
  LineNumberTable: 
   line 70: 0

  LocalVariableTable: 
   Start  Length  Slot  Name   Signature
   0      8      0    this       Lscala/collection/mutable/IndexedSeqView$$anon$3;
   0      8      1    f       Lscala/Function1;

  Signature: length = 0x2
   00 FFFFFFAB 

public scala.collection.SeqViewLike$Transformed newFlatMapped(scala.Function1);
  Code:
   Stack=2, Locals=2, Args_size=2
   0:	aload_0
   1:	aload_1
   2:	invokeinterface	#250,  2; //InterfaceMethod scala/collection/IndexedSeqViewLike.newFlatMapped:(Lscala/Function1;)Lscala/collection/IndexedSeqViewLike$Transformed;
   7:	areturn
  LineNumberTable: 
   line 70: 0

  LocalVariableTable: 
   Start  Length  Slot  Name   Signature
   0      8      0    this       Lscala/collection/mutable/IndexedSeqView$$anon$3;
   0      8      1    f       Lscala/Function1;

  Signature: length = 0x2
   00 FFFFFFA9 

public scala.collection.IterableViewLike$Transformed newFlatMapped(scala.Function1);
  Code:
   Stack=2, Locals=2, Args_size=2
   0:	aload_0
   1:	aload_1
   2:	invokeinterface	#250,  2; //InterfaceMethod scala/collection/IndexedSeqViewLike.newFlatMapped:(Lscala/Function1;)Lscala/collection/IndexedSeqViewLike$Transformed;
   7:	areturn
  LineNumberTable: 
   line 70: 0

  LocalVariableTable: 
   Start  Length  Slot  Name   Signature
   0      8      0    this       Lscala/collection/mutable/IndexedSeqView$$anon$3;
   0      8      1    f       Lscala/Function1;

  Signature: length = 0x2
   00 FFFFFFAA 

public scala.collection.TraversableViewLike$Transformed newFlatMapped(scala.Function1);
  Code:
   Stack=2, Locals=2, Args_size=2
   0:	aload_0
   1:	aload_1
   2:	invokeinterface	#250,  2; //InterfaceMethod scala/collection/IndexedSeqViewLike.newFlatMapped:(Lscala/Function1;)Lscala/collection/IndexedSeqViewLike$Transformed;
   7:	areturn
  LineNumberTable: 
   line 70: 0

  LocalVariableTable: 
   Start  Length  Slot  Name   Signature
   0      8      0    this       Lscala/collection/mutable/IndexedSeqView$$anon$3;
   0      8      1    f       Lscala/Function1;

  Signature: length = 0x2
   00 FFFFFFAB 

public scala.collection.SeqViewLike$Transformed newZipped(scala.collection.Iterable);
  Code:
   Stack=2, Locals=2, Args_size=2
   0:	aload_0
   1:	aload_1
   2:	invokeinterface	#255,  2; //InterfaceMethod scala/collection/IndexedSeqViewLike.newZipped:(Lscala/collection/Iterable;)Lscala/collection/IndexedSeqViewLike$Transformed;
   7:	areturn
  LineNumberTable: 
   line 70: 0

  LocalVariableTable: 
   Start  Length  Slot  Name   Signature
   0      8      0    this       Lscala/collection/mutable/IndexedSeqView$$anon$3;
   0      8      1    that       Lscala/collection/Iterable;

  Signature: length = 0x2
   00 FFFFFFFC 

public scala.collection.IterableViewLike$Transformed newZipped(scala.collection.Iterable);
  Code:
   Stack=2, Locals=2, Args_size=2
   0:	aload_0
   1:	aload_1
   2:	invokeinterface	#255,  2; //InterfaceMethod scala/collection/IndexedSeqViewLike.newZipped:(Lscala/collection/Iterable;)Lscala/collection/IndexedSeqViewLike$Transformed;
   7:	areturn
  LineNumberTable: 
   line 70: 0

  LocalVariableTable: 
   Start  Length  Slot  Name   Signature
   0      8      0    this       Lscala/collection/mutable/IndexedSeqView$$anon$3;
   0      8      1    that       Lscala/collection/Iterable;

  Signature: length = 0x2
   01 01 

public scala.collection.SeqViewLike$Transformed newZippedAll(scala.collection.Iterable, java.lang.Object, java.lang.Object);
  Code:
   Stack=4, Locals=4, Args_size=4
   0:	aload_0
   1:	aload_1
   2:	aload_2
   3:	aload_3
   4:	invokeinterface	#262,  4; //InterfaceMethod scala/collection/IndexedSeqViewLike.newZippedAll:(Lscala/collection/Iterable;Ljava/lang/Object;Ljava/lang/Object;)Lscala/collection/IndexedSeqViewLike$Transformed;
   9:	areturn
  LineNumberTable: 
   line 70: 0

  LocalVariableTable: 
   Start  Length  Slot  Name   Signature
   0      10      0    this       Lscala/collection/mutable/IndexedSeqView$$anon$3;
   0      10      1    that       Lscala/collection/Iterable;
   0      10      2    _thisElem       Ljava/lang/Object;
   0      10      3    _thatElem       Ljava/lang/Object;

  Signature: length = 0x2
   01 03 

public scala.collection.IterableViewLike$Transformed newZippedAll(scala.collection.Iterable, java.lang.Object, java.lang.Object);
  Code:
   Stack=4, Locals=4, Args_size=4
   0:	aload_0
   1:	aload_1
   2:	aload_2
   3:	aload_3
   4:	invokeinterface	#262,  4; //InterfaceMethod scala/collection/IndexedSeqViewLike.newZippedAll:(Lscala/collection/Iterable;Ljava/lang/Object;Ljava/lang/Object;)Lscala/collection/IndexedSeqViewLike$Transformed;
   9:	areturn
  LineNumberTable: 
   line 70: 0

  LocalVariableTable: 
   Start  Length  Slot  Name   Signature
   0      10      0    this       Lscala/collection/mutable/IndexedSeqView$$anon$3;
   0      10      1    that       Lscala/collection/Iterable;
   0      10      2    _thisElem       Ljava/lang/Object;
   0      10      3    _thatElem       Ljava/lang/Object;

  Signature: length = 0x2
   01 09 

public scala.collection.SeqViewLike$Transformed newPatched(int, scala.collection.Seq, int);
  Code:
   Stack=4, Locals=4, Args_size=4
   0:	aload_0
   1:	iload_1
   2:	aload_2
   3:	iload_3
   4:	invokeinterface	#270,  4; //InterfaceMethod scala/collection/IndexedSeqViewLike.newPatched:(ILscala/collection/Seq;I)Lscala/collection/IndexedSeqViewLike$Transformed;
   9:	areturn
  LineNumberTable: 
   line 70: 0

  LocalVariableTable: 
   Start  Length  Slot  Name   Signature
   0      10      0    this       Lscala/collection/mutable/IndexedSeqView$$anon$3;
   0      10      1    _from       I
   0      10      2    _patch       Lscala/collection/Seq;
   0      10      3    _replaced       I

  Signature: length = 0x2
   01 0B 

public scala.collection.Seq thisCollection();
  Code:
   Stack=1, Locals=1, Args_size=1
   0:	aload_0
   1:	invokeinterface	#280,  1; //InterfaceMethod scala/collection/IndexedSeqLike.thisCollection:()Lscala/collection/IndexedSeq;
   6:	areturn
  LineNumberTable: 
   line 70: 0


public scala.collection.Iterable thisCollection();
  Code:
   Stack=1, Locals=1, Args_size=1
   0:	aload_0
   1:	invokeinterface	#280,  1; //InterfaceMethod scala/collection/IndexedSeqLike.thisCollection:()Lscala/collection/IndexedSeq;
   6:	areturn
  LineNumberTable: 
   line 70: 0


public scala.collection.Traversable thisCollection();
  Code:
   Stack=1, Locals=1, Args_size=1
   0:	aload_0
   1:	invokeinterface	#280,  1; //InterfaceMethod scala/collection/IndexedSeqLike.thisCollection:()Lscala/collection/IndexedSeq;
   6:	areturn
  LineNumberTable: 
   line 70: 0


public scala.collection.Seq toCollection(java.lang.Object);
  Code:
   Stack=2, Locals=2, Args_size=2
   0:	aload_0
   1:	aload_1
   2:	invokeinterface	#287,  2; //InterfaceMethod scala/collection/IndexedSeqLike.toCollection:(Ljava/lang/Object;)Lscala/collection/IndexedSeq;
   7:	areturn
  LineNumberTable: 
   line 70: 0

  LocalVariableTable: 
   Start  Length  Slot  Name   Signature
   0      8      0    this       Lscala/collection/mutable/IndexedSeqView$$anon$3;
   0      8      1    repr       Ljava/lang/Object;


public scala.collection.Iterable toCollection(java.lang.Object);
  Code:
   Stack=2, Locals=2, Args_size=2
   0:	aload_0
   1:	aload_1
   2:	invokeinterface	#287,  2; //InterfaceMethod scala/collection/IndexedSeqLike.toCollection:(Ljava/lang/Object;)Lscala/collection/IndexedSeq;
   7:	areturn
  LineNumberTable: 
   line 70: 0

  LocalVariableTable: 
   Start  Length  Slot  Name   Signature
   0      8      0    this       Lscala/collection/mutable/IndexedSeqView$$anon$3;
   0      8      1    repr       Ljava/lang/Object;


public scala.collection.Traversable toCollection(java.lang.Object);
  Code:
   Stack=2, Locals=2, Args_size=2
   0:	aload_0
   1:	aload_1
   2:	invokeinterface	#287,  2; //InterfaceMethod scala/collection/IndexedSeqLike.toCollection:(Ljava/lang/Object;)Lscala/collection/IndexedSeq;
   7:	areturn
  LineNumberTable: 
   line 70: 0

  LocalVariableTable: 
   Start  Length  Slot  Name   Signature
   0      8      0    this       Lscala/collection/mutable/IndexedSeqView$$anon$3;
   0      8      1    repr       Ljava/lang/Object;


public scala.collection.SeqView view(int, int);
  Code:
   Stack=3, Locals=3, Args_size=3
   0:	aload_0
   1:	iload_1
   2:	iload_2
   3:	invokeinterface	#295,  3; //InterfaceMethod scala/collection/IndexedSeqLike.view:(II)Lscala/collection/IndexedSeqView;
   8:	areturn
  LineNumberTable: 
   line 70: 0

  LocalVariableTable: 
   Start  Length  Slot  Name   Signature
   0      9      0    this       Lscala/collection/mutable/IndexedSeqView$$anon$3;
   0      9      1    from       I
   0      9      2    until       I


public scala.collection.IterableView view(int, int);
  Code:
   Stack=3, Locals=3, Args_size=3
   0:	aload_0
   1:	iload_1
   2:	iload_2
   3:	invokeinterface	#295,  3; //InterfaceMethod scala/collection/IndexedSeqLike.view:(II)Lscala/collection/IndexedSeqView;
   8:	areturn
  LineNumberTable: 
   line 70: 0

  LocalVariableTable: 
   Start  Length  Slot  Name   Signature
   0      9      0    this       Lscala/collection/mutable/IndexedSeqView$$anon$3;
   0      9      1    from       I
   0      9      2    until       I


public scala.collection.TraversableView view(int, int);
  Code:
   Stack=3, Locals=3, Args_size=3
   0:	aload_0
   1:	iload_1
   2:	iload_2
   3:	invokeinterface	#295,  3; //InterfaceMethod scala/collection/IndexedSeqLike.view:(II)Lscala/collection/IndexedSeqView;
   8:	areturn
  LineNumberTable: 
   line 70: 0

  LocalVariableTable: 
   Start  Length  Slot  Name   Signature
   0      9      0    this       Lscala/collection/mutable/IndexedSeqView$$anon$3;
   0      9      1    from       I
   0      9      2    until       I


public boolean isDefinedAt(java.lang.Object);
  Code:
   Stack=2, Locals=2, Args_size=2
   0:	aload_0
   1:	aload_1
   2:	invokestatic	#154; //Method scala/runtime/BoxesRunTime.unboxToInt:(Ljava/lang/Object;)I
   5:	invokeinterface	#303,  2; //InterfaceMethod scala/collection/SeqLike.isDefinedAt:(I)Z
   10:	ireturn
  LineNumberTable: 
   line 70: 0

  LocalVariableTable: 
   Start  Length  Slot  Name   Signature
   0      11      0    this       Lscala/collection/mutable/IndexedSeqView$$anon$3;
   0      11      1    x       Ljava/lang/Object;


public scala.Function1 andThen(scala.Function1);
  Code:
   Stack=2, Locals=2, Args_size=2
   0:	aload_0
   1:	aload_1
   2:	invokeinterface	#311,  2; //InterfaceMethod scala/PartialFunction.andThen:(Lscala/Function1;)Lscala/PartialFunction;
   7:	areturn
  LineNumberTable: 
   line 70: 0

  LocalVariableTable: 
   Start  Length  Slot  Name   Signature
   0      8      0    this       Lscala/collection/mutable/IndexedSeqView$$anon$3;
   0      8      1    g       Lscala/Function1;


public scala.collection.TraversableViewLike scala$collection$TraversableViewLike$Transformed$$$outer();
  Code:
   Stack=1, Locals=1, Args_size=1
   0:	aload_0
   1:	getfield	#26; //Field $outer:Lscala/collection/mutable/IndexedSeqView;
   4:	areturn
  LineNumberTable: 
   line 70: 1


public scala.collection.TraversableViewLike scala$collection$TraversableViewLike$DroppedWhile$$$outer();
  Code:
   Stack=1, Locals=1, Args_size=1
   0:	aload_0
   1:	getfield	#26; //Field $outer:Lscala/collection/mutable/IndexedSeqView;
   4:	areturn
  LineNumberTable: 
   line 70: 1


public scala.collection.IterableViewLike scala$collection$IterableViewLike$DroppedWhile$$$outer();
  Code:
   Stack=1, Locals=1, Args_size=1
   0:	aload_0
   1:	getfield	#26; //Field $outer:Lscala/collection/mutable/IndexedSeqView;
   4:	areturn
  LineNumberTable: 
   line 70: 1


public scala.collection.SeqViewLike scala$collection$SeqViewLike$DroppedWhile$$$outer();
  Code:
   Stack=1, Locals=1, Args_size=1
   0:	aload_0
   1:	getfield	#26; //Field $outer:Lscala/collection/mutable/IndexedSeqView;
   4:	areturn
  LineNumberTable: 
   line 70: 1


public scala.collection.IndexedSeqViewLike scala$collection$IndexedSeqViewLike$DroppedWhile$$$outer();
  Code:
   Stack=1, Locals=1, Args_size=1
   0:	aload_0
   1:	getfield	#26; //Field $outer:Lscala/collection/mutable/IndexedSeqView;
   4:	areturn
  LineNumberTable: 
   line 70: 1


public scala.collection.mutable.IndexedSeqView scala$collection$mutable$IndexedSeqView$DroppedWhile$$$outer();
  Code:
   Stack=1, Locals=1, Args_size=1
   0:	aload_0
   1:	getfield	#26; //Field $outer:Lscala/collection/mutable/IndexedSeqView;
   4:	areturn
  LineNumberTable: 
   line 70: 1


public scala.Function1 pred();
  Code:
   Stack=1, Locals=1, Args_size=1
   0:	aload_0
   1:	getfield	#142; //Field pred:Lscala/Function1;
   4:	areturn
  LineNumberTable: 
   line 70: 0

  Signature: length = 0x2
   01 44 

public scala.Function1 compose(scala.Function1);
  Code:
   Stack=2, Locals=2, Args_size=2
   0:	aload_0
   1:	aload_1
   2:	invokestatic	#328; //Method scala/Function1$class.compose:(Lscala/Function1;Lscala/Function1;)Lscala/Function1;
   5:	areturn
  LineNumberTable: 
   line 70: 0

  LocalVariableTable: 
   Start  Length  Slot  Name   Signature
   0      6      0    this       Lscala/collection/mutable/IndexedSeqView$$anon$3;
   0      6      1    g       Lscala/Function1;


public scala.Function1 lift();
  Code:
   Stack=1, Locals=1, Args_size=1
   0:	aload_0
   1:	invokestatic	#332; //Method scala/PartialFunction$class.lift:(Lscala/PartialFunction;)Lscala/Function1;
   4:	areturn
  LineNumberTable: 
   line 70: 0


public scala.PartialFunction andThen(scala.Function1);
  Code:
   Stack=2, Locals=2, Args_size=2
   0:	aload_0
   1:	aload_1
   2:	invokestatic	#335; //Method scala/PartialFunction$class.andThen:(Lscala/PartialFunction;Lscala/Function1;)Lscala/PartialFunction;
   5:	areturn
  LineNumberTable: 
   line 70: 0

  LocalVariableTable: 
   Start  Length  Slot  Name   Signature
   0      6      0    this       Lscala/collection/mutable/IndexedSeqView$$anon$3;
   0      6      1    k       Lscala/Function1;


public scala.PartialFunction orElse(scala.PartialFunction);
  Code:
   Stack=2, Locals=2, Args_size=2
   0:	aload_0
   1:	aload_1
   2:	invokestatic	#341; //Method scala/PartialFunction$class.orElse:(Lscala/PartialFunction;Lscala/PartialFunction;)Lscala/PartialFunction;
   5:	areturn
  LineNumberTable: 
   line 70: 0

  LocalVariableTable: 
   Start  Length  Slot  Name   Signature
   0      6      0    this       Lscala/collection/mutable/IndexedSeqView$$anon$3;
   0      6      1    that       Lscala/PartialFunction;


public scala.collection.TraversableLike$WithFilter withFilter(scala.Function1);
  Code:
   Stack=2, Locals=2, Args_size=2
   0:	aload_0
   1:	aload_1
   2:	invokestatic	#347; //Method scala/collection/TraversableLike$class.withFilter:(Lscala/collection/TraversableLike;Lscala/Function1;)Lscala/collection/TraversableLike$WithFilter;
   5:	areturn
  LineNumberTable: 
   line 70: 0

  LocalVariableTable: 
   Start  Length  Slot  Name   Signature
   0      6      0    this       Lscala/collection/mutable/IndexedSeqView$$anon$3;
   0      6      1    p       Lscala/Function1;

  Signature: length = 0x2
   01 58 

public scala.collection.mutable.StringBuilder addString(scala.collection.mutable.StringBuilder);
  Code:
   Stack=2, Locals=2, Args_size=2
   0:	aload_0
   1:	aload_1
   2:	invokestatic	#352; //Method scala/collection/TraversableLike$class.addString:(Lscala/collection/TraversableLike;Lscala/collection/mutable/StringBuilder;)Lscala/collection/mutable/StringBuilder;
   5:	areturn
  LineNumberTable: 
   line 70: 0

  LocalVariableTable: 
   Start  Length  Slot  Name   Signature
   0      6      0    this       Lscala/collection/mutable/IndexedSeqView$$anon$3;
   0      6      1    b       Lscala/collection/mutable/StringBuilder;


public scala.collection.mutable.StringBuilder addString(scala.collection.mutable.StringBuilder, java.lang.String);
  Code:
   Stack=3, Locals=3, Args_size=3
   0:	aload_0
   1:	aload_1
   2:	aload_2
   3:	invokestatic	#358; //Method scala/collection/TraversableLike$class.addString:(Lscala/collection/TraversableLike;Lscala/collection/mutable/StringBuilder;Ljava/lang/String;)Lscala/collection/mutable/StringBuilder;
   6:	areturn
  LineNumberTable: 
   line 70: 0

  LocalVariableTable: 
   Start  Length  Slot  Name   Signature
   0      7      0    this       Lscala/collection/mutable/IndexedSeqView$$anon$3;
   0      7      1    b       Lscala/collection/mutable/StringBuilder;
   0      7      2    sep       Ljava/lang/String;


public scala.collection.mutable.StringBuilder addString(scala.collection.mutable.StringBuilder, java.lang.String, java.lang.String, java.lang.String);
  Code:
   Stack=5, Locals=5, Args_size=5
   0:	aload_0
   1:	aload_1
   2:	aload_2
   3:	aload_3
   4:	aload	4
   6:	invokestatic	#364; //Method scala/collection/TraversableLike$class.addString:(Lscala/collection/TraversableLike;Lscala/collection/mutable/StringBuilder;Ljava/lang/String;Ljava/lang/String;Ljava/lang/String;)Lscala/collection/mutable/StringBuilder;
   9:	areturn
  LineNumberTable: 
   line 70: 0

  LocalVariableTable: 
   Start  Length  Slot  Name   Signature
   0      10      0    this       Lscala/collection/mutable/IndexedSeqView$$anon$3;
   0      10      1    b       Lscala/collection/mutable/StringBuilder;
   0      10      2    start       Ljava/lang/String;
   0      10      3    sep       Ljava/lang/String;
   0      10      4    end       Ljava/lang/String;


public java.lang.String mkString();
  Code:
   Stack=1, Locals=1, Args_size=1
   0:	aload_0
   1:	invokestatic	#370; //Method scala/collection/TraversableLike$class.mkString:(Lscala/collection/TraversableLike;)Ljava/lang/String;
   4:	areturn
  LineNumberTable: 
   line 70: 0


public java.lang.String mkString(java.lang.String);
  Code:
   Stack=2, Locals=2, Args_size=2
   0:	aload_0
   1:	aload_1
   2:	invokestatic	#374; //Method scala/collection/TraversableLike$class.mkString:(Lscala/collection/TraversableLike;Ljava/lang/String;)Ljava/lang/String;
   5:	areturn
  LineNumberTable: 
   line 70: 0

  LocalVariableTable: 
   Start  Length  Slot  Name   Signature
   0      6      0    this       Lscala/collection/mutable/IndexedSeqView$$anon$3;
   0      6      1    sep       Ljava/lang/String;


public java.lang.String mkString(java.lang.String, java.lang.String, java.lang.String);
  Code:
   Stack=4, Locals=4, Args_size=4
   0:	aload_0
   1:	aload_1
   2:	aload_2
   3:	aload_3
   4:	invokestatic	#378; //Method scala/collection/TraversableLike$class.mkString:(Lscala/collection/TraversableLike;Ljava/lang/String;Ljava/lang/String;Ljava/lang/String;)Ljava/lang/String;
   7:	areturn
  LineNumberTable: 
   line 70: 0

  LocalVariableTable: 
   Start  Length  Slot  Name   Signature
   0      8      0    this       Lscala/collection/mutable/IndexedSeqView$$anon$3;
   0      8      1    start       Ljava/lang/String;
   0      8      2    sep       Ljava/lang/String;
   0      8      3    end       Ljava/lang/String;


public scala.collection.immutable.Set toSet();
  Code:
   Stack=1, Locals=1, Args_size=1
   0:	aload_0
   1:	invokestatic	#383; //Method scala/collection/TraversableLike$class.toSet:(Lscala/collection/TraversableLike;)Lscala/collection/immutable/Set;
   4:	areturn
  LineNumberTable: 
   line 70: 0


public scala.collection.mutable.IndexedSeq toIndexedSeq();
  Code:
   Stack=1, Locals=1, Args_size=1
   0:	aload_0
   1:	invokestatic	#388; //Method scala/collection/TraversableLike$class.toIndexedSeq:(Lscala/collection/TraversableLike;)Lscala/collection/mutable/IndexedSeq;
   4:	areturn
  LineNumberTable: 
   line 70: 0


public scala.collection.immutable.List toList();
  Code:
   Stack=1, Locals=1, Args_size=1
   0:	aload_0
   1:	invokestatic	#393; //Method scala/collection/TraversableLike$class.toList:(Lscala/collection/TraversableLike;)Lscala/collection/immutable/List;
   4:	areturn
  LineNumberTable: 
   line 70: 0


public java.lang.Object toArray(scala.reflect.ClassManifest);
  Code:
   Stack=2, Locals=2, Args_size=2
   0:	aload_0
   1:	aload_1
   2:	invokestatic	#398; //Method scala/collection/TraversableLike$class.toArray:(Lscala/collection/TraversableLike;Lscala/reflect/ClassManifest;)Ljava/lang/Object;
   5:	areturn
  LineNumberTable: 
   line 70: 0

  LocalVariableTable: 
   Start  Length  Slot  Name   Signature
   0      6      0    this       Lscala/collection/mutable/IndexedSeqView$$anon$3;
   0      6      1    evidence$1       Lscala/reflect/ClassManifest;


public void copyToArray(java.lang.Object);
  Code:
   Stack=2, Locals=2, Args_size=2
   0:	aload_0
   1:	aload_1
   2:	invokestatic	#405; //Method scala/collection/TraversableLike$class.copyToArray:(Lscala/collection/TraversableLike;Ljava/lang/Object;)V
   5:	return
  LineNumberTable: 
   line 70: 0

  LocalVariableTable: 
   Start  Length  Slot  Name   Signature
   0      6      0    this       Lscala/collection/mutable/IndexedSeqView$$anon$3;
   0      6      1    xs       Ljava/lang/Object;


public void copyToArray(java.lang.Object, int);
  Code:
   Stack=3, Locals=3, Args_size=3
   0:	aload_0
   1:	aload_1
   2:	iload_2
   3:	invokestatic	#410; //Method scala/collection/TraversableLike$class.copyToArray:(Lscala/collection/TraversableLike;Ljava/lang/Object;I)V
   6:	return
  LineNumberTable: 
   line 70: 0

  LocalVariableTable: 
   Start  Length  Slot  Name   Signature
   0      7      0    this       Lscala/collection/mutable/IndexedSeqView$$anon$3;
   0      7      1    xs       Ljava/lang/Object;
   0      7      2    start       I


public void copyToBuffer(scala.collection.mutable.Buffer);
  Code:
   Stack=2, Locals=2, Args_size=2
   0:	aload_0
   1:	aload_1
   2:	invokestatic	#415; //Method scala/collection/TraversableLike$class.copyToBuffer:(Lscala/collection/TraversableLike;Lscala/collection/mutable/Buffer;)V
   5:	return
  LineNumberTable: 
   line 70: 0

  LocalVariableTable: 
   Start  Length  Slot  Name   Signature
   0      6      0    this       Lscala/collection/mutable/IndexedSeqView$$anon$3;
   0      6      1    dest       Lscala/collection/mutable/Buffer;


public scala.Option lastOption();
  Code:
   Stack=1, Locals=1, Args_size=1
   0:	aload_0
   1:	invokestatic	#422; //Method scala/collection/TraversableLike$class.lastOption:(Lscala/collection/TraversableLike;)Lscala/Option;
   4:	areturn
  LineNumberTable: 
   line 70: 0


public scala.Option headOption();
  Code:
   Stack=1, Locals=1, Args_size=1
   0:	aload_0
   1:	invokestatic	#425; //Method scala/collection/TraversableLike$class.headOption:(Lscala/collection/TraversableLike;)Lscala/Option;
   4:	areturn
  LineNumberTable: 
   line 70: 0


public java.lang.Object max(scala.math.Ordering);
  Code:
   Stack=2, Locals=2, Args_size=2
   0:	aload_0
   1:	aload_1
   2:	invokestatic	#430; //Method scala/collection/TraversableLike$class.max:(Lscala/collection/TraversableLike;Lscala/math/Ordering;)Ljava/lang/Object;
   5:	areturn
  LineNumberTable: 
   line 70: 0

  LocalVariableTable: 
   Start  Length  Slot  Name   Signature
   0      6      0    this       Lscala/collection/mutable/IndexedSeqView$$anon$3;
   0      6      1    cmp       Lscala/math/Ordering;


public java.lang.Object min(scala.math.Ordering);
  Code:
   Stack=2, Locals=2, Args_size=2
   0:	aload_0
   1:	aload_1
   2:	invokestatic	#435; //Method scala/collection/TraversableLike$class.min:(Lscala/collection/TraversableLike;Lscala/math/Ordering;)Ljava/lang/Object;
   5:	areturn
  LineNumberTable: 
   line 70: 0

  LocalVariableTable: 
   Start  Length  Slot  Name   Signature
   0      6      0    this       Lscala/collection/mutable/IndexedSeqView$$anon$3;
   0      6      1    cmp       Lscala/math/Ordering;


public java.lang.Object product(scala.math.Numeric);
  Code:
   Stack=2, Locals=2, Args_size=2
   0:	aload_0
   1:	aload_1
   2:	invokestatic	#440; //Method scala/collection/TraversableLike$class.product:(Lscala/collection/TraversableLike;Lscala/math/Numeric;)Ljava/lang/Object;
   5:	areturn
  LineNumberTable: 
   line 70: 0

  LocalVariableTable: 
   Start  Length  Slot  Name   Signature
   0      6      0    this       Lscala/collection/mutable/IndexedSeqView$$anon$3;
   0      6      1    num       Lscala/math/Numeric;


public java.lang.Object sum(scala.math.Numeric);
  Code:
   Stack=2, Locals=2, Args_size=2
   0:	aload_0
   1:	aload_1
   2:	invokestatic	#445; //Method scala/collection/TraversableLike$class.sum:(Lscala/collection/TraversableLike;Lscala/math/Numeric;)Ljava/lang/Object;
   5:	areturn
  LineNumberTable: 
   line 70: 0

  LocalVariableTable: 
   Start  Length  Slot  Name   Signature
   0      6      0    this       Lscala/collection/mutable/IndexedSeqView$$anon$3;
   0      6      1    num       Lscala/math/Numeric;


public scala.Option reduceRightOption(scala.Function2);
  Code:
   Stack=2, Locals=2, Args_size=2
   0:	aload_0
   1:	aload_1
   2:	invokestatic	#450; //Method scala/collection/TraversableLike$class.reduceRightOption:(Lscala/collection/TraversableLike;Lscala/Function2;)Lscala/Option;
   5:	areturn
  LineNumberTable: 
   line 70: 0

  LocalVariableTable: 
   Start  Length  Slot  Name   Signature
   0      6      0    this       Lscala/collection/mutable/IndexedSeqView$$anon$3;
   0      6      1    op       Lscala/Function2;


public scala.Option reduceLeftOption(scala.Function2);
  Code:
   Stack=2, Locals=2, Args_size=2
   0:	aload_0
   1:	aload_1
   2:	invokestatic	#455; //Method scala/collection/TraversableLike$class.reduceLeftOption:(Lscala/collection/TraversableLike;Lscala/Function2;)Lscala/Option;
   5:	areturn
  LineNumberTable: 
   line 70: 0

  LocalVariableTable: 
   Start  Length  Slot  Name   Signature
   0      6      0    this       Lscala/collection/mutable/IndexedSeqView$$anon$3;
   0      6      1    op       Lscala/Function2;


public java.lang.Object $colon$bslash(java.lang.Object, scala.Function2);
  Code:
   Stack=3, Locals=3, Args_size=3
   0:	aload_0
   1:	aload_1
   2:	aload_2
   3:	invokestatic	#460; //Method scala/collection/TraversableLike$class.$colon$bslash:(Lscala/collection/TraversableLike;Ljava/lang/Object;Lscala/Function2;)Ljava/lang/Object;
   6:	areturn
  LineNumberTable: 
   line 70: 0

  LocalVariableTable: 
   Start  Length  Slot  Name   Signature
   0      7      0    this       Lscala/collection/mutable/IndexedSeqView$$anon$3;
   0      7      1    z       Ljava/lang/Object;
   0      7      2    op       Lscala/Function2;


public java.lang.Object $div$colon(java.lang.Object, scala.Function2);
  Code:
   Stack=3, Locals=3, Args_size=3
   0:	aload_0
   1:	aload_1
   2:	aload_2
   3:	invokestatic	#464; //Method scala/collection/TraversableLike$class.$div$colon:(Lscala/collection/TraversableLike;Ljava/lang/Object;Lscala/Function2;)Ljava/lang/Object;
   6:	areturn
  LineNumberTable: 
   line 70: 0

  LocalVariableTable: 
   Start  Length  Slot  Name   Signature
   0      7      0    this       Lscala/collection/mutable/IndexedSeqView$$anon$3;
   0      7      1    z       Ljava/lang/Object;
   0      7      2    op       Lscala/Function2;


public int count(scala.Function1);
  Code:
   Stack=2, Locals=2, Args_size=2
   0:	aload_0
   1:	aload_1
   2:	invokestatic	#469; //Method scala/collection/TraversableLike$class.count:(Lscala/collection/TraversableLike;Lscala/Function1;)I
   5:	ireturn
  LineNumberTable: 
   line 70: 0

  LocalVariableTable: 
   Start  Length  Slot  Name   Signature
   0      6      0    this       Lscala/collection/mutable/IndexedSeqView$$anon$3;
   0      6      1    p       Lscala/Function1;


public scala.collection.Map groupBy(scala.Function1);
  Code:
   Stack=2, Locals=2, Args_size=2
   0:	aload_0
   1:	aload_1
   2:	invokestatic	#474; //Method scala/collection/TraversableLike$class.groupBy:(Lscala/collection/TraversableLike;Lscala/Function1;)Lscala/collection/Map;
   5:	areturn
  LineNumberTable: 
   line 70: 0

  LocalVariableTable: 
   Start  Length  Slot  Name   Signature
   0      6      0    this       Lscala/collection/mutable/IndexedSeqView$$anon$3;
   0      6      1    f       Lscala/Function1;


public scala.Tuple2 partition(scala.Function1);
  Code:
   Stack=2, Locals=2, Args_size=2
   0:	aload_0
   1:	aload_1
   2:	invokestatic	#479; //Method scala/collection/TraversableLike$class.partition:(Lscala/collection/TraversableLike;Lscala/Function1;)Lscala/Tuple2;
   5:	areturn
  LineNumberTable: 
   line 70: 0

  LocalVariableTable: 
   Start  Length  Slot  Name   Signature
   0      6      0    this       Lscala/collection/mutable/IndexedSeqView$$anon$3;
   0      6      1    p       Lscala/Function1;


public java.lang.Object partialMap(scala.PartialFunction, scala.collection.generic.CanBuildFrom);
  Code:
   Stack=3, Locals=3, Args_size=3
   0:	aload_0
   1:	aload_1
   2:	aload_2
   3:	invokestatic	#484; //Method scala/collection/TraversableLike$class.partialMap:(Lscala/collection/TraversableLike;Lscala/PartialFunction;Lscala/collection/generic/CanBuildFrom;)Ljava/lang/Object;
   6:	areturn
  LineNumberTable: 
   line 70: 0

  LocalVariableTable: 
   Start  Length  Slot  Name   Signature
   0      7      0    this       Lscala/collection/mutable/IndexedSeqView$$anon$3;
   0      7      1    pf       Lscala/PartialFunction;
   0      7      2    bf       Lscala/collection/generic/CanBuildFrom;


public java.lang.Object filterNot(scala.Function1);
  Code:
   Stack=2, Locals=2, Args_size=2
   0:	aload_0
   1:	aload_1
   2:	invokestatic	#491; //Method scala/collection/TraversableLike$class.filterNot:(Lscala/collection/TraversableLike;Lscala/Function1;)Ljava/lang/Object;
   5:	areturn
  LineNumberTable: 
   line 70: 0

  LocalVariableTable: 
   Start  Length  Slot  Name   Signature
   0      6      0    this       Lscala/collection/mutable/IndexedSeqView$$anon$3;
   0      6      1    p       Lscala/Function1;


public boolean hasDefiniteSize();
  Code:
   Stack=1, Locals=1, Args_size=1
   0:	aload_0
   1:	invokestatic	#496; //Method scala/collection/TraversableLike$class.hasDefiniteSize:(Lscala/collection/TraversableLike;)Z
   4:	ireturn
  LineNumberTable: 
   line 70: 0


public boolean nonEmpty();
  Code:
   Stack=1, Locals=1, Args_size=1
   0:	aload_0
   1:	invokestatic	#499; //Method scala/collection/TraversableLike$class.nonEmpty:(Lscala/collection/TraversableLike;)Z
   4:	ireturn
  LineNumberTable: 
   line 70: 0


public java.lang.Object repr();
  Code:
   Stack=1, Locals=1, Args_size=1
   0:	aload_0
   1:	invokestatic	#502; //Method scala/collection/TraversableLike$class.repr:(Lscala/collection/TraversableLike;)Ljava/lang/Object;
   4:	areturn
  LineNumberTable: 
   line 70: 0


public scala.collection.Traversable transpose(scala.Function1);
  Code:
   Stack=2, Locals=2, Args_size=2
   0:	aload_0
   1:	aload_1
   2:	invokestatic	#507; //Method scala/collection/generic/GenericTraversableTemplate$class.transpose:(Lscala/collection/generic/GenericTraversableTemplate;Lscala/Function1;)Lscala/collection/Traversable;
   5:	areturn
  LineNumberTable: 
   line 70: 0

  LocalVariableTable: 
   Start  Length  Slot  Name   Signature
   0      6      0    this       Lscala/collection/mutable/IndexedSeqView$$anon$3;
   0      6      1    asTraversable       Lscala/Function1;


public scala.collection.Traversable flatten(scala.Function1);
  Code:
   Stack=2, Locals=2, Args_size=2
   0:	aload_0
   1:	aload_1
   2:	invokestatic	#511; //Method scala/collection/generic/GenericTraversableTemplate$class.flatten:(Lscala/collection/generic/GenericTraversableTemplate;Lscala/Function1;)Lscala/collection/Traversable;
   5:	areturn
  LineNumberTable: 
   line 70: 0

  LocalVariableTable: 
   Start  Length  Slot  Name   Signature
   0      6      0    this       Lscala/collection/mutable/IndexedSeqView$$anon$3;
   0      6      1    asTraversable       Lscala/Function1;


public scala.Tuple2 unzip(scala.Function1);
  Code:
   Stack=2, Locals=2, Args_size=2
   0:	aload_0
   1:	aload_1
   2:	invokestatic	#515; //Method scala/collection/generic/GenericTraversableTemplate$class.unzip:(Lscala/collection/generic/GenericTraversableTemplate;Lscala/Function1;)Lscala/Tuple2;
   5:	areturn
  LineNumberTable: 
   line 70: 0

  LocalVariableTable: 
   Start  Length  Slot  Name   Signature
   0      6      0    this       Lscala/collection/mutable/IndexedSeqView$$anon$3;
   0      6      1    asPair       Lscala/Function1;


public scala.collection.mutable.Builder genericBuilder();
  Code:
   Stack=1, Locals=1, Args_size=1
   0:	aload_0
   1:	invokestatic	#521; //Method scala/collection/generic/GenericTraversableTemplate$class.genericBuilder:(Lscala/collection/generic/GenericTraversableTemplate;)Lscala/collection/mutable/Builder;
   4:	areturn
  LineNumberTable: 
   line 70: 0


public scala.Option firstOption();
  Code:
   Stack=1, Locals=1, Args_size=1
   0:	aload_0
   1:	invokestatic	#525; //Method scala/collection/IterableLike$class.firstOption:(Lscala/collection/IterableLike;)Lscala/Option;
   4:	areturn
  LineNumberTable: 
   line 70: 0

  Deprecated: true

public java.lang.Object first();
  Code:
   Stack=1, Locals=1, Args_size=1
   0:	aload_0
   1:	invokestatic	#530; //Method scala/collection/IterableLike$class.first:(Lscala/collection/IterableLike;)Ljava/lang/Object;
   4:	areturn
  LineNumberTable: 
   line 70: 0

  Deprecated: true

public boolean canEqual(java.lang.Object);
  Code:
   Stack=2, Locals=2, Args_size=2
   0:	aload_0
   1:	aload_1
   2:	invokestatic	#534; //Method scala/collection/IterableLike$class.canEqual:(Lscala/collection/IterableLike;Ljava/lang/Object;)Z
   5:	ireturn
  LineNumberTable: 
   line 70: 0

  LocalVariableTable: 
   Start  Length  Slot  Name   Signature
   0      6      0    this       Lscala/collection/mutable/IndexedSeqView$$anon$3;
   0      6      1    that       Ljava/lang/Object;


public scala.collection.immutable.Stream toStream();
  Code:
   Stack=1, Locals=1, Args_size=1
   0:	aload_0
   1:	invokestatic	#539; //Method scala/collection/IterableLike$class.toStream:(Lscala/collection/IterableLike;)Lscala/collection/immutable/Stream;
   4:	areturn
  LineNumberTable: 
   line 70: 0


public scala.collection.Iterable toIterable();
  Code:
   Stack=1, Locals=1, Args_size=1
   0:	aload_0
   1:	invokestatic	#543; //Method scala/collection/IterableLike$class.toIterable:(Lscala/collection/IterableLike;)Lscala/collection/Iterable;
   4:	areturn
  LineNumberTable: 
   line 70: 0


public scala.collection.Iterator elements();
  Code:
   Stack=1, Locals=1, Args_size=1
   0:	aload_0
   1:	invokestatic	#548; //Method scala/collection/IterableLike$class.elements:(Lscala/collection/IterableLike;)Lscala/collection/Iterator;
   4:	areturn
  LineNumberTable: 
   line 70: 0

  Deprecated: true

public java.lang.Object projection();
  Code:
   Stack=1, Locals=1, Args_size=1
   0:	aload_0
   1:	invokestatic	#552; //Method scala/collection/SeqLike$class.projection:(Lscala/collection/SeqLike;)Ljava/lang/Object;
   4:	areturn
  LineNumberTable: 
   line 70: 0

  Deprecated: true

public boolean equalsWith(scala.collection.Seq, scala.Function2);
  Code:
   Stack=3, Locals=3, Args_size=3
   0:	aload_0
   1:	aload_1
   2:	aload_2
   3:	invokestatic	#557; //Method scala/collection/SeqLike$class.equalsWith:(Lscala/collection/SeqLike;Lscala/collection/Seq;Lscala/Function2;)Z
   6:	ireturn
  LineNumberTable: 
   line 70: 0

  LocalVariableTable: 
   Start  Length  Slot  Name   Signature
   0      7      0    this       Lscala/collection/mutable/IndexedSeqView$$anon$3;
   0      7      1    that       Lscala/collection/Seq;
   0      7      2    f       Lscala/Function2;

  Deprecated: true

public int findLastIndexOf(scala.Function1);
  Code:
   Stack=2, Locals=2, Args_size=2
   0:	aload_0
   1:	aload_1
   2:	invokestatic	#561; //Method scala/collection/SeqLike$class.findLastIndexOf:(Lscala/collection/SeqLike;Lscala/Function1;)I
   5:	ireturn
  LineNumberTable: 
   line 70: 0

  LocalVariableTable: 
   Start  Length  Slot  Name   Signature
   0      6      0    this       Lscala/collection/mutable/IndexedSeqView$$anon$3;
   0      6      1    p       Lscala/Function1;


public java.lang.String toString();
  Code:
   Stack=1, Locals=1, Args_size=1
   0:	aload_0
   1:	invokestatic	#565; //Method scala/collection/SeqLike$class.toString:(Lscala/collection/SeqLike;)Ljava/lang/String;
   4:	areturn
  LineNumberTable: 
   line 70: 0


public boolean equals(java.lang.Object);
  Code:
   Stack=2, Locals=2, Args_size=2
   0:	aload_0
   1:	aload_1
   2:	invokestatic	#569; //Method scala/collection/SeqLike$class.equals:(Lscala/collection/SeqLike;Ljava/lang/Object;)Z
   5:	ireturn
  LineNumberTable: 
   line 70: 0

  LocalVariableTable: 
   Start  Length  Slot  Name   Signature
   0      6      0    this       Lscala/collection/mutable/IndexedSeqView$$anon$3;
   0      6      1    that       Ljava/lang/Object;


public int hashCode();
  Code:
   Stack=1, Locals=1, Args_size=1
   0:	aload_0
   1:	invokestatic	#574; //Method scala/collection/SeqLike$class.hashCode:(Lscala/collection/SeqLike;)I
   4:	ireturn
  LineNumberTable: 
   line 70: 0


public scala.collection.immutable.Range indices();
  Code:
   Stack=1, Locals=1, Args_size=1
   0:	aload_0
   1:	invokestatic	#579; //Method scala/collection/SeqLike$class.indices:(Lscala/collection/SeqLike;)Lscala/collection/immutable/Range;
   4:	areturn
  LineNumberTable: 
   line 70: 0


public scala.collection.Seq toSeq();
  Code:
   Stack=1, Locals=1, Args_size=1
   0:	aload_0
   1:	invokestatic	#583; //Method scala/collection/SeqLike$class.toSeq:(Lscala/collection/SeqLike;)Lscala/collection/Seq;
   4:	areturn
  LineNumberTable: 
   line 70: 0


public java.lang.Object sortBy(scala.Function1, scala.math.Ordering);
  Code:
   Stack=3, Locals=3, Args_size=3
   0:	aload_0
   1:	aload_1
   2:	aload_2
   3:	invokestatic	#588; //Method scala/collection/SeqLike$class.sortBy:(Lscala/collection/SeqLike;Lscala/Function1;Lscala/math/Ordering;)Ljava/lang/Object;
   6:	areturn
  LineNumberTable: 
   line 70: 0

  LocalVariableTable: 
   Start  Length  Slot  Name   Signature
   0      7      0    this       Lscala/collection/mutable/IndexedSeqView$$anon$3;
   0      7      1    f       Lscala/Function1;
   0      7      2    ord       Lscala/math/Ordering;


public java.lang.Object sortWith(scala.math.Ordering);
  Code:
   Stack=2, Locals=2, Args_size=2
   0:	aload_0
   1:	aload_1
   2:	invokestatic	#593; //Method scala/collection/SeqLike$class.sortWith:(Lscala/collection/SeqLike;Lscala/math/Ordering;)Ljava/lang/Object;
   5:	areturn
  LineNumberTable: 
   line 70: 0

  LocalVariableTable: 
   Start  Length  Slot  Name   Signature
   0      6      0    this       Lscala/collection/mutable/IndexedSeqView$$anon$3;
   0      6      1    ord       Lscala/math/Ordering;


public java.lang.Object sortWith(scala.Function2);
  Code:
   Stack=2, Locals=2, Args_size=2
   0:	aload_0
   1:	aload_1
   2:	invokestatic	#597; //Method scala/collection/SeqLike$class.sortWith:(Lscala/collection/SeqLike;Lscala/Function2;)Ljava/lang/Object;
   5:	areturn
  LineNumberTable: 
   line 70: 0

  LocalVariableTable: 
   Start  Length  Slot  Name   Signature
   0      6      0    this       Lscala/collection/mutable/IndexedSeqView$$anon$3;
   0      6      1    lt       Lscala/Function2;


public boolean corresponds(scala.collection.Seq, scala.Function2);
  Code:
   Stack=3, Locals=3, Args_size=3
   0:	aload_0
   1:	aload_1
   2:	aload_2
   3:	invokestatic	#601; //Method scala/collection/SeqLike$class.corresponds:(Lscala/collection/SeqLike;Lscala/collection/Seq;Lscala/Function2;)Z
   6:	ireturn
  LineNumberTable: 
   line 70: 0

  LocalVariableTable: 
   Start  Length  Slot  Name   Signature
   0      7      0    this       Lscala/collection/mutable/IndexedSeqView$$anon$3;
   0      7      1    that       Lscala/collection/Seq;
   0      7      2    p       Lscala/Function2;


public java.lang.Object $colon$plus(java.lang.Object, scala.collection.generic.CanBuildFrom);
  Code:
   Stack=3, Locals=3, Args_size=3
   0:	aload_0
   1:	aload_1
   2:	aload_2
   3:	invokestatic	#606; //Method scala/collection/SeqLike$class.$colon$plus:(Lscala/collection/SeqLike;Ljava/lang/Object;Lscala/collection/generic/CanBuildFrom;)Ljava/lang/Object;
   6:	areturn
  LineNumberTable: 
   line 70: 0

  LocalVariableTable: 
   Start  Length  Slot  Name   Signature
   0      7      0    this       Lscala/collection/mutable/IndexedSeqView$$anon$3;
   0      7      1    elem       Ljava/lang/Object;
   0      7      2    bf       Lscala/collection/generic/CanBuildFrom;


public java.lang.Object $plus$colon(java.lang.Object, scala.collection.generic.CanBuildFrom);
  Code:
   Stack=3, Locals=3, Args_size=3
   0:	aload_0
   1:	aload_1
   2:	aload_2
   3:	invokestatic	#610; //Method scala/collection/SeqLike$class.$plus$colon:(Lscala/collection/SeqLike;Ljava/lang/Object;Lscala/collection/generic/CanBuildFrom;)Ljava/lang/Object;
   6:	areturn
  LineNumberTable: 
   line 70: 0

  LocalVariableTable: 
   Start  Length  Slot  Name   Signature
   0      7      0    this       Lscala/collection/mutable/IndexedSeqView$$anon$3;
   0      7      1    elem       Ljava/lang/Object;
   0      7      2    bf       Lscala/collection/generic/CanBuildFrom;


public java.lang.Object updated(int, java.lang.Object, scala.collection.generic.CanBuildFrom);
  Code:
   Stack=4, Locals=4, Args_size=4
   0:	aload_0
   1:	iload_1
   2:	aload_2
   3:	aload_3
   4:	invokestatic	#615; //Method scala/collection/SeqLike$class.updated:(Lscala/collection/SeqLike;ILjava/lang/Object;Lscala/collection/generic/CanBuildFrom;)Ljava/lang/Object;
   7:	areturn
  LineNumberTable: 
   line 70: 0

  LocalVariableTable: 
   Start  Length  Slot  Name   Signature
   0      8      0    this       Lscala/collection/mutable/IndexedSeqView$$anon$3;
   0      8      1    index       I
   0      8      2    elem       Ljava/lang/Object;
   0      8      3    bf       Lscala/collection/generic/CanBuildFrom;


public java.lang.Object removeDuplicates();
  Code:
   Stack=1, Locals=1, Args_size=1
   0:	aload_0
   1:	invokestatic	#619; //Method scala/collection/SeqLike$class.removeDuplicates:(Lscala/collection/SeqLike;)Ljava/lang/Object;
   4:	areturn
  LineNumberTable: 
   line 70: 0


public java.lang.Object intersect(scala.collection.Seq);
  Code:
   Stack=2, Locals=2, Args_size=2
   0:	aload_0
   1:	aload_1
   2:	invokestatic	#624; //Method scala/collection/SeqLike$class.intersect:(Lscala/collection/SeqLike;Lscala/collection/Seq;)Ljava/lang/Object;
   5:	areturn
  LineNumberTable: 
   line 70: 0

  LocalVariableTable: 
   Start  Length  Slot  Name   Signature
   0      6      0    this       Lscala/collection/mutable/IndexedSeqView$$anon$3;
   0      6      1    that       Lscala/collection/Seq;


public java.lang.Object diff(scala.collection.Seq);
  Code:
   Stack=2, Locals=2, Args_size=2
   0:	aload_0
   1:	aload_1
   2:	invokestatic	#627; //Method scala/collection/SeqLike$class.diff:(Lscala/collection/SeqLike;Lscala/collection/Seq;)Ljava/lang/Object;
   5:	areturn
  LineNumberTable: 
   line 70: 0

  LocalVariableTable: 
   Start  Length  Slot  Name   Signature
   0      6      0    this       Lscala/collection/mutable/IndexedSeqView$$anon$3;
   0      6      1    that       Lscala/collection/Seq;


public java.lang.Object union(scala.collection.Seq, scala.collection.generic.CanBuildFrom);
  Code:
   Stack=3, Locals=3, Args_size=3
   0:	aload_0
   1:	aload_1
   2:	aload_2
   3:	invokestatic	#632; //Method scala/collection/SeqLike$class.union:(Lscala/collection/SeqLike;Lscala/collection/Seq;Lscala/collection/generic/CanBuildFrom;)Ljava/lang/Object;
   6:	areturn
  LineNumberTable: 
   line 70: 0

  LocalVariableTable: 
   Start  Length  Slot  Name   Signature
   0      7      0    this       Lscala/collection/mutable/IndexedSeqView$$anon$3;
   0      7      1    that       Lscala/collection/Seq;
   0      7      2    bf       Lscala/collection/generic/CanBuildFrom;


public boolean contains(java.lang.Object);
  Code:
   Stack=2, Locals=2, Args_size=2
   0:	aload_0
   1:	aload_1
   2:	invokestatic	#635; //Method scala/collection/SeqLike$class.contains:(Lscala/collection/SeqLike;Ljava/lang/Object;)Z
   5:	ireturn
  LineNumberTable: 
   line 70: 0

  LocalVariableTable: 
   Start  Length  Slot  Name   Signature
   0      6      0    this       Lscala/collection/mutable/IndexedSeqView$$anon$3;
   0      6      1    elem       Ljava/lang/Object;


public boolean containsSlice(scala.collection.Seq);
  Code:
   Stack=2, Locals=2, Args_size=2
   0:	aload_0
   1:	aload_1
   2:	invokestatic	#640; //Method scala/collection/SeqLike$class.containsSlice:(Lscala/collection/SeqLike;Lscala/collection/Seq;)Z
   5:	ireturn
  LineNumberTable: 
   line 70: 0

  LocalVariableTable: 
   Start  Length  Slot  Name   Signature
   0      6      0    this       Lscala/collection/mutable/IndexedSeqView$$anon$3;
   0      6      1    that       Lscala/collection/Seq;


public int lastIndexOfSlice(scala.collection.Seq, int);
  Code:
   Stack=3, Locals=3, Args_size=3
   0:	aload_0
   1:	aload_1
   2:	iload_2
   3:	invokestatic	#645; //Method scala/collection/SeqLike$class.lastIndexOfSlice:(Lscala/collection/SeqLike;Lscala/collection/Seq;I)I
   6:	ireturn
  LineNumberTable: 
   line 70: 0

  LocalVariableTable: 
   Start  Length  Slot  Name   Signature
   0      7      0    this       Lscala/collection/mutable/IndexedSeqView$$anon$3;
   0      7      1    that       Lscala/collection/Seq;
   0      7      2    end       I


public int lastIndexOfSlice(scala.collection.Seq);
  Code:
   Stack=2, Locals=2, Args_size=2
   0:	aload_0
   1:	aload_1
   2:	invokestatic	#649; //Method scala/collection/SeqLike$class.lastIndexOfSlice:(Lscala/collection/SeqLike;Lscala/collection/Seq;)I
   5:	ireturn
  LineNumberTable: 
   line 70: 0

  LocalVariableTable: 
   Start  Length  Slot  Name   Signature
   0      6      0    this       Lscala/collection/mutable/IndexedSeqView$$anon$3;
   0      6      1    that       Lscala/collection/Seq;


public int indexOfSlice(scala.collection.Seq, int);
  Code:
   Stack=3, Locals=3, Args_size=3
   0:	aload_0
   1:	aload_1
   2:	iload_2
   3:	invokestatic	#652; //Method scala/collection/SeqLike$class.indexOfSlice:(Lscala/collection/SeqLike;Lscala/collection/Seq;I)I
   6:	ireturn
  LineNumberTable: 
   line 70: 0

  LocalVariableTable: 
   Start  Length  Slot  Name   Signature
   0      7      0    this       Lscala/collection/mutable/IndexedSeqView$$anon$3;
   0      7      1    that       Lscala/collection/Seq;
   0      7      2    from       I


public int indexOfSlice(scala.collection.Seq);
  Code:
   Stack=2, Locals=2, Args_size=2
   0:	aload_0
   1:	aload_1
   2:	invokestatic	#654; //Method scala/collection/SeqLike$class.indexOfSlice:(Lscala/collection/SeqLike;Lscala/collection/Seq;)I
   5:	ireturn
  LineNumberTable: 
   line 70: 0

  LocalVariableTable: 
   Start  Length  Slot  Name   Signature
   0      6      0    this       Lscala/collection/mutable/IndexedSeqView$$anon$3;
   0      6      1    that       Lscala/collection/Seq;


public boolean startsWith(scala.collection.Seq);
  Code:
   Stack=2, Locals=2, Args_size=2
   0:	aload_0
   1:	aload_1
   2:	invokestatic	#657; //Method scala/collection/SeqLike$class.startsWith:(Lscala/collection/SeqLike;Lscala/collection/Seq;)Z
   5:	ireturn
  LineNumberTable: 
   line 70: 0

  LocalVariableTable: 
   Start  Length  Slot  Name   Signature
   0      6      0    this       Lscala/collection/mutable/IndexedSeqView$$anon$3;
   0      6      1    that       Lscala/collection/Seq;


public scala.collection.Iterator reversedElements();
  Code:
   Stack=1, Locals=1, Args_size=1
   0:	aload_0
   1:	invokestatic	#661; //Method scala/collection/SeqLike$class.reversedElements:(Lscala/collection/SeqLike;)Lscala/collection/Iterator;
   4:	areturn
  LineNumberTable: 
   line 70: 0

  Deprecated: true

public java.lang.Object reverseMap(scala.Function1, scala.collection.generic.CanBuildFrom);
  Code:
   Stack=3, Locals=3, Args_size=3
   0:	aload_0
   1:	aload_1
   2:	aload_2
   3:	invokestatic	#666; //Method scala/collection/SeqLike$class.reverseMap:(Lscala/collection/SeqLike;Lscala/Function1;Lscala/collection/generic/CanBuildFrom;)Ljava/lang/Object;
   6:	areturn
  LineNumberTable: 
   line 70: 0

  LocalVariableTable: 
   Start  Length  Slot  Name   Signature
   0      7      0    this       Lscala/collection/mutable/IndexedSeqView$$anon$3;
   0      7      1    f       Lscala/Function1;
   0      7      2    bf       Lscala/collection/generic/CanBuildFrom;


public int lastIndexWhere(scala.Function1);
  Code:
   Stack=2, Locals=2, Args_size=2
   0:	aload_0
   1:	aload_1
   2:	invokestatic	#669; //Method scala/collection/SeqLike$class.lastIndexWhere:(Lscala/collection/SeqLike;Lscala/Function1;)I
   5:	ireturn
  LineNumberTable: 
   line 70: 0

  LocalVariableTable: 
   Start  Length  Slot  Name   Signature
   0      6      0    this       Lscala/collection/mutable/IndexedSeqView$$anon$3;
   0      6      1    p       Lscala/Function1;


public int lastIndexOf(java.lang.Object, int);
  Code:
   Stack=3, Locals=3, Args_size=3
   0:	aload_0
   1:	aload_1
   2:	iload_2
   3:	invokestatic	#674; //Method scala/collection/SeqLike$class.lastIndexOf:(Lscala/collection/SeqLike;Ljava/lang/Object;I)I
   6:	ireturn
  LineNumberTable: 
   line 70: 0

  LocalVariableTable: 
   Start  Length  Slot  Name   Signature
   0      7      0    this       Lscala/collection/mutable/IndexedSeqView$$anon$3;
   0      7      1    elem       Ljava/lang/Object;
   0      7      2    end       I


public int lastIndexOf(java.lang.Object);
  Code:
   Stack=2, Locals=2, Args_size=2
   0:	aload_0
   1:	aload_1
   2:	invokestatic	#677; //Method scala/collection/SeqLike$class.lastIndexOf:(Lscala/collection/SeqLike;Ljava/lang/Object;)I
   5:	ireturn
  LineNumberTable: 
   line 70: 0

  LocalVariableTable: 
   Start  Length  Slot  Name   Signature
   0      6      0    this       Lscala/collection/mutable/IndexedSeqView$$anon$3;
   0      6      1    elem       Ljava/lang/Object;


public int indexOf(java.lang.Object, int);
  Code:
   Stack=3, Locals=3, Args_size=3
   0:	aload_0
   1:	aload_1
   2:	iload_2
   3:	invokestatic	#680; //Method scala/collection/SeqLike$class.indexOf:(Lscala/collection/SeqLike;Ljava/lang/Object;I)I
   6:	ireturn
  LineNumberTable: 
   line 70: 0

  LocalVariableTable: 
   Start  Length  Slot  Name   Signature
   0      7      0    this       Lscala/collection/mutable/IndexedSeqView$$anon$3;
   0      7      1    elem       Ljava/lang/Object;
   0      7      2    from       I


public int indexOf(java.lang.Object);
  Code:
   Stack=2, Locals=2, Args_size=2
   0:	aload_0
   1:	aload_1
   2:	invokestatic	#682; //Method scala/collection/SeqLike$class.indexOf:(Lscala/collection/SeqLike;Ljava/lang/Object;)I
   5:	ireturn
  LineNumberTable: 
   line 70: 0

  LocalVariableTable: 
   Start  Length  Slot  Name   Signature
   0      6      0    this       Lscala/collection/mutable/IndexedSeqView$$anon$3;
   0      6      1    elem       Ljava/lang/Object;


public int findIndexOf(scala.Function1);
  Code:
   Stack=2, Locals=2, Args_size=2
   0:	aload_0
   1:	aload_1
   2:	invokestatic	#685; //Method scala/collection/SeqLike$class.findIndexOf:(Lscala/collection/SeqLike;Lscala/Function1;)I
   5:	ireturn
  LineNumberTable: 
   line 70: 0

  LocalVariableTable: 
   Start  Length  Slot  Name   Signature
   0      6      0    this       Lscala/collection/mutable/IndexedSeqView$$anon$3;
   0      6      1    p       Lscala/Function1;


public int indexWhere(scala.Function1);
  Code:
   Stack=2, Locals=2, Args_size=2
   0:	aload_0
   1:	aload_1
   2:	invokestatic	#688; //Method scala/collection/SeqLike$class.indexWhere:(Lscala/collection/SeqLike;Lscala/Function1;)I
   5:	ireturn
  LineNumberTable: 
   line 70: 0

  LocalVariableTable: 
   Start  Length  Slot  Name   Signature
   0      6      0    this       Lscala/collection/mutable/IndexedSeqView$$anon$3;
   0      6      1    p       Lscala/Function1;


public int prefixLength(scala.Function1);
  Code:
   Stack=2, Locals=2, Args_size=2
   0:	aload_0
   1:	aload_1
   2:	invokestatic	#691; //Method scala/collection/SeqLike$class.prefixLength:(Lscala/collection/SeqLike;Lscala/Function1;)I
   5:	ireturn
  LineNumberTable: 
   line 70: 0

  LocalVariableTable: 
   Start  Length  Slot  Name   Signature
   0      6      0    this       Lscala/collection/mutable/IndexedSeqView$$anon$3;
   0      6      1    p       Lscala/Function1;


public boolean isDefinedAt(int);
  Code:
   Stack=2, Locals=2, Args_size=2
   0:	aload_0
   1:	iload_1
   2:	invokestatic	#694; //Method scala/collection/SeqLike$class.isDefinedAt:(Lscala/collection/SeqLike;I)Z
   5:	ireturn
  LineNumberTable: 
   line 70: 0

  LocalVariableTable: 
   Start  Length  Slot  Name   Signature
   0      6      0    this       Lscala/collection/mutable/IndexedSeqView$$anon$3;
   0      6      1    idx       I


public int size();
  Code:
   Stack=1, Locals=1, Args_size=1
   0:	aload_0
   1:	invokestatic	#698; //Method scala/collection/SeqLike$class.size:(Lscala/collection/SeqLike;)I
   4:	ireturn
  LineNumberTable: 
   line 70: 0


public scala.collection.IndexedSeqView view(int, int);
  Code:
   Stack=3, Locals=3, Args_size=3
   0:	aload_0
   1:	iload_1
   2:	iload_2
   3:	invokestatic	#701; //Method scala/collection/IndexedSeqLike$class.view:(Lscala/collection/IndexedSeqLike;II)Lscala/collection/IndexedSeqView;
   6:	areturn
  LineNumberTable: 
   line 70: 0

  LocalVariableTable: 
   Start  Length  Slot  Name   Signature
   0      7      0    this       Lscala/collection/mutable/IndexedSeqView$$anon$3;
   0      7      1    from       I
   0      7      2    until       I


public java.lang.Object view();
  Code:
   Stack=1, Locals=1, Args_size=1
   0:	aload_0
   1:	invokestatic	#704; //Method scala/collection/IndexedSeqLike$class.view:(Lscala/collection/IndexedSeqLike;)Ljava/lang/Object;
   4:	areturn
  LineNumberTable: 
   line 70: 0


public boolean endsWith(scala.collection.Seq);
  Code:
   Stack=2, Locals=2, Args_size=2
   0:	aload_0
   1:	aload_1
   2:	invokestatic	#708; //Method scala/collection/IndexedSeqLike$class.endsWith:(Lscala/collection/IndexedSeqLike;Lscala/collection/Seq;)Z
   5:	ireturn
  LineNumberTable: 
   line 70: 0

  LocalVariableTable: 
   Start  Length  Slot  Name   Signature
   0      6      0    this       Lscala/collection/mutable/IndexedSeqView$$anon$3;
   0      6      1    that       Lscala/collection/Seq;


public boolean startsWith(scala.collection.Seq, int);
  Code:
   Stack=3, Locals=3, Args_size=3
   0:	aload_0
   1:	aload_1
   2:	iload_2
   3:	invokestatic	#712; //Method scala/collection/IndexedSeqLike$class.startsWith:(Lscala/collection/IndexedSeqLike;Lscala/collection/Seq;I)Z
   6:	ireturn
  LineNumberTable: 
   line 70: 0

  LocalVariableTable: 
   Start  Length  Slot  Name   Signature
   0      7      0    this       Lscala/collection/mutable/IndexedSeqView$$anon$3;
   0      7      1    that       Lscala/collection/Seq;
   0      7      2    offset       I


public scala.collection.Iterator reverseIterator();
  Code:
   Stack=1, Locals=1, Args_size=1
   0:	aload_0
   1:	invokestatic	#717; //Method scala/collection/IndexedSeqLike$class.reverseIterator:(Lscala/collection/IndexedSeqLike;)Lscala/collection/Iterator;
   4:	areturn
  LineNumberTable: 
   line 70: 0


public int lastIndexWhere(scala.Function1, int);
  Code:
   Stack=3, Locals=3, Args_size=3
   0:	aload_0
   1:	aload_1
   2:	iload_2
   3:	invokestatic	#721; //Method scala/collection/IndexedSeqLike$class.lastIndexWhere:(Lscala/collection/IndexedSeqLike;Lscala/Function1;I)I
   6:	ireturn
  LineNumberTable: 
   line 70: 0

  LocalVariableTable: 
   Start  Length  Slot  Name   Signature
   0      7      0    this       Lscala/collection/mutable/IndexedSeqView$$anon$3;
   0      7      1    p       Lscala/Function1;
   0      7      2    end       I


public int indexWhere(scala.Function1, int);
  Code:
   Stack=3, Locals=3, Args_size=3
   0:	aload_0
   1:	aload_1
   2:	iload_2
   3:	invokestatic	#723; //Method scala/collection/IndexedSeqLike$class.indexWhere:(Lscala/collection/IndexedSeqLike;Lscala/Function1;I)I
   6:	ireturn
  LineNumberTable: 
   line 70: 0

  LocalVariableTable: 
   Start  Length  Slot  Name   Signature
   0      7      0    this       Lscala/collection/mutable/IndexedSeqView$$anon$3;
   0      7      1    p       Lscala/Function1;
   0      7      2    from       I


public int segmentLength(scala.Function1, int);
  Code:
   Stack=3, Locals=3, Args_size=3
   0:	aload_0
   1:	aload_1
   2:	iload_2
   3:	invokestatic	#726; //Method scala/collection/IndexedSeqLike$class.segmentLength:(Lscala/collection/IndexedSeqLike;Lscala/Function1;I)I
   6:	ireturn
  LineNumberTable: 
   line 70: 0

  LocalVariableTable: 
   Start  Length  Slot  Name   Signature
   0      7      0    this       Lscala/collection/mutable/IndexedSeqView$$anon$3;
   0      7      1    p       Lscala/Function1;
   0      7      2    from       I


public int lengthCompare(int);
  Code:
   Stack=2, Locals=2, Args_size=2
   0:	aload_0
   1:	iload_1
   2:	invokestatic	#731; //Method scala/collection/IndexedSeqLike$class.lengthCompare:(Lscala/collection/IndexedSeqLike;I)I
   5:	ireturn
  LineNumberTable: 
   line 70: 0

  LocalVariableTable: 
   Start  Length  Slot  Name   Signature
   0      6      0    this       Lscala/collection/mutable/IndexedSeqView$$anon$3;
   0      6      1    len       I


public void copyToArray(java.lang.Object, int, int);
  Code:
   Stack=4, Locals=4, Args_size=4
   0:	aload_0
   1:	aload_1
   2:	iload_2
   3:	iload_3
   4:	invokestatic	#736; //Method scala/collection/IndexedSeqLike$class.copyToArray:(Lscala/collection/IndexedSeqLike;Ljava/lang/Object;II)V
   7:	return
  LineNumberTable: 
   line 70: 0

  LocalVariableTable: 
   Start  Length  Slot  Name   Signature
   0      8      0    this       Lscala/collection/mutable/IndexedSeqView$$anon$3;
   0      8      1    xs       Ljava/lang/Object;
   0      8      2    start       I
   0      8      3    len       I


public boolean sameElements(scala.collection.Iterable);
  Code:
   Stack=2, Locals=2, Args_size=2
   0:	aload_0
   1:	aload_1
   2:	invokestatic	#741; //Method scala/collection/IndexedSeqLike$class.sameElements:(Lscala/collection/IndexedSeqLike;Lscala/collection/Iterable;)Z
   5:	ireturn
  LineNumberTable: 
   line 70: 0

  LocalVariableTable: 
   Start  Length  Slot  Name   Signature
   0      6      0    this       Lscala/collection/mutable/IndexedSeqView$$anon$3;
   0      6      1    that       Lscala/collection/Iterable;


public java.lang.Object dropRight(int);
  Code:
   Stack=2, Locals=2, Args_size=2
   0:	aload_0
   1:	iload_1
   2:	invokestatic	#745; //Method scala/collection/IndexedSeqLike$class.dropRight:(Lscala/collection/IndexedSeqLike;I)Ljava/lang/Object;
   5:	areturn
  LineNumberTable: 
   line 70: 0

  LocalVariableTable: 
   Start  Length  Slot  Name   Signature
   0      6      0    this       Lscala/collection/mutable/IndexedSeqView$$anon$3;
   0      6      1    n       I


public java.lang.Object takeRight(int);
  Code:
   Stack=2, Locals=2, Args_size=2
   0:	aload_0
   1:	iload_1
   2:	invokestatic	#748; //Method scala/collection/IndexedSeqLike$class.takeRight:(Lscala/collection/IndexedSeqLike;I)Ljava/lang/Object;
   5:	areturn
  LineNumberTable: 
   line 70: 0

  LocalVariableTable: 
   Start  Length  Slot  Name   Signature
   0      6      0    this       Lscala/collection/mutable/IndexedSeqView$$anon$3;
   0      6      1    n       I


public java.lang.Object last();
  Code:
   Stack=1, Locals=1, Args_size=1
   0:	aload_0
   1:	invokestatic	#751; //Method scala/collection/IndexedSeqLike$class.last:(Lscala/collection/IndexedSeqLike;)Ljava/lang/Object;
   4:	areturn
  LineNumberTable: 
   line 70: 0


public java.lang.Object tail();
  Code:
   Stack=1, Locals=1, Args_size=1
   0:	aload_0
   1:	invokestatic	#754; //Method scala/collection/IndexedSeqLike$class.tail:(Lscala/collection/IndexedSeqLike;)Ljava/lang/Object;
   4:	areturn
  LineNumberTable: 
   line 70: 0


public java.lang.Object head();
  Code:
   Stack=1, Locals=1, Args_size=1
   0:	aload_0
   1:	invokestatic	#757; //Method scala/collection/IndexedSeqLike$class.head:(Lscala/collection/IndexedSeqLike;)Ljava/lang/Object;
   4:	areturn
  LineNumberTable: 
   line 70: 0


public java.lang.Object reduceRight(scala.Function2);
  Code:
   Stack=2, Locals=2, Args_size=2
   0:	aload_0
   1:	aload_1
   2:	invokestatic	#761; //Method scala/collection/IndexedSeqLike$class.reduceRight:(Lscala/collection/IndexedSeqLike;Lscala/Function2;)Ljava/lang/Object;
   5:	areturn
  LineNumberTable: 
   line 70: 0

  LocalVariableTable: 
   Start  Length  Slot  Name   Signature
   0      6      0    this       Lscala/collection/mutable/IndexedSeqView$$anon$3;
   0      6      1    op       Lscala/Function2;


public java.lang.Object reduceLeft(scala.Function2);
  Code:
   Stack=2, Locals=2, Args_size=2
   0:	aload_0
   1:	aload_1
   2:	invokestatic	#764; //Method scala/collection/IndexedSeqLike$class.reduceLeft:(Lscala/collection/IndexedSeqLike;Lscala/Function2;)Ljava/lang/Object;
   5:	areturn
  LineNumberTable: 
   line 70: 0

  LocalVariableTable: 
   Start  Length  Slot  Name   Signature
   0      6      0    this       Lscala/collection/mutable/IndexedSeqView$$anon$3;
   0      6      1    op       Lscala/Function2;


public java.lang.Object foldRight(java.lang.Object, scala.Function2);
  Code:
   Stack=3, Locals=3, Args_size=3
   0:	aload_0
   1:	aload_1
   2:	aload_2
   3:	invokestatic	#768; //Method scala/collection/IndexedSeqLike$class.foldRight:(Lscala/collection/IndexedSeqLike;Ljava/lang/Object;Lscala/Function2;)Ljava/lang/Object;
   6:	areturn
  LineNumberTable: 
   line 70: 0

  LocalVariableTable: 
   Start  Length  Slot  Name   Signature
   0      7      0    this       Lscala/collection/mutable/IndexedSeqView$$anon$3;
   0      7      1    z       Ljava/lang/Object;
   0      7      2    op       Lscala/Function2;


public java.lang.Object foldLeft(java.lang.Object, scala.Function2);
  Code:
   Stack=3, Locals=3, Args_size=3
   0:	aload_0
   1:	aload_1
   2:	aload_2
   3:	invokestatic	#771; //Method scala/collection/IndexedSeqLike$class.foldLeft:(Lscala/collection/IndexedSeqLike;Ljava/lang/Object;Lscala/Function2;)Ljava/lang/Object;
   6:	areturn
  LineNumberTable: 
   line 70: 0

  LocalVariableTable: 
   Start  Length  Slot  Name   Signature
   0      7      0    this       Lscala/collection/mutable/IndexedSeqView$$anon$3;
   0      7      1    z       Ljava/lang/Object;
   0      7      2    op       Lscala/Function2;


public scala.Option find(scala.Function1);
  Code:
   Stack=2, Locals=2, Args_size=2
   0:	aload_0
   1:	aload_1
   2:	invokestatic	#776; //Method scala/collection/IndexedSeqLike$class.find:(Lscala/collection/IndexedSeqLike;Lscala/Function1;)Lscala/Option;
   5:	areturn
  LineNumberTable: 
   line 70: 0

  LocalVariableTable: 
   Start  Length  Slot  Name   Signature
   0      6      0    this       Lscala/collection/mutable/IndexedSeqView$$anon$3;
   0      6      1    p       Lscala/Function1;


public boolean exists(scala.Function1);
  Code:
   Stack=2, Locals=2, Args_size=2
   0:	aload_0
   1:	aload_1
   2:	invokestatic	#781; //Method scala/collection/IndexedSeqLike$class.exists:(Lscala/collection/IndexedSeqLike;Lscala/Function1;)Z
   5:	ireturn
  LineNumberTable: 
   line 70: 0

  LocalVariableTable: 
   Start  Length  Slot  Name   Signature
   0      6      0    this       Lscala/collection/mutable/IndexedSeqView$$anon$3;
   0      6      1    p       Lscala/Function1;


public boolean forall(scala.Function1);
  Code:
   Stack=2, Locals=2, Args_size=2
   0:	aload_0
   1:	aload_1
   2:	invokestatic	#784; //Method scala/collection/IndexedSeqLike$class.forall:(Lscala/collection/IndexedSeqLike;Lscala/Function1;)Z
   5:	ireturn
  LineNumberTable: 
   line 70: 0

  LocalVariableTable: 
   Start  Length  Slot  Name   Signature
   0      6      0    this       Lscala/collection/mutable/IndexedSeqView$$anon$3;
   0      6      1    p       Lscala/Function1;


public boolean isEmpty();
  Code:
   Stack=1, Locals=1, Args_size=1
   0:	aload_0
   1:	invokestatic	#788; //Method scala/collection/IndexedSeqLike$class.isEmpty:(Lscala/collection/IndexedSeqLike;)Z
   4:	ireturn
  LineNumberTable: 
   line 70: 0


public scala.collection.IndexedSeq toCollection(java.lang.Object);
  Code:
   Stack=2, Locals=2, Args_size=2
   0:	aload_0
   1:	aload_1
   2:	invokestatic	#791; //Method scala/collection/IndexedSeqLike$class.toCollection:(Lscala/collection/IndexedSeqLike;Ljava/lang/Object;)Lscala/collection/IndexedSeq;
   5:	areturn
  LineNumberTable: 
   line 70: 0

  LocalVariableTable: 
   Start  Length  Slot  Name   Signature
   0      6      0    this       Lscala/collection/mutable/IndexedSeqView$$anon$3;
   0      6      1    repr       Ljava/lang/Object;


public scala.collection.IndexedSeq thisCollection();
  Code:
   Stack=1, Locals=1, Args_size=1
   0:	aload_0
   1:	invokestatic	#794; //Method scala/collection/IndexedSeqLike$class.thisCollection:(Lscala/collection/IndexedSeqLike;)Lscala/collection/IndexedSeq;
   4:	areturn
  LineNumberTable: 
   line 70: 0


public final boolean scala$collection$IndexedSeqLike$$super$endsWith(scala.collection.Seq);
  Code:
   Stack=2, Locals=2, Args_size=2
   0:	aload_0
   1:	aload_1
   2:	invokestatic	#797; //Method scala/collection/SeqLike$class.endsWith:(Lscala/collection/SeqLike;Lscala/collection/Seq;)Z
   5:	ireturn
  LineNumberTable: 
   line 70: 0

  LocalVariableTable: 
   Start  Length  Slot  Name   Signature
   0      6      0    this       Lscala/collection/mutable/IndexedSeqView$$anon$3;
   0      6      1    that       Lscala/collection/Seq;


public final boolean scala$collection$IndexedSeqLike$$super$sameElements(scala.collection.Iterable);
  Code:
   Stack=2, Locals=2, Args_size=2
   0:	aload_0
   1:	aload_1
   2:	invokestatic	#801; //Method scala/collection/IterableLike$class.sameElements:(Lscala/collection/IterableLike;Lscala/collection/Iterable;)Z
   5:	ireturn
  LineNumberTable: 
   line 70: 0

  LocalVariableTable: 
   Start  Length  Slot  Name   Signature
   0      6      0    this       Lscala/collection/mutable/IndexedSeqView$$anon$3;
   0      6      1    that       Lscala/collection/Iterable;


public final java.lang.Object scala$collection$IndexedSeqLike$$super$init();
  Code:
   Stack=1, Locals=1, Args_size=1
   0:	aload_0
   1:	invokestatic	#804; //Method scala/collection/TraversableLike$class.init:(Lscala/collection/TraversableLike;)Ljava/lang/Object;
   4:	areturn
  LineNumberTable: 
   line 70: 0


public final java.lang.Object scala$collection$IndexedSeqLike$$super$last();
  Code:
   Stack=1, Locals=1, Args_size=1
   0:	aload_0
   1:	invokestatic	#807; //Method scala/collection/TraversableLike$class.last:(Lscala/collection/TraversableLike;)Ljava/lang/Object;
   4:	areturn
  LineNumberTable: 
   line 70: 0


public final java.lang.Object scala$collection$IndexedSeqLike$$super$tail();
  Code:
   Stack=1, Locals=1, Args_size=1
   0:	aload_0
   1:	invokestatic	#810; //Method scala/collection/TraversableLike$class.tail:(Lscala/collection/TraversableLike;)Ljava/lang/Object;
   4:	areturn
  LineNumberTable: 
   line 70: 0


public final java.lang.Object scala$collection$IndexedSeqLike$$super$head();
  Code:
   Stack=1, Locals=1, Args_size=1
   0:	aload_0
   1:	invokestatic	#813; //Method scala/collection/IterableLike$class.head:(Lscala/collection/IterableLike;)Ljava/lang/Object;
   4:	areturn
  LineNumberTable: 
   line 70: 0


public final java.lang.Object scala$collection$IndexedSeqLike$$super$zip(scala.collection.Iterable, scala.collection.generic.CanBuildFrom);
  Code:
   Stack=3, Locals=3, Args_size=3
   0:	aload_0
   1:	aload_1
   2:	aload_2
   3:	invokestatic	#819; //Method scala/collection/IterableLike$class.zip:(Lscala/collection/IterableLike;Lscala/collection/Iterable;Lscala/collection/generic/CanBuildFrom;)Ljava/lang/Object;
   6:	areturn
  LineNumberTable: 
   line 70: 0

  LocalVariableTable: 
   Start  Length  Slot  Name   Signature
   0      7      0    this       Lscala/collection/mutable/IndexedSeqView$$anon$3;
   0      7      1    that       Lscala/collection/Iterable;
   0      7      2    bf       Lscala/collection/generic/CanBuildFrom;


public final java.lang.Object scala$collection$IndexedSeqLike$$super$reduceRight(scala.Function2);
  Code:
   Stack=2, Locals=2, Args_size=2
   0:	aload_0
   1:	aload_1
   2:	invokestatic	#823; //Method scala/collection/IterableLike$class.reduceRight:(Lscala/collection/IterableLike;Lscala/Function2;)Ljava/lang/Object;
   5:	areturn
  LineNumberTable: 
   line 70: 0

  LocalVariableTable: 
   Start  Length  Slot  Name   Signature
   0      6      0    this       Lscala/collection/mutable/IndexedSeqView$$anon$3;
   0      6      1    op       Lscala/Function2;


public final java.lang.Object scala$collection$IndexedSeqLike$$super$reduceLeft(scala.Function2);
  Code:
   Stack=2, Locals=2, Args_size=2
   0:	aload_0
   1:	aload_1
   2:	invokestatic	#827; //Method scala/collection/TraversableLike$class.reduceLeft:(Lscala/collection/TraversableLike;Lscala/Function2;)Ljava/lang/Object;
   5:	areturn
  LineNumberTable: 
   line 70: 0

  LocalVariableTable: 
   Start  Length  Slot  Name   Signature
   0      6      0    this       Lscala/collection/mutable/IndexedSeqView$$anon$3;
   0      6      1    op       Lscala/Function2;


public scala.collection.generic.GenericCompanion companion();
  Code:
   Stack=1, Locals=1, Args_size=1
   0:	aload_0
   1:	invokestatic	#832; //Method scala/collection/IndexedSeq$class.companion:(Lscala/collection/IndexedSeq;)Lscala/collection/generic/GenericCompanion;
   4:	areturn
  LineNumberTable: 
   line 70: 0


public java.lang.Object flatMap(scala.Function1, scala.collection.generic.CanBuildFrom);
  Code:
   Stack=3, Locals=3, Args_size=3
   0:	aload_0
   1:	aload_1
   2:	aload_2
   3:	invokestatic	#836; //Method scala/collection/TraversableViewLike$class.flatMap:(Lscala/collection/TraversableViewLike;Lscala/Function1;Lscala/collection/generic/CanBuildFrom;)Ljava/lang/Object;
   6:	areturn
  LineNumberTable: 
   line 70: 0

  LocalVariableTable: 
   Start  Length  Slot  Name   Signature
   0      7      0    this       Lscala/collection/mutable/IndexedSeqView$$anon$3;
   0      7      1    f       Lscala/Function1;
   0      7      2    bf       Lscala/collection/generic/CanBuildFrom;


public java.lang.Object map(scala.Function1, scala.collection.generic.CanBuildFrom);
  Code:
   Stack=3, Locals=3, Args_size=3
   0:	aload_0
   1:	aload_1
   2:	aload_2
   3:	invokestatic	#839; //Method scala/collection/TraversableViewLike$class.map:(Lscala/collection/TraversableViewLike;Lscala/Function1;Lscala/collection/generic/CanBuildFrom;)Ljava/lang/Object;
   6:	areturn
  LineNumberTable: 
   line 70: 0

  LocalVariableTable: 
   Start  Length  Slot  Name   Signature
   0      7      0    this       Lscala/collection/mutable/IndexedSeqView$$anon$3;
   0      7      1    f       Lscala/Function1;
   0      7      2    bf       Lscala/collection/generic/CanBuildFrom;


public java.lang.Object $plus$plus(scala.collection.Iterator, scala.collection.generic.CanBuildFrom);
  Code:
   Stack=3, Locals=3, Args_size=3
   0:	aload_0
   1:	aload_1
   2:	aload_2
   3:	invokestatic	#844; //Method scala/collection/TraversableViewLike$class.$plus$plus:(Lscala/collection/TraversableViewLike;Lscala/collection/Iterator;Lscala/collection/generic/CanBuildFrom;)Ljava/lang/Object;
   6:	areturn
  LineNumberTable: 
   line 70: 0

  LocalVariableTable: 
   Start  Length  Slot  Name   Signature
   0      7      0    this       Lscala/collection/mutable/IndexedSeqView$$anon$3;
   0      7      1    that       Lscala/collection/Iterator;
   0      7      2    bf       Lscala/collection/generic/CanBuildFrom;


public java.lang.Object $plus$plus(scala.collection.Traversable, scala.collection.generic.CanBuildFrom);
  Code:
   Stack=3, Locals=3, Args_size=3
   0:	aload_0
   1:	aload_1
   2:	aload_2
   3:	invokestatic	#849; //Method scala/collection/TraversableViewLike$class.$plus$plus:(Lscala/collection/TraversableViewLike;Lscala/collection/Traversable;Lscala/collection/generic/CanBuildFrom;)Ljava/lang/Object;
   6:	areturn
  LineNumberTable: 
   line 70: 0

  LocalVariableTable: 
   Start  Length  Slot  Name   Signature
   0      7      0    this       Lscala/collection/mutable/IndexedSeqView$$anon$3;
   0      7      1    that       Lscala/collection/Traversable;
   0      7      2    bf       Lscala/collection/generic/CanBuildFrom;


public java.lang.Object force(scala.collection.generic.CanBuildFrom);
  Code:
   Stack=2, Locals=2, Args_size=2
   0:	aload_0
   1:	aload_1
   2:	invokestatic	#854; //Method scala/collection/TraversableViewLike$class.force:(Lscala/collection/TraversableViewLike;Lscala/collection/generic/CanBuildFrom;)Ljava/lang/Object;
   5:	areturn
  LineNumberTable: 
   line 70: 0

  LocalVariableTable: 
   Start  Length  Slot  Name   Signature
   0      6      0    this       Lscala/collection/mutable/IndexedSeqView$$anon$3;
   0      6      1    bf       Lscala/collection/generic/CanBuildFrom;


public scala.collection.mutable.Builder newBuilder();
  Code:
   Stack=1, Locals=1, Args_size=1
   0:	aload_0
   1:	invokestatic	#858; //Method scala/collection/TraversableViewLike$class.newBuilder:(Lscala/collection/TraversableViewLike;)Lscala/collection/mutable/Builder;
   4:	areturn
  LineNumberTable: 
   line 70: 0


public java.lang.Object zipAll(scala.collection.Iterable, java.lang.Object, java.lang.Object, scala.collection.generic.CanBuildFrom);
  Code:
   Stack=5, Locals=5, Args_size=5
   0:	aload_0
   1:	aload_1
   2:	aload_2
   3:	aload_3
   4:	aload	4
   6:	invokestatic	#863; //Method scala/collection/IterableViewLike$class.zipAll:(Lscala/collection/IterableViewLike;Lscala/collection/Iterable;Ljava/lang/Object;Ljava/lang/Object;Lscala/collection/generic/CanBuildFrom;)Ljava/lang/Object;
   9:	areturn
  LineNumberTable: 
   line 70: 0

  LocalVariableTable: 
   Start  Length  Slot  Name   Signature
   0      10      0    this       Lscala/collection/mutable/IndexedSeqView$$anon$3;
   0      10      1    that       Lscala/collection/Iterable;
   0      10      2    thisElem       Ljava/lang/Object;
   0      10      3    thatElem       Ljava/lang/Object;
   0      10      4    bf       Lscala/collection/generic/CanBuildFrom;


public java.lang.Object zipWithIndex(scala.collection.generic.CanBuildFrom);
  Code:
   Stack=2, Locals=2, Args_size=2
   0:	aload_0
   1:	aload_1
   2:	invokestatic	#869; //Method scala/collection/IterableViewLike$class.zipWithIndex:(Lscala/collection/IterableViewLike;Lscala/collection/generic/CanBuildFrom;)Ljava/lang/Object;
   5:	areturn
  LineNumberTable: 
   line 70: 0

  LocalVariableTable: 
   Start  Length  Slot  Name   Signature
   0      6      0    this       Lscala/collection/mutable/IndexedSeqView$$anon$3;
   0      6      1    bf       Lscala/collection/generic/CanBuildFrom;


public java.lang.Object zip(scala.collection.Iterable, scala.collection.generic.CanBuildFrom);
  Code:
   Stack=3, Locals=3, Args_size=3
   0:	aload_0
   1:	aload_1
   2:	aload_2
   3:	invokestatic	#872; //Method scala/collection/IterableViewLike$class.zip:(Lscala/collection/IterableViewLike;Lscala/collection/Iterable;Lscala/collection/generic/CanBuildFrom;)Ljava/lang/Object;
   6:	areturn
  LineNumberTable: 
   line 70: 0

  LocalVariableTable: 
   Start  Length  Slot  Name   Signature
   0      7      0    this       Lscala/collection/mutable/IndexedSeqView$$anon$3;
   0      7      1    that       Lscala/collection/Iterable;
   0      7      2    bf       Lscala/collection/generic/CanBuildFrom;


public java.lang.Object padTo(int, java.lang.Object, scala.collection.generic.CanBuildFrom);
  Code:
   Stack=4, Locals=4, Args_size=4
   0:	aload_0
   1:	iload_1
   2:	aload_2
   3:	aload_3
   4:	invokestatic	#876; //Method scala/collection/SeqViewLike$class.padTo:(Lscala/collection/SeqViewLike;ILjava/lang/Object;Lscala/collection/generic/CanBuildFrom;)Ljava/lang/Object;
   7:	areturn
  LineNumberTable: 
   line 70: 0

  LocalVariableTable: 
   Start  Length  Slot  Name   Signature
   0      8      0    this       Lscala/collection/mutable/IndexedSeqView$$anon$3;
   0      8      1    len       I
   0      8      2    elem       Ljava/lang/Object;
   0      8      3    bf       Lscala/collection/generic/CanBuildFrom;


public java.lang.Object patch(int, scala.collection.Seq, int, scala.collection.generic.CanBuildFrom);
  Code:
   Stack=5, Locals=5, Args_size=5
   0:	aload_0
   1:	iload_1
   2:	aload_2
   3:	iload_3
   4:	aload	4
   6:	invokestatic	#881; //Method scala/collection/SeqViewLike$class.patch:(Lscala/collection/SeqViewLike;ILscala/collection/Seq;ILscala/collection/generic/CanBuildFrom;)Ljava/lang/Object;
   9:	areturn
  LineNumberTable: 
   line 70: 0

  LocalVariableTable: 
   Start  Length  Slot  Name   Signature
   0      10      0    this       Lscala/collection/mutable/IndexedSeqView$$anon$3;
   0      10      1    from       I
   0      10      2    patch       Lscala/collection/Seq;
   0      10      3    replaced       I
   0      10      4    bf       Lscala/collection/generic/CanBuildFrom;


public scala.collection.IndexedSeqViewLike$Transformed newPatched(int, scala.collection.Seq, int);
  Code:
   Stack=4, Locals=4, Args_size=4
   0:	aload_0
   1:	iload_1
   2:	aload_2
   3:	iload_3
   4:	invokestatic	#885; //Method scala/collection/IndexedSeqViewLike$class.newPatched:(Lscala/collection/IndexedSeqViewLike;ILscala/collection/Seq;I)Lscala/collection/IndexedSeqViewLike$Transformed;
   7:	areturn
  LineNumberTable: 
   line 70: 0

  LocalVariableTable: 
   Start  Length  Slot  Name   Signature
   0      8      0    this       Lscala/collection/mutable/IndexedSeqView$$anon$3;
   0      8      1    _from       I
   0      8      2    _patch       Lscala/collection/Seq;
   0      8      3    _replaced       I

  Signature: length = 0x2
   01 0C 

public scala.collection.IndexedSeqViewLike$Transformed newZippedAll(scala.collection.Iterable, java.lang.Object, java.lang.Object);
  Code:
   Stack=4, Locals=4, Args_size=4
   0:	aload_0
   1:	aload_1
   2:	aload_2
   3:	aload_3
   4:	invokestatic	#888; //Method scala/collection/IndexedSeqViewLike$class.newZippedAll:(Lscala/collection/IndexedSeqViewLike;Lscala/collection/Iterable;Ljava/lang/Object;Ljava/lang/Object;)Lscala/collection/IndexedSeqViewLike$Transformed;
   7:	areturn
  LineNumberTable: 
   line 70: 0

  LocalVariableTable: 
   Start  Length  Slot  Name   Signature
   0      8      0    this       Lscala/collection/mutable/IndexedSeqView$$anon$3;
   0      8      1    that       Lscala/collection/Iterable;
   0      8      2    _thisElem       Ljava/lang/Object;
   0      8      3    _thatElem       Ljava/lang/Object;

  Signature: length = 0x2
   01 04 

public scala.collection.IndexedSeqViewLike$Transformed newZipped(scala.collection.Iterable);
  Code:
   Stack=2, Locals=2, Args_size=2
   0:	aload_0
   1:	aload_1
   2:	invokestatic	#891; //Method scala/collection/IndexedSeqViewLike$class.newZipped:(Lscala/collection/IndexedSeqViewLike;Lscala/collection/Iterable;)Lscala/collection/IndexedSeqViewLike$Transformed;
   5:	areturn
  LineNumberTable: 
   line 70: 0

  LocalVariableTable: 
   Start  Length  Slot  Name   Signature
   0      6      0    this       Lscala/collection/mutable/IndexedSeqView$$anon$3;
   0      6      1    that       Lscala/collection/Iterable;

  Signature: length = 0x2
   00 FFFFFFFD 

public scala.collection.IndexedSeqViewLike$Transformed newFlatMapped(scala.Function1);
  Code:
   Stack=2, Locals=2, Args_size=2
   0:	aload_0
   1:	aload_1
   2:	invokestatic	#894; //Method scala/collection/IndexedSeqViewLike$class.newFlatMapped:(Lscala/collection/IndexedSeqViewLike;Lscala/Function1;)Lscala/collection/IndexedSeqViewLike$Transformed;
   5:	areturn
  LineNumberTable: 
   line 70: 0

  LocalVariableTable: 
   Start  Length  Slot  Name   Signature
   0      6      0    this       Lscala/collection/mutable/IndexedSeqView$$anon$3;
   0      6      1    f       Lscala/Function1;

  Signature: length = 0x2
   00 FFFFFFA2 

public scala.collection.IndexedSeqViewLike$Transformed newMapped(scala.Function1);
  Code:
   Stack=2, Locals=2, Args_size=2
   0:	aload_0
   1:	aload_1
   2:	invokestatic	#896; //Method scala/collection/IndexedSeqViewLike$class.newMapped:(Lscala/collection/IndexedSeqViewLike;Lscala/Function1;)Lscala/collection/IndexedSeqViewLike$Transformed;
   5:	areturn
  LineNumberTable: 
   line 70: 0

  LocalVariableTable: 
   Start  Length  Slot  Name   Signature
   0      6      0    this       Lscala/collection/mutable/IndexedSeqView$$anon$3;
   0      6      1    f       Lscala/Function1;

  Signature: length = 0x2
   00 FFFFFFA2 

public scala.collection.IndexedSeqViewLike$Transformed newAppended(scala.collection.Traversable);
  Code:
   Stack=2, Locals=2, Args_size=2
   0:	aload_0
   1:	aload_1
   2:	invokestatic	#899; //Method scala/collection/IndexedSeqViewLike$class.newAppended:(Lscala/collection/IndexedSeqViewLike;Lscala/collection/Traversable;)Lscala/collection/IndexedSeqViewLike$Transformed;
   5:	areturn
  LineNumberTable: 
   line 70: 0

  LocalVariableTable: 
   Start  Length  Slot  Name   Signature
   0      6      0    this       Lscala/collection/mutable/IndexedSeqView$$anon$3;
   0      6      1    that       Lscala/collection/Traversable;

  Signature: length = 0x2
   00 FFFFFFED 

public scala.collection.mutable.IndexedSeqView reverse();
  Code:
   Stack=1, Locals=1, Args_size=1
   0:	aload_0
   1:	invokestatic	#902; //Method scala/collection/mutable/IndexedSeqView$class.reverse:(Lscala/collection/mutable/IndexedSeqView;)Lscala/collection/mutable/IndexedSeqView;
   4:	areturn
  LineNumberTable: 
   line 70: 0


public scala.Tuple2 splitAt(int);
  Code:
   Stack=2, Locals=2, Args_size=2
   0:	aload_0
   1:	iload_1
   2:	invokestatic	#907; //Method scala/collection/mutable/IndexedSeqView$class.splitAt:(Lscala/collection/mutable/IndexedSeqView;I)Lscala/Tuple2;
   5:	areturn
  LineNumberTable: 
   line 70: 0

  LocalVariableTable: 
   Start  Length  Slot  Name   Signature
   0      6      0    this       Lscala/collection/mutable/IndexedSeqView$$anon$3;
   0      6      1    n       I


public scala.Tuple2 span(scala.Function1);
  Code:
   Stack=2, Locals=2, Args_size=2
   0:	aload_0
   1:	aload_1
   2:	invokestatic	#911; //Method scala/collection/mutable/IndexedSeqView$class.span:(Lscala/collection/mutable/IndexedSeqView;Lscala/Function1;)Lscala/Tuple2;
   5:	areturn
  LineNumberTable: 
   line 70: 0

  LocalVariableTable: 
   Start  Length  Slot  Name   Signature
   0      6      0    this       Lscala/collection/mutable/IndexedSeqView$$anon$3;
   0      6      1    p       Lscala/Function1;


public scala.collection.mutable.IndexedSeqView takeWhile(scala.Function1);
  Code:
   Stack=2, Locals=2, Args_size=2
   0:	aload_0
   1:	aload_1
   2:	invokestatic	#914; //Method scala/collection/mutable/IndexedSeqView$class.takeWhile:(Lscala/collection/mutable/IndexedSeqView;Lscala/Function1;)Lscala/collection/mutable/IndexedSeqView;
   5:	areturn
  LineNumberTable: 
   line 70: 0

  LocalVariableTable: 
   Start  Length  Slot  Name   Signature
   0      6      0    this       Lscala/collection/mutable/IndexedSeqView$$anon$3;
   0      6      1    p       Lscala/Function1;


public scala.collection.mutable.IndexedSeqView dropWhile(scala.Function1);
  Code:
   Stack=2, Locals=2, Args_size=2
   0:	aload_0
   1:	aload_1
   2:	invokestatic	#916; //Method scala/collection/mutable/IndexedSeqView$class.dropWhile:(Lscala/collection/mutable/IndexedSeqView;Lscala/Function1;)Lscala/collection/mutable/IndexedSeqView;
   5:	areturn
  LineNumberTable: 
   line 70: 0

  LocalVariableTable: 
   Start  Length  Slot  Name   Signature
   0      6      0    this       Lscala/collection/mutable/IndexedSeqView$$anon$3;
   0      6      1    p       Lscala/Function1;


public scala.collection.mutable.IndexedSeqView slice(int, int);
  Code:
   Stack=3, Locals=3, Args_size=3
   0:	aload_0
   1:	iload_1
   2:	iload_2
   3:	invokestatic	#919; //Method scala/collection/mutable/IndexedSeqView$class.slice:(Lscala/collection/mutable/IndexedSeqView;II)Lscala/collection/mutable/IndexedSeqView;
   6:	areturn
  LineNumberTable: 
   line 70: 0

  LocalVariableTable: 
   Start  Length  Slot  Name   Signature
   0      7      0    this       Lscala/collection/mutable/IndexedSeqView$$anon$3;
   0      7      1    from       I
   0      7      2    until       I


public scala.collection.mutable.IndexedSeqView take(int);
  Code:
   Stack=2, Locals=2, Args_size=2
   0:	aload_0
   1:	iload_1
   2:	invokestatic	#922; //Method scala/collection/mutable/IndexedSeqView$class.take:(Lscala/collection/mutable/IndexedSeqView;I)Lscala/collection/mutable/IndexedSeqView;
   5:	areturn
  LineNumberTable: 
   line 70: 0

  LocalVariableTable: 
   Start  Length  Slot  Name   Signature
   0      6      0    this       Lscala/collection/mutable/IndexedSeqView$$anon$3;
   0      6      1    n       I


public scala.collection.mutable.IndexedSeqView drop(int);
  Code:
   Stack=2, Locals=2, Args_size=2
   0:	aload_0
   1:	iload_1
   2:	invokestatic	#924; //Method scala/collection/mutable/IndexedSeqView$class.drop:(Lscala/collection/mutable/IndexedSeqView;I)Lscala/collection/mutable/IndexedSeqView;
   5:	areturn
  LineNumberTable: 
   line 70: 0

  LocalVariableTable: 
   Start  Length  Slot  Name   Signature
   0      6      0    this       Lscala/collection/mutable/IndexedSeqView$$anon$3;
   0      6      1    n       I


public scala.collection.mutable.IndexedSeqView init();
  Code:
   Stack=1, Locals=1, Args_size=1
   0:	aload_0
   1:	invokestatic	#926; //Method scala/collection/mutable/IndexedSeqView$class.init:(Lscala/collection/mutable/IndexedSeqView;)Lscala/collection/mutable/IndexedSeqView;
   4:	areturn
  LineNumberTable: 
   line 70: 0


public scala.collection.mutable.IndexedSeqView filter(scala.Function1);
  Code:
   Stack=2, Locals=2, Args_size=2
   0:	aload_0
   1:	aload_1
   2:	invokestatic	#928; //Method scala/collection/mutable/IndexedSeqView$class.filter:(Lscala/collection/mutable/IndexedSeqView;Lscala/Function1;)Lscala/collection/mutable/IndexedSeqView;
   5:	areturn
  LineNumberTable: 
   line 70: 0

  LocalVariableTable: 
   Start  Length  Slot  Name   Signature
   0      6      0    this       Lscala/collection/mutable/IndexedSeqView$$anon$3;
   0      6      1    p       Lscala/Function1;


public scala.collection.mutable.IndexedSeqView$Transformed newReversed();
  Code:
   Stack=1, Locals=1, Args_size=1
   0:	aload_0
   1:	invokestatic	#931; //Method scala/collection/mutable/IndexedSeqView$class.newReversed:(Lscala/collection/mutable/IndexedSeqView;)Lscala/collection/mutable/IndexedSeqView$Transformed;
   4:	areturn
  LineNumberTable: 
   line 70: 0

  Signature: length = 0x2
   00 FFFFFFBE 

public scala.collection.mutable.IndexedSeqView$Transformed newTakenWhile(scala.Function1);
  Code:
   Stack=2, Locals=2, Args_size=2
   0:	aload_0
   1:	aload_1
   2:	invokestatic	#934; //Method scala/collection/mutable/IndexedSeqView$class.newTakenWhile:(Lscala/collection/mutable/IndexedSeqView;Lscala/Function1;)Lscala/collection/mutable/IndexedSeqView$Transformed;
   5:	areturn
  LineNumberTable: 
   line 70: 0

  LocalVariableTable: 
   Start  Length  Slot  Name   Signature
   0      6      0    this       Lscala/collection/mutable/IndexedSeqView$$anon$3;
   0      6      1    p       Lscala/Function1;

  Signature: length = 0x2
   00 FFFFFFA5 

public scala.collection.mutable.IndexedSeqView$Transformed newDroppedWhile(scala.Function1);
  Code:
   Stack=2, Locals=2, Args_size=2
   0:	aload_0
   1:	aload_1
   2:	invokestatic	#936; //Method scala/collection/mutable/IndexedSeqView$class.newDroppedWhile:(Lscala/collection/mutable/IndexedSeqView;Lscala/Function1;)Lscala/collection/mutable/IndexedSeqView$Transformed;
   5:	areturn
  LineNumberTable: 
   line 70: 0

  LocalVariableTable: 
   Start  Length  Slot  Name   Signature
   0      6      0    this       Lscala/collection/mutable/IndexedSeqView$$anon$3;
   0      6      1    p       Lscala/Function1;

  Signature: length = 0x2
   00 FFFFFFA5 

public scala.collection.mutable.IndexedSeqView$Transformed newSliced(int, int);
  Code:
   Stack=3, Locals=3, Args_size=3
   0:	aload_0
   1:	iload_1
   2:	iload_2
   3:	invokestatic	#939; //Method scala/collection/mutable/IndexedSeqView$class.newSliced:(Lscala/collection/mutable/IndexedSeqView;II)Lscala/collection/mutable/IndexedSeqView$Transformed;
   6:	areturn
  LineNumberTable: 
   line 70: 0

  LocalVariableTable: 
   Start  Length  Slot  Name   Signature
   0      7      0    this       Lscala/collection/mutable/IndexedSeqView$$anon$3;
   0      7      1    _from       I
   0      7      2    _until       I

  Signature: length = 0x2
   00 FFFFFFAE 

public scala.collection.mutable.IndexedSeqView$Transformed newFiltered(scala.Function1);
  Code:
   Stack=2, Locals=2, Args_size=2
   0:	aload_0
   1:	aload_1
   2:	invokestatic	#941; //Method scala/collection/mutable/IndexedSeqView$class.newFiltered:(Lscala/collection/mutable/IndexedSeqView;Lscala/Function1;)Lscala/collection/mutable/IndexedSeqView$Transformed;
   5:	areturn
  LineNumberTable: 
   line 70: 0

  LocalVariableTable: 
   Start  Length  Slot  Name   Signature
   0      6      0    this       Lscala/collection/mutable/IndexedSeqView$$anon$3;
   0      6      1    p       Lscala/Function1;

  Signature: length = 0x2
   00 FFFFFFA5 

public java.lang.Object underlying();
  Code:
   Stack=3, Locals=1, Args_size=1
   0:	aload_0
   1:	getfield	#943; //Field bitmap$0:I
   4:	iconst_4
   5:	iand
   6:	iconst_0
   7:	if_icmpne	44
   10:	aload_0
   11:	dup
   12:	pop
   13:	monitorenter
   14:	aload_0
   15:	getfield	#943; //Field bitmap$0:I
   18:	iconst_4
   19:	iand
   20:	iconst_0
   21:	if_icmpne	42
   24:	aload_0
   25:	aload_0
   26:	invokestatic	#946; //Method scala/collection/TraversableViewLike$Transformed$class.underlying:(Lscala/collection/TraversableViewLike$Transformed;)Ljava/lang/Object;
   29:	putfield	#948; //Field underlying:Ljava/lang/Object;
   32:	aload_0
   33:	aload_0
   34:	getfield	#943; //Field bitmap$0:I
   37:	iconst_4
   38:	ior
   39:	putfield	#943; //Field bitmap$0:I
   42:	aload_0
   43:	monitorexit
   44:	aload_0
   45:	getfield	#948; //Field underlying:Ljava/lang/Object;
   48:	areturn
   49:	aload_0
   50:	monitorexit
   51:	athrow
  Exception table:
   from   to  target type
    14    44    49   any
  LineNumberTable: 
   line 70: 0
   line 341: 6
   line 70: 10
   line 341: 20
   line 70: 24


public java.lang.String stringPrefix();
  Code:
   Stack=1, Locals=1, Args_size=1
   0:	aload_0
   1:	invokestatic	#952; //Method scala/collection/TraversableViewLike$DroppedWhile$class.stringPrefix:(Lscala/collection/TraversableViewLike$DroppedWhile;)Ljava/lang/String;
   4:	areturn
  LineNumberTable: 
   line 70: 0


public scala.collection.Iterator iterator();
  Code:
   Stack=1, Locals=1, Args_size=1
   0:	aload_0
   1:	invokestatic	#956; //Method scala/collection/IterableViewLike$DroppedWhile$class.iterator:(Lscala/collection/IterableViewLike$DroppedWhile;)Lscala/collection/Iterator;
   4:	areturn
  LineNumberTable: 
   line 70: 0


public java.lang.Object apply(int);
  Code:
   Stack=2, Locals=2, Args_size=2
   0:	aload_0
   1:	iload_1
   2:	invokestatic	#959; //Method scala/collection/SeqViewLike$DroppedWhile$class.apply:(Lscala/collection/SeqViewLike$DroppedWhile;I)Ljava/lang/Object;
   5:	areturn
  LineNumberTable: 
   line 70: 0

  LocalVariableTable: 
   Start  Length  Slot  Name   Signature
   0      6      0    this       Lscala/collection/mutable/IndexedSeqView$$anon$3;
   0      6      1    idx       I


public int length();
  Code:
   Stack=1, Locals=1, Args_size=1
   0:	aload_0
   1:	invokestatic	#963; //Method scala/collection/SeqViewLike$DroppedWhile$class.length:(Lscala/collection/SeqViewLike$DroppedWhile;)I
   4:	ireturn
  LineNumberTable: 
   line 70: 0


public int start();
  Code:
   Stack=3, Locals=1, Args_size=1
   0:	aload_0
   1:	getfield	#943; //Field bitmap$0:I
   4:	iconst_1
   5:	iand
   6:	iconst_0
   7:	if_icmpne	44
   10:	aload_0
   11:	dup
   12:	pop
   13:	monitorenter
   14:	aload_0
   15:	getfield	#943; //Field bitmap$0:I
   18:	iconst_1
   19:	iand
   20:	iconst_0
   21:	if_icmpne	42
   24:	aload_0
   25:	aload_0
   26:	invokestatic	#965; //Method scala/collection/SeqViewLike$DroppedWhile$class.start:(Lscala/collection/SeqViewLike$DroppedWhile;)I
   29:	putfield	#967; //Field start:I
   32:	aload_0
   33:	aload_0
   34:	getfield	#943; //Field bitmap$0:I
   37:	iconst_1
   38:	ior
   39:	putfield	#943; //Field bitmap$0:I
   42:	aload_0
   43:	monitorexit
   44:	aload_0
   45:	getfield	#967; //Field start:I
   48:	ireturn
   49:	aload_0
   50:	monitorexit
   51:	athrow
  Exception table:
   from   to  target type
    14    44    49   any
  LineNumberTable: 
   line 70: 0
   line 341: 6
   line 70: 10
   line 341: 20
   line 70: 24


public void foreach(scala.Function1);
  Code:
   Stack=2, Locals=2, Args_size=2
   0:	aload_0
   1:	aload_1
   2:	invokestatic	#971; //Method scala/collection/IndexedSeqViewLike$DroppedWhile$class.foreach:(Lscala/collection/IndexedSeqViewLike$DroppedWhile;Lscala/Function1;)V
   5:	return
  LineNumberTable: 
   line 70: 0

  LocalVariableTable: 
   Start  Length  Slot  Name   Signature
   0      6      0    this       Lscala/collection/mutable/IndexedSeqView$$anon$3;
   0      6      1    f       Lscala/Function1;


public void update(int, java.lang.Object);
  Code:
   Stack=3, Locals=3, Args_size=3
   0:	aload_0
   1:	iload_1
   2:	aload_2
   3:	invokestatic	#976; //Method scala/collection/mutable/IndexedSeqView$DroppedWhile$class.update:(Lscala/collection/mutable/IndexedSeqView$DroppedWhile;ILjava/lang/Object;)V
   6:	return
  LineNumberTable: 
   line 70: 0

  LocalVariableTable: 
   Start  Length  Slot  Name   Signature
   0      7      0    this       Lscala/collection/mutable/IndexedSeqView$$anon$3;
   0      7      1    idx       I
   0      7      2    elem       Ljava/lang/Object;


}

