Compiled from "LinkedEntry.scala"
public final class scala.collection.mutable.LinkedEntry extends java.lang.Object implements scala.collection.mutable.HashEntry,scala.ScalaObject,java.io.Serializable
  SourceFile: "LinkedEntry.scala"
  Signature: length = 0x2
   00 39 
  ScalaSig: length = 0x230
   05 00 56 06 04 01 02 02 09 02 0B 4C 69 6E 6B 65
   64 45 6E 74 72 79 0A 02 03 04 01 07 6D 75 74 61
   62 6C 65 0A 02 05 06 01 0A 63 6F 6C 6C 65 63 74
   69 6F 6E 0A 01 07 01 05 73 63 61 6C 61 03 00 15
   03 0A 19 25 13 04 00 0B 13 27 10 02 0C 11 0D 01
   0D 0A 02 0E 0F 01 04 6C 61 6E 67 0A 01 10 01 04
   6A 61 76 61 09 02 12 0D 02 06 4F 62 6A 65 63 74
   10 04 14 15 17 23 0D 01 02 09 02 16 02 02 09 48
   61 73 68 45 6E 74 72 79 10 02 18 19 0C 00 04 08
   1A 00 FFFFFF84 FFFFFF80 FFFFFF80 FFFFFFC2 00 1B 02 01 41 11 02 1C 20 10
   02 1D 1E 0D 01 06 09 02 1F 06 02 07 4E 6F 74 68
   69 6E 67 10 02 1D 21 09 02 22 06 02 03 41 6E 79
   10 04 14 00 17 24 10 02 18 25 04 08 26 00 FFFFFF84 FFFFFF80
   FFFFFF80 FFFFFFC2 00 1B 02 01 42 10 02 1D 28 09 02 29 06 02
   0B 53 63 61 6C 61 4F 62 6A 65 63 74 08 08 2B 00
   FFFFFF82 FFFFFFC2 FFFFFF80 FFFFFF84 00 2C 01 03 6B 65 79 15 01 17 08 08
   2E 00 FFFFFF82 FFFFFF80 FFFFFFA0 FFFFFF80 04 17 01 04 6B 65 79 20 08 08
   30 00 FFFFFF82 FFFFFFC0 FFFFFF80 FFFFFF84 00 31 01 05 76 61 6C 75 65 15
   01 24 08 08 33 00 FFFFFF82 FFFFFFC0 FFFFFF80 FFFFFF84 00 34 01 09 76 61
   6C 75 65 5F 24 65 71 14 02 35 38 10 02 1D 36 09
   02 37 06 02 04 55 6E 69 74 08 07 39 32 FFFFFF81 FFFFFF80 FFFFFFC0
   00 24 01 03 78 24 31 08 08 3B 00 FFFFFF82 FFFFFF80 FFFFFFA0 FFFFFFA0 04
   24 01 06 76 61 6C 75 65 20 08 05 3D 00 FFFFFF84 00 3E
   01 06 3C 69 6E 69 74 3E 14 03 23 3F 40 08 05 2B
   3C FFFFFFC0 00 17 08 05 30 3C FFFFFFC0 00 24 08 07 42 00 FFFFFFC0
   FFFFFF80 FFFFFF84 00 43 01 07 65 61 72 6C 69 65 72 15 01 23
   08 07 45 00 FFFFFFC0 FFFFFF80 FFFFFF84 00 46 01 0B 65 61 72 6C 69
   65 72 5F 24 65 71 14 02 35 47 08 07 39 44 FFFFFF81 FFFFFF80
   FFFFFFC0 00 23 08 06 49 00 FFFFFFA0 FFFFFFA0 04 23 01 08 65 61 72
   6C 69 65 72 20 08 07 4B 00 FFFFFFC0 FFFFFF80 FFFFFF84 00 43 01 05
   6C 61 74 65 72 08 07 4D 00 FFFFFFC0 FFFFFF80 FFFFFF84 00 4E 01 09
   6C 61 74 65 72 5F 24 65 71 14 02 35 4F 08 07 39
   4C FFFFFF81 FFFFFF80 FFFFFFC0 00 23 08 06 51 00 FFFFFFA0 FFFFFFA0 04 23 01 06
   6C 61 74 65 72 20 28 02 00 53 10 02 1D 54 09 02
   55 06 02 0C 73 65 72 69 61 6C 69 7A 61 62 6C 65
   
  minor version: 0
  major version: 49
  Constant pool:
const #1 = Asciz	SourceFile;
const #2 = Asciz	LinkedEntry.scala;
const #3 = Asciz	next;
const #4 = Asciz	Ljava/lang/Object;;
const #5 = Asciz	later;
const #6 = Asciz	Lscala/collection/mutable/LinkedEntry;;
const #7 = Asciz	Lscala/collection/mutable/LinkedEntry<TA;TB;>;;
const #8 = Asciz	Signature;
const #9 = Asciz	earlier;
const #10 = Asciz	value;
const #11 = Asciz	TB;;
const #12 = Asciz	key;
const #13 = Asciz	TA;;
const #14 = Asciz	<init>;
const #15 = Asciz	(Ljava/lang/Object;Ljava/lang/Object;)V;
const #16 = Asciz	Code;
const #17 = Asciz	LineNumberTable;
const #18 = Asciz	scala/collection/mutable/LinkedEntry;
const #19 = class	#18;	//  scala/collection/mutable/LinkedEntry
const #20 = NameAndType	#12:#4;//  key:Ljava/lang/Object;
const #21 = Field	#19.#20;	//  scala/collection/mutable/LinkedEntry.key:Ljava/lang/Object;
const #22 = NameAndType	#10:#4;//  value:Ljava/lang/Object;
const #23 = Field	#19.#22;	//  scala/collection/mutable/LinkedEntry.value:Ljava/lang/Object;
const #24 = Asciz	java/lang/Object;
const #25 = class	#24;	//  java/lang/Object
const #26 = Asciz	()V;
const #27 = NameAndType	#14:#26;//  "<init>":()V
const #28 = Method	#25.#27;	//  java/lang/Object."<init>":()V
const #29 = Asciz	scala/collection/mutable/HashEntry$class;
const #30 = class	#29;	//  scala/collection/mutable/HashEntry$class
const #31 = Asciz	$init$;
const #32 = Asciz	(Lscala/collection/mutable/HashEntry;)V;
const #33 = NameAndType	#31:#32;//  $init$:(Lscala/collection/mutable/HashEntry;)V
const #34 = Method	#30.#33;	//  scala/collection/mutable/HashEntry$class.$init$:(Lscala/collection/mutable/HashEntry;)V
const #35 = NameAndType	#9:#6;//  earlier:Lscala/collection/mutable/LinkedEntry;
const #36 = Field	#19.#35;	//  scala/collection/mutable/LinkedEntry.earlier:Lscala/collection/mutable/LinkedEntry;
const #37 = NameAndType	#5:#6;//  later:Lscala/collection/mutable/LinkedEntry;
const #38 = Field	#19.#37;	//  scala/collection/mutable/LinkedEntry.later:Lscala/collection/mutable/LinkedEntry;
const #39 = Asciz	this;
const #40 = Asciz	LocalVariableTable;
const #41 = Asciz	(TA;TB;)V;
const #42 = Asciz	later_$eq;
const #43 = Asciz	(Lscala/collection/mutable/LinkedEntry;)V;
const #44 = Asciz	(Lscala/collection/mutable/LinkedEntry<TA;TB;>;)V;
const #45 = Asciz	()Lscala/collection/mutable/LinkedEntry;;
const #46 = Asciz	()Lscala/collection/mutable/LinkedEntry<TA;TB;>;;
const #47 = Asciz	earlier_$eq;
const #48 = Asciz	value_$eq;
const #49 = Asciz	(Ljava/lang/Object;)V;
const #50 = Asciz	(TB;)V;
const #51 = Asciz	()Ljava/lang/Object;;
const #52 = Asciz	()TB;;
const #53 = Asciz	()TA;;
const #54 = Asciz	next_$eq;
const #55 = NameAndType	#3:#4;//  next:Ljava/lang/Object;
const #56 = Field	#19.#55;	//  scala/collection/mutable/LinkedEntry.next:Ljava/lang/Object;
const #57 = Asciz	<A:Ljava/lang/Object;B:Ljava/lang/Object;>Ljava/lang/Object;Lscala/collection/mutable/HashEntry<TA;Lscala/collection/mutable/LinkedEntry<TA;TB;>;>;Lscala/ScalaObject;;
const #58 = Asciz	ScalaSig;
const #59 = Asciz	scala/collection/mutable/HashEntry;
const #60 = class	#59;	//  scala/collection/mutable/HashEntry
const #61 = Asciz	scala/ScalaObject;
const #62 = class	#61;	//  scala/ScalaObject
const #63 = Asciz	java/io/Serializable;
const #64 = class	#63;	//  java/io/Serializable

{
public scala.collection.mutable.LinkedEntry(java.lang.Object, java.lang.Object);
  Code:
   Stack=2, Locals=3, Args_size=3
   0:	aload_0
   1:	aload_1
   2:	putfield	#21; //Field key:Ljava/lang/Object;
   5:	aload_0
   6:	aload_2
   7:	putfield	#23; //Field value:Ljava/lang/Object;
   10:	aload_0
   11:	invokespecial	#28; //Method java/lang/Object."<init>":()V
   14:	aload_0
   15:	invokestatic	#34; //Method scala/collection/mutable/HashEntry$class.$init$:(Lscala/collection/mutable/HashEntry;)V
   18:	aload_0
   19:	aconst_null
   20:	pop
   21:	aconst_null
   22:	putfield	#36; //Field earlier:Lscala/collection/mutable/LinkedEntry;
   25:	aload_0
   26:	aconst_null
   27:	pop
   28:	aconst_null
   29:	putfield	#38; //Field later:Lscala/collection/mutable/LinkedEntry;
   32:	return
  LineNumberTable: 
   line 15: 0
   line 17: 18
   line 18: 25

  LocalVariableTable: 
   Start  Length  Slot  Name   Signature
   0      33      0    this       Lscala/collection/mutable/LinkedEntry;
   0      33      1    key       Ljava/lang/Object;
   0      33      2    value       Ljava/lang/Object;

  Signature: length = 0x2
   00 29 

public void later_$eq(scala.collection.mutable.LinkedEntry);
  Code:
   Stack=2, Locals=2, Args_size=2
   0:	aload_0
   1:	aload_1
   2:	putfield	#38; //Field later:Lscala/collection/mutable/LinkedEntry;
   5:	return
  LineNumberTable: 
   line 18: 0

  Signature: length = 0x2
   00 2C 

public scala.collection.mutable.LinkedEntry later();
  Code:
   Stack=1, Locals=1, Args_size=1
   0:	aload_0
   1:	getfield	#38; //Field later:Lscala/collection/mutable/LinkedEntry;
   4:	areturn
  LineNumberTable: 
   line 18: 0

  Signature: length = 0x2
   00 2E 

public void earlier_$eq(scala.collection.mutable.LinkedEntry);
  Code:
   Stack=2, Locals=2, Args_size=2
   0:	aload_0
   1:	aload_1
   2:	putfield	#36; //Field earlier:Lscala/collection/mutable/LinkedEntry;
   5:	return
  LineNumberTable: 
   line 17: 0

  Signature: length = 0x2
   00 2C 

public scala.collection.mutable.LinkedEntry earlier();
  Code:
   Stack=1, Locals=1, Args_size=1
   0:	aload_0
   1:	getfield	#36; //Field earlier:Lscala/collection/mutable/LinkedEntry;
   4:	areturn
  LineNumberTable: 
   line 17: 0

  Signature: length = 0x2
   00 2E 

public void value_$eq(java.lang.Object);
  Code:
   Stack=2, Locals=2, Args_size=2
   0:	aload_0
   1:	aload_1
   2:	putfield	#23; //Field value:Ljava/lang/Object;
   5:	return
  LineNumberTable: 
   line 15: 0

  Signature: length = 0x2
   00 32 

public java.lang.Object value();
  Code:
   Stack=1, Locals=1, Args_size=1
   0:	aload_0
   1:	getfield	#23; //Field value:Ljava/lang/Object;
   4:	areturn
  LineNumberTable: 
   line 15: 0

  Signature: length = 0x2
   00 34 

public java.lang.Object key();
  Code:
   Stack=1, Locals=1, Args_size=1
   0:	aload_0
   1:	getfield	#21; //Field key:Ljava/lang/Object;
   4:	areturn
  LineNumberTable: 
   line 15: 0

  Signature: length = 0x2
   00 35 

public void next_$eq(java.lang.Object);
  Code:
   Stack=2, Locals=2, Args_size=2
   0:	aload_0
   1:	aload_1
   2:	putfield	#56; //Field next:Ljava/lang/Object;
   5:	return
  LineNumberTable: 
   line 15: 0


public java.lang.Object next();
  Code:
   Stack=1, Locals=1, Args_size=1
   0:	aload_0
   1:	getfield	#56; //Field next:Ljava/lang/Object;
   4:	areturn
  LineNumberTable: 
   line 15: 0


}

