Compiled from "LinkedHashMap.scala"
public class scala.collection.mutable.LinkedHashMap extends java.lang.Object implements scala.collection.mutable.Map,scala.collection.mutable.MapLike,scala.collection.mutable.HashTable,scala.ScalaObject,java.io.Serializable
  SourceFile: "LinkedHashMap.scala"
  Signature: length = 0x2
   04 00 
  ScalaSig: length = 0x634
   05 00 FFFFFF81 61 07 05 01 02 FFFFFF88 02 09 01 0D 4C 69 6E
   6B 65 64 48 61 73 68 4D 61 70 0A 02 03 04 01 07
   6D 75 74 61 62 6C 65 0A 02 05 06 01 0A 63 6F 6C
   6C 65 63 74 69 6F 6E 0A 01 07 01 05 73 63 61 6C
   61 03 00 10 02 0A 0B 0D 01 02 06 08 0C 02 FFFFFF84 FFFFFF80
   FFFFFF80 FFFFFF88 02 0D 02 0D 4C 69 6E 6B 65 64 48 61 73 68
   4D 61 70 13 03 0B 0E 39 10 03 0F 12 14 0D 01 10
   0A 02 11 04 01 07 67 65 6E 65 72 69 63 09 02 13
   10 02 11 4D 75 74 61 62 6C 65 4D 61 70 46 61 63
   74 6F 72 79 10 02 0A 15 06 04 0C 02 00 16 15 03
   17 25 30 13 06 15 18 20 32 36 39 10 02 19 1E 0D
   01 1A 0A 02 1B 1C 01 04 6C 61 6E 67 0A 01 1D 01
   04 6A 61 76 61 09 02 1F 1A 02 06 4F 62 6A 65 63
   74 10 04 0A 21 23 2F 09 02 22 02 02 03 4D 61 70
   10 02 24 25 0C 00 04 08 26 15 FFFFFF84 FFFFFF80 FFFFFF80 FFFFFFC2 00 27
   02 01 41 11 02 28 2C 10 02 29 2A 0D 01 06 09 02
   2B 06 02 07 4E 6F 74 68 69 6E 67 10 02 29 2D 09
   02 2E 06 02 03 41 6E 79 10 02 24 30 04 08 31 15
   FFFFFF84 FFFFFF80 FFFFFF80 FFFFFFC2 00 27 02 01 42 10 05 0A 33 23 2F 35
   09 02 34 02 02 07 4D 61 70 4C 69 6B 65 10 04 0A
   15 23 2F 10 03 0A 37 23 09 02 38 02 02 09 48 61
   73 68 54 61 62 6C 65 10 02 29 3A 09 02 3B 06 02
   0B 53 63 61 6C 61 4F 62 6A 65 63 74 08 05 3D 15
   FFFFFF84 00 3E 01 06 3C 69 6E 69 74 3E 14 01 35 08 05
   40 15 FFFFFF84 20 41 01 05 65 6D 70 74 79 15 01 35 08
   05 43 15 FFFFFF84 20 44 01 04 73 69 7A 65 15 01 45 10
   02 29 46 09 02 47 06 02 03 49 6E 74 05 08 49 15
   FFFFFF84 FFFFFF80 FFFFFF80 FFFFFF80 00 4A 02 05 45 6E 74 72 79 10 04 0A
   4B 23 2F 09 02 4C 02 02 0B 4C 69 6E 6B 65 64 45
   6E 74 72 79 08 07 4E 15 FFFFFFC0 FFFFFF80 FFFFFF84 08 4F 01 0A 66
   69 72 73 74 45 6E 74 72 79 15 01 50 10 02 51 48
   0D 01 15 08 07 53 15 FFFFFFC0 FFFFFF80 FFFFFF84 08 54 01 0E 66 69
   72 73 74 45 6E 74 72 79 5F 24 65 71 14 02 55 58
   10 02 29 56 09 02 57 06 02 04 55 6E 69 74 08 07
   59 52 FFFFFF81 FFFFFF80 FFFFFFC0 00 50 01 03 78 24 31 08 06 5B 15
   FFFFFFA0 FFFFFFA0 04 50 01 0B 66 69 72 73 74 45 6E 74 72 79
   20 28 02 5A 5D 10 02 29 5E 09 02 5F 06 02 09 74
   72 61 6E 73 69 65 6E 74 08 07 61 15 FFFFFFC0 FFFFFF80 FFFFFF84 08
   4F 01 09 6C 61 73 74 45 6E 74 72 79 08 07 63 15
   FFFFFFC0 FFFFFF80 FFFFFF84 08 64 01 0D 6C 61 73 74 45 6E 74 72 79
   5F 24 65 71 14 02 55 65 08 07 59 62 FFFFFF81 FFFFFF80 FFFFFFC0 00
   50 08 06 67 15 FFFFFFA0 FFFFFFA0 04 50 01 0A 6C 61 73 74 45
   6E 74 72 79 20 28 02 66 5D 08 05 6A 15 FFFFFF84 00 6B
   01 03 67 65 74 14 02 6C 6F 10 03 29 6D 2F 09 02
   6E 06 02 06 4F 70 74 69 6F 6E 08 05 70 69 FFFFFFC0 00
   23 01 03 6B 65 79 08 05 72 15 FFFFFF84 20 73 01 03 70
   75 74 14 03 6C 74 75 08 05 70 71 FFFFFFC0 00 23 08 05
   76 71 FFFFFFC0 00 2F 01 05 76 61 6C 75 65 08 05 78 15
   FFFFFF84 04 79 01 13 75 70 64 61 74 65 4C 69 6E 6B 65
   64 45 6E 74 72 69 65 73 14 02 55 7A 08 05 7B 77
   FFFFFFC0 00 50 01 01 65 08 05 7D 15 FFFFFF84 20 7E 01 06 72
   65 6D 6F 76 65 14 02 6C 7F 08 05 70 7C FFFFFFC0 00 23
   08 07 FFFFFF81 01 15 FFFFFF84 00 FFFFFF81 02 01 08 24 70 6C 75 73
   24 65 71 14 03 51 FFFFFF81 03 08 08 FFFFFF81 04 FFFFFF81 00 FFFFFFC0 00
   FFFFFF81 05 01 02 6B 76 10 05 29 FFFFFF81 06 23 2F 09 03 FFFFFF81
   07 06 02 06 54 75 70 6C 65 32 08 07 FFFFFF81 09 15 FFFFFF84
   00 FFFFFF81 0A 01 09 24 6D 69 6E 75 73 24 65 71 14 03
   51 FFFFFF81 0B 08 06 70 FFFFFF81 08 FFFFFFC0 00 23 08 07 FFFFFF81 0D 15
   FFFFFF84 00 FFFFFF81 0E 01 08 69 74 65 72 61 74 6F 72 15 02
   FFFFFF81 0F 10 06 FFFFFF81 10 FFFFFF81 11 FFFFFF81 05 0D 01 04 09 03 FFFFFF81
   12 04 02 08 49 74 65 72 61 74 6F 72 08 07 FFFFFF81 14
   15 FFFFFF84 20 FFFFFF81 15 01 0C 6B 65 79 73 49 74 65 72 61
   74 6F 72 15 02 FFFFFF81 16 10 05 FFFFFF81 10 FFFFFF81 11 23 08 07
   FFFFFF81 18 15 FFFFFF84 20 FFFFFF81 19 01 0E 76 61 6C 75 65 73 49
   74 65 72 61 74 6F 72 15 02 FFFFFF81 1A 10 05 FFFFFF81 10 FFFFFF81
   11 2F 08 07 FFFFFF81 1C 15 FFFFFF84 20 FFFFFF81 1D 01 07 66 6F 72
   65 61 63 68 15 04 FFFFFF81 1E FFFFFF81 25 14 03 55 FFFFFF81 1F 08
   08 FFFFFF81 20 FFFFFF81 1B FFFFFFC0 00 FFFFFF81 21 01 01 66 10 07 29 FFFFFF81
   22 FFFFFF81 05 FFFFFF81 24 09 03 FFFFFF81 23 06 02 09 46 75 6E 63
   74 69 6F 6E 31 10 03 24 FFFFFF81 25 04 0A FFFFFF81 26 FFFFFF81 1B
   FFFFFF84 FFFFFF80 FFFFFF80 FFFFFFC2 00 27 02 01 55 08 07 FFFFFF81 28 15 FFFFFF84 20
   FFFFFF81 29 01 05 63 6C 65 61 72 14 01 55 08 07 FFFFFF81 2B
   15 FFFFFF84 04 FFFFFF81 2C 01 0B 77 72 69 74 65 4F 62 6A 65
   63 74 14 03 55 FFFFFF81 2D 08 08 FFFFFF81 2E FFFFFF81 2A FFFFFFC0 00 FFFFFF81
   2F 01 03 6F 75 74 10 04 FFFFFF81 30 FFFFFF81 33 0D 02 FFFFFF81 31
   0A 03 FFFFFF81 32 1C 01 02 69 6F 09 04 FFFFFF81 34 FFFFFF81 31 02
   12 4F 62 6A 65 63 74 4F 75 74 70 75 74 53 74 72
   65 61 6D 08 07 FFFFFF81 36 15 FFFFFF84 04 FFFFFF81 37 01 0A 72 65
   61 64 4F 62 6A 65 63 74 14 03 55 FFFFFF81 38 08 08 FFFFFF81
   39 FFFFFF81 35 FFFFFFC0 00 FFFFFF81 3A 01 02 69 6E 10 04 FFFFFF81 30 FFFFFF81
   3B 09 04 FFFFFF81 3C FFFFFF81 31 02 11 4F 62 6A 65 63 74 49
   6E 70 75 74 53 74 72 65 61 6D 28 05 15 FFFFFF81 3E FFFFFF81
   41 10 03 29 FFFFFF81 3F 09 03 FFFFFF81 40 06 02 10 53 65 72
   69 61 6C 56 65 72 73 69 6F 6E 55 49 44 1E 01 01
   28 03 15 FFFFFF81 43 10 03 29 FFFFFF81 44 09 03 FFFFFF81 45 06 02
   0C 73 65 72 69 61 6C 69 7A 61 62 6C 65 08 06 3D
   0B FFFFFF84 00 FFFFFF81 47 14 01 09 08 07 FFFFFF81 49 0B FFFFFF84 01 FFFFFF81
   4A 01 0C 63 61 6E 42 75 69 6C 64 46 72 6F 6D 15
   06 FFFFFF81 4B FFFFFF81 56 FFFFFF81 58 10 09 0F FFFFFF81 4C FFFFFF81 4E FFFFFF81 54
   FFFFFF81 59 09 03 FFFFFF81 4D 10 02 0C 43 61 6E 42 75 69 6C
   64 46 72 6F 6D 10 04 FFFFFF81 4F FFFFFF81 50 0D 01 0B 09 04
   FFFFFF81 51 FFFFFF81 52 02 04 43 6F 6C 6C 09 03 FFFFFF81 53 10 02
   0A 4D 61 70 46 61 63 74 6F 72 79 10 07 29 FFFFFF81 06
   FFFFFF81 55 FFFFFF81 57 10 03 24 FFFFFF81 56 04 09 26 FFFFFF81 48 FFFFFF84 FFFFFF80
   FFFFFF80 FFFFFFC2 00 27 10 03 24 FFFFFF81 58 04 09 31 FFFFFF81 48 FFFFFF84 FFFFFF80
   FFFFFF80 FFFFFFC2 00 27 10 06 0A 15 FFFFFF81 55 FFFFFF81 57 08 06 40 0B
   FFFFFF84 00 FFFFFF81 5B 15 06 FFFFFF81 5C FFFFFF81 5E FFFFFF81 60 10 06 0A 15
   FFFFFF81 5D FFFFFF81 5F 10 03 24 FFFFFF81 5E 04 09 26 FFFFFF81 5A FFFFFF84 FFFFFF80
   FFFFFF80 FFFFFFC2 00 27 10 03 24 FFFFFF81 60 04 09 31 FFFFFF81 5A FFFFFF84 FFFFFF80
   FFFFFF80 FFFFFFC2 00 27 
  InnerClass: 
   public final #1027= #320 of #9; //$anon$1=class scala/collection/mutable/LinkedHashMap$$anon$1 of class scala/collection/mutable/LinkedHashMap
   public final #1028= #315 of #9; //$anon$2=class scala/collection/mutable/LinkedHashMap$$anon$2 of class scala/collection/mutable/LinkedHashMap
   public final #1029= #310 of #9; //$anon$3=class scala/collection/mutable/LinkedHashMap$$anon$3 of class scala/collection/mutable/LinkedHashMap
   public #1032= #1031 of #243; //WithFilter=class scala/collection/TraversableLike$WithFilter of class scala/collection/TraversableLike
   public final #1033= #251 of #9; //$anonfun$readObject$1=class scala/collection/mutable/LinkedHashMap$$anonfun$readObject$1 of class scala/collection/mutable/LinkedHashMap
   public final #1034= #266 of #9; //$anonfun$writeObject$1=class scala/collection/mutable/LinkedHashMap$$anonfun$writeObject$1 of class scala/collection/mutable/LinkedHashMap
  minor version: 0
  major version: 49
  Constant pool:
const #1 = Asciz	SourceFile;
const #2 = Asciz	LinkedHashMap.scala;
const #3 = Asciz	<clinit>;
const #4 = Asciz	()V;
const #5 = Asciz	Code;
const #6 = Asciz	serialVersionUID;
const #7 = Asciz	J;
const #8 = Asciz	scala/collection/mutable/LinkedHashMap;
const #9 = class	#8;	//  scala/collection/mutable/LinkedHashMap
const #10 = NameAndType	#6:#7;//  serialVersionUID:J
const #11 = Field	#9.#10;	//  scala/collection/mutable/LinkedHashMap.serialVersionUID:J
const #12 = Asciz	threshold;
const #13 = Asciz	I;
const #14 = Asciz	tableSize;
const #15 = Asciz	table;
const #16 = Asciz	[Lscala/collection/mutable/HashEntry;;
const #17 = Asciz	_loadFactor;
const #18 = Asciz	lastEntry;
const #19 = Asciz	Lscala/collection/mutable/LinkedEntry;;
const #20 = Asciz	Lscala/collection/mutable/LinkedEntry<TA;TB;>;;
const #21 = Asciz	Signature;
const #22 = Asciz	firstEntry;
const #23 = Asciz	<init>;
const #24 = Asciz	LineNumberTable;
const #25 = Asciz	java/lang/Object;
const #26 = class	#25;	//  java/lang/Object
const #27 = NameAndType	#23:#4;//  "<init>":()V
const #28 = Method	#26.#27;	//  java/lang/Object."<init>":()V
const #29 = Asciz	scala/collection/TraversableLike$class;
const #30 = class	#29;	//  scala/collection/TraversableLike$class
const #31 = Asciz	$init$;
const #32 = Asciz	(Lscala/collection/TraversableLike;)V;
const #33 = NameAndType	#31:#32;//  $init$:(Lscala/collection/TraversableLike;)V
const #34 = Method	#30.#33;	//  scala/collection/TraversableLike$class.$init$:(Lscala/collection/TraversableLike;)V
const #35 = Asciz	scala/collection/generic/GenericTraversableTemplate$class;
const #36 = class	#35;	//  scala/collection/generic/GenericTraversableTemplate$class
const #37 = Asciz	(Lscala/collection/generic/GenericTraversableTemplate;)V;
const #38 = NameAndType	#31:#37;//  $init$:(Lscala/collection/generic/GenericTraversableTemplate;)V
const #39 = Method	#36.#38;	//  scala/collection/generic/GenericTraversableTemplate$class.$init$:(Lscala/collection/generic/GenericTraversableTemplate;)V
const #40 = Asciz	scala/collection/Traversable$class;
const #41 = class	#40;	//  scala/collection/Traversable$class
const #42 = Asciz	(Lscala/collection/Traversable;)V;
const #43 = NameAndType	#31:#42;//  $init$:(Lscala/collection/Traversable;)V
const #44 = Method	#41.#43;	//  scala/collection/Traversable$class.$init$:(Lscala/collection/Traversable;)V
const #45 = Asciz	scala/collection/mutable/Traversable$class;
const #46 = class	#45;	//  scala/collection/mutable/Traversable$class
const #47 = Asciz	(Lscala/collection/mutable/Traversable;)V;
const #48 = NameAndType	#31:#47;//  $init$:(Lscala/collection/mutable/Traversable;)V
const #49 = Method	#46.#48;	//  scala/collection/mutable/Traversable$class.$init$:(Lscala/collection/mutable/Traversable;)V
const #50 = Asciz	scala/collection/IterableLike$class;
const #51 = class	#50;	//  scala/collection/IterableLike$class
const #52 = Asciz	(Lscala/collection/IterableLike;)V;
const #53 = NameAndType	#31:#52;//  $init$:(Lscala/collection/IterableLike;)V
const #54 = Method	#51.#53;	//  scala/collection/IterableLike$class.$init$:(Lscala/collection/IterableLike;)V
const #55 = Asciz	scala/collection/Iterable$class;
const #56 = class	#55;	//  scala/collection/Iterable$class
const #57 = Asciz	(Lscala/collection/Iterable;)V;
const #58 = NameAndType	#31:#57;//  $init$:(Lscala/collection/Iterable;)V
const #59 = Method	#56.#58;	//  scala/collection/Iterable$class.$init$:(Lscala/collection/Iterable;)V
const #60 = Asciz	scala/collection/mutable/Iterable$class;
const #61 = class	#60;	//  scala/collection/mutable/Iterable$class
const #62 = Asciz	(Lscala/collection/mutable/Iterable;)V;
const #63 = NameAndType	#31:#62;//  $init$:(Lscala/collection/mutable/Iterable;)V
const #64 = Method	#61.#63;	//  scala/collection/mutable/Iterable$class.$init$:(Lscala/collection/mutable/Iterable;)V
const #65 = Asciz	scala/Function1$class;
const #66 = class	#65;	//  scala/Function1$class
const #67 = Asciz	(Lscala/Function1;)V;
const #68 = NameAndType	#31:#67;//  $init$:(Lscala/Function1;)V
const #69 = Method	#66.#68;	//  scala/Function1$class.$init$:(Lscala/Function1;)V
const #70 = Asciz	scala/PartialFunction$class;
const #71 = class	#70;	//  scala/PartialFunction$class
const #72 = Asciz	(Lscala/PartialFunction;)V;
const #73 = NameAndType	#31:#72;//  $init$:(Lscala/PartialFunction;)V
const #74 = Method	#71.#73;	//  scala/PartialFunction$class.$init$:(Lscala/PartialFunction;)V
const #75 = Asciz	scala/collection/generic/Subtractable$class;
const #76 = class	#75;	//  scala/collection/generic/Subtractable$class
const #77 = Asciz	(Lscala/collection/generic/Subtractable;)V;
const #78 = NameAndType	#31:#77;//  $init$:(Lscala/collection/generic/Subtractable;)V
const #79 = Method	#76.#78;	//  scala/collection/generic/Subtractable$class.$init$:(Lscala/collection/generic/Subtractable;)V
const #80 = Asciz	scala/collection/MapLike$class;
const #81 = class	#80;	//  scala/collection/MapLike$class
const #82 = Asciz	(Lscala/collection/MapLike;)V;
const #83 = NameAndType	#31:#82;//  $init$:(Lscala/collection/MapLike;)V
const #84 = Method	#81.#83;	//  scala/collection/MapLike$class.$init$:(Lscala/collection/MapLike;)V
const #85 = Asciz	scala/collection/Map$class;
const #86 = class	#85;	//  scala/collection/Map$class
const #87 = Asciz	(Lscala/collection/Map;)V;
const #88 = NameAndType	#31:#87;//  $init$:(Lscala/collection/Map;)V
const #89 = Method	#86.#88;	//  scala/collection/Map$class.$init$:(Lscala/collection/Map;)V
const #90 = Asciz	scala/collection/mutable/Cloneable$class;
const #91 = class	#90;	//  scala/collection/mutable/Cloneable$class
const #92 = Asciz	(Lscala/collection/mutable/Cloneable;)V;
const #93 = NameAndType	#31:#92;//  $init$:(Lscala/collection/mutable/Cloneable;)V
const #94 = Method	#91.#93;	//  scala/collection/mutable/Cloneable$class.$init$:(Lscala/collection/mutable/Cloneable;)V
const #95 = Asciz	scala/collection/mutable/MapLikeBase$class;
const #96 = class	#95;	//  scala/collection/mutable/MapLikeBase$class
const #97 = Asciz	(Lscala/collection/mutable/MapLikeBase;)V;
const #98 = NameAndType	#31:#97;//  $init$:(Lscala/collection/mutable/MapLikeBase;)V
const #99 = Method	#96.#98;	//  scala/collection/mutable/MapLikeBase$class.$init$:(Lscala/collection/mutable/MapLikeBase;)V
const #100 = Asciz	scala/collection/generic/Growable$class;
const #101 = class	#100;	//  scala/collection/generic/Growable$class
const #102 = Asciz	(Lscala/collection/generic/Growable;)V;
const #103 = NameAndType	#31:#102;//  $init$:(Lscala/collection/generic/Growable;)V
const #104 = Method	#101.#103;	//  scala/collection/generic/Growable$class.$init$:(Lscala/collection/generic/Growable;)V
const #105 = Asciz	scala/collection/mutable/Builder$class;
const #106 = class	#105;	//  scala/collection/mutable/Builder$class
const #107 = Asciz	(Lscala/collection/mutable/Builder;)V;
const #108 = NameAndType	#31:#107;//  $init$:(Lscala/collection/mutable/Builder;)V
const #109 = Method	#106.#108;	//  scala/collection/mutable/Builder$class.$init$:(Lscala/collection/mutable/Builder;)V
const #110 = Asciz	scala/collection/generic/Shrinkable$class;
const #111 = class	#110;	//  scala/collection/generic/Shrinkable$class
const #112 = Asciz	(Lscala/collection/generic/Shrinkable;)V;
const #113 = NameAndType	#31:#112;//  $init$:(Lscala/collection/generic/Shrinkable;)V
const #114 = Method	#111.#113;	//  scala/collection/generic/Shrinkable$class.$init$:(Lscala/collection/generic/Shrinkable;)V
const #115 = Asciz	scala/collection/mutable/MapLike$class;
const #116 = class	#115;	//  scala/collection/mutable/MapLike$class
const #117 = Asciz	(Lscala/collection/mutable/MapLike;)V;
const #118 = NameAndType	#31:#117;//  $init$:(Lscala/collection/mutable/MapLike;)V
const #119 = Method	#116.#118;	//  scala/collection/mutable/MapLike$class.$init$:(Lscala/collection/mutable/MapLike;)V
const #120 = Asciz	scala/collection/mutable/Map$class;
const #121 = class	#120;	//  scala/collection/mutable/Map$class
const #122 = Asciz	(Lscala/collection/mutable/Map;)V;
const #123 = NameAndType	#31:#122;//  $init$:(Lscala/collection/mutable/Map;)V
const #124 = Method	#121.#123;	//  scala/collection/mutable/Map$class.$init$:(Lscala/collection/mutable/Map;)V
const #125 = Asciz	scala/collection/mutable/HashTable$class;
const #126 = class	#125;	//  scala/collection/mutable/HashTable$class
const #127 = Asciz	(Lscala/collection/mutable/HashTable;)V;
const #128 = NameAndType	#31:#127;//  $init$:(Lscala/collection/mutable/HashTable;)V
const #129 = Method	#126.#128;	//  scala/collection/mutable/HashTable$class.$init$:(Lscala/collection/mutable/HashTable;)V
const #130 = NameAndType	#22:#19;//  firstEntry:Lscala/collection/mutable/LinkedEntry;
const #131 = Field	#9.#130;	//  scala/collection/mutable/LinkedHashMap.firstEntry:Lscala/collection/mutable/LinkedEntry;
const #132 = NameAndType	#18:#19;//  lastEntry:Lscala/collection/mutable/LinkedEntry;
const #133 = Field	#9.#132;	//  scala/collection/mutable/LinkedHashMap.lastEntry:Lscala/collection/mutable/LinkedEntry;
const #134 = Asciz	empty;
const #135 = Asciz	()Lscala/collection/mutable/Map;;
const #136 = Asciz	()Lscala/collection/mutable/LinkedHashMap;;
const #137 = NameAndType	#134:#136;//  empty:()Lscala/collection/mutable/LinkedHashMap;
const #138 = Method	#9.#137;	//  scala/collection/mutable/LinkedHashMap.empty:()Lscala/collection/mutable/LinkedHashMap;
const #139 = Asciz	()Lscala/collection/Map;;
const #140 = Asciz	()Lscala/collection/MapLike;;
const #141 = Asciz	$plus$eq;
const #142 = Asciz	(Lscala/Tuple2;)Lscala/collection/mutable/MapLike;;
const #143 = Asciz	(Lscala/Tuple2;)Lscala/collection/mutable/LinkedHashMap;;
const #144 = NameAndType	#141:#143;//  $plus$eq:(Lscala/Tuple2;)Lscala/collection/mutable/LinkedHashMap;
const #145 = Method	#9.#144;	//  scala/collection/mutable/LinkedHashMap.$plus$eq:(Lscala/Tuple2;)Lscala/collection/mutable/LinkedHashMap;
const #146 = Asciz	this;
const #147 = Asciz	Lscala/collection/mutable/LinkedHashMap;;
const #148 = Asciz	kv;
const #149 = Asciz	Lscala/Tuple2;;
const #150 = Asciz	LocalVariableTable;
const #151 = Asciz	(Ljava/lang/Object;)Lscala/collection/mutable/Builder;;
const #152 = Asciz	scala/Tuple2;
const #153 = class	#152;	//  scala/Tuple2
const #154 = Asciz	elem;
const #155 = Asciz	Ljava/lang/Object;;
const #156 = Asciz	(Ljava/lang/Object;)Lscala/collection/generic/Growable;;
const #157 = Asciz	$minus$eq;
const #158 = Asciz	(Ljava/lang/Object;)Lscala/collection/mutable/MapLike;;
const #159 = Asciz	(Ljava/lang/Object;)Lscala/collection/mutable/LinkedHashMap;;
const #160 = NameAndType	#157:#159;//  $minus$eq:(Ljava/lang/Object;)Lscala/collection/mutable/LinkedHashMap;
const #161 = Method	#9.#160;	//  scala/collection/mutable/LinkedHashMap.$minus$eq:(Ljava/lang/Object;)Lscala/collection/mutable/LinkedHashMap;
const #162 = Asciz	key;
const #163 = Asciz	(Ljava/lang/Object;)Lscala/collection/generic/Shrinkable;;
const #164 = Asciz	updated;
const #165 = Asciz	(Ljava/lang/Object;Ljava/lang/Object;)Lscala/collection/Map;;
const #166 = Asciz	scala/collection/mutable/MapLike;
const #167 = class	#166;	//  scala/collection/mutable/MapLike
const #168 = Asciz	(Ljava/lang/Object;Ljava/lang/Object;)Lscala/collection/mutable/Map;;
const #169 = NameAndType	#164:#168;//  updated:(Ljava/lang/Object;Ljava/lang/Object;)Lscala/collection/mutable/Map;
const #170 = InterfaceMethod	#167.#169;	//  scala/collection/mutable/MapLike.updated:(Ljava/lang/Object;Ljava/lang/Object;)Lscala/collection/mutable/Map;
const #171 = Asciz	value;
const #172 = Asciz	$minus;
const #173 = Asciz	(Ljava/lang/Object;)Lscala/collection/MapLike;;
const #174 = NameAndType	#172:#158;//  $minus:(Ljava/lang/Object;)Lscala/collection/mutable/MapLike;
const #175 = InterfaceMethod	#167.#174;	//  scala/collection/mutable/MapLike.$minus:(Ljava/lang/Object;)Lscala/collection/mutable/MapLike;
const #176 = Asciz	(Ljava/lang/Object;)Lscala/collection/generic/Subtractable;;
const #177 = Asciz	clone;
const #178 = Asciz	()Ljava/lang/Object;;
const #179 = Asciz	()Lscala/collection/mutable/MapLike;;
const #180 = NameAndType	#177:#179;//  clone:()Lscala/collection/mutable/MapLike;
const #181 = InterfaceMethod	#167.#180;	//  scala/collection/mutable/MapLike.clone:()Lscala/collection/mutable/MapLike;
const #182 = Asciz	result;
const #183 = NameAndType	#182:#179;//  result:()Lscala/collection/mutable/MapLike;
const #184 = InterfaceMethod	#167.#183;	//  scala/collection/mutable/MapLike.result:()Lscala/collection/mutable/MapLike;
const #185 = Asciz	(Ljava/lang/Object;Ljava/lang/Object;Lscala/collection/Seq;)Lscala/collection/generic/Subtractable;;
const #186 = Asciz	(Ljava/lang/Object;Ljava/lang/Object;Lscala/collection/Seq;)Lscala/collection/mutable/MapLike;;
const #187 = NameAndType	#172:#186;//  $minus:(Ljava/lang/Object;Ljava/lang/Object;Lscala/collection/Seq;)Lscala/collection/mutable/MapLike;
const #188 = InterfaceMethod	#167.#187;	//  scala/collection/mutable/MapLike.$minus:(Ljava/lang/Object;Ljava/lang/Object;Lscala/collection/Seq;)Lscala/collection/mutable/MapLike;
const #189 = Asciz	elem1;
const #190 = Asciz	elem2;
const #191 = Asciz	elems;
const #192 = Asciz	Lscala/collection/Seq;;
const #193 = Asciz	$minus$minus;
const #194 = Asciz	(Lscala/collection/Traversable;)Lscala/collection/generic/Subtractable;;
const #195 = Asciz	(Lscala/collection/Traversable;)Lscala/collection/mutable/MapLike;;
const #196 = NameAndType	#193:#195;//  $minus$minus:(Lscala/collection/Traversable;)Lscala/collection/mutable/MapLike;
const #197 = InterfaceMethod	#167.#196;	//  scala/collection/mutable/MapLike.$minus$minus:(Lscala/collection/Traversable;)Lscala/collection/mutable/MapLike;
const #198 = Asciz	Lscala/collection/Traversable;;
const #199 = Asciz	(Lscala/collection/Iterator;)Lscala/collection/generic/Subtractable;;
const #200 = Asciz	(Lscala/collection/Iterator;)Lscala/collection/mutable/MapLike;;
const #201 = NameAndType	#193:#200;//  $minus$minus:(Lscala/collection/Iterator;)Lscala/collection/mutable/MapLike;
const #202 = InterfaceMethod	#167.#201;	//  scala/collection/mutable/MapLike.$minus$minus:(Lscala/collection/Iterator;)Lscala/collection/mutable/MapLike;
const #203 = Asciz	iter;
const #204 = Asciz	Lscala/collection/Iterator;;
const #205 = Asciz	$plus;
const #206 = Asciz	(Lscala/Tuple2;)Lscala/collection/Map;;
const #207 = Asciz	scala/collection/mutable/MapLikeBase;
const #208 = class	#207;	//  scala/collection/mutable/MapLikeBase
const #209 = Asciz	(Lscala/Tuple2;)Lscala/collection/mutable/Map;;
const #210 = NameAndType	#205:#209;//  $plus:(Lscala/Tuple2;)Lscala/collection/mutable/Map;
const #211 = InterfaceMethod	#208.#210;	//  scala/collection/mutable/MapLikeBase.$plus:(Lscala/Tuple2;)Lscala/collection/mutable/Map;
const #212 = Asciz	andThen;
const #213 = Asciz	(Lscala/Function1;)Lscala/Function1;;
const #214 = Asciz	scala/PartialFunction;
const #215 = class	#214;	//  scala/PartialFunction
const #216 = Asciz	(Lscala/Function1;)Lscala/PartialFunction;;
const #217 = NameAndType	#212:#216;//  andThen:(Lscala/Function1;)Lscala/PartialFunction;
const #218 = InterfaceMethod	#215.#217;	//  scala/PartialFunction.andThen:(Lscala/Function1;)Lscala/PartialFunction;
const #219 = Asciz	g;
const #220 = Asciz	Lscala/Function1;;
const #221 = Asciz	thisCollection;
const #222 = Asciz	()Lscala/collection/Traversable;;
const #223 = Asciz	scala/collection/IterableLike;
const #224 = class	#223;	//  scala/collection/IterableLike
const #225 = Asciz	()Lscala/collection/Iterable;;
const #226 = NameAndType	#221:#225;//  thisCollection:()Lscala/collection/Iterable;
const #227 = InterfaceMethod	#224.#226;	//  scala/collection/IterableLike.thisCollection:()Lscala/collection/Iterable;
const #228 = Asciz	toCollection;
const #229 = Asciz	(Ljava/lang/Object;)Lscala/collection/Traversable;;
const #230 = Asciz	(Ljava/lang/Object;)Lscala/collection/Iterable;;
const #231 = NameAndType	#228:#230;//  toCollection:(Ljava/lang/Object;)Lscala/collection/Iterable;
const #232 = InterfaceMethod	#224.#231;	//  scala/collection/IterableLike.toCollection:(Ljava/lang/Object;)Lscala/collection/Iterable;
const #233 = Asciz	repr;
const #234 = Asciz	view;
const #235 = Asciz	(II)Lscala/collection/TraversableView;;
const #236 = Asciz	(II)Lscala/collection/IterableView;;
const #237 = NameAndType	#234:#236;//  view:(II)Lscala/collection/IterableView;
const #238 = InterfaceMethod	#224.#237;	//  scala/collection/IterableLike.view:(II)Lscala/collection/IterableView;
const #239 = Asciz	from;
const #240 = Asciz	until;
const #241 = Asciz	()Lscala/collection/generic/Subtractable;;
const #242 = Asciz	scala/collection/TraversableLike;
const #243 = class	#242;	//  scala/collection/TraversableLike
const #244 = NameAndType	#233:#178;//  repr:()Ljava/lang/Object;
const #245 = InterfaceMethod	#243.#244;	//  scala/collection/TraversableLike.repr:()Ljava/lang/Object;
const #246 = Asciz	scala/collection/generic/Subtractable;
const #247 = class	#246;	//  scala/collection/generic/Subtractable
const #248 = Asciz	readObject;
const #249 = Asciz	(Ljava/io/ObjectInputStream;)V;
const #250 = Asciz	scala/collection/mutable/LinkedHashMap$$anonfun$readObject$1;
const #251 = class	#250;	//  scala/collection/mutable/LinkedHashMap$$anonfun$readObject$1
const #252 = Asciz	(Lscala/collection/mutable/LinkedHashMap;)V;
const #253 = NameAndType	#23:#252;//  "<init>":(Lscala/collection/mutable/LinkedHashMap;)V
const #254 = Method	#251.#253;	//  scala/collection/mutable/LinkedHashMap$$anonfun$readObject$1."<init>":(Lscala/collection/mutable/LinkedHashMap;)V
const #255 = Asciz	scala/collection/mutable/HashTable;
const #256 = class	#255;	//  scala/collection/mutable/HashTable
const #257 = Asciz	init;
const #258 = Asciz	(Ljava/io/ObjectInputStream;Lscala/Function2;)V;
const #259 = NameAndType	#257:#258;//  init:(Ljava/io/ObjectInputStream;Lscala/Function2;)V
const #260 = InterfaceMethod	#256.#259;	//  scala/collection/mutable/HashTable.init:(Ljava/io/ObjectInputStream;Lscala/Function2;)V
const #261 = Asciz	in;
const #262 = Asciz	Ljava/io/ObjectInputStream;;
const #263 = Asciz	writeObject;
const #264 = Asciz	(Ljava/io/ObjectOutputStream;)V;
const #265 = Asciz	scala/collection/mutable/LinkedHashMap$$anonfun$writeObject$1;
const #266 = class	#265;	//  scala/collection/mutable/LinkedHashMap$$anonfun$writeObject$1
const #267 = Method	#266.#253;	//  scala/collection/mutable/LinkedHashMap$$anonfun$writeObject$1."<init>":(Lscala/collection/mutable/LinkedHashMap;)V
const #268 = Asciz	serializeTo;
const #269 = Asciz	(Ljava/io/ObjectOutputStream;Lscala/Function1;)V;
const #270 = NameAndType	#268:#269;//  serializeTo:(Ljava/io/ObjectOutputStream;Lscala/Function1;)V
const #271 = InterfaceMethod	#256.#270;	//  scala/collection/mutable/HashTable.serializeTo:(Ljava/io/ObjectOutputStream;Lscala/Function1;)V
const #272 = Asciz	out;
const #273 = Asciz	Ljava/io/ObjectOutputStream;;
const #274 = Asciz	clear;
const #275 = Asciz	clearTable;
const #276 = NameAndType	#275:#4;//  clearTable:()V
const #277 = InterfaceMethod	#256.#276;	//  scala/collection/mutable/HashTable.clearTable:()V
const #278 = Asciz	firstEntry_$eq;
const #279 = Asciz	(Lscala/collection/mutable/LinkedEntry;)V;
const #280 = NameAndType	#278:#279;//  firstEntry_$eq:(Lscala/collection/mutable/LinkedEntry;)V
const #281 = Method	#9.#280;	//  scala/collection/mutable/LinkedHashMap.firstEntry_$eq:(Lscala/collection/mutable/LinkedEntry;)V
const #282 = Asciz	foreach;
const #283 = Asciz	()Lscala/collection/mutable/LinkedEntry;;
const #284 = NameAndType	#22:#283;//  firstEntry:()Lscala/collection/mutable/LinkedEntry;
const #285 = Method	#9.#284;	//  scala/collection/mutable/LinkedHashMap.firstEntry:()Lscala/collection/mutable/LinkedEntry;
const #286 = Asciz	scala/collection/mutable/LinkedEntry;
const #287 = class	#286;	//  scala/collection/mutable/LinkedEntry
const #288 = NameAndType	#162:#155;//  key:Ljava/lang/Object;
const #289 = Field	#287.#288;	//  scala/collection/mutable/LinkedEntry.key:Ljava/lang/Object;
const #290 = NameAndType	#171:#155;//  value:Ljava/lang/Object;
const #291 = Field	#287.#290;	//  scala/collection/mutable/LinkedEntry.value:Ljava/lang/Object;
const #292 = Asciz	(Ljava/lang/Object;Ljava/lang/Object;)V;
const #293 = NameAndType	#23:#292;//  "<init>":(Ljava/lang/Object;Ljava/lang/Object;)V
const #294 = Method	#153.#293;	//  scala/Tuple2."<init>":(Ljava/lang/Object;Ljava/lang/Object;)V
const #295 = Asciz	scala/Function1;
const #296 = class	#295;	//  scala/Function1
const #297 = Asciz	apply;
const #298 = Asciz	(Ljava/lang/Object;)Ljava/lang/Object;;
const #299 = NameAndType	#297:#298;//  apply:(Ljava/lang/Object;)Ljava/lang/Object;
const #300 = InterfaceMethod	#296.#299;	//  scala/Function1.apply:(Ljava/lang/Object;)Ljava/lang/Object;
const #301 = Asciz	later;
const #302 = NameAndType	#301:#283;//  later:()Lscala/collection/mutable/LinkedEntry;
const #303 = Method	#287.#302;	//  scala/collection/mutable/LinkedEntry.later:()Lscala/collection/mutable/LinkedEntry;
const #304 = Asciz	f;
const #305 = Asciz	cur;
const #306 = Asciz	<U:Ljava/lang/Object;>(Lscala/Function1<Lscala/Tuple2<TA;TB;>;TU;>;)V;
const #307 = Asciz	valuesIterator;
const #308 = Asciz	()Lscala/collection/Iterator;;
const #309 = Asciz	scala/collection/mutable/LinkedHashMap$$anon$3;
const #310 = class	#309;	//  scala/collection/mutable/LinkedHashMap$$anon$3
const #311 = Method	#310.#253;	//  scala/collection/mutable/LinkedHashMap$$anon$3."<init>":(Lscala/collection/mutable/LinkedHashMap;)V
const #312 = Asciz	()Lscala/collection/Iterator<TB;>;;
const #313 = Asciz	keysIterator;
const #314 = Asciz	scala/collection/mutable/LinkedHashMap$$anon$2;
const #315 = class	#314;	//  scala/collection/mutable/LinkedHashMap$$anon$2
const #316 = Method	#315.#253;	//  scala/collection/mutable/LinkedHashMap$$anon$2."<init>":(Lscala/collection/mutable/LinkedHashMap;)V
const #317 = Asciz	()Lscala/collection/Iterator<TA;>;;
const #318 = Asciz	iterator;
const #319 = Asciz	scala/collection/mutable/LinkedHashMap$$anon$1;
const #320 = class	#319;	//  scala/collection/mutable/LinkedHashMap$$anon$1
const #321 = Method	#320.#253;	//  scala/collection/mutable/LinkedHashMap$$anon$1."<init>":(Lscala/collection/mutable/LinkedHashMap;)V
const #322 = Asciz	()Lscala/collection/Iterator<Lscala/Tuple2<TA;TB;>;>;;
const #323 = Asciz	remove;
const #324 = Asciz	(Ljava/lang/Object;)Lscala/Option;;
const #325 = NameAndType	#323:#324;//  remove:(Ljava/lang/Object;)Lscala/Option;
const #326 = Method	#9.#325;	//  scala/collection/mutable/LinkedHashMap.remove:(Ljava/lang/Object;)Lscala/Option;
const #327 = Asciz	(TA;)Lscala/collection/mutable/LinkedHashMap<TA;TB;>;;
const #328 = Asciz	_1;
const #329 = NameAndType	#328:#178;//  _1:()Ljava/lang/Object;
const #330 = Method	#153.#329;	//  scala/Tuple2._1:()Ljava/lang/Object;
const #331 = Asciz	_2;
const #332 = NameAndType	#331:#178;//  _2:()Ljava/lang/Object;
const #333 = Method	#153.#332;	//  scala/Tuple2._2:()Ljava/lang/Object;
const #334 = Asciz	put;
const #335 = Asciz	(Ljava/lang/Object;Ljava/lang/Object;)Lscala/Option;;
const #336 = NameAndType	#334:#335;//  put:(Ljava/lang/Object;Ljava/lang/Object;)Lscala/Option;
const #337 = Method	#9.#336;	//  scala/collection/mutable/LinkedHashMap.put:(Ljava/lang/Object;Ljava/lang/Object;)Lscala/Option;
const #338 = Asciz	(Lscala/Tuple2<TA;TB;>;)Lscala/collection/mutable/LinkedHashMap<TA;TB;>;;
const #339 = Asciz	removeEntry;
const #340 = Asciz	(Ljava/lang/Object;)Lscala/collection/mutable/HashEntry;;
const #341 = NameAndType	#339:#340;//  removeEntry:(Ljava/lang/Object;)Lscala/collection/mutable/HashEntry;
const #342 = InterfaceMethod	#256.#341;	//  scala/collection/mutable/HashTable.removeEntry:(Ljava/lang/Object;)Lscala/collection/mutable/HashEntry;
const #343 = Asciz	scala/None$;
const #344 = class	#343;	//  scala/None$
const #345 = Asciz	MODULE$;
const #346 = Asciz	Lscala/None$;;
const #347 = NameAndType	#345:#346;//  MODULE$:Lscala/None$;
const #348 = Field	#344.#347;	//  scala/None$.MODULE$:Lscala/None$;
const #349 = Asciz	earlier;
const #350 = NameAndType	#349:#283;//  earlier:()Lscala/collection/mutable/LinkedEntry;
const #351 = Method	#287.#350;	//  scala/collection/mutable/LinkedEntry.earlier:()Lscala/collection/mutable/LinkedEntry;
const #352 = Asciz	later_$eq;
const #353 = NameAndType	#352:#279;//  later_$eq:(Lscala/collection/mutable/LinkedEntry;)V
const #354 = Method	#287.#353;	//  scala/collection/mutable/LinkedEntry.later_$eq:(Lscala/collection/mutable/LinkedEntry;)V
const #355 = Asciz	lastEntry_$eq;
const #356 = NameAndType	#355:#279;//  lastEntry_$eq:(Lscala/collection/mutable/LinkedEntry;)V
const #357 = Method	#9.#356;	//  scala/collection/mutable/LinkedHashMap.lastEntry_$eq:(Lscala/collection/mutable/LinkedEntry;)V
const #358 = Asciz	earlier_$eq;
const #359 = NameAndType	#358:#279;//  earlier_$eq:(Lscala/collection/mutable/LinkedEntry;)V
const #360 = Method	#287.#359;	//  scala/collection/mutable/LinkedEntry.earlier_$eq:(Lscala/collection/mutable/LinkedEntry;)V
const #361 = Asciz	scala/Some;
const #362 = class	#361;	//  scala/Some
const #363 = Asciz	(Ljava/lang/Object;)V;
const #364 = NameAndType	#23:#363;//  "<init>":(Ljava/lang/Object;)V
const #365 = Method	#362.#364;	//  scala/Some."<init>":(Ljava/lang/Object;)V
const #366 = Asciz	e;
const #367 = Asciz	(TA;)Lscala/Option<TB;>;;
const #368 = Asciz	scala$collection$mutable$LinkedHashMap$$updateLinkedEntries;
const #369 = Asciz	equals;
const #370 = Asciz	(Ljava/lang/Object;)Z;
const #371 = NameAndType	#369:#370;//  equals:(Ljava/lang/Object;)Z
const #372 = Method	#26.#371;	//  java/lang/Object.equals:(Ljava/lang/Object;)Z
const #373 = NameAndType	#18:#283;//  lastEntry:()Lscala/collection/mutable/LinkedEntry;
const #374 = Method	#9.#373;	//  scala/collection/mutable/LinkedHashMap.lastEntry:()Lscala/collection/mutable/LinkedEntry;
const #375 = Asciz	findEntry;
const #376 = NameAndType	#375:#340;//  findEntry:(Ljava/lang/Object;)Lscala/collection/mutable/HashEntry;
const #377 = InterfaceMethod	#256.#376;	//  scala/collection/mutable/HashTable.findEntry:(Ljava/lang/Object;)Lscala/collection/mutable/HashEntry;
const #378 = Method	#287.#293;	//  scala/collection/mutable/LinkedEntry."<init>":(Ljava/lang/Object;Ljava/lang/Object;)V
const #379 = Asciz	addEntry;
const #380 = Asciz	(Lscala/collection/mutable/HashEntry;)V;
const #381 = NameAndType	#379:#380;//  addEntry:(Lscala/collection/mutable/HashEntry;)V
const #382 = InterfaceMethod	#256.#381;	//  scala/collection/mutable/HashTable.addEntry:(Lscala/collection/mutable/HashEntry;)V
const #383 = NameAndType	#368:#279;//  scala$collection$mutable$LinkedHashMap$$updateLinkedEntries:(Lscala/collection/mutable/LinkedEntry;)V
const #384 = Method	#9.#383;	//  scala/collection/mutable/LinkedHashMap.scala$collection$mutable$LinkedHashMap$$updateLinkedEntries:(Lscala/collection/mutable/LinkedEntry;)V
const #385 = Asciz	v;
const #386 = Asciz	(TA;TB;)Lscala/Option<TB;>;;
const #387 = Asciz	get;
const #388 = Asciz	(Lscala/collection/mutable/LinkedEntry<TA;TB;>;)V;
const #389 = Asciz	()Lscala/collection/mutable/LinkedEntry<TA;TB;>;;
const #390 = Asciz	size;
const #391 = Asciz	()I;
const #392 = NameAndType	#14:#391;//  tableSize:()I
const #393 = InterfaceMethod	#256.#392;	//  scala/collection/mutable/HashTable.tableSize:()I
const #394 = Asciz	scala/collection/mutable/LinkedHashMap$;
const #395 = class	#394;	//  scala/collection/mutable/LinkedHashMap$
const #396 = Asciz	Lscala/collection/mutable/LinkedHashMap$;;
const #397 = NameAndType	#345:#396;//  MODULE$:Lscala/collection/mutable/LinkedHashMap$;
const #398 = Field	#395.#397;	//  scala/collection/mutable/LinkedHashMap$.MODULE$:Lscala/collection/mutable/LinkedHashMap$;
const #399 = Method	#395.#137;	//  scala/collection/mutable/LinkedHashMap$.empty:()Lscala/collection/mutable/LinkedHashMap;
const #400 = Asciz	()Lscala/collection/mutable/LinkedHashMap<TA;TB;>;;
const #401 = Asciz	withFilter;
const #402 = Asciz	(Lscala/Function1;)Lscala/collection/TraversableLike$WithFilter;;
const #403 = Asciz	(Lscala/collection/TraversableLike;Lscala/Function1;)Lscala/collection/TraversableLike$WithFilter;;
const #404 = NameAndType	#401:#403;//  withFilter:(Lscala/collection/TraversableLike;Lscala/Function1;)Lscala/collection/TraversableLike$WithFilter;
const #405 = Method	#30.#404;	//  scala/collection/TraversableLike$class.withFilter:(Lscala/collection/TraversableLike;Lscala/Function1;)Lscala/collection/TraversableLike$WithFilter;
const #406 = Asciz	p;
const #407 = Asciz	addString;
const #408 = Asciz	(Lscala/collection/mutable/StringBuilder;)Lscala/collection/mutable/StringBuilder;;
const #409 = Asciz	(Lscala/collection/TraversableLike;Lscala/collection/mutable/StringBuilder;)Lscala/collection/mutable/StringBuilder;;
const #410 = NameAndType	#407:#409;//  addString:(Lscala/collection/TraversableLike;Lscala/collection/mutable/StringBuilder;)Lscala/collection/mutable/StringBuilder;
const #411 = Method	#30.#410;	//  scala/collection/TraversableLike$class.addString:(Lscala/collection/TraversableLike;Lscala/collection/mutable/StringBuilder;)Lscala/collection/mutable/StringBuilder;
const #412 = Asciz	b;
const #413 = Asciz	Lscala/collection/mutable/StringBuilder;;
const #414 = Asciz	(Lscala/collection/mutable/StringBuilder;Ljava/lang/String;)Lscala/collection/mutable/StringBuilder;;
const #415 = Asciz	(Lscala/collection/TraversableLike;Lscala/collection/mutable/StringBuilder;Ljava/lang/String;)Lscala/collection/mutable/StringBuilder;;
const #416 = NameAndType	#407:#415;//  addString:(Lscala/collection/TraversableLike;Lscala/collection/mutable/StringBuilder;Ljava/lang/String;)Lscala/collection/mutable/StringBuilder;
const #417 = Method	#30.#416;	//  scala/collection/TraversableLike$class.addString:(Lscala/collection/TraversableLike;Lscala/collection/mutable/StringBuilder;Ljava/lang/String;)Lscala/collection/mutable/StringBuilder;
const #418 = Asciz	sep;
const #419 = Asciz	Ljava/lang/String;;
const #420 = Asciz	mkString;
const #421 = Asciz	()Ljava/lang/String;;
const #422 = Asciz	(Lscala/collection/TraversableLike;)Ljava/lang/String;;
const #423 = NameAndType	#420:#422;//  mkString:(Lscala/collection/TraversableLike;)Ljava/lang/String;
const #424 = Method	#30.#423;	//  scala/collection/TraversableLike$class.mkString:(Lscala/collection/TraversableLike;)Ljava/lang/String;
const #425 = Asciz	(Ljava/lang/String;)Ljava/lang/String;;
const #426 = Asciz	(Lscala/collection/TraversableLike;Ljava/lang/String;)Ljava/lang/String;;
const #427 = NameAndType	#420:#426;//  mkString:(Lscala/collection/TraversableLike;Ljava/lang/String;)Ljava/lang/String;
const #428 = Method	#30.#427;	//  scala/collection/TraversableLike$class.mkString:(Lscala/collection/TraversableLike;Ljava/lang/String;)Ljava/lang/String;
const #429 = Asciz	(Ljava/lang/String;Ljava/lang/String;Ljava/lang/String;)Ljava/lang/String;;
const #430 = Asciz	(Lscala/collection/TraversableLike;Ljava/lang/String;Ljava/lang/String;Ljava/lang/String;)Ljava/lang/String;;
const #431 = NameAndType	#420:#430;//  mkString:(Lscala/collection/TraversableLike;Ljava/lang/String;Ljava/lang/String;Ljava/lang/String;)Ljava/lang/String;
const #432 = Method	#30.#431;	//  scala/collection/TraversableLike$class.mkString:(Lscala/collection/TraversableLike;Ljava/lang/String;Ljava/lang/String;Ljava/lang/String;)Ljava/lang/String;
const #433 = Asciz	start;
const #434 = Asciz	end;
const #435 = Asciz	toSet;
const #436 = Asciz	()Lscala/collection/immutable/Set;;
const #437 = Asciz	(Lscala/collection/TraversableLike;)Lscala/collection/immutable/Set;;
const #438 = NameAndType	#435:#437;//  toSet:(Lscala/collection/TraversableLike;)Lscala/collection/immutable/Set;
const #439 = Method	#30.#438;	//  scala/collection/TraversableLike$class.toSet:(Lscala/collection/TraversableLike;)Lscala/collection/immutable/Set;
const #440 = Asciz	toIndexedSeq;
const #441 = Asciz	()Lscala/collection/mutable/IndexedSeq;;
const #442 = Asciz	(Lscala/collection/TraversableLike;)Lscala/collection/mutable/IndexedSeq;;
const #443 = NameAndType	#440:#442;//  toIndexedSeq:(Lscala/collection/TraversableLike;)Lscala/collection/mutable/IndexedSeq;
const #444 = Method	#30.#443;	//  scala/collection/TraversableLike$class.toIndexedSeq:(Lscala/collection/TraversableLike;)Lscala/collection/mutable/IndexedSeq;
const #445 = Asciz	toSeq;
const #446 = Asciz	()Lscala/collection/Seq;;
const #447 = Asciz	(Lscala/collection/TraversableLike;)Lscala/collection/Seq;;
const #448 = NameAndType	#445:#447;//  toSeq:(Lscala/collection/TraversableLike;)Lscala/collection/Seq;
const #449 = Method	#30.#448;	//  scala/collection/TraversableLike$class.toSeq:(Lscala/collection/TraversableLike;)Lscala/collection/Seq;
const #450 = Asciz	toList;
const #451 = Asciz	()Lscala/collection/immutable/List;;
const #452 = Asciz	(Lscala/collection/TraversableLike;)Lscala/collection/immutable/List;;
const #453 = NameAndType	#450:#452;//  toList:(Lscala/collection/TraversableLike;)Lscala/collection/immutable/List;
const #454 = Method	#30.#453;	//  scala/collection/TraversableLike$class.toList:(Lscala/collection/TraversableLike;)Lscala/collection/immutable/List;
const #455 = Asciz	toArray;
const #456 = Asciz	(Lscala/reflect/ClassManifest;)Ljava/lang/Object;;
const #457 = Asciz	(Lscala/collection/TraversableLike;Lscala/reflect/ClassManifest;)Ljava/lang/Object;;
const #458 = NameAndType	#455:#457;//  toArray:(Lscala/collection/TraversableLike;Lscala/reflect/ClassManifest;)Ljava/lang/Object;
const #459 = Method	#30.#458;	//  scala/collection/TraversableLike$class.toArray:(Lscala/collection/TraversableLike;Lscala/reflect/ClassManifest;)Ljava/lang/Object;
const #460 = Asciz	evidence$1;
const #461 = Asciz	Lscala/reflect/ClassManifest;;
const #462 = Asciz	copyToArray;
const #463 = Asciz	(Lscala/collection/TraversableLike;Ljava/lang/Object;)V;
const #464 = NameAndType	#462:#463;//  copyToArray:(Lscala/collection/TraversableLike;Ljava/lang/Object;)V
const #465 = Method	#30.#464;	//  scala/collection/TraversableLike$class.copyToArray:(Lscala/collection/TraversableLike;Ljava/lang/Object;)V
const #466 = Asciz	xs;
const #467 = Asciz	(Ljava/lang/Object;I)V;
const #468 = Asciz	(Lscala/collection/TraversableLike;Ljava/lang/Object;I)V;
const #469 = NameAndType	#462:#468;//  copyToArray:(Lscala/collection/TraversableLike;Ljava/lang/Object;I)V
const #470 = Method	#30.#469;	//  scala/collection/TraversableLike$class.copyToArray:(Lscala/collection/TraversableLike;Ljava/lang/Object;I)V
const #471 = Asciz	copyToBuffer;
const #472 = Asciz	(Lscala/collection/mutable/Buffer;)V;
const #473 = Asciz	(Lscala/collection/TraversableLike;Lscala/collection/mutable/Buffer;)V;
const #474 = NameAndType	#471:#473;//  copyToBuffer:(Lscala/collection/TraversableLike;Lscala/collection/mutable/Buffer;)V
const #475 = Method	#30.#474;	//  scala/collection/TraversableLike$class.copyToBuffer:(Lscala/collection/TraversableLike;Lscala/collection/mutable/Buffer;)V
const #476 = Asciz	dest;
const #477 = Asciz	Lscala/collection/mutable/Buffer;;
const #478 = Asciz	splitAt;
const #479 = Asciz	(I)Lscala/Tuple2;;
const #480 = Asciz	(Lscala/collection/TraversableLike;I)Lscala/Tuple2;;
const #481 = NameAndType	#478:#480;//  splitAt:(Lscala/collection/TraversableLike;I)Lscala/Tuple2;
const #482 = Method	#30.#481;	//  scala/collection/TraversableLike$class.splitAt:(Lscala/collection/TraversableLike;I)Lscala/Tuple2;
const #483 = Asciz	n;
const #484 = Asciz	span;
const #485 = Asciz	(Lscala/Function1;)Lscala/Tuple2;;
const #486 = Asciz	(Lscala/collection/TraversableLike;Lscala/Function1;)Lscala/Tuple2;;
const #487 = NameAndType	#484:#486;//  span:(Lscala/collection/TraversableLike;Lscala/Function1;)Lscala/Tuple2;
const #488 = Method	#30.#487;	//  scala/collection/TraversableLike$class.span:(Lscala/collection/TraversableLike;Lscala/Function1;)Lscala/Tuple2;
const #489 = Asciz	dropWhile;
const #490 = Asciz	(Lscala/Function1;)Ljava/lang/Object;;
const #491 = Asciz	(Lscala/collection/TraversableLike;Lscala/Function1;)Ljava/lang/Object;;
const #492 = NameAndType	#489:#491;//  dropWhile:(Lscala/collection/TraversableLike;Lscala/Function1;)Ljava/lang/Object;
const #493 = Method	#30.#492;	//  scala/collection/TraversableLike$class.dropWhile:(Lscala/collection/TraversableLike;Lscala/Function1;)Ljava/lang/Object;
const #494 = Asciz	drop;
const #495 = Asciz	(I)Ljava/lang/Object;;
const #496 = Asciz	(Lscala/collection/TraversableLike;I)Ljava/lang/Object;;
const #497 = NameAndType	#494:#496;//  drop:(Lscala/collection/TraversableLike;I)Ljava/lang/Object;
const #498 = Method	#30.#497;	//  scala/collection/TraversableLike$class.drop:(Lscala/collection/TraversableLike;I)Ljava/lang/Object;
const #499 = Asciz	(Lscala/collection/TraversableLike;)Ljava/lang/Object;;
const #500 = NameAndType	#257:#499;//  init:(Lscala/collection/TraversableLike;)Ljava/lang/Object;
const #501 = Method	#30.#500;	//  scala/collection/TraversableLike$class.init:(Lscala/collection/TraversableLike;)Ljava/lang/Object;
const #502 = Asciz	lastOption;
const #503 = Asciz	()Lscala/Option;;
const #504 = Asciz	(Lscala/collection/TraversableLike;)Lscala/Option;;
const #505 = NameAndType	#502:#504;//  lastOption:(Lscala/collection/TraversableLike;)Lscala/Option;
const #506 = Method	#30.#505;	//  scala/collection/TraversableLike$class.lastOption:(Lscala/collection/TraversableLike;)Lscala/Option;
const #507 = Asciz	last;
const #508 = NameAndType	#507:#499;//  last:(Lscala/collection/TraversableLike;)Ljava/lang/Object;
const #509 = Method	#30.#508;	//  scala/collection/TraversableLike$class.last:(Lscala/collection/TraversableLike;)Ljava/lang/Object;
const #510 = Asciz	tail;
const #511 = NameAndType	#510:#499;//  tail:(Lscala/collection/TraversableLike;)Ljava/lang/Object;
const #512 = Method	#30.#511;	//  scala/collection/TraversableLike$class.tail:(Lscala/collection/TraversableLike;)Ljava/lang/Object;
const #513 = Asciz	headOption;
const #514 = NameAndType	#513:#504;//  headOption:(Lscala/collection/TraversableLike;)Lscala/Option;
const #515 = Method	#30.#514;	//  scala/collection/TraversableLike$class.headOption:(Lscala/collection/TraversableLike;)Lscala/Option;
const #516 = Asciz	max;
const #517 = Asciz	(Lscala/math/Ordering;)Ljava/lang/Object;;
const #518 = Asciz	(Lscala/collection/TraversableLike;Lscala/math/Ordering;)Ljava/lang/Object;;
const #519 = NameAndType	#516:#518;//  max:(Lscala/collection/TraversableLike;Lscala/math/Ordering;)Ljava/lang/Object;
const #520 = Method	#30.#519;	//  scala/collection/TraversableLike$class.max:(Lscala/collection/TraversableLike;Lscala/math/Ordering;)Ljava/lang/Object;
const #521 = Asciz	cmp;
const #522 = Asciz	Lscala/math/Ordering;;
const #523 = Asciz	min;
const #524 = NameAndType	#523:#518;//  min:(Lscala/collection/TraversableLike;Lscala/math/Ordering;)Ljava/lang/Object;
const #525 = Method	#30.#524;	//  scala/collection/TraversableLike$class.min:(Lscala/collection/TraversableLike;Lscala/math/Ordering;)Ljava/lang/Object;
const #526 = Asciz	product;
const #527 = Asciz	(Lscala/math/Numeric;)Ljava/lang/Object;;
const #528 = Asciz	(Lscala/collection/TraversableLike;Lscala/math/Numeric;)Ljava/lang/Object;;
const #529 = NameAndType	#526:#528;//  product:(Lscala/collection/TraversableLike;Lscala/math/Numeric;)Ljava/lang/Object;
const #530 = Method	#30.#529;	//  scala/collection/TraversableLike$class.product:(Lscala/collection/TraversableLike;Lscala/math/Numeric;)Ljava/lang/Object;
const #531 = Asciz	num;
const #532 = Asciz	Lscala/math/Numeric;;
const #533 = Asciz	sum;
const #534 = NameAndType	#533:#528;//  sum:(Lscala/collection/TraversableLike;Lscala/math/Numeric;)Ljava/lang/Object;
const #535 = Method	#30.#534;	//  scala/collection/TraversableLike$class.sum:(Lscala/collection/TraversableLike;Lscala/math/Numeric;)Ljava/lang/Object;
const #536 = Asciz	reduceRightOption;
const #537 = Asciz	(Lscala/Function2;)Lscala/Option;;
const #538 = Asciz	(Lscala/collection/TraversableLike;Lscala/Function2;)Lscala/Option;;
const #539 = NameAndType	#536:#538;//  reduceRightOption:(Lscala/collection/TraversableLike;Lscala/Function2;)Lscala/Option;
const #540 = Method	#30.#539;	//  scala/collection/TraversableLike$class.reduceRightOption:(Lscala/collection/TraversableLike;Lscala/Function2;)Lscala/Option;
const #541 = Asciz	op;
const #542 = Asciz	Lscala/Function2;;
const #543 = Asciz	reduceLeftOption;
const #544 = NameAndType	#543:#538;//  reduceLeftOption:(Lscala/collection/TraversableLike;Lscala/Function2;)Lscala/Option;
const #545 = Method	#30.#544;	//  scala/collection/TraversableLike$class.reduceLeftOption:(Lscala/collection/TraversableLike;Lscala/Function2;)Lscala/Option;
const #546 = Asciz	reduceLeft;
const #547 = Asciz	(Lscala/Function2;)Ljava/lang/Object;;
const #548 = Asciz	(Lscala/collection/TraversableLike;Lscala/Function2;)Ljava/lang/Object;;
const #549 = NameAndType	#546:#548;//  reduceLeft:(Lscala/collection/TraversableLike;Lscala/Function2;)Ljava/lang/Object;
const #550 = Method	#30.#549;	//  scala/collection/TraversableLike$class.reduceLeft:(Lscala/collection/TraversableLike;Lscala/Function2;)Ljava/lang/Object;
const #551 = Asciz	$colon$bslash;
const #552 = Asciz	(Ljava/lang/Object;Lscala/Function2;)Ljava/lang/Object;;
const #553 = Asciz	(Lscala/collection/TraversableLike;Ljava/lang/Object;Lscala/Function2;)Ljava/lang/Object;;
const #554 = NameAndType	#551:#553;//  $colon$bslash:(Lscala/collection/TraversableLike;Ljava/lang/Object;Lscala/Function2;)Ljava/lang/Object;
const #555 = Method	#30.#554;	//  scala/collection/TraversableLike$class.$colon$bslash:(Lscala/collection/TraversableLike;Ljava/lang/Object;Lscala/Function2;)Ljava/lang/Object;
const #556 = Asciz	z;
const #557 = Asciz	$div$colon;
const #558 = NameAndType	#557:#553;//  $div$colon:(Lscala/collection/TraversableLike;Ljava/lang/Object;Lscala/Function2;)Ljava/lang/Object;
const #559 = Method	#30.#558;	//  scala/collection/TraversableLike$class.$div$colon:(Lscala/collection/TraversableLike;Ljava/lang/Object;Lscala/Function2;)Ljava/lang/Object;
const #560 = Asciz	foldLeft;
const #561 = NameAndType	#560:#553;//  foldLeft:(Lscala/collection/TraversableLike;Ljava/lang/Object;Lscala/Function2;)Ljava/lang/Object;
const #562 = Method	#30.#561;	//  scala/collection/TraversableLike$class.foldLeft:(Lscala/collection/TraversableLike;Ljava/lang/Object;Lscala/Function2;)Ljava/lang/Object;
const #563 = Asciz	count;
const #564 = Asciz	(Lscala/Function1;)I;
const #565 = Asciz	(Lscala/collection/TraversableLike;Lscala/Function1;)I;
const #566 = NameAndType	#563:#565;//  count:(Lscala/collection/TraversableLike;Lscala/Function1;)I
const #567 = Method	#30.#566;	//  scala/collection/TraversableLike$class.count:(Lscala/collection/TraversableLike;Lscala/Function1;)I
const #568 = Asciz	groupBy;
const #569 = Asciz	(Lscala/Function1;)Lscala/collection/Map;;
const #570 = Asciz	(Lscala/collection/TraversableLike;Lscala/Function1;)Lscala/collection/Map;;
const #571 = NameAndType	#568:#570;//  groupBy:(Lscala/collection/TraversableLike;Lscala/Function1;)Lscala/collection/Map;
const #572 = Method	#30.#571;	//  scala/collection/TraversableLike$class.groupBy:(Lscala/collection/TraversableLike;Lscala/Function1;)Lscala/collection/Map;
const #573 = Asciz	partition;
const #574 = NameAndType	#573:#486;//  partition:(Lscala/collection/TraversableLike;Lscala/Function1;)Lscala/Tuple2;
const #575 = Method	#30.#574;	//  scala/collection/TraversableLike$class.partition:(Lscala/collection/TraversableLike;Lscala/Function1;)Lscala/Tuple2;
const #576 = Asciz	partialMap;
const #577 = Asciz	(Lscala/PartialFunction;Lscala/collection/generic/CanBuildFrom;)Ljava/lang/Object;;
const #578 = Asciz	(Lscala/collection/TraversableLike;Lscala/PartialFunction;Lscala/collection/generic/CanBuildFrom;)Ljava/lang/Object;;
const #579 = NameAndType	#576:#578;//  partialMap:(Lscala/collection/TraversableLike;Lscala/PartialFunction;Lscala/collection/generic/CanBuildFrom;)Ljava/lang/Object;
const #580 = Method	#30.#579;	//  scala/collection/TraversableLike$class.partialMap:(Lscala/collection/TraversableLike;Lscala/PartialFunction;Lscala/collection/generic/CanBuildFrom;)Ljava/lang/Object;
const #581 = Asciz	pf;
const #582 = Asciz	Lscala/PartialFunction;;
const #583 = Asciz	bf;
const #584 = Asciz	Lscala/collection/generic/CanBuildFrom;;
const #585 = Asciz	filterNot;
const #586 = NameAndType	#585:#491;//  filterNot:(Lscala/collection/TraversableLike;Lscala/Function1;)Ljava/lang/Object;
const #587 = Method	#30.#586;	//  scala/collection/TraversableLike$class.filterNot:(Lscala/collection/TraversableLike;Lscala/Function1;)Ljava/lang/Object;
const #588 = Asciz	filter;
const #589 = NameAndType	#588:#491;//  filter:(Lscala/collection/TraversableLike;Lscala/Function1;)Ljava/lang/Object;
const #590 = Method	#30.#589;	//  scala/collection/TraversableLike$class.filter:(Lscala/collection/TraversableLike;Lscala/Function1;)Ljava/lang/Object;
const #591 = Asciz	flatMap;
const #592 = Asciz	(Lscala/Function1;Lscala/collection/generic/CanBuildFrom;)Ljava/lang/Object;;
const #593 = Asciz	(Lscala/collection/TraversableLike;Lscala/Function1;Lscala/collection/generic/CanBuildFrom;)Ljava/lang/Object;;
const #594 = NameAndType	#591:#593;//  flatMap:(Lscala/collection/TraversableLike;Lscala/Function1;Lscala/collection/generic/CanBuildFrom;)Ljava/lang/Object;
const #595 = Method	#30.#594;	//  scala/collection/TraversableLike$class.flatMap:(Lscala/collection/TraversableLike;Lscala/Function1;Lscala/collection/generic/CanBuildFrom;)Ljava/lang/Object;
const #596 = Asciz	map;
const #597 = NameAndType	#596:#593;//  map:(Lscala/collection/TraversableLike;Lscala/Function1;Lscala/collection/generic/CanBuildFrom;)Ljava/lang/Object;
const #598 = Method	#30.#597;	//  scala/collection/TraversableLike$class.map:(Lscala/collection/TraversableLike;Lscala/Function1;Lscala/collection/generic/CanBuildFrom;)Ljava/lang/Object;
const #599 = Asciz	$plus$plus;
const #600 = Asciz	(Lscala/collection/Iterator;Lscala/collection/generic/CanBuildFrom;)Ljava/lang/Object;;
const #601 = Asciz	(Lscala/collection/TraversableLike;Lscala/collection/Iterator;Lscala/collection/generic/CanBuildFrom;)Ljava/lang/Object;;
const #602 = NameAndType	#599:#601;//  $plus$plus:(Lscala/collection/TraversableLike;Lscala/collection/Iterator;Lscala/collection/generic/CanBuildFrom;)Ljava/lang/Object;
const #603 = Method	#30.#602;	//  scala/collection/TraversableLike$class.$plus$plus:(Lscala/collection/TraversableLike;Lscala/collection/Iterator;Lscala/collection/generic/CanBuildFrom;)Ljava/lang/Object;
const #604 = Asciz	that;
const #605 = Asciz	(Lscala/collection/Traversable;Lscala/collection/generic/CanBuildFrom;)Ljava/lang/Object;;
const #606 = Asciz	(Lscala/collection/TraversableLike;Lscala/collection/Traversable;Lscala/collection/generic/CanBuildFrom;)Ljava/lang/Object;;
const #607 = NameAndType	#599:#606;//  $plus$plus:(Lscala/collection/TraversableLike;Lscala/collection/Traversable;Lscala/collection/generic/CanBuildFrom;)Ljava/lang/Object;
const #608 = Method	#30.#607;	//  scala/collection/TraversableLike$class.$plus$plus:(Lscala/collection/TraversableLike;Lscala/collection/Traversable;Lscala/collection/generic/CanBuildFrom;)Ljava/lang/Object;
const #609 = Asciz	hasDefiniteSize;
const #610 = Asciz	()Z;
const #611 = Asciz	(Lscala/collection/TraversableLike;)Z;
const #612 = NameAndType	#609:#611;//  hasDefiniteSize:(Lscala/collection/TraversableLike;)Z
const #613 = Method	#30.#612;	//  scala/collection/TraversableLike$class.hasDefiniteSize:(Lscala/collection/TraversableLike;)Z
const #614 = Asciz	nonEmpty;
const #615 = NameAndType	#614:#611;//  nonEmpty:(Lscala/collection/TraversableLike;)Z
const #616 = Method	#30.#615;	//  scala/collection/TraversableLike$class.nonEmpty:(Lscala/collection/TraversableLike;)Z
const #617 = NameAndType	#233:#499;//  repr:(Lscala/collection/TraversableLike;)Ljava/lang/Object;
const #618 = Method	#30.#617;	//  scala/collection/TraversableLike$class.repr:(Lscala/collection/TraversableLike;)Ljava/lang/Object;
const #619 = Asciz	transpose;
const #620 = Asciz	(Lscala/Function1;)Lscala/collection/Traversable;;
const #621 = Asciz	(Lscala/collection/generic/GenericTraversableTemplate;Lscala/Function1;)Lscala/collection/Traversable;;
const #622 = NameAndType	#619:#621;//  transpose:(Lscala/collection/generic/GenericTraversableTemplate;Lscala/Function1;)Lscala/collection/Traversable;
const #623 = Method	#36.#622;	//  scala/collection/generic/GenericTraversableTemplate$class.transpose:(Lscala/collection/generic/GenericTraversableTemplate;Lscala/Function1;)Lscala/collection/Traversable;
const #624 = Asciz	asTraversable;
const #625 = Asciz	flatten;
const #626 = NameAndType	#625:#621;//  flatten:(Lscala/collection/generic/GenericTraversableTemplate;Lscala/Function1;)Lscala/collection/Traversable;
const #627 = Method	#36.#626;	//  scala/collection/generic/GenericTraversableTemplate$class.flatten:(Lscala/collection/generic/GenericTraversableTemplate;Lscala/Function1;)Lscala/collection/Traversable;
const #628 = Asciz	unzip;
const #629 = Asciz	(Lscala/collection/generic/GenericTraversableTemplate;Lscala/Function1;)Lscala/Tuple2;;
const #630 = NameAndType	#628:#629;//  unzip:(Lscala/collection/generic/GenericTraversableTemplate;Lscala/Function1;)Lscala/Tuple2;
const #631 = Method	#36.#630;	//  scala/collection/generic/GenericTraversableTemplate$class.unzip:(Lscala/collection/generic/GenericTraversableTemplate;Lscala/Function1;)Lscala/Tuple2;
const #632 = Asciz	asPair;
const #633 = Asciz	genericBuilder;
const #634 = Asciz	()Lscala/collection/mutable/Builder;;
const #635 = Asciz	(Lscala/collection/generic/GenericTraversableTemplate;)Lscala/collection/mutable/Builder;;
const #636 = NameAndType	#633:#635;//  genericBuilder:(Lscala/collection/generic/GenericTraversableTemplate;)Lscala/collection/mutable/Builder;
const #637 = Method	#36.#636;	//  scala/collection/generic/GenericTraversableTemplate$class.genericBuilder:(Lscala/collection/generic/GenericTraversableTemplate;)Lscala/collection/mutable/Builder;
const #638 = Asciz	projection;
const #639 = Asciz	(Lscala/collection/IterableLike;)Ljava/lang/Object;;
const #640 = NameAndType	#638:#639;//  projection:(Lscala/collection/IterableLike;)Ljava/lang/Object;
const #641 = Method	#51.#640;	//  scala/collection/IterableLike$class.projection:(Lscala/collection/IterableLike;)Ljava/lang/Object;
const #642 = Asciz	Deprecated;
const #643 = Asciz	firstOption;
const #644 = Asciz	(Lscala/collection/IterableLike;)Lscala/Option;;
const #645 = NameAndType	#643:#644;//  firstOption:(Lscala/collection/IterableLike;)Lscala/Option;
const #646 = Method	#51.#645;	//  scala/collection/IterableLike$class.firstOption:(Lscala/collection/IterableLike;)Lscala/Option;
const #647 = Asciz	first;
const #648 = NameAndType	#647:#639;//  first:(Lscala/collection/IterableLike;)Ljava/lang/Object;
const #649 = Method	#51.#648;	//  scala/collection/IterableLike$class.first:(Lscala/collection/IterableLike;)Ljava/lang/Object;
const #650 = Asciz	(Lscala/collection/IterableLike;II)Lscala/collection/IterableView;;
const #651 = NameAndType	#234:#650;//  view:(Lscala/collection/IterableLike;II)Lscala/collection/IterableView;
const #652 = Method	#51.#651;	//  scala/collection/IterableLike$class.view:(Lscala/collection/IterableLike;II)Lscala/collection/IterableView;
const #653 = NameAndType	#234:#639;//  view:(Lscala/collection/IterableLike;)Ljava/lang/Object;
const #654 = Method	#51.#653;	//  scala/collection/IterableLike$class.view:(Lscala/collection/IterableLike;)Ljava/lang/Object;
const #655 = Asciz	canEqual;
const #656 = Asciz	(Lscala/collection/IterableLike;Ljava/lang/Object;)Z;
const #657 = NameAndType	#655:#656;//  canEqual:(Lscala/collection/IterableLike;Ljava/lang/Object;)Z
const #658 = Method	#51.#657;	//  scala/collection/IterableLike$class.canEqual:(Lscala/collection/IterableLike;Ljava/lang/Object;)Z
const #659 = Asciz	toStream;
const #660 = Asciz	()Lscala/collection/immutable/Stream;;
const #661 = Asciz	(Lscala/collection/IterableLike;)Lscala/collection/immutable/Stream;;
const #662 = NameAndType	#659:#661;//  toStream:(Lscala/collection/IterableLike;)Lscala/collection/immutable/Stream;
const #663 = Method	#51.#662;	//  scala/collection/IterableLike$class.toStream:(Lscala/collection/IterableLike;)Lscala/collection/immutable/Stream;
const #664 = Asciz	sameElements;
const #665 = Asciz	(Lscala/collection/Iterable;)Z;
const #666 = Asciz	(Lscala/collection/IterableLike;Lscala/collection/Iterable;)Z;
const #667 = NameAndType	#664:#666;//  sameElements:(Lscala/collection/IterableLike;Lscala/collection/Iterable;)Z
const #668 = Method	#51.#667;	//  scala/collection/IterableLike$class.sameElements:(Lscala/collection/IterableLike;Lscala/collection/Iterable;)Z
const #669 = Asciz	Lscala/collection/Iterable;;
const #670 = Asciz	zipWithIndex;
const #671 = Asciz	(Lscala/collection/generic/CanBuildFrom;)Ljava/lang/Object;;
const #672 = Asciz	(Lscala/collection/IterableLike;Lscala/collection/generic/CanBuildFrom;)Ljava/lang/Object;;
const #673 = NameAndType	#670:#672;//  zipWithIndex:(Lscala/collection/IterableLike;Lscala/collection/generic/CanBuildFrom;)Ljava/lang/Object;
const #674 = Method	#51.#673;	//  scala/collection/IterableLike$class.zipWithIndex:(Lscala/collection/IterableLike;Lscala/collection/generic/CanBuildFrom;)Ljava/lang/Object;
const #675 = Asciz	zipAll;
const #676 = Asciz	(Lscala/collection/Iterable;Ljava/lang/Object;Ljava/lang/Object;Lscala/collection/generic/CanBuildFrom;)Ljava/lang/Object;;
const #677 = Asciz	(Lscala/collection/IterableLike;Lscala/collection/Iterable;Ljava/lang/Object;Ljava/lang/Object;Lscala/collection/generic/CanBuildFrom;)Ljava/lang/Object;;
const #678 = NameAndType	#675:#677;//  zipAll:(Lscala/collection/IterableLike;Lscala/collection/Iterable;Ljava/lang/Object;Ljava/lang/Object;Lscala/collection/generic/CanBuildFrom;)Ljava/lang/Object;
const #679 = Method	#51.#678;	//  scala/collection/IterableLike$class.zipAll:(Lscala/collection/IterableLike;Lscala/collection/Iterable;Ljava/lang/Object;Ljava/lang/Object;Lscala/collection/generic/CanBuildFrom;)Ljava/lang/Object;
const #680 = Asciz	thisElem;
const #681 = Asciz	thatElem;
const #682 = Asciz	zip;
const #683 = Asciz	(Lscala/collection/Iterable;Lscala/collection/generic/CanBuildFrom;)Ljava/lang/Object;;
const #684 = Asciz	(Lscala/collection/IterableLike;Lscala/collection/Iterable;Lscala/collection/generic/CanBuildFrom;)Ljava/lang/Object;;
const #685 = NameAndType	#682:#684;//  zip:(Lscala/collection/IterableLike;Lscala/collection/Iterable;Lscala/collection/generic/CanBuildFrom;)Ljava/lang/Object;
const #686 = Method	#51.#685;	//  scala/collection/IterableLike$class.zip:(Lscala/collection/IterableLike;Lscala/collection/Iterable;Lscala/collection/generic/CanBuildFrom;)Ljava/lang/Object;
const #687 = Asciz	(Ljava/lang/Object;II)V;
const #688 = Asciz	(Lscala/collection/IterableLike;Ljava/lang/Object;II)V;
const #689 = NameAndType	#462:#688;//  copyToArray:(Lscala/collection/IterableLike;Ljava/lang/Object;II)V
const #690 = Method	#51.#689;	//  scala/collection/IterableLike$class.copyToArray:(Lscala/collection/IterableLike;Ljava/lang/Object;II)V
const #691 = Asciz	len;
const #692 = Asciz	dropRight;
const #693 = Asciz	(Lscala/collection/IterableLike;I)Ljava/lang/Object;;
const #694 = NameAndType	#692:#693;//  dropRight:(Lscala/collection/IterableLike;I)Ljava/lang/Object;
const #695 = Method	#51.#694;	//  scala/collection/IterableLike$class.dropRight:(Lscala/collection/IterableLike;I)Ljava/lang/Object;
const #696 = Asciz	takeRight;
const #697 = NameAndType	#696:#693;//  takeRight:(Lscala/collection/IterableLike;I)Ljava/lang/Object;
const #698 = Method	#51.#697;	//  scala/collection/IterableLike$class.takeRight:(Lscala/collection/IterableLike;I)Ljava/lang/Object;
const #699 = Asciz	takeWhile;
const #700 = Asciz	(Lscala/collection/IterableLike;Lscala/Function1;)Ljava/lang/Object;;
const #701 = NameAndType	#699:#700;//  takeWhile:(Lscala/collection/IterableLike;Lscala/Function1;)Ljava/lang/Object;
const #702 = Method	#51.#701;	//  scala/collection/IterableLike$class.takeWhile:(Lscala/collection/IterableLike;Lscala/Function1;)Ljava/lang/Object;
const #703 = Asciz	slice;
const #704 = Asciz	(II)Ljava/lang/Object;;
const #705 = Asciz	(Lscala/collection/IterableLike;II)Ljava/lang/Object;;
const #706 = NameAndType	#703:#705;//  slice:(Lscala/collection/IterableLike;II)Ljava/lang/Object;
const #707 = Method	#51.#706;	//  scala/collection/IterableLike$class.slice:(Lscala/collection/IterableLike;II)Ljava/lang/Object;
const #708 = Asciz	take;
const #709 = NameAndType	#708:#693;//  take:(Lscala/collection/IterableLike;I)Ljava/lang/Object;
const #710 = Method	#51.#709;	//  scala/collection/IterableLike$class.take:(Lscala/collection/IterableLike;I)Ljava/lang/Object;
const #711 = Asciz	head;
const #712 = NameAndType	#711:#639;//  head:(Lscala/collection/IterableLike;)Ljava/lang/Object;
const #713 = Method	#51.#712;	//  scala/collection/IterableLike$class.head:(Lscala/collection/IterableLike;)Ljava/lang/Object;
const #714 = Asciz	toIterable;
const #715 = Asciz	(Lscala/collection/IterableLike;)Lscala/collection/Iterable;;
const #716 = NameAndType	#714:#715;//  toIterable:(Lscala/collection/IterableLike;)Lscala/collection/Iterable;
const #717 = Method	#51.#716;	//  scala/collection/IterableLike$class.toIterable:(Lscala/collection/IterableLike;)Lscala/collection/Iterable;
const #718 = Asciz	reduceRight;
const #719 = Asciz	(Lscala/collection/IterableLike;Lscala/Function2;)Ljava/lang/Object;;
const #720 = NameAndType	#718:#719;//  reduceRight:(Lscala/collection/IterableLike;Lscala/Function2;)Ljava/lang/Object;
const #721 = Method	#51.#720;	//  scala/collection/IterableLike$class.reduceRight:(Lscala/collection/IterableLike;Lscala/Function2;)Ljava/lang/Object;
const #722 = Asciz	foldRight;
const #723 = Asciz	(Lscala/collection/IterableLike;Ljava/lang/Object;Lscala/Function2;)Ljava/lang/Object;;
const #724 = NameAndType	#722:#723;//  foldRight:(Lscala/collection/IterableLike;Ljava/lang/Object;Lscala/Function2;)Ljava/lang/Object;
const #725 = Method	#51.#724;	//  scala/collection/IterableLike$class.foldRight:(Lscala/collection/IterableLike;Ljava/lang/Object;Lscala/Function2;)Ljava/lang/Object;
const #726 = Asciz	find;
const #727 = Asciz	(Lscala/Function1;)Lscala/Option;;
const #728 = Asciz	(Lscala/collection/IterableLike;Lscala/Function1;)Lscala/Option;;
const #729 = NameAndType	#726:#728;//  find:(Lscala/collection/IterableLike;Lscala/Function1;)Lscala/Option;
const #730 = Method	#51.#729;	//  scala/collection/IterableLike$class.find:(Lscala/collection/IterableLike;Lscala/Function1;)Lscala/Option;
const #731 = Asciz	exists;
const #732 = Asciz	(Lscala/Function1;)Z;
const #733 = Asciz	(Lscala/collection/IterableLike;Lscala/Function1;)Z;
const #734 = NameAndType	#731:#733;//  exists:(Lscala/collection/IterableLike;Lscala/Function1;)Z
const #735 = Method	#51.#734;	//  scala/collection/IterableLike$class.exists:(Lscala/collection/IterableLike;Lscala/Function1;)Z
const #736 = Asciz	forall;
const #737 = NameAndType	#736:#733;//  forall:(Lscala/collection/IterableLike;Lscala/Function1;)Z
const #738 = Method	#51.#737;	//  scala/collection/IterableLike$class.forall:(Lscala/collection/IterableLike;Lscala/Function1;)Z
const #739 = Asciz	elements;
const #740 = Asciz	(Lscala/collection/IterableLike;)Lscala/collection/Iterator;;
const #741 = NameAndType	#739:#740;//  elements:(Lscala/collection/IterableLike;)Lscala/collection/Iterator;
const #742 = Method	#51.#741;	//  scala/collection/IterableLike$class.elements:(Lscala/collection/IterableLike;)Lscala/collection/Iterator;
const #743 = Asciz	(Lscala/collection/IterableLike;Ljava/lang/Object;)Lscala/collection/Iterable;;
const #744 = NameAndType	#228:#743;//  toCollection:(Lscala/collection/IterableLike;Ljava/lang/Object;)Lscala/collection/Iterable;
const #745 = Method	#51.#744;	//  scala/collection/IterableLike$class.toCollection:(Lscala/collection/IterableLike;Ljava/lang/Object;)Lscala/collection/Iterable;
const #746 = NameAndType	#221:#715;//  thisCollection:(Lscala/collection/IterableLike;)Lscala/collection/Iterable;
const #747 = Method	#51.#746;	//  scala/collection/IterableLike$class.thisCollection:(Lscala/collection/IterableLike;)Lscala/collection/Iterable;
const #748 = Asciz	companion;
const #749 = Asciz	()Lscala/collection/generic/GenericCompanion;;
const #750 = Asciz	(Lscala/collection/mutable/Iterable;)Lscala/collection/generic/GenericCompanion;;
const #751 = NameAndType	#748:#750;//  companion:(Lscala/collection/mutable/Iterable;)Lscala/collection/generic/GenericCompanion;
const #752 = Method	#61.#751;	//  scala/collection/mutable/Iterable$class.companion:(Lscala/collection/mutable/Iterable;)Lscala/collection/generic/GenericCompanion;
const #753 = Asciz	compose;
const #754 = Asciz	(Lscala/Function1;Lscala/Function1;)Lscala/Function1;;
const #755 = NameAndType	#753:#754;//  compose:(Lscala/Function1;Lscala/Function1;)Lscala/Function1;
const #756 = Method	#66.#755;	//  scala/Function1$class.compose:(Lscala/Function1;Lscala/Function1;)Lscala/Function1;
const #757 = Asciz	lift;
const #758 = Asciz	()Lscala/Function1;;
const #759 = Asciz	(Lscala/PartialFunction;)Lscala/Function1;;
const #760 = NameAndType	#757:#759;//  lift:(Lscala/PartialFunction;)Lscala/Function1;
const #761 = Method	#71.#760;	//  scala/PartialFunction$class.lift:(Lscala/PartialFunction;)Lscala/Function1;
const #762 = Asciz	(Lscala/PartialFunction;Lscala/Function1;)Lscala/PartialFunction;;
const #763 = NameAndType	#212:#762;//  andThen:(Lscala/PartialFunction;Lscala/Function1;)Lscala/PartialFunction;
const #764 = Method	#71.#763;	//  scala/PartialFunction$class.andThen:(Lscala/PartialFunction;Lscala/Function1;)Lscala/PartialFunction;
const #765 = Asciz	k;
const #766 = Asciz	orElse;
const #767 = Asciz	(Lscala/PartialFunction;)Lscala/PartialFunction;;
const #768 = Asciz	(Lscala/PartialFunction;Lscala/PartialFunction;)Lscala/PartialFunction;;
const #769 = NameAndType	#766:#768;//  orElse:(Lscala/PartialFunction;Lscala/PartialFunction;)Lscala/PartialFunction;
const #770 = Method	#71.#769;	//  scala/PartialFunction$class.orElse:(Lscala/PartialFunction;Lscala/PartialFunction;)Lscala/PartialFunction;
const #771 = Asciz	(Lscala/collection/MapLike;Ljava/lang/Object;)Z;
const #772 = NameAndType	#369:#771;//  equals:(Lscala/collection/MapLike;Ljava/lang/Object;)Z
const #773 = Method	#81.#772;	//  scala/collection/MapLike$class.equals:(Lscala/collection/MapLike;Ljava/lang/Object;)Z
const #774 = Asciz	hashCode;
const #775 = Asciz	(Lscala/collection/MapLike;)I;
const #776 = NameAndType	#774:#775;//  hashCode:(Lscala/collection/MapLike;)I
const #777 = Method	#81.#776;	//  scala/collection/MapLike$class.hashCode:(Lscala/collection/MapLike;)I
const #778 = Asciz	toString;
const #779 = Asciz	(Lscala/collection/MapLike;)Ljava/lang/String;;
const #780 = NameAndType	#778:#779;//  toString:(Lscala/collection/MapLike;)Ljava/lang/String;
const #781 = Method	#81.#780;	//  scala/collection/MapLike$class.toString:(Lscala/collection/MapLike;)Ljava/lang/String;
const #782 = Asciz	stringPrefix;
const #783 = NameAndType	#782:#779;//  stringPrefix:(Lscala/collection/MapLike;)Ljava/lang/String;
const #784 = Method	#81.#783;	//  scala/collection/MapLike$class.stringPrefix:(Lscala/collection/MapLike;)Ljava/lang/String;
const #785 = Asciz	(Lscala/collection/mutable/StringBuilder;Ljava/lang/String;Ljava/lang/String;Ljava/lang/String;)Lscala/collection/mutable/StringBuilder;;
const #786 = Asciz	(Lscala/collection/MapLike;Lscala/collection/mutable/StringBuilder;Ljava/lang/String;Ljava/lang/String;Ljava/lang/String;)Lscala/collection/mutable/StringBuilder;;
const #787 = NameAndType	#407:#786;//  addString:(Lscala/collection/MapLike;Lscala/collection/mutable/StringBuilder;Ljava/lang/String;Ljava/lang/String;Ljava/lang/String;)Lscala/collection/mutable/StringBuilder;
const #788 = Method	#81.#787;	//  scala/collection/MapLike$class.addString:(Lscala/collection/MapLike;Lscala/collection/mutable/StringBuilder;Ljava/lang/String;Ljava/lang/String;Ljava/lang/String;)Lscala/collection/mutable/StringBuilder;
const #789 = Asciz	(Lscala/collection/Iterator;)Lscala/collection/Map;;
const #790 = Asciz	(Lscala/collection/MapLike;Lscala/collection/Iterator;)Lscala/collection/Map;;
const #791 = NameAndType	#599:#790;//  $plus$plus:(Lscala/collection/MapLike;Lscala/collection/Iterator;)Lscala/collection/Map;
const #792 = Method	#81.#791;	//  scala/collection/MapLike$class.$plus$plus:(Lscala/collection/MapLike;Lscala/collection/Iterator;)Lscala/collection/Map;
const #793 = Asciz	(Lscala/collection/Traversable;)Lscala/collection/Map;;
const #794 = Asciz	(Lscala/collection/MapLike;Lscala/collection/Traversable;)Lscala/collection/Map;;
const #795 = NameAndType	#599:#794;//  $plus$plus:(Lscala/collection/MapLike;Lscala/collection/Traversable;)Lscala/collection/Map;
const #796 = Method	#81.#795;	//  scala/collection/MapLike$class.$plus$plus:(Lscala/collection/MapLike;Lscala/collection/Traversable;)Lscala/collection/Map;
const #797 = Asciz	kvs;
const #798 = Asciz	(Lscala/Tuple2;Lscala/Tuple2;Lscala/collection/Seq;)Lscala/collection/Map;;
const #799 = Asciz	(Lscala/collection/MapLike;Lscala/Tuple2;Lscala/Tuple2;Lscala/collection/Seq;)Lscala/collection/Map;;
const #800 = NameAndType	#205:#799;//  $plus:(Lscala/collection/MapLike;Lscala/Tuple2;Lscala/Tuple2;Lscala/collection/Seq;)Lscala/collection/Map;
const #801 = Method	#81.#800;	//  scala/collection/MapLike$class.$plus:(Lscala/collection/MapLike;Lscala/Tuple2;Lscala/Tuple2;Lscala/collection/Seq;)Lscala/collection/Map;
const #802 = Asciz	kv1;
const #803 = Asciz	kv2;
const #804 = Asciz	mapElements;
const #805 = Asciz	(Lscala/collection/MapLike;Lscala/Function1;)Ljava/lang/Object;;
const #806 = NameAndType	#804:#805;//  mapElements:(Lscala/collection/MapLike;Lscala/Function1;)Ljava/lang/Object;
const #807 = Method	#81.#806;	//  scala/collection/MapLike$class.mapElements:(Lscala/collection/MapLike;Lscala/Function1;)Ljava/lang/Object;
const #808 = Asciz	mapValues;
const #809 = NameAndType	#808:#805;//  mapValues:(Lscala/collection/MapLike;Lscala/Function1;)Ljava/lang/Object;
const #810 = Method	#81.#809;	//  scala/collection/MapLike$class.mapValues:(Lscala/collection/MapLike;Lscala/Function1;)Ljava/lang/Object;
const #811 = Asciz	filterKeys;
const #812 = NameAndType	#811:#805;//  filterKeys:(Lscala/collection/MapLike;Lscala/Function1;)Ljava/lang/Object;
const #813 = Method	#81.#812;	//  scala/collection/MapLike$class.filterKeys:(Lscala/collection/MapLike;Lscala/Function1;)Ljava/lang/Object;
const #814 = Asciz	default;
const #815 = Asciz	(Lscala/collection/MapLike;Ljava/lang/Object;)Ljava/lang/Object;;
const #816 = NameAndType	#814:#815;//  default:(Lscala/collection/MapLike;Ljava/lang/Object;)Ljava/lang/Object;
const #817 = Method	#81.#816;	//  scala/collection/MapLike$class.default:(Lscala/collection/MapLike;Ljava/lang/Object;)Ljava/lang/Object;
const #818 = Asciz	values;
const #819 = Asciz	(Lscala/collection/MapLike;)Lscala/collection/Iterator;;
const #820 = NameAndType	#818:#819;//  values:(Lscala/collection/MapLike;)Lscala/collection/Iterator;
const #821 = Method	#81.#820;	//  scala/collection/MapLike$class.values:(Lscala/collection/MapLike;)Lscala/collection/Iterator;
const #822 = Asciz	valuesIterable;
const #823 = Asciz	(Lscala/collection/MapLike;)Lscala/collection/Iterable;;
const #824 = NameAndType	#822:#823;//  valuesIterable:(Lscala/collection/MapLike;)Lscala/collection/Iterable;
const #825 = Method	#81.#824;	//  scala/collection/MapLike$class.valuesIterable:(Lscala/collection/MapLike;)Lscala/collection/Iterable;
const #826 = Asciz	keys;
const #827 = NameAndType	#826:#819;//  keys:(Lscala/collection/MapLike;)Lscala/collection/Iterator;
const #828 = Method	#81.#827;	//  scala/collection/MapLike$class.keys:(Lscala/collection/MapLike;)Lscala/collection/Iterator;
const #829 = Asciz	keySet;
const #830 = Asciz	()Lscala/collection/Set;;
const #831 = Asciz	(Lscala/collection/MapLike;)Lscala/collection/Set;;
const #832 = NameAndType	#829:#831;//  keySet:(Lscala/collection/MapLike;)Lscala/collection/Set;
const #833 = Method	#81.#832;	//  scala/collection/MapLike$class.keySet:(Lscala/collection/MapLike;)Lscala/collection/Set;
const #834 = Asciz	isDefinedAt;
const #835 = NameAndType	#834:#771;//  isDefinedAt:(Lscala/collection/MapLike;Ljava/lang/Object;)Z
const #836 = Method	#81.#835;	//  scala/collection/MapLike$class.isDefinedAt:(Lscala/collection/MapLike;Ljava/lang/Object;)Z
const #837 = Asciz	contains;
const #838 = NameAndType	#837:#771;//  contains:(Lscala/collection/MapLike;Ljava/lang/Object;)Z
const #839 = Method	#81.#838;	//  scala/collection/MapLike$class.contains:(Lscala/collection/MapLike;Ljava/lang/Object;)Z
const #840 = NameAndType	#297:#815;//  apply:(Lscala/collection/MapLike;Ljava/lang/Object;)Ljava/lang/Object;
const #841 = Method	#81.#840;	//  scala/collection/MapLike$class.apply:(Lscala/collection/MapLike;Ljava/lang/Object;)Ljava/lang/Object;
const #842 = Asciz	getOrElse;
const #843 = Asciz	(Ljava/lang/Object;Lscala/Function0;)Ljava/lang/Object;;
const #844 = Asciz	(Lscala/collection/MapLike;Ljava/lang/Object;Lscala/Function0;)Ljava/lang/Object;;
const #845 = NameAndType	#842:#844;//  getOrElse:(Lscala/collection/MapLike;Ljava/lang/Object;Lscala/Function0;)Ljava/lang/Object;
const #846 = Method	#81.#845;	//  scala/collection/MapLike$class.getOrElse:(Lscala/collection/MapLike;Ljava/lang/Object;Lscala/Function0;)Ljava/lang/Object;
const #847 = Asciz	Lscala/Function0;;
const #848 = Asciz	isEmpty;
const #849 = Asciz	(Lscala/collection/MapLike;)Z;
const #850 = NameAndType	#848:#849;//  isEmpty:(Lscala/collection/MapLike;)Z
const #851 = Method	#81.#850;	//  scala/collection/MapLike$class.isEmpty:(Lscala/collection/MapLike;)Z
const #852 = Asciz	scala$collection$mutable$Cloneable$$super$clone;
const #853 = NameAndType	#177:#178;//  clone:()Ljava/lang/Object;
const #854 = Method	#26.#853;	//  java/lang/Object.clone:()Ljava/lang/Object;
const #855 = Asciz	(Lscala/collection/mutable/MapLikeBase;Lscala/Tuple2;)Lscala/collection/mutable/Map;;
const #856 = NameAndType	#205:#855;//  $plus:(Lscala/collection/mutable/MapLikeBase;Lscala/Tuple2;)Lscala/collection/mutable/Map;
const #857 = Method	#96.#856;	//  scala/collection/mutable/MapLikeBase$class.$plus:(Lscala/collection/mutable/MapLikeBase;Lscala/Tuple2;)Lscala/collection/mutable/Map;
const #858 = Asciz	$plus$plus$eq;
const #859 = Asciz	(Lscala/collection/Traversable;)Lscala/collection/generic/Growable;;
const #860 = Asciz	(Lscala/collection/generic/Growable;Lscala/collection/Traversable;)Lscala/collection/generic/Growable;;
const #861 = NameAndType	#858:#860;//  $plus$plus$eq:(Lscala/collection/generic/Growable;Lscala/collection/Traversable;)Lscala/collection/generic/Growable;
const #862 = Method	#101.#861;	//  scala/collection/generic/Growable$class.$plus$plus$eq:(Lscala/collection/generic/Growable;Lscala/collection/Traversable;)Lscala/collection/generic/Growable;
const #863 = Asciz	(Lscala/collection/Iterator;)Lscala/collection/generic/Growable;;
const #864 = Asciz	(Lscala/collection/generic/Growable;Lscala/collection/Iterator;)Lscala/collection/generic/Growable;;
const #865 = NameAndType	#858:#864;//  $plus$plus$eq:(Lscala/collection/generic/Growable;Lscala/collection/Iterator;)Lscala/collection/generic/Growable;
const #866 = Method	#101.#865;	//  scala/collection/generic/Growable$class.$plus$plus$eq:(Lscala/collection/generic/Growable;Lscala/collection/Iterator;)Lscala/collection/generic/Growable;
const #867 = Asciz	(Ljava/lang/Object;Ljava/lang/Object;Lscala/collection/Seq;)Lscala/collection/generic/Growable;;
const #868 = Asciz	(Lscala/collection/generic/Growable;Ljava/lang/Object;Ljava/lang/Object;Lscala/collection/Seq;)Lscala/collection/generic/Growable;;
const #869 = NameAndType	#141:#868;//  $plus$eq:(Lscala/collection/generic/Growable;Ljava/lang/Object;Ljava/lang/Object;Lscala/collection/Seq;)Lscala/collection/generic/Growable;
const #870 = Method	#101.#869;	//  scala/collection/generic/Growable$class.$plus$eq:(Lscala/collection/generic/Growable;Ljava/lang/Object;Ljava/lang/Object;Lscala/collection/Seq;)Lscala/collection/generic/Growable;
const #871 = Asciz	mapResult;
const #872 = Asciz	(Lscala/Function1;)Lscala/collection/mutable/Builder;;
const #873 = Asciz	(Lscala/collection/mutable/Builder;Lscala/Function1;)Lscala/collection/mutable/Builder;;
const #874 = NameAndType	#871:#873;//  mapResult:(Lscala/collection/mutable/Builder;Lscala/Function1;)Lscala/collection/mutable/Builder;
const #875 = Method	#106.#874;	//  scala/collection/mutable/Builder$class.mapResult:(Lscala/collection/mutable/Builder;Lscala/Function1;)Lscala/collection/mutable/Builder;
const #876 = Asciz	sizeHint;
const #877 = Asciz	(I)V;
const #878 = Asciz	(Lscala/collection/mutable/Builder;I)V;
const #879 = NameAndType	#876:#878;//  sizeHint:(Lscala/collection/mutable/Builder;I)V
const #880 = Method	#106.#879;	//  scala/collection/mutable/Builder$class.sizeHint:(Lscala/collection/mutable/Builder;I)V
const #881 = Asciz	$minus$minus$eq;
const #882 = Asciz	(Lscala/collection/Traversable;)Lscala/collection/generic/Shrinkable;;
const #883 = Asciz	(Lscala/collection/generic/Shrinkable;Lscala/collection/Traversable;)Lscala/collection/generic/Shrinkable;;
const #884 = NameAndType	#881:#883;//  $minus$minus$eq:(Lscala/collection/generic/Shrinkable;Lscala/collection/Traversable;)Lscala/collection/generic/Shrinkable;
const #885 = Method	#111.#884;	//  scala/collection/generic/Shrinkable$class.$minus$minus$eq:(Lscala/collection/generic/Shrinkable;Lscala/collection/Traversable;)Lscala/collection/generic/Shrinkable;
const #886 = Asciz	(Lscala/collection/Iterator;)Lscala/collection/generic/Shrinkable;;
const #887 = Asciz	(Lscala/collection/generic/Shrinkable;Lscala/collection/Iterator;)Lscala/collection/generic/Shrinkable;;
const #888 = NameAndType	#881:#887;//  $minus$minus$eq:(Lscala/collection/generic/Shrinkable;Lscala/collection/Iterator;)Lscala/collection/generic/Shrinkable;
const #889 = Method	#111.#888;	//  scala/collection/generic/Shrinkable$class.$minus$minus$eq:(Lscala/collection/generic/Shrinkable;Lscala/collection/Iterator;)Lscala/collection/generic/Shrinkable;
const #890 = Asciz	(Ljava/lang/Object;Ljava/lang/Object;Lscala/collection/Seq;)Lscala/collection/generic/Shrinkable;;
const #891 = Asciz	(Lscala/collection/generic/Shrinkable;Ljava/lang/Object;Ljava/lang/Object;Lscala/collection/Seq;)Lscala/collection/generic/Shrinkable;;
const #892 = NameAndType	#157:#891;//  $minus$eq:(Lscala/collection/generic/Shrinkable;Ljava/lang/Object;Ljava/lang/Object;Lscala/collection/Seq;)Lscala/collection/generic/Shrinkable;
const #893 = Method	#111.#892;	//  scala/collection/generic/Shrinkable$class.$minus$eq:(Lscala/collection/generic/Shrinkable;Ljava/lang/Object;Ljava/lang/Object;Lscala/collection/Seq;)Lscala/collection/generic/Shrinkable;
const #894 = Asciz	(Lscala/collection/mutable/MapLike;Lscala/collection/Iterator;)Lscala/collection/mutable/MapLike;;
const #895 = NameAndType	#193:#894;//  $minus$minus:(Lscala/collection/mutable/MapLike;Lscala/collection/Iterator;)Lscala/collection/mutable/MapLike;
const #896 = Method	#116.#895;	//  scala/collection/mutable/MapLike$class.$minus$minus:(Lscala/collection/mutable/MapLike;Lscala/collection/Iterator;)Lscala/collection/mutable/MapLike;
const #897 = Asciz	(Lscala/collection/mutable/MapLike;Lscala/collection/Traversable;)Lscala/collection/mutable/MapLike;;
const #898 = NameAndType	#193:#897;//  $minus$minus:(Lscala/collection/mutable/MapLike;Lscala/collection/Traversable;)Lscala/collection/mutable/MapLike;
const #899 = Method	#116.#898;	//  scala/collection/mutable/MapLike$class.$minus$minus:(Lscala/collection/mutable/MapLike;Lscala/collection/Traversable;)Lscala/collection/mutable/MapLike;
const #900 = Asciz	(Lscala/collection/mutable/MapLike;Ljava/lang/Object;Ljava/lang/Object;Lscala/collection/Seq;)Lscala/collection/mutable/MapLike;;
const #901 = NameAndType	#172:#900;//  $minus:(Lscala/collection/mutable/MapLike;Ljava/lang/Object;Ljava/lang/Object;Lscala/collection/Seq;)Lscala/collection/mutable/MapLike;
const #902 = Method	#116.#901;	//  scala/collection/mutable/MapLike$class.$minus:(Lscala/collection/mutable/MapLike;Ljava/lang/Object;Ljava/lang/Object;Lscala/collection/Seq;)Lscala/collection/mutable/MapLike;
const #903 = Asciz	(Lscala/collection/mutable/MapLike;)Lscala/collection/mutable/MapLike;;
const #904 = NameAndType	#182:#903;//  result:(Lscala/collection/mutable/MapLike;)Lscala/collection/mutable/MapLike;
const #905 = Method	#116.#904;	//  scala/collection/mutable/MapLike$class.result:(Lscala/collection/mutable/MapLike;)Lscala/collection/mutable/MapLike;
const #906 = NameAndType	#177:#903;//  clone:(Lscala/collection/mutable/MapLike;)Lscala/collection/mutable/MapLike;
const #907 = Method	#116.#906;	//  scala/collection/mutable/MapLike$class.clone:(Lscala/collection/mutable/MapLike;)Lscala/collection/mutable/MapLike;
const #908 = Asciz	retain;
const #909 = Asciz	(Lscala/Function2;)Lscala/collection/mutable/MapLike;;
const #910 = Asciz	(Lscala/collection/mutable/MapLike;Lscala/Function2;)Lscala/collection/mutable/MapLike;;
const #911 = NameAndType	#908:#910;//  retain:(Lscala/collection/mutable/MapLike;Lscala/Function2;)Lscala/collection/mutable/MapLike;
const #912 = Method	#116.#911;	//  scala/collection/mutable/MapLike$class.retain:(Lscala/collection/mutable/MapLike;Lscala/Function2;)Lscala/collection/mutable/MapLike;
const #913 = Asciz	transform;
const #914 = NameAndType	#913:#910;//  transform:(Lscala/collection/mutable/MapLike;Lscala/Function2;)Lscala/collection/mutable/MapLike;
const #915 = Method	#116.#914;	//  scala/collection/mutable/MapLike$class.transform:(Lscala/collection/mutable/MapLike;Lscala/Function2;)Lscala/collection/mutable/MapLike;
const #916 = Asciz	getOrElseUpdate;
const #917 = Asciz	(Lscala/collection/mutable/MapLike;Ljava/lang/Object;Lscala/Function0;)Ljava/lang/Object;;
const #918 = NameAndType	#916:#917;//  getOrElseUpdate:(Lscala/collection/mutable/MapLike;Ljava/lang/Object;Lscala/Function0;)Ljava/lang/Object;
const #919 = Method	#116.#918;	//  scala/collection/mutable/MapLike$class.getOrElseUpdate:(Lscala/collection/mutable/MapLike;Ljava/lang/Object;Lscala/Function0;)Ljava/lang/Object;
const #920 = Asciz	removeKey;
const #921 = Asciz	(Lscala/collection/mutable/MapLike;Ljava/lang/Object;)Lscala/Option;;
const #922 = NameAndType	#920:#921;//  removeKey:(Lscala/collection/mutable/MapLike;Ljava/lang/Object;)Lscala/Option;
const #923 = Method	#116.#922;	//  scala/collection/mutable/MapLike$class.removeKey:(Lscala/collection/mutable/MapLike;Ljava/lang/Object;)Lscala/Option;
const #924 = Asciz	(Lscala/collection/mutable/MapLike;Ljava/lang/Object;)Lscala/collection/mutable/MapLike;;
const #925 = NameAndType	#172:#924;//  $minus:(Lscala/collection/mutable/MapLike;Ljava/lang/Object;)Lscala/collection/mutable/MapLike;
const #926 = Method	#116.#925;	//  scala/collection/mutable/MapLike$class.$minus:(Lscala/collection/mutable/MapLike;Ljava/lang/Object;)Lscala/collection/mutable/MapLike;
const #927 = NameAndType	#599:#894;//  $plus$plus:(Lscala/collection/mutable/MapLike;Lscala/collection/Iterator;)Lscala/collection/mutable/MapLike;
const #928 = Method	#116.#927;	//  scala/collection/mutable/MapLike$class.$plus$plus:(Lscala/collection/mutable/MapLike;Lscala/collection/Iterator;)Lscala/collection/mutable/MapLike;
const #929 = NameAndType	#599:#897;//  $plus$plus:(Lscala/collection/mutable/MapLike;Lscala/collection/Traversable;)Lscala/collection/mutable/MapLike;
const #930 = Method	#116.#929;	//  scala/collection/mutable/MapLike$class.$plus$plus:(Lscala/collection/mutable/MapLike;Lscala/collection/Traversable;)Lscala/collection/mutable/MapLike;
const #931 = Asciz	(Lscala/Tuple2;Lscala/Tuple2;Lscala/collection/Seq;)Lscala/collection/mutable/MapLike;;
const #932 = Asciz	(Lscala/collection/mutable/MapLike;Lscala/Tuple2;Lscala/Tuple2;Lscala/collection/Seq;)Lscala/collection/mutable/MapLike;;
const #933 = NameAndType	#205:#932;//  $plus:(Lscala/collection/mutable/MapLike;Lscala/Tuple2;Lscala/Tuple2;Lscala/collection/Seq;)Lscala/collection/mutable/MapLike;
const #934 = Method	#116.#933;	//  scala/collection/mutable/MapLike$class.$plus:(Lscala/collection/mutable/MapLike;Lscala/Tuple2;Lscala/Tuple2;Lscala/collection/Seq;)Lscala/collection/mutable/MapLike;
const #935 = Asciz	(Lscala/collection/mutable/MapLike;Lscala/Tuple2;)Lscala/collection/mutable/MapLike;;
const #936 = NameAndType	#205:#935;//  $plus:(Lscala/collection/mutable/MapLike;Lscala/Tuple2;)Lscala/collection/mutable/MapLike;
const #937 = Method	#116.#936;	//  scala/collection/mutable/MapLike$class.$plus:(Lscala/collection/mutable/MapLike;Lscala/Tuple2;)Lscala/collection/mutable/MapLike;
const #938 = Asciz	(Lscala/collection/mutable/MapLike;Ljava/lang/Object;Ljava/lang/Object;)Lscala/collection/mutable/Map;;
const #939 = NameAndType	#164:#938;//  updated:(Lscala/collection/mutable/MapLike;Ljava/lang/Object;Ljava/lang/Object;)Lscala/collection/mutable/Map;
const #940 = Method	#116.#939;	//  scala/collection/mutable/MapLike$class.updated:(Lscala/collection/mutable/MapLike;Ljava/lang/Object;Ljava/lang/Object;)Lscala/collection/mutable/Map;
const #941 = Asciz	update;
const #942 = Asciz	(Lscala/collection/mutable/MapLike;Ljava/lang/Object;Ljava/lang/Object;)V;
const #943 = NameAndType	#941:#942;//  update:(Lscala/collection/mutable/MapLike;Ljava/lang/Object;Ljava/lang/Object;)V
const #944 = Method	#116.#943;	//  scala/collection/mutable/MapLike$class.update:(Lscala/collection/mutable/MapLike;Ljava/lang/Object;Ljava/lang/Object;)V
const #945 = Asciz	newBuilder;
const #946 = Asciz	(Lscala/collection/mutable/MapLike;)Lscala/collection/mutable/Builder;;
const #947 = NameAndType	#945:#946;//  newBuilder:(Lscala/collection/mutable/MapLike;)Lscala/collection/mutable/Builder;
const #948 = Method	#116.#947;	//  scala/collection/mutable/MapLike$class.newBuilder:(Lscala/collection/mutable/MapLike;)Lscala/collection/mutable/Builder;
const #949 = Asciz	index;
const #950 = Asciz	(I)I;
const #951 = Asciz	(Lscala/collection/mutable/HashTable;I)I;
const #952 = NameAndType	#949:#951;//  index:(Lscala/collection/mutable/HashTable;I)I
const #953 = Method	#126.#952;	//  scala/collection/mutable/HashTable$class.index:(Lscala/collection/mutable/HashTable;I)I
const #954 = Asciz	hcode;
const #955 = Asciz	improve;
const #956 = NameAndType	#955:#951;//  improve:(Lscala/collection/mutable/HashTable;I)I
const #957 = Method	#126.#956;	//  scala/collection/mutable/HashTable$class.improve:(Lscala/collection/mutable/HashTable;I)I
const #958 = Asciz	elemHashCode;
const #959 = Asciz	(Ljava/lang/Object;)I;
const #960 = Asciz	(Lscala/collection/mutable/HashTable;Ljava/lang/Object;)I;
const #961 = NameAndType	#958:#960;//  elemHashCode:(Lscala/collection/mutable/HashTable;Ljava/lang/Object;)I
const #962 = Method	#126.#961;	//  scala/collection/mutable/HashTable$class.elemHashCode:(Lscala/collection/mutable/HashTable;Ljava/lang/Object;)I
const #963 = Asciz	elemEquals;
const #964 = Asciz	(Ljava/lang/Object;Ljava/lang/Object;)Z;
const #965 = Asciz	(Lscala/collection/mutable/HashTable;Ljava/lang/Object;Ljava/lang/Object;)Z;
const #966 = NameAndType	#963:#965;//  elemEquals:(Lscala/collection/mutable/HashTable;Ljava/lang/Object;Ljava/lang/Object;)Z
const #967 = Method	#126.#966;	//  scala/collection/mutable/HashTable$class.elemEquals:(Lscala/collection/mutable/HashTable;Ljava/lang/Object;Ljava/lang/Object;)Z
const #968 = Asciz	key1;
const #969 = Asciz	key2;
const #970 = NameAndType	#275:#127;//  clearTable:(Lscala/collection/mutable/HashTable;)V
const #971 = Method	#126.#970;	//  scala/collection/mutable/HashTable$class.clearTable:(Lscala/collection/mutable/HashTable;)V
const #972 = Asciz	entries;
const #973 = Asciz	(Lscala/collection/mutable/HashTable;)Lscala/collection/Iterator;;
const #974 = NameAndType	#972:#973;//  entries:(Lscala/collection/mutable/HashTable;)Lscala/collection/Iterator;
const #975 = Method	#126.#974;	//  scala/collection/mutable/HashTable$class.entries:(Lscala/collection/mutable/HashTable;)Lscala/collection/Iterator;
const #976 = Asciz	foreachEntry;
const #977 = Asciz	(Lscala/collection/mutable/HashTable;Lscala/Function1;)V;
const #978 = NameAndType	#976:#977;//  foreachEntry:(Lscala/collection/mutable/HashTable;Lscala/Function1;)V
const #979 = Method	#126.#978;	//  scala/collection/mutable/HashTable$class.foreachEntry:(Lscala/collection/mutable/HashTable;Lscala/Function1;)V
const #980 = Asciz	entriesIterator;
const #981 = NameAndType	#980:#973;//  entriesIterator:(Lscala/collection/mutable/HashTable;)Lscala/collection/Iterator;
const #982 = Method	#126.#981;	//  scala/collection/mutable/HashTable$class.entriesIterator:(Lscala/collection/mutable/HashTable;)Lscala/collection/Iterator;
const #983 = Asciz	(Lscala/collection/mutable/HashTable;Ljava/lang/Object;)Lscala/collection/mutable/HashEntry;;
const #984 = NameAndType	#339:#983;//  removeEntry:(Lscala/collection/mutable/HashTable;Ljava/lang/Object;)Lscala/collection/mutable/HashEntry;
const #985 = Method	#126.#984;	//  scala/collection/mutable/HashTable$class.removeEntry:(Lscala/collection/mutable/HashTable;Ljava/lang/Object;)Lscala/collection/mutable/HashEntry;
const #986 = Asciz	(Lscala/collection/mutable/HashTable;Lscala/collection/mutable/HashEntry;)V;
const #987 = NameAndType	#379:#986;//  addEntry:(Lscala/collection/mutable/HashTable;Lscala/collection/mutable/HashEntry;)V
const #988 = Method	#126.#987;	//  scala/collection/mutable/HashTable$class.addEntry:(Lscala/collection/mutable/HashTable;Lscala/collection/mutable/HashEntry;)V
const #989 = Asciz	Lscala/collection/mutable/HashEntry;;
const #990 = NameAndType	#375:#983;//  findEntry:(Lscala/collection/mutable/HashTable;Ljava/lang/Object;)Lscala/collection/mutable/HashEntry;
const #991 = Method	#126.#990;	//  scala/collection/mutable/HashTable$class.findEntry:(Lscala/collection/mutable/HashTable;Ljava/lang/Object;)Lscala/collection/mutable/HashEntry;
const #992 = Asciz	(Lscala/collection/mutable/HashTable;Ljava/io/ObjectOutputStream;Lscala/Function1;)V;
const #993 = NameAndType	#268:#992;//  serializeTo:(Lscala/collection/mutable/HashTable;Ljava/io/ObjectOutputStream;Lscala/Function1;)V
const #994 = Method	#126.#993;	//  scala/collection/mutable/HashTable$class.serializeTo:(Lscala/collection/mutable/HashTable;Ljava/io/ObjectOutputStream;Lscala/Function1;)V
const #995 = Asciz	(Lscala/collection/mutable/HashTable;Ljava/io/ObjectInputStream;Lscala/Function2;)V;
const #996 = NameAndType	#257:#995;//  init:(Lscala/collection/mutable/HashTable;Ljava/io/ObjectInputStream;Lscala/Function2;)V
const #997 = Method	#126.#996;	//  scala/collection/mutable/HashTable$class.init:(Lscala/collection/mutable/HashTable;Ljava/io/ObjectInputStream;Lscala/Function2;)V
const #998 = Asciz	initialThreshold;
const #999 = Asciz	(Lscala/collection/mutable/HashTable;)I;
const #1000 = NameAndType	#998:#999;//  initialThreshold:(Lscala/collection/mutable/HashTable;)I
const #1001 = Method	#126.#1000;	//  scala/collection/mutable/HashTable$class.initialThreshold:(Lscala/collection/mutable/HashTable;)I
const #1002 = Asciz	initialSize;
const #1003 = NameAndType	#1002:#999;//  initialSize:(Lscala/collection/mutable/HashTable;)I
const #1004 = Method	#126.#1003;	//  scala/collection/mutable/HashTable$class.initialSize:(Lscala/collection/mutable/HashTable;)I
const #1005 = Asciz	loadFactor;
const #1006 = NameAndType	#1005:#999;//  loadFactor:(Lscala/collection/mutable/HashTable;)I
const #1007 = Method	#126.#1006;	//  scala/collection/mutable/HashTable$class.loadFactor:(Lscala/collection/mutable/HashTable;)I
const #1008 = Asciz	threshold_$eq;
const #1009 = NameAndType	#12:#13;//  threshold:I
const #1010 = Field	#9.#1009;	//  scala/collection/mutable/LinkedHashMap.threshold:I
const #1011 = Asciz	tableSize_$eq;
const #1012 = NameAndType	#14:#13;//  tableSize:I
const #1013 = Field	#9.#1012;	//  scala/collection/mutable/LinkedHashMap.tableSize:I
const #1014 = Asciz	table_$eq;
const #1015 = Asciz	([Lscala/collection/mutable/HashEntry;)V;
const #1016 = NameAndType	#15:#16;//  table:[Lscala/collection/mutable/HashEntry;
const #1017 = Field	#9.#1016;	//  scala/collection/mutable/LinkedHashMap.table:[Lscala/collection/mutable/HashEntry;
const #1018 = Asciz	()[Lscala/collection/mutable/HashEntry;;
const #1019 = Asciz	_loadFactor_$eq;
const #1020 = NameAndType	#17:#13;//  _loadFactor:I
const #1021 = Field	#9.#1020;	//  scala/collection/mutable/LinkedHashMap._loadFactor:I
const #1022 = Asciz	loadFactorDenum;
const #1023 = int	1000;
const #1024 = Asciz	<A:Ljava/lang/Object;B:Ljava/lang/Object;>Ljava/lang/Object;Lscala/collection/mutable/Map<TA;TB;>;Lscala/collection/mutable/MapLike<TA;TB;Lscala/collection/mutable/LinkedHashMap<TA;TB;>;>;Lscala/collection/mutable/HashTable<TA;>;Lscala/ScalaObject;;
const #1025 = Asciz	ScalaSig;
const #1026 = Asciz	InnerClasses;
const #1027 = Asciz	$anon$1;
const #1028 = Asciz	$anon$2;
const #1029 = Asciz	$anon$3;
const #1030 = Asciz	scala/collection/TraversableLike$WithFilter;
const #1031 = class	#1030;	//  scala/collection/TraversableLike$WithFilter
const #1032 = Asciz	WithFilter;
const #1033 = Asciz	$anonfun$readObject$1;
const #1034 = Asciz	$anonfun$writeObject$1;
const #1035 = Asciz	scala/collection/mutable/Map;
const #1036 = class	#1035;	//  scala/collection/mutable/Map
const #1037 = Asciz	scala/ScalaObject;
const #1038 = class	#1037;	//  scala/ScalaObject
const #1039 = Asciz	java/io/Serializable;
const #1040 = class	#1039;	//  java/io/Serializable

{
public static final long serialVersionUID;

public static {};
  Code:
   Stack=2, Locals=0, Args_size=0
   0:	lconst_1
   1:	putstatic	#11; //Field serialVersionUID:J
   4:	return

public scala.collection.mutable.LinkedHashMap();
  Code:
   Stack=2, Locals=1, Args_size=1
   0:	aload_0
   1:	invokespecial	#28; //Method java/lang/Object."<init>":()V
   4:	aload_0
   5:	invokestatic	#34; //Method scala/collection/TraversableLike$class.$init$:(Lscala/collection/TraversableLike;)V
   8:	aload_0
   9:	invokestatic	#39; //Method scala/collection/generic/GenericTraversableTemplate$class.$init$:(Lscala/collection/generic/GenericTraversableTemplate;)V
   12:	aload_0
   13:	invokestatic	#44; //Method scala/collection/Traversable$class.$init$:(Lscala/collection/Traversable;)V
   16:	aload_0
   17:	invokestatic	#49; //Method scala/collection/mutable/Traversable$class.$init$:(Lscala/collection/mutable/Traversable;)V
   20:	aload_0
   21:	invokestatic	#54; //Method scala/collection/IterableLike$class.$init$:(Lscala/collection/IterableLike;)V
   24:	aload_0
   25:	invokestatic	#59; //Method scala/collection/Iterable$class.$init$:(Lscala/collection/Iterable;)V
   28:	aload_0
   29:	invokestatic	#64; //Method scala/collection/mutable/Iterable$class.$init$:(Lscala/collection/mutable/Iterable;)V
   32:	aload_0
   33:	invokestatic	#69; //Method scala/Function1$class.$init$:(Lscala/Function1;)V
   36:	aload_0
   37:	invokestatic	#74; //Method scala/PartialFunction$class.$init$:(Lscala/PartialFunction;)V
   40:	aload_0
   41:	invokestatic	#79; //Method scala/collection/generic/Subtractable$class.$init$:(Lscala/collection/generic/Subtractable;)V
   44:	aload_0
   45:	invokestatic	#84; //Method scala/collection/MapLike$class.$init$:(Lscala/collection/MapLike;)V
   48:	aload_0
   49:	invokestatic	#89; //Method scala/collection/Map$class.$init$:(Lscala/collection/Map;)V
   52:	aload_0
   53:	invokestatic	#94; //Method scala/collection/mutable/Cloneable$class.$init$:(Lscala/collection/mutable/Cloneable;)V
   56:	aload_0
   57:	invokestatic	#99; //Method scala/collection/mutable/MapLikeBase$class.$init$:(Lscala/collection/mutable/MapLikeBase;)V
   60:	aload_0
   61:	invokestatic	#104; //Method scala/collection/generic/Growable$class.$init$:(Lscala/collection/generic/Growable;)V
   64:	aload_0
   65:	invokestatic	#109; //Method scala/collection/mutable/Builder$class.$init$:(Lscala/collection/mutable/Builder;)V
   68:	aload_0
   69:	invokestatic	#114; //Method scala/collection/generic/Shrinkable$class.$init$:(Lscala/collection/generic/Shrinkable;)V
   72:	aload_0
   73:	invokestatic	#119; //Method scala/collection/mutable/MapLike$class.$init$:(Lscala/collection/mutable/MapLike;)V
   76:	aload_0
   77:	invokestatic	#124; //Method scala/collection/mutable/Map$class.$init$:(Lscala/collection/mutable/Map;)V
   80:	aload_0
   81:	invokestatic	#129; //Method scala/collection/mutable/HashTable$class.$init$:(Lscala/collection/mutable/HashTable;)V
   84:	aload_0
   85:	aconst_null
   86:	putfield	#131; //Field firstEntry:Lscala/collection/mutable/LinkedEntry;
   89:	aload_0
   90:	aconst_null
   91:	putfield	#133; //Field lastEntry:Lscala/collection/mutable/LinkedEntry;
   94:	return
  LineNumberTable: 
   line 33: 0
   line 42: 84
   line 43: 89

  Signature: length = 0x2
   00 04 

public scala.collection.mutable.Map empty();
  Code:
   Stack=1, Locals=1, Args_size=1
   0:	aload_0
   1:	invokevirtual	#138; //Method empty:()Lscala/collection/mutable/LinkedHashMap;
   4:	areturn
  LineNumberTable: 
   line 33: 0


public scala.collection.Map empty();
  Code:
   Stack=1, Locals=1, Args_size=1
   0:	aload_0
   1:	invokevirtual	#138; //Method empty:()Lscala/collection/mutable/LinkedHashMap;
   4:	areturn
  LineNumberTable: 
   line 33: 0


public scala.collection.MapLike empty();
  Code:
   Stack=1, Locals=1, Args_size=1
   0:	aload_0
   1:	invokevirtual	#138; //Method empty:()Lscala/collection/mutable/LinkedHashMap;
   4:	areturn
  LineNumberTable: 
   line 33: 0


public scala.collection.mutable.MapLike $plus$eq(scala.Tuple2);
  Code:
   Stack=2, Locals=2, Args_size=2
   0:	aload_0
   1:	aload_1
   2:	invokevirtual	#145; //Method $plus$eq:(Lscala/Tuple2;)Lscala/collection/mutable/LinkedHashMap;
   5:	areturn
  LineNumberTable: 
   line 33: 0

  LocalVariableTable: 
   Start  Length  Slot  Name   Signature
   0      6      0    this       Lscala/collection/mutable/LinkedHashMap;
   0      6      1    kv       Lscala/Tuple2;


public scala.collection.mutable.Builder $plus$eq(java.lang.Object);
  Code:
   Stack=2, Locals=2, Args_size=2
   0:	aload_0
   1:	aload_1
   2:	checkcast	#153; //class scala/Tuple2
   5:	invokevirtual	#145; //Method $plus$eq:(Lscala/Tuple2;)Lscala/collection/mutable/LinkedHashMap;
   8:	areturn
  LineNumberTable: 
   line 33: 0

  LocalVariableTable: 
   Start  Length  Slot  Name   Signature
   0      9      0    this       Lscala/collection/mutable/LinkedHashMap;
   0      9      1    elem       Ljava/lang/Object;


public scala.collection.generic.Growable $plus$eq(java.lang.Object);
  Code:
   Stack=2, Locals=2, Args_size=2
   0:	aload_0
   1:	aload_1
   2:	checkcast	#153; //class scala/Tuple2
   5:	invokevirtual	#145; //Method $plus$eq:(Lscala/Tuple2;)Lscala/collection/mutable/LinkedHashMap;
   8:	areturn
  LineNumberTable: 
   line 33: 0

  LocalVariableTable: 
   Start  Length  Slot  Name   Signature
   0      9      0    this       Lscala/collection/mutable/LinkedHashMap;
   0      9      1    elem       Ljava/lang/Object;


public scala.collection.mutable.MapLike $minus$eq(java.lang.Object);
  Code:
   Stack=2, Locals=2, Args_size=2
   0:	aload_0
   1:	aload_1
   2:	invokevirtual	#161; //Method $minus$eq:(Ljava/lang/Object;)Lscala/collection/mutable/LinkedHashMap;
   5:	areturn
  LineNumberTable: 
   line 33: 0

  LocalVariableTable: 
   Start  Length  Slot  Name   Signature
   0      6      0    this       Lscala/collection/mutable/LinkedHashMap;
   0      6      1    key       Ljava/lang/Object;


public scala.collection.generic.Shrinkable $minus$eq(java.lang.Object);
  Code:
   Stack=2, Locals=2, Args_size=2
   0:	aload_0
   1:	aload_1
   2:	invokevirtual	#161; //Method $minus$eq:(Ljava/lang/Object;)Lscala/collection/mutable/LinkedHashMap;
   5:	areturn
  LineNumberTable: 
   line 33: 0

  LocalVariableTable: 
   Start  Length  Slot  Name   Signature
   0      6      0    this       Lscala/collection/mutable/LinkedHashMap;
   0      6      1    elem       Ljava/lang/Object;


public scala.collection.Map updated(java.lang.Object, java.lang.Object);
  Code:
   Stack=3, Locals=3, Args_size=3
   0:	aload_0
   1:	aload_1
   2:	aload_2
   3:	invokeinterface	#170,  3; //InterfaceMethod scala/collection/mutable/MapLike.updated:(Ljava/lang/Object;Ljava/lang/Object;)Lscala/collection/mutable/Map;
   8:	areturn
  LineNumberTable: 
   line 33: 0

  LocalVariableTable: 
   Start  Length  Slot  Name   Signature
   0      9      0    this       Lscala/collection/mutable/LinkedHashMap;
   0      9      1    key       Ljava/lang/Object;
   0      9      2    value       Ljava/lang/Object;


public scala.collection.MapLike $minus(java.lang.Object);
  Code:
   Stack=2, Locals=2, Args_size=2
   0:	aload_0
   1:	aload_1
   2:	invokeinterface	#175,  2; //InterfaceMethod scala/collection/mutable/MapLike.$minus:(Ljava/lang/Object;)Lscala/collection/mutable/MapLike;
   7:	areturn
  LineNumberTable: 
   line 33: 0

  LocalVariableTable: 
   Start  Length  Slot  Name   Signature
   0      8      0    this       Lscala/collection/mutable/LinkedHashMap;
   0      8      1    key       Ljava/lang/Object;


public scala.collection.generic.Subtractable $minus(java.lang.Object);
  Code:
   Stack=2, Locals=2, Args_size=2
   0:	aload_0
   1:	aload_1
   2:	invokeinterface	#175,  2; //InterfaceMethod scala/collection/mutable/MapLike.$minus:(Ljava/lang/Object;)Lscala/collection/mutable/MapLike;
   7:	areturn
  LineNumberTable: 
   line 33: 0

  LocalVariableTable: 
   Start  Length  Slot  Name   Signature
   0      8      0    this       Lscala/collection/mutable/LinkedHashMap;
   0      8      1    elem       Ljava/lang/Object;


public java.lang.Object clone();
  Code:
   Stack=1, Locals=1, Args_size=1
   0:	aload_0
   1:	invokeinterface	#181,  1; //InterfaceMethod scala/collection/mutable/MapLike.clone:()Lscala/collection/mutable/MapLike;
   6:	areturn
  LineNumberTable: 
   line 33: 0


public java.lang.Object result();
  Code:
   Stack=1, Locals=1, Args_size=1
   0:	aload_0
   1:	invokeinterface	#184,  1; //InterfaceMethod scala/collection/mutable/MapLike.result:()Lscala/collection/mutable/MapLike;
   6:	areturn
  LineNumberTable: 
   line 33: 0


public scala.collection.generic.Subtractable $minus(java.lang.Object, java.lang.Object, scala.collection.Seq);
  Code:
   Stack=4, Locals=4, Args_size=4
   0:	aload_0
   1:	aload_1
   2:	aload_2
   3:	aload_3
   4:	invokeinterface	#188,  4; //InterfaceMethod scala/collection/mutable/MapLike.$minus:(Ljava/lang/Object;Ljava/lang/Object;Lscala/collection/Seq;)Lscala/collection/mutable/MapLike;
   9:	areturn
  LineNumberTable: 
   line 33: 0

  LocalVariableTable: 
   Start  Length  Slot  Name   Signature
   0      10      0    this       Lscala/collection/mutable/LinkedHashMap;
   0      10      1    elem1       Ljava/lang/Object;
   0      10      2    elem2       Ljava/lang/Object;
   0      10      3    elems       Lscala/collection/Seq;


public scala.collection.generic.Subtractable $minus$minus(scala.collection.Traversable);
  Code:
   Stack=2, Locals=2, Args_size=2
   0:	aload_0
   1:	aload_1
   2:	invokeinterface	#197,  2; //InterfaceMethod scala/collection/mutable/MapLike.$minus$minus:(Lscala/collection/Traversable;)Lscala/collection/mutable/MapLike;
   7:	areturn
  LineNumberTable: 
   line 33: 0

  LocalVariableTable: 
   Start  Length  Slot  Name   Signature
   0      8      0    this       Lscala/collection/mutable/LinkedHashMap;
   0      8      1    elems       Lscala/collection/Traversable;


public scala.collection.generic.Subtractable $minus$minus(scala.collection.Iterator);
  Code:
   Stack=2, Locals=2, Args_size=2
   0:	aload_0
   1:	aload_1
   2:	invokeinterface	#202,  2; //InterfaceMethod scala/collection/mutable/MapLike.$minus$minus:(Lscala/collection/Iterator;)Lscala/collection/mutable/MapLike;
   7:	areturn
  LineNumberTable: 
   line 33: 0

  LocalVariableTable: 
   Start  Length  Slot  Name   Signature
   0      8      0    this       Lscala/collection/mutable/LinkedHashMap;
   0      8      1    iter       Lscala/collection/Iterator;


public scala.collection.Map $plus(scala.Tuple2);
  Code:
   Stack=2, Locals=2, Args_size=2
   0:	aload_0
   1:	aload_1
   2:	invokeinterface	#211,  2; //InterfaceMethod scala/collection/mutable/MapLikeBase.$plus:(Lscala/Tuple2;)Lscala/collection/mutable/Map;
   7:	areturn
  LineNumberTable: 
   line 33: 0

  LocalVariableTable: 
   Start  Length  Slot  Name   Signature
   0      8      0    this       Lscala/collection/mutable/LinkedHashMap;
   0      8      1    kv       Lscala/Tuple2;


public scala.Function1 andThen(scala.Function1);
  Code:
   Stack=2, Locals=2, Args_size=2
   0:	aload_0
   1:	aload_1
   2:	invokeinterface	#218,  2; //InterfaceMethod scala/PartialFunction.andThen:(Lscala/Function1;)Lscala/PartialFunction;
   7:	areturn
  LineNumberTable: 
   line 33: 0

  LocalVariableTable: 
   Start  Length  Slot  Name   Signature
   0      8      0    this       Lscala/collection/mutable/LinkedHashMap;
   0      8      1    g       Lscala/Function1;


public scala.collection.Traversable thisCollection();
  Code:
   Stack=1, Locals=1, Args_size=1
   0:	aload_0
   1:	invokeinterface	#227,  1; //InterfaceMethod scala/collection/IterableLike.thisCollection:()Lscala/collection/Iterable;
   6:	areturn
  LineNumberTable: 
   line 33: 0


public scala.collection.Traversable toCollection(java.lang.Object);
  Code:
   Stack=2, Locals=2, Args_size=2
   0:	aload_0
   1:	aload_1
   2:	invokeinterface	#232,  2; //InterfaceMethod scala/collection/IterableLike.toCollection:(Ljava/lang/Object;)Lscala/collection/Iterable;
   7:	areturn
  LineNumberTable: 
   line 33: 0

  LocalVariableTable: 
   Start  Length  Slot  Name   Signature
   0      8      0    this       Lscala/collection/mutable/LinkedHashMap;
   0      8      1    repr       Ljava/lang/Object;


public scala.collection.TraversableView view(int, int);
  Code:
   Stack=3, Locals=3, Args_size=3
   0:	aload_0
   1:	iload_1
   2:	iload_2
   3:	invokeinterface	#238,  3; //InterfaceMethod scala/collection/IterableLike.view:(II)Lscala/collection/IterableView;
   8:	areturn
  LineNumberTable: 
   line 33: 0

  LocalVariableTable: 
   Start  Length  Slot  Name   Signature
   0      9      0    this       Lscala/collection/mutable/LinkedHashMap;
   0      9      1    from       I
   0      9      2    until       I


public scala.collection.generic.Subtractable repr();
  Code:
   Stack=1, Locals=1, Args_size=1
   0:	aload_0
   1:	invokeinterface	#245,  1; //InterfaceMethod scala/collection/TraversableLike.repr:()Ljava/lang/Object;
   6:	checkcast	#247; //class scala/collection/generic/Subtractable
   9:	areturn
  LineNumberTable: 
   line 33: 0


public void clear();
  Code:
   Stack=2, Locals=1, Args_size=1
   0:	aload_0
   1:	invokeinterface	#277,  1; //InterfaceMethod scala/collection/mutable/HashTable.clearTable:()V
   6:	aload_0
   7:	aconst_null
   8:	invokevirtual	#281; //Method firstEntry_$eq:(Lscala/collection/mutable/LinkedEntry;)V
   11:	return
  LineNumberTable: 
   line 119: 0
   line 120: 6


public void foreach(scala.Function1);
  Code:
   Stack=5, Locals=3, Args_size=2
   0:	aload_0
   1:	invokevirtual	#285; //Method firstEntry:()Lscala/collection/mutable/LinkedEntry;
   4:	astore_2
   5:	aload_2
   6:	ifnull	39
   9:	aload_1
   10:	new	#153; //class scala/Tuple2
   13:	dup
   14:	aload_2
   15:	getfield	#289; //Field scala/collection/mutable/LinkedEntry.key:Ljava/lang/Object;
   18:	aload_2
   19:	getfield	#291; //Field scala/collection/mutable/LinkedEntry.value:Ljava/lang/Object;
   22:	invokespecial	#294; //Method scala/Tuple2."<init>":(Ljava/lang/Object;Ljava/lang/Object;)V
   25:	invokeinterface	#300,  2; //InterfaceMethod scala/Function1.apply:(Ljava/lang/Object;)Ljava/lang/Object;
   30:	pop
   31:	aload_2
   32:	invokevirtual	#303; //Method scala/collection/mutable/LinkedEntry.later:()Lscala/collection/mutable/LinkedEntry;
   35:	astore_2
   36:	goto	5
   39:	return
  LineNumberTable: 
   line 111: 0
   line 112: 5
   line 113: 9
   line 114: 31
   line 110: 39

  LocalVariableTable: 
   Start  Length  Slot  Name   Signature
   0      40      0    this       Lscala/collection/mutable/LinkedHashMap;
   0      40      1    f       Lscala/Function1;
   5      35      2    cur       Lscala/collection/mutable/LinkedEntry;

  Signature: length = 0x2
   01 32 

public scala.collection.Iterator valuesIterator();
  Code:
   Stack=3, Locals=1, Args_size=1
   0:	new	#310; //class scala/collection/mutable/LinkedHashMap$$anon$3
   3:	dup
   4:	aload_0
   5:	invokespecial	#311; //Method scala/collection/mutable/LinkedHashMap$$anon$3."<init>":(Lscala/collection/mutable/LinkedHashMap;)V
   8:	areturn
  LineNumberTable: 
   line 102: 0

  Signature: length = 0x2
   01 38 

public scala.collection.Iterator keysIterator();
  Code:
   Stack=3, Locals=1, Args_size=1
   0:	new	#315; //class scala/collection/mutable/LinkedHashMap$$anon$2
   3:	dup
   4:	aload_0
   5:	invokespecial	#316; //Method scala/collection/mutable/LinkedHashMap$$anon$2."<init>":(Lscala/collection/mutable/LinkedHashMap;)V
   8:	areturn
  LineNumberTable: 
   line 94: 0

  Signature: length = 0x2
   01 3D 

public scala.collection.Iterator iterator();
  Code:
   Stack=3, Locals=1, Args_size=1
   0:	new	#320; //class scala/collection/mutable/LinkedHashMap$$anon$1
   3:	dup
   4:	aload_0
   5:	invokespecial	#321; //Method scala/collection/mutable/LinkedHashMap$$anon$1."<init>":(Lscala/collection/mutable/LinkedHashMap;)V
   8:	areturn
  LineNumberTable: 
   line 86: 0

  Signature: length = 0x2
   01 42 

public scala.collection.mutable.LinkedHashMap $minus$eq(java.lang.Object);
  Code:
   Stack=2, Locals=2, Args_size=2
   0:	aload_0
   1:	aload_1
   2:	invokevirtual	#326; //Method remove:(Ljava/lang/Object;)Lscala/Option;
   5:	pop
   6:	aload_0
   7:	areturn
  LineNumberTable: 
   line 84: 0

  LocalVariableTable: 
   Start  Length  Slot  Name   Signature
   0      8      0    this       Lscala/collection/mutable/LinkedHashMap;
   0      8      1    key       Ljava/lang/Object;

  Signature: length = 0x2
   01 47 

public scala.collection.mutable.LinkedHashMap $plus$eq(scala.Tuple2);
  Code:
   Stack=3, Locals=2, Args_size=2
   0:	aload_0
   1:	aload_1
   2:	invokevirtual	#330; //Method scala/Tuple2._1:()Ljava/lang/Object;
   5:	aload_1
   6:	invokevirtual	#333; //Method scala/Tuple2._2:()Ljava/lang/Object;
   9:	invokevirtual	#337; //Method put:(Ljava/lang/Object;Ljava/lang/Object;)Lscala/Option;
   12:	pop
   13:	aload_0
   14:	areturn
  LineNumberTable: 
   line 83: 0

  LocalVariableTable: 
   Start  Length  Slot  Name   Signature
   0      15      0    this       Lscala/collection/mutable/LinkedHashMap;
   0      15      1    kv       Lscala/Tuple2;

  Signature: length = 0x2
   01 52 

public scala.Option remove(java.lang.Object);
  Code:
   Stack=3, Locals=3, Args_size=2
   0:	aload_0
   1:	aload_1
   2:	invokeinterface	#342,  2; //InterfaceMethod scala/collection/mutable/HashTable.removeEntry:(Ljava/lang/Object;)Lscala/collection/mutable/HashEntry;
   7:	checkcast	#287; //class scala/collection/mutable/LinkedEntry
   10:	astore_2
   11:	aload_2
   12:	ifnonnull	21
   15:	getstatic	#348; //Field scala/None$.MODULE$:Lscala/None$;
   18:	goto	90
   21:	aload_2
   22:	invokevirtual	#351; //Method scala/collection/mutable/LinkedEntry.earlier:()Lscala/collection/mutable/LinkedEntry;
   25:	ifnonnull	39
   28:	aload_0
   29:	aload_2
   30:	invokevirtual	#303; //Method scala/collection/mutable/LinkedEntry.later:()Lscala/collection/mutable/LinkedEntry;
   33:	invokevirtual	#281; //Method firstEntry_$eq:(Lscala/collection/mutable/LinkedEntry;)V
   36:	goto	50
   39:	aload_2
   40:	invokevirtual	#351; //Method scala/collection/mutable/LinkedEntry.earlier:()Lscala/collection/mutable/LinkedEntry;
   43:	aload_2
   44:	invokevirtual	#303; //Method scala/collection/mutable/LinkedEntry.later:()Lscala/collection/mutable/LinkedEntry;
   47:	invokevirtual	#354; //Method scala/collection/mutable/LinkedEntry.later_$eq:(Lscala/collection/mutable/LinkedEntry;)V
   50:	aload_2
   51:	invokevirtual	#303; //Method scala/collection/mutable/LinkedEntry.later:()Lscala/collection/mutable/LinkedEntry;
   54:	ifnonnull	68
   57:	aload_0
   58:	aload_2
   59:	invokevirtual	#351; //Method scala/collection/mutable/LinkedEntry.earlier:()Lscala/collection/mutable/LinkedEntry;
   62:	invokevirtual	#357; //Method lastEntry_$eq:(Lscala/collection/mutable/LinkedEntry;)V
   65:	goto	79
   68:	aload_2
   69:	invokevirtual	#303; //Method scala/collection/mutable/LinkedEntry.later:()Lscala/collection/mutable/LinkedEntry;
   72:	aload_2
   73:	invokevirtual	#351; //Method scala/collection/mutable/LinkedEntry.earlier:()Lscala/collection/mutable/LinkedEntry;
   76:	invokevirtual	#360; //Method scala/collection/mutable/LinkedEntry.earlier_$eq:(Lscala/collection/mutable/LinkedEntry;)V
   79:	new	#362; //class scala/Some
   82:	dup
   83:	aload_2
   84:	getfield	#291; //Field scala/collection/mutable/LinkedEntry.value:Ljava/lang/Object;
   87:	invokespecial	#365; //Method scala/Some."<init>":(Ljava/lang/Object;)V
   90:	areturn
  LineNumberTable: 
   line 72: 0
   line 73: 11
   line 75: 21
   line 76: 39
   line 77: 50
   line 78: 68
   line 79: 79
   line 71: 90

  LocalVariableTable: 
   Start  Length  Slot  Name   Signature
   0      91      0    this       Lscala/collection/mutable/LinkedHashMap;
   0      91      1    key       Ljava/lang/Object;
   11      80      2    e       Lscala/collection/mutable/LinkedEntry;

  Signature: length = 0x2
   01 6F 

public final void scala$collection$mutable$LinkedHashMap$$updateLinkedEntries(scala.collection.mutable.LinkedEntry);
  Code:
   Stack=2, Locals=3, Args_size=2
   0:	aload_0
   1:	invokevirtual	#285; //Method firstEntry:()Lscala/collection/mutable/LinkedEntry;
   4:	dup
   5:	astore_2
   6:	ifnull	17
   9:	aload_2
   10:	aconst_null
   11:	invokevirtual	#372; //Method java/lang/Object.equals:(Ljava/lang/Object;)Z
   14:	ifeq	25
   17:	aload_0
   18:	aload_1
   19:	invokevirtual	#281; //Method firstEntry_$eq:(Lscala/collection/mutable/LinkedEntry;)V
   22:	goto	41
   25:	aload_0
   26:	invokevirtual	#374; //Method lastEntry:()Lscala/collection/mutable/LinkedEntry;
   29:	aload_1
   30:	invokevirtual	#354; //Method scala/collection/mutable/LinkedEntry.later_$eq:(Lscala/collection/mutable/LinkedEntry;)V
   33:	aload_1
   34:	aload_0
   35:	invokevirtual	#374; //Method lastEntry:()Lscala/collection/mutable/LinkedEntry;
   38:	invokevirtual	#360; //Method scala/collection/mutable/LinkedEntry.earlier_$eq:(Lscala/collection/mutable/LinkedEntry;)V
   41:	aload_0
   42:	aload_1
   43:	invokevirtual	#357; //Method lastEntry_$eq:(Lscala/collection/mutable/LinkedEntry;)V
   46:	return
  LineNumberTable: 
   line 66: 0
   line 67: 25
   line 68: 41

  LocalVariableTable: 
   Start  Length  Slot  Name   Signature
   0      47      0    this       Lscala/collection/mutable/LinkedHashMap;
   0      47      1    e       Lscala/collection/mutable/LinkedEntry;


public scala.Option put(java.lang.Object, java.lang.Object);
  Code:
   Stack=4, Locals=6, Args_size=3
   0:	aload_0
   1:	aload_1
   2:	invokeinterface	#377,  2; //InterfaceMethod scala/collection/mutable/HashTable.findEntry:(Ljava/lang/Object;)Lscala/collection/mutable/HashEntry;
   7:	checkcast	#287; //class scala/collection/mutable/LinkedEntry
   10:	astore	4
   12:	aload	4
   14:	dup
   15:	pop
   16:	ifnull	28
   19:	aload	4
   21:	aconst_null
   22:	invokevirtual	#372; //Method java/lang/Object.equals:(Ljava/lang/Object;)Z
   25:	ifeq	56
   28:	new	#287; //class scala/collection/mutable/LinkedEntry
   31:	dup
   32:	aload_1
   33:	aload_2
   34:	invokespecial	#378; //Method scala/collection/mutable/LinkedEntry."<init>":(Ljava/lang/Object;Ljava/lang/Object;)V
   37:	astore_3
   38:	aload_0
   39:	aload_3
   40:	invokeinterface	#382,  2; //InterfaceMethod scala/collection/mutable/HashTable.addEntry:(Lscala/collection/mutable/HashEntry;)V
   45:	aload_0
   46:	aload_3
   47:	invokevirtual	#384; //Method scala$collection$mutable$LinkedHashMap$$updateLinkedEntries:(Lscala/collection/mutable/LinkedEntry;)V
   50:	getstatic	#348; //Field scala/None$.MODULE$:Lscala/None$;
   53:	goto	78
   56:	aload	4
   58:	getfield	#291; //Field scala/collection/mutable/LinkedEntry.value:Ljava/lang/Object;
   61:	astore	5
   63:	aload	4
   65:	aload_2
   66:	putfield	#291; //Field scala/collection/mutable/LinkedEntry.value:Ljava/lang/Object;
   69:	new	#362; //class scala/Some
   72:	dup
   73:	aload	5
   75:	invokespecial	#365; //Method scala/Some."<init>":(Ljava/lang/Object;)V
   78:	areturn
  LineNumberTable: 
   line 52: 0
   line 53: 12
   line 54: 28
   line 55: 38
   line 56: 39
   line 55: 40
   line 56: 45
   line 57: 50
   line 59: 56
   line 60: 63
   line 61: 69
   line 51: 78

  LocalVariableTable: 
   Start  Length  Slot  Name   Signature
   0      79      0    this       Lscala/collection/mutable/LinkedHashMap;
   0      79      1    key       Ljava/lang/Object;
   0      79      2    value       Ljava/lang/Object;
   38      15      3    e       Lscala/collection/mutable/LinkedEntry;
   12      67      4    e       Lscala/collection/mutable/LinkedEntry;
   63      15      5    v       Ljava/lang/Object;

  Signature: length = 0x2
   01 FFFFFF82 

public scala.Option get(java.lang.Object);
  Code:
   Stack=3, Locals=3, Args_size=2
   0:	aload_0
   1:	aload_1
   2:	invokeinterface	#377,  2; //InterfaceMethod scala/collection/mutable/HashTable.findEntry:(Ljava/lang/Object;)Lscala/collection/mutable/HashEntry;
   7:	checkcast	#287; //class scala/collection/mutable/LinkedEntry
   10:	astore_2
   11:	aload_2
   12:	dup
   13:	pop
   14:	ifnull	25
   17:	aload_2
   18:	aconst_null
   19:	invokevirtual	#372; //Method java/lang/Object.equals:(Ljava/lang/Object;)Z
   22:	ifeq	31
   25:	getstatic	#348; //Field scala/None$.MODULE$:Lscala/None$;
   28:	goto	42
   31:	new	#362; //class scala/Some
   34:	dup
   35:	aload_2
   36:	getfield	#291; //Field scala/collection/mutable/LinkedEntry.value:Ljava/lang/Object;
   39:	invokespecial	#365; //Method scala/Some."<init>":(Ljava/lang/Object;)V
   42:	areturn
  LineNumberTable: 
   line 46: 0
   line 47: 11
   line 48: 31
   line 45: 42

  LocalVariableTable: 
   Start  Length  Slot  Name   Signature
   0      43      0    this       Lscala/collection/mutable/LinkedHashMap;
   0      43      1    key       Ljava/lang/Object;
   11      32      2    e       Lscala/collection/mutable/LinkedEntry;

  Signature: length = 0x2
   01 6F 

public void lastEntry_$eq(scala.collection.mutable.LinkedEntry);
  Code:
   Stack=2, Locals=2, Args_size=2
   0:	aload_0
   1:	aload_1
   2:	putfield	#133; //Field lastEntry:Lscala/collection/mutable/LinkedEntry;
   5:	return
  LineNumberTable: 
   line 43: 0

  Signature: length = 0x2
   01 FFFFFF84 

public scala.collection.mutable.LinkedEntry lastEntry();
  Code:
   Stack=1, Locals=1, Args_size=1
   0:	aload_0
   1:	getfield	#133; //Field lastEntry:Lscala/collection/mutable/LinkedEntry;
   4:	areturn
  LineNumberTable: 
   line 43: 0

  Signature: length = 0x2
   01 FFFFFF85 

public void firstEntry_$eq(scala.collection.mutable.LinkedEntry);
  Code:
   Stack=2, Locals=2, Args_size=2
   0:	aload_0
   1:	aload_1
   2:	putfield	#131; //Field firstEntry:Lscala/collection/mutable/LinkedEntry;
   5:	return
  LineNumberTable: 
   line 42: 0

  Signature: length = 0x2
   01 FFFFFF84 

public scala.collection.mutable.LinkedEntry firstEntry();
  Code:
   Stack=1, Locals=1, Args_size=1
   0:	aload_0
   1:	getfield	#131; //Field firstEntry:Lscala/collection/mutable/LinkedEntry;
   4:	areturn
  LineNumberTable: 
   line 42: 0

  Signature: length = 0x2
   01 FFFFFF85 

public int size();
  Code:
   Stack=1, Locals=1, Args_size=1
   0:	aload_0
   1:	invokeinterface	#393,  1; //InterfaceMethod scala/collection/mutable/HashTable.tableSize:()I
   6:	ireturn
  LineNumberTable: 
   line 38: 0


public scala.collection.mutable.LinkedHashMap empty();
  Code:
   Stack=1, Locals=1, Args_size=1
   0:	getstatic	#398; //Field scala/collection/mutable/LinkedHashMap$.MODULE$:Lscala/collection/mutable/LinkedHashMap$;
   3:	invokevirtual	#399; //Method scala/collection/mutable/LinkedHashMap$.empty:()Lscala/collection/mutable/LinkedHashMap;
   6:	areturn
  LineNumberTable: 
   line 37: 0

  Signature: length = 0x2
   01 FFFFFF90 

public scala.collection.TraversableLike$WithFilter withFilter(scala.Function1);
  Code:
   Stack=2, Locals=2, Args_size=2
   0:	aload_0
   1:	aload_1
   2:	invokestatic	#405; //Method scala/collection/TraversableLike$class.withFilter:(Lscala/collection/TraversableLike;Lscala/Function1;)Lscala/collection/TraversableLike$WithFilter;
   5:	areturn
  LineNumberTable: 
   line 33: 0

  LocalVariableTable: 
   Start  Length  Slot  Name   Signature
   0      6      0    this       Lscala/collection/mutable/LinkedHashMap;
   0      6      1    p       Lscala/Function1;

  Signature: length = 0x2
   01 FFFFFF92 

public scala.collection.mutable.StringBuilder addString(scala.collection.mutable.StringBuilder);
  Code:
   Stack=2, Locals=2, Args_size=2
   0:	aload_0
   1:	aload_1
   2:	invokestatic	#411; //Method scala/collection/TraversableLike$class.addString:(Lscala/collection/TraversableLike;Lscala/collection/mutable/StringBuilder;)Lscala/collection/mutable/StringBuilder;
   5:	areturn
  LineNumberTable: 
   line 33: 0

  LocalVariableTable: 
   Start  Length  Slot  Name   Signature
   0      6      0    this       Lscala/collection/mutable/LinkedHashMap;
   0      6      1    b       Lscala/collection/mutable/StringBuilder;


public scala.collection.mutable.StringBuilder addString(scala.collection.mutable.StringBuilder, java.lang.String);
  Code:
   Stack=3, Locals=3, Args_size=3
   0:	aload_0
   1:	aload_1
   2:	aload_2
   3:	invokestatic	#417; //Method scala/collection/TraversableLike$class.addString:(Lscala/collection/TraversableLike;Lscala/collection/mutable/StringBuilder;Ljava/lang/String;)Lscala/collection/mutable/StringBuilder;
   6:	areturn
  LineNumberTable: 
   line 33: 0

  LocalVariableTable: 
   Start  Length  Slot  Name   Signature
   0      7      0    this       Lscala/collection/mutable/LinkedHashMap;
   0      7      1    b       Lscala/collection/mutable/StringBuilder;
   0      7      2    sep       Ljava/lang/String;


public java.lang.String mkString();
  Code:
   Stack=1, Locals=1, Args_size=1
   0:	aload_0
   1:	invokestatic	#424; //Method scala/collection/TraversableLike$class.mkString:(Lscala/collection/TraversableLike;)Ljava/lang/String;
   4:	areturn
  LineNumberTable: 
   line 33: 0


public java.lang.String mkString(java.lang.String);
  Code:
   Stack=2, Locals=2, Args_size=2
   0:	aload_0
   1:	aload_1
   2:	invokestatic	#428; //Method scala/collection/TraversableLike$class.mkString:(Lscala/collection/TraversableLike;Ljava/lang/String;)Ljava/lang/String;
   5:	areturn
  LineNumberTable: 
   line 33: 0

  LocalVariableTable: 
   Start  Length  Slot  Name   Signature
   0      6      0    this       Lscala/collection/mutable/LinkedHashMap;
   0      6      1    sep       Ljava/lang/String;


public java.lang.String mkString(java.lang.String, java.lang.String, java.lang.String);
  Code:
   Stack=4, Locals=4, Args_size=4
   0:	aload_0
   1:	aload_1
   2:	aload_2
   3:	aload_3
   4:	invokestatic	#432; //Method scala/collection/TraversableLike$class.mkString:(Lscala/collection/TraversableLike;Ljava/lang/String;Ljava/lang/String;Ljava/lang/String;)Ljava/lang/String;
   7:	areturn
  LineNumberTable: 
   line 33: 0

  LocalVariableTable: 
   Start  Length  Slot  Name   Signature
   0      8      0    this       Lscala/collection/mutable/LinkedHashMap;
   0      8      1    start       Ljava/lang/String;
   0      8      2    sep       Ljava/lang/String;
   0      8      3    end       Ljava/lang/String;


public scala.collection.immutable.Set toSet();
  Code:
   Stack=1, Locals=1, Args_size=1
   0:	aload_0
   1:	invokestatic	#439; //Method scala/collection/TraversableLike$class.toSet:(Lscala/collection/TraversableLike;)Lscala/collection/immutable/Set;
   4:	areturn
  LineNumberTable: 
   line 33: 0


public scala.collection.mutable.IndexedSeq toIndexedSeq();
  Code:
   Stack=1, Locals=1, Args_size=1
   0:	aload_0
   1:	invokestatic	#444; //Method scala/collection/TraversableLike$class.toIndexedSeq:(Lscala/collection/TraversableLike;)Lscala/collection/mutable/IndexedSeq;
   4:	areturn
  LineNumberTable: 
   line 33: 0


public scala.collection.Seq toSeq();
  Code:
   Stack=1, Locals=1, Args_size=1
   0:	aload_0
   1:	invokestatic	#449; //Method scala/collection/TraversableLike$class.toSeq:(Lscala/collection/TraversableLike;)Lscala/collection/Seq;
   4:	areturn
  LineNumberTable: 
   line 33: 0


public scala.collection.immutable.List toList();
  Code:
   Stack=1, Locals=1, Args_size=1
   0:	aload_0
   1:	invokestatic	#454; //Method scala/collection/TraversableLike$class.toList:(Lscala/collection/TraversableLike;)Lscala/collection/immutable/List;
   4:	areturn
  LineNumberTable: 
   line 33: 0


public java.lang.Object toArray(scala.reflect.ClassManifest);
  Code:
   Stack=2, Locals=2, Args_size=2
   0:	aload_0
   1:	aload_1
   2:	invokestatic	#459; //Method scala/collection/TraversableLike$class.toArray:(Lscala/collection/TraversableLike;Lscala/reflect/ClassManifest;)Ljava/lang/Object;
   5:	areturn
  LineNumberTable: 
   line 33: 0

  LocalVariableTable: 
   Start  Length  Slot  Name   Signature
   0      6      0    this       Lscala/collection/mutable/LinkedHashMap;
   0      6      1    evidence$1       Lscala/reflect/ClassManifest;


public void copyToArray(java.lang.Object);
  Code:
   Stack=2, Locals=2, Args_size=2
   0:	aload_0
   1:	aload_1
   2:	invokestatic	#465; //Method scala/collection/TraversableLike$class.copyToArray:(Lscala/collection/TraversableLike;Ljava/lang/Object;)V
   5:	return
  LineNumberTable: 
   line 33: 0

  LocalVariableTable: 
   Start  Length  Slot  Name   Signature
   0      6      0    this       Lscala/collection/mutable/LinkedHashMap;
   0      6      1    xs       Ljava/lang/Object;


public void copyToArray(java.lang.Object, int);
  Code:
   Stack=3, Locals=3, Args_size=3
   0:	aload_0
   1:	aload_1
   2:	iload_2
   3:	invokestatic	#470; //Method scala/collection/TraversableLike$class.copyToArray:(Lscala/collection/TraversableLike;Ljava/lang/Object;I)V
   6:	return
  LineNumberTable: 
   line 33: 0

  LocalVariableTable: 
   Start  Length  Slot  Name   Signature
   0      7      0    this       Lscala/collection/mutable/LinkedHashMap;
   0      7      1    xs       Ljava/lang/Object;
   0      7      2    start       I


public void copyToBuffer(scala.collection.mutable.Buffer);
  Code:
   Stack=2, Locals=2, Args_size=2
   0:	aload_0
   1:	aload_1
   2:	invokestatic	#475; //Method scala/collection/TraversableLike$class.copyToBuffer:(Lscala/collection/TraversableLike;Lscala/collection/mutable/Buffer;)V
   5:	return
  LineNumberTable: 
   line 33: 0

  LocalVariableTable: 
   Start  Length  Slot  Name   Signature
   0      6      0    this       Lscala/collection/mutable/LinkedHashMap;
   0      6      1    dest       Lscala/collection/mutable/Buffer;


public scala.Tuple2 splitAt(int);
  Code:
   Stack=2, Locals=2, Args_size=2
   0:	aload_0
   1:	iload_1
   2:	invokestatic	#482; //Method scala/collection/TraversableLike$class.splitAt:(Lscala/collection/TraversableLike;I)Lscala/Tuple2;
   5:	areturn
  LineNumberTable: 
   line 33: 0

  LocalVariableTable: 
   Start  Length  Slot  Name   Signature
   0      6      0    this       Lscala/collection/mutable/LinkedHashMap;
   0      6      1    n       I


public scala.Tuple2 span(scala.Function1);
  Code:
   Stack=2, Locals=2, Args_size=2
   0:	aload_0
   1:	aload_1
   2:	invokestatic	#488; //Method scala/collection/TraversableLike$class.span:(Lscala/collection/TraversableLike;Lscala/Function1;)Lscala/Tuple2;
   5:	areturn
  LineNumberTable: 
   line 33: 0

  LocalVariableTable: 
   Start  Length  Slot  Name   Signature
   0      6      0    this       Lscala/collection/mutable/LinkedHashMap;
   0      6      1    p       Lscala/Function1;


public java.lang.Object dropWhile(scala.Function1);
  Code:
   Stack=2, Locals=2, Args_size=2
   0:	aload_0
   1:	aload_1
   2:	invokestatic	#493; //Method scala/collection/TraversableLike$class.dropWhile:(Lscala/collection/TraversableLike;Lscala/Function1;)Ljava/lang/Object;
   5:	areturn
  LineNumberTable: 
   line 33: 0

  LocalVariableTable: 
   Start  Length  Slot  Name   Signature
   0      6      0    this       Lscala/collection/mutable/LinkedHashMap;
   0      6      1    p       Lscala/Function1;


public java.lang.Object drop(int);
  Code:
   Stack=2, Locals=2, Args_size=2
   0:	aload_0
   1:	iload_1
   2:	invokestatic	#498; //Method scala/collection/TraversableLike$class.drop:(Lscala/collection/TraversableLike;I)Ljava/lang/Object;
   5:	areturn
  LineNumberTable: 
   line 33: 0

  LocalVariableTable: 
   Start  Length  Slot  Name   Signature
   0      6      0    this       Lscala/collection/mutable/LinkedHashMap;
   0      6      1    n       I


public java.lang.Object init();
  Code:
   Stack=1, Locals=1, Args_size=1
   0:	aload_0
   1:	invokestatic	#501; //Method scala/collection/TraversableLike$class.init:(Lscala/collection/TraversableLike;)Ljava/lang/Object;
   4:	areturn
  LineNumberTable: 
   line 33: 0


public scala.Option lastOption();
  Code:
   Stack=1, Locals=1, Args_size=1
   0:	aload_0
   1:	invokestatic	#506; //Method scala/collection/TraversableLike$class.lastOption:(Lscala/collection/TraversableLike;)Lscala/Option;
   4:	areturn
  LineNumberTable: 
   line 33: 0


public java.lang.Object last();
  Code:
   Stack=1, Locals=1, Args_size=1
   0:	aload_0
   1:	invokestatic	#509; //Method scala/collection/TraversableLike$class.last:(Lscala/collection/TraversableLike;)Ljava/lang/Object;
   4:	areturn
  LineNumberTable: 
   line 33: 0


public java.lang.Object tail();
  Code:
   Stack=1, Locals=1, Args_size=1
   0:	aload_0
   1:	invokestatic	#512; //Method scala/collection/TraversableLike$class.tail:(Lscala/collection/TraversableLike;)Ljava/lang/Object;
   4:	areturn
  LineNumberTable: 
   line 33: 0


public scala.Option headOption();
  Code:
   Stack=1, Locals=1, Args_size=1
   0:	aload_0
   1:	invokestatic	#515; //Method scala/collection/TraversableLike$class.headOption:(Lscala/collection/TraversableLike;)Lscala/Option;
   4:	areturn
  LineNumberTable: 
   line 33: 0


public java.lang.Object max(scala.math.Ordering);
  Code:
   Stack=2, Locals=2, Args_size=2
   0:	aload_0
   1:	aload_1
   2:	invokestatic	#520; //Method scala/collection/TraversableLike$class.max:(Lscala/collection/TraversableLike;Lscala/math/Ordering;)Ljava/lang/Object;
   5:	areturn
  LineNumberTable: 
   line 33: 0

  LocalVariableTable: 
   Start  Length  Slot  Name   Signature
   0      6      0    this       Lscala/collection/mutable/LinkedHashMap;
   0      6      1    cmp       Lscala/math/Ordering;


public java.lang.Object min(scala.math.Ordering);
  Code:
   Stack=2, Locals=2, Args_size=2
   0:	aload_0
   1:	aload_1
   2:	invokestatic	#525; //Method scala/collection/TraversableLike$class.min:(Lscala/collection/TraversableLike;Lscala/math/Ordering;)Ljava/lang/Object;
   5:	areturn
  LineNumberTable: 
   line 33: 0

  LocalVariableTable: 
   Start  Length  Slot  Name   Signature
   0      6      0    this       Lscala/collection/mutable/LinkedHashMap;
   0      6      1    cmp       Lscala/math/Ordering;


public java.lang.Object product(scala.math.Numeric);
  Code:
   Stack=2, Locals=2, Args_size=2
   0:	aload_0
   1:	aload_1
   2:	invokestatic	#530; //Method scala/collection/TraversableLike$class.product:(Lscala/collection/TraversableLike;Lscala/math/Numeric;)Ljava/lang/Object;
   5:	areturn
  LineNumberTable: 
   line 33: 0

  LocalVariableTable: 
   Start  Length  Slot  Name   Signature
   0      6      0    this       Lscala/collection/mutable/LinkedHashMap;
   0      6      1    num       Lscala/math/Numeric;


public java.lang.Object sum(scala.math.Numeric);
  Code:
   Stack=2, Locals=2, Args_size=2
   0:	aload_0
   1:	aload_1
   2:	invokestatic	#535; //Method scala/collection/TraversableLike$class.sum:(Lscala/collection/TraversableLike;Lscala/math/Numeric;)Ljava/lang/Object;
   5:	areturn
  LineNumberTable: 
   line 33: 0

  LocalVariableTable: 
   Start  Length  Slot  Name   Signature
   0      6      0    this       Lscala/collection/mutable/LinkedHashMap;
   0      6      1    num       Lscala/math/Numeric;


public scala.Option reduceRightOption(scala.Function2);
  Code:
   Stack=2, Locals=2, Args_size=2
   0:	aload_0
   1:	aload_1
   2:	invokestatic	#540; //Method scala/collection/TraversableLike$class.reduceRightOption:(Lscala/collection/TraversableLike;Lscala/Function2;)Lscala/Option;
   5:	areturn
  LineNumberTable: 
   line 33: 0

  LocalVariableTable: 
   Start  Length  Slot  Name   Signature
   0      6      0    this       Lscala/collection/mutable/LinkedHashMap;
   0      6      1    op       Lscala/Function2;


public scala.Option reduceLeftOption(scala.Function2);
  Code:
   Stack=2, Locals=2, Args_size=2
   0:	aload_0
   1:	aload_1
   2:	invokestatic	#545; //Method scala/collection/TraversableLike$class.reduceLeftOption:(Lscala/collection/TraversableLike;Lscala/Function2;)Lscala/Option;
   5:	areturn
  LineNumberTable: 
   line 33: 0

  LocalVariableTable: 
   Start  Length  Slot  Name   Signature
   0      6      0    this       Lscala/collection/mutable/LinkedHashMap;
   0      6      1    op       Lscala/Function2;


public java.lang.Object reduceLeft(scala.Function2);
  Code:
   Stack=2, Locals=2, Args_size=2
   0:	aload_0
   1:	aload_1
   2:	invokestatic	#550; //Method scala/collection/TraversableLike$class.reduceLeft:(Lscala/collection/TraversableLike;Lscala/Function2;)Ljava/lang/Object;
   5:	areturn
  LineNumberTable: 
   line 33: 0

  LocalVariableTable: 
   Start  Length  Slot  Name   Signature
   0      6      0    this       Lscala/collection/mutable/LinkedHashMap;
   0      6      1    op       Lscala/Function2;


public java.lang.Object $colon$bslash(java.lang.Object, scala.Function2);
  Code:
   Stack=3, Locals=3, Args_size=3
   0:	aload_0
   1:	aload_1
   2:	aload_2
   3:	invokestatic	#555; //Method scala/collection/TraversableLike$class.$colon$bslash:(Lscala/collection/TraversableLike;Ljava/lang/Object;Lscala/Function2;)Ljava/lang/Object;
   6:	areturn
  LineNumberTable: 
   line 33: 0

  LocalVariableTable: 
   Start  Length  Slot  Name   Signature
   0      7      0    this       Lscala/collection/mutable/LinkedHashMap;
   0      7      1    z       Ljava/lang/Object;
   0      7      2    op       Lscala/Function2;


public java.lang.Object $div$colon(java.lang.Object, scala.Function2);
  Code:
   Stack=3, Locals=3, Args_size=3
   0:	aload_0
   1:	aload_1
   2:	aload_2
   3:	invokestatic	#559; //Method scala/collection/TraversableLike$class.$div$colon:(Lscala/collection/TraversableLike;Ljava/lang/Object;Lscala/Function2;)Ljava/lang/Object;
   6:	areturn
  LineNumberTable: 
   line 33: 0

  LocalVariableTable: 
   Start  Length  Slot  Name   Signature
   0      7      0    this       Lscala/collection/mutable/LinkedHashMap;
   0      7      1    z       Ljava/lang/Object;
   0      7      2    op       Lscala/Function2;


public java.lang.Object foldLeft(java.lang.Object, scala.Function2);
  Code:
   Stack=3, Locals=3, Args_size=3
   0:	aload_0
   1:	aload_1
   2:	aload_2
   3:	invokestatic	#562; //Method scala/collection/TraversableLike$class.foldLeft:(Lscala/collection/TraversableLike;Ljava/lang/Object;Lscala/Function2;)Ljava/lang/Object;
   6:	areturn
  LineNumberTable: 
   line 33: 0

  LocalVariableTable: 
   Start  Length  Slot  Name   Signature
   0      7      0    this       Lscala/collection/mutable/LinkedHashMap;
   0      7      1    z       Ljava/lang/Object;
   0      7      2    op       Lscala/Function2;


public int count(scala.Function1);
  Code:
   Stack=2, Locals=2, Args_size=2
   0:	aload_0
   1:	aload_1
   2:	invokestatic	#567; //Method scala/collection/TraversableLike$class.count:(Lscala/collection/TraversableLike;Lscala/Function1;)I
   5:	ireturn
  LineNumberTable: 
   line 33: 0

  LocalVariableTable: 
   Start  Length  Slot  Name   Signature
   0      6      0    this       Lscala/collection/mutable/LinkedHashMap;
   0      6      1    p       Lscala/Function1;


public scala.collection.Map groupBy(scala.Function1);
  Code:
   Stack=2, Locals=2, Args_size=2
   0:	aload_0
   1:	aload_1
   2:	invokestatic	#572; //Method scala/collection/TraversableLike$class.groupBy:(Lscala/collection/TraversableLike;Lscala/Function1;)Lscala/collection/Map;
   5:	areturn
  LineNumberTable: 
   line 33: 0

  LocalVariableTable: 
   Start  Length  Slot  Name   Signature
   0      6      0    this       Lscala/collection/mutable/LinkedHashMap;
   0      6      1    f       Lscala/Function1;


public scala.Tuple2 partition(scala.Function1);
  Code:
   Stack=2, Locals=2, Args_size=2
   0:	aload_0
   1:	aload_1
   2:	invokestatic	#575; //Method scala/collection/TraversableLike$class.partition:(Lscala/collection/TraversableLike;Lscala/Function1;)Lscala/Tuple2;
   5:	areturn
  LineNumberTable: 
   line 33: 0

  LocalVariableTable: 
   Start  Length  Slot  Name   Signature
   0      6      0    this       Lscala/collection/mutable/LinkedHashMap;
   0      6      1    p       Lscala/Function1;


public java.lang.Object partialMap(scala.PartialFunction, scala.collection.generic.CanBuildFrom);
  Code:
   Stack=3, Locals=3, Args_size=3
   0:	aload_0
   1:	aload_1
   2:	aload_2
   3:	invokestatic	#580; //Method scala/collection/TraversableLike$class.partialMap:(Lscala/collection/TraversableLike;Lscala/PartialFunction;Lscala/collection/generic/CanBuildFrom;)Ljava/lang/Object;
   6:	areturn
  LineNumberTable: 
   line 33: 0

  LocalVariableTable: 
   Start  Length  Slot  Name   Signature
   0      7      0    this       Lscala/collection/mutable/LinkedHashMap;
   0      7      1    pf       Lscala/PartialFunction;
   0      7      2    bf       Lscala/collection/generic/CanBuildFrom;


public java.lang.Object filterNot(scala.Function1);
  Code:
   Stack=2, Locals=2, Args_size=2
   0:	aload_0
   1:	aload_1
   2:	invokestatic	#587; //Method scala/collection/TraversableLike$class.filterNot:(Lscala/collection/TraversableLike;Lscala/Function1;)Ljava/lang/Object;
   5:	areturn
  LineNumberTable: 
   line 33: 0

  LocalVariableTable: 
   Start  Length  Slot  Name   Signature
   0      6      0    this       Lscala/collection/mutable/LinkedHashMap;
   0      6      1    p       Lscala/Function1;


public java.lang.Object filter(scala.Function1);
  Code:
   Stack=2, Locals=2, Args_size=2
   0:	aload_0
   1:	aload_1
   2:	invokestatic	#590; //Method scala/collection/TraversableLike$class.filter:(Lscala/collection/TraversableLike;Lscala/Function1;)Ljava/lang/Object;
   5:	areturn
  LineNumberTable: 
   line 33: 0

  LocalVariableTable: 
   Start  Length  Slot  Name   Signature
   0      6      0    this       Lscala/collection/mutable/LinkedHashMap;
   0      6      1    p       Lscala/Function1;


public java.lang.Object flatMap(scala.Function1, scala.collection.generic.CanBuildFrom);
  Code:
   Stack=3, Locals=3, Args_size=3
   0:	aload_0
   1:	aload_1
   2:	aload_2
   3:	invokestatic	#595; //Method scala/collection/TraversableLike$class.flatMap:(Lscala/collection/TraversableLike;Lscala/Function1;Lscala/collection/generic/CanBuildFrom;)Ljava/lang/Object;
   6:	areturn
  LineNumberTable: 
   line 33: 0

  LocalVariableTable: 
   Start  Length  Slot  Name   Signature
   0      7      0    this       Lscala/collection/mutable/LinkedHashMap;
   0      7      1    f       Lscala/Function1;
   0      7      2    bf       Lscala/collection/generic/CanBuildFrom;


public java.lang.Object map(scala.Function1, scala.collection.generic.CanBuildFrom);
  Code:
   Stack=3, Locals=3, Args_size=3
   0:	aload_0
   1:	aload_1
   2:	aload_2
   3:	invokestatic	#598; //Method scala/collection/TraversableLike$class.map:(Lscala/collection/TraversableLike;Lscala/Function1;Lscala/collection/generic/CanBuildFrom;)Ljava/lang/Object;
   6:	areturn
  LineNumberTable: 
   line 33: 0

  LocalVariableTable: 
   Start  Length  Slot  Name   Signature
   0      7      0    this       Lscala/collection/mutable/LinkedHashMap;
   0      7      1    f       Lscala/Function1;
   0      7      2    bf       Lscala/collection/generic/CanBuildFrom;


public java.lang.Object $plus$plus(scala.collection.Iterator, scala.collection.generic.CanBuildFrom);
  Code:
   Stack=3, Locals=3, Args_size=3
   0:	aload_0
   1:	aload_1
   2:	aload_2
   3:	invokestatic	#603; //Method scala/collection/TraversableLike$class.$plus$plus:(Lscala/collection/TraversableLike;Lscala/collection/Iterator;Lscala/collection/generic/CanBuildFrom;)Ljava/lang/Object;
   6:	areturn
  LineNumberTable: 
   line 33: 0

  LocalVariableTable: 
   Start  Length  Slot  Name   Signature
   0      7      0    this       Lscala/collection/mutable/LinkedHashMap;
   0      7      1    that       Lscala/collection/Iterator;
   0      7      2    bf       Lscala/collection/generic/CanBuildFrom;


public java.lang.Object $plus$plus(scala.collection.Traversable, scala.collection.generic.CanBuildFrom);
  Code:
   Stack=3, Locals=3, Args_size=3
   0:	aload_0
   1:	aload_1
   2:	aload_2
   3:	invokestatic	#608; //Method scala/collection/TraversableLike$class.$plus$plus:(Lscala/collection/TraversableLike;Lscala/collection/Traversable;Lscala/collection/generic/CanBuildFrom;)Ljava/lang/Object;
   6:	areturn
  LineNumberTable: 
   line 33: 0

  LocalVariableTable: 
   Start  Length  Slot  Name   Signature
   0      7      0    this       Lscala/collection/mutable/LinkedHashMap;
   0      7      1    that       Lscala/collection/Traversable;
   0      7      2    bf       Lscala/collection/generic/CanBuildFrom;


public boolean hasDefiniteSize();
  Code:
   Stack=1, Locals=1, Args_size=1
   0:	aload_0
   1:	invokestatic	#613; //Method scala/collection/TraversableLike$class.hasDefiniteSize:(Lscala/collection/TraversableLike;)Z
   4:	ireturn
  LineNumberTable: 
   line 33: 0


public boolean nonEmpty();
  Code:
   Stack=1, Locals=1, Args_size=1
   0:	aload_0
   1:	invokestatic	#616; //Method scala/collection/TraversableLike$class.nonEmpty:(Lscala/collection/TraversableLike;)Z
   4:	ireturn
  LineNumberTable: 
   line 33: 0


public java.lang.Object repr();
  Code:
   Stack=1, Locals=1, Args_size=1
   0:	aload_0
   1:	invokestatic	#618; //Method scala/collection/TraversableLike$class.repr:(Lscala/collection/TraversableLike;)Ljava/lang/Object;
   4:	areturn
  LineNumberTable: 
   line 33: 0


public scala.collection.Traversable transpose(scala.Function1);
  Code:
   Stack=2, Locals=2, Args_size=2
   0:	aload_0
   1:	aload_1
   2:	invokestatic	#623; //Method scala/collection/generic/GenericTraversableTemplate$class.transpose:(Lscala/collection/generic/GenericTraversableTemplate;Lscala/Function1;)Lscala/collection/Traversable;
   5:	areturn
  LineNumberTable: 
   line 33: 0

  LocalVariableTable: 
   Start  Length  Slot  Name   Signature
   0      6      0    this       Lscala/collection/mutable/LinkedHashMap;
   0      6      1    asTraversable       Lscala/Function1;


public scala.collection.Traversable flatten(scala.Function1);
  Code:
   Stack=2, Locals=2, Args_size=2
   0:	aload_0
   1:	aload_1
   2:	invokestatic	#627; //Method scala/collection/generic/GenericTraversableTemplate$class.flatten:(Lscala/collection/generic/GenericTraversableTemplate;Lscala/Function1;)Lscala/collection/Traversable;
   5:	areturn
  LineNumberTable: 
   line 33: 0

  LocalVariableTable: 
   Start  Length  Slot  Name   Signature
   0      6      0    this       Lscala/collection/mutable/LinkedHashMap;
   0      6      1    asTraversable       Lscala/Function1;


public scala.Tuple2 unzip(scala.Function1);
  Code:
   Stack=2, Locals=2, Args_size=2
   0:	aload_0
   1:	aload_1
   2:	invokestatic	#631; //Method scala/collection/generic/GenericTraversableTemplate$class.unzip:(Lscala/collection/generic/GenericTraversableTemplate;Lscala/Function1;)Lscala/Tuple2;
   5:	areturn
  LineNumberTable: 
   line 33: 0

  LocalVariableTable: 
   Start  Length  Slot  Name   Signature
   0      6      0    this       Lscala/collection/mutable/LinkedHashMap;
   0      6      1    asPair       Lscala/Function1;


public scala.collection.mutable.Builder genericBuilder();
  Code:
   Stack=1, Locals=1, Args_size=1
   0:	aload_0
   1:	invokestatic	#637; //Method scala/collection/generic/GenericTraversableTemplate$class.genericBuilder:(Lscala/collection/generic/GenericTraversableTemplate;)Lscala/collection/mutable/Builder;
   4:	areturn
  LineNumberTable: 
   line 33: 0


public java.lang.Object projection();
  Code:
   Stack=1, Locals=1, Args_size=1
   0:	aload_0
   1:	invokestatic	#641; //Method scala/collection/IterableLike$class.projection:(Lscala/collection/IterableLike;)Ljava/lang/Object;
   4:	areturn
  LineNumberTable: 
   line 33: 0

  Deprecated: true

public scala.Option firstOption();
  Code:
   Stack=1, Locals=1, Args_size=1
   0:	aload_0
   1:	invokestatic	#646; //Method scala/collection/IterableLike$class.firstOption:(Lscala/collection/IterableLike;)Lscala/Option;
   4:	areturn
  LineNumberTable: 
   line 33: 0

  Deprecated: true

public java.lang.Object first();
  Code:
   Stack=1, Locals=1, Args_size=1
   0:	aload_0
   1:	invokestatic	#649; //Method scala/collection/IterableLike$class.first:(Lscala/collection/IterableLike;)Ljava/lang/Object;
   4:	areturn
  LineNumberTable: 
   line 33: 0

  Deprecated: true

public scala.collection.IterableView view(int, int);
  Code:
   Stack=3, Locals=3, Args_size=3
   0:	aload_0
   1:	iload_1
   2:	iload_2
   3:	invokestatic	#652; //Method scala/collection/IterableLike$class.view:(Lscala/collection/IterableLike;II)Lscala/collection/IterableView;
   6:	areturn
  LineNumberTable: 
   line 33: 0

  LocalVariableTable: 
   Start  Length  Slot  Name   Signature
   0      7      0    this       Lscala/collection/mutable/LinkedHashMap;
   0      7      1    from       I
   0      7      2    until       I


public java.lang.Object view();
  Code:
   Stack=1, Locals=1, Args_size=1
   0:	aload_0
   1:	invokestatic	#654; //Method scala/collection/IterableLike$class.view:(Lscala/collection/IterableLike;)Ljava/lang/Object;
   4:	areturn
  LineNumberTable: 
   line 33: 0


public boolean canEqual(java.lang.Object);
  Code:
   Stack=2, Locals=2, Args_size=2
   0:	aload_0
   1:	aload_1
   2:	invokestatic	#658; //Method scala/collection/IterableLike$class.canEqual:(Lscala/collection/IterableLike;Ljava/lang/Object;)Z
   5:	ireturn
  LineNumberTable: 
   line 33: 0

  LocalVariableTable: 
   Start  Length  Slot  Name   Signature
   0      6      0    this       Lscala/collection/mutable/LinkedHashMap;
   0      6      1    that       Ljava/lang/Object;


public scala.collection.immutable.Stream toStream();
  Code:
   Stack=1, Locals=1, Args_size=1
   0:	aload_0
   1:	invokestatic	#663; //Method scala/collection/IterableLike$class.toStream:(Lscala/collection/IterableLike;)Lscala/collection/immutable/Stream;
   4:	areturn
  LineNumberTable: 
   line 33: 0


public boolean sameElements(scala.collection.Iterable);
  Code:
   Stack=2, Locals=2, Args_size=2
   0:	aload_0
   1:	aload_1
   2:	invokestatic	#668; //Method scala/collection/IterableLike$class.sameElements:(Lscala/collection/IterableLike;Lscala/collection/Iterable;)Z
   5:	ireturn
  LineNumberTable: 
   line 33: 0

  LocalVariableTable: 
   Start  Length  Slot  Name   Signature
   0      6      0    this       Lscala/collection/mutable/LinkedHashMap;
   0      6      1    that       Lscala/collection/Iterable;


public java.lang.Object zipWithIndex(scala.collection.generic.CanBuildFrom);
  Code:
   Stack=2, Locals=2, Args_size=2
   0:	aload_0
   1:	aload_1
   2:	invokestatic	#674; //Method scala/collection/IterableLike$class.zipWithIndex:(Lscala/collection/IterableLike;Lscala/collection/generic/CanBuildFrom;)Ljava/lang/Object;
   5:	areturn
  LineNumberTable: 
   line 33: 0

  LocalVariableTable: 
   Start  Length  Slot  Name   Signature
   0      6      0    this       Lscala/collection/mutable/LinkedHashMap;
   0      6      1    bf       Lscala/collection/generic/CanBuildFrom;


public java.lang.Object zipAll(scala.collection.Iterable, java.lang.Object, java.lang.Object, scala.collection.generic.CanBuildFrom);
  Code:
   Stack=5, Locals=5, Args_size=5
   0:	aload_0
   1:	aload_1
   2:	aload_2
   3:	aload_3
   4:	aload	4
   6:	invokestatic	#679; //Method scala/collection/IterableLike$class.zipAll:(Lscala/collection/IterableLike;Lscala/collection/Iterable;Ljava/lang/Object;Ljava/lang/Object;Lscala/collection/generic/CanBuildFrom;)Ljava/lang/Object;
   9:	areturn
  LineNumberTable: 
   line 33: 0

  LocalVariableTable: 
   Start  Length  Slot  Name   Signature
   0      10      0    this       Lscala/collection/mutable/LinkedHashMap;
   0      10      1    that       Lscala/collection/Iterable;
   0      10      2    thisElem       Ljava/lang/Object;
   0      10      3    thatElem       Ljava/lang/Object;
   0      10      4    bf       Lscala/collection/generic/CanBuildFrom;


public java.lang.Object zip(scala.collection.Iterable, scala.collection.generic.CanBuildFrom);
  Code:
   Stack=3, Locals=3, Args_size=3
   0:	aload_0
   1:	aload_1
   2:	aload_2
   3:	invokestatic	#686; //Method scala/collection/IterableLike$class.zip:(Lscala/collection/IterableLike;Lscala/collection/Iterable;Lscala/collection/generic/CanBuildFrom;)Ljava/lang/Object;
   6:	areturn
  LineNumberTable: 
   line 33: 0

  LocalVariableTable: 
   Start  Length  Slot  Name   Signature
   0      7      0    this       Lscala/collection/mutable/LinkedHashMap;
   0      7      1    that       Lscala/collection/Iterable;
   0      7      2    bf       Lscala/collection/generic/CanBuildFrom;


public void copyToArray(java.lang.Object, int, int);
  Code:
   Stack=4, Locals=4, Args_size=4
   0:	aload_0
   1:	aload_1
   2:	iload_2
   3:	iload_3
   4:	invokestatic	#690; //Method scala/collection/IterableLike$class.copyToArray:(Lscala/collection/IterableLike;Ljava/lang/Object;II)V
   7:	return
  LineNumberTable: 
   line 33: 0

  LocalVariableTable: 
   Start  Length  Slot  Name   Signature
   0      8      0    this       Lscala/collection/mutable/LinkedHashMap;
   0      8      1    xs       Ljava/lang/Object;
   0      8      2    start       I
   0      8      3    len       I


public java.lang.Object dropRight(int);
  Code:
   Stack=2, Locals=2, Args_size=2
   0:	aload_0
   1:	iload_1
   2:	invokestatic	#695; //Method scala/collection/IterableLike$class.dropRight:(Lscala/collection/IterableLike;I)Ljava/lang/Object;
   5:	areturn
  LineNumberTable: 
   line 33: 0

  LocalVariableTable: 
   Start  Length  Slot  Name   Signature
   0      6      0    this       Lscala/collection/mutable/LinkedHashMap;
   0      6      1    n       I


public java.lang.Object takeRight(int);
  Code:
   Stack=2, Locals=2, Args_size=2
   0:	aload_0
   1:	iload_1
   2:	invokestatic	#698; //Method scala/collection/IterableLike$class.takeRight:(Lscala/collection/IterableLike;I)Ljava/lang/Object;
   5:	areturn
  LineNumberTable: 
   line 33: 0

  LocalVariableTable: 
   Start  Length  Slot  Name   Signature
   0      6      0    this       Lscala/collection/mutable/LinkedHashMap;
   0      6      1    n       I


public java.lang.Object takeWhile(scala.Function1);
  Code:
   Stack=2, Locals=2, Args_size=2
   0:	aload_0
   1:	aload_1
   2:	invokestatic	#702; //Method scala/collection/IterableLike$class.takeWhile:(Lscala/collection/IterableLike;Lscala/Function1;)Ljava/lang/Object;
   5:	areturn
  LineNumberTable: 
   line 33: 0

  LocalVariableTable: 
   Start  Length  Slot  Name   Signature
   0      6      0    this       Lscala/collection/mutable/LinkedHashMap;
   0      6      1    p       Lscala/Function1;


public java.lang.Object slice(int, int);
  Code:
   Stack=3, Locals=3, Args_size=3
   0:	aload_0
   1:	iload_1
   2:	iload_2
   3:	invokestatic	#707; //Method scala/collection/IterableLike$class.slice:(Lscala/collection/IterableLike;II)Ljava/lang/Object;
   6:	areturn
  LineNumberTable: 
   line 33: 0

  LocalVariableTable: 
   Start  Length  Slot  Name   Signature
   0      7      0    this       Lscala/collection/mutable/LinkedHashMap;
   0      7      1    from       I
   0      7      2    until       I


public java.lang.Object take(int);
  Code:
   Stack=2, Locals=2, Args_size=2
   0:	aload_0
   1:	iload_1
   2:	invokestatic	#710; //Method scala/collection/IterableLike$class.take:(Lscala/collection/IterableLike;I)Ljava/lang/Object;
   5:	areturn
  LineNumberTable: 
   line 33: 0

  LocalVariableTable: 
   Start  Length  Slot  Name   Signature
   0      6      0    this       Lscala/collection/mutable/LinkedHashMap;
   0      6      1    n       I


public java.lang.Object head();
  Code:
   Stack=1, Locals=1, Args_size=1
   0:	aload_0
   1:	invokestatic	#713; //Method scala/collection/IterableLike$class.head:(Lscala/collection/IterableLike;)Ljava/lang/Object;
   4:	areturn
  LineNumberTable: 
   line 33: 0


public scala.collection.Iterable toIterable();
  Code:
   Stack=1, Locals=1, Args_size=1
   0:	aload_0
   1:	invokestatic	#717; //Method scala/collection/IterableLike$class.toIterable:(Lscala/collection/IterableLike;)Lscala/collection/Iterable;
   4:	areturn
  LineNumberTable: 
   line 33: 0


public java.lang.Object reduceRight(scala.Function2);
  Code:
   Stack=2, Locals=2, Args_size=2
   0:	aload_0
   1:	aload_1
   2:	invokestatic	#721; //Method scala/collection/IterableLike$class.reduceRight:(Lscala/collection/IterableLike;Lscala/Function2;)Ljava/lang/Object;
   5:	areturn
  LineNumberTable: 
   line 33: 0

  LocalVariableTable: 
   Start  Length  Slot  Name   Signature
   0      6      0    this       Lscala/collection/mutable/LinkedHashMap;
   0      6      1    op       Lscala/Function2;


public java.lang.Object foldRight(java.lang.Object, scala.Function2);
  Code:
   Stack=3, Locals=3, Args_size=3
   0:	aload_0
   1:	aload_1
   2:	aload_2
   3:	invokestatic	#725; //Method scala/collection/IterableLike$class.foldRight:(Lscala/collection/IterableLike;Ljava/lang/Object;Lscala/Function2;)Ljava/lang/Object;
   6:	areturn
  LineNumberTable: 
   line 33: 0

  LocalVariableTable: 
   Start  Length  Slot  Name   Signature
   0      7      0    this       Lscala/collection/mutable/LinkedHashMap;
   0      7      1    z       Ljava/lang/Object;
   0      7      2    op       Lscala/Function2;


public scala.Option find(scala.Function1);
  Code:
   Stack=2, Locals=2, Args_size=2
   0:	aload_0
   1:	aload_1
   2:	invokestatic	#730; //Method scala/collection/IterableLike$class.find:(Lscala/collection/IterableLike;Lscala/Function1;)Lscala/Option;
   5:	areturn
  LineNumberTable: 
   line 33: 0

  LocalVariableTable: 
   Start  Length  Slot  Name   Signature
   0      6      0    this       Lscala/collection/mutable/LinkedHashMap;
   0      6      1    p       Lscala/Function1;


public boolean exists(scala.Function1);
  Code:
   Stack=2, Locals=2, Args_size=2
   0:	aload_0
   1:	aload_1
   2:	invokestatic	#735; //Method scala/collection/IterableLike$class.exists:(Lscala/collection/IterableLike;Lscala/Function1;)Z
   5:	ireturn
  LineNumberTable: 
   line 33: 0

  LocalVariableTable: 
   Start  Length  Slot  Name   Signature
   0      6      0    this       Lscala/collection/mutable/LinkedHashMap;
   0      6      1    p       Lscala/Function1;


public boolean forall(scala.Function1);
  Code:
   Stack=2, Locals=2, Args_size=2
   0:	aload_0
   1:	aload_1
   2:	invokestatic	#738; //Method scala/collection/IterableLike$class.forall:(Lscala/collection/IterableLike;Lscala/Function1;)Z
   5:	ireturn
  LineNumberTable: 
   line 33: 0

  LocalVariableTable: 
   Start  Length  Slot  Name   Signature
   0      6      0    this       Lscala/collection/mutable/LinkedHashMap;
   0      6      1    p       Lscala/Function1;


public scala.collection.Iterator elements();
  Code:
   Stack=1, Locals=1, Args_size=1
   0:	aload_0
   1:	invokestatic	#742; //Method scala/collection/IterableLike$class.elements:(Lscala/collection/IterableLike;)Lscala/collection/Iterator;
   4:	areturn
  LineNumberTable: 
   line 33: 0

  Deprecated: true

public scala.collection.Iterable toCollection(java.lang.Object);
  Code:
   Stack=2, Locals=2, Args_size=2
   0:	aload_0
   1:	aload_1
   2:	invokestatic	#745; //Method scala/collection/IterableLike$class.toCollection:(Lscala/collection/IterableLike;Ljava/lang/Object;)Lscala/collection/Iterable;
   5:	areturn
  LineNumberTable: 
   line 33: 0

  LocalVariableTable: 
   Start  Length  Slot  Name   Signature
   0      6      0    this       Lscala/collection/mutable/LinkedHashMap;
   0      6      1    repr       Ljava/lang/Object;


public scala.collection.Iterable thisCollection();
  Code:
   Stack=1, Locals=1, Args_size=1
   0:	aload_0
   1:	invokestatic	#747; //Method scala/collection/IterableLike$class.thisCollection:(Lscala/collection/IterableLike;)Lscala/collection/Iterable;
   4:	areturn
  LineNumberTable: 
   line 33: 0


public scala.collection.generic.GenericCompanion companion();
  Code:
   Stack=1, Locals=1, Args_size=1
   0:	aload_0
   1:	invokestatic	#752; //Method scala/collection/mutable/Iterable$class.companion:(Lscala/collection/mutable/Iterable;)Lscala/collection/generic/GenericCompanion;
   4:	areturn
  LineNumberTable: 
   line 33: 0


public scala.Function1 compose(scala.Function1);
  Code:
   Stack=2, Locals=2, Args_size=2
   0:	aload_0
   1:	aload_1
   2:	invokestatic	#756; //Method scala/Function1$class.compose:(Lscala/Function1;Lscala/Function1;)Lscala/Function1;
   5:	areturn
  LineNumberTable: 
   line 33: 0

  LocalVariableTable: 
   Start  Length  Slot  Name   Signature
   0      6      0    this       Lscala/collection/mutable/LinkedHashMap;
   0      6      1    g       Lscala/Function1;


public scala.Function1 lift();
  Code:
   Stack=1, Locals=1, Args_size=1
   0:	aload_0
   1:	invokestatic	#761; //Method scala/PartialFunction$class.lift:(Lscala/PartialFunction;)Lscala/Function1;
   4:	areturn
  LineNumberTable: 
   line 33: 0


public scala.PartialFunction andThen(scala.Function1);
  Code:
   Stack=2, Locals=2, Args_size=2
   0:	aload_0
   1:	aload_1
   2:	invokestatic	#764; //Method scala/PartialFunction$class.andThen:(Lscala/PartialFunction;Lscala/Function1;)Lscala/PartialFunction;
   5:	areturn
  LineNumberTable: 
   line 33: 0

  LocalVariableTable: 
   Start  Length  Slot  Name   Signature
   0      6      0    this       Lscala/collection/mutable/LinkedHashMap;
   0      6      1    k       Lscala/Function1;


public scala.PartialFunction orElse(scala.PartialFunction);
  Code:
   Stack=2, Locals=2, Args_size=2
   0:	aload_0
   1:	aload_1
   2:	invokestatic	#770; //Method scala/PartialFunction$class.orElse:(Lscala/PartialFunction;Lscala/PartialFunction;)Lscala/PartialFunction;
   5:	areturn
  LineNumberTable: 
   line 33: 0

  LocalVariableTable: 
   Start  Length  Slot  Name   Signature
   0      6      0    this       Lscala/collection/mutable/LinkedHashMap;
   0      6      1    that       Lscala/PartialFunction;


public boolean equals(java.lang.Object);
  Code:
   Stack=2, Locals=2, Args_size=2
   0:	aload_0
   1:	aload_1
   2:	invokestatic	#773; //Method scala/collection/MapLike$class.equals:(Lscala/collection/MapLike;Ljava/lang/Object;)Z
   5:	ireturn
  LineNumberTable: 
   line 33: 0

  LocalVariableTable: 
   Start  Length  Slot  Name   Signature
   0      6      0    this       Lscala/collection/mutable/LinkedHashMap;
   0      6      1    that       Ljava/lang/Object;


public int hashCode();
  Code:
   Stack=1, Locals=1, Args_size=1
   0:	aload_0
   1:	invokestatic	#777; //Method scala/collection/MapLike$class.hashCode:(Lscala/collection/MapLike;)I
   4:	ireturn
  LineNumberTable: 
   line 33: 0


public java.lang.String toString();
  Code:
   Stack=1, Locals=1, Args_size=1
   0:	aload_0
   1:	invokestatic	#781; //Method scala/collection/MapLike$class.toString:(Lscala/collection/MapLike;)Ljava/lang/String;
   4:	areturn
  LineNumberTable: 
   line 33: 0


public java.lang.String stringPrefix();
  Code:
   Stack=1, Locals=1, Args_size=1
   0:	aload_0
   1:	invokestatic	#784; //Method scala/collection/MapLike$class.stringPrefix:(Lscala/collection/MapLike;)Ljava/lang/String;
   4:	areturn
  LineNumberTable: 
   line 33: 0


public scala.collection.mutable.StringBuilder addString(scala.collection.mutable.StringBuilder, java.lang.String, java.lang.String, java.lang.String);
  Code:
   Stack=5, Locals=5, Args_size=5
   0:	aload_0
   1:	aload_1
   2:	aload_2
   3:	aload_3
   4:	aload	4
   6:	invokestatic	#788; //Method scala/collection/MapLike$class.addString:(Lscala/collection/MapLike;Lscala/collection/mutable/StringBuilder;Ljava/lang/String;Ljava/lang/String;Ljava/lang/String;)Lscala/collection/mutable/StringBuilder;
   9:	areturn
  LineNumberTable: 
   line 33: 0

  LocalVariableTable: 
   Start  Length  Slot  Name   Signature
   0      10      0    this       Lscala/collection/mutable/LinkedHashMap;
   0      10      1    b       Lscala/collection/mutable/StringBuilder;
   0      10      2    start       Ljava/lang/String;
   0      10      3    sep       Ljava/lang/String;
   0      10      4    end       Ljava/lang/String;


public scala.collection.Map $plus$plus(scala.collection.Iterator);
  Code:
   Stack=2, Locals=2, Args_size=2
   0:	aload_0
   1:	aload_1
   2:	invokestatic	#792; //Method scala/collection/MapLike$class.$plus$plus:(Lscala/collection/MapLike;Lscala/collection/Iterator;)Lscala/collection/Map;
   5:	areturn
  LineNumberTable: 
   line 33: 0

  LocalVariableTable: 
   Start  Length  Slot  Name   Signature
   0      6      0    this       Lscala/collection/mutable/LinkedHashMap;
   0      6      1    iter       Lscala/collection/Iterator;


public scala.collection.Map $plus$plus(scala.collection.Traversable);
  Code:
   Stack=2, Locals=2, Args_size=2
   0:	aload_0
   1:	aload_1
   2:	invokestatic	#796; //Method scala/collection/MapLike$class.$plus$plus:(Lscala/collection/MapLike;Lscala/collection/Traversable;)Lscala/collection/Map;
   5:	areturn
  LineNumberTable: 
   line 33: 0

  LocalVariableTable: 
   Start  Length  Slot  Name   Signature
   0      6      0    this       Lscala/collection/mutable/LinkedHashMap;
   0      6      1    kvs       Lscala/collection/Traversable;


public scala.collection.Map $plus(scala.Tuple2, scala.Tuple2, scala.collection.Seq);
  Code:
   Stack=4, Locals=4, Args_size=4
   0:	aload_0
   1:	aload_1
   2:	aload_2
   3:	aload_3
   4:	invokestatic	#801; //Method scala/collection/MapLike$class.$plus:(Lscala/collection/MapLike;Lscala/Tuple2;Lscala/Tuple2;Lscala/collection/Seq;)Lscala/collection/Map;
   7:	areturn
  LineNumberTable: 
   line 33: 0

  LocalVariableTable: 
   Start  Length  Slot  Name   Signature
   0      8      0    this       Lscala/collection/mutable/LinkedHashMap;
   0      8      1    kv1       Lscala/Tuple2;
   0      8      2    kv2       Lscala/Tuple2;
   0      8      3    kvs       Lscala/collection/Seq;


public java.lang.Object mapElements(scala.Function1);
  Code:
   Stack=2, Locals=2, Args_size=2
   0:	aload_0
   1:	aload_1
   2:	invokestatic	#807; //Method scala/collection/MapLike$class.mapElements:(Lscala/collection/MapLike;Lscala/Function1;)Ljava/lang/Object;
   5:	areturn
  LineNumberTable: 
   line 33: 0

  LocalVariableTable: 
   Start  Length  Slot  Name   Signature
   0      6      0    this       Lscala/collection/mutable/LinkedHashMap;
   0      6      1    f       Lscala/Function1;

  Deprecated: true

public java.lang.Object mapValues(scala.Function1);
  Code:
   Stack=2, Locals=2, Args_size=2
   0:	aload_0
   1:	aload_1
   2:	invokestatic	#810; //Method scala/collection/MapLike$class.mapValues:(Lscala/collection/MapLike;Lscala/Function1;)Ljava/lang/Object;
   5:	areturn
  LineNumberTable: 
   line 33: 0

  LocalVariableTable: 
   Start  Length  Slot  Name   Signature
   0      6      0    this       Lscala/collection/mutable/LinkedHashMap;
   0      6      1    f       Lscala/Function1;


public java.lang.Object filterKeys(scala.Function1);
  Code:
   Stack=2, Locals=2, Args_size=2
   0:	aload_0
   1:	aload_1
   2:	invokestatic	#813; //Method scala/collection/MapLike$class.filterKeys:(Lscala/collection/MapLike;Lscala/Function1;)Ljava/lang/Object;
   5:	areturn
  LineNumberTable: 
   line 33: 0

  LocalVariableTable: 
   Start  Length  Slot  Name   Signature
   0      6      0    this       Lscala/collection/mutable/LinkedHashMap;
   0      6      1    p       Lscala/Function1;


public java.lang.Object default(java.lang.Object);
  Code:
   Stack=2, Locals=2, Args_size=2
   0:	aload_0
   1:	aload_1
   2:	invokestatic	#817; //Method scala/collection/MapLike$class.default:(Lscala/collection/MapLike;Ljava/lang/Object;)Ljava/lang/Object;
   5:	areturn
  LineNumberTable: 
   line 33: 0

  LocalVariableTable: 
   Start  Length  Slot  Name   Signature
   0      6      0    this       Lscala/collection/mutable/LinkedHashMap;
   0      6      1    key       Ljava/lang/Object;


public scala.collection.Iterator values();
  Code:
   Stack=1, Locals=1, Args_size=1
   0:	aload_0
   1:	invokestatic	#821; //Method scala/collection/MapLike$class.values:(Lscala/collection/MapLike;)Lscala/collection/Iterator;
   4:	areturn
  LineNumberTable: 
   line 33: 0

  Deprecated: true

public scala.collection.Iterable valuesIterable();
  Code:
   Stack=1, Locals=1, Args_size=1
   0:	aload_0
   1:	invokestatic	#825; //Method scala/collection/MapLike$class.valuesIterable:(Lscala/collection/MapLike;)Lscala/collection/Iterable;
   4:	areturn
  LineNumberTable: 
   line 33: 0


public scala.collection.Iterator keys();
  Code:
   Stack=1, Locals=1, Args_size=1
   0:	aload_0
   1:	invokestatic	#828; //Method scala/collection/MapLike$class.keys:(Lscala/collection/MapLike;)Lscala/collection/Iterator;
   4:	areturn
  LineNumberTable: 
   line 33: 0

  Deprecated: true

public scala.collection.Set keySet();
  Code:
   Stack=1, Locals=1, Args_size=1
   0:	aload_0
   1:	invokestatic	#833; //Method scala/collection/MapLike$class.keySet:(Lscala/collection/MapLike;)Lscala/collection/Set;
   4:	areturn
  LineNumberTable: 
   line 33: 0


public boolean isDefinedAt(java.lang.Object);
  Code:
   Stack=2, Locals=2, Args_size=2
   0:	aload_0
   1:	aload_1
   2:	invokestatic	#836; //Method scala/collection/MapLike$class.isDefinedAt:(Lscala/collection/MapLike;Ljava/lang/Object;)Z
   5:	ireturn
  LineNumberTable: 
   line 33: 0

  LocalVariableTable: 
   Start  Length  Slot  Name   Signature
   0      6      0    this       Lscala/collection/mutable/LinkedHashMap;
   0      6      1    key       Ljava/lang/Object;


public boolean contains(java.lang.Object);
  Code:
   Stack=2, Locals=2, Args_size=2
   0:	aload_0
   1:	aload_1
   2:	invokestatic	#839; //Method scala/collection/MapLike$class.contains:(Lscala/collection/MapLike;Ljava/lang/Object;)Z
   5:	ireturn
  LineNumberTable: 
   line 33: 0

  LocalVariableTable: 
   Start  Length  Slot  Name   Signature
   0      6      0    this       Lscala/collection/mutable/LinkedHashMap;
   0      6      1    key       Ljava/lang/Object;


public java.lang.Object apply(java.lang.Object);
  Code:
   Stack=2, Locals=2, Args_size=2
   0:	aload_0
   1:	aload_1
   2:	invokestatic	#841; //Method scala/collection/MapLike$class.apply:(Lscala/collection/MapLike;Ljava/lang/Object;)Ljava/lang/Object;
   5:	areturn
  LineNumberTable: 
   line 33: 0

  LocalVariableTable: 
   Start  Length  Slot  Name   Signature
   0      6      0    this       Lscala/collection/mutable/LinkedHashMap;
   0      6      1    key       Ljava/lang/Object;


public java.lang.Object getOrElse(java.lang.Object, scala.Function0);
  Code:
   Stack=3, Locals=3, Args_size=3
   0:	aload_0
   1:	aload_1
   2:	aload_2
   3:	invokestatic	#846; //Method scala/collection/MapLike$class.getOrElse:(Lscala/collection/MapLike;Ljava/lang/Object;Lscala/Function0;)Ljava/lang/Object;
   6:	areturn
  LineNumberTable: 
   line 33: 0

  LocalVariableTable: 
   Start  Length  Slot  Name   Signature
   0      7      0    this       Lscala/collection/mutable/LinkedHashMap;
   0      7      1    key       Ljava/lang/Object;
   0      7      2    default       Lscala/Function0;


public boolean isEmpty();
  Code:
   Stack=1, Locals=1, Args_size=1
   0:	aload_0
   1:	invokestatic	#851; //Method scala/collection/MapLike$class.isEmpty:(Lscala/collection/MapLike;)Z
   4:	ireturn
  LineNumberTable: 
   line 33: 0


public final java.lang.Object scala$collection$mutable$Cloneable$$super$clone();
  Code:
   Stack=1, Locals=1, Args_size=1
   0:	aload_0
   1:	invokespecial	#854; //Method java/lang/Object.clone:()Ljava/lang/Object;
   4:	areturn
  LineNumberTable: 
   line 33: 0


public scala.collection.mutable.Map $plus(scala.Tuple2);
  Code:
   Stack=2, Locals=2, Args_size=2
   0:	aload_0
   1:	aload_1
   2:	invokestatic	#857; //Method scala/collection/mutable/MapLikeBase$class.$plus:(Lscala/collection/mutable/MapLikeBase;Lscala/Tuple2;)Lscala/collection/mutable/Map;
   5:	areturn
  LineNumberTable: 
   line 33: 0

  LocalVariableTable: 
   Start  Length  Slot  Name   Signature
   0      6      0    this       Lscala/collection/mutable/LinkedHashMap;
   0      6      1    kv       Lscala/Tuple2;


public scala.collection.generic.Growable $plus$plus$eq(scala.collection.Traversable);
  Code:
   Stack=2, Locals=2, Args_size=2
   0:	aload_0
   1:	aload_1
   2:	invokestatic	#862; //Method scala/collection/generic/Growable$class.$plus$plus$eq:(Lscala/collection/generic/Growable;Lscala/collection/Traversable;)Lscala/collection/generic/Growable;
   5:	areturn
  LineNumberTable: 
   line 33: 0

  LocalVariableTable: 
   Start  Length  Slot  Name   Signature
   0      6      0    this       Lscala/collection/mutable/LinkedHashMap;
   0      6      1    elems       Lscala/collection/Traversable;


public scala.collection.generic.Growable $plus$plus$eq(scala.collection.Iterator);
  Code:
   Stack=2, Locals=2, Args_size=2
   0:	aload_0
   1:	aload_1
   2:	invokestatic	#866; //Method scala/collection/generic/Growable$class.$plus$plus$eq:(Lscala/collection/generic/Growable;Lscala/collection/Iterator;)Lscala/collection/generic/Growable;
   5:	areturn
  LineNumberTable: 
   line 33: 0

  LocalVariableTable: 
   Start  Length  Slot  Name   Signature
   0      6      0    this       Lscala/collection/mutable/LinkedHashMap;
   0      6      1    iter       Lscala/collection/Iterator;


public scala.collection.generic.Growable $plus$eq(java.lang.Object, java.lang.Object, scala.collection.Seq);
  Code:
   Stack=4, Locals=4, Args_size=4
   0:	aload_0
   1:	aload_1
   2:	aload_2
   3:	aload_3
   4:	invokestatic	#870; //Method scala/collection/generic/Growable$class.$plus$eq:(Lscala/collection/generic/Growable;Ljava/lang/Object;Ljava/lang/Object;Lscala/collection/Seq;)Lscala/collection/generic/Growable;
   7:	areturn
  LineNumberTable: 
   line 33: 0

  LocalVariableTable: 
   Start  Length  Slot  Name   Signature
   0      8      0    this       Lscala/collection/mutable/LinkedHashMap;
   0      8      1    elem1       Ljava/lang/Object;
   0      8      2    elem2       Ljava/lang/Object;
   0      8      3    elems       Lscala/collection/Seq;


public scala.collection.mutable.Builder mapResult(scala.Function1);
  Code:
   Stack=2, Locals=2, Args_size=2
   0:	aload_0
   1:	aload_1
   2:	invokestatic	#875; //Method scala/collection/mutable/Builder$class.mapResult:(Lscala/collection/mutable/Builder;Lscala/Function1;)Lscala/collection/mutable/Builder;
   5:	areturn
  LineNumberTable: 
   line 33: 0

  LocalVariableTable: 
   Start  Length  Slot  Name   Signature
   0      6      0    this       Lscala/collection/mutable/LinkedHashMap;
   0      6      1    f       Lscala/Function1;


public void sizeHint(int);
  Code:
   Stack=2, Locals=2, Args_size=2
   0:	aload_0
   1:	iload_1
   2:	invokestatic	#880; //Method scala/collection/mutable/Builder$class.sizeHint:(Lscala/collection/mutable/Builder;I)V
   5:	return
  LineNumberTable: 
   line 33: 0

  LocalVariableTable: 
   Start  Length  Slot  Name   Signature
   0      6      0    this       Lscala/collection/mutable/LinkedHashMap;
   0      6      1    size       I


public scala.collection.generic.Shrinkable $minus$minus$eq(scala.collection.Traversable);
  Code:
   Stack=2, Locals=2, Args_size=2
   0:	aload_0
   1:	aload_1
   2:	invokestatic	#885; //Method scala/collection/generic/Shrinkable$class.$minus$minus$eq:(Lscala/collection/generic/Shrinkable;Lscala/collection/Traversable;)Lscala/collection/generic/Shrinkable;
   5:	areturn
  LineNumberTable: 
   line 33: 0

  LocalVariableTable: 
   Start  Length  Slot  Name   Signature
   0      6      0    this       Lscala/collection/mutable/LinkedHashMap;
   0      6      1    iter       Lscala/collection/Traversable;


public scala.collection.generic.Shrinkable $minus$minus$eq(scala.collection.Iterator);
  Code:
   Stack=2, Locals=2, Args_size=2
   0:	aload_0
   1:	aload_1
   2:	invokestatic	#889; //Method scala/collection/generic/Shrinkable$class.$minus$minus$eq:(Lscala/collection/generic/Shrinkable;Lscala/collection/Iterator;)Lscala/collection/generic/Shrinkable;
   5:	areturn
  LineNumberTable: 
   line 33: 0

  LocalVariableTable: 
   Start  Length  Slot  Name   Signature
   0      6      0    this       Lscala/collection/mutable/LinkedHashMap;
   0      6      1    iter       Lscala/collection/Iterator;


public scala.collection.generic.Shrinkable $minus$eq(java.lang.Object, java.lang.Object, scala.collection.Seq);
  Code:
   Stack=4, Locals=4, Args_size=4
   0:	aload_0
   1:	aload_1
   2:	aload_2
   3:	aload_3
   4:	invokestatic	#893; //Method scala/collection/generic/Shrinkable$class.$minus$eq:(Lscala/collection/generic/Shrinkable;Ljava/lang/Object;Ljava/lang/Object;Lscala/collection/Seq;)Lscala/collection/generic/Shrinkable;
   7:	areturn
  LineNumberTable: 
   line 33: 0

  LocalVariableTable: 
   Start  Length  Slot  Name   Signature
   0      8      0    this       Lscala/collection/mutable/LinkedHashMap;
   0      8      1    elem1       Ljava/lang/Object;
   0      8      2    elem2       Ljava/lang/Object;
   0      8      3    elems       Lscala/collection/Seq;


public scala.collection.mutable.MapLike $minus$minus(scala.collection.Iterator);
  Code:
   Stack=2, Locals=2, Args_size=2
   0:	aload_0
   1:	aload_1
   2:	invokestatic	#896; //Method scala/collection/mutable/MapLike$class.$minus$minus:(Lscala/collection/mutable/MapLike;Lscala/collection/Iterator;)Lscala/collection/mutable/MapLike;
   5:	areturn
  LineNumberTable: 
   line 33: 0

  LocalVariableTable: 
   Start  Length  Slot  Name   Signature
   0      6      0    this       Lscala/collection/mutable/LinkedHashMap;
   0      6      1    iter       Lscala/collection/Iterator;

  Deprecated: true

public scala.collection.mutable.MapLike $minus$minus(scala.collection.Traversable);
  Code:
   Stack=2, Locals=2, Args_size=2
   0:	aload_0
   1:	aload_1
   2:	invokestatic	#899; //Method scala/collection/mutable/MapLike$class.$minus$minus:(Lscala/collection/mutable/MapLike;Lscala/collection/Traversable;)Lscala/collection/mutable/MapLike;
   5:	areturn
  LineNumberTable: 
   line 33: 0

  LocalVariableTable: 
   Start  Length  Slot  Name   Signature
   0      6      0    this       Lscala/collection/mutable/LinkedHashMap;
   0      6      1    iter       Lscala/collection/Traversable;

  Deprecated: true

public scala.collection.mutable.MapLike $minus(java.lang.Object, java.lang.Object, scala.collection.Seq);
  Code:
   Stack=4, Locals=4, Args_size=4
   0:	aload_0
   1:	aload_1
   2:	aload_2
   3:	aload_3
   4:	invokestatic	#902; //Method scala/collection/mutable/MapLike$class.$minus:(Lscala/collection/mutable/MapLike;Ljava/lang/Object;Ljava/lang/Object;Lscala/collection/Seq;)Lscala/collection/mutable/MapLike;
   7:	areturn
  LineNumberTable: 
   line 33: 0

  LocalVariableTable: 
   Start  Length  Slot  Name   Signature
   0      8      0    this       Lscala/collection/mutable/LinkedHashMap;
   0      8      1    elem1       Ljava/lang/Object;
   0      8      2    elem2       Ljava/lang/Object;
   0      8      3    elems       Lscala/collection/Seq;

  Deprecated: true

public scala.collection.mutable.MapLike result();
  Code:
   Stack=1, Locals=1, Args_size=1
   0:	aload_0
   1:	invokestatic	#905; //Method scala/collection/mutable/MapLike$class.result:(Lscala/collection/mutable/MapLike;)Lscala/collection/mutable/MapLike;
   4:	areturn
  LineNumberTable: 
   line 33: 0


public scala.collection.mutable.MapLike clone();
  Code:
   Stack=1, Locals=1, Args_size=1
   0:	aload_0
   1:	invokestatic	#907; //Method scala/collection/mutable/MapLike$class.clone:(Lscala/collection/mutable/MapLike;)Lscala/collection/mutable/MapLike;
   4:	areturn
  LineNumberTable: 
   line 33: 0


public scala.collection.mutable.MapLike retain(scala.Function2);
  Code:
   Stack=2, Locals=2, Args_size=2
   0:	aload_0
   1:	aload_1
   2:	invokestatic	#912; //Method scala/collection/mutable/MapLike$class.retain:(Lscala/collection/mutable/MapLike;Lscala/Function2;)Lscala/collection/mutable/MapLike;
   5:	areturn
  LineNumberTable: 
   line 33: 0

  LocalVariableTable: 
   Start  Length  Slot  Name   Signature
   0      6      0    this       Lscala/collection/mutable/LinkedHashMap;
   0      6      1    p       Lscala/Function2;

  Deprecated: true

public scala.collection.mutable.MapLike transform(scala.Function2);
  Code:
   Stack=2, Locals=2, Args_size=2
   0:	aload_0
   1:	aload_1
   2:	invokestatic	#915; //Method scala/collection/mutable/MapLike$class.transform:(Lscala/collection/mutable/MapLike;Lscala/Function2;)Lscala/collection/mutable/MapLike;
   5:	areturn
  LineNumberTable: 
   line 33: 0

  LocalVariableTable: 
   Start  Length  Slot  Name   Signature
   0      6      0    this       Lscala/collection/mutable/LinkedHashMap;
   0      6      1    f       Lscala/Function2;


public java.lang.Object getOrElseUpdate(java.lang.Object, scala.Function0);
  Code:
   Stack=3, Locals=3, Args_size=3
   0:	aload_0
   1:	aload_1
   2:	aload_2
   3:	invokestatic	#919; //Method scala/collection/mutable/MapLike$class.getOrElseUpdate:(Lscala/collection/mutable/MapLike;Ljava/lang/Object;Lscala/Function0;)Ljava/lang/Object;
   6:	areturn
  LineNumberTable: 
   line 33: 0

  LocalVariableTable: 
   Start  Length  Slot  Name   Signature
   0      7      0    this       Lscala/collection/mutable/LinkedHashMap;
   0      7      1    key       Ljava/lang/Object;
   0      7      2    op       Lscala/Function0;


public scala.Option removeKey(java.lang.Object);
  Code:
   Stack=2, Locals=2, Args_size=2
   0:	aload_0
   1:	aload_1
   2:	invokestatic	#923; //Method scala/collection/mutable/MapLike$class.removeKey:(Lscala/collection/mutable/MapLike;Ljava/lang/Object;)Lscala/Option;
   5:	areturn
  LineNumberTable: 
   line 33: 0

  LocalVariableTable: 
   Start  Length  Slot  Name   Signature
   0      6      0    this       Lscala/collection/mutable/LinkedHashMap;
   0      6      1    key       Ljava/lang/Object;

  Deprecated: true

public scala.collection.mutable.MapLike $minus(java.lang.Object);
  Code:
   Stack=2, Locals=2, Args_size=2
   0:	aload_0
   1:	aload_1
   2:	invokestatic	#926; //Method scala/collection/mutable/MapLike$class.$minus:(Lscala/collection/mutable/MapLike;Ljava/lang/Object;)Lscala/collection/mutable/MapLike;
   5:	areturn
  LineNumberTable: 
   line 33: 0

  LocalVariableTable: 
   Start  Length  Slot  Name   Signature
   0      6      0    this       Lscala/collection/mutable/LinkedHashMap;
   0      6      1    key       Ljava/lang/Object;

  Deprecated: true

public scala.collection.mutable.MapLike $plus$plus(scala.collection.Iterator);
  Code:
   Stack=2, Locals=2, Args_size=2
   0:	aload_0
   1:	aload_1
   2:	invokestatic	#928; //Method scala/collection/mutable/MapLike$class.$plus$plus:(Lscala/collection/mutable/MapLike;Lscala/collection/Iterator;)Lscala/collection/mutable/MapLike;
   5:	areturn
  LineNumberTable: 
   line 33: 0

  LocalVariableTable: 
   Start  Length  Slot  Name   Signature
   0      6      0    this       Lscala/collection/mutable/LinkedHashMap;
   0      6      1    iter       Lscala/collection/Iterator;

  Deprecated: true

public scala.collection.mutable.MapLike $plus$plus(scala.collection.Traversable);
  Code:
   Stack=2, Locals=2, Args_size=2
   0:	aload_0
   1:	aload_1
   2:	invokestatic	#930; //Method scala/collection/mutable/MapLike$class.$plus$plus:(Lscala/collection/mutable/MapLike;Lscala/collection/Traversable;)Lscala/collection/mutable/MapLike;
   5:	areturn
  LineNumberTable: 
   line 33: 0

  LocalVariableTable: 
   Start  Length  Slot  Name   Signature
   0      6      0    this       Lscala/collection/mutable/LinkedHashMap;
   0      6      1    iter       Lscala/collection/Traversable;

  Deprecated: true

public scala.collection.mutable.MapLike $plus(scala.Tuple2, scala.Tuple2, scala.collection.Seq);
  Code:
   Stack=4, Locals=4, Args_size=4
   0:	aload_0
   1:	aload_1
   2:	aload_2
   3:	aload_3
   4:	invokestatic	#934; //Method scala/collection/mutable/MapLike$class.$plus:(Lscala/collection/mutable/MapLike;Lscala/Tuple2;Lscala/Tuple2;Lscala/collection/Seq;)Lscala/collection/mutable/MapLike;
   7:	areturn
  LineNumberTable: 
   line 33: 0

  LocalVariableTable: 
   Start  Length  Slot  Name   Signature
   0      8      0    this       Lscala/collection/mutable/LinkedHashMap;
   0      8      1    elem1       Lscala/Tuple2;
   0      8      2    elem2       Lscala/Tuple2;
   0      8      3    elems       Lscala/collection/Seq;

  Deprecated: true

public scala.collection.mutable.MapLike $plus(scala.Tuple2);
  Code:
   Stack=2, Locals=2, Args_size=2
   0:	aload_0
   1:	aload_1
   2:	invokestatic	#937; //Method scala/collection/mutable/MapLike$class.$plus:(Lscala/collection/mutable/MapLike;Lscala/Tuple2;)Lscala/collection/mutable/MapLike;
   5:	areturn
  LineNumberTable: 
   line 33: 0

  LocalVariableTable: 
   Start  Length  Slot  Name   Signature
   0      6      0    this       Lscala/collection/mutable/LinkedHashMap;
   0      6      1    kv       Lscala/Tuple2;

  Deprecated: true

public scala.collection.mutable.Map updated(java.lang.Object, java.lang.Object);
  Code:
   Stack=3, Locals=3, Args_size=3
   0:	aload_0
   1:	aload_1
   2:	aload_2
   3:	invokestatic	#940; //Method scala/collection/mutable/MapLike$class.updated:(Lscala/collection/mutable/MapLike;Ljava/lang/Object;Ljava/lang/Object;)Lscala/collection/mutable/Map;
   6:	areturn
  LineNumberTable: 
   line 33: 0

  LocalVariableTable: 
   Start  Length  Slot  Name   Signature
   0      7      0    this       Lscala/collection/mutable/LinkedHashMap;
   0      7      1    key       Ljava/lang/Object;
   0      7      2    value       Ljava/lang/Object;


public void update(java.lang.Object, java.lang.Object);
  Code:
   Stack=3, Locals=3, Args_size=3
   0:	aload_0
   1:	aload_1
   2:	aload_2
   3:	invokestatic	#944; //Method scala/collection/mutable/MapLike$class.update:(Lscala/collection/mutable/MapLike;Ljava/lang/Object;Ljava/lang/Object;)V
   6:	return
  LineNumberTable: 
   line 33: 0

  LocalVariableTable: 
   Start  Length  Slot  Name   Signature
   0      7      0    this       Lscala/collection/mutable/LinkedHashMap;
   0      7      1    key       Ljava/lang/Object;
   0      7      2    value       Ljava/lang/Object;


public scala.collection.mutable.Builder newBuilder();
  Code:
   Stack=1, Locals=1, Args_size=1
   0:	aload_0
   1:	invokestatic	#948; //Method scala/collection/mutable/MapLike$class.newBuilder:(Lscala/collection/mutable/MapLike;)Lscala/collection/mutable/Builder;
   4:	areturn
  LineNumberTable: 
   line 33: 0


public final int index(int);
  Code:
   Stack=2, Locals=2, Args_size=2
   0:	aload_0
   1:	iload_1
   2:	invokestatic	#953; //Method scala/collection/mutable/HashTable$class.index:(Lscala/collection/mutable/HashTable;I)I
   5:	ireturn
  LineNumberTable: 
   line 33: 0

  LocalVariableTable: 
   Start  Length  Slot  Name   Signature
   0      6      0    this       Lscala/collection/mutable/LinkedHashMap;
   0      6      1    hcode       I


public final int improve(int);
  Code:
   Stack=2, Locals=2, Args_size=2
   0:	aload_0
   1:	iload_1
   2:	invokestatic	#957; //Method scala/collection/mutable/HashTable$class.improve:(Lscala/collection/mutable/HashTable;I)I
   5:	ireturn
  LineNumberTable: 
   line 33: 0

  LocalVariableTable: 
   Start  Length  Slot  Name   Signature
   0      6      0    this       Lscala/collection/mutable/LinkedHashMap;
   0      6      1    hcode       I


public int elemHashCode(java.lang.Object);
  Code:
   Stack=2, Locals=2, Args_size=2
   0:	aload_0
   1:	aload_1
   2:	invokestatic	#962; //Method scala/collection/mutable/HashTable$class.elemHashCode:(Lscala/collection/mutable/HashTable;Ljava/lang/Object;)I
   5:	ireturn
  LineNumberTable: 
   line 33: 0

  LocalVariableTable: 
   Start  Length  Slot  Name   Signature
   0      6      0    this       Lscala/collection/mutable/LinkedHashMap;
   0      6      1    key       Ljava/lang/Object;


public boolean elemEquals(java.lang.Object, java.lang.Object);
  Code:
   Stack=3, Locals=3, Args_size=3
   0:	aload_0
   1:	aload_1
   2:	aload_2
   3:	invokestatic	#967; //Method scala/collection/mutable/HashTable$class.elemEquals:(Lscala/collection/mutable/HashTable;Ljava/lang/Object;Ljava/lang/Object;)Z
   6:	ireturn
  LineNumberTable: 
   line 33: 0

  LocalVariableTable: 
   Start  Length  Slot  Name   Signature
   0      7      0    this       Lscala/collection/mutable/LinkedHashMap;
   0      7      1    key1       Ljava/lang/Object;
   0      7      2    key2       Ljava/lang/Object;


public void clearTable();
  Code:
   Stack=1, Locals=1, Args_size=1
   0:	aload_0
   1:	invokestatic	#971; //Method scala/collection/mutable/HashTable$class.clearTable:(Lscala/collection/mutable/HashTable;)V
   4:	return
  LineNumberTable: 
   line 33: 0


public scala.collection.Iterator entries();
  Code:
   Stack=1, Locals=1, Args_size=1
   0:	aload_0
   1:	invokestatic	#975; //Method scala/collection/mutable/HashTable$class.entries:(Lscala/collection/mutable/HashTable;)Lscala/collection/Iterator;
   4:	areturn
  LineNumberTable: 
   line 33: 0

  Deprecated: true

public final void foreachEntry(scala.Function1);
  Code:
   Stack=2, Locals=2, Args_size=2
   0:	aload_0
   1:	aload_1
   2:	invokestatic	#979; //Method scala/collection/mutable/HashTable$class.foreachEntry:(Lscala/collection/mutable/HashTable;Lscala/Function1;)V
   5:	return
  LineNumberTable: 
   line 33: 0

  LocalVariableTable: 
   Start  Length  Slot  Name   Signature
   0      6      0    this       Lscala/collection/mutable/LinkedHashMap;
   0      6      1    f       Lscala/Function1;


public scala.collection.Iterator entriesIterator();
  Code:
   Stack=1, Locals=1, Args_size=1
   0:	aload_0
   1:	invokestatic	#982; //Method scala/collection/mutable/HashTable$class.entriesIterator:(Lscala/collection/mutable/HashTable;)Lscala/collection/Iterator;
   4:	areturn
  LineNumberTable: 
   line 33: 0


public scala.collection.mutable.HashEntry removeEntry(java.lang.Object);
  Code:
   Stack=2, Locals=2, Args_size=2
   0:	aload_0
   1:	aload_1
   2:	invokestatic	#985; //Method scala/collection/mutable/HashTable$class.removeEntry:(Lscala/collection/mutable/HashTable;Ljava/lang/Object;)Lscala/collection/mutable/HashEntry;
   5:	areturn
  LineNumberTable: 
   line 33: 0

  LocalVariableTable: 
   Start  Length  Slot  Name   Signature
   0      6      0    this       Lscala/collection/mutable/LinkedHashMap;
   0      6      1    key       Ljava/lang/Object;


public void addEntry(scala.collection.mutable.HashEntry);
  Code:
   Stack=2, Locals=2, Args_size=2
   0:	aload_0
   1:	aload_1
   2:	invokestatic	#988; //Method scala/collection/mutable/HashTable$class.addEntry:(Lscala/collection/mutable/HashTable;Lscala/collection/mutable/HashEntry;)V
   5:	return
  LineNumberTable: 
   line 33: 0

  LocalVariableTable: 
   Start  Length  Slot  Name   Signature
   0      6      0    this       Lscala/collection/mutable/LinkedHashMap;
   0      6      1    e       Lscala/collection/mutable/HashEntry;


public scala.collection.mutable.HashEntry findEntry(java.lang.Object);
  Code:
   Stack=2, Locals=2, Args_size=2
   0:	aload_0
   1:	aload_1
   2:	invokestatic	#991; //Method scala/collection/mutable/HashTable$class.findEntry:(Lscala/collection/mutable/HashTable;Ljava/lang/Object;)Lscala/collection/mutable/HashEntry;
   5:	areturn
  LineNumberTable: 
   line 33: 0

  LocalVariableTable: 
   Start  Length  Slot  Name   Signature
   0      6      0    this       Lscala/collection/mutable/LinkedHashMap;
   0      6      1    key       Ljava/lang/Object;


public void serializeTo(java.io.ObjectOutputStream, scala.Function1);
  Code:
   Stack=3, Locals=3, Args_size=3
   0:	aload_0
   1:	aload_1
   2:	aload_2
   3:	invokestatic	#994; //Method scala/collection/mutable/HashTable$class.serializeTo:(Lscala/collection/mutable/HashTable;Ljava/io/ObjectOutputStream;Lscala/Function1;)V
   6:	return
  LineNumberTable: 
   line 33: 0

  LocalVariableTable: 
   Start  Length  Slot  Name   Signature
   0      7      0    this       Lscala/collection/mutable/LinkedHashMap;
   0      7      1    out       Ljava/io/ObjectOutputStream;
   0      7      2    value       Lscala/Function1;


public void init(java.io.ObjectInputStream, scala.Function2);
  Code:
   Stack=3, Locals=3, Args_size=3
   0:	aload_0
   1:	aload_1
   2:	aload_2
   3:	invokestatic	#997; //Method scala/collection/mutable/HashTable$class.init:(Lscala/collection/mutable/HashTable;Ljava/io/ObjectInputStream;Lscala/Function2;)V
   6:	return
  LineNumberTable: 
   line 33: 0

  LocalVariableTable: 
   Start  Length  Slot  Name   Signature
   0      7      0    this       Lscala/collection/mutable/LinkedHashMap;
   0      7      1    in       Ljava/io/ObjectInputStream;
   0      7      2    f       Lscala/Function2;


public int initialThreshold();
  Code:
   Stack=1, Locals=1, Args_size=1
   0:	aload_0
   1:	invokestatic	#1001; //Method scala/collection/mutable/HashTable$class.initialThreshold:(Lscala/collection/mutable/HashTable;)I
   4:	ireturn
  LineNumberTable: 
   line 33: 0


public int initialSize();
  Code:
   Stack=1, Locals=1, Args_size=1
   0:	aload_0
   1:	invokestatic	#1004; //Method scala/collection/mutable/HashTable$class.initialSize:(Lscala/collection/mutable/HashTable;)I
   4:	ireturn
  LineNumberTable: 
   line 33: 0


public int loadFactor();
  Code:
   Stack=1, Locals=1, Args_size=1
   0:	aload_0
   1:	invokestatic	#1007; //Method scala/collection/mutable/HashTable$class.loadFactor:(Lscala/collection/mutable/HashTable;)I
   4:	ireturn
  LineNumberTable: 
   line 33: 0


public void threshold_$eq(int);
  Code:
   Stack=2, Locals=2, Args_size=2
   0:	aload_0
   1:	iload_1
   2:	putfield	#1010; //Field threshold:I
   5:	return
  LineNumberTable: 
   line 33: 0


public int threshold();
  Code:
   Stack=1, Locals=1, Args_size=1
   0:	aload_0
   1:	getfield	#1010; //Field threshold:I
   4:	ireturn
  LineNumberTable: 
   line 33: 0


public void tableSize_$eq(int);
  Code:
   Stack=2, Locals=2, Args_size=2
   0:	aload_0
   1:	iload_1
   2:	putfield	#1013; //Field tableSize:I
   5:	return
  LineNumberTable: 
   line 33: 0


public int tableSize();
  Code:
   Stack=1, Locals=1, Args_size=1
   0:	aload_0
   1:	getfield	#1013; //Field tableSize:I
   4:	ireturn
  LineNumberTable: 
   line 33: 0


public void table_$eq(scala.collection.mutable.HashEntry[]);
  Code:
   Stack=2, Locals=2, Args_size=2
   0:	aload_0
   1:	aload_1
   2:	putfield	#1017; //Field table:[Lscala/collection/mutable/HashEntry;
   5:	return
  LineNumberTable: 
   line 33: 0


public scala.collection.mutable.HashEntry[] table();
  Code:
   Stack=1, Locals=1, Args_size=1
   0:	aload_0
   1:	getfield	#1017; //Field table:[Lscala/collection/mutable/HashEntry;
   4:	areturn
  LineNumberTable: 
   line 33: 0


public void _loadFactor_$eq(int);
  Code:
   Stack=2, Locals=2, Args_size=2
   0:	aload_0
   1:	iload_1
   2:	putfield	#1021; //Field _loadFactor:I
   5:	return
  LineNumberTable: 
   line 33: 0


public int _loadFactor();
  Code:
   Stack=1, Locals=1, Args_size=1
   0:	aload_0
   1:	getfield	#1021; //Field _loadFactor:I
   4:	ireturn
  LineNumberTable: 
   line 33: 0


public final int loadFactorDenum();
  Code:
   Stack=1, Locals=1, Args_size=1
   0:	ldc_w	#1023; //int 1000
   3:	ireturn
  LineNumberTable: 
   line 33: 0


}

