Compiled from "LinkedHashMap.scala"
public final class scala.collection.mutable.LinkedHashMap$$anonfun$readObject$1 extends scala.runtime.AbstractFunction2 implements java.io.Serializable
  SourceFile: "LinkedHashMap.scala"
  Scala: length = 0x
   
  InnerClass: 
   public final #57= #9 of #45; //$anonfun$readObject$1=class scala/collection/mutable/LinkedHashMap$$anonfun$readObject$1 of class scala/collection/mutable/LinkedHashMap
  minor version: 0
  major version: 49
  Constant pool:
const #1 = Asciz	SourceFile;
const #2 = Asciz	LinkedHashMap.scala;
const #3 = Asciz	<clinit>;
const #4 = Asciz	()V;
const #5 = Asciz	Code;
const #6 = Asciz	serialVersionUID;
const #7 = Asciz	J;
const #8 = Asciz	scala/collection/mutable/LinkedHashMap$$anonfun$readObject$1;
const #9 = class	#8;	//  scala/collection/mutable/LinkedHashMap$$anonfun$readObject$1
const #10 = NameAndType	#6:#7;//  serialVersionUID:J
const #11 = Field	#9.#10;	//  scala/collection/mutable/LinkedHashMap$$anonfun$readObject$1.serialVersionUID:J
const #12 = Asciz	$outer;
const #13 = Asciz	Lscala/collection/mutable/LinkedHashMap;;
const #14 = Asciz	<init>;
const #15 = Asciz	(Lscala/collection/mutable/LinkedHashMap;)V;
const #16 = Asciz	LineNumberTable;
const #17 = Asciz	java/lang/NullPointerException;
const #18 = class	#17;	//  java/lang/NullPointerException
const #19 = NameAndType	#14:#4;//  "<init>":()V
const #20 = Method	#18.#19;	//  java/lang/NullPointerException."<init>":()V
const #21 = NameAndType	#12:#13;//  $outer:Lscala/collection/mutable/LinkedHashMap;
const #22 = Field	#9.#21;	//  scala/collection/mutable/LinkedHashMap$$anonfun$readObject$1.$outer:Lscala/collection/mutable/LinkedHashMap;
const #23 = Asciz	scala/runtime/AbstractFunction2;
const #24 = class	#23;	//  scala/runtime/AbstractFunction2
const #25 = Method	#24.#19;	//  scala/runtime/AbstractFunction2."<init>":()V
const #26 = Asciz	this;
const #27 = Asciz	Lscala/collection/mutable/LinkedHashMap$$anonfun$readObject$1;;
const #28 = Asciz	LocalVariableTable;
const #29 = Asciz	(Lscala/collection/mutable/LinkedHashMap<TA;TB;>;)V;
const #30 = Asciz	Signature;
const #31 = Asciz	apply;
const #32 = Asciz	(Ljava/lang/Object;Ljava/lang/Object;)Ljava/lang/Object;;
const #33 = Asciz	(Ljava/lang/Object;Ljava/lang/Object;)Lscala/collection/mutable/LinkedEntry;;
const #34 = NameAndType	#31:#33;//  apply:(Ljava/lang/Object;Ljava/lang/Object;)Lscala/collection/mutable/LinkedEntry;
const #35 = Method	#9.#34;	//  scala/collection/mutable/LinkedHashMap$$anonfun$readObject$1.apply:(Ljava/lang/Object;Ljava/lang/Object;)Lscala/collection/mutable/LinkedEntry;
const #36 = Asciz	v1;
const #37 = Asciz	Ljava/lang/Object;;
const #38 = Asciz	v2;
const #39 = Asciz	scala/collection/mutable/LinkedEntry;
const #40 = class	#39;	//  scala/collection/mutable/LinkedEntry
const #41 = Asciz	(Ljava/lang/Object;Ljava/lang/Object;)V;
const #42 = NameAndType	#14:#41;//  "<init>":(Ljava/lang/Object;Ljava/lang/Object;)V
const #43 = Method	#40.#42;	//  scala/collection/mutable/LinkedEntry."<init>":(Ljava/lang/Object;Ljava/lang/Object;)V
const #44 = Asciz	scala/collection/mutable/LinkedHashMap;
const #45 = class	#44;	//  scala/collection/mutable/LinkedHashMap
const #46 = Asciz	scala$collection$mutable$LinkedHashMap$$updateLinkedEntries;
const #47 = Asciz	(Lscala/collection/mutable/LinkedEntry;)V;
const #48 = NameAndType	#46:#47;//  scala$collection$mutable$LinkedHashMap$$updateLinkedEntries:(Lscala/collection/mutable/LinkedEntry;)V
const #49 = Method	#45.#48;	//  scala/collection/mutable/LinkedHashMap.scala$collection$mutable$LinkedHashMap$$updateLinkedEntries:(Lscala/collection/mutable/LinkedEntry;)V
const #50 = Asciz	key;
const #51 = Asciz	value;
const #52 = Asciz	entry;
const #53 = Asciz	Lscala/collection/mutable/LinkedEntry;;
const #54 = Asciz	(TA;TB;)Lscala/collection/mutable/LinkedEntry<TA;TB;>;;
const #55 = Asciz	Scala;
const #56 = Asciz	InnerClasses;
const #57 = Asciz	$anonfun$readObject$1;
const #58 = Asciz	java/io/Serializable;
const #59 = class	#58;	//  java/io/Serializable

{
public static final long serialVersionUID;

public static {};
  Code:
   Stack=2, Locals=0, Args_size=0
   0:	lconst_0
   1:	putstatic	#11; //Field serialVersionUID:J
   4:	return

public scala.collection.mutable.LinkedHashMap$$anonfun$readObject$1(scala.collection.mutable.LinkedHashMap);
  Code:
   Stack=2, Locals=2, Args_size=2
   0:	aload_1
   1:	ifnonnull	12
   4:	new	#18; //class java/lang/NullPointerException
   7:	dup
   8:	invokespecial	#20; //Method java/lang/NullPointerException."<init>":()V
   11:	athrow
   12:	aload_0
   13:	aload_1
   14:	putfield	#22; //Field $outer:Lscala/collection/mutable/LinkedHashMap;
   17:	aload_0
   18:	invokespecial	#25; //Method scala/runtime/AbstractFunction2."<init>":()V
   21:	return
  LineNumberTable: 
   line 128: 0

  LocalVariableTable: 
   Start  Length  Slot  Name   Signature
   0      22      0    this       Lscala/collection/mutable/LinkedHashMap$$anonfun$readObject$1;
   0      22      1    $outer       Lscala/collection/mutable/LinkedHashMap;

  Signature: length = 0x2
   00 1D 

public final java.lang.Object apply(java.lang.Object, java.lang.Object);
  Code:
   Stack=3, Locals=3, Args_size=3
   0:	aload_0
   1:	aload_1
   2:	aload_2
   3:	invokevirtual	#35; //Method apply:(Ljava/lang/Object;Ljava/lang/Object;)Lscala/collection/mutable/LinkedEntry;
   6:	areturn
  LineNumberTable: 
   line 128: 0

  LocalVariableTable: 
   Start  Length  Slot  Name   Signature
   0      7      0    this       Lscala/collection/mutable/LinkedHashMap$$anonfun$readObject$1;
   0      7      1    v1       Ljava/lang/Object;
   0      7      2    v2       Ljava/lang/Object;


public final scala.collection.mutable.LinkedEntry apply(java.lang.Object, java.lang.Object);
  Code:
   Stack=4, Locals=4, Args_size=3
   0:	new	#40; //class scala/collection/mutable/LinkedEntry
   3:	dup
   4:	aload_1
   5:	aload_2
   6:	invokespecial	#43; //Method scala/collection/mutable/LinkedEntry."<init>":(Ljava/lang/Object;Ljava/lang/Object;)V
   9:	astore_3
   10:	aload_0
   11:	getfield	#22; //Field $outer:Lscala/collection/mutable/LinkedHashMap;
   14:	aload_3
   15:	invokevirtual	#49; //Method scala/collection/mutable/LinkedHashMap.scala$collection$mutable$LinkedHashMap$$updateLinkedEntries:(Lscala/collection/mutable/LinkedEntry;)V
   18:	aload_3
   19:	areturn
  LineNumberTable: 
   line 129: 0
   line 130: 10
   line 131: 14
   line 130: 15
   line 131: 18

  LocalVariableTable: 
   Start  Length  Slot  Name   Signature
   0      20      0    this       Lscala/collection/mutable/LinkedHashMap$$anonfun$readObject$1;
   0      20      1    key       Ljava/lang/Object;
   0      20      2    value       Ljava/lang/Object;
   10      9      3    entry       Lscala/collection/mutable/LinkedEntry;

  Signature: length = 0x2
   00 36 

}

