Compiled from "LinkedList.scala"
public final class scala.collection.mutable.LinkedList$ extends scala.collection.generic.SeqFactory implements scala.ScalaObject
  SourceFile: "LinkedList.scala"
  Scala: length = 0x
   
  Signature: length = 0x2
   00 35 
  InnerClass: 
   public final #55= #31 of #50; //$anonfun$newBuilder$1=class scala/collection/mutable/LinkedList$$anonfun$newBuilder$1 of class scala/collection/mutable/LinkedList
   public #58= #44 of #57; //GenericCanBuildFrom=class scala/collection/generic/TraversableFactory$GenericCanBuildFrom of class scala/collection/generic/TraversableFactory
  minor version: 0
  major version: 49
  Constant pool:
const #1 = Asciz	SourceFile;
const #2 = Asciz	LinkedList.scala;
const #3 = Asciz	Scala;
const #4 = Asciz	MODULE$;
const #5 = Asciz	Lscala/collection/mutable/LinkedList$;;
const #6 = Asciz	<clinit>;
const #7 = Asciz	()V;
const #8 = Asciz	Code;
const #9 = Asciz	scala/collection/mutable/LinkedList$;
const #10 = class	#9;	//  scala/collection/mutable/LinkedList$
const #11 = Asciz	<init>;
const #12 = NameAndType	#11:#7;//  "<init>":()V
const #13 = Method	#10.#12;	//  scala/collection/mutable/LinkedList$."<init>":()V
const #14 = Asciz	LineNumberTable;
const #15 = Asciz	scala/collection/generic/SeqFactory;
const #16 = class	#15;	//  scala/collection/generic/SeqFactory
const #17 = Method	#16.#12;	//  scala/collection/generic/SeqFactory."<init>":()V
const #18 = NameAndType	#4:#5;//  MODULE$:Lscala/collection/mutable/LinkedList$;
const #19 = Field	#10.#18;	//  scala/collection/mutable/LinkedList$.MODULE$:Lscala/collection/mutable/LinkedList$;
const #20 = Asciz	empty;
const #21 = Asciz	()Lscala/collection/Traversable;;
const #22 = Asciz	()Lscala/collection/mutable/LinkedList;;
const #23 = NameAndType	#20:#22;//  empty:()Lscala/collection/mutable/LinkedList;
const #24 = Method	#10.#23;	//  scala/collection/mutable/LinkedList$.empty:()Lscala/collection/mutable/LinkedList;
const #25 = Asciz	newBuilder;
const #26 = Asciz	()Lscala/collection/mutable/Builder;;
const #27 = Asciz	scala/collection/mutable/MutableList;
const #28 = class	#27;	//  scala/collection/mutable/MutableList
const #29 = Method	#28.#12;	//  scala/collection/mutable/MutableList."<init>":()V
const #30 = Asciz	scala/collection/mutable/LinkedList$$anonfun$newBuilder$1;
const #31 = class	#30;	//  scala/collection/mutable/LinkedList$$anonfun$newBuilder$1
const #32 = Method	#31.#12;	//  scala/collection/mutable/LinkedList$$anonfun$newBuilder$1."<init>":()V
const #33 = Asciz	scala/collection/mutable/Builder;
const #34 = class	#33;	//  scala/collection/mutable/Builder
const #35 = Asciz	mapResult;
const #36 = Asciz	(Lscala/Function1;)Lscala/collection/mutable/Builder;;
const #37 = NameAndType	#35:#36;//  mapResult:(Lscala/Function1;)Lscala/collection/mutable/Builder;
const #38 = InterfaceMethod	#34.#37;	//  scala/collection/mutable/Builder.mapResult:(Lscala/Function1;)Lscala/collection/mutable/Builder;
const #39 = Asciz	<A:Ljava/lang/Object;>()Lscala/collection/mutable/Builder<TA;Lscala/collection/mutable/LinkedList<TA;>;>;;
const #40 = Asciz	Signature;
const #41 = Asciz	canBuildFrom;
const #42 = Asciz	()Lscala/collection/generic/CanBuildFrom;;
const #43 = Asciz	scala/collection/generic/TraversableFactory$GenericCanBuildFrom;
const #44 = class	#43;	//  scala/collection/generic/TraversableFactory$GenericCanBuildFrom
const #45 = Asciz	(Lscala/collection/generic/TraversableFactory;)V;
const #46 = NameAndType	#11:#45;//  "<init>":(Lscala/collection/generic/TraversableFactory;)V
const #47 = Method	#44.#46;	//  scala/collection/generic/TraversableFactory$GenericCanBuildFrom."<init>":(Lscala/collection/generic/TraversableFactory;)V
const #48 = Asciz	<A:Ljava/lang/Object;>()Lscala/collection/generic/CanBuildFrom<Lscala/collection/mutable/LinkedList<*>;TA;Lscala/collection/mutable/LinkedList<TA;>;>;;
const #49 = Asciz	scala/collection/mutable/LinkedList;
const #50 = class	#49;	//  scala/collection/mutable/LinkedList
const #51 = Method	#50.#12;	//  scala/collection/mutable/LinkedList."<init>":()V
const #52 = Asciz	<A:Ljava/lang/Object;>()Lscala/collection/mutable/LinkedList<TA;>;;
const #53 = Asciz	Lscala/collection/generic/SeqFactory<Lscala/collection/mutable/LinkedList;>;Lscala/ScalaObject;;
const #54 = Asciz	InnerClasses;
const #55 = Asciz	$anonfun$newBuilder$1;
const #56 = Asciz	scala/collection/generic/TraversableFactory;
const #57 = class	#56;	//  scala/collection/generic/TraversableFactory
const #58 = Asciz	GenericCanBuildFrom;
const #59 = Asciz	scala/ScalaObject;
const #60 = class	#59;	//  scala/ScalaObject

{
public static final scala.collection.mutable.LinkedList$ MODULE$;

public static {};
  Code:
   Stack=1, Locals=0, Args_size=0
   0:	new	#10; //class scala/collection/mutable/LinkedList$
   3:	invokespecial	#13; //Method "<init>":()V
   6:	return

public scala.collection.Traversable empty();
  Code:
   Stack=1, Locals=1, Args_size=1
   0:	aload_0
   1:	invokevirtual	#24; //Method empty:()Lscala/collection/mutable/LinkedList;
   4:	areturn
  LineNumberTable: 
   line 42: 0


public scala.collection.mutable.Builder newBuilder();
  Code:
   Stack=3, Locals=1, Args_size=1
   0:	new	#28; //class scala/collection/mutable/MutableList
   3:	dup
   4:	invokespecial	#29; //Method scala/collection/mutable/MutableList."<init>":()V
   7:	new	#31; //class scala/collection/mutable/LinkedList$$anonfun$newBuilder$1
   10:	dup
   11:	invokespecial	#32; //Method scala/collection/mutable/LinkedList$$anonfun$newBuilder$1."<init>":()V
   14:	invokeinterface	#38,  2; //InterfaceMethod scala/collection/mutable/Builder.mapResult:(Lscala/Function1;)Lscala/collection/mutable/Builder;
   19:	areturn
  LineNumberTable: 
   line 48: 0

  Signature: length = 0x2
   00 27 

public scala.collection.generic.CanBuildFrom canBuildFrom();
  Code:
   Stack=3, Locals=1, Args_size=1
   0:	new	#44; //class scala/collection/generic/TraversableFactory$GenericCanBuildFrom
   3:	dup
   4:	aload_0
   5:	invokespecial	#47; //Method scala/collection/generic/TraversableFactory$GenericCanBuildFrom."<init>":(Lscala/collection/generic/TraversableFactory;)V
   8:	areturn
  LineNumberTable: 
   line 46: 0

  Signature: length = 0x2
   00 30 

public scala.collection.mutable.LinkedList empty();
  Code:
   Stack=2, Locals=1, Args_size=1
   0:	new	#50; //class scala/collection/mutable/LinkedList
   3:	dup
   4:	invokespecial	#51; //Method scala/collection/mutable/LinkedList."<init>":()V
   7:	areturn
  LineNumberTable: 
   line 44: 0

  Signature: length = 0x2
   00 34 

}

