Compiled from "LinkedListLike.scala"
public final class scala.collection.mutable.LinkedListLike$$anonfun$apply$1 extends java.lang.Object implements scala.Function1,scala.ScalaObject,java.io.Serializable
  SourceFile: "LinkedListLike.scala"
  Scala: length = 0x
   
  InnerClass: 
   public final $anonfun$apply$1=class scala/collection/mutable/LinkedListLike$$anonfun$apply$1 of class scala/collection/mutable/LinkedListLike
  minor version: 0
  major version: 49
  Constant pool:
Asciz	SourceFile;
Asciz	LinkedListLike.scala;
Asciz	<clinit>;
Asciz	()V;
Asciz	Code;
Asciz	serialVersionUID;
Asciz	J;
Asciz	scala/collection/mutable/LinkedListLike$$anonfun$apply$1;
class	scala/collection/mutable/LinkedListLike$$anonfun$apply$1
NameAndType	serialVersionUID:J
Field	scala/collection/mutable/LinkedListLike$$anonfun$apply$1.serialVersionUID:J
Asciz	<init>;
Asciz	(Lscala/collection/mutable/LinkedListLike;)V;
Asciz	LineNumberTable;
Asciz	java/lang/Object;
class	java/lang/Object
NameAndType	"<init>":()V
Method	java/lang/Object."<init>":()V
Asciz	scala/Function1$class;
class	scala/Function1$class
Asciz	$init$;
Asciz	(Lscala/Function1;)V;
NameAndType	$init$:(Lscala/Function1;)V
Method	scala/Function1$class.$init$:(Lscala/Function1;)V
Asciz	this;
Asciz	Lscala/collection/mutable/LinkedListLike$$anonfun$apply$1;;
Asciz	$outer;
Asciz	Lscala/collection/mutable/LinkedListLike;;
Asciz	LocalVariableTable;
Asciz	(Lscala/collection/mutable/LinkedListLike<TA;TThis;>;)V;
Asciz	Signature;
Asciz	apply;
Asciz	(Ljava/lang/Object;)Ljava/lang/Object;;
Asciz	scala/collection/mutable/Seq;
class	scala/collection/mutable/Seq
Asciz	(Lscala/collection/mutable/Seq;)Ljava/lang/Object;;
NameAndType	apply:(Lscala/collection/mutable/Seq;)Ljava/lang/Object;
Method	scala/collection/mutable/LinkedListLike$$anonfun$apply$1.apply:(Lscala/collection/mutable/Seq;)Ljava/lang/Object;
Asciz	v1;
Asciz	Ljava/lang/Object;;
Asciz	scala/collection/mutable/LinkedListLike;
class	scala/collection/mutable/LinkedListLike
Asciz	elem;
Asciz	()Ljava/lang/Object;;
NameAndType	elem:()Ljava/lang/Object;
InterfaceMethod	scala/collection/mutable/LinkedListLike.elem:()Ljava/lang/Object;
Asciz	(TThis;)TA;;
Asciz	andThen;
Asciz	(Lscala/Function1;)Lscala/Function1;;
Asciz	(Lscala/Function1;Lscala/Function1;)Lscala/Function1;;
NameAndType	andThen:(Lscala/Function1;Lscala/Function1;)Lscala/Function1;
Method	scala/Function1$class.andThen:(Lscala/Function1;Lscala/Function1;)Lscala/Function1;
Asciz	g;
Asciz	Lscala/Function1;;
Asciz	compose;
NameAndType	compose:(Lscala/Function1;Lscala/Function1;)Lscala/Function1;
Method	scala/Function1$class.compose:(Lscala/Function1;Lscala/Function1;)Lscala/Function1;
Asciz	toString;
Asciz	()Ljava/lang/String;;
Asciz	(Lscala/Function1;)Ljava/lang/String;;
NameAndType	toString:(Lscala/Function1;)Ljava/lang/String;
Method	scala/Function1$class.toString:(Lscala/Function1;)Ljava/lang/String;
Asciz	Scala;
Asciz	InnerClasses;
Asciz	$anonfun$apply$1;
Asciz	scala/Function1;
class	scala/Function1
Asciz	scala/ScalaObject;
class	scala/ScalaObject
Asciz	java/io/Serializable;
class	java/io/Serializable

{
public static final long serialVersionUID;
  Signature: J

public static {};
  Signature: ()V
  Code:
   Stack=2, Locals=0, Args_size=0
	lconst_0
	putstatic	Field serialVersionUID:J
	return
  Labels:

public scala.collection.mutable.LinkedListLike$$anonfun$apply$1(scala.collection.mutable.LinkedListLike);
  Signature: (Lscala/collection/mutable/LinkedListLike;)V
  Code:
   Stack=1, Locals=2, Args_size=2
	aload_0
	invokespecial	Method java/lang/Object."<init>":()V
	aload_0
	invokestatic	Method scala/Function1$class.$init$:(Lscala/Function1;)V
	return
  Labels:
  LocalVariableTable: 
   Start  Length  Slot  Name   Signature
   0      9      0    this       Lscala/collection/mutable/LinkedListLike$$anonfun$apply$1;
   0      9      1    $outer       Lscala/collection/mutable/LinkedListLike;

  Signature: length = 0x2
   00 1E 

public final java.lang.Object apply(java.lang.Object);
  Signature: (Ljava/lang/Object;)Ljava/lang/Object;
  Code:
   Stack=2, Locals=2, Args_size=2
	aload_0
	aload_1
	checkcast	class scala/collection/mutable/Seq
	invokevirtual	Method apply:(Lscala/collection/mutable/Seq;)Ljava/lang/Object;
	areturn
  Labels:
  LocalVariableTable: 
   Start  Length  Slot  Name   Signature
   0      9      0    this       Lscala/collection/mutable/LinkedListLike$$anonfun$apply$1;
   0      9      1    v1       Ljava/lang/Object;


public final java.lang.Object apply(scala.collection.mutable.Seq);
  Signature: (Lscala/collection/mutable/Seq;)Ljava/lang/Object;
  Code:
   Stack=1, Locals=2, Args_size=2
	aload_1
	checkcast	class scala/collection/mutable/LinkedListLike
	invokeinterface	InterfaceMethod scala/collection/mutable/LinkedListLike.elem:()Ljava/lang/Object;
	areturn
  Labels:
  Signature: length = 0x2
   00 2F 

public scala.Function1 andThen(scala.Function1);
  Signature: (Lscala/Function1;)Lscala/Function1;
  Code:
   Stack=2, Locals=2, Args_size=2
	aload_0
	aload_1
	invokestatic	Method scala/Function1$class.andThen:(Lscala/Function1;Lscala/Function1;)Lscala/Function1;
	areturn
  Labels:
  LocalVariableTable: 
   Start  Length  Slot  Name   Signature
   0      6      0    this       Lscala/collection/mutable/LinkedListLike$$anonfun$apply$1;
   0      6      1    g       Lscala/Function1;


public scala.Function1 compose(scala.Function1);
  Signature: (Lscala/Function1;)Lscala/Function1;
  Code:
   Stack=2, Locals=2, Args_size=2
	aload_0
	aload_1
	invokestatic	Method scala/Function1$class.compose:(Lscala/Function1;Lscala/Function1;)Lscala/Function1;
	areturn
  Labels:
  LocalVariableTable: 
   Start  Length  Slot  Name   Signature
   0      6      0    this       Lscala/collection/mutable/LinkedListLike$$anonfun$apply$1;
   0      6      1    g       Lscala/Function1;


public java.lang.String toString();
  Signature: ()Ljava/lang/String;
  Code:
   Stack=1, Locals=1, Args_size=1
	aload_0
	invokestatic	Method scala/Function1$class.toString:(Lscala/Function1;)Ljava/lang/String;
	areturn
  Labels:

}

