Compiled from "LinkedListLike.scala"
public abstract class scala.collection.mutable.LinkedListLike$class extends java.lang.Object
  SourceFile: "LinkedListLike.scala"
  Scala: length = 0x
   
  InnerClass: 
   public final #174= #51 of #13; //$anon$1=class scala/collection/mutable/LinkedListLike$$anon$1 of class scala/collection/mutable/LinkedListLike
   public final #175= #158 of #13; //$anonfun$tail$1=class scala/collection/mutable/LinkedListLike$$anonfun$tail$1 of class scala/collection/mutable/LinkedListLike
   public final #176= #92 of #13; //$anonfun$apply$1=class scala/collection/mutable/LinkedListLike$$anonfun$apply$1 of class scala/collection/mutable/LinkedListLike
   public final #177= #121 of #13; //$anonfun$insert$1=class scala/collection/mutable/LinkedListLike$$anonfun$insert$1 of class scala/collection/mutable/LinkedListLike
   public final #178= #78 of #13; //$anonfun$update$1=class scala/collection/mutable/LinkedListLike$$anonfun$update$1 of class scala/collection/mutable/LinkedListLike
  minor version: 0
  major version: 49
  Constant pool:
const #1 = Asciz	SourceFile;
const #2 = Asciz	LinkedListLike.scala;
const #3 = Asciz	$init$;
const #4 = Asciz	(Lscala/collection/mutable/LinkedListLike;)V;
const #5 = Asciz	Code;
const #6 = Asciz	LineNumberTable;
const #7 = Asciz	$this;
const #8 = Asciz	Lscala/collection/mutable/LinkedListLike;;
const #9 = Asciz	LocalVariableTable;
const #10 = Asciz	loop$1;
const #11 = Asciz	(Lscala/collection/mutable/LinkedListLike;Lscala/collection/mutable/Seq;Lscala/collection/mutable/Seq;)V;
const #12 = Asciz	scala/collection/mutable/LinkedListLike;
const #13 = class	#12;	//  scala/collection/mutable/LinkedListLike
const #14 = Asciz	next;
const #15 = Asciz	()Lscala/collection/mutable/Seq;;
const #16 = NameAndType	#14:#15;//  next:()Lscala/collection/mutable/Seq;
const #17 = InterfaceMethod	#13.#16;	//  scala/collection/mutable/LinkedListLike.next:()Lscala/collection/mutable/Seq;
const #18 = Asciz	isEmpty;
const #19 = Asciz	()Z;
const #20 = NameAndType	#18:#19;//  isEmpty:()Z
const #21 = InterfaceMethod	#13.#20;	//  scala/collection/mutable/LinkedListLike.isEmpty:()Z
const #22 = Asciz	next_$eq;
const #23 = Asciz	(Lscala/collection/mutable/Seq;)V;
const #24 = NameAndType	#22:#23;//  next_$eq:(Lscala/collection/mutable/Seq;)V
const #25 = InterfaceMethod	#13.#24;	//  scala/collection/mutable/LinkedListLike.next_$eq:(Lscala/collection/mutable/Seq;)V
const #26 = Asciz	x;
const #27 = Asciz	Lscala/collection/mutable/Seq;;
const #28 = Asciz	foreach;
const #29 = Asciz	(Lscala/collection/mutable/LinkedListLike;Lscala/Function1;)V;
const #30 = Asciz	scala/collection/TraversableLike;
const #31 = class	#30;	//  scala/collection/TraversableLike
const #32 = Asciz	nonEmpty;
const #33 = NameAndType	#32:#19;//  nonEmpty:()Z
const #34 = InterfaceMethod	#31.#33;	//  scala/collection/TraversableLike.nonEmpty:()Z
const #35 = Asciz	elem;
const #36 = Asciz	()Ljava/lang/Object;;
const #37 = NameAndType	#35:#36;//  elem:()Ljava/lang/Object;
const #38 = InterfaceMethod	#13.#37;	//  scala/collection/mutable/LinkedListLike.elem:()Ljava/lang/Object;
const #39 = Asciz	scala/Function1;
const #40 = class	#39;	//  scala/Function1
const #41 = Asciz	apply;
const #42 = Asciz	(Ljava/lang/Object;)Ljava/lang/Object;;
const #43 = NameAndType	#41:#42;//  apply:(Ljava/lang/Object;)Ljava/lang/Object;
const #44 = InterfaceMethod	#40.#43;	//  scala/Function1.apply:(Ljava/lang/Object;)Ljava/lang/Object;
const #45 = Asciz	f;
const #46 = Asciz	Lscala/Function1;;
const #47 = Asciz	these;
const #48 = Asciz	iterator;
const #49 = Asciz	(Lscala/collection/mutable/LinkedListLike;)Lscala/collection/Iterator;;
const #50 = Asciz	scala/collection/mutable/LinkedListLike$$anon$1;
const #51 = class	#50;	//  scala/collection/mutable/LinkedListLike$$anon$1
const #52 = Asciz	<init>;
const #53 = NameAndType	#52:#4;//  "<init>":(Lscala/collection/mutable/LinkedListLike;)V
const #54 = Method	#51.#53;	//  scala/collection/mutable/LinkedListLike$$anon$1."<init>":(Lscala/collection/mutable/LinkedListLike;)V
const #55 = Asciz	get;
const #56 = Asciz	(Lscala/collection/mutable/LinkedListLike;I)Lscala/Option;;
const #57 = Asciz	drop;
const #58 = Asciz	(I)Lscala/collection/mutable/Seq;;
const #59 = NameAndType	#57:#58;//  drop:(I)Lscala/collection/mutable/Seq;
const #60 = InterfaceMethod	#13.#59;	//  scala/collection/mutable/LinkedListLike.drop:(I)Lscala/collection/mutable/Seq;
const #61 = Asciz	scala/Some;
const #62 = class	#61;	//  scala/Some
const #63 = Asciz	(Ljava/lang/Object;)V;
const #64 = NameAndType	#52:#63;//  "<init>":(Ljava/lang/Object;)V
const #65 = Method	#62.#64;	//  scala/Some."<init>":(Ljava/lang/Object;)V
const #66 = Asciz	scala/None$;
const #67 = class	#66;	//  scala/None$
const #68 = Asciz	MODULE$;
const #69 = Asciz	Lscala/None$;;
const #70 = NameAndType	#68:#69;//  MODULE$:Lscala/None$;
const #71 = Field	#67.#70;	//  scala/None$.MODULE$:Lscala/None$;
const #72 = Asciz	n;
const #73 = Asciz	I;
const #74 = Asciz	loc;
const #75 = Asciz	update;
const #76 = Asciz	(Lscala/collection/mutable/LinkedListLike;ILjava/lang/Object;)V;
const #77 = Asciz	scala/collection/mutable/LinkedListLike$$anonfun$update$1;
const #78 = class	#77;	//  scala/collection/mutable/LinkedListLike$$anonfun$update$1
const #79 = Asciz	(Lscala/collection/mutable/LinkedListLike;Ljava/lang/Object;)V;
const #80 = NameAndType	#52:#79;//  "<init>":(Lscala/collection/mutable/LinkedListLike;Ljava/lang/Object;)V
const #81 = Method	#78.#80;	//  scala/collection/mutable/LinkedListLike$$anonfun$update$1."<init>":(Lscala/collection/mutable/LinkedListLike;Ljava/lang/Object;)V
const #82 = Asciz	scala/collection/mutable/LinkedListLike$class;
const #83 = class	#82;	//  scala/collection/mutable/LinkedListLike$class
const #84 = Asciz	atLocation;
const #85 = Asciz	(Lscala/collection/mutable/LinkedListLike;ILscala/Function1;)Ljava/lang/Object;;
const #86 = NameAndType	#84:#85;//  atLocation:(Lscala/collection/mutable/LinkedListLike;ILscala/Function1;)Ljava/lang/Object;
const #87 = Method	#83.#86;	//  scala/collection/mutable/LinkedListLike$class.atLocation:(Lscala/collection/mutable/LinkedListLike;ILscala/Function1;)Ljava/lang/Object;
const #88 = Asciz	x$3;
const #89 = Asciz	Ljava/lang/Object;;
const #90 = Asciz	(Lscala/collection/mutable/LinkedListLike;I)Ljava/lang/Object;;
const #91 = Asciz	scala/collection/mutable/LinkedListLike$$anonfun$apply$1;
const #92 = class	#91;	//  scala/collection/mutable/LinkedListLike$$anonfun$apply$1
const #93 = Method	#92.#53;	//  scala/collection/mutable/LinkedListLike$$anonfun$apply$1."<init>":(Lscala/collection/mutable/LinkedListLike;)V
const #94 = Asciz	java/lang/IndexOutOfBoundsException;
const #95 = class	#94;	//  java/lang/IndexOutOfBoundsException
const #96 = Asciz	scala/runtime/BoxesRunTime;
const #97 = class	#96;	//  scala/runtime/BoxesRunTime
const #98 = Asciz	boxToInteger;
const #99 = Asciz	(I)Ljava/lang/Integer;;
const #100 = NameAndType	#98:#99;//  boxToInteger:(I)Ljava/lang/Integer;
const #101 = Method	#97.#100;	//  scala/runtime/BoxesRunTime.boxToInteger:(I)Ljava/lang/Integer;
const #102 = Asciz	java/lang/Object;
const #103 = class	#102;	//  java/lang/Object
const #104 = Asciz	toString;
const #105 = Asciz	()Ljava/lang/String;;
const #106 = NameAndType	#104:#105;//  toString:()Ljava/lang/String;
const #107 = Method	#103.#106;	//  java/lang/Object.toString:()Ljava/lang/String;
const #108 = Asciz	(Ljava/lang/String;)V;
const #109 = NameAndType	#52:#108;//  "<init>":(Ljava/lang/String;)V
const #110 = Method	#95.#109;	//  java/lang/IndexOutOfBoundsException."<init>":(Ljava/lang/String;)V
const #111 = Asciz	(Lscala/collection/mutable/LinkedListLike;I)Lscala/collection/mutable/Seq;;
const #112 = Asciz	repr;
const #113 = NameAndType	#112:#36;//  repr:()Ljava/lang/Object;
const #114 = InterfaceMethod	#31.#113;	//  scala/collection/TraversableLike.repr:()Ljava/lang/Object;
const #115 = Asciz	scala/collection/mutable/Seq;
const #116 = class	#115;	//  scala/collection/mutable/Seq
const #117 = Asciz	i;
const #118 = Asciz	insert;
const #119 = Asciz	(Lscala/collection/mutable/LinkedListLike;Lscala/collection/mutable/Seq;)V;
const #120 = Asciz	scala/collection/mutable/LinkedListLike$$anonfun$insert$1;
const #121 = class	#120;	//  scala/collection/mutable/LinkedListLike$$anonfun$insert$1
const #122 = Method	#121.#53;	//  scala/collection/mutable/LinkedListLike$$anonfun$insert$1."<init>":(Lscala/collection/mutable/LinkedListLike;)V
const #123 = Asciz	append;
const #124 = Asciz	(Lscala/collection/mutable/Seq;)Lscala/collection/mutable/Seq;;
const #125 = NameAndType	#123:#124;//  append:(Lscala/collection/mutable/Seq;)Lscala/collection/mutable/Seq;
const #126 = InterfaceMethod	#13.#125;	//  scala/collection/mutable/LinkedListLike.append:(Lscala/collection/mutable/Seq;)Lscala/collection/mutable/Seq;
const #127 = Asciz	java/lang/IllegalArgumentException;
const #128 = class	#127;	//  java/lang/IllegalArgumentException
const #129 = Asciz	scala/collection/mutable/StringBuilder;
const #130 = class	#129;	//  scala/collection/mutable/StringBuilder
const #131 = Asciz	()V;
const #132 = NameAndType	#52:#131;//  "<init>":()V
const #133 = Method	#130.#132;	//  scala/collection/mutable/StringBuilder."<init>":()V
const #134 = Asciz	requirement failed: ;
const #135 = String	#134;	//  requirement failed: 
const #136 = Asciz	(Ljava/lang/Object;)Lscala/collection/mutable/StringBuilder;;
const #137 = NameAndType	#123:#136;//  append:(Ljava/lang/Object;)Lscala/collection/mutable/StringBuilder;
const #138 = Method	#130.#137;	//  scala/collection/mutable/StringBuilder.append:(Ljava/lang/Object;)Lscala/collection/mutable/StringBuilder;
const #139 = Asciz	insert into empty list;
const #140 = String	#139;	//  insert into empty list
const #141 = Method	#130.#106;	//  scala/collection/mutable/StringBuilder.toString:()Ljava/lang/String;
const #142 = Method	#128.#109;	//  java/lang/IllegalArgumentException."<init>":(Ljava/lang/String;)V
const #143 = Asciz	that;
const #144 = Asciz	requirement0;
const #145 = Asciz	Z;
const #146 = Asciz	(Lscala/collection/mutable/LinkedListLike;Lscala/collection/mutable/Seq;)Lscala/collection/mutable/Seq;;
const #147 = NameAndType	#10:#11;//  loop$1:(Lscala/collection/mutable/LinkedListLike;Lscala/collection/mutable/Seq;Lscala/collection/mutable/Seq;)V
const #148 = Method	#83.#147;	//  scala/collection/mutable/LinkedListLike$class.loop$1:(Lscala/collection/mutable/LinkedListLike;Lscala/collection/mutable/Seq;Lscala/collection/mutable/Seq;)V
const #149 = Asciz	that$1;
const #150 = Asciz	tail;
const #151 = Asciz	(Lscala/collection/mutable/LinkedListLike;)Lscala/collection/mutable/Seq;;
const #152 = Asciz	scala/Predef$;
const #153 = class	#152;	//  scala/Predef$
const #154 = Asciz	Lscala/Predef$;;
const #155 = NameAndType	#68:#154;//  MODULE$:Lscala/Predef$;
const #156 = Field	#153.#155;	//  scala/Predef$.MODULE$:Lscala/Predef$;
const #157 = Asciz	scala/collection/mutable/LinkedListLike$$anonfun$tail$1;
const #158 = class	#157;	//  scala/collection/mutable/LinkedListLike$$anonfun$tail$1
const #159 = Method	#158.#53;	//  scala/collection/mutable/LinkedListLike$$anonfun$tail$1."<init>":(Lscala/collection/mutable/LinkedListLike;)V
const #160 = Asciz	require;
const #161 = Asciz	(ZLscala/Function0;)V;
const #162 = NameAndType	#160:#161;//  require:(ZLscala/Function0;)V
const #163 = Method	#153.#162;	//  scala/Predef$.require:(ZLscala/Function0;)V
const #164 = Asciz	head;
const #165 = Asciz	(Lscala/collection/mutable/LinkedListLike;)Ljava/lang/Object;;
const #166 = Asciz	length;
const #167 = Asciz	(Lscala/collection/mutable/LinkedListLike;)I;
const #168 = Asciz	()I;
const #169 = NameAndType	#166:#168;//  length:()I
const #170 = InterfaceMethod	#13.#169;	//  scala/collection/mutable/LinkedListLike.length:()I
const #171 = Asciz	(Lscala/collection/mutable/LinkedListLike;)Z;
const #172 = Asciz	Scala;
const #173 = Asciz	InnerClasses;
const #174 = Asciz	$anon$1;
const #175 = Asciz	$anonfun$tail$1;
const #176 = Asciz	$anonfun$apply$1;
const #177 = Asciz	$anonfun$insert$1;
const #178 = Asciz	$anonfun$update$1;

{
public static void $init$(scala.collection.mutable.LinkedListLike);
  Code:
   Stack=0, Locals=1, Args_size=1
   0:	return
  LineNumberTable: 
   line 27: 0

  LocalVariableTable: 
   Start  Length  Slot  Name   Signature
   0      1      0    $this       Lscala/collection/mutable/LinkedListLike;


public static void foreach(scala.collection.mutable.LinkedListLike, scala.Function1);
  Code:
   Stack=2, Locals=3, Args_size=2
   0:	aload_0
   1:	astore_2
   2:	aload_2
   3:	invokeinterface	#34,  1; //InterfaceMethod scala/collection/TraversableLike.nonEmpty:()Z
   8:	ifeq	37
   11:	aload_1
   12:	aload_2
   13:	invokeinterface	#38,  1; //InterfaceMethod scala/collection/mutable/LinkedListLike.elem:()Ljava/lang/Object;
   18:	invokeinterface	#44,  2; //InterfaceMethod scala/Function1.apply:(Ljava/lang/Object;)Ljava/lang/Object;
   23:	pop
   24:	aload_2
   25:	invokeinterface	#17,  1; //InterfaceMethod scala/collection/mutable/LinkedListLike.next:()Lscala/collection/mutable/Seq;
   30:	checkcast	#13; //class scala/collection/mutable/LinkedListLike
   33:	astore_2
   34:	goto	2
   37:	return
  LineNumberTable: 
   line 104: 0
   line 105: 2
   line 106: 11
   line 107: 24
   line 103: 37

  LocalVariableTable: 
   Start  Length  Slot  Name   Signature
   0      38      0    $this       Lscala/collection/mutable/LinkedListLike;
   0      38      1    f       Lscala/Function1;
   2      36      2    these       Lscala/collection/mutable/LinkedListLike;


public static scala.collection.Iterator iterator(scala.collection.mutable.LinkedListLike);
  Code:
   Stack=3, Locals=1, Args_size=1
   0:	new	#51; //class scala/collection/mutable/LinkedListLike$$anon$1
   3:	dup
   4:	aload_0
   5:	invokespecial	#54; //Method scala/collection/mutable/LinkedListLike$$anon$1."<init>":(Lscala/collection/mutable/LinkedListLike;)V
   8:	areturn
  LineNumberTable: 
   line 93: 0

  LocalVariableTable: 
   Start  Length  Slot  Name   Signature
   0      9      0    $this       Lscala/collection/mutable/LinkedListLike;


public static scala.Option get(scala.collection.mutable.LinkedListLike, int);
  Code:
   Stack=3, Locals=3, Args_size=2
   0:	aload_0
   1:	iload_1
   2:	invokeinterface	#60,  2; //InterfaceMethod scala/collection/mutable/LinkedListLike.drop:(I)Lscala/collection/mutable/Seq;
   7:	astore_2
   8:	aload_2
   9:	invokeinterface	#34,  1; //InterfaceMethod scala/collection/TraversableLike.nonEmpty:()Z
   14:	ifeq	36
   17:	new	#62; //class scala/Some
   20:	dup
   21:	aload_2
   22:	checkcast	#13; //class scala/collection/mutable/LinkedListLike
   25:	invokeinterface	#38,  1; //InterfaceMethod scala/collection/mutable/LinkedListLike.elem:()Ljava/lang/Object;
   30:	invokespecial	#65; //Method scala/Some."<init>":(Ljava/lang/Object;)V
   33:	goto	39
   36:	getstatic	#71; //Field scala/None$.MODULE$:Lscala/None$;
   39:	areturn
  LineNumberTable: 
   line 88: 0
   line 89: 8
   line 90: 36
   line 87: 39

  LocalVariableTable: 
   Start  Length  Slot  Name   Signature
   0      40      0    $this       Lscala/collection/mutable/LinkedListLike;
   0      40      1    n       I
   8      32      2    loc       Lscala/collection/mutable/Seq;


public static void update(scala.collection.mutable.LinkedListLike, int, java.lang.Object);
  Code:
   Stack=6, Locals=3, Args_size=3
   0:	aload_0
   1:	iload_1
   2:	new	#78; //class scala/collection/mutable/LinkedListLike$$anonfun$update$1
   5:	dup
   6:	aload_0
   7:	aload_2
   8:	invokespecial	#81; //Method scala/collection/mutable/LinkedListLike$$anonfun$update$1."<init>":(Lscala/collection/mutable/LinkedListLike;Ljava/lang/Object;)V
   11:	invokestatic	#87; //Method atLocation:(Lscala/collection/mutable/LinkedListLike;ILscala/Function1;)Ljava/lang/Object;
   14:	pop
   15:	return
  LineNumberTable: 
   line 85: 0

  LocalVariableTable: 
   Start  Length  Slot  Name   Signature
   0      16      0    $this       Lscala/collection/mutable/LinkedListLike;
   0      16      1    n       I
   0      16      2    x$3       Ljava/lang/Object;


public static java.lang.Object apply(scala.collection.mutable.LinkedListLike, int);
  Code:
   Stack=5, Locals=2, Args_size=2
   0:	aload_0
   1:	iload_1
   2:	new	#92; //class scala/collection/mutable/LinkedListLike$$anonfun$apply$1
   5:	dup
   6:	aload_0
   7:	invokespecial	#93; //Method scala/collection/mutable/LinkedListLike$$anonfun$apply$1."<init>":(Lscala/collection/mutable/LinkedListLike;)V
   10:	invokestatic	#87; //Method atLocation:(Lscala/collection/mutable/LinkedListLike;ILscala/Function1;)Ljava/lang/Object;
   13:	areturn
  LineNumberTable: 
   line 84: 0

  LocalVariableTable: 
   Start  Length  Slot  Name   Signature
   0      14      0    $this       Lscala/collection/mutable/LinkedListLike;
   0      14      1    n       I


public static scala.collection.mutable.Seq drop(scala.collection.mutable.LinkedListLike, int);
  Code:
   Stack=2, Locals=4, Args_size=2
   0:	iconst_0
   1:	istore_2
   2:	aload_0
   3:	invokeinterface	#114,  1; //InterfaceMethod scala/collection/TraversableLike.repr:()Ljava/lang/Object;
   8:	checkcast	#116; //class scala/collection/mutable/Seq
   11:	astore_3
   12:	iload_2
   13:	iload_1
   14:	if_icmpge	46
   17:	aload_3
   18:	checkcast	#13; //class scala/collection/mutable/LinkedListLike
   21:	invokeinterface	#21,  1; //InterfaceMethod scala/collection/mutable/LinkedListLike.isEmpty:()Z
   26:	ifne	46
   29:	aload_3
   30:	checkcast	#13; //class scala/collection/mutable/LinkedListLike
   33:	invokeinterface	#17,  1; //InterfaceMethod scala/collection/mutable/LinkedListLike.next:()Lscala/collection/mutable/Seq;
   38:	astore_3
   39:	iload_2
   40:	iconst_1
   41:	iadd
   42:	istore_2
   43:	goto	12
   46:	aload_3
   47:	areturn
  LineNumberTable: 
   line 69: 0
   line 70: 2
   line 71: 12
   line 72: 29
   line 73: 39
   line 75: 46

  LocalVariableTable: 
   Start  Length  Slot  Name   Signature
   0      48      0    $this       Lscala/collection/mutable/LinkedListLike;
   0      48      1    n       I
   2      45      2    i       I
   12      35      3    these       Lscala/collection/mutable/Seq;


public static void insert(scala.collection.mutable.LinkedListLike, scala.collection.mutable.Seq);
  Code:
   Stack=4, Locals=3, Args_size=2
   0:	aload_0
   1:	invokeinterface	#34,  1; //InterfaceMethod scala/collection/TraversableLike.nonEmpty:()Z
   6:	new	#121; //class scala/collection/mutable/LinkedListLike$$anonfun$insert$1
   9:	dup
   10:	pop
   11:	aload_0
   12:	invokespecial	#122; //Method scala/collection/mutable/LinkedListLike$$anonfun$insert$1."<init>":(Lscala/collection/mutable/LinkedListLike;)V
   15:	istore_2
   16:	iload_2
   17:	ifeq	53
   20:	aload_1
   21:	invokeinterface	#34,  1; //InterfaceMethod scala/collection/TraversableLike.nonEmpty:()Z
   26:	ifeq	52
   29:	aload_1
   30:	checkcast	#13; //class scala/collection/mutable/LinkedListLike
   33:	aload_0
   34:	invokeinterface	#17,  1; //InterfaceMethod scala/collection/mutable/LinkedListLike.next:()Lscala/collection/mutable/Seq;
   39:	invokeinterface	#126,  2; //InterfaceMethod scala/collection/mutable/LinkedListLike.append:(Lscala/collection/mutable/Seq;)Lscala/collection/mutable/Seq;
   44:	pop
   45:	aload_0
   46:	aload_1
   47:	invokeinterface	#25,  2; //InterfaceMethod scala/collection/mutable/LinkedListLike.next_$eq:(Lscala/collection/mutable/Seq;)V
   52:	return
   53:	new	#128; //class java/lang/IllegalArgumentException
   56:	dup
   57:	new	#130; //class scala/collection/mutable/StringBuilder
   60:	dup
   61:	invokespecial	#133; //Method scala/collection/mutable/StringBuilder."<init>":()V
   64:	ldc	#135; //String requirement failed: 
   66:	invokevirtual	#138; //Method scala/collection/mutable/StringBuilder.append:(Ljava/lang/Object;)Lscala/collection/mutable/StringBuilder;
   69:	ldc	#140; //String insert into empty list
   71:	invokevirtual	#138; //Method scala/collection/mutable/StringBuilder.append:(Ljava/lang/Object;)Lscala/collection/mutable/StringBuilder;
   74:	invokevirtual	#141; //Method scala/collection/mutable/StringBuilder.toString:()Ljava/lang/String;
   77:	invokespecial	#142; //Method java/lang/IllegalArgumentException."<init>":(Ljava/lang/String;)V
   80:	athrow
  LineNumberTable: 
   line 61: 0
   line 62: 20
   line 63: 29
   line 64: 45
   line 60: 52
   line 61: 53

  LocalVariableTable: 
   Start  Length  Slot  Name   Signature
   0      81      0    $this       Lscala/collection/mutable/LinkedListLike;
   0      81      1    that       Lscala/collection/mutable/Seq;
   20      9      2    requirement0       Z
   53      28      2    requirement0       Z


public static scala.collection.mutable.Seq append(scala.collection.mutable.LinkedListLike, scala.collection.mutable.Seq);
  Code:
   Stack=3, Locals=2, Args_size=2
   0:	aload_0
   1:	invokeinterface	#21,  1; //InterfaceMethod scala/collection/mutable/LinkedListLike.isEmpty:()Z
   6:	ifeq	13
   9:	aload_1
   10:	goto	36
   13:	aload_0
   14:	aload_0
   15:	invokeinterface	#114,  1; //InterfaceMethod scala/collection/TraversableLike.repr:()Ljava/lang/Object;
   20:	checkcast	#116; //class scala/collection/mutable/Seq
   23:	aload_1
   24:	invokestatic	#148; //Method loop$1:(Lscala/collection/mutable/LinkedListLike;Lscala/collection/mutable/Seq;Lscala/collection/mutable/Seq;)V
   27:	aload_0
   28:	invokeinterface	#114,  1; //InterfaceMethod scala/collection/TraversableLike.repr:()Ljava/lang/Object;
   33:	checkcast	#116; //class scala/collection/mutable/Seq
   36:	areturn
  LineNumberTable: 
   line 53: 0
   line 54: 13
   line 53: 36

  LocalVariableTable: 
   Start  Length  Slot  Name   Signature
   0      37      0    $this       Lscala/collection/mutable/LinkedListLike;
   0      37      1    that$1       Lscala/collection/mutable/Seq;


public static scala.collection.mutable.Seq tail(scala.collection.mutable.LinkedListLike);
  Code:
   Stack=5, Locals=1, Args_size=1
   0:	getstatic	#156; //Field scala/Predef$.MODULE$:Lscala/Predef$;
   3:	aload_0
   4:	invokeinterface	#34,  1; //InterfaceMethod scala/collection/TraversableLike.nonEmpty:()Z
   9:	new	#158; //class scala/collection/mutable/LinkedListLike$$anonfun$tail$1
   12:	dup
   13:	aload_0
   14:	invokespecial	#159; //Method scala/collection/mutable/LinkedListLike$$anonfun$tail$1."<init>":(Lscala/collection/mutable/LinkedListLike;)V
   17:	invokevirtual	#163; //Method scala/Predef$.require:(ZLscala/Function0;)V
   20:	aload_0
   21:	invokeinterface	#17,  1; //InterfaceMethod scala/collection/mutable/LinkedListLike.next:()Lscala/collection/mutable/Seq;
   26:	areturn
  LineNumberTable: 
   line 39: 0
   line 40: 20

  LocalVariableTable: 
   Start  Length  Slot  Name   Signature
   0      27      0    $this       Lscala/collection/mutable/LinkedListLike;


public static java.lang.Object head(scala.collection.mutable.LinkedListLike);
  Code:
   Stack=1, Locals=1, Args_size=1
   0:	aload_0
   1:	invokeinterface	#38,  1; //InterfaceMethod scala/collection/mutable/LinkedListLike.elem:()Ljava/lang/Object;
   6:	areturn
  LineNumberTable: 
   line 36: 0

  LocalVariableTable: 
   Start  Length  Slot  Name   Signature
   0      7      0    $this       Lscala/collection/mutable/LinkedListLike;


public static int length(scala.collection.mutable.LinkedListLike);
  Code:
   Stack=2, Locals=1, Args_size=1
   0:	aload_0
   1:	invokeinterface	#21,  1; //InterfaceMethod scala/collection/mutable/LinkedListLike.isEmpty:()Z
   6:	ifeq	13
   9:	iconst_0
   10:	goto	29
   13:	aload_0
   14:	invokeinterface	#17,  1; //InterfaceMethod scala/collection/mutable/LinkedListLike.next:()Lscala/collection/mutable/Seq;
   19:	checkcast	#13; //class scala/collection/mutable/LinkedListLike
   22:	invokeinterface	#170,  1; //InterfaceMethod scala/collection/mutable/LinkedListLike.length:()I
   27:	iconst_1
   28:	iadd
   29:	ireturn
  LineNumberTable: 
   line 34: 0

  LocalVariableTable: 
   Start  Length  Slot  Name   Signature
   0      30      0    $this       Lscala/collection/mutable/LinkedListLike;


public static boolean isEmpty(scala.collection.mutable.LinkedListLike);
  Code:
   Stack=2, Locals=1, Args_size=1
   0:	aload_0
   1:	invokeinterface	#17,  1; //InterfaceMethod scala/collection/mutable/LinkedListLike.next:()Lscala/collection/mutable/Seq;
   6:	aload_0
   7:	if_acmpne	14
   10:	iconst_1
   11:	goto	15
   14:	iconst_0
   15:	ireturn
  LineNumberTable: 
   line 32: 0

  LocalVariableTable: 
   Start  Length  Slot  Name   Signature
   0      16      0    $this       Lscala/collection/mutable/LinkedListLike;


}

