Compiled from "LinkedHashSet.scala"
public final class scala.collection.mutable.LinkedHashSet$$anonfun$readObject$1 extends scala.runtime.AbstractFunction1 implements java.io.Serializable
  SourceFile: "LinkedHashSet.scala"
  Scala: length = 0x
   
  InnerClass: 
   public final #54= #9 of #53; //$anonfun$readObject$1=class scala/collection/mutable/LinkedHashSet$$anonfun$readObject$1 of class scala/collection/mutable/LinkedHashSet
  minor version: 0
  major version: 49
  Constant pool:
const #1 = Asciz	SourceFile;
const #2 = Asciz	LinkedHashSet.scala;
const #3 = Asciz	<clinit>;
const #4 = Asciz	()V;
const #5 = Asciz	Code;
const #6 = Asciz	serialVersionUID;
const #7 = Asciz	J;
const #8 = Asciz	scala/collection/mutable/LinkedHashSet$$anonfun$readObject$1;
const #9 = class	#8;	//  scala/collection/mutable/LinkedHashSet$$anonfun$readObject$1
const #10 = NameAndType	#6:#7;//  serialVersionUID:J
const #11 = Field	#9.#10;	//  scala/collection/mutable/LinkedHashSet$$anonfun$readObject$1.serialVersionUID:J
const #12 = Asciz	eta$0$1$1;
const #13 = Asciz	Lscala/collection/mutable/ListBuffer;;
const #14 = Asciz	<init>;
const #15 = Asciz	(Lscala/collection/mutable/LinkedHashSet;Lscala/collection/mutable/ListBuffer;)V;
const #16 = Asciz	LineNumberTable;
const #17 = NameAndType	#12:#13;//  eta$0$1$1:Lscala/collection/mutable/ListBuffer;
const #18 = Field	#9.#17;	//  scala/collection/mutable/LinkedHashSet$$anonfun$readObject$1.eta$0$1$1:Lscala/collection/mutable/ListBuffer;
const #19 = Asciz	scala/runtime/AbstractFunction1;
const #20 = class	#19;	//  scala/runtime/AbstractFunction1
const #21 = NameAndType	#14:#4;//  "<init>":()V
const #22 = Method	#20.#21;	//  scala/runtime/AbstractFunction1."<init>":()V
const #23 = Asciz	this;
const #24 = Asciz	Lscala/collection/mutable/LinkedHashSet$$anonfun$readObject$1;;
const #25 = Asciz	$outer;
const #26 = Asciz	Lscala/collection/mutable/LinkedHashSet;;
const #27 = Asciz	LocalVariableTable;
const #28 = Asciz	(Lscala/collection/mutable/LinkedHashSet<TA;>;)V;
const #29 = Asciz	Signature;
const #30 = Asciz	apply;
const #31 = Asciz	(Ljava/lang/Object;)Ljava/lang/Object;;
const #32 = Asciz	(Ljava/lang/Object;)V;
const #33 = NameAndType	#30:#32;//  apply:(Ljava/lang/Object;)V
const #34 = Method	#9.#33;	//  scala/collection/mutable/LinkedHashSet$$anonfun$readObject$1.apply:(Ljava/lang/Object;)V
const #35 = Asciz	scala/runtime/BoxedUnit;
const #36 = class	#35;	//  scala/runtime/BoxedUnit
const #37 = Asciz	UNIT;
const #38 = Asciz	Lscala/runtime/BoxedUnit;;
const #39 = NameAndType	#37:#38;//  UNIT:Lscala/runtime/BoxedUnit;
const #40 = Field	#36.#39;	//  scala/runtime/BoxedUnit.UNIT:Lscala/runtime/BoxedUnit;
const #41 = Asciz	v1;
const #42 = Asciz	Ljava/lang/Object;;
const #43 = Asciz	scala/collection/mutable/ListBuffer;
const #44 = class	#43;	//  scala/collection/mutable/ListBuffer
const #45 = Asciz	$plus$eq;
const #46 = Asciz	(Ljava/lang/Object;)Lscala/collection/mutable/ListBuffer;;
const #47 = NameAndType	#45:#46;//  $plus$eq:(Ljava/lang/Object;)Lscala/collection/mutable/ListBuffer;
const #48 = Method	#44.#47;	//  scala/collection/mutable/ListBuffer.$plus$eq:(Ljava/lang/Object;)Lscala/collection/mutable/ListBuffer;
const #49 = Asciz	(TA;)V;
const #50 = Asciz	Scala;
const #51 = Asciz	InnerClasses;
const #52 = Asciz	scala/collection/mutable/LinkedHashSet;
const #53 = class	#52;	//  scala/collection/mutable/LinkedHashSet
const #54 = Asciz	$anonfun$readObject$1;
const #55 = Asciz	java/io/Serializable;
const #56 = class	#55;	//  java/io/Serializable

{
public static final long serialVersionUID;

public static {};
  Code:
   Stack=2, Locals=0, Args_size=0
   0:	lconst_0
   1:	putstatic	#11; //Field serialVersionUID:J
   4:	return

public scala.collection.mutable.LinkedHashSet$$anonfun$readObject$1(scala.collection.mutable.LinkedHashSet, scala.collection.mutable.ListBuffer);
  Code:
   Stack=2, Locals=3, Args_size=3
   0:	aload_0
   1:	aload_2
   2:	putfield	#18; //Field eta$0$1$1:Lscala/collection/mutable/ListBuffer;
   5:	aload_0
   6:	invokespecial	#22; //Method scala/runtime/AbstractFunction1."<init>":()V
   9:	return
  LineNumberTable: 
   line 62: 0

  LocalVariableTable: 
   Start  Length  Slot  Name   Signature
   0      10      0    this       Lscala/collection/mutable/LinkedHashSet$$anonfun$readObject$1;
   0      10      1    $outer       Lscala/collection/mutable/LinkedHashSet;

  Signature: length = 0x2
   00 1C 

public final java.lang.Object apply(java.lang.Object);
  Code:
   Stack=2, Locals=2, Args_size=2
   0:	aload_0
   1:	aload_1
   2:	invokevirtual	#34; //Method apply:(Ljava/lang/Object;)V
   5:	getstatic	#40; //Field scala/runtime/BoxedUnit.UNIT:Lscala/runtime/BoxedUnit;
   8:	areturn
  LineNumberTable: 
   line 62: 0

  LocalVariableTable: 
   Start  Length  Slot  Name   Signature
   0      9      0    this       Lscala/collection/mutable/LinkedHashSet$$anonfun$readObject$1;
   0      9      1    v1       Ljava/lang/Object;


public final void apply(java.lang.Object);
  Code:
   Stack=2, Locals=2, Args_size=2
   0:	aload_0
   1:	getfield	#18; //Field eta$0$1$1:Lscala/collection/mutable/ListBuffer;
   4:	aload_1
   5:	invokevirtual	#48; //Method scala/collection/mutable/ListBuffer.$plus$eq:(Ljava/lang/Object;)Lscala/collection/mutable/ListBuffer;
   8:	pop
   9:	return
  LineNumberTable: 
   line 62: 0

  Signature: length = 0x2
   00 31 

}

