Compiled from "ListBuffer.scala"
public final class scala.collection.mutable.ListBuffer$$anonfun$equals$1 extends java.lang.Object implements java.io.Serializable,scala.Function1
  InnerClass: 
   public final $anonfun$equals$1=class scala/collection/mutable/ListBuffer$$anonfun$equals$1 of class scala/collection/mutable/ListBuffer
  Scala: length = 0x
   
  SourceFile: "ListBuffer.scala"
  minor version: 0
  major version: 49
  Constant pool:
class	java/io/Serializable
class	java/lang/Object
class	scala/Function1
class	scala/Function1$class
class	scala/MatchError
class	scala/Tuple2
class	scala/collection/mutable/ListBuffer
class	scala/collection/mutable/ListBuffer$$anonfun$equals$1
class	scala/runtime/BoxesRunTime
Method	java/lang/Object."<init>":()V
Method	scala/Function1$class.$init$:(Lscala/Function1;)V
Method	scala/Function1$class.toString:(Lscala/Function1;)Ljava/lang/String;
Method	scala/MatchError."<init>":(Ljava/lang/Object;)V
Method	scala/Tuple2._1:()Ljava/lang/Object;
Method	scala/Tuple2._2:()Ljava/lang/Object;
Method	scala/collection/mutable/ListBuffer$$anonfun$equals$1.apply:(Lscala/Tuple2;)Z
Method	scala/runtime/BoxesRunTime.boxToBoolean:(Z)Ljava/lang/Boolean;
Method	scala/runtime/BoxesRunTime.equals:(Ljava/lang/Object;Ljava/lang/Object;)Z
NameAndType	$init$:(Lscala/Function1;)V
NameAndType	"<init>":()V
NameAndType	"<init>":(Ljava/lang/Object;)V
NameAndType	_1:()Ljava/lang/Object;
NameAndType	_2:()Ljava/lang/Object;
NameAndType	apply:(Lscala/Tuple2;)Z
NameAndType	boxToBoolean:(Z)Ljava/lang/Boolean;
NameAndType	equals:(Ljava/lang/Object;Ljava/lang/Object;)Z
NameAndType	toString:(Lscala/Function1;)Ljava/lang/String;
Asciz	$anonfun$equals$1;
Asciz	$init$;
Asciz	$outer;
Asciz	()Ljava/lang/Object;;
Asciz	()Ljava/lang/String;;
Asciz	()V;
Asciz	(Ljava/lang/Object;)Ljava/lang/Object;;
Asciz	(Ljava/lang/Object;)V;
Asciz	(Ljava/lang/Object;Ljava/lang/Object;)Z;
Asciz	(Lscala/Function1;)Ljava/lang/String;;
Asciz	(Lscala/Function1;)V;
Asciz	(Lscala/Tuple2;)Z;
Asciz	(Lscala/Tuple2<TA;Ljava/lang/Object;>;)Z;
Asciz	(Lscala/collection/mutable/ListBuffer;)V;
Asciz	(Lscala/collection/mutable/ListBuffer<TA;>;)V;
Asciz	(Z)Ljava/lang/Boolean;;
Asciz	<init>;
Asciz	Code;
Asciz	InnerClasses;
Asciz	LineNumberTable;
Asciz	ListBuffer.scala;
Asciz	Ljava/lang/Object;;
Asciz	LocalVariableTable;
Asciz	Lscala/collection/mutable/ListBuffer$$anonfun$equals$1;;
Asciz	Lscala/collection/mutable/ListBuffer;;
Asciz	Scala;
Asciz	Signature;
Asciz	SourceFile;
Asciz	_1;
Asciz	_2;
Asciz	apply;
Asciz	boxToBoolean;
Asciz	equals;
Asciz	java/io/Serializable;
Asciz	java/lang/Object;
Asciz	scala/Function1;
Asciz	scala/Function1$class;
Asciz	scala/MatchError;
Asciz	scala/Tuple2;
Asciz	scala/collection/mutable/ListBuffer;
Asciz	scala/collection/mutable/ListBuffer$$anonfun$equals$1;
Asciz	scala/runtime/BoxesRunTime;
Asciz	this;
Asciz	toString;
Asciz	x$1;

{
public scala.collection.mutable.ListBuffer$$anonfun$equals$1(scala.collection.mutable.ListBuffer);
  Signature: (Lscala/collection/mutable/ListBuffer;)V
  Code:
   Stack=1, Locals=2, Args_size=2
	aload_0
	invokespecial	Method java/lang/Object."<init>":()V
	aload_0
	invokestatic	Method scala/Function1$class.$init$:(Lscala/Function1;)V
	return
  Labels:
  LocalVariableTable: 
   Start  Length  Slot  Name   Signature
   0      9      0    this       Lscala/collection/mutable/ListBuffer$$anonfun$equals$1;
   0      9      1    $outer       Lscala/collection/mutable/ListBuffer;

  Signature: length = 0x2
   00 2A 

public final java.lang.Object apply(java.lang.Object);
  Signature: (Ljava/lang/Object;)Ljava/lang/Object;
  Code:
   Stack=2, Locals=2, Args_size=2
	aload_0
	aload_1
	checkcast	class scala/Tuple2
	invokevirtual	Method apply:(Lscala/Tuple2;)Z
	invokestatic	Method scala/runtime/BoxesRunTime.boxToBoolean:(Z)Ljava/lang/Boolean;
	areturn
  Labels:
  LocalVariableTable: 
   Start  Length  Slot  Name   Signature
   0      12      0    this       Lscala/collection/mutable/ListBuffer$$anonfun$equals$1;
   0      12      1    x$1       Ljava/lang/Object;


public final boolean apply(scala.Tuple2);
  Signature: (Lscala/Tuple2;)Z
  Code:
   Stack=3, Locals=3, Args_size=2
	aload_1
	astore_2
	aload_2
	ifnonnull	l1 // aload_2
	new	class scala/MatchError
	dup
	aload_2
	invokespecial	Method scala/MatchError."<init>":(Ljava/lang/Object;)V
	athrow
l1	aload_2
	invokevirtual	Method scala/Tuple2._1:()Ljava/lang/Object;
	aload_2
	invokevirtual	Method scala/Tuple2._2:()Ljava/lang/Object;
	invokestatic	Method scala/runtime/BoxesRunTime.equals:(Ljava/lang/Object;Ljava/lang/Object;)Z
	ifeq	l2 // iconst_0
	iconst_1
	goto	l3 // ireturn
l2	iconst_0
l3	ireturn
  Labels:
   	l1 = 15 // aload_2
   	l2 = 33 // iconst_0
   	l3 = 34 // ireturn
  Signature: length = 0x2
   00 28 

public java.lang.String toString();
  Signature: ()Ljava/lang/String;
  Code:
   Stack=1, Locals=1, Args_size=1
	aload_0
	invokestatic	Method scala/Function1$class.toString:(Lscala/Function1;)Ljava/lang/String;
	areturn
  Labels:

}

