Compiled from "ListBuffer.scala"
public final class scala.collection.mutable.ListBuffer extends java.lang.Object implements scala.collection.mutable.Buffer,scala.collection.generic.GenericTraversableTemplate,scala.collection.mutable.BufferLike,scala.collection.mutable.Builder,scala.collection.generic.SeqForwarder,scala.ScalaObject,java.io.Serializable
  SourceFile: "ListBuffer.scala"
  Signature: length = 0x2
   04 5D 
  ScalaSig: length = 0x724
   05 00 FFFFFF81 7D 06 04 01 02 02 09 02 0A 4C 69 73 74
   42 75 66 66 65 72 0A 02 03 04 01 07 6D 75 74 61
   62 6C 65 0A 02 05 06 01 0A 63 6F 6C 6C 65 63 74
   69 6F 6E 0A 01 07 01 05 73 63 61 6C 61 03 00 15
   02 0A 19 13 08 00 0B 13 23 2A 2E 37 3A 10 02 0C
   11 0D 01 0D 0A 02 0E 0F 01 04 6C 61 6E 67 0A 01
   10 01 04 6A 61 76 61 09 02 12 0D 02 06 4F 62 6A
   65 63 74 10 03 14 15 17 0D 01 02 09 02 16 02 02
   06 42 75 66 66 65 72 10 02 18 19 0C 00 04 08 1A
   00 FFFFFF84 FFFFFF80 FFFFFF80 FFFFFFC2 00 1B 02 01 41 11 02 1C 20 10 02
   1D 1E 0D 01 06 09 02 1F 06 02 07 4E 6F 74 68 69
   6E 67 10 02 1D 21 09 02 22 06 02 03 41 6E 79 10
   04 24 27 17 29 0D 01 25 0A 02 26 04 01 07 67 65
   6E 65 72 69 63 09 02 28 25 02 1A 47 65 6E 65 72
   69 63 54 72 61 76 65 72 73 61 62 6C 65 54 65 6D
   70 6C 61 74 65 10 02 14 00 10 04 14 2B 17 2D 09
   02 2C 02 02 0A 42 75 66 66 65 72 4C 69 6B 65 10
   03 14 00 17 10 04 14 2F 17 31 09 02 30 02 02 07
   42 75 69 6C 64 65 72 10 03 32 35 17 0D 01 33 0A
   02 34 04 01 09 69 6D 6D 75 74 61 62 6C 65 09 02
   36 33 02 04 4C 69 73 74 10 03 24 38 17 09 02 39
   25 02 0C 53 65 71 46 6F 72 77 61 72 64 65 72 10
   02 1D 3B 09 02 3C 06 02 0B 53 63 61 6C 61 4F 62
   6A 65 63 74 08 05 3E 00 FFFFFF84 00 3F 01 06 3C 69 6E
   69 74 3E 14 01 2D 08 05 41 00 FFFFFF84 20 42 01 09 63
   6F 6D 70 61 6E 69 6F 6E 15 01 43 10 03 24 44 29
   09 02 45 25 02 10 47 65 6E 65 72 69 63 43 6F 6D
   70 61 6E 69 6F 6E 08 07 47 00 FFFFFFC0 FFFFFF80 FFFFFF84 04 48 01
   05 73 74 61 72 74 15 01 31 08 07 4A 00 FFFFFFC0 FFFFFF80 FFFFFF84
   04 4B 01 09 73 74 61 72 74 5F 24 65 71 14 02 4C
   4F 10 02 1D 4D 09 02 4E 06 02 04 55 6E 69 74 08
   07 50 49 FFFFFF81 FFFFFF80 FFFFFFC0 00 31 01 03 78 24 31 08 06 52
   00 FFFFFFA0 FFFFFFA0 04 31 01 06 73 74 61 72 74 20 08 07 54
   00 FFFFFFC0 FFFFFF80 FFFFFF84 04 55 01 05 6C 61 73 74 30 15 01 56
   10 03 32 57 17 09 02 58 33 02 0C 24 63 6F 6C 6F
   6E 24 63 6F 6C 6F 6E 08 07 5A 00 FFFFFFC0 FFFFFF80 FFFFFF84 04 5B
   01 09 6C 61 73 74 30 5F 24 65 71 14 02 4C 5C 08
   07 50 59 FFFFFF81 FFFFFF80 FFFFFFC0 00 56 08 06 5E 00 FFFFFFA0 FFFFFFA0 04 56
   01 06 6C 61 73 74 30 20 08 07 60 00 FFFFFFC0 FFFFFF80 FFFFFF84 04
   61 01 08 65 78 70 6F 72 74 65 64 15 01 62 10 02
   1D 63 09 02 64 06 02 07 42 6F 6F 6C 65 61 6E 08
   07 66 00 FFFFFFC0 FFFFFF80 FFFFFF84 04 67 01 0C 65 78 70 6F 72 74
   65 64 5F 24 65 71 14 02 4C 68 08 07 50 65 FFFFFF81 FFFFFF80
   FFFFFFC0 00 62 08 06 6A 00 FFFFFFA0 FFFFFFA0 04 62 01 09 65 78 70
   6F 72 74 65 64 20 08 07 6C 00 FFFFFFC0 FFFFFF80 FFFFFF84 04 6D 01
   03 6C 65 6E 15 01 6E 10 02 1D 6F 09 02 70 06 02
   03 49 6E 74 08 07 72 00 FFFFFFC0 FFFFFF80 FFFFFF84 04 73 01 07 6C
   65 6E 5F 24 65 71 14 02 4C 74 08 07 50 71 FFFFFF81 FFFFFF80
   FFFFFFC0 00 6E 08 06 76 00 FFFFFFA0 FFFFFFA0 04 6E 01 04 6C 65 6E
   20 08 05 78 00 FFFFFF84 08 79 01 0A 75 6E 64 65 72 6C
   79 69 6E 67 15 01 7A 10 03 32 7B 17 09 02 7C 33
   02 03 53 65 71 08 05 7E 00 FFFFFF84 20 6D 01 06 6C 65
   6E 67 74 68 08 07 FFFFFF81 00 00 FFFFFF84 20 FFFFFF81 01 01 05 61
   70 70 6C 79 14 03 17 FFFFFF81 02 08 06 FFFFFF81 03 7F FFFFFFC0 00
   6E 01 01 6E 08 07 FFFFFF81 05 00 FFFFFF84 00 FFFFFF81 06 01 06 75
   70 64 61 74 65 14 05 4C FFFFFF81 07 FFFFFF81 08 08 07 FFFFFF81 03
   FFFFFF81 04 FFFFFFC0 00 6E 08 07 FFFFFF81 09 FFFFFF81 04 FFFFFFC0 00 17 01 01
   78 08 07 FFFFFF81 0B 00 FFFFFF84 00 FFFFFF81 0C 01 08 24 70 6C 75
   73 24 65 71 14 04 FFFFFF81 0D FFFFFF81 0E 0D 01 00 08 07 FFFFFF81
   09 FFFFFF81 0A FFFFFFC0 00 17 08 07 FFFFFF81 10 00 FFFFFF84 00 FFFFFF81 11 01
   05 63 6C 65 61 72 14 01 4C 08 07 FFFFFF81 13 00 FFFFFF84 00
   FFFFFF81 14 01 0E 24 70 6C 75 73 24 65 71 24 63 6F 6C
   6F 6E 14 04 FFFFFF81 0D FFFFFF81 15 08 07 FFFFFF81 09 FFFFFF81 12 FFFFFFC0 00
   17 08 07 FFFFFF81 17 00 FFFFFF84 00 FFFFFF81 18 01 09 69 6E 73 65
   72 74 41 6C 6C 14 05 4C FFFFFF81 19 FFFFFF81 1A 08 07 FFFFFF81 03
   FFFFFF81 16 FFFFFFC0 00 6E 08 08 FFFFFF81 1B FFFFFF81 16 FFFFFFC0 00 FFFFFF81 1C 01
   03 73 65 71 10 05 FFFFFF81 1D FFFFFF81 1E 17 0D 01 04 09 03
   FFFFFF81 1F 04 02 0B 54 72 61 76 65 72 73 61 62 6C 65
   08 07 FFFFFF81 21 00 FFFFFF84 20 FFFFFF81 22 01 06 72 65 6D 6F 76
   65 14 05 4C FFFFFF81 23 FFFFFF81 24 08 07 FFFFFF81 03 FFFFFF81 20 FFFFFFC0 00
   6E 08 07 FFFFFF81 25 FFFFFF81 20 FFFFFFC0 00 6E 01 05 63 6F 75 6E
   74 08 07 FFFFFF81 27 00 FFFFFF84 00 FFFFFF81 28 01 06 72 65 73 75
   6C 74 14 01 31 08 06 FFFFFF81 2A 00 FFFFFF84 20 48 01 06 74
   6F 4C 69 73 74 08 07 FFFFFF81 2C 00 FFFFFF84 00 FFFFFF81 2D 01 0D
   70 72 65 70 65 6E 64 54 6F 4C 69 73 74 14 03 31
   FFFFFF81 2E 08 07 FFFFFF81 2F FFFFFF81 2B FFFFFFC0 00 31 01 02 78 73 08
   07 FFFFFF81 21 00 FFFFFF84 00 FFFFFF81 31 14 03 17 FFFFFF81 32 08 07 FFFFFF81
   03 FFFFFF81 30 FFFFFFC0 00 6E 08 07 FFFFFF81 34 00 FFFFFF84 20 FFFFFF81 35 01
   09 24 6D 69 6E 75 73 24 65 71 14 04 FFFFFF81 0D FFFFFF81 36
   08 07 FFFFFF81 37 FFFFFF81 33 FFFFFFC0 00 17 01 04 65 6C 65 6D 08
   07 FFFFFF81 39 00 FFFFFF84 20 FFFFFF81 3A 01 08 69 74 65 72 61 74
   6F 72 15 02 FFFFFF81 3B 12 05 FFFFFF81 3C 0B FFFFFF81 3E 06 0B FFFFFF81
   3D FFFFFF81 38 FFFFFF84 FFFFFF80 FFFFFF80 FFFFFF80 00 FFFFFF81 3B 02 0C 3C 72 65 66
   69 6E 65 6D 65 6E 74 3E 10 05 FFFFFF81 1D FFFFFF81 3F 17 09
   03 FFFFFF81 40 04 02 08 49 74 65 72 61 74 6F 72 08 06
   FFFFFF81 42 00 FFFFFF84 20 48 01 08 72 65 61 64 4F 6E 6C 79
   08 07 FFFFFF81 44 00 FFFFFF84 04 FFFFFF81 11 01 04 63 6F 70 79 08
   07 FFFFFF81 46 00 FFFFFF84 20 FFFFFF81 47 01 06 65 71 75 61 6C 73
   14 03 62 FFFFFF81 48 08 07 FFFFFF81 49 FFFFFF81 45 FFFFFFC0 00 20 01 04
   74 68 61 74 08 06 FFFFFF81 4B 00 FFFFFF84 20 3F 01 05 63 6C
   6F 6E 65 08 07 FFFFFF81 4D 00 FFFFFF84 20 FFFFFF81 4E 01 0C 73 74
   72 69 6E 67 50 72 65 66 69 78 15 02 FFFFFF81 4F 10 04
   FFFFFF81 50 FFFFFF81 53 0E 03 1D FFFFFF81 51 09 03 FFFFFF81 52 06 01 06
   50 72 65 64 65 66 09 04 FFFFFF81 54 FFFFFF81 55 02 06 53 74
   72 69 6E 67 0A 03 FFFFFF81 52 06 28 05 00 FFFFFF81 57 FFFFFF81 5A
   10 03 1D FFFFFF81 58 09 03 FFFFFF81 59 06 02 10 53 65 72 69
   61 6C 56 65 72 73 69 6F 6E 55 49 44 1E 08 2F 72
   FFFFFFF4 FFFFFF8E FFFFFFD0 FFFFFFC9 6C FFFFFFC5 28 03 00 FFFFFF81 5C 10 03 1D FFFFFF81 5D
   09 03 FFFFFF81 5E 06 02 0C 73 65 72 69 61 6C 69 7A 61
   62 6C 65 07 07 FFFFFF81 60 02 FFFFFF88 02 FFFFFF81 61 01 0A 4C 69
   73 74 42 75 66 66 65 72 10 03 14 FFFFFF81 62 06 09 01
   02 FFFFFF84 FFFFFF80 FFFFFF80 FFFFFF88 02 FFFFFF81 63 13 05 FFFFFF81 62 FFFFFF81 64 3A 10
   04 24 FFFFFF81 65 29 09 03 FFFFFF81 66 25 02 0A 53 65 71 46
   61 63 74 6F 72 79 08 07 3E FFFFFF81 62 FFFFFF84 00 FFFFFF81 68 14
   02 FFFFFF81 61 08 08 FFFFFF81 6A FFFFFF81 62 FFFFFF84 01 FFFFFF81 6B 01 0C 63
   61 6E 42 75 69 6C 64 46 72 6F 6D 15 04 FFFFFF81 6C FFFFFF81
   74 10 09 24 FFFFFF81 6D FFFFFF81 6F FFFFFF81 73 FFFFFF81 75 09 03 FFFFFF81 6E
   25 02 0C 43 61 6E 42 75 69 6C 64 46 72 6F 6D 10
   04 FFFFFF81 70 FFFFFF81 71 0D 02 FFFFFF81 62 09 03 FFFFFF81 72 44 02 04
   43 6F 6C 6C 10 03 18 FFFFFF81 74 04 09 1A FFFFFF81 69 FFFFFF84 FFFFFF80
   FFFFFF80 FFFFFFC2 00 1B 10 04 14 00 FFFFFF81 73 08 08 FFFFFF81 77 FFFFFF81 62
   FFFFFF84 00 FFFFFF81 78 01 0A 6E 65 77 42 75 69 6C 64 65 72
   15 04 FFFFFF81 79 FFFFFF81 7B 10 06 14 2F FFFFFF81 7A FFFFFF81 7C 10 03
   18 FFFFFF81 7B 04 09 1A FFFFFF81 76 FFFFFF84 FFFFFF80 FFFFFF80 FFFFFFC2 00 1B 10 04
   14 00 FFFFFF81 7A 
  InnerClass: 
   public final #1120= #364 of #11; //$anon$1=class scala/collection/mutable/ListBuffer$$anon$1 of class scala/collection/mutable/ListBuffer
   public #1123= #1122 of #292; //WithFilter=class scala/collection/TraversableLike$WithFilter of class scala/collection/TraversableLike
  minor version: 0
  major version: 49
  Constant pool:
const #1 = Asciz	SourceFile;
const #2 = Asciz	ListBuffer.scala;
const #3 = Asciz	<clinit>;
const #4 = Asciz	()V;
const #5 = Asciz	Code;
const #6 = Asciz	serialVersionUID;
const #7 = Asciz	J;
const #8 = long	3419063961353022661l;
const #10 = Asciz	scala/collection/mutable/ListBuffer;
const #11 = class	#10;	//  scala/collection/mutable/ListBuffer
const #12 = NameAndType	#6:#7;//  serialVersionUID:J
const #13 = Field	#11.#12;	//  scala/collection/mutable/ListBuffer.serialVersionUID:J
const #14 = Asciz	len;
const #15 = Asciz	I;
const #16 = Asciz	exported;
const #17 = Asciz	Z;
const #18 = Asciz	scala$collection$mutable$ListBuffer$$last0;
const #19 = Asciz	Lscala/collection/immutable/$colon$colon;;
const #20 = Asciz	scala$collection$mutable$ListBuffer$$start;
const #21 = Asciz	Lscala/collection/immutable/List;;
const #22 = Asciz	<init>;
const #23 = Asciz	LineNumberTable;
const #24 = Asciz	java/lang/Object;
const #25 = class	#24;	//  java/lang/Object
const #26 = NameAndType	#22:#4;//  "<init>":()V
const #27 = Method	#25.#26;	//  java/lang/Object."<init>":()V
const #28 = Asciz	scala/collection/TraversableLike$class;
const #29 = class	#28;	//  scala/collection/TraversableLike$class
const #30 = Asciz	$init$;
const #31 = Asciz	(Lscala/collection/TraversableLike;)V;
const #32 = NameAndType	#30:#31;//  $init$:(Lscala/collection/TraversableLike;)V
const #33 = Method	#29.#32;	//  scala/collection/TraversableLike$class.$init$:(Lscala/collection/TraversableLike;)V
const #34 = Asciz	scala/collection/generic/GenericTraversableTemplate$class;
const #35 = class	#34;	//  scala/collection/generic/GenericTraversableTemplate$class
const #36 = Asciz	(Lscala/collection/generic/GenericTraversableTemplate;)V;
const #37 = NameAndType	#30:#36;//  $init$:(Lscala/collection/generic/GenericTraversableTemplate;)V
const #38 = Method	#35.#37;	//  scala/collection/generic/GenericTraversableTemplate$class.$init$:(Lscala/collection/generic/GenericTraversableTemplate;)V
const #39 = Asciz	scala/collection/Traversable$class;
const #40 = class	#39;	//  scala/collection/Traversable$class
const #41 = Asciz	(Lscala/collection/Traversable;)V;
const #42 = NameAndType	#30:#41;//  $init$:(Lscala/collection/Traversable;)V
const #43 = Method	#40.#42;	//  scala/collection/Traversable$class.$init$:(Lscala/collection/Traversable;)V
const #44 = Asciz	scala/collection/mutable/Traversable$class;
const #45 = class	#44;	//  scala/collection/mutable/Traversable$class
const #46 = Asciz	(Lscala/collection/mutable/Traversable;)V;
const #47 = NameAndType	#30:#46;//  $init$:(Lscala/collection/mutable/Traversable;)V
const #48 = Method	#45.#47;	//  scala/collection/mutable/Traversable$class.$init$:(Lscala/collection/mutable/Traversable;)V
const #49 = Asciz	scala/collection/IterableLike$class;
const #50 = class	#49;	//  scala/collection/IterableLike$class
const #51 = Asciz	(Lscala/collection/IterableLike;)V;
const #52 = NameAndType	#30:#51;//  $init$:(Lscala/collection/IterableLike;)V
const #53 = Method	#50.#52;	//  scala/collection/IterableLike$class.$init$:(Lscala/collection/IterableLike;)V
const #54 = Asciz	scala/collection/Iterable$class;
const #55 = class	#54;	//  scala/collection/Iterable$class
const #56 = Asciz	(Lscala/collection/Iterable;)V;
const #57 = NameAndType	#30:#56;//  $init$:(Lscala/collection/Iterable;)V
const #58 = Method	#55.#57;	//  scala/collection/Iterable$class.$init$:(Lscala/collection/Iterable;)V
const #59 = Asciz	scala/collection/mutable/Iterable$class;
const #60 = class	#59;	//  scala/collection/mutable/Iterable$class
const #61 = Asciz	(Lscala/collection/mutable/Iterable;)V;
const #62 = NameAndType	#30:#61;//  $init$:(Lscala/collection/mutable/Iterable;)V
const #63 = Method	#60.#62;	//  scala/collection/mutable/Iterable$class.$init$:(Lscala/collection/mutable/Iterable;)V
const #64 = Asciz	scala/Function1$class;
const #65 = class	#64;	//  scala/Function1$class
const #66 = Asciz	(Lscala/Function1;)V;
const #67 = NameAndType	#30:#66;//  $init$:(Lscala/Function1;)V
const #68 = Method	#65.#67;	//  scala/Function1$class.$init$:(Lscala/Function1;)V
const #69 = Asciz	scala/PartialFunction$class;
const #70 = class	#69;	//  scala/PartialFunction$class
const #71 = Asciz	(Lscala/PartialFunction;)V;
const #72 = NameAndType	#30:#71;//  $init$:(Lscala/PartialFunction;)V
const #73 = Method	#70.#72;	//  scala/PartialFunction$class.$init$:(Lscala/PartialFunction;)V
const #74 = Asciz	scala/collection/SeqLike$class;
const #75 = class	#74;	//  scala/collection/SeqLike$class
const #76 = Asciz	(Lscala/collection/SeqLike;)V;
const #77 = NameAndType	#30:#76;//  $init$:(Lscala/collection/SeqLike;)V
const #78 = Method	#75.#77;	//  scala/collection/SeqLike$class.$init$:(Lscala/collection/SeqLike;)V
const #79 = Asciz	scala/collection/Seq$class;
const #80 = class	#79;	//  scala/collection/Seq$class
const #81 = Asciz	(Lscala/collection/Seq;)V;
const #82 = NameAndType	#30:#81;//  $init$:(Lscala/collection/Seq;)V
const #83 = Method	#80.#82;	//  scala/collection/Seq$class.$init$:(Lscala/collection/Seq;)V
const #84 = Asciz	scala/collection/mutable/Seq$class;
const #85 = class	#84;	//  scala/collection/mutable/Seq$class
const #86 = Asciz	(Lscala/collection/mutable/Seq;)V;
const #87 = NameAndType	#30:#86;//  $init$:(Lscala/collection/mutable/Seq;)V
const #88 = Method	#85.#87;	//  scala/collection/mutable/Seq$class.$init$:(Lscala/collection/mutable/Seq;)V
const #89 = Asciz	scala/collection/generic/Growable$class;
const #90 = class	#89;	//  scala/collection/generic/Growable$class
const #91 = Asciz	(Lscala/collection/generic/Growable;)V;
const #92 = NameAndType	#30:#91;//  $init$:(Lscala/collection/generic/Growable;)V
const #93 = Method	#90.#92;	//  scala/collection/generic/Growable$class.$init$:(Lscala/collection/generic/Growable;)V
const #94 = Asciz	scala/collection/generic/Shrinkable$class;
const #95 = class	#94;	//  scala/collection/generic/Shrinkable$class
const #96 = Asciz	(Lscala/collection/generic/Shrinkable;)V;
const #97 = NameAndType	#30:#96;//  $init$:(Lscala/collection/generic/Shrinkable;)V
const #98 = Method	#95.#97;	//  scala/collection/generic/Shrinkable$class.$init$:(Lscala/collection/generic/Shrinkable;)V
const #99 = Asciz	scala/collection/generic/Addable$class;
const #100 = class	#99;	//  scala/collection/generic/Addable$class
const #101 = Asciz	(Lscala/collection/generic/Addable;)V;
const #102 = NameAndType	#30:#101;//  $init$:(Lscala/collection/generic/Addable;)V
const #103 = Method	#100.#102;	//  scala/collection/generic/Addable$class.$init$:(Lscala/collection/generic/Addable;)V
const #104 = Asciz	scala/collection/generic/Subtractable$class;
const #105 = class	#104;	//  scala/collection/generic/Subtractable$class
const #106 = Asciz	(Lscala/collection/generic/Subtractable;)V;
const #107 = NameAndType	#30:#106;//  $init$:(Lscala/collection/generic/Subtractable;)V
const #108 = Method	#105.#107;	//  scala/collection/generic/Subtractable$class.$init$:(Lscala/collection/generic/Subtractable;)V
const #109 = Asciz	scala/collection/mutable/Cloneable$class;
const #110 = class	#109;	//  scala/collection/mutable/Cloneable$class
const #111 = Asciz	(Lscala/collection/mutable/Cloneable;)V;
const #112 = NameAndType	#30:#111;//  $init$:(Lscala/collection/mutable/Cloneable;)V
const #113 = Method	#110.#112;	//  scala/collection/mutable/Cloneable$class.$init$:(Lscala/collection/mutable/Cloneable;)V
const #114 = Asciz	scala/collection/mutable/BufferLike$class;
const #115 = class	#114;	//  scala/collection/mutable/BufferLike$class
const #116 = Asciz	(Lscala/collection/mutable/BufferLike;)V;
const #117 = NameAndType	#30:#116;//  $init$:(Lscala/collection/mutable/BufferLike;)V
const #118 = Method	#115.#117;	//  scala/collection/mutable/BufferLike$class.$init$:(Lscala/collection/mutable/BufferLike;)V
const #119 = Asciz	scala/collection/mutable/Buffer$class;
const #120 = class	#119;	//  scala/collection/mutable/Buffer$class
const #121 = Asciz	(Lscala/collection/mutable/Buffer;)V;
const #122 = NameAndType	#30:#121;//  $init$:(Lscala/collection/mutable/Buffer;)V
const #123 = Method	#120.#122;	//  scala/collection/mutable/Buffer$class.$init$:(Lscala/collection/mutable/Buffer;)V
const #124 = Asciz	scala/collection/mutable/Builder$class;
const #125 = class	#124;	//  scala/collection/mutable/Builder$class
const #126 = Asciz	(Lscala/collection/mutable/Builder;)V;
const #127 = NameAndType	#30:#126;//  $init$:(Lscala/collection/mutable/Builder;)V
const #128 = Method	#125.#127;	//  scala/collection/mutable/Builder$class.$init$:(Lscala/collection/mutable/Builder;)V
const #129 = Asciz	scala/collection/generic/TraversableForwarder$class;
const #130 = class	#129;	//  scala/collection/generic/TraversableForwarder$class
const #131 = Asciz	(Lscala/collection/generic/TraversableForwarder;)V;
const #132 = NameAndType	#30:#131;//  $init$:(Lscala/collection/generic/TraversableForwarder;)V
const #133 = Method	#130.#132;	//  scala/collection/generic/TraversableForwarder$class.$init$:(Lscala/collection/generic/TraversableForwarder;)V
const #134 = Asciz	scala/collection/generic/IterableForwarder$class;
const #135 = class	#134;	//  scala/collection/generic/IterableForwarder$class
const #136 = Asciz	(Lscala/collection/generic/IterableForwarder;)V;
const #137 = NameAndType	#30:#136;//  $init$:(Lscala/collection/generic/IterableForwarder;)V
const #138 = Method	#135.#137;	//  scala/collection/generic/IterableForwarder$class.$init$:(Lscala/collection/generic/IterableForwarder;)V
const #139 = Asciz	scala/collection/generic/SeqForwarder$class;
const #140 = class	#139;	//  scala/collection/generic/SeqForwarder$class
const #141 = Asciz	(Lscala/collection/generic/SeqForwarder;)V;
const #142 = NameAndType	#30:#141;//  $init$:(Lscala/collection/generic/SeqForwarder;)V
const #143 = Method	#140.#142;	//  scala/collection/generic/SeqForwarder$class.$init$:(Lscala/collection/generic/SeqForwarder;)V
const #144 = Asciz	scala/collection/immutable/Nil$;
const #145 = class	#144;	//  scala/collection/immutable/Nil$
const #146 = Asciz	MODULE$;
const #147 = Asciz	Lscala/collection/immutable/Nil$;;
const #148 = NameAndType	#146:#147;//  MODULE$:Lscala/collection/immutable/Nil$;
const #149 = Field	#145.#148;	//  scala/collection/immutable/Nil$.MODULE$:Lscala/collection/immutable/Nil$;
const #150 = NameAndType	#20:#21;//  scala$collection$mutable$ListBuffer$$start:Lscala/collection/immutable/List;
const #151 = Field	#11.#150;	//  scala/collection/mutable/ListBuffer.scala$collection$mutable$ListBuffer$$start:Lscala/collection/immutable/List;
const #152 = NameAndType	#16:#17;//  exported:Z
const #153 = Field	#11.#152;	//  scala/collection/mutable/ListBuffer.exported:Z
const #154 = NameAndType	#14:#15;//  len:I
const #155 = Field	#11.#154;	//  scala/collection/mutable/ListBuffer.len:I
const #156 = Asciz	Signature;
const #157 = Asciz	underlying;
const #158 = Asciz	()Lscala/collection/Seq;;
const #159 = Asciz	()Lscala/collection/immutable/Seq;;
const #160 = NameAndType	#157:#159;//  underlying:()Lscala/collection/immutable/Seq;
const #161 = Method	#11.#160;	//  scala/collection/mutable/ListBuffer.underlying:()Lscala/collection/immutable/Seq;
const #162 = Asciz	()Lscala/collection/Iterable;;
const #163 = Asciz	()Lscala/collection/Traversable;;
const #164 = Asciz	apply;
const #165 = Asciz	(Ljava/lang/Object;)Ljava/lang/Object;;
const #166 = Asciz	scala/runtime/BoxesRunTime;
const #167 = class	#166;	//  scala/runtime/BoxesRunTime
const #168 = Asciz	unboxToInt;
const #169 = Asciz	(Ljava/lang/Object;)I;
const #170 = NameAndType	#168:#169;//  unboxToInt:(Ljava/lang/Object;)I
const #171 = Method	#167.#170;	//  scala/runtime/BoxesRunTime.unboxToInt:(Ljava/lang/Object;)I
const #172 = Asciz	(I)Ljava/lang/Object;;
const #173 = NameAndType	#164:#172;//  apply:(I)Ljava/lang/Object;
const #174 = Method	#11.#173;	//  scala/collection/mutable/ListBuffer.apply:(I)Ljava/lang/Object;
const #175 = Asciz	this;
const #176 = Asciz	Lscala/collection/mutable/ListBuffer;;
const #177 = Asciz	v1;
const #178 = Asciz	Ljava/lang/Object;;
const #179 = Asciz	LocalVariableTable;
const #180 = Asciz	$plus$eq;
const #181 = Asciz	(Ljava/lang/Object;)Lscala/collection/mutable/Builder;;
const #182 = Asciz	(Ljava/lang/Object;)Lscala/collection/mutable/ListBuffer;;
const #183 = NameAndType	#180:#182;//  $plus$eq:(Ljava/lang/Object;)Lscala/collection/mutable/ListBuffer;
const #184 = Method	#11.#183;	//  scala/collection/mutable/ListBuffer.$plus$eq:(Ljava/lang/Object;)Lscala/collection/mutable/ListBuffer;
const #185 = Asciz	elem;
const #186 = Asciz	(Ljava/lang/Object;)Lscala/collection/mutable/BufferLike;;
const #187 = Asciz	(Ljava/lang/Object;)Lscala/collection/generic/Growable;;
const #188 = Asciz	$plus$eq$colon;
const #189 = NameAndType	#188:#182;//  $plus$eq$colon:(Ljava/lang/Object;)Lscala/collection/mutable/ListBuffer;
const #190 = Method	#11.#189;	//  scala/collection/mutable/ListBuffer.$plus$eq$colon:(Ljava/lang/Object;)Lscala/collection/mutable/ListBuffer;
const #191 = Asciz	result;
const #192 = Asciz	()Ljava/lang/Object;;
const #193 = Asciz	()Lscala/collection/immutable/List;;
const #194 = NameAndType	#191:#193;//  result:()Lscala/collection/immutable/List;
const #195 = Method	#11.#194;	//  scala/collection/mutable/ListBuffer.result:()Lscala/collection/immutable/List;
const #196 = Asciz	$minus$eq;
const #197 = NameAndType	#196:#182;//  $minus$eq:(Ljava/lang/Object;)Lscala/collection/mutable/ListBuffer;
const #198 = Method	#11.#197;	//  scala/collection/mutable/ListBuffer.$minus$eq:(Ljava/lang/Object;)Lscala/collection/mutable/ListBuffer;
const #199 = Asciz	x;
const #200 = Asciz	(Ljava/lang/Object;)Lscala/collection/generic/Shrinkable;;
const #201 = Asciz	iterator;
const #202 = Asciz	()Lscala/collection/Iterator;;
const #203 = NameAndType	#201:#192;//  iterator:()Ljava/lang/Object;
const #204 = Method	#11.#203;	//  scala/collection/mutable/ListBuffer.iterator:()Ljava/lang/Object;
const #205 = Asciz	scala/collection/Iterator;
const #206 = class	#205;	//  scala/collection/Iterator
const #207 = Asciz	readOnly;
const #208 = NameAndType	#207:#193;//  readOnly:()Lscala/collection/immutable/List;
const #209 = Method	#11.#208;	//  scala/collection/mutable/ListBuffer.readOnly:()Lscala/collection/immutable/List;
const #210 = Asciz	clone;
const #211 = Asciz	()Lscala/collection/mutable/ListBuffer;;
const #212 = NameAndType	#210:#211;//  clone:()Lscala/collection/mutable/ListBuffer;
const #213 = Method	#11.#212;	//  scala/collection/mutable/ListBuffer.clone:()Lscala/collection/mutable/ListBuffer;
const #214 = Asciz	isDefinedAt;
const #215 = Asciz	(Ljava/lang/Object;)Z;
const #216 = Asciz	scala/collection/generic/SeqForwarder;
const #217 = class	#216;	//  scala/collection/generic/SeqForwarder
const #218 = Asciz	(I)Z;
const #219 = NameAndType	#214:#218;//  isDefinedAt:(I)Z
const #220 = InterfaceMethod	#217.#219;	//  scala/collection/generic/SeqForwarder.isDefinedAt:(I)Z
const #221 = Asciz	$plus;
const #222 = Asciz	(Ljava/lang/Object;)Lscala/collection/generic/Addable;;
const #223 = Asciz	scala/collection/mutable/BufferLike;
const #224 = class	#223;	//  scala/collection/mutable/BufferLike
const #225 = NameAndType	#221:#186;//  $plus:(Ljava/lang/Object;)Lscala/collection/mutable/BufferLike;
const #226 = InterfaceMethod	#224.#225;	//  scala/collection/mutable/BufferLike.$plus:(Ljava/lang/Object;)Lscala/collection/mutable/BufferLike;
const #227 = Asciz	(Ljava/lang/Object;Ljava/lang/Object;Lscala/collection/Seq;)Lscala/collection/generic/Addable;;
const #228 = Asciz	(Ljava/lang/Object;Ljava/lang/Object;Lscala/collection/Seq;)Lscala/collection/mutable/BufferLike;;
const #229 = NameAndType	#221:#228;//  $plus:(Ljava/lang/Object;Ljava/lang/Object;Lscala/collection/Seq;)Lscala/collection/mutable/BufferLike;
const #230 = InterfaceMethod	#224.#229;	//  scala/collection/mutable/BufferLike.$plus:(Ljava/lang/Object;Ljava/lang/Object;Lscala/collection/Seq;)Lscala/collection/mutable/BufferLike;
const #231 = Asciz	elem1;
const #232 = Asciz	elem2;
const #233 = Asciz	elems;
const #234 = Asciz	Lscala/collection/Seq;;
const #235 = Asciz	$plus$plus;
const #236 = Asciz	(Lscala/collection/Traversable;)Lscala/collection/generic/Addable;;
const #237 = Asciz	(Lscala/collection/Traversable;)Lscala/collection/mutable/BufferLike;;
const #238 = NameAndType	#235:#237;//  $plus$plus:(Lscala/collection/Traversable;)Lscala/collection/mutable/BufferLike;
const #239 = InterfaceMethod	#224.#238;	//  scala/collection/mutable/BufferLike.$plus$plus:(Lscala/collection/Traversable;)Lscala/collection/mutable/BufferLike;
const #240 = Asciz	Lscala/collection/Traversable;;
const #241 = Asciz	(Lscala/collection/Iterator;)Lscala/collection/generic/Addable;;
const #242 = Asciz	(Lscala/collection/Iterator;)Lscala/collection/mutable/BufferLike;;
const #243 = NameAndType	#235:#242;//  $plus$plus:(Lscala/collection/Iterator;)Lscala/collection/mutable/BufferLike;
const #244 = InterfaceMethod	#224.#243;	//  scala/collection/mutable/BufferLike.$plus$plus:(Lscala/collection/Iterator;)Lscala/collection/mutable/BufferLike;
const #245 = Asciz	iter;
const #246 = Asciz	Lscala/collection/Iterator;;
const #247 = Asciz	$minus;
const #248 = Asciz	(Ljava/lang/Object;)Lscala/collection/generic/Subtractable;;
const #249 = NameAndType	#247:#186;//  $minus:(Ljava/lang/Object;)Lscala/collection/mutable/BufferLike;
const #250 = InterfaceMethod	#224.#249;	//  scala/collection/mutable/BufferLike.$minus:(Ljava/lang/Object;)Lscala/collection/mutable/BufferLike;
const #251 = Asciz	(Ljava/lang/Object;Ljava/lang/Object;Lscala/collection/Seq;)Lscala/collection/generic/Subtractable;;
const #252 = NameAndType	#247:#228;//  $minus:(Ljava/lang/Object;Ljava/lang/Object;Lscala/collection/Seq;)Lscala/collection/mutable/BufferLike;
const #253 = InterfaceMethod	#224.#252;	//  scala/collection/mutable/BufferLike.$minus:(Ljava/lang/Object;Ljava/lang/Object;Lscala/collection/Seq;)Lscala/collection/mutable/BufferLike;
const #254 = Asciz	$minus$minus;
const #255 = Asciz	(Lscala/collection/Traversable;)Lscala/collection/generic/Subtractable;;
const #256 = NameAndType	#254:#237;//  $minus$minus:(Lscala/collection/Traversable;)Lscala/collection/mutable/BufferLike;
const #257 = InterfaceMethod	#224.#256;	//  scala/collection/mutable/BufferLike.$minus$minus:(Lscala/collection/Traversable;)Lscala/collection/mutable/BufferLike;
const #258 = Asciz	(Lscala/collection/Iterator;)Lscala/collection/generic/Subtractable;;
const #259 = NameAndType	#254:#242;//  $minus$minus:(Lscala/collection/Iterator;)Lscala/collection/mutable/BufferLike;
const #260 = InterfaceMethod	#224.#259;	//  scala/collection/mutable/BufferLike.$minus$minus:(Lscala/collection/Iterator;)Lscala/collection/mutable/BufferLike;
const #261 = Asciz	thisCollection;
const #262 = Asciz	scala/collection/SeqLike;
const #263 = class	#262;	//  scala/collection/SeqLike
const #264 = NameAndType	#261:#158;//  thisCollection:()Lscala/collection/Seq;
const #265 = InterfaceMethod	#263.#264;	//  scala/collection/SeqLike.thisCollection:()Lscala/collection/Seq;
const #266 = Asciz	toCollection;
const #267 = Asciz	(Ljava/lang/Object;)Lscala/collection/Iterable;;
const #268 = Asciz	(Ljava/lang/Object;)Lscala/collection/Seq;;
const #269 = NameAndType	#266:#268;//  toCollection:(Ljava/lang/Object;)Lscala/collection/Seq;
const #270 = InterfaceMethod	#263.#269;	//  scala/collection/SeqLike.toCollection:(Ljava/lang/Object;)Lscala/collection/Seq;
const #271 = Asciz	repr;
const #272 = Asciz	(Ljava/lang/Object;)Lscala/collection/Traversable;;
const #273 = Asciz	view;
const #274 = Asciz	(II)Lscala/collection/IterableView;;
const #275 = Asciz	(II)Lscala/collection/SeqView;;
const #276 = NameAndType	#273:#275;//  view:(II)Lscala/collection/SeqView;
const #277 = InterfaceMethod	#263.#276;	//  scala/collection/SeqLike.view:(II)Lscala/collection/SeqView;
const #278 = Asciz	from;
const #279 = Asciz	until;
const #280 = Asciz	(II)Lscala/collection/TraversableView;;
const #281 = Asciz	andThen;
const #282 = Asciz	(Lscala/Function1;)Lscala/Function1;;
const #283 = Asciz	scala/PartialFunction;
const #284 = class	#283;	//  scala/PartialFunction
const #285 = Asciz	(Lscala/Function1;)Lscala/PartialFunction;;
const #286 = NameAndType	#281:#285;//  andThen:(Lscala/Function1;)Lscala/PartialFunction;
const #287 = InterfaceMethod	#284.#286;	//  scala/PartialFunction.andThen:(Lscala/Function1;)Lscala/PartialFunction;
const #288 = Asciz	g;
const #289 = Asciz	Lscala/Function1;;
const #290 = Asciz	()Lscala/collection/generic/Subtractable;;
const #291 = Asciz	scala/collection/TraversableLike;
const #292 = class	#291;	//  scala/collection/TraversableLike
const #293 = NameAndType	#271:#192;//  repr:()Ljava/lang/Object;
const #294 = InterfaceMethod	#292.#293;	//  scala/collection/TraversableLike.repr:()Ljava/lang/Object;
const #295 = Asciz	scala/collection/generic/Subtractable;
const #296 = class	#295;	//  scala/collection/generic/Subtractable
const #297 = Asciz	()Lscala/collection/generic/Addable;;
const #298 = Asciz	scala/collection/generic/Addable;
const #299 = class	#298;	//  scala/collection/generic/Addable
const #300 = Asciz	stringPrefix;
const #301 = Asciz	()Ljava/lang/String;;
const #302 = Asciz	ListBuffer;
const #303 = String	#302;	//  ListBuffer
const #304 = Method	#11.#26;	//  scala/collection/mutable/ListBuffer."<init>":()V
const #305 = Asciz	scala/collection/generic/Growable;
const #306 = class	#305;	//  scala/collection/generic/Growable
const #307 = Asciz	$plus$plus$eq;
const #308 = Asciz	(Lscala/collection/Traversable;)Lscala/collection/generic/Growable;;
const #309 = NameAndType	#307:#308;//  $plus$plus$eq:(Lscala/collection/Traversable;)Lscala/collection/generic/Growable;
const #310 = InterfaceMethod	#306.#309;	//  scala/collection/generic/Growable.$plus$plus$eq:(Lscala/collection/Traversable;)Lscala/collection/generic/Growable;
const #311 = Asciz	()Lscala/collection/mutable/ListBuffer<TA;>;;
const #312 = Asciz	equals;
const #313 = NameAndType	#312:#215;//  equals:(Ljava/lang/Object;)Z
const #314 = InterfaceMethod	#263.#313;	//  scala/collection/SeqLike.equals:(Ljava/lang/Object;)Z
const #315 = Asciz	scala/MatchError;
const #316 = class	#315;	//  scala/MatchError
const #317 = Asciz	toString;
const #318 = NameAndType	#317:#301;//  toString:()Ljava/lang/String;
const #319 = Method	#25.#318;	//  java/lang/Object.toString:()Ljava/lang/String;
const #320 = Asciz	(Ljava/lang/String;)V;
const #321 = NameAndType	#22:#320;//  "<init>":(Ljava/lang/String;)V
const #322 = Method	#316.#321;	//  scala/MatchError."<init>":(Ljava/lang/String;)V
const #323 = Asciz	(Lscala/collection/SeqLike;Ljava/lang/Object;)Z;
const #324 = NameAndType	#312:#323;//  equals:(Lscala/collection/SeqLike;Ljava/lang/Object;)Z
const #325 = Method	#75.#324;	//  scala/collection/SeqLike$class.equals:(Lscala/collection/SeqLike;Ljava/lang/Object;)Z
const #326 = Asciz	that;
const #327 = Asciz	temp2;
const #328 = Asciz	copy;
const #329 = NameAndType	#18:#19;//  scala$collection$mutable$ListBuffer$$last0:Lscala/collection/immutable/$colon$colon;
const #330 = Field	#11.#329;	//  scala/collection/mutable/ListBuffer.scala$collection$mutable$ListBuffer$$last0:Lscala/collection/immutable/$colon$colon;
const #331 = Asciz	scala/collection/immutable/$colon$colon;
const #332 = class	#331;	//  scala/collection/immutable/$colon$colon
const #333 = Asciz	tl;
const #334 = NameAndType	#333:#21;//  tl:Lscala/collection/immutable/List;
const #335 = Field	#332.#334;	//  scala/collection/immutable/$colon$colon.tl:Lscala/collection/immutable/List;
const #336 = Asciz	scala$collection$mutable$ListBuffer$$start_$eq;
const #337 = Asciz	(Lscala/collection/immutable/List;)V;
const #338 = NameAndType	#336:#337;//  scala$collection$mutable$ListBuffer$$start_$eq:(Lscala/collection/immutable/List;)V
const #339 = Method	#11.#338;	//  scala/collection/mutable/ListBuffer.scala$collection$mutable$ListBuffer$$start_$eq:(Lscala/collection/immutable/List;)V
const #340 = Asciz	exported_$eq;
const #341 = Asciz	(Z)V;
const #342 = NameAndType	#340:#341;//  exported_$eq:(Z)V
const #343 = Method	#11.#342;	//  scala/collection/mutable/ListBuffer.exported_$eq:(Z)V
const #344 = Asciz	len_$eq;
const #345 = Asciz	(I)V;
const #346 = NameAndType	#344:#345;//  len_$eq:(I)V
const #347 = Method	#11.#346;	//  scala/collection/mutable/ListBuffer.len_$eq:(I)V
const #348 = Asciz	scala/collection/IterableLike;
const #349 = class	#348;	//  scala/collection/IterableLike
const #350 = Asciz	head;
const #351 = NameAndType	#350:#192;//  head:()Ljava/lang/Object;
const #352 = InterfaceMethod	#349.#351;	//  scala/collection/IterableLike.head:()Ljava/lang/Object;
const #353 = Asciz	tail;
const #354 = NameAndType	#353:#192;//  tail:()Ljava/lang/Object;
const #355 = InterfaceMethod	#292.#354;	//  scala/collection/TraversableLike.tail:()Ljava/lang/Object;
const #356 = Asciz	scala/collection/immutable/List;
const #357 = class	#356;	//  scala/collection/immutable/List
const #358 = Asciz	limit;
const #359 = Asciz	cursor;
const #360 = NameAndType	#20:#193;//  scala$collection$mutable$ListBuffer$$start:()Lscala/collection/immutable/List;
const #361 = Method	#11.#360;	//  scala/collection/mutable/ListBuffer.scala$collection$mutable$ListBuffer$$start:()Lscala/collection/immutable/List;
const #362 = Asciz	()Lscala/collection/immutable/List<TA;>;;
const #363 = Asciz	scala/collection/mutable/ListBuffer$$anon$1;
const #364 = class	#363;	//  scala/collection/mutable/ListBuffer$$anon$1
const #365 = Asciz	(Lscala/collection/mutable/ListBuffer;)V;
const #366 = NameAndType	#22:#365;//  "<init>":(Lscala/collection/mutable/ListBuffer;)V
const #367 = Method	#364.#366;	//  scala/collection/mutable/ListBuffer$$anon$1."<init>":(Lscala/collection/mutable/ListBuffer;)V
const #368 = Asciz	()Z;
const #369 = NameAndType	#16:#368;//  exported:()Z
const #370 = Method	#11.#369;	//  scala/collection/mutable/ListBuffer.exported:()Z
const #371 = NameAndType	#328:#4;//  copy:()V
const #372 = Method	#11.#371;	//  scala/collection/mutable/ListBuffer.copy:()V
const #373 = Asciz	isEmpty;
const #374 = NameAndType	#373:#368;//  isEmpty:()Z
const #375 = InterfaceMethod	#349.#374;	//  scala/collection/IterableLike.isEmpty:()Z
const #376 = Asciz	java/lang/Number;
const #377 = class	#376;	//  java/lang/Number
const #378 = Asciz	java/lang/Character;
const #379 = class	#378;	//  java/lang/Character
const #380 = Asciz	equals2;
const #381 = Asciz	(Ljava/lang/Object;Ljava/lang/Object;)Z;
const #382 = NameAndType	#380:#381;//  equals2:(Ljava/lang/Object;Ljava/lang/Object;)Z
const #383 = Method	#167.#382;	//  scala/runtime/BoxesRunTime.equals2:(Ljava/lang/Object;Ljava/lang/Object;)Z
const #384 = Method	#25.#313;	//  java/lang/Object.equals:(Ljava/lang/Object;)Z
const #385 = Asciz	()I;
const #386 = NameAndType	#14:#385;//  len:()I
const #387 = Method	#11.#386;	//  scala/collection/mutable/ListBuffer.len:()I
const #388 = Asciz	scala$collection$mutable$ListBuffer$$last0_$eq;
const #389 = Asciz	(Lscala/collection/immutable/$colon$colon;)V;
const #390 = NameAndType	#388:#389;//  scala$collection$mutable$ListBuffer$$last0_$eq:(Lscala/collection/immutable/$colon$colon;)V
const #391 = Method	#11.#390;	//  scala/collection/mutable/ListBuffer.scala$collection$mutable$ListBuffer$$last0_$eq:(Lscala/collection/immutable/$colon$colon;)V
const #392 = Asciz	x0;
const #393 = Asciz	x1;
const #394 = Asciz	z;
const #395 = Asciz	(TA;)Lscala/collection/mutable/ListBuffer<TA;>;;
const #396 = Asciz	remove;
const #397 = Asciz	java/lang/IndexOutOfBoundsException;
const #398 = class	#397;	//  java/lang/IndexOutOfBoundsException
const #399 = Asciz	boxToInteger;
const #400 = Asciz	(I)Ljava/lang/Integer;;
const #401 = NameAndType	#399:#400;//  boxToInteger:(I)Ljava/lang/Integer;
const #402 = Method	#167.#401;	//  scala/runtime/BoxesRunTime.boxToInteger:(I)Ljava/lang/Integer;
const #403 = Method	#398.#321;	//  java/lang/IndexOutOfBoundsException."<init>":(Ljava/lang/String;)V
const #404 = Asciz	n;
const #405 = Asciz	i;
const #406 = Asciz	old;
const #407 = Asciz	(I)TA;;
const #408 = Asciz	prependToList;
const #409 = Asciz	(Lscala/collection/immutable/List;)Lscala/collection/immutable/List;;
const #410 = Asciz	toList;
const #411 = NameAndType	#410:#193;//  toList:()Lscala/collection/immutable/List;
const #412 = Method	#11.#411;	//  scala/collection/mutable/ListBuffer.toList:()Lscala/collection/immutable/List;
const #413 = Asciz	xs;
const #414 = Asciz	(Lscala/collection/immutable/List<TA;>;)Lscala/collection/immutable/List<TA;>;;
const #415 = Asciz	(II)V;
const #416 = Asciz	scala/runtime/RichInt;
const #417 = class	#416;	//  scala/runtime/RichInt
const #418 = NameAndType	#22:#345;//  "<init>":(I)V
const #419 = Method	#417.#418;	//  scala/runtime/RichInt."<init>":(I)V
const #420 = Asciz	max;
const #421 = Asciz	(I)I;
const #422 = NameAndType	#420:#421;//  max:(I)I
const #423 = Method	#417.#422;	//  scala/runtime/RichInt.max:(I)I
const #424 = Asciz	min;
const #425 = NameAndType	#424:#421;//  min:(I)I
const #426 = Method	#417.#425;	//  scala/runtime/RichInt.min:(I)I
const #427 = Asciz	count;
const #428 = Asciz	c;
const #429 = Asciz	n1;
const #430 = Asciz	count1;
const #431 = Asciz	insertAll;
const #432 = Asciz	(ILscala/collection/Traversable;)V;
const #433 = InterfaceMethod	#292.#411;	//  scala/collection/TraversableLike.toList:()Lscala/collection/immutable/List;
const #434 = Asciz	reverse;
const #435 = NameAndType	#434:#193;//  reverse:()Lscala/collection/immutable/List;
const #436 = Method	#357.#435;	//  scala/collection/immutable/List.reverse:()Lscala/collection/immutable/List;
const #437 = Asciz	scala/collection/LinearSeqLike;
const #438 = class	#437;	//  scala/collection/LinearSeqLike
const #439 = Asciz	length;
const #440 = NameAndType	#439:#385;//  length:()I
const #441 = InterfaceMethod	#438.#440;	//  scala/collection/LinearSeqLike.length:()I
const #442 = Asciz	(Ljava/lang/Object;Lscala/collection/immutable/List;)V;
const #443 = NameAndType	#22:#442;//  "<init>":(Ljava/lang/Object;Lscala/collection/immutable/List;)V
const #444 = Method	#332.#443;	//  scala/collection/immutable/$colon$colon."<init>":(Ljava/lang/Object;Lscala/collection/immutable/List;)V
const #445 = Asciz	java/lang/Exception;
const #446 = class	#445;	//  java/lang/Exception
const #447 = Asciz	seq;
const #448 = Asciz	newElem;
const #449 = Asciz	$inlThis3;
const #450 = Asciz	(ILscala/collection/Traversable<TA;>;)V;
const #451 = Asciz	clear;
const #452 = Asciz	last1;
const #453 = Asciz	update;
const #454 = Asciz	(ILjava/lang/Object;)V;
const #455 = Asciz	$inlThis5;
const #456 = Asciz	(ITA;)V;
const #457 = Asciz	(Lscala/collection/generic/SeqForwarder;I)Ljava/lang/Object;;
const #458 = NameAndType	#164:#457;//  apply:(Lscala/collection/generic/SeqForwarder;I)Ljava/lang/Object;
const #459 = Method	#140.#458;	//  scala/collection/generic/SeqForwarder$class.apply:(Lscala/collection/generic/SeqForwarder;I)Ljava/lang/Object;
const #460 = Asciz	()Lscala/collection/immutable/Seq<TA;>;;
const #461 = Asciz	()Lscala/collection/immutable/$colon$colon;;
const #462 = Asciz	companion;
const #463 = Asciz	()Lscala/collection/generic/GenericCompanion;;
const #464 = Asciz	scala/collection/mutable/ListBuffer$;
const #465 = class	#464;	//  scala/collection/mutable/ListBuffer$
const #466 = Asciz	Lscala/collection/mutable/ListBuffer$;;
const #467 = NameAndType	#146:#466;//  MODULE$:Lscala/collection/mutable/ListBuffer$;
const #468 = Field	#465.#467;	//  scala/collection/mutable/ListBuffer$.MODULE$:Lscala/collection/mutable/ListBuffer$;
const #469 = Asciz	()Lscala/collection/generic/GenericCompanion<Lscala/collection/mutable/ListBuffer;>;;
const #470 = Asciz	withFilter;
const #471 = Asciz	(Lscala/Function1;)Lscala/collection/TraversableLike$WithFilter;;
const #472 = Asciz	(Lscala/collection/TraversableLike;Lscala/Function1;)Lscala/collection/TraversableLike$WithFilter;;
const #473 = NameAndType	#470:#472;//  withFilter:(Lscala/collection/TraversableLike;Lscala/Function1;)Lscala/collection/TraversableLike$WithFilter;
const #474 = Method	#29.#473;	//  scala/collection/TraversableLike$class.withFilter:(Lscala/collection/TraversableLike;Lscala/Function1;)Lscala/collection/TraversableLike$WithFilter;
const #475 = Asciz	p;
const #476 = Asciz	addString;
const #477 = Asciz	(Lscala/collection/mutable/StringBuilder;)Lscala/collection/mutable/StringBuilder;;
const #478 = Asciz	(Lscala/collection/TraversableLike;Lscala/collection/mutable/StringBuilder;)Lscala/collection/mutable/StringBuilder;;
const #479 = NameAndType	#476:#478;//  addString:(Lscala/collection/TraversableLike;Lscala/collection/mutable/StringBuilder;)Lscala/collection/mutable/StringBuilder;
const #480 = Method	#29.#479;	//  scala/collection/TraversableLike$class.addString:(Lscala/collection/TraversableLike;Lscala/collection/mutable/StringBuilder;)Lscala/collection/mutable/StringBuilder;
const #481 = Asciz	b;
const #482 = Asciz	Lscala/collection/mutable/StringBuilder;;
const #483 = Asciz	(Lscala/collection/mutable/StringBuilder;Ljava/lang/String;)Lscala/collection/mutable/StringBuilder;;
const #484 = Asciz	(Lscala/collection/TraversableLike;Lscala/collection/mutable/StringBuilder;Ljava/lang/String;)Lscala/collection/mutable/StringBuilder;;
const #485 = NameAndType	#476:#484;//  addString:(Lscala/collection/TraversableLike;Lscala/collection/mutable/StringBuilder;Ljava/lang/String;)Lscala/collection/mutable/StringBuilder;
const #486 = Method	#29.#485;	//  scala/collection/TraversableLike$class.addString:(Lscala/collection/TraversableLike;Lscala/collection/mutable/StringBuilder;Ljava/lang/String;)Lscala/collection/mutable/StringBuilder;
const #487 = Asciz	sep;
const #488 = Asciz	Ljava/lang/String;;
const #489 = Asciz	mkString;
const #490 = Asciz	(Lscala/collection/TraversableLike;)Ljava/lang/String;;
const #491 = NameAndType	#489:#490;//  mkString:(Lscala/collection/TraversableLike;)Ljava/lang/String;
const #492 = Method	#29.#491;	//  scala/collection/TraversableLike$class.mkString:(Lscala/collection/TraversableLike;)Ljava/lang/String;
const #493 = Asciz	(Ljava/lang/String;)Ljava/lang/String;;
const #494 = Asciz	(Lscala/collection/TraversableLike;Ljava/lang/String;)Ljava/lang/String;;
const #495 = NameAndType	#489:#494;//  mkString:(Lscala/collection/TraversableLike;Ljava/lang/String;)Ljava/lang/String;
const #496 = Method	#29.#495;	//  scala/collection/TraversableLike$class.mkString:(Lscala/collection/TraversableLike;Ljava/lang/String;)Ljava/lang/String;
const #497 = Asciz	toSet;
const #498 = Asciz	()Lscala/collection/immutable/Set;;
const #499 = Asciz	(Lscala/collection/TraversableLike;)Lscala/collection/immutable/Set;;
const #500 = NameAndType	#497:#499;//  toSet:(Lscala/collection/TraversableLike;)Lscala/collection/immutable/Set;
const #501 = Method	#29.#500;	//  scala/collection/TraversableLike$class.toSet:(Lscala/collection/TraversableLike;)Lscala/collection/immutable/Set;
const #502 = Asciz	toIndexedSeq;
const #503 = Asciz	()Lscala/collection/mutable/IndexedSeq;;
const #504 = Asciz	(Lscala/collection/TraversableLike;)Lscala/collection/mutable/IndexedSeq;;
const #505 = NameAndType	#502:#504;//  toIndexedSeq:(Lscala/collection/TraversableLike;)Lscala/collection/mutable/IndexedSeq;
const #506 = Method	#29.#505;	//  scala/collection/TraversableLike$class.toIndexedSeq:(Lscala/collection/TraversableLike;)Lscala/collection/mutable/IndexedSeq;
const #507 = Asciz	copyToArray;
const #508 = Asciz	(Ljava/lang/Object;)V;
const #509 = Asciz	(Lscala/collection/TraversableLike;Ljava/lang/Object;)V;
const #510 = NameAndType	#507:#509;//  copyToArray:(Lscala/collection/TraversableLike;Ljava/lang/Object;)V
const #511 = Method	#29.#510;	//  scala/collection/TraversableLike$class.copyToArray:(Lscala/collection/TraversableLike;Ljava/lang/Object;)V
const #512 = Asciz	(Ljava/lang/Object;I)V;
const #513 = Asciz	(Lscala/collection/TraversableLike;Ljava/lang/Object;I)V;
const #514 = NameAndType	#507:#513;//  copyToArray:(Lscala/collection/TraversableLike;Ljava/lang/Object;I)V
const #515 = Method	#29.#514;	//  scala/collection/TraversableLike$class.copyToArray:(Lscala/collection/TraversableLike;Ljava/lang/Object;I)V
const #516 = Asciz	start;
const #517 = Asciz	splitAt;
const #518 = Asciz	(I)Lscala/Tuple2;;
const #519 = Asciz	(Lscala/collection/TraversableLike;I)Lscala/Tuple2;;
const #520 = NameAndType	#517:#519;//  splitAt:(Lscala/collection/TraversableLike;I)Lscala/Tuple2;
const #521 = Method	#29.#520;	//  scala/collection/TraversableLike$class.splitAt:(Lscala/collection/TraversableLike;I)Lscala/Tuple2;
const #522 = Asciz	span;
const #523 = Asciz	(Lscala/Function1;)Lscala/Tuple2;;
const #524 = Asciz	(Lscala/collection/TraversableLike;Lscala/Function1;)Lscala/Tuple2;;
const #525 = NameAndType	#522:#524;//  span:(Lscala/collection/TraversableLike;Lscala/Function1;)Lscala/Tuple2;
const #526 = Method	#29.#525;	//  scala/collection/TraversableLike$class.span:(Lscala/collection/TraversableLike;Lscala/Function1;)Lscala/Tuple2;
const #527 = Asciz	dropWhile;
const #528 = Asciz	(Lscala/Function1;)Ljava/lang/Object;;
const #529 = Asciz	(Lscala/collection/TraversableLike;Lscala/Function1;)Ljava/lang/Object;;
const #530 = NameAndType	#527:#529;//  dropWhile:(Lscala/collection/TraversableLike;Lscala/Function1;)Ljava/lang/Object;
const #531 = Method	#29.#530;	//  scala/collection/TraversableLike$class.dropWhile:(Lscala/collection/TraversableLike;Lscala/Function1;)Ljava/lang/Object;
const #532 = Asciz	drop;
const #533 = Asciz	(Lscala/collection/TraversableLike;I)Ljava/lang/Object;;
const #534 = NameAndType	#532:#533;//  drop:(Lscala/collection/TraversableLike;I)Ljava/lang/Object;
const #535 = Method	#29.#534;	//  scala/collection/TraversableLike$class.drop:(Lscala/collection/TraversableLike;I)Ljava/lang/Object;
const #536 = Asciz	init;
const #537 = Asciz	(Lscala/collection/TraversableLike;)Ljava/lang/Object;;
const #538 = NameAndType	#536:#537;//  init:(Lscala/collection/TraversableLike;)Ljava/lang/Object;
const #539 = Method	#29.#538;	//  scala/collection/TraversableLike$class.init:(Lscala/collection/TraversableLike;)Ljava/lang/Object;
const #540 = NameAndType	#353:#537;//  tail:(Lscala/collection/TraversableLike;)Ljava/lang/Object;
const #541 = Method	#29.#540;	//  scala/collection/TraversableLike$class.tail:(Lscala/collection/TraversableLike;)Ljava/lang/Object;
const #542 = Asciz	headOption;
const #543 = Asciz	()Lscala/Option;;
const #544 = Asciz	(Lscala/collection/TraversableLike;)Lscala/Option;;
const #545 = NameAndType	#542:#544;//  headOption:(Lscala/collection/TraversableLike;)Lscala/Option;
const #546 = Method	#29.#545;	//  scala/collection/TraversableLike$class.headOption:(Lscala/collection/TraversableLike;)Lscala/Option;
const #547 = Asciz	(Lscala/math/Ordering;)Ljava/lang/Object;;
const #548 = Asciz	(Lscala/collection/TraversableLike;Lscala/math/Ordering;)Ljava/lang/Object;;
const #549 = NameAndType	#420:#548;//  max:(Lscala/collection/TraversableLike;Lscala/math/Ordering;)Ljava/lang/Object;
const #550 = Method	#29.#549;	//  scala/collection/TraversableLike$class.max:(Lscala/collection/TraversableLike;Lscala/math/Ordering;)Ljava/lang/Object;
const #551 = Asciz	cmp;
const #552 = Asciz	Lscala/math/Ordering;;
const #553 = NameAndType	#424:#548;//  min:(Lscala/collection/TraversableLike;Lscala/math/Ordering;)Ljava/lang/Object;
const #554 = Method	#29.#553;	//  scala/collection/TraversableLike$class.min:(Lscala/collection/TraversableLike;Lscala/math/Ordering;)Ljava/lang/Object;
const #555 = Asciz	product;
const #556 = Asciz	(Lscala/math/Numeric;)Ljava/lang/Object;;
const #557 = Asciz	(Lscala/collection/TraversableLike;Lscala/math/Numeric;)Ljava/lang/Object;;
const #558 = NameAndType	#555:#557;//  product:(Lscala/collection/TraversableLike;Lscala/math/Numeric;)Ljava/lang/Object;
const #559 = Method	#29.#558;	//  scala/collection/TraversableLike$class.product:(Lscala/collection/TraversableLike;Lscala/math/Numeric;)Ljava/lang/Object;
const #560 = Asciz	num;
const #561 = Asciz	Lscala/math/Numeric;;
const #562 = Asciz	sum;
const #563 = NameAndType	#562:#557;//  sum:(Lscala/collection/TraversableLike;Lscala/math/Numeric;)Ljava/lang/Object;
const #564 = Method	#29.#563;	//  scala/collection/TraversableLike$class.sum:(Lscala/collection/TraversableLike;Lscala/math/Numeric;)Ljava/lang/Object;
const #565 = Asciz	$colon$bslash;
const #566 = Asciz	(Ljava/lang/Object;Lscala/Function2;)Ljava/lang/Object;;
const #567 = Asciz	(Lscala/collection/TraversableLike;Ljava/lang/Object;Lscala/Function2;)Ljava/lang/Object;;
const #568 = NameAndType	#565:#567;//  $colon$bslash:(Lscala/collection/TraversableLike;Ljava/lang/Object;Lscala/Function2;)Ljava/lang/Object;
const #569 = Method	#29.#568;	//  scala/collection/TraversableLike$class.$colon$bslash:(Lscala/collection/TraversableLike;Ljava/lang/Object;Lscala/Function2;)Ljava/lang/Object;
const #570 = Asciz	op;
const #571 = Asciz	Lscala/Function2;;
const #572 = Asciz	$div$colon;
const #573 = NameAndType	#572:#567;//  $div$colon:(Lscala/collection/TraversableLike;Ljava/lang/Object;Lscala/Function2;)Ljava/lang/Object;
const #574 = Method	#29.#573;	//  scala/collection/TraversableLike$class.$div$colon:(Lscala/collection/TraversableLike;Ljava/lang/Object;Lscala/Function2;)Ljava/lang/Object;
const #575 = Asciz	groupBy;
const #576 = Asciz	(Lscala/Function1;)Lscala/collection/Map;;
const #577 = Asciz	(Lscala/collection/TraversableLike;Lscala/Function1;)Lscala/collection/Map;;
const #578 = NameAndType	#575:#577;//  groupBy:(Lscala/collection/TraversableLike;Lscala/Function1;)Lscala/collection/Map;
const #579 = Method	#29.#578;	//  scala/collection/TraversableLike$class.groupBy:(Lscala/collection/TraversableLike;Lscala/Function1;)Lscala/collection/Map;
const #580 = Asciz	f;
const #581 = Asciz	partition;
const #582 = NameAndType	#581:#524;//  partition:(Lscala/collection/TraversableLike;Lscala/Function1;)Lscala/Tuple2;
const #583 = Method	#29.#582;	//  scala/collection/TraversableLike$class.partition:(Lscala/collection/TraversableLike;Lscala/Function1;)Lscala/Tuple2;
const #584 = Asciz	partialMap;
const #585 = Asciz	(Lscala/PartialFunction;Lscala/collection/generic/CanBuildFrom;)Ljava/lang/Object;;
const #586 = Asciz	(Lscala/collection/TraversableLike;Lscala/PartialFunction;Lscala/collection/generic/CanBuildFrom;)Ljava/lang/Object;;
const #587 = NameAndType	#584:#586;//  partialMap:(Lscala/collection/TraversableLike;Lscala/PartialFunction;Lscala/collection/generic/CanBuildFrom;)Ljava/lang/Object;
const #588 = Method	#29.#587;	//  scala/collection/TraversableLike$class.partialMap:(Lscala/collection/TraversableLike;Lscala/PartialFunction;Lscala/collection/generic/CanBuildFrom;)Ljava/lang/Object;
const #589 = Asciz	pf;
const #590 = Asciz	Lscala/PartialFunction;;
const #591 = Asciz	bf;
const #592 = Asciz	Lscala/collection/generic/CanBuildFrom;;
const #593 = Asciz	filterNot;
const #594 = NameAndType	#593:#529;//  filterNot:(Lscala/collection/TraversableLike;Lscala/Function1;)Ljava/lang/Object;
const #595 = Method	#29.#594;	//  scala/collection/TraversableLike$class.filterNot:(Lscala/collection/TraversableLike;Lscala/Function1;)Ljava/lang/Object;
const #596 = Asciz	filter;
const #597 = NameAndType	#596:#529;//  filter:(Lscala/collection/TraversableLike;Lscala/Function1;)Ljava/lang/Object;
const #598 = Method	#29.#597;	//  scala/collection/TraversableLike$class.filter:(Lscala/collection/TraversableLike;Lscala/Function1;)Ljava/lang/Object;
const #599 = Asciz	flatMap;
const #600 = Asciz	(Lscala/Function1;Lscala/collection/generic/CanBuildFrom;)Ljava/lang/Object;;
const #601 = Asciz	(Lscala/collection/TraversableLike;Lscala/Function1;Lscala/collection/generic/CanBuildFrom;)Ljava/lang/Object;;
const #602 = NameAndType	#599:#601;//  flatMap:(Lscala/collection/TraversableLike;Lscala/Function1;Lscala/collection/generic/CanBuildFrom;)Ljava/lang/Object;
const #603 = Method	#29.#602;	//  scala/collection/TraversableLike$class.flatMap:(Lscala/collection/TraversableLike;Lscala/Function1;Lscala/collection/generic/CanBuildFrom;)Ljava/lang/Object;
const #604 = Asciz	map;
const #605 = NameAndType	#604:#601;//  map:(Lscala/collection/TraversableLike;Lscala/Function1;Lscala/collection/generic/CanBuildFrom;)Ljava/lang/Object;
const #606 = Method	#29.#605;	//  scala/collection/TraversableLike$class.map:(Lscala/collection/TraversableLike;Lscala/Function1;Lscala/collection/generic/CanBuildFrom;)Ljava/lang/Object;
const #607 = Asciz	(Lscala/collection/Iterator;Lscala/collection/generic/CanBuildFrom;)Ljava/lang/Object;;
const #608 = Asciz	(Lscala/collection/TraversableLike;Lscala/collection/Iterator;Lscala/collection/generic/CanBuildFrom;)Ljava/lang/Object;;
const #609 = NameAndType	#235:#608;//  $plus$plus:(Lscala/collection/TraversableLike;Lscala/collection/Iterator;Lscala/collection/generic/CanBuildFrom;)Ljava/lang/Object;
const #610 = Method	#29.#609;	//  scala/collection/TraversableLike$class.$plus$plus:(Lscala/collection/TraversableLike;Lscala/collection/Iterator;Lscala/collection/generic/CanBuildFrom;)Ljava/lang/Object;
const #611 = Asciz	(Lscala/collection/Traversable;Lscala/collection/generic/CanBuildFrom;)Ljava/lang/Object;;
const #612 = Asciz	(Lscala/collection/TraversableLike;Lscala/collection/Traversable;Lscala/collection/generic/CanBuildFrom;)Ljava/lang/Object;;
const #613 = NameAndType	#235:#612;//  $plus$plus:(Lscala/collection/TraversableLike;Lscala/collection/Traversable;Lscala/collection/generic/CanBuildFrom;)Ljava/lang/Object;
const #614 = Method	#29.#613;	//  scala/collection/TraversableLike$class.$plus$plus:(Lscala/collection/TraversableLike;Lscala/collection/Traversable;Lscala/collection/generic/CanBuildFrom;)Ljava/lang/Object;
const #615 = NameAndType	#271:#537;//  repr:(Lscala/collection/TraversableLike;)Ljava/lang/Object;
const #616 = Method	#29.#615;	//  scala/collection/TraversableLike$class.repr:(Lscala/collection/TraversableLike;)Ljava/lang/Object;
const #617 = Asciz	transpose;
const #618 = Asciz	(Lscala/Function1;)Lscala/collection/Traversable;;
const #619 = Asciz	(Lscala/collection/generic/GenericTraversableTemplate;Lscala/Function1;)Lscala/collection/Traversable;;
const #620 = NameAndType	#617:#619;//  transpose:(Lscala/collection/generic/GenericTraversableTemplate;Lscala/Function1;)Lscala/collection/Traversable;
const #621 = Method	#35.#620;	//  scala/collection/generic/GenericTraversableTemplate$class.transpose:(Lscala/collection/generic/GenericTraversableTemplate;Lscala/Function1;)Lscala/collection/Traversable;
const #622 = Asciz	asTraversable;
const #623 = Asciz	flatten;
const #624 = NameAndType	#623:#619;//  flatten:(Lscala/collection/generic/GenericTraversableTemplate;Lscala/Function1;)Lscala/collection/Traversable;
const #625 = Method	#35.#624;	//  scala/collection/generic/GenericTraversableTemplate$class.flatten:(Lscala/collection/generic/GenericTraversableTemplate;Lscala/Function1;)Lscala/collection/Traversable;
const #626 = Asciz	unzip;
const #627 = Asciz	(Lscala/collection/generic/GenericTraversableTemplate;Lscala/Function1;)Lscala/Tuple2;;
const #628 = NameAndType	#626:#627;//  unzip:(Lscala/collection/generic/GenericTraversableTemplate;Lscala/Function1;)Lscala/Tuple2;
const #629 = Method	#35.#628;	//  scala/collection/generic/GenericTraversableTemplate$class.unzip:(Lscala/collection/generic/GenericTraversableTemplate;Lscala/Function1;)Lscala/Tuple2;
const #630 = Asciz	asPair;
const #631 = Asciz	genericBuilder;
const #632 = Asciz	()Lscala/collection/mutable/Builder;;
const #633 = Asciz	(Lscala/collection/generic/GenericTraversableTemplate;)Lscala/collection/mutable/Builder;;
const #634 = NameAndType	#631:#633;//  genericBuilder:(Lscala/collection/generic/GenericTraversableTemplate;)Lscala/collection/mutable/Builder;
const #635 = Method	#35.#634;	//  scala/collection/generic/GenericTraversableTemplate$class.genericBuilder:(Lscala/collection/generic/GenericTraversableTemplate;)Lscala/collection/mutable/Builder;
const #636 = Asciz	newBuilder;
const #637 = NameAndType	#636:#633;//  newBuilder:(Lscala/collection/generic/GenericTraversableTemplate;)Lscala/collection/mutable/Builder;
const #638 = Method	#35.#637;	//  scala/collection/generic/GenericTraversableTemplate$class.newBuilder:(Lscala/collection/generic/GenericTraversableTemplate;)Lscala/collection/mutable/Builder;
const #639 = Asciz	firstOption;
const #640 = Asciz	(Lscala/collection/IterableLike;)Lscala/Option;;
const #641 = NameAndType	#639:#640;//  firstOption:(Lscala/collection/IterableLike;)Lscala/Option;
const #642 = Method	#50.#641;	//  scala/collection/IterableLike$class.firstOption:(Lscala/collection/IterableLike;)Lscala/Option;
const #643 = Asciz	Deprecated;
const #644 = Asciz	first;
const #645 = Asciz	(Lscala/collection/IterableLike;)Ljava/lang/Object;;
const #646 = NameAndType	#644:#645;//  first:(Lscala/collection/IterableLike;)Ljava/lang/Object;
const #647 = Method	#50.#646;	//  scala/collection/IterableLike$class.first:(Lscala/collection/IterableLike;)Ljava/lang/Object;
const #648 = Asciz	canEqual;
const #649 = Asciz	(Lscala/collection/IterableLike;Ljava/lang/Object;)Z;
const #650 = NameAndType	#648:#649;//  canEqual:(Lscala/collection/IterableLike;Ljava/lang/Object;)Z
const #651 = Method	#50.#650;	//  scala/collection/IterableLike$class.canEqual:(Lscala/collection/IterableLike;Ljava/lang/Object;)Z
const #652 = Asciz	zipWithIndex;
const #653 = Asciz	(Lscala/collection/generic/CanBuildFrom;)Ljava/lang/Object;;
const #654 = Asciz	(Lscala/collection/IterableLike;Lscala/collection/generic/CanBuildFrom;)Ljava/lang/Object;;
const #655 = NameAndType	#652:#654;//  zipWithIndex:(Lscala/collection/IterableLike;Lscala/collection/generic/CanBuildFrom;)Ljava/lang/Object;
const #656 = Method	#50.#655;	//  scala/collection/IterableLike$class.zipWithIndex:(Lscala/collection/IterableLike;Lscala/collection/generic/CanBuildFrom;)Ljava/lang/Object;
const #657 = Asciz	zipAll;
const #658 = Asciz	(Lscala/collection/Iterable;Ljava/lang/Object;Ljava/lang/Object;Lscala/collection/generic/CanBuildFrom;)Ljava/lang/Object;;
const #659 = Asciz	(Lscala/collection/IterableLike;Lscala/collection/Iterable;Ljava/lang/Object;Ljava/lang/Object;Lscala/collection/generic/CanBuildFrom;)Ljava/lang/Object;;
const #660 = NameAndType	#657:#659;//  zipAll:(Lscala/collection/IterableLike;Lscala/collection/Iterable;Ljava/lang/Object;Ljava/lang/Object;Lscala/collection/generic/CanBuildFrom;)Ljava/lang/Object;
const #661 = Method	#50.#660;	//  scala/collection/IterableLike$class.zipAll:(Lscala/collection/IterableLike;Lscala/collection/Iterable;Ljava/lang/Object;Ljava/lang/Object;Lscala/collection/generic/CanBuildFrom;)Ljava/lang/Object;
const #662 = Asciz	Lscala/collection/Iterable;;
const #663 = Asciz	thisElem;
const #664 = Asciz	thatElem;
const #665 = Asciz	zip;
const #666 = Asciz	(Lscala/collection/Iterable;Lscala/collection/generic/CanBuildFrom;)Ljava/lang/Object;;
const #667 = Asciz	(Lscala/collection/IterableLike;Lscala/collection/Iterable;Lscala/collection/generic/CanBuildFrom;)Ljava/lang/Object;;
const #668 = NameAndType	#665:#667;//  zip:(Lscala/collection/IterableLike;Lscala/collection/Iterable;Lscala/collection/generic/CanBuildFrom;)Ljava/lang/Object;
const #669 = Method	#50.#668;	//  scala/collection/IterableLike$class.zip:(Lscala/collection/IterableLike;Lscala/collection/Iterable;Lscala/collection/generic/CanBuildFrom;)Ljava/lang/Object;
const #670 = Asciz	dropRight;
const #671 = Asciz	(Lscala/collection/IterableLike;I)Ljava/lang/Object;;
const #672 = NameAndType	#670:#671;//  dropRight:(Lscala/collection/IterableLike;I)Ljava/lang/Object;
const #673 = Method	#50.#672;	//  scala/collection/IterableLike$class.dropRight:(Lscala/collection/IterableLike;I)Ljava/lang/Object;
const #674 = Asciz	takeRight;
const #675 = NameAndType	#674:#671;//  takeRight:(Lscala/collection/IterableLike;I)Ljava/lang/Object;
const #676 = Method	#50.#675;	//  scala/collection/IterableLike$class.takeRight:(Lscala/collection/IterableLike;I)Ljava/lang/Object;
const #677 = Asciz	takeWhile;
const #678 = Asciz	(Lscala/collection/IterableLike;Lscala/Function1;)Ljava/lang/Object;;
const #679 = NameAndType	#677:#678;//  takeWhile:(Lscala/collection/IterableLike;Lscala/Function1;)Ljava/lang/Object;
const #680 = Method	#50.#679;	//  scala/collection/IterableLike$class.takeWhile:(Lscala/collection/IterableLike;Lscala/Function1;)Ljava/lang/Object;
const #681 = Asciz	slice;
const #682 = Asciz	(II)Ljava/lang/Object;;
const #683 = Asciz	(Lscala/collection/IterableLike;II)Ljava/lang/Object;;
const #684 = NameAndType	#681:#683;//  slice:(Lscala/collection/IterableLike;II)Ljava/lang/Object;
const #685 = Method	#50.#684;	//  scala/collection/IterableLike$class.slice:(Lscala/collection/IterableLike;II)Ljava/lang/Object;
const #686 = Asciz	take;
const #687 = NameAndType	#686:#671;//  take:(Lscala/collection/IterableLike;I)Ljava/lang/Object;
const #688 = Method	#50.#687;	//  scala/collection/IterableLike$class.take:(Lscala/collection/IterableLike;I)Ljava/lang/Object;
const #689 = Asciz	toIterable;
const #690 = Asciz	(Lscala/collection/IterableLike;)Lscala/collection/Iterable;;
const #691 = NameAndType	#689:#690;//  toIterable:(Lscala/collection/IterableLike;)Lscala/collection/Iterable;
const #692 = Method	#50.#691;	//  scala/collection/IterableLike$class.toIterable:(Lscala/collection/IterableLike;)Lscala/collection/Iterable;
const #693 = Asciz	elements;
const #694 = Asciz	(Lscala/collection/IterableLike;)Lscala/collection/Iterator;;
const #695 = NameAndType	#693:#694;//  elements:(Lscala/collection/IterableLike;)Lscala/collection/Iterator;
const #696 = Method	#50.#695;	//  scala/collection/IterableLike$class.elements:(Lscala/collection/IterableLike;)Lscala/collection/Iterator;
const #697 = Asciz	compose;
const #698 = Asciz	(Lscala/Function1;Lscala/Function1;)Lscala/Function1;;
const #699 = NameAndType	#697:#698;//  compose:(Lscala/Function1;Lscala/Function1;)Lscala/Function1;
const #700 = Method	#65.#699;	//  scala/Function1$class.compose:(Lscala/Function1;Lscala/Function1;)Lscala/Function1;
const #701 = Asciz	lift;
const #702 = Asciz	()Lscala/Function1;;
const #703 = Asciz	(Lscala/PartialFunction;)Lscala/Function1;;
const #704 = NameAndType	#701:#703;//  lift:(Lscala/PartialFunction;)Lscala/Function1;
const #705 = Method	#70.#704;	//  scala/PartialFunction$class.lift:(Lscala/PartialFunction;)Lscala/Function1;
const #706 = Asciz	(Lscala/PartialFunction;Lscala/Function1;)Lscala/PartialFunction;;
const #707 = NameAndType	#281:#706;//  andThen:(Lscala/PartialFunction;Lscala/Function1;)Lscala/PartialFunction;
const #708 = Method	#70.#707;	//  scala/PartialFunction$class.andThen:(Lscala/PartialFunction;Lscala/Function1;)Lscala/PartialFunction;
const #709 = Asciz	k;
const #710 = Asciz	orElse;
const #711 = Asciz	(Lscala/PartialFunction;)Lscala/PartialFunction;;
const #712 = Asciz	(Lscala/PartialFunction;Lscala/PartialFunction;)Lscala/PartialFunction;;
const #713 = NameAndType	#710:#712;//  orElse:(Lscala/PartialFunction;Lscala/PartialFunction;)Lscala/PartialFunction;
const #714 = Method	#70.#713;	//  scala/PartialFunction$class.orElse:(Lscala/PartialFunction;Lscala/PartialFunction;)Lscala/PartialFunction;
const #715 = Asciz	projection;
const #716 = Asciz	(Lscala/collection/SeqLike;)Ljava/lang/Object;;
const #717 = NameAndType	#715:#716;//  projection:(Lscala/collection/SeqLike;)Ljava/lang/Object;
const #718 = Method	#75.#717;	//  scala/collection/SeqLike$class.projection:(Lscala/collection/SeqLike;)Ljava/lang/Object;
const #719 = Asciz	equalsWith;
const #720 = Asciz	(Lscala/collection/Seq;Lscala/Function2;)Z;
const #721 = Asciz	(Lscala/collection/SeqLike;Lscala/collection/Seq;Lscala/Function2;)Z;
const #722 = NameAndType	#719:#721;//  equalsWith:(Lscala/collection/SeqLike;Lscala/collection/Seq;Lscala/Function2;)Z
const #723 = Method	#75.#722;	//  scala/collection/SeqLike$class.equalsWith:(Lscala/collection/SeqLike;Lscala/collection/Seq;Lscala/Function2;)Z
const #724 = Asciz	findLastIndexOf;
const #725 = Asciz	(Lscala/Function1;)I;
const #726 = Asciz	(Lscala/collection/SeqLike;Lscala/Function1;)I;
const #727 = NameAndType	#724:#726;//  findLastIndexOf:(Lscala/collection/SeqLike;Lscala/Function1;)I
const #728 = Method	#75.#727;	//  scala/collection/SeqLike$class.findLastIndexOf:(Lscala/collection/SeqLike;Lscala/Function1;)I
const #729 = Asciz	(Lscala/collection/SeqLike;)Ljava/lang/String;;
const #730 = NameAndType	#317:#729;//  toString:(Lscala/collection/SeqLike;)Ljava/lang/String;
const #731 = Method	#75.#730;	//  scala/collection/SeqLike$class.toString:(Lscala/collection/SeqLike;)Ljava/lang/String;
const #732 = Asciz	hashCode;
const #733 = Asciz	(Lscala/collection/SeqLike;)I;
const #734 = NameAndType	#732:#733;//  hashCode:(Lscala/collection/SeqLike;)I
const #735 = Method	#75.#734;	//  scala/collection/SeqLike$class.hashCode:(Lscala/collection/SeqLike;)I
const #736 = Asciz	(Lscala/collection/SeqLike;II)Lscala/collection/SeqView;;
const #737 = NameAndType	#273:#736;//  view:(Lscala/collection/SeqLike;II)Lscala/collection/SeqView;
const #738 = Method	#75.#737;	//  scala/collection/SeqLike$class.view:(Lscala/collection/SeqLike;II)Lscala/collection/SeqView;
const #739 = NameAndType	#273:#716;//  view:(Lscala/collection/SeqLike;)Ljava/lang/Object;
const #740 = Method	#75.#739;	//  scala/collection/SeqLike$class.view:(Lscala/collection/SeqLike;)Ljava/lang/Object;
const #741 = Asciz	sortBy;
const #742 = Asciz	(Lscala/Function1;Lscala/math/Ordering;)Ljava/lang/Object;;
const #743 = Asciz	(Lscala/collection/SeqLike;Lscala/Function1;Lscala/math/Ordering;)Ljava/lang/Object;;
const #744 = NameAndType	#741:#743;//  sortBy:(Lscala/collection/SeqLike;Lscala/Function1;Lscala/math/Ordering;)Ljava/lang/Object;
const #745 = Method	#75.#744;	//  scala/collection/SeqLike$class.sortBy:(Lscala/collection/SeqLike;Lscala/Function1;Lscala/math/Ordering;)Ljava/lang/Object;
const #746 = Asciz	ord;
const #747 = Asciz	sortWith;
const #748 = Asciz	(Lscala/collection/SeqLike;Lscala/math/Ordering;)Ljava/lang/Object;;
const #749 = NameAndType	#747:#748;//  sortWith:(Lscala/collection/SeqLike;Lscala/math/Ordering;)Ljava/lang/Object;
const #750 = Method	#75.#749;	//  scala/collection/SeqLike$class.sortWith:(Lscala/collection/SeqLike;Lscala/math/Ordering;)Ljava/lang/Object;
const #751 = Asciz	(Lscala/Function2;)Ljava/lang/Object;;
const #752 = Asciz	(Lscala/collection/SeqLike;Lscala/Function2;)Ljava/lang/Object;;
const #753 = NameAndType	#747:#752;//  sortWith:(Lscala/collection/SeqLike;Lscala/Function2;)Ljava/lang/Object;
const #754 = Method	#75.#753;	//  scala/collection/SeqLike$class.sortWith:(Lscala/collection/SeqLike;Lscala/Function2;)Ljava/lang/Object;
const #755 = Asciz	lt;
const #756 = Asciz	corresponds;
const #757 = NameAndType	#756:#721;//  corresponds:(Lscala/collection/SeqLike;Lscala/collection/Seq;Lscala/Function2;)Z
const #758 = Method	#75.#757;	//  scala/collection/SeqLike$class.corresponds:(Lscala/collection/SeqLike;Lscala/collection/Seq;Lscala/Function2;)Z
const #759 = Asciz	padTo;
const #760 = Asciz	(ILjava/lang/Object;Lscala/collection/generic/CanBuildFrom;)Ljava/lang/Object;;
const #761 = Asciz	(Lscala/collection/SeqLike;ILjava/lang/Object;Lscala/collection/generic/CanBuildFrom;)Ljava/lang/Object;;
const #762 = NameAndType	#759:#761;//  padTo:(Lscala/collection/SeqLike;ILjava/lang/Object;Lscala/collection/generic/CanBuildFrom;)Ljava/lang/Object;
const #763 = Method	#75.#762;	//  scala/collection/SeqLike$class.padTo:(Lscala/collection/SeqLike;ILjava/lang/Object;Lscala/collection/generic/CanBuildFrom;)Ljava/lang/Object;
const #764 = Asciz	$colon$plus;
const #765 = Asciz	(Ljava/lang/Object;Lscala/collection/generic/CanBuildFrom;)Ljava/lang/Object;;
const #766 = Asciz	(Lscala/collection/SeqLike;Ljava/lang/Object;Lscala/collection/generic/CanBuildFrom;)Ljava/lang/Object;;
const #767 = NameAndType	#764:#766;//  $colon$plus:(Lscala/collection/SeqLike;Ljava/lang/Object;Lscala/collection/generic/CanBuildFrom;)Ljava/lang/Object;
const #768 = Method	#75.#767;	//  scala/collection/SeqLike$class.$colon$plus:(Lscala/collection/SeqLike;Ljava/lang/Object;Lscala/collection/generic/CanBuildFrom;)Ljava/lang/Object;
const #769 = Asciz	$plus$colon;
const #770 = NameAndType	#769:#766;//  $plus$colon:(Lscala/collection/SeqLike;Ljava/lang/Object;Lscala/collection/generic/CanBuildFrom;)Ljava/lang/Object;
const #771 = Method	#75.#770;	//  scala/collection/SeqLike$class.$plus$colon:(Lscala/collection/SeqLike;Ljava/lang/Object;Lscala/collection/generic/CanBuildFrom;)Ljava/lang/Object;
const #772 = Asciz	updated;
const #773 = NameAndType	#772:#761;//  updated:(Lscala/collection/SeqLike;ILjava/lang/Object;Lscala/collection/generic/CanBuildFrom;)Ljava/lang/Object;
const #774 = Method	#75.#773;	//  scala/collection/SeqLike$class.updated:(Lscala/collection/SeqLike;ILjava/lang/Object;Lscala/collection/generic/CanBuildFrom;)Ljava/lang/Object;
const #775 = Asciz	index;
const #776 = Asciz	patch;
const #777 = Asciz	(ILscala/collection/Seq;ILscala/collection/generic/CanBuildFrom;)Ljava/lang/Object;;
const #778 = Asciz	(Lscala/collection/SeqLike;ILscala/collection/Seq;ILscala/collection/generic/CanBuildFrom;)Ljava/lang/Object;;
const #779 = NameAndType	#776:#778;//  patch:(Lscala/collection/SeqLike;ILscala/collection/Seq;ILscala/collection/generic/CanBuildFrom;)Ljava/lang/Object;
const #780 = Method	#75.#779;	//  scala/collection/SeqLike$class.patch:(Lscala/collection/SeqLike;ILscala/collection/Seq;ILscala/collection/generic/CanBuildFrom;)Ljava/lang/Object;
const #781 = Asciz	replaced;
const #782 = Asciz	removeDuplicates;
const #783 = NameAndType	#782:#716;//  removeDuplicates:(Lscala/collection/SeqLike;)Ljava/lang/Object;
const #784 = Method	#75.#783;	//  scala/collection/SeqLike$class.removeDuplicates:(Lscala/collection/SeqLike;)Ljava/lang/Object;
const #785 = Asciz	intersect;
const #786 = Asciz	(Lscala/collection/Seq;)Ljava/lang/Object;;
const #787 = Asciz	(Lscala/collection/SeqLike;Lscala/collection/Seq;)Ljava/lang/Object;;
const #788 = NameAndType	#785:#787;//  intersect:(Lscala/collection/SeqLike;Lscala/collection/Seq;)Ljava/lang/Object;
const #789 = Method	#75.#788;	//  scala/collection/SeqLike$class.intersect:(Lscala/collection/SeqLike;Lscala/collection/Seq;)Ljava/lang/Object;
const #790 = Asciz	diff;
const #791 = NameAndType	#790:#787;//  diff:(Lscala/collection/SeqLike;Lscala/collection/Seq;)Ljava/lang/Object;
const #792 = Method	#75.#791;	//  scala/collection/SeqLike$class.diff:(Lscala/collection/SeqLike;Lscala/collection/Seq;)Ljava/lang/Object;
const #793 = Asciz	union;
const #794 = Asciz	(Lscala/collection/Seq;Lscala/collection/generic/CanBuildFrom;)Ljava/lang/Object;;
const #795 = Asciz	(Lscala/collection/SeqLike;Lscala/collection/Seq;Lscala/collection/generic/CanBuildFrom;)Ljava/lang/Object;;
const #796 = NameAndType	#793:#795;//  union:(Lscala/collection/SeqLike;Lscala/collection/Seq;Lscala/collection/generic/CanBuildFrom;)Ljava/lang/Object;
const #797 = Method	#75.#796;	//  scala/collection/SeqLike$class.union:(Lscala/collection/SeqLike;Lscala/collection/Seq;Lscala/collection/generic/CanBuildFrom;)Ljava/lang/Object;
const #798 = Asciz	containsSlice;
const #799 = Asciz	(Lscala/collection/Seq;)Z;
const #800 = Asciz	(Lscala/collection/SeqLike;Lscala/collection/Seq;)Z;
const #801 = NameAndType	#798:#800;//  containsSlice:(Lscala/collection/SeqLike;Lscala/collection/Seq;)Z
const #802 = Method	#75.#801;	//  scala/collection/SeqLike$class.containsSlice:(Lscala/collection/SeqLike;Lscala/collection/Seq;)Z
const #803 = Asciz	lastIndexOfSlice;
const #804 = Asciz	(Lscala/collection/Seq;I)I;
const #805 = Asciz	(Lscala/collection/SeqLike;Lscala/collection/Seq;I)I;
const #806 = NameAndType	#803:#805;//  lastIndexOfSlice:(Lscala/collection/SeqLike;Lscala/collection/Seq;I)I
const #807 = Method	#75.#806;	//  scala/collection/SeqLike$class.lastIndexOfSlice:(Lscala/collection/SeqLike;Lscala/collection/Seq;I)I
const #808 = Asciz	end;
const #809 = Asciz	(Lscala/collection/Seq;)I;
const #810 = Asciz	(Lscala/collection/SeqLike;Lscala/collection/Seq;)I;
const #811 = NameAndType	#803:#810;//  lastIndexOfSlice:(Lscala/collection/SeqLike;Lscala/collection/Seq;)I
const #812 = Method	#75.#811;	//  scala/collection/SeqLike$class.lastIndexOfSlice:(Lscala/collection/SeqLike;Lscala/collection/Seq;)I
const #813 = Asciz	indexOfSlice;
const #814 = NameAndType	#813:#805;//  indexOfSlice:(Lscala/collection/SeqLike;Lscala/collection/Seq;I)I
const #815 = Method	#75.#814;	//  scala/collection/SeqLike$class.indexOfSlice:(Lscala/collection/SeqLike;Lscala/collection/Seq;I)I
const #816 = Asciz	startsWith;
const #817 = NameAndType	#816:#800;//  startsWith:(Lscala/collection/SeqLike;Lscala/collection/Seq;)Z
const #818 = Method	#75.#817;	//  scala/collection/SeqLike$class.startsWith:(Lscala/collection/SeqLike;Lscala/collection/Seq;)Z
const #819 = Asciz	reversedElements;
const #820 = Asciz	(Lscala/collection/SeqLike;)Lscala/collection/Iterator;;
const #821 = NameAndType	#819:#820;//  reversedElements:(Lscala/collection/SeqLike;)Lscala/collection/Iterator;
const #822 = Method	#75.#821;	//  scala/collection/SeqLike$class.reversedElements:(Lscala/collection/SeqLike;)Lscala/collection/Iterator;
const #823 = Asciz	reverseMap;
const #824 = Asciz	(Lscala/collection/SeqLike;Lscala/Function1;Lscala/collection/generic/CanBuildFrom;)Ljava/lang/Object;;
const #825 = NameAndType	#823:#824;//  reverseMap:(Lscala/collection/SeqLike;Lscala/Function1;Lscala/collection/generic/CanBuildFrom;)Ljava/lang/Object;
const #826 = Method	#75.#825;	//  scala/collection/SeqLike$class.reverseMap:(Lscala/collection/SeqLike;Lscala/Function1;Lscala/collection/generic/CanBuildFrom;)Ljava/lang/Object;
const #827 = NameAndType	#434:#716;//  reverse:(Lscala/collection/SeqLike;)Ljava/lang/Object;
const #828 = Method	#75.#827;	//  scala/collection/SeqLike$class.reverse:(Lscala/collection/SeqLike;)Ljava/lang/Object;
const #829 = Asciz	lastIndexWhere;
const #830 = Asciz	(Lscala/Function1;I)I;
const #831 = Asciz	(Lscala/collection/SeqLike;Lscala/Function1;I)I;
const #832 = NameAndType	#829:#831;//  lastIndexWhere:(Lscala/collection/SeqLike;Lscala/Function1;I)I
const #833 = Method	#75.#832;	//  scala/collection/SeqLike$class.lastIndexWhere:(Lscala/collection/SeqLike;Lscala/Function1;I)I
const #834 = NameAndType	#829:#726;//  lastIndexWhere:(Lscala/collection/SeqLike;Lscala/Function1;)I
const #835 = Method	#75.#834;	//  scala/collection/SeqLike$class.lastIndexWhere:(Lscala/collection/SeqLike;Lscala/Function1;)I
const #836 = Asciz	lastIndexOf;
const #837 = Asciz	(Ljava/lang/Object;I)I;
const #838 = Asciz	(Lscala/collection/SeqLike;Ljava/lang/Object;I)I;
const #839 = NameAndType	#836:#838;//  lastIndexOf:(Lscala/collection/SeqLike;Ljava/lang/Object;I)I
const #840 = Method	#75.#839;	//  scala/collection/SeqLike$class.lastIndexOf:(Lscala/collection/SeqLike;Ljava/lang/Object;I)I
const #841 = Asciz	(Lscala/collection/SeqLike;Ljava/lang/Object;)I;
const #842 = NameAndType	#836:#841;//  lastIndexOf:(Lscala/collection/SeqLike;Ljava/lang/Object;)I
const #843 = Method	#75.#842;	//  scala/collection/SeqLike$class.lastIndexOf:(Lscala/collection/SeqLike;Ljava/lang/Object;)I
const #844 = Asciz	indexOf;
const #845 = NameAndType	#844:#841;//  indexOf:(Lscala/collection/SeqLike;Ljava/lang/Object;)I
const #846 = Method	#75.#845;	//  scala/collection/SeqLike$class.indexOf:(Lscala/collection/SeqLike;Ljava/lang/Object;)I
const #847 = Asciz	findIndexOf;
const #848 = NameAndType	#847:#726;//  findIndexOf:(Lscala/collection/SeqLike;Lscala/Function1;)I
const #849 = Method	#75.#848;	//  scala/collection/SeqLike$class.findIndexOf:(Lscala/collection/SeqLike;Lscala/Function1;)I
const #850 = Asciz	indexWhere;
const #851 = NameAndType	#850:#726;//  indexWhere:(Lscala/collection/SeqLike;Lscala/Function1;)I
const #852 = Method	#75.#851;	//  scala/collection/SeqLike$class.indexWhere:(Lscala/collection/SeqLike;Lscala/Function1;)I
const #853 = Asciz	size;
const #854 = NameAndType	#853:#733;//  size:(Lscala/collection/SeqLike;)I
const #855 = Method	#75.#854;	//  scala/collection/SeqLike$class.size:(Lscala/collection/SeqLike;)I
const #856 = Asciz	(Lscala/collection/SeqLike;Ljava/lang/Object;)Lscala/collection/Seq;;
const #857 = NameAndType	#266:#856;//  toCollection:(Lscala/collection/SeqLike;Ljava/lang/Object;)Lscala/collection/Seq;
const #858 = Method	#75.#857;	//  scala/collection/SeqLike$class.toCollection:(Lscala/collection/SeqLike;Ljava/lang/Object;)Lscala/collection/Seq;
const #859 = Asciz	(Lscala/collection/SeqLike;)Lscala/collection/Seq;;
const #860 = NameAndType	#261:#859;//  thisCollection:(Lscala/collection/SeqLike;)Lscala/collection/Seq;
const #861 = Method	#75.#860;	//  scala/collection/SeqLike$class.thisCollection:(Lscala/collection/SeqLike;)Lscala/collection/Seq;
const #862 = Asciz	(Lscala/collection/generic/Growable;Lscala/collection/Traversable;)Lscala/collection/generic/Growable;;
const #863 = NameAndType	#307:#862;//  $plus$plus$eq:(Lscala/collection/generic/Growable;Lscala/collection/Traversable;)Lscala/collection/generic/Growable;
const #864 = Method	#90.#863;	//  scala/collection/generic/Growable$class.$plus$plus$eq:(Lscala/collection/generic/Growable;Lscala/collection/Traversable;)Lscala/collection/generic/Growable;
const #865 = Asciz	(Lscala/collection/Iterator;)Lscala/collection/generic/Growable;;
const #866 = Asciz	(Lscala/collection/generic/Growable;Lscala/collection/Iterator;)Lscala/collection/generic/Growable;;
const #867 = NameAndType	#307:#866;//  $plus$plus$eq:(Lscala/collection/generic/Growable;Lscala/collection/Iterator;)Lscala/collection/generic/Growable;
const #868 = Method	#90.#867;	//  scala/collection/generic/Growable$class.$plus$plus$eq:(Lscala/collection/generic/Growable;Lscala/collection/Iterator;)Lscala/collection/generic/Growable;
const #869 = Asciz	(Ljava/lang/Object;Ljava/lang/Object;Lscala/collection/Seq;)Lscala/collection/generic/Growable;;
const #870 = Asciz	(Lscala/collection/generic/Growable;Ljava/lang/Object;Ljava/lang/Object;Lscala/collection/Seq;)Lscala/collection/generic/Growable;;
const #871 = NameAndType	#180:#870;//  $plus$eq:(Lscala/collection/generic/Growable;Ljava/lang/Object;Ljava/lang/Object;Lscala/collection/Seq;)Lscala/collection/generic/Growable;
const #872 = Method	#90.#871;	//  scala/collection/generic/Growable$class.$plus$eq:(Lscala/collection/generic/Growable;Ljava/lang/Object;Ljava/lang/Object;Lscala/collection/Seq;)Lscala/collection/generic/Growable;
const #873 = Asciz	$minus$minus$eq;
const #874 = Asciz	(Lscala/collection/Traversable;)Lscala/collection/generic/Shrinkable;;
const #875 = Asciz	(Lscala/collection/generic/Shrinkable;Lscala/collection/Traversable;)Lscala/collection/generic/Shrinkable;;
const #876 = NameAndType	#873:#875;//  $minus$minus$eq:(Lscala/collection/generic/Shrinkable;Lscala/collection/Traversable;)Lscala/collection/generic/Shrinkable;
const #877 = Method	#95.#876;	//  scala/collection/generic/Shrinkable$class.$minus$minus$eq:(Lscala/collection/generic/Shrinkable;Lscala/collection/Traversable;)Lscala/collection/generic/Shrinkable;
const #878 = Asciz	(Lscala/collection/Iterator;)Lscala/collection/generic/Shrinkable;;
const #879 = Asciz	(Lscala/collection/generic/Shrinkable;Lscala/collection/Iterator;)Lscala/collection/generic/Shrinkable;;
const #880 = NameAndType	#873:#879;//  $minus$minus$eq:(Lscala/collection/generic/Shrinkable;Lscala/collection/Iterator;)Lscala/collection/generic/Shrinkable;
const #881 = Method	#95.#880;	//  scala/collection/generic/Shrinkable$class.$minus$minus$eq:(Lscala/collection/generic/Shrinkable;Lscala/collection/Iterator;)Lscala/collection/generic/Shrinkable;
const #882 = Asciz	(Ljava/lang/Object;Ljava/lang/Object;Lscala/collection/Seq;)Lscala/collection/generic/Shrinkable;;
const #883 = Asciz	(Lscala/collection/generic/Shrinkable;Ljava/lang/Object;Ljava/lang/Object;Lscala/collection/Seq;)Lscala/collection/generic/Shrinkable;;
const #884 = NameAndType	#196:#883;//  $minus$eq:(Lscala/collection/generic/Shrinkable;Ljava/lang/Object;Ljava/lang/Object;Lscala/collection/Seq;)Lscala/collection/generic/Shrinkable;
const #885 = Method	#95.#884;	//  scala/collection/generic/Shrinkable$class.$minus$eq:(Lscala/collection/generic/Shrinkable;Ljava/lang/Object;Ljava/lang/Object;Lscala/collection/Seq;)Lscala/collection/generic/Shrinkable;
const #886 = Asciz	scala$collection$mutable$Cloneable$$super$clone;
const #887 = NameAndType	#210:#192;//  clone:()Ljava/lang/Object;
const #888 = Method	#25.#887;	//  java/lang/Object.clone:()Ljava/lang/Object;
const #889 = Asciz	(Lscala/collection/mutable/BufferLike;Lscala/collection/Iterator;)Lscala/collection/mutable/BufferLike;;
const #890 = NameAndType	#254:#889;//  $minus$minus:(Lscala/collection/mutable/BufferLike;Lscala/collection/Iterator;)Lscala/collection/mutable/BufferLike;
const #891 = Method	#115.#890;	//  scala/collection/mutable/BufferLike$class.$minus$minus:(Lscala/collection/mutable/BufferLike;Lscala/collection/Iterator;)Lscala/collection/mutable/BufferLike;
const #892 = Asciz	(Lscala/collection/mutable/BufferLike;Ljava/lang/Object;)Lscala/collection/mutable/BufferLike;;
const #893 = NameAndType	#769:#892;//  $plus$colon:(Lscala/collection/mutable/BufferLike;Ljava/lang/Object;)Lscala/collection/mutable/BufferLike;
const #894 = Method	#115.#893;	//  scala/collection/mutable/BufferLike$class.$plus$colon:(Lscala/collection/mutable/BufferLike;Ljava/lang/Object;)Lscala/collection/mutable/BufferLike;
const #895 = Asciz	(Lscala/collection/mutable/BufferLike;Lscala/collection/Traversable;)Lscala/collection/mutable/BufferLike;;
const #896 = NameAndType	#254:#895;//  $minus$minus:(Lscala/collection/mutable/BufferLike;Lscala/collection/Traversable;)Lscala/collection/mutable/BufferLike;
const #897 = Method	#115.#896;	//  scala/collection/mutable/BufferLike$class.$minus$minus:(Lscala/collection/mutable/BufferLike;Lscala/collection/Traversable;)Lscala/collection/mutable/BufferLike;
const #898 = Asciz	(Lscala/collection/mutable/BufferLike;Ljava/lang/Object;Ljava/lang/Object;Lscala/collection/Seq;)Lscala/collection/mutable/BufferLike;;
const #899 = NameAndType	#247:#898;//  $minus:(Lscala/collection/mutable/BufferLike;Ljava/lang/Object;Ljava/lang/Object;Lscala/collection/Seq;)Lscala/collection/mutable/BufferLike;
const #900 = Method	#115.#899;	//  scala/collection/mutable/BufferLike$class.$minus:(Lscala/collection/mutable/BufferLike;Ljava/lang/Object;Ljava/lang/Object;Lscala/collection/Seq;)Lscala/collection/mutable/BufferLike;
const #901 = NameAndType	#247:#892;//  $minus:(Lscala/collection/mutable/BufferLike;Ljava/lang/Object;)Lscala/collection/mutable/BufferLike;
const #902 = Method	#115.#901;	//  scala/collection/mutable/BufferLike$class.$minus:(Lscala/collection/mutable/BufferLike;Ljava/lang/Object;)Lscala/collection/mutable/BufferLike;
const #903 = NameAndType	#235:#889;//  $plus$plus:(Lscala/collection/mutable/BufferLike;Lscala/collection/Iterator;)Lscala/collection/mutable/BufferLike;
const #904 = Method	#115.#903;	//  scala/collection/mutable/BufferLike$class.$plus$plus:(Lscala/collection/mutable/BufferLike;Lscala/collection/Iterator;)Lscala/collection/mutable/BufferLike;
const #905 = NameAndType	#235:#895;//  $plus$plus:(Lscala/collection/mutable/BufferLike;Lscala/collection/Traversable;)Lscala/collection/mutable/BufferLike;
const #906 = Method	#115.#905;	//  scala/collection/mutable/BufferLike$class.$plus$plus:(Lscala/collection/mutable/BufferLike;Lscala/collection/Traversable;)Lscala/collection/mutable/BufferLike;
const #907 = NameAndType	#221:#898;//  $plus:(Lscala/collection/mutable/BufferLike;Ljava/lang/Object;Ljava/lang/Object;Lscala/collection/Seq;)Lscala/collection/mutable/BufferLike;
const #908 = Method	#115.#907;	//  scala/collection/mutable/BufferLike$class.$plus:(Lscala/collection/mutable/BufferLike;Ljava/lang/Object;Ljava/lang/Object;Lscala/collection/Seq;)Lscala/collection/mutable/BufferLike;
const #909 = NameAndType	#221:#892;//  $plus:(Lscala/collection/mutable/BufferLike;Ljava/lang/Object;)Lscala/collection/mutable/BufferLike;
const #910 = Method	#115.#909;	//  scala/collection/mutable/BufferLike$class.$plus:(Lscala/collection/mutable/BufferLike;Ljava/lang/Object;)Lscala/collection/mutable/BufferLike;
const #911 = Asciz	$plus$plus$colon;
const #912 = NameAndType	#911:#895;//  $plus$plus$colon:(Lscala/collection/mutable/BufferLike;Lscala/collection/Traversable;)Lscala/collection/mutable/BufferLike;
const #913 = Method	#115.#912;	//  scala/collection/mutable/BufferLike$class.$plus$plus$colon:(Lscala/collection/mutable/BufferLike;Lscala/collection/Traversable;)Lscala/collection/mutable/BufferLike;
const #914 = Asciz	(Ljava/lang/Object;II)V;
const #915 = Asciz	(Lscala/collection/mutable/BufferLike;Ljava/lang/Object;II)V;
const #916 = NameAndType	#307:#915;//  $plus$plus$eq:(Lscala/collection/mutable/BufferLike;Ljava/lang/Object;II)V
const #917 = Method	#115.#916;	//  scala/collection/mutable/BufferLike$class.$plus$plus$eq:(Lscala/collection/mutable/BufferLike;Ljava/lang/Object;II)V
const #918 = Asciz	src;
const #919 = Asciz	$less$less;
const #920 = Asciz	(Lscala/collection/script/Message;)V;
const #921 = Asciz	(Lscala/collection/mutable/BufferLike;Lscala/collection/script/Message;)V;
const #922 = NameAndType	#919:#921;//  $less$less:(Lscala/collection/mutable/BufferLike;Lscala/collection/script/Message;)V
const #923 = Method	#115.#922;	//  scala/collection/mutable/BufferLike$class.$less$less:(Lscala/collection/mutable/BufferLike;Lscala/collection/script/Message;)V
const #924 = Asciz	cmd;
const #925 = Asciz	Lscala/collection/script/Message;;
const #926 = Asciz	trimEnd;
const #927 = Asciz	(Lscala/collection/mutable/BufferLike;I)V;
const #928 = NameAndType	#926:#927;//  trimEnd:(Lscala/collection/mutable/BufferLike;I)V
const #929 = Method	#115.#928;	//  scala/collection/mutable/BufferLike$class.trimEnd:(Lscala/collection/mutable/BufferLike;I)V
const #930 = Asciz	trimStart;
const #931 = NameAndType	#930:#927;//  trimStart:(Lscala/collection/mutable/BufferLike;I)V
const #932 = Method	#115.#931;	//  scala/collection/mutable/BufferLike$class.trimStart:(Lscala/collection/mutable/BufferLike;I)V
const #933 = Asciz	insert;
const #934 = Asciz	(ILscala/collection/Seq;)V;
const #935 = Asciz	(Lscala/collection/mutable/BufferLike;ILscala/collection/Seq;)V;
const #936 = NameAndType	#933:#935;//  insert:(Lscala/collection/mutable/BufferLike;ILscala/collection/Seq;)V
const #937 = Method	#115.#936;	//  scala/collection/mutable/BufferLike$class.insert:(Lscala/collection/mutable/BufferLike;ILscala/collection/Seq;)V
const #938 = Asciz	prependAll;
const #939 = Asciz	(Lscala/collection/Iterator;)V;
const #940 = Asciz	(Lscala/collection/mutable/BufferLike;Lscala/collection/Iterator;)V;
const #941 = NameAndType	#938:#940;//  prependAll:(Lscala/collection/mutable/BufferLike;Lscala/collection/Iterator;)V
const #942 = Method	#115.#941;	//  scala/collection/mutable/BufferLike$class.prependAll:(Lscala/collection/mutable/BufferLike;Lscala/collection/Iterator;)V
const #943 = Asciz	(Lscala/collection/mutable/BufferLike;Lscala/collection/Traversable;)V;
const #944 = NameAndType	#938:#943;//  prependAll:(Lscala/collection/mutable/BufferLike;Lscala/collection/Traversable;)V
const #945 = Method	#115.#944;	//  scala/collection/mutable/BufferLike$class.prependAll:(Lscala/collection/mutable/BufferLike;Lscala/collection/Traversable;)V
const #946 = Asciz	prepend;
const #947 = Asciz	(Lscala/collection/mutable/BufferLike;Lscala/collection/Seq;)V;
const #948 = NameAndType	#946:#947;//  prepend:(Lscala/collection/mutable/BufferLike;Lscala/collection/Seq;)V
const #949 = Method	#115.#948;	//  scala/collection/mutable/BufferLike$class.prepend:(Lscala/collection/mutable/BufferLike;Lscala/collection/Seq;)V
const #950 = Asciz	appendAll;
const #951 = NameAndType	#950:#940;//  appendAll:(Lscala/collection/mutable/BufferLike;Lscala/collection/Iterator;)V
const #952 = Method	#115.#951;	//  scala/collection/mutable/BufferLike$class.appendAll:(Lscala/collection/mutable/BufferLike;Lscala/collection/Iterator;)V
const #953 = NameAndType	#950:#943;//  appendAll:(Lscala/collection/mutable/BufferLike;Lscala/collection/Traversable;)V
const #954 = Method	#115.#953;	//  scala/collection/mutable/BufferLike$class.appendAll:(Lscala/collection/mutable/BufferLike;Lscala/collection/Traversable;)V
const #955 = Asciz	append;
const #956 = NameAndType	#955:#947;//  append:(Lscala/collection/mutable/BufferLike;Lscala/collection/Seq;)V
const #957 = Method	#115.#956;	//  scala/collection/mutable/BufferLike$class.append:(Lscala/collection/mutable/BufferLike;Lscala/collection/Seq;)V
const #958 = Asciz	$plus$plus$eq$colon;
const #959 = NameAndType	#958:#889;//  $plus$plus$eq$colon:(Lscala/collection/mutable/BufferLike;Lscala/collection/Iterator;)Lscala/collection/mutable/BufferLike;
const #960 = Method	#115.#959;	//  scala/collection/mutable/BufferLike$class.$plus$plus$eq$colon:(Lscala/collection/mutable/BufferLike;Lscala/collection/Iterator;)Lscala/collection/mutable/BufferLike;
const #961 = NameAndType	#958:#895;//  $plus$plus$eq$colon:(Lscala/collection/mutable/BufferLike;Lscala/collection/Traversable;)Lscala/collection/mutable/BufferLike;
const #962 = Method	#115.#961;	//  scala/collection/mutable/BufferLike$class.$plus$plus$eq$colon:(Lscala/collection/mutable/BufferLike;Lscala/collection/Traversable;)Lscala/collection/mutable/BufferLike;
const #963 = Asciz	mapResult;
const #964 = Asciz	(Lscala/Function1;)Lscala/collection/mutable/Builder;;
const #965 = Asciz	(Lscala/collection/mutable/Builder;Lscala/Function1;)Lscala/collection/mutable/Builder;;
const #966 = NameAndType	#963:#965;//  mapResult:(Lscala/collection/mutable/Builder;Lscala/Function1;)Lscala/collection/mutable/Builder;
const #967 = Method	#125.#966;	//  scala/collection/mutable/Builder$class.mapResult:(Lscala/collection/mutable/Builder;Lscala/Function1;)Lscala/collection/mutable/Builder;
const #968 = Asciz	sizeHint;
const #969 = Asciz	(Lscala/collection/mutable/Builder;I)V;
const #970 = NameAndType	#968:#969;//  sizeHint:(Lscala/collection/mutable/Builder;I)V
const #971 = Method	#125.#970;	//  scala/collection/mutable/Builder$class.sizeHint:(Lscala/collection/mutable/Builder;I)V
const #972 = Asciz	lastOption;
const #973 = Asciz	(Lscala/collection/generic/TraversableForwarder;)Lscala/Option;;
const #974 = NameAndType	#972:#973;//  lastOption:(Lscala/collection/generic/TraversableForwarder;)Lscala/Option;
const #975 = Method	#130.#974;	//  scala/collection/generic/TraversableForwarder$class.lastOption:(Lscala/collection/generic/TraversableForwarder;)Lscala/Option;
const #976 = Asciz	last;
const #977 = Asciz	(Lscala/collection/generic/TraversableForwarder;)Ljava/lang/Object;;
const #978 = NameAndType	#976:#977;//  last:(Lscala/collection/generic/TraversableForwarder;)Ljava/lang/Object;
const #979 = Method	#130.#978;	//  scala/collection/generic/TraversableForwarder$class.last:(Lscala/collection/generic/TraversableForwarder;)Ljava/lang/Object;
const #980 = NameAndType	#350:#977;//  head:(Lscala/collection/generic/TraversableForwarder;)Ljava/lang/Object;
const #981 = Method	#130.#980;	//  scala/collection/generic/TraversableForwarder$class.head:(Lscala/collection/generic/TraversableForwarder;)Ljava/lang/Object;
const #982 = Asciz	(Lscala/collection/mutable/StringBuilder;Ljava/lang/String;Ljava/lang/String;Ljava/lang/String;)Lscala/collection/mutable/StringBuilder;;
const #983 = Asciz	(Lscala/collection/generic/TraversableForwarder;Lscala/collection/mutable/StringBuilder;Ljava/lang/String;Ljava/lang/String;Ljava/lang/String;)Lscala/collection/mutable/StringBuilder;;
const #984 = NameAndType	#476:#983;//  addString:(Lscala/collection/generic/TraversableForwarder;Lscala/collection/mutable/StringBuilder;Ljava/lang/String;Ljava/lang/String;Ljava/lang/String;)Lscala/collection/mutable/StringBuilder;
const #985 = Method	#130.#984;	//  scala/collection/generic/TraversableForwarder$class.addString:(Lscala/collection/generic/TraversableForwarder;Lscala/collection/mutable/StringBuilder;Ljava/lang/String;Ljava/lang/String;Ljava/lang/String;)Lscala/collection/mutable/StringBuilder;
const #986 = Asciz	(Ljava/lang/String;Ljava/lang/String;Ljava/lang/String;)Ljava/lang/String;;
const #987 = Asciz	(Lscala/collection/generic/TraversableForwarder;Ljava/lang/String;Ljava/lang/String;Ljava/lang/String;)Ljava/lang/String;;
const #988 = NameAndType	#489:#987;//  mkString:(Lscala/collection/generic/TraversableForwarder;Ljava/lang/String;Ljava/lang/String;Ljava/lang/String;)Ljava/lang/String;
const #989 = Method	#130.#988;	//  scala/collection/generic/TraversableForwarder$class.mkString:(Lscala/collection/generic/TraversableForwarder;Ljava/lang/String;Ljava/lang/String;Ljava/lang/String;)Ljava/lang/String;
const #990 = Asciz	toStream;
const #991 = Asciz	()Lscala/collection/immutable/Stream;;
const #992 = Asciz	(Lscala/collection/generic/TraversableForwarder;)Lscala/collection/immutable/Stream;;
const #993 = NameAndType	#990:#992;//  toStream:(Lscala/collection/generic/TraversableForwarder;)Lscala/collection/immutable/Stream;
const #994 = Method	#130.#993;	//  scala/collection/generic/TraversableForwarder$class.toStream:(Lscala/collection/generic/TraversableForwarder;)Lscala/collection/immutable/Stream;
const #995 = Asciz	toSeq;
const #996 = Asciz	(Lscala/collection/generic/TraversableForwarder;)Lscala/collection/Seq;;
const #997 = NameAndType	#995:#996;//  toSeq:(Lscala/collection/generic/TraversableForwarder;)Lscala/collection/Seq;
const #998 = Method	#130.#997;	//  scala/collection/generic/TraversableForwarder$class.toSeq:(Lscala/collection/generic/TraversableForwarder;)Lscala/collection/Seq;
const #999 = Asciz	toArray;
const #1000 = Asciz	(Lscala/reflect/ClassManifest;)Ljava/lang/Object;;
const #1001 = Asciz	(Lscala/collection/generic/TraversableForwarder;Lscala/reflect/ClassManifest;)Ljava/lang/Object;;
const #1002 = NameAndType	#999:#1001;//  toArray:(Lscala/collection/generic/TraversableForwarder;Lscala/reflect/ClassManifest;)Ljava/lang/Object;
const #1003 = Method	#130.#1002;	//  scala/collection/generic/TraversableForwarder$class.toArray:(Lscala/collection/generic/TraversableForwarder;Lscala/reflect/ClassManifest;)Ljava/lang/Object;
const #1004 = Asciz	evidence$1;
const #1005 = Asciz	Lscala/reflect/ClassManifest;;
const #1006 = Asciz	(Lscala/collection/generic/TraversableForwarder;Ljava/lang/Object;II)V;
const #1007 = NameAndType	#507:#1006;//  copyToArray:(Lscala/collection/generic/TraversableForwarder;Ljava/lang/Object;II)V
const #1008 = Method	#130.#1007;	//  scala/collection/generic/TraversableForwarder$class.copyToArray:(Lscala/collection/generic/TraversableForwarder;Ljava/lang/Object;II)V
const #1009 = Asciz	copyToBuffer;
const #1010 = Asciz	(Lscala/collection/generic/TraversableForwarder;Lscala/collection/mutable/Buffer;)V;
const #1011 = NameAndType	#1009:#1010;//  copyToBuffer:(Lscala/collection/generic/TraversableForwarder;Lscala/collection/mutable/Buffer;)V
const #1012 = Method	#130.#1011;	//  scala/collection/generic/TraversableForwarder$class.copyToBuffer:(Lscala/collection/generic/TraversableForwarder;Lscala/collection/mutable/Buffer;)V
const #1013 = Asciz	dest;
const #1014 = Asciz	Lscala/collection/mutable/Buffer;;
const #1015 = Asciz	reduceRightOption;
const #1016 = Asciz	(Lscala/Function2;)Lscala/Option;;
const #1017 = Asciz	(Lscala/collection/generic/TraversableForwarder;Lscala/Function2;)Lscala/Option;;
const #1018 = NameAndType	#1015:#1017;//  reduceRightOption:(Lscala/collection/generic/TraversableForwarder;Lscala/Function2;)Lscala/Option;
const #1019 = Method	#130.#1018;	//  scala/collection/generic/TraversableForwarder$class.reduceRightOption:(Lscala/collection/generic/TraversableForwarder;Lscala/Function2;)Lscala/Option;
const #1020 = Asciz	reduceLeftOption;
const #1021 = NameAndType	#1020:#1017;//  reduceLeftOption:(Lscala/collection/generic/TraversableForwarder;Lscala/Function2;)Lscala/Option;
const #1022 = Method	#130.#1021;	//  scala/collection/generic/TraversableForwarder$class.reduceLeftOption:(Lscala/collection/generic/TraversableForwarder;Lscala/Function2;)Lscala/Option;
const #1023 = Asciz	reduceRight;
const #1024 = Asciz	(Lscala/collection/generic/TraversableForwarder;Lscala/Function2;)Ljava/lang/Object;;
const #1025 = NameAndType	#1023:#1024;//  reduceRight:(Lscala/collection/generic/TraversableForwarder;Lscala/Function2;)Ljava/lang/Object;
const #1026 = Method	#130.#1025;	//  scala/collection/generic/TraversableForwarder$class.reduceRight:(Lscala/collection/generic/TraversableForwarder;Lscala/Function2;)Ljava/lang/Object;
const #1027 = Asciz	reduceLeft;
const #1028 = NameAndType	#1027:#1024;//  reduceLeft:(Lscala/collection/generic/TraversableForwarder;Lscala/Function2;)Ljava/lang/Object;
const #1029 = Method	#130.#1028;	//  scala/collection/generic/TraversableForwarder$class.reduceLeft:(Lscala/collection/generic/TraversableForwarder;Lscala/Function2;)Ljava/lang/Object;
const #1030 = Asciz	foldRight;
const #1031 = Asciz	(Lscala/collection/generic/TraversableForwarder;Ljava/lang/Object;Lscala/Function2;)Ljava/lang/Object;;
const #1032 = NameAndType	#1030:#1031;//  foldRight:(Lscala/collection/generic/TraversableForwarder;Ljava/lang/Object;Lscala/Function2;)Ljava/lang/Object;
const #1033 = Method	#130.#1032;	//  scala/collection/generic/TraversableForwarder$class.foldRight:(Lscala/collection/generic/TraversableForwarder;Ljava/lang/Object;Lscala/Function2;)Ljava/lang/Object;
const #1034 = Asciz	foldLeft;
const #1035 = NameAndType	#1034:#1031;//  foldLeft:(Lscala/collection/generic/TraversableForwarder;Ljava/lang/Object;Lscala/Function2;)Ljava/lang/Object;
const #1036 = Method	#130.#1035;	//  scala/collection/generic/TraversableForwarder$class.foldLeft:(Lscala/collection/generic/TraversableForwarder;Ljava/lang/Object;Lscala/Function2;)Ljava/lang/Object;
const #1037 = Asciz	find;
const #1038 = Asciz	(Lscala/Function1;)Lscala/Option;;
const #1039 = Asciz	(Lscala/collection/generic/TraversableForwarder;Lscala/Function1;)Lscala/Option;;
const #1040 = NameAndType	#1037:#1039;//  find:(Lscala/collection/generic/TraversableForwarder;Lscala/Function1;)Lscala/Option;
const #1041 = Method	#130.#1040;	//  scala/collection/generic/TraversableForwarder$class.find:(Lscala/collection/generic/TraversableForwarder;Lscala/Function1;)Lscala/Option;
const #1042 = Asciz	(Lscala/collection/generic/TraversableForwarder;Lscala/Function1;)I;
const #1043 = NameAndType	#427:#1042;//  count:(Lscala/collection/generic/TraversableForwarder;Lscala/Function1;)I
const #1044 = Method	#130.#1043;	//  scala/collection/generic/TraversableForwarder$class.count:(Lscala/collection/generic/TraversableForwarder;Lscala/Function1;)I
const #1045 = Asciz	exists;
const #1046 = Asciz	(Lscala/Function1;)Z;
const #1047 = Asciz	(Lscala/collection/generic/TraversableForwarder;Lscala/Function1;)Z;
const #1048 = NameAndType	#1045:#1047;//  exists:(Lscala/collection/generic/TraversableForwarder;Lscala/Function1;)Z
const #1049 = Method	#130.#1048;	//  scala/collection/generic/TraversableForwarder$class.exists:(Lscala/collection/generic/TraversableForwarder;Lscala/Function1;)Z
const #1050 = Asciz	forall;
const #1051 = NameAndType	#1050:#1047;//  forall:(Lscala/collection/generic/TraversableForwarder;Lscala/Function1;)Z
const #1052 = Method	#130.#1051;	//  scala/collection/generic/TraversableForwarder$class.forall:(Lscala/collection/generic/TraversableForwarder;Lscala/Function1;)Z
const #1053 = Asciz	foreach;
const #1054 = Asciz	(Lscala/collection/generic/TraversableForwarder;Lscala/Function1;)V;
const #1055 = NameAndType	#1053:#1054;//  foreach:(Lscala/collection/generic/TraversableForwarder;Lscala/Function1;)V
const #1056 = Method	#130.#1055;	//  scala/collection/generic/TraversableForwarder$class.foreach:(Lscala/collection/generic/TraversableForwarder;Lscala/Function1;)V
const #1057 = Asciz	hasDefiniteSize;
const #1058 = Asciz	(Lscala/collection/generic/TraversableForwarder;)Z;
const #1059 = NameAndType	#1057:#1058;//  hasDefiniteSize:(Lscala/collection/generic/TraversableForwarder;)Z
const #1060 = Method	#130.#1059;	//  scala/collection/generic/TraversableForwarder$class.hasDefiniteSize:(Lscala/collection/generic/TraversableForwarder;)Z
const #1061 = Asciz	nonEmpty;
const #1062 = NameAndType	#1061:#1058;//  nonEmpty:(Lscala/collection/generic/TraversableForwarder;)Z
const #1063 = Method	#130.#1062;	//  scala/collection/generic/TraversableForwarder$class.nonEmpty:(Lscala/collection/generic/TraversableForwarder;)Z
const #1064 = NameAndType	#373:#1058;//  isEmpty:(Lscala/collection/generic/TraversableForwarder;)Z
const #1065 = Method	#130.#1064;	//  scala/collection/generic/TraversableForwarder$class.isEmpty:(Lscala/collection/generic/TraversableForwarder;)Z
const #1066 = Asciz	sameElements;
const #1067 = Asciz	(Lscala/collection/Iterable;)Z;
const #1068 = Asciz	(Lscala/collection/generic/IterableForwarder;Lscala/collection/Iterable;)Z;
const #1069 = NameAndType	#1066:#1068;//  sameElements:(Lscala/collection/generic/IterableForwarder;Lscala/collection/Iterable;)Z
const #1070 = Method	#135.#1069;	//  scala/collection/generic/IterableForwarder$class.sameElements:(Lscala/collection/generic/IterableForwarder;Lscala/collection/Iterable;)Z
const #1071 = Asciz	indices;
const #1072 = Asciz	()Lscala/collection/immutable/Range;;
const #1073 = Asciz	(Lscala/collection/generic/SeqForwarder;)Lscala/collection/immutable/Range;;
const #1074 = NameAndType	#1071:#1073;//  indices:(Lscala/collection/generic/SeqForwarder;)Lscala/collection/immutable/Range;
const #1075 = Method	#140.#1074;	//  scala/collection/generic/SeqForwarder$class.indices:(Lscala/collection/generic/SeqForwarder;)Lscala/collection/immutable/Range;
const #1076 = Asciz	contains;
const #1077 = Asciz	(Lscala/collection/generic/SeqForwarder;Ljava/lang/Object;)Z;
const #1078 = NameAndType	#1076:#1077;//  contains:(Lscala/collection/generic/SeqForwarder;Ljava/lang/Object;)Z
const #1079 = Method	#140.#1078;	//  scala/collection/generic/SeqForwarder$class.contains:(Lscala/collection/generic/SeqForwarder;Ljava/lang/Object;)Z
const #1080 = Asciz	(Lscala/collection/generic/SeqForwarder;Lscala/collection/Seq;)I;
const #1081 = NameAndType	#813:#1080;//  indexOfSlice:(Lscala/collection/generic/SeqForwarder;Lscala/collection/Seq;)I
const #1082 = Method	#140.#1081;	//  scala/collection/generic/SeqForwarder$class.indexOfSlice:(Lscala/collection/generic/SeqForwarder;Lscala/collection/Seq;)I
const #1083 = Asciz	endsWith;
const #1084 = Asciz	(Lscala/collection/generic/SeqForwarder;Lscala/collection/Seq;)Z;
const #1085 = NameAndType	#1083:#1084;//  endsWith:(Lscala/collection/generic/SeqForwarder;Lscala/collection/Seq;)Z
const #1086 = Method	#140.#1085;	//  scala/collection/generic/SeqForwarder$class.endsWith:(Lscala/collection/generic/SeqForwarder;Lscala/collection/Seq;)Z
const #1087 = Asciz	(Lscala/collection/Seq;I)Z;
const #1088 = Asciz	(Lscala/collection/generic/SeqForwarder;Lscala/collection/Seq;I)Z;
const #1089 = NameAndType	#816:#1088;//  startsWith:(Lscala/collection/generic/SeqForwarder;Lscala/collection/Seq;I)Z
const #1090 = Method	#140.#1089;	//  scala/collection/generic/SeqForwarder$class.startsWith:(Lscala/collection/generic/SeqForwarder;Lscala/collection/Seq;I)Z
const #1091 = Asciz	offset;
const #1092 = Asciz	reverseIterator;
const #1093 = Asciz	(Lscala/collection/generic/SeqForwarder;)Lscala/collection/Iterator;;
const #1094 = NameAndType	#1092:#1093;//  reverseIterator:(Lscala/collection/generic/SeqForwarder;)Lscala/collection/Iterator;
const #1095 = Method	#140.#1094;	//  scala/collection/generic/SeqForwarder$class.reverseIterator:(Lscala/collection/generic/SeqForwarder;)Lscala/collection/Iterator;
const #1096 = Asciz	(Lscala/collection/generic/SeqForwarder;Ljava/lang/Object;I)I;
const #1097 = NameAndType	#844:#1096;//  indexOf:(Lscala/collection/generic/SeqForwarder;Ljava/lang/Object;I)I
const #1098 = Method	#140.#1097;	//  scala/collection/generic/SeqForwarder$class.indexOf:(Lscala/collection/generic/SeqForwarder;Ljava/lang/Object;I)I
const #1099 = Asciz	(Lscala/collection/generic/SeqForwarder;Lscala/Function1;I)I;
const #1100 = NameAndType	#850:#1099;//  indexWhere:(Lscala/collection/generic/SeqForwarder;Lscala/Function1;I)I
const #1101 = Method	#140.#1100;	//  scala/collection/generic/SeqForwarder$class.indexWhere:(Lscala/collection/generic/SeqForwarder;Lscala/Function1;I)I
const #1102 = Asciz	prefixLength;
const #1103 = Asciz	(Lscala/collection/generic/SeqForwarder;Lscala/Function1;)I;
const #1104 = NameAndType	#1102:#1103;//  prefixLength:(Lscala/collection/generic/SeqForwarder;Lscala/Function1;)I
const #1105 = Method	#140.#1104;	//  scala/collection/generic/SeqForwarder$class.prefixLength:(Lscala/collection/generic/SeqForwarder;Lscala/Function1;)I
const #1106 = Asciz	segmentLength;
const #1107 = NameAndType	#1106:#1099;//  segmentLength:(Lscala/collection/generic/SeqForwarder;Lscala/Function1;I)I
const #1108 = Method	#140.#1107;	//  scala/collection/generic/SeqForwarder$class.segmentLength:(Lscala/collection/generic/SeqForwarder;Lscala/Function1;I)I
const #1109 = Asciz	lengthCompare;
const #1110 = Asciz	(Lscala/collection/generic/SeqForwarder;I)I;
const #1111 = NameAndType	#1109:#1110;//  lengthCompare:(Lscala/collection/generic/SeqForwarder;I)I
const #1112 = Method	#140.#1111;	//  scala/collection/generic/SeqForwarder$class.lengthCompare:(Lscala/collection/generic/SeqForwarder;I)I
const #1113 = Asciz	l;
const #1114 = Asciz	(Lscala/collection/generic/SeqForwarder;I)Z;
const #1115 = NameAndType	#214:#1114;//  isDefinedAt:(Lscala/collection/generic/SeqForwarder;I)Z
const #1116 = Method	#140.#1115;	//  scala/collection/generic/SeqForwarder$class.isDefinedAt:(Lscala/collection/generic/SeqForwarder;I)Z
const #1117 = Asciz	<A:Ljava/lang/Object;>Ljava/lang/Object;Lscala/collection/mutable/Buffer<TA;>;Lscala/collection/generic/GenericTraversableTemplate<TA;Lscala/collection/mutable/ListBuffer;>;Lscala/collection/mutable/BufferLike<TA;Lscala/collection/mutable/ListBuffer<TA;>;>;Lscala/collection/mutable/Builder<TA;Lscala/collection/immutable/List<TA;>;>;Lscala/collection/generic/SeqForwarder<TA;>;Lscala/ScalaObject;;
const #1118 = Asciz	ScalaSig;
const #1119 = Asciz	InnerClasses;
const #1120 = Asciz	$anon$1;
const #1121 = Asciz	scala/collection/TraversableLike$WithFilter;
const #1122 = class	#1121;	//  scala/collection/TraversableLike$WithFilter
const #1123 = Asciz	WithFilter;
const #1124 = Asciz	scala/collection/mutable/Buffer;
const #1125 = class	#1124;	//  scala/collection/mutable/Buffer
const #1126 = Asciz	scala/collection/generic/GenericTraversableTemplate;
const #1127 = class	#1126;	//  scala/collection/generic/GenericTraversableTemplate
const #1128 = Asciz	scala/collection/mutable/Builder;
const #1129 = class	#1128;	//  scala/collection/mutable/Builder
const #1130 = Asciz	scala/ScalaObject;
const #1131 = class	#1130;	//  scala/ScalaObject
const #1132 = Asciz	java/io/Serializable;
const #1133 = class	#1132;	//  java/io/Serializable

{
public static final long serialVersionUID;

public static {};
  Code:
   Stack=2, Locals=0, Args_size=0
   0:	ldc2_w	#8; //long 3419063961353022661l
   3:	putstatic	#13; //Field serialVersionUID:J
   6:	return

public scala.collection.mutable.ListBuffer();
  Code:
   Stack=2, Locals=1, Args_size=1
   0:	aload_0
   1:	invokespecial	#27; //Method java/lang/Object."<init>":()V
   4:	aload_0
   5:	invokestatic	#33; //Method scala/collection/TraversableLike$class.$init$:(Lscala/collection/TraversableLike;)V
   8:	aload_0
   9:	invokestatic	#38; //Method scala/collection/generic/GenericTraversableTemplate$class.$init$:(Lscala/collection/generic/GenericTraversableTemplate;)V
   12:	aload_0
   13:	invokestatic	#43; //Method scala/collection/Traversable$class.$init$:(Lscala/collection/Traversable;)V
   16:	aload_0
   17:	invokestatic	#48; //Method scala/collection/mutable/Traversable$class.$init$:(Lscala/collection/mutable/Traversable;)V
   20:	aload_0
   21:	invokestatic	#53; //Method scala/collection/IterableLike$class.$init$:(Lscala/collection/IterableLike;)V
   24:	aload_0
   25:	invokestatic	#58; //Method scala/collection/Iterable$class.$init$:(Lscala/collection/Iterable;)V
   28:	aload_0
   29:	invokestatic	#63; //Method scala/collection/mutable/Iterable$class.$init$:(Lscala/collection/mutable/Iterable;)V
   32:	aload_0
   33:	invokestatic	#68; //Method scala/Function1$class.$init$:(Lscala/Function1;)V
   36:	aload_0
   37:	invokestatic	#73; //Method scala/PartialFunction$class.$init$:(Lscala/PartialFunction;)V
   40:	aload_0
   41:	invokestatic	#78; //Method scala/collection/SeqLike$class.$init$:(Lscala/collection/SeqLike;)V
   44:	aload_0
   45:	invokestatic	#83; //Method scala/collection/Seq$class.$init$:(Lscala/collection/Seq;)V
   48:	aload_0
   49:	invokestatic	#88; //Method scala/collection/mutable/Seq$class.$init$:(Lscala/collection/mutable/Seq;)V
   52:	aload_0
   53:	invokestatic	#93; //Method scala/collection/generic/Growable$class.$init$:(Lscala/collection/generic/Growable;)V
   56:	aload_0
   57:	invokestatic	#98; //Method scala/collection/generic/Shrinkable$class.$init$:(Lscala/collection/generic/Shrinkable;)V
   60:	aload_0
   61:	invokestatic	#103; //Method scala/collection/generic/Addable$class.$init$:(Lscala/collection/generic/Addable;)V
   64:	aload_0
   65:	invokestatic	#108; //Method scala/collection/generic/Subtractable$class.$init$:(Lscala/collection/generic/Subtractable;)V
   68:	aload_0
   69:	invokestatic	#113; //Method scala/collection/mutable/Cloneable$class.$init$:(Lscala/collection/mutable/Cloneable;)V
   72:	aload_0
   73:	invokestatic	#118; //Method scala/collection/mutable/BufferLike$class.$init$:(Lscala/collection/mutable/BufferLike;)V
   76:	aload_0
   77:	invokestatic	#123; //Method scala/collection/mutable/Buffer$class.$init$:(Lscala/collection/mutable/Buffer;)V
   80:	aload_0
   81:	invokestatic	#128; //Method scala/collection/mutable/Builder$class.$init$:(Lscala/collection/mutable/Builder;)V
   84:	aload_0
   85:	invokestatic	#133; //Method scala/collection/generic/TraversableForwarder$class.$init$:(Lscala/collection/generic/TraversableForwarder;)V
   88:	aload_0
   89:	invokestatic	#138; //Method scala/collection/generic/IterableForwarder$class.$init$:(Lscala/collection/generic/IterableForwarder;)V
   92:	aload_0
   93:	invokestatic	#143; //Method scala/collection/generic/SeqForwarder$class.$init$:(Lscala/collection/generic/SeqForwarder;)V
   96:	aload_0
   97:	getstatic	#149; //Field scala/collection/immutable/Nil$.MODULE$:Lscala/collection/immutable/Nil$;
   100:	putfield	#151; //Field scala$collection$mutable$ListBuffer$$start:Lscala/collection/immutable/List;
   103:	aload_0
   104:	iconst_0
   105:	putfield	#153; //Field exported:Z
   108:	aload_0
   109:	iconst_0
   110:	putfield	#155; //Field len:I
   113:	return
  LineNumberTable: 
   line 28: 0
   line 38: 96
   line 40: 103
   line 41: 108

  Signature: length = 0x2
   00 04 

public scala.collection.Seq underlying();
  Code:
   Stack=1, Locals=1, Args_size=1
   0:	aload_0
   1:	invokevirtual	#161; //Method underlying:()Lscala/collection/immutable/Seq;
   4:	areturn
  LineNumberTable: 
   line 27: 0


public scala.collection.Iterable underlying();
  Code:
   Stack=1, Locals=1, Args_size=1
   0:	aload_0
   1:	invokevirtual	#161; //Method underlying:()Lscala/collection/immutable/Seq;
   4:	areturn
  LineNumberTable: 
   line 27: 0


public scala.collection.Traversable underlying();
  Code:
   Stack=1, Locals=1, Args_size=1
   0:	aload_0
   1:	invokevirtual	#161; //Method underlying:()Lscala/collection/immutable/Seq;
   4:	areturn
  LineNumberTable: 
   line 27: 0


public java.lang.Object apply(java.lang.Object);
  Code:
   Stack=2, Locals=2, Args_size=2
   0:	aload_0
   1:	aload_1
   2:	invokestatic	#171; //Method scala/runtime/BoxesRunTime.unboxToInt:(Ljava/lang/Object;)I
   5:	invokevirtual	#174; //Method apply:(I)Ljava/lang/Object;
   8:	areturn
  LineNumberTable: 
   line 27: 0

  LocalVariableTable: 
   Start  Length  Slot  Name   Signature
   0      9      0    this       Lscala/collection/mutable/ListBuffer;
   0      9      1    v1       Ljava/lang/Object;


public scala.collection.mutable.Builder $plus$eq(java.lang.Object);
  Code:
   Stack=2, Locals=2, Args_size=2
   0:	aload_0
   1:	aload_1
   2:	invokevirtual	#184; //Method $plus$eq:(Ljava/lang/Object;)Lscala/collection/mutable/ListBuffer;
   5:	areturn
  LineNumberTable: 
   line 27: 0

  LocalVariableTable: 
   Start  Length  Slot  Name   Signature
   0      6      0    this       Lscala/collection/mutable/ListBuffer;
   0      6      1    elem       Ljava/lang/Object;


public scala.collection.mutable.BufferLike $plus$eq(java.lang.Object);
  Code:
   Stack=2, Locals=2, Args_size=2
   0:	aload_0
   1:	aload_1
   2:	invokevirtual	#184; //Method $plus$eq:(Ljava/lang/Object;)Lscala/collection/mutable/ListBuffer;
   5:	areturn
  LineNumberTable: 
   line 27: 0

  LocalVariableTable: 
   Start  Length  Slot  Name   Signature
   0      6      0    this       Lscala/collection/mutable/ListBuffer;
   0      6      1    elem       Ljava/lang/Object;


public scala.collection.generic.Growable $plus$eq(java.lang.Object);
  Code:
   Stack=2, Locals=2, Args_size=2
   0:	aload_0
   1:	aload_1
   2:	invokevirtual	#184; //Method $plus$eq:(Ljava/lang/Object;)Lscala/collection/mutable/ListBuffer;
   5:	areturn
  LineNumberTable: 
   line 27: 0

  LocalVariableTable: 
   Start  Length  Slot  Name   Signature
   0      6      0    this       Lscala/collection/mutable/ListBuffer;
   0      6      1    elem       Ljava/lang/Object;


public scala.collection.mutable.BufferLike $plus$eq$colon(java.lang.Object);
  Code:
   Stack=2, Locals=2, Args_size=2
   0:	aload_0
   1:	aload_1
   2:	invokevirtual	#190; //Method $plus$eq$colon:(Ljava/lang/Object;)Lscala/collection/mutable/ListBuffer;
   5:	areturn
  LineNumberTable: 
   line 27: 0

  LocalVariableTable: 
   Start  Length  Slot  Name   Signature
   0      6      0    this       Lscala/collection/mutable/ListBuffer;
   0      6      1    elem       Ljava/lang/Object;


public java.lang.Object result();
  Code:
   Stack=1, Locals=1, Args_size=1
   0:	aload_0
   1:	invokevirtual	#195; //Method result:()Lscala/collection/immutable/List;
   4:	areturn
  LineNumberTable: 
   line 27: 0


public scala.collection.mutable.BufferLike $minus$eq(java.lang.Object);
  Code:
   Stack=2, Locals=2, Args_size=2
   0:	aload_0
   1:	aload_1
   2:	invokevirtual	#198; //Method $minus$eq:(Ljava/lang/Object;)Lscala/collection/mutable/ListBuffer;
   5:	areturn
  LineNumberTable: 
   line 27: 0

  LocalVariableTable: 
   Start  Length  Slot  Name   Signature
   0      6      0    this       Lscala/collection/mutable/ListBuffer;
   0      6      1    x       Ljava/lang/Object;


public scala.collection.generic.Shrinkable $minus$eq(java.lang.Object);
  Code:
   Stack=2, Locals=2, Args_size=2
   0:	aload_0
   1:	aload_1
   2:	invokevirtual	#198; //Method $minus$eq:(Ljava/lang/Object;)Lscala/collection/mutable/ListBuffer;
   5:	areturn
  LineNumberTable: 
   line 27: 0

  LocalVariableTable: 
   Start  Length  Slot  Name   Signature
   0      6      0    this       Lscala/collection/mutable/ListBuffer;
   0      6      1    elem       Ljava/lang/Object;


public scala.collection.Iterator iterator();
  Code:
   Stack=1, Locals=1, Args_size=1
   0:	aload_0
   1:	invokevirtual	#204; //Method iterator:()Ljava/lang/Object;
   4:	checkcast	#206; //class scala/collection/Iterator
   7:	areturn
  LineNumberTable: 
   line 27: 0


public scala.collection.Seq readOnly();
  Code:
   Stack=1, Locals=1, Args_size=1
   0:	aload_0
   1:	invokevirtual	#209; //Method readOnly:()Lscala/collection/immutable/List;
   4:	areturn
  LineNumberTable: 
   line 27: 0


public java.lang.Object clone();
  Code:
   Stack=1, Locals=1, Args_size=1
   0:	aload_0
   1:	invokevirtual	#213; //Method clone:()Lscala/collection/mutable/ListBuffer;
   4:	areturn
  LineNumberTable: 
   line 27: 0


public boolean isDefinedAt(java.lang.Object);
  Code:
   Stack=2, Locals=2, Args_size=2
   0:	aload_0
   1:	aload_1
   2:	invokestatic	#171; //Method scala/runtime/BoxesRunTime.unboxToInt:(Ljava/lang/Object;)I
   5:	invokeinterface	#220,  2; //InterfaceMethod scala/collection/generic/SeqForwarder.isDefinedAt:(I)Z
   10:	ireturn
  LineNumberTable: 
   line 27: 0

  LocalVariableTable: 
   Start  Length  Slot  Name   Signature
   0      11      0    this       Lscala/collection/mutable/ListBuffer;
   0      11      1    x       Ljava/lang/Object;


public scala.collection.generic.Addable $plus(java.lang.Object);
  Code:
   Stack=2, Locals=2, Args_size=2
   0:	aload_0
   1:	aload_1
   2:	invokeinterface	#226,  2; //InterfaceMethod scala/collection/mutable/BufferLike.$plus:(Ljava/lang/Object;)Lscala/collection/mutable/BufferLike;
   7:	areturn
  LineNumberTable: 
   line 27: 0

  LocalVariableTable: 
   Start  Length  Slot  Name   Signature
   0      8      0    this       Lscala/collection/mutable/ListBuffer;
   0      8      1    elem       Ljava/lang/Object;


public scala.collection.generic.Addable $plus(java.lang.Object, java.lang.Object, scala.collection.Seq);
  Code:
   Stack=4, Locals=4, Args_size=4
   0:	aload_0
   1:	aload_1
   2:	aload_2
   3:	aload_3
   4:	invokeinterface	#230,  4; //InterfaceMethod scala/collection/mutable/BufferLike.$plus:(Ljava/lang/Object;Ljava/lang/Object;Lscala/collection/Seq;)Lscala/collection/mutable/BufferLike;
   9:	areturn
  LineNumberTable: 
   line 27: 0

  LocalVariableTable: 
   Start  Length  Slot  Name   Signature
   0      10      0    this       Lscala/collection/mutable/ListBuffer;
   0      10      1    elem1       Ljava/lang/Object;
   0      10      2    elem2       Ljava/lang/Object;
   0      10      3    elems       Lscala/collection/Seq;


public scala.collection.generic.Addable $plus$plus(scala.collection.Traversable);
  Code:
   Stack=2, Locals=2, Args_size=2
   0:	aload_0
   1:	aload_1
   2:	invokeinterface	#239,  2; //InterfaceMethod scala/collection/mutable/BufferLike.$plus$plus:(Lscala/collection/Traversable;)Lscala/collection/mutable/BufferLike;
   7:	areturn
  LineNumberTable: 
   line 27: 0

  LocalVariableTable: 
   Start  Length  Slot  Name   Signature
   0      8      0    this       Lscala/collection/mutable/ListBuffer;
   0      8      1    elems       Lscala/collection/Traversable;


public scala.collection.generic.Addable $plus$plus(scala.collection.Iterator);
  Code:
   Stack=2, Locals=2, Args_size=2
   0:	aload_0
   1:	aload_1
   2:	invokeinterface	#244,  2; //InterfaceMethod scala/collection/mutable/BufferLike.$plus$plus:(Lscala/collection/Iterator;)Lscala/collection/mutable/BufferLike;
   7:	areturn
  LineNumberTable: 
   line 27: 0

  LocalVariableTable: 
   Start  Length  Slot  Name   Signature
   0      8      0    this       Lscala/collection/mutable/ListBuffer;
   0      8      1    iter       Lscala/collection/Iterator;


public scala.collection.generic.Subtractable $minus(java.lang.Object);
  Code:
   Stack=2, Locals=2, Args_size=2
   0:	aload_0
   1:	aload_1
   2:	invokeinterface	#250,  2; //InterfaceMethod scala/collection/mutable/BufferLike.$minus:(Ljava/lang/Object;)Lscala/collection/mutable/BufferLike;
   7:	areturn
  LineNumberTable: 
   line 27: 0

  LocalVariableTable: 
   Start  Length  Slot  Name   Signature
   0      8      0    this       Lscala/collection/mutable/ListBuffer;
   0      8      1    elem       Ljava/lang/Object;


public scala.collection.generic.Subtractable $minus(java.lang.Object, java.lang.Object, scala.collection.Seq);
  Code:
   Stack=4, Locals=4, Args_size=4
   0:	aload_0
   1:	aload_1
   2:	aload_2
   3:	aload_3
   4:	invokeinterface	#253,  4; //InterfaceMethod scala/collection/mutable/BufferLike.$minus:(Ljava/lang/Object;Ljava/lang/Object;Lscala/collection/Seq;)Lscala/collection/mutable/BufferLike;
   9:	areturn
  LineNumberTable: 
   line 27: 0

  LocalVariableTable: 
   Start  Length  Slot  Name   Signature
   0      10      0    this       Lscala/collection/mutable/ListBuffer;
   0      10      1    elem1       Ljava/lang/Object;
   0      10      2    elem2       Ljava/lang/Object;
   0      10      3    elems       Lscala/collection/Seq;


public scala.collection.generic.Subtractable $minus$minus(scala.collection.Traversable);
  Code:
   Stack=2, Locals=2, Args_size=2
   0:	aload_0
   1:	aload_1
   2:	invokeinterface	#257,  2; //InterfaceMethod scala/collection/mutable/BufferLike.$minus$minus:(Lscala/collection/Traversable;)Lscala/collection/mutable/BufferLike;
   7:	areturn
  LineNumberTable: 
   line 27: 0

  LocalVariableTable: 
   Start  Length  Slot  Name   Signature
   0      8      0    this       Lscala/collection/mutable/ListBuffer;
   0      8      1    elems       Lscala/collection/Traversable;


public scala.collection.generic.Subtractable $minus$minus(scala.collection.Iterator);
  Code:
   Stack=2, Locals=2, Args_size=2
   0:	aload_0
   1:	aload_1
   2:	invokeinterface	#260,  2; //InterfaceMethod scala/collection/mutable/BufferLike.$minus$minus:(Lscala/collection/Iterator;)Lscala/collection/mutable/BufferLike;
   7:	areturn
  LineNumberTable: 
   line 27: 0

  LocalVariableTable: 
   Start  Length  Slot  Name   Signature
   0      8      0    this       Lscala/collection/mutable/ListBuffer;
   0      8      1    iter       Lscala/collection/Iterator;


public scala.collection.Iterable thisCollection();
  Code:
   Stack=1, Locals=1, Args_size=1
   0:	aload_0
   1:	invokeinterface	#265,  1; //InterfaceMethod scala/collection/SeqLike.thisCollection:()Lscala/collection/Seq;
   6:	areturn
  LineNumberTable: 
   line 27: 0


public scala.collection.Traversable thisCollection();
  Code:
   Stack=1, Locals=1, Args_size=1
   0:	aload_0
   1:	invokeinterface	#265,  1; //InterfaceMethod scala/collection/SeqLike.thisCollection:()Lscala/collection/Seq;
   6:	areturn
  LineNumberTable: 
   line 27: 0


public scala.collection.Iterable toCollection(java.lang.Object);
  Code:
   Stack=2, Locals=2, Args_size=2
   0:	aload_0
   1:	aload_1
   2:	invokeinterface	#270,  2; //InterfaceMethod scala/collection/SeqLike.toCollection:(Ljava/lang/Object;)Lscala/collection/Seq;
   7:	areturn
  LineNumberTable: 
   line 27: 0

  LocalVariableTable: 
   Start  Length  Slot  Name   Signature
   0      8      0    this       Lscala/collection/mutable/ListBuffer;
   0      8      1    repr       Ljava/lang/Object;


public scala.collection.Traversable toCollection(java.lang.Object);
  Code:
   Stack=2, Locals=2, Args_size=2
   0:	aload_0
   1:	aload_1
   2:	invokeinterface	#270,  2; //InterfaceMethod scala/collection/SeqLike.toCollection:(Ljava/lang/Object;)Lscala/collection/Seq;
   7:	areturn
  LineNumberTable: 
   line 27: 0

  LocalVariableTable: 
   Start  Length  Slot  Name   Signature
   0      8      0    this       Lscala/collection/mutable/ListBuffer;
   0      8      1    repr       Ljava/lang/Object;


public scala.collection.IterableView view(int, int);
  Code:
   Stack=3, Locals=3, Args_size=3
   0:	aload_0
   1:	iload_1
   2:	iload_2
   3:	invokeinterface	#277,  3; //InterfaceMethod scala/collection/SeqLike.view:(II)Lscala/collection/SeqView;
   8:	areturn
  LineNumberTable: 
   line 27: 0

  LocalVariableTable: 
   Start  Length  Slot  Name   Signature
   0      9      0    this       Lscala/collection/mutable/ListBuffer;
   0      9      1    from       I
   0      9      2    until       I


public scala.collection.TraversableView view(int, int);
  Code:
   Stack=3, Locals=3, Args_size=3
   0:	aload_0
   1:	iload_1
   2:	iload_2
   3:	invokeinterface	#277,  3; //InterfaceMethod scala/collection/SeqLike.view:(II)Lscala/collection/SeqView;
   8:	areturn
  LineNumberTable: 
   line 27: 0

  LocalVariableTable: 
   Start  Length  Slot  Name   Signature
   0      9      0    this       Lscala/collection/mutable/ListBuffer;
   0      9      1    from       I
   0      9      2    until       I


public scala.Function1 andThen(scala.Function1);
  Code:
   Stack=2, Locals=2, Args_size=2
   0:	aload_0
   1:	aload_1
   2:	invokeinterface	#287,  2; //InterfaceMethod scala/PartialFunction.andThen:(Lscala/Function1;)Lscala/PartialFunction;
   7:	areturn
  LineNumberTable: 
   line 27: 0

  LocalVariableTable: 
   Start  Length  Slot  Name   Signature
   0      8      0    this       Lscala/collection/mutable/ListBuffer;
   0      8      1    g       Lscala/Function1;


public scala.collection.generic.Subtractable repr();
  Code:
   Stack=1, Locals=1, Args_size=1
   0:	aload_0
   1:	invokeinterface	#294,  1; //InterfaceMethod scala/collection/TraversableLike.repr:()Ljava/lang/Object;
   6:	checkcast	#296; //class scala/collection/generic/Subtractable
   9:	areturn
  LineNumberTable: 
   line 27: 0


public scala.collection.generic.Addable repr();
  Code:
   Stack=1, Locals=1, Args_size=1
   0:	aload_0
   1:	invokeinterface	#294,  1; //InterfaceMethod scala/collection/TraversableLike.repr:()Ljava/lang/Object;
   6:	checkcast	#299; //class scala/collection/generic/Addable
   9:	areturn
  LineNumberTable: 
   line 27: 0


public java.lang.String stringPrefix();
  Code:
   Stack=1, Locals=1, Args_size=1
   0:	ldc_w	#303; //String ListBuffer
   3:	areturn
  LineNumberTable: 
   line 328: 0


public scala.collection.mutable.ListBuffer clone();
  Code:
   Stack=2, Locals=1, Args_size=1
   0:	new	#11; //class scala/collection/mutable/ListBuffer
   3:	dup
   4:	invokespecial	#304; //Method "<init>":()V
   7:	aload_0
   8:	invokeinterface	#310,  2; //InterfaceMethod scala/collection/generic/Growable.$plus$plus$eq:(Lscala/collection/Traversable;)Lscala/collection/generic/Growable;
   13:	checkcast	#11; //class scala/collection/mutable/ListBuffer
   16:	areturn
  LineNumberTable: 
   line 322: 0

  Signature: length = 0x2
   01 37 

public boolean equals(java.lang.Object);
  Code:
   Stack=3, Locals=3, Args_size=2
   0:	aload_1
   1:	instanceof	#11; //class scala/collection/mutable/ListBuffer
   4:	ifeq	44
   7:	aload_1
   8:	checkcast	#11; //class scala/collection/mutable/ListBuffer
   11:	astore_2
   12:	iconst_1
   13:	ifeq	32
   16:	aload_0
   17:	getfield	#151; //Field scala$collection$mutable$ListBuffer$$start:Lscala/collection/immutable/List;
   20:	aload_2
   21:	getfield	#151; //Field scala$collection$mutable$ListBuffer$$start:Lscala/collection/immutable/List;
   24:	invokeinterface	#314,  2; //InterfaceMethod scala/collection/SeqLike.equals:(Ljava/lang/Object;)Z
   29:	goto	53
   32:	new	#316; //class scala/MatchError
   35:	dup
   36:	aload_1
   37:	invokevirtual	#319; //Method java/lang/Object.toString:()Ljava/lang/String;
   40:	invokespecial	#322; //Method scala/MatchError."<init>":(Ljava/lang/String;)V
   43:	athrow
   44:	iconst_1
   45:	ifeq	54
   48:	aload_0
   49:	aload_1
   50:	invokestatic	#325; //Method scala/collection/SeqLike$class.equals:(Lscala/collection/SeqLike;Ljava/lang/Object;)Z
   53:	ireturn
   54:	new	#316; //class scala/MatchError
   57:	dup
   58:	aload_1
   59:	invokevirtual	#319; //Method java/lang/Object.toString:()Ljava/lang/String;
   62:	invokespecial	#322; //Method scala/MatchError."<init>":(Ljava/lang/String;)V
   65:	athrow
  LineNumberTable: 
   line 313: 0
   line 21: 12
   line 314: 16
   line 313: 32
   line 21: 44
   line 315: 48
   line 313: 53

  LocalVariableTable: 
   Start  Length  Slot  Name   Signature
   0      66      0    this       Lscala/collection/mutable/ListBuffer;
   0      66      1    that       Ljava/lang/Object;
   12      32      2    temp2       Lscala/collection/mutable/ListBuffer;


public scala.collection.immutable.List readOnly();
  Code:
   Stack=1, Locals=1, Args_size=1
   0:	aload_0
   1:	invokevirtual	#361; //Method scala$collection$mutable$ListBuffer$$start:()Lscala/collection/immutable/List;
   4:	areturn
  LineNumberTable: 
   line 298: 0

  Signature: length = 0x2
   01 6A 

public java.lang.Object iterator();
  Code:
   Stack=3, Locals=1, Args_size=1
   0:	new	#364; //class scala/collection/mutable/ListBuffer$$anon$1
   3:	dup
   4:	aload_0
   5:	invokespecial	#367; //Method scala/collection/mutable/ListBuffer$$anon$1."<init>":(Lscala/collection/mutable/ListBuffer;)V
   8:	areturn
  LineNumberTable: 
   line 285: 0


public scala.collection.mutable.ListBuffer $minus$eq(java.lang.Object);
  Code:
   Stack=3, Locals=8, Args_size=2
   0:	aload_0
   1:	invokespecial	#370; //Method exported:()Z
   4:	ifeq	11
   7:	aload_0
   8:	invokespecial	#372; //Method copy:()V
   11:	aload_0
   12:	getfield	#151; //Field scala$collection$mutable$ListBuffer$$start:Lscala/collection/immutable/List;
   15:	invokeinterface	#375,  1; //InterfaceMethod scala/collection/IterableLike.isEmpty:()Z
   20:	ifne	296
   23:	aload_0
   24:	getfield	#151; //Field scala$collection$mutable$ListBuffer$$start:Lscala/collection/immutable/List;
   27:	invokeinterface	#352,  1; //InterfaceMethod scala/collection/IterableLike.head:()Ljava/lang/Object;
   32:	astore_2
   33:	aload_2
   34:	aload_1
   35:	if_acmpne	42
   38:	iconst_1
   39:	goto	77
   42:	aload_2
   43:	ifnonnull	50
   46:	iconst_0
   47:	goto	77
   50:	aload_2
   51:	instanceof	#377; //class java/lang/Number
   54:	ifne	64
   57:	aload_2
   58:	instanceof	#379; //class java/lang/Character
   61:	ifeq	72
   64:	aload_2
   65:	aload_1
   66:	invokestatic	#383; //Method scala/runtime/BoxesRunTime.equals2:(Ljava/lang/Object;Ljava/lang/Object;)Z
   69:	goto	77
   72:	aload_2
   73:	aload_1
   74:	invokevirtual	#384; //Method java/lang/Object.equals:(Ljava/lang/Object;)Z
   77:	ifeq	109
   80:	aload_0
   81:	aload_0
   82:	getfield	#151; //Field scala$collection$mutable$ListBuffer$$start:Lscala/collection/immutable/List;
   85:	invokeinterface	#355,  1; //InterfaceMethod scala/collection/TraversableLike.tail:()Ljava/lang/Object;
   90:	checkcast	#357; //class scala/collection/immutable/List
   93:	invokespecial	#339; //Method scala$collection$mutable$ListBuffer$$start_$eq:(Lscala/collection/immutable/List;)V
   96:	aload_0
   97:	aload_0
   98:	invokespecial	#387; //Method len:()I
   101:	iconst_1
   102:	isub
   103:	invokespecial	#347; //Method len_$eq:(I)V
   106:	goto	296
   109:	aload_0
   110:	invokevirtual	#361; //Method scala$collection$mutable$ListBuffer$$start:()Lscala/collection/immutable/List;
   113:	astore	7
   115:	aload	7
   117:	invokeinterface	#355,  1; //InterfaceMethod scala/collection/TraversableLike.tail:()Ljava/lang/Object;
   122:	checkcast	#349; //class scala/collection/IterableLike
   125:	invokeinterface	#375,  1; //InterfaceMethod scala/collection/IterableLike.isEmpty:()Z
   130:	ifne	196
   133:	aload	7
   135:	invokeinterface	#355,  1; //InterfaceMethod scala/collection/TraversableLike.tail:()Ljava/lang/Object;
   140:	checkcast	#349; //class scala/collection/IterableLike
   143:	invokeinterface	#352,  1; //InterfaceMethod scala/collection/IterableLike.head:()Ljava/lang/Object;
   148:	astore_3
   149:	aload_3
   150:	aload_1
   151:	if_acmpne	158
   154:	iconst_1
   155:	goto	193
   158:	aload_3
   159:	ifnonnull	166
   162:	iconst_0
   163:	goto	193
   166:	aload_3
   167:	instanceof	#377; //class java/lang/Number
   170:	ifne	180
   173:	aload_3
   174:	instanceof	#379; //class java/lang/Character
   177:	ifeq	188
   180:	aload_3
   181:	aload_1
   182:	invokestatic	#383; //Method scala/runtime/BoxesRunTime.equals2:(Ljava/lang/Object;Ljava/lang/Object;)Z
   185:	goto	193
   188:	aload_3
   189:	aload_1
   190:	invokevirtual	#384; //Method java/lang/Object.equals:(Ljava/lang/Object;)Z
   193:	ifeq	298
   196:	aload	7
   198:	invokeinterface	#355,  1; //InterfaceMethod scala/collection/TraversableLike.tail:()Ljava/lang/Object;
   203:	checkcast	#349; //class scala/collection/IterableLike
   206:	invokeinterface	#375,  1; //InterfaceMethod scala/collection/IterableLike.isEmpty:()Z
   211:	ifne	296
   214:	aload	7
   216:	checkcast	#332; //class scala/collection/immutable/$colon$colon
   219:	astore	5
   221:	aload	5
   223:	getfield	#335; //Field scala/collection/immutable/$colon$colon.tl:Lscala/collection/immutable/List;
   226:	aload_0
   227:	getfield	#330; //Field scala$collection$mutable$ListBuffer$$last0:Lscala/collection/immutable/$colon$colon;
   230:	astore	4
   232:	dup
   233:	ifnonnull	245
   236:	pop
   237:	aload	4
   239:	ifnull	253
   242:	goto	259
   245:	aload	4
   247:	invokevirtual	#384; //Method java/lang/Object.equals:(Ljava/lang/Object;)Z
   250:	ifeq	259
   253:	aload_0
   254:	aload	5
   256:	invokespecial	#391; //Method scala$collection$mutable$ListBuffer$$last0_$eq:(Lscala/collection/immutable/$colon$colon;)V
   259:	aload	7
   261:	invokeinterface	#355,  1; //InterfaceMethod scala/collection/TraversableLike.tail:()Ljava/lang/Object;
   266:	checkcast	#292; //class scala/collection/TraversableLike
   269:	invokeinterface	#355,  1; //InterfaceMethod scala/collection/TraversableLike.tail:()Ljava/lang/Object;
   274:	checkcast	#357; //class scala/collection/immutable/List
   277:	astore	6
   279:	aload	5
   281:	aload	6
   283:	putfield	#335; //Field scala/collection/immutable/$colon$colon.tl:Lscala/collection/immutable/List;
   286:	aload_0
   287:	aload_0
   288:	invokespecial	#387; //Method len:()I
   291:	iconst_1
   292:	isub
   293:	invokespecial	#347; //Method len_$eq:(I)V
   296:	aload_0
   297:	areturn
   298:	aload	7
   300:	invokeinterface	#355,  1; //InterfaceMethod scala/collection/TraversableLike.tail:()Ljava/lang/Object;
   305:	checkcast	#357; //class scala/collection/immutable/List
   308:	astore	7
   310:	goto	115
  LineNumberTable: 
   line 264: 0
   line 265: 11
   line 266: 23
   line 267: 80
   line 268: 96
   line 270: 109
   line 271: 115
   line 274: 196
   line 275: 214
   line 276: 221
   line 277: 253
   line 278: 259
   line 279: 286
   line 282: 296
   line 272: 298

  LocalVariableTable: 
   Start  Length  Slot  Name   Signature
   0      313      0    this       Lscala/collection/mutable/ListBuffer;
   0      313      1    elem       Ljava/lang/Object;
   38      42      2    x0       Ljava/lang/Object;
   154      42      3    x1       Ljava/lang/Object;
   221      75      5    z       Lscala/collection/immutable/$colon$colon;
   115      181      7    cursor       Lscala/collection/immutable/List;
   298      15      7    cursor       Lscala/collection/immutable/List;

  Signature: length = 0x2
   01 FFFFFF8B 

public java.lang.Object remove(int);
  Code:
   Stack=3, Locals=7, Args_size=2
   0:	iload_1
   1:	iconst_0
   2:	if_icmplt	13
   5:	iload_1
   6:	aload_0
   7:	invokespecial	#387; //Method len:()I
   10:	if_icmplt	28
   13:	new	#398; //class java/lang/IndexOutOfBoundsException
   16:	dup
   17:	iload_1
   18:	invokestatic	#402; //Method scala/runtime/BoxesRunTime.boxToInteger:(I)Ljava/lang/Integer;
   21:	invokevirtual	#319; //Method java/lang/Object.toString:()Ljava/lang/String;
   24:	invokespecial	#403; //Method java/lang/IndexOutOfBoundsException."<init>":(Ljava/lang/String;)V
   27:	athrow
   28:	aload_0
   29:	invokespecial	#370; //Method exported:()Z
   32:	ifeq	39
   35:	aload_0
   36:	invokespecial	#372; //Method copy:()V
   39:	aload_0
   40:	getfield	#151; //Field scala$collection$mutable$ListBuffer$$start:Lscala/collection/immutable/List;
   43:	invokeinterface	#352,  1; //InterfaceMethod scala/collection/IterableLike.head:()Ljava/lang/Object;
   48:	astore	6
   50:	iload_1
   51:	iconst_0
   52:	if_icmpne	74
   55:	aload_0
   56:	aload_0
   57:	getfield	#151; //Field scala$collection$mutable$ListBuffer$$start:Lscala/collection/immutable/List;
   60:	invokeinterface	#355,  1; //InterfaceMethod scala/collection/TraversableLike.tail:()Ljava/lang/Object;
   65:	checkcast	#357; //class scala/collection/immutable/List
   68:	invokespecial	#339; //Method scala$collection$mutable$ListBuffer$$start_$eq:(Lscala/collection/immutable/List;)V
   71:	goto	172
   74:	aload_0
   75:	getfield	#151; //Field scala$collection$mutable$ListBuffer$$start:Lscala/collection/immutable/List;
   78:	astore_3
   79:	iconst_1
   80:	istore_2
   81:	iload_2
   82:	iload_1
   83:	if_icmpge	103
   86:	aload_3
   87:	invokeinterface	#355,  1; //InterfaceMethod scala/collection/TraversableLike.tail:()Ljava/lang/Object;
   92:	checkcast	#357; //class scala/collection/immutable/List
   95:	astore_3
   96:	iload_2
   97:	iconst_1
   98:	iadd
   99:	istore_2
   100:	goto	81
   103:	aload_3
   104:	invokeinterface	#355,  1; //InterfaceMethod scala/collection/TraversableLike.tail:()Ljava/lang/Object;
   109:	checkcast	#349; //class scala/collection/IterableLike
   112:	invokeinterface	#352,  1; //InterfaceMethod scala/collection/IterableLike.head:()Ljava/lang/Object;
   117:	astore	6
   119:	aload_0
   120:	getfield	#330; //Field scala$collection$mutable$ListBuffer$$last0:Lscala/collection/immutable/$colon$colon;
   123:	aload_3
   124:	invokeinterface	#355,  1; //InterfaceMethod scala/collection/TraversableLike.tail:()Ljava/lang/Object;
   129:	if_acmpne	140
   132:	aload_0
   133:	aload_3
   134:	checkcast	#332; //class scala/collection/immutable/$colon$colon
   137:	invokespecial	#391; //Method scala$collection$mutable$ListBuffer$$last0_$eq:(Lscala/collection/immutable/$colon$colon;)V
   140:	aload_3
   141:	checkcast	#332; //class scala/collection/immutable/$colon$colon
   144:	aload_3
   145:	invokeinterface	#355,  1; //InterfaceMethod scala/collection/TraversableLike.tail:()Ljava/lang/Object;
   150:	checkcast	#292; //class scala/collection/TraversableLike
   153:	invokeinterface	#355,  1; //InterfaceMethod scala/collection/TraversableLike.tail:()Ljava/lang/Object;
   158:	checkcast	#357; //class scala/collection/immutable/List
   161:	astore	5
   163:	astore	4
   165:	aload	4
   167:	aload	5
   169:	putfield	#335; //Field scala/collection/immutable/$colon$colon.tl:Lscala/collection/immutable/List;
   172:	aload_0
   173:	aload_0
   174:	invokespecial	#387; //Method len:()I
   177:	iconst_1
   178:	isub
   179:	invokespecial	#347; //Method len_$eq:(I)V
   182:	aload	6
   184:	areturn
  LineNumberTable: 
   line 238: 0
   line 239: 28
   line 240: 39
   line 241: 50
   line 242: 55
   line 244: 74
   line 245: 79
   line 246: 81
   line 247: 86
   line 248: 96
   line 250: 103
   line 251: 119
   line 252: 140
   line 254: 172
   line 255: 182

  LocalVariableTable: 
   Start  Length  Slot  Name   Signature
   0      185      0    this       Lscala/collection/mutable/ListBuffer;
   0      185      1    n       I
   81      91      2    i       I
   79      93      3    cursor       Lscala/collection/immutable/List;
   50      134      6    old       Ljava/lang/Object;

  Signature: length = 0x2
   01 FFFFFF97 

public scala.collection.immutable.List prependToList(scala.collection.immutable.List);
  Code:
   Stack=2, Locals=3, Args_size=2
   0:	aload_0
   1:	getfield	#151; //Field scala$collection$mutable$ListBuffer$$start:Lscala/collection/immutable/List;
   4:	invokeinterface	#375,  1; //InterfaceMethod scala/collection/IterableLike.isEmpty:()Z
   9:	ifeq	16
   12:	aload_1
   13:	goto	30
   16:	aload_0
   17:	getfield	#330; //Field scala$collection$mutable$ListBuffer$$last0:Lscala/collection/immutable/$colon$colon;
   20:	astore_2
   21:	aload_2
   22:	aload_1
   23:	putfield	#335; //Field scala/collection/immutable/$colon$colon.tl:Lscala/collection/immutable/List;
   26:	aload_0
   27:	invokevirtual	#412; //Method toList:()Lscala/collection/immutable/List;
   30:	areturn
  LineNumberTable: 
   line 224: 0
   line 225: 16
   line 224: 30

  LocalVariableTable: 
   Start  Length  Slot  Name   Signature
   0      31      0    this       Lscala/collection/mutable/ListBuffer;
   0      31      1    xs       Lscala/collection/immutable/List;

  Signature: length = 0x2
   01 FFFFFF9E 

public scala.collection.immutable.List toList();
  Code:
   Stack=2, Locals=1, Args_size=1
   0:	aload_0
   1:	aload_0
   2:	getfield	#151; //Field scala$collection$mutable$ListBuffer$$start:Lscala/collection/immutable/List;
   5:	invokeinterface	#375,  1; //InterfaceMethod scala/collection/IterableLike.isEmpty:()Z
   10:	ifeq	17
   13:	iconst_0
   14:	goto	18
   17:	iconst_1
   18:	invokespecial	#343; //Method exported_$eq:(Z)V
   21:	aload_0
   22:	getfield	#151; //Field scala$collection$mutable$ListBuffer$$start:Lscala/collection/immutable/List;
   25:	areturn
  LineNumberTable: 
   line 213: 0
   line 214: 21

  Signature: length = 0x2
   01 6A 

public scala.collection.immutable.List result();
  Code:
   Stack=1, Locals=1, Args_size=1
   0:	aload_0
   1:	invokevirtual	#412; //Method toList:()Lscala/collection/immutable/List;
   4:	areturn
  LineNumberTable: 
   line 207: 0

  Signature: length = 0x2
   01 6A 

public void remove(int, int);
  Code:
   Stack=3, Locals=11, Args_size=3
   0:	aload_0
   1:	invokespecial	#370; //Method exported:()Z
   4:	ifeq	11
   7:	aload_0
   8:	invokespecial	#372; //Method copy:()V
   11:	new	#417; //class scala/runtime/RichInt
   14:	dup
   15:	iload_1
   16:	invokespecial	#419; //Method scala/runtime/RichInt."<init>":(I)V
   19:	iconst_0
   20:	invokevirtual	#423; //Method scala/runtime/RichInt.max:(I)I
   23:	istore	4
   25:	new	#417; //class scala/runtime/RichInt
   28:	dup
   29:	iload_2
   30:	invokespecial	#419; //Method scala/runtime/RichInt."<init>":(I)V
   33:	aload_0
   34:	invokespecial	#387; //Method len:()I
   37:	iload	4
   39:	isub
   40:	invokevirtual	#426; //Method scala/runtime/RichInt.min:(I)I
   43:	istore	10
   45:	aload_0
   46:	getfield	#151; //Field scala$collection$mutable$ListBuffer$$start:Lscala/collection/immutable/List;
   49:	invokeinterface	#352,  1; //InterfaceMethod scala/collection/IterableLike.head:()Ljava/lang/Object;
   54:	pop
   55:	iload	4
   57:	iconst_0
   58:	if_icmpne	92
   61:	iload	10
   63:	istore_3
   64:	iload_3
   65:	iconst_0
   66:	if_icmple	205
   69:	aload_0
   70:	aload_0
   71:	getfield	#151; //Field scala$collection$mutable$ListBuffer$$start:Lscala/collection/immutable/List;
   74:	invokeinterface	#355,  1; //InterfaceMethod scala/collection/TraversableLike.tail:()Ljava/lang/Object;
   79:	checkcast	#357; //class scala/collection/immutable/List
   82:	invokespecial	#339; //Method scala$collection$mutable$ListBuffer$$start_$eq:(Lscala/collection/immutable/List;)V
   85:	iload_3
   86:	iconst_1
   87:	isub
   88:	istore_3
   89:	goto	64
   92:	aload_0
   93:	getfield	#151; //Field scala$collection$mutable$ListBuffer$$start:Lscala/collection/immutable/List;
   96:	astore	6
   98:	iconst_1
   99:	istore	5
   101:	iload	5
   103:	iload	4
   105:	if_icmpge	129
   108:	aload	6
   110:	invokeinterface	#355,  1; //InterfaceMethod scala/collection/TraversableLike.tail:()Ljava/lang/Object;
   115:	checkcast	#357; //class scala/collection/immutable/List
   118:	astore	6
   120:	iload	5
   122:	iconst_1
   123:	iadd
   124:	istore	5
   126:	goto	101
   129:	iload	10
   131:	istore	9
   133:	iload	9
   135:	iconst_0
   136:	if_icmple	205
   139:	aload_0
   140:	getfield	#330; //Field scala$collection$mutable$ListBuffer$$last0:Lscala/collection/immutable/$colon$colon;
   143:	aload	6
   145:	invokeinterface	#355,  1; //InterfaceMethod scala/collection/TraversableLike.tail:()Ljava/lang/Object;
   150:	if_acmpne	162
   153:	aload_0
   154:	aload	6
   156:	checkcast	#332; //class scala/collection/immutable/$colon$colon
   159:	invokespecial	#391; //Method scala$collection$mutable$ListBuffer$$last0_$eq:(Lscala/collection/immutable/$colon$colon;)V
   162:	aload	6
   164:	checkcast	#332; //class scala/collection/immutable/$colon$colon
   167:	aload	6
   169:	invokeinterface	#355,  1; //InterfaceMethod scala/collection/TraversableLike.tail:()Ljava/lang/Object;
   174:	checkcast	#292; //class scala/collection/TraversableLike
   177:	invokeinterface	#355,  1; //InterfaceMethod scala/collection/TraversableLike.tail:()Ljava/lang/Object;
   182:	checkcast	#357; //class scala/collection/immutable/List
   185:	astore	8
   187:	astore	7
   189:	aload	7
   191:	aload	8
   193:	putfield	#335; //Field scala/collection/immutable/$colon$colon.tl:Lscala/collection/immutable/List;
   196:	iload	9
   198:	iconst_1
   199:	isub
   200:	istore	9
   202:	goto	133
   205:	aload_0
   206:	aload_0
   207:	invokespecial	#387; //Method len:()I
   210:	iload	10
   212:	isub
   213:	invokespecial	#347; //Method len_$eq:(I)V
   216:	return
  LineNumberTable: 
   line 178: 0
   line 179: 11
   line 180: 25
   line 181: 45
   line 182: 55
   line 183: 61
   line 184: 64
   line 185: 69
   line 186: 85
   line 189: 92
   line 190: 98
   line 191: 101
   line 192: 108
   line 193: 120
   line 195: 129
   line 196: 133
   line 197: 139
   line 198: 162
   line 199: 196
   line 202: 205

  LocalVariableTable: 
   Start  Length  Slot  Name   Signature
   0      217      0    this       Lscala/collection/mutable/ListBuffer;
   0      217      1    n       I
   0      217      2    count       I
   64      28      3    c       I
   25      191      4    n1       I
   101      104      5    i       I
   98      107      6    cursor       Lscala/collection/immutable/List;
   133      72      9    c       I
   45      171      10    count1       I


public void insertAll(int, scala.collection.Traversable);
  Code:
   Stack=4, Locals=9, Args_size=3
   0:	aload_0
   1:	invokespecial	#370; //Method exported:()Z
   4:	ifeq	11
   7:	aload_0
   8:	invokespecial	#372; //Method copy:()V
   11:	aload_2
   12:	invokeinterface	#433,  1; //InterfaceMethod scala/collection/TraversableLike.toList:()Lscala/collection/immutable/List;
   17:	invokevirtual	#436; //Method scala/collection/immutable/List.reverse:()Lscala/collection/immutable/List;
   20:	astore	8
   22:	aload_0
   23:	aload_0
   24:	invokespecial	#387; //Method len:()I
   27:	aload	8
   29:	invokeinterface	#441,  1; //InterfaceMethod scala/collection/LinearSeqLike.length:()I
   34:	iadd
   35:	invokespecial	#347; //Method len_$eq:(I)V
   38:	iload_1
   39:	iconst_0
   40:	if_icmpne	109
   43:	aload	8
   45:	invokeinterface	#375,  1; //InterfaceMethod scala/collection/IterableLike.isEmpty:()Z
   50:	ifne	155
   53:	new	#332; //class scala/collection/immutable/$colon$colon
   56:	dup
   57:	aload	8
   59:	invokeinterface	#352,  1; //InterfaceMethod scala/collection/IterableLike.head:()Ljava/lang/Object;
   64:	aload_0
   65:	getfield	#151; //Field scala$collection$mutable$ListBuffer$$start:Lscala/collection/immutable/List;
   68:	invokespecial	#444; //Method scala/collection/immutable/$colon$colon."<init>":(Ljava/lang/Object;Lscala/collection/immutable/List;)V
   71:	astore_3
   72:	aload_0
   73:	getfield	#151; //Field scala$collection$mutable$ListBuffer$$start:Lscala/collection/immutable/List;
   76:	invokeinterface	#375,  1; //InterfaceMethod scala/collection/IterableLike.isEmpty:()Z
   81:	ifeq	89
   84:	aload_0
   85:	aload_3
   86:	invokespecial	#391; //Method scala$collection$mutable$ListBuffer$$last0_$eq:(Lscala/collection/immutable/$colon$colon;)V
   89:	aload_0
   90:	aload_3
   91:	invokespecial	#339; //Method scala$collection$mutable$ListBuffer$$start_$eq:(Lscala/collection/immutable/List;)V
   94:	aload	8
   96:	invokeinterface	#355,  1; //InterfaceMethod scala/collection/TraversableLike.tail:()Ljava/lang/Object;
   101:	checkcast	#357; //class scala/collection/immutable/List
   104:	astore	8
   106:	goto	43
   109:	aload_0
   110:	getfield	#151; //Field scala$collection$mutable$ListBuffer$$start:Lscala/collection/immutable/List;
   113:	astore	5
   115:	iconst_1
   116:	istore	4
   118:	iload	4
   120:	iload_1
   121:	if_icmpge	145
   124:	aload	5
   126:	invokeinterface	#355,  1; //InterfaceMethod scala/collection/TraversableLike.tail:()Ljava/lang/Object;
   131:	checkcast	#357; //class scala/collection/immutable/List
   134:	astore	5
   136:	iload	4
   138:	iconst_1
   139:	iadd
   140:	istore	4
   142:	goto	118
   145:	aload	8
   147:	invokeinterface	#375,  1; //InterfaceMethod scala/collection/IterableLike.isEmpty:()Z
   152:	ifeq	156
   155:	return
   156:	new	#332; //class scala/collection/immutable/$colon$colon
   159:	dup
   160:	aload	8
   162:	invokeinterface	#352,  1; //InterfaceMethod scala/collection/IterableLike.head:()Ljava/lang/Object;
   167:	aload	5
   169:	invokeinterface	#355,  1; //InterfaceMethod scala/collection/TraversableLike.tail:()Ljava/lang/Object;
   174:	checkcast	#357; //class scala/collection/immutable/List
   177:	invokespecial	#444; //Method scala/collection/immutable/$colon$colon."<init>":(Ljava/lang/Object;Lscala/collection/immutable/List;)V
   180:	astore	7
   182:	aload	5
   184:	invokeinterface	#355,  1; //InterfaceMethod scala/collection/TraversableLike.tail:()Ljava/lang/Object;
   189:	checkcast	#349; //class scala/collection/IterableLike
   192:	invokeinterface	#375,  1; //InterfaceMethod scala/collection/IterableLike.isEmpty:()Z
   197:	ifeq	206
   200:	aload_0
   201:	aload	7
   203:	invokespecial	#391; //Method scala$collection$mutable$ListBuffer$$last0_$eq:(Lscala/collection/immutable/$colon$colon;)V
   206:	aload	5
   208:	checkcast	#332; //class scala/collection/immutable/$colon$colon
   211:	astore	6
   213:	aload	6
   215:	aload	7
   217:	putfield	#335; //Field scala/collection/immutable/$colon$colon.tl:Lscala/collection/immutable/List;
   220:	aload	8
   222:	invokeinterface	#355,  1; //InterfaceMethod scala/collection/TraversableLike.tail:()Ljava/lang/Object;
   227:	checkcast	#357; //class scala/collection/immutable/List
   230:	astore	8
   232:	goto	145
   235:	pop
   236:	new	#398; //class java/lang/IndexOutOfBoundsException
   239:	dup
   240:	iload_1
   241:	invokestatic	#402; //Method scala/runtime/BoxesRunTime.boxToInteger:(I)Ljava/lang/Integer;
   244:	invokevirtual	#319; //Method java/lang/Object.toString:()Ljava/lang/String;
   247:	invokespecial	#403; //Method java/lang/IndexOutOfBoundsException."<init>":(Ljava/lang/String;)V
   250:	athrow
  Exception table:
   from   to  target type
     0   155   235   Class java/lang/Exception

   156   235   235   Class java/lang/Exception

  LineNumberTable: 
   line 141: 0
   line 142: 11
   line 143: 22
   line 144: 38
   line 145: 43
   line 146: 53
   line 147: 72
   line 148: 89
   line 149: 94
   line 152: 109
   line 153: 115
   line 154: 118
   line 155: 124
   line 156: 136
   line 158: 145
   line 140: 155
   line 159: 156
   line 160: 182
   line 161: 206
   line 162: 220
   line 167: 236

  LocalVariableTable: 
   Start  Length  Slot  Name   Signature
   0      251      0    this       Lscala/collection/mutable/ListBuffer;
   0      251      1    n       I
   0      251      2    seq       Lscala/collection/Traversable;
   72      34      3    newElem       Lscala/collection/immutable/$colon$colon;
   118      37      4    i       I
   156      79      4    i       I
   115      40      5    cursor       Lscala/collection/immutable/List;
   156      79      5    cursor       Lscala/collection/immutable/List;
   213      22      6    $inlThis3       Ljava/lang/Object;
   182      50      7    newElem       Lscala/collection/immutable/$colon$colon;
   22      133      8    elems       Lscala/collection/immutable/List;
   156      79      8    elems       Lscala/collection/immutable/List;

  Signature: length = 0x2
   01 FFFFFFC2 

public scala.collection.mutable.ListBuffer $plus$eq$colon(java.lang.Object);
  Code:
   Stack=4, Locals=3, Args_size=2
   0:	aload_0
   1:	invokespecial	#370; //Method exported:()Z
   4:	ifeq	11
   7:	aload_0
   8:	invokespecial	#372; //Method copy:()V
   11:	new	#332; //class scala/collection/immutable/$colon$colon
   14:	dup
   15:	aload_1
   16:	aload_0
   17:	getfield	#151; //Field scala$collection$mutable$ListBuffer$$start:Lscala/collection/immutable/List;
   20:	invokespecial	#444; //Method scala/collection/immutable/$colon$colon."<init>":(Ljava/lang/Object;Lscala/collection/immutable/List;)V
   23:	astore_2
   24:	aload_0
   25:	getfield	#151; //Field scala$collection$mutable$ListBuffer$$start:Lscala/collection/immutable/List;
   28:	invokeinterface	#375,  1; //InterfaceMethod scala/collection/IterableLike.isEmpty:()Z
   33:	ifeq	41
   36:	aload_0
   37:	aload_2
   38:	invokespecial	#391; //Method scala$collection$mutable$ListBuffer$$last0_$eq:(Lscala/collection/immutable/$colon$colon;)V
   41:	aload_0
   42:	aload_2
   43:	invokespecial	#339; //Method scala$collection$mutable$ListBuffer$$start_$eq:(Lscala/collection/immutable/List;)V
   46:	aload_0
   47:	aload_0
   48:	invokespecial	#387; //Method len:()I
   51:	iconst_1
   52:	iadd
   53:	invokespecial	#347; //Method len_$eq:(I)V
   56:	aload_0
   57:	areturn
  LineNumberTable: 
   line 123: 0
   line 124: 11
   line 125: 24
   line 126: 41
   line 127: 46
   line 128: 56

  LocalVariableTable: 
   Start  Length  Slot  Name   Signature
   0      58      0    this       Lscala/collection/mutable/ListBuffer;
   0      58      1    x       Ljava/lang/Object;
   24      33      2    newElem       Lscala/collection/immutable/$colon$colon;

  Signature: length = 0x2
   01 FFFFFF8B 

public void clear();
  Code:
   Stack=2, Locals=1, Args_size=1
   0:	aload_0
   1:	getstatic	#149; //Field scala/collection/immutable/Nil$.MODULE$:Lscala/collection/immutable/Nil$;
   4:	invokespecial	#339; //Method scala$collection$mutable$ListBuffer$$start_$eq:(Lscala/collection/immutable/List;)V
   7:	aload_0
   8:	iconst_0
   9:	invokespecial	#343; //Method exported_$eq:(Z)V
   12:	aload_0
   13:	iconst_0
   14:	invokespecial	#347; //Method len_$eq:(I)V
   17:	return
  LineNumberTable: 
   line 111: 0
   line 112: 7
   line 113: 12


public scala.collection.mutable.ListBuffer $plus$eq(java.lang.Object);
  Code:
   Stack=5, Locals=4, Args_size=2
   0:	aload_0
   1:	invokespecial	#370; //Method exported:()Z
   4:	ifeq	11
   7:	aload_0
   8:	invokespecial	#372; //Method copy:()V
   11:	aload_0
   12:	getfield	#151; //Field scala$collection$mutable$ListBuffer$$start:Lscala/collection/immutable/List;
   15:	invokeinterface	#375,  1; //InterfaceMethod scala/collection/IterableLike.isEmpty:()Z
   20:	ifeq	49
   23:	aload_0
   24:	new	#332; //class scala/collection/immutable/$colon$colon
   27:	dup
   28:	aload_1
   29:	getstatic	#149; //Field scala/collection/immutable/Nil$.MODULE$:Lscala/collection/immutable/Nil$;
   32:	invokespecial	#444; //Method scala/collection/immutable/$colon$colon."<init>":(Ljava/lang/Object;Lscala/collection/immutable/List;)V
   35:	invokespecial	#391; //Method scala$collection$mutable$ListBuffer$$last0_$eq:(Lscala/collection/immutable/$colon$colon;)V
   38:	aload_0
   39:	aload_0
   40:	getfield	#330; //Field scala$collection$mutable$ListBuffer$$last0:Lscala/collection/immutable/$colon$colon;
   43:	invokespecial	#339; //Method scala$collection$mutable$ListBuffer$$start_$eq:(Lscala/collection/immutable/List;)V
   46:	goto	79
   49:	aload_0
   50:	getfield	#330; //Field scala$collection$mutable$ListBuffer$$last0:Lscala/collection/immutable/$colon$colon;
   53:	astore_2
   54:	aload_0
   55:	new	#332; //class scala/collection/immutable/$colon$colon
   58:	dup
   59:	aload_1
   60:	getstatic	#149; //Field scala/collection/immutable/Nil$.MODULE$:Lscala/collection/immutable/Nil$;
   63:	invokespecial	#444; //Method scala/collection/immutable/$colon$colon."<init>":(Ljava/lang/Object;Lscala/collection/immutable/List;)V
   66:	invokespecial	#391; //Method scala$collection$mutable$ListBuffer$$last0_$eq:(Lscala/collection/immutable/$colon$colon;)V
   69:	aload_0
   70:	getfield	#330; //Field scala$collection$mutable$ListBuffer$$last0:Lscala/collection/immutable/$colon$colon;
   73:	astore_3
   74:	aload_2
   75:	aload_3
   76:	putfield	#335; //Field scala/collection/immutable/$colon$colon.tl:Lscala/collection/immutable/List;
   79:	aload_0
   80:	aload_0
   81:	invokespecial	#387; //Method len:()I
   84:	iconst_1
   85:	iadd
   86:	invokespecial	#347; //Method len_$eq:(I)V
   89:	aload_0
   90:	areturn
  LineNumberTable: 
   line 95: 0
   line 96: 11
   line 97: 23
   line 98: 38
   line 100: 49
   line 101: 54
   line 102: 69
   line 104: 79
   line 105: 89

  LocalVariableTable: 
   Start  Length  Slot  Name   Signature
   0      91      0    this       Lscala/collection/mutable/ListBuffer;
   0      91      1    x       Ljava/lang/Object;
   54      25      2    last1       Lscala/collection/immutable/$colon$colon;

  Signature: length = 0x2
   01 FFFFFF8B 

public void update(int, java.lang.Object);
  Code:
   Stack=4, Locals=8, Args_size=3
   0:	aload_0
   1:	invokespecial	#370; //Method exported:()Z
   4:	ifeq	11
   7:	aload_0
   8:	invokespecial	#372; //Method copy:()V
   11:	iload_1
   12:	iconst_0
   13:	if_icmpne	61
   16:	new	#332; //class scala/collection/immutable/$colon$colon
   19:	dup
   20:	aload_2
   21:	aload_0
   22:	getfield	#151; //Field scala$collection$mutable$ListBuffer$$start:Lscala/collection/immutable/List;
   25:	invokeinterface	#355,  1; //InterfaceMethod scala/collection/TraversableLike.tail:()Ljava/lang/Object;
   30:	checkcast	#357; //class scala/collection/immutable/List
   33:	invokespecial	#444; //Method scala/collection/immutable/$colon$colon."<init>":(Ljava/lang/Object;Lscala/collection/immutable/List;)V
   36:	astore_3
   37:	aload_0
   38:	getfield	#330; //Field scala$collection$mutable$ListBuffer$$last0:Lscala/collection/immutable/$colon$colon;
   41:	aload_0
   42:	getfield	#151; //Field scala$collection$mutable$ListBuffer$$start:Lscala/collection/immutable/List;
   45:	if_acmpne	53
   48:	aload_0
   49:	aload_3
   50:	invokespecial	#391; //Method scala$collection$mutable$ListBuffer$$last0_$eq:(Lscala/collection/immutable/$colon$colon;)V
   53:	aload_0
   54:	aload_3
   55:	invokespecial	#339; //Method scala$collection$mutable$ListBuffer$$start_$eq:(Lscala/collection/immutable/List;)V
   58:	goto	159
   61:	aload_0
   62:	getfield	#151; //Field scala$collection$mutable$ListBuffer$$start:Lscala/collection/immutable/List;
   65:	astore	5
   67:	iconst_1
   68:	istore	4
   70:	iload	4
   72:	iload_1
   73:	if_icmpge	97
   76:	aload	5
   78:	invokeinterface	#355,  1; //InterfaceMethod scala/collection/TraversableLike.tail:()Ljava/lang/Object;
   83:	checkcast	#357; //class scala/collection/immutable/List
   86:	astore	5
   88:	iload	4
   90:	iconst_1
   91:	iadd
   92:	istore	4
   94:	goto	70
   97:	new	#332; //class scala/collection/immutable/$colon$colon
   100:	dup
   101:	aload_2
   102:	aload	5
   104:	invokeinterface	#355,  1; //InterfaceMethod scala/collection/TraversableLike.tail:()Ljava/lang/Object;
   109:	checkcast	#292; //class scala/collection/TraversableLike
   112:	invokeinterface	#355,  1; //InterfaceMethod scala/collection/TraversableLike.tail:()Ljava/lang/Object;
   117:	checkcast	#357; //class scala/collection/immutable/List
   120:	invokespecial	#444; //Method scala/collection/immutable/$colon$colon."<init>":(Ljava/lang/Object;Lscala/collection/immutable/List;)V
   123:	astore	7
   125:	aload_0
   126:	getfield	#330; //Field scala$collection$mutable$ListBuffer$$last0:Lscala/collection/immutable/$colon$colon;
   129:	aload	5
   131:	invokeinterface	#355,  1; //InterfaceMethod scala/collection/TraversableLike.tail:()Ljava/lang/Object;
   136:	if_acmpne	145
   139:	aload_0
   140:	aload	7
   142:	invokespecial	#391; //Method scala$collection$mutable$ListBuffer$$last0_$eq:(Lscala/collection/immutable/$colon$colon;)V
   145:	aload	5
   147:	checkcast	#332; //class scala/collection/immutable/$colon$colon
   150:	astore	6
   152:	aload	6
   154:	aload	7
   156:	putfield	#335; //Field scala/collection/immutable/$colon$colon.tl:Lscala/collection/immutable/List;
   159:	return
   160:	pop
   161:	new	#398; //class java/lang/IndexOutOfBoundsException
   164:	dup
   165:	iload_1
   166:	invokestatic	#402; //Method scala/runtime/BoxesRunTime.boxToInteger:(I)Ljava/lang/Integer;
   169:	invokevirtual	#319; //Method java/lang/Object.toString:()Ljava/lang/String;
   172:	invokespecial	#403; //Method java/lang/IndexOutOfBoundsException."<init>":(Ljava/lang/String;)V
   175:	athrow
  Exception table:
   from   to  target type
     0   159   160   Class java/lang/Exception

  LineNumberTable: 
   line 65: 0
   line 66: 11
   line 67: 16
   line 68: 37
   line 69: 48
   line 71: 53
   line 73: 61
   line 74: 67
   line 75: 70
   line 76: 76
   line 77: 88
   line 79: 97
   line 80: 125
   line 81: 139
   line 83: 145
   line 64: 159
   line 86: 161

  LocalVariableTable: 
   Start  Length  Slot  Name   Signature
   0      176      0    this       Lscala/collection/mutable/ListBuffer;
   0      176      1    n       I
   0      176      2    x       Ljava/lang/Object;
   37      21      3    newElem       Lscala/collection/immutable/$colon$colon;
   70      89      4    i       I
   67      92      5    cursor       Lscala/collection/immutable/List;
   152      7      6    $inlThis5       Ljava/lang/Object;
   125      34      7    newElem       Lscala/collection/immutable/$colon$colon;

  Signature: length = 0x2
   01 FFFFFFC8 

public java.lang.Object apply(int);
  Code:
   Stack=3, Locals=2, Args_size=2
   0:	iload_1
   1:	iconst_0
   2:	if_icmplt	13
   5:	iload_1
   6:	aload_0
   7:	invokespecial	#387; //Method len:()I
   10:	if_icmplt	28
   13:	new	#398; //class java/lang/IndexOutOfBoundsException
   16:	dup
   17:	iload_1
   18:	invokestatic	#402; //Method scala/runtime/BoxesRunTime.boxToInteger:(I)Ljava/lang/Integer;
   21:	invokevirtual	#319; //Method java/lang/Object.toString:()Ljava/lang/String;
   24:	invokespecial	#403; //Method java/lang/IndexOutOfBoundsException."<init>":(Ljava/lang/String;)V
   27:	athrow
   28:	aload_0
   29:	iload_1
   30:	invokestatic	#459; //Method scala/collection/generic/SeqForwarder$class.apply:(Lscala/collection/generic/SeqForwarder;I)Ljava/lang/Object;
   33:	areturn
  LineNumberTable: 
   line 52: 0
   line 53: 28
   line 52: 33

  LocalVariableTable: 
   Start  Length  Slot  Name   Signature
   0      34      0    this       Lscala/collection/mutable/ListBuffer;
   0      34      1    n       I

  Signature: length = 0x2
   01 FFFFFF97 

public int length();
  Code:
   Stack=1, Locals=1, Args_size=1
   0:	aload_0
   1:	invokespecial	#387; //Method len:()I
   4:	ireturn
  LineNumberTable: 
   line 47: 0


public scala.collection.immutable.Seq underlying();
  Code:
   Stack=1, Locals=1, Args_size=1
   0:	aload_0
   1:	invokevirtual	#361; //Method scala$collection$mutable$ListBuffer$$start:()Lscala/collection/immutable/List;
   4:	areturn
  LineNumberTable: 
   line 43: 0

  Signature: length = 0x2
   01 FFFFFFCC 

public final scala.collection.immutable.$colon$colon scala$collection$mutable$ListBuffer$$last0();
  Code:
   Stack=1, Locals=1, Args_size=1
   0:	aload_0
   1:	getfield	#330; //Field scala$collection$mutable$ListBuffer$$last0:Lscala/collection/immutable/$colon$colon;
   4:	areturn
  LineNumberTable: 
   line 39: 0


public final scala.collection.immutable.List scala$collection$mutable$ListBuffer$$start();
  Code:
   Stack=1, Locals=1, Args_size=1
   0:	aload_0
   1:	getfield	#151; //Field scala$collection$mutable$ListBuffer$$start:Lscala/collection/immutable/List;
   4:	areturn
  LineNumberTable: 
   line 38: 0


public scala.collection.generic.GenericCompanion companion();
  Code:
   Stack=1, Locals=1, Args_size=1
   0:	getstatic	#468; //Field scala/collection/mutable/ListBuffer$.MODULE$:Lscala/collection/mutable/ListBuffer$;
   3:	areturn
  LineNumberTable: 
   line 34: 0

  Signature: length = 0x2
   01 FFFFFFD5 

public scala.collection.TraversableLike$WithFilter withFilter(scala.Function1);
  Code:
   Stack=2, Locals=2, Args_size=2
   0:	aload_0
   1:	aload_1
   2:	invokestatic	#474; //Method scala/collection/TraversableLike$class.withFilter:(Lscala/collection/TraversableLike;Lscala/Function1;)Lscala/collection/TraversableLike$WithFilter;
   5:	areturn
  LineNumberTable: 
   line 27: 0

  LocalVariableTable: 
   Start  Length  Slot  Name   Signature
   0      6      0    this       Lscala/collection/mutable/ListBuffer;
   0      6      1    p       Lscala/Function1;

  Signature: length = 0x2
   01 FFFFFFD7 

public scala.collection.mutable.StringBuilder addString(scala.collection.mutable.StringBuilder);
  Code:
   Stack=2, Locals=2, Args_size=2
   0:	aload_0
   1:	aload_1
   2:	invokestatic	#480; //Method scala/collection/TraversableLike$class.addString:(Lscala/collection/TraversableLike;Lscala/collection/mutable/StringBuilder;)Lscala/collection/mutable/StringBuilder;
   5:	areturn
  LineNumberTable: 
   line 27: 0

  LocalVariableTable: 
   Start  Length  Slot  Name   Signature
   0      6      0    this       Lscala/collection/mutable/ListBuffer;
   0      6      1    b       Lscala/collection/mutable/StringBuilder;


public scala.collection.mutable.StringBuilder addString(scala.collection.mutable.StringBuilder, java.lang.String);
  Code:
   Stack=3, Locals=3, Args_size=3
   0:	aload_0
   1:	aload_1
   2:	aload_2
   3:	invokestatic	#486; //Method scala/collection/TraversableLike$class.addString:(Lscala/collection/TraversableLike;Lscala/collection/mutable/StringBuilder;Ljava/lang/String;)Lscala/collection/mutable/StringBuilder;
   6:	areturn
  LineNumberTable: 
   line 27: 0

  LocalVariableTable: 
   Start  Length  Slot  Name   Signature
   0      7      0    this       Lscala/collection/mutable/ListBuffer;
   0      7      1    b       Lscala/collection/mutable/StringBuilder;
   0      7      2    sep       Ljava/lang/String;


public java.lang.String mkString();
  Code:
   Stack=1, Locals=1, Args_size=1
   0:	aload_0
   1:	invokestatic	#492; //Method scala/collection/TraversableLike$class.mkString:(Lscala/collection/TraversableLike;)Ljava/lang/String;
   4:	areturn
  LineNumberTable: 
   line 27: 0


public java.lang.String mkString(java.lang.String);
  Code:
   Stack=2, Locals=2, Args_size=2
   0:	aload_0
   1:	aload_1
   2:	invokestatic	#496; //Method scala/collection/TraversableLike$class.mkString:(Lscala/collection/TraversableLike;Ljava/lang/String;)Ljava/lang/String;
   5:	areturn
  LineNumberTable: 
   line 27: 0

  LocalVariableTable: 
   Start  Length  Slot  Name   Signature
   0      6      0    this       Lscala/collection/mutable/ListBuffer;
   0      6      1    sep       Ljava/lang/String;


public scala.collection.immutable.Set toSet();
  Code:
   Stack=1, Locals=1, Args_size=1
   0:	aload_0
   1:	invokestatic	#501; //Method scala/collection/TraversableLike$class.toSet:(Lscala/collection/TraversableLike;)Lscala/collection/immutable/Set;
   4:	areturn
  LineNumberTable: 
   line 27: 0


public scala.collection.mutable.IndexedSeq toIndexedSeq();
  Code:
   Stack=1, Locals=1, Args_size=1
   0:	aload_0
   1:	invokestatic	#506; //Method scala/collection/TraversableLike$class.toIndexedSeq:(Lscala/collection/TraversableLike;)Lscala/collection/mutable/IndexedSeq;
   4:	areturn
  LineNumberTable: 
   line 27: 0


public void copyToArray(java.lang.Object);
  Code:
   Stack=2, Locals=2, Args_size=2
   0:	aload_0
   1:	aload_1
   2:	invokestatic	#511; //Method scala/collection/TraversableLike$class.copyToArray:(Lscala/collection/TraversableLike;Ljava/lang/Object;)V
   5:	return
  LineNumberTable: 
   line 27: 0

  LocalVariableTable: 
   Start  Length  Slot  Name   Signature
   0      6      0    this       Lscala/collection/mutable/ListBuffer;
   0      6      1    xs       Ljava/lang/Object;


public void copyToArray(java.lang.Object, int);
  Code:
   Stack=3, Locals=3, Args_size=3
   0:	aload_0
   1:	aload_1
   2:	iload_2
   3:	invokestatic	#515; //Method scala/collection/TraversableLike$class.copyToArray:(Lscala/collection/TraversableLike;Ljava/lang/Object;I)V
   6:	return
  LineNumberTable: 
   line 27: 0

  LocalVariableTable: 
   Start  Length  Slot  Name   Signature
   0      7      0    this       Lscala/collection/mutable/ListBuffer;
   0      7      1    xs       Ljava/lang/Object;
   0      7      2    start       I


public scala.Tuple2 splitAt(int);
  Code:
   Stack=2, Locals=2, Args_size=2
   0:	aload_0
   1:	iload_1
   2:	invokestatic	#521; //Method scala/collection/TraversableLike$class.splitAt:(Lscala/collection/TraversableLike;I)Lscala/Tuple2;
   5:	areturn
  LineNumberTable: 
   line 27: 0

  LocalVariableTable: 
   Start  Length  Slot  Name   Signature
   0      6      0    this       Lscala/collection/mutable/ListBuffer;
   0      6      1    n       I


public scala.Tuple2 span(scala.Function1);
  Code:
   Stack=2, Locals=2, Args_size=2
   0:	aload_0
   1:	aload_1
   2:	invokestatic	#526; //Method scala/collection/TraversableLike$class.span:(Lscala/collection/TraversableLike;Lscala/Function1;)Lscala/Tuple2;
   5:	areturn
  LineNumberTable: 
   line 27: 0

  LocalVariableTable: 
   Start  Length  Slot  Name   Signature
   0      6      0    this       Lscala/collection/mutable/ListBuffer;
   0      6      1    p       Lscala/Function1;


public java.lang.Object dropWhile(scala.Function1);
  Code:
   Stack=2, Locals=2, Args_size=2
   0:	aload_0
   1:	aload_1
   2:	invokestatic	#531; //Method scala/collection/TraversableLike$class.dropWhile:(Lscala/collection/TraversableLike;Lscala/Function1;)Ljava/lang/Object;
   5:	areturn
  LineNumberTable: 
   line 27: 0

  LocalVariableTable: 
   Start  Length  Slot  Name   Signature
   0      6      0    this       Lscala/collection/mutable/ListBuffer;
   0      6      1    p       Lscala/Function1;


public java.lang.Object drop(int);
  Code:
   Stack=2, Locals=2, Args_size=2
   0:	aload_0
   1:	iload_1
   2:	invokestatic	#535; //Method scala/collection/TraversableLike$class.drop:(Lscala/collection/TraversableLike;I)Ljava/lang/Object;
   5:	areturn
  LineNumberTable: 
   line 27: 0

  LocalVariableTable: 
   Start  Length  Slot  Name   Signature
   0      6      0    this       Lscala/collection/mutable/ListBuffer;
   0      6      1    n       I


public java.lang.Object init();
  Code:
   Stack=1, Locals=1, Args_size=1
   0:	aload_0
   1:	invokestatic	#539; //Method scala/collection/TraversableLike$class.init:(Lscala/collection/TraversableLike;)Ljava/lang/Object;
   4:	areturn
  LineNumberTable: 
   line 27: 0


public java.lang.Object tail();
  Code:
   Stack=1, Locals=1, Args_size=1
   0:	aload_0
   1:	invokestatic	#541; //Method scala/collection/TraversableLike$class.tail:(Lscala/collection/TraversableLike;)Ljava/lang/Object;
   4:	areturn
  LineNumberTable: 
   line 27: 0


public scala.Option headOption();
  Code:
   Stack=1, Locals=1, Args_size=1
   0:	aload_0
   1:	invokestatic	#546; //Method scala/collection/TraversableLike$class.headOption:(Lscala/collection/TraversableLike;)Lscala/Option;
   4:	areturn
  LineNumberTable: 
   line 27: 0


public java.lang.Object max(scala.math.Ordering);
  Code:
   Stack=2, Locals=2, Args_size=2
   0:	aload_0
   1:	aload_1
   2:	invokestatic	#550; //Method scala/collection/TraversableLike$class.max:(Lscala/collection/TraversableLike;Lscala/math/Ordering;)Ljava/lang/Object;
   5:	areturn
  LineNumberTable: 
   line 27: 0

  LocalVariableTable: 
   Start  Length  Slot  Name   Signature
   0      6      0    this       Lscala/collection/mutable/ListBuffer;
   0      6      1    cmp       Lscala/math/Ordering;


public java.lang.Object min(scala.math.Ordering);
  Code:
   Stack=2, Locals=2, Args_size=2
   0:	aload_0
   1:	aload_1
   2:	invokestatic	#554; //Method scala/collection/TraversableLike$class.min:(Lscala/collection/TraversableLike;Lscala/math/Ordering;)Ljava/lang/Object;
   5:	areturn
  LineNumberTable: 
   line 27: 0

  LocalVariableTable: 
   Start  Length  Slot  Name   Signature
   0      6      0    this       Lscala/collection/mutable/ListBuffer;
   0      6      1    cmp       Lscala/math/Ordering;


public java.lang.Object product(scala.math.Numeric);
  Code:
   Stack=2, Locals=2, Args_size=2
   0:	aload_0
   1:	aload_1
   2:	invokestatic	#559; //Method scala/collection/TraversableLike$class.product:(Lscala/collection/TraversableLike;Lscala/math/Numeric;)Ljava/lang/Object;
   5:	areturn
  LineNumberTable: 
   line 27: 0

  LocalVariableTable: 
   Start  Length  Slot  Name   Signature
   0      6      0    this       Lscala/collection/mutable/ListBuffer;
   0      6      1    num       Lscala/math/Numeric;


public java.lang.Object sum(scala.math.Numeric);
  Code:
   Stack=2, Locals=2, Args_size=2
   0:	aload_0
   1:	aload_1
   2:	invokestatic	#564; //Method scala/collection/TraversableLike$class.sum:(Lscala/collection/TraversableLike;Lscala/math/Numeric;)Ljava/lang/Object;
   5:	areturn
  LineNumberTable: 
   line 27: 0

  LocalVariableTable: 
   Start  Length  Slot  Name   Signature
   0      6      0    this       Lscala/collection/mutable/ListBuffer;
   0      6      1    num       Lscala/math/Numeric;


public java.lang.Object $colon$bslash(java.lang.Object, scala.Function2);
  Code:
   Stack=3, Locals=3, Args_size=3
   0:	aload_0
   1:	aload_1
   2:	aload_2
   3:	invokestatic	#569; //Method scala/collection/TraversableLike$class.$colon$bslash:(Lscala/collection/TraversableLike;Ljava/lang/Object;Lscala/Function2;)Ljava/lang/Object;
   6:	areturn
  LineNumberTable: 
   line 27: 0

  LocalVariableTable: 
   Start  Length  Slot  Name   Signature
   0      7      0    this       Lscala/collection/mutable/ListBuffer;
   0      7      1    z       Ljava/lang/Object;
   0      7      2    op       Lscala/Function2;


public java.lang.Object $div$colon(java.lang.Object, scala.Function2);
  Code:
   Stack=3, Locals=3, Args_size=3
   0:	aload_0
   1:	aload_1
   2:	aload_2
   3:	invokestatic	#574; //Method scala/collection/TraversableLike$class.$div$colon:(Lscala/collection/TraversableLike;Ljava/lang/Object;Lscala/Function2;)Ljava/lang/Object;
   6:	areturn
  LineNumberTable: 
   line 27: 0

  LocalVariableTable: 
   Start  Length  Slot  Name   Signature
   0      7      0    this       Lscala/collection/mutable/ListBuffer;
   0      7      1    z       Ljava/lang/Object;
   0      7      2    op       Lscala/Function2;


public scala.collection.Map groupBy(scala.Function1);
  Code:
   Stack=2, Locals=2, Args_size=2
   0:	aload_0
   1:	aload_1
   2:	invokestatic	#579; //Method scala/collection/TraversableLike$class.groupBy:(Lscala/collection/TraversableLike;Lscala/Function1;)Lscala/collection/Map;
   5:	areturn
  LineNumberTable: 
   line 27: 0

  LocalVariableTable: 
   Start  Length  Slot  Name   Signature
   0      6      0    this       Lscala/collection/mutable/ListBuffer;
   0      6      1    f       Lscala/Function1;


public scala.Tuple2 partition(scala.Function1);
  Code:
   Stack=2, Locals=2, Args_size=2
   0:	aload_0
   1:	aload_1
   2:	invokestatic	#583; //Method scala/collection/TraversableLike$class.partition:(Lscala/collection/TraversableLike;Lscala/Function1;)Lscala/Tuple2;
   5:	areturn
  LineNumberTable: 
   line 27: 0

  LocalVariableTable: 
   Start  Length  Slot  Name   Signature
   0      6      0    this       Lscala/collection/mutable/ListBuffer;
   0      6      1    p       Lscala/Function1;


public java.lang.Object partialMap(scala.PartialFunction, scala.collection.generic.CanBuildFrom);
  Code:
   Stack=3, Locals=3, Args_size=3
   0:	aload_0
   1:	aload_1
   2:	aload_2
   3:	invokestatic	#588; //Method scala/collection/TraversableLike$class.partialMap:(Lscala/collection/TraversableLike;Lscala/PartialFunction;Lscala/collection/generic/CanBuildFrom;)Ljava/lang/Object;
   6:	areturn
  LineNumberTable: 
   line 27: 0

  LocalVariableTable: 
   Start  Length  Slot  Name   Signature
   0      7      0    this       Lscala/collection/mutable/ListBuffer;
   0      7      1    pf       Lscala/PartialFunction;
   0      7      2    bf       Lscala/collection/generic/CanBuildFrom;


public java.lang.Object filterNot(scala.Function1);
  Code:
   Stack=2, Locals=2, Args_size=2
   0:	aload_0
   1:	aload_1
   2:	invokestatic	#595; //Method scala/collection/TraversableLike$class.filterNot:(Lscala/collection/TraversableLike;Lscala/Function1;)Ljava/lang/Object;
   5:	areturn
  LineNumberTable: 
   line 27: 0

  LocalVariableTable: 
   Start  Length  Slot  Name   Signature
   0      6      0    this       Lscala/collection/mutable/ListBuffer;
   0      6      1    p       Lscala/Function1;


public java.lang.Object filter(scala.Function1);
  Code:
   Stack=2, Locals=2, Args_size=2
   0:	aload_0
   1:	aload_1
   2:	invokestatic	#598; //Method scala/collection/TraversableLike$class.filter:(Lscala/collection/TraversableLike;Lscala/Function1;)Ljava/lang/Object;
   5:	areturn
  LineNumberTable: 
   line 27: 0

  LocalVariableTable: 
   Start  Length  Slot  Name   Signature
   0      6      0    this       Lscala/collection/mutable/ListBuffer;
   0      6      1    p       Lscala/Function1;


public java.lang.Object flatMap(scala.Function1, scala.collection.generic.CanBuildFrom);
  Code:
   Stack=3, Locals=3, Args_size=3
   0:	aload_0
   1:	aload_1
   2:	aload_2
   3:	invokestatic	#603; //Method scala/collection/TraversableLike$class.flatMap:(Lscala/collection/TraversableLike;Lscala/Function1;Lscala/collection/generic/CanBuildFrom;)Ljava/lang/Object;
   6:	areturn
  LineNumberTable: 
   line 27: 0

  LocalVariableTable: 
   Start  Length  Slot  Name   Signature
   0      7      0    this       Lscala/collection/mutable/ListBuffer;
   0      7      1    f       Lscala/Function1;
   0      7      2    bf       Lscala/collection/generic/CanBuildFrom;


public java.lang.Object map(scala.Function1, scala.collection.generic.CanBuildFrom);
  Code:
   Stack=3, Locals=3, Args_size=3
   0:	aload_0
   1:	aload_1
   2:	aload_2
   3:	invokestatic	#606; //Method scala/collection/TraversableLike$class.map:(Lscala/collection/TraversableLike;Lscala/Function1;Lscala/collection/generic/CanBuildFrom;)Ljava/lang/Object;
   6:	areturn
  LineNumberTable: 
   line 27: 0

  LocalVariableTable: 
   Start  Length  Slot  Name   Signature
   0      7      0    this       Lscala/collection/mutable/ListBuffer;
   0      7      1    f       Lscala/Function1;
   0      7      2    bf       Lscala/collection/generic/CanBuildFrom;


public java.lang.Object $plus$plus(scala.collection.Iterator, scala.collection.generic.CanBuildFrom);
  Code:
   Stack=3, Locals=3, Args_size=3
   0:	aload_0
   1:	aload_1
   2:	aload_2
   3:	invokestatic	#610; //Method scala/collection/TraversableLike$class.$plus$plus:(Lscala/collection/TraversableLike;Lscala/collection/Iterator;Lscala/collection/generic/CanBuildFrom;)Ljava/lang/Object;
   6:	areturn
  LineNumberTable: 
   line 27: 0

  LocalVariableTable: 
   Start  Length  Slot  Name   Signature
   0      7      0    this       Lscala/collection/mutable/ListBuffer;
   0      7      1    that       Lscala/collection/Iterator;
   0      7      2    bf       Lscala/collection/generic/CanBuildFrom;


public java.lang.Object $plus$plus(scala.collection.Traversable, scala.collection.generic.CanBuildFrom);
  Code:
   Stack=3, Locals=3, Args_size=3
   0:	aload_0
   1:	aload_1
   2:	aload_2
   3:	invokestatic	#614; //Method scala/collection/TraversableLike$class.$plus$plus:(Lscala/collection/TraversableLike;Lscala/collection/Traversable;Lscala/collection/generic/CanBuildFrom;)Ljava/lang/Object;
   6:	areturn
  LineNumberTable: 
   line 27: 0

  LocalVariableTable: 
   Start  Length  Slot  Name   Signature
   0      7      0    this       Lscala/collection/mutable/ListBuffer;
   0      7      1    that       Lscala/collection/Traversable;
   0      7      2    bf       Lscala/collection/generic/CanBuildFrom;


public java.lang.Object repr();
  Code:
   Stack=1, Locals=1, Args_size=1
   0:	aload_0
   1:	invokestatic	#616; //Method scala/collection/TraversableLike$class.repr:(Lscala/collection/TraversableLike;)Ljava/lang/Object;
   4:	areturn
  LineNumberTable: 
   line 27: 0


public scala.collection.Traversable transpose(scala.Function1);
  Code:
   Stack=2, Locals=2, Args_size=2
   0:	aload_0
   1:	aload_1
   2:	invokestatic	#621; //Method scala/collection/generic/GenericTraversableTemplate$class.transpose:(Lscala/collection/generic/GenericTraversableTemplate;Lscala/Function1;)Lscala/collection/Traversable;
   5:	areturn
  LineNumberTable: 
   line 27: 0

  LocalVariableTable: 
   Start  Length  Slot  Name   Signature
   0      6      0    this       Lscala/collection/mutable/ListBuffer;
   0      6      1    asTraversable       Lscala/Function1;


public scala.collection.Traversable flatten(scala.Function1);
  Code:
   Stack=2, Locals=2, Args_size=2
   0:	aload_0
   1:	aload_1
   2:	invokestatic	#625; //Method scala/collection/generic/GenericTraversableTemplate$class.flatten:(Lscala/collection/generic/GenericTraversableTemplate;Lscala/Function1;)Lscala/collection/Traversable;
   5:	areturn
  LineNumberTable: 
   line 27: 0

  LocalVariableTable: 
   Start  Length  Slot  Name   Signature
   0      6      0    this       Lscala/collection/mutable/ListBuffer;
   0      6      1    asTraversable       Lscala/Function1;


public scala.Tuple2 unzip(scala.Function1);
  Code:
   Stack=2, Locals=2, Args_size=2
   0:	aload_0
   1:	aload_1
   2:	invokestatic	#629; //Method scala/collection/generic/GenericTraversableTemplate$class.unzip:(Lscala/collection/generic/GenericTraversableTemplate;Lscala/Function1;)Lscala/Tuple2;
   5:	areturn
  LineNumberTable: 
   line 27: 0

  LocalVariableTable: 
   Start  Length  Slot  Name   Signature
   0      6      0    this       Lscala/collection/mutable/ListBuffer;
   0      6      1    asPair       Lscala/Function1;


public scala.collection.mutable.Builder genericBuilder();
  Code:
   Stack=1, Locals=1, Args_size=1
   0:	aload_0
   1:	invokestatic	#635; //Method scala/collection/generic/GenericTraversableTemplate$class.genericBuilder:(Lscala/collection/generic/GenericTraversableTemplate;)Lscala/collection/mutable/Builder;
   4:	areturn
  LineNumberTable: 
   line 27: 0


public scala.collection.mutable.Builder newBuilder();
  Code:
   Stack=1, Locals=1, Args_size=1
   0:	aload_0
   1:	invokestatic	#638; //Method scala/collection/generic/GenericTraversableTemplate$class.newBuilder:(Lscala/collection/generic/GenericTraversableTemplate;)Lscala/collection/mutable/Builder;
   4:	areturn
  LineNumberTable: 
   line 27: 0


public scala.Option firstOption();
  Code:
   Stack=1, Locals=1, Args_size=1
   0:	aload_0
   1:	invokestatic	#642; //Method scala/collection/IterableLike$class.firstOption:(Lscala/collection/IterableLike;)Lscala/Option;
   4:	areturn
  LineNumberTable: 
   line 27: 0

  Deprecated: true

public java.lang.Object first();
  Code:
   Stack=1, Locals=1, Args_size=1
   0:	aload_0
   1:	invokestatic	#647; //Method scala/collection/IterableLike$class.first:(Lscala/collection/IterableLike;)Ljava/lang/Object;
   4:	areturn
  LineNumberTable: 
   line 27: 0

  Deprecated: true

public boolean canEqual(java.lang.Object);
  Code:
   Stack=2, Locals=2, Args_size=2
   0:	aload_0
   1:	aload_1
   2:	invokestatic	#651; //Method scala/collection/IterableLike$class.canEqual:(Lscala/collection/IterableLike;Ljava/lang/Object;)Z
   5:	ireturn
  LineNumberTable: 
   line 27: 0

  LocalVariableTable: 
   Start  Length  Slot  Name   Signature
   0      6      0    this       Lscala/collection/mutable/ListBuffer;
   0      6      1    that       Ljava/lang/Object;


public java.lang.Object zipWithIndex(scala.collection.generic.CanBuildFrom);
  Code:
   Stack=2, Locals=2, Args_size=2
   0:	aload_0
   1:	aload_1
   2:	invokestatic	#656; //Method scala/collection/IterableLike$class.zipWithIndex:(Lscala/collection/IterableLike;Lscala/collection/generic/CanBuildFrom;)Ljava/lang/Object;
   5:	areturn
  LineNumberTable: 
   line 27: 0

  LocalVariableTable: 
   Start  Length  Slot  Name   Signature
   0      6      0    this       Lscala/collection/mutable/ListBuffer;
   0      6      1    bf       Lscala/collection/generic/CanBuildFrom;


public java.lang.Object zipAll(scala.collection.Iterable, java.lang.Object, java.lang.Object, scala.collection.generic.CanBuildFrom);
  Code:
   Stack=5, Locals=5, Args_size=5
   0:	aload_0
   1:	aload_1
   2:	aload_2
   3:	aload_3
   4:	aload	4
   6:	invokestatic	#661; //Method scala/collection/IterableLike$class.zipAll:(Lscala/collection/IterableLike;Lscala/collection/Iterable;Ljava/lang/Object;Ljava/lang/Object;Lscala/collection/generic/CanBuildFrom;)Ljava/lang/Object;
   9:	areturn
  LineNumberTable: 
   line 27: 0

  LocalVariableTable: 
   Start  Length  Slot  Name   Signature
   0      10      0    this       Lscala/collection/mutable/ListBuffer;
   0      10      1    that       Lscala/collection/Iterable;
   0      10      2    thisElem       Ljava/lang/Object;
   0      10      3    thatElem       Ljava/lang/Object;
   0      10      4    bf       Lscala/collection/generic/CanBuildFrom;


public java.lang.Object zip(scala.collection.Iterable, scala.collection.generic.CanBuildFrom);
  Code:
   Stack=3, Locals=3, Args_size=3
   0:	aload_0
   1:	aload_1
   2:	aload_2
   3:	invokestatic	#669; //Method scala/collection/IterableLike$class.zip:(Lscala/collection/IterableLike;Lscala/collection/Iterable;Lscala/collection/generic/CanBuildFrom;)Ljava/lang/Object;
   6:	areturn
  LineNumberTable: 
   line 27: 0

  LocalVariableTable: 
   Start  Length  Slot  Name   Signature
   0      7      0    this       Lscala/collection/mutable/ListBuffer;
   0      7      1    that       Lscala/collection/Iterable;
   0      7      2    bf       Lscala/collection/generic/CanBuildFrom;


public java.lang.Object dropRight(int);
  Code:
   Stack=2, Locals=2, Args_size=2
   0:	aload_0
   1:	iload_1
   2:	invokestatic	#673; //Method scala/collection/IterableLike$class.dropRight:(Lscala/collection/IterableLike;I)Ljava/lang/Object;
   5:	areturn
  LineNumberTable: 
   line 27: 0

  LocalVariableTable: 
   Start  Length  Slot  Name   Signature
   0      6      0    this       Lscala/collection/mutable/ListBuffer;
   0      6      1    n       I


public java.lang.Object takeRight(int);
  Code:
   Stack=2, Locals=2, Args_size=2
   0:	aload_0
   1:	iload_1
   2:	invokestatic	#676; //Method scala/collection/IterableLike$class.takeRight:(Lscala/collection/IterableLike;I)Ljava/lang/Object;
   5:	areturn
  LineNumberTable: 
   line 27: 0

  LocalVariableTable: 
   Start  Length  Slot  Name   Signature
   0      6      0    this       Lscala/collection/mutable/ListBuffer;
   0      6      1    n       I


public java.lang.Object takeWhile(scala.Function1);
  Code:
   Stack=2, Locals=2, Args_size=2
   0:	aload_0
   1:	aload_1
   2:	invokestatic	#680; //Method scala/collection/IterableLike$class.takeWhile:(Lscala/collection/IterableLike;Lscala/Function1;)Ljava/lang/Object;
   5:	areturn
  LineNumberTable: 
   line 27: 0

  LocalVariableTable: 
   Start  Length  Slot  Name   Signature
   0      6      0    this       Lscala/collection/mutable/ListBuffer;
   0      6      1    p       Lscala/Function1;


public java.lang.Object slice(int, int);
  Code:
   Stack=3, Locals=3, Args_size=3
   0:	aload_0
   1:	iload_1
   2:	iload_2
   3:	invokestatic	#685; //Method scala/collection/IterableLike$class.slice:(Lscala/collection/IterableLike;II)Ljava/lang/Object;
   6:	areturn
  LineNumberTable: 
   line 27: 0

  LocalVariableTable: 
   Start  Length  Slot  Name   Signature
   0      7      0    this       Lscala/collection/mutable/ListBuffer;
   0      7      1    from       I
   0      7      2    until       I


public java.lang.Object take(int);
  Code:
   Stack=2, Locals=2, Args_size=2
   0:	aload_0
   1:	iload_1
   2:	invokestatic	#688; //Method scala/collection/IterableLike$class.take:(Lscala/collection/IterableLike;I)Ljava/lang/Object;
   5:	areturn
  LineNumberTable: 
   line 27: 0

  LocalVariableTable: 
   Start  Length  Slot  Name   Signature
   0      6      0    this       Lscala/collection/mutable/ListBuffer;
   0      6      1    n       I


public scala.collection.Iterable toIterable();
  Code:
   Stack=1, Locals=1, Args_size=1
   0:	aload_0
   1:	invokestatic	#692; //Method scala/collection/IterableLike$class.toIterable:(Lscala/collection/IterableLike;)Lscala/collection/Iterable;
   4:	areturn
  LineNumberTable: 
   line 27: 0


public scala.collection.Iterator elements();
  Code:
   Stack=1, Locals=1, Args_size=1
   0:	aload_0
   1:	invokestatic	#696; //Method scala/collection/IterableLike$class.elements:(Lscala/collection/IterableLike;)Lscala/collection/Iterator;
   4:	areturn
  LineNumberTable: 
   line 27: 0

  Deprecated: true

public scala.Function1 compose(scala.Function1);
  Code:
   Stack=2, Locals=2, Args_size=2
   0:	aload_0
   1:	aload_1
   2:	invokestatic	#700; //Method scala/Function1$class.compose:(Lscala/Function1;Lscala/Function1;)Lscala/Function1;
   5:	areturn
  LineNumberTable: 
   line 27: 0

  LocalVariableTable: 
   Start  Length  Slot  Name   Signature
   0      6      0    this       Lscala/collection/mutable/ListBuffer;
   0      6      1    g       Lscala/Function1;


public scala.Function1 lift();
  Code:
   Stack=1, Locals=1, Args_size=1
   0:	aload_0
   1:	invokestatic	#705; //Method scala/PartialFunction$class.lift:(Lscala/PartialFunction;)Lscala/Function1;
   4:	areturn
  LineNumberTable: 
   line 27: 0


public scala.PartialFunction andThen(scala.Function1);
  Code:
   Stack=2, Locals=2, Args_size=2
   0:	aload_0
   1:	aload_1
   2:	invokestatic	#708; //Method scala/PartialFunction$class.andThen:(Lscala/PartialFunction;Lscala/Function1;)Lscala/PartialFunction;
   5:	areturn
  LineNumberTable: 
   line 27: 0

  LocalVariableTable: 
   Start  Length  Slot  Name   Signature
   0      6      0    this       Lscala/collection/mutable/ListBuffer;
   0      6      1    k       Lscala/Function1;


public scala.PartialFunction orElse(scala.PartialFunction);
  Code:
   Stack=2, Locals=2, Args_size=2
   0:	aload_0
   1:	aload_1
   2:	invokestatic	#714; //Method scala/PartialFunction$class.orElse:(Lscala/PartialFunction;Lscala/PartialFunction;)Lscala/PartialFunction;
   5:	areturn
  LineNumberTable: 
   line 27: 0

  LocalVariableTable: 
   Start  Length  Slot  Name   Signature
   0      6      0    this       Lscala/collection/mutable/ListBuffer;
   0      6      1    that       Lscala/PartialFunction;


public java.lang.Object projection();
  Code:
   Stack=1, Locals=1, Args_size=1
   0:	aload_0
   1:	invokestatic	#718; //Method scala/collection/SeqLike$class.projection:(Lscala/collection/SeqLike;)Ljava/lang/Object;
   4:	areturn
  LineNumberTable: 
   line 27: 0

  Deprecated: true

public boolean equalsWith(scala.collection.Seq, scala.Function2);
  Code:
   Stack=3, Locals=3, Args_size=3
   0:	aload_0
   1:	aload_1
   2:	aload_2
   3:	invokestatic	#723; //Method scala/collection/SeqLike$class.equalsWith:(Lscala/collection/SeqLike;Lscala/collection/Seq;Lscala/Function2;)Z
   6:	ireturn
  LineNumberTable: 
   line 27: 0

  LocalVariableTable: 
   Start  Length  Slot  Name   Signature
   0      7      0    this       Lscala/collection/mutable/ListBuffer;
   0      7      1    that       Lscala/collection/Seq;
   0      7      2    f       Lscala/Function2;

  Deprecated: true

public int findLastIndexOf(scala.Function1);
  Code:
   Stack=2, Locals=2, Args_size=2
   0:	aload_0
   1:	aload_1
   2:	invokestatic	#728; //Method scala/collection/SeqLike$class.findLastIndexOf:(Lscala/collection/SeqLike;Lscala/Function1;)I
   5:	ireturn
  LineNumberTable: 
   line 27: 0

  LocalVariableTable: 
   Start  Length  Slot  Name   Signature
   0      6      0    this       Lscala/collection/mutable/ListBuffer;
   0      6      1    p       Lscala/Function1;


public java.lang.String toString();
  Code:
   Stack=1, Locals=1, Args_size=1
   0:	aload_0
   1:	invokestatic	#731; //Method scala/collection/SeqLike$class.toString:(Lscala/collection/SeqLike;)Ljava/lang/String;
   4:	areturn
  LineNumberTable: 
   line 27: 0


public int hashCode();
  Code:
   Stack=1, Locals=1, Args_size=1
   0:	aload_0
   1:	invokestatic	#735; //Method scala/collection/SeqLike$class.hashCode:(Lscala/collection/SeqLike;)I
   4:	ireturn
  LineNumberTable: 
   line 27: 0


public scala.collection.SeqView view(int, int);
  Code:
   Stack=3, Locals=3, Args_size=3
   0:	aload_0
   1:	iload_1
   2:	iload_2
   3:	invokestatic	#738; //Method scala/collection/SeqLike$class.view:(Lscala/collection/SeqLike;II)Lscala/collection/SeqView;
   6:	areturn
  LineNumberTable: 
   line 27: 0

  LocalVariableTable: 
   Start  Length  Slot  Name   Signature
   0      7      0    this       Lscala/collection/mutable/ListBuffer;
   0      7      1    from       I
   0      7      2    until       I


public java.lang.Object view();
  Code:
   Stack=1, Locals=1, Args_size=1
   0:	aload_0
   1:	invokestatic	#740; //Method scala/collection/SeqLike$class.view:(Lscala/collection/SeqLike;)Ljava/lang/Object;
   4:	areturn
  LineNumberTable: 
   line 27: 0


public java.lang.Object sortBy(scala.Function1, scala.math.Ordering);
  Code:
   Stack=3, Locals=3, Args_size=3
   0:	aload_0
   1:	aload_1
   2:	aload_2
   3:	invokestatic	#745; //Method scala/collection/SeqLike$class.sortBy:(Lscala/collection/SeqLike;Lscala/Function1;Lscala/math/Ordering;)Ljava/lang/Object;
   6:	areturn
  LineNumberTable: 
   line 27: 0

  LocalVariableTable: 
   Start  Length  Slot  Name   Signature
   0      7      0    this       Lscala/collection/mutable/ListBuffer;
   0      7      1    f       Lscala/Function1;
   0      7      2    ord       Lscala/math/Ordering;


public java.lang.Object sortWith(scala.math.Ordering);
  Code:
   Stack=2, Locals=2, Args_size=2
   0:	aload_0
   1:	aload_1
   2:	invokestatic	#750; //Method scala/collection/SeqLike$class.sortWith:(Lscala/collection/SeqLike;Lscala/math/Ordering;)Ljava/lang/Object;
   5:	areturn
  LineNumberTable: 
   line 27: 0

  LocalVariableTable: 
   Start  Length  Slot  Name   Signature
   0      6      0    this       Lscala/collection/mutable/ListBuffer;
   0      6      1    ord       Lscala/math/Ordering;


public java.lang.Object sortWith(scala.Function2);
  Code:
   Stack=2, Locals=2, Args_size=2
   0:	aload_0
   1:	aload_1
   2:	invokestatic	#754; //Method scala/collection/SeqLike$class.sortWith:(Lscala/collection/SeqLike;Lscala/Function2;)Ljava/lang/Object;
   5:	areturn
  LineNumberTable: 
   line 27: 0

  LocalVariableTable: 
   Start  Length  Slot  Name   Signature
   0      6      0    this       Lscala/collection/mutable/ListBuffer;
   0      6      1    lt       Lscala/Function2;


public boolean corresponds(scala.collection.Seq, scala.Function2);
  Code:
   Stack=3, Locals=3, Args_size=3
   0:	aload_0
   1:	aload_1
   2:	aload_2
   3:	invokestatic	#758; //Method scala/collection/SeqLike$class.corresponds:(Lscala/collection/SeqLike;Lscala/collection/Seq;Lscala/Function2;)Z
   6:	ireturn
  LineNumberTable: 
   line 27: 0

  LocalVariableTable: 
   Start  Length  Slot  Name   Signature
   0      7      0    this       Lscala/collection/mutable/ListBuffer;
   0      7      1    that       Lscala/collection/Seq;
   0      7      2    p       Lscala/Function2;


public java.lang.Object padTo(int, java.lang.Object, scala.collection.generic.CanBuildFrom);
  Code:
   Stack=4, Locals=4, Args_size=4
   0:	aload_0
   1:	iload_1
   2:	aload_2
   3:	aload_3
   4:	invokestatic	#763; //Method scala/collection/SeqLike$class.padTo:(Lscala/collection/SeqLike;ILjava/lang/Object;Lscala/collection/generic/CanBuildFrom;)Ljava/lang/Object;
   7:	areturn
  LineNumberTable: 
   line 27: 0

  LocalVariableTable: 
   Start  Length  Slot  Name   Signature
   0      8      0    this       Lscala/collection/mutable/ListBuffer;
   0      8      1    len       I
   0      8      2    elem       Ljava/lang/Object;
   0      8      3    bf       Lscala/collection/generic/CanBuildFrom;


public java.lang.Object $colon$plus(java.lang.Object, scala.collection.generic.CanBuildFrom);
  Code:
   Stack=3, Locals=3, Args_size=3
   0:	aload_0
   1:	aload_1
   2:	aload_2
   3:	invokestatic	#768; //Method scala/collection/SeqLike$class.$colon$plus:(Lscala/collection/SeqLike;Ljava/lang/Object;Lscala/collection/generic/CanBuildFrom;)Ljava/lang/Object;
   6:	areturn
  LineNumberTable: 
   line 27: 0

  LocalVariableTable: 
   Start  Length  Slot  Name   Signature
   0      7      0    this       Lscala/collection/mutable/ListBuffer;
   0      7      1    elem       Ljava/lang/Object;
   0      7      2    bf       Lscala/collection/generic/CanBuildFrom;


public java.lang.Object $plus$colon(java.lang.Object, scala.collection.generic.CanBuildFrom);
  Code:
   Stack=3, Locals=3, Args_size=3
   0:	aload_0
   1:	aload_1
   2:	aload_2
   3:	invokestatic	#771; //Method scala/collection/SeqLike$class.$plus$colon:(Lscala/collection/SeqLike;Ljava/lang/Object;Lscala/collection/generic/CanBuildFrom;)Ljava/lang/Object;
   6:	areturn
  LineNumberTable: 
   line 27: 0

  LocalVariableTable: 
   Start  Length  Slot  Name   Signature
   0      7      0    this       Lscala/collection/mutable/ListBuffer;
   0      7      1    elem       Ljava/lang/Object;
   0      7      2    bf       Lscala/collection/generic/CanBuildFrom;


public java.lang.Object updated(int, java.lang.Object, scala.collection.generic.CanBuildFrom);
  Code:
   Stack=4, Locals=4, Args_size=4
   0:	aload_0
   1:	iload_1
   2:	aload_2
   3:	aload_3
   4:	invokestatic	#774; //Method scala/collection/SeqLike$class.updated:(Lscala/collection/SeqLike;ILjava/lang/Object;Lscala/collection/generic/CanBuildFrom;)Ljava/lang/Object;
   7:	areturn
  LineNumberTable: 
   line 27: 0

  LocalVariableTable: 
   Start  Length  Slot  Name   Signature
   0      8      0    this       Lscala/collection/mutable/ListBuffer;
   0      8      1    index       I
   0      8      2    elem       Ljava/lang/Object;
   0      8      3    bf       Lscala/collection/generic/CanBuildFrom;


public java.lang.Object patch(int, scala.collection.Seq, int, scala.collection.generic.CanBuildFrom);
  Code:
   Stack=5, Locals=5, Args_size=5
   0:	aload_0
   1:	iload_1
   2:	aload_2
   3:	iload_3
   4:	aload	4
   6:	invokestatic	#780; //Method scala/collection/SeqLike$class.patch:(Lscala/collection/SeqLike;ILscala/collection/Seq;ILscala/collection/generic/CanBuildFrom;)Ljava/lang/Object;
   9:	areturn
  LineNumberTable: 
   line 27: 0

  LocalVariableTable: 
   Start  Length  Slot  Name   Signature
   0      10      0    this       Lscala/collection/mutable/ListBuffer;
   0      10      1    from       I
   0      10      2    patch       Lscala/collection/Seq;
   0      10      3    replaced       I
   0      10      4    bf       Lscala/collection/generic/CanBuildFrom;


public java.lang.Object removeDuplicates();
  Code:
   Stack=1, Locals=1, Args_size=1
   0:	aload_0
   1:	invokestatic	#784; //Method scala/collection/SeqLike$class.removeDuplicates:(Lscala/collection/SeqLike;)Ljava/lang/Object;
   4:	areturn
  LineNumberTable: 
   line 27: 0


public java.lang.Object intersect(scala.collection.Seq);
  Code:
   Stack=2, Locals=2, Args_size=2
   0:	aload_0
   1:	aload_1
   2:	invokestatic	#789; //Method scala/collection/SeqLike$class.intersect:(Lscala/collection/SeqLike;Lscala/collection/Seq;)Ljava/lang/Object;
   5:	areturn
  LineNumberTable: 
   line 27: 0

  LocalVariableTable: 
   Start  Length  Slot  Name   Signature
   0      6      0    this       Lscala/collection/mutable/ListBuffer;
   0      6      1    that       Lscala/collection/Seq;


public java.lang.Object diff(scala.collection.Seq);
  Code:
   Stack=2, Locals=2, Args_size=2
   0:	aload_0
   1:	aload_1
   2:	invokestatic	#792; //Method scala/collection/SeqLike$class.diff:(Lscala/collection/SeqLike;Lscala/collection/Seq;)Ljava/lang/Object;
   5:	areturn
  LineNumberTable: 
   line 27: 0

  LocalVariableTable: 
   Start  Length  Slot  Name   Signature
   0      6      0    this       Lscala/collection/mutable/ListBuffer;
   0      6      1    that       Lscala/collection/Seq;


public java.lang.Object union(scala.collection.Seq, scala.collection.generic.CanBuildFrom);
  Code:
   Stack=3, Locals=3, Args_size=3
   0:	aload_0
   1:	aload_1
   2:	aload_2
   3:	invokestatic	#797; //Method scala/collection/SeqLike$class.union:(Lscala/collection/SeqLike;Lscala/collection/Seq;Lscala/collection/generic/CanBuildFrom;)Ljava/lang/Object;
   6:	areturn
  LineNumberTable: 
   line 27: 0

  LocalVariableTable: 
   Start  Length  Slot  Name   Signature
   0      7      0    this       Lscala/collection/mutable/ListBuffer;
   0      7      1    that       Lscala/collection/Seq;
   0      7      2    bf       Lscala/collection/generic/CanBuildFrom;


public boolean containsSlice(scala.collection.Seq);
  Code:
   Stack=2, Locals=2, Args_size=2
   0:	aload_0
   1:	aload_1
   2:	invokestatic	#802; //Method scala/collection/SeqLike$class.containsSlice:(Lscala/collection/SeqLike;Lscala/collection/Seq;)Z
   5:	ireturn
  LineNumberTable: 
   line 27: 0

  LocalVariableTable: 
   Start  Length  Slot  Name   Signature
   0      6      0    this       Lscala/collection/mutable/ListBuffer;
   0      6      1    that       Lscala/collection/Seq;


public int lastIndexOfSlice(scala.collection.Seq, int);
  Code:
   Stack=3, Locals=3, Args_size=3
   0:	aload_0
   1:	aload_1
   2:	iload_2
   3:	invokestatic	#807; //Method scala/collection/SeqLike$class.lastIndexOfSlice:(Lscala/collection/SeqLike;Lscala/collection/Seq;I)I
   6:	ireturn
  LineNumberTable: 
   line 27: 0

  LocalVariableTable: 
   Start  Length  Slot  Name   Signature
   0      7      0    this       Lscala/collection/mutable/ListBuffer;
   0      7      1    that       Lscala/collection/Seq;
   0      7      2    end       I


public int lastIndexOfSlice(scala.collection.Seq);
  Code:
   Stack=2, Locals=2, Args_size=2
   0:	aload_0
   1:	aload_1
   2:	invokestatic	#812; //Method scala/collection/SeqLike$class.lastIndexOfSlice:(Lscala/collection/SeqLike;Lscala/collection/Seq;)I
   5:	ireturn
  LineNumberTable: 
   line 27: 0

  LocalVariableTable: 
   Start  Length  Slot  Name   Signature
   0      6      0    this       Lscala/collection/mutable/ListBuffer;
   0      6      1    that       Lscala/collection/Seq;


public int indexOfSlice(scala.collection.Seq, int);
  Code:
   Stack=3, Locals=3, Args_size=3
   0:	aload_0
   1:	aload_1
   2:	iload_2
   3:	invokestatic	#815; //Method scala/collection/SeqLike$class.indexOfSlice:(Lscala/collection/SeqLike;Lscala/collection/Seq;I)I
   6:	ireturn
  LineNumberTable: 
   line 27: 0

  LocalVariableTable: 
   Start  Length  Slot  Name   Signature
   0      7      0    this       Lscala/collection/mutable/ListBuffer;
   0      7      1    that       Lscala/collection/Seq;
   0      7      2    from       I


public boolean startsWith(scala.collection.Seq);
  Code:
   Stack=2, Locals=2, Args_size=2
   0:	aload_0
   1:	aload_1
   2:	invokestatic	#818; //Method scala/collection/SeqLike$class.startsWith:(Lscala/collection/SeqLike;Lscala/collection/Seq;)Z
   5:	ireturn
  LineNumberTable: 
   line 27: 0

  LocalVariableTable: 
   Start  Length  Slot  Name   Signature
   0      6      0    this       Lscala/collection/mutable/ListBuffer;
   0      6      1    that       Lscala/collection/Seq;


public scala.collection.Iterator reversedElements();
  Code:
   Stack=1, Locals=1, Args_size=1
   0:	aload_0
   1:	invokestatic	#822; //Method scala/collection/SeqLike$class.reversedElements:(Lscala/collection/SeqLike;)Lscala/collection/Iterator;
   4:	areturn
  LineNumberTable: 
   line 27: 0

  Deprecated: true

public java.lang.Object reverseMap(scala.Function1, scala.collection.generic.CanBuildFrom);
  Code:
   Stack=3, Locals=3, Args_size=3
   0:	aload_0
   1:	aload_1
   2:	aload_2
   3:	invokestatic	#826; //Method scala/collection/SeqLike$class.reverseMap:(Lscala/collection/SeqLike;Lscala/Function1;Lscala/collection/generic/CanBuildFrom;)Ljava/lang/Object;
   6:	areturn
  LineNumberTable: 
   line 27: 0

  LocalVariableTable: 
   Start  Length  Slot  Name   Signature
   0      7      0    this       Lscala/collection/mutable/ListBuffer;
   0      7      1    f       Lscala/Function1;
   0      7      2    bf       Lscala/collection/generic/CanBuildFrom;


public java.lang.Object reverse();
  Code:
   Stack=1, Locals=1, Args_size=1
   0:	aload_0
   1:	invokestatic	#828; //Method scala/collection/SeqLike$class.reverse:(Lscala/collection/SeqLike;)Ljava/lang/Object;
   4:	areturn
  LineNumberTable: 
   line 27: 0


public int lastIndexWhere(scala.Function1, int);
  Code:
   Stack=3, Locals=3, Args_size=3
   0:	aload_0
   1:	aload_1
   2:	iload_2
   3:	invokestatic	#833; //Method scala/collection/SeqLike$class.lastIndexWhere:(Lscala/collection/SeqLike;Lscala/Function1;I)I
   6:	ireturn
  LineNumberTable: 
   line 27: 0

  LocalVariableTable: 
   Start  Length  Slot  Name   Signature
   0      7      0    this       Lscala/collection/mutable/ListBuffer;
   0      7      1    p       Lscala/Function1;
   0      7      2    end       I


public int lastIndexWhere(scala.Function1);
  Code:
   Stack=2, Locals=2, Args_size=2
   0:	aload_0
   1:	aload_1
   2:	invokestatic	#835; //Method scala/collection/SeqLike$class.lastIndexWhere:(Lscala/collection/SeqLike;Lscala/Function1;)I
   5:	ireturn
  LineNumberTable: 
   line 27: 0

  LocalVariableTable: 
   Start  Length  Slot  Name   Signature
   0      6      0    this       Lscala/collection/mutable/ListBuffer;
   0      6      1    p       Lscala/Function1;


public int lastIndexOf(java.lang.Object, int);
  Code:
   Stack=3, Locals=3, Args_size=3
   0:	aload_0
   1:	aload_1
   2:	iload_2
   3:	invokestatic	#840; //Method scala/collection/SeqLike$class.lastIndexOf:(Lscala/collection/SeqLike;Ljava/lang/Object;I)I
   6:	ireturn
  LineNumberTable: 
   line 27: 0

  LocalVariableTable: 
   Start  Length  Slot  Name   Signature
   0      7      0    this       Lscala/collection/mutable/ListBuffer;
   0      7      1    elem       Ljava/lang/Object;
   0      7      2    end       I


public int lastIndexOf(java.lang.Object);
  Code:
   Stack=2, Locals=2, Args_size=2
   0:	aload_0
   1:	aload_1
   2:	invokestatic	#843; //Method scala/collection/SeqLike$class.lastIndexOf:(Lscala/collection/SeqLike;Ljava/lang/Object;)I
   5:	ireturn
  LineNumberTable: 
   line 27: 0

  LocalVariableTable: 
   Start  Length  Slot  Name   Signature
   0      6      0    this       Lscala/collection/mutable/ListBuffer;
   0      6      1    elem       Ljava/lang/Object;


public int indexOf(java.lang.Object);
  Code:
   Stack=2, Locals=2, Args_size=2
   0:	aload_0
   1:	aload_1
   2:	invokestatic	#846; //Method scala/collection/SeqLike$class.indexOf:(Lscala/collection/SeqLike;Ljava/lang/Object;)I
   5:	ireturn
  LineNumberTable: 
   line 27: 0

  LocalVariableTable: 
   Start  Length  Slot  Name   Signature
   0      6      0    this       Lscala/collection/mutable/ListBuffer;
   0      6      1    elem       Ljava/lang/Object;


public int findIndexOf(scala.Function1);
  Code:
   Stack=2, Locals=2, Args_size=2
   0:	aload_0
   1:	aload_1
   2:	invokestatic	#849; //Method scala/collection/SeqLike$class.findIndexOf:(Lscala/collection/SeqLike;Lscala/Function1;)I
   5:	ireturn
  LineNumberTable: 
   line 27: 0

  LocalVariableTable: 
   Start  Length  Slot  Name   Signature
   0      6      0    this       Lscala/collection/mutable/ListBuffer;
   0      6      1    p       Lscala/Function1;


public int indexWhere(scala.Function1);
  Code:
   Stack=2, Locals=2, Args_size=2
   0:	aload_0
   1:	aload_1
   2:	invokestatic	#852; //Method scala/collection/SeqLike$class.indexWhere:(Lscala/collection/SeqLike;Lscala/Function1;)I
   5:	ireturn
  LineNumberTable: 
   line 27: 0

  LocalVariableTable: 
   Start  Length  Slot  Name   Signature
   0      6      0    this       Lscala/collection/mutable/ListBuffer;
   0      6      1    p       Lscala/Function1;


public int size();
  Code:
   Stack=1, Locals=1, Args_size=1
   0:	aload_0
   1:	invokestatic	#855; //Method scala/collection/SeqLike$class.size:(Lscala/collection/SeqLike;)I
   4:	ireturn
  LineNumberTable: 
   line 27: 0


public scala.collection.Seq toCollection(java.lang.Object);
  Code:
   Stack=2, Locals=2, Args_size=2
   0:	aload_0
   1:	aload_1
   2:	invokestatic	#858; //Method scala/collection/SeqLike$class.toCollection:(Lscala/collection/SeqLike;Ljava/lang/Object;)Lscala/collection/Seq;
   5:	areturn
  LineNumberTable: 
   line 27: 0

  LocalVariableTable: 
   Start  Length  Slot  Name   Signature
   0      6      0    this       Lscala/collection/mutable/ListBuffer;
   0      6      1    repr       Ljava/lang/Object;


public scala.collection.Seq thisCollection();
  Code:
   Stack=1, Locals=1, Args_size=1
   0:	aload_0
   1:	invokestatic	#861; //Method scala/collection/SeqLike$class.thisCollection:(Lscala/collection/SeqLike;)Lscala/collection/Seq;
   4:	areturn
  LineNumberTable: 
   line 27: 0


public scala.collection.generic.Growable $plus$plus$eq(scala.collection.Traversable);
  Code:
   Stack=2, Locals=2, Args_size=2
   0:	aload_0
   1:	aload_1
   2:	invokestatic	#864; //Method scala/collection/generic/Growable$class.$plus$plus$eq:(Lscala/collection/generic/Growable;Lscala/collection/Traversable;)Lscala/collection/generic/Growable;
   5:	areturn
  LineNumberTable: 
   line 27: 0

  LocalVariableTable: 
   Start  Length  Slot  Name   Signature
   0      6      0    this       Lscala/collection/mutable/ListBuffer;
   0      6      1    elems       Lscala/collection/Traversable;


public scala.collection.generic.Growable $plus$plus$eq(scala.collection.Iterator);
  Code:
   Stack=2, Locals=2, Args_size=2
   0:	aload_0
   1:	aload_1
   2:	invokestatic	#868; //Method scala/collection/generic/Growable$class.$plus$plus$eq:(Lscala/collection/generic/Growable;Lscala/collection/Iterator;)Lscala/collection/generic/Growable;
   5:	areturn
  LineNumberTable: 
   line 27: 0

  LocalVariableTable: 
   Start  Length  Slot  Name   Signature
   0      6      0    this       Lscala/collection/mutable/ListBuffer;
   0      6      1    iter       Lscala/collection/Iterator;


public scala.collection.generic.Growable $plus$eq(java.lang.Object, java.lang.Object, scala.collection.Seq);
  Code:
   Stack=4, Locals=4, Args_size=4
   0:	aload_0
   1:	aload_1
   2:	aload_2
   3:	aload_3
   4:	invokestatic	#872; //Method scala/collection/generic/Growable$class.$plus$eq:(Lscala/collection/generic/Growable;Ljava/lang/Object;Ljava/lang/Object;Lscala/collection/Seq;)Lscala/collection/generic/Growable;
   7:	areturn
  LineNumberTable: 
   line 27: 0

  LocalVariableTable: 
   Start  Length  Slot  Name   Signature
   0      8      0    this       Lscala/collection/mutable/ListBuffer;
   0      8      1    elem1       Ljava/lang/Object;
   0      8      2    elem2       Ljava/lang/Object;
   0      8      3    elems       Lscala/collection/Seq;


public scala.collection.generic.Shrinkable $minus$minus$eq(scala.collection.Traversable);
  Code:
   Stack=2, Locals=2, Args_size=2
   0:	aload_0
   1:	aload_1
   2:	invokestatic	#877; //Method scala/collection/generic/Shrinkable$class.$minus$minus$eq:(Lscala/collection/generic/Shrinkable;Lscala/collection/Traversable;)Lscala/collection/generic/Shrinkable;
   5:	areturn
  LineNumberTable: 
   line 27: 0

  LocalVariableTable: 
   Start  Length  Slot  Name   Signature
   0      6      0    this       Lscala/collection/mutable/ListBuffer;
   0      6      1    iter       Lscala/collection/Traversable;


public scala.collection.generic.Shrinkable $minus$minus$eq(scala.collection.Iterator);
  Code:
   Stack=2, Locals=2, Args_size=2
   0:	aload_0
   1:	aload_1
   2:	invokestatic	#881; //Method scala/collection/generic/Shrinkable$class.$minus$minus$eq:(Lscala/collection/generic/Shrinkable;Lscala/collection/Iterator;)Lscala/collection/generic/Shrinkable;
   5:	areturn
  LineNumberTable: 
   line 27: 0

  LocalVariableTable: 
   Start  Length  Slot  Name   Signature
   0      6      0    this       Lscala/collection/mutable/ListBuffer;
   0      6      1    iter       Lscala/collection/Iterator;


public scala.collection.generic.Shrinkable $minus$eq(java.lang.Object, java.lang.Object, scala.collection.Seq);
  Code:
   Stack=4, Locals=4, Args_size=4
   0:	aload_0
   1:	aload_1
   2:	aload_2
   3:	aload_3
   4:	invokestatic	#885; //Method scala/collection/generic/Shrinkable$class.$minus$eq:(Lscala/collection/generic/Shrinkable;Ljava/lang/Object;Ljava/lang/Object;Lscala/collection/Seq;)Lscala/collection/generic/Shrinkable;
   7:	areturn
  LineNumberTable: 
   line 27: 0

  LocalVariableTable: 
   Start  Length  Slot  Name   Signature
   0      8      0    this       Lscala/collection/mutable/ListBuffer;
   0      8      1    elem1       Ljava/lang/Object;
   0      8      2    elem2       Ljava/lang/Object;
   0      8      3    elems       Lscala/collection/Seq;


public final java.lang.Object scala$collection$mutable$Cloneable$$super$clone();
  Code:
   Stack=1, Locals=1, Args_size=1
   0:	aload_0
   1:	invokespecial	#888; //Method java/lang/Object.clone:()Ljava/lang/Object;
   4:	areturn
  LineNumberTable: 
   line 27: 0


public scala.collection.mutable.BufferLike $minus$minus(scala.collection.Iterator);
  Code:
   Stack=2, Locals=2, Args_size=2
   0:	aload_0
   1:	aload_1
   2:	invokestatic	#891; //Method scala/collection/mutable/BufferLike$class.$minus$minus:(Lscala/collection/mutable/BufferLike;Lscala/collection/Iterator;)Lscala/collection/mutable/BufferLike;
   5:	areturn
  LineNumberTable: 
   line 27: 0

  LocalVariableTable: 
   Start  Length  Slot  Name   Signature
   0      6      0    this       Lscala/collection/mutable/ListBuffer;
   0      6      1    iter       Lscala/collection/Iterator;

  Deprecated: true

public final scala.collection.mutable.BufferLike $plus$colon(java.lang.Object);
  Code:
   Stack=2, Locals=2, Args_size=2
   0:	aload_0
   1:	aload_1
   2:	invokestatic	#894; //Method scala/collection/mutable/BufferLike$class.$plus$colon:(Lscala/collection/mutable/BufferLike;Ljava/lang/Object;)Lscala/collection/mutable/BufferLike;
   5:	areturn
  LineNumberTable: 
   line 27: 0

  LocalVariableTable: 
   Start  Length  Slot  Name   Signature
   0      6      0    this       Lscala/collection/mutable/ListBuffer;
   0      6      1    elem       Ljava/lang/Object;

  Deprecated: true

public scala.collection.mutable.BufferLike $minus$minus(scala.collection.Traversable);
  Code:
   Stack=2, Locals=2, Args_size=2
   0:	aload_0
   1:	aload_1
   2:	invokestatic	#897; //Method scala/collection/mutable/BufferLike$class.$minus$minus:(Lscala/collection/mutable/BufferLike;Lscala/collection/Traversable;)Lscala/collection/mutable/BufferLike;
   5:	areturn
  LineNumberTable: 
   line 27: 0

  LocalVariableTable: 
   Start  Length  Slot  Name   Signature
   0      6      0    this       Lscala/collection/mutable/ListBuffer;
   0      6      1    iter       Lscala/collection/Traversable;

  Deprecated: true

public scala.collection.mutable.BufferLike $minus(java.lang.Object, java.lang.Object, scala.collection.Seq);
  Code:
   Stack=4, Locals=4, Args_size=4
   0:	aload_0
   1:	aload_1
   2:	aload_2
   3:	aload_3
   4:	invokestatic	#900; //Method scala/collection/mutable/BufferLike$class.$minus:(Lscala/collection/mutable/BufferLike;Ljava/lang/Object;Ljava/lang/Object;Lscala/collection/Seq;)Lscala/collection/mutable/BufferLike;
   7:	areturn
  LineNumberTable: 
   line 27: 0

  LocalVariableTable: 
   Start  Length  Slot  Name   Signature
   0      8      0    this       Lscala/collection/mutable/ListBuffer;
   0      8      1    elem1       Ljava/lang/Object;
   0      8      2    elem2       Ljava/lang/Object;
   0      8      3    elems       Lscala/collection/Seq;

  Deprecated: true

public scala.collection.mutable.BufferLike $minus(java.lang.Object);
  Code:
   Stack=2, Locals=2, Args_size=2
   0:	aload_0
   1:	aload_1
   2:	invokestatic	#902; //Method scala/collection/mutable/BufferLike$class.$minus:(Lscala/collection/mutable/BufferLike;Ljava/lang/Object;)Lscala/collection/mutable/BufferLike;
   5:	areturn
  LineNumberTable: 
   line 27: 0

  LocalVariableTable: 
   Start  Length  Slot  Name   Signature
   0      6      0    this       Lscala/collection/mutable/ListBuffer;
   0      6      1    elem       Ljava/lang/Object;

  Deprecated: true

public scala.collection.mutable.BufferLike $plus$plus(scala.collection.Iterator);
  Code:
   Stack=2, Locals=2, Args_size=2
   0:	aload_0
   1:	aload_1
   2:	invokestatic	#904; //Method scala/collection/mutable/BufferLike$class.$plus$plus:(Lscala/collection/mutable/BufferLike;Lscala/collection/Iterator;)Lscala/collection/mutable/BufferLike;
   5:	areturn
  LineNumberTable: 
   line 27: 0

  LocalVariableTable: 
   Start  Length  Slot  Name   Signature
   0      6      0    this       Lscala/collection/mutable/ListBuffer;
   0      6      1    iter       Lscala/collection/Iterator;

  Deprecated: true

public scala.collection.mutable.BufferLike $plus$plus(scala.collection.Traversable);
  Code:
   Stack=2, Locals=2, Args_size=2
   0:	aload_0
   1:	aload_1
   2:	invokestatic	#906; //Method scala/collection/mutable/BufferLike$class.$plus$plus:(Lscala/collection/mutable/BufferLike;Lscala/collection/Traversable;)Lscala/collection/mutable/BufferLike;
   5:	areturn
  LineNumberTable: 
   line 27: 0

  LocalVariableTable: 
   Start  Length  Slot  Name   Signature
   0      6      0    this       Lscala/collection/mutable/ListBuffer;
   0      6      1    iter       Lscala/collection/Traversable;

  Deprecated: true

public scala.collection.mutable.BufferLike $plus(java.lang.Object, java.lang.Object, scala.collection.Seq);
  Code:
   Stack=4, Locals=4, Args_size=4
   0:	aload_0
   1:	aload_1
   2:	aload_2
   3:	aload_3
   4:	invokestatic	#908; //Method scala/collection/mutable/BufferLike$class.$plus:(Lscala/collection/mutable/BufferLike;Ljava/lang/Object;Ljava/lang/Object;Lscala/collection/Seq;)Lscala/collection/mutable/BufferLike;
   7:	areturn
  LineNumberTable: 
   line 27: 0

  LocalVariableTable: 
   Start  Length  Slot  Name   Signature
   0      8      0    this       Lscala/collection/mutable/ListBuffer;
   0      8      1    elem1       Ljava/lang/Object;
   0      8      2    elem2       Ljava/lang/Object;
   0      8      3    elems       Lscala/collection/Seq;

  Deprecated: true

public scala.collection.mutable.BufferLike $plus(java.lang.Object);
  Code:
   Stack=2, Locals=2, Args_size=2
   0:	aload_0
   1:	aload_1
   2:	invokestatic	#910; //Method scala/collection/mutable/BufferLike$class.$plus:(Lscala/collection/mutable/BufferLike;Ljava/lang/Object;)Lscala/collection/mutable/BufferLike;
   5:	areturn
  LineNumberTable: 
   line 27: 0

  LocalVariableTable: 
   Start  Length  Slot  Name   Signature
   0      6      0    this       Lscala/collection/mutable/ListBuffer;
   0      6      1    elem       Ljava/lang/Object;

  Deprecated: true

public final scala.collection.mutable.BufferLike $plus$plus$colon(scala.collection.Traversable);
  Code:
   Stack=2, Locals=2, Args_size=2
   0:	aload_0
   1:	aload_1
   2:	invokestatic	#913; //Method scala/collection/mutable/BufferLike$class.$plus$plus$colon:(Lscala/collection/mutable/BufferLike;Lscala/collection/Traversable;)Lscala/collection/mutable/BufferLike;
   5:	areturn
  LineNumberTable: 
   line 27: 0

  LocalVariableTable: 
   Start  Length  Slot  Name   Signature
   0      6      0    this       Lscala/collection/mutable/ListBuffer;
   0      6      1    iter       Lscala/collection/Traversable;

  Deprecated: true

public void $plus$plus$eq(java.lang.Object, int, int);
  Code:
   Stack=4, Locals=4, Args_size=4
   0:	aload_0
   1:	aload_1
   2:	iload_2
   3:	iload_3
   4:	invokestatic	#917; //Method scala/collection/mutable/BufferLike$class.$plus$plus$eq:(Lscala/collection/mutable/BufferLike;Ljava/lang/Object;II)V
   7:	return
  LineNumberTable: 
   line 27: 0

  LocalVariableTable: 
   Start  Length  Slot  Name   Signature
   0      8      0    this       Lscala/collection/mutable/ListBuffer;
   0      8      1    src       Ljava/lang/Object;
   0      8      2    start       I
   0      8      3    len       I

  Deprecated: true

public void $less$less(scala.collection.script.Message);
  Code:
   Stack=2, Locals=2, Args_size=2
   0:	aload_0
   1:	aload_1
   2:	invokestatic	#923; //Method scala/collection/mutable/BufferLike$class.$less$less:(Lscala/collection/mutable/BufferLike;Lscala/collection/script/Message;)V
   5:	return
  LineNumberTable: 
   line 27: 0

  LocalVariableTable: 
   Start  Length  Slot  Name   Signature
   0      6      0    this       Lscala/collection/mutable/ListBuffer;
   0      6      1    cmd       Lscala/collection/script/Message;


public void trimEnd(int);
  Code:
   Stack=2, Locals=2, Args_size=2
   0:	aload_0
   1:	iload_1
   2:	invokestatic	#929; //Method scala/collection/mutable/BufferLike$class.trimEnd:(Lscala/collection/mutable/BufferLike;I)V
   5:	return
  LineNumberTable: 
   line 27: 0

  LocalVariableTable: 
   Start  Length  Slot  Name   Signature
   0      6      0    this       Lscala/collection/mutable/ListBuffer;
   0      6      1    n       I


public void trimStart(int);
  Code:
   Stack=2, Locals=2, Args_size=2
   0:	aload_0
   1:	iload_1
   2:	invokestatic	#932; //Method scala/collection/mutable/BufferLike$class.trimStart:(Lscala/collection/mutable/BufferLike;I)V
   5:	return
  LineNumberTable: 
   line 27: 0

  LocalVariableTable: 
   Start  Length  Slot  Name   Signature
   0      6      0    this       Lscala/collection/mutable/ListBuffer;
   0      6      1    n       I


public void insert(int, scala.collection.Seq);
  Code:
   Stack=3, Locals=3, Args_size=3
   0:	aload_0
   1:	iload_1
   2:	aload_2
   3:	invokestatic	#937; //Method scala/collection/mutable/BufferLike$class.insert:(Lscala/collection/mutable/BufferLike;ILscala/collection/Seq;)V
   6:	return
  LineNumberTable: 
   line 27: 0

  LocalVariableTable: 
   Start  Length  Slot  Name   Signature
   0      7      0    this       Lscala/collection/mutable/ListBuffer;
   0      7      1    n       I
   0      7      2    elems       Lscala/collection/Seq;


public void prependAll(scala.collection.Iterator);
  Code:
   Stack=2, Locals=2, Args_size=2
   0:	aload_0
   1:	aload_1
   2:	invokestatic	#942; //Method scala/collection/mutable/BufferLike$class.prependAll:(Lscala/collection/mutable/BufferLike;Lscala/collection/Iterator;)V
   5:	return
  LineNumberTable: 
   line 27: 0

  LocalVariableTable: 
   Start  Length  Slot  Name   Signature
   0      6      0    this       Lscala/collection/mutable/ListBuffer;
   0      6      1    iter       Lscala/collection/Iterator;


public void prependAll(scala.collection.Traversable);
  Code:
   Stack=2, Locals=2, Args_size=2
   0:	aload_0
   1:	aload_1
   2:	invokestatic	#945; //Method scala/collection/mutable/BufferLike$class.prependAll:(Lscala/collection/mutable/BufferLike;Lscala/collection/Traversable;)V
   5:	return
  LineNumberTable: 
   line 27: 0

  LocalVariableTable: 
   Start  Length  Slot  Name   Signature
   0      6      0    this       Lscala/collection/mutable/ListBuffer;
   0      6      1    iter       Lscala/collection/Traversable;


public void prepend(scala.collection.Seq);
  Code:
   Stack=2, Locals=2, Args_size=2
   0:	aload_0
   1:	aload_1
   2:	invokestatic	#949; //Method scala/collection/mutable/BufferLike$class.prepend:(Lscala/collection/mutable/BufferLike;Lscala/collection/Seq;)V
   5:	return
  LineNumberTable: 
   line 27: 0

  LocalVariableTable: 
   Start  Length  Slot  Name   Signature
   0      6      0    this       Lscala/collection/mutable/ListBuffer;
   0      6      1    elems       Lscala/collection/Seq;


public void appendAll(scala.collection.Iterator);
  Code:
   Stack=2, Locals=2, Args_size=2
   0:	aload_0
   1:	aload_1
   2:	invokestatic	#952; //Method scala/collection/mutable/BufferLike$class.appendAll:(Lscala/collection/mutable/BufferLike;Lscala/collection/Iterator;)V
   5:	return
  LineNumberTable: 
   line 27: 0

  LocalVariableTable: 
   Start  Length  Slot  Name   Signature
   0      6      0    this       Lscala/collection/mutable/ListBuffer;
   0      6      1    iter       Lscala/collection/Iterator;


public void appendAll(scala.collection.Traversable);
  Code:
   Stack=2, Locals=2, Args_size=2
   0:	aload_0
   1:	aload_1
   2:	invokestatic	#954; //Method scala/collection/mutable/BufferLike$class.appendAll:(Lscala/collection/mutable/BufferLike;Lscala/collection/Traversable;)V
   5:	return
  LineNumberTable: 
   line 27: 0

  LocalVariableTable: 
   Start  Length  Slot  Name   Signature
   0      6      0    this       Lscala/collection/mutable/ListBuffer;
   0      6      1    elems       Lscala/collection/Traversable;


public void append(scala.collection.Seq);
  Code:
   Stack=2, Locals=2, Args_size=2
   0:	aload_0
   1:	aload_1
   2:	invokestatic	#957; //Method scala/collection/mutable/BufferLike$class.append:(Lscala/collection/mutable/BufferLike;Lscala/collection/Seq;)V
   5:	return
  LineNumberTable: 
   line 27: 0

  LocalVariableTable: 
   Start  Length  Slot  Name   Signature
   0      6      0    this       Lscala/collection/mutable/ListBuffer;
   0      6      1    elems       Lscala/collection/Seq;


public scala.collection.mutable.BufferLike $plus$plus$eq$colon(scala.collection.Iterator);
  Code:
   Stack=2, Locals=2, Args_size=2
   0:	aload_0
   1:	aload_1
   2:	invokestatic	#960; //Method scala/collection/mutable/BufferLike$class.$plus$plus$eq$colon:(Lscala/collection/mutable/BufferLike;Lscala/collection/Iterator;)Lscala/collection/mutable/BufferLike;
   5:	areturn
  LineNumberTable: 
   line 27: 0

  LocalVariableTable: 
   Start  Length  Slot  Name   Signature
   0      6      0    this       Lscala/collection/mutable/ListBuffer;
   0      6      1    iter       Lscala/collection/Iterator;


public scala.collection.mutable.BufferLike $plus$plus$eq$colon(scala.collection.Traversable);
  Code:
   Stack=2, Locals=2, Args_size=2
   0:	aload_0
   1:	aload_1
   2:	invokestatic	#962; //Method scala/collection/mutable/BufferLike$class.$plus$plus$eq$colon:(Lscala/collection/mutable/BufferLike;Lscala/collection/Traversable;)Lscala/collection/mutable/BufferLike;
   5:	areturn
  LineNumberTable: 
   line 27: 0

  LocalVariableTable: 
   Start  Length  Slot  Name   Signature
   0      6      0    this       Lscala/collection/mutable/ListBuffer;
   0      6      1    elems       Lscala/collection/Traversable;


public scala.collection.mutable.Builder mapResult(scala.Function1);
  Code:
   Stack=2, Locals=2, Args_size=2
   0:	aload_0
   1:	aload_1
   2:	invokestatic	#967; //Method scala/collection/mutable/Builder$class.mapResult:(Lscala/collection/mutable/Builder;Lscala/Function1;)Lscala/collection/mutable/Builder;
   5:	areturn
  LineNumberTable: 
   line 27: 0

  LocalVariableTable: 
   Start  Length  Slot  Name   Signature
   0      6      0    this       Lscala/collection/mutable/ListBuffer;
   0      6      1    f       Lscala/Function1;


public void sizeHint(int);
  Code:
   Stack=2, Locals=2, Args_size=2
   0:	aload_0
   1:	iload_1
   2:	invokestatic	#971; //Method scala/collection/mutable/Builder$class.sizeHint:(Lscala/collection/mutable/Builder;I)V
   5:	return
  LineNumberTable: 
   line 27: 0

  LocalVariableTable: 
   Start  Length  Slot  Name   Signature
   0      6      0    this       Lscala/collection/mutable/ListBuffer;
   0      6      1    size       I


public scala.Option lastOption();
  Code:
   Stack=1, Locals=1, Args_size=1
   0:	aload_0
   1:	invokestatic	#975; //Method scala/collection/generic/TraversableForwarder$class.lastOption:(Lscala/collection/generic/TraversableForwarder;)Lscala/Option;
   4:	areturn
  LineNumberTable: 
   line 27: 0


public java.lang.Object last();
  Code:
   Stack=1, Locals=1, Args_size=1
   0:	aload_0
   1:	invokestatic	#979; //Method scala/collection/generic/TraversableForwarder$class.last:(Lscala/collection/generic/TraversableForwarder;)Ljava/lang/Object;
   4:	areturn
  LineNumberTable: 
   line 27: 0


public java.lang.Object head();
  Code:
   Stack=1, Locals=1, Args_size=1
   0:	aload_0
   1:	invokestatic	#981; //Method scala/collection/generic/TraversableForwarder$class.head:(Lscala/collection/generic/TraversableForwarder;)Ljava/lang/Object;
   4:	areturn
  LineNumberTable: 
   line 27: 0


public scala.collection.mutable.StringBuilder addString(scala.collection.mutable.StringBuilder, java.lang.String, java.lang.String, java.lang.String);
  Code:
   Stack=5, Locals=5, Args_size=5
   0:	aload_0
   1:	aload_1
   2:	aload_2
   3:	aload_3
   4:	aload	4
   6:	invokestatic	#985; //Method scala/collection/generic/TraversableForwarder$class.addString:(Lscala/collection/generic/TraversableForwarder;Lscala/collection/mutable/StringBuilder;Ljava/lang/String;Ljava/lang/String;Ljava/lang/String;)Lscala/collection/mutable/StringBuilder;
   9:	areturn
  LineNumberTable: 
   line 27: 0

  LocalVariableTable: 
   Start  Length  Slot  Name   Signature
   0      10      0    this       Lscala/collection/mutable/ListBuffer;
   0      10      1    b       Lscala/collection/mutable/StringBuilder;
   0      10      2    start       Ljava/lang/String;
   0      10      3    sep       Ljava/lang/String;
   0      10      4    end       Ljava/lang/String;


public java.lang.String mkString(java.lang.String, java.lang.String, java.lang.String);
  Code:
   Stack=4, Locals=4, Args_size=4
   0:	aload_0
   1:	aload_1
   2:	aload_2
   3:	aload_3
   4:	invokestatic	#989; //Method scala/collection/generic/TraversableForwarder$class.mkString:(Lscala/collection/generic/TraversableForwarder;Ljava/lang/String;Ljava/lang/String;Ljava/lang/String;)Ljava/lang/String;
   7:	areturn
  LineNumberTable: 
   line 27: 0

  LocalVariableTable: 
   Start  Length  Slot  Name   Signature
   0      8      0    this       Lscala/collection/mutable/ListBuffer;
   0      8      1    start       Ljava/lang/String;
   0      8      2    sep       Ljava/lang/String;
   0      8      3    end       Ljava/lang/String;


public scala.collection.immutable.Stream toStream();
  Code:
   Stack=1, Locals=1, Args_size=1
   0:	aload_0
   1:	invokestatic	#994; //Method scala/collection/generic/TraversableForwarder$class.toStream:(Lscala/collection/generic/TraversableForwarder;)Lscala/collection/immutable/Stream;
   4:	areturn
  LineNumberTable: 
   line 27: 0


public scala.collection.Seq toSeq();
  Code:
   Stack=1, Locals=1, Args_size=1
   0:	aload_0
   1:	invokestatic	#998; //Method scala/collection/generic/TraversableForwarder$class.toSeq:(Lscala/collection/generic/TraversableForwarder;)Lscala/collection/Seq;
   4:	areturn
  LineNumberTable: 
   line 27: 0


public java.lang.Object toArray(scala.reflect.ClassManifest);
  Code:
   Stack=2, Locals=2, Args_size=2
   0:	aload_0
   1:	aload_1
   2:	invokestatic	#1003; //Method scala/collection/generic/TraversableForwarder$class.toArray:(Lscala/collection/generic/TraversableForwarder;Lscala/reflect/ClassManifest;)Ljava/lang/Object;
   5:	areturn
  LineNumberTable: 
   line 27: 0

  LocalVariableTable: 
   Start  Length  Slot  Name   Signature
   0      6      0    this       Lscala/collection/mutable/ListBuffer;
   0      6      1    evidence$1       Lscala/reflect/ClassManifest;


public void copyToArray(java.lang.Object, int, int);
  Code:
   Stack=4, Locals=4, Args_size=4
   0:	aload_0
   1:	aload_1
   2:	iload_2
   3:	iload_3
   4:	invokestatic	#1008; //Method scala/collection/generic/TraversableForwarder$class.copyToArray:(Lscala/collection/generic/TraversableForwarder;Ljava/lang/Object;II)V
   7:	return
  LineNumberTable: 
   line 27: 0

  LocalVariableTable: 
   Start  Length  Slot  Name   Signature
   0      8      0    this       Lscala/collection/mutable/ListBuffer;
   0      8      1    xs       Ljava/lang/Object;
   0      8      2    start       I
   0      8      3    len       I


public void copyToBuffer(scala.collection.mutable.Buffer);
  Code:
   Stack=2, Locals=2, Args_size=2
   0:	aload_0
   1:	aload_1
   2:	invokestatic	#1012; //Method scala/collection/generic/TraversableForwarder$class.copyToBuffer:(Lscala/collection/generic/TraversableForwarder;Lscala/collection/mutable/Buffer;)V
   5:	return
  LineNumberTable: 
   line 27: 0

  LocalVariableTable: 
   Start  Length  Slot  Name   Signature
   0      6      0    this       Lscala/collection/mutable/ListBuffer;
   0      6      1    dest       Lscala/collection/mutable/Buffer;


public scala.Option reduceRightOption(scala.Function2);
  Code:
   Stack=2, Locals=2, Args_size=2
   0:	aload_0
   1:	aload_1
   2:	invokestatic	#1019; //Method scala/collection/generic/TraversableForwarder$class.reduceRightOption:(Lscala/collection/generic/TraversableForwarder;Lscala/Function2;)Lscala/Option;
   5:	areturn
  LineNumberTable: 
   line 27: 0

  LocalVariableTable: 
   Start  Length  Slot  Name   Signature
   0      6      0    this       Lscala/collection/mutable/ListBuffer;
   0      6      1    op       Lscala/Function2;


public scala.Option reduceLeftOption(scala.Function2);
  Code:
   Stack=2, Locals=2, Args_size=2
   0:	aload_0
   1:	aload_1
   2:	invokestatic	#1022; //Method scala/collection/generic/TraversableForwarder$class.reduceLeftOption:(Lscala/collection/generic/TraversableForwarder;Lscala/Function2;)Lscala/Option;
   5:	areturn
  LineNumberTable: 
   line 27: 0

  LocalVariableTable: 
   Start  Length  Slot  Name   Signature
   0      6      0    this       Lscala/collection/mutable/ListBuffer;
   0      6      1    op       Lscala/Function2;


public java.lang.Object reduceRight(scala.Function2);
  Code:
   Stack=2, Locals=2, Args_size=2
   0:	aload_0
   1:	aload_1
   2:	invokestatic	#1026; //Method scala/collection/generic/TraversableForwarder$class.reduceRight:(Lscala/collection/generic/TraversableForwarder;Lscala/Function2;)Ljava/lang/Object;
   5:	areturn
  LineNumberTable: 
   line 27: 0

  LocalVariableTable: 
   Start  Length  Slot  Name   Signature
   0      6      0    this       Lscala/collection/mutable/ListBuffer;
   0      6      1    op       Lscala/Function2;


public java.lang.Object reduceLeft(scala.Function2);
  Code:
   Stack=2, Locals=2, Args_size=2
   0:	aload_0
   1:	aload_1
   2:	invokestatic	#1029; //Method scala/collection/generic/TraversableForwarder$class.reduceLeft:(Lscala/collection/generic/TraversableForwarder;Lscala/Function2;)Ljava/lang/Object;
   5:	areturn
  LineNumberTable: 
   line 27: 0

  LocalVariableTable: 
   Start  Length  Slot  Name   Signature
   0      6      0    this       Lscala/collection/mutable/ListBuffer;
   0      6      1    op       Lscala/Function2;


public java.lang.Object foldRight(java.lang.Object, scala.Function2);
  Code:
   Stack=3, Locals=3, Args_size=3
   0:	aload_0
   1:	aload_1
   2:	aload_2
   3:	invokestatic	#1033; //Method scala/collection/generic/TraversableForwarder$class.foldRight:(Lscala/collection/generic/TraversableForwarder;Ljava/lang/Object;Lscala/Function2;)Ljava/lang/Object;
   6:	areturn
  LineNumberTable: 
   line 27: 0

  LocalVariableTable: 
   Start  Length  Slot  Name   Signature
   0      7      0    this       Lscala/collection/mutable/ListBuffer;
   0      7      1    z       Ljava/lang/Object;
   0      7      2    op       Lscala/Function2;


public java.lang.Object foldLeft(java.lang.Object, scala.Function2);
  Code:
   Stack=3, Locals=3, Args_size=3
   0:	aload_0
   1:	aload_1
   2:	aload_2
   3:	invokestatic	#1036; //Method scala/collection/generic/TraversableForwarder$class.foldLeft:(Lscala/collection/generic/TraversableForwarder;Ljava/lang/Object;Lscala/Function2;)Ljava/lang/Object;
   6:	areturn
  LineNumberTable: 
   line 27: 0

  LocalVariableTable: 
   Start  Length  Slot  Name   Signature
   0      7      0    this       Lscala/collection/mutable/ListBuffer;
   0      7      1    z       Ljava/lang/Object;
   0      7      2    op       Lscala/Function2;


public scala.Option find(scala.Function1);
  Code:
   Stack=2, Locals=2, Args_size=2
   0:	aload_0
   1:	aload_1
   2:	invokestatic	#1041; //Method scala/collection/generic/TraversableForwarder$class.find:(Lscala/collection/generic/TraversableForwarder;Lscala/Function1;)Lscala/Option;
   5:	areturn
  LineNumberTable: 
   line 27: 0

  LocalVariableTable: 
   Start  Length  Slot  Name   Signature
   0      6      0    this       Lscala/collection/mutable/ListBuffer;
   0      6      1    p       Lscala/Function1;


public int count(scala.Function1);
  Code:
   Stack=2, Locals=2, Args_size=2
   0:	aload_0
   1:	aload_1
   2:	invokestatic	#1044; //Method scala/collection/generic/TraversableForwarder$class.count:(Lscala/collection/generic/TraversableForwarder;Lscala/Function1;)I
   5:	ireturn
  LineNumberTable: 
   line 27: 0

  LocalVariableTable: 
   Start  Length  Slot  Name   Signature
   0      6      0    this       Lscala/collection/mutable/ListBuffer;
   0      6      1    p       Lscala/Function1;


public boolean exists(scala.Function1);
  Code:
   Stack=2, Locals=2, Args_size=2
   0:	aload_0
   1:	aload_1
   2:	invokestatic	#1049; //Method scala/collection/generic/TraversableForwarder$class.exists:(Lscala/collection/generic/TraversableForwarder;Lscala/Function1;)Z
   5:	ireturn
  LineNumberTable: 
   line 27: 0

  LocalVariableTable: 
   Start  Length  Slot  Name   Signature
   0      6      0    this       Lscala/collection/mutable/ListBuffer;
   0      6      1    p       Lscala/Function1;


public boolean forall(scala.Function1);
  Code:
   Stack=2, Locals=2, Args_size=2
   0:	aload_0
   1:	aload_1
   2:	invokestatic	#1052; //Method scala/collection/generic/TraversableForwarder$class.forall:(Lscala/collection/generic/TraversableForwarder;Lscala/Function1;)Z
   5:	ireturn
  LineNumberTable: 
   line 27: 0

  LocalVariableTable: 
   Start  Length  Slot  Name   Signature
   0      6      0    this       Lscala/collection/mutable/ListBuffer;
   0      6      1    p       Lscala/Function1;


public void foreach(scala.Function1);
  Code:
   Stack=2, Locals=2, Args_size=2
   0:	aload_0
   1:	aload_1
   2:	invokestatic	#1056; //Method scala/collection/generic/TraversableForwarder$class.foreach:(Lscala/collection/generic/TraversableForwarder;Lscala/Function1;)V
   5:	return
  LineNumberTable: 
   line 27: 0

  LocalVariableTable: 
   Start  Length  Slot  Name   Signature
   0      6      0    this       Lscala/collection/mutable/ListBuffer;
   0      6      1    f       Lscala/Function1;


public boolean hasDefiniteSize();
  Code:
   Stack=1, Locals=1, Args_size=1
   0:	aload_0
   1:	invokestatic	#1060; //Method scala/collection/generic/TraversableForwarder$class.hasDefiniteSize:(Lscala/collection/generic/TraversableForwarder;)Z
   4:	ireturn
  LineNumberTable: 
   line 27: 0


public boolean nonEmpty();
  Code:
   Stack=1, Locals=1, Args_size=1
   0:	aload_0
   1:	invokestatic	#1063; //Method scala/collection/generic/TraversableForwarder$class.nonEmpty:(Lscala/collection/generic/TraversableForwarder;)Z
   4:	ireturn
  LineNumberTable: 
   line 27: 0


public boolean isEmpty();
  Code:
   Stack=1, Locals=1, Args_size=1
   0:	aload_0
   1:	invokestatic	#1065; //Method scala/collection/generic/TraversableForwarder$class.isEmpty:(Lscala/collection/generic/TraversableForwarder;)Z
   4:	ireturn
  LineNumberTable: 
   line 27: 0


public boolean sameElements(scala.collection.Iterable);
  Code:
   Stack=2, Locals=2, Args_size=2
   0:	aload_0
   1:	aload_1
   2:	invokestatic	#1070; //Method scala/collection/generic/IterableForwarder$class.sameElements:(Lscala/collection/generic/IterableForwarder;Lscala/collection/Iterable;)Z
   5:	ireturn
  LineNumberTable: 
   line 27: 0

  LocalVariableTable: 
   Start  Length  Slot  Name   Signature
   0      6      0    this       Lscala/collection/mutable/ListBuffer;
   0      6      1    that       Lscala/collection/Iterable;


public scala.collection.immutable.Range indices();
  Code:
   Stack=1, Locals=1, Args_size=1
   0:	aload_0
   1:	invokestatic	#1075; //Method scala/collection/generic/SeqForwarder$class.indices:(Lscala/collection/generic/SeqForwarder;)Lscala/collection/immutable/Range;
   4:	areturn
  LineNumberTable: 
   line 27: 0


public boolean contains(java.lang.Object);
  Code:
   Stack=2, Locals=2, Args_size=2
   0:	aload_0
   1:	aload_1
   2:	invokestatic	#1079; //Method scala/collection/generic/SeqForwarder$class.contains:(Lscala/collection/generic/SeqForwarder;Ljava/lang/Object;)Z
   5:	ireturn
  LineNumberTable: 
   line 27: 0

  LocalVariableTable: 
   Start  Length  Slot  Name   Signature
   0      6      0    this       Lscala/collection/mutable/ListBuffer;
   0      6      1    elem       Ljava/lang/Object;


public int indexOfSlice(scala.collection.Seq);
  Code:
   Stack=2, Locals=2, Args_size=2
   0:	aload_0
   1:	aload_1
   2:	invokestatic	#1082; //Method scala/collection/generic/SeqForwarder$class.indexOfSlice:(Lscala/collection/generic/SeqForwarder;Lscala/collection/Seq;)I
   5:	ireturn
  LineNumberTable: 
   line 27: 0

  LocalVariableTable: 
   Start  Length  Slot  Name   Signature
   0      6      0    this       Lscala/collection/mutable/ListBuffer;
   0      6      1    that       Lscala/collection/Seq;


public boolean endsWith(scala.collection.Seq);
  Code:
   Stack=2, Locals=2, Args_size=2
   0:	aload_0
   1:	aload_1
   2:	invokestatic	#1086; //Method scala/collection/generic/SeqForwarder$class.endsWith:(Lscala/collection/generic/SeqForwarder;Lscala/collection/Seq;)Z
   5:	ireturn
  LineNumberTable: 
   line 27: 0

  LocalVariableTable: 
   Start  Length  Slot  Name   Signature
   0      6      0    this       Lscala/collection/mutable/ListBuffer;
   0      6      1    that       Lscala/collection/Seq;


public boolean startsWith(scala.collection.Seq, int);
  Code:
   Stack=3, Locals=3, Args_size=3
   0:	aload_0
   1:	aload_1
   2:	iload_2
   3:	invokestatic	#1090; //Method scala/collection/generic/SeqForwarder$class.startsWith:(Lscala/collection/generic/SeqForwarder;Lscala/collection/Seq;I)Z
   6:	ireturn
  LineNumberTable: 
   line 27: 0

  LocalVariableTable: 
   Start  Length  Slot  Name   Signature
   0      7      0    this       Lscala/collection/mutable/ListBuffer;
   0      7      1    that       Lscala/collection/Seq;
   0      7      2    offset       I


public scala.collection.Iterator reverseIterator();
  Code:
   Stack=1, Locals=1, Args_size=1
   0:	aload_0
   1:	invokestatic	#1095; //Method scala/collection/generic/SeqForwarder$class.reverseIterator:(Lscala/collection/generic/SeqForwarder;)Lscala/collection/Iterator;
   4:	areturn
  LineNumberTable: 
   line 27: 0


public int indexOf(java.lang.Object, int);
  Code:
   Stack=3, Locals=3, Args_size=3
   0:	aload_0
   1:	aload_1
   2:	iload_2
   3:	invokestatic	#1098; //Method scala/collection/generic/SeqForwarder$class.indexOf:(Lscala/collection/generic/SeqForwarder;Ljava/lang/Object;I)I
   6:	ireturn
  LineNumberTable: 
   line 27: 0

  LocalVariableTable: 
   Start  Length  Slot  Name   Signature
   0      7      0    this       Lscala/collection/mutable/ListBuffer;
   0      7      1    elem       Ljava/lang/Object;
   0      7      2    from       I


public int indexWhere(scala.Function1, int);
  Code:
   Stack=3, Locals=3, Args_size=3
   0:	aload_0
   1:	aload_1
   2:	iload_2
   3:	invokestatic	#1101; //Method scala/collection/generic/SeqForwarder$class.indexWhere:(Lscala/collection/generic/SeqForwarder;Lscala/Function1;I)I
   6:	ireturn
  LineNumberTable: 
   line 27: 0

  LocalVariableTable: 
   Start  Length  Slot  Name   Signature
   0      7      0    this       Lscala/collection/mutable/ListBuffer;
   0      7      1    p       Lscala/Function1;
   0      7      2    from       I


public int prefixLength(scala.Function1);
  Code:
   Stack=2, Locals=2, Args_size=2
   0:	aload_0
   1:	aload_1
   2:	invokestatic	#1105; //Method scala/collection/generic/SeqForwarder$class.prefixLength:(Lscala/collection/generic/SeqForwarder;Lscala/Function1;)I
   5:	ireturn
  LineNumberTable: 
   line 27: 0

  LocalVariableTable: 
   Start  Length  Slot  Name   Signature
   0      6      0    this       Lscala/collection/mutable/ListBuffer;
   0      6      1    p       Lscala/Function1;


public int segmentLength(scala.Function1, int);
  Code:
   Stack=3, Locals=3, Args_size=3
   0:	aload_0
   1:	aload_1
   2:	iload_2
   3:	invokestatic	#1108; //Method scala/collection/generic/SeqForwarder$class.segmentLength:(Lscala/collection/generic/SeqForwarder;Lscala/Function1;I)I
   6:	ireturn
  LineNumberTable: 
   line 27: 0

  LocalVariableTable: 
   Start  Length  Slot  Name   Signature
   0      7      0    this       Lscala/collection/mutable/ListBuffer;
   0      7      1    p       Lscala/Function1;
   0      7      2    from       I


public int lengthCompare(int);
  Code:
   Stack=2, Locals=2, Args_size=2
   0:	aload_0
   1:	iload_1
   2:	invokestatic	#1112; //Method scala/collection/generic/SeqForwarder$class.lengthCompare:(Lscala/collection/generic/SeqForwarder;I)I
   5:	ireturn
  LineNumberTable: 
   line 27: 0

  LocalVariableTable: 
   Start  Length  Slot  Name   Signature
   0      6      0    this       Lscala/collection/mutable/ListBuffer;
   0      6      1    l       I


public boolean isDefinedAt(int);
  Code:
   Stack=2, Locals=2, Args_size=2
   0:	aload_0
   1:	iload_1
   2:	invokestatic	#1116; //Method scala/collection/generic/SeqForwarder$class.isDefinedAt:(Lscala/collection/generic/SeqForwarder;I)Z
   5:	ireturn
  LineNumberTable: 
   line 27: 0

  LocalVariableTable: 
   Start  Length  Slot  Name   Signature
   0      6      0    this       Lscala/collection/mutable/ListBuffer;
   0      6      1    x       I


}

