Compiled from "MapLikeBase.scala"
public abstract class scala.collection.mutable.MapLikeBase$class extends java.lang.Object
  SourceFile: "MapLikeBase.scala"
  Scala: length = 0x
   
  minor version: 0
  major version: 49
  Constant pool:
const #1 = Asciz	SourceFile;
const #2 = Asciz	MapLikeBase.scala;
const #3 = Asciz	$init$;
const #4 = Asciz	(Lscala/collection/mutable/MapLikeBase;)V;
const #5 = Asciz	Code;
const #6 = Asciz	LineNumberTable;
const #7 = Asciz	$this;
const #8 = Asciz	Lscala/collection/mutable/MapLikeBase;;
const #9 = Asciz	LocalVariableTable;
const #10 = Asciz	$plus;
const #11 = Asciz	(Lscala/collection/mutable/MapLikeBase;Lscala/Tuple2;)Lscala/collection/mutable/Map;;
const #12 = Asciz	scala/collection/mutable/Cloneable;
const #13 = class	#12;	//  scala/collection/mutable/Cloneable
const #14 = Asciz	clone;
const #15 = Asciz	()Ljava/lang/Object;;
const #16 = NameAndType	#14:#15;//  clone:()Ljava/lang/Object;
const #17 = InterfaceMethod	#13.#16;	//  scala/collection/mutable/Cloneable.clone:()Ljava/lang/Object;
const #18 = Asciz	scala/collection/mutable/Map;
const #19 = class	#18;	//  scala/collection/mutable/Map
const #20 = Asciz	scala/collection/mutable/MapLike;
const #21 = class	#20;	//  scala/collection/mutable/MapLike
const #22 = Asciz	$plus$eq;
const #23 = Asciz	(Lscala/Tuple2;)Lscala/collection/mutable/MapLike;;
const #24 = NameAndType	#22:#23;//  $plus$eq:(Lscala/Tuple2;)Lscala/collection/mutable/MapLike;
const #25 = InterfaceMethod	#21.#24;	//  scala/collection/mutable/MapLike.$plus$eq:(Lscala/Tuple2;)Lscala/collection/mutable/MapLike;
const #26 = Asciz	kv;
const #27 = Asciz	Lscala/Tuple2;;
const #28 = Asciz	Scala;
const #29 = Asciz	scala/collection/mutable/MapLikeBase$class;
const #30 = class	#29;	//  scala/collection/mutable/MapLikeBase$class
const #31 = Asciz	java/lang/Object;
const #32 = class	#31;	//  java/lang/Object

{
public static void $init$(scala.collection.mutable.MapLikeBase);
  Code:
   Stack=0, Locals=1, Args_size=1
   0:	return
  LineNumberTable: 
   line 35: 0

  LocalVariableTable: 
   Start  Length  Slot  Name   Signature
   0      1      0    $this       Lscala/collection/mutable/MapLikeBase;


public static scala.collection.mutable.Map $plus(scala.collection.mutable.MapLikeBase, scala.Tuple2);
  Code:
   Stack=2, Locals=2, Args_size=2
   0:	aload_0
   1:	invokeinterface	#17,  1; //InterfaceMethod scala/collection/mutable/Cloneable.clone:()Ljava/lang/Object;
   6:	checkcast	#19; //class scala/collection/mutable/Map
   9:	aload_1
   10:	invokeinterface	#25,  2; //InterfaceMethod scala/collection/mutable/MapLike.$plus$eq:(Lscala/Tuple2;)Lscala/collection/mutable/MapLike;
   15:	checkcast	#19; //class scala/collection/mutable/Map
   18:	areturn
  LineNumberTable: 
   line 36: 0

  LocalVariableTable: 
   Start  Length  Slot  Name   Signature
   0      19      0    $this       Lscala/collection/mutable/MapLikeBase;
   0      19      1    kv       Lscala/Tuple2;


}

