Compiled from "ObservableSet.scala"
public abstract class scala.collection.mutable.ObservableSet$class extends java.lang.Object
  SourceFile: "ObservableSet.scala"
  Scala: length = 0x
   
  InnerClass: 
   public final #57= #52 of #12; //$anon$1=class scala/collection/mutable/ObservableSet$$anon$1 of class scala/collection/mutable/ObservableSet
   public final #58= #41 of #12; //$anon$2=class scala/collection/mutable/ObservableSet$$anon$2 of class scala/collection/mutable/ObservableSet
   public final #59= #18 of #12; //$anon$3=class scala/collection/mutable/ObservableSet$$anon$3 of class scala/collection/mutable/ObservableSet
  minor version: 0
  major version: 49
  Constant pool:
const #1 = Asciz	SourceFile;
const #2 = Asciz	ObservableSet.scala;
const #3 = Asciz	$init$;
const #4 = Asciz	(Lscala/collection/mutable/ObservableSet;)V;
const #5 = Asciz	Code;
const #6 = Asciz	LineNumberTable;
const #7 = Asciz	$this;
const #8 = Asciz	Lscala/collection/mutable/ObservableSet;;
const #9 = Asciz	LocalVariableTable;
const #10 = Asciz	clear;
const #11 = Asciz	scala/collection/mutable/ObservableSet;
const #12 = class	#11;	//  scala/collection/mutable/ObservableSet
const #13 = Asciz	scala$collection$mutable$ObservableSet$$super$clear;
const #14 = Asciz	()V;
const #15 = NameAndType	#13:#14;//  scala$collection$mutable$ObservableSet$$super$clear:()V
const #16 = InterfaceMethod	#12.#15;	//  scala/collection/mutable/ObservableSet.scala$collection$mutable$ObservableSet$$super$clear:()V
const #17 = Asciz	scala/collection/mutable/ObservableSet$$anon$3;
const #18 = class	#17;	//  scala/collection/mutable/ObservableSet$$anon$3
const #19 = Asciz	<init>;
const #20 = NameAndType	#19:#4;//  "<init>":(Lscala/collection/mutable/ObservableSet;)V
const #21 = Method	#18.#20;	//  scala/collection/mutable/ObservableSet$$anon$3."<init>":(Lscala/collection/mutable/ObservableSet;)V
const #22 = Asciz	scala/collection/mutable/Publisher;
const #23 = class	#22;	//  scala/collection/mutable/Publisher
const #24 = Asciz	publish;
const #25 = Asciz	(Ljava/lang/Object;)V;
const #26 = NameAndType	#24:#25;//  publish:(Ljava/lang/Object;)V
const #27 = InterfaceMethod	#23.#26;	//  scala/collection/mutable/Publisher.publish:(Ljava/lang/Object;)V
const #28 = Asciz	$minus$eq;
const #29 = Asciz	(Lscala/collection/mutable/ObservableSet;Ljava/lang/Object;)Lscala/collection/mutable/ObservableSet;;
const #30 = Asciz	scala/collection/SetLike;
const #31 = class	#30;	//  scala/collection/SetLike
const #32 = Asciz	contains;
const #33 = Asciz	(Ljava/lang/Object;)Z;
const #34 = NameAndType	#32:#33;//  contains:(Ljava/lang/Object;)Z
const #35 = InterfaceMethod	#31.#34;	//  scala/collection/SetLike.contains:(Ljava/lang/Object;)Z
const #36 = Asciz	scala$collection$mutable$ObservableSet$$super$$minus$eq;
const #37 = Asciz	(Ljava/lang/Object;)Lscala/collection/mutable/ObservableSet;;
const #38 = NameAndType	#36:#37;//  scala$collection$mutable$ObservableSet$$super$$minus$eq:(Ljava/lang/Object;)Lscala/collection/mutable/ObservableSet;
const #39 = InterfaceMethod	#12.#38;	//  scala/collection/mutable/ObservableSet.scala$collection$mutable$ObservableSet$$super$$minus$eq:(Ljava/lang/Object;)Lscala/collection/mutable/ObservableSet;
const #40 = Asciz	scala/collection/mutable/ObservableSet$$anon$2;
const #41 = class	#40;	//  scala/collection/mutable/ObservableSet$$anon$2
const #42 = Asciz	(Lscala/collection/mutable/ObservableSet;Ljava/lang/Object;)V;
const #43 = NameAndType	#19:#42;//  "<init>":(Lscala/collection/mutable/ObservableSet;Ljava/lang/Object;)V
const #44 = Method	#41.#43;	//  scala/collection/mutable/ObservableSet$$anon$2."<init>":(Lscala/collection/mutable/ObservableSet;Ljava/lang/Object;)V
const #45 = Asciz	elem$2;
const #46 = Asciz	Ljava/lang/Object;;
const #47 = Asciz	$plus$eq;
const #48 = Asciz	scala$collection$mutable$ObservableSet$$super$$plus$eq;
const #49 = NameAndType	#48:#37;//  scala$collection$mutable$ObservableSet$$super$$plus$eq:(Ljava/lang/Object;)Lscala/collection/mutable/ObservableSet;
const #50 = InterfaceMethod	#12.#49;	//  scala/collection/mutable/ObservableSet.scala$collection$mutable$ObservableSet$$super$$plus$eq:(Ljava/lang/Object;)Lscala/collection/mutable/ObservableSet;
const #51 = Asciz	scala/collection/mutable/ObservableSet$$anon$1;
const #52 = class	#51;	//  scala/collection/mutable/ObservableSet$$anon$1
const #53 = Method	#52.#43;	//  scala/collection/mutable/ObservableSet$$anon$1."<init>":(Lscala/collection/mutable/ObservableSet;Ljava/lang/Object;)V
const #54 = Asciz	elem$1;
const #55 = Asciz	Scala;
const #56 = Asciz	InnerClasses;
const #57 = Asciz	$anon$1;
const #58 = Asciz	$anon$2;
const #59 = Asciz	$anon$3;
const #60 = Asciz	scala/collection/mutable/ObservableSet$class;
const #61 = class	#60;	//  scala/collection/mutable/ObservableSet$class
const #62 = Asciz	java/lang/Object;
const #63 = class	#62;	//  java/lang/Object

{
public static void $init$(scala.collection.mutable.ObservableSet);
  Code:
   Stack=0, Locals=1, Args_size=1
   0:	return
  LineNumberTable: 
   line 26: 0

  LocalVariableTable: 
   Start  Length  Slot  Name   Signature
   0      1      0    $this       Lscala/collection/mutable/ObservableSet;


public static void clear(scala.collection.mutable.ObservableSet);
  Code:
   Stack=4, Locals=1, Args_size=1
   0:	aload_0
   1:	invokeinterface	#16,  1; //InterfaceMethod scala/collection/mutable/ObservableSet.scala$collection$mutable$ObservableSet$$super$clear:()V
   6:	aload_0
   7:	new	#18; //class scala/collection/mutable/ObservableSet$$anon$3
   10:	dup
   11:	aload_0
   12:	invokespecial	#21; //Method scala/collection/mutable/ObservableSet$$anon$3."<init>":(Lscala/collection/mutable/ObservableSet;)V
   15:	invokeinterface	#27,  2; //InterfaceMethod scala/collection/mutable/Publisher.publish:(Ljava/lang/Object;)V
   20:	return
  LineNumberTable: 
   line 48: 0
   line 49: 6

  LocalVariableTable: 
   Start  Length  Slot  Name   Signature
   0      21      0    $this       Lscala/collection/mutable/ObservableSet;


public static scala.collection.mutable.ObservableSet $minus$eq(scala.collection.mutable.ObservableSet, java.lang.Object);
  Code:
   Stack=5, Locals=2, Args_size=2
   0:	aload_0
   1:	aload_1
   2:	invokeinterface	#35,  2; //InterfaceMethod scala/collection/SetLike.contains:(Ljava/lang/Object;)Z
   7:	ifeq	33
   10:	aload_0
   11:	aload_1
   12:	invokeinterface	#39,  2; //InterfaceMethod scala/collection/mutable/ObservableSet.scala$collection$mutable$ObservableSet$$super$$minus$eq:(Ljava/lang/Object;)Lscala/collection/mutable/ObservableSet;
   17:	pop
   18:	aload_0
   19:	new	#41; //class scala/collection/mutable/ObservableSet$$anon$2
   22:	dup
   23:	aload_0
   24:	aload_1
   25:	invokespecial	#44; //Method scala/collection/mutable/ObservableSet$$anon$2."<init>":(Lscala/collection/mutable/ObservableSet;Ljava/lang/Object;)V
   28:	invokeinterface	#27,  2; //InterfaceMethod scala/collection/mutable/Publisher.publish:(Ljava/lang/Object;)V
   33:	aload_0
   34:	areturn
  LineNumberTable: 
   line 40: 0
   line 41: 10
   line 42: 18
   line 44: 33

  LocalVariableTable: 
   Start  Length  Slot  Name   Signature
   0      35      0    $this       Lscala/collection/mutable/ObservableSet;
   0      35      1    elem$2       Ljava/lang/Object;


public static scala.collection.mutable.ObservableSet $plus$eq(scala.collection.mutable.ObservableSet, java.lang.Object);
  Code:
   Stack=5, Locals=2, Args_size=2
   0:	aload_0
   1:	aload_1
   2:	invokeinterface	#35,  2; //InterfaceMethod scala/collection/SetLike.contains:(Ljava/lang/Object;)Z
   7:	ifne	33
   10:	aload_0
   11:	aload_1
   12:	invokeinterface	#50,  2; //InterfaceMethod scala/collection/mutable/ObservableSet.scala$collection$mutable$ObservableSet$$super$$plus$eq:(Ljava/lang/Object;)Lscala/collection/mutable/ObservableSet;
   17:	pop
   18:	aload_0
   19:	new	#52; //class scala/collection/mutable/ObservableSet$$anon$1
   22:	dup
   23:	aload_0
   24:	aload_1
   25:	invokespecial	#53; //Method scala/collection/mutable/ObservableSet$$anon$1."<init>":(Lscala/collection/mutable/ObservableSet;Ljava/lang/Object;)V
   28:	invokeinterface	#27,  2; //InterfaceMethod scala/collection/mutable/Publisher.publish:(Ljava/lang/Object;)V
   33:	aload_0
   34:	areturn
  LineNumberTable: 
   line 32: 0
   line 33: 10
   line 34: 18
   line 36: 33

  LocalVariableTable: 
   Start  Length  Slot  Name   Signature
   0      35      0    $this       Lscala/collection/mutable/ObservableSet;
   0      35      1    elem$1       Ljava/lang/Object;


}

