Compiled from "ObservableSet.scala"
public final class scala.collection.mutable.ObservableSet$$anon$2 extends scala.collection.script.Remove implements scala.collection.mutable.Undoable
  SourceFile: "ObservableSet.scala"
  Signature: length = 0x2
   00 27 
  Scala: length = 0x
   
  InnerClass: 
   public final #42= #15 of #34; //$anon$2=class scala/collection/mutable/ObservableSet$$anon$2 of class scala/collection/mutable/ObservableSet
  minor version: 0
  major version: 49
  Constant pool:
const #1 = Asciz	SourceFile;
const #2 = Asciz	ObservableSet.scala;
const #3 = Asciz	$outer;
const #4 = Asciz	Lscala/collection/mutable/ObservableSet;;
const #5 = Asciz	<init>;
const #6 = Asciz	(Lscala/collection/mutable/ObservableSet;Ljava/lang/Object;)V;
const #7 = Asciz	Code;
const #8 = Asciz	LineNumberTable;
const #9 = Asciz	java/lang/NullPointerException;
const #10 = class	#9;	//  java/lang/NullPointerException
const #11 = Asciz	()V;
const #12 = NameAndType	#5:#11;//  "<init>":()V
const #13 = Method	#10.#12;	//  java/lang/NullPointerException."<init>":()V
const #14 = Asciz	scala/collection/mutable/ObservableSet$$anon$2;
const #15 = class	#14;	//  scala/collection/mutable/ObservableSet$$anon$2
const #16 = NameAndType	#3:#4;//  $outer:Lscala/collection/mutable/ObservableSet;
const #17 = Field	#15.#16;	//  scala/collection/mutable/ObservableSet$$anon$2.$outer:Lscala/collection/mutable/ObservableSet;
const #18 = Asciz	scala/collection/script/Remove;
const #19 = class	#18;	//  scala/collection/script/Remove
const #20 = Asciz	(Ljava/lang/Object;)V;
const #21 = NameAndType	#5:#20;//  "<init>":(Ljava/lang/Object;)V
const #22 = Method	#19.#21;	//  scala/collection/script/Remove."<init>":(Ljava/lang/Object;)V
const #23 = Asciz	this;
const #24 = Asciz	Lscala/collection/mutable/ObservableSet$$anon$2;;
const #25 = Asciz	LocalVariableTable;
const #26 = Asciz	(TThis;)V;
const #27 = Asciz	Signature;
const #28 = Asciz	undo;
const #29 = Asciz	elem;
const #30 = Asciz	()Ljava/lang/Object;;
const #31 = NameAndType	#29:#30;//  elem:()Ljava/lang/Object;
const #32 = Method	#15.#31;	//  scala/collection/mutable/ObservableSet$$anon$2.elem:()Ljava/lang/Object;
const #33 = Asciz	scala/collection/mutable/ObservableSet;
const #34 = class	#33;	//  scala/collection/mutable/ObservableSet
const #35 = Asciz	$plus$eq;
const #36 = Asciz	(Ljava/lang/Object;)Lscala/collection/mutable/ObservableSet;;
const #37 = NameAndType	#35:#36;//  $plus$eq:(Ljava/lang/Object;)Lscala/collection/mutable/ObservableSet;
const #38 = InterfaceMethod	#34.#37;	//  scala/collection/mutable/ObservableSet.$plus$eq:(Ljava/lang/Object;)Lscala/collection/mutable/ObservableSet;
const #39 = Asciz	Lscala/collection/script/Remove<TA;>;Lscala/collection/mutable/Undoable;;
const #40 = Asciz	Scala;
const #41 = Asciz	InnerClasses;
const #42 = Asciz	$anon$2;
const #43 = Asciz	scala/collection/mutable/Undoable;
const #44 = class	#43;	//  scala/collection/mutable/Undoable

{
public scala.collection.mutable.ObservableSet$$anon$2(scala.collection.mutable.ObservableSet, java.lang.Object);
  Code:
   Stack=2, Locals=3, Args_size=3
   0:	aload_1
   1:	ifnonnull	12
   4:	new	#10; //class java/lang/NullPointerException
   7:	dup
   8:	invokespecial	#13; //Method java/lang/NullPointerException."<init>":()V
   11:	athrow
   12:	aload_0
   13:	aload_1
   14:	putfield	#17; //Field $outer:Lscala/collection/mutable/ObservableSet;
   17:	aload_0
   18:	aload_2
   19:	invokespecial	#22; //Method scala/collection/script/Remove."<init>":(Ljava/lang/Object;)V
   22:	return
  LineNumberTable: 
   line 40: 0

  LocalVariableTable: 
   Start  Length  Slot  Name   Signature
   0      23      0    this       Lscala/collection/mutable/ObservableSet$$anon$2;
   0      23      1    $outer       Lscala/collection/mutable/ObservableSet;

  Signature: length = 0x2
   00 1A 

public void undo();
  Code:
   Stack=2, Locals=1, Args_size=1
   0:	aload_0
   1:	getfield	#17; //Field $outer:Lscala/collection/mutable/ObservableSet;
   4:	aload_0
   5:	invokevirtual	#32; //Method elem:()Ljava/lang/Object;
   8:	invokeinterface	#38,  2; //InterfaceMethod scala/collection/mutable/ObservableSet.$plus$eq:(Ljava/lang/Object;)Lscala/collection/mutable/ObservableSet;
   13:	pop
   14:	return
  LineNumberTable: 
   line 40: 0


}

