Compiled from "ObservableBuffer.scala"
public final class scala.collection.mutable.ObservableBuffer$$anon$2 extends scala.collection.script.Include implements scala.collection.mutable.Undoable
  SourceFile: "ObservableBuffer.scala"
  Signature: length = 0x2
   00 29 
  Scala: length = 0x
   
  InnerClass: 
   public final #46= #15 of #45; //$anon$2=class scala/collection/mutable/ObservableBuffer$$anon$2 of class scala/collection/mutable/ObservableBuffer
  minor version: 0
  major version: 49
  Constant pool:
const #1 = Asciz	SourceFile;
const #2 = Asciz	ObservableBuffer.scala;
const #3 = Asciz	$outer;
const #4 = Asciz	Lscala/collection/mutable/ObservableBuffer;;
const #5 = Asciz	<init>;
const #6 = Asciz	(Lscala/collection/mutable/ObservableBuffer;Ljava/lang/Object;)V;
const #7 = Asciz	Code;
const #8 = Asciz	LineNumberTable;
const #9 = Asciz	java/lang/NullPointerException;
const #10 = class	#9;	//  java/lang/NullPointerException
const #11 = Asciz	()V;
const #12 = NameAndType	#5:#11;//  "<init>":()V
const #13 = Method	#10.#12;	//  java/lang/NullPointerException."<init>":()V
const #14 = Asciz	scala/collection/mutable/ObservableBuffer$$anon$2;
const #15 = class	#14;	//  scala/collection/mutable/ObservableBuffer$$anon$2
const #16 = NameAndType	#3:#4;//  $outer:Lscala/collection/mutable/ObservableBuffer;
const #17 = Field	#15.#16;	//  scala/collection/mutable/ObservableBuffer$$anon$2.$outer:Lscala/collection/mutable/ObservableBuffer;
const #18 = Asciz	scala/collection/script/Start$;
const #19 = class	#18;	//  scala/collection/script/Start$
const #20 = Asciz	MODULE$;
const #21 = Asciz	Lscala/collection/script/Start$;;
const #22 = NameAndType	#20:#21;//  MODULE$:Lscala/collection/script/Start$;
const #23 = Field	#19.#22;	//  scala/collection/script/Start$.MODULE$:Lscala/collection/script/Start$;
const #24 = Asciz	scala/collection/script/Include;
const #25 = class	#24;	//  scala/collection/script/Include
const #26 = Asciz	(Lscala/collection/script/Location;Ljava/lang/Object;)V;
const #27 = NameAndType	#5:#26;//  "<init>":(Lscala/collection/script/Location;Ljava/lang/Object;)V
const #28 = Method	#25.#27;	//  scala/collection/script/Include."<init>":(Lscala/collection/script/Location;Ljava/lang/Object;)V
const #29 = Asciz	this;
const #30 = Asciz	Lscala/collection/mutable/ObservableBuffer$$anon$2;;
const #31 = Asciz	LocalVariableTable;
const #32 = Asciz	(TThis;)V;
const #33 = Asciz	Signature;
const #34 = Asciz	undo;
const #35 = Asciz	scala/collection/generic/BufferTemplate;
const #36 = class	#35;	//  scala/collection/generic/BufferTemplate
const #37 = Asciz	trimStart;
const #38 = Asciz	(I)V;
const #39 = NameAndType	#37:#38;//  trimStart:(I)V
const #40 = InterfaceMethod	#36.#39;	//  scala/collection/generic/BufferTemplate.trimStart:(I)V
const #41 = Asciz	Lscala/collection/script/Include<TA;>;Lscala/collection/mutable/Undoable;;
const #42 = Asciz	Scala;
const #43 = Asciz	InnerClasses;
const #44 = Asciz	scala/collection/mutable/ObservableBuffer;
const #45 = class	#44;	//  scala/collection/mutable/ObservableBuffer
const #46 = Asciz	$anon$2;
const #47 = Asciz	scala/collection/mutable/Undoable;
const #48 = class	#47;	//  scala/collection/mutable/Undoable

{
public scala.collection.mutable.ObservableBuffer$$anon$2(scala.collection.mutable.ObservableBuffer, java.lang.Object);
  Code:
   Stack=3, Locals=3, Args_size=3
   0:	aload_1
   1:	ifnonnull	12
   4:	new	#10; //class java/lang/NullPointerException
   7:	dup
   8:	invokespecial	#13; //Method java/lang/NullPointerException."<init>":()V
   11:	athrow
   12:	aload_0
   13:	aload_1
   14:	putfield	#17; //Field $outer:Lscala/collection/mutable/ObservableBuffer;
   17:	aload_0
   18:	getstatic	#23; //Field scala/collection/script/Start$.MODULE$:Lscala/collection/script/Start$;
   21:	aload_2
   22:	invokespecial	#28; //Method scala/collection/script/Include."<init>":(Lscala/collection/script/Location;Ljava/lang/Object;)V
   25:	return
  LineNumberTable: 
   line 39: 0

  LocalVariableTable: 
   Start  Length  Slot  Name   Signature
   0      26      0    this       Lscala/collection/mutable/ObservableBuffer$$anon$2;
   0      26      1    $outer       Lscala/collection/mutable/ObservableBuffer;

  Signature: length = 0x2
   00 20 

public void undo();
  Code:
   Stack=2, Locals=1, Args_size=1
   0:	aload_0
   1:	getfield	#17; //Field $outer:Lscala/collection/mutable/ObservableBuffer;
   4:	iconst_1
   5:	invokeinterface	#40,  2; //InterfaceMethod scala/collection/generic/BufferTemplate.trimStart:(I)V
   10:	return
  LineNumberTable: 
   line 40: 0


}

