Compiled from "ObservableBuffer.scala"
public abstract class scala.collection.mutable.ObservableBuffer$class extends java.lang.Object
  SourceFile: "ObservableBuffer.scala"
  Scala: length = 0x
   
  InnerClass: 
   public final #84= #40 of #12; //$anon$4=class scala/collection/mutable/ObservableBuffer$$anon$4 of class scala/collection/mutable/ObservableBuffer
   public final #85= #68 of #12; //$anon$2=class scala/collection/mutable/ObservableBuffer$$anon$2 of class scala/collection/mutable/ObservableBuffer
   public final #86= #54 of #12; //$anon$3=class scala/collection/mutable/ObservableBuffer$$anon$3 of class scala/collection/mutable/ObservableBuffer
   public final #87= #18 of #12; //$anon$5=class scala/collection/mutable/ObservableBuffer$$anon$5 of class scala/collection/mutable/ObservableBuffer
   public final #88= #79 of #12; //$anon$1=class scala/collection/mutable/ObservableBuffer$$anon$1 of class scala/collection/mutable/ObservableBuffer
  minor version: 0
  major version: 49
  Constant pool:
const #1 = Asciz	SourceFile;
const #2 = Asciz	ObservableBuffer.scala;
const #3 = Asciz	$init$;
const #4 = Asciz	(Lscala/collection/mutable/ObservableBuffer;)V;
const #5 = Asciz	Code;
const #6 = Asciz	LineNumberTable;
const #7 = Asciz	$this;
const #8 = Asciz	Lscala/collection/mutable/ObservableBuffer;;
const #9 = Asciz	LocalVariableTable;
const #10 = Asciz	clear;
const #11 = Asciz	scala/collection/mutable/ObservableBuffer;
const #12 = class	#11;	//  scala/collection/mutable/ObservableBuffer
const #13 = Asciz	scala$collection$mutable$ObservableBuffer$$super$clear;
const #14 = Asciz	()V;
const #15 = NameAndType	#13:#14;//  scala$collection$mutable$ObservableBuffer$$super$clear:()V
const #16 = InterfaceMethod	#12.#15;	//  scala/collection/mutable/ObservableBuffer.scala$collection$mutable$ObservableBuffer$$super$clear:()V
const #17 = Asciz	scala/collection/mutable/ObservableBuffer$$anon$5;
const #18 = class	#17;	//  scala/collection/mutable/ObservableBuffer$$anon$5
const #19 = Asciz	<init>;
const #20 = NameAndType	#19:#4;//  "<init>":(Lscala/collection/mutable/ObservableBuffer;)V
const #21 = Method	#18.#20;	//  scala/collection/mutable/ObservableBuffer$$anon$5."<init>":(Lscala/collection/mutable/ObservableBuffer;)V
const #22 = Asciz	scala/collection/mutable/Publisher;
const #23 = class	#22;	//  scala/collection/mutable/Publisher
const #24 = Asciz	publish;
const #25 = Asciz	(Ljava/lang/Object;)V;
const #26 = NameAndType	#24:#25;//  publish:(Ljava/lang/Object;)V
const #27 = InterfaceMethod	#23.#26;	//  scala/collection/mutable/Publisher.publish:(Ljava/lang/Object;)V
const #28 = Asciz	remove;
const #29 = Asciz	(Lscala/collection/mutable/ObservableBuffer;I)Ljava/lang/Object;;
const #30 = Asciz	scala/collection/generic/BufferTemplate;
const #31 = class	#30;	//  scala/collection/generic/BufferTemplate
const #32 = Asciz	apply;
const #33 = Asciz	(I)Ljava/lang/Object;;
const #34 = NameAndType	#32:#33;//  apply:(I)Ljava/lang/Object;
const #35 = InterfaceMethod	#31.#34;	//  scala/collection/generic/BufferTemplate.apply:(I)Ljava/lang/Object;
const #36 = Asciz	scala$collection$mutable$ObservableBuffer$$super$remove;
const #37 = NameAndType	#36:#33;//  scala$collection$mutable$ObservableBuffer$$super$remove:(I)Ljava/lang/Object;
const #38 = InterfaceMethod	#12.#37;	//  scala/collection/mutable/ObservableBuffer.scala$collection$mutable$ObservableBuffer$$super$remove:(I)Ljava/lang/Object;
const #39 = Asciz	scala/collection/mutable/ObservableBuffer$$anon$4;
const #40 = class	#39;	//  scala/collection/mutable/ObservableBuffer$$anon$4
const #41 = Asciz	(Lscala/collection/mutable/ObservableBuffer;ILjava/lang/Object;)V;
const #42 = NameAndType	#19:#41;//  "<init>":(Lscala/collection/mutable/ObservableBuffer;ILjava/lang/Object;)V
const #43 = Method	#40.#42;	//  scala/collection/mutable/ObservableBuffer$$anon$4."<init>":(Lscala/collection/mutable/ObservableBuffer;ILjava/lang/Object;)V
const #44 = Asciz	n$2;
const #45 = Asciz	I;
const #46 = Asciz	oldelement$2;
const #47 = Asciz	Ljava/lang/Object;;
const #48 = Asciz	update;
const #49 = Asciz	scala$collection$mutable$ObservableBuffer$$super$update;
const #50 = Asciz	(ILjava/lang/Object;)V;
const #51 = NameAndType	#49:#50;//  scala$collection$mutable$ObservableBuffer$$super$update:(ILjava/lang/Object;)V
const #52 = InterfaceMethod	#12.#51;	//  scala/collection/mutable/ObservableBuffer.scala$collection$mutable$ObservableBuffer$$super$update:(ILjava/lang/Object;)V
const #53 = Asciz	scala/collection/mutable/ObservableBuffer$$anon$3;
const #54 = class	#53;	//  scala/collection/mutable/ObservableBuffer$$anon$3
const #55 = Asciz	(Lscala/collection/mutable/ObservableBuffer;ILjava/lang/Object;Ljava/lang/Object;)V;
const #56 = NameAndType	#19:#55;//  "<init>":(Lscala/collection/mutable/ObservableBuffer;ILjava/lang/Object;Ljava/lang/Object;)V
const #57 = Method	#54.#56;	//  scala/collection/mutable/ObservableBuffer$$anon$3."<init>":(Lscala/collection/mutable/ObservableBuffer;ILjava/lang/Object;Ljava/lang/Object;)V
const #58 = Asciz	n$1;
const #59 = Asciz	newelement$1;
const #60 = Asciz	oldelement$1;
const #61 = Asciz	$plus$colon;
const #62 = Asciz	(Lscala/collection/mutable/ObservableBuffer;Ljava/lang/Object;)Lscala/collection/mutable/ObservableBuffer;;
const #63 = Asciz	scala$collection$mutable$ObservableBuffer$$super$$plus$colon;
const #64 = Asciz	(Ljava/lang/Object;)Lscala/collection/mutable/Buffer;;
const #65 = NameAndType	#63:#64;//  scala$collection$mutable$ObservableBuffer$$super$$plus$colon:(Ljava/lang/Object;)Lscala/collection/mutable/Buffer;
const #66 = InterfaceMethod	#12.#65;	//  scala/collection/mutable/ObservableBuffer.scala$collection$mutable$ObservableBuffer$$super$$plus$colon:(Ljava/lang/Object;)Lscala/collection/mutable/Buffer;
const #67 = Asciz	scala/collection/mutable/ObservableBuffer$$anon$2;
const #68 = class	#67;	//  scala/collection/mutable/ObservableBuffer$$anon$2
const #69 = Asciz	(Lscala/collection/mutable/ObservableBuffer;Ljava/lang/Object;)V;
const #70 = NameAndType	#19:#69;//  "<init>":(Lscala/collection/mutable/ObservableBuffer;Ljava/lang/Object;)V
const #71 = Method	#68.#70;	//  scala/collection/mutable/ObservableBuffer$$anon$2."<init>":(Lscala/collection/mutable/ObservableBuffer;Ljava/lang/Object;)V
const #72 = Asciz	element$2;
const #73 = Asciz	$plus$eq;
const #74 = Asciz	scala$collection$mutable$ObservableBuffer$$super$$plus$eq;
const #75 = Asciz	(Ljava/lang/Object;)Lscala/collection/mutable/ObservableBuffer;;
const #76 = NameAndType	#74:#75;//  scala$collection$mutable$ObservableBuffer$$super$$plus$eq:(Ljava/lang/Object;)Lscala/collection/mutable/ObservableBuffer;
const #77 = InterfaceMethod	#12.#76;	//  scala/collection/mutable/ObservableBuffer.scala$collection$mutable$ObservableBuffer$$super$$plus$eq:(Ljava/lang/Object;)Lscala/collection/mutable/ObservableBuffer;
const #78 = Asciz	scala/collection/mutable/ObservableBuffer$$anon$1;
const #79 = class	#78;	//  scala/collection/mutable/ObservableBuffer$$anon$1
const #80 = Method	#79.#70;	//  scala/collection/mutable/ObservableBuffer$$anon$1."<init>":(Lscala/collection/mutable/ObservableBuffer;Ljava/lang/Object;)V
const #81 = Asciz	element$1;
const #82 = Asciz	Scala;
const #83 = Asciz	InnerClasses;
const #84 = Asciz	$anon$4;
const #85 = Asciz	$anon$2;
const #86 = Asciz	$anon$3;
const #87 = Asciz	$anon$5;
const #88 = Asciz	$anon$1;
const #89 = Asciz	scala/collection/mutable/ObservableBuffer$class;
const #90 = class	#89;	//  scala/collection/mutable/ObservableBuffer$class
const #91 = Asciz	java/lang/Object;
const #92 = class	#91;	//  java/lang/Object

{
public static void $init$(scala.collection.mutable.ObservableBuffer);
  Code:
   Stack=0, Locals=1, Args_size=1
   0:	return
  LineNumberTable: 
   line 25: 0

  LocalVariableTable: 
   Start  Length  Slot  Name   Signature
   0      1      0    $this       Lscala/collection/mutable/ObservableBuffer;


public static void clear(scala.collection.mutable.ObservableBuffer);
  Code:
   Stack=4, Locals=1, Args_size=1
   0:	aload_0
   1:	invokeinterface	#16,  1; //InterfaceMethod scala/collection/mutable/ObservableBuffer.scala$collection$mutable$ObservableBuffer$$super$clear:()V
   6:	aload_0
   7:	new	#18; //class scala/collection/mutable/ObservableBuffer$$anon$5
   10:	dup
   11:	aload_0
   12:	invokespecial	#21; //Method scala/collection/mutable/ObservableBuffer$$anon$5."<init>":(Lscala/collection/mutable/ObservableBuffer;)V
   15:	invokeinterface	#27,  2; //InterfaceMethod scala/collection/mutable/Publisher.publish:(Ljava/lang/Object;)V
   20:	return
  LineNumberTable: 
   line 63: 0
   line 64: 6

  LocalVariableTable: 
   Start  Length  Slot  Name   Signature
   0      21      0    $this       Lscala/collection/mutable/ObservableBuffer;


public static java.lang.Object remove(scala.collection.mutable.ObservableBuffer, int);
  Code:
   Stack=6, Locals=3, Args_size=2
   0:	aload_0
   1:	iload_1
   2:	invokeinterface	#35,  2; //InterfaceMethod scala/collection/generic/BufferTemplate.apply:(I)Ljava/lang/Object;
   7:	astore_2
   8:	aload_0
   9:	iload_1
   10:	invokeinterface	#38,  2; //InterfaceMethod scala/collection/mutable/ObservableBuffer.scala$collection$mutable$ObservableBuffer$$super$remove:(I)Ljava/lang/Object;
   15:	pop
   16:	aload_0
   17:	new	#40; //class scala/collection/mutable/ObservableBuffer$$anon$4
   20:	dup
   21:	aload_0
   22:	iload_1
   23:	aload_2
   24:	invokespecial	#43; //Method scala/collection/mutable/ObservableBuffer$$anon$4."<init>":(Lscala/collection/mutable/ObservableBuffer;ILjava/lang/Object;)V
   27:	invokeinterface	#27,  2; //InterfaceMethod scala/collection/mutable/Publisher.publish:(Ljava/lang/Object;)V
   32:	aload_2
   33:	areturn
  LineNumberTable: 
   line 54: 0
   line 55: 8
   line 56: 16
   line 59: 32

  LocalVariableTable: 
   Start  Length  Slot  Name   Signature
   0      34      0    $this       Lscala/collection/mutable/ObservableBuffer;
   0      34      1    n$2       I
   8      25      2    oldelement$2       Ljava/lang/Object;


public static void update(scala.collection.mutable.ObservableBuffer, int, java.lang.Object);
  Code:
   Stack=7, Locals=4, Args_size=3
   0:	aload_0
   1:	iload_1
   2:	invokeinterface	#35,  2; //InterfaceMethod scala/collection/generic/BufferTemplate.apply:(I)Ljava/lang/Object;
   7:	astore_3
   8:	aload_0
   9:	iload_1
   10:	aload_2
   11:	invokeinterface	#52,  3; //InterfaceMethod scala/collection/mutable/ObservableBuffer.scala$collection$mutable$ObservableBuffer$$super$update:(ILjava/lang/Object;)V
   16:	aload_0
   17:	new	#54; //class scala/collection/mutable/ObservableBuffer$$anon$3
   20:	dup
   21:	aload_0
   22:	iload_1
   23:	aload_2
   24:	aload_3
   25:	invokespecial	#57; //Method scala/collection/mutable/ObservableBuffer$$anon$3."<init>":(Lscala/collection/mutable/ObservableBuffer;ILjava/lang/Object;Ljava/lang/Object;)V
   28:	invokeinterface	#27,  2; //InterfaceMethod scala/collection/mutable/Publisher.publish:(Ljava/lang/Object;)V
   33:	return
  LineNumberTable: 
   line 46: 0
   line 47: 8
   line 48: 16

  LocalVariableTable: 
   Start  Length  Slot  Name   Signature
   0      34      0    $this       Lscala/collection/mutable/ObservableBuffer;
   0      34      1    n$1       I
   0      34      2    newelement$1       Ljava/lang/Object;
   8      25      3    oldelement$1       Ljava/lang/Object;


public static scala.collection.mutable.ObservableBuffer $plus$colon(scala.collection.mutable.ObservableBuffer, java.lang.Object);
  Code:
   Stack=5, Locals=2, Args_size=2
   0:	aload_0
   1:	aload_1
   2:	invokeinterface	#66,  2; //InterfaceMethod scala/collection/mutable/ObservableBuffer.scala$collection$mutable$ObservableBuffer$$super$$plus$colon:(Ljava/lang/Object;)Lscala/collection/mutable/Buffer;
   7:	pop
   8:	aload_0
   9:	new	#68; //class scala/collection/mutable/ObservableBuffer$$anon$2
   12:	dup
   13:	aload_0
   14:	aload_1
   15:	invokespecial	#71; //Method scala/collection/mutable/ObservableBuffer$$anon$2."<init>":(Lscala/collection/mutable/ObservableBuffer;Ljava/lang/Object;)V
   18:	invokeinterface	#27,  2; //InterfaceMethod scala/collection/mutable/Publisher.publish:(Ljava/lang/Object;)V
   23:	aload_0
   24:	areturn
  LineNumberTable: 
   line 38: 0
   line 39: 8
   line 42: 23

  LocalVariableTable: 
   Start  Length  Slot  Name   Signature
   0      25      0    $this       Lscala/collection/mutable/ObservableBuffer;
   0      25      1    element$2       Ljava/lang/Object;


public static scala.collection.mutable.ObservableBuffer $plus$eq(scala.collection.mutable.ObservableBuffer, java.lang.Object);
  Code:
   Stack=5, Locals=2, Args_size=2
   0:	aload_0
   1:	aload_1
   2:	invokeinterface	#77,  2; //InterfaceMethod scala/collection/mutable/ObservableBuffer.scala$collection$mutable$ObservableBuffer$$super$$plus$eq:(Ljava/lang/Object;)Lscala/collection/mutable/ObservableBuffer;
   7:	pop
   8:	aload_0
   9:	new	#79; //class scala/collection/mutable/ObservableBuffer$$anon$1
   12:	dup
   13:	aload_0
   14:	aload_1
   15:	invokespecial	#80; //Method scala/collection/mutable/ObservableBuffer$$anon$1."<init>":(Lscala/collection/mutable/ObservableBuffer;Ljava/lang/Object;)V
   18:	invokeinterface	#27,  2; //InterfaceMethod scala/collection/mutable/Publisher.publish:(Ljava/lang/Object;)V
   23:	aload_0
   24:	areturn
  LineNumberTable: 
   line 30: 0
   line 31: 8
   line 34: 23

  LocalVariableTable: 
   Start  Length  Slot  Name   Signature
   0      25      0    $this       Lscala/collection/mutable/ObservableBuffer;
   0      25      1    element$1       Ljava/lang/Object;


}

