Compiled from "ObservableBuffer.scala"
public final class scala.collection.mutable.ObservableBuffer$$anon$4 extends scala.collection.script.Remove implements scala.collection.mutable.Undoable
  SourceFile: "ObservableBuffer.scala"
  Signature: length = 0x2
   00 3C 
  Scala: length = 0x
   
  InnerClass: 
   public final $anon$4=class scala/collection/mutable/ObservableBuffer$$anon$4 of class scala/collection/mutable/ObservableBuffer
  minor version: 0
  major version: 49
  Constant pool:
Asciz	SourceFile;
Asciz	ObservableBuffer.scala;
Asciz	oldelement$2;
Asciz	Ljava/lang/Object;;
Asciz	n$2;
Asciz	I;
Asciz	$outer;
Asciz	Lscala/collection/mutable/ObservableBuffer;;
Asciz	undo;
Asciz	()V;
Asciz	Code;
Asciz	LineNumberTable;
Asciz	scala/collection/mutable/ObservableBuffer$$anon$4;
class	scala/collection/mutable/ObservableBuffer$$anon$4
NameAndType	$outer:Lscala/collection/mutable/ObservableBuffer;
Field	scala/collection/mutable/ObservableBuffer$$anon$4.$outer:Lscala/collection/mutable/ObservableBuffer;
NameAndType	n$2:I
Field	scala/collection/mutable/ObservableBuffer$$anon$4.n$2:I
Asciz	scala/Predef$;
class	scala/Predef$
Asciz	MODULE$;
Asciz	Lscala/Predef$;;
NameAndType	MODULE$:Lscala/Predef$;
Field	scala/Predef$.MODULE$:Lscala/Predef$;
Asciz	java/lang/Object;
class	java/lang/Object
NameAndType	oldelement$2:Ljava/lang/Object;
Field	scala/collection/mutable/ObservableBuffer$$anon$4.oldelement$2:Ljava/lang/Object;
Asciz	genericWrapArray;
Asciz	(Ljava/lang/Object;)Lscala/collection/mutable/WrappedArray;;
NameAndType	genericWrapArray:(Ljava/lang/Object;)Lscala/collection/mutable/WrappedArray;
Method	scala/Predef$.genericWrapArray:(Ljava/lang/Object;)Lscala/collection/mutable/WrappedArray;
Asciz	scala/collection/mutable/BufferLike;
class	scala/collection/mutable/BufferLike
Asciz	insert;
Asciz	(ILscala/collection/Seq;)V;
NameAndType	insert:(ILscala/collection/Seq;)V
InterfaceMethod	scala/collection/mutable/BufferLike.insert:(ILscala/collection/Seq;)V
Asciz	<init>;
Asciz	(Lscala/collection/mutable/ObservableBuffer;ILjava/lang/Object;)V;
Asciz	java/lang/NullPointerException;
class	java/lang/NullPointerException
NameAndType	"<init>":()V
Method	java/lang/NullPointerException."<init>":()V
Asciz	scala/collection/script/Index;
class	scala/collection/script/Index
Asciz	(I)V;
NameAndType	"<init>":(I)V
Method	scala/collection/script/Index."<init>":(I)V
Asciz	scala/collection/script/Remove;
class	scala/collection/script/Remove
Asciz	(Lscala/collection/script/Location;Ljava/lang/Object;)V;
NameAndType	"<init>":(Lscala/collection/script/Location;Ljava/lang/Object;)V
Method	scala/collection/script/Remove."<init>":(Lscala/collection/script/Location;Ljava/lang/Object;)V
Asciz	this;
Asciz	Lscala/collection/mutable/ObservableBuffer$$anon$4;;
Asciz	LocalVariableTable;
Asciz	(Lscala/collection/mutable/ObservableBuffer<TA;>;)V;
Asciz	Signature;
Asciz	Lscala/collection/script/Remove<TA;>;Lscala/collection/mutable/Undoable;;
Asciz	Scala;
Asciz	InnerClasses;
Asciz	scala/collection/mutable/ObservableBuffer;
class	scala/collection/mutable/ObservableBuffer
Asciz	$anon$4;
Asciz	scala/collection/mutable/Undoable;
class	scala/collection/mutable/Undoable

{
private final java.lang.Object oldelement$2;
  Signature: Ljava/lang/Object;

private final int n$2;
  Signature: I

private final scala.collection.mutable.ObservableBuffer $outer;
  Signature: Lscala/collection/mutable/ObservableBuffer;

public void undo();
  Signature: ()V
  Code:
   Stack=7, Locals=1, Args_size=1
	aload_0
	getfield	Field $outer:Lscala/collection/mutable/ObservableBuffer;
	aload_0
	getfield	Field n$2:I
	getstatic	Field scala/Predef$.MODULE$:Lscala/Predef$;
	iconst_1
	anewarray	class java/lang/Object
	dup
	iconst_0
	aload_0
	getfield	Field oldelement$2:Ljava/lang/Object;
	aastore
	invokevirtual	Method scala/Predef$.genericWrapArray:(Ljava/lang/Object;)Lscala/collection/mutable/WrappedArray;
	invokeinterface	InterfaceMethod scala/collection/mutable/BufferLike.insert:(ILscala/collection/Seq;)V
	return
  Labels:

public scala.collection.mutable.ObservableBuffer$$anon$4(scala.collection.mutable.ObservableBuffer, int, java.lang.Object);
  Signature: (Lscala/collection/mutable/ObservableBuffer;ILjava/lang/Object;)V
  Code:
   Stack=4, Locals=4, Args_size=4
	aload_1
	ifnonnull	l1 // aload_0
	new	class java/lang/NullPointerException
	dup
	invokespecial	Method java/lang/NullPointerException."<init>":()V
	athrow
l1	aload_0
	aload_1
	putfield	Field $outer:Lscala/collection/mutable/ObservableBuffer;
	aload_0
	iload_2
	putfield	Field n$2:I
	aload_0
	aload_3
	putfield	Field oldelement$2:Ljava/lang/Object;
	aload_0
	new	class scala/collection/script/Index
	dup
	iload_2
	invokespecial	Method scala/collection/script/Index."<init>":(I)V
	aload_3
	invokespecial	Method scala/collection/script/Remove."<init>":(Lscala/collection/script/Location;Ljava/lang/Object;)V
	return
  Labels:
   	l1 = 12 // aload_0
  LocalVariableTable: 
   Start  Length  Slot  Name   Signature
   0      41      0    this       Lscala/collection/mutable/ObservableBuffer$$anon$4;
   0      41      1    $outer       Lscala/collection/mutable/ObservableBuffer;

  Signature: length = 0x2
   00 3A 

}

