Compiled from "ObservableBuffer.scala"
public final class scala.collection.mutable.ObservableBuffer$$anon$4 extends scala.collection.script.Remove implements scala.collection.mutable.Undoable
  SourceFile: "ObservableBuffer.scala"
  Signature: length = 0x2
   00 3C 
  Scala: length = 0x
   
  InnerClass: 
   public final #65= #19 of #64; //$anon$4=class scala/collection/mutable/ObservableBuffer$$anon$4 of class scala/collection/mutable/ObservableBuffer
  minor version: 0
  major version: 49
  Constant pool:
const #1 = Asciz	SourceFile;
const #2 = Asciz	ObservableBuffer.scala;
const #3 = Asciz	oldelement$2;
const #4 = Asciz	Ljava/lang/Object;;
const #5 = Asciz	n$2;
const #6 = Asciz	I;
const #7 = Asciz	$outer;
const #8 = Asciz	Lscala/collection/mutable/ObservableBuffer;;
const #9 = Asciz	<init>;
const #10 = Asciz	(Lscala/collection/mutable/ObservableBuffer;ILjava/lang/Object;)V;
const #11 = Asciz	Code;
const #12 = Asciz	LineNumberTable;
const #13 = Asciz	java/lang/NullPointerException;
const #14 = class	#13;	//  java/lang/NullPointerException
const #15 = Asciz	()V;
const #16 = NameAndType	#9:#15;//  "<init>":()V
const #17 = Method	#14.#16;	//  java/lang/NullPointerException."<init>":()V
const #18 = Asciz	scala/collection/mutable/ObservableBuffer$$anon$4;
const #19 = class	#18;	//  scala/collection/mutable/ObservableBuffer$$anon$4
const #20 = NameAndType	#7:#8;//  $outer:Lscala/collection/mutable/ObservableBuffer;
const #21 = Field	#19.#20;	//  scala/collection/mutable/ObservableBuffer$$anon$4.$outer:Lscala/collection/mutable/ObservableBuffer;
const #22 = NameAndType	#5:#6;//  n$2:I
const #23 = Field	#19.#22;	//  scala/collection/mutable/ObservableBuffer$$anon$4.n$2:I
const #24 = NameAndType	#3:#4;//  oldelement$2:Ljava/lang/Object;
const #25 = Field	#19.#24;	//  scala/collection/mutable/ObservableBuffer$$anon$4.oldelement$2:Ljava/lang/Object;
const #26 = Asciz	scala/collection/script/Index;
const #27 = class	#26;	//  scala/collection/script/Index
const #28 = Asciz	(I)V;
const #29 = NameAndType	#9:#28;//  "<init>":(I)V
const #30 = Method	#27.#29;	//  scala/collection/script/Index."<init>":(I)V
const #31 = Asciz	scala/collection/script/Remove;
const #32 = class	#31;	//  scala/collection/script/Remove
const #33 = Asciz	(Lscala/collection/script/Location;Ljava/lang/Object;)V;
const #34 = NameAndType	#9:#33;//  "<init>":(Lscala/collection/script/Location;Ljava/lang/Object;)V
const #35 = Method	#32.#34;	//  scala/collection/script/Remove."<init>":(Lscala/collection/script/Location;Ljava/lang/Object;)V
const #36 = Asciz	this;
const #37 = Asciz	Lscala/collection/mutable/ObservableBuffer$$anon$4;;
const #38 = Asciz	LocalVariableTable;
const #39 = Asciz	(Lscala/collection/mutable/ObservableBuffer<TA;>;)V;
const #40 = Asciz	Signature;
const #41 = Asciz	undo;
const #42 = Asciz	scala/Predef$;
const #43 = class	#42;	//  scala/Predef$
const #44 = Asciz	MODULE$;
const #45 = Asciz	Lscala/Predef$;;
const #46 = NameAndType	#44:#45;//  MODULE$:Lscala/Predef$;
const #47 = Field	#43.#46;	//  scala/Predef$.MODULE$:Lscala/Predef$;
const #48 = Asciz	java/lang/Object;
const #49 = class	#48;	//  java/lang/Object
const #50 = Asciz	genericWrapArray;
const #51 = Asciz	(Ljava/lang/Object;)Lscala/collection/mutable/WrappedArray;;
const #52 = NameAndType	#50:#51;//  genericWrapArray:(Ljava/lang/Object;)Lscala/collection/mutable/WrappedArray;
const #53 = Method	#43.#52;	//  scala/Predef$.genericWrapArray:(Ljava/lang/Object;)Lscala/collection/mutable/WrappedArray;
const #54 = Asciz	scala/collection/mutable/BufferLike;
const #55 = class	#54;	//  scala/collection/mutable/BufferLike
const #56 = Asciz	insert;
const #57 = Asciz	(ILscala/collection/Seq;)V;
const #58 = NameAndType	#56:#57;//  insert:(ILscala/collection/Seq;)V
const #59 = InterfaceMethod	#55.#58;	//  scala/collection/mutable/BufferLike.insert:(ILscala/collection/Seq;)V
const #60 = Asciz	Lscala/collection/script/Remove<TA;>;Lscala/collection/mutable/Undoable;;
const #61 = Asciz	Scala;
const #62 = Asciz	InnerClasses;
const #63 = Asciz	scala/collection/mutable/ObservableBuffer;
const #64 = class	#63;	//  scala/collection/mutable/ObservableBuffer
const #65 = Asciz	$anon$4;
const #66 = Asciz	scala/collection/mutable/Undoable;
const #67 = class	#66;	//  scala/collection/mutable/Undoable

{
public scala.collection.mutable.ObservableBuffer$$anon$4(scala.collection.mutable.ObservableBuffer, int, java.lang.Object);
  Code:
   Stack=4, Locals=4, Args_size=4
   0:	aload_1
   1:	ifnonnull	12
   4:	new	#14; //class java/lang/NullPointerException
   7:	dup
   8:	invokespecial	#17; //Method java/lang/NullPointerException."<init>":()V
   11:	athrow
   12:	aload_0
   13:	aload_1
   14:	putfield	#21; //Field $outer:Lscala/collection/mutable/ObservableBuffer;
   17:	aload_0
   18:	iload_2
   19:	putfield	#23; //Field n$2:I
   22:	aload_0
   23:	aload_3
   24:	putfield	#25; //Field oldelement$2:Ljava/lang/Object;
   27:	aload_0
   28:	new	#27; //class scala/collection/script/Index
   31:	dup
   32:	iload_2
   33:	invokespecial	#30; //Method scala/collection/script/Index."<init>":(I)V
   36:	aload_3
   37:	invokespecial	#35; //Method scala/collection/script/Remove."<init>":(Lscala/collection/script/Location;Ljava/lang/Object;)V
   40:	return
  LineNumberTable: 
   line 57: 0

  LocalVariableTable: 
   Start  Length  Slot  Name   Signature
   0      41      0    this       Lscala/collection/mutable/ObservableBuffer$$anon$4;
   0      41      1    $outer       Lscala/collection/mutable/ObservableBuffer;

  Signature: length = 0x2
   00 27 

public void undo();
  Code:
   Stack=7, Locals=1, Args_size=1
   0:	aload_0
   1:	getfield	#21; //Field $outer:Lscala/collection/mutable/ObservableBuffer;
   4:	aload_0
   5:	getfield	#23; //Field n$2:I
   8:	getstatic	#47; //Field scala/Predef$.MODULE$:Lscala/Predef$;
   11:	iconst_1
   12:	anewarray	#49; //class java/lang/Object
   15:	dup
   16:	iconst_0
   17:	aload_0
   18:	getfield	#25; //Field oldelement$2:Ljava/lang/Object;
   21:	aastore
   22:	invokevirtual	#53; //Method scala/Predef$.genericWrapArray:(Ljava/lang/Object;)Lscala/collection/mutable/WrappedArray;
   25:	invokeinterface	#59,  3; //InterfaceMethod scala/collection/mutable/BufferLike.insert:(ILscala/collection/Seq;)V
   30:	return
  LineNumberTable: 
   line 58: 0


}

