Compiled from "OpenHashMap.scala"
public final class scala.collection.mutable.OpenHashMap$$anonfun$foreach$1 extends java.lang.Object implements scala.Function1,scala.ScalaObject,java.io.Serializable
  SourceFile: "OpenHashMap.scala"
  Scala: length = 0x
   
  InnerClass: 
   public final #113= #48 of #61; //OpenEntry=class scala/collection/mutable/OpenHashMap$OpenEntry of class scala/collection/mutable/OpenHashMap
   public final #114= #9 of #61; //$anonfun$foreach$1=class scala/collection/mutable/OpenHashMap$$anonfun$foreach$1 of class scala/collection/mutable/OpenHashMap
  minor version: 0
  major version: 49
  Constant pool:
const #1 = Asciz	SourceFile;
const #2 = Asciz	OpenHashMap.scala;
const #3 = Asciz	<clinit>;
const #4 = Asciz	()V;
const #5 = Asciz	Code;
const #6 = Asciz	serialVersionUID;
const #7 = Asciz	J;
const #8 = Asciz	scala/collection/mutable/OpenHashMap$$anonfun$foreach$1;
const #9 = class	#8;	//  scala/collection/mutable/OpenHashMap$$anonfun$foreach$1
const #10 = NameAndType	#6:#7;//  serialVersionUID:J
const #11 = Field	#9.#10;	//  scala/collection/mutable/OpenHashMap$$anonfun$foreach$1.serialVersionUID:J
const #12 = Asciz	startModCount$1;
const #13 = Asciz	I;
const #14 = Asciz	f$2;
const #15 = Asciz	Lscala/Function1;;
const #16 = Asciz	$outer;
const #17 = Asciz	Lscala/collection/mutable/OpenHashMap;;
const #18 = Asciz	<init>;
const #19 = Asciz	(Lscala/collection/mutable/OpenHashMap;Lscala/Function1;I)V;
const #20 = Asciz	LineNumberTable;
const #21 = Asciz	java/lang/NullPointerException;
const #22 = class	#21;	//  java/lang/NullPointerException
const #23 = NameAndType	#18:#4;//  "<init>":()V
const #24 = Method	#22.#23;	//  java/lang/NullPointerException."<init>":()V
const #25 = NameAndType	#16:#17;//  $outer:Lscala/collection/mutable/OpenHashMap;
const #26 = Field	#9.#25;	//  scala/collection/mutable/OpenHashMap$$anonfun$foreach$1.$outer:Lscala/collection/mutable/OpenHashMap;
const #27 = NameAndType	#14:#15;//  f$2:Lscala/Function1;
const #28 = Field	#9.#27;	//  scala/collection/mutable/OpenHashMap$$anonfun$foreach$1.f$2:Lscala/Function1;
const #29 = NameAndType	#12:#13;//  startModCount$1:I
const #30 = Field	#9.#29;	//  scala/collection/mutable/OpenHashMap$$anonfun$foreach$1.startModCount$1:I
const #31 = Asciz	java/lang/Object;
const #32 = class	#31;	//  java/lang/Object
const #33 = Method	#32.#23;	//  java/lang/Object."<init>":()V
const #34 = Asciz	scala/Function1$class;
const #35 = class	#34;	//  scala/Function1$class
const #36 = Asciz	$init$;
const #37 = Asciz	(Lscala/Function1;)V;
const #38 = NameAndType	#36:#37;//  $init$:(Lscala/Function1;)V
const #39 = Method	#35.#38;	//  scala/Function1$class.$init$:(Lscala/Function1;)V
const #40 = Asciz	this;
const #41 = Asciz	Lscala/collection/mutable/OpenHashMap$$anonfun$foreach$1;;
const #42 = Asciz	LocalVariableTable;
const #43 = Asciz	(Lscala/collection/mutable/OpenHashMap<TKey;TValue;>;)V;
const #44 = Asciz	Signature;
const #45 = Asciz	apply;
const #46 = Asciz	(Ljava/lang/Object;)Ljava/lang/Object;;
const #47 = Asciz	scala/collection/mutable/OpenHashMap$OpenEntry;
const #48 = class	#47;	//  scala/collection/mutable/OpenHashMap$OpenEntry
const #49 = Asciz	(Lscala/collection/mutable/OpenHashMap$OpenEntry;)V;
const #50 = NameAndType	#45:#49;//  apply:(Lscala/collection/mutable/OpenHashMap$OpenEntry;)V
const #51 = Method	#9.#50;	//  scala/collection/mutable/OpenHashMap$$anonfun$foreach$1.apply:(Lscala/collection/mutable/OpenHashMap$OpenEntry;)V
const #52 = Asciz	scala/runtime/BoxedUnit;
const #53 = class	#52;	//  scala/runtime/BoxedUnit
const #54 = Asciz	UNIT;
const #55 = Asciz	Lscala/runtime/BoxedUnit;;
const #56 = NameAndType	#54:#55;//  UNIT:Lscala/runtime/BoxedUnit;
const #57 = Field	#53.#56;	//  scala/runtime/BoxedUnit.UNIT:Lscala/runtime/BoxedUnit;
const #58 = Asciz	v1;
const #59 = Asciz	Ljava/lang/Object;;
const #60 = Asciz	scala/collection/mutable/OpenHashMap;
const #61 = class	#60;	//  scala/collection/mutable/OpenHashMap
const #62 = Asciz	scala$collection$mutable$OpenHashMap$$modCount;
const #63 = NameAndType	#62:#13;//  scala$collection$mutable$OpenHashMap$$modCount:I
const #64 = Field	#61.#63;	//  scala/collection/mutable/OpenHashMap.scala$collection$mutable$OpenHashMap$$modCount:I
const #65 = Asciz	Concurrent Modification;
const #66 = String	#65;	//  Concurrent Modification
const #67 = Asciz	java/lang/RuntimeException;
const #68 = class	#67;	//  java/lang/RuntimeException
const #69 = Asciz	(Ljava/lang/String;)V;
const #70 = NameAndType	#18:#69;//  "<init>":(Ljava/lang/String;)V
const #71 = Method	#68.#70;	//  java/lang/RuntimeException."<init>":(Ljava/lang/String;)V
const #72 = Asciz	scala/Tuple2;
const #73 = class	#72;	//  scala/Tuple2
const #74 = Asciz	key;
const #75 = NameAndType	#74:#59;//  key:Ljava/lang/Object;
const #76 = Field	#48.#75;	//  scala/collection/mutable/OpenHashMap$OpenEntry.key:Ljava/lang/Object;
const #77 = Asciz	value;
const #78 = Asciz	Lscala/Option;;
const #79 = NameAndType	#77:#78;//  value:Lscala/Option;
const #80 = Field	#48.#79;	//  scala/collection/mutable/OpenHashMap$OpenEntry.value:Lscala/Option;
const #81 = Asciz	scala/Option;
const #82 = class	#81;	//  scala/Option
const #83 = Asciz	get;
const #84 = Asciz	()Ljava/lang/Object;;
const #85 = NameAndType	#83:#84;//  get:()Ljava/lang/Object;
const #86 = Method	#82.#85;	//  scala/Option.get:()Ljava/lang/Object;
const #87 = Asciz	(Ljava/lang/Object;Ljava/lang/Object;)V;
const #88 = NameAndType	#18:#87;//  "<init>":(Ljava/lang/Object;Ljava/lang/Object;)V
const #89 = Method	#73.#88;	//  scala/Tuple2."<init>":(Ljava/lang/Object;Ljava/lang/Object;)V
const #90 = Asciz	scala/Function1;
const #91 = class	#90;	//  scala/Function1
const #92 = NameAndType	#45:#46;//  apply:(Ljava/lang/Object;)Ljava/lang/Object;
const #93 = InterfaceMethod	#91.#92;	//  scala/Function1.apply:(Ljava/lang/Object;)Ljava/lang/Object;
const #94 = Asciz	entry;
const #95 = Asciz	Lscala/collection/mutable/OpenHashMap$OpenEntry;;
const #96 = Asciz	(Lscala/collection/mutable/OpenHashMap$OpenEntry<TKey;TValue;>;)V;
const #97 = Asciz	andThen;
const #98 = Asciz	(Lscala/Function1;)Lscala/Function1;;
const #99 = Asciz	(Lscala/Function1;Lscala/Function1;)Lscala/Function1;;
const #100 = NameAndType	#97:#99;//  andThen:(Lscala/Function1;Lscala/Function1;)Lscala/Function1;
const #101 = Method	#35.#100;	//  scala/Function1$class.andThen:(Lscala/Function1;Lscala/Function1;)Lscala/Function1;
const #102 = Asciz	g;
const #103 = Asciz	compose;
const #104 = NameAndType	#103:#99;//  compose:(Lscala/Function1;Lscala/Function1;)Lscala/Function1;
const #105 = Method	#35.#104;	//  scala/Function1$class.compose:(Lscala/Function1;Lscala/Function1;)Lscala/Function1;
const #106 = Asciz	toString;
const #107 = Asciz	()Ljava/lang/String;;
const #108 = Asciz	(Lscala/Function1;)Ljava/lang/String;;
const #109 = NameAndType	#106:#108;//  toString:(Lscala/Function1;)Ljava/lang/String;
const #110 = Method	#35.#109;	//  scala/Function1$class.toString:(Lscala/Function1;)Ljava/lang/String;
const #111 = Asciz	Scala;
const #112 = Asciz	InnerClasses;
const #113 = Asciz	OpenEntry;
const #114 = Asciz	$anonfun$foreach$1;
const #115 = Asciz	scala/ScalaObject;
const #116 = class	#115;	//  scala/ScalaObject
const #117 = Asciz	java/io/Serializable;
const #118 = class	#117;	//  java/io/Serializable

{
public static final long serialVersionUID;

public static {};
  Code:
   Stack=2, Locals=0, Args_size=0
   0:	lconst_0
   1:	putstatic	#11; //Field serialVersionUID:J
   4:	return

public scala.collection.mutable.OpenHashMap$$anonfun$foreach$1(scala.collection.mutable.OpenHashMap, scala.Function1, int);
  Code:
   Stack=2, Locals=4, Args_size=4
   0:	aload_1
   1:	ifnonnull	12
   4:	new	#22; //class java/lang/NullPointerException
   7:	dup
   8:	invokespecial	#24; //Method java/lang/NullPointerException."<init>":()V
   11:	athrow
   12:	aload_0
   13:	aload_1
   14:	putfield	#26; //Field $outer:Lscala/collection/mutable/OpenHashMap;
   17:	aload_0
   18:	aload_2
   19:	putfield	#28; //Field f$2:Lscala/Function1;
   22:	aload_0
   23:	iload_3
   24:	putfield	#30; //Field startModCount$1:I
   27:	aload_0
   28:	invokespecial	#33; //Method java/lang/Object."<init>":()V
   31:	aload_0
   32:	invokestatic	#39; //Method scala/Function1$class.$init$:(Lscala/Function1;)V
   35:	return
  LineNumberTable: 
   line 217: 0

  LocalVariableTable: 
   Start  Length  Slot  Name   Signature
   0      36      0    this       Lscala/collection/mutable/OpenHashMap$$anonfun$foreach$1;
   0      36      1    $outer       Lscala/collection/mutable/OpenHashMap;

  Signature: length = 0x2
   00 2B 

public final java.lang.Object apply(java.lang.Object);
  Code:
   Stack=2, Locals=3, Args_size=2
   0:	aload_0
   1:	getfield	#26; //Field $outer:Lscala/collection/mutable/OpenHashMap;
   4:	astore_2
   5:	aload_0
   6:	aload_1
   7:	checkcast	#48; //class scala/collection/mutable/OpenHashMap$OpenEntry
   10:	invokevirtual	#51; //Method apply:(Lscala/collection/mutable/OpenHashMap$OpenEntry;)V
   13:	getstatic	#57; //Field scala/runtime/BoxedUnit.UNIT:Lscala/runtime/BoxedUnit;
   16:	areturn
  LineNumberTable: 
   line 217: 0

  LocalVariableTable: 
   Start  Length  Slot  Name   Signature
   0      17      0    this       Lscala/collection/mutable/OpenHashMap$$anonfun$foreach$1;
   5      12      1    v1       Ljava/lang/Object;


public final void apply(scala.collection.mutable.OpenHashMap$OpenEntry);
  Code:
   Stack=5, Locals=4, Args_size=2
   0:	aload_0
   1:	getfield	#26; //Field $outer:Lscala/collection/mutable/OpenHashMap;
   4:	astore_3
   5:	aload_0
   6:	getfield	#26; //Field $outer:Lscala/collection/mutable/OpenHashMap;
   9:	getfield	#64; //Field scala/collection/mutable/OpenHashMap.scala$collection$mutable$OpenHashMap$$modCount:I
   12:	aload_0
   13:	getfield	#30; //Field startModCount$1:I
   16:	if_icmpeq	31
   19:	ldc	#66; //String Concurrent Modification
   21:	astore_2
   22:	new	#68; //class java/lang/RuntimeException
   25:	dup
   26:	aload_2
   27:	invokespecial	#71; //Method java/lang/RuntimeException."<init>":(Ljava/lang/String;)V
   30:	athrow
   31:	aload_0
   32:	getfield	#28; //Field f$2:Lscala/Function1;
   35:	new	#73; //class scala/Tuple2
   38:	dup
   39:	aload_1
   40:	getfield	#76; //Field scala/collection/mutable/OpenHashMap$OpenEntry.key:Ljava/lang/Object;
   43:	aload_1
   44:	getfield	#80; //Field scala/collection/mutable/OpenHashMap$OpenEntry.value:Lscala/Option;
   47:	invokevirtual	#86; //Method scala/Option.get:()Ljava/lang/Object;
   50:	invokespecial	#89; //Method scala/Tuple2."<init>":(Ljava/lang/Object;Ljava/lang/Object;)V
   53:	invokeinterface	#93,  2; //InterfaceMethod scala/Function1.apply:(Ljava/lang/Object;)Ljava/lang/Object;
   58:	pop
   59:	return
  LineNumberTable: 
   line 218: 0
   line 219: 31

  LocalVariableTable: 
   Start  Length  Slot  Name   Signature
   0      60      0    this       Lscala/collection/mutable/OpenHashMap$$anonfun$foreach$1;
   5      55      1    entry       Lscala/collection/mutable/OpenHashMap$OpenEntry;

  Signature: length = 0x2
   00 60 

public scala.Function1 andThen(scala.Function1);
  Code:
   Stack=2, Locals=2, Args_size=2
   0:	aload_0
   1:	aload_1
   2:	invokestatic	#101; //Method scala/Function1$class.andThen:(Lscala/Function1;Lscala/Function1;)Lscala/Function1;
   5:	areturn
  LineNumberTable: 
   line 217: 0

  LocalVariableTable: 
   Start  Length  Slot  Name   Signature
   0      6      0    this       Lscala/collection/mutable/OpenHashMap$$anonfun$foreach$1;
   0      6      1    g       Lscala/Function1;


public scala.Function1 compose(scala.Function1);
  Code:
   Stack=2, Locals=2, Args_size=2
   0:	aload_0
   1:	aload_1
   2:	invokestatic	#105; //Method scala/Function1$class.compose:(Lscala/Function1;Lscala/Function1;)Lscala/Function1;
   5:	areturn
  LineNumberTable: 
   line 217: 0

  LocalVariableTable: 
   Start  Length  Slot  Name   Signature
   0      6      0    this       Lscala/collection/mutable/OpenHashMap$$anonfun$foreach$1;
   0      6      1    g       Lscala/Function1;


public java.lang.String toString();
  Code:
   Stack=1, Locals=1, Args_size=1
   0:	aload_0
   1:	invokestatic	#110; //Method scala/Function1$class.toString:(Lscala/Function1;)Ljava/lang/String;
   4:	areturn
  LineNumberTable: 
   line 217: 0


}

