Compiled from "OpenHashMap.scala"
public final class scala.collection.mutable.OpenHashMap$$anonfun$retain$1 extends java.lang.Object implements scala.Function1,scala.ScalaObject,java.io.Serializable
  SourceFile: "OpenHashMap.scala"
  Scala: length = 0x
   
  InnerClass: 
   public final OpenEntry=class scala/collection/mutable/OpenHashMap$OpenEntry of class scala/collection/mutable/OpenHashMap
   public final $anonfun$retain$1=class scala/collection/mutable/OpenHashMap$$anonfun$retain$1 of class scala/collection/mutable/OpenHashMap
  minor version: 0
  major version: 49
  Constant pool:
Asciz	SourceFile;
Asciz	OpenHashMap.scala;
Asciz	<clinit>;
Asciz	()V;
Asciz	Code;
Asciz	serialVersionUID;
Asciz	J;
Asciz	scala/collection/mutable/OpenHashMap$$anonfun$retain$1;
class	scala/collection/mutable/OpenHashMap$$anonfun$retain$1
NameAndType	serialVersionUID:J
Field	scala/collection/mutable/OpenHashMap$$anonfun$retain$1.serialVersionUID:J
Asciz	f$4;
Asciz	Lscala/Function2;;
Asciz	$outer;
Asciz	Lscala/collection/mutable/OpenHashMap;;
Asciz	<init>;
Asciz	(Lscala/collection/mutable/OpenHashMap;Lscala/Function2;)V;
Asciz	LineNumberTable;
Asciz	java/lang/NullPointerException;
class	java/lang/NullPointerException
NameAndType	"<init>":()V
Method	java/lang/NullPointerException."<init>":()V
NameAndType	$outer:Lscala/collection/mutable/OpenHashMap;
Field	scala/collection/mutable/OpenHashMap$$anonfun$retain$1.$outer:Lscala/collection/mutable/OpenHashMap;
NameAndType	f$4:Lscala/Function2;
Field	scala/collection/mutable/OpenHashMap$$anonfun$retain$1.f$4:Lscala/Function2;
Asciz	java/lang/Object;
class	java/lang/Object
Method	java/lang/Object."<init>":()V
Asciz	scala/Function1$class;
class	scala/Function1$class
Asciz	$init$;
Asciz	(Lscala/Function1;)V;
NameAndType	$init$:(Lscala/Function1;)V
Method	scala/Function1$class.$init$:(Lscala/Function1;)V
Asciz	this;
Asciz	Lscala/collection/mutable/OpenHashMap$$anonfun$retain$1;;
Asciz	LocalVariableTable;
Asciz	(Lscala/collection/mutable/OpenHashMap<TKey;TValue;>;)V;
Asciz	Signature;
Asciz	apply;
Asciz	(Ljava/lang/Object;)Ljava/lang/Object;;
Asciz	scala/collection/mutable/OpenHashMap$OpenEntry;
class	scala/collection/mutable/OpenHashMap$OpenEntry
Asciz	(Lscala/collection/mutable/OpenHashMap$OpenEntry;)V;
NameAndType	apply:(Lscala/collection/mutable/OpenHashMap$OpenEntry;)V
Method	scala/collection/mutable/OpenHashMap$$anonfun$retain$1.apply:(Lscala/collection/mutable/OpenHashMap$OpenEntry;)V
Asciz	scala/runtime/BoxedUnit;
class	scala/runtime/BoxedUnit
Asciz	UNIT;
Asciz	Lscala/runtime/BoxedUnit;;
NameAndType	UNIT:Lscala/runtime/BoxedUnit;
Field	scala/runtime/BoxedUnit.UNIT:Lscala/runtime/BoxedUnit;
Asciz	v1;
Asciz	Ljava/lang/Object;;
Asciz	key;
NameAndType	key:Ljava/lang/Object;
Field	scala/collection/mutable/OpenHashMap$OpenEntry.key:Ljava/lang/Object;
Asciz	value;
Asciz	Lscala/Option;;
NameAndType	value:Lscala/Option;
Field	scala/collection/mutable/OpenHashMap$OpenEntry.value:Lscala/Option;
Asciz	scala/Option;
class	scala/Option
Asciz	get;
Asciz	()Ljava/lang/Object;;
NameAndType	get:()Ljava/lang/Object;
Method	scala/Option.get:()Ljava/lang/Object;
Asciz	scala/Function2;
class	scala/Function2
Asciz	(Ljava/lang/Object;Ljava/lang/Object;)Ljava/lang/Object;;
NameAndType	apply:(Ljava/lang/Object;Ljava/lang/Object;)Ljava/lang/Object;
InterfaceMethod	scala/Function2.apply:(Ljava/lang/Object;Ljava/lang/Object;)Ljava/lang/Object;
Asciz	scala/runtime/BoxesRunTime;
class	scala/runtime/BoxesRunTime
Asciz	unboxToBoolean;
Asciz	(Ljava/lang/Object;)Z;
NameAndType	unboxToBoolean:(Ljava/lang/Object;)Z
Method	scala/runtime/BoxesRunTime.unboxToBoolean:(Ljava/lang/Object;)Z
Asciz	scala/None$;
class	scala/None$
Asciz	MODULE$;
Asciz	Lscala/None$;;
NameAndType	MODULE$:Lscala/None$;
Field	scala/None$.MODULE$:Lscala/None$;
Asciz	scala/collection/mutable/OpenHashMap;
class	scala/collection/mutable/OpenHashMap
Asciz	size;
Asciz	()I;
NameAndType	size:()I
Method	scala/collection/mutable/OpenHashMap.size:()I
Asciz	scala$collection$mutable$OpenHashMap$$size_$eq;
Asciz	(I)V;
NameAndType	scala$collection$mutable$OpenHashMap$$size_$eq:(I)V
Method	scala/collection/mutable/OpenHashMap.scala$collection$mutable$OpenHashMap$$size_$eq:(I)V
Asciz	scala$collection$mutable$OpenHashMap$$deleted;
NameAndType	scala$collection$mutable$OpenHashMap$$deleted:()I
Method	scala/collection/mutable/OpenHashMap.scala$collection$mutable$OpenHashMap$$deleted:()I
Asciz	scala$collection$mutable$OpenHashMap$$deleted_$eq;
NameAndType	scala$collection$mutable$OpenHashMap$$deleted_$eq:(I)V
Method	scala/collection/mutable/OpenHashMap.scala$collection$mutable$OpenHashMap$$deleted_$eq:(I)V
Asciz	entry;
Asciz	Lscala/collection/mutable/OpenHashMap$OpenEntry;;
Asciz	(Lscala/collection/mutable/OpenHashMap$OpenEntry<TKey;TValue;>;)V;
Asciz	andThen;
Asciz	(Lscala/Function1;)Lscala/Function1;;
Asciz	(Lscala/Function1;Lscala/Function1;)Lscala/Function1;;
NameAndType	andThen:(Lscala/Function1;Lscala/Function1;)Lscala/Function1;
Method	scala/Function1$class.andThen:(Lscala/Function1;Lscala/Function1;)Lscala/Function1;
Asciz	g;
Asciz	Lscala/Function1;;
Asciz	compose;
NameAndType	compose:(Lscala/Function1;Lscala/Function1;)Lscala/Function1;
Method	scala/Function1$class.compose:(Lscala/Function1;Lscala/Function1;)Lscala/Function1;
Asciz	toString;
Asciz	()Ljava/lang/String;;
Asciz	(Lscala/Function1;)Ljava/lang/String;;
NameAndType	toString:(Lscala/Function1;)Ljava/lang/String;
Method	scala/Function1$class.toString:(Lscala/Function1;)Ljava/lang/String;
Asciz	Scala;
Asciz	InnerClasses;
Asciz	OpenEntry;
Asciz	$anonfun$retain$1;
Asciz	scala/Function1;
class	scala/Function1
Asciz	scala/ScalaObject;
class	scala/ScalaObject
Asciz	java/io/Serializable;
class	java/io/Serializable

{
public static final long serialVersionUID;
  Signature: J

private final scala.Function2 f$4;
  Signature: Lscala/Function2;

private final scala.collection.mutable.OpenHashMap $outer;
  Signature: Lscala/collection/mutable/OpenHashMap;

public static {};
  Signature: ()V
  Code:
   Stack=2, Locals=0, Args_size=0
	lconst_0
	putstatic	Field serialVersionUID:J
	return
  Labels:

public scala.collection.mutable.OpenHashMap$$anonfun$retain$1(scala.collection.mutable.OpenHashMap, scala.Function2);
  Signature: (Lscala/collection/mutable/OpenHashMap;Lscala/Function2;)V
  Code:
   Stack=2, Locals=3, Args_size=3
	aload_1
	ifnonnull	l1 // aload_0
	new	class java/lang/NullPointerException
	dup
	invokespecial	Method java/lang/NullPointerException."<init>":()V
	athrow
l1	aload_0
	aload_1
	putfield	Field $outer:Lscala/collection/mutable/OpenHashMap;
	aload_0
	aload_2
	putfield	Field f$4:Lscala/Function2;
	aload_0
	invokespecial	Method java/lang/Object."<init>":()V
	aload_0
	invokestatic	Method scala/Function1$class.$init$:(Lscala/Function1;)V
	return
  Labels:
   	l1 = 12 // aload_0
  LocalVariableTable: 
   Start  Length  Slot  Name   Signature
   0      31      0    this       Lscala/collection/mutable/OpenHashMap$$anonfun$retain$1;
   0      31      1    $outer       Lscala/collection/mutable/OpenHashMap;

  Signature: length = 0x2
   00 27 

public final java.lang.Object apply(java.lang.Object);
  Signature: (Ljava/lang/Object;)Ljava/lang/Object;
  Code:
   Stack=2, Locals=3, Args_size=2
	aload_0
	getfield	Field $outer:Lscala/collection/mutable/OpenHashMap;
	astore_2
	aload_0
	aload_1
	checkcast	class scala/collection/mutable/OpenHashMap$OpenEntry
	invokevirtual	Method apply:(Lscala/collection/mutable/OpenHashMap$OpenEntry;)V
	getstatic	Field scala/runtime/BoxedUnit.UNIT:Lscala/runtime/BoxedUnit;
	areturn
  Labels:
  LocalVariableTable: 
   Start  Length  Slot  Name   Signature
   0      17      0    this       Lscala/collection/mutable/OpenHashMap$$anonfun$retain$1;
   5      12      1    v1       Ljava/lang/Object;


public final void apply(scala.collection.mutable.OpenHashMap$OpenEntry);
  Signature: (Lscala/collection/mutable/OpenHashMap$OpenEntry;)V
  Code:
   Stack=3, Locals=4, Args_size=2
	aload_0
	getfield	Field $outer:Lscala/collection/mutable/OpenHashMap;
	astore_3
	aload_0
	getfield	Field f$4:Lscala/Function2;
	aload_1
	getfield	Field scala/collection/mutable/OpenHashMap$OpenEntry.key:Ljava/lang/Object;
	aload_1
	getfield	Field scala/collection/mutable/OpenHashMap$OpenEntry.value:Lscala/Option;
	invokevirtual	Method scala/Option.get:()Ljava/lang/Object;
	invokeinterface	InterfaceMethod scala/Function2.apply:(Ljava/lang/Object;Ljava/lang/Object;)Ljava/lang/Object;
	invokestatic	Method scala/runtime/BoxesRunTime.unboxToBoolean:(Ljava/lang/Object;)Z
	ifne	l1 // return
	getstatic	Field scala/None$.MODULE$:Lscala/None$;
	astore_2
	aload_1
	aload_2
	putfield	Field scala/collection/mutable/OpenHashMap$OpenEntry.value:Lscala/Option;
	aload_0
	getfield	Field $outer:Lscala/collection/mutable/OpenHashMap;
	aload_0
	getfield	Field $outer:Lscala/collection/mutable/OpenHashMap;
	invokevirtual	Method scala/collection/mutable/OpenHashMap.size:()I
	iconst_1
	isub
	invokevirtual	Method scala/collection/mutable/OpenHashMap.scala$collection$mutable$OpenHashMap$$size_$eq:(I)V
	aload_0
	getfield	Field $outer:Lscala/collection/mutable/OpenHashMap;
	aload_0
	getfield	Field $outer:Lscala/collection/mutable/OpenHashMap;
	invokevirtual	Method scala/collection/mutable/OpenHashMap.scala$collection$mutable$OpenHashMap$$deleted:()I
	iconst_1
	iadd
	invokevirtual	Method scala/collection/mutable/OpenHashMap.scala$collection$mutable$OpenHashMap$$deleted_$eq:(I)V
l1	return
  Labels:
   	l1 = 72 // return
  LocalVariableTable: 
   Start  Length  Slot  Name   Signature
   0      73      0    this       Lscala/collection/mutable/OpenHashMap$$anonfun$retain$1;
   5      68      1    entry       Lscala/collection/mutable/OpenHashMap$OpenEntry;

  Signature: length = 0x2
   00 68 

public scala.Function1 andThen(scala.Function1);
  Signature: (Lscala/Function1;)Lscala/Function1;
  Code:
   Stack=2, Locals=2, Args_size=2
	aload_0
	aload_1
	invokestatic	Method scala/Function1$class.andThen:(Lscala/Function1;Lscala/Function1;)Lscala/Function1;
	areturn
  Labels:
  LocalVariableTable: 
   Start  Length  Slot  Name   Signature
   0      6      0    this       Lscala/collection/mutable/OpenHashMap$$anonfun$retain$1;
   0      6      1    g       Lscala/Function1;


public scala.Function1 compose(scala.Function1);
  Signature: (Lscala/Function1;)Lscala/Function1;
  Code:
   Stack=2, Locals=2, Args_size=2
	aload_0
	aload_1
	invokestatic	Method scala/Function1$class.compose:(Lscala/Function1;Lscala/Function1;)Lscala/Function1;
	areturn
  Labels:
  LocalVariableTable: 
   Start  Length  Slot  Name   Signature
   0      6      0    this       Lscala/collection/mutable/OpenHashMap$$anonfun$retain$1;
   0      6      1    g       Lscala/Function1;


public java.lang.String toString();
  Signature: ()Ljava/lang/String;
  Code:
   Stack=1, Locals=1, Args_size=1
	aload_0
	invokestatic	Method scala/Function1$class.toString:(Lscala/Function1;)Ljava/lang/String;
	areturn
  Labels:

}

