Compiled from "OpenHashMap.scala"
public final class scala.collection.mutable.OpenHashMap$$anonfun$transform$1 extends java.lang.Object implements scala.Function1,scala.ScalaObject,java.io.Serializable
  SourceFile: "OpenHashMap.scala"
  Scala: length = 0x
   
  InnerClass: 
   public final OpenEntry=class scala/collection/mutable/OpenHashMap$OpenEntry of class scala/collection/mutable/OpenHashMap
   public final $anonfun$transform$1=class scala/collection/mutable/OpenHashMap$$anonfun$transform$1 of class scala/collection/mutable/OpenHashMap
  minor version: 0
  major version: 49
  Constant pool:
Asciz	SourceFile;
Asciz	OpenHashMap.scala;
Asciz	<clinit>;
Asciz	()V;
Asciz	Code;
Asciz	serialVersionUID;
Asciz	J;
Asciz	scala/collection/mutable/OpenHashMap$$anonfun$transform$1;
class	scala/collection/mutable/OpenHashMap$$anonfun$transform$1
NameAndType	serialVersionUID:J
Field	scala/collection/mutable/OpenHashMap$$anonfun$transform$1.serialVersionUID:J
Asciz	f$3;
Asciz	Lscala/Function2;;
Asciz	<init>;
Asciz	(Lscala/collection/mutable/OpenHashMap;Lscala/Function2;)V;
Asciz	LineNumberTable;
NameAndType	f$3:Lscala/Function2;
Field	scala/collection/mutable/OpenHashMap$$anonfun$transform$1.f$3:Lscala/Function2;
Asciz	java/lang/Object;
class	java/lang/Object
NameAndType	"<init>":()V
Method	java/lang/Object."<init>":()V
Asciz	scala/Function1$class;
class	scala/Function1$class
Asciz	$init$;
Asciz	(Lscala/Function1;)V;
NameAndType	$init$:(Lscala/Function1;)V
Method	scala/Function1$class.$init$:(Lscala/Function1;)V
Asciz	this;
Asciz	Lscala/collection/mutable/OpenHashMap$$anonfun$transform$1;;
Asciz	$outer;
Asciz	Lscala/collection/mutable/OpenHashMap;;
Asciz	LocalVariableTable;
Asciz	(Lscala/collection/mutable/OpenHashMap<TKey;TValue;>;)V;
Asciz	Signature;
Asciz	apply;
Asciz	(Ljava/lang/Object;)Ljava/lang/Object;;
Asciz	scala/collection/mutable/OpenHashMap$OpenEntry;
class	scala/collection/mutable/OpenHashMap$OpenEntry
Asciz	(Lscala/collection/mutable/OpenHashMap$OpenEntry;)V;
NameAndType	apply:(Lscala/collection/mutable/OpenHashMap$OpenEntry;)V
Method	scala/collection/mutable/OpenHashMap$$anonfun$transform$1.apply:(Lscala/collection/mutable/OpenHashMap$OpenEntry;)V
Asciz	scala/runtime/BoxedUnit;
class	scala/runtime/BoxedUnit
Asciz	UNIT;
Asciz	Lscala/runtime/BoxedUnit;;
NameAndType	UNIT:Lscala/runtime/BoxedUnit;
Field	scala/runtime/BoxedUnit.UNIT:Lscala/runtime/BoxedUnit;
Asciz	v1;
Asciz	Ljava/lang/Object;;
Asciz	scala/Some;
class	scala/Some
Asciz	key;
Asciz	()Ljava/lang/Object;;
NameAndType	key:()Ljava/lang/Object;
Method	scala/collection/mutable/OpenHashMap$OpenEntry.key:()Ljava/lang/Object;
Asciz	value;
Asciz	()Lscala/Option;;
NameAndType	value:()Lscala/Option;
Method	scala/collection/mutable/OpenHashMap$OpenEntry.value:()Lscala/Option;
Asciz	scala/Option;
class	scala/Option
Asciz	get;
NameAndType	get:()Ljava/lang/Object;
Method	scala/Option.get:()Ljava/lang/Object;
Asciz	scala/Function2;
class	scala/Function2
Asciz	(Ljava/lang/Object;Ljava/lang/Object;)Ljava/lang/Object;;
NameAndType	apply:(Ljava/lang/Object;Ljava/lang/Object;)Ljava/lang/Object;
InterfaceMethod	scala/Function2.apply:(Ljava/lang/Object;Ljava/lang/Object;)Ljava/lang/Object;
Asciz	(Ljava/lang/Object;)V;
NameAndType	"<init>":(Ljava/lang/Object;)V
Method	scala/Some."<init>":(Ljava/lang/Object;)V
Asciz	value_$eq;
Asciz	(Lscala/Option;)V;
NameAndType	value_$eq:(Lscala/Option;)V
Method	scala/collection/mutable/OpenHashMap$OpenEntry.value_$eq:(Lscala/Option;)V
Asciz	entry;
Asciz	Lscala/collection/mutable/OpenHashMap$OpenEntry;;
Asciz	(Lscala/collection/mutable/OpenHashMap$OpenEntry<TKey;TValue;>;)V;
Asciz	andThen;
Asciz	(Lscala/Function1;)Lscala/Function1;;
Asciz	(Lscala/Function1;Lscala/Function1;)Lscala/Function1;;
NameAndType	andThen:(Lscala/Function1;Lscala/Function1;)Lscala/Function1;
Method	scala/Function1$class.andThen:(Lscala/Function1;Lscala/Function1;)Lscala/Function1;
Asciz	g;
Asciz	Lscala/Function1;;
Asciz	compose;
NameAndType	compose:(Lscala/Function1;Lscala/Function1;)Lscala/Function1;
Method	scala/Function1$class.compose:(Lscala/Function1;Lscala/Function1;)Lscala/Function1;
Asciz	toString;
Asciz	()Ljava/lang/String;;
Asciz	(Lscala/Function1;)Ljava/lang/String;;
NameAndType	toString:(Lscala/Function1;)Ljava/lang/String;
Method	scala/Function1$class.toString:(Lscala/Function1;)Ljava/lang/String;
Asciz	Scala;
Asciz	InnerClasses;
Asciz	scala/collection/mutable/OpenHashMap;
class	scala/collection/mutable/OpenHashMap
Asciz	OpenEntry;
Asciz	$anonfun$transform$1;
Asciz	scala/Function1;
class	scala/Function1
Asciz	scala/ScalaObject;
class	scala/ScalaObject
Asciz	java/io/Serializable;
class	java/io/Serializable

{
public static final long serialVersionUID;
  Signature: J

private final scala.Function2 f$3;
  Signature: Lscala/Function2;

public static {};
  Signature: ()V
  Code:
   Stack=2, Locals=0, Args_size=0
	lconst_0
	putstatic	Field serialVersionUID:J
	return
  Labels:

public scala.collection.mutable.OpenHashMap$$anonfun$transform$1(scala.collection.mutable.OpenHashMap, scala.Function2);
  Signature: (Lscala/collection/mutable/OpenHashMap;Lscala/Function2;)V
  Code:
   Stack=2, Locals=3, Args_size=3
	aload_0
	aload_2
	putfield	Field f$3:Lscala/Function2;
	aload_0
	invokespecial	Method java/lang/Object."<init>":()V
	aload_0
	invokestatic	Method scala/Function1$class.$init$:(Lscala/Function1;)V
	return
  Labels:
  LocalVariableTable: 
   Start  Length  Slot  Name   Signature
   0      14      0    this       Lscala/collection/mutable/OpenHashMap$$anonfun$transform$1;
   0      14      1    $outer       Lscala/collection/mutable/OpenHashMap;

  Signature: length = 0x2
   00 22 

public final java.lang.Object apply(java.lang.Object);
  Signature: (Ljava/lang/Object;)Ljava/lang/Object;
  Code:
   Stack=2, Locals=2, Args_size=2
	aload_0
	aload_1
	checkcast	class scala/collection/mutable/OpenHashMap$OpenEntry
	invokevirtual	Method apply:(Lscala/collection/mutable/OpenHashMap$OpenEntry;)V
	getstatic	Field scala/runtime/BoxedUnit.UNIT:Lscala/runtime/BoxedUnit;
	areturn
  Labels:
  LocalVariableTable: 
   Start  Length  Slot  Name   Signature
   0      12      0    this       Lscala/collection/mutable/OpenHashMap$$anonfun$transform$1;
   0      12      1    v1       Ljava/lang/Object;


public final void apply(scala.collection.mutable.OpenHashMap$OpenEntry);
  Signature: (Lscala/collection/mutable/OpenHashMap$OpenEntry;)V
  Code:
   Stack=6, Locals=2, Args_size=2
	aload_1
	new	class scala/Some
	dup
	aload_0
	getfield	Field f$3:Lscala/Function2;
	aload_1
	invokevirtual	Method scala/collection/mutable/OpenHashMap$OpenEntry.key:()Ljava/lang/Object;
	aload_1
	invokevirtual	Method scala/collection/mutable/OpenHashMap$OpenEntry.value:()Lscala/Option;
	invokevirtual	Method scala/Option.get:()Ljava/lang/Object;
	invokeinterface	InterfaceMethod scala/Function2.apply:(Ljava/lang/Object;Ljava/lang/Object;)Ljava/lang/Object;
	invokespecial	Method scala/Some."<init>":(Ljava/lang/Object;)V
	invokevirtual	Method scala/collection/mutable/OpenHashMap$OpenEntry.value_$eq:(Lscala/Option;)V
	return
  Labels:
  LocalVariableTable: 
   Start  Length  Slot  Name   Signature
   0      32      0    this       Lscala/collection/mutable/OpenHashMap$$anonfun$transform$1;
   0      32      1    entry       Lscala/collection/mutable/OpenHashMap$OpenEntry;

  Signature: length = 0x2
   00 50 

public scala.Function1 andThen(scala.Function1);
  Signature: (Lscala/Function1;)Lscala/Function1;
  Code:
   Stack=2, Locals=2, Args_size=2
	aload_0
	aload_1
	invokestatic	Method scala/Function1$class.andThen:(Lscala/Function1;Lscala/Function1;)Lscala/Function1;
	areturn
  Labels:
  LocalVariableTable: 
   Start  Length  Slot  Name   Signature
   0      6      0    this       Lscala/collection/mutable/OpenHashMap$$anonfun$transform$1;
   0      6      1    g       Lscala/Function1;


public scala.Function1 compose(scala.Function1);
  Signature: (Lscala/Function1;)Lscala/Function1;
  Code:
   Stack=2, Locals=2, Args_size=2
	aload_0
	aload_1
	invokestatic	Method scala/Function1$class.compose:(Lscala/Function1;Lscala/Function1;)Lscala/Function1;
	areturn
  Labels:
  LocalVariableTable: 
   Start  Length  Slot  Name   Signature
   0      6      0    this       Lscala/collection/mutable/OpenHashMap$$anonfun$transform$1;
   0      6      1    g       Lscala/Function1;


public java.lang.String toString();
  Signature: ()Ljava/lang/String;
  Code:
   Stack=1, Locals=1, Args_size=1
	aload_0
	invokestatic	Method scala/Function1$class.toString:(Lscala/Function1;)Ljava/lang/String;
	areturn
  Labels:

}

