Compiled from "OpenHashMap.scala"
public final class scala.collection.mutable.OpenHashMap$ extends java.lang.Object implements scala.ScalaObject
  SourceFile: "OpenHashMap.scala"
  Scala: length = 0x
   
  InnerClass: 
   public final #60= #59 of #35; //$anon$1=class scala/collection/mutable/OpenHashMap$$anon$1 of class scala/collection/mutable/OpenHashMap
   public final #63= #62 of #35; //OpenEntry=class scala/collection/mutable/OpenHashMap$OpenEntry of class scala/collection/mutable/OpenHashMap
   public final #66= #65 of #35; //$anonfun$clone$1=class scala/collection/mutable/OpenHashMap$$anonfun$clone$1 of class scala/collection/mutable/OpenHashMap
   public final #67= #42 of #35; //$anonfun$apply$1=class scala/collection/mutable/OpenHashMap$$anonfun$apply$1 of class scala/collection/mutable/OpenHashMap
   public final #70= #69 of #35; //$anonfun$retain$1=class scala/collection/mutable/OpenHashMap$$anonfun$retain$1 of class scala/collection/mutable/OpenHashMap
   public final #73= #72 of #35; //$anonfun$foreach$1=class scala/collection/mutable/OpenHashMap$$anonfun$foreach$1 of class scala/collection/mutable/OpenHashMap
   public final #76= #75 of #35; //$anonfun$transform$1=class scala/collection/mutable/OpenHashMap$$anonfun$transform$1 of class scala/collection/mutable/OpenHashMap
   public final #79= #78 of #35; //$anonfun$growTable$1=class scala/collection/mutable/OpenHashMap$$anonfun$growTable$1 of class scala/collection/mutable/OpenHashMap
   public final #82= #81 of #35; //$anonfun$foreachUndeletedEntry$1=class scala/collection/mutable/OpenHashMap$$anonfun$foreachUndeletedEntry$1 of class scala/collection/mutable/OpenHashMap
  minor version: 0
  major version: 49
  Constant pool:
const #1 = Asciz	SourceFile;
const #2 = Asciz	OpenHashMap.scala;
const #3 = Asciz	Scala;
const #4 = Asciz	MODULE$;
const #5 = Asciz	Lscala/collection/mutable/OpenHashMap$;;
const #6 = Asciz	<clinit>;
const #7 = Asciz	()V;
const #8 = Asciz	Code;
const #9 = Asciz	scala/collection/mutable/OpenHashMap$;
const #10 = class	#9;	//  scala/collection/mutable/OpenHashMap$
const #11 = Asciz	<init>;
const #12 = NameAndType	#11:#7;//  "<init>":()V
const #13 = Method	#10.#12;	//  scala/collection/mutable/OpenHashMap$."<init>":()V
const #14 = Asciz	LineNumberTable;
const #15 = Asciz	java/lang/Object;
const #16 = class	#15;	//  java/lang/Object
const #17 = Method	#16.#12;	//  java/lang/Object."<init>":()V
const #18 = NameAndType	#4:#5;//  MODULE$:Lscala/collection/mutable/OpenHashMap$;
const #19 = Field	#10.#18;	//  scala/collection/mutable/OpenHashMap$.MODULE$:Lscala/collection/mutable/OpenHashMap$;
const #20 = Asciz	nextPowerOfTwo;
const #21 = Asciz	(I)I;
const #22 = Asciz	highestOneBit;
const #23 = NameAndType	#22:#21;//  highestOneBit:(I)I
const #24 = Method	#10.#23;	//  scala/collection/mutable/OpenHashMap$.highestOneBit:(I)I
const #25 = Asciz	this;
const #26 = Asciz	i;
const #27 = Asciz	I;
const #28 = Asciz	LocalVariableTable;
const #29 = int	8;
const #30 = int	16;
const #31 = Asciz	j;
const #32 = Asciz	empty;
const #33 = Asciz	()Lscala/collection/mutable/OpenHashMap;;
const #34 = Asciz	scala/collection/mutable/OpenHashMap;
const #35 = class	#34;	//  scala/collection/mutable/OpenHashMap
const #36 = Method	#35.#12;	//  scala/collection/mutable/OpenHashMap."<init>":()V
const #37 = Asciz	<K:Ljava/lang/Object;V:Ljava/lang/Object;>()Lscala/collection/mutable/OpenHashMap<TK;TV;>;;
const #38 = Asciz	Signature;
const #39 = Asciz	apply;
const #40 = Asciz	(Lscala/collection/Seq;)Lscala/collection/mutable/OpenHashMap;;
const #41 = Asciz	scala/collection/mutable/OpenHashMap$$anonfun$apply$1;
const #42 = class	#41;	//  scala/collection/mutable/OpenHashMap$$anonfun$apply$1
const #43 = Asciz	(Lscala/collection/mutable/OpenHashMap;)V;
const #44 = NameAndType	#11:#43;//  "<init>":(Lscala/collection/mutable/OpenHashMap;)V
const #45 = Method	#42.#44;	//  scala/collection/mutable/OpenHashMap$$anonfun$apply$1."<init>":(Lscala/collection/mutable/OpenHashMap;)V
const #46 = Asciz	scala/collection/IterableLike;
const #47 = class	#46;	//  scala/collection/IterableLike
const #48 = Asciz	foreach;
const #49 = Asciz	(Lscala/Function1;)V;
const #50 = NameAndType	#48:#49;//  foreach:(Lscala/Function1;)V
const #51 = InterfaceMethod	#47.#50;	//  scala/collection/IterableLike.foreach:(Lscala/Function1;)V
const #52 = Asciz	elems;
const #53 = Asciz	Lscala/collection/Seq;;
const #54 = Asciz	dict$1;
const #55 = Asciz	Lscala/collection/mutable/OpenHashMap;;
const #56 = Asciz	<K:Ljava/lang/Object;V:Ljava/lang/Object;>(Lscala/collection/Seq<Lscala/Tuple2<TK;TV;>;>;)Lscala/collection/mutable/OpenHashMap<TK;TV;>;;
const #57 = Asciz	InnerClasses;
const #58 = Asciz	scala/collection/mutable/OpenHashMap$$anon$1;
const #59 = class	#58;	//  scala/collection/mutable/OpenHashMap$$anon$1
const #60 = Asciz	$anon$1;
const #61 = Asciz	scala/collection/mutable/OpenHashMap$OpenEntry;
const #62 = class	#61;	//  scala/collection/mutable/OpenHashMap$OpenEntry
const #63 = Asciz	OpenEntry;
const #64 = Asciz	scala/collection/mutable/OpenHashMap$$anonfun$clone$1;
const #65 = class	#64;	//  scala/collection/mutable/OpenHashMap$$anonfun$clone$1
const #66 = Asciz	$anonfun$clone$1;
const #67 = Asciz	$anonfun$apply$1;
const #68 = Asciz	scala/collection/mutable/OpenHashMap$$anonfun$retain$1;
const #69 = class	#68;	//  scala/collection/mutable/OpenHashMap$$anonfun$retain$1
const #70 = Asciz	$anonfun$retain$1;
const #71 = Asciz	scala/collection/mutable/OpenHashMap$$anonfun$foreach$1;
const #72 = class	#71;	//  scala/collection/mutable/OpenHashMap$$anonfun$foreach$1
const #73 = Asciz	$anonfun$foreach$1;
const #74 = Asciz	scala/collection/mutable/OpenHashMap$$anonfun$transform$1;
const #75 = class	#74;	//  scala/collection/mutable/OpenHashMap$$anonfun$transform$1
const #76 = Asciz	$anonfun$transform$1;
const #77 = Asciz	scala/collection/mutable/OpenHashMap$$anonfun$growTable$1;
const #78 = class	#77;	//  scala/collection/mutable/OpenHashMap$$anonfun$growTable$1
const #79 = Asciz	$anonfun$growTable$1;
const #80 = Asciz	scala/collection/mutable/OpenHashMap$$anonfun$foreachUndeletedEntry$1;
const #81 = class	#80;	//  scala/collection/mutable/OpenHashMap$$anonfun$foreachUndeletedEntry$1
const #82 = Asciz	$anonfun$foreachUndeletedEntry$1;
const #83 = Asciz	scala/ScalaObject;
const #84 = class	#83;	//  scala/ScalaObject

{
public static final scala.collection.mutable.OpenHashMap$ MODULE$;

public static {};
  Code:
   Stack=1, Locals=0, Args_size=0
   0:	new	#10; //class scala/collection/mutable/OpenHashMap$
   3:	invokespecial	#13; //Method "<init>":()V
   6:	return

public int nextPowerOfTwo(int);
  Code:
   Stack=2, Locals=2, Args_size=2
   0:	aload_0
   1:	iload_1
   2:	invokevirtual	#24; //Method highestOneBit:(I)I
   5:	iconst_1
   6:	ishl
   7:	ireturn
  LineNumberTable: 
   line 42: 0

  LocalVariableTable: 
   Start  Length  Slot  Name   Signature
   0      8      0    this       Lscala/collection/mutable/OpenHashMap$;
   0      8      1    i       I


public int highestOneBit(int);
  Code:
   Stack=3, Locals=3, Args_size=2
   0:	iload_1
   1:	iload_1
   2:	iconst_1
   3:	ishr
   4:	ior
   5:	istore_2
   6:	iload_2
   7:	iload_2
   8:	iconst_2
   9:	ishr
   10:	ior
   11:	istore_2
   12:	iload_2
   13:	iload_2
   14:	iconst_4
   15:	ishr
   16:	ior
   17:	istore_2
   18:	iload_2
   19:	iload_2
   20:	ldc	#29; //int 8
   22:	ishr
   23:	ior
   24:	istore_2
   25:	iload_2
   26:	iload_2
   27:	ldc	#30; //int 16
   29:	ishr
   30:	ior
   31:	istore_2
   32:	iload_2
   33:	iload_2
   34:	iconst_1
   35:	iushr
   36:	isub
   37:	ireturn
  LineNumberTable: 
   line 34: 0
   line 35: 6
   line 36: 12
   line 37: 18
   line 38: 25
   line 39: 32

  LocalVariableTable: 
   Start  Length  Slot  Name   Signature
   0      38      0    this       Lscala/collection/mutable/OpenHashMap$;
   0      38      1    j       I
   0      37      2    i       I


public scala.collection.mutable.OpenHashMap empty();
  Code:
   Stack=2, Locals=1, Args_size=1
   0:	new	#35; //class scala/collection/mutable/OpenHashMap
   3:	dup
   4:	invokespecial	#36; //Method scala/collection/mutable/OpenHashMap."<init>":()V
   7:	areturn
  LineNumberTable: 
   line 25: 0

  Signature: length = 0x2
   00 25 

public scala.collection.mutable.OpenHashMap apply(scala.collection.Seq);
  Code:
   Stack=4, Locals=3, Args_size=2
   0:	new	#35; //class scala/collection/mutable/OpenHashMap
   3:	dup
   4:	invokespecial	#36; //Method scala/collection/mutable/OpenHashMap."<init>":()V
   7:	astore_2
   8:	aload_1
   9:	new	#42; //class scala/collection/mutable/OpenHashMap$$anonfun$apply$1
   12:	dup
   13:	aload_2
   14:	invokespecial	#45; //Method scala/collection/mutable/OpenHashMap$$anonfun$apply$1."<init>":(Lscala/collection/mutable/OpenHashMap;)V
   17:	invokeinterface	#51,  2; //InterfaceMethod scala/collection/IterableLike.foreach:(Lscala/Function1;)V
   22:	aload_2
   23:	areturn
  LineNumberTable: 
   line 20: 0
   line 21: 8
   line 22: 13
   line 21: 14
   line 22: 22

  LocalVariableTable: 
   Start  Length  Slot  Name   Signature
   0      24      0    this       Lscala/collection/mutable/OpenHashMap$;
   0      24      1    elems       Lscala/collection/Seq;
   8      15      2    dict$1       Lscala/collection/mutable/OpenHashMap;

  Signature: length = 0x2
   00 38 

}

