Compiled from "OpenHashMap.scala"
public class scala.collection.mutable.OpenHashMap$Entry extends java.lang.Object implements scala.ScalaObject
  SourceFile: "OpenHashMap.scala"
  Signature: length = 0x2
   00 29 
  Scala: length = 0x
   
  InnerClass: 
   public #46= #17 of #45; //Entry=class scala/collection/mutable/OpenHashMap$Entry of class scala/collection/mutable/OpenHashMap
  minor version: 0
  major version: 49
  Constant pool:
const #1 = Asciz	SourceFile;
const #2 = Asciz	OpenHashMap.scala;
const #3 = Asciz	value;
const #4 = Asciz	Lscala/Option;;
const #5 = Asciz	Lscala/Option<TValue;>;;
const #6 = Asciz	Signature;
const #7 = Asciz	hash;
const #8 = Asciz	I;
const #9 = Asciz	key;
const #10 = Asciz	Ljava/lang/Object;;
const #11 = Asciz	TKey;;
const #12 = Asciz	<init>;
const #13 = Asciz	(Ljava/lang/Object;ILscala/Option;)V;
const #14 = Asciz	Code;
const #15 = Asciz	LineNumberTable;
const #16 = Asciz	scala/collection/mutable/OpenHashMap$Entry;
const #17 = class	#16;	//  scala/collection/mutable/OpenHashMap$Entry
const #18 = NameAndType	#9:#10;//  key:Ljava/lang/Object;
const #19 = Field	#17.#18;	//  scala/collection/mutable/OpenHashMap$Entry.key:Ljava/lang/Object;
const #20 = NameAndType	#7:#8;//  hash:I
const #21 = Field	#17.#20;	//  scala/collection/mutable/OpenHashMap$Entry.hash:I
const #22 = NameAndType	#3:#4;//  value:Lscala/Option;
const #23 = Field	#17.#22;	//  scala/collection/mutable/OpenHashMap$Entry.value:Lscala/Option;
const #24 = Asciz	java/lang/Object;
const #25 = class	#24;	//  java/lang/Object
const #26 = Asciz	()V;
const #27 = NameAndType	#12:#26;//  "<init>":()V
const #28 = Method	#25.#27;	//  java/lang/Object."<init>":()V
const #29 = Asciz	this;
const #30 = Asciz	Lscala/collection/mutable/OpenHashMap$Entry;;
const #31 = Asciz	LocalVariableTable;
const #32 = Asciz	(TKey;ILscala/Option<TValue;>;)V;
const #33 = Asciz	value_$eq;
const #34 = Asciz	(Lscala/Option;)V;
const #35 = Asciz	(Lscala/Option<TValue;>;)V;
const #36 = Asciz	()Lscala/Option;;
const #37 = Asciz	()Lscala/Option<TValue;>;;
const #38 = Asciz	()I;
const #39 = Asciz	()Ljava/lang/Object;;
const #40 = Asciz	()TKey;;
const #41 = Asciz	<Key:Ljava/lang/Object;Value:Ljava/lang/Object;>Ljava/lang/Object;Lscala/ScalaObject;;
const #42 = Asciz	Scala;
const #43 = Asciz	InnerClasses;
const #44 = Asciz	scala/collection/mutable/OpenHashMap;
const #45 = class	#44;	//  scala/collection/mutable/OpenHashMap
const #46 = Asciz	Entry;
const #47 = Asciz	scala/ScalaObject;
const #48 = class	#47;	//  scala/ScalaObject

{
public scala.collection.mutable.OpenHashMap$Entry(java.lang.Object, int, scala.Option);
  Code:
   Stack=2, Locals=4, Args_size=4
   0:	aload_0
   1:	aload_1
   2:	putfield	#19; //Field key:Ljava/lang/Object;
   5:	aload_0
   6:	iload_2
   7:	putfield	#21; //Field hash:I
   10:	aload_0
   11:	aload_3
   12:	putfield	#23; //Field value:Lscala/Option;
   15:	aload_0
   16:	invokespecial	#28; //Method java/lang/Object."<init>":()V
   19:	return
  LineNumberTable: 
   line 23: 0
   line 24: 5
   line 25: 10
   line 23: 15

  LocalVariableTable: 
   Start  Length  Slot  Name   Signature
   0      20      0    this       Lscala/collection/mutable/OpenHashMap$Entry;
   0      20      1    key       Ljava/lang/Object;
   0      20      2    hash       I
   0      20      3    value       Lscala/Option;

  Signature: length = 0x2
   00 20 

public void value_$eq(scala.Option);
  Code:
   Stack=2, Locals=2, Args_size=2
   0:	aload_0
   1:	aload_1
   2:	putfield	#23; //Field value:Lscala/Option;
   5:	return
  LineNumberTable: 
   line 25: 0

  Signature: length = 0x2
   00 23 

public scala.Option value();
  Code:
   Stack=1, Locals=1, Args_size=1
   0:	aload_0
   1:	getfield	#23; //Field value:Lscala/Option;
   4:	areturn
  LineNumberTable: 
   line 25: 0

  Signature: length = 0x2
   00 25 

public int hash();
  Code:
   Stack=1, Locals=1, Args_size=1
   0:	aload_0
   1:	getfield	#21; //Field hash:I
   4:	ireturn
  LineNumberTable: 
   line 24: 0


public java.lang.Object key();
  Code:
   Stack=1, Locals=1, Args_size=1
   0:	aload_0
   1:	getfield	#19; //Field key:Ljava/lang/Object;
   4:	areturn
  LineNumberTable: 
   line 23: 0

  Signature: length = 0x2
   00 28 

}

