Compiled from "PriorityQueue.scala"
public final class scala.collection.mutable.PriorityQueue$ResizableArrayAccess extends java.lang.Object implements scala.collection.mutable.ResizableArray,scala.ScalaObject
  SourceFile: "PriorityQueue.scala"
  Signature: length = 0x2
   03 6C 
  Scala: length = 0x
   
  InnerClass: 
   public abstract $less$colon$less=class scala/Predef$$less$colon$less of class scala/Predef
   public WithFilter=class scala/collection/TraversableLike$WithFilter of class scala/collection/TraversableLike
   public final ResizableArrayAccess=class scala/collection/mutable/PriorityQueue$ResizableArrayAccess of class scala/collection/mutable/PriorityQueue
  minor version: 0
  major version: 49
  Constant pool:
Asciz	SourceFile;
Asciz	PriorityQueue.scala;
Asciz	size0;
Asciz	I;
Asciz	array;
Asciz	[Ljava/lang/Object;;
Asciz	()[Ljava/lang/Object;;
Asciz	Code;
Asciz	LineNumberTable;
Asciz	scala/collection/mutable/PriorityQueue$ResizableArrayAccess;
class	scala/collection/mutable/PriorityQueue$ResizableArrayAccess
NameAndType	array:[Ljava/lang/Object;
Field	scala/collection/mutable/PriorityQueue$ResizableArrayAccess.array:[Ljava/lang/Object;
Asciz	array_$eq;
Asciz	([Ljava/lang/Object;)V;
Asciz	()I;
NameAndType	size0:I
Field	scala/collection/mutable/PriorityQueue$ResizableArrayAccess.size0:I
Asciz	size0_$eq;
Asciz	(I)V;
Asciz	companion;
Asciz	()Lscala/collection/generic/GenericCompanion;;
Asciz	scala/collection/mutable/ResizableArray$class;
class	scala/collection/mutable/ResizableArray$class
Asciz	(Lscala/collection/mutable/ResizableArray;)Lscala/collection/generic/GenericCompanion;;
NameAndType	companion:(Lscala/collection/mutable/ResizableArray;)Lscala/collection/generic/GenericCompanion;
Method	scala/collection/mutable/ResizableArray$class.companion:(Lscala/collection/mutable/ResizableArray;)Lscala/collection/generic/GenericCompanion;
Asciz	initialSize;
Asciz	(Lscala/collection/mutable/ResizableArray;)I;
NameAndType	initialSize:(Lscala/collection/mutable/ResizableArray;)I
Method	scala/collection/mutable/ResizableArray$class.initialSize:(Lscala/collection/mutable/ResizableArray;)I
Asciz	length;
NameAndType	length:(Lscala/collection/mutable/ResizableArray;)I
Method	scala/collection/mutable/ResizableArray$class.length:(Lscala/collection/mutable/ResizableArray;)I
Asciz	apply;
Asciz	(I)Ljava/lang/Object;;
Asciz	(Lscala/collection/mutable/ResizableArray;I)Ljava/lang/Object;;
NameAndType	apply:(Lscala/collection/mutable/ResizableArray;I)Ljava/lang/Object;
Method	scala/collection/mutable/ResizableArray$class.apply:(Lscala/collection/mutable/ResizableArray;I)Ljava/lang/Object;
Asciz	this;
Asciz	Lscala/collection/mutable/PriorityQueue$ResizableArrayAccess;;
Asciz	idx;
Asciz	LocalVariableTable;
Asciz	update;
Asciz	(ILjava/lang/Object;)V;
Asciz	(Lscala/collection/mutable/ResizableArray;ILjava/lang/Object;)V;
NameAndType	update:(Lscala/collection/mutable/ResizableArray;ILjava/lang/Object;)V
Method	scala/collection/mutable/ResizableArray$class.update:(Lscala/collection/mutable/ResizableArray;ILjava/lang/Object;)V
Asciz	elem;
Asciz	Ljava/lang/Object;;
Asciz	foreach;
Asciz	(Lscala/Function1;)V;
Asciz	(Lscala/collection/mutable/ResizableArray;Lscala/Function1;)V;
NameAndType	foreach:(Lscala/collection/mutable/ResizableArray;Lscala/Function1;)V
Method	scala/collection/mutable/ResizableArray$class.foreach:(Lscala/collection/mutable/ResizableArray;Lscala/Function1;)V
Asciz	f;
Asciz	Lscala/Function1;;
Asciz	copyToArray;
Asciz	(Ljava/lang/Object;II)V;
Asciz	(Lscala/collection/mutable/ResizableArray;Ljava/lang/Object;II)V;
NameAndType	copyToArray:(Lscala/collection/mutable/ResizableArray;Ljava/lang/Object;II)V
Method	scala/collection/mutable/ResizableArray$class.copyToArray:(Lscala/collection/mutable/ResizableArray;Ljava/lang/Object;II)V
Asciz	xs;
Asciz	start;
Asciz	len;
Asciz	reduceToSize;
Asciz	(Lscala/collection/mutable/ResizableArray;I)V;
NameAndType	reduceToSize:(Lscala/collection/mutable/ResizableArray;I)V
Method	scala/collection/mutable/ResizableArray$class.reduceToSize:(Lscala/collection/mutable/ResizableArray;I)V
Asciz	sz;
Asciz	ensureSize;
NameAndType	ensureSize:(Lscala/collection/mutable/ResizableArray;I)V
Method	scala/collection/mutable/ResizableArray$class.ensureSize:(Lscala/collection/mutable/ResizableArray;I)V
Asciz	n;
Asciz	swap;
Asciz	(II)V;
Asciz	(Lscala/collection/mutable/ResizableArray;II)V;
NameAndType	swap:(Lscala/collection/mutable/ResizableArray;II)V
Method	scala/collection/mutable/ResizableArray$class.swap:(Lscala/collection/mutable/ResizableArray;II)V
Asciz	a;
Asciz	b;
Asciz	copy;
Asciz	(III)V;
Asciz	(Lscala/collection/mutable/ResizableArray;III)V;
NameAndType	copy:(Lscala/collection/mutable/ResizableArray;III)V
Method	scala/collection/mutable/ResizableArray$class.copy:(Lscala/collection/mutable/ResizableArray;III)V
Asciz	m;
Asciz	thisCollection;
Asciz	()Lscala/collection/mutable/IndexedSeq;;
Asciz	scala/collection/mutable/IndexedSeqLike$class;
class	scala/collection/mutable/IndexedSeqLike$class
Asciz	(Lscala/collection/mutable/IndexedSeqLike;)Lscala/collection/mutable/IndexedSeq;;
NameAndType	thisCollection:(Lscala/collection/mutable/IndexedSeqLike;)Lscala/collection/mutable/IndexedSeq;
Method	scala/collection/mutable/IndexedSeqLike$class.thisCollection:(Lscala/collection/mutable/IndexedSeqLike;)Lscala/collection/mutable/IndexedSeq;
Asciz	toCollection;
Asciz	(Ljava/lang/Object;)Lscala/collection/mutable/IndexedSeq;;
Asciz	(Lscala/collection/mutable/IndexedSeqLike;Ljava/lang/Object;)Lscala/collection/mutable/IndexedSeq;;
NameAndType	toCollection:(Lscala/collection/mutable/IndexedSeqLike;Ljava/lang/Object;)Lscala/collection/mutable/IndexedSeq;
Method	scala/collection/mutable/IndexedSeqLike$class.toCollection:(Lscala/collection/mutable/IndexedSeqLike;Ljava/lang/Object;)Lscala/collection/mutable/IndexedSeq;
Asciz	repr;
Asciz	view;
Asciz	()Lscala/collection/mutable/IndexedSeqView;;
Asciz	(Lscala/collection/mutable/IndexedSeqLike;)Lscala/collection/mutable/IndexedSeqView;;
NameAndType	view:(Lscala/collection/mutable/IndexedSeqLike;)Lscala/collection/mutable/IndexedSeqView;
Method	scala/collection/mutable/IndexedSeqLike$class.view:(Lscala/collection/mutable/IndexedSeqLike;)Lscala/collection/mutable/IndexedSeqView;
Asciz	(II)Lscala/collection/mutable/IndexedSeqView;;
Asciz	(Lscala/collection/mutable/IndexedSeqLike;II)Lscala/collection/mutable/IndexedSeqView;;
NameAndType	view:(Lscala/collection/mutable/IndexedSeqLike;II)Lscala/collection/mutable/IndexedSeqView;
Method	scala/collection/mutable/IndexedSeqLike$class.view:(Lscala/collection/mutable/IndexedSeqLike;II)Lscala/collection/mutable/IndexedSeqView;
Asciz	from;
Asciz	until;
Asciz	scala$collection$IndexedSeqLike$$super$reduceLeft;
Asciz	(Lscala/Function2;)Ljava/lang/Object;;
Asciz	scala/collection/TraversableLike$class;
class	scala/collection/TraversableLike$class
Asciz	reduceLeft;
Asciz	(Lscala/collection/TraversableLike;Lscala/Function2;)Ljava/lang/Object;;
NameAndType	reduceLeft:(Lscala/collection/TraversableLike;Lscala/Function2;)Ljava/lang/Object;
Method	scala/collection/TraversableLike$class.reduceLeft:(Lscala/collection/TraversableLike;Lscala/Function2;)Ljava/lang/Object;
Asciz	op;
Asciz	Lscala/Function2;;
Asciz	scala$collection$IndexedSeqLike$$super$reduceRight;
Asciz	scala/collection/IterableLike$class;
class	scala/collection/IterableLike$class
Asciz	reduceRight;
Asciz	(Lscala/collection/IterableLike;Lscala/Function2;)Ljava/lang/Object;;
NameAndType	reduceRight:(Lscala/collection/IterableLike;Lscala/Function2;)Ljava/lang/Object;
Method	scala/collection/IterableLike$class.reduceRight:(Lscala/collection/IterableLike;Lscala/Function2;)Ljava/lang/Object;
Asciz	scala$collection$IndexedSeqLike$$super$zip;
Asciz	(Lscala/collection/Iterable;Lscala/collection/generic/CanBuildFrom;)Ljava/lang/Object;;
Asciz	zip;
Asciz	(Lscala/collection/IterableLike;Lscala/collection/Iterable;Lscala/collection/generic/CanBuildFrom;)Ljava/lang/Object;;
NameAndType	zip:(Lscala/collection/IterableLike;Lscala/collection/Iterable;Lscala/collection/generic/CanBuildFrom;)Ljava/lang/Object;
Method	scala/collection/IterableLike$class.zip:(Lscala/collection/IterableLike;Lscala/collection/Iterable;Lscala/collection/generic/CanBuildFrom;)Ljava/lang/Object;
Asciz	that;
Asciz	Lscala/collection/Iterable;;
Asciz	bf;
Asciz	Lscala/collection/generic/CanBuildFrom;;
Asciz	scala$collection$IndexedSeqLike$$super$head;
Asciz	()Ljava/lang/Object;;
Asciz	head;
Asciz	(Lscala/collection/IterableLike;)Ljava/lang/Object;;
NameAndType	head:(Lscala/collection/IterableLike;)Ljava/lang/Object;
Method	scala/collection/IterableLike$class.head:(Lscala/collection/IterableLike;)Ljava/lang/Object;
Asciz	scala$collection$IndexedSeqLike$$super$tail;
Asciz	tail;
Asciz	(Lscala/collection/TraversableLike;)Ljava/lang/Object;;
NameAndType	tail:(Lscala/collection/TraversableLike;)Ljava/lang/Object;
Method	scala/collection/TraversableLike$class.tail:(Lscala/collection/TraversableLike;)Ljava/lang/Object;
Asciz	scala$collection$IndexedSeqLike$$super$last;
Asciz	last;
NameAndType	last:(Lscala/collection/TraversableLike;)Ljava/lang/Object;
Method	scala/collection/TraversableLike$class.last:(Lscala/collection/TraversableLike;)Ljava/lang/Object;
Asciz	scala$collection$IndexedSeqLike$$super$init;
Asciz	init;
NameAndType	init:(Lscala/collection/TraversableLike;)Ljava/lang/Object;
Method	scala/collection/TraversableLike$class.init:(Lscala/collection/TraversableLike;)Ljava/lang/Object;
Asciz	scala$collection$IndexedSeqLike$$super$sameElements;
Asciz	(Lscala/collection/Iterable;)Z;
Asciz	sameElements;
Asciz	(Lscala/collection/IterableLike;Lscala/collection/Iterable;)Z;
NameAndType	sameElements:(Lscala/collection/IterableLike;Lscala/collection/Iterable;)Z
Method	scala/collection/IterableLike$class.sameElements:(Lscala/collection/IterableLike;Lscala/collection/Iterable;)Z
Asciz	scala$collection$IndexedSeqLike$$super$endsWith;
Asciz	(Lscala/collection/Seq;)Z;
Asciz	scala/collection/SeqLike$class;
class	scala/collection/SeqLike$class
Asciz	endsWith;
Asciz	(Lscala/collection/SeqLike;Lscala/collection/Seq;)Z;
NameAndType	endsWith:(Lscala/collection/SeqLike;Lscala/collection/Seq;)Z
Method	scala/collection/SeqLike$class.endsWith:(Lscala/collection/SeqLike;Lscala/collection/Seq;)Z
Asciz	Lscala/collection/Seq;;
Asciz	iterator;
Asciz	()Lscala/collection/Iterator;;
Asciz	scala/collection/IndexedSeqLike$class;
class	scala/collection/IndexedSeqLike$class
Asciz	(Lscala/collection/IndexedSeqLike;)Lscala/collection/Iterator;;
NameAndType	iterator:(Lscala/collection/IndexedSeqLike;)Lscala/collection/Iterator;
Method	scala/collection/IndexedSeqLike$class.iterator:(Lscala/collection/IndexedSeqLike;)Lscala/collection/Iterator;
Asciz	isEmpty;
Asciz	()Z;
Asciz	(Lscala/collection/IndexedSeqLike;)Z;
NameAndType	isEmpty:(Lscala/collection/IndexedSeqLike;)Z
Method	scala/collection/IndexedSeqLike$class.isEmpty:(Lscala/collection/IndexedSeqLike;)Z
Asciz	forall;
Asciz	(Lscala/Function1;)Z;
Asciz	(Lscala/collection/IndexedSeqLike;Lscala/Function1;)Z;
NameAndType	forall:(Lscala/collection/IndexedSeqLike;Lscala/Function1;)Z
Method	scala/collection/IndexedSeqLike$class.forall:(Lscala/collection/IndexedSeqLike;Lscala/Function1;)Z
Asciz	p;
Asciz	exists;
NameAndType	exists:(Lscala/collection/IndexedSeqLike;Lscala/Function1;)Z
Method	scala/collection/IndexedSeqLike$class.exists:(Lscala/collection/IndexedSeqLike;Lscala/Function1;)Z
Asciz	find;
Asciz	(Lscala/Function1;)Lscala/Option;;
Asciz	(Lscala/collection/IndexedSeqLike;Lscala/Function1;)Lscala/Option;;
NameAndType	find:(Lscala/collection/IndexedSeqLike;Lscala/Function1;)Lscala/Option;
Method	scala/collection/IndexedSeqLike$class.find:(Lscala/collection/IndexedSeqLike;Lscala/Function1;)Lscala/Option;
Asciz	foldLeft;
Asciz	(Ljava/lang/Object;Lscala/Function2;)Ljava/lang/Object;;
Asciz	(Lscala/collection/IndexedSeqLike;Ljava/lang/Object;Lscala/Function2;)Ljava/lang/Object;;
NameAndType	foldLeft:(Lscala/collection/IndexedSeqLike;Ljava/lang/Object;Lscala/Function2;)Ljava/lang/Object;
Method	scala/collection/IndexedSeqLike$class.foldLeft:(Lscala/collection/IndexedSeqLike;Ljava/lang/Object;Lscala/Function2;)Ljava/lang/Object;
Asciz	z;
Asciz	foldRight;
NameAndType	foldRight:(Lscala/collection/IndexedSeqLike;Ljava/lang/Object;Lscala/Function2;)Ljava/lang/Object;
Method	scala/collection/IndexedSeqLike$class.foldRight:(Lscala/collection/IndexedSeqLike;Ljava/lang/Object;Lscala/Function2;)Ljava/lang/Object;
Asciz	(Lscala/collection/IndexedSeqLike;Lscala/Function2;)Ljava/lang/Object;;
NameAndType	reduceLeft:(Lscala/collection/IndexedSeqLike;Lscala/Function2;)Ljava/lang/Object;
Method	scala/collection/IndexedSeqLike$class.reduceLeft:(Lscala/collection/IndexedSeqLike;Lscala/Function2;)Ljava/lang/Object;
NameAndType	reduceRight:(Lscala/collection/IndexedSeqLike;Lscala/Function2;)Ljava/lang/Object;
Method	scala/collection/IndexedSeqLike$class.reduceRight:(Lscala/collection/IndexedSeqLike;Lscala/Function2;)Ljava/lang/Object;
Asciz	(Lscala/collection/IndexedSeqLike;Lscala/collection/Iterable;Lscala/collection/generic/CanBuildFrom;)Ljava/lang/Object;;
NameAndType	zip:(Lscala/collection/IndexedSeqLike;Lscala/collection/Iterable;Lscala/collection/generic/CanBuildFrom;)Ljava/lang/Object;
Method	scala/collection/IndexedSeqLike$class.zip:(Lscala/collection/IndexedSeqLike;Lscala/collection/Iterable;Lscala/collection/generic/CanBuildFrom;)Ljava/lang/Object;
Asciz	zipWithIndex;
Asciz	(Lscala/collection/generic/CanBuildFrom;)Ljava/lang/Object;;
Asciz	(Lscala/collection/IndexedSeqLike;Lscala/collection/generic/CanBuildFrom;)Ljava/lang/Object;;
NameAndType	zipWithIndex:(Lscala/collection/IndexedSeqLike;Lscala/collection/generic/CanBuildFrom;)Ljava/lang/Object;
Method	scala/collection/IndexedSeqLike$class.zipWithIndex:(Lscala/collection/IndexedSeqLike;Lscala/collection/generic/CanBuildFrom;)Ljava/lang/Object;
Asciz	slice;
Asciz	(II)Ljava/lang/Object;;
Asciz	(Lscala/collection/IndexedSeqLike;II)Ljava/lang/Object;;
NameAndType	slice:(Lscala/collection/IndexedSeqLike;II)Ljava/lang/Object;
Method	scala/collection/IndexedSeqLike$class.slice:(Lscala/collection/IndexedSeqLike;II)Ljava/lang/Object;
Asciz	(Lscala/collection/IndexedSeqLike;)Ljava/lang/Object;;
NameAndType	head:(Lscala/collection/IndexedSeqLike;)Ljava/lang/Object;
Method	scala/collection/IndexedSeqLike$class.head:(Lscala/collection/IndexedSeqLike;)Ljava/lang/Object;
NameAndType	tail:(Lscala/collection/IndexedSeqLike;)Ljava/lang/Object;
Method	scala/collection/IndexedSeqLike$class.tail:(Lscala/collection/IndexedSeqLike;)Ljava/lang/Object;
NameAndType	last:(Lscala/collection/IndexedSeqLike;)Ljava/lang/Object;
Method	scala/collection/IndexedSeqLike$class.last:(Lscala/collection/IndexedSeqLike;)Ljava/lang/Object;
NameAndType	init:(Lscala/collection/IndexedSeqLike;)Ljava/lang/Object;
Method	scala/collection/IndexedSeqLike$class.init:(Lscala/collection/IndexedSeqLike;)Ljava/lang/Object;
Asciz	take;
Asciz	(Lscala/collection/IndexedSeqLike;I)Ljava/lang/Object;;
NameAndType	take:(Lscala/collection/IndexedSeqLike;I)Ljava/lang/Object;
Method	scala/collection/IndexedSeqLike$class.take:(Lscala/collection/IndexedSeqLike;I)Ljava/lang/Object;
Asciz	drop;
NameAndType	drop:(Lscala/collection/IndexedSeqLike;I)Ljava/lang/Object;
Method	scala/collection/IndexedSeqLike$class.drop:(Lscala/collection/IndexedSeqLike;I)Ljava/lang/Object;
Asciz	takeRight;
NameAndType	takeRight:(Lscala/collection/IndexedSeqLike;I)Ljava/lang/Object;
Method	scala/collection/IndexedSeqLike$class.takeRight:(Lscala/collection/IndexedSeqLike;I)Ljava/lang/Object;
Asciz	dropRight;
NameAndType	dropRight:(Lscala/collection/IndexedSeqLike;I)Ljava/lang/Object;
Method	scala/collection/IndexedSeqLike$class.dropRight:(Lscala/collection/IndexedSeqLike;I)Ljava/lang/Object;
Asciz	splitAt;
Asciz	(I)Lscala/Tuple2;;
Asciz	(Lscala/collection/IndexedSeqLike;I)Lscala/Tuple2;;
NameAndType	splitAt:(Lscala/collection/IndexedSeqLike;I)Lscala/Tuple2;
Method	scala/collection/IndexedSeqLike$class.splitAt:(Lscala/collection/IndexedSeqLike;I)Lscala/Tuple2;
Asciz	takeWhile;
Asciz	(Lscala/Function1;)Ljava/lang/Object;;
Asciz	(Lscala/collection/IndexedSeqLike;Lscala/Function1;)Ljava/lang/Object;;
NameAndType	takeWhile:(Lscala/collection/IndexedSeqLike;Lscala/Function1;)Ljava/lang/Object;
Method	scala/collection/IndexedSeqLike$class.takeWhile:(Lscala/collection/IndexedSeqLike;Lscala/Function1;)Ljava/lang/Object;
Asciz	dropWhile;
NameAndType	dropWhile:(Lscala/collection/IndexedSeqLike;Lscala/Function1;)Ljava/lang/Object;
Method	scala/collection/IndexedSeqLike$class.dropWhile:(Lscala/collection/IndexedSeqLike;Lscala/Function1;)Ljava/lang/Object;
Asciz	span;
Asciz	(Lscala/Function1;)Lscala/Tuple2;;
Asciz	(Lscala/collection/IndexedSeqLike;Lscala/Function1;)Lscala/Tuple2;;
NameAndType	span:(Lscala/collection/IndexedSeqLike;Lscala/Function1;)Lscala/Tuple2;
Method	scala/collection/IndexedSeqLike$class.span:(Lscala/collection/IndexedSeqLike;Lscala/Function1;)Lscala/Tuple2;
Asciz	(Lscala/collection/IndexedSeqLike;Lscala/collection/Iterable;)Z;
NameAndType	sameElements:(Lscala/collection/IndexedSeqLike;Lscala/collection/Iterable;)Z
Method	scala/collection/IndexedSeqLike$class.sameElements:(Lscala/collection/IndexedSeqLike;Lscala/collection/Iterable;)Z
Asciz	lengthCompare;
Asciz	(I)I;
Asciz	(Lscala/collection/IndexedSeqLike;I)I;
NameAndType	lengthCompare:(Lscala/collection/IndexedSeqLike;I)I
Method	scala/collection/IndexedSeqLike$class.lengthCompare:(Lscala/collection/IndexedSeqLike;I)I
Asciz	segmentLength;
Asciz	(Lscala/Function1;I)I;
Asciz	(Lscala/collection/IndexedSeqLike;Lscala/Function1;I)I;
NameAndType	segmentLength:(Lscala/collection/IndexedSeqLike;Lscala/Function1;I)I
Method	scala/collection/IndexedSeqLike$class.segmentLength:(Lscala/collection/IndexedSeqLike;Lscala/Function1;I)I
Asciz	indexWhere;
NameAndType	indexWhere:(Lscala/collection/IndexedSeqLike;Lscala/Function1;I)I
Method	scala/collection/IndexedSeqLike$class.indexWhere:(Lscala/collection/IndexedSeqLike;Lscala/Function1;I)I
Asciz	lastIndexWhere;
NameAndType	lastIndexWhere:(Lscala/collection/IndexedSeqLike;Lscala/Function1;I)I
Method	scala/collection/IndexedSeqLike$class.lastIndexWhere:(Lscala/collection/IndexedSeqLike;Lscala/Function1;I)I
Asciz	end;
Asciz	reverse;
NameAndType	reverse:(Lscala/collection/IndexedSeqLike;)Ljava/lang/Object;
Method	scala/collection/IndexedSeqLike$class.reverse:(Lscala/collection/IndexedSeqLike;)Ljava/lang/Object;
Asciz	reverseIterator;
NameAndType	reverseIterator:(Lscala/collection/IndexedSeqLike;)Lscala/collection/Iterator;
Method	scala/collection/IndexedSeqLike$class.reverseIterator:(Lscala/collection/IndexedSeqLike;)Lscala/collection/Iterator;
Asciz	startsWith;
Asciz	(Lscala/collection/Seq;I)Z;
Asciz	(Lscala/collection/IndexedSeqLike;Lscala/collection/Seq;I)Z;
NameAndType	startsWith:(Lscala/collection/IndexedSeqLike;Lscala/collection/Seq;I)Z
Method	scala/collection/IndexedSeqLike$class.startsWith:(Lscala/collection/IndexedSeqLike;Lscala/collection/Seq;I)Z
Asciz	offset;
Asciz	(Lscala/collection/IndexedSeqLike;Lscala/collection/Seq;)Z;
NameAndType	endsWith:(Lscala/collection/IndexedSeqLike;Lscala/collection/Seq;)Z
Method	scala/collection/IndexedSeqLike$class.endsWith:(Lscala/collection/IndexedSeqLike;Lscala/collection/Seq;)Z
Asciz	size;
Asciz	(Lscala/collection/SeqLike;)I;
NameAndType	size:(Lscala/collection/SeqLike;)I
Method	scala/collection/SeqLike$class.size:(Lscala/collection/SeqLike;)I
Asciz	isDefinedAt;
Asciz	(I)Z;
Asciz	(Lscala/collection/SeqLike;I)Z;
NameAndType	isDefinedAt:(Lscala/collection/SeqLike;I)Z
Method	scala/collection/SeqLike$class.isDefinedAt:(Lscala/collection/SeqLike;I)Z
Asciz	prefixLength;
Asciz	(Lscala/Function1;)I;
Asciz	(Lscala/collection/SeqLike;Lscala/Function1;)I;
NameAndType	prefixLength:(Lscala/collection/SeqLike;Lscala/Function1;)I
Method	scala/collection/SeqLike$class.prefixLength:(Lscala/collection/SeqLike;Lscala/Function1;)I
NameAndType	indexWhere:(Lscala/collection/SeqLike;Lscala/Function1;)I
Method	scala/collection/SeqLike$class.indexWhere:(Lscala/collection/SeqLike;Lscala/Function1;)I
Asciz	findIndexOf;
NameAndType	findIndexOf:(Lscala/collection/SeqLike;Lscala/Function1;)I
Method	scala/collection/SeqLike$class.findIndexOf:(Lscala/collection/SeqLike;Lscala/Function1;)I
Asciz	indexOf;
Asciz	(Ljava/lang/Object;)I;
Asciz	(Lscala/collection/SeqLike;Ljava/lang/Object;)I;
NameAndType	indexOf:(Lscala/collection/SeqLike;Ljava/lang/Object;)I
Method	scala/collection/SeqLike$class.indexOf:(Lscala/collection/SeqLike;Ljava/lang/Object;)I
Asciz	(Ljava/lang/Object;I)I;
Asciz	(Lscala/collection/SeqLike;Ljava/lang/Object;I)I;
NameAndType	indexOf:(Lscala/collection/SeqLike;Ljava/lang/Object;I)I
Method	scala/collection/SeqLike$class.indexOf:(Lscala/collection/SeqLike;Ljava/lang/Object;I)I
Asciz	lastIndexOf;
NameAndType	lastIndexOf:(Lscala/collection/SeqLike;Ljava/lang/Object;)I
Method	scala/collection/SeqLike$class.lastIndexOf:(Lscala/collection/SeqLike;Ljava/lang/Object;)I
NameAndType	lastIndexOf:(Lscala/collection/SeqLike;Ljava/lang/Object;I)I
Method	scala/collection/SeqLike$class.lastIndexOf:(Lscala/collection/SeqLike;Ljava/lang/Object;I)I
NameAndType	lastIndexWhere:(Lscala/collection/SeqLike;Lscala/Function1;)I
Method	scala/collection/SeqLike$class.lastIndexWhere:(Lscala/collection/SeqLike;Lscala/Function1;)I
Asciz	reverseMap;
Asciz	(Lscala/Function1;Lscala/collection/generic/CanBuildFrom;)Ljava/lang/Object;;
Asciz	(Lscala/collection/SeqLike;Lscala/Function1;Lscala/collection/generic/CanBuildFrom;)Ljava/lang/Object;;
NameAndType	reverseMap:(Lscala/collection/SeqLike;Lscala/Function1;Lscala/collection/generic/CanBuildFrom;)Ljava/lang/Object;
Method	scala/collection/SeqLike$class.reverseMap:(Lscala/collection/SeqLike;Lscala/Function1;Lscala/collection/generic/CanBuildFrom;)Ljava/lang/Object;
Asciz	reversedElements;
Asciz	(Lscala/collection/SeqLike;)Lscala/collection/Iterator;;
NameAndType	reversedElements:(Lscala/collection/SeqLike;)Lscala/collection/Iterator;
Method	scala/collection/SeqLike$class.reversedElements:(Lscala/collection/SeqLike;)Lscala/collection/Iterator;
Asciz	Deprecated;
NameAndType	startsWith:(Lscala/collection/SeqLike;Lscala/collection/Seq;)Z
Method	scala/collection/SeqLike$class.startsWith:(Lscala/collection/SeqLike;Lscala/collection/Seq;)Z
Asciz	indexOfSlice;
Asciz	(Lscala/collection/Seq;)I;
Asciz	(Lscala/collection/SeqLike;Lscala/collection/Seq;)I;
NameAndType	indexOfSlice:(Lscala/collection/SeqLike;Lscala/collection/Seq;)I
Method	scala/collection/SeqLike$class.indexOfSlice:(Lscala/collection/SeqLike;Lscala/collection/Seq;)I
Asciz	(Lscala/collection/Seq;I)I;
Asciz	(Lscala/collection/SeqLike;Lscala/collection/Seq;I)I;
NameAndType	indexOfSlice:(Lscala/collection/SeqLike;Lscala/collection/Seq;I)I
Method	scala/collection/SeqLike$class.indexOfSlice:(Lscala/collection/SeqLike;Lscala/collection/Seq;I)I
Asciz	lastIndexOfSlice;
NameAndType	lastIndexOfSlice:(Lscala/collection/SeqLike;Lscala/collection/Seq;)I
Method	scala/collection/SeqLike$class.lastIndexOfSlice:(Lscala/collection/SeqLike;Lscala/collection/Seq;)I
NameAndType	lastIndexOfSlice:(Lscala/collection/SeqLike;Lscala/collection/Seq;I)I
Method	scala/collection/SeqLike$class.lastIndexOfSlice:(Lscala/collection/SeqLike;Lscala/collection/Seq;I)I
Asciz	containsSlice;
NameAndType	containsSlice:(Lscala/collection/SeqLike;Lscala/collection/Seq;)Z
Method	scala/collection/SeqLike$class.containsSlice:(Lscala/collection/SeqLike;Lscala/collection/Seq;)Z
Asciz	contains;
Asciz	(Ljava/lang/Object;)Z;
Asciz	(Lscala/collection/SeqLike;Ljava/lang/Object;)Z;
NameAndType	contains:(Lscala/collection/SeqLike;Ljava/lang/Object;)Z
Method	scala/collection/SeqLike$class.contains:(Lscala/collection/SeqLike;Ljava/lang/Object;)Z
Asciz	union;
Asciz	(Lscala/collection/Seq;Lscala/collection/generic/CanBuildFrom;)Ljava/lang/Object;;
Asciz	(Lscala/collection/SeqLike;Lscala/collection/Seq;Lscala/collection/generic/CanBuildFrom;)Ljava/lang/Object;;
NameAndType	union:(Lscala/collection/SeqLike;Lscala/collection/Seq;Lscala/collection/generic/CanBuildFrom;)Ljava/lang/Object;
Method	scala/collection/SeqLike$class.union:(Lscala/collection/SeqLike;Lscala/collection/Seq;Lscala/collection/generic/CanBuildFrom;)Ljava/lang/Object;
Asciz	diff;
Asciz	(Lscala/collection/Seq;)Ljava/lang/Object;;
Asciz	(Lscala/collection/SeqLike;Lscala/collection/Seq;)Ljava/lang/Object;;
NameAndType	diff:(Lscala/collection/SeqLike;Lscala/collection/Seq;)Ljava/lang/Object;
Method	scala/collection/SeqLike$class.diff:(Lscala/collection/SeqLike;Lscala/collection/Seq;)Ljava/lang/Object;
Asciz	intersect;
NameAndType	intersect:(Lscala/collection/SeqLike;Lscala/collection/Seq;)Ljava/lang/Object;
Method	scala/collection/SeqLike$class.intersect:(Lscala/collection/SeqLike;Lscala/collection/Seq;)Ljava/lang/Object;
Asciz	distinct;
Asciz	(Lscala/collection/SeqLike;)Ljava/lang/Object;;
NameAndType	distinct:(Lscala/collection/SeqLike;)Ljava/lang/Object;
Method	scala/collection/SeqLike$class.distinct:(Lscala/collection/SeqLike;)Ljava/lang/Object;
Asciz	patch;
Asciz	(ILscala/collection/Seq;ILscala/collection/generic/CanBuildFrom;)Ljava/lang/Object;;
Asciz	(Lscala/collection/SeqLike;ILscala/collection/Seq;ILscala/collection/generic/CanBuildFrom;)Ljava/lang/Object;;
NameAndType	patch:(Lscala/collection/SeqLike;ILscala/collection/Seq;ILscala/collection/generic/CanBuildFrom;)Ljava/lang/Object;
Method	scala/collection/SeqLike$class.patch:(Lscala/collection/SeqLike;ILscala/collection/Seq;ILscala/collection/generic/CanBuildFrom;)Ljava/lang/Object;
Asciz	replaced;
Asciz	updated;
Asciz	(ILjava/lang/Object;Lscala/collection/generic/CanBuildFrom;)Ljava/lang/Object;;
Asciz	(Lscala/collection/SeqLike;ILjava/lang/Object;Lscala/collection/generic/CanBuildFrom;)Ljava/lang/Object;;
NameAndType	updated:(Lscala/collection/SeqLike;ILjava/lang/Object;Lscala/collection/generic/CanBuildFrom;)Ljava/lang/Object;
Method	scala/collection/SeqLike$class.updated:(Lscala/collection/SeqLike;ILjava/lang/Object;Lscala/collection/generic/CanBuildFrom;)Ljava/lang/Object;
Asciz	index;
Asciz	$plus$colon;
Asciz	(Ljava/lang/Object;Lscala/collection/generic/CanBuildFrom;)Ljava/lang/Object;;
Asciz	(Lscala/collection/SeqLike;Ljava/lang/Object;Lscala/collection/generic/CanBuildFrom;)Ljava/lang/Object;;
NameAndType	$plus$colon:(Lscala/collection/SeqLike;Ljava/lang/Object;Lscala/collection/generic/CanBuildFrom;)Ljava/lang/Object;
Method	scala/collection/SeqLike$class.$plus$colon:(Lscala/collection/SeqLike;Ljava/lang/Object;Lscala/collection/generic/CanBuildFrom;)Ljava/lang/Object;
Asciz	$colon$plus;
NameAndType	$colon$plus:(Lscala/collection/SeqLike;Ljava/lang/Object;Lscala/collection/generic/CanBuildFrom;)Ljava/lang/Object;
Method	scala/collection/SeqLike$class.$colon$plus:(Lscala/collection/SeqLike;Ljava/lang/Object;Lscala/collection/generic/CanBuildFrom;)Ljava/lang/Object;
Asciz	padTo;
NameAndType	padTo:(Lscala/collection/SeqLike;ILjava/lang/Object;Lscala/collection/generic/CanBuildFrom;)Ljava/lang/Object;
Method	scala/collection/SeqLike$class.padTo:(Lscala/collection/SeqLike;ILjava/lang/Object;Lscala/collection/generic/CanBuildFrom;)Ljava/lang/Object;
Asciz	corresponds;
Asciz	(Lscala/collection/Seq;Lscala/Function2;)Z;
Asciz	(Lscala/collection/SeqLike;Lscala/collection/Seq;Lscala/Function2;)Z;
NameAndType	corresponds:(Lscala/collection/SeqLike;Lscala/collection/Seq;Lscala/Function2;)Z
Method	scala/collection/SeqLike$class.corresponds:(Lscala/collection/SeqLike;Lscala/collection/Seq;Lscala/Function2;)Z
Asciz	sortWith;
Asciz	(Lscala/collection/SeqLike;Lscala/Function2;)Ljava/lang/Object;;
NameAndType	sortWith:(Lscala/collection/SeqLike;Lscala/Function2;)Ljava/lang/Object;
Method	scala/collection/SeqLike$class.sortWith:(Lscala/collection/SeqLike;Lscala/Function2;)Ljava/lang/Object;
Asciz	lt;
Asciz	sortBy;
Asciz	(Lscala/Function1;Lscala/math/Ordering;)Ljava/lang/Object;;
Asciz	(Lscala/collection/SeqLike;Lscala/Function1;Lscala/math/Ordering;)Ljava/lang/Object;;
NameAndType	sortBy:(Lscala/collection/SeqLike;Lscala/Function1;Lscala/math/Ordering;)Ljava/lang/Object;
Method	scala/collection/SeqLike$class.sortBy:(Lscala/collection/SeqLike;Lscala/Function1;Lscala/math/Ordering;)Ljava/lang/Object;
Asciz	ord;
Asciz	Lscala/math/Ordering;;
Asciz	sorted;
Asciz	(Lscala/math/Ordering;)Ljava/lang/Object;;
Asciz	(Lscala/collection/SeqLike;Lscala/math/Ordering;)Ljava/lang/Object;;
NameAndType	sorted:(Lscala/collection/SeqLike;Lscala/math/Ordering;)Ljava/lang/Object;
Method	scala/collection/SeqLike$class.sorted:(Lscala/collection/SeqLike;Lscala/math/Ordering;)Ljava/lang/Object;
Asciz	toSeq;
Asciz	()Lscala/collection/Seq;;
Asciz	(Lscala/collection/SeqLike;)Lscala/collection/Seq;;
NameAndType	toSeq:(Lscala/collection/SeqLike;)Lscala/collection/Seq;
Method	scala/collection/SeqLike$class.toSeq:(Lscala/collection/SeqLike;)Lscala/collection/Seq;
Asciz	indices;
Asciz	()Lscala/collection/immutable/Range;;
Asciz	(Lscala/collection/SeqLike;)Lscala/collection/immutable/Range;;
NameAndType	indices:(Lscala/collection/SeqLike;)Lscala/collection/immutable/Range;
Method	scala/collection/SeqLike$class.indices:(Lscala/collection/SeqLike;)Lscala/collection/immutable/Range;
Asciz	hashCode;
NameAndType	hashCode:(Lscala/collection/SeqLike;)I
Method	scala/collection/SeqLike$class.hashCode:(Lscala/collection/SeqLike;)I
Asciz	equals;
NameAndType	equals:(Lscala/collection/SeqLike;Ljava/lang/Object;)Z
Method	scala/collection/SeqLike$class.equals:(Lscala/collection/SeqLike;Ljava/lang/Object;)Z
Asciz	toString;
Asciz	()Ljava/lang/String;;
Asciz	(Lscala/collection/SeqLike;)Ljava/lang/String;;
NameAndType	toString:(Lscala/collection/SeqLike;)Ljava/lang/String;
Method	scala/collection/SeqLike$class.toString:(Lscala/collection/SeqLike;)Ljava/lang/String;
Asciz	findLastIndexOf;
NameAndType	findLastIndexOf:(Lscala/collection/SeqLike;Lscala/Function1;)I
Method	scala/collection/SeqLike$class.findLastIndexOf:(Lscala/collection/SeqLike;Lscala/Function1;)I
Asciz	equalsWith;
NameAndType	equalsWith:(Lscala/collection/SeqLike;Lscala/collection/Seq;Lscala/Function2;)Z
Method	scala/collection/SeqLike$class.equalsWith:(Lscala/collection/SeqLike;Lscala/collection/Seq;Lscala/Function2;)Z
Asciz	projection;
Asciz	()Lscala/collection/SeqView;;
Asciz	(Lscala/collection/SeqLike;)Lscala/collection/SeqView;;
NameAndType	projection:(Lscala/collection/SeqLike;)Lscala/collection/SeqView;
Method	scala/collection/SeqLike$class.projection:(Lscala/collection/SeqLike;)Lscala/collection/SeqView;
Asciz	orElse;
Asciz	(Lscala/PartialFunction;)Lscala/PartialFunction;;
Asciz	scala/PartialFunction$class;
class	scala/PartialFunction$class
Asciz	(Lscala/PartialFunction;Lscala/PartialFunction;)Lscala/PartialFunction;;
NameAndType	orElse:(Lscala/PartialFunction;Lscala/PartialFunction;)Lscala/PartialFunction;
Method	scala/PartialFunction$class.orElse:(Lscala/PartialFunction;Lscala/PartialFunction;)Lscala/PartialFunction;
Asciz	Lscala/PartialFunction;;
Asciz	andThen;
Asciz	(Lscala/Function1;)Lscala/PartialFunction;;
Asciz	(Lscala/PartialFunction;Lscala/Function1;)Lscala/PartialFunction;;
NameAndType	andThen:(Lscala/PartialFunction;Lscala/Function1;)Lscala/PartialFunction;
Method	scala/PartialFunction$class.andThen:(Lscala/PartialFunction;Lscala/Function1;)Lscala/PartialFunction;
Asciz	k;
Asciz	lift;
Asciz	()Lscala/Function1;;
Asciz	(Lscala/PartialFunction;)Lscala/Function1;;
NameAndType	lift:(Lscala/PartialFunction;)Lscala/Function1;
Method	scala/PartialFunction$class.lift:(Lscala/PartialFunction;)Lscala/Function1;
Asciz	compose;
Asciz	(Lscala/Function1;)Lscala/Function1;;
Asciz	scala/Function1$class;
class	scala/Function1$class
Asciz	(Lscala/Function1;Lscala/Function1;)Lscala/Function1;;
NameAndType	compose:(Lscala/Function1;Lscala/Function1;)Lscala/Function1;
Method	scala/Function1$class.compose:(Lscala/Function1;Lscala/Function1;)Lscala/Function1;
Asciz	g;
Asciz	elements;
Asciz	(Lscala/collection/IterableLike;)Lscala/collection/Iterator;;
NameAndType	elements:(Lscala/collection/IterableLike;)Lscala/collection/Iterator;
Method	scala/collection/IterableLike$class.elements:(Lscala/collection/IterableLike;)Lscala/collection/Iterator;
Asciz	toIterable;
Asciz	()Lscala/collection/Iterable;;
Asciz	(Lscala/collection/IterableLike;)Lscala/collection/Iterable;;
NameAndType	toIterable:(Lscala/collection/IterableLike;)Lscala/collection/Iterable;
Method	scala/collection/IterableLike$class.toIterable:(Lscala/collection/IterableLike;)Lscala/collection/Iterable;
Asciz	grouped;
Asciz	(I)Lscala/collection/Iterator;;
Asciz	(Lscala/collection/IterableLike;I)Lscala/collection/Iterator;;
NameAndType	grouped:(Lscala/collection/IterableLike;I)Lscala/collection/Iterator;
Method	scala/collection/IterableLike$class.grouped:(Lscala/collection/IterableLike;I)Lscala/collection/Iterator;
Asciz	sliding;
NameAndType	sliding:(Lscala/collection/IterableLike;I)Lscala/collection/Iterator;
Method	scala/collection/IterableLike$class.sliding:(Lscala/collection/IterableLike;I)Lscala/collection/Iterator;
Asciz	(II)Lscala/collection/Iterator;;
Asciz	(Lscala/collection/IterableLike;II)Lscala/collection/Iterator;;
NameAndType	sliding:(Lscala/collection/IterableLike;II)Lscala/collection/Iterator;
Method	scala/collection/IterableLike$class.sliding:(Lscala/collection/IterableLike;II)Lscala/collection/Iterator;
Asciz	step;
Asciz	zipAll;
Asciz	(Lscala/collection/Iterable;Ljava/lang/Object;Ljava/lang/Object;Lscala/collection/generic/CanBuildFrom;)Ljava/lang/Object;;
Asciz	(Lscala/collection/IterableLike;Lscala/collection/Iterable;Ljava/lang/Object;Ljava/lang/Object;Lscala/collection/generic/CanBuildFrom;)Ljava/lang/Object;;
NameAndType	zipAll:(Lscala/collection/IterableLike;Lscala/collection/Iterable;Ljava/lang/Object;Ljava/lang/Object;Lscala/collection/generic/CanBuildFrom;)Ljava/lang/Object;
Method	scala/collection/IterableLike$class.zipAll:(Lscala/collection/IterableLike;Lscala/collection/Iterable;Ljava/lang/Object;Ljava/lang/Object;Lscala/collection/generic/CanBuildFrom;)Ljava/lang/Object;
Asciz	thisElem;
Asciz	thatElem;
Asciz	toStream;
Asciz	()Lscala/collection/immutable/Stream;;
Asciz	(Lscala/collection/IterableLike;)Lscala/collection/immutable/Stream;;
NameAndType	toStream:(Lscala/collection/IterableLike;)Lscala/collection/immutable/Stream;
Method	scala/collection/IterableLike$class.toStream:(Lscala/collection/IterableLike;)Lscala/collection/immutable/Stream;
Asciz	canEqual;
Asciz	(Lscala/collection/IterableLike;Ljava/lang/Object;)Z;
NameAndType	canEqual:(Lscala/collection/IterableLike;Ljava/lang/Object;)Z
Method	scala/collection/IterableLike$class.canEqual:(Lscala/collection/IterableLike;Ljava/lang/Object;)Z
Asciz	first;
NameAndType	first:(Lscala/collection/IterableLike;)Ljava/lang/Object;
Method	scala/collection/IterableLike$class.first:(Lscala/collection/IterableLike;)Ljava/lang/Object;
Asciz	firstOption;
Asciz	()Lscala/Option;;
Asciz	(Lscala/collection/IterableLike;)Lscala/Option;;
NameAndType	firstOption:(Lscala/collection/IterableLike;)Lscala/Option;
Method	scala/collection/IterableLike$class.firstOption:(Lscala/collection/IterableLike;)Lscala/Option;
Asciz	newBuilder;
Asciz	()Lscala/collection/mutable/Builder;;
Asciz	scala/collection/generic/GenericTraversableTemplate$class;
class	scala/collection/generic/GenericTraversableTemplate$class
Asciz	(Lscala/collection/generic/GenericTraversableTemplate;)Lscala/collection/mutable/Builder;;
NameAndType	newBuilder:(Lscala/collection/generic/GenericTraversableTemplate;)Lscala/collection/mutable/Builder;
Method	scala/collection/generic/GenericTraversableTemplate$class.newBuilder:(Lscala/collection/generic/GenericTraversableTemplate;)Lscala/collection/mutable/Builder;
Asciz	genericBuilder;
NameAndType	genericBuilder:(Lscala/collection/generic/GenericTraversableTemplate;)Lscala/collection/mutable/Builder;
Method	scala/collection/generic/GenericTraversableTemplate$class.genericBuilder:(Lscala/collection/generic/GenericTraversableTemplate;)Lscala/collection/mutable/Builder;
Asciz	unzip;
Asciz	(Lscala/collection/generic/GenericTraversableTemplate;Lscala/Function1;)Lscala/Tuple2;;
NameAndType	unzip:(Lscala/collection/generic/GenericTraversableTemplate;Lscala/Function1;)Lscala/Tuple2;
Method	scala/collection/generic/GenericTraversableTemplate$class.unzip:(Lscala/collection/generic/GenericTraversableTemplate;Lscala/Function1;)Lscala/Tuple2;
Asciz	asPair;
Asciz	flatten;
Asciz	(Lscala/Function1;)Lscala/collection/Traversable;;
Asciz	(Lscala/collection/generic/GenericTraversableTemplate;Lscala/Function1;)Lscala/collection/Traversable;;
NameAndType	flatten:(Lscala/collection/generic/GenericTraversableTemplate;Lscala/Function1;)Lscala/collection/Traversable;
Method	scala/collection/generic/GenericTraversableTemplate$class.flatten:(Lscala/collection/generic/GenericTraversableTemplate;Lscala/Function1;)Lscala/collection/Traversable;
Asciz	asTraversable;
Asciz	transpose;
NameAndType	transpose:(Lscala/collection/generic/GenericTraversableTemplate;Lscala/Function1;)Lscala/collection/Traversable;
Method	scala/collection/generic/GenericTraversableTemplate$class.transpose:(Lscala/collection/generic/GenericTraversableTemplate;Lscala/Function1;)Lscala/collection/Traversable;
NameAndType	repr:(Lscala/collection/TraversableLike;)Ljava/lang/Object;
Method	scala/collection/TraversableLike$class.repr:(Lscala/collection/TraversableLike;)Ljava/lang/Object;
Asciz	nonEmpty;
Asciz	(Lscala/collection/TraversableLike;)Z;
NameAndType	nonEmpty:(Lscala/collection/TraversableLike;)Z
Method	scala/collection/TraversableLike$class.nonEmpty:(Lscala/collection/TraversableLike;)Z
Asciz	hasDefiniteSize;
NameAndType	hasDefiniteSize:(Lscala/collection/TraversableLike;)Z
Method	scala/collection/TraversableLike$class.hasDefiniteSize:(Lscala/collection/TraversableLike;)Z
Asciz	$plus$plus;
Asciz	(Lscala/collection/Traversable;Lscala/collection/generic/CanBuildFrom;)Ljava/lang/Object;;
Asciz	(Lscala/collection/TraversableLike;Lscala/collection/Traversable;Lscala/collection/generic/CanBuildFrom;)Ljava/lang/Object;;
NameAndType	$plus$plus:(Lscala/collection/TraversableLike;Lscala/collection/Traversable;Lscala/collection/generic/CanBuildFrom;)Ljava/lang/Object;
Method	scala/collection/TraversableLike$class.$plus$plus:(Lscala/collection/TraversableLike;Lscala/collection/Traversable;Lscala/collection/generic/CanBuildFrom;)Ljava/lang/Object;
Asciz	Lscala/collection/Traversable;;
Asciz	(Lscala/collection/Iterator;Lscala/collection/generic/CanBuildFrom;)Ljava/lang/Object;;
Asciz	(Lscala/collection/TraversableLike;Lscala/collection/Iterator;Lscala/collection/generic/CanBuildFrom;)Ljava/lang/Object;;
NameAndType	$plus$plus:(Lscala/collection/TraversableLike;Lscala/collection/Iterator;Lscala/collection/generic/CanBuildFrom;)Ljava/lang/Object;
Method	scala/collection/TraversableLike$class.$plus$plus:(Lscala/collection/TraversableLike;Lscala/collection/Iterator;Lscala/collection/generic/CanBuildFrom;)Ljava/lang/Object;
Asciz	Lscala/collection/Iterator;;
Asciz	map;
Asciz	(Lscala/collection/TraversableLike;Lscala/Function1;Lscala/collection/generic/CanBuildFrom;)Ljava/lang/Object;;
NameAndType	map:(Lscala/collection/TraversableLike;Lscala/Function1;Lscala/collection/generic/CanBuildFrom;)Ljava/lang/Object;
Method	scala/collection/TraversableLike$class.map:(Lscala/collection/TraversableLike;Lscala/Function1;Lscala/collection/generic/CanBuildFrom;)Ljava/lang/Object;
Asciz	flatMap;
NameAndType	flatMap:(Lscala/collection/TraversableLike;Lscala/Function1;Lscala/collection/generic/CanBuildFrom;)Ljava/lang/Object;
Method	scala/collection/TraversableLike$class.flatMap:(Lscala/collection/TraversableLike;Lscala/Function1;Lscala/collection/generic/CanBuildFrom;)Ljava/lang/Object;
Asciz	filter;
Asciz	(Lscala/collection/TraversableLike;Lscala/Function1;)Ljava/lang/Object;;
NameAndType	filter:(Lscala/collection/TraversableLike;Lscala/Function1;)Ljava/lang/Object;
Method	scala/collection/TraversableLike$class.filter:(Lscala/collection/TraversableLike;Lscala/Function1;)Ljava/lang/Object;
Asciz	filterNot;
NameAndType	filterNot:(Lscala/collection/TraversableLike;Lscala/Function1;)Ljava/lang/Object;
Method	scala/collection/TraversableLike$class.filterNot:(Lscala/collection/TraversableLike;Lscala/Function1;)Ljava/lang/Object;
Asciz	partialMap;
Asciz	(Lscala/PartialFunction;Lscala/collection/generic/CanBuildFrom;)Ljava/lang/Object;;
Asciz	(Lscala/collection/TraversableLike;Lscala/PartialFunction;Lscala/collection/generic/CanBuildFrom;)Ljava/lang/Object;;
NameAndType	partialMap:(Lscala/collection/TraversableLike;Lscala/PartialFunction;Lscala/collection/generic/CanBuildFrom;)Ljava/lang/Object;
Method	scala/collection/TraversableLike$class.partialMap:(Lscala/collection/TraversableLike;Lscala/PartialFunction;Lscala/collection/generic/CanBuildFrom;)Ljava/lang/Object;
Asciz	pf;
Asciz	partition;
Asciz	(Lscala/collection/TraversableLike;Lscala/Function1;)Lscala/Tuple2;;
NameAndType	partition:(Lscala/collection/TraversableLike;Lscala/Function1;)Lscala/Tuple2;
Method	scala/collection/TraversableLike$class.partition:(Lscala/collection/TraversableLike;Lscala/Function1;)Lscala/Tuple2;
Asciz	groupBy;
Asciz	(Lscala/Function1;)Lscala/collection/Map;;
Asciz	(Lscala/collection/TraversableLike;Lscala/Function1;)Lscala/collection/Map;;
NameAndType	groupBy:(Lscala/collection/TraversableLike;Lscala/Function1;)Lscala/collection/Map;
Method	scala/collection/TraversableLike$class.groupBy:(Lscala/collection/TraversableLike;Lscala/Function1;)Lscala/collection/Map;
Asciz	count;
Asciz	(Lscala/collection/TraversableLike;Lscala/Function1;)I;
NameAndType	count:(Lscala/collection/TraversableLike;Lscala/Function1;)I
Method	scala/collection/TraversableLike$class.count:(Lscala/collection/TraversableLike;Lscala/Function1;)I
Asciz	$div$colon;
Asciz	(Lscala/collection/TraversableLike;Ljava/lang/Object;Lscala/Function2;)Ljava/lang/Object;;
NameAndType	$div$colon:(Lscala/collection/TraversableLike;Ljava/lang/Object;Lscala/Function2;)Ljava/lang/Object;
Method	scala/collection/TraversableLike$class.$div$colon:(Lscala/collection/TraversableLike;Ljava/lang/Object;Lscala/Function2;)Ljava/lang/Object;
Asciz	$colon$bslash;
NameAndType	$colon$bslash:(Lscala/collection/TraversableLike;Ljava/lang/Object;Lscala/Function2;)Ljava/lang/Object;
Method	scala/collection/TraversableLike$class.$colon$bslash:(Lscala/collection/TraversableLike;Ljava/lang/Object;Lscala/Function2;)Ljava/lang/Object;
Asciz	reduceLeftOption;
Asciz	(Lscala/Function2;)Lscala/Option;;
Asciz	(Lscala/collection/TraversableLike;Lscala/Function2;)Lscala/Option;;
NameAndType	reduceLeftOption:(Lscala/collection/TraversableLike;Lscala/Function2;)Lscala/Option;
Method	scala/collection/TraversableLike$class.reduceLeftOption:(Lscala/collection/TraversableLike;Lscala/Function2;)Lscala/Option;
Asciz	reduceRightOption;
NameAndType	reduceRightOption:(Lscala/collection/TraversableLike;Lscala/Function2;)Lscala/Option;
Method	scala/collection/TraversableLike$class.reduceRightOption:(Lscala/collection/TraversableLike;Lscala/Function2;)Lscala/Option;
Asciz	scanLeft;
Asciz	(Ljava/lang/Object;Lscala/Function2;Lscala/collection/generic/CanBuildFrom;)Ljava/lang/Object;;
Asciz	(Lscala/collection/TraversableLike;Ljava/lang/Object;Lscala/Function2;Lscala/collection/generic/CanBuildFrom;)Ljava/lang/Object;;
NameAndType	scanLeft:(Lscala/collection/TraversableLike;Ljava/lang/Object;Lscala/Function2;Lscala/collection/generic/CanBuildFrom;)Ljava/lang/Object;
Method	scala/collection/TraversableLike$class.scanLeft:(Lscala/collection/TraversableLike;Ljava/lang/Object;Lscala/Function2;Lscala/collection/generic/CanBuildFrom;)Ljava/lang/Object;
Asciz	scanRight;
NameAndType	scanRight:(Lscala/collection/TraversableLike;Ljava/lang/Object;Lscala/Function2;Lscala/collection/generic/CanBuildFrom;)Ljava/lang/Object;
Method	scala/collection/TraversableLike$class.scanRight:(Lscala/collection/TraversableLike;Ljava/lang/Object;Lscala/Function2;Lscala/collection/generic/CanBuildFrom;)Ljava/lang/Object;
Asciz	sum;
Asciz	(Lscala/math/Numeric;)Ljava/lang/Object;;
Asciz	(Lscala/collection/TraversableLike;Lscala/math/Numeric;)Ljava/lang/Object;;
NameAndType	sum:(Lscala/collection/TraversableLike;Lscala/math/Numeric;)Ljava/lang/Object;
Method	scala/collection/TraversableLike$class.sum:(Lscala/collection/TraversableLike;Lscala/math/Numeric;)Ljava/lang/Object;
Asciz	num;
Asciz	Lscala/math/Numeric;;
Asciz	product;
NameAndType	product:(Lscala/collection/TraversableLike;Lscala/math/Numeric;)Ljava/lang/Object;
Method	scala/collection/TraversableLike$class.product:(Lscala/collection/TraversableLike;Lscala/math/Numeric;)Ljava/lang/Object;
Asciz	min;
Asciz	(Lscala/collection/TraversableLike;Lscala/math/Ordering;)Ljava/lang/Object;;
NameAndType	min:(Lscala/collection/TraversableLike;Lscala/math/Ordering;)Ljava/lang/Object;
Method	scala/collection/TraversableLike$class.min:(Lscala/collection/TraversableLike;Lscala/math/Ordering;)Ljava/lang/Object;
Asciz	cmp;
Asciz	max;
NameAndType	max:(Lscala/collection/TraversableLike;Lscala/math/Ordering;)Ljava/lang/Object;
Method	scala/collection/TraversableLike$class.max:(Lscala/collection/TraversableLike;Lscala/math/Ordering;)Ljava/lang/Object;
Asciz	headOption;
Asciz	(Lscala/collection/TraversableLike;)Lscala/Option;;
NameAndType	headOption:(Lscala/collection/TraversableLike;)Lscala/Option;
Method	scala/collection/TraversableLike$class.headOption:(Lscala/collection/TraversableLike;)Lscala/Option;
Asciz	lastOption;
NameAndType	lastOption:(Lscala/collection/TraversableLike;)Lscala/Option;
Method	scala/collection/TraversableLike$class.lastOption:(Lscala/collection/TraversableLike;)Lscala/Option;
Asciz	copyToBuffer;
Asciz	(Lscala/collection/mutable/Buffer;)V;
Asciz	(Lscala/collection/TraversableLike;Lscala/collection/mutable/Buffer;)V;
NameAndType	copyToBuffer:(Lscala/collection/TraversableLike;Lscala/collection/mutable/Buffer;)V
Method	scala/collection/TraversableLike$class.copyToBuffer:(Lscala/collection/TraversableLike;Lscala/collection/mutable/Buffer;)V
Asciz	dest;
Asciz	Lscala/collection/mutable/Buffer;;
Asciz	(Ljava/lang/Object;I)V;
Asciz	(Lscala/collection/TraversableLike;Ljava/lang/Object;I)V;
NameAndType	copyToArray:(Lscala/collection/TraversableLike;Ljava/lang/Object;I)V
Method	scala/collection/TraversableLike$class.copyToArray:(Lscala/collection/TraversableLike;Ljava/lang/Object;I)V
Asciz	(Ljava/lang/Object;)V;
Asciz	(Lscala/collection/TraversableLike;Ljava/lang/Object;)V;
NameAndType	copyToArray:(Lscala/collection/TraversableLike;Ljava/lang/Object;)V
Method	scala/collection/TraversableLike$class.copyToArray:(Lscala/collection/TraversableLike;Ljava/lang/Object;)V
Asciz	toArray;
Asciz	(Lscala/reflect/ClassManifest;)Ljava/lang/Object;;
Asciz	(Lscala/collection/TraversableLike;Lscala/reflect/ClassManifest;)Ljava/lang/Object;;
NameAndType	toArray:(Lscala/collection/TraversableLike;Lscala/reflect/ClassManifest;)Ljava/lang/Object;
Method	scala/collection/TraversableLike$class.toArray:(Lscala/collection/TraversableLike;Lscala/reflect/ClassManifest;)Ljava/lang/Object;
Asciz	evidence$1;
Asciz	Lscala/reflect/ClassManifest;;
Asciz	toList;
Asciz	()Lscala/collection/immutable/List;;
Asciz	(Lscala/collection/TraversableLike;)Lscala/collection/immutable/List;;
NameAndType	toList:(Lscala/collection/TraversableLike;)Lscala/collection/immutable/List;
Method	scala/collection/TraversableLike$class.toList:(Lscala/collection/TraversableLike;)Lscala/collection/immutable/List;
Asciz	toIndexedSeq;
Asciz	(Lscala/collection/TraversableLike;)Lscala/collection/mutable/IndexedSeq;;
NameAndType	toIndexedSeq:(Lscala/collection/TraversableLike;)Lscala/collection/mutable/IndexedSeq;
Method	scala/collection/TraversableLike$class.toIndexedSeq:(Lscala/collection/TraversableLike;)Lscala/collection/mutable/IndexedSeq;
Asciz	toSet;
Asciz	()Lscala/collection/immutable/Set;;
Asciz	(Lscala/collection/TraversableLike;)Lscala/collection/immutable/Set;;
NameAndType	toSet:(Lscala/collection/TraversableLike;)Lscala/collection/immutable/Set;
Method	scala/collection/TraversableLike$class.toSet:(Lscala/collection/TraversableLike;)Lscala/collection/immutable/Set;
Asciz	toMap;
Asciz	(Lscala/Predef$$less$colon$less;)Lscala/collection/immutable/Map;;
Asciz	(Lscala/collection/TraversableLike;Lscala/Predef$$less$colon$less;)Lscala/collection/immutable/Map;;
NameAndType	toMap:(Lscala/collection/TraversableLike;Lscala/Predef$$less$colon$less;)Lscala/collection/immutable/Map;
Method	scala/collection/TraversableLike$class.toMap:(Lscala/collection/TraversableLike;Lscala/Predef$$less$colon$less;)Lscala/collection/immutable/Map;
Asciz	ev;
Asciz	Lscala/Predef$$less$colon$less;;
Asciz	mkString;
Asciz	(Ljava/lang/String;Ljava/lang/String;Ljava/lang/String;)Ljava/lang/String;;
Asciz	(Lscala/collection/TraversableLike;Ljava/lang/String;Ljava/lang/String;Ljava/lang/String;)Ljava/lang/String;;
NameAndType	mkString:(Lscala/collection/TraversableLike;Ljava/lang/String;Ljava/lang/String;Ljava/lang/String;)Ljava/lang/String;
Method	scala/collection/TraversableLike$class.mkString:(Lscala/collection/TraversableLike;Ljava/lang/String;Ljava/lang/String;Ljava/lang/String;)Ljava/lang/String;
Asciz	Ljava/lang/String;;
Asciz	sep;
Asciz	(Ljava/lang/String;)Ljava/lang/String;;
Asciz	(Lscala/collection/TraversableLike;Ljava/lang/String;)Ljava/lang/String;;
NameAndType	mkString:(Lscala/collection/TraversableLike;Ljava/lang/String;)Ljava/lang/String;
Method	scala/collection/TraversableLike$class.mkString:(Lscala/collection/TraversableLike;Ljava/lang/String;)Ljava/lang/String;
Asciz	(Lscala/collection/TraversableLike;)Ljava/lang/String;;
NameAndType	mkString:(Lscala/collection/TraversableLike;)Ljava/lang/String;
Method	scala/collection/TraversableLike$class.mkString:(Lscala/collection/TraversableLike;)Ljava/lang/String;
Asciz	addString;
Asciz	(Lscala/collection/mutable/StringBuilder;Ljava/lang/String;Ljava/lang/String;Ljava/lang/String;)Lscala/collection/mutable/StringBuilder;;
Asciz	(Lscala/collection/TraversableLike;Lscala/collection/mutable/StringBuilder;Ljava/lang/String;Ljava/lang/String;Ljava/lang/String;)Lscala/collection/mutable/StringBuilder;;
NameAndType	addString:(Lscala/collection/TraversableLike;Lscala/collection/mutable/StringBuilder;Ljava/lang/String;Ljava/lang/String;Ljava/lang/String;)Lscala/collection/mutable/StringBuilder;
Method	scala/collection/TraversableLike$class.addString:(Lscala/collection/TraversableLike;Lscala/collection/mutable/StringBuilder;Ljava/lang/String;Ljava/lang/String;Ljava/lang/String;)Lscala/collection/mutable/StringBuilder;
Asciz	Lscala/collection/mutable/StringBuilder;;
Asciz	(Lscala/collection/mutable/StringBuilder;Ljava/lang/String;)Lscala/collection/mutable/StringBuilder;;
Asciz	(Lscala/collection/TraversableLike;Lscala/collection/mutable/StringBuilder;Ljava/lang/String;)Lscala/collection/mutable/StringBuilder;;
NameAndType	addString:(Lscala/collection/TraversableLike;Lscala/collection/mutable/StringBuilder;Ljava/lang/String;)Lscala/collection/mutable/StringBuilder;
Method	scala/collection/TraversableLike$class.addString:(Lscala/collection/TraversableLike;Lscala/collection/mutable/StringBuilder;Ljava/lang/String;)Lscala/collection/mutable/StringBuilder;
Asciz	(Lscala/collection/mutable/StringBuilder;)Lscala/collection/mutable/StringBuilder;;
Asciz	(Lscala/collection/TraversableLike;Lscala/collection/mutable/StringBuilder;)Lscala/collection/mutable/StringBuilder;;
NameAndType	addString:(Lscala/collection/TraversableLike;Lscala/collection/mutable/StringBuilder;)Lscala/collection/mutable/StringBuilder;
Method	scala/collection/TraversableLike$class.addString:(Lscala/collection/TraversableLike;Lscala/collection/mutable/StringBuilder;)Lscala/collection/mutable/StringBuilder;
Asciz	stringPrefix;
NameAndType	stringPrefix:(Lscala/collection/TraversableLike;)Ljava/lang/String;
Method	scala/collection/TraversableLike$class.stringPrefix:(Lscala/collection/TraversableLike;)Ljava/lang/String;
Asciz	withFilter;
Asciz	(Lscala/Function1;)Lscala/collection/TraversableLike$WithFilter;;
Asciz	(Lscala/collection/TraversableLike;Lscala/Function1;)Lscala/collection/TraversableLike$WithFilter;;
NameAndType	withFilter:(Lscala/collection/TraversableLike;Lscala/Function1;)Lscala/collection/TraversableLike$WithFilter;
Method	scala/collection/TraversableLike$class.withFilter:(Lscala/collection/TraversableLike;Lscala/Function1;)Lscala/collection/TraversableLike$WithFilter;
Asciz	Signature;
Asciz	p_size0;
Asciz	scala/collection/mutable/ResizableArray;
class	scala/collection/mutable/ResizableArray
NameAndType	size0:()I
InterfaceMethod	scala/collection/mutable/ResizableArray.size0:()I
Asciz	p_size0_$eq;
NameAndType	size0_$eq:(I)V
InterfaceMethod	scala/collection/mutable/ResizableArray.size0_$eq:(I)V
Asciz	s;
Asciz	p_array;
NameAndType	array:()[Ljava/lang/Object;
InterfaceMethod	scala/collection/mutable/ResizableArray.array:()[Ljava/lang/Object;
Asciz	p_ensureSize;
Asciz	p_swap;
Asciz	scala/PartialFunction;
class	scala/PartialFunction
NameAndType	andThen:(Lscala/Function1;)Lscala/PartialFunction;
InterfaceMethod	scala/PartialFunction.andThen:(Lscala/Function1;)Lscala/PartialFunction;
Asciz	()Lscala/collection/IterableView;;
Asciz	scala/collection/SeqLike;
class	scala/collection/SeqLike
NameAndType	projection:()Lscala/collection/SeqView;
InterfaceMethod	scala/collection/SeqLike.projection:()Lscala/collection/SeqView;
Asciz	scala/runtime/BoxesRunTime;
class	scala/runtime/BoxesRunTime
Asciz	unboxToInt;
NameAndType	unboxToInt:(Ljava/lang/Object;)I
Method	scala/runtime/BoxesRunTime.unboxToInt:(Ljava/lang/Object;)I
NameAndType	isDefinedAt:(I)Z
InterfaceMethod	scala/collection/SeqLike.isDefinedAt:(I)Z
Asciz	x;
Asciz	(II)Lscala/collection/TraversableView;;
Asciz	scala/collection/mutable/IndexedSeqLike;
class	scala/collection/mutable/IndexedSeqLike
NameAndType	view:(II)Lscala/collection/mutable/IndexedSeqView;
InterfaceMethod	scala/collection/mutable/IndexedSeqLike.view:(II)Lscala/collection/mutable/IndexedSeqView;
Asciz	(II)Lscala/collection/IterableView;;
Asciz	(II)Lscala/collection/SeqView;;
Asciz	(II)Lscala/collection/IndexedSeqView;;
Asciz	()Lscala/collection/TraversableView;;
NameAndType	view:()Lscala/collection/mutable/IndexedSeqView;
InterfaceMethod	scala/collection/mutable/IndexedSeqLike.view:()Lscala/collection/mutable/IndexedSeqView;
Asciz	()Lscala/collection/IndexedSeqView;;
Asciz	(Ljava/lang/Object;)Lscala/collection/Traversable;;
NameAndType	toCollection:(Ljava/lang/Object;)Lscala/collection/mutable/IndexedSeq;
InterfaceMethod	scala/collection/mutable/IndexedSeqLike.toCollection:(Ljava/lang/Object;)Lscala/collection/mutable/IndexedSeq;
Asciz	(Ljava/lang/Object;)Lscala/collection/Iterable;;
Asciz	(Ljava/lang/Object;)Lscala/collection/Seq;;
Asciz	(Ljava/lang/Object;)Lscala/collection/IndexedSeq;;
Asciz	()Lscala/collection/Traversable;;
NameAndType	thisCollection:()Lscala/collection/mutable/IndexedSeq;
InterfaceMethod	scala/collection/mutable/IndexedSeqLike.thisCollection:()Lscala/collection/mutable/IndexedSeq;
Asciz	()Lscala/collection/IndexedSeq;;
Asciz	(Ljava/lang/Object;)Ljava/lang/Object;;
NameAndType	apply:(I)Ljava/lang/Object;
InterfaceMethod	scala/collection/mutable/ResizableArray.apply:(I)Ljava/lang/Object;
Asciz	v1;
Asciz	<init>;
Asciz	(Lscala/collection/mutable/PriorityQueue;)V;
Asciz	java/lang/Object;
class	java/lang/Object
Asciz	()V;
NameAndType	"<init>":()V
Method	java/lang/Object."<init>":()V
Asciz	$init$;
Asciz	(Lscala/collection/TraversableLike;)V;
NameAndType	$init$:(Lscala/collection/TraversableLike;)V
Method	scala/collection/TraversableLike$class.$init$:(Lscala/collection/TraversableLike;)V
Asciz	(Lscala/collection/generic/GenericTraversableTemplate;)V;
NameAndType	$init$:(Lscala/collection/generic/GenericTraversableTemplate;)V
Method	scala/collection/generic/GenericTraversableTemplate$class.$init$:(Lscala/collection/generic/GenericTraversableTemplate;)V
Asciz	scala/collection/Traversable$class;
class	scala/collection/Traversable$class
Asciz	(Lscala/collection/Traversable;)V;
NameAndType	$init$:(Lscala/collection/Traversable;)V
Method	scala/collection/Traversable$class.$init$:(Lscala/collection/Traversable;)V
Asciz	scala/collection/mutable/Traversable$class;
class	scala/collection/mutable/Traversable$class
Asciz	(Lscala/collection/mutable/Traversable;)V;
NameAndType	$init$:(Lscala/collection/mutable/Traversable;)V
Method	scala/collection/mutable/Traversable$class.$init$:(Lscala/collection/mutable/Traversable;)V
Asciz	(Lscala/collection/IterableLike;)V;
NameAndType	$init$:(Lscala/collection/IterableLike;)V
Method	scala/collection/IterableLike$class.$init$:(Lscala/collection/IterableLike;)V
Asciz	scala/collection/Iterable$class;
class	scala/collection/Iterable$class
Asciz	(Lscala/collection/Iterable;)V;
NameAndType	$init$:(Lscala/collection/Iterable;)V
Method	scala/collection/Iterable$class.$init$:(Lscala/collection/Iterable;)V
Asciz	scala/collection/mutable/Iterable$class;
class	scala/collection/mutable/Iterable$class
Asciz	(Lscala/collection/mutable/Iterable;)V;
NameAndType	$init$:(Lscala/collection/mutable/Iterable;)V
Method	scala/collection/mutable/Iterable$class.$init$:(Lscala/collection/mutable/Iterable;)V
NameAndType	$init$:(Lscala/Function1;)V
Method	scala/Function1$class.$init$:(Lscala/Function1;)V
Asciz	(Lscala/PartialFunction;)V;
NameAndType	$init$:(Lscala/PartialFunction;)V
Method	scala/PartialFunction$class.$init$:(Lscala/PartialFunction;)V
Asciz	(Lscala/collection/SeqLike;)V;
NameAndType	$init$:(Lscala/collection/SeqLike;)V
Method	scala/collection/SeqLike$class.$init$:(Lscala/collection/SeqLike;)V
Asciz	scala/collection/Seq$class;
class	scala/collection/Seq$class
Asciz	(Lscala/collection/Seq;)V;
NameAndType	$init$:(Lscala/collection/Seq;)V
Method	scala/collection/Seq$class.$init$:(Lscala/collection/Seq;)V
Asciz	scala/collection/mutable/Seq$class;
class	scala/collection/mutable/Seq$class
Asciz	(Lscala/collection/mutable/Seq;)V;
NameAndType	$init$:(Lscala/collection/mutable/Seq;)V
Method	scala/collection/mutable/Seq$class.$init$:(Lscala/collection/mutable/Seq;)V
Asciz	(Lscala/collection/IndexedSeqLike;)V;
NameAndType	$init$:(Lscala/collection/IndexedSeqLike;)V
Method	scala/collection/IndexedSeqLike$class.$init$:(Lscala/collection/IndexedSeqLike;)V
Asciz	scala/collection/IndexedSeq$class;
class	scala/collection/IndexedSeq$class
Asciz	(Lscala/collection/IndexedSeq;)V;
NameAndType	$init$:(Lscala/collection/IndexedSeq;)V
Method	scala/collection/IndexedSeq$class.$init$:(Lscala/collection/IndexedSeq;)V
Asciz	(Lscala/collection/mutable/IndexedSeqLike;)V;
NameAndType	$init$:(Lscala/collection/mutable/IndexedSeqLike;)V
Method	scala/collection/mutable/IndexedSeqLike$class.$init$:(Lscala/collection/mutable/IndexedSeqLike;)V
Asciz	scala/collection/mutable/IndexedSeq$class;
class	scala/collection/mutable/IndexedSeq$class
Asciz	(Lscala/collection/mutable/IndexedSeq;)V;
NameAndType	$init$:(Lscala/collection/mutable/IndexedSeq;)V
Method	scala/collection/mutable/IndexedSeq$class.$init$:(Lscala/collection/mutable/IndexedSeq;)V
Asciz	(Lscala/collection/mutable/ResizableArray;)V;
NameAndType	$init$:(Lscala/collection/mutable/ResizableArray;)V
Method	scala/collection/mutable/ResizableArray$class.$init$:(Lscala/collection/mutable/ResizableArray;)V
Asciz	$outer;
Asciz	Lscala/collection/mutable/PriorityQueue;;
Asciz	(Lscala/collection/mutable/PriorityQueue<TA;>;)V;
Asciz	<A:Ljava/lang/Object;>Ljava/lang/Object;Lscala/collection/mutable/ResizableArray<TA;>;Lscala/ScalaObject;;
Asciz	Scala;
Asciz	InnerClasses;
Asciz	scala/Predef$$less$colon$less;
class	scala/Predef$$less$colon$less
Asciz	scala/Predef;
class	scala/Predef
Asciz	$less$colon$less;
Asciz	scala/collection/TraversableLike$WithFilter;
class	scala/collection/TraversableLike$WithFilter
Asciz	scala/collection/TraversableLike;
class	scala/collection/TraversableLike
Asciz	WithFilter;
Asciz	scala/collection/mutable/PriorityQueue;
class	scala/collection/mutable/PriorityQueue
Asciz	ResizableArrayAccess;
Asciz	scala/ScalaObject;
class	scala/ScalaObject

{
private int size0;
  Signature: I

private java.lang.Object[] array;
  Signature: [Ljava/lang/Object;

public java.lang.Object[] array();
  Signature: ()[Ljava/lang/Object;
  Code:
   Stack=1, Locals=1, Args_size=1
	aload_0
	getfield	Field array:[Ljava/lang/Object;
	areturn
  Labels:

public void array_$eq(java.lang.Object[]);
  Signature: ([Ljava/lang/Object;)V
  Code:
   Stack=2, Locals=2, Args_size=2
	aload_0
	aload_1
	putfield	Field array:[Ljava/lang/Object;
	return
  Labels:

public int size0();
  Signature: ()I
  Code:
   Stack=1, Locals=1, Args_size=1
	aload_0
	getfield	Field size0:I
	ireturn
  Labels:

public void size0_$eq(int);
  Signature: (I)V
  Code:
   Stack=2, Locals=2, Args_size=2
	aload_0
	iload_1
	putfield	Field size0:I
	return
  Labels:

public scala.collection.generic.GenericCompanion companion();
  Signature: ()Lscala/collection/generic/GenericCompanion;
  Code:
   Stack=1, Locals=1, Args_size=1
	aload_0
	invokestatic	Method scala/collection/mutable/ResizableArray$class.companion:(Lscala/collection/mutable/ResizableArray;)Lscala/collection/generic/GenericCompanion;
	areturn
  Labels:

public int initialSize();
  Signature: ()I
  Code:
   Stack=1, Locals=1, Args_size=1
	aload_0
	invokestatic	Method scala/collection/mutable/ResizableArray$class.initialSize:(Lscala/collection/mutable/ResizableArray;)I
	ireturn
  Labels:

public int length();
  Signature: ()I
  Code:
   Stack=1, Locals=1, Args_size=1
	aload_0
	invokestatic	Method scala/collection/mutable/ResizableArray$class.length:(Lscala/collection/mutable/ResizableArray;)I
	ireturn
  Labels:

public java.lang.Object apply(int);
  Signature: (I)Ljava/lang/Object;
  Code:
   Stack=2, Locals=2, Args_size=2
	aload_0
	iload_1
	invokestatic	Method scala/collection/mutable/ResizableArray$class.apply:(Lscala/collection/mutable/ResizableArray;I)Ljava/lang/Object;
	areturn
  Labels:
  LocalVariableTable: 
   Start  Length  Slot  Name   Signature
   0      6      0    this       Lscala/collection/mutable/PriorityQueue$ResizableArrayAccess;
   0      6      1    idx       I


public void update(int, java.lang.Object);
  Signature: (ILjava/lang/Object;)V
  Code:
   Stack=3, Locals=3, Args_size=3
	aload_0
	iload_1
	aload_2
	invokestatic	Method scala/collection/mutable/ResizableArray$class.update:(Lscala/collection/mutable/ResizableArray;ILjava/lang/Object;)V
	return
  Labels:
  LocalVariableTable: 
   Start  Length  Slot  Name   Signature
   0      7      0    this       Lscala/collection/mutable/PriorityQueue$ResizableArrayAccess;
   0      7      1    idx       I
   0      7      2    elem       Ljava/lang/Object;


public void foreach(scala.Function1);
  Signature: (Lscala/Function1;)V
  Code:
   Stack=2, Locals=2, Args_size=2
	aload_0
	aload_1
	invokestatic	Method scala/collection/mutable/ResizableArray$class.foreach:(Lscala/collection/mutable/ResizableArray;Lscala/Function1;)V
	return
  Labels:
  LocalVariableTable: 
   Start  Length  Slot  Name   Signature
   0      6      0    this       Lscala/collection/mutable/PriorityQueue$ResizableArrayAccess;
   0      6      1    f       Lscala/Function1;


public void copyToArray(java.lang.Object, int, int);
  Signature: (Ljava/lang/Object;II)V
  Code:
   Stack=4, Locals=4, Args_size=4
	aload_0
	aload_1
	iload_2
	iload_3
	invokestatic	Method scala/collection/mutable/ResizableArray$class.copyToArray:(Lscala/collection/mutable/ResizableArray;Ljava/lang/Object;II)V
	return
  Labels:
  LocalVariableTable: 
   Start  Length  Slot  Name   Signature
   0      8      0    this       Lscala/collection/mutable/PriorityQueue$ResizableArrayAccess;
   0      8      1    xs       Ljava/lang/Object;
   0      8      2    start       I
   0      8      3    len       I


public void reduceToSize(int);
  Signature: (I)V
  Code:
   Stack=2, Locals=2, Args_size=2
	aload_0
	iload_1
	invokestatic	Method scala/collection/mutable/ResizableArray$class.reduceToSize:(Lscala/collection/mutable/ResizableArray;I)V
	return
  Labels:
  LocalVariableTable: 
   Start  Length  Slot  Name   Signature
   0      6      0    this       Lscala/collection/mutable/PriorityQueue$ResizableArrayAccess;
   0      6      1    sz       I


public void ensureSize(int);
  Signature: (I)V
  Code:
   Stack=2, Locals=2, Args_size=2
	aload_0
	iload_1
	invokestatic	Method scala/collection/mutable/ResizableArray$class.ensureSize:(Lscala/collection/mutable/ResizableArray;I)V
	return
  Labels:
  LocalVariableTable: 
   Start  Length  Slot  Name   Signature
   0      6      0    this       Lscala/collection/mutable/PriorityQueue$ResizableArrayAccess;
   0      6      1    n       I


public void swap(int, int);
  Signature: (II)V
  Code:
   Stack=3, Locals=3, Args_size=3
	aload_0
	iload_1
	iload_2
	invokestatic	Method scala/collection/mutable/ResizableArray$class.swap:(Lscala/collection/mutable/ResizableArray;II)V
	return
  Labels:
  LocalVariableTable: 
   Start  Length  Slot  Name   Signature
   0      7      0    this       Lscala/collection/mutable/PriorityQueue$ResizableArrayAccess;
   0      7      1    a       I
   0      7      2    b       I


public void copy(int, int, int);
  Signature: (III)V
  Code:
   Stack=4, Locals=4, Args_size=4
	aload_0
	iload_1
	iload_2
	iload_3
	invokestatic	Method scala/collection/mutable/ResizableArray$class.copy:(Lscala/collection/mutable/ResizableArray;III)V
	return
  Labels:
  LocalVariableTable: 
   Start  Length  Slot  Name   Signature
   0      8      0    this       Lscala/collection/mutable/PriorityQueue$ResizableArrayAccess;
   0      8      1    m       I
   0      8      2    n       I
   0      8      3    len       I


public scala.collection.mutable.IndexedSeq thisCollection();
  Signature: ()Lscala/collection/mutable/IndexedSeq;
  Code:
   Stack=1, Locals=1, Args_size=1
	aload_0
	invokestatic	Method scala/collection/mutable/IndexedSeqLike$class.thisCollection:(Lscala/collection/mutable/IndexedSeqLike;)Lscala/collection/mutable/IndexedSeq;
	areturn
  Labels:

public scala.collection.mutable.IndexedSeq toCollection(java.lang.Object);
  Signature: (Ljava/lang/Object;)Lscala/collection/mutable/IndexedSeq;
  Code:
   Stack=2, Locals=2, Args_size=2
	aload_0
	aload_1
	invokestatic	Method scala/collection/mutable/IndexedSeqLike$class.toCollection:(Lscala/collection/mutable/IndexedSeqLike;Ljava/lang/Object;)Lscala/collection/mutable/IndexedSeq;
	areturn
  Labels:
  LocalVariableTable: 
   Start  Length  Slot  Name   Signature
   0      6      0    this       Lscala/collection/mutable/PriorityQueue$ResizableArrayAccess;
   0      6      1    repr       Ljava/lang/Object;


public scala.collection.mutable.IndexedSeqView view();
  Signature: ()Lscala/collection/mutable/IndexedSeqView;
  Code:
   Stack=1, Locals=1, Args_size=1
	aload_0
	invokestatic	Method scala/collection/mutable/IndexedSeqLike$class.view:(Lscala/collection/mutable/IndexedSeqLike;)Lscala/collection/mutable/IndexedSeqView;
	areturn
  Labels:

public scala.collection.mutable.IndexedSeqView view(int, int);
  Signature: (II)Lscala/collection/mutable/IndexedSeqView;
  Code:
   Stack=3, Locals=3, Args_size=3
	aload_0
	iload_1
	iload_2
	invokestatic	Method scala/collection/mutable/IndexedSeqLike$class.view:(Lscala/collection/mutable/IndexedSeqLike;II)Lscala/collection/mutable/IndexedSeqView;
	areturn
  Labels:
  LocalVariableTable: 
   Start  Length  Slot  Name   Signature
   0      7      0    this       Lscala/collection/mutable/PriorityQueue$ResizableArrayAccess;
   0      7      1    from       I
   0      7      2    until       I


public final java.lang.Object scala$collection$IndexedSeqLike$$super$reduceLeft(scala.Function2);
  Signature: (Lscala/Function2;)Ljava/lang/Object;
  Code:
   Stack=2, Locals=2, Args_size=2
	aload_0
	aload_1
	invokestatic	Method scala/collection/TraversableLike$class.reduceLeft:(Lscala/collection/TraversableLike;Lscala/Function2;)Ljava/lang/Object;
	areturn
  Labels:
  LocalVariableTable: 
   Start  Length  Slot  Name   Signature
   0      6      0    this       Lscala/collection/mutable/PriorityQueue$ResizableArrayAccess;
   0      6      1    op       Lscala/Function2;


public final java.lang.Object scala$collection$IndexedSeqLike$$super$reduceRight(scala.Function2);
  Signature: (Lscala/Function2;)Ljava/lang/Object;
  Code:
   Stack=2, Locals=2, Args_size=2
	aload_0
	aload_1
	invokestatic	Method scala/collection/IterableLike$class.reduceRight:(Lscala/collection/IterableLike;Lscala/Function2;)Ljava/lang/Object;
	areturn
  Labels:
  LocalVariableTable: 
   Start  Length  Slot  Name   Signature
   0      6      0    this       Lscala/collection/mutable/PriorityQueue$ResizableArrayAccess;
   0      6      1    op       Lscala/Function2;


public final java.lang.Object scala$collection$IndexedSeqLike$$super$zip(scala.collection.Iterable, scala.collection.generic.CanBuildFrom);
  Signature: (Lscala/collection/Iterable;Lscala/collection/generic/CanBuildFrom;)Ljava/lang/Object;
  Code:
   Stack=3, Locals=3, Args_size=3
	aload_0
	aload_1
	aload_2
	invokestatic	Method scala/collection/IterableLike$class.zip:(Lscala/collection/IterableLike;Lscala/collection/Iterable;Lscala/collection/generic/CanBuildFrom;)Ljava/lang/Object;
	areturn
  Labels:
  LocalVariableTable: 
   Start  Length  Slot  Name   Signature
   0      7      0    this       Lscala/collection/mutable/PriorityQueue$ResizableArrayAccess;
   0      7      1    that       Lscala/collection/Iterable;
   0      7      2    bf       Lscala/collection/generic/CanBuildFrom;


public final java.lang.Object scala$collection$IndexedSeqLike$$super$head();
  Signature: ()Ljava/lang/Object;
  Code:
   Stack=1, Locals=1, Args_size=1
	aload_0
	invokestatic	Method scala/collection/IterableLike$class.head:(Lscala/collection/IterableLike;)Ljava/lang/Object;
	areturn
  Labels:

public final java.lang.Object scala$collection$IndexedSeqLike$$super$tail();
  Signature: ()Ljava/lang/Object;
  Code:
   Stack=1, Locals=1, Args_size=1
	aload_0
	invokestatic	Method scala/collection/TraversableLike$class.tail:(Lscala/collection/TraversableLike;)Ljava/lang/Object;
	areturn
  Labels:

public final java.lang.Object scala$collection$IndexedSeqLike$$super$last();
  Signature: ()Ljava/lang/Object;
  Code:
   Stack=1, Locals=1, Args_size=1
	aload_0
	invokestatic	Method scala/collection/TraversableLike$class.last:(Lscala/collection/TraversableLike;)Ljava/lang/Object;
	areturn
  Labels:

public final java.lang.Object scala$collection$IndexedSeqLike$$super$init();
  Signature: ()Ljava/lang/Object;
  Code:
   Stack=1, Locals=1, Args_size=1
	aload_0
	invokestatic	Method scala/collection/TraversableLike$class.init:(Lscala/collection/TraversableLike;)Ljava/lang/Object;
	areturn
  Labels:

public final boolean scala$collection$IndexedSeqLike$$super$sameElements(scala.collection.Iterable);
  Signature: (Lscala/collection/Iterable;)Z
  Code:
   Stack=2, Locals=2, Args_size=2
	aload_0
	aload_1
	invokestatic	Method scala/collection/IterableLike$class.sameElements:(Lscala/collection/IterableLike;Lscala/collection/Iterable;)Z
	ireturn
  Labels:
  LocalVariableTable: 
   Start  Length  Slot  Name   Signature
   0      6      0    this       Lscala/collection/mutable/PriorityQueue$ResizableArrayAccess;
   0      6      1    that       Lscala/collection/Iterable;


public final boolean scala$collection$IndexedSeqLike$$super$endsWith(scala.collection.Seq);
  Signature: (Lscala/collection/Seq;)Z
  Code:
   Stack=2, Locals=2, Args_size=2
	aload_0
	aload_1
	invokestatic	Method scala/collection/SeqLike$class.endsWith:(Lscala/collection/SeqLike;Lscala/collection/Seq;)Z
	ireturn
  Labels:
  LocalVariableTable: 
   Start  Length  Slot  Name   Signature
   0      6      0    this       Lscala/collection/mutable/PriorityQueue$ResizableArrayAccess;
   0      6      1    that       Lscala/collection/Seq;


public scala.collection.Iterator iterator();
  Signature: ()Lscala/collection/Iterator;
  Code:
   Stack=1, Locals=1, Args_size=1
	aload_0
	invokestatic	Method scala/collection/IndexedSeqLike$class.iterator:(Lscala/collection/IndexedSeqLike;)Lscala/collection/Iterator;
	areturn
  Labels:

public boolean isEmpty();
  Signature: ()Z
  Code:
   Stack=1, Locals=1, Args_size=1
	aload_0
	invokestatic	Method scala/collection/IndexedSeqLike$class.isEmpty:(Lscala/collection/IndexedSeqLike;)Z
	ireturn
  Labels:

public boolean forall(scala.Function1);
  Signature: (Lscala/Function1;)Z
  Code:
   Stack=2, Locals=2, Args_size=2
	aload_0
	aload_1
	invokestatic	Method scala/collection/IndexedSeqLike$class.forall:(Lscala/collection/IndexedSeqLike;Lscala/Function1;)Z
	ireturn
  Labels:
  LocalVariableTable: 
   Start  Length  Slot  Name   Signature
   0      6      0    this       Lscala/collection/mutable/PriorityQueue$ResizableArrayAccess;
   0      6      1    p       Lscala/Function1;


public boolean exists(scala.Function1);
  Signature: (Lscala/Function1;)Z
  Code:
   Stack=2, Locals=2, Args_size=2
	aload_0
	aload_1
	invokestatic	Method scala/collection/IndexedSeqLike$class.exists:(Lscala/collection/IndexedSeqLike;Lscala/Function1;)Z
	ireturn
  Labels:
  LocalVariableTable: 
   Start  Length  Slot  Name   Signature
   0      6      0    this       Lscala/collection/mutable/PriorityQueue$ResizableArrayAccess;
   0      6      1    p       Lscala/Function1;


public scala.Option find(scala.Function1);
  Signature: (Lscala/Function1;)Lscala/Option;
  Code:
   Stack=2, Locals=2, Args_size=2
	aload_0
	aload_1
	invokestatic	Method scala/collection/IndexedSeqLike$class.find:(Lscala/collection/IndexedSeqLike;Lscala/Function1;)Lscala/Option;
	areturn
  Labels:
  LocalVariableTable: 
   Start  Length  Slot  Name   Signature
   0      6      0    this       Lscala/collection/mutable/PriorityQueue$ResizableArrayAccess;
   0      6      1    p       Lscala/Function1;


public java.lang.Object foldLeft(java.lang.Object, scala.Function2);
  Signature: (Ljava/lang/Object;Lscala/Function2;)Ljava/lang/Object;
  Code:
   Stack=3, Locals=3, Args_size=3
	aload_0
	aload_1
	aload_2
	invokestatic	Method scala/collection/IndexedSeqLike$class.foldLeft:(Lscala/collection/IndexedSeqLike;Ljava/lang/Object;Lscala/Function2;)Ljava/lang/Object;
	areturn
  Labels:
  LocalVariableTable: 
   Start  Length  Slot  Name   Signature
   0      7      0    this       Lscala/collection/mutable/PriorityQueue$ResizableArrayAccess;
   0      7      1    z       Ljava/lang/Object;
   0      7      2    op       Lscala/Function2;


public java.lang.Object foldRight(java.lang.Object, scala.Function2);
  Signature: (Ljava/lang/Object;Lscala/Function2;)Ljava/lang/Object;
  Code:
   Stack=3, Locals=3, Args_size=3
	aload_0
	aload_1
	aload_2
	invokestatic	Method scala/collection/IndexedSeqLike$class.foldRight:(Lscala/collection/IndexedSeqLike;Ljava/lang/Object;Lscala/Function2;)Ljava/lang/Object;
	areturn
  Labels:
  LocalVariableTable: 
   Start  Length  Slot  Name   Signature
   0      7      0    this       Lscala/collection/mutable/PriorityQueue$ResizableArrayAccess;
   0      7      1    z       Ljava/lang/Object;
   0      7      2    op       Lscala/Function2;


public java.lang.Object reduceLeft(scala.Function2);
  Signature: (Lscala/Function2;)Ljava/lang/Object;
  Code:
   Stack=2, Locals=2, Args_size=2
	aload_0
	aload_1
	invokestatic	Method scala/collection/IndexedSeqLike$class.reduceLeft:(Lscala/collection/IndexedSeqLike;Lscala/Function2;)Ljava/lang/Object;
	areturn
  Labels:
  LocalVariableTable: 
   Start  Length  Slot  Name   Signature
   0      6      0    this       Lscala/collection/mutable/PriorityQueue$ResizableArrayAccess;
   0      6      1    op       Lscala/Function2;


public java.lang.Object reduceRight(scala.Function2);
  Signature: (Lscala/Function2;)Ljava/lang/Object;
  Code:
   Stack=2, Locals=2, Args_size=2
	aload_0
	aload_1
	invokestatic	Method scala/collection/IndexedSeqLike$class.reduceRight:(Lscala/collection/IndexedSeqLike;Lscala/Function2;)Ljava/lang/Object;
	areturn
  Labels:
  LocalVariableTable: 
   Start  Length  Slot  Name   Signature
   0      6      0    this       Lscala/collection/mutable/PriorityQueue$ResizableArrayAccess;
   0      6      1    op       Lscala/Function2;


public java.lang.Object zip(scala.collection.Iterable, scala.collection.generic.CanBuildFrom);
  Signature: (Lscala/collection/Iterable;Lscala/collection/generic/CanBuildFrom;)Ljava/lang/Object;
  Code:
   Stack=3, Locals=3, Args_size=3
	aload_0
	aload_1
	aload_2
	invokestatic	Method scala/collection/IndexedSeqLike$class.zip:(Lscala/collection/IndexedSeqLike;Lscala/collection/Iterable;Lscala/collection/generic/CanBuildFrom;)Ljava/lang/Object;
	areturn
  Labels:
  LocalVariableTable: 
   Start  Length  Slot  Name   Signature
   0      7      0    this       Lscala/collection/mutable/PriorityQueue$ResizableArrayAccess;
   0      7      1    that       Lscala/collection/Iterable;
   0      7      2    bf       Lscala/collection/generic/CanBuildFrom;


public java.lang.Object zipWithIndex(scala.collection.generic.CanBuildFrom);
  Signature: (Lscala/collection/generic/CanBuildFrom;)Ljava/lang/Object;
  Code:
   Stack=2, Locals=2, Args_size=2
	aload_0
	aload_1
	invokestatic	Method scala/collection/IndexedSeqLike$class.zipWithIndex:(Lscala/collection/IndexedSeqLike;Lscala/collection/generic/CanBuildFrom;)Ljava/lang/Object;
	areturn
  Labels:
  LocalVariableTable: 
   Start  Length  Slot  Name   Signature
   0      6      0    this       Lscala/collection/mutable/PriorityQueue$ResizableArrayAccess;
   0      6      1    bf       Lscala/collection/generic/CanBuildFrom;


public java.lang.Object slice(int, int);
  Signature: (II)Ljava/lang/Object;
  Code:
   Stack=3, Locals=3, Args_size=3
	aload_0
	iload_1
	iload_2
	invokestatic	Method scala/collection/IndexedSeqLike$class.slice:(Lscala/collection/IndexedSeqLike;II)Ljava/lang/Object;
	areturn
  Labels:
  LocalVariableTable: 
   Start  Length  Slot  Name   Signature
   0      7      0    this       Lscala/collection/mutable/PriorityQueue$ResizableArrayAccess;
   0      7      1    from       I
   0      7      2    until       I


public java.lang.Object head();
  Signature: ()Ljava/lang/Object;
  Code:
   Stack=1, Locals=1, Args_size=1
	aload_0
	invokestatic	Method scala/collection/IndexedSeqLike$class.head:(Lscala/collection/IndexedSeqLike;)Ljava/lang/Object;
	areturn
  Labels:

public java.lang.Object tail();
  Signature: ()Ljava/lang/Object;
  Code:
   Stack=1, Locals=1, Args_size=1
	aload_0
	invokestatic	Method scala/collection/IndexedSeqLike$class.tail:(Lscala/collection/IndexedSeqLike;)Ljava/lang/Object;
	areturn
  Labels:

public java.lang.Object last();
  Signature: ()Ljava/lang/Object;
  Code:
   Stack=1, Locals=1, Args_size=1
	aload_0
	invokestatic	Method scala/collection/IndexedSeqLike$class.last:(Lscala/collection/IndexedSeqLike;)Ljava/lang/Object;
	areturn
  Labels:

public java.lang.Object init();
  Signature: ()Ljava/lang/Object;
  Code:
   Stack=1, Locals=1, Args_size=1
	aload_0
	invokestatic	Method scala/collection/IndexedSeqLike$class.init:(Lscala/collection/IndexedSeqLike;)Ljava/lang/Object;
	areturn
  Labels:

public java.lang.Object take(int);
  Signature: (I)Ljava/lang/Object;
  Code:
   Stack=2, Locals=2, Args_size=2
	aload_0
	iload_1
	invokestatic	Method scala/collection/IndexedSeqLike$class.take:(Lscala/collection/IndexedSeqLike;I)Ljava/lang/Object;
	areturn
  Labels:
  LocalVariableTable: 
   Start  Length  Slot  Name   Signature
   0      6      0    this       Lscala/collection/mutable/PriorityQueue$ResizableArrayAccess;
   0      6      1    n       I


public java.lang.Object drop(int);
  Signature: (I)Ljava/lang/Object;
  Code:
   Stack=2, Locals=2, Args_size=2
	aload_0
	iload_1
	invokestatic	Method scala/collection/IndexedSeqLike$class.drop:(Lscala/collection/IndexedSeqLike;I)Ljava/lang/Object;
	areturn
  Labels:
  LocalVariableTable: 
   Start  Length  Slot  Name   Signature
   0      6      0    this       Lscala/collection/mutable/PriorityQueue$ResizableArrayAccess;
   0      6      1    n       I


public java.lang.Object takeRight(int);
  Signature: (I)Ljava/lang/Object;
  Code:
   Stack=2, Locals=2, Args_size=2
	aload_0
	iload_1
	invokestatic	Method scala/collection/IndexedSeqLike$class.takeRight:(Lscala/collection/IndexedSeqLike;I)Ljava/lang/Object;
	areturn
  Labels:
  LocalVariableTable: 
   Start  Length  Slot  Name   Signature
   0      6      0    this       Lscala/collection/mutable/PriorityQueue$ResizableArrayAccess;
   0      6      1    n       I


public java.lang.Object dropRight(int);
  Signature: (I)Ljava/lang/Object;
  Code:
   Stack=2, Locals=2, Args_size=2
	aload_0
	iload_1
	invokestatic	Method scala/collection/IndexedSeqLike$class.dropRight:(Lscala/collection/IndexedSeqLike;I)Ljava/lang/Object;
	areturn
  Labels:
  LocalVariableTable: 
   Start  Length  Slot  Name   Signature
   0      6      0    this       Lscala/collection/mutable/PriorityQueue$ResizableArrayAccess;
   0      6      1    n       I


public scala.Tuple2 splitAt(int);
  Signature: (I)Lscala/Tuple2;
  Code:
   Stack=2, Locals=2, Args_size=2
	aload_0
	iload_1
	invokestatic	Method scala/collection/IndexedSeqLike$class.splitAt:(Lscala/collection/IndexedSeqLike;I)Lscala/Tuple2;
	areturn
  Labels:
  LocalVariableTable: 
   Start  Length  Slot  Name   Signature
   0      6      0    this       Lscala/collection/mutable/PriorityQueue$ResizableArrayAccess;
   0      6      1    n       I


public java.lang.Object takeWhile(scala.Function1);
  Signature: (Lscala/Function1;)Ljava/lang/Object;
  Code:
   Stack=2, Locals=2, Args_size=2
	aload_0
	aload_1
	invokestatic	Method scala/collection/IndexedSeqLike$class.takeWhile:(Lscala/collection/IndexedSeqLike;Lscala/Function1;)Ljava/lang/Object;
	areturn
  Labels:
  LocalVariableTable: 
   Start  Length  Slot  Name   Signature
   0      6      0    this       Lscala/collection/mutable/PriorityQueue$ResizableArrayAccess;
   0      6      1    p       Lscala/Function1;


public java.lang.Object dropWhile(scala.Function1);
  Signature: (Lscala/Function1;)Ljava/lang/Object;
  Code:
   Stack=2, Locals=2, Args_size=2
	aload_0
	aload_1
	invokestatic	Method scala/collection/IndexedSeqLike$class.dropWhile:(Lscala/collection/IndexedSeqLike;Lscala/Function1;)Ljava/lang/Object;
	areturn
  Labels:
  LocalVariableTable: 
   Start  Length  Slot  Name   Signature
   0      6      0    this       Lscala/collection/mutable/PriorityQueue$ResizableArrayAccess;
   0      6      1    p       Lscala/Function1;


public scala.Tuple2 span(scala.Function1);
  Signature: (Lscala/Function1;)Lscala/Tuple2;
  Code:
   Stack=2, Locals=2, Args_size=2
	aload_0
	aload_1
	invokestatic	Method scala/collection/IndexedSeqLike$class.span:(Lscala/collection/IndexedSeqLike;Lscala/Function1;)Lscala/Tuple2;
	areturn
  Labels:
  LocalVariableTable: 
   Start  Length  Slot  Name   Signature
   0      6      0    this       Lscala/collection/mutable/PriorityQueue$ResizableArrayAccess;
   0      6      1    p       Lscala/Function1;


public boolean sameElements(scala.collection.Iterable);
  Signature: (Lscala/collection/Iterable;)Z
  Code:
   Stack=2, Locals=2, Args_size=2
	aload_0
	aload_1
	invokestatic	Method scala/collection/IndexedSeqLike$class.sameElements:(Lscala/collection/IndexedSeqLike;Lscala/collection/Iterable;)Z
	ireturn
  Labels:
  LocalVariableTable: 
   Start  Length  Slot  Name   Signature
   0      6      0    this       Lscala/collection/mutable/PriorityQueue$ResizableArrayAccess;
   0      6      1    that       Lscala/collection/Iterable;


public int lengthCompare(int);
  Signature: (I)I
  Code:
   Stack=2, Locals=2, Args_size=2
	aload_0
	iload_1
	invokestatic	Method scala/collection/IndexedSeqLike$class.lengthCompare:(Lscala/collection/IndexedSeqLike;I)I
	ireturn
  Labels:
  LocalVariableTable: 
   Start  Length  Slot  Name   Signature
   0      6      0    this       Lscala/collection/mutable/PriorityQueue$ResizableArrayAccess;
   0      6      1    len       I


public int segmentLength(scala.Function1, int);
  Signature: (Lscala/Function1;I)I
  Code:
   Stack=3, Locals=3, Args_size=3
	aload_0
	aload_1
	iload_2
	invokestatic	Method scala/collection/IndexedSeqLike$class.segmentLength:(Lscala/collection/IndexedSeqLike;Lscala/Function1;I)I
	ireturn
  Labels:
  LocalVariableTable: 
   Start  Length  Slot  Name   Signature
   0      7      0    this       Lscala/collection/mutable/PriorityQueue$ResizableArrayAccess;
   0      7      1    p       Lscala/Function1;
   0      7      2    from       I


public int indexWhere(scala.Function1, int);
  Signature: (Lscala/Function1;I)I
  Code:
   Stack=3, Locals=3, Args_size=3
	aload_0
	aload_1
	iload_2
	invokestatic	Method scala/collection/IndexedSeqLike$class.indexWhere:(Lscala/collection/IndexedSeqLike;Lscala/Function1;I)I
	ireturn
  Labels:
  LocalVariableTable: 
   Start  Length  Slot  Name   Signature
   0      7      0    this       Lscala/collection/mutable/PriorityQueue$ResizableArrayAccess;
   0      7      1    p       Lscala/Function1;
   0      7      2    from       I


public int lastIndexWhere(scala.Function1, int);
  Signature: (Lscala/Function1;I)I
  Code:
   Stack=3, Locals=3, Args_size=3
	aload_0
	aload_1
	iload_2
	invokestatic	Method scala/collection/IndexedSeqLike$class.lastIndexWhere:(Lscala/collection/IndexedSeqLike;Lscala/Function1;I)I
	ireturn
  Labels:
  LocalVariableTable: 
   Start  Length  Slot  Name   Signature
   0      7      0    this       Lscala/collection/mutable/PriorityQueue$ResizableArrayAccess;
   0      7      1    p       Lscala/Function1;
   0      7      2    end       I


public java.lang.Object reverse();
  Signature: ()Ljava/lang/Object;
  Code:
   Stack=1, Locals=1, Args_size=1
	aload_0
	invokestatic	Method scala/collection/IndexedSeqLike$class.reverse:(Lscala/collection/IndexedSeqLike;)Ljava/lang/Object;
	areturn
  Labels:

public scala.collection.Iterator reverseIterator();
  Signature: ()Lscala/collection/Iterator;
  Code:
   Stack=1, Locals=1, Args_size=1
	aload_0
	invokestatic	Method scala/collection/IndexedSeqLike$class.reverseIterator:(Lscala/collection/IndexedSeqLike;)Lscala/collection/Iterator;
	areturn
  Labels:

public boolean startsWith(scala.collection.Seq, int);
  Signature: (Lscala/collection/Seq;I)Z
  Code:
   Stack=3, Locals=3, Args_size=3
	aload_0
	aload_1
	iload_2
	invokestatic	Method scala/collection/IndexedSeqLike$class.startsWith:(Lscala/collection/IndexedSeqLike;Lscala/collection/Seq;I)Z
	ireturn
  Labels:
  LocalVariableTable: 
   Start  Length  Slot  Name   Signature
   0      7      0    this       Lscala/collection/mutable/PriorityQueue$ResizableArrayAccess;
   0      7      1    that       Lscala/collection/Seq;
   0      7      2    offset       I


public boolean endsWith(scala.collection.Seq);
  Signature: (Lscala/collection/Seq;)Z
  Code:
   Stack=2, Locals=2, Args_size=2
	aload_0
	aload_1
	invokestatic	Method scala/collection/IndexedSeqLike$class.endsWith:(Lscala/collection/IndexedSeqLike;Lscala/collection/Seq;)Z
	ireturn
  Labels:
  LocalVariableTable: 
   Start  Length  Slot  Name   Signature
   0      6      0    this       Lscala/collection/mutable/PriorityQueue$ResizableArrayAccess;
   0      6      1    that       Lscala/collection/Seq;


public int size();
  Signature: ()I
  Code:
   Stack=1, Locals=1, Args_size=1
	aload_0
	invokestatic	Method scala/collection/SeqLike$class.size:(Lscala/collection/SeqLike;)I
	ireturn
  Labels:

public boolean isDefinedAt(int);
  Signature: (I)Z
  Code:
   Stack=2, Locals=2, Args_size=2
	aload_0
	iload_1
	invokestatic	Method scala/collection/SeqLike$class.isDefinedAt:(Lscala/collection/SeqLike;I)Z
	ireturn
  Labels:
  LocalVariableTable: 
   Start  Length  Slot  Name   Signature
   0      6      0    this       Lscala/collection/mutable/PriorityQueue$ResizableArrayAccess;
   0      6      1    idx       I


public int prefixLength(scala.Function1);
  Signature: (Lscala/Function1;)I
  Code:
   Stack=2, Locals=2, Args_size=2
	aload_0
	aload_1
	invokestatic	Method scala/collection/SeqLike$class.prefixLength:(Lscala/collection/SeqLike;Lscala/Function1;)I
	ireturn
  Labels:
  LocalVariableTable: 
   Start  Length  Slot  Name   Signature
   0      6      0    this       Lscala/collection/mutable/PriorityQueue$ResizableArrayAccess;
   0      6      1    p       Lscala/Function1;


public int indexWhere(scala.Function1);
  Signature: (Lscala/Function1;)I
  Code:
   Stack=2, Locals=2, Args_size=2
	aload_0
	aload_1
	invokestatic	Method scala/collection/SeqLike$class.indexWhere:(Lscala/collection/SeqLike;Lscala/Function1;)I
	ireturn
  Labels:
  LocalVariableTable: 
   Start  Length  Slot  Name   Signature
   0      6      0    this       Lscala/collection/mutable/PriorityQueue$ResizableArrayAccess;
   0      6      1    p       Lscala/Function1;


public int findIndexOf(scala.Function1);
  Signature: (Lscala/Function1;)I
  Code:
   Stack=2, Locals=2, Args_size=2
	aload_0
	aload_1
	invokestatic	Method scala/collection/SeqLike$class.findIndexOf:(Lscala/collection/SeqLike;Lscala/Function1;)I
	ireturn
  Labels:
  LocalVariableTable: 
   Start  Length  Slot  Name   Signature
   0      6      0    this       Lscala/collection/mutable/PriorityQueue$ResizableArrayAccess;
   0      6      1    p       Lscala/Function1;


public int indexOf(java.lang.Object);
  Signature: (Ljava/lang/Object;)I
  Code:
   Stack=2, Locals=2, Args_size=2
	aload_0
	aload_1
	invokestatic	Method scala/collection/SeqLike$class.indexOf:(Lscala/collection/SeqLike;Ljava/lang/Object;)I
	ireturn
  Labels:
  LocalVariableTable: 
   Start  Length  Slot  Name   Signature
   0      6      0    this       Lscala/collection/mutable/PriorityQueue$ResizableArrayAccess;
   0      6      1    elem       Ljava/lang/Object;


public int indexOf(java.lang.Object, int);
  Signature: (Ljava/lang/Object;I)I
  Code:
   Stack=3, Locals=3, Args_size=3
	aload_0
	aload_1
	iload_2
	invokestatic	Method scala/collection/SeqLike$class.indexOf:(Lscala/collection/SeqLike;Ljava/lang/Object;I)I
	ireturn
  Labels:
  LocalVariableTable: 
   Start  Length  Slot  Name   Signature
   0      7      0    this       Lscala/collection/mutable/PriorityQueue$ResizableArrayAccess;
   0      7      1    elem       Ljava/lang/Object;
   0      7      2    from       I


public int lastIndexOf(java.lang.Object);
  Signature: (Ljava/lang/Object;)I
  Code:
   Stack=2, Locals=2, Args_size=2
	aload_0
	aload_1
	invokestatic	Method scala/collection/SeqLike$class.lastIndexOf:(Lscala/collection/SeqLike;Ljava/lang/Object;)I
	ireturn
  Labels:
  LocalVariableTable: 
   Start  Length  Slot  Name   Signature
   0      6      0    this       Lscala/collection/mutable/PriorityQueue$ResizableArrayAccess;
   0      6      1    elem       Ljava/lang/Object;


public int lastIndexOf(java.lang.Object, int);
  Signature: (Ljava/lang/Object;I)I
  Code:
   Stack=3, Locals=3, Args_size=3
	aload_0
	aload_1
	iload_2
	invokestatic	Method scala/collection/SeqLike$class.lastIndexOf:(Lscala/collection/SeqLike;Ljava/lang/Object;I)I
	ireturn
  Labels:
  LocalVariableTable: 
   Start  Length  Slot  Name   Signature
   0      7      0    this       Lscala/collection/mutable/PriorityQueue$ResizableArrayAccess;
   0      7      1    elem       Ljava/lang/Object;
   0      7      2    end       I


public int lastIndexWhere(scala.Function1);
  Signature: (Lscala/Function1;)I
  Code:
   Stack=2, Locals=2, Args_size=2
	aload_0
	aload_1
	invokestatic	Method scala/collection/SeqLike$class.lastIndexWhere:(Lscala/collection/SeqLike;Lscala/Function1;)I
	ireturn
  Labels:
  LocalVariableTable: 
   Start  Length  Slot  Name   Signature
   0      6      0    this       Lscala/collection/mutable/PriorityQueue$ResizableArrayAccess;
   0      6      1    p       Lscala/Function1;


public java.lang.Object reverseMap(scala.Function1, scala.collection.generic.CanBuildFrom);
  Signature: (Lscala/Function1;Lscala/collection/generic/CanBuildFrom;)Ljava/lang/Object;
  Code:
   Stack=3, Locals=3, Args_size=3
	aload_0
	aload_1
	aload_2
	invokestatic	Method scala/collection/SeqLike$class.reverseMap:(Lscala/collection/SeqLike;Lscala/Function1;Lscala/collection/generic/CanBuildFrom;)Ljava/lang/Object;
	areturn
  Labels:
  LocalVariableTable: 
   Start  Length  Slot  Name   Signature
   0      7      0    this       Lscala/collection/mutable/PriorityQueue$ResizableArrayAccess;
   0      7      1    f       Lscala/Function1;
   0      7      2    bf       Lscala/collection/generic/CanBuildFrom;


public scala.collection.Iterator reversedElements();
  Signature: ()Lscala/collection/Iterator;
  Code:
   Stack=1, Locals=1, Args_size=1
	aload_0
	invokestatic	Method scala/collection/SeqLike$class.reversedElements:(Lscala/collection/SeqLike;)Lscala/collection/Iterator;
	areturn
  Labels:
  Deprecated: true

public boolean startsWith(scala.collection.Seq);
  Signature: (Lscala/collection/Seq;)Z
  Code:
   Stack=2, Locals=2, Args_size=2
	aload_0
	aload_1
	invokestatic	Method scala/collection/SeqLike$class.startsWith:(Lscala/collection/SeqLike;Lscala/collection/Seq;)Z
	ireturn
  Labels:
  LocalVariableTable: 
   Start  Length  Slot  Name   Signature
   0      6      0    this       Lscala/collection/mutable/PriorityQueue$ResizableArrayAccess;
   0      6      1    that       Lscala/collection/Seq;


public int indexOfSlice(scala.collection.Seq);
  Signature: (Lscala/collection/Seq;)I
  Code:
   Stack=2, Locals=2, Args_size=2
	aload_0
	aload_1
	invokestatic	Method scala/collection/SeqLike$class.indexOfSlice:(Lscala/collection/SeqLike;Lscala/collection/Seq;)I
	ireturn
  Labels:
  LocalVariableTable: 
   Start  Length  Slot  Name   Signature
   0      6      0    this       Lscala/collection/mutable/PriorityQueue$ResizableArrayAccess;
   0      6      1    that       Lscala/collection/Seq;


public int indexOfSlice(scala.collection.Seq, int);
  Signature: (Lscala/collection/Seq;I)I
  Code:
   Stack=3, Locals=3, Args_size=3
	aload_0
	aload_1
	iload_2
	invokestatic	Method scala/collection/SeqLike$class.indexOfSlice:(Lscala/collection/SeqLike;Lscala/collection/Seq;I)I
	ireturn
  Labels:
  LocalVariableTable: 
   Start  Length  Slot  Name   Signature
   0      7      0    this       Lscala/collection/mutable/PriorityQueue$ResizableArrayAccess;
   0      7      1    that       Lscala/collection/Seq;
   0      7      2    from       I


public int lastIndexOfSlice(scala.collection.Seq);
  Signature: (Lscala/collection/Seq;)I
  Code:
   Stack=2, Locals=2, Args_size=2
	aload_0
	aload_1
	invokestatic	Method scala/collection/SeqLike$class.lastIndexOfSlice:(Lscala/collection/SeqLike;Lscala/collection/Seq;)I
	ireturn
  Labels:
  LocalVariableTable: 
   Start  Length  Slot  Name   Signature
   0      6      0    this       Lscala/collection/mutable/PriorityQueue$ResizableArrayAccess;
   0      6      1    that       Lscala/collection/Seq;


public int lastIndexOfSlice(scala.collection.Seq, int);
  Signature: (Lscala/collection/Seq;I)I
  Code:
   Stack=3, Locals=3, Args_size=3
	aload_0
	aload_1
	iload_2
	invokestatic	Method scala/collection/SeqLike$class.lastIndexOfSlice:(Lscala/collection/SeqLike;Lscala/collection/Seq;I)I
	ireturn
  Labels:
  LocalVariableTable: 
   Start  Length  Slot  Name   Signature
   0      7      0    this       Lscala/collection/mutable/PriorityQueue$ResizableArrayAccess;
   0      7      1    that       Lscala/collection/Seq;
   0      7      2    end       I


public boolean containsSlice(scala.collection.Seq);
  Signature: (Lscala/collection/Seq;)Z
  Code:
   Stack=2, Locals=2, Args_size=2
	aload_0
	aload_1
	invokestatic	Method scala/collection/SeqLike$class.containsSlice:(Lscala/collection/SeqLike;Lscala/collection/Seq;)Z
	ireturn
  Labels:
  LocalVariableTable: 
   Start  Length  Slot  Name   Signature
   0      6      0    this       Lscala/collection/mutable/PriorityQueue$ResizableArrayAccess;
   0      6      1    that       Lscala/collection/Seq;


public boolean contains(java.lang.Object);
  Signature: (Ljava/lang/Object;)Z
  Code:
   Stack=2, Locals=2, Args_size=2
	aload_0
	aload_1
	invokestatic	Method scala/collection/SeqLike$class.contains:(Lscala/collection/SeqLike;Ljava/lang/Object;)Z
	ireturn
  Labels:
  LocalVariableTable: 
   Start  Length  Slot  Name   Signature
   0      6      0    this       Lscala/collection/mutable/PriorityQueue$ResizableArrayAccess;
   0      6      1    elem       Ljava/lang/Object;


public java.lang.Object union(scala.collection.Seq, scala.collection.generic.CanBuildFrom);
  Signature: (Lscala/collection/Seq;Lscala/collection/generic/CanBuildFrom;)Ljava/lang/Object;
  Code:
   Stack=3, Locals=3, Args_size=3
	aload_0
	aload_1
	aload_2
	invokestatic	Method scala/collection/SeqLike$class.union:(Lscala/collection/SeqLike;Lscala/collection/Seq;Lscala/collection/generic/CanBuildFrom;)Ljava/lang/Object;
	areturn
  Labels:
  LocalVariableTable: 
   Start  Length  Slot  Name   Signature
   0      7      0    this       Lscala/collection/mutable/PriorityQueue$ResizableArrayAccess;
   0      7      1    that       Lscala/collection/Seq;
   0      7      2    bf       Lscala/collection/generic/CanBuildFrom;


public java.lang.Object diff(scala.collection.Seq);
  Signature: (Lscala/collection/Seq;)Ljava/lang/Object;
  Code:
   Stack=2, Locals=2, Args_size=2
	aload_0
	aload_1
	invokestatic	Method scala/collection/SeqLike$class.diff:(Lscala/collection/SeqLike;Lscala/collection/Seq;)Ljava/lang/Object;
	areturn
  Labels:
  LocalVariableTable: 
   Start  Length  Slot  Name   Signature
   0      6      0    this       Lscala/collection/mutable/PriorityQueue$ResizableArrayAccess;
   0      6      1    that       Lscala/collection/Seq;


public java.lang.Object intersect(scala.collection.Seq);
  Signature: (Lscala/collection/Seq;)Ljava/lang/Object;
  Code:
   Stack=2, Locals=2, Args_size=2
	aload_0
	aload_1
	invokestatic	Method scala/collection/SeqLike$class.intersect:(Lscala/collection/SeqLike;Lscala/collection/Seq;)Ljava/lang/Object;
	areturn
  Labels:
  LocalVariableTable: 
   Start  Length  Slot  Name   Signature
   0      6      0    this       Lscala/collection/mutable/PriorityQueue$ResizableArrayAccess;
   0      6      1    that       Lscala/collection/Seq;


public java.lang.Object distinct();
  Signature: ()Ljava/lang/Object;
  Code:
   Stack=1, Locals=1, Args_size=1
	aload_0
	invokestatic	Method scala/collection/SeqLike$class.distinct:(Lscala/collection/SeqLike;)Ljava/lang/Object;
	areturn
  Labels:

public java.lang.Object patch(int, scala.collection.Seq, int, scala.collection.generic.CanBuildFrom);
  Signature: (ILscala/collection/Seq;ILscala/collection/generic/CanBuildFrom;)Ljava/lang/Object;
  Code:
   Stack=5, Locals=5, Args_size=5
	aload_0
	iload_1
	aload_2
	iload_3
	aload	4
	invokestatic	Method scala/collection/SeqLike$class.patch:(Lscala/collection/SeqLike;ILscala/collection/Seq;ILscala/collection/generic/CanBuildFrom;)Ljava/lang/Object;
	areturn
  Labels:
  LocalVariableTable: 
   Start  Length  Slot  Name   Signature
   0      10      0    this       Lscala/collection/mutable/PriorityQueue$ResizableArrayAccess;
   0      10      1    from       I
   0      10      2    patch       Lscala/collection/Seq;
   0      10      3    replaced       I
   0      10      4    bf       Lscala/collection/generic/CanBuildFrom;


public java.lang.Object updated(int, java.lang.Object, scala.collection.generic.CanBuildFrom);
  Signature: (ILjava/lang/Object;Lscala/collection/generic/CanBuildFrom;)Ljava/lang/Object;
  Code:
   Stack=4, Locals=4, Args_size=4
	aload_0
	iload_1
	aload_2
	aload_3
	invokestatic	Method scala/collection/SeqLike$class.updated:(Lscala/collection/SeqLike;ILjava/lang/Object;Lscala/collection/generic/CanBuildFrom;)Ljava/lang/Object;
	areturn
  Labels:
  LocalVariableTable: 
   Start  Length  Slot  Name   Signature
   0      8      0    this       Lscala/collection/mutable/PriorityQueue$ResizableArrayAccess;
   0      8      1    index       I
   0      8      2    elem       Ljava/lang/Object;
   0      8      3    bf       Lscala/collection/generic/CanBuildFrom;


public java.lang.Object $plus$colon(java.lang.Object, scala.collection.generic.CanBuildFrom);
  Signature: (Ljava/lang/Object;Lscala/collection/generic/CanBuildFrom;)Ljava/lang/Object;
  Code:
   Stack=3, Locals=3, Args_size=3
	aload_0
	aload_1
	aload_2
	invokestatic	Method scala/collection/SeqLike$class.$plus$colon:(Lscala/collection/SeqLike;Ljava/lang/Object;Lscala/collection/generic/CanBuildFrom;)Ljava/lang/Object;
	areturn
  Labels:
  LocalVariableTable: 
   Start  Length  Slot  Name   Signature
   0      7      0    this       Lscala/collection/mutable/PriorityQueue$ResizableArrayAccess;
   0      7      1    elem       Ljava/lang/Object;
   0      7      2    bf       Lscala/collection/generic/CanBuildFrom;


public java.lang.Object $colon$plus(java.lang.Object, scala.collection.generic.CanBuildFrom);
  Signature: (Ljava/lang/Object;Lscala/collection/generic/CanBuildFrom;)Ljava/lang/Object;
  Code:
   Stack=3, Locals=3, Args_size=3
	aload_0
	aload_1
	aload_2
	invokestatic	Method scala/collection/SeqLike$class.$colon$plus:(Lscala/collection/SeqLike;Ljava/lang/Object;Lscala/collection/generic/CanBuildFrom;)Ljava/lang/Object;
	areturn
  Labels:
  LocalVariableTable: 
   Start  Length  Slot  Name   Signature
   0      7      0    this       Lscala/collection/mutable/PriorityQueue$ResizableArrayAccess;
   0      7      1    elem       Ljava/lang/Object;
   0      7      2    bf       Lscala/collection/generic/CanBuildFrom;


public java.lang.Object padTo(int, java.lang.Object, scala.collection.generic.CanBuildFrom);
  Signature: (ILjava/lang/Object;Lscala/collection/generic/CanBuildFrom;)Ljava/lang/Object;
  Code:
   Stack=4, Locals=4, Args_size=4
	aload_0
	iload_1
	aload_2
	aload_3
	invokestatic	Method scala/collection/SeqLike$class.padTo:(Lscala/collection/SeqLike;ILjava/lang/Object;Lscala/collection/generic/CanBuildFrom;)Ljava/lang/Object;
	areturn
  Labels:
  LocalVariableTable: 
   Start  Length  Slot  Name   Signature
   0      8      0    this       Lscala/collection/mutable/PriorityQueue$ResizableArrayAccess;
   0      8      1    len       I
   0      8      2    elem       Ljava/lang/Object;
   0      8      3    bf       Lscala/collection/generic/CanBuildFrom;


public boolean corresponds(scala.collection.Seq, scala.Function2);
  Signature: (Lscala/collection/Seq;Lscala/Function2;)Z
  Code:
   Stack=3, Locals=3, Args_size=3
	aload_0
	aload_1
	aload_2
	invokestatic	Method scala/collection/SeqLike$class.corresponds:(Lscala/collection/SeqLike;Lscala/collection/Seq;Lscala/Function2;)Z
	ireturn
  Labels:
  LocalVariableTable: 
   Start  Length  Slot  Name   Signature
   0      7      0    this       Lscala/collection/mutable/PriorityQueue$ResizableArrayAccess;
   0      7      1    that       Lscala/collection/Seq;
   0      7      2    p       Lscala/Function2;


public java.lang.Object sortWith(scala.Function2);
  Signature: (Lscala/Function2;)Ljava/lang/Object;
  Code:
   Stack=2, Locals=2, Args_size=2
	aload_0
	aload_1
	invokestatic	Method scala/collection/SeqLike$class.sortWith:(Lscala/collection/SeqLike;Lscala/Function2;)Ljava/lang/Object;
	areturn
  Labels:
  LocalVariableTable: 
   Start  Length  Slot  Name   Signature
   0      6      0    this       Lscala/collection/mutable/PriorityQueue$ResizableArrayAccess;
   0      6      1    lt       Lscala/Function2;


public java.lang.Object sortBy(scala.Function1, scala.math.Ordering);
  Signature: (Lscala/Function1;Lscala/math/Ordering;)Ljava/lang/Object;
  Code:
   Stack=3, Locals=3, Args_size=3
	aload_0
	aload_1
	aload_2
	invokestatic	Method scala/collection/SeqLike$class.sortBy:(Lscala/collection/SeqLike;Lscala/Function1;Lscala/math/Ordering;)Ljava/lang/Object;
	areturn
  Labels:
  LocalVariableTable: 
   Start  Length  Slot  Name   Signature
   0      7      0    this       Lscala/collection/mutable/PriorityQueue$ResizableArrayAccess;
   0      7      1    f       Lscala/Function1;
   0      7      2    ord       Lscala/math/Ordering;


public java.lang.Object sorted(scala.math.Ordering);
  Signature: (Lscala/math/Ordering;)Ljava/lang/Object;
  Code:
   Stack=2, Locals=2, Args_size=2
	aload_0
	aload_1
	invokestatic	Method scala/collection/SeqLike$class.sorted:(Lscala/collection/SeqLike;Lscala/math/Ordering;)Ljava/lang/Object;
	areturn
  Labels:
  LocalVariableTable: 
   Start  Length  Slot  Name   Signature
   0      6      0    this       Lscala/collection/mutable/PriorityQueue$ResizableArrayAccess;
   0      6      1    ord       Lscala/math/Ordering;


public scala.collection.Seq toSeq();
  Signature: ()Lscala/collection/Seq;
  Code:
   Stack=1, Locals=1, Args_size=1
	aload_0
	invokestatic	Method scala/collection/SeqLike$class.toSeq:(Lscala/collection/SeqLike;)Lscala/collection/Seq;
	areturn
  Labels:

public scala.collection.immutable.Range indices();
  Signature: ()Lscala/collection/immutable/Range;
  Code:
   Stack=1, Locals=1, Args_size=1
	aload_0
	invokestatic	Method scala/collection/SeqLike$class.indices:(Lscala/collection/SeqLike;)Lscala/collection/immutable/Range;
	areturn
  Labels:

public int hashCode();
  Signature: ()I
  Code:
   Stack=1, Locals=1, Args_size=1
	aload_0
	invokestatic	Method scala/collection/SeqLike$class.hashCode:(Lscala/collection/SeqLike;)I
	ireturn
  Labels:

public boolean equals(java.lang.Object);
  Signature: (Ljava/lang/Object;)Z
  Code:
   Stack=2, Locals=2, Args_size=2
	aload_0
	aload_1
	invokestatic	Method scala/collection/SeqLike$class.equals:(Lscala/collection/SeqLike;Ljava/lang/Object;)Z
	ireturn
  Labels:
  LocalVariableTable: 
   Start  Length  Slot  Name   Signature
   0      6      0    this       Lscala/collection/mutable/PriorityQueue$ResizableArrayAccess;
   0      6      1    that       Ljava/lang/Object;


public java.lang.String toString();
  Signature: ()Ljava/lang/String;
  Code:
   Stack=1, Locals=1, Args_size=1
	aload_0
	invokestatic	Method scala/collection/SeqLike$class.toString:(Lscala/collection/SeqLike;)Ljava/lang/String;
	areturn
  Labels:

public int findLastIndexOf(scala.Function1);
  Signature: (Lscala/Function1;)I
  Code:
   Stack=2, Locals=2, Args_size=2
	aload_0
	aload_1
	invokestatic	Method scala/collection/SeqLike$class.findLastIndexOf:(Lscala/collection/SeqLike;Lscala/Function1;)I
	ireturn
  Labels:
  LocalVariableTable: 
   Start  Length  Slot  Name   Signature
   0      6      0    this       Lscala/collection/mutable/PriorityQueue$ResizableArrayAccess;
   0      6      1    p       Lscala/Function1;


public boolean equalsWith(scala.collection.Seq, scala.Function2);
  Signature: (Lscala/collection/Seq;Lscala/Function2;)Z
  Code:
   Stack=3, Locals=3, Args_size=3
	aload_0
	aload_1
	aload_2
	invokestatic	Method scala/collection/SeqLike$class.equalsWith:(Lscala/collection/SeqLike;Lscala/collection/Seq;Lscala/Function2;)Z
	ireturn
  Labels:
  LocalVariableTable: 
   Start  Length  Slot  Name   Signature
   0      7      0    this       Lscala/collection/mutable/PriorityQueue$ResizableArrayAccess;
   0      7      1    that       Lscala/collection/Seq;
   0      7      2    f       Lscala/Function2;

  Deprecated: true

public scala.collection.SeqView projection();
  Signature: ()Lscala/collection/SeqView;
  Code:
   Stack=1, Locals=1, Args_size=1
	aload_0
	invokestatic	Method scala/collection/SeqLike$class.projection:(Lscala/collection/SeqLike;)Lscala/collection/SeqView;
	areturn
  Labels:
  Deprecated: true

public scala.PartialFunction orElse(scala.PartialFunction);
  Signature: (Lscala/PartialFunction;)Lscala/PartialFunction;
  Code:
   Stack=2, Locals=2, Args_size=2
	aload_0
	aload_1
	invokestatic	Method scala/PartialFunction$class.orElse:(Lscala/PartialFunction;Lscala/PartialFunction;)Lscala/PartialFunction;
	areturn
  Labels:
  LocalVariableTable: 
   Start  Length  Slot  Name   Signature
   0      6      0    this       Lscala/collection/mutable/PriorityQueue$ResizableArrayAccess;
   0      6      1    that       Lscala/PartialFunction;


public scala.PartialFunction andThen(scala.Function1);
  Signature: (Lscala/Function1;)Lscala/PartialFunction;
  Code:
   Stack=2, Locals=2, Args_size=2
	aload_0
	aload_1
	invokestatic	Method scala/PartialFunction$class.andThen:(Lscala/PartialFunction;Lscala/Function1;)Lscala/PartialFunction;
	areturn
  Labels:
  LocalVariableTable: 
   Start  Length  Slot  Name   Signature
   0      6      0    this       Lscala/collection/mutable/PriorityQueue$ResizableArrayAccess;
   0      6      1    k       Lscala/Function1;


public scala.Function1 lift();
  Signature: ()Lscala/Function1;
  Code:
   Stack=1, Locals=1, Args_size=1
	aload_0
	invokestatic	Method scala/PartialFunction$class.lift:(Lscala/PartialFunction;)Lscala/Function1;
	areturn
  Labels:

public scala.Function1 compose(scala.Function1);
  Signature: (Lscala/Function1;)Lscala/Function1;
  Code:
   Stack=2, Locals=2, Args_size=2
	aload_0
	aload_1
	invokestatic	Method scala/Function1$class.compose:(Lscala/Function1;Lscala/Function1;)Lscala/Function1;
	areturn
  Labels:
  LocalVariableTable: 
   Start  Length  Slot  Name   Signature
   0      6      0    this       Lscala/collection/mutable/PriorityQueue$ResizableArrayAccess;
   0      6      1    g       Lscala/Function1;


public scala.collection.Iterator elements();
  Signature: ()Lscala/collection/Iterator;
  Code:
   Stack=1, Locals=1, Args_size=1
	aload_0
	invokestatic	Method scala/collection/IterableLike$class.elements:(Lscala/collection/IterableLike;)Lscala/collection/Iterator;
	areturn
  Labels:
  Deprecated: true

public scala.collection.Iterable toIterable();
  Signature: ()Lscala/collection/Iterable;
  Code:
   Stack=1, Locals=1, Args_size=1
	aload_0
	invokestatic	Method scala/collection/IterableLike$class.toIterable:(Lscala/collection/IterableLike;)Lscala/collection/Iterable;
	areturn
  Labels:

public scala.collection.Iterator grouped(int);
  Signature: (I)Lscala/collection/Iterator;
  Code:
   Stack=2, Locals=2, Args_size=2
	aload_0
	iload_1
	invokestatic	Method scala/collection/IterableLike$class.grouped:(Lscala/collection/IterableLike;I)Lscala/collection/Iterator;
	areturn
  Labels:
  LocalVariableTable: 
   Start  Length  Slot  Name   Signature
   0      6      0    this       Lscala/collection/mutable/PriorityQueue$ResizableArrayAccess;
   0      6      1    size       I


public scala.collection.Iterator sliding(int);
  Signature: (I)Lscala/collection/Iterator;
  Code:
   Stack=2, Locals=2, Args_size=2
	aload_0
	iload_1
	invokestatic	Method scala/collection/IterableLike$class.sliding:(Lscala/collection/IterableLike;I)Lscala/collection/Iterator;
	areturn
  Labels:
  LocalVariableTable: 
   Start  Length  Slot  Name   Signature
   0      6      0    this       Lscala/collection/mutable/PriorityQueue$ResizableArrayAccess;
   0      6      1    size       I


public scala.collection.Iterator sliding(int, int);
  Signature: (II)Lscala/collection/Iterator;
  Code:
   Stack=3, Locals=3, Args_size=3
	aload_0
	iload_1
	iload_2
	invokestatic	Method scala/collection/IterableLike$class.sliding:(Lscala/collection/IterableLike;II)Lscala/collection/Iterator;
	areturn
  Labels:
  LocalVariableTable: 
   Start  Length  Slot  Name   Signature
   0      7      0    this       Lscala/collection/mutable/PriorityQueue$ResizableArrayAccess;
   0      7      1    size       I
   0      7      2    step       I


public java.lang.Object zipAll(scala.collection.Iterable, java.lang.Object, java.lang.Object, scala.collection.generic.CanBuildFrom);
  Signature: (Lscala/collection/Iterable;Ljava/lang/Object;Ljava/lang/Object;Lscala/collection/generic/CanBuildFrom;)Ljava/lang/Object;
  Code:
   Stack=5, Locals=5, Args_size=5
	aload_0
	aload_1
	aload_2
	aload_3
	aload	4
	invokestatic	Method scala/collection/IterableLike$class.zipAll:(Lscala/collection/IterableLike;Lscala/collection/Iterable;Ljava/lang/Object;Ljava/lang/Object;Lscala/collection/generic/CanBuildFrom;)Ljava/lang/Object;
	areturn
  Labels:
  LocalVariableTable: 
   Start  Length  Slot  Name   Signature
   0      10      0    this       Lscala/collection/mutable/PriorityQueue$ResizableArrayAccess;
   0      10      1    that       Lscala/collection/Iterable;
   0      10      2    thisElem       Ljava/lang/Object;
   0      10      3    thatElem       Ljava/lang/Object;
   0      10      4    bf       Lscala/collection/generic/CanBuildFrom;


public scala.collection.immutable.Stream toStream();
  Signature: ()Lscala/collection/immutable/Stream;
  Code:
   Stack=1, Locals=1, Args_size=1
	aload_0
	invokestatic	Method scala/collection/IterableLike$class.toStream:(Lscala/collection/IterableLike;)Lscala/collection/immutable/Stream;
	areturn
  Labels:

public boolean canEqual(java.lang.Object);
  Signature: (Ljava/lang/Object;)Z
  Code:
   Stack=2, Locals=2, Args_size=2
	aload_0
	aload_1
	invokestatic	Method scala/collection/IterableLike$class.canEqual:(Lscala/collection/IterableLike;Ljava/lang/Object;)Z
	ireturn
  Labels:
  LocalVariableTable: 
   Start  Length  Slot  Name   Signature
   0      6      0    this       Lscala/collection/mutable/PriorityQueue$ResizableArrayAccess;
   0      6      1    that       Ljava/lang/Object;


public java.lang.Object first();
  Signature: ()Ljava/lang/Object;
  Code:
   Stack=1, Locals=1, Args_size=1
	aload_0
	invokestatic	Method scala/collection/IterableLike$class.first:(Lscala/collection/IterableLike;)Ljava/lang/Object;
	areturn
  Labels:
  Deprecated: true

public scala.Option firstOption();
  Signature: ()Lscala/Option;
  Code:
   Stack=1, Locals=1, Args_size=1
	aload_0
	invokestatic	Method scala/collection/IterableLike$class.firstOption:(Lscala/collection/IterableLike;)Lscala/Option;
	areturn
  Labels:
  Deprecated: true

public scala.collection.mutable.Builder newBuilder();
  Signature: ()Lscala/collection/mutable/Builder;
  Code:
   Stack=1, Locals=1, Args_size=1
	aload_0
	invokestatic	Method scala/collection/generic/GenericTraversableTemplate$class.newBuilder:(Lscala/collection/generic/GenericTraversableTemplate;)Lscala/collection/mutable/Builder;
	areturn
  Labels:

public scala.collection.mutable.Builder genericBuilder();
  Signature: ()Lscala/collection/mutable/Builder;
  Code:
   Stack=1, Locals=1, Args_size=1
	aload_0
	invokestatic	Method scala/collection/generic/GenericTraversableTemplate$class.genericBuilder:(Lscala/collection/generic/GenericTraversableTemplate;)Lscala/collection/mutable/Builder;
	areturn
  Labels:

public scala.Tuple2 unzip(scala.Function1);
  Signature: (Lscala/Function1;)Lscala/Tuple2;
  Code:
   Stack=2, Locals=2, Args_size=2
	aload_0
	aload_1
	invokestatic	Method scala/collection/generic/GenericTraversableTemplate$class.unzip:(Lscala/collection/generic/GenericTraversableTemplate;Lscala/Function1;)Lscala/Tuple2;
	areturn
  Labels:
  LocalVariableTable: 
   Start  Length  Slot  Name   Signature
   0      6      0    this       Lscala/collection/mutable/PriorityQueue$ResizableArrayAccess;
   0      6      1    asPair       Lscala/Function1;


public scala.collection.Traversable flatten(scala.Function1);
  Signature: (Lscala/Function1;)Lscala/collection/Traversable;
  Code:
   Stack=2, Locals=2, Args_size=2
	aload_0
	aload_1
	invokestatic	Method scala/collection/generic/GenericTraversableTemplate$class.flatten:(Lscala/collection/generic/GenericTraversableTemplate;Lscala/Function1;)Lscala/collection/Traversable;
	areturn
  Labels:
  LocalVariableTable: 
   Start  Length  Slot  Name   Signature
   0      6      0    this       Lscala/collection/mutable/PriorityQueue$ResizableArrayAccess;
   0      6      1    asTraversable       Lscala/Function1;


public scala.collection.Traversable transpose(scala.Function1);
  Signature: (Lscala/Function1;)Lscala/collection/Traversable;
  Code:
   Stack=2, Locals=2, Args_size=2
	aload_0
	aload_1
	invokestatic	Method scala/collection/generic/GenericTraversableTemplate$class.transpose:(Lscala/collection/generic/GenericTraversableTemplate;Lscala/Function1;)Lscala/collection/Traversable;
	areturn
  Labels:
  LocalVariableTable: 
   Start  Length  Slot  Name   Signature
   0      6      0    this       Lscala/collection/mutable/PriorityQueue$ResizableArrayAccess;
   0      6      1    asTraversable       Lscala/Function1;


public java.lang.Object repr();
  Signature: ()Ljava/lang/Object;
  Code:
   Stack=1, Locals=1, Args_size=1
	aload_0
	invokestatic	Method scala/collection/TraversableLike$class.repr:(Lscala/collection/TraversableLike;)Ljava/lang/Object;
	areturn
  Labels:

public boolean nonEmpty();
  Signature: ()Z
  Code:
   Stack=1, Locals=1, Args_size=1
	aload_0
	invokestatic	Method scala/collection/TraversableLike$class.nonEmpty:(Lscala/collection/TraversableLike;)Z
	ireturn
  Labels:

public boolean hasDefiniteSize();
  Signature: ()Z
  Code:
   Stack=1, Locals=1, Args_size=1
	aload_0
	invokestatic	Method scala/collection/TraversableLike$class.hasDefiniteSize:(Lscala/collection/TraversableLike;)Z
	ireturn
  Labels:

public java.lang.Object $plus$plus(scala.collection.Traversable, scala.collection.generic.CanBuildFrom);
  Signature: (Lscala/collection/Traversable;Lscala/collection/generic/CanBuildFrom;)Ljava/lang/Object;
  Code:
   Stack=3, Locals=3, Args_size=3
	aload_0
	aload_1
	aload_2
	invokestatic	Method scala/collection/TraversableLike$class.$plus$plus:(Lscala/collection/TraversableLike;Lscala/collection/Traversable;Lscala/collection/generic/CanBuildFrom;)Ljava/lang/Object;
	areturn
  Labels:
  LocalVariableTable: 
   Start  Length  Slot  Name   Signature
   0      7      0    this       Lscala/collection/mutable/PriorityQueue$ResizableArrayAccess;
   0      7      1    that       Lscala/collection/Traversable;
   0      7      2    bf       Lscala/collection/generic/CanBuildFrom;


public java.lang.Object $plus$plus(scala.collection.Iterator, scala.collection.generic.CanBuildFrom);
  Signature: (Lscala/collection/Iterator;Lscala/collection/generic/CanBuildFrom;)Ljava/lang/Object;
  Code:
   Stack=3, Locals=3, Args_size=3
	aload_0
	aload_1
	aload_2
	invokestatic	Method scala/collection/TraversableLike$class.$plus$plus:(Lscala/collection/TraversableLike;Lscala/collection/Iterator;Lscala/collection/generic/CanBuildFrom;)Ljava/lang/Object;
	areturn
  Labels:
  LocalVariableTable: 
   Start  Length  Slot  Name   Signature
   0      7      0    this       Lscala/collection/mutable/PriorityQueue$ResizableArrayAccess;
   0      7      1    that       Lscala/collection/Iterator;
   0      7      2    bf       Lscala/collection/generic/CanBuildFrom;


public java.lang.Object map(scala.Function1, scala.collection.generic.CanBuildFrom);
  Signature: (Lscala/Function1;Lscala/collection/generic/CanBuildFrom;)Ljava/lang/Object;
  Code:
   Stack=3, Locals=3, Args_size=3
	aload_0
	aload_1
	aload_2
	invokestatic	Method scala/collection/TraversableLike$class.map:(Lscala/collection/TraversableLike;Lscala/Function1;Lscala/collection/generic/CanBuildFrom;)Ljava/lang/Object;
	areturn
  Labels:
  LocalVariableTable: 
   Start  Length  Slot  Name   Signature
   0      7      0    this       Lscala/collection/mutable/PriorityQueue$ResizableArrayAccess;
   0      7      1    f       Lscala/Function1;
   0      7      2    bf       Lscala/collection/generic/CanBuildFrom;


public java.lang.Object flatMap(scala.Function1, scala.collection.generic.CanBuildFrom);
  Signature: (Lscala/Function1;Lscala/collection/generic/CanBuildFrom;)Ljava/lang/Object;
  Code:
   Stack=3, Locals=3, Args_size=3
	aload_0
	aload_1
	aload_2
	invokestatic	Method scala/collection/TraversableLike$class.flatMap:(Lscala/collection/TraversableLike;Lscala/Function1;Lscala/collection/generic/CanBuildFrom;)Ljava/lang/Object;
	areturn
  Labels:
  LocalVariableTable: 
   Start  Length  Slot  Name   Signature
   0      7      0    this       Lscala/collection/mutable/PriorityQueue$ResizableArrayAccess;
   0      7      1    f       Lscala/Function1;
   0      7      2    bf       Lscala/collection/generic/CanBuildFrom;


public java.lang.Object filter(scala.Function1);
  Signature: (Lscala/Function1;)Ljava/lang/Object;
  Code:
   Stack=2, Locals=2, Args_size=2
	aload_0
	aload_1
	invokestatic	Method scala/collection/TraversableLike$class.filter:(Lscala/collection/TraversableLike;Lscala/Function1;)Ljava/lang/Object;
	areturn
  Labels:
  LocalVariableTable: 
   Start  Length  Slot  Name   Signature
   0      6      0    this       Lscala/collection/mutable/PriorityQueue$ResizableArrayAccess;
   0      6      1    p       Lscala/Function1;


public java.lang.Object filterNot(scala.Function1);
  Signature: (Lscala/Function1;)Ljava/lang/Object;
  Code:
   Stack=2, Locals=2, Args_size=2
	aload_0
	aload_1
	invokestatic	Method scala/collection/TraversableLike$class.filterNot:(Lscala/collection/TraversableLike;Lscala/Function1;)Ljava/lang/Object;
	areturn
  Labels:
  LocalVariableTable: 
   Start  Length  Slot  Name   Signature
   0      6      0    this       Lscala/collection/mutable/PriorityQueue$ResizableArrayAccess;
   0      6      1    p       Lscala/Function1;


public java.lang.Object partialMap(scala.PartialFunction, scala.collection.generic.CanBuildFrom);
  Signature: (Lscala/PartialFunction;Lscala/collection/generic/CanBuildFrom;)Ljava/lang/Object;
  Code:
   Stack=3, Locals=3, Args_size=3
	aload_0
	aload_1
	aload_2
	invokestatic	Method scala/collection/TraversableLike$class.partialMap:(Lscala/collection/TraversableLike;Lscala/PartialFunction;Lscala/collection/generic/CanBuildFrom;)Ljava/lang/Object;
	areturn
  Labels:
  LocalVariableTable: 
   Start  Length  Slot  Name   Signature
   0      7      0    this       Lscala/collection/mutable/PriorityQueue$ResizableArrayAccess;
   0      7      1    pf       Lscala/PartialFunction;
   0      7      2    bf       Lscala/collection/generic/CanBuildFrom;


public scala.Tuple2 partition(scala.Function1);
  Signature: (Lscala/Function1;)Lscala/Tuple2;
  Code:
   Stack=2, Locals=2, Args_size=2
	aload_0
	aload_1
	invokestatic	Method scala/collection/TraversableLike$class.partition:(Lscala/collection/TraversableLike;Lscala/Function1;)Lscala/Tuple2;
	areturn
  Labels:
  LocalVariableTable: 
   Start  Length  Slot  Name   Signature
   0      6      0    this       Lscala/collection/mutable/PriorityQueue$ResizableArrayAccess;
   0      6      1    p       Lscala/Function1;


public scala.collection.Map groupBy(scala.Function1);
  Signature: (Lscala/Function1;)Lscala/collection/Map;
  Code:
   Stack=2, Locals=2, Args_size=2
	aload_0
	aload_1
	invokestatic	Method scala/collection/TraversableLike$class.groupBy:(Lscala/collection/TraversableLike;Lscala/Function1;)Lscala/collection/Map;
	areturn
  Labels:
  LocalVariableTable: 
   Start  Length  Slot  Name   Signature
   0      6      0    this       Lscala/collection/mutable/PriorityQueue$ResizableArrayAccess;
   0      6      1    f       Lscala/Function1;


public int count(scala.Function1);
  Signature: (Lscala/Function1;)I
  Code:
   Stack=2, Locals=2, Args_size=2
	aload_0
	aload_1
	invokestatic	Method scala/collection/TraversableLike$class.count:(Lscala/collection/TraversableLike;Lscala/Function1;)I
	ireturn
  Labels:
  LocalVariableTable: 
   Start  Length  Slot  Name   Signature
   0      6      0    this       Lscala/collection/mutable/PriorityQueue$ResizableArrayAccess;
   0      6      1    p       Lscala/Function1;


public java.lang.Object $div$colon(java.lang.Object, scala.Function2);
  Signature: (Ljava/lang/Object;Lscala/Function2;)Ljava/lang/Object;
  Code:
   Stack=3, Locals=3, Args_size=3
	aload_0
	aload_1
	aload_2
	invokestatic	Method scala/collection/TraversableLike$class.$div$colon:(Lscala/collection/TraversableLike;Ljava/lang/Object;Lscala/Function2;)Ljava/lang/Object;
	areturn
  Labels:
  LocalVariableTable: 
   Start  Length  Slot  Name   Signature
   0      7      0    this       Lscala/collection/mutable/PriorityQueue$ResizableArrayAccess;
   0      7      1    z       Ljava/lang/Object;
   0      7      2    op       Lscala/Function2;


public java.lang.Object $colon$bslash(java.lang.Object, scala.Function2);
  Signature: (Ljava/lang/Object;Lscala/Function2;)Ljava/lang/Object;
  Code:
   Stack=3, Locals=3, Args_size=3
	aload_0
	aload_1
	aload_2
	invokestatic	Method scala/collection/TraversableLike$class.$colon$bslash:(Lscala/collection/TraversableLike;Ljava/lang/Object;Lscala/Function2;)Ljava/lang/Object;
	areturn
  Labels:
  LocalVariableTable: 
   Start  Length  Slot  Name   Signature
   0      7      0    this       Lscala/collection/mutable/PriorityQueue$ResizableArrayAccess;
   0      7      1    z       Ljava/lang/Object;
   0      7      2    op       Lscala/Function2;


public scala.Option reduceLeftOption(scala.Function2);
  Signature: (Lscala/Function2;)Lscala/Option;
  Code:
   Stack=2, Locals=2, Args_size=2
	aload_0
	aload_1
	invokestatic	Method scala/collection/TraversableLike$class.reduceLeftOption:(Lscala/collection/TraversableLike;Lscala/Function2;)Lscala/Option;
	areturn
  Labels:
  LocalVariableTable: 
   Start  Length  Slot  Name   Signature
   0      6      0    this       Lscala/collection/mutable/PriorityQueue$ResizableArrayAccess;
   0      6      1    op       Lscala/Function2;


public scala.Option reduceRightOption(scala.Function2);
  Signature: (Lscala/Function2;)Lscala/Option;
  Code:
   Stack=2, Locals=2, Args_size=2
	aload_0
	aload_1
	invokestatic	Method scala/collection/TraversableLike$class.reduceRightOption:(Lscala/collection/TraversableLike;Lscala/Function2;)Lscala/Option;
	areturn
  Labels:
  LocalVariableTable: 
   Start  Length  Slot  Name   Signature
   0      6      0    this       Lscala/collection/mutable/PriorityQueue$ResizableArrayAccess;
   0      6      1    op       Lscala/Function2;


public java.lang.Object scanLeft(java.lang.Object, scala.Function2, scala.collection.generic.CanBuildFrom);
  Signature: (Ljava/lang/Object;Lscala/Function2;Lscala/collection/generic/CanBuildFrom;)Ljava/lang/Object;
  Code:
   Stack=4, Locals=4, Args_size=4
	aload_0
	aload_1
	aload_2
	aload_3
	invokestatic	Method scala/collection/TraversableLike$class.scanLeft:(Lscala/collection/TraversableLike;Ljava/lang/Object;Lscala/Function2;Lscala/collection/generic/CanBuildFrom;)Ljava/lang/Object;
	areturn
  Labels:
  LocalVariableTable: 
   Start  Length  Slot  Name   Signature
   0      8      0    this       Lscala/collection/mutable/PriorityQueue$ResizableArrayAccess;
   0      8      1    z       Ljava/lang/Object;
   0      8      2    op       Lscala/Function2;
   0      8      3    bf       Lscala/collection/generic/CanBuildFrom;


public java.lang.Object scanRight(java.lang.Object, scala.Function2, scala.collection.generic.CanBuildFrom);
  Signature: (Ljava/lang/Object;Lscala/Function2;Lscala/collection/generic/CanBuildFrom;)Ljava/lang/Object;
  Code:
   Stack=4, Locals=4, Args_size=4
	aload_0
	aload_1
	aload_2
	aload_3
	invokestatic	Method scala/collection/TraversableLike$class.scanRight:(Lscala/collection/TraversableLike;Ljava/lang/Object;Lscala/Function2;Lscala/collection/generic/CanBuildFrom;)Ljava/lang/Object;
	areturn
  Labels:
  LocalVariableTable: 
   Start  Length  Slot  Name   Signature
   0      8      0    this       Lscala/collection/mutable/PriorityQueue$ResizableArrayAccess;
   0      8      1    z       Ljava/lang/Object;
   0      8      2    op       Lscala/Function2;
   0      8      3    bf       Lscala/collection/generic/CanBuildFrom;


public java.lang.Object sum(scala.math.Numeric);
  Signature: (Lscala/math/Numeric;)Ljava/lang/Object;
  Code:
   Stack=2, Locals=2, Args_size=2
	aload_0
	aload_1
	invokestatic	Method scala/collection/TraversableLike$class.sum:(Lscala/collection/TraversableLike;Lscala/math/Numeric;)Ljava/lang/Object;
	areturn
  Labels:
  LocalVariableTable: 
   Start  Length  Slot  Name   Signature
   0      6      0    this       Lscala/collection/mutable/PriorityQueue$ResizableArrayAccess;
   0      6      1    num       Lscala/math/Numeric;


public java.lang.Object product(scala.math.Numeric);
  Signature: (Lscala/math/Numeric;)Ljava/lang/Object;
  Code:
   Stack=2, Locals=2, Args_size=2
	aload_0
	aload_1
	invokestatic	Method scala/collection/TraversableLike$class.product:(Lscala/collection/TraversableLike;Lscala/math/Numeric;)Ljava/lang/Object;
	areturn
  Labels:
  LocalVariableTable: 
   Start  Length  Slot  Name   Signature
   0      6      0    this       Lscala/collection/mutable/PriorityQueue$ResizableArrayAccess;
   0      6      1    num       Lscala/math/Numeric;


public java.lang.Object min(scala.math.Ordering);
  Signature: (Lscala/math/Ordering;)Ljava/lang/Object;
  Code:
   Stack=2, Locals=2, Args_size=2
	aload_0
	aload_1
	invokestatic	Method scala/collection/TraversableLike$class.min:(Lscala/collection/TraversableLike;Lscala/math/Ordering;)Ljava/lang/Object;
	areturn
  Labels:
  LocalVariableTable: 
   Start  Length  Slot  Name   Signature
   0      6      0    this       Lscala/collection/mutable/PriorityQueue$ResizableArrayAccess;
   0      6      1    cmp       Lscala/math/Ordering;


public java.lang.Object max(scala.math.Ordering);
  Signature: (Lscala/math/Ordering;)Ljava/lang/Object;
  Code:
   Stack=2, Locals=2, Args_size=2
	aload_0
	aload_1
	invokestatic	Method scala/collection/TraversableLike$class.max:(Lscala/collection/TraversableLike;Lscala/math/Ordering;)Ljava/lang/Object;
	areturn
  Labels:
  LocalVariableTable: 
   Start  Length  Slot  Name   Signature
   0      6      0    this       Lscala/collection/mutable/PriorityQueue$ResizableArrayAccess;
   0      6      1    cmp       Lscala/math/Ordering;


public scala.Option headOption();
  Signature: ()Lscala/Option;
  Code:
   Stack=1, Locals=1, Args_size=1
	aload_0
	invokestatic	Method scala/collection/TraversableLike$class.headOption:(Lscala/collection/TraversableLike;)Lscala/Option;
	areturn
  Labels:

public scala.Option lastOption();
  Signature: ()Lscala/Option;
  Code:
   Stack=1, Locals=1, Args_size=1
	aload_0
	invokestatic	Method scala/collection/TraversableLike$class.lastOption:(Lscala/collection/TraversableLike;)Lscala/Option;
	areturn
  Labels:

public void copyToBuffer(scala.collection.mutable.Buffer);
  Signature: (Lscala/collection/mutable/Buffer;)V
  Code:
   Stack=2, Locals=2, Args_size=2
	aload_0
	aload_1
	invokestatic	Method scala/collection/TraversableLike$class.copyToBuffer:(Lscala/collection/TraversableLike;Lscala/collection/mutable/Buffer;)V
	return
  Labels:
  LocalVariableTable: 
   Start  Length  Slot  Name   Signature
   0      6      0    this       Lscala/collection/mutable/PriorityQueue$ResizableArrayAccess;
   0      6      1    dest       Lscala/collection/mutable/Buffer;


public void copyToArray(java.lang.Object, int);
  Signature: (Ljava/lang/Object;I)V
  Code:
   Stack=3, Locals=3, Args_size=3
	aload_0
	aload_1
	iload_2
	invokestatic	Method scala/collection/TraversableLike$class.copyToArray:(Lscala/collection/TraversableLike;Ljava/lang/Object;I)V
	return
  Labels:
  LocalVariableTable: 
   Start  Length  Slot  Name   Signature
   0      7      0    this       Lscala/collection/mutable/PriorityQueue$ResizableArrayAccess;
   0      7      1    xs       Ljava/lang/Object;
   0      7      2    start       I


public void copyToArray(java.lang.Object);
  Signature: (Ljava/lang/Object;)V
  Code:
   Stack=2, Locals=2, Args_size=2
	aload_0
	aload_1
	invokestatic	Method scala/collection/TraversableLike$class.copyToArray:(Lscala/collection/TraversableLike;Ljava/lang/Object;)V
	return
  Labels:
  LocalVariableTable: 
   Start  Length  Slot  Name   Signature
   0      6      0    this       Lscala/collection/mutable/PriorityQueue$ResizableArrayAccess;
   0      6      1    xs       Ljava/lang/Object;


public java.lang.Object toArray(scala.reflect.ClassManifest);
  Signature: (Lscala/reflect/ClassManifest;)Ljava/lang/Object;
  Code:
   Stack=2, Locals=2, Args_size=2
	aload_0
	aload_1
	invokestatic	Method scala/collection/TraversableLike$class.toArray:(Lscala/collection/TraversableLike;Lscala/reflect/ClassManifest;)Ljava/lang/Object;
	areturn
  Labels:
  LocalVariableTable: 
   Start  Length  Slot  Name   Signature
   0      6      0    this       Lscala/collection/mutable/PriorityQueue$ResizableArrayAccess;
   0      6      1    evidence$1       Lscala/reflect/ClassManifest;


public scala.collection.immutable.List toList();
  Signature: ()Lscala/collection/immutable/List;
  Code:
   Stack=1, Locals=1, Args_size=1
	aload_0
	invokestatic	Method scala/collection/TraversableLike$class.toList:(Lscala/collection/TraversableLike;)Lscala/collection/immutable/List;
	areturn
  Labels:

public scala.collection.mutable.IndexedSeq toIndexedSeq();
  Signature: ()Lscala/collection/mutable/IndexedSeq;
  Code:
   Stack=1, Locals=1, Args_size=1
	aload_0
	invokestatic	Method scala/collection/TraversableLike$class.toIndexedSeq:(Lscala/collection/TraversableLike;)Lscala/collection/mutable/IndexedSeq;
	areturn
  Labels:

public scala.collection.immutable.Set toSet();
  Signature: ()Lscala/collection/immutable/Set;
  Code:
   Stack=1, Locals=1, Args_size=1
	aload_0
	invokestatic	Method scala/collection/TraversableLike$class.toSet:(Lscala/collection/TraversableLike;)Lscala/collection/immutable/Set;
	areturn
  Labels:

public scala.collection.immutable.Map toMap(scala.Predef$$less$colon$less);
  Signature: (Lscala/Predef$$less$colon$less;)Lscala/collection/immutable/Map;
  Code:
   Stack=2, Locals=2, Args_size=2
	aload_0
	aload_1
	invokestatic	Method scala/collection/TraversableLike$class.toMap:(Lscala/collection/TraversableLike;Lscala/Predef$$less$colon$less;)Lscala/collection/immutable/Map;
	areturn
  Labels:
  LocalVariableTable: 
   Start  Length  Slot  Name   Signature
   0      6      0    this       Lscala/collection/mutable/PriorityQueue$ResizableArrayAccess;
   0      6      1    ev       Lscala/Predef$$less$colon$less;


public java.lang.String mkString(java.lang.String, java.lang.String, java.lang.String);
  Signature: (Ljava/lang/String;Ljava/lang/String;Ljava/lang/String;)Ljava/lang/String;
  Code:
   Stack=4, Locals=4, Args_size=4
	aload_0
	aload_1
	aload_2
	aload_3
	invokestatic	Method scala/collection/TraversableLike$class.mkString:(Lscala/collection/TraversableLike;Ljava/lang/String;Ljava/lang/String;Ljava/lang/String;)Ljava/lang/String;
	areturn
  Labels:
  LocalVariableTable: 
   Start  Length  Slot  Name   Signature
   0      8      0    this       Lscala/collection/mutable/PriorityQueue$ResizableArrayAccess;
   0      8      1    start       Ljava/lang/String;
   0      8      2    sep       Ljava/lang/String;
   0      8      3    end       Ljava/lang/String;


public java.lang.String mkString(java.lang.String);
  Signature: (Ljava/lang/String;)Ljava/lang/String;
  Code:
   Stack=2, Locals=2, Args_size=2
	aload_0
	aload_1
	invokestatic	Method scala/collection/TraversableLike$class.mkString:(Lscala/collection/TraversableLike;Ljava/lang/String;)Ljava/lang/String;
	areturn
  Labels:
  LocalVariableTable: 
   Start  Length  Slot  Name   Signature
   0      6      0    this       Lscala/collection/mutable/PriorityQueue$ResizableArrayAccess;
   0      6      1    sep       Ljava/lang/String;


public java.lang.String mkString();
  Signature: ()Ljava/lang/String;
  Code:
   Stack=1, Locals=1, Args_size=1
	aload_0
	invokestatic	Method scala/collection/TraversableLike$class.mkString:(Lscala/collection/TraversableLike;)Ljava/lang/String;
	areturn
  Labels:

public scala.collection.mutable.StringBuilder addString(scala.collection.mutable.StringBuilder, java.lang.String, java.lang.String, java.lang.String);
  Signature: (Lscala/collection/mutable/StringBuilder;Ljava/lang/String;Ljava/lang/String;Ljava/lang/String;)Lscala/collection/mutable/StringBuilder;
  Code:
   Stack=5, Locals=5, Args_size=5
	aload_0
	aload_1
	aload_2
	aload_3
	aload	4
	invokestatic	Method scala/collection/TraversableLike$class.addString:(Lscala/collection/TraversableLike;Lscala/collection/mutable/StringBuilder;Ljava/lang/String;Ljava/lang/String;Ljava/lang/String;)Lscala/collection/mutable/StringBuilder;
	areturn
  Labels:
  LocalVariableTable: 
   Start  Length  Slot  Name   Signature
   0      10      0    this       Lscala/collection/mutable/PriorityQueue$ResizableArrayAccess;
   0      10      1    b       Lscala/collection/mutable/StringBuilder;
   0      10      2    start       Ljava/lang/String;
   0      10      3    sep       Ljava/lang/String;
   0      10      4    end       Ljava/lang/String;


public scala.collection.mutable.StringBuilder addString(scala.collection.mutable.StringBuilder, java.lang.String);
  Signature: (Lscala/collection/mutable/StringBuilder;Ljava/lang/String;)Lscala/collection/mutable/StringBuilder;
  Code:
   Stack=3, Locals=3, Args_size=3
	aload_0
	aload_1
	aload_2
	invokestatic	Method scala/collection/TraversableLike$class.addString:(Lscala/collection/TraversableLike;Lscala/collection/mutable/StringBuilder;Ljava/lang/String;)Lscala/collection/mutable/StringBuilder;
	areturn
  Labels:
  LocalVariableTable: 
   Start  Length  Slot  Name   Signature
   0      7      0    this       Lscala/collection/mutable/PriorityQueue$ResizableArrayAccess;
   0      7      1    b       Lscala/collection/mutable/StringBuilder;
   0      7      2    sep       Ljava/lang/String;


public scala.collection.mutable.StringBuilder addString(scala.collection.mutable.StringBuilder);
  Signature: (Lscala/collection/mutable/StringBuilder;)Lscala/collection/mutable/StringBuilder;
  Code:
   Stack=2, Locals=2, Args_size=2
	aload_0
	aload_1
	invokestatic	Method scala/collection/TraversableLike$class.addString:(Lscala/collection/TraversableLike;Lscala/collection/mutable/StringBuilder;)Lscala/collection/mutable/StringBuilder;
	areturn
  Labels:
  LocalVariableTable: 
   Start  Length  Slot  Name   Signature
   0      6      0    this       Lscala/collection/mutable/PriorityQueue$ResizableArrayAccess;
   0      6      1    b       Lscala/collection/mutable/StringBuilder;


public java.lang.String stringPrefix();
  Signature: ()Ljava/lang/String;
  Code:
   Stack=1, Locals=1, Args_size=1
	aload_0
	invokestatic	Method scala/collection/TraversableLike$class.stringPrefix:(Lscala/collection/TraversableLike;)Ljava/lang/String;
	areturn
  Labels:

public scala.collection.TraversableLike$WithFilter withFilter(scala.Function1);
  Signature: (Lscala/Function1;)Lscala/collection/TraversableLike$WithFilter;
  Code:
   Stack=2, Locals=2, Args_size=2
	aload_0
	aload_1
	invokestatic	Method scala/collection/TraversableLike$class.withFilter:(Lscala/collection/TraversableLike;Lscala/Function1;)Lscala/collection/TraversableLike$WithFilter;
	areturn
  Labels:
  LocalVariableTable: 
   Start  Length  Slot  Name   Signature
   0      6      0    this       Lscala/collection/mutable/PriorityQueue$ResizableArrayAccess;
   0      6      1    p       Lscala/Function1;

  Signature: length = 0x2
   02 FFFFFFE1 

public int p_size0();
  Signature: ()I
  Code:
   Stack=1, Locals=1, Args_size=1
	aload_0
	invokeinterface	InterfaceMethod scala/collection/mutable/ResizableArray.size0:()I
	ireturn
  Labels:

public void p_size0_$eq(int);
  Signature: (I)V
  Code:
   Stack=2, Locals=2, Args_size=2
	aload_0
	iload_1
	invokeinterface	InterfaceMethod scala/collection/mutable/ResizableArray.size0_$eq:(I)V
	return
  Labels:
  LocalVariableTable: 
   Start  Length  Slot  Name   Signature
   0      8      0    this       Lscala/collection/mutable/PriorityQueue$ResizableArrayAccess;
   0      8      1    s       I


public java.lang.Object[] p_array();
  Signature: ()[Ljava/lang/Object;
  Code:
   Stack=1, Locals=1, Args_size=1
	aload_0
	invokeinterface	InterfaceMethod scala/collection/mutable/ResizableArray.array:()[Ljava/lang/Object;
	areturn
  Labels:

public void p_ensureSize(int);
  Signature: (I)V
  Code:
   Stack=2, Locals=2, Args_size=2
	aload_0
	iload_1
	invokestatic	Method scala/collection/mutable/ResizableArray$class.ensureSize:(Lscala/collection/mutable/ResizableArray;I)V
	return
  Labels:
  LocalVariableTable: 
   Start  Length  Slot  Name   Signature
   0      6      0    this       Lscala/collection/mutable/PriorityQueue$ResizableArrayAccess;
   0      6      1    n       I


public void p_swap(int, int);
  Signature: (II)V
  Code:
   Stack=3, Locals=3, Args_size=3
	aload_0
	iload_1
	iload_2
	invokestatic	Method scala/collection/mutable/ResizableArray$class.swap:(Lscala/collection/mutable/ResizableArray;II)V
	return
  Labels:
  LocalVariableTable: 
   Start  Length  Slot  Name   Signature
   0      7      0    this       Lscala/collection/mutable/PriorityQueue$ResizableArrayAccess;
   0      7      1    a       I
   0      7      2    b       I


public scala.Function1 andThen(scala.Function1);
  Signature: (Lscala/Function1;)Lscala/Function1;
  Code:
   Stack=2, Locals=2, Args_size=2
	aload_0
	aload_1
	invokeinterface	InterfaceMethod scala/PartialFunction.andThen:(Lscala/Function1;)Lscala/PartialFunction;
	areturn
  Labels:
  LocalVariableTable: 
   Start  Length  Slot  Name   Signature
   0      8      0    this       Lscala/collection/mutable/PriorityQueue$ResizableArrayAccess;
   0      8      1    g       Lscala/Function1;


public scala.collection.IterableView projection();
  Signature: ()Lscala/collection/IterableView;
  Code:
   Stack=1, Locals=1, Args_size=1
	aload_0
	invokeinterface	InterfaceMethod scala/collection/SeqLike.projection:()Lscala/collection/SeqView;
	areturn
  Labels:

public boolean isDefinedAt(java.lang.Object);
  Signature: (Ljava/lang/Object;)Z
  Code:
   Stack=2, Locals=2, Args_size=2
	aload_0
	aload_1
	invokestatic	Method scala/runtime/BoxesRunTime.unboxToInt:(Ljava/lang/Object;)I
	invokeinterface	InterfaceMethod scala/collection/SeqLike.isDefinedAt:(I)Z
	ireturn
  Labels:
  LocalVariableTable: 
   Start  Length  Slot  Name   Signature
   0      11      0    this       Lscala/collection/mutable/PriorityQueue$ResizableArrayAccess;
   0      11      1    x       Ljava/lang/Object;


public scala.collection.TraversableView view(int, int);
  Signature: (II)Lscala/collection/TraversableView;
  Code:
   Stack=3, Locals=3, Args_size=3
	aload_0
	iload_1
	iload_2
	invokeinterface	InterfaceMethod scala/collection/mutable/IndexedSeqLike.view:(II)Lscala/collection/mutable/IndexedSeqView;
	areturn
  Labels:
  LocalVariableTable: 
   Start  Length  Slot  Name   Signature
   0      9      0    this       Lscala/collection/mutable/PriorityQueue$ResizableArrayAccess;
   0      9      1    from       I
   0      9      2    until       I


public scala.collection.IterableView view(int, int);
  Signature: (II)Lscala/collection/IterableView;
  Code:
   Stack=3, Locals=3, Args_size=3
	aload_0
	iload_1
	iload_2
	invokeinterface	InterfaceMethod scala/collection/mutable/IndexedSeqLike.view:(II)Lscala/collection/mutable/IndexedSeqView;
	areturn
  Labels:
  LocalVariableTable: 
   Start  Length  Slot  Name   Signature
   0      9      0    this       Lscala/collection/mutable/PriorityQueue$ResizableArrayAccess;
   0      9      1    from       I
   0      9      2    until       I


public scala.collection.SeqView view(int, int);
  Signature: (II)Lscala/collection/SeqView;
  Code:
   Stack=3, Locals=3, Args_size=3
	aload_0
	iload_1
	iload_2
	invokeinterface	InterfaceMethod scala/collection/mutable/IndexedSeqLike.view:(II)Lscala/collection/mutable/IndexedSeqView;
	areturn
  Labels:
  LocalVariableTable: 
   Start  Length  Slot  Name   Signature
   0      9      0    this       Lscala/collection/mutable/PriorityQueue$ResizableArrayAccess;
   0      9      1    from       I
   0      9      2    until       I


public scala.collection.IndexedSeqView view(int, int);
  Signature: (II)Lscala/collection/IndexedSeqView;
  Code:
   Stack=3, Locals=3, Args_size=3
	aload_0
	iload_1
	iload_2
	invokeinterface	InterfaceMethod scala/collection/mutable/IndexedSeqLike.view:(II)Lscala/collection/mutable/IndexedSeqView;
	areturn
  Labels:
  LocalVariableTable: 
   Start  Length  Slot  Name   Signature
   0      9      0    this       Lscala/collection/mutable/PriorityQueue$ResizableArrayAccess;
   0      9      1    from       I
   0      9      2    until       I


public scala.collection.TraversableView view();
  Signature: ()Lscala/collection/TraversableView;
  Code:
   Stack=1, Locals=1, Args_size=1
	aload_0
	invokeinterface	InterfaceMethod scala/collection/mutable/IndexedSeqLike.view:()Lscala/collection/mutable/IndexedSeqView;
	areturn
  Labels:

public scala.collection.IterableView view();
  Signature: ()Lscala/collection/IterableView;
  Code:
   Stack=1, Locals=1, Args_size=1
	aload_0
	invokeinterface	InterfaceMethod scala/collection/mutable/IndexedSeqLike.view:()Lscala/collection/mutable/IndexedSeqView;
	areturn
  Labels:

public scala.collection.SeqView view();
  Signature: ()Lscala/collection/SeqView;
  Code:
   Stack=1, Locals=1, Args_size=1
	aload_0
	invokeinterface	InterfaceMethod scala/collection/mutable/IndexedSeqLike.view:()Lscala/collection/mutable/IndexedSeqView;
	areturn
  Labels:

public scala.collection.IndexedSeqView view();
  Signature: ()Lscala/collection/IndexedSeqView;
  Code:
   Stack=1, Locals=1, Args_size=1
	aload_0
	invokeinterface	InterfaceMethod scala/collection/mutable/IndexedSeqLike.view:()Lscala/collection/mutable/IndexedSeqView;
	areturn
  Labels:

public scala.collection.Traversable toCollection(java.lang.Object);
  Signature: (Ljava/lang/Object;)Lscala/collection/Traversable;
  Code:
   Stack=2, Locals=2, Args_size=2
	aload_0
	aload_1
	invokeinterface	InterfaceMethod scala/collection/mutable/IndexedSeqLike.toCollection:(Ljava/lang/Object;)Lscala/collection/mutable/IndexedSeq;
	areturn
  Labels:
  LocalVariableTable: 
   Start  Length  Slot  Name   Signature
   0      8      0    this       Lscala/collection/mutable/PriorityQueue$ResizableArrayAccess;
   0      8      1    repr       Ljava/lang/Object;


public scala.collection.Iterable toCollection(java.lang.Object);
  Signature: (Ljava/lang/Object;)Lscala/collection/Iterable;
  Code:
   Stack=2, Locals=2, Args_size=2
	aload_0
	aload_1
	invokeinterface	InterfaceMethod scala/collection/mutable/IndexedSeqLike.toCollection:(Ljava/lang/Object;)Lscala/collection/mutable/IndexedSeq;
	areturn
  Labels:
  LocalVariableTable: 
   Start  Length  Slot  Name   Signature
   0      8      0    this       Lscala/collection/mutable/PriorityQueue$ResizableArrayAccess;
   0      8      1    repr       Ljava/lang/Object;


public scala.collection.Seq toCollection(java.lang.Object);
  Signature: (Ljava/lang/Object;)Lscala/collection/Seq;
  Code:
   Stack=2, Locals=2, Args_size=2
	aload_0
	aload_1
	invokeinterface	InterfaceMethod scala/collection/mutable/IndexedSeqLike.toCollection:(Ljava/lang/Object;)Lscala/collection/mutable/IndexedSeq;
	areturn
  Labels:
  LocalVariableTable: 
   Start  Length  Slot  Name   Signature
   0      8      0    this       Lscala/collection/mutable/PriorityQueue$ResizableArrayAccess;
   0      8      1    repr       Ljava/lang/Object;


public scala.collection.IndexedSeq toCollection(java.lang.Object);
  Signature: (Ljava/lang/Object;)Lscala/collection/IndexedSeq;
  Code:
   Stack=2, Locals=2, Args_size=2
	aload_0
	aload_1
	invokeinterface	InterfaceMethod scala/collection/mutable/IndexedSeqLike.toCollection:(Ljava/lang/Object;)Lscala/collection/mutable/IndexedSeq;
	areturn
  Labels:
  LocalVariableTable: 
   Start  Length  Slot  Name   Signature
   0      8      0    this       Lscala/collection/mutable/PriorityQueue$ResizableArrayAccess;
   0      8      1    repr       Ljava/lang/Object;


public scala.collection.Traversable thisCollection();
  Signature: ()Lscala/collection/Traversable;
  Code:
   Stack=1, Locals=1, Args_size=1
	aload_0
	invokeinterface	InterfaceMethod scala/collection/mutable/IndexedSeqLike.thisCollection:()Lscala/collection/mutable/IndexedSeq;
	areturn
  Labels:

public scala.collection.Iterable thisCollection();
  Signature: ()Lscala/collection/Iterable;
  Code:
   Stack=1, Locals=1, Args_size=1
	aload_0
	invokeinterface	InterfaceMethod scala/collection/mutable/IndexedSeqLike.thisCollection:()Lscala/collection/mutable/IndexedSeq;
	areturn
  Labels:

public scala.collection.Seq thisCollection();
  Signature: ()Lscala/collection/Seq;
  Code:
   Stack=1, Locals=1, Args_size=1
	aload_0
	invokeinterface	InterfaceMethod scala/collection/mutable/IndexedSeqLike.thisCollection:()Lscala/collection/mutable/IndexedSeq;
	areturn
  Labels:

public scala.collection.IndexedSeq thisCollection();
  Signature: ()Lscala/collection/IndexedSeq;
  Code:
   Stack=1, Locals=1, Args_size=1
	aload_0
	invokeinterface	InterfaceMethod scala/collection/mutable/IndexedSeqLike.thisCollection:()Lscala/collection/mutable/IndexedSeq;
	areturn
  Labels:

public java.lang.Object apply(java.lang.Object);
  Signature: (Ljava/lang/Object;)Ljava/lang/Object;
  Code:
   Stack=2, Locals=2, Args_size=2
	aload_0
	aload_1
	invokestatic	Method scala/runtime/BoxesRunTime.unboxToInt:(Ljava/lang/Object;)I
	invokeinterface	InterfaceMethod scala/collection/mutable/ResizableArray.apply:(I)Ljava/lang/Object;
	areturn
  Labels:
  LocalVariableTable: 
   Start  Length  Slot  Name   Signature
   0      11      0    this       Lscala/collection/mutable/PriorityQueue$ResizableArrayAccess;
   0      11      1    v1       Ljava/lang/Object;


public scala.collection.mutable.PriorityQueue$ResizableArrayAccess(scala.collection.mutable.PriorityQueue);
  Signature: (Lscala/collection/mutable/PriorityQueue;)V
  Code:
   Stack=1, Locals=2, Args_size=2
	aload_0
	invokespecial	Method java/lang/Object."<init>":()V
	aload_0
	invokestatic	Method scala/collection/TraversableLike$class.$init$:(Lscala/collection/TraversableLike;)V
	aload_0
	invokestatic	Method scala/collection/generic/GenericTraversableTemplate$class.$init$:(Lscala/collection/generic/GenericTraversableTemplate;)V
	aload_0
	invokestatic	Method scala/collection/Traversable$class.$init$:(Lscala/collection/Traversable;)V
	aload_0
	invokestatic	Method scala/collection/mutable/Traversable$class.$init$:(Lscala/collection/mutable/Traversable;)V
	aload_0
	invokestatic	Method scala/collection/IterableLike$class.$init$:(Lscala/collection/IterableLike;)V
	aload_0
	invokestatic	Method scala/collection/Iterable$class.$init$:(Lscala/collection/Iterable;)V
	aload_0
	invokestatic	Method scala/collection/mutable/Iterable$class.$init$:(Lscala/collection/mutable/Iterable;)V
	aload_0
	invokestatic	Method scala/Function1$class.$init$:(Lscala/Function1;)V
	aload_0
	invokestatic	Method scala/PartialFunction$class.$init$:(Lscala/PartialFunction;)V
	aload_0
	invokestatic	Method scala/collection/SeqLike$class.$init$:(Lscala/collection/SeqLike;)V
	aload_0
	invokestatic	Method scala/collection/Seq$class.$init$:(Lscala/collection/Seq;)V
	aload_0
	invokestatic	Method scala/collection/mutable/Seq$class.$init$:(Lscala/collection/mutable/Seq;)V
	aload_0
	invokestatic	Method scala/collection/IndexedSeqLike$class.$init$:(Lscala/collection/IndexedSeqLike;)V
	aload_0
	invokestatic	Method scala/collection/IndexedSeq$class.$init$:(Lscala/collection/IndexedSeq;)V
	aload_0
	invokestatic	Method scala/collection/mutable/IndexedSeqLike$class.$init$:(Lscala/collection/mutable/IndexedSeqLike;)V
	aload_0
	invokestatic	Method scala/collection/mutable/IndexedSeq$class.$init$:(Lscala/collection/mutable/IndexedSeq;)V
	aload_0
	invokestatic	Method scala/collection/mutable/ResizableArray$class.$init$:(Lscala/collection/mutable/ResizableArray;)V
	return
  Labels:
  LocalVariableTable: 
   Start  Length  Slot  Name   Signature
   0      73      0    this       Lscala/collection/mutable/PriorityQueue$ResizableArrayAccess;
   0      73      1    $outer       Lscala/collection/mutable/PriorityQueue;

  Signature: length = 0x2
   03 6B 

}

