Compiled from "PriorityQueue.scala"
public final class scala.collection.mutable.PriorityQueue$$anonfun$reverse$1 extends java.lang.Object implements scala.Function1,scala.ScalaObject,java.io.Serializable
  SourceFile: "PriorityQueue.scala"
  Scala: length = 0x
   
  InnerClass: 
   public final $anonfun$reverse$1=class scala/collection/mutable/PriorityQueue$$anonfun$reverse$1 of class scala/collection/mutable/PriorityQueue
   public ResizableArrayAccess=class scala/collection/mutable/PriorityQueue$ResizableArrayAccess of class scala/collection/mutable/PriorityQueue
  minor version: 0
  major version: 49
  Constant pool:
Asciz	SourceFile;
Asciz	PriorityQueue.scala;
Asciz	<clinit>;
Asciz	()V;
Asciz	Code;
Asciz	serialVersionUID;
Asciz	J;
Asciz	scala/collection/mutable/PriorityQueue$$anonfun$reverse$1;
class	scala/collection/mutable/PriorityQueue$$anonfun$reverse$1
NameAndType	serialVersionUID:J
Field	scala/collection/mutable/PriorityQueue$$anonfun$reverse$1.serialVersionUID:J
Asciz	revq$1;
Asciz	Lscala/collection/mutable/PriorityQueue;;
Asciz	$outer;
Asciz	<init>;
Asciz	(Lscala/collection/mutable/PriorityQueue;Lscala/collection/mutable/PriorityQueue;)V;
Asciz	LineNumberTable;
Asciz	java/lang/NullPointerException;
class	java/lang/NullPointerException
NameAndType	"<init>":()V
Method	java/lang/NullPointerException."<init>":()V
NameAndType	$outer:Lscala/collection/mutable/PriorityQueue;
Field	scala/collection/mutable/PriorityQueue$$anonfun$reverse$1.$outer:Lscala/collection/mutable/PriorityQueue;
NameAndType	revq$1:Lscala/collection/mutable/PriorityQueue;
Field	scala/collection/mutable/PriorityQueue$$anonfun$reverse$1.revq$1:Lscala/collection/mutable/PriorityQueue;
Asciz	java/lang/Object;
class	java/lang/Object
Method	java/lang/Object."<init>":()V
Asciz	scala/Function1$class;
class	scala/Function1$class
Asciz	$init$;
Asciz	(Lscala/Function1;)V;
NameAndType	$init$:(Lscala/Function1;)V
Method	scala/Function1$class.$init$:(Lscala/Function1;)V
Asciz	this;
Asciz	Lscala/collection/mutable/PriorityQueue$$anonfun$reverse$1;;
Asciz	LocalVariableTable;
Asciz	(Lscala/collection/mutable/PriorityQueue<TA;>;)V;
Asciz	Signature;
Asciz	apply;
Asciz	(Ljava/lang/Object;)Ljava/lang/Object;;
Asciz	scala/runtime/BoxesRunTime;
class	scala/runtime/BoxesRunTime
Asciz	unboxToInt;
Asciz	(Ljava/lang/Object;)I;
NameAndType	unboxToInt:(Ljava/lang/Object;)I
Method	scala/runtime/BoxesRunTime.unboxToInt:(Ljava/lang/Object;)I
Asciz	(I)Lscala/collection/mutable/PriorityQueue;;
NameAndType	apply:(I)Lscala/collection/mutable/PriorityQueue;
Method	scala/collection/mutable/PriorityQueue$$anonfun$reverse$1.apply:(I)Lscala/collection/mutable/PriorityQueue;
Asciz	v1;
Asciz	Ljava/lang/Object;;
Asciz	scala/collection/mutable/PriorityQueue;
class	scala/collection/mutable/PriorityQueue
Asciz	scala$collection$mutable$PriorityQueue$$resarr;
Asciz	()Lscala/collection/mutable/PriorityQueue$ResizableArrayAccess;;
NameAndType	scala$collection$mutable$PriorityQueue$$resarr:()Lscala/collection/mutable/PriorityQueue$ResizableArrayAccess;
Method	scala/collection/mutable/PriorityQueue.scala$collection$mutable$PriorityQueue$$resarr:()Lscala/collection/mutable/PriorityQueue$ResizableArrayAccess;
Asciz	scala/collection/mutable/ResizableArray;
class	scala/collection/mutable/ResizableArray
Asciz	(I)Ljava/lang/Object;;
NameAndType	apply:(I)Ljava/lang/Object;
InterfaceMethod	scala/collection/mutable/ResizableArray.apply:(I)Ljava/lang/Object;
Asciz	$plus$eq;
Asciz	(Ljava/lang/Object;)Lscala/collection/mutable/PriorityQueue;;
NameAndType	$plus$eq:(Ljava/lang/Object;)Lscala/collection/mutable/PriorityQueue;
Method	scala/collection/mutable/PriorityQueue.$plus$eq:(Ljava/lang/Object;)Lscala/collection/mutable/PriorityQueue;
Asciz	i;
Asciz	I;
Asciz	(I)Lscala/collection/mutable/PriorityQueue<TA;>;;
Asciz	andThen;
Asciz	(Lscala/Function1;)Lscala/Function1;;
Asciz	(Lscala/Function1;Lscala/Function1;)Lscala/Function1;;
NameAndType	andThen:(Lscala/Function1;Lscala/Function1;)Lscala/Function1;
Method	scala/Function1$class.andThen:(Lscala/Function1;Lscala/Function1;)Lscala/Function1;
Asciz	g;
Asciz	Lscala/Function1;;
Asciz	compose;
NameAndType	compose:(Lscala/Function1;Lscala/Function1;)Lscala/Function1;
Method	scala/Function1$class.compose:(Lscala/Function1;Lscala/Function1;)Lscala/Function1;
Asciz	toString;
Asciz	()Ljava/lang/String;;
Asciz	(Lscala/Function1;)Ljava/lang/String;;
NameAndType	toString:(Lscala/Function1;)Ljava/lang/String;
Method	scala/Function1$class.toString:(Lscala/Function1;)Ljava/lang/String;
Asciz	Scala;
Asciz	InnerClasses;
Asciz	$anonfun$reverse$1;
Asciz	scala/collection/mutable/PriorityQueue$ResizableArrayAccess;
class	scala/collection/mutable/PriorityQueue$ResizableArrayAccess
Asciz	ResizableArrayAccess;
Asciz	scala/Function1;
class	scala/Function1
Asciz	scala/ScalaObject;
class	scala/ScalaObject
Asciz	java/io/Serializable;
class	java/io/Serializable

{
public static final long serialVersionUID;
  Signature: J

private final scala.collection.mutable.PriorityQueue revq$1;
  Signature: Lscala/collection/mutable/PriorityQueue;

private final scala.collection.mutable.PriorityQueue $outer;
  Signature: Lscala/collection/mutable/PriorityQueue;

public static {};
  Signature: ()V
  Code:
   Stack=2, Locals=0, Args_size=0
	lconst_0
	putstatic	Field serialVersionUID:J
	return
  Labels:

public scala.collection.mutable.PriorityQueue$$anonfun$reverse$1(scala.collection.mutable.PriorityQueue, scala.collection.mutable.PriorityQueue);
  Signature: (Lscala/collection/mutable/PriorityQueue;Lscala/collection/mutable/PriorityQueue;)V
  Code:
   Stack=2, Locals=3, Args_size=3
	aload_1
	ifnonnull	l1 // aload_0
	new	class java/lang/NullPointerException
	dup
	invokespecial	Method java/lang/NullPointerException."<init>":()V
	athrow
l1	aload_0
	aload_1
	putfield	Field $outer:Lscala/collection/mutable/PriorityQueue;
	aload_0
	aload_2
	putfield	Field revq$1:Lscala/collection/mutable/PriorityQueue;
	aload_0
	invokespecial	Method java/lang/Object."<init>":()V
	aload_0
	invokestatic	Method scala/Function1$class.$init$:(Lscala/Function1;)V
	return
  Labels:
   	l1 = 12 // aload_0
  LocalVariableTable: 
   Start  Length  Slot  Name   Signature
   0      31      0    this       Lscala/collection/mutable/PriorityQueue$$anonfun$reverse$1;
   0      31      1    $outer       Lscala/collection/mutable/PriorityQueue;

  Signature: length = 0x2
   00 26 

public final java.lang.Object apply(java.lang.Object);
  Signature: (Ljava/lang/Object;)Ljava/lang/Object;
  Code:
   Stack=2, Locals=3, Args_size=2
	aload_0
	getfield	Field $outer:Lscala/collection/mutable/PriorityQueue;
	astore_2
	aload_0
	aload_1
	invokestatic	Method scala/runtime/BoxesRunTime.unboxToInt:(Ljava/lang/Object;)I
	invokevirtual	Method apply:(I)Lscala/collection/mutable/PriorityQueue;
	areturn
  Labels:
  LocalVariableTable: 
   Start  Length  Slot  Name   Signature
   0      14      0    this       Lscala/collection/mutable/PriorityQueue$$anonfun$reverse$1;
   5      9      1    v1       Ljava/lang/Object;


public final scala.collection.mutable.PriorityQueue apply(int);
  Signature: (I)Lscala/collection/mutable/PriorityQueue;
  Code:
   Stack=3, Locals=3, Args_size=2
	aload_0
	getfield	Field $outer:Lscala/collection/mutable/PriorityQueue;
	astore_2
	aload_0
	getfield	Field revq$1:Lscala/collection/mutable/PriorityQueue;
	aload_0
	getfield	Field $outer:Lscala/collection/mutable/PriorityQueue;
	invokevirtual	Method scala/collection/mutable/PriorityQueue.scala$collection$mutable$PriorityQueue$$resarr:()Lscala/collection/mutable/PriorityQueue$ResizableArrayAccess;
	iload_1
	invokeinterface	InterfaceMethod scala/collection/mutable/ResizableArray.apply:(I)Ljava/lang/Object;
	invokevirtual	Method scala/collection/mutable/PriorityQueue.$plus$eq:(Ljava/lang/Object;)Lscala/collection/mutable/PriorityQueue;
	areturn
  Labels:
  LocalVariableTable: 
   Start  Length  Slot  Name   Signature
   0      26      0    this       Lscala/collection/mutable/PriorityQueue$$anonfun$reverse$1;
   5      21      1    i       I

  Signature: length = 0x2
   00 46 

public scala.Function1 andThen(scala.Function1);
  Signature: (Lscala/Function1;)Lscala/Function1;
  Code:
   Stack=2, Locals=2, Args_size=2
	aload_0
	aload_1
	invokestatic	Method scala/Function1$class.andThen:(Lscala/Function1;Lscala/Function1;)Lscala/Function1;
	areturn
  Labels:
  LocalVariableTable: 
   Start  Length  Slot  Name   Signature
   0      6      0    this       Lscala/collection/mutable/PriorityQueue$$anonfun$reverse$1;
   0      6      1    g       Lscala/Function1;


public scala.Function1 compose(scala.Function1);
  Signature: (Lscala/Function1;)Lscala/Function1;
  Code:
   Stack=2, Locals=2, Args_size=2
	aload_0
	aload_1
	invokestatic	Method scala/Function1$class.compose:(Lscala/Function1;Lscala/Function1;)Lscala/Function1;
	areturn
  Labels:
  LocalVariableTable: 
   Start  Length  Slot  Name   Signature
   0      6      0    this       Lscala/collection/mutable/PriorityQueue$$anonfun$reverse$1;
   0      6      1    g       Lscala/Function1;


public java.lang.String toString();
  Signature: ()Ljava/lang/String;
  Code:
   Stack=1, Locals=1, Args_size=1
	aload_0
	invokestatic	Method scala/Function1$class.toString:(Lscala/Function1;)Ljava/lang/String;
	areturn
  Labels:

}

