Compiled from "PriorityQueueProxy.scala"
public final class scala.collection.mutable.PriorityQueueProxy$$anon$1 extends scala.collection.mutable.PriorityQueueProxy
  SourceFile: "PriorityQueueProxy.scala"
  Signature: length = 0x2
   00 2C 
  Scala: length = 0x
   
  InnerClass: 
   public final #47= #15 of #19; //$anon$1=class scala/collection/mutable/PriorityQueueProxy$$anon$1 of class scala/collection/mutable/PriorityQueueProxy
  minor version: 0
  major version: 49
  Constant pool:
const #1 = Asciz	SourceFile;
const #2 = Asciz	PriorityQueueProxy.scala;
const #3 = Asciz	$outer;
const #4 = Asciz	Lscala/collection/mutable/PriorityQueueProxy;;
const #5 = Asciz	<init>;
const #6 = Asciz	(Lscala/collection/mutable/PriorityQueueProxy;)V;
const #7 = Asciz	Code;
const #8 = Asciz	LineNumberTable;
const #9 = Asciz	java/lang/NullPointerException;
const #10 = class	#9;	//  java/lang/NullPointerException
const #11 = Asciz	()V;
const #12 = NameAndType	#5:#11;//  "<init>":()V
const #13 = Method	#10.#12;	//  java/lang/NullPointerException."<init>":()V
const #14 = Asciz	scala/collection/mutable/PriorityQueueProxy$$anon$1;
const #15 = class	#14;	//  scala/collection/mutable/PriorityQueueProxy$$anon$1
const #16 = NameAndType	#3:#4;//  $outer:Lscala/collection/mutable/PriorityQueueProxy;
const #17 = Field	#15.#16;	//  scala/collection/mutable/PriorityQueueProxy$$anon$1.$outer:Lscala/collection/mutable/PriorityQueueProxy;
const #18 = Asciz	scala/collection/mutable/PriorityQueueProxy;
const #19 = class	#18;	//  scala/collection/mutable/PriorityQueueProxy
const #20 = Asciz	scala$collection$mutable$PriorityQueueProxy$$ord;
const #21 = Asciz	Lscala/math/Ordering;;
const #22 = NameAndType	#20:#21;//  scala$collection$mutable$PriorityQueueProxy$$ord:Lscala/math/Ordering;
const #23 = Field	#19.#22;	//  scala/collection/mutable/PriorityQueueProxy.scala$collection$mutable$PriorityQueueProxy$$ord:Lscala/math/Ordering;
const #24 = Asciz	(Lscala/math/Ordering;)V;
const #25 = NameAndType	#5:#24;//  "<init>":(Lscala/math/Ordering;)V
const #26 = Method	#19.#25;	//  scala/collection/mutable/PriorityQueueProxy."<init>":(Lscala/math/Ordering;)V
const #27 = Asciz	this;
const #28 = Asciz	Lscala/collection/mutable/PriorityQueueProxy$$anon$1;;
const #29 = Asciz	LocalVariableTable;
const #30 = Asciz	(Lscala/collection/mutable/PriorityQueueProxy<TA;>;)V;
const #31 = Asciz	Signature;
const #32 = Asciz	self;
const #33 = Asciz	()Ljava/lang/Object;;
const #34 = Asciz	()Lscala/collection/mutable/PriorityQueue;;
const #35 = NameAndType	#32:#34;//  self:()Lscala/collection/mutable/PriorityQueue;
const #36 = Method	#15.#35;	//  scala/collection/mutable/PriorityQueueProxy$$anon$1.self:()Lscala/collection/mutable/PriorityQueue;
const #37 = Method	#19.#35;	//  scala/collection/mutable/PriorityQueueProxy.self:()Lscala/collection/mutable/PriorityQueue;
const #38 = Asciz	scala/collection/mutable/PriorityQueue;
const #39 = class	#38;	//  scala/collection/mutable/PriorityQueue
const #40 = Asciz	clone;
const #41 = NameAndType	#40:#34;//  clone:()Lscala/collection/mutable/PriorityQueue;
const #42 = Method	#39.#41;	//  scala/collection/mutable/PriorityQueue.clone:()Lscala/collection/mutable/PriorityQueue;
const #43 = Asciz	()Lscala/collection/mutable/PriorityQueue<TA;>;;
const #44 = Asciz	Lscala/collection/mutable/PriorityQueueProxy<TA;>;;
const #45 = Asciz	Scala;
const #46 = Asciz	InnerClasses;
const #47 = Asciz	$anon$1;

{
public scala.collection.mutable.PriorityQueueProxy$$anon$1(scala.collection.mutable.PriorityQueueProxy);
  Code:
   Stack=2, Locals=2, Args_size=2
   0:	aload_1
   1:	ifnonnull	12
   4:	new	#10; //class java/lang/NullPointerException
   7:	dup
   8:	invokespecial	#13; //Method java/lang/NullPointerException."<init>":()V
   11:	athrow
   12:	aload_0
   13:	aload_1
   14:	putfield	#17; //Field $outer:Lscala/collection/mutable/PriorityQueueProxy;
   17:	aload_0
   18:	aload_1
   19:	getfield	#23; //Field scala/collection/mutable/PriorityQueueProxy.scala$collection$mutable$PriorityQueueProxy$$ord:Lscala/math/Ordering;
   22:	invokespecial	#26; //Method scala/collection/mutable/PriorityQueueProxy."<init>":(Lscala/math/Ordering;)V
   25:	return
  LineNumberTable: 
   line 103: 0

  LocalVariableTable: 
   Start  Length  Slot  Name   Signature
   0      26      0    this       Lscala/collection/mutable/PriorityQueueProxy$$anon$1;
   0      26      1    $outer       Lscala/collection/mutable/PriorityQueueProxy;

  Signature: length = 0x2
   00 1E 

public java.lang.Object self();
  Code:
   Stack=1, Locals=1, Args_size=1
   0:	aload_0
   1:	invokevirtual	#36; //Method self:()Lscala/collection/mutable/PriorityQueue;
   4:	areturn
  LineNumberTable: 
   line 103: 0


public scala.collection.mutable.PriorityQueue self();
  Code:
   Stack=1, Locals=1, Args_size=1
   0:	aload_0
   1:	getfield	#17; //Field $outer:Lscala/collection/mutable/PriorityQueueProxy;
   4:	invokevirtual	#37; //Method scala/collection/mutable/PriorityQueueProxy.self:()Lscala/collection/mutable/PriorityQueue;
   7:	invokevirtual	#42; //Method scala/collection/mutable/PriorityQueue.clone:()Lscala/collection/mutable/PriorityQueue;
   10:	areturn
  LineNumberTable: 
   line 104: 0

  Signature: length = 0x2
   00 2B 

}

