Compiled from "Publisher.scala"
public abstract class scala.collection.mutable.Publisher$class extends java.lang.Object
  SourceFile: "Publisher.scala"
  Scala: length = 0x
   
  InnerClass: 
   public final #117= #13 of #8; //$anon$1=class scala/collection/mutable/Publisher$$anon$1 of class scala/collection/mutable/Publisher
   public final #118= #69 of #8; //$anonfun$publish$1=class scala/collection/mutable/Publisher$$anonfun$publish$1 of class scala/collection/mutable/Publisher
   public final #119= #110 of #8; //$anonfun$subscribe$1=class scala/collection/mutable/Publisher$$anonfun$subscribe$1 of class scala/collection/mutable/Publisher
  minor version: 0
  major version: 49
  Constant pool:
const #1 = Asciz	SourceFile;
const #2 = Asciz	Publisher.scala;
const #3 = Asciz	$init$;
const #4 = Asciz	(Lscala/collection/mutable/Publisher;)V;
const #5 = Asciz	Code;
const #6 = Asciz	LineNumberTable;
const #7 = Asciz	scala/collection/mutable/Publisher;
const #8 = class	#7;	//  scala/collection/mutable/Publisher
const #9 = Asciz	scala$collection$mutable$Publisher$_setter_$self_$eq;
const #10 = NameAndType	#9:#4;//  scala$collection$mutable$Publisher$_setter_$self_$eq:(Lscala/collection/mutable/Publisher;)V
const #11 = InterfaceMethod	#8.#10;	//  scala/collection/mutable/Publisher.scala$collection$mutable$Publisher$_setter_$self_$eq:(Lscala/collection/mutable/Publisher;)V
const #12 = Asciz	scala/collection/mutable/Publisher$$anon$1;
const #13 = class	#12;	//  scala/collection/mutable/Publisher$$anon$1
const #14 = Asciz	<init>;
const #15 = NameAndType	#14:#4;//  "<init>":(Lscala/collection/mutable/Publisher;)V
const #16 = Method	#13.#15;	//  scala/collection/mutable/Publisher$$anon$1."<init>":(Lscala/collection/mutable/Publisher;)V
const #17 = Asciz	scala$collection$mutable$Publisher$_setter_$scala$collection$mutable$Publisher$$filters_$eq;
const #18 = Asciz	(Lscala/collection/mutable/HashMap;)V;
const #19 = NameAndType	#17:#18;//  scala$collection$mutable$Publisher$_setter_$scala$collection$mutable$Publisher$$filters_$eq:(Lscala/collection/mutable/HashMap;)V
const #20 = InterfaceMethod	#8.#19;	//  scala/collection/mutable/Publisher.scala$collection$mutable$Publisher$_setter_$scala$collection$mutable$Publisher$$filters_$eq:(Lscala/collection/mutable/HashMap;)V
const #21 = Asciz	scala/collection/mutable/HashSet;
const #22 = class	#21;	//  scala/collection/mutable/HashSet
const #23 = Asciz	()V;
const #24 = NameAndType	#14:#23;//  "<init>":()V
const #25 = Method	#22.#24;	//  scala/collection/mutable/HashSet."<init>":()V
const #26 = Asciz	scala$collection$mutable$Publisher$_setter_$scala$collection$mutable$Publisher$$suspended_$eq;
const #27 = Asciz	(Lscala/collection/mutable/HashSet;)V;
const #28 = NameAndType	#26:#27;//  scala$collection$mutable$Publisher$_setter_$scala$collection$mutable$Publisher$$suspended_$eq:(Lscala/collection/mutable/HashSet;)V
const #29 = InterfaceMethod	#8.#28;	//  scala/collection/mutable/Publisher.scala$collection$mutable$Publisher$_setter_$scala$collection$mutable$Publisher$$suspended_$eq:(Lscala/collection/mutable/HashSet;)V
const #30 = Asciz	$this;
const #31 = Asciz	Lscala/collection/mutable/Publisher;;
const #32 = Asciz	LocalVariableTable;
const #33 = Asciz	equals;
const #34 = Asciz	(Lscala/collection/mutable/Publisher;Ljava/lang/Object;)Z;
const #35 = Asciz	scala$collection$mutable$Publisher$$filters;
const #36 = Asciz	()Lscala/collection/mutable/HashMap;;
const #37 = NameAndType	#35:#36;//  scala$collection$mutable$Publisher$$filters:()Lscala/collection/mutable/HashMap;
const #38 = InterfaceMethod	#8.#37;	//  scala/collection/mutable/Publisher.scala$collection$mutable$Publisher$$filters:()Lscala/collection/mutable/HashMap;
const #39 = Asciz	java/lang/Object;
const #40 = class	#39;	//  java/lang/Object
const #41 = Asciz	(Ljava/lang/Object;)Z;
const #42 = NameAndType	#33:#41;//  equals:(Ljava/lang/Object;)Z
const #43 = Method	#40.#42;	//  java/lang/Object.equals:(Ljava/lang/Object;)Z
const #44 = Asciz	scala$collection$mutable$Publisher$$suspended;
const #45 = Asciz	()Lscala/collection/mutable/HashSet;;
const #46 = NameAndType	#44:#45;//  scala$collection$mutable$Publisher$$suspended:()Lscala/collection/mutable/HashSet;
const #47 = InterfaceMethod	#8.#46;	//  scala/collection/mutable/Publisher.scala$collection$mutable$Publisher$$suspended:()Lscala/collection/mutable/HashSet;
const #48 = Asciz	scala/MatchError;
const #49 = class	#48;	//  scala/MatchError
const #50 = Asciz	toString;
const #51 = Asciz	()Ljava/lang/String;;
const #52 = NameAndType	#50:#51;//  toString:()Ljava/lang/String;
const #53 = Method	#40.#52;	//  java/lang/Object.toString:()Ljava/lang/String;
const #54 = Asciz	(Ljava/lang/String;)V;
const #55 = NameAndType	#14:#54;//  "<init>":(Ljava/lang/String;)V
const #56 = Method	#49.#55;	//  scala/MatchError."<init>":(Ljava/lang/String;)V
const #57 = Asciz	obj;
const #58 = Asciz	Ljava/lang/Object;;
const #59 = Asciz	temp2;
const #60 = Asciz	publish;
const #61 = Asciz	(Lscala/collection/mutable/Publisher;Ljava/lang/Object;)V;
const #62 = Asciz	scala/collection/mutable/HashMap;
const #63 = class	#62;	//  scala/collection/mutable/HashMap
const #64 = Asciz	keysIterator;
const #65 = Asciz	()Lscala/collection/Iterator;;
const #66 = NameAndType	#64:#65;//  keysIterator:()Lscala/collection/Iterator;
const #67 = Method	#63.#66;	//  scala/collection/mutable/HashMap.keysIterator:()Lscala/collection/Iterator;
const #68 = Asciz	scala/collection/mutable/Publisher$$anonfun$publish$1;
const #69 = class	#68;	//  scala/collection/mutable/Publisher$$anonfun$publish$1
const #70 = NameAndType	#14:#61;//  "<init>":(Lscala/collection/mutable/Publisher;Ljava/lang/Object;)V
const #71 = Method	#69.#70;	//  scala/collection/mutable/Publisher$$anonfun$publish$1."<init>":(Lscala/collection/mutable/Publisher;Ljava/lang/Object;)V
const #72 = Asciz	scala/collection/Iterator;
const #73 = class	#72;	//  scala/collection/Iterator
const #74 = Asciz	foreach;
const #75 = Asciz	(Lscala/Function1;)V;
const #76 = NameAndType	#74:#75;//  foreach:(Lscala/Function1;)V
const #77 = InterfaceMethod	#73.#76;	//  scala/collection/Iterator.foreach:(Lscala/Function1;)V
const #78 = Asciz	event$1;
const #79 = Asciz	removeSubscriptions;
const #80 = Asciz	clear;
const #81 = NameAndType	#80:#23;//  clear:()V
const #82 = Method	#63.#81;	//  scala/collection/mutable/HashMap.clear:()V
const #83 = Asciz	removeSubscription;
const #84 = Asciz	(Lscala/collection/mutable/Publisher;Lscala/collection/mutable/Subscriber;)V;
const #85 = Asciz	$minus$eq;
const #86 = Asciz	(Ljava/lang/Object;)Lscala/collection/mutable/HashMap;;
const #87 = NameAndType	#85:#86;//  $minus$eq:(Ljava/lang/Object;)Lscala/collection/mutable/HashMap;
const #88 = Method	#63.#87;	//  scala/collection/mutable/HashMap.$minus$eq:(Ljava/lang/Object;)Lscala/collection/mutable/HashMap;
const #89 = Asciz	sub;
const #90 = Asciz	Lscala/collection/mutable/Subscriber;;
const #91 = Asciz	activateSubscription;
const #92 = Asciz	(Ljava/lang/Object;)Lscala/collection/mutable/HashSet;;
const #93 = NameAndType	#85:#92;//  $minus$eq:(Ljava/lang/Object;)Lscala/collection/mutable/HashSet;
const #94 = Method	#22.#93;	//  scala/collection/mutable/HashSet.$minus$eq:(Ljava/lang/Object;)Lscala/collection/mutable/HashSet;
const #95 = Asciz	suspendSubscription;
const #96 = Asciz	$plus$eq;
const #97 = NameAndType	#96:#92;//  $plus$eq:(Ljava/lang/Object;)Lscala/collection/mutable/HashSet;
const #98 = Method	#22.#97;	//  scala/collection/mutable/HashSet.$plus$eq:(Ljava/lang/Object;)Lscala/collection/mutable/HashSet;
const #99 = Asciz	subscribe;
const #100 = Asciz	(Lscala/collection/mutable/Publisher;Lscala/collection/mutable/Subscriber;Lscala/Function1;)V;
const #101 = Asciz	scala/collection/mutable/MultiMap;
const #102 = class	#101;	//  scala/collection/mutable/MultiMap
const #103 = Asciz	addBinding;
const #104 = Asciz	(Ljava/lang/Object;Ljava/lang/Object;)Lscala/collection/mutable/MultiMap;;
const #105 = NameAndType	#103:#104;//  addBinding:(Ljava/lang/Object;Ljava/lang/Object;)Lscala/collection/mutable/MultiMap;
const #106 = InterfaceMethod	#102.#105;	//  scala/collection/mutable/MultiMap.addBinding:(Ljava/lang/Object;Ljava/lang/Object;)Lscala/collection/mutable/MultiMap;
const #107 = Asciz	filter;
const #108 = Asciz	Lscala/Function1;;
const #109 = Asciz	scala/collection/mutable/Publisher$$anonfun$subscribe$1;
const #110 = class	#109;	//  scala/collection/mutable/Publisher$$anonfun$subscribe$1
const #111 = Method	#110.#15;	//  scala/collection/mutable/Publisher$$anonfun$subscribe$1."<init>":(Lscala/collection/mutable/Publisher;)V
const #112 = Asciz	(Lscala/collection/mutable/Subscriber;Lscala/Function1;)V;
const #113 = NameAndType	#99:#112;//  subscribe:(Lscala/collection/mutable/Subscriber;Lscala/Function1;)V
const #114 = InterfaceMethod	#8.#113;	//  scala/collection/mutable/Publisher.subscribe:(Lscala/collection/mutable/Subscriber;Lscala/Function1;)V
const #115 = Asciz	Scala;
const #116 = Asciz	InnerClasses;
const #117 = Asciz	$anon$1;
const #118 = Asciz	$anonfun$publish$1;
const #119 = Asciz	$anonfun$subscribe$1;
const #120 = Asciz	scala/collection/mutable/Publisher$class;
const #121 = class	#120;	//  scala/collection/mutable/Publisher$class

{
public static void $init$(scala.collection.mutable.Publisher);
  Code:
   Stack=4, Locals=1, Args_size=1
   0:	aload_0
   1:	aload_0
   2:	invokeinterface	#11,  2; //InterfaceMethod scala/collection/mutable/Publisher.scala$collection$mutable$Publisher$_setter_$self_$eq:(Lscala/collection/mutable/Publisher;)V
   7:	aload_0
   8:	new	#13; //class scala/collection/mutable/Publisher$$anon$1
   11:	dup
   12:	aload_0
   13:	invokespecial	#16; //Method scala/collection/mutable/Publisher$$anon$1."<init>":(Lscala/collection/mutable/Publisher;)V
   16:	invokeinterface	#20,  2; //InterfaceMethod scala/collection/mutable/Publisher.scala$collection$mutable$Publisher$_setter_$scala$collection$mutable$Publisher$$filters_$eq:(Lscala/collection/mutable/HashMap;)V
   21:	aload_0
   22:	new	#22; //class scala/collection/mutable/HashSet
   25:	dup
   26:	invokespecial	#25; //Method scala/collection/mutable/HashSet."<init>":()V
   29:	invokeinterface	#29,  2; //InterfaceMethod scala/collection/mutable/Publisher.scala$collection$mutable$Publisher$_setter_$scala$collection$mutable$Publisher$$suspended_$eq:(Lscala/collection/mutable/HashSet;)V
   34:	return
  LineNumberTable: 
   line 37: 0
   line 39: 7
   line 40: 21

  LocalVariableTable: 
   Start  Length  Slot  Name   Signature
   0      35      0    $this       Lscala/collection/mutable/Publisher;


public static boolean equals(scala.collection.mutable.Publisher, java.lang.Object);
  Code:
   Stack=3, Locals=5, Args_size=2
   0:	aload_1
   1:	instanceof	#8; //class scala/collection/mutable/Publisher
   4:	ifeq	103
   7:	aload_1
   8:	checkcast	#8; //class scala/collection/mutable/Publisher
   11:	astore_3
   12:	iconst_1
   13:	ifeq	91
   16:	aload_0
   17:	invokeinterface	#38,  1; //InterfaceMethod scala/collection/mutable/Publisher.scala$collection$mutable$Publisher$$filters:()Lscala/collection/mutable/HashMap;
   22:	aload_3
   23:	invokeinterface	#38,  1; //InterfaceMethod scala/collection/mutable/Publisher.scala$collection$mutable$Publisher$$filters:()Lscala/collection/mutable/HashMap;
   28:	astore_2
   29:	dup
   30:	ifnonnull	41
   33:	pop
   34:	aload_2
   35:	ifnull	48
   38:	goto	87
   41:	aload_2
   42:	invokevirtual	#43; //Method java/lang/Object.equals:(Ljava/lang/Object;)Z
   45:	ifeq	87
   48:	aload_0
   49:	invokeinterface	#47,  1; //InterfaceMethod scala/collection/mutable/Publisher.scala$collection$mutable$Publisher$$suspended:()Lscala/collection/mutable/HashSet;
   54:	aload_3
   55:	invokeinterface	#47,  1; //InterfaceMethod scala/collection/mutable/Publisher.scala$collection$mutable$Publisher$$suspended:()Lscala/collection/mutable/HashSet;
   60:	astore	4
   62:	dup
   63:	ifnonnull	75
   66:	pop
   67:	aload	4
   69:	ifnull	83
   72:	goto	87
   75:	aload	4
   77:	invokevirtual	#43; //Method java/lang/Object.equals:(Ljava/lang/Object;)Z
   80:	ifeq	87
   83:	iconst_1
   84:	goto	108
   87:	iconst_0
   88:	goto	108
   91:	new	#49; //class scala/MatchError
   94:	dup
   95:	aload_1
   96:	invokevirtual	#53; //Method java/lang/Object.toString:()Ljava/lang/String;
   99:	invokespecial	#56; //Method scala/MatchError."<init>":(Ljava/lang/String;)V
   102:	athrow
   103:	iconst_1
   104:	ifeq	109
   107:	iconst_0
   108:	ireturn
   109:	new	#49; //class scala/MatchError
   112:	dup
   113:	aload_1
   114:	invokevirtual	#53; //Method java/lang/Object.toString:()Ljava/lang/String;
   117:	invokespecial	#56; //Method scala/MatchError."<init>":(Ljava/lang/String;)V
   120:	athrow
  LineNumberTable: 
   line 60: 0
   line 21: 12
   line 61: 16
   line 60: 91
   line 21: 103
   line 62: 107
   line 60: 108

  LocalVariableTable: 
   Start  Length  Slot  Name   Signature
   0      121      0    $this       Lscala/collection/mutable/Publisher;
   0      121      1    obj       Ljava/lang/Object;
   12      91      3    temp2       Lscala/collection/mutable/Publisher;


public static void publish(scala.collection.mutable.Publisher, java.lang.Object);
  Code:
   Stack=5, Locals=2, Args_size=2
   0:	aload_0
   1:	invokeinterface	#38,  1; //InterfaceMethod scala/collection/mutable/Publisher.scala$collection$mutable$Publisher$$filters:()Lscala/collection/mutable/HashMap;
   6:	invokevirtual	#67; //Method scala/collection/mutable/HashMap.keysIterator:()Lscala/collection/Iterator;
   9:	new	#69; //class scala/collection/mutable/Publisher$$anonfun$publish$1
   12:	dup
   13:	aload_0
   14:	aload_1
   15:	invokespecial	#71; //Method scala/collection/mutable/Publisher$$anonfun$publish$1."<init>":(Lscala/collection/mutable/Publisher;Ljava/lang/Object;)V
   18:	invokeinterface	#77,  2; //InterfaceMethod scala/collection/Iterator.foreach:(Lscala/Function1;)V
   23:	return
  LineNumberTable: 
   line 50: 0

  LocalVariableTable: 
   Start  Length  Slot  Name   Signature
   0      24      0    $this       Lscala/collection/mutable/Publisher;
   0      24      1    event$1       Ljava/lang/Object;


public static void removeSubscriptions(scala.collection.mutable.Publisher);
  Code:
   Stack=1, Locals=1, Args_size=1
   0:	aload_0
   1:	invokeinterface	#38,  1; //InterfaceMethod scala/collection/mutable/Publisher.scala$collection$mutable$Publisher$$filters:()Lscala/collection/mutable/HashMap;
   6:	invokevirtual	#82; //Method scala/collection/mutable/HashMap.clear:()V
   9:	return
  LineNumberTable: 
   line 47: 0

  LocalVariableTable: 
   Start  Length  Slot  Name   Signature
   0      10      0    $this       Lscala/collection/mutable/Publisher;


public static void removeSubscription(scala.collection.mutable.Publisher, scala.collection.mutable.Subscriber);
  Code:
   Stack=2, Locals=2, Args_size=2
   0:	aload_0
   1:	invokeinterface	#38,  1; //InterfaceMethod scala/collection/mutable/Publisher.scala$collection$mutable$Publisher$$filters:()Lscala/collection/mutable/HashMap;
   6:	aload_1
   7:	invokevirtual	#88; //Method scala/collection/mutable/HashMap.$minus$eq:(Ljava/lang/Object;)Lscala/collection/mutable/HashMap;
   10:	pop
   11:	return
  LineNumberTable: 
   line 46: 0

  LocalVariableTable: 
   Start  Length  Slot  Name   Signature
   0      12      0    $this       Lscala/collection/mutable/Publisher;
   0      12      1    sub       Lscala/collection/mutable/Subscriber;


public static void activateSubscription(scala.collection.mutable.Publisher, scala.collection.mutable.Subscriber);
  Code:
   Stack=2, Locals=2, Args_size=2
   0:	aload_0
   1:	invokeinterface	#47,  1; //InterfaceMethod scala/collection/mutable/Publisher.scala$collection$mutable$Publisher$$suspended:()Lscala/collection/mutable/HashSet;
   6:	aload_1
   7:	invokevirtual	#94; //Method scala/collection/mutable/HashSet.$minus$eq:(Ljava/lang/Object;)Lscala/collection/mutable/HashSet;
   10:	pop
   11:	return
  LineNumberTable: 
   line 45: 0

  LocalVariableTable: 
   Start  Length  Slot  Name   Signature
   0      12      0    $this       Lscala/collection/mutable/Publisher;
   0      12      1    sub       Lscala/collection/mutable/Subscriber;


public static void suspendSubscription(scala.collection.mutable.Publisher, scala.collection.mutable.Subscriber);
  Code:
   Stack=2, Locals=2, Args_size=2
   0:	aload_0
   1:	invokeinterface	#47,  1; //InterfaceMethod scala/collection/mutable/Publisher.scala$collection$mutable$Publisher$$suspended:()Lscala/collection/mutable/HashSet;
   6:	aload_1
   7:	invokevirtual	#98; //Method scala/collection/mutable/HashSet.$plus$eq:(Ljava/lang/Object;)Lscala/collection/mutable/HashSet;
   10:	pop
   11:	return
  LineNumberTable: 
   line 44: 0

  LocalVariableTable: 
   Start  Length  Slot  Name   Signature
   0      12      0    $this       Lscala/collection/mutable/Publisher;
   0      12      1    sub       Lscala/collection/mutable/Subscriber;


public static void subscribe(scala.collection.mutable.Publisher, scala.collection.mutable.Subscriber, scala.Function1);
  Code:
   Stack=3, Locals=3, Args_size=3
   0:	aload_0
   1:	invokeinterface	#38,  1; //InterfaceMethod scala/collection/mutable/Publisher.scala$collection$mutable$Publisher$$filters:()Lscala/collection/mutable/HashMap;
   6:	checkcast	#102; //class scala/collection/mutable/MultiMap
   9:	aload_1
   10:	aload_2
   11:	invokeinterface	#106,  3; //InterfaceMethod scala/collection/mutable/MultiMap.addBinding:(Ljava/lang/Object;Ljava/lang/Object;)Lscala/collection/mutable/MultiMap;
   16:	pop
   17:	return
  LineNumberTable: 
   line 43: 0

  LocalVariableTable: 
   Start  Length  Slot  Name   Signature
   0      18      0    $this       Lscala/collection/mutable/Publisher;
   0      18      1    sub       Lscala/collection/mutable/Subscriber;
   0      18      2    filter       Lscala/Function1;


public static void subscribe(scala.collection.mutable.Publisher, scala.collection.mutable.Subscriber);
  Code:
   Stack=5, Locals=2, Args_size=2
   0:	aload_0
   1:	aload_1
   2:	new	#110; //class scala/collection/mutable/Publisher$$anonfun$subscribe$1
   5:	dup
   6:	aload_0
   7:	invokespecial	#111; //Method scala/collection/mutable/Publisher$$anonfun$subscribe$1."<init>":(Lscala/collection/mutable/Publisher;)V
   10:	invokeinterface	#114,  3; //InterfaceMethod scala/collection/mutable/Publisher.subscribe:(Lscala/collection/mutable/Subscriber;Lscala/Function1;)V
   15:	return
  LineNumberTable: 
   line 42: 0

  LocalVariableTable: 
   Start  Length  Slot  Name   Signature
   0      16      0    $this       Lscala/collection/mutable/Publisher;
   0      16      1    sub       Lscala/collection/mutable/Subscriber;


}

