Compiled from "Publisher.scala"
public final class scala.collection.mutable.Publisher$$anon$1 extends scala.collection.mutable.HashMap implements scala.collection.mutable.MultiMap
  SourceFile: "Publisher.scala"
  Signature: length = 0x2
   00 30 
  Scala: length = 0x
   
  InnerClass: 
   public final #55= #52 of #54; //$anon$1=class scala/collection/mutable/Publisher$$anon$1 of class scala/collection/mutable/Publisher
  minor version: 0
  major version: 49
  Constant pool:
const #1 = Asciz	SourceFile;
const #2 = Asciz	Publisher.scala;
const #3 = Asciz	<init>;
const #4 = Asciz	(Lscala/collection/mutable/Publisher;)V;
const #5 = Asciz	Code;
const #6 = Asciz	LineNumberTable;
const #7 = Asciz	scala/collection/mutable/HashMap;
const #8 = class	#7;	//  scala/collection/mutable/HashMap
const #9 = Asciz	()V;
const #10 = NameAndType	#3:#9;//  "<init>":()V
const #11 = Method	#8.#10;	//  scala/collection/mutable/HashMap."<init>":()V
const #12 = Asciz	scala/collection/mutable/MultiMap$class;
const #13 = class	#12;	//  scala/collection/mutable/MultiMap$class
const #14 = Asciz	$init$;
const #15 = Asciz	(Lscala/collection/mutable/MultiMap;)V;
const #16 = NameAndType	#14:#15;//  $init$:(Lscala/collection/mutable/MultiMap;)V
const #17 = Method	#13.#16;	//  scala/collection/mutable/MultiMap$class.$init$:(Lscala/collection/mutable/MultiMap;)V
const #18 = Asciz	this;
const #19 = Asciz	Lscala/collection/mutable/Publisher$$anon$1;;
const #20 = Asciz	$outer;
const #21 = Asciz	Lscala/collection/mutable/Publisher;;
const #22 = Asciz	LocalVariableTable;
const #23 = Asciz	(Lscala/collection/mutable/Publisher$class;)V;
const #24 = Asciz	Signature;
const #25 = Asciz	entryExists;
const #26 = Asciz	(Ljava/lang/Object;Lscala/Function1;)Z;
const #27 = Asciz	(Lscala/collection/mutable/MultiMap;Ljava/lang/Object;Lscala/Function1;)Z;
const #28 = NameAndType	#25:#27;//  entryExists:(Lscala/collection/mutable/MultiMap;Ljava/lang/Object;Lscala/Function1;)Z
const #29 = Method	#13.#28;	//  scala/collection/mutable/MultiMap$class.entryExists:(Lscala/collection/mutable/MultiMap;Ljava/lang/Object;Lscala/Function1;)Z
const #30 = Asciz	key;
const #31 = Asciz	Ljava/lang/Object;;
const #32 = Asciz	p;
const #33 = Asciz	Lscala/Function1;;
const #34 = Asciz	removeBinding;
const #35 = Asciz	(Ljava/lang/Object;Ljava/lang/Object;)Lscala/collection/mutable/MultiMap;;
const #36 = Asciz	(Lscala/collection/mutable/MultiMap;Ljava/lang/Object;Ljava/lang/Object;)Lscala/collection/mutable/MultiMap;;
const #37 = NameAndType	#34:#36;//  removeBinding:(Lscala/collection/mutable/MultiMap;Ljava/lang/Object;Ljava/lang/Object;)Lscala/collection/mutable/MultiMap;
const #38 = Method	#13.#37;	//  scala/collection/mutable/MultiMap$class.removeBinding:(Lscala/collection/mutable/MultiMap;Ljava/lang/Object;Ljava/lang/Object;)Lscala/collection/mutable/MultiMap;
const #39 = Asciz	value;
const #40 = Asciz	addBinding;
const #41 = NameAndType	#40:#36;//  addBinding:(Lscala/collection/mutable/MultiMap;Ljava/lang/Object;Ljava/lang/Object;)Lscala/collection/mutable/MultiMap;
const #42 = Method	#13.#41;	//  scala/collection/mutable/MultiMap$class.addBinding:(Lscala/collection/mutable/MultiMap;Ljava/lang/Object;Ljava/lang/Object;)Lscala/collection/mutable/MultiMap;
const #43 = Asciz	makeSet;
const #44 = Asciz	()Lscala/collection/mutable/Set;;
const #45 = Asciz	(Lscala/collection/mutable/MultiMap;)Lscala/collection/mutable/Set;;
const #46 = NameAndType	#43:#45;//  makeSet:(Lscala/collection/mutable/MultiMap;)Lscala/collection/mutable/Set;
const #47 = Method	#13.#46;	//  scala/collection/mutable/MultiMap$class.makeSet:(Lscala/collection/mutable/MultiMap;)Lscala/collection/mutable/Set;
const #48 = Asciz	Lscala/collection/mutable/HashMap<Lscala/collection/mutable/Subscriber<TEvt;Lscala/collection/mutable/Publisher;>;Lscala/collection/mutable/Set<Lscala/Function1<TEvt;Ljava/lang/Boolean;>;>;>;Lscala/collection/mutable/MultiMap<Lscala/collection/mutable/Subscriber<TEvt;Lscala/collection/mutable/Publisher;>;Lscala/Function1<TEvt;Ljava/lang/Boolean;>;>;;
const #49 = Asciz	Scala;
const #50 = Asciz	InnerClasses;
const #51 = Asciz	scala/collection/mutable/Publisher$$anon$1;
const #52 = class	#51;	//  scala/collection/mutable/Publisher$$anon$1
const #53 = Asciz	scala/collection/mutable/Publisher;
const #54 = class	#53;	//  scala/collection/mutable/Publisher
const #55 = Asciz	$anon$1;
const #56 = Asciz	scala/collection/mutable/MultiMap;
const #57 = class	#56;	//  scala/collection/mutable/MultiMap

{
public scala.collection.mutable.Publisher$$anon$1(scala.collection.mutable.Publisher);
  Code:
   Stack=1, Locals=2, Args_size=2
   0:	aload_0
   1:	invokespecial	#11; //Method scala/collection/mutable/HashMap."<init>":()V
   4:	aload_0
   5:	invokestatic	#17; //Method scala/collection/mutable/MultiMap$class.$init$:(Lscala/collection/mutable/MultiMap;)V
   8:	return
  LineNumberTable: 
   line 39: 0

  LocalVariableTable: 
   Start  Length  Slot  Name   Signature
   0      9      0    this       Lscala/collection/mutable/Publisher$$anon$1;
   0      9      1    $outer       Lscala/collection/mutable/Publisher;

  Signature: length = 0x2
   00 17 

public boolean entryExists(java.lang.Object, scala.Function1);
  Code:
   Stack=3, Locals=3, Args_size=3
   0:	aload_0
   1:	aload_1
   2:	aload_2
   3:	invokestatic	#29; //Method scala/collection/mutable/MultiMap$class.entryExists:(Lscala/collection/mutable/MultiMap;Ljava/lang/Object;Lscala/Function1;)Z
   6:	ireturn
  LineNumberTable: 
   line 39: 0

  LocalVariableTable: 
   Start  Length  Slot  Name   Signature
   0      7      0    this       Lscala/collection/mutable/Publisher$$anon$1;
   0      7      1    key       Ljava/lang/Object;
   0      7      2    p       Lscala/Function1;


public scala.collection.mutable.MultiMap removeBinding(java.lang.Object, java.lang.Object);
  Code:
   Stack=3, Locals=3, Args_size=3
   0:	aload_0
   1:	aload_1
   2:	aload_2
   3:	invokestatic	#38; //Method scala/collection/mutable/MultiMap$class.removeBinding:(Lscala/collection/mutable/MultiMap;Ljava/lang/Object;Ljava/lang/Object;)Lscala/collection/mutable/MultiMap;
   6:	areturn
  LineNumberTable: 
   line 39: 0

  LocalVariableTable: 
   Start  Length  Slot  Name   Signature
   0      7      0    this       Lscala/collection/mutable/Publisher$$anon$1;
   0      7      1    key       Ljava/lang/Object;
   0      7      2    value       Ljava/lang/Object;


public scala.collection.mutable.MultiMap addBinding(java.lang.Object, java.lang.Object);
  Code:
   Stack=3, Locals=3, Args_size=3
   0:	aload_0
   1:	aload_1
   2:	aload_2
   3:	invokestatic	#42; //Method scala/collection/mutable/MultiMap$class.addBinding:(Lscala/collection/mutable/MultiMap;Ljava/lang/Object;Ljava/lang/Object;)Lscala/collection/mutable/MultiMap;
   6:	areturn
  LineNumberTable: 
   line 39: 0

  LocalVariableTable: 
   Start  Length  Slot  Name   Signature
   0      7      0    this       Lscala/collection/mutable/Publisher$$anon$1;
   0      7      1    key       Ljava/lang/Object;
   0      7      2    value       Ljava/lang/Object;


public scala.collection.mutable.Set makeSet();
  Code:
   Stack=1, Locals=1, Args_size=1
   0:	aload_0
   1:	invokestatic	#47; //Method scala/collection/mutable/MultiMap$class.makeSet:(Lscala/collection/mutable/MultiMap;)Lscala/collection/mutable/Set;
   4:	areturn
  LineNumberTable: 
   line 39: 0


}

