Compiled from "QueueProxy.scala"
public final class scala.collection.mutable.QueueProxy$$anon$1 extends scala.collection.mutable.Queue implements scala.collection.mutable.QueueProxy
  SourceFile: "QueueProxy.scala"
  Signature: length = 0x2
   00 FFFFFF99 
  Scala: length = 0x
   
  InnerClass: 
   public final #156= #15 of #50; //$anon$1=class scala/collection/mutable/QueueProxy$$anon$1 of class scala/collection/mutable/QueueProxy
  minor version: 0
  major version: 49
  Constant pool:
const #1 = Asciz	SourceFile;
const #2 = Asciz	QueueProxy.scala;
const #3 = Asciz	$outer;
const #4 = Asciz	Lscala/collection/mutable/QueueProxy;;
const #5 = Asciz	<init>;
const #6 = Asciz	(Lscala/collection/mutable/QueueProxy;)V;
const #7 = Asciz	Code;
const #8 = Asciz	LineNumberTable;
const #9 = Asciz	java/lang/NullPointerException;
const #10 = class	#9;	//  java/lang/NullPointerException
const #11 = Asciz	()V;
const #12 = NameAndType	#5:#11;//  "<init>":()V
const #13 = Method	#10.#12;	//  java/lang/NullPointerException."<init>":()V
const #14 = Asciz	scala/collection/mutable/QueueProxy$$anon$1;
const #15 = class	#14;	//  scala/collection/mutable/QueueProxy$$anon$1
const #16 = NameAndType	#3:#4;//  $outer:Lscala/collection/mutable/QueueProxy;
const #17 = Field	#15.#16;	//  scala/collection/mutable/QueueProxy$$anon$1.$outer:Lscala/collection/mutable/QueueProxy;
const #18 = Asciz	scala/collection/mutable/Queue;
const #19 = class	#18;	//  scala/collection/mutable/Queue
const #20 = Method	#19.#12;	//  scala/collection/mutable/Queue."<init>":()V
const #21 = Asciz	scala/Proxy$class;
const #22 = class	#21;	//  scala/Proxy$class
const #23 = Asciz	$init$;
const #24 = Asciz	(Lscala/Proxy;)V;
const #25 = NameAndType	#23:#24;//  $init$:(Lscala/Proxy;)V
const #26 = Method	#22.#25;	//  scala/Proxy$class.$init$:(Lscala/Proxy;)V
const #27 = Asciz	scala/collection/mutable/QueueProxy$class;
const #28 = class	#27;	//  scala/collection/mutable/QueueProxy$class
const #29 = NameAndType	#23:#6;//  $init$:(Lscala/collection/mutable/QueueProxy;)V
const #30 = Method	#28.#29;	//  scala/collection/mutable/QueueProxy$class.$init$:(Lscala/collection/mutable/QueueProxy;)V
const #31 = Asciz	this;
const #32 = Asciz	Lscala/collection/mutable/QueueProxy$$anon$1;;
const #33 = Asciz	LocalVariableTable;
const #34 = Asciz	(Lscala/collection/mutable/QueueProxy<TA;>;)V;
const #35 = Asciz	Signature;
const #36 = Asciz	self;
const #37 = Asciz	()Ljava/lang/Object;;
const #38 = Asciz	()Lscala/collection/mutable/Queue;;
const #39 = NameAndType	#36:#38;//  self:()Lscala/collection/mutable/Queue;
const #40 = Method	#15.#39;	//  scala/collection/mutable/QueueProxy$$anon$1.self:()Lscala/collection/mutable/Queue;
const #41 = Asciz	apply;
const #42 = Asciz	(Ljava/lang/Object;)Ljava/lang/Object;;
const #43 = Asciz	scala/runtime/BoxesRunTime;
const #44 = class	#43;	//  scala/runtime/BoxesRunTime
const #45 = Asciz	unboxToInt;
const #46 = Asciz	(Ljava/lang/Object;)I;
const #47 = NameAndType	#45:#46;//  unboxToInt:(Ljava/lang/Object;)I
const #48 = Method	#44.#47;	//  scala/runtime/BoxesRunTime.unboxToInt:(Ljava/lang/Object;)I
const #49 = Asciz	scala/collection/mutable/QueueProxy;
const #50 = class	#49;	//  scala/collection/mutable/QueueProxy
const #51 = Asciz	(I)Ljava/lang/Object;;
const #52 = NameAndType	#41:#51;//  apply:(I)Ljava/lang/Object;
const #53 = InterfaceMethod	#50.#52;	//  scala/collection/mutable/QueueProxy.apply:(I)Ljava/lang/Object;
const #54 = Asciz	v1;
const #55 = Asciz	Ljava/lang/Object;;
const #56 = Asciz	$plus$eq;
const #57 = Asciz	(Ljava/lang/Object;)Lscala/collection/mutable/MutableList;;
const #58 = Asciz	(Ljava/lang/Object;)Lscala/collection/mutable/QueueProxy;;
const #59 = NameAndType	#56:#58;//  $plus$eq:(Ljava/lang/Object;)Lscala/collection/mutable/QueueProxy;
const #60 = InterfaceMethod	#50.#59;	//  scala/collection/mutable/QueueProxy.$plus$eq:(Ljava/lang/Object;)Lscala/collection/mutable/QueueProxy;
const #61 = Asciz	scala/collection/mutable/MutableList;
const #62 = class	#61;	//  scala/collection/mutable/MutableList
const #63 = Asciz	elem;
const #64 = Asciz	(Ljava/lang/Object;)Lscala/collection/mutable/Builder;;
const #65 = Asciz	scala/collection/mutable/Builder;
const #66 = class	#65;	//  scala/collection/mutable/Builder
const #67 = Asciz	(Ljava/lang/Object;)Lscala/collection/generic/Growable;;
const #68 = Asciz	scala/collection/generic/Growable;
const #69 = class	#68;	//  scala/collection/generic/Growable
const #70 = Asciz	$plus$plus$eq;
const #71 = Asciz	(Lscala/collection/Iterator;)Lscala/collection/generic/Growable;;
const #72 = Asciz	(Lscala/collection/Iterator;)Lscala/collection/mutable/QueueProxy;;
const #73 = NameAndType	#70:#72;//  $plus$plus$eq:(Lscala/collection/Iterator;)Lscala/collection/mutable/QueueProxy;
const #74 = InterfaceMethod	#50.#73;	//  scala/collection/mutable/QueueProxy.$plus$plus$eq:(Lscala/collection/Iterator;)Lscala/collection/mutable/QueueProxy;
const #75 = Asciz	iter;
const #76 = Asciz	Lscala/collection/Iterator;;
const #77 = Asciz	clone;
const #78 = NameAndType	#77:#38;//  clone:()Lscala/collection/mutable/Queue;
const #79 = InterfaceMethod	#50.#78;	//  scala/collection/mutable/QueueProxy.clone:()Lscala/collection/mutable/Queue;
const #80 = InterfaceMethod	#50.#39;	//  scala/collection/mutable/QueueProxy.self:()Lscala/collection/mutable/Queue;
const #81 = Asciz	scala/collection/mutable/Cloneable;
const #82 = class	#81;	//  scala/collection/mutable/Cloneable
const #83 = NameAndType	#77:#37;//  clone:()Ljava/lang/Object;
const #84 = InterfaceMethod	#82.#83;	//  scala/collection/mutable/Cloneable.clone:()Ljava/lang/Object;
const #85 = Asciz	()Lscala/collection/mutable/Queue<TA;>;;
const #86 = Asciz	toString;
const #87 = Asciz	()Ljava/lang/String;;
const #88 = Asciz	(Lscala/Proxy;)Ljava/lang/String;;
const #89 = NameAndType	#86:#88;//  toString:(Lscala/Proxy;)Ljava/lang/String;
const #90 = Method	#22.#89;	//  scala/Proxy$class.toString:(Lscala/Proxy;)Ljava/lang/String;
const #91 = Asciz	equals;
const #92 = Asciz	(Ljava/lang/Object;)Z;
const #93 = Asciz	(Lscala/Proxy;Ljava/lang/Object;)Z;
const #94 = NameAndType	#91:#93;//  equals:(Lscala/Proxy;Ljava/lang/Object;)Z
const #95 = Method	#22.#94;	//  scala/Proxy$class.equals:(Lscala/Proxy;Ljava/lang/Object;)Z
const #96 = Asciz	that;
const #97 = Asciz	hashCode;
const #98 = Asciz	()I;
const #99 = Asciz	(Lscala/Proxy;)I;
const #100 = NameAndType	#97:#99;//  hashCode:(Lscala/Proxy;)I
const #101 = Method	#22.#100;	//  scala/Proxy$class.hashCode:(Lscala/Proxy;)I
const #102 = Asciz	(Lscala/collection/mutable/QueueProxy;)Lscala/collection/mutable/Queue;;
const #103 = NameAndType	#77:#102;//  clone:(Lscala/collection/mutable/QueueProxy;)Lscala/collection/mutable/Queue;
const #104 = Method	#28.#103;	//  scala/collection/mutable/QueueProxy$class.clone:(Lscala/collection/mutable/QueueProxy;)Lscala/collection/mutable/Queue;
const #105 = Asciz	iterator;
const #106 = Asciz	()Lscala/collection/Iterator;;
const #107 = Asciz	(Lscala/collection/mutable/QueueProxy;)Lscala/collection/Iterator;;
const #108 = NameAndType	#105:#107;//  iterator:(Lscala/collection/mutable/QueueProxy;)Lscala/collection/Iterator;
const #109 = Method	#28.#108;	//  scala/collection/mutable/QueueProxy$class.iterator:(Lscala/collection/mutable/QueueProxy;)Lscala/collection/Iterator;
const #110 = Asciz	clear;
const #111 = NameAndType	#110:#6;//  clear:(Lscala/collection/mutable/QueueProxy;)V
const #112 = Method	#28.#111;	//  scala/collection/mutable/QueueProxy$class.clear:(Lscala/collection/mutable/QueueProxy;)V
const #113 = Asciz	front;
const #114 = Asciz	(Lscala/collection/mutable/QueueProxy;)Ljava/lang/Object;;
const #115 = NameAndType	#113:#114;//  front:(Lscala/collection/mutable/QueueProxy;)Ljava/lang/Object;
const #116 = Method	#28.#115;	//  scala/collection/mutable/QueueProxy$class.front:(Lscala/collection/mutable/QueueProxy;)Ljava/lang/Object;
const #117 = Asciz	dequeue;
const #118 = NameAndType	#117:#114;//  dequeue:(Lscala/collection/mutable/QueueProxy;)Ljava/lang/Object;
const #119 = Method	#28.#118;	//  scala/collection/mutable/QueueProxy$class.dequeue:(Lscala/collection/mutable/QueueProxy;)Ljava/lang/Object;
const #120 = Asciz	enqueue;
const #121 = Asciz	(Lscala/collection/Seq;)V;
const #122 = Asciz	(Lscala/collection/mutable/QueueProxy;Lscala/collection/Seq;)V;
const #123 = NameAndType	#120:#122;//  enqueue:(Lscala/collection/mutable/QueueProxy;Lscala/collection/Seq;)V
const #124 = Method	#28.#123;	//  scala/collection/mutable/QueueProxy$class.enqueue:(Lscala/collection/mutable/QueueProxy;Lscala/collection/Seq;)V
const #125 = Asciz	elems;
const #126 = Asciz	Lscala/collection/Seq;;
const #127 = Asciz	(Lscala/collection/mutable/QueueProxy;Lscala/collection/Iterator;)Lscala/collection/mutable/QueueProxy;;
const #128 = NameAndType	#70:#127;//  $plus$plus$eq:(Lscala/collection/mutable/QueueProxy;Lscala/collection/Iterator;)Lscala/collection/mutable/QueueProxy;
const #129 = Method	#28.#128;	//  scala/collection/mutable/QueueProxy$class.$plus$plus$eq:(Lscala/collection/mutable/QueueProxy;Lscala/collection/Iterator;)Lscala/collection/mutable/QueueProxy;
const #130 = Asciz	it;
const #131 = Asciz	(Lscala/collection/Iterable;)Lscala/collection/mutable/QueueProxy;;
const #132 = Asciz	(Lscala/collection/mutable/QueueProxy;Lscala/collection/Iterable;)Lscala/collection/mutable/QueueProxy;;
const #133 = NameAndType	#70:#132;//  $plus$plus$eq:(Lscala/collection/mutable/QueueProxy;Lscala/collection/Iterable;)Lscala/collection/mutable/QueueProxy;
const #134 = Method	#28.#133;	//  scala/collection/mutable/QueueProxy$class.$plus$plus$eq:(Lscala/collection/mutable/QueueProxy;Lscala/collection/Iterable;)Lscala/collection/mutable/QueueProxy;
const #135 = Asciz	Lscala/collection/Iterable;;
const #136 = Asciz	(Lscala/collection/mutable/QueueProxy;Ljava/lang/Object;)Lscala/collection/mutable/QueueProxy;;
const #137 = NameAndType	#56:#136;//  $plus$eq:(Lscala/collection/mutable/QueueProxy;Ljava/lang/Object;)Lscala/collection/mutable/QueueProxy;
const #138 = Method	#28.#137;	//  scala/collection/mutable/QueueProxy$class.$plus$eq:(Lscala/collection/mutable/QueueProxy;Ljava/lang/Object;)Lscala/collection/mutable/QueueProxy;
const #139 = Asciz	isEmpty;
const #140 = Asciz	()Z;
const #141 = Asciz	(Lscala/collection/mutable/QueueProxy;)Z;
const #142 = NameAndType	#139:#141;//  isEmpty:(Lscala/collection/mutable/QueueProxy;)Z
const #143 = Method	#28.#142;	//  scala/collection/mutable/QueueProxy$class.isEmpty:(Lscala/collection/mutable/QueueProxy;)Z
const #144 = Asciz	length;
const #145 = Asciz	(Lscala/collection/mutable/QueueProxy;)I;
const #146 = NameAndType	#144:#145;//  length:(Lscala/collection/mutable/QueueProxy;)I
const #147 = Method	#28.#146;	//  scala/collection/mutable/QueueProxy$class.length:(Lscala/collection/mutable/QueueProxy;)I
const #148 = Asciz	(Lscala/collection/mutable/QueueProxy;I)Ljava/lang/Object;;
const #149 = NameAndType	#41:#148;//  apply:(Lscala/collection/mutable/QueueProxy;I)Ljava/lang/Object;
const #150 = Method	#28.#149;	//  scala/collection/mutable/QueueProxy$class.apply:(Lscala/collection/mutable/QueueProxy;I)Ljava/lang/Object;
const #151 = Asciz	n;
const #152 = Asciz	I;
const #153 = Asciz	Lscala/collection/mutable/Queue<TA;>;Lscala/collection/mutable/QueueProxy<TA;>;;
const #154 = Asciz	Scala;
const #155 = Asciz	InnerClasses;
const #156 = Asciz	$anon$1;

{
public scala.collection.mutable.QueueProxy$$anon$1(scala.collection.mutable.QueueProxy);
  Code:
   Stack=2, Locals=2, Args_size=2
   0:	aload_1
   1:	ifnonnull	12
   4:	new	#10; //class java/lang/NullPointerException
   7:	dup
   8:	invokespecial	#13; //Method java/lang/NullPointerException."<init>":()V
   11:	athrow
   12:	aload_0
   13:	aload_1
   14:	putfield	#17; //Field $outer:Lscala/collection/mutable/QueueProxy;
   17:	aload_0
   18:	invokespecial	#20; //Method scala/collection/mutable/Queue."<init>":()V
   21:	aload_0
   22:	invokestatic	#26; //Method scala/Proxy$class.$init$:(Lscala/Proxy;)V
   25:	aload_0
   26:	invokestatic	#30; //Method scala/collection/mutable/QueueProxy$class.$init$:(Lscala/collection/mutable/QueueProxy;)V
   29:	return
  LineNumberTable: 
   line 105: 0

  LocalVariableTable: 
   Start  Length  Slot  Name   Signature
   0      30      0    this       Lscala/collection/mutable/QueueProxy$$anon$1;
   0      30      1    $outer       Lscala/collection/mutable/QueueProxy;

  Signature: length = 0x2
   00 22 

public java.lang.Object self();
  Code:
   Stack=1, Locals=1, Args_size=1
   0:	aload_0
   1:	invokevirtual	#40; //Method self:()Lscala/collection/mutable/Queue;
   4:	areturn
  LineNumberTable: 
   line 105: 0


public java.lang.Object apply(java.lang.Object);
  Code:
   Stack=2, Locals=2, Args_size=2
   0:	aload_0
   1:	aload_1
   2:	invokestatic	#48; //Method scala/runtime/BoxesRunTime.unboxToInt:(Ljava/lang/Object;)I
   5:	invokeinterface	#53,  2; //InterfaceMethod scala/collection/mutable/QueueProxy.apply:(I)Ljava/lang/Object;
   10:	areturn
  LineNumberTable: 
   line 105: 0

  LocalVariableTable: 
   Start  Length  Slot  Name   Signature
   0      11      0    this       Lscala/collection/mutable/QueueProxy$$anon$1;
   0      11      1    v1       Ljava/lang/Object;


public scala.collection.mutable.MutableList $plus$eq(java.lang.Object);
  Code:
   Stack=2, Locals=2, Args_size=2
   0:	aload_0
   1:	aload_1
   2:	invokeinterface	#60,  2; //InterfaceMethod scala/collection/mutable/QueueProxy.$plus$eq:(Ljava/lang/Object;)Lscala/collection/mutable/QueueProxy;
   7:	checkcast	#62; //class scala/collection/mutable/MutableList
   10:	areturn
  LineNumberTable: 
   line 105: 0

  LocalVariableTable: 
   Start  Length  Slot  Name   Signature
   0      11      0    this       Lscala/collection/mutable/QueueProxy$$anon$1;
   0      11      1    elem       Ljava/lang/Object;


public scala.collection.mutable.Builder $plus$eq(java.lang.Object);
  Code:
   Stack=2, Locals=2, Args_size=2
   0:	aload_0
   1:	aload_1
   2:	invokeinterface	#60,  2; //InterfaceMethod scala/collection/mutable/QueueProxy.$plus$eq:(Ljava/lang/Object;)Lscala/collection/mutable/QueueProxy;
   7:	checkcast	#66; //class scala/collection/mutable/Builder
   10:	areturn
  LineNumberTable: 
   line 105: 0

  LocalVariableTable: 
   Start  Length  Slot  Name   Signature
   0      11      0    this       Lscala/collection/mutable/QueueProxy$$anon$1;
   0      11      1    elem       Ljava/lang/Object;


public scala.collection.generic.Growable $plus$eq(java.lang.Object);
  Code:
   Stack=2, Locals=2, Args_size=2
   0:	aload_0
   1:	aload_1
   2:	invokeinterface	#60,  2; //InterfaceMethod scala/collection/mutable/QueueProxy.$plus$eq:(Ljava/lang/Object;)Lscala/collection/mutable/QueueProxy;
   7:	checkcast	#69; //class scala/collection/generic/Growable
   10:	areturn
  LineNumberTable: 
   line 105: 0

  LocalVariableTable: 
   Start  Length  Slot  Name   Signature
   0      11      0    this       Lscala/collection/mutable/QueueProxy$$anon$1;
   0      11      1    elem       Ljava/lang/Object;


public scala.collection.generic.Growable $plus$plus$eq(scala.collection.Iterator);
  Code:
   Stack=2, Locals=2, Args_size=2
   0:	aload_0
   1:	aload_1
   2:	invokeinterface	#74,  2; //InterfaceMethod scala/collection/mutable/QueueProxy.$plus$plus$eq:(Lscala/collection/Iterator;)Lscala/collection/mutable/QueueProxy;
   7:	checkcast	#69; //class scala/collection/generic/Growable
   10:	areturn
  LineNumberTable: 
   line 105: 0

  LocalVariableTable: 
   Start  Length  Slot  Name   Signature
   0      11      0    this       Lscala/collection/mutable/QueueProxy$$anon$1;
   0      11      1    iter       Lscala/collection/Iterator;


public java.lang.Object clone();
  Code:
   Stack=1, Locals=1, Args_size=1
   0:	aload_0
   1:	invokeinterface	#79,  1; //InterfaceMethod scala/collection/mutable/QueueProxy.clone:()Lscala/collection/mutable/Queue;
   6:	areturn
  LineNumberTable: 
   line 105: 0


public scala.collection.mutable.Queue self();
  Code:
   Stack=1, Locals=1, Args_size=1
   0:	aload_0
   1:	getfield	#17; //Field $outer:Lscala/collection/mutable/QueueProxy;
   4:	invokeinterface	#80,  1; //InterfaceMethod scala/collection/mutable/QueueProxy.self:()Lscala/collection/mutable/Queue;
   9:	invokeinterface	#84,  1; //InterfaceMethod scala/collection/mutable/Cloneable.clone:()Ljava/lang/Object;
   14:	checkcast	#19; //class scala/collection/mutable/Queue
   17:	areturn
  LineNumberTable: 
   line 106: 0

  Signature: length = 0x2
   00 55 

public java.lang.String toString();
  Code:
   Stack=1, Locals=1, Args_size=1
   0:	aload_0
   1:	invokestatic	#90; //Method scala/Proxy$class.toString:(Lscala/Proxy;)Ljava/lang/String;
   4:	areturn
  LineNumberTable: 
   line 105: 0


public boolean equals(java.lang.Object);
  Code:
   Stack=2, Locals=2, Args_size=2
   0:	aload_0
   1:	aload_1
   2:	invokestatic	#95; //Method scala/Proxy$class.equals:(Lscala/Proxy;Ljava/lang/Object;)Z
   5:	ireturn
  LineNumberTable: 
   line 105: 0

  LocalVariableTable: 
   Start  Length  Slot  Name   Signature
   0      6      0    this       Lscala/collection/mutable/QueueProxy$$anon$1;
   0      6      1    that       Ljava/lang/Object;


public int hashCode();
  Code:
   Stack=1, Locals=1, Args_size=1
   0:	aload_0
   1:	invokestatic	#101; //Method scala/Proxy$class.hashCode:(Lscala/Proxy;)I
   4:	ireturn
  LineNumberTable: 
   line 105: 0


public scala.collection.mutable.Queue clone();
  Code:
   Stack=1, Locals=1, Args_size=1
   0:	aload_0
   1:	invokestatic	#104; //Method scala/collection/mutable/QueueProxy$class.clone:(Lscala/collection/mutable/QueueProxy;)Lscala/collection/mutable/Queue;
   4:	areturn
  LineNumberTable: 
   line 105: 0


public scala.collection.Iterator iterator();
  Code:
   Stack=1, Locals=1, Args_size=1
   0:	aload_0
   1:	invokestatic	#109; //Method scala/collection/mutable/QueueProxy$class.iterator:(Lscala/collection/mutable/QueueProxy;)Lscala/collection/Iterator;
   4:	areturn
  LineNumberTable: 
   line 105: 0


public void clear();
  Code:
   Stack=1, Locals=1, Args_size=1
   0:	aload_0
   1:	invokestatic	#112; //Method scala/collection/mutable/QueueProxy$class.clear:(Lscala/collection/mutable/QueueProxy;)V
   4:	return
  LineNumberTable: 
   line 105: 0


public java.lang.Object front();
  Code:
   Stack=1, Locals=1, Args_size=1
   0:	aload_0
   1:	invokestatic	#116; //Method scala/collection/mutable/QueueProxy$class.front:(Lscala/collection/mutable/QueueProxy;)Ljava/lang/Object;
   4:	areturn
  LineNumberTable: 
   line 105: 0


public java.lang.Object dequeue();
  Code:
   Stack=1, Locals=1, Args_size=1
   0:	aload_0
   1:	invokestatic	#119; //Method scala/collection/mutable/QueueProxy$class.dequeue:(Lscala/collection/mutable/QueueProxy;)Ljava/lang/Object;
   4:	areturn
  LineNumberTable: 
   line 105: 0


public void enqueue(scala.collection.Seq);
  Code:
   Stack=2, Locals=2, Args_size=2
   0:	aload_0
   1:	aload_1
   2:	invokestatic	#124; //Method scala/collection/mutable/QueueProxy$class.enqueue:(Lscala/collection/mutable/QueueProxy;Lscala/collection/Seq;)V
   5:	return
  LineNumberTable: 
   line 105: 0

  LocalVariableTable: 
   Start  Length  Slot  Name   Signature
   0      6      0    this       Lscala/collection/mutable/QueueProxy$$anon$1;
   0      6      1    elems       Lscala/collection/Seq;


public scala.collection.mutable.QueueProxy $plus$plus$eq(scala.collection.Iterator);
  Code:
   Stack=2, Locals=2, Args_size=2
   0:	aload_0
   1:	aload_1
   2:	invokestatic	#129; //Method scala/collection/mutable/QueueProxy$class.$plus$plus$eq:(Lscala/collection/mutable/QueueProxy;Lscala/collection/Iterator;)Lscala/collection/mutable/QueueProxy;
   5:	areturn
  LineNumberTable: 
   line 105: 0

  LocalVariableTable: 
   Start  Length  Slot  Name   Signature
   0      6      0    this       Lscala/collection/mutable/QueueProxy$$anon$1;
   0      6      1    it       Lscala/collection/Iterator;


public scala.collection.mutable.QueueProxy $plus$plus$eq(scala.collection.Iterable);
  Code:
   Stack=2, Locals=2, Args_size=2
   0:	aload_0
   1:	aload_1
   2:	invokestatic	#134; //Method scala/collection/mutable/QueueProxy$class.$plus$plus$eq:(Lscala/collection/mutable/QueueProxy;Lscala/collection/Iterable;)Lscala/collection/mutable/QueueProxy;
   5:	areturn
  LineNumberTable: 
   line 105: 0

  LocalVariableTable: 
   Start  Length  Slot  Name   Signature
   0      6      0    this       Lscala/collection/mutable/QueueProxy$$anon$1;
   0      6      1    iter       Lscala/collection/Iterable;


public scala.collection.mutable.QueueProxy $plus$eq(java.lang.Object);
  Code:
   Stack=2, Locals=2, Args_size=2
   0:	aload_0
   1:	aload_1
   2:	invokestatic	#138; //Method scala/collection/mutable/QueueProxy$class.$plus$eq:(Lscala/collection/mutable/QueueProxy;Ljava/lang/Object;)Lscala/collection/mutable/QueueProxy;
   5:	areturn
  LineNumberTable: 
   line 105: 0

  LocalVariableTable: 
   Start  Length  Slot  Name   Signature
   0      6      0    this       Lscala/collection/mutable/QueueProxy$$anon$1;
   0      6      1    elem       Ljava/lang/Object;


public boolean isEmpty();
  Code:
   Stack=1, Locals=1, Args_size=1
   0:	aload_0
   1:	invokestatic	#143; //Method scala/collection/mutable/QueueProxy$class.isEmpty:(Lscala/collection/mutable/QueueProxy;)Z
   4:	ireturn
  LineNumberTable: 
   line 105: 0


public int length();
  Code:
   Stack=1, Locals=1, Args_size=1
   0:	aload_0
   1:	invokestatic	#147; //Method scala/collection/mutable/QueueProxy$class.length:(Lscala/collection/mutable/QueueProxy;)I
   4:	ireturn
  LineNumberTable: 
   line 105: 0


public java.lang.Object apply(int);
  Code:
   Stack=2, Locals=2, Args_size=2
   0:	aload_0
   1:	iload_1
   2:	invokestatic	#150; //Method scala/collection/mutable/QueueProxy$class.apply:(Lscala/collection/mutable/QueueProxy;I)Ljava/lang/Object;
   5:	areturn
  LineNumberTable: 
   line 105: 0

  LocalVariableTable: 
   Start  Length  Slot  Name   Signature
   0      6      0    this       Lscala/collection/mutable/QueueProxy$$anon$1;
   0      6      1    n       I


}

