Compiled from "QueueProxy.scala"
public abstract class scala.collection.mutable.QueueProxy$class extends java.lang.Object
  SourceFile: "QueueProxy.scala"
  Scala: length = 0x
   
  InnerClass: 
   public final #87= #13 of #20; //$anon$1=class scala/collection/mutable/QueueProxy$$anon$1 of class scala/collection/mutable/QueueProxy
  minor version: 0
  major version: 49
  Constant pool:
const #1 = Asciz	SourceFile;
const #2 = Asciz	QueueProxy.scala;
const #3 = Asciz	$init$;
const #4 = Asciz	(Lscala/collection/mutable/QueueProxy;)V;
const #5 = Asciz	Code;
const #6 = Asciz	LineNumberTable;
const #7 = Asciz	$this;
const #8 = Asciz	Lscala/collection/mutable/QueueProxy;;
const #9 = Asciz	LocalVariableTable;
const #10 = Asciz	clone;
const #11 = Asciz	(Lscala/collection/mutable/QueueProxy;)Lscala/collection/mutable/Queue;;
const #12 = Asciz	scala/collection/mutable/QueueProxy$$anon$1;
const #13 = class	#12;	//  scala/collection/mutable/QueueProxy$$anon$1
const #14 = Asciz	<init>;
const #15 = NameAndType	#14:#4;//  "<init>":(Lscala/collection/mutable/QueueProxy;)V
const #16 = Method	#13.#15;	//  scala/collection/mutable/QueueProxy$$anon$1."<init>":(Lscala/collection/mutable/QueueProxy;)V
const #17 = Asciz	iterator;
const #18 = Asciz	(Lscala/collection/mutable/QueueProxy;)Lscala/collection/Iterator;;
const #19 = Asciz	scala/collection/mutable/QueueProxy;
const #20 = class	#19;	//  scala/collection/mutable/QueueProxy
const #21 = Asciz	self;
const #22 = Asciz	()Lscala/collection/mutable/Queue;;
const #23 = NameAndType	#21:#22;//  self:()Lscala/collection/mutable/Queue;
const #24 = InterfaceMethod	#20.#23;	//  scala/collection/mutable/QueueProxy.self:()Lscala/collection/mutable/Queue;
const #25 = Asciz	scala/collection/mutable/Queue;
const #26 = class	#25;	//  scala/collection/mutable/Queue
const #27 = Asciz	()Lscala/collection/Iterator;;
const #28 = NameAndType	#17:#27;//  iterator:()Lscala/collection/Iterator;
const #29 = Method	#26.#28;	//  scala/collection/mutable/Queue.iterator:()Lscala/collection/Iterator;
const #30 = Asciz	clear;
const #31 = Asciz	()V;
const #32 = NameAndType	#30:#31;//  clear:()V
const #33 = Method	#26.#32;	//  scala/collection/mutable/Queue.clear:()V
const #34 = Asciz	front;
const #35 = Asciz	(Lscala/collection/mutable/QueueProxy;)Ljava/lang/Object;;
const #36 = Asciz	()Ljava/lang/Object;;
const #37 = NameAndType	#34:#36;//  front:()Ljava/lang/Object;
const #38 = Method	#26.#37;	//  scala/collection/mutable/Queue.front:()Ljava/lang/Object;
const #39 = Asciz	dequeue;
const #40 = NameAndType	#39:#36;//  dequeue:()Ljava/lang/Object;
const #41 = Method	#26.#40;	//  scala/collection/mutable/Queue.dequeue:()Ljava/lang/Object;
const #42 = Asciz	enqueue;
const #43 = Asciz	(Lscala/collection/mutable/QueueProxy;Lscala/collection/Seq;)V;
const #44 = Asciz	scala/collection/generic/Growable;
const #45 = class	#44;	//  scala/collection/generic/Growable
const #46 = Asciz	$plus$plus$eq;
const #47 = Asciz	(Lscala/collection/Traversable;)Lscala/collection/generic/Growable;;
const #48 = NameAndType	#46:#47;//  $plus$plus$eq:(Lscala/collection/Traversable;)Lscala/collection/generic/Growable;
const #49 = InterfaceMethod	#45.#48;	//  scala/collection/generic/Growable.$plus$plus$eq:(Lscala/collection/Traversable;)Lscala/collection/generic/Growable;
const #50 = Asciz	elems;
const #51 = Asciz	Lscala/collection/Seq;;
const #52 = Asciz	(Lscala/collection/mutable/QueueProxy;Lscala/collection/Iterator;)Lscala/collection/mutable/QueueProxy;;
const #53 = Asciz	(Lscala/collection/Iterator;)Lscala/collection/generic/Growable;;
const #54 = NameAndType	#46:#53;//  $plus$plus$eq:(Lscala/collection/Iterator;)Lscala/collection/generic/Growable;
const #55 = InterfaceMethod	#45.#54;	//  scala/collection/generic/Growable.$plus$plus$eq:(Lscala/collection/Iterator;)Lscala/collection/generic/Growable;
const #56 = Asciz	it;
const #57 = Asciz	Lscala/collection/Iterator;;
const #58 = Asciz	(Lscala/collection/mutable/QueueProxy;Lscala/collection/Iterable;)Lscala/collection/mutable/QueueProxy;;
const #59 = Asciz	iter;
const #60 = Asciz	Lscala/collection/Iterable;;
const #61 = Asciz	$plus$eq;
const #62 = Asciz	(Lscala/collection/mutable/QueueProxy;Ljava/lang/Object;)Lscala/collection/mutable/QueueProxy;;
const #63 = Asciz	(Ljava/lang/Object;)Lscala/collection/mutable/MutableList;;
const #64 = NameAndType	#61:#63;//  $plus$eq:(Ljava/lang/Object;)Lscala/collection/mutable/MutableList;
const #65 = Method	#26.#64;	//  scala/collection/mutable/Queue.$plus$eq:(Ljava/lang/Object;)Lscala/collection/mutable/MutableList;
const #66 = Asciz	elem;
const #67 = Asciz	Ljava/lang/Object;;
const #68 = Asciz	isEmpty;
const #69 = Asciz	(Lscala/collection/mutable/QueueProxy;)Z;
const #70 = Asciz	()Z;
const #71 = NameAndType	#68:#70;//  isEmpty:()Z
const #72 = Method	#26.#71;	//  scala/collection/mutable/Queue.isEmpty:()Z
const #73 = Asciz	length;
const #74 = Asciz	(Lscala/collection/mutable/QueueProxy;)I;
const #75 = Asciz	()I;
const #76 = NameAndType	#73:#75;//  length:()I
const #77 = Method	#26.#76;	//  scala/collection/mutable/Queue.length:()I
const #78 = Asciz	apply;
const #79 = Asciz	(Lscala/collection/mutable/QueueProxy;I)Ljava/lang/Object;;
const #80 = Asciz	(I)Ljava/lang/Object;;
const #81 = NameAndType	#78:#80;//  apply:(I)Ljava/lang/Object;
const #82 = Method	#26.#81;	//  scala/collection/mutable/Queue.apply:(I)Ljava/lang/Object;
const #83 = Asciz	n;
const #84 = Asciz	I;
const #85 = Asciz	Scala;
const #86 = Asciz	InnerClasses;
const #87 = Asciz	$anon$1;
const #88 = Asciz	scala/collection/mutable/QueueProxy$class;
const #89 = class	#88;	//  scala/collection/mutable/QueueProxy$class
const #90 = Asciz	java/lang/Object;
const #91 = class	#90;	//  java/lang/Object

{
public static void $init$(scala.collection.mutable.QueueProxy);
  Code:
   Stack=0, Locals=1, Args_size=1
   0:	return
  LineNumberTable: 
   line 22: 0

  LocalVariableTable: 
   Start  Length  Slot  Name   Signature
   0      1      0    $this       Lscala/collection/mutable/QueueProxy;


public static scala.collection.mutable.Queue clone(scala.collection.mutable.QueueProxy);
  Code:
   Stack=3, Locals=1, Args_size=1
   0:	new	#13; //class scala/collection/mutable/QueueProxy$$anon$1
   3:	dup
   4:	aload_0
   5:	invokespecial	#16; //Method scala/collection/mutable/QueueProxy$$anon$1."<init>":(Lscala/collection/mutable/QueueProxy;)V
   8:	areturn
  LineNumberTable: 
   line 105: 0

  LocalVariableTable: 
   Start  Length  Slot  Name   Signature
   0      9      0    $this       Lscala/collection/mutable/QueueProxy;


public static scala.collection.Iterator iterator(scala.collection.mutable.QueueProxy);
  Code:
   Stack=1, Locals=1, Args_size=1
   0:	aload_0
   1:	invokeinterface	#24,  1; //InterfaceMethod scala/collection/mutable/QueueProxy.self:()Lscala/collection/mutable/Queue;
   6:	invokevirtual	#29; //Method scala/collection/mutable/Queue.iterator:()Lscala/collection/Iterator;
   9:	areturn
  LineNumberTable: 
   line 99: 0

  LocalVariableTable: 
   Start  Length  Slot  Name   Signature
   0      10      0    $this       Lscala/collection/mutable/QueueProxy;


public static void clear(scala.collection.mutable.QueueProxy);
  Code:
   Stack=1, Locals=1, Args_size=1
   0:	aload_0
   1:	invokeinterface	#24,  1; //InterfaceMethod scala/collection/mutable/QueueProxy.self:()Lscala/collection/mutable/Queue;
   6:	invokevirtual	#33; //Method scala/collection/mutable/Queue.clear:()V
   9:	return
  LineNumberTable: 
   line 93: 0

  LocalVariableTable: 
   Start  Length  Slot  Name   Signature
   0      10      0    $this       Lscala/collection/mutable/QueueProxy;


public static java.lang.Object front(scala.collection.mutable.QueueProxy);
  Code:
   Stack=1, Locals=1, Args_size=1
   0:	aload_0
   1:	invokeinterface	#24,  1; //InterfaceMethod scala/collection/mutable/QueueProxy.self:()Lscala/collection/mutable/Queue;
   6:	invokevirtual	#38; //Method scala/collection/mutable/Queue.front:()Ljava/lang/Object;
   9:	areturn
  LineNumberTable: 
   line 88: 0

  LocalVariableTable: 
   Start  Length  Slot  Name   Signature
   0      10      0    $this       Lscala/collection/mutable/QueueProxy;


public static java.lang.Object dequeue(scala.collection.mutable.QueueProxy);
  Code:
   Stack=1, Locals=1, Args_size=1
   0:	aload_0
   1:	invokeinterface	#24,  1; //InterfaceMethod scala/collection/mutable/QueueProxy.self:()Lscala/collection/mutable/Queue;
   6:	invokevirtual	#41; //Method scala/collection/mutable/Queue.dequeue:()Ljava/lang/Object;
   9:	areturn
  LineNumberTable: 
   line 81: 0

  LocalVariableTable: 
   Start  Length  Slot  Name   Signature
   0      10      0    $this       Lscala/collection/mutable/QueueProxy;


public static void enqueue(scala.collection.mutable.QueueProxy, scala.collection.Seq);
  Code:
   Stack=2, Locals=2, Args_size=2
   0:	aload_0
   1:	invokeinterface	#24,  1; //InterfaceMethod scala/collection/mutable/QueueProxy.self:()Lscala/collection/mutable/Queue;
   6:	aload_1
   7:	invokeinterface	#49,  2; //InterfaceMethod scala/collection/generic/Growable.$plus$plus$eq:(Lscala/collection/Traversable;)Lscala/collection/generic/Growable;
   12:	pop
   13:	return
  LineNumberTable: 
   line 74: 0

  LocalVariableTable: 
   Start  Length  Slot  Name   Signature
   0      14      0    $this       Lscala/collection/mutable/QueueProxy;
   0      14      1    elems       Lscala/collection/Seq;


public static scala.collection.mutable.QueueProxy $plus$plus$eq(scala.collection.mutable.QueueProxy, scala.collection.Iterator);
  Code:
   Stack=2, Locals=2, Args_size=2
   0:	aload_0
   1:	invokeinterface	#24,  1; //InterfaceMethod scala/collection/mutable/QueueProxy.self:()Lscala/collection/mutable/Queue;
   6:	aload_1
   7:	invokeinterface	#55,  2; //InterfaceMethod scala/collection/generic/Growable.$plus$plus$eq:(Lscala/collection/Iterator;)Lscala/collection/generic/Growable;
   12:	pop
   13:	aload_0
   14:	areturn
  LineNumberTable: 
   line 66: 0
   line 67: 13

  LocalVariableTable: 
   Start  Length  Slot  Name   Signature
   0      15      0    $this       Lscala/collection/mutable/QueueProxy;
   0      15      1    it       Lscala/collection/Iterator;


public static scala.collection.mutable.QueueProxy $plus$plus$eq(scala.collection.mutable.QueueProxy, scala.collection.Iterable);
  Code:
   Stack=2, Locals=2, Args_size=2
   0:	aload_0
   1:	invokeinterface	#24,  1; //InterfaceMethod scala/collection/mutable/QueueProxy.self:()Lscala/collection/mutable/Queue;
   6:	aload_1
   7:	invokeinterface	#49,  2; //InterfaceMethod scala/collection/generic/Growable.$plus$plus$eq:(Lscala/collection/Traversable;)Lscala/collection/generic/Growable;
   12:	pop
   13:	aload_0
   14:	areturn
  LineNumberTable: 
   line 55: 0
   line 56: 13

  LocalVariableTable: 
   Start  Length  Slot  Name   Signature
   0      15      0    $this       Lscala/collection/mutable/QueueProxy;
   0      15      1    iter       Lscala/collection/Iterable;


public static scala.collection.mutable.QueueProxy $plus$eq(scala.collection.mutable.QueueProxy, java.lang.Object);
  Code:
   Stack=2, Locals=2, Args_size=2
   0:	aload_0
   1:	invokeinterface	#24,  1; //InterfaceMethod scala/collection/mutable/QueueProxy.self:()Lscala/collection/mutable/Queue;
   6:	aload_1
   7:	invokevirtual	#65; //Method scala/collection/mutable/Queue.$plus$eq:(Ljava/lang/Object;)Lscala/collection/mutable/MutableList;
   10:	pop
   11:	aload_0
   12:	areturn
  LineNumberTable: 
   line 46: 0

  LocalVariableTable: 
   Start  Length  Slot  Name   Signature
   0      13      0    $this       Lscala/collection/mutable/QueueProxy;
   0      13      1    elem       Ljava/lang/Object;


public static boolean isEmpty(scala.collection.mutable.QueueProxy);
  Code:
   Stack=1, Locals=1, Args_size=1
   0:	aload_0
   1:	invokeinterface	#24,  1; //InterfaceMethod scala/collection/mutable/QueueProxy.self:()Lscala/collection/mutable/Queue;
   6:	invokevirtual	#72; //Method scala/collection/mutable/Queue.isEmpty:()Z
   9:	ireturn
  LineNumberTable: 
   line 40: 0

  LocalVariableTable: 
   Start  Length  Slot  Name   Signature
   0      10      0    $this       Lscala/collection/mutable/QueueProxy;


public static int length(scala.collection.mutable.QueueProxy);
  Code:
   Stack=1, Locals=1, Args_size=1
   0:	aload_0
   1:	invokeinterface	#24,  1; //InterfaceMethod scala/collection/mutable/QueueProxy.self:()Lscala/collection/mutable/Queue;
   6:	invokevirtual	#77; //Method scala/collection/mutable/Queue.length:()I
   9:	ireturn
  LineNumberTable: 
   line 34: 0

  LocalVariableTable: 
   Start  Length  Slot  Name   Signature
   0      10      0    $this       Lscala/collection/mutable/QueueProxy;


public static java.lang.Object apply(scala.collection.mutable.QueueProxy, int);
  Code:
   Stack=2, Locals=2, Args_size=2
   0:	aload_0
   1:	invokeinterface	#24,  1; //InterfaceMethod scala/collection/mutable/QueueProxy.self:()Lscala/collection/mutable/Queue;
   6:	iload_1
   7:	invokevirtual	#82; //Method scala/collection/mutable/Queue.apply:(I)Ljava/lang/Object;
   10:	areturn
  LineNumberTable: 
   line 30: 0

  LocalVariableTable: 
   Start  Length  Slot  Name   Signature
   0      11      0    $this       Lscala/collection/mutable/QueueProxy;
   0      11      1    n       I


}

