Compiled from "ResizableArray.scala"
public abstract class scala.collection.mutable.ResizableArray$class extends java.lang.Object
  SourceFile: "ResizableArray.scala"
  Scala: length = 0x
   
  minor version: 0
  major version: 49
  Constant pool:
const #1 = Asciz	SourceFile;
const #2 = Asciz	ResizableArray.scala;
const #3 = Asciz	$init$;
const #4 = Asciz	(Lscala/collection/mutable/ResizableArray;)V;
const #5 = Asciz	Code;
const #6 = Asciz	LineNumberTable;
const #7 = Asciz	scala/Predef$;
const #8 = class	#7;	//  scala/Predef$
const #9 = Asciz	MODULE$;
const #10 = Asciz	Lscala/Predef$;;
const #11 = NameAndType	#9:#10;//  MODULE$:Lscala/Predef$;
const #12 = Field	#8.#11;	//  scala/Predef$.MODULE$:Lscala/Predef$;
const #13 = Asciz	scala/collection/mutable/ResizableArray;
const #14 = class	#13;	//  scala/collection/mutable/ResizableArray
const #15 = Asciz	initialSize;
const #16 = Asciz	()I;
const #17 = NameAndType	#15:#16;//  initialSize:()I
const #18 = InterfaceMethod	#14.#17;	//  scala/collection/mutable/ResizableArray.initialSize:()I
const #19 = Asciz	intWrapper;
const #20 = Asciz	(I)Lscala/runtime/RichInt;;
const #21 = NameAndType	#19:#20;//  intWrapper:(I)Lscala/runtime/RichInt;
const #22 = Method	#8.#21;	//  scala/Predef$.intWrapper:(I)Lscala/runtime/RichInt;
const #23 = Asciz	scala/runtime/RichInt;
const #24 = class	#23;	//  scala/runtime/RichInt
const #25 = Asciz	max;
const #26 = Asciz	(I)I;
const #27 = NameAndType	#25:#26;//  max:(I)I
const #28 = Method	#24.#27;	//  scala/runtime/RichInt.max:(I)I
const #29 = Asciz	java/lang/Object;
const #30 = class	#29;	//  java/lang/Object
const #31 = Asciz	array_$eq;
const #32 = Asciz	([Ljava/lang/Object;)V;
const #33 = NameAndType	#31:#32;//  array_$eq:([Ljava/lang/Object;)V
const #34 = InterfaceMethod	#14.#33;	//  scala/collection/mutable/ResizableArray.array_$eq:([Ljava/lang/Object;)V
const #35 = Asciz	size0_$eq;
const #36 = Asciz	(I)V;
const #37 = NameAndType	#35:#36;//  size0_$eq:(I)V
const #38 = InterfaceMethod	#14.#37;	//  scala/collection/mutable/ResizableArray.size0_$eq:(I)V
const #39 = Asciz	$this;
const #40 = Asciz	Lscala/collection/mutable/ResizableArray;;
const #41 = Asciz	LocalVariableTable;
const #42 = Asciz	copy;
const #43 = Asciz	(Lscala/collection/mutable/ResizableArray;III)V;
const #44 = Asciz	scala/Array$;
const #45 = class	#44;	//  scala/Array$
const #46 = Asciz	Lscala/Array$;;
const #47 = NameAndType	#9:#46;//  MODULE$:Lscala/Array$;
const #48 = Field	#45.#47;	//  scala/Array$.MODULE$:Lscala/Array$;
const #49 = Asciz	array;
const #50 = Asciz	()[Ljava/lang/Object;;
const #51 = NameAndType	#49:#50;//  array:()[Ljava/lang/Object;
const #52 = InterfaceMethod	#14.#51;	//  scala/collection/mutable/ResizableArray.array:()[Ljava/lang/Object;
const #53 = Asciz	(Ljava/lang/Object;ILjava/lang/Object;II)V;
const #54 = NameAndType	#42:#53;//  copy:(Ljava/lang/Object;ILjava/lang/Object;II)V
const #55 = Method	#45.#54;	//  scala/Array$.copy:(Ljava/lang/Object;ILjava/lang/Object;II)V
const #56 = Asciz	m;
const #57 = Asciz	I;
const #58 = Asciz	n;
const #59 = Asciz	len;
const #60 = Asciz	swap;
const #61 = Asciz	(Lscala/collection/mutable/ResizableArray;II)V;
const #62 = Asciz	a;
const #63 = Asciz	b;
const #64 = Asciz	h;
const #65 = Asciz	Ljava/lang/Object;;
const #66 = Asciz	ensureSize;
const #67 = Asciz	(Lscala/collection/mutable/ResizableArray;I)V;
const #68 = Asciz	size0;
const #69 = NameAndType	#68:#16;//  size0:()I
const #70 = InterfaceMethod	#14.#69;	//  scala/collection/mutable/ResizableArray.size0:()I
const #71 = Asciz	newsize;
const #72 = Asciz	newar;
const #73 = Asciz	[Ljava/lang/Object;;
const #74 = Asciz	reduceToSize;
const #75 = Asciz	require;
const #76 = Asciz	(Z)V;
const #77 = NameAndType	#75:#76;//  require:(Z)V
const #78 = Method	#8.#77;	//  scala/Predef$.require:(Z)V
const #79 = Asciz	sz;
const #80 = Asciz	copyToArray;
const #81 = Asciz	(Lscala/collection/mutable/ResizableArray;Ljava/lang/Object;II)V;
const #82 = Asciz	scala/runtime/ScalaRunTime$;
const #83 = class	#82;	//  scala/runtime/ScalaRunTime$
const #84 = Asciz	Lscala/runtime/ScalaRunTime$;;
const #85 = NameAndType	#9:#84;//  MODULE$:Lscala/runtime/ScalaRunTime$;
const #86 = Field	#83.#85;	//  scala/runtime/ScalaRunTime$.MODULE$:Lscala/runtime/ScalaRunTime$;
const #87 = Asciz	array_length;
const #88 = Asciz	(Ljava/lang/Object;)I;
const #89 = NameAndType	#87:#88;//  array_length:(Ljava/lang/Object;)I
const #90 = Method	#83.#89;	//  scala/runtime/ScalaRunTime$.array_length:(Ljava/lang/Object;)I
const #91 = Asciz	min;
const #92 = NameAndType	#91:#26;//  min:(I)I
const #93 = Method	#24.#92;	//  scala/runtime/RichInt.min:(I)I
const #94 = Asciz	length;
const #95 = NameAndType	#94:#16;//  length:()I
const #96 = InterfaceMethod	#14.#95;	//  scala/collection/mutable/ResizableArray.length:()I
const #97 = Asciz	xs;
const #98 = Asciz	start;
const #99 = Asciz	len1;
const #100 = Asciz	foreach;
const #101 = Asciz	(Lscala/collection/mutable/ResizableArray;Lscala/Function1;)V;
const #102 = Asciz	scala/collection/SeqLike;
const #103 = class	#102;	//  scala/collection/SeqLike
const #104 = Asciz	size;
const #105 = NameAndType	#104:#16;//  size:()I
const #106 = InterfaceMethod	#103.#105;	//  scala/collection/SeqLike.size:()I
const #107 = Asciz	scala/Function1;
const #108 = class	#107;	//  scala/Function1
const #109 = Asciz	apply;
const #110 = Asciz	(Ljava/lang/Object;)Ljava/lang/Object;;
const #111 = NameAndType	#109:#110;//  apply:(Ljava/lang/Object;)Ljava/lang/Object;
const #112 = InterfaceMethod	#108.#111;	//  scala/Function1.apply:(Ljava/lang/Object;)Ljava/lang/Object;
const #113 = Asciz	f;
const #114 = Asciz	Lscala/Function1;;
const #115 = Asciz	i;
const #116 = Asciz	update;
const #117 = Asciz	(Lscala/collection/mutable/ResizableArray;ILjava/lang/Object;)V;
const #118 = Asciz	java/lang/IndexOutOfBoundsException;
const #119 = class	#118;	//  java/lang/IndexOutOfBoundsException
const #120 = Asciz	scala/runtime/BoxesRunTime;
const #121 = class	#120;	//  scala/runtime/BoxesRunTime
const #122 = Asciz	boxToInteger;
const #123 = Asciz	(I)Ljava/lang/Integer;;
const #124 = NameAndType	#122:#123;//  boxToInteger:(I)Ljava/lang/Integer;
const #125 = Method	#121.#124;	//  scala/runtime/BoxesRunTime.boxToInteger:(I)Ljava/lang/Integer;
const #126 = Asciz	toString;
const #127 = Asciz	()Ljava/lang/String;;
const #128 = NameAndType	#126:#127;//  toString:()Ljava/lang/String;
const #129 = Method	#30.#128;	//  java/lang/Object.toString:()Ljava/lang/String;
const #130 = Asciz	<init>;
const #131 = Asciz	(Ljava/lang/String;)V;
const #132 = NameAndType	#130:#131;//  "<init>":(Ljava/lang/String;)V
const #133 = Method	#119.#132;	//  java/lang/IndexOutOfBoundsException."<init>":(Ljava/lang/String;)V
const #134 = Asciz	idx;
const #135 = Asciz	elem;
const #136 = Asciz	(Lscala/collection/mutable/ResizableArray;I)Ljava/lang/Object;;
const #137 = Asciz	(Lscala/collection/mutable/ResizableArray;)I;
const #138 = int	16;
const #139 = Asciz	companion;
const #140 = Asciz	(Lscala/collection/mutable/ResizableArray;)Lscala/collection/generic/GenericCompanion;;
const #141 = Asciz	scala/collection/mutable/ResizableArray$;
const #142 = class	#141;	//  scala/collection/mutable/ResizableArray$
const #143 = Asciz	Lscala/collection/mutable/ResizableArray$;;
const #144 = NameAndType	#9:#143;//  MODULE$:Lscala/collection/mutable/ResizableArray$;
const #145 = Field	#142.#144;	//  scala/collection/mutable/ResizableArray$.MODULE$:Lscala/collection/mutable/ResizableArray$;
const #146 = Asciz	Scala;
const #147 = Asciz	scala/collection/mutable/ResizableArray$class;
const #148 = class	#147;	//  scala/collection/mutable/ResizableArray$class

{
public static void $init$(scala.collection.mutable.ResizableArray);
  Code:
   Stack=3, Locals=1, Args_size=1
   0:	aload_0
   1:	getstatic	#12; //Field scala/Predef$.MODULE$:Lscala/Predef$;
   4:	aload_0
   5:	invokeinterface	#18,  1; //InterfaceMethod scala/collection/mutable/ResizableArray.initialSize:()I
   10:	invokevirtual	#22; //Method scala/Predef$.intWrapper:(I)Lscala/runtime/RichInt;
   13:	iconst_1
   14:	invokevirtual	#28; //Method scala/runtime/RichInt.max:(I)I
   17:	anewarray	#30; //class java/lang/Object
   20:	invokeinterface	#34,  2; //InterfaceMethod scala/collection/mutable/ResizableArray.array_$eq:([Ljava/lang/Object;)V
   25:	aload_0
   26:	iconst_0
   27:	invokeinterface	#38,  2; //InterfaceMethod scala/collection/mutable/ResizableArray.size0_$eq:(I)V
   32:	return
  LineNumberTable: 
   line 32: 0
   line 34: 25

  LocalVariableTable: 
   Start  Length  Slot  Name   Signature
   0      33      0    $this       Lscala/collection/mutable/ResizableArray;


public static void copy(scala.collection.mutable.ResizableArray, int, int, int);
  Code:
   Stack=6, Locals=4, Args_size=4
   0:	getstatic	#48; //Field scala/Array$.MODULE$:Lscala/Array$;
   3:	aload_0
   4:	invokeinterface	#52,  1; //InterfaceMethod scala/collection/mutable/ResizableArray.array:()[Ljava/lang/Object;
   9:	iload_1
   10:	aload_0
   11:	invokeinterface	#52,  1; //InterfaceMethod scala/collection/mutable/ResizableArray.array:()[Ljava/lang/Object;
   16:	iload_2
   17:	iload_3
   18:	invokevirtual	#55; //Method scala/Array$.copy:(Ljava/lang/Object;ILjava/lang/Object;II)V
   21:	return
  LineNumberTable: 
   line 113: 0

  LocalVariableTable: 
   Start  Length  Slot  Name   Signature
   0      22      0    $this       Lscala/collection/mutable/ResizableArray;
   0      22      1    m       I
   0      22      2    n       I
   0      22      3    len       I


public static void swap(scala.collection.mutable.ResizableArray, int, int);
  Code:
   Stack=4, Locals=4, Args_size=3
   0:	aload_0
   1:	invokeinterface	#52,  1; //InterfaceMethod scala/collection/mutable/ResizableArray.array:()[Ljava/lang/Object;
   6:	iload_1
   7:	aaload
   8:	astore_3
   9:	aload_0
   10:	invokeinterface	#52,  1; //InterfaceMethod scala/collection/mutable/ResizableArray.array:()[Ljava/lang/Object;
   15:	iload_1
   16:	aload_0
   17:	invokeinterface	#52,  1; //InterfaceMethod scala/collection/mutable/ResizableArray.array:()[Ljava/lang/Object;
   22:	iload_2
   23:	aaload
   24:	aastore
   25:	aload_0
   26:	invokeinterface	#52,  1; //InterfaceMethod scala/collection/mutable/ResizableArray.array:()[Ljava/lang/Object;
   31:	iload_2
   32:	aload_3
   33:	aastore
   34:	return
  LineNumberTable: 
   line 105: 0
   line 106: 9
   line 107: 25

  LocalVariableTable: 
   Start  Length  Slot  Name   Signature
   0      35      0    $this       Lscala/collection/mutable/ResizableArray;
   0      35      1    a       I
   0      35      2    b       I
   9      25      3    h       Ljava/lang/Object;


public static void ensureSize(scala.collection.mutable.ResizableArray, int);
  Code:
   Stack=6, Locals=4, Args_size=2
   0:	iload_1
   1:	aload_0
   2:	invokeinterface	#52,  1; //InterfaceMethod scala/collection/mutable/ResizableArray.array:()[Ljava/lang/Object;
   7:	arraylength
   8:	if_icmple	66
   11:	aload_0
   12:	invokeinterface	#52,  1; //InterfaceMethod scala/collection/mutable/ResizableArray.array:()[Ljava/lang/Object;
   17:	arraylength
   18:	iconst_2
   19:	imul
   20:	istore_2
   21:	iload_1
   22:	iload_2
   23:	if_icmple	33
   26:	iload_2
   27:	iconst_2
   28:	imul
   29:	istore_2
   30:	goto	21
   33:	iload_2
   34:	anewarray	#30; //class java/lang/Object
   37:	astore_3
   38:	getstatic	#48; //Field scala/Array$.MODULE$:Lscala/Array$;
   41:	aload_0
   42:	invokeinterface	#52,  1; //InterfaceMethod scala/collection/mutable/ResizableArray.array:()[Ljava/lang/Object;
   47:	iconst_0
   48:	aload_3
   49:	iconst_0
   50:	aload_0
   51:	invokeinterface	#70,  1; //InterfaceMethod scala/collection/mutable/ResizableArray.size0:()I
   56:	invokevirtual	#55; //Method scala/Array$.copy:(Ljava/lang/Object;ILjava/lang/Object;II)V
   59:	aload_0
   60:	aload_3
   61:	invokeinterface	#34,  2; //InterfaceMethod scala/collection/mutable/ResizableArray.array_$eq:([Ljava/lang/Object;)V
   66:	return
  LineNumberTable: 
   line 89: 0
   line 90: 11
   line 91: 21
   line 92: 26
   line 94: 33
   line 95: 38
   line 97: 59
   line 89: 66

  LocalVariableTable: 
   Start  Length  Slot  Name   Signature
   0      67      0    $this       Lscala/collection/mutable/ResizableArray;
   0      67      1    n       I
   21      45      2    newsize       I
   38      28      3    newar       [Ljava/lang/Object;


public static void reduceToSize(scala.collection.mutable.ResizableArray, int);
  Code:
   Stack=3, Locals=2, Args_size=2
   0:	getstatic	#12; //Field scala/Predef$.MODULE$:Lscala/Predef$;
   3:	iload_1
   4:	aload_0
   5:	invokeinterface	#70,  1; //InterfaceMethod scala/collection/mutable/ResizableArray.size0:()I
   10:	if_icmpgt	17
   13:	iconst_1
   14:	goto	18
   17:	iconst_0
   18:	invokevirtual	#78; //Method scala/Predef$.require:(Z)V
   21:	aload_0
   22:	invokeinterface	#70,  1; //InterfaceMethod scala/collection/mutable/ResizableArray.size0:()I
   27:	iload_1
   28:	if_icmple	62
   31:	aload_0
   32:	aload_0
   33:	invokeinterface	#70,  1; //InterfaceMethod scala/collection/mutable/ResizableArray.size0:()I
   38:	iconst_1
   39:	isub
   40:	invokeinterface	#38,  2; //InterfaceMethod scala/collection/mutable/ResizableArray.size0_$eq:(I)V
   45:	aload_0
   46:	invokeinterface	#52,  1; //InterfaceMethod scala/collection/mutable/ResizableArray.array:()[Ljava/lang/Object;
   51:	aload_0
   52:	invokeinterface	#70,  1; //InterfaceMethod scala/collection/mutable/ResizableArray.size0:()I
   57:	aconst_null
   58:	aastore
   59:	goto	21
   62:	return
  LineNumberTable: 
   line 80: 0
   line 81: 21
   line 82: 31
   line 83: 45
   line 79: 62

  LocalVariableTable: 
   Start  Length  Slot  Name   Signature
   0      63      0    $this       Lscala/collection/mutable/ResizableArray;
   0      63      1    sz       I


public static void copyToArray(scala.collection.mutable.ResizableArray, java.lang.Object, int, int);
  Code:
   Stack=6, Locals=5, Args_size=4
   0:	getstatic	#12; //Field scala/Predef$.MODULE$:Lscala/Predef$;
   3:	getstatic	#12; //Field scala/Predef$.MODULE$:Lscala/Predef$;
   6:	iload_3
   7:	invokevirtual	#22; //Method scala/Predef$.intWrapper:(I)Lscala/runtime/RichInt;
   10:	getstatic	#86; //Field scala/runtime/ScalaRunTime$.MODULE$:Lscala/runtime/ScalaRunTime$;
   13:	aload_1
   14:	invokevirtual	#90; //Method scala/runtime/ScalaRunTime$.array_length:(Ljava/lang/Object;)I
   17:	iload_2
   18:	isub
   19:	invokevirtual	#93; //Method scala/runtime/RichInt.min:(I)I
   22:	invokevirtual	#22; //Method scala/Predef$.intWrapper:(I)Lscala/runtime/RichInt;
   25:	aload_0
   26:	invokeinterface	#96,  1; //InterfaceMethod scala/collection/mutable/ResizableArray.length:()I
   31:	invokevirtual	#93; //Method scala/runtime/RichInt.min:(I)I
   34:	istore	4
   36:	getstatic	#48; //Field scala/Array$.MODULE$:Lscala/Array$;
   39:	aload_0
   40:	invokeinterface	#52,  1; //InterfaceMethod scala/collection/mutable/ResizableArray.array:()[Ljava/lang/Object;
   45:	iconst_0
   46:	aload_1
   47:	iload_2
   48:	iload	4
   50:	invokevirtual	#55; //Method scala/Array$.copy:(Ljava/lang/Object;ILjava/lang/Object;II)V
   53:	return
  LineNumberTable: 
   line 71: 0
   line 72: 36

  LocalVariableTable: 
   Start  Length  Slot  Name   Signature
   0      54      0    $this       Lscala/collection/mutable/ResizableArray;
   0      54      1    xs       Ljava/lang/Object;
   0      54      2    start       I
   0      54      3    len       I
   36      17      4    len1       I


public static void foreach(scala.collection.mutable.ResizableArray, scala.Function1);
  Code:
   Stack=3, Locals=3, Args_size=2
   0:	iconst_0
   1:	istore_2
   2:	iload_2
   3:	aload_0
   4:	invokeinterface	#106,  1; //InterfaceMethod scala/collection/SeqLike.size:()I
   9:	if_icmpge	34
   12:	aload_1
   13:	aload_0
   14:	invokeinterface	#52,  1; //InterfaceMethod scala/collection/mutable/ResizableArray.array:()[Ljava/lang/Object;
   19:	iload_2
   20:	aaload
   21:	invokeinterface	#112,  2; //InterfaceMethod scala/Function1.apply:(Ljava/lang/Object;)Ljava/lang/Object;
   26:	pop
   27:	iload_2
   28:	iconst_1
   29:	iadd
   30:	istore_2
   31:	goto	2
   34:	return
  LineNumberTable: 
   line 54: 0
   line 55: 2
   line 56: 12
   line 57: 27
   line 53: 34

  LocalVariableTable: 
   Start  Length  Slot  Name   Signature
   0      35      0    $this       Lscala/collection/mutable/ResizableArray;
   0      35      1    f       Lscala/Function1;
   2      33      2    i       I


public static void update(scala.collection.mutable.ResizableArray, int, java.lang.Object);
  Code:
   Stack=3, Locals=3, Args_size=3
   0:	iload_1
   1:	aload_0
   2:	invokeinterface	#70,  1; //InterfaceMethod scala/collection/mutable/ResizableArray.size0:()I
   7:	if_icmplt	25
   10:	new	#119; //class java/lang/IndexOutOfBoundsException
   13:	dup
   14:	iload_1
   15:	invokestatic	#125; //Method scala/runtime/BoxesRunTime.boxToInteger:(I)Ljava/lang/Integer;
   18:	invokevirtual	#129; //Method java/lang/Object.toString:()Ljava/lang/String;
   21:	invokespecial	#133; //Method java/lang/IndexOutOfBoundsException."<init>":(Ljava/lang/String;)V
   24:	athrow
   25:	aload_0
   26:	invokeinterface	#52,  1; //InterfaceMethod scala/collection/mutable/ResizableArray.array:()[Ljava/lang/Object;
   31:	iload_1
   32:	aload_2
   33:	aastore
   34:	return
  LineNumberTable: 
   line 49: 0
   line 50: 25

  LocalVariableTable: 
   Start  Length  Slot  Name   Signature
   0      35      0    $this       Lscala/collection/mutable/ResizableArray;
   0      35      1    idx       I
   0      35      2    elem       Ljava/lang/Object;


public static java.lang.Object apply(scala.collection.mutable.ResizableArray, int);
  Code:
   Stack=3, Locals=2, Args_size=2
   0:	iload_1
   1:	aload_0
   2:	invokeinterface	#70,  1; //InterfaceMethod scala/collection/mutable/ResizableArray.size0:()I
   7:	if_icmplt	25
   10:	new	#119; //class java/lang/IndexOutOfBoundsException
   13:	dup
   14:	iload_1
   15:	invokestatic	#125; //Method scala/runtime/BoxesRunTime.boxToInteger:(I)Ljava/lang/Integer;
   18:	invokevirtual	#129; //Method java/lang/Object.toString:()Ljava/lang/String;
   21:	invokespecial	#133; //Method java/lang/IndexOutOfBoundsException."<init>":(Ljava/lang/String;)V
   24:	athrow
   25:	aload_0
   26:	invokeinterface	#52,  1; //InterfaceMethod scala/collection/mutable/ResizableArray.array:()[Ljava/lang/Object;
   31:	iload_1
   32:	aaload
   33:	areturn
  LineNumberTable: 
   line 44: 0
   line 45: 25

  LocalVariableTable: 
   Start  Length  Slot  Name   Signature
   0      34      0    $this       Lscala/collection/mutable/ResizableArray;
   0      34      1    idx       I


public static int length(scala.collection.mutable.ResizableArray);
  Code:
   Stack=1, Locals=1, Args_size=1
   0:	aload_0
   1:	invokeinterface	#70,  1; //InterfaceMethod scala/collection/mutable/ResizableArray.size0:()I
   6:	ireturn
  LineNumberTable: 
   line 41: 0

  LocalVariableTable: 
   Start  Length  Slot  Name   Signature
   0      7      0    $this       Lscala/collection/mutable/ResizableArray;


public static int initialSize(scala.collection.mutable.ResizableArray);
  Code:
   Stack=1, Locals=1, Args_size=1
   0:	ldc	#138; //int 16
   2:	ireturn
  LineNumberTable: 
   line 31: 0

  LocalVariableTable: 
   Start  Length  Slot  Name   Signature
   0      3      0    $this       Lscala/collection/mutable/ResizableArray;


public static scala.collection.generic.GenericCompanion companion(scala.collection.mutable.ResizableArray);
  Code:
   Stack=1, Locals=1, Args_size=1
   0:	getstatic	#145; //Field scala/collection/mutable/ResizableArray$.MODULE$:Lscala/collection/mutable/ResizableArray$;
   3:	areturn
  LineNumberTable: 
   line 29: 0

  LocalVariableTable: 
   Start  Length  Slot  Name   Signature
   0      4      0    $this       Lscala/collection/mutable/ResizableArray;


}

