Compiled from "RevertibleHistory.scala"
public class scala.collection.mutable.RevertibleHistory extends scala.collection.mutable.History implements scala.collection.mutable.Undoable,scala.ScalaObject,java.io.Serializable
  SourceFile: "RevertibleHistory.scala"
  Signature: length = 0x2
   00 31 
  ScalaSig: length = 0x12E
   05 00 33 06 04 01 02 00 09 02 11 52 65 76 65 72
   74 69 62 6C 65 48 69 73 74 6F 72 79 0A 02 03 04
   01 07 6D 75 74 61 62 6C 65 0A 02 05 06 01 0A 63
   6F 6C 6C 65 63 74 69 6F 6E 0A 01 07 01 05 73 63
   61 6C 61 03 00 15 03 0A 11 1C 13 04 00 0B 18 22
   10 04 0C 0D 0F 1B 0D 01 02 09 02 0E 02 02 07 48
   69 73 74 6F 72 79 10 02 10 11 0C 00 04 08 12 00
   FFFFFF84 FFFFFF80 FFFFFF80 FFFFFFC2 00 13 02 03 45 76 74 11 02 14 18 10
   02 15 16 0D 01 06 09 02 17 06 02 07 4E 6F 74 68
   69 6E 67 10 02 0C 19 09 02 1A 02 02 08 55 6E 64
   6F 61 62 6C 65 10 02 10 1C 04 08 1D 00 FFFFFF84 FFFFFF80 FFFFFF80
   FFFFFFC2 00 1E 02 03 50 75 62 11 02 14 1F 10 02 15 20
   09 02 21 06 02 03 41 6E 79 10 02 15 23 09 02 24
   06 02 0B 53 63 61 6C 61 4F 62 6A 65 63 74 08 05
   26 00 FFFFFF84 00 27 01 06 3C 69 6E 69 74 3E 14 01 28
   10 04 0C 00 0F 1B 08 05 2A 00 FFFFFF84 00 2B 01 04 75
   6E 64 6F 14 01 2C 10 02 15 2D 09 02 2E 06 02 04
   55 6E 69 74 28 02 00 30 10 02 15 31 09 02 32 06
   02 0C 73 65 72 69 61 6C 69 7A 61 62 6C 65 
  InnerClass: 
   public final $anonfun$undo$1=class scala/collection/mutable/RevertibleHistory$$anonfun$undo$1 of class scala/collection/mutable/RevertibleHistory
  minor version: 0
  major version: 49
  Constant pool:
Asciz	SourceFile;
Asciz	RevertibleHistory.scala;
Asciz	undo;
Asciz	()V;
Asciz	Code;
Asciz	LineNumberTable;
Asciz	scala/collection/mutable/RevertibleHistory;
class	scala/collection/mutable/RevertibleHistory
Asciz	log;
Asciz	()Lscala/collection/mutable/Queue;;
NameAndType	log:()Lscala/collection/mutable/Queue;
Method	scala/collection/mutable/RevertibleHistory.log:()Lscala/collection/mutable/Queue;
Asciz	scala/collection/mutable/Queue;
class	scala/collection/mutable/Queue
Asciz	toList;
Asciz	()Lscala/collection/immutable/List;;
NameAndType	toList:()Lscala/collection/immutable/List;
Method	scala/collection/mutable/Queue.toList:()Lscala/collection/immutable/List;
Asciz	scala/collection/immutable/List;
class	scala/collection/immutable/List
Asciz	reverse;
NameAndType	reverse:()Lscala/collection/immutable/List;
Method	scala/collection/immutable/List.reverse:()Lscala/collection/immutable/List;
Asciz	clear;
NameAndType	clear:()V
Method	scala/collection/mutable/RevertibleHistory.clear:()V
Asciz	scala/collection/mutable/RevertibleHistory$$anonfun$undo$1;
class	scala/collection/mutable/RevertibleHistory$$anonfun$undo$1
Asciz	<init>;
Asciz	(Lscala/collection/mutable/RevertibleHistory;)V;
NameAndType	"<init>":(Lscala/collection/mutable/RevertibleHistory;)V
Method	scala/collection/mutable/RevertibleHistory$$anonfun$undo$1."<init>":(Lscala/collection/mutable/RevertibleHistory;)V
Asciz	scala/collection/LinearSeqLike;
class	scala/collection/LinearSeqLike
Asciz	foreach;
Asciz	(Lscala/Function1;)V;
NameAndType	foreach:(Lscala/Function1;)V
InterfaceMethod	scala/collection/LinearSeqLike.foreach:(Lscala/Function1;)V
Asciz	this;
Asciz	Lscala/collection/mutable/RevertibleHistory;;
Asciz	old;
Asciz	Lscala/collection/immutable/List;;
Asciz	LocalVariableTable;
Asciz	scala/collection/mutable/History;
class	scala/collection/mutable/History
NameAndType	"<init>":()V
Method	scala/collection/mutable/History."<init>":()V
Asciz	Signature;
Asciz	<Evt::Lscala/collection/mutable/Undoable;Pub:Ljava/lang/Object;>Lscala/collection/mutable/History<TEvt;TPub;>;Lscala/collection/mutable/Undoable;Lscala/ScalaObject;;
Asciz	ScalaSig;
Asciz	InnerClasses;
Asciz	$anonfun$undo$1;
Asciz	scala/collection/mutable/Undoable;
class	scala/collection/mutable/Undoable
Asciz	scala/ScalaObject;
class	scala/ScalaObject
Asciz	java/io/Serializable;
class	java/io/Serializable

{
public void undo();
  Signature: ()V
  Code:
   Stack=4, Locals=2, Args_size=1
	aload_0
	invokevirtual	Method log:()Lscala/collection/mutable/Queue;
	invokevirtual	Method scala/collection/mutable/Queue.toList:()Lscala/collection/immutable/List;
	invokevirtual	Method scala/collection/immutable/List.reverse:()Lscala/collection/immutable/List;
	astore_1
	aload_0
	invokevirtual	Method clear:()V
	aload_1
	new	class scala/collection/mutable/RevertibleHistory$$anonfun$undo$1
	dup
	aload_0
	invokespecial	Method scala/collection/mutable/RevertibleHistory$$anonfun$undo$1."<init>":(Lscala/collection/mutable/RevertibleHistory;)V
	invokeinterface	InterfaceMethod scala/collection/LinearSeqLike.foreach:(Lscala/Function1;)V
	return
  Labels:
  LocalVariableTable: 
   Start  Length  Slot  Name   Signature
   0      30      0    this       Lscala/collection/mutable/RevertibleHistory;
   11      18      1    old       Lscala/collection/immutable/List;


public scala.collection.mutable.RevertibleHistory();
  Signature: ()V
  Code:
   Stack=1, Locals=1, Args_size=1
	aload_0
	invokespecial	Method scala/collection/mutable/History."<init>":()V
	return
  Labels:
  Signature: length = 0x2
   00 04 

}

