Compiled from "RevertibleHistory.scala"
public class scala.collection.mutable.RevertableHistory extends scala.collection.mutable.History implements scala.collection.mutable.Undoable,scala.ScalaObject,java.io.Serializable
  SourceFile: "RevertibleHistory.scala"
  Signature: length = 0x2
   00 31 
  ScalaSig: length = 0x12A
   05 00 33 06 04 01 02 00 09 02 11 52 65 76 65 72
   74 61 62 6C 65 48 69 73 74 6F 72 79 0A 02 03 04
   01 07 6D 75 74 61 62 6C 65 0A 02 05 06 01 0A 63
   6F 6C 6C 65 63 74 69 6F 6E 0A 01 07 01 05 73 63
   61 6C 61 03 00 15 03 0A 11 1C 13 04 00 0B 18 22
   10 04 0C 0D 0F 1B 0D 01 02 09 02 0E 02 02 07 48
   69 73 74 6F 72 79 10 02 10 11 0C 00 04 08 12 00
   FFFFFF84 FFFFFF80 FFFFFF80 FFFFFFC2 00 13 02 01 41 11 02 14 18 10 02 15
   16 0D 01 06 09 02 17 06 02 07 4E 6F 74 68 69 6E
   67 10 02 0C 19 09 02 1A 02 02 08 55 6E 64 6F 61
   62 6C 65 10 02 10 1C 04 08 1D 00 FFFFFF84 FFFFFF80 FFFFFF80 FFFFFFC2 00
   1E 02 01 42 11 02 14 1F 10 02 15 20 09 02 21 06
   02 03 41 6E 79 10 02 15 23 09 02 24 06 02 0B 53
   63 61 6C 61 4F 62 6A 65 63 74 08 05 26 00 FFFFFF84 00
   27 01 06 3C 69 6E 69 74 3E 14 01 28 10 04 0C 00
   0F 1B 08 05 2A 00 FFFFFF84 00 2B 01 04 75 6E 64 6F 14
   01 2C 10 02 15 2D 09 02 2E 06 02 04 55 6E 69 74
   28 02 00 30 10 02 15 31 09 02 32 06 02 0C 73 65
   72 69 61 6C 69 7A 61 62 6C 65 
  InnerClass: 
   public final #52= #34 of #14; //$anonfun$undo$1=class scala/collection/mutable/RevertableHistory$$anonfun$undo$1 of class scala/collection/mutable/RevertableHistory
  minor version: 0
  major version: 49
  Constant pool:
const #1 = Asciz	SourceFile;
const #2 = Asciz	RevertibleHistory.scala;
const #3 = Asciz	<init>;
const #4 = Asciz	()V;
const #5 = Asciz	Code;
const #6 = Asciz	LineNumberTable;
const #7 = Asciz	scala/collection/mutable/History;
const #8 = class	#7;	//  scala/collection/mutable/History
const #9 = NameAndType	#3:#4;//  "<init>":()V
const #10 = Method	#8.#9;	//  scala/collection/mutable/History."<init>":()V
const #11 = Asciz	Signature;
const #12 = Asciz	undo;
const #13 = Asciz	scala/collection/mutable/RevertableHistory;
const #14 = class	#13;	//  scala/collection/mutable/RevertableHistory
const #15 = Asciz	log;
const #16 = Asciz	()Lscala/collection/mutable/Queue;;
const #17 = NameAndType	#15:#16;//  log:()Lscala/collection/mutable/Queue;
const #18 = Method	#14.#17;	//  scala/collection/mutable/RevertableHistory.log:()Lscala/collection/mutable/Queue;
const #19 = Asciz	scala/collection/mutable/Queue;
const #20 = class	#19;	//  scala/collection/mutable/Queue
const #21 = Asciz	toList;
const #22 = Asciz	()Lscala/collection/immutable/List;;
const #23 = NameAndType	#21:#22;//  toList:()Lscala/collection/immutable/List;
const #24 = Method	#20.#23;	//  scala/collection/mutable/Queue.toList:()Lscala/collection/immutable/List;
const #25 = Asciz	scala/collection/immutable/List;
const #26 = class	#25;	//  scala/collection/immutable/List
const #27 = Asciz	reverse;
const #28 = NameAndType	#27:#22;//  reverse:()Lscala/collection/immutable/List;
const #29 = Method	#26.#28;	//  scala/collection/immutable/List.reverse:()Lscala/collection/immutable/List;
const #30 = Asciz	clear;
const #31 = NameAndType	#30:#4;//  clear:()V
const #32 = Method	#14.#31;	//  scala/collection/mutable/RevertableHistory.clear:()V
const #33 = Asciz	scala/collection/mutable/RevertableHistory$$anonfun$undo$1;
const #34 = class	#33;	//  scala/collection/mutable/RevertableHistory$$anonfun$undo$1
const #35 = Asciz	(Lscala/collection/mutable/RevertableHistory;)V;
const #36 = NameAndType	#3:#35;//  "<init>":(Lscala/collection/mutable/RevertableHistory;)V
const #37 = Method	#34.#36;	//  scala/collection/mutable/RevertableHistory$$anonfun$undo$1."<init>":(Lscala/collection/mutable/RevertableHistory;)V
const #38 = Asciz	scala/collection/generic/LinearSequenceTemplate;
const #39 = class	#38;	//  scala/collection/generic/LinearSequenceTemplate
const #40 = Asciz	foreach;
const #41 = Asciz	(Lscala/Function1;)V;
const #42 = NameAndType	#40:#41;//  foreach:(Lscala/Function1;)V
const #43 = InterfaceMethod	#39.#42;	//  scala/collection/generic/LinearSequenceTemplate.foreach:(Lscala/Function1;)V
const #44 = Asciz	this;
const #45 = Asciz	Lscala/collection/mutable/RevertableHistory;;
const #46 = Asciz	old;
const #47 = Asciz	Lscala/collection/immutable/List;;
const #48 = Asciz	LocalVariableTable;
const #49 = Asciz	<A::Lscala/collection/mutable/Undoable;B:Ljava/lang/Object;>Lscala/collection/mutable/History<TA;TB;>;Lscala/collection/mutable/Undoable;Lscala/ScalaObject;;
const #50 = Asciz	ScalaSig;
const #51 = Asciz	InnerClasses;
const #52 = Asciz	$anonfun$undo$1;
const #53 = Asciz	scala/collection/mutable/Undoable;
const #54 = class	#53;	//  scala/collection/mutable/Undoable
const #55 = Asciz	scala/ScalaObject;
const #56 = class	#55;	//  scala/ScalaObject
const #57 = Asciz	java/io/Serializable;
const #58 = class	#57;	//  java/io/Serializable

{
public scala.collection.mutable.RevertableHistory();
  Code:
   Stack=1, Locals=1, Args_size=1
   0:	aload_0
   1:	invokespecial	#10; //Method scala/collection/mutable/History."<init>":()V
   4:	return
  LineNumberTable: 
   line 24: 0

  Signature: length = 0x2
   00 04 

public void undo();
  Code:
   Stack=4, Locals=2, Args_size=1
   0:	aload_0
   1:	invokevirtual	#18; //Method log:()Lscala/collection/mutable/Queue;
   4:	invokevirtual	#24; //Method scala/collection/mutable/Queue.toList:()Lscala/collection/immutable/List;
   7:	invokevirtual	#29; //Method scala/collection/immutable/List.reverse:()Lscala/collection/immutable/List;
   10:	astore_1
   11:	aload_0
   12:	invokevirtual	#32; //Method clear:()V
   15:	aload_1
   16:	new	#34; //class scala/collection/mutable/RevertableHistory$$anonfun$undo$1
   19:	dup
   20:	aload_0
   21:	invokespecial	#37; //Method scala/collection/mutable/RevertableHistory$$anonfun$undo$1."<init>":(Lscala/collection/mutable/RevertableHistory;)V
   24:	invokeinterface	#43,  2; //InterfaceMethod scala/collection/generic/LinearSequenceTemplate.foreach:(Lscala/Function1;)V
   29:	return
  LineNumberTable: 
   line 29: 0
   line 30: 11
   line 31: 15

  LocalVariableTable: 
   Start  Length  Slot  Name   Signature
   0      30      0    this       Lscala/collection/mutable/RevertableHistory;
   11      18      1    old       Lscala/collection/immutable/List;


}

