Compiled from "SetLike.scala"
public abstract class scala.collection.mutable.SetLike$class extends java.lang.Object
  SourceFile: "SetLike.scala"
  Scala: length = 0x
   
  InnerClass: 
   public final #194= #156 of #19; //$anonfun$clear$1=class scala/collection/mutable/SetLike$$anonfun$clear$1 of class scala/collection/mutable/SetLike
   public final #195= #168 of #19; //$anonfun$retain$1=class scala/collection/mutable/SetLike$$anonfun$retain$1 of class scala/collection/mutable/SetLike
   public final #196= #132 of #19; //$anonfun$$plus$plus$1=class scala/collection/mutable/SetLike$$anonfun$$plus$plus$1 of class scala/collection/mutable/SetLike
   public final #197= #129 of #19; //$anonfun$$plus$plus$2=class scala/collection/mutable/SetLike$$anonfun$$plus$plus$2 of class scala/collection/mutable/SetLike
   public final #198= #57 of #19; //$anonfun$$less$less$1=class scala/collection/mutable/SetLike$$anonfun$$less$less$1 of class scala/collection/mutable/SetLike
   public final #199= #108 of #19; //$anonfun$$minus$minus$1=class scala/collection/mutable/SetLike$$anonfun$$minus$minus$1 of class scala/collection/mutable/SetLike
   public final #200= #96 of #19; //$anonfun$$minus$minus$2=class scala/collection/mutable/SetLike$$anonfun$$minus$minus$2 of class scala/collection/mutable/SetLike
  minor version: 0
  major version: 49
  Constant pool:
const #1 = Asciz	SourceFile;
const #2 = Asciz	SetLike.scala;
const #3 = Asciz	$init$;
const #4 = Asciz	(Lscala/collection/mutable/SetLike;)V;
const #5 = Asciz	Code;
const #6 = Asciz	LineNumberTable;
const #7 = Asciz	$this;
const #8 = Asciz	Lscala/collection/mutable/SetLike;;
const #9 = Asciz	LocalVariableTable;
const #10 = Asciz	$less$less;
const #11 = Asciz	(Lscala/collection/mutable/SetLike;Lscala/collection/script/Message;)V;
const #12 = Asciz	scala/collection/script/Include;
const #13 = class	#12;	//  scala/collection/script/Include
const #14 = Asciz	elem;
const #15 = Asciz	()Ljava/lang/Object;;
const #16 = NameAndType	#14:#15;//  elem:()Ljava/lang/Object;
const #17 = Method	#13.#16;	//  scala/collection/script/Include.elem:()Ljava/lang/Object;
const #18 = Asciz	scala/collection/mutable/SetLike;
const #19 = class	#18;	//  scala/collection/mutable/SetLike
const #20 = Asciz	$plus$eq;
const #21 = Asciz	(Ljava/lang/Object;)Lscala/collection/mutable/SetLike;;
const #22 = NameAndType	#20:#21;//  $plus$eq:(Ljava/lang/Object;)Lscala/collection/mutable/SetLike;
const #23 = InterfaceMethod	#19.#22;	//  scala/collection/mutable/SetLike.$plus$eq:(Ljava/lang/Object;)Lscala/collection/mutable/SetLike;
const #24 = Asciz	scala/MatchError;
const #25 = class	#24;	//  scala/MatchError
const #26 = Asciz	java/lang/Object;
const #27 = class	#26;	//  java/lang/Object
const #28 = Asciz	toString;
const #29 = Asciz	()Ljava/lang/String;;
const #30 = NameAndType	#28:#29;//  toString:()Ljava/lang/String;
const #31 = Method	#27.#30;	//  java/lang/Object.toString:()Ljava/lang/String;
const #32 = Asciz	<init>;
const #33 = Asciz	(Ljava/lang/String;)V;
const #34 = NameAndType	#32:#33;//  "<init>":(Ljava/lang/String;)V
const #35 = Method	#25.#34;	//  scala/MatchError."<init>":(Ljava/lang/String;)V
const #36 = Asciz	scala/collection/script/Remove;
const #37 = class	#36;	//  scala/collection/script/Remove
const #38 = Method	#37.#16;	//  scala/collection/script/Remove.elem:()Ljava/lang/Object;
const #39 = Asciz	$minus$eq;
const #40 = NameAndType	#39:#21;//  $minus$eq:(Ljava/lang/Object;)Lscala/collection/mutable/SetLike;
const #41 = InterfaceMethod	#19.#40;	//  scala/collection/mutable/SetLike.$minus$eq:(Ljava/lang/Object;)Lscala/collection/mutable/SetLike;
const #42 = Asciz	scala/collection/script/Reset;
const #43 = class	#42;	//  scala/collection/script/Reset
const #44 = Asciz	clear;
const #45 = Asciz	()V;
const #46 = NameAndType	#44:#45;//  clear:()V
const #47 = InterfaceMethod	#19.#46;	//  scala/collection/mutable/SetLike.clear:()V
const #48 = Asciz	scala/collection/script/Script;
const #49 = class	#48;	//  scala/collection/script/Script
const #50 = Asciz	scala/collection/IndexedSeqLike;
const #51 = class	#50;	//  scala/collection/IndexedSeqLike
const #52 = Asciz	iterator;
const #53 = Asciz	()Lscala/collection/Iterator;;
const #54 = NameAndType	#52:#53;//  iterator:()Lscala/collection/Iterator;
const #55 = InterfaceMethod	#51.#54;	//  scala/collection/IndexedSeqLike.iterator:()Lscala/collection/Iterator;
const #56 = Asciz	scala/collection/mutable/SetLike$$anonfun$$less$less$1;
const #57 = class	#56;	//  scala/collection/mutable/SetLike$$anonfun$$less$less$1
const #58 = NameAndType	#32:#4;//  "<init>":(Lscala/collection/mutable/SetLike;)V
const #59 = Method	#57.#58;	//  scala/collection/mutable/SetLike$$anonfun$$less$less$1."<init>":(Lscala/collection/mutable/SetLike;)V
const #60 = Asciz	scala/collection/Iterator;
const #61 = class	#60;	//  scala/collection/Iterator
const #62 = Asciz	foreach;
const #63 = Asciz	(Lscala/Function1;)V;
const #64 = NameAndType	#62:#63;//  foreach:(Lscala/Function1;)V
const #65 = InterfaceMethod	#61.#64;	//  scala/collection/Iterator.foreach:(Lscala/Function1;)V
const #66 = Asciz	java/lang/UnsupportedOperationException;
const #67 = class	#66;	//  java/lang/UnsupportedOperationException
const #68 = Asciz	scala/collection/mutable/StringBuilder;
const #69 = class	#68;	//  scala/collection/mutable/StringBuilder
const #70 = NameAndType	#32:#45;//  "<init>":()V
const #71 = Method	#69.#70;	//  scala/collection/mutable/StringBuilder."<init>":()V
const #72 = Asciz	message ;
const #73 = String	#72;	//  message 
const #74 = Asciz	append;
const #75 = Asciz	(Ljava/lang/Object;)Lscala/collection/mutable/StringBuilder;;
const #76 = NameAndType	#74:#75;//  append:(Ljava/lang/Object;)Lscala/collection/mutable/StringBuilder;
const #77 = Method	#69.#76;	//  scala/collection/mutable/StringBuilder.append:(Ljava/lang/Object;)Lscala/collection/mutable/StringBuilder;
const #78 = Asciz	 not understood;
const #79 = String	#78;	//   not understood
const #80 = Method	#69.#30;	//  scala/collection/mutable/StringBuilder.toString:()Ljava/lang/String;
const #81 = Method	#67.#34;	//  java/lang/UnsupportedOperationException."<init>":(Ljava/lang/String;)V
const #82 = Asciz	cmd;
const #83 = Asciz	Lscala/collection/script/Message;;
const #84 = Asciz	temp2;
const #85 = Asciz	Lscala/collection/script/Include;;
const #86 = Asciz	temp4;
const #87 = Asciz	Ljava/lang/Object;;
const #88 = Asciz	temp5;
const #89 = Asciz	Lscala/collection/script/Remove;;
const #90 = Asciz	temp7;
const #91 = Asciz	temp9;
const #92 = Asciz	Lscala/collection/script/Script;;
const #93 = Asciz	$minus$minus;
const #94 = Asciz	(Lscala/collection/mutable/SetLike;Lscala/collection/Iterator;)Lscala/collection/mutable/SetLike;;
const #95 = Asciz	scala/collection/mutable/SetLike$$anonfun$$minus$minus$2;
const #96 = class	#95;	//  scala/collection/mutable/SetLike$$anonfun$$minus$minus$2
const #97 = Method	#96.#58;	//  scala/collection/mutable/SetLike$$anonfun$$minus$minus$2."<init>":(Lscala/collection/mutable/SetLike;)V
const #98 = Asciz	scala/collection/TraversableLike;
const #99 = class	#98;	//  scala/collection/TraversableLike
const #100 = Asciz	repr;
const #101 = NameAndType	#100:#15;//  repr:()Ljava/lang/Object;
const #102 = InterfaceMethod	#99.#101;	//  scala/collection/TraversableLike.repr:()Ljava/lang/Object;
const #103 = Asciz	iter;
const #104 = Asciz	Lscala/collection/Iterator;;
const #105 = Asciz	Deprecated;
const #106 = Asciz	(Lscala/collection/mutable/SetLike;Lscala/collection/Traversable;)Lscala/collection/mutable/SetLike;;
const #107 = Asciz	scala/collection/mutable/SetLike$$anonfun$$minus$minus$1;
const #108 = class	#107;	//  scala/collection/mutable/SetLike$$anonfun$$minus$minus$1
const #109 = Method	#108.#58;	//  scala/collection/mutable/SetLike$$anonfun$$minus$minus$1."<init>":(Lscala/collection/mutable/SetLike;)V
const #110 = Asciz	scala/collection/generic/GenericTraversableTemplate;
const #111 = class	#110;	//  scala/collection/generic/GenericTraversableTemplate
const #112 = InterfaceMethod	#111.#64;	//  scala/collection/generic/GenericTraversableTemplate.foreach:(Lscala/Function1;)V
const #113 = Asciz	Lscala/collection/Traversable;;
const #114 = Asciz	$minus;
const #115 = Asciz	(Lscala/collection/mutable/SetLike;Ljava/lang/Object;Ljava/lang/Object;Lscala/collection/Seq;)Lscala/collection/mutable/SetLike;;
const #116 = Asciz	scala/collection/generic/Shrinkable;
const #117 = class	#116;	//  scala/collection/generic/Shrinkable
const #118 = Asciz	$minus$minus$eq;
const #119 = Asciz	(Lscala/collection/Traversable;)Lscala/collection/generic/Shrinkable;;
const #120 = NameAndType	#118:#119;//  $minus$minus$eq:(Lscala/collection/Traversable;)Lscala/collection/generic/Shrinkable;
const #121 = InterfaceMethod	#117.#120;	//  scala/collection/generic/Shrinkable.$minus$minus$eq:(Lscala/collection/Traversable;)Lscala/collection/generic/Shrinkable;
const #122 = Asciz	elem1;
const #123 = Asciz	elem2;
const #124 = Asciz	elems;
const #125 = Asciz	Lscala/collection/Seq;;
const #126 = Asciz	(Lscala/collection/mutable/SetLike;Ljava/lang/Object;)Lscala/collection/mutable/SetLike;;
const #127 = Asciz	$plus$plus;
const #128 = Asciz	scala/collection/mutable/SetLike$$anonfun$$plus$plus$2;
const #129 = class	#128;	//  scala/collection/mutable/SetLike$$anonfun$$plus$plus$2
const #130 = Method	#129.#58;	//  scala/collection/mutable/SetLike$$anonfun$$plus$plus$2."<init>":(Lscala/collection/mutable/SetLike;)V
const #131 = Asciz	scala/collection/mutable/SetLike$$anonfun$$plus$plus$1;
const #132 = class	#131;	//  scala/collection/mutable/SetLike$$anonfun$$plus$plus$1
const #133 = Method	#132.#58;	//  scala/collection/mutable/SetLike$$anonfun$$plus$plus$1."<init>":(Lscala/collection/mutable/SetLike;)V
const #134 = Asciz	$plus;
const #135 = Asciz	scala/collection/generic/Growable;
const #136 = class	#135;	//  scala/collection/generic/Growable
const #137 = Asciz	$plus$plus$eq;
const #138 = Asciz	(Lscala/collection/Traversable;)Lscala/collection/generic/Growable;;
const #139 = NameAndType	#137:#138;//  $plus$plus$eq:(Lscala/collection/Traversable;)Lscala/collection/generic/Growable;
const #140 = InterfaceMethod	#136.#139;	//  scala/collection/generic/Growable.$plus$plus$eq:(Lscala/collection/Traversable;)Lscala/collection/generic/Growable;
const #141 = Asciz	result;
const #142 = Asciz	(Lscala/collection/mutable/SetLike;)Lscala/collection/mutable/SetLike;;
const #143 = Asciz	clone;
const #144 = Asciz	(Lscala/collection/mutable/SetLike;)Lscala/collection/mutable/Set;;
const #145 = Asciz	scala/collection/SetLike;
const #146 = class	#145;	//  scala/collection/SetLike
const #147 = Asciz	empty;
const #148 = Asciz	()Lscala/collection/SetLike;;
const #149 = NameAndType	#147:#148;//  empty:()Lscala/collection/SetLike;
const #150 = InterfaceMethod	#146.#149;	//  scala/collection/SetLike.empty:()Lscala/collection/SetLike;
const #151 = Asciz	scala/collection/Traversable;
const #152 = class	#151;	//  scala/collection/Traversable
const #153 = Asciz	scala/collection/mutable/Set;
const #154 = class	#153;	//  scala/collection/mutable/Set
const #155 = Asciz	scala/collection/mutable/SetLike$$anonfun$clear$1;
const #156 = class	#155;	//  scala/collection/mutable/SetLike$$anonfun$clear$1
const #157 = Method	#156.#58;	//  scala/collection/mutable/SetLike$$anonfun$clear$1."<init>":(Lscala/collection/mutable/SetLike;)V
const #158 = Asciz	scala/collection/IterableLike;
const #159 = class	#158;	//  scala/collection/IterableLike
const #160 = InterfaceMethod	#159.#64;	//  scala/collection/IterableLike.foreach:(Lscala/Function1;)V
const #161 = Asciz	retain;
const #162 = Asciz	(Lscala/collection/mutable/SetLike;Lscala/Function1;)V;
const #163 = Asciz	toList;
const #164 = Asciz	()Lscala/collection/immutable/List;;
const #165 = NameAndType	#163:#164;//  toList:()Lscala/collection/immutable/List;
const #166 = InterfaceMethod	#99.#165;	//  scala/collection/TraversableLike.toList:()Lscala/collection/immutable/List;
const #167 = Asciz	scala/collection/mutable/SetLike$$anonfun$retain$1;
const #168 = class	#167;	//  scala/collection/mutable/SetLike$$anonfun$retain$1
const #169 = NameAndType	#32:#162;//  "<init>":(Lscala/collection/mutable/SetLike;Lscala/Function1;)V
const #170 = Method	#168.#169;	//  scala/collection/mutable/SetLike$$anonfun$retain$1."<init>":(Lscala/collection/mutable/SetLike;Lscala/Function1;)V
const #171 = Asciz	scala/collection/LinearSeqLike;
const #172 = class	#171;	//  scala/collection/LinearSeqLike
const #173 = InterfaceMethod	#172.#64;	//  scala/collection/LinearSeqLike.foreach:(Lscala/Function1;)V
const #174 = Asciz	p$1;
const #175 = Asciz	Lscala/Function1;;
const #176 = Asciz	update;
const #177 = Asciz	(Lscala/collection/mutable/SetLike;Ljava/lang/Object;Z)V;
const #178 = Asciz	included;
const #179 = Asciz	Z;
const #180 = Asciz	remove;
const #181 = Asciz	(Lscala/collection/mutable/SetLike;Ljava/lang/Object;)Z;
const #182 = Asciz	contains;
const #183 = Asciz	(Ljava/lang/Object;)Z;
const #184 = NameAndType	#182:#183;//  contains:(Ljava/lang/Object;)Z
const #185 = InterfaceMethod	#146.#184;	//  scala/collection/SetLike.contains:(Ljava/lang/Object;)Z
const #186 = Asciz	r;
const #187 = Asciz	add;
const #188 = Asciz	newBuilder;
const #189 = Asciz	(Lscala/collection/mutable/SetLike;)Lscala/collection/mutable/Builder;;
const #190 = Asciz	scala/collection/mutable/Builder;
const #191 = class	#190;	//  scala/collection/mutable/Builder
const #192 = Asciz	Scala;
const #193 = Asciz	InnerClasses;
const #194 = Asciz	$anonfun$clear$1;
const #195 = Asciz	$anonfun$retain$1;
const #196 = Asciz	$anonfun$$plus$plus$1;
const #197 = Asciz	$anonfun$$plus$plus$2;
const #198 = Asciz	$anonfun$$less$less$1;
const #199 = Asciz	$anonfun$$minus$minus$1;
const #200 = Asciz	$anonfun$$minus$minus$2;
const #201 = Asciz	scala/collection/mutable/SetLike$class;
const #202 = class	#201;	//  scala/collection/mutable/SetLike$class

{
public static void $init$(scala.collection.mutable.SetLike);
  Code:
   Stack=0, Locals=1, Args_size=1
   0:	return
  LineNumberTable: 
   line 52: 0

  LocalVariableTable: 
   Start  Length  Slot  Name   Signature
   0      1      0    $this       Lscala/collection/mutable/SetLike;


public static void $less$less(scala.collection.mutable.SetLike, scala.collection.script.Message);
  Code:
   Stack=4, Locals=7, Args_size=2
   0:	aload_1
   1:	instanceof	#13; //class scala/collection/script/Include
   4:	ifeq	44
   7:	aload_1
   8:	checkcast	#13; //class scala/collection/script/Include
   11:	astore_2
   12:	aload_2
   13:	invokevirtual	#17; //Method scala/collection/script/Include.elem:()Ljava/lang/Object;
   16:	astore_3
   17:	iconst_1
   18:	ifeq	32
   21:	aload_0
   22:	aload_3
   23:	invokeinterface	#23,  2; //InterfaceMethod scala/collection/mutable/SetLike.$plus$eq:(Ljava/lang/Object;)Lscala/collection/mutable/SetLike;
   28:	pop
   29:	goto	161
   32:	new	#25; //class scala/MatchError
   35:	dup
   36:	aload_1
   37:	invokevirtual	#31; //Method java/lang/Object.toString:()Ljava/lang/String;
   40:	invokespecial	#35; //Method scala/MatchError."<init>":(Ljava/lang/String;)V
   43:	athrow
   44:	aload_1
   45:	instanceof	#37; //class scala/collection/script/Remove
   48:	ifeq	92
   51:	aload_1
   52:	checkcast	#37; //class scala/collection/script/Remove
   55:	astore	4
   57:	aload	4
   59:	invokevirtual	#38; //Method scala/collection/script/Remove.elem:()Ljava/lang/Object;
   62:	astore	5
   64:	iconst_1
   65:	ifeq	80
   68:	aload_0
   69:	aload	5
   71:	invokeinterface	#41,  2; //InterfaceMethod scala/collection/mutable/SetLike.$minus$eq:(Ljava/lang/Object;)Lscala/collection/mutable/SetLike;
   76:	pop
   77:	goto	161
   80:	new	#25; //class scala/MatchError
   83:	dup
   84:	aload_1
   85:	invokevirtual	#31; //Method java/lang/Object.toString:()Ljava/lang/String;
   88:	invokespecial	#35; //Method scala/MatchError."<init>":(Ljava/lang/String;)V
   91:	athrow
   92:	aload_1
   93:	instanceof	#43; //class scala/collection/script/Reset
   96:	ifeq	124
   99:	iconst_1
   100:	ifeq	112
   103:	aload_0
   104:	invokeinterface	#47,  1; //InterfaceMethod scala/collection/mutable/SetLike.clear:()V
   109:	goto	161
   112:	new	#25; //class scala/MatchError
   115:	dup
   116:	aload_1
   117:	invokevirtual	#31; //Method java/lang/Object.toString:()Ljava/lang/String;
   120:	invokespecial	#35; //Method scala/MatchError."<init>":(Ljava/lang/String;)V
   123:	athrow
   124:	aload_1
   125:	instanceof	#49; //class scala/collection/script/Script
   128:	ifeq	174
   131:	aload_1
   132:	checkcast	#49; //class scala/collection/script/Script
   135:	astore	6
   137:	iconst_1
   138:	ifeq	162
   141:	aload	6
   143:	invokeinterface	#55,  1; //InterfaceMethod scala/collection/IndexedSeqLike.iterator:()Lscala/collection/Iterator;
   148:	new	#57; //class scala/collection/mutable/SetLike$$anonfun$$less$less$1
   151:	dup
   152:	aload_0
   153:	invokespecial	#59; //Method scala/collection/mutable/SetLike$$anonfun$$less$less$1."<init>":(Lscala/collection/mutable/SetLike;)V
   156:	invokeinterface	#65,  2; //InterfaceMethod scala/collection/Iterator.foreach:(Lscala/Function1;)V
   161:	return
   162:	new	#25; //class scala/MatchError
   165:	dup
   166:	aload_1
   167:	invokevirtual	#31; //Method java/lang/Object.toString:()Ljava/lang/String;
   170:	invokespecial	#35; //Method scala/MatchError."<init>":(Ljava/lang/String;)V
   173:	athrow
   174:	iconst_1
   175:	ifeq	210
   178:	new	#67; //class java/lang/UnsupportedOperationException
   181:	dup
   182:	new	#69; //class scala/collection/mutable/StringBuilder
   185:	dup
   186:	invokespecial	#71; //Method scala/collection/mutable/StringBuilder."<init>":()V
   189:	ldc	#73; //String message 
   191:	invokevirtual	#77; //Method scala/collection/mutable/StringBuilder.append:(Ljava/lang/Object;)Lscala/collection/mutable/StringBuilder;
   194:	aload_1
   195:	invokevirtual	#77; //Method scala/collection/mutable/StringBuilder.append:(Ljava/lang/Object;)Lscala/collection/mutable/StringBuilder;
   198:	ldc	#79; //String  not understood
   200:	invokevirtual	#77; //Method scala/collection/mutable/StringBuilder.append:(Ljava/lang/Object;)Lscala/collection/mutable/StringBuilder;
   203:	invokevirtual	#80; //Method scala/collection/mutable/StringBuilder.toString:()Ljava/lang/String;
   206:	invokespecial	#81; //Method java/lang/UnsupportedOperationException."<init>":(Ljava/lang/String;)V
   209:	athrow
   210:	new	#25; //class scala/MatchError
   213:	dup
   214:	aload_1
   215:	invokevirtual	#31; //Method java/lang/Object.toString:()Ljava/lang/String;
   218:	invokespecial	#35; //Method scala/MatchError."<init>":(Ljava/lang/String;)V
   221:	athrow
  LineNumberTable: 
   line 229: 0
   line 21: 17
   line 230: 21
   line 229: 32
   line 21: 64
   line 231: 68
   line 229: 80
   line 21: 99
   line 232: 103
   line 229: 112
   line 21: 137
   line 233: 141
   line 229: 161
   line 21: 174
   line 234: 178
   line 229: 210

  LocalVariableTable: 
   Start  Length  Slot  Name   Signature
   0      222      0    $this       Lscala/collection/mutable/SetLike;
   0      222      1    cmd       Lscala/collection/script/Message;
   12      32      2    temp2       Lscala/collection/script/Include;
   17      27      3    temp4       Ljava/lang/Object;
   57      35      4    temp5       Lscala/collection/script/Remove;
   64      28      5    temp7       Ljava/lang/Object;
   137      24      6    temp9       Lscala/collection/script/Script;
   162      12      6    temp9       Lscala/collection/script/Script;


public static scala.collection.mutable.SetLike $minus$minus(scala.collection.mutable.SetLike, scala.collection.Iterator);
  Code:
   Stack=4, Locals=2, Args_size=2
   0:	aload_1
   1:	new	#96; //class scala/collection/mutable/SetLike$$anonfun$$minus$minus$2
   4:	dup
   5:	aload_0
   6:	invokespecial	#97; //Method scala/collection/mutable/SetLike$$anonfun$$minus$minus$2."<init>":(Lscala/collection/mutable/SetLike;)V
   9:	invokeinterface	#65,  2; //InterfaceMethod scala/collection/Iterator.foreach:(Lscala/Function1;)V
   14:	aload_0
   15:	invokeinterface	#102,  1; //InterfaceMethod scala/collection/TraversableLike.repr:()Ljava/lang/Object;
   20:	checkcast	#19; //class scala/collection/mutable/SetLike
   23:	areturn
  LineNumberTable: 
   line 219: 0
   line 220: 14

  LocalVariableTable: 
   Start  Length  Slot  Name   Signature
   0      24      0    $this       Lscala/collection/mutable/SetLike;
   0      24      1    iter       Lscala/collection/Iterator;

  Deprecated: true

public static scala.collection.mutable.SetLike $minus$minus(scala.collection.mutable.SetLike, scala.collection.Traversable);
  Code:
   Stack=4, Locals=2, Args_size=2
   0:	aload_1
   1:	new	#108; //class scala/collection/mutable/SetLike$$anonfun$$minus$minus$1
   4:	dup
   5:	aload_0
   6:	invokespecial	#109; //Method scala/collection/mutable/SetLike$$anonfun$$minus$minus$1."<init>":(Lscala/collection/mutable/SetLike;)V
   9:	invokeinterface	#112,  2; //InterfaceMethod scala/collection/generic/GenericTraversableTemplate.foreach:(Lscala/Function1;)V
   14:	aload_0
   15:	invokeinterface	#102,  1; //InterfaceMethod scala/collection/TraversableLike.repr:()Ljava/lang/Object;
   20:	checkcast	#19; //class scala/collection/mutable/SetLike
   23:	areturn
  LineNumberTable: 
   line 207: 0
   line 208: 14

  LocalVariableTable: 
   Start  Length  Slot  Name   Signature
   0      24      0    $this       Lscala/collection/mutable/SetLike;
   0      24      1    iter       Lscala/collection/Traversable;

  Deprecated: true

public static scala.collection.mutable.SetLike $minus(scala.collection.mutable.SetLike, java.lang.Object, java.lang.Object, scala.collection.Seq);
  Code:
   Stack=2, Locals=4, Args_size=4
   0:	aload_0
   1:	aload_1
   2:	invokeinterface	#41,  2; //InterfaceMethod scala/collection/mutable/SetLike.$minus$eq:(Ljava/lang/Object;)Lscala/collection/mutable/SetLike;
   7:	aload_2
   8:	invokeinterface	#41,  2; //InterfaceMethod scala/collection/mutable/SetLike.$minus$eq:(Ljava/lang/Object;)Lscala/collection/mutable/SetLike;
   13:	aload_3
   14:	invokeinterface	#121,  2; //InterfaceMethod scala/collection/generic/Shrinkable.$minus$minus$eq:(Lscala/collection/Traversable;)Lscala/collection/generic/Shrinkable;
   19:	pop
   20:	aload_0
   21:	invokeinterface	#102,  1; //InterfaceMethod scala/collection/TraversableLike.repr:()Ljava/lang/Object;
   26:	checkcast	#19; //class scala/collection/mutable/SetLike
   29:	areturn
  LineNumberTable: 
   line 195: 0
   line 196: 20

  LocalVariableTable: 
   Start  Length  Slot  Name   Signature
   0      30      0    $this       Lscala/collection/mutable/SetLike;
   0      30      1    elem1       Ljava/lang/Object;
   0      30      2    elem2       Ljava/lang/Object;
   0      30      3    elems       Lscala/collection/Seq;

  Deprecated: true

public static scala.collection.mutable.SetLike $minus(scala.collection.mutable.SetLike, java.lang.Object);
  Code:
   Stack=2, Locals=2, Args_size=2
   0:	aload_0
   1:	aload_1
   2:	invokeinterface	#41,  2; //InterfaceMethod scala/collection/mutable/SetLike.$minus$eq:(Ljava/lang/Object;)Lscala/collection/mutable/SetLike;
   7:	pop
   8:	aload_0
   9:	invokeinterface	#102,  1; //InterfaceMethod scala/collection/TraversableLike.repr:()Ljava/lang/Object;
   14:	checkcast	#19; //class scala/collection/mutable/SetLike
   17:	areturn
  LineNumberTable: 
   line 183: 0

  LocalVariableTable: 
   Start  Length  Slot  Name   Signature
   0      18      0    $this       Lscala/collection/mutable/SetLike;
   0      18      1    elem       Ljava/lang/Object;

  Deprecated: true

public static scala.collection.mutable.SetLike $plus$plus(scala.collection.mutable.SetLike, scala.collection.Iterator);
  Code:
   Stack=4, Locals=2, Args_size=2
   0:	aload_1
   1:	new	#129; //class scala/collection/mutable/SetLike$$anonfun$$plus$plus$2
   4:	dup
   5:	aload_0
   6:	invokespecial	#130; //Method scala/collection/mutable/SetLike$$anonfun$$plus$plus$2."<init>":(Lscala/collection/mutable/SetLike;)V
   9:	invokeinterface	#65,  2; //InterfaceMethod scala/collection/Iterator.foreach:(Lscala/Function1;)V
   14:	aload_0
   15:	invokeinterface	#102,  1; //InterfaceMethod scala/collection/TraversableLike.repr:()Ljava/lang/Object;
   20:	checkcast	#19; //class scala/collection/mutable/SetLike
   23:	areturn
  LineNumberTable: 
   line 172: 0
   line 173: 14

  LocalVariableTable: 
   Start  Length  Slot  Name   Signature
   0      24      0    $this       Lscala/collection/mutable/SetLike;
   0      24      1    iter       Lscala/collection/Iterator;

  Deprecated: true

public static scala.collection.mutable.SetLike $plus$plus(scala.collection.mutable.SetLike, scala.collection.Traversable);
  Code:
   Stack=4, Locals=2, Args_size=2
   0:	aload_1
   1:	new	#132; //class scala/collection/mutable/SetLike$$anonfun$$plus$plus$1
   4:	dup
   5:	aload_0
   6:	invokespecial	#133; //Method scala/collection/mutable/SetLike$$anonfun$$plus$plus$1."<init>":(Lscala/collection/mutable/SetLike;)V
   9:	invokeinterface	#112,  2; //InterfaceMethod scala/collection/generic/GenericTraversableTemplate.foreach:(Lscala/Function1;)V
   14:	aload_0
   15:	invokeinterface	#102,  1; //InterfaceMethod scala/collection/TraversableLike.repr:()Ljava/lang/Object;
   20:	checkcast	#19; //class scala/collection/mutable/SetLike
   23:	areturn
  LineNumberTable: 
   line 160: 0
   line 161: 14

  LocalVariableTable: 
   Start  Length  Slot  Name   Signature
   0      24      0    $this       Lscala/collection/mutable/SetLike;
   0      24      1    iter       Lscala/collection/Traversable;

  Deprecated: true

public static scala.collection.mutable.SetLike $plus(scala.collection.mutable.SetLike, java.lang.Object, java.lang.Object, scala.collection.Seq);
  Code:
   Stack=2, Locals=4, Args_size=4
   0:	aload_0
   1:	aload_1
   2:	invokeinterface	#23,  2; //InterfaceMethod scala/collection/mutable/SetLike.$plus$eq:(Ljava/lang/Object;)Lscala/collection/mutable/SetLike;
   7:	aload_2
   8:	invokeinterface	#23,  2; //InterfaceMethod scala/collection/mutable/SetLike.$plus$eq:(Ljava/lang/Object;)Lscala/collection/mutable/SetLike;
   13:	aload_3
   14:	invokeinterface	#140,  2; //InterfaceMethod scala/collection/generic/Growable.$plus$plus$eq:(Lscala/collection/Traversable;)Lscala/collection/generic/Growable;
   19:	pop
   20:	aload_0
   21:	invokeinterface	#102,  1; //InterfaceMethod scala/collection/TraversableLike.repr:()Ljava/lang/Object;
   26:	checkcast	#19; //class scala/collection/mutable/SetLike
   29:	areturn
  LineNumberTable: 
   line 148: 0
   line 149: 20

  LocalVariableTable: 
   Start  Length  Slot  Name   Signature
   0      30      0    $this       Lscala/collection/mutable/SetLike;
   0      30      1    elem1       Ljava/lang/Object;
   0      30      2    elem2       Ljava/lang/Object;
   0      30      3    elems       Lscala/collection/Seq;

  Deprecated: true

public static scala.collection.mutable.SetLike $plus(scala.collection.mutable.SetLike, java.lang.Object);
  Code:
   Stack=2, Locals=2, Args_size=2
   0:	aload_0
   1:	aload_1
   2:	invokeinterface	#23,  2; //InterfaceMethod scala/collection/mutable/SetLike.$plus$eq:(Ljava/lang/Object;)Lscala/collection/mutable/SetLike;
   7:	pop
   8:	aload_0
   9:	invokeinterface	#102,  1; //InterfaceMethod scala/collection/TraversableLike.repr:()Ljava/lang/Object;
   14:	checkcast	#19; //class scala/collection/mutable/SetLike
   17:	areturn
  LineNumberTable: 
   line 136: 0

  LocalVariableTable: 
   Start  Length  Slot  Name   Signature
   0      18      0    $this       Lscala/collection/mutable/SetLike;
   0      18      1    elem       Ljava/lang/Object;

  Deprecated: true

public static scala.collection.mutable.SetLike result(scala.collection.mutable.SetLike);
  Code:
   Stack=1, Locals=1, Args_size=1
   0:	aload_0
   1:	invokeinterface	#102,  1; //InterfaceMethod scala/collection/TraversableLike.repr:()Ljava/lang/Object;
   6:	checkcast	#19; //class scala/collection/mutable/SetLike
   9:	areturn
  LineNumberTable: 
   line 127: 0

  LocalVariableTable: 
   Start  Length  Slot  Name   Signature
   0      10      0    $this       Lscala/collection/mutable/SetLike;


public static scala.collection.mutable.Set clone(scala.collection.mutable.SetLike);
  Code:
   Stack=2, Locals=1, Args_size=1
   0:	aload_0
   1:	invokeinterface	#150,  1; //InterfaceMethod scala/collection/SetLike.empty:()Lscala/collection/SetLike;
   6:	checkcast	#136; //class scala/collection/generic/Growable
   9:	aload_0
   10:	invokeinterface	#102,  1; //InterfaceMethod scala/collection/TraversableLike.repr:()Ljava/lang/Object;
   15:	checkcast	#152; //class scala/collection/Traversable
   18:	invokeinterface	#140,  2; //InterfaceMethod scala/collection/generic/Growable.$plus$plus$eq:(Lscala/collection/Traversable;)Lscala/collection/generic/Growable;
   23:	checkcast	#154; //class scala/collection/mutable/Set
   26:	areturn
  LineNumberTable: 
   line 122: 0

  LocalVariableTable: 
   Start  Length  Slot  Name   Signature
   0      27      0    $this       Lscala/collection/mutable/SetLike;


public static void clear(scala.collection.mutable.SetLike);
  Code:
   Stack=4, Locals=1, Args_size=1
   0:	aload_0
   1:	new	#156; //class scala/collection/mutable/SetLike$$anonfun$clear$1
   4:	dup
   5:	aload_0
   6:	invokespecial	#157; //Method scala/collection/mutable/SetLike$$anonfun$clear$1."<init>":(Lscala/collection/mutable/SetLike;)V
   9:	invokeinterface	#160,  2; //InterfaceMethod scala/collection/IterableLike.foreach:(Lscala/Function1;)V
   14:	return
  LineNumberTable: 
   line 120: 0

  LocalVariableTable: 
   Start  Length  Slot  Name   Signature
   0      15      0    $this       Lscala/collection/mutable/SetLike;


public static void retain(scala.collection.mutable.SetLike, scala.Function1);
  Code:
   Stack=5, Locals=2, Args_size=2
   0:	aload_0
   1:	invokeinterface	#166,  1; //InterfaceMethod scala/collection/TraversableLike.toList:()Lscala/collection/immutable/List;
   6:	new	#168; //class scala/collection/mutable/SetLike$$anonfun$retain$1
   9:	dup
   10:	aload_0
   11:	aload_1
   12:	invokespecial	#170; //Method scala/collection/mutable/SetLike$$anonfun$retain$1."<init>":(Lscala/collection/mutable/SetLike;Lscala/Function1;)V
   15:	invokeinterface	#173,  2; //InterfaceMethod scala/collection/LinearSeqLike.foreach:(Lscala/Function1;)V
   20:	return
  LineNumberTable: 
   line 115: 0

  LocalVariableTable: 
   Start  Length  Slot  Name   Signature
   0      21      0    $this       Lscala/collection/mutable/SetLike;
   0      21      1    p$1       Lscala/Function1;


public static void update(scala.collection.mutable.SetLike, java.lang.Object, boolean);
  Code:
   Stack=2, Locals=3, Args_size=3
   0:	iload_2
   1:	ifeq	15
   4:	aload_0
   5:	aload_1
   6:	invokeinterface	#23,  2; //InterfaceMethod scala/collection/mutable/SetLike.$plus$eq:(Ljava/lang/Object;)Lscala/collection/mutable/SetLike;
   11:	pop
   12:	goto	23
   15:	aload_0
   16:	aload_1
   17:	invokeinterface	#41,  2; //InterfaceMethod scala/collection/mutable/SetLike.$minus$eq:(Ljava/lang/Object;)Lscala/collection/mutable/SetLike;
   22:	pop
   23:	return
  LineNumberTable: 
   line 102: 0

  LocalVariableTable: 
   Start  Length  Slot  Name   Signature
   0      24      0    $this       Lscala/collection/mutable/SetLike;
   0      24      1    elem       Ljava/lang/Object;
   0      24      2    included       Z


public static boolean remove(scala.collection.mutable.SetLike, java.lang.Object);
  Code:
   Stack=2, Locals=3, Args_size=2
   0:	aload_0
   1:	aload_1
   2:	invokeinterface	#185,  2; //InterfaceMethod scala/collection/SetLike.contains:(Ljava/lang/Object;)Z
   7:	istore_2
   8:	aload_0
   9:	aload_1
   10:	invokeinterface	#41,  2; //InterfaceMethod scala/collection/mutable/SetLike.$minus$eq:(Ljava/lang/Object;)Lscala/collection/mutable/SetLike;
   15:	pop
   16:	iload_2
   17:	ireturn
  LineNumberTable: 
   line 83: 0
   line 84: 8
   line 85: 16

  LocalVariableTable: 
   Start  Length  Slot  Name   Signature
   0      18      0    $this       Lscala/collection/mutable/SetLike;
   0      18      1    elem       Ljava/lang/Object;
   8      9      2    r       Z


public static boolean add(scala.collection.mutable.SetLike, java.lang.Object);
  Code:
   Stack=2, Locals=3, Args_size=2
   0:	aload_0
   1:	aload_1
   2:	invokeinterface	#185,  2; //InterfaceMethod scala/collection/SetLike.contains:(Ljava/lang/Object;)Z
   7:	istore_2
   8:	aload_0
   9:	aload_1
   10:	invokeinterface	#23,  2; //InterfaceMethod scala/collection/mutable/SetLike.$plus$eq:(Ljava/lang/Object;)Lscala/collection/mutable/SetLike;
   15:	pop
   16:	iload_2
   17:	ireturn
  LineNumberTable: 
   line 72: 0
   line 73: 8
   line 74: 16

  LocalVariableTable: 
   Start  Length  Slot  Name   Signature
   0      18      0    $this       Lscala/collection/mutable/SetLike;
   0      18      1    elem       Ljava/lang/Object;
   8      9      2    r       Z


public static scala.collection.mutable.Builder newBuilder(scala.collection.mutable.SetLike);
  Code:
   Stack=1, Locals=1, Args_size=1
   0:	aload_0
   1:	invokeinterface	#150,  1; //InterfaceMethod scala/collection/SetLike.empty:()Lscala/collection/SetLike;
   6:	checkcast	#191; //class scala/collection/mutable/Builder
   9:	areturn
  LineNumberTable: 
   line 64: 0

  LocalVariableTable: 
   Start  Length  Slot  Name   Signature
   0      10      0    $this       Lscala/collection/mutable/SetLike;


}

