Compiled from "SetProxy.scala"
public abstract class scala.collection.mutable.SetProxy$class extends java.lang.Object
  SourceFile: "SetProxy.scala"
  Scala: length = 0x
   
  InnerClass: 
   public final #43= #33 of #42; //$anon$1=class scala/collection/mutable/SetProxy$$anon$1 of class scala/collection/mutable/SetProxy
  minor version: 0
  major version: 49
  Constant pool:
const #1 = Asciz	SourceFile;
const #2 = Asciz	SetProxy.scala;
const #3 = Asciz	$init$;
const #4 = Asciz	(Lscala/collection/mutable/SetProxy;)V;
const #5 = Asciz	Code;
const #6 = Asciz	LineNumberTable;
const #7 = Asciz	$this;
const #8 = Asciz	Lscala/collection/mutable/SetProxy;;
const #9 = Asciz	LocalVariableTable;
const #10 = Asciz	$minus$eq;
const #11 = Asciz	(Lscala/collection/mutable/SetProxy;Ljava/lang/Object;)Lscala/collection/mutable/SetProxy;;
const #12 = Asciz	scala/collection/TraversableProxyLike;
const #13 = class	#12;	//  scala/collection/TraversableProxyLike
const #14 = Asciz	self;
const #15 = Asciz	()Lscala/collection/TraversableLike;;
const #16 = NameAndType	#14:#15;//  self:()Lscala/collection/TraversableLike;
const #17 = InterfaceMethod	#13.#16;	//  scala/collection/TraversableProxyLike.self:()Lscala/collection/TraversableLike;
const #18 = Asciz	scala/collection/mutable/SetLike;
const #19 = class	#18;	//  scala/collection/mutable/SetLike
const #20 = Asciz	(Ljava/lang/Object;)Lscala/collection/mutable/SetLike;;
const #21 = NameAndType	#10:#20;//  $minus$eq:(Ljava/lang/Object;)Lscala/collection/mutable/SetLike;
const #22 = InterfaceMethod	#19.#21;	//  scala/collection/mutable/SetLike.$minus$eq:(Ljava/lang/Object;)Lscala/collection/mutable/SetLike;
const #23 = Asciz	elem;
const #24 = Asciz	Ljava/lang/Object;;
const #25 = Asciz	$plus$eq;
const #26 = NameAndType	#25:#20;//  $plus$eq:(Ljava/lang/Object;)Lscala/collection/mutable/SetLike;
const #27 = InterfaceMethod	#19.#26;	//  scala/collection/mutable/SetLike.$plus$eq:(Ljava/lang/Object;)Lscala/collection/mutable/SetLike;
const #28 = Asciz	$minus;
const #29 = Asciz	$plus;
const #30 = Asciz	empty;
const #31 = Asciz	(Lscala/collection/mutable/SetProxy;)Ljava/lang/Object;;
const #32 = Asciz	scala/collection/mutable/SetProxy$$anon$1;
const #33 = class	#32;	//  scala/collection/mutable/SetProxy$$anon$1
const #34 = Asciz	<init>;
const #35 = NameAndType	#34:#4;//  "<init>":(Lscala/collection/mutable/SetProxy;)V
const #36 = Method	#33.#35;	//  scala/collection/mutable/SetProxy$$anon$1."<init>":(Lscala/collection/mutable/SetProxy;)V
const #37 = Asciz	repr;
const #38 = Asciz	(Lscala/collection/mutable/SetProxy;)Lscala/collection/mutable/SetProxy;;
const #39 = Asciz	Scala;
const #40 = Asciz	InnerClasses;
const #41 = Asciz	scala/collection/mutable/SetProxy;
const #42 = class	#41;	//  scala/collection/mutable/SetProxy
const #43 = Asciz	$anon$1;
const #44 = Asciz	scala/collection/mutable/SetProxy$class;
const #45 = class	#44;	//  scala/collection/mutable/SetProxy$class
const #46 = Asciz	java/lang/Object;
const #47 = class	#46;	//  java/lang/Object

{
public static void $init$(scala.collection.mutable.SetProxy);
  Code:
   Stack=0, Locals=1, Args_size=1
   0:	return
  LineNumberTable: 
   line 23: 0

  LocalVariableTable: 
   Start  Length  Slot  Name   Signature
   0      1      0    $this       Lscala/collection/mutable/SetProxy;


public static scala.collection.mutable.SetProxy $minus$eq(scala.collection.mutable.SetProxy, java.lang.Object);
  Code:
   Stack=2, Locals=2, Args_size=2
   0:	aload_0
   1:	invokeinterface	#17,  1; //InterfaceMethod scala/collection/TraversableProxyLike.self:()Lscala/collection/TraversableLike;
   6:	checkcast	#19; //class scala/collection/mutable/SetLike
   9:	aload_1
   10:	invokeinterface	#22,  2; //InterfaceMethod scala/collection/mutable/SetLike.$minus$eq:(Ljava/lang/Object;)Lscala/collection/mutable/SetLike;
   15:	pop
   16:	aload_0
   17:	areturn
  LineNumberTable: 
   line 31: 0

  LocalVariableTable: 
   Start  Length  Slot  Name   Signature
   0      18      0    $this       Lscala/collection/mutable/SetProxy;
   0      18      1    elem       Ljava/lang/Object;


public static scala.collection.mutable.SetProxy $plus$eq(scala.collection.mutable.SetProxy, java.lang.Object);
  Code:
   Stack=2, Locals=2, Args_size=2
   0:	aload_0
   1:	invokeinterface	#17,  1; //InterfaceMethod scala/collection/TraversableProxyLike.self:()Lscala/collection/TraversableLike;
   6:	checkcast	#19; //class scala/collection/mutable/SetLike
   9:	aload_1
   10:	invokeinterface	#27,  2; //InterfaceMethod scala/collection/mutable/SetLike.$plus$eq:(Ljava/lang/Object;)Lscala/collection/mutable/SetLike;
   15:	pop
   16:	aload_0
   17:	areturn
  LineNumberTable: 
   line 30: 0

  LocalVariableTable: 
   Start  Length  Slot  Name   Signature
   0      18      0    $this       Lscala/collection/mutable/SetProxy;
   0      18      1    elem       Ljava/lang/Object;


public static scala.collection.mutable.SetProxy $minus(scala.collection.mutable.SetProxy, java.lang.Object);
  Code:
   Stack=2, Locals=2, Args_size=2
   0:	aload_0
   1:	invokeinterface	#17,  1; //InterfaceMethod scala/collection/TraversableProxyLike.self:()Lscala/collection/TraversableLike;
   6:	checkcast	#19; //class scala/collection/mutable/SetLike
   9:	aload_1
   10:	invokeinterface	#22,  2; //InterfaceMethod scala/collection/mutable/SetLike.$minus$eq:(Ljava/lang/Object;)Lscala/collection/mutable/SetLike;
   15:	pop
   16:	aload_0
   17:	areturn
  LineNumberTable: 
   line 28: 0

  LocalVariableTable: 
   Start  Length  Slot  Name   Signature
   0      18      0    $this       Lscala/collection/mutable/SetProxy;
   0      18      1    elem       Ljava/lang/Object;


public static scala.collection.mutable.SetProxy $plus(scala.collection.mutable.SetProxy, java.lang.Object);
  Code:
   Stack=2, Locals=2, Args_size=2
   0:	aload_0
   1:	invokeinterface	#17,  1; //InterfaceMethod scala/collection/TraversableProxyLike.self:()Lscala/collection/TraversableLike;
   6:	checkcast	#19; //class scala/collection/mutable/SetLike
   9:	aload_1
   10:	invokeinterface	#27,  2; //InterfaceMethod scala/collection/mutable/SetLike.$plus$eq:(Ljava/lang/Object;)Lscala/collection/mutable/SetLike;
   15:	pop
   16:	aload_0
   17:	areturn
  LineNumberTable: 
   line 27: 0

  LocalVariableTable: 
   Start  Length  Slot  Name   Signature
   0      18      0    $this       Lscala/collection/mutable/SetProxy;
   0      18      1    elem       Ljava/lang/Object;


public static java.lang.Object empty(scala.collection.mutable.SetProxy);
  Code:
   Stack=3, Locals=1, Args_size=1
   0:	new	#33; //class scala/collection/mutable/SetProxy$$anon$1
   3:	dup
   4:	aload_0
   5:	invokespecial	#36; //Method scala/collection/mutable/SetProxy$$anon$1."<init>":(Lscala/collection/mutable/SetProxy;)V
   8:	areturn
  LineNumberTable: 
   line 26: 0

  LocalVariableTable: 
   Start  Length  Slot  Name   Signature
   0      9      0    $this       Lscala/collection/mutable/SetProxy;


public static scala.collection.mutable.SetProxy repr(scala.collection.mutable.SetProxy);
  Code:
   Stack=1, Locals=1, Args_size=1
   0:	aload_0
   1:	areturn
  LineNumberTable: 
   line 25: 0

  LocalVariableTable: 
   Start  Length  Slot  Name   Signature
   0      2      0    $this       Lscala/collection/mutable/SetProxy;


}

