Compiled from "SetProxy.scala"
public final class scala.collection.mutable.SetProxy$$anon$1 extends java.lang.Object implements scala.collection.mutable.SetProxy
  SourceFile: "SetProxy.scala"
  Signature: length = 0x2
   03 68 
  Scala: length = 0x
   
  InnerClass: 
   public final $anon$1=class scala/collection/mutable/SetProxy$$anon$1 of class scala/collection/mutable/SetProxy
   public abstract $less$colon$less=class scala/Predef$$less$colon$less of class scala/Predef
   public WithFilter=class scala/collection/TraversableLike$WithFilter of class scala/collection/TraversableLike
  minor version: 0
  major version: 49
  Constant pool:
Asciz	SourceFile;
Asciz	SetProxy.scala;
Asciz	self;
Asciz	Lscala/collection/mutable/Set;;
Asciz	Lscala/collection/mutable/Set<TA;>;;
Asciz	Signature;
Asciz	repr;
Asciz	()Lscala/collection/mutable/SetProxy;;
Asciz	Code;
Asciz	LineNumberTable;
Asciz	scala/collection/mutable/SetProxy$class;
class	scala/collection/mutable/SetProxy$class
Asciz	(Lscala/collection/mutable/SetProxy;)Lscala/collection/mutable/SetProxy;;
NameAndType	repr:(Lscala/collection/mutable/SetProxy;)Lscala/collection/mutable/SetProxy;
Method	scala/collection/mutable/SetProxy$class.repr:(Lscala/collection/mutable/SetProxy;)Lscala/collection/mutable/SetProxy;
Asciz	empty;
NameAndType	empty:(Lscala/collection/mutable/SetProxy;)Lscala/collection/mutable/SetProxy;
Method	scala/collection/mutable/SetProxy$class.empty:(Lscala/collection/mutable/SetProxy;)Lscala/collection/mutable/SetProxy;
Asciz	$plus;
Asciz	(Ljava/lang/Object;)Lscala/collection/mutable/SetProxy;;
Asciz	(Lscala/collection/mutable/SetProxy;Ljava/lang/Object;)Lscala/collection/mutable/SetProxy;;
NameAndType	$plus:(Lscala/collection/mutable/SetProxy;Ljava/lang/Object;)Lscala/collection/mutable/SetProxy;
Method	scala/collection/mutable/SetProxy$class.$plus:(Lscala/collection/mutable/SetProxy;Ljava/lang/Object;)Lscala/collection/mutable/SetProxy;
Asciz	this;
Asciz	Lscala/collection/mutable/SetProxy$$anon$1;;
Asciz	elem;
Asciz	Ljava/lang/Object;;
Asciz	LocalVariableTable;
Asciz	$minus;
NameAndType	$minus:(Lscala/collection/mutable/SetProxy;Ljava/lang/Object;)Lscala/collection/mutable/SetProxy;
Method	scala/collection/mutable/SetProxy$class.$minus:(Lscala/collection/mutable/SetProxy;Ljava/lang/Object;)Lscala/collection/mutable/SetProxy;
Asciz	$plus$eq;
NameAndType	$plus$eq:(Lscala/collection/mutable/SetProxy;Ljava/lang/Object;)Lscala/collection/mutable/SetProxy;
Method	scala/collection/mutable/SetProxy$class.$plus$eq:(Lscala/collection/mutable/SetProxy;Ljava/lang/Object;)Lscala/collection/mutable/SetProxy;
Asciz	$minus$eq;
NameAndType	$minus$eq:(Lscala/collection/mutable/SetProxy;Ljava/lang/Object;)Lscala/collection/mutable/SetProxy;
Method	scala/collection/mutable/SetProxy$class.$minus$eq:(Lscala/collection/mutable/SetProxy;Ljava/lang/Object;)Lscala/collection/mutable/SetProxy;
Asciz	contains;
Asciz	(Ljava/lang/Object;)Z;
Asciz	scala/collection/SetProxyLike$class;
class	scala/collection/SetProxyLike$class
Asciz	(Lscala/collection/SetProxyLike;Ljava/lang/Object;)Z;
NameAndType	contains:(Lscala/collection/SetProxyLike;Ljava/lang/Object;)Z
Method	scala/collection/SetProxyLike$class.contains:(Lscala/collection/SetProxyLike;Ljava/lang/Object;)Z
Asciz	isEmpty;
Asciz	()Z;
Asciz	(Lscala/collection/SetProxyLike;)Z;
NameAndType	isEmpty:(Lscala/collection/SetProxyLike;)Z
Method	scala/collection/SetProxyLike$class.isEmpty:(Lscala/collection/SetProxyLike;)Z
Asciz	apply;
NameAndType	apply:(Lscala/collection/SetProxyLike;Ljava/lang/Object;)Z
Method	scala/collection/SetProxyLike$class.apply:(Lscala/collection/SetProxyLike;Ljava/lang/Object;)Z
Asciz	intersect;
Asciz	(Lscala/collection/Set;)Lscala/collection/Set;;
Asciz	(Lscala/collection/SetProxyLike;Lscala/collection/Set;)Lscala/collection/Set;;
NameAndType	intersect:(Lscala/collection/SetProxyLike;Lscala/collection/Set;)Lscala/collection/Set;
Method	scala/collection/SetProxyLike$class.intersect:(Lscala/collection/SetProxyLike;Lscala/collection/Set;)Lscala/collection/Set;
Asciz	that;
Asciz	Lscala/collection/Set;;
Asciz	$amp;
NameAndType	$amp:(Lscala/collection/SetProxyLike;Lscala/collection/Set;)Lscala/collection/Set;
Method	scala/collection/SetProxyLike$class.$amp:(Lscala/collection/SetProxyLike;Lscala/collection/Set;)Lscala/collection/Set;
Asciz	union;
NameAndType	union:(Lscala/collection/SetProxyLike;Lscala/collection/Set;)Lscala/collection/Set;
Method	scala/collection/SetProxyLike$class.union:(Lscala/collection/SetProxyLike;Lscala/collection/Set;)Lscala/collection/Set;
Asciz	$bar;
NameAndType	$bar:(Lscala/collection/SetProxyLike;Lscala/collection/Set;)Lscala/collection/Set;
Method	scala/collection/SetProxyLike$class.$bar:(Lscala/collection/SetProxyLike;Lscala/collection/Set;)Lscala/collection/Set;
Asciz	diff;
NameAndType	diff:(Lscala/collection/SetProxyLike;Lscala/collection/Set;)Lscala/collection/Set;
Method	scala/collection/SetProxyLike$class.diff:(Lscala/collection/SetProxyLike;Lscala/collection/Set;)Lscala/collection/Set;
Asciz	$amp$tilde;
NameAndType	$amp$tilde:(Lscala/collection/SetProxyLike;Lscala/collection/Set;)Lscala/collection/Set;
Method	scala/collection/SetProxyLike$class.$amp$tilde:(Lscala/collection/SetProxyLike;Lscala/collection/Set;)Lscala/collection/Set;
Asciz	subsetOf;
Asciz	(Lscala/collection/Set;)Z;
Asciz	(Lscala/collection/SetProxyLike;Lscala/collection/Set;)Z;
NameAndType	subsetOf:(Lscala/collection/SetProxyLike;Lscala/collection/Set;)Z
Method	scala/collection/SetProxyLike$class.subsetOf:(Lscala/collection/SetProxyLike;Lscala/collection/Set;)Z
Asciz	iterator;
Asciz	()Lscala/collection/Iterator;;
Asciz	scala/collection/IterableProxyLike$class;
class	scala/collection/IterableProxyLike$class
Asciz	(Lscala/collection/IterableProxyLike;)Lscala/collection/Iterator;;
NameAndType	iterator:(Lscala/collection/IterableProxyLike;)Lscala/collection/Iterator;
Method	scala/collection/IterableProxyLike$class.iterator:(Lscala/collection/IterableProxyLike;)Lscala/collection/Iterator;
Asciz	grouped;
Asciz	(I)Lscala/collection/Iterator;;
Asciz	(Lscala/collection/IterableProxyLike;I)Lscala/collection/Iterator;;
NameAndType	grouped:(Lscala/collection/IterableProxyLike;I)Lscala/collection/Iterator;
Method	scala/collection/IterableProxyLike$class.grouped:(Lscala/collection/IterableProxyLike;I)Lscala/collection/Iterator;
Asciz	size;
Asciz	I;
Asciz	sliding;
NameAndType	sliding:(Lscala/collection/IterableProxyLike;I)Lscala/collection/Iterator;
Method	scala/collection/IterableProxyLike$class.sliding:(Lscala/collection/IterableProxyLike;I)Lscala/collection/Iterator;
Asciz	(II)Lscala/collection/Iterator;;
Asciz	(Lscala/collection/IterableProxyLike;II)Lscala/collection/Iterator;;
NameAndType	sliding:(Lscala/collection/IterableProxyLike;II)Lscala/collection/Iterator;
Method	scala/collection/IterableProxyLike$class.sliding:(Lscala/collection/IterableProxyLike;II)Lscala/collection/Iterator;
Asciz	step;
Asciz	takeRight;
Asciz	(I)Lscala/collection/Iterable;;
Asciz	(Lscala/collection/IterableProxyLike;I)Lscala/collection/Iterable;;
NameAndType	takeRight:(Lscala/collection/IterableProxyLike;I)Lscala/collection/Iterable;
Method	scala/collection/IterableProxyLike$class.takeRight:(Lscala/collection/IterableProxyLike;I)Lscala/collection/Iterable;
Asciz	n;
Asciz	dropRight;
NameAndType	dropRight:(Lscala/collection/IterableProxyLike;I)Lscala/collection/Iterable;
Method	scala/collection/IterableProxyLike$class.dropRight:(Lscala/collection/IterableProxyLike;I)Lscala/collection/Iterable;
Asciz	zip;
Asciz	(Lscala/collection/Iterable;Lscala/collection/generic/CanBuildFrom;)Ljava/lang/Object;;
Asciz	(Lscala/collection/IterableProxyLike;Lscala/collection/Iterable;Lscala/collection/generic/CanBuildFrom;)Ljava/lang/Object;;
NameAndType	zip:(Lscala/collection/IterableProxyLike;Lscala/collection/Iterable;Lscala/collection/generic/CanBuildFrom;)Ljava/lang/Object;
Method	scala/collection/IterableProxyLike$class.zip:(Lscala/collection/IterableProxyLike;Lscala/collection/Iterable;Lscala/collection/generic/CanBuildFrom;)Ljava/lang/Object;
Asciz	Lscala/collection/Iterable;;
Asciz	bf;
Asciz	Lscala/collection/generic/CanBuildFrom;;
Asciz	zipAll;
Asciz	(Lscala/collection/Iterable;Ljava/lang/Object;Ljava/lang/Object;Lscala/collection/generic/CanBuildFrom;)Ljava/lang/Object;;
Asciz	(Lscala/collection/IterableProxyLike;Lscala/collection/Iterable;Ljava/lang/Object;Ljava/lang/Object;Lscala/collection/generic/CanBuildFrom;)Ljava/lang/Object;;
NameAndType	zipAll:(Lscala/collection/IterableProxyLike;Lscala/collection/Iterable;Ljava/lang/Object;Ljava/lang/Object;Lscala/collection/generic/CanBuildFrom;)Ljava/lang/Object;
Method	scala/collection/IterableProxyLike$class.zipAll:(Lscala/collection/IterableProxyLike;Lscala/collection/Iterable;Ljava/lang/Object;Ljava/lang/Object;Lscala/collection/generic/CanBuildFrom;)Ljava/lang/Object;
Asciz	thisElem;
Asciz	thatElem;
Asciz	zipWithIndex;
Asciz	(Lscala/collection/generic/CanBuildFrom;)Ljava/lang/Object;;
Asciz	(Lscala/collection/IterableProxyLike;Lscala/collection/generic/CanBuildFrom;)Ljava/lang/Object;;
NameAndType	zipWithIndex:(Lscala/collection/IterableProxyLike;Lscala/collection/generic/CanBuildFrom;)Ljava/lang/Object;
Method	scala/collection/IterableProxyLike$class.zipWithIndex:(Lscala/collection/IterableProxyLike;Lscala/collection/generic/CanBuildFrom;)Ljava/lang/Object;
Asciz	sameElements;
Asciz	(Lscala/collection/Iterable;)Z;
Asciz	(Lscala/collection/IterableProxyLike;Lscala/collection/Iterable;)Z;
NameAndType	sameElements:(Lscala/collection/IterableProxyLike;Lscala/collection/Iterable;)Z
Method	scala/collection/IterableProxyLike$class.sameElements:(Lscala/collection/IterableProxyLike;Lscala/collection/Iterable;)Z
Asciz	view;
Asciz	()Lscala/collection/IterableView;;
Asciz	(Lscala/collection/IterableProxyLike;)Lscala/collection/IterableView;;
NameAndType	view:(Lscala/collection/IterableProxyLike;)Lscala/collection/IterableView;
Method	scala/collection/IterableProxyLike$class.view:(Lscala/collection/IterableProxyLike;)Lscala/collection/IterableView;
Asciz	(II)Lscala/collection/IterableView;;
Asciz	(Lscala/collection/IterableProxyLike;II)Lscala/collection/IterableView;;
NameAndType	view:(Lscala/collection/IterableProxyLike;II)Lscala/collection/IterableView;
Method	scala/collection/IterableProxyLike$class.view:(Lscala/collection/IterableProxyLike;II)Lscala/collection/IterableView;
Asciz	from;
Asciz	until;
Asciz	foreach;
Asciz	(Lscala/Function1;)V;
Asciz	scala/collection/TraversableProxyLike$class;
class	scala/collection/TraversableProxyLike$class
Asciz	(Lscala/collection/TraversableProxyLike;Lscala/Function1;)V;
NameAndType	foreach:(Lscala/collection/TraversableProxyLike;Lscala/Function1;)V
Method	scala/collection/TraversableProxyLike$class.foreach:(Lscala/collection/TraversableProxyLike;Lscala/Function1;)V
Asciz	f;
Asciz	Lscala/Function1;;
Asciz	nonEmpty;
Asciz	(Lscala/collection/TraversableProxyLike;)Z;
NameAndType	nonEmpty:(Lscala/collection/TraversableProxyLike;)Z
Method	scala/collection/TraversableProxyLike$class.nonEmpty:(Lscala/collection/TraversableProxyLike;)Z
Asciz	()I;
Asciz	(Lscala/collection/TraversableProxyLike;)I;
NameAndType	size:(Lscala/collection/TraversableProxyLike;)I
Method	scala/collection/TraversableProxyLike$class.size:(Lscala/collection/TraversableProxyLike;)I
Asciz	hasDefiniteSize;
NameAndType	hasDefiniteSize:(Lscala/collection/TraversableProxyLike;)Z
Method	scala/collection/TraversableProxyLike$class.hasDefiniteSize:(Lscala/collection/TraversableProxyLike;)Z
Asciz	$plus$plus;
Asciz	(Lscala/collection/Traversable;Lscala/collection/generic/CanBuildFrom;)Ljava/lang/Object;;
Asciz	(Lscala/collection/TraversableProxyLike;Lscala/collection/Traversable;Lscala/collection/generic/CanBuildFrom;)Ljava/lang/Object;;
NameAndType	$plus$plus:(Lscala/collection/TraversableProxyLike;Lscala/collection/Traversable;Lscala/collection/generic/CanBuildFrom;)Ljava/lang/Object;
Method	scala/collection/TraversableProxyLike$class.$plus$plus:(Lscala/collection/TraversableProxyLike;Lscala/collection/Traversable;Lscala/collection/generic/CanBuildFrom;)Ljava/lang/Object;
Asciz	Lscala/collection/Traversable;;
Asciz	(Lscala/collection/Iterator;Lscala/collection/generic/CanBuildFrom;)Ljava/lang/Object;;
Asciz	(Lscala/collection/TraversableProxyLike;Lscala/collection/Iterator;Lscala/collection/generic/CanBuildFrom;)Ljava/lang/Object;;
NameAndType	$plus$plus:(Lscala/collection/TraversableProxyLike;Lscala/collection/Iterator;Lscala/collection/generic/CanBuildFrom;)Ljava/lang/Object;
Method	scala/collection/TraversableProxyLike$class.$plus$plus:(Lscala/collection/TraversableProxyLike;Lscala/collection/Iterator;Lscala/collection/generic/CanBuildFrom;)Ljava/lang/Object;
Asciz	Lscala/collection/Iterator;;
Asciz	map;
Asciz	(Lscala/Function1;Lscala/collection/generic/CanBuildFrom;)Ljava/lang/Object;;
Asciz	(Lscala/collection/TraversableProxyLike;Lscala/Function1;Lscala/collection/generic/CanBuildFrom;)Ljava/lang/Object;;
NameAndType	map:(Lscala/collection/TraversableProxyLike;Lscala/Function1;Lscala/collection/generic/CanBuildFrom;)Ljava/lang/Object;
Method	scala/collection/TraversableProxyLike$class.map:(Lscala/collection/TraversableProxyLike;Lscala/Function1;Lscala/collection/generic/CanBuildFrom;)Ljava/lang/Object;
Asciz	flatMap;
NameAndType	flatMap:(Lscala/collection/TraversableProxyLike;Lscala/Function1;Lscala/collection/generic/CanBuildFrom;)Ljava/lang/Object;
Method	scala/collection/TraversableProxyLike$class.flatMap:(Lscala/collection/TraversableProxyLike;Lscala/Function1;Lscala/collection/generic/CanBuildFrom;)Ljava/lang/Object;
Asciz	filter;
Asciz	(Lscala/Function1;)Lscala/collection/Traversable;;
Asciz	(Lscala/collection/TraversableProxyLike;Lscala/Function1;)Lscala/collection/Traversable;;
NameAndType	filter:(Lscala/collection/TraversableProxyLike;Lscala/Function1;)Lscala/collection/Traversable;
Method	scala/collection/TraversableProxyLike$class.filter:(Lscala/collection/TraversableProxyLike;Lscala/Function1;)Lscala/collection/Traversable;
Asciz	p;
Asciz	filterNot;
NameAndType	filterNot:(Lscala/collection/TraversableProxyLike;Lscala/Function1;)Lscala/collection/Traversable;
Method	scala/collection/TraversableProxyLike$class.filterNot:(Lscala/collection/TraversableProxyLike;Lscala/Function1;)Lscala/collection/Traversable;
Asciz	partialMap;
Asciz	(Lscala/PartialFunction;Lscala/collection/generic/CanBuildFrom;)Ljava/lang/Object;;
Asciz	(Lscala/collection/TraversableProxyLike;Lscala/PartialFunction;Lscala/collection/generic/CanBuildFrom;)Ljava/lang/Object;;
NameAndType	partialMap:(Lscala/collection/TraversableProxyLike;Lscala/PartialFunction;Lscala/collection/generic/CanBuildFrom;)Ljava/lang/Object;
Method	scala/collection/TraversableProxyLike$class.partialMap:(Lscala/collection/TraversableProxyLike;Lscala/PartialFunction;Lscala/collection/generic/CanBuildFrom;)Ljava/lang/Object;
Asciz	pf;
Asciz	Lscala/PartialFunction;;
Asciz	partition;
Asciz	(Lscala/Function1;)Lscala/Tuple2;;
Asciz	(Lscala/collection/TraversableProxyLike;Lscala/Function1;)Lscala/Tuple2;;
NameAndType	partition:(Lscala/collection/TraversableProxyLike;Lscala/Function1;)Lscala/Tuple2;
Method	scala/collection/TraversableProxyLike$class.partition:(Lscala/collection/TraversableProxyLike;Lscala/Function1;)Lscala/Tuple2;
Asciz	groupBy;
Asciz	(Lscala/Function1;)Lscala/collection/Map;;
Asciz	(Lscala/collection/TraversableProxyLike;Lscala/Function1;)Lscala/collection/Map;;
NameAndType	groupBy:(Lscala/collection/TraversableProxyLike;Lscala/Function1;)Lscala/collection/Map;
Method	scala/collection/TraversableProxyLike$class.groupBy:(Lscala/collection/TraversableProxyLike;Lscala/Function1;)Lscala/collection/Map;
Asciz	forall;
Asciz	(Lscala/Function1;)Z;
Asciz	(Lscala/collection/TraversableProxyLike;Lscala/Function1;)Z;
NameAndType	forall:(Lscala/collection/TraversableProxyLike;Lscala/Function1;)Z
Method	scala/collection/TraversableProxyLike$class.forall:(Lscala/collection/TraversableProxyLike;Lscala/Function1;)Z
Asciz	exists;
NameAndType	exists:(Lscala/collection/TraversableProxyLike;Lscala/Function1;)Z
Method	scala/collection/TraversableProxyLike$class.exists:(Lscala/collection/TraversableProxyLike;Lscala/Function1;)Z
Asciz	count;
Asciz	(Lscala/Function1;)I;
Asciz	(Lscala/collection/TraversableProxyLike;Lscala/Function1;)I;
NameAndType	count:(Lscala/collection/TraversableProxyLike;Lscala/Function1;)I
Method	scala/collection/TraversableProxyLike$class.count:(Lscala/collection/TraversableProxyLike;Lscala/Function1;)I
Asciz	find;
Asciz	(Lscala/Function1;)Lscala/Option;;
Asciz	(Lscala/collection/TraversableProxyLike;Lscala/Function1;)Lscala/Option;;
NameAndType	find:(Lscala/collection/TraversableProxyLike;Lscala/Function1;)Lscala/Option;
Method	scala/collection/TraversableProxyLike$class.find:(Lscala/collection/TraversableProxyLike;Lscala/Function1;)Lscala/Option;
Asciz	foldLeft;
Asciz	(Ljava/lang/Object;Lscala/Function2;)Ljava/lang/Object;;
Asciz	(Lscala/collection/TraversableProxyLike;Ljava/lang/Object;Lscala/Function2;)Ljava/lang/Object;;
NameAndType	foldLeft:(Lscala/collection/TraversableProxyLike;Ljava/lang/Object;Lscala/Function2;)Ljava/lang/Object;
Method	scala/collection/TraversableProxyLike$class.foldLeft:(Lscala/collection/TraversableProxyLike;Ljava/lang/Object;Lscala/Function2;)Ljava/lang/Object;
Asciz	z;
Asciz	op;
Asciz	Lscala/Function2;;
Asciz	$div$colon;
NameAndType	$div$colon:(Lscala/collection/TraversableProxyLike;Ljava/lang/Object;Lscala/Function2;)Ljava/lang/Object;
Method	scala/collection/TraversableProxyLike$class.$div$colon:(Lscala/collection/TraversableProxyLike;Ljava/lang/Object;Lscala/Function2;)Ljava/lang/Object;
Asciz	foldRight;
NameAndType	foldRight:(Lscala/collection/TraversableProxyLike;Ljava/lang/Object;Lscala/Function2;)Ljava/lang/Object;
Method	scala/collection/TraversableProxyLike$class.foldRight:(Lscala/collection/TraversableProxyLike;Ljava/lang/Object;Lscala/Function2;)Ljava/lang/Object;
Asciz	$colon$bslash;
NameAndType	$colon$bslash:(Lscala/collection/TraversableProxyLike;Ljava/lang/Object;Lscala/Function2;)Ljava/lang/Object;
Method	scala/collection/TraversableProxyLike$class.$colon$bslash:(Lscala/collection/TraversableProxyLike;Ljava/lang/Object;Lscala/Function2;)Ljava/lang/Object;
Asciz	reduceLeft;
Asciz	(Lscala/Function2;)Ljava/lang/Object;;
Asciz	(Lscala/collection/TraversableProxyLike;Lscala/Function2;)Ljava/lang/Object;;
NameAndType	reduceLeft:(Lscala/collection/TraversableProxyLike;Lscala/Function2;)Ljava/lang/Object;
Method	scala/collection/TraversableProxyLike$class.reduceLeft:(Lscala/collection/TraversableProxyLike;Lscala/Function2;)Ljava/lang/Object;
Asciz	reduceLeftOption;
Asciz	(Lscala/Function2;)Lscala/Option;;
Asciz	(Lscala/collection/TraversableProxyLike;Lscala/Function2;)Lscala/Option;;
NameAndType	reduceLeftOption:(Lscala/collection/TraversableProxyLike;Lscala/Function2;)Lscala/Option;
Method	scala/collection/TraversableProxyLike$class.reduceLeftOption:(Lscala/collection/TraversableProxyLike;Lscala/Function2;)Lscala/Option;
Asciz	reduceRight;
NameAndType	reduceRight:(Lscala/collection/TraversableProxyLike;Lscala/Function2;)Ljava/lang/Object;
Method	scala/collection/TraversableProxyLike$class.reduceRight:(Lscala/collection/TraversableProxyLike;Lscala/Function2;)Ljava/lang/Object;
Asciz	reduceRightOption;
NameAndType	reduceRightOption:(Lscala/collection/TraversableProxyLike;Lscala/Function2;)Lscala/Option;
Method	scala/collection/TraversableProxyLike$class.reduceRightOption:(Lscala/collection/TraversableProxyLike;Lscala/Function2;)Lscala/Option;
Asciz	scanLeft;
Asciz	(Ljava/lang/Object;Lscala/Function2;Lscala/collection/generic/CanBuildFrom;)Ljava/lang/Object;;
Asciz	(Lscala/collection/TraversableProxyLike;Ljava/lang/Object;Lscala/Function2;Lscala/collection/generic/CanBuildFrom;)Ljava/lang/Object;;
NameAndType	scanLeft:(Lscala/collection/TraversableProxyLike;Ljava/lang/Object;Lscala/Function2;Lscala/collection/generic/CanBuildFrom;)Ljava/lang/Object;
Method	scala/collection/TraversableProxyLike$class.scanLeft:(Lscala/collection/TraversableProxyLike;Ljava/lang/Object;Lscala/Function2;Lscala/collection/generic/CanBuildFrom;)Ljava/lang/Object;
Asciz	scanRight;
NameAndType	scanRight:(Lscala/collection/TraversableProxyLike;Ljava/lang/Object;Lscala/Function2;Lscala/collection/generic/CanBuildFrom;)Ljava/lang/Object;
Method	scala/collection/TraversableProxyLike$class.scanRight:(Lscala/collection/TraversableProxyLike;Ljava/lang/Object;Lscala/Function2;Lscala/collection/generic/CanBuildFrom;)Ljava/lang/Object;
Asciz	sum;
Asciz	(Lscala/math/Numeric;)Ljava/lang/Object;;
Asciz	(Lscala/collection/TraversableProxyLike;Lscala/math/Numeric;)Ljava/lang/Object;;
NameAndType	sum:(Lscala/collection/TraversableProxyLike;Lscala/math/Numeric;)Ljava/lang/Object;
Method	scala/collection/TraversableProxyLike$class.sum:(Lscala/collection/TraversableProxyLike;Lscala/math/Numeric;)Ljava/lang/Object;
Asciz	num;
Asciz	Lscala/math/Numeric;;
Asciz	product;
NameAndType	product:(Lscala/collection/TraversableProxyLike;Lscala/math/Numeric;)Ljava/lang/Object;
Method	scala/collection/TraversableProxyLike$class.product:(Lscala/collection/TraversableProxyLike;Lscala/math/Numeric;)Ljava/lang/Object;
Asciz	min;
Asciz	(Lscala/math/Ordering;)Ljava/lang/Object;;
Asciz	(Lscala/collection/TraversableProxyLike;Lscala/math/Ordering;)Ljava/lang/Object;;
NameAndType	min:(Lscala/collection/TraversableProxyLike;Lscala/math/Ordering;)Ljava/lang/Object;
Method	scala/collection/TraversableProxyLike$class.min:(Lscala/collection/TraversableProxyLike;Lscala/math/Ordering;)Ljava/lang/Object;
Asciz	cmp;
Asciz	Lscala/math/Ordering;;
Asciz	max;
NameAndType	max:(Lscala/collection/TraversableProxyLike;Lscala/math/Ordering;)Ljava/lang/Object;
Method	scala/collection/TraversableProxyLike$class.max:(Lscala/collection/TraversableProxyLike;Lscala/math/Ordering;)Ljava/lang/Object;
Asciz	head;
Asciz	()Ljava/lang/Object;;
Asciz	(Lscala/collection/TraversableProxyLike;)Ljava/lang/Object;;
NameAndType	head:(Lscala/collection/TraversableProxyLike;)Ljava/lang/Object;
Method	scala/collection/TraversableProxyLike$class.head:(Lscala/collection/TraversableProxyLike;)Ljava/lang/Object;
Asciz	headOption;
Asciz	()Lscala/Option;;
Asciz	(Lscala/collection/TraversableProxyLike;)Lscala/Option;;
NameAndType	headOption:(Lscala/collection/TraversableProxyLike;)Lscala/Option;
Method	scala/collection/TraversableProxyLike$class.headOption:(Lscala/collection/TraversableProxyLike;)Lscala/Option;
Asciz	tail;
Asciz	()Lscala/collection/Traversable;;
Asciz	(Lscala/collection/TraversableProxyLike;)Lscala/collection/Traversable;;
NameAndType	tail:(Lscala/collection/TraversableProxyLike;)Lscala/collection/Traversable;
Method	scala/collection/TraversableProxyLike$class.tail:(Lscala/collection/TraversableProxyLike;)Lscala/collection/Traversable;
Asciz	last;
NameAndType	last:(Lscala/collection/TraversableProxyLike;)Ljava/lang/Object;
Method	scala/collection/TraversableProxyLike$class.last:(Lscala/collection/TraversableProxyLike;)Ljava/lang/Object;
Asciz	lastOption;
NameAndType	lastOption:(Lscala/collection/TraversableProxyLike;)Lscala/Option;
Method	scala/collection/TraversableProxyLike$class.lastOption:(Lscala/collection/TraversableProxyLike;)Lscala/Option;
Asciz	init;
NameAndType	init:(Lscala/collection/TraversableProxyLike;)Lscala/collection/Traversable;
Method	scala/collection/TraversableProxyLike$class.init:(Lscala/collection/TraversableProxyLike;)Lscala/collection/Traversable;
Asciz	take;
Asciz	(I)Lscala/collection/Traversable;;
Asciz	(Lscala/collection/TraversableProxyLike;I)Lscala/collection/Traversable;;
NameAndType	take:(Lscala/collection/TraversableProxyLike;I)Lscala/collection/Traversable;
Method	scala/collection/TraversableProxyLike$class.take:(Lscala/collection/TraversableProxyLike;I)Lscala/collection/Traversable;
Asciz	drop;
NameAndType	drop:(Lscala/collection/TraversableProxyLike;I)Lscala/collection/Traversable;
Method	scala/collection/TraversableProxyLike$class.drop:(Lscala/collection/TraversableProxyLike;I)Lscala/collection/Traversable;
Asciz	slice;
Asciz	(II)Lscala/collection/Traversable;;
Asciz	(Lscala/collection/TraversableProxyLike;II)Lscala/collection/Traversable;;
NameAndType	slice:(Lscala/collection/TraversableProxyLike;II)Lscala/collection/Traversable;
Method	scala/collection/TraversableProxyLike$class.slice:(Lscala/collection/TraversableProxyLike;II)Lscala/collection/Traversable;
Asciz	takeWhile;
NameAndType	takeWhile:(Lscala/collection/TraversableProxyLike;Lscala/Function1;)Lscala/collection/Traversable;
Method	scala/collection/TraversableProxyLike$class.takeWhile:(Lscala/collection/TraversableProxyLike;Lscala/Function1;)Lscala/collection/Traversable;
Asciz	dropWhile;
NameAndType	dropWhile:(Lscala/collection/TraversableProxyLike;Lscala/Function1;)Lscala/collection/Traversable;
Method	scala/collection/TraversableProxyLike$class.dropWhile:(Lscala/collection/TraversableProxyLike;Lscala/Function1;)Lscala/collection/Traversable;
Asciz	span;
NameAndType	span:(Lscala/collection/TraversableProxyLike;Lscala/Function1;)Lscala/Tuple2;
Method	scala/collection/TraversableProxyLike$class.span:(Lscala/collection/TraversableProxyLike;Lscala/Function1;)Lscala/Tuple2;
Asciz	splitAt;
Asciz	(I)Lscala/Tuple2;;
Asciz	(Lscala/collection/TraversableProxyLike;I)Lscala/Tuple2;;
NameAndType	splitAt:(Lscala/collection/TraversableProxyLike;I)Lscala/Tuple2;
Method	scala/collection/TraversableProxyLike$class.splitAt:(Lscala/collection/TraversableProxyLike;I)Lscala/Tuple2;
Asciz	copyToBuffer;
Asciz	(Lscala/collection/mutable/Buffer;)V;
Asciz	(Lscala/collection/TraversableProxyLike;Lscala/collection/mutable/Buffer;)V;
NameAndType	copyToBuffer:(Lscala/collection/TraversableProxyLike;Lscala/collection/mutable/Buffer;)V
Method	scala/collection/TraversableProxyLike$class.copyToBuffer:(Lscala/collection/TraversableProxyLike;Lscala/collection/mutable/Buffer;)V
Asciz	dest;
Asciz	Lscala/collection/mutable/Buffer;;
Asciz	copyToArray;
Asciz	(Ljava/lang/Object;II)V;
Asciz	(Lscala/collection/TraversableProxyLike;Ljava/lang/Object;II)V;
NameAndType	copyToArray:(Lscala/collection/TraversableProxyLike;Ljava/lang/Object;II)V
Method	scala/collection/TraversableProxyLike$class.copyToArray:(Lscala/collection/TraversableProxyLike;Ljava/lang/Object;II)V
Asciz	xs;
Asciz	start;
Asciz	len;
Asciz	(Ljava/lang/Object;I)V;
Asciz	(Lscala/collection/TraversableProxyLike;Ljava/lang/Object;I)V;
NameAndType	copyToArray:(Lscala/collection/TraversableProxyLike;Ljava/lang/Object;I)V
Method	scala/collection/TraversableProxyLike$class.copyToArray:(Lscala/collection/TraversableProxyLike;Ljava/lang/Object;I)V
Asciz	(Ljava/lang/Object;)V;
Asciz	(Lscala/collection/TraversableProxyLike;Ljava/lang/Object;)V;
NameAndType	copyToArray:(Lscala/collection/TraversableProxyLike;Ljava/lang/Object;)V
Method	scala/collection/TraversableProxyLike$class.copyToArray:(Lscala/collection/TraversableProxyLike;Ljava/lang/Object;)V
Asciz	toArray;
Asciz	(Lscala/reflect/ClassManifest;)Ljava/lang/Object;;
Asciz	(Lscala/collection/TraversableProxyLike;Lscala/reflect/ClassManifest;)Ljava/lang/Object;;
NameAndType	toArray:(Lscala/collection/TraversableProxyLike;Lscala/reflect/ClassManifest;)Ljava/lang/Object;
Method	scala/collection/TraversableProxyLike$class.toArray:(Lscala/collection/TraversableProxyLike;Lscala/reflect/ClassManifest;)Ljava/lang/Object;
Asciz	evidence$1;
Asciz	Lscala/reflect/ClassManifest;;
Asciz	toList;
Asciz	()Lscala/collection/immutable/List;;
Asciz	(Lscala/collection/TraversableProxyLike;)Lscala/collection/immutable/List;;
NameAndType	toList:(Lscala/collection/TraversableProxyLike;)Lscala/collection/immutable/List;
Method	scala/collection/TraversableProxyLike$class.toList:(Lscala/collection/TraversableProxyLike;)Lscala/collection/immutable/List;
Asciz	toIterable;
Asciz	()Lscala/collection/Iterable;;
Asciz	(Lscala/collection/TraversableProxyLike;)Lscala/collection/Iterable;;
NameAndType	toIterable:(Lscala/collection/TraversableProxyLike;)Lscala/collection/Iterable;
Method	scala/collection/TraversableProxyLike$class.toIterable:(Lscala/collection/TraversableProxyLike;)Lscala/collection/Iterable;
Asciz	toSeq;
Asciz	()Lscala/collection/Seq;;
Asciz	(Lscala/collection/TraversableProxyLike;)Lscala/collection/Seq;;
NameAndType	toSeq:(Lscala/collection/TraversableProxyLike;)Lscala/collection/Seq;
Method	scala/collection/TraversableProxyLike$class.toSeq:(Lscala/collection/TraversableProxyLike;)Lscala/collection/Seq;
Asciz	toIndexedSeq;
Asciz	()Lscala/collection/mutable/IndexedSeq;;
Asciz	(Lscala/collection/TraversableProxyLike;)Lscala/collection/mutable/IndexedSeq;;
NameAndType	toIndexedSeq:(Lscala/collection/TraversableProxyLike;)Lscala/collection/mutable/IndexedSeq;
Method	scala/collection/TraversableProxyLike$class.toIndexedSeq:(Lscala/collection/TraversableProxyLike;)Lscala/collection/mutable/IndexedSeq;
Asciz	toStream;
Asciz	()Lscala/collection/immutable/Stream;;
Asciz	(Lscala/collection/TraversableProxyLike;)Lscala/collection/immutable/Stream;;
NameAndType	toStream:(Lscala/collection/TraversableProxyLike;)Lscala/collection/immutable/Stream;
Method	scala/collection/TraversableProxyLike$class.toStream:(Lscala/collection/TraversableProxyLike;)Lscala/collection/immutable/Stream;
Asciz	toSet;
Asciz	()Lscala/collection/immutable/Set;;
Asciz	(Lscala/collection/TraversableProxyLike;)Lscala/collection/immutable/Set;;
NameAndType	toSet:(Lscala/collection/TraversableProxyLike;)Lscala/collection/immutable/Set;
Method	scala/collection/TraversableProxyLike$class.toSet:(Lscala/collection/TraversableProxyLike;)Lscala/collection/immutable/Set;
Asciz	toMap;
Asciz	(Lscala/Predef$$less$colon$less;)Lscala/collection/immutable/Map;;
Asciz	(Lscala/collection/TraversableProxyLike;Lscala/Predef$$less$colon$less;)Lscala/collection/immutable/Map;;
NameAndType	toMap:(Lscala/collection/TraversableProxyLike;Lscala/Predef$$less$colon$less;)Lscala/collection/immutable/Map;
Method	scala/collection/TraversableProxyLike$class.toMap:(Lscala/collection/TraversableProxyLike;Lscala/Predef$$less$colon$less;)Lscala/collection/immutable/Map;
Asciz	ev;
Asciz	Lscala/Predef$$less$colon$less;;
Asciz	mkString;
Asciz	(Ljava/lang/String;Ljava/lang/String;Ljava/lang/String;)Ljava/lang/String;;
Asciz	(Lscala/collection/TraversableProxyLike;Ljava/lang/String;Ljava/lang/String;Ljava/lang/String;)Ljava/lang/String;;
NameAndType	mkString:(Lscala/collection/TraversableProxyLike;Ljava/lang/String;Ljava/lang/String;Ljava/lang/String;)Ljava/lang/String;
Method	scala/collection/TraversableProxyLike$class.mkString:(Lscala/collection/TraversableProxyLike;Ljava/lang/String;Ljava/lang/String;Ljava/lang/String;)Ljava/lang/String;
Asciz	Ljava/lang/String;;
Asciz	sep;
Asciz	end;
Asciz	(Ljava/lang/String;)Ljava/lang/String;;
Asciz	(Lscala/collection/TraversableProxyLike;Ljava/lang/String;)Ljava/lang/String;;
NameAndType	mkString:(Lscala/collection/TraversableProxyLike;Ljava/lang/String;)Ljava/lang/String;
Method	scala/collection/TraversableProxyLike$class.mkString:(Lscala/collection/TraversableProxyLike;Ljava/lang/String;)Ljava/lang/String;
Asciz	()Ljava/lang/String;;
Asciz	(Lscala/collection/TraversableProxyLike;)Ljava/lang/String;;
NameAndType	mkString:(Lscala/collection/TraversableProxyLike;)Ljava/lang/String;
Method	scala/collection/TraversableProxyLike$class.mkString:(Lscala/collection/TraversableProxyLike;)Ljava/lang/String;
Asciz	addString;
Asciz	(Lscala/collection/mutable/StringBuilder;Ljava/lang/String;Ljava/lang/String;Ljava/lang/String;)Lscala/collection/mutable/StringBuilder;;
Asciz	(Lscala/collection/TraversableProxyLike;Lscala/collection/mutable/StringBuilder;Ljava/lang/String;Ljava/lang/String;Ljava/lang/String;)Lscala/collection/mutable/StringBuilder;;
NameAndType	addString:(Lscala/collection/TraversableProxyLike;Lscala/collection/mutable/StringBuilder;Ljava/lang/String;Ljava/lang/String;Ljava/lang/String;)Lscala/collection/mutable/StringBuilder;
Method	scala/collection/TraversableProxyLike$class.addString:(Lscala/collection/TraversableProxyLike;Lscala/collection/mutable/StringBuilder;Ljava/lang/String;Ljava/lang/String;Ljava/lang/String;)Lscala/collection/mutable/StringBuilder;
Asciz	b;
Asciz	Lscala/collection/mutable/StringBuilder;;
Asciz	(Lscala/collection/mutable/StringBuilder;Ljava/lang/String;)Lscala/collection/mutable/StringBuilder;;
Asciz	(Lscala/collection/TraversableProxyLike;Lscala/collection/mutable/StringBuilder;Ljava/lang/String;)Lscala/collection/mutable/StringBuilder;;
NameAndType	addString:(Lscala/collection/TraversableProxyLike;Lscala/collection/mutable/StringBuilder;Ljava/lang/String;)Lscala/collection/mutable/StringBuilder;
Method	scala/collection/TraversableProxyLike$class.addString:(Lscala/collection/TraversableProxyLike;Lscala/collection/mutable/StringBuilder;Ljava/lang/String;)Lscala/collection/mutable/StringBuilder;
Asciz	(Lscala/collection/mutable/StringBuilder;)Lscala/collection/mutable/StringBuilder;;
Asciz	(Lscala/collection/TraversableProxyLike;Lscala/collection/mutable/StringBuilder;)Lscala/collection/mutable/StringBuilder;;
NameAndType	addString:(Lscala/collection/TraversableProxyLike;Lscala/collection/mutable/StringBuilder;)Lscala/collection/mutable/StringBuilder;
Method	scala/collection/TraversableProxyLike$class.addString:(Lscala/collection/TraversableProxyLike;Lscala/collection/mutable/StringBuilder;)Lscala/collection/mutable/StringBuilder;
Asciz	stringPrefix;
NameAndType	stringPrefix:(Lscala/collection/TraversableProxyLike;)Ljava/lang/String;
Method	scala/collection/TraversableProxyLike$class.stringPrefix:(Lscala/collection/TraversableProxyLike;)Ljava/lang/String;
Asciz	hashCode;
Asciz	scala/Proxy$class;
class	scala/Proxy$class
Asciz	(Lscala/Proxy;)I;
NameAndType	hashCode:(Lscala/Proxy;)I
Method	scala/Proxy$class.hashCode:(Lscala/Proxy;)I
Asciz	equals;
Asciz	(Lscala/Proxy;Ljava/lang/Object;)Z;
NameAndType	equals:(Lscala/Proxy;Ljava/lang/Object;)Z
Method	scala/Proxy$class.equals:(Lscala/Proxy;Ljava/lang/Object;)Z
Asciz	toString;
Asciz	(Lscala/Proxy;)Ljava/lang/String;;
NameAndType	toString:(Lscala/Proxy;)Ljava/lang/String;
Method	scala/Proxy$class.toString:(Lscala/Proxy;)Ljava/lang/String;
Asciz	companion;
Asciz	()Lscala/collection/generic/GenericCompanion;;
Asciz	scala/collection/mutable/Set$class;
class	scala/collection/mutable/Set$class
Asciz	(Lscala/collection/mutable/Set;)Lscala/collection/generic/GenericCompanion;;
NameAndType	companion:(Lscala/collection/mutable/Set;)Lscala/collection/generic/GenericCompanion;
Method	scala/collection/mutable/Set$class.companion:(Lscala/collection/mutable/Set;)Lscala/collection/generic/GenericCompanion;
Asciz	scala$collection$mutable$SetLike$$super$map;
Asciz	scala/collection/TraversableLike$class;
class	scala/collection/TraversableLike$class
Asciz	(Lscala/collection/TraversableLike;Lscala/Function1;Lscala/collection/generic/CanBuildFrom;)Ljava/lang/Object;;
NameAndType	map:(Lscala/collection/TraversableLike;Lscala/Function1;Lscala/collection/generic/CanBuildFrom;)Ljava/lang/Object;
Method	scala/collection/TraversableLike$class.map:(Lscala/collection/TraversableLike;Lscala/Function1;Lscala/collection/generic/CanBuildFrom;)Ljava/lang/Object;
Asciz	newBuilder;
Asciz	()Lscala/collection/mutable/Builder;;
Asciz	scala/collection/mutable/SetLike$class;
class	scala/collection/mutable/SetLike$class
Asciz	(Lscala/collection/mutable/SetLike;)Lscala/collection/mutable/Builder;;
NameAndType	newBuilder:(Lscala/collection/mutable/SetLike;)Lscala/collection/mutable/Builder;
Method	scala/collection/mutable/SetLike$class.newBuilder:(Lscala/collection/mutable/SetLike;)Lscala/collection/mutable/Builder;
Asciz	add;
Asciz	(Lscala/collection/mutable/SetLike;Ljava/lang/Object;)Z;
NameAndType	add:(Lscala/collection/mutable/SetLike;Ljava/lang/Object;)Z
Method	scala/collection/mutable/SetLike$class.add:(Lscala/collection/mutable/SetLike;Ljava/lang/Object;)Z
Asciz	remove;
NameAndType	remove:(Lscala/collection/mutable/SetLike;Ljava/lang/Object;)Z
Method	scala/collection/mutable/SetLike$class.remove:(Lscala/collection/mutable/SetLike;Ljava/lang/Object;)Z
Asciz	update;
Asciz	(Ljava/lang/Object;Z)V;
Asciz	(Lscala/collection/mutable/SetLike;Ljava/lang/Object;Z)V;
NameAndType	update:(Lscala/collection/mutable/SetLike;Ljava/lang/Object;Z)V
Method	scala/collection/mutable/SetLike$class.update:(Lscala/collection/mutable/SetLike;Ljava/lang/Object;Z)V
Asciz	included;
Asciz	Z;
Asciz	retain;
Asciz	(Lscala/collection/mutable/SetLike;Lscala/Function1;)V;
NameAndType	retain:(Lscala/collection/mutable/SetLike;Lscala/Function1;)V
Method	scala/collection/mutable/SetLike$class.retain:(Lscala/collection/mutable/SetLike;Lscala/Function1;)V
Asciz	clear;
Asciz	()V;
Asciz	(Lscala/collection/mutable/SetLike;)V;
NameAndType	clear:(Lscala/collection/mutable/SetLike;)V
Method	scala/collection/mutable/SetLike$class.clear:(Lscala/collection/mutable/SetLike;)V
Asciz	clone;
Asciz	()Lscala/collection/mutable/Set;;
Asciz	(Lscala/collection/mutable/SetLike;)Lscala/collection/mutable/Set;;
NameAndType	clone:(Lscala/collection/mutable/SetLike;)Lscala/collection/mutable/Set;
Method	scala/collection/mutable/SetLike$class.clone:(Lscala/collection/mutable/SetLike;)Lscala/collection/mutable/Set;
Asciz	result;
NameAndType	result:(Lscala/collection/mutable/SetLike;)Lscala/collection/mutable/Set;
Method	scala/collection/mutable/SetLike$class.result:(Lscala/collection/mutable/SetLike;)Lscala/collection/mutable/Set;
Asciz	(Ljava/lang/Object;Ljava/lang/Object;Lscala/collection/Seq;)Lscala/collection/mutable/Set;;
Asciz	(Lscala/collection/mutable/SetLike;Ljava/lang/Object;Ljava/lang/Object;Lscala/collection/Seq;)Lscala/collection/mutable/Set;;
NameAndType	$plus:(Lscala/collection/mutable/SetLike;Ljava/lang/Object;Ljava/lang/Object;Lscala/collection/Seq;)Lscala/collection/mutable/Set;
Method	scala/collection/mutable/SetLike$class.$plus:(Lscala/collection/mutable/SetLike;Ljava/lang/Object;Ljava/lang/Object;Lscala/collection/Seq;)Lscala/collection/mutable/Set;
Asciz	elem1;
Asciz	elem2;
Asciz	elems;
Asciz	Lscala/collection/Seq;;
Asciz	(Lscala/collection/Traversable;)Lscala/collection/mutable/Set;;
Asciz	(Lscala/collection/mutable/SetLike;Lscala/collection/Traversable;)Lscala/collection/mutable/Set;;
NameAndType	$plus$plus:(Lscala/collection/mutable/SetLike;Lscala/collection/Traversable;)Lscala/collection/mutable/Set;
Method	scala/collection/mutable/SetLike$class.$plus$plus:(Lscala/collection/mutable/SetLike;Lscala/collection/Traversable;)Lscala/collection/mutable/Set;
Asciz	iter;
Asciz	(Lscala/collection/Iterator;)Lscala/collection/mutable/Set;;
Asciz	(Lscala/collection/mutable/SetLike;Lscala/collection/Iterator;)Lscala/collection/mutable/Set;;
NameAndType	$plus$plus:(Lscala/collection/mutable/SetLike;Lscala/collection/Iterator;)Lscala/collection/mutable/Set;
Method	scala/collection/mutable/SetLike$class.$plus$plus:(Lscala/collection/mutable/SetLike;Lscala/collection/Iterator;)Lscala/collection/mutable/Set;
NameAndType	$minus:(Lscala/collection/mutable/SetLike;Ljava/lang/Object;Ljava/lang/Object;Lscala/collection/Seq;)Lscala/collection/mutable/Set;
Method	scala/collection/mutable/SetLike$class.$minus:(Lscala/collection/mutable/SetLike;Ljava/lang/Object;Ljava/lang/Object;Lscala/collection/Seq;)Lscala/collection/mutable/Set;
Asciz	$minus$minus;
NameAndType	$minus$minus:(Lscala/collection/mutable/SetLike;Lscala/collection/Traversable;)Lscala/collection/mutable/Set;
Method	scala/collection/mutable/SetLike$class.$minus$minus:(Lscala/collection/mutable/SetLike;Lscala/collection/Traversable;)Lscala/collection/mutable/Set;
NameAndType	$minus$minus:(Lscala/collection/mutable/SetLike;Lscala/collection/Iterator;)Lscala/collection/mutable/Set;
Method	scala/collection/mutable/SetLike$class.$minus$minus:(Lscala/collection/mutable/SetLike;Lscala/collection/Iterator;)Lscala/collection/mutable/Set;
Asciz	$less$less;
Asciz	(Lscala/collection/script/Message;)V;
Asciz	(Lscala/collection/mutable/SetLike;Lscala/collection/script/Message;)V;
NameAndType	$less$less:(Lscala/collection/mutable/SetLike;Lscala/collection/script/Message;)V
Method	scala/collection/mutable/SetLike$class.$less$less:(Lscala/collection/mutable/SetLike;Lscala/collection/script/Message;)V
Asciz	cmd;
Asciz	Lscala/collection/script/Message;;
Asciz	scala$collection$mutable$Cloneable$$super$clone;
Asciz	java/lang/Object;
class	java/lang/Object
NameAndType	clone:()Ljava/lang/Object;
Method	java/lang/Object.clone:()Ljava/lang/Object;
Asciz	(Ljava/lang/Object;Ljava/lang/Object;Lscala/collection/Seq;)Lscala/collection/generic/Shrinkable;;
Asciz	scala/collection/generic/Shrinkable$class;
class	scala/collection/generic/Shrinkable$class
Asciz	(Lscala/collection/generic/Shrinkable;Ljava/lang/Object;Ljava/lang/Object;Lscala/collection/Seq;)Lscala/collection/generic/Shrinkable;;
NameAndType	$minus$eq:(Lscala/collection/generic/Shrinkable;Ljava/lang/Object;Ljava/lang/Object;Lscala/collection/Seq;)Lscala/collection/generic/Shrinkable;
Method	scala/collection/generic/Shrinkable$class.$minus$eq:(Lscala/collection/generic/Shrinkable;Ljava/lang/Object;Ljava/lang/Object;Lscala/collection/Seq;)Lscala/collection/generic/Shrinkable;
Asciz	$minus$minus$eq;
Asciz	(Lscala/collection/Iterator;)Lscala/collection/generic/Shrinkable;;
Asciz	(Lscala/collection/generic/Shrinkable;Lscala/collection/Iterator;)Lscala/collection/generic/Shrinkable;;
NameAndType	$minus$minus$eq:(Lscala/collection/generic/Shrinkable;Lscala/collection/Iterator;)Lscala/collection/generic/Shrinkable;
Method	scala/collection/generic/Shrinkable$class.$minus$minus$eq:(Lscala/collection/generic/Shrinkable;Lscala/collection/Iterator;)Lscala/collection/generic/Shrinkable;
Asciz	(Lscala/collection/Traversable;)Lscala/collection/generic/Shrinkable;;
Asciz	(Lscala/collection/generic/Shrinkable;Lscala/collection/Traversable;)Lscala/collection/generic/Shrinkable;;
NameAndType	$minus$minus$eq:(Lscala/collection/generic/Shrinkable;Lscala/collection/Traversable;)Lscala/collection/generic/Shrinkable;
Method	scala/collection/generic/Shrinkable$class.$minus$minus$eq:(Lscala/collection/generic/Shrinkable;Lscala/collection/Traversable;)Lscala/collection/generic/Shrinkable;
Asciz	sizeHint;
Asciz	(I)V;
Asciz	scala/collection/mutable/Builder$class;
class	scala/collection/mutable/Builder$class
Asciz	(Lscala/collection/mutable/Builder;I)V;
NameAndType	sizeHint:(Lscala/collection/mutable/Builder;I)V
Method	scala/collection/mutable/Builder$class.sizeHint:(Lscala/collection/mutable/Builder;I)V
Asciz	mapResult;
Asciz	(Lscala/Function1;)Lscala/collection/mutable/Builder;;
Asciz	(Lscala/collection/mutable/Builder;Lscala/Function1;)Lscala/collection/mutable/Builder;;
NameAndType	mapResult:(Lscala/collection/mutable/Builder;Lscala/Function1;)Lscala/collection/mutable/Builder;
Method	scala/collection/mutable/Builder$class.mapResult:(Lscala/collection/mutable/Builder;Lscala/Function1;)Lscala/collection/mutable/Builder;
Asciz	(Ljava/lang/Object;Ljava/lang/Object;Lscala/collection/Seq;)Lscala/collection/generic/Growable;;
Asciz	scala/collection/generic/Growable$class;
class	scala/collection/generic/Growable$class
Asciz	(Lscala/collection/generic/Growable;Ljava/lang/Object;Ljava/lang/Object;Lscala/collection/Seq;)Lscala/collection/generic/Growable;;
NameAndType	$plus$eq:(Lscala/collection/generic/Growable;Ljava/lang/Object;Ljava/lang/Object;Lscala/collection/Seq;)Lscala/collection/generic/Growable;
Method	scala/collection/generic/Growable$class.$plus$eq:(Lscala/collection/generic/Growable;Ljava/lang/Object;Ljava/lang/Object;Lscala/collection/Seq;)Lscala/collection/generic/Growable;
Asciz	$plus$plus$eq;
Asciz	(Lscala/collection/Iterator;)Lscala/collection/generic/Growable;;
Asciz	(Lscala/collection/generic/Growable;Lscala/collection/Iterator;)Lscala/collection/generic/Growable;;
NameAndType	$plus$plus$eq:(Lscala/collection/generic/Growable;Lscala/collection/Iterator;)Lscala/collection/generic/Growable;
Method	scala/collection/generic/Growable$class.$plus$plus$eq:(Lscala/collection/generic/Growable;Lscala/collection/Iterator;)Lscala/collection/generic/Growable;
Asciz	(Lscala/collection/Traversable;)Lscala/collection/generic/Growable;;
Asciz	(Lscala/collection/generic/Growable;Lscala/collection/Traversable;)Lscala/collection/generic/Growable;;
NameAndType	$plus$plus$eq:(Lscala/collection/generic/Growable;Lscala/collection/Traversable;)Lscala/collection/generic/Growable;
Method	scala/collection/generic/Growable$class.$plus$plus$eq:(Lscala/collection/generic/Growable;Lscala/collection/Traversable;)Lscala/collection/generic/Growable;
Asciz	$times$times;
Asciz	scala/collection/SetLike$class;
class	scala/collection/SetLike$class
Asciz	(Lscala/collection/SetLike;Lscala/collection/Set;)Lscala/collection/Set;;
NameAndType	$times$times:(Lscala/collection/SetLike;Lscala/collection/Set;)Lscala/collection/Set;
Method	scala/collection/SetLike$class.$times$times:(Lscala/collection/SetLike;Lscala/collection/Set;)Lscala/collection/Set;
Asciz	Deprecated;
Asciz	compose;
Asciz	(Lscala/Function1;)Lscala/Function1;;
Asciz	scala/Function1$class;
class	scala/Function1$class
Asciz	(Lscala/Function1;Lscala/Function1;)Lscala/Function1;;
NameAndType	compose:(Lscala/Function1;Lscala/Function1;)Lscala/Function1;
Method	scala/Function1$class.compose:(Lscala/Function1;Lscala/Function1;)Lscala/Function1;
Asciz	g;
Asciz	andThen;
NameAndType	andThen:(Lscala/Function1;Lscala/Function1;)Lscala/Function1;
Method	scala/Function1$class.andThen:(Lscala/Function1;Lscala/Function1;)Lscala/Function1;
Asciz	thisCollection;
Asciz	scala/collection/IterableLike$class;
class	scala/collection/IterableLike$class
Asciz	(Lscala/collection/IterableLike;)Lscala/collection/Iterable;;
NameAndType	thisCollection:(Lscala/collection/IterableLike;)Lscala/collection/Iterable;
Method	scala/collection/IterableLike$class.thisCollection:(Lscala/collection/IterableLike;)Lscala/collection/Iterable;
Asciz	toCollection;
Asciz	(Ljava/lang/Object;)Lscala/collection/Iterable;;
Asciz	(Lscala/collection/IterableLike;Ljava/lang/Object;)Lscala/collection/Iterable;;
NameAndType	toCollection:(Lscala/collection/IterableLike;Ljava/lang/Object;)Lscala/collection/Iterable;
Method	scala/collection/IterableLike$class.toCollection:(Lscala/collection/IterableLike;Ljava/lang/Object;)Lscala/collection/Iterable;
Asciz	canEqual;
Asciz	(Lscala/collection/IterableLike;Ljava/lang/Object;)Z;
NameAndType	canEqual:(Lscala/collection/IterableLike;Ljava/lang/Object;)Z
Method	scala/collection/IterableLike$class.canEqual:(Lscala/collection/IterableLike;Ljava/lang/Object;)Z
Asciz	elements;
Asciz	(Lscala/collection/IterableLike;)Lscala/collection/Iterator;;
NameAndType	elements:(Lscala/collection/IterableLike;)Lscala/collection/Iterator;
Method	scala/collection/IterableLike$class.elements:(Lscala/collection/IterableLike;)Lscala/collection/Iterator;
Asciz	first;
Asciz	(Lscala/collection/IterableLike;)Ljava/lang/Object;;
NameAndType	first:(Lscala/collection/IterableLike;)Ljava/lang/Object;
Method	scala/collection/IterableLike$class.first:(Lscala/collection/IterableLike;)Ljava/lang/Object;
Asciz	firstOption;
Asciz	(Lscala/collection/IterableLike;)Lscala/Option;;
NameAndType	firstOption:(Lscala/collection/IterableLike;)Lscala/Option;
Method	scala/collection/IterableLike$class.firstOption:(Lscala/collection/IterableLike;)Lscala/Option;
Asciz	projection;
Asciz	(Lscala/collection/IterableLike;)Lscala/collection/IterableView;;
NameAndType	projection:(Lscala/collection/IterableLike;)Lscala/collection/IterableView;
Method	scala/collection/IterableLike$class.projection:(Lscala/collection/IterableLike;)Lscala/collection/IterableView;
Asciz	genericBuilder;
Asciz	scala/collection/generic/GenericTraversableTemplate$class;
class	scala/collection/generic/GenericTraversableTemplate$class
Asciz	(Lscala/collection/generic/GenericTraversableTemplate;)Lscala/collection/mutable/Builder;;
NameAndType	genericBuilder:(Lscala/collection/generic/GenericTraversableTemplate;)Lscala/collection/mutable/Builder;
Method	scala/collection/generic/GenericTraversableTemplate$class.genericBuilder:(Lscala/collection/generic/GenericTraversableTemplate;)Lscala/collection/mutable/Builder;
Asciz	unzip;
Asciz	(Lscala/collection/generic/GenericTraversableTemplate;Lscala/Function1;)Lscala/Tuple2;;
NameAndType	unzip:(Lscala/collection/generic/GenericTraversableTemplate;Lscala/Function1;)Lscala/Tuple2;
Method	scala/collection/generic/GenericTraversableTemplate$class.unzip:(Lscala/collection/generic/GenericTraversableTemplate;Lscala/Function1;)Lscala/Tuple2;
Asciz	asPair;
Asciz	flatten;
Asciz	(Lscala/collection/generic/GenericTraversableTemplate;Lscala/Function1;)Lscala/collection/Traversable;;
NameAndType	flatten:(Lscala/collection/generic/GenericTraversableTemplate;Lscala/Function1;)Lscala/collection/Traversable;
Method	scala/collection/generic/GenericTraversableTemplate$class.flatten:(Lscala/collection/generic/GenericTraversableTemplate;Lscala/Function1;)Lscala/collection/Traversable;
Asciz	asTraversable;
Asciz	transpose;
NameAndType	transpose:(Lscala/collection/generic/GenericTraversableTemplate;Lscala/Function1;)Lscala/collection/Traversable;
Method	scala/collection/generic/GenericTraversableTemplate$class.transpose:(Lscala/collection/generic/GenericTraversableTemplate;Lscala/Function1;)Lscala/collection/Traversable;
Asciz	withFilter;
Asciz	(Lscala/Function1;)Lscala/collection/TraversableLike$WithFilter;;
Asciz	(Lscala/collection/TraversableLike;Lscala/Function1;)Lscala/collection/TraversableLike$WithFilter;;
NameAndType	withFilter:(Lscala/collection/TraversableLike;Lscala/Function1;)Lscala/collection/TraversableLike$WithFilter;
Method	scala/collection/TraversableLike$class.withFilter:(Lscala/collection/TraversableLike;Lscala/Function1;)Lscala/collection/TraversableLike$WithFilter;
Asciz	scala/collection/mutable/SetProxy$$anon$1;
class	scala/collection/mutable/SetProxy$$anon$1
NameAndType	self:Lscala/collection/mutable/Set;
Field	scala/collection/mutable/SetProxy$$anon$1.self:Lscala/collection/mutable/Set;
Asciz	()Lscala/collection/mutable/Set<TA;>;;
Asciz	(Ljava/lang/Object;)Lscala/collection/Traversable;;
Asciz	scala/collection/IterableLike;
class	scala/collection/IterableLike
NameAndType	toCollection:(Ljava/lang/Object;)Lscala/collection/Iterable;
InterfaceMethod	scala/collection/IterableLike.toCollection:(Ljava/lang/Object;)Lscala/collection/Iterable;
NameAndType	thisCollection:()Lscala/collection/Iterable;
InterfaceMethod	scala/collection/IterableLike.thisCollection:()Lscala/collection/Iterable;
Asciz	(Lscala/collection/Iterator;)Lscala/collection/generic/Subtractable;;
Asciz	scala/collection/mutable/SetLike;
class	scala/collection/mutable/SetLike
NameAndType	$minus$minus:(Lscala/collection/Iterator;)Lscala/collection/mutable/Set;
InterfaceMethod	scala/collection/mutable/SetLike.$minus$minus:(Lscala/collection/Iterator;)Lscala/collection/mutable/Set;
Asciz	(Lscala/collection/Traversable;)Lscala/collection/generic/Subtractable;;
NameAndType	$minus$minus:(Lscala/collection/Traversable;)Lscala/collection/mutable/Set;
InterfaceMethod	scala/collection/mutable/SetLike.$minus$minus:(Lscala/collection/Traversable;)Lscala/collection/mutable/Set;
Asciz	(Ljava/lang/Object;Ljava/lang/Object;Lscala/collection/Seq;)Lscala/collection/generic/Subtractable;;
NameAndType	$minus:(Ljava/lang/Object;Ljava/lang/Object;Lscala/collection/Seq;)Lscala/collection/mutable/Set;
InterfaceMethod	scala/collection/mutable/SetLike.$minus:(Ljava/lang/Object;Ljava/lang/Object;Lscala/collection/Seq;)Lscala/collection/mutable/Set;
Asciz	(Lscala/collection/Iterator;)Lscala/collection/generic/Addable;;
NameAndType	$plus$plus:(Lscala/collection/Iterator;)Lscala/collection/mutable/Set;
InterfaceMethod	scala/collection/mutable/SetLike.$plus$plus:(Lscala/collection/Iterator;)Lscala/collection/mutable/Set;
Asciz	(Lscala/collection/Traversable;)Lscala/collection/generic/Addable;;
NameAndType	$plus$plus:(Lscala/collection/Traversable;)Lscala/collection/mutable/Set;
InterfaceMethod	scala/collection/mutable/SetLike.$plus$plus:(Lscala/collection/Traversable;)Lscala/collection/mutable/Set;
Asciz	(Ljava/lang/Object;Ljava/lang/Object;Lscala/collection/Seq;)Lscala/collection/generic/Addable;;
NameAndType	$plus:(Ljava/lang/Object;Ljava/lang/Object;Lscala/collection/Seq;)Lscala/collection/mutable/Set;
InterfaceMethod	scala/collection/mutable/SetLike.$plus:(Ljava/lang/Object;Ljava/lang/Object;Lscala/collection/Seq;)Lscala/collection/mutable/Set;
NameAndType	result:()Lscala/collection/mutable/Set;
InterfaceMethod	scala/collection/mutable/SetLike.result:()Lscala/collection/mutable/Set;
NameAndType	clone:()Lscala/collection/mutable/Set;
InterfaceMethod	scala/collection/mutable/SetLike.clone:()Lscala/collection/mutable/Set;
Asciz	(Lscala/Function1;)Ljava/lang/Object;;
Asciz	scala/collection/TraversableProxyLike;
class	scala/collection/TraversableProxyLike
NameAndType	dropWhile:(Lscala/Function1;)Lscala/collection/Traversable;
InterfaceMethod	scala/collection/TraversableProxyLike.dropWhile:(Lscala/Function1;)Lscala/collection/Traversable;
NameAndType	takeWhile:(Lscala/Function1;)Lscala/collection/Traversable;
InterfaceMethod	scala/collection/TraversableProxyLike.takeWhile:(Lscala/Function1;)Lscala/collection/Traversable;
Asciz	(II)Ljava/lang/Object;;
NameAndType	slice:(II)Lscala/collection/Traversable;
InterfaceMethod	scala/collection/TraversableProxyLike.slice:(II)Lscala/collection/Traversable;
Asciz	(I)Ljava/lang/Object;;
NameAndType	drop:(I)Lscala/collection/Traversable;
InterfaceMethod	scala/collection/TraversableProxyLike.drop:(I)Lscala/collection/Traversable;
NameAndType	take:(I)Lscala/collection/Traversable;
InterfaceMethod	scala/collection/TraversableProxyLike.take:(I)Lscala/collection/Traversable;
NameAndType	init:()Lscala/collection/Traversable;
InterfaceMethod	scala/collection/TraversableProxyLike.init:()Lscala/collection/Traversable;
NameAndType	tail:()Lscala/collection/Traversable;
InterfaceMethod	scala/collection/TraversableProxyLike.tail:()Lscala/collection/Traversable;
NameAndType	filterNot:(Lscala/Function1;)Lscala/collection/Traversable;
InterfaceMethod	scala/collection/TraversableProxyLike.filterNot:(Lscala/Function1;)Lscala/collection/Traversable;
NameAndType	filter:(Lscala/Function1;)Lscala/collection/Traversable;
InterfaceMethod	scala/collection/TraversableProxyLike.filter:(Lscala/Function1;)Lscala/collection/Traversable;
Asciz	(II)Lscala/collection/TraversableView;;
Asciz	scala/collection/IterableProxyLike;
class	scala/collection/IterableProxyLike
NameAndType	view:(II)Lscala/collection/IterableView;
InterfaceMethod	scala/collection/IterableProxyLike.view:(II)Lscala/collection/IterableView;
Asciz	()Lscala/collection/TraversableView;;
NameAndType	view:()Lscala/collection/IterableView;
InterfaceMethod	scala/collection/IterableProxyLike.view:()Lscala/collection/IterableView;
NameAndType	dropRight:(I)Lscala/collection/Iterable;
InterfaceMethod	scala/collection/IterableProxyLike.dropRight:(I)Lscala/collection/Iterable;
NameAndType	takeRight:(I)Lscala/collection/Iterable;
InterfaceMethod	scala/collection/IterableProxyLike.takeRight:(I)Lscala/collection/Iterable;
Asciz	(Ljava/lang/Object;)Ljava/lang/Object;;
Asciz	scala/collection/SetProxyLike;
class	scala/collection/SetProxyLike
NameAndType	apply:(Ljava/lang/Object;)Z
InterfaceMethod	scala/collection/SetProxyLike.apply:(Ljava/lang/Object;)Z
Asciz	scala/runtime/BoxesRunTime;
class	scala/runtime/BoxesRunTime
Asciz	boxToBoolean;
Asciz	(Z)Ljava/lang/Boolean;;
NameAndType	boxToBoolean:(Z)Ljava/lang/Boolean;
Method	scala/runtime/BoxesRunTime.boxToBoolean:(Z)Ljava/lang/Boolean;
Asciz	v1;
Asciz	(Ljava/lang/Object;)Lscala/collection/generic/Shrinkable;;
Asciz	scala/collection/mutable/SetProxy;
class	scala/collection/mutable/SetProxy
NameAndType	$minus$eq:(Ljava/lang/Object;)Lscala/collection/mutable/SetProxy;
InterfaceMethod	scala/collection/mutable/SetProxy.$minus$eq:(Ljava/lang/Object;)Lscala/collection/mutable/SetProxy;
Asciz	(Ljava/lang/Object;)Lscala/collection/mutable/SetLike;;
Asciz	(Ljava/lang/Object;)Lscala/collection/generic/Growable;;
NameAndType	$plus$eq:(Ljava/lang/Object;)Lscala/collection/mutable/SetProxy;
InterfaceMethod	scala/collection/mutable/SetProxy.$plus$eq:(Ljava/lang/Object;)Lscala/collection/mutable/SetProxy;
Asciz	(Ljava/lang/Object;)Lscala/collection/mutable/Builder;;
Asciz	(Ljava/lang/Object;)Lscala/collection/generic/Subtractable;;
NameAndType	$minus:(Ljava/lang/Object;)Lscala/collection/mutable/SetProxy;
InterfaceMethod	scala/collection/mutable/SetProxy.$minus:(Ljava/lang/Object;)Lscala/collection/mutable/SetProxy;
Asciz	(Ljava/lang/Object;)Lscala/collection/Set;;
Asciz	(Ljava/lang/Object;)Lscala/collection/mutable/Set;;
Asciz	(Ljava/lang/Object;)Lscala/collection/generic/Addable;;
NameAndType	$plus:(Ljava/lang/Object;)Lscala/collection/mutable/SetProxy;
InterfaceMethod	scala/collection/mutable/SetProxy.$plus:(Ljava/lang/Object;)Lscala/collection/mutable/SetProxy;
Asciz	()Lscala/collection/Set;;
NameAndType	empty:()Lscala/collection/mutable/SetProxy;
InterfaceMethod	scala/collection/mutable/SetProxy.empty:()Lscala/collection/mutable/SetProxy;
Asciz	()Lscala/collection/generic/Addable;;
NameAndType	repr:()Lscala/collection/mutable/SetProxy;
InterfaceMethod	scala/collection/mutable/SetProxy.repr:()Lscala/collection/mutable/SetProxy;
Asciz	()Lscala/collection/generic/Subtractable;;
NameAndType	self:()Lscala/collection/mutable/Set;
Method	scala/collection/mutable/SetProxy$$anon$1.self:()Lscala/collection/mutable/Set;
Asciz	<init>;
Asciz	(Lscala/collection/mutable/SetProxy;)V;
NameAndType	"<init>":()V
Method	java/lang/Object."<init>":()V
Asciz	$init$;
Asciz	(Lscala/collection/TraversableLike;)V;
NameAndType	$init$:(Lscala/collection/TraversableLike;)V
Method	scala/collection/TraversableLike$class.$init$:(Lscala/collection/TraversableLike;)V
Asciz	(Lscala/collection/generic/GenericTraversableTemplate;)V;
NameAndType	$init$:(Lscala/collection/generic/GenericTraversableTemplate;)V
Method	scala/collection/generic/GenericTraversableTemplate$class.$init$:(Lscala/collection/generic/GenericTraversableTemplate;)V
Asciz	scala/collection/Traversable$class;
class	scala/collection/Traversable$class
Asciz	(Lscala/collection/Traversable;)V;
NameAndType	$init$:(Lscala/collection/Traversable;)V
Method	scala/collection/Traversable$class.$init$:(Lscala/collection/Traversable;)V
Asciz	scala/collection/mutable/Traversable$class;
class	scala/collection/mutable/Traversable$class
Asciz	(Lscala/collection/mutable/Traversable;)V;
NameAndType	$init$:(Lscala/collection/mutable/Traversable;)V
Method	scala/collection/mutable/Traversable$class.$init$:(Lscala/collection/mutable/Traversable;)V
Asciz	(Lscala/collection/IterableLike;)V;
NameAndType	$init$:(Lscala/collection/IterableLike;)V
Method	scala/collection/IterableLike$class.$init$:(Lscala/collection/IterableLike;)V
Asciz	scala/collection/Iterable$class;
class	scala/collection/Iterable$class
Asciz	(Lscala/collection/Iterable;)V;
NameAndType	$init$:(Lscala/collection/Iterable;)V
Method	scala/collection/Iterable$class.$init$:(Lscala/collection/Iterable;)V
Asciz	scala/collection/mutable/Iterable$class;
class	scala/collection/mutable/Iterable$class
Asciz	(Lscala/collection/mutable/Iterable;)V;
NameAndType	$init$:(Lscala/collection/mutable/Iterable;)V
Method	scala/collection/mutable/Iterable$class.$init$:(Lscala/collection/mutable/Iterable;)V
NameAndType	$init$:(Lscala/Function1;)V
Method	scala/Function1$class.$init$:(Lscala/Function1;)V
Asciz	scala/collection/generic/GenericSetTemplate$class;
class	scala/collection/generic/GenericSetTemplate$class
Asciz	(Lscala/collection/generic/GenericSetTemplate;)V;
NameAndType	$init$:(Lscala/collection/generic/GenericSetTemplate;)V
Method	scala/collection/generic/GenericSetTemplate$class.$init$:(Lscala/collection/generic/GenericSetTemplate;)V
Asciz	scala/collection/generic/Addable$class;
class	scala/collection/generic/Addable$class
Asciz	(Lscala/collection/generic/Addable;)V;
NameAndType	$init$:(Lscala/collection/generic/Addable;)V
Method	scala/collection/generic/Addable$class.$init$:(Lscala/collection/generic/Addable;)V
Asciz	scala/collection/generic/Subtractable$class;
class	scala/collection/generic/Subtractable$class
Asciz	(Lscala/collection/generic/Subtractable;)V;
NameAndType	$init$:(Lscala/collection/generic/Subtractable;)V
Method	scala/collection/generic/Subtractable$class.$init$:(Lscala/collection/generic/Subtractable;)V
Asciz	(Lscala/collection/SetLike;)V;
NameAndType	$init$:(Lscala/collection/SetLike;)V
Method	scala/collection/SetLike$class.$init$:(Lscala/collection/SetLike;)V
Asciz	scala/collection/Set$class;
class	scala/collection/Set$class
Asciz	(Lscala/collection/Set;)V;
NameAndType	$init$:(Lscala/collection/Set;)V
Method	scala/collection/Set$class.$init$:(Lscala/collection/Set;)V
Asciz	(Lscala/collection/generic/Growable;)V;
NameAndType	$init$:(Lscala/collection/generic/Growable;)V
Method	scala/collection/generic/Growable$class.$init$:(Lscala/collection/generic/Growable;)V
Asciz	(Lscala/collection/mutable/Builder;)V;
NameAndType	$init$:(Lscala/collection/mutable/Builder;)V
Method	scala/collection/mutable/Builder$class.$init$:(Lscala/collection/mutable/Builder;)V
Asciz	(Lscala/collection/generic/Shrinkable;)V;
NameAndType	$init$:(Lscala/collection/generic/Shrinkable;)V
Method	scala/collection/generic/Shrinkable$class.$init$:(Lscala/collection/generic/Shrinkable;)V
Asciz	scala/collection/mutable/Cloneable$class;
class	scala/collection/mutable/Cloneable$class
Asciz	(Lscala/collection/mutable/Cloneable;)V;
NameAndType	$init$:(Lscala/collection/mutable/Cloneable;)V
Method	scala/collection/mutable/Cloneable$class.$init$:(Lscala/collection/mutable/Cloneable;)V
NameAndType	$init$:(Lscala/collection/mutable/SetLike;)V
Method	scala/collection/mutable/SetLike$class.$init$:(Lscala/collection/mutable/SetLike;)V
Asciz	(Lscala/collection/mutable/Set;)V;
NameAndType	$init$:(Lscala/collection/mutable/Set;)V
Method	scala/collection/mutable/Set$class.$init$:(Lscala/collection/mutable/Set;)V
Asciz	(Lscala/Proxy;)V;
NameAndType	$init$:(Lscala/Proxy;)V
Method	scala/Proxy$class.$init$:(Lscala/Proxy;)V
Asciz	(Lscala/collection/TraversableProxyLike;)V;
NameAndType	$init$:(Lscala/collection/TraversableProxyLike;)V
Method	scala/collection/TraversableProxyLike$class.$init$:(Lscala/collection/TraversableProxyLike;)V
Asciz	(Lscala/collection/IterableProxyLike;)V;
NameAndType	$init$:(Lscala/collection/IterableProxyLike;)V
Method	scala/collection/IterableProxyLike$class.$init$:(Lscala/collection/IterableProxyLike;)V
Asciz	(Lscala/collection/SetProxyLike;)V;
NameAndType	$init$:(Lscala/collection/SetProxyLike;)V
Method	scala/collection/SetProxyLike$class.$init$:(Lscala/collection/SetProxyLike;)V
NameAndType	$init$:(Lscala/collection/mutable/SetProxy;)V
Method	scala/collection/mutable/SetProxy$class.$init$:(Lscala/collection/mutable/SetProxy;)V
NameAndType	self:()Lscala/collection/Traversable;
InterfaceMethod	scala/collection/TraversableProxyLike.self:()Lscala/collection/Traversable;
Asciz	scala/collection/generic/GenericSetTemplate;
class	scala/collection/generic/GenericSetTemplate
NameAndType	empty:()Lscala/collection/Set;
InterfaceMethod	scala/collection/generic/GenericSetTemplate.empty:()Lscala/collection/Set;
Asciz	scala/collection/mutable/Set;
class	scala/collection/mutable/Set
Asciz	$outer;
Asciz	Lscala/collection/mutable/SetProxy;;
Asciz	(Lscala/collection/mutable/SetProxy<TA;>;)V;
Asciz	Ljava/lang/Object;Lscala/collection/mutable/SetProxy<TA;>;;
Asciz	Scala;
Asciz	InnerClasses;
Asciz	$anon$1;
Asciz	scala/Predef$$less$colon$less;
class	scala/Predef$$less$colon$less
Asciz	scala/Predef;
class	scala/Predef
Asciz	$less$colon$less;
Asciz	scala/collection/TraversableLike$WithFilter;
class	scala/collection/TraversableLike$WithFilter
Asciz	scala/collection/TraversableLike;
class	scala/collection/TraversableLike
Asciz	WithFilter;

{
private final scala.collection.mutable.Set self;
  Signature: Lscala/collection/mutable/Set;
  Signature: length = 0x2
   00 05 

public scala.collection.mutable.SetProxy repr();
  Signature: ()Lscala/collection/mutable/SetProxy;
  Code:
   Stack=1, Locals=1, Args_size=1
	aload_0
	invokestatic	Method scala/collection/mutable/SetProxy$class.repr:(Lscala/collection/mutable/SetProxy;)Lscala/collection/mutable/SetProxy;
	areturn
  Labels:

public scala.collection.mutable.SetProxy empty();
  Signature: ()Lscala/collection/mutable/SetProxy;
  Code:
   Stack=1, Locals=1, Args_size=1
	aload_0
	invokestatic	Method scala/collection/mutable/SetProxy$class.empty:(Lscala/collection/mutable/SetProxy;)Lscala/collection/mutable/SetProxy;
	areturn
  Labels:

public scala.collection.mutable.SetProxy $plus(java.lang.Object);
  Signature: (Ljava/lang/Object;)Lscala/collection/mutable/SetProxy;
  Code:
   Stack=2, Locals=2, Args_size=2
	aload_0
	aload_1
	invokestatic	Method scala/collection/mutable/SetProxy$class.$plus:(Lscala/collection/mutable/SetProxy;Ljava/lang/Object;)Lscala/collection/mutable/SetProxy;
	areturn
  Labels:
  LocalVariableTable: 
   Start  Length  Slot  Name   Signature
   0      6      0    this       Lscala/collection/mutable/SetProxy$$anon$1;
   0      6      1    elem       Ljava/lang/Object;


public scala.collection.mutable.SetProxy $minus(java.lang.Object);
  Signature: (Ljava/lang/Object;)Lscala/collection/mutable/SetProxy;
  Code:
   Stack=2, Locals=2, Args_size=2
	aload_0
	aload_1
	invokestatic	Method scala/collection/mutable/SetProxy$class.$minus:(Lscala/collection/mutable/SetProxy;Ljava/lang/Object;)Lscala/collection/mutable/SetProxy;
	areturn
  Labels:
  LocalVariableTable: 
   Start  Length  Slot  Name   Signature
   0      6      0    this       Lscala/collection/mutable/SetProxy$$anon$1;
   0      6      1    elem       Ljava/lang/Object;


public scala.collection.mutable.SetProxy $plus$eq(java.lang.Object);
  Signature: (Ljava/lang/Object;)Lscala/collection/mutable/SetProxy;
  Code:
   Stack=2, Locals=2, Args_size=2
	aload_0
	aload_1
	invokestatic	Method scala/collection/mutable/SetProxy$class.$plus$eq:(Lscala/collection/mutable/SetProxy;Ljava/lang/Object;)Lscala/collection/mutable/SetProxy;
	areturn
  Labels:
  LocalVariableTable: 
   Start  Length  Slot  Name   Signature
   0      6      0    this       Lscala/collection/mutable/SetProxy$$anon$1;
   0      6      1    elem       Ljava/lang/Object;


public scala.collection.mutable.SetProxy $minus$eq(java.lang.Object);
  Signature: (Ljava/lang/Object;)Lscala/collection/mutable/SetProxy;
  Code:
   Stack=2, Locals=2, Args_size=2
	aload_0
	aload_1
	invokestatic	Method scala/collection/mutable/SetProxy$class.$minus$eq:(Lscala/collection/mutable/SetProxy;Ljava/lang/Object;)Lscala/collection/mutable/SetProxy;
	areturn
  Labels:
  LocalVariableTable: 
   Start  Length  Slot  Name   Signature
   0      6      0    this       Lscala/collection/mutable/SetProxy$$anon$1;
   0      6      1    elem       Ljava/lang/Object;


public boolean contains(java.lang.Object);
  Signature: (Ljava/lang/Object;)Z
  Code:
   Stack=2, Locals=2, Args_size=2
	aload_0
	aload_1
	invokestatic	Method scala/collection/SetProxyLike$class.contains:(Lscala/collection/SetProxyLike;Ljava/lang/Object;)Z
	ireturn
  Labels:
  LocalVariableTable: 
   Start  Length  Slot  Name   Signature
   0      6      0    this       Lscala/collection/mutable/SetProxy$$anon$1;
   0      6      1    elem       Ljava/lang/Object;


public boolean isEmpty();
  Signature: ()Z
  Code:
   Stack=1, Locals=1, Args_size=1
	aload_0
	invokestatic	Method scala/collection/SetProxyLike$class.isEmpty:(Lscala/collection/SetProxyLike;)Z
	ireturn
  Labels:

public boolean apply(java.lang.Object);
  Signature: (Ljava/lang/Object;)Z
  Code:
   Stack=2, Locals=2, Args_size=2
	aload_0
	aload_1
	invokestatic	Method scala/collection/SetProxyLike$class.apply:(Lscala/collection/SetProxyLike;Ljava/lang/Object;)Z
	ireturn
  Labels:
  LocalVariableTable: 
   Start  Length  Slot  Name   Signature
   0      6      0    this       Lscala/collection/mutable/SetProxy$$anon$1;
   0      6      1    elem       Ljava/lang/Object;


public scala.collection.Set intersect(scala.collection.Set);
  Signature: (Lscala/collection/Set;)Lscala/collection/Set;
  Code:
   Stack=2, Locals=2, Args_size=2
	aload_0
	aload_1
	invokestatic	Method scala/collection/SetProxyLike$class.intersect:(Lscala/collection/SetProxyLike;Lscala/collection/Set;)Lscala/collection/Set;
	areturn
  Labels:
  LocalVariableTable: 
   Start  Length  Slot  Name   Signature
   0      6      0    this       Lscala/collection/mutable/SetProxy$$anon$1;
   0      6      1    that       Lscala/collection/Set;


public scala.collection.Set $amp(scala.collection.Set);
  Signature: (Lscala/collection/Set;)Lscala/collection/Set;
  Code:
   Stack=2, Locals=2, Args_size=2
	aload_0
	aload_1
	invokestatic	Method scala/collection/SetProxyLike$class.$amp:(Lscala/collection/SetProxyLike;Lscala/collection/Set;)Lscala/collection/Set;
	areturn
  Labels:
  LocalVariableTable: 
   Start  Length  Slot  Name   Signature
   0      6      0    this       Lscala/collection/mutable/SetProxy$$anon$1;
   0      6      1    that       Lscala/collection/Set;


public scala.collection.Set union(scala.collection.Set);
  Signature: (Lscala/collection/Set;)Lscala/collection/Set;
  Code:
   Stack=2, Locals=2, Args_size=2
	aload_0
	aload_1
	invokestatic	Method scala/collection/SetProxyLike$class.union:(Lscala/collection/SetProxyLike;Lscala/collection/Set;)Lscala/collection/Set;
	areturn
  Labels:
  LocalVariableTable: 
   Start  Length  Slot  Name   Signature
   0      6      0    this       Lscala/collection/mutable/SetProxy$$anon$1;
   0      6      1    that       Lscala/collection/Set;


public scala.collection.Set $bar(scala.collection.Set);
  Signature: (Lscala/collection/Set;)Lscala/collection/Set;
  Code:
   Stack=2, Locals=2, Args_size=2
	aload_0
	aload_1
	invokestatic	Method scala/collection/SetProxyLike$class.$bar:(Lscala/collection/SetProxyLike;Lscala/collection/Set;)Lscala/collection/Set;
	areturn
  Labels:
  LocalVariableTable: 
   Start  Length  Slot  Name   Signature
   0      6      0    this       Lscala/collection/mutable/SetProxy$$anon$1;
   0      6      1    that       Lscala/collection/Set;


public scala.collection.Set diff(scala.collection.Set);
  Signature: (Lscala/collection/Set;)Lscala/collection/Set;
  Code:
   Stack=2, Locals=2, Args_size=2
	aload_0
	aload_1
	invokestatic	Method scala/collection/SetProxyLike$class.diff:(Lscala/collection/SetProxyLike;Lscala/collection/Set;)Lscala/collection/Set;
	areturn
  Labels:
  LocalVariableTable: 
   Start  Length  Slot  Name   Signature
   0      6      0    this       Lscala/collection/mutable/SetProxy$$anon$1;
   0      6      1    that       Lscala/collection/Set;


public scala.collection.Set $amp$tilde(scala.collection.Set);
  Signature: (Lscala/collection/Set;)Lscala/collection/Set;
  Code:
   Stack=2, Locals=2, Args_size=2
	aload_0
	aload_1
	invokestatic	Method scala/collection/SetProxyLike$class.$amp$tilde:(Lscala/collection/SetProxyLike;Lscala/collection/Set;)Lscala/collection/Set;
	areturn
  Labels:
  LocalVariableTable: 
   Start  Length  Slot  Name   Signature
   0      6      0    this       Lscala/collection/mutable/SetProxy$$anon$1;
   0      6      1    that       Lscala/collection/Set;


public boolean subsetOf(scala.collection.Set);
  Signature: (Lscala/collection/Set;)Z
  Code:
   Stack=2, Locals=2, Args_size=2
	aload_0
	aload_1
	invokestatic	Method scala/collection/SetProxyLike$class.subsetOf:(Lscala/collection/SetProxyLike;Lscala/collection/Set;)Z
	ireturn
  Labels:
  LocalVariableTable: 
   Start  Length  Slot  Name   Signature
   0      6      0    this       Lscala/collection/mutable/SetProxy$$anon$1;
   0      6      1    that       Lscala/collection/Set;


public scala.collection.Iterator iterator();
  Signature: ()Lscala/collection/Iterator;
  Code:
   Stack=1, Locals=1, Args_size=1
	aload_0
	invokestatic	Method scala/collection/IterableProxyLike$class.iterator:(Lscala/collection/IterableProxyLike;)Lscala/collection/Iterator;
	areturn
  Labels:

public scala.collection.Iterator grouped(int);
  Signature: (I)Lscala/collection/Iterator;
  Code:
   Stack=2, Locals=2, Args_size=2
	aload_0
	iload_1
	invokestatic	Method scala/collection/IterableProxyLike$class.grouped:(Lscala/collection/IterableProxyLike;I)Lscala/collection/Iterator;
	areturn
  Labels:
  LocalVariableTable: 
   Start  Length  Slot  Name   Signature
   0      6      0    this       Lscala/collection/mutable/SetProxy$$anon$1;
   0      6      1    size       I


public scala.collection.Iterator sliding(int);
  Signature: (I)Lscala/collection/Iterator;
  Code:
   Stack=2, Locals=2, Args_size=2
	aload_0
	iload_1
	invokestatic	Method scala/collection/IterableProxyLike$class.sliding:(Lscala/collection/IterableProxyLike;I)Lscala/collection/Iterator;
	areturn
  Labels:
  LocalVariableTable: 
   Start  Length  Slot  Name   Signature
   0      6      0    this       Lscala/collection/mutable/SetProxy$$anon$1;
   0      6      1    size       I


public scala.collection.Iterator sliding(int, int);
  Signature: (II)Lscala/collection/Iterator;
  Code:
   Stack=3, Locals=3, Args_size=3
	aload_0
	iload_1
	iload_2
	invokestatic	Method scala/collection/IterableProxyLike$class.sliding:(Lscala/collection/IterableProxyLike;II)Lscala/collection/Iterator;
	areturn
  Labels:
  LocalVariableTable: 
   Start  Length  Slot  Name   Signature
   0      7      0    this       Lscala/collection/mutable/SetProxy$$anon$1;
   0      7      1    size       I
   0      7      2    step       I


public scala.collection.Iterable takeRight(int);
  Signature: (I)Lscala/collection/Iterable;
  Code:
   Stack=2, Locals=2, Args_size=2
	aload_0
	iload_1
	invokestatic	Method scala/collection/IterableProxyLike$class.takeRight:(Lscala/collection/IterableProxyLike;I)Lscala/collection/Iterable;
	areturn
  Labels:
  LocalVariableTable: 
   Start  Length  Slot  Name   Signature
   0      6      0    this       Lscala/collection/mutable/SetProxy$$anon$1;
   0      6      1    n       I


public scala.collection.Iterable dropRight(int);
  Signature: (I)Lscala/collection/Iterable;
  Code:
   Stack=2, Locals=2, Args_size=2
	aload_0
	iload_1
	invokestatic	Method scala/collection/IterableProxyLike$class.dropRight:(Lscala/collection/IterableProxyLike;I)Lscala/collection/Iterable;
	areturn
  Labels:
  LocalVariableTable: 
   Start  Length  Slot  Name   Signature
   0      6      0    this       Lscala/collection/mutable/SetProxy$$anon$1;
   0      6      1    n       I


public java.lang.Object zip(scala.collection.Iterable, scala.collection.generic.CanBuildFrom);
  Signature: (Lscala/collection/Iterable;Lscala/collection/generic/CanBuildFrom;)Ljava/lang/Object;
  Code:
   Stack=3, Locals=3, Args_size=3
	aload_0
	aload_1
	aload_2
	invokestatic	Method scala/collection/IterableProxyLike$class.zip:(Lscala/collection/IterableProxyLike;Lscala/collection/Iterable;Lscala/collection/generic/CanBuildFrom;)Ljava/lang/Object;
	areturn
  Labels:
  LocalVariableTable: 
   Start  Length  Slot  Name   Signature
   0      7      0    this       Lscala/collection/mutable/SetProxy$$anon$1;
   0      7      1    that       Lscala/collection/Iterable;
   0      7      2    bf       Lscala/collection/generic/CanBuildFrom;


public java.lang.Object zipAll(scala.collection.Iterable, java.lang.Object, java.lang.Object, scala.collection.generic.CanBuildFrom);
  Signature: (Lscala/collection/Iterable;Ljava/lang/Object;Ljava/lang/Object;Lscala/collection/generic/CanBuildFrom;)Ljava/lang/Object;
  Code:
   Stack=5, Locals=5, Args_size=5
	aload_0
	aload_1
	aload_2
	aload_3
	aload	4
	invokestatic	Method scala/collection/IterableProxyLike$class.zipAll:(Lscala/collection/IterableProxyLike;Lscala/collection/Iterable;Ljava/lang/Object;Ljava/lang/Object;Lscala/collection/generic/CanBuildFrom;)Ljava/lang/Object;
	areturn
  Labels:
  LocalVariableTable: 
   Start  Length  Slot  Name   Signature
   0      10      0    this       Lscala/collection/mutable/SetProxy$$anon$1;
   0      10      1    that       Lscala/collection/Iterable;
   0      10      2    thisElem       Ljava/lang/Object;
   0      10      3    thatElem       Ljava/lang/Object;
   0      10      4    bf       Lscala/collection/generic/CanBuildFrom;


public java.lang.Object zipWithIndex(scala.collection.generic.CanBuildFrom);
  Signature: (Lscala/collection/generic/CanBuildFrom;)Ljava/lang/Object;
  Code:
   Stack=2, Locals=2, Args_size=2
	aload_0
	aload_1
	invokestatic	Method scala/collection/IterableProxyLike$class.zipWithIndex:(Lscala/collection/IterableProxyLike;Lscala/collection/generic/CanBuildFrom;)Ljava/lang/Object;
	areturn
  Labels:
  LocalVariableTable: 
   Start  Length  Slot  Name   Signature
   0      6      0    this       Lscala/collection/mutable/SetProxy$$anon$1;
   0      6      1    bf       Lscala/collection/generic/CanBuildFrom;


public boolean sameElements(scala.collection.Iterable);
  Signature: (Lscala/collection/Iterable;)Z
  Code:
   Stack=2, Locals=2, Args_size=2
	aload_0
	aload_1
	invokestatic	Method scala/collection/IterableProxyLike$class.sameElements:(Lscala/collection/IterableProxyLike;Lscala/collection/Iterable;)Z
	ireturn
  Labels:
  LocalVariableTable: 
   Start  Length  Slot  Name   Signature
   0      6      0    this       Lscala/collection/mutable/SetProxy$$anon$1;
   0      6      1    that       Lscala/collection/Iterable;


public scala.collection.IterableView view();
  Signature: ()Lscala/collection/IterableView;
  Code:
   Stack=1, Locals=1, Args_size=1
	aload_0
	invokestatic	Method scala/collection/IterableProxyLike$class.view:(Lscala/collection/IterableProxyLike;)Lscala/collection/IterableView;
	areturn
  Labels:

public scala.collection.IterableView view(int, int);
  Signature: (II)Lscala/collection/IterableView;
  Code:
   Stack=3, Locals=3, Args_size=3
	aload_0
	iload_1
	iload_2
	invokestatic	Method scala/collection/IterableProxyLike$class.view:(Lscala/collection/IterableProxyLike;II)Lscala/collection/IterableView;
	areturn
  Labels:
  LocalVariableTable: 
   Start  Length  Slot  Name   Signature
   0      7      0    this       Lscala/collection/mutable/SetProxy$$anon$1;
   0      7      1    from       I
   0      7      2    until       I


public void foreach(scala.Function1);
  Signature: (Lscala/Function1;)V
  Code:
   Stack=2, Locals=2, Args_size=2
	aload_0
	aload_1
	invokestatic	Method scala/collection/TraversableProxyLike$class.foreach:(Lscala/collection/TraversableProxyLike;Lscala/Function1;)V
	return
  Labels:
  LocalVariableTable: 
   Start  Length  Slot  Name   Signature
   0      6      0    this       Lscala/collection/mutable/SetProxy$$anon$1;
   0      6      1    f       Lscala/Function1;


public boolean nonEmpty();
  Signature: ()Z
  Code:
   Stack=1, Locals=1, Args_size=1
	aload_0
	invokestatic	Method scala/collection/TraversableProxyLike$class.nonEmpty:(Lscala/collection/TraversableProxyLike;)Z
	ireturn
  Labels:

public int size();
  Signature: ()I
  Code:
   Stack=1, Locals=1, Args_size=1
	aload_0
	invokestatic	Method scala/collection/TraversableProxyLike$class.size:(Lscala/collection/TraversableProxyLike;)I
	ireturn
  Labels:

public boolean hasDefiniteSize();
  Signature: ()Z
  Code:
   Stack=1, Locals=1, Args_size=1
	aload_0
	invokestatic	Method scala/collection/TraversableProxyLike$class.hasDefiniteSize:(Lscala/collection/TraversableProxyLike;)Z
	ireturn
  Labels:

public java.lang.Object $plus$plus(scala.collection.Traversable, scala.collection.generic.CanBuildFrom);
  Signature: (Lscala/collection/Traversable;Lscala/collection/generic/CanBuildFrom;)Ljava/lang/Object;
  Code:
   Stack=3, Locals=3, Args_size=3
	aload_0
	aload_1
	aload_2
	invokestatic	Method scala/collection/TraversableProxyLike$class.$plus$plus:(Lscala/collection/TraversableProxyLike;Lscala/collection/Traversable;Lscala/collection/generic/CanBuildFrom;)Ljava/lang/Object;
	areturn
  Labels:
  LocalVariableTable: 
   Start  Length  Slot  Name   Signature
   0      7      0    this       Lscala/collection/mutable/SetProxy$$anon$1;
   0      7      1    that       Lscala/collection/Traversable;
   0      7      2    bf       Lscala/collection/generic/CanBuildFrom;


public java.lang.Object $plus$plus(scala.collection.Iterator, scala.collection.generic.CanBuildFrom);
  Signature: (Lscala/collection/Iterator;Lscala/collection/generic/CanBuildFrom;)Ljava/lang/Object;
  Code:
   Stack=3, Locals=3, Args_size=3
	aload_0
	aload_1
	aload_2
	invokestatic	Method scala/collection/TraversableProxyLike$class.$plus$plus:(Lscala/collection/TraversableProxyLike;Lscala/collection/Iterator;Lscala/collection/generic/CanBuildFrom;)Ljava/lang/Object;
	areturn
  Labels:
  LocalVariableTable: 
   Start  Length  Slot  Name   Signature
   0      7      0    this       Lscala/collection/mutable/SetProxy$$anon$1;
   0      7      1    that       Lscala/collection/Iterator;
   0      7      2    bf       Lscala/collection/generic/CanBuildFrom;


public java.lang.Object map(scala.Function1, scala.collection.generic.CanBuildFrom);
  Signature: (Lscala/Function1;Lscala/collection/generic/CanBuildFrom;)Ljava/lang/Object;
  Code:
   Stack=3, Locals=3, Args_size=3
	aload_0
	aload_1
	aload_2
	invokestatic	Method scala/collection/TraversableProxyLike$class.map:(Lscala/collection/TraversableProxyLike;Lscala/Function1;Lscala/collection/generic/CanBuildFrom;)Ljava/lang/Object;
	areturn
  Labels:
  LocalVariableTable: 
   Start  Length  Slot  Name   Signature
   0      7      0    this       Lscala/collection/mutable/SetProxy$$anon$1;
   0      7      1    f       Lscala/Function1;
   0      7      2    bf       Lscala/collection/generic/CanBuildFrom;


public java.lang.Object flatMap(scala.Function1, scala.collection.generic.CanBuildFrom);
  Signature: (Lscala/Function1;Lscala/collection/generic/CanBuildFrom;)Ljava/lang/Object;
  Code:
   Stack=3, Locals=3, Args_size=3
	aload_0
	aload_1
	aload_2
	invokestatic	Method scala/collection/TraversableProxyLike$class.flatMap:(Lscala/collection/TraversableProxyLike;Lscala/Function1;Lscala/collection/generic/CanBuildFrom;)Ljava/lang/Object;
	areturn
  Labels:
  LocalVariableTable: 
   Start  Length  Slot  Name   Signature
   0      7      0    this       Lscala/collection/mutable/SetProxy$$anon$1;
   0      7      1    f       Lscala/Function1;
   0      7      2    bf       Lscala/collection/generic/CanBuildFrom;


public scala.collection.Traversable filter(scala.Function1);
  Signature: (Lscala/Function1;)Lscala/collection/Traversable;
  Code:
   Stack=2, Locals=2, Args_size=2
	aload_0
	aload_1
	invokestatic	Method scala/collection/TraversableProxyLike$class.filter:(Lscala/collection/TraversableProxyLike;Lscala/Function1;)Lscala/collection/Traversable;
	areturn
  Labels:
  LocalVariableTable: 
   Start  Length  Slot  Name   Signature
   0      6      0    this       Lscala/collection/mutable/SetProxy$$anon$1;
   0      6      1    p       Lscala/Function1;


public scala.collection.Traversable filterNot(scala.Function1);
  Signature: (Lscala/Function1;)Lscala/collection/Traversable;
  Code:
   Stack=2, Locals=2, Args_size=2
	aload_0
	aload_1
	invokestatic	Method scala/collection/TraversableProxyLike$class.filterNot:(Lscala/collection/TraversableProxyLike;Lscala/Function1;)Lscala/collection/Traversable;
	areturn
  Labels:
  LocalVariableTable: 
   Start  Length  Slot  Name   Signature
   0      6      0    this       Lscala/collection/mutable/SetProxy$$anon$1;
   0      6      1    p       Lscala/Function1;


public java.lang.Object partialMap(scala.PartialFunction, scala.collection.generic.CanBuildFrom);
  Signature: (Lscala/PartialFunction;Lscala/collection/generic/CanBuildFrom;)Ljava/lang/Object;
  Code:
   Stack=3, Locals=3, Args_size=3
	aload_0
	aload_1
	aload_2
	invokestatic	Method scala/collection/TraversableProxyLike$class.partialMap:(Lscala/collection/TraversableProxyLike;Lscala/PartialFunction;Lscala/collection/generic/CanBuildFrom;)Ljava/lang/Object;
	areturn
  Labels:
  LocalVariableTable: 
   Start  Length  Slot  Name   Signature
   0      7      0    this       Lscala/collection/mutable/SetProxy$$anon$1;
   0      7      1    pf       Lscala/PartialFunction;
   0      7      2    bf       Lscala/collection/generic/CanBuildFrom;


public scala.Tuple2 partition(scala.Function1);
  Signature: (Lscala/Function1;)Lscala/Tuple2;
  Code:
   Stack=2, Locals=2, Args_size=2
	aload_0
	aload_1
	invokestatic	Method scala/collection/TraversableProxyLike$class.partition:(Lscala/collection/TraversableProxyLike;Lscala/Function1;)Lscala/Tuple2;
	areturn
  Labels:
  LocalVariableTable: 
   Start  Length  Slot  Name   Signature
   0      6      0    this       Lscala/collection/mutable/SetProxy$$anon$1;
   0      6      1    p       Lscala/Function1;


public scala.collection.Map groupBy(scala.Function1);
  Signature: (Lscala/Function1;)Lscala/collection/Map;
  Code:
   Stack=2, Locals=2, Args_size=2
	aload_0
	aload_1
	invokestatic	Method scala/collection/TraversableProxyLike$class.groupBy:(Lscala/collection/TraversableProxyLike;Lscala/Function1;)Lscala/collection/Map;
	areturn
  Labels:
  LocalVariableTable: 
   Start  Length  Slot  Name   Signature
   0      6      0    this       Lscala/collection/mutable/SetProxy$$anon$1;
   0      6      1    f       Lscala/Function1;


public boolean forall(scala.Function1);
  Signature: (Lscala/Function1;)Z
  Code:
   Stack=2, Locals=2, Args_size=2
	aload_0
	aload_1
	invokestatic	Method scala/collection/TraversableProxyLike$class.forall:(Lscala/collection/TraversableProxyLike;Lscala/Function1;)Z
	ireturn
  Labels:
  LocalVariableTable: 
   Start  Length  Slot  Name   Signature
   0      6      0    this       Lscala/collection/mutable/SetProxy$$anon$1;
   0      6      1    p       Lscala/Function1;


public boolean exists(scala.Function1);
  Signature: (Lscala/Function1;)Z
  Code:
   Stack=2, Locals=2, Args_size=2
	aload_0
	aload_1
	invokestatic	Method scala/collection/TraversableProxyLike$class.exists:(Lscala/collection/TraversableProxyLike;Lscala/Function1;)Z
	ireturn
  Labels:
  LocalVariableTable: 
   Start  Length  Slot  Name   Signature
   0      6      0    this       Lscala/collection/mutable/SetProxy$$anon$1;
   0      6      1    p       Lscala/Function1;


public int count(scala.Function1);
  Signature: (Lscala/Function1;)I
  Code:
   Stack=2, Locals=2, Args_size=2
	aload_0
	aload_1
	invokestatic	Method scala/collection/TraversableProxyLike$class.count:(Lscala/collection/TraversableProxyLike;Lscala/Function1;)I
	ireturn
  Labels:
  LocalVariableTable: 
   Start  Length  Slot  Name   Signature
   0      6      0    this       Lscala/collection/mutable/SetProxy$$anon$1;
   0      6      1    p       Lscala/Function1;


public scala.Option find(scala.Function1);
  Signature: (Lscala/Function1;)Lscala/Option;
  Code:
   Stack=2, Locals=2, Args_size=2
	aload_0
	aload_1
	invokestatic	Method scala/collection/TraversableProxyLike$class.find:(Lscala/collection/TraversableProxyLike;Lscala/Function1;)Lscala/Option;
	areturn
  Labels:
  LocalVariableTable: 
   Start  Length  Slot  Name   Signature
   0      6      0    this       Lscala/collection/mutable/SetProxy$$anon$1;
   0      6      1    p       Lscala/Function1;


public java.lang.Object foldLeft(java.lang.Object, scala.Function2);
  Signature: (Ljava/lang/Object;Lscala/Function2;)Ljava/lang/Object;
  Code:
   Stack=3, Locals=3, Args_size=3
	aload_0
	aload_1
	aload_2
	invokestatic	Method scala/collection/TraversableProxyLike$class.foldLeft:(Lscala/collection/TraversableProxyLike;Ljava/lang/Object;Lscala/Function2;)Ljava/lang/Object;
	areturn
  Labels:
  LocalVariableTable: 
   Start  Length  Slot  Name   Signature
   0      7      0    this       Lscala/collection/mutable/SetProxy$$anon$1;
   0      7      1    z       Ljava/lang/Object;
   0      7      2    op       Lscala/Function2;


public java.lang.Object $div$colon(java.lang.Object, scala.Function2);
  Signature: (Ljava/lang/Object;Lscala/Function2;)Ljava/lang/Object;
  Code:
   Stack=3, Locals=3, Args_size=3
	aload_0
	aload_1
	aload_2
	invokestatic	Method scala/collection/TraversableProxyLike$class.$div$colon:(Lscala/collection/TraversableProxyLike;Ljava/lang/Object;Lscala/Function2;)Ljava/lang/Object;
	areturn
  Labels:
  LocalVariableTable: 
   Start  Length  Slot  Name   Signature
   0      7      0    this       Lscala/collection/mutable/SetProxy$$anon$1;
   0      7      1    z       Ljava/lang/Object;
   0      7      2    op       Lscala/Function2;


public java.lang.Object foldRight(java.lang.Object, scala.Function2);
  Signature: (Ljava/lang/Object;Lscala/Function2;)Ljava/lang/Object;
  Code:
   Stack=3, Locals=3, Args_size=3
	aload_0
	aload_1
	aload_2
	invokestatic	Method scala/collection/TraversableProxyLike$class.foldRight:(Lscala/collection/TraversableProxyLike;Ljava/lang/Object;Lscala/Function2;)Ljava/lang/Object;
	areturn
  Labels:
  LocalVariableTable: 
   Start  Length  Slot  Name   Signature
   0      7      0    this       Lscala/collection/mutable/SetProxy$$anon$1;
   0      7      1    z       Ljava/lang/Object;
   0      7      2    op       Lscala/Function2;


public java.lang.Object $colon$bslash(java.lang.Object, scala.Function2);
  Signature: (Ljava/lang/Object;Lscala/Function2;)Ljava/lang/Object;
  Code:
   Stack=3, Locals=3, Args_size=3
	aload_0
	aload_1
	aload_2
	invokestatic	Method scala/collection/TraversableProxyLike$class.$colon$bslash:(Lscala/collection/TraversableProxyLike;Ljava/lang/Object;Lscala/Function2;)Ljava/lang/Object;
	areturn
  Labels:
  LocalVariableTable: 
   Start  Length  Slot  Name   Signature
   0      7      0    this       Lscala/collection/mutable/SetProxy$$anon$1;
   0      7      1    z       Ljava/lang/Object;
   0      7      2    op       Lscala/Function2;


public java.lang.Object reduceLeft(scala.Function2);
  Signature: (Lscala/Function2;)Ljava/lang/Object;
  Code:
   Stack=2, Locals=2, Args_size=2
	aload_0
	aload_1
	invokestatic	Method scala/collection/TraversableProxyLike$class.reduceLeft:(Lscala/collection/TraversableProxyLike;Lscala/Function2;)Ljava/lang/Object;
	areturn
  Labels:
  LocalVariableTable: 
   Start  Length  Slot  Name   Signature
   0      6      0    this       Lscala/collection/mutable/SetProxy$$anon$1;
   0      6      1    op       Lscala/Function2;


public scala.Option reduceLeftOption(scala.Function2);
  Signature: (Lscala/Function2;)Lscala/Option;
  Code:
   Stack=2, Locals=2, Args_size=2
	aload_0
	aload_1
	invokestatic	Method scala/collection/TraversableProxyLike$class.reduceLeftOption:(Lscala/collection/TraversableProxyLike;Lscala/Function2;)Lscala/Option;
	areturn
  Labels:
  LocalVariableTable: 
   Start  Length  Slot  Name   Signature
   0      6      0    this       Lscala/collection/mutable/SetProxy$$anon$1;
   0      6      1    op       Lscala/Function2;


public java.lang.Object reduceRight(scala.Function2);
  Signature: (Lscala/Function2;)Ljava/lang/Object;
  Code:
   Stack=2, Locals=2, Args_size=2
	aload_0
	aload_1
	invokestatic	Method scala/collection/TraversableProxyLike$class.reduceRight:(Lscala/collection/TraversableProxyLike;Lscala/Function2;)Ljava/lang/Object;
	areturn
  Labels:
  LocalVariableTable: 
   Start  Length  Slot  Name   Signature
   0      6      0    this       Lscala/collection/mutable/SetProxy$$anon$1;
   0      6      1    op       Lscala/Function2;


public scala.Option reduceRightOption(scala.Function2);
  Signature: (Lscala/Function2;)Lscala/Option;
  Code:
   Stack=2, Locals=2, Args_size=2
	aload_0
	aload_1
	invokestatic	Method scala/collection/TraversableProxyLike$class.reduceRightOption:(Lscala/collection/TraversableProxyLike;Lscala/Function2;)Lscala/Option;
	areturn
  Labels:
  LocalVariableTable: 
   Start  Length  Slot  Name   Signature
   0      6      0    this       Lscala/collection/mutable/SetProxy$$anon$1;
   0      6      1    op       Lscala/Function2;


public java.lang.Object scanLeft(java.lang.Object, scala.Function2, scala.collection.generic.CanBuildFrom);
  Signature: (Ljava/lang/Object;Lscala/Function2;Lscala/collection/generic/CanBuildFrom;)Ljava/lang/Object;
  Code:
   Stack=4, Locals=4, Args_size=4
	aload_0
	aload_1
	aload_2
	aload_3
	invokestatic	Method scala/collection/TraversableProxyLike$class.scanLeft:(Lscala/collection/TraversableProxyLike;Ljava/lang/Object;Lscala/Function2;Lscala/collection/generic/CanBuildFrom;)Ljava/lang/Object;
	areturn
  Labels:
  LocalVariableTable: 
   Start  Length  Slot  Name   Signature
   0      8      0    this       Lscala/collection/mutable/SetProxy$$anon$1;
   0      8      1    z       Ljava/lang/Object;
   0      8      2    op       Lscala/Function2;
   0      8      3    bf       Lscala/collection/generic/CanBuildFrom;


public java.lang.Object scanRight(java.lang.Object, scala.Function2, scala.collection.generic.CanBuildFrom);
  Signature: (Ljava/lang/Object;Lscala/Function2;Lscala/collection/generic/CanBuildFrom;)Ljava/lang/Object;
  Code:
   Stack=4, Locals=4, Args_size=4
	aload_0
	aload_1
	aload_2
	aload_3
	invokestatic	Method scala/collection/TraversableProxyLike$class.scanRight:(Lscala/collection/TraversableProxyLike;Ljava/lang/Object;Lscala/Function2;Lscala/collection/generic/CanBuildFrom;)Ljava/lang/Object;
	areturn
  Labels:
  LocalVariableTable: 
   Start  Length  Slot  Name   Signature
   0      8      0    this       Lscala/collection/mutable/SetProxy$$anon$1;
   0      8      1    z       Ljava/lang/Object;
   0      8      2    op       Lscala/Function2;
   0      8      3    bf       Lscala/collection/generic/CanBuildFrom;


public java.lang.Object sum(scala.math.Numeric);
  Signature: (Lscala/math/Numeric;)Ljava/lang/Object;
  Code:
   Stack=2, Locals=2, Args_size=2
	aload_0
	aload_1
	invokestatic	Method scala/collection/TraversableProxyLike$class.sum:(Lscala/collection/TraversableProxyLike;Lscala/math/Numeric;)Ljava/lang/Object;
	areturn
  Labels:
  LocalVariableTable: 
   Start  Length  Slot  Name   Signature
   0      6      0    this       Lscala/collection/mutable/SetProxy$$anon$1;
   0      6      1    num       Lscala/math/Numeric;


public java.lang.Object product(scala.math.Numeric);
  Signature: (Lscala/math/Numeric;)Ljava/lang/Object;
  Code:
   Stack=2, Locals=2, Args_size=2
	aload_0
	aload_1
	invokestatic	Method scala/collection/TraversableProxyLike$class.product:(Lscala/collection/TraversableProxyLike;Lscala/math/Numeric;)Ljava/lang/Object;
	areturn
  Labels:
  LocalVariableTable: 
   Start  Length  Slot  Name   Signature
   0      6      0    this       Lscala/collection/mutable/SetProxy$$anon$1;
   0      6      1    num       Lscala/math/Numeric;


public java.lang.Object min(scala.math.Ordering);
  Signature: (Lscala/math/Ordering;)Ljava/lang/Object;
  Code:
   Stack=2, Locals=2, Args_size=2
	aload_0
	aload_1
	invokestatic	Method scala/collection/TraversableProxyLike$class.min:(Lscala/collection/TraversableProxyLike;Lscala/math/Ordering;)Ljava/lang/Object;
	areturn
  Labels:
  LocalVariableTable: 
   Start  Length  Slot  Name   Signature
   0      6      0    this       Lscala/collection/mutable/SetProxy$$anon$1;
   0      6      1    cmp       Lscala/math/Ordering;


public java.lang.Object max(scala.math.Ordering);
  Signature: (Lscala/math/Ordering;)Ljava/lang/Object;
  Code:
   Stack=2, Locals=2, Args_size=2
	aload_0
	aload_1
	invokestatic	Method scala/collection/TraversableProxyLike$class.max:(Lscala/collection/TraversableProxyLike;Lscala/math/Ordering;)Ljava/lang/Object;
	areturn
  Labels:
  LocalVariableTable: 
   Start  Length  Slot  Name   Signature
   0      6      0    this       Lscala/collection/mutable/SetProxy$$anon$1;
   0      6      1    cmp       Lscala/math/Ordering;


public java.lang.Object head();
  Signature: ()Ljava/lang/Object;
  Code:
   Stack=1, Locals=1, Args_size=1
	aload_0
	invokestatic	Method scala/collection/TraversableProxyLike$class.head:(Lscala/collection/TraversableProxyLike;)Ljava/lang/Object;
	areturn
  Labels:

public scala.Option headOption();
  Signature: ()Lscala/Option;
  Code:
   Stack=1, Locals=1, Args_size=1
	aload_0
	invokestatic	Method scala/collection/TraversableProxyLike$class.headOption:(Lscala/collection/TraversableProxyLike;)Lscala/Option;
	areturn
  Labels:

public scala.collection.Traversable tail();
  Signature: ()Lscala/collection/Traversable;
  Code:
   Stack=1, Locals=1, Args_size=1
	aload_0
	invokestatic	Method scala/collection/TraversableProxyLike$class.tail:(Lscala/collection/TraversableProxyLike;)Lscala/collection/Traversable;
	areturn
  Labels:

public java.lang.Object last();
  Signature: ()Ljava/lang/Object;
  Code:
   Stack=1, Locals=1, Args_size=1
	aload_0
	invokestatic	Method scala/collection/TraversableProxyLike$class.last:(Lscala/collection/TraversableProxyLike;)Ljava/lang/Object;
	areturn
  Labels:

public scala.Option lastOption();
  Signature: ()Lscala/Option;
  Code:
   Stack=1, Locals=1, Args_size=1
	aload_0
	invokestatic	Method scala/collection/TraversableProxyLike$class.lastOption:(Lscala/collection/TraversableProxyLike;)Lscala/Option;
	areturn
  Labels:

public scala.collection.Traversable init();
  Signature: ()Lscala/collection/Traversable;
  Code:
   Stack=1, Locals=1, Args_size=1
	aload_0
	invokestatic	Method scala/collection/TraversableProxyLike$class.init:(Lscala/collection/TraversableProxyLike;)Lscala/collection/Traversable;
	areturn
  Labels:

public scala.collection.Traversable take(int);
  Signature: (I)Lscala/collection/Traversable;
  Code:
   Stack=2, Locals=2, Args_size=2
	aload_0
	iload_1
	invokestatic	Method scala/collection/TraversableProxyLike$class.take:(Lscala/collection/TraversableProxyLike;I)Lscala/collection/Traversable;
	areturn
  Labels:
  LocalVariableTable: 
   Start  Length  Slot  Name   Signature
   0      6      0    this       Lscala/collection/mutable/SetProxy$$anon$1;
   0      6      1    n       I


public scala.collection.Traversable drop(int);
  Signature: (I)Lscala/collection/Traversable;
  Code:
   Stack=2, Locals=2, Args_size=2
	aload_0
	iload_1
	invokestatic	Method scala/collection/TraversableProxyLike$class.drop:(Lscala/collection/TraversableProxyLike;I)Lscala/collection/Traversable;
	areturn
  Labels:
  LocalVariableTable: 
   Start  Length  Slot  Name   Signature
   0      6      0    this       Lscala/collection/mutable/SetProxy$$anon$1;
   0      6      1    n       I


public scala.collection.Traversable slice(int, int);
  Signature: (II)Lscala/collection/Traversable;
  Code:
   Stack=3, Locals=3, Args_size=3
	aload_0
	iload_1
	iload_2
	invokestatic	Method scala/collection/TraversableProxyLike$class.slice:(Lscala/collection/TraversableProxyLike;II)Lscala/collection/Traversable;
	areturn
  Labels:
  LocalVariableTable: 
   Start  Length  Slot  Name   Signature
   0      7      0    this       Lscala/collection/mutable/SetProxy$$anon$1;
   0      7      1    from       I
   0      7      2    until       I


public scala.collection.Traversable takeWhile(scala.Function1);
  Signature: (Lscala/Function1;)Lscala/collection/Traversable;
  Code:
   Stack=2, Locals=2, Args_size=2
	aload_0
	aload_1
	invokestatic	Method scala/collection/TraversableProxyLike$class.takeWhile:(Lscala/collection/TraversableProxyLike;Lscala/Function1;)Lscala/collection/Traversable;
	areturn
  Labels:
  LocalVariableTable: 
   Start  Length  Slot  Name   Signature
   0      6      0    this       Lscala/collection/mutable/SetProxy$$anon$1;
   0      6      1    p       Lscala/Function1;


public scala.collection.Traversable dropWhile(scala.Function1);
  Signature: (Lscala/Function1;)Lscala/collection/Traversable;
  Code:
   Stack=2, Locals=2, Args_size=2
	aload_0
	aload_1
	invokestatic	Method scala/collection/TraversableProxyLike$class.dropWhile:(Lscala/collection/TraversableProxyLike;Lscala/Function1;)Lscala/collection/Traversable;
	areturn
  Labels:
  LocalVariableTable: 
   Start  Length  Slot  Name   Signature
   0      6      0    this       Lscala/collection/mutable/SetProxy$$anon$1;
   0      6      1    p       Lscala/Function1;


public scala.Tuple2 span(scala.Function1);
  Signature: (Lscala/Function1;)Lscala/Tuple2;
  Code:
   Stack=2, Locals=2, Args_size=2
	aload_0
	aload_1
	invokestatic	Method scala/collection/TraversableProxyLike$class.span:(Lscala/collection/TraversableProxyLike;Lscala/Function1;)Lscala/Tuple2;
	areturn
  Labels:
  LocalVariableTable: 
   Start  Length  Slot  Name   Signature
   0      6      0    this       Lscala/collection/mutable/SetProxy$$anon$1;
   0      6      1    p       Lscala/Function1;


public scala.Tuple2 splitAt(int);
  Signature: (I)Lscala/Tuple2;
  Code:
   Stack=2, Locals=2, Args_size=2
	aload_0
	iload_1
	invokestatic	Method scala/collection/TraversableProxyLike$class.splitAt:(Lscala/collection/TraversableProxyLike;I)Lscala/Tuple2;
	areturn
  Labels:
  LocalVariableTable: 
   Start  Length  Slot  Name   Signature
   0      6      0    this       Lscala/collection/mutable/SetProxy$$anon$1;
   0      6      1    n       I


public void copyToBuffer(scala.collection.mutable.Buffer);
  Signature: (Lscala/collection/mutable/Buffer;)V
  Code:
   Stack=2, Locals=2, Args_size=2
	aload_0
	aload_1
	invokestatic	Method scala/collection/TraversableProxyLike$class.copyToBuffer:(Lscala/collection/TraversableProxyLike;Lscala/collection/mutable/Buffer;)V
	return
  Labels:
  LocalVariableTable: 
   Start  Length  Slot  Name   Signature
   0      6      0    this       Lscala/collection/mutable/SetProxy$$anon$1;
   0      6      1    dest       Lscala/collection/mutable/Buffer;


public void copyToArray(java.lang.Object, int, int);
  Signature: (Ljava/lang/Object;II)V
  Code:
   Stack=4, Locals=4, Args_size=4
	aload_0
	aload_1
	iload_2
	iload_3
	invokestatic	Method scala/collection/TraversableProxyLike$class.copyToArray:(Lscala/collection/TraversableProxyLike;Ljava/lang/Object;II)V
	return
  Labels:
  LocalVariableTable: 
   Start  Length  Slot  Name   Signature
   0      8      0    this       Lscala/collection/mutable/SetProxy$$anon$1;
   0      8      1    xs       Ljava/lang/Object;
   0      8      2    start       I
   0      8      3    len       I


public void copyToArray(java.lang.Object, int);
  Signature: (Ljava/lang/Object;I)V
  Code:
   Stack=3, Locals=3, Args_size=3
	aload_0
	aload_1
	iload_2
	invokestatic	Method scala/collection/TraversableProxyLike$class.copyToArray:(Lscala/collection/TraversableProxyLike;Ljava/lang/Object;I)V
	return
  Labels:
  LocalVariableTable: 
   Start  Length  Slot  Name   Signature
   0      7      0    this       Lscala/collection/mutable/SetProxy$$anon$1;
   0      7      1    xs       Ljava/lang/Object;
   0      7      2    start       I


public void copyToArray(java.lang.Object);
  Signature: (Ljava/lang/Object;)V
  Code:
   Stack=2, Locals=2, Args_size=2
	aload_0
	aload_1
	invokestatic	Method scala/collection/TraversableProxyLike$class.copyToArray:(Lscala/collection/TraversableProxyLike;Ljava/lang/Object;)V
	return
  Labels:
  LocalVariableTable: 
   Start  Length  Slot  Name   Signature
   0      6      0    this       Lscala/collection/mutable/SetProxy$$anon$1;
   0      6      1    xs       Ljava/lang/Object;


public java.lang.Object toArray(scala.reflect.ClassManifest);
  Signature: (Lscala/reflect/ClassManifest;)Ljava/lang/Object;
  Code:
   Stack=2, Locals=2, Args_size=2
	aload_0
	aload_1
	invokestatic	Method scala/collection/TraversableProxyLike$class.toArray:(Lscala/collection/TraversableProxyLike;Lscala/reflect/ClassManifest;)Ljava/lang/Object;
	areturn
  Labels:
  LocalVariableTable: 
   Start  Length  Slot  Name   Signature
   0      6      0    this       Lscala/collection/mutable/SetProxy$$anon$1;
   0      6      1    evidence$1       Lscala/reflect/ClassManifest;


public scala.collection.immutable.List toList();
  Signature: ()Lscala/collection/immutable/List;
  Code:
   Stack=1, Locals=1, Args_size=1
	aload_0
	invokestatic	Method scala/collection/TraversableProxyLike$class.toList:(Lscala/collection/TraversableProxyLike;)Lscala/collection/immutable/List;
	areturn
  Labels:

public scala.collection.Iterable toIterable();
  Signature: ()Lscala/collection/Iterable;
  Code:
   Stack=1, Locals=1, Args_size=1
	aload_0
	invokestatic	Method scala/collection/TraversableProxyLike$class.toIterable:(Lscala/collection/TraversableProxyLike;)Lscala/collection/Iterable;
	areturn
  Labels:

public scala.collection.Seq toSeq();
  Signature: ()Lscala/collection/Seq;
  Code:
   Stack=1, Locals=1, Args_size=1
	aload_0
	invokestatic	Method scala/collection/TraversableProxyLike$class.toSeq:(Lscala/collection/TraversableProxyLike;)Lscala/collection/Seq;
	areturn
  Labels:

public scala.collection.mutable.IndexedSeq toIndexedSeq();
  Signature: ()Lscala/collection/mutable/IndexedSeq;
  Code:
   Stack=1, Locals=1, Args_size=1
	aload_0
	invokestatic	Method scala/collection/TraversableProxyLike$class.toIndexedSeq:(Lscala/collection/TraversableProxyLike;)Lscala/collection/mutable/IndexedSeq;
	areturn
  Labels:

public scala.collection.immutable.Stream toStream();
  Signature: ()Lscala/collection/immutable/Stream;
  Code:
   Stack=1, Locals=1, Args_size=1
	aload_0
	invokestatic	Method scala/collection/TraversableProxyLike$class.toStream:(Lscala/collection/TraversableProxyLike;)Lscala/collection/immutable/Stream;
	areturn
  Labels:

public scala.collection.immutable.Set toSet();
  Signature: ()Lscala/collection/immutable/Set;
  Code:
   Stack=1, Locals=1, Args_size=1
	aload_0
	invokestatic	Method scala/collection/TraversableProxyLike$class.toSet:(Lscala/collection/TraversableProxyLike;)Lscala/collection/immutable/Set;
	areturn
  Labels:

public scala.collection.immutable.Map toMap(scala.Predef$$less$colon$less);
  Signature: (Lscala/Predef$$less$colon$less;)Lscala/collection/immutable/Map;
  Code:
   Stack=2, Locals=2, Args_size=2
	aload_0
	aload_1
	invokestatic	Method scala/collection/TraversableProxyLike$class.toMap:(Lscala/collection/TraversableProxyLike;Lscala/Predef$$less$colon$less;)Lscala/collection/immutable/Map;
	areturn
  Labels:
  LocalVariableTable: 
   Start  Length  Slot  Name   Signature
   0      6      0    this       Lscala/collection/mutable/SetProxy$$anon$1;
   0      6      1    ev       Lscala/Predef$$less$colon$less;


public java.lang.String mkString(java.lang.String, java.lang.String, java.lang.String);
  Signature: (Ljava/lang/String;Ljava/lang/String;Ljava/lang/String;)Ljava/lang/String;
  Code:
   Stack=4, Locals=4, Args_size=4
	aload_0
	aload_1
	aload_2
	aload_3
	invokestatic	Method scala/collection/TraversableProxyLike$class.mkString:(Lscala/collection/TraversableProxyLike;Ljava/lang/String;Ljava/lang/String;Ljava/lang/String;)Ljava/lang/String;
	areturn
  Labels:
  LocalVariableTable: 
   Start  Length  Slot  Name   Signature
   0      8      0    this       Lscala/collection/mutable/SetProxy$$anon$1;
   0      8      1    start       Ljava/lang/String;
   0      8      2    sep       Ljava/lang/String;
   0      8      3    end       Ljava/lang/String;


public java.lang.String mkString(java.lang.String);
  Signature: (Ljava/lang/String;)Ljava/lang/String;
  Code:
   Stack=2, Locals=2, Args_size=2
	aload_0
	aload_1
	invokestatic	Method scala/collection/TraversableProxyLike$class.mkString:(Lscala/collection/TraversableProxyLike;Ljava/lang/String;)Ljava/lang/String;
	areturn
  Labels:
  LocalVariableTable: 
   Start  Length  Slot  Name   Signature
   0      6      0    this       Lscala/collection/mutable/SetProxy$$anon$1;
   0      6      1    sep       Ljava/lang/String;


public java.lang.String mkString();
  Signature: ()Ljava/lang/String;
  Code:
   Stack=1, Locals=1, Args_size=1
	aload_0
	invokestatic	Method scala/collection/TraversableProxyLike$class.mkString:(Lscala/collection/TraversableProxyLike;)Ljava/lang/String;
	areturn
  Labels:

public scala.collection.mutable.StringBuilder addString(scala.collection.mutable.StringBuilder, java.lang.String, java.lang.String, java.lang.String);
  Signature: (Lscala/collection/mutable/StringBuilder;Ljava/lang/String;Ljava/lang/String;Ljava/lang/String;)Lscala/collection/mutable/StringBuilder;
  Code:
   Stack=5, Locals=5, Args_size=5
	aload_0
	aload_1
	aload_2
	aload_3
	aload	4
	invokestatic	Method scala/collection/TraversableProxyLike$class.addString:(Lscala/collection/TraversableProxyLike;Lscala/collection/mutable/StringBuilder;Ljava/lang/String;Ljava/lang/String;Ljava/lang/String;)Lscala/collection/mutable/StringBuilder;
	areturn
  Labels:
  LocalVariableTable: 
   Start  Length  Slot  Name   Signature
   0      10      0    this       Lscala/collection/mutable/SetProxy$$anon$1;
   0      10      1    b       Lscala/collection/mutable/StringBuilder;
   0      10      2    start       Ljava/lang/String;
   0      10      3    sep       Ljava/lang/String;
   0      10      4    end       Ljava/lang/String;


public scala.collection.mutable.StringBuilder addString(scala.collection.mutable.StringBuilder, java.lang.String);
  Signature: (Lscala/collection/mutable/StringBuilder;Ljava/lang/String;)Lscala/collection/mutable/StringBuilder;
  Code:
   Stack=3, Locals=3, Args_size=3
	aload_0
	aload_1
	aload_2
	invokestatic	Method scala/collection/TraversableProxyLike$class.addString:(Lscala/collection/TraversableProxyLike;Lscala/collection/mutable/StringBuilder;Ljava/lang/String;)Lscala/collection/mutable/StringBuilder;
	areturn
  Labels:
  LocalVariableTable: 
   Start  Length  Slot  Name   Signature
   0      7      0    this       Lscala/collection/mutable/SetProxy$$anon$1;
   0      7      1    b       Lscala/collection/mutable/StringBuilder;
   0      7      2    sep       Ljava/lang/String;


public scala.collection.mutable.StringBuilder addString(scala.collection.mutable.StringBuilder);
  Signature: (Lscala/collection/mutable/StringBuilder;)Lscala/collection/mutable/StringBuilder;
  Code:
   Stack=2, Locals=2, Args_size=2
	aload_0
	aload_1
	invokestatic	Method scala/collection/TraversableProxyLike$class.addString:(Lscala/collection/TraversableProxyLike;Lscala/collection/mutable/StringBuilder;)Lscala/collection/mutable/StringBuilder;
	areturn
  Labels:
  LocalVariableTable: 
   Start  Length  Slot  Name   Signature
   0      6      0    this       Lscala/collection/mutable/SetProxy$$anon$1;
   0      6      1    b       Lscala/collection/mutable/StringBuilder;


public java.lang.String stringPrefix();
  Signature: ()Ljava/lang/String;
  Code:
   Stack=1, Locals=1, Args_size=1
	aload_0
	invokestatic	Method scala/collection/TraversableProxyLike$class.stringPrefix:(Lscala/collection/TraversableProxyLike;)Ljava/lang/String;
	areturn
  Labels:

public int hashCode();
  Signature: ()I
  Code:
   Stack=1, Locals=1, Args_size=1
	aload_0
	invokestatic	Method scala/Proxy$class.hashCode:(Lscala/Proxy;)I
	ireturn
  Labels:

public boolean equals(java.lang.Object);
  Signature: (Ljava/lang/Object;)Z
  Code:
   Stack=2, Locals=2, Args_size=2
	aload_0
	aload_1
	invokestatic	Method scala/Proxy$class.equals:(Lscala/Proxy;Ljava/lang/Object;)Z
	ireturn
  Labels:
  LocalVariableTable: 
   Start  Length  Slot  Name   Signature
   0      6      0    this       Lscala/collection/mutable/SetProxy$$anon$1;
   0      6      1    that       Ljava/lang/Object;


public java.lang.String toString();
  Signature: ()Ljava/lang/String;
  Code:
   Stack=1, Locals=1, Args_size=1
	aload_0
	invokestatic	Method scala/Proxy$class.toString:(Lscala/Proxy;)Ljava/lang/String;
	areturn
  Labels:

public scala.collection.generic.GenericCompanion companion();
  Signature: ()Lscala/collection/generic/GenericCompanion;
  Code:
   Stack=1, Locals=1, Args_size=1
	aload_0
	invokestatic	Method scala/collection/mutable/Set$class.companion:(Lscala/collection/mutable/Set;)Lscala/collection/generic/GenericCompanion;
	areturn
  Labels:

public final java.lang.Object scala$collection$mutable$SetLike$$super$map(scala.Function1, scala.collection.generic.CanBuildFrom);
  Signature: (Lscala/Function1;Lscala/collection/generic/CanBuildFrom;)Ljava/lang/Object;
  Code:
   Stack=3, Locals=3, Args_size=3
	aload_0
	aload_1
	aload_2
	invokestatic	Method scala/collection/TraversableLike$class.map:(Lscala/collection/TraversableLike;Lscala/Function1;Lscala/collection/generic/CanBuildFrom;)Ljava/lang/Object;
	areturn
  Labels:
  LocalVariableTable: 
   Start  Length  Slot  Name   Signature
   0      7      0    this       Lscala/collection/mutable/SetProxy$$anon$1;
   0      7      1    f       Lscala/Function1;
   0      7      2    bf       Lscala/collection/generic/CanBuildFrom;


public scala.collection.mutable.Builder newBuilder();
  Signature: ()Lscala/collection/mutable/Builder;
  Code:
   Stack=1, Locals=1, Args_size=1
	aload_0
	invokestatic	Method scala/collection/mutable/SetLike$class.newBuilder:(Lscala/collection/mutable/SetLike;)Lscala/collection/mutable/Builder;
	areturn
  Labels:

public boolean add(java.lang.Object);
  Signature: (Ljava/lang/Object;)Z
  Code:
   Stack=2, Locals=2, Args_size=2
	aload_0
	aload_1
	invokestatic	Method scala/collection/mutable/SetLike$class.add:(Lscala/collection/mutable/SetLike;Ljava/lang/Object;)Z
	ireturn
  Labels:
  LocalVariableTable: 
   Start  Length  Slot  Name   Signature
   0      6      0    this       Lscala/collection/mutable/SetProxy$$anon$1;
   0      6      1    elem       Ljava/lang/Object;


public boolean remove(java.lang.Object);
  Signature: (Ljava/lang/Object;)Z
  Code:
   Stack=2, Locals=2, Args_size=2
	aload_0
	aload_1
	invokestatic	Method scala/collection/mutable/SetLike$class.remove:(Lscala/collection/mutable/SetLike;Ljava/lang/Object;)Z
	ireturn
  Labels:
  LocalVariableTable: 
   Start  Length  Slot  Name   Signature
   0      6      0    this       Lscala/collection/mutable/SetProxy$$anon$1;
   0      6      1    elem       Ljava/lang/Object;


public void update(java.lang.Object, boolean);
  Signature: (Ljava/lang/Object;Z)V
  Code:
   Stack=3, Locals=3, Args_size=3
	aload_0
	aload_1
	iload_2
	invokestatic	Method scala/collection/mutable/SetLike$class.update:(Lscala/collection/mutable/SetLike;Ljava/lang/Object;Z)V
	return
  Labels:
  LocalVariableTable: 
   Start  Length  Slot  Name   Signature
   0      7      0    this       Lscala/collection/mutable/SetProxy$$anon$1;
   0      7      1    elem       Ljava/lang/Object;
   0      7      2    included       Z


public void retain(scala.Function1);
  Signature: (Lscala/Function1;)V
  Code:
   Stack=2, Locals=2, Args_size=2
	aload_0
	aload_1
	invokestatic	Method scala/collection/mutable/SetLike$class.retain:(Lscala/collection/mutable/SetLike;Lscala/Function1;)V
	return
  Labels:
  LocalVariableTable: 
   Start  Length  Slot  Name   Signature
   0      6      0    this       Lscala/collection/mutable/SetProxy$$anon$1;
   0      6      1    p       Lscala/Function1;


public void clear();
  Signature: ()V
  Code:
   Stack=1, Locals=1, Args_size=1
	aload_0
	invokestatic	Method scala/collection/mutable/SetLike$class.clear:(Lscala/collection/mutable/SetLike;)V
	return
  Labels:

public scala.collection.mutable.Set clone();
  Signature: ()Lscala/collection/mutable/Set;
  Code:
   Stack=1, Locals=1, Args_size=1
	aload_0
	invokestatic	Method scala/collection/mutable/SetLike$class.clone:(Lscala/collection/mutable/SetLike;)Lscala/collection/mutable/Set;
	areturn
  Labels:

public scala.collection.mutable.Set result();
  Signature: ()Lscala/collection/mutable/Set;
  Code:
   Stack=1, Locals=1, Args_size=1
	aload_0
	invokestatic	Method scala/collection/mutable/SetLike$class.result:(Lscala/collection/mutable/SetLike;)Lscala/collection/mutable/Set;
	areturn
  Labels:

public scala.collection.mutable.Set $plus(java.lang.Object, java.lang.Object, scala.collection.Seq);
  Signature: (Ljava/lang/Object;Ljava/lang/Object;Lscala/collection/Seq;)Lscala/collection/mutable/Set;
  Code:
   Stack=4, Locals=4, Args_size=4
	aload_0
	aload_1
	aload_2
	aload_3
	invokestatic	Method scala/collection/mutable/SetLike$class.$plus:(Lscala/collection/mutable/SetLike;Ljava/lang/Object;Ljava/lang/Object;Lscala/collection/Seq;)Lscala/collection/mutable/Set;
	areturn
  Labels:
  LocalVariableTable: 
   Start  Length  Slot  Name   Signature
   0      8      0    this       Lscala/collection/mutable/SetProxy$$anon$1;
   0      8      1    elem1       Ljava/lang/Object;
   0      8      2    elem2       Ljava/lang/Object;
   0      8      3    elems       Lscala/collection/Seq;


public scala.collection.mutable.Set $plus$plus(scala.collection.Traversable);
  Signature: (Lscala/collection/Traversable;)Lscala/collection/mutable/Set;
  Code:
   Stack=2, Locals=2, Args_size=2
	aload_0
	aload_1
	invokestatic	Method scala/collection/mutable/SetLike$class.$plus$plus:(Lscala/collection/mutable/SetLike;Lscala/collection/Traversable;)Lscala/collection/mutable/Set;
	areturn
  Labels:
  LocalVariableTable: 
   Start  Length  Slot  Name   Signature
   0      6      0    this       Lscala/collection/mutable/SetProxy$$anon$1;
   0      6      1    iter       Lscala/collection/Traversable;


public scala.collection.mutable.Set $plus$plus(scala.collection.Iterator);
  Signature: (Lscala/collection/Iterator;)Lscala/collection/mutable/Set;
  Code:
   Stack=2, Locals=2, Args_size=2
	aload_0
	aload_1
	invokestatic	Method scala/collection/mutable/SetLike$class.$plus$plus:(Lscala/collection/mutable/SetLike;Lscala/collection/Iterator;)Lscala/collection/mutable/Set;
	areturn
  Labels:
  LocalVariableTable: 
   Start  Length  Slot  Name   Signature
   0      6      0    this       Lscala/collection/mutable/SetProxy$$anon$1;
   0      6      1    iter       Lscala/collection/Iterator;


public scala.collection.mutable.Set $minus(java.lang.Object, java.lang.Object, scala.collection.Seq);
  Signature: (Ljava/lang/Object;Ljava/lang/Object;Lscala/collection/Seq;)Lscala/collection/mutable/Set;
  Code:
   Stack=4, Locals=4, Args_size=4
	aload_0
	aload_1
	aload_2
	aload_3
	invokestatic	Method scala/collection/mutable/SetLike$class.$minus:(Lscala/collection/mutable/SetLike;Ljava/lang/Object;Ljava/lang/Object;Lscala/collection/Seq;)Lscala/collection/mutable/Set;
	areturn
  Labels:
  LocalVariableTable: 
   Start  Length  Slot  Name   Signature
   0      8      0    this       Lscala/collection/mutable/SetProxy$$anon$1;
   0      8      1    elem1       Ljava/lang/Object;
   0      8      2    elem2       Ljava/lang/Object;
   0      8      3    elems       Lscala/collection/Seq;


public scala.collection.mutable.Set $minus$minus(scala.collection.Traversable);
  Signature: (Lscala/collection/Traversable;)Lscala/collection/mutable/Set;
  Code:
   Stack=2, Locals=2, Args_size=2
	aload_0
	aload_1
	invokestatic	Method scala/collection/mutable/SetLike$class.$minus$minus:(Lscala/collection/mutable/SetLike;Lscala/collection/Traversable;)Lscala/collection/mutable/Set;
	areturn
  Labels:
  LocalVariableTable: 
   Start  Length  Slot  Name   Signature
   0      6      0    this       Lscala/collection/mutable/SetProxy$$anon$1;
   0      6      1    iter       Lscala/collection/Traversable;


public scala.collection.mutable.Set $minus$minus(scala.collection.Iterator);
  Signature: (Lscala/collection/Iterator;)Lscala/collection/mutable/Set;
  Code:
   Stack=2, Locals=2, Args_size=2
	aload_0
	aload_1
	invokestatic	Method scala/collection/mutable/SetLike$class.$minus$minus:(Lscala/collection/mutable/SetLike;Lscala/collection/Iterator;)Lscala/collection/mutable/Set;
	areturn
  Labels:
  LocalVariableTable: 
   Start  Length  Slot  Name   Signature
   0      6      0    this       Lscala/collection/mutable/SetProxy$$anon$1;
   0      6      1    iter       Lscala/collection/Iterator;


public void $less$less(scala.collection.script.Message);
  Signature: (Lscala/collection/script/Message;)V
  Code:
   Stack=2, Locals=2, Args_size=2
	aload_0
	aload_1
	invokestatic	Method scala/collection/mutable/SetLike$class.$less$less:(Lscala/collection/mutable/SetLike;Lscala/collection/script/Message;)V
	return
  Labels:
  LocalVariableTable: 
   Start  Length  Slot  Name   Signature
   0      6      0    this       Lscala/collection/mutable/SetProxy$$anon$1;
   0      6      1    cmd       Lscala/collection/script/Message;


public final java.lang.Object scala$collection$mutable$Cloneable$$super$clone();
  Signature: ()Ljava/lang/Object;
  Code:
   Stack=1, Locals=1, Args_size=1
	aload_0
	invokespecial	Method java/lang/Object.clone:()Ljava/lang/Object;
	areturn
  Labels:

public scala.collection.generic.Shrinkable $minus$eq(java.lang.Object, java.lang.Object, scala.collection.Seq);
  Signature: (Ljava/lang/Object;Ljava/lang/Object;Lscala/collection/Seq;)Lscala/collection/generic/Shrinkable;
  Code:
   Stack=4, Locals=4, Args_size=4
	aload_0
	aload_1
	aload_2
	aload_3
	invokestatic	Method scala/collection/generic/Shrinkable$class.$minus$eq:(Lscala/collection/generic/Shrinkable;Ljava/lang/Object;Ljava/lang/Object;Lscala/collection/Seq;)Lscala/collection/generic/Shrinkable;
	areturn
  Labels:
  LocalVariableTable: 
   Start  Length  Slot  Name   Signature
   0      8      0    this       Lscala/collection/mutable/SetProxy$$anon$1;
   0      8      1    elem1       Ljava/lang/Object;
   0      8      2    elem2       Ljava/lang/Object;
   0      8      3    elems       Lscala/collection/Seq;


public scala.collection.generic.Shrinkable $minus$minus$eq(scala.collection.Iterator);
  Signature: (Lscala/collection/Iterator;)Lscala/collection/generic/Shrinkable;
  Code:
   Stack=2, Locals=2, Args_size=2
	aload_0
	aload_1
	invokestatic	Method scala/collection/generic/Shrinkable$class.$minus$minus$eq:(Lscala/collection/generic/Shrinkable;Lscala/collection/Iterator;)Lscala/collection/generic/Shrinkable;
	areturn
  Labels:
  LocalVariableTable: 
   Start  Length  Slot  Name   Signature
   0      6      0    this       Lscala/collection/mutable/SetProxy$$anon$1;
   0      6      1    iter       Lscala/collection/Iterator;


public scala.collection.generic.Shrinkable $minus$minus$eq(scala.collection.Traversable);
  Signature: (Lscala/collection/Traversable;)Lscala/collection/generic/Shrinkable;
  Code:
   Stack=2, Locals=2, Args_size=2
	aload_0
	aload_1
	invokestatic	Method scala/collection/generic/Shrinkable$class.$minus$minus$eq:(Lscala/collection/generic/Shrinkable;Lscala/collection/Traversable;)Lscala/collection/generic/Shrinkable;
	areturn
  Labels:
  LocalVariableTable: 
   Start  Length  Slot  Name   Signature
   0      6      0    this       Lscala/collection/mutable/SetProxy$$anon$1;
   0      6      1    iter       Lscala/collection/Traversable;


public void sizeHint(int);
  Signature: (I)V
  Code:
   Stack=2, Locals=2, Args_size=2
	aload_0
	iload_1
	invokestatic	Method scala/collection/mutable/Builder$class.sizeHint:(Lscala/collection/mutable/Builder;I)V
	return
  Labels:
  LocalVariableTable: 
   Start  Length  Slot  Name   Signature
   0      6      0    this       Lscala/collection/mutable/SetProxy$$anon$1;
   0      6      1    size       I


public scala.collection.mutable.Builder mapResult(scala.Function1);
  Signature: (Lscala/Function1;)Lscala/collection/mutable/Builder;
  Code:
   Stack=2, Locals=2, Args_size=2
	aload_0
	aload_1
	invokestatic	Method scala/collection/mutable/Builder$class.mapResult:(Lscala/collection/mutable/Builder;Lscala/Function1;)Lscala/collection/mutable/Builder;
	areturn
  Labels:
  LocalVariableTable: 
   Start  Length  Slot  Name   Signature
   0      6      0    this       Lscala/collection/mutable/SetProxy$$anon$1;
   0      6      1    f       Lscala/Function1;


public scala.collection.generic.Growable $plus$eq(java.lang.Object, java.lang.Object, scala.collection.Seq);
  Signature: (Ljava/lang/Object;Ljava/lang/Object;Lscala/collection/Seq;)Lscala/collection/generic/Growable;
  Code:
   Stack=4, Locals=4, Args_size=4
	aload_0
	aload_1
	aload_2
	aload_3
	invokestatic	Method scala/collection/generic/Growable$class.$plus$eq:(Lscala/collection/generic/Growable;Ljava/lang/Object;Ljava/lang/Object;Lscala/collection/Seq;)Lscala/collection/generic/Growable;
	areturn
  Labels:
  LocalVariableTable: 
   Start  Length  Slot  Name   Signature
   0      8      0    this       Lscala/collection/mutable/SetProxy$$anon$1;
   0      8      1    elem1       Ljava/lang/Object;
   0      8      2    elem2       Ljava/lang/Object;
   0      8      3    elems       Lscala/collection/Seq;


public scala.collection.generic.Growable $plus$plus$eq(scala.collection.Iterator);
  Signature: (Lscala/collection/Iterator;)Lscala/collection/generic/Growable;
  Code:
   Stack=2, Locals=2, Args_size=2
	aload_0
	aload_1
	invokestatic	Method scala/collection/generic/Growable$class.$plus$plus$eq:(Lscala/collection/generic/Growable;Lscala/collection/Iterator;)Lscala/collection/generic/Growable;
	areturn
  Labels:
  LocalVariableTable: 
   Start  Length  Slot  Name   Signature
   0      6      0    this       Lscala/collection/mutable/SetProxy$$anon$1;
   0      6      1    iter       Lscala/collection/Iterator;


public scala.collection.generic.Growable $plus$plus$eq(scala.collection.Traversable);
  Signature: (Lscala/collection/Traversable;)Lscala/collection/generic/Growable;
  Code:
   Stack=2, Locals=2, Args_size=2
	aload_0
	aload_1
	invokestatic	Method scala/collection/generic/Growable$class.$plus$plus$eq:(Lscala/collection/generic/Growable;Lscala/collection/Traversable;)Lscala/collection/generic/Growable;
	areturn
  Labels:
  LocalVariableTable: 
   Start  Length  Slot  Name   Signature
   0      6      0    this       Lscala/collection/mutable/SetProxy$$anon$1;
   0      6      1    elems       Lscala/collection/Traversable;


public scala.collection.Set $times$times(scala.collection.Set);
  Signature: (Lscala/collection/Set;)Lscala/collection/Set;
  Code:
   Stack=2, Locals=2, Args_size=2
	aload_0
	aload_1
	invokestatic	Method scala/collection/SetLike$class.$times$times:(Lscala/collection/SetLike;Lscala/collection/Set;)Lscala/collection/Set;
	areturn
  Labels:
  LocalVariableTable: 
   Start  Length  Slot  Name   Signature
   0      6      0    this       Lscala/collection/mutable/SetProxy$$anon$1;
   0      6      1    that       Lscala/collection/Set;

  Deprecated: true

public scala.Function1 compose(scala.Function1);
  Signature: (Lscala/Function1;)Lscala/Function1;
  Code:
   Stack=2, Locals=2, Args_size=2
	aload_0
	aload_1
	invokestatic	Method scala/Function1$class.compose:(Lscala/Function1;Lscala/Function1;)Lscala/Function1;
	areturn
  Labels:
  LocalVariableTable: 
   Start  Length  Slot  Name   Signature
   0      6      0    this       Lscala/collection/mutable/SetProxy$$anon$1;
   0      6      1    g       Lscala/Function1;


public scala.Function1 andThen(scala.Function1);
  Signature: (Lscala/Function1;)Lscala/Function1;
  Code:
   Stack=2, Locals=2, Args_size=2
	aload_0
	aload_1
	invokestatic	Method scala/Function1$class.andThen:(Lscala/Function1;Lscala/Function1;)Lscala/Function1;
	areturn
  Labels:
  LocalVariableTable: 
   Start  Length  Slot  Name   Signature
   0      6      0    this       Lscala/collection/mutable/SetProxy$$anon$1;
   0      6      1    g       Lscala/Function1;


public scala.collection.Iterable thisCollection();
  Signature: ()Lscala/collection/Iterable;
  Code:
   Stack=1, Locals=1, Args_size=1
	aload_0
	invokestatic	Method scala/collection/IterableLike$class.thisCollection:(Lscala/collection/IterableLike;)Lscala/collection/Iterable;
	areturn
  Labels:

public scala.collection.Iterable toCollection(java.lang.Object);
  Signature: (Ljava/lang/Object;)Lscala/collection/Iterable;
  Code:
   Stack=2, Locals=2, Args_size=2
	aload_0
	aload_1
	invokestatic	Method scala/collection/IterableLike$class.toCollection:(Lscala/collection/IterableLike;Ljava/lang/Object;)Lscala/collection/Iterable;
	areturn
  Labels:
  LocalVariableTable: 
   Start  Length  Slot  Name   Signature
   0      6      0    this       Lscala/collection/mutable/SetProxy$$anon$1;
   0      6      1    repr       Ljava/lang/Object;


public boolean canEqual(java.lang.Object);
  Signature: (Ljava/lang/Object;)Z
  Code:
   Stack=2, Locals=2, Args_size=2
	aload_0
	aload_1
	invokestatic	Method scala/collection/IterableLike$class.canEqual:(Lscala/collection/IterableLike;Ljava/lang/Object;)Z
	ireturn
  Labels:
  LocalVariableTable: 
   Start  Length  Slot  Name   Signature
   0      6      0    this       Lscala/collection/mutable/SetProxy$$anon$1;
   0      6      1    that       Ljava/lang/Object;


public scala.collection.Iterator elements();
  Signature: ()Lscala/collection/Iterator;
  Code:
   Stack=1, Locals=1, Args_size=1
	aload_0
	invokestatic	Method scala/collection/IterableLike$class.elements:(Lscala/collection/IterableLike;)Lscala/collection/Iterator;
	areturn
  Labels:
  Deprecated: true

public java.lang.Object first();
  Signature: ()Ljava/lang/Object;
  Code:
   Stack=1, Locals=1, Args_size=1
	aload_0
	invokestatic	Method scala/collection/IterableLike$class.first:(Lscala/collection/IterableLike;)Ljava/lang/Object;
	areturn
  Labels:
  Deprecated: true

public scala.Option firstOption();
  Signature: ()Lscala/Option;
  Code:
   Stack=1, Locals=1, Args_size=1
	aload_0
	invokestatic	Method scala/collection/IterableLike$class.firstOption:(Lscala/collection/IterableLike;)Lscala/Option;
	areturn
  Labels:
  Deprecated: true

public scala.collection.IterableView projection();
  Signature: ()Lscala/collection/IterableView;
  Code:
   Stack=1, Locals=1, Args_size=1
	aload_0
	invokestatic	Method scala/collection/IterableLike$class.projection:(Lscala/collection/IterableLike;)Lscala/collection/IterableView;
	areturn
  Labels:
  Deprecated: true

public scala.collection.mutable.Builder genericBuilder();
  Signature: ()Lscala/collection/mutable/Builder;
  Code:
   Stack=1, Locals=1, Args_size=1
	aload_0
	invokestatic	Method scala/collection/generic/GenericTraversableTemplate$class.genericBuilder:(Lscala/collection/generic/GenericTraversableTemplate;)Lscala/collection/mutable/Builder;
	areturn
  Labels:

public scala.Tuple2 unzip(scala.Function1);
  Signature: (Lscala/Function1;)Lscala/Tuple2;
  Code:
   Stack=2, Locals=2, Args_size=2
	aload_0
	aload_1
	invokestatic	Method scala/collection/generic/GenericTraversableTemplate$class.unzip:(Lscala/collection/generic/GenericTraversableTemplate;Lscala/Function1;)Lscala/Tuple2;
	areturn
  Labels:
  LocalVariableTable: 
   Start  Length  Slot  Name   Signature
   0      6      0    this       Lscala/collection/mutable/SetProxy$$anon$1;
   0      6      1    asPair       Lscala/Function1;


public scala.collection.Traversable flatten(scala.Function1);
  Signature: (Lscala/Function1;)Lscala/collection/Traversable;
  Code:
   Stack=2, Locals=2, Args_size=2
	aload_0
	aload_1
	invokestatic	Method scala/collection/generic/GenericTraversableTemplate$class.flatten:(Lscala/collection/generic/GenericTraversableTemplate;Lscala/Function1;)Lscala/collection/Traversable;
	areturn
  Labels:
  LocalVariableTable: 
   Start  Length  Slot  Name   Signature
   0      6      0    this       Lscala/collection/mutable/SetProxy$$anon$1;
   0      6      1    asTraversable       Lscala/Function1;


public scala.collection.Traversable transpose(scala.Function1);
  Signature: (Lscala/Function1;)Lscala/collection/Traversable;
  Code:
   Stack=2, Locals=2, Args_size=2
	aload_0
	aload_1
	invokestatic	Method scala/collection/generic/GenericTraversableTemplate$class.transpose:(Lscala/collection/generic/GenericTraversableTemplate;Lscala/Function1;)Lscala/collection/Traversable;
	areturn
  Labels:
  LocalVariableTable: 
   Start  Length  Slot  Name   Signature
   0      6      0    this       Lscala/collection/mutable/SetProxy$$anon$1;
   0      6      1    asTraversable       Lscala/Function1;


public scala.collection.TraversableLike$WithFilter withFilter(scala.Function1);
  Signature: (Lscala/Function1;)Lscala/collection/TraversableLike$WithFilter;
  Code:
   Stack=2, Locals=2, Args_size=2
	aload_0
	aload_1
	invokestatic	Method scala/collection/TraversableLike$class.withFilter:(Lscala/collection/TraversableLike;Lscala/Function1;)Lscala/collection/TraversableLike$WithFilter;
	areturn
  Labels:
  LocalVariableTable: 
   Start  Length  Slot  Name   Signature
   0      6      0    this       Lscala/collection/mutable/SetProxy$$anon$1;
   0      6      1    p       Lscala/Function1;

  Signature: length = 0x2
   02 FFFFFF8F 

public scala.collection.mutable.Set self();
  Signature: ()Lscala/collection/mutable/Set;
  Code:
   Stack=1, Locals=1, Args_size=1
	aload_0
	getfield	Field self:Lscala/collection/mutable/Set;
	areturn
  Labels:
  Signature: length = 0x2
   02 FFFFFF97 

public scala.collection.Traversable toCollection(java.lang.Object);
  Signature: (Ljava/lang/Object;)Lscala/collection/Traversable;
  Code:
   Stack=2, Locals=2, Args_size=2
	aload_0
	aload_1
	invokeinterface	InterfaceMethod scala/collection/IterableLike.toCollection:(Ljava/lang/Object;)Lscala/collection/Iterable;
	areturn
  Labels:
  LocalVariableTable: 
   Start  Length  Slot  Name   Signature
   0      8      0    this       Lscala/collection/mutable/SetProxy$$anon$1;
   0      8      1    repr       Ljava/lang/Object;


public scala.collection.Traversable thisCollection();
  Signature: ()Lscala/collection/Traversable;
  Code:
   Stack=1, Locals=1, Args_size=1
	aload_0
	invokeinterface	InterfaceMethod scala/collection/IterableLike.thisCollection:()Lscala/collection/Iterable;
	areturn
  Labels:

public scala.collection.generic.Subtractable $minus$minus(scala.collection.Iterator);
  Signature: (Lscala/collection/Iterator;)Lscala/collection/generic/Subtractable;
  Code:
   Stack=2, Locals=2, Args_size=2
	aload_0
	aload_1
	invokeinterface	InterfaceMethod scala/collection/mutable/SetLike.$minus$minus:(Lscala/collection/Iterator;)Lscala/collection/mutable/Set;
	areturn
  Labels:
  LocalVariableTable: 
   Start  Length  Slot  Name   Signature
   0      8      0    this       Lscala/collection/mutable/SetProxy$$anon$1;
   0      8      1    iter       Lscala/collection/Iterator;


public scala.collection.generic.Subtractable $minus$minus(scala.collection.Traversable);
  Signature: (Lscala/collection/Traversable;)Lscala/collection/generic/Subtractable;
  Code:
   Stack=2, Locals=2, Args_size=2
	aload_0
	aload_1
	invokeinterface	InterfaceMethod scala/collection/mutable/SetLike.$minus$minus:(Lscala/collection/Traversable;)Lscala/collection/mutable/Set;
	areturn
  Labels:
  LocalVariableTable: 
   Start  Length  Slot  Name   Signature
   0      8      0    this       Lscala/collection/mutable/SetProxy$$anon$1;
   0      8      1    elems       Lscala/collection/Traversable;


public scala.collection.generic.Subtractable $minus(java.lang.Object, java.lang.Object, scala.collection.Seq);
  Signature: (Ljava/lang/Object;Ljava/lang/Object;Lscala/collection/Seq;)Lscala/collection/generic/Subtractable;
  Code:
   Stack=4, Locals=4, Args_size=4
	aload_0
	aload_1
	aload_2
	aload_3
	invokeinterface	InterfaceMethod scala/collection/mutable/SetLike.$minus:(Ljava/lang/Object;Ljava/lang/Object;Lscala/collection/Seq;)Lscala/collection/mutable/Set;
	areturn
  Labels:
  LocalVariableTable: 
   Start  Length  Slot  Name   Signature
   0      10      0    this       Lscala/collection/mutable/SetProxy$$anon$1;
   0      10      1    elem1       Ljava/lang/Object;
   0      10      2    elem2       Ljava/lang/Object;
   0      10      3    elems       Lscala/collection/Seq;


public scala.collection.generic.Addable $plus$plus(scala.collection.Iterator);
  Signature: (Lscala/collection/Iterator;)Lscala/collection/generic/Addable;
  Code:
   Stack=2, Locals=2, Args_size=2
	aload_0
	aload_1
	invokeinterface	InterfaceMethod scala/collection/mutable/SetLike.$plus$plus:(Lscala/collection/Iterator;)Lscala/collection/mutable/Set;
	areturn
  Labels:
  LocalVariableTable: 
   Start  Length  Slot  Name   Signature
   0      8      0    this       Lscala/collection/mutable/SetProxy$$anon$1;
   0      8      1    iter       Lscala/collection/Iterator;


public scala.collection.generic.Addable $plus$plus(scala.collection.Traversable);
  Signature: (Lscala/collection/Traversable;)Lscala/collection/generic/Addable;
  Code:
   Stack=2, Locals=2, Args_size=2
	aload_0
	aload_1
	invokeinterface	InterfaceMethod scala/collection/mutable/SetLike.$plus$plus:(Lscala/collection/Traversable;)Lscala/collection/mutable/Set;
	areturn
  Labels:
  LocalVariableTable: 
   Start  Length  Slot  Name   Signature
   0      8      0    this       Lscala/collection/mutable/SetProxy$$anon$1;
   0      8      1    elems       Lscala/collection/Traversable;


public scala.collection.generic.Addable $plus(java.lang.Object, java.lang.Object, scala.collection.Seq);
  Signature: (Ljava/lang/Object;Ljava/lang/Object;Lscala/collection/Seq;)Lscala/collection/generic/Addable;
  Code:
   Stack=4, Locals=4, Args_size=4
	aload_0
	aload_1
	aload_2
	aload_3
	invokeinterface	InterfaceMethod scala/collection/mutable/SetLike.$plus:(Ljava/lang/Object;Ljava/lang/Object;Lscala/collection/Seq;)Lscala/collection/mutable/Set;
	areturn
  Labels:
  LocalVariableTable: 
   Start  Length  Slot  Name   Signature
   0      10      0    this       Lscala/collection/mutable/SetProxy$$anon$1;
   0      10      1    elem1       Ljava/lang/Object;
   0      10      2    elem2       Ljava/lang/Object;
   0      10      3    elems       Lscala/collection/Seq;


public java.lang.Object result();
  Signature: ()Ljava/lang/Object;
  Code:
   Stack=1, Locals=1, Args_size=1
	aload_0
	invokeinterface	InterfaceMethod scala/collection/mutable/SetLike.result:()Lscala/collection/mutable/Set;
	areturn
  Labels:

public java.lang.Object clone();
  Signature: ()Ljava/lang/Object;
  Code:
   Stack=1, Locals=1, Args_size=1
	aload_0
	invokeinterface	InterfaceMethod scala/collection/mutable/SetLike.clone:()Lscala/collection/mutable/Set;
	areturn
  Labels:

public java.lang.Object dropWhile(scala.Function1);
  Signature: (Lscala/Function1;)Ljava/lang/Object;
  Code:
   Stack=2, Locals=2, Args_size=2
	aload_0
	aload_1
	invokeinterface	InterfaceMethod scala/collection/TraversableProxyLike.dropWhile:(Lscala/Function1;)Lscala/collection/Traversable;
	areturn
  Labels:
  LocalVariableTable: 
   Start  Length  Slot  Name   Signature
   0      8      0    this       Lscala/collection/mutable/SetProxy$$anon$1;
   0      8      1    p       Lscala/Function1;


public java.lang.Object takeWhile(scala.Function1);
  Signature: (Lscala/Function1;)Ljava/lang/Object;
  Code:
   Stack=2, Locals=2, Args_size=2
	aload_0
	aload_1
	invokeinterface	InterfaceMethod scala/collection/TraversableProxyLike.takeWhile:(Lscala/Function1;)Lscala/collection/Traversable;
	areturn
  Labels:
  LocalVariableTable: 
   Start  Length  Slot  Name   Signature
   0      8      0    this       Lscala/collection/mutable/SetProxy$$anon$1;
   0      8      1    p       Lscala/Function1;


public java.lang.Object slice(int, int);
  Signature: (II)Ljava/lang/Object;
  Code:
   Stack=3, Locals=3, Args_size=3
	aload_0
	iload_1
	iload_2
	invokeinterface	InterfaceMethod scala/collection/TraversableProxyLike.slice:(II)Lscala/collection/Traversable;
	areturn
  Labels:
  LocalVariableTable: 
   Start  Length  Slot  Name   Signature
   0      9      0    this       Lscala/collection/mutable/SetProxy$$anon$1;
   0      9      1    from       I
   0      9      2    until       I


public java.lang.Object drop(int);
  Signature: (I)Ljava/lang/Object;
  Code:
   Stack=2, Locals=2, Args_size=2
	aload_0
	iload_1
	invokeinterface	InterfaceMethod scala/collection/TraversableProxyLike.drop:(I)Lscala/collection/Traversable;
	areturn
  Labels:
  LocalVariableTable: 
   Start  Length  Slot  Name   Signature
   0      8      0    this       Lscala/collection/mutable/SetProxy$$anon$1;
   0      8      1    n       I


public java.lang.Object take(int);
  Signature: (I)Ljava/lang/Object;
  Code:
   Stack=2, Locals=2, Args_size=2
	aload_0
	iload_1
	invokeinterface	InterfaceMethod scala/collection/TraversableProxyLike.take:(I)Lscala/collection/Traversable;
	areturn
  Labels:
  LocalVariableTable: 
   Start  Length  Slot  Name   Signature
   0      8      0    this       Lscala/collection/mutable/SetProxy$$anon$1;
   0      8      1    n       I


public java.lang.Object init();
  Signature: ()Ljava/lang/Object;
  Code:
   Stack=1, Locals=1, Args_size=1
	aload_0
	invokeinterface	InterfaceMethod scala/collection/TraversableProxyLike.init:()Lscala/collection/Traversable;
	areturn
  Labels:

public java.lang.Object tail();
  Signature: ()Ljava/lang/Object;
  Code:
   Stack=1, Locals=1, Args_size=1
	aload_0
	invokeinterface	InterfaceMethod scala/collection/TraversableProxyLike.tail:()Lscala/collection/Traversable;
	areturn
  Labels:

public java.lang.Object filterNot(scala.Function1);
  Signature: (Lscala/Function1;)Ljava/lang/Object;
  Code:
   Stack=2, Locals=2, Args_size=2
	aload_0
	aload_1
	invokeinterface	InterfaceMethod scala/collection/TraversableProxyLike.filterNot:(Lscala/Function1;)Lscala/collection/Traversable;
	areturn
  Labels:
  LocalVariableTable: 
   Start  Length  Slot  Name   Signature
   0      8      0    this       Lscala/collection/mutable/SetProxy$$anon$1;
   0      8      1    p       Lscala/Function1;


public java.lang.Object filter(scala.Function1);
  Signature: (Lscala/Function1;)Ljava/lang/Object;
  Code:
   Stack=2, Locals=2, Args_size=2
	aload_0
	aload_1
	invokeinterface	InterfaceMethod scala/collection/TraversableProxyLike.filter:(Lscala/Function1;)Lscala/collection/Traversable;
	areturn
  Labels:
  LocalVariableTable: 
   Start  Length  Slot  Name   Signature
   0      8      0    this       Lscala/collection/mutable/SetProxy$$anon$1;
   0      8      1    p       Lscala/Function1;


public scala.collection.TraversableView view(int, int);
  Signature: (II)Lscala/collection/TraversableView;
  Code:
   Stack=3, Locals=3, Args_size=3
	aload_0
	iload_1
	iload_2
	invokeinterface	InterfaceMethod scala/collection/IterableProxyLike.view:(II)Lscala/collection/IterableView;
	areturn
  Labels:
  LocalVariableTable: 
   Start  Length  Slot  Name   Signature
   0      9      0    this       Lscala/collection/mutable/SetProxy$$anon$1;
   0      9      1    from       I
   0      9      2    until       I


public scala.collection.TraversableView view();
  Signature: ()Lscala/collection/TraversableView;
  Code:
   Stack=1, Locals=1, Args_size=1
	aload_0
	invokeinterface	InterfaceMethod scala/collection/IterableProxyLike.view:()Lscala/collection/IterableView;
	areturn
  Labels:

public java.lang.Object dropRight(int);
  Signature: (I)Ljava/lang/Object;
  Code:
   Stack=2, Locals=2, Args_size=2
	aload_0
	iload_1
	invokeinterface	InterfaceMethod scala/collection/IterableProxyLike.dropRight:(I)Lscala/collection/Iterable;
	areturn
  Labels:
  LocalVariableTable: 
   Start  Length  Slot  Name   Signature
   0      8      0    this       Lscala/collection/mutable/SetProxy$$anon$1;
   0      8      1    n       I


public java.lang.Object takeRight(int);
  Signature: (I)Ljava/lang/Object;
  Code:
   Stack=2, Locals=2, Args_size=2
	aload_0
	iload_1
	invokeinterface	InterfaceMethod scala/collection/IterableProxyLike.takeRight:(I)Lscala/collection/Iterable;
	areturn
  Labels:
  LocalVariableTable: 
   Start  Length  Slot  Name   Signature
   0      8      0    this       Lscala/collection/mutable/SetProxy$$anon$1;
   0      8      1    n       I


public java.lang.Object apply(java.lang.Object);
  Signature: (Ljava/lang/Object;)Ljava/lang/Object;
  Code:
   Stack=2, Locals=3, Args_size=2
	aload_0
	aload_1
	invokeinterface	InterfaceMethod scala/collection/SetProxyLike.apply:(Ljava/lang/Object;)Z
	istore_2
	iload_2
	invokestatic	Method scala/runtime/BoxesRunTime.boxToBoolean:(Z)Ljava/lang/Boolean;
	areturn
  Labels:
  LocalVariableTable: 
   Start  Length  Slot  Name   Signature
   0      13      0    this       Lscala/collection/mutable/SetProxy$$anon$1;
   0      13      1    v1       Ljava/lang/Object;


public scala.collection.generic.Shrinkable $minus$eq(java.lang.Object);
  Signature: (Ljava/lang/Object;)Lscala/collection/generic/Shrinkable;
  Code:
   Stack=2, Locals=2, Args_size=2
	aload_0
	aload_1
	invokeinterface	InterfaceMethod scala/collection/mutable/SetProxy.$minus$eq:(Ljava/lang/Object;)Lscala/collection/mutable/SetProxy;
	areturn
  Labels:
  LocalVariableTable: 
   Start  Length  Slot  Name   Signature
   0      8      0    this       Lscala/collection/mutable/SetProxy$$anon$1;
   0      8      1    elem       Ljava/lang/Object;


public scala.collection.mutable.SetLike $minus$eq(java.lang.Object);
  Signature: (Ljava/lang/Object;)Lscala/collection/mutable/SetLike;
  Code:
   Stack=2, Locals=2, Args_size=2
	aload_0
	aload_1
	invokeinterface	InterfaceMethod scala/collection/mutable/SetProxy.$minus$eq:(Ljava/lang/Object;)Lscala/collection/mutable/SetProxy;
	areturn
  Labels:
  LocalVariableTable: 
   Start  Length  Slot  Name   Signature
   0      8      0    this       Lscala/collection/mutable/SetProxy$$anon$1;
   0      8      1    elem       Ljava/lang/Object;


public scala.collection.generic.Growable $plus$eq(java.lang.Object);
  Signature: (Ljava/lang/Object;)Lscala/collection/generic/Growable;
  Code:
   Stack=2, Locals=2, Args_size=2
	aload_0
	aload_1
	invokeinterface	InterfaceMethod scala/collection/mutable/SetProxy.$plus$eq:(Ljava/lang/Object;)Lscala/collection/mutable/SetProxy;
	areturn
  Labels:
  LocalVariableTable: 
   Start  Length  Slot  Name   Signature
   0      8      0    this       Lscala/collection/mutable/SetProxy$$anon$1;
   0      8      1    elem       Ljava/lang/Object;


public scala.collection.mutable.Builder $plus$eq(java.lang.Object);
  Signature: (Ljava/lang/Object;)Lscala/collection/mutable/Builder;
  Code:
   Stack=2, Locals=2, Args_size=2
	aload_0
	aload_1
	invokeinterface	InterfaceMethod scala/collection/mutable/SetProxy.$plus$eq:(Ljava/lang/Object;)Lscala/collection/mutable/SetProxy;
	areturn
  Labels:
  LocalVariableTable: 
   Start  Length  Slot  Name   Signature
   0      8      0    this       Lscala/collection/mutable/SetProxy$$anon$1;
   0      8      1    elem       Ljava/lang/Object;


public scala.collection.mutable.SetLike $plus$eq(java.lang.Object);
  Signature: (Ljava/lang/Object;)Lscala/collection/mutable/SetLike;
  Code:
   Stack=2, Locals=2, Args_size=2
	aload_0
	aload_1
	invokeinterface	InterfaceMethod scala/collection/mutable/SetProxy.$plus$eq:(Ljava/lang/Object;)Lscala/collection/mutable/SetProxy;
	areturn
  Labels:
  LocalVariableTable: 
   Start  Length  Slot  Name   Signature
   0      8      0    this       Lscala/collection/mutable/SetProxy$$anon$1;
   0      8      1    elem       Ljava/lang/Object;


public scala.collection.generic.Subtractable $minus(java.lang.Object);
  Signature: (Ljava/lang/Object;)Lscala/collection/generic/Subtractable;
  Code:
   Stack=2, Locals=2, Args_size=2
	aload_0
	aload_1
	invokeinterface	InterfaceMethod scala/collection/mutable/SetProxy.$minus:(Ljava/lang/Object;)Lscala/collection/mutable/SetProxy;
	areturn
  Labels:
  LocalVariableTable: 
   Start  Length  Slot  Name   Signature
   0      8      0    this       Lscala/collection/mutable/SetProxy$$anon$1;
   0      8      1    elem       Ljava/lang/Object;


public scala.collection.Set $minus(java.lang.Object);
  Signature: (Ljava/lang/Object;)Lscala/collection/Set;
  Code:
   Stack=2, Locals=2, Args_size=2
	aload_0
	aload_1
	invokeinterface	InterfaceMethod scala/collection/mutable/SetProxy.$minus:(Ljava/lang/Object;)Lscala/collection/mutable/SetProxy;
	areturn
  Labels:
  LocalVariableTable: 
   Start  Length  Slot  Name   Signature
   0      8      0    this       Lscala/collection/mutable/SetProxy$$anon$1;
   0      8      1    elem       Ljava/lang/Object;


public scala.collection.mutable.Set $minus(java.lang.Object);
  Signature: (Ljava/lang/Object;)Lscala/collection/mutable/Set;
  Code:
   Stack=2, Locals=2, Args_size=2
	aload_0
	aload_1
	invokeinterface	InterfaceMethod scala/collection/mutable/SetProxy.$minus:(Ljava/lang/Object;)Lscala/collection/mutable/SetProxy;
	areturn
  Labels:
  LocalVariableTable: 
   Start  Length  Slot  Name   Signature
   0      8      0    this       Lscala/collection/mutable/SetProxy$$anon$1;
   0      8      1    elem       Ljava/lang/Object;


public scala.collection.generic.Addable $plus(java.lang.Object);
  Signature: (Ljava/lang/Object;)Lscala/collection/generic/Addable;
  Code:
   Stack=2, Locals=2, Args_size=2
	aload_0
	aload_1
	invokeinterface	InterfaceMethod scala/collection/mutable/SetProxy.$plus:(Ljava/lang/Object;)Lscala/collection/mutable/SetProxy;
	areturn
  Labels:
  LocalVariableTable: 
   Start  Length  Slot  Name   Signature
   0      8      0    this       Lscala/collection/mutable/SetProxy$$anon$1;
   0      8      1    elem       Ljava/lang/Object;


public scala.collection.Set $plus(java.lang.Object);
  Signature: (Ljava/lang/Object;)Lscala/collection/Set;
  Code:
   Stack=2, Locals=2, Args_size=2
	aload_0
	aload_1
	invokeinterface	InterfaceMethod scala/collection/mutable/SetProxy.$plus:(Ljava/lang/Object;)Lscala/collection/mutable/SetProxy;
	areturn
  Labels:
  LocalVariableTable: 
   Start  Length  Slot  Name   Signature
   0      8      0    this       Lscala/collection/mutable/SetProxy$$anon$1;
   0      8      1    elem       Ljava/lang/Object;


public scala.collection.mutable.Set $plus(java.lang.Object);
  Signature: (Ljava/lang/Object;)Lscala/collection/mutable/Set;
  Code:
   Stack=2, Locals=2, Args_size=2
	aload_0
	aload_1
	invokeinterface	InterfaceMethod scala/collection/mutable/SetProxy.$plus:(Ljava/lang/Object;)Lscala/collection/mutable/SetProxy;
	areturn
  Labels:
  LocalVariableTable: 
   Start  Length  Slot  Name   Signature
   0      8      0    this       Lscala/collection/mutable/SetProxy$$anon$1;
   0      8      1    elem       Ljava/lang/Object;


public scala.collection.Set empty();
  Signature: ()Lscala/collection/Set;
  Code:
   Stack=1, Locals=1, Args_size=1
	aload_0
	invokeinterface	InterfaceMethod scala/collection/mutable/SetProxy.empty:()Lscala/collection/mutable/SetProxy;
	areturn
  Labels:

public scala.collection.generic.Addable repr();
  Signature: ()Lscala/collection/generic/Addable;
  Code:
   Stack=1, Locals=1, Args_size=1
	aload_0
	invokeinterface	InterfaceMethod scala/collection/mutable/SetProxy.repr:()Lscala/collection/mutable/SetProxy;
	areturn
  Labels:

public scala.collection.generic.Subtractable repr();
  Signature: ()Lscala/collection/generic/Subtractable;
  Code:
   Stack=1, Locals=1, Args_size=1
	aload_0
	invokeinterface	InterfaceMethod scala/collection/mutable/SetProxy.repr:()Lscala/collection/mutable/SetProxy;
	areturn
  Labels:

public java.lang.Object repr();
  Signature: ()Ljava/lang/Object;
  Code:
   Stack=1, Locals=1, Args_size=1
	aload_0
	invokeinterface	InterfaceMethod scala/collection/mutable/SetProxy.repr:()Lscala/collection/mutable/SetProxy;
	areturn
  Labels:

public java.lang.Object self();
  Signature: ()Ljava/lang/Object;
  Code:
   Stack=1, Locals=1, Args_size=1
	aload_0
	invokevirtual	Method self:()Lscala/collection/mutable/Set;
	areturn
  Labels:

public scala.collection.Traversable self();
  Signature: ()Lscala/collection/Traversable;
  Code:
   Stack=1, Locals=1, Args_size=1
	aload_0
	invokevirtual	Method self:()Lscala/collection/mutable/Set;
	areturn
  Labels:

public scala.collection.mutable.SetProxy$$anon$1(scala.collection.mutable.SetProxy);
  Signature: (Lscala/collection/mutable/SetProxy;)V
  Code:
   Stack=2, Locals=2, Args_size=2
	aload_0
	invokespecial	Method java/lang/Object."<init>":()V
	aload_0
	invokestatic	Method scala/collection/TraversableLike$class.$init$:(Lscala/collection/TraversableLike;)V
	aload_0
	invokestatic	Method scala/collection/generic/GenericTraversableTemplate$class.$init$:(Lscala/collection/generic/GenericTraversableTemplate;)V
	aload_0
	invokestatic	Method scala/collection/Traversable$class.$init$:(Lscala/collection/Traversable;)V
	aload_0
	invokestatic	Method scala/collection/mutable/Traversable$class.$init$:(Lscala/collection/mutable/Traversable;)V
	aload_0
	invokestatic	Method scala/collection/IterableLike$class.$init$:(Lscala/collection/IterableLike;)V
	aload_0
	invokestatic	Method scala/collection/Iterable$class.$init$:(Lscala/collection/Iterable;)V
	aload_0
	invokestatic	Method scala/collection/mutable/Iterable$class.$init$:(Lscala/collection/mutable/Iterable;)V
	aload_0
	invokestatic	Method scala/Function1$class.$init$:(Lscala/Function1;)V
	aload_0
	invokestatic	Method scala/collection/generic/GenericSetTemplate$class.$init$:(Lscala/collection/generic/GenericSetTemplate;)V
	aload_0
	invokestatic	Method scala/collection/generic/Addable$class.$init$:(Lscala/collection/generic/Addable;)V
	aload_0
	invokestatic	Method scala/collection/generic/Subtractable$class.$init$:(Lscala/collection/generic/Subtractable;)V
	aload_0
	invokestatic	Method scala/collection/SetLike$class.$init$:(Lscala/collection/SetLike;)V
	aload_0
	invokestatic	Method scala/collection/Set$class.$init$:(Lscala/collection/Set;)V
	aload_0
	invokestatic	Method scala/collection/generic/Growable$class.$init$:(Lscala/collection/generic/Growable;)V
	aload_0
	invokestatic	Method scala/collection/mutable/Builder$class.$init$:(Lscala/collection/mutable/Builder;)V
	aload_0
	invokestatic	Method scala/collection/generic/Shrinkable$class.$init$:(Lscala/collection/generic/Shrinkable;)V
	aload_0
	invokestatic	Method scala/collection/mutable/Cloneable$class.$init$:(Lscala/collection/mutable/Cloneable;)V
	aload_0
	invokestatic	Method scala/collection/mutable/SetLike$class.$init$:(Lscala/collection/mutable/SetLike;)V
	aload_0
	invokestatic	Method scala/collection/mutable/Set$class.$init$:(Lscala/collection/mutable/Set;)V
	aload_0
	invokestatic	Method scala/Proxy$class.$init$:(Lscala/Proxy;)V
	aload_0
	invokestatic	Method scala/collection/TraversableProxyLike$class.$init$:(Lscala/collection/TraversableProxyLike;)V
	aload_0
	invokestatic	Method scala/collection/IterableProxyLike$class.$init$:(Lscala/collection/IterableProxyLike;)V
	aload_0
	invokestatic	Method scala/collection/SetProxyLike$class.$init$:(Lscala/collection/SetProxyLike;)V
	aload_0
	invokestatic	Method scala/collection/mutable/SetProxy$class.$init$:(Lscala/collection/mutable/SetProxy;)V
	aload_0
	aload_1
	invokeinterface	InterfaceMethod scala/collection/TraversableProxyLike.self:()Lscala/collection/Traversable;
	checkcast	class scala/collection/generic/GenericSetTemplate
	invokeinterface	InterfaceMethod scala/collection/generic/GenericSetTemplate.empty:()Lscala/collection/Set;
	checkcast	class scala/collection/mutable/Set
	putfield	Field self:Lscala/collection/mutable/Set;
	return
  Labels:
  LocalVariableTable: 
   Start  Length  Slot  Name   Signature
   0      122      0    this       Lscala/collection/mutable/SetProxy$$anon$1;
   0      122      1    $outer       Lscala/collection/mutable/SetProxy;

  Signature: length = 0x2
   03 67 

}

