Compiled from "Stack.scala"
public final class scala.collection.mutable.Stack$$anonfun$pushAll$2 extends java.lang.Object implements scala.Function1,scala.ScalaObject,java.io.Serializable
  SourceFile: "Stack.scala"
  Scala: length = 0x
   
  InnerClass: 
   public final $anonfun$pushAll$2=class scala/collection/mutable/Stack$$anonfun$pushAll$2 of class scala/collection/mutable/Stack
  minor version: 0
  major version: 49
  Constant pool:
Asciz	SourceFile;
Asciz	Stack.scala;
Asciz	<clinit>;
Asciz	()V;
Asciz	Code;
Asciz	serialVersionUID;
Asciz	J;
Asciz	scala/collection/mutable/Stack$$anonfun$pushAll$2;
class	scala/collection/mutable/Stack$$anonfun$pushAll$2
NameAndType	serialVersionUID:J
Field	scala/collection/mutable/Stack$$anonfun$pushAll$2.serialVersionUID:J
Asciz	$outer;
Asciz	Lscala/collection/mutable/Stack;;
Asciz	<init>;
Asciz	(Lscala/collection/mutable/Stack;)V;
Asciz	LineNumberTable;
Asciz	java/lang/NullPointerException;
class	java/lang/NullPointerException
NameAndType	"<init>":()V
Method	java/lang/NullPointerException."<init>":()V
NameAndType	$outer:Lscala/collection/mutable/Stack;
Field	scala/collection/mutable/Stack$$anonfun$pushAll$2.$outer:Lscala/collection/mutable/Stack;
Asciz	java/lang/Object;
class	java/lang/Object
Method	java/lang/Object."<init>":()V
Asciz	scala/Function1$class;
class	scala/Function1$class
Asciz	$init$;
Asciz	(Lscala/Function1;)V;
NameAndType	$init$:(Lscala/Function1;)V
Method	scala/Function1$class.$init$:(Lscala/Function1;)V
Asciz	this;
Asciz	Lscala/collection/mutable/Stack$$anonfun$pushAll$2;;
Asciz	LocalVariableTable;
Asciz	(Lscala/collection/mutable/Stack<TA;>;)V;
Asciz	Signature;
Asciz	apply;
Asciz	(Ljava/lang/Object;)Ljava/lang/Object;;
Asciz	(Ljava/lang/Object;)V;
NameAndType	apply:(Ljava/lang/Object;)V
Method	scala/collection/mutable/Stack$$anonfun$pushAll$2.apply:(Ljava/lang/Object;)V
Asciz	scala/runtime/BoxedUnit;
class	scala/runtime/BoxedUnit
Asciz	UNIT;
Asciz	Lscala/runtime/BoxedUnit;;
NameAndType	UNIT:Lscala/runtime/BoxedUnit;
Field	scala/runtime/BoxedUnit.UNIT:Lscala/runtime/BoxedUnit;
Asciz	v1;
Asciz	Ljava/lang/Object;;
Asciz	scala/collection/mutable/Stack;
class	scala/collection/mutable/Stack
Asciz	push;
Asciz	(Ljava/lang/Object;)Lscala/collection/mutable/Stack;;
NameAndType	push:(Ljava/lang/Object;)Lscala/collection/mutable/Stack;
Method	scala/collection/mutable/Stack.push:(Ljava/lang/Object;)Lscala/collection/mutable/Stack;
Asciz	elem;
Asciz	(TA;)V;
Asciz	andThen;
Asciz	(Lscala/Function1;)Lscala/Function1;;
Asciz	(Lscala/Function1;Lscala/Function1;)Lscala/Function1;;
NameAndType	andThen:(Lscala/Function1;Lscala/Function1;)Lscala/Function1;
Method	scala/Function1$class.andThen:(Lscala/Function1;Lscala/Function1;)Lscala/Function1;
Asciz	g;
Asciz	Lscala/Function1;;
Asciz	compose;
NameAndType	compose:(Lscala/Function1;Lscala/Function1;)Lscala/Function1;
Method	scala/Function1$class.compose:(Lscala/Function1;Lscala/Function1;)Lscala/Function1;
Asciz	toString;
Asciz	()Ljava/lang/String;;
Asciz	(Lscala/Function1;)Ljava/lang/String;;
NameAndType	toString:(Lscala/Function1;)Ljava/lang/String;
Method	scala/Function1$class.toString:(Lscala/Function1;)Ljava/lang/String;
Asciz	Scala;
Asciz	InnerClasses;
Asciz	$anonfun$pushAll$2;
Asciz	scala/Function1;
class	scala/Function1
Asciz	scala/ScalaObject;
class	scala/ScalaObject
Asciz	java/io/Serializable;
class	java/io/Serializable

{
public static final long serialVersionUID;
  Signature: J

private final scala.collection.mutable.Stack $outer;
  Signature: Lscala/collection/mutable/Stack;

public static {};
  Signature: ()V
  Code:
   Stack=2, Locals=0, Args_size=0
	lconst_0
	putstatic	Field serialVersionUID:J
	return
  Labels:

public scala.collection.mutable.Stack$$anonfun$pushAll$2(scala.collection.mutable.Stack);
  Signature: (Lscala/collection/mutable/Stack;)V
  Code:
   Stack=2, Locals=2, Args_size=2
	aload_1
	ifnonnull	l1 // aload_0
	new	class java/lang/NullPointerException
	dup
	invokespecial	Method java/lang/NullPointerException."<init>":()V
	athrow
l1	aload_0
	aload_1
	putfield	Field $outer:Lscala/collection/mutable/Stack;
	aload_0
	invokespecial	Method java/lang/Object."<init>":()V
	aload_0
	invokestatic	Method scala/Function1$class.$init$:(Lscala/Function1;)V
	return
  Labels:
   	l1 = 12 // aload_0
  LocalVariableTable: 
   Start  Length  Slot  Name   Signature
   0      26      0    this       Lscala/collection/mutable/Stack$$anonfun$pushAll$2;
   0      26      1    $outer       Lscala/collection/mutable/Stack;

  Signature: length = 0x2
   00 23 

public final java.lang.Object apply(java.lang.Object);
  Signature: (Ljava/lang/Object;)Ljava/lang/Object;
  Code:
   Stack=2, Locals=3, Args_size=2
	aload_0
	getfield	Field $outer:Lscala/collection/mutable/Stack;
	astore_2
	aload_0
	aload_1
	invokevirtual	Method apply:(Ljava/lang/Object;)V
	getstatic	Field scala/runtime/BoxedUnit.UNIT:Lscala/runtime/BoxedUnit;
	areturn
  Labels:
  LocalVariableTable: 
   Start  Length  Slot  Name   Signature
   0      14      0    this       Lscala/collection/mutable/Stack$$anonfun$pushAll$2;
   5      9      1    v1       Ljava/lang/Object;


public final void apply(java.lang.Object);
  Signature: (Ljava/lang/Object;)V
  Code:
   Stack=2, Locals=3, Args_size=2
	aload_0
	getfield	Field $outer:Lscala/collection/mutable/Stack;
	astore_2
	aload_0
	getfield	Field $outer:Lscala/collection/mutable/Stack;
	aload_1
	invokevirtual	Method scala/collection/mutable/Stack.push:(Ljava/lang/Object;)Lscala/collection/mutable/Stack;
	pop
	return
  Labels:
  LocalVariableTable: 
   Start  Length  Slot  Name   Signature
   0      15      0    this       Lscala/collection/mutable/Stack$$anonfun$pushAll$2;
   5      10      1    elem       Ljava/lang/Object;

  Signature: length = 0x2
   00 39 

public scala.Function1 andThen(scala.Function1);
  Signature: (Lscala/Function1;)Lscala/Function1;
  Code:
   Stack=2, Locals=2, Args_size=2
	aload_0
	aload_1
	invokestatic	Method scala/Function1$class.andThen:(Lscala/Function1;Lscala/Function1;)Lscala/Function1;
	areturn
  Labels:
  LocalVariableTable: 
   Start  Length  Slot  Name   Signature
   0      6      0    this       Lscala/collection/mutable/Stack$$anonfun$pushAll$2;
   0      6      1    g       Lscala/Function1;


public scala.Function1 compose(scala.Function1);
  Signature: (Lscala/Function1;)Lscala/Function1;
  Code:
   Stack=2, Locals=2, Args_size=2
	aload_0
	aload_1
	invokestatic	Method scala/Function1$class.compose:(Lscala/Function1;Lscala/Function1;)Lscala/Function1;
	areturn
  Labels:
  LocalVariableTable: 
   Start  Length  Slot  Name   Signature
   0      6      0    this       Lscala/collection/mutable/Stack$$anonfun$pushAll$2;
   0      6      1    g       Lscala/Function1;


public java.lang.String toString();
  Signature: ()Ljava/lang/String;
  Code:
   Stack=1, Locals=1, Args_size=1
	aload_0
	invokestatic	Method scala/Function1$class.toString:(Lscala/Function1;)Ljava/lang/String;
	areturn
  Labels:

}

