Compiled from "StackProxy.scala"
public abstract class scala.collection.mutable.StackProxy$class extends java.lang.Object
  SourceFile: "StackProxy.scala"
  Scala: length = 0x
   
  InnerClass: 
   public final #101= #13 of #20; //$anon$1=class scala/collection/mutable/StackProxy$$anon$1 of class scala/collection/mutable/StackProxy
  minor version: 0
  major version: 49
  Constant pool:
const #1 = Asciz	SourceFile;
const #2 = Asciz	StackProxy.scala;
const #3 = Asciz	$init$;
const #4 = Asciz	(Lscala/collection/mutable/StackProxy;)V;
const #5 = Asciz	Code;
const #6 = Asciz	LineNumberTable;
const #7 = Asciz	$this;
const #8 = Asciz	Lscala/collection/mutable/StackProxy;;
const #9 = Asciz	LocalVariableTable;
const #10 = Asciz	clone;
const #11 = Asciz	(Lscala/collection/mutable/StackProxy;)Lscala/collection/mutable/Stack;;
const #12 = Asciz	scala/collection/mutable/StackProxy$$anon$1;
const #13 = class	#12;	//  scala/collection/mutable/StackProxy$$anon$1
const #14 = Asciz	<init>;
const #15 = NameAndType	#14:#4;//  "<init>":(Lscala/collection/mutable/StackProxy;)V
const #16 = Method	#13.#15;	//  scala/collection/mutable/StackProxy$$anon$1."<init>":(Lscala/collection/mutable/StackProxy;)V
const #17 = Asciz	toList;
const #18 = Asciz	(Lscala/collection/mutable/StackProxy;)Lscala/collection/immutable/List;;
const #19 = Asciz	scala/collection/mutable/StackProxy;
const #20 = class	#19;	//  scala/collection/mutable/StackProxy
const #21 = Asciz	self;
const #22 = Asciz	()Lscala/collection/mutable/Stack;;
const #23 = NameAndType	#21:#22;//  self:()Lscala/collection/mutable/Stack;
const #24 = InterfaceMethod	#20.#23;	//  scala/collection/mutable/StackProxy.self:()Lscala/collection/mutable/Stack;
const #25 = Asciz	scala/collection/mutable/Stack;
const #26 = class	#25;	//  scala/collection/mutable/Stack
const #27 = Asciz	()Lscala/collection/immutable/List;;
const #28 = NameAndType	#17:#27;//  toList:()Lscala/collection/immutable/List;
const #29 = Method	#26.#28;	//  scala/collection/mutable/Stack.toList:()Lscala/collection/immutable/List;
const #30 = Asciz	iterator;
const #31 = Asciz	(Lscala/collection/mutable/StackProxy;)Lscala/collection/Iterator;;
const #32 = Asciz	()Lscala/collection/Iterator;;
const #33 = NameAndType	#30:#32;//  iterator:()Lscala/collection/Iterator;
const #34 = Method	#26.#33;	//  scala/collection/mutable/Stack.iterator:()Lscala/collection/Iterator;
const #35 = Asciz	clear;
const #36 = Asciz	()V;
const #37 = NameAndType	#35:#36;//  clear:()V
const #38 = Method	#26.#37;	//  scala/collection/mutable/Stack.clear:()V
const #39 = Asciz	pop;
const #40 = Asciz	(Lscala/collection/mutable/StackProxy;)Ljava/lang/Object;;
const #41 = Asciz	()Ljava/lang/Object;;
const #42 = NameAndType	#39:#41;//  pop:()Ljava/lang/Object;
const #43 = Method	#26.#42;	//  scala/collection/mutable/Stack.pop:()Ljava/lang/Object;
const #44 = Asciz	top;
const #45 = NameAndType	#44:#41;//  top:()Ljava/lang/Object;
const #46 = Method	#26.#45;	//  scala/collection/mutable/Stack.top:()Ljava/lang/Object;
const #47 = Asciz	push;
const #48 = Asciz	(Lscala/collection/mutable/StackProxy;Ljava/lang/Object;Ljava/lang/Object;Lscala/collection/Seq;)Lscala/collection/mutable/StackProxy;;
const #49 = Asciz	(Ljava/lang/Object;)Lscala/collection/mutable/Stack;;
const #50 = NameAndType	#47:#49;//  push:(Ljava/lang/Object;)Lscala/collection/mutable/Stack;
const #51 = Method	#26.#50;	//  scala/collection/mutable/Stack.push:(Ljava/lang/Object;)Lscala/collection/mutable/Stack;
const #52 = Asciz	pushAll;
const #53 = Asciz	(Lscala/collection/Traversable;)Lscala/collection/mutable/Stack;;
const #54 = NameAndType	#52:#53;//  pushAll:(Lscala/collection/Traversable;)Lscala/collection/mutable/Stack;
const #55 = Method	#26.#54;	//  scala/collection/mutable/Stack.pushAll:(Lscala/collection/Traversable;)Lscala/collection/mutable/Stack;
const #56 = Asciz	elem1;
const #57 = Asciz	Ljava/lang/Object;;
const #58 = Asciz	elem2;
const #59 = Asciz	elems;
const #60 = Asciz	Lscala/collection/Seq;;
const #61 = Asciz	$plus$plus$eq;
const #62 = Asciz	(Lscala/collection/mutable/StackProxy;Lscala/collection/Iterator;)Lscala/collection/mutable/StackProxy;;
const #63 = Asciz	(Lscala/collection/Iterator;)Lscala/collection/mutable/Stack;;
const #64 = NameAndType	#61:#63;//  $plus$plus$eq:(Lscala/collection/Iterator;)Lscala/collection/mutable/Stack;
const #65 = Method	#26.#64;	//  scala/collection/mutable/Stack.$plus$plus$eq:(Lscala/collection/Iterator;)Lscala/collection/mutable/Stack;
const #66 = Asciz	it;
const #67 = Asciz	Lscala/collection/Iterator;;
const #68 = Asciz	Deprecated;
const #69 = Asciz	(Lscala/collection/mutable/StackProxy;Lscala/collection/Iterable;)Lscala/collection/mutable/StackProxy;;
const #70 = Asciz	(Lscala/collection/Iterable;)Lscala/collection/mutable/Stack;;
const #71 = NameAndType	#61:#70;//  $plus$plus$eq:(Lscala/collection/Iterable;)Lscala/collection/mutable/Stack;
const #72 = Method	#26.#71;	//  scala/collection/mutable/Stack.$plus$plus$eq:(Lscala/collection/Iterable;)Lscala/collection/mutable/Stack;
const #73 = Asciz	iter;
const #74 = Asciz	Lscala/collection/Iterable;;
const #75 = Asciz	(Lscala/collection/mutable/StackProxy;Lscala/collection/Traversable;)Lscala/collection/mutable/StackProxy;;
const #76 = Asciz	Lscala/collection/Traversable;;
const #77 = NameAndType	#52:#63;//  pushAll:(Lscala/collection/Iterator;)Lscala/collection/mutable/Stack;
const #78 = Method	#26.#77;	//  scala/collection/mutable/Stack.pushAll:(Lscala/collection/Iterator;)Lscala/collection/mutable/Stack;
const #79 = Asciz	$plus$eq;
const #80 = Asciz	(Lscala/collection/mutable/StackProxy;Ljava/lang/Object;)Lscala/collection/mutable/StackProxy;;
const #81 = Asciz	elem;
const #82 = Asciz	isEmpty;
const #83 = Asciz	(Lscala/collection/mutable/StackProxy;)Z;
const #84 = Asciz	()Z;
const #85 = NameAndType	#82:#84;//  isEmpty:()Z
const #86 = Method	#26.#85;	//  scala/collection/mutable/Stack.isEmpty:()Z
const #87 = Asciz	length;
const #88 = Asciz	(Lscala/collection/mutable/StackProxy;)I;
const #89 = Asciz	()I;
const #90 = NameAndType	#87:#89;//  length:()I
const #91 = Method	#26.#90;	//  scala/collection/mutable/Stack.length:()I
const #92 = Asciz	apply;
const #93 = Asciz	(Lscala/collection/mutable/StackProxy;I)Ljava/lang/Object;;
const #94 = Asciz	(I)Ljava/lang/Object;;
const #95 = NameAndType	#92:#94;//  apply:(I)Ljava/lang/Object;
const #96 = Method	#26.#95;	//  scala/collection/mutable/Stack.apply:(I)Ljava/lang/Object;
const #97 = Asciz	n;
const #98 = Asciz	I;
const #99 = Asciz	Scala;
const #100 = Asciz	InnerClasses;
const #101 = Asciz	$anon$1;
const #102 = Asciz	scala/collection/mutable/StackProxy$class;
const #103 = class	#102;	//  scala/collection/mutable/StackProxy$class
const #104 = Asciz	java/lang/Object;
const #105 = class	#104;	//  java/lang/Object

{
public static void $init$(scala.collection.mutable.StackProxy);
  Code:
   Stack=0, Locals=1, Args_size=1
   0:	return
  LineNumberTable: 
   line 22: 0

  LocalVariableTable: 
   Start  Length  Slot  Name   Signature
   0      1      0    $this       Lscala/collection/mutable/StackProxy;


public static scala.collection.mutable.Stack clone(scala.collection.mutable.StackProxy);
  Code:
   Stack=3, Locals=1, Args_size=1
   0:	new	#13; //class scala/collection/mutable/StackProxy$$anon$1
   3:	dup
   4:	aload_0
   5:	invokespecial	#16; //Method scala/collection/mutable/StackProxy$$anon$1."<init>":(Lscala/collection/mutable/StackProxy;)V
   8:	areturn
  LineNumberTable: 
   line 126: 0

  LocalVariableTable: 
   Start  Length  Slot  Name   Signature
   0      9      0    $this       Lscala/collection/mutable/StackProxy;


public static scala.collection.immutable.List toList(scala.collection.mutable.StackProxy);
  Code:
   Stack=1, Locals=1, Args_size=1
   0:	aload_0
   1:	invokeinterface	#24,  1; //InterfaceMethod scala/collection/mutable/StackProxy.self:()Lscala/collection/mutable/Stack;
   6:	invokevirtual	#29; //Method scala/collection/mutable/Stack.toList:()Lscala/collection/immutable/List;
   9:	areturn
  LineNumberTable: 
   line 120: 0

  LocalVariableTable: 
   Start  Length  Slot  Name   Signature
   0      10      0    $this       Lscala/collection/mutable/StackProxy;


public static scala.collection.Iterator iterator(scala.collection.mutable.StackProxy);
  Code:
   Stack=1, Locals=1, Args_size=1
   0:	aload_0
   1:	invokeinterface	#24,  1; //InterfaceMethod scala/collection/mutable/StackProxy.self:()Lscala/collection/mutable/Stack;
   6:	invokevirtual	#34; //Method scala/collection/mutable/Stack.iterator:()Lscala/collection/Iterator;
   9:	areturn
  LineNumberTable: 
   line 114: 0

  LocalVariableTable: 
   Start  Length  Slot  Name   Signature
   0      10      0    $this       Lscala/collection/mutable/StackProxy;


public static void clear(scala.collection.mutable.StackProxy);
  Code:
   Stack=1, Locals=1, Args_size=1
   0:	aload_0
   1:	invokeinterface	#24,  1; //InterfaceMethod scala/collection/mutable/StackProxy.self:()Lscala/collection/mutable/Stack;
   6:	invokevirtual	#38; //Method scala/collection/mutable/Stack.clear:()V
   9:	return
  LineNumberTable: 
   line 104: 0

  LocalVariableTable: 
   Start  Length  Slot  Name   Signature
   0      10      0    $this       Lscala/collection/mutable/StackProxy;


public static java.lang.Object pop(scala.collection.mutable.StackProxy);
  Code:
   Stack=1, Locals=1, Args_size=1
   0:	aload_0
   1:	invokeinterface	#24,  1; //InterfaceMethod scala/collection/mutable/StackProxy.self:()Lscala/collection/mutable/Stack;
   6:	invokevirtual	#43; //Method scala/collection/mutable/Stack.pop:()Ljava/lang/Object;
   9:	areturn
  LineNumberTable: 
   line 98: 0

  LocalVariableTable: 
   Start  Length  Slot  Name   Signature
   0      10      0    $this       Lscala/collection/mutable/StackProxy;


public static java.lang.Object top(scala.collection.mutable.StackProxy);
  Code:
   Stack=1, Locals=1, Args_size=1
   0:	aload_0
   1:	invokeinterface	#24,  1; //InterfaceMethod scala/collection/mutable/StackProxy.self:()Lscala/collection/mutable/Stack;
   6:	invokevirtual	#46; //Method scala/collection/mutable/Stack.top:()Ljava/lang/Object;
   9:	areturn
  LineNumberTable: 
   line 94: 0

  LocalVariableTable: 
   Start  Length  Slot  Name   Signature
   0      10      0    $this       Lscala/collection/mutable/StackProxy;


public static scala.collection.mutable.StackProxy push(scala.collection.mutable.StackProxy, java.lang.Object, java.lang.Object, scala.collection.Seq);
  Code:
   Stack=2, Locals=4, Args_size=4
   0:	aload_0
   1:	invokeinterface	#24,  1; //InterfaceMethod scala/collection/mutable/StackProxy.self:()Lscala/collection/mutable/Stack;
   6:	aload_1
   7:	invokevirtual	#51; //Method scala/collection/mutable/Stack.push:(Ljava/lang/Object;)Lscala/collection/mutable/Stack;
   10:	aload_2
   11:	invokevirtual	#51; //Method scala/collection/mutable/Stack.push:(Ljava/lang/Object;)Lscala/collection/mutable/Stack;
   14:	aload_3
   15:	invokevirtual	#55; //Method scala/collection/mutable/Stack.pushAll:(Lscala/collection/Traversable;)Lscala/collection/mutable/Stack;
   18:	pop
   19:	aload_0
   20:	areturn
  LineNumberTable: 
   line 84: 0
   line 85: 19

  LocalVariableTable: 
   Start  Length  Slot  Name   Signature
   0      21      0    $this       Lscala/collection/mutable/StackProxy;
   0      21      1    elem1       Ljava/lang/Object;
   0      21      2    elem2       Ljava/lang/Object;
   0      21      3    elems       Lscala/collection/Seq;


public static scala.collection.mutable.StackProxy $plus$plus$eq(scala.collection.mutable.StackProxy, scala.collection.Iterator);
  Code:
   Stack=2, Locals=2, Args_size=2
   0:	aload_0
   1:	invokeinterface	#24,  1; //InterfaceMethod scala/collection/mutable/StackProxy.self:()Lscala/collection/mutable/Stack;
   6:	aload_1
   7:	invokevirtual	#65; //Method scala/collection/mutable/Stack.$plus$plus$eq:(Lscala/collection/Iterator;)Lscala/collection/mutable/Stack;
   10:	pop
   11:	aload_0
   12:	areturn
  LineNumberTable: 
   line 79: 0
   line 80: 11

  LocalVariableTable: 
   Start  Length  Slot  Name   Signature
   0      13      0    $this       Lscala/collection/mutable/StackProxy;
   0      13      1    it       Lscala/collection/Iterator;

  Deprecated: true

public static scala.collection.mutable.StackProxy $plus$plus$eq(scala.collection.mutable.StackProxy, scala.collection.Iterable);
  Code:
   Stack=2, Locals=2, Args_size=2
   0:	aload_0
   1:	invokeinterface	#24,  1; //InterfaceMethod scala/collection/mutable/StackProxy.self:()Lscala/collection/mutable/Stack;
   6:	aload_1
   7:	invokevirtual	#72; //Method scala/collection/mutable/Stack.$plus$plus$eq:(Lscala/collection/Iterable;)Lscala/collection/mutable/Stack;
   10:	pop
   11:	aload_0
   12:	areturn
  LineNumberTable: 
   line 68: 0
   line 69: 11

  LocalVariableTable: 
   Start  Length  Slot  Name   Signature
   0      13      0    $this       Lscala/collection/mutable/StackProxy;
   0      13      1    iter       Lscala/collection/Iterable;

  Deprecated: true

public static scala.collection.mutable.StackProxy pushAll(scala.collection.mutable.StackProxy, scala.collection.Traversable);
  Code:
   Stack=2, Locals=2, Args_size=2
   0:	aload_0
   1:	invokeinterface	#24,  1; //InterfaceMethod scala/collection/mutable/StackProxy.self:()Lscala/collection/mutable/Stack;
   6:	aload_1
   7:	invokevirtual	#55; //Method scala/collection/mutable/Stack.pushAll:(Lscala/collection/Traversable;)Lscala/collection/mutable/Stack;
   10:	pop
   11:	aload_0
   12:	areturn
  LineNumberTable: 
   line 57: 0
   line 58: 11

  LocalVariableTable: 
   Start  Length  Slot  Name   Signature
   0      13      0    $this       Lscala/collection/mutable/StackProxy;
   0      13      1    elems       Lscala/collection/Traversable;


public static scala.collection.mutable.StackProxy pushAll(scala.collection.mutable.StackProxy, scala.collection.Iterator);
  Code:
   Stack=2, Locals=2, Args_size=2
   0:	aload_0
   1:	invokeinterface	#24,  1; //InterfaceMethod scala/collection/mutable/StackProxy.self:()Lscala/collection/mutable/Stack;
   6:	aload_1
   7:	invokevirtual	#78; //Method scala/collection/mutable/Stack.pushAll:(Lscala/collection/Iterator;)Lscala/collection/mutable/Stack;
   10:	pop
   11:	aload_0
   12:	areturn
  LineNumberTable: 
   line 52: 0
   line 53: 11

  LocalVariableTable: 
   Start  Length  Slot  Name   Signature
   0      13      0    $this       Lscala/collection/mutable/StackProxy;
   0      13      1    elems       Lscala/collection/Iterator;


public static scala.collection.mutable.StackProxy $plus$eq(scala.collection.mutable.StackProxy, java.lang.Object);
  Code:
   Stack=2, Locals=2, Args_size=2
   0:	aload_0
   1:	invokeinterface	#24,  1; //InterfaceMethod scala/collection/mutable/StackProxy.self:()Lscala/collection/mutable/Stack;
   6:	aload_1
   7:	invokevirtual	#51; //Method scala/collection/mutable/Stack.push:(Ljava/lang/Object;)Lscala/collection/mutable/Stack;
   10:	pop
   11:	aload_0
   12:	areturn
  LineNumberTable: 
   line 47: 0
   line 48: 11

  LocalVariableTable: 
   Start  Length  Slot  Name   Signature
   0      13      0    $this       Lscala/collection/mutable/StackProxy;
   0      13      1    elem       Ljava/lang/Object;


public static boolean isEmpty(scala.collection.mutable.StackProxy);
  Code:
   Stack=1, Locals=1, Args_size=1
   0:	aload_0
   1:	invokeinterface	#24,  1; //InterfaceMethod scala/collection/mutable/StackProxy.self:()Lscala/collection/mutable/Stack;
   6:	invokevirtual	#86; //Method scala/collection/mutable/Stack.isEmpty:()Z
   9:	ireturn
  LineNumberTable: 
   line 40: 0

  LocalVariableTable: 
   Start  Length  Slot  Name   Signature
   0      10      0    $this       Lscala/collection/mutable/StackProxy;


public static int length(scala.collection.mutable.StackProxy);
  Code:
   Stack=1, Locals=1, Args_size=1
   0:	aload_0
   1:	invokeinterface	#24,  1; //InterfaceMethod scala/collection/mutable/StackProxy.self:()Lscala/collection/mutable/Stack;
   6:	invokevirtual	#91; //Method scala/collection/mutable/Stack.length:()I
   9:	ireturn
  LineNumberTable: 
   line 34: 0

  LocalVariableTable: 
   Start  Length  Slot  Name   Signature
   0      10      0    $this       Lscala/collection/mutable/StackProxy;


public static java.lang.Object apply(scala.collection.mutable.StackProxy, int);
  Code:
   Stack=2, Locals=2, Args_size=2
   0:	aload_0
   1:	invokeinterface	#24,  1; //InterfaceMethod scala/collection/mutable/StackProxy.self:()Lscala/collection/mutable/Stack;
   6:	iload_1
   7:	invokevirtual	#96; //Method scala/collection/mutable/Stack.apply:(I)Ljava/lang/Object;
   10:	areturn
  LineNumberTable: 
   line 30: 0

  LocalVariableTable: 
   Start  Length  Slot  Name   Signature
   0      11      0    $this       Lscala/collection/mutable/StackProxy;
   0      11      1    n       I


}

