Compiled from "StringBuilder.scala"
public final class scala.collection.mutable.StringBuilder extends java.lang.Object implements scala.collection.mutable.Builder,scala.collection.mutable.IndexedSeq,scala.ScalaObject,java.io.Serializable
  SourceFile: "StringBuilder.scala"
  Signature: length = 0x2
   04 47 
  ScalaSig: length = 0xE42
   05 00 FFFFFF83 16 06 08 01 02 FFFFFF84 FFFFFF80 FFFFFF80 FFFFFF80 02 09 02 0D
   53 74 72 69 6E 67 42 75 69 6C 64 65 72 0A 02 03
   04 01 07 6D 75 74 61 62 6C 65 0A 02 05 06 01 0A
   63 6F 6C 6C 65 63 74 69 6F 6E 0A 01 07 01 05 73
   63 61 6C 61 03 00 13 05 00 0A 12 21 24 10 02 0B
   10 0D 01 0C 0A 02 0D 0E 01 04 6C 61 6E 67 0A 01
   0F 01 04 6A 61 76 61 09 02 11 0C 02 06 4F 62 6A
   65 63 74 10 04 13 14 16 1A 0D 01 02 09 02 15 02
   02 07 42 75 69 6C 64 65 72 10 02 17 18 0D 01 06
   09 02 19 06 02 04 43 68 61 72 10 02 1B 1E 0E 02
   17 1C 09 02 1D 06 01 06 50 72 65 64 65 66 09 02
   1F 20 02 06 53 74 72 69 6E 67 0A 02 1D 06 10 03
   13 22 16 09 02 23 02 02 0A 49 6E 64 65 78 65 64
   53 65 71 10 02 17 25 09 02 26 06 02 0B 53 63 61
   6C 61 4F 62 6A 65 63 74 08 08 28 00 FFFFFF82 FFFFFF80 FFFFFFA0 FFFFFF80
   04 29 01 0C 69 6E 69 74 43 61 70 61 63 69 74 79
   10 02 17 2A 09 02 2B 06 02 03 49 6E 74 08 08 2D
   00 FFFFFF82 FFFFFFC2 FFFFFF80 FFFFFF84 04 2E 01 09 69 6E 69 74 56 61 6C
   75 65 15 01 1A 08 08 30 00 FFFFFF82 FFFFFF80 FFFFFFA0 FFFFFF80 04 1A 01
   0A 69 6E 69 74 56 61 6C 75 65 20 08 05 32 00 FFFFFF84
   00 33 01 06 3C 69 6E 69 74 3E 14 03 34 35 36 10
   02 13 00 08 05 28 31 FFFFFFC0 00 29 08 05 2D 31 FFFFFFC0 00
   1A 08 07 38 00 FFFFFFC0 FFFFFF80 FFFFFF84 04 39 01 05 61 72 72 61
   79 15 01 3A 10 03 17 3B 16 09 02 3C 06 02 05 41
   72 72 61 79 08 07 3E 00 FFFFFFC0 FFFFFF80 FFFFFF84 04 3F 01 09 61
   72 72 61 79 5F 24 65 71 14 02 40 43 10 02 17 41
   09 02 42 06 02 04 55 6E 69 74 08 07 44 3D FFFFFF81 FFFFFF80
   FFFFFFC0 00 3A 01 03 78 24 31 08 06 46 00 FFFFFFA0 FFFFFFA0 04 3A
   01 06 61 72 72 61 79 20 08 07 48 00 FFFFFFC0 FFFFFF80 FFFFFF84 04
   49 01 05 63 6F 75 6E 74 15 01 29 08 07 4B 00 FFFFFFC0
   FFFFFF80 FFFFFF84 04 4C 01 09 63 6F 75 6E 74 5F 24 65 71 14
   02 40 4D 08 07 44 4A FFFFFF81 FFFFFF80 FFFFFFC0 00 29 08 06 4F 00
   FFFFFFA0 FFFFFFA0 04 29 01 06 63 6F 75 6E 74 20 08 05 32 00
   FFFFFF84 00 51 14 01 34 08 05 32 00 FFFFFF84 00 53 14 02 34
   54 08 05 55 52 FFFFFFC0 00 29 01 08 63 61 70 61 63 69
   74 79 08 05 32 00 FFFFFF84 00 57 14 02 34 58 08 05 59
   56 FFFFFFC0 00 1A 01 03 73 74 72 08 05 5B 00 FFFFFF84 00 39
   01 07 74 6F 41 72 72 61 79 08 05 5D 00 FFFFFF84 00 49
   01 06 6C 65 6E 67 74 68 08 05 5F 00 FFFFFF84 00 60 01
   0A 6C 65 6E 67 74 68 5F 24 65 71 14 02 40 61 08
   05 62 5E FFFFFFC0 00 29 01 01 6E 08 05 64 00 FFFFFF84 00 65
   01 05 63 6C 65 61 72 14 01 40 08 05 67 00 FFFFFF84 00
   68 01 09 73 65 74 4C 65 6E 67 74 68 14 02 40 69
   08 05 62 66 FFFFFFC0 00 29 08 05 55 00 FFFFFF84 00 49 08 05
   6C 00 FFFFFF84 00 6D 01 0C 63 61 70 61 63 69 74 79 5F
   24 65 71 14 02 40 6E 08 05 62 6B FFFFFFC0 00 29 28 03
   6B 70 73 10 02 17 71 09 02 72 06 02 0A 64 65 70
   72 65 63 61 74 65 64 21 01 74 01 65 75 73 65 20
   60 65 6E 73 75 72 65 43 61 70 61 63 69 74 79 27
   20 69 6E 73 74 65 61 64 2E 20 41 6E 20 61 73 73
   69 67 6E 6D 65 6E 74 20 69 73 20 6D 69 73 6C 65
   61 64 69 6E 67 20 62 65 63 61 75 73 65 0A 69 74
   20 63 61 6E 20 6E 65 76 65 72 20 64 65 63 72 65
   61 73 65 20 74 68 65 20 63 61 70 61 63 69 74 79
   2E 08 05 76 00 FFFFFF84 00 77 01 0E 65 6E 73 75 72 65
   43 61 70 61 63 69 74 79 14 02 40 78 08 05 62 75
   FFFFFFC0 00 29 08 05 7A 00 FFFFFF84 00 7B 01 06 63 68 61 72
   41 74 14 02 16 7C 08 05 7D 79 FFFFFFC0 00 29 01 05 69
   6E 64 65 78 08 06 7F 00 FFFFFF84 00 FFFFFF81 00 01 05 61 70
   70 6C 79 14 03 16 FFFFFF81 01 08 06 FFFFFF81 02 7E FFFFFFC0 00 29
   01 01 69 08 07 FFFFFF81 04 00 FFFFFF84 00 FFFFFF81 05 01 0C 64 65
   6C 65 74 65 43 68 61 72 41 74 14 03 34 FFFFFF81 06 08
   06 7D FFFFFF81 03 FFFFFFC0 00 29 08 07 FFFFFF81 08 00 FFFFFF84 00 FFFFFF81 09
   01 09 73 65 74 43 68 61 72 41 74 14 05 40 FFFFFF81 0A
   FFFFFF81 0B 08 06 7D FFFFFF81 07 FFFFFFC0 00 29 08 07 FFFFFF81 0C FFFFFF81 07
   FFFFFFC0 00 16 01 02 63 68 08 07 FFFFFF81 0E 00 FFFFFF84 00 FFFFFF81 0F
   01 06 75 70 64 61 74 65 14 05 40 FFFFFF81 10 FFFFFF81 11 08
   07 FFFFFF81 02 FFFFFF81 0D FFFFFFC0 00 29 08 07 FFFFFF81 12 FFFFFF81 0D FFFFFFC0 00
   16 01 01 63 08 07 FFFFFF81 14 00 FFFFFF84 00 FFFFFF81 15 01 09 73
   75 62 73 74 72 69 6E 67 14 03 1A FFFFFF81 16 08 07 FFFFFF81
   17 FFFFFF81 13 FFFFFFC0 00 29 01 05 73 74 61 72 74 08 07 FFFFFF81
   14 00 FFFFFF84 00 FFFFFF81 19 14 05 1A FFFFFF81 1A FFFFFF81 1B 08 07 FFFFFF81
   17 FFFFFF81 18 FFFFFFC0 00 29 08 07 FFFFFF81 1C FFFFFF81 18 FFFFFFC0 00 29 01
   03 65 6E 64 08 07 FFFFFF81 1E 00 FFFFFF84 00 FFFFFF81 1F 01 0B 73
   75 62 53 65 71 75 65 6E 63 65 14 06 FFFFFF81 20 FFFFFF81 23
   FFFFFF81 24 10 03 0B FFFFFF81 21 09 03 FFFFFF81 22 0C 02 0C 43 68
   61 72 53 65 71 75 65 6E 63 65 08 07 FFFFFF81 17 FFFFFF81 1D
   FFFFFFC0 00 29 08 07 FFFFFF81 1C FFFFFF81 1D FFFFFFC0 00 29 08 07 FFFFFF81 26
   00 FFFFFF84 00 FFFFFF81 27 01 08 24 70 6C 75 73 24 65 71 14
   04 FFFFFF81 28 FFFFFF81 29 0D 01 00 08 07 FFFFFF81 2A FFFFFF81 25 FFFFFFC0 00
   16 01 01 78 08 07 FFFFFF81 2C 00 FFFFFF84 00 FFFFFF81 2D 01 05 24
   70 6C 75 73 14 04 FFFFFF81 28 FFFFFF81 2E 08 07 FFFFFF81 2A FFFFFF81 2B
   FFFFFFC0 00 16 08 07 FFFFFF81 30 00 FFFFFF84 00 FFFFFF81 31 01 06 61 70
   70 65 6E 64 14 03 34 FFFFFF81 32 08 08 FFFFFF81 2A FFFFFF81 2F FFFFFFC0
   00 FFFFFF81 33 10 03 17 FFFFFF81 34 09 03 FFFFFF81 35 06 02 03 41
   6E 79 08 07 FFFFFF81 30 00 FFFFFF84 00 FFFFFF81 37 14 03 34 FFFFFF81 38
   08 07 FFFFFF81 39 FFFFFF81 36 FFFFFFC0 00 1A 01 01 73 08 07 FFFFFF81 30
   00 FFFFFF84 00 FFFFFF81 3B 14 03 34 FFFFFF81 3C 08 07 FFFFFF81 3D FFFFFF81 3A
   FFFFFFC0 00 34 01 02 73 62 08 07 FFFFFF81 3F 00 FFFFFF84 00 FFFFFF81 40
   01 09 61 70 70 65 6E 64 41 6C 6C 14 03 34 FFFFFF81 41
   08 08 FFFFFF81 2A FFFFFF81 3E FFFFFFC0 00 FFFFFF81 42 10 05 FFFFFF81 43 FFFFFF81 44
   16 0D 01 04 09 03 FFFFFF81 45 04 02 03 53 65 71 08 07
   FFFFFF81 30 00 FFFFFF84 00 FFFFFF81 47 14 03 34 FFFFFF81 48 08 08 FFFFFF81 2A
   FFFFFF81 46 FFFFFFC0 00 FFFFFF81 42 28 05 FFFFFF81 46 70 FFFFFF81 4A 21 02 FFFFFF81
   4B 01 66 75 73 65 20 61 70 70 65 6E 64 41 6C 6C
   20 69 6E 73 74 65 61 64 2E 20 54 68 69 73 20 6D
   65 74 68 6F 64 20 69 73 20 64 65 70 72 65 63 61
   74 65 64 20 62 65 63 61 75 73 65 20 6F 66 20 74
   68 65 0A 70 6F 73 73 69 62 6C 65 20 63 6F 6E 66
   75 73 69 6F 6E 20 77 69 74 68 20 60 61 70 70 65
   6E 64 28 41 6E 79 29 27 2E 08 07 FFFFFF81 3F 00 FFFFFF84 00
   FFFFFF81 4D 14 03 34 FFFFFF81 4E 08 07 FFFFFF81 2A FFFFFF81 4C FFFFFFC0 00 3A
   08 07 FFFFFF81 30 00 FFFFFF84 00 FFFFFF81 50 14 03 34 FFFFFF81 51 08 07
   FFFFFF81 2A FFFFFF81 4F FFFFFFC0 00 3A 28 05 FFFFFF81 4F 70 FFFFFF81 53 21 02
   FFFFFF81 54 01 66 75 73 65 20 61 70 70 65 6E 64 41 6C
   6C 20 69 6E 73 74 65 61 64 2E 20 54 68 69 73 20
   6D 65 74 68 6F 64 20 69 73 20 64 65 70 72 65 63
   61 74 65 64 20 62 65 63 61 75 73 65 0A 6F 66 20
   74 68 65 20 70 6F 73 73 69 62 6C 65 20 63 6F 6E
   66 75 73 69 6F 6E 20 77 69 74 68 20 60 61 70 70
   65 6E 64 28 41 6E 79 29 27 2E 08 07 FFFFFF81 3F 00 FFFFFF84
   00 FFFFFF81 56 14 07 34 FFFFFF81 57 FFFFFF81 58 FFFFFF81 5A 08 07 FFFFFF81 2A
   FFFFFF81 55 FFFFFFC0 00 3A 08 07 FFFFFF81 59 FFFFFF81 55 FFFFFFC0 00 29 01 06
   6F 66 66 73 65 74 08 07 FFFFFF81 5B FFFFFF81 55 FFFFFFC0 00 29 01
   03 6C 65 6E 08 07 FFFFFF81 30 00 FFFFFF84 00 FFFFFF81 5D 14 07 34
   FFFFFF81 5E FFFFFF81 5F FFFFFF81 60 08 07 FFFFFF81 2A FFFFFF81 5C FFFFFFC0 00 3A 08
   07 FFFFFF81 59 FFFFFF81 5C FFFFFFC0 00 29 08 07 FFFFFF81 5B FFFFFF81 5C FFFFFFC0 00
   29 28 05 FFFFFF81 5C 70 FFFFFF81 62 21 02 FFFFFF81 63 01 70 75 73
   65 20 61 70 70 65 6E 64 41 6C 6C 20 69 6E 73 74
   65 61 64 2E 20 54 68 69 73 20 6D 65 74 68 6F 64
   20 69 73 20 64 65 70 72 65 63 61 74 65 64 20 62
   65 63 61 75 73 65 0A 6F 66 20 74 68 65 20 70 6F
   73 73 69 62 6C 65 20 63 6F 6E 66 75 73 69 6F 6E
   20 77 69 74 68 20 60 61 70 70 65 6E 64 28 41 6E
   79 2C 20 49 6E 74 2C 20 49 6E 74 29 27 2E 08 07
   FFFFFF81 30 00 FFFFFF84 00 FFFFFF81 65 14 03 34 FFFFFF81 66 08 08 FFFFFF81 2A
   FFFFFF81 64 FFFFFFC0 00 FFFFFF81 67 10 03 17 FFFFFF81 68 09 03 FFFFFF81 69 06
   02 07 42 6F 6F 6C 65 61 6E 08 07 FFFFFF81 30 00 FFFFFF84 00
   FFFFFF81 6B 14 03 34 FFFFFF81 6C 08 08 FFFFFF81 2A FFFFFF81 6A FFFFFFC0 00 FFFFFF81
   6D 10 03 17 FFFFFF81 6E 09 03 FFFFFF81 6F 06 02 04 42 79 74
   65 08 07 FFFFFF81 30 00 FFFFFF84 00 FFFFFF81 71 14 03 34 FFFFFF81 72 08
   07 FFFFFF81 2A FFFFFF81 70 FFFFFFC0 00 16 08 07 FFFFFF81 30 00 FFFFFF84 00 FFFFFF81
   74 14 03 34 FFFFFF81 75 08 08 FFFFFF81 2A FFFFFF81 73 FFFFFFC0 00 FFFFFF81 76
   10 03 17 FFFFFF81 77 09 03 FFFFFF81 78 06 02 05 53 68 6F 72
   74 08 07 FFFFFF81 30 00 FFFFFF84 00 FFFFFF81 7A 14 03 34 FFFFFF81 7B 08
   07 FFFFFF81 2A FFFFFF81 79 FFFFFFC0 00 29 08 07 FFFFFF81 30 00 FFFFFF84 00 FFFFFF81
   7D 14 03 34 FFFFFF81 7E 08 08 FFFFFF81 2A FFFFFF81 7C FFFFFFC0 00 FFFFFF81 7F
   10 03 17 FFFFFF82 00 09 03 FFFFFF82 01 06 02 04 4C 6F 6E 67
   08 07 FFFFFF81 30 00 FFFFFF84 00 FFFFFF82 03 14 03 34 FFFFFF82 04 08 08
   FFFFFF81 2A FFFFFF82 02 FFFFFFC0 00 FFFFFF82 05 10 03 17 FFFFFF82 06 09 03 FFFFFF82
   07 06 02 05 46 6C 6F 61 74 08 07 FFFFFF81 30 00 FFFFFF84 00
   FFFFFF82 09 14 03 34 FFFFFF82 0A 08 08 FFFFFF81 2A FFFFFF82 08 FFFFFFC0 00 FFFFFF82
   0B 10 03 17 FFFFFF82 0C 09 03 FFFFFF82 0D 06 02 06 44 6F 75
   62 6C 65 08 07 FFFFFF82 0F 00 FFFFFF84 00 FFFFFF82 10 01 06 64 65
   6C 65 74 65 14 05 34 FFFFFF82 11 FFFFFF82 12 08 07 FFFFFF81 17 FFFFFF82
   0E FFFFFFC0 00 29 08 07 FFFFFF81 1C FFFFFF82 0E FFFFFFC0 00 29 08 07 FFFFFF82
   14 00 FFFFFF84 00 FFFFFF82 15 01 07 72 65 70 6C 61 63 65 14
   07 40 FFFFFF82 16 FFFFFF82 17 FFFFFF82 18 08 07 FFFFFF81 17 FFFFFF82 13 FFFFFFC0 00
   29 08 07 FFFFFF81 1C FFFFFF82 13 FFFFFFC0 00 29 08 06 59 FFFFFF82 13 FFFFFFC0
   00 1A 08 07 FFFFFF82 1A 00 FFFFFF84 00 FFFFFF82 1B 01 09 69 6E 73
   65 72 74 41 6C 6C 14 09 34 FFFFFF82 1C FFFFFF82 1D FFFFFF82 1E FFFFFF82
   1F 08 06 7D FFFFFF82 19 FFFFFFC0 00 29 08 06 59 FFFFFF82 19 FFFFFFC0 00
   3A 08 07 FFFFFF81 59 FFFFFF82 19 FFFFFFC0 00 29 08 07 FFFFFF81 5B FFFFFF82 19
   FFFFFFC0 00 29 08 07 FFFFFF82 21 00 FFFFFF84 00 FFFFFF82 22 01 06 69 6E
   73 65 72 74 14 09 34 FFFFFF82 23 FFFFFF82 24 FFFFFF82 25 FFFFFF82 26 08
   06 7D FFFFFF82 20 FFFFFFC0 00 29 08 06 59 FFFFFF82 20 FFFFFFC0 00 3A 08
   07 FFFFFF81 59 FFFFFF82 20 FFFFFFC0 00 29 08 07 FFFFFF81 5B FFFFFF82 20 FFFFFFC0 00
   29 28 05 FFFFFF82 20 70 FFFFFF82 28 21 02 FFFFFF82 29 01 75 75 73
   65 20 69 6E 73 65 72 74 41 6C 6C 20 69 6E 73 74
   65 61 64 2E 20 54 68 69 73 20 6D 65 74 68 6F 64
   20 69 73 20 64 65 70 72 65 63 61 74 65 64 20 62
   65 63 61 75 73 65 20 6F 66 20 74 68 65 0A 70 6F
   73 73 69 62 6C 65 20 63 6F 6E 66 75 73 69 6F 6E
   20 77 69 74 68 20 60 69 6E 73 65 72 74 28 49 6E
   74 2C 20 41 6E 79 2C 20 49 6E 74 2C 20 49 6E 74
   29 27 2E 08 07 FFFFFF82 21 00 FFFFFF84 00 FFFFFF82 2B 14 05 34 FFFFFF82
   2C FFFFFF82 2E 08 07 FFFFFF82 2D FFFFFF82 2A FFFFFFC0 00 29 01 02 61 74
   08 08 FFFFFF81 2A FFFFFF82 2A FFFFFFC0 00 FFFFFF81 33 08 07 FFFFFF82 21 00 FFFFFF84
   00 FFFFFF82 30 14 05 34 FFFFFF82 31 FFFFFF82 32 08 07 FFFFFF82 2D FFFFFF82 2F
   FFFFFFC0 00 29 08 07 FFFFFF81 2A FFFFFF82 2F FFFFFFC0 00 1A 08 07 FFFFFF82 1A
   00 FFFFFF84 00 FFFFFF82 34 14 05 34 FFFFFF82 35 FFFFFF82 36 08 07 FFFFFF82 2D
   FFFFFF82 33 FFFFFFC0 00 29 08 08 FFFFFF81 2A FFFFFF82 33 FFFFFFC0 00 FFFFFF81 42 08
   07 FFFFFF82 21 00 FFFFFF84 00 FFFFFF82 38 14 05 34 FFFFFF82 39 FFFFFF82 3A 08
   07 FFFFFF82 2D FFFFFF82 37 FFFFFFC0 00 29 08 08 FFFFFF81 2A FFFFFF82 37 FFFFFFC0 00
   FFFFFF81 42 28 05 FFFFFF82 37 70 FFFFFF82 3C 21 02 FFFFFF82 3D 01 6B 75
   73 65 20 69 6E 73 65 72 74 41 6C 6C 20 69 6E 73
   74 65 61 64 2E 20 54 68 69 73 20 6D 65 74 68 6F
   64 20 69 73 20 64 65 70 72 65 63 61 74 65 64 20
   62 65 63 61 75 73 65 20 6F 66 0A 74 68 65 20 70
   6F 73 73 69 62 6C 65 20 63 6F 6E 66 75 73 69 6F
   6E 20 77 69 74 68 20 60 69 6E 73 65 72 74 28 49
   6E 74 2C 20 41 6E 79 29 27 2E 08 07 FFFFFF82 1A 00 FFFFFF84
   00 FFFFFF82 3F 14 05 34 FFFFFF82 40 FFFFFF82 41 08 07 FFFFFF82 2D FFFFFF82 3E
   FFFFFFC0 00 29 08 07 FFFFFF81 2A FFFFFF82 3E FFFFFFC0 00 3A 08 07 FFFFFF82 21
   00 FFFFFF84 00 FFFFFF82 43 14 05 34 FFFFFF82 44 FFFFFF82 45 08 07 FFFFFF82 2D
   FFFFFF82 42 FFFFFFC0 00 29 08 07 FFFFFF81 2A FFFFFF82 42 FFFFFFC0 00 3A 28 05
   FFFFFF82 42 70 FFFFFF82 3C 08 07 FFFFFF82 21 00 FFFFFF84 00 FFFFFF82 48 14 05
   34 FFFFFF82 49 FFFFFF82 4A 08 07 FFFFFF82 2D FFFFFF82 47 FFFFFFC0 00 29 08 08
   FFFFFF81 2A FFFFFF82 47 FFFFFFC0 00 FFFFFF81 67 08 07 FFFFFF82 21 00 FFFFFF84 00 FFFFFF82
   4C 14 05 34 FFFFFF82 4D FFFFFF82 4E 08 07 FFFFFF82 2D FFFFFF82 4B FFFFFFC0 00
   29 08 08 FFFFFF81 2A FFFFFF82 4B FFFFFFC0 00 FFFFFF81 6D 08 07 FFFFFF82 21 00
   FFFFFF84 00 FFFFFF82 50 14 05 34 FFFFFF82 51 FFFFFF82 52 08 07 FFFFFF82 2D FFFFFF82
   4F FFFFFFC0 00 29 08 07 FFFFFF81 2A FFFFFF82 4F FFFFFFC0 00 16 08 07 FFFFFF82
   21 00 FFFFFF84 00 FFFFFF82 54 14 05 34 FFFFFF82 55 FFFFFF82 56 08 07 FFFFFF82
   2D FFFFFF82 53 FFFFFFC0 00 29 08 08 FFFFFF81 2A FFFFFF82 53 FFFFFFC0 00 FFFFFF81 76
   08 07 FFFFFF82 21 00 FFFFFF84 00 FFFFFF82 58 14 05 34 FFFFFF82 59 FFFFFF82 5A
   08 07 FFFFFF82 2D FFFFFF82 57 FFFFFFC0 00 29 08 07 FFFFFF81 2A FFFFFF82 57 FFFFFFC0
   00 29 08 07 FFFFFF82 21 00 FFFFFF84 00 FFFFFF82 5C 14 05 34 FFFFFF82 5D
   FFFFFF82 5E 08 07 FFFFFF82 2D FFFFFF82 5B FFFFFFC0 00 29 08 08 FFFFFF81 2A FFFFFF82
   5B FFFFFFC0 00 FFFFFF81 7F 08 07 FFFFFF82 21 00 FFFFFF84 00 FFFFFF82 60 14 05
   34 FFFFFF82 61 FFFFFF82 62 08 07 FFFFFF82 2D FFFFFF82 5F FFFFFFC0 00 29 08 08
   FFFFFF81 2A FFFFFF82 5F FFFFFFC0 00 FFFFFF82 05 08 07 FFFFFF82 21 00 FFFFFF84 00 FFFFFF82
   64 14 05 34 FFFFFF82 65 FFFFFF82 66 08 07 FFFFFF82 2D FFFFFF82 63 FFFFFFC0 00
   29 08 08 FFFFFF81 2A FFFFFF82 63 FFFFFFC0 00 FFFFFF82 0B 08 07 FFFFFF82 68 00
   FFFFFF84 00 FFFFFF82 69 01 07 69 6E 64 65 78 4F 66 14 03 29
   FFFFFF82 6A 08 06 59 FFFFFF82 67 FFFFFFC0 00 1A 08 07 FFFFFF82 68 00 FFFFFF84
   00 FFFFFF82 6C 14 05 29 FFFFFF82 6D FFFFFF82 6E 08 06 59 FFFFFF82 6B FFFFFFC0
   00 1A 08 07 FFFFFF82 6F FFFFFF82 6B FFFFFFC0 00 29 01 09 66 72 6F
   6D 49 6E 64 65 78 08 07 FFFFFF82 71 00 FFFFFF84 00 FFFFFF82 72 01
   0B 6C 61 73 74 49 6E 64 65 78 4F 66 14 03 29 FFFFFF82
   73 08 06 59 FFFFFF82 70 FFFFFFC0 00 1A 08 07 FFFFFF82 71 00 FFFFFF84 00
   FFFFFF82 75 14 05 29 FFFFFF82 76 FFFFFF82 77 08 06 59 FFFFFF82 74 FFFFFFC0 00
   1A 08 07 FFFFFF82 6F FFFFFF82 74 FFFFFFC0 00 29 08 06 FFFFFF82 79 00 FFFFFF84
   20 51 01 07 72 65 76 65 72 73 65 08 07 FFFFFF82 7B 00
   FFFFFF84 20 FFFFFF82 7C 01 08 74 6F 53 74 72 69 6E 67 14 01
   1A 08 07 FFFFFF82 7E 00 FFFFFF84 00 FFFFFF82 7C 01 06 72 65 73 75
   6C 74 28 05 00 FFFFFF83 00 FFFFFF83 03 10 03 17 FFFFFF83 01 09 03
   FFFFFF83 02 06 02 10 53 65 72 69 61 6C 56 65 72 73 69
   6F 6E 55 49 44 1E 08 FFFFFF89 FFFFFFAF FFFFFFAA 01 FFFFFFAF FFFFFFD6 FFFFFFD4 FFFFFFF1 28
   03 00 FFFFFF83 05 10 03 17 FFFFFF83 06 09 03 FFFFFF83 07 06 02 0C
   73 65 72 69 61 6C 69 7A 61 62 6C 65 07 07 FFFFFF83 09
   02 FFFFFF88 02 FFFFFF83 0A 01 0D 53 74 72 69 6E 67 42 75 69
   6C 64 65 72 10 03 13 FFFFFF83 0B 06 09 01 02 FFFFFF84 FFFFFF80 FFFFFF80
   FFFFFF88 02 FFFFFF83 0C 13 04 FFFFFF83 0B 0A 24 08 07 32 FFFFFF83 0B FFFFFF84
   00 FFFFFF83 0E 14 02 FFFFFF83 0A 08 08 FFFFFF83 10 FFFFFF83 0B FFFFFF84 04 FFFFFF83
   11 01 06 63 6F 70 79 4F 66 14 05 3A FFFFFF83 12 FFFFFF83 14
   08 07 FFFFFF83 13 FFFFFF83 0F FFFFFFC0 00 3A 01 03 73 72 63 08 07
   FFFFFF83 15 FFFFFF83 0F FFFFFFC0 00 29 01 09 6E 65 77 4C 65 6E 67
   74 68 
  InnerClass: 
   public #1100= #1099 of #277; //WithFilter=class scala/collection/TraversableLike$WithFilter of class scala/collection/TraversableLike
   public final #1101= #478 of #11; //$anonfun$setLength$1=class scala/collection/mutable/StringBuilder$$anonfun$setLength$1 of class scala/collection/mutable/StringBuilder
  minor version: 0
  major version: 49
  Constant pool:
const #1 = Asciz	SourceFile;
const #2 = Asciz	StringBuilder.scala;
const #3 = Asciz	<clinit>;
const #4 = Asciz	()V;
const #5 = Asciz	Code;
const #6 = Asciz	serialVersionUID;
const #7 = Asciz	J;
const #8 = long	-8525408645367278351l;
const #10 = Asciz	scala/collection/mutable/StringBuilder;
const #11 = class	#10;	//  scala/collection/mutable/StringBuilder
const #12 = NameAndType	#6:#7;//  serialVersionUID:J
const #13 = Field	#11.#12;	//  scala/collection/mutable/StringBuilder.serialVersionUID:J
const #14 = Asciz	count;
const #15 = Asciz	I;
const #16 = Asciz	array;
const #17 = Asciz	[C;
const #18 = Asciz	initValue;
const #19 = Asciz	Ljava/lang/String;;
const #20 = Asciz	<init>;
const #21 = Asciz	(ILjava/lang/String;)V;
const #22 = Asciz	LineNumberTable;
const #23 = NameAndType	#18:#19;//  initValue:Ljava/lang/String;
const #24 = Field	#11.#23;	//  scala/collection/mutable/StringBuilder.initValue:Ljava/lang/String;
const #25 = Asciz	java/lang/Object;
const #26 = class	#25;	//  java/lang/Object
const #27 = NameAndType	#20:#4;//  "<init>":()V
const #28 = Method	#26.#27;	//  java/lang/Object."<init>":()V
const #29 = Asciz	scala/collection/generic/Growable$class;
const #30 = class	#29;	//  scala/collection/generic/Growable$class
const #31 = Asciz	$init$;
const #32 = Asciz	(Lscala/collection/generic/Growable;)V;
const #33 = NameAndType	#31:#32;//  $init$:(Lscala/collection/generic/Growable;)V
const #34 = Method	#30.#33;	//  scala/collection/generic/Growable$class.$init$:(Lscala/collection/generic/Growable;)V
const #35 = Asciz	scala/collection/mutable/Builder$class;
const #36 = class	#35;	//  scala/collection/mutable/Builder$class
const #37 = Asciz	(Lscala/collection/mutable/Builder;)V;
const #38 = NameAndType	#31:#37;//  $init$:(Lscala/collection/mutable/Builder;)V
const #39 = Method	#36.#38;	//  scala/collection/mutable/Builder$class.$init$:(Lscala/collection/mutable/Builder;)V
const #40 = Asciz	scala/collection/TraversableLike$class;
const #41 = class	#40;	//  scala/collection/TraversableLike$class
const #42 = Asciz	(Lscala/collection/TraversableLike;)V;
const #43 = NameAndType	#31:#42;//  $init$:(Lscala/collection/TraversableLike;)V
const #44 = Method	#41.#43;	//  scala/collection/TraversableLike$class.$init$:(Lscala/collection/TraversableLike;)V
const #45 = Asciz	scala/collection/generic/GenericTraversableTemplate$class;
const #46 = class	#45;	//  scala/collection/generic/GenericTraversableTemplate$class
const #47 = Asciz	(Lscala/collection/generic/GenericTraversableTemplate;)V;
const #48 = NameAndType	#31:#47;//  $init$:(Lscala/collection/generic/GenericTraversableTemplate;)V
const #49 = Method	#46.#48;	//  scala/collection/generic/GenericTraversableTemplate$class.$init$:(Lscala/collection/generic/GenericTraversableTemplate;)V
const #50 = Asciz	scala/collection/Traversable$class;
const #51 = class	#50;	//  scala/collection/Traversable$class
const #52 = Asciz	(Lscala/collection/Traversable;)V;
const #53 = NameAndType	#31:#52;//  $init$:(Lscala/collection/Traversable;)V
const #54 = Method	#51.#53;	//  scala/collection/Traversable$class.$init$:(Lscala/collection/Traversable;)V
const #55 = Asciz	scala/collection/mutable/Traversable$class;
const #56 = class	#55;	//  scala/collection/mutable/Traversable$class
const #57 = Asciz	(Lscala/collection/mutable/Traversable;)V;
const #58 = NameAndType	#31:#57;//  $init$:(Lscala/collection/mutable/Traversable;)V
const #59 = Method	#56.#58;	//  scala/collection/mutable/Traversable$class.$init$:(Lscala/collection/mutable/Traversable;)V
const #60 = Asciz	scala/collection/IterableLike$class;
const #61 = class	#60;	//  scala/collection/IterableLike$class
const #62 = Asciz	(Lscala/collection/IterableLike;)V;
const #63 = NameAndType	#31:#62;//  $init$:(Lscala/collection/IterableLike;)V
const #64 = Method	#61.#63;	//  scala/collection/IterableLike$class.$init$:(Lscala/collection/IterableLike;)V
const #65 = Asciz	scala/collection/Iterable$class;
const #66 = class	#65;	//  scala/collection/Iterable$class
const #67 = Asciz	(Lscala/collection/Iterable;)V;
const #68 = NameAndType	#31:#67;//  $init$:(Lscala/collection/Iterable;)V
const #69 = Method	#66.#68;	//  scala/collection/Iterable$class.$init$:(Lscala/collection/Iterable;)V
const #70 = Asciz	scala/collection/mutable/Iterable$class;
const #71 = class	#70;	//  scala/collection/mutable/Iterable$class
const #72 = Asciz	(Lscala/collection/mutable/Iterable;)V;
const #73 = NameAndType	#31:#72;//  $init$:(Lscala/collection/mutable/Iterable;)V
const #74 = Method	#71.#73;	//  scala/collection/mutable/Iterable$class.$init$:(Lscala/collection/mutable/Iterable;)V
const #75 = Asciz	scala/Function1$class;
const #76 = class	#75;	//  scala/Function1$class
const #77 = Asciz	(Lscala/Function1;)V;
const #78 = NameAndType	#31:#77;//  $init$:(Lscala/Function1;)V
const #79 = Method	#76.#78;	//  scala/Function1$class.$init$:(Lscala/Function1;)V
const #80 = Asciz	scala/PartialFunction$class;
const #81 = class	#80;	//  scala/PartialFunction$class
const #82 = Asciz	(Lscala/PartialFunction;)V;
const #83 = NameAndType	#31:#82;//  $init$:(Lscala/PartialFunction;)V
const #84 = Method	#81.#83;	//  scala/PartialFunction$class.$init$:(Lscala/PartialFunction;)V
const #85 = Asciz	scala/collection/SeqLike$class;
const #86 = class	#85;	//  scala/collection/SeqLike$class
const #87 = Asciz	(Lscala/collection/SeqLike;)V;
const #88 = NameAndType	#31:#87;//  $init$:(Lscala/collection/SeqLike;)V
const #89 = Method	#86.#88;	//  scala/collection/SeqLike$class.$init$:(Lscala/collection/SeqLike;)V
const #90 = Asciz	scala/collection/Seq$class;
const #91 = class	#90;	//  scala/collection/Seq$class
const #92 = Asciz	(Lscala/collection/Seq;)V;
const #93 = NameAndType	#31:#92;//  $init$:(Lscala/collection/Seq;)V
const #94 = Method	#91.#93;	//  scala/collection/Seq$class.$init$:(Lscala/collection/Seq;)V
const #95 = Asciz	scala/collection/mutable/Seq$class;
const #96 = class	#95;	//  scala/collection/mutable/Seq$class
const #97 = Asciz	(Lscala/collection/mutable/Seq;)V;
const #98 = NameAndType	#31:#97;//  $init$:(Lscala/collection/mutable/Seq;)V
const #99 = Method	#96.#98;	//  scala/collection/mutable/Seq$class.$init$:(Lscala/collection/mutable/Seq;)V
const #100 = Asciz	scala/collection/IndexedSeqLike$class;
const #101 = class	#100;	//  scala/collection/IndexedSeqLike$class
const #102 = Asciz	(Lscala/collection/IndexedSeqLike;)V;
const #103 = NameAndType	#31:#102;//  $init$:(Lscala/collection/IndexedSeqLike;)V
const #104 = Method	#101.#103;	//  scala/collection/IndexedSeqLike$class.$init$:(Lscala/collection/IndexedSeqLike;)V
const #105 = Asciz	scala/collection/IndexedSeq$class;
const #106 = class	#105;	//  scala/collection/IndexedSeq$class
const #107 = Asciz	(Lscala/collection/IndexedSeq;)V;
const #108 = NameAndType	#31:#107;//  $init$:(Lscala/collection/IndexedSeq;)V
const #109 = Method	#106.#108;	//  scala/collection/IndexedSeq$class.$init$:(Lscala/collection/IndexedSeq;)V
const #110 = Asciz	scala/collection/mutable/IndexedSeqLike$class;
const #111 = class	#110;	//  scala/collection/mutable/IndexedSeqLike$class
const #112 = Asciz	(Lscala/collection/mutable/IndexedSeqLike;)V;
const #113 = NameAndType	#31:#112;//  $init$:(Lscala/collection/mutable/IndexedSeqLike;)V
const #114 = Method	#111.#113;	//  scala/collection/mutable/IndexedSeqLike$class.$init$:(Lscala/collection/mutable/IndexedSeqLike;)V
const #115 = Asciz	scala/collection/mutable/IndexedSeq$class;
const #116 = class	#115;	//  scala/collection/mutable/IndexedSeq$class
const #117 = Asciz	(Lscala/collection/mutable/IndexedSeq;)V;
const #118 = NameAndType	#31:#117;//  $init$:(Lscala/collection/mutable/IndexedSeq;)V
const #119 = Method	#116.#118;	//  scala/collection/mutable/IndexedSeq$class.$init$:(Lscala/collection/mutable/IndexedSeq;)V
const #120 = Asciz	scala/Predef$;
const #121 = class	#120;	//  scala/Predef$
const #122 = Asciz	MODULE$;
const #123 = Asciz	Lscala/Predef$;;
const #124 = NameAndType	#122:#123;//  MODULE$:Lscala/Predef$;
const #125 = Field	#121.#124;	//  scala/Predef$.MODULE$:Lscala/Predef$;
const #126 = Asciz	require;
const #127 = Asciz	(Z)V;
const #128 = NameAndType	#126:#127;//  require:(Z)V
const #129 = Method	#121.#128;	//  scala/Predef$.require:(Z)V
const #130 = Asciz	java/lang/String;
const #131 = class	#130;	//  java/lang/String
const #132 = Asciz	length;
const #133 = Asciz	()I;
const #134 = NameAndType	#132:#133;//  length:()I
const #135 = Method	#131.#134;	//  java/lang/String.length:()I
const #136 = NameAndType	#16:#17;//  array:[C
const #137 = Field	#11.#136;	//  scala/collection/mutable/StringBuilder.array:[C
const #138 = NameAndType	#14:#15;//  count:I
const #139 = Field	#11.#138;	//  scala/collection/mutable/StringBuilder.count:I
const #140 = Asciz	append;
const #141 = Asciz	(Ljava/lang/String;)Lscala/collection/mutable/StringBuilder;;
const #142 = NameAndType	#140:#141;//  append:(Ljava/lang/String;)Lscala/collection/mutable/StringBuilder;
const #143 = Method	#11.#142;	//  scala/collection/mutable/StringBuilder.append:(Ljava/lang/String;)Lscala/collection/mutable/StringBuilder;
const #144 = Asciz	this;
const #145 = Asciz	Lscala/collection/mutable/StringBuilder;;
const #146 = Asciz	initCapacity;
const #147 = Asciz	LocalVariableTable;
const #148 = Asciz	apply;
const #149 = Asciz	(I)Ljava/lang/Object;;
const #150 = Asciz	(I)C;
const #151 = NameAndType	#148:#150;//  apply:(I)C
const #152 = Method	#11.#151;	//  scala/collection/mutable/StringBuilder.apply:(I)C
const #153 = Asciz	scala/runtime/BoxesRunTime;
const #154 = class	#153;	//  scala/runtime/BoxesRunTime
const #155 = Asciz	boxToCharacter;
const #156 = Asciz	(C)Ljava/lang/Character;;
const #157 = NameAndType	#155:#156;//  boxToCharacter:(C)Ljava/lang/Character;
const #158 = Method	#154.#157;	//  scala/runtime/BoxesRunTime.boxToCharacter:(C)Ljava/lang/Character;
const #159 = Asciz	idx;
const #160 = Asciz	(Ljava/lang/Object;)Ljava/lang/Object;;
const #161 = Asciz	unboxToInt;
const #162 = Asciz	(Ljava/lang/Object;)I;
const #163 = NameAndType	#161:#162;//  unboxToInt:(Ljava/lang/Object;)I
const #164 = Method	#154.#163;	//  scala/runtime/BoxesRunTime.unboxToInt:(Ljava/lang/Object;)I
const #165 = Asciz	v1;
const #166 = Asciz	Ljava/lang/Object;;
const #167 = Asciz	update;
const #168 = Asciz	(ILjava/lang/Object;)V;
const #169 = Asciz	unboxToChar;
const #170 = Asciz	(Ljava/lang/Object;)C;
const #171 = NameAndType	#169:#170;//  unboxToChar:(Ljava/lang/Object;)C
const #172 = Method	#154.#171;	//  scala/runtime/BoxesRunTime.unboxToChar:(Ljava/lang/Object;)C
const #173 = Asciz	(IC)V;
const #174 = NameAndType	#167:#173;//  update:(IC)V
const #175 = Method	#11.#174;	//  scala/collection/mutable/StringBuilder.update:(IC)V
const #176 = Asciz	elem;
const #177 = Asciz	$plus$eq;
const #178 = Asciz	(Ljava/lang/Object;)Lscala/collection/mutable/Builder;;
const #179 = Asciz	(C)Lscala/collection/mutable/StringBuilder;;
const #180 = NameAndType	#177:#179;//  $plus$eq:(C)Lscala/collection/mutable/StringBuilder;
const #181 = Method	#11.#180;	//  scala/collection/mutable/StringBuilder.$plus$eq:(C)Lscala/collection/mutable/StringBuilder;
const #182 = Asciz	(Ljava/lang/Object;)Lscala/collection/generic/Growable;;
const #183 = Asciz	reverse;
const #184 = Asciz	()Ljava/lang/Object;;
const #185 = Asciz	()Lscala/collection/mutable/StringBuilder;;
const #186 = NameAndType	#183:#185;//  reverse:()Lscala/collection/mutable/StringBuilder;
const #187 = Method	#11.#186;	//  scala/collection/mutable/StringBuilder.reverse:()Lscala/collection/mutable/StringBuilder;
const #188 = Asciz	result;
const #189 = Asciz	()Ljava/lang/String;;
const #190 = NameAndType	#188:#189;//  result:()Ljava/lang/String;
const #191 = Method	#11.#190;	//  scala/collection/mutable/StringBuilder.result:()Ljava/lang/String;
const #192 = Asciz	thisCollection;
const #193 = Asciz	()Lscala/collection/IndexedSeq;;
const #194 = Asciz	scala/collection/mutable/IndexedSeqLike;
const #195 = class	#194;	//  scala/collection/mutable/IndexedSeqLike
const #196 = Asciz	()Lscala/collection/mutable/IndexedSeq;;
const #197 = NameAndType	#192:#196;//  thisCollection:()Lscala/collection/mutable/IndexedSeq;
const #198 = InterfaceMethod	#195.#197;	//  scala/collection/mutable/IndexedSeqLike.thisCollection:()Lscala/collection/mutable/IndexedSeq;
const #199 = Asciz	()Lscala/collection/Seq;;
const #200 = Asciz	()Lscala/collection/Iterable;;
const #201 = Asciz	()Lscala/collection/Traversable;;
const #202 = Asciz	toCollection;
const #203 = Asciz	(Ljava/lang/Object;)Lscala/collection/IndexedSeq;;
const #204 = Asciz	(Ljava/lang/Object;)Lscala/collection/mutable/IndexedSeq;;
const #205 = NameAndType	#202:#204;//  toCollection:(Ljava/lang/Object;)Lscala/collection/mutable/IndexedSeq;
const #206 = InterfaceMethod	#195.#205;	//  scala/collection/mutable/IndexedSeqLike.toCollection:(Ljava/lang/Object;)Lscala/collection/mutable/IndexedSeq;
const #207 = Asciz	repr;
const #208 = Asciz	(Ljava/lang/Object;)Lscala/collection/Seq;;
const #209 = Asciz	(Ljava/lang/Object;)Lscala/collection/Iterable;;
const #210 = Asciz	(Ljava/lang/Object;)Lscala/collection/Traversable;;
const #211 = Asciz	view;
const #212 = Asciz	(II)Lscala/collection/IndexedSeqView;;
const #213 = Asciz	(II)Lscala/collection/mutable/IndexedSeqView;;
const #214 = NameAndType	#211:#213;//  view:(II)Lscala/collection/mutable/IndexedSeqView;
const #215 = InterfaceMethod	#195.#214;	//  scala/collection/mutable/IndexedSeqLike.view:(II)Lscala/collection/mutable/IndexedSeqView;
const #216 = Asciz	from;
const #217 = Asciz	until;
const #218 = Asciz	(II)Lscala/collection/SeqView;;
const #219 = Asciz	(II)Lscala/collection/IterableView;;
const #220 = Asciz	(II)Lscala/collection/TraversableView;;
const #221 = Asciz	isDefinedAt;
const #222 = Asciz	(Ljava/lang/Object;)Z;
const #223 = Asciz	scala/collection/SeqLike;
const #224 = class	#223;	//  scala/collection/SeqLike
const #225 = Asciz	(I)Z;
const #226 = NameAndType	#221:#225;//  isDefinedAt:(I)Z
const #227 = InterfaceMethod	#224.#226;	//  scala/collection/SeqLike.isDefinedAt:(I)Z
const #228 = Asciz	x;
const #229 = Asciz	andThen;
const #230 = Asciz	(Lscala/Function1;)Lscala/Function1;;
const #231 = Asciz	scala/PartialFunction;
const #232 = class	#231;	//  scala/PartialFunction
const #233 = Asciz	(Lscala/Function1;)Lscala/PartialFunction;;
const #234 = NameAndType	#229:#233;//  andThen:(Lscala/Function1;)Lscala/PartialFunction;
const #235 = InterfaceMethod	#232.#234;	//  scala/PartialFunction.andThen:(Lscala/Function1;)Lscala/PartialFunction;
const #236 = Asciz	g;
const #237 = Asciz	Lscala/Function1;;
const #238 = Asciz	toString;
const #239 = NameAndType	#238:#189;//  toString:()Ljava/lang/String;
const #240 = Method	#11.#239;	//  scala/collection/mutable/StringBuilder.toString:()Ljava/lang/String;
const #241 = Asciz	()[C;
const #242 = NameAndType	#16:#241;//  array:()[C
const #243 = Method	#11.#242;	//  scala/collection/mutable/StringBuilder.array:()[C
const #244 = NameAndType	#14:#133;//  count:()I
const #245 = Method	#11.#244;	//  scala/collection/mutable/StringBuilder.count:()I
const #246 = Asciz	([CII)V;
const #247 = NameAndType	#20:#246;//  "<init>":([CII)V
const #248 = Method	#131.#247;	//  java/lang/String."<init>":([CII)V
const #249 = int	55296;
const #250 = int	57343;
const #251 = Asciz	java/lang/Character;
const #252 = class	#251;	//  java/lang/Character
const #253 = Asciz	isLowSurrogate;
const #254 = Asciz	(C)Z;
const #255 = NameAndType	#253:#254;//  isLowSurrogate:(C)Z
const #256 = Method	#252.#255;	//  java/lang/Character.isLowSurrogate:(C)Z
const #257 = Asciz	isHighSurrogate;
const #258 = NameAndType	#257:#254;//  isHighSurrogate:(C)Z
const #259 = Method	#252.#258;	//  java/lang/Character.isHighSurrogate:(C)Z
const #260 = Asciz	hasSurrogate;
const #261 = Asciz	Z;
const #262 = Asciz	n;
const #263 = Asciz	j;
const #264 = Asciz	temp;
const #265 = Asciz	C;
const #266 = Asciz	temp2;
const #267 = Asciz	i;
const #268 = Asciz	c2;
const #269 = Asciz	c1;
const #270 = Asciz	lastIndexOf;
const #271 = Asciz	(Ljava/lang/String;I)I;
const #272 = Asciz	augmentString;
const #273 = Asciz	(Ljava/lang/String;)Lscala/collection/immutable/StringOps;;
const #274 = NameAndType	#272:#273;//  augmentString:(Ljava/lang/String;)Lscala/collection/immutable/StringOps;
const #275 = Method	#121.#274;	//  scala/Predef$.augmentString:(Ljava/lang/String;)Lscala/collection/immutable/StringOps;
const #276 = Asciz	scala/collection/TraversableLike;
const #277 = class	#276;	//  scala/collection/TraversableLike
const #278 = Asciz	toIndexedSeq;
const #279 = NameAndType	#278:#196;//  toIndexedSeq:()Lscala/collection/mutable/IndexedSeq;
const #280 = InterfaceMethod	#277.#279;	//  scala/collection/TraversableLike.toIndexedSeq:()Lscala/collection/mutable/IndexedSeq;
const #281 = Asciz	lastIndexOfSlice;
const #282 = Asciz	(Lscala/collection/Seq;I)I;
const #283 = NameAndType	#281:#282;//  lastIndexOfSlice:(Lscala/collection/Seq;I)I
const #284 = InterfaceMethod	#224.#283;	//  scala/collection/SeqLike.lastIndexOfSlice:(Lscala/collection/Seq;I)I
const #285 = Asciz	str;
const #286 = Asciz	fromIndex;
const #287 = Asciz	(Ljava/lang/String;)I;
const #288 = NameAndType	#270:#271;//  lastIndexOf:(Ljava/lang/String;I)I
const #289 = Method	#11.#288;	//  scala/collection/mutable/StringBuilder.lastIndexOf:(Ljava/lang/String;I)I
const #290 = Asciz	indexOf;
const #291 = Asciz	indexOfSlice;
const #292 = NameAndType	#291:#282;//  indexOfSlice:(Lscala/collection/Seq;I)I
const #293 = InterfaceMethod	#224.#292;	//  scala/collection/SeqLike.indexOfSlice:(Lscala/collection/Seq;I)I
const #294 = NameAndType	#290:#271;//  indexOf:(Ljava/lang/String;I)I
const #295 = Method	#11.#294;	//  scala/collection/mutable/StringBuilder.indexOf:(Ljava/lang/String;I)I
const #296 = Asciz	insert;
const #297 = Asciz	(ID)Lscala/collection/mutable/StringBuilder;;
const #298 = Asciz	valueOf;
const #299 = Asciz	(D)Ljava/lang/String;;
const #300 = NameAndType	#298:#299;//  valueOf:(D)Ljava/lang/String;
const #301 = Method	#131.#300;	//  java/lang/String.valueOf:(D)Ljava/lang/String;
const #302 = Asciz	(ILjava/lang/String;)Lscala/collection/mutable/StringBuilder;;
const #303 = NameAndType	#296:#302;//  insert:(ILjava/lang/String;)Lscala/collection/mutable/StringBuilder;
const #304 = Method	#11.#303;	//  scala/collection/mutable/StringBuilder.insert:(ILjava/lang/String;)Lscala/collection/mutable/StringBuilder;
const #305 = Asciz	at;
const #306 = Asciz	D;
const #307 = Asciz	(IF)Lscala/collection/mutable/StringBuilder;;
const #308 = Asciz	(F)Ljava/lang/String;;
const #309 = NameAndType	#298:#308;//  valueOf:(F)Ljava/lang/String;
const #310 = Method	#131.#309;	//  java/lang/String.valueOf:(F)Ljava/lang/String;
const #311 = Asciz	F;
const #312 = Asciz	(IJ)Lscala/collection/mutable/StringBuilder;;
const #313 = Asciz	(J)Ljava/lang/String;;
const #314 = NameAndType	#298:#313;//  valueOf:(J)Ljava/lang/String;
const #315 = Method	#131.#314;	//  java/lang/String.valueOf:(J)Ljava/lang/String;
const #316 = Asciz	(II)Lscala/collection/mutable/StringBuilder;;
const #317 = Asciz	(I)Ljava/lang/String;;
const #318 = NameAndType	#298:#317;//  valueOf:(I)Ljava/lang/String;
const #319 = Method	#131.#318;	//  java/lang/String.valueOf:(I)Ljava/lang/String;
const #320 = Asciz	(IS)Lscala/collection/mutable/StringBuilder;;
const #321 = Asciz	S;
const #322 = Asciz	(IC)Lscala/collection/mutable/StringBuilder;;
const #323 = Asciz	java/lang/StringIndexOutOfBoundsException;
const #324 = class	#323;	//  java/lang/StringIndexOutOfBoundsException
const #325 = Asciz	(I)V;
const #326 = NameAndType	#20:#325;//  "<init>":(I)V
const #327 = Method	#324.#326;	//  java/lang/StringIndexOutOfBoundsException."<init>":(I)V
const #328 = Asciz	ensureCapacity;
const #329 = NameAndType	#328:#325;//  ensureCapacity:(I)V
const #330 = Method	#11.#329;	//  scala/collection/mutable/StringBuilder.ensureCapacity:(I)V
const #331 = Asciz	java/lang/System;
const #332 = class	#331;	//  java/lang/System
const #333 = Asciz	arraycopy;
const #334 = Asciz	(Ljava/lang/Object;ILjava/lang/Object;II)V;
const #335 = NameAndType	#333:#334;//  arraycopy:(Ljava/lang/Object;ILjava/lang/Object;II)V
const #336 = Method	#332.#335;	//  java/lang/System.arraycopy:(Ljava/lang/Object;ILjava/lang/Object;II)V
const #337 = Asciz	count_$eq;
const #338 = NameAndType	#337:#325;//  count_$eq:(I)V
const #339 = Method	#11.#338;	//  scala/collection/mutable/StringBuilder.count_$eq:(I)V
const #340 = Asciz	(IB)Lscala/collection/mutable/StringBuilder;;
const #341 = Asciz	(C)Ljava/lang/String;;
const #342 = NameAndType	#298:#341;//  valueOf:(C)Ljava/lang/String;
const #343 = Method	#131.#342;	//  java/lang/String.valueOf:(C)Ljava/lang/String;
const #344 = Asciz	B;
const #345 = Asciz	(IZ)Lscala/collection/mutable/StringBuilder;;
const #346 = Asciz	(Z)Ljava/lang/String;;
const #347 = NameAndType	#298:#346;//  valueOf:(Z)Ljava/lang/String;
const #348 = Method	#131.#347;	//  java/lang/String.valueOf:(Z)Ljava/lang/String;
const #349 = Asciz	(I[C)Lscala/collection/mutable/StringBuilder;;
const #350 = Asciz	insertAll;
const #351 = NameAndType	#350:#349;//  insertAll:(I[C)Lscala/collection/mutable/StringBuilder;
const #352 = Method	#11.#351;	//  scala/collection/mutable/StringBuilder.insertAll:(I[C)Lscala/collection/mutable/StringBuilder;
const #353 = Asciz	Deprecated;
const #354 = Asciz	len;
const #355 = Asciz	(ILscala/collection/Seq;)Lscala/collection/mutable/StringBuilder;;
const #356 = NameAndType	#350:#355;//  insertAll:(ILscala/collection/Seq;)Lscala/collection/mutable/StringBuilder;
const #357 = Method	#11.#356;	//  scala/collection/mutable/StringBuilder.insertAll:(ILscala/collection/Seq;)Lscala/collection/mutable/StringBuilder;
const #358 = Asciz	Lscala/collection/Seq;;
const #359 = Asciz	(ILscala/collection/Seq<Ljava/lang/Character;>;)Lscala/collection/mutable/StringBuilder;;
const #360 = Asciz	Signature;
const #361 = Asciz	scala/reflect/Manifest$;
const #362 = class	#361;	//  scala/reflect/Manifest$
const #363 = Asciz	Lscala/reflect/Manifest$;;
const #364 = NameAndType	#122:#363;//  MODULE$:Lscala/reflect/Manifest$;
const #365 = Field	#362.#364;	//  scala/reflect/Manifest$.MODULE$:Lscala/reflect/Manifest$;
const #366 = Asciz	Char;
const #367 = Asciz	()Lscala/reflect/AnyValManifest;;
const #368 = NameAndType	#366:#367;//  Char:()Lscala/reflect/AnyValManifest;
const #369 = Method	#362.#368;	//  scala/reflect/Manifest$.Char:()Lscala/reflect/AnyValManifest;
const #370 = Asciz	toArray;
const #371 = Asciz	(Lscala/reflect/ClassManifest;)Ljava/lang/Object;;
const #372 = NameAndType	#370:#371;//  toArray:(Lscala/reflect/ClassManifest;)Ljava/lang/Object;
const #373 = InterfaceMethod	#277.#372;	//  scala/collection/TraversableLike.toArray:(Lscala/reflect/ClassManifest;)Ljava/lang/Object;
const #374 = class	#17;	//  "[C"
const #375 = Asciz	equals;
const #376 = NameAndType	#375:#222;//  equals:(Ljava/lang/Object;)Z
const #377 = Method	#26.#376;	//  java/lang/Object.equals:(Ljava/lang/Object;)Z
const #378 = Asciz	null;
const #379 = String	#378;	//  null
const #380 = Asciz	getChars;
const #381 = Asciz	(II[CI)V;
const #382 = NameAndType	#380:#381;//  getChars:(II[CI)V
const #383 = Method	#131.#382;	//  java/lang/String.getChars:(II[CI)V
const #384 = Asciz	(ILjava/lang/Object;)Lscala/collection/mutable/StringBuilder;;
const #385 = Asciz	(Ljava/lang/Object;)Ljava/lang/String;;
const #386 = NameAndType	#298:#385;//  valueOf:(Ljava/lang/Object;)Ljava/lang/String;
const #387 = Method	#131.#386;	//  java/lang/String.valueOf:(Ljava/lang/Object;)Ljava/lang/String;
const #388 = Asciz	(I[CII)Lscala/collection/mutable/StringBuilder;;
const #389 = NameAndType	#350:#388;//  insertAll:(I[CII)Lscala/collection/mutable/StringBuilder;
const #390 = Method	#11.#389;	//  scala/collection/mutable/StringBuilder.insertAll:(I[CII)Lscala/collection/mutable/StringBuilder;
const #391 = Asciz	index;
const #392 = Asciz	offset;
const #393 = Method	#11.#27;	//  scala/collection/mutable/StringBuilder."<init>":()V
const #394 = Asciz	offset ;
const #395 = String	#394;	//  offset 
const #396 = Asciz	(Ljava/lang/Object;)Lscala/collection/mutable/StringBuilder;;
const #397 = NameAndType	#140:#396;//  append:(Ljava/lang/Object;)Lscala/collection/mutable/StringBuilder;
const #398 = Method	#11.#397;	//  scala/collection/mutable/StringBuilder.append:(Ljava/lang/Object;)Lscala/collection/mutable/StringBuilder;
const #399 = Asciz	boxToInteger;
const #400 = Asciz	(I)Ljava/lang/Integer;;
const #401 = NameAndType	#399:#400;//  boxToInteger:(I)Ljava/lang/Integer;
const #402 = Method	#154.#401;	//  scala/runtime/BoxesRunTime.boxToInteger:(I)Ljava/lang/Integer;
const #403 = Asciz	, len ;
const #404 = String	#403;	//  , len 
const #405 = Asciz	, str.length ;
const #406 = String	#405;	//  , str.length 
const #407 = Method	#11.#239;	//  scala/collection/mutable/StringBuilder.toString:()Ljava/lang/String;
const #408 = Asciz	(Ljava/lang/String;)V;
const #409 = NameAndType	#20:#408;//  "<init>":(Ljava/lang/String;)V
const #410 = Method	#324.#409;	//  java/lang/StringIndexOutOfBoundsException."<init>":(Ljava/lang/String;)V
const #411 = Asciz	replace;
const #412 = Asciz	(IILjava/lang/String;)V;
const #413 = Asciz	start;
const #414 = Asciz	end;
const #415 = Asciz	end0;
const #416 = Asciz	newCount;
const #417 = Asciz	delete;
const #418 = Asciz	(D)Lscala/collection/mutable/StringBuilder;;
const #419 = Asciz	(F)Lscala/collection/mutable/StringBuilder;;
const #420 = Asciz	(J)Lscala/collection/mutable/StringBuilder;;
const #421 = Asciz	(I)Lscala/collection/mutable/StringBuilder;;
const #422 = Asciz	(S)Lscala/collection/mutable/StringBuilder;;
const #423 = Asciz	(B)Lscala/collection/mutable/StringBuilder;;
const #424 = Asciz	(Z)Lscala/collection/mutable/StringBuilder;;
const #425 = Asciz	([CII)Lscala/collection/mutable/StringBuilder;;
const #426 = Asciz	appendAll;
const #427 = NameAndType	#426:#425;//  appendAll:([CII)Lscala/collection/mutable/StringBuilder;
const #428 = Method	#11.#427;	//  scala/collection/mutable/StringBuilder.appendAll:([CII)Lscala/collection/mutable/StringBuilder;
const #429 = Asciz	([C)Lscala/collection/mutable/StringBuilder;;
const #430 = NameAndType	#426:#429;//  appendAll:([C)Lscala/collection/mutable/StringBuilder;
const #431 = Method	#11.#430;	//  scala/collection/mutable/StringBuilder.appendAll:([C)Lscala/collection/mutable/StringBuilder;
const #432 = Asciz	(Lscala/collection/Seq;)Lscala/collection/mutable/StringBuilder;;
const #433 = NameAndType	#426:#432;//  appendAll:(Lscala/collection/Seq;)Lscala/collection/mutable/StringBuilder;
const #434 = Method	#11.#433;	//  scala/collection/mutable/StringBuilder.appendAll:(Lscala/collection/Seq;)Lscala/collection/mutable/StringBuilder;
const #435 = Asciz	(Lscala/collection/Seq<Ljava/lang/Character;>;)Lscala/collection/mutable/StringBuilder;;
const #436 = InterfaceMethod	#224.#134;	//  scala/collection/SeqLike.length:()I
const #437 = Asciz	(Lscala/collection/mutable/StringBuilder;)Lscala/collection/mutable/StringBuilder;;
const #438 = Asciz	(Lscala/collection/SeqLike;Ljava/lang/Object;)Z;
const #439 = NameAndType	#375:#438;//  equals:(Lscala/collection/SeqLike;Ljava/lang/Object;)Z
const #440 = Method	#86.#439;	//  scala/collection/SeqLike$class.equals:(Lscala/collection/SeqLike;Ljava/lang/Object;)Z
const #441 = Asciz	sb;
const #442 = Asciz	s;
const #443 = Asciz	$plus;
const #444 = NameAndType	#140:#179;//  append:(C)Lscala/collection/mutable/StringBuilder;
const #445 = Method	#11.#444;	//  scala/collection/mutable/StringBuilder.append:(C)Lscala/collection/mutable/StringBuilder;
const #446 = Asciz	subSequence;
const #447 = Asciz	(II)Ljava/lang/CharSequence;;
const #448 = Asciz	substring;
const #449 = Asciz	(II)Ljava/lang/String;;
const #450 = NameAndType	#448:#449;//  substring:(II)Ljava/lang/String;
const #451 = Method	#11.#450;	//  scala/collection/mutable/StringBuilder.substring:(II)Ljava/lang/String;
const #452 = Asciz	setCharAt;
const #453 = NameAndType	#452:#173;//  setCharAt:(IC)V
const #454 = Method	#11.#453;	//  scala/collection/mutable/StringBuilder.setCharAt:(IC)V
const #455 = Asciz	c;
const #456 = Asciz	ch;
const #457 = Asciz	deleteCharAt;
const #458 = Asciz	charAt;
const #459 = NameAndType	#458:#150;//  charAt:(I)C
const #460 = Method	#11.#459;	//  scala/collection/mutable/StringBuilder.charAt:(I)C
const #461 = Asciz	scala/runtime/RichInt;
const #462 = class	#461;	//  scala/runtime/RichInt
const #463 = Method	#462.#326;	//  scala/runtime/RichInt."<init>":(I)V
const #464 = Asciz	max;
const #465 = Asciz	(I)I;
const #466 = NameAndType	#464:#465;//  max:(I)I
const #467 = Method	#462.#466;	//  scala/runtime/RichInt.max:(I)I
const #468 = Asciz	array_$eq;
const #469 = Asciz	([C)V;
const #470 = NameAndType	#468:#469;//  array_$eq:([C)V
const #471 = Method	#11.#470;	//  scala/collection/mutable/StringBuilder.array_$eq:([C)V
const #472 = Asciz	newsize;
const #473 = Asciz	newar;
const #474 = Asciz	capacity_$eq;
const #475 = Asciz	capacity;
const #476 = Asciz	setLength;
const #477 = Asciz	scala/collection/mutable/StringBuilder$$anonfun$setLength$1;
const #478 = class	#477;	//  scala/collection/mutable/StringBuilder$$anonfun$setLength$1
const #479 = Asciz	(Lscala/collection/mutable/StringBuilder;I)V;
const #480 = NameAndType	#20:#479;//  "<init>":(Lscala/collection/mutable/StringBuilder;I)V
const #481 = Method	#478.#480;	//  scala/collection/mutable/StringBuilder$$anonfun$setLength$1."<init>":(Lscala/collection/mutable/StringBuilder;I)V
const #482 = Asciz	java/lang/IllegalArgumentException;
const #483 = class	#482;	//  java/lang/IllegalArgumentException
const #484 = Asciz	requirement failed: ;
const #485 = String	#484;	//  requirement failed: 
const #486 = Method	#483.#409;	//  java/lang/IllegalArgumentException."<init>":(Ljava/lang/String;)V
const #487 = Asciz	n$1;
const #488 = Asciz	requirement0;
const #489 = Asciz	clear;
const #490 = NameAndType	#476:#325;//  setLength:(I)V
const #491 = Method	#11.#490;	//  scala/collection/mutable/StringBuilder.setLength:(I)V
const #492 = Asciz	length_$eq;
const #493 = int	16;
const #494 = NameAndType	#20:#21;//  "<init>":(ILjava/lang/String;)V
const #495 = Method	#11.#494;	//  scala/collection/mutable/StringBuilder."<init>":(ILjava/lang/String;)V
const #496 = Asciz	;
const #497 = String	#496;	//  
const #498 = Asciz	$plus$plus$eq;
const #499 = Asciz	(Lscala/collection/Traversable;)Lscala/collection/generic/Growable;;
const #500 = Asciz	(Lscala/collection/generic/Growable;Lscala/collection/Traversable;)Lscala/collection/generic/Growable;;
const #501 = NameAndType	#498:#500;//  $plus$plus$eq:(Lscala/collection/generic/Growable;Lscala/collection/Traversable;)Lscala/collection/generic/Growable;
const #502 = Method	#30.#501;	//  scala/collection/generic/Growable$class.$plus$plus$eq:(Lscala/collection/generic/Growable;Lscala/collection/Traversable;)Lscala/collection/generic/Growable;
const #503 = Asciz	elems;
const #504 = Asciz	Lscala/collection/Traversable;;
const #505 = Asciz	(Lscala/collection/Iterator;)Lscala/collection/generic/Growable;;
const #506 = Asciz	(Lscala/collection/generic/Growable;Lscala/collection/Iterator;)Lscala/collection/generic/Growable;;
const #507 = NameAndType	#498:#506;//  $plus$plus$eq:(Lscala/collection/generic/Growable;Lscala/collection/Iterator;)Lscala/collection/generic/Growable;
const #508 = Method	#30.#507;	//  scala/collection/generic/Growable$class.$plus$plus$eq:(Lscala/collection/generic/Growable;Lscala/collection/Iterator;)Lscala/collection/generic/Growable;
const #509 = Asciz	iter;
const #510 = Asciz	Lscala/collection/Iterator;;
const #511 = Asciz	(Ljava/lang/Object;Ljava/lang/Object;Lscala/collection/Seq;)Lscala/collection/generic/Growable;;
const #512 = Asciz	(Lscala/collection/generic/Growable;Ljava/lang/Object;Ljava/lang/Object;Lscala/collection/Seq;)Lscala/collection/generic/Growable;;
const #513 = NameAndType	#177:#512;//  $plus$eq:(Lscala/collection/generic/Growable;Ljava/lang/Object;Ljava/lang/Object;Lscala/collection/Seq;)Lscala/collection/generic/Growable;
const #514 = Method	#30.#513;	//  scala/collection/generic/Growable$class.$plus$eq:(Lscala/collection/generic/Growable;Ljava/lang/Object;Ljava/lang/Object;Lscala/collection/Seq;)Lscala/collection/generic/Growable;
const #515 = Asciz	elem1;
const #516 = Asciz	elem2;
const #517 = Asciz	mapResult;
const #518 = Asciz	(Lscala/Function1;)Lscala/collection/mutable/Builder;;
const #519 = Asciz	(Lscala/collection/mutable/Builder;Lscala/Function1;)Lscala/collection/mutable/Builder;;
const #520 = NameAndType	#517:#519;//  mapResult:(Lscala/collection/mutable/Builder;Lscala/Function1;)Lscala/collection/mutable/Builder;
const #521 = Method	#36.#520;	//  scala/collection/mutable/Builder$class.mapResult:(Lscala/collection/mutable/Builder;Lscala/Function1;)Lscala/collection/mutable/Builder;
const #522 = Asciz	f;
const #523 = Asciz	sizeHint;
const #524 = Asciz	(Lscala/collection/mutable/Builder;I)V;
const #525 = NameAndType	#523:#524;//  sizeHint:(Lscala/collection/mutable/Builder;I)V
const #526 = Method	#36.#525;	//  scala/collection/mutable/Builder$class.sizeHint:(Lscala/collection/mutable/Builder;I)V
const #527 = Asciz	size;
const #528 = Asciz	withFilter;
const #529 = Asciz	(Lscala/Function1;)Lscala/collection/TraversableLike$WithFilter;;
const #530 = Asciz	(Lscala/collection/TraversableLike;Lscala/Function1;)Lscala/collection/TraversableLike$WithFilter;;
const #531 = NameAndType	#528:#530;//  withFilter:(Lscala/collection/TraversableLike;Lscala/Function1;)Lscala/collection/TraversableLike$WithFilter;
const #532 = Method	#41.#531;	//  scala/collection/TraversableLike$class.withFilter:(Lscala/collection/TraversableLike;Lscala/Function1;)Lscala/collection/TraversableLike$WithFilter;
const #533 = Asciz	p;
const #534 = Asciz	stringPrefix;
const #535 = Asciz	(Lscala/collection/TraversableLike;)Ljava/lang/String;;
const #536 = NameAndType	#534:#535;//  stringPrefix:(Lscala/collection/TraversableLike;)Ljava/lang/String;
const #537 = Method	#41.#536;	//  scala/collection/TraversableLike$class.stringPrefix:(Lscala/collection/TraversableLike;)Ljava/lang/String;
const #538 = Asciz	addString;
const #539 = Asciz	(Lscala/collection/TraversableLike;Lscala/collection/mutable/StringBuilder;)Lscala/collection/mutable/StringBuilder;;
const #540 = NameAndType	#538:#539;//  addString:(Lscala/collection/TraversableLike;Lscala/collection/mutable/StringBuilder;)Lscala/collection/mutable/StringBuilder;
const #541 = Method	#41.#540;	//  scala/collection/TraversableLike$class.addString:(Lscala/collection/TraversableLike;Lscala/collection/mutable/StringBuilder;)Lscala/collection/mutable/StringBuilder;
const #542 = Asciz	b;
const #543 = Asciz	(Lscala/collection/mutable/StringBuilder;Ljava/lang/String;)Lscala/collection/mutable/StringBuilder;;
const #544 = Asciz	(Lscala/collection/TraversableLike;Lscala/collection/mutable/StringBuilder;Ljava/lang/String;)Lscala/collection/mutable/StringBuilder;;
const #545 = NameAndType	#538:#544;//  addString:(Lscala/collection/TraversableLike;Lscala/collection/mutable/StringBuilder;Ljava/lang/String;)Lscala/collection/mutable/StringBuilder;
const #546 = Method	#41.#545;	//  scala/collection/TraversableLike$class.addString:(Lscala/collection/TraversableLike;Lscala/collection/mutable/StringBuilder;Ljava/lang/String;)Lscala/collection/mutable/StringBuilder;
const #547 = Asciz	sep;
const #548 = Asciz	(Lscala/collection/mutable/StringBuilder;Ljava/lang/String;Ljava/lang/String;Ljava/lang/String;)Lscala/collection/mutable/StringBuilder;;
const #549 = Asciz	(Lscala/collection/TraversableLike;Lscala/collection/mutable/StringBuilder;Ljava/lang/String;Ljava/lang/String;Ljava/lang/String;)Lscala/collection/mutable/StringBuilder;;
const #550 = NameAndType	#538:#549;//  addString:(Lscala/collection/TraversableLike;Lscala/collection/mutable/StringBuilder;Ljava/lang/String;Ljava/lang/String;Ljava/lang/String;)Lscala/collection/mutable/StringBuilder;
const #551 = Method	#41.#550;	//  scala/collection/TraversableLike$class.addString:(Lscala/collection/TraversableLike;Lscala/collection/mutable/StringBuilder;Ljava/lang/String;Ljava/lang/String;Ljava/lang/String;)Lscala/collection/mutable/StringBuilder;
const #552 = Asciz	mkString;
const #553 = NameAndType	#552:#535;//  mkString:(Lscala/collection/TraversableLike;)Ljava/lang/String;
const #554 = Method	#41.#553;	//  scala/collection/TraversableLike$class.mkString:(Lscala/collection/TraversableLike;)Ljava/lang/String;
const #555 = Asciz	(Ljava/lang/String;)Ljava/lang/String;;
const #556 = Asciz	(Lscala/collection/TraversableLike;Ljava/lang/String;)Ljava/lang/String;;
const #557 = NameAndType	#552:#556;//  mkString:(Lscala/collection/TraversableLike;Ljava/lang/String;)Ljava/lang/String;
const #558 = Method	#41.#557;	//  scala/collection/TraversableLike$class.mkString:(Lscala/collection/TraversableLike;Ljava/lang/String;)Ljava/lang/String;
const #559 = Asciz	(Ljava/lang/String;Ljava/lang/String;Ljava/lang/String;)Ljava/lang/String;;
const #560 = Asciz	(Lscala/collection/TraversableLike;Ljava/lang/String;Ljava/lang/String;Ljava/lang/String;)Ljava/lang/String;;
const #561 = NameAndType	#552:#560;//  mkString:(Lscala/collection/TraversableLike;Ljava/lang/String;Ljava/lang/String;Ljava/lang/String;)Ljava/lang/String;
const #562 = Method	#41.#561;	//  scala/collection/TraversableLike$class.mkString:(Lscala/collection/TraversableLike;Ljava/lang/String;Ljava/lang/String;Ljava/lang/String;)Ljava/lang/String;
const #563 = Asciz	toSet;
const #564 = Asciz	()Lscala/collection/immutable/Set;;
const #565 = Asciz	(Lscala/collection/TraversableLike;)Lscala/collection/immutable/Set;;
const #566 = NameAndType	#563:#565;//  toSet:(Lscala/collection/TraversableLike;)Lscala/collection/immutable/Set;
const #567 = Method	#41.#566;	//  scala/collection/TraversableLike$class.toSet:(Lscala/collection/TraversableLike;)Lscala/collection/immutable/Set;
const #568 = Asciz	(Lscala/collection/TraversableLike;)Lscala/collection/mutable/IndexedSeq;;
const #569 = NameAndType	#278:#568;//  toIndexedSeq:(Lscala/collection/TraversableLike;)Lscala/collection/mutable/IndexedSeq;
const #570 = Method	#41.#569;	//  scala/collection/TraversableLike$class.toIndexedSeq:(Lscala/collection/TraversableLike;)Lscala/collection/mutable/IndexedSeq;
const #571 = Asciz	toList;
const #572 = Asciz	()Lscala/collection/immutable/List;;
const #573 = Asciz	(Lscala/collection/TraversableLike;)Lscala/collection/immutable/List;;
const #574 = NameAndType	#571:#573;//  toList:(Lscala/collection/TraversableLike;)Lscala/collection/immutable/List;
const #575 = Method	#41.#574;	//  scala/collection/TraversableLike$class.toList:(Lscala/collection/TraversableLike;)Lscala/collection/immutable/List;
const #576 = Asciz	(Lscala/collection/TraversableLike;Lscala/reflect/ClassManifest;)Ljava/lang/Object;;
const #577 = NameAndType	#370:#576;//  toArray:(Lscala/collection/TraversableLike;Lscala/reflect/ClassManifest;)Ljava/lang/Object;
const #578 = Method	#41.#577;	//  scala/collection/TraversableLike$class.toArray:(Lscala/collection/TraversableLike;Lscala/reflect/ClassManifest;)Ljava/lang/Object;
const #579 = Asciz	evidence$1;
const #580 = Asciz	Lscala/reflect/ClassManifest;;
const #581 = Asciz	copyToArray;
const #582 = Asciz	(Ljava/lang/Object;)V;
const #583 = Asciz	(Lscala/collection/TraversableLike;Ljava/lang/Object;)V;
const #584 = NameAndType	#581:#583;//  copyToArray:(Lscala/collection/TraversableLike;Ljava/lang/Object;)V
const #585 = Method	#41.#584;	//  scala/collection/TraversableLike$class.copyToArray:(Lscala/collection/TraversableLike;Ljava/lang/Object;)V
const #586 = Asciz	xs;
const #587 = Asciz	(Ljava/lang/Object;I)V;
const #588 = Asciz	(Lscala/collection/TraversableLike;Ljava/lang/Object;I)V;
const #589 = NameAndType	#581:#588;//  copyToArray:(Lscala/collection/TraversableLike;Ljava/lang/Object;I)V
const #590 = Method	#41.#589;	//  scala/collection/TraversableLike$class.copyToArray:(Lscala/collection/TraversableLike;Ljava/lang/Object;I)V
const #591 = Asciz	copyToBuffer;
const #592 = Asciz	(Lscala/collection/mutable/Buffer;)V;
const #593 = Asciz	(Lscala/collection/TraversableLike;Lscala/collection/mutable/Buffer;)V;
const #594 = NameAndType	#591:#593;//  copyToBuffer:(Lscala/collection/TraversableLike;Lscala/collection/mutable/Buffer;)V
const #595 = Method	#41.#594;	//  scala/collection/TraversableLike$class.copyToBuffer:(Lscala/collection/TraversableLike;Lscala/collection/mutable/Buffer;)V
const #596 = Asciz	dest;
const #597 = Asciz	Lscala/collection/mutable/Buffer;;
const #598 = Asciz	lastOption;
const #599 = Asciz	()Lscala/Option;;
const #600 = Asciz	(Lscala/collection/TraversableLike;)Lscala/Option;;
const #601 = NameAndType	#598:#600;//  lastOption:(Lscala/collection/TraversableLike;)Lscala/Option;
const #602 = Method	#41.#601;	//  scala/collection/TraversableLike$class.lastOption:(Lscala/collection/TraversableLike;)Lscala/Option;
const #603 = Asciz	headOption;
const #604 = NameAndType	#603:#600;//  headOption:(Lscala/collection/TraversableLike;)Lscala/Option;
const #605 = Method	#41.#604;	//  scala/collection/TraversableLike$class.headOption:(Lscala/collection/TraversableLike;)Lscala/Option;
const #606 = Asciz	(Lscala/math/Ordering;)Ljava/lang/Object;;
const #607 = Asciz	(Lscala/collection/TraversableLike;Lscala/math/Ordering;)Ljava/lang/Object;;
const #608 = NameAndType	#464:#607;//  max:(Lscala/collection/TraversableLike;Lscala/math/Ordering;)Ljava/lang/Object;
const #609 = Method	#41.#608;	//  scala/collection/TraversableLike$class.max:(Lscala/collection/TraversableLike;Lscala/math/Ordering;)Ljava/lang/Object;
const #610 = Asciz	cmp;
const #611 = Asciz	Lscala/math/Ordering;;
const #612 = Asciz	min;
const #613 = NameAndType	#612:#607;//  min:(Lscala/collection/TraversableLike;Lscala/math/Ordering;)Ljava/lang/Object;
const #614 = Method	#41.#613;	//  scala/collection/TraversableLike$class.min:(Lscala/collection/TraversableLike;Lscala/math/Ordering;)Ljava/lang/Object;
const #615 = Asciz	product;
const #616 = Asciz	(Lscala/math/Numeric;)Ljava/lang/Object;;
const #617 = Asciz	(Lscala/collection/TraversableLike;Lscala/math/Numeric;)Ljava/lang/Object;;
const #618 = NameAndType	#615:#617;//  product:(Lscala/collection/TraversableLike;Lscala/math/Numeric;)Ljava/lang/Object;
const #619 = Method	#41.#618;	//  scala/collection/TraversableLike$class.product:(Lscala/collection/TraversableLike;Lscala/math/Numeric;)Ljava/lang/Object;
const #620 = Asciz	num;
const #621 = Asciz	Lscala/math/Numeric;;
const #622 = Asciz	sum;
const #623 = NameAndType	#622:#617;//  sum:(Lscala/collection/TraversableLike;Lscala/math/Numeric;)Ljava/lang/Object;
const #624 = Method	#41.#623;	//  scala/collection/TraversableLike$class.sum:(Lscala/collection/TraversableLike;Lscala/math/Numeric;)Ljava/lang/Object;
const #625 = Asciz	reduceRightOption;
const #626 = Asciz	(Lscala/Function2;)Lscala/Option;;
const #627 = Asciz	(Lscala/collection/TraversableLike;Lscala/Function2;)Lscala/Option;;
const #628 = NameAndType	#625:#627;//  reduceRightOption:(Lscala/collection/TraversableLike;Lscala/Function2;)Lscala/Option;
const #629 = Method	#41.#628;	//  scala/collection/TraversableLike$class.reduceRightOption:(Lscala/collection/TraversableLike;Lscala/Function2;)Lscala/Option;
const #630 = Asciz	op;
const #631 = Asciz	Lscala/Function2;;
const #632 = Asciz	reduceLeftOption;
const #633 = NameAndType	#632:#627;//  reduceLeftOption:(Lscala/collection/TraversableLike;Lscala/Function2;)Lscala/Option;
const #634 = Method	#41.#633;	//  scala/collection/TraversableLike$class.reduceLeftOption:(Lscala/collection/TraversableLike;Lscala/Function2;)Lscala/Option;
const #635 = Asciz	$colon$bslash;
const #636 = Asciz	(Ljava/lang/Object;Lscala/Function2;)Ljava/lang/Object;;
const #637 = Asciz	(Lscala/collection/TraversableLike;Ljava/lang/Object;Lscala/Function2;)Ljava/lang/Object;;
const #638 = NameAndType	#635:#637;//  $colon$bslash:(Lscala/collection/TraversableLike;Ljava/lang/Object;Lscala/Function2;)Ljava/lang/Object;
const #639 = Method	#41.#638;	//  scala/collection/TraversableLike$class.$colon$bslash:(Lscala/collection/TraversableLike;Ljava/lang/Object;Lscala/Function2;)Ljava/lang/Object;
const #640 = Asciz	z;
const #641 = Asciz	$div$colon;
const #642 = NameAndType	#641:#637;//  $div$colon:(Lscala/collection/TraversableLike;Ljava/lang/Object;Lscala/Function2;)Ljava/lang/Object;
const #643 = Method	#41.#642;	//  scala/collection/TraversableLike$class.$div$colon:(Lscala/collection/TraversableLike;Ljava/lang/Object;Lscala/Function2;)Ljava/lang/Object;
const #644 = Asciz	(Lscala/Function1;)I;
const #645 = Asciz	(Lscala/collection/TraversableLike;Lscala/Function1;)I;
const #646 = NameAndType	#14:#645;//  count:(Lscala/collection/TraversableLike;Lscala/Function1;)I
const #647 = Method	#41.#646;	//  scala/collection/TraversableLike$class.count:(Lscala/collection/TraversableLike;Lscala/Function1;)I
const #648 = Asciz	groupBy;
const #649 = Asciz	(Lscala/Function1;)Lscala/collection/Map;;
const #650 = Asciz	(Lscala/collection/TraversableLike;Lscala/Function1;)Lscala/collection/Map;;
const #651 = NameAndType	#648:#650;//  groupBy:(Lscala/collection/TraversableLike;Lscala/Function1;)Lscala/collection/Map;
const #652 = Method	#41.#651;	//  scala/collection/TraversableLike$class.groupBy:(Lscala/collection/TraversableLike;Lscala/Function1;)Lscala/collection/Map;
const #653 = Asciz	partition;
const #654 = Asciz	(Lscala/Function1;)Lscala/Tuple2;;
const #655 = Asciz	(Lscala/collection/TraversableLike;Lscala/Function1;)Lscala/Tuple2;;
const #656 = NameAndType	#653:#655;//  partition:(Lscala/collection/TraversableLike;Lscala/Function1;)Lscala/Tuple2;
const #657 = Method	#41.#656;	//  scala/collection/TraversableLike$class.partition:(Lscala/collection/TraversableLike;Lscala/Function1;)Lscala/Tuple2;
const #658 = Asciz	partialMap;
const #659 = Asciz	(Lscala/PartialFunction;Lscala/collection/generic/CanBuildFrom;)Ljava/lang/Object;;
const #660 = Asciz	(Lscala/collection/TraversableLike;Lscala/PartialFunction;Lscala/collection/generic/CanBuildFrom;)Ljava/lang/Object;;
const #661 = NameAndType	#658:#660;//  partialMap:(Lscala/collection/TraversableLike;Lscala/PartialFunction;Lscala/collection/generic/CanBuildFrom;)Ljava/lang/Object;
const #662 = Method	#41.#661;	//  scala/collection/TraversableLike$class.partialMap:(Lscala/collection/TraversableLike;Lscala/PartialFunction;Lscala/collection/generic/CanBuildFrom;)Ljava/lang/Object;
const #663 = Asciz	pf;
const #664 = Asciz	Lscala/PartialFunction;;
const #665 = Asciz	bf;
const #666 = Asciz	Lscala/collection/generic/CanBuildFrom;;
const #667 = Asciz	filterNot;
const #668 = Asciz	(Lscala/Function1;)Ljava/lang/Object;;
const #669 = Asciz	(Lscala/collection/TraversableLike;Lscala/Function1;)Ljava/lang/Object;;
const #670 = NameAndType	#667:#669;//  filterNot:(Lscala/collection/TraversableLike;Lscala/Function1;)Ljava/lang/Object;
const #671 = Method	#41.#670;	//  scala/collection/TraversableLike$class.filterNot:(Lscala/collection/TraversableLike;Lscala/Function1;)Ljava/lang/Object;
const #672 = Asciz	filter;
const #673 = NameAndType	#672:#669;//  filter:(Lscala/collection/TraversableLike;Lscala/Function1;)Ljava/lang/Object;
const #674 = Method	#41.#673;	//  scala/collection/TraversableLike$class.filter:(Lscala/collection/TraversableLike;Lscala/Function1;)Ljava/lang/Object;
const #675 = Asciz	flatMap;
const #676 = Asciz	(Lscala/Function1;Lscala/collection/generic/CanBuildFrom;)Ljava/lang/Object;;
const #677 = Asciz	(Lscala/collection/TraversableLike;Lscala/Function1;Lscala/collection/generic/CanBuildFrom;)Ljava/lang/Object;;
const #678 = NameAndType	#675:#677;//  flatMap:(Lscala/collection/TraversableLike;Lscala/Function1;Lscala/collection/generic/CanBuildFrom;)Ljava/lang/Object;
const #679 = Method	#41.#678;	//  scala/collection/TraversableLike$class.flatMap:(Lscala/collection/TraversableLike;Lscala/Function1;Lscala/collection/generic/CanBuildFrom;)Ljava/lang/Object;
const #680 = Asciz	map;
const #681 = NameAndType	#680:#677;//  map:(Lscala/collection/TraversableLike;Lscala/Function1;Lscala/collection/generic/CanBuildFrom;)Ljava/lang/Object;
const #682 = Method	#41.#681;	//  scala/collection/TraversableLike$class.map:(Lscala/collection/TraversableLike;Lscala/Function1;Lscala/collection/generic/CanBuildFrom;)Ljava/lang/Object;
const #683 = Asciz	$plus$plus;
const #684 = Asciz	(Lscala/collection/Iterator;Lscala/collection/generic/CanBuildFrom;)Ljava/lang/Object;;
const #685 = Asciz	(Lscala/collection/TraversableLike;Lscala/collection/Iterator;Lscala/collection/generic/CanBuildFrom;)Ljava/lang/Object;;
const #686 = NameAndType	#683:#685;//  $plus$plus:(Lscala/collection/TraversableLike;Lscala/collection/Iterator;Lscala/collection/generic/CanBuildFrom;)Ljava/lang/Object;
const #687 = Method	#41.#686;	//  scala/collection/TraversableLike$class.$plus$plus:(Lscala/collection/TraversableLike;Lscala/collection/Iterator;Lscala/collection/generic/CanBuildFrom;)Ljava/lang/Object;
const #688 = Asciz	that;
const #689 = Asciz	(Lscala/collection/Traversable;Lscala/collection/generic/CanBuildFrom;)Ljava/lang/Object;;
const #690 = Asciz	(Lscala/collection/TraversableLike;Lscala/collection/Traversable;Lscala/collection/generic/CanBuildFrom;)Ljava/lang/Object;;
const #691 = NameAndType	#683:#690;//  $plus$plus:(Lscala/collection/TraversableLike;Lscala/collection/Traversable;Lscala/collection/generic/CanBuildFrom;)Ljava/lang/Object;
const #692 = Method	#41.#691;	//  scala/collection/TraversableLike$class.$plus$plus:(Lscala/collection/TraversableLike;Lscala/collection/Traversable;Lscala/collection/generic/CanBuildFrom;)Ljava/lang/Object;
const #693 = Asciz	hasDefiniteSize;
const #694 = Asciz	()Z;
const #695 = Asciz	(Lscala/collection/TraversableLike;)Z;
const #696 = NameAndType	#693:#695;//  hasDefiniteSize:(Lscala/collection/TraversableLike;)Z
const #697 = Method	#41.#696;	//  scala/collection/TraversableLike$class.hasDefiniteSize:(Lscala/collection/TraversableLike;)Z
const #698 = Asciz	nonEmpty;
const #699 = NameAndType	#698:#695;//  nonEmpty:(Lscala/collection/TraversableLike;)Z
const #700 = Method	#41.#699;	//  scala/collection/TraversableLike$class.nonEmpty:(Lscala/collection/TraversableLike;)Z
const #701 = Asciz	(Lscala/collection/TraversableLike;)Ljava/lang/Object;;
const #702 = NameAndType	#207:#701;//  repr:(Lscala/collection/TraversableLike;)Ljava/lang/Object;
const #703 = Method	#41.#702;	//  scala/collection/TraversableLike$class.repr:(Lscala/collection/TraversableLike;)Ljava/lang/Object;
const #704 = Asciz	transpose;
const #705 = Asciz	(Lscala/Function1;)Lscala/collection/Traversable;;
const #706 = Asciz	(Lscala/collection/generic/GenericTraversableTemplate;Lscala/Function1;)Lscala/collection/Traversable;;
const #707 = NameAndType	#704:#706;//  transpose:(Lscala/collection/generic/GenericTraversableTemplate;Lscala/Function1;)Lscala/collection/Traversable;
const #708 = Method	#46.#707;	//  scala/collection/generic/GenericTraversableTemplate$class.transpose:(Lscala/collection/generic/GenericTraversableTemplate;Lscala/Function1;)Lscala/collection/Traversable;
const #709 = Asciz	asTraversable;
const #710 = Asciz	flatten;
const #711 = NameAndType	#710:#706;//  flatten:(Lscala/collection/generic/GenericTraversableTemplate;Lscala/Function1;)Lscala/collection/Traversable;
const #712 = Method	#46.#711;	//  scala/collection/generic/GenericTraversableTemplate$class.flatten:(Lscala/collection/generic/GenericTraversableTemplate;Lscala/Function1;)Lscala/collection/Traversable;
const #713 = Asciz	unzip;
const #714 = Asciz	(Lscala/collection/generic/GenericTraversableTemplate;Lscala/Function1;)Lscala/Tuple2;;
const #715 = NameAndType	#713:#714;//  unzip:(Lscala/collection/generic/GenericTraversableTemplate;Lscala/Function1;)Lscala/Tuple2;
const #716 = Method	#46.#715;	//  scala/collection/generic/GenericTraversableTemplate$class.unzip:(Lscala/collection/generic/GenericTraversableTemplate;Lscala/Function1;)Lscala/Tuple2;
const #717 = Asciz	asPair;
const #718 = Asciz	genericBuilder;
const #719 = Asciz	()Lscala/collection/mutable/Builder;;
const #720 = Asciz	(Lscala/collection/generic/GenericTraversableTemplate;)Lscala/collection/mutable/Builder;;
const #721 = NameAndType	#718:#720;//  genericBuilder:(Lscala/collection/generic/GenericTraversableTemplate;)Lscala/collection/mutable/Builder;
const #722 = Method	#46.#721;	//  scala/collection/generic/GenericTraversableTemplate$class.genericBuilder:(Lscala/collection/generic/GenericTraversableTemplate;)Lscala/collection/mutable/Builder;
const #723 = Asciz	newBuilder;
const #724 = NameAndType	#723:#720;//  newBuilder:(Lscala/collection/generic/GenericTraversableTemplate;)Lscala/collection/mutable/Builder;
const #725 = Method	#46.#724;	//  scala/collection/generic/GenericTraversableTemplate$class.newBuilder:(Lscala/collection/generic/GenericTraversableTemplate;)Lscala/collection/mutable/Builder;
const #726 = Asciz	firstOption;
const #727 = Asciz	(Lscala/collection/IterableLike;)Lscala/Option;;
const #728 = NameAndType	#726:#727;//  firstOption:(Lscala/collection/IterableLike;)Lscala/Option;
const #729 = Method	#61.#728;	//  scala/collection/IterableLike$class.firstOption:(Lscala/collection/IterableLike;)Lscala/Option;
const #730 = Asciz	first;
const #731 = Asciz	(Lscala/collection/IterableLike;)Ljava/lang/Object;;
const #732 = NameAndType	#730:#731;//  first:(Lscala/collection/IterableLike;)Ljava/lang/Object;
const #733 = Method	#61.#732;	//  scala/collection/IterableLike$class.first:(Lscala/collection/IterableLike;)Ljava/lang/Object;
const #734 = Asciz	canEqual;
const #735 = Asciz	(Lscala/collection/IterableLike;Ljava/lang/Object;)Z;
const #736 = NameAndType	#734:#735;//  canEqual:(Lscala/collection/IterableLike;Ljava/lang/Object;)Z
const #737 = Method	#61.#736;	//  scala/collection/IterableLike$class.canEqual:(Lscala/collection/IterableLike;Ljava/lang/Object;)Z
const #738 = Asciz	toStream;
const #739 = Asciz	()Lscala/collection/immutable/Stream;;
const #740 = Asciz	(Lscala/collection/IterableLike;)Lscala/collection/immutable/Stream;;
const #741 = NameAndType	#738:#740;//  toStream:(Lscala/collection/IterableLike;)Lscala/collection/immutable/Stream;
const #742 = Method	#61.#741;	//  scala/collection/IterableLike$class.toStream:(Lscala/collection/IterableLike;)Lscala/collection/immutable/Stream;
const #743 = Asciz	zipAll;
const #744 = Asciz	(Lscala/collection/Iterable;Ljava/lang/Object;Ljava/lang/Object;Lscala/collection/generic/CanBuildFrom;)Ljava/lang/Object;;
const #745 = Asciz	(Lscala/collection/IterableLike;Lscala/collection/Iterable;Ljava/lang/Object;Ljava/lang/Object;Lscala/collection/generic/CanBuildFrom;)Ljava/lang/Object;;
const #746 = NameAndType	#743:#745;//  zipAll:(Lscala/collection/IterableLike;Lscala/collection/Iterable;Ljava/lang/Object;Ljava/lang/Object;Lscala/collection/generic/CanBuildFrom;)Ljava/lang/Object;
const #747 = Method	#61.#746;	//  scala/collection/IterableLike$class.zipAll:(Lscala/collection/IterableLike;Lscala/collection/Iterable;Ljava/lang/Object;Ljava/lang/Object;Lscala/collection/generic/CanBuildFrom;)Ljava/lang/Object;
const #748 = Asciz	Lscala/collection/Iterable;;
const #749 = Asciz	thisElem;
const #750 = Asciz	thatElem;
const #751 = Asciz	toIterable;
const #752 = Asciz	(Lscala/collection/IterableLike;)Lscala/collection/Iterable;;
const #753 = NameAndType	#751:#752;//  toIterable:(Lscala/collection/IterableLike;)Lscala/collection/Iterable;
const #754 = Method	#61.#753;	//  scala/collection/IterableLike$class.toIterable:(Lscala/collection/IterableLike;)Lscala/collection/Iterable;
const #755 = Asciz	elements;
const #756 = Asciz	()Lscala/collection/Iterator;;
const #757 = Asciz	(Lscala/collection/IterableLike;)Lscala/collection/Iterator;;
const #758 = NameAndType	#755:#757;//  elements:(Lscala/collection/IterableLike;)Lscala/collection/Iterator;
const #759 = Method	#61.#758;	//  scala/collection/IterableLike$class.elements:(Lscala/collection/IterableLike;)Lscala/collection/Iterator;
const #760 = Asciz	compose;
const #761 = Asciz	(Lscala/Function1;Lscala/Function1;)Lscala/Function1;;
const #762 = NameAndType	#760:#761;//  compose:(Lscala/Function1;Lscala/Function1;)Lscala/Function1;
const #763 = Method	#76.#762;	//  scala/Function1$class.compose:(Lscala/Function1;Lscala/Function1;)Lscala/Function1;
const #764 = Asciz	lift;
const #765 = Asciz	()Lscala/Function1;;
const #766 = Asciz	(Lscala/PartialFunction;)Lscala/Function1;;
const #767 = NameAndType	#764:#766;//  lift:(Lscala/PartialFunction;)Lscala/Function1;
const #768 = Method	#81.#767;	//  scala/PartialFunction$class.lift:(Lscala/PartialFunction;)Lscala/Function1;
const #769 = Asciz	(Lscala/PartialFunction;Lscala/Function1;)Lscala/PartialFunction;;
const #770 = NameAndType	#229:#769;//  andThen:(Lscala/PartialFunction;Lscala/Function1;)Lscala/PartialFunction;
const #771 = Method	#81.#770;	//  scala/PartialFunction$class.andThen:(Lscala/PartialFunction;Lscala/Function1;)Lscala/PartialFunction;
const #772 = Asciz	k;
const #773 = Asciz	orElse;
const #774 = Asciz	(Lscala/PartialFunction;)Lscala/PartialFunction;;
const #775 = Asciz	(Lscala/PartialFunction;Lscala/PartialFunction;)Lscala/PartialFunction;;
const #776 = NameAndType	#773:#775;//  orElse:(Lscala/PartialFunction;Lscala/PartialFunction;)Lscala/PartialFunction;
const #777 = Method	#81.#776;	//  scala/PartialFunction$class.orElse:(Lscala/PartialFunction;Lscala/PartialFunction;)Lscala/PartialFunction;
const #778 = Asciz	projection;
const #779 = Asciz	(Lscala/collection/SeqLike;)Ljava/lang/Object;;
const #780 = NameAndType	#778:#779;//  projection:(Lscala/collection/SeqLike;)Ljava/lang/Object;
const #781 = Method	#86.#780;	//  scala/collection/SeqLike$class.projection:(Lscala/collection/SeqLike;)Ljava/lang/Object;
const #782 = Asciz	equalsWith;
const #783 = Asciz	(Lscala/collection/Seq;Lscala/Function2;)Z;
const #784 = Asciz	(Lscala/collection/SeqLike;Lscala/collection/Seq;Lscala/Function2;)Z;
const #785 = NameAndType	#782:#784;//  equalsWith:(Lscala/collection/SeqLike;Lscala/collection/Seq;Lscala/Function2;)Z
const #786 = Method	#86.#785;	//  scala/collection/SeqLike$class.equalsWith:(Lscala/collection/SeqLike;Lscala/collection/Seq;Lscala/Function2;)Z
const #787 = Asciz	findLastIndexOf;
const #788 = Asciz	(Lscala/collection/SeqLike;Lscala/Function1;)I;
const #789 = NameAndType	#787:#788;//  findLastIndexOf:(Lscala/collection/SeqLike;Lscala/Function1;)I
const #790 = Method	#86.#789;	//  scala/collection/SeqLike$class.findLastIndexOf:(Lscala/collection/SeqLike;Lscala/Function1;)I
const #791 = Asciz	hashCode;
const #792 = Asciz	(Lscala/collection/SeqLike;)I;
const #793 = NameAndType	#791:#792;//  hashCode:(Lscala/collection/SeqLike;)I
const #794 = Method	#86.#793;	//  scala/collection/SeqLike$class.hashCode:(Lscala/collection/SeqLike;)I
const #795 = Asciz	indices;
const #796 = Asciz	()Lscala/collection/immutable/Range;;
const #797 = Asciz	(Lscala/collection/SeqLike;)Lscala/collection/immutable/Range;;
const #798 = NameAndType	#795:#797;//  indices:(Lscala/collection/SeqLike;)Lscala/collection/immutable/Range;
const #799 = Method	#86.#798;	//  scala/collection/SeqLike$class.indices:(Lscala/collection/SeqLike;)Lscala/collection/immutable/Range;
const #800 = Asciz	toSeq;
const #801 = Asciz	(Lscala/collection/SeqLike;)Lscala/collection/Seq;;
const #802 = NameAndType	#800:#801;//  toSeq:(Lscala/collection/SeqLike;)Lscala/collection/Seq;
const #803 = Method	#86.#802;	//  scala/collection/SeqLike$class.toSeq:(Lscala/collection/SeqLike;)Lscala/collection/Seq;
const #804 = Asciz	sortBy;
const #805 = Asciz	(Lscala/Function1;Lscala/math/Ordering;)Ljava/lang/Object;;
const #806 = Asciz	(Lscala/collection/SeqLike;Lscala/Function1;Lscala/math/Ordering;)Ljava/lang/Object;;
const #807 = NameAndType	#804:#806;//  sortBy:(Lscala/collection/SeqLike;Lscala/Function1;Lscala/math/Ordering;)Ljava/lang/Object;
const #808 = Method	#86.#807;	//  scala/collection/SeqLike$class.sortBy:(Lscala/collection/SeqLike;Lscala/Function1;Lscala/math/Ordering;)Ljava/lang/Object;
const #809 = Asciz	ord;
const #810 = Asciz	sortWith;
const #811 = Asciz	(Lscala/collection/SeqLike;Lscala/math/Ordering;)Ljava/lang/Object;;
const #812 = NameAndType	#810:#811;//  sortWith:(Lscala/collection/SeqLike;Lscala/math/Ordering;)Ljava/lang/Object;
const #813 = Method	#86.#812;	//  scala/collection/SeqLike$class.sortWith:(Lscala/collection/SeqLike;Lscala/math/Ordering;)Ljava/lang/Object;
const #814 = Asciz	(Lscala/Function2;)Ljava/lang/Object;;
const #815 = Asciz	(Lscala/collection/SeqLike;Lscala/Function2;)Ljava/lang/Object;;
const #816 = NameAndType	#810:#815;//  sortWith:(Lscala/collection/SeqLike;Lscala/Function2;)Ljava/lang/Object;
const #817 = Method	#86.#816;	//  scala/collection/SeqLike$class.sortWith:(Lscala/collection/SeqLike;Lscala/Function2;)Ljava/lang/Object;
const #818 = Asciz	lt;
const #819 = Asciz	corresponds;
const #820 = NameAndType	#819:#784;//  corresponds:(Lscala/collection/SeqLike;Lscala/collection/Seq;Lscala/Function2;)Z
const #821 = Method	#86.#820;	//  scala/collection/SeqLike$class.corresponds:(Lscala/collection/SeqLike;Lscala/collection/Seq;Lscala/Function2;)Z
const #822 = Asciz	padTo;
const #823 = Asciz	(ILjava/lang/Object;Lscala/collection/generic/CanBuildFrom;)Ljava/lang/Object;;
const #824 = Asciz	(Lscala/collection/SeqLike;ILjava/lang/Object;Lscala/collection/generic/CanBuildFrom;)Ljava/lang/Object;;
const #825 = NameAndType	#822:#824;//  padTo:(Lscala/collection/SeqLike;ILjava/lang/Object;Lscala/collection/generic/CanBuildFrom;)Ljava/lang/Object;
const #826 = Method	#86.#825;	//  scala/collection/SeqLike$class.padTo:(Lscala/collection/SeqLike;ILjava/lang/Object;Lscala/collection/generic/CanBuildFrom;)Ljava/lang/Object;
const #827 = Asciz	$colon$plus;
const #828 = Asciz	(Ljava/lang/Object;Lscala/collection/generic/CanBuildFrom;)Ljava/lang/Object;;
const #829 = Asciz	(Lscala/collection/SeqLike;Ljava/lang/Object;Lscala/collection/generic/CanBuildFrom;)Ljava/lang/Object;;
const #830 = NameAndType	#827:#829;//  $colon$plus:(Lscala/collection/SeqLike;Ljava/lang/Object;Lscala/collection/generic/CanBuildFrom;)Ljava/lang/Object;
const #831 = Method	#86.#830;	//  scala/collection/SeqLike$class.$colon$plus:(Lscala/collection/SeqLike;Ljava/lang/Object;Lscala/collection/generic/CanBuildFrom;)Ljava/lang/Object;
const #832 = Asciz	$plus$colon;
const #833 = NameAndType	#832:#829;//  $plus$colon:(Lscala/collection/SeqLike;Ljava/lang/Object;Lscala/collection/generic/CanBuildFrom;)Ljava/lang/Object;
const #834 = Method	#86.#833;	//  scala/collection/SeqLike$class.$plus$colon:(Lscala/collection/SeqLike;Ljava/lang/Object;Lscala/collection/generic/CanBuildFrom;)Ljava/lang/Object;
const #835 = Asciz	updated;
const #836 = NameAndType	#835:#824;//  updated:(Lscala/collection/SeqLike;ILjava/lang/Object;Lscala/collection/generic/CanBuildFrom;)Ljava/lang/Object;
const #837 = Method	#86.#836;	//  scala/collection/SeqLike$class.updated:(Lscala/collection/SeqLike;ILjava/lang/Object;Lscala/collection/generic/CanBuildFrom;)Ljava/lang/Object;
const #838 = Asciz	patch;
const #839 = Asciz	(ILscala/collection/Seq;ILscala/collection/generic/CanBuildFrom;)Ljava/lang/Object;;
const #840 = Asciz	(Lscala/collection/SeqLike;ILscala/collection/Seq;ILscala/collection/generic/CanBuildFrom;)Ljava/lang/Object;;
const #841 = NameAndType	#838:#840;//  patch:(Lscala/collection/SeqLike;ILscala/collection/Seq;ILscala/collection/generic/CanBuildFrom;)Ljava/lang/Object;
const #842 = Method	#86.#841;	//  scala/collection/SeqLike$class.patch:(Lscala/collection/SeqLike;ILscala/collection/Seq;ILscala/collection/generic/CanBuildFrom;)Ljava/lang/Object;
const #843 = Asciz	replaced;
const #844 = Asciz	removeDuplicates;
const #845 = NameAndType	#844:#779;//  removeDuplicates:(Lscala/collection/SeqLike;)Ljava/lang/Object;
const #846 = Method	#86.#845;	//  scala/collection/SeqLike$class.removeDuplicates:(Lscala/collection/SeqLike;)Ljava/lang/Object;
const #847 = Asciz	intersect;
const #848 = Asciz	(Lscala/collection/Seq;)Ljava/lang/Object;;
const #849 = Asciz	(Lscala/collection/SeqLike;Lscala/collection/Seq;)Ljava/lang/Object;;
const #850 = NameAndType	#847:#849;//  intersect:(Lscala/collection/SeqLike;Lscala/collection/Seq;)Ljava/lang/Object;
const #851 = Method	#86.#850;	//  scala/collection/SeqLike$class.intersect:(Lscala/collection/SeqLike;Lscala/collection/Seq;)Ljava/lang/Object;
const #852 = Asciz	diff;
const #853 = NameAndType	#852:#849;//  diff:(Lscala/collection/SeqLike;Lscala/collection/Seq;)Ljava/lang/Object;
const #854 = Method	#86.#853;	//  scala/collection/SeqLike$class.diff:(Lscala/collection/SeqLike;Lscala/collection/Seq;)Ljava/lang/Object;
const #855 = Asciz	union;
const #856 = Asciz	(Lscala/collection/Seq;Lscala/collection/generic/CanBuildFrom;)Ljava/lang/Object;;
const #857 = Asciz	(Lscala/collection/SeqLike;Lscala/collection/Seq;Lscala/collection/generic/CanBuildFrom;)Ljava/lang/Object;;
const #858 = NameAndType	#855:#857;//  union:(Lscala/collection/SeqLike;Lscala/collection/Seq;Lscala/collection/generic/CanBuildFrom;)Ljava/lang/Object;
const #859 = Method	#86.#858;	//  scala/collection/SeqLike$class.union:(Lscala/collection/SeqLike;Lscala/collection/Seq;Lscala/collection/generic/CanBuildFrom;)Ljava/lang/Object;
const #860 = Asciz	contains;
const #861 = NameAndType	#860:#438;//  contains:(Lscala/collection/SeqLike;Ljava/lang/Object;)Z
const #862 = Method	#86.#861;	//  scala/collection/SeqLike$class.contains:(Lscala/collection/SeqLike;Ljava/lang/Object;)Z
const #863 = Asciz	containsSlice;
const #864 = Asciz	(Lscala/collection/Seq;)Z;
const #865 = Asciz	(Lscala/collection/SeqLike;Lscala/collection/Seq;)Z;
const #866 = NameAndType	#863:#865;//  containsSlice:(Lscala/collection/SeqLike;Lscala/collection/Seq;)Z
const #867 = Method	#86.#866;	//  scala/collection/SeqLike$class.containsSlice:(Lscala/collection/SeqLike;Lscala/collection/Seq;)Z
const #868 = Asciz	(Lscala/collection/SeqLike;Lscala/collection/Seq;I)I;
const #869 = NameAndType	#281:#868;//  lastIndexOfSlice:(Lscala/collection/SeqLike;Lscala/collection/Seq;I)I
const #870 = Method	#86.#869;	//  scala/collection/SeqLike$class.lastIndexOfSlice:(Lscala/collection/SeqLike;Lscala/collection/Seq;I)I
const #871 = Asciz	(Lscala/collection/Seq;)I;
const #872 = Asciz	(Lscala/collection/SeqLike;Lscala/collection/Seq;)I;
const #873 = NameAndType	#281:#872;//  lastIndexOfSlice:(Lscala/collection/SeqLike;Lscala/collection/Seq;)I
const #874 = Method	#86.#873;	//  scala/collection/SeqLike$class.lastIndexOfSlice:(Lscala/collection/SeqLike;Lscala/collection/Seq;)I
const #875 = NameAndType	#291:#868;//  indexOfSlice:(Lscala/collection/SeqLike;Lscala/collection/Seq;I)I
const #876 = Method	#86.#875;	//  scala/collection/SeqLike$class.indexOfSlice:(Lscala/collection/SeqLike;Lscala/collection/Seq;I)I
const #877 = NameAndType	#291:#872;//  indexOfSlice:(Lscala/collection/SeqLike;Lscala/collection/Seq;)I
const #878 = Method	#86.#877;	//  scala/collection/SeqLike$class.indexOfSlice:(Lscala/collection/SeqLike;Lscala/collection/Seq;)I
const #879 = Asciz	startsWith;
const #880 = NameAndType	#879:#865;//  startsWith:(Lscala/collection/SeqLike;Lscala/collection/Seq;)Z
const #881 = Method	#86.#880;	//  scala/collection/SeqLike$class.startsWith:(Lscala/collection/SeqLike;Lscala/collection/Seq;)Z
const #882 = Asciz	reversedElements;
const #883 = Asciz	(Lscala/collection/SeqLike;)Lscala/collection/Iterator;;
const #884 = NameAndType	#882:#883;//  reversedElements:(Lscala/collection/SeqLike;)Lscala/collection/Iterator;
const #885 = Method	#86.#884;	//  scala/collection/SeqLike$class.reversedElements:(Lscala/collection/SeqLike;)Lscala/collection/Iterator;
const #886 = Asciz	reverseMap;
const #887 = Asciz	(Lscala/collection/SeqLike;Lscala/Function1;Lscala/collection/generic/CanBuildFrom;)Ljava/lang/Object;;
const #888 = NameAndType	#886:#887;//  reverseMap:(Lscala/collection/SeqLike;Lscala/Function1;Lscala/collection/generic/CanBuildFrom;)Ljava/lang/Object;
const #889 = Method	#86.#888;	//  scala/collection/SeqLike$class.reverseMap:(Lscala/collection/SeqLike;Lscala/Function1;Lscala/collection/generic/CanBuildFrom;)Ljava/lang/Object;
const #890 = Asciz	lastIndexWhere;
const #891 = NameAndType	#890:#788;//  lastIndexWhere:(Lscala/collection/SeqLike;Lscala/Function1;)I
const #892 = Method	#86.#891;	//  scala/collection/SeqLike$class.lastIndexWhere:(Lscala/collection/SeqLike;Lscala/Function1;)I
const #893 = Asciz	(Ljava/lang/Object;I)I;
const #894 = Asciz	(Lscala/collection/SeqLike;Ljava/lang/Object;I)I;
const #895 = NameAndType	#270:#894;//  lastIndexOf:(Lscala/collection/SeqLike;Ljava/lang/Object;I)I
const #896 = Method	#86.#895;	//  scala/collection/SeqLike$class.lastIndexOf:(Lscala/collection/SeqLike;Ljava/lang/Object;I)I
const #897 = Asciz	(Lscala/collection/SeqLike;Ljava/lang/Object;)I;
const #898 = NameAndType	#270:#897;//  lastIndexOf:(Lscala/collection/SeqLike;Ljava/lang/Object;)I
const #899 = Method	#86.#898;	//  scala/collection/SeqLike$class.lastIndexOf:(Lscala/collection/SeqLike;Ljava/lang/Object;)I
const #900 = NameAndType	#290:#894;//  indexOf:(Lscala/collection/SeqLike;Ljava/lang/Object;I)I
const #901 = Method	#86.#900;	//  scala/collection/SeqLike$class.indexOf:(Lscala/collection/SeqLike;Ljava/lang/Object;I)I
const #902 = NameAndType	#290:#897;//  indexOf:(Lscala/collection/SeqLike;Ljava/lang/Object;)I
const #903 = Method	#86.#902;	//  scala/collection/SeqLike$class.indexOf:(Lscala/collection/SeqLike;Ljava/lang/Object;)I
const #904 = Asciz	findIndexOf;
const #905 = NameAndType	#904:#788;//  findIndexOf:(Lscala/collection/SeqLike;Lscala/Function1;)I
const #906 = Method	#86.#905;	//  scala/collection/SeqLike$class.findIndexOf:(Lscala/collection/SeqLike;Lscala/Function1;)I
const #907 = Asciz	indexWhere;
const #908 = NameAndType	#907:#788;//  indexWhere:(Lscala/collection/SeqLike;Lscala/Function1;)I
const #909 = Method	#86.#908;	//  scala/collection/SeqLike$class.indexWhere:(Lscala/collection/SeqLike;Lscala/Function1;)I
const #910 = Asciz	prefixLength;
const #911 = NameAndType	#910:#788;//  prefixLength:(Lscala/collection/SeqLike;Lscala/Function1;)I
const #912 = Method	#86.#911;	//  scala/collection/SeqLike$class.prefixLength:(Lscala/collection/SeqLike;Lscala/Function1;)I
const #913 = Asciz	(Lscala/collection/SeqLike;I)Z;
const #914 = NameAndType	#221:#913;//  isDefinedAt:(Lscala/collection/SeqLike;I)Z
const #915 = Method	#86.#914;	//  scala/collection/SeqLike$class.isDefinedAt:(Lscala/collection/SeqLike;I)Z
const #916 = NameAndType	#527:#792;//  size:(Lscala/collection/SeqLike;)I
const #917 = Method	#86.#916;	//  scala/collection/SeqLike$class.size:(Lscala/collection/SeqLike;)I
const #918 = Asciz	endsWith;
const #919 = Asciz	(Lscala/collection/IndexedSeqLike;Lscala/collection/Seq;)Z;
const #920 = NameAndType	#918:#919;//  endsWith:(Lscala/collection/IndexedSeqLike;Lscala/collection/Seq;)Z
const #921 = Method	#101.#920;	//  scala/collection/IndexedSeqLike$class.endsWith:(Lscala/collection/IndexedSeqLike;Lscala/collection/Seq;)Z
const #922 = Asciz	(Lscala/collection/Seq;I)Z;
const #923 = Asciz	(Lscala/collection/IndexedSeqLike;Lscala/collection/Seq;I)Z;
const #924 = NameAndType	#879:#923;//  startsWith:(Lscala/collection/IndexedSeqLike;Lscala/collection/Seq;I)Z
const #925 = Method	#101.#924;	//  scala/collection/IndexedSeqLike$class.startsWith:(Lscala/collection/IndexedSeqLike;Lscala/collection/Seq;I)Z
const #926 = Asciz	reverseIterator;
const #927 = Asciz	(Lscala/collection/IndexedSeqLike;)Lscala/collection/Iterator;;
const #928 = NameAndType	#926:#927;//  reverseIterator:(Lscala/collection/IndexedSeqLike;)Lscala/collection/Iterator;
const #929 = Method	#101.#928;	//  scala/collection/IndexedSeqLike$class.reverseIterator:(Lscala/collection/IndexedSeqLike;)Lscala/collection/Iterator;
const #930 = Asciz	(Lscala/Function1;I)I;
const #931 = Asciz	(Lscala/collection/IndexedSeqLike;Lscala/Function1;I)I;
const #932 = NameAndType	#890:#931;//  lastIndexWhere:(Lscala/collection/IndexedSeqLike;Lscala/Function1;I)I
const #933 = Method	#101.#932;	//  scala/collection/IndexedSeqLike$class.lastIndexWhere:(Lscala/collection/IndexedSeqLike;Lscala/Function1;I)I
const #934 = NameAndType	#907:#931;//  indexWhere:(Lscala/collection/IndexedSeqLike;Lscala/Function1;I)I
const #935 = Method	#101.#934;	//  scala/collection/IndexedSeqLike$class.indexWhere:(Lscala/collection/IndexedSeqLike;Lscala/Function1;I)I
const #936 = Asciz	segmentLength;
const #937 = NameAndType	#936:#931;//  segmentLength:(Lscala/collection/IndexedSeqLike;Lscala/Function1;I)I
const #938 = Method	#101.#937;	//  scala/collection/IndexedSeqLike$class.segmentLength:(Lscala/collection/IndexedSeqLike;Lscala/Function1;I)I
const #939 = Asciz	lengthCompare;
const #940 = Asciz	(Lscala/collection/IndexedSeqLike;I)I;
const #941 = NameAndType	#939:#940;//  lengthCompare:(Lscala/collection/IndexedSeqLike;I)I
const #942 = Method	#101.#941;	//  scala/collection/IndexedSeqLike$class.lengthCompare:(Lscala/collection/IndexedSeqLike;I)I
const #943 = Asciz	(Ljava/lang/Object;II)V;
const #944 = Asciz	(Lscala/collection/IndexedSeqLike;Ljava/lang/Object;II)V;
const #945 = NameAndType	#581:#944;//  copyToArray:(Lscala/collection/IndexedSeqLike;Ljava/lang/Object;II)V
const #946 = Method	#101.#945;	//  scala/collection/IndexedSeqLike$class.copyToArray:(Lscala/collection/IndexedSeqLike;Ljava/lang/Object;II)V
const #947 = Asciz	sameElements;
const #948 = Asciz	(Lscala/collection/Iterable;)Z;
const #949 = Asciz	(Lscala/collection/IndexedSeqLike;Lscala/collection/Iterable;)Z;
const #950 = NameAndType	#947:#949;//  sameElements:(Lscala/collection/IndexedSeqLike;Lscala/collection/Iterable;)Z
const #951 = Method	#101.#950;	//  scala/collection/IndexedSeqLike$class.sameElements:(Lscala/collection/IndexedSeqLike;Lscala/collection/Iterable;)Z
const #952 = Asciz	span;
const #953 = Asciz	(Lscala/collection/IndexedSeqLike;Lscala/Function1;)Lscala/Tuple2;;
const #954 = NameAndType	#952:#953;//  span:(Lscala/collection/IndexedSeqLike;Lscala/Function1;)Lscala/Tuple2;
const #955 = Method	#101.#954;	//  scala/collection/IndexedSeqLike$class.span:(Lscala/collection/IndexedSeqLike;Lscala/Function1;)Lscala/Tuple2;
const #956 = Asciz	dropWhile;
const #957 = Asciz	(Lscala/collection/IndexedSeqLike;Lscala/Function1;)Ljava/lang/Object;;
const #958 = NameAndType	#956:#957;//  dropWhile:(Lscala/collection/IndexedSeqLike;Lscala/Function1;)Ljava/lang/Object;
const #959 = Method	#101.#958;	//  scala/collection/IndexedSeqLike$class.dropWhile:(Lscala/collection/IndexedSeqLike;Lscala/Function1;)Ljava/lang/Object;
const #960 = Asciz	takeWhile;
const #961 = NameAndType	#960:#957;//  takeWhile:(Lscala/collection/IndexedSeqLike;Lscala/Function1;)Ljava/lang/Object;
const #962 = Method	#101.#961;	//  scala/collection/IndexedSeqLike$class.takeWhile:(Lscala/collection/IndexedSeqLike;Lscala/Function1;)Ljava/lang/Object;
const #963 = Asciz	splitAt;
const #964 = Asciz	(I)Lscala/Tuple2;;
const #965 = Asciz	(Lscala/collection/IndexedSeqLike;I)Lscala/Tuple2;;
const #966 = NameAndType	#963:#965;//  splitAt:(Lscala/collection/IndexedSeqLike;I)Lscala/Tuple2;
const #967 = Method	#101.#966;	//  scala/collection/IndexedSeqLike$class.splitAt:(Lscala/collection/IndexedSeqLike;I)Lscala/Tuple2;
const #968 = Asciz	dropRight;
const #969 = Asciz	(Lscala/collection/IndexedSeqLike;I)Ljava/lang/Object;;
const #970 = NameAndType	#968:#969;//  dropRight:(Lscala/collection/IndexedSeqLike;I)Ljava/lang/Object;
const #971 = Method	#101.#970;	//  scala/collection/IndexedSeqLike$class.dropRight:(Lscala/collection/IndexedSeqLike;I)Ljava/lang/Object;
const #972 = Asciz	takeRight;
const #973 = NameAndType	#972:#969;//  takeRight:(Lscala/collection/IndexedSeqLike;I)Ljava/lang/Object;
const #974 = Method	#101.#973;	//  scala/collection/IndexedSeqLike$class.takeRight:(Lscala/collection/IndexedSeqLike;I)Ljava/lang/Object;
const #975 = Asciz	drop;
const #976 = NameAndType	#975:#969;//  drop:(Lscala/collection/IndexedSeqLike;I)Ljava/lang/Object;
const #977 = Method	#101.#976;	//  scala/collection/IndexedSeqLike$class.drop:(Lscala/collection/IndexedSeqLike;I)Ljava/lang/Object;
const #978 = Asciz	take;
const #979 = NameAndType	#978:#969;//  take:(Lscala/collection/IndexedSeqLike;I)Ljava/lang/Object;
const #980 = Method	#101.#979;	//  scala/collection/IndexedSeqLike$class.take:(Lscala/collection/IndexedSeqLike;I)Ljava/lang/Object;
const #981 = Asciz	init;
const #982 = Asciz	(Lscala/collection/IndexedSeqLike;)Ljava/lang/Object;;
const #983 = NameAndType	#981:#982;//  init:(Lscala/collection/IndexedSeqLike;)Ljava/lang/Object;
const #984 = Method	#101.#983;	//  scala/collection/IndexedSeqLike$class.init:(Lscala/collection/IndexedSeqLike;)Ljava/lang/Object;
const #985 = Asciz	last;
const #986 = NameAndType	#985:#982;//  last:(Lscala/collection/IndexedSeqLike;)Ljava/lang/Object;
const #987 = Method	#101.#986;	//  scala/collection/IndexedSeqLike$class.last:(Lscala/collection/IndexedSeqLike;)Ljava/lang/Object;
const #988 = Asciz	tail;
const #989 = NameAndType	#988:#982;//  tail:(Lscala/collection/IndexedSeqLike;)Ljava/lang/Object;
const #990 = Method	#101.#989;	//  scala/collection/IndexedSeqLike$class.tail:(Lscala/collection/IndexedSeqLike;)Ljava/lang/Object;
const #991 = Asciz	head;
const #992 = NameAndType	#991:#982;//  head:(Lscala/collection/IndexedSeqLike;)Ljava/lang/Object;
const #993 = Method	#101.#992;	//  scala/collection/IndexedSeqLike$class.head:(Lscala/collection/IndexedSeqLike;)Ljava/lang/Object;
const #994 = Asciz	slice;
const #995 = Asciz	(II)Ljava/lang/Object;;
const #996 = Asciz	(Lscala/collection/IndexedSeqLike;II)Ljava/lang/Object;;
const #997 = NameAndType	#994:#996;//  slice:(Lscala/collection/IndexedSeqLike;II)Ljava/lang/Object;
const #998 = Method	#101.#997;	//  scala/collection/IndexedSeqLike$class.slice:(Lscala/collection/IndexedSeqLike;II)Ljava/lang/Object;
const #999 = Asciz	zipWithIndex;
const #1000 = Asciz	(Lscala/collection/generic/CanBuildFrom;)Ljava/lang/Object;;
const #1001 = Asciz	(Lscala/collection/IndexedSeqLike;Lscala/collection/generic/CanBuildFrom;)Ljava/lang/Object;;
const #1002 = NameAndType	#999:#1001;//  zipWithIndex:(Lscala/collection/IndexedSeqLike;Lscala/collection/generic/CanBuildFrom;)Ljava/lang/Object;
const #1003 = Method	#101.#1002;	//  scala/collection/IndexedSeqLike$class.zipWithIndex:(Lscala/collection/IndexedSeqLike;Lscala/collection/generic/CanBuildFrom;)Ljava/lang/Object;
const #1004 = Asciz	zip;
const #1005 = Asciz	(Lscala/collection/Iterable;Lscala/collection/generic/CanBuildFrom;)Ljava/lang/Object;;
const #1006 = Asciz	(Lscala/collection/IndexedSeqLike;Lscala/collection/Iterable;Lscala/collection/generic/CanBuildFrom;)Ljava/lang/Object;;
const #1007 = NameAndType	#1004:#1006;//  zip:(Lscala/collection/IndexedSeqLike;Lscala/collection/Iterable;Lscala/collection/generic/CanBuildFrom;)Ljava/lang/Object;
const #1008 = Method	#101.#1007;	//  scala/collection/IndexedSeqLike$class.zip:(Lscala/collection/IndexedSeqLike;Lscala/collection/Iterable;Lscala/collection/generic/CanBuildFrom;)Ljava/lang/Object;
const #1009 = Asciz	reduceRight;
const #1010 = Asciz	(Lscala/collection/IndexedSeqLike;Lscala/Function2;)Ljava/lang/Object;;
const #1011 = NameAndType	#1009:#1010;//  reduceRight:(Lscala/collection/IndexedSeqLike;Lscala/Function2;)Ljava/lang/Object;
const #1012 = Method	#101.#1011;	//  scala/collection/IndexedSeqLike$class.reduceRight:(Lscala/collection/IndexedSeqLike;Lscala/Function2;)Ljava/lang/Object;
const #1013 = Asciz	reduceLeft;
const #1014 = NameAndType	#1013:#1010;//  reduceLeft:(Lscala/collection/IndexedSeqLike;Lscala/Function2;)Ljava/lang/Object;
const #1015 = Method	#101.#1014;	//  scala/collection/IndexedSeqLike$class.reduceLeft:(Lscala/collection/IndexedSeqLike;Lscala/Function2;)Ljava/lang/Object;
const #1016 = Asciz	foldRight;
const #1017 = Asciz	(Lscala/collection/IndexedSeqLike;Ljava/lang/Object;Lscala/Function2;)Ljava/lang/Object;;
const #1018 = NameAndType	#1016:#1017;//  foldRight:(Lscala/collection/IndexedSeqLike;Ljava/lang/Object;Lscala/Function2;)Ljava/lang/Object;
const #1019 = Method	#101.#1018;	//  scala/collection/IndexedSeqLike$class.foldRight:(Lscala/collection/IndexedSeqLike;Ljava/lang/Object;Lscala/Function2;)Ljava/lang/Object;
const #1020 = Asciz	foldLeft;
const #1021 = NameAndType	#1020:#1017;//  foldLeft:(Lscala/collection/IndexedSeqLike;Ljava/lang/Object;Lscala/Function2;)Ljava/lang/Object;
const #1022 = Method	#101.#1021;	//  scala/collection/IndexedSeqLike$class.foldLeft:(Lscala/collection/IndexedSeqLike;Ljava/lang/Object;Lscala/Function2;)Ljava/lang/Object;
const #1023 = Asciz	find;
const #1024 = Asciz	(Lscala/Function1;)Lscala/Option;;
const #1025 = Asciz	(Lscala/collection/IndexedSeqLike;Lscala/Function1;)Lscala/Option;;
const #1026 = NameAndType	#1023:#1025;//  find:(Lscala/collection/IndexedSeqLike;Lscala/Function1;)Lscala/Option;
const #1027 = Method	#101.#1026;	//  scala/collection/IndexedSeqLike$class.find:(Lscala/collection/IndexedSeqLike;Lscala/Function1;)Lscala/Option;
const #1028 = Asciz	exists;
const #1029 = Asciz	(Lscala/Function1;)Z;
const #1030 = Asciz	(Lscala/collection/IndexedSeqLike;Lscala/Function1;)Z;
const #1031 = NameAndType	#1028:#1030;//  exists:(Lscala/collection/IndexedSeqLike;Lscala/Function1;)Z
const #1032 = Method	#101.#1031;	//  scala/collection/IndexedSeqLike$class.exists:(Lscala/collection/IndexedSeqLike;Lscala/Function1;)Z
const #1033 = Asciz	forall;
const #1034 = NameAndType	#1033:#1030;//  forall:(Lscala/collection/IndexedSeqLike;Lscala/Function1;)Z
const #1035 = Method	#101.#1034;	//  scala/collection/IndexedSeqLike$class.forall:(Lscala/collection/IndexedSeqLike;Lscala/Function1;)Z
const #1036 = Asciz	foreach;
const #1037 = Asciz	(Lscala/collection/IndexedSeqLike;Lscala/Function1;)V;
const #1038 = NameAndType	#1036:#1037;//  foreach:(Lscala/collection/IndexedSeqLike;Lscala/Function1;)V
const #1039 = Method	#101.#1038;	//  scala/collection/IndexedSeqLike$class.foreach:(Lscala/collection/IndexedSeqLike;Lscala/Function1;)V
const #1040 = Asciz	isEmpty;
const #1041 = Asciz	(Lscala/collection/IndexedSeqLike;)Z;
const #1042 = NameAndType	#1040:#1041;//  isEmpty:(Lscala/collection/IndexedSeqLike;)Z
const #1043 = Method	#101.#1042;	//  scala/collection/IndexedSeqLike$class.isEmpty:(Lscala/collection/IndexedSeqLike;)Z
const #1044 = Asciz	iterator;
const #1045 = NameAndType	#1044:#927;//  iterator:(Lscala/collection/IndexedSeqLike;)Lscala/collection/Iterator;
const #1046 = Method	#101.#1045;	//  scala/collection/IndexedSeqLike$class.iterator:(Lscala/collection/IndexedSeqLike;)Lscala/collection/Iterator;
const #1047 = Asciz	scala$collection$IndexedSeqLike$$super$endsWith;
const #1048 = NameAndType	#918:#865;//  endsWith:(Lscala/collection/SeqLike;Lscala/collection/Seq;)Z
const #1049 = Method	#86.#1048;	//  scala/collection/SeqLike$class.endsWith:(Lscala/collection/SeqLike;Lscala/collection/Seq;)Z
const #1050 = Asciz	scala$collection$IndexedSeqLike$$super$sameElements;
const #1051 = Asciz	(Lscala/collection/IterableLike;Lscala/collection/Iterable;)Z;
const #1052 = NameAndType	#947:#1051;//  sameElements:(Lscala/collection/IterableLike;Lscala/collection/Iterable;)Z
const #1053 = Method	#61.#1052;	//  scala/collection/IterableLike$class.sameElements:(Lscala/collection/IterableLike;Lscala/collection/Iterable;)Z
const #1054 = Asciz	scala$collection$IndexedSeqLike$$super$init;
const #1055 = NameAndType	#981:#701;//  init:(Lscala/collection/TraversableLike;)Ljava/lang/Object;
const #1056 = Method	#41.#1055;	//  scala/collection/TraversableLike$class.init:(Lscala/collection/TraversableLike;)Ljava/lang/Object;
const #1057 = Asciz	scala$collection$IndexedSeqLike$$super$last;
const #1058 = NameAndType	#985:#701;//  last:(Lscala/collection/TraversableLike;)Ljava/lang/Object;
const #1059 = Method	#41.#1058;	//  scala/collection/TraversableLike$class.last:(Lscala/collection/TraversableLike;)Ljava/lang/Object;
const #1060 = Asciz	scala$collection$IndexedSeqLike$$super$tail;
const #1061 = NameAndType	#988:#701;//  tail:(Lscala/collection/TraversableLike;)Ljava/lang/Object;
const #1062 = Method	#41.#1061;	//  scala/collection/TraversableLike$class.tail:(Lscala/collection/TraversableLike;)Ljava/lang/Object;
const #1063 = Asciz	scala$collection$IndexedSeqLike$$super$head;
const #1064 = NameAndType	#991:#731;//  head:(Lscala/collection/IterableLike;)Ljava/lang/Object;
const #1065 = Method	#61.#1064;	//  scala/collection/IterableLike$class.head:(Lscala/collection/IterableLike;)Ljava/lang/Object;
const #1066 = Asciz	scala$collection$IndexedSeqLike$$super$zip;
const #1067 = Asciz	(Lscala/collection/IterableLike;Lscala/collection/Iterable;Lscala/collection/generic/CanBuildFrom;)Ljava/lang/Object;;
const #1068 = NameAndType	#1004:#1067;//  zip:(Lscala/collection/IterableLike;Lscala/collection/Iterable;Lscala/collection/generic/CanBuildFrom;)Ljava/lang/Object;
const #1069 = Method	#61.#1068;	//  scala/collection/IterableLike$class.zip:(Lscala/collection/IterableLike;Lscala/collection/Iterable;Lscala/collection/generic/CanBuildFrom;)Ljava/lang/Object;
const #1070 = Asciz	scala$collection$IndexedSeqLike$$super$reduceRight;
const #1071 = Asciz	(Lscala/collection/IterableLike;Lscala/Function2;)Ljava/lang/Object;;
const #1072 = NameAndType	#1009:#1071;//  reduceRight:(Lscala/collection/IterableLike;Lscala/Function2;)Ljava/lang/Object;
const #1073 = Method	#61.#1072;	//  scala/collection/IterableLike$class.reduceRight:(Lscala/collection/IterableLike;Lscala/Function2;)Ljava/lang/Object;
const #1074 = Asciz	scala$collection$IndexedSeqLike$$super$reduceLeft;
const #1075 = Asciz	(Lscala/collection/TraversableLike;Lscala/Function2;)Ljava/lang/Object;;
const #1076 = NameAndType	#1013:#1075;//  reduceLeft:(Lscala/collection/TraversableLike;Lscala/Function2;)Ljava/lang/Object;
const #1077 = Method	#41.#1076;	//  scala/collection/TraversableLike$class.reduceLeft:(Lscala/collection/TraversableLike;Lscala/Function2;)Ljava/lang/Object;
const #1078 = Asciz	(Lscala/collection/mutable/IndexedSeqLike;II)Lscala/collection/mutable/IndexedSeqView;;
const #1079 = NameAndType	#211:#1078;//  view:(Lscala/collection/mutable/IndexedSeqLike;II)Lscala/collection/mutable/IndexedSeqView;
const #1080 = Method	#111.#1079;	//  scala/collection/mutable/IndexedSeqLike$class.view:(Lscala/collection/mutable/IndexedSeqLike;II)Lscala/collection/mutable/IndexedSeqView;
const #1081 = Asciz	(Lscala/collection/mutable/IndexedSeqLike;)Ljava/lang/Object;;
const #1082 = NameAndType	#211:#1081;//  view:(Lscala/collection/mutable/IndexedSeqLike;)Ljava/lang/Object;
const #1083 = Method	#111.#1082;	//  scala/collection/mutable/IndexedSeqLike$class.view:(Lscala/collection/mutable/IndexedSeqLike;)Ljava/lang/Object;
const #1084 = Asciz	(Lscala/collection/mutable/IndexedSeqLike;Ljava/lang/Object;)Lscala/collection/mutable/IndexedSeq;;
const #1085 = NameAndType	#202:#1084;//  toCollection:(Lscala/collection/mutable/IndexedSeqLike;Ljava/lang/Object;)Lscala/collection/mutable/IndexedSeq;
const #1086 = Method	#111.#1085;	//  scala/collection/mutable/IndexedSeqLike$class.toCollection:(Lscala/collection/mutable/IndexedSeqLike;Ljava/lang/Object;)Lscala/collection/mutable/IndexedSeq;
const #1087 = Asciz	(Lscala/collection/mutable/IndexedSeqLike;)Lscala/collection/mutable/IndexedSeq;;
const #1088 = NameAndType	#192:#1087;//  thisCollection:(Lscala/collection/mutable/IndexedSeqLike;)Lscala/collection/mutable/IndexedSeq;
const #1089 = Method	#111.#1088;	//  scala/collection/mutable/IndexedSeqLike$class.thisCollection:(Lscala/collection/mutable/IndexedSeqLike;)Lscala/collection/mutable/IndexedSeq;
const #1090 = Asciz	companion;
const #1091 = Asciz	()Lscala/collection/generic/GenericCompanion;;
const #1092 = Asciz	(Lscala/collection/mutable/IndexedSeq;)Lscala/collection/generic/GenericCompanion;;
const #1093 = NameAndType	#1090:#1092;//  companion:(Lscala/collection/mutable/IndexedSeq;)Lscala/collection/generic/GenericCompanion;
const #1094 = Method	#116.#1093;	//  scala/collection/mutable/IndexedSeq$class.companion:(Lscala/collection/mutable/IndexedSeq;)Lscala/collection/generic/GenericCompanion;
const #1095 = Asciz	Ljava/lang/Object;Lscala/collection/mutable/Builder<Ljava/lang/Character;Ljava/lang/String;>;Lscala/collection/mutable/IndexedSeq<Ljava/lang/Character;>;Lscala/ScalaObject;;
const #1096 = Asciz	ScalaSig;
const #1097 = Asciz	InnerClasses;
const #1098 = Asciz	scala/collection/TraversableLike$WithFilter;
const #1099 = class	#1098;	//  scala/collection/TraversableLike$WithFilter
const #1100 = Asciz	WithFilter;
const #1101 = Asciz	$anonfun$setLength$1;
const #1102 = Asciz	scala/collection/mutable/Builder;
const #1103 = class	#1102;	//  scala/collection/mutable/Builder
const #1104 = Asciz	scala/collection/mutable/IndexedSeq;
const #1105 = class	#1104;	//  scala/collection/mutable/IndexedSeq
const #1106 = Asciz	scala/ScalaObject;
const #1107 = class	#1106;	//  scala/ScalaObject
const #1108 = Asciz	java/io/Serializable;
const #1109 = class	#1108;	//  java/io/Serializable

{
public static final long serialVersionUID;

public static {};
  Code:
   Stack=2, Locals=0, Args_size=0
   0:	ldc2_w	#8; //long -8525408645367278351l
   3:	putstatic	#13; //Field serialVersionUID:J
   6:	return

public scala.collection.mutable.StringBuilder(int, java.lang.String);
  Code:
   Stack=3, Locals=3, Args_size=3
   0:	aload_0
   1:	aload_2
   2:	putfield	#24; //Field initValue:Ljava/lang/String;
   5:	aload_0
   6:	invokespecial	#28; //Method java/lang/Object."<init>":()V
   9:	aload_0
   10:	invokestatic	#34; //Method scala/collection/generic/Growable$class.$init$:(Lscala/collection/generic/Growable;)V
   13:	aload_0
   14:	invokestatic	#39; //Method scala/collection/mutable/Builder$class.$init$:(Lscala/collection/mutable/Builder;)V
   17:	aload_0
   18:	invokestatic	#44; //Method scala/collection/TraversableLike$class.$init$:(Lscala/collection/TraversableLike;)V
   21:	aload_0
   22:	invokestatic	#49; //Method scala/collection/generic/GenericTraversableTemplate$class.$init$:(Lscala/collection/generic/GenericTraversableTemplate;)V
   25:	aload_0
   26:	invokestatic	#54; //Method scala/collection/Traversable$class.$init$:(Lscala/collection/Traversable;)V
   29:	aload_0
   30:	invokestatic	#59; //Method scala/collection/mutable/Traversable$class.$init$:(Lscala/collection/mutable/Traversable;)V
   33:	aload_0
   34:	invokestatic	#64; //Method scala/collection/IterableLike$class.$init$:(Lscala/collection/IterableLike;)V
   37:	aload_0
   38:	invokestatic	#69; //Method scala/collection/Iterable$class.$init$:(Lscala/collection/Iterable;)V
   41:	aload_0
   42:	invokestatic	#74; //Method scala/collection/mutable/Iterable$class.$init$:(Lscala/collection/mutable/Iterable;)V
   45:	aload_0
   46:	invokestatic	#79; //Method scala/Function1$class.$init$:(Lscala/Function1;)V
   49:	aload_0
   50:	invokestatic	#84; //Method scala/PartialFunction$class.$init$:(Lscala/PartialFunction;)V
   53:	aload_0
   54:	invokestatic	#89; //Method scala/collection/SeqLike$class.$init$:(Lscala/collection/SeqLike;)V
   57:	aload_0
   58:	invokestatic	#94; //Method scala/collection/Seq$class.$init$:(Lscala/collection/Seq;)V
   61:	aload_0
   62:	invokestatic	#99; //Method scala/collection/mutable/Seq$class.$init$:(Lscala/collection/mutable/Seq;)V
   65:	aload_0
   66:	invokestatic	#104; //Method scala/collection/IndexedSeqLike$class.$init$:(Lscala/collection/IndexedSeqLike;)V
   69:	aload_0
   70:	invokestatic	#109; //Method scala/collection/IndexedSeq$class.$init$:(Lscala/collection/IndexedSeq;)V
   73:	aload_0
   74:	invokestatic	#114; //Method scala/collection/mutable/IndexedSeqLike$class.$init$:(Lscala/collection/mutable/IndexedSeqLike;)V
   77:	aload_0
   78:	invokestatic	#119; //Method scala/collection/mutable/IndexedSeq$class.$init$:(Lscala/collection/mutable/IndexedSeq;)V
   81:	getstatic	#125; //Field scala/Predef$.MODULE$:Lscala/Predef$;
   84:	iload_1
   85:	iconst_0
   86:	if_icmplt	93
   89:	iconst_1
   90:	goto	94
   93:	iconst_0
   94:	invokevirtual	#129; //Method scala/Predef$.require:(Z)V
   97:	aload_0
   98:	iload_1
   99:	aload_2
   100:	invokevirtual	#135; //Method java/lang/String.length:()I
   103:	iadd
   104:	newarray char
   106:	putfield	#137; //Field array:[C
   109:	aload_0
   110:	iconst_0
   111:	putfield	#139; //Field count:I
   114:	aload_0
   115:	aload_2
   116:	invokevirtual	#143; //Method append:(Ljava/lang/String;)Lscala/collection/mutable/StringBuilder;
   119:	pop
   120:	return
  LineNumberTable: 
   line 32: 0
   line 36: 81
   line 41: 97
   line 44: 109
   line 65: 114

  LocalVariableTable: 
   Start  Length  Slot  Name   Signature
   0      121      0    this       Lscala/collection/mutable/StringBuilder;
   0      121      1    initCapacity       I
   0      121      2    initValue       Ljava/lang/String;


public java.lang.Object apply(int);
  Code:
   Stack=2, Locals=3, Args_size=2
   0:	aload_0
   1:	iload_1
   2:	invokevirtual	#152; //Method apply:(I)C
   5:	istore_2
   6:	iload_2
   7:	invokestatic	#158; //Method scala/runtime/BoxesRunTime.boxToCharacter:(C)Ljava/lang/Character;
   10:	areturn
  LineNumberTable: 
   line 32: 0

  LocalVariableTable: 
   Start  Length  Slot  Name   Signature
   0      11      0    this       Lscala/collection/mutable/StringBuilder;
   0      11      1    idx       I


public java.lang.Object apply(java.lang.Object);
  Code:
   Stack=2, Locals=3, Args_size=2
   0:	aload_0
   1:	aload_1
   2:	invokestatic	#164; //Method scala/runtime/BoxesRunTime.unboxToInt:(Ljava/lang/Object;)I
   5:	invokevirtual	#152; //Method apply:(I)C
   8:	istore_2
   9:	iload_2
   10:	invokestatic	#158; //Method scala/runtime/BoxesRunTime.boxToCharacter:(C)Ljava/lang/Character;
   13:	areturn
  LineNumberTable: 
   line 32: 0

  LocalVariableTable: 
   Start  Length  Slot  Name   Signature
   0      14      0    this       Lscala/collection/mutable/StringBuilder;
   0      14      1    v1       Ljava/lang/Object;


public void update(int, java.lang.Object);
  Code:
   Stack=3, Locals=3, Args_size=3
   0:	aload_0
   1:	iload_1
   2:	aload_2
   3:	invokestatic	#172; //Method scala/runtime/BoxesRunTime.unboxToChar:(Ljava/lang/Object;)C
   6:	invokevirtual	#175; //Method update:(IC)V
   9:	return
  LineNumberTable: 
   line 32: 0

  LocalVariableTable: 
   Start  Length  Slot  Name   Signature
   0      10      0    this       Lscala/collection/mutable/StringBuilder;
   0      10      1    idx       I
   0      10      2    elem       Ljava/lang/Object;


public scala.collection.mutable.Builder $plus$eq(java.lang.Object);
  Code:
   Stack=2, Locals=2, Args_size=2
   0:	aload_0
   1:	aload_1
   2:	invokestatic	#172; //Method scala/runtime/BoxesRunTime.unboxToChar:(Ljava/lang/Object;)C
   5:	invokevirtual	#181; //Method $plus$eq:(C)Lscala/collection/mutable/StringBuilder;
   8:	areturn
  LineNumberTable: 
   line 32: 0

  LocalVariableTable: 
   Start  Length  Slot  Name   Signature
   0      9      0    this       Lscala/collection/mutable/StringBuilder;
   0      9      1    elem       Ljava/lang/Object;


public scala.collection.generic.Growable $plus$eq(java.lang.Object);
  Code:
   Stack=2, Locals=2, Args_size=2
   0:	aload_0
   1:	aload_1
   2:	invokestatic	#172; //Method scala/runtime/BoxesRunTime.unboxToChar:(Ljava/lang/Object;)C
   5:	invokevirtual	#181; //Method $plus$eq:(C)Lscala/collection/mutable/StringBuilder;
   8:	areturn
  LineNumberTable: 
   line 32: 0

  LocalVariableTable: 
   Start  Length  Slot  Name   Signature
   0      9      0    this       Lscala/collection/mutable/StringBuilder;
   0      9      1    elem       Ljava/lang/Object;


public java.lang.Object reverse();
  Code:
   Stack=1, Locals=1, Args_size=1
   0:	aload_0
   1:	invokevirtual	#187; //Method reverse:()Lscala/collection/mutable/StringBuilder;
   4:	areturn
  LineNumberTable: 
   line 32: 0


public java.lang.Object result();
  Code:
   Stack=1, Locals=1, Args_size=1
   0:	aload_0
   1:	invokevirtual	#191; //Method result:()Ljava/lang/String;
   4:	areturn
  LineNumberTable: 
   line 32: 0


public scala.collection.IndexedSeq thisCollection();
  Code:
   Stack=1, Locals=1, Args_size=1
   0:	aload_0
   1:	invokeinterface	#198,  1; //InterfaceMethod scala/collection/mutable/IndexedSeqLike.thisCollection:()Lscala/collection/mutable/IndexedSeq;
   6:	areturn
  LineNumberTable: 
   line 32: 0


public scala.collection.Seq thisCollection();
  Code:
   Stack=1, Locals=1, Args_size=1
   0:	aload_0
   1:	invokeinterface	#198,  1; //InterfaceMethod scala/collection/mutable/IndexedSeqLike.thisCollection:()Lscala/collection/mutable/IndexedSeq;
   6:	areturn
  LineNumberTable: 
   line 32: 0


public scala.collection.Iterable thisCollection();
  Code:
   Stack=1, Locals=1, Args_size=1
   0:	aload_0
   1:	invokeinterface	#198,  1; //InterfaceMethod scala/collection/mutable/IndexedSeqLike.thisCollection:()Lscala/collection/mutable/IndexedSeq;
   6:	areturn
  LineNumberTable: 
   line 32: 0


public scala.collection.Traversable thisCollection();
  Code:
   Stack=1, Locals=1, Args_size=1
   0:	aload_0
   1:	invokeinterface	#198,  1; //InterfaceMethod scala/collection/mutable/IndexedSeqLike.thisCollection:()Lscala/collection/mutable/IndexedSeq;
   6:	areturn
  LineNumberTable: 
   line 32: 0


public scala.collection.IndexedSeq toCollection(java.lang.Object);
  Code:
   Stack=2, Locals=2, Args_size=2
   0:	aload_0
   1:	aload_1
   2:	invokeinterface	#206,  2; //InterfaceMethod scala/collection/mutable/IndexedSeqLike.toCollection:(Ljava/lang/Object;)Lscala/collection/mutable/IndexedSeq;
   7:	areturn
  LineNumberTable: 
   line 32: 0

  LocalVariableTable: 
   Start  Length  Slot  Name   Signature
   0      8      0    this       Lscala/collection/mutable/StringBuilder;
   0      8      1    repr       Ljava/lang/Object;


public scala.collection.Seq toCollection(java.lang.Object);
  Code:
   Stack=2, Locals=2, Args_size=2
   0:	aload_0
   1:	aload_1
   2:	invokeinterface	#206,  2; //InterfaceMethod scala/collection/mutable/IndexedSeqLike.toCollection:(Ljava/lang/Object;)Lscala/collection/mutable/IndexedSeq;
   7:	areturn
  LineNumberTable: 
   line 32: 0

  LocalVariableTable: 
   Start  Length  Slot  Name   Signature
   0      8      0    this       Lscala/collection/mutable/StringBuilder;
   0      8      1    repr       Ljava/lang/Object;


public scala.collection.Iterable toCollection(java.lang.Object);
  Code:
   Stack=2, Locals=2, Args_size=2
   0:	aload_0
   1:	aload_1
   2:	invokeinterface	#206,  2; //InterfaceMethod scala/collection/mutable/IndexedSeqLike.toCollection:(Ljava/lang/Object;)Lscala/collection/mutable/IndexedSeq;
   7:	areturn
  LineNumberTable: 
   line 32: 0

  LocalVariableTable: 
   Start  Length  Slot  Name   Signature
   0      8      0    this       Lscala/collection/mutable/StringBuilder;
   0      8      1    repr       Ljava/lang/Object;


public scala.collection.Traversable toCollection(java.lang.Object);
  Code:
   Stack=2, Locals=2, Args_size=2
   0:	aload_0
   1:	aload_1
   2:	invokeinterface	#206,  2; //InterfaceMethod scala/collection/mutable/IndexedSeqLike.toCollection:(Ljava/lang/Object;)Lscala/collection/mutable/IndexedSeq;
   7:	areturn
  LineNumberTable: 
   line 32: 0

  LocalVariableTable: 
   Start  Length  Slot  Name   Signature
   0      8      0    this       Lscala/collection/mutable/StringBuilder;
   0      8      1    repr       Ljava/lang/Object;


public scala.collection.IndexedSeqView view(int, int);
  Code:
   Stack=3, Locals=3, Args_size=3
   0:	aload_0
   1:	iload_1
   2:	iload_2
   3:	invokeinterface	#215,  3; //InterfaceMethod scala/collection/mutable/IndexedSeqLike.view:(II)Lscala/collection/mutable/IndexedSeqView;
   8:	areturn
  LineNumberTable: 
   line 32: 0

  LocalVariableTable: 
   Start  Length  Slot  Name   Signature
   0      9      0    this       Lscala/collection/mutable/StringBuilder;
   0      9      1    from       I
   0      9      2    until       I


public scala.collection.SeqView view(int, int);
  Code:
   Stack=3, Locals=3, Args_size=3
   0:	aload_0
   1:	iload_1
   2:	iload_2
   3:	invokeinterface	#215,  3; //InterfaceMethod scala/collection/mutable/IndexedSeqLike.view:(II)Lscala/collection/mutable/IndexedSeqView;
   8:	areturn
  LineNumberTable: 
   line 32: 0

  LocalVariableTable: 
   Start  Length  Slot  Name   Signature
   0      9      0    this       Lscala/collection/mutable/StringBuilder;
   0      9      1    from       I
   0      9      2    until       I


public scala.collection.IterableView view(int, int);
  Code:
   Stack=3, Locals=3, Args_size=3
   0:	aload_0
   1:	iload_1
   2:	iload_2
   3:	invokeinterface	#215,  3; //InterfaceMethod scala/collection/mutable/IndexedSeqLike.view:(II)Lscala/collection/mutable/IndexedSeqView;
   8:	areturn
  LineNumberTable: 
   line 32: 0

  LocalVariableTable: 
   Start  Length  Slot  Name   Signature
   0      9      0    this       Lscala/collection/mutable/StringBuilder;
   0      9      1    from       I
   0      9      2    until       I


public scala.collection.TraversableView view(int, int);
  Code:
   Stack=3, Locals=3, Args_size=3
   0:	aload_0
   1:	iload_1
   2:	iload_2
   3:	invokeinterface	#215,  3; //InterfaceMethod scala/collection/mutable/IndexedSeqLike.view:(II)Lscala/collection/mutable/IndexedSeqView;
   8:	areturn
  LineNumberTable: 
   line 32: 0

  LocalVariableTable: 
   Start  Length  Slot  Name   Signature
   0      9      0    this       Lscala/collection/mutable/StringBuilder;
   0      9      1    from       I
   0      9      2    until       I


public boolean isDefinedAt(java.lang.Object);
  Code:
   Stack=2, Locals=2, Args_size=2
   0:	aload_0
   1:	aload_1
   2:	invokestatic	#164; //Method scala/runtime/BoxesRunTime.unboxToInt:(Ljava/lang/Object;)I
   5:	invokeinterface	#227,  2; //InterfaceMethod scala/collection/SeqLike.isDefinedAt:(I)Z
   10:	ireturn
  LineNumberTable: 
   line 32: 0

  LocalVariableTable: 
   Start  Length  Slot  Name   Signature
   0      11      0    this       Lscala/collection/mutable/StringBuilder;
   0      11      1    x       Ljava/lang/Object;


public scala.Function1 andThen(scala.Function1);
  Code:
   Stack=2, Locals=2, Args_size=2
   0:	aload_0
   1:	aload_1
   2:	invokeinterface	#235,  2; //InterfaceMethod scala/PartialFunction.andThen:(Lscala/Function1;)Lscala/PartialFunction;
   7:	areturn
  LineNumberTable: 
   line 32: 0

  LocalVariableTable: 
   Start  Length  Slot  Name   Signature
   0      8      0    this       Lscala/collection/mutable/StringBuilder;
   0      8      1    g       Lscala/Function1;


public java.lang.String result();
  Code:
   Stack=1, Locals=1, Args_size=1
   0:	aload_0
   1:	invokevirtual	#240; //Method toString:()Ljava/lang/String;
   4:	areturn
  LineNumberTable: 
   line 846: 0


public java.lang.String toString();
  Code:
   Stack=5, Locals=1, Args_size=1
   0:	new	#131; //class java/lang/String
   3:	dup
   4:	aload_0
   5:	invokespecial	#243; //Method array:()[C
   8:	iconst_0
   9:	aload_0
   10:	invokespecial	#245; //Method count:()I
   13:	invokespecial	#248; //Method java/lang/String."<init>":([CII)V
   16:	areturn
  LineNumberTable: 
   line 844: 0


public scala.collection.mutable.StringBuilder reverse();
  Code:
   Stack=3, Locals=9, Args_size=1
   0:	iconst_0
   1:	istore_1
   2:	aload_0
   3:	invokespecial	#245; //Method count:()I
   6:	iconst_1
   7:	isub
   8:	istore_2
   9:	iload_2
   10:	iconst_1
   11:	isub
   12:	iconst_1
   13:	ishr
   14:	istore_3
   15:	iload_3
   16:	iconst_0
   17:	if_icmplt	101
   20:	aload_0
   21:	invokespecial	#243; //Method array:()[C
   24:	iload_3
   25:	caload
   26:	istore	4
   28:	aload_0
   29:	invokespecial	#243; //Method array:()[C
   32:	iload_2
   33:	iload_3
   34:	isub
   35:	caload
   36:	istore	5
   38:	iload_1
   39:	ifne	76
   42:	iload	4
   44:	ldc	#249; //int 55296
   46:	if_icmplt	56
   49:	iload	4
   51:	ldc	#250; //int 57343
   53:	if_icmple	70
   56:	iload	5
   58:	ldc	#249; //int 55296
   60:	if_icmplt	74
   63:	iload	5
   65:	ldc	#250; //int 57343
   67:	if_icmpgt	74
   70:	iconst_1
   71:	goto	75
   74:	iconst_0
   75:	istore_1
   76:	aload_0
   77:	invokespecial	#243; //Method array:()[C
   80:	iload_3
   81:	iload	5
   83:	castore
   84:	aload_0
   85:	invokespecial	#243; //Method array:()[C
   88:	iload_2
   89:	iload_3
   90:	isub
   91:	iload	4
   93:	castore
   94:	iload_3
   95:	iconst_1
   96:	isub
   97:	istore_3
   98:	goto	15
   101:	iload_1
   102:	ifeq	188
   105:	iconst_0
   106:	istore	6
   108:	iload	6
   110:	aload_0
   111:	invokespecial	#245; //Method count:()I
   114:	iconst_1
   115:	isub
   116:	if_icmpge	188
   119:	aload_0
   120:	invokespecial	#243; //Method array:()[C
   123:	iload	6
   125:	caload
   126:	istore	7
   128:	iload	7
   130:	invokestatic	#256; //Method java/lang/Character.isLowSurrogate:(C)Z
   133:	ifeq	179
   136:	aload_0
   137:	invokespecial	#243; //Method array:()[C
   140:	iload	6
   142:	iconst_1
   143:	iadd
   144:	caload
   145:	istore	8
   147:	iload	8
   149:	invokestatic	#259; //Method java/lang/Character.isHighSurrogate:(C)Z
   152:	ifeq	179
   155:	aload_0
   156:	invokespecial	#243; //Method array:()[C
   159:	iload	6
   161:	iload	8
   163:	castore
   164:	iload	6
   166:	iconst_1
   167:	iadd
   168:	istore	6
   170:	aload_0
   171:	invokespecial	#243; //Method array:()[C
   174:	iload	6
   176:	iload	7
   178:	castore
   179:	iload	6
   181:	iconst_1
   182:	iadd
   183:	istore	6
   185:	goto	108
   188:	aload_0
   189:	areturn
  LineNumberTable: 
   line 803: 0
   line 804: 2
   line 805: 9
   line 806: 15
   line 807: 20
   line 808: 28
   line 809: 38
   line 811: 42
   line 812: 56
   line 811: 70
   line 810: 75
   line 813: 76
   line 814: 84
   line 815: 94
   line 817: 101
   line 819: 105
   line 820: 108
   line 821: 119
   line 822: 128
   line 823: 136
   line 824: 147
   line 825: 155
   line 826: 170
   line 829: 179
   line 832: 188

  LocalVariableTable: 
   Start  Length  Slot  Name   Signature
   0      190      0    this       Lscala/collection/mutable/StringBuilder;
   2      187      1    hasSurrogate       Z
   9      180      2    n       I
   15      174      3    j       I
   28      70      4    temp       C
   38      60      5    temp2       C
   108      80      6    i       I
   128      57      7    c2       C
   147      32      8    c1       C


public int lastIndexOf(java.lang.String, int);
  Code:
   Stack=3, Locals=3, Args_size=3
   0:	aload_0
   1:	getstatic	#125; //Field scala/Predef$.MODULE$:Lscala/Predef$;
   4:	aload_1
   5:	invokevirtual	#275; //Method scala/Predef$.augmentString:(Ljava/lang/String;)Lscala/collection/immutable/StringOps;
   8:	invokeinterface	#280,  1; //InterfaceMethod scala/collection/TraversableLike.toIndexedSeq:()Lscala/collection/mutable/IndexedSeq;
   13:	iload_2
   14:	invokeinterface	#284,  3; //InterfaceMethod scala/collection/SeqLike.lastIndexOfSlice:(Lscala/collection/Seq;I)I
   19:	ireturn
  LineNumberTable: 
   line 783: 0

  LocalVariableTable: 
   Start  Length  Slot  Name   Signature
   0      20      0    this       Lscala/collection/mutable/StringBuilder;
   0      20      1    str       Ljava/lang/String;
   0      20      2    fromIndex       I


public int lastIndexOf(java.lang.String);
  Code:
   Stack=3, Locals=2, Args_size=2
   0:	aload_0
   1:	aload_1
   2:	aload_0
   3:	invokespecial	#245; //Method count:()I
   6:	invokevirtual	#289; //Method lastIndexOf:(Ljava/lang/String;I)I
   9:	ireturn
  LineNumberTable: 
   line 764: 0

  LocalVariableTable: 
   Start  Length  Slot  Name   Signature
   0      10      0    this       Lscala/collection/mutable/StringBuilder;
   0      10      1    str       Ljava/lang/String;


public int indexOf(java.lang.String, int);
  Code:
   Stack=3, Locals=3, Args_size=3
   0:	aload_0
   1:	getstatic	#125; //Field scala/Predef$.MODULE$:Lscala/Predef$;
   4:	aload_1
   5:	invokevirtual	#275; //Method scala/Predef$.augmentString:(Ljava/lang/String;)Lscala/collection/immutable/StringOps;
   8:	invokeinterface	#280,  1; //InterfaceMethod scala/collection/TraversableLike.toIndexedSeq:()Lscala/collection/mutable/IndexedSeq;
   13:	iload_2
   14:	invokeinterface	#293,  3; //InterfaceMethod scala/collection/SeqLike.indexOfSlice:(Lscala/collection/Seq;I)I
   19:	ireturn
  LineNumberTable: 
   line 742: 0

  LocalVariableTable: 
   Start  Length  Slot  Name   Signature
   0      20      0    this       Lscala/collection/mutable/StringBuilder;
   0      20      1    str       Ljava/lang/String;
   0      20      2    fromIndex       I


public int indexOf(java.lang.String);
  Code:
   Stack=3, Locals=2, Args_size=2
   0:	aload_0
   1:	aload_1
   2:	iconst_0
   3:	invokevirtual	#295; //Method indexOf:(Ljava/lang/String;I)I
   6:	ireturn
  LineNumberTable: 
   line 723: 0

  LocalVariableTable: 
   Start  Length  Slot  Name   Signature
   0      7      0    this       Lscala/collection/mutable/StringBuilder;
   0      7      1    str       Ljava/lang/String;


public scala.collection.mutable.StringBuilder insert(int, double);
  Code:
   Stack=4, Locals=4, Args_size=3
   0:	aload_0
   1:	iload_1
   2:	dload_2
   3:	invokestatic	#301; //Method java/lang/String.valueOf:(D)Ljava/lang/String;
   6:	invokevirtual	#304; //Method insert:(ILjava/lang/String;)Lscala/collection/mutable/StringBuilder;
   9:	areturn
  LineNumberTable: 
   line 702: 0

  LocalVariableTable: 
   Start  Length  Slot  Name   Signature
   0      10      0    this       Lscala/collection/mutable/StringBuilder;
   0      10      1    at       I
   0      10      2    x       D


public scala.collection.mutable.StringBuilder insert(int, float);
  Code:
   Stack=3, Locals=3, Args_size=3
   0:	aload_0
   1:	iload_1
   2:	fload_2
   3:	invokestatic	#310; //Method java/lang/String.valueOf:(F)Ljava/lang/String;
   6:	invokevirtual	#304; //Method insert:(ILjava/lang/String;)Lscala/collection/mutable/StringBuilder;
   9:	areturn
  LineNumberTable: 
   line 686: 0

  LocalVariableTable: 
   Start  Length  Slot  Name   Signature
   0      10      0    this       Lscala/collection/mutable/StringBuilder;
   0      10      1    at       I
   0      10      2    x       F


public scala.collection.mutable.StringBuilder insert(int, long);
  Code:
   Stack=4, Locals=4, Args_size=3
   0:	aload_0
   1:	iload_1
   2:	lload_2
   3:	invokestatic	#315; //Method java/lang/String.valueOf:(J)Ljava/lang/String;
   6:	invokevirtual	#304; //Method insert:(ILjava/lang/String;)Lscala/collection/mutable/StringBuilder;
   9:	areturn
  LineNumberTable: 
   line 670: 0

  LocalVariableTable: 
   Start  Length  Slot  Name   Signature
   0      10      0    this       Lscala/collection/mutable/StringBuilder;
   0      10      1    at       I
   0      10      2    x       J


public scala.collection.mutable.StringBuilder insert(int, int);
  Code:
   Stack=3, Locals=3, Args_size=3
   0:	aload_0
   1:	iload_1
   2:	iload_2
   3:	invokestatic	#319; //Method java/lang/String.valueOf:(I)Ljava/lang/String;
   6:	invokevirtual	#304; //Method insert:(ILjava/lang/String;)Lscala/collection/mutable/StringBuilder;
   9:	areturn
  LineNumberTable: 
   line 654: 0

  LocalVariableTable: 
   Start  Length  Slot  Name   Signature
   0      10      0    this       Lscala/collection/mutable/StringBuilder;
   0      10      1    at       I
   0      10      2    x       I


public scala.collection.mutable.StringBuilder insert(int, short);
  Code:
   Stack=3, Locals=3, Args_size=3
   0:	aload_0
   1:	iload_1
   2:	iload_2
   3:	invokestatic	#319; //Method java/lang/String.valueOf:(I)Ljava/lang/String;
   6:	invokevirtual	#304; //Method insert:(ILjava/lang/String;)Lscala/collection/mutable/StringBuilder;
   9:	areturn
  LineNumberTable: 
   line 638: 0

  LocalVariableTable: 
   Start  Length  Slot  Name   Signature
   0      10      0    this       Lscala/collection/mutable/StringBuilder;
   0      10      1    at       I
   0      10      2    x       S


public scala.collection.mutable.StringBuilder insert(int, char);
  Code:
   Stack=5, Locals=7, Args_size=3
   0:	iload_1
   1:	iconst_0
   2:	if_icmplt	13
   5:	iload_1
   6:	aload_0
   7:	invokespecial	#245; //Method count:()I
   10:	if_icmple	22
   13:	new	#324; //class java/lang/StringIndexOutOfBoundsException
   16:	dup
   17:	iload_1
   18:	invokespecial	#327; //Method java/lang/StringIndexOutOfBoundsException."<init>":(I)V
   21:	athrow
   22:	aload_0
   23:	aload_0
   24:	invokespecial	#245; //Method count:()I
   27:	iconst_1
   28:	iadd
   29:	invokevirtual	#330; //Method ensureCapacity:(I)V
   32:	aload_0
   33:	invokespecial	#243; //Method array:()[C
   36:	aload_0
   37:	invokespecial	#243; //Method array:()[C
   40:	iload_1
   41:	iconst_1
   42:	iadd
   43:	aload_0
   44:	invokespecial	#245; //Method count:()I
   47:	iload_1
   48:	isub
   49:	istore	6
   51:	istore	5
   53:	astore	4
   55:	astore_3
   56:	aload_3
   57:	iload_1
   58:	aload	4
   60:	iload	5
   62:	iload	6
   64:	invokestatic	#336; //Method java/lang/System.arraycopy:(Ljava/lang/Object;ILjava/lang/Object;II)V
   67:	aload_0
   68:	invokespecial	#243; //Method array:()[C
   71:	iload_1
   72:	iload_2
   73:	castore
   74:	aload_0
   75:	aload_0
   76:	invokespecial	#245; //Method count:()I
   79:	iconst_1
   80:	iadd
   81:	invokespecial	#339; //Method count_$eq:(I)V
   84:	aload_0
   85:	areturn
  LineNumberTable: 
   line 615: 0
   line 616: 13
   line 617: 22
   line 618: 32
   line 619: 67
   line 620: 74
   line 621: 84

  LocalVariableTable: 
   Start  Length  Slot  Name   Signature
   0      86      0    this       Lscala/collection/mutable/StringBuilder;
   0      86      1    at       I
   0      86      2    x       C


public scala.collection.mutable.StringBuilder insert(int, byte);
  Code:
   Stack=3, Locals=3, Args_size=3
   0:	aload_0
   1:	iload_1
   2:	iload_2
   3:	i2c
   4:	invokestatic	#343; //Method java/lang/String.valueOf:(C)Ljava/lang/String;
   7:	invokevirtual	#304; //Method insert:(ILjava/lang/String;)Lscala/collection/mutable/StringBuilder;
   10:	areturn
  LineNumberTable: 
   line 599: 0

  LocalVariableTable: 
   Start  Length  Slot  Name   Signature
   0      11      0    this       Lscala/collection/mutable/StringBuilder;
   0      11      1    at       I
   0      11      2    x       B


public scala.collection.mutable.StringBuilder insert(int, boolean);
  Code:
   Stack=3, Locals=3, Args_size=3
   0:	aload_0
   1:	iload_1
   2:	iload_2
   3:	invokestatic	#348; //Method java/lang/String.valueOf:(Z)Ljava/lang/String;
   6:	invokevirtual	#304; //Method insert:(ILjava/lang/String;)Lscala/collection/mutable/StringBuilder;
   9:	areturn
  LineNumberTable: 
   line 583: 0

  LocalVariableTable: 
   Start  Length  Slot  Name   Signature
   0      10      0    this       Lscala/collection/mutable/StringBuilder;
   0      10      1    at       I
   0      10      2    x       Z


public scala.collection.mutable.StringBuilder insert(int, char[]);
  Code:
   Stack=3, Locals=3, Args_size=3
   0:	aload_0
   1:	iload_1
   2:	aload_2
   3:	invokevirtual	#352; //Method insertAll:(I[C)Lscala/collection/mutable/StringBuilder;
   6:	areturn
  LineNumberTable: 
   line 567: 0

  LocalVariableTable: 
   Start  Length  Slot  Name   Signature
   0      7      0    this       Lscala/collection/mutable/StringBuilder;
   0      7      1    at       I
   0      7      2    x       [C

  Deprecated: true

public scala.collection.mutable.StringBuilder insertAll(int, char[]);
  Code:
   Stack=5, Locals=10, Args_size=3
   0:	iload_1
   1:	iconst_0
   2:	if_icmplt	13
   5:	iload_1
   6:	aload_0
   7:	invokespecial	#245; //Method count:()I
   10:	if_icmple	22
   13:	new	#324; //class java/lang/StringIndexOutOfBoundsException
   16:	dup
   17:	iload_1
   18:	invokespecial	#327; //Method java/lang/StringIndexOutOfBoundsException."<init>":(I)V
   21:	athrow
   22:	aload_2
   23:	arraylength
   24:	istore	9
   26:	aload_0
   27:	aload_0
   28:	invokespecial	#245; //Method count:()I
   31:	iload	9
   33:	iadd
   34:	invokevirtual	#330; //Method ensureCapacity:(I)V
   37:	aload_0
   38:	invokespecial	#243; //Method array:()[C
   41:	aload_0
   42:	invokespecial	#243; //Method array:()[C
   45:	iload_1
   46:	iload	9
   48:	iadd
   49:	aload_0
   50:	invokespecial	#245; //Method count:()I
   53:	iload_1
   54:	isub
   55:	istore	6
   57:	istore	5
   59:	astore	4
   61:	astore_3
   62:	aload_3
   63:	iload_1
   64:	aload	4
   66:	iload	5
   68:	iload	6
   70:	invokestatic	#336; //Method java/lang/System.arraycopy:(Ljava/lang/Object;ILjava/lang/Object;II)V
   73:	iconst_0
   74:	aload_0
   75:	invokespecial	#243; //Method array:()[C
   78:	astore	8
   80:	istore	7
   82:	aload_2
   83:	iload	7
   85:	aload	8
   87:	iload_1
   88:	iload	9
   90:	invokestatic	#336; //Method java/lang/System.arraycopy:(Ljava/lang/Object;ILjava/lang/Object;II)V
   93:	aload_0
   94:	aload_0
   95:	invokespecial	#245; //Method count:()I
   98:	iload	9
   100:	iadd
   101:	invokespecial	#339; //Method count_$eq:(I)V
   104:	aload_0
   105:	areturn
  LineNumberTable: 
   line 554: 0
   line 555: 13
   line 556: 22
   line 557: 26
   line 558: 37
   line 559: 73
   line 560: 93
   line 561: 104

  LocalVariableTable: 
   Start  Length  Slot  Name   Signature
   0      106      0    this       Lscala/collection/mutable/StringBuilder;
   0      106      1    at       I
   0      106      2    x       [C
   26      79      9    len       I


public scala.collection.mutable.StringBuilder insert(int, scala.collection.Seq);
  Code:
   Stack=3, Locals=3, Args_size=3
   0:	aload_0
   1:	iload_1
   2:	aload_2
   3:	invokevirtual	#357; //Method insertAll:(ILscala/collection/Seq;)Lscala/collection/mutable/StringBuilder;
   6:	areturn
  LineNumberTable: 
   line 543: 0

  LocalVariableTable: 
   Start  Length  Slot  Name   Signature
   0      7      0    this       Lscala/collection/mutable/StringBuilder;
   0      7      1    at       I
   0      7      2    x       Lscala/collection/Seq;

  Signature: length = 0x2
   01 67 
  Deprecated: true

public scala.collection.mutable.StringBuilder insertAll(int, scala.collection.Seq);
  Code:
   Stack=4, Locals=3, Args_size=3
   0:	aload_0
   1:	iload_1
   2:	aload_2
   3:	getstatic	#365; //Field scala/reflect/Manifest$.MODULE$:Lscala/reflect/Manifest$;
   6:	invokevirtual	#369; //Method scala/reflect/Manifest$.Char:()Lscala/reflect/AnyValManifest;
   9:	invokeinterface	#373,  2; //InterfaceMethod scala/collection/TraversableLike.toArray:(Lscala/reflect/ClassManifest;)Ljava/lang/Object;
   14:	checkcast	#374; //class "[C"
   17:	invokevirtual	#352; //Method insertAll:(I[C)Lscala/collection/mutable/StringBuilder;
   20:	areturn
  LineNumberTable: 
   line 538: 0

  LocalVariableTable: 
   Start  Length  Slot  Name   Signature
   0      21      0    this       Lscala/collection/mutable/StringBuilder;
   0      21      1    at       I
   0      21      2    x       Lscala/collection/Seq;

  Signature: length = 0x2
   01 67 

public scala.collection.mutable.StringBuilder insert(int, java.lang.String);
  Code:
   Stack=5, Locals=9, Args_size=3
   0:	iload_1
   1:	iconst_0
   2:	if_icmplt	13
   5:	iload_1
   6:	aload_0
   7:	invokespecial	#245; //Method count:()I
   10:	if_icmple	22
   13:	new	#324; //class java/lang/StringIndexOutOfBoundsException
   16:	dup
   17:	iload_1
   18:	invokespecial	#327; //Method java/lang/StringIndexOutOfBoundsException."<init>":(I)V
   21:	athrow
   22:	aload_2
   23:	dup
   24:	pop
   25:	ifnull	36
   28:	aload_2
   29:	aconst_null
   30:	invokevirtual	#377; //Method java/lang/Object.equals:(Ljava/lang/Object;)Z
   33:	ifeq	42
   36:	ldc_w	#379; //String null
   39:	goto	43
   42:	aload_2
   43:	astore	7
   45:	aload	7
   47:	invokevirtual	#135; //Method java/lang/String.length:()I
   50:	istore	8
   52:	aload_0
   53:	aload_0
   54:	invokespecial	#245; //Method count:()I
   57:	iload	8
   59:	iadd
   60:	invokevirtual	#330; //Method ensureCapacity:(I)V
   63:	aload_0
   64:	invokespecial	#243; //Method array:()[C
   67:	aload_0
   68:	invokespecial	#243; //Method array:()[C
   71:	iload_1
   72:	iload	8
   74:	iadd
   75:	aload_0
   76:	invokespecial	#245; //Method count:()I
   79:	iload_1
   80:	isub
   81:	istore	6
   83:	istore	5
   85:	astore	4
   87:	astore_3
   88:	aload_3
   89:	iload_1
   90:	aload	4
   92:	iload	5
   94:	iload	6
   96:	invokestatic	#336; //Method java/lang/System.arraycopy:(Ljava/lang/Object;ILjava/lang/Object;II)V
   99:	aload	7
   101:	iconst_0
   102:	iload	8
   104:	aload_0
   105:	invokespecial	#243; //Method array:()[C
   108:	iload_1
   109:	invokevirtual	#383; //Method java/lang/String.getChars:(II[CI)V
   112:	aload_0
   113:	aload_0
   114:	invokespecial	#245; //Method count:()I
   117:	iload	8
   119:	iadd
   120:	invokespecial	#339; //Method count_$eq:(I)V
   123:	aload_0
   124:	areturn
  LineNumberTable: 
   line 518: 0
   line 519: 13
   line 520: 22
   line 521: 45
   line 522: 52
   line 523: 63
   line 524: 99
   line 525: 112
   line 526: 123

  LocalVariableTable: 
   Start  Length  Slot  Name   Signature
   0      125      0    this       Lscala/collection/mutable/StringBuilder;
   0      125      1    at       I
   0      125      2    x       Ljava/lang/String;
   45      79      7    str       Ljava/lang/String;
   52      72      8    len       I


public scala.collection.mutable.StringBuilder insert(int, java.lang.Object);
  Code:
   Stack=3, Locals=3, Args_size=3
   0:	aload_0
   1:	iload_1
   2:	aload_2
   3:	invokestatic	#387; //Method java/lang/String.valueOf:(Ljava/lang/Object;)Ljava/lang/String;
   6:	invokevirtual	#304; //Method insert:(ILjava/lang/String;)Lscala/collection/mutable/StringBuilder;
   9:	areturn
  LineNumberTable: 
   line 508: 0

  LocalVariableTable: 
   Start  Length  Slot  Name   Signature
   0      10      0    this       Lscala/collection/mutable/StringBuilder;
   0      10      1    at       I
   0      10      2    x       Ljava/lang/Object;


public scala.collection.mutable.StringBuilder insert(int, char[], int, int);
  Code:
   Stack=5, Locals=5, Args_size=5
   0:	aload_0
   1:	iload_1
   2:	aload_2
   3:	iload_3
   4:	iload	4
   6:	invokevirtual	#390; //Method insertAll:(I[CII)Lscala/collection/mutable/StringBuilder;
   9:	areturn
  LineNumberTable: 
   line 484: 0

  LocalVariableTable: 
   Start  Length  Slot  Name   Signature
   0      10      0    this       Lscala/collection/mutable/StringBuilder;
   0      10      1    index       I
   0      10      2    str       [C
   0      10      3    offset       I
   0      10      4    len       I

  Deprecated: true

public scala.collection.mutable.StringBuilder insertAll(int, char[], int, int);
  Code:
   Stack=5, Locals=11, Args_size=5
   0:	iload_1
   1:	iconst_0
   2:	if_icmplt	13
   5:	iload_1
   6:	aload_0
   7:	invokespecial	#245; //Method count:()I
   10:	if_icmple	22
   13:	new	#324; //class java/lang/StringIndexOutOfBoundsException
   16:	dup
   17:	iload_1
   18:	invokespecial	#327; //Method java/lang/StringIndexOutOfBoundsException."<init>":(I)V
   21:	athrow
   22:	iload_3
   23:	iconst_0
   24:	if_icmplt	42
   27:	iload	4
   29:	iconst_0
   30:	if_icmplt	42
   33:	iload_3
   34:	aload_2
   35:	arraylength
   36:	iload	4
   38:	isub
   39:	if_icmple	105
   42:	new	#324; //class java/lang/StringIndexOutOfBoundsException
   45:	dup
   46:	new	#11; //class scala/collection/mutable/StringBuilder
   49:	dup
   50:	invokespecial	#393; //Method "<init>":()V
   53:	ldc_w	#395; //String offset 
   56:	invokevirtual	#398; //Method append:(Ljava/lang/Object;)Lscala/collection/mutable/StringBuilder;
   59:	iload_3
   60:	invokestatic	#402; //Method scala/runtime/BoxesRunTime.boxToInteger:(I)Ljava/lang/Integer;
   63:	invokevirtual	#398; //Method append:(Ljava/lang/Object;)Lscala/collection/mutable/StringBuilder;
   66:	ldc_w	#404; //String , len 
   69:	invokevirtual	#398; //Method append:(Ljava/lang/Object;)Lscala/collection/mutable/StringBuilder;
   72:	iload	4
   74:	invokestatic	#402; //Method scala/runtime/BoxesRunTime.boxToInteger:(I)Ljava/lang/Integer;
   77:	invokevirtual	#398; //Method append:(Ljava/lang/Object;)Lscala/collection/mutable/StringBuilder;
   80:	ldc_w	#406; //String , str.length 
   83:	invokevirtual	#398; //Method append:(Ljava/lang/Object;)Lscala/collection/mutable/StringBuilder;
   86:	aload_2
   87:	arraylength
   88:	istore	5
   90:	iload	5
   92:	invokestatic	#402; //Method scala/runtime/BoxesRunTime.boxToInteger:(I)Ljava/lang/Integer;
   95:	invokevirtual	#398; //Method append:(Ljava/lang/Object;)Lscala/collection/mutable/StringBuilder;
   98:	invokevirtual	#407; //Method toString:()Ljava/lang/String;
   101:	invokespecial	#410; //Method java/lang/StringIndexOutOfBoundsException."<init>":(Ljava/lang/String;)V
   104:	athrow
   105:	aload_0
   106:	aload_0
   107:	invokespecial	#245; //Method count:()I
   110:	iload	4
   112:	iadd
   113:	invokevirtual	#330; //Method ensureCapacity:(I)V
   116:	aload_0
   117:	invokespecial	#243; //Method array:()[C
   120:	aload_0
   121:	invokespecial	#243; //Method array:()[C
   124:	iload_1
   125:	iload	4
   127:	iadd
   128:	aload_0
   129:	invokespecial	#245; //Method count:()I
   132:	iload_1
   133:	isub
   134:	istore	9
   136:	istore	8
   138:	astore	7
   140:	astore	6
   142:	aload	6
   144:	iload_1
   145:	aload	7
   147:	iload	8
   149:	iload	9
   151:	invokestatic	#336; //Method java/lang/System.arraycopy:(Ljava/lang/Object;ILjava/lang/Object;II)V
   154:	aload_0
   155:	invokespecial	#243; //Method array:()[C
   158:	astore	10
   160:	aload_2
   161:	iload_3
   162:	aload	10
   164:	iload_1
   165:	iload	4
   167:	invokestatic	#336; //Method java/lang/System.arraycopy:(Ljava/lang/Object;ILjava/lang/Object;II)V
   170:	aload_0
   171:	aload_0
   172:	invokespecial	#245; //Method count:()I
   175:	iload	4
   177:	iadd
   178:	invokespecial	#339; //Method count_$eq:(I)V
   181:	aload_0
   182:	areturn
  LineNumberTable: 
   line 468: 0
   line 469: 13
   line 470: 22
   line 471: 42
   line 473: 46
   line 472: 53
   line 473: 80
   line 471: 101
   line 474: 105
   line 475: 116
   line 476: 154
   line 477: 170
   line 478: 181

  LocalVariableTable: 
   Start  Length  Slot  Name   Signature
   0      183      0    this       Lscala/collection/mutable/StringBuilder;
   0      183      1    index       I
   0      183      2    str       [C
   0      183      3    offset       I
   0      183      4    len       I


public void replace(int, int, java.lang.String);
  Code:
   Stack=5, Locals=11, Args_size=4
   0:	iload_1
   1:	iconst_0
   2:	if_icmplt	18
   5:	iload_1
   6:	aload_0
   7:	invokespecial	#245; //Method count:()I
   10:	if_icmpgt	18
   13:	iload_1
   14:	iload_2
   15:	if_icmple	27
   18:	new	#324; //class java/lang/StringIndexOutOfBoundsException
   21:	dup
   22:	iload_1
   23:	invokespecial	#327; //Method java/lang/StringIndexOutOfBoundsException."<init>":(I)V
   26:	athrow
   27:	iload_2
   28:	aload_0
   29:	invokespecial	#245; //Method count:()I
   32:	if_icmple	42
   35:	aload_0
   36:	invokespecial	#245; //Method count:()I
   39:	goto	43
   42:	iload_2
   43:	istore	4
   45:	aload_3
   46:	invokevirtual	#135; //Method java/lang/String.length:()I
   49:	istore	9
   51:	aload_0
   52:	invokespecial	#245; //Method count:()I
   55:	iload	9
   57:	iadd
   58:	iload	4
   60:	iload_1
   61:	isub
   62:	isub
   63:	istore	10
   65:	aload_0
   66:	iload	10
   68:	invokevirtual	#330; //Method ensureCapacity:(I)V
   71:	aload_0
   72:	invokespecial	#243; //Method array:()[C
   75:	aload_0
   76:	invokespecial	#243; //Method array:()[C
   79:	iload_1
   80:	iload	9
   82:	iadd
   83:	aload_0
   84:	invokespecial	#245; //Method count:()I
   87:	iload_2
   88:	isub
   89:	istore	8
   91:	istore	7
   93:	astore	6
   95:	astore	5
   97:	aload	5
   99:	iload_2
   100:	aload	6
   102:	iload	7
   104:	iload	8
   106:	invokestatic	#336; //Method java/lang/System.arraycopy:(Ljava/lang/Object;ILjava/lang/Object;II)V
   109:	aload_3
   110:	iconst_0
   111:	iload	9
   113:	aload_0
   114:	invokespecial	#243; //Method array:()[C
   117:	iload_1
   118:	invokevirtual	#383; //Method java/lang/String.getChars:(II[CI)V
   121:	aload_0
   122:	iload	10
   124:	invokespecial	#339; //Method count_$eq:(I)V
   127:	return
  LineNumberTable: 
   line 433: 0
   line 434: 18
   line 436: 27
   line 437: 45
   line 438: 51
   line 439: 65
   line 441: 71
   line 442: 109
   line 443: 121
   line 444: 127

  LocalVariableTable: 
   Start  Length  Slot  Name   Signature
   0      128      0    this       Lscala/collection/mutable/StringBuilder;
   0      128      1    start       I
   0      128      2    end       I
   0      128      3    str       Ljava/lang/String;
   45      82      4    end0       I
   51      76      9    len       I
   65      62      10    newCount       I


public scala.collection.mutable.StringBuilder delete(int, int);
  Code:
   Stack=5, Locals=9, Args_size=3
   0:	iload_1
   1:	iconst_0
   2:	if_icmplt	10
   5:	iload_1
   6:	iload_2
   7:	if_icmple	19
   10:	new	#324; //class java/lang/StringIndexOutOfBoundsException
   13:	dup
   14:	iload_1
   15:	invokespecial	#327; //Method java/lang/StringIndexOutOfBoundsException."<init>":(I)V
   18:	athrow
   19:	iload_2
   20:	aload_0
   21:	invokespecial	#245; //Method count:()I
   24:	if_icmple	34
   27:	aload_0
   28:	invokespecial	#245; //Method count:()I
   31:	goto	35
   34:	iload_2
   35:	istore_3
   36:	iload_3
   37:	iload_1
   38:	isub
   39:	istore	8
   41:	iload	8
   43:	iconst_0
   44:	if_icmple	96
   47:	aload_0
   48:	invokespecial	#243; //Method array:()[C
   51:	iload_1
   52:	iload	8
   54:	iadd
   55:	aload_0
   56:	invokespecial	#243; //Method array:()[C
   59:	aload_0
   60:	invokespecial	#245; //Method count:()I
   63:	iload_3
   64:	isub
   65:	istore	7
   67:	astore	6
   69:	istore	5
   71:	astore	4
   73:	aload	4
   75:	iload	5
   77:	aload	6
   79:	iload_1
   80:	iload	7
   82:	invokestatic	#336; //Method java/lang/System.arraycopy:(Ljava/lang/Object;ILjava/lang/Object;II)V
   85:	aload_0
   86:	aload_0
   87:	invokespecial	#245; //Method count:()I
   90:	iload	8
   92:	isub
   93:	invokespecial	#339; //Method count_$eq:(I)V
   96:	aload_0
   97:	areturn
  LineNumberTable: 
   line 406: 0
   line 407: 10
   line 408: 19
   line 409: 36
   line 410: 41
   line 411: 47
   line 412: 85
   line 414: 96

  LocalVariableTable: 
   Start  Length  Slot  Name   Signature
   0      98      0    this       Lscala/collection/mutable/StringBuilder;
   0      98      1    start       I
   0      98      2    end       I
   36      61      3    end0       I
   41      56      8    len       I


public scala.collection.mutable.StringBuilder append(double);
  Code:
   Stack=3, Locals=3, Args_size=2
   0:	aload_0
   1:	dload_1
   2:	invokestatic	#301; //Method java/lang/String.valueOf:(D)Ljava/lang/String;
   5:	invokevirtual	#143; //Method append:(Ljava/lang/String;)Lscala/collection/mutable/StringBuilder;
   8:	areturn
  LineNumberTable: 
   line 390: 0

  LocalVariableTable: 
   Start  Length  Slot  Name   Signature
   0      9      0    this       Lscala/collection/mutable/StringBuilder;
   0      9      1    x       D


public scala.collection.mutable.StringBuilder append(float);
  Code:
   Stack=2, Locals=2, Args_size=2
   0:	aload_0
   1:	fload_1
   2:	invokestatic	#310; //Method java/lang/String.valueOf:(F)Ljava/lang/String;
   5:	invokevirtual	#143; //Method append:(Ljava/lang/String;)Lscala/collection/mutable/StringBuilder;
   8:	areturn
  LineNumberTable: 
   line 387: 0

  LocalVariableTable: 
   Start  Length  Slot  Name   Signature
   0      9      0    this       Lscala/collection/mutable/StringBuilder;
   0      9      1    x       F


public scala.collection.mutable.StringBuilder append(long);
  Code:
   Stack=3, Locals=3, Args_size=2
   0:	aload_0
   1:	lload_1
   2:	invokestatic	#315; //Method java/lang/String.valueOf:(J)Ljava/lang/String;
   5:	invokevirtual	#143; //Method append:(Ljava/lang/String;)Lscala/collection/mutable/StringBuilder;
   8:	areturn
  LineNumberTable: 
   line 384: 0

  LocalVariableTable: 
   Start  Length  Slot  Name   Signature
   0      9      0    this       Lscala/collection/mutable/StringBuilder;
   0      9      1    x       J


public scala.collection.mutable.StringBuilder append(int);
  Code:
   Stack=2, Locals=2, Args_size=2
   0:	aload_0
   1:	iload_1
   2:	invokestatic	#319; //Method java/lang/String.valueOf:(I)Ljava/lang/String;
   5:	invokevirtual	#143; //Method append:(Ljava/lang/String;)Lscala/collection/mutable/StringBuilder;
   8:	areturn
  LineNumberTable: 
   line 381: 0

  LocalVariableTable: 
   Start  Length  Slot  Name   Signature
   0      9      0    this       Lscala/collection/mutable/StringBuilder;
   0      9      1    x       I


public scala.collection.mutable.StringBuilder append(short);
  Code:
   Stack=2, Locals=2, Args_size=2
   0:	aload_0
   1:	iload_1
   2:	invokestatic	#319; //Method java/lang/String.valueOf:(I)Ljava/lang/String;
   5:	invokevirtual	#143; //Method append:(Ljava/lang/String;)Lscala/collection/mutable/StringBuilder;
   8:	areturn
  LineNumberTable: 
   line 378: 0

  LocalVariableTable: 
   Start  Length  Slot  Name   Signature
   0      9      0    this       Lscala/collection/mutable/StringBuilder;
   0      9      1    x       S


public scala.collection.mutable.StringBuilder append(char);
  Code:
   Stack=3, Locals=2, Args_size=2
   0:	aload_0
   1:	aload_0
   2:	invokespecial	#245; //Method count:()I
   5:	iconst_1
   6:	iadd
   7:	invokevirtual	#330; //Method ensureCapacity:(I)V
   10:	aload_0
   11:	invokespecial	#243; //Method array:()[C
   14:	aload_0
   15:	invokespecial	#245; //Method count:()I
   18:	iload_1
   19:	castore
   20:	aload_0
   21:	aload_0
   22:	invokespecial	#245; //Method count:()I
   25:	iconst_1
   26:	iadd
   27:	invokespecial	#339; //Method count_$eq:(I)V
   30:	aload_0
   31:	areturn
  LineNumberTable: 
   line 371: 0
   line 372: 10
   line 373: 20
   line 374: 30

  LocalVariableTable: 
   Start  Length  Slot  Name   Signature
   0      32      0    this       Lscala/collection/mutable/StringBuilder;
   0      32      1    x       C


public scala.collection.mutable.StringBuilder append(byte);
  Code:
   Stack=2, Locals=2, Args_size=2
   0:	aload_0
   1:	iload_1
   2:	i2c
   3:	invokestatic	#343; //Method java/lang/String.valueOf:(C)Ljava/lang/String;
   6:	invokevirtual	#143; //Method append:(Ljava/lang/String;)Lscala/collection/mutable/StringBuilder;
   9:	areturn
  LineNumberTable: 
   line 368: 0

  LocalVariableTable: 
   Start  Length  Slot  Name   Signature
   0      10      0    this       Lscala/collection/mutable/StringBuilder;
   0      10      1    x       B


public scala.collection.mutable.StringBuilder append(boolean);
  Code:
   Stack=2, Locals=2, Args_size=2
   0:	aload_0
   1:	iload_1
   2:	invokestatic	#348; //Method java/lang/String.valueOf:(Z)Ljava/lang/String;
   5:	invokevirtual	#143; //Method append:(Ljava/lang/String;)Lscala/collection/mutable/StringBuilder;
   8:	areturn
  LineNumberTable: 
   line 367: 0

  LocalVariableTable: 
   Start  Length  Slot  Name   Signature
   0      9      0    this       Lscala/collection/mutable/StringBuilder;
   0      9      1    x       Z


public scala.collection.mutable.StringBuilder append(char[], int, int);
  Code:
   Stack=4, Locals=4, Args_size=4
   0:	aload_0
   1:	aload_1
   2:	iload_2
   3:	iload_3
   4:	invokevirtual	#428; //Method appendAll:([CII)Lscala/collection/mutable/StringBuilder;
   7:	areturn
  LineNumberTable: 
   line 352: 0

  LocalVariableTable: 
   Start  Length  Slot  Name   Signature
   0      8      0    this       Lscala/collection/mutable/StringBuilder;
   0      8      1    x       [C
   0      8      2    offset       I
   0      8      3    len       I

  Deprecated: true

public scala.collection.mutable.StringBuilder appendAll(char[], int, int);
  Code:
   Stack=5, Locals=6, Args_size=4
   0:	aload_0
   1:	aload_0
   2:	invokespecial	#245; //Method count:()I
   5:	iload_3
   6:	iadd
   7:	invokevirtual	#330; //Method ensureCapacity:(I)V
   10:	aload_0
   11:	invokespecial	#243; //Method array:()[C
   14:	aload_0
   15:	invokespecial	#245; //Method count:()I
   18:	istore	5
   20:	astore	4
   22:	aload_1
   23:	iload_2
   24:	aload	4
   26:	iload	5
   28:	iload_3
   29:	invokestatic	#336; //Method java/lang/System.arraycopy:(Ljava/lang/Object;ILjava/lang/Object;II)V
   32:	aload_0
   33:	aload_0
   34:	invokespecial	#245; //Method count:()I
   37:	iload_3
   38:	iadd
   39:	invokespecial	#339; //Method count_$eq:(I)V
   42:	aload_0
   43:	areturn
  LineNumberTable: 
   line 343: 0
   line 344: 10
   line 345: 32
   line 346: 42

  LocalVariableTable: 
   Start  Length  Slot  Name   Signature
   0      44      0    this       Lscala/collection/mutable/StringBuilder;
   0      44      1    x       [C
   0      44      2    offset       I
   0      44      3    len       I


public scala.collection.mutable.StringBuilder append(char[]);
  Code:
   Stack=2, Locals=2, Args_size=2
   0:	aload_0
   1:	aload_1
   2:	invokevirtual	#431; //Method appendAll:([C)Lscala/collection/mutable/StringBuilder;
   5:	areturn
  LineNumberTable: 
   line 324: 0

  LocalVariableTable: 
   Start  Length  Slot  Name   Signature
   0      6      0    this       Lscala/collection/mutable/StringBuilder;
   0      6      1    x       [C

  Deprecated: true

public scala.collection.mutable.StringBuilder appendAll(char[]);
  Code:
   Stack=4, Locals=2, Args_size=2
   0:	aload_0
   1:	aload_1
   2:	iconst_0
   3:	aload_1
   4:	arraylength
   5:	invokevirtual	#428; //Method appendAll:([CII)Lscala/collection/mutable/StringBuilder;
   8:	areturn
  LineNumberTable: 
   line 319: 0

  LocalVariableTable: 
   Start  Length  Slot  Name   Signature
   0      9      0    this       Lscala/collection/mutable/StringBuilder;
   0      9      1    x       [C


public scala.collection.mutable.StringBuilder append(scala.collection.Seq);
  Code:
   Stack=2, Locals=2, Args_size=2
   0:	aload_0
   1:	aload_1
   2:	invokevirtual	#434; //Method appendAll:(Lscala/collection/Seq;)Lscala/collection/mutable/StringBuilder;
   5:	areturn
  LineNumberTable: 
   line 303: 0

  LocalVariableTable: 
   Start  Length  Slot  Name   Signature
   0      6      0    this       Lscala/collection/mutable/StringBuilder;
   0      6      1    x       Lscala/collection/Seq;

  Signature: length = 0x2
   01 FFFFFFB3 
  Deprecated: true

public scala.collection.mutable.StringBuilder appendAll(scala.collection.Seq);
  Code:
   Stack=4, Locals=2, Args_size=2
   0:	aload_0
   1:	aload_1
   2:	getstatic	#365; //Field scala/reflect/Manifest$.MODULE$:Lscala/reflect/Manifest$;
   5:	invokevirtual	#369; //Method scala/reflect/Manifest$.Char:()Lscala/reflect/AnyValManifest;
   8:	invokeinterface	#373,  2; //InterfaceMethod scala/collection/TraversableLike.toArray:(Lscala/reflect/ClassManifest;)Ljava/lang/Object;
   13:	checkcast	#374; //class "[C"
   16:	iconst_0
   17:	aload_1
   18:	invokeinterface	#436,  1; //InterfaceMethod scala/collection/SeqLike.length:()I
   23:	invokevirtual	#428; //Method appendAll:([CII)Lscala/collection/mutable/StringBuilder;
   26:	areturn
  LineNumberTable: 
   line 298: 0

  LocalVariableTable: 
   Start  Length  Slot  Name   Signature
   0      27      0    this       Lscala/collection/mutable/StringBuilder;
   0      27      1    x       Lscala/collection/Seq;

  Signature: length = 0x2
   01 FFFFFFB3 

public scala.collection.mutable.StringBuilder append(scala.collection.mutable.StringBuilder);
  Code:
   Stack=5, Locals=8, Args_size=2
   0:	aload_1
   1:	dup
   2:	pop
   3:	ifnull	16
   6:	aconst_null
   7:	astore_2
   8:	aload_1
   9:	aload_2
   10:	invokestatic	#440; //Method scala/collection/SeqLike$class.equals:(Lscala/collection/SeqLike;Ljava/lang/Object;)Z
   13:	ifeq	26
   16:	aload_0
   17:	ldc_w	#379; //String null
   20:	invokevirtual	#143; //Method append:(Ljava/lang/String;)Lscala/collection/mutable/StringBuilder;
   23:	goto	87
   26:	aload_1
   27:	invokespecial	#245; //Method count:()I
   30:	istore	7
   32:	aload_0
   33:	aload_0
   34:	invokespecial	#245; //Method count:()I
   37:	iload	7
   39:	iadd
   40:	invokevirtual	#330; //Method ensureCapacity:(I)V
   43:	aload_1
   44:	invokespecial	#243; //Method array:()[C
   47:	iconst_0
   48:	aload_0
   49:	invokespecial	#243; //Method array:()[C
   52:	aload_0
   53:	invokespecial	#245; //Method count:()I
   56:	istore	6
   58:	astore	5
   60:	istore	4
   62:	astore_3
   63:	aload_3
   64:	iload	4
   66:	aload	5
   68:	iload	6
   70:	iload	7
   72:	invokestatic	#336; //Method java/lang/System.arraycopy:(Ljava/lang/Object;ILjava/lang/Object;II)V
   75:	aload_0
   76:	aload_0
   77:	invokespecial	#245; //Method count:()I
   80:	iload	7
   82:	iadd
   83:	invokespecial	#339; //Method count_$eq:(I)V
   86:	aload_0
   87:	areturn
  LineNumberTable: 
   line 274: 0
   line 275: 16
   line 277: 26
   line 278: 32
   line 279: 43
   line 280: 75
   line 281: 86
   line 274: 87

  LocalVariableTable: 
   Start  Length  Slot  Name   Signature
   0      88      0    this       Lscala/collection/mutable/StringBuilder;
   0      88      1    sb       Lscala/collection/mutable/StringBuilder;
   32      55      7    len       I


public scala.collection.mutable.StringBuilder append(java.lang.String);
  Code:
   Stack=5, Locals=4, Args_size=2
   0:	aload_1
   1:	dup
   2:	pop
   3:	ifnull	14
   6:	aload_1
   7:	aconst_null
   8:	invokevirtual	#377; //Method java/lang/Object.equals:(Ljava/lang/Object;)Z
   11:	ifeq	20
   14:	ldc_w	#379; //String null
   17:	goto	21
   20:	aload_1
   21:	astore_2
   22:	aload_2
   23:	invokevirtual	#135; //Method java/lang/String.length:()I
   26:	istore_3
   27:	aload_0
   28:	aload_0
   29:	invokespecial	#245; //Method count:()I
   32:	iload_3
   33:	iadd
   34:	invokevirtual	#330; //Method ensureCapacity:(I)V
   37:	aload_2
   38:	iconst_0
   39:	iload_3
   40:	aload_0
   41:	invokespecial	#243; //Method array:()[C
   44:	aload_0
   45:	invokespecial	#245; //Method count:()I
   48:	invokevirtual	#383; //Method java/lang/String.getChars:(II[CI)V
   51:	aload_0
   52:	aload_0
   53:	invokespecial	#245; //Method count:()I
   56:	iload_3
   57:	iadd
   58:	invokespecial	#339; //Method count_$eq:(I)V
   61:	aload_0
   62:	areturn
  LineNumberTable: 
   line 260: 0
   line 261: 22
   line 262: 27
   line 263: 37
   line 264: 51
   line 265: 61

  LocalVariableTable: 
   Start  Length  Slot  Name   Signature
   0      63      0    this       Lscala/collection/mutable/StringBuilder;
   0      63      1    s       Ljava/lang/String;
   22      40      2    str       Ljava/lang/String;
   27      35      3    len       I


public scala.collection.mutable.StringBuilder append(java.lang.Object);
  Code:
   Stack=2, Locals=2, Args_size=2
   0:	aload_0
   1:	aload_1
   2:	invokestatic	#387; //Method java/lang/String.valueOf:(Ljava/lang/Object;)Ljava/lang/String;
   5:	invokevirtual	#143; //Method append:(Ljava/lang/String;)Lscala/collection/mutable/StringBuilder;
   8:	areturn
  LineNumberTable: 
   line 252: 0

  LocalVariableTable: 
   Start  Length  Slot  Name   Signature
   0      9      0    this       Lscala/collection/mutable/StringBuilder;
   0      9      1    x       Ljava/lang/Object;


public scala.collection.mutable.StringBuilder $plus(char);
  Code:
   Stack=2, Locals=2, Args_size=2
   0:	aload_0
   1:	iload_1
   2:	invokevirtual	#181; //Method $plus$eq:(C)Lscala/collection/mutable/StringBuilder;
   5:	pop
   6:	aload_0
   7:	areturn
  LineNumberTable: 
   line 235: 0

  LocalVariableTable: 
   Start  Length  Slot  Name   Signature
   0      8      0    this       Lscala/collection/mutable/StringBuilder;
   0      8      1    x       C


public scala.collection.mutable.StringBuilder $plus$eq(char);
  Code:
   Stack=2, Locals=2, Args_size=2
   0:	aload_0
   1:	iload_1
   2:	invokevirtual	#445; //Method append:(C)Lscala/collection/mutable/StringBuilder;
   5:	pop
   6:	aload_0
   7:	areturn
  LineNumberTable: 
   line 233: 0

  LocalVariableTable: 
   Start  Length  Slot  Name   Signature
   0      8      0    this       Lscala/collection/mutable/StringBuilder;
   0      8      1    x       C


public java.lang.CharSequence subSequence(int, int);
  Code:
   Stack=3, Locals=3, Args_size=3
   0:	aload_0
   1:	iload_1
   2:	iload_2
   3:	invokevirtual	#451; //Method substring:(II)Ljava/lang/String;
   6:	areturn
  LineNumberTable: 
   line 229: 0

  LocalVariableTable: 
   Start  Length  Slot  Name   Signature
   0      7      0    this       Lscala/collection/mutable/StringBuilder;
   0      7      1    start       I
   0      7      2    end       I


public java.lang.String substring(int, int);
  Code:
   Stack=6, Locals=3, Args_size=3
   0:	iload_1
   1:	iconst_0
   2:	if_icmpge	14
   5:	new	#324; //class java/lang/StringIndexOutOfBoundsException
   8:	dup
   9:	iload_1
   10:	invokespecial	#327; //Method java/lang/StringIndexOutOfBoundsException."<init>":(I)V
   13:	athrow
   14:	iload_2
   15:	aload_0
   16:	invokespecial	#245; //Method count:()I
   19:	if_icmple	31
   22:	new	#324; //class java/lang/StringIndexOutOfBoundsException
   25:	dup
   26:	iload_2
   27:	invokespecial	#327; //Method java/lang/StringIndexOutOfBoundsException."<init>":(I)V
   30:	athrow
   31:	iload_1
   32:	iload_2
   33:	if_icmple	47
   36:	new	#324; //class java/lang/StringIndexOutOfBoundsException
   39:	dup
   40:	iload_2
   41:	iload_1
   42:	isub
   43:	invokespecial	#327; //Method java/lang/StringIndexOutOfBoundsException."<init>":(I)V
   46:	athrow
   47:	new	#131; //class java/lang/String
   50:	dup
   51:	aload_0
   52:	invokespecial	#243; //Method array:()[C
   55:	iload_1
   56:	iload_2
   57:	iload_1
   58:	isub
   59:	invokespecial	#248; //Method java/lang/String."<init>":([CII)V
   62:	areturn
  LineNumberTable: 
   line 220: 0
   line 221: 5
   line 222: 14
   line 223: 22
   line 224: 31
   line 225: 36
   line 226: 47

  LocalVariableTable: 
   Start  Length  Slot  Name   Signature
   0      63      0    this       Lscala/collection/mutable/StringBuilder;
   0      63      1    start       I
   0      63      2    end       I


public java.lang.String substring(int);
  Code:
   Stack=3, Locals=2, Args_size=2
   0:	aload_0
   1:	iload_1
   2:	aload_0
   3:	invokespecial	#245; //Method count:()I
   6:	invokevirtual	#451; //Method substring:(II)Ljava/lang/String;
   9:	areturn
  LineNumberTable: 
   line 204: 0

  LocalVariableTable: 
   Start  Length  Slot  Name   Signature
   0      10      0    this       Lscala/collection/mutable/StringBuilder;
   0      10      1    start       I


public void update(int, char);
  Code:
   Stack=3, Locals=3, Args_size=3
   0:	aload_0
   1:	iload_1
   2:	iload_2
   3:	invokevirtual	#454; //Method setCharAt:(IC)V
   6:	return
  LineNumberTable: 
   line 192: 0

  LocalVariableTable: 
   Start  Length  Slot  Name   Signature
   0      7      0    this       Lscala/collection/mutable/StringBuilder;
   0      7      1    i       I
   0      7      2    c       C


public void setCharAt(int, char);
  Code:
   Stack=3, Locals=3, Args_size=3
   0:	iload_1
   1:	iconst_0
   2:	if_icmplt	13
   5:	iload_1
   6:	aload_0
   7:	invokespecial	#245; //Method count:()I
   10:	if_icmplt	22
   13:	new	#324; //class java/lang/StringIndexOutOfBoundsException
   16:	dup
   17:	iload_1
   18:	invokespecial	#327; //Method java/lang/StringIndexOutOfBoundsException."<init>":(I)V
   21:	athrow
   22:	aload_0
   23:	invokespecial	#243; //Method array:()[C
   26:	iload_1
   27:	iload_2
   28:	castore
   29:	return
  LineNumberTable: 
   line 186: 0
   line 187: 13
   line 188: 22

  LocalVariableTable: 
   Start  Length  Slot  Name   Signature
   0      30      0    this       Lscala/collection/mutable/StringBuilder;
   0      30      1    index       I
   0      30      2    ch       C


public scala.collection.mutable.StringBuilder deleteCharAt(int);
  Code:
   Stack=5, Locals=6, Args_size=2
   0:	iload_1
   1:	iconst_0
   2:	if_icmplt	13
   5:	iload_1
   6:	aload_0
   7:	invokespecial	#245; //Method count:()I
   10:	if_icmplt	22
   13:	new	#324; //class java/lang/StringIndexOutOfBoundsException
   16:	dup
   17:	iload_1
   18:	invokespecial	#327; //Method java/lang/StringIndexOutOfBoundsException."<init>":(I)V
   21:	athrow
   22:	aload_0
   23:	invokespecial	#243; //Method array:()[C
   26:	iload_1
   27:	iconst_1
   28:	iadd
   29:	aload_0
   30:	invokespecial	#243; //Method array:()[C
   33:	aload_0
   34:	invokespecial	#245; //Method count:()I
   37:	iload_1
   38:	isub
   39:	iconst_1
   40:	isub
   41:	istore	5
   43:	astore	4
   45:	istore_3
   46:	astore_2
   47:	aload_2
   48:	iload_3
   49:	aload	4
   51:	iload_1
   52:	iload	5
   54:	invokestatic	#336; //Method java/lang/System.arraycopy:(Ljava/lang/Object;ILjava/lang/Object;II)V
   57:	aload_0
   58:	aload_0
   59:	invokespecial	#245; //Method count:()I
   62:	iconst_1
   63:	isub
   64:	invokespecial	#339; //Method count_$eq:(I)V
   67:	aload_0
   68:	areturn
  LineNumberTable: 
   line 162: 0
   line 163: 13
   line 164: 22
   line 165: 57
   line 166: 67

  LocalVariableTable: 
   Start  Length  Slot  Name   Signature
   0      69      0    this       Lscala/collection/mutable/StringBuilder;
   0      69      1    index       I


public char apply(int);
  Code:
   Stack=2, Locals=2, Args_size=2
   0:	aload_0
   1:	iload_1
   2:	invokevirtual	#460; //Method charAt:(I)C
   5:	ireturn
  LineNumberTable: 
   line 149: 0

  LocalVariableTable: 
   Start  Length  Slot  Name   Signature
   0      6      0    this       Lscala/collection/mutable/StringBuilder;
   0      6      1    i       I


public char charAt(int);
  Code:
   Stack=3, Locals=2, Args_size=2
   0:	iload_1
   1:	iconst_0
   2:	if_icmplt	13
   5:	iload_1
   6:	aload_0
   7:	invokespecial	#245; //Method count:()I
   10:	if_icmplt	22
   13:	new	#324; //class java/lang/StringIndexOutOfBoundsException
   16:	dup
   17:	iload_1
   18:	invokespecial	#327; //Method java/lang/StringIndexOutOfBoundsException."<init>":(I)V
   21:	athrow
   22:	aload_0
   23:	invokespecial	#243; //Method array:()[C
   26:	iload_1
   27:	caload
   28:	ireturn
  LineNumberTable: 
   line 143: 0
   line 144: 13
   line 145: 22

  LocalVariableTable: 
   Start  Length  Slot  Name   Signature
   0      29      0    this       Lscala/collection/mutable/StringBuilder;
   0      29      1    index       I


public void ensureCapacity(int);
  Code:
   Stack=5, Locals=9, Args_size=2
   0:	iload_1
   1:	aload_0
   2:	invokespecial	#243; //Method array:()[C
   5:	arraylength
   6:	if_icmple	84
   9:	aload_0
   10:	invokespecial	#243; //Method array:()[C
   13:	arraylength
   14:	iconst_2
   15:	imul
   16:	istore_2
   17:	new	#462; //class scala/runtime/RichInt
   20:	dup
   21:	iload_2
   22:	invokespecial	#463; //Method scala/runtime/RichInt."<init>":(I)V
   25:	iconst_1
   26:	invokevirtual	#467; //Method scala/runtime/RichInt.max:(I)I
   29:	istore_3
   30:	iload_1
   31:	iload_3
   32:	if_icmple	42
   35:	iload_3
   36:	iconst_2
   37:	imul
   38:	istore_3
   39:	goto	30
   42:	iload_3
   43:	newarray char
   45:	astore	8
   47:	aload_0
   48:	invokespecial	#243; //Method array:()[C
   51:	iconst_0
   52:	iconst_0
   53:	aload_0
   54:	invokespecial	#245; //Method count:()I
   57:	istore	7
   59:	istore	6
   61:	istore	5
   63:	astore	4
   65:	aload	4
   67:	iload	5
   69:	aload	8
   71:	iload	6
   73:	iload	7
   75:	invokestatic	#336; //Method java/lang/System.arraycopy:(Ljava/lang/Object;ILjava/lang/Object;II)V
   78:	aload_0
   79:	aload	8
   81:	invokespecial	#471; //Method array_$eq:([C)V
   84:	return
  LineNumberTable: 
   line 117: 0
   line 118: 9
   line 119: 30
   line 120: 35
   line 121: 42
   line 122: 47
   line 123: 78
   line 117: 84

  LocalVariableTable: 
   Start  Length  Slot  Name   Signature
   0      85      0    this       Lscala/collection/mutable/StringBuilder;
   0      85      1    n       I
   30      54      3    newsize       I
   47      37      8    newar       [C


public void capacity_$eq(int);
  Code:
   Stack=2, Locals=2, Args_size=2
   0:	aload_0
   1:	iload_1
   2:	invokevirtual	#330; //Method ensureCapacity:(I)V
   5:	return
  LineNumberTable: 
   line 98: 0

  LocalVariableTable: 
   Start  Length  Slot  Name   Signature
   0      6      0    this       Lscala/collection/mutable/StringBuilder;
   0      6      1    n       I

  Deprecated: true

public int capacity();
  Code:
   Stack=1, Locals=1, Args_size=1
   0:	aload_0
   1:	invokespecial	#243; //Method array:()[C
   4:	arraylength
   5:	ireturn
  LineNumberTable: 
   line 93: 0


public void setLength(int);
  Code:
   Stack=4, Locals=5, Args_size=2
   0:	iload_1
   1:	iconst_0
   2:	if_icmplt	9
   5:	iconst_1
   6:	goto	10
   9:	iconst_0
   10:	new	#478; //class scala/collection/mutable/StringBuilder$$anonfun$setLength$1
   13:	dup
   14:	pop
   15:	aload_0
   16:	iload_1
   17:	invokespecial	#481; //Method scala/collection/mutable/StringBuilder$$anonfun$setLength$1."<init>":(Lscala/collection/mutable/StringBuilder;I)V
   20:	istore_2
   21:	iload_2
   22:	ifeq	74
   25:	aload_0
   26:	invokespecial	#245; //Method count:()I
   29:	iload_1
   30:	if_icmpge	68
   33:	iconst_0
   34:	istore_3
   35:	aload_0
   36:	aload_0
   37:	invokespecial	#245; //Method count:()I
   40:	iconst_1
   41:	iadd
   42:	invokevirtual	#330; //Method ensureCapacity:(I)V
   45:	aload_0
   46:	invokespecial	#243; //Method array:()[C
   49:	aload_0
   50:	invokespecial	#245; //Method count:()I
   53:	iload_3
   54:	castore
   55:	aload_0
   56:	aload_0
   57:	invokespecial	#245; //Method count:()I
   60:	iconst_1
   61:	iadd
   62:	invokespecial	#339; //Method count_$eq:(I)V
   65:	goto	25
   68:	aload_0
   69:	iload_1
   70:	invokespecial	#339; //Method count_$eq:(I)V
   73:	return
   74:	new	#483; //class java/lang/IllegalArgumentException
   77:	dup
   78:	new	#11; //class scala/collection/mutable/StringBuilder
   81:	dup
   82:	invokespecial	#393; //Method "<init>":()V
   85:	ldc_w	#485; //String requirement failed: 
   88:	invokevirtual	#398; //Method append:(Ljava/lang/Object;)Lscala/collection/mutable/StringBuilder;
   91:	iload_1
   92:	istore	4
   94:	iload	4
   96:	invokestatic	#402; //Method scala/runtime/BoxesRunTime.boxToInteger:(I)Ljava/lang/Integer;
   99:	invokevirtual	#398; //Method append:(Ljava/lang/Object;)Lscala/collection/mutable/StringBuilder;
   102:	invokevirtual	#407; //Method toString:()Ljava/lang/String;
   105:	invokespecial	#486; //Method java/lang/IllegalArgumentException."<init>":(Ljava/lang/String;)V
   108:	athrow
  LineNumberTable: 
   line 82: 0
   line 83: 25
   line 84: 68
   line 82: 74

  LocalVariableTable: 
   Start  Length  Slot  Name   Signature
   0      109      0    this       Lscala/collection/mutable/StringBuilder;
   0      109      1    n$1       I
   25      0      2    requirement0       Z
   74      35      2    requirement0       Z


public void clear();
  Code:
   Stack=2, Locals=1, Args_size=1
   0:	aload_0
   1:	iconst_0
   2:	invokevirtual	#491; //Method setLength:(I)V
   5:	return
  LineNumberTable: 
   line 74: 0


public void length_$eq(int);
  Code:
   Stack=2, Locals=2, Args_size=2
   0:	aload_0
   1:	iload_1
   2:	invokevirtual	#491; //Method setLength:(I)V
   5:	return
  LineNumberTable: 
   line 70: 0

  LocalVariableTable: 
   Start  Length  Slot  Name   Signature
   0      6      0    this       Lscala/collection/mutable/StringBuilder;
   0      6      1    n       I


public int length();
  Code:
   Stack=1, Locals=1, Args_size=1
   0:	aload_0
   1:	invokespecial	#245; //Method count:()I
   4:	ireturn
  LineNumberTable: 
   line 69: 0


public char[] toArray();
  Code:
   Stack=1, Locals=1, Args_size=1
   0:	aload_0
   1:	invokespecial	#243; //Method array:()[C
   4:	areturn
  LineNumberTable: 
   line 67: 0


public scala.collection.mutable.StringBuilder(java.lang.String);
  Code:
   Stack=3, Locals=2, Args_size=2
   0:	aload_0
   1:	ldc_w	#493; //int 16
   4:	aload_1
   5:	invokespecial	#495; //Method "<init>":(ILjava/lang/String;)V
   8:	return
  LineNumberTable: 
   line 63: 0

  LocalVariableTable: 
   Start  Length  Slot  Name   Signature
   0      9      0    this       Lscala/collection/mutable/StringBuilder;
   0      9      1    str       Ljava/lang/String;


public scala.collection.mutable.StringBuilder(int);
  Code:
   Stack=3, Locals=2, Args_size=2
   0:	aload_0
   1:	iload_1
   2:	ldc_w	#497; //String 
   5:	invokespecial	#495; //Method "<init>":(ILjava/lang/String;)V
   8:	return
  LineNumberTable: 
   line 58: 0

  LocalVariableTable: 
   Start  Length  Slot  Name   Signature
   0      9      0    this       Lscala/collection/mutable/StringBuilder;
   0      9      1    capacity       I


public scala.collection.mutable.StringBuilder();
  Code:
   Stack=3, Locals=1, Args_size=1
   0:	aload_0
   1:	ldc_w	#493; //int 16
   4:	ldc_w	#497; //String 
   7:	invokespecial	#495; //Method "<init>":(ILjava/lang/String;)V
   10:	return
  LineNumberTable: 
   line 49: 0


public scala.collection.generic.Growable $plus$plus$eq(scala.collection.Traversable);
  Code:
   Stack=2, Locals=2, Args_size=2
   0:	aload_0
   1:	aload_1
   2:	invokestatic	#502; //Method scala/collection/generic/Growable$class.$plus$plus$eq:(Lscala/collection/generic/Growable;Lscala/collection/Traversable;)Lscala/collection/generic/Growable;
   5:	areturn
  LineNumberTable: 
   line 32: 0

  LocalVariableTable: 
   Start  Length  Slot  Name   Signature
   0      6      0    this       Lscala/collection/mutable/StringBuilder;
   0      6      1    elems       Lscala/collection/Traversable;


public scala.collection.generic.Growable $plus$plus$eq(scala.collection.Iterator);
  Code:
   Stack=2, Locals=2, Args_size=2
   0:	aload_0
   1:	aload_1
   2:	invokestatic	#508; //Method scala/collection/generic/Growable$class.$plus$plus$eq:(Lscala/collection/generic/Growable;Lscala/collection/Iterator;)Lscala/collection/generic/Growable;
   5:	areturn
  LineNumberTable: 
   line 32: 0

  LocalVariableTable: 
   Start  Length  Slot  Name   Signature
   0      6      0    this       Lscala/collection/mutable/StringBuilder;
   0      6      1    iter       Lscala/collection/Iterator;


public scala.collection.generic.Growable $plus$eq(java.lang.Object, java.lang.Object, scala.collection.Seq);
  Code:
   Stack=4, Locals=4, Args_size=4
   0:	aload_0
   1:	aload_1
   2:	aload_2
   3:	aload_3
   4:	invokestatic	#514; //Method scala/collection/generic/Growable$class.$plus$eq:(Lscala/collection/generic/Growable;Ljava/lang/Object;Ljava/lang/Object;Lscala/collection/Seq;)Lscala/collection/generic/Growable;
   7:	areturn
  LineNumberTable: 
   line 32: 0

  LocalVariableTable: 
   Start  Length  Slot  Name   Signature
   0      8      0    this       Lscala/collection/mutable/StringBuilder;
   0      8      1    elem1       Ljava/lang/Object;
   0      8      2    elem2       Ljava/lang/Object;
   0      8      3    elems       Lscala/collection/Seq;


public scala.collection.mutable.Builder mapResult(scala.Function1);
  Code:
   Stack=2, Locals=2, Args_size=2
   0:	aload_0
   1:	aload_1
   2:	invokestatic	#521; //Method scala/collection/mutable/Builder$class.mapResult:(Lscala/collection/mutable/Builder;Lscala/Function1;)Lscala/collection/mutable/Builder;
   5:	areturn
  LineNumberTable: 
   line 32: 0

  LocalVariableTable: 
   Start  Length  Slot  Name   Signature
   0      6      0    this       Lscala/collection/mutable/StringBuilder;
   0      6      1    f       Lscala/Function1;


public void sizeHint(int);
  Code:
   Stack=2, Locals=2, Args_size=2
   0:	aload_0
   1:	iload_1
   2:	invokestatic	#526; //Method scala/collection/mutable/Builder$class.sizeHint:(Lscala/collection/mutable/Builder;I)V
   5:	return
  LineNumberTable: 
   line 32: 0

  LocalVariableTable: 
   Start  Length  Slot  Name   Signature
   0      6      0    this       Lscala/collection/mutable/StringBuilder;
   0      6      1    size       I


public scala.collection.TraversableLike$WithFilter withFilter(scala.Function1);
  Code:
   Stack=2, Locals=2, Args_size=2
   0:	aload_0
   1:	aload_1
   2:	invokestatic	#532; //Method scala/collection/TraversableLike$class.withFilter:(Lscala/collection/TraversableLike;Lscala/Function1;)Lscala/collection/TraversableLike$WithFilter;
   5:	areturn
  LineNumberTable: 
   line 32: 0

  LocalVariableTable: 
   Start  Length  Slot  Name   Signature
   0      6      0    this       Lscala/collection/mutable/StringBuilder;
   0      6      1    p       Lscala/Function1;

  Signature: length = 0x2
   02 11 

public java.lang.String stringPrefix();
  Code:
   Stack=1, Locals=1, Args_size=1
   0:	aload_0
   1:	invokestatic	#537; //Method scala/collection/TraversableLike$class.stringPrefix:(Lscala/collection/TraversableLike;)Ljava/lang/String;
   4:	areturn
  LineNumberTable: 
   line 32: 0


public scala.collection.mutable.StringBuilder addString(scala.collection.mutable.StringBuilder);
  Code:
   Stack=2, Locals=2, Args_size=2
   0:	aload_0
   1:	aload_1
   2:	invokestatic	#541; //Method scala/collection/TraversableLike$class.addString:(Lscala/collection/TraversableLike;Lscala/collection/mutable/StringBuilder;)Lscala/collection/mutable/StringBuilder;
   5:	areturn
  LineNumberTable: 
   line 32: 0

  LocalVariableTable: 
   Start  Length  Slot  Name   Signature
   0      6      0    this       Lscala/collection/mutable/StringBuilder;
   0      6      1    b       Lscala/collection/mutable/StringBuilder;


public scala.collection.mutable.StringBuilder addString(scala.collection.mutable.StringBuilder, java.lang.String);
  Code:
   Stack=3, Locals=3, Args_size=3
   0:	aload_0
   1:	aload_1
   2:	aload_2
   3:	invokestatic	#546; //Method scala/collection/TraversableLike$class.addString:(Lscala/collection/TraversableLike;Lscala/collection/mutable/StringBuilder;Ljava/lang/String;)Lscala/collection/mutable/StringBuilder;
   6:	areturn
  LineNumberTable: 
   line 32: 0

  LocalVariableTable: 
   Start  Length  Slot  Name   Signature
   0      7      0    this       Lscala/collection/mutable/StringBuilder;
   0      7      1    b       Lscala/collection/mutable/StringBuilder;
   0      7      2    sep       Ljava/lang/String;


public scala.collection.mutable.StringBuilder addString(scala.collection.mutable.StringBuilder, java.lang.String, java.lang.String, java.lang.String);
  Code:
   Stack=5, Locals=5, Args_size=5
   0:	aload_0
   1:	aload_1
   2:	aload_2
   3:	aload_3
   4:	aload	4
   6:	invokestatic	#551; //Method scala/collection/TraversableLike$class.addString:(Lscala/collection/TraversableLike;Lscala/collection/mutable/StringBuilder;Ljava/lang/String;Ljava/lang/String;Ljava/lang/String;)Lscala/collection/mutable/StringBuilder;
   9:	areturn
  LineNumberTable: 
   line 32: 0

  LocalVariableTable: 
   Start  Length  Slot  Name   Signature
   0      10      0    this       Lscala/collection/mutable/StringBuilder;
   0      10      1    b       Lscala/collection/mutable/StringBuilder;
   0      10      2    start       Ljava/lang/String;
   0      10      3    sep       Ljava/lang/String;
   0      10      4    end       Ljava/lang/String;


public java.lang.String mkString();
  Code:
   Stack=1, Locals=1, Args_size=1
   0:	aload_0
   1:	invokestatic	#554; //Method scala/collection/TraversableLike$class.mkString:(Lscala/collection/TraversableLike;)Ljava/lang/String;
   4:	areturn
  LineNumberTable: 
   line 32: 0


public java.lang.String mkString(java.lang.String);
  Code:
   Stack=2, Locals=2, Args_size=2
   0:	aload_0
   1:	aload_1
   2:	invokestatic	#558; //Method scala/collection/TraversableLike$class.mkString:(Lscala/collection/TraversableLike;Ljava/lang/String;)Ljava/lang/String;
   5:	areturn
  LineNumberTable: 
   line 32: 0

  LocalVariableTable: 
   Start  Length  Slot  Name   Signature
   0      6      0    this       Lscala/collection/mutable/StringBuilder;
   0      6      1    sep       Ljava/lang/String;


public java.lang.String mkString(java.lang.String, java.lang.String, java.lang.String);
  Code:
   Stack=4, Locals=4, Args_size=4
   0:	aload_0
   1:	aload_1
   2:	aload_2
   3:	aload_3
   4:	invokestatic	#562; //Method scala/collection/TraversableLike$class.mkString:(Lscala/collection/TraversableLike;Ljava/lang/String;Ljava/lang/String;Ljava/lang/String;)Ljava/lang/String;
   7:	areturn
  LineNumberTable: 
   line 32: 0

  LocalVariableTable: 
   Start  Length  Slot  Name   Signature
   0      8      0    this       Lscala/collection/mutable/StringBuilder;
   0      8      1    start       Ljava/lang/String;
   0      8      2    sep       Ljava/lang/String;
   0      8      3    end       Ljava/lang/String;


public scala.collection.immutable.Set toSet();
  Code:
   Stack=1, Locals=1, Args_size=1
   0:	aload_0
   1:	invokestatic	#567; //Method scala/collection/TraversableLike$class.toSet:(Lscala/collection/TraversableLike;)Lscala/collection/immutable/Set;
   4:	areturn
  LineNumberTable: 
   line 32: 0


public scala.collection.mutable.IndexedSeq toIndexedSeq();
  Code:
   Stack=1, Locals=1, Args_size=1
   0:	aload_0
   1:	invokestatic	#570; //Method scala/collection/TraversableLike$class.toIndexedSeq:(Lscala/collection/TraversableLike;)Lscala/collection/mutable/IndexedSeq;
   4:	areturn
  LineNumberTable: 
   line 32: 0


public scala.collection.immutable.List toList();
  Code:
   Stack=1, Locals=1, Args_size=1
   0:	aload_0
   1:	invokestatic	#575; //Method scala/collection/TraversableLike$class.toList:(Lscala/collection/TraversableLike;)Lscala/collection/immutable/List;
   4:	areturn
  LineNumberTable: 
   line 32: 0


public java.lang.Object toArray(scala.reflect.ClassManifest);
  Code:
   Stack=2, Locals=2, Args_size=2
   0:	aload_0
   1:	aload_1
   2:	invokestatic	#578; //Method scala/collection/TraversableLike$class.toArray:(Lscala/collection/TraversableLike;Lscala/reflect/ClassManifest;)Ljava/lang/Object;
   5:	areturn
  LineNumberTable: 
   line 32: 0

  LocalVariableTable: 
   Start  Length  Slot  Name   Signature
   0      6      0    this       Lscala/collection/mutable/StringBuilder;
   0      6      1    evidence$1       Lscala/reflect/ClassManifest;


public void copyToArray(java.lang.Object);
  Code:
   Stack=2, Locals=2, Args_size=2
   0:	aload_0
   1:	aload_1
   2:	invokestatic	#585; //Method scala/collection/TraversableLike$class.copyToArray:(Lscala/collection/TraversableLike;Ljava/lang/Object;)V
   5:	return
  LineNumberTable: 
   line 32: 0

  LocalVariableTable: 
   Start  Length  Slot  Name   Signature
   0      6      0    this       Lscala/collection/mutable/StringBuilder;
   0      6      1    xs       Ljava/lang/Object;


public void copyToArray(java.lang.Object, int);
  Code:
   Stack=3, Locals=3, Args_size=3
   0:	aload_0
   1:	aload_1
   2:	iload_2
   3:	invokestatic	#590; //Method scala/collection/TraversableLike$class.copyToArray:(Lscala/collection/TraversableLike;Ljava/lang/Object;I)V
   6:	return
  LineNumberTable: 
   line 32: 0

  LocalVariableTable: 
   Start  Length  Slot  Name   Signature
   0      7      0    this       Lscala/collection/mutable/StringBuilder;
   0      7      1    xs       Ljava/lang/Object;
   0      7      2    start       I


public void copyToBuffer(scala.collection.mutable.Buffer);
  Code:
   Stack=2, Locals=2, Args_size=2
   0:	aload_0
   1:	aload_1
   2:	invokestatic	#595; //Method scala/collection/TraversableLike$class.copyToBuffer:(Lscala/collection/TraversableLike;Lscala/collection/mutable/Buffer;)V
   5:	return
  LineNumberTable: 
   line 32: 0

  LocalVariableTable: 
   Start  Length  Slot  Name   Signature
   0      6      0    this       Lscala/collection/mutable/StringBuilder;
   0      6      1    dest       Lscala/collection/mutable/Buffer;


public scala.Option lastOption();
  Code:
   Stack=1, Locals=1, Args_size=1
   0:	aload_0
   1:	invokestatic	#602; //Method scala/collection/TraversableLike$class.lastOption:(Lscala/collection/TraversableLike;)Lscala/Option;
   4:	areturn
  LineNumberTable: 
   line 32: 0


public scala.Option headOption();
  Code:
   Stack=1, Locals=1, Args_size=1
   0:	aload_0
   1:	invokestatic	#605; //Method scala/collection/TraversableLike$class.headOption:(Lscala/collection/TraversableLike;)Lscala/Option;
   4:	areturn
  LineNumberTable: 
   line 32: 0


public java.lang.Object max(scala.math.Ordering);
  Code:
   Stack=2, Locals=2, Args_size=2
   0:	aload_0
   1:	aload_1
   2:	invokestatic	#609; //Method scala/collection/TraversableLike$class.max:(Lscala/collection/TraversableLike;Lscala/math/Ordering;)Ljava/lang/Object;
   5:	areturn
  LineNumberTable: 
   line 32: 0

  LocalVariableTable: 
   Start  Length  Slot  Name   Signature
   0      6      0    this       Lscala/collection/mutable/StringBuilder;
   0      6      1    cmp       Lscala/math/Ordering;


public java.lang.Object min(scala.math.Ordering);
  Code:
   Stack=2, Locals=2, Args_size=2
   0:	aload_0
   1:	aload_1
   2:	invokestatic	#614; //Method scala/collection/TraversableLike$class.min:(Lscala/collection/TraversableLike;Lscala/math/Ordering;)Ljava/lang/Object;
   5:	areturn
  LineNumberTable: 
   line 32: 0

  LocalVariableTable: 
   Start  Length  Slot  Name   Signature
   0      6      0    this       Lscala/collection/mutable/StringBuilder;
   0      6      1    cmp       Lscala/math/Ordering;


public java.lang.Object product(scala.math.Numeric);
  Code:
   Stack=2, Locals=2, Args_size=2
   0:	aload_0
   1:	aload_1
   2:	invokestatic	#619; //Method scala/collection/TraversableLike$class.product:(Lscala/collection/TraversableLike;Lscala/math/Numeric;)Ljava/lang/Object;
   5:	areturn
  LineNumberTable: 
   line 32: 0

  LocalVariableTable: 
   Start  Length  Slot  Name   Signature
   0      6      0    this       Lscala/collection/mutable/StringBuilder;
   0      6      1    num       Lscala/math/Numeric;


public java.lang.Object sum(scala.math.Numeric);
  Code:
   Stack=2, Locals=2, Args_size=2
   0:	aload_0
   1:	aload_1
   2:	invokestatic	#624; //Method scala/collection/TraversableLike$class.sum:(Lscala/collection/TraversableLike;Lscala/math/Numeric;)Ljava/lang/Object;
   5:	areturn
  LineNumberTable: 
   line 32: 0

  LocalVariableTable: 
   Start  Length  Slot  Name   Signature
   0      6      0    this       Lscala/collection/mutable/StringBuilder;
   0      6      1    num       Lscala/math/Numeric;


public scala.Option reduceRightOption(scala.Function2);
  Code:
   Stack=2, Locals=2, Args_size=2
   0:	aload_0
   1:	aload_1
   2:	invokestatic	#629; //Method scala/collection/TraversableLike$class.reduceRightOption:(Lscala/collection/TraversableLike;Lscala/Function2;)Lscala/Option;
   5:	areturn
  LineNumberTable: 
   line 32: 0

  LocalVariableTable: 
   Start  Length  Slot  Name   Signature
   0      6      0    this       Lscala/collection/mutable/StringBuilder;
   0      6      1    op       Lscala/Function2;


public scala.Option reduceLeftOption(scala.Function2);
  Code:
   Stack=2, Locals=2, Args_size=2
   0:	aload_0
   1:	aload_1
   2:	invokestatic	#634; //Method scala/collection/TraversableLike$class.reduceLeftOption:(Lscala/collection/TraversableLike;Lscala/Function2;)Lscala/Option;
   5:	areturn
  LineNumberTable: 
   line 32: 0

  LocalVariableTable: 
   Start  Length  Slot  Name   Signature
   0      6      0    this       Lscala/collection/mutable/StringBuilder;
   0      6      1    op       Lscala/Function2;


public java.lang.Object $colon$bslash(java.lang.Object, scala.Function2);
  Code:
   Stack=3, Locals=3, Args_size=3
   0:	aload_0
   1:	aload_1
   2:	aload_2
   3:	invokestatic	#639; //Method scala/collection/TraversableLike$class.$colon$bslash:(Lscala/collection/TraversableLike;Ljava/lang/Object;Lscala/Function2;)Ljava/lang/Object;
   6:	areturn
  LineNumberTable: 
   line 32: 0

  LocalVariableTable: 
   Start  Length  Slot  Name   Signature
   0      7      0    this       Lscala/collection/mutable/StringBuilder;
   0      7      1    z       Ljava/lang/Object;
   0      7      2    op       Lscala/Function2;


public java.lang.Object $div$colon(java.lang.Object, scala.Function2);
  Code:
   Stack=3, Locals=3, Args_size=3
   0:	aload_0
   1:	aload_1
   2:	aload_2
   3:	invokestatic	#643; //Method scala/collection/TraversableLike$class.$div$colon:(Lscala/collection/TraversableLike;Ljava/lang/Object;Lscala/Function2;)Ljava/lang/Object;
   6:	areturn
  LineNumberTable: 
   line 32: 0

  LocalVariableTable: 
   Start  Length  Slot  Name   Signature
   0      7      0    this       Lscala/collection/mutable/StringBuilder;
   0      7      1    z       Ljava/lang/Object;
   0      7      2    op       Lscala/Function2;


public int count(scala.Function1);
  Code:
   Stack=2, Locals=2, Args_size=2
   0:	aload_0
   1:	aload_1
   2:	invokestatic	#647; //Method scala/collection/TraversableLike$class.count:(Lscala/collection/TraversableLike;Lscala/Function1;)I
   5:	ireturn
  LineNumberTable: 
   line 32: 0

  LocalVariableTable: 
   Start  Length  Slot  Name   Signature
   0      6      0    this       Lscala/collection/mutable/StringBuilder;
   0      6      1    p       Lscala/Function1;


public scala.collection.Map groupBy(scala.Function1);
  Code:
   Stack=2, Locals=2, Args_size=2
   0:	aload_0
   1:	aload_1
   2:	invokestatic	#652; //Method scala/collection/TraversableLike$class.groupBy:(Lscala/collection/TraversableLike;Lscala/Function1;)Lscala/collection/Map;
   5:	areturn
  LineNumberTable: 
   line 32: 0

  LocalVariableTable: 
   Start  Length  Slot  Name   Signature
   0      6      0    this       Lscala/collection/mutable/StringBuilder;
   0      6      1    f       Lscala/Function1;


public scala.Tuple2 partition(scala.Function1);
  Code:
   Stack=2, Locals=2, Args_size=2
   0:	aload_0
   1:	aload_1
   2:	invokestatic	#657; //Method scala/collection/TraversableLike$class.partition:(Lscala/collection/TraversableLike;Lscala/Function1;)Lscala/Tuple2;
   5:	areturn
  LineNumberTable: 
   line 32: 0

  LocalVariableTable: 
   Start  Length  Slot  Name   Signature
   0      6      0    this       Lscala/collection/mutable/StringBuilder;
   0      6      1    p       Lscala/Function1;


public java.lang.Object partialMap(scala.PartialFunction, scala.collection.generic.CanBuildFrom);
  Code:
   Stack=3, Locals=3, Args_size=3
   0:	aload_0
   1:	aload_1
   2:	aload_2
   3:	invokestatic	#662; //Method scala/collection/TraversableLike$class.partialMap:(Lscala/collection/TraversableLike;Lscala/PartialFunction;Lscala/collection/generic/CanBuildFrom;)Ljava/lang/Object;
   6:	areturn
  LineNumberTable: 
   line 32: 0

  LocalVariableTable: 
   Start  Length  Slot  Name   Signature
   0      7      0    this       Lscala/collection/mutable/StringBuilder;
   0      7      1    pf       Lscala/PartialFunction;
   0      7      2    bf       Lscala/collection/generic/CanBuildFrom;


public java.lang.Object filterNot(scala.Function1);
  Code:
   Stack=2, Locals=2, Args_size=2
   0:	aload_0
   1:	aload_1
   2:	invokestatic	#671; //Method scala/collection/TraversableLike$class.filterNot:(Lscala/collection/TraversableLike;Lscala/Function1;)Ljava/lang/Object;
   5:	areturn
  LineNumberTable: 
   line 32: 0

  LocalVariableTable: 
   Start  Length  Slot  Name   Signature
   0      6      0    this       Lscala/collection/mutable/StringBuilder;
   0      6      1    p       Lscala/Function1;


public java.lang.Object filter(scala.Function1);
  Code:
   Stack=2, Locals=2, Args_size=2
   0:	aload_0
   1:	aload_1
   2:	invokestatic	#674; //Method scala/collection/TraversableLike$class.filter:(Lscala/collection/TraversableLike;Lscala/Function1;)Ljava/lang/Object;
   5:	areturn
  LineNumberTable: 
   line 32: 0

  LocalVariableTable: 
   Start  Length  Slot  Name   Signature
   0      6      0    this       Lscala/collection/mutable/StringBuilder;
   0      6      1    p       Lscala/Function1;


public java.lang.Object flatMap(scala.Function1, scala.collection.generic.CanBuildFrom);
  Code:
   Stack=3, Locals=3, Args_size=3
   0:	aload_0
   1:	aload_1
   2:	aload_2
   3:	invokestatic	#679; //Method scala/collection/TraversableLike$class.flatMap:(Lscala/collection/TraversableLike;Lscala/Function1;Lscala/collection/generic/CanBuildFrom;)Ljava/lang/Object;
   6:	areturn
  LineNumberTable: 
   line 32: 0

  LocalVariableTable: 
   Start  Length  Slot  Name   Signature
   0      7      0    this       Lscala/collection/mutable/StringBuilder;
   0      7      1    f       Lscala/Function1;
   0      7      2    bf       Lscala/collection/generic/CanBuildFrom;


public java.lang.Object map(scala.Function1, scala.collection.generic.CanBuildFrom);
  Code:
   Stack=3, Locals=3, Args_size=3
   0:	aload_0
   1:	aload_1
   2:	aload_2
   3:	invokestatic	#682; //Method scala/collection/TraversableLike$class.map:(Lscala/collection/TraversableLike;Lscala/Function1;Lscala/collection/generic/CanBuildFrom;)Ljava/lang/Object;
   6:	areturn
  LineNumberTable: 
   line 32: 0

  LocalVariableTable: 
   Start  Length  Slot  Name   Signature
   0      7      0    this       Lscala/collection/mutable/StringBuilder;
   0      7      1    f       Lscala/Function1;
   0      7      2    bf       Lscala/collection/generic/CanBuildFrom;


public java.lang.Object $plus$plus(scala.collection.Iterator, scala.collection.generic.CanBuildFrom);
  Code:
   Stack=3, Locals=3, Args_size=3
   0:	aload_0
   1:	aload_1
   2:	aload_2
   3:	invokestatic	#687; //Method scala/collection/TraversableLike$class.$plus$plus:(Lscala/collection/TraversableLike;Lscala/collection/Iterator;Lscala/collection/generic/CanBuildFrom;)Ljava/lang/Object;
   6:	areturn
  LineNumberTable: 
   line 32: 0

  LocalVariableTable: 
   Start  Length  Slot  Name   Signature
   0      7      0    this       Lscala/collection/mutable/StringBuilder;
   0      7      1    that       Lscala/collection/Iterator;
   0      7      2    bf       Lscala/collection/generic/CanBuildFrom;


public java.lang.Object $plus$plus(scala.collection.Traversable, scala.collection.generic.CanBuildFrom);
  Code:
   Stack=3, Locals=3, Args_size=3
   0:	aload_0
   1:	aload_1
   2:	aload_2
   3:	invokestatic	#692; //Method scala/collection/TraversableLike$class.$plus$plus:(Lscala/collection/TraversableLike;Lscala/collection/Traversable;Lscala/collection/generic/CanBuildFrom;)Ljava/lang/Object;
   6:	areturn
  LineNumberTable: 
   line 32: 0

  LocalVariableTable: 
   Start  Length  Slot  Name   Signature
   0      7      0    this       Lscala/collection/mutable/StringBuilder;
   0      7      1    that       Lscala/collection/Traversable;
   0      7      2    bf       Lscala/collection/generic/CanBuildFrom;


public boolean hasDefiniteSize();
  Code:
   Stack=1, Locals=1, Args_size=1
   0:	aload_0
   1:	invokestatic	#697; //Method scala/collection/TraversableLike$class.hasDefiniteSize:(Lscala/collection/TraversableLike;)Z
   4:	ireturn
  LineNumberTable: 
   line 32: 0


public boolean nonEmpty();
  Code:
   Stack=1, Locals=1, Args_size=1
   0:	aload_0
   1:	invokestatic	#700; //Method scala/collection/TraversableLike$class.nonEmpty:(Lscala/collection/TraversableLike;)Z
   4:	ireturn
  LineNumberTable: 
   line 32: 0


public java.lang.Object repr();
  Code:
   Stack=1, Locals=1, Args_size=1
   0:	aload_0
   1:	invokestatic	#703; //Method scala/collection/TraversableLike$class.repr:(Lscala/collection/TraversableLike;)Ljava/lang/Object;
   4:	areturn
  LineNumberTable: 
   line 32: 0


public scala.collection.Traversable transpose(scala.Function1);
  Code:
   Stack=2, Locals=2, Args_size=2
   0:	aload_0
   1:	aload_1
   2:	invokestatic	#708; //Method scala/collection/generic/GenericTraversableTemplate$class.transpose:(Lscala/collection/generic/GenericTraversableTemplate;Lscala/Function1;)Lscala/collection/Traversable;
   5:	areturn
  LineNumberTable: 
   line 32: 0

  LocalVariableTable: 
   Start  Length  Slot  Name   Signature
   0      6      0    this       Lscala/collection/mutable/StringBuilder;
   0      6      1    asTraversable       Lscala/Function1;


public scala.collection.Traversable flatten(scala.Function1);
  Code:
   Stack=2, Locals=2, Args_size=2
   0:	aload_0
   1:	aload_1
   2:	invokestatic	#712; //Method scala/collection/generic/GenericTraversableTemplate$class.flatten:(Lscala/collection/generic/GenericTraversableTemplate;Lscala/Function1;)Lscala/collection/Traversable;
   5:	areturn
  LineNumberTable: 
   line 32: 0

  LocalVariableTable: 
   Start  Length  Slot  Name   Signature
   0      6      0    this       Lscala/collection/mutable/StringBuilder;
   0      6      1    asTraversable       Lscala/Function1;


public scala.Tuple2 unzip(scala.Function1);
  Code:
   Stack=2, Locals=2, Args_size=2
   0:	aload_0
   1:	aload_1
   2:	invokestatic	#716; //Method scala/collection/generic/GenericTraversableTemplate$class.unzip:(Lscala/collection/generic/GenericTraversableTemplate;Lscala/Function1;)Lscala/Tuple2;
   5:	areturn
  LineNumberTable: 
   line 32: 0

  LocalVariableTable: 
   Start  Length  Slot  Name   Signature
   0      6      0    this       Lscala/collection/mutable/StringBuilder;
   0      6      1    asPair       Lscala/Function1;


public scala.collection.mutable.Builder genericBuilder();
  Code:
   Stack=1, Locals=1, Args_size=1
   0:	aload_0
   1:	invokestatic	#722; //Method scala/collection/generic/GenericTraversableTemplate$class.genericBuilder:(Lscala/collection/generic/GenericTraversableTemplate;)Lscala/collection/mutable/Builder;
   4:	areturn
  LineNumberTable: 
   line 32: 0


public scala.collection.mutable.Builder newBuilder();
  Code:
   Stack=1, Locals=1, Args_size=1
   0:	aload_0
   1:	invokestatic	#725; //Method scala/collection/generic/GenericTraversableTemplate$class.newBuilder:(Lscala/collection/generic/GenericTraversableTemplate;)Lscala/collection/mutable/Builder;
   4:	areturn
  LineNumberTable: 
   line 32: 0


public scala.Option firstOption();
  Code:
   Stack=1, Locals=1, Args_size=1
   0:	aload_0
   1:	invokestatic	#729; //Method scala/collection/IterableLike$class.firstOption:(Lscala/collection/IterableLike;)Lscala/Option;
   4:	areturn
  LineNumberTable: 
   line 32: 0

  Deprecated: true

public java.lang.Object first();
  Code:
   Stack=1, Locals=1, Args_size=1
   0:	aload_0
   1:	invokestatic	#733; //Method scala/collection/IterableLike$class.first:(Lscala/collection/IterableLike;)Ljava/lang/Object;
   4:	areturn
  LineNumberTable: 
   line 32: 0

  Deprecated: true

public boolean canEqual(java.lang.Object);
  Code:
   Stack=2, Locals=2, Args_size=2
   0:	aload_0
   1:	aload_1
   2:	invokestatic	#737; //Method scala/collection/IterableLike$class.canEqual:(Lscala/collection/IterableLike;Ljava/lang/Object;)Z
   5:	ireturn
  LineNumberTable: 
   line 32: 0

  LocalVariableTable: 
   Start  Length  Slot  Name   Signature
   0      6      0    this       Lscala/collection/mutable/StringBuilder;
   0      6      1    that       Ljava/lang/Object;


public scala.collection.immutable.Stream toStream();
  Code:
   Stack=1, Locals=1, Args_size=1
   0:	aload_0
   1:	invokestatic	#742; //Method scala/collection/IterableLike$class.toStream:(Lscala/collection/IterableLike;)Lscala/collection/immutable/Stream;
   4:	areturn
  LineNumberTable: 
   line 32: 0


public java.lang.Object zipAll(scala.collection.Iterable, java.lang.Object, java.lang.Object, scala.collection.generic.CanBuildFrom);
  Code:
   Stack=5, Locals=5, Args_size=5
   0:	aload_0
   1:	aload_1
   2:	aload_2
   3:	aload_3
   4:	aload	4
   6:	invokestatic	#747; //Method scala/collection/IterableLike$class.zipAll:(Lscala/collection/IterableLike;Lscala/collection/Iterable;Ljava/lang/Object;Ljava/lang/Object;Lscala/collection/generic/CanBuildFrom;)Ljava/lang/Object;
   9:	areturn
  LineNumberTable: 
   line 32: 0

  LocalVariableTable: 
   Start  Length  Slot  Name   Signature
   0      10      0    this       Lscala/collection/mutable/StringBuilder;
   0      10      1    that       Lscala/collection/Iterable;
   0      10      2    thisElem       Ljava/lang/Object;
   0      10      3    thatElem       Ljava/lang/Object;
   0      10      4    bf       Lscala/collection/generic/CanBuildFrom;


public scala.collection.Iterable toIterable();
  Code:
   Stack=1, Locals=1, Args_size=1
   0:	aload_0
   1:	invokestatic	#754; //Method scala/collection/IterableLike$class.toIterable:(Lscala/collection/IterableLike;)Lscala/collection/Iterable;
   4:	areturn
  LineNumberTable: 
   line 32: 0


public scala.collection.Iterator elements();
  Code:
   Stack=1, Locals=1, Args_size=1
   0:	aload_0
   1:	invokestatic	#759; //Method scala/collection/IterableLike$class.elements:(Lscala/collection/IterableLike;)Lscala/collection/Iterator;
   4:	areturn
  LineNumberTable: 
   line 32: 0

  Deprecated: true

public scala.Function1 compose(scala.Function1);
  Code:
   Stack=2, Locals=2, Args_size=2
   0:	aload_0
   1:	aload_1
   2:	invokestatic	#763; //Method scala/Function1$class.compose:(Lscala/Function1;Lscala/Function1;)Lscala/Function1;
   5:	areturn
  LineNumberTable: 
   line 32: 0

  LocalVariableTable: 
   Start  Length  Slot  Name   Signature
   0      6      0    this       Lscala/collection/mutable/StringBuilder;
   0      6      1    g       Lscala/Function1;


public scala.Function1 lift();
  Code:
   Stack=1, Locals=1, Args_size=1
   0:	aload_0
   1:	invokestatic	#768; //Method scala/PartialFunction$class.lift:(Lscala/PartialFunction;)Lscala/Function1;
   4:	areturn
  LineNumberTable: 
   line 32: 0


public scala.PartialFunction andThen(scala.Function1);
  Code:
   Stack=2, Locals=2, Args_size=2
   0:	aload_0
   1:	aload_1
   2:	invokestatic	#771; //Method scala/PartialFunction$class.andThen:(Lscala/PartialFunction;Lscala/Function1;)Lscala/PartialFunction;
   5:	areturn
  LineNumberTable: 
   line 32: 0

  LocalVariableTable: 
   Start  Length  Slot  Name   Signature
   0      6      0    this       Lscala/collection/mutable/StringBuilder;
   0      6      1    k       Lscala/Function1;


public scala.PartialFunction orElse(scala.PartialFunction);
  Code:
   Stack=2, Locals=2, Args_size=2
   0:	aload_0
   1:	aload_1
   2:	invokestatic	#777; //Method scala/PartialFunction$class.orElse:(Lscala/PartialFunction;Lscala/PartialFunction;)Lscala/PartialFunction;
   5:	areturn
  LineNumberTable: 
   line 32: 0

  LocalVariableTable: 
   Start  Length  Slot  Name   Signature
   0      6      0    this       Lscala/collection/mutable/StringBuilder;
   0      6      1    that       Lscala/PartialFunction;


public java.lang.Object projection();
  Code:
   Stack=1, Locals=1, Args_size=1
   0:	aload_0
   1:	invokestatic	#781; //Method scala/collection/SeqLike$class.projection:(Lscala/collection/SeqLike;)Ljava/lang/Object;
   4:	areturn
  LineNumberTable: 
   line 32: 0

  Deprecated: true

public boolean equalsWith(scala.collection.Seq, scala.Function2);
  Code:
   Stack=3, Locals=3, Args_size=3
   0:	aload_0
   1:	aload_1
   2:	aload_2
   3:	invokestatic	#786; //Method scala/collection/SeqLike$class.equalsWith:(Lscala/collection/SeqLike;Lscala/collection/Seq;Lscala/Function2;)Z
   6:	ireturn
  LineNumberTable: 
   line 32: 0

  LocalVariableTable: 
   Start  Length  Slot  Name   Signature
   0      7      0    this       Lscala/collection/mutable/StringBuilder;
   0      7      1    that       Lscala/collection/Seq;
   0      7      2    f       Lscala/Function2;

  Deprecated: true

public int findLastIndexOf(scala.Function1);
  Code:
   Stack=2, Locals=2, Args_size=2
   0:	aload_0
   1:	aload_1
   2:	invokestatic	#790; //Method scala/collection/SeqLike$class.findLastIndexOf:(Lscala/collection/SeqLike;Lscala/Function1;)I
   5:	ireturn
  LineNumberTable: 
   line 32: 0

  LocalVariableTable: 
   Start  Length  Slot  Name   Signature
   0      6      0    this       Lscala/collection/mutable/StringBuilder;
   0      6      1    p       Lscala/Function1;


public boolean equals(java.lang.Object);
  Code:
   Stack=2, Locals=2, Args_size=2
   0:	aload_0
   1:	aload_1
   2:	invokestatic	#440; //Method scala/collection/SeqLike$class.equals:(Lscala/collection/SeqLike;Ljava/lang/Object;)Z
   5:	ireturn
  LineNumberTable: 
   line 32: 0

  LocalVariableTable: 
   Start  Length  Slot  Name   Signature
   0      6      0    this       Lscala/collection/mutable/StringBuilder;
   0      6      1    that       Ljava/lang/Object;


public int hashCode();
  Code:
   Stack=1, Locals=1, Args_size=1
   0:	aload_0
   1:	invokestatic	#794; //Method scala/collection/SeqLike$class.hashCode:(Lscala/collection/SeqLike;)I
   4:	ireturn
  LineNumberTable: 
   line 32: 0


public scala.collection.immutable.Range indices();
  Code:
   Stack=1, Locals=1, Args_size=1
   0:	aload_0
   1:	invokestatic	#799; //Method scala/collection/SeqLike$class.indices:(Lscala/collection/SeqLike;)Lscala/collection/immutable/Range;
   4:	areturn
  LineNumberTable: 
   line 32: 0


public scala.collection.Seq toSeq();
  Code:
   Stack=1, Locals=1, Args_size=1
   0:	aload_0
   1:	invokestatic	#803; //Method scala/collection/SeqLike$class.toSeq:(Lscala/collection/SeqLike;)Lscala/collection/Seq;
   4:	areturn
  LineNumberTable: 
   line 32: 0


public java.lang.Object sortBy(scala.Function1, scala.math.Ordering);
  Code:
   Stack=3, Locals=3, Args_size=3
   0:	aload_0
   1:	aload_1
   2:	aload_2
   3:	invokestatic	#808; //Method scala/collection/SeqLike$class.sortBy:(Lscala/collection/SeqLike;Lscala/Function1;Lscala/math/Ordering;)Ljava/lang/Object;
   6:	areturn
  LineNumberTable: 
   line 32: 0

  LocalVariableTable: 
   Start  Length  Slot  Name   Signature
   0      7      0    this       Lscala/collection/mutable/StringBuilder;
   0      7      1    f       Lscala/Function1;
   0      7      2    ord       Lscala/math/Ordering;


public java.lang.Object sortWith(scala.math.Ordering);
  Code:
   Stack=2, Locals=2, Args_size=2
   0:	aload_0
   1:	aload_1
   2:	invokestatic	#813; //Method scala/collection/SeqLike$class.sortWith:(Lscala/collection/SeqLike;Lscala/math/Ordering;)Ljava/lang/Object;
   5:	areturn
  LineNumberTable: 
   line 32: 0

  LocalVariableTable: 
   Start  Length  Slot  Name   Signature
   0      6      0    this       Lscala/collection/mutable/StringBuilder;
   0      6      1    ord       Lscala/math/Ordering;


public java.lang.Object sortWith(scala.Function2);
  Code:
   Stack=2, Locals=2, Args_size=2
   0:	aload_0
   1:	aload_1
   2:	invokestatic	#817; //Method scala/collection/SeqLike$class.sortWith:(Lscala/collection/SeqLike;Lscala/Function2;)Ljava/lang/Object;
   5:	areturn
  LineNumberTable: 
   line 32: 0

  LocalVariableTable: 
   Start  Length  Slot  Name   Signature
   0      6      0    this       Lscala/collection/mutable/StringBuilder;
   0      6      1    lt       Lscala/Function2;


public boolean corresponds(scala.collection.Seq, scala.Function2);
  Code:
   Stack=3, Locals=3, Args_size=3
   0:	aload_0
   1:	aload_1
   2:	aload_2
   3:	invokestatic	#821; //Method scala/collection/SeqLike$class.corresponds:(Lscala/collection/SeqLike;Lscala/collection/Seq;Lscala/Function2;)Z
   6:	ireturn
  LineNumberTable: 
   line 32: 0

  LocalVariableTable: 
   Start  Length  Slot  Name   Signature
   0      7      0    this       Lscala/collection/mutable/StringBuilder;
   0      7      1    that       Lscala/collection/Seq;
   0      7      2    p       Lscala/Function2;


public java.lang.Object padTo(int, java.lang.Object, scala.collection.generic.CanBuildFrom);
  Code:
   Stack=4, Locals=4, Args_size=4
   0:	aload_0
   1:	iload_1
   2:	aload_2
   3:	aload_3
   4:	invokestatic	#826; //Method scala/collection/SeqLike$class.padTo:(Lscala/collection/SeqLike;ILjava/lang/Object;Lscala/collection/generic/CanBuildFrom;)Ljava/lang/Object;
   7:	areturn
  LineNumberTable: 
   line 32: 0

  LocalVariableTable: 
   Start  Length  Slot  Name   Signature
   0      8      0    this       Lscala/collection/mutable/StringBuilder;
   0      8      1    len       I
   0      8      2    elem       Ljava/lang/Object;
   0      8      3    bf       Lscala/collection/generic/CanBuildFrom;


public java.lang.Object $colon$plus(java.lang.Object, scala.collection.generic.CanBuildFrom);
  Code:
   Stack=3, Locals=3, Args_size=3
   0:	aload_0
   1:	aload_1
   2:	aload_2
   3:	invokestatic	#831; //Method scala/collection/SeqLike$class.$colon$plus:(Lscala/collection/SeqLike;Ljava/lang/Object;Lscala/collection/generic/CanBuildFrom;)Ljava/lang/Object;
   6:	areturn
  LineNumberTable: 
   line 32: 0

  LocalVariableTable: 
   Start  Length  Slot  Name   Signature
   0      7      0    this       Lscala/collection/mutable/StringBuilder;
   0      7      1    elem       Ljava/lang/Object;
   0      7      2    bf       Lscala/collection/generic/CanBuildFrom;


public java.lang.Object $plus$colon(java.lang.Object, scala.collection.generic.CanBuildFrom);
  Code:
   Stack=3, Locals=3, Args_size=3
   0:	aload_0
   1:	aload_1
   2:	aload_2
   3:	invokestatic	#834; //Method scala/collection/SeqLike$class.$plus$colon:(Lscala/collection/SeqLike;Ljava/lang/Object;Lscala/collection/generic/CanBuildFrom;)Ljava/lang/Object;
   6:	areturn
  LineNumberTable: 
   line 32: 0

  LocalVariableTable: 
   Start  Length  Slot  Name   Signature
   0      7      0    this       Lscala/collection/mutable/StringBuilder;
   0      7      1    elem       Ljava/lang/Object;
   0      7      2    bf       Lscala/collection/generic/CanBuildFrom;


public java.lang.Object updated(int, java.lang.Object, scala.collection.generic.CanBuildFrom);
  Code:
   Stack=4, Locals=4, Args_size=4
   0:	aload_0
   1:	iload_1
   2:	aload_2
   3:	aload_3
   4:	invokestatic	#837; //Method scala/collection/SeqLike$class.updated:(Lscala/collection/SeqLike;ILjava/lang/Object;Lscala/collection/generic/CanBuildFrom;)Ljava/lang/Object;
   7:	areturn
  LineNumberTable: 
   line 32: 0

  LocalVariableTable: 
   Start  Length  Slot  Name   Signature
   0      8      0    this       Lscala/collection/mutable/StringBuilder;
   0      8      1    index       I
   0      8      2    elem       Ljava/lang/Object;
   0      8      3    bf       Lscala/collection/generic/CanBuildFrom;


public java.lang.Object patch(int, scala.collection.Seq, int, scala.collection.generic.CanBuildFrom);
  Code:
   Stack=5, Locals=5, Args_size=5
   0:	aload_0
   1:	iload_1
   2:	aload_2
   3:	iload_3
   4:	aload	4
   6:	invokestatic	#842; //Method scala/collection/SeqLike$class.patch:(Lscala/collection/SeqLike;ILscala/collection/Seq;ILscala/collection/generic/CanBuildFrom;)Ljava/lang/Object;
   9:	areturn
  LineNumberTable: 
   line 32: 0

  LocalVariableTable: 
   Start  Length  Slot  Name   Signature
   0      10      0    this       Lscala/collection/mutable/StringBuilder;
   0      10      1    from       I
   0      10      2    patch       Lscala/collection/Seq;
   0      10      3    replaced       I
   0      10      4    bf       Lscala/collection/generic/CanBuildFrom;


public java.lang.Object removeDuplicates();
  Code:
   Stack=1, Locals=1, Args_size=1
   0:	aload_0
   1:	invokestatic	#846; //Method scala/collection/SeqLike$class.removeDuplicates:(Lscala/collection/SeqLike;)Ljava/lang/Object;
   4:	areturn
  LineNumberTable: 
   line 32: 0


public java.lang.Object intersect(scala.collection.Seq);
  Code:
   Stack=2, Locals=2, Args_size=2
   0:	aload_0
   1:	aload_1
   2:	invokestatic	#851; //Method scala/collection/SeqLike$class.intersect:(Lscala/collection/SeqLike;Lscala/collection/Seq;)Ljava/lang/Object;
   5:	areturn
  LineNumberTable: 
   line 32: 0

  LocalVariableTable: 
   Start  Length  Slot  Name   Signature
   0      6      0    this       Lscala/collection/mutable/StringBuilder;
   0      6      1    that       Lscala/collection/Seq;


public java.lang.Object diff(scala.collection.Seq);
  Code:
   Stack=2, Locals=2, Args_size=2
   0:	aload_0
   1:	aload_1
   2:	invokestatic	#854; //Method scala/collection/SeqLike$class.diff:(Lscala/collection/SeqLike;Lscala/collection/Seq;)Ljava/lang/Object;
   5:	areturn
  LineNumberTable: 
   line 32: 0

  LocalVariableTable: 
   Start  Length  Slot  Name   Signature
   0      6      0    this       Lscala/collection/mutable/StringBuilder;
   0      6      1    that       Lscala/collection/Seq;


public java.lang.Object union(scala.collection.Seq, scala.collection.generic.CanBuildFrom);
  Code:
   Stack=3, Locals=3, Args_size=3
   0:	aload_0
   1:	aload_1
   2:	aload_2
   3:	invokestatic	#859; //Method scala/collection/SeqLike$class.union:(Lscala/collection/SeqLike;Lscala/collection/Seq;Lscala/collection/generic/CanBuildFrom;)Ljava/lang/Object;
   6:	areturn
  LineNumberTable: 
   line 32: 0

  LocalVariableTable: 
   Start  Length  Slot  Name   Signature
   0      7      0    this       Lscala/collection/mutable/StringBuilder;
   0      7      1    that       Lscala/collection/Seq;
   0      7      2    bf       Lscala/collection/generic/CanBuildFrom;


public boolean contains(java.lang.Object);
  Code:
   Stack=2, Locals=2, Args_size=2
   0:	aload_0
   1:	aload_1
   2:	invokestatic	#862; //Method scala/collection/SeqLike$class.contains:(Lscala/collection/SeqLike;Ljava/lang/Object;)Z
   5:	ireturn
  LineNumberTable: 
   line 32: 0

  LocalVariableTable: 
   Start  Length  Slot  Name   Signature
   0      6      0    this       Lscala/collection/mutable/StringBuilder;
   0      6      1    elem       Ljava/lang/Object;


public boolean containsSlice(scala.collection.Seq);
  Code:
   Stack=2, Locals=2, Args_size=2
   0:	aload_0
   1:	aload_1
   2:	invokestatic	#867; //Method scala/collection/SeqLike$class.containsSlice:(Lscala/collection/SeqLike;Lscala/collection/Seq;)Z
   5:	ireturn
  LineNumberTable: 
   line 32: 0

  LocalVariableTable: 
   Start  Length  Slot  Name   Signature
   0      6      0    this       Lscala/collection/mutable/StringBuilder;
   0      6      1    that       Lscala/collection/Seq;


public int lastIndexOfSlice(scala.collection.Seq, int);
  Code:
   Stack=3, Locals=3, Args_size=3
   0:	aload_0
   1:	aload_1
   2:	iload_2
   3:	invokestatic	#870; //Method scala/collection/SeqLike$class.lastIndexOfSlice:(Lscala/collection/SeqLike;Lscala/collection/Seq;I)I
   6:	ireturn
  LineNumberTable: 
   line 32: 0

  LocalVariableTable: 
   Start  Length  Slot  Name   Signature
   0      7      0    this       Lscala/collection/mutable/StringBuilder;
   0      7      1    that       Lscala/collection/Seq;
   0      7      2    end       I


public int lastIndexOfSlice(scala.collection.Seq);
  Code:
   Stack=2, Locals=2, Args_size=2
   0:	aload_0
   1:	aload_1
   2:	invokestatic	#874; //Method scala/collection/SeqLike$class.lastIndexOfSlice:(Lscala/collection/SeqLike;Lscala/collection/Seq;)I
   5:	ireturn
  LineNumberTable: 
   line 32: 0

  LocalVariableTable: 
   Start  Length  Slot  Name   Signature
   0      6      0    this       Lscala/collection/mutable/StringBuilder;
   0      6      1    that       Lscala/collection/Seq;


public int indexOfSlice(scala.collection.Seq, int);
  Code:
   Stack=3, Locals=3, Args_size=3
   0:	aload_0
   1:	aload_1
   2:	iload_2
   3:	invokestatic	#876; //Method scala/collection/SeqLike$class.indexOfSlice:(Lscala/collection/SeqLike;Lscala/collection/Seq;I)I
   6:	ireturn
  LineNumberTable: 
   line 32: 0

  LocalVariableTable: 
   Start  Length  Slot  Name   Signature
   0      7      0    this       Lscala/collection/mutable/StringBuilder;
   0      7      1    that       Lscala/collection/Seq;
   0      7      2    from       I


public int indexOfSlice(scala.collection.Seq);
  Code:
   Stack=2, Locals=2, Args_size=2
   0:	aload_0
   1:	aload_1
   2:	invokestatic	#878; //Method scala/collection/SeqLike$class.indexOfSlice:(Lscala/collection/SeqLike;Lscala/collection/Seq;)I
   5:	ireturn
  LineNumberTable: 
   line 32: 0

  LocalVariableTable: 
   Start  Length  Slot  Name   Signature
   0      6      0    this       Lscala/collection/mutable/StringBuilder;
   0      6      1    that       Lscala/collection/Seq;


public boolean startsWith(scala.collection.Seq);
  Code:
   Stack=2, Locals=2, Args_size=2
   0:	aload_0
   1:	aload_1
   2:	invokestatic	#881; //Method scala/collection/SeqLike$class.startsWith:(Lscala/collection/SeqLike;Lscala/collection/Seq;)Z
   5:	ireturn
  LineNumberTable: 
   line 32: 0

  LocalVariableTable: 
   Start  Length  Slot  Name   Signature
   0      6      0    this       Lscala/collection/mutable/StringBuilder;
   0      6      1    that       Lscala/collection/Seq;


public scala.collection.Iterator reversedElements();
  Code:
   Stack=1, Locals=1, Args_size=1
   0:	aload_0
   1:	invokestatic	#885; //Method scala/collection/SeqLike$class.reversedElements:(Lscala/collection/SeqLike;)Lscala/collection/Iterator;
   4:	areturn
  LineNumberTable: 
   line 32: 0

  Deprecated: true

public java.lang.Object reverseMap(scala.Function1, scala.collection.generic.CanBuildFrom);
  Code:
   Stack=3, Locals=3, Args_size=3
   0:	aload_0
   1:	aload_1
   2:	aload_2
   3:	invokestatic	#889; //Method scala/collection/SeqLike$class.reverseMap:(Lscala/collection/SeqLike;Lscala/Function1;Lscala/collection/generic/CanBuildFrom;)Ljava/lang/Object;
   6:	areturn
  LineNumberTable: 
   line 32: 0

  LocalVariableTable: 
   Start  Length  Slot  Name   Signature
   0      7      0    this       Lscala/collection/mutable/StringBuilder;
   0      7      1    f       Lscala/Function1;
   0      7      2    bf       Lscala/collection/generic/CanBuildFrom;


public int lastIndexWhere(scala.Function1);
  Code:
   Stack=2, Locals=2, Args_size=2
   0:	aload_0
   1:	aload_1
   2:	invokestatic	#892; //Method scala/collection/SeqLike$class.lastIndexWhere:(Lscala/collection/SeqLike;Lscala/Function1;)I
   5:	ireturn
  LineNumberTable: 
   line 32: 0

  LocalVariableTable: 
   Start  Length  Slot  Name   Signature
   0      6      0    this       Lscala/collection/mutable/StringBuilder;
   0      6      1    p       Lscala/Function1;


public int lastIndexOf(java.lang.Object, int);
  Code:
   Stack=3, Locals=3, Args_size=3
   0:	aload_0
   1:	aload_1
   2:	iload_2
   3:	invokestatic	#896; //Method scala/collection/SeqLike$class.lastIndexOf:(Lscala/collection/SeqLike;Ljava/lang/Object;I)I
   6:	ireturn
  LineNumberTable: 
   line 32: 0

  LocalVariableTable: 
   Start  Length  Slot  Name   Signature
   0      7      0    this       Lscala/collection/mutable/StringBuilder;
   0      7      1    elem       Ljava/lang/Object;
   0      7      2    end       I


public int lastIndexOf(java.lang.Object);
  Code:
   Stack=2, Locals=2, Args_size=2
   0:	aload_0
   1:	aload_1
   2:	invokestatic	#899; //Method scala/collection/SeqLike$class.lastIndexOf:(Lscala/collection/SeqLike;Ljava/lang/Object;)I
   5:	ireturn
  LineNumberTable: 
   line 32: 0

  LocalVariableTable: 
   Start  Length  Slot  Name   Signature
   0      6      0    this       Lscala/collection/mutable/StringBuilder;
   0      6      1    elem       Ljava/lang/Object;


public int indexOf(java.lang.Object, int);
  Code:
   Stack=3, Locals=3, Args_size=3
   0:	aload_0
   1:	aload_1
   2:	iload_2
   3:	invokestatic	#901; //Method scala/collection/SeqLike$class.indexOf:(Lscala/collection/SeqLike;Ljava/lang/Object;I)I
   6:	ireturn
  LineNumberTable: 
   line 32: 0

  LocalVariableTable: 
   Start  Length  Slot  Name   Signature
   0      7      0    this       Lscala/collection/mutable/StringBuilder;
   0      7      1    elem       Ljava/lang/Object;
   0      7      2    from       I


public int indexOf(java.lang.Object);
  Code:
   Stack=2, Locals=2, Args_size=2
   0:	aload_0
   1:	aload_1
   2:	invokestatic	#903; //Method scala/collection/SeqLike$class.indexOf:(Lscala/collection/SeqLike;Ljava/lang/Object;)I
   5:	ireturn
  LineNumberTable: 
   line 32: 0

  LocalVariableTable: 
   Start  Length  Slot  Name   Signature
   0      6      0    this       Lscala/collection/mutable/StringBuilder;
   0      6      1    elem       Ljava/lang/Object;


public int findIndexOf(scala.Function1);
  Code:
   Stack=2, Locals=2, Args_size=2
   0:	aload_0
   1:	aload_1
   2:	invokestatic	#906; //Method scala/collection/SeqLike$class.findIndexOf:(Lscala/collection/SeqLike;Lscala/Function1;)I
   5:	ireturn
  LineNumberTable: 
   line 32: 0

  LocalVariableTable: 
   Start  Length  Slot  Name   Signature
   0      6      0    this       Lscala/collection/mutable/StringBuilder;
   0      6      1    p       Lscala/Function1;


public int indexWhere(scala.Function1);
  Code:
   Stack=2, Locals=2, Args_size=2
   0:	aload_0
   1:	aload_1
   2:	invokestatic	#909; //Method scala/collection/SeqLike$class.indexWhere:(Lscala/collection/SeqLike;Lscala/Function1;)I
   5:	ireturn
  LineNumberTable: 
   line 32: 0

  LocalVariableTable: 
   Start  Length  Slot  Name   Signature
   0      6      0    this       Lscala/collection/mutable/StringBuilder;
   0      6      1    p       Lscala/Function1;


public int prefixLength(scala.Function1);
  Code:
   Stack=2, Locals=2, Args_size=2
   0:	aload_0
   1:	aload_1
   2:	invokestatic	#912; //Method scala/collection/SeqLike$class.prefixLength:(Lscala/collection/SeqLike;Lscala/Function1;)I
   5:	ireturn
  LineNumberTable: 
   line 32: 0

  LocalVariableTable: 
   Start  Length  Slot  Name   Signature
   0      6      0    this       Lscala/collection/mutable/StringBuilder;
   0      6      1    p       Lscala/Function1;


public boolean isDefinedAt(int);
  Code:
   Stack=2, Locals=2, Args_size=2
   0:	aload_0
   1:	iload_1
   2:	invokestatic	#915; //Method scala/collection/SeqLike$class.isDefinedAt:(Lscala/collection/SeqLike;I)Z
   5:	ireturn
  LineNumberTable: 
   line 32: 0

  LocalVariableTable: 
   Start  Length  Slot  Name   Signature
   0      6      0    this       Lscala/collection/mutable/StringBuilder;
   0      6      1    idx       I


public int size();
  Code:
   Stack=1, Locals=1, Args_size=1
   0:	aload_0
   1:	invokestatic	#917; //Method scala/collection/SeqLike$class.size:(Lscala/collection/SeqLike;)I
   4:	ireturn
  LineNumberTable: 
   line 32: 0


public boolean endsWith(scala.collection.Seq);
  Code:
   Stack=2, Locals=2, Args_size=2
   0:	aload_0
   1:	aload_1
   2:	invokestatic	#921; //Method scala/collection/IndexedSeqLike$class.endsWith:(Lscala/collection/IndexedSeqLike;Lscala/collection/Seq;)Z
   5:	ireturn
  LineNumberTable: 
   line 32: 0

  LocalVariableTable: 
   Start  Length  Slot  Name   Signature
   0      6      0    this       Lscala/collection/mutable/StringBuilder;
   0      6      1    that       Lscala/collection/Seq;


public boolean startsWith(scala.collection.Seq, int);
  Code:
   Stack=3, Locals=3, Args_size=3
   0:	aload_0
   1:	aload_1
   2:	iload_2
   3:	invokestatic	#925; //Method scala/collection/IndexedSeqLike$class.startsWith:(Lscala/collection/IndexedSeqLike;Lscala/collection/Seq;I)Z
   6:	ireturn
  LineNumberTable: 
   line 32: 0

  LocalVariableTable: 
   Start  Length  Slot  Name   Signature
   0      7      0    this       Lscala/collection/mutable/StringBuilder;
   0      7      1    that       Lscala/collection/Seq;
   0      7      2    offset       I


public scala.collection.Iterator reverseIterator();
  Code:
   Stack=1, Locals=1, Args_size=1
   0:	aload_0
   1:	invokestatic	#929; //Method scala/collection/IndexedSeqLike$class.reverseIterator:(Lscala/collection/IndexedSeqLike;)Lscala/collection/Iterator;
   4:	areturn
  LineNumberTable: 
   line 32: 0


public int lastIndexWhere(scala.Function1, int);
  Code:
   Stack=3, Locals=3, Args_size=3
   0:	aload_0
   1:	aload_1
   2:	iload_2
   3:	invokestatic	#933; //Method scala/collection/IndexedSeqLike$class.lastIndexWhere:(Lscala/collection/IndexedSeqLike;Lscala/Function1;I)I
   6:	ireturn
  LineNumberTable: 
   line 32: 0

  LocalVariableTable: 
   Start  Length  Slot  Name   Signature
   0      7      0    this       Lscala/collection/mutable/StringBuilder;
   0      7      1    p       Lscala/Function1;
   0      7      2    end       I


public int indexWhere(scala.Function1, int);
  Code:
   Stack=3, Locals=3, Args_size=3
   0:	aload_0
   1:	aload_1
   2:	iload_2
   3:	invokestatic	#935; //Method scala/collection/IndexedSeqLike$class.indexWhere:(Lscala/collection/IndexedSeqLike;Lscala/Function1;I)I
   6:	ireturn
  LineNumberTable: 
   line 32: 0

  LocalVariableTable: 
   Start  Length  Slot  Name   Signature
   0      7      0    this       Lscala/collection/mutable/StringBuilder;
   0      7      1    p       Lscala/Function1;
   0      7      2    from       I


public int segmentLength(scala.Function1, int);
  Code:
   Stack=3, Locals=3, Args_size=3
   0:	aload_0
   1:	aload_1
   2:	iload_2
   3:	invokestatic	#938; //Method scala/collection/IndexedSeqLike$class.segmentLength:(Lscala/collection/IndexedSeqLike;Lscala/Function1;I)I
   6:	ireturn
  LineNumberTable: 
   line 32: 0

  LocalVariableTable: 
   Start  Length  Slot  Name   Signature
   0      7      0    this       Lscala/collection/mutable/StringBuilder;
   0      7      1    p       Lscala/Function1;
   0      7      2    from       I


public int lengthCompare(int);
  Code:
   Stack=2, Locals=2, Args_size=2
   0:	aload_0
   1:	iload_1
   2:	invokestatic	#942; //Method scala/collection/IndexedSeqLike$class.lengthCompare:(Lscala/collection/IndexedSeqLike;I)I
   5:	ireturn
  LineNumberTable: 
   line 32: 0

  LocalVariableTable: 
   Start  Length  Slot  Name   Signature
   0      6      0    this       Lscala/collection/mutable/StringBuilder;
   0      6      1    len       I


public void copyToArray(java.lang.Object, int, int);
  Code:
   Stack=4, Locals=4, Args_size=4
   0:	aload_0
   1:	aload_1
   2:	iload_2
   3:	iload_3
   4:	invokestatic	#946; //Method scala/collection/IndexedSeqLike$class.copyToArray:(Lscala/collection/IndexedSeqLike;Ljava/lang/Object;II)V
   7:	return
  LineNumberTable: 
   line 32: 0

  LocalVariableTable: 
   Start  Length  Slot  Name   Signature
   0      8      0    this       Lscala/collection/mutable/StringBuilder;
   0      8      1    xs       Ljava/lang/Object;
   0      8      2    start       I
   0      8      3    len       I


public boolean sameElements(scala.collection.Iterable);
  Code:
   Stack=2, Locals=2, Args_size=2
   0:	aload_0
   1:	aload_1
   2:	invokestatic	#951; //Method scala/collection/IndexedSeqLike$class.sameElements:(Lscala/collection/IndexedSeqLike;Lscala/collection/Iterable;)Z
   5:	ireturn
  LineNumberTable: 
   line 32: 0

  LocalVariableTable: 
   Start  Length  Slot  Name   Signature
   0      6      0    this       Lscala/collection/mutable/StringBuilder;
   0      6      1    that       Lscala/collection/Iterable;


public scala.Tuple2 span(scala.Function1);
  Code:
   Stack=2, Locals=2, Args_size=2
   0:	aload_0
   1:	aload_1
   2:	invokestatic	#955; //Method scala/collection/IndexedSeqLike$class.span:(Lscala/collection/IndexedSeqLike;Lscala/Function1;)Lscala/Tuple2;
   5:	areturn
  LineNumberTable: 
   line 32: 0

  LocalVariableTable: 
   Start  Length  Slot  Name   Signature
   0      6      0    this       Lscala/collection/mutable/StringBuilder;
   0      6      1    p       Lscala/Function1;


public java.lang.Object dropWhile(scala.Function1);
  Code:
   Stack=2, Locals=2, Args_size=2
   0:	aload_0
   1:	aload_1
   2:	invokestatic	#959; //Method scala/collection/IndexedSeqLike$class.dropWhile:(Lscala/collection/IndexedSeqLike;Lscala/Function1;)Ljava/lang/Object;
   5:	areturn
  LineNumberTable: 
   line 32: 0

  LocalVariableTable: 
   Start  Length  Slot  Name   Signature
   0      6      0    this       Lscala/collection/mutable/StringBuilder;
   0      6      1    p       Lscala/Function1;


public java.lang.Object takeWhile(scala.Function1);
  Code:
   Stack=2, Locals=2, Args_size=2
   0:	aload_0
   1:	aload_1
   2:	invokestatic	#962; //Method scala/collection/IndexedSeqLike$class.takeWhile:(Lscala/collection/IndexedSeqLike;Lscala/Function1;)Ljava/lang/Object;
   5:	areturn
  LineNumberTable: 
   line 32: 0

  LocalVariableTable: 
   Start  Length  Slot  Name   Signature
   0      6      0    this       Lscala/collection/mutable/StringBuilder;
   0      6      1    p       Lscala/Function1;


public scala.Tuple2 splitAt(int);
  Code:
   Stack=2, Locals=2, Args_size=2
   0:	aload_0
   1:	iload_1
   2:	invokestatic	#967; //Method scala/collection/IndexedSeqLike$class.splitAt:(Lscala/collection/IndexedSeqLike;I)Lscala/Tuple2;
   5:	areturn
  LineNumberTable: 
   line 32: 0

  LocalVariableTable: 
   Start  Length  Slot  Name   Signature
   0      6      0    this       Lscala/collection/mutable/StringBuilder;
   0      6      1    n       I


public java.lang.Object dropRight(int);
  Code:
   Stack=2, Locals=2, Args_size=2
   0:	aload_0
   1:	iload_1
   2:	invokestatic	#971; //Method scala/collection/IndexedSeqLike$class.dropRight:(Lscala/collection/IndexedSeqLike;I)Ljava/lang/Object;
   5:	areturn
  LineNumberTable: 
   line 32: 0

  LocalVariableTable: 
   Start  Length  Slot  Name   Signature
   0      6      0    this       Lscala/collection/mutable/StringBuilder;
   0      6      1    n       I


public java.lang.Object takeRight(int);
  Code:
   Stack=2, Locals=2, Args_size=2
   0:	aload_0
   1:	iload_1
   2:	invokestatic	#974; //Method scala/collection/IndexedSeqLike$class.takeRight:(Lscala/collection/IndexedSeqLike;I)Ljava/lang/Object;
   5:	areturn
  LineNumberTable: 
   line 32: 0

  LocalVariableTable: 
   Start  Length  Slot  Name   Signature
   0      6      0    this       Lscala/collection/mutable/StringBuilder;
   0      6      1    n       I


public java.lang.Object drop(int);
  Code:
   Stack=2, Locals=2, Args_size=2
   0:	aload_0
   1:	iload_1
   2:	invokestatic	#977; //Method scala/collection/IndexedSeqLike$class.drop:(Lscala/collection/IndexedSeqLike;I)Ljava/lang/Object;
   5:	areturn
  LineNumberTable: 
   line 32: 0

  LocalVariableTable: 
   Start  Length  Slot  Name   Signature
   0      6      0    this       Lscala/collection/mutable/StringBuilder;
   0      6      1    n       I


public java.lang.Object take(int);
  Code:
   Stack=2, Locals=2, Args_size=2
   0:	aload_0
   1:	iload_1
   2:	invokestatic	#980; //Method scala/collection/IndexedSeqLike$class.take:(Lscala/collection/IndexedSeqLike;I)Ljava/lang/Object;
   5:	areturn
  LineNumberTable: 
   line 32: 0

  LocalVariableTable: 
   Start  Length  Slot  Name   Signature
   0      6      0    this       Lscala/collection/mutable/StringBuilder;
   0      6      1    n       I


public java.lang.Object init();
  Code:
   Stack=1, Locals=1, Args_size=1
   0:	aload_0
   1:	invokestatic	#984; //Method scala/collection/IndexedSeqLike$class.init:(Lscala/collection/IndexedSeqLike;)Ljava/lang/Object;
   4:	areturn
  LineNumberTable: 
   line 32: 0


public java.lang.Object last();
  Code:
   Stack=1, Locals=1, Args_size=1
   0:	aload_0
   1:	invokestatic	#987; //Method scala/collection/IndexedSeqLike$class.last:(Lscala/collection/IndexedSeqLike;)Ljava/lang/Object;
   4:	areturn
  LineNumberTable: 
   line 32: 0


public java.lang.Object tail();
  Code:
   Stack=1, Locals=1, Args_size=1
   0:	aload_0
   1:	invokestatic	#990; //Method scala/collection/IndexedSeqLike$class.tail:(Lscala/collection/IndexedSeqLike;)Ljava/lang/Object;
   4:	areturn
  LineNumberTable: 
   line 32: 0


public java.lang.Object head();
  Code:
   Stack=1, Locals=1, Args_size=1
   0:	aload_0
   1:	invokestatic	#993; //Method scala/collection/IndexedSeqLike$class.head:(Lscala/collection/IndexedSeqLike;)Ljava/lang/Object;
   4:	areturn
  LineNumberTable: 
   line 32: 0


public java.lang.Object slice(int, int);
  Code:
   Stack=3, Locals=3, Args_size=3
   0:	aload_0
   1:	iload_1
   2:	iload_2
   3:	invokestatic	#998; //Method scala/collection/IndexedSeqLike$class.slice:(Lscala/collection/IndexedSeqLike;II)Ljava/lang/Object;
   6:	areturn
  LineNumberTable: 
   line 32: 0

  LocalVariableTable: 
   Start  Length  Slot  Name   Signature
   0      7      0    this       Lscala/collection/mutable/StringBuilder;
   0      7      1    from       I
   0      7      2    until       I


public java.lang.Object zipWithIndex(scala.collection.generic.CanBuildFrom);
  Code:
   Stack=2, Locals=2, Args_size=2
   0:	aload_0
   1:	aload_1
   2:	invokestatic	#1003; //Method scala/collection/IndexedSeqLike$class.zipWithIndex:(Lscala/collection/IndexedSeqLike;Lscala/collection/generic/CanBuildFrom;)Ljava/lang/Object;
   5:	areturn
  LineNumberTable: 
   line 32: 0

  LocalVariableTable: 
   Start  Length  Slot  Name   Signature
   0      6      0    this       Lscala/collection/mutable/StringBuilder;
   0      6      1    bf       Lscala/collection/generic/CanBuildFrom;


public java.lang.Object zip(scala.collection.Iterable, scala.collection.generic.CanBuildFrom);
  Code:
   Stack=3, Locals=3, Args_size=3
   0:	aload_0
   1:	aload_1
   2:	aload_2
   3:	invokestatic	#1008; //Method scala/collection/IndexedSeqLike$class.zip:(Lscala/collection/IndexedSeqLike;Lscala/collection/Iterable;Lscala/collection/generic/CanBuildFrom;)Ljava/lang/Object;
   6:	areturn
  LineNumberTable: 
   line 32: 0

  LocalVariableTable: 
   Start  Length  Slot  Name   Signature
   0      7      0    this       Lscala/collection/mutable/StringBuilder;
   0      7      1    that       Lscala/collection/Iterable;
   0      7      2    bf       Lscala/collection/generic/CanBuildFrom;


public java.lang.Object reduceRight(scala.Function2);
  Code:
   Stack=2, Locals=2, Args_size=2
   0:	aload_0
   1:	aload_1
   2:	invokestatic	#1012; //Method scala/collection/IndexedSeqLike$class.reduceRight:(Lscala/collection/IndexedSeqLike;Lscala/Function2;)Ljava/lang/Object;
   5:	areturn
  LineNumberTable: 
   line 32: 0

  LocalVariableTable: 
   Start  Length  Slot  Name   Signature
   0      6      0    this       Lscala/collection/mutable/StringBuilder;
   0      6      1    op       Lscala/Function2;


public java.lang.Object reduceLeft(scala.Function2);
  Code:
   Stack=2, Locals=2, Args_size=2
   0:	aload_0
   1:	aload_1
   2:	invokestatic	#1015; //Method scala/collection/IndexedSeqLike$class.reduceLeft:(Lscala/collection/IndexedSeqLike;Lscala/Function2;)Ljava/lang/Object;
   5:	areturn
  LineNumberTable: 
   line 32: 0

  LocalVariableTable: 
   Start  Length  Slot  Name   Signature
   0      6      0    this       Lscala/collection/mutable/StringBuilder;
   0      6      1    op       Lscala/Function2;


public java.lang.Object foldRight(java.lang.Object, scala.Function2);
  Code:
   Stack=3, Locals=3, Args_size=3
   0:	aload_0
   1:	aload_1
   2:	aload_2
   3:	invokestatic	#1019; //Method scala/collection/IndexedSeqLike$class.foldRight:(Lscala/collection/IndexedSeqLike;Ljava/lang/Object;Lscala/Function2;)Ljava/lang/Object;
   6:	areturn
  LineNumberTable: 
   line 32: 0

  LocalVariableTable: 
   Start  Length  Slot  Name   Signature
   0      7      0    this       Lscala/collection/mutable/StringBuilder;
   0      7      1    z       Ljava/lang/Object;
   0      7      2    op       Lscala/Function2;


public java.lang.Object foldLeft(java.lang.Object, scala.Function2);
  Code:
   Stack=3, Locals=3, Args_size=3
   0:	aload_0
   1:	aload_1
   2:	aload_2
   3:	invokestatic	#1022; //Method scala/collection/IndexedSeqLike$class.foldLeft:(Lscala/collection/IndexedSeqLike;Ljava/lang/Object;Lscala/Function2;)Ljava/lang/Object;
   6:	areturn
  LineNumberTable: 
   line 32: 0

  LocalVariableTable: 
   Start  Length  Slot  Name   Signature
   0      7      0    this       Lscala/collection/mutable/StringBuilder;
   0      7      1    z       Ljava/lang/Object;
   0      7      2    op       Lscala/Function2;


public scala.Option find(scala.Function1);
  Code:
   Stack=2, Locals=2, Args_size=2
   0:	aload_0
   1:	aload_1
   2:	invokestatic	#1027; //Method scala/collection/IndexedSeqLike$class.find:(Lscala/collection/IndexedSeqLike;Lscala/Function1;)Lscala/Option;
   5:	areturn
  LineNumberTable: 
   line 32: 0

  LocalVariableTable: 
   Start  Length  Slot  Name   Signature
   0      6      0    this       Lscala/collection/mutable/StringBuilder;
   0      6      1    p       Lscala/Function1;


public boolean exists(scala.Function1);
  Code:
   Stack=2, Locals=2, Args_size=2
   0:	aload_0
   1:	aload_1
   2:	invokestatic	#1032; //Method scala/collection/IndexedSeqLike$class.exists:(Lscala/collection/IndexedSeqLike;Lscala/Function1;)Z
   5:	ireturn
  LineNumberTable: 
   line 32: 0

  LocalVariableTable: 
   Start  Length  Slot  Name   Signature
   0      6      0    this       Lscala/collection/mutable/StringBuilder;
   0      6      1    p       Lscala/Function1;


public boolean forall(scala.Function1);
  Code:
   Stack=2, Locals=2, Args_size=2
   0:	aload_0
   1:	aload_1
   2:	invokestatic	#1035; //Method scala/collection/IndexedSeqLike$class.forall:(Lscala/collection/IndexedSeqLike;Lscala/Function1;)Z
   5:	ireturn
  LineNumberTable: 
   line 32: 0

  LocalVariableTable: 
   Start  Length  Slot  Name   Signature
   0      6      0    this       Lscala/collection/mutable/StringBuilder;
   0      6      1    p       Lscala/Function1;


public void foreach(scala.Function1);
  Code:
   Stack=2, Locals=2, Args_size=2
   0:	aload_0
   1:	aload_1
   2:	invokestatic	#1039; //Method scala/collection/IndexedSeqLike$class.foreach:(Lscala/collection/IndexedSeqLike;Lscala/Function1;)V
   5:	return
  LineNumberTable: 
   line 32: 0

  LocalVariableTable: 
   Start  Length  Slot  Name   Signature
   0      6      0    this       Lscala/collection/mutable/StringBuilder;
   0      6      1    f       Lscala/Function1;


public boolean isEmpty();
  Code:
   Stack=1, Locals=1, Args_size=1
   0:	aload_0
   1:	invokestatic	#1043; //Method scala/collection/IndexedSeqLike$class.isEmpty:(Lscala/collection/IndexedSeqLike;)Z
   4:	ireturn
  LineNumberTable: 
   line 32: 0


public scala.collection.Iterator iterator();
  Code:
   Stack=1, Locals=1, Args_size=1
   0:	aload_0
   1:	invokestatic	#1046; //Method scala/collection/IndexedSeqLike$class.iterator:(Lscala/collection/IndexedSeqLike;)Lscala/collection/Iterator;
   4:	areturn
  LineNumberTable: 
   line 32: 0


public final boolean scala$collection$IndexedSeqLike$$super$endsWith(scala.collection.Seq);
  Code:
   Stack=2, Locals=2, Args_size=2
   0:	aload_0
   1:	aload_1
   2:	invokestatic	#1049; //Method scala/collection/SeqLike$class.endsWith:(Lscala/collection/SeqLike;Lscala/collection/Seq;)Z
   5:	ireturn
  LineNumberTable: 
   line 32: 0

  LocalVariableTable: 
   Start  Length  Slot  Name   Signature
   0      6      0    this       Lscala/collection/mutable/StringBuilder;
   0      6      1    that       Lscala/collection/Seq;


public final boolean scala$collection$IndexedSeqLike$$super$sameElements(scala.collection.Iterable);
  Code:
   Stack=2, Locals=2, Args_size=2
   0:	aload_0
   1:	aload_1
   2:	invokestatic	#1053; //Method scala/collection/IterableLike$class.sameElements:(Lscala/collection/IterableLike;Lscala/collection/Iterable;)Z
   5:	ireturn
  LineNumberTable: 
   line 32: 0

  LocalVariableTable: 
   Start  Length  Slot  Name   Signature
   0      6      0    this       Lscala/collection/mutable/StringBuilder;
   0      6      1    that       Lscala/collection/Iterable;


public final java.lang.Object scala$collection$IndexedSeqLike$$super$init();
  Code:
   Stack=1, Locals=1, Args_size=1
   0:	aload_0
   1:	invokestatic	#1056; //Method scala/collection/TraversableLike$class.init:(Lscala/collection/TraversableLike;)Ljava/lang/Object;
   4:	areturn
  LineNumberTable: 
   line 32: 0


public final java.lang.Object scala$collection$IndexedSeqLike$$super$last();
  Code:
   Stack=1, Locals=1, Args_size=1
   0:	aload_0
   1:	invokestatic	#1059; //Method scala/collection/TraversableLike$class.last:(Lscala/collection/TraversableLike;)Ljava/lang/Object;
   4:	areturn
  LineNumberTable: 
   line 32: 0


public final java.lang.Object scala$collection$IndexedSeqLike$$super$tail();
  Code:
   Stack=1, Locals=1, Args_size=1
   0:	aload_0
   1:	invokestatic	#1062; //Method scala/collection/TraversableLike$class.tail:(Lscala/collection/TraversableLike;)Ljava/lang/Object;
   4:	areturn
  LineNumberTable: 
   line 32: 0


public final java.lang.Object scala$collection$IndexedSeqLike$$super$head();
  Code:
   Stack=1, Locals=1, Args_size=1
   0:	aload_0
   1:	invokestatic	#1065; //Method scala/collection/IterableLike$class.head:(Lscala/collection/IterableLike;)Ljava/lang/Object;
   4:	areturn
  LineNumberTable: 
   line 32: 0


public final java.lang.Object scala$collection$IndexedSeqLike$$super$zip(scala.collection.Iterable, scala.collection.generic.CanBuildFrom);
  Code:
   Stack=3, Locals=3, Args_size=3
   0:	aload_0
   1:	aload_1
   2:	aload_2
   3:	invokestatic	#1069; //Method scala/collection/IterableLike$class.zip:(Lscala/collection/IterableLike;Lscala/collection/Iterable;Lscala/collection/generic/CanBuildFrom;)Ljava/lang/Object;
   6:	areturn
  LineNumberTable: 
   line 32: 0

  LocalVariableTable: 
   Start  Length  Slot  Name   Signature
   0      7      0    this       Lscala/collection/mutable/StringBuilder;
   0      7      1    that       Lscala/collection/Iterable;
   0      7      2    bf       Lscala/collection/generic/CanBuildFrom;


public final java.lang.Object scala$collection$IndexedSeqLike$$super$reduceRight(scala.Function2);
  Code:
   Stack=2, Locals=2, Args_size=2
   0:	aload_0
   1:	aload_1
   2:	invokestatic	#1073; //Method scala/collection/IterableLike$class.reduceRight:(Lscala/collection/IterableLike;Lscala/Function2;)Ljava/lang/Object;
   5:	areturn
  LineNumberTable: 
   line 32: 0

  LocalVariableTable: 
   Start  Length  Slot  Name   Signature
   0      6      0    this       Lscala/collection/mutable/StringBuilder;
   0      6      1    op       Lscala/Function2;


public final java.lang.Object scala$collection$IndexedSeqLike$$super$reduceLeft(scala.Function2);
  Code:
   Stack=2, Locals=2, Args_size=2
   0:	aload_0
   1:	aload_1
   2:	invokestatic	#1077; //Method scala/collection/TraversableLike$class.reduceLeft:(Lscala/collection/TraversableLike;Lscala/Function2;)Ljava/lang/Object;
   5:	areturn
  LineNumberTable: 
   line 32: 0

  LocalVariableTable: 
   Start  Length  Slot  Name   Signature
   0      6      0    this       Lscala/collection/mutable/StringBuilder;
   0      6      1    op       Lscala/Function2;


public scala.collection.mutable.IndexedSeqView view(int, int);
  Code:
   Stack=3, Locals=3, Args_size=3
   0:	aload_0
   1:	iload_1
   2:	iload_2
   3:	invokestatic	#1080; //Method scala/collection/mutable/IndexedSeqLike$class.view:(Lscala/collection/mutable/IndexedSeqLike;II)Lscala/collection/mutable/IndexedSeqView;
   6:	areturn
  LineNumberTable: 
   line 32: 0

  LocalVariableTable: 
   Start  Length  Slot  Name   Signature
   0      7      0    this       Lscala/collection/mutable/StringBuilder;
   0      7      1    from       I
   0      7      2    until       I


public java.lang.Object view();
  Code:
   Stack=1, Locals=1, Args_size=1
   0:	aload_0
   1:	invokestatic	#1083; //Method scala/collection/mutable/IndexedSeqLike$class.view:(Lscala/collection/mutable/IndexedSeqLike;)Ljava/lang/Object;
   4:	areturn
  LineNumberTable: 
   line 32: 0


public scala.collection.mutable.IndexedSeq toCollection(java.lang.Object);
  Code:
   Stack=2, Locals=2, Args_size=2
   0:	aload_0
   1:	aload_1
   2:	invokestatic	#1086; //Method scala/collection/mutable/IndexedSeqLike$class.toCollection:(Lscala/collection/mutable/IndexedSeqLike;Ljava/lang/Object;)Lscala/collection/mutable/IndexedSeq;
   5:	areturn
  LineNumberTable: 
   line 32: 0

  LocalVariableTable: 
   Start  Length  Slot  Name   Signature
   0      6      0    this       Lscala/collection/mutable/StringBuilder;
   0      6      1    repr       Ljava/lang/Object;


public scala.collection.mutable.IndexedSeq thisCollection();
  Code:
   Stack=1, Locals=1, Args_size=1
   0:	aload_0
   1:	invokestatic	#1089; //Method scala/collection/mutable/IndexedSeqLike$class.thisCollection:(Lscala/collection/mutable/IndexedSeqLike;)Lscala/collection/mutable/IndexedSeq;
   4:	areturn
  LineNumberTable: 
   line 32: 0


public scala.collection.generic.GenericCompanion companion();
  Code:
   Stack=1, Locals=1, Args_size=1
   0:	aload_0
   1:	invokestatic	#1094; //Method scala/collection/mutable/IndexedSeq$class.companion:(Lscala/collection/mutable/IndexedSeq;)Lscala/collection/generic/GenericCompanion;
   4:	areturn
  LineNumberTable: 
   line 32: 0


}

