Compiled from "StringBuilder.scala"
public final class scala.collection.mutable.StringBuilder$ extends java.lang.Object implements scala.ScalaObject
  SourceFile: "StringBuilder.scala"
  Scala: length = 0x
   
  InnerClass: 
   public final $anonfun$setLength$1=class scala/collection/mutable/StringBuilder$$anonfun$setLength$1 of class scala/collection/mutable/StringBuilder
  minor version: 0
  major version: 49
  Constant pool:
Asciz	SourceFile;
Asciz	StringBuilder.scala;
Asciz	Scala;
Asciz	MODULE$;
Asciz	Lscala/collection/mutable/StringBuilder$;;
Asciz	<clinit>;
Asciz	()V;
Asciz	Code;
Asciz	scala/collection/mutable/StringBuilder$;
class	scala/collection/mutable/StringBuilder$
Asciz	<init>;
NameAndType	"<init>":()V
Method	scala/collection/mutable/StringBuilder$."<init>":()V
Asciz	copyOf;
Asciz	([CI)[C;
Asciz	LineNumberTable;
Asciz	scala/compat/Platform$;
class	scala/compat/Platform$
Asciz	Lscala/compat/Platform$;;
NameAndType	MODULE$:Lscala/compat/Platform$;
Field	scala/compat/Platform$.MODULE$:Lscala/compat/Platform$;
Asciz	scala/Predef$;
class	scala/Predef$
Asciz	Lscala/Predef$;;
NameAndType	MODULE$:Lscala/Predef$;
Field	scala/Predef$.MODULE$:Lscala/Predef$;
Asciz	intWrapper;
Asciz	(I)Lscala/runtime/RichInt;;
NameAndType	intWrapper:(I)Lscala/runtime/RichInt;
Method	scala/Predef$.intWrapper:(I)Lscala/runtime/RichInt;
Asciz	scala/runtime/RichInt;
class	scala/runtime/RichInt
Asciz	min;
Asciz	(I)I;
NameAndType	min:(I)I
Method	scala/runtime/RichInt.min:(I)I
Asciz	arraycopy;
Asciz	(Ljava/lang/Object;ILjava/lang/Object;II)V;
NameAndType	arraycopy:(Ljava/lang/Object;ILjava/lang/Object;II)V
Method	scala/compat/Platform$.arraycopy:(Ljava/lang/Object;ILjava/lang/Object;II)V
Asciz	this;
Asciz	src;
Asciz	[C;
Asciz	newLength;
Asciz	I;
Asciz	dest;
Asciz	LocalVariableTable;
Asciz	java/lang/Object;
class	java/lang/Object
Method	java/lang/Object."<init>":()V
NameAndType	MODULE$:Lscala/collection/mutable/StringBuilder$;
Field	scala/collection/mutable/StringBuilder$.MODULE$:Lscala/collection/mutable/StringBuilder$;
Asciz	InnerClasses;
Asciz	scala/collection/mutable/StringBuilder$$anonfun$setLength$1;
class	scala/collection/mutable/StringBuilder$$anonfun$setLength$1
Asciz	scala/collection/mutable/StringBuilder;
class	scala/collection/mutable/StringBuilder
Asciz	$anonfun$setLength$1;
Asciz	scala/ScalaObject;
class	scala/ScalaObject

{
public static final scala.collection.mutable.StringBuilder$ MODULE$;
  Signature: Lscala/collection/mutable/StringBuilder$;

public static {};
  Signature: ()V
  Code:
   Stack=1, Locals=0, Args_size=0
	new	class scala/collection/mutable/StringBuilder$
	invokespecial	Method "<init>":()V
	return
  Labels:

private char[] copyOf(char[], int);
  Signature: ([CI)[C
  Code:
   Stack=7, Locals=4, Args_size=3
	iload_2
	newarray char
	astore_3
	getstatic	Field scala/compat/Platform$.MODULE$:Lscala/compat/Platform$;
	aload_1
	iconst_0
	aload_3
	iconst_0
	getstatic	Field scala/Predef$.MODULE$:Lscala/Predef$;
	aload_1
	arraylength
	invokevirtual	Method scala/Predef$.intWrapper:(I)Lscala/runtime/RichInt;
	iload_2
	invokevirtual	Method scala/runtime/RichInt.min:(I)I
	invokevirtual	Method scala/compat/Platform$.arraycopy:(Ljava/lang/Object;ILjava/lang/Object;II)V
	aload_3
	areturn
  Labels:
  LocalVariableTable: 
   Start  Length  Slot  Name   Signature
   0      28      0    this       Lscala/collection/mutable/StringBuilder$;
   0      28      1    src       [C
   0      28      2    newLength       I
   4      23      3    dest       [C


private scala.collection.mutable.StringBuilder$();
  Signature: ()V
  Code:
   Stack=1, Locals=1, Args_size=1
	aload_0
	invokespecial	Method java/lang/Object."<init>":()V
	aload_0
	putstatic	Field MODULE$:Lscala/collection/mutable/StringBuilder$;
	return
  Labels:

}

