Compiled from "StringBuilder.scala"
public final class scala.collection.mutable.StringBuilder$$anonfun$setLength$1 extends java.lang.Object implements scala.Function0,scala.ScalaObject,java.io.Serializable
  SourceFile: "StringBuilder.scala"
  Scala: length = 0x
   
  InnerClass: 
   public final #49= #10 of #48; //$anonfun$setLength$1=class scala/collection/mutable/StringBuilder$$anonfun$setLength$1 of class scala/collection/mutable/StringBuilder
  minor version: 0
  major version: 49
  Constant pool:
const #1 = Asciz	SourceFile;
const #2 = Asciz	StringBuilder.scala;
const #3 = Asciz	n$1;
const #4 = Asciz	I;
const #5 = Asciz	<init>;
const #6 = Asciz	(Lscala/collection/mutable/StringBuilder;I)V;
const #7 = Asciz	Code;
const #8 = Asciz	LineNumberTable;
const #9 = Asciz	scala/collection/mutable/StringBuilder$$anonfun$setLength$1;
const #10 = class	#9;	//  scala/collection/mutable/StringBuilder$$anonfun$setLength$1
const #11 = NameAndType	#3:#4;//  n$1:I
const #12 = Field	#10.#11;	//  scala/collection/mutable/StringBuilder$$anonfun$setLength$1.n$1:I
const #13 = Asciz	java/lang/Object;
const #14 = class	#13;	//  java/lang/Object
const #15 = Asciz	()V;
const #16 = NameAndType	#5:#15;//  "<init>":()V
const #17 = Method	#14.#16;	//  java/lang/Object."<init>":()V
const #18 = Asciz	scala/Function0$class;
const #19 = class	#18;	//  scala/Function0$class
const #20 = Asciz	$init$;
const #21 = Asciz	(Lscala/Function0;)V;
const #22 = NameAndType	#20:#21;//  $init$:(Lscala/Function0;)V
const #23 = Method	#19.#22;	//  scala/Function0$class.$init$:(Lscala/Function0;)V
const #24 = Asciz	this;
const #25 = Asciz	Lscala/collection/mutable/StringBuilder$$anonfun$setLength$1;;
const #26 = Asciz	$outer;
const #27 = Asciz	Lscala/collection/mutable/StringBuilder;;
const #28 = Asciz	LocalVariableTable;
const #29 = Asciz	apply;
const #30 = Asciz	()Ljava/lang/Object;;
const #31 = Asciz	()I;
const #32 = NameAndType	#29:#31;//  apply:()I
const #33 = Method	#10.#32;	//  scala/collection/mutable/StringBuilder$$anonfun$setLength$1.apply:()I
const #34 = Asciz	scala/runtime/BoxesRunTime;
const #35 = class	#34;	//  scala/runtime/BoxesRunTime
const #36 = Asciz	boxToInteger;
const #37 = Asciz	(I)Ljava/lang/Integer;;
const #38 = NameAndType	#36:#37;//  boxToInteger:(I)Ljava/lang/Integer;
const #39 = Method	#35.#38;	//  scala/runtime/BoxesRunTime.boxToInteger:(I)Ljava/lang/Integer;
const #40 = Asciz	toString;
const #41 = Asciz	()Ljava/lang/String;;
const #42 = Asciz	(Lscala/Function0;)Ljava/lang/String;;
const #43 = NameAndType	#40:#42;//  toString:(Lscala/Function0;)Ljava/lang/String;
const #44 = Method	#19.#43;	//  scala/Function0$class.toString:(Lscala/Function0;)Ljava/lang/String;
const #45 = Asciz	Scala;
const #46 = Asciz	InnerClasses;
const #47 = Asciz	scala/collection/mutable/StringBuilder;
const #48 = class	#47;	//  scala/collection/mutable/StringBuilder
const #49 = Asciz	$anonfun$setLength$1;
const #50 = Asciz	scala/Function0;
const #51 = class	#50;	//  scala/Function0
const #52 = Asciz	scala/ScalaObject;
const #53 = class	#52;	//  scala/ScalaObject
const #54 = Asciz	java/io/Serializable;
const #55 = class	#54;	//  java/io/Serializable

{
public scala.collection.mutable.StringBuilder$$anonfun$setLength$1(scala.collection.mutable.StringBuilder, int);
  Code:
   Stack=2, Locals=3, Args_size=3
   0:	aload_0
   1:	iload_2
   2:	putfield	#12; //Field n$1:I
   5:	aload_0
   6:	invokespecial	#17; //Method java/lang/Object."<init>":()V
   9:	aload_0
   10:	invokestatic	#23; //Method scala/Function0$class.$init$:(Lscala/Function0;)V
   13:	return
  LineNumberTable: 
   line 78: 0

  LocalVariableTable: 
   Start  Length  Slot  Name   Signature
   0      14      0    this       Lscala/collection/mutable/StringBuilder$$anonfun$setLength$1;
   0      14      1    $outer       Lscala/collection/mutable/StringBuilder;


public final java.lang.Object apply();
  Code:
   Stack=1, Locals=1, Args_size=1
   0:	aload_0
   1:	invokevirtual	#33; //Method apply:()I
   4:	invokestatic	#39; //Method scala/runtime/BoxesRunTime.boxToInteger:(I)Ljava/lang/Integer;
   7:	areturn
  LineNumberTable: 
   line 78: 0


public final int apply();
  Code:
   Stack=1, Locals=1, Args_size=1
   0:	aload_0
   1:	getfield	#12; //Field n$1:I
   4:	ireturn
  LineNumberTable: 
   line 78: 0


public java.lang.String toString();
  Code:
   Stack=1, Locals=1, Args_size=1
   0:	aload_0
   1:	invokestatic	#44; //Method scala/Function0$class.toString:(Lscala/Function0;)Ljava/lang/String;
   4:	areturn
  LineNumberTable: 
   line 78: 0


}

