Compiled from "StringBuilder.scala"
public final class scala.collection.mutable.StringBuilder$ extends java.lang.Object implements scala.ScalaObject
  SourceFile: "StringBuilder.scala"
  Scala: length = 0x
   
  InnerClass: 
   public final #88= #85 of #87; //$anonfun$setLength$1=class scala/collection/mutable/StringBuilder$$anonfun$setLength$1 of class scala/collection/mutable/StringBuilder
  minor version: 0
  major version: 49
  Constant pool:
const #1 = Asciz	SourceFile;
const #2 = Asciz	StringBuilder.scala;
const #3 = Asciz	Scala;
const #4 = Asciz	MODULE$;
const #5 = Asciz	Lscala/collection/mutable/StringBuilder$;;
const #6 = Asciz	<clinit>;
const #7 = Asciz	()V;
const #8 = Asciz	Code;
const #9 = Asciz	scala/collection/mutable/StringBuilder$;
const #10 = class	#9;	//  scala/collection/mutable/StringBuilder$
const #11 = Asciz	<init>;
const #12 = NameAndType	#11:#7;//  "<init>":()V
const #13 = Method	#10.#12;	//  scala/collection/mutable/StringBuilder$."<init>":()V
const #14 = Asciz	scala$collection$mutable$StringBuilder$$MAX_SURROGATE;
const #15 = Asciz	C;
const #16 = Asciz	scala$collection$mutable$StringBuilder$$MIN_SURROGATE;
const #17 = Asciz	MAX_LOW_SURROGATE;
const #18 = Asciz	MIN_LOW_SURROGATE;
const #19 = Asciz	MAX_HIGH_SURROGATE;
const #20 = Asciz	MIN_HIGH_SURROGATE;
const #21 = Asciz	LineNumberTable;
const #22 = Asciz	java/lang/Object;
const #23 = class	#22;	//  java/lang/Object
const #24 = Method	#23.#12;	//  java/lang/Object."<init>":()V
const #25 = NameAndType	#4:#5;//  MODULE$:Lscala/collection/mutable/StringBuilder$;
const #26 = Field	#10.#25;	//  scala/collection/mutable/StringBuilder$.MODULE$:Lscala/collection/mutable/StringBuilder$;
const #27 = int	55296;
const #28 = NameAndType	#20:#15;//  MIN_HIGH_SURROGATE:C
const #29 = Field	#10.#28;	//  scala/collection/mutable/StringBuilder$.MIN_HIGH_SURROGATE:C
const #30 = int	56319;
const #31 = NameAndType	#19:#15;//  MAX_HIGH_SURROGATE:C
const #32 = Field	#10.#31;	//  scala/collection/mutable/StringBuilder$.MAX_HIGH_SURROGATE:C
const #33 = int	56320;
const #34 = NameAndType	#18:#15;//  MIN_LOW_SURROGATE:C
const #35 = Field	#10.#34;	//  scala/collection/mutable/StringBuilder$.MIN_LOW_SURROGATE:C
const #36 = int	57343;
const #37 = NameAndType	#17:#15;//  MAX_LOW_SURROGATE:C
const #38 = Field	#10.#37;	//  scala/collection/mutable/StringBuilder$.MAX_LOW_SURROGATE:C
const #39 = Asciz	()C;
const #40 = NameAndType	#20:#39;//  MIN_HIGH_SURROGATE:()C
const #41 = Method	#10.#40;	//  scala/collection/mutable/StringBuilder$.MIN_HIGH_SURROGATE:()C
const #42 = NameAndType	#16:#15;//  scala$collection$mutable$StringBuilder$$MIN_SURROGATE:C
const #43 = Field	#10.#42;	//  scala/collection/mutable/StringBuilder$.scala$collection$mutable$StringBuilder$$MIN_SURROGATE:C
const #44 = NameAndType	#17:#39;//  MAX_LOW_SURROGATE:()C
const #45 = Method	#10.#44;	//  scala/collection/mutable/StringBuilder$.MAX_LOW_SURROGATE:()C
const #46 = NameAndType	#14:#15;//  scala$collection$mutable$StringBuilder$$MAX_SURROGATE:C
const #47 = Field	#10.#46;	//  scala/collection/mutable/StringBuilder$.scala$collection$mutable$StringBuilder$$MAX_SURROGATE:C
const #48 = Asciz	copyOf;
const #49 = Asciz	([CI)[C;
const #50 = Asciz	scala/compat/Platform$;
const #51 = class	#50;	//  scala/compat/Platform$
const #52 = Asciz	Lscala/compat/Platform$;;
const #53 = NameAndType	#4:#52;//  MODULE$:Lscala/compat/Platform$;
const #54 = Field	#51.#53;	//  scala/compat/Platform$.MODULE$:Lscala/compat/Platform$;
const #55 = Asciz	scala/Math$;
const #56 = class	#55;	//  scala/Math$
const #57 = Asciz	Lscala/Math$;;
const #58 = NameAndType	#4:#57;//  MODULE$:Lscala/Math$;
const #59 = Field	#56.#58;	//  scala/Math$.MODULE$:Lscala/Math$;
const #60 = Asciz	min;
const #61 = Asciz	(II)I;
const #62 = NameAndType	#60:#61;//  min:(II)I
const #63 = Method	#56.#62;	//  scala/Math$.min:(II)I
const #64 = Asciz	arraycopy;
const #65 = Asciz	(Ljava/lang/Object;ILjava/lang/Object;II)V;
const #66 = NameAndType	#64:#65;//  arraycopy:(Ljava/lang/Object;ILjava/lang/Object;II)V
const #67 = Method	#51.#66;	//  scala/compat/Platform$.arraycopy:(Ljava/lang/Object;ILjava/lang/Object;II)V
const #68 = Asciz	this;
const #69 = Asciz	src;
const #70 = Asciz	[C;
const #71 = Asciz	newLength;
const #72 = Asciz	I;
const #73 = Asciz	dest;
const #74 = Asciz	LocalVariableTable;
const #75 = Asciz	scala$collection$mutable$StringBuilder$$isHighSurrogate;
const #76 = Asciz	(C)Z;
const #77 = NameAndType	#19:#39;//  MAX_HIGH_SURROGATE:()C
const #78 = Method	#10.#77;	//  scala/collection/mutable/StringBuilder$.MAX_HIGH_SURROGATE:()C
const #79 = Asciz	ch;
const #80 = Asciz	scala$collection$mutable$StringBuilder$$isLowSurrogate;
const #81 = NameAndType	#18:#39;//  MIN_LOW_SURROGATE:()C
const #82 = Method	#10.#81;	//  scala/collection/mutable/StringBuilder$.MIN_LOW_SURROGATE:()C
const #83 = Asciz	InnerClasses;
const #84 = Asciz	scala/collection/mutable/StringBuilder$$anonfun$setLength$1;
const #85 = class	#84;	//  scala/collection/mutable/StringBuilder$$anonfun$setLength$1
const #86 = Asciz	scala/collection/mutable/StringBuilder;
const #87 = class	#86;	//  scala/collection/mutable/StringBuilder
const #88 = Asciz	$anonfun$setLength$1;
const #89 = Asciz	scala/ScalaObject;
const #90 = class	#89;	//  scala/ScalaObject

{
public static final scala.collection.mutable.StringBuilder$ MODULE$;

public static {};
  Code:
   Stack=1, Locals=0, Args_size=0
   0:	new	#10; //class scala/collection/mutable/StringBuilder$
   3:	invokespecial	#13; //Method "<init>":()V
   6:	return

public final boolean scala$collection$mutable$StringBuilder$$isHighSurrogate(char);
  Code:
   Stack=2, Locals=2, Args_size=2
   0:	aload_0
   1:	invokespecial	#41; //Method MIN_HIGH_SURROGATE:()C
   4:	iload_1
   5:	if_icmpgt	20
   8:	iload_1
   9:	aload_0
   10:	invokespecial	#78; //Method MAX_HIGH_SURROGATE:()C
   13:	if_icmpgt	20
   16:	iconst_1
   17:	goto	21
   20:	iconst_0
   21:	ireturn
  LineNumberTable: 
   line 865: 0

  LocalVariableTable: 
   Start  Length  Slot  Name   Signature
   0      22      0    this       Lscala/collection/mutable/StringBuilder$;
   0      22      1    ch       C


public final boolean scala$collection$mutable$StringBuilder$$isLowSurrogate(char);
  Code:
   Stack=2, Locals=2, Args_size=2
   0:	aload_0
   1:	invokespecial	#82; //Method MIN_LOW_SURROGATE:()C
   4:	iload_1
   5:	if_icmpgt	20
   8:	iload_1
   9:	aload_0
   10:	invokespecial	#45; //Method MAX_LOW_SURROGATE:()C
   13:	if_icmpgt	20
   16:	iconst_1
   17:	goto	21
   20:	iconst_0
   21:	ireturn
  LineNumberTable: 
   line 862: 0

  LocalVariableTable: 
   Start  Length  Slot  Name   Signature
   0      22      0    this       Lscala/collection/mutable/StringBuilder$;
   0      22      1    ch       C


public final char scala$collection$mutable$StringBuilder$$MAX_SURROGATE();
  Code:
   Stack=1, Locals=1, Args_size=1
   0:	aload_0
   1:	getfield	#47; //Field scala$collection$mutable$StringBuilder$$MAX_SURROGATE:C
   4:	ireturn
  LineNumberTable: 
   line 858: 0


public final char scala$collection$mutable$StringBuilder$$MIN_SURROGATE();
  Code:
   Stack=1, Locals=1, Args_size=1
   0:	aload_0
   1:	getfield	#43; //Field scala$collection$mutable$StringBuilder$$MIN_SURROGATE:C
   4:	ireturn
  LineNumberTable: 
   line 857: 0


}

