Compiled from "SynchronizedBuffer.scala"
public abstract class scala.collection.mutable.SynchronizedBuffer$class extends java.lang.Object
  SourceFile: "SynchronizedBuffer.scala"
  Scala: length = 0x
   
  minor version: 0
  major version: 49
  Constant pool:
const #1 = Asciz	SourceFile;
const #2 = Asciz	SynchronizedBuffer.scala;
const #3 = Asciz	$init$;
const #4 = Asciz	(Lscala/collection/mutable/SynchronizedBuffer;)V;
const #5 = Asciz	Code;
const #6 = Asciz	LineNumberTable;
const #7 = Asciz	$this;
const #8 = Asciz	Lscala/collection/mutable/SynchronizedBuffer;;
const #9 = Asciz	LocalVariableTable;
const #10 = Asciz	hashCode;
const #11 = Asciz	(Lscala/collection/mutable/SynchronizedBuffer;)I;
const #12 = Asciz	scala/collection/mutable/SynchronizedBuffer;
const #13 = class	#12;	//  scala/collection/mutable/SynchronizedBuffer
const #14 = Asciz	scala$collection$mutable$SynchronizedBuffer$$super$hashCode;
const #15 = Asciz	()I;
const #16 = NameAndType	#14:#15;//  scala$collection$mutable$SynchronizedBuffer$$super$hashCode:()I
const #17 = InterfaceMethod	#13.#16;	//  scala/collection/mutable/SynchronizedBuffer.scala$collection$mutable$SynchronizedBuffer$$super$hashCode:()I
const #18 = Asciz	java/lang/Throwable;
const #19 = class	#18;	//  java/lang/Throwable
const #20 = Asciz	clone;
const #21 = Asciz	(Lscala/collection/mutable/SynchronizedBuffer;)Lscala/collection/mutable/Buffer;;
const #22 = Asciz	scala$collection$mutable$SynchronizedBuffer$$super$clone;
const #23 = Asciz	()Lscala/collection/mutable/Buffer;;
const #24 = NameAndType	#22:#23;//  scala$collection$mutable$SynchronizedBuffer$$super$clone:()Lscala/collection/mutable/Buffer;
const #25 = InterfaceMethod	#13.#24;	//  scala/collection/mutable/SynchronizedBuffer.scala$collection$mutable$SynchronizedBuffer$$super$clone:()Lscala/collection/mutable/Buffer;
const #26 = Asciz	scala/collection/mutable/Buffer;
const #27 = class	#26;	//  scala/collection/mutable/Buffer
const #28 = Asciz	$less$less;
const #29 = Asciz	(Lscala/collection/mutable/SynchronizedBuffer;Lscala/collection/script/Message;)V;
const #30 = Asciz	scala$collection$mutable$SynchronizedBuffer$$super$$less$less;
const #31 = Asciz	(Lscala/collection/script/Message;)V;
const #32 = NameAndType	#30:#31;//  scala$collection$mutable$SynchronizedBuffer$$super$$less$less:(Lscala/collection/script/Message;)V
const #33 = InterfaceMethod	#13.#32;	//  scala/collection/mutable/SynchronizedBuffer.scala$collection$mutable$SynchronizedBuffer$$super$$less$less:(Lscala/collection/script/Message;)V
const #34 = Asciz	cmd;
const #35 = Asciz	Lscala/collection/script/Message;;
const #36 = Asciz	clear;
const #37 = Asciz	scala$collection$mutable$SynchronizedBuffer$$super$clear;
const #38 = Asciz	()V;
const #39 = NameAndType	#37:#38;//  scala$collection$mutable$SynchronizedBuffer$$super$clear:()V
const #40 = InterfaceMethod	#13.#39;	//  scala/collection/mutable/SynchronizedBuffer.scala$collection$mutable$SynchronizedBuffer$$super$clear:()V
const #41 = Asciz	remove;
const #42 = Asciz	(Lscala/collection/mutable/SynchronizedBuffer;I)Ljava/lang/Object;;
const #43 = Asciz	scala$collection$mutable$SynchronizedBuffer$$super$remove;
const #44 = Asciz	(I)Ljava/lang/Object;;
const #45 = NameAndType	#43:#44;//  scala$collection$mutable$SynchronizedBuffer$$super$remove:(I)Ljava/lang/Object;
const #46 = InterfaceMethod	#13.#45;	//  scala/collection/mutable/SynchronizedBuffer.scala$collection$mutable$SynchronizedBuffer$$super$remove:(I)Ljava/lang/Object;
const #47 = Asciz	n;
const #48 = Asciz	I;
const #49 = Asciz	update;
const #50 = Asciz	(Lscala/collection/mutable/SynchronizedBuffer;ILjava/lang/Object;)V;
const #51 = Asciz	scala$collection$mutable$SynchronizedBuffer$$super$update;
const #52 = Asciz	(ILjava/lang/Object;)V;
const #53 = NameAndType	#51:#52;//  scala$collection$mutable$SynchronizedBuffer$$super$update:(ILjava/lang/Object;)V
const #54 = InterfaceMethod	#13.#53;	//  scala/collection/mutable/SynchronizedBuffer.scala$collection$mutable$SynchronizedBuffer$$super$update:(ILjava/lang/Object;)V
const #55 = Asciz	newelem;
const #56 = Asciz	Ljava/lang/Object;;
const #57 = Asciz	insertAll;
const #58 = Asciz	(Lscala/collection/mutable/SynchronizedBuffer;ILscala/collection/Traversable;)V;
const #59 = Asciz	scala$collection$mutable$SynchronizedBuffer$$super$insertAll;
const #60 = Asciz	(ILscala/collection/Traversable;)V;
const #61 = NameAndType	#59:#60;//  scala$collection$mutable$SynchronizedBuffer$$super$insertAll:(ILscala/collection/Traversable;)V
const #62 = InterfaceMethod	#13.#61;	//  scala/collection/mutable/SynchronizedBuffer.scala$collection$mutable$SynchronizedBuffer$$super$insertAll:(ILscala/collection/Traversable;)V
const #63 = Asciz	iter;
const #64 = Asciz	Lscala/collection/Traversable;;
const #65 = Asciz	insert;
const #66 = Asciz	(Lscala/collection/mutable/SynchronizedBuffer;ILscala/collection/Seq;)V;
const #67 = Asciz	elems;
const #68 = Asciz	Lscala/collection/Seq;;
const #69 = Asciz	prependAll;
const #70 = Asciz	(Lscala/collection/mutable/SynchronizedBuffer;Lscala/collection/Traversable;)V;
const #71 = Asciz	scala$collection$mutable$SynchronizedBuffer$$super$prependAll;
const #72 = Asciz	(Lscala/collection/Traversable;)V;
const #73 = NameAndType	#71:#72;//  scala$collection$mutable$SynchronizedBuffer$$super$prependAll:(Lscala/collection/Traversable;)V
const #74 = InterfaceMethod	#13.#73;	//  scala/collection/mutable/SynchronizedBuffer.scala$collection$mutable$SynchronizedBuffer$$super$prependAll:(Lscala/collection/Traversable;)V
const #75 = Asciz	prepend;
const #76 = Asciz	(Lscala/collection/mutable/SynchronizedBuffer;Lscala/collection/Seq;)V;
const #77 = Asciz	$plus$plus$eq$colon;
const #78 = Asciz	(Lscala/collection/mutable/SynchronizedBuffer;Lscala/collection/Traversable;)Lscala/collection/mutable/SynchronizedBuffer;;
const #79 = Asciz	scala$collection$mutable$SynchronizedBuffer$$super$$plus$plus$eq$colon;
const #80 = Asciz	(Lscala/collection/Traversable;)Lscala/collection/mutable/SynchronizedBuffer;;
const #81 = NameAndType	#79:#80;//  scala$collection$mutable$SynchronizedBuffer$$super$$plus$plus$eq$colon:(Lscala/collection/Traversable;)Lscala/collection/mutable/SynchronizedBuffer;
const #82 = InterfaceMethod	#13.#81;	//  scala/collection/mutable/SynchronizedBuffer.scala$collection$mutable$SynchronizedBuffer$$super$$plus$plus$eq$colon:(Lscala/collection/Traversable;)Lscala/collection/mutable/SynchronizedBuffer;
const #83 = Asciz	$plus$eq$colon;
const #84 = Asciz	(Lscala/collection/mutable/SynchronizedBuffer;Ljava/lang/Object;)Lscala/collection/mutable/SynchronizedBuffer;;
const #85 = Asciz	scala$collection$mutable$SynchronizedBuffer$$super$$plus$eq$colon;
const #86 = Asciz	(Ljava/lang/Object;)Lscala/collection/mutable/SynchronizedBuffer;;
const #87 = NameAndType	#85:#86;//  scala$collection$mutable$SynchronizedBuffer$$super$$plus$eq$colon:(Ljava/lang/Object;)Lscala/collection/mutable/SynchronizedBuffer;
const #88 = InterfaceMethod	#13.#87;	//  scala/collection/mutable/SynchronizedBuffer.scala$collection$mutable$SynchronizedBuffer$$super$$plus$eq$colon:(Ljava/lang/Object;)Lscala/collection/mutable/SynchronizedBuffer;
const #89 = Asciz	elem;
const #90 = Asciz	appendAll;
const #91 = Asciz	scala$collection$mutable$SynchronizedBuffer$$super$appendAll;
const #92 = NameAndType	#91:#72;//  scala$collection$mutable$SynchronizedBuffer$$super$appendAll:(Lscala/collection/Traversable;)V
const #93 = InterfaceMethod	#13.#92;	//  scala/collection/mutable/SynchronizedBuffer.scala$collection$mutable$SynchronizedBuffer$$super$appendAll:(Lscala/collection/Traversable;)V
const #94 = Asciz	append;
const #95 = Asciz	scala$collection$mutable$SynchronizedBuffer$$super$$plus$plus$eq;
const #96 = NameAndType	#95:#80;//  scala$collection$mutable$SynchronizedBuffer$$super$$plus$plus$eq:(Lscala/collection/Traversable;)Lscala/collection/mutable/SynchronizedBuffer;
const #97 = InterfaceMethod	#13.#96;	//  scala/collection/mutable/SynchronizedBuffer.scala$collection$mutable$SynchronizedBuffer$$super$$plus$plus$eq:(Lscala/collection/Traversable;)Lscala/collection/mutable/SynchronizedBuffer;
const #98 = Asciz	$plus$plus$eq;
const #99 = Asciz	$plus$plus;
const #100 = Asciz	(Lscala/collection/mutable/SynchronizedBuffer;Lscala/collection/Traversable;)Lscala/collection/mutable/Buffer;;
const #101 = Asciz	scala$collection$mutable$SynchronizedBuffer$$super$$plus$plus;
const #102 = Asciz	(Lscala/collection/Traversable;)Lscala/collection/mutable/Buffer;;
const #103 = NameAndType	#101:#102;//  scala$collection$mutable$SynchronizedBuffer$$super$$plus$plus:(Lscala/collection/Traversable;)Lscala/collection/mutable/Buffer;
const #104 = InterfaceMethod	#13.#103;	//  scala/collection/mutable/SynchronizedBuffer.scala$collection$mutable$SynchronizedBuffer$$super$$plus$plus:(Lscala/collection/Traversable;)Lscala/collection/mutable/Buffer;
const #105 = Asciz	$plus$eq;
const #106 = Asciz	scala$collection$mutable$SynchronizedBuffer$$super$$plus$eq;
const #107 = NameAndType	#106:#86;//  scala$collection$mutable$SynchronizedBuffer$$super$$plus$eq:(Ljava/lang/Object;)Lscala/collection/mutable/SynchronizedBuffer;
const #108 = InterfaceMethod	#13.#107;	//  scala/collection/mutable/SynchronizedBuffer.scala$collection$mutable$SynchronizedBuffer$$super$$plus$eq:(Ljava/lang/Object;)Lscala/collection/mutable/SynchronizedBuffer;
const #109 = Asciz	$plus;
const #110 = Asciz	(Lscala/collection/mutable/SynchronizedBuffer;Ljava/lang/Object;)Lscala/collection/mutable/Buffer;;
const #111 = Asciz	scala$collection$mutable$SynchronizedBuffer$$super$$plus;
const #112 = Asciz	(Ljava/lang/Object;)Lscala/collection/mutable/Buffer;;
const #113 = NameAndType	#111:#112;//  scala$collection$mutable$SynchronizedBuffer$$super$$plus:(Ljava/lang/Object;)Lscala/collection/mutable/Buffer;
const #114 = InterfaceMethod	#13.#113;	//  scala/collection/mutable/SynchronizedBuffer.scala$collection$mutable$SynchronizedBuffer$$super$$plus:(Ljava/lang/Object;)Lscala/collection/mutable/Buffer;
const #115 = Asciz	apply;
const #116 = Asciz	scala$collection$mutable$SynchronizedBuffer$$super$apply;
const #117 = NameAndType	#116:#44;//  scala$collection$mutable$SynchronizedBuffer$$super$apply:(I)Ljava/lang/Object;
const #118 = InterfaceMethod	#13.#117;	//  scala/collection/mutable/SynchronizedBuffer.scala$collection$mutable$SynchronizedBuffer$$super$apply:(I)Ljava/lang/Object;
const #119 = Asciz	iterator;
const #120 = Asciz	(Lscala/collection/mutable/SynchronizedBuffer;)Lscala/collection/Iterator;;
const #121 = Asciz	scala$collection$mutable$SynchronizedBuffer$$super$iterator;
const #122 = Asciz	()Lscala/collection/Iterator;;
const #123 = NameAndType	#121:#122;//  scala$collection$mutable$SynchronizedBuffer$$super$iterator:()Lscala/collection/Iterator;
const #124 = InterfaceMethod	#13.#123;	//  scala/collection/mutable/SynchronizedBuffer.scala$collection$mutable$SynchronizedBuffer$$super$iterator:()Lscala/collection/Iterator;
const #125 = Asciz	scala/collection/Iterator;
const #126 = class	#125;	//  scala/collection/Iterator
const #127 = Asciz	length;
const #128 = Asciz	scala$collection$mutable$SynchronizedBuffer$$super$length;
const #129 = NameAndType	#128:#15;//  scala$collection$mutable$SynchronizedBuffer$$super$length:()I
const #130 = InterfaceMethod	#13.#129;	//  scala/collection/mutable/SynchronizedBuffer.scala$collection$mutable$SynchronizedBuffer$$super$length:()I
const #131 = Asciz	Scala;
const #132 = Asciz	scala/collection/mutable/SynchronizedBuffer$class;
const #133 = class	#132;	//  scala/collection/mutable/SynchronizedBuffer$class
const #134 = Asciz	java/lang/Object;
const #135 = class	#134;	//  java/lang/Object

{
public static void $init$(scala.collection.mutable.SynchronizedBuffer);
  Code:
   Stack=0, Locals=1, Args_size=1
   0:	return
  LineNumberTable: 
   line 24: 0

  LocalVariableTable: 
   Start  Length  Slot  Name   Signature
   0      1      0    $this       Lscala/collection/mutable/SynchronizedBuffer;


public static int hashCode(scala.collection.mutable.SynchronizedBuffer);
  Code:
   Stack=2, Locals=2, Args_size=1
   0:	aload_0
   1:	dup
   2:	pop
   3:	monitorenter
   4:	aload_0
   5:	invokeinterface	#17,  1; //InterfaceMethod scala/collection/mutable/SynchronizedBuffer.scala$collection$mutable$SynchronizedBuffer$$super$hashCode:()I
   10:	istore_1
   11:	aload_0
   12:	monitorexit
   13:	iload_1
   14:	ireturn
   15:	aload_0
   16:	monitorexit
   17:	athrow
  Exception table:
   from   to  target type
     4    13    15   Class java/lang/Throwable

  LineNumberTable: 
   line 193: 0
   line 194: 4
   line 193: 12

  LocalVariableTable: 
   Start  Length  Slot  Name   Signature
   0      18      0    $this       Lscala/collection/mutable/SynchronizedBuffer;


public static scala.collection.mutable.Buffer clone(scala.collection.mutable.SynchronizedBuffer);
  Code:
   Stack=2, Locals=1, Args_size=1
   0:	aload_0
   1:	dup
   2:	pop
   3:	monitorenter
   4:	aload_0
   5:	invokeinterface	#25,  1; //InterfaceMethod scala/collection/mutable/SynchronizedBuffer.scala$collection$mutable$SynchronizedBuffer$$super$clone:()Lscala/collection/mutable/Buffer;
   10:	aload_0
   11:	monitorexit
   12:	checkcast	#27; //class scala/collection/mutable/Buffer
   15:	areturn
   16:	aload_0
   17:	monitorexit
   18:	athrow
  Exception table:
   from   to  target type
     4    12    16   Class java/lang/Throwable

  LineNumberTable: 
   line 184: 0
   line 185: 4
   line 184: 11

  LocalVariableTable: 
   Start  Length  Slot  Name   Signature
   0      19      0    $this       Lscala/collection/mutable/SynchronizedBuffer;


public static void $less$less(scala.collection.mutable.SynchronizedBuffer, scala.collection.script.Message);
  Code:
   Stack=2, Locals=2, Args_size=2
   0:	aload_0
   1:	dup
   2:	pop
   3:	monitorenter
   4:	aload_0
   5:	aload_1
   6:	invokeinterface	#33,  2; //InterfaceMethod scala/collection/mutable/SynchronizedBuffer.scala$collection$mutable$SynchronizedBuffer$$super$$less$less:(Lscala/collection/script/Message;)V
   11:	aload_0
   12:	monitorexit
   13:	return
   14:	aload_0
   15:	monitorexit
   16:	athrow
  Exception table:
   from   to  target type
     4    13    14   Class java/lang/Throwable

  LineNumberTable: 
   line 176: 0
   line 177: 4
   line 176: 12

  LocalVariableTable: 
   Start  Length  Slot  Name   Signature
   0      17      0    $this       Lscala/collection/mutable/SynchronizedBuffer;
   0      17      1    cmd       Lscala/collection/script/Message;


public static void clear(scala.collection.mutable.SynchronizedBuffer);
  Code:
   Stack=2, Locals=1, Args_size=1
   0:	aload_0
   1:	dup
   2:	pop
   3:	monitorenter
   4:	aload_0
   5:	invokeinterface	#40,  1; //InterfaceMethod scala/collection/mutable/SynchronizedBuffer.scala$collection$mutable$SynchronizedBuffer$$super$clear:()V
   10:	aload_0
   11:	monitorexit
   12:	return
   13:	aload_0
   14:	monitorexit
   15:	athrow
  Exception table:
   from   to  target type
     4    12    13   Class java/lang/Throwable

  LineNumberTable: 
   line 172: 0
   line 173: 4
   line 172: 11

  LocalVariableTable: 
   Start  Length  Slot  Name   Signature
   0      16      0    $this       Lscala/collection/mutable/SynchronizedBuffer;


public static java.lang.Object remove(scala.collection.mutable.SynchronizedBuffer, int);
  Code:
   Stack=2, Locals=2, Args_size=2
   0:	aload_0
   1:	dup
   2:	pop
   3:	monitorenter
   4:	aload_0
   5:	iload_1
   6:	invokeinterface	#46,  2; //InterfaceMethod scala/collection/mutable/SynchronizedBuffer.scala$collection$mutable$SynchronizedBuffer$$super$remove:(I)Ljava/lang/Object;
   11:	aload_0
   12:	monitorexit
   13:	areturn
   14:	aload_0
   15:	monitorexit
   16:	athrow
  Exception table:
   from   to  target type
     4    13    14   Class java/lang/Throwable

  LineNumberTable: 
   line 166: 0
   line 167: 4
   line 166: 12

  LocalVariableTable: 
   Start  Length  Slot  Name   Signature
   0      17      0    $this       Lscala/collection/mutable/SynchronizedBuffer;
   0      17      1    n       I


public static void update(scala.collection.mutable.SynchronizedBuffer, int, java.lang.Object);
  Code:
   Stack=3, Locals=3, Args_size=3
   0:	aload_0
   1:	dup
   2:	pop
   3:	monitorenter
   4:	aload_0
   5:	iload_1
   6:	aload_2
   7:	invokeinterface	#54,  3; //InterfaceMethod scala/collection/mutable/SynchronizedBuffer.scala$collection$mutable$SynchronizedBuffer$$super$update:(ILjava/lang/Object;)V
   12:	aload_0
   13:	monitorexit
   14:	return
   15:	aload_0
   16:	monitorexit
   17:	athrow
  Exception table:
   from   to  target type
     4    14    15   Class java/lang/Throwable

  LineNumberTable: 
   line 158: 0
   line 159: 4
   line 158: 13

  LocalVariableTable: 
   Start  Length  Slot  Name   Signature
   0      18      0    $this       Lscala/collection/mutable/SynchronizedBuffer;
   0      18      1    n       I
   0      18      2    newelem       Ljava/lang/Object;


public static void insertAll(scala.collection.mutable.SynchronizedBuffer, int, scala.collection.Traversable);
  Code:
   Stack=3, Locals=3, Args_size=3
   0:	aload_0
   1:	dup
   2:	pop
   3:	monitorenter
   4:	aload_0
   5:	iload_1
   6:	aload_2
   7:	invokeinterface	#62,  3; //InterfaceMethod scala/collection/mutable/SynchronizedBuffer.scala$collection$mutable$SynchronizedBuffer$$super$insertAll:(ILscala/collection/Traversable;)V
   12:	aload_0
   13:	monitorexit
   14:	return
   15:	aload_0
   16:	monitorexit
   17:	athrow
  Exception table:
   from   to  target type
     4    14    15   Class java/lang/Throwable

  LineNumberTable: 
   line 148: 0
   line 149: 4
   line 148: 13

  LocalVariableTable: 
   Start  Length  Slot  Name   Signature
   0      18      0    $this       Lscala/collection/mutable/SynchronizedBuffer;
   0      18      1    n       I
   0      18      2    iter       Lscala/collection/Traversable;


public static void insert(scala.collection.mutable.SynchronizedBuffer, int, scala.collection.Seq);
  Code:
   Stack=3, Locals=3, Args_size=3
   0:	aload_0
   1:	dup
   2:	pop
   3:	monitorenter
   4:	aload_0
   5:	iload_1
   6:	aload_2
   7:	invokeinterface	#62,  3; //InterfaceMethod scala/collection/mutable/SynchronizedBuffer.scala$collection$mutable$SynchronizedBuffer$$super$insertAll:(ILscala/collection/Traversable;)V
   12:	aload_0
   13:	monitorexit
   14:	return
   15:	aload_0
   16:	monitorexit
   17:	athrow
  Exception table:
   from   to  target type
     4    14    15   Class java/lang/Throwable

  LineNumberTable: 
   line 137: 0
   line 138: 4
   line 137: 13

  LocalVariableTable: 
   Start  Length  Slot  Name   Signature
   0      18      0    $this       Lscala/collection/mutable/SynchronizedBuffer;
   0      18      1    n       I
   0      18      2    elems       Lscala/collection/Seq;


public static void prependAll(scala.collection.mutable.SynchronizedBuffer, scala.collection.Traversable);
  Code:
   Stack=2, Locals=2, Args_size=2
   0:	aload_0
   1:	dup
   2:	pop
   3:	monitorenter
   4:	aload_0
   5:	aload_1
   6:	invokeinterface	#74,  2; //InterfaceMethod scala/collection/mutable/SynchronizedBuffer.scala$collection$mutable$SynchronizedBuffer$$super$prependAll:(Lscala/collection/Traversable;)V
   11:	aload_0
   12:	monitorexit
   13:	return
   14:	aload_0
   15:	monitorexit
   16:	athrow
  Exception table:
   from   to  target type
     4    13    14   Class java/lang/Throwable

  LineNumberTable: 
   line 126: 0
   line 127: 4
   line 126: 12

  LocalVariableTable: 
   Start  Length  Slot  Name   Signature
   0      17      0    $this       Lscala/collection/mutable/SynchronizedBuffer;
   0      17      1    elems       Lscala/collection/Traversable;


public static void prepend(scala.collection.mutable.SynchronizedBuffer, scala.collection.Seq);
  Code:
   Stack=2, Locals=2, Args_size=2
   0:	aload_0
   1:	dup
   2:	pop
   3:	monitorenter
   4:	aload_0
   5:	aload_1
   6:	invokeinterface	#74,  2; //InterfaceMethod scala/collection/mutable/SynchronizedBuffer.scala$collection$mutable$SynchronizedBuffer$$super$prependAll:(Lscala/collection/Traversable;)V
   11:	aload_0
   12:	monitorexit
   13:	return
   14:	aload_0
   15:	monitorexit
   16:	athrow
  Exception table:
   from   to  target type
     4    13    14   Class java/lang/Throwable

  LineNumberTable: 
   line 116: 0
   line 117: 4
   line 116: 12

  LocalVariableTable: 
   Start  Length  Slot  Name   Signature
   0      17      0    $this       Lscala/collection/mutable/SynchronizedBuffer;
   0      17      1    elems       Lscala/collection/Seq;


public static scala.collection.mutable.SynchronizedBuffer $plus$plus$eq$colon(scala.collection.mutable.SynchronizedBuffer, scala.collection.Traversable);
  Code:
   Stack=2, Locals=2, Args_size=2
   0:	aload_0
   1:	dup
   2:	pop
   3:	monitorenter
   4:	aload_0
   5:	aload_1
   6:	invokeinterface	#82,  2; //InterfaceMethod scala/collection/mutable/SynchronizedBuffer.scala$collection$mutable$SynchronizedBuffer$$super$$plus$plus$eq$colon:(Lscala/collection/Traversable;)Lscala/collection/mutable/SynchronizedBuffer;
   11:	aload_0
   12:	monitorexit
   13:	checkcast	#13; //class scala/collection/mutable/SynchronizedBuffer
   16:	areturn
   17:	aload_0
   18:	monitorexit
   19:	athrow
  Exception table:
   from   to  target type
     4    13    17   Class java/lang/Throwable

  LineNumberTable: 
   line 108: 0
   line 109: 4
   line 108: 12

  LocalVariableTable: 
   Start  Length  Slot  Name   Signature
   0      20      0    $this       Lscala/collection/mutable/SynchronizedBuffer;
   0      20      1    iter       Lscala/collection/Traversable;


public static scala.collection.mutable.SynchronizedBuffer $plus$eq$colon(scala.collection.mutable.SynchronizedBuffer, java.lang.Object);
  Code:
   Stack=2, Locals=2, Args_size=2
   0:	aload_0
   1:	dup
   2:	pop
   3:	monitorenter
   4:	aload_0
   5:	aload_1
   6:	invokeinterface	#88,  2; //InterfaceMethod scala/collection/mutable/SynchronizedBuffer.scala$collection$mutable$SynchronizedBuffer$$super$$plus$eq$colon:(Ljava/lang/Object;)Lscala/collection/mutable/SynchronizedBuffer;
   11:	aload_0
   12:	monitorexit
   13:	checkcast	#13; //class scala/collection/mutable/SynchronizedBuffer
   16:	areturn
   17:	aload_0
   18:	monitorexit
   19:	athrow
  Exception table:
   from   to  target type
     4    13    17   Class java/lang/Throwable

  LineNumberTable: 
   line 98: 0
   line 99: 4
   line 98: 12

  LocalVariableTable: 
   Start  Length  Slot  Name   Signature
   0      20      0    $this       Lscala/collection/mutable/SynchronizedBuffer;
   0      20      1    elem       Ljava/lang/Object;


public static void appendAll(scala.collection.mutable.SynchronizedBuffer, scala.collection.Traversable);
  Code:
   Stack=2, Locals=2, Args_size=2
   0:	aload_0
   1:	dup
   2:	pop
   3:	monitorenter
   4:	aload_0
   5:	aload_1
   6:	invokeinterface	#93,  2; //InterfaceMethod scala/collection/mutable/SynchronizedBuffer.scala$collection$mutable$SynchronizedBuffer$$super$appendAll:(Lscala/collection/Traversable;)V
   11:	aload_0
   12:	monitorexit
   13:	return
   14:	aload_0
   15:	monitorexit
   16:	athrow
  Exception table:
   from   to  target type
     4    13    14   Class java/lang/Throwable

  LineNumberTable: 
   line 89: 0
   line 90: 4
   line 89: 12

  LocalVariableTable: 
   Start  Length  Slot  Name   Signature
   0      17      0    $this       Lscala/collection/mutable/SynchronizedBuffer;
   0      17      1    iter       Lscala/collection/Traversable;


public static void append(scala.collection.mutable.SynchronizedBuffer, scala.collection.Seq);
  Code:
   Stack=2, Locals=2, Args_size=2
   0:	aload_0
   1:	dup
   2:	pop
   3:	monitorenter
   4:	aload_0
   5:	aload_1
   6:	invokeinterface	#97,  2; //InterfaceMethod scala/collection/mutable/SynchronizedBuffer.scala$collection$mutable$SynchronizedBuffer$$super$$plus$plus$eq:(Lscala/collection/Traversable;)Lscala/collection/mutable/SynchronizedBuffer;
   11:	pop
   12:	aload_0
   13:	monitorexit
   14:	return
   15:	aload_0
   16:	monitorexit
   17:	athrow
  Exception table:
   from   to  target type
     4    14    15   Class java/lang/Throwable

  LineNumberTable: 
   line 80: 0
   line 81: 4
   line 80: 13

  LocalVariableTable: 
   Start  Length  Slot  Name   Signature
   0      18      0    $this       Lscala/collection/mutable/SynchronizedBuffer;
   0      18      1    elems       Lscala/collection/Seq;


public static scala.collection.mutable.SynchronizedBuffer $plus$plus$eq(scala.collection.mutable.SynchronizedBuffer, scala.collection.Traversable);
  Code:
   Stack=2, Locals=2, Args_size=2
   0:	aload_0
   1:	dup
   2:	pop
   3:	monitorenter
   4:	aload_0
   5:	aload_1
   6:	invokeinterface	#97,  2; //InterfaceMethod scala/collection/mutable/SynchronizedBuffer.scala$collection$mutable$SynchronizedBuffer$$super$$plus$plus$eq:(Lscala/collection/Traversable;)Lscala/collection/mutable/SynchronizedBuffer;
   11:	aload_0
   12:	monitorexit
   13:	checkcast	#13; //class scala/collection/mutable/SynchronizedBuffer
   16:	areturn
   17:	aload_0
   18:	monitorexit
   19:	athrow
  Exception table:
   from   to  target type
     4    13    17   Class java/lang/Throwable

  LineNumberTable: 
   line 72: 0
   line 73: 4
   line 72: 12

  LocalVariableTable: 
   Start  Length  Slot  Name   Signature
   0      20      0    $this       Lscala/collection/mutable/SynchronizedBuffer;
   0      20      1    iter       Lscala/collection/Traversable;


public static scala.collection.mutable.Buffer $plus$plus(scala.collection.mutable.SynchronizedBuffer, scala.collection.Traversable);
  Code:
   Stack=2, Locals=2, Args_size=2
   0:	aload_0
   1:	dup
   2:	pop
   3:	monitorenter
   4:	aload_0
   5:	aload_1
   6:	invokeinterface	#104,  2; //InterfaceMethod scala/collection/mutable/SynchronizedBuffer.scala$collection$mutable$SynchronizedBuffer$$super$$plus$plus:(Lscala/collection/Traversable;)Lscala/collection/mutable/Buffer;
   11:	aload_0
   12:	monitorexit
   13:	checkcast	#27; //class scala/collection/mutable/Buffer
   16:	areturn
   17:	aload_0
   18:	monitorexit
   19:	athrow
  Exception table:
   from   to  target type
     4    13    17   Class java/lang/Throwable

  LineNumberTable: 
   line 63: 0
   line 64: 4
   line 63: 12

  LocalVariableTable: 
   Start  Length  Slot  Name   Signature
   0      20      0    $this       Lscala/collection/mutable/SynchronizedBuffer;
   0      20      1    iter       Lscala/collection/Traversable;


public static scala.collection.mutable.SynchronizedBuffer $plus$eq(scala.collection.mutable.SynchronizedBuffer, java.lang.Object);
  Code:
   Stack=2, Locals=2, Args_size=2
   0:	aload_0
   1:	dup
   2:	pop
   3:	monitorenter
   4:	aload_0
   5:	aload_1
   6:	invokeinterface	#108,  2; //InterfaceMethod scala/collection/mutable/SynchronizedBuffer.scala$collection$mutable$SynchronizedBuffer$$super$$plus$eq:(Ljava/lang/Object;)Lscala/collection/mutable/SynchronizedBuffer;
   11:	aload_0
   12:	monitorexit
   13:	checkcast	#13; //class scala/collection/mutable/SynchronizedBuffer
   16:	areturn
   17:	aload_0
   18:	monitorexit
   19:	athrow
  Exception table:
   from   to  target type
     4    13    17   Class java/lang/Throwable

  LineNumberTable: 
   line 53: 0
   line 54: 4
   line 53: 12

  LocalVariableTable: 
   Start  Length  Slot  Name   Signature
   0      20      0    $this       Lscala/collection/mutable/SynchronizedBuffer;
   0      20      1    elem       Ljava/lang/Object;


public static scala.collection.mutable.Buffer $plus(scala.collection.mutable.SynchronizedBuffer, java.lang.Object);
  Code:
   Stack=2, Locals=2, Args_size=2
   0:	aload_0
   1:	dup
   2:	pop
   3:	monitorenter
   4:	aload_0
   5:	aload_1
   6:	invokeinterface	#114,  2; //InterfaceMethod scala/collection/mutable/SynchronizedBuffer.scala$collection$mutable$SynchronizedBuffer$$super$$plus:(Ljava/lang/Object;)Lscala/collection/mutable/Buffer;
   11:	aload_0
   12:	monitorexit
   13:	checkcast	#27; //class scala/collection/mutable/Buffer
   16:	areturn
   17:	aload_0
   18:	monitorexit
   19:	athrow
  Exception table:
   from   to  target type
     4    13    17   Class java/lang/Throwable

  LineNumberTable: 
   line 45: 0
   line 46: 4
   line 45: 12

  LocalVariableTable: 
   Start  Length  Slot  Name   Signature
   0      20      0    $this       Lscala/collection/mutable/SynchronizedBuffer;
   0      20      1    elem       Ljava/lang/Object;


public static java.lang.Object apply(scala.collection.mutable.SynchronizedBuffer, int);
  Code:
   Stack=2, Locals=2, Args_size=2
   0:	aload_0
   1:	dup
   2:	pop
   3:	monitorenter
   4:	aload_0
   5:	iload_1
   6:	invokeinterface	#118,  2; //InterfaceMethod scala/collection/mutable/SynchronizedBuffer.scala$collection$mutable$SynchronizedBuffer$$super$apply:(I)Ljava/lang/Object;
   11:	aload_0
   12:	monitorexit
   13:	areturn
   14:	aload_0
   15:	monitorexit
   16:	athrow
  Exception table:
   from   to  target type
     4    13    14   Class java/lang/Throwable

  LineNumberTable: 
   line 36: 0
   line 37: 4
   line 36: 12

  LocalVariableTable: 
   Start  Length  Slot  Name   Signature
   0      17      0    $this       Lscala/collection/mutable/SynchronizedBuffer;
   0      17      1    n       I


public static scala.collection.Iterator iterator(scala.collection.mutable.SynchronizedBuffer);
  Code:
   Stack=2, Locals=1, Args_size=1
   0:	aload_0
   1:	dup
   2:	pop
   3:	monitorenter
   4:	aload_0
   5:	invokeinterface	#124,  1; //InterfaceMethod scala/collection/mutable/SynchronizedBuffer.scala$collection$mutable$SynchronizedBuffer$$super$iterator:()Lscala/collection/Iterator;
   10:	aload_0
   11:	monitorexit
   12:	checkcast	#126; //class scala/collection/Iterator
   15:	areturn
   16:	aload_0
   17:	monitorexit
   18:	athrow
  Exception table:
   from   to  target type
     4    12    16   Class java/lang/Throwable

  LineNumberTable: 
   line 32: 0
   line 33: 4
   line 32: 11

  LocalVariableTable: 
   Start  Length  Slot  Name   Signature
   0      19      0    $this       Lscala/collection/mutable/SynchronizedBuffer;


public static int length(scala.collection.mutable.SynchronizedBuffer);
  Code:
   Stack=2, Locals=2, Args_size=1
   0:	aload_0
   1:	dup
   2:	pop
   3:	monitorenter
   4:	aload_0
   5:	invokeinterface	#130,  1; //InterfaceMethod scala/collection/mutable/SynchronizedBuffer.scala$collection$mutable$SynchronizedBuffer$$super$length:()I
   10:	istore_1
   11:	aload_0
   12:	monitorexit
   13:	iload_1
   14:	ireturn
   15:	aload_0
   16:	monitorexit
   17:	athrow
  Exception table:
   from   to  target type
     4    13    15   Class java/lang/Throwable

  LineNumberTable: 
   line 28: 0
   line 29: 4
   line 28: 12

  LocalVariableTable: 
   Start  Length  Slot  Name   Signature
   0      18      0    $this       Lscala/collection/mutable/SynchronizedBuffer;


}

