Compiled from "SynchronizedQueue.scala"
public class scala.collection.mutable.SynchronizedQueue extends scala.collection.mutable.Queue implements scala.ScalaObject
  SourceFile: "SynchronizedQueue.scala"
  Signature: length = 0x2
   00 6A 
  ScalaSig: length = 0x274
   05 00 6A 06 04 01 02 00 09 02 11 53 79 6E 63 68
   72 6F 6E 69 7A 65 64 51 75 65 75 65 0A 02 03 04
   01 07 6D 75 74 61 62 6C 65 0A 02 05 06 01 0A 63
   6F 6C 6C 65 63 74 69 6F 6E 0A 01 07 01 05 73 63
   61 6C 61 03 00 15 02 0A 11 13 03 00 0B 1B 10 03
   0C 0D 0F 0D 01 02 09 02 0E 02 02 05 51 75 65 75
   65 10 02 10 11 0C 00 04 08 12 00 FFFFFF84 FFFFFF80 FFFFFF80 FFFFFFC2 00
   13 02 01 41 11 02 14 18 10 02 15 16 0D 01 06 09
   02 17 06 02 07 4E 6F 74 68 69 6E 67 10 02 15 19
   09 02 1A 06 02 03 41 6E 79 10 02 15 1C 09 02 1D
   06 02 0B 53 63 61 6C 61 4F 62 6A 65 63 74 08 05
   1F 00 FFFFFF84 00 20 01 06 3C 69 6E 69 74 3E 14 01 21
   10 03 0C 00 0F 08 05 23 00 FFFFFF84 20 24 01 07 69 73
   45 6D 70 74 79 15 01 25 10 02 15 26 09 02 27 06
   02 07 42 6F 6F 6C 65 61 6E 08 05 29 00 FFFFFF84 20 2A
   01 08 24 70 6C 75 73 24 65 71 14 02 2B 2C 0D 01
   00 08 05 2D 28 FFFFFFC0 00 0F 01 04 65 6C 65 6D 08 05
   2F 00 FFFFFF84 20 30 01 0D 24 70 6C 75 73 24 70 6C 75
   73 24 65 71 14 02 2B 31 08 05 32 2E FFFFFFC0 00 33 01
   04 69 74 65 72 10 03 34 35 0F 0D 01 04 09 02 36
   04 02 0B 54 72 61 76 65 72 73 61 62 6C 65 08 05
   2F 00 FFFFFF84 20 38 14 02 2B 39 08 05 3A 37 FFFFFFC0 00 3B
   01 02 69 74 10 03 3C 44 0F 0E 02 3D 42 0E 02 3E
   41 0D 01 3F 0A 02 40 08 01 06 3C 72 6F 6F 74 3E
   09 01 07 09 02 43 06 01 07 70 61 63 6B 61 67 65
   09 02 45 46 02 08 49 74 65 72 61 74 6F 72 0A 02
   43 06 08 05 48 00 FFFFFF84 20 49 01 07 65 6E 71 75 65
   75 65 14 02 4A 4D 10 02 15 4B 09 02 4C 06 02 04
   55 6E 69 74 08 05 4E 47 FFFFFFC0 00 4F 01 05 65 6C 65
   6D 73 10 03 15 50 0F 09 02 51 06 02 0A 3C 72 65
   70 65 61 74 65 64 3E 08 05 53 00 FFFFFF84 20 54 01 07
   64 65 71 75 65 75 65 14 01 0F 08 05 56 00 FFFFFF84 20
   57 01 05 66 72 6F 6E 74 15 01 0F 08 05 59 00 FFFFFF84
   20 5A 01 05 63 6C 65 61 72 14 01 4A 08 05 5C 00
   FFFFFF84 20 5D 01 06 65 71 75 61 6C 73 14 02 25 5E 08
   05 5F 5B FFFFFFC0 00 18 01 04 74 68 61 74 08 05 61 00
   FFFFFF84 20 62 01 08 74 6F 53 74 72 69 6E 67 14 01 63
   10 02 64 67 0E 02 15 65 09 02 66 06 01 06 50 72
   65 64 65 66 09 02 68 69 02 06 53 74 72 69 6E 67
   0A 02 66 06 
  minor version: 0
  major version: 49
  Constant pool:
const #1 = Asciz	SourceFile;
const #2 = Asciz	SynchronizedQueue.scala;
const #3 = Asciz	<init>;
const #4 = Asciz	()V;
const #5 = Asciz	Code;
const #6 = Asciz	LineNumberTable;
const #7 = Asciz	scala/collection/mutable/Queue;
const #8 = class	#7;	//  scala/collection/mutable/Queue
const #9 = NameAndType	#3:#4;//  "<init>":()V
const #10 = Method	#8.#9;	//  scala/collection/mutable/Queue."<init>":()V
const #11 = Asciz	Signature;
const #12 = Asciz	$plus$eq;
const #13 = Asciz	(Ljava/lang/Object;)Lscala/collection/mutable/MutableList;;
const #14 = Asciz	scala/collection/mutable/SynchronizedQueue;
const #15 = class	#14;	//  scala/collection/mutable/SynchronizedQueue
const #16 = Asciz	(Ljava/lang/Object;)Lscala/collection/mutable/SynchronizedQueue;;
const #17 = NameAndType	#12:#16;//  $plus$eq:(Ljava/lang/Object;)Lscala/collection/mutable/SynchronizedQueue;
const #18 = Method	#15.#17;	//  scala/collection/mutable/SynchronizedQueue.$plus$eq:(Ljava/lang/Object;)Lscala/collection/mutable/SynchronizedQueue;
const #19 = Asciz	this;
const #20 = Asciz	Lscala/collection/mutable/SynchronizedQueue;;
const #21 = Asciz	elem;
const #22 = Asciz	Ljava/lang/Object;;
const #23 = Asciz	LocalVariableTable;
const #24 = Asciz	(Ljava/lang/Object;)Lscala/collection/generic/Builder;;
const #25 = Asciz	(Ljava/lang/Object;)Lscala/collection/generic/Growable;;
const #26 = Asciz	$plus$plus$eq;
const #27 = Asciz	(Lscala/collection/Traversable;)Lscala/collection/generic/Growable;;
const #28 = Asciz	(Lscala/collection/Traversable;)Lscala/collection/mutable/SynchronizedQueue;;
const #29 = NameAndType	#26:#28;//  $plus$plus$eq:(Lscala/collection/Traversable;)Lscala/collection/mutable/SynchronizedQueue;
const #30 = Method	#15.#29;	//  scala/collection/mutable/SynchronizedQueue.$plus$plus$eq:(Lscala/collection/Traversable;)Lscala/collection/mutable/SynchronizedQueue;
const #31 = Asciz	iter;
const #32 = Asciz	Lscala/collection/Traversable;;
const #33 = Asciz	(Lscala/collection/Iterator;)Lscala/collection/generic/Growable;;
const #34 = Asciz	(Lscala/collection/Iterator;)Lscala/collection/mutable/SynchronizedQueue;;
const #35 = NameAndType	#26:#34;//  $plus$plus$eq:(Lscala/collection/Iterator;)Lscala/collection/mutable/SynchronizedQueue;
const #36 = Method	#15.#35;	//  scala/collection/mutable/SynchronizedQueue.$plus$plus$eq:(Lscala/collection/Iterator;)Lscala/collection/mutable/SynchronizedQueue;
const #37 = Asciz	Lscala/collection/Iterator;;
const #38 = Asciz	toString;
const #39 = Asciz	()Ljava/lang/String;;
const #40 = Asciz	scala/collection/generic/SequenceTemplate$class;
const #41 = class	#40;	//  scala/collection/generic/SequenceTemplate$class
const #42 = Asciz	(Lscala/collection/generic/SequenceTemplate;)Ljava/lang/String;;
const #43 = NameAndType	#38:#42;//  toString:(Lscala/collection/generic/SequenceTemplate;)Ljava/lang/String;
const #44 = Method	#41.#43;	//  scala/collection/generic/SequenceTemplate$class.toString:(Lscala/collection/generic/SequenceTemplate;)Ljava/lang/String;
const #45 = Asciz	java/lang/String;
const #46 = class	#45;	//  java/lang/String
const #47 = Asciz	equals;
const #48 = Asciz	(Ljava/lang/Object;)Z;
const #49 = Asciz	scala/collection/generic/LinearSequenceTemplate$class;
const #50 = class	#49;	//  scala/collection/generic/LinearSequenceTemplate$class
const #51 = Asciz	(Lscala/collection/generic/LinearSequenceTemplate;Ljava/lang/Object;)Z;
const #52 = NameAndType	#47:#51;//  equals:(Lscala/collection/generic/LinearSequenceTemplate;Ljava/lang/Object;)Z
const #53 = Method	#50.#52;	//  scala/collection/generic/LinearSequenceTemplate$class.equals:(Lscala/collection/generic/LinearSequenceTemplate;Ljava/lang/Object;)Z
const #54 = Asciz	scala/runtime/BoxesRunTime;
const #55 = class	#54;	//  scala/runtime/BoxesRunTime
const #56 = Asciz	boxToBoolean;
const #57 = Asciz	(Z)Ljava/lang/Boolean;;
const #58 = NameAndType	#56:#57;//  boxToBoolean:(Z)Ljava/lang/Boolean;
const #59 = Method	#55.#58;	//  scala/runtime/BoxesRunTime.boxToBoolean:(Z)Ljava/lang/Boolean;
const #60 = Asciz	unboxToBoolean;
const #61 = NameAndType	#60:#48;//  unboxToBoolean:(Ljava/lang/Object;)Z
const #62 = Method	#55.#61;	//  scala/runtime/BoxesRunTime.unboxToBoolean:(Ljava/lang/Object;)Z
const #63 = Asciz	that;
const #64 = Asciz	clear;
const #65 = Asciz	scala/collection/mutable/MutableList;
const #66 = class	#65;	//  scala/collection/mutable/MutableList
const #67 = NameAndType	#64:#4;//  clear:()V
const #68 = Method	#66.#67;	//  scala/collection/mutable/MutableList.clear:()V
const #69 = Asciz	scala/runtime/BoxedUnit;
const #70 = class	#69;	//  scala/runtime/BoxedUnit
const #71 = Asciz	UNIT;
const #72 = Asciz	Lscala/runtime/BoxedUnit;;
const #73 = NameAndType	#71:#72;//  UNIT:Lscala/runtime/BoxedUnit;
const #74 = Field	#70.#73;	//  scala/runtime/BoxedUnit.UNIT:Lscala/runtime/BoxedUnit;
const #75 = Asciz	front;
const #76 = Asciz	()Ljava/lang/Object;;
const #77 = NameAndType	#75:#76;//  front:()Ljava/lang/Object;
const #78 = Method	#8.#77;	//  scala/collection/mutable/Queue.front:()Ljava/lang/Object;
const #79 = Asciz	()TA;;
const #80 = Asciz	dequeue;
const #81 = NameAndType	#80:#76;//  dequeue:()Ljava/lang/Object;
const #82 = Method	#8.#81;	//  scala/collection/mutable/Queue.dequeue:()Ljava/lang/Object;
const #83 = Asciz	enqueue;
const #84 = Asciz	(Lscala/collection/Sequence;)V;
const #85 = Asciz	scala/collection/generic/Growable$class;
const #86 = class	#85;	//  scala/collection/generic/Growable$class
const #87 = Asciz	(Lscala/collection/generic/Growable;Lscala/collection/Traversable;)Lscala/collection/generic/Growable;;
const #88 = NameAndType	#26:#87;//  $plus$plus$eq:(Lscala/collection/generic/Growable;Lscala/collection/Traversable;)Lscala/collection/generic/Growable;
const #89 = Method	#86.#88;	//  scala/collection/generic/Growable$class.$plus$plus$eq:(Lscala/collection/generic/Growable;Lscala/collection/Traversable;)Lscala/collection/generic/Growable;
const #90 = Asciz	elems;
const #91 = Asciz	Lscala/collection/Sequence;;
const #92 = Asciz	(Lscala/collection/Sequence<TA;>;)V;
const #93 = Asciz	(Lscala/collection/generic/Growable;Lscala/collection/Iterator;)Lscala/collection/generic/Growable;;
const #94 = NameAndType	#26:#93;//  $plus$plus$eq:(Lscala/collection/generic/Growable;Lscala/collection/Iterator;)Lscala/collection/generic/Growable;
const #95 = Method	#86.#94;	//  scala/collection/generic/Growable$class.$plus$plus$eq:(Lscala/collection/generic/Growable;Lscala/collection/Iterator;)Lscala/collection/generic/Growable;
const #96 = Asciz	it;
const #97 = Asciz	(Lscala/collection/Iterator<TA;>;)Lscala/collection/mutable/SynchronizedQueue<TA;>;;
const #98 = Asciz	(Lscala/collection/Traversable<TA;>;)Lscala/collection/mutable/SynchronizedQueue<TA;>;;
const #99 = NameAndType	#12:#13;//  $plus$eq:(Ljava/lang/Object;)Lscala/collection/mutable/MutableList;
const #100 = Method	#66.#99;	//  scala/collection/mutable/MutableList.$plus$eq:(Ljava/lang/Object;)Lscala/collection/mutable/MutableList;
const #101 = Asciz	(TA;)Lscala/collection/mutable/SynchronizedQueue<TA;>;;
const #102 = Asciz	isEmpty;
const #103 = Asciz	()Z;
const #104 = NameAndType	#102:#103;//  isEmpty:()Z
const #105 = Method	#66.#104;	//  scala/collection/mutable/MutableList.isEmpty:()Z
const #106 = Asciz	<A:Ljava/lang/Object;>Lscala/collection/mutable/Queue<TA;>;Lscala/ScalaObject;;
const #107 = Asciz	ScalaSig;
const #108 = Asciz	scala/ScalaObject;
const #109 = class	#108;	//  scala/ScalaObject

{
public scala.collection.mutable.SynchronizedQueue();
  Code:
   Stack=1, Locals=1, Args_size=1
   0:	aload_0
   1:	invokespecial	#10; //Method scala/collection/mutable/Queue."<init>":()V
   4:	return
  LineNumberTable: 
   line 22: 0

  Signature: length = 0x2
   00 04 

public scala.collection.mutable.MutableList $plus$eq(java.lang.Object);
  Code:
   Stack=2, Locals=2, Args_size=2
   0:	aload_0
   1:	aload_1
   2:	invokevirtual	#18; //Method $plus$eq:(Ljava/lang/Object;)Lscala/collection/mutable/SynchronizedQueue;
   5:	areturn
  LineNumberTable: 
   line 22: 0

  LocalVariableTable: 
   Start  Length  Slot  Name   Signature
   0      6      0    this       Lscala/collection/mutable/SynchronizedQueue;
   0      6      1    elem       Ljava/lang/Object;


public scala.collection.generic.Builder $plus$eq(java.lang.Object);
  Code:
   Stack=2, Locals=2, Args_size=2
   0:	aload_0
   1:	aload_1
   2:	invokevirtual	#18; //Method $plus$eq:(Ljava/lang/Object;)Lscala/collection/mutable/SynchronizedQueue;
   5:	areturn
  LineNumberTable: 
   line 22: 0

  LocalVariableTable: 
   Start  Length  Slot  Name   Signature
   0      6      0    this       Lscala/collection/mutable/SynchronizedQueue;
   0      6      1    elem       Ljava/lang/Object;


public scala.collection.generic.Growable $plus$eq(java.lang.Object);
  Code:
   Stack=2, Locals=2, Args_size=2
   0:	aload_0
   1:	aload_1
   2:	invokevirtual	#18; //Method $plus$eq:(Ljava/lang/Object;)Lscala/collection/mutable/SynchronizedQueue;
   5:	areturn
  LineNumberTable: 
   line 22: 0

  LocalVariableTable: 
   Start  Length  Slot  Name   Signature
   0      6      0    this       Lscala/collection/mutable/SynchronizedQueue;
   0      6      1    elem       Ljava/lang/Object;


public scala.collection.generic.Growable $plus$plus$eq(scala.collection.Traversable);
  Code:
   Stack=2, Locals=2, Args_size=2
   0:	aload_0
   1:	aload_1
   2:	invokevirtual	#30; //Method $plus$plus$eq:(Lscala/collection/Traversable;)Lscala/collection/mutable/SynchronizedQueue;
   5:	areturn
  LineNumberTable: 
   line 22: 0

  LocalVariableTable: 
   Start  Length  Slot  Name   Signature
   0      6      0    this       Lscala/collection/mutable/SynchronizedQueue;
   0      6      1    iter       Lscala/collection/Traversable;


public scala.collection.generic.Growable $plus$plus$eq(scala.collection.Iterator);
  Code:
   Stack=2, Locals=2, Args_size=2
   0:	aload_0
   1:	aload_1
   2:	invokevirtual	#36; //Method $plus$plus$eq:(Lscala/collection/Iterator;)Lscala/collection/mutable/SynchronizedQueue;
   5:	areturn
  LineNumberTable: 
   line 22: 0

  LocalVariableTable: 
   Start  Length  Slot  Name   Signature
   0      6      0    this       Lscala/collection/mutable/SynchronizedQueue;
   0      6      1    iter       Lscala/collection/Iterator;


public java.lang.String toString();
  Code:
   Stack=2, Locals=2, Args_size=1
   0:	aload_0
   1:	dup
   2:	astore_1
   3:	monitorenter
   4:	aload_0
   5:	invokestatic	#44; //Method scala/collection/generic/SequenceTemplate$class.toString:(Lscala/collection/generic/SequenceTemplate;)Ljava/lang/String;
   8:	aload_1
   9:	monitorexit
   10:	checkcast	#46; //class java/lang/String
   13:	areturn
   14:	aload_1
   15:	monitorexit
   16:	athrow
  Exception table:
   from   to  target type
     4    10    14   any
  LineNumberTable: 
   line 88: 0


public boolean equals(java.lang.Object);
  Code:
   Stack=2, Locals=3, Args_size=2
   0:	aload_0
   1:	dup
   2:	astore_2
   3:	monitorenter
   4:	aload_0
   5:	aload_1
   6:	invokestatic	#53; //Method scala/collection/generic/LinearSequenceTemplate$class.equals:(Lscala/collection/generic/LinearSequenceTemplate;Ljava/lang/Object;)Z
   9:	invokestatic	#59; //Method scala/runtime/BoxesRunTime.boxToBoolean:(Z)Ljava/lang/Boolean;
   12:	aload_2
   13:	monitorexit
   14:	invokestatic	#62; //Method scala/runtime/BoxesRunTime.unboxToBoolean:(Ljava/lang/Object;)Z
   17:	ireturn
   18:	aload_2
   19:	monitorexit
   20:	athrow
  Exception table:
   from   to  target type
     4    14    18   any
  LineNumberTable: 
   line 82: 0

  LocalVariableTable: 
   Start  Length  Slot  Name   Signature
   0      21      0    this       Lscala/collection/mutable/SynchronizedQueue;
   0      21      1    that       Ljava/lang/Object;


public void clear();
  Code:
   Stack=2, Locals=2, Args_size=1
   0:	aload_0
   1:	dup
   2:	astore_1
   3:	monitorenter
   4:	aload_0
   5:	invokespecial	#68; //Method scala/collection/mutable/MutableList.clear:()V
   8:	getstatic	#74; //Field scala/runtime/BoxedUnit.UNIT:Lscala/runtime/BoxedUnit;
   11:	pop
   12:	aload_1
   13:	monitorexit
   14:	return
   15:	aload_1
   16:	monitorexit
   17:	athrow
  Exception table:
   from   to  target type
     4    14    15   any
  LineNumberTable: 
   line 76: 0


public java.lang.Object front();
  Code:
   Stack=2, Locals=2, Args_size=1
   0:	aload_0
   1:	dup
   2:	astore_1
   3:	monitorenter
   4:	aload_0
   5:	invokespecial	#78; //Method scala/collection/mutable/Queue.front:()Ljava/lang/Object;
   8:	aload_1
   9:	monitorexit
   10:	areturn
   11:	aload_1
   12:	monitorexit
   13:	athrow
  Exception table:
   from   to  target type
     4    10    11   any
  LineNumberTable: 
   line 71: 0

  Signature: length = 0x2
   00 4F 

public java.lang.Object dequeue();
  Code:
   Stack=2, Locals=2, Args_size=1
   0:	aload_0
   1:	dup
   2:	astore_1
   3:	monitorenter
   4:	aload_0
   5:	invokespecial	#82; //Method scala/collection/mutable/Queue.dequeue:()Ljava/lang/Object;
   8:	aload_1
   9:	monitorexit
   10:	areturn
   11:	aload_1
   12:	monitorexit
   13:	athrow
  Exception table:
   from   to  target type
     4    10    11   any
  LineNumberTable: 
   line 64: 0

  Signature: length = 0x2
   00 4F 

public void enqueue(scala.collection.Sequence);
  Code:
   Stack=2, Locals=3, Args_size=2
   0:	aload_0
   1:	dup
   2:	astore_2
   3:	monitorenter
   4:	aload_0
   5:	aload_1
   6:	invokestatic	#89; //Method scala/collection/generic/Growable$class.$plus$plus$eq:(Lscala/collection/generic/Growable;Lscala/collection/Traversable;)Lscala/collection/generic/Growable;
   9:	pop
   10:	aload_2
   11:	monitorexit
   12:	return
   13:	aload_2
   14:	monitorexit
   15:	athrow
  Exception table:
   from   to  target type
     4    12    13   any
  LineNumberTable: 
   line 57: 0

  LocalVariableTable: 
   Start  Length  Slot  Name   Signature
   0      16      0    this       Lscala/collection/mutable/SynchronizedQueue;
   0      16      1    elems       Lscala/collection/Sequence;

  Signature: length = 0x2
   00 5C 

public scala.collection.mutable.SynchronizedQueue $plus$plus$eq(scala.collection.Iterator);
  Code:
   Stack=2, Locals=3, Args_size=2
   0:	aload_0
   1:	dup
   2:	astore_2
   3:	monitorenter
   4:	aload_0
   5:	aload_1
   6:	invokestatic	#95; //Method scala/collection/generic/Growable$class.$plus$plus$eq:(Lscala/collection/generic/Growable;Lscala/collection/Iterator;)Lscala/collection/generic/Growable;
   9:	aload_2
   10:	monitorexit
   11:	checkcast	#15; //class scala/collection/mutable/SynchronizedQueue
   14:	areturn
   15:	aload_2
   16:	monitorexit
   17:	athrow
  Exception table:
   from   to  target type
     4    11    15   any
  LineNumberTable: 
   line 51: 0

  LocalVariableTable: 
   Start  Length  Slot  Name   Signature
   0      18      0    this       Lscala/collection/mutable/SynchronizedQueue;
   0      18      1    it       Lscala/collection/Iterator;

  Signature: length = 0x2
   00 61 

public scala.collection.mutable.SynchronizedQueue $plus$plus$eq(scala.collection.Traversable);
  Code:
   Stack=2, Locals=3, Args_size=2
   0:	aload_0
   1:	dup
   2:	astore_2
   3:	monitorenter
   4:	aload_0
   5:	aload_1
   6:	invokestatic	#89; //Method scala/collection/generic/Growable$class.$plus$plus$eq:(Lscala/collection/generic/Growable;Lscala/collection/Traversable;)Lscala/collection/generic/Growable;
   9:	aload_2
   10:	monitorexit
   11:	checkcast	#15; //class scala/collection/mutable/SynchronizedQueue
   14:	areturn
   15:	aload_2
   16:	monitorexit
   17:	athrow
  Exception table:
   from   to  target type
     4    11    15   any
  LineNumberTable: 
   line 43: 0

  LocalVariableTable: 
   Start  Length  Slot  Name   Signature
   0      18      0    this       Lscala/collection/mutable/SynchronizedQueue;
   0      18      1    iter       Lscala/collection/Traversable;

  Signature: length = 0x2
   00 62 

public scala.collection.mutable.SynchronizedQueue $plus$eq(java.lang.Object);
  Code:
   Stack=2, Locals=3, Args_size=2
   0:	aload_0
   1:	dup
   2:	astore_2
   3:	monitorenter
   4:	aload_0
   5:	aload_1
   6:	invokespecial	#100; //Method scala/collection/mutable/MutableList.$plus$eq:(Ljava/lang/Object;)Lscala/collection/mutable/MutableList;
   9:	aload_2
   10:	monitorexit
   11:	checkcast	#15; //class scala/collection/mutable/SynchronizedQueue
   14:	areturn
   15:	aload_2
   16:	monitorexit
   17:	athrow
  Exception table:
   from   to  target type
     4    11    15   any
  LineNumberTable: 
   line 35: 0

  LocalVariableTable: 
   Start  Length  Slot  Name   Signature
   0      18      0    this       Lscala/collection/mutable/SynchronizedQueue;
   0      18      1    elem       Ljava/lang/Object;

  Signature: length = 0x2
   00 65 

public boolean isEmpty();
  Code:
   Stack=2, Locals=2, Args_size=1
   0:	aload_0
   1:	dup
   2:	astore_1
   3:	monitorenter
   4:	aload_0
   5:	invokespecial	#105; //Method scala/collection/mutable/MutableList.isEmpty:()Z
   8:	invokestatic	#59; //Method scala/runtime/BoxesRunTime.boxToBoolean:(Z)Ljava/lang/Boolean;
   11:	aload_1
   12:	monitorexit
   13:	invokestatic	#62; //Method scala/runtime/BoxesRunTime.unboxToBoolean:(Ljava/lang/Object;)Z
   16:	ireturn
   17:	aload_1
   18:	monitorexit
   19:	athrow
  Exception table:
   from   to  target type
     4    13    17   any
  LineNumberTable: 
   line 29: 0


}

