Compiled from "SynchronizedPriorityQueue.scala"
public class scala.collection.mutable.SynchronizedPriorityQueue extends scala.collection.mutable.PriorityQueue implements scala.ScalaObject
  SourceFile: "SynchronizedPriorityQueue.scala"
  Signature: length = 0x2
   00 60 
  ScalaSig: length = 0x2C0
   05 00 74 06 04 01 02 00 09 02 19 53 79 6E 63 68
   72 6F 6E 69 7A 65 64 50 72 69 6F 72 69 74 79 51
   75 65 75 65 0A 02 03 04 01 07 6D 75 74 61 62 6C
   65 0A 02 05 06 01 0A 63 6F 6C 6C 65 63 74 69 6F
   6E 0A 01 07 01 05 73 63 61 6C 61 03 00 15 02 0A
   11 13 03 00 0B 1B 10 03 0C 0D 0F 0D 01 02 09 02
   0E 02 02 0D 50 72 69 6F 72 69 74 79 51 75 65 75
   65 10 02 10 11 0C 00 04 08 12 00 FFFFFF84 FFFFFF80 FFFFFF80 FFFFFFC2 00
   13 02 01 41 11 02 14 18 10 02 15 16 0D 01 06 09
   02 17 06 02 07 4E 6F 74 68 69 6E 67 10 02 15 19
   09 02 1A 06 02 03 41 6E 79 10 02 15 1C 09 02 1D
   06 02 0B 53 63 61 6C 61 4F 62 6A 65 63 74 08 08
   1F 00 FFFFFF82 FFFFFF80 FFFFFFA0 FFFFFF80 05 20 01 03 6F 72 64 10 03 21
   29 0F 0E 02 22 27 0E 02 23 26 0D 01 24 0A 02 25
   08 01 06 3C 72 6F 6F 74 3E 09 01 07 09 02 28 06
   01 07 70 61 63 6B 61 67 65 09 02 2A 2B 02 08 4F
   72 64 65 72 69 6E 67 0A 02 28 06 08 05 2D 00 FFFFFF84
   00 2E 01 06 3C 69 6E 69 74 3E 14 01 2F 16 02 30
   31 10 03 0C 00 0F 08 05 1F 2C FFFFFFC0 01 20 08 05 33
   00 FFFFFF84 20 34 01 07 69 73 45 6D 70 74 79 15 01 35
   10 02 15 36 09 02 37 06 02 07 42 6F 6F 6C 65 61
   6E 08 05 39 00 FFFFFF84 20 3A 01 08 24 70 6C 75 73 24
   65 71 14 02 3B 3C 0D 01 00 08 05 3D 38 FFFFFFC0 00 0F
   01 04 65 6C 65 6D 08 05 3F 00 FFFFFF84 00 40 01 0D 24
   70 6C 75 73 24 70 6C 75 73 24 65 71 14 02 3B 41
   08 05 42 3E FFFFFFC0 00 43 01 04 69 74 65 72 10 03 44
   45 0F 0D 01 04 09 02 46 04 02 08 49 74 65 72 61
   62 6C 65 08 05 3F 00 FFFFFF84 20 48 14 02 3B 49 08 05
   4A 47 FFFFFFC0 00 4B 01 02 69 74 10 03 44 4C 0F 09 02
   4D 04 02 08 49 74 65 72 61 74 6F 72 08 05 4F 00
   FFFFFF84 20 50 01 07 65 6E 71 75 65 75 65 14 02 51 54
   10 02 15 52 09 02 53 06 02 04 55 6E 69 74 08 05
   55 4E FFFFFFC0 00 56 01 05 65 6C 65 6D 73 10 03 15 57
   0F 09 02 58 06 02 0A 3C 72 65 70 65 61 74 65 64
   3E 08 05 5A 00 FFFFFF84 20 5B 01 07 64 65 71 75 65 75
   65 14 01 0F 08 05 5D 00 FFFFFF84 20 5E 01 03 6D 61 78
   15 01 0F 08 05 60 00 FFFFFF84 20 61 01 05 63 6C 65 61
   72 14 01 51 08 05 63 00 FFFFFF84 20 64 01 08 69 74 65
   72 61 74 6F 72 15 01 4B 08 05 66 00 FFFFFF84 20 67 01
   06 65 71 75 61 6C 73 14 02 35 68 08 05 69 65 FFFFFFC0
   00 18 01 04 74 68 61 74 08 05 6B 00 FFFFFF84 20 6C 01
   08 74 6F 53 74 72 69 6E 67 14 01 6D 10 02 6E 71
   0E 02 15 6F 09 02 70 06 01 06 50 72 65 64 65 66
   09 02 72 73 02 06 53 74 72 69 6E 67 0A 02 70 06
   
  minor version: 0
  major version: 49
  Constant pool:
const #1 = Asciz	SourceFile;
const #2 = Asciz	SynchronizedPriorityQueue.scala;
const #3 = Asciz	<init>;
const #4 = Asciz	(Lscala/math/Ordering;)V;
const #5 = Asciz	Code;
const #6 = Asciz	LineNumberTable;
const #7 = Asciz	scala/collection/mutable/PriorityQueue;
const #8 = class	#7;	//  scala/collection/mutable/PriorityQueue
const #9 = NameAndType	#3:#4;//  "<init>":(Lscala/math/Ordering;)V
const #10 = Method	#8.#9;	//  scala/collection/mutable/PriorityQueue."<init>":(Lscala/math/Ordering;)V
const #11 = Asciz	this;
const #12 = Asciz	Lscala/collection/mutable/SynchronizedPriorityQueue;;
const #13 = Asciz	ord;
const #14 = Asciz	Lscala/math/Ordering;;
const #15 = Asciz	LocalVariableTable;
const #16 = Asciz	(Lscala/math/Ordering<TA;>;)V;
const #17 = Asciz	Signature;
const #18 = Asciz	$plus$eq;
const #19 = Asciz	(Ljava/lang/Object;)Lscala/collection/mutable/PriorityQueue;;
const #20 = Asciz	scala/collection/mutable/SynchronizedPriorityQueue;
const #21 = class	#20;	//  scala/collection/mutable/SynchronizedPriorityQueue
const #22 = Asciz	(Ljava/lang/Object;)Lscala/collection/mutable/SynchronizedPriorityQueue;;
const #23 = NameAndType	#18:#22;//  $plus$eq:(Ljava/lang/Object;)Lscala/collection/mutable/SynchronizedPriorityQueue;
const #24 = Method	#21.#23;	//  scala/collection/mutable/SynchronizedPriorityQueue.$plus$eq:(Ljava/lang/Object;)Lscala/collection/mutable/SynchronizedPriorityQueue;
const #25 = Asciz	elem;
const #26 = Asciz	Ljava/lang/Object;;
const #27 = Asciz	(Ljava/lang/Object;)Lscala/collection/mutable/Builder;;
const #28 = Asciz	(Ljava/lang/Object;)Lscala/collection/generic/Growable;;
const #29 = Asciz	$plus$plus$eq;
const #30 = Asciz	(Lscala/collection/Iterator;)Lscala/collection/generic/Growable;;
const #31 = Asciz	(Lscala/collection/Iterator;)Lscala/collection/mutable/SynchronizedPriorityQueue;;
const #32 = NameAndType	#29:#31;//  $plus$plus$eq:(Lscala/collection/Iterator;)Lscala/collection/mutable/SynchronizedPriorityQueue;
const #33 = Method	#21.#32;	//  scala/collection/mutable/SynchronizedPriorityQueue.$plus$plus$eq:(Lscala/collection/Iterator;)Lscala/collection/mutable/SynchronizedPriorityQueue;
const #34 = Asciz	iter;
const #35 = Asciz	Lscala/collection/Iterator;;
const #36 = Asciz	toString;
const #37 = Asciz	()Ljava/lang/String;;
const #38 = NameAndType	#36:#37;//  toString:()Ljava/lang/String;
const #39 = Method	#8.#38;	//  scala/collection/mutable/PriorityQueue.toString:()Ljava/lang/String;
const #40 = Asciz	java/lang/String;
const #41 = class	#40;	//  java/lang/String
const #42 = Asciz	java/lang/Throwable;
const #43 = class	#42;	//  java/lang/Throwable
const #44 = Asciz	equals;
const #45 = Asciz	(Ljava/lang/Object;)Z;
const #46 = Asciz	scala/collection/SeqLike$class;
const #47 = class	#46;	//  scala/collection/SeqLike$class
const #48 = Asciz	(Lscala/collection/SeqLike;Ljava/lang/Object;)Z;
const #49 = NameAndType	#44:#48;//  equals:(Lscala/collection/SeqLike;Ljava/lang/Object;)Z
const #50 = Method	#47.#49;	//  scala/collection/SeqLike$class.equals:(Lscala/collection/SeqLike;Ljava/lang/Object;)Z
const #51 = Asciz	that;
const #52 = Asciz	iterator;
const #53 = Asciz	()Lscala/collection/Iterator;;
const #54 = NameAndType	#52:#53;//  iterator:()Lscala/collection/Iterator;
const #55 = Method	#8.#54;	//  scala/collection/mutable/PriorityQueue.iterator:()Lscala/collection/Iterator;
const #56 = Asciz	scala/collection/Iterator;
const #57 = class	#56;	//  scala/collection/Iterator
const #58 = Asciz	()Lscala/collection/Iterator<TA;>;;
const #59 = Asciz	clear;
const #60 = Asciz	()V;
const #61 = NameAndType	#59:#60;//  clear:()V
const #62 = Method	#8.#61;	//  scala/collection/mutable/PriorityQueue.clear:()V
const #63 = Asciz	max;
const #64 = Asciz	()Ljava/lang/Object;;
const #65 = NameAndType	#63:#64;//  max:()Ljava/lang/Object;
const #66 = Method	#8.#65;	//  scala/collection/mutable/PriorityQueue.max:()Ljava/lang/Object;
const #67 = Asciz	()TA;;
const #68 = Asciz	dequeue;
const #69 = NameAndType	#68:#64;//  dequeue:()Ljava/lang/Object;
const #70 = Method	#8.#69;	//  scala/collection/mutable/PriorityQueue.dequeue:()Ljava/lang/Object;
const #71 = Asciz	enqueue;
const #72 = Asciz	(Lscala/collection/Seq;)V;
const #73 = Asciz	scala/collection/generic/Growable$class;
const #74 = class	#73;	//  scala/collection/generic/Growable$class
const #75 = Asciz	(Lscala/collection/generic/Growable;Lscala/collection/Traversable;)Lscala/collection/generic/Growable;;
const #76 = NameAndType	#29:#75;//  $plus$plus$eq:(Lscala/collection/generic/Growable;Lscala/collection/Traversable;)Lscala/collection/generic/Growable;
const #77 = Method	#74.#76;	//  scala/collection/generic/Growable$class.$plus$plus$eq:(Lscala/collection/generic/Growable;Lscala/collection/Traversable;)Lscala/collection/generic/Growable;
const #78 = Asciz	elems;
const #79 = Asciz	Lscala/collection/Seq;;
const #80 = Asciz	(Lscala/collection/Seq<TA;>;)V;
const #81 = Asciz	(Lscala/collection/generic/Growable;Lscala/collection/Iterator;)Lscala/collection/generic/Growable;;
const #82 = NameAndType	#29:#81;//  $plus$plus$eq:(Lscala/collection/generic/Growable;Lscala/collection/Iterator;)Lscala/collection/generic/Growable;
const #83 = Method	#74.#82;	//  scala/collection/generic/Growable$class.$plus$plus$eq:(Lscala/collection/generic/Growable;Lscala/collection/Iterator;)Lscala/collection/generic/Growable;
const #84 = Asciz	it;
const #85 = Asciz	(Lscala/collection/Iterator<TA;>;)Lscala/collection/mutable/SynchronizedPriorityQueue<TA;>;;
const #86 = Asciz	(Lscala/collection/Iterable;)Lscala/collection/mutable/SynchronizedPriorityQueue;;
const #87 = Asciz	Lscala/collection/Iterable;;
const #88 = Asciz	(Lscala/collection/Iterable<TA;>;)Lscala/collection/mutable/SynchronizedPriorityQueue<TA;>;;
const #89 = NameAndType	#18:#19;//  $plus$eq:(Ljava/lang/Object;)Lscala/collection/mutable/PriorityQueue;
const #90 = Method	#8.#89;	//  scala/collection/mutable/PriorityQueue.$plus$eq:(Ljava/lang/Object;)Lscala/collection/mutable/PriorityQueue;
const #91 = Asciz	(TA;)Lscala/collection/mutable/SynchronizedPriorityQueue<TA;>;;
const #92 = Asciz	isEmpty;
const #93 = Asciz	()Z;
const #94 = NameAndType	#92:#93;//  isEmpty:()Z
const #95 = Method	#8.#94;	//  scala/collection/mutable/PriorityQueue.isEmpty:()Z
const #96 = Asciz	<A:Ljava/lang/Object;>Lscala/collection/mutable/PriorityQueue<TA;>;Lscala/ScalaObject;;
const #97 = Asciz	ScalaSig;
const #98 = Asciz	scala/ScalaObject;
const #99 = class	#98;	//  scala/ScalaObject

{
public scala.collection.mutable.SynchronizedPriorityQueue(scala.math.Ordering);
  Code:
   Stack=2, Locals=2, Args_size=2
   0:	aload_0
   1:	aload_1
   2:	invokespecial	#10; //Method scala/collection/mutable/PriorityQueue."<init>":(Lscala/math/Ordering;)V
   5:	return
  LineNumberTable: 
   line 23: 0

  LocalVariableTable: 
   Start  Length  Slot  Name   Signature
   0      6      0    this       Lscala/collection/mutable/SynchronizedPriorityQueue;
   0      6      1    ord       Lscala/math/Ordering;

  Signature: length = 0x2
   00 10 

public scala.collection.mutable.PriorityQueue $plus$eq(java.lang.Object);
  Code:
   Stack=2, Locals=2, Args_size=2
   0:	aload_0
   1:	aload_1
   2:	invokevirtual	#24; //Method $plus$eq:(Ljava/lang/Object;)Lscala/collection/mutable/SynchronizedPriorityQueue;
   5:	areturn
  LineNumberTable: 
   line 23: 0

  LocalVariableTable: 
   Start  Length  Slot  Name   Signature
   0      6      0    this       Lscala/collection/mutable/SynchronizedPriorityQueue;
   0      6      1    elem       Ljava/lang/Object;


public scala.collection.mutable.Builder $plus$eq(java.lang.Object);
  Code:
   Stack=2, Locals=2, Args_size=2
   0:	aload_0
   1:	aload_1
   2:	invokevirtual	#24; //Method $plus$eq:(Ljava/lang/Object;)Lscala/collection/mutable/SynchronizedPriorityQueue;
   5:	areturn
  LineNumberTable: 
   line 23: 0

  LocalVariableTable: 
   Start  Length  Slot  Name   Signature
   0      6      0    this       Lscala/collection/mutable/SynchronizedPriorityQueue;
   0      6      1    elem       Ljava/lang/Object;


public scala.collection.generic.Growable $plus$eq(java.lang.Object);
  Code:
   Stack=2, Locals=2, Args_size=2
   0:	aload_0
   1:	aload_1
   2:	invokevirtual	#24; //Method $plus$eq:(Ljava/lang/Object;)Lscala/collection/mutable/SynchronizedPriorityQueue;
   5:	areturn
  LineNumberTable: 
   line 23: 0

  LocalVariableTable: 
   Start  Length  Slot  Name   Signature
   0      6      0    this       Lscala/collection/mutable/SynchronizedPriorityQueue;
   0      6      1    elem       Ljava/lang/Object;


public scala.collection.generic.Growable $plus$plus$eq(scala.collection.Iterator);
  Code:
   Stack=2, Locals=2, Args_size=2
   0:	aload_0
   1:	aload_1
   2:	invokevirtual	#33; //Method $plus$plus$eq:(Lscala/collection/Iterator;)Lscala/collection/mutable/SynchronizedPriorityQueue;
   5:	areturn
  LineNumberTable: 
   line 23: 0

  LocalVariableTable: 
   Start  Length  Slot  Name   Signature
   0      6      0    this       Lscala/collection/mutable/SynchronizedPriorityQueue;
   0      6      1    iter       Lscala/collection/Iterator;


public java.lang.String toString();
  Code:
   Stack=2, Locals=1, Args_size=1
   0:	aload_0
   1:	dup
   2:	pop
   3:	monitorenter
   4:	aload_0
   5:	invokespecial	#39; //Method scala/collection/mutable/PriorityQueue.toString:()Ljava/lang/String;
   8:	aload_0
   9:	monitorexit
   10:	checkcast	#41; //class java/lang/String
   13:	areturn
   14:	aload_0
   15:	monitorexit
   16:	athrow
  Exception table:
   from   to  target type
     4    10    14   Class java/lang/Throwable

  LineNumberTable: 
   line 107: 0


public boolean equals(java.lang.Object);
  Code:
   Stack=2, Locals=3, Args_size=2
   0:	aload_0
   1:	dup
   2:	pop
   3:	monitorenter
   4:	aload_0
   5:	aload_1
   6:	invokestatic	#50; //Method scala/collection/SeqLike$class.equals:(Lscala/collection/SeqLike;Ljava/lang/Object;)Z
   9:	istore_2
   10:	aload_0
   11:	monitorexit
   12:	iload_2
   13:	ireturn
   14:	aload_0
   15:	monitorexit
   16:	athrow
  Exception table:
   from   to  target type
     4    12    14   Class java/lang/Throwable

  LineNumberTable: 
   line 101: 0

  LocalVariableTable: 
   Start  Length  Slot  Name   Signature
   0      17      0    this       Lscala/collection/mutable/SynchronizedPriorityQueue;
   0      17      1    that       Ljava/lang/Object;


public scala.collection.Iterator iterator();
  Code:
   Stack=2, Locals=1, Args_size=1
   0:	aload_0
   1:	dup
   2:	pop
   3:	monitorenter
   4:	aload_0
   5:	invokespecial	#55; //Method scala/collection/mutable/PriorityQueue.iterator:()Lscala/collection/Iterator;
   8:	aload_0
   9:	monitorexit
   10:	checkcast	#57; //class scala/collection/Iterator
   13:	areturn
   14:	aload_0
   15:	monitorexit
   16:	athrow
  Exception table:
   from   to  target type
     4    10    14   Class java/lang/Throwable

  LineNumberTable: 
   line 95: 0

  Signature: length = 0x2
   00 3A 

public void clear();
  Code:
   Stack=2, Locals=1, Args_size=1
   0:	aload_0
   1:	dup
   2:	pop
   3:	monitorenter
   4:	aload_0
   5:	invokespecial	#62; //Method scala/collection/mutable/PriorityQueue.clear:()V
   8:	aload_0
   9:	monitorexit
   10:	return
   11:	aload_0
   12:	monitorexit
   13:	athrow
  Exception table:
   from   to  target type
     4    10    11   Class java/lang/Throwable

  LineNumberTable: 
   line 88: 0


public java.lang.Object max();
  Code:
   Stack=2, Locals=1, Args_size=1
   0:	aload_0
   1:	dup
   2:	pop
   3:	monitorenter
   4:	aload_0
   5:	invokespecial	#66; //Method scala/collection/mutable/PriorityQueue.max:()Ljava/lang/Object;
   8:	aload_0
   9:	monitorexit
   10:	areturn
   11:	aload_0
   12:	monitorexit
   13:	athrow
  Exception table:
   from   to  target type
     4    10    11   Class java/lang/Throwable

  LineNumberTable: 
   line 83: 0

  Signature: length = 0x2
   00 43 

public java.lang.Object dequeue();
  Code:
   Stack=2, Locals=1, Args_size=1
   0:	aload_0
   1:	dup
   2:	pop
   3:	monitorenter
   4:	aload_0
   5:	invokespecial	#70; //Method scala/collection/mutable/PriorityQueue.dequeue:()Ljava/lang/Object;
   8:	aload_0
   9:	monitorexit
   10:	areturn
   11:	aload_0
   12:	monitorexit
   13:	athrow
  Exception table:
   from   to  target type
     4    10    11   Class java/lang/Throwable

  LineNumberTable: 
   line 76: 0

  Signature: length = 0x2
   00 43 

public void enqueue(scala.collection.Seq);
  Code:
   Stack=2, Locals=2, Args_size=2
   0:	aload_0
   1:	dup
   2:	pop
   3:	monitorenter
   4:	aload_0
   5:	aload_1
   6:	invokestatic	#77; //Method scala/collection/generic/Growable$class.$plus$plus$eq:(Lscala/collection/generic/Growable;Lscala/collection/Traversable;)Lscala/collection/generic/Growable;
   9:	pop
   10:	aload_0
   11:	monitorexit
   12:	return
   13:	aload_0
   14:	monitorexit
   15:	athrow
  Exception table:
   from   to  target type
     4    12    13   Class java/lang/Throwable

  LineNumberTable: 
   line 69: 0

  LocalVariableTable: 
   Start  Length  Slot  Name   Signature
   0      16      0    this       Lscala/collection/mutable/SynchronizedPriorityQueue;
   0      16      1    elems       Lscala/collection/Seq;

  Signature: length = 0x2
   00 50 

public scala.collection.mutable.SynchronizedPriorityQueue $plus$plus$eq(scala.collection.Iterator);
  Code:
   Stack=2, Locals=2, Args_size=2
   0:	aload_0
   1:	dup
   2:	pop
   3:	monitorenter
   4:	aload_0
   5:	aload_1
   6:	invokestatic	#83; //Method scala/collection/generic/Growable$class.$plus$plus$eq:(Lscala/collection/generic/Growable;Lscala/collection/Iterator;)Lscala/collection/generic/Growable;
   9:	pop
   10:	aload_0
   11:	monitorexit
   12:	aload_0
   13:	areturn
   14:	aload_0
   15:	monitorexit
   16:	athrow
  Exception table:
   from   to  target type
     4    12    14   Class java/lang/Throwable

  LineNumberTable: 
   line 59: 0
   line 60: 4
   line 59: 11
   line 62: 12
   line 59: 15

  LocalVariableTable: 
   Start  Length  Slot  Name   Signature
   0      17      0    this       Lscala/collection/mutable/SynchronizedPriorityQueue;
   0      17      1    it       Lscala/collection/Iterator;

  Signature: length = 0x2
   00 55 

public scala.collection.mutable.SynchronizedPriorityQueue $plus$plus$eq(scala.collection.Iterable);
  Code:
   Stack=2, Locals=2, Args_size=2
   0:	aload_0
   1:	dup
   2:	pop
   3:	monitorenter
   4:	aload_0
   5:	aload_1
   6:	invokestatic	#77; //Method scala/collection/generic/Growable$class.$plus$plus$eq:(Lscala/collection/generic/Growable;Lscala/collection/Traversable;)Lscala/collection/generic/Growable;
   9:	pop
   10:	aload_0
   11:	monitorexit
   12:	aload_0
   13:	areturn
   14:	aload_0
   15:	monitorexit
   16:	athrow
  Exception table:
   from   to  target type
     4    12    14   Class java/lang/Throwable

  LineNumberTable: 
   line 48: 0
   line 49: 4
   line 48: 11
   line 51: 12
   line 48: 15

  LocalVariableTable: 
   Start  Length  Slot  Name   Signature
   0      17      0    this       Lscala/collection/mutable/SynchronizedPriorityQueue;
   0      17      1    iter       Lscala/collection/Iterable;

  Signature: length = 0x2
   00 58 

public scala.collection.mutable.SynchronizedPriorityQueue $plus$eq(java.lang.Object);
  Code:
   Stack=2, Locals=2, Args_size=2
   0:	aload_0
   1:	dup
   2:	pop
   3:	monitorenter
   4:	aload_0
   5:	aload_1
   6:	invokespecial	#90; //Method scala/collection/mutable/PriorityQueue.$plus$eq:(Ljava/lang/Object;)Lscala/collection/mutable/PriorityQueue;
   9:	pop
   10:	aload_0
   11:	monitorexit
   12:	aload_0
   13:	areturn
   14:	aload_0
   15:	monitorexit
   16:	athrow
  Exception table:
   from   to  target type
     4    12    14   Class java/lang/Throwable

  LineNumberTable: 
   line 36: 0
   line 37: 4
   line 36: 11
   line 39: 12
   line 36: 15

  LocalVariableTable: 
   Start  Length  Slot  Name   Signature
   0      17      0    this       Lscala/collection/mutable/SynchronizedPriorityQueue;
   0      17      1    elem       Ljava/lang/Object;

  Signature: length = 0x2
   00 5B 

public boolean isEmpty();
  Code:
   Stack=2, Locals=2, Args_size=1
   0:	aload_0
   1:	dup
   2:	pop
   3:	monitorenter
   4:	aload_0
   5:	invokespecial	#95; //Method scala/collection/mutable/PriorityQueue.isEmpty:()Z
   8:	istore_1
   9:	aload_0
   10:	monitorexit
   11:	iload_1
   12:	ireturn
   13:	aload_0
   14:	monitorexit
   15:	athrow
  Exception table:
   from   to  target type
     4    11    13   Class java/lang/Throwable

  LineNumberTable: 
   line 29: 0


}

