Compiled from "SynchronizedStack.scala"
public class scala.collection.mutable.SynchronizedStack extends scala.collection.mutable.Stack implements scala.ScalaObject
  SourceFile: "SynchronizedStack.scala"
  Signature: length = 0x2
   00 6D 
  ScalaSig: length = 0x284
   05 00 6F 06 04 01 02 00 09 02 11 53 79 6E 63 68
   72 6F 6E 69 7A 65 64 53 74 61 63 6B 0A 02 03 04
   01 07 6D 75 74 61 62 6C 65 0A 02 05 06 01 0A 63
   6F 6C 6C 65 63 74 69 6F 6E 0A 01 07 01 05 73 63
   61 6C 61 03 00 15 02 0A 11 13 03 00 0B 1B 10 03
   0C 0D 0F 0D 01 02 09 02 0E 02 02 05 53 74 61 63
   6B 10 02 10 11 0C 00 04 08 12 00 FFFFFF84 FFFFFF80 FFFFFF80 FFFFFFC2 00
   13 02 01 41 11 02 14 18 10 02 15 16 0D 01 06 09
   02 17 06 02 07 4E 6F 74 68 69 6E 67 10 02 15 19
   09 02 1A 06 02 03 41 6E 79 10 02 15 1C 09 02 1D
   06 02 0B 53 63 61 6C 61 4F 62 6A 65 63 74 08 05
   1F 00 FFFFFF84 00 20 01 06 3C 69 6E 69 74 3E 14 01 21
   10 03 0C 00 0F 08 05 23 00 FFFFFF84 20 24 01 07 69 73
   45 6D 70 74 79 15 01 25 10 02 15 26 09 02 27 06
   02 07 42 6F 6F 6C 65 61 6E 08 05 29 00 FFFFFF84 20 2A
   01 04 70 75 73 68 14 02 2B 2C 0D 01 00 08 05 2D
   28 FFFFFFC0 00 0F 01 04 65 6C 65 6D 08 05 29 00 FFFFFF84 20
   2F 14 04 2B 30 32 34 08 05 31 2E FFFFFFC0 00 0F 01 05
   65 6C 65 6D 31 08 05 33 2E FFFFFFC0 00 0F 01 05 65 6C
   65 6D 32 08 05 35 2E FFFFFFC0 00 36 01 05 65 6C 65 6D
   73 10 03 15 37 0F 09 02 38 06 02 0A 3C 72 65 70
   65 61 74 65 64 3E 08 05 3A 00 FFFFFF84 20 3B 01 07 70
   75 73 68 41 6C 6C 14 02 2B 3C 08 05 35 39 FFFFFFC0 00
   3D 10 03 3E 3F 0F 0D 01 04 09 02 40 04 02 0B 54
   72 61 76 65 72 73 61 62 6C 65 08 05 3A 00 FFFFFF84 20
   42 14 02 2B 43 08 05 35 41 FFFFFFC0 00 44 10 03 45 4D
   0F 0E 02 46 4B 0E 02 47 4A 0D 01 48 0A 02 49 08
   01 06 3C 72 6F 6F 74 3E 09 01 07 09 02 4C 06 01
   07 70 61 63 6B 61 67 65 09 02 4E 4F 02 08 49 74
   65 72 61 74 6F 72 0A 02 4C 06 08 05 51 00 FFFFFF84 20
   52 01 03 74 6F 70 15 01 0F 08 05 54 00 FFFFFF84 20 55
   01 03 70 6F 70 14 01 0F 08 05 57 00 FFFFFF84 20 58 01
   05 63 6C 65 61 72 14 01 59 10 02 15 5A 09 02 5B
   06 02 04 55 6E 69 74 08 05 5D 00 FFFFFF84 20 5E 01 08
   69 74 65 72 61 74 6F 72 15 01 44 08 05 60 00 FFFFFF84
   20 61 01 06 74 6F 4C 69 73 74 15 01 62 10 03 45
   63 0F 09 02 64 4F 02 04 4C 69 73 74 08 05 66 00
   FFFFFF84 20 67 01 08 74 6F 53 74 72 69 6E 67 14 01 68
   10 02 69 6C 0E 02 15 6A 09 02 6B 06 01 06 50 72
   65 64 65 66 09 02 6D 6E 02 06 53 74 72 69 6E 67
   0A 02 6B 06 
  minor version: 0
  major version: 49
  Constant pool:
const #1 = Asciz	SourceFile;
const #2 = Asciz	SynchronizedStack.scala;
const #3 = Asciz	<init>;
const #4 = Asciz	()V;
const #5 = Asciz	Code;
const #6 = Asciz	LineNumberTable;
const #7 = Asciz	scala/collection/mutable/Stack;
const #8 = class	#7;	//  scala/collection/mutable/Stack
const #9 = NameAndType	#3:#4;//  "<init>":()V
const #10 = Method	#8.#9;	//  scala/collection/mutable/Stack."<init>":()V
const #11 = Asciz	Signature;
const #12 = Asciz	push;
const #13 = Asciz	(Ljava/lang/Object;)Lscala/collection/mutable/Stack;;
const #14 = Asciz	scala/collection/mutable/SynchronizedStack;
const #15 = class	#14;	//  scala/collection/mutable/SynchronizedStack
const #16 = Asciz	(Ljava/lang/Object;)Lscala/collection/mutable/SynchronizedStack;;
const #17 = NameAndType	#12:#16;//  push:(Ljava/lang/Object;)Lscala/collection/mutable/SynchronizedStack;
const #18 = Method	#15.#17;	//  scala/collection/mutable/SynchronizedStack.push:(Ljava/lang/Object;)Lscala/collection/mutable/SynchronizedStack;
const #19 = Asciz	this;
const #20 = Asciz	Lscala/collection/mutable/SynchronizedStack;;
const #21 = Asciz	elem;
const #22 = Asciz	Ljava/lang/Object;;
const #23 = Asciz	LocalVariableTable;
const #24 = Asciz	(Ljava/lang/Object;Ljava/lang/Object;Lscala/collection/Sequence;)Lscala/collection/mutable/Stack;;
const #25 = Asciz	(Ljava/lang/Object;Ljava/lang/Object;Lscala/collection/Sequence;)Lscala/collection/mutable/SynchronizedStack;;
const #26 = NameAndType	#12:#25;//  push:(Ljava/lang/Object;Ljava/lang/Object;Lscala/collection/Sequence;)Lscala/collection/mutable/SynchronizedStack;
const #27 = Method	#15.#26;	//  scala/collection/mutable/SynchronizedStack.push:(Ljava/lang/Object;Ljava/lang/Object;Lscala/collection/Sequence;)Lscala/collection/mutable/SynchronizedStack;
const #28 = Asciz	elem1;
const #29 = Asciz	elem2;
const #30 = Asciz	elems;
const #31 = Asciz	Lscala/collection/Sequence;;
const #32 = Asciz	pushAll;
const #33 = Asciz	(Lscala/collection/Traversable;)Lscala/collection/mutable/Stack;;
const #34 = Asciz	(Lscala/collection/Traversable;)Lscala/collection/mutable/SynchronizedStack;;
const #35 = NameAndType	#32:#34;//  pushAll:(Lscala/collection/Traversable;)Lscala/collection/mutable/SynchronizedStack;
const #36 = Method	#15.#35;	//  scala/collection/mutable/SynchronizedStack.pushAll:(Lscala/collection/Traversable;)Lscala/collection/mutable/SynchronizedStack;
const #37 = Asciz	Lscala/collection/Traversable;;
const #38 = Asciz	(Lscala/collection/Iterator;)Lscala/collection/mutable/Stack;;
const #39 = Asciz	(Lscala/collection/Iterator;)Lscala/collection/mutable/SynchronizedStack;;
const #40 = NameAndType	#32:#39;//  pushAll:(Lscala/collection/Iterator;)Lscala/collection/mutable/SynchronizedStack;
const #41 = Method	#15.#40;	//  scala/collection/mutable/SynchronizedStack.pushAll:(Lscala/collection/Iterator;)Lscala/collection/mutable/SynchronizedStack;
const #42 = Asciz	Lscala/collection/Iterator;;
const #43 = Asciz	toString;
const #44 = Asciz	()Ljava/lang/String;;
const #45 = Asciz	scala/collection/generic/SequenceTemplate$class;
const #46 = class	#45;	//  scala/collection/generic/SequenceTemplate$class
const #47 = Asciz	(Lscala/collection/generic/SequenceTemplate;)Ljava/lang/String;;
const #48 = NameAndType	#43:#47;//  toString:(Lscala/collection/generic/SequenceTemplate;)Ljava/lang/String;
const #49 = Method	#46.#48;	//  scala/collection/generic/SequenceTemplate$class.toString:(Lscala/collection/generic/SequenceTemplate;)Ljava/lang/String;
const #50 = Asciz	java/lang/String;
const #51 = class	#50;	//  java/lang/String
const #52 = Asciz	toList;
const #53 = Asciz	()Lscala/collection/immutable/List;;
const #54 = NameAndType	#52:#53;//  toList:()Lscala/collection/immutable/List;
const #55 = Method	#8.#54;	//  scala/collection/mutable/Stack.toList:()Lscala/collection/immutable/List;
const #56 = Asciz	scala/collection/immutable/List;
const #57 = class	#56;	//  scala/collection/immutable/List
const #58 = Asciz	()Lscala/collection/immutable/List<TA;>;;
const #59 = Asciz	iterator;
const #60 = Asciz	()Lscala/collection/Iterator;;
const #61 = NameAndType	#59:#60;//  iterator:()Lscala/collection/Iterator;
const #62 = Method	#8.#61;	//  scala/collection/mutable/Stack.iterator:()Lscala/collection/Iterator;
const #63 = Asciz	scala/collection/Iterator;
const #64 = class	#63;	//  scala/collection/Iterator
const #65 = Asciz	()Lscala/collection/Iterator<TA;>;;
const #66 = Asciz	clear;
const #67 = NameAndType	#66:#4;//  clear:()V
const #68 = Method	#8.#67;	//  scala/collection/mutable/Stack.clear:()V
const #69 = Asciz	scala/runtime/BoxedUnit;
const #70 = class	#69;	//  scala/runtime/BoxedUnit
const #71 = Asciz	UNIT;
const #72 = Asciz	Lscala/runtime/BoxedUnit;;
const #73 = NameAndType	#71:#72;//  UNIT:Lscala/runtime/BoxedUnit;
const #74 = Field	#70.#73;	//  scala/runtime/BoxedUnit.UNIT:Lscala/runtime/BoxedUnit;
const #75 = Asciz	pop;
const #76 = Asciz	()Ljava/lang/Object;;
const #77 = NameAndType	#75:#76;//  pop:()Ljava/lang/Object;
const #78 = Method	#8.#77;	//  scala/collection/mutable/Stack.pop:()Ljava/lang/Object;
const #79 = Asciz	()TA;;
const #80 = Asciz	top;
const #81 = NameAndType	#80:#76;//  top:()Ljava/lang/Object;
const #82 = Method	#8.#81;	//  scala/collection/mutable/Stack.top:()Ljava/lang/Object;
const #83 = NameAndType	#32:#38;//  pushAll:(Lscala/collection/Iterator;)Lscala/collection/mutable/Stack;
const #84 = Method	#8.#83;	//  scala/collection/mutable/Stack.pushAll:(Lscala/collection/Iterator;)Lscala/collection/mutable/Stack;
const #85 = Asciz	(Lscala/collection/Iterator<TA;>;)Lscala/collection/mutable/SynchronizedStack<TA;>;;
const #86 = NameAndType	#32:#33;//  pushAll:(Lscala/collection/Traversable;)Lscala/collection/mutable/Stack;
const #87 = Method	#8.#86;	//  scala/collection/mutable/Stack.pushAll:(Lscala/collection/Traversable;)Lscala/collection/mutable/Stack;
const #88 = Asciz	(Lscala/collection/Traversable<TA;>;)Lscala/collection/mutable/SynchronizedStack<TA;>;;
const #89 = NameAndType	#12:#24;//  push:(Ljava/lang/Object;Ljava/lang/Object;Lscala/collection/Sequence;)Lscala/collection/mutable/Stack;
const #90 = Method	#8.#89;	//  scala/collection/mutable/Stack.push:(Ljava/lang/Object;Ljava/lang/Object;Lscala/collection/Sequence;)Lscala/collection/mutable/Stack;
const #91 = Asciz	(TA;TA;Lscala/collection/Sequence<TA;>;)Lscala/collection/mutable/SynchronizedStack<TA;>;;
const #92 = NameAndType	#12:#13;//  push:(Ljava/lang/Object;)Lscala/collection/mutable/Stack;
const #93 = Method	#8.#92;	//  scala/collection/mutable/Stack.push:(Ljava/lang/Object;)Lscala/collection/mutable/Stack;
const #94 = Asciz	(TA;)Lscala/collection/mutable/SynchronizedStack<TA;>;;
const #95 = Asciz	isEmpty;
const #96 = Asciz	()Z;
const #97 = NameAndType	#95:#96;//  isEmpty:()Z
const #98 = Method	#8.#97;	//  scala/collection/mutable/Stack.isEmpty:()Z
const #99 = Asciz	scala/runtime/BoxesRunTime;
const #100 = class	#99;	//  scala/runtime/BoxesRunTime
const #101 = Asciz	boxToBoolean;
const #102 = Asciz	(Z)Ljava/lang/Boolean;;
const #103 = NameAndType	#101:#102;//  boxToBoolean:(Z)Ljava/lang/Boolean;
const #104 = Method	#100.#103;	//  scala/runtime/BoxesRunTime.boxToBoolean:(Z)Ljava/lang/Boolean;
const #105 = Asciz	unboxToBoolean;
const #106 = Asciz	(Ljava/lang/Object;)Z;
const #107 = NameAndType	#105:#106;//  unboxToBoolean:(Ljava/lang/Object;)Z
const #108 = Method	#100.#107;	//  scala/runtime/BoxesRunTime.unboxToBoolean:(Ljava/lang/Object;)Z
const #109 = Asciz	<A:Ljava/lang/Object;>Lscala/collection/mutable/Stack<TA;>;Lscala/ScalaObject;;
const #110 = Asciz	ScalaSig;
const #111 = Asciz	scala/ScalaObject;
const #112 = class	#111;	//  scala/ScalaObject

{
public scala.collection.mutable.SynchronizedStack();
  Code:
   Stack=1, Locals=1, Args_size=1
   0:	aload_0
   1:	invokespecial	#10; //Method scala/collection/mutable/Stack."<init>":()V
   4:	return
  LineNumberTable: 
   line 22: 0

  Signature: length = 0x2
   00 04 

public scala.collection.mutable.Stack push(java.lang.Object);
  Code:
   Stack=2, Locals=2, Args_size=2
   0:	aload_0
   1:	aload_1
   2:	invokevirtual	#18; //Method push:(Ljava/lang/Object;)Lscala/collection/mutable/SynchronizedStack;
   5:	areturn
  LineNumberTable: 
   line 22: 0

  LocalVariableTable: 
   Start  Length  Slot  Name   Signature
   0      6      0    this       Lscala/collection/mutable/SynchronizedStack;
   0      6      1    elem       Ljava/lang/Object;


public scala.collection.mutable.Stack push(java.lang.Object, java.lang.Object, scala.collection.Sequence);
  Code:
   Stack=4, Locals=4, Args_size=4
   0:	aload_0
   1:	aload_1
   2:	aload_2
   3:	aload_3
   4:	invokevirtual	#27; //Method push:(Ljava/lang/Object;Ljava/lang/Object;Lscala/collection/Sequence;)Lscala/collection/mutable/SynchronizedStack;
   7:	areturn
  LineNumberTable: 
   line 22: 0

  LocalVariableTable: 
   Start  Length  Slot  Name   Signature
   0      8      0    this       Lscala/collection/mutable/SynchronizedStack;
   0      8      1    elem1       Ljava/lang/Object;
   0      8      2    elem2       Ljava/lang/Object;
   0      8      3    elems       Lscala/collection/Sequence;


public scala.collection.mutable.Stack pushAll(scala.collection.Traversable);
  Code:
   Stack=2, Locals=2, Args_size=2
   0:	aload_0
   1:	aload_1
   2:	invokevirtual	#36; //Method pushAll:(Lscala/collection/Traversable;)Lscala/collection/mutable/SynchronizedStack;
   5:	areturn
  LineNumberTable: 
   line 22: 0

  LocalVariableTable: 
   Start  Length  Slot  Name   Signature
   0      6      0    this       Lscala/collection/mutable/SynchronizedStack;
   0      6      1    elems       Lscala/collection/Traversable;


public scala.collection.mutable.Stack pushAll(scala.collection.Iterator);
  Code:
   Stack=2, Locals=2, Args_size=2
   0:	aload_0
   1:	aload_1
   2:	invokevirtual	#41; //Method pushAll:(Lscala/collection/Iterator;)Lscala/collection/mutable/SynchronizedStack;
   5:	areturn
  LineNumberTable: 
   line 22: 0

  LocalVariableTable: 
   Start  Length  Slot  Name   Signature
   0      6      0    this       Lscala/collection/mutable/SynchronizedStack;
   0      6      1    elems       Lscala/collection/Iterator;


public java.lang.String toString();
  Code:
   Stack=2, Locals=2, Args_size=1
   0:	aload_0
   1:	dup
   2:	astore_1
   3:	monitorenter
   4:	aload_0
   5:	invokestatic	#49; //Method scala/collection/generic/SequenceTemplate$class.toString:(Lscala/collection/generic/SequenceTemplate;)Ljava/lang/String;
   8:	aload_1
   9:	monitorexit
   10:	checkcast	#51; //class java/lang/String
   13:	areturn
   14:	aload_1
   15:	monitorexit
   16:	athrow
  Exception table:
   from   to  target type
     4    10    14   any
  LineNumberTable: 
   line 99: 0


public scala.collection.immutable.List toList();
  Code:
   Stack=2, Locals=2, Args_size=1
   0:	aload_0
   1:	dup
   2:	astore_1
   3:	monitorenter
   4:	aload_0
   5:	invokespecial	#55; //Method scala/collection/mutable/Stack.toList:()Lscala/collection/immutable/List;
   8:	aload_1
   9:	monitorexit
   10:	checkcast	#57; //class scala/collection/immutable/List
   13:	areturn
   14:	aload_1
   15:	monitorexit
   16:	athrow
  Exception table:
   from   to  target type
     4    10    14   any
  LineNumberTable: 
   line 93: 0

  Signature: length = 0x2
   00 3A 

public scala.collection.Iterator iterator();
  Code:
   Stack=2, Locals=2, Args_size=1
   0:	aload_0
   1:	dup
   2:	astore_1
   3:	monitorenter
   4:	aload_0
   5:	invokespecial	#62; //Method scala/collection/mutable/Stack.iterator:()Lscala/collection/Iterator;
   8:	aload_1
   9:	monitorexit
   10:	checkcast	#64; //class scala/collection/Iterator
   13:	areturn
   14:	aload_1
   15:	monitorexit
   16:	athrow
  Exception table:
   from   to  target type
     4    10    14   any
  LineNumberTable: 
   line 87: 0

  Signature: length = 0x2
   00 41 

public void clear();
  Code:
   Stack=2, Locals=2, Args_size=1
   0:	aload_0
   1:	dup
   2:	astore_1
   3:	monitorenter
   4:	aload_0
   5:	invokespecial	#68; //Method scala/collection/mutable/Stack.clear:()V
   8:	getstatic	#74; //Field scala/runtime/BoxedUnit.UNIT:Lscala/runtime/BoxedUnit;
   11:	pop
   12:	aload_1
   13:	monitorexit
   14:	return
   15:	aload_1
   16:	monitorexit
   17:	athrow
  Exception table:
   from   to  target type
     4    14    15   any
  LineNumberTable: 
   line 77: 0


public java.lang.Object pop();
  Code:
   Stack=2, Locals=2, Args_size=1
   0:	aload_0
   1:	dup
   2:	astore_1
   3:	monitorenter
   4:	aload_0
   5:	invokespecial	#78; //Method scala/collection/mutable/Stack.pop:()Ljava/lang/Object;
   8:	aload_1
   9:	monitorexit
   10:	areturn
   11:	aload_1
   12:	monitorexit
   13:	athrow
  Exception table:
   from   to  target type
     4    10    11   any
  LineNumberTable: 
   line 71: 0

  Signature: length = 0x2
   00 4F 

public java.lang.Object top();
  Code:
   Stack=2, Locals=2, Args_size=1
   0:	aload_0
   1:	dup
   2:	astore_1
   3:	monitorenter
   4:	aload_0
   5:	invokespecial	#82; //Method scala/collection/mutable/Stack.top:()Ljava/lang/Object;
   8:	aload_1
   9:	monitorexit
   10:	areturn
   11:	aload_1
   12:	monitorexit
   13:	athrow
  Exception table:
   from   to  target type
     4    10    11   any
  LineNumberTable: 
   line 67: 0

  Signature: length = 0x2
   00 4F 

public scala.collection.mutable.SynchronizedStack pushAll(scala.collection.Iterator);
  Code:
   Stack=2, Locals=3, Args_size=2
   0:	aload_0
   1:	dup
   2:	astore_2
   3:	monitorenter
   4:	aload_0
   5:	aload_1
   6:	invokespecial	#84; //Method scala/collection/mutable/Stack.pushAll:(Lscala/collection/Iterator;)Lscala/collection/mutable/Stack;
   9:	aload_2
   10:	monitorexit
   11:	checkcast	#15; //class scala/collection/mutable/SynchronizedStack
   14:	areturn
   15:	aload_2
   16:	monitorexit
   17:	athrow
  Exception table:
   from   to  target type
     4    11    15   any
  LineNumberTable: 
   line 59: 0

  LocalVariableTable: 
   Start  Length  Slot  Name   Signature
   0      18      0    this       Lscala/collection/mutable/SynchronizedStack;
   0      18      1    elems       Lscala/collection/Iterator;

  Signature: length = 0x2
   00 55 

public scala.collection.mutable.SynchronizedStack pushAll(scala.collection.Traversable);
  Code:
   Stack=2, Locals=3, Args_size=2
   0:	aload_0
   1:	dup
   2:	astore_2
   3:	monitorenter
   4:	aload_0
   5:	aload_1
   6:	invokespecial	#87; //Method scala/collection/mutable/Stack.pushAll:(Lscala/collection/Traversable;)Lscala/collection/mutable/Stack;
   9:	aload_2
   10:	monitorexit
   11:	checkcast	#15; //class scala/collection/mutable/SynchronizedStack
   14:	areturn
   15:	aload_2
   16:	monitorexit
   17:	athrow
  Exception table:
   from   to  target type
     4    11    15   any
  LineNumberTable: 
   line 51: 0

  LocalVariableTable: 
   Start  Length  Slot  Name   Signature
   0      18      0    this       Lscala/collection/mutable/SynchronizedStack;
   0      18      1    elems       Lscala/collection/Traversable;

  Signature: length = 0x2
   00 58 

public scala.collection.mutable.SynchronizedStack push(java.lang.Object, java.lang.Object, scala.collection.Sequence);
  Code:
   Stack=4, Locals=5, Args_size=4
   0:	aload_0
   1:	dup
   2:	astore	4
   4:	monitorenter
   5:	aload_0
   6:	aload_1
   7:	aload_2
   8:	aload_3
   9:	invokespecial	#90; //Method scala/collection/mutable/Stack.push:(Ljava/lang/Object;Ljava/lang/Object;Lscala/collection/Sequence;)Lscala/collection/mutable/Stack;
   12:	aload	4
   14:	monitorexit
   15:	checkcast	#15; //class scala/collection/mutable/SynchronizedStack
   18:	areturn
   19:	aload	4
   21:	monitorexit
   22:	athrow
  Exception table:
   from   to  target type
     5    15    19   any
  LineNumberTable: 
   line 43: 0

  LocalVariableTable: 
   Start  Length  Slot  Name   Signature
   0      23      0    this       Lscala/collection/mutable/SynchronizedStack;
   0      23      1    elem1       Ljava/lang/Object;
   0      23      2    elem2       Ljava/lang/Object;
   0      23      3    elems       Lscala/collection/Sequence;

  Signature: length = 0x2
   00 5B 

public scala.collection.mutable.SynchronizedStack push(java.lang.Object);
  Code:
   Stack=2, Locals=3, Args_size=2
   0:	aload_0
   1:	dup
   2:	astore_2
   3:	monitorenter
   4:	aload_0
   5:	aload_1
   6:	invokespecial	#93; //Method scala/collection/mutable/Stack.push:(Ljava/lang/Object;)Lscala/collection/mutable/Stack;
   9:	aload_2
   10:	monitorexit
   11:	checkcast	#15; //class scala/collection/mutable/SynchronizedStack
   14:	areturn
   15:	aload_2
   16:	monitorexit
   17:	athrow
  Exception table:
   from   to  target type
     4    11    15   any
  LineNumberTable: 
   line 35: 0

  LocalVariableTable: 
   Start  Length  Slot  Name   Signature
   0      18      0    this       Lscala/collection/mutable/SynchronizedStack;
   0      18      1    elem       Ljava/lang/Object;

  Signature: length = 0x2
   00 5E 

public boolean isEmpty();
  Code:
   Stack=2, Locals=2, Args_size=1
   0:	aload_0
   1:	dup
   2:	astore_1
   3:	monitorenter
   4:	aload_0
   5:	invokespecial	#98; //Method scala/collection/mutable/Stack.isEmpty:()Z
   8:	invokestatic	#104; //Method scala/runtime/BoxesRunTime.boxToBoolean:(Z)Ljava/lang/Boolean;
   11:	aload_1
   12:	monitorexit
   13:	invokestatic	#108; //Method scala/runtime/BoxesRunTime.unboxToBoolean:(Ljava/lang/Object;)Z
   16:	ireturn
   17:	aload_1
   18:	monitorexit
   19:	athrow
  Exception table:
   from   to  target type
     4    13    17   any
  LineNumberTable: 
   line 29: 0


}

