Compiled from "SynchronizedSet.scala"
public abstract class scala.collection.mutable.SynchronizedSet$class extends java.lang.Object
  SourceFile: "SynchronizedSet.scala"
  Scala: length = 0x
   
  minor version: 0
  major version: 49
  Constant pool:
const #1 = Asciz	SourceFile;
const #2 = Asciz	SynchronizedSet.scala;
const #3 = Asciz	$init$;
const #4 = Asciz	(Lscala/collection/mutable/SynchronizedSet;)V;
const #5 = Asciz	Code;
const #6 = Asciz	LineNumberTable;
const #7 = Asciz	$this;
const #8 = Asciz	Lscala/collection/mutable/SynchronizedSet;;
const #9 = Asciz	LocalVariableTable;
const #10 = Asciz	clone;
const #11 = Asciz	(Lscala/collection/mutable/SynchronizedSet;)Lscala/collection/mutable/Set;;
const #12 = Asciz	scala/collection/mutable/SynchronizedSet;
const #13 = class	#12;	//  scala/collection/mutable/SynchronizedSet
const #14 = Asciz	scala$collection$mutable$SynchronizedSet$$super$clone;
const #15 = Asciz	()Lscala/collection/mutable/Set;;
const #16 = NameAndType	#14:#15;//  scala$collection$mutable$SynchronizedSet$$super$clone:()Lscala/collection/mutable/Set;
const #17 = InterfaceMethod	#13.#16;	//  scala/collection/mutable/SynchronizedSet.scala$collection$mutable$SynchronizedSet$$super$clone:()Lscala/collection/mutable/Set;
const #18 = Asciz	scala/collection/mutable/Set;
const #19 = class	#18;	//  scala/collection/mutable/Set
const #20 = Asciz	toString;
const #21 = Asciz	(Lscala/collection/mutable/SynchronizedSet;)Ljava/lang/String;;
const #22 = Asciz	scala$collection$mutable$SynchronizedSet$$super$toString;
const #23 = Asciz	()Ljava/lang/String;;
const #24 = NameAndType	#22:#23;//  scala$collection$mutable$SynchronizedSet$$super$toString:()Ljava/lang/String;
const #25 = InterfaceMethod	#13.#24;	//  scala/collection/mutable/SynchronizedSet.scala$collection$mutable$SynchronizedSet$$super$toString:()Ljava/lang/String;
const #26 = Asciz	java/lang/String;
const #27 = class	#26;	//  java/lang/String
const #28 = Asciz	toList;
const #29 = Asciz	(Lscala/collection/mutable/SynchronizedSet;)Lscala/collection/immutable/List;;
const #30 = Asciz	scala$collection$mutable$SynchronizedSet$$super$toList;
const #31 = Asciz	()Lscala/collection/immutable/List;;
const #32 = NameAndType	#30:#31;//  scala$collection$mutable$SynchronizedSet$$super$toList:()Lscala/collection/immutable/List;
const #33 = InterfaceMethod	#13.#32;	//  scala/collection/mutable/SynchronizedSet.scala$collection$mutable$SynchronizedSet$$super$toList:()Lscala/collection/immutable/List;
const #34 = Asciz	scala/collection/immutable/List;
const #35 = class	#34;	//  scala/collection/immutable/List
const #36 = Asciz	retain;
const #37 = Asciz	(Lscala/collection/mutable/SynchronizedSet;Lscala/Function1;)V;
const #38 = Asciz	scala$collection$mutable$SynchronizedSet$$super$retain;
const #39 = Asciz	(Lscala/Function1;)V;
const #40 = NameAndType	#38:#39;//  scala$collection$mutable$SynchronizedSet$$super$retain:(Lscala/Function1;)V
const #41 = InterfaceMethod	#13.#40;	//  scala/collection/mutable/SynchronizedSet.scala$collection$mutable$SynchronizedSet$$super$retain:(Lscala/Function1;)V
const #42 = Asciz	scala/runtime/BoxedUnit;
const #43 = class	#42;	//  scala/runtime/BoxedUnit
const #44 = Asciz	UNIT;
const #45 = Asciz	Lscala/runtime/BoxedUnit;;
const #46 = NameAndType	#44:#45;//  UNIT:Lscala/runtime/BoxedUnit;
const #47 = Field	#43.#46;	//  scala/runtime/BoxedUnit.UNIT:Lscala/runtime/BoxedUnit;
const #48 = Asciz	p;
const #49 = Asciz	Lscala/Function1;;
const #50 = Asciz	foreach;
const #51 = Asciz	scala$collection$mutable$SynchronizedSet$$super$foreach;
const #52 = NameAndType	#51:#39;//  scala$collection$mutable$SynchronizedSet$$super$foreach:(Lscala/Function1;)V
const #53 = InterfaceMethod	#13.#52;	//  scala/collection/mutable/SynchronizedSet.scala$collection$mutable$SynchronizedSet$$super$foreach:(Lscala/Function1;)V
const #54 = Asciz	f;
const #55 = Asciz	subsetOf;
const #56 = Asciz	(Lscala/collection/mutable/SynchronizedSet;Lscala/collection/Set;)Z;
const #57 = Asciz	scala$collection$mutable$SynchronizedSet$$super$subsetOf;
const #58 = Asciz	(Lscala/collection/Set;)Z;
const #59 = NameAndType	#57:#58;//  scala$collection$mutable$SynchronizedSet$$super$subsetOf:(Lscala/collection/Set;)Z
const #60 = InterfaceMethod	#13.#59;	//  scala/collection/mutable/SynchronizedSet.scala$collection$mutable$SynchronizedSet$$super$subsetOf:(Lscala/collection/Set;)Z
const #61 = Asciz	scala/runtime/BoxesRunTime;
const #62 = class	#61;	//  scala/runtime/BoxesRunTime
const #63 = Asciz	boxToBoolean;
const #64 = Asciz	(Z)Ljava/lang/Boolean;;
const #65 = NameAndType	#63:#64;//  boxToBoolean:(Z)Ljava/lang/Boolean;
const #66 = Method	#62.#65;	//  scala/runtime/BoxesRunTime.boxToBoolean:(Z)Ljava/lang/Boolean;
const #67 = Asciz	unboxToBoolean;
const #68 = Asciz	(Ljava/lang/Object;)Z;
const #69 = NameAndType	#67:#68;//  unboxToBoolean:(Ljava/lang/Object;)Z
const #70 = Method	#62.#69;	//  scala/runtime/BoxesRunTime.unboxToBoolean:(Ljava/lang/Object;)Z
const #71 = Asciz	that;
const #72 = Asciz	Lscala/collection/Set;;
const #73 = Asciz	clear;
const #74 = Asciz	scala$collection$mutable$SynchronizedSet$$super$clear;
const #75 = Asciz	()V;
const #76 = NameAndType	#74:#75;//  scala$collection$mutable$SynchronizedSet$$super$clear:()V
const #77 = InterfaceMethod	#13.#76;	//  scala/collection/mutable/SynchronizedSet.scala$collection$mutable$SynchronizedSet$$super$clear:()V
const #78 = Asciz	intersect;
const #79 = Asciz	(Lscala/collection/mutable/SynchronizedSet;Lscala/collection/Set;)Lscala/collection/mutable/Set;;
const #80 = Asciz	scala$collection$mutable$SynchronizedSet$$super$intersect;
const #81 = Asciz	(Lscala/collection/Set;)Lscala/collection/mutable/Set;;
const #82 = NameAndType	#80:#81;//  scala$collection$mutable$SynchronizedSet$$super$intersect:(Lscala/collection/Set;)Lscala/collection/mutable/Set;
const #83 = InterfaceMethod	#13.#82;	//  scala/collection/mutable/SynchronizedSet.scala$collection$mutable$SynchronizedSet$$super$intersect:(Lscala/collection/Set;)Lscala/collection/mutable/Set;
const #84 = Asciz	remove;
const #85 = Asciz	(Lscala/collection/mutable/SynchronizedSet;Ljava/lang/Object;)Z;
const #86 = Asciz	scala$collection$mutable$SynchronizedSet$$super$remove;
const #87 = NameAndType	#86:#68;//  scala$collection$mutable$SynchronizedSet$$super$remove:(Ljava/lang/Object;)Z
const #88 = InterfaceMethod	#13.#87;	//  scala/collection/mutable/SynchronizedSet.scala$collection$mutable$SynchronizedSet$$super$remove:(Ljava/lang/Object;)Z
const #89 = Asciz	elem;
const #90 = Asciz	Ljava/lang/Object;;
const #91 = Asciz	add;
const #92 = Asciz	scala$collection$mutable$SynchronizedSet$$super$add;
const #93 = NameAndType	#92:#68;//  scala$collection$mutable$SynchronizedSet$$super$add:(Ljava/lang/Object;)Z
const #94 = InterfaceMethod	#13.#93;	//  scala/collection/mutable/SynchronizedSet.scala$collection$mutable$SynchronizedSet$$super$add:(Ljava/lang/Object;)Z
const #95 = Asciz	update;
const #96 = Asciz	(Lscala/collection/mutable/SynchronizedSet;Ljava/lang/Object;Z)V;
const #97 = Asciz	scala$collection$mutable$SynchronizedSet$$super$update;
const #98 = Asciz	(Ljava/lang/Object;Z)V;
const #99 = NameAndType	#97:#98;//  scala$collection$mutable$SynchronizedSet$$super$update:(Ljava/lang/Object;Z)V
const #100 = InterfaceMethod	#13.#99;	//  scala/collection/mutable/SynchronizedSet.scala$collection$mutable$SynchronizedSet$$super$update:(Ljava/lang/Object;Z)V
const #101 = Asciz	included;
const #102 = Asciz	Z;
const #103 = Asciz	$minus$minus$eq;
const #104 = Asciz	(Lscala/collection/mutable/SynchronizedSet;Lscala/collection/Iterator;)Lscala/collection/mutable/SynchronizedSet;;
const #105 = Asciz	scala$collection$mutable$SynchronizedSet$$super$$minus$minus$eq;
const #106 = Asciz	(Lscala/collection/Iterator;)Lscala/collection/mutable/SynchronizedSet;;
const #107 = NameAndType	#105:#106;//  scala$collection$mutable$SynchronizedSet$$super$$minus$minus$eq:(Lscala/collection/Iterator;)Lscala/collection/mutable/SynchronizedSet;
const #108 = InterfaceMethod	#13.#107;	//  scala/collection/mutable/SynchronizedSet.scala$collection$mutable$SynchronizedSet$$super$$minus$minus$eq:(Lscala/collection/Iterator;)Lscala/collection/mutable/SynchronizedSet;
const #109 = Asciz	it;
const #110 = Asciz	Lscala/collection/Iterator;;
const #111 = Asciz	(Lscala/collection/mutable/SynchronizedSet;Lscala/collection/Traversable;)Lscala/collection/mutable/SynchronizedSet;;
const #112 = Asciz	(Lscala/collection/Traversable;)Lscala/collection/mutable/SynchronizedSet;;
const #113 = NameAndType	#105:#112;//  scala$collection$mutable$SynchronizedSet$$super$$minus$minus$eq:(Lscala/collection/Traversable;)Lscala/collection/mutable/SynchronizedSet;
const #114 = InterfaceMethod	#13.#113;	//  scala/collection/mutable/SynchronizedSet.scala$collection$mutable$SynchronizedSet$$super$$minus$minus$eq:(Lscala/collection/Traversable;)Lscala/collection/mutable/SynchronizedSet;
const #115 = Asciz	Lscala/collection/Traversable;;
const #116 = Asciz	$minus$eq;
const #117 = Asciz	(Lscala/collection/mutable/SynchronizedSet;Ljava/lang/Object;)Lscala/collection/mutable/SynchronizedSet;;
const #118 = Asciz	scala$collection$mutable$SynchronizedSet$$super$$minus$eq;
const #119 = Asciz	(Ljava/lang/Object;)Lscala/collection/mutable/SynchronizedSet;;
const #120 = NameAndType	#118:#119;//  scala$collection$mutable$SynchronizedSet$$super$$minus$eq:(Ljava/lang/Object;)Lscala/collection/mutable/SynchronizedSet;
const #121 = InterfaceMethod	#13.#120;	//  scala/collection/mutable/SynchronizedSet.scala$collection$mutable$SynchronizedSet$$super$$minus$eq:(Ljava/lang/Object;)Lscala/collection/mutable/SynchronizedSet;
const #122 = Asciz	$plus$plus$eq;
const #123 = Asciz	scala$collection$mutable$SynchronizedSet$$super$$plus$plus$eq;
const #124 = NameAndType	#123:#106;//  scala$collection$mutable$SynchronizedSet$$super$$plus$plus$eq:(Lscala/collection/Iterator;)Lscala/collection/mutable/SynchronizedSet;
const #125 = InterfaceMethod	#13.#124;	//  scala/collection/mutable/SynchronizedSet.scala$collection$mutable$SynchronizedSet$$super$$plus$plus$eq:(Lscala/collection/Iterator;)Lscala/collection/mutable/SynchronizedSet;
const #126 = NameAndType	#123:#112;//  scala$collection$mutable$SynchronizedSet$$super$$plus$plus$eq:(Lscala/collection/Traversable;)Lscala/collection/mutable/SynchronizedSet;
const #127 = InterfaceMethod	#13.#126;	//  scala/collection/mutable/SynchronizedSet.scala$collection$mutable$SynchronizedSet$$super$$plus$plus$eq:(Lscala/collection/Traversable;)Lscala/collection/mutable/SynchronizedSet;
const #128 = Asciz	$plus$eq;
const #129 = Asciz	scala$collection$mutable$SynchronizedSet$$super$$plus$eq;
const #130 = NameAndType	#129:#119;//  scala$collection$mutable$SynchronizedSet$$super$$plus$eq:(Ljava/lang/Object;)Lscala/collection/mutable/SynchronizedSet;
const #131 = InterfaceMethod	#13.#130;	//  scala/collection/mutable/SynchronizedSet.scala$collection$mutable$SynchronizedSet$$super$$plus$eq:(Ljava/lang/Object;)Lscala/collection/mutable/SynchronizedSet;
const #132 = Asciz	contains;
const #133 = Asciz	scala$collection$mutable$SynchronizedSet$$super$contains;
const #134 = NameAndType	#133:#68;//  scala$collection$mutable$SynchronizedSet$$super$contains:(Ljava/lang/Object;)Z
const #135 = InterfaceMethod	#13.#134;	//  scala/collection/mutable/SynchronizedSet.scala$collection$mutable$SynchronizedSet$$super$contains:(Ljava/lang/Object;)Z
const #136 = Asciz	isEmpty;
const #137 = Asciz	(Lscala/collection/mutable/SynchronizedSet;)Z;
const #138 = Asciz	scala$collection$mutable$SynchronizedSet$$super$isEmpty;
const #139 = Asciz	()Z;
const #140 = NameAndType	#138:#139;//  scala$collection$mutable$SynchronizedSet$$super$isEmpty:()Z
const #141 = InterfaceMethod	#13.#140;	//  scala/collection/mutable/SynchronizedSet.scala$collection$mutable$SynchronizedSet$$super$isEmpty:()Z
const #142 = Asciz	size;
const #143 = Asciz	(Lscala/collection/mutable/SynchronizedSet;)I;
const #144 = Asciz	scala$collection$mutable$SynchronizedSet$$super$size;
const #145 = Asciz	()I;
const #146 = NameAndType	#144:#145;//  scala$collection$mutable$SynchronizedSet$$super$size:()I
const #147 = InterfaceMethod	#13.#146;	//  scala/collection/mutable/SynchronizedSet.scala$collection$mutable$SynchronizedSet$$super$size:()I
const #148 = Asciz	boxToInteger;
const #149 = Asciz	(I)Ljava/lang/Integer;;
const #150 = NameAndType	#148:#149;//  boxToInteger:(I)Ljava/lang/Integer;
const #151 = Method	#62.#150;	//  scala/runtime/BoxesRunTime.boxToInteger:(I)Ljava/lang/Integer;
const #152 = Asciz	unboxToInt;
const #153 = Asciz	(Ljava/lang/Object;)I;
const #154 = NameAndType	#152:#153;//  unboxToInt:(Ljava/lang/Object;)I
const #155 = Method	#62.#154;	//  scala/runtime/BoxesRunTime.unboxToInt:(Ljava/lang/Object;)I
const #156 = Asciz	Scala;
const #157 = Asciz	scala/collection/mutable/SynchronizedSet$class;
const #158 = class	#157;	//  scala/collection/mutable/SynchronizedSet$class
const #159 = Asciz	java/lang/Object;
const #160 = class	#159;	//  java/lang/Object

{
public static void $init$(scala.collection.mutable.SynchronizedSet);
  Code:
   Stack=0, Locals=1, Args_size=1
   0:	return
  LineNumberTable: 
   line 21: 0

  LocalVariableTable: 
   Start  Length  Slot  Name   Signature
   0      1      0    $this       Lscala/collection/mutable/SynchronizedSet;


public static scala.collection.mutable.Set clone(scala.collection.mutable.SynchronizedSet);
  Code:
   Stack=2, Locals=2, Args_size=1
   0:	aload_0
   1:	dup
   2:	astore_1
   3:	monitorenter
   4:	aload_0
   5:	invokeinterface	#17,  1; //InterfaceMethod scala/collection/mutable/SynchronizedSet.scala$collection$mutable$SynchronizedSet$$super$clone:()Lscala/collection/mutable/Set;
   10:	aload_1
   11:	monitorexit
   12:	checkcast	#19; //class scala/collection/mutable/Set
   15:	areturn
   16:	aload_1
   17:	monitorexit
   18:	athrow
  Exception table:
   from   to  target type
     4    12    16   any
  LineNumberTable: 
   line 105: 0
   line 106: 4
   line 105: 11

  LocalVariableTable: 
   Start  Length  Slot  Name   Signature
   0      19      0    $this       Lscala/collection/mutable/SynchronizedSet;


public static java.lang.String toString(scala.collection.mutable.SynchronizedSet);
  Code:
   Stack=2, Locals=2, Args_size=1
   0:	aload_0
   1:	dup
   2:	astore_1
   3:	monitorenter
   4:	aload_0
   5:	invokeinterface	#25,  1; //InterfaceMethod scala/collection/mutable/SynchronizedSet.scala$collection$mutable$SynchronizedSet$$super$toString:()Ljava/lang/String;
   10:	aload_1
   11:	monitorexit
   12:	checkcast	#27; //class java/lang/String
   15:	areturn
   16:	aload_1
   17:	monitorexit
   18:	athrow
  Exception table:
   from   to  target type
     4    12    16   any
  LineNumberTable: 
   line 96: 0
   line 97: 4
   line 96: 11

  LocalVariableTable: 
   Start  Length  Slot  Name   Signature
   0      19      0    $this       Lscala/collection/mutable/SynchronizedSet;


public static scala.collection.immutable.List toList(scala.collection.mutable.SynchronizedSet);
  Code:
   Stack=2, Locals=2, Args_size=1
   0:	aload_0
   1:	dup
   2:	astore_1
   3:	monitorenter
   4:	aload_0
   5:	invokeinterface	#33,  1; //InterfaceMethod scala/collection/mutable/SynchronizedSet.scala$collection$mutable$SynchronizedSet$$super$toList:()Lscala/collection/immutable/List;
   10:	aload_1
   11:	monitorexit
   12:	checkcast	#35; //class scala/collection/immutable/List
   15:	areturn
   16:	aload_1
   17:	monitorexit
   18:	athrow
  Exception table:
   from   to  target type
     4    12    16   any
  LineNumberTable: 
   line 92: 0
   line 93: 4
   line 92: 11

  LocalVariableTable: 
   Start  Length  Slot  Name   Signature
   0      19      0    $this       Lscala/collection/mutable/SynchronizedSet;


public static void retain(scala.collection.mutable.SynchronizedSet, scala.Function1);
  Code:
   Stack=2, Locals=3, Args_size=2
   0:	aload_0
   1:	dup
   2:	astore_2
   3:	monitorenter
   4:	aload_0
   5:	aload_1
   6:	invokeinterface	#41,  2; //InterfaceMethod scala/collection/mutable/SynchronizedSet.scala$collection$mutable$SynchronizedSet$$super$retain:(Lscala/Function1;)V
   11:	getstatic	#47; //Field scala/runtime/BoxedUnit.UNIT:Lscala/runtime/BoxedUnit;
   14:	pop
   15:	aload_2
   16:	monitorexit
   17:	return
   18:	aload_2
   19:	monitorexit
   20:	athrow
  Exception table:
   from   to  target type
     4    17    18   any
  LineNumberTable: 
   line 88: 0
   line 89: 4
   line 88: 16

  LocalVariableTable: 
   Start  Length  Slot  Name   Signature
   0      21      0    $this       Lscala/collection/mutable/SynchronizedSet;
   0      21      1    p       Lscala/Function1;


public static void foreach(scala.collection.mutable.SynchronizedSet, scala.Function1);
  Code:
   Stack=2, Locals=3, Args_size=2
   0:	aload_0
   1:	dup
   2:	astore_2
   3:	monitorenter
   4:	aload_0
   5:	aload_1
   6:	invokeinterface	#53,  2; //InterfaceMethod scala/collection/mutable/SynchronizedSet.scala$collection$mutable$SynchronizedSet$$super$foreach:(Lscala/Function1;)V
   11:	getstatic	#47; //Field scala/runtime/BoxedUnit.UNIT:Lscala/runtime/BoxedUnit;
   14:	pop
   15:	aload_2
   16:	monitorexit
   17:	return
   18:	aload_2
   19:	monitorexit
   20:	athrow
  Exception table:
   from   to  target type
     4    17    18   any
  LineNumberTable: 
   line 84: 0
   line 85: 4
   line 84: 16

  LocalVariableTable: 
   Start  Length  Slot  Name   Signature
   0      21      0    $this       Lscala/collection/mutable/SynchronizedSet;
   0      21      1    f       Lscala/Function1;


public static boolean subsetOf(scala.collection.mutable.SynchronizedSet, scala.collection.Set);
  Code:
   Stack=2, Locals=3, Args_size=2
   0:	aload_0
   1:	dup
   2:	astore_2
   3:	monitorenter
   4:	aload_0
   5:	aload_1
   6:	invokeinterface	#60,  2; //InterfaceMethod scala/collection/mutable/SynchronizedSet.scala$collection$mutable$SynchronizedSet$$super$subsetOf:(Lscala/collection/Set;)Z
   11:	invokestatic	#66; //Method scala/runtime/BoxesRunTime.boxToBoolean:(Z)Ljava/lang/Boolean;
   14:	aload_2
   15:	monitorexit
   16:	invokestatic	#70; //Method scala/runtime/BoxesRunTime.unboxToBoolean:(Ljava/lang/Object;)Z
   19:	ireturn
   20:	aload_2
   21:	monitorexit
   22:	athrow
  Exception table:
   from   to  target type
     4    16    20   any
  LineNumberTable: 
   line 80: 0
   line 81: 4
   line 80: 15

  LocalVariableTable: 
   Start  Length  Slot  Name   Signature
   0      23      0    $this       Lscala/collection/mutable/SynchronizedSet;
   0      23      1    that       Lscala/collection/Set;


public static void clear(scala.collection.mutable.SynchronizedSet);
  Code:
   Stack=2, Locals=2, Args_size=1
   0:	aload_0
   1:	dup
   2:	astore_1
   3:	monitorenter
   4:	aload_0
   5:	invokeinterface	#77,  1; //InterfaceMethod scala/collection/mutable/SynchronizedSet.scala$collection$mutable$SynchronizedSet$$super$clear:()V
   10:	getstatic	#47; //Field scala/runtime/BoxedUnit.UNIT:Lscala/runtime/BoxedUnit;
   13:	pop
   14:	aload_1
   15:	monitorexit
   16:	return
   17:	aload_1
   18:	monitorexit
   19:	athrow
  Exception table:
   from   to  target type
     4    16    17   any
  LineNumberTable: 
   line 76: 0
   line 77: 4
   line 76: 15

  LocalVariableTable: 
   Start  Length  Slot  Name   Signature
   0      20      0    $this       Lscala/collection/mutable/SynchronizedSet;


public static scala.collection.mutable.Set intersect(scala.collection.mutable.SynchronizedSet, scala.collection.Set);
  Code:
   Stack=2, Locals=3, Args_size=2
   0:	aload_0
   1:	dup
   2:	astore_2
   3:	monitorenter
   4:	aload_0
   5:	aload_1
   6:	invokeinterface	#83,  2; //InterfaceMethod scala/collection/mutable/SynchronizedSet.scala$collection$mutable$SynchronizedSet$$super$intersect:(Lscala/collection/Set;)Lscala/collection/mutable/Set;
   11:	aload_2
   12:	monitorexit
   13:	checkcast	#19; //class scala/collection/mutable/Set
   16:	areturn
   17:	aload_2
   18:	monitorexit
   19:	athrow
  Exception table:
   from   to  target type
     4    13    17   any
  LineNumberTable: 
   line 72: 0
   line 73: 4
   line 72: 12

  LocalVariableTable: 
   Start  Length  Slot  Name   Signature
   0      20      0    $this       Lscala/collection/mutable/SynchronizedSet;
   0      20      1    that       Lscala/collection/Set;


public static boolean remove(scala.collection.mutable.SynchronizedSet, java.lang.Object);
  Code:
   Stack=2, Locals=3, Args_size=2
   0:	aload_0
   1:	dup
   2:	astore_2
   3:	monitorenter
   4:	aload_0
   5:	aload_1
   6:	invokeinterface	#88,  2; //InterfaceMethod scala/collection/mutable/SynchronizedSet.scala$collection$mutable$SynchronizedSet$$super$remove:(Ljava/lang/Object;)Z
   11:	invokestatic	#66; //Method scala/runtime/BoxesRunTime.boxToBoolean:(Z)Ljava/lang/Boolean;
   14:	aload_2
   15:	monitorexit
   16:	invokestatic	#70; //Method scala/runtime/BoxesRunTime.unboxToBoolean:(Ljava/lang/Object;)Z
   19:	ireturn
   20:	aload_2
   21:	monitorexit
   22:	athrow
  Exception table:
   from   to  target type
     4    16    20   any
  LineNumberTable: 
   line 68: 0
   line 69: 4
   line 68: 15

  LocalVariableTable: 
   Start  Length  Slot  Name   Signature
   0      23      0    $this       Lscala/collection/mutable/SynchronizedSet;
   0      23      1    elem       Ljava/lang/Object;


public static boolean add(scala.collection.mutable.SynchronizedSet, java.lang.Object);
  Code:
   Stack=2, Locals=3, Args_size=2
   0:	aload_0
   1:	dup
   2:	astore_2
   3:	monitorenter
   4:	aload_0
   5:	aload_1
   6:	invokeinterface	#94,  2; //InterfaceMethod scala/collection/mutable/SynchronizedSet.scala$collection$mutable$SynchronizedSet$$super$add:(Ljava/lang/Object;)Z
   11:	invokestatic	#66; //Method scala/runtime/BoxesRunTime.boxToBoolean:(Z)Ljava/lang/Boolean;
   14:	aload_2
   15:	monitorexit
   16:	invokestatic	#70; //Method scala/runtime/BoxesRunTime.unboxToBoolean:(Ljava/lang/Object;)Z
   19:	ireturn
   20:	aload_2
   21:	monitorexit
   22:	athrow
  Exception table:
   from   to  target type
     4    16    20   any
  LineNumberTable: 
   line 64: 0
   line 65: 4
   line 64: 15

  LocalVariableTable: 
   Start  Length  Slot  Name   Signature
   0      23      0    $this       Lscala/collection/mutable/SynchronizedSet;
   0      23      1    elem       Ljava/lang/Object;


public static void update(scala.collection.mutable.SynchronizedSet, java.lang.Object, boolean);
  Code:
   Stack=3, Locals=4, Args_size=3
   0:	aload_0
   1:	dup
   2:	astore_3
   3:	monitorenter
   4:	aload_0
   5:	aload_1
   6:	iload_2
   7:	invokeinterface	#100,  3; //InterfaceMethod scala/collection/mutable/SynchronizedSet.scala$collection$mutable$SynchronizedSet$$super$update:(Ljava/lang/Object;Z)V
   12:	getstatic	#47; //Field scala/runtime/BoxedUnit.UNIT:Lscala/runtime/BoxedUnit;
   15:	pop
   16:	aload_3
   17:	monitorexit
   18:	return
   19:	aload_3
   20:	monitorexit
   21:	athrow
  Exception table:
   from   to  target type
     4    18    19   any
  LineNumberTable: 
   line 60: 0
   line 61: 4
   line 60: 17

  LocalVariableTable: 
   Start  Length  Slot  Name   Signature
   0      22      0    $this       Lscala/collection/mutable/SynchronizedSet;
   0      22      1    elem       Ljava/lang/Object;
   0      22      2    included       Z


public static scala.collection.mutable.SynchronizedSet $minus$minus$eq(scala.collection.mutable.SynchronizedSet, scala.collection.Iterator);
  Code:
   Stack=2, Locals=3, Args_size=2
   0:	aload_0
   1:	dup
   2:	astore_2
   3:	monitorenter
   4:	aload_0
   5:	aload_1
   6:	invokeinterface	#108,  2; //InterfaceMethod scala/collection/mutable/SynchronizedSet.scala$collection$mutable$SynchronizedSet$$super$$minus$minus$eq:(Lscala/collection/Iterator;)Lscala/collection/mutable/SynchronizedSet;
   11:	aload_2
   12:	monitorexit
   13:	checkcast	#13; //class scala/collection/mutable/SynchronizedSet
   16:	areturn
   17:	aload_2
   18:	monitorexit
   19:	athrow
  Exception table:
   from   to  target type
     4    13    17   any
  LineNumberTable: 
   line 56: 0
   line 57: 4
   line 56: 12

  LocalVariableTable: 
   Start  Length  Slot  Name   Signature
   0      20      0    $this       Lscala/collection/mutable/SynchronizedSet;
   0      20      1    it       Lscala/collection/Iterator;


public static scala.collection.mutable.SynchronizedSet $minus$minus$eq(scala.collection.mutable.SynchronizedSet, scala.collection.Traversable);
  Code:
   Stack=2, Locals=3, Args_size=2
   0:	aload_0
   1:	dup
   2:	astore_2
   3:	monitorenter
   4:	aload_0
   5:	aload_1
   6:	invokeinterface	#114,  2; //InterfaceMethod scala/collection/mutable/SynchronizedSet.scala$collection$mutable$SynchronizedSet$$super$$minus$minus$eq:(Lscala/collection/Traversable;)Lscala/collection/mutable/SynchronizedSet;
   11:	aload_2
   12:	monitorexit
   13:	checkcast	#13; //class scala/collection/mutable/SynchronizedSet
   16:	areturn
   17:	aload_2
   18:	monitorexit
   19:	athrow
  Exception table:
   from   to  target type
     4    13    17   any
  LineNumberTable: 
   line 52: 0
   line 53: 4
   line 52: 12

  LocalVariableTable: 
   Start  Length  Slot  Name   Signature
   0      20      0    $this       Lscala/collection/mutable/SynchronizedSet;
   0      20      1    that       Lscala/collection/Traversable;


public static scala.collection.mutable.SynchronizedSet $minus$eq(scala.collection.mutable.SynchronizedSet, java.lang.Object);
  Code:
   Stack=2, Locals=3, Args_size=2
   0:	aload_0
   1:	dup
   2:	astore_2
   3:	monitorenter
   4:	aload_0
   5:	aload_1
   6:	invokeinterface	#121,  2; //InterfaceMethod scala/collection/mutable/SynchronizedSet.scala$collection$mutable$SynchronizedSet$$super$$minus$eq:(Ljava/lang/Object;)Lscala/collection/mutable/SynchronizedSet;
   11:	aload_2
   12:	monitorexit
   13:	checkcast	#13; //class scala/collection/mutable/SynchronizedSet
   16:	areturn
   17:	aload_2
   18:	monitorexit
   19:	athrow
  Exception table:
   from   to  target type
     4    13    17   any
  LineNumberTable: 
   line 48: 0
   line 49: 4
   line 48: 12

  LocalVariableTable: 
   Start  Length  Slot  Name   Signature
   0      20      0    $this       Lscala/collection/mutable/SynchronizedSet;
   0      20      1    elem       Ljava/lang/Object;


public static scala.collection.mutable.SynchronizedSet $plus$plus$eq(scala.collection.mutable.SynchronizedSet, scala.collection.Iterator);
  Code:
   Stack=2, Locals=3, Args_size=2
   0:	aload_0
   1:	dup
   2:	astore_2
   3:	monitorenter
   4:	aload_0
   5:	aload_1
   6:	invokeinterface	#125,  2; //InterfaceMethod scala/collection/mutable/SynchronizedSet.scala$collection$mutable$SynchronizedSet$$super$$plus$plus$eq:(Lscala/collection/Iterator;)Lscala/collection/mutable/SynchronizedSet;
   11:	aload_2
   12:	monitorexit
   13:	checkcast	#13; //class scala/collection/mutable/SynchronizedSet
   16:	areturn
   17:	aload_2
   18:	monitorexit
   19:	athrow
  Exception table:
   from   to  target type
     4    13    17   any
  LineNumberTable: 
   line 44: 0
   line 45: 4
   line 44: 12

  LocalVariableTable: 
   Start  Length  Slot  Name   Signature
   0      20      0    $this       Lscala/collection/mutable/SynchronizedSet;
   0      20      1    it       Lscala/collection/Iterator;


public static scala.collection.mutable.SynchronizedSet $plus$plus$eq(scala.collection.mutable.SynchronizedSet, scala.collection.Traversable);
  Code:
   Stack=2, Locals=3, Args_size=2
   0:	aload_0
   1:	dup
   2:	astore_2
   3:	monitorenter
   4:	aload_0
   5:	aload_1
   6:	invokeinterface	#127,  2; //InterfaceMethod scala/collection/mutable/SynchronizedSet.scala$collection$mutable$SynchronizedSet$$super$$plus$plus$eq:(Lscala/collection/Traversable;)Lscala/collection/mutable/SynchronizedSet;
   11:	aload_2
   12:	monitorexit
   13:	checkcast	#13; //class scala/collection/mutable/SynchronizedSet
   16:	areturn
   17:	aload_2
   18:	monitorexit
   19:	athrow
  Exception table:
   from   to  target type
     4    13    17   any
  LineNumberTable: 
   line 40: 0
   line 41: 4
   line 40: 12

  LocalVariableTable: 
   Start  Length  Slot  Name   Signature
   0      20      0    $this       Lscala/collection/mutable/SynchronizedSet;
   0      20      1    that       Lscala/collection/Traversable;


public static scala.collection.mutable.SynchronizedSet $plus$eq(scala.collection.mutable.SynchronizedSet, java.lang.Object);
  Code:
   Stack=2, Locals=3, Args_size=2
   0:	aload_0
   1:	dup
   2:	astore_2
   3:	monitorenter
   4:	aload_0
   5:	aload_1
   6:	invokeinterface	#131,  2; //InterfaceMethod scala/collection/mutable/SynchronizedSet.scala$collection$mutable$SynchronizedSet$$super$$plus$eq:(Ljava/lang/Object;)Lscala/collection/mutable/SynchronizedSet;
   11:	aload_2
   12:	monitorexit
   13:	checkcast	#13; //class scala/collection/mutable/SynchronizedSet
   16:	areturn
   17:	aload_2
   18:	monitorexit
   19:	athrow
  Exception table:
   from   to  target type
     4    13    17   any
  LineNumberTable: 
   line 36: 0
   line 37: 4
   line 36: 12

  LocalVariableTable: 
   Start  Length  Slot  Name   Signature
   0      20      0    $this       Lscala/collection/mutable/SynchronizedSet;
   0      20      1    elem       Ljava/lang/Object;


public static boolean contains(scala.collection.mutable.SynchronizedSet, java.lang.Object);
  Code:
   Stack=2, Locals=3, Args_size=2
   0:	aload_0
   1:	dup
   2:	astore_2
   3:	monitorenter
   4:	aload_0
   5:	aload_1
   6:	invokeinterface	#135,  2; //InterfaceMethod scala/collection/mutable/SynchronizedSet.scala$collection$mutable$SynchronizedSet$$super$contains:(Ljava/lang/Object;)Z
   11:	invokestatic	#66; //Method scala/runtime/BoxesRunTime.boxToBoolean:(Z)Ljava/lang/Boolean;
   14:	aload_2
   15:	monitorexit
   16:	invokestatic	#70; //Method scala/runtime/BoxesRunTime.unboxToBoolean:(Ljava/lang/Object;)Z
   19:	ireturn
   20:	aload_2
   21:	monitorexit
   22:	athrow
  Exception table:
   from   to  target type
     4    16    20   any
  LineNumberTable: 
   line 32: 0
   line 33: 4
   line 32: 15

  LocalVariableTable: 
   Start  Length  Slot  Name   Signature
   0      23      0    $this       Lscala/collection/mutable/SynchronizedSet;
   0      23      1    elem       Ljava/lang/Object;


public static boolean isEmpty(scala.collection.mutable.SynchronizedSet);
  Code:
   Stack=2, Locals=2, Args_size=1
   0:	aload_0
   1:	dup
   2:	astore_1
   3:	monitorenter
   4:	aload_0
   5:	invokeinterface	#141,  1; //InterfaceMethod scala/collection/mutable/SynchronizedSet.scala$collection$mutable$SynchronizedSet$$super$isEmpty:()Z
   10:	invokestatic	#66; //Method scala/runtime/BoxesRunTime.boxToBoolean:(Z)Ljava/lang/Boolean;
   13:	aload_1
   14:	monitorexit
   15:	invokestatic	#70; //Method scala/runtime/BoxesRunTime.unboxToBoolean:(Ljava/lang/Object;)Z
   18:	ireturn
   19:	aload_1
   20:	monitorexit
   21:	athrow
  Exception table:
   from   to  target type
     4    15    19   any
  LineNumberTable: 
   line 28: 0
   line 29: 4
   line 28: 14

  LocalVariableTable: 
   Start  Length  Slot  Name   Signature
   0      22      0    $this       Lscala/collection/mutable/SynchronizedSet;


public static int size(scala.collection.mutable.SynchronizedSet);
  Code:
   Stack=2, Locals=2, Args_size=1
   0:	aload_0
   1:	dup
   2:	astore_1
   3:	monitorenter
   4:	aload_0
   5:	invokeinterface	#147,  1; //InterfaceMethod scala/collection/mutable/SynchronizedSet.scala$collection$mutable$SynchronizedSet$$super$size:()I
   10:	invokestatic	#151; //Method scala/runtime/BoxesRunTime.boxToInteger:(I)Ljava/lang/Integer;
   13:	aload_1
   14:	monitorexit
   15:	invokestatic	#155; //Method scala/runtime/BoxesRunTime.unboxToInt:(Ljava/lang/Object;)I
   18:	ireturn
   19:	aload_1
   20:	monitorexit
   21:	athrow
  Exception table:
   from   to  target type
     4    15    19   any
  LineNumberTable: 
   line 24: 0
   line 25: 4
   line 24: 14

  LocalVariableTable: 
   Start  Length  Slot  Name   Signature
   0      22      0    $this       Lscala/collection/mutable/SynchronizedSet;


}

