Compiled from "SynchronizedMap.scala"
public abstract class scala.collection.mutable.SynchronizedMap$class extends java.lang.Object
  SourceFile: "SynchronizedMap.scala"
  Scala: length = 0x
   
  minor version: 0
  major version: 49
  Constant pool:
const #1 = Asciz	SourceFile;
const #2 = Asciz	SynchronizedMap.scala;
const #3 = Asciz	$init$;
const #4 = Asciz	(Lscala/collection/mutable/SynchronizedMap;)V;
const #5 = Asciz	Code;
const #6 = Asciz	LineNumberTable;
const #7 = Asciz	$this;
const #8 = Asciz	Lscala/collection/mutable/SynchronizedMap;;
const #9 = Asciz	LocalVariableTable;
const #10 = Asciz	$plus;
const #11 = Asciz	(Lscala/collection/mutable/SynchronizedMap;Lscala/Tuple2;)Lscala/collection/mutable/SynchronizedMap;;
const #12 = Asciz	scala/collection/mutable/SynchronizedMap;
const #13 = class	#12;	//  scala/collection/mutable/SynchronizedMap
const #14 = Asciz	scala$collection$mutable$SynchronizedMap$$super$$plus;
const #15 = Asciz	(Lscala/Tuple2;)Lscala/collection/mutable/SynchronizedMap;;
const #16 = NameAndType	#14:#15;//  scala$collection$mutable$SynchronizedMap$$super$$plus:(Lscala/Tuple2;)Lscala/collection/mutable/SynchronizedMap;
const #17 = InterfaceMethod	#13.#16;	//  scala/collection/mutable/SynchronizedMap.scala$collection$mutable$SynchronizedMap$$super$$plus:(Lscala/Tuple2;)Lscala/collection/mutable/SynchronizedMap;
const #18 = Asciz	kv;
const #19 = Asciz	Lscala/Tuple2;;
const #20 = Asciz	isDefinedAt;
const #21 = Asciz	(Lscala/collection/mutable/SynchronizedMap;Ljava/lang/Object;)Z;
const #22 = Asciz	scala$collection$mutable$SynchronizedMap$$super$isDefinedAt;
const #23 = Asciz	(Ljava/lang/Object;)Z;
const #24 = NameAndType	#22:#23;//  scala$collection$mutable$SynchronizedMap$$super$isDefinedAt:(Ljava/lang/Object;)Z
const #25 = InterfaceMethod	#13.#24;	//  scala/collection/mutable/SynchronizedMap.scala$collection$mutable$SynchronizedMap$$super$isDefinedAt:(Ljava/lang/Object;)Z
const #26 = Asciz	scala/runtime/BoxesRunTime;
const #27 = class	#26;	//  scala/runtime/BoxesRunTime
const #28 = Asciz	boxToBoolean;
const #29 = Asciz	(Z)Ljava/lang/Boolean;;
const #30 = NameAndType	#28:#29;//  boxToBoolean:(Z)Ljava/lang/Boolean;
const #31 = Method	#27.#30;	//  scala/runtime/BoxesRunTime.boxToBoolean:(Z)Ljava/lang/Boolean;
const #32 = Asciz	unboxToBoolean;
const #33 = NameAndType	#32:#23;//  unboxToBoolean:(Ljava/lang/Object;)Z
const #34 = Method	#27.#33;	//  scala/runtime/BoxesRunTime.unboxToBoolean:(Ljava/lang/Object;)Z
const #35 = Asciz	key;
const #36 = Asciz	Ljava/lang/Object;;
const #37 = Asciz	contains;
const #38 = Asciz	scala$collection$mutable$SynchronizedMap$$super$contains;
const #39 = NameAndType	#38:#23;//  scala$collection$mutable$SynchronizedMap$$super$contains:(Ljava/lang/Object;)Z
const #40 = InterfaceMethod	#13.#39;	//  scala/collection/mutable/SynchronizedMap.scala$collection$mutable$SynchronizedMap$$super$contains:(Ljava/lang/Object;)Z
const #41 = Asciz	isEmpty;
const #42 = Asciz	(Lscala/collection/mutable/SynchronizedMap;)Z;
const #43 = Asciz	scala$collection$mutable$SynchronizedMap$$super$isEmpty;
const #44 = Asciz	()Z;
const #45 = NameAndType	#43:#44;//  scala$collection$mutable$SynchronizedMap$$super$isEmpty:()Z
const #46 = InterfaceMethod	#13.#45;	//  scala/collection/mutable/SynchronizedMap.scala$collection$mutable$SynchronizedMap$$super$isEmpty:()Z
const #47 = Asciz	keysIterator;
const #48 = Asciz	(Lscala/collection/mutable/SynchronizedMap;)Lscala/collection/Iterator;;
const #49 = Asciz	scala$collection$mutable$SynchronizedMap$$super$keysIterator;
const #50 = Asciz	()Lscala/collection/Iterator;;
const #51 = NameAndType	#49:#50;//  scala$collection$mutable$SynchronizedMap$$super$keysIterator:()Lscala/collection/Iterator;
const #52 = InterfaceMethod	#13.#51;	//  scala/collection/mutable/SynchronizedMap.scala$collection$mutable$SynchronizedMap$$super$keysIterator:()Lscala/collection/Iterator;
const #53 = Asciz	scala/collection/Iterator;
const #54 = class	#53;	//  scala/collection/Iterator
const #55 = Asciz	keys;
const #56 = Asciz	keySet;
const #57 = Asciz	(Lscala/collection/mutable/SynchronizedMap;)Lscala/collection/Set;;
const #58 = Asciz	scala$collection$mutable$SynchronizedMap$$super$keySet;
const #59 = Asciz	()Lscala/collection/Set;;
const #60 = NameAndType	#58:#59;//  scala$collection$mutable$SynchronizedMap$$super$keySet:()Lscala/collection/Set;
const #61 = InterfaceMethod	#13.#60;	//  scala/collection/mutable/SynchronizedMap.scala$collection$mutable$SynchronizedMap$$super$keySet:()Lscala/collection/Set;
const #62 = Asciz	scala/collection/Set;
const #63 = class	#62;	//  scala/collection/Set
const #64 = Asciz	apply;
const #65 = Asciz	(Lscala/collection/mutable/SynchronizedMap;Ljava/lang/Object;)Ljava/lang/Object;;
const #66 = Asciz	scala$collection$mutable$SynchronizedMap$$super$apply;
const #67 = Asciz	(Ljava/lang/Object;)Ljava/lang/Object;;
const #68 = NameAndType	#66:#67;//  scala$collection$mutable$SynchronizedMap$$super$apply:(Ljava/lang/Object;)Ljava/lang/Object;
const #69 = InterfaceMethod	#13.#68;	//  scala/collection/mutable/SynchronizedMap.scala$collection$mutable$SynchronizedMap$$super$apply:(Ljava/lang/Object;)Ljava/lang/Object;
const #70 = Asciz	foreach;
const #71 = Asciz	(Lscala/collection/mutable/SynchronizedMap;Lscala/Function1;)V;
const #72 = Asciz	scala$collection$mutable$SynchronizedMap$$super$foreach;
const #73 = Asciz	(Lscala/Function1;)V;
const #74 = NameAndType	#72:#73;//  scala$collection$mutable$SynchronizedMap$$super$foreach:(Lscala/Function1;)V
const #75 = InterfaceMethod	#13.#74;	//  scala/collection/mutable/SynchronizedMap.scala$collection$mutable$SynchronizedMap$$super$foreach:(Lscala/Function1;)V
const #76 = Asciz	scala/runtime/BoxedUnit;
const #77 = class	#76;	//  scala/runtime/BoxedUnit
const #78 = Asciz	UNIT;
const #79 = Asciz	Lscala/runtime/BoxedUnit;;
const #80 = NameAndType	#78:#79;//  UNIT:Lscala/runtime/BoxedUnit;
const #81 = Field	#77.#80;	//  scala/runtime/BoxedUnit.UNIT:Lscala/runtime/BoxedUnit;
const #82 = Asciz	f;
const #83 = Asciz	Lscala/Function1;;
const #84 = Asciz	clone;
const #85 = Asciz	(Lscala/collection/mutable/SynchronizedMap;)Lscala/collection/mutable/Map;;
const #86 = Asciz	scala$collection$mutable$SynchronizedMap$$super$clone;
const #87 = Asciz	()Lscala/collection/mutable/Map;;
const #88 = NameAndType	#86:#87;//  scala$collection$mutable$SynchronizedMap$$super$clone:()Lscala/collection/mutable/Map;
const #89 = InterfaceMethod	#13.#88;	//  scala/collection/mutable/SynchronizedMap.scala$collection$mutable$SynchronizedMap$$super$clone:()Lscala/collection/mutable/Map;
const #90 = Asciz	scala/collection/mutable/Map;
const #91 = class	#90;	//  scala/collection/mutable/Map
const #92 = Asciz	valuesIterator;
const #93 = Asciz	scala$collection$mutable$SynchronizedMap$$super$valuesIterator;
const #94 = NameAndType	#93:#50;//  scala$collection$mutable$SynchronizedMap$$super$valuesIterator:()Lscala/collection/Iterator;
const #95 = InterfaceMethod	#13.#94;	//  scala/collection/mutable/SynchronizedMap.scala$collection$mutable$SynchronizedMap$$super$valuesIterator:()Lscala/collection/Iterator;
const #96 = Asciz	values;
const #97 = Asciz	valueIterable;
const #98 = Asciz	(Lscala/collection/mutable/SynchronizedMap;)Lscala/collection/Iterable;;
const #99 = Asciz	scala$collection$mutable$SynchronizedMap$$super$valueIterable;
const #100 = Asciz	()Lscala/collection/Iterable;;
const #101 = NameAndType	#99:#100;//  scala$collection$mutable$SynchronizedMap$$super$valueIterable:()Lscala/collection/Iterable;
const #102 = InterfaceMethod	#13.#101;	//  scala/collection/mutable/SynchronizedMap.scala$collection$mutable$SynchronizedMap$$super$valueIterable:()Lscala/collection/Iterable;
const #103 = Asciz	scala/collection/Iterable;
const #104 = class	#103;	//  scala/collection/Iterable
const #105 = Asciz	scala/runtime/ScalaRunTime$;
const #106 = class	#105;	//  scala/runtime/ScalaRunTime$
const #107 = Asciz	MODULE$;
const #108 = Asciz	Lscala/runtime/ScalaRunTime$;;
const #109 = NameAndType	#107:#108;//  MODULE$:Lscala/runtime/ScalaRunTime$;
const #110 = Field	#106.#109;	//  scala/runtime/ScalaRunTime$.MODULE$:Lscala/runtime/ScalaRunTime$;
const #111 = Asciz	boxArray;
const #112 = Asciz	(Ljava/lang/Object;)Lscala/runtime/BoxedArray;;
const #113 = NameAndType	#111:#112;//  boxArray:(Ljava/lang/Object;)Lscala/runtime/BoxedArray;
const #114 = Method	#106.#113;	//  scala/runtime/ScalaRunTime$.boxArray:(Ljava/lang/Object;)Lscala/runtime/BoxedArray;
const #115 = Asciz	retain;
const #116 = Asciz	(Lscala/collection/mutable/SynchronizedMap;Lscala/Function2;)Lscala/collection/mutable/SynchronizedMap;;
const #117 = Asciz	scala$collection$mutable$SynchronizedMap$$super$retain;
const #118 = Asciz	(Lscala/Function2;)Lscala/collection/mutable/SynchronizedMap;;
const #119 = NameAndType	#117:#118;//  scala$collection$mutable$SynchronizedMap$$super$retain:(Lscala/Function2;)Lscala/collection/mutable/SynchronizedMap;
const #120 = InterfaceMethod	#13.#119;	//  scala/collection/mutable/SynchronizedMap.scala$collection$mutable$SynchronizedMap$$super$retain:(Lscala/Function2;)Lscala/collection/mutable/SynchronizedMap;
const #121 = Asciz	p;
const #122 = Asciz	Lscala/Function2;;
const #123 = Asciz	transform;
const #124 = Asciz	scala$collection$mutable$SynchronizedMap$$super$transform;
const #125 = NameAndType	#124:#118;//  scala$collection$mutable$SynchronizedMap$$super$transform:(Lscala/Function2;)Lscala/collection/mutable/SynchronizedMap;
const #126 = InterfaceMethod	#13.#125;	//  scala/collection/mutable/SynchronizedMap.scala$collection$mutable$SynchronizedMap$$super$transform:(Lscala/Function2;)Lscala/collection/mutable/SynchronizedMap;
const #127 = Asciz	getOrElseUpdate;
const #128 = Asciz	(Lscala/collection/mutable/SynchronizedMap;Ljava/lang/Object;Lscala/Function0;)Ljava/lang/Object;;
const #129 = Asciz	scala$collection$mutable$SynchronizedMap$$super$getOrElseUpdate;
const #130 = Asciz	(Ljava/lang/Object;Lscala/Function0;)Ljava/lang/Object;;
const #131 = NameAndType	#129:#130;//  scala$collection$mutable$SynchronizedMap$$super$getOrElseUpdate:(Ljava/lang/Object;Lscala/Function0;)Ljava/lang/Object;
const #132 = InterfaceMethod	#13.#131;	//  scala/collection/mutable/SynchronizedMap.scala$collection$mutable$SynchronizedMap$$super$getOrElseUpdate:(Ljava/lang/Object;Lscala/Function0;)Ljava/lang/Object;
const #133 = Asciz	default;
const #134 = Asciz	Lscala/Function0;;
const #135 = Asciz	clear;
const #136 = Asciz	scala$collection$mutable$SynchronizedMap$$super$clear;
const #137 = Asciz	()V;
const #138 = NameAndType	#136:#137;//  scala$collection$mutable$SynchronizedMap$$super$clear:()V
const #139 = InterfaceMethod	#13.#138;	//  scala/collection/mutable/SynchronizedMap.scala$collection$mutable$SynchronizedMap$$super$clear:()V
const #140 = Asciz	remove;
const #141 = Asciz	(Lscala/collection/mutable/SynchronizedMap;Ljava/lang/Object;)Lscala/Option;;
const #142 = Asciz	scala$collection$mutable$SynchronizedMap$$super$remove;
const #143 = Asciz	(Ljava/lang/Object;)Lscala/Option;;
const #144 = NameAndType	#142:#143;//  scala$collection$mutable$SynchronizedMap$$super$remove:(Ljava/lang/Object;)Lscala/Option;
const #145 = InterfaceMethod	#13.#144;	//  scala/collection/mutable/SynchronizedMap.scala$collection$mutable$SynchronizedMap$$super$remove:(Ljava/lang/Object;)Lscala/Option;
const #146 = Asciz	scala/Option;
const #147 = class	#146;	//  scala/Option
const #148 = Asciz	update;
const #149 = Asciz	(Lscala/collection/mutable/SynchronizedMap;Ljava/lang/Object;Ljava/lang/Object;)V;
const #150 = Asciz	scala$collection$mutable$SynchronizedMap$$super$update;
const #151 = Asciz	(Ljava/lang/Object;Ljava/lang/Object;)V;
const #152 = NameAndType	#150:#151;//  scala$collection$mutable$SynchronizedMap$$super$update:(Ljava/lang/Object;Ljava/lang/Object;)V
const #153 = InterfaceMethod	#13.#152;	//  scala/collection/mutable/SynchronizedMap.scala$collection$mutable$SynchronizedMap$$super$update:(Ljava/lang/Object;Ljava/lang/Object;)V
const #154 = Asciz	value;
const #155 = Asciz	put;
const #156 = Asciz	(Lscala/collection/mutable/SynchronizedMap;Ljava/lang/Object;Ljava/lang/Object;)Lscala/Option;;
const #157 = Asciz	scala$collection$mutable$SynchronizedMap$$super$put;
const #158 = Asciz	(Ljava/lang/Object;Ljava/lang/Object;)Lscala/Option;;
const #159 = NameAndType	#157:#158;//  scala$collection$mutable$SynchronizedMap$$super$put:(Ljava/lang/Object;Ljava/lang/Object;)Lscala/Option;
const #160 = InterfaceMethod	#13.#159;	//  scala/collection/mutable/SynchronizedMap.scala$collection$mutable$SynchronizedMap$$super$put:(Ljava/lang/Object;Ljava/lang/Object;)Lscala/Option;
const #161 = Asciz	size;
const #162 = Asciz	(Lscala/collection/mutable/SynchronizedMap;)I;
const #163 = Asciz	scala$collection$mutable$SynchronizedMap$$super$size;
const #164 = Asciz	()I;
const #165 = NameAndType	#163:#164;//  scala$collection$mutable$SynchronizedMap$$super$size:()I
const #166 = InterfaceMethod	#13.#165;	//  scala/collection/mutable/SynchronizedMap.scala$collection$mutable$SynchronizedMap$$super$size:()I
const #167 = Asciz	boxToInteger;
const #168 = Asciz	(I)Ljava/lang/Integer;;
const #169 = NameAndType	#167:#168;//  boxToInteger:(I)Ljava/lang/Integer;
const #170 = Method	#27.#169;	//  scala/runtime/BoxesRunTime.boxToInteger:(I)Ljava/lang/Integer;
const #171 = Asciz	unboxToInt;
const #172 = Asciz	(Ljava/lang/Object;)I;
const #173 = NameAndType	#171:#172;//  unboxToInt:(Ljava/lang/Object;)I
const #174 = Method	#27.#173;	//  scala/runtime/BoxesRunTime.unboxToInt:(Ljava/lang/Object;)I
const #175 = Asciz	$minus$eq;
const #176 = Asciz	(Lscala/collection/mutable/SynchronizedMap;Ljava/lang/Object;)Lscala/collection/mutable/SynchronizedMap;;
const #177 = Asciz	scala$collection$mutable$SynchronizedMap$$super$$minus$eq;
const #178 = Asciz	(Ljava/lang/Object;)Lscala/collection/mutable/SynchronizedMap;;
const #179 = NameAndType	#177:#178;//  scala$collection$mutable$SynchronizedMap$$super$$minus$eq:(Ljava/lang/Object;)Lscala/collection/mutable/SynchronizedMap;
const #180 = InterfaceMethod	#13.#179;	//  scala/collection/mutable/SynchronizedMap.scala$collection$mutable$SynchronizedMap$$super$$minus$eq:(Ljava/lang/Object;)Lscala/collection/mutable/SynchronizedMap;
const #181 = Asciz	$plus$eq;
const #182 = Asciz	scala$collection$mutable$SynchronizedMap$$super$$plus$eq;
const #183 = NameAndType	#182:#15;//  scala$collection$mutable$SynchronizedMap$$super$$plus$eq:(Lscala/Tuple2;)Lscala/collection/mutable/SynchronizedMap;
const #184 = InterfaceMethod	#13.#183;	//  scala/collection/mutable/SynchronizedMap.scala$collection$mutable$SynchronizedMap$$super$$plus$eq:(Lscala/Tuple2;)Lscala/collection/mutable/SynchronizedMap;
const #185 = Asciz	iterator;
const #186 = Asciz	scala$collection$mutable$SynchronizedMap$$super$iterator;
const #187 = NameAndType	#186:#50;//  scala$collection$mutable$SynchronizedMap$$super$iterator:()Lscala/collection/Iterator;
const #188 = InterfaceMethod	#13.#187;	//  scala/collection/mutable/SynchronizedMap.scala$collection$mutable$SynchronizedMap$$super$iterator:()Lscala/collection/Iterator;
const #189 = Asciz	get;
const #190 = Asciz	scala$collection$mutable$SynchronizedMap$$super$get;
const #191 = NameAndType	#190:#143;//  scala$collection$mutable$SynchronizedMap$$super$get:(Ljava/lang/Object;)Lscala/Option;
const #192 = InterfaceMethod	#13.#191;	//  scala/collection/mutable/SynchronizedMap.scala$collection$mutable$SynchronizedMap$$super$get:(Ljava/lang/Object;)Lscala/Option;
const #193 = Asciz	Scala;
const #194 = Asciz	scala/collection/mutable/SynchronizedMap$class;
const #195 = class	#194;	//  scala/collection/mutable/SynchronizedMap$class
const #196 = Asciz	java/lang/Object;
const #197 = class	#196;	//  java/lang/Object

{
public static void $init$(scala.collection.mutable.SynchronizedMap);
  Code:
   Stack=0, Locals=1, Args_size=1
   0:	return
  LineNumberTable: 
   line 21: 0

  LocalVariableTable: 
   Start  Length  Slot  Name   Signature
   0      1      0    $this       Lscala/collection/mutable/SynchronizedMap;


public static scala.collection.mutable.SynchronizedMap $plus(scala.collection.mutable.SynchronizedMap, scala.Tuple2);
  Code:
   Stack=2, Locals=3, Args_size=2
   0:	aload_0
   1:	dup
   2:	astore_2
   3:	monitorenter
   4:	aload_0
   5:	aload_1
   6:	invokeinterface	#17,  2; //InterfaceMethod scala/collection/mutable/SynchronizedMap.scala$collection$mutable$SynchronizedMap$$super$$plus:(Lscala/Tuple2;)Lscala/collection/mutable/SynchronizedMap;
   11:	aload_2
   12:	monitorexit
   13:	checkcast	#13; //class scala/collection/mutable/SynchronizedMap
   16:	areturn
   17:	aload_2
   18:	monitorexit
   19:	athrow
  Exception table:
   from   to  target type
     4    13    17   any
  LineNumberTable: 
   line 49: 0

  LocalVariableTable: 
   Start  Length  Slot  Name   Signature
   0      20      0    $this       Lscala/collection/mutable/SynchronizedMap;
   0      20      1    kv       Lscala/Tuple2;


public static boolean isDefinedAt(scala.collection.mutable.SynchronizedMap, java.lang.Object);
  Code:
   Stack=2, Locals=3, Args_size=2
   0:	aload_0
   1:	dup
   2:	astore_2
   3:	monitorenter
   4:	aload_0
   5:	aload_1
   6:	invokeinterface	#25,  2; //InterfaceMethod scala/collection/mutable/SynchronizedMap.scala$collection$mutable$SynchronizedMap$$super$isDefinedAt:(Ljava/lang/Object;)Z
   11:	invokestatic	#31; //Method scala/runtime/BoxesRunTime.boxToBoolean:(Z)Ljava/lang/Boolean;
   14:	aload_2
   15:	monitorexit
   16:	invokestatic	#34; //Method scala/runtime/BoxesRunTime.unboxToBoolean:(Ljava/lang/Object;)Z
   19:	ireturn
   20:	aload_2
   21:	monitorexit
   22:	athrow
  Exception table:
   from   to  target type
     4    16    20   any
  LineNumberTable: 
   line 47: 0

  LocalVariableTable: 
   Start  Length  Slot  Name   Signature
   0      23      0    $this       Lscala/collection/mutable/SynchronizedMap;
   0      23      1    key       Ljava/lang/Object;


public static boolean contains(scala.collection.mutable.SynchronizedMap, java.lang.Object);
  Code:
   Stack=2, Locals=3, Args_size=2
   0:	aload_0
   1:	dup
   2:	astore_2
   3:	monitorenter
   4:	aload_0
   5:	aload_1
   6:	invokeinterface	#40,  2; //InterfaceMethod scala/collection/mutable/SynchronizedMap.scala$collection$mutable$SynchronizedMap$$super$contains:(Ljava/lang/Object;)Z
   11:	invokestatic	#31; //Method scala/runtime/BoxesRunTime.boxToBoolean:(Z)Ljava/lang/Boolean;
   14:	aload_2
   15:	monitorexit
   16:	invokestatic	#34; //Method scala/runtime/BoxesRunTime.unboxToBoolean:(Ljava/lang/Object;)Z
   19:	ireturn
   20:	aload_2
   21:	monitorexit
   22:	athrow
  Exception table:
   from   to  target type
     4    16    20   any
  LineNumberTable: 
   line 46: 0

  LocalVariableTable: 
   Start  Length  Slot  Name   Signature
   0      23      0    $this       Lscala/collection/mutable/SynchronizedMap;
   0      23      1    key       Ljava/lang/Object;


public static boolean isEmpty(scala.collection.mutable.SynchronizedMap);
  Code:
   Stack=2, Locals=2, Args_size=1
   0:	aload_0
   1:	dup
   2:	astore_1
   3:	monitorenter
   4:	aload_0
   5:	invokeinterface	#46,  1; //InterfaceMethod scala/collection/mutable/SynchronizedMap.scala$collection$mutable$SynchronizedMap$$super$isEmpty:()Z
   10:	invokestatic	#31; //Method scala/runtime/BoxesRunTime.boxToBoolean:(Z)Ljava/lang/Boolean;
   13:	aload_1
   14:	monitorexit
   15:	invokestatic	#34; //Method scala/runtime/BoxesRunTime.unboxToBoolean:(Ljava/lang/Object;)Z
   18:	ireturn
   19:	aload_1
   20:	monitorexit
   21:	athrow
  Exception table:
   from   to  target type
     4    15    19   any
  LineNumberTable: 
   line 45: 0

  LocalVariableTable: 
   Start  Length  Slot  Name   Signature
   0      22      0    $this       Lscala/collection/mutable/SynchronizedMap;


public static scala.collection.Iterator keysIterator(scala.collection.mutable.SynchronizedMap);
  Code:
   Stack=2, Locals=2, Args_size=1
   0:	aload_0
   1:	dup
   2:	astore_1
   3:	monitorenter
   4:	aload_0
   5:	invokeinterface	#52,  1; //InterfaceMethod scala/collection/mutable/SynchronizedMap.scala$collection$mutable$SynchronizedMap$$super$keysIterator:()Lscala/collection/Iterator;
   10:	aload_1
   11:	monitorexit
   12:	checkcast	#54; //class scala/collection/Iterator
   15:	areturn
   16:	aload_1
   17:	monitorexit
   18:	athrow
  Exception table:
   from   to  target type
     4    12    16   any
  LineNumberTable: 
   line 44: 0

  LocalVariableTable: 
   Start  Length  Slot  Name   Signature
   0      19      0    $this       Lscala/collection/mutable/SynchronizedMap;


public static scala.collection.Iterator keys(scala.collection.mutable.SynchronizedMap);
  Code:
   Stack=2, Locals=2, Args_size=1
   0:	aload_0
   1:	dup
   2:	astore_1
   3:	monitorenter
   4:	aload_0
   5:	invokeinterface	#52,  1; //InterfaceMethod scala/collection/mutable/SynchronizedMap.scala$collection$mutable$SynchronizedMap$$super$keysIterator:()Lscala/collection/Iterator;
   10:	aload_1
   11:	monitorexit
   12:	checkcast	#54; //class scala/collection/Iterator
   15:	areturn
   16:	aload_1
   17:	monitorexit
   18:	athrow
  Exception table:
   from   to  target type
     4    12    16   any
  LineNumberTable: 
   line 43: 0

  LocalVariableTable: 
   Start  Length  Slot  Name   Signature
   0      19      0    $this       Lscala/collection/mutable/SynchronizedMap;


public static scala.collection.Set keySet(scala.collection.mutable.SynchronizedMap);
  Code:
   Stack=2, Locals=2, Args_size=1
   0:	aload_0
   1:	dup
   2:	astore_1
   3:	monitorenter
   4:	aload_0
   5:	invokeinterface	#61,  1; //InterfaceMethod scala/collection/mutable/SynchronizedMap.scala$collection$mutable$SynchronizedMap$$super$keySet:()Lscala/collection/Set;
   10:	aload_1
   11:	monitorexit
   12:	checkcast	#63; //class scala/collection/Set
   15:	areturn
   16:	aload_1
   17:	monitorexit
   18:	athrow
  Exception table:
   from   to  target type
     4    12    16   any
  LineNumberTable: 
   line 42: 0

  LocalVariableTable: 
   Start  Length  Slot  Name   Signature
   0      19      0    $this       Lscala/collection/mutable/SynchronizedMap;


public static java.lang.Object apply(scala.collection.mutable.SynchronizedMap, java.lang.Object);
  Code:
   Stack=2, Locals=3, Args_size=2
   0:	aload_0
   1:	dup
   2:	astore_2
   3:	monitorenter
   4:	aload_0
   5:	aload_1
   6:	invokeinterface	#69,  2; //InterfaceMethod scala/collection/mutable/SynchronizedMap.scala$collection$mutable$SynchronizedMap$$super$apply:(Ljava/lang/Object;)Ljava/lang/Object;
   11:	aload_2
   12:	monitorexit
   13:	areturn
   14:	aload_2
   15:	monitorexit
   16:	athrow
  Exception table:
   from   to  target type
     4    13    14   any
  LineNumberTable: 
   line 41: 0

  LocalVariableTable: 
   Start  Length  Slot  Name   Signature
   0      17      0    $this       Lscala/collection/mutable/SynchronizedMap;
   0      17      1    key       Ljava/lang/Object;


public static void foreach(scala.collection.mutable.SynchronizedMap, scala.Function1);
  Code:
   Stack=2, Locals=3, Args_size=2
   0:	aload_0
   1:	dup
   2:	astore_2
   3:	monitorenter
   4:	aload_0
   5:	aload_1
   6:	invokeinterface	#75,  2; //InterfaceMethod scala/collection/mutable/SynchronizedMap.scala$collection$mutable$SynchronizedMap$$super$foreach:(Lscala/Function1;)V
   11:	getstatic	#81; //Field scala/runtime/BoxedUnit.UNIT:Lscala/runtime/BoxedUnit;
   14:	pop
   15:	aload_2
   16:	monitorexit
   17:	return
   18:	aload_2
   19:	monitorexit
   20:	athrow
  Exception table:
   from   to  target type
     4    17    18   any
  LineNumberTable: 
   line 40: 0

  LocalVariableTable: 
   Start  Length  Slot  Name   Signature
   0      21      0    $this       Lscala/collection/mutable/SynchronizedMap;
   0      21      1    f       Lscala/Function1;


public static scala.collection.mutable.Map clone(scala.collection.mutable.SynchronizedMap);
  Code:
   Stack=2, Locals=2, Args_size=1
   0:	aload_0
   1:	dup
   2:	astore_1
   3:	monitorenter
   4:	aload_0
   5:	invokeinterface	#89,  1; //InterfaceMethod scala/collection/mutable/SynchronizedMap.scala$collection$mutable$SynchronizedMap$$super$clone:()Lscala/collection/mutable/Map;
   10:	aload_1
   11:	monitorexit
   12:	checkcast	#91; //class scala/collection/mutable/Map
   15:	areturn
   16:	aload_1
   17:	monitorexit
   18:	athrow
  Exception table:
   from   to  target type
     4    12    16   any
  LineNumberTable: 
   line 39: 0

  LocalVariableTable: 
   Start  Length  Slot  Name   Signature
   0      19      0    $this       Lscala/collection/mutable/SynchronizedMap;


public static scala.collection.Iterator valuesIterator(scala.collection.mutable.SynchronizedMap);
  Code:
   Stack=2, Locals=2, Args_size=1
   0:	aload_0
   1:	dup
   2:	astore_1
   3:	monitorenter
   4:	aload_0
   5:	invokeinterface	#95,  1; //InterfaceMethod scala/collection/mutable/SynchronizedMap.scala$collection$mutable$SynchronizedMap$$super$valuesIterator:()Lscala/collection/Iterator;
   10:	aload_1
   11:	monitorexit
   12:	checkcast	#54; //class scala/collection/Iterator
   15:	areturn
   16:	aload_1
   17:	monitorexit
   18:	athrow
  Exception table:
   from   to  target type
     4    12    16   any
  LineNumberTable: 
   line 38: 0

  LocalVariableTable: 
   Start  Length  Slot  Name   Signature
   0      19      0    $this       Lscala/collection/mutable/SynchronizedMap;


public static scala.collection.Iterator values(scala.collection.mutable.SynchronizedMap);
  Code:
   Stack=2, Locals=2, Args_size=1
   0:	aload_0
   1:	dup
   2:	astore_1
   3:	monitorenter
   4:	aload_0
   5:	invokeinterface	#95,  1; //InterfaceMethod scala/collection/mutable/SynchronizedMap.scala$collection$mutable$SynchronizedMap$$super$valuesIterator:()Lscala/collection/Iterator;
   10:	aload_1
   11:	monitorexit
   12:	checkcast	#54; //class scala/collection/Iterator
   15:	areturn
   16:	aload_1
   17:	monitorexit
   18:	athrow
  Exception table:
   from   to  target type
     4    12    16   any
  LineNumberTable: 
   line 37: 0

  LocalVariableTable: 
   Start  Length  Slot  Name   Signature
   0      19      0    $this       Lscala/collection/mutable/SynchronizedMap;


public static scala.collection.Iterable valueIterable(scala.collection.mutable.SynchronizedMap);
  Code:
   Stack=2, Locals=3, Args_size=1
   0:	aload_0
   1:	dup
   2:	astore_2
   3:	monitorenter
   4:	aload_0
   5:	invokeinterface	#102,  1; //InterfaceMethod scala/collection/mutable/SynchronizedMap.scala$collection$mutable$SynchronizedMap$$super$valueIterable:()Lscala/collection/Iterable;
   10:	aload_2
   11:	monitorexit
   12:	astore_1
   13:	aload_1
   14:	instanceof	#104; //class scala/collection/Iterable
   17:	ifeq	24
   20:	aload_1
   21:	goto	31
   24:	getstatic	#110; //Field scala/runtime/ScalaRunTime$.MODULE$:Lscala/runtime/ScalaRunTime$;
   27:	aload_1
   28:	invokevirtual	#114; //Method scala/runtime/ScalaRunTime$.boxArray:(Ljava/lang/Object;)Lscala/runtime/BoxedArray;
   31:	checkcast	#104; //class scala/collection/Iterable
   34:	areturn
   35:	aload_2
   36:	monitorexit
   37:	athrow
  Exception table:
   from   to  target type
     4    12    35   any
  LineNumberTable: 
   line 36: 0

  LocalVariableTable: 
   Start  Length  Slot  Name   Signature
   0      38      0    $this       Lscala/collection/mutable/SynchronizedMap;


public static scala.collection.mutable.SynchronizedMap retain(scala.collection.mutable.SynchronizedMap, scala.Function2);
  Code:
   Stack=2, Locals=3, Args_size=2
   0:	aload_0
   1:	dup
   2:	astore_2
   3:	monitorenter
   4:	aload_0
   5:	aload_1
   6:	invokeinterface	#120,  2; //InterfaceMethod scala/collection/mutable/SynchronizedMap.scala$collection$mutable$SynchronizedMap$$super$retain:(Lscala/Function2;)Lscala/collection/mutable/SynchronizedMap;
   11:	aload_2
   12:	monitorexit
   13:	checkcast	#13; //class scala/collection/mutable/SynchronizedMap
   16:	areturn
   17:	aload_2
   18:	monitorexit
   19:	athrow
  Exception table:
   from   to  target type
     4    13    17   any
  LineNumberTable: 
   line 35: 0

  LocalVariableTable: 
   Start  Length  Slot  Name   Signature
   0      20      0    $this       Lscala/collection/mutable/SynchronizedMap;
   0      20      1    p       Lscala/Function2;


public static scala.collection.mutable.SynchronizedMap transform(scala.collection.mutable.SynchronizedMap, scala.Function2);
  Code:
   Stack=2, Locals=3, Args_size=2
   0:	aload_0
   1:	dup
   2:	astore_2
   3:	monitorenter
   4:	aload_0
   5:	aload_1
   6:	invokeinterface	#126,  2; //InterfaceMethod scala/collection/mutable/SynchronizedMap.scala$collection$mutable$SynchronizedMap$$super$transform:(Lscala/Function2;)Lscala/collection/mutable/SynchronizedMap;
   11:	aload_2
   12:	monitorexit
   13:	checkcast	#13; //class scala/collection/mutable/SynchronizedMap
   16:	areturn
   17:	aload_2
   18:	monitorexit
   19:	athrow
  Exception table:
   from   to  target type
     4    13    17   any
  LineNumberTable: 
   line 34: 0

  LocalVariableTable: 
   Start  Length  Slot  Name   Signature
   0      20      0    $this       Lscala/collection/mutable/SynchronizedMap;
   0      20      1    f       Lscala/Function2;


public static java.lang.Object getOrElseUpdate(scala.collection.mutable.SynchronizedMap, java.lang.Object, scala.Function0);
  Code:
   Stack=3, Locals=4, Args_size=3
   0:	aload_0
   1:	dup
   2:	astore_3
   3:	monitorenter
   4:	aload_0
   5:	aload_1
   6:	aload_2
   7:	invokeinterface	#132,  3; //InterfaceMethod scala/collection/mutable/SynchronizedMap.scala$collection$mutable$SynchronizedMap$$super$getOrElseUpdate:(Ljava/lang/Object;Lscala/Function0;)Ljava/lang/Object;
   12:	aload_3
   13:	monitorexit
   14:	areturn
   15:	aload_3
   16:	monitorexit
   17:	athrow
  Exception table:
   from   to  target type
     4    14    15   any
  LineNumberTable: 
   line 33: 0

  LocalVariableTable: 
   Start  Length  Slot  Name   Signature
   0      18      0    $this       Lscala/collection/mutable/SynchronizedMap;
   0      18      1    key       Ljava/lang/Object;
   0      18      2    default       Lscala/Function0;


public static void clear(scala.collection.mutable.SynchronizedMap);
  Code:
   Stack=2, Locals=2, Args_size=1
   0:	aload_0
   1:	dup
   2:	astore_1
   3:	monitorenter
   4:	aload_0
   5:	invokeinterface	#139,  1; //InterfaceMethod scala/collection/mutable/SynchronizedMap.scala$collection$mutable$SynchronizedMap$$super$clear:()V
   10:	getstatic	#81; //Field scala/runtime/BoxedUnit.UNIT:Lscala/runtime/BoxedUnit;
   13:	pop
   14:	aload_1
   15:	monitorexit
   16:	return
   17:	aload_1
   18:	monitorexit
   19:	athrow
  Exception table:
   from   to  target type
     4    16    17   any
  LineNumberTable: 
   line 32: 0

  LocalVariableTable: 
   Start  Length  Slot  Name   Signature
   0      20      0    $this       Lscala/collection/mutable/SynchronizedMap;


public static scala.Option remove(scala.collection.mutable.SynchronizedMap, java.lang.Object);
  Code:
   Stack=2, Locals=3, Args_size=2
   0:	aload_0
   1:	dup
   2:	astore_2
   3:	monitorenter
   4:	aload_0
   5:	aload_1
   6:	invokeinterface	#145,  2; //InterfaceMethod scala/collection/mutable/SynchronizedMap.scala$collection$mutable$SynchronizedMap$$super$remove:(Ljava/lang/Object;)Lscala/Option;
   11:	aload_2
   12:	monitorexit
   13:	checkcast	#147; //class scala/Option
   16:	areturn
   17:	aload_2
   18:	monitorexit
   19:	athrow
  Exception table:
   from   to  target type
     4    13    17   any
  LineNumberTable: 
   line 31: 0

  LocalVariableTable: 
   Start  Length  Slot  Name   Signature
   0      20      0    $this       Lscala/collection/mutable/SynchronizedMap;
   0      20      1    key       Ljava/lang/Object;


public static void update(scala.collection.mutable.SynchronizedMap, java.lang.Object, java.lang.Object);
  Code:
   Stack=3, Locals=4, Args_size=3
   0:	aload_0
   1:	dup
   2:	astore_3
   3:	monitorenter
   4:	aload_0
   5:	aload_1
   6:	aload_2
   7:	invokeinterface	#153,  3; //InterfaceMethod scala/collection/mutable/SynchronizedMap.scala$collection$mutable$SynchronizedMap$$super$update:(Ljava/lang/Object;Ljava/lang/Object;)V
   12:	getstatic	#81; //Field scala/runtime/BoxedUnit.UNIT:Lscala/runtime/BoxedUnit;
   15:	pop
   16:	aload_3
   17:	monitorexit
   18:	return
   19:	aload_3
   20:	monitorexit
   21:	athrow
  Exception table:
   from   to  target type
     4    18    19   any
  LineNumberTable: 
   line 30: 0

  LocalVariableTable: 
   Start  Length  Slot  Name   Signature
   0      22      0    $this       Lscala/collection/mutable/SynchronizedMap;
   0      22      1    key       Ljava/lang/Object;
   0      22      2    value       Ljava/lang/Object;


public static scala.Option put(scala.collection.mutable.SynchronizedMap, java.lang.Object, java.lang.Object);
  Code:
   Stack=3, Locals=4, Args_size=3
   0:	aload_0
   1:	dup
   2:	astore_3
   3:	monitorenter
   4:	aload_0
   5:	aload_1
   6:	aload_2
   7:	invokeinterface	#160,  3; //InterfaceMethod scala/collection/mutable/SynchronizedMap.scala$collection$mutable$SynchronizedMap$$super$put:(Ljava/lang/Object;Ljava/lang/Object;)Lscala/Option;
   12:	aload_3
   13:	monitorexit
   14:	checkcast	#147; //class scala/Option
   17:	areturn
   18:	aload_3
   19:	monitorexit
   20:	athrow
  Exception table:
   from   to  target type
     4    14    18   any
  LineNumberTable: 
   line 29: 0

  LocalVariableTable: 
   Start  Length  Slot  Name   Signature
   0      21      0    $this       Lscala/collection/mutable/SynchronizedMap;
   0      21      1    key       Ljava/lang/Object;
   0      21      2    value       Ljava/lang/Object;


public static int size(scala.collection.mutable.SynchronizedMap);
  Code:
   Stack=2, Locals=2, Args_size=1
   0:	aload_0
   1:	dup
   2:	astore_1
   3:	monitorenter
   4:	aload_0
   5:	invokeinterface	#166,  1; //InterfaceMethod scala/collection/mutable/SynchronizedMap.scala$collection$mutable$SynchronizedMap$$super$size:()I
   10:	invokestatic	#170; //Method scala/runtime/BoxesRunTime.boxToInteger:(I)Ljava/lang/Integer;
   13:	aload_1
   14:	monitorexit
   15:	invokestatic	#174; //Method scala/runtime/BoxesRunTime.unboxToInt:(Ljava/lang/Object;)I
   18:	ireturn
   19:	aload_1
   20:	monitorexit
   21:	athrow
  Exception table:
   from   to  target type
     4    15    19   any
  LineNumberTable: 
   line 28: 0

  LocalVariableTable: 
   Start  Length  Slot  Name   Signature
   0      22      0    $this       Lscala/collection/mutable/SynchronizedMap;


public static scala.collection.mutable.SynchronizedMap $minus$eq(scala.collection.mutable.SynchronizedMap, java.lang.Object);
  Code:
   Stack=2, Locals=3, Args_size=2
   0:	aload_0
   1:	dup
   2:	astore_2
   3:	monitorenter
   4:	aload_0
   5:	aload_1
   6:	invokeinterface	#180,  2; //InterfaceMethod scala/collection/mutable/SynchronizedMap.scala$collection$mutable$SynchronizedMap$$super$$minus$eq:(Ljava/lang/Object;)Lscala/collection/mutable/SynchronizedMap;
   11:	aload_2
   12:	monitorexit
   13:	checkcast	#13; //class scala/collection/mutable/SynchronizedMap
   16:	areturn
   17:	aload_2
   18:	monitorexit
   19:	athrow
  Exception table:
   from   to  target type
     4    13    17   any
  LineNumberTable: 
   line 26: 0

  LocalVariableTable: 
   Start  Length  Slot  Name   Signature
   0      20      0    $this       Lscala/collection/mutable/SynchronizedMap;
   0      20      1    key       Ljava/lang/Object;


public static scala.collection.mutable.SynchronizedMap $plus$eq(scala.collection.mutable.SynchronizedMap, scala.Tuple2);
  Code:
   Stack=2, Locals=3, Args_size=2
   0:	aload_0
   1:	dup
   2:	astore_2
   3:	monitorenter
   4:	aload_0
   5:	aload_1
   6:	invokeinterface	#184,  2; //InterfaceMethod scala/collection/mutable/SynchronizedMap.scala$collection$mutable$SynchronizedMap$$super$$plus$eq:(Lscala/Tuple2;)Lscala/collection/mutable/SynchronizedMap;
   11:	aload_2
   12:	monitorexit
   13:	checkcast	#13; //class scala/collection/mutable/SynchronizedMap
   16:	areturn
   17:	aload_2
   18:	monitorexit
   19:	athrow
  Exception table:
   from   to  target type
     4    13    17   any
  LineNumberTable: 
   line 25: 0

  LocalVariableTable: 
   Start  Length  Slot  Name   Signature
   0      20      0    $this       Lscala/collection/mutable/SynchronizedMap;
   0      20      1    kv       Lscala/Tuple2;


public static scala.collection.Iterator iterator(scala.collection.mutable.SynchronizedMap);
  Code:
   Stack=2, Locals=2, Args_size=1
   0:	aload_0
   1:	dup
   2:	astore_1
   3:	monitorenter
   4:	aload_0
   5:	invokeinterface	#188,  1; //InterfaceMethod scala/collection/mutable/SynchronizedMap.scala$collection$mutable$SynchronizedMap$$super$iterator:()Lscala/collection/Iterator;
   10:	aload_1
   11:	monitorexit
   12:	checkcast	#54; //class scala/collection/Iterator
   15:	areturn
   16:	aload_1
   17:	monitorexit
   18:	athrow
  Exception table:
   from   to  target type
     4    12    16   any
  LineNumberTable: 
   line 24: 0

  LocalVariableTable: 
   Start  Length  Slot  Name   Signature
   0      19      0    $this       Lscala/collection/mutable/SynchronizedMap;


public static scala.Option get(scala.collection.mutable.SynchronizedMap, java.lang.Object);
  Code:
   Stack=2, Locals=3, Args_size=2
   0:	aload_0
   1:	dup
   2:	astore_2
   3:	monitorenter
   4:	aload_0
   5:	aload_1
   6:	invokeinterface	#192,  2; //InterfaceMethod scala/collection/mutable/SynchronizedMap.scala$collection$mutable$SynchronizedMap$$super$get:(Ljava/lang/Object;)Lscala/Option;
   11:	aload_2
   12:	monitorexit
   13:	checkcast	#147; //class scala/Option
   16:	areturn
   17:	aload_2
   18:	monitorexit
   19:	athrow
  Exception table:
   from   to  target type
     4    13    17   any
  LineNumberTable: 
   line 23: 0

  LocalVariableTable: 
   Start  Length  Slot  Name   Signature
   0      20      0    $this       Lscala/collection/mutable/SynchronizedMap;
   0      20      1    key       Ljava/lang/Object;


}

