Compiled from "ArrayStack.scala"
public final class scala.collection.mutable.Utils$ extends java.lang.Object implements scala.ScalaObject
  SourceFile: "ArrayStack.scala"
  Scala: length = 0x
   
  minor version: 0
  major version: 49
  Constant pool:
Asciz	SourceFile;
Asciz	ArrayStack.scala;
Asciz	Scala;
Asciz	MODULE$;
Asciz	Lscala/collection/mutable/Utils$;;
Asciz	<clinit>;
Asciz	()V;
Asciz	Code;
Asciz	scala/collection/mutable/Utils$;
class	scala/collection/mutable/Utils$
Asciz	<init>;
NameAndType	"<init>":()V
Method	scala/collection/mutable/Utils$."<init>":()V
Asciz	LineNumberTable;
Asciz	java/lang/Object;
class	java/lang/Object
Method	java/lang/Object."<init>":()V
NameAndType	MODULE$:Lscala/collection/mutable/Utils$;
Field	scala/collection/mutable/Utils$.MODULE$:Lscala/collection/mutable/Utils$;
Asciz	clone;
Asciz	([Ljava/lang/Object;)[Ljava/lang/Object;;
Asciz	scala/Array$;
class	scala/Array$
Asciz	Lscala/Array$;;
NameAndType	MODULE$:Lscala/Array$;
Field	scala/Array$.MODULE$:Lscala/Array$;
Asciz	copy;
Asciz	(Ljava/lang/Object;ILjava/lang/Object;II)V;
NameAndType	copy:(Ljava/lang/Object;ILjava/lang/Object;II)V
Method	scala/Array$.copy:(Ljava/lang/Object;ILjava/lang/Object;II)V
Asciz	this;
Asciz	x;
Asciz	[Ljava/lang/Object;;
Asciz	y;
Asciz	LocalVariableTable;
Asciz	growArray;
Asciz	scala/ScalaObject;
class	scala/ScalaObject

{
public static final scala.collection.mutable.Utils$ MODULE$;
  Signature: Lscala/collection/mutable/Utils$;

public static {};
  Signature: ()V
  Code:
   Stack=1, Locals=0, Args_size=0
	new	class scala/collection/mutable/Utils$
	invokespecial	Method "<init>":()V
	return
  Labels:

private scala.collection.mutable.Utils$();
  Signature: ()V
  Code:
   Stack=1, Locals=1, Args_size=1
	aload_0
	invokespecial	Method java/lang/Object."<init>":()V
	aload_0
	putstatic	Field MODULE$:Lscala/collection/mutable/Utils$;
	return
  Labels:

public java.lang.Object[] clone(java.lang.Object[]);
  Signature: ([Ljava/lang/Object;)[Ljava/lang/Object;
  Code:
   Stack=6, Locals=3, Args_size=2
	aload_1
	arraylength
	anewarray	class java/lang/Object
	astore_2
	getstatic	Field scala/Array$.MODULE$:Lscala/Array$;
	aload_1
	iconst_0
	aload_2
	iconst_0
	aload_1
	arraylength
	invokevirtual	Method scala/Array$.copy:(Ljava/lang/Object;ILjava/lang/Object;II)V
	aload_2
	areturn
  Labels:
  LocalVariableTable: 
   Start  Length  Slot  Name   Signature
   0      20      0    this       Lscala/collection/mutable/Utils$;
   0      20      1    x       [Ljava/lang/Object;
   6      13      2    y       [Ljava/lang/Object;


public java.lang.Object[] growArray(java.lang.Object[]);
  Signature: ([Ljava/lang/Object;)[Ljava/lang/Object;
  Code:
   Stack=6, Locals=3, Args_size=2
	aload_1
	arraylength
	iconst_2
	imul
	anewarray	class java/lang/Object
	astore_2
	getstatic	Field scala/Array$.MODULE$:Lscala/Array$;
	aload_1
	iconst_0
	aload_2
	iconst_0
	aload_1
	arraylength
	invokevirtual	Method scala/Array$.copy:(Ljava/lang/Object;ILjava/lang/Object;II)V
	aload_2
	areturn
  Labels:
  LocalVariableTable: 
   Start  Length  Slot  Name   Signature
   0      22      0    this       Lscala/collection/mutable/Utils$;
   0      22      1    x       [Ljava/lang/Object;
   8      13      2    y       [Ljava/lang/Object;


}

