Compiled from "ArrayStack.scala"
public final class scala.collection.mutable.Utils$ extends java.lang.Object implements scala.ScalaObject
  SourceFile: "ArrayStack.scala"
  Scala: length = 0x
   
  minor version: 0
  major version: 49
  Constant pool:
const #1 = Asciz	SourceFile;
const #2 = Asciz	ArrayStack.scala;
const #3 = Asciz	Scala;
const #4 = Asciz	MODULE$;
const #5 = Asciz	Lscala/collection/mutable/Utils$;;
const #6 = Asciz	<clinit>;
const #7 = Asciz	()V;
const #8 = Asciz	Code;
const #9 = Asciz	scala/collection/mutable/Utils$;
const #10 = class	#9;	//  scala/collection/mutable/Utils$
const #11 = Asciz	<init>;
const #12 = NameAndType	#11:#7;//  "<init>":()V
const #13 = Method	#10.#12;	//  scala/collection/mutable/Utils$."<init>":()V
const #14 = Asciz	LineNumberTable;
const #15 = Asciz	java/lang/Object;
const #16 = class	#15;	//  java/lang/Object
const #17 = Method	#16.#12;	//  java/lang/Object."<init>":()V
const #18 = NameAndType	#4:#5;//  MODULE$:Lscala/collection/mutable/Utils$;
const #19 = Field	#10.#18;	//  scala/collection/mutable/Utils$.MODULE$:Lscala/collection/mutable/Utils$;
const #20 = Asciz	clone;
const #21 = Asciz	([Ljava/lang/Object;)[Ljava/lang/Object;;
const #22 = Asciz	scala/Array$;
const #23 = class	#22;	//  scala/Array$
const #24 = Asciz	Lscala/Array$;;
const #25 = NameAndType	#4:#24;//  MODULE$:Lscala/Array$;
const #26 = Field	#23.#25;	//  scala/Array$.MODULE$:Lscala/Array$;
const #27 = Asciz	copy;
const #28 = Asciz	(Ljava/lang/Object;ILjava/lang/Object;II)V;
const #29 = NameAndType	#27:#28;//  copy:(Ljava/lang/Object;ILjava/lang/Object;II)V
const #30 = Method	#23.#29;	//  scala/Array$.copy:(Ljava/lang/Object;ILjava/lang/Object;II)V
const #31 = Asciz	this;
const #32 = Asciz	x;
const #33 = Asciz	[Ljava/lang/Object;;
const #34 = Asciz	y;
const #35 = Asciz	LocalVariableTable;
const #36 = Asciz	growArray;
const #37 = Asciz	scala/ScalaObject;
const #38 = class	#37;	//  scala/ScalaObject

{
public static final scala.collection.mutable.Utils$ MODULE$;

public static {};
  Code:
   Stack=1, Locals=0, Args_size=0
   0:	new	#10; //class scala/collection/mutable/Utils$
   3:	invokespecial	#13; //Method "<init>":()V
   6:	return

public java.lang.Object[] clone(java.lang.Object[]);
  Code:
   Stack=6, Locals=3, Args_size=2
   0:	aload_1
   1:	arraylength
   2:	anewarray	#16; //class java/lang/Object
   5:	astore_2
   6:	getstatic	#26; //Field scala/Array$.MODULE$:Lscala/Array$;
   9:	aload_1
   10:	iconst_0
   11:	aload_2
   12:	iconst_0
   13:	aload_1
   14:	arraylength
   15:	invokevirtual	#30; //Method scala/Array$.copy:(Ljava/lang/Object;ILjava/lang/Object;II)V
   18:	aload_2
   19:	areturn
  LineNumberTable: 
   line 25: 0
   line 26: 6
   line 27: 18

  LocalVariableTable: 
   Start  Length  Slot  Name   Signature
   0      20      0    this       Lscala/collection/mutable/Utils$;
   0      20      1    x       [Ljava/lang/Object;
   6      13      2    y       [Ljava/lang/Object;


public java.lang.Object[] growArray(java.lang.Object[]);
  Code:
   Stack=6, Locals=3, Args_size=2
   0:	aload_1
   1:	arraylength
   2:	iconst_2
   3:	imul
   4:	anewarray	#16; //class java/lang/Object
   7:	astore_2
   8:	getstatic	#26; //Field scala/Array$.MODULE$:Lscala/Array$;
   11:	aload_1
   12:	iconst_0
   13:	aload_2
   14:	iconst_0
   15:	aload_1
   16:	arraylength
   17:	invokevirtual	#30; //Method scala/Array$.copy:(Ljava/lang/Object;ILjava/lang/Object;II)V
   20:	aload_2
   21:	areturn
  LineNumberTable: 
   line 19: 0
   line 20: 8
   line 21: 20

  LocalVariableTable: 
   Start  Length  Slot  Name   Signature
   0      22      0    this       Lscala/collection/mutable/Utils$;
   0      22      1    x       [Ljava/lang/Object;
   8      13      2    y       [Ljava/lang/Object;


}

