Compiled from "WrappedArray.scala"
public final class scala.collection.mutable.WrappedArray$$anon$1$$anonfun$apply$2 extends java.lang.Object implements scala.Function1,scala.ScalaObject,java.io.Serializable
  SourceFile: "WrappedArray.scala"
  Scala: length = 0x
   
  InnerClass: 
   public final #69= #66 of #68; //$anon$1=class scala/collection/mutable/WrappedArray$$anon$1 of class scala/collection/mutable/WrappedArray
   public final #70= #9 of #66; //$anonfun$apply$2=class scala/collection/mutable/WrappedArray$$anon$1$$anonfun$apply$2 of class scala/collection/mutable/WrappedArray$$anon$1
  minor version: 0
  major version: 49
  Constant pool:
const #1 = Asciz	SourceFile;
const #2 = Asciz	WrappedArray.scala;
const #3 = Asciz	<clinit>;
const #4 = Asciz	()V;
const #5 = Asciz	Code;
const #6 = Asciz	serialVersionUID;
const #7 = Asciz	J;
const #8 = Asciz	scala/collection/mutable/WrappedArray$$anon$1$$anonfun$apply$2;
const #9 = class	#8;	//  scala/collection/mutable/WrappedArray$$anon$1$$anonfun$apply$2
const #10 = NameAndType	#6:#7;//  serialVersionUID:J
const #11 = Field	#9.#10;	//  scala/collection/mutable/WrappedArray$$anon$1$$anonfun$apply$2.serialVersionUID:J
const #12 = Asciz	<init>;
const #13 = Asciz	(Lscala/collection/mutable/WrappedArray$$anon$1;)V;
const #14 = Asciz	LineNumberTable;
const #15 = Asciz	java/lang/Object;
const #16 = class	#15;	//  java/lang/Object
const #17 = NameAndType	#12:#4;//  "<init>":()V
const #18 = Method	#16.#17;	//  java/lang/Object."<init>":()V
const #19 = Asciz	scala/Function1$class;
const #20 = class	#19;	//  scala/Function1$class
const #21 = Asciz	$init$;
const #22 = Asciz	(Lscala/Function1;)V;
const #23 = NameAndType	#21:#22;//  $init$:(Lscala/Function1;)V
const #24 = Method	#20.#23;	//  scala/Function1$class.$init$:(Lscala/Function1;)V
const #25 = Asciz	this;
const #26 = Asciz	Lscala/collection/mutable/WrappedArray$$anon$1$$anonfun$apply$2;;
const #27 = Asciz	$outer;
const #28 = Asciz	Lscala/collection/mutable/WrappedArray$$anon$1;;
const #29 = Asciz	LocalVariableTable;
const #30 = Asciz	apply;
const #31 = Asciz	(Ljava/lang/Object;)Ljava/lang/Object;;
const #32 = Asciz	(Ljava/lang/Object;)Lscala/collection/mutable/WrappedArray;;
const #33 = NameAndType	#30:#32;//  apply:(Ljava/lang/Object;)Lscala/collection/mutable/WrappedArray;
const #34 = Method	#9.#33;	//  scala/collection/mutable/WrappedArray$$anon$1$$anonfun$apply$2.apply:(Ljava/lang/Object;)Lscala/collection/mutable/WrappedArray;
const #35 = Asciz	v1;
const #36 = Asciz	Ljava/lang/Object;;
const #37 = Asciz	scala/collection/mutable/WrappedArray$;
const #38 = class	#37;	//  scala/collection/mutable/WrappedArray$
const #39 = Asciz	MODULE$;
const #40 = Asciz	Lscala/collection/mutable/WrappedArray$;;
const #41 = NameAndType	#39:#40;//  MODULE$:Lscala/collection/mutable/WrappedArray$;
const #42 = Field	#38.#41;	//  scala/collection/mutable/WrappedArray$.MODULE$:Lscala/collection/mutable/WrappedArray$;
const #43 = Asciz	make;
const #44 = NameAndType	#43:#32;//  make:(Ljava/lang/Object;)Lscala/collection/mutable/WrappedArray;
const #45 = Method	#38.#44;	//  scala/collection/mutable/WrappedArray$.make:(Ljava/lang/Object;)Lscala/collection/mutable/WrappedArray;
const #46 = Asciz	(Ljava/lang/Object;)Lscala/collection/mutable/WrappedArray<TT;>;;
const #47 = Asciz	Signature;
const #48 = Asciz	andThen;
const #49 = Asciz	(Lscala/Function1;)Lscala/Function1;;
const #50 = Asciz	(Lscala/Function1;Lscala/Function1;)Lscala/Function1;;
const #51 = NameAndType	#48:#50;//  andThen:(Lscala/Function1;Lscala/Function1;)Lscala/Function1;
const #52 = Method	#20.#51;	//  scala/Function1$class.andThen:(Lscala/Function1;Lscala/Function1;)Lscala/Function1;
const #53 = Asciz	g;
const #54 = Asciz	Lscala/Function1;;
const #55 = Asciz	compose;
const #56 = NameAndType	#55:#50;//  compose:(Lscala/Function1;Lscala/Function1;)Lscala/Function1;
const #57 = Method	#20.#56;	//  scala/Function1$class.compose:(Lscala/Function1;Lscala/Function1;)Lscala/Function1;
const #58 = Asciz	toString;
const #59 = Asciz	()Ljava/lang/String;;
const #60 = Asciz	(Lscala/Function1;)Ljava/lang/String;;
const #61 = NameAndType	#58:#60;//  toString:(Lscala/Function1;)Ljava/lang/String;
const #62 = Method	#20.#61;	//  scala/Function1$class.toString:(Lscala/Function1;)Ljava/lang/String;
const #63 = Asciz	Scala;
const #64 = Asciz	InnerClasses;
const #65 = Asciz	scala/collection/mutable/WrappedArray$$anon$1;
const #66 = class	#65;	//  scala/collection/mutable/WrappedArray$$anon$1
const #67 = Asciz	scala/collection/mutable/WrappedArray;
const #68 = class	#67;	//  scala/collection/mutable/WrappedArray
const #69 = Asciz	$anon$1;
const #70 = Asciz	$anonfun$apply$2;
const #71 = Asciz	scala/Function1;
const #72 = class	#71;	//  scala/Function1
const #73 = Asciz	scala/ScalaObject;
const #74 = class	#73;	//  scala/ScalaObject
const #75 = Asciz	java/io/Serializable;
const #76 = class	#75;	//  java/io/Serializable

{
public static final long serialVersionUID;

public static {};
  Code:
   Stack=2, Locals=0, Args_size=0
   0:	lconst_0
   1:	putstatic	#11; //Field serialVersionUID:J
   4:	return

public scala.collection.mutable.WrappedArray$$anon$1$$anonfun$apply$2(scala.collection.mutable.WrappedArray$$anon$1);
  Code:
   Stack=1, Locals=2, Args_size=2
   0:	aload_0
   1:	invokespecial	#18; //Method java/lang/Object."<init>":()V
   4:	aload_0
   5:	invokestatic	#24; //Method scala/Function1$class.$init$:(Lscala/Function1;)V
   8:	return
  LineNumberTable: 
   line 72: 0

  LocalVariableTable: 
   Start  Length  Slot  Name   Signature
   0      9      0    this       Lscala/collection/mutable/WrappedArray$$anon$1$$anonfun$apply$2;
   0      9      1    $outer       Lscala/collection/mutable/WrappedArray$$anon$1;


public final java.lang.Object apply(java.lang.Object);
  Code:
   Stack=2, Locals=2, Args_size=2
   0:	aload_0
   1:	aload_1
   2:	invokevirtual	#34; //Method apply:(Ljava/lang/Object;)Lscala/collection/mutable/WrappedArray;
   5:	areturn
  LineNumberTable: 
   line 72: 0

  LocalVariableTable: 
   Start  Length  Slot  Name   Signature
   0      6      0    this       Lscala/collection/mutable/WrappedArray$$anon$1$$anonfun$apply$2;
   0      6      1    v1       Ljava/lang/Object;


public final scala.collection.mutable.WrappedArray apply(java.lang.Object);
  Code:
   Stack=2, Locals=2, Args_size=2
   0:	getstatic	#42; //Field scala/collection/mutable/WrappedArray$.MODULE$:Lscala/collection/mutable/WrappedArray$;
   3:	aload_1
   4:	invokevirtual	#45; //Method scala/collection/mutable/WrappedArray$.make:(Ljava/lang/Object;)Lscala/collection/mutable/WrappedArray;
   7:	areturn
  LineNumberTable: 
   line 72: 0

  Signature: length = 0x2
   00 2E 

public scala.Function1 andThen(scala.Function1);
  Code:
   Stack=2, Locals=2, Args_size=2
   0:	aload_0
   1:	aload_1
   2:	invokestatic	#52; //Method scala/Function1$class.andThen:(Lscala/Function1;Lscala/Function1;)Lscala/Function1;
   5:	areturn
  LineNumberTable: 
   line 72: 0

  LocalVariableTable: 
   Start  Length  Slot  Name   Signature
   0      6      0    this       Lscala/collection/mutable/WrappedArray$$anon$1$$anonfun$apply$2;
   0      6      1    g       Lscala/Function1;


public scala.Function1 compose(scala.Function1);
  Code:
   Stack=2, Locals=2, Args_size=2
   0:	aload_0
   1:	aload_1
   2:	invokestatic	#57; //Method scala/Function1$class.compose:(Lscala/Function1;Lscala/Function1;)Lscala/Function1;
   5:	areturn
  LineNumberTable: 
   line 72: 0

  LocalVariableTable: 
   Start  Length  Slot  Name   Signature
   0      6      0    this       Lscala/collection/mutable/WrappedArray$$anon$1$$anonfun$apply$2;
   0      6      1    g       Lscala/Function1;


public java.lang.String toString();
  Code:
   Stack=1, Locals=1, Args_size=1
   0:	aload_0
   1:	invokestatic	#62; //Method scala/Function1$class.toString:(Lscala/Function1;)Ljava/lang/String;
   4:	areturn
  LineNumberTable: 
   line 72: 0


}

