Compiled from "WrappedArray.scala"
public final class scala.collection.mutable.WrappedArray$ extends java.lang.Object implements scala.ScalaObject
  SourceFile: "WrappedArray.scala"
  Scala: length = 0x
   
  InnerClass: 
   public final #133= #130 of #132; //ofInt=class scala/collection/mutable/WrappedArray$ofInt of class scala/collection/mutable/WrappedArray
   public final #136= #135 of #132; //ofRef=class scala/collection/mutable/WrappedArray$ofRef of class scala/collection/mutable/WrappedArray
   public final #139= #138 of #132; //ofUnit=class scala/collection/mutable/WrappedArray$ofUnit of class scala/collection/mutable/WrappedArray
   public final #142= #141 of #132; //ofLong=class scala/collection/mutable/WrappedArray$ofLong of class scala/collection/mutable/WrappedArray
   public final #145= #144 of #132; //ofChar=class scala/collection/mutable/WrappedArray$ofChar of class scala/collection/mutable/WrappedArray
   public final #148= #147 of #132; //ofByte=class scala/collection/mutable/WrappedArray$ofByte of class scala/collection/mutable/WrappedArray
   public final #151= #150 of #132; //ofFloat=class scala/collection/mutable/WrappedArray$ofFloat of class scala/collection/mutable/WrappedArray
   public final #154= #153 of #132; //ofShort=class scala/collection/mutable/WrappedArray$ofShort of class scala/collection/mutable/WrappedArray
   public final #155= #30 of #132; //$anon$1=class scala/collection/mutable/WrappedArray$$anon$1 of class scala/collection/mutable/WrappedArray
   public final #158= #157 of #132; //ofDouble=class scala/collection/mutable/WrappedArray$ofDouble of class scala/collection/mutable/WrappedArray
   public final #161= #160 of #132; //ofBoolean=class scala/collection/mutable/WrappedArray$ofBoolean of class scala/collection/mutable/WrappedArray
  minor version: 0
  major version: 49
  Constant pool:
const #1 = Asciz	SourceFile;
const #2 = Asciz	WrappedArray.scala;
const #3 = Asciz	Scala;
const #4 = Asciz	MODULE$;
const #5 = Asciz	Lscala/collection/mutable/WrappedArray$;;
const #6 = Asciz	<clinit>;
const #7 = Asciz	()V;
const #8 = Asciz	Code;
const #9 = Asciz	scala/collection/mutable/WrappedArray$;
const #10 = class	#9;	//  scala/collection/mutable/WrappedArray$
const #11 = Asciz	<init>;
const #12 = NameAndType	#11:#7;//  "<init>":()V
const #13 = Method	#10.#12;	//  scala/collection/mutable/WrappedArray$."<init>":()V
const #14 = Asciz	LineNumberTable;
const #15 = Asciz	java/lang/Object;
const #16 = class	#15;	//  java/lang/Object
const #17 = Method	#16.#12;	//  java/lang/Object."<init>":()V
const #18 = NameAndType	#4:#5;//  MODULE$:Lscala/collection/mutable/WrappedArray$;
const #19 = Field	#10.#18;	//  scala/collection/mutable/WrappedArray$.MODULE$:Lscala/collection/mutable/WrappedArray$;
const #20 = Asciz	newBuilder;
const #21 = Asciz	()Lscala/collection/mutable/Builder;;
const #22 = Asciz	scala/collection/mutable/ArrayBuffer;
const #23 = class	#22;	//  scala/collection/mutable/ArrayBuffer
const #24 = Method	#23.#12;	//  scala/collection/mutable/ArrayBuffer."<init>":()V
const #25 = Asciz	<A:Ljava/lang/Object;>()Lscala/collection/mutable/Builder<TA;Lscala/collection/mutable/IndexedSeq<TA;>;>;;
const #26 = Asciz	Signature;
const #27 = Asciz	canBuildFrom;
const #28 = Asciz	(Lscala/reflect/ClassManifest;)Lscala/collection/generic/CanBuildFrom;;
const #29 = Asciz	scala/collection/mutable/WrappedArray$$anon$1;
const #30 = class	#29;	//  scala/collection/mutable/WrappedArray$$anon$1
const #31 = Asciz	(Lscala/reflect/ClassManifest;)V;
const #32 = NameAndType	#11:#31;//  "<init>":(Lscala/reflect/ClassManifest;)V
const #33 = Method	#30.#32;	//  scala/collection/mutable/WrappedArray$$anon$1."<init>":(Lscala/reflect/ClassManifest;)V
const #34 = Asciz	this;
const #35 = Asciz	m$1;
const #36 = Asciz	Lscala/reflect/ClassManifest;;
const #37 = Asciz	LocalVariableTable;
const #38 = Asciz	<T:Ljava/lang/Object;>(Lscala/reflect/ClassManifest<TT;>;)Lscala/collection/generic/CanBuildFrom<Lscala/collection/mutable/WrappedArray<*>;TT;Lscala/collection/mutable/WrappedArray<TT;>;>;;
const #39 = Asciz	make;
const #40 = Asciz	(Ljava/lang/Object;)Lscala/collection/mutable/WrappedArray;;
const #41 = Asciz	[Ljava/lang/Object;;
const #42 = class	#41;	//  "[Ljava/lang/Object;"
const #43 = Asciz	scala/Predef$;
const #44 = class	#43;	//  scala/Predef$
const #45 = Asciz	Lscala/Predef$;;
const #46 = NameAndType	#4:#45;//  MODULE$:Lscala/Predef$;
const #47 = Field	#44.#46;	//  scala/Predef$.MODULE$:Lscala/Predef$;
const #48 = Asciz	wrapRefArray;
const #49 = Asciz	([Ljava/lang/Object;)Lscala/collection/mutable/WrappedArray;;
const #50 = NameAndType	#48:#49;//  wrapRefArray:([Ljava/lang/Object;)Lscala/collection/mutable/WrappedArray;
const #51 = Method	#44.#50;	//  scala/Predef$.wrapRefArray:([Ljava/lang/Object;)Lscala/collection/mutable/WrappedArray;
const #52 = Asciz	scala/MatchError;
const #53 = class	#52;	//  scala/MatchError
const #54 = Asciz	toString;
const #55 = Asciz	()Ljava/lang/String;;
const #56 = NameAndType	#54:#55;//  toString:()Ljava/lang/String;
const #57 = Method	#16.#56;	//  java/lang/Object.toString:()Ljava/lang/String;
const #58 = Asciz	(Ljava/lang/String;)V;
const #59 = NameAndType	#11:#58;//  "<init>":(Ljava/lang/String;)V
const #60 = Method	#53.#59;	//  scala/MatchError."<init>":(Ljava/lang/String;)V
const #61 = Asciz	[I;
const #62 = class	#61;	//  "[I"
const #63 = Asciz	wrapIntArray;
const #64 = Asciz	([I)Lscala/collection/mutable/WrappedArray;;
const #65 = NameAndType	#63:#64;//  wrapIntArray:([I)Lscala/collection/mutable/WrappedArray;
const #66 = Method	#44.#65;	//  scala/Predef$.wrapIntArray:([I)Lscala/collection/mutable/WrappedArray;
const #67 = Asciz	[D;
const #68 = class	#67;	//  "[D"
const #69 = Asciz	wrapDoubleArray;
const #70 = Asciz	([D)Lscala/collection/mutable/WrappedArray;;
const #71 = NameAndType	#69:#70;//  wrapDoubleArray:([D)Lscala/collection/mutable/WrappedArray;
const #72 = Method	#44.#71;	//  scala/Predef$.wrapDoubleArray:([D)Lscala/collection/mutable/WrappedArray;
const #73 = Asciz	[J;
const #74 = class	#73;	//  "[J"
const #75 = Asciz	wrapLongArray;
const #76 = Asciz	([J)Lscala/collection/mutable/WrappedArray;;
const #77 = NameAndType	#75:#76;//  wrapLongArray:([J)Lscala/collection/mutable/WrappedArray;
const #78 = Method	#44.#77;	//  scala/Predef$.wrapLongArray:([J)Lscala/collection/mutable/WrappedArray;
const #79 = Asciz	[F;
const #80 = class	#79;	//  "[F"
const #81 = Asciz	wrapFloatArray;
const #82 = Asciz	([F)Lscala/collection/mutable/WrappedArray;;
const #83 = NameAndType	#81:#82;//  wrapFloatArray:([F)Lscala/collection/mutable/WrappedArray;
const #84 = Method	#44.#83;	//  scala/Predef$.wrapFloatArray:([F)Lscala/collection/mutable/WrappedArray;
const #85 = Asciz	[C;
const #86 = class	#85;	//  "[C"
const #87 = Asciz	wrapCharArray;
const #88 = Asciz	([C)Lscala/collection/mutable/WrappedArray;;
const #89 = NameAndType	#87:#88;//  wrapCharArray:([C)Lscala/collection/mutable/WrappedArray;
const #90 = Method	#44.#89;	//  scala/Predef$.wrapCharArray:([C)Lscala/collection/mutable/WrappedArray;
const #91 = Asciz	[B;
const #92 = class	#91;	//  "[B"
const #93 = Asciz	wrapByteArray;
const #94 = Asciz	([B)Lscala/collection/mutable/WrappedArray;;
const #95 = NameAndType	#93:#94;//  wrapByteArray:([B)Lscala/collection/mutable/WrappedArray;
const #96 = Method	#44.#95;	//  scala/Predef$.wrapByteArray:([B)Lscala/collection/mutable/WrappedArray;
const #97 = Asciz	[S;
const #98 = class	#97;	//  "[S"
const #99 = Asciz	wrapShortArray;
const #100 = Asciz	([S)Lscala/collection/mutable/WrappedArray;;
const #101 = NameAndType	#99:#100;//  wrapShortArray:([S)Lscala/collection/mutable/WrappedArray;
const #102 = Method	#44.#101;	//  scala/Predef$.wrapShortArray:([S)Lscala/collection/mutable/WrappedArray;
const #103 = Asciz	[Z;
const #104 = class	#103;	//  "[Z"
const #105 = Asciz	wrapBooleanArray;
const #106 = Asciz	([Z)Lscala/collection/mutable/WrappedArray;;
const #107 = NameAndType	#105:#106;//  wrapBooleanArray:([Z)Lscala/collection/mutable/WrappedArray;
const #108 = Method	#44.#107;	//  scala/Predef$.wrapBooleanArray:([Z)Lscala/collection/mutable/WrappedArray;
const #109 = Asciz	[Lscala/runtime/BoxedUnit;;
const #110 = class	#109;	//  "[Lscala/runtime/BoxedUnit;"
const #111 = Asciz	wrapUnitArray;
const #112 = Asciz	([Lscala/runtime/BoxedUnit;)Lscala/collection/mutable/WrappedArray;;
const #113 = NameAndType	#111:#112;//  wrapUnitArray:([Lscala/runtime/BoxedUnit;)Lscala/collection/mutable/WrappedArray;
const #114 = Method	#44.#113;	//  scala/Predef$.wrapUnitArray:([Lscala/runtime/BoxedUnit;)Lscala/collection/mutable/WrappedArray;
const #115 = Asciz	x;
const #116 = Asciz	Ljava/lang/Object;;
const #117 = Asciz	temp2;
const #118 = Asciz	temp3;
const #119 = Asciz	temp4;
const #120 = Asciz	temp5;
const #121 = Asciz	temp6;
const #122 = Asciz	temp7;
const #123 = Asciz	temp8;
const #124 = Asciz	temp9;
const #125 = Asciz	temp10;
const #126 = Asciz	temp11;
const #127 = Asciz	<T:Ljava/lang/Object;>(Ljava/lang/Object;)Lscala/collection/mutable/WrappedArray<TT;>;;
const #128 = Asciz	InnerClasses;
const #129 = Asciz	scala/collection/mutable/WrappedArray$ofInt;
const #130 = class	#129;	//  scala/collection/mutable/WrappedArray$ofInt
const #131 = Asciz	scala/collection/mutable/WrappedArray;
const #132 = class	#131;	//  scala/collection/mutable/WrappedArray
const #133 = Asciz	ofInt;
const #134 = Asciz	scala/collection/mutable/WrappedArray$ofRef;
const #135 = class	#134;	//  scala/collection/mutable/WrappedArray$ofRef
const #136 = Asciz	ofRef;
const #137 = Asciz	scala/collection/mutable/WrappedArray$ofUnit;
const #138 = class	#137;	//  scala/collection/mutable/WrappedArray$ofUnit
const #139 = Asciz	ofUnit;
const #140 = Asciz	scala/collection/mutable/WrappedArray$ofLong;
const #141 = class	#140;	//  scala/collection/mutable/WrappedArray$ofLong
const #142 = Asciz	ofLong;
const #143 = Asciz	scala/collection/mutable/WrappedArray$ofChar;
const #144 = class	#143;	//  scala/collection/mutable/WrappedArray$ofChar
const #145 = Asciz	ofChar;
const #146 = Asciz	scala/collection/mutable/WrappedArray$ofByte;
const #147 = class	#146;	//  scala/collection/mutable/WrappedArray$ofByte
const #148 = Asciz	ofByte;
const #149 = Asciz	scala/collection/mutable/WrappedArray$ofFloat;
const #150 = class	#149;	//  scala/collection/mutable/WrappedArray$ofFloat
const #151 = Asciz	ofFloat;
const #152 = Asciz	scala/collection/mutable/WrappedArray$ofShort;
const #153 = class	#152;	//  scala/collection/mutable/WrappedArray$ofShort
const #154 = Asciz	ofShort;
const #155 = Asciz	$anon$1;
const #156 = Asciz	scala/collection/mutable/WrappedArray$ofDouble;
const #157 = class	#156;	//  scala/collection/mutable/WrappedArray$ofDouble
const #158 = Asciz	ofDouble;
const #159 = Asciz	scala/collection/mutable/WrappedArray$ofBoolean;
const #160 = class	#159;	//  scala/collection/mutable/WrappedArray$ofBoolean
const #161 = Asciz	ofBoolean;
const #162 = Asciz	scala/ScalaObject;
const #163 = class	#162;	//  scala/ScalaObject

{
public static final scala.collection.mutable.WrappedArray$ MODULE$;

public static {};
  Code:
   Stack=1, Locals=0, Args_size=0
   0:	new	#10; //class scala/collection/mutable/WrappedArray$
   3:	invokespecial	#13; //Method "<init>":()V
   6:	return

public scala.collection.mutable.Builder newBuilder();
  Code:
   Stack=2, Locals=1, Args_size=1
   0:	new	#23; //class scala/collection/mutable/ArrayBuffer
   3:	dup
   4:	invokespecial	#24; //Method scala/collection/mutable/ArrayBuffer."<init>":()V
   7:	areturn
  LineNumberTable: 
   line 75: 0

  Signature: length = 0x2
   00 19 

public scala.collection.generic.CanBuildFrom canBuildFrom(scala.reflect.ClassManifest);
  Code:
   Stack=3, Locals=2, Args_size=2
   0:	new	#30; //class scala/collection/mutable/WrappedArray$$anon$1
   3:	dup
   4:	aload_1
   5:	invokespecial	#33; //Method scala/collection/mutable/WrappedArray$$anon$1."<init>":(Lscala/reflect/ClassManifest;)V
   8:	areturn
  LineNumberTable: 
   line 68: 0

  LocalVariableTable: 
   Start  Length  Slot  Name   Signature
   0      9      0    this       Lscala/collection/mutable/WrappedArray$;
   0      9      1    m$1       Lscala/reflect/ClassManifest;

  Signature: length = 0x2
   00 26 

public scala.collection.mutable.WrappedArray make(java.lang.Object);
  Code:
   Stack=3, Locals=12, Args_size=2
   0:	aload_1
   1:	instanceof	#42; //class "[Ljava/lang/Object;"
   4:	ifeq	38
   7:	aload_1
   8:	checkcast	#42; //class "[Ljava/lang/Object;"
   11:	astore_2
   12:	iconst_1
   13:	ifeq	26
   16:	getstatic	#47; //Field scala/Predef$.MODULE$:Lscala/Predef$;
   19:	aload_2
   20:	invokevirtual	#51; //Method scala/Predef$.wrapRefArray:([Ljava/lang/Object;)Lscala/collection/mutable/WrappedArray;
   23:	goto	381
   26:	new	#53; //class scala/MatchError
   29:	dup
   30:	aload_1
   31:	invokevirtual	#57; //Method java/lang/Object.toString:()Ljava/lang/String;
   34:	invokespecial	#60; //Method scala/MatchError."<init>":(Ljava/lang/String;)V
   37:	athrow
   38:	aload_1
   39:	instanceof	#62; //class "[I"
   42:	ifeq	76
   45:	aload_1
   46:	checkcast	#62; //class "[I"
   49:	astore_3
   50:	iconst_1
   51:	ifeq	64
   54:	getstatic	#47; //Field scala/Predef$.MODULE$:Lscala/Predef$;
   57:	aload_3
   58:	invokevirtual	#66; //Method scala/Predef$.wrapIntArray:([I)Lscala/collection/mutable/WrappedArray;
   61:	goto	381
   64:	new	#53; //class scala/MatchError
   67:	dup
   68:	aload_1
   69:	invokevirtual	#57; //Method java/lang/Object.toString:()Ljava/lang/String;
   72:	invokespecial	#60; //Method scala/MatchError."<init>":(Ljava/lang/String;)V
   75:	athrow
   76:	aload_1
   77:	instanceof	#68; //class "[D"
   80:	ifeq	116
   83:	aload_1
   84:	checkcast	#68; //class "[D"
   87:	astore	4
   89:	iconst_1
   90:	ifeq	104
   93:	getstatic	#47; //Field scala/Predef$.MODULE$:Lscala/Predef$;
   96:	aload	4
   98:	invokevirtual	#72; //Method scala/Predef$.wrapDoubleArray:([D)Lscala/collection/mutable/WrappedArray;
   101:	goto	381
   104:	new	#53; //class scala/MatchError
   107:	dup
   108:	aload_1
   109:	invokevirtual	#57; //Method java/lang/Object.toString:()Ljava/lang/String;
   112:	invokespecial	#60; //Method scala/MatchError."<init>":(Ljava/lang/String;)V
   115:	athrow
   116:	aload_1
   117:	instanceof	#74; //class "[J"
   120:	ifeq	156
   123:	aload_1
   124:	checkcast	#74; //class "[J"
   127:	astore	5
   129:	iconst_1
   130:	ifeq	144
   133:	getstatic	#47; //Field scala/Predef$.MODULE$:Lscala/Predef$;
   136:	aload	5
   138:	invokevirtual	#78; //Method scala/Predef$.wrapLongArray:([J)Lscala/collection/mutable/WrappedArray;
   141:	goto	381
   144:	new	#53; //class scala/MatchError
   147:	dup
   148:	aload_1
   149:	invokevirtual	#57; //Method java/lang/Object.toString:()Ljava/lang/String;
   152:	invokespecial	#60; //Method scala/MatchError."<init>":(Ljava/lang/String;)V
   155:	athrow
   156:	aload_1
   157:	instanceof	#80; //class "[F"
   160:	ifeq	196
   163:	aload_1
   164:	checkcast	#80; //class "[F"
   167:	astore	6
   169:	iconst_1
   170:	ifeq	184
   173:	getstatic	#47; //Field scala/Predef$.MODULE$:Lscala/Predef$;
   176:	aload	6
   178:	invokevirtual	#84; //Method scala/Predef$.wrapFloatArray:([F)Lscala/collection/mutable/WrappedArray;
   181:	goto	381
   184:	new	#53; //class scala/MatchError
   187:	dup
   188:	aload_1
   189:	invokevirtual	#57; //Method java/lang/Object.toString:()Ljava/lang/String;
   192:	invokespecial	#60; //Method scala/MatchError."<init>":(Ljava/lang/String;)V
   195:	athrow
   196:	aload_1
   197:	instanceof	#86; //class "[C"
   200:	ifeq	236
   203:	aload_1
   204:	checkcast	#86; //class "[C"
   207:	astore	7
   209:	iconst_1
   210:	ifeq	224
   213:	getstatic	#47; //Field scala/Predef$.MODULE$:Lscala/Predef$;
   216:	aload	7
   218:	invokevirtual	#90; //Method scala/Predef$.wrapCharArray:([C)Lscala/collection/mutable/WrappedArray;
   221:	goto	381
   224:	new	#53; //class scala/MatchError
   227:	dup
   228:	aload_1
   229:	invokevirtual	#57; //Method java/lang/Object.toString:()Ljava/lang/String;
   232:	invokespecial	#60; //Method scala/MatchError."<init>":(Ljava/lang/String;)V
   235:	athrow
   236:	aload_1
   237:	instanceof	#92; //class "[B"
   240:	ifeq	276
   243:	aload_1
   244:	checkcast	#92; //class "[B"
   247:	astore	8
   249:	iconst_1
   250:	ifeq	264
   253:	getstatic	#47; //Field scala/Predef$.MODULE$:Lscala/Predef$;
   256:	aload	8
   258:	invokevirtual	#96; //Method scala/Predef$.wrapByteArray:([B)Lscala/collection/mutable/WrappedArray;
   261:	goto	381
   264:	new	#53; //class scala/MatchError
   267:	dup
   268:	aload_1
   269:	invokevirtual	#57; //Method java/lang/Object.toString:()Ljava/lang/String;
   272:	invokespecial	#60; //Method scala/MatchError."<init>":(Ljava/lang/String;)V
   275:	athrow
   276:	aload_1
   277:	instanceof	#98; //class "[S"
   280:	ifeq	316
   283:	aload_1
   284:	checkcast	#98; //class "[S"
   287:	astore	9
   289:	iconst_1
   290:	ifeq	304
   293:	getstatic	#47; //Field scala/Predef$.MODULE$:Lscala/Predef$;
   296:	aload	9
   298:	invokevirtual	#102; //Method scala/Predef$.wrapShortArray:([S)Lscala/collection/mutable/WrappedArray;
   301:	goto	381
   304:	new	#53; //class scala/MatchError
   307:	dup
   308:	aload_1
   309:	invokevirtual	#57; //Method java/lang/Object.toString:()Ljava/lang/String;
   312:	invokespecial	#60; //Method scala/MatchError."<init>":(Ljava/lang/String;)V
   315:	athrow
   316:	aload_1
   317:	instanceof	#104; //class "[Z"
   320:	ifeq	356
   323:	aload_1
   324:	checkcast	#104; //class "[Z"
   327:	astore	10
   329:	iconst_1
   330:	ifeq	344
   333:	getstatic	#47; //Field scala/Predef$.MODULE$:Lscala/Predef$;
   336:	aload	10
   338:	invokevirtual	#108; //Method scala/Predef$.wrapBooleanArray:([Z)Lscala/collection/mutable/WrappedArray;
   341:	goto	381
   344:	new	#53; //class scala/MatchError
   347:	dup
   348:	aload_1
   349:	invokevirtual	#57; //Method java/lang/Object.toString:()Ljava/lang/String;
   352:	invokespecial	#60; //Method scala/MatchError."<init>":(Ljava/lang/String;)V
   355:	athrow
   356:	aload_1
   357:	instanceof	#110; //class "[Lscala/runtime/BoxedUnit;"
   360:	ifeq	394
   363:	aload_1
   364:	checkcast	#110; //class "[Lscala/runtime/BoxedUnit;"
   367:	astore	11
   369:	iconst_1
   370:	ifeq	382
   373:	getstatic	#47; //Field scala/Predef$.MODULE$:Lscala/Predef$;
   376:	aload	11
   378:	invokevirtual	#114; //Method scala/Predef$.wrapUnitArray:([Lscala/runtime/BoxedUnit;)Lscala/collection/mutable/WrappedArray;
   381:	areturn
   382:	new	#53; //class scala/MatchError
   385:	dup
   386:	aload_1
   387:	invokevirtual	#57; //Method java/lang/Object.toString:()Ljava/lang/String;
   390:	invokespecial	#60; //Method scala/MatchError."<init>":(Ljava/lang/String;)V
   393:	athrow
   394:	new	#53; //class scala/MatchError
   397:	dup
   398:	aload_1
   399:	invokevirtual	#57; //Method java/lang/Object.toString:()Ljava/lang/String;
   402:	invokespecial	#60; //Method scala/MatchError."<init>":(Ljava/lang/String;)V
   405:	athrow
  LineNumberTable: 
   line 54: 0
   line 21: 12
   line 55: 16
   line 54: 26
   line 21: 50
   line 56: 54
   line 54: 64
   line 21: 89
   line 57: 93
   line 54: 104
   line 21: 129
   line 58: 133
   line 54: 144
   line 21: 169
   line 59: 173
   line 54: 184
   line 21: 209
   line 60: 213
   line 54: 224
   line 21: 249
   line 61: 253
   line 54: 264
   line 21: 289
   line 62: 293
   line 54: 304
   line 21: 329
   line 63: 333
   line 54: 344
   line 21: 369
   line 64: 373
   line 54: 381

  LocalVariableTable: 
   Start  Length  Slot  Name   Signature
   0      406      0    this       Lscala/collection/mutable/WrappedArray$;
   0      406      1    x       Ljava/lang/Object;
   12      26      2    temp2       [Ljava/lang/Object;
   50      26      3    temp3       [I
   89      27      4    temp4       [D
   129      27      5    temp5       [J
   169      27      6    temp6       [F
   209      27      7    temp7       [C
   249      27      8    temp8       [B
   289      27      9    temp9       [S
   329      27      10    temp10       [Z
   369      12      11    temp11       [Lscala/runtime/BoxedUnit;
   382      12      11    temp11       [Lscala/runtime/BoxedUnit;

  Signature: length = 0x2
   00 7F 

}

