Compiled from "WrappedArray.scala"
public final class scala.collection.mutable.WrappedArray$ofByte extends scala.collection.mutable.WrappedArray implements scala.ScalaObject,java.io.Serializable
  SourceFile: "WrappedArray.scala"
  Signature: length = 0x2
   00 49 
  Scala: length = 0x
   
  InnerClass: 
   public final #77= #10 of #14; //ofByte=class scala/collection/mutable/WrappedArray$ofByte of class scala/collection/mutable/WrappedArray
  minor version: 0
  major version: 49
  Constant pool:
const #1 = Asciz	SourceFile;
const #2 = Asciz	WrappedArray.scala;
const #3 = Asciz	array;
const #4 = Asciz	[B;
const #5 = Asciz	<init>;
const #6 = Asciz	([B)V;
const #7 = Asciz	Code;
const #8 = Asciz	LineNumberTable;
const #9 = Asciz	scala/collection/mutable/WrappedArray$ofByte;
const #10 = class	#9;	//  scala/collection/mutable/WrappedArray$ofByte
const #11 = NameAndType	#3:#4;//  array:[B
const #12 = Field	#10.#11;	//  scala/collection/mutable/WrappedArray$ofByte.array:[B
const #13 = Asciz	scala/collection/mutable/WrappedArray;
const #14 = class	#13;	//  scala/collection/mutable/WrappedArray
const #15 = Asciz	()V;
const #16 = NameAndType	#5:#15;//  "<init>":()V
const #17 = Method	#14.#16;	//  scala/collection/mutable/WrappedArray."<init>":()V
const #18 = Asciz	this;
const #19 = Asciz	Lscala/collection/mutable/WrappedArray$ofByte;;
const #20 = Asciz	LocalVariableTable;
const #21 = Asciz	()Ljava/lang/Object;;
const #22 = Asciz	()[B;
const #23 = NameAndType	#3:#22;//  array:()[B
const #24 = Method	#10.#23;	//  scala/collection/mutable/WrappedArray$ofByte.array:()[B
const #25 = Asciz	elemManifest;
const #26 = Asciz	()Lscala/reflect/ClassManifest;;
const #27 = NameAndType	#25:#21;//  elemManifest:()Ljava/lang/Object;
const #28 = Method	#10.#27;	//  scala/collection/mutable/WrappedArray$ofByte.elemManifest:()Ljava/lang/Object;
const #29 = Asciz	scala/reflect/ClassManifest;
const #30 = class	#29;	//  scala/reflect/ClassManifest
const #31 = Asciz	apply;
const #32 = Asciz	(I)Ljava/lang/Object;;
const #33 = Asciz	(I)B;
const #34 = NameAndType	#31:#33;//  apply:(I)B
const #35 = Method	#10.#34;	//  scala/collection/mutable/WrappedArray$ofByte.apply:(I)B
const #36 = Asciz	scala/runtime/BoxesRunTime;
const #37 = class	#36;	//  scala/runtime/BoxesRunTime
const #38 = Asciz	boxToByte;
const #39 = Asciz	(B)Ljava/lang/Byte;;
const #40 = NameAndType	#38:#39;//  boxToByte:(B)Ljava/lang/Byte;
const #41 = Method	#37.#40;	//  scala/runtime/BoxesRunTime.boxToByte:(B)Ljava/lang/Byte;
const #42 = Asciz	index;
const #43 = Asciz	I;
const #44 = Asciz	(Ljava/lang/Object;)Ljava/lang/Object;;
const #45 = Asciz	unboxToInt;
const #46 = Asciz	(Ljava/lang/Object;)I;
const #47 = NameAndType	#45:#46;//  unboxToInt:(Ljava/lang/Object;)I
const #48 = Method	#37.#47;	//  scala/runtime/BoxesRunTime.unboxToInt:(Ljava/lang/Object;)I
const #49 = Asciz	v1;
const #50 = Asciz	Ljava/lang/Object;;
const #51 = Asciz	update;
const #52 = Asciz	(ILjava/lang/Object;)V;
const #53 = Asciz	unboxToByte;
const #54 = Asciz	(Ljava/lang/Object;)B;
const #55 = NameAndType	#53:#54;//  unboxToByte:(Ljava/lang/Object;)B
const #56 = Method	#37.#55;	//  scala/runtime/BoxesRunTime.unboxToByte:(Ljava/lang/Object;)B
const #57 = Asciz	(IB)V;
const #58 = NameAndType	#51:#57;//  update:(IB)V
const #59 = Method	#10.#58;	//  scala/collection/mutable/WrappedArray$ofByte.update:(IB)V
const #60 = Asciz	elem;
const #61 = Asciz	B;
const #62 = Asciz	length;
const #63 = Asciz	()I;
const #64 = Asciz	scala/reflect/ClassManifest$;
const #65 = class	#64;	//  scala/reflect/ClassManifest$
const #66 = Asciz	MODULE$;
const #67 = Asciz	Lscala/reflect/ClassManifest$;;
const #68 = NameAndType	#66:#67;//  MODULE$:Lscala/reflect/ClassManifest$;
const #69 = Field	#65.#68;	//  scala/reflect/ClassManifest$.MODULE$:Lscala/reflect/ClassManifest$;
const #70 = Asciz	Byte;
const #71 = NameAndType	#70:#21;//  Byte:()Ljava/lang/Object;
const #72 = Method	#65.#71;	//  scala/reflect/ClassManifest$.Byte:()Ljava/lang/Object;
const #73 = Asciz	Lscala/collection/mutable/WrappedArray<Ljava/lang/Byte;>;Lscala/ScalaObject;;
const #74 = Asciz	Signature;
const #75 = Asciz	Scala;
const #76 = Asciz	InnerClasses;
const #77 = Asciz	ofByte;
const #78 = Asciz	scala/ScalaObject;
const #79 = class	#78;	//  scala/ScalaObject
const #80 = Asciz	java/io/Serializable;
const #81 = class	#80;	//  java/io/Serializable

{
public final byte[] array;

public scala.collection.mutable.WrappedArray$ofByte(byte[]);
  Code:
   Stack=2, Locals=2, Args_size=2
   0:	aload_0
   1:	aload_1
   2:	putfield	#12; //Field array:[B
   5:	aload_0
   6:	invokespecial	#17; //Method scala/collection/mutable/WrappedArray."<init>":()V
   9:	return
  LineNumberTable: 
   line 86: 0

  LocalVariableTable: 
   Start  Length  Slot  Name   Signature
   0      10      0    this       Lscala/collection/mutable/WrappedArray$ofByte;
   0      10      1    array       [B


public java.lang.Object array();
  Code:
   Stack=1, Locals=1, Args_size=1
   0:	aload_0
   1:	invokevirtual	#24; //Method array:()[B
   4:	areturn
  LineNumberTable: 
   line 86: 0


public scala.reflect.ClassManifest elemManifest();
  Code:
   Stack=1, Locals=1, Args_size=1
   0:	aload_0
   1:	invokevirtual	#28; //Method elemManifest:()Ljava/lang/Object;
   4:	checkcast	#30; //class scala/reflect/ClassManifest
   7:	areturn
  LineNumberTable: 
   line 86: 0


public java.lang.Object apply(int);
  Code:
   Stack=2, Locals=3, Args_size=2
   0:	aload_0
   1:	iload_1
   2:	invokevirtual	#35; //Method apply:(I)B
   5:	istore_2
   6:	iload_2
   7:	invokestatic	#41; //Method scala/runtime/BoxesRunTime.boxToByte:(B)Ljava/lang/Byte;
   10:	areturn
  LineNumberTable: 
   line 86: 0

  LocalVariableTable: 
   Start  Length  Slot  Name   Signature
   0      11      0    this       Lscala/collection/mutable/WrappedArray$ofByte;
   0      11      1    index       I


public java.lang.Object apply(java.lang.Object);
  Code:
   Stack=2, Locals=3, Args_size=2
   0:	aload_0
   1:	aload_1
   2:	invokestatic	#48; //Method scala/runtime/BoxesRunTime.unboxToInt:(Ljava/lang/Object;)I
   5:	invokevirtual	#35; //Method apply:(I)B
   8:	istore_2
   9:	iload_2
   10:	invokestatic	#41; //Method scala/runtime/BoxesRunTime.boxToByte:(B)Ljava/lang/Byte;
   13:	areturn
  LineNumberTable: 
   line 86: 0

  LocalVariableTable: 
   Start  Length  Slot  Name   Signature
   0      14      0    this       Lscala/collection/mutable/WrappedArray$ofByte;
   0      14      1    v1       Ljava/lang/Object;


public void update(int, java.lang.Object);
  Code:
   Stack=3, Locals=3, Args_size=3
   0:	aload_0
   1:	iload_1
   2:	aload_2
   3:	invokestatic	#56; //Method scala/runtime/BoxesRunTime.unboxToByte:(Ljava/lang/Object;)B
   6:	invokevirtual	#59; //Method update:(IB)V
   9:	return
  LineNumberTable: 
   line 86: 0

  LocalVariableTable: 
   Start  Length  Slot  Name   Signature
   0      10      0    this       Lscala/collection/mutable/WrappedArray$ofByte;
   0      10      1    index       I
   0      10      2    elem       Ljava/lang/Object;


public void update(int, byte);
  Code:
   Stack=3, Locals=3, Args_size=3
   0:	aload_0
   1:	invokevirtual	#24; //Method array:()[B
   4:	iload_1
   5:	iload_2
   6:	bastore
   7:	return
  LineNumberTable: 
   line 90: 0

  LocalVariableTable: 
   Start  Length  Slot  Name   Signature
   0      8      0    this       Lscala/collection/mutable/WrappedArray$ofByte;
   0      8      1    index       I
   0      8      2    elem       B


public byte apply(int);
  Code:
   Stack=2, Locals=2, Args_size=2
   0:	aload_0
   1:	invokevirtual	#24; //Method array:()[B
   4:	iload_1
   5:	baload
   6:	ireturn
  LineNumberTable: 
   line 89: 0

  LocalVariableTable: 
   Start  Length  Slot  Name   Signature
   0      7      0    this       Lscala/collection/mutable/WrappedArray$ofByte;
   0      7      1    index       I


public int length();
  Code:
   Stack=1, Locals=1, Args_size=1
   0:	aload_0
   1:	invokevirtual	#24; //Method array:()[B
   4:	arraylength
   5:	ireturn
  LineNumberTable: 
   line 88: 0


public java.lang.Object elemManifest();
  Code:
   Stack=1, Locals=1, Args_size=1
   0:	getstatic	#69; //Field scala/reflect/ClassManifest$.MODULE$:Lscala/reflect/ClassManifest$;
   3:	invokevirtual	#72; //Method scala/reflect/ClassManifest$.Byte:()Ljava/lang/Object;
   6:	areturn
  LineNumberTable: 
   line 87: 0


public byte[] array();
  Code:
   Stack=1, Locals=1, Args_size=1
   0:	aload_0
   1:	getfield	#12; //Field array:[B
   4:	areturn
  LineNumberTable: 
   line 86: 0


}

