Compiled from "WrappedArray.scala"
public final class scala.collection.mutable.WrappedArray$ofUnit extends scala.collection.mutable.WrappedArray implements scala.ScalaObject,java.io.Serializable
  SourceFile: "WrappedArray.scala"
  Signature: length = 0x2
   00 47 
  Scala: length = 0x
   
  InnerClass: 
   public final #74= #10 of #14; //ofUnit=class scala/collection/mutable/WrappedArray$ofUnit of class scala/collection/mutable/WrappedArray
  minor version: 0
  major version: 49
  Constant pool:
const #1 = Asciz	SourceFile;
const #2 = Asciz	WrappedArray.scala;
const #3 = Asciz	array;
const #4 = Asciz	[Lscala/runtime/BoxedUnit;;
const #5 = Asciz	<init>;
const #6 = Asciz	([Lscala/runtime/BoxedUnit;)V;
const #7 = Asciz	Code;
const #8 = Asciz	LineNumberTable;
const #9 = Asciz	scala/collection/mutable/WrappedArray$ofUnit;
const #10 = class	#9;	//  scala/collection/mutable/WrappedArray$ofUnit
const #11 = NameAndType	#3:#4;//  array:[Lscala/runtime/BoxedUnit;
const #12 = Field	#10.#11;	//  scala/collection/mutable/WrappedArray$ofUnit.array:[Lscala/runtime/BoxedUnit;
const #13 = Asciz	scala/collection/mutable/WrappedArray;
const #14 = class	#13;	//  scala/collection/mutable/WrappedArray
const #15 = Asciz	()V;
const #16 = NameAndType	#5:#15;//  "<init>":()V
const #17 = Method	#14.#16;	//  scala/collection/mutable/WrappedArray."<init>":()V
const #18 = Asciz	this;
const #19 = Asciz	Lscala/collection/mutable/WrappedArray$ofUnit;;
const #20 = Asciz	LocalVariableTable;
const #21 = Asciz	()Ljava/lang/Object;;
const #22 = Asciz	()[Lscala/runtime/BoxedUnit;;
const #23 = NameAndType	#3:#22;//  array:()[Lscala/runtime/BoxedUnit;
const #24 = Method	#10.#23;	//  scala/collection/mutable/WrappedArray$ofUnit.array:()[Lscala/runtime/BoxedUnit;
const #25 = Asciz	elemManifest;
const #26 = Asciz	()Lscala/reflect/ClassManifest;;
const #27 = Asciz	()Lscala/reflect/AnyValManifest;;
const #28 = NameAndType	#25:#27;//  elemManifest:()Lscala/reflect/AnyValManifest;
const #29 = Method	#10.#28;	//  scala/collection/mutable/WrappedArray$ofUnit.elemManifest:()Lscala/reflect/AnyValManifest;
const #30 = Asciz	apply;
const #31 = Asciz	(I)Ljava/lang/Object;;
const #32 = Asciz	(I)V;
const #33 = NameAndType	#30:#32;//  apply:(I)V
const #34 = Method	#10.#33;	//  scala/collection/mutable/WrappedArray$ofUnit.apply:(I)V
const #35 = Asciz	scala/runtime/BoxedUnit;
const #36 = class	#35;	//  scala/runtime/BoxedUnit
const #37 = Asciz	UNIT;
const #38 = Asciz	Lscala/runtime/BoxedUnit;;
const #39 = NameAndType	#37:#38;//  UNIT:Lscala/runtime/BoxedUnit;
const #40 = Field	#36.#39;	//  scala/runtime/BoxedUnit.UNIT:Lscala/runtime/BoxedUnit;
const #41 = Asciz	index;
const #42 = Asciz	I;
const #43 = Asciz	(Ljava/lang/Object;)Ljava/lang/Object;;
const #44 = Asciz	scala/runtime/BoxesRunTime;
const #45 = class	#44;	//  scala/runtime/BoxesRunTime
const #46 = Asciz	unboxToInt;
const #47 = Asciz	(Ljava/lang/Object;)I;
const #48 = NameAndType	#46:#47;//  unboxToInt:(Ljava/lang/Object;)I
const #49 = Method	#45.#48;	//  scala/runtime/BoxesRunTime.unboxToInt:(Ljava/lang/Object;)I
const #50 = Asciz	v1;
const #51 = Asciz	Ljava/lang/Object;;
const #52 = Asciz	update;
const #53 = Asciz	(ILjava/lang/Object;)V;
const #54 = Asciz	(ILscala/runtime/BoxedUnit;)V;
const #55 = NameAndType	#52:#54;//  update:(ILscala/runtime/BoxedUnit;)V
const #56 = Method	#10.#55;	//  scala/collection/mutable/WrappedArray$ofUnit.update:(ILscala/runtime/BoxedUnit;)V
const #57 = Asciz	elem;
const #58 = Asciz	length;
const #59 = Asciz	()I;
const #60 = Asciz	scala/reflect/ClassManifest$;
const #61 = class	#60;	//  scala/reflect/ClassManifest$
const #62 = Asciz	MODULE$;
const #63 = Asciz	Lscala/reflect/ClassManifest$;;
const #64 = NameAndType	#62:#63;//  MODULE$:Lscala/reflect/ClassManifest$;
const #65 = Field	#61.#64;	//  scala/reflect/ClassManifest$.MODULE$:Lscala/reflect/ClassManifest$;
const #66 = Asciz	Unit;
const #67 = NameAndType	#66:#27;//  Unit:()Lscala/reflect/AnyValManifest;
const #68 = Method	#61.#67;	//  scala/reflect/ClassManifest$.Unit:()Lscala/reflect/AnyValManifest;
const #69 = Asciz	()Lscala/reflect/AnyValManifest<Ljava/lang/Object;>;;
const #70 = Asciz	Signature;
const #71 = Asciz	Lscala/collection/mutable/WrappedArray<Ljava/lang/Object;>;Lscala/ScalaObject;;
const #72 = Asciz	Scala;
const #73 = Asciz	InnerClasses;
const #74 = Asciz	ofUnit;
const #75 = Asciz	scala/ScalaObject;
const #76 = class	#75;	//  scala/ScalaObject
const #77 = Asciz	java/io/Serializable;
const #78 = class	#77;	//  java/io/Serializable

{
public final scala.runtime.BoxedUnit[] array;

public scala.collection.mutable.WrappedArray$ofUnit(scala.runtime.BoxedUnit[]);
  Code:
   Stack=2, Locals=2, Args_size=2
   0:	aload_0
   1:	aload_1
   2:	putfield	#12; //Field array:[Lscala/runtime/BoxedUnit;
   5:	aload_0
   6:	invokespecial	#17; //Method scala/collection/mutable/WrappedArray."<init>":()V
   9:	return
  LineNumberTable: 
   line 150: 0

  LocalVariableTable: 
   Start  Length  Slot  Name   Signature
   0      10      0    this       Lscala/collection/mutable/WrappedArray$ofUnit;
   0      10      1    array       [Lscala/runtime/BoxedUnit;


public java.lang.Object array();
  Code:
   Stack=1, Locals=1, Args_size=1
   0:	aload_0
   1:	invokevirtual	#24; //Method array:()[Lscala/runtime/BoxedUnit;
   4:	areturn
  LineNumberTable: 
   line 150: 0


public scala.reflect.ClassManifest elemManifest();
  Code:
   Stack=1, Locals=1, Args_size=1
   0:	aload_0
   1:	invokevirtual	#29; //Method elemManifest:()Lscala/reflect/AnyValManifest;
   4:	areturn
  LineNumberTable: 
   line 150: 0


public java.lang.Object apply(int);
  Code:
   Stack=2, Locals=2, Args_size=2
   0:	aload_0
   1:	iload_1
   2:	invokevirtual	#34; //Method apply:(I)V
   5:	getstatic	#40; //Field scala/runtime/BoxedUnit.UNIT:Lscala/runtime/BoxedUnit;
   8:	areturn
  LineNumberTable: 
   line 150: 0

  LocalVariableTable: 
   Start  Length  Slot  Name   Signature
   0      9      0    this       Lscala/collection/mutable/WrappedArray$ofUnit;
   0      9      1    index       I


public java.lang.Object apply(java.lang.Object);
  Code:
   Stack=2, Locals=2, Args_size=2
   0:	aload_0
   1:	aload_1
   2:	invokestatic	#49; //Method scala/runtime/BoxesRunTime.unboxToInt:(Ljava/lang/Object;)I
   5:	invokevirtual	#34; //Method apply:(I)V
   8:	getstatic	#40; //Field scala/runtime/BoxedUnit.UNIT:Lscala/runtime/BoxedUnit;
   11:	areturn
  LineNumberTable: 
   line 150: 0

  LocalVariableTable: 
   Start  Length  Slot  Name   Signature
   0      12      0    this       Lscala/collection/mutable/WrappedArray$ofUnit;
   0      12      1    v1       Ljava/lang/Object;


public void update(int, java.lang.Object);
  Code:
   Stack=3, Locals=3, Args_size=3
   0:	aload_0
   1:	iload_1
   2:	aload_2
   3:	checkcast	#36; //class scala/runtime/BoxedUnit
   6:	invokevirtual	#56; //Method update:(ILscala/runtime/BoxedUnit;)V
   9:	return
  LineNumberTable: 
   line 150: 0

  LocalVariableTable: 
   Start  Length  Slot  Name   Signature
   0      10      0    this       Lscala/collection/mutable/WrappedArray$ofUnit;
   0      10      1    index       I
   0      10      2    elem       Ljava/lang/Object;


public void update(int, scala.runtime.BoxedUnit);
  Code:
   Stack=3, Locals=3, Args_size=3
   0:	aload_0
   1:	invokevirtual	#24; //Method array:()[Lscala/runtime/BoxedUnit;
   4:	iload_1
   5:	aload_2
   6:	aastore
   7:	return
  LineNumberTable: 
   line 154: 0

  LocalVariableTable: 
   Start  Length  Slot  Name   Signature
   0      8      0    this       Lscala/collection/mutable/WrappedArray$ofUnit;
   0      8      1    index       I
   0      8      2    elem       Lscala/runtime/BoxedUnit;


public void apply(int);
  Code:
   Stack=0, Locals=2, Args_size=2
   0:	return
  LineNumberTable: 
   line 153: 0

  LocalVariableTable: 
   Start  Length  Slot  Name   Signature
   0      1      0    this       Lscala/collection/mutable/WrappedArray$ofUnit;
   0      1      1    index       I


public int length();
  Code:
   Stack=1, Locals=1, Args_size=1
   0:	aload_0
   1:	invokevirtual	#24; //Method array:()[Lscala/runtime/BoxedUnit;
   4:	arraylength
   5:	ireturn
  LineNumberTable: 
   line 152: 0


public scala.reflect.AnyValManifest elemManifest();
  Code:
   Stack=1, Locals=1, Args_size=1
   0:	getstatic	#65; //Field scala/reflect/ClassManifest$.MODULE$:Lscala/reflect/ClassManifest$;
   3:	invokevirtual	#68; //Method scala/reflect/ClassManifest$.Unit:()Lscala/reflect/AnyValManifest;
   6:	areturn
  LineNumberTable: 
   line 151: 0

  Signature: length = 0x2
   00 45 

public scala.runtime.BoxedUnit[] array();
  Code:
   Stack=1, Locals=1, Args_size=1
   0:	aload_0
   1:	getfield	#12; //Field array:[Lscala/runtime/BoxedUnit;
   4:	areturn
  LineNumberTable: 
   line 150: 0


}

