Compiled from "WrappedArrayBuilder.scala"
public class scala.collection.mutable.WrappedArrayBuilder extends java.lang.Object implements scala.collection.mutable.Builder,scala.ScalaObject
  SourceFile: "WrappedArrayBuilder.scala"
  Signature: length = 0x2
   00 FFFFFF93 
  ScalaSig: length = 0x2F2
   05 00 73 06 04 01 02 00 09 02 13 57 72 61 70 70
   65 64 41 72 72 61 79 42 75 69 6C 64 65 72 0A 02
   03 04 01 07 6D 75 74 61 62 6C 65 0A 02 05 06 01
   0A 63 6F 6C 6C 65 63 74 69 6F 6E 0A 01 07 01 05
   73 63 61 6C 61 03 00 15 02 0A 19 13 04 00 0B 13
   26 10 02 0C 11 0D 01 0D 0A 02 0E 0F 01 04 6C 61
   6E 67 0A 01 10 01 04 6A 61 76 61 09 02 12 0D 02
   06 4F 62 6A 65 63 74 10 04 14 15 17 23 0D 01 02
   09 02 16 02 02 07 42 75 69 6C 64 65 72 10 02 18
   19 0C 00 04 08 1A 00 FFFFFF84 FFFFFF80 FFFFFF80 FFFFFFC2 00 1B 02 01 41
   11 02 1C 20 10 02 1D 1E 0D 01 06 09 02 1F 06 02
   07 4E 6F 74 68 69 6E 67 10 02 1D 21 09 02 22 06
   02 03 41 6E 79 10 03 14 24 17 09 02 25 02 02 0C
   57 72 61 70 70 65 64 41 72 72 61 79 10 02 1D 27
   09 02 28 06 02 0B 53 63 61 6C 61 4F 62 6A 65 63
   74 08 08 2A 00 FFFFFF82 FFFFFF80 FFFFFFA0 FFFFFF80 04 2B 01 08 6D 61 6E
   69 66 65 73 74 10 03 2C 2F 17 0D 01 2D 0A 02 2E
   06 01 07 72 65 66 6C 65 63 74 09 02 30 2D 02 0D
   43 6C 61 73 73 4D 61 6E 69 66 65 73 74 08 05 32
   00 FFFFFF84 00 33 01 06 3C 69 6E 69 74 3E 14 02 34 35
   10 03 14 00 17 08 05 2A 31 FFFFFFC0 00 2B 08 07 37 00
   FFFFFFC0 FFFFFF80 FFFFFF84 04 38 01 05 65 6C 65 6D 73 15 01 23 08
   07 3A 00 FFFFFFC0 FFFFFF80 FFFFFF84 04 3B 01 09 65 6C 65 6D 73 5F
   24 65 71 14 02 3C 3F 10 02 1D 3D 09 02 3E 06 02
   04 55 6E 69 74 08 07 40 39 FFFFFF81 FFFFFF80 FFFFFFC0 00 23 01 03
   78 24 31 08 06 42 00 FFFFFFA0 FFFFFFA0 04 23 01 06 65 6C 65
   6D 73 20 08 07 44 00 FFFFFFC0 FFFFFF80 FFFFFF84 04 45 01 08 63 61
   70 61 63 69 74 79 15 01 46 10 02 1D 47 09 02 48
   06 02 03 49 6E 74 08 07 4A 00 FFFFFFC0 FFFFFF80 FFFFFF84 04 4B 01
   0C 63 61 70 61 63 69 74 79 5F 24 65 71 14 02 3C
   4C 08 07 40 49 FFFFFF81 FFFFFF80 FFFFFFC0 00 46 08 06 4E 00 FFFFFFA0 FFFFFFA0
   04 46 01 09 63 61 70 61 63 69 74 79 20 08 07 50
   00 FFFFFFC0 FFFFFF80 FFFFFF84 04 45 01 04 73 69 7A 65 08 07 52 00
   FFFFFFC0 FFFFFF80 FFFFFF84 04 53 01 08 73 69 7A 65 5F 24 65 71 14
   02 3C 54 08 07 40 51 FFFFFF81 FFFFFF80 FFFFFFC0 00 46 08 06 56 00
   FFFFFFA0 FFFFFFA0 04 46 01 05 73 69 7A 65 20 08 05 58 00 FFFFFF84
   04 59 01 07 6D 6B 41 72 72 61 79 14 02 23 5A 08
   05 50 57 FFFFFFC0 00 46 08 05 5C 00 FFFFFF84 04 5D 01 06 72
   65 73 69 7A 65 14 02 3C 5E 08 05 50 5B FFFFFFC0 00 46
   08 05 60 00 FFFFFF84 20 61 01 08 73 69 7A 65 48 69 6E
   74 14 02 3C 62 08 05 50 5F FFFFFFC0 00 46 08 05 64 00
   FFFFFF84 04 65 01 0A 65 6E 73 75 72 65 53 69 7A 65 14
   02 3C 66 08 05 50 63 FFFFFFC0 00 46 08 05 68 00 FFFFFF84 00
   69 01 08 24 70 6C 75 73 24 65 71 14 02 6A 6B 0D
   01 00 08 05 6C 67 FFFFFFC0 00 17 01 04 65 6C 65 6D 08
   05 6E 00 FFFFFF84 00 6F 01 05 63 6C 65 61 72 14 01 3C
   08 05 71 00 FFFFFF84 00 72 01 06 72 65 73 75 6C 74 14
   01 23 
  minor version: 0
  major version: 49
  Constant pool:
Asciz	SourceFile;
Asciz	WrappedArrayBuilder.scala;
Asciz	size;
Asciz	I;
Asciz	capacity;
Asciz	elems;
Asciz	Lscala/collection/mutable/WrappedArray;;
Asciz	Lscala/collection/mutable/WrappedArray<TA;>;;
Asciz	Signature;
Asciz	manifest;
Asciz	Lscala/reflect/ClassManifest;;
Asciz	Lscala/reflect/ClassManifest<TA;>;;
Asciz	<init>;
Asciz	(Lscala/reflect/ClassManifest;)V;
Asciz	Code;
Asciz	LineNumberTable;
Asciz	scala/collection/mutable/WrappedArrayBuilder;
class	scala/collection/mutable/WrappedArrayBuilder
NameAndType	manifest:Lscala/reflect/ClassManifest;
Field	scala/collection/mutable/WrappedArrayBuilder.manifest:Lscala/reflect/ClassManifest;
Asciz	java/lang/Object;
class	java/lang/Object
Asciz	()V;
NameAndType	"<init>":()V
Method	java/lang/Object."<init>":()V
Asciz	scala/collection/generic/Growable$class;
class	scala/collection/generic/Growable$class
Asciz	$init$;
Asciz	(Lscala/collection/generic/Growable;)V;
NameAndType	$init$:(Lscala/collection/generic/Growable;)V
Method	scala/collection/generic/Growable$class.$init$:(Lscala/collection/generic/Growable;)V
Asciz	scala/collection/mutable/Builder$class;
class	scala/collection/mutable/Builder$class
Asciz	(Lscala/collection/mutable/Builder;)V;
NameAndType	$init$:(Lscala/collection/mutable/Builder;)V
Method	scala/collection/mutable/Builder$class.$init$:(Lscala/collection/mutable/Builder;)V
NameAndType	capacity:I
Field	scala/collection/mutable/WrappedArrayBuilder.capacity:I
NameAndType	size:I
Field	scala/collection/mutable/WrappedArrayBuilder.size:I
Asciz	this;
Asciz	Lscala/collection/mutable/WrappedArrayBuilder;;
Asciz	LocalVariableTable;
Asciz	(Lscala/reflect/ClassManifest<TA;>;)V;
Asciz	$plus$eq;
Asciz	(Ljava/lang/Object;)Lscala/collection/mutable/Builder;;
Asciz	(Ljava/lang/Object;)Lscala/collection/mutable/WrappedArrayBuilder;;
NameAndType	$plus$eq:(Ljava/lang/Object;)Lscala/collection/mutable/WrappedArrayBuilder;
Method	scala/collection/mutable/WrappedArrayBuilder.$plus$eq:(Ljava/lang/Object;)Lscala/collection/mutable/WrappedArrayBuilder;
Asciz	elem;
Asciz	Ljava/lang/Object;;
Asciz	(Ljava/lang/Object;)Lscala/collection/generic/Growable;;
Asciz	result;
Asciz	()Ljava/lang/Object;;
Asciz	()Lscala/collection/mutable/WrappedArray;;
NameAndType	result:()Lscala/collection/mutable/WrappedArray;
Method	scala/collection/mutable/WrappedArrayBuilder.result:()Lscala/collection/mutable/WrappedArray;
Asciz	()I;
NameAndType	capacity:()I
Method	scala/collection/mutable/WrappedArrayBuilder.capacity:()I
NameAndType	size:()I
Method	scala/collection/mutable/WrappedArrayBuilder.size:()I
NameAndType	elems:()Lscala/collection/mutable/WrappedArray;
Method	scala/collection/mutable/WrappedArrayBuilder.elems:()Lscala/collection/mutable/WrappedArray;
Asciz	mkArray;
Asciz	(I)Lscala/collection/mutable/WrappedArray;;
NameAndType	mkArray:(I)Lscala/collection/mutable/WrappedArray;
Method	scala/collection/mutable/WrappedArrayBuilder.mkArray:(I)Lscala/collection/mutable/WrappedArray;
Asciz	()Lscala/collection/mutable/WrappedArray<TA;>;;
Asciz	clear;
Asciz	size_$eq;
Asciz	(I)V;
NameAndType	size_$eq:(I)V
Method	scala/collection/mutable/WrappedArrayBuilder.size_$eq:(I)V
Asciz	ensureSize;
NameAndType	ensureSize:(I)V
Method	scala/collection/mutable/WrappedArrayBuilder.ensureSize:(I)V
Asciz	scala/collection/mutable/WrappedArray;
class	scala/collection/mutable/WrappedArray
Asciz	update;
Asciz	(ILjava/lang/Object;)V;
NameAndType	update:(ILjava/lang/Object;)V
Method	scala/collection/mutable/WrappedArray.update:(ILjava/lang/Object;)V
Asciz	(TA;)Lscala/collection/mutable/WrappedArrayBuilder<TA;>;;
int	16;
Asciz	resize;
NameAndType	resize:(I)V
Method	scala/collection/mutable/WrappedArrayBuilder.resize:(I)V
Asciz	newsize;
Asciz	sizeHint;
Asciz	elems_$eq;
Asciz	(Lscala/collection/mutable/WrappedArray;)V;
NameAndType	elems_$eq:(Lscala/collection/mutable/WrappedArray;)V
Method	scala/collection/mutable/WrappedArrayBuilder.elems_$eq:(Lscala/collection/mutable/WrappedArray;)V
Asciz	capacity_$eq;
NameAndType	capacity_$eq:(I)V
Method	scala/collection/mutable/WrappedArrayBuilder.capacity_$eq:(I)V
Asciz	scala/reflect/ClassManifest;
class	scala/reflect/ClassManifest
Asciz	newWrappedArray;
NameAndType	newWrappedArray:(I)Lscala/collection/mutable/WrappedArray;
InterfaceMethod	scala/reflect/ClassManifest.newWrappedArray:(I)Lscala/collection/mutable/WrappedArray;
Asciz	scala/Array$;
class	scala/Array$
Asciz	MODULE$;
Asciz	Lscala/Array$;;
NameAndType	MODULE$:Lscala/Array$;
Field	scala/Array$.MODULE$:Lscala/Array$;
Asciz	array;
NameAndType	array:()Ljava/lang/Object;
Method	scala/collection/mutable/WrappedArray.array:()Ljava/lang/Object;
Asciz	copy;
Asciz	(Ljava/lang/Object;ILjava/lang/Object;II)V;
NameAndType	copy:(Ljava/lang/Object;ILjava/lang/Object;II)V
Method	scala/Array$.copy:(Ljava/lang/Object;ILjava/lang/Object;II)V
Asciz	newelems;
Asciz	(I)Lscala/collection/mutable/WrappedArray<TA;>;;
NameAndType	elems:Lscala/collection/mutable/WrappedArray;
Field	scala/collection/mutable/WrappedArrayBuilder.elems:Lscala/collection/mutable/WrappedArray;
Asciz	(Lscala/collection/mutable/WrappedArray<TA;>;)V;
Asciz	$plus$plus$eq;
Asciz	(Lscala/collection/Traversable;)Lscala/collection/generic/Growable;;
Asciz	(Lscala/collection/generic/Growable;Lscala/collection/Traversable;)Lscala/collection/generic/Growable;;
NameAndType	$plus$plus$eq:(Lscala/collection/generic/Growable;Lscala/collection/Traversable;)Lscala/collection/generic/Growable;
Method	scala/collection/generic/Growable$class.$plus$plus$eq:(Lscala/collection/generic/Growable;Lscala/collection/Traversable;)Lscala/collection/generic/Growable;
Asciz	Lscala/collection/Traversable;;
Asciz	(Lscala/collection/Iterator;)Lscala/collection/generic/Growable;;
Asciz	(Lscala/collection/generic/Growable;Lscala/collection/Iterator;)Lscala/collection/generic/Growable;;
NameAndType	$plus$plus$eq:(Lscala/collection/generic/Growable;Lscala/collection/Iterator;)Lscala/collection/generic/Growable;
Method	scala/collection/generic/Growable$class.$plus$plus$eq:(Lscala/collection/generic/Growable;Lscala/collection/Iterator;)Lscala/collection/generic/Growable;
Asciz	iter;
Asciz	Lscala/collection/Iterator;;
Asciz	(Ljava/lang/Object;Ljava/lang/Object;Lscala/collection/Seq;)Lscala/collection/generic/Growable;;
Asciz	(Lscala/collection/generic/Growable;Ljava/lang/Object;Ljava/lang/Object;Lscala/collection/Seq;)Lscala/collection/generic/Growable;;
NameAndType	$plus$eq:(Lscala/collection/generic/Growable;Ljava/lang/Object;Ljava/lang/Object;Lscala/collection/Seq;)Lscala/collection/generic/Growable;
Method	scala/collection/generic/Growable$class.$plus$eq:(Lscala/collection/generic/Growable;Ljava/lang/Object;Ljava/lang/Object;Lscala/collection/Seq;)Lscala/collection/generic/Growable;
Asciz	elem1;
Asciz	elem2;
Asciz	Lscala/collection/Seq;;
Asciz	mapResult;
Asciz	(Lscala/Function1;)Lscala/collection/mutable/Builder;;
Asciz	(Lscala/collection/mutable/Builder;Lscala/Function1;)Lscala/collection/mutable/Builder;;
NameAndType	mapResult:(Lscala/collection/mutable/Builder;Lscala/Function1;)Lscala/collection/mutable/Builder;
Method	scala/collection/mutable/Builder$class.mapResult:(Lscala/collection/mutable/Builder;Lscala/Function1;)Lscala/collection/mutable/Builder;
Asciz	f;
Asciz	Lscala/Function1;;
Asciz	<A:Ljava/lang/Object;>Ljava/lang/Object;Lscala/collection/mutable/Builder<TA;Lscala/collection/mutable/WrappedArray<TA;>;>;Lscala/ScalaObject;;
Asciz	ScalaSig;
Asciz	scala/collection/mutable/Builder;
class	scala/collection/mutable/Builder
Asciz	scala/ScalaObject;
class	scala/ScalaObject

{
private int size;
  Signature: I

private int capacity;
  Signature: I

private scala.collection.mutable.WrappedArray elems;
  Signature: Lscala/collection/mutable/WrappedArray;
  Signature: length = 0x2
   00 08 

private final scala.reflect.ClassManifest manifest;
  Signature: Lscala/reflect/ClassManifest;
  Signature: length = 0x2
   00 0C 

public scala.collection.mutable.WrappedArrayBuilder(scala.reflect.ClassManifest);
  Signature: (Lscala/reflect/ClassManifest;)V
  Code:
   Stack=2, Locals=2, Args_size=2
	aload_0
	aload_1
	putfield	Field manifest:Lscala/reflect/ClassManifest;
	aload_0
	invokespecial	Method java/lang/Object."<init>":()V
	aload_0
	invokestatic	Method scala/collection/generic/Growable$class.$init$:(Lscala/collection/generic/Growable;)V
	aload_0
	invokestatic	Method scala/collection/mutable/Builder$class.$init$:(Lscala/collection/mutable/Builder;)V
	aload_0
	iconst_0
	putfield	Field capacity:I
	aload_0
	iconst_0
	putfield	Field size:I
	return
  Labels:
  LocalVariableTable: 
   Start  Length  Slot  Name   Signature
   0      28      0    this       Lscala/collection/mutable/WrappedArrayBuilder;
   0      28      1    manifest       Lscala/reflect/ClassManifest;

  Signature: length = 0x2
   00 2C 

public scala.collection.mutable.Builder $plus$eq(java.lang.Object);
  Signature: (Ljava/lang/Object;)Lscala/collection/mutable/Builder;
  Code:
   Stack=2, Locals=2, Args_size=2
	aload_0
	aload_1
	invokevirtual	Method $plus$eq:(Ljava/lang/Object;)Lscala/collection/mutable/WrappedArrayBuilder;
	areturn
  Labels:
  LocalVariableTable: 
   Start  Length  Slot  Name   Signature
   0      6      0    this       Lscala/collection/mutable/WrappedArrayBuilder;
   0      6      1    elem       Ljava/lang/Object;


public scala.collection.generic.Growable $plus$eq(java.lang.Object);
  Signature: (Ljava/lang/Object;)Lscala/collection/generic/Growable;
  Code:
   Stack=2, Locals=2, Args_size=2
	aload_0
	aload_1
	invokevirtual	Method $plus$eq:(Ljava/lang/Object;)Lscala/collection/mutable/WrappedArrayBuilder;
	areturn
  Labels:
  LocalVariableTable: 
   Start  Length  Slot  Name   Signature
   0      6      0    this       Lscala/collection/mutable/WrappedArrayBuilder;
   0      6      1    elem       Ljava/lang/Object;


public java.lang.Object result();
  Signature: ()Ljava/lang/Object;
  Code:
   Stack=1, Locals=1, Args_size=1
	aload_0
	invokevirtual	Method result:()Lscala/collection/mutable/WrappedArray;
	areturn
  Labels:

public scala.collection.mutable.WrappedArray result();
  Signature: ()Lscala/collection/mutable/WrappedArray;
  Code:
   Stack=2, Locals=1, Args_size=1
	aload_0
	invokespecial	Method capacity:()I
	iconst_0
	if_icmpeq	l1 // aload_0
	aload_0
	invokespecial	Method capacity:()I
	aload_0
	invokespecial	Method size:()I
	if_icmpne	l1 // aload_0
	aload_0
	invokespecial	Method elems:()Lscala/collection/mutable/WrappedArray;
	goto	l2 // areturn
l1	aload_0
	aload_0
	invokespecial	Method size:()I
	invokespecial	Method mkArray:(I)Lscala/collection/mutable/WrappedArray;
l2	areturn
  Labels:
   	l1 = 26 // aload_0
   	l2 = 34 // areturn
  Signature: length = 0x2
   00 45 

public void clear();
  Signature: ()V
  Code:
   Stack=2, Locals=1, Args_size=1
	aload_0
	iconst_0
	invokespecial	Method size_$eq:(I)V
	return
  Labels:

public scala.collection.mutable.WrappedArrayBuilder $plus$eq(java.lang.Object);
  Signature: (Ljava/lang/Object;)Lscala/collection/mutable/WrappedArrayBuilder;
  Code:
   Stack=3, Locals=2, Args_size=2
	aload_0
	aload_0
	invokespecial	Method size:()I
	iconst_1
	iadd
	invokespecial	Method ensureSize:(I)V
	aload_0
	invokespecial	Method elems:()Lscala/collection/mutable/WrappedArray;
	aload_0
	invokespecial	Method size:()I
	aload_1
	invokevirtual	Method scala/collection/mutable/WrappedArray.update:(ILjava/lang/Object;)V
	aload_0
	aload_0
	invokespecial	Method size:()I
	iconst_1
	iadd
	invokespecial	Method size_$eq:(I)V
	aload_0
	areturn
  Labels:
  LocalVariableTable: 
   Start  Length  Slot  Name   Signature
   0      34      0    this       Lscala/collection/mutable/WrappedArrayBuilder;
   0      34      1    elem       Ljava/lang/Object;

  Signature: length = 0x2
   00 54 

private void ensureSize(int);
  Signature: (I)V
  Code:
   Stack=2, Locals=3, Args_size=2
	aload_0
	invokespecial	Method capacity:()I
	iload_1
	if_icmpge	l1 // return
	aload_0
	invokespecial	Method capacity:()I
	iconst_0
	if_icmpne	l2 // aload_0
	ldc	int 16
	goto	l3 // istore_2
l2	aload_0
	invokespecial	Method capacity:()I
	iconst_2
	imul
l3	istore_2
l5	iload_2
	iload_1
	if_icmpge	l4 // aload_0
	iload_2
	iconst_2
	imul
	istore_2
	goto	l5 // iload_2
l4	aload_0
	iload_2
	invokespecial	Method resize:(I)V
l1	return
  Labels:
   	l2 = 21 // aload_0
   	l3 = 27 // istore_2
   	l5 = 28 // iload_2
   	l4 = 40 // aload_0
   	l1 = 45 // return
  LocalVariableTable: 
   Start  Length  Slot  Name   Signature
   0      46      0    this       Lscala/collection/mutable/WrappedArrayBuilder;
   0      46      1    size       I
   28      17      2    newsize       I


public void sizeHint(int);
  Signature: (I)V
  Code:
   Stack=2, Locals=2, Args_size=2
	aload_0
	invokespecial	Method capacity:()I
	iload_1
	if_icmpge	l1 // return
	aload_0
	iload_1
	invokespecial	Method resize:(I)V
l1	return
  Labels:
   	l1 = 13 // return
  LocalVariableTable: 
   Start  Length  Slot  Name   Signature
   0      14      0    this       Lscala/collection/mutable/WrappedArrayBuilder;
   0      14      1    size       I


private void resize(int);
  Signature: (I)V
  Code:
   Stack=3, Locals=2, Args_size=2
	aload_0
	aload_0
	iload_1
	invokespecial	Method mkArray:(I)Lscala/collection/mutable/WrappedArray;
	invokespecial	Method elems_$eq:(Lscala/collection/mutable/WrappedArray;)V
	aload_0
	iload_1
	invokespecial	Method capacity_$eq:(I)V
	return
  Labels:
  LocalVariableTable: 
   Start  Length  Slot  Name   Signature
   0      15      0    this       Lscala/collection/mutable/WrappedArrayBuilder;
   0      15      1    size       I


private scala.collection.mutable.WrappedArray mkArray(int);
  Signature: (I)Lscala/collection/mutable/WrappedArray;
  Code:
   Stack=6, Locals=3, Args_size=2
	aload_0
	getfield	Field manifest:Lscala/reflect/ClassManifest;
	iload_1
	invokeinterface	InterfaceMethod scala/reflect/ClassManifest.newWrappedArray:(I)Lscala/collection/mutable/WrappedArray;
	astore_2
	aload_0
	invokespecial	Method size:()I
	iconst_0
	if_icmple	l1 // aload_2
	getstatic	Field scala/Array$.MODULE$:Lscala/Array$;
	aload_0
	invokespecial	Method elems:()Lscala/collection/mutable/WrappedArray;
	invokevirtual	Method scala/collection/mutable/WrappedArray.array:()Ljava/lang/Object;
	iconst_0
	aload_2
	invokevirtual	Method scala/collection/mutable/WrappedArray.array:()Ljava/lang/Object;
	iconst_0
	aload_0
	invokespecial	Method size:()I
	invokevirtual	Method scala/Array$.copy:(Ljava/lang/Object;ILjava/lang/Object;II)V
l1	aload_2
	areturn
  Labels:
   	l1 = 42 // aload_2
  LocalVariableTable: 
   Start  Length  Slot  Name   Signature
   0      44      0    this       Lscala/collection/mutable/WrappedArrayBuilder;
   0      44      1    size       I
   11      32      2    newelems       Lscala/collection/mutable/WrappedArray;

  Signature: length = 0x2
   00 75 

private void size_$eq(int);
  Signature: (I)V
  Code:
   Stack=2, Locals=2, Args_size=2
	aload_0
	iload_1
	putfield	Field size:I
	return
  Labels:

private int size();
  Signature: ()I
  Code:
   Stack=1, Locals=1, Args_size=1
	aload_0
	getfield	Field size:I
	ireturn
  Labels:

private void capacity_$eq(int);
  Signature: (I)V
  Code:
   Stack=2, Locals=2, Args_size=2
	aload_0
	iload_1
	putfield	Field capacity:I
	return
  Labels:

private int capacity();
  Signature: ()I
  Code:
   Stack=1, Locals=1, Args_size=1
	aload_0
	getfield	Field capacity:I
	ireturn
  Labels:

private void elems_$eq(scala.collection.mutable.WrappedArray);
  Signature: (Lscala/collection/mutable/WrappedArray;)V
  Code:
   Stack=2, Locals=2, Args_size=2
	aload_0
	aload_1
	putfield	Field elems:Lscala/collection/mutable/WrappedArray;
	return
  Labels:
  Signature: length = 0x2
   00 78 

private scala.collection.mutable.WrappedArray elems();
  Signature: ()Lscala/collection/mutable/WrappedArray;
  Code:
   Stack=1, Locals=1, Args_size=1
	aload_0
	getfield	Field elems:Lscala/collection/mutable/WrappedArray;
	areturn
  Labels:
  Signature: length = 0x2
   00 45 

public scala.collection.generic.Growable $plus$plus$eq(scala.collection.Traversable);
  Signature: (Lscala/collection/Traversable;)Lscala/collection/generic/Growable;
  Code:
   Stack=2, Locals=2, Args_size=2
	aload_0
	aload_1
	invokestatic	Method scala/collection/generic/Growable$class.$plus$plus$eq:(Lscala/collection/generic/Growable;Lscala/collection/Traversable;)Lscala/collection/generic/Growable;
	areturn
  Labels:
  LocalVariableTable: 
   Start  Length  Slot  Name   Signature
   0      6      0    this       Lscala/collection/mutable/WrappedArrayBuilder;
   0      6      1    elems       Lscala/collection/Traversable;


public scala.collection.generic.Growable $plus$plus$eq(scala.collection.Iterator);
  Signature: (Lscala/collection/Iterator;)Lscala/collection/generic/Growable;
  Code:
   Stack=2, Locals=2, Args_size=2
	aload_0
	aload_1
	invokestatic	Method scala/collection/generic/Growable$class.$plus$plus$eq:(Lscala/collection/generic/Growable;Lscala/collection/Iterator;)Lscala/collection/generic/Growable;
	areturn
  Labels:
  LocalVariableTable: 
   Start  Length  Slot  Name   Signature
   0      6      0    this       Lscala/collection/mutable/WrappedArrayBuilder;
   0      6      1    iter       Lscala/collection/Iterator;


public scala.collection.generic.Growable $plus$eq(java.lang.Object, java.lang.Object, scala.collection.Seq);
  Signature: (Ljava/lang/Object;Ljava/lang/Object;Lscala/collection/Seq;)Lscala/collection/generic/Growable;
  Code:
   Stack=4, Locals=4, Args_size=4
	aload_0
	aload_1
	aload_2
	aload_3
	invokestatic	Method scala/collection/generic/Growable$class.$plus$eq:(Lscala/collection/generic/Growable;Ljava/lang/Object;Ljava/lang/Object;Lscala/collection/Seq;)Lscala/collection/generic/Growable;
	areturn
  Labels:
  LocalVariableTable: 
   Start  Length  Slot  Name   Signature
   0      8      0    this       Lscala/collection/mutable/WrappedArrayBuilder;
   0      8      1    elem1       Ljava/lang/Object;
   0      8      2    elem2       Ljava/lang/Object;
   0      8      3    elems       Lscala/collection/Seq;


public scala.collection.mutable.Builder mapResult(scala.Function1);
  Signature: (Lscala/Function1;)Lscala/collection/mutable/Builder;
  Code:
   Stack=2, Locals=2, Args_size=2
	aload_0
	aload_1
	invokestatic	Method scala/collection/mutable/Builder$class.mapResult:(Lscala/collection/mutable/Builder;Lscala/Function1;)Lscala/collection/mutable/Builder;
	areturn
  Labels:
  LocalVariableTable: 
   Start  Length  Slot  Name   Signature
   0      6      0    this       Lscala/collection/mutable/WrappedArrayBuilder;
   0      6      1    f       Lscala/Function1;


}

