Compiled from "WrappedArray.scala"
public final class scala.collection.mutable.WrappedArray$ofBoolean extends scala.collection.mutable.WrappedArray implements scala.ScalaObject,java.io.Serializable
  SourceFile: "WrappedArray.scala"
  Signature: length = 0x2
   00 4A 
  Scala: length = 0x
   
  InnerClass: 
   public final #77= #10 of #14; //ofBoolean=class scala/collection/mutable/WrappedArray$ofBoolean of class scala/collection/mutable/WrappedArray
  minor version: 0
  major version: 49
  Constant pool:
const #1 = Asciz	SourceFile;
const #2 = Asciz	WrappedArray.scala;
const #3 = Asciz	array;
const #4 = Asciz	[Z;
const #5 = Asciz	<init>;
const #6 = Asciz	([Z)V;
const #7 = Asciz	Code;
const #8 = Asciz	LineNumberTable;
const #9 = Asciz	scala/collection/mutable/WrappedArray$ofBoolean;
const #10 = class	#9;	//  scala/collection/mutable/WrappedArray$ofBoolean
const #11 = NameAndType	#3:#4;//  array:[Z
const #12 = Field	#10.#11;	//  scala/collection/mutable/WrappedArray$ofBoolean.array:[Z
const #13 = Asciz	scala/collection/mutable/WrappedArray;
const #14 = class	#13;	//  scala/collection/mutable/WrappedArray
const #15 = Asciz	()V;
const #16 = NameAndType	#5:#15;//  "<init>":()V
const #17 = Method	#14.#16;	//  scala/collection/mutable/WrappedArray."<init>":()V
const #18 = Asciz	this;
const #19 = Asciz	Lscala/collection/mutable/WrappedArray$ofBoolean;;
const #20 = Asciz	LocalVariableTable;
const #21 = Asciz	()Ljava/lang/Object;;
const #22 = Asciz	()[Z;
const #23 = NameAndType	#3:#22;//  array:()[Z
const #24 = Method	#10.#23;	//  scala/collection/mutable/WrappedArray$ofBoolean.array:()[Z
const #25 = Asciz	elemManifest;
const #26 = Asciz	()Lscala/reflect/ClassManifest;;
const #27 = Asciz	()Lscala/reflect/AnyValManifest;;
const #28 = NameAndType	#25:#27;//  elemManifest:()Lscala/reflect/AnyValManifest;
const #29 = Method	#10.#28;	//  scala/collection/mutable/WrappedArray$ofBoolean.elemManifest:()Lscala/reflect/AnyValManifest;
const #30 = Asciz	apply;
const #31 = Asciz	(I)Ljava/lang/Object;;
const #32 = Asciz	(I)Z;
const #33 = NameAndType	#30:#32;//  apply:(I)Z
const #34 = Method	#10.#33;	//  scala/collection/mutable/WrappedArray$ofBoolean.apply:(I)Z
const #35 = Asciz	scala/runtime/BoxesRunTime;
const #36 = class	#35;	//  scala/runtime/BoxesRunTime
const #37 = Asciz	boxToBoolean;
const #38 = Asciz	(Z)Ljava/lang/Boolean;;
const #39 = NameAndType	#37:#38;//  boxToBoolean:(Z)Ljava/lang/Boolean;
const #40 = Method	#36.#39;	//  scala/runtime/BoxesRunTime.boxToBoolean:(Z)Ljava/lang/Boolean;
const #41 = Asciz	index;
const #42 = Asciz	I;
const #43 = Asciz	(Ljava/lang/Object;)Ljava/lang/Object;;
const #44 = Asciz	unboxToInt;
const #45 = Asciz	(Ljava/lang/Object;)I;
const #46 = NameAndType	#44:#45;//  unboxToInt:(Ljava/lang/Object;)I
const #47 = Method	#36.#46;	//  scala/runtime/BoxesRunTime.unboxToInt:(Ljava/lang/Object;)I
const #48 = Asciz	v1;
const #49 = Asciz	Ljava/lang/Object;;
const #50 = Asciz	update;
const #51 = Asciz	(ILjava/lang/Object;)V;
const #52 = Asciz	unboxToBoolean;
const #53 = Asciz	(Ljava/lang/Object;)Z;
const #54 = NameAndType	#52:#53;//  unboxToBoolean:(Ljava/lang/Object;)Z
const #55 = Method	#36.#54;	//  scala/runtime/BoxesRunTime.unboxToBoolean:(Ljava/lang/Object;)Z
const #56 = Asciz	(IZ)V;
const #57 = NameAndType	#50:#56;//  update:(IZ)V
const #58 = Method	#10.#57;	//  scala/collection/mutable/WrappedArray$ofBoolean.update:(IZ)V
const #59 = Asciz	elem;
const #60 = Asciz	Z;
const #61 = Asciz	length;
const #62 = Asciz	()I;
const #63 = Asciz	scala/reflect/ClassManifest$;
const #64 = class	#63;	//  scala/reflect/ClassManifest$
const #65 = Asciz	MODULE$;
const #66 = Asciz	Lscala/reflect/ClassManifest$;;
const #67 = NameAndType	#65:#66;//  MODULE$:Lscala/reflect/ClassManifest$;
const #68 = Field	#64.#67;	//  scala/reflect/ClassManifest$.MODULE$:Lscala/reflect/ClassManifest$;
const #69 = Asciz	Boolean;
const #70 = NameAndType	#69:#27;//  Boolean:()Lscala/reflect/AnyValManifest;
const #71 = Method	#64.#70;	//  scala/reflect/ClassManifest$.Boolean:()Lscala/reflect/AnyValManifest;
const #72 = Asciz	()Lscala/reflect/AnyValManifest<Ljava/lang/Boolean;>;;
const #73 = Asciz	Signature;
const #74 = Asciz	Lscala/collection/mutable/WrappedArray<Ljava/lang/Boolean;>;Lscala/ScalaObject;;
const #75 = Asciz	Scala;
const #76 = Asciz	InnerClasses;
const #77 = Asciz	ofBoolean;
const #78 = Asciz	scala/ScalaObject;
const #79 = class	#78;	//  scala/ScalaObject
const #80 = Asciz	java/io/Serializable;
const #81 = class	#80;	//  java/io/Serializable

{
public final boolean[] array;

public scala.collection.mutable.WrappedArray$ofBoolean(boolean[]);
  Code:
   Stack=2, Locals=2, Args_size=2
   0:	aload_0
   1:	aload_1
   2:	putfield	#12; //Field array:[Z
   5:	aload_0
   6:	invokespecial	#17; //Method scala/collection/mutable/WrappedArray."<init>":()V
   9:	return
  LineNumberTable: 
   line 142: 0

  LocalVariableTable: 
   Start  Length  Slot  Name   Signature
   0      10      0    this       Lscala/collection/mutable/WrappedArray$ofBoolean;
   0      10      1    array       [Z


public java.lang.Object array();
  Code:
   Stack=1, Locals=1, Args_size=1
   0:	aload_0
   1:	invokevirtual	#24; //Method array:()[Z
   4:	areturn
  LineNumberTable: 
   line 142: 0


public scala.reflect.ClassManifest elemManifest();
  Code:
   Stack=1, Locals=1, Args_size=1
   0:	aload_0
   1:	invokevirtual	#29; //Method elemManifest:()Lscala/reflect/AnyValManifest;
   4:	areturn
  LineNumberTable: 
   line 142: 0


public java.lang.Object apply(int);
  Code:
   Stack=2, Locals=3, Args_size=2
   0:	aload_0
   1:	iload_1
   2:	invokevirtual	#34; //Method apply:(I)Z
   5:	istore_2
   6:	iload_2
   7:	invokestatic	#40; //Method scala/runtime/BoxesRunTime.boxToBoolean:(Z)Ljava/lang/Boolean;
   10:	areturn
  LineNumberTable: 
   line 142: 0

  LocalVariableTable: 
   Start  Length  Slot  Name   Signature
   0      11      0    this       Lscala/collection/mutable/WrappedArray$ofBoolean;
   0      11      1    index       I


public java.lang.Object apply(java.lang.Object);
  Code:
   Stack=2, Locals=3, Args_size=2
   0:	aload_0
   1:	aload_1
   2:	invokestatic	#47; //Method scala/runtime/BoxesRunTime.unboxToInt:(Ljava/lang/Object;)I
   5:	invokevirtual	#34; //Method apply:(I)Z
   8:	istore_2
   9:	iload_2
   10:	invokestatic	#40; //Method scala/runtime/BoxesRunTime.boxToBoolean:(Z)Ljava/lang/Boolean;
   13:	areturn
  LineNumberTable: 
   line 142: 0

  LocalVariableTable: 
   Start  Length  Slot  Name   Signature
   0      14      0    this       Lscala/collection/mutable/WrappedArray$ofBoolean;
   0      14      1    v1       Ljava/lang/Object;


public void update(int, java.lang.Object);
  Code:
   Stack=3, Locals=3, Args_size=3
   0:	aload_0
   1:	iload_1
   2:	aload_2
   3:	invokestatic	#55; //Method scala/runtime/BoxesRunTime.unboxToBoolean:(Ljava/lang/Object;)Z
   6:	invokevirtual	#58; //Method update:(IZ)V
   9:	return
  LineNumberTable: 
   line 142: 0

  LocalVariableTable: 
   Start  Length  Slot  Name   Signature
   0      10      0    this       Lscala/collection/mutable/WrappedArray$ofBoolean;
   0      10      1    index       I
   0      10      2    elem       Ljava/lang/Object;


public void update(int, boolean);
  Code:
   Stack=3, Locals=3, Args_size=3
   0:	aload_0
   1:	invokevirtual	#24; //Method array:()[Z
   4:	iload_1
   5:	iload_2
   6:	bastore
   7:	return
  LineNumberTable: 
   line 146: 0

  LocalVariableTable: 
   Start  Length  Slot  Name   Signature
   0      8      0    this       Lscala/collection/mutable/WrappedArray$ofBoolean;
   0      8      1    index       I
   0      8      2    elem       Z


public boolean apply(int);
  Code:
   Stack=2, Locals=2, Args_size=2
   0:	aload_0
   1:	invokevirtual	#24; //Method array:()[Z
   4:	iload_1
   5:	baload
   6:	ireturn
  LineNumberTable: 
   line 145: 0

  LocalVariableTable: 
   Start  Length  Slot  Name   Signature
   0      7      0    this       Lscala/collection/mutable/WrappedArray$ofBoolean;
   0      7      1    index       I


public int length();
  Code:
   Stack=1, Locals=1, Args_size=1
   0:	aload_0
   1:	invokevirtual	#24; //Method array:()[Z
   4:	arraylength
   5:	ireturn
  LineNumberTable: 
   line 144: 0


public scala.reflect.AnyValManifest elemManifest();
  Code:
   Stack=1, Locals=1, Args_size=1
   0:	getstatic	#68; //Field scala/reflect/ClassManifest$.MODULE$:Lscala/reflect/ClassManifest$;
   3:	invokevirtual	#71; //Method scala/reflect/ClassManifest$.Boolean:()Lscala/reflect/AnyValManifest;
   6:	areturn
  LineNumberTable: 
   line 143: 0

  Signature: length = 0x2
   00 48 

public boolean[] array();
  Code:
   Stack=1, Locals=1, Args_size=1
   0:	aload_0
   1:	getfield	#12; //Field array:[Z
   4:	areturn
  LineNumberTable: 
   line 142: 0


}

