Compiled from "WrappedArray.scala"
public final class scala.collection.mutable.WrappedArray$$anon$1 extends java.lang.Object implements scala.collection.generic.CanBuildFrom
  SourceFile: "WrappedArray.scala"
  Signature: length = 0x2
   00 3B 
  Scala: length = 0x
   
  InnerClass: 
   public final #62= #10 of #21; //$anon$1=class scala/collection/mutable/WrappedArray$$anon$1 of class scala/collection/mutable/WrappedArray
   public final #63= #55 of #10; //$anonfun$apply$1=class scala/collection/mutable/WrappedArray$$anon$1$$anonfun$apply$1 of class scala/collection/mutable/WrappedArray$$anon$1
   public final #64= #42 of #10; //$anonfun$apply$2=class scala/collection/mutable/WrappedArray$$anon$1$$anonfun$apply$2 of class scala/collection/mutable/WrappedArray$$anon$1
  minor version: 0
  major version: 49
  Constant pool:
const #1 = Asciz	SourceFile;
const #2 = Asciz	WrappedArray.scala;
const #3 = Asciz	m$1;
const #4 = Asciz	Lscala/reflect/ClassManifest;;
const #5 = Asciz	<init>;
const #6 = Asciz	(Lscala/reflect/ClassManifest;)V;
const #7 = Asciz	Code;
const #8 = Asciz	LineNumberTable;
const #9 = Asciz	scala/collection/mutable/WrappedArray$$anon$1;
const #10 = class	#9;	//  scala/collection/mutable/WrappedArray$$anon$1
const #11 = NameAndType	#3:#4;//  m$1:Lscala/reflect/ClassManifest;
const #12 = Field	#10.#11;	//  scala/collection/mutable/WrappedArray$$anon$1.m$1:Lscala/reflect/ClassManifest;
const #13 = Asciz	java/lang/Object;
const #14 = class	#13;	//  java/lang/Object
const #15 = Asciz	()V;
const #16 = NameAndType	#5:#15;//  "<init>":()V
const #17 = Method	#14.#16;	//  java/lang/Object."<init>":()V
const #18 = Asciz	apply;
const #19 = Asciz	(Ljava/lang/Object;)Lscala/collection/mutable/Builder;;
const #20 = Asciz	scala/collection/mutable/WrappedArray;
const #21 = class	#20;	//  scala/collection/mutable/WrappedArray
const #22 = Asciz	(Lscala/collection/mutable/WrappedArray;)Lscala/collection/mutable/Builder;;
const #23 = NameAndType	#18:#22;//  apply:(Lscala/collection/mutable/WrappedArray;)Lscala/collection/mutable/Builder;
const #24 = Method	#10.#23;	//  scala/collection/mutable/WrappedArray$$anon$1.apply:(Lscala/collection/mutable/WrappedArray;)Lscala/collection/mutable/Builder;
const #25 = Asciz	this;
const #26 = Asciz	Lscala/collection/mutable/WrappedArray$$anon$1;;
const #27 = Asciz	from;
const #28 = Asciz	Ljava/lang/Object;;
const #29 = Asciz	LocalVariableTable;
const #30 = Asciz	()Lscala/collection/mutable/Builder;;
const #31 = Asciz	scala/collection/mutable/ArrayBuilder$;
const #32 = class	#31;	//  scala/collection/mutable/ArrayBuilder$
const #33 = Asciz	MODULE$;
const #34 = Asciz	Lscala/collection/mutable/ArrayBuilder$;;
const #35 = NameAndType	#33:#34;//  MODULE$:Lscala/collection/mutable/ArrayBuilder$;
const #36 = Field	#32.#35;	//  scala/collection/mutable/ArrayBuilder$.MODULE$:Lscala/collection/mutable/ArrayBuilder$;
const #37 = Asciz	make;
const #38 = Asciz	(Lscala/reflect/ClassManifest;)Lscala/collection/mutable/ArrayBuilder;;
const #39 = NameAndType	#37:#38;//  make:(Lscala/reflect/ClassManifest;)Lscala/collection/mutable/ArrayBuilder;
const #40 = Method	#32.#39;	//  scala/collection/mutable/ArrayBuilder$.make:(Lscala/reflect/ClassManifest;)Lscala/collection/mutable/ArrayBuilder;
const #41 = Asciz	scala/collection/mutable/WrappedArray$$anon$1$$anonfun$apply$2;
const #42 = class	#41;	//  scala/collection/mutable/WrappedArray$$anon$1$$anonfun$apply$2
const #43 = Asciz	(Lscala/collection/mutable/WrappedArray$$anon$1;)V;
const #44 = NameAndType	#5:#43;//  "<init>":(Lscala/collection/mutable/WrappedArray$$anon$1;)V
const #45 = Method	#42.#44;	//  scala/collection/mutable/WrappedArray$$anon$1$$anonfun$apply$2."<init>":(Lscala/collection/mutable/WrappedArray$$anon$1;)V
const #46 = Asciz	scala/collection/mutable/Builder;
const #47 = class	#46;	//  scala/collection/mutable/Builder
const #48 = Asciz	mapResult;
const #49 = Asciz	(Lscala/Function1;)Lscala/collection/mutable/Builder;;
const #50 = NameAndType	#48:#49;//  mapResult:(Lscala/Function1;)Lscala/collection/mutable/Builder;
const #51 = InterfaceMethod	#47.#50;	//  scala/collection/mutable/Builder.mapResult:(Lscala/Function1;)Lscala/collection/mutable/Builder;
const #52 = Asciz	()Lscala/collection/mutable/Builder<TT;Lscala/collection/mutable/WrappedArray<TT;>;>;;
const #53 = Asciz	Signature;
const #54 = Asciz	scala/collection/mutable/WrappedArray$$anon$1$$anonfun$apply$1;
const #55 = class	#54;	//  scala/collection/mutable/WrappedArray$$anon$1$$anonfun$apply$1
const #56 = Method	#55.#44;	//  scala/collection/mutable/WrappedArray$$anon$1$$anonfun$apply$1."<init>":(Lscala/collection/mutable/WrappedArray$$anon$1;)V
const #57 = Asciz	Lscala/collection/mutable/WrappedArray;;
const #58 = Asciz	(Lscala/collection/mutable/WrappedArray<*>;)Lscala/collection/mutable/Builder<TT;Lscala/collection/mutable/WrappedArray<TT;>;>;;
const #59 = Asciz	Ljava/lang/Object;Lscala/collection/generic/CanBuildFrom<Lscala/collection/mutable/WrappedArray<*>;TT;Lscala/collection/mutable/WrappedArray<TT;>;>;;
const #60 = Asciz	Scala;
const #61 = Asciz	InnerClasses;
const #62 = Asciz	$anon$1;
const #63 = Asciz	$anonfun$apply$1;
const #64 = Asciz	$anonfun$apply$2;
const #65 = Asciz	scala/collection/generic/CanBuildFrom;
const #66 = class	#65;	//  scala/collection/generic/CanBuildFrom

{
public scala.collection.mutable.WrappedArray$$anon$1(scala.reflect.ClassManifest);
  Code:
   Stack=2, Locals=2, Args_size=2
   0:	aload_0
   1:	aload_1
   2:	putfield	#12; //Field m$1:Lscala/reflect/ClassManifest;
   5:	aload_0
   6:	invokespecial	#17; //Method java/lang/Object."<init>":()V
   9:	return
  LineNumberTable: 
   line 68: 0


public scala.collection.mutable.Builder apply(java.lang.Object);
  Code:
   Stack=2, Locals=2, Args_size=2
   0:	aload_0
   1:	aload_1
   2:	checkcast	#21; //class scala/collection/mutable/WrappedArray
   5:	invokevirtual	#24; //Method apply:(Lscala/collection/mutable/WrappedArray;)Lscala/collection/mutable/Builder;
   8:	areturn
  LineNumberTable: 
   line 68: 0

  LocalVariableTable: 
   Start  Length  Slot  Name   Signature
   0      9      0    this       Lscala/collection/mutable/WrappedArray$$anon$1;
   0      9      1    from       Ljava/lang/Object;


public scala.collection.mutable.Builder apply();
  Code:
   Stack=4, Locals=1, Args_size=1
   0:	getstatic	#36; //Field scala/collection/mutable/ArrayBuilder$.MODULE$:Lscala/collection/mutable/ArrayBuilder$;
   3:	aload_0
   4:	getfield	#12; //Field m$1:Lscala/reflect/ClassManifest;
   7:	invokevirtual	#40; //Method scala/collection/mutable/ArrayBuilder$.make:(Lscala/reflect/ClassManifest;)Lscala/collection/mutable/ArrayBuilder;
   10:	new	#42; //class scala/collection/mutable/WrappedArray$$anon$1$$anonfun$apply$2
   13:	dup
   14:	aload_0
   15:	invokespecial	#45; //Method scala/collection/mutable/WrappedArray$$anon$1$$anonfun$apply$2."<init>":(Lscala/collection/mutable/WrappedArray$$anon$1;)V
   18:	invokeinterface	#51,  2; //InterfaceMethod scala/collection/mutable/Builder.mapResult:(Lscala/Function1;)Lscala/collection/mutable/Builder;
   23:	areturn
  LineNumberTable: 
   line 72: 0

  Signature: length = 0x2
   00 34 

public scala.collection.mutable.Builder apply(scala.collection.mutable.WrappedArray);
  Code:
   Stack=4, Locals=2, Args_size=2
   0:	getstatic	#36; //Field scala/collection/mutable/ArrayBuilder$.MODULE$:Lscala/collection/mutable/ArrayBuilder$;
   3:	aload_0
   4:	getfield	#12; //Field m$1:Lscala/reflect/ClassManifest;
   7:	invokevirtual	#40; //Method scala/collection/mutable/ArrayBuilder$.make:(Lscala/reflect/ClassManifest;)Lscala/collection/mutable/ArrayBuilder;
   10:	new	#55; //class scala/collection/mutable/WrappedArray$$anon$1$$anonfun$apply$1
   13:	dup
   14:	aload_0
   15:	invokespecial	#56; //Method scala/collection/mutable/WrappedArray$$anon$1$$anonfun$apply$1."<init>":(Lscala/collection/mutable/WrappedArray$$anon$1;)V
   18:	invokeinterface	#51,  2; //InterfaceMethod scala/collection/mutable/Builder.mapResult:(Lscala/Function1;)Lscala/collection/mutable/Builder;
   23:	areturn
  LineNumberTable: 
   line 70: 0

  LocalVariableTable: 
   Start  Length  Slot  Name   Signature
   0      24      0    this       Lscala/collection/mutable/WrappedArray$$anon$1;
   0      24      1    from       Lscala/collection/mutable/WrappedArray;

  Signature: length = 0x2
   00 3A 

}

