Compiled from "ReferenceWrapper.scala"
public abstract class scala.ref.ReferenceWrapper$class extends java.lang.Object
  SourceFile: "ReferenceWrapper.scala"
  Scala: length = 0x
   
  minor version: 0
  major version: 49
  Constant pool:
Asciz	SourceFile;
Asciz	ReferenceWrapper.scala;
Asciz	get;
Asciz	(Lscala/ref/ReferenceWrapper;)Lscala/Option;;
Asciz	Code;
Asciz	LineNumberTable;
Asciz	scala/ref/ReferenceWrapper;
class	scala/ref/ReferenceWrapper
Asciz	underlying;
Asciz	()Ljava/lang/ref/Reference;;
NameAndType	underlying:()Ljava/lang/ref/Reference;
InterfaceMethod	scala/ref/ReferenceWrapper.underlying:()Ljava/lang/ref/Reference;
Asciz	java/lang/ref/Reference;
class	java/lang/ref/Reference
Asciz	()Ljava/lang/Object;;
NameAndType	get:()Ljava/lang/Object;
Method	java/lang/ref/Reference.get:()Ljava/lang/Object;
Asciz	scala/None$;
class	scala/None$
Asciz	MODULE$;
Asciz	Lscala/None$;;
NameAndType	MODULE$:Lscala/None$;
Field	scala/None$.MODULE$:Lscala/None$;
Asciz	scala/Some;
class	scala/Some
Asciz	<init>;
Asciz	(Ljava/lang/Object;)V;
NameAndType	"<init>":(Ljava/lang/Object;)V
Method	scala/Some."<init>":(Ljava/lang/Object;)V
Asciz	$this;
Asciz	Lscala/ref/ReferenceWrapper;;
Asciz	ret;
Asciz	Ljava/lang/Object;;
Asciz	LocalVariableTable;
Asciz	apply;
Asciz	(Lscala/ref/ReferenceWrapper;)Ljava/lang/Object;;
Asciz	java/util/NoSuchElementException;
class	java/util/NoSuchElementException
Asciz	()V;
NameAndType	"<init>":()V
Method	java/util/NoSuchElementException."<init>":()V
Asciz	clear;
Asciz	(Lscala/ref/ReferenceWrapper;)V;
NameAndType	clear:()V
Method	java/lang/ref/Reference.clear:()V
Asciz	enqueue;
Asciz	(Lscala/ref/ReferenceWrapper;)Z;
Asciz	()Z;
NameAndType	enqueue:()Z
Method	java/lang/ref/Reference.enqueue:()Z
Asciz	isEnqueued;
NameAndType	isEnqueued:()Z
Method	java/lang/ref/Reference.isEnqueued:()Z
Asciz	self;
Asciz	(Lscala/ref/ReferenceWrapper;)Ljava/lang/ref/Reference;;
Asciz	$init$;
Asciz	Scala;
Asciz	scala/ref/ReferenceWrapper$class;
class	scala/ref/ReferenceWrapper$class
Asciz	java/lang/Object;
class	java/lang/Object

{
public static scala.Option get(scala.ref.ReferenceWrapper);
  Signature: (Lscala/ref/ReferenceWrapper;)Lscala/Option;
  Code:
   Stack=3, Locals=2, Args_size=1
	aload_0
	invokeinterface	InterfaceMethod scala/ref/ReferenceWrapper.underlying:()Ljava/lang/ref/Reference;
	invokevirtual	Method java/lang/ref/Reference.get:()Ljava/lang/Object;
	astore_1
	aload_1
	ifnonnull	l1 // new
	getstatic	Field scala/None$.MODULE$:Lscala/None$;
	goto	l2 // areturn
l1	new	class scala/Some
	dup
	aload_1
	invokespecial	Method scala/Some."<init>":(Ljava/lang/Object;)V
l2	areturn
  Labels:
   	l1 = 20 // new
   	l2 = 28 // areturn
  LocalVariableTable: 
   Start  Length  Slot  Name   Signature
   0      29      0    $this       Lscala/ref/ReferenceWrapper;
   10      19      1    ret       Ljava/lang/Object;


public static java.lang.Object apply(scala.ref.ReferenceWrapper);
  Signature: (Lscala/ref/ReferenceWrapper;)Ljava/lang/Object;
  Code:
   Stack=2, Locals=2, Args_size=1
	aload_0
	invokeinterface	InterfaceMethod scala/ref/ReferenceWrapper.underlying:()Ljava/lang/ref/Reference;
	invokevirtual	Method java/lang/ref/Reference.get:()Ljava/lang/Object;
	astore_1
	aload_1
	ifnonnull	l1 // aload_1
	new	class java/util/NoSuchElementException
	dup
	invokespecial	Method java/util/NoSuchElementException."<init>":()V
	athrow
l1	aload_1
	areturn
  Labels:
   	l1 = 22 // aload_1
  LocalVariableTable: 
   Start  Length  Slot  Name   Signature
   0      24      0    $this       Lscala/ref/ReferenceWrapper;
   10      13      1    ret       Ljava/lang/Object;


public static void clear(scala.ref.ReferenceWrapper);
  Signature: (Lscala/ref/ReferenceWrapper;)V
  Code:
   Stack=1, Locals=1, Args_size=1
	aload_0
	invokeinterface	InterfaceMethod scala/ref/ReferenceWrapper.underlying:()Ljava/lang/ref/Reference;
	invokevirtual	Method java/lang/ref/Reference.clear:()V
	return
  Labels:
  LocalVariableTable: 
   Start  Length  Slot  Name   Signature
   0      10      0    $this       Lscala/ref/ReferenceWrapper;


public static boolean enqueue(scala.ref.ReferenceWrapper);
  Signature: (Lscala/ref/ReferenceWrapper;)Z
  Code:
   Stack=1, Locals=1, Args_size=1
	aload_0
	invokeinterface	InterfaceMethod scala/ref/ReferenceWrapper.underlying:()Ljava/lang/ref/Reference;
	invokevirtual	Method java/lang/ref/Reference.enqueue:()Z
	ireturn
  Labels:
  LocalVariableTable: 
   Start  Length  Slot  Name   Signature
   0      10      0    $this       Lscala/ref/ReferenceWrapper;


public static boolean isEnqueued(scala.ref.ReferenceWrapper);
  Signature: (Lscala/ref/ReferenceWrapper;)Z
  Code:
   Stack=1, Locals=1, Args_size=1
	aload_0
	invokeinterface	InterfaceMethod scala/ref/ReferenceWrapper.underlying:()Ljava/lang/ref/Reference;
	invokevirtual	Method java/lang/ref/Reference.isEnqueued:()Z
	ireturn
  Labels:
  LocalVariableTable: 
   Start  Length  Slot  Name   Signature
   0      10      0    $this       Lscala/ref/ReferenceWrapper;


public static java.lang.ref.Reference self(scala.ref.ReferenceWrapper);
  Signature: (Lscala/ref/ReferenceWrapper;)Ljava/lang/ref/Reference;
  Code:
   Stack=1, Locals=1, Args_size=1
	aload_0
	invokeinterface	InterfaceMethod scala/ref/ReferenceWrapper.underlying:()Ljava/lang/ref/Reference;
	areturn
  Labels:
  LocalVariableTable: 
   Start  Length  Slot  Name   Signature
   0      7      0    $this       Lscala/ref/ReferenceWrapper;


public static void $init$(scala.ref.ReferenceWrapper);
  Signature: (Lscala/ref/ReferenceWrapper;)V
  Code:
   Stack=0, Locals=1, Args_size=1
	return
  Labels:
  LocalVariableTable: 
   Start  Length  Slot  Name   Signature
   0      1      0    $this       Lscala/ref/ReferenceWrapper;


}

