Compiled from "SoftReference.scala"
public class scala.ref.SoftReference extends java.lang.Object implements scala.ref.ReferenceWrapper,scala.ScalaObject
  SourceFile: "SoftReference.scala"
  Signature: length = 0x2
   00 7B 
  ScalaSig: length = 0x1AE
   05 00 46 06 04 01 02 00 07 02 0D 53 6F 66 74 52
   65 66 65 72 65 6E 63 65 0A 02 03 04 01 03 72 65
   66 0A 01 05 01 05 73 63 61 6C 61 03 00 15 02 08
   17 13 04 00 09 11 21 10 02 0A 0F 0D 01 0B 0A 02
   0C 0D 01 04 6C 61 6E 67 0A 01 0E 01 04 6A 61 76
   61 09 02 10 0B 02 06 4F 62 6A 65 63 74 10 03 12
   13 15 0D 01 02 09 02 14 02 02 10 52 65 66 65 72
   65 6E 63 65 57 72 61 70 70 65 72 10 02 16 17 0C
   00 04 08 18 00 FFFFFF84 FFFFFF80 FFFFFF84 FFFFFFC2 00 19 02 01 54 11 02
   1A 1E 10 02 1B 1C 0D 01 04 09 02 1D 04 02 07 4E
   6F 74 68 69 6E 67 10 02 1B 1F 09 02 20 04 02 06
   41 6E 79 52 65 66 10 02 1B 22 09 02 23 04 02 0B
   53 63 61 6C 61 4F 62 6A 65 63 74 08 08 25 00 FFFFFF82
   FFFFFF80 FFFFFFA0 FFFFFF80 04 15 01 05 76 61 6C 75 65 08 08 27 00
   FFFFFF82 FFFFFF80 FFFFFFA0 FFFFFF80 04 28 01 05 71 75 65 75 65 10 03 12
   29 15 09 02 2A 02 02 0E 52 65 66 65 72 65 6E 63
   65 51 75 65 75 65 08 05 2C 00 FFFFFF84 00 2D 01 06 3C
   69 6E 69 74 3E 14 03 2E 2F 30 10 03 12 00 15 08
   05 25 2B FFFFFFC0 00 15 08 05 27 2B FFFFFFC0 00 28 08 05 2C
   00 FFFFFF84 00 32 14 02 2E 33 08 05 25 31 FFFFFFC0 00 15 08
   07 35 00 FFFFFFC2 FFFFFF80 FFFFFF84 00 36 01 0A 75 6E 64 65 72 6C
   79 69 6E 67 15 01 37 30 02 38 3D 10 03 39 3B 3C
   0D 01 3A 0A 02 03 0B 09 02 01 3A 10 02 16 3D 04
   08 3E 00 FFFFFF84 FFFFFF80 FFFFFF80 FFFFFF82 00 3F 02 03 5F 24 31 11 02
   1A 15 08 06 41 00 FFFFFFA0 FFFFFF80 04 42 01 0B 75 6E 64 65
   72 6C 79 69 6E 67 20 30 02 43 45 10 03 39 3B 44
   10 02 16 45 04 08 3E 00 FFFFFF84 FFFFFF80 FFFFFF80 FFFFFF82 00 3F 
  minor version: 0
  major version: 49
  Constant pool:
const #1 = Asciz	SourceFile;
const #2 = Asciz	SoftReference.scala;
const #3 = Asciz	underlying;
const #4 = Asciz	Ljava/lang/ref/SoftReference;;
const #5 = Asciz	Ljava/lang/ref/SoftReference<+TT;>;;
const #6 = Asciz	Signature;
const #7 = Asciz	<init>;
const #8 = Asciz	(Ljava/lang/Object;Lscala/ref/ReferenceQueue;)V;
const #9 = Asciz	Code;
const #10 = Asciz	LineNumberTable;
const #11 = Asciz	java/lang/Object;
const #12 = class	#11;	//  java/lang/Object
const #13 = Asciz	()V;
const #14 = NameAndType	#7:#13;//  "<init>":()V
const #15 = Method	#12.#14;	//  java/lang/Object."<init>":()V
const #16 = Asciz	scala/Function0$class;
const #17 = class	#16;	//  scala/Function0$class
const #18 = Asciz	$init$;
const #19 = Asciz	(Lscala/Function0;)V;
const #20 = NameAndType	#18:#19;//  $init$:(Lscala/Function0;)V
const #21 = Method	#17.#20;	//  scala/Function0$class.$init$:(Lscala/Function0;)V
const #22 = Asciz	scala/ref/Reference$class;
const #23 = class	#22;	//  scala/ref/Reference$class
const #24 = Asciz	(Lscala/ref/Reference;)V;
const #25 = NameAndType	#18:#24;//  $init$:(Lscala/ref/Reference;)V
const #26 = Method	#23.#25;	//  scala/ref/Reference$class.$init$:(Lscala/ref/Reference;)V
const #27 = Asciz	scala/Proxy$class;
const #28 = class	#27;	//  scala/Proxy$class
const #29 = Asciz	(Lscala/Proxy;)V;
const #30 = NameAndType	#18:#29;//  $init$:(Lscala/Proxy;)V
const #31 = Method	#28.#30;	//  scala/Proxy$class.$init$:(Lscala/Proxy;)V
const #32 = Asciz	scala/ref/ReferenceWrapper$class;
const #33 = class	#32;	//  scala/ref/ReferenceWrapper$class
const #34 = Asciz	(Lscala/ref/ReferenceWrapper;)V;
const #35 = NameAndType	#18:#34;//  $init$:(Lscala/ref/ReferenceWrapper;)V
const #36 = Method	#33.#35;	//  scala/ref/ReferenceWrapper$class.$init$:(Lscala/ref/ReferenceWrapper;)V
const #37 = Asciz	equals;
const #38 = Asciz	(Ljava/lang/Object;)Z;
const #39 = NameAndType	#37:#38;//  equals:(Ljava/lang/Object;)Z
const #40 = Method	#12.#39;	//  java/lang/Object.equals:(Ljava/lang/Object;)Z
const #41 = Asciz	java/lang/ref/SoftReference;
const #42 = class	#41;	//  java/lang/ref/SoftReference
const #43 = Asciz	(Ljava/lang/Object;)V;
const #44 = NameAndType	#7:#43;//  "<init>":(Ljava/lang/Object;)V
const #45 = Method	#42.#44;	//  java/lang/ref/SoftReference."<init>":(Ljava/lang/Object;)V
const #46 = Asciz	scala/ref/ReferenceQueue;
const #47 = class	#46;	//  scala/ref/ReferenceQueue
const #48 = Asciz	()Ljava/lang/ref/ReferenceQueue;;
const #49 = NameAndType	#3:#48;//  underlying:()Ljava/lang/ref/ReferenceQueue;
const #50 = Method	#47.#49;	//  scala/ref/ReferenceQueue.underlying:()Ljava/lang/ref/ReferenceQueue;
const #51 = Asciz	(Ljava/lang/Object;Ljava/lang/ref/ReferenceQueue;)V;
const #52 = NameAndType	#7:#51;//  "<init>":(Ljava/lang/Object;Ljava/lang/ref/ReferenceQueue;)V
const #53 = Method	#42.#52;	//  java/lang/ref/SoftReference."<init>":(Ljava/lang/Object;Ljava/lang/ref/ReferenceQueue;)V
const #54 = Asciz	scala/ref/SoftReference;
const #55 = class	#54;	//  scala/ref/SoftReference
const #56 = NameAndType	#3:#4;//  underlying:Ljava/lang/ref/SoftReference;
const #57 = Field	#55.#56;	//  scala/ref/SoftReference.underlying:Ljava/lang/ref/SoftReference;
const #58 = Asciz	register;
const #59 = NameAndType	#58:#34;//  register:(Lscala/ref/ReferenceWrapper;)V
const #60 = Method	#47.#59;	//  scala/ref/ReferenceQueue.register:(Lscala/ref/ReferenceWrapper;)V
const #61 = Asciz	this;
const #62 = Asciz	Lscala/ref/SoftReference;;
const #63 = Asciz	value;
const #64 = Asciz	Ljava/lang/Object;;
const #65 = Asciz	queue;
const #66 = Asciz	Lscala/ref/ReferenceQueue;;
const #67 = Asciz	LocalVariableTable;
const #68 = Asciz	(TT;Lscala/ref/ReferenceQueue<TT;>;)V;
const #69 = Asciz	()Ljava/lang/ref/Reference;;
const #70 = Asciz	()Ljava/lang/ref/SoftReference;;
const #71 = NameAndType	#3:#70;//  underlying:()Ljava/lang/ref/SoftReference;
const #72 = Method	#55.#71;	//  scala/ref/SoftReference.underlying:()Ljava/lang/ref/SoftReference;
const #73 = Asciz	self;
const #74 = Asciz	()Ljava/lang/Object;;
const #75 = Asciz	scala/ref/ReferenceWrapper;
const #76 = class	#75;	//  scala/ref/ReferenceWrapper
const #77 = NameAndType	#73:#69;//  self:()Ljava/lang/ref/Reference;
const #78 = InterfaceMethod	#76.#77;	//  scala/ref/ReferenceWrapper.self:()Ljava/lang/ref/Reference;
const #79 = Asciz	()Ljava/lang/ref/SoftReference<+TT;>;;
const #80 = NameAndType	#7:#8;//  "<init>":(Ljava/lang/Object;Lscala/ref/ReferenceQueue;)V
const #81 = Method	#55.#80;	//  scala/ref/SoftReference."<init>":(Ljava/lang/Object;Lscala/ref/ReferenceQueue;)V
const #82 = Asciz	(TT;)V;
const #83 = Asciz	toString;
const #84 = Asciz	()Ljava/lang/String;;
const #85 = Asciz	(Lscala/Proxy;)Ljava/lang/String;;
const #86 = NameAndType	#83:#85;//  toString:(Lscala/Proxy;)Ljava/lang/String;
const #87 = Method	#28.#86;	//  scala/Proxy$class.toString:(Lscala/Proxy;)Ljava/lang/String;
const #88 = Asciz	(Lscala/Proxy;Ljava/lang/Object;)Z;
const #89 = NameAndType	#37:#88;//  equals:(Lscala/Proxy;Ljava/lang/Object;)Z
const #90 = Method	#28.#89;	//  scala/Proxy$class.equals:(Lscala/Proxy;Ljava/lang/Object;)Z
const #91 = Asciz	that;
const #92 = Asciz	hashCode;
const #93 = Asciz	()I;
const #94 = Asciz	(Lscala/Proxy;)I;
const #95 = NameAndType	#92:#94;//  hashCode:(Lscala/Proxy;)I
const #96 = Method	#28.#95;	//  scala/Proxy$class.hashCode:(Lscala/Proxy;)I
const #97 = Asciz	(Lscala/ref/ReferenceWrapper;)Ljava/lang/ref/Reference;;
const #98 = NameAndType	#73:#97;//  self:(Lscala/ref/ReferenceWrapper;)Ljava/lang/ref/Reference;
const #99 = Method	#33.#98;	//  scala/ref/ReferenceWrapper$class.self:(Lscala/ref/ReferenceWrapper;)Ljava/lang/ref/Reference;
const #100 = Asciz	isEnqueued;
const #101 = Asciz	()Z;
const #102 = Asciz	(Lscala/ref/ReferenceWrapper;)Z;
const #103 = NameAndType	#100:#102;//  isEnqueued:(Lscala/ref/ReferenceWrapper;)Z
const #104 = Method	#33.#103;	//  scala/ref/ReferenceWrapper$class.isEnqueued:(Lscala/ref/ReferenceWrapper;)Z
const #105 = Asciz	enqueue;
const #106 = NameAndType	#105:#102;//  enqueue:(Lscala/ref/ReferenceWrapper;)Z
const #107 = Method	#33.#106;	//  scala/ref/ReferenceWrapper$class.enqueue:(Lscala/ref/ReferenceWrapper;)Z
const #108 = Asciz	clear;
const #109 = NameAndType	#108:#34;//  clear:(Lscala/ref/ReferenceWrapper;)V
const #110 = Method	#33.#109;	//  scala/ref/ReferenceWrapper$class.clear:(Lscala/ref/ReferenceWrapper;)V
const #111 = Asciz	apply;
const #112 = Asciz	(Lscala/ref/ReferenceWrapper;)Ljava/lang/Object;;
const #113 = NameAndType	#111:#112;//  apply:(Lscala/ref/ReferenceWrapper;)Ljava/lang/Object;
const #114 = Method	#33.#113;	//  scala/ref/ReferenceWrapper$class.apply:(Lscala/ref/ReferenceWrapper;)Ljava/lang/Object;
const #115 = Asciz	get;
const #116 = Asciz	()Lscala/Option;;
const #117 = Asciz	(Lscala/ref/ReferenceWrapper;)Lscala/Option;;
const #118 = NameAndType	#115:#117;//  get:(Lscala/ref/ReferenceWrapper;)Lscala/Option;
const #119 = Method	#33.#118;	//  scala/ref/ReferenceWrapper$class.get:(Lscala/ref/ReferenceWrapper;)Lscala/Option;
const #120 = Asciz	isValid;
const #121 = NameAndType	#120:#102;//  isValid:(Lscala/ref/ReferenceWrapper;)Z
const #122 = Method	#33.#121;	//  scala/ref/ReferenceWrapper$class.isValid:(Lscala/ref/ReferenceWrapper;)Z
const #123 = Asciz	<T:Ljava/lang/Object;>Ljava/lang/Object;Lscala/ref/ReferenceWrapper<TT;>;Lscala/ScalaObject;;
const #124 = Asciz	ScalaSig;
const #125 = Asciz	scala/ScalaObject;
const #126 = class	#125;	//  scala/ScalaObject

{
public scala.ref.SoftReference(java.lang.Object, scala.ref.ReferenceQueue);
  Code:
   Stack=5, Locals=4, Args_size=3
   0:	aload_0
   1:	invokespecial	#15; //Method java/lang/Object."<init>":()V
   4:	aload_0
   5:	invokestatic	#21; //Method scala/Function0$class.$init$:(Lscala/Function0;)V
   8:	aload_0
   9:	invokestatic	#26; //Method scala/ref/Reference$class.$init$:(Lscala/ref/Reference;)V
   12:	aload_0
   13:	invokestatic	#31; //Method scala/Proxy$class.$init$:(Lscala/Proxy;)V
   16:	aload_0
   17:	invokestatic	#36; //Method scala/ref/ReferenceWrapper$class.$init$:(Lscala/ref/ReferenceWrapper;)V
   20:	aload_0
   21:	aload_2
   22:	dup
   23:	astore_3
   24:	ifnull	35
   27:	aload_3
   28:	aconst_null
   29:	invokevirtual	#40; //Method java/lang/Object.equals:(Ljava/lang/Object;)Z
   32:	ifeq	46
   35:	new	#42; //class java/lang/ref/SoftReference
   38:	dup
   39:	aload_1
   40:	invokespecial	#45; //Method java/lang/ref/SoftReference."<init>":(Ljava/lang/Object;)V
   43:	goto	58
   46:	new	#42; //class java/lang/ref/SoftReference
   49:	dup
   50:	aload_1
   51:	aload_2
   52:	invokevirtual	#50; //Method scala/ref/ReferenceQueue.underlying:()Ljava/lang/ref/ReferenceQueue;
   55:	invokespecial	#53; //Method java/lang/ref/SoftReference."<init>":(Ljava/lang/Object;Ljava/lang/ref/ReferenceQueue;)V
   58:	putfield	#57; //Field underlying:Ljava/lang/ref/SoftReference;
   61:	aload_2
   62:	aload_0
   63:	invokevirtual	#60; //Method scala/ref/ReferenceQueue.register:(Lscala/ref/ReferenceWrapper;)V
   66:	return
  LineNumberTable: 
   line 16: 0
   line 18: 20
   line 19: 21
   line 20: 46
   line 18: 58
   line 21: 61

  LocalVariableTable: 
   Start  Length  Slot  Name   Signature
   0      67      0    this       Lscala/ref/SoftReference;
   0      67      1    value       Ljava/lang/Object;
   0      67      2    queue       Lscala/ref/ReferenceQueue;

  Signature: length = 0x2
   00 44 

public java.lang.ref.Reference underlying();
  Code:
   Stack=1, Locals=1, Args_size=1
   0:	aload_0
   1:	invokevirtual	#72; //Method underlying:()Ljava/lang/ref/SoftReference;
   4:	areturn
  LineNumberTable: 
   line 16: 0


public java.lang.Object self();
  Code:
   Stack=1, Locals=1, Args_size=1
   0:	aload_0
   1:	invokeinterface	#78,  1; //InterfaceMethod scala/ref/ReferenceWrapper.self:()Ljava/lang/ref/Reference;
   6:	areturn
  LineNumberTable: 
   line 16: 0


public java.lang.ref.SoftReference underlying();
  Code:
   Stack=1, Locals=1, Args_size=1
   0:	aload_0
   1:	getfield	#57; //Field underlying:Ljava/lang/ref/SoftReference;
   4:	areturn
  LineNumberTable: 
   line 18: 0

  Signature: length = 0x2
   00 4F 

public scala.ref.SoftReference(java.lang.Object);
  Code:
   Stack=3, Locals=2, Args_size=2
   0:	aload_0
   1:	aload_1
   2:	aconst_null
   3:	pop
   4:	aconst_null
   5:	invokespecial	#81; //Method "<init>":(Ljava/lang/Object;Lscala/ref/ReferenceQueue;)V
   8:	return
  LineNumberTable: 
   line 17: 0

  LocalVariableTable: 
   Start  Length  Slot  Name   Signature
   0      9      0    this       Lscala/ref/SoftReference;
   0      9      1    value       Ljava/lang/Object;

  Signature: length = 0x2
   00 52 

public java.lang.String toString();
  Code:
   Stack=1, Locals=1, Args_size=1
   0:	aload_0
   1:	invokestatic	#87; //Method scala/Proxy$class.toString:(Lscala/Proxy;)Ljava/lang/String;
   4:	areturn
  LineNumberTable: 
   line 16: 0


public boolean equals(java.lang.Object);
  Code:
   Stack=2, Locals=2, Args_size=2
   0:	aload_0
   1:	aload_1
   2:	invokestatic	#90; //Method scala/Proxy$class.equals:(Lscala/Proxy;Ljava/lang/Object;)Z
   5:	ireturn
  LineNumberTable: 
   line 16: 0

  LocalVariableTable: 
   Start  Length  Slot  Name   Signature
   0      6      0    this       Lscala/ref/SoftReference;
   0      6      1    that       Ljava/lang/Object;


public int hashCode();
  Code:
   Stack=1, Locals=1, Args_size=1
   0:	aload_0
   1:	invokestatic	#96; //Method scala/Proxy$class.hashCode:(Lscala/Proxy;)I
   4:	ireturn
  LineNumberTable: 
   line 16: 0


public java.lang.ref.Reference self();
  Code:
   Stack=1, Locals=1, Args_size=1
   0:	aload_0
   1:	invokestatic	#99; //Method scala/ref/ReferenceWrapper$class.self:(Lscala/ref/ReferenceWrapper;)Ljava/lang/ref/Reference;
   4:	areturn
  LineNumberTable: 
   line 16: 0


public boolean isEnqueued();
  Code:
   Stack=1, Locals=1, Args_size=1
   0:	aload_0
   1:	invokestatic	#104; //Method scala/ref/ReferenceWrapper$class.isEnqueued:(Lscala/ref/ReferenceWrapper;)Z
   4:	ireturn
  LineNumberTable: 
   line 16: 0


public boolean enqueue();
  Code:
   Stack=1, Locals=1, Args_size=1
   0:	aload_0
   1:	invokestatic	#107; //Method scala/ref/ReferenceWrapper$class.enqueue:(Lscala/ref/ReferenceWrapper;)Z
   4:	ireturn
  LineNumberTable: 
   line 16: 0


public void clear();
  Code:
   Stack=1, Locals=1, Args_size=1
   0:	aload_0
   1:	invokestatic	#110; //Method scala/ref/ReferenceWrapper$class.clear:(Lscala/ref/ReferenceWrapper;)V
   4:	return
  LineNumberTable: 
   line 16: 0


public java.lang.Object apply();
  Code:
   Stack=1, Locals=1, Args_size=1
   0:	aload_0
   1:	invokestatic	#114; //Method scala/ref/ReferenceWrapper$class.apply:(Lscala/ref/ReferenceWrapper;)Ljava/lang/Object;
   4:	areturn
  LineNumberTable: 
   line 16: 0


public scala.Option get();
  Code:
   Stack=1, Locals=1, Args_size=1
   0:	aload_0
   1:	invokestatic	#119; //Method scala/ref/ReferenceWrapper$class.get:(Lscala/ref/ReferenceWrapper;)Lscala/Option;
   4:	areturn
  LineNumberTable: 
   line 16: 0


public boolean isValid();
  Code:
   Stack=1, Locals=1, Args_size=1
   0:	aload_0
   1:	invokestatic	#122; //Method scala/ref/ReferenceWrapper$class.isValid:(Lscala/ref/ReferenceWrapper;)Z
   4:	ireturn
  LineNumberTable: 
   line 16: 0


}

