Compiled from "RegexTest.scala"
public class scala.util.parsing.combinator.testing.Ident extends java.lang.Object implements scala.ScalaObject,scala.Product,java.io.Serializable
  SourceFile: "RegexTest.scala"
  ScalaSig: length = 0x363
   05 00 FFFFFF81 02 06 08 01 02 FFFFFF84 FFFFFF80 FFFFFF80 FFFFFF80 40 0D 02 05
   49 64 65 6E 74 0A 02 03 04 01 07 74 65 73 74 69
   6E 67 0A 02 05 06 01 0A 63 6F 6D 62 69 6E 61 74
   6F 72 0A 02 07 08 01 07 70 61 72 73 69 6E 67 0A
   02 09 0A 01 04 75 74 69 6C 0A 01 0B 01 05 73 63
   61 6C 61 03 00 13 04 00 0E 16 1A 10 02 0F 14 0D
   01 10 0A 02 11 12 01 04 6C 61 6E 67 0A 01 13 01
   04 6A 61 76 61 09 02 15 10 02 06 4F 62 6A 65 63
   74 10 02 17 18 0D 01 0A 09 02 19 0A 02 0B 53 63
   61 6C 61 4F 62 6A 65 63 74 10 02 17 1B 09 02 1C
   0A 02 07 50 72 6F 64 75 63 74 08 08 1E 00 FFFFFF82 FFFFFFCA
   FFFFFF80 FFFFFF84 00 1F 01 01 73 15 01 20 10 02 21 24 0E 02
   17 22 09 02 23 0A 01 06 50 72 65 64 65 66 09 02
   25 26 02 06 53 74 72 69 6E 67 0A 02 23 0A 08 08
   28 00 FFFFFF82 FFFFFF88 FFFFFFA0 FFFFFF80 04 20 01 02 73 20 08 05 2A 00
   FFFFFF84 00 2B 01 06 3C 69 6E 69 74 3E 14 02 2C 2E 10
   02 2D 00 0D 01 02 08 05 1E 29 FFFFFFC0 00 20 08 07 30
   00 FFFFFF81 FFFFFF80 FFFFFF84 00 31 01 04 63 6F 70 79 14 02 2C 32
   08 07 1E 2F FFFFFF90 FFFFFF80 FFFFFFC0 00 20 08 07 34 00 FFFFFF91 FFFFFF80 FFFFFF84
   00 35 01 0E 63 6F 70 79 24 64 65 66 61 75 6C 74
   24 31 15 01 36 2A 02 20 37 2B 01 38 10 02 39 3E
   0D 01 3A 0A 02 3B 3C 01 09 75 6E 63 68 65 63 6B
   65 64 0A 02 3D 0A 01 0A 61 6E 6E 6F 74 61 74 69
   6F 6E 09 02 3F 3A 02 11 75 6E 63 68 65 63 6B 65
   64 56 61 72 69 61 6E 63 65 08 08 41 00 FFFFFF84 FFFFFF80 FFFFFF80
   FFFFFF84 20 42 01 08 68 61 73 68 43 6F 64 65 14 01 43
   10 02 17 44 09 02 45 0A 02 03 49 6E 74 08 08 47
   00 FFFFFF84 FFFFFF80 FFFFFF80 FFFFFF84 20 48 01 08 74 6F 53 74 72 69 6E
   67 14 01 20 08 08 4A 00 FFFFFF84 FFFFFF80 FFFFFF80 FFFFFF84 20 4B 01 06
   65 71 75 61 6C 73 14 02 4C 4F 10 02 17 4D 09 02
   4E 0A 02 07 42 6F 6F 6C 65 61 6E 08 07 50 49 FFFFFF81
   FFFFFF80 FFFFFFC0 00 51 01 03 78 24 31 10 02 17 52 09 02 53
   0A 02 03 41 6E 79 08 08 55 00 FFFFFF84 FFFFFF80 FFFFFF80 FFFFFF84 20 56
   01 0D 70 72 6F 64 75 63 74 50 72 65 66 69 78 15
   01 57 10 02 0F 58 09 02 25 10 08 08 5A 00 FFFFFF84 FFFFFF80
   FFFFFF80 FFFFFF84 20 5B 01 0C 70 72 6F 64 75 63 74 41 72 69
   74 79 15 01 43 08 08 5D 00 FFFFFF84 FFFFFF80 FFFFFF80 FFFFFF84 20 5E 01
   0E 70 72 6F 64 75 63 74 45 6C 65 6D 65 6E 74 14
   02 51 5F 08 07 50 5C FFFFFF81 FFFFFF80 FFFFFFC0 00 43 08 08 61 00
   FFFFFF84 FFFFFF80 FFFFFF80 FFFFFF84 20 62 01 12 70 72 6F 64 75 63 74 45
   6C 65 6D 65 6E 74 4E 61 6D 65 14 02 57 63 08 07
   50 60 FFFFFF81 FFFFFF80 FFFFFFC0 00 43 08 08 65 00 FFFFFF84 FFFFFF80 FFFFFF80 FFFFFF84 20
   66 01 08 63 61 6E 45 71 75 61 6C 14 02 4C 67 08
   07 50 64 FFFFFF81 FFFFFF80 FFFFFFC0 00 51 28 02 00 69 10 02 17 6A
   09 02 6B 0A 02 0C 73 65 72 69 61 6C 69 7A 61 62
   6C 65 07 07 6D 02 FFFFFF81 FFFFFF80 FFFFFF88 02 6E 01 05 49 64 65
   6E 74 10 02 2D 6F 06 08 01 02 FFFFFF84 FFFFFF81 FFFFFF80 FFFFFF88 02 70
   13 04 6F 0E 71 16 10 04 17 72 20 2C 09 02 73 0A
   02 09 46 75 6E 63 74 69 6F 6E 31 08 05 2A 6F FFFFFF84
   00 75 14 01 6E 08 07 77 6F FFFFFF81 FFFFFF80 FFFFFF84 40 78 01 05
   61 70 70 6C 79 14 02 2C 79 08 05 1E 76 FFFFFFC0 00 20
   08 07 7B 6F FFFFFF81 FFFFFF80 FFFFFF84 40 7C 01 07 75 6E 61 70 70
   6C 79 14 03 7D FFFFFF81 00 10 03 17 7E 20 09 02 7F 0A
   02 04 53 6F 6D 65 08 06 FFFFFF81 01 7A FFFFFFC0 00 2C 01 03
   78 24 30 
  minor version: 0
  major version: 49
  Constant pool:
Asciz	SourceFile;
Asciz	RegexTest.scala;
Asciz	andThen;
Asciz	(Lscala/Function1;)Lscala/Function1;;
Asciz	Code;
Asciz	scala/util/parsing/combinator/testing/Ident$;
class	scala/util/parsing/combinator/testing/Ident$
Asciz	MODULE$;
Asciz	Lscala/util/parsing/combinator/testing/Ident$;;
NameAndType	MODULE$:Lscala/util/parsing/combinator/testing/Ident$;
Field	scala/util/parsing/combinator/testing/Ident$.MODULE$:Lscala/util/parsing/combinator/testing/Ident$;
NameAndType	andThen:(Lscala/Function1;)Lscala/Function1;
Method	scala/util/parsing/combinator/testing/Ident$.andThen:(Lscala/Function1;)Lscala/Function1;
Asciz	compose;
NameAndType	compose:(Lscala/Function1;)Lscala/Function1;
Method	scala/util/parsing/combinator/testing/Ident$.compose:(Lscala/Function1;)Lscala/Function1;
Asciz	s;
Asciz	Ljava/lang/String;;
Asciz	productIterator;
Asciz	()Lscala/collection/Iterator;;
Asciz	LineNumberTable;
Asciz	scala/Product$class;
class	scala/Product$class
Asciz	(Lscala/Product;)Lscala/collection/Iterator;;
NameAndType	productIterator:(Lscala/Product;)Lscala/collection/Iterator;
Method	scala/Product$class.productIterator:(Lscala/Product;)Lscala/collection/Iterator;
Asciz	productElements;
NameAndType	productElements:(Lscala/Product;)Lscala/collection/Iterator;
Method	scala/Product$class.productElements:(Lscala/Product;)Lscala/collection/Iterator;
Asciz	Deprecated;
Asciz	copy$default$1;
Asciz	()Ljava/lang/String;;
Asciz	scala/util/parsing/combinator/testing/Ident;
class	scala/util/parsing/combinator/testing/Ident
NameAndType	s:()Ljava/lang/String;
Method	scala/util/parsing/combinator/testing/Ident.s:()Ljava/lang/String;
NameAndType	s:Ljava/lang/String;
Field	scala/util/parsing/combinator/testing/Ident.s:Ljava/lang/String;
Asciz	copy;
Asciz	(Ljava/lang/String;)Lscala/util/parsing/combinator/testing/Ident;;
Asciz	<init>;
Asciz	(Ljava/lang/String;)V;
NameAndType	"<init>":(Ljava/lang/String;)V
Method	scala/util/parsing/combinator/testing/Ident."<init>":(Ljava/lang/String;)V
Asciz	this;
Asciz	Lscala/util/parsing/combinator/testing/Ident;;
Asciz	LocalVariableTable;
Asciz	hashCode;
Asciz	()I;
Asciz	scala/runtime/ScalaRunTime$;
class	scala/runtime/ScalaRunTime$
Asciz	Lscala/runtime/ScalaRunTime$;;
NameAndType	MODULE$:Lscala/runtime/ScalaRunTime$;
Field	scala/runtime/ScalaRunTime$.MODULE$:Lscala/runtime/ScalaRunTime$;
Asciz	_hashCode;
Asciz	(Lscala/Product;)I;
NameAndType	_hashCode:(Lscala/Product;)I
Method	scala/runtime/ScalaRunTime$._hashCode:(Lscala/Product;)I
Asciz	toString;
Asciz	_toString;
Asciz	(Lscala/Product;)Ljava/lang/String;;
NameAndType	_toString:(Lscala/Product;)Ljava/lang/String;
Method	scala/runtime/ScalaRunTime$._toString:(Lscala/Product;)Ljava/lang/String;
Asciz	equals;
Asciz	(Ljava/lang/Object;)Z;
Asciz	gd1$1;
Asciz	(Ljava/lang/String;)Z;
NameAndType	gd1$1:(Ljava/lang/String;)Z
Method	scala/util/parsing/combinator/testing/Ident.gd1$1:(Ljava/lang/String;)Z
Asciz	scala/Equals;
class	scala/Equals
Asciz	canEqual;
NameAndType	canEqual:(Ljava/lang/Object;)Z
InterfaceMethod	scala/Equals.canEqual:(Ljava/lang/Object;)Z
Asciz	temp2;
Asciz	temp3;
Asciz	productPrefix;
Asciz	Ident;
String	Ident
Asciz	productArity;
Asciz	productElement;
Asciz	(I)Ljava/lang/Object;;
Asciz	java/lang/IndexOutOfBoundsException;
class	java/lang/IndexOutOfBoundsException
Asciz	scala/runtime/BoxesRunTime;
class	scala/runtime/BoxesRunTime
Asciz	boxToInteger;
Asciz	(I)Ljava/lang/Integer;;
NameAndType	boxToInteger:(I)Ljava/lang/Integer;
Method	scala/runtime/BoxesRunTime.boxToInteger:(I)Ljava/lang/Integer;
Asciz	java/lang/Object;
class	java/lang/Object
NameAndType	toString:()Ljava/lang/String;
Method	java/lang/Object.toString:()Ljava/lang/String;
Method	java/lang/IndexOutOfBoundsException."<init>":(Ljava/lang/String;)V
Asciz	productElementName;
Asciz	(I)Ljava/lang/String;;
String	s
NameAndType	equals:(Ljava/lang/Object;)Z
Method	java/lang/Object.equals:(Ljava/lang/Object;)Z
Asciz	()V;
NameAndType	"<init>":()V
Method	java/lang/Object."<init>":()V
Asciz	$init$;
Asciz	(Lscala/Product;)V;
NameAndType	$init$:(Lscala/Product;)V
Method	scala/Product$class.$init$:(Lscala/Product;)V
Asciz	ScalaSig;
Asciz	scala/ScalaObject;
class	scala/ScalaObject
Asciz	scala/Product;
class	scala/Product
Asciz	java/io/Serializable;
class	java/io/Serializable

{
private final java.lang.String s;
  Signature: Ljava/lang/String;

public static final scala.Function1 andThen(scala.Function1);
  Signature: (Lscala/Function1;)Lscala/Function1;
  Code:
   Stack=2, Locals=1, Args_size=1
	getstatic	Field scala/util/parsing/combinator/testing/Ident$.MODULE$:Lscala/util/parsing/combinator/testing/Ident$;
	aload_0
	invokevirtual	Method scala/util/parsing/combinator/testing/Ident$.andThen:(Lscala/Function1;)Lscala/Function1;
	areturn
  Labels:

public static final scala.Function1 compose(scala.Function1);
  Signature: (Lscala/Function1;)Lscala/Function1;
  Code:
   Stack=2, Locals=1, Args_size=1
	getstatic	Field scala/util/parsing/combinator/testing/Ident$.MODULE$:Lscala/util/parsing/combinator/testing/Ident$;
	aload_0
	invokevirtual	Method scala/util/parsing/combinator/testing/Ident$.compose:(Lscala/Function1;)Lscala/Function1;
	areturn
  Labels:

public scala.collection.Iterator productIterator();
  Signature: ()Lscala/collection/Iterator;
  Code:
   Stack=1, Locals=1, Args_size=1
	aload_0
	invokestatic	Method scala/Product$class.productIterator:(Lscala/Product;)Lscala/collection/Iterator;
	areturn
  Labels:

public scala.collection.Iterator productElements();
  Signature: ()Lscala/collection/Iterator;
  Code:
   Stack=1, Locals=1, Args_size=1
	aload_0
	invokestatic	Method scala/Product$class.productElements:(Lscala/Product;)Lscala/collection/Iterator;
	areturn
  Labels:
  Deprecated: true

public java.lang.String copy$default$1();
  Signature: ()Ljava/lang/String;
  Code:
   Stack=1, Locals=1, Args_size=1
	aload_0
	invokevirtual	Method s:()Ljava/lang/String;
	areturn
  Labels:

public java.lang.String s();
  Signature: ()Ljava/lang/String;
  Code:
   Stack=1, Locals=1, Args_size=1
	aload_0
	getfield	Field s:Ljava/lang/String;
	areturn
  Labels:

public scala.util.parsing.combinator.testing.Ident copy(java.lang.String);
  Signature: (Ljava/lang/String;)Lscala/util/parsing/combinator/testing/Ident;
  Code:
   Stack=3, Locals=2, Args_size=2
	new	class scala/util/parsing/combinator/testing/Ident
	dup
	aload_1
	invokespecial	Method "<init>":(Ljava/lang/String;)V
	areturn
  Labels:
  LocalVariableTable: 
   Start  Length  Slot  Name   Signature
   0      9      0    this       Lscala/util/parsing/combinator/testing/Ident;
   0      9      1    s       Ljava/lang/String;


public int hashCode();
  Signature: ()I
  Code:
   Stack=2, Locals=1, Args_size=1
	getstatic	Field scala/runtime/ScalaRunTime$.MODULE$:Lscala/runtime/ScalaRunTime$;
	aload_0
	invokevirtual	Method scala/runtime/ScalaRunTime$._hashCode:(Lscala/Product;)I
	ireturn
  Labels:

public java.lang.String toString();
  Signature: ()Ljava/lang/String;
  Code:
   Stack=2, Locals=1, Args_size=1
	getstatic	Field scala/runtime/ScalaRunTime$.MODULE$:Lscala/runtime/ScalaRunTime$;
	aload_0
	invokevirtual	Method scala/runtime/ScalaRunTime$._toString:(Lscala/Product;)Ljava/lang/String;
	areturn
  Labels:

public boolean equals(java.lang.Object);
  Signature: (Ljava/lang/Object;)Z
  Code:
   Stack=2, Locals=4, Args_size=2
	aload_0
	aload_1
	if_acmpeq	l1 // iconst_1
	aload_1
	instanceof	class scala/util/parsing/combinator/testing/Ident
	ifeq	l2 // iconst_0
	aload_1
	checkcast	class scala/util/parsing/combinator/testing/Ident
	astore_2
	aload_2
	invokevirtual	Method s:()Ljava/lang/String;
	astore_3
	aload_0
	aload_3
	invokespecial	Method gd1$1:(Ljava/lang/String;)Z
	ifeq	l3 // iconst_0
	aload_1
	checkcast	class scala/util/parsing/combinator/testing/Ident
	aload_0
	invokeinterface	InterfaceMethod scala/Equals.canEqual:(Ljava/lang/Object;)Z
	goto	l4 // ifeq
l3	iconst_0
	goto	l4 // ifeq
l2	iconst_0
l4	ifeq	l5 // iconst_0
l1	iconst_1
	goto	l6 // ireturn
l5	iconst_0
l6	ireturn
  Labels:
   	l3 = 43 // iconst_0
   	l2 = 47 // iconst_0
   	l4 = 48 // ifeq
   	l1 = 51 // iconst_1
   	l5 = 55 // iconst_0
   	l6 = 56 // ireturn
  LocalVariableTable: 
   Start  Length  Slot  Name   Signature
   0      57      0    this       Lscala/util/parsing/combinator/testing/Ident;
   17      30      2    temp2       Lscala/util/parsing/combinator/testing/Ident;
   22      25      3    temp3       Ljava/lang/String;


public java.lang.String productPrefix();
  Signature: ()Ljava/lang/String;
  Code:
   Stack=1, Locals=1, Args_size=1
	ldc	String Ident
	areturn
  Labels:

public int productArity();
  Signature: ()I
  Code:
   Stack=1, Locals=1, Args_size=1
	iconst_1
	ireturn
  Labels:

public java.lang.Object productElement(int);
  Signature: (I)Ljava/lang/Object;
  Code:
   Stack=3, Locals=2, Args_size=2
	iload_1
	iconst_0
	if_icmpne	l1 // new
	aload_0
	invokevirtual	Method s:()Ljava/lang/String;
	areturn
l1	new	class java/lang/IndexOutOfBoundsException
	dup
	iload_1
	invokestatic	Method scala/runtime/BoxesRunTime.boxToInteger:(I)Ljava/lang/Integer;
	invokevirtual	Method java/lang/Object.toString:()Ljava/lang/String;
	invokespecial	Method java/lang/IndexOutOfBoundsException."<init>":(Ljava/lang/String;)V
	athrow
  Labels:
   	l1 = 10 // new

public java.lang.String productElementName(int);
  Signature: (I)Ljava/lang/String;
  Code:
   Stack=3, Locals=2, Args_size=2
	iload_1
	iconst_0
	if_icmpne	l1 // new
	ldc	String s
	areturn
l1	new	class java/lang/IndexOutOfBoundsException
	dup
	iload_1
	invokestatic	Method scala/runtime/BoxesRunTime.boxToInteger:(I)Ljava/lang/Integer;
	invokevirtual	Method java/lang/Object.toString:()Ljava/lang/String;
	invokespecial	Method java/lang/IndexOutOfBoundsException."<init>":(Ljava/lang/String;)V
	athrow
  Labels:
   	l1 = 8 // new

public boolean canEqual(java.lang.Object);
  Signature: (Ljava/lang/Object;)Z
  Code:
   Stack=1, Locals=2, Args_size=2
	aload_1
	instanceof	class scala/util/parsing/combinator/testing/Ident
	ireturn
  Labels:

private final boolean gd1$1(java.lang.String);
  Signature: (Ljava/lang/String;)Z
  Code:
   Stack=2, Locals=3, Args_size=2
	aload_1
	aload_0
	invokevirtual	Method s:()Ljava/lang/String;
	astore_2
	dup
	ifnonnull	l1 // aload_2
	pop
	aload_2
	ifnull	l2 // iconst_1
	goto	l3 // iconst_0
l1	aload_2
	invokevirtual	Method java/lang/Object.equals:(Ljava/lang/Object;)Z
	ifeq	l3 // iconst_0
l2	iconst_1
	goto	l4 // ireturn
l3	iconst_0
l4	ireturn
  Labels:
   	l1 = 18 // aload_2
   	l2 = 25 // iconst_1
   	l3 = 29 // iconst_0
   	l4 = 30 // ireturn

public scala.util.parsing.combinator.testing.Ident(java.lang.String);
  Signature: (Ljava/lang/String;)V
  Code:
   Stack=2, Locals=2, Args_size=2
	aload_0
	aload_1
	putfield	Field s:Ljava/lang/String;
	aload_0
	invokespecial	Method java/lang/Object."<init>":()V
	aload_0
	invokestatic	Method scala/Product$class.$init$:(Lscala/Product;)V
	return
  Labels:
  LocalVariableTable: 
   Start  Length  Slot  Name   Signature
   0      14      0    this       Lscala/util/parsing/combinator/testing/Ident;
   0      14      1    s       Ljava/lang/String;


}

