Compiled from "RegexTest.scala"
public final class scala.util.parsing.combinator.testing.Number$ extends java.lang.Object implements scala.Function1,scala.ScalaObject
  SourceFile: "RegexTest.scala"
  Scala: length = 0x
   
  minor version: 0
  major version: 49
  Constant pool:
Asciz	SourceFile;
Asciz	RegexTest.scala;
Asciz	Scala;
Asciz	MODULE$;
Asciz	Lscala/util/parsing/combinator/testing/Number$;;
Asciz	<clinit>;
Asciz	()V;
Asciz	Code;
Asciz	scala/util/parsing/combinator/testing/Number$;
class	scala/util/parsing/combinator/testing/Number$
Asciz	<init>;
NameAndType	"<init>":()V
Method	scala/util/parsing/combinator/testing/Number$."<init>":()V
Asciz	LineNumberTable;
Asciz	java/lang/Object;
class	java/lang/Object
Method	java/lang/Object."<init>":()V
NameAndType	MODULE$:Lscala/util/parsing/combinator/testing/Number$;
Field	scala/util/parsing/combinator/testing/Number$.MODULE$:Lscala/util/parsing/combinator/testing/Number$;
Asciz	scala/Function1$class;
class	scala/Function1$class
Asciz	$init$;
Asciz	(Lscala/Function1;)V;
NameAndType	$init$:(Lscala/Function1;)V
Method	scala/Function1$class.$init$:(Lscala/Function1;)V
Asciz	apply;
Asciz	(Ljava/lang/Object;)Ljava/lang/Object;;
Asciz	scala/runtime/BoxesRunTime;
class	scala/runtime/BoxesRunTime
Asciz	unboxToInt;
Asciz	(Ljava/lang/Object;)I;
NameAndType	unboxToInt:(Ljava/lang/Object;)I
Method	scala/runtime/BoxesRunTime.unboxToInt:(Ljava/lang/Object;)I
Asciz	(I)Lscala/util/parsing/combinator/testing/Number;;
NameAndType	apply:(I)Lscala/util/parsing/combinator/testing/Number;
Method	scala/util/parsing/combinator/testing/Number$.apply:(I)Lscala/util/parsing/combinator/testing/Number;
Asciz	this;
Asciz	v1;
Asciz	Ljava/lang/Object;;
Asciz	LocalVariableTable;
Asciz	scala/util/parsing/combinator/testing/Number;
class	scala/util/parsing/combinator/testing/Number
Asciz	(I)V;
NameAndType	"<init>":(I)V
Method	scala/util/parsing/combinator/testing/Number."<init>":(I)V
Asciz	n;
Asciz	I;
Asciz	unapply;
Asciz	(Lscala/util/parsing/combinator/testing/Number;)Lscala/Some;;
Asciz	scala/Some;
class	scala/Some
Asciz	()I;
NameAndType	n:()I
Method	scala/util/parsing/combinator/testing/Number.n:()I
Asciz	boxToInteger;
Asciz	(I)Ljava/lang/Integer;;
NameAndType	boxToInteger:(I)Ljava/lang/Integer;
Method	scala/runtime/BoxesRunTime.boxToInteger:(I)Ljava/lang/Integer;
Asciz	(Ljava/lang/Object;)V;
NameAndType	"<init>":(Ljava/lang/Object;)V
Method	scala/Some."<init>":(Ljava/lang/Object;)V
Asciz	x$0;
Asciz	Lscala/util/parsing/combinator/testing/Number;;
Asciz	andThen;
Asciz	(Lscala/Function1;)Lscala/Function1;;
Asciz	(Lscala/Function1;Lscala/Function1;)Lscala/Function1;;
NameAndType	andThen:(Lscala/Function1;Lscala/Function1;)Lscala/Function1;
Method	scala/Function1$class.andThen:(Lscala/Function1;Lscala/Function1;)Lscala/Function1;
Asciz	g;
Asciz	Lscala/Function1;;
Asciz	compose;
NameAndType	compose:(Lscala/Function1;Lscala/Function1;)Lscala/Function1;
Method	scala/Function1$class.compose:(Lscala/Function1;Lscala/Function1;)Lscala/Function1;
Asciz	toString;
Asciz	()Ljava/lang/String;;
Asciz	(Lscala/Function1;)Ljava/lang/String;;
NameAndType	toString:(Lscala/Function1;)Ljava/lang/String;
Method	scala/Function1$class.toString:(Lscala/Function1;)Ljava/lang/String;
Asciz	scala/Function1;
class	scala/Function1
Asciz	scala/ScalaObject;
class	scala/ScalaObject

{
public static final scala.util.parsing.combinator.testing.Number$ MODULE$;
  Signature: Lscala/util/parsing/combinator/testing/Number$;

public static {};
  Signature: ()V
  Code:
   Stack=1, Locals=0, Args_size=0
	new	class scala/util/parsing/combinator/testing/Number$
	invokespecial	Method "<init>":()V
	return
  Labels:

private scala.util.parsing.combinator.testing.Number$();
  Signature: ()V
  Code:
   Stack=1, Locals=1, Args_size=1
	aload_0
	invokespecial	Method java/lang/Object."<init>":()V
	aload_0
	putstatic	Field MODULE$:Lscala/util/parsing/combinator/testing/Number$;
	aload_0
	invokestatic	Method scala/Function1$class.$init$:(Lscala/Function1;)V
	return
  Labels:

public java.lang.Object apply(java.lang.Object);
  Signature: (Ljava/lang/Object;)Ljava/lang/Object;
  Code:
   Stack=2, Locals=2, Args_size=2
	aload_0
	aload_1
	invokestatic	Method scala/runtime/BoxesRunTime.unboxToInt:(Ljava/lang/Object;)I
	invokevirtual	Method apply:(I)Lscala/util/parsing/combinator/testing/Number;
	areturn
  Labels:
  LocalVariableTable: 
   Start  Length  Slot  Name   Signature
   0      9      0    this       Lscala/util/parsing/combinator/testing/Number$;
   0      9      1    v1       Ljava/lang/Object;


public scala.util.parsing.combinator.testing.Number apply(int);
  Signature: (I)Lscala/util/parsing/combinator/testing/Number;
  Code:
   Stack=3, Locals=2, Args_size=2
	new	class scala/util/parsing/combinator/testing/Number
	dup
	iload_1
	invokespecial	Method scala/util/parsing/combinator/testing/Number."<init>":(I)V
	areturn
  Labels:
  LocalVariableTable: 
   Start  Length  Slot  Name   Signature
   0      9      0    this       Lscala/util/parsing/combinator/testing/Number$;
   0      9      1    n       I


public scala.Some unapply(scala.util.parsing.combinator.testing.Number);
  Signature: (Lscala/util/parsing/combinator/testing/Number;)Lscala/Some;
  Code:
   Stack=3, Locals=3, Args_size=2
	new	class scala/Some
	dup
	aload_1
	invokevirtual	Method scala/util/parsing/combinator/testing/Number.n:()I
	istore_2
	iload_2
	invokestatic	Method scala/runtime/BoxesRunTime.boxToInteger:(I)Ljava/lang/Integer;
	invokespecial	Method scala/Some."<init>":(Ljava/lang/Object;)V
	areturn
  Labels:
  LocalVariableTable: 
   Start  Length  Slot  Name   Signature
   0      17      0    this       Lscala/util/parsing/combinator/testing/Number$;
   0      17      1    x$0       Lscala/util/parsing/combinator/testing/Number;


public scala.Function1 andThen(scala.Function1);
  Signature: (Lscala/Function1;)Lscala/Function1;
  Code:
   Stack=2, Locals=2, Args_size=2
	aload_0
	aload_1
	invokestatic	Method scala/Function1$class.andThen:(Lscala/Function1;Lscala/Function1;)Lscala/Function1;
	areturn
  Labels:
  LocalVariableTable: 
   Start  Length  Slot  Name   Signature
   0      6      0    this       Lscala/util/parsing/combinator/testing/Number$;
   0      6      1    g       Lscala/Function1;


public scala.Function1 compose(scala.Function1);
  Signature: (Lscala/Function1;)Lscala/Function1;
  Code:
   Stack=2, Locals=2, Args_size=2
	aload_0
	aload_1
	invokestatic	Method scala/Function1$class.compose:(Lscala/Function1;Lscala/Function1;)Lscala/Function1;
	areturn
  Labels:
  LocalVariableTable: 
   Start  Length  Slot  Name   Signature
   0      6      0    this       Lscala/util/parsing/combinator/testing/Number$;
   0      6      1    g       Lscala/Function1;


public java.lang.String toString();
  Signature: ()Ljava/lang/String;
  Code:
   Stack=1, Locals=1, Args_size=1
	aload_0
	invokestatic	Method scala/Function1$class.toString:(Lscala/Function1;)Ljava/lang/String;
	areturn
  Labels:

}

