Compiled from "RegexTest.scala"
public final class scala.util.parsing.combinator.testing.Number$ extends java.lang.Object implements scala.Function1,scala.ScalaObject
  SourceFile: "RegexTest.scala"
  Scala: length = 0x
   
  minor version: 0
  major version: 49
  Constant pool:
const #1 = Asciz	SourceFile;
const #2 = Asciz	RegexTest.scala;
const #3 = Asciz	Scala;
const #4 = Asciz	MODULE$;
const #5 = Asciz	Lscala/util/parsing/combinator/testing/Number$;;
const #6 = Asciz	<clinit>;
const #7 = Asciz	()V;
const #8 = Asciz	Code;
const #9 = Asciz	scala/util/parsing/combinator/testing/Number$;
const #10 = class	#9;	//  scala/util/parsing/combinator/testing/Number$
const #11 = Asciz	<init>;
const #12 = NameAndType	#11:#7;//  "<init>":()V
const #13 = Method	#10.#12;	//  scala/util/parsing/combinator/testing/Number$."<init>":()V
const #14 = Asciz	LineNumberTable;
const #15 = Asciz	java/lang/Object;
const #16 = class	#15;	//  java/lang/Object
const #17 = Method	#16.#12;	//  java/lang/Object."<init>":()V
const #18 = NameAndType	#4:#5;//  MODULE$:Lscala/util/parsing/combinator/testing/Number$;
const #19 = Field	#10.#18;	//  scala/util/parsing/combinator/testing/Number$.MODULE$:Lscala/util/parsing/combinator/testing/Number$;
const #20 = Asciz	scala/Function1$class;
const #21 = class	#20;	//  scala/Function1$class
const #22 = Asciz	$init$;
const #23 = Asciz	(Lscala/Function1;)V;
const #24 = NameAndType	#22:#23;//  $init$:(Lscala/Function1;)V
const #25 = Method	#21.#24;	//  scala/Function1$class.$init$:(Lscala/Function1;)V
const #26 = Asciz	apply;
const #27 = Asciz	(Ljava/lang/Object;)Ljava/lang/Object;;
const #28 = Asciz	scala/runtime/BoxesRunTime;
const #29 = class	#28;	//  scala/runtime/BoxesRunTime
const #30 = Asciz	unboxToInt;
const #31 = Asciz	(Ljava/lang/Object;)I;
const #32 = NameAndType	#30:#31;//  unboxToInt:(Ljava/lang/Object;)I
const #33 = Method	#29.#32;	//  scala/runtime/BoxesRunTime.unboxToInt:(Ljava/lang/Object;)I
const #34 = Asciz	(I)Lscala/util/parsing/combinator/testing/Number;;
const #35 = NameAndType	#26:#34;//  apply:(I)Lscala/util/parsing/combinator/testing/Number;
const #36 = Method	#10.#35;	//  scala/util/parsing/combinator/testing/Number$.apply:(I)Lscala/util/parsing/combinator/testing/Number;
const #37 = Asciz	this;
const #38 = Asciz	v1;
const #39 = Asciz	Ljava/lang/Object;;
const #40 = Asciz	LocalVariableTable;
const #41 = Asciz	scala/util/parsing/combinator/testing/Number;
const #42 = class	#41;	//  scala/util/parsing/combinator/testing/Number
const #43 = Asciz	(I)V;
const #44 = NameAndType	#11:#43;//  "<init>":(I)V
const #45 = Method	#42.#44;	//  scala/util/parsing/combinator/testing/Number."<init>":(I)V
const #46 = Asciz	n;
const #47 = Asciz	I;
const #48 = Asciz	unapply;
const #49 = Asciz	(Lscala/util/parsing/combinator/testing/Number;)Lscala/Some;;
const #50 = Asciz	scala/Some;
const #51 = class	#50;	//  scala/Some
const #52 = Asciz	()I;
const #53 = NameAndType	#46:#52;//  n:()I
const #54 = Method	#42.#53;	//  scala/util/parsing/combinator/testing/Number.n:()I
const #55 = Asciz	boxToInteger;
const #56 = Asciz	(I)Ljava/lang/Integer;;
const #57 = NameAndType	#55:#56;//  boxToInteger:(I)Ljava/lang/Integer;
const #58 = Method	#29.#57;	//  scala/runtime/BoxesRunTime.boxToInteger:(I)Ljava/lang/Integer;
const #59 = Asciz	(Ljava/lang/Object;)V;
const #60 = NameAndType	#11:#59;//  "<init>":(Ljava/lang/Object;)V
const #61 = Method	#51.#60;	//  scala/Some."<init>":(Ljava/lang/Object;)V
const #62 = Asciz	x$0;
const #63 = Asciz	Lscala/util/parsing/combinator/testing/Number;;
const #64 = Asciz	andThen;
const #65 = Asciz	(Lscala/Function1;)Lscala/Function1;;
const #66 = Asciz	(Lscala/Function1;Lscala/Function1;)Lscala/Function1;;
const #67 = NameAndType	#64:#66;//  andThen:(Lscala/Function1;Lscala/Function1;)Lscala/Function1;
const #68 = Method	#21.#67;	//  scala/Function1$class.andThen:(Lscala/Function1;Lscala/Function1;)Lscala/Function1;
const #69 = Asciz	g;
const #70 = Asciz	Lscala/Function1;;
const #71 = Asciz	compose;
const #72 = NameAndType	#71:#66;//  compose:(Lscala/Function1;Lscala/Function1;)Lscala/Function1;
const #73 = Method	#21.#72;	//  scala/Function1$class.compose:(Lscala/Function1;Lscala/Function1;)Lscala/Function1;
const #74 = Asciz	toString;
const #75 = Asciz	()Ljava/lang/String;;
const #76 = Asciz	(Lscala/Function1;)Ljava/lang/String;;
const #77 = NameAndType	#74:#76;//  toString:(Lscala/Function1;)Ljava/lang/String;
const #78 = Method	#21.#77;	//  scala/Function1$class.toString:(Lscala/Function1;)Ljava/lang/String;
const #79 = Asciz	scala/Function1;
const #80 = class	#79;	//  scala/Function1
const #81 = Asciz	scala/ScalaObject;
const #82 = class	#81;	//  scala/ScalaObject

{
public static final scala.util.parsing.combinator.testing.Number$ MODULE$;

public static {};
  Code:
   Stack=1, Locals=0, Args_size=0
   0:	new	#10; //class scala/util/parsing/combinator/testing/Number$
   3:	invokespecial	#13; //Method "<init>":()V
   6:	return

public java.lang.Object apply(java.lang.Object);
  Code:
   Stack=2, Locals=2, Args_size=2
   0:	aload_0
   1:	aload_1
   2:	invokestatic	#33; //Method scala/runtime/BoxesRunTime.unboxToInt:(Ljava/lang/Object;)I
   5:	invokevirtual	#36; //Method apply:(I)Lscala/util/parsing/combinator/testing/Number;
   8:	areturn
  LineNumberTable: 
   line 9: 0

  LocalVariableTable: 
   Start  Length  Slot  Name   Signature
   0      9      0    this       Lscala/util/parsing/combinator/testing/Number$;
   0      9      1    v1       Ljava/lang/Object;


public scala.util.parsing.combinator.testing.Number apply(int);
  Code:
   Stack=3, Locals=2, Args_size=2
   0:	new	#42; //class scala/util/parsing/combinator/testing/Number
   3:	dup
   4:	iload_1
   5:	invokespecial	#45; //Method scala/util/parsing/combinator/testing/Number."<init>":(I)V
   8:	areturn
  LineNumberTable: 
   line 9: 0

  LocalVariableTable: 
   Start  Length  Slot  Name   Signature
   0      9      0    this       Lscala/util/parsing/combinator/testing/Number$;
   0      9      1    n       I


public scala.Some unapply(scala.util.parsing.combinator.testing.Number);
  Code:
   Stack=3, Locals=2, Args_size=2
   0:	new	#51; //class scala/Some
   3:	dup
   4:	aload_1
   5:	invokevirtual	#54; //Method scala/util/parsing/combinator/testing/Number.n:()I
   8:	invokestatic	#58; //Method scala/runtime/BoxesRunTime.boxToInteger:(I)Ljava/lang/Integer;
   11:	invokespecial	#61; //Method scala/Some."<init>":(Ljava/lang/Object;)V
   14:	areturn
  LineNumberTable: 
   line 9: 0

  LocalVariableTable: 
   Start  Length  Slot  Name   Signature
   0      15      0    this       Lscala/util/parsing/combinator/testing/Number$;
   0      15      1    x$0       Lscala/util/parsing/combinator/testing/Number;


public scala.Function1 andThen(scala.Function1);
  Code:
   Stack=2, Locals=2, Args_size=2
   0:	aload_0
   1:	aload_1
   2:	invokestatic	#68; //Method scala/Function1$class.andThen:(Lscala/Function1;Lscala/Function1;)Lscala/Function1;
   5:	areturn
  LineNumberTable: 
   line 9: 0

  LocalVariableTable: 
   Start  Length  Slot  Name   Signature
   0      6      0    this       Lscala/util/parsing/combinator/testing/Number$;
   0      6      1    g       Lscala/Function1;


public scala.Function1 compose(scala.Function1);
  Code:
   Stack=2, Locals=2, Args_size=2
   0:	aload_0
   1:	aload_1
   2:	invokestatic	#73; //Method scala/Function1$class.compose:(Lscala/Function1;Lscala/Function1;)Lscala/Function1;
   5:	areturn
  LineNumberTable: 
   line 9: 0

  LocalVariableTable: 
   Start  Length  Slot  Name   Signature
   0      6      0    this       Lscala/util/parsing/combinator/testing/Number$;
   0      6      1    g       Lscala/Function1;


public java.lang.String toString();
  Code:
   Stack=1, Locals=1, Args_size=1
   0:	aload_0
   1:	invokestatic	#78; //Method scala/Function1$class.toString:(Lscala/Function1;)Ljava/lang/String;
   4:	areturn
  LineNumberTable: 
   line 9: 0


}

