Compiled from "RegexTest.scala"
public class scala.util.parsing.combinator.testing.Number extends java.lang.Object implements scala.ScalaObject,scala.Product,java.io.Serializable
  SourceFile: "RegexTest.scala"
  ScalaSig: length = 0x335
   05 00 7D 06 08 01 02 FFFFFF84 FFFFFF80 FFFFFF80 FFFFFF80 40 0D 02 06 4E
   75 6D 62 65 72 0A 02 03 04 01 07 74 65 73 74 69
   6E 67 0A 02 05 06 01 0A 63 6F 6D 62 69 6E 61 74
   6F 72 0A 02 07 08 01 07 70 61 72 73 69 6E 67 0A
   02 09 0A 01 04 75 74 69 6C 0A 01 0B 01 05 73 63
   61 6C 61 03 00 13 04 00 0E 16 1A 10 02 0F 14 0D
   01 10 0A 02 11 12 01 04 6C 61 6E 67 0A 01 13 01
   04 6A 61 76 61 09 02 15 10 02 06 4F 62 6A 65 63
   74 10 02 17 18 0D 01 0A 09 02 19 0A 02 0B 53 63
   61 6C 61 4F 62 6A 65 63 74 10 02 17 1B 09 02 1C
   0A 02 07 50 72 6F 64 75 63 74 08 08 1E 00 FFFFFF82 FFFFFFCA
   FFFFFF80 FFFFFF84 00 1F 01 01 6E 15 01 20 10 02 17 21 09 02
   22 0A 02 03 49 6E 74 08 08 24 00 FFFFFF82 FFFFFF88 FFFFFFA0 FFFFFF80 04
   20 01 02 6E 20 08 05 26 00 FFFFFF84 00 27 01 06 3C 69
   6E 69 74 3E 14 02 28 2A 10 02 29 00 0D 01 02 08
   05 1E 25 FFFFFFC0 00 20 08 07 2C 00 FFFFFF81 FFFFFF80 FFFFFF84 00 2D 01
   04 63 6F 70 79 14 02 28 2E 08 08 2F 1E 2B FFFFFF90 FFFFFF80
   FFFFFFC0 00 20 08 07 30 00 FFFFFF91 FFFFFF80 FFFFFF84 00 31 01 0E 63 6F
   70 79 24 64 65 66 61 75 6C 74 24 31 15 01 32 2A
   02 20 33 2B 01 34 10 02 35 3A 0D 01 36 0A 02 37
   38 01 09 75 6E 63 68 65 63 6B 65 64 0A 02 39 0A
   01 0A 61 6E 6E 6F 74 61 74 69 6F 6E 09 02 3B 36
   02 11 75 6E 63 68 65 63 6B 65 64 56 61 72 69 61
   6E 63 65 08 08 3D 00 FFFFFF84 FFFFFF80 FFFFFF80 FFFFFF84 20 3E 01 08 68
   61 73 68 43 6F 64 65 14 01 20 08 08 40 00 FFFFFF84 FFFFFF80
   FFFFFF80 FFFFFF84 20 41 01 08 74 6F 53 74 72 69 6E 67 14 01
   42 10 02 43 46 0E 02 17 44 09 02 45 0A 01 06 50
   72 65 64 65 66 09 02 47 48 02 06 53 74 72 69 6E
   67 0A 02 45 0A 08 08 4A 00 FFFFFF84 FFFFFF80 FFFFFF80 FFFFFF84 20 4B 01
   06 65 71 75 61 6C 73 14 02 4C 4F 10 02 17 4D 09
   02 4E 0A 02 07 42 6F 6F 6C 65 61 6E 08 07 50 49
   FFFFFF81 FFFFFF80 FFFFFFC0 00 51 01 03 78 24 31 10 02 17 52 09 02
   53 0A 02 03 41 6E 79 08 08 55 00 FFFFFF84 FFFFFF80 FFFFFF80 FFFFFF84 20
   56 01 0D 70 72 6F 64 75 63 74 50 72 65 66 69 78
   15 01 57 10 02 0F 58 09 02 47 10 08 08 5A 00 FFFFFF84
   FFFFFF80 FFFFFF80 FFFFFF84 20 1F 01 0C 70 72 6F 64 75 63 74 41 72
   69 74 79 08 08 5C 00 FFFFFF84 FFFFFF80 FFFFFF80 FFFFFF84 20 5D 01 0E 70
   72 6F 64 75 63 74 45 6C 65 6D 65 6E 74 14 02 51
   5E 08 07 50 5B FFFFFF81 FFFFFF80 FFFFFFC0 00 20 08 08 60 00 FFFFFF84 FFFFFF80
   FFFFFF80 FFFFFF84 20 61 01 08 63 61 6E 45 71 75 61 6C 14 02
   4C 62 08 07 50 5F FFFFFF81 FFFFFF80 FFFFFFC0 00 51 28 02 00 64 10
   02 17 65 09 02 66 0A 02 0C 73 65 72 69 61 6C 69
   7A 61 62 6C 65 07 07 68 02 FFFFFF81 FFFFFF80 FFFFFF88 02 69 01 06
   4E 75 6D 62 65 72 10 02 29 6A 06 08 01 02 FFFFFF84 FFFFFF81
   FFFFFF80 FFFFFF88 02 6B 13 04 6A 0E 6C 16 10 04 17 6D 20 28
   09 02 6E 0A 02 09 46 75 6E 63 74 69 6F 6E 31 08
   05 26 6A FFFFFF84 00 70 14 01 69 08 07 72 6A FFFFFF81 FFFFFF80 FFFFFF84
   40 73 01 05 61 70 70 6C 79 14 02 28 74 08 05 1E
   71 FFFFFFC0 00 20 08 07 76 6A FFFFFF81 FFFFFF80 FFFFFF84 40 77 01 07 75
   6E 61 70 70 6C 79 14 02 78 7B 10 03 17 79 20 09
   02 7A 0A 02 04 53 6F 6D 65 08 05 7C 75 FFFFFFC0 00 28
   01 03 78 24 30 
  minor version: 0
  major version: 49
  Constant pool:
Asciz	SourceFile;
Asciz	RegexTest.scala;
Asciz	andThen;
Asciz	(Lscala/Function1;)Lscala/Function1;;
Asciz	Code;
Asciz	scala/util/parsing/combinator/testing/Number$;
class	scala/util/parsing/combinator/testing/Number$
Asciz	MODULE$;
Asciz	Lscala/util/parsing/combinator/testing/Number$;;
NameAndType	MODULE$:Lscala/util/parsing/combinator/testing/Number$;
Field	scala/util/parsing/combinator/testing/Number$.MODULE$:Lscala/util/parsing/combinator/testing/Number$;
NameAndType	andThen:(Lscala/Function1;)Lscala/Function1;
Method	scala/util/parsing/combinator/testing/Number$.andThen:(Lscala/Function1;)Lscala/Function1;
Asciz	compose;
NameAndType	compose:(Lscala/Function1;)Lscala/Function1;
Method	scala/util/parsing/combinator/testing/Number$.compose:(Lscala/Function1;)Lscala/Function1;
Asciz	n;
Asciz	I;
Asciz	<init>;
Asciz	(I)V;
Asciz	LineNumberTable;
Asciz	scala/util/parsing/combinator/testing/Number;
class	scala/util/parsing/combinator/testing/Number
NameAndType	n:I
Field	scala/util/parsing/combinator/testing/Number.n:I
Asciz	java/lang/Object;
class	java/lang/Object
Asciz	()V;
NameAndType	"<init>":()V
Method	java/lang/Object."<init>":()V
Asciz	scala/Product$class;
class	scala/Product$class
Asciz	$init$;
Asciz	(Lscala/Product;)V;
NameAndType	$init$:(Lscala/Product;)V
Method	scala/Product$class.$init$:(Lscala/Product;)V
Asciz	this;
Asciz	Lscala/util/parsing/combinator/testing/Number;;
Asciz	LocalVariableTable;
Asciz	gd2$1;
Asciz	(I)Z;
Asciz	()I;
NameAndType	n:()I
Method	scala/util/parsing/combinator/testing/Number.n:()I
Asciz	canEqual;
Asciz	(Ljava/lang/Object;)Z;
Asciz	productElement;
Asciz	(I)Ljava/lang/Object;;
Asciz	scala/runtime/BoxesRunTime;
class	scala/runtime/BoxesRunTime
Asciz	boxToInteger;
Asciz	(I)Ljava/lang/Integer;;
NameAndType	boxToInteger:(I)Ljava/lang/Integer;
Method	scala/runtime/BoxesRunTime.boxToInteger:(I)Ljava/lang/Integer;
Asciz	scala/MatchError;
class	scala/MatchError
Asciz	toString;
Asciz	()Ljava/lang/String;;
NameAndType	toString:()Ljava/lang/String;
Method	java/lang/Object.toString:()Ljava/lang/String;
Asciz	(Ljava/lang/String;)V;
NameAndType	"<init>":(Ljava/lang/String;)V
Method	scala/MatchError."<init>":(Ljava/lang/String;)V
Asciz	java/lang/IndexOutOfBoundsException;
class	java/lang/IndexOutOfBoundsException
Method	java/lang/IndexOutOfBoundsException."<init>":(Ljava/lang/String;)V
Asciz	productArity;
Asciz	productPrefix;
Asciz	Number;
String	Number
Asciz	equals;
NameAndType	gd2$1:(I)Z
Method	scala/util/parsing/combinator/testing/Number.gd2$1:(I)Z
Asciz	scala/Equals;
class	scala/Equals
NameAndType	canEqual:(Ljava/lang/Object;)Z
InterfaceMethod	scala/Equals.canEqual:(Ljava/lang/Object;)Z
Asciz	temp6;
Asciz	temp7;
Asciz	scala/runtime/ScalaRunTime$;
class	scala/runtime/ScalaRunTime$
Asciz	Lscala/runtime/ScalaRunTime$;;
NameAndType	MODULE$:Lscala/runtime/ScalaRunTime$;
Field	scala/runtime/ScalaRunTime$.MODULE$:Lscala/runtime/ScalaRunTime$;
Asciz	_toString;
Asciz	(Lscala/Product;)Ljava/lang/String;;
NameAndType	_toString:(Lscala/Product;)Ljava/lang/String;
Method	scala/runtime/ScalaRunTime$._toString:(Lscala/Product;)Ljava/lang/String;
Asciz	hashCode;
Asciz	_hashCode;
Asciz	(Lscala/Product;)I;
NameAndType	_hashCode:(Lscala/Product;)I
Method	scala/runtime/ScalaRunTime$._hashCode:(Lscala/Product;)I
Asciz	copy;
Asciz	(I)Lscala/util/parsing/combinator/testing/Number;;
NameAndType	"<init>":(I)V
Method	scala/util/parsing/combinator/testing/Number."<init>":(I)V
Asciz	copy$default$1;
Asciz	productElements;
Asciz	()Lscala/collection/Iterator;;
Asciz	(Lscala/Product;)Lscala/collection/Iterator;;
NameAndType	productElements:(Lscala/Product;)Lscala/collection/Iterator;
Method	scala/Product$class.productElements:(Lscala/Product;)Lscala/collection/Iterator;
Asciz	Deprecated;
Asciz	productIterator;
NameAndType	productIterator:(Lscala/Product;)Lscala/collection/Iterator;
Method	scala/Product$class.productIterator:(Lscala/Product;)Lscala/collection/Iterator;
Asciz	ScalaSig;
Asciz	scala/ScalaObject;
class	scala/ScalaObject
Asciz	scala/Product;
class	scala/Product
Asciz	java/io/Serializable;
class	java/io/Serializable

{
private final int n;
  Signature: I

public static final scala.Function1 andThen(scala.Function1);
  Signature: (Lscala/Function1;)Lscala/Function1;
  Code:
   Stack=2, Locals=1, Args_size=1
	getstatic	Field scala/util/parsing/combinator/testing/Number$.MODULE$:Lscala/util/parsing/combinator/testing/Number$;
	aload_0
	invokevirtual	Method scala/util/parsing/combinator/testing/Number$.andThen:(Lscala/Function1;)Lscala/Function1;
	areturn
  Labels:

public static final scala.Function1 compose(scala.Function1);
  Signature: (Lscala/Function1;)Lscala/Function1;
  Code:
   Stack=2, Locals=1, Args_size=1
	getstatic	Field scala/util/parsing/combinator/testing/Number$.MODULE$:Lscala/util/parsing/combinator/testing/Number$;
	aload_0
	invokevirtual	Method scala/util/parsing/combinator/testing/Number$.compose:(Lscala/Function1;)Lscala/Function1;
	areturn
  Labels:

public scala.util.parsing.combinator.testing.Number(int);
  Signature: (I)V
  Code:
   Stack=2, Locals=2, Args_size=2
	aload_0
	iload_1
	putfield	Field n:I
	aload_0
	invokespecial	Method java/lang/Object."<init>":()V
	aload_0
	invokestatic	Method scala/Product$class.$init$:(Lscala/Product;)V
	return
  Labels:
  LocalVariableTable: 
   Start  Length  Slot  Name   Signature
   0      14      0    this       Lscala/util/parsing/combinator/testing/Number;
   0      14      1    n       I


private final boolean gd2$1(int);
  Signature: (I)Z
  Code:
   Stack=2, Locals=2, Args_size=2
	iload_1
	aload_0
	invokevirtual	Method n:()I
	if_icmpne	l1 // iconst_0
	iconst_1
	goto	l2 // ireturn
l1	iconst_0
l2	ireturn
  Labels:
   	l1 = 12 // iconst_0
   	l2 = 13 // ireturn

public boolean canEqual(java.lang.Object);
  Signature: (Ljava/lang/Object;)Z
  Code:
   Stack=1, Locals=2, Args_size=2
	aload_1
	instanceof	class scala/util/parsing/combinator/testing/Number
	ireturn
  Labels:

public java.lang.Object productElement(int);
  Signature: (I)Ljava/lang/Object;
  Code:
   Stack=3, Locals=3, Args_size=2
	iload_1
	iconst_0
	if_icmpne	l1 // iconst_1
	iconst_1
	ifeq	l2 // new
	aload_0
	invokevirtual	Method n:()I
	istore_2
	iload_2
	invokestatic	Method scala/runtime/BoxesRunTime.boxToInteger:(I)Ljava/lang/Integer;
	areturn
l2	new	class scala/MatchError
	dup
	iload_1
	invokestatic	Method scala/runtime/BoxesRunTime.boxToInteger:(I)Ljava/lang/Integer;
	invokevirtual	Method java/lang/Object.toString:()Ljava/lang/String;
	invokespecial	Method scala/MatchError."<init>":(Ljava/lang/String;)V
	athrow
l1	iconst_1
	ifeq	l3 // new
	new	class java/lang/IndexOutOfBoundsException
	dup
	iload_1
	invokestatic	Method scala/runtime/BoxesRunTime.boxToInteger:(I)Ljava/lang/Integer;
	invokevirtual	Method java/lang/Object.toString:()Ljava/lang/String;
	invokespecial	Method java/lang/IndexOutOfBoundsException."<init>":(Ljava/lang/String;)V
	athrow
l3	new	class scala/MatchError
	dup
	iload_1
	invokestatic	Method scala/runtime/BoxesRunTime.boxToInteger:(I)Ljava/lang/Integer;
	invokevirtual	Method java/lang/Object.toString:()Ljava/lang/String;
	invokespecial	Method scala/MatchError."<init>":(Ljava/lang/String;)V
	athrow
  Labels:
   	l2 = 19 // new
   	l1 = 34 // iconst_1
   	l3 = 53 // new

public int productArity();
  Signature: ()I
  Code:
   Stack=1, Locals=1, Args_size=1
	iconst_1
	ireturn
  Labels:

public java.lang.String productPrefix();
  Signature: ()Ljava/lang/String;
  Code:
   Stack=1, Locals=1, Args_size=1
	ldc	String Number
	areturn
  Labels:

public boolean equals(java.lang.Object);
  Signature: (Ljava/lang/Object;)Z
  Code:
   Stack=3, Locals=4, Args_size=2
	aload_0
	aload_1
	if_acmpeq	l1 // iconst_1
	aload_1
	instanceof	class scala/util/parsing/combinator/testing/Number
	ifeq	l2 // iconst_1
	aload_1
	checkcast	class scala/util/parsing/combinator/testing/Number
	astore_2
	aload_2
	invokevirtual	Method n:()I
	istore_3
	aload_0
	iload_3
	invokespecial	Method gd2$1:(I)Z
	ifeq	l3 // iconst_1
	aload_1
	checkcast	class scala/util/parsing/combinator/testing/Number
	aload_0
	invokeinterface	InterfaceMethod scala/Equals.canEqual:(Ljava/lang/Object;)Z
	goto	l4 // ifeq
l3	iconst_1
	ifeq	l5 // new
	iconst_0
	goto	l4 // ifeq
l5	new	class scala/MatchError
	dup
	aload_1
	invokevirtual	Method java/lang/Object.toString:()Ljava/lang/String;
	invokespecial	Method scala/MatchError."<init>":(Ljava/lang/String;)V
	athrow
l2	iconst_1
	ifeq	l6 // new
	iconst_0
l4	ifeq	l7 // iconst_0
l1	iconst_1
	goto	l8 // ireturn
l7	iconst_0
l8	ireturn
l6	new	class scala/MatchError
	dup
	aload_1
	invokevirtual	Method java/lang/Object.toString:()Ljava/lang/String;
	invokespecial	Method scala/MatchError."<init>":(Ljava/lang/String;)V
	athrow
  Labels:
   	l3 = 43 // iconst_1
   	l5 = 51 // new
   	l2 = 63 // iconst_1
   	l4 = 68 // ifeq
   	l1 = 71 // iconst_1
   	l7 = 75 // iconst_0
   	l8 = 76 // ireturn
   	l6 = 77 // new
  LocalVariableTable: 
   Start  Length  Slot  Name   Signature
   0      89      0    this       Lscala/util/parsing/combinator/testing/Number;
   17      46      2    temp6       Lscala/util/parsing/combinator/testing/Number;
   22      41      3    temp7       I


public java.lang.String toString();
  Signature: ()Ljava/lang/String;
  Code:
   Stack=2, Locals=1, Args_size=1
	getstatic	Field scala/runtime/ScalaRunTime$.MODULE$:Lscala/runtime/ScalaRunTime$;
	aload_0
	invokevirtual	Method scala/runtime/ScalaRunTime$._toString:(Lscala/Product;)Ljava/lang/String;
	areturn
  Labels:

public int hashCode();
  Signature: ()I
  Code:
   Stack=2, Locals=1, Args_size=1
	getstatic	Field scala/runtime/ScalaRunTime$.MODULE$:Lscala/runtime/ScalaRunTime$;
	aload_0
	invokevirtual	Method scala/runtime/ScalaRunTime$._hashCode:(Lscala/Product;)I
	ireturn
  Labels:

public scala.util.parsing.combinator.testing.Number copy(int);
  Signature: (I)Lscala/util/parsing/combinator/testing/Number;
  Code:
   Stack=3, Locals=2, Args_size=2
	new	class scala/util/parsing/combinator/testing/Number
	dup
	iload_1
	invokespecial	Method "<init>":(I)V
	areturn
  Labels:
  LocalVariableTable: 
   Start  Length  Slot  Name   Signature
   0      9      0    this       Lscala/util/parsing/combinator/testing/Number;
   0      9      1    n       I


public int n();
  Signature: ()I
  Code:
   Stack=1, Locals=1, Args_size=1
	aload_0
	getfield	Field n:I
	ireturn
  Labels:

public int copy$default$1();
  Signature: ()I
  Code:
   Stack=1, Locals=1, Args_size=1
	aload_0
	invokevirtual	Method n:()I
	ireturn
  Labels:

public scala.collection.Iterator productElements();
  Signature: ()Lscala/collection/Iterator;
  Code:
   Stack=1, Locals=1, Args_size=1
	aload_0
	invokestatic	Method scala/Product$class.productElements:(Lscala/Product;)Lscala/collection/Iterator;
	areturn
  Labels:
  Deprecated: true

public scala.collection.Iterator productIterator();
  Signature: ()Lscala/collection/Iterator;
  Code:
   Stack=1, Locals=1, Args_size=1
	aload_0
	invokestatic	Method scala/Product$class.productIterator:(Lscala/Product;)Lscala/collection/Iterator;
	areturn
  Labels:

}

