Compiled from "RegexTest.scala"
public final class scala.util.parsing.combinator.testing.RegexTest$$anonfun$2 extends java.lang.Object implements scala.Function1,scala.ScalaObject,java.io.Serializable
  SourceFile: "RegexTest.scala"
  Scala: length = 0x
   
  InnerClass: 
   public final $anonfun$2=class scala/util/parsing/combinator/testing/RegexTest$$anonfun$2 of class scala/util/parsing/combinator/testing/RegexTest
  minor version: 0
  major version: 49
  Constant pool:
Asciz	SourceFile;
Asciz	RegexTest.scala;
Asciz	<clinit>;
Asciz	()V;
Asciz	Code;
Asciz	serialVersionUID;
Asciz	J;
Asciz	scala/util/parsing/combinator/testing/RegexTest$$anonfun$2;
class	scala/util/parsing/combinator/testing/RegexTest$$anonfun$2
NameAndType	serialVersionUID:J
Field	scala/util/parsing/combinator/testing/RegexTest$$anonfun$2.serialVersionUID:J
Asciz	<init>;
Asciz	LineNumberTable;
Asciz	java/lang/Object;
class	java/lang/Object
NameAndType	"<init>":()V
Method	java/lang/Object."<init>":()V
Asciz	scala/Function1$class;
class	scala/Function1$class
Asciz	$init$;
Asciz	(Lscala/Function1;)V;
NameAndType	$init$:(Lscala/Function1;)V
Method	scala/Function1$class.$init$:(Lscala/Function1;)V
Asciz	apply;
Asciz	(Ljava/lang/Object;)Ljava/lang/Object;;
Asciz	java/lang/String;
class	java/lang/String
Asciz	(Ljava/lang/String;)Lscala/util/parsing/combinator/testing/Number;;
NameAndType	apply:(Ljava/lang/String;)Lscala/util/parsing/combinator/testing/Number;
Method	scala/util/parsing/combinator/testing/RegexTest$$anonfun$2.apply:(Ljava/lang/String;)Lscala/util/parsing/combinator/testing/Number;
Asciz	this;
Asciz	Lscala/util/parsing/combinator/testing/RegexTest$$anonfun$2;;
Asciz	v1;
Asciz	Ljava/lang/Object;;
Asciz	LocalVariableTable;
Asciz	scala/util/parsing/combinator/testing/Number;
class	scala/util/parsing/combinator/testing/Number
Asciz	scala/Predef$;
class	scala/Predef$
Asciz	MODULE$;
Asciz	Lscala/Predef$;;
NameAndType	MODULE$:Lscala/Predef$;
Field	scala/Predef$.MODULE$:Lscala/Predef$;
Asciz	augmentString;
Asciz	(Ljava/lang/String;)Lscala/collection/immutable/StringOps;;
NameAndType	augmentString:(Ljava/lang/String;)Lscala/collection/immutable/StringOps;
Method	scala/Predef$.augmentString:(Ljava/lang/String;)Lscala/collection/immutable/StringOps;
Asciz	scala/collection/immutable/StringLike;
class	scala/collection/immutable/StringLike
Asciz	toInt;
Asciz	()I;
NameAndType	toInt:()I
InterfaceMethod	scala/collection/immutable/StringLike.toInt:()I
Asciz	(I)V;
NameAndType	"<init>":(I)V
Method	scala/util/parsing/combinator/testing/Number."<init>":(I)V
Asciz	s;
Asciz	Ljava/lang/String;;
Asciz	andThen;
Asciz	(Lscala/Function1;)Lscala/Function1;;
Asciz	(Lscala/Function1;Lscala/Function1;)Lscala/Function1;;
NameAndType	andThen:(Lscala/Function1;Lscala/Function1;)Lscala/Function1;
Method	scala/Function1$class.andThen:(Lscala/Function1;Lscala/Function1;)Lscala/Function1;
Asciz	g;
Asciz	Lscala/Function1;;
Asciz	compose;
NameAndType	compose:(Lscala/Function1;Lscala/Function1;)Lscala/Function1;
Method	scala/Function1$class.compose:(Lscala/Function1;Lscala/Function1;)Lscala/Function1;
Asciz	toString;
Asciz	()Ljava/lang/String;;
Asciz	(Lscala/Function1;)Ljava/lang/String;;
NameAndType	toString:(Lscala/Function1;)Ljava/lang/String;
Method	scala/Function1$class.toString:(Lscala/Function1;)Ljava/lang/String;
Asciz	Scala;
Asciz	InnerClasses;
Asciz	scala/util/parsing/combinator/testing/RegexTest;
class	scala/util/parsing/combinator/testing/RegexTest
Asciz	$anonfun$2;
Asciz	scala/Function1;
class	scala/Function1
Asciz	scala/ScalaObject;
class	scala/ScalaObject
Asciz	java/io/Serializable;
class	java/io/Serializable

{
public static final long serialVersionUID;
  Signature: J

public static {};
  Signature: ()V
  Code:
   Stack=2, Locals=0, Args_size=0
	lconst_0
	putstatic	Field serialVersionUID:J
	return
  Labels:

public scala.util.parsing.combinator.testing.RegexTest$$anonfun$2();
  Signature: ()V
  Code:
   Stack=1, Locals=1, Args_size=1
	aload_0
	invokespecial	Method java/lang/Object."<init>":()V
	aload_0
	invokestatic	Method scala/Function1$class.$init$:(Lscala/Function1;)V
	return
  Labels:

public final java.lang.Object apply(java.lang.Object);
  Signature: (Ljava/lang/Object;)Ljava/lang/Object;
  Code:
   Stack=2, Locals=2, Args_size=2
	aload_0
	aload_1
	checkcast	class java/lang/String
	invokevirtual	Method apply:(Ljava/lang/String;)Lscala/util/parsing/combinator/testing/Number;
	areturn
  Labels:
  LocalVariableTable: 
   Start  Length  Slot  Name   Signature
   0      9      0    this       Lscala/util/parsing/combinator/testing/RegexTest$$anonfun$2;
   0      9      1    v1       Ljava/lang/Object;


public final scala.util.parsing.combinator.testing.Number apply(java.lang.String);
  Signature: (Ljava/lang/String;)Lscala/util/parsing/combinator/testing/Number;
  Code:
   Stack=4, Locals=2, Args_size=2
	new	class scala/util/parsing/combinator/testing/Number
	dup
	getstatic	Field scala/Predef$.MODULE$:Lscala/Predef$;
	aload_1
	invokevirtual	Method scala/Predef$.augmentString:(Ljava/lang/String;)Lscala/collection/immutable/StringOps;
	invokeinterface	InterfaceMethod scala/collection/immutable/StringLike.toInt:()I
	invokespecial	Method scala/util/parsing/combinator/testing/Number."<init>":(I)V
	areturn
  Labels:
  LocalVariableTable: 
   Start  Length  Slot  Name   Signature
   0      20      0    this       Lscala/util/parsing/combinator/testing/RegexTest$$anonfun$2;
   0      20      1    s       Ljava/lang/String;


public scala.Function1 andThen(scala.Function1);
  Signature: (Lscala/Function1;)Lscala/Function1;
  Code:
   Stack=2, Locals=2, Args_size=2
	aload_0
	aload_1
	invokestatic	Method scala/Function1$class.andThen:(Lscala/Function1;Lscala/Function1;)Lscala/Function1;
	areturn
  Labels:
  LocalVariableTable: 
   Start  Length  Slot  Name   Signature
   0      6      0    this       Lscala/util/parsing/combinator/testing/RegexTest$$anonfun$2;
   0      6      1    g       Lscala/Function1;


public scala.Function1 compose(scala.Function1);
  Signature: (Lscala/Function1;)Lscala/Function1;
  Code:
   Stack=2, Locals=2, Args_size=2
	aload_0
	aload_1
	invokestatic	Method scala/Function1$class.compose:(Lscala/Function1;Lscala/Function1;)Lscala/Function1;
	areturn
  Labels:
  LocalVariableTable: 
   Start  Length  Slot  Name   Signature
   0      6      0    this       Lscala/util/parsing/combinator/testing/RegexTest$$anonfun$2;
   0      6      1    g       Lscala/Function1;


public java.lang.String toString();
  Signature: ()Ljava/lang/String;
  Code:
   Stack=1, Locals=1, Args_size=1
	aload_0
	invokestatic	Method scala/Function1$class.toString:(Lscala/Function1;)Ljava/lang/String;
	areturn
  Labels:

}

