Compiled from "RegexTest.scala"
public final class scala.util.parsing.combinator.testing.RegexTest$$anonfun$3 extends scala.runtime.AbstractFunction1 implements java.io.Serializable
  SourceFile: "RegexTest.scala"
  Scala: length = 0x
   
  InnerClass: 
   public final $anonfun$3=class scala/util/parsing/combinator/testing/RegexTest$$anonfun$3 of class scala/util/parsing/combinator/testing/RegexTest
  minor version: 0
  major version: 49
  Constant pool:
Asciz	SourceFile;
Asciz	RegexTest.scala;
Asciz	<clinit>;
Asciz	()V;
Asciz	Code;
Asciz	serialVersionUID;
Asciz	J;
Asciz	scala/util/parsing/combinator/testing/RegexTest$$anonfun$3;
class	scala/util/parsing/combinator/testing/RegexTest$$anonfun$3
NameAndType	serialVersionUID:J
Field	scala/util/parsing/combinator/testing/RegexTest$$anonfun$3.serialVersionUID:J
Asciz	apply;
Asciz	(Ljava/lang/String;)Lscala/util/parsing/combinator/testing/Str;;
Asciz	scala/util/parsing/combinator/testing/Str;
class	scala/util/parsing/combinator/testing/Str
Asciz	LineNumberTable;
Asciz	java/lang/String;
class	java/lang/String
Asciz	length;
Asciz	()I;
NameAndType	length:()I
Method	java/lang/String.length:()I
Asciz	substring;
Asciz	(II)Ljava/lang/String;;
NameAndType	substring:(II)Ljava/lang/String;
Method	java/lang/String.substring:(II)Ljava/lang/String;
Asciz	<init>;
Asciz	(Ljava/lang/String;)V;
NameAndType	"<init>":(Ljava/lang/String;)V
Method	scala/util/parsing/combinator/testing/Str."<init>":(Ljava/lang/String;)V
Asciz	this;
Asciz	Lscala/util/parsing/combinator/testing/RegexTest$$anonfun$3;;
Asciz	s;
Asciz	Ljava/lang/String;;
Asciz	LocalVariableTable;
Asciz	(Ljava/lang/Object;)Ljava/lang/Object;;
NameAndType	apply:(Ljava/lang/String;)Lscala/util/parsing/combinator/testing/Str;
Method	scala/util/parsing/combinator/testing/RegexTest$$anonfun$3.apply:(Ljava/lang/String;)Lscala/util/parsing/combinator/testing/Str;
Asciz	v1;
Asciz	Ljava/lang/Object;;
Asciz	scala/runtime/AbstractFunction1;
class	scala/runtime/AbstractFunction1
NameAndType	"<init>":()V
Method	scala/runtime/AbstractFunction1."<init>":()V
Asciz	Scala;
Asciz	InnerClasses;
Asciz	scala/util/parsing/combinator/testing/RegexTest;
class	scala/util/parsing/combinator/testing/RegexTest
Asciz	$anonfun$3;
Asciz	java/io/Serializable;
class	java/io/Serializable

{
public static final long serialVersionUID;
  Signature: J

public static {};
  Signature: ()V
  Code:
   Stack=2, Locals=0, Args_size=0
	lconst_0
	putstatic	Field serialVersionUID:J
	return
  Labels:

public final scala.util.parsing.combinator.testing.Str apply(java.lang.String);
  Signature: (Ljava/lang/String;)Lscala/util/parsing/combinator/testing/Str;
  Code:
   Stack=6, Locals=2, Args_size=2
	new	class scala/util/parsing/combinator/testing/Str
	dup
	aload_1
	iconst_1
	aload_1
	invokevirtual	Method java/lang/String.length:()I
	iconst_1
	isub
	invokevirtual	Method java/lang/String.substring:(II)Ljava/lang/String;
	invokespecial	Method scala/util/parsing/combinator/testing/Str."<init>":(Ljava/lang/String;)V
	areturn
  Labels:
  LocalVariableTable: 
   Start  Length  Slot  Name   Signature
   0      19      0    this       Lscala/util/parsing/combinator/testing/RegexTest$$anonfun$3;
   0      19      1    s       Ljava/lang/String;


public final java.lang.Object apply(java.lang.Object);
  Signature: (Ljava/lang/Object;)Ljava/lang/Object;
  Code:
   Stack=2, Locals=2, Args_size=2
	aload_0
	aload_1
	checkcast	class java/lang/String
	invokevirtual	Method apply:(Ljava/lang/String;)Lscala/util/parsing/combinator/testing/Str;
	areturn
  Labels:
  LocalVariableTable: 
   Start  Length  Slot  Name   Signature
   0      9      0    this       Lscala/util/parsing/combinator/testing/RegexTest$$anonfun$3;
   0      9      1    v1       Ljava/lang/Object;


public scala.util.parsing.combinator.testing.RegexTest$$anonfun$3();
  Signature: ()V
  Code:
   Stack=1, Locals=1, Args_size=1
	aload_0
	invokespecial	Method scala/runtime/AbstractFunction1."<init>":()V
	return
  Labels:

}

