Compiled from "RegexTest.scala"
public final class scala.util.parsing.combinator.testing.RegexTest$ extends java.lang.Object implements scala.util.parsing.combinator.RegexParsers,scala.ScalaObject
  SourceFile: "RegexTest.scala"
  Scala: length = 0x
   
  InnerClass: 
   public abstract #304= #80 of #404; //Parser=class scala/util/parsing/combinator/Parsers$Parser of class scala/util/parsing/combinator/Parsers
   public abstract #329= #406 of #404; //NoSuccess=class scala/util/parsing/combinator/Parsers$NoSuccess of class scala/util/parsing/combinator/Parsers
   public abstract #409= #408 of #404; //ParseResult=class scala/util/parsing/combinator/Parsers$ParseResult of class scala/util/parsing/combinator/Parsers
   public final #412= #90 of #411; //$anonfun$2=class scala/util/parsing/combinator/testing/RegexTest$$anonfun$2 of class scala/util/parsing/combinator/testing/RegexTest
   public final #413= #105 of #411; //$anonfun$4=class scala/util/parsing/combinator/testing/RegexTest$$anonfun$4 of class scala/util/parsing/combinator/testing/RegexTest
   public final #414= #97 of #411; //$anonfun$3=class scala/util/parsing/combinator/testing/RegexTest$$anonfun$3 of class scala/util/parsing/combinator/testing/RegexTest
   public final #415= #77 of #411; //$anonfun$1=class scala/util/parsing/combinator/testing/RegexTest$$anonfun$1 of class scala/util/parsing/combinator/testing/RegexTest
   public final #416= #112 of #411; //$anonfun$5=class scala/util/parsing/combinator/testing/RegexTest$$anonfun$5 of class scala/util/parsing/combinator/testing/RegexTest
  minor version: 0
  major version: 49
  Constant pool:
const #1 = Asciz	SourceFile;
const #2 = Asciz	RegexTest.scala;
const #3 = Asciz	Scala;
const #4 = Asciz	MODULE$;
const #5 = Asciz	Lscala/util/parsing/combinator/testing/RegexTest$;;
const #6 = Asciz	<clinit>;
const #7 = Asciz	()V;
const #8 = Asciz	Code;
const #9 = Asciz	scala/util/parsing/combinator/testing/RegexTest$;
const #10 = class	#9;	//  scala/util/parsing/combinator/testing/RegexTest$
const #11 = Asciz	<init>;
const #12 = NameAndType	#11:#7;//  "<init>":()V
const #13 = Method	#10.#12;	//  scala/util/parsing/combinator/testing/RegexTest$."<init>":()V
const #14 = Asciz	$tilde$module;
const #15 = Asciz	Lscala/util/parsing/combinator/Parsers$$tilde$;;
const #16 = Asciz	Error$module;
const #17 = Asciz	Lscala/util/parsing/combinator/Parsers$Error$;;
const #18 = Asciz	Failure$module;
const #19 = Asciz	Lscala/util/parsing/combinator/Parsers$Failure$;;
const #20 = Asciz	NoSuccess$module;
const #21 = Asciz	Lscala/util/parsing/combinator/Parsers$NoSuccess$;;
const #22 = Asciz	Success$module;
const #23 = Asciz	Lscala/util/parsing/combinator/Parsers$Success$;;
const #24 = Asciz	lastNoSuccess;
const #25 = Asciz	Lscala/util/parsing/combinator/Parsers$NoSuccess;;
const #26 = Asciz	whiteSpace;
const #27 = Asciz	Lscala/util/matching/Regex;;
const #28 = Asciz	parser;
const #29 = Asciz	Lscala/util/parsing/combinator/Parsers$Parser;;
const #30 = Asciz	Lscala/util/parsing/combinator/Parsers$Parser<Lscala/collection/immutable/List<Ljava/lang/Object;>;>;;
const #31 = Asciz	Signature;
const #32 = Asciz	string;
const #33 = Asciz	Lscala/util/parsing/combinator/Parsers$Parser<Ljava/lang/Object;>;;
const #34 = Asciz	number;
const #35 = Asciz	ident;
const #36 = Asciz	LineNumberTable;
const #37 = Asciz	java/lang/Object;
const #38 = class	#37;	//  java/lang/Object
const #39 = Method	#38.#12;	//  java/lang/Object."<init>":()V
const #40 = NameAndType	#4:#5;//  MODULE$:Lscala/util/parsing/combinator/testing/RegexTest$;
const #41 = Field	#10.#40;	//  scala/util/parsing/combinator/testing/RegexTest$.MODULE$:Lscala/util/parsing/combinator/testing/RegexTest$;
const #42 = Asciz	scala/util/parsing/combinator/Parsers$class;
const #43 = class	#42;	//  scala/util/parsing/combinator/Parsers$class
const #44 = Asciz	$init$;
const #45 = Asciz	(Lscala/util/parsing/combinator/Parsers;)V;
const #46 = NameAndType	#44:#45;//  $init$:(Lscala/util/parsing/combinator/Parsers;)V
const #47 = Method	#43.#46;	//  scala/util/parsing/combinator/Parsers$class.$init$:(Lscala/util/parsing/combinator/Parsers;)V
const #48 = Asciz	scala/util/parsing/combinator/RegexParsers$class;
const #49 = class	#48;	//  scala/util/parsing/combinator/RegexParsers$class
const #50 = Asciz	(Lscala/util/parsing/combinator/RegexParsers;)V;
const #51 = NameAndType	#44:#50;//  $init$:(Lscala/util/parsing/combinator/RegexParsers;)V
const #52 = Method	#49.#51;	//  scala/util/parsing/combinator/RegexParsers$class.$init$:(Lscala/util/parsing/combinator/RegexParsers;)V
const #53 = Asciz	scala/Predef$;
const #54 = class	#53;	//  scala/Predef$
const #55 = Asciz	Lscala/Predef$;;
const #56 = NameAndType	#4:#55;//  MODULE$:Lscala/Predef$;
const #57 = Field	#54.#56;	//  scala/Predef$.MODULE$:Lscala/Predef$;
const #58 = Asciz	[a-zA-Z_]\w*;
const #59 = String	#58;	//  [a-zA-Z_]\w*
const #60 = Asciz	stringWrapper;
const #61 = Asciz	(Ljava/lang/String;)Lscala/runtime/RichString;;
const #62 = NameAndType	#60:#61;//  stringWrapper:(Ljava/lang/String;)Lscala/runtime/RichString;
const #63 = Method	#54.#62;	//  scala/Predef$.stringWrapper:(Ljava/lang/String;)Lscala/runtime/RichString;
const #64 = Asciz	scala/runtime/RichString;
const #65 = class	#64;	//  scala/runtime/RichString
const #66 = Asciz	r;
const #67 = Asciz	()Lscala/util/matching/Regex;;
const #68 = NameAndType	#66:#67;//  r:()Lscala/util/matching/Regex;
const #69 = Method	#65.#68;	//  scala/runtime/RichString.r:()Lscala/util/matching/Regex;
const #70 = Asciz	scala/util/parsing/combinator/RegexParsers;
const #71 = class	#70;	//  scala/util/parsing/combinator/RegexParsers
const #72 = Asciz	regex;
const #73 = Asciz	(Lscala/util/matching/Regex;)Lscala/util/parsing/combinator/Parsers$Parser;;
const #74 = NameAndType	#72:#73;//  regex:(Lscala/util/matching/Regex;)Lscala/util/parsing/combinator/Parsers$Parser;
const #75 = InterfaceMethod	#71.#74;	//  scala/util/parsing/combinator/RegexParsers.regex:(Lscala/util/matching/Regex;)Lscala/util/parsing/combinator/Parsers$Parser;
const #76 = Asciz	scala/util/parsing/combinator/testing/RegexTest$$anonfun$1;
const #77 = class	#76;	//  scala/util/parsing/combinator/testing/RegexTest$$anonfun$1
const #78 = Method	#77.#12;	//  scala/util/parsing/combinator/testing/RegexTest$$anonfun$1."<init>":()V
const #79 = Asciz	scala/util/parsing/combinator/Parsers$Parser;
const #80 = class	#79;	//  scala/util/parsing/combinator/Parsers$Parser
const #81 = Asciz	$up$up;
const #82 = Asciz	(Lscala/Function1;)Lscala/util/parsing/combinator/Parsers$Parser;;
const #83 = NameAndType	#81:#82;//  $up$up:(Lscala/Function1;)Lscala/util/parsing/combinator/Parsers$Parser;
const #84 = Method	#80.#83;	//  scala/util/parsing/combinator/Parsers$Parser.$up$up:(Lscala/Function1;)Lscala/util/parsing/combinator/Parsers$Parser;
const #85 = NameAndType	#35:#29;//  ident:Lscala/util/parsing/combinator/Parsers$Parser;
const #86 = Field	#10.#85;	//  scala/util/parsing/combinator/testing/RegexTest$.ident:Lscala/util/parsing/combinator/Parsers$Parser;
const #87 = Asciz	\d\d*;
const #88 = String	#87;	//  \d\d*
const #89 = Asciz	scala/util/parsing/combinator/testing/RegexTest$$anonfun$2;
const #90 = class	#89;	//  scala/util/parsing/combinator/testing/RegexTest$$anonfun$2
const #91 = Method	#90.#12;	//  scala/util/parsing/combinator/testing/RegexTest$$anonfun$2."<init>":()V
const #92 = NameAndType	#34:#29;//  number:Lscala/util/parsing/combinator/Parsers$Parser;
const #93 = Field	#10.#92;	//  scala/util/parsing/combinator/testing/RegexTest$.number:Lscala/util/parsing/combinator/Parsers$Parser;
const #94 = Asciz	\".*\";
const #95 = String	#94;	//  \".*\"
const #96 = Asciz	scala/util/parsing/combinator/testing/RegexTest$$anonfun$3;
const #97 = class	#96;	//  scala/util/parsing/combinator/testing/RegexTest$$anonfun$3
const #98 = Method	#97.#12;	//  scala/util/parsing/combinator/testing/RegexTest$$anonfun$3."<init>":()V
const #99 = NameAndType	#32:#29;//  string:Lscala/util/parsing/combinator/Parsers$Parser;
const #100 = Field	#10.#99;	//  scala/util/parsing/combinator/testing/RegexTest$.string:Lscala/util/parsing/combinator/Parsers$Parser;
const #101 = Asciz	()Lscala/util/parsing/combinator/Parsers$Parser;;
const #102 = NameAndType	#35:#101;//  ident:()Lscala/util/parsing/combinator/Parsers$Parser;
const #103 = Method	#10.#102;	//  scala/util/parsing/combinator/testing/RegexTest$.ident:()Lscala/util/parsing/combinator/Parsers$Parser;
const #104 = Asciz	scala/util/parsing/combinator/testing/RegexTest$$anonfun$4;
const #105 = class	#104;	//  scala/util/parsing/combinator/testing/RegexTest$$anonfun$4
const #106 = Method	#105.#12;	//  scala/util/parsing/combinator/testing/RegexTest$$anonfun$4."<init>":()V
const #107 = Asciz	$bar;
const #108 = Asciz	(Lscala/Function0;)Lscala/util/parsing/combinator/Parsers$Parser;;
const #109 = NameAndType	#107:#108;//  $bar:(Lscala/Function0;)Lscala/util/parsing/combinator/Parsers$Parser;
const #110 = Method	#80.#109;	//  scala/util/parsing/combinator/Parsers$Parser.$bar:(Lscala/Function0;)Lscala/util/parsing/combinator/Parsers$Parser;
const #111 = Asciz	scala/util/parsing/combinator/testing/RegexTest$$anonfun$5;
const #112 = class	#111;	//  scala/util/parsing/combinator/testing/RegexTest$$anonfun$5
const #113 = Method	#112.#12;	//  scala/util/parsing/combinator/testing/RegexTest$$anonfun$5."<init>":()V
const #114 = Asciz	$times;
const #115 = NameAndType	#114:#101;//  $times:()Lscala/util/parsing/combinator/Parsers$Parser;
const #116 = Method	#80.#115;	//  scala/util/parsing/combinator/Parsers$Parser.$times:()Lscala/util/parsing/combinator/Parsers$Parser;
const #117 = NameAndType	#28:#29;//  parser:Lscala/util/parsing/combinator/Parsers$Parser;
const #118 = Field	#10.#117;	//  scala/util/parsing/combinator/testing/RegexTest$.parser:Lscala/util/parsing/combinator/Parsers$Parser;
const #119 = Asciz	main;
const #120 = Asciz	([Ljava/lang/String;)V;
const #121 = Asciz	scala/runtime/ScalaRunTime$;
const #122 = class	#121;	//  scala/runtime/ScalaRunTime$
const #123 = Asciz	Lscala/runtime/ScalaRunTime$;;
const #124 = NameAndType	#4:#123;//  MODULE$:Lscala/runtime/ScalaRunTime$;
const #125 = Field	#122.#124;	//  scala/runtime/ScalaRunTime$.MODULE$:Lscala/runtime/ScalaRunTime$;
const #126 = Asciz	boxArray;
const #127 = Asciz	(Ljava/lang/Object;)Lscala/runtime/BoxedArray;;
const #128 = NameAndType	#126:#127;//  boxArray:(Ljava/lang/Object;)Lscala/runtime/BoxedArray;
const #129 = Method	#122.#128;	//  scala/runtime/ScalaRunTime$.boxArray:(Ljava/lang/Object;)Lscala/runtime/BoxedArray;
const #130 = Asciz	 ;
const #131 = String	#130;	//   
const #132 = Asciz	scala/collection/generic/TraversableTemplate;
const #133 = class	#132;	//  scala/collection/generic/TraversableTemplate
const #134 = Asciz	mkString;
const #135 = Asciz	(Ljava/lang/String;)Ljava/lang/String;;
const #136 = NameAndType	#134:#135;//  mkString:(Ljava/lang/String;)Ljava/lang/String;
const #137 = InterfaceMethod	#133.#136;	//  scala/collection/generic/TraversableTemplate.mkString:(Ljava/lang/String;)Ljava/lang/String;
const #138 = Asciz	scala/collection/mutable/StringBuilder;
const #139 = class	#138;	//  scala/collection/mutable/StringBuilder
const #140 = Method	#139.#12;	//  scala/collection/mutable/StringBuilder."<init>":()V
const #141 = Asciz	\nin : ;
const #142 = String	#141;	//  \nin : 
const #143 = Asciz	append;
const #144 = Asciz	(Ljava/lang/Object;)Lscala/collection/mutable/StringBuilder;;
const #145 = NameAndType	#143:#144;//  append:(Ljava/lang/Object;)Lscala/collection/mutable/StringBuilder;
const #146 = Method	#139.#145;	//  scala/collection/mutable/StringBuilder.append:(Ljava/lang/Object;)Lscala/collection/mutable/StringBuilder;
const #147 = Asciz	toString;
const #148 = Asciz	()Ljava/lang/String;;
const #149 = NameAndType	#147:#148;//  toString:()Ljava/lang/String;
const #150 = Method	#139.#149;	//  scala/collection/mutable/StringBuilder.toString:()Ljava/lang/String;
const #151 = Asciz	println;
const #152 = Asciz	(Ljava/lang/Object;)V;
const #153 = NameAndType	#151:#152;//  println:(Ljava/lang/Object;)V
const #154 = Method	#54.#153;	//  scala/Predef$.println:(Ljava/lang/Object;)V
const #155 = NameAndType	#28:#101;//  parser:()Lscala/util/parsing/combinator/Parsers$Parser;
const #156 = Method	#10.#155;	//  scala/util/parsing/combinator/testing/RegexTest$.parser:()Lscala/util/parsing/combinator/Parsers$Parser;
const #157 = Asciz	phrase;
const #158 = Asciz	(Lscala/util/parsing/combinator/Parsers$Parser;)Lscala/util/parsing/combinator/Parsers$Parser;;
const #159 = NameAndType	#157:#158;//  phrase:(Lscala/util/parsing/combinator/Parsers$Parser;)Lscala/util/parsing/combinator/Parsers$Parser;
const #160 = InterfaceMethod	#71.#159;	//  scala/util/parsing/combinator/RegexParsers.phrase:(Lscala/util/parsing/combinator/Parsers$Parser;)Lscala/util/parsing/combinator/Parsers$Parser;
const #161 = Asciz	scala/util/parsing/input/CharSequenceReader;
const #162 = class	#161;	//  scala/util/parsing/input/CharSequenceReader
const #163 = Asciz	(Ljava/lang/CharSequence;)V;
const #164 = NameAndType	#11:#163;//  "<init>":(Ljava/lang/CharSequence;)V
const #165 = Method	#162.#164;	//  scala/util/parsing/input/CharSequenceReader."<init>":(Ljava/lang/CharSequence;)V
const #166 = Asciz	apply;
const #167 = Asciz	(Lscala/util/parsing/input/Reader;)Lscala/util/parsing/combinator/Parsers$ParseResult;;
const #168 = NameAndType	#166:#167;//  apply:(Lscala/util/parsing/input/Reader;)Lscala/util/parsing/combinator/Parsers$ParseResult;
const #169 = Method	#80.#168;	//  scala/util/parsing/combinator/Parsers$Parser.apply:(Lscala/util/parsing/input/Reader;)Lscala/util/parsing/combinator/Parsers$ParseResult;
const #170 = Asciz	this;
const #171 = Asciz	args;
const #172 = Asciz	[Ljava/lang/String;;
const #173 = Asciz	in;
const #174 = Asciz	Ljava/lang/String;;
const #175 = Asciz	LocalVariableTable;
const #176 = Asciz	()Lscala/util/parsing/combinator/Parsers$Parser<Lscala/collection/immutable/List<Ljava/lang/Object;>;>;;
const #177 = Asciz	()Lscala/util/parsing/combinator/Parsers$Parser<Ljava/lang/Object;>;;
const #178 = Asciz	mkList;
const #179 = Asciz	()Lscala/Function1;;
const #180 = Asciz	(Lscala/util/parsing/combinator/Parsers;)Lscala/Function1;;
const #181 = NameAndType	#178:#180;//  mkList:(Lscala/util/parsing/combinator/Parsers;)Lscala/Function1;
const #182 = Method	#43.#181;	//  scala/util/parsing/combinator/Parsers$class.mkList:(Lscala/util/parsing/combinator/Parsers;)Lscala/Function1;
const #183 = Asciz	positioned;
const #184 = Asciz	(Lscala/util/parsing/combinator/Parsers;Lscala/Function0;)Lscala/util/parsing/combinator/Parsers$Parser;;
const #185 = NameAndType	#183:#184;//  positioned:(Lscala/util/parsing/combinator/Parsers;Lscala/Function0;)Lscala/util/parsing/combinator/Parsers$Parser;
const #186 = Method	#43.#185;	//  scala/util/parsing/combinator/Parsers$class.positioned:(Lscala/util/parsing/combinator/Parsers;Lscala/Function0;)Lscala/util/parsing/combinator/Parsers$Parser;
const #187 = Asciz	p;
const #188 = Asciz	Lscala/Function0;;
const #189 = Asciz	guard;
const #190 = NameAndType	#189:#184;//  guard:(Lscala/util/parsing/combinator/Parsers;Lscala/Function0;)Lscala/util/parsing/combinator/Parsers$Parser;
const #191 = Method	#43.#190;	//  scala/util/parsing/combinator/Parsers$class.guard:(Lscala/util/parsing/combinator/Parsers;Lscala/Function0;)Lscala/util/parsing/combinator/Parsers$Parser;
const #192 = Asciz	not;
const #193 = NameAndType	#192:#184;//  not:(Lscala/util/parsing/combinator/Parsers;Lscala/Function0;)Lscala/util/parsing/combinator/Parsers$Parser;
const #194 = Method	#43.#193;	//  scala/util/parsing/combinator/Parsers$class.not:(Lscala/util/parsing/combinator/Parsers;Lscala/Function0;)Lscala/util/parsing/combinator/Parsers$Parser;
const #195 = Asciz	opt;
const #196 = NameAndType	#195:#184;//  opt:(Lscala/util/parsing/combinator/Parsers;Lscala/Function0;)Lscala/util/parsing/combinator/Parsers$Parser;
const #197 = Method	#43.#196;	//  scala/util/parsing/combinator/Parsers$class.opt:(Lscala/util/parsing/combinator/Parsers;Lscala/Function0;)Lscala/util/parsing/combinator/Parsers$Parser;
const #198 = Asciz	chainr1;
const #199 = Asciz	(Lscala/Function0;Lscala/Function0;Lscala/Function2;Ljava/lang/Object;)Lscala/util/parsing/combinator/Parsers$Parser;;
const #200 = Asciz	(Lscala/util/parsing/combinator/Parsers;Lscala/Function0;Lscala/Function0;Lscala/Function2;Ljava/lang/Object;)Lscala/util/parsing/combinator/Parsers$Parser;;
const #201 = NameAndType	#198:#200;//  chainr1:(Lscala/util/parsing/combinator/Parsers;Lscala/Function0;Lscala/Function0;Lscala/Function2;Ljava/lang/Object;)Lscala/util/parsing/combinator/Parsers$Parser;
const #202 = Method	#43.#201;	//  scala/util/parsing/combinator/Parsers$class.chainr1:(Lscala/util/parsing/combinator/Parsers;Lscala/Function0;Lscala/Function0;Lscala/Function2;Ljava/lang/Object;)Lscala/util/parsing/combinator/Parsers$Parser;
const #203 = Asciz	q;
const #204 = Asciz	combine;
const #205 = Asciz	Lscala/Function2;;
const #206 = Asciz	first;
const #207 = Asciz	Ljava/lang/Object;;
const #208 = Asciz	chainl1;
const #209 = Asciz	(Lscala/Function0;Lscala/Function0;Lscala/Function0;)Lscala/util/parsing/combinator/Parsers$Parser;;
const #210 = Asciz	(Lscala/util/parsing/combinator/Parsers;Lscala/Function0;Lscala/Function0;Lscala/Function0;)Lscala/util/parsing/combinator/Parsers$Parser;;
const #211 = NameAndType	#208:#210;//  chainl1:(Lscala/util/parsing/combinator/Parsers;Lscala/Function0;Lscala/Function0;Lscala/Function0;)Lscala/util/parsing/combinator/Parsers$Parser;
const #212 = Method	#43.#211;	//  scala/util/parsing/combinator/Parsers$class.chainl1:(Lscala/util/parsing/combinator/Parsers;Lscala/Function0;Lscala/Function0;Lscala/Function0;)Lscala/util/parsing/combinator/Parsers$Parser;
const #213 = Asciz	(Lscala/Function0;Lscala/Function0;)Lscala/util/parsing/combinator/Parsers$Parser;;
const #214 = Asciz	(Lscala/util/parsing/combinator/Parsers;Lscala/Function0;Lscala/Function0;)Lscala/util/parsing/combinator/Parsers$Parser;;
const #215 = NameAndType	#208:#214;//  chainl1:(Lscala/util/parsing/combinator/Parsers;Lscala/Function0;Lscala/Function0;)Lscala/util/parsing/combinator/Parsers$Parser;
const #216 = Method	#43.#215;	//  scala/util/parsing/combinator/Parsers$class.chainl1:(Lscala/util/parsing/combinator/Parsers;Lscala/Function0;Lscala/Function0;)Lscala/util/parsing/combinator/Parsers$Parser;
const #217 = Asciz	rep1sep;
const #218 = NameAndType	#217:#214;//  rep1sep:(Lscala/util/parsing/combinator/Parsers;Lscala/Function0;Lscala/Function0;)Lscala/util/parsing/combinator/Parsers$Parser;
const #219 = Method	#43.#218;	//  scala/util/parsing/combinator/Parsers$class.rep1sep:(Lscala/util/parsing/combinator/Parsers;Lscala/Function0;Lscala/Function0;)Lscala/util/parsing/combinator/Parsers$Parser;
const #220 = Asciz	repN;
const #221 = Asciz	(ILscala/Function0;)Lscala/util/parsing/combinator/Parsers$Parser;;
const #222 = Asciz	(Lscala/util/parsing/combinator/Parsers;ILscala/Function0;)Lscala/util/parsing/combinator/Parsers$Parser;;
const #223 = NameAndType	#220:#222;//  repN:(Lscala/util/parsing/combinator/Parsers;ILscala/Function0;)Lscala/util/parsing/combinator/Parsers$Parser;
const #224 = Method	#43.#223;	//  scala/util/parsing/combinator/Parsers$class.repN:(Lscala/util/parsing/combinator/Parsers;ILscala/Function0;)Lscala/util/parsing/combinator/Parsers$Parser;
const #225 = Asciz	n;
const #226 = Asciz	I;
const #227 = Asciz	rep1;
const #228 = NameAndType	#227:#214;//  rep1:(Lscala/util/parsing/combinator/Parsers;Lscala/Function0;Lscala/Function0;)Lscala/util/parsing/combinator/Parsers$Parser;
const #229 = Method	#43.#228;	//  scala/util/parsing/combinator/Parsers$class.rep1:(Lscala/util/parsing/combinator/Parsers;Lscala/Function0;Lscala/Function0;)Lscala/util/parsing/combinator/Parsers$Parser;
const #230 = NameAndType	#227:#184;//  rep1:(Lscala/util/parsing/combinator/Parsers;Lscala/Function0;)Lscala/util/parsing/combinator/Parsers$Parser;
const #231 = Method	#43.#230;	//  scala/util/parsing/combinator/Parsers$class.rep1:(Lscala/util/parsing/combinator/Parsers;Lscala/Function0;)Lscala/util/parsing/combinator/Parsers$Parser;
const #232 = Asciz	repsep;
const #233 = NameAndType	#232:#214;//  repsep:(Lscala/util/parsing/combinator/Parsers;Lscala/Function0;Lscala/Function0;)Lscala/util/parsing/combinator/Parsers$Parser;
const #234 = Method	#43.#233;	//  scala/util/parsing/combinator/Parsers$class.repsep:(Lscala/util/parsing/combinator/Parsers;Lscala/Function0;Lscala/Function0;)Lscala/util/parsing/combinator/Parsers$Parser;
const #235 = Asciz	rep;
const #236 = NameAndType	#235:#184;//  rep:(Lscala/util/parsing/combinator/Parsers;Lscala/Function0;)Lscala/util/parsing/combinator/Parsers$Parser;
const #237 = Method	#43.#236;	//  scala/util/parsing/combinator/Parsers$class.rep:(Lscala/util/parsing/combinator/Parsers;Lscala/Function0;)Lscala/util/parsing/combinator/Parsers$Parser;
const #238 = Asciz	log;
const #239 = Asciz	(Lscala/Function0;Ljava/lang/String;)Lscala/util/parsing/combinator/Parsers$Parser;;
const #240 = Asciz	(Lscala/util/parsing/combinator/Parsers;Lscala/Function0;Ljava/lang/String;)Lscala/util/parsing/combinator/Parsers$Parser;;
const #241 = NameAndType	#238:#240;//  log:(Lscala/util/parsing/combinator/Parsers;Lscala/Function0;Ljava/lang/String;)Lscala/util/parsing/combinator/Parsers$Parser;
const #242 = Method	#43.#241;	//  scala/util/parsing/combinator/Parsers$class.log:(Lscala/util/parsing/combinator/Parsers;Lscala/Function0;Ljava/lang/String;)Lscala/util/parsing/combinator/Parsers$Parser;
const #243 = Asciz	name;
const #244 = Asciz	success;
const #245 = Asciz	(Ljava/lang/Object;)Lscala/util/parsing/combinator/Parsers$Parser;;
const #246 = Asciz	(Lscala/util/parsing/combinator/Parsers;Ljava/lang/Object;)Lscala/util/parsing/combinator/Parsers$Parser;;
const #247 = NameAndType	#244:#246;//  success:(Lscala/util/parsing/combinator/Parsers;Ljava/lang/Object;)Lscala/util/parsing/combinator/Parsers$Parser;
const #248 = Method	#43.#247;	//  scala/util/parsing/combinator/Parsers$class.success:(Lscala/util/parsing/combinator/Parsers;Ljava/lang/Object;)Lscala/util/parsing/combinator/Parsers$Parser;
const #249 = Asciz	v;
const #250 = Asciz	err;
const #251 = Asciz	(Ljava/lang/String;)Lscala/util/parsing/combinator/Parsers$Parser;;
const #252 = Asciz	(Lscala/util/parsing/combinator/Parsers;Ljava/lang/String;)Lscala/util/parsing/combinator/Parsers$Parser;;
const #253 = NameAndType	#250:#252;//  err:(Lscala/util/parsing/combinator/Parsers;Ljava/lang/String;)Lscala/util/parsing/combinator/Parsers$Parser;
const #254 = Method	#43.#253;	//  scala/util/parsing/combinator/Parsers$class.err:(Lscala/util/parsing/combinator/Parsers;Ljava/lang/String;)Lscala/util/parsing/combinator/Parsers$Parser;
const #255 = Asciz	msg;
const #256 = Asciz	failure;
const #257 = NameAndType	#256:#252;//  failure:(Lscala/util/parsing/combinator/Parsers;Ljava/lang/String;)Lscala/util/parsing/combinator/Parsers$Parser;
const #258 = Method	#43.#257;	//  scala/util/parsing/combinator/Parsers$class.failure:(Lscala/util/parsing/combinator/Parsers;Ljava/lang/String;)Lscala/util/parsing/combinator/Parsers$Parser;
const #259 = Asciz	acceptSeq;
const #260 = Asciz	(Ljava/lang/Object;Lscala/Function1;)Lscala/util/parsing/combinator/Parsers$Parser;;
const #261 = Asciz	(Lscala/util/parsing/combinator/Parsers;Ljava/lang/Object;Lscala/Function1;)Lscala/util/parsing/combinator/Parsers$Parser;;
const #262 = NameAndType	#259:#261;//  acceptSeq:(Lscala/util/parsing/combinator/Parsers;Ljava/lang/Object;Lscala/Function1;)Lscala/util/parsing/combinator/Parsers$Parser;
const #263 = Method	#43.#262;	//  scala/util/parsing/combinator/Parsers$class.acceptSeq:(Lscala/util/parsing/combinator/Parsers;Ljava/lang/Object;Lscala/Function1;)Lscala/util/parsing/combinator/Parsers$Parser;
const #264 = Asciz	es;
const #265 = Asciz	view$2;
const #266 = Asciz	Lscala/Function1;;
const #267 = Asciz	acceptMatch;
const #268 = Asciz	(Ljava/lang/String;Lscala/PartialFunction;)Lscala/util/parsing/combinator/Parsers$Parser;;
const #269 = Asciz	(Lscala/util/parsing/combinator/Parsers;Ljava/lang/String;Lscala/PartialFunction;)Lscala/util/parsing/combinator/Parsers$Parser;;
const #270 = NameAndType	#267:#269;//  acceptMatch:(Lscala/util/parsing/combinator/Parsers;Ljava/lang/String;Lscala/PartialFunction;)Lscala/util/parsing/combinator/Parsers$Parser;
const #271 = Method	#43.#270;	//  scala/util/parsing/combinator/Parsers$class.acceptMatch:(Lscala/util/parsing/combinator/Parsers;Ljava/lang/String;Lscala/PartialFunction;)Lscala/util/parsing/combinator/Parsers$Parser;
const #272 = Asciz	expected;
const #273 = Asciz	f;
const #274 = Asciz	Lscala/PartialFunction;;
const #275 = Asciz	acceptIf;
const #276 = Asciz	(Lscala/Function1;Lscala/Function1;)Lscala/util/parsing/combinator/Parsers$Parser;;
const #277 = Asciz	(Lscala/util/parsing/combinator/Parsers;Lscala/Function1;Lscala/Function1;)Lscala/util/parsing/combinator/Parsers$Parser;;
const #278 = NameAndType	#275:#277;//  acceptIf:(Lscala/util/parsing/combinator/Parsers;Lscala/Function1;Lscala/Function1;)Lscala/util/parsing/combinator/Parsers$Parser;
const #279 = Method	#43.#278;	//  scala/util/parsing/combinator/Parsers$class.acceptIf:(Lscala/util/parsing/combinator/Parsers;Lscala/Function1;Lscala/Function1;)Lscala/util/parsing/combinator/Parsers$Parser;
const #280 = Asciz	accept;
const #281 = NameAndType	#280:#269;//  accept:(Lscala/util/parsing/combinator/Parsers;Ljava/lang/String;Lscala/PartialFunction;)Lscala/util/parsing/combinator/Parsers$Parser;
const #282 = Method	#43.#281;	//  scala/util/parsing/combinator/Parsers$class.accept:(Lscala/util/parsing/combinator/Parsers;Ljava/lang/String;Lscala/PartialFunction;)Lscala/util/parsing/combinator/Parsers$Parser;
const #283 = NameAndType	#280:#261;//  accept:(Lscala/util/parsing/combinator/Parsers;Ljava/lang/Object;Lscala/Function1;)Lscala/util/parsing/combinator/Parsers$Parser;
const #284 = Method	#43.#283;	//  scala/util/parsing/combinator/Parsers$class.accept:(Lscala/util/parsing/combinator/Parsers;Ljava/lang/Object;Lscala/Function1;)Lscala/util/parsing/combinator/Parsers$Parser;
const #285 = Asciz	view$1;
const #286 = NameAndType	#280:#246;//  accept:(Lscala/util/parsing/combinator/Parsers;Ljava/lang/Object;)Lscala/util/parsing/combinator/Parsers$Parser;
const #287 = Method	#43.#286;	//  scala/util/parsing/combinator/Parsers$class.accept:(Lscala/util/parsing/combinator/Parsers;Ljava/lang/Object;)Lscala/util/parsing/combinator/Parsers$Parser;
const #288 = Asciz	e;
const #289 = Asciz	elem;
const #290 = NameAndType	#289:#246;//  elem:(Lscala/util/parsing/combinator/Parsers;Ljava/lang/Object;)Lscala/util/parsing/combinator/Parsers$Parser;
const #291 = Method	#43.#290;	//  scala/util/parsing/combinator/Parsers$class.elem:(Lscala/util/parsing/combinator/Parsers;Ljava/lang/Object;)Lscala/util/parsing/combinator/Parsers$Parser;
const #292 = Asciz	(Ljava/lang/String;Lscala/Function1;)Lscala/util/parsing/combinator/Parsers$Parser;;
const #293 = Asciz	(Lscala/util/parsing/combinator/Parsers;Ljava/lang/String;Lscala/Function1;)Lscala/util/parsing/combinator/Parsers$Parser;;
const #294 = NameAndType	#289:#293;//  elem:(Lscala/util/parsing/combinator/Parsers;Ljava/lang/String;Lscala/Function1;)Lscala/util/parsing/combinator/Parsers$Parser;
const #295 = Method	#43.#294;	//  scala/util/parsing/combinator/Parsers$class.elem:(Lscala/util/parsing/combinator/Parsers;Ljava/lang/String;Lscala/Function1;)Lscala/util/parsing/combinator/Parsers$Parser;
const #296 = Asciz	kind;
const #297 = Asciz	commit;
const #298 = NameAndType	#297:#184;//  commit:(Lscala/util/parsing/combinator/Parsers;Lscala/Function0;)Lscala/util/parsing/combinator/Parsers$Parser;
const #299 = Method	#43.#298;	//  scala/util/parsing/combinator/Parsers$class.commit:(Lscala/util/parsing/combinator/Parsers;Lscala/Function0;)Lscala/util/parsing/combinator/Parsers$Parser;
const #300 = Asciz	OnceParser;
const #301 = Asciz	(Lscala/util/parsing/combinator/Parsers;Lscala/Function1;)Lscala/util/parsing/combinator/Parsers$Parser;;
const #302 = NameAndType	#300:#301;//  OnceParser:(Lscala/util/parsing/combinator/Parsers;Lscala/Function1;)Lscala/util/parsing/combinator/Parsers$Parser;
const #303 = Method	#43.#302;	//  scala/util/parsing/combinator/Parsers$class.OnceParser:(Lscala/util/parsing/combinator/Parsers;Lscala/Function1;)Lscala/util/parsing/combinator/Parsers$Parser;
const #304 = Asciz	Parser;
const #305 = NameAndType	#304:#301;//  Parser:(Lscala/util/parsing/combinator/Parsers;Lscala/Function1;)Lscala/util/parsing/combinator/Parsers$Parser;
const #306 = Method	#43.#305;	//  scala/util/parsing/combinator/Parsers$class.Parser:(Lscala/util/parsing/combinator/Parsers;Lscala/Function1;)Lscala/util/parsing/combinator/Parsers$Parser;
const #307 = Asciz	$tilde;
const #308 = Asciz	()Lscala/util/parsing/combinator/Parsers$$tilde$;;
const #309 = NameAndType	#14:#15;//  $tilde$module:Lscala/util/parsing/combinator/Parsers$$tilde$;
const #310 = Field	#10.#309;	//  scala/util/parsing/combinator/testing/RegexTest$.$tilde$module:Lscala/util/parsing/combinator/Parsers$$tilde$;
const #311 = Asciz	scala/util/parsing/combinator/Parsers$$tilde$;
const #312 = class	#311;	//  scala/util/parsing/combinator/Parsers$$tilde$
const #313 = NameAndType	#11:#45;//  "<init>":(Lscala/util/parsing/combinator/Parsers;)V
const #314 = Method	#312.#313;	//  scala/util/parsing/combinator/Parsers$$tilde$."<init>":(Lscala/util/parsing/combinator/Parsers;)V
const #315 = Asciz	Error;
const #316 = Asciz	()Lscala/util/parsing/combinator/Parsers$Error$;;
const #317 = NameAndType	#16:#17;//  Error$module:Lscala/util/parsing/combinator/Parsers$Error$;
const #318 = Field	#10.#317;	//  scala/util/parsing/combinator/testing/RegexTest$.Error$module:Lscala/util/parsing/combinator/Parsers$Error$;
const #319 = Asciz	scala/util/parsing/combinator/Parsers$Error$;
const #320 = class	#319;	//  scala/util/parsing/combinator/Parsers$Error$
const #321 = Method	#320.#313;	//  scala/util/parsing/combinator/Parsers$Error$."<init>":(Lscala/util/parsing/combinator/Parsers;)V
const #322 = Asciz	Failure;
const #323 = Asciz	()Lscala/util/parsing/combinator/Parsers$Failure$;;
const #324 = NameAndType	#18:#19;//  Failure$module:Lscala/util/parsing/combinator/Parsers$Failure$;
const #325 = Field	#10.#324;	//  scala/util/parsing/combinator/testing/RegexTest$.Failure$module:Lscala/util/parsing/combinator/Parsers$Failure$;
const #326 = Asciz	scala/util/parsing/combinator/Parsers$Failure$;
const #327 = class	#326;	//  scala/util/parsing/combinator/Parsers$Failure$
const #328 = Method	#327.#313;	//  scala/util/parsing/combinator/Parsers$Failure$."<init>":(Lscala/util/parsing/combinator/Parsers;)V
const #329 = Asciz	NoSuccess;
const #330 = Asciz	()Lscala/util/parsing/combinator/Parsers$NoSuccess$;;
const #331 = NameAndType	#20:#21;//  NoSuccess$module:Lscala/util/parsing/combinator/Parsers$NoSuccess$;
const #332 = Field	#10.#331;	//  scala/util/parsing/combinator/testing/RegexTest$.NoSuccess$module:Lscala/util/parsing/combinator/Parsers$NoSuccess$;
const #333 = Asciz	scala/util/parsing/combinator/Parsers$NoSuccess$;
const #334 = class	#333;	//  scala/util/parsing/combinator/Parsers$NoSuccess$
const #335 = Method	#334.#313;	//  scala/util/parsing/combinator/Parsers$NoSuccess$."<init>":(Lscala/util/parsing/combinator/Parsers;)V
const #336 = Asciz	lastNoSuccess_$eq;
const #337 = Asciz	(Lscala/util/parsing/combinator/Parsers$NoSuccess;)V;
const #338 = NameAndType	#24:#25;//  lastNoSuccess:Lscala/util/parsing/combinator/Parsers$NoSuccess;
const #339 = Field	#10.#338;	//  scala/util/parsing/combinator/testing/RegexTest$.lastNoSuccess:Lscala/util/parsing/combinator/Parsers$NoSuccess;
const #340 = Asciz	()Lscala/util/parsing/combinator/Parsers$NoSuccess;;
const #341 = Asciz	Success;
const #342 = Asciz	()Lscala/util/parsing/combinator/Parsers$Success$;;
const #343 = NameAndType	#22:#23;//  Success$module:Lscala/util/parsing/combinator/Parsers$Success$;
const #344 = Field	#10.#343;	//  scala/util/parsing/combinator/testing/RegexTest$.Success$module:Lscala/util/parsing/combinator/Parsers$Success$;
const #345 = Asciz	scala/util/parsing/combinator/Parsers$Success$;
const #346 = class	#345;	//  scala/util/parsing/combinator/Parsers$Success$
const #347 = Method	#346.#313;	//  scala/util/parsing/combinator/Parsers$Success$."<init>":(Lscala/util/parsing/combinator/Parsers;)V
const #348 = Asciz	parseAll;
const #349 = Asciz	(Lscala/util/parsing/combinator/Parsers$Parser;Ljava/lang/CharSequence;)Lscala/util/parsing/combinator/Parsers$ParseResult;;
const #350 = Asciz	(Lscala/util/parsing/combinator/RegexParsers;Lscala/util/parsing/combinator/Parsers$Parser;Ljava/lang/CharSequence;)Lscala/util/parsing/combinator/Parsers$ParseResult;;
const #351 = NameAndType	#348:#350;//  parseAll:(Lscala/util/parsing/combinator/RegexParsers;Lscala/util/parsing/combinator/Parsers$Parser;Ljava/lang/CharSequence;)Lscala/util/parsing/combinator/Parsers$ParseResult;
const #352 = Method	#49.#351;	//  scala/util/parsing/combinator/RegexParsers$class.parseAll:(Lscala/util/parsing/combinator/RegexParsers;Lscala/util/parsing/combinator/Parsers$Parser;Ljava/lang/CharSequence;)Lscala/util/parsing/combinator/Parsers$ParseResult;
const #353 = Asciz	Ljava/lang/CharSequence;;
const #354 = Asciz	(Lscala/util/parsing/combinator/Parsers$Parser;Ljava/io/Reader;)Lscala/util/parsing/combinator/Parsers$ParseResult;;
const #355 = Asciz	(Lscala/util/parsing/combinator/RegexParsers;Lscala/util/parsing/combinator/Parsers$Parser;Ljava/io/Reader;)Lscala/util/parsing/combinator/Parsers$ParseResult;;
const #356 = NameAndType	#348:#355;//  parseAll:(Lscala/util/parsing/combinator/RegexParsers;Lscala/util/parsing/combinator/Parsers$Parser;Ljava/io/Reader;)Lscala/util/parsing/combinator/Parsers$ParseResult;
const #357 = Method	#49.#356;	//  scala/util/parsing/combinator/RegexParsers$class.parseAll:(Lscala/util/parsing/combinator/RegexParsers;Lscala/util/parsing/combinator/Parsers$Parser;Ljava/io/Reader;)Lscala/util/parsing/combinator/Parsers$ParseResult;
const #358 = Asciz	Ljava/io/Reader;;
const #359 = Asciz	(Lscala/util/parsing/combinator/Parsers$Parser;Lscala/util/parsing/input/Reader;)Lscala/util/parsing/combinator/Parsers$ParseResult;;
const #360 = Asciz	(Lscala/util/parsing/combinator/RegexParsers;Lscala/util/parsing/combinator/Parsers$Parser;Lscala/util/parsing/input/Reader;)Lscala/util/parsing/combinator/Parsers$ParseResult;;
const #361 = NameAndType	#348:#360;//  parseAll:(Lscala/util/parsing/combinator/RegexParsers;Lscala/util/parsing/combinator/Parsers$Parser;Lscala/util/parsing/input/Reader;)Lscala/util/parsing/combinator/Parsers$ParseResult;
const #362 = Method	#49.#361;	//  scala/util/parsing/combinator/RegexParsers$class.parseAll:(Lscala/util/parsing/combinator/RegexParsers;Lscala/util/parsing/combinator/Parsers$Parser;Lscala/util/parsing/input/Reader;)Lscala/util/parsing/combinator/Parsers$ParseResult;
const #363 = Asciz	Lscala/util/parsing/input/Reader;;
const #364 = Asciz	parse;
const #365 = NameAndType	#364:#355;//  parse:(Lscala/util/parsing/combinator/RegexParsers;Lscala/util/parsing/combinator/Parsers$Parser;Ljava/io/Reader;)Lscala/util/parsing/combinator/Parsers$ParseResult;
const #366 = Method	#49.#365;	//  scala/util/parsing/combinator/RegexParsers$class.parse:(Lscala/util/parsing/combinator/RegexParsers;Lscala/util/parsing/combinator/Parsers$Parser;Ljava/io/Reader;)Lscala/util/parsing/combinator/Parsers$ParseResult;
const #367 = NameAndType	#364:#350;//  parse:(Lscala/util/parsing/combinator/RegexParsers;Lscala/util/parsing/combinator/Parsers$Parser;Ljava/lang/CharSequence;)Lscala/util/parsing/combinator/Parsers$ParseResult;
const #368 = Method	#49.#367;	//  scala/util/parsing/combinator/RegexParsers$class.parse:(Lscala/util/parsing/combinator/RegexParsers;Lscala/util/parsing/combinator/Parsers$Parser;Ljava/lang/CharSequence;)Lscala/util/parsing/combinator/Parsers$ParseResult;
const #369 = NameAndType	#364:#360;//  parse:(Lscala/util/parsing/combinator/RegexParsers;Lscala/util/parsing/combinator/Parsers$Parser;Lscala/util/parsing/input/Reader;)Lscala/util/parsing/combinator/Parsers$ParseResult;
const #370 = Method	#49.#369;	//  scala/util/parsing/combinator/RegexParsers$class.parse:(Lscala/util/parsing/combinator/RegexParsers;Lscala/util/parsing/combinator/Parsers$Parser;Lscala/util/parsing/input/Reader;)Lscala/util/parsing/combinator/Parsers$ParseResult;
const #371 = Asciz	(Lscala/util/parsing/combinator/RegexParsers;Lscala/util/parsing/combinator/Parsers$Parser;)Lscala/util/parsing/combinator/Parsers$Parser;;
const #372 = NameAndType	#157:#371;//  phrase:(Lscala/util/parsing/combinator/RegexParsers;Lscala/util/parsing/combinator/Parsers$Parser;)Lscala/util/parsing/combinator/Parsers$Parser;
const #373 = Method	#49.#372;	//  scala/util/parsing/combinator/RegexParsers$class.phrase:(Lscala/util/parsing/combinator/RegexParsers;Lscala/util/parsing/combinator/Parsers$Parser;)Lscala/util/parsing/combinator/Parsers$Parser;
const #374 = Asciz	(Lscala/util/parsing/combinator/RegexParsers;Lscala/util/matching/Regex;)Lscala/util/parsing/combinator/Parsers$Parser;;
const #375 = NameAndType	#72:#374;//  regex:(Lscala/util/parsing/combinator/RegexParsers;Lscala/util/matching/Regex;)Lscala/util/parsing/combinator/Parsers$Parser;
const #376 = Method	#49.#375;	//  scala/util/parsing/combinator/RegexParsers$class.regex:(Lscala/util/parsing/combinator/RegexParsers;Lscala/util/matching/Regex;)Lscala/util/parsing/combinator/Parsers$Parser;
const #377 = Asciz	literal;
const #378 = Asciz	(Lscala/util/parsing/combinator/RegexParsers;Ljava/lang/String;)Lscala/util/parsing/combinator/Parsers$Parser;;
const #379 = NameAndType	#377:#378;//  literal:(Lscala/util/parsing/combinator/RegexParsers;Ljava/lang/String;)Lscala/util/parsing/combinator/Parsers$Parser;
const #380 = Method	#49.#379;	//  scala/util/parsing/combinator/RegexParsers$class.literal:(Lscala/util/parsing/combinator/RegexParsers;Ljava/lang/String;)Lscala/util/parsing/combinator/Parsers$Parser;
const #381 = Asciz	s;
const #382 = Asciz	handleWhiteSpace;
const #383 = Asciz	(Ljava/lang/CharSequence;I)I;
const #384 = Asciz	(Lscala/util/parsing/combinator/RegexParsers;Ljava/lang/CharSequence;I)I;
const #385 = NameAndType	#382:#384;//  handleWhiteSpace:(Lscala/util/parsing/combinator/RegexParsers;Ljava/lang/CharSequence;I)I
const #386 = Method	#49.#385;	//  scala/util/parsing/combinator/RegexParsers$class.handleWhiteSpace:(Lscala/util/parsing/combinator/RegexParsers;Ljava/lang/CharSequence;I)I
const #387 = Asciz	source;
const #388 = Asciz	offset;
const #389 = Asciz	skipWhitespace;
const #390 = Asciz	()Z;
const #391 = Asciz	(Lscala/util/parsing/combinator/RegexParsers;)Z;
const #392 = NameAndType	#389:#391;//  skipWhitespace:(Lscala/util/parsing/combinator/RegexParsers;)Z
const #393 = Method	#49.#392;	//  scala/util/parsing/combinator/RegexParsers$class.skipWhitespace:(Lscala/util/parsing/combinator/RegexParsers;)Z
const #394 = Asciz	scala$util$parsing$combinator$RegexParsers$_setter_$whiteSpace_$eq;
const #395 = Asciz	(Lscala/util/matching/Regex;)V;
const #396 = NameAndType	#26:#27;//  whiteSpace:Lscala/util/matching/Regex;
const #397 = Field	#10.#396;	//  scala/util/parsing/combinator/testing/RegexTest$.whiteSpace:Lscala/util/matching/Regex;
const #398 = Asciz	scala$util$parsing$combinator$RegexParsers$$super$phrase;
const #399 = Asciz	(Lscala/util/parsing/combinator/Parsers;Lscala/util/parsing/combinator/Parsers$Parser;)Lscala/util/parsing/combinator/Parsers$Parser;;
const #400 = NameAndType	#157:#399;//  phrase:(Lscala/util/parsing/combinator/Parsers;Lscala/util/parsing/combinator/Parsers$Parser;)Lscala/util/parsing/combinator/Parsers$Parser;
const #401 = Method	#43.#400;	//  scala/util/parsing/combinator/Parsers$class.phrase:(Lscala/util/parsing/combinator/Parsers;Lscala/util/parsing/combinator/Parsers$Parser;)Lscala/util/parsing/combinator/Parsers$Parser;
const #402 = Asciz	InnerClasses;
const #403 = Asciz	scala/util/parsing/combinator/Parsers;
const #404 = class	#403;	//  scala/util/parsing/combinator/Parsers
const #405 = Asciz	scala/util/parsing/combinator/Parsers$NoSuccess;
const #406 = class	#405;	//  scala/util/parsing/combinator/Parsers$NoSuccess
const #407 = Asciz	scala/util/parsing/combinator/Parsers$ParseResult;
const #408 = class	#407;	//  scala/util/parsing/combinator/Parsers$ParseResult
const #409 = Asciz	ParseResult;
const #410 = Asciz	scala/util/parsing/combinator/testing/RegexTest;
const #411 = class	#410;	//  scala/util/parsing/combinator/testing/RegexTest
const #412 = Asciz	$anonfun$2;
const #413 = Asciz	$anonfun$4;
const #414 = Asciz	$anonfun$3;
const #415 = Asciz	$anonfun$1;
const #416 = Asciz	$anonfun$5;
const #417 = Asciz	scala/ScalaObject;
const #418 = class	#417;	//  scala/ScalaObject

{
public static final scala.util.parsing.combinator.testing.RegexTest$ MODULE$;

public static {};
  Code:
   Stack=1, Locals=0, Args_size=0
   0:	new	#10; //class scala/util/parsing/combinator/testing/RegexTest$
   3:	invokespecial	#13; //Method "<init>":()V
   6:	return

public void main(java.lang.String[]);
  Code:
   Stack=5, Locals=3, Args_size=2
   0:	getstatic	#125; //Field scala/runtime/ScalaRunTime$.MODULE$:Lscala/runtime/ScalaRunTime$;
   3:	aload_1
   4:	invokevirtual	#129; //Method scala/runtime/ScalaRunTime$.boxArray:(Ljava/lang/Object;)Lscala/runtime/BoxedArray;
   7:	ldc	#131; //String  
   9:	invokeinterface	#137,  2; //InterfaceMethod scala/collection/generic/TraversableTemplate.mkString:(Ljava/lang/String;)Ljava/lang/String;
   14:	astore_2
   15:	getstatic	#57; //Field scala/Predef$.MODULE$:Lscala/Predef$;
   18:	new	#139; //class scala/collection/mutable/StringBuilder
   21:	dup
   22:	invokespecial	#140; //Method scala/collection/mutable/StringBuilder."<init>":()V
   25:	ldc	#142; //String \nin : 
   27:	invokevirtual	#146; //Method scala/collection/mutable/StringBuilder.append:(Ljava/lang/Object;)Lscala/collection/mutable/StringBuilder;
   30:	aload_2
   31:	invokevirtual	#146; //Method scala/collection/mutable/StringBuilder.append:(Ljava/lang/Object;)Lscala/collection/mutable/StringBuilder;
   34:	invokevirtual	#150; //Method scala/collection/mutable/StringBuilder.toString:()Ljava/lang/String;
   37:	invokevirtual	#154; //Method scala/Predef$.println:(Ljava/lang/Object;)V
   40:	getstatic	#57; //Field scala/Predef$.MODULE$:Lscala/Predef$;
   43:	aload_0
   44:	aload_0
   45:	invokevirtual	#156; //Method parser:()Lscala/util/parsing/combinator/Parsers$Parser;
   48:	invokeinterface	#160,  2; //InterfaceMethod scala/util/parsing/combinator/RegexParsers.phrase:(Lscala/util/parsing/combinator/Parsers$Parser;)Lscala/util/parsing/combinator/Parsers$Parser;
   53:	new	#162; //class scala/util/parsing/input/CharSequenceReader
   56:	dup
   57:	aload_2
   58:	invokespecial	#165; //Method scala/util/parsing/input/CharSequenceReader."<init>":(Ljava/lang/CharSequence;)V
   61:	invokevirtual	#169; //Method scala/util/parsing/combinator/Parsers$Parser.apply:(Lscala/util/parsing/input/Reader;)Lscala/util/parsing/combinator/Parsers$ParseResult;
   64:	invokevirtual	#154; //Method scala/Predef$.println:(Ljava/lang/Object;)V
   67:	return
  LineNumberTable: 
   line 19: 0
   line 20: 15
   line 21: 40

  LocalVariableTable: 
   Start  Length  Slot  Name   Signature
   0      68      0    this       Lscala/util/parsing/combinator/testing/RegexTest$;
   0      68      1    args       [Ljava/lang/String;
   15      52      2    in       Ljava/lang/String;


public scala.util.parsing.combinator.Parsers$Parser parser();
  Code:
   Stack=1, Locals=1, Args_size=1
   0:	aload_0
   1:	getfield	#118; //Field parser:Lscala/util/parsing/combinator/Parsers$Parser;
   4:	areturn
  LineNumberTable: 
   line 16: 0

  Signature: length = 0x2
   00 FFFFFFB0 

public scala.util.parsing.combinator.Parsers$Parser string();
  Code:
   Stack=1, Locals=1, Args_size=1
   0:	aload_0
   1:	getfield	#100; //Field string:Lscala/util/parsing/combinator/Parsers$Parser;
   4:	areturn
  LineNumberTable: 
   line 15: 0

  Signature: length = 0x2
   00 FFFFFFB1 

public scala.util.parsing.combinator.Parsers$Parser number();
  Code:
   Stack=1, Locals=1, Args_size=1
   0:	aload_0
   1:	getfield	#93; //Field number:Lscala/util/parsing/combinator/Parsers$Parser;
   4:	areturn
  LineNumberTable: 
   line 14: 0

  Signature: length = 0x2
   00 FFFFFFB1 

public scala.util.parsing.combinator.Parsers$Parser ident();
  Code:
   Stack=1, Locals=1, Args_size=1
   0:	aload_0
   1:	getfield	#86; //Field ident:Lscala/util/parsing/combinator/Parsers$Parser;
   4:	areturn
  LineNumberTable: 
   line 13: 0

  Signature: length = 0x2
   00 FFFFFFB1 

public scala.Function1 mkList();
  Code:
   Stack=1, Locals=1, Args_size=1
   0:	aload_0
   1:	invokestatic	#182; //Method scala/util/parsing/combinator/Parsers$class.mkList:(Lscala/util/parsing/combinator/Parsers;)Lscala/Function1;
   4:	areturn
  LineNumberTable: 
   line 12: 0


public scala.util.parsing.combinator.Parsers$Parser positioned(scala.Function0);
  Code:
   Stack=2, Locals=2, Args_size=2
   0:	aload_0
   1:	aload_1
   2:	invokestatic	#186; //Method scala/util/parsing/combinator/Parsers$class.positioned:(Lscala/util/parsing/combinator/Parsers;Lscala/Function0;)Lscala/util/parsing/combinator/Parsers$Parser;
   5:	areturn
  LineNumberTable: 
   line 12: 0

  LocalVariableTable: 
   Start  Length  Slot  Name   Signature
   0      6      0    this       Lscala/util/parsing/combinator/testing/RegexTest$;
   0      6      1    p       Lscala/Function0;


public scala.util.parsing.combinator.Parsers$Parser guard(scala.Function0);
  Code:
   Stack=2, Locals=2, Args_size=2
   0:	aload_0
   1:	aload_1
   2:	invokestatic	#191; //Method scala/util/parsing/combinator/Parsers$class.guard:(Lscala/util/parsing/combinator/Parsers;Lscala/Function0;)Lscala/util/parsing/combinator/Parsers$Parser;
   5:	areturn
  LineNumberTable: 
   line 12: 0

  LocalVariableTable: 
   Start  Length  Slot  Name   Signature
   0      6      0    this       Lscala/util/parsing/combinator/testing/RegexTest$;
   0      6      1    p       Lscala/Function0;


public scala.util.parsing.combinator.Parsers$Parser not(scala.Function0);
  Code:
   Stack=2, Locals=2, Args_size=2
   0:	aload_0
   1:	aload_1
   2:	invokestatic	#194; //Method scala/util/parsing/combinator/Parsers$class.not:(Lscala/util/parsing/combinator/Parsers;Lscala/Function0;)Lscala/util/parsing/combinator/Parsers$Parser;
   5:	areturn
  LineNumberTable: 
   line 12: 0

  LocalVariableTable: 
   Start  Length  Slot  Name   Signature
   0      6      0    this       Lscala/util/parsing/combinator/testing/RegexTest$;
   0      6      1    p       Lscala/Function0;


public scala.util.parsing.combinator.Parsers$Parser opt(scala.Function0);
  Code:
   Stack=2, Locals=2, Args_size=2
   0:	aload_0
   1:	aload_1
   2:	invokestatic	#197; //Method scala/util/parsing/combinator/Parsers$class.opt:(Lscala/util/parsing/combinator/Parsers;Lscala/Function0;)Lscala/util/parsing/combinator/Parsers$Parser;
   5:	areturn
  LineNumberTable: 
   line 12: 0

  LocalVariableTable: 
   Start  Length  Slot  Name   Signature
   0      6      0    this       Lscala/util/parsing/combinator/testing/RegexTest$;
   0      6      1    p       Lscala/Function0;


public scala.util.parsing.combinator.Parsers$Parser chainr1(scala.Function0, scala.Function0, scala.Function2, java.lang.Object);
  Code:
   Stack=5, Locals=5, Args_size=5
   0:	aload_0
   1:	aload_1
   2:	aload_2
   3:	aload_3
   4:	aload	4
   6:	invokestatic	#202; //Method scala/util/parsing/combinator/Parsers$class.chainr1:(Lscala/util/parsing/combinator/Parsers;Lscala/Function0;Lscala/Function0;Lscala/Function2;Ljava/lang/Object;)Lscala/util/parsing/combinator/Parsers$Parser;
   9:	areturn
  LineNumberTable: 
   line 12: 0

  LocalVariableTable: 
   Start  Length  Slot  Name   Signature
   0      10      0    this       Lscala/util/parsing/combinator/testing/RegexTest$;
   0      10      1    p       Lscala/Function0;
   0      10      2    q       Lscala/Function0;
   0      10      3    combine       Lscala/Function2;
   0      10      4    first       Ljava/lang/Object;


public scala.util.parsing.combinator.Parsers$Parser chainl1(scala.Function0, scala.Function0, scala.Function0);
  Code:
   Stack=4, Locals=4, Args_size=4
   0:	aload_0
   1:	aload_1
   2:	aload_2
   3:	aload_3
   4:	invokestatic	#212; //Method scala/util/parsing/combinator/Parsers$class.chainl1:(Lscala/util/parsing/combinator/Parsers;Lscala/Function0;Lscala/Function0;Lscala/Function0;)Lscala/util/parsing/combinator/Parsers$Parser;
   7:	areturn
  LineNumberTable: 
   line 12: 0

  LocalVariableTable: 
   Start  Length  Slot  Name   Signature
   0      8      0    this       Lscala/util/parsing/combinator/testing/RegexTest$;
   0      8      1    first       Lscala/Function0;
   0      8      2    p       Lscala/Function0;
   0      8      3    q       Lscala/Function0;


public scala.util.parsing.combinator.Parsers$Parser chainl1(scala.Function0, scala.Function0);
  Code:
   Stack=3, Locals=3, Args_size=3
   0:	aload_0
   1:	aload_1
   2:	aload_2
   3:	invokestatic	#216; //Method scala/util/parsing/combinator/Parsers$class.chainl1:(Lscala/util/parsing/combinator/Parsers;Lscala/Function0;Lscala/Function0;)Lscala/util/parsing/combinator/Parsers$Parser;
   6:	areturn
  LineNumberTable: 
   line 12: 0

  LocalVariableTable: 
   Start  Length  Slot  Name   Signature
   0      7      0    this       Lscala/util/parsing/combinator/testing/RegexTest$;
   0      7      1    p       Lscala/Function0;
   0      7      2    q       Lscala/Function0;


public scala.util.parsing.combinator.Parsers$Parser rep1sep(scala.Function0, scala.Function0);
  Code:
   Stack=3, Locals=3, Args_size=3
   0:	aload_0
   1:	aload_1
   2:	aload_2
   3:	invokestatic	#219; //Method scala/util/parsing/combinator/Parsers$class.rep1sep:(Lscala/util/parsing/combinator/Parsers;Lscala/Function0;Lscala/Function0;)Lscala/util/parsing/combinator/Parsers$Parser;
   6:	areturn
  LineNumberTable: 
   line 12: 0

  LocalVariableTable: 
   Start  Length  Slot  Name   Signature
   0      7      0    this       Lscala/util/parsing/combinator/testing/RegexTest$;
   0      7      1    p       Lscala/Function0;
   0      7      2    q       Lscala/Function0;


public scala.util.parsing.combinator.Parsers$Parser repN(int, scala.Function0);
  Code:
   Stack=3, Locals=3, Args_size=3
   0:	aload_0
   1:	iload_1
   2:	aload_2
   3:	invokestatic	#224; //Method scala/util/parsing/combinator/Parsers$class.repN:(Lscala/util/parsing/combinator/Parsers;ILscala/Function0;)Lscala/util/parsing/combinator/Parsers$Parser;
   6:	areturn
  LineNumberTable: 
   line 12: 0

  LocalVariableTable: 
   Start  Length  Slot  Name   Signature
   0      7      0    this       Lscala/util/parsing/combinator/testing/RegexTest$;
   0      7      1    n       I
   0      7      2    p       Lscala/Function0;


public scala.util.parsing.combinator.Parsers$Parser rep1(scala.Function0, scala.Function0);
  Code:
   Stack=3, Locals=3, Args_size=3
   0:	aload_0
   1:	aload_1
   2:	aload_2
   3:	invokestatic	#229; //Method scala/util/parsing/combinator/Parsers$class.rep1:(Lscala/util/parsing/combinator/Parsers;Lscala/Function0;Lscala/Function0;)Lscala/util/parsing/combinator/Parsers$Parser;
   6:	areturn
  LineNumberTable: 
   line 12: 0

  LocalVariableTable: 
   Start  Length  Slot  Name   Signature
   0      7      0    this       Lscala/util/parsing/combinator/testing/RegexTest$;
   0      7      1    first       Lscala/Function0;
   0      7      2    p       Lscala/Function0;


public scala.util.parsing.combinator.Parsers$Parser rep1(scala.Function0);
  Code:
   Stack=2, Locals=2, Args_size=2
   0:	aload_0
   1:	aload_1
   2:	invokestatic	#231; //Method scala/util/parsing/combinator/Parsers$class.rep1:(Lscala/util/parsing/combinator/Parsers;Lscala/Function0;)Lscala/util/parsing/combinator/Parsers$Parser;
   5:	areturn
  LineNumberTable: 
   line 12: 0

  LocalVariableTable: 
   Start  Length  Slot  Name   Signature
   0      6      0    this       Lscala/util/parsing/combinator/testing/RegexTest$;
   0      6      1    p       Lscala/Function0;


public scala.util.parsing.combinator.Parsers$Parser repsep(scala.Function0, scala.Function0);
  Code:
   Stack=3, Locals=3, Args_size=3
   0:	aload_0
   1:	aload_1
   2:	aload_2
   3:	invokestatic	#234; //Method scala/util/parsing/combinator/Parsers$class.repsep:(Lscala/util/parsing/combinator/Parsers;Lscala/Function0;Lscala/Function0;)Lscala/util/parsing/combinator/Parsers$Parser;
   6:	areturn
  LineNumberTable: 
   line 12: 0

  LocalVariableTable: 
   Start  Length  Slot  Name   Signature
   0      7      0    this       Lscala/util/parsing/combinator/testing/RegexTest$;
   0      7      1    p       Lscala/Function0;
   0      7      2    q       Lscala/Function0;


public scala.util.parsing.combinator.Parsers$Parser rep(scala.Function0);
  Code:
   Stack=2, Locals=2, Args_size=2
   0:	aload_0
   1:	aload_1
   2:	invokestatic	#237; //Method scala/util/parsing/combinator/Parsers$class.rep:(Lscala/util/parsing/combinator/Parsers;Lscala/Function0;)Lscala/util/parsing/combinator/Parsers$Parser;
   5:	areturn
  LineNumberTable: 
   line 12: 0

  LocalVariableTable: 
   Start  Length  Slot  Name   Signature
   0      6      0    this       Lscala/util/parsing/combinator/testing/RegexTest$;
   0      6      1    p       Lscala/Function0;


public scala.util.parsing.combinator.Parsers$Parser log(scala.Function0, java.lang.String);
  Code:
   Stack=3, Locals=3, Args_size=3
   0:	aload_0
   1:	aload_1
   2:	aload_2
   3:	invokestatic	#242; //Method scala/util/parsing/combinator/Parsers$class.log:(Lscala/util/parsing/combinator/Parsers;Lscala/Function0;Ljava/lang/String;)Lscala/util/parsing/combinator/Parsers$Parser;
   6:	areturn
  LineNumberTable: 
   line 12: 0

  LocalVariableTable: 
   Start  Length  Slot  Name   Signature
   0      7      0    this       Lscala/util/parsing/combinator/testing/RegexTest$;
   0      7      1    p       Lscala/Function0;
   0      7      2    name       Ljava/lang/String;


public scala.util.parsing.combinator.Parsers$Parser success(java.lang.Object);
  Code:
   Stack=2, Locals=2, Args_size=2
   0:	aload_0
   1:	aload_1
   2:	invokestatic	#248; //Method scala/util/parsing/combinator/Parsers$class.success:(Lscala/util/parsing/combinator/Parsers;Ljava/lang/Object;)Lscala/util/parsing/combinator/Parsers$Parser;
   5:	areturn
  LineNumberTable: 
   line 12: 0

  LocalVariableTable: 
   Start  Length  Slot  Name   Signature
   0      6      0    this       Lscala/util/parsing/combinator/testing/RegexTest$;
   0      6      1    v       Ljava/lang/Object;


public scala.util.parsing.combinator.Parsers$Parser err(java.lang.String);
  Code:
   Stack=2, Locals=2, Args_size=2
   0:	aload_0
   1:	aload_1
   2:	invokestatic	#254; //Method scala/util/parsing/combinator/Parsers$class.err:(Lscala/util/parsing/combinator/Parsers;Ljava/lang/String;)Lscala/util/parsing/combinator/Parsers$Parser;
   5:	areturn
  LineNumberTable: 
   line 12: 0

  LocalVariableTable: 
   Start  Length  Slot  Name   Signature
   0      6      0    this       Lscala/util/parsing/combinator/testing/RegexTest$;
   0      6      1    msg       Ljava/lang/String;


public scala.util.parsing.combinator.Parsers$Parser failure(java.lang.String);
  Code:
   Stack=2, Locals=2, Args_size=2
   0:	aload_0
   1:	aload_1
   2:	invokestatic	#258; //Method scala/util/parsing/combinator/Parsers$class.failure:(Lscala/util/parsing/combinator/Parsers;Ljava/lang/String;)Lscala/util/parsing/combinator/Parsers$Parser;
   5:	areturn
  LineNumberTable: 
   line 12: 0

  LocalVariableTable: 
   Start  Length  Slot  Name   Signature
   0      6      0    this       Lscala/util/parsing/combinator/testing/RegexTest$;
   0      6      1    msg       Ljava/lang/String;


public scala.util.parsing.combinator.Parsers$Parser acceptSeq(java.lang.Object, scala.Function1);
  Code:
   Stack=3, Locals=3, Args_size=3
   0:	aload_0
   1:	aload_1
   2:	aload_2
   3:	invokestatic	#263; //Method scala/util/parsing/combinator/Parsers$class.acceptSeq:(Lscala/util/parsing/combinator/Parsers;Ljava/lang/Object;Lscala/Function1;)Lscala/util/parsing/combinator/Parsers$Parser;
   6:	areturn
  LineNumberTable: 
   line 12: 0

  LocalVariableTable: 
   Start  Length  Slot  Name   Signature
   0      7      0    this       Lscala/util/parsing/combinator/testing/RegexTest$;
   0      7      1    es       Ljava/lang/Object;
   0      7      2    view$2       Lscala/Function1;


public scala.util.parsing.combinator.Parsers$Parser acceptMatch(java.lang.String, scala.PartialFunction);
  Code:
   Stack=3, Locals=3, Args_size=3
   0:	aload_0
   1:	aload_1
   2:	aload_2
   3:	invokestatic	#271; //Method scala/util/parsing/combinator/Parsers$class.acceptMatch:(Lscala/util/parsing/combinator/Parsers;Ljava/lang/String;Lscala/PartialFunction;)Lscala/util/parsing/combinator/Parsers$Parser;
   6:	areturn
  LineNumberTable: 
   line 12: 0

  LocalVariableTable: 
   Start  Length  Slot  Name   Signature
   0      7      0    this       Lscala/util/parsing/combinator/testing/RegexTest$;
   0      7      1    expected       Ljava/lang/String;
   0      7      2    f       Lscala/PartialFunction;


public scala.util.parsing.combinator.Parsers$Parser acceptIf(scala.Function1, scala.Function1);
  Code:
   Stack=3, Locals=3, Args_size=3
   0:	aload_0
   1:	aload_1
   2:	aload_2
   3:	invokestatic	#279; //Method scala/util/parsing/combinator/Parsers$class.acceptIf:(Lscala/util/parsing/combinator/Parsers;Lscala/Function1;Lscala/Function1;)Lscala/util/parsing/combinator/Parsers$Parser;
   6:	areturn
  LineNumberTable: 
   line 12: 0

  LocalVariableTable: 
   Start  Length  Slot  Name   Signature
   0      7      0    this       Lscala/util/parsing/combinator/testing/RegexTest$;
   0      7      1    p       Lscala/Function1;
   0      7      2    err       Lscala/Function1;


public scala.util.parsing.combinator.Parsers$Parser accept(java.lang.String, scala.PartialFunction);
  Code:
   Stack=3, Locals=3, Args_size=3
   0:	aload_0
   1:	aload_1
   2:	aload_2
   3:	invokestatic	#282; //Method scala/util/parsing/combinator/Parsers$class.accept:(Lscala/util/parsing/combinator/Parsers;Ljava/lang/String;Lscala/PartialFunction;)Lscala/util/parsing/combinator/Parsers$Parser;
   6:	areturn
  LineNumberTable: 
   line 12: 0

  LocalVariableTable: 
   Start  Length  Slot  Name   Signature
   0      7      0    this       Lscala/util/parsing/combinator/testing/RegexTest$;
   0      7      1    expected       Ljava/lang/String;
   0      7      2    f       Lscala/PartialFunction;


public scala.util.parsing.combinator.Parsers$Parser accept(java.lang.Object, scala.Function1);
  Code:
   Stack=3, Locals=3, Args_size=3
   0:	aload_0
   1:	aload_1
   2:	aload_2
   3:	invokestatic	#284; //Method scala/util/parsing/combinator/Parsers$class.accept:(Lscala/util/parsing/combinator/Parsers;Ljava/lang/Object;Lscala/Function1;)Lscala/util/parsing/combinator/Parsers$Parser;
   6:	areturn
  LineNumberTable: 
   line 12: 0

  LocalVariableTable: 
   Start  Length  Slot  Name   Signature
   0      7      0    this       Lscala/util/parsing/combinator/testing/RegexTest$;
   0      7      1    es       Ljava/lang/Object;
   0      7      2    view$1       Lscala/Function1;


public scala.util.parsing.combinator.Parsers$Parser accept(java.lang.Object);
  Code:
   Stack=2, Locals=2, Args_size=2
   0:	aload_0
   1:	aload_1
   2:	invokestatic	#287; //Method scala/util/parsing/combinator/Parsers$class.accept:(Lscala/util/parsing/combinator/Parsers;Ljava/lang/Object;)Lscala/util/parsing/combinator/Parsers$Parser;
   5:	areturn
  LineNumberTable: 
   line 12: 0

  LocalVariableTable: 
   Start  Length  Slot  Name   Signature
   0      6      0    this       Lscala/util/parsing/combinator/testing/RegexTest$;
   0      6      1    e       Ljava/lang/Object;


public scala.util.parsing.combinator.Parsers$Parser elem(java.lang.Object);
  Code:
   Stack=2, Locals=2, Args_size=2
   0:	aload_0
   1:	aload_1
   2:	invokestatic	#291; //Method scala/util/parsing/combinator/Parsers$class.elem:(Lscala/util/parsing/combinator/Parsers;Ljava/lang/Object;)Lscala/util/parsing/combinator/Parsers$Parser;
   5:	areturn
  LineNumberTable: 
   line 12: 0

  LocalVariableTable: 
   Start  Length  Slot  Name   Signature
   0      6      0    this       Lscala/util/parsing/combinator/testing/RegexTest$;
   0      6      1    e       Ljava/lang/Object;


public scala.util.parsing.combinator.Parsers$Parser elem(java.lang.String, scala.Function1);
  Code:
   Stack=3, Locals=3, Args_size=3
   0:	aload_0
   1:	aload_1
   2:	aload_2
   3:	invokestatic	#295; //Method scala/util/parsing/combinator/Parsers$class.elem:(Lscala/util/parsing/combinator/Parsers;Ljava/lang/String;Lscala/Function1;)Lscala/util/parsing/combinator/Parsers$Parser;
   6:	areturn
  LineNumberTable: 
   line 12: 0

  LocalVariableTable: 
   Start  Length  Slot  Name   Signature
   0      7      0    this       Lscala/util/parsing/combinator/testing/RegexTest$;
   0      7      1    kind       Ljava/lang/String;
   0      7      2    p       Lscala/Function1;


public scala.util.parsing.combinator.Parsers$Parser commit(scala.Function0);
  Code:
   Stack=2, Locals=2, Args_size=2
   0:	aload_0
   1:	aload_1
   2:	invokestatic	#299; //Method scala/util/parsing/combinator/Parsers$class.commit:(Lscala/util/parsing/combinator/Parsers;Lscala/Function0;)Lscala/util/parsing/combinator/Parsers$Parser;
   5:	areturn
  LineNumberTable: 
   line 12: 0

  LocalVariableTable: 
   Start  Length  Slot  Name   Signature
   0      6      0    this       Lscala/util/parsing/combinator/testing/RegexTest$;
   0      6      1    p       Lscala/Function0;


public scala.util.parsing.combinator.Parsers$Parser OnceParser(scala.Function1);
  Code:
   Stack=2, Locals=2, Args_size=2
   0:	aload_0
   1:	aload_1
   2:	invokestatic	#303; //Method scala/util/parsing/combinator/Parsers$class.OnceParser:(Lscala/util/parsing/combinator/Parsers;Lscala/Function1;)Lscala/util/parsing/combinator/Parsers$Parser;
   5:	areturn
  LineNumberTable: 
   line 12: 0

  LocalVariableTable: 
   Start  Length  Slot  Name   Signature
   0      6      0    this       Lscala/util/parsing/combinator/testing/RegexTest$;
   0      6      1    f       Lscala/Function1;


public scala.util.parsing.combinator.Parsers$Parser Parser(scala.Function1);
  Code:
   Stack=2, Locals=2, Args_size=2
   0:	aload_0
   1:	aload_1
   2:	invokestatic	#306; //Method scala/util/parsing/combinator/Parsers$class.Parser:(Lscala/util/parsing/combinator/Parsers;Lscala/Function1;)Lscala/util/parsing/combinator/Parsers$Parser;
   5:	areturn
  LineNumberTable: 
   line 12: 0

  LocalVariableTable: 
   Start  Length  Slot  Name   Signature
   0      6      0    this       Lscala/util/parsing/combinator/testing/RegexTest$;
   0      6      1    f       Lscala/Function1;


public final scala.util.parsing.combinator.Parsers$$tilde$ $tilde();
  Code:
   Stack=4, Locals=1, Args_size=1
   0:	aload_0
   1:	getfield	#310; //Field $tilde$module:Lscala/util/parsing/combinator/Parsers$$tilde$;
   4:	ifnonnull	19
   7:	aload_0
   8:	new	#312; //class scala/util/parsing/combinator/Parsers$$tilde$
   11:	dup
   12:	aload_0
   13:	invokespecial	#314; //Method scala/util/parsing/combinator/Parsers$$tilde$."<init>":(Lscala/util/parsing/combinator/Parsers;)V
   16:	putfield	#310; //Field $tilde$module:Lscala/util/parsing/combinator/Parsers$$tilde$;
   19:	aload_0
   20:	getfield	#310; //Field $tilde$module:Lscala/util/parsing/combinator/Parsers$$tilde$;
   23:	areturn
  LineNumberTable: 
   line 12: 0


public final scala.util.parsing.combinator.Parsers$Error$ Error();
  Code:
   Stack=4, Locals=1, Args_size=1
   0:	aload_0
   1:	getfield	#318; //Field Error$module:Lscala/util/parsing/combinator/Parsers$Error$;
   4:	ifnonnull	19
   7:	aload_0
   8:	new	#320; //class scala/util/parsing/combinator/Parsers$Error$
   11:	dup
   12:	aload_0
   13:	invokespecial	#321; //Method scala/util/parsing/combinator/Parsers$Error$."<init>":(Lscala/util/parsing/combinator/Parsers;)V
   16:	putfield	#318; //Field Error$module:Lscala/util/parsing/combinator/Parsers$Error$;
   19:	aload_0
   20:	getfield	#318; //Field Error$module:Lscala/util/parsing/combinator/Parsers$Error$;
   23:	areturn
  LineNumberTable: 
   line 12: 0


public final scala.util.parsing.combinator.Parsers$Failure$ Failure();
  Code:
   Stack=4, Locals=1, Args_size=1
   0:	aload_0
   1:	getfield	#325; //Field Failure$module:Lscala/util/parsing/combinator/Parsers$Failure$;
   4:	ifnonnull	19
   7:	aload_0
   8:	new	#327; //class scala/util/parsing/combinator/Parsers$Failure$
   11:	dup
   12:	aload_0
   13:	invokespecial	#328; //Method scala/util/parsing/combinator/Parsers$Failure$."<init>":(Lscala/util/parsing/combinator/Parsers;)V
   16:	putfield	#325; //Field Failure$module:Lscala/util/parsing/combinator/Parsers$Failure$;
   19:	aload_0
   20:	getfield	#325; //Field Failure$module:Lscala/util/parsing/combinator/Parsers$Failure$;
   23:	areturn
  LineNumberTable: 
   line 12: 0


public final scala.util.parsing.combinator.Parsers$NoSuccess$ NoSuccess();
  Code:
   Stack=4, Locals=1, Args_size=1
   0:	aload_0
   1:	getfield	#332; //Field NoSuccess$module:Lscala/util/parsing/combinator/Parsers$NoSuccess$;
   4:	ifnonnull	19
   7:	aload_0
   8:	new	#334; //class scala/util/parsing/combinator/Parsers$NoSuccess$
   11:	dup
   12:	aload_0
   13:	invokespecial	#335; //Method scala/util/parsing/combinator/Parsers$NoSuccess$."<init>":(Lscala/util/parsing/combinator/Parsers;)V
   16:	putfield	#332; //Field NoSuccess$module:Lscala/util/parsing/combinator/Parsers$NoSuccess$;
   19:	aload_0
   20:	getfield	#332; //Field NoSuccess$module:Lscala/util/parsing/combinator/Parsers$NoSuccess$;
   23:	areturn
  LineNumberTable: 
   line 12: 0


public void lastNoSuccess_$eq(scala.util.parsing.combinator.Parsers$NoSuccess);
  Code:
   Stack=2, Locals=2, Args_size=2
   0:	aload_0
   1:	aload_1
   2:	putfield	#339; //Field lastNoSuccess:Lscala/util/parsing/combinator/Parsers$NoSuccess;
   5:	return
  LineNumberTable: 
   line 12: 0


public scala.util.parsing.combinator.Parsers$NoSuccess lastNoSuccess();
  Code:
   Stack=1, Locals=1, Args_size=1
   0:	aload_0
   1:	getfield	#339; //Field lastNoSuccess:Lscala/util/parsing/combinator/Parsers$NoSuccess;
   4:	areturn
  LineNumberTable: 
   line 12: 0


public final scala.util.parsing.combinator.Parsers$Success$ Success();
  Code:
   Stack=4, Locals=1, Args_size=1
   0:	aload_0
   1:	getfield	#344; //Field Success$module:Lscala/util/parsing/combinator/Parsers$Success$;
   4:	ifnonnull	19
   7:	aload_0
   8:	new	#346; //class scala/util/parsing/combinator/Parsers$Success$
   11:	dup
   12:	aload_0
   13:	invokespecial	#347; //Method scala/util/parsing/combinator/Parsers$Success$."<init>":(Lscala/util/parsing/combinator/Parsers;)V
   16:	putfield	#344; //Field Success$module:Lscala/util/parsing/combinator/Parsers$Success$;
   19:	aload_0
   20:	getfield	#344; //Field Success$module:Lscala/util/parsing/combinator/Parsers$Success$;
   23:	areturn
  LineNumberTable: 
   line 12: 0


public scala.util.parsing.combinator.Parsers$ParseResult parseAll(scala.util.parsing.combinator.Parsers$Parser, java.lang.CharSequence);
  Code:
   Stack=3, Locals=3, Args_size=3
   0:	aload_0
   1:	aload_1
   2:	aload_2
   3:	invokestatic	#352; //Method scala/util/parsing/combinator/RegexParsers$class.parseAll:(Lscala/util/parsing/combinator/RegexParsers;Lscala/util/parsing/combinator/Parsers$Parser;Ljava/lang/CharSequence;)Lscala/util/parsing/combinator/Parsers$ParseResult;
   6:	areturn
  LineNumberTable: 
   line 12: 0

  LocalVariableTable: 
   Start  Length  Slot  Name   Signature
   0      7      0    this       Lscala/util/parsing/combinator/testing/RegexTest$;
   0      7      1    p       Lscala/util/parsing/combinator/Parsers$Parser;
   0      7      2    in       Ljava/lang/CharSequence;


public scala.util.parsing.combinator.Parsers$ParseResult parseAll(scala.util.parsing.combinator.Parsers$Parser, java.io.Reader);
  Code:
   Stack=3, Locals=3, Args_size=3
   0:	aload_0
   1:	aload_1
   2:	aload_2
   3:	invokestatic	#357; //Method scala/util/parsing/combinator/RegexParsers$class.parseAll:(Lscala/util/parsing/combinator/RegexParsers;Lscala/util/parsing/combinator/Parsers$Parser;Ljava/io/Reader;)Lscala/util/parsing/combinator/Parsers$ParseResult;
   6:	areturn
  LineNumberTable: 
   line 12: 0

  LocalVariableTable: 
   Start  Length  Slot  Name   Signature
   0      7      0    this       Lscala/util/parsing/combinator/testing/RegexTest$;
   0      7      1    p       Lscala/util/parsing/combinator/Parsers$Parser;
   0      7      2    in       Ljava/io/Reader;


public scala.util.parsing.combinator.Parsers$ParseResult parseAll(scala.util.parsing.combinator.Parsers$Parser, scala.util.parsing.input.Reader);
  Code:
   Stack=3, Locals=3, Args_size=3
   0:	aload_0
   1:	aload_1
   2:	aload_2
   3:	invokestatic	#362; //Method scala/util/parsing/combinator/RegexParsers$class.parseAll:(Lscala/util/parsing/combinator/RegexParsers;Lscala/util/parsing/combinator/Parsers$Parser;Lscala/util/parsing/input/Reader;)Lscala/util/parsing/combinator/Parsers$ParseResult;
   6:	areturn
  LineNumberTable: 
   line 12: 0

  LocalVariableTable: 
   Start  Length  Slot  Name   Signature
   0      7      0    this       Lscala/util/parsing/combinator/testing/RegexTest$;
   0      7      1    p       Lscala/util/parsing/combinator/Parsers$Parser;
   0      7      2    in       Lscala/util/parsing/input/Reader;


public scala.util.parsing.combinator.Parsers$ParseResult parse(scala.util.parsing.combinator.Parsers$Parser, java.io.Reader);
  Code:
   Stack=3, Locals=3, Args_size=3
   0:	aload_0
   1:	aload_1
   2:	aload_2
   3:	invokestatic	#366; //Method scala/util/parsing/combinator/RegexParsers$class.parse:(Lscala/util/parsing/combinator/RegexParsers;Lscala/util/parsing/combinator/Parsers$Parser;Ljava/io/Reader;)Lscala/util/parsing/combinator/Parsers$ParseResult;
   6:	areturn
  LineNumberTable: 
   line 12: 0

  LocalVariableTable: 
   Start  Length  Slot  Name   Signature
   0      7      0    this       Lscala/util/parsing/combinator/testing/RegexTest$;
   0      7      1    p       Lscala/util/parsing/combinator/Parsers$Parser;
   0      7      2    in       Ljava/io/Reader;


public scala.util.parsing.combinator.Parsers$ParseResult parse(scala.util.parsing.combinator.Parsers$Parser, java.lang.CharSequence);
  Code:
   Stack=3, Locals=3, Args_size=3
   0:	aload_0
   1:	aload_1
   2:	aload_2
   3:	invokestatic	#368; //Method scala/util/parsing/combinator/RegexParsers$class.parse:(Lscala/util/parsing/combinator/RegexParsers;Lscala/util/parsing/combinator/Parsers$Parser;Ljava/lang/CharSequence;)Lscala/util/parsing/combinator/Parsers$ParseResult;
   6:	areturn
  LineNumberTable: 
   line 12: 0

  LocalVariableTable: 
   Start  Length  Slot  Name   Signature
   0      7      0    this       Lscala/util/parsing/combinator/testing/RegexTest$;
   0      7      1    p       Lscala/util/parsing/combinator/Parsers$Parser;
   0      7      2    in       Ljava/lang/CharSequence;


public scala.util.parsing.combinator.Parsers$ParseResult parse(scala.util.parsing.combinator.Parsers$Parser, scala.util.parsing.input.Reader);
  Code:
   Stack=3, Locals=3, Args_size=3
   0:	aload_0
   1:	aload_1
   2:	aload_2
   3:	invokestatic	#370; //Method scala/util/parsing/combinator/RegexParsers$class.parse:(Lscala/util/parsing/combinator/RegexParsers;Lscala/util/parsing/combinator/Parsers$Parser;Lscala/util/parsing/input/Reader;)Lscala/util/parsing/combinator/Parsers$ParseResult;
   6:	areturn
  LineNumberTable: 
   line 12: 0

  LocalVariableTable: 
   Start  Length  Slot  Name   Signature
   0      7      0    this       Lscala/util/parsing/combinator/testing/RegexTest$;
   0      7      1    p       Lscala/util/parsing/combinator/Parsers$Parser;
   0      7      2    in       Lscala/util/parsing/input/Reader;


public scala.util.parsing.combinator.Parsers$Parser phrase(scala.util.parsing.combinator.Parsers$Parser);
  Code:
   Stack=2, Locals=2, Args_size=2
   0:	aload_0
   1:	aload_1
   2:	invokestatic	#373; //Method scala/util/parsing/combinator/RegexParsers$class.phrase:(Lscala/util/parsing/combinator/RegexParsers;Lscala/util/parsing/combinator/Parsers$Parser;)Lscala/util/parsing/combinator/Parsers$Parser;
   5:	areturn
  LineNumberTable: 
   line 12: 0

  LocalVariableTable: 
   Start  Length  Slot  Name   Signature
   0      6      0    this       Lscala/util/parsing/combinator/testing/RegexTest$;
   0      6      1    p       Lscala/util/parsing/combinator/Parsers$Parser;


public scala.util.parsing.combinator.Parsers$Parser regex(scala.util.matching.Regex);
  Code:
   Stack=2, Locals=2, Args_size=2
   0:	aload_0
   1:	aload_1
   2:	invokestatic	#376; //Method scala/util/parsing/combinator/RegexParsers$class.regex:(Lscala/util/parsing/combinator/RegexParsers;Lscala/util/matching/Regex;)Lscala/util/parsing/combinator/Parsers$Parser;
   5:	areturn
  LineNumberTable: 
   line 12: 0

  LocalVariableTable: 
   Start  Length  Slot  Name   Signature
   0      6      0    this       Lscala/util/parsing/combinator/testing/RegexTest$;
   0      6      1    r       Lscala/util/matching/Regex;


public scala.util.parsing.combinator.Parsers$Parser literal(java.lang.String);
  Code:
   Stack=2, Locals=2, Args_size=2
   0:	aload_0
   1:	aload_1
   2:	invokestatic	#380; //Method scala/util/parsing/combinator/RegexParsers$class.literal:(Lscala/util/parsing/combinator/RegexParsers;Ljava/lang/String;)Lscala/util/parsing/combinator/Parsers$Parser;
   5:	areturn
  LineNumberTable: 
   line 12: 0

  LocalVariableTable: 
   Start  Length  Slot  Name   Signature
   0      6      0    this       Lscala/util/parsing/combinator/testing/RegexTest$;
   0      6      1    s       Ljava/lang/String;


public int handleWhiteSpace(java.lang.CharSequence, int);
  Code:
   Stack=3, Locals=3, Args_size=3
   0:	aload_0
   1:	aload_1
   2:	iload_2
   3:	invokestatic	#386; //Method scala/util/parsing/combinator/RegexParsers$class.handleWhiteSpace:(Lscala/util/parsing/combinator/RegexParsers;Ljava/lang/CharSequence;I)I
   6:	ireturn
  LineNumberTable: 
   line 12: 0

  LocalVariableTable: 
   Start  Length  Slot  Name   Signature
   0      7      0    this       Lscala/util/parsing/combinator/testing/RegexTest$;
   0      7      1    source       Ljava/lang/CharSequence;
   0      7      2    offset       I


public boolean skipWhitespace();
  Code:
   Stack=1, Locals=1, Args_size=1
   0:	aload_0
   1:	invokestatic	#393; //Method scala/util/parsing/combinator/RegexParsers$class.skipWhitespace:(Lscala/util/parsing/combinator/RegexParsers;)Z
   4:	ireturn
  LineNumberTable: 
   line 12: 0


public void scala$util$parsing$combinator$RegexParsers$_setter_$whiteSpace_$eq(scala.util.matching.Regex);
  Code:
   Stack=2, Locals=2, Args_size=2
   0:	aload_0
   1:	aload_1
   2:	putfield	#397; //Field whiteSpace:Lscala/util/matching/Regex;
   5:	return
  LineNumberTable: 
   line 12: 0


public final scala.util.parsing.combinator.Parsers$Parser scala$util$parsing$combinator$RegexParsers$$super$phrase(scala.util.parsing.combinator.Parsers$Parser);
  Code:
   Stack=2, Locals=2, Args_size=2
   0:	aload_0
   1:	aload_1
   2:	invokestatic	#401; //Method scala/util/parsing/combinator/Parsers$class.phrase:(Lscala/util/parsing/combinator/Parsers;Lscala/util/parsing/combinator/Parsers$Parser;)Lscala/util/parsing/combinator/Parsers$Parser;
   5:	areturn
  LineNumberTable: 
   line 12: 0

  LocalVariableTable: 
   Start  Length  Slot  Name   Signature
   0      6      0    this       Lscala/util/parsing/combinator/testing/RegexTest$;
   0      6      1    p       Lscala/util/parsing/combinator/Parsers$Parser;


public scala.util.matching.Regex whiteSpace();
  Code:
   Stack=1, Locals=1, Args_size=1
   0:	aload_0
   1:	getfield	#397; //Field whiteSpace:Lscala/util/matching/Regex;
   4:	areturn
  LineNumberTable: 
   line 12: 0


}

