Compiled from "RegexTest.scala"
public class scala.util.parsing.combinator.testing.Str extends java.lang.Object implements scala.ScalaObject,scala.Product,java.io.Serializable
  SourceFile: "RegexTest.scala"
  ScalaSig: length = 0x3
   05 00 00 
  RuntimeVisibleAnnotations: length = 0xB
   00 01 00 71 00 01 00 72 73 00 73 
  minor version: 0
  major version: 49
  Constant pool:
Asciz	SourceFile;
Asciz	RegexTest.scala;
Asciz	andThen;
Asciz	(Lscala/Function1;)Lscala/Function1;;
Asciz	Code;
Asciz	scala/util/parsing/combinator/testing/Str$;
class	scala/util/parsing/combinator/testing/Str$
Asciz	MODULE$;
Asciz	Lscala/util/parsing/combinator/testing/Str$;;
NameAndType	MODULE$:Lscala/util/parsing/combinator/testing/Str$;
Field	scala/util/parsing/combinator/testing/Str$.MODULE$:Lscala/util/parsing/combinator/testing/Str$;
NameAndType	andThen:(Lscala/Function1;)Lscala/Function1;
Method	scala/util/parsing/combinator/testing/Str$.andThen:(Lscala/Function1;)Lscala/Function1;
Asciz	compose;
NameAndType	compose:(Lscala/Function1;)Lscala/Function1;
Method	scala/util/parsing/combinator/testing/Str$.compose:(Lscala/Function1;)Lscala/Function1;
Asciz	s;
Asciz	Ljava/lang/String;;
Asciz	productElementName;
Asciz	(I)Ljava/lang/String;;
Asciz	LineNumberTable;
Asciz	scala/Product$class;
class	scala/Product$class
Asciz	(Lscala/Product;I)Ljava/lang/String;;
NameAndType	productElementName:(Lscala/Product;I)Ljava/lang/String;
Method	scala/Product$class.productElementName:(Lscala/Product;I)Ljava/lang/String;
Asciz	this;
Asciz	Lscala/util/parsing/combinator/testing/Str;;
Asciz	n;
Asciz	I;
Asciz	LocalVariableTable;
Asciz	productIterator;
Asciz	()Lscala/collection/Iterator;;
Asciz	(Lscala/Product;)Lscala/collection/Iterator;;
NameAndType	productIterator:(Lscala/Product;)Lscala/collection/Iterator;
Method	scala/Product$class.productIterator:(Lscala/Product;)Lscala/collection/Iterator;
Asciz	productElements;
NameAndType	productElements:(Lscala/Product;)Lscala/collection/Iterator;
Method	scala/Product$class.productElements:(Lscala/Product;)Lscala/collection/Iterator;
Asciz	Deprecated;
Asciz	copy$default$1;
Asciz	()Ljava/lang/String;;
Asciz	scala/util/parsing/combinator/testing/Str;
class	scala/util/parsing/combinator/testing/Str
NameAndType	s:()Ljava/lang/String;
Method	scala/util/parsing/combinator/testing/Str.s:()Ljava/lang/String;
NameAndType	s:Ljava/lang/String;
Field	scala/util/parsing/combinator/testing/Str.s:Ljava/lang/String;
Asciz	copy;
Asciz	(Ljava/lang/String;)Lscala/util/parsing/combinator/testing/Str;;
Asciz	<init>;
Asciz	(Ljava/lang/String;)V;
NameAndType	"<init>":(Ljava/lang/String;)V
Method	scala/util/parsing/combinator/testing/Str."<init>":(Ljava/lang/String;)V
Asciz	hashCode;
Asciz	()I;
Asciz	scala/runtime/ScalaRunTime$;
class	scala/runtime/ScalaRunTime$
Asciz	Lscala/runtime/ScalaRunTime$;;
NameAndType	MODULE$:Lscala/runtime/ScalaRunTime$;
Field	scala/runtime/ScalaRunTime$.MODULE$:Lscala/runtime/ScalaRunTime$;
Asciz	_hashCode;
Asciz	(Lscala/Product;)I;
NameAndType	_hashCode:(Lscala/Product;)I
Method	scala/runtime/ScalaRunTime$._hashCode:(Lscala/Product;)I
Asciz	toString;
Asciz	_toString;
Asciz	(Lscala/Product;)Ljava/lang/String;;
NameAndType	_toString:(Lscala/Product;)Ljava/lang/String;
Method	scala/runtime/ScalaRunTime$._toString:(Lscala/Product;)Ljava/lang/String;
Asciz	equals;
Asciz	(Ljava/lang/Object;)Z;
Asciz	gd3$1;
Asciz	(Ljava/lang/String;)Z;
NameAndType	gd3$1:(Ljava/lang/String;)Z
Method	scala/util/parsing/combinator/testing/Str.gd3$1:(Ljava/lang/String;)Z
Asciz	scala/Equals;
class	scala/Equals
Asciz	canEqual;
NameAndType	canEqual:(Ljava/lang/Object;)Z
InterfaceMethod	scala/Equals.canEqual:(Ljava/lang/Object;)Z
Asciz	temp10;
Asciz	temp11;
Asciz	productPrefix;
Asciz	Str;
String	Str
Asciz	productArity;
Asciz	productElement;
Asciz	(I)Ljava/lang/Object;;
Asciz	java/lang/IndexOutOfBoundsException;
class	java/lang/IndexOutOfBoundsException
Asciz	scala/runtime/BoxesRunTime;
class	scala/runtime/BoxesRunTime
Asciz	boxToInteger;
Asciz	(I)Ljava/lang/Integer;;
NameAndType	boxToInteger:(I)Ljava/lang/Integer;
Method	scala/runtime/BoxesRunTime.boxToInteger:(I)Ljava/lang/Integer;
Asciz	java/lang/Object;
class	java/lang/Object
NameAndType	toString:()Ljava/lang/String;
Method	java/lang/Object.toString:()Ljava/lang/String;
Method	java/lang/IndexOutOfBoundsException."<init>":(Ljava/lang/String;)V
NameAndType	equals:(Ljava/lang/Object;)Z
Method	java/lang/Object.equals:(Ljava/lang/Object;)Z
Asciz	()V;
NameAndType	"<init>":()V
Method	java/lang/Object."<init>":()V
Asciz	$init$;
Asciz	(Lscala/Product;)V;
NameAndType	$init$:(Lscala/Product;)V
Method	scala/Product$class.$init$:(Lscala/Product;)V
Asciz	ScalaSig;
Asciz	Lscala/reflect/ScalaSignature;;
Asciz	bytes;
Asciz	\raC\t\tQM#(O\t9A/Z:uS:<'BA)w.2j]$xN!\tq]1sg&twM\n!Q^5mY!B:dC27A\n91\")5\tC%!A.8h6bmL!!\t\r='.Z2u!\t9$D\tI\"BATGdm2kK$CA\ta\"BAQe>$Wo;\ty!Q3A}\ta]AA\n/\tJ!a\t\rAX\rZ3g\t)cETiJLgnG)AIIgBQA-\naP5oSRtDC/!\ti!Dq1!!!AE\nAaY8qsRAF\r==\n1!!!%AU\nabY8qs\"WMZ1vYR$'F7U\tsgK9!\tId(D;\tYD(Av]DWmY6fI*QHCC:tw^1uS>tBA ;E)hn5fG.,GMV1sSt7-\t!\t!C!A.Y:i>$W\rFD!\t9B)F\tJ;\tA!AB!^8TiJLgnA!A!\nC3*fcVGn>\"aF'\n9S!a\"p_2,M!&\t1R\rAH%\r\t/IK!asV\t\"W5(o3vGR&/4jqV\tq1&Q\t5!\t!C!7aO]8ek$I]5usV\t1\t^\t\"_9(o3vGR,E.Z7f]R$\"!U0\tAc!a\"A\rC#-dC:,/^1m)\ta5\rCQA\tA)))CAg\t9'BtKJL\r\5{C\ndWmBj\tR6M#(.WAAC#AnEl[ZBA\9!Y5\tqNq9!/8uS6,B:pE\t%m;sC$h)8di&|g.\rU-$\tU\"9ao[A\n;!B1qa2LHCyqR1!Q8.!Anq!8baBd}Bq# \nyT!AB(qi&|ge\rLq;
Asciz	RuntimeVisibleAnnotations;
Asciz	scala/ScalaObject;
class	scala/ScalaObject
Asciz	scala/Product;
class	scala/Product
Asciz	java/io/Serializable;
class	java/io/Serializable

{
private final java.lang.String s;
  Signature: Ljava/lang/String;

public static final scala.Function1 andThen(scala.Function1);
  Signature: (Lscala/Function1;)Lscala/Function1;
  Code:
   Stack=2, Locals=1, Args_size=1
	getstatic	Field scala/util/parsing/combinator/testing/Str$.MODULE$:Lscala/util/parsing/combinator/testing/Str$;
	aload_0
	invokevirtual	Method scala/util/parsing/combinator/testing/Str$.andThen:(Lscala/Function1;)Lscala/Function1;
	areturn
  Labels:

public static final scala.Function1 compose(scala.Function1);
  Signature: (Lscala/Function1;)Lscala/Function1;
  Code:
   Stack=2, Locals=1, Args_size=1
	getstatic	Field scala/util/parsing/combinator/testing/Str$.MODULE$:Lscala/util/parsing/combinator/testing/Str$;
	aload_0
	invokevirtual	Method scala/util/parsing/combinator/testing/Str$.compose:(Lscala/Function1;)Lscala/Function1;
	areturn
  Labels:

public java.lang.String productElementName(int);
  Signature: (I)Ljava/lang/String;
  Code:
   Stack=2, Locals=2, Args_size=2
	aload_0
	iload_1
	invokestatic	Method scala/Product$class.productElementName:(Lscala/Product;I)Ljava/lang/String;
	areturn
  Labels:
  LocalVariableTable: 
   Start  Length  Slot  Name   Signature
   0      6      0    this       Lscala/util/parsing/combinator/testing/Str;
   0      6      1    n       I


public scala.collection.Iterator productIterator();
  Signature: ()Lscala/collection/Iterator;
  Code:
   Stack=1, Locals=1, Args_size=1
	aload_0
	invokestatic	Method scala/Product$class.productIterator:(Lscala/Product;)Lscala/collection/Iterator;
	areturn
  Labels:

public scala.collection.Iterator productElements();
  Signature: ()Lscala/collection/Iterator;
  Code:
   Stack=1, Locals=1, Args_size=1
	aload_0
	invokestatic	Method scala/Product$class.productElements:(Lscala/Product;)Lscala/collection/Iterator;
	areturn
  Labels:
  Deprecated: true

public java.lang.String copy$default$1();
  Signature: ()Ljava/lang/String;
  Code:
   Stack=1, Locals=1, Args_size=1
	aload_0
	invokevirtual	Method s:()Ljava/lang/String;
	areturn
  Labels:

public java.lang.String s();
  Signature: ()Ljava/lang/String;
  Code:
   Stack=1, Locals=1, Args_size=1
	aload_0
	getfield	Field s:Ljava/lang/String;
	areturn
  Labels:

public scala.util.parsing.combinator.testing.Str copy(java.lang.String);
  Signature: (Ljava/lang/String;)Lscala/util/parsing/combinator/testing/Str;
  Code:
   Stack=3, Locals=2, Args_size=2
	new	class scala/util/parsing/combinator/testing/Str
	dup
	aload_1
	invokespecial	Method "<init>":(Ljava/lang/String;)V
	areturn
  Labels:
  LocalVariableTable: 
   Start  Length  Slot  Name   Signature
   0      9      0    this       Lscala/util/parsing/combinator/testing/Str;
   0      9      1    s       Ljava/lang/String;


public int hashCode();
  Signature: ()I
  Code:
   Stack=2, Locals=1, Args_size=1
	getstatic	Field scala/runtime/ScalaRunTime$.MODULE$:Lscala/runtime/ScalaRunTime$;
	aload_0
	invokevirtual	Method scala/runtime/ScalaRunTime$._hashCode:(Lscala/Product;)I
	ireturn
  Labels:

public java.lang.String toString();
  Signature: ()Ljava/lang/String;
  Code:
   Stack=2, Locals=1, Args_size=1
	getstatic	Field scala/runtime/ScalaRunTime$.MODULE$:Lscala/runtime/ScalaRunTime$;
	aload_0
	invokevirtual	Method scala/runtime/ScalaRunTime$._toString:(Lscala/Product;)Ljava/lang/String;
	areturn
  Labels:

public boolean equals(java.lang.Object);
  Signature: (Ljava/lang/Object;)Z
  Code:
   Stack=2, Locals=4, Args_size=2
	aload_0
	aload_1
	if_acmpeq	l1 // iconst_1
	aload_1
	instanceof	class scala/util/parsing/combinator/testing/Str
	ifeq	l2 // iconst_0
	aload_1
	checkcast	class scala/util/parsing/combinator/testing/Str
	astore_2
	aload_2
	invokevirtual	Method s:()Ljava/lang/String;
	astore_3
	aload_0
	aload_3
	invokespecial	Method gd3$1:(Ljava/lang/String;)Z
	ifeq	l3 // iconst_0
	aload_1
	checkcast	class scala/util/parsing/combinator/testing/Str
	aload_0
	invokeinterface	InterfaceMethod scala/Equals.canEqual:(Ljava/lang/Object;)Z
	goto	l4 // ifeq
l3	iconst_0
	goto	l4 // ifeq
l2	iconst_0
l4	ifeq	l5 // iconst_0
l1	iconst_1
	goto	l6 // ireturn
l5	iconst_0
l6	ireturn
  Labels:
   	l3 = 43 // iconst_0
   	l2 = 47 // iconst_0
   	l4 = 48 // ifeq
   	l1 = 51 // iconst_1
   	l5 = 55 // iconst_0
   	l6 = 56 // ireturn
  LocalVariableTable: 
   Start  Length  Slot  Name   Signature
   0      57      0    this       Lscala/util/parsing/combinator/testing/Str;
   17      30      2    temp10       Lscala/util/parsing/combinator/testing/Str;
   22      25      3    temp11       Ljava/lang/String;


public java.lang.String productPrefix();
  Signature: ()Ljava/lang/String;
  Code:
   Stack=1, Locals=1, Args_size=1
	ldc	String Str
	areturn
  Labels:

public int productArity();
  Signature: ()I
  Code:
   Stack=1, Locals=1, Args_size=1
	iconst_1
	ireturn
  Labels:

public java.lang.Object productElement(int);
  Signature: (I)Ljava/lang/Object;
  Code:
   Stack=3, Locals=2, Args_size=2
	iload_1
	iconst_0
	if_icmpne	l1 // new
	aload_0
	invokevirtual	Method s:()Ljava/lang/String;
	areturn
l1	new	class java/lang/IndexOutOfBoundsException
	dup
	iload_1
	invokestatic	Method scala/runtime/BoxesRunTime.boxToInteger:(I)Ljava/lang/Integer;
	invokevirtual	Method java/lang/Object.toString:()Ljava/lang/String;
	invokespecial	Method java/lang/IndexOutOfBoundsException."<init>":(Ljava/lang/String;)V
	athrow
  Labels:
   	l1 = 10 // new

public boolean canEqual(java.lang.Object);
  Signature: (Ljava/lang/Object;)Z
  Code:
   Stack=1, Locals=2, Args_size=2
	aload_1
	instanceof	class scala/util/parsing/combinator/testing/Str
	ireturn
  Labels:

private final boolean gd3$1(java.lang.String);
  Signature: (Ljava/lang/String;)Z
  Code:
   Stack=2, Locals=3, Args_size=2
	aload_1
	aload_0
	invokevirtual	Method s:()Ljava/lang/String;
	astore_2
	dup
	ifnonnull	l1 // aload_2
	pop
	aload_2
	ifnull	l2 // iconst_1
	goto	l3 // iconst_0
l1	aload_2
	invokevirtual	Method java/lang/Object.equals:(Ljava/lang/Object;)Z
	ifeq	l3 // iconst_0
l2	iconst_1
	goto	l4 // ireturn
l3	iconst_0
l4	ireturn
  Labels:
   	l1 = 18 // aload_2
   	l2 = 25 // iconst_1
   	l3 = 29 // iconst_0
   	l4 = 30 // ireturn

public scala.util.parsing.combinator.testing.Str(java.lang.String);
  Signature: (Ljava/lang/String;)V
  Code:
   Stack=2, Locals=2, Args_size=2
	aload_0
	aload_1
	putfield	Field s:Ljava/lang/String;
	aload_0
	invokespecial	Method java/lang/Object."<init>":()V
	aload_0
	invokestatic	Method scala/Product$class.$init$:(Lscala/Product;)V
	return
  Labels:
  LocalVariableTable: 
   Start  Length  Slot  Name   Signature
   0      14      0    this       Lscala/util/parsing/combinator/testing/Str;
   0      14      1    s       Ljava/lang/String;


}

