Compiled from "Tester.scala"
public abstract class scala.util.parsing.combinator.testing.Tester extends java.lang.Object implements scala.ScalaObject
  SourceFile: "Tester.scala"
  ScalaSig: length = 0x1CF
   05 00 4F 06 08 01 02 FFFFFF84 FFFFFF80 FFFFFF80 FFFFFF81 00 0D 02 06 54
   65 73 74 65 72 0A 02 03 04 01 07 74 65 73 74 69
   6E 67 0A 02 05 06 01 0A 63 6F 6D 62 69 6E 61 74
   6F 72 0A 02 07 08 01 07 70 61 72 73 69 6E 67 0A
   02 09 0A 01 04 75 74 69 6C 0A 01 0B 01 05 73 63
   61 6C 61 03 00 13 03 00 0E 16 10 02 0F 14 0D 01
   10 0A 02 11 12 01 04 6C 61 6E 67 0A 01 13 01 04
   6A 61 76 61 09 02 15 10 02 06 4F 62 6A 65 63 74
   10 02 17 18 0D 01 0A 09 02 19 0A 02 0B 53 63 61
   6C 61 4F 62 6A 65 63 74 08 05 1B 00 FFFFFF84 00 1C 01
   06 3C 69 6E 69 74 3E 14 01 1D 10 02 1E 00 0D 01
   02 08 07 20 00 FFFFFFC2 FFFFFF80 FFFFFF86 00 21 01 09 73 79 6E 74
   61 63 74 69 63 15 01 22 12 02 23 25 06 08 24 00
   FFFFFF84 FFFFFF80 FFFFFF80 FFFFFF80 00 22 02 0C 3C 72 65 66 69 6E 65 6D
   65 6E 74 3E 10 02 26 29 0D 01 27 0A 02 28 04 01
   0B 73 79 6E 74 61 63 74 69 63 61 6C 09 02 2A 27
   02 0C 54 6F 6B 65 6E 50 61 72 73 65 72 73 08 07
   2C 23 FFFFFFC2 FFFFFF80 FFFFFF86 20 2D 01 07 6C 65 78 69 63 61 6C
   15 01 2E 10 02 2F 31 0D 01 30 0A 02 2C 04 09 02
   32 30 02 07 4C 65 78 69 63 61 6C 08 07 34 00 FFFFFFC2
   FFFFFF80 FFFFFF86 00 35 01 06 70 61 72 73 65 72 15 01 36 10
   03 37 39 3D 0E 02 38 1F 0D 01 00 09 02 3A 3B 02
   06 50 61 72 73 65 72 09 02 3C 04 02 07 50 61 72
   73 65 72 73 10 02 17 3E 09 02 3F 0A 02 03 41 6E
   79 08 05 41 00 FFFFFF84 00 42 01 04 74 65 73 74 14 02
   43 46 10 02 17 44 09 02 45 0A 02 04 55 6E 69 74
   08 05 47 40 FFFFFFC0 00 48 01 02 69 6E 10 02 49 4C 0E
   02 17 4A 09 02 4B 0A 01 06 50 72 65 64 65 66 09
   02 4D 4E 02 06 53 74 72 69 6E 67 0A 02 4B 0A 
  InnerClass: 
   public abstract #80= #66 of #47; //Parser=class scala/util/parsing/combinator/Parsers$Parser of class scala/util/parsing/combinator/Parsers
   public #81= #53 of #61; //Scanner=class scala/util/parsing/combinator/lexical/Scanners$Scanner of class scala/util/parsing/combinator/lexical/Scanners
   public abstract #84= #83 of #47; //ParseResult=class scala/util/parsing/combinator/Parsers$ParseResult of class scala/util/parsing/combinator/Parsers
  minor version: 0
  major version: 49
  Constant pool:
const #1 = Asciz	SourceFile;
const #2 = Asciz	Tester.scala;
const #3 = Asciz	<init>;
const #4 = Asciz	()V;
const #5 = Asciz	Code;
const #6 = Asciz	LineNumberTable;
const #7 = Asciz	java/lang/Object;
const #8 = class	#7;	//  java/lang/Object
const #9 = NameAndType	#3:#4;//  "<init>":()V
const #10 = Method	#8.#9;	//  java/lang/Object."<init>":()V
const #11 = Asciz	test;
const #12 = Asciz	(Ljava/lang/String;)V;
const #13 = Asciz	scala/Console$;
const #14 = class	#13;	//  scala/Console$
const #15 = Asciz	MODULE$;
const #16 = Asciz	Lscala/Console$;;
const #17 = NameAndType	#15:#16;//  MODULE$:Lscala/Console$;
const #18 = Field	#14.#17;	//  scala/Console$.MODULE$:Lscala/Console$;
const #19 = Asciz	scala/collection/mutable/StringBuilder;
const #20 = class	#19;	//  scala/collection/mutable/StringBuilder
const #21 = Method	#20.#9;	//  scala/collection/mutable/StringBuilder."<init>":()V
const #22 = Asciz	\nin : ;
const #23 = String	#22;	//  \nin : 
const #24 = Asciz	append;
const #25 = Asciz	(Ljava/lang/Object;)Lscala/collection/mutable/StringBuilder;;
const #26 = NameAndType	#24:#25;//  append:(Ljava/lang/Object;)Lscala/collection/mutable/StringBuilder;
const #27 = Method	#20.#26;	//  scala/collection/mutable/StringBuilder.append:(Ljava/lang/Object;)Lscala/collection/mutable/StringBuilder;
const #28 = Asciz	toString;
const #29 = Asciz	()Ljava/lang/String;;
const #30 = NameAndType	#28:#29;//  toString:()Ljava/lang/String;
const #31 = Method	#20.#30;	//  scala/collection/mutable/StringBuilder.toString:()Ljava/lang/String;
const #32 = Asciz	println;
const #33 = Asciz	(Ljava/lang/Object;)V;
const #34 = NameAndType	#32:#33;//  println:(Ljava/lang/Object;)V
const #35 = Method	#14.#34;	//  scala/Console$.println:(Ljava/lang/Object;)V
const #36 = Asciz	scala/util/parsing/combinator/testing/Tester;
const #37 = class	#36;	//  scala/util/parsing/combinator/testing/Tester
const #38 = Asciz	syntactic;
const #39 = Asciz	()Lscala/util/parsing/combinator/syntactical/TokenParsers;;
const #40 = NameAndType	#38:#39;//  syntactic:()Lscala/util/parsing/combinator/syntactical/TokenParsers;
const #41 = Method	#37.#40;	//  scala/util/parsing/combinator/testing/Tester.syntactic:()Lscala/util/parsing/combinator/syntactical/TokenParsers;
const #42 = Asciz	parser;
const #43 = Asciz	()Lscala/util/parsing/combinator/Parsers$Parser;;
const #44 = NameAndType	#42:#43;//  parser:()Lscala/util/parsing/combinator/Parsers$Parser;
const #45 = Method	#37.#44;	//  scala/util/parsing/combinator/testing/Tester.parser:()Lscala/util/parsing/combinator/Parsers$Parser;
const #46 = Asciz	scala/util/parsing/combinator/Parsers;
const #47 = class	#46;	//  scala/util/parsing/combinator/Parsers
const #48 = Asciz	phrase;
const #49 = Asciz	(Lscala/util/parsing/combinator/Parsers$Parser;)Lscala/util/parsing/combinator/Parsers$Parser;;
const #50 = NameAndType	#48:#49;//  phrase:(Lscala/util/parsing/combinator/Parsers$Parser;)Lscala/util/parsing/combinator/Parsers$Parser;
const #51 = InterfaceMethod	#47.#50;	//  scala/util/parsing/combinator/Parsers.phrase:(Lscala/util/parsing/combinator/Parsers$Parser;)Lscala/util/parsing/combinator/Parsers$Parser;
const #52 = Asciz	scala/util/parsing/combinator/lexical/Scanners$Scanner;
const #53 = class	#52;	//  scala/util/parsing/combinator/lexical/Scanners$Scanner
const #54 = Asciz	scala/util/parsing/combinator/syntactical/TokenParsers;
const #55 = class	#54;	//  scala/util/parsing/combinator/syntactical/TokenParsers
const #56 = Asciz	lexical;
const #57 = Asciz	()Lscala/util/parsing/syntax/Tokens;;
const #58 = NameAndType	#56:#57;//  lexical:()Lscala/util/parsing/syntax/Tokens;
const #59 = InterfaceMethod	#55.#58;	//  scala/util/parsing/combinator/syntactical/TokenParsers.lexical:()Lscala/util/parsing/syntax/Tokens;
const #60 = Asciz	scala/util/parsing/combinator/lexical/Scanners;
const #61 = class	#60;	//  scala/util/parsing/combinator/lexical/Scanners
const #62 = Asciz	(Lscala/util/parsing/combinator/lexical/Scanners;Ljava/lang/String;)V;
const #63 = NameAndType	#3:#62;//  "<init>":(Lscala/util/parsing/combinator/lexical/Scanners;Ljava/lang/String;)V
const #64 = Method	#53.#63;	//  scala/util/parsing/combinator/lexical/Scanners$Scanner."<init>":(Lscala/util/parsing/combinator/lexical/Scanners;Ljava/lang/String;)V
const #65 = Asciz	scala/util/parsing/combinator/Parsers$Parser;
const #66 = class	#65;	//  scala/util/parsing/combinator/Parsers$Parser
const #67 = Asciz	apply;
const #68 = Asciz	(Lscala/util/parsing/input/Reader;)Lscala/util/parsing/combinator/Parsers$ParseResult;;
const #69 = NameAndType	#67:#68;//  apply:(Lscala/util/parsing/input/Reader;)Lscala/util/parsing/combinator/Parsers$ParseResult;
const #70 = Method	#66.#69;	//  scala/util/parsing/combinator/Parsers$Parser.apply:(Lscala/util/parsing/input/Reader;)Lscala/util/parsing/combinator/Parsers$ParseResult;
const #71 = Asciz	this;
const #72 = Asciz	Lscala/util/parsing/combinator/testing/Tester;;
const #73 = Asciz	in;
const #74 = Asciz	Ljava/lang/String;;
const #75 = Asciz	LocalVariableTable;
const #76 = Asciz	()Lscala/util/parsing/combinator/Parsers$Parser<Ljava/lang/Object;>;;
const #77 = Asciz	Signature;
const #78 = Asciz	ScalaSig;
const #79 = Asciz	InnerClasses;
const #80 = Asciz	Parser;
const #81 = Asciz	Scanner;
const #82 = Asciz	scala/util/parsing/combinator/Parsers$ParseResult;
const #83 = class	#82;	//  scala/util/parsing/combinator/Parsers$ParseResult
const #84 = Asciz	ParseResult;
const #85 = Asciz	scala/ScalaObject;
const #86 = class	#85;	//  scala/ScalaObject

{
public scala.util.parsing.combinator.testing.Tester();
  Code:
   Stack=1, Locals=1, Args_size=1
   0:	aload_0
   1:	invokespecial	#10; //Method java/lang/Object."<init>":()V
   4:	return
  LineNumberTable: 
   line 34: 0


public void test(java.lang.String);
  Code:
   Stack=6, Locals=2, Args_size=2
   0:	getstatic	#18; //Field scala/Console$.MODULE$:Lscala/Console$;
   3:	new	#20; //class scala/collection/mutable/StringBuilder
   6:	dup
   7:	invokespecial	#21; //Method scala/collection/mutable/StringBuilder."<init>":()V
   10:	ldc	#23; //String \nin : 
   12:	invokevirtual	#27; //Method scala/collection/mutable/StringBuilder.append:(Ljava/lang/Object;)Lscala/collection/mutable/StringBuilder;
   15:	aload_1
   16:	invokevirtual	#27; //Method scala/collection/mutable/StringBuilder.append:(Ljava/lang/Object;)Lscala/collection/mutable/StringBuilder;
   19:	invokevirtual	#31; //Method scala/collection/mutable/StringBuilder.toString:()Ljava/lang/String;
   22:	invokevirtual	#35; //Method scala/Console$.println:(Ljava/lang/Object;)V
   25:	getstatic	#18; //Field scala/Console$.MODULE$:Lscala/Console$;
   28:	aload_0
   29:	invokevirtual	#41; //Method syntactic:()Lscala/util/parsing/combinator/syntactical/TokenParsers;
   32:	aload_0
   33:	invokevirtual	#45; //Method parser:()Lscala/util/parsing/combinator/Parsers$Parser;
   36:	invokeinterface	#51,  2; //InterfaceMethod scala/util/parsing/combinator/Parsers.phrase:(Lscala/util/parsing/combinator/Parsers$Parser;)Lscala/util/parsing/combinator/Parsers$Parser;
   41:	new	#53; //class scala/util/parsing/combinator/lexical/Scanners$Scanner
   44:	dup
   45:	aload_0
   46:	invokevirtual	#41; //Method syntactic:()Lscala/util/parsing/combinator/syntactical/TokenParsers;
   49:	invokeinterface	#59,  1; //InterfaceMethod scala/util/parsing/combinator/syntactical/TokenParsers.lexical:()Lscala/util/parsing/syntax/Tokens;
   54:	checkcast	#61; //class scala/util/parsing/combinator/lexical/Scanners
   57:	aload_1
   58:	invokespecial	#64; //Method scala/util/parsing/combinator/lexical/Scanners$Scanner."<init>":(Lscala/util/parsing/combinator/lexical/Scanners;Ljava/lang/String;)V
   61:	invokevirtual	#70; //Method scala/util/parsing/combinator/Parsers$Parser.apply:(Lscala/util/parsing/input/Reader;)Lscala/util/parsing/combinator/Parsers$ParseResult;
   64:	invokevirtual	#35; //Method scala/Console$.println:(Ljava/lang/Object;)V
   67:	return
  LineNumberTable: 
   line 45: 0
   line 46: 25

  LocalVariableTable: 
   Start  Length  Slot  Name   Signature
   0      68      0    this       Lscala/util/parsing/combinator/testing/Tester;
   0      68      1    in       Ljava/lang/String;


public abstract scala.util.parsing.combinator.Parsers$Parser parser();
  Signature: length = 0x2
   00 4C 

public abstract scala.util.parsing.combinator.syntactical.TokenParsers syntactic();

}

