Compiled from "Tester.scala"
public abstract class scala.util.parsing.combinator.testing.Tester extends java.lang.Object implements scala.ScalaObject
  SourceFile: "Tester.scala"
  ScalaSig: length = 0x1CF
   05 00 4F 06 08 01 02 FFFFFF84 FFFFFF80 FFFFFF80 FFFFFF81 00 0D 02 06 54
   65 73 74 65 72 0A 02 03 04 01 07 74 65 73 74 69
   6E 67 0A 02 05 06 01 0A 63 6F 6D 62 69 6E 61 74
   6F 72 0A 02 07 08 01 07 70 61 72 73 69 6E 67 0A
   02 09 0A 01 04 75 74 69 6C 0A 01 0B 01 05 73 63
   61 6C 61 03 00 13 03 00 0E 16 10 02 0F 14 0D 01
   10 0A 02 11 12 01 04 6C 61 6E 67 0A 01 13 01 04
   6A 61 76 61 09 02 15 10 02 06 4F 62 6A 65 63 74
   10 02 17 18 0D 01 0A 09 02 19 0A 02 0B 53 63 61
   6C 61 4F 62 6A 65 63 74 08 05 1B 00 FFFFFF84 00 1C 01
   06 3C 69 6E 69 74 3E 14 01 1D 10 02 1E 00 0D 01
   02 08 07 20 00 FFFFFFC2 FFFFFF80 FFFFFF86 00 21 01 09 73 79 6E 74
   61 63 74 69 63 15 01 22 12 02 23 25 06 08 24 00
   FFFFFF84 FFFFFF80 FFFFFF80 FFFFFF80 00 22 02 0C 3C 72 65 66 69 6E 65 6D
   65 6E 74 3E 10 02 26 29 0D 01 27 0A 02 28 04 01
   0B 73 79 6E 74 61 63 74 69 63 61 6C 09 02 2A 27
   02 0C 54 6F 6B 65 6E 50 61 72 73 65 72 73 08 07
   2C 23 FFFFFFC2 FFFFFF80 FFFFFF86 20 2D 01 07 6C 65 78 69 63 61 6C
   15 01 2E 10 02 2F 31 0D 01 30 0A 02 2C 04 09 02
   32 30 02 07 4C 65 78 69 63 61 6C 08 07 34 00 FFFFFFC2
   FFFFFF80 FFFFFF86 00 35 01 06 70 61 72 73 65 72 15 01 36 10
   03 37 39 3D 0E 02 38 1F 0D 01 00 09 02 3A 3B 02
   06 50 61 72 73 65 72 09 02 3C 04 02 07 50 61 72
   73 65 72 73 10 02 17 3E 09 02 3F 0A 02 03 41 6E
   79 08 05 41 00 FFFFFF84 00 42 01 04 74 65 73 74 14 02
   43 46 10 02 17 44 09 02 45 0A 02 04 55 6E 69 74
   08 05 47 40 FFFFFFC0 00 48 01 02 69 6E 10 02 49 4C 0E
   02 17 4A 09 02 4B 0A 01 06 50 72 65 64 65 66 09
   02 4D 4E 02 06 53 74 72 69 6E 67 0A 02 4B 0A 
  InnerClass: 
   public abstract Parser=class scala/util/parsing/combinator/Parsers$Parser of class scala/util/parsing/combinator/Parsers
   public Scanner=class scala/util/parsing/combinator/lexical/Scanners$Scanner of class scala/util/parsing/combinator/lexical/Scanners
   public abstract ParseResult=class scala/util/parsing/combinator/Parsers$ParseResult of class scala/util/parsing/combinator/Parsers
  minor version: 0
  major version: 49
  Constant pool:
Asciz	SourceFile;
Asciz	Tester.scala;
Asciz	syntactic;
Asciz	()Lscala/util/parsing/combinator/syntactical/TokenParsers;;
Asciz	parser;
Asciz	()Lscala/util/parsing/combinator/Parsers$Parser;;
Asciz	()Lscala/util/parsing/combinator/Parsers$Parser<Ljava/lang/Object;>;;
Asciz	Signature;
Asciz	test;
Asciz	(Ljava/lang/String;)V;
Asciz	Code;
Asciz	scala/Console$;
class	scala/Console$
Asciz	MODULE$;
Asciz	Lscala/Console$;;
NameAndType	MODULE$:Lscala/Console$;
Field	scala/Console$.MODULE$:Lscala/Console$;
Asciz	LineNumberTable;
Asciz	scala/collection/mutable/StringBuilder;
class	scala/collection/mutable/StringBuilder
Asciz	<init>;
Asciz	()V;
NameAndType	"<init>":()V
Method	scala/collection/mutable/StringBuilder."<init>":()V
Asciz	\nin : ;
String	\nin : 
Asciz	append;
Asciz	(Ljava/lang/Object;)Lscala/collection/mutable/StringBuilder;;
NameAndType	append:(Ljava/lang/Object;)Lscala/collection/mutable/StringBuilder;
Method	scala/collection/mutable/StringBuilder.append:(Ljava/lang/Object;)Lscala/collection/mutable/StringBuilder;
Asciz	toString;
Asciz	()Ljava/lang/String;;
NameAndType	toString:()Ljava/lang/String;
Method	scala/collection/mutable/StringBuilder.toString:()Ljava/lang/String;
Asciz	println;
Asciz	(Ljava/lang/Object;)V;
NameAndType	println:(Ljava/lang/Object;)V
Method	scala/Console$.println:(Ljava/lang/Object;)V
Asciz	scala/util/parsing/combinator/testing/Tester;
class	scala/util/parsing/combinator/testing/Tester
NameAndType	syntactic:()Lscala/util/parsing/combinator/syntactical/TokenParsers;
Method	scala/util/parsing/combinator/testing/Tester.syntactic:()Lscala/util/parsing/combinator/syntactical/TokenParsers;
NameAndType	parser:()Lscala/util/parsing/combinator/Parsers$Parser;
Method	scala/util/parsing/combinator/testing/Tester.parser:()Lscala/util/parsing/combinator/Parsers$Parser;
Asciz	scala/util/parsing/combinator/Parsers;
class	scala/util/parsing/combinator/Parsers
Asciz	phrase;
Asciz	(Lscala/util/parsing/combinator/Parsers$Parser;)Lscala/util/parsing/combinator/Parsers$Parser;;
NameAndType	phrase:(Lscala/util/parsing/combinator/Parsers$Parser;)Lscala/util/parsing/combinator/Parsers$Parser;
InterfaceMethod	scala/util/parsing/combinator/Parsers.phrase:(Lscala/util/parsing/combinator/Parsers$Parser;)Lscala/util/parsing/combinator/Parsers$Parser;
Asciz	scala/util/parsing/combinator/lexical/Scanners$Scanner;
class	scala/util/parsing/combinator/lexical/Scanners$Scanner
Asciz	scala/util/parsing/combinator/syntactical/TokenParsers;
class	scala/util/parsing/combinator/syntactical/TokenParsers
Asciz	lexical;
Asciz	()Lscala/util/parsing/combinator/token/Tokens;;
NameAndType	lexical:()Lscala/util/parsing/combinator/token/Tokens;
InterfaceMethod	scala/util/parsing/combinator/syntactical/TokenParsers.lexical:()Lscala/util/parsing/combinator/token/Tokens;
Asciz	scala/util/parsing/combinator/lexical/Scanners;
class	scala/util/parsing/combinator/lexical/Scanners
Asciz	(Lscala/util/parsing/combinator/lexical/Scanners;Ljava/lang/String;)V;
NameAndType	"<init>":(Lscala/util/parsing/combinator/lexical/Scanners;Ljava/lang/String;)V
Method	scala/util/parsing/combinator/lexical/Scanners$Scanner."<init>":(Lscala/util/parsing/combinator/lexical/Scanners;Ljava/lang/String;)V
Asciz	scala/util/parsing/combinator/Parsers$Parser;
class	scala/util/parsing/combinator/Parsers$Parser
Asciz	apply;
Asciz	(Lscala/util/parsing/input/Reader;)Lscala/util/parsing/combinator/Parsers$ParseResult;;
NameAndType	apply:(Lscala/util/parsing/input/Reader;)Lscala/util/parsing/combinator/Parsers$ParseResult;
Method	scala/util/parsing/combinator/Parsers$Parser.apply:(Lscala/util/parsing/input/Reader;)Lscala/util/parsing/combinator/Parsers$ParseResult;
Asciz	this;
Asciz	Lscala/util/parsing/combinator/testing/Tester;;
Asciz	in;
Asciz	Ljava/lang/String;;
Asciz	LocalVariableTable;
Asciz	java/lang/Object;
class	java/lang/Object
Method	java/lang/Object."<init>":()V
Asciz	ScalaSig;
Asciz	InnerClasses;
Asciz	Parser;
Asciz	Scanner;
Asciz	scala/util/parsing/combinator/Parsers$ParseResult;
class	scala/util/parsing/combinator/Parsers$ParseResult
Asciz	ParseResult;
Asciz	scala/ScalaObject;
class	scala/ScalaObject

{
public abstract scala.util.parsing.combinator.syntactical.TokenParsers syntactic();
  Signature: ()Lscala/util/parsing/combinator/syntactical/TokenParsers;

public abstract scala.util.parsing.combinator.Parsers$Parser parser();
  Signature: ()Lscala/util/parsing/combinator/Parsers$Parser;
  Signature: length = 0x2
   00 07 

public void test(java.lang.String);
  Signature: (Ljava/lang/String;)V
  Code:
   Stack=6, Locals=2, Args_size=2
	getstatic	Field scala/Console$.MODULE$:Lscala/Console$;
	new	class scala/collection/mutable/StringBuilder
	dup
	invokespecial	Method scala/collection/mutable/StringBuilder."<init>":()V
	ldc	String \nin : 
	invokevirtual	Method scala/collection/mutable/StringBuilder.append:(Ljava/lang/Object;)Lscala/collection/mutable/StringBuilder;
	aload_1
	invokevirtual	Method scala/collection/mutable/StringBuilder.append:(Ljava/lang/Object;)Lscala/collection/mutable/StringBuilder;
	invokevirtual	Method scala/collection/mutable/StringBuilder.toString:()Ljava/lang/String;
	invokevirtual	Method scala/Console$.println:(Ljava/lang/Object;)V
	getstatic	Field scala/Console$.MODULE$:Lscala/Console$;
	aload_0
	invokevirtual	Method syntactic:()Lscala/util/parsing/combinator/syntactical/TokenParsers;
	aload_0
	invokevirtual	Method parser:()Lscala/util/parsing/combinator/Parsers$Parser;
	invokeinterface	InterfaceMethod scala/util/parsing/combinator/Parsers.phrase:(Lscala/util/parsing/combinator/Parsers$Parser;)Lscala/util/parsing/combinator/Parsers$Parser;
	new	class scala/util/parsing/combinator/lexical/Scanners$Scanner
	dup
	aload_0
	invokevirtual	Method syntactic:()Lscala/util/parsing/combinator/syntactical/TokenParsers;
	invokeinterface	InterfaceMethod scala/util/parsing/combinator/syntactical/TokenParsers.lexical:()Lscala/util/parsing/combinator/token/Tokens;
	checkcast	class scala/util/parsing/combinator/lexical/Scanners
	aload_1
	invokespecial	Method scala/util/parsing/combinator/lexical/Scanners$Scanner."<init>":(Lscala/util/parsing/combinator/lexical/Scanners;Ljava/lang/String;)V
	invokevirtual	Method scala/util/parsing/combinator/Parsers$Parser.apply:(Lscala/util/parsing/input/Reader;)Lscala/util/parsing/combinator/Parsers$ParseResult;
	invokevirtual	Method scala/Console$.println:(Ljava/lang/Object;)V
	return
  Labels:
  LocalVariableTable: 
   Start  Length  Slot  Name   Signature
   0      68      0    this       Lscala/util/parsing/combinator/testing/Tester;
   0      68      1    in       Ljava/lang/String;


public scala.util.parsing.combinator.testing.Tester();
  Signature: ()V
  Code:
   Stack=1, Locals=1, Args_size=1
	aload_0
	invokespecial	Method java/lang/Object."<init>":()V
	return
  Labels:

}

