Compiled from "CachedFileStorage.scala"
public abstract class scala.xml.persistent.CachedFileStorage extends java.lang.Thread implements scala.util.logging.Logged,scala.ScalaObject
  SourceFile: "CachedFileStorage.scala"
  ScalaSig: length = 0x312
   05 00 7D 06 08 01 02 FFFFFF84 FFFFFF80 FFFFFF80 FFFFFF81 00 09 02 11 43
   61 63 68 65 64 46 69 6C 65 53 74 6F 72 61 67 65
   0A 02 03 04 01 0A 70 65 72 73 69 73 74 65 6E 74
   0A 02 05 06 01 03 78 6D 6C 0A 01 07 01 05 73 63
   61 6C 61 03 00 13 04 00 0A 12 1A 10 02 0B 10 0D
   01 0C 0A 02 0D 0E 01 04 6C 61 6E 67 0A 01 0F 01
   04 6A 61 76 61 09 02 11 0C 02 06 54 68 72 65 61
   64 10 02 13 18 0D 01 14 0A 02 15 16 01 07 6C 6F
   67 67 69 6E 67 0A 02 17 06 01 04 75 74 69 6C 09
   02 19 14 02 06 4C 6F 67 67 65 64 10 02 1B 1C 0D
   01 06 09 02 1D 06 02 0B 53 63 61 6C 61 4F 62 6A
   65 63 74 08 08 1F 00 FFFFFF82 FFFFFFC2 FFFFFF80 FFFFFF84 04 20 01 05 66
   69 6C 65 31 15 01 21 10 02 22 25 0D 01 23 0A 02
   24 0E 01 02 69 6F 09 02 26 23 02 04 46 69 6C 65
   08 08 28 00 FFFFFF82 FFFFFF80 FFFFFFA0 FFFFFF80 04 21 01 06 66 69 6C 65
   31 20 08 05 2A 00 FFFFFF84 00 2B 01 06 3C 69 6E 69 74
   3E 14 02 2C 2E 10 02 2D 00 0D 01 02 08 05 1F 29
   FFFFFFC0 00 21 08 07 30 00 FFFFFFC2 FFFFFF80 FFFFFF84 04 20 01 05 66 69
   6C 65 32 08 06 32 00 FFFFFFA0 FFFFFF80 04 21 01 06 66 69 6C
   65 32 20 08 07 34 00 FFFFFFC0 FFFFFF80 FFFFFF84 04 20 01 07 74 68
   65 46 69 6C 65 08 07 36 00 FFFFFFC0 FFFFFF80 FFFFFF84 04 37 01 0B
   74 68 65 46 69 6C 65 5F 24 65 71 14 02 38 3B 10
   02 1B 39 09 02 3A 06 02 04 55 6E 69 74 08 07 3C
   35 FFFFFF81 FFFFFF80 FFFFFFC0 00 21 01 03 78 24 31 08 06 3E 00 FFFFFFA0
   FFFFFFA0 04 21 01 08 74 68 65 46 69 6C 65 20 08 05 40
   00 FFFFFF84 04 41 01 06 73 77 69 74 63 68 15 01 38 08
   07 43 00 FFFFFFC0 FFFFFF80 FFFFFF84 08 44 01 05 64 69 72 74 79 15
   01 45 10 02 1B 46 09 02 47 06 02 07 42 6F 6F 6C
   65 61 6E 08 07 49 00 FFFFFFC0 FFFFFF80 FFFFFF84 08 4A 01 09 64 69
   72 74 79 5F 24 65 71 14 02 38 4B 08 07 3C 48 FFFFFF81
   FFFFFF80 FFFFFFC0 00 45 08 06 4D 00 FFFFFFA0 FFFFFFA0 04 45 01 06 64 69
   72 74 79 20 08 07 4F 00 FFFFFFC2 FFFFFF80 FFFFFF84 08 50 01 08 69
   6E 74 65 72 76 61 6C 15 01 51 10 02 1B 52 09 02
   53 06 02 03 49 6E 74 08 06 55 00 FFFFFFA0 FFFFFF80 04 51 01
   09 69 6E 74 65 72 76 61 6C 20 08 05 57 00 FFFFFF84 08
   58 01 0C 69 6E 69 74 69 61 6C 4E 6F 64 65 73 15
   01 59 10 03 5A 62 65 0E 02 5B 60 0E 02 5C 5F 0D
   01 5D 0A 02 5E 08 01 06 3C 72 6F 6F 74 3E 09 01
   07 09 02 61 06 01 07 70 61 63 6B 61 67 65 09 02
   63 64 02 08 49 74 65 72 61 74 6F 72 0A 02 61 06
   10 02 66 67 0D 01 04 09 02 68 04 02 04 4E 6F 64
   65 08 05 6A 00 FFFFFF86 00 58 01 05 6E 6F 64 65 73 08
   05 6C 00 FFFFFF86 00 6D 01 08 24 70 6C 75 73 24 65 71
   14 02 38 6E 08 05 6F 6B FFFFFFC0 00 65 01 01 65 08 05
   71 00 FFFFFF86 00 72 01 09 24 6D 69 6E 75 73 24 65 71
   14 02 38 73 08 05 6F 70 FFFFFFC0 00 65 08 05 75 00 FFFFFF84
   04 58 01 04 6C 6F 61 64 08 05 77 00 FFFFFF84 04 41 01
   04 73 61 76 65 08 05 79 00 FFFFFF84 20 7A 01 03 72 75
   6E 14 01 38 08 05 7C 00 FFFFFF84 00 41 01 05 66 6C 75
   73 68 
  minor version: 0
  major version: 49
  Constant pool:
Asciz	SourceFile;
Asciz	CachedFileStorage.scala;
Asciz	interval;
Asciz	I;
Asciz	dirty;
Asciz	Z;
Asciz	theFile;
Asciz	Ljava/io/File;;
Asciz	file2;
Asciz	file1;
Asciz	log;
Asciz	(Ljava/lang/String;)V;
Asciz	Code;
Asciz	LineNumberTable;
Asciz	scala/util/logging/Logged$class;
class	scala/util/logging/Logged$class
Asciz	(Lscala/util/logging/Logged;Ljava/lang/String;)V;
NameAndType	log:(Lscala/util/logging/Logged;Ljava/lang/String;)V
Method	scala/util/logging/Logged$class.log:(Lscala/util/logging/Logged;Ljava/lang/String;)V
Asciz	this;
Asciz	Lscala/xml/persistent/CachedFileStorage;;
Asciz	msg;
Asciz	Ljava/lang/String;;
Asciz	LocalVariableTable;
Asciz	()Ljava/io/File;;
Asciz	scala/xml/persistent/CachedFileStorage;
class	scala/xml/persistent/CachedFileStorage
NameAndType	file1:Ljava/io/File;
Field	scala/xml/persistent/CachedFileStorage.file1:Ljava/io/File;
NameAndType	file2:Ljava/io/File;
Field	scala/xml/persistent/CachedFileStorage.file2:Ljava/io/File;
NameAndType	theFile:Ljava/io/File;
Field	scala/xml/persistent/CachedFileStorage.theFile:Ljava/io/File;
Asciz	theFile_$eq;
Asciz	(Ljava/io/File;)V;
Asciz	switch;
Asciz	()V;
NameAndType	theFile:()Ljava/io/File;
Method	scala/xml/persistent/CachedFileStorage.theFile:()Ljava/io/File;
NameAndType	file1:()Ljava/io/File;
Method	scala/xml/persistent/CachedFileStorage.file1:()Ljava/io/File;
Asciz	java/lang/Object;
class	java/lang/Object
Asciz	equals;
Asciz	(Ljava/lang/Object;)Z;
NameAndType	equals:(Ljava/lang/Object;)Z
Method	java/lang/Object.equals:(Ljava/lang/Object;)Z
NameAndType	file2:()Ljava/io/File;
Method	scala/xml/persistent/CachedFileStorage.file2:()Ljava/io/File;
NameAndType	theFile_$eq:(Ljava/io/File;)V
Method	scala/xml/persistent/CachedFileStorage.theFile_$eq:(Ljava/io/File;)V
Asciz	()Z;
NameAndType	dirty:Z
Field	scala/xml/persistent/CachedFileStorage.dirty:Z
Asciz	dirty_$eq;
Asciz	(Z)V;
Asciz	()I;
NameAndType	interval:I
Field	scala/xml/persistent/CachedFileStorage.interval:I
Asciz	initialNodes;
Asciz	()Lscala/collection/Iterator;;
Asciz	java/io/File;
class	java/io/File
Asciz	exists;
NameAndType	exists:()Z
Method	java/io/File.exists:()Z
Asciz	scala/package$;
class	scala/package$
Asciz	MODULE$;
Asciz	Lscala/package$;;
NameAndType	MODULE$:Lscala/package$;
Field	scala/package$.MODULE$:Lscala/package$;
Asciz	Iterator;
Asciz	()Lscala/collection/Iterator$;;
NameAndType	Iterator:()Lscala/collection/Iterator$;
Method	scala/package$.Iterator:()Lscala/collection/Iterator$;
Asciz	scala/collection/Iterator$;
class	scala/collection/Iterator$
Asciz	empty;
NameAndType	empty:()Lscala/collection/Iterator;
Method	scala/collection/Iterator$.empty:()Lscala/collection/Iterator;
Asciz	gd1$1;
NameAndType	gd1$1:()Z
Method	scala/xml/persistent/CachedFileStorage.gd1$1:()Z
Asciz	load;
NameAndType	load:()Lscala/collection/Iterator;
Method	scala/xml/persistent/CachedFileStorage.load:()Lscala/collection/Iterator;
Asciz	tp1;
Asciz	tp2;
Asciz	()Lscala/collection/Iterator<Lscala/xml/Node;>;;
Asciz	Signature;
Asciz	nodes;
Asciz	$plus$eq;
Asciz	(Lscala/xml/Node;)V;
Asciz	$minus$eq;
Asciz	scala/collection/mutable/StringBuilder;
class	scala/collection/mutable/StringBuilder
Asciz	<init>;
NameAndType	"<init>":()V
Method	scala/collection/mutable/StringBuilder."<init>":()V
Asciz	[load]\nloading ;
String	[load]\nloading 
Asciz	append;
Asciz	(Ljava/lang/Object;)Lscala/collection/mutable/StringBuilder;;
NameAndType	append:(Ljava/lang/Object;)Lscala/collection/mutable/StringBuilder;
Method	scala/collection/mutable/StringBuilder.append:(Ljava/lang/Object;)Lscala/collection/mutable/StringBuilder;
Asciz	toString;
Asciz	()Ljava/lang/String;;
NameAndType	toString:()Ljava/lang/String;
Method	scala/collection/mutable/StringBuilder.toString:()Ljava/lang/String;
Asciz	scala/util/logging/Logged;
class	scala/util/logging/Logged
NameAndType	log:(Ljava/lang/String;)V
InterfaceMethod	scala/util/logging/Logged.log:(Ljava/lang/String;)V
Asciz	scala/io/Source$;
class	scala/io/Source$
Asciz	Lscala/io/Source$;;
NameAndType	MODULE$:Lscala/io/Source$;
Field	scala/io/Source$.MODULE$:Lscala/io/Source$;
Asciz	fromFile$default$2;
NameAndType	fromFile$default$2:()I
Method	scala/io/Source$.fromFile$default$2:()I
Asciz	fromFile$default$3;
Asciz	(Ljava/io/File;I)Lscala/io/Codec;;
NameAndType	fromFile$default$3:(Ljava/io/File;I)Lscala/io/Codec;
Method	scala/io/Source$.fromFile$default$3:(Ljava/io/File;I)Lscala/io/Codec;
Asciz	fromFile;
Asciz	(Ljava/io/File;ILscala/io/Codec;)Lscala/io/Source;;
NameAndType	fromFile:(Ljava/io/File;ILscala/io/Codec;)Lscala/io/Source;
Method	scala/io/Source$.fromFile:(Ljava/io/File;ILscala/io/Codec;)Lscala/io/Source;
Asciz	parsing ;
String	parsing 
Asciz	scala/xml/parsing/ConstructingParser$;
class	scala/xml/parsing/ConstructingParser$
Asciz	Lscala/xml/parsing/ConstructingParser$;;
NameAndType	MODULE$:Lscala/xml/parsing/ConstructingParser$;
Field	scala/xml/parsing/ConstructingParser$.MODULE$:Lscala/xml/parsing/ConstructingParser$;
Asciz	fromSource;
Asciz	(Lscala/io/Source;Z)Lscala/xml/parsing/ConstructingParser;;
NameAndType	fromSource:(Lscala/io/Source;Z)Lscala/xml/parsing/ConstructingParser;
Method	scala/xml/parsing/ConstructingParser$.fromSource:(Lscala/io/Source;Z)Lscala/xml/parsing/ConstructingParser;
Asciz	scala/xml/parsing/MarkupParser;
class	scala/xml/parsing/MarkupParser
Asciz	document;
Asciz	()Lscala/xml/Document;;
NameAndType	document:()Lscala/xml/Document;
InterfaceMethod	scala/xml/parsing/MarkupParser.document:()Lscala/xml/Document;
Asciz	scala/xml/Document;
class	scala/xml/Document
Asciz	docElem;
Asciz	()Lscala/xml/Node;;
NameAndType	docElem:()Lscala/xml/Node;
Method	scala/xml/Document.docElem:()Lscala/xml/Node;
Asciz	scala/xml/Node;
class	scala/xml/Node
Asciz	apply;
Asciz	(I)Lscala/xml/Node;;
NameAndType	apply:(I)Lscala/xml/Node;
Method	scala/xml/Node.apply:(I)Lscala/xml/Node;
NameAndType	switch:()V
Method	scala/xml/persistent/CachedFileStorage.switch:()V
Asciz	[load done];
String	[load done]
Asciz	child;
Asciz	()Lscala/collection/Seq;;
NameAndType	child:()Lscala/collection/Seq;
Method	scala/xml/Node.child:()Lscala/collection/Seq;
Asciz	scala/collection/IterableLike;
class	scala/collection/IterableLike
Asciz	iterator;
NameAndType	iterator:()Lscala/collection/Iterator;
InterfaceMethod	scala/collection/IterableLike.iterator:()Lscala/collection/Iterator;
Asciz	src;
Asciz	Lscala/io/Source;;
Asciz	x$1;
Asciz	x$2;
Asciz	x$3;
Asciz	Lscala/io/Codec;;
Asciz	res;
Asciz	Lscala/xml/Node;;
Asciz	save;
NameAndType	dirty:()Z
Method	scala/xml/persistent/CachedFileStorage.dirty:()Z
Asciz	[save]\ndeleting ;
String	[save]\ndeleting 
Asciz	delete;
NameAndType	delete:()Z
Method	java/io/File.delete:()Z
Asciz	creating new ;
String	creating new 
Asciz	createNewFile;
NameAndType	createNewFile:()Z
Method	java/io/File.createNewFile:()Z
Asciz	java/io/FileOutputStream;
class	java/io/FileOutputStream
NameAndType	"<init>":(Ljava/io/File;)V
Method	java/io/FileOutputStream."<init>":(Ljava/io/File;)V
Asciz	getChannel;
Asciz	()Ljava/nio/channels/FileChannel;;
NameAndType	getChannel:()Ljava/nio/channels/FileChannel;
Method	java/io/FileOutputStream.getChannel:()Ljava/nio/channels/FileChannel;
Asciz	scala/xml/Elem;
class	scala/xml/Elem
String	nodes
Asciz	scala/xml/Null$;
class	scala/xml/Null$
Asciz	Lscala/xml/Null$;;
NameAndType	MODULE$:Lscala/xml/Null$;
Field	scala/xml/Null$.MODULE$:Lscala/xml/Null$;
Asciz	$scope;
Asciz	()Lscala/xml/TopScope$;;
NameAndType	$scope:()Lscala/xml/TopScope$;
Method	scala/package$.$scope:()Lscala/xml/TopScope$;
Asciz	scala/xml/NodeBuffer;
class	scala/xml/NodeBuffer
Method	scala/xml/NodeBuffer."<init>":()V
NameAndType	nodes:()Lscala/collection/Iterator;
Method	scala/xml/persistent/CachedFileStorage.nodes:()Lscala/collection/Iterator;
Asciz	scala/collection/Iterator;
class	scala/collection/Iterator
Asciz	toList;
Asciz	()Lscala/collection/immutable/List;;
NameAndType	toList:()Lscala/collection/immutable/List;
InterfaceMethod	scala/collection/Iterator.toList:()Lscala/collection/immutable/List;
Asciz	$amp$plus;
Asciz	(Ljava/lang/Object;)Lscala/xml/NodeBuffer;;
NameAndType	$amp$plus:(Ljava/lang/Object;)Lscala/xml/NodeBuffer;
Method	scala/xml/NodeBuffer.$amp$plus:(Ljava/lang/Object;)Lscala/xml/NodeBuffer;
Asciz	(Ljava/lang/String;Ljava/lang/String;Lscala/xml/MetaData;Lscala/xml/NamespaceBinding;Lscala/collection/Seq;)V;
NameAndType	"<init>":(Ljava/lang/String;Ljava/lang/String;Lscala/xml/MetaData;Lscala/xml/NamespaceBinding;Lscala/collection/Seq;)V
Method	scala/xml/Elem."<init>":(Ljava/lang/String;Ljava/lang/String;Lscala/xml/MetaData;Lscala/xml/NamespaceBinding;Lscala/collection/Seq;)V
Asciz	utf-8;
String	utf-8
Asciz	java/nio/channels/Channels;
class	java/nio/channels/Channels
Asciz	newWriter;
Asciz	(Ljava/nio/channels/WritableByteChannel;Ljava/lang/String;)Ljava/io/Writer;;
NameAndType	newWriter:(Ljava/nio/channels/WritableByteChannel;Ljava/lang/String;)Ljava/io/Writer;
Method	java/nio/channels/Channels.newWriter:(Ljava/nio/channels/WritableByteChannel;Ljava/lang/String;)Ljava/io/Writer;
Asciz	scala/xml/XML$;
class	scala/xml/XML$
Asciz	Lscala/xml/XML$;;
NameAndType	MODULE$:Lscala/xml/XML$;
Field	scala/xml/XML$.MODULE$:Lscala/xml/XML$;
Asciz	write;
Asciz	(Ljava/io/Writer;Lscala/xml/Node;Ljava/lang/String;ZLscala/xml/dtd/DocType;)V;
NameAndType	write:(Ljava/io/Writer;Lscala/xml/Node;Ljava/lang/String;ZLscala/xml/dtd/DocType;)V
Method	scala/xml/XML$.write:(Ljava/io/Writer;Lscala/xml/Node;Ljava/lang/String;ZLscala/xml/dtd/DocType;)V
Asciz	writing to ;
String	writing to 
Asciz	java/io/Writer;
class	java/io/Writer
Asciz	close;
NameAndType	close:()V
Method	java/io/Writer.close:()V
Asciz	java/nio/channels/FileChannel;
class	java/nio/channels/FileChannel
Method	java/nio/channels/FileChannel.close:()V
Method	java/io/FileOutputStream.close:()V
NameAndType	dirty_$eq:(Z)V
Method	scala/xml/persistent/CachedFileStorage.dirty_$eq:(Z)V
Asciz	[save done];
String	[save done]
Asciz	fos;
Asciz	Ljava/io/FileOutputStream;;
Asciz	c;
Asciz	Ljava/nio/channels/FileChannel;;
Asciz	storageNode;
Asciz	Lscala/xml/Elem;;
Asciz	$buf;
Asciz	Lscala/xml/NodeBuffer;;
Asciz	w;
Asciz	Ljava/io/Writer;;
Asciz	run;
Asciz	[run]\nstarting storage thread, checking every ;
String	[run]\nstarting storage thread, checking every 
NameAndType	interval:()I
Method	scala/xml/persistent/CachedFileStorage.interval:()I
Asciz	scala/runtime/BoxesRunTime;
class	scala/runtime/BoxesRunTime
Asciz	boxToInteger;
Asciz	(I)Ljava/lang/Integer;;
NameAndType	boxToInteger:(I)Ljava/lang/Integer;
Method	scala/runtime/BoxesRunTime.boxToInteger:(I)Ljava/lang/Integer;
Asciz	 ms;
String	 ms
Asciz	java/lang/Thread;
class	java/lang/Thread
Asciz	sleep;
Asciz	(J)V;
NameAndType	sleep:(J)V
Method	java/lang/Thread.sleep:(J)V
NameAndType	save:()V
Method	scala/xml/persistent/CachedFileStorage.save:()V
Asciz	flush;
Asciz	lastModified;
Asciz	()J;
NameAndType	lastModified:()J
Method	java/io/File.lastModified:()J
Method	java/lang/Thread."<init>":()V
Asciz	$init$;
Asciz	(Lscala/util/logging/Logged;)V;
NameAndType	$init$:(Lscala/util/logging/Logged;)V
Method	scala/util/logging/Logged$class.$init$:(Lscala/util/logging/Logged;)V
Asciz	getParent;
NameAndType	getParent:()Ljava/lang/String;
Method	java/io/File.getParent:()Ljava/lang/String;
Asciz	getName;
NameAndType	getName:()Ljava/lang/String;
Method	java/io/File.getName:()Ljava/lang/String;
Asciz	$;
String	$
Asciz	(Ljava/lang/String;Ljava/lang/String;)V;
NameAndType	"<init>":(Ljava/lang/String;Ljava/lang/String;)V
Method	java/io/File."<init>":(Ljava/lang/String;Ljava/lang/String;)V
int	1000;
Asciz	ScalaSig;
Asciz	scala/ScalaObject;
class	scala/ScalaObject

{
private final int interval;
  Signature: I

private boolean dirty;
  Signature: Z

private java.io.File theFile;
  Signature: Ljava/io/File;

private final java.io.File file2;
  Signature: Ljava/io/File;

private final java.io.File file1;
  Signature: Ljava/io/File;

public void log(java.lang.String);
  Signature: (Ljava/lang/String;)V
  Code:
   Stack=2, Locals=2, Args_size=2
	aload_0
	aload_1
	invokestatic	Method scala/util/logging/Logged$class.log:(Lscala/util/logging/Logged;Ljava/lang/String;)V
	return
  Labels:
  LocalVariableTable: 
   Start  Length  Slot  Name   Signature
   0      6      0    this       Lscala/xml/persistent/CachedFileStorage;
   0      6      1    msg       Ljava/lang/String;


private java.io.File file1();
  Signature: ()Ljava/io/File;
  Code:
   Stack=1, Locals=1, Args_size=1
	aload_0
	getfield	Field file1:Ljava/io/File;
	areturn
  Labels:

private java.io.File file2();
  Signature: ()Ljava/io/File;
  Code:
   Stack=1, Locals=1, Args_size=1
	aload_0
	getfield	Field file2:Ljava/io/File;
	areturn
  Labels:

private java.io.File theFile();
  Signature: ()Ljava/io/File;
  Code:
   Stack=1, Locals=1, Args_size=1
	aload_0
	getfield	Field theFile:Ljava/io/File;
	areturn
  Labels:

private void theFile_$eq(java.io.File);
  Signature: (Ljava/io/File;)V
  Code:
   Stack=2, Locals=2, Args_size=2
	aload_0
	aload_1
	putfield	Field theFile:Ljava/io/File;
	return
  Labels:

private void switch();
  Signature: ()V
  Code:
   Stack=3, Locals=2, Args_size=1
	aload_0
	aload_0
	invokespecial	Method theFile:()Ljava/io/File;
	aload_0
	invokespecial	Method file1:()Ljava/io/File;
	astore_1
	dup
	ifnonnull	l1 // aload_1
	pop
	aload_1
	ifnull	l2 // aload_0
	goto	l3 // aload_0
l1	aload_1
	invokevirtual	Method java/lang/Object.equals:(Ljava/lang/Object;)Z
	ifeq	l3 // aload_0
l2	aload_0
	invokespecial	Method file2:()Ljava/io/File;
	goto	l4 // invokespecial
l3	aload_0
	invokespecial	Method file1:()Ljava/io/File;
l4	invokespecial	Method theFile_$eq:(Ljava/io/File;)V
	return
  Labels:
   	l1 = 22 // aload_1
   	l2 = 29 // aload_0
   	l3 = 36 // aload_0
   	l4 = 40 // invokespecial

public boolean dirty();
  Signature: ()Z
  Code:
   Stack=1, Locals=1, Args_size=1
	aload_0
	getfield	Field dirty:Z
	ireturn
  Labels:

public void dirty_$eq(boolean);
  Signature: (Z)V
  Code:
   Stack=2, Locals=2, Args_size=2
	aload_0
	iload_1
	putfield	Field dirty:Z
	return
  Labels:

public int interval();
  Signature: ()I
  Code:
   Stack=1, Locals=1, Args_size=1
	aload_0
	getfield	Field interval:I
	ireturn
  Labels:

public scala.collection.Iterator initialNodes();
  Signature: ()Lscala/collection/Iterator;
  Code:
   Stack=2, Locals=3, Args_size=1
	aload_0
	invokespecial	Method file1:()Ljava/io/File;
	invokevirtual	Method java/io/File.exists:()Z
	istore_1
	aload_0
	invokespecial	Method file2:()Ljava/io/File;
	invokevirtual	Method java/io/File.exists:()Z
	istore_2
	iload_1
	iconst_0
	if_icmpne	l1 // iload_1
	iload_2
	iconst_0
	if_icmpne	l2 // aload_0
	aload_0
	aload_0
	invokespecial	Method file1:()Ljava/io/File;
	invokespecial	Method theFile_$eq:(Ljava/io/File;)V
	getstatic	Field scala/package$.MODULE$:Lscala/package$;
	invokevirtual	Method scala/package$.Iterator:()Lscala/collection/Iterator$;
	invokevirtual	Method scala/collection/Iterator$.empty:()Lscala/collection/Iterator;
	goto	l3 // areturn
l1	iload_1
	iconst_1
	if_icmpne	l2 // aload_0
	iload_2
	iconst_1
	if_icmpne	l4 // aload_0
	aload_0
	invokespecial	Method gd1$1:()Z
	ifeq	l4 // aload_0
	aload_0
	aload_0
	invokespecial	Method file2:()Ljava/io/File;
	invokespecial	Method theFile_$eq:(Ljava/io/File;)V
	aload_0
	invokespecial	Method load:()Lscala/collection/Iterator;
	goto	l3 // areturn
l4	aload_0
	aload_0
	invokespecial	Method file1:()Ljava/io/File;
	invokespecial	Method theFile_$eq:(Ljava/io/File;)V
	aload_0
	invokespecial	Method load:()Lscala/collection/Iterator;
	goto	l3 // areturn
l2	aload_0
	aload_0
	invokespecial	Method file2:()Ljava/io/File;
	invokespecial	Method theFile_$eq:(Ljava/io/File;)V
	aload_0
	invokespecial	Method load:()Lscala/collection/Iterator;
l3	areturn
  Labels:
   	l1 = 46 // iload_1
   	l4 = 78 // aload_0
   	l2 = 93 // aload_0
   	l3 = 105 // areturn
  LocalVariableTable: 
   Start  Length  Slot  Name   Signature
   0      106      0    this       Lscala/xml/persistent/CachedFileStorage;
   8      98      1    tp1       Z
   16      90      2    tp2       Z

  Signature: length = 0x2
   00 5A 

public abstract scala.collection.Iterator nodes();
  Signature: ()Lscala/collection/Iterator;
  Signature: length = 0x2
   00 5A 

public abstract void $plus$eq(scala.xml.Node);
  Signature: (Lscala/xml/Node;)V

public abstract void $minus$eq(scala.xml.Node);
  Signature: (Lscala/xml/Node;)V

private scala.collection.Iterator load();
  Signature: ()Lscala/collection/Iterator;
  Code:
   Stack=4, Locals=6, Args_size=1
	aload_0
	new	class scala/collection/mutable/StringBuilder
	dup
	invokespecial	Method scala/collection/mutable/StringBuilder."<init>":()V
	ldc	String [load]\nloading 
	invokevirtual	Method scala/collection/mutable/StringBuilder.append:(Ljava/lang/Object;)Lscala/collection/mutable/StringBuilder;
	aload_0
	invokespecial	Method theFile:()Ljava/io/File;
	invokevirtual	Method scala/collection/mutable/StringBuilder.append:(Ljava/lang/Object;)Lscala/collection/mutable/StringBuilder;
	invokevirtual	Method scala/collection/mutable/StringBuilder.toString:()Ljava/lang/String;
	invokeinterface	InterfaceMethod scala/util/logging/Logged.log:(Ljava/lang/String;)V
	aload_0
	invokespecial	Method theFile:()Ljava/io/File;
	astore_2
	getstatic	Field scala/io/Source$.MODULE$:Lscala/io/Source$;
	invokevirtual	Method scala/io/Source$.fromFile$default$2:()I
	istore_3
	getstatic	Field scala/io/Source$.MODULE$:Lscala/io/Source$;
	aload_2
	iload_3
	invokevirtual	Method scala/io/Source$.fromFile$default$3:(Ljava/io/File;I)Lscala/io/Codec;
	astore	4
	getstatic	Field scala/io/Source$.MODULE$:Lscala/io/Source$;
	aload_2
	iload_3
	aload	4
	invokevirtual	Method scala/io/Source$.fromFile:(Ljava/io/File;ILscala/io/Codec;)Lscala/io/Source;
	astore_1
	aload_0
	new	class scala/collection/mutable/StringBuilder
	dup
	invokespecial	Method scala/collection/mutable/StringBuilder."<init>":()V
	ldc	String parsing 
	invokevirtual	Method scala/collection/mutable/StringBuilder.append:(Ljava/lang/Object;)Lscala/collection/mutable/StringBuilder;
	aload_0
	invokespecial	Method theFile:()Ljava/io/File;
	invokevirtual	Method scala/collection/mutable/StringBuilder.append:(Ljava/lang/Object;)Lscala/collection/mutable/StringBuilder;
	invokevirtual	Method scala/collection/mutable/StringBuilder.toString:()Ljava/lang/String;
	invokeinterface	InterfaceMethod scala/util/logging/Logged.log:(Ljava/lang/String;)V
	getstatic	Field scala/xml/parsing/ConstructingParser$.MODULE$:Lscala/xml/parsing/ConstructingParser$;
	aload_1
	iconst_0
	invokevirtual	Method scala/xml/parsing/ConstructingParser$.fromSource:(Lscala/io/Source;Z)Lscala/xml/parsing/ConstructingParser;
	invokeinterface	InterfaceMethod scala/xml/parsing/MarkupParser.document:()Lscala/xml/Document;
	invokevirtual	Method scala/xml/Document.docElem:()Lscala/xml/Node;
	iconst_0
	invokevirtual	Method scala/xml/Node.apply:(I)Lscala/xml/Node;
	astore	5
	aload_0
	invokespecial	Method switch:()V
	aload_0
	ldc	String [load done]
	invokeinterface	InterfaceMethod scala/util/logging/Logged.log:(Ljava/lang/String;)V
	aload	5
	invokevirtual	Method scala/xml/Node.child:()Lscala/collection/Seq;
	invokeinterface	InterfaceMethod scala/collection/IterableLike.iterator:()Lscala/collection/Iterator;
	areturn
  Labels:
  LocalVariableTable: 
   Start  Length  Slot  Name   Signature
   0      134      0    this       Lscala/xml/persistent/CachedFileStorage;
   61      72      1    src       Lscala/io/Source;
   33      27      2    x$1       Ljava/io/File;
   40      20      3    x$2       I
   50      10      4    x$3       Lscala/io/Codec;
   111      22      5    res       Lscala/xml/Node;

  Signature: length = 0x2
   00 5A 

private void save();
  Signature: ()V
  Code:
   Stack=8, Locals=6, Args_size=1
	aload_0
	invokevirtual	Method dirty:()Z
	ifeq	l1 // return
	aload_0
	new	class scala/collection/mutable/StringBuilder
	dup
	invokespecial	Method scala/collection/mutable/StringBuilder."<init>":()V
	ldc	String [save]\ndeleting 
	invokevirtual	Method scala/collection/mutable/StringBuilder.append:(Ljava/lang/Object;)Lscala/collection/mutable/StringBuilder;
	aload_0
	invokespecial	Method theFile:()Ljava/io/File;
	invokevirtual	Method scala/collection/mutable/StringBuilder.append:(Ljava/lang/Object;)Lscala/collection/mutable/StringBuilder;
	invokevirtual	Method scala/collection/mutable/StringBuilder.toString:()Ljava/lang/String;
	invokeinterface	InterfaceMethod scala/util/logging/Logged.log:(Ljava/lang/String;)V
	aload_0
	invokespecial	Method theFile:()Ljava/io/File;
	invokevirtual	Method java/io/File.delete:()Z
	pop
	aload_0
	new	class scala/collection/mutable/StringBuilder
	dup
	invokespecial	Method scala/collection/mutable/StringBuilder."<init>":()V
	ldc	String creating new 
	invokevirtual	Method scala/collection/mutable/StringBuilder.append:(Ljava/lang/Object;)Lscala/collection/mutable/StringBuilder;
	aload_0
	invokespecial	Method theFile:()Ljava/io/File;
	invokevirtual	Method scala/collection/mutable/StringBuilder.append:(Ljava/lang/Object;)Lscala/collection/mutable/StringBuilder;
	invokevirtual	Method scala/collection/mutable/StringBuilder.toString:()Ljava/lang/String;
	invokeinterface	InterfaceMethod scala/util/logging/Logged.log:(Ljava/lang/String;)V
	aload_0
	invokespecial	Method theFile:()Ljava/io/File;
	invokevirtual	Method java/io/File.createNewFile:()Z
	pop
	new	class java/io/FileOutputStream
	dup
	aload_0
	invokespecial	Method theFile:()Ljava/io/File;
	invokespecial	Method java/io/FileOutputStream."<init>":(Ljava/io/File;)V
	astore_1
	aload_1
	invokevirtual	Method java/io/FileOutputStream.getChannel:()Ljava/nio/channels/FileChannel;
	astore_2
	new	class scala/xml/Elem
	dup
	aconst_null
	ldc	String nodes
	getstatic	Field scala/xml/Null$.MODULE$:Lscala/xml/Null$;
	getstatic	Field scala/package$.MODULE$:Lscala/package$;
	invokevirtual	Method scala/package$.$scope:()Lscala/xml/TopScope$;
	new	class scala/xml/NodeBuffer
	dup
	invokespecial	Method scala/xml/NodeBuffer."<init>":()V
	astore	4
	aload	4
	aload_0
	invokevirtual	Method nodes:()Lscala/collection/Iterator;
	invokeinterface	InterfaceMethod scala/collection/Iterator.toList:()Lscala/collection/immutable/List;
	invokevirtual	Method scala/xml/NodeBuffer.$amp$plus:(Ljava/lang/Object;)Lscala/xml/NodeBuffer;
	pop
	aload	4
	invokespecial	Method scala/xml/Elem."<init>":(Ljava/lang/String;Ljava/lang/String;Lscala/xml/MetaData;Lscala/xml/NamespaceBinding;Lscala/collection/Seq;)V
	astore_3
	aload_2
	ldc	String utf-8
	invokestatic	Method java/nio/channels/Channels.newWriter:(Ljava/nio/channels/WritableByteChannel;Ljava/lang/String;)Ljava/io/Writer;
	astore	5
	getstatic	Field scala/xml/XML$.MODULE$:Lscala/xml/XML$;
	aload	5
	aload_3
	ldc	String utf-8
	iconst_1
	aconst_null
	invokevirtual	Method scala/xml/XML$.write:(Ljava/io/Writer;Lscala/xml/Node;Ljava/lang/String;ZLscala/xml/dtd/DocType;)V
	aload_0
	new	class scala/collection/mutable/StringBuilder
	dup
	invokespecial	Method scala/collection/mutable/StringBuilder."<init>":()V
	ldc	String writing to 
	invokevirtual	Method scala/collection/mutable/StringBuilder.append:(Ljava/lang/Object;)Lscala/collection/mutable/StringBuilder;
	aload_0
	invokespecial	Method theFile:()Ljava/io/File;
	invokevirtual	Method scala/collection/mutable/StringBuilder.append:(Ljava/lang/Object;)Lscala/collection/mutable/StringBuilder;
	invokevirtual	Method scala/collection/mutable/StringBuilder.toString:()Ljava/lang/String;
	invokeinterface	InterfaceMethod scala/util/logging/Logged.log:(Ljava/lang/String;)V
	aload	5
	invokevirtual	Method java/io/Writer.close:()V
	aload_2
	invokevirtual	Method java/nio/channels/FileChannel.close:()V
	aload_1
	invokevirtual	Method java/io/FileOutputStream.close:()V
	aload_0
	iconst_0
	invokevirtual	Method dirty_$eq:(Z)V
	aload_0
	invokespecial	Method switch:()V
	aload_0
	ldc_w	String [save done]
	invokeinterface	InterfaceMethod scala/util/logging/Logged.log:(Ljava/lang/String;)V
l1	return
  Labels:
   	l1 = 222 // return
  LocalVariableTable: 
   Start  Length  Slot  Name   Signature
   0      223      0    this       Lscala/xml/persistent/CachedFileStorage;
   91      131      1    fos       Ljava/io/FileOutputStream;
   96      126      2    c       Ljava/nio/channels/FileChannel;
   142      80      3    storageNode       Lscala/xml/Elem;
   121      17      4    $buf       Lscala/xml/NodeBuffer;
   150      72      5    w       Ljava/io/Writer;


public void run();
  Signature: ()V
  Code:
   Stack=3, Locals=2, Args_size=1
	aload_0
	new	class scala/collection/mutable/StringBuilder
	dup
	invokespecial	Method scala/collection/mutable/StringBuilder."<init>":()V
	ldc_w	String [run]\nstarting storage thread, checking every 
	invokevirtual	Method scala/collection/mutable/StringBuilder.append:(Ljava/lang/Object;)Lscala/collection/mutable/StringBuilder;
	aload_0
	invokevirtual	Method interval:()I
	istore_1
	iload_1
	invokestatic	Method scala/runtime/BoxesRunTime.boxToInteger:(I)Ljava/lang/Integer;
	invokevirtual	Method scala/collection/mutable/StringBuilder.append:(Ljava/lang/Object;)Lscala/collection/mutable/StringBuilder;
	ldc_w	String  ms
	invokevirtual	Method scala/collection/mutable/StringBuilder.append:(Ljava/lang/Object;)Lscala/collection/mutable/StringBuilder;
	invokevirtual	Method scala/collection/mutable/StringBuilder.toString:()Ljava/lang/String;
	invokeinterface	InterfaceMethod scala/util/logging/Logged.log:(Ljava/lang/String;)V
l1	aload_0
	invokevirtual	Method interval:()I
	i2l
	invokestatic	Method java/lang/Thread.sleep:(J)V
	aload_0
	invokespecial	Method save:()V
	goto	l1 // aload_0
  Labels:
   	l1 = 40 // aload_0

public void flush();
  Signature: ()V
  Code:
   Stack=2, Locals=1, Args_size=1
	aload_0
	iconst_1
	invokevirtual	Method dirty_$eq:(Z)V
	aload_0
	invokespecial	Method save:()V
	return
  Labels:

private final boolean gd1$1();
  Signature: ()Z
  Code:
   Stack=4, Locals=1, Args_size=1
	aload_0
	invokespecial	Method file1:()Ljava/io/File;
	invokevirtual	Method java/io/File.lastModified:()J
	aload_0
	invokespecial	Method file2:()Ljava/io/File;
	invokevirtual	Method java/io/File.lastModified:()J
	lcmp
	ifge	l1 // iconst_0
	iconst_1
	goto	l2 // ireturn
l1	iconst_0
l2	ireturn
  Labels:
   	l1 = 22 // iconst_0
   	l2 = 23 // ireturn

public scala.xml.persistent.CachedFileStorage(java.io.File);
  Signature: (Ljava/io/File;)V
  Code:
   Stack=6, Locals=2, Args_size=2
	aload_0
	aload_1
	putfield	Field file1:Ljava/io/File;
	aload_0
	invokespecial	Method java/lang/Thread."<init>":()V
	aload_0
	invokestatic	Method scala/util/logging/Logged$class.$init$:(Lscala/util/logging/Logged;)V
	aload_0
	new	class java/io/File
	dup
	aload_1
	invokevirtual	Method java/io/File.getParent:()Ljava/lang/String;
	new	class scala/collection/mutable/StringBuilder
	dup
	invokespecial	Method scala/collection/mutable/StringBuilder."<init>":()V
	aload_1
	invokevirtual	Method java/io/File.getName:()Ljava/lang/String;
	invokevirtual	Method scala/collection/mutable/StringBuilder.append:(Ljava/lang/Object;)Lscala/collection/mutable/StringBuilder;
	ldc_w	String $
	invokevirtual	Method scala/collection/mutable/StringBuilder.append:(Ljava/lang/Object;)Lscala/collection/mutable/StringBuilder;
	invokevirtual	Method scala/collection/mutable/StringBuilder.toString:()Ljava/lang/String;
	invokespecial	Method java/io/File."<init>":(Ljava/lang/String;Ljava/lang/String;)V
	putfield	Field file2:Ljava/io/File;
	aload_0
	aconst_null
	putfield	Field theFile:Ljava/io/File;
	aload_0
	iconst_0
	putfield	Field dirty:Z
	aload_0
	ldc_w	int 1000
	putfield	Field interval:I
	return
  Labels:
  LocalVariableTable: 
   Start  Length  Slot  Name   Signature
   0      69      0    this       Lscala/xml/persistent/CachedFileStorage;
   0      69      1    file1       Ljava/io/File;


}

