Compiled from "IndexedStorage.scala"
public class scala.xml.persistent.IndexedStorage extends scala.xml.persistent.CachedFileStorage implements scala.ScalaObject
  SourceFile: "IndexedStorage.scala"
  Signature: length = 0x2
   00 7E 
  ScalaSig: length = 0x27F
   05 00 6C 06 04 01 02 00 09 02 0E 49 6E 64 65 78
   65 64 53 74 6F 72 61 67 65 0A 02 03 04 01 0A 70
   65 72 73 69 73 74 65 6E 74 0A 02 05 06 01 03 78
   6D 6C 0A 01 07 01 05 73 63 61 6C 61 03 00 15 02
   0A 24 13 03 00 0B 0F 10 02 0C 0D 0D 01 02 09 02
   0E 02 02 11 43 61 63 68 65 64 46 69 6C 65 53 74
   6F 72 61 67 65 10 02 10 11 0D 01 06 09 02 12 06
   02 0B 53 63 61 6C 61 4F 62 6A 65 63 74 08 08 14
   00 FFFFFF82 FFFFFF80 FFFFFFA0 FFFFFF80 04 15 01 04 66 69 6C 65 10 02 16
   1B 0D 01 17 0A 02 18 19 01 02 69 6F 0A 01 1A 01
   04 6A 61 76 61 09 02 1C 17 02 04 46 69 6C 65 08
   08 1E 00 FFFFFF82 FFFFFF80 FFFFFFA0 FFFFFF80 04 1F 01 05 69 6E 64 65 78
   10 03 0C 20 22 09 02 21 02 02 05 49 6E 64 65 78
   10 02 23 24 0C 00 04 08 25 00 FFFFFF84 FFFFFF80 FFFFFF80 FFFFFFC2 00 26
   02 01 41 11 02 27 2A 10 02 10 28 09 02 29 06 02
   07 4E 6F 74 68 69 6E 67 10 02 10 2B 09 02 2C 06
   02 03 41 6E 79 08 05 2E 00 FFFFFF84 00 2F 01 06 3C 69
   6E 69 74 3E 14 03 30 31 32 10 03 0C 00 22 08 05
   14 2D FFFFFFC0 00 15 08 05 1E 2D FFFFFFC0 00 1F 08 07 34 00
   FFFFFFC0 FFFFFF80 FFFFFF84 04 35 01 06 74 68 65 4D 61 70 15 01 36
   10 04 37 3C 22 3E 0D 01 38 0A 02 39 3A 01 07 6D
   75 74 61 62 6C 65 0A 02 3B 06 01 0A 63 6F 6C 6C
   65 63 74 69 6F 6E 09 02 3D 38 02 03 4D 61 70 10
   02 3F 40 0D 01 04 09 02 41 04 02 04 4E 6F 64 65
   08 07 43 00 FFFFFFC0 FFFFFF80 FFFFFF84 04 44 01 0A 74 68 65 4D 61
   70 5F 24 65 71 14 02 45 48 10 02 10 46 09 02 47
   06 02 04 55 6E 69 74 08 07 49 42 FFFFFF81 FFFFFF80 FFFFFFC0 00 36
   01 03 78 24 31 08 06 4B 00 FFFFFFA0 FFFFFFA0 04 36 01 07 74
   68 65 4D 61 70 20 08 05 4D 00 FFFFFF84 00 4E 01 08 24
   70 6C 75 73 24 65 71 14 02 45 4F 08 05 50 4C FFFFFFC0
   00 3E 01 01 65 08 05 52 00 FFFFFF84 00 53 01 09 24 6D
   69 6E 75 73 24 65 71 14 02 45 54 08 05 50 51 FFFFFFC0
   00 3E 08 05 56 00 FFFFFF84 00 57 01 05 6E 6F 64 65 73
   15 01 58 10 03 59 61 3E 0E 02 5A 5F 0E 02 5B 5E
   0D 01 5C 0A 02 5D 08 01 06 3C 72 6F 6F 74 3E 09
   01 07 09 02 60 06 01 07 70 61 63 6B 61 67 65 09
   02 62 63 02 08 49 74 65 72 61 74 6F 72 0A 02 60
   06 08 05 65 00 FFFFFF84 00 66 01 06 6C 6F 6F 6B 75 70
   14 02 67 6A 10 03 10 68 3E 09 02 69 06 02 06 4F
   70 74 69 6F 6E 08 05 6B 64 FFFFFFC0 00 22 01 01 6E 
  InnerClass: 
   public final #129= #35 of #15; //$anonfun$1=class scala/xml/persistent/IndexedStorage$$anonfun$1 of class scala/xml/persistent/IndexedStorage
  minor version: 0
  major version: 49
  Constant pool:
const #1 = Asciz	SourceFile;
const #2 = Asciz	IndexedStorage.scala;
const #3 = Asciz	theMap;
const #4 = Asciz	Lscala/collection/mutable/Map;;
const #5 = Asciz	Lscala/collection/mutable/Map<TA;Lscala/xml/Node;>;;
const #6 = Asciz	Signature;
const #7 = Asciz	index;
const #8 = Asciz	Lscala/xml/persistent/Index;;
const #9 = Asciz	Lscala/xml/persistent/Index<TA;>;;
const #10 = Asciz	<init>;
const #11 = Asciz	(Ljava/io/File;Lscala/xml/persistent/Index;)V;
const #12 = Asciz	Code;
const #13 = Asciz	LineNumberTable;
const #14 = Asciz	scala/xml/persistent/IndexedStorage;
const #15 = class	#14;	//  scala/xml/persistent/IndexedStorage
const #16 = NameAndType	#7:#8;//  index:Lscala/xml/persistent/Index;
const #17 = Field	#15.#16;	//  scala/xml/persistent/IndexedStorage.index:Lscala/xml/persistent/Index;
const #18 = Asciz	scala/xml/persistent/CachedFileStorage;
const #19 = class	#18;	//  scala/xml/persistent/CachedFileStorage
const #20 = Asciz	(Ljava/io/File;)V;
const #21 = NameAndType	#10:#20;//  "<init>":(Ljava/io/File;)V
const #22 = Method	#19.#21;	//  scala/xml/persistent/CachedFileStorage."<init>":(Ljava/io/File;)V
const #23 = Asciz	scala/collection/mutable/HashMap;
const #24 = class	#23;	//  scala/collection/mutable/HashMap
const #25 = Asciz	()V;
const #26 = NameAndType	#10:#25;//  "<init>":()V
const #27 = Method	#24.#26;	//  scala/collection/mutable/HashMap."<init>":()V
const #28 = NameAndType	#3:#4;//  theMap:Lscala/collection/mutable/Map;
const #29 = Field	#15.#28;	//  scala/xml/persistent/IndexedStorage.theMap:Lscala/collection/mutable/Map;
const #30 = Asciz	initialNodes;
const #31 = Asciz	()Lscala/collection/Iterator;;
const #32 = NameAndType	#30:#31;//  initialNodes:()Lscala/collection/Iterator;
const #33 = Method	#19.#32;	//  scala/xml/persistent/CachedFileStorage.initialNodes:()Lscala/collection/Iterator;
const #34 = Asciz	scala/xml/persistent/IndexedStorage$$anonfun$1;
const #35 = class	#34;	//  scala/xml/persistent/IndexedStorage$$anonfun$1
const #36 = Asciz	(Lscala/xml/persistent/IndexedStorage;)V;
const #37 = NameAndType	#10:#36;//  "<init>":(Lscala/xml/persistent/IndexedStorage;)V
const #38 = Method	#35.#37;	//  scala/xml/persistent/IndexedStorage$$anonfun$1."<init>":(Lscala/xml/persistent/IndexedStorage;)V
const #39 = Asciz	scala/collection/Iterator;
const #40 = class	#39;	//  scala/collection/Iterator
const #41 = Asciz	foreach;
const #42 = Asciz	(Lscala/Function1;)V;
const #43 = NameAndType	#41:#42;//  foreach:(Lscala/Function1;)V
const #44 = InterfaceMethod	#40.#43;	//  scala/collection/Iterator.foreach:(Lscala/Function1;)V
const #45 = Asciz	dirty_$eq;
const #46 = Asciz	(Z)V;
const #47 = NameAndType	#45:#46;//  dirty_$eq:(Z)V
const #48 = Method	#15.#47;	//  scala/xml/persistent/IndexedStorage.dirty_$eq:(Z)V
const #49 = Asciz	this;
const #50 = Asciz	Lscala/xml/persistent/IndexedStorage;;
const #51 = Asciz	file;
const #52 = Asciz	Ljava/io/File;;
const #53 = Asciz	LocalVariableTable;
const #54 = Asciz	(Ljava/io/File;Lscala/xml/persistent/Index<TA;>;)V;
const #55 = Asciz	lookup;
const #56 = Asciz	(Ljava/lang/Object;)Lscala/Option;;
const #57 = Asciz	()Lscala/collection/mutable/Map;;
const #58 = NameAndType	#3:#57;//  theMap:()Lscala/collection/mutable/Map;
const #59 = Method	#15.#58;	//  scala/xml/persistent/IndexedStorage.theMap:()Lscala/collection/mutable/Map;
const #60 = Asciz	scala/collection/generic/MapTemplate;
const #61 = class	#60;	//  scala/collection/generic/MapTemplate
const #62 = Asciz	get;
const #63 = NameAndType	#62:#56;//  get:(Ljava/lang/Object;)Lscala/Option;
const #64 = InterfaceMethod	#61.#63;	//  scala/collection/generic/MapTemplate.get:(Ljava/lang/Object;)Lscala/Option;
const #65 = Asciz	n;
const #66 = Asciz	Ljava/lang/Object;;
const #67 = Asciz	(TA;)Lscala/Option<Lscala/xml/Node;>;;
const #68 = Asciz	nodes;
const #69 = Asciz	valuesIterator;
const #70 = NameAndType	#69:#31;//  valuesIterator:()Lscala/collection/Iterator;
const #71 = InterfaceMethod	#61.#70;	//  scala/collection/generic/MapTemplate.valuesIterator:()Lscala/collection/Iterator;
const #72 = Asciz	()Lscala/collection/Iterator<Lscala/xml/Node;>;;
const #73 = Asciz	$minus$eq;
const #74 = Asciz	(Lscala/xml/Node;)V;
const #75 = Asciz	scala/collection/mutable/StringBuilder;
const #76 = class	#75;	//  scala/collection/mutable/StringBuilder
const #77 = Method	#76.#26;	//  scala/collection/mutable/StringBuilder."<init>":()V
const #78 = Asciz	removed element at index ';
const #79 = String	#78;	//  removed element at index '
const #80 = Asciz	append;
const #81 = Asciz	(Ljava/lang/Object;)Lscala/collection/mutable/StringBuilder;;
const #82 = NameAndType	#80:#81;//  append:(Ljava/lang/Object;)Lscala/collection/mutable/StringBuilder;
const #83 = Method	#76.#82;	//  scala/collection/mutable/StringBuilder.append:(Ljava/lang/Object;)Lscala/collection/mutable/StringBuilder;
const #84 = Asciz	scala/Function1;
const #85 = class	#84;	//  scala/Function1
const #86 = Asciz	apply;
const #87 = Asciz	(Ljava/lang/Object;)Ljava/lang/Object;;
const #88 = NameAndType	#86:#87;//  apply:(Ljava/lang/Object;)Ljava/lang/Object;
const #89 = InterfaceMethod	#85.#88;	//  scala/Function1.apply:(Ljava/lang/Object;)Ljava/lang/Object;
const #90 = Asciz	';
const #91 = String	#90;	//  '
const #92 = Asciz	toString;
const #93 = Asciz	()Ljava/lang/String;;
const #94 = NameAndType	#92:#93;//  toString:()Ljava/lang/String;
const #95 = Method	#76.#94;	//  scala/collection/mutable/StringBuilder.toString:()Ljava/lang/String;
const #96 = Asciz	scala/util/logging/Logged;
const #97 = class	#96;	//  scala/util/logging/Logged
const #98 = Asciz	log;
const #99 = Asciz	(Ljava/lang/String;)V;
const #100 = NameAndType	#98:#99;//  log:(Ljava/lang/String;)V
const #101 = InterfaceMethod	#97.#100;	//  scala/util/logging/Logged.log:(Ljava/lang/String;)V
const #102 = Asciz	scala/collection/generic/MutableMapTemplate;
const #103 = class	#102;	//  scala/collection/generic/MutableMapTemplate
const #104 = Asciz	(Ljava/lang/Object;)Lscala/collection/generic/MutableMapTemplate;;
const #105 = NameAndType	#73:#104;//  $minus$eq:(Ljava/lang/Object;)Lscala/collection/generic/MutableMapTemplate;
const #106 = InterfaceMethod	#103.#105;	//  scala/collection/generic/MutableMapTemplate.$minus$eq:(Ljava/lang/Object;)Lscala/collection/generic/MutableMapTemplate;
const #107 = Asciz	e;
const #108 = Asciz	Lscala/xml/Node;;
const #109 = Asciz	$plus$eq;
const #110 = Asciz	added element at index ';
const #111 = String	#110;	//  added element at index '
const #112 = Asciz	update;
const #113 = Asciz	(Ljava/lang/Object;Ljava/lang/Object;)V;
const #114 = NameAndType	#112:#113;//  update:(Ljava/lang/Object;Ljava/lang/Object;)V
const #115 = InterfaceMethod	#103.#114;	//  scala/collection/generic/MutableMapTemplate.update:(Ljava/lang/Object;Ljava/lang/Object;)V
const #116 = Asciz	scala/runtime/BoxedUnit;
const #117 = class	#116;	//  scala/runtime/BoxedUnit
const #118 = Asciz	UNIT;
const #119 = Asciz	Lscala/runtime/BoxedUnit;;
const #120 = NameAndType	#118:#119;//  UNIT:Lscala/runtime/BoxedUnit;
const #121 = Field	#117.#120;	//  scala/runtime/BoxedUnit.UNIT:Lscala/runtime/BoxedUnit;
const #122 = Asciz	theMap_$eq;
const #123 = Asciz	(Lscala/collection/mutable/Map;)V;
const #124 = Asciz	(Lscala/collection/mutable/Map<TA;Lscala/xml/Node;>;)V;
const #125 = Asciz	()Lscala/collection/mutable/Map<TA;Lscala/xml/Node;>;;
const #126 = Asciz	<A:Ljava/lang/Object;>Lscala/xml/persistent/CachedFileStorage;Lscala/ScalaObject;;
const #127 = Asciz	ScalaSig;
const #128 = Asciz	InnerClasses;
const #129 = Asciz	$anonfun$1;
const #130 = Asciz	scala/ScalaObject;
const #131 = class	#130;	//  scala/ScalaObject

{
public scala.xml.persistent.IndexedStorage(java.io.File, scala.xml.persistent.Index);
  Code:
   Stack=4, Locals=3, Args_size=3
   0:	aload_0
   1:	aload_2
   2:	putfield	#17; //Field index:Lscala/xml/persistent/Index;
   5:	aload_0
   6:	aload_1
   7:	invokespecial	#22; //Method scala/xml/persistent/CachedFileStorage."<init>":(Ljava/io/File;)V
   10:	aload_0
   11:	new	#24; //class scala/collection/mutable/HashMap
   14:	dup
   15:	invokespecial	#27; //Method scala/collection/mutable/HashMap."<init>":()V
   18:	putfield	#29; //Field theMap:Lscala/collection/mutable/Map;
   21:	aload_0
   22:	invokespecial	#33; //Method scala/xml/persistent/CachedFileStorage.initialNodes:()Lscala/collection/Iterator;
   25:	new	#35; //class scala/xml/persistent/IndexedStorage$$anonfun$1
   28:	dup
   29:	aload_0
   30:	invokespecial	#38; //Method scala/xml/persistent/IndexedStorage$$anonfun$1."<init>":(Lscala/xml/persistent/IndexedStorage;)V
   33:	invokeinterface	#44,  2; //InterfaceMethod scala/collection/Iterator.foreach:(Lscala/Function1;)V
   38:	aload_0
   39:	iconst_0
   40:	invokevirtual	#48; //Method dirty_$eq:(Z)V
   43:	return
  LineNumberTable: 
   line 22: 0
   line 23: 6
   line 22: 7
   line 25: 10
   line 27: 21
   line 29: 38

  LocalVariableTable: 
   Start  Length  Slot  Name   Signature
   0      44      0    this       Lscala/xml/persistent/IndexedStorage;
   0      44      1    file       Ljava/io/File;
   0      44      2    index       Lscala/xml/persistent/Index;

  Signature: length = 0x2
   00 36 

public scala.Option lookup(java.lang.Object);
  Code:
   Stack=2, Locals=2, Args_size=2
   0:	aload_0
   1:	invokespecial	#59; //Method theMap:()Lscala/collection/mutable/Map;
   4:	aload_1
   5:	invokeinterface	#64,  2; //InterfaceMethod scala/collection/generic/MapTemplate.get:(Ljava/lang/Object;)Lscala/Option;
   10:	areturn
  LineNumberTable: 
   line 47: 0

  LocalVariableTable: 
   Start  Length  Slot  Name   Signature
   0      11      0    this       Lscala/xml/persistent/IndexedStorage;
   0      11      1    n       Ljava/lang/Object;

  Signature: length = 0x2
   00 43 

public scala.collection.Iterator nodes();
  Code:
   Stack=2, Locals=2, Args_size=1
   0:	aload_0
   1:	dup
   2:	astore_1
   3:	monitorenter
   4:	aload_0
   5:	invokespecial	#59; //Method theMap:()Lscala/collection/mutable/Map;
   8:	invokeinterface	#71,  1; //InterfaceMethod scala/collection/generic/MapTemplate.valuesIterator:()Lscala/collection/Iterator;
   13:	aload_1
   14:	monitorexit
   15:	checkcast	#40; //class scala/collection/Iterator
   18:	areturn
   19:	aload_1
   20:	monitorexit
   21:	athrow
  Exception table:
   from   to  target type
     4    15    19   any
  LineNumberTable: 
   line 43: 0
   line 44: 4
   line 43: 14

  Signature: length = 0x2
   00 48 

public void $minus$eq(scala.xml.Node);
  Code:
   Stack=4, Locals=3, Args_size=2
   0:	aload_0
   1:	dup
   2:	astore_2
   3:	monitorenter
   4:	aload_0
   5:	new	#76; //class scala/collection/mutable/StringBuilder
   8:	dup
   9:	invokespecial	#77; //Method scala/collection/mutable/StringBuilder."<init>":()V
   12:	ldc	#79; //String removed element at index '
   14:	invokevirtual	#83; //Method scala/collection/mutable/StringBuilder.append:(Ljava/lang/Object;)Lscala/collection/mutable/StringBuilder;
   17:	aload_0
   18:	getfield	#17; //Field index:Lscala/xml/persistent/Index;
   21:	aload_1
   22:	invokeinterface	#89,  2; //InterfaceMethod scala/Function1.apply:(Ljava/lang/Object;)Ljava/lang/Object;
   27:	invokevirtual	#83; //Method scala/collection/mutable/StringBuilder.append:(Ljava/lang/Object;)Lscala/collection/mutable/StringBuilder;
   30:	ldc	#91; //String '
   32:	invokevirtual	#83; //Method scala/collection/mutable/StringBuilder.append:(Ljava/lang/Object;)Lscala/collection/mutable/StringBuilder;
   35:	invokevirtual	#95; //Method scala/collection/mutable/StringBuilder.toString:()Ljava/lang/String;
   38:	invokeinterface	#101,  2; //InterfaceMethod scala/util/logging/Logged.log:(Ljava/lang/String;)V
   43:	aload_0
   44:	iconst_1
   45:	invokevirtual	#48; //Method dirty_$eq:(Z)V
   48:	aload_0
   49:	invokespecial	#59; //Method theMap:()Lscala/collection/mutable/Map;
   52:	aload_0
   53:	getfield	#17; //Field index:Lscala/xml/persistent/Index;
   56:	aload_1
   57:	invokeinterface	#89,  2; //InterfaceMethod scala/Function1.apply:(Ljava/lang/Object;)Ljava/lang/Object;
   62:	invokeinterface	#106,  2; //InterfaceMethod scala/collection/generic/MutableMapTemplate.$minus$eq:(Ljava/lang/Object;)Lscala/collection/generic/MutableMapTemplate;
   67:	pop
   68:	aload_2
   69:	monitorexit
   70:	return
   71:	aload_2
   72:	monitorexit
   73:	athrow
  Exception table:
   from   to  target type
     4    70    71   any
  LineNumberTable: 
   line 37: 0
   line 38: 4
   line 39: 43
   line 40: 48
   line 37: 69

  LocalVariableTable: 
   Start  Length  Slot  Name   Signature
   0      74      0    this       Lscala/xml/persistent/IndexedStorage;
   0      74      1    e       Lscala/xml/Node;


public void $plus$eq(scala.xml.Node);
  Code:
   Stack=4, Locals=3, Args_size=2
   0:	aload_0
   1:	dup
   2:	astore_2
   3:	monitorenter
   4:	aload_0
   5:	new	#76; //class scala/collection/mutable/StringBuilder
   8:	dup
   9:	invokespecial	#77; //Method scala/collection/mutable/StringBuilder."<init>":()V
   12:	ldc	#111; //String added element at index '
   14:	invokevirtual	#83; //Method scala/collection/mutable/StringBuilder.append:(Ljava/lang/Object;)Lscala/collection/mutable/StringBuilder;
   17:	aload_0
   18:	getfield	#17; //Field index:Lscala/xml/persistent/Index;
   21:	aload_1
   22:	invokeinterface	#89,  2; //InterfaceMethod scala/Function1.apply:(Ljava/lang/Object;)Ljava/lang/Object;
   27:	invokevirtual	#83; //Method scala/collection/mutable/StringBuilder.append:(Ljava/lang/Object;)Lscala/collection/mutable/StringBuilder;
   30:	ldc	#91; //String '
   32:	invokevirtual	#83; //Method scala/collection/mutable/StringBuilder.append:(Ljava/lang/Object;)Lscala/collection/mutable/StringBuilder;
   35:	invokevirtual	#95; //Method scala/collection/mutable/StringBuilder.toString:()Ljava/lang/String;
   38:	invokeinterface	#101,  2; //InterfaceMethod scala/util/logging/Logged.log:(Ljava/lang/String;)V
   43:	aload_0
   44:	iconst_1
   45:	invokevirtual	#48; //Method dirty_$eq:(Z)V
   48:	aload_0
   49:	invokespecial	#59; //Method theMap:()Lscala/collection/mutable/Map;
   52:	aload_0
   53:	getfield	#17; //Field index:Lscala/xml/persistent/Index;
   56:	aload_1
   57:	invokeinterface	#89,  2; //InterfaceMethod scala/Function1.apply:(Ljava/lang/Object;)Ljava/lang/Object;
   62:	aload_1
   63:	invokeinterface	#115,  3; //InterfaceMethod scala/collection/generic/MutableMapTemplate.update:(Ljava/lang/Object;Ljava/lang/Object;)V
   68:	getstatic	#121; //Field scala/runtime/BoxedUnit.UNIT:Lscala/runtime/BoxedUnit;
   71:	pop
   72:	aload_2
   73:	monitorexit
   74:	return
   75:	aload_2
   76:	monitorexit
   77:	athrow
  Exception table:
   from   to  target type
     4    74    75   any
  LineNumberTable: 
   line 31: 0
   line 32: 4
   line 33: 43
   line 34: 48
   line 31: 73

  LocalVariableTable: 
   Start  Length  Slot  Name   Signature
   0      78      0    this       Lscala/xml/persistent/IndexedStorage;
   0      78      1    e       Lscala/xml/Node;


}

