Compiled from "Index.scala"
public abstract class scala.xml.persistent.Index extends java.lang.Object implements scala.Function1,scala.ScalaObject
  SourceFile: "Index.scala"
  Signature: length = 0x2
   00 24 
  ScalaSig: length = 0xF3
   05 00 2E 06 05 01 02 FFFFFF81 00 09 02 05 49 6E 64 65
   78 0A 02 03 04 01 0A 70 65 72 73 69 73 74 65 6E
   74 0A 02 05 06 01 03 78 6D 6C 0A 01 07 01 05 73
   63 61 6C 61 03 00 15 02 0A 1D 13 04 00 0B 13 26
   10 02 0C 11 0D 01 0D 0A 02 0E 0F 01 04 6C 61 6E
   67 0A 01 10 01 04 6A 61 76 61 09 02 12 0D 02 06
   4F 62 6A 65 63 74 10 04 14 15 17 1B 0D 01 06 09
   02 16 06 02 09 46 75 6E 63 74 69 6F 6E 31 10 02
   18 19 0D 01 04 09 02 1A 04 02 04 4E 6F 64 65 10
   02 1C 1D 0C 00 04 08 1E 00 FFFFFF84 FFFFFF80 FFFFFF80 FFFFFFC2 00 1F 02
   01 41 11 02 20 23 10 02 14 21 09 02 22 06 02 07
   4E 6F 74 68 69 6E 67 10 02 14 24 09 02 25 06 02
   03 41 6E 79 10 02 14 27 09 02 28 06 02 0B 53 63
   61 6C 61 4F 62 6A 65 63 74 08 05 2A 00 FFFFFF84 00 2B
   01 06 3C 69 6E 69 74 3E 14 01 2C 10 03 2D 00 1B
   0D 01 02 
  minor version: 0
  major version: 49
  Constant pool:
Asciz	SourceFile;
Asciz	Index.scala;
Asciz	toString;
Asciz	()Ljava/lang/String;;
Asciz	Code;
Asciz	LineNumberTable;
Asciz	scala/Function1$class;
class	scala/Function1$class
Asciz	(Lscala/Function1;)Ljava/lang/String;;
NameAndType	toString:(Lscala/Function1;)Ljava/lang/String;
Method	scala/Function1$class.toString:(Lscala/Function1;)Ljava/lang/String;
Asciz	compose;
Asciz	(Lscala/Function1;)Lscala/Function1;;
Asciz	(Lscala/Function1;Lscala/Function1;)Lscala/Function1;;
NameAndType	compose:(Lscala/Function1;Lscala/Function1;)Lscala/Function1;
Method	scala/Function1$class.compose:(Lscala/Function1;Lscala/Function1;)Lscala/Function1;
Asciz	this;
Asciz	Lscala/xml/persistent/Index;;
Asciz	g;
Asciz	Lscala/Function1;;
Asciz	LocalVariableTable;
Asciz	andThen;
NameAndType	andThen:(Lscala/Function1;Lscala/Function1;)Lscala/Function1;
Method	scala/Function1$class.andThen:(Lscala/Function1;Lscala/Function1;)Lscala/Function1;
Asciz	<init>;
Asciz	()V;
Asciz	java/lang/Object;
class	java/lang/Object
NameAndType	"<init>":()V
Method	java/lang/Object."<init>":()V
Asciz	$init$;
Asciz	(Lscala/Function1;)V;
NameAndType	$init$:(Lscala/Function1;)V
Method	scala/Function1$class.$init$:(Lscala/Function1;)V
Asciz	Signature;
Asciz	<A:Ljava/lang/Object;>Ljava/lang/Object;Lscala/Function1<Lscala/xml/Node;TA;>;Lscala/ScalaObject;;
Asciz	ScalaSig;
Asciz	scala/xml/persistent/Index;
class	scala/xml/persistent/Index
Asciz	scala/Function1;
class	scala/Function1
Asciz	scala/ScalaObject;
class	scala/ScalaObject

{
public java.lang.String toString();
  Signature: ()Ljava/lang/String;
  Code:
   Stack=1, Locals=1, Args_size=1
	aload_0
	invokestatic	Method scala/Function1$class.toString:(Lscala/Function1;)Ljava/lang/String;
	areturn
  Labels:

public scala.Function1 compose(scala.Function1);
  Signature: (Lscala/Function1;)Lscala/Function1;
  Code:
   Stack=2, Locals=2, Args_size=2
	aload_0
	aload_1
	invokestatic	Method scala/Function1$class.compose:(Lscala/Function1;Lscala/Function1;)Lscala/Function1;
	areturn
  Labels:
  LocalVariableTable: 
   Start  Length  Slot  Name   Signature
   0      6      0    this       Lscala/xml/persistent/Index;
   0      6      1    g       Lscala/Function1;


public scala.Function1 andThen(scala.Function1);
  Signature: (Lscala/Function1;)Lscala/Function1;
  Code:
   Stack=2, Locals=2, Args_size=2
	aload_0
	aload_1
	invokestatic	Method scala/Function1$class.andThen:(Lscala/Function1;Lscala/Function1;)Lscala/Function1;
	areturn
  Labels:
  LocalVariableTable: 
   Start  Length  Slot  Name   Signature
   0      6      0    this       Lscala/xml/persistent/Index;
   0      6      1    g       Lscala/Function1;


public scala.xml.persistent.Index();
  Signature: ()V
  Code:
   Stack=1, Locals=1, Args_size=1
	aload_0
	invokespecial	Method java/lang/Object."<init>":()V
	aload_0
	invokestatic	Method scala/Function1$class.$init$:(Lscala/Function1;)V
	return
  Labels:
  Signature: length = 0x2
   00 1A 

}

