Compiled from "Index.scala"
public abstract class scala.xml.persistent.Index extends java.lang.Object implements scala.Function1,scala.ScalaObject
  SourceFile: "Index.scala"
  Signature: length = 0x2
   00 24 
  ScalaSig: length = 0xF3
   05 00 2E 06 05 01 02 FFFFFF81 00 09 02 05 49 6E 64 65
   78 0A 02 03 04 01 0A 70 65 72 73 69 73 74 65 6E
   74 0A 02 05 06 01 03 78 6D 6C 0A 01 07 01 05 73
   63 61 6C 61 03 00 15 02 0A 1D 13 04 00 0B 13 26
   10 02 0C 11 0D 01 0D 0A 02 0E 0F 01 04 6C 61 6E
   67 0A 01 10 01 04 6A 61 76 61 09 02 12 0D 02 06
   4F 62 6A 65 63 74 10 04 14 15 17 1B 0D 01 06 09
   02 16 06 02 09 46 75 6E 63 74 69 6F 6E 31 10 02
   18 19 0D 01 04 09 02 1A 04 02 04 4E 6F 64 65 10
   02 1C 1D 0C 00 04 08 1E 00 FFFFFF84 FFFFFF80 FFFFFF80 FFFFFFC2 00 1F 02
   01 41 11 02 20 23 10 02 14 21 09 02 22 06 02 07
   4E 6F 74 68 69 6E 67 10 02 14 24 09 02 25 06 02
   03 41 6E 79 10 02 14 27 09 02 28 06 02 0B 53 63
   61 6C 61 4F 62 6A 65 63 74 08 05 2A 00 FFFFFF84 00 2B
   01 06 3C 69 6E 69 74 3E 14 01 2C 10 03 2D 00 1B
   0D 01 02 
  minor version: 0
  major version: 49
  Constant pool:
const #1 = Asciz	SourceFile;
const #2 = Asciz	Index.scala;
const #3 = Asciz	<init>;
const #4 = Asciz	()V;
const #5 = Asciz	Code;
const #6 = Asciz	LineNumberTable;
const #7 = Asciz	java/lang/Object;
const #8 = class	#7;	//  java/lang/Object
const #9 = NameAndType	#3:#4;//  "<init>":()V
const #10 = Method	#8.#9;	//  java/lang/Object."<init>":()V
const #11 = Asciz	scala/Function1$class;
const #12 = class	#11;	//  scala/Function1$class
const #13 = Asciz	$init$;
const #14 = Asciz	(Lscala/Function1;)V;
const #15 = NameAndType	#13:#14;//  $init$:(Lscala/Function1;)V
const #16 = Method	#12.#15;	//  scala/Function1$class.$init$:(Lscala/Function1;)V
const #17 = Asciz	Signature;
const #18 = Asciz	andThen;
const #19 = Asciz	(Lscala/Function1;)Lscala/Function1;;
const #20 = Asciz	(Lscala/Function1;Lscala/Function1;)Lscala/Function1;;
const #21 = NameAndType	#18:#20;//  andThen:(Lscala/Function1;Lscala/Function1;)Lscala/Function1;
const #22 = Method	#12.#21;	//  scala/Function1$class.andThen:(Lscala/Function1;Lscala/Function1;)Lscala/Function1;
const #23 = Asciz	this;
const #24 = Asciz	Lscala/xml/persistent/Index;;
const #25 = Asciz	g;
const #26 = Asciz	Lscala/Function1;;
const #27 = Asciz	LocalVariableTable;
const #28 = Asciz	compose;
const #29 = NameAndType	#28:#20;//  compose:(Lscala/Function1;Lscala/Function1;)Lscala/Function1;
const #30 = Method	#12.#29;	//  scala/Function1$class.compose:(Lscala/Function1;Lscala/Function1;)Lscala/Function1;
const #31 = Asciz	toString;
const #32 = Asciz	()Ljava/lang/String;;
const #33 = Asciz	(Lscala/Function1;)Ljava/lang/String;;
const #34 = NameAndType	#31:#33;//  toString:(Lscala/Function1;)Ljava/lang/String;
const #35 = Method	#12.#34;	//  scala/Function1$class.toString:(Lscala/Function1;)Ljava/lang/String;
const #36 = Asciz	<A:Ljava/lang/Object;>Ljava/lang/Object;Lscala/Function1<Lscala/xml/Node;TA;>;Lscala/ScalaObject;;
const #37 = Asciz	ScalaSig;
const #38 = Asciz	scala/xml/persistent/Index;
const #39 = class	#38;	//  scala/xml/persistent/Index
const #40 = Asciz	scala/Function1;
const #41 = class	#40;	//  scala/Function1
const #42 = Asciz	scala/ScalaObject;
const #43 = class	#42;	//  scala/ScalaObject

{
public scala.xml.persistent.Index();
  Code:
   Stack=1, Locals=1, Args_size=1
   0:	aload_0
   1:	invokespecial	#10; //Method java/lang/Object."<init>":()V
   4:	aload_0
   5:	invokestatic	#16; //Method scala/Function1$class.$init$:(Lscala/Function1;)V
   8:	return
  LineNumberTable: 
   line 17: 0

  Signature: length = 0x2
   00 04 

public scala.Function1 andThen(scala.Function1);
  Code:
   Stack=2, Locals=2, Args_size=2
   0:	aload_0
   1:	aload_1
   2:	invokestatic	#22; //Method scala/Function1$class.andThen:(Lscala/Function1;Lscala/Function1;)Lscala/Function1;
   5:	areturn
  LineNumberTable: 
   line 17: 0

  LocalVariableTable: 
   Start  Length  Slot  Name   Signature
   0      6      0    this       Lscala/xml/persistent/Index;
   0      6      1    g       Lscala/Function1;


public scala.Function1 compose(scala.Function1);
  Code:
   Stack=2, Locals=2, Args_size=2
   0:	aload_0
   1:	aload_1
   2:	invokestatic	#30; //Method scala/Function1$class.compose:(Lscala/Function1;Lscala/Function1;)Lscala/Function1;
   5:	areturn
  LineNumberTable: 
   line 17: 0

  LocalVariableTable: 
   Start  Length  Slot  Name   Signature
   0      6      0    this       Lscala/xml/persistent/Index;
   0      6      1    g       Lscala/Function1;


public java.lang.String toString();
  Code:
   Stack=1, Locals=1, Args_size=1
   0:	aload_0
   1:	invokestatic	#35; //Method scala/Function1$class.toString:(Lscala/Function1;)Ljava/lang/String;
   4:	areturn
  LineNumberTable: 
   line 17: 0


}

