Compiled from "SetStorage.scala"
public class scala.xml.persistent.SetStorage extends scala.xml.persistent.CachedFileStorage implements scala.ScalaObject
  SourceFile: "SetStorage.scala"
  ScalaSig: length = 0x224
   05 00 57 06 08 01 02 FFFFFF84 FFFFFF80 FFFFFF80 FFFFFF80 00 09 02 0A 53
   65 74 53 74 6F 72 61 67 65 0A 02 03 04 01 0A 70
   65 72 73 69 73 74 65 6E 74 0A 02 05 06 01 03 78
   6D 6C 0A 01 07 01 05 73 63 61 6C 61 03 00 13 03
   00 0A 0E 10 02 0B 0C 0D 01 02 09 02 0D 02 02 11
   43 61 63 68 65 64 46 69 6C 65 53 74 6F 72 61 67
   65 10 02 0F 10 0D 01 06 09 02 11 06 02 0B 53 63
   61 6C 61 4F 62 6A 65 63 74 08 08 13 00 FFFFFF82 FFFFFF80 FFFFFFA0
   FFFFFF80 04 14 01 04 66 69 6C 65 10 02 15 1A 0D 01 16
   0A 02 17 18 01 02 69 6F 0A 01 19 01 04 6A 61 76
   61 09 02 1B 16 02 04 46 69 6C 65 08 05 1D 00 FFFFFF84
   00 1E 01 06 3C 69 6E 69 74 3E 14 02 1F 20 10 02
   0B 00 08 05 13 1C FFFFFFC0 00 14 08 07 22 00 FFFFFFC0 FFFFFF80 FFFFFF84
   04 23 01 06 74 68 65 53 65 74 15 01 24 10 03 25
   2A 2C 0D 01 26 0A 02 27 28 01 07 6D 75 74 61 62
   6C 65 0A 02 29 06 01 0A 63 6F 6C 6C 65 63 74 69
   6F 6E 09 02 2B 26 02 07 48 61 73 68 53 65 74 10
   02 2D 2E 0D 01 04 09 02 2F 04 02 04 4E 6F 64 65
   08 07 31 00 FFFFFFC0 FFFFFF80 FFFFFF84 04 32 01 0A 74 68 65 53 65
   74 5F 24 65 71 14 02 33 36 10 02 0F 34 09 02 35
   06 02 04 55 6E 69 74 08 07 37 30 FFFFFF81 FFFFFF80 FFFFFFC0 00 24
   01 03 78 24 31 08 06 39 00 FFFFFFA0 FFFFFFA0 04 24 01 07 74
   68 65 53 65 74 20 08 05 3B 00 FFFFFF84 00 3C 01 08 24
   70 6C 75 73 24 65 71 14 02 33 3D 08 05 3E 3A FFFFFFC0
   00 2C 01 01 65 08 05 40 00 FFFFFF84 00 41 01 09 24 6D
   69 6E 75 73 24 65 71 14 02 33 42 08 05 3E 3F FFFFFFC0
   00 2C 08 05 44 00 FFFFFF84 00 45 01 05 6E 6F 64 65 73
   15 01 46 12 03 47 4D 53 06 08 48 00 FFFFFF84 FFFFFF80 FFFFFF80 FFFFFF80
   00 46 02 0C 3C 72 65 66 69 6E 65 6D 65 6E 74 3E
   09 02 4A 4B 01 08 69 74 65 72 61 74 6F 72 09 02
   4C 26 02 0D 46 6C 61 74 48 61 73 68 54 61 62 6C
   65 10 02 4E 51 0D 01 4F 0A 02 50 18 01 04 6C 61
   6E 67 09 02 52 4F 02 06 4F 62 6A 65 63 74 10 03
   54 55 2C 0D 01 28 09 02 56 28 02 08 49 74 65 72
   61 74 6F 72 
  InnerClass: 
   public final $anonfun$1=class scala/xml/persistent/SetStorage$$anonfun$1 of class scala/xml/persistent/SetStorage
  minor version: 0
  major version: 49
  Constant pool:
Asciz	SourceFile;
Asciz	SetStorage.scala;
Asciz	scala$xml$persistent$SetStorage$$theSet;
Asciz	Lscala/collection/mutable/HashSet;;
Asciz	()Lscala/collection/mutable/HashSet;;
Asciz	Code;
Asciz	LineNumberTable;
Asciz	scala/xml/persistent/SetStorage;
class	scala/xml/persistent/SetStorage
NameAndType	scala$xml$persistent$SetStorage$$theSet:Lscala/collection/mutable/HashSet;
Field	scala/xml/persistent/SetStorage.scala$xml$persistent$SetStorage$$theSet:Lscala/collection/mutable/HashSet;
Asciz	scala$xml$persistent$SetStorage$$theSet_$eq;
Asciz	(Lscala/collection/mutable/HashSet;)V;
Asciz	$plus$eq;
Asciz	(Lscala/xml/Node;)V;
Asciz	dirty_$eq;
Asciz	(Z)V;
NameAndType	dirty_$eq:(Z)V
Method	scala/xml/persistent/SetStorage.dirty_$eq:(Z)V
Asciz	scala/collection/mutable/HashSet;
class	scala/collection/mutable/HashSet
Asciz	(Ljava/lang/Object;)Lscala/collection/mutable/HashSet;;
NameAndType	$plus$eq:(Ljava/lang/Object;)Lscala/collection/mutable/HashSet;
Method	scala/collection/mutable/HashSet.$plus$eq:(Ljava/lang/Object;)Lscala/collection/mutable/HashSet;
Asciz	this;
Asciz	Lscala/xml/persistent/SetStorage;;
Asciz	e;
Asciz	Lscala/xml/Node;;
Asciz	LocalVariableTable;
Asciz	$minus$eq;
NameAndType	$minus$eq:(Ljava/lang/Object;)Lscala/collection/mutable/HashSet;
Method	scala/collection/mutable/HashSet.$minus$eq:(Ljava/lang/Object;)Lscala/collection/mutable/HashSet;
Asciz	nodes;
Asciz	()Lscala/collection/Iterator;;
Asciz	scala/collection/mutable/FlatHashTable;
class	scala/collection/mutable/FlatHashTable
Asciz	iterator;
NameAndType	iterator:()Lscala/collection/Iterator;
InterfaceMethod	scala/collection/mutable/FlatHashTable.iterator:()Lscala/collection/Iterator;
Asciz	scala/collection/Iterator;
class	scala/collection/Iterator
Asciz	<init>;
Asciz	(Ljava/io/File;)V;
Asciz	scala/xml/persistent/CachedFileStorage;
class	scala/xml/persistent/CachedFileStorage
NameAndType	"<init>":(Ljava/io/File;)V
Method	scala/xml/persistent/CachedFileStorage."<init>":(Ljava/io/File;)V
Asciz	()V;
NameAndType	"<init>":()V
Method	scala/collection/mutable/HashSet."<init>":()V
Asciz	initialNodes;
NameAndType	initialNodes:()Lscala/collection/Iterator;
Method	scala/xml/persistent/CachedFileStorage.initialNodes:()Lscala/collection/Iterator;
Asciz	hasNext;
Asciz	()Z;
NameAndType	hasNext:()Z
InterfaceMethod	scala/collection/Iterator.hasNext:()Z
Asciz	scala/xml/persistent/SetStorage$$anonfun$1;
class	scala/xml/persistent/SetStorage$$anonfun$1
Asciz	(Lscala/xml/persistent/SetStorage;)V;
NameAndType	"<init>":(Lscala/xml/persistent/SetStorage;)V
Method	scala/xml/persistent/SetStorage$$anonfun$1."<init>":(Lscala/xml/persistent/SetStorage;)V
Asciz	foreach;
Asciz	(Lscala/Function1;)V;
NameAndType	foreach:(Lscala/Function1;)V
InterfaceMethod	scala/collection/Iterator.foreach:(Lscala/Function1;)V
Asciz	file;
Asciz	Ljava/io/File;;
Asciz	it;
Asciz	Lscala/collection/Iterator;;
Asciz	ScalaSig;
Asciz	InnerClasses;
Asciz	$anonfun$1;
Asciz	scala/ScalaObject;
class	scala/ScalaObject

{
private scala.collection.mutable.HashSet scala$xml$persistent$SetStorage$$theSet;
  Signature: Lscala/collection/mutable/HashSet;

public final scala.collection.mutable.HashSet scala$xml$persistent$SetStorage$$theSet();
  Signature: ()Lscala/collection/mutable/HashSet;
  Code:
   Stack=1, Locals=1, Args_size=1
	aload_0
	getfield	Field scala$xml$persistent$SetStorage$$theSet:Lscala/collection/mutable/HashSet;
	areturn
  Labels:

private void scala$xml$persistent$SetStorage$$theSet_$eq(scala.collection.mutable.HashSet);
  Signature: (Lscala/collection/mutable/HashSet;)V
  Code:
   Stack=2, Locals=2, Args_size=2
	aload_0
	aload_1
	putfield	Field scala$xml$persistent$SetStorage$$theSet:Lscala/collection/mutable/HashSet;
	return
  Labels:

public void $plus$eq(scala.xml.Node);
  Signature: (Lscala/xml/Node;)V
  Code:
   Stack=2, Locals=2, Args_size=2
	aload_0
	dup
	pop
	monitorenter
	aload_0
	iconst_1
	invokevirtual	Method dirty_$eq:(Z)V
	aload_0
	getfield	Field scala$xml$persistent$SetStorage$$theSet:Lscala/collection/mutable/HashSet;
	aload_1
	invokevirtual	Method scala/collection/mutable/HashSet.$plus$eq:(Ljava/lang/Object;)Lscala/collection/mutable/HashSet;
	pop
	aload_0
	monitorexit
	return
	aload_0
	monitorexit
	athrow
  Labels:
  Exception table:
   from   to  target type
     4    20    21   any
  LocalVariableTable: 
   Start  Length  Slot  Name   Signature
   0      24      0    this       Lscala/xml/persistent/SetStorage;
   0      24      1    e       Lscala/xml/Node;


public void $minus$eq(scala.xml.Node);
  Signature: (Lscala/xml/Node;)V
  Code:
   Stack=2, Locals=2, Args_size=2
	aload_0
	dup
	pop
	monitorenter
	aload_0
	iconst_1
	invokevirtual	Method dirty_$eq:(Z)V
	aload_0
	getfield	Field scala$xml$persistent$SetStorage$$theSet:Lscala/collection/mutable/HashSet;
	aload_1
	invokevirtual	Method scala/collection/mutable/HashSet.$minus$eq:(Ljava/lang/Object;)Lscala/collection/mutable/HashSet;
	pop
	aload_0
	monitorexit
	return
	aload_0
	monitorexit
	athrow
  Labels:
  Exception table:
   from   to  target type
     4    20    21   any
  LocalVariableTable: 
   Start  Length  Slot  Name   Signature
   0      24      0    this       Lscala/xml/persistent/SetStorage;
   0      24      1    e       Lscala/xml/Node;


public scala.collection.Iterator nodes();
  Signature: ()Lscala/collection/Iterator;
  Code:
   Stack=2, Locals=2, Args_size=1
	aload_0
	dup
	pop
	monitorenter
	aload_0
	getfield	Field scala$xml$persistent$SetStorage$$theSet:Lscala/collection/mutable/HashSet;
	invokeinterface	InterfaceMethod scala/collection/mutable/FlatHashTable.iterator:()Lscala/collection/Iterator;
	astore_1
	aload_0
	monitorexit
	aload_1
	checkcast	class scala/collection/Iterator
	areturn
	aload_0
	monitorexit
	athrow
  Labels:
  Exception table:
   from   to  target type
     4    16    21   any

public scala.xml.persistent.SetStorage(java.io.File);
  Signature: (Ljava/io/File;)V
  Code:
   Stack=4, Locals=3, Args_size=2
	aload_0
	aload_1
	invokespecial	Method scala/xml/persistent/CachedFileStorage."<init>":(Ljava/io/File;)V
	aload_0
	new	class scala/collection/mutable/HashSet
	dup
	invokespecial	Method scala/collection/mutable/HashSet."<init>":()V
	putfield	Field scala$xml$persistent$SetStorage$$theSet:Lscala/collection/mutable/HashSet;
	aload_0
	invokespecial	Method scala/xml/persistent/CachedFileStorage.initialNodes:()Lscala/collection/Iterator;
	astore_2
	aload_0
	aload_2
	invokeinterface	InterfaceMethod scala/collection/Iterator.hasNext:()Z
	invokevirtual	Method dirty_$eq:(Z)V
	aload_2
	new	class scala/xml/persistent/SetStorage$$anonfun$1
	dup
	aload_0
	invokespecial	Method scala/xml/persistent/SetStorage$$anonfun$1."<init>":(Lscala/xml/persistent/SetStorage;)V
	invokeinterface	InterfaceMethod scala/collection/Iterator.foreach:(Lscala/Function1;)V
	return
  Labels:
  LocalVariableTable: 
   Start  Length  Slot  Name   Signature
   0      46      0    this       Lscala/xml/persistent/SetStorage;
   0      46      1    file       Ljava/io/File;
   21      24      2    it       Lscala/collection/Iterator;


}

