Compiled from "ConsoleLogger.scala"
public abstract class scala.util.logging.ConsoleLogger$class extends java.lang.Object
  SourceFile: "ConsoleLogger.scala"
  Scala: length = 0x
   
  minor version: 0
  major version: 49
  Constant pool:
const #1 = Asciz	SourceFile;
const #2 = Asciz	ConsoleLogger.scala;
const #3 = Asciz	$init$;
const #4 = Asciz	(Lscala/util/logging/ConsoleLogger;)V;
const #5 = Asciz	Code;
const #6 = Asciz	LineNumberTable;
const #7 = Asciz	$this;
const #8 = Asciz	Lscala/util/logging/ConsoleLogger;;
const #9 = Asciz	LocalVariableTable;
const #10 = Asciz	log;
const #11 = Asciz	(Lscala/util/logging/ConsoleLogger;Ljava/lang/String;)V;
const #12 = Asciz	scala/Console$;
const #13 = class	#12;	//  scala/Console$
const #14 = Asciz	MODULE$;
const #15 = Asciz	Lscala/Console$;;
const #16 = NameAndType	#14:#15;//  MODULE$:Lscala/Console$;
const #17 = Field	#13.#16;	//  scala/Console$.MODULE$:Lscala/Console$;
const #18 = Asciz	println;
const #19 = Asciz	(Ljava/lang/Object;)V;
const #20 = NameAndType	#18:#19;//  println:(Ljava/lang/Object;)V
const #21 = Method	#13.#20;	//  scala/Console$.println:(Ljava/lang/Object;)V
const #22 = Asciz	msg;
const #23 = Asciz	Ljava/lang/String;;
const #24 = Asciz	Scala;
const #25 = Asciz	scala/util/logging/ConsoleLogger$class;
const #26 = class	#25;	//  scala/util/logging/ConsoleLogger$class
const #27 = Asciz	java/lang/Object;
const #28 = class	#27;	//  java/lang/Object

{
public static void $init$(scala.util.logging.ConsoleLogger);
  Code:
   Stack=0, Locals=1, Args_size=1
   0:	return
  LineNumberTable: 
   line 21: 0

  LocalVariableTable: 
   Start  Length  Slot  Name   Signature
   0      1      0    $this       Lscala/util/logging/ConsoleLogger;


public static void log(scala.util.logging.ConsoleLogger, java.lang.String);
  Code:
   Stack=2, Locals=2, Args_size=2
   0:	getstatic	#17; //Field scala/Console$.MODULE$:Lscala/Console$;
   3:	aload_1
   4:	invokevirtual	#21; //Method scala/Console$.println:(Ljava/lang/Object;)V
   7:	return
  LineNumberTable: 
   line 27: 0

  LocalVariableTable: 
   Start  Length  Slot  Name   Signature
   0      8      0    $this       Lscala/util/logging/ConsoleLogger;
   0      8      1    msg       Ljava/lang/String;


}

