Compiled from "Code.scala"
public class scala.mobile.Code extends java.lang.Object implements scala.ScalaObject
  SourceFile: "Code.scala"
  ScalaSig: length = 0xA0C
   05 00 FFFFFF82 54 06 08 01 02 FFFFFF84 FFFFFF80 FFFFFF80 FFFFFF80 00 07 02 04
   43 6F 64 65 0A 02 03 04 01 06 6D 6F 62 69 6C 65
   0A 01 05 01 05 73 63 61 6C 61 03 00 13 03 00 08
   10 10 02 09 0E 0D 01 0A 0A 02 0B 0C 01 04 6C 61
   6E 67 0A 01 0D 01 04 6A 61 76 61 09 02 0F 0A 02
   06 4F 62 6A 65 63 74 10 02 11 12 0D 01 04 09 02
   13 04 02 0B 53 63 61 6C 61 4F 62 6A 65 63 74 08
   08 15 00 FFFFFF82 FFFFFF80 FFFFFFA0 FFFFFF80 04 16 01 05 63 6C 61 7A 7A
   30 02 17 1C 10 03 09 18 1A 09 02 19 0A 02 05 43
   6C 61 73 73 10 02 1B 1C 0C 00 04 08 1D 00 FFFFFF84 FFFFFF80
   FFFFFF80 FFFFFF82 00 1E 02 03 5F 24 31 11 02 1F 22 10 02 11
   20 09 02 21 04 02 07 4E 6F 74 68 69 6E 67 10 02
   11 23 09 02 24 04 02 03 41 6E 79 08 05 26 00 FFFFFF84
   00 27 01 06 3C 69 6E 69 74 3E 14 02 28 2A 10 02
   29 00 0D 01 02 08 05 15 25 FFFFFFC0 00 2B 30 02 2C 2E
   10 03 09 18 2D 10 02 1B 2E 04 08 1D 25 FFFFFF84 FFFFFF80 FFFFFF80
   FFFFFF82 00 1E 05 08 30 00 FFFFFF84 FFFFFF80 FFFFFF80 FFFFFF80 04 08 02 07 4A
   4F 62 6A 65 63 74 08 07 32 00 FFFFFFC0 FFFFFF80 FFFFFF84 04 33 01
   08 69 6E 73 74 61 6E 63 65 15 01 34 10 02 35 2F
   0D 01 00 08 07 37 00 FFFFFFC0 FFFFFF80 FFFFFF84 04 38 01 0C 69 6E
   73 74 61 6E 63 65 5F 24 65 71 14 02 39 3C 10 02
   11 3A 09 02 3B 04 02 04 55 6E 69 74 08 07 3D 36
   FFFFFF81 FFFFFF80 FFFFFFC0 00 34 01 03 78 24 31 08 06 3F 00 FFFFFFA0 FFFFFFA0
   04 34 01 09 69 6E 73 74 61 6E 63 65 20 05 08 41
   00 FFFFFF84 FFFFFF80 FFFFFF80 FFFFFF80 00 42 02 08 41 6E 79 43 6C 61 73
   73 30 02 43 4A 10 03 44 47 49 0E 02 11 45 09 02
   46 04 01 06 50 72 65 64 65 66 09 02 19 48 0A 02
   46 04 10 02 1B 4A 04 08 4B 40 FFFFFF84 FFFFFF80 FFFFFF80 FFFFFF82 00 1E
   02 01 54 08 05 4D 00 FFFFFF84 00 4E 01 05 61 70 70 6C
   79 15 02 4F 54 14 02 50 56 10 03 11 51 53 09 02
   52 04 02 09 46 75 6E 63 74 69 6F 6E 30 10 02 1B
   54 04 08 55 4C FFFFFF84 FFFFFF80 FFFFFF80 FFFFFFC2 00 1E 02 01 52 08 05
   57 4C FFFFFFC0 00 58 01 07 66 75 6E 4E 61 6D 65 10 02
   44 59 09 02 5A 48 02 06 53 74 72 69 6E 67 08 05
   4D 00 FFFFFF84 00 5C 15 03 5D 62 65 14 02 5E 66 10 04
   11 5F 61 64 09 02 60 04 02 09 46 75 6E 63 74 69
   6F 6E 31 10 02 1B 62 04 08 63 5B FFFFFF84 FFFFFF80 FFFFFF80 FFFFFFC2 00
   1E 02 02 41 30 10 02 1B 65 04 08 55 5B FFFFFF84 FFFFFF80 FFFFFF80
   FFFFFFC2 00 1E 08 05 57 5B FFFFFFC0 00 58 08 05 4D 00 FFFFFF84 00
   68 15 04 69 6E 70 73 14 02 6A 74 10 05 11 6B 6D
   6F 72 09 02 6C 04 02 09 46 75 6E 63 74 69 6F 6E
   32 10 02 1B 6E 04 08 63 67 FFFFFF84 FFFFFF80 FFFFFF80 FFFFFFC2 00 1E 10
   02 1B 70 04 08 71 67 FFFFFF84 FFFFFF80 FFFFFF80 FFFFFFC2 00 1E 02 02 41
   31 10 02 1B 73 04 08 55 67 FFFFFF84 FFFFFF80 FFFFFF80 FFFFFFC2 00 1E 08
   05 57 67 FFFFFFC0 00 58 08 05 4D 00 FFFFFF84 00 76 15 07 77
   7C 7E FFFFFF81 00 FFFFFF81 03 14 03 78 FFFFFF81 04 10 07 11 79 7B
   7D 7F FFFFFF81 02 09 02 7A 04 02 09 46 75 6E 63 74 69
   6F 6E 33 10 02 1B 7C 04 08 63 75 FFFFFF84 FFFFFF80 FFFFFF80 FFFFFFC2 00
   1E 10 02 1B 7E 04 08 71 75 FFFFFF84 FFFFFF80 FFFFFF80 FFFFFFC2 00 1E 10
   03 1B FFFFFF81 00 04 09 FFFFFF81 01 75 FFFFFF84 FFFFFF80 FFFFFF80 FFFFFFC2 00 1E 02
   02 41 32 10 03 1B FFFFFF81 03 04 08 55 75 FFFFFF84 FFFFFF80 FFFFFF80 FFFFFFC2
   00 1E 08 05 57 75 FFFFFFC0 00 58 08 06 4D 00 FFFFFF84 00 FFFFFF81
   06 15 0C FFFFFF81 07 FFFFFF81 0C FFFFFF81 0E FFFFFF81 10 FFFFFF81 12 FFFFFF81 15 14
   04 FFFFFF81 08 FFFFFF81 16 10 0D 11 FFFFFF81 09 FFFFFF81 0B FFFFFF81 0D FFFFFF81 0F
   FFFFFF81 11 FFFFFF81 14 09 03 FFFFFF81 0A 04 02 09 46 75 6E 63 74
   69 6F 6E 34 10 03 1B FFFFFF81 0C 04 09 63 FFFFFF81 05 FFFFFF84 FFFFFF80
   FFFFFF80 FFFFFFC2 00 1E 10 03 1B FFFFFF81 0E 04 09 71 FFFFFF81 05 FFFFFF84 FFFFFF80
   FFFFFF80 FFFFFFC2 00 1E 10 03 1B FFFFFF81 10 04 0A FFFFFF81 01 FFFFFF81 05 FFFFFF84
   FFFFFF80 FFFFFF80 FFFFFFC2 00 1E 10 03 1B FFFFFF81 12 04 0A FFFFFF81 13 FFFFFF81 05
   FFFFFF84 FFFFFF80 FFFFFF80 FFFFFFC2 00 1E 02 02 41 33 10 03 1B FFFFFF81 15 04
   09 55 FFFFFF81 05 FFFFFF84 FFFFFF80 FFFFFF80 FFFFFFC2 00 1E 08 06 57 FFFFFF81 05 FFFFFFC0
   00 58 08 06 4D 00 FFFFFF84 00 FFFFFF81 18 15 0E FFFFFF81 19 FFFFFF81 1E
   FFFFFF81 20 FFFFFF81 22 FFFFFF81 24 FFFFFF81 26 FFFFFF81 29 14 04 FFFFFF81 1A FFFFFF81 2A
   10 0F 11 FFFFFF81 1B FFFFFF81 1D FFFFFF81 1F FFFFFF81 21 FFFFFF81 23 FFFFFF81 25 FFFFFF81
   28 09 03 FFFFFF81 1C 04 02 09 46 75 6E 63 74 69 6F 6E
   35 10 03 1B FFFFFF81 1E 04 09 63 FFFFFF81 17 FFFFFF84 FFFFFF80 FFFFFF80 FFFFFFC2 00
   1E 10 03 1B FFFFFF81 20 04 09 71 FFFFFF81 17 FFFFFF84 FFFFFF80 FFFFFF80 FFFFFFC2 00
   1E 10 03 1B FFFFFF81 22 04 0A FFFFFF81 01 FFFFFF81 17 FFFFFF84 FFFFFF80 FFFFFF80 FFFFFFC2
   00 1E 10 03 1B FFFFFF81 24 04 0A FFFFFF81 13 FFFFFF81 17 FFFFFF84 FFFFFF80 FFFFFF80
   FFFFFFC2 00 1E 10 03 1B FFFFFF81 26 04 0A FFFFFF81 27 FFFFFF81 17 FFFFFF84 FFFFFF80
   FFFFFF80 FFFFFFC2 00 1E 02 02 41 34 10 03 1B FFFFFF81 29 04 09 55
   FFFFFF81 17 FFFFFF84 FFFFFF80 FFFFFF80 FFFFFFC2 00 1E 08 06 57 FFFFFF81 17 FFFFFFC0 00 58
   08 06 4D 00 FFFFFF84 00 FFFFFF81 2C 15 10 FFFFFF81 2D FFFFFF81 32 FFFFFF81 34
   FFFFFF81 36 FFFFFF81 38 FFFFFF81 3A FFFFFF81 3C FFFFFF81 3F 14 04 FFFFFF81 2E FFFFFF81 40
   10 11 11 FFFFFF81 2F FFFFFF81 31 FFFFFF81 33 FFFFFF81 35 FFFFFF81 37 FFFFFF81 39 FFFFFF81
   3B FFFFFF81 3E 09 03 FFFFFF81 30 04 02 09 46 75 6E 63 74 69
   6F 6E 36 10 03 1B FFFFFF81 32 04 09 63 FFFFFF81 2B FFFFFF84 FFFFFF80 FFFFFF80
   FFFFFFC2 00 1E 10 03 1B FFFFFF81 34 04 09 71 FFFFFF81 2B FFFFFF84 FFFFFF80 FFFFFF80
   FFFFFFC2 00 1E 10 03 1B FFFFFF81 36 04 0A FFFFFF81 01 FFFFFF81 2B FFFFFF84 FFFFFF80
   FFFFFF80 FFFFFFC2 00 1E 10 03 1B FFFFFF81 38 04 0A FFFFFF81 13 FFFFFF81 2B FFFFFF84
   FFFFFF80 FFFFFF80 FFFFFFC2 00 1E 10 03 1B FFFFFF81 3A 04 0A FFFFFF81 27 FFFFFF81 2B
   FFFFFF84 FFFFFF80 FFFFFF80 FFFFFFC2 00 1E 10 03 1B FFFFFF81 3C 04 0A FFFFFF81 3D FFFFFF81
   2B FFFFFF84 FFFFFF80 FFFFFF80 FFFFFFC2 00 1E 02 02 41 35 10 03 1B FFFFFF81 3F
   04 09 55 FFFFFF81 2B FFFFFF84 FFFFFF80 FFFFFF80 FFFFFFC2 00 1E 08 06 57 FFFFFF81 2B
   FFFFFFC0 00 58 08 06 4D 00 FFFFFF84 00 FFFFFF81 42 15 12 FFFFFF81 43 FFFFFF81
   48 FFFFFF81 4A FFFFFF81 4C FFFFFF81 4E FFFFFF81 50 FFFFFF81 52 FFFFFF81 54 FFFFFF81 57 14
   04 FFFFFF81 44 FFFFFF81 58 10 13 11 FFFFFF81 45 FFFFFF81 47 FFFFFF81 49 FFFFFF81 4B
   FFFFFF81 4D FFFFFF81 4F FFFFFF81 51 FFFFFF81 53 FFFFFF81 56 09 03 FFFFFF81 46 04 02
   09 46 75 6E 63 74 69 6F 6E 37 10 03 1B FFFFFF81 48 04
   09 63 FFFFFF81 41 FFFFFF84 FFFFFF80 FFFFFF80 FFFFFFC2 00 1E 10 03 1B FFFFFF81 4A 04
   09 71 FFFFFF81 41 FFFFFF84 FFFFFF80 FFFFFF80 FFFFFFC2 00 1E 10 03 1B FFFFFF81 4C 04
   0A FFFFFF81 01 FFFFFF81 41 FFFFFF84 FFFFFF80 FFFFFF80 FFFFFFC2 00 1E 10 03 1B FFFFFF81 4E
   04 0A FFFFFF81 13 FFFFFF81 41 FFFFFF84 FFFFFF80 FFFFFF80 FFFFFFC2 00 1E 10 03 1B FFFFFF81
   50 04 0A FFFFFF81 27 FFFFFF81 41 FFFFFF84 FFFFFF80 FFFFFF80 FFFFFFC2 00 1E 10 03 1B
   FFFFFF81 52 04 0A FFFFFF81 3D FFFFFF81 41 FFFFFF84 FFFFFF80 FFFFFF80 FFFFFFC2 00 1E 10 03
   1B FFFFFF81 54 04 0A FFFFFF81 55 FFFFFF81 41 FFFFFF84 FFFFFF80 FFFFFF80 FFFFFFC2 00 1E 02
   02 41 36 10 03 1B FFFFFF81 57 04 09 55 FFFFFF81 41 FFFFFF84 FFFFFF80 FFFFFF80
   FFFFFFC2 00 1E 08 06 57 FFFFFF81 41 FFFFFFC0 00 58 08 06 4D 00 FFFFFF84
   00 FFFFFF81 5A 15 14 FFFFFF81 5B FFFFFF81 60 FFFFFF81 62 FFFFFF81 64 FFFFFF81 66 FFFFFF81
   68 FFFFFF81 6A FFFFFF81 6C FFFFFF81 6E FFFFFF81 71 14 04 FFFFFF81 5C FFFFFF81 72 10
   15 11 FFFFFF81 5D FFFFFF81 5F FFFFFF81 61 FFFFFF81 63 FFFFFF81 65 FFFFFF81 67 FFFFFF81 69
   FFFFFF81 6B FFFFFF81 6D FFFFFF81 70 09 03 FFFFFF81 5E 04 02 09 46 75 6E
   63 74 69 6F 6E 38 10 03 1B FFFFFF81 60 04 09 63 FFFFFF81 59
   FFFFFF84 FFFFFF80 FFFFFF80 FFFFFFC2 00 1E 10 03 1B FFFFFF81 62 04 09 71 FFFFFF81 59
   FFFFFF84 FFFFFF80 FFFFFF80 FFFFFFC2 00 1E 10 03 1B FFFFFF81 64 04 0A FFFFFF81 01 FFFFFF81
   59 FFFFFF84 FFFFFF80 FFFFFF80 FFFFFFC2 00 1E 10 03 1B FFFFFF81 66 04 0A FFFFFF81 13
   FFFFFF81 59 FFFFFF84 FFFFFF80 FFFFFF80 FFFFFFC2 00 1E 10 03 1B FFFFFF81 68 04 0A FFFFFF81
   27 FFFFFF81 59 FFFFFF84 FFFFFF80 FFFFFF80 FFFFFFC2 00 1E 10 03 1B FFFFFF81 6A 04 0A
   FFFFFF81 3D FFFFFF81 59 FFFFFF84 FFFFFF80 FFFFFF80 FFFFFFC2 00 1E 10 03 1B FFFFFF81 6C 04
   0A FFFFFF81 55 FFFFFF81 59 FFFFFF84 FFFFFF80 FFFFFF80 FFFFFFC2 00 1E 10 03 1B FFFFFF81 6E
   04 0A FFFFFF81 6F FFFFFF81 59 FFFFFF84 FFFFFF80 FFFFFF80 FFFFFFC2 00 1E 02 02 41 37
   10 03 1B FFFFFF81 71 04 09 55 FFFFFF81 59 FFFFFF84 FFFFFF80 FFFFFF80 FFFFFFC2 00 1E
   08 06 57 FFFFFF81 59 FFFFFFC0 00 58 08 06 4D 00 FFFFFF84 00 FFFFFF81 74
   15 16 FFFFFF81 75 FFFFFF81 7A FFFFFF81 7C FFFFFF81 7E FFFFFF82 00 FFFFFF82 02 FFFFFF82 04
   FFFFFF82 06 FFFFFF82 08 FFFFFF82 0A FFFFFF82 0D 14 04 FFFFFF81 76 FFFFFF82 0E 10 17
   11 FFFFFF81 77 FFFFFF81 79 FFFFFF81 7B FFFFFF81 7D FFFFFF81 7F FFFFFF82 01 FFFFFF82 03 FFFFFF82
   05 FFFFFF82 07 FFFFFF82 09 FFFFFF82 0C 09 03 FFFFFF81 78 04 02 09 46 75
   6E 63 74 69 6F 6E 39 10 03 1B FFFFFF81 7A 04 09 63 FFFFFF81
   73 FFFFFF84 FFFFFF80 FFFFFF80 FFFFFFC2 00 1E 10 03 1B FFFFFF81 7C 04 09 71 FFFFFF81
   73 FFFFFF84 FFFFFF80 FFFFFF80 FFFFFFC2 00 1E 10 03 1B FFFFFF81 7E 04 0A FFFFFF81 01
   FFFFFF81 73 FFFFFF84 FFFFFF80 FFFFFF80 FFFFFFC2 00 1E 10 03 1B FFFFFF82 00 04 0A FFFFFF81
   13 FFFFFF81 73 FFFFFF84 FFFFFF80 FFFFFF80 FFFFFFC2 00 1E 10 03 1B FFFFFF82 02 04 0A
   FFFFFF81 27 FFFFFF81 73 FFFFFF84 FFFFFF80 FFFFFF80 FFFFFFC2 00 1E 10 03 1B FFFFFF82 04 04
   0A FFFFFF81 3D FFFFFF81 73 FFFFFF84 FFFFFF80 FFFFFF80 FFFFFFC2 00 1E 10 03 1B FFFFFF82 06
   04 0A FFFFFF81 55 FFFFFF81 73 FFFFFF84 FFFFFF80 FFFFFF80 FFFFFFC2 00 1E 10 03 1B FFFFFF82
   08 04 0A FFFFFF81 6F FFFFFF81 73 FFFFFF84 FFFFFF80 FFFFFF80 FFFFFFC2 00 1E 10 03 1B
   FFFFFF82 0A 04 0A FFFFFF82 0B FFFFFF81 73 FFFFFF84 FFFFFF80 FFFFFF80 FFFFFFC2 00 1E 02 02
   41 38 10 03 1B FFFFFF82 0D 04 09 55 FFFFFF81 73 FFFFFF84 FFFFFF80 FFFFFF80 FFFFFFC2
   00 1E 08 06 57 FFFFFF81 73 FFFFFFC0 00 58 08 07 FFFFFF82 10 00 FFFFFF84
   04 FFFFFF82 11 01 08 62 6F 78 56 61 6C 75 65 14 04 FFFFFF82
   12 FFFFFF82 3B 30 04 FFFFFF82 13 FFFFFF82 38 10 06 11 FFFFFF82 14 08 FFFFFF82
   16 09 03 FFFFFF82 15 04 02 06 54 75 70 6C 65 32 30 04
   FFFFFF82 17 FFFFFF82 19 10 04 09 18 FFFFFF82 18 10 03 1B FFFFFF82 19 04
   0A FFFFFF82 1A 00 FFFFFF84 FFFFFF80 FFFFFF80 FFFFFF82 00 FFFFFF82 1B 02 04 5F 31 35
   39 11 03 FFFFFF82 1C 08 12 14 FFFFFF82 1D FFFFFF82 1F FFFFFF82 22 FFFFFF82 25
   FFFFFF82 28 FFFFFF82 2B FFFFFF82 2E FFFFFF82 31 FFFFFF82 34 FFFFFF82 37 06 0A FFFFFF82 1E
   00 FFFFFF84 FFFFFF80 FFFFFF80 FFFFFF80 00 FFFFFF82 1C 02 0C 3C 72 65 66 69 6E
   65 6D 65 6E 74 3E 10 03 09 FFFFFF82 20 09 03 FFFFFF82 21 0A
   02 04 42 79 74 65 10 03 09 FFFFFF82 23 09 03 FFFFFF82 24 0A
   02 07 42 6F 6F 6C 65 61 6E 10 03 09 FFFFFF82 26 09 03
   FFFFFF82 27 0A 02 09 43 68 61 72 61 63 74 65 72 10 03
   09 FFFFFF82 29 09 03 FFFFFF82 2A 0A 02 05 53 68 6F 72 74 10
   03 09 FFFFFF82 2C 09 03 FFFFFF82 2D 0A 02 07 49 6E 74 65 67
   65 72 10 03 09 FFFFFF82 2F 09 03 FFFFFF82 30 0A 02 04 4C 6F
   6E 67 10 03 09 FFFFFF82 32 09 03 FFFFFF82 33 0A 02 05 46 6C
   6F 61 74 10 03 09 FFFFFF82 35 09 03 FFFFFF82 36 0A 02 06 44
   6F 75 62 6C 65 10 03 1B FFFFFF82 38 04 0B FFFFFF82 39 FFFFFF82 0F
   FFFFFF84 FFFFFF80 FFFFFF80 FFFFFF82 00 FFFFFF82 3A 02 02 3F 30 11 02 1F 08 08
   07 FFFFFF82 3C FFFFFF82 0F FFFFFFC0 00 22 01 05 76 61 6C 75 65 08
   07 FFFFFF82 3E 00 FFFFFF84 04 FFFFFF82 3F 01 11 69 73 43 6F 6E 73
   74 72 75 63 74 6F 72 4E 61 6D 65 14 04 FFFFFF82 40 FFFFFF82
   42 10 03 11 FFFFFF82 41 09 03 FFFFFF82 24 04 08 07 FFFFFF82 43 FFFFFF82
   3D FFFFFFC0 00 58 01 08 6D 65 74 68 4E 61 6D 65 08 07
   FFFFFF82 45 00 FFFFFF84 04 FFFFFF82 46 01 08 61 70 70 6C 79 46 75
   6E 14 07 34 FFFFFF82 47 FFFFFF82 48 FFFFFF82 4D 08 07 FFFFFF82 43 FFFFFF82 44
   FFFFFFC0 00 58 08 08 FFFFFF82 49 FFFFFF82 44 FFFFFFC0 00 FFFFFF82 4A 01 04 61
   72 67 73 10 04 11 FFFFFF82 4B 34 09 03 FFFFFF82 4C 04 02 05
   41 72 72 61 79 08 08 FFFFFF82 4E FFFFFF82 44 FFFFFFC0 00 FFFFFF82 4F 01
   08 61 72 67 54 79 70 65 73 10 05 11 FFFFFF82 4B FFFFFF82 50
   30 04 FFFFFF82 51 FFFFFF82 53 10 04 44 47 FFFFFF82 52 10 03 1B FFFFFF82
   53 04 09 4B FFFFFF82 44 FFFFFF84 FFFFFF80 FFFFFF80 FFFFFF82 00 1E 
  InnerClass: 
   public final $anonfun$apply$1=class scala/mobile/Code$$anonfun$apply$1 of class scala/mobile/Code
   public final $anonfun$apply$2=class scala/mobile/Code$$anonfun$apply$2 of class scala/mobile/Code
   public final $anonfun$apply$3=class scala/mobile/Code$$anonfun$apply$3 of class scala/mobile/Code
   public final $anonfun$apply$4=class scala/mobile/Code$$anonfun$apply$4 of class scala/mobile/Code
   public final $anonfun$apply$5=class scala/mobile/Code$$anonfun$apply$5 of class scala/mobile/Code
   public final $anonfun$apply$6=class scala/mobile/Code$$anonfun$apply$6 of class scala/mobile/Code
   public final $anonfun$apply$7=class scala/mobile/Code$$anonfun$apply$7 of class scala/mobile/Code
   public final $anonfun$apply$8=class scala/mobile/Code$$anonfun$apply$8 of class scala/mobile/Code
   public final $anonfun$apply$9=class scala/mobile/Code$$anonfun$apply$9 of class scala/mobile/Code
   public final $anonfun$apply$10=class scala/mobile/Code$$anonfun$apply$10 of class scala/mobile/Code
  minor version: 0
  major version: 49
  Constant pool:
Asciz	SourceFile;
Asciz	Code.scala;
Asciz	instance;
Asciz	Ljava/lang/Object;;
Asciz	clazz;
Asciz	Ljava/lang/Class;;
Asciz	Ljava/lang/Class<*>;;
Asciz	Signature;
Asciz	<init>;
Asciz	(Ljava/lang/Class;)V;
Asciz	Code;
Asciz	LineNumberTable;
Asciz	scala/mobile/Code;
class	scala/mobile/Code
NameAndType	clazz:Ljava/lang/Class;
Field	scala/mobile/Code.clazz:Ljava/lang/Class;
Asciz	java/lang/Object;
class	java/lang/Object
Asciz	()V;
NameAndType	"<init>":()V
Method	java/lang/Object."<init>":()V
Asciz	this;
Asciz	Lscala/mobile/Code;;
Asciz	LocalVariableTable;
Asciz	(Ljava/lang/Class<*>;)V;
Asciz	liftedTree1$1;
Asciz	()Ljava/lang/Object;;
Asciz	java/lang/Class;
class	java/lang/Class
Asciz	newInstance;
NameAndType	newInstance:()Ljava/lang/Object;
Method	java/lang/Class.newInstance:()Ljava/lang/Object;
Asciz	getConstructors;
Asciz	()[Ljava/lang/reflect/Constructor;;
NameAndType	getConstructors:()[Ljava/lang/reflect/Constructor;
Method	java/lang/Class.getConstructors:()[Ljava/lang/reflect/Constructor;
Asciz	;
String	
Asciz	java/lang/reflect/Constructor;
class	java/lang/reflect/Constructor
Asciz	([Ljava/lang/Object;)Ljava/lang/Object;;
NameAndType	newInstance:([Ljava/lang/Object;)Ljava/lang/Object;
Method	java/lang/reflect/Constructor.newInstance:([Ljava/lang/Object;)Ljava/lang/Object;
Asciz	scala/collection/mutable/StringBuilder;
class	scala/collection/mutable/StringBuilder
Method	scala/collection/mutable/StringBuilder."<init>":()V
Asciz	class ;
String	class 
Asciz	append;
Asciz	(Ljava/lang/Object;)Lscala/collection/mutable/StringBuilder;;
NameAndType	append:(Ljava/lang/Object;)Lscala/collection/mutable/StringBuilder;
Method	scala/collection/mutable/StringBuilder.append:(Ljava/lang/Object;)Lscala/collection/mutable/StringBuilder;
Asciz	getName;
Asciz	()Ljava/lang/String;;
NameAndType	getName:()Ljava/lang/String;
Method	java/lang/Class.getName:()Ljava/lang/String;
Asciz	 has no public constructor;
String	 has no public constructor
Asciz	toString;
NameAndType	toString:()Ljava/lang/String;
Method	scala/collection/mutable/StringBuilder.toString:()Ljava/lang/String;
Asciz	java/lang/RuntimeException;
class	java/lang/RuntimeException
Asciz	(Ljava/lang/String;)V;
NameAndType	"<init>":(Ljava/lang/String;)V
Method	java/lang/RuntimeException."<init>":(Ljava/lang/String;)V
Asciz	cs;
Asciz	[Ljava/lang/reflect/Constructor;;
Asciz	exceptionResult3;
Asciz	scala$mobile$Code$$applyFun;
Asciz	(Ljava/lang/String;[Ljava/lang/Object;[Ljava/lang/Class;)Ljava/lang/Object;;
Asciz	getMethod;
Asciz	(Ljava/lang/String;[Ljava/lang/Class;)Ljava/lang/reflect/Method;;
NameAndType	getMethod:(Ljava/lang/String;[Ljava/lang/Class;)Ljava/lang/reflect/Method;
Method	java/lang/Class.getMethod:(Ljava/lang/String;[Ljava/lang/Class;)Ljava/lang/reflect/Method;
Asciz	java/lang/reflect/Method;
class	java/lang/reflect/Method
Asciz	getModifiers;
Asciz	()I;
NameAndType	getModifiers:()I
Method	java/lang/reflect/Method.getModifiers:()I
Asciz	java/lang/reflect/Modifier;
class	java/lang/reflect/Modifier
Asciz	isStatic;
Asciz	(I)Z;
NameAndType	isStatic:(I)Z
Method	java/lang/reflect/Modifier.isStatic:(I)Z
NameAndType	instance:()Ljava/lang/Object;
Method	scala/mobile/Code.instance:()Ljava/lang/Object;
NameAndType	liftedTree1$1:()Ljava/lang/Object;
Method	scala/mobile/Code.liftedTree1$1:()Ljava/lang/Object;
Asciz	instance_$eq;
Asciz	(Ljava/lang/Object;)V;
NameAndType	instance_$eq:(Ljava/lang/Object;)V
Method	scala/mobile/Code.instance_$eq:(Ljava/lang/Object;)V
Asciz	invoke;
Asciz	(Ljava/lang/Object;[Ljava/lang/Object;)Ljava/lang/Object;;
NameAndType	invoke:(Ljava/lang/Object;[Ljava/lang/Object;)Ljava/lang/Object;
Method	java/lang/reflect/Method.invoke:(Ljava/lang/Object;[Ljava/lang/Object;)Ljava/lang/Object;
Asciz	scala/runtime/BoxedUnit;
class	scala/runtime/BoxedUnit
Asciz	UNIT;
Asciz	Lscala/runtime/BoxedUnit;;
NameAndType	UNIT:Lscala/runtime/BoxedUnit;
Field	scala/runtime/BoxedUnit.UNIT:Lscala/runtime/BoxedUnit;
Asciz	scala/Console$;
class	scala/Console$
Asciz	MODULE$;
Asciz	Lscala/Console$;;
NameAndType	MODULE$:Lscala/Console$;
Field	scala/Console$.MODULE$:Lscala/Console$;
Asciz	java/lang/Exception;
class	java/lang/Exception
Asciz	getMessage;
NameAndType	getMessage:()Ljava/lang/String;
Method	java/lang/Exception.getMessage:()Ljava/lang/String;
Asciz	out;
Asciz	()Ljava/io/PrintStream;;
NameAndType	out:()Ljava/io/PrintStream;
Method	scala/Console$.out:()Ljava/io/PrintStream;
Asciz	java/io/PrintStream;
class	java/io/PrintStream
Asciz	println;
NameAndType	println:(Ljava/lang/Object;)V
Method	java/io/PrintStream.println:(Ljava/lang/Object;)V
Asciz	printStackTrace;
NameAndType	printStackTrace:()V
Method	java/lang/Exception.printStackTrace:()V
Asciz	isConstructorName;
Asciz	(Ljava/lang/String;)Z;
NameAndType	isConstructorName:(Ljava/lang/String;)Z
Method	scala/mobile/Code.isConstructorName:(Ljava/lang/String;)Z
Asciz	getConstructor;
Asciz	([Ljava/lang/Class;)Ljava/lang/reflect/Constructor;;
NameAndType	getConstructor:([Ljava/lang/Class;)Ljava/lang/reflect/Constructor;
Method	java/lang/Class.getConstructor:([Ljava/lang/Class;)Ljava/lang/reflect/Constructor;
Asciz	java/lang/NoSuchMethodException;
class	java/lang/NoSuchMethodException
Method	java/lang/NoSuchMethodException.getMessage:()Ljava/lang/String;
Method	java/lang/NoSuchMethodException.printStackTrace:()V
Asciz	methName;
Asciz	Ljava/lang/String;;
Asciz	args;
Asciz	[Ljava/lang/Object;;
Asciz	argTypes;
Asciz	[Ljava/lang/Class;;
Asciz	method;
Asciz	Ljava/lang/reflect/Method;;
Asciz	obj;
Asciz	result;
Asciz	cstr;
Asciz	Ljava/lang/reflect/Constructor;;
Asciz	exceptionResult1;
Asciz	.;
String	.
Asciz	java/lang/String;
class	java/lang/String
Asciz	lastIndexOf;
Asciz	(Ljava/lang/String;)I;
NameAndType	lastIndexOf:(Ljava/lang/String;)I
Method	java/lang/String.lastIndexOf:(Ljava/lang/String;)I
Asciz	length;
NameAndType	length:()I
Method	java/lang/String.length:()I
Asciz	substring;
Asciz	(II)Ljava/lang/String;;
NameAndType	substring:(II)Ljava/lang/String;
Method	java/lang/String.substring:(II)Ljava/lang/String;
Asciz	equals;
Asciz	(Ljava/lang/Object;)Z;
NameAndType	equals:(Ljava/lang/Object;)Z
Method	java/lang/String.equals:(Ljava/lang/Object;)Z
Asciz	className;
Asciz	classInx;
Asciz	I;
Asciz	methInx;
Asciz	scala$mobile$Code$$boxValue;
Asciz	(Ljava/lang/Object;)Lscala/Tuple2;;
Asciz	java/lang/Byte;
class	java/lang/Byte
Asciz	scala/runtime/BoxesRunTime;
class	scala/runtime/BoxesRunTime
Asciz	unboxToByte;
Asciz	(Ljava/lang/Object;)B;
NameAndType	unboxToByte:(Ljava/lang/Object;)B
Method	scala/runtime/BoxesRunTime.unboxToByte:(Ljava/lang/Object;)B
Asciz	scala/Tuple2;
class	scala/Tuple2
Asciz	valueOf;
Asciz	(B)Ljava/lang/Byte;;
NameAndType	valueOf:(B)Ljava/lang/Byte;
Method	java/lang/Byte.valueOf:(B)Ljava/lang/Byte;
Asciz	TYPE;
NameAndType	TYPE:Ljava/lang/Class;
Field	java/lang/Byte.TYPE:Ljava/lang/Class;
Asciz	(Ljava/lang/Object;Ljava/lang/Object;)V;
NameAndType	"<init>":(Ljava/lang/Object;Ljava/lang/Object;)V
Method	scala/Tuple2."<init>":(Ljava/lang/Object;Ljava/lang/Object;)V
Asciz	java/lang/Boolean;
class	java/lang/Boolean
Asciz	unboxToBoolean;
NameAndType	unboxToBoolean:(Ljava/lang/Object;)Z
Method	scala/runtime/BoxesRunTime.unboxToBoolean:(Ljava/lang/Object;)Z
Asciz	(Z)Ljava/lang/Boolean;;
NameAndType	valueOf:(Z)Ljava/lang/Boolean;
Method	java/lang/Boolean.valueOf:(Z)Ljava/lang/Boolean;
Field	java/lang/Boolean.TYPE:Ljava/lang/Class;
Asciz	java/lang/Character;
class	java/lang/Character
Asciz	unboxToChar;
Asciz	(Ljava/lang/Object;)C;
NameAndType	unboxToChar:(Ljava/lang/Object;)C
Method	scala/runtime/BoxesRunTime.unboxToChar:(Ljava/lang/Object;)C
Asciz	(C)Ljava/lang/Character;;
NameAndType	valueOf:(C)Ljava/lang/Character;
Method	java/lang/Character.valueOf:(C)Ljava/lang/Character;
Field	java/lang/Character.TYPE:Ljava/lang/Class;
Asciz	java/lang/Short;
class	java/lang/Short
Asciz	unboxToShort;
Asciz	(Ljava/lang/Object;)S;
NameAndType	unboxToShort:(Ljava/lang/Object;)S
Method	scala/runtime/BoxesRunTime.unboxToShort:(Ljava/lang/Object;)S
Asciz	(S)Ljava/lang/Short;;
NameAndType	valueOf:(S)Ljava/lang/Short;
Method	java/lang/Short.valueOf:(S)Ljava/lang/Short;
Field	java/lang/Short.TYPE:Ljava/lang/Class;
Asciz	java/lang/Integer;
class	java/lang/Integer
Asciz	unboxToInt;
Asciz	(Ljava/lang/Object;)I;
NameAndType	unboxToInt:(Ljava/lang/Object;)I
Method	scala/runtime/BoxesRunTime.unboxToInt:(Ljava/lang/Object;)I
Asciz	(I)Ljava/lang/Integer;;
NameAndType	valueOf:(I)Ljava/lang/Integer;
Method	java/lang/Integer.valueOf:(I)Ljava/lang/Integer;
Field	java/lang/Integer.TYPE:Ljava/lang/Class;
Asciz	java/lang/Long;
class	java/lang/Long
Asciz	unboxToLong;
Asciz	(Ljava/lang/Object;)J;
NameAndType	unboxToLong:(Ljava/lang/Object;)J
Method	scala/runtime/BoxesRunTime.unboxToLong:(Ljava/lang/Object;)J
Asciz	(J)Ljava/lang/Long;;
NameAndType	valueOf:(J)Ljava/lang/Long;
Method	java/lang/Long.valueOf:(J)Ljava/lang/Long;
Field	java/lang/Long.TYPE:Ljava/lang/Class;
Asciz	java/lang/Float;
class	java/lang/Float
Asciz	unboxToFloat;
Asciz	(Ljava/lang/Object;)F;
NameAndType	unboxToFloat:(Ljava/lang/Object;)F
Method	scala/runtime/BoxesRunTime.unboxToFloat:(Ljava/lang/Object;)F
Asciz	(F)Ljava/lang/Float;;
NameAndType	valueOf:(F)Ljava/lang/Float;
Method	java/lang/Float.valueOf:(F)Ljava/lang/Float;
Field	java/lang/Float.TYPE:Ljava/lang/Class;
Asciz	java/lang/Double;
class	java/lang/Double
Asciz	unboxToDouble;
Asciz	(Ljava/lang/Object;)D;
NameAndType	unboxToDouble:(Ljava/lang/Object;)D
Method	scala/runtime/BoxesRunTime.unboxToDouble:(Ljava/lang/Object;)D
Asciz	(D)Ljava/lang/Double;;
NameAndType	valueOf:(D)Ljava/lang/Double;
Method	java/lang/Double.valueOf:(D)Ljava/lang/Double;
Field	java/lang/Double.TYPE:Ljava/lang/Class;
Asciz	getClass;
Asciz	()Ljava/lang/Class;;
NameAndType	getClass:()Ljava/lang/Class;
Method	java/lang/Object.getClass:()Ljava/lang/Class;
Asciz	value;
Asciz	temp2;
Asciz	B;
Asciz	temp3;
Asciz	Z;
Asciz	temp4;
Asciz	C;
Asciz	temp5;
Asciz	S;
Asciz	temp6;
Asciz	temp7;
Asciz	J;
Asciz	temp8;
Asciz	F;
Asciz	temp9;
Asciz	D;
Asciz	apply;
Asciz	(Ljava/lang/String;)Lscala/Function9;;
Asciz	scala/mobile/Code$$anonfun$apply$10;
class	scala/mobile/Code$$anonfun$apply$10
Asciz	(Lscala/mobile/Code;Ljava/lang/String;)V;
NameAndType	"<init>":(Lscala/mobile/Code;Ljava/lang/String;)V
Method	scala/mobile/Code$$anonfun$apply$10."<init>":(Lscala/mobile/Code;Ljava/lang/String;)V
Asciz	funName$10;
Asciz	<A0:Ljava/lang/Object;A1:Ljava/lang/Object;A2:Ljava/lang/Object;A3:Ljava/lang/Object;A4:Ljava/lang/Object;A5:Ljava/lang/Object;A6:Ljava/lang/Object;A7:Ljava/lang/Object;A8:Ljava/lang/Object;R:Ljava/lang/Object;>(Ljava/lang/String;)Lscala/Function9<TA0;TA1;TA2;TA3;TA4;TA5;TA6;TA7;TA8;TR;>;;
Asciz	(Ljava/lang/String;)Lscala/Function8;;
Asciz	scala/mobile/Code$$anonfun$apply$9;
class	scala/mobile/Code$$anonfun$apply$9
Method	scala/mobile/Code$$anonfun$apply$9."<init>":(Lscala/mobile/Code;Ljava/lang/String;)V
Asciz	funName$9;
Asciz	<A0:Ljava/lang/Object;A1:Ljava/lang/Object;A2:Ljava/lang/Object;A3:Ljava/lang/Object;A4:Ljava/lang/Object;A5:Ljava/lang/Object;A6:Ljava/lang/Object;A7:Ljava/lang/Object;R:Ljava/lang/Object;>(Ljava/lang/String;)Lscala/Function8<TA0;TA1;TA2;TA3;TA4;TA5;TA6;TA7;TR;>;;
Asciz	(Ljava/lang/String;)Lscala/Function7;;
Asciz	scala/mobile/Code$$anonfun$apply$8;
class	scala/mobile/Code$$anonfun$apply$8
Method	scala/mobile/Code$$anonfun$apply$8."<init>":(Lscala/mobile/Code;Ljava/lang/String;)V
Asciz	funName$8;
Asciz	<A0:Ljava/lang/Object;A1:Ljava/lang/Object;A2:Ljava/lang/Object;A3:Ljava/lang/Object;A4:Ljava/lang/Object;A5:Ljava/lang/Object;A6:Ljava/lang/Object;R:Ljava/lang/Object;>(Ljava/lang/String;)Lscala/Function7<TA0;TA1;TA2;TA3;TA4;TA5;TA6;TR;>;;
Asciz	(Ljava/lang/String;)Lscala/Function6;;
Asciz	scala/mobile/Code$$anonfun$apply$7;
class	scala/mobile/Code$$anonfun$apply$7
Method	scala/mobile/Code$$anonfun$apply$7."<init>":(Lscala/mobile/Code;Ljava/lang/String;)V
Asciz	funName$7;
Asciz	<A0:Ljava/lang/Object;A1:Ljava/lang/Object;A2:Ljava/lang/Object;A3:Ljava/lang/Object;A4:Ljava/lang/Object;A5:Ljava/lang/Object;R:Ljava/lang/Object;>(Ljava/lang/String;)Lscala/Function6<TA0;TA1;TA2;TA3;TA4;TA5;TR;>;;
Asciz	(Ljava/lang/String;)Lscala/Function5;;
Asciz	scala/mobile/Code$$anonfun$apply$6;
class	scala/mobile/Code$$anonfun$apply$6
Method	scala/mobile/Code$$anonfun$apply$6."<init>":(Lscala/mobile/Code;Ljava/lang/String;)V
Asciz	funName$6;
Asciz	<A0:Ljava/lang/Object;A1:Ljava/lang/Object;A2:Ljava/lang/Object;A3:Ljava/lang/Object;A4:Ljava/lang/Object;R:Ljava/lang/Object;>(Ljava/lang/String;)Lscala/Function5<TA0;TA1;TA2;TA3;TA4;TR;>;;
Asciz	(Ljava/lang/String;)Lscala/Function4;;
Asciz	scala/mobile/Code$$anonfun$apply$5;
class	scala/mobile/Code$$anonfun$apply$5
Method	scala/mobile/Code$$anonfun$apply$5."<init>":(Lscala/mobile/Code;Ljava/lang/String;)V
Asciz	funName$5;
Asciz	<A0:Ljava/lang/Object;A1:Ljava/lang/Object;A2:Ljava/lang/Object;A3:Ljava/lang/Object;R:Ljava/lang/Object;>(Ljava/lang/String;)Lscala/Function4<TA0;TA1;TA2;TA3;TR;>;;
Asciz	(Ljava/lang/String;)Lscala/Function3;;
Asciz	scala/mobile/Code$$anonfun$apply$4;
class	scala/mobile/Code$$anonfun$apply$4
Method	scala/mobile/Code$$anonfun$apply$4."<init>":(Lscala/mobile/Code;Ljava/lang/String;)V
Asciz	funName$4;
Asciz	<A0:Ljava/lang/Object;A1:Ljava/lang/Object;A2:Ljava/lang/Object;R:Ljava/lang/Object;>(Ljava/lang/String;)Lscala/Function3<TA0;TA1;TA2;TR;>;;
Asciz	(Ljava/lang/String;)Lscala/Function2;;
Asciz	scala/mobile/Code$$anonfun$apply$3;
class	scala/mobile/Code$$anonfun$apply$3
Method	scala/mobile/Code$$anonfun$apply$3."<init>":(Lscala/mobile/Code;Ljava/lang/String;)V
Asciz	funName$3;
Asciz	<A0:Ljava/lang/Object;A1:Ljava/lang/Object;R:Ljava/lang/Object;>(Ljava/lang/String;)Lscala/Function2<TA0;TA1;TR;>;;
Asciz	(Ljava/lang/String;)Lscala/Function1;;
Asciz	scala/mobile/Code$$anonfun$apply$2;
class	scala/mobile/Code$$anonfun$apply$2
Method	scala/mobile/Code$$anonfun$apply$2."<init>":(Lscala/mobile/Code;Ljava/lang/String;)V
Asciz	funName$2;
Asciz	<A0:Ljava/lang/Object;R:Ljava/lang/Object;>(Ljava/lang/String;)Lscala/Function1<TA0;TR;>;;
Asciz	(Ljava/lang/String;)Lscala/Function0;;
Asciz	scala/mobile/Code$$anonfun$apply$1;
class	scala/mobile/Code$$anonfun$apply$1
Method	scala/mobile/Code$$anonfun$apply$1."<init>":(Lscala/mobile/Code;Ljava/lang/String;)V
Asciz	funName$1;
Asciz	<R:Ljava/lang/Object;>(Ljava/lang/String;)Lscala/Function0<TR;>;;
NameAndType	instance:Ljava/lang/Object;
Field	scala/mobile/Code.instance:Ljava/lang/Object;
Asciz	ScalaSig;
Asciz	InnerClasses;
Asciz	$anonfun$apply$1;
Asciz	$anonfun$apply$2;
Asciz	$anonfun$apply$3;
Asciz	$anonfun$apply$4;
Asciz	$anonfun$apply$5;
Asciz	$anonfun$apply$6;
Asciz	$anonfun$apply$7;
Asciz	$anonfun$apply$8;
Asciz	$anonfun$apply$9;
Asciz	$anonfun$apply$10;
Asciz	scala/ScalaObject;
class	scala/ScalaObject

{
private java.lang.Object instance;
  Signature: Ljava/lang/Object;

private final java.lang.Class clazz;
  Signature: Ljava/lang/Class;
  Signature: length = 0x2
   00 07 

public scala.mobile.Code(java.lang.Class);
  Signature: (Ljava/lang/Class;)V
  Code:
   Stack=2, Locals=2, Args_size=2
	aload_0
	aload_1
	putfield	Field clazz:Ljava/lang/Class;
	aload_0
	invokespecial	Method java/lang/Object."<init>":()V
	return
  Labels:
  LocalVariableTable: 
   Start  Length  Slot  Name   Signature
   0      10      0    this       Lscala/mobile/Code;
   0      10      1    clazz       Ljava/lang/Class;

  Signature: length = 0x2
   00 19 

private final java.lang.Object liftedTree1$1();
  Signature: ()Ljava/lang/Object;
  Code:
   Stack=5, Locals=4, Args_size=1
	aload_0
	getfield	Field clazz:Ljava/lang/Class;
	invokevirtual	Method java/lang/Class.newInstance:()Ljava/lang/Object;
	astore_2
	goto	l1 // aload_2
	pop
	aload_0
	getfield	Field clazz:Ljava/lang/Class;
	invokevirtual	Method java/lang/Class.getConstructors:()[Ljava/lang/reflect/Constructor;
	astore_1
	aload_1
	arraylength
	iconst_0
	if_icmple	l2 // new
	aload_1
	iconst_0
	aaload
	iconst_1
	anewarray	class java/lang/Object
	dup
	iconst_0
	ldc	String 
	aastore
	invokevirtual	Method java/lang/reflect/Constructor.newInstance:([Ljava/lang/Object;)Ljava/lang/Object;
	astore_2
l1	aload_2
	areturn
l2	new	class scala/collection/mutable/StringBuilder
	dup
	invokespecial	Method scala/collection/mutable/StringBuilder."<init>":()V
	ldc	String class 
	invokevirtual	Method scala/collection/mutable/StringBuilder.append:(Ljava/lang/Object;)Lscala/collection/mutable/StringBuilder;
	aload_0
	getfield	Field clazz:Ljava/lang/Class;
	invokevirtual	Method java/lang/Class.getName:()Ljava/lang/String;
	invokevirtual	Method scala/collection/mutable/StringBuilder.append:(Ljava/lang/Object;)Lscala/collection/mutable/StringBuilder;
	ldc	String  has no public constructor
	invokevirtual	Method scala/collection/mutable/StringBuilder.append:(Ljava/lang/Object;)Lscala/collection/mutable/StringBuilder;
	invokevirtual	Method scala/collection/mutable/StringBuilder.toString:()Ljava/lang/String;
	astore_3
	new	class java/lang/RuntimeException
	dup
	aload_3
	invokespecial	Method java/lang/RuntimeException."<init>":(Ljava/lang/String;)V
	athrow
  Labels:
   	l1 = 42 // aload_2
   	l2 = 44 // new
  Exception table:
   from   to  target type
     0    11    11   any
  LocalVariableTable: 
   Start  Length  Slot  Name   Signature
   0      84      0    this       Lscala/mobile/Code;
   20      22      1    cs       [Ljava/lang/reflect/Constructor;
   44      40      1    cs       [Ljava/lang/reflect/Constructor;
   0      43      2    exceptionResult3       Ljava/lang/Object;
   44      40      2    exceptionResult3       Ljava/lang/Object;


public final java.lang.Object scala$mobile$Code$$applyFun(java.lang.String, java.lang.Object[], java.lang.Class[]);
  Signature: (Ljava/lang/String;[Ljava/lang/Object;[Ljava/lang/Class;)Ljava/lang/Object;
  Code:
   Stack=3, Locals=18, Args_size=4
	aload_0
	getfield	Field clazz:Ljava/lang/Class;
	aload_1
	aload_3
	invokevirtual	Method java/lang/Class.getMethod:(Ljava/lang/String;[Ljava/lang/Class;)Ljava/lang/reflect/Method;
	astore	4
	aconst_null
	astore	5
	aload	4
	invokevirtual	Method java/lang/reflect/Method.getModifiers:()I
	invokestatic	Method java/lang/reflect/Modifier.isStatic:(I)Z
	ifne	l1 // aload
	aload_0
	invokespecial	Method instance:()Ljava/lang/Object;
	ifnonnull	l2 // aload_0
	aload_0
	aload_0
	invokespecial	Method liftedTree1$1:()Ljava/lang/Object;
	invokespecial	Method instance_$eq:(Ljava/lang/Object;)V
l2	aload_0
	invokespecial	Method instance:()Ljava/lang/Object;
	astore	5
l1	aload	4
	aload	5
	aload_2
	invokevirtual	Method java/lang/reflect/Method.invoke:(Ljava/lang/Object;[Ljava/lang/Object;)Ljava/lang/Object;
	astore	6
	aload	6
	ifnonnull	l3 // aload
	getstatic	Field scala/runtime/BoxedUnit.UNIT:Lscala/runtime/BoxedUnit;
	goto	l4 // astore
l3	aload	6
l4	astore	17
	goto	l5 // aload
	astore	9
	getstatic	Field scala/Console$.MODULE$:Lscala/Console$;
	aload	9
	invokevirtual	Method java/lang/Exception.getMessage:()Ljava/lang/String;
	astore	8
	astore	7
	aload	7
	invokevirtual	Method scala/Console$.out:()Ljava/io/PrintStream;
	aload	8
	invokevirtual	Method java/io/PrintStream.println:(Ljava/lang/Object;)V
	aload	9
	invokevirtual	Method java/lang/Exception.printStackTrace:()V
	aconst_null
	astore	17
	goto	l5 // aload
	astore	13
	aload_0
	aload_1
	invokespecial	Method isConstructorName:(Ljava/lang/String;)Z
	ifeq	l6 // getstatic
	aload_0
	getfield	Field clazz:Ljava/lang/Class;
	aload_3
	invokevirtual	Method java/lang/Class.getConstructor:([Ljava/lang/Class;)Ljava/lang/reflect/Constructor;
	astore	10
	aload_0
	aload	10
	aload_2
	invokevirtual	Method java/lang/reflect/Constructor.newInstance:([Ljava/lang/Object;)Ljava/lang/Object;
	invokespecial	Method instance_$eq:(Ljava/lang/Object;)V
	goto	l7 // aconst_null
l6	getstatic	Field scala/Console$.MODULE$:Lscala/Console$;
	aload	13
	invokevirtual	Method java/lang/NoSuchMethodException.getMessage:()Ljava/lang/String;
	astore	12
	astore	11
	aload	11
	invokevirtual	Method scala/Console$.out:()Ljava/io/PrintStream;
	aload	12
	invokevirtual	Method java/io/PrintStream.println:(Ljava/lang/Object;)V
	aload	13
	invokevirtual	Method java/lang/NoSuchMethodException.printStackTrace:()V
	goto	l7 // aconst_null
	astore	16
	getstatic	Field scala/Console$.MODULE$:Lscala/Console$;
	aload	16
	invokevirtual	Method java/lang/Exception.getMessage:()Ljava/lang/String;
	astore	15
	astore	14
	aload	14
	invokevirtual	Method scala/Console$.out:()Ljava/io/PrintStream;
	aload	15
	invokevirtual	Method java/io/PrintStream.println:(Ljava/lang/Object;)V
	aload	16
	invokevirtual	Method java/lang/Exception.printStackTrace:()V
l7	aconst_null
	astore	17
l5	aload	17
	areturn
  Labels:
   	l2 = 40 // aload_0
   	l1 = 46 // aload
   	l3 = 67 // aload
   	l4 = 69 // astore
   	l6 = 142 // getstatic
   	l7 = 201 // aconst_null
   	l5 = 204 // aload
  Exception table:
   from   to  target type
   119   142   172   Class java/lang/Exception

     0    74   109   Class java/lang/NoSuchMethodException

     0    74    74   Class java/lang/Exception

  LocalVariableTable: 
   Start  Length  Slot  Name   Signature
   0      207      0    this       Lscala/mobile/Code;
   0      207      1    methName       Ljava/lang/String;
   0      207      2    args       [Ljava/lang/Object;
   0      207      3    argTypes       [Ljava/lang/Class;
   11      63      4    method       Ljava/lang/reflect/Method;
   14      60      5    obj       Ljava/lang/Object;
   56      18      6    result       Ljava/lang/Object;
   129      10      10    cstr       Ljava/lang/reflect/Constructor;
   0      206      17    exceptionResult1       Ljava/lang/Object;


private boolean isConstructorName(java.lang.String);
  Signature: (Ljava/lang/String;)Z
  Code:
   Stack=3, Locals=5, Args_size=2
	aload_0
	getfield	Field clazz:Ljava/lang/Class;
	invokevirtual	Method java/lang/Class.getName:()Ljava/lang/String;
	astore_2
	aload_2
	ldc	String .
	invokevirtual	Method java/lang/String.lastIndexOf:(Ljava/lang/String;)I
	istore_3
	aload_1
	ldc	String .
	invokevirtual	Method java/lang/String.lastIndexOf:(Ljava/lang/String;)I
	istore	4
	iload_3
	iconst_0
	if_icmple	l1 // aload_1
	iload	4
	iconst_0
	if_icmpge	l1 // aload_1
	aload_2
	iload_3
	iconst_1
	iadd
	aload_2
	invokevirtual	Method java/lang/String.length:()I
	invokevirtual	Method java/lang/String.substring:(II)Ljava/lang/String;
	astore_2
l1	aload_1
	aload_2
	invokevirtual	Method java/lang/String.equals:(Ljava/lang/Object;)Z
	ireturn
  Labels:
   	l1 = 46 // aload_1
  LocalVariableTable: 
   Start  Length  Slot  Name   Signature
   0      52      0    this       Lscala/mobile/Code;
   0      52      1    methName       Ljava/lang/String;
   8      43      2    className       Ljava/lang/String;
   15      36      3    classInx       I
   23      28      4    methInx       I


public final scala.Tuple2 scala$mobile$Code$$boxValue(java.lang.Object);
  Signature: (Ljava/lang/Object;)Lscala/Tuple2;
  Code:
   Stack=4, Locals=12, Args_size=2
	aload_1
	instanceof	class java/lang/Byte
	ifeq	l1 // aload_1
	aload_1
	invokestatic	Method scala/runtime/BoxesRunTime.unboxToByte:(Ljava/lang/Object;)B
	istore_2
	new	class scala/Tuple2
	dup
	iload_2
	invokestatic	Method java/lang/Byte.valueOf:(B)Ljava/lang/Byte;
	getstatic	Field java/lang/Byte.TYPE:Ljava/lang/Class;
	invokespecial	Method scala/Tuple2."<init>":(Ljava/lang/Object;Ljava/lang/Object;)V
	goto	l2 // areturn
l1	aload_1
	instanceof	class java/lang/Boolean
	ifeq	l3 // aload_1
	aload_1
	invokestatic	Method scala/runtime/BoxesRunTime.unboxToBoolean:(Ljava/lang/Object;)Z
	istore_3
	new	class scala/Tuple2
	dup
	iload_3
	invokestatic	Method java/lang/Boolean.valueOf:(Z)Ljava/lang/Boolean;
	getstatic	Field java/lang/Boolean.TYPE:Ljava/lang/Class;
	invokespecial	Method scala/Tuple2."<init>":(Ljava/lang/Object;Ljava/lang/Object;)V
	goto	l2 // areturn
l3	aload_1
	instanceof	class java/lang/Character
	ifeq	l4 // aload_1
	aload_1
	invokestatic	Method scala/runtime/BoxesRunTime.unboxToChar:(Ljava/lang/Object;)C
	istore	4
	new	class scala/Tuple2
	dup
	iload	4
	invokestatic	Method java/lang/Character.valueOf:(C)Ljava/lang/Character;
	getstatic	Field java/lang/Character.TYPE:Ljava/lang/Class;
	invokespecial	Method scala/Tuple2."<init>":(Ljava/lang/Object;Ljava/lang/Object;)V
	goto	l2 // areturn
l4	aload_1
	instanceof	class java/lang/Short
	ifeq	l5 // aload_1
	aload_1
	invokestatic	Method scala/runtime/BoxesRunTime.unboxToShort:(Ljava/lang/Object;)S
	istore	5
	new	class scala/Tuple2
	dup
	iload	5
	invokestatic	Method java/lang/Short.valueOf:(S)Ljava/lang/Short;
	getstatic	Field java/lang/Short.TYPE:Ljava/lang/Class;
	invokespecial	Method scala/Tuple2."<init>":(Ljava/lang/Object;Ljava/lang/Object;)V
	goto	l2 // areturn
l5	aload_1
	instanceof	class java/lang/Integer
	ifeq	l6 // aload_1
	aload_1
	invokestatic	Method scala/runtime/BoxesRunTime.unboxToInt:(Ljava/lang/Object;)I
	istore	6
	new	class scala/Tuple2
	dup
	iload	6
	invokestatic	Method java/lang/Integer.valueOf:(I)Ljava/lang/Integer;
	getstatic	Field java/lang/Integer.TYPE:Ljava/lang/Class;
	invokespecial	Method scala/Tuple2."<init>":(Ljava/lang/Object;Ljava/lang/Object;)V
	goto	l2 // areturn
l6	aload_1
	instanceof	class java/lang/Long
	ifeq	l7 // aload_1
	aload_1
	invokestatic	Method scala/runtime/BoxesRunTime.unboxToLong:(Ljava/lang/Object;)J
	lstore	7
	new	class scala/Tuple2
	dup
	lload	7
	invokestatic	Method java/lang/Long.valueOf:(J)Ljava/lang/Long;
	getstatic	Field java/lang/Long.TYPE:Ljava/lang/Class;
	invokespecial	Method scala/Tuple2."<init>":(Ljava/lang/Object;Ljava/lang/Object;)V
	goto	l2 // areturn
l7	aload_1
	instanceof	class java/lang/Float
	ifeq	l8 // aload_1
	aload_1
	invokestatic	Method scala/runtime/BoxesRunTime.unboxToFloat:(Ljava/lang/Object;)F
	fstore	9
	new	class scala/Tuple2
	dup
	fload	9
	invokestatic	Method java/lang/Float.valueOf:(F)Ljava/lang/Float;
	getstatic	Field java/lang/Float.TYPE:Ljava/lang/Class;
	invokespecial	Method scala/Tuple2."<init>":(Ljava/lang/Object;Ljava/lang/Object;)V
	goto	l2 // areturn
l8	aload_1
	instanceof	class java/lang/Double
	ifeq	l9 // new
	aload_1
	invokestatic	Method scala/runtime/BoxesRunTime.unboxToDouble:(Ljava/lang/Object;)D
	dstore	10
	new	class scala/Tuple2
	dup
	dload	10
	invokestatic	Method java/lang/Double.valueOf:(D)Ljava/lang/Double;
	getstatic	Field java/lang/Double.TYPE:Ljava/lang/Class;
	invokespecial	Method scala/Tuple2."<init>":(Ljava/lang/Object;Ljava/lang/Object;)V
	goto	l2 // areturn
l9	new	class scala/Tuple2
	dup
	aload_1
	aload_1
	invokevirtual	Method java/lang/Object.getClass:()Ljava/lang/Class;
	invokespecial	Method scala/Tuple2."<init>":(Ljava/lang/Object;Ljava/lang/Object;)V
l2	areturn
  Labels:
   	l1 = 29 // aload_1
   	l3 = 58 // aload_1
   	l4 = 89 // aload_1
   	l5 = 120 // aload_1
   	l6 = 151 // aload_1
   	l7 = 182 // aload_1
   	l8 = 213 // aload_1
   	l9 = 244 // new
   	l2 = 256 // areturn
  LocalVariableTable: 
   Start  Length  Slot  Name   Signature
   0      257      0    this       Lscala/mobile/Code;
   0      257      1    value       Ljava/lang/Object;
   12      14      2    temp2       B
   41      14      3    temp3       Z
   71      15      4    temp4       C
   102      15      5    temp5       S
   133      15      6    temp6       I
   164      15      7    temp7       J
   195      15      9    temp8       F
   226      15      10    temp9       D


public scala.Function9 apply(java.lang.String);
  Signature: (Ljava/lang/String;)Lscala/Function9;
  Code:
   Stack=4, Locals=2, Args_size=2
	new	class scala/mobile/Code$$anonfun$apply$10
	dup
	aload_0
	aload_1
	invokespecial	Method scala/mobile/Code$$anonfun$apply$10."<init>":(Lscala/mobile/Code;Ljava/lang/String;)V
	areturn
  Labels:
  LocalVariableTable: 
   Start  Length  Slot  Name   Signature
   0      10      0    this       Lscala/mobile/Code;
   0      10      1    funName$10       Ljava/lang/String;

  Signature: length = 0x2
   01 28 

public scala.Function8 apply(java.lang.String);
  Signature: (Ljava/lang/String;)Lscala/Function8;
  Code:
   Stack=4, Locals=2, Args_size=2
	new	class scala/mobile/Code$$anonfun$apply$9
	dup
	aload_0
	aload_1
	invokespecial	Method scala/mobile/Code$$anonfun$apply$9."<init>":(Lscala/mobile/Code;Ljava/lang/String;)V
	areturn
  Labels:
  LocalVariableTable: 
   Start  Length  Slot  Name   Signature
   0      10      0    this       Lscala/mobile/Code;
   0      10      1    funName$9       Ljava/lang/String;

  Signature: length = 0x2
   01 2E 

public scala.Function7 apply(java.lang.String);
  Signature: (Ljava/lang/String;)Lscala/Function7;
  Code:
   Stack=4, Locals=2, Args_size=2
	new	class scala/mobile/Code$$anonfun$apply$8
	dup
	aload_0
	aload_1
	invokespecial	Method scala/mobile/Code$$anonfun$apply$8."<init>":(Lscala/mobile/Code;Ljava/lang/String;)V
	areturn
  Labels:
  LocalVariableTable: 
   Start  Length  Slot  Name   Signature
   0      10      0    this       Lscala/mobile/Code;
   0      10      1    funName$8       Ljava/lang/String;

  Signature: length = 0x2
   01 34 

public scala.Function6 apply(java.lang.String);
  Signature: (Ljava/lang/String;)Lscala/Function6;
  Code:
   Stack=4, Locals=2, Args_size=2
	new	class scala/mobile/Code$$anonfun$apply$7
	dup
	aload_0
	aload_1
	invokespecial	Method scala/mobile/Code$$anonfun$apply$7."<init>":(Lscala/mobile/Code;Ljava/lang/String;)V
	areturn
  Labels:
  LocalVariableTable: 
   Start  Length  Slot  Name   Signature
   0      10      0    this       Lscala/mobile/Code;
   0      10      1    funName$7       Ljava/lang/String;

  Signature: length = 0x2
   01 3A 

public scala.Function5 apply(java.lang.String);
  Signature: (Ljava/lang/String;)Lscala/Function5;
  Code:
   Stack=4, Locals=2, Args_size=2
	new	class scala/mobile/Code$$anonfun$apply$6
	dup
	aload_0
	aload_1
	invokespecial	Method scala/mobile/Code$$anonfun$apply$6."<init>":(Lscala/mobile/Code;Ljava/lang/String;)V
	areturn
  Labels:
  LocalVariableTable: 
   Start  Length  Slot  Name   Signature
   0      10      0    this       Lscala/mobile/Code;
   0      10      1    funName$6       Ljava/lang/String;

  Signature: length = 0x2
   01 40 

public scala.Function4 apply(java.lang.String);
  Signature: (Ljava/lang/String;)Lscala/Function4;
  Code:
   Stack=4, Locals=2, Args_size=2
	new	class scala/mobile/Code$$anonfun$apply$5
	dup
	aload_0
	aload_1
	invokespecial	Method scala/mobile/Code$$anonfun$apply$5."<init>":(Lscala/mobile/Code;Ljava/lang/String;)V
	areturn
  Labels:
  LocalVariableTable: 
   Start  Length  Slot  Name   Signature
   0      10      0    this       Lscala/mobile/Code;
   0      10      1    funName$5       Ljava/lang/String;

  Signature: length = 0x2
   01 46 

public scala.Function3 apply(java.lang.String);
  Signature: (Ljava/lang/String;)Lscala/Function3;
  Code:
   Stack=4, Locals=2, Args_size=2
	new	class scala/mobile/Code$$anonfun$apply$4
	dup
	aload_0
	aload_1
	invokespecial	Method scala/mobile/Code$$anonfun$apply$4."<init>":(Lscala/mobile/Code;Ljava/lang/String;)V
	areturn
  Labels:
  LocalVariableTable: 
   Start  Length  Slot  Name   Signature
   0      10      0    this       Lscala/mobile/Code;
   0      10      1    funName$4       Ljava/lang/String;

  Signature: length = 0x2
   01 4C 

public scala.Function2 apply(java.lang.String);
  Signature: (Ljava/lang/String;)Lscala/Function2;
  Code:
   Stack=4, Locals=2, Args_size=2
	new	class scala/mobile/Code$$anonfun$apply$3
	dup
	aload_0
	aload_1
	invokespecial	Method scala/mobile/Code$$anonfun$apply$3."<init>":(Lscala/mobile/Code;Ljava/lang/String;)V
	areturn
  Labels:
  LocalVariableTable: 
   Start  Length  Slot  Name   Signature
   0      10      0    this       Lscala/mobile/Code;
   0      10      1    funName$3       Ljava/lang/String;

  Signature: length = 0x2
   01 52 

public scala.Function1 apply(java.lang.String);
  Signature: (Ljava/lang/String;)Lscala/Function1;
  Code:
   Stack=4, Locals=2, Args_size=2
	new	class scala/mobile/Code$$anonfun$apply$2
	dup
	aload_0
	aload_1
	invokespecial	Method scala/mobile/Code$$anonfun$apply$2."<init>":(Lscala/mobile/Code;Ljava/lang/String;)V
	areturn
  Labels:
  LocalVariableTable: 
   Start  Length  Slot  Name   Signature
   0      10      0    this       Lscala/mobile/Code;
   0      10      1    funName$2       Ljava/lang/String;

  Signature: length = 0x2
   01 58 

public scala.Function0 apply(java.lang.String);
  Signature: (Ljava/lang/String;)Lscala/Function0;
  Code:
   Stack=4, Locals=2, Args_size=2
	new	class scala/mobile/Code$$anonfun$apply$1
	dup
	aload_0
	aload_1
	invokespecial	Method scala/mobile/Code$$anonfun$apply$1."<init>":(Lscala/mobile/Code;Ljava/lang/String;)V
	areturn
  Labels:
  LocalVariableTable: 
   Start  Length  Slot  Name   Signature
   0      10      0    this       Lscala/mobile/Code;
   0      10      1    funName$1       Ljava/lang/String;

  Signature: length = 0x2
   01 5E 

private void instance_$eq(java.lang.Object);
  Signature: (Ljava/lang/Object;)V
  Code:
   Stack=2, Locals=2, Args_size=2
	aload_0
	aload_1
	putfield	Field instance:Ljava/lang/Object;
	return
  Labels:

private java.lang.Object instance();
  Signature: ()Ljava/lang/Object;
  Code:
   Stack=1, Locals=1, Args_size=1
	aload_0
	getfield	Field instance:Ljava/lang/Object;
	areturn
  Labels:

}

