Compiled from "Code.scala"
public final class scala.mobile.Code$$anonfun$apply$10 extends java.lang.Object implements scala.Function9,scala.ScalaObject,java.io.Serializable
  SourceFile: "Code.scala"
  Scala: length = 0x
   
  InnerClass: 
   public final #141= #9 of #42; //$anonfun$apply$10=class scala/mobile/Code$$anonfun$apply$10 of class scala/mobile/Code
  minor version: 0
  major version: 49
  Constant pool:
const #1 = Asciz	SourceFile;
const #2 = Asciz	Code.scala;
const #3 = Asciz	<clinit>;
const #4 = Asciz	()V;
const #5 = Asciz	Code;
const #6 = Asciz	serialVersionUID;
const #7 = Asciz	J;
const #8 = Asciz	scala/mobile/Code$$anonfun$apply$10;
const #9 = class	#8;	//  scala/mobile/Code$$anonfun$apply$10
const #10 = NameAndType	#6:#7;//  serialVersionUID:J
const #11 = Field	#9.#10;	//  scala/mobile/Code$$anonfun$apply$10.serialVersionUID:J
const #12 = Asciz	funName$10;
const #13 = Asciz	Ljava/lang/String;;
const #14 = Asciz	$outer;
const #15 = Asciz	Lscala/mobile/Code;;
const #16 = Asciz	<init>;
const #17 = Asciz	(Lscala/mobile/Code;Ljava/lang/String;)V;
const #18 = Asciz	LineNumberTable;
const #19 = Asciz	java/lang/NullPointerException;
const #20 = class	#19;	//  java/lang/NullPointerException
const #21 = NameAndType	#16:#4;//  "<init>":()V
const #22 = Method	#20.#21;	//  java/lang/NullPointerException."<init>":()V
const #23 = NameAndType	#14:#15;//  $outer:Lscala/mobile/Code;
const #24 = Field	#9.#23;	//  scala/mobile/Code$$anonfun$apply$10.$outer:Lscala/mobile/Code;
const #25 = NameAndType	#12:#13;//  funName$10:Ljava/lang/String;
const #26 = Field	#9.#25;	//  scala/mobile/Code$$anonfun$apply$10.funName$10:Ljava/lang/String;
const #27 = Asciz	java/lang/Object;
const #28 = class	#27;	//  java/lang/Object
const #29 = Method	#28.#21;	//  java/lang/Object."<init>":()V
const #30 = Asciz	scala/Function9$class;
const #31 = class	#30;	//  scala/Function9$class
const #32 = Asciz	$init$;
const #33 = Asciz	(Lscala/Function9;)V;
const #34 = NameAndType	#32:#33;//  $init$:(Lscala/Function9;)V
const #35 = Method	#31.#34;	//  scala/Function9$class.$init$:(Lscala/Function9;)V
const #36 = Asciz	this;
const #37 = Asciz	Lscala/mobile/Code$$anonfun$apply$10;;
const #38 = Asciz	LocalVariableTable;
const #39 = Asciz	apply;
const #40 = Asciz	(Ljava/lang/Object;Ljava/lang/Object;Ljava/lang/Object;Ljava/lang/Object;Ljava/lang/Object;Ljava/lang/Object;Ljava/lang/Object;Ljava/lang/Object;Ljava/lang/Object;)Ljava/lang/Object;;
const #41 = Asciz	scala/mobile/Code;
const #42 = class	#41;	//  scala/mobile/Code
const #43 = Asciz	scala$mobile$Code$$boxValue;
const #44 = Asciz	(Ljava/lang/Object;)Lscala/Tuple2;;
const #45 = NameAndType	#43:#44;//  scala$mobile$Code$$boxValue:(Ljava/lang/Object;)Lscala/Tuple2;
const #46 = Method	#42.#45;	//  scala/mobile/Code.scala$mobile$Code$$boxValue:(Ljava/lang/Object;)Lscala/Tuple2;
const #47 = Asciz	scala/Array$;
const #48 = class	#47;	//  scala/Array$
const #49 = Asciz	MODULE$;
const #50 = Asciz	Lscala/Array$;;
const #51 = NameAndType	#49:#50;//  MODULE$:Lscala/Array$;
const #52 = Field	#48.#51;	//  scala/Array$.MODULE$:Lscala/Array$;
const #53 = Asciz	scala/Predef$;
const #54 = class	#53;	//  scala/Predef$
const #55 = Asciz	Lscala/Predef$;;
const #56 = NameAndType	#49:#55;//  MODULE$:Lscala/Predef$;
const #57 = Field	#54.#56;	//  scala/Predef$.MODULE$:Lscala/Predef$;
const #58 = int	9;
const #59 = Asciz	scala/Tuple2;
const #60 = class	#59;	//  scala/Tuple2
const #61 = Asciz	_1;
const #62 = Asciz	()Ljava/lang/Object;;
const #63 = NameAndType	#61:#62;//  _1:()Ljava/lang/Object;
const #64 = Method	#60.#63;	//  scala/Tuple2._1:()Ljava/lang/Object;
const #65 = int	6;
const #66 = int	7;
const #67 = int	8;
const #68 = Asciz	wrapRefArray;
const #69 = Asciz	([Ljava/lang/Object;)Lscala/collection/mutable/WrappedArray;;
const #70 = NameAndType	#68:#69;//  wrapRefArray:([Ljava/lang/Object;)Lscala/collection/mutable/WrappedArray;
const #71 = Method	#54.#70;	//  scala/Predef$.wrapRefArray:([Ljava/lang/Object;)Lscala/collection/mutable/WrappedArray;
const #72 = Asciz	scala/reflect/ClassManifest$;
const #73 = class	#72;	//  scala/reflect/ClassManifest$
const #74 = Asciz	Lscala/reflect/ClassManifest$;;
const #75 = NameAndType	#49:#74;//  MODULE$:Lscala/reflect/ClassManifest$;
const #76 = Field	#73.#75;	//  scala/reflect/ClassManifest$.MODULE$:Lscala/reflect/ClassManifest$;
const #77 = Asciz	classType;
const #78 = Asciz	(Ljava/lang/Class;)Lscala/reflect/ClassManifest;;
const #79 = NameAndType	#77:#78;//  classType:(Ljava/lang/Class;)Lscala/reflect/ClassManifest;
const #80 = Method	#73.#79;	//  scala/reflect/ClassManifest$.classType:(Ljava/lang/Class;)Lscala/reflect/ClassManifest;
const #81 = Asciz	(Lscala/collection/Seq;Lscala/reflect/ClassManifest;)Ljava/lang/Object;;
const #82 = NameAndType	#39:#81;//  apply:(Lscala/collection/Seq;Lscala/reflect/ClassManifest;)Ljava/lang/Object;
const #83 = Method	#48.#82;	//  scala/Array$.apply:(Lscala/collection/Seq;Lscala/reflect/ClassManifest;)Ljava/lang/Object;
const #84 = Asciz	[Ljava/lang/Object;;
const #85 = class	#84;	//  "[Ljava/lang/Object;"
const #86 = Asciz	java/lang/Class;
const #87 = class	#86;	//  java/lang/Class
const #88 = Asciz	_2;
const #89 = NameAndType	#88:#62;//  _2:()Ljava/lang/Object;
const #90 = Method	#60.#89;	//  scala/Tuple2._2:()Ljava/lang/Object;
const #91 = Asciz	scala/reflect/NoManifest$;
const #92 = class	#91;	//  scala/reflect/NoManifest$
const #93 = Asciz	Lscala/reflect/NoManifest$;;
const #94 = NameAndType	#49:#93;//  MODULE$:Lscala/reflect/NoManifest$;
const #95 = Field	#92.#94;	//  scala/reflect/NoManifest$.MODULE$:Lscala/reflect/NoManifest$;
const #96 = Asciz	scala/reflect/OptManifest;
const #97 = class	#96;	//  scala/reflect/OptManifest
const #98 = Asciz	(Ljava/lang/Class;Lscala/reflect/OptManifest;Lscala/collection/Seq;)Lscala/reflect/ClassManifest;;
const #99 = NameAndType	#77:#98;//  classType:(Ljava/lang/Class;Lscala/reflect/OptManifest;Lscala/collection/Seq;)Lscala/reflect/ClassManifest;
const #100 = Method	#73.#99;	//  scala/reflect/ClassManifest$.classType:(Ljava/lang/Class;Lscala/reflect/OptManifest;Lscala/collection/Seq;)Lscala/reflect/ClassManifest;
const #101 = Asciz	[Ljava/lang/Class;;
const #102 = class	#101;	//  "[Ljava/lang/Class;"
const #103 = Asciz	scala$mobile$Code$$applyFun;
const #104 = Asciz	(Ljava/lang/String;[Ljava/lang/Object;[Ljava/lang/Class;)Ljava/lang/Object;;
const #105 = NameAndType	#103:#104;//  scala$mobile$Code$$applyFun:(Ljava/lang/String;[Ljava/lang/Object;[Ljava/lang/Class;)Ljava/lang/Object;
const #106 = Method	#42.#105;	//  scala/mobile/Code.scala$mobile$Code$$applyFun:(Ljava/lang/String;[Ljava/lang/Object;[Ljava/lang/Class;)Ljava/lang/Object;
const #107 = Asciz	_0;
const #108 = Asciz	Ljava/lang/Object;;
const #109 = Asciz	_3;
const #110 = Asciz	_4;
const #111 = Asciz	_5;
const #112 = Asciz	_6;
const #113 = Asciz	_7;
const #114 = Asciz	_8;
const #115 = Asciz	p0;
const #116 = Asciz	Lscala/Tuple2;;
const #117 = Asciz	p1;
const #118 = Asciz	p2;
const #119 = Asciz	p3;
const #120 = Asciz	p4;
const #121 = Asciz	p5;
const #122 = Asciz	p6;
const #123 = Asciz	p7;
const #124 = Asciz	p8;
const #125 = Asciz	args;
const #126 = Asciz	types;
const #127 = Asciz	(TA0;TA1;TA2;TA3;TA4;TA5;TA6;TA7;TA8;)TR;;
const #128 = Asciz	Signature;
const #129 = Asciz	curry;
const #130 = Asciz	()Lscala/Function1;;
const #131 = Asciz	(Lscala/Function9;)Lscala/Function1;;
const #132 = NameAndType	#129:#131;//  curry:(Lscala/Function9;)Lscala/Function1;
const #133 = Method	#31.#132;	//  scala/Function9$class.curry:(Lscala/Function9;)Lscala/Function1;
const #134 = Asciz	toString;
const #135 = Asciz	()Ljava/lang/String;;
const #136 = Asciz	(Lscala/Function9;)Ljava/lang/String;;
const #137 = NameAndType	#134:#136;//  toString:(Lscala/Function9;)Ljava/lang/String;
const #138 = Method	#31.#137;	//  scala/Function9$class.toString:(Lscala/Function9;)Ljava/lang/String;
const #139 = Asciz	Scala;
const #140 = Asciz	InnerClasses;
const #141 = Asciz	$anonfun$apply$10;
const #142 = Asciz	scala/Function9;
const #143 = class	#142;	//  scala/Function9
const #144 = Asciz	scala/ScalaObject;
const #145 = class	#144;	//  scala/ScalaObject
const #146 = Asciz	java/io/Serializable;
const #147 = class	#146;	//  java/io/Serializable

{
public static final long serialVersionUID;

public static {};
  Code:
   Stack=2, Locals=0, Args_size=0
   0:	lconst_0
   1:	putstatic	#11; //Field serialVersionUID:J
   4:	return

public scala.mobile.Code$$anonfun$apply$10(scala.mobile.Code, java.lang.String);
  Code:
   Stack=2, Locals=3, Args_size=3
   0:	aload_1
   1:	ifnonnull	12
   4:	new	#20; //class java/lang/NullPointerException
   7:	dup
   8:	invokespecial	#22; //Method java/lang/NullPointerException."<init>":()V
   11:	athrow
   12:	aload_0
   13:	aload_1
   14:	putfield	#24; //Field $outer:Lscala/mobile/Code;
   17:	aload_0
   18:	aload_2
   19:	putfield	#26; //Field funName$10:Ljava/lang/String;
   22:	aload_0
   23:	invokespecial	#29; //Method java/lang/Object."<init>":()V
   26:	aload_0
   27:	invokestatic	#35; //Method scala/Function9$class.$init$:(Lscala/Function9;)V
   30:	return
  LineNumberTable: 
   line 145: 0

  LocalVariableTable: 
   Start  Length  Slot  Name   Signature
   0      31      0    this       Lscala/mobile/Code$$anonfun$apply$10;
   0      31      1    $outer       Lscala/mobile/Code;


public final java.lang.Object apply(java.lang.Object, java.lang.Object, java.lang.Object, java.lang.Object, java.lang.Object, java.lang.Object, java.lang.Object, java.lang.Object, java.lang.Object);
  Code:
   Stack=7, Locals=22, Args_size=10
   0:	aload_0
   1:	getfield	#24; //Field $outer:Lscala/mobile/Code;
   4:	astore	21
   6:	aload_0
   7:	getfield	#24; //Field $outer:Lscala/mobile/Code;
   10:	aload_1
   11:	invokevirtual	#46; //Method scala/mobile/Code.scala$mobile$Code$$boxValue:(Ljava/lang/Object;)Lscala/Tuple2;
   14:	astore	10
   16:	aload_0
   17:	getfield	#24; //Field $outer:Lscala/mobile/Code;
   20:	aload_2
   21:	invokevirtual	#46; //Method scala/mobile/Code.scala$mobile$Code$$boxValue:(Ljava/lang/Object;)Lscala/Tuple2;
   24:	astore	11
   26:	aload_0
   27:	getfield	#24; //Field $outer:Lscala/mobile/Code;
   30:	aload_3
   31:	invokevirtual	#46; //Method scala/mobile/Code.scala$mobile$Code$$boxValue:(Ljava/lang/Object;)Lscala/Tuple2;
   34:	astore	12
   36:	aload_0
   37:	getfield	#24; //Field $outer:Lscala/mobile/Code;
   40:	aload	4
   42:	invokevirtual	#46; //Method scala/mobile/Code.scala$mobile$Code$$boxValue:(Ljava/lang/Object;)Lscala/Tuple2;
   45:	astore	13
   47:	aload_0
   48:	getfield	#24; //Field $outer:Lscala/mobile/Code;
   51:	aload	5
   53:	invokevirtual	#46; //Method scala/mobile/Code.scala$mobile$Code$$boxValue:(Ljava/lang/Object;)Lscala/Tuple2;
   56:	astore	14
   58:	aload_0
   59:	getfield	#24; //Field $outer:Lscala/mobile/Code;
   62:	aload	6
   64:	invokevirtual	#46; //Method scala/mobile/Code.scala$mobile$Code$$boxValue:(Ljava/lang/Object;)Lscala/Tuple2;
   67:	astore	15
   69:	aload_0
   70:	getfield	#24; //Field $outer:Lscala/mobile/Code;
   73:	aload	7
   75:	invokevirtual	#46; //Method scala/mobile/Code.scala$mobile$Code$$boxValue:(Ljava/lang/Object;)Lscala/Tuple2;
   78:	astore	16
   80:	aload_0
   81:	getfield	#24; //Field $outer:Lscala/mobile/Code;
   84:	aload	8
   86:	invokevirtual	#46; //Method scala/mobile/Code.scala$mobile$Code$$boxValue:(Ljava/lang/Object;)Lscala/Tuple2;
   89:	astore	17
   91:	aload_0
   92:	getfield	#24; //Field $outer:Lscala/mobile/Code;
   95:	aload	9
   97:	invokevirtual	#46; //Method scala/mobile/Code.scala$mobile$Code$$boxValue:(Ljava/lang/Object;)Lscala/Tuple2;
   100:	astore	18
   102:	getstatic	#52; //Field scala/Array$.MODULE$:Lscala/Array$;
   105:	getstatic	#57; //Field scala/Predef$.MODULE$:Lscala/Predef$;
   108:	ldc	#58; //int 9
   110:	anewarray	#28; //class java/lang/Object
   113:	dup
   114:	iconst_0
   115:	aload	10
   117:	invokevirtual	#64; //Method scala/Tuple2._1:()Ljava/lang/Object;
   120:	aastore
   121:	dup
   122:	iconst_1
   123:	aload	11
   125:	invokevirtual	#64; //Method scala/Tuple2._1:()Ljava/lang/Object;
   128:	aastore
   129:	dup
   130:	iconst_2
   131:	aload	12
   133:	invokevirtual	#64; //Method scala/Tuple2._1:()Ljava/lang/Object;
   136:	aastore
   137:	dup
   138:	iconst_3
   139:	aload	13
   141:	invokevirtual	#64; //Method scala/Tuple2._1:()Ljava/lang/Object;
   144:	aastore
   145:	dup
   146:	iconst_4
   147:	aload	14
   149:	invokevirtual	#64; //Method scala/Tuple2._1:()Ljava/lang/Object;
   152:	aastore
   153:	dup
   154:	iconst_5
   155:	aload	15
   157:	invokevirtual	#64; //Method scala/Tuple2._1:()Ljava/lang/Object;
   160:	aastore
   161:	dup
   162:	ldc	#65; //int 6
   164:	aload	16
   166:	invokevirtual	#64; //Method scala/Tuple2._1:()Ljava/lang/Object;
   169:	aastore
   170:	dup
   171:	ldc	#66; //int 7
   173:	aload	17
   175:	invokevirtual	#64; //Method scala/Tuple2._1:()Ljava/lang/Object;
   178:	aastore
   179:	dup
   180:	ldc	#67; //int 8
   182:	aload	18
   184:	invokevirtual	#64; //Method scala/Tuple2._1:()Ljava/lang/Object;
   187:	aastore
   188:	invokevirtual	#71; //Method scala/Predef$.wrapRefArray:([Ljava/lang/Object;)Lscala/collection/mutable/WrappedArray;
   191:	getstatic	#76; //Field scala/reflect/ClassManifest$.MODULE$:Lscala/reflect/ClassManifest$;
   194:	ldc	#28; //class java/lang/Object
   196:	invokevirtual	#80; //Method scala/reflect/ClassManifest$.classType:(Ljava/lang/Class;)Lscala/reflect/ClassManifest;
   199:	invokevirtual	#83; //Method scala/Array$.apply:(Lscala/collection/Seq;Lscala/reflect/ClassManifest;)Ljava/lang/Object;
   202:	checkcast	#85; //class "[Ljava/lang/Object;"
   205:	astore	19
   207:	getstatic	#52; //Field scala/Array$.MODULE$:Lscala/Array$;
   210:	getstatic	#57; //Field scala/Predef$.MODULE$:Lscala/Predef$;
   213:	ldc	#58; //int 9
   215:	anewarray	#87; //class java/lang/Class
   218:	dup
   219:	iconst_0
   220:	aload	10
   222:	invokevirtual	#90; //Method scala/Tuple2._2:()Ljava/lang/Object;
   225:	checkcast	#87; //class java/lang/Class
   228:	aastore
   229:	dup
   230:	iconst_1
   231:	aload	11
   233:	invokevirtual	#90; //Method scala/Tuple2._2:()Ljava/lang/Object;
   236:	checkcast	#87; //class java/lang/Class
   239:	aastore
   240:	dup
   241:	iconst_2
   242:	aload	12
   244:	invokevirtual	#90; //Method scala/Tuple2._2:()Ljava/lang/Object;
   247:	checkcast	#87; //class java/lang/Class
   250:	aastore
   251:	dup
   252:	iconst_3
   253:	aload	13
   255:	invokevirtual	#90; //Method scala/Tuple2._2:()Ljava/lang/Object;
   258:	checkcast	#87; //class java/lang/Class
   261:	aastore
   262:	dup
   263:	iconst_4
   264:	aload	14
   266:	invokevirtual	#90; //Method scala/Tuple2._2:()Ljava/lang/Object;
   269:	checkcast	#87; //class java/lang/Class
   272:	aastore
   273:	dup
   274:	iconst_5
   275:	aload	15
   277:	invokevirtual	#90; //Method scala/Tuple2._2:()Ljava/lang/Object;
   280:	checkcast	#87; //class java/lang/Class
   283:	aastore
   284:	dup
   285:	ldc	#65; //int 6
   287:	aload	16
   289:	invokevirtual	#90; //Method scala/Tuple2._2:()Ljava/lang/Object;
   292:	checkcast	#87; //class java/lang/Class
   295:	aastore
   296:	dup
   297:	ldc	#66; //int 7
   299:	aload	17
   301:	invokevirtual	#90; //Method scala/Tuple2._2:()Ljava/lang/Object;
   304:	checkcast	#87; //class java/lang/Class
   307:	aastore
   308:	dup
   309:	ldc	#67; //int 8
   311:	aload	18
   313:	invokevirtual	#90; //Method scala/Tuple2._2:()Ljava/lang/Object;
   316:	checkcast	#87; //class java/lang/Class
   319:	aastore
   320:	checkcast	#85; //class "[Ljava/lang/Object;"
   323:	invokevirtual	#71; //Method scala/Predef$.wrapRefArray:([Ljava/lang/Object;)Lscala/collection/mutable/WrappedArray;
   326:	getstatic	#76; //Field scala/reflect/ClassManifest$.MODULE$:Lscala/reflect/ClassManifest$;
   329:	ldc	#87; //class java/lang/Class
   331:	getstatic	#95; //Field scala/reflect/NoManifest$.MODULE$:Lscala/reflect/NoManifest$;
   334:	getstatic	#57; //Field scala/Predef$.MODULE$:Lscala/Predef$;
   337:	iconst_0
   338:	anewarray	#97; //class scala/reflect/OptManifest
   341:	checkcast	#85; //class "[Ljava/lang/Object;"
   344:	invokevirtual	#71; //Method scala/Predef$.wrapRefArray:([Ljava/lang/Object;)Lscala/collection/mutable/WrappedArray;
   347:	invokevirtual	#100; //Method scala/reflect/ClassManifest$.classType:(Ljava/lang/Class;Lscala/reflect/OptManifest;Lscala/collection/Seq;)Lscala/reflect/ClassManifest;
   350:	invokevirtual	#83; //Method scala/Array$.apply:(Lscala/collection/Seq;Lscala/reflect/ClassManifest;)Ljava/lang/Object;
   353:	checkcast	#102; //class "[Ljava/lang/Class;"
   356:	astore	20
   358:	aload_0
   359:	getfield	#24; //Field $outer:Lscala/mobile/Code;
   362:	aload_0
   363:	getfield	#26; //Field funName$10:Ljava/lang/String;
   366:	aload	19
   368:	aload	20
   370:	invokevirtual	#106; //Method scala/mobile/Code.scala$mobile$Code$$applyFun:(Ljava/lang/String;[Ljava/lang/Object;[Ljava/lang/Class;)Ljava/lang/Object;
   373:	areturn
  LineNumberTable: 
   line 146: 0
   line 147: 16
   line 148: 26
   line 149: 36
   line 150: 47
   line 151: 58
   line 152: 69
   line 153: 80
   line 154: 91
   line 155: 102
   line 156: 207
   line 157: 358

  LocalVariableTable: 
   Start  Length  Slot  Name   Signature
   0      374      0    this       Lscala/mobile/Code$$anonfun$apply$10;
   6      368      1    _0       Ljava/lang/Object;
   6      368      2    _1       Ljava/lang/Object;
   6      368      3    _2       Ljava/lang/Object;
   6      368      4    _3       Ljava/lang/Object;
   6      368      5    _4       Ljava/lang/Object;
   6      368      6    _5       Ljava/lang/Object;
   6      368      7    _6       Ljava/lang/Object;
   6      368      8    _7       Ljava/lang/Object;
   6      368      9    _8       Ljava/lang/Object;
   16      357      10    p0       Lscala/Tuple2;
   26      347      11    p1       Lscala/Tuple2;
   36      337      12    p2       Lscala/Tuple2;
   47      326      13    p3       Lscala/Tuple2;
   58      315      14    p4       Lscala/Tuple2;
   69      304      15    p5       Lscala/Tuple2;
   80      293      16    p6       Lscala/Tuple2;
   91      282      17    p7       Lscala/Tuple2;
   102      271      18    p8       Lscala/Tuple2;
   207      166      19    args       [Ljava/lang/Object;
   358      15      20    types       [Ljava/lang/Class;

  Signature: length = 0x2
   00 7F 

public scala.Function1 curry();
  Code:
   Stack=1, Locals=1, Args_size=1
   0:	aload_0
   1:	invokestatic	#133; //Method scala/Function9$class.curry:(Lscala/Function9;)Lscala/Function1;
   4:	areturn
  LineNumberTable: 
   line 145: 0


public java.lang.String toString();
  Code:
   Stack=1, Locals=1, Args_size=1
   0:	aload_0
   1:	invokestatic	#138; //Method scala/Function9$class.toString:(Lscala/Function9;)Ljava/lang/String;
   4:	areturn
  LineNumberTable: 
   line 145: 0


}

