Compiled from "Code.scala"
public class scala.mobile.Code extends java.lang.Object implements scala.ScalaObject
  SourceFile: "Code.scala"
  ScalaSig: length = 0xA0A
   05 00 FFFFFF82 54 06 08 01 02 FFFFFF84 FFFFFF80 FFFFFF80 FFFFFF80 00 07 02 04
   43 6F 64 65 0A 02 03 04 01 06 6D 6F 62 69 6C 65
   0A 01 05 01 05 73 63 61 6C 61 03 00 13 03 00 08
   10 10 02 09 0E 0D 01 0A 0A 02 0B 0C 01 04 6C 61
   6E 67 0A 01 0D 01 04 6A 61 76 61 09 02 0F 0A 02
   06 4F 62 6A 65 63 74 10 02 11 12 0D 01 04 09 02
   13 04 02 0B 53 63 61 6C 61 4F 62 6A 65 63 74 08
   08 15 00 FFFFFF82 FFFFFF80 FFFFFFA0 FFFFFF80 04 16 01 05 63 6C 61 7A 7A
   30 02 17 1C 10 03 09 18 1A 09 02 19 0A 02 05 43
   6C 61 73 73 10 02 1B 1C 0C 00 04 08 1D 00 FFFFFF84 FFFFFF80
   FFFFFF80 FFFFFF82 00 1E 02 03 5F 24 31 11 02 1F 22 10 02 11
   20 09 02 21 04 02 07 4E 6F 74 68 69 6E 67 10 02
   11 23 09 02 24 04 02 03 41 6E 79 08 05 26 00 FFFFFF84
   00 27 01 06 3C 69 6E 69 74 3E 14 02 28 2A 10 02
   29 00 0D 01 02 08 05 15 25 FFFFFFC0 00 2B 30 02 2C 2E
   10 03 09 18 2D 10 02 1B 2E 04 08 1D 00 FFFFFF84 FFFFFF80 FFFFFF80
   FFFFFF82 00 1E 05 08 30 00 FFFFFF84 FFFFFF80 FFFFFF80 FFFFFF80 04 08 02 07 4A
   4F 62 6A 65 63 74 08 07 32 00 FFFFFFC0 FFFFFF80 FFFFFF84 04 33 01
   08 69 6E 73 74 61 6E 63 65 15 01 34 10 02 35 2F
   0D 01 00 08 07 37 00 FFFFFFC0 FFFFFF80 FFFFFF84 04 38 01 0C 69 6E
   73 74 61 6E 63 65 5F 24 65 71 14 02 39 3C 10 02
   11 3A 09 02 3B 04 02 04 55 6E 69 74 08 07 3D 36
   FFFFFF81 FFFFFF80 FFFFFFC0 00 34 01 03 78 24 31 08 06 3F 00 FFFFFFA0 FFFFFFA0
   04 34 01 09 69 6E 73 74 61 6E 63 65 20 05 08 41
   00 FFFFFF84 FFFFFF80 FFFFFF80 FFFFFF80 00 42 02 08 41 6E 79 43 6C 61 73
   73 30 02 43 4A 10 03 44 47 49 0E 02 11 45 09 02
   46 04 01 06 50 72 65 64 65 66 09 02 19 48 0A 02
   46 04 10 02 1B 4A 04 08 4B 00 FFFFFF84 FFFFFF80 FFFFFF80 FFFFFF82 00 1E
   02 01 54 08 05 4D 00 FFFFFF84 00 4E 01 05 61 70 70 6C
   79 15 02 4F 54 14 02 50 56 10 03 11 51 53 09 02
   52 04 02 09 46 75 6E 63 74 69 6F 6E 30 10 02 1B
   54 04 08 55 4C FFFFFF84 FFFFFF80 FFFFFF80 FFFFFFC2 00 1E 02 01 52 08 05
   57 4C FFFFFFC0 00 58 01 07 66 75 6E 4E 61 6D 65 10 02
   44 59 09 02 5A 48 02 06 53 74 72 69 6E 67 08 05
   4D 00 FFFFFF84 00 5C 15 03 5D 62 65 14 02 5E 66 10 04
   11 5F 61 64 09 02 60 04 02 09 46 75 6E 63 74 69
   6F 6E 31 10 02 1B 62 04 08 63 5B FFFFFF84 FFFFFF80 FFFFFF80 FFFFFFC2 00
   1E 02 02 41 30 10 02 1B 65 04 08 55 5B FFFFFF84 FFFFFF80 FFFFFF80
   FFFFFFC2 00 1E 08 05 57 5B FFFFFFC0 00 58 08 05 4D 00 FFFFFF84 00
   68 15 04 69 6E 70 73 14 02 6A 74 10 05 11 6B 6D
   6F 72 09 02 6C 04 02 09 46 75 6E 63 74 69 6F 6E
   32 10 02 1B 6E 04 08 63 67 FFFFFF84 FFFFFF80 FFFFFF80 FFFFFFC2 00 1E 10
   02 1B 70 04 08 71 67 FFFFFF84 FFFFFF80 FFFFFF80 FFFFFFC2 00 1E 02 02 41
   31 10 02 1B 73 04 08 55 67 FFFFFF84 FFFFFF80 FFFFFF80 FFFFFFC2 00 1E 08
   05 57 67 FFFFFFC0 00 58 08 05 4D 00 FFFFFF84 00 76 15 07 77
   7C 7E FFFFFF81 00 FFFFFF81 03 14 03 78 FFFFFF81 04 10 07 11 79 7B
   7D 7F FFFFFF81 02 09 02 7A 04 02 09 46 75 6E 63 74 69
   6F 6E 33 10 02 1B 7C 04 08 63 75 FFFFFF84 FFFFFF80 FFFFFF80 FFFFFFC2 00
   1E 10 02 1B 7E 04 08 71 75 FFFFFF84 FFFFFF80 FFFFFF80 FFFFFFC2 00 1E 10
   03 1B FFFFFF81 00 04 09 FFFFFF81 01 75 FFFFFF84 FFFFFF80 FFFFFF80 FFFFFFC2 00 1E 02
   02 41 32 10 03 1B FFFFFF81 03 04 08 55 75 FFFFFF84 FFFFFF80 FFFFFF80 FFFFFFC2
   00 1E 08 05 57 75 FFFFFFC0 00 58 08 06 4D 00 FFFFFF84 00 FFFFFF81
   06 15 0C FFFFFF81 07 FFFFFF81 0C FFFFFF81 0E FFFFFF81 10 FFFFFF81 12 FFFFFF81 15 14
   04 FFFFFF81 08 FFFFFF81 16 10 0D 11 FFFFFF81 09 FFFFFF81 0B FFFFFF81 0D FFFFFF81 0F
   FFFFFF81 11 FFFFFF81 14 09 03 FFFFFF81 0A 04 02 09 46 75 6E 63 74
   69 6F 6E 34 10 03 1B FFFFFF81 0C 04 09 63 FFFFFF81 05 FFFFFF84 FFFFFF80
   FFFFFF80 FFFFFFC2 00 1E 10 03 1B FFFFFF81 0E 04 09 71 FFFFFF81 05 FFFFFF84 FFFFFF80
   FFFFFF80 FFFFFFC2 00 1E 10 03 1B FFFFFF81 10 04 0A FFFFFF81 01 FFFFFF81 05 FFFFFF84
   FFFFFF80 FFFFFF80 FFFFFFC2 00 1E 10 03 1B FFFFFF81 12 04 0A FFFFFF81 13 FFFFFF81 05
   FFFFFF84 FFFFFF80 FFFFFF80 FFFFFFC2 00 1E 02 02 41 33 10 03 1B FFFFFF81 15 04
   09 55 FFFFFF81 05 FFFFFF84 FFFFFF80 FFFFFF80 FFFFFFC2 00 1E 08 06 57 FFFFFF81 05 FFFFFFC0
   00 58 08 06 4D 00 FFFFFF84 00 FFFFFF81 18 15 0E FFFFFF81 19 FFFFFF81 1E
   FFFFFF81 20 FFFFFF81 22 FFFFFF81 24 FFFFFF81 26 FFFFFF81 29 14 04 FFFFFF81 1A FFFFFF81 2A
   10 0F 11 FFFFFF81 1B FFFFFF81 1D FFFFFF81 1F FFFFFF81 21 FFFFFF81 23 FFFFFF81 25 FFFFFF81
   28 09 03 FFFFFF81 1C 04 02 09 46 75 6E 63 74 69 6F 6E
   35 10 03 1B FFFFFF81 1E 04 09 63 FFFFFF81 17 FFFFFF84 FFFFFF80 FFFFFF80 FFFFFFC2 00
   1E 10 03 1B FFFFFF81 20 04 09 71 FFFFFF81 17 FFFFFF84 FFFFFF80 FFFFFF80 FFFFFFC2 00
   1E 10 03 1B FFFFFF81 22 04 0A FFFFFF81 01 FFFFFF81 17 FFFFFF84 FFFFFF80 FFFFFF80 FFFFFFC2
   00 1E 10 03 1B FFFFFF81 24 04 0A FFFFFF81 13 FFFFFF81 17 FFFFFF84 FFFFFF80 FFFFFF80
   FFFFFFC2 00 1E 10 03 1B FFFFFF81 26 04 0A FFFFFF81 27 FFFFFF81 17 FFFFFF84 FFFFFF80
   FFFFFF80 FFFFFFC2 00 1E 02 02 41 34 10 03 1B FFFFFF81 29 04 09 55
   FFFFFF81 17 FFFFFF84 FFFFFF80 FFFFFF80 FFFFFFC2 00 1E 08 06 57 FFFFFF81 17 FFFFFFC0 00 58
   08 06 4D 00 FFFFFF84 00 FFFFFF81 2C 15 10 FFFFFF81 2D FFFFFF81 32 FFFFFF81 34
   FFFFFF81 36 FFFFFF81 38 FFFFFF81 3A FFFFFF81 3C FFFFFF81 3F 14 04 FFFFFF81 2E FFFFFF81 40
   10 11 11 FFFFFF81 2F FFFFFF81 31 FFFFFF81 33 FFFFFF81 35 FFFFFF81 37 FFFFFF81 39 FFFFFF81
   3B FFFFFF81 3E 09 03 FFFFFF81 30 04 02 09 46 75 6E 63 74 69
   6F 6E 36 10 03 1B FFFFFF81 32 04 09 63 FFFFFF81 2B FFFFFF84 FFFFFF80 FFFFFF80
   FFFFFFC2 00 1E 10 03 1B FFFFFF81 34 04 09 71 FFFFFF81 2B FFFFFF84 FFFFFF80 FFFFFF80
   FFFFFFC2 00 1E 10 03 1B FFFFFF81 36 04 0A FFFFFF81 01 FFFFFF81 2B FFFFFF84 FFFFFF80
   FFFFFF80 FFFFFFC2 00 1E 10 03 1B FFFFFF81 38 04 0A FFFFFF81 13 FFFFFF81 2B FFFFFF84
   FFFFFF80 FFFFFF80 FFFFFFC2 00 1E 10 03 1B FFFFFF81 3A 04 0A FFFFFF81 27 FFFFFF81 2B
   FFFFFF84 FFFFFF80 FFFFFF80 FFFFFFC2 00 1E 10 03 1B FFFFFF81 3C 04 0A FFFFFF81 3D FFFFFF81
   2B FFFFFF84 FFFFFF80 FFFFFF80 FFFFFFC2 00 1E 02 02 41 35 10 03 1B FFFFFF81 3F
   04 09 55 FFFFFF81 2B FFFFFF84 FFFFFF80 FFFFFF80 FFFFFFC2 00 1E 08 06 57 FFFFFF81 2B
   FFFFFFC0 00 58 08 06 4D 00 FFFFFF84 00 FFFFFF81 42 15 12 FFFFFF81 43 FFFFFF81
   48 FFFFFF81 4A FFFFFF81 4C FFFFFF81 4E FFFFFF81 50 FFFFFF81 52 FFFFFF81 54 FFFFFF81 57 14
   04 FFFFFF81 44 FFFFFF81 58 10 13 11 FFFFFF81 45 FFFFFF81 47 FFFFFF81 49 FFFFFF81 4B
   FFFFFF81 4D FFFFFF81 4F FFFFFF81 51 FFFFFF81 53 FFFFFF81 56 09 03 FFFFFF81 46 04 02
   09 46 75 6E 63 74 69 6F 6E 37 10 03 1B FFFFFF81 48 04
   09 63 FFFFFF81 41 FFFFFF84 FFFFFF80 FFFFFF80 FFFFFFC2 00 1E 10 03 1B FFFFFF81 4A 04
   09 71 FFFFFF81 41 FFFFFF84 FFFFFF80 FFFFFF80 FFFFFFC2 00 1E 10 03 1B FFFFFF81 4C 04
   0A FFFFFF81 01 FFFFFF81 41 FFFFFF84 FFFFFF80 FFFFFF80 FFFFFFC2 00 1E 10 03 1B FFFFFF81 4E
   04 0A FFFFFF81 13 FFFFFF81 41 FFFFFF84 FFFFFF80 FFFFFF80 FFFFFFC2 00 1E 10 03 1B FFFFFF81
   50 04 0A FFFFFF81 27 FFFFFF81 41 FFFFFF84 FFFFFF80 FFFFFF80 FFFFFFC2 00 1E 10 03 1B
   FFFFFF81 52 04 0A FFFFFF81 3D FFFFFF81 41 FFFFFF84 FFFFFF80 FFFFFF80 FFFFFFC2 00 1E 10 03
   1B FFFFFF81 54 04 0A FFFFFF81 55 FFFFFF81 41 FFFFFF84 FFFFFF80 FFFFFF80 FFFFFFC2 00 1E 02
   02 41 36 10 03 1B FFFFFF81 57 04 09 55 FFFFFF81 41 FFFFFF84 FFFFFF80 FFFFFF80
   FFFFFFC2 00 1E 08 06 57 FFFFFF81 41 FFFFFFC0 00 58 08 06 4D 00 FFFFFF84
   00 FFFFFF81 5A 15 14 FFFFFF81 5B FFFFFF81 60 FFFFFF81 62 FFFFFF81 64 FFFFFF81 66 FFFFFF81
   68 FFFFFF81 6A FFFFFF81 6C FFFFFF81 6E FFFFFF81 71 14 04 FFFFFF81 5C FFFFFF81 72 10
   15 11 FFFFFF81 5D FFFFFF81 5F FFFFFF81 61 FFFFFF81 63 FFFFFF81 65 FFFFFF81 67 FFFFFF81 69
   FFFFFF81 6B FFFFFF81 6D FFFFFF81 70 09 03 FFFFFF81 5E 04 02 09 46 75 6E
   63 74 69 6F 6E 38 10 03 1B FFFFFF81 60 04 09 63 FFFFFF81 59
   FFFFFF84 FFFFFF80 FFFFFF80 FFFFFFC2 00 1E 10 03 1B FFFFFF81 62 04 09 71 FFFFFF81 59
   FFFFFF84 FFFFFF80 FFFFFF80 FFFFFFC2 00 1E 10 03 1B FFFFFF81 64 04 0A FFFFFF81 01 FFFFFF81
   59 FFFFFF84 FFFFFF80 FFFFFF80 FFFFFFC2 00 1E 10 03 1B FFFFFF81 66 04 0A FFFFFF81 13
   FFFFFF81 59 FFFFFF84 FFFFFF80 FFFFFF80 FFFFFFC2 00 1E 10 03 1B FFFFFF81 68 04 0A FFFFFF81
   27 FFFFFF81 59 FFFFFF84 FFFFFF80 FFFFFF80 FFFFFFC2 00 1E 10 03 1B FFFFFF81 6A 04 0A
   FFFFFF81 3D FFFFFF81 59 FFFFFF84 FFFFFF80 FFFFFF80 FFFFFFC2 00 1E 10 03 1B FFFFFF81 6C 04
   0A FFFFFF81 55 FFFFFF81 59 FFFFFF84 FFFFFF80 FFFFFF80 FFFFFFC2 00 1E 10 03 1B FFFFFF81 6E
   04 0A FFFFFF81 6F FFFFFF81 59 FFFFFF84 FFFFFF80 FFFFFF80 FFFFFFC2 00 1E 02 02 41 37
   10 03 1B FFFFFF81 71 04 09 55 FFFFFF81 59 FFFFFF84 FFFFFF80 FFFFFF80 FFFFFFC2 00 1E
   08 06 57 FFFFFF81 59 FFFFFFC0 00 58 08 06 4D 00 FFFFFF84 00 FFFFFF81 74
   15 16 FFFFFF81 75 FFFFFF81 7A FFFFFF81 7C FFFFFF81 7E FFFFFF82 00 FFFFFF82 02 FFFFFF82 04
   FFFFFF82 06 FFFFFF82 08 FFFFFF82 0A FFFFFF82 0D 14 04 FFFFFF81 76 FFFFFF82 0E 10 17
   11 FFFFFF81 77 FFFFFF81 79 FFFFFF81 7B FFFFFF81 7D FFFFFF81 7F FFFFFF82 01 FFFFFF82 03 FFFFFF82
   05 FFFFFF82 07 FFFFFF82 09 FFFFFF82 0C 09 03 FFFFFF81 78 04 02 09 46 75
   6E 63 74 69 6F 6E 39 10 03 1B FFFFFF81 7A 04 09 63 FFFFFF81
   73 FFFFFF84 FFFFFF80 FFFFFF80 FFFFFFC2 00 1E 10 03 1B FFFFFF81 7C 04 09 71 FFFFFF81
   73 FFFFFF84 FFFFFF80 FFFFFF80 FFFFFFC2 00 1E 10 03 1B FFFFFF81 7E 04 0A FFFFFF81 01
   FFFFFF81 73 FFFFFF84 FFFFFF80 FFFFFF80 FFFFFFC2 00 1E 10 03 1B FFFFFF82 00 04 0A FFFFFF81
   13 FFFFFF81 73 FFFFFF84 FFFFFF80 FFFFFF80 FFFFFFC2 00 1E 10 03 1B FFFFFF82 02 04 0A
   FFFFFF81 27 FFFFFF81 73 FFFFFF84 FFFFFF80 FFFFFF80 FFFFFFC2 00 1E 10 03 1B FFFFFF82 04 04
   0A FFFFFF81 3D FFFFFF81 73 FFFFFF84 FFFFFF80 FFFFFF80 FFFFFFC2 00 1E 10 03 1B FFFFFF82 06
   04 0A FFFFFF81 55 FFFFFF81 73 FFFFFF84 FFFFFF80 FFFFFF80 FFFFFFC2 00 1E 10 03 1B FFFFFF82
   08 04 0A FFFFFF81 6F FFFFFF81 73 FFFFFF84 FFFFFF80 FFFFFF80 FFFFFFC2 00 1E 10 03 1B
   FFFFFF82 0A 04 0A FFFFFF82 0B FFFFFF81 73 FFFFFF84 FFFFFF80 FFFFFF80 FFFFFFC2 00 1E 02 02
   41 38 10 03 1B FFFFFF82 0D 04 09 55 FFFFFF81 73 FFFFFF84 FFFFFF80 FFFFFF80 FFFFFFC2
   00 1E 08 06 57 FFFFFF81 73 FFFFFFC0 00 58 08 07 FFFFFF82 10 00 FFFFFF84
   04 FFFFFF82 11 01 08 62 6F 78 56 61 6C 75 65 14 04 FFFFFF82
   12 FFFFFF82 3B 30 04 FFFFFF82 13 FFFFFF82 38 10 06 11 FFFFFF82 14 08 FFFFFF82
   16 09 03 FFFFFF82 15 04 02 06 54 75 70 6C 65 32 30 04
   FFFFFF82 17 FFFFFF82 19 10 04 09 18 FFFFFF82 18 10 03 1B FFFFFF82 19 04
   0A FFFFFF82 1A 00 FFFFFF84 FFFFFF80 FFFFFF80 FFFFFF82 00 FFFFFF82 1B 02 04 5F 31 30
   31 11 03 FFFFFF82 1C 08 12 14 FFFFFF82 1D FFFFFF82 1F FFFFFF82 22 FFFFFF82 25
   FFFFFF82 28 FFFFFF82 2B FFFFFF82 2E FFFFFF82 31 FFFFFF82 34 FFFFFF82 37 06 0A FFFFFF82 1E
   06 FFFFFF84 FFFFFF80 FFFFFF80 FFFFFF80 00 FFFFFF82 1C 02 0C 3C 72 65 66 69 6E
   65 6D 65 6E 74 3E 10 03 09 FFFFFF82 20 09 03 FFFFFF82 21 0A
   02 04 42 79 74 65 10 03 09 FFFFFF82 23 09 03 FFFFFF82 24 0A
   02 07 42 6F 6F 6C 65 61 6E 10 03 09 FFFFFF82 26 09 03
   FFFFFF82 27 0A 02 09 43 68 61 72 61 63 74 65 72 10 03
   09 FFFFFF82 29 09 03 FFFFFF82 2A 0A 02 05 53 68 6F 72 74 10
   03 09 FFFFFF82 2C 09 03 FFFFFF82 2D 0A 02 07 49 6E 74 65 67
   65 72 10 03 09 FFFFFF82 2F 09 03 FFFFFF82 30 0A 02 04 4C 6F
   6E 67 10 03 09 FFFFFF82 32 09 03 FFFFFF82 33 0A 02 05 46 6C
   6F 61 74 10 03 09 FFFFFF82 35 09 03 FFFFFF82 36 0A 02 06 44
   6F 75 62 6C 65 10 03 1B FFFFFF82 38 04 0A FFFFFF82 39 00 FFFFFF84
   FFFFFF80 FFFFFF80 FFFFFF82 00 FFFFFF82 3A 02 02 3F 30 11 02 1F 08 08 07
   FFFFFF82 3C FFFFFF82 0F FFFFFFC0 00 22 01 05 76 61 6C 75 65 08 07
   FFFFFF82 3E 00 FFFFFF84 04 FFFFFF82 3F 01 11 69 73 43 6F 6E 73 74
   72 75 63 74 6F 72 4E 61 6D 65 14 04 FFFFFF82 40 FFFFFF82 42
   10 03 11 FFFFFF82 41 09 03 FFFFFF82 24 04 08 07 FFFFFF82 43 FFFFFF82 3D
   FFFFFFC0 00 58 01 08 6D 65 74 68 4E 61 6D 65 08 07 FFFFFF82
   45 00 FFFFFF84 04 FFFFFF82 46 01 08 61 70 70 6C 79 46 75 6E
   14 07 34 FFFFFF82 47 FFFFFF82 48 FFFFFF82 4D 08 07 FFFFFF82 43 FFFFFF82 44 FFFFFFC0
   00 58 08 08 FFFFFF82 49 FFFFFF82 44 FFFFFFC0 00 FFFFFF82 4A 01 04 61 72
   67 73 10 04 11 FFFFFF82 4B 34 09 03 FFFFFF82 4C 04 02 05 41
   72 72 61 79 08 08 FFFFFF82 4E FFFFFF82 44 FFFFFFC0 00 FFFFFF82 4F 01 08
   61 72 67 54 79 70 65 73 10 05 11 FFFFFF82 4B FFFFFF82 50 30
   04 FFFFFF82 51 FFFFFF82 53 10 04 44 47 FFFFFF82 52 10 03 1B FFFFFF82 53
   04 08 4B 00 FFFFFF84 FFFFFF80 FFFFFF80 FFFFFF82 00 1E 
  InnerClass: 
   public final #381= #331 of #14; //$anonfun$apply$8=class scala/mobile/Code$$anonfun$apply$8 of class scala/mobile/Code
   public final #382= #355 of #14; //$anonfun$apply$4=class scala/mobile/Code$$anonfun$apply$4 of class scala/mobile/Code
   public final #383= #343 of #14; //$anonfun$apply$6=class scala/mobile/Code$$anonfun$apply$6 of class scala/mobile/Code
   public final #384= #367 of #14; //$anonfun$apply$2=class scala/mobile/Code$$anonfun$apply$2 of class scala/mobile/Code
   public final #385= #337 of #14; //$anonfun$apply$7=class scala/mobile/Code$$anonfun$apply$7 of class scala/mobile/Code
   public final #386= #361 of #14; //$anonfun$apply$3=class scala/mobile/Code$$anonfun$apply$3 of class scala/mobile/Code
   public final #387= #349 of #14; //$anonfun$apply$5=class scala/mobile/Code$$anonfun$apply$5 of class scala/mobile/Code
   public final #388= #325 of #14; //$anonfun$apply$9=class scala/mobile/Code$$anonfun$apply$9 of class scala/mobile/Code
   public final #389= #373 of #14; //$anonfun$apply$1=class scala/mobile/Code$$anonfun$apply$1 of class scala/mobile/Code
   public final #390= #317 of #14; //$anonfun$apply$10=class scala/mobile/Code$$anonfun$apply$10 of class scala/mobile/Code
  minor version: 0
  major version: 49
  Constant pool:
const #1 = Asciz	SourceFile;
const #2 = Asciz	Code.scala;
const #3 = Asciz	instance;
const #4 = Asciz	Ljava/lang/Object;;
const #5 = Asciz	clazz;
const #6 = Asciz	Ljava/lang/Class;;
const #7 = Asciz	Ljava/lang/Class<*>;;
const #8 = Asciz	Signature;
const #9 = Asciz	<init>;
const #10 = Asciz	(Ljava/lang/Class;)V;
const #11 = Asciz	Code;
const #12 = Asciz	LineNumberTable;
const #13 = Asciz	scala/mobile/Code;
const #14 = class	#13;	//  scala/mobile/Code
const #15 = NameAndType	#5:#6;//  clazz:Ljava/lang/Class;
const #16 = Field	#14.#15;	//  scala/mobile/Code.clazz:Ljava/lang/Class;
const #17 = Asciz	java/lang/Object;
const #18 = class	#17;	//  java/lang/Object
const #19 = Asciz	()V;
const #20 = NameAndType	#9:#19;//  "<init>":()V
const #21 = Method	#18.#20;	//  java/lang/Object."<init>":()V
const #22 = Asciz	this;
const #23 = Asciz	Lscala/mobile/Code;;
const #24 = Asciz	LocalVariableTable;
const #25 = Asciz	(Ljava/lang/Class<*>;)V;
const #26 = Asciz	liftedTree1$1;
const #27 = Asciz	()Ljava/lang/Object;;
const #28 = Asciz	java/lang/Class;
const #29 = class	#28;	//  java/lang/Class
const #30 = Asciz	newInstance;
const #31 = NameAndType	#30:#27;//  newInstance:()Ljava/lang/Object;
const #32 = Method	#29.#31;	//  java/lang/Class.newInstance:()Ljava/lang/Object;
const #33 = Asciz	getConstructors;
const #34 = Asciz	()[Ljava/lang/reflect/Constructor;;
const #35 = NameAndType	#33:#34;//  getConstructors:()[Ljava/lang/reflect/Constructor;
const #36 = Method	#29.#35;	//  java/lang/Class.getConstructors:()[Ljava/lang/reflect/Constructor;
const #37 = Asciz	;
const #38 = String	#37;	//  
const #39 = Asciz	java/lang/reflect/Constructor;
const #40 = class	#39;	//  java/lang/reflect/Constructor
const #41 = Asciz	([Ljava/lang/Object;)Ljava/lang/Object;;
const #42 = NameAndType	#30:#41;//  newInstance:([Ljava/lang/Object;)Ljava/lang/Object;
const #43 = Method	#40.#42;	//  java/lang/reflect/Constructor.newInstance:([Ljava/lang/Object;)Ljava/lang/Object;
const #44 = Asciz	scala/Predef$;
const #45 = class	#44;	//  scala/Predef$
const #46 = Asciz	MODULE$;
const #47 = Asciz	Lscala/Predef$;;
const #48 = NameAndType	#46:#47;//  MODULE$:Lscala/Predef$;
const #49 = Field	#45.#48;	//  scala/Predef$.MODULE$:Lscala/Predef$;
const #50 = Asciz	scala/collection/mutable/StringBuilder;
const #51 = class	#50;	//  scala/collection/mutable/StringBuilder
const #52 = Method	#51.#20;	//  scala/collection/mutable/StringBuilder."<init>":()V
const #53 = Asciz	class ;
const #54 = String	#53;	//  class 
const #55 = Asciz	append;
const #56 = Asciz	(Ljava/lang/Object;)Lscala/collection/mutable/StringBuilder;;
const #57 = NameAndType	#55:#56;//  append:(Ljava/lang/Object;)Lscala/collection/mutable/StringBuilder;
const #58 = Method	#51.#57;	//  scala/collection/mutable/StringBuilder.append:(Ljava/lang/Object;)Lscala/collection/mutable/StringBuilder;
const #59 = Asciz	getName;
const #60 = Asciz	()Ljava/lang/String;;
const #61 = NameAndType	#59:#60;//  getName:()Ljava/lang/String;
const #62 = Method	#29.#61;	//  java/lang/Class.getName:()Ljava/lang/String;
const #63 = Asciz	 has no public constructor;
const #64 = String	#63;	//   has no public constructor
const #65 = Asciz	toString;
const #66 = NameAndType	#65:#60;//  toString:()Ljava/lang/String;
const #67 = Method	#51.#66;	//  scala/collection/mutable/StringBuilder.toString:()Ljava/lang/String;
const #68 = Asciz	error;
const #69 = Asciz	(Ljava/lang/String;)Lscala/runtime/Nothing$;;
const #70 = NameAndType	#68:#69;//  error:(Ljava/lang/String;)Lscala/runtime/Nothing$;
const #71 = Method	#45.#70;	//  scala/Predef$.error:(Ljava/lang/String;)Lscala/runtime/Nothing$;
const #72 = Asciz	java/lang/Throwable;
const #73 = class	#72;	//  java/lang/Throwable
const #74 = Asciz	exceptionResult3;
const #75 = Asciz	cs;
const #76 = Asciz	[Ljava/lang/reflect/Constructor;;
const #77 = Asciz	scala$mobile$Code$$applyFun;
const #78 = Asciz	(Ljava/lang/String;[Ljava/lang/Object;[Ljava/lang/Class;)Ljava/lang/Object;;
const #79 = Asciz	scala/runtime/ScalaRunTime$;
const #80 = class	#79;	//  scala/runtime/ScalaRunTime$
const #81 = Asciz	Lscala/runtime/ScalaRunTime$;;
const #82 = NameAndType	#46:#81;//  MODULE$:Lscala/runtime/ScalaRunTime$;
const #83 = Field	#80.#82;	//  scala/runtime/ScalaRunTime$.MODULE$:Lscala/runtime/ScalaRunTime$;
const #84 = Asciz	boxArray;
const #85 = Asciz	(Ljava/lang/Object;)Lscala/runtime/BoxedArray;;
const #86 = NameAndType	#84:#85;//  boxArray:(Ljava/lang/Object;)Lscala/runtime/BoxedArray;
const #87 = Method	#80.#86;	//  scala/runtime/ScalaRunTime$.boxArray:(Ljava/lang/Object;)Lscala/runtime/BoxedArray;
const #88 = Asciz	scala/collection/generic/TraversableTemplate;
const #89 = class	#88;	//  scala/collection/generic/TraversableTemplate
const #90 = Asciz	toArray;
const #91 = Asciz	()Lscala/runtime/BoxedArray;;
const #92 = NameAndType	#90:#91;//  toArray:()Lscala/runtime/BoxedArray;
const #93 = InterfaceMethod	#89.#92;	//  scala/collection/generic/TraversableTemplate.toArray:()Lscala/runtime/BoxedArray;
const #94 = Asciz	arrayValue;
const #95 = Asciz	(Lscala/runtime/BoxedArray;Ljava/lang/Class;)Ljava/lang/Object;;
const #96 = NameAndType	#94:#95;//  arrayValue:(Lscala/runtime/BoxedArray;Ljava/lang/Class;)Ljava/lang/Object;
const #97 = Method	#80.#96;	//  scala/runtime/ScalaRunTime$.arrayValue:(Lscala/runtime/BoxedArray;Ljava/lang/Class;)Ljava/lang/Object;
const #98 = Asciz	scala/runtime/BoxedArray;
const #99 = class	#98;	//  scala/runtime/BoxedArray
const #100 = Asciz	[Ljava/lang/Class;;
const #101 = class	#100;	//  "[Ljava/lang/Class;"
const #102 = Asciz	getMethod;
const #103 = Asciz	(Ljava/lang/String;[Ljava/lang/Class;)Ljava/lang/reflect/Method;;
const #104 = NameAndType	#102:#103;//  getMethod:(Ljava/lang/String;[Ljava/lang/Class;)Ljava/lang/reflect/Method;
const #105 = Method	#29.#104;	//  java/lang/Class.getMethod:(Ljava/lang/String;[Ljava/lang/Class;)Ljava/lang/reflect/Method;
const #106 = Asciz	java/lang/reflect/Method;
const #107 = class	#106;	//  java/lang/reflect/Method
const #108 = Asciz	getModifiers;
const #109 = Asciz	()I;
const #110 = NameAndType	#108:#109;//  getModifiers:()I
const #111 = Method	#107.#110;	//  java/lang/reflect/Method.getModifiers:()I
const #112 = Asciz	java/lang/reflect/Modifier;
const #113 = class	#112;	//  java/lang/reflect/Modifier
const #114 = Asciz	isStatic;
const #115 = Asciz	(I)Z;
const #116 = NameAndType	#114:#115;//  isStatic:(I)Z
const #117 = Method	#113.#116;	//  java/lang/reflect/Modifier.isStatic:(I)Z
const #118 = NameAndType	#3:#27;//  instance:()Ljava/lang/Object;
const #119 = Method	#14.#118;	//  scala/mobile/Code.instance:()Ljava/lang/Object;
const #120 = NameAndType	#26:#27;//  liftedTree1$1:()Ljava/lang/Object;
const #121 = Method	#14.#120;	//  scala/mobile/Code.liftedTree1$1:()Ljava/lang/Object;
const #122 = Asciz	instance_$eq;
const #123 = Asciz	(Ljava/lang/Object;)V;
const #124 = NameAndType	#122:#123;//  instance_$eq:(Ljava/lang/Object;)V
const #125 = Method	#14.#124;	//  scala/mobile/Code.instance_$eq:(Ljava/lang/Object;)V
const #126 = Asciz	[Ljava/lang/Object;;
const #127 = class	#126;	//  "[Ljava/lang/Object;"
const #128 = Asciz	invoke;
const #129 = Asciz	(Ljava/lang/Object;[Ljava/lang/Object;)Ljava/lang/Object;;
const #130 = NameAndType	#128:#129;//  invoke:(Ljava/lang/Object;[Ljava/lang/Object;)Ljava/lang/Object;
const #131 = Method	#107.#130;	//  java/lang/reflect/Method.invoke:(Ljava/lang/Object;[Ljava/lang/Object;)Ljava/lang/Object;
const #132 = Asciz	scala/runtime/BoxedUnit;
const #133 = class	#132;	//  scala/runtime/BoxedUnit
const #134 = Asciz	UNIT;
const #135 = Asciz	Lscala/runtime/BoxedUnit;;
const #136 = NameAndType	#134:#135;//  UNIT:Lscala/runtime/BoxedUnit;
const #137 = Field	#133.#136;	//  scala/runtime/BoxedUnit.UNIT:Lscala/runtime/BoxedUnit;
const #138 = Asciz	scala/Console$;
const #139 = class	#138;	//  scala/Console$
const #140 = Asciz	Lscala/Console$;;
const #141 = NameAndType	#46:#140;//  MODULE$:Lscala/Console$;
const #142 = Field	#139.#141;	//  scala/Console$.MODULE$:Lscala/Console$;
const #143 = Asciz	java/lang/Exception;
const #144 = class	#143;	//  java/lang/Exception
const #145 = Asciz	getMessage;
const #146 = NameAndType	#145:#60;//  getMessage:()Ljava/lang/String;
const #147 = Method	#144.#146;	//  java/lang/Exception.getMessage:()Ljava/lang/String;
const #148 = Asciz	println;
const #149 = NameAndType	#148:#123;//  println:(Ljava/lang/Object;)V
const #150 = Method	#139.#149;	//  scala/Console$.println:(Ljava/lang/Object;)V
const #151 = Asciz	printStackTrace;
const #152 = NameAndType	#151:#19;//  printStackTrace:()V
const #153 = Method	#144.#152;	//  java/lang/Exception.printStackTrace:()V
const #154 = Asciz	isConstructorName;
const #155 = Asciz	(Ljava/lang/String;)Z;
const #156 = NameAndType	#154:#155;//  isConstructorName:(Ljava/lang/String;)Z
const #157 = Method	#14.#156;	//  scala/mobile/Code.isConstructorName:(Ljava/lang/String;)Z
const #158 = Asciz	getConstructor;
const #159 = Asciz	([Ljava/lang/Class;)Ljava/lang/reflect/Constructor;;
const #160 = NameAndType	#158:#159;//  getConstructor:([Ljava/lang/Class;)Ljava/lang/reflect/Constructor;
const #161 = Method	#29.#160;	//  java/lang/Class.getConstructor:([Ljava/lang/Class;)Ljava/lang/reflect/Constructor;
const #162 = Asciz	java/lang/NoSuchMethodException;
const #163 = class	#162;	//  java/lang/NoSuchMethodException
const #164 = Method	#163.#146;	//  java/lang/NoSuchMethodException.getMessage:()Ljava/lang/String;
const #165 = Method	#163.#152;	//  java/lang/NoSuchMethodException.printStackTrace:()V
const #166 = Asciz	methName;
const #167 = Asciz	Ljava/lang/String;;
const #168 = Asciz	args;
const #169 = Asciz	argTypes;
const #170 = Asciz	exceptionResult1;
const #171 = Asciz	exceptionResult2;
const #172 = Asciz	cstr;
const #173 = Asciz	Ljava/lang/reflect/Constructor;;
const #174 = Asciz	method;
const #175 = Asciz	Ljava/lang/reflect/Method;;
const #176 = Asciz	obj;
const #177 = Asciz	result;
const #178 = Asciz	.;
const #179 = String	#178;	//  .
const #180 = Asciz	java/lang/String;
const #181 = class	#180;	//  java/lang/String
const #182 = Asciz	lastIndexOf;
const #183 = Asciz	(Ljava/lang/String;)I;
const #184 = NameAndType	#182:#183;//  lastIndexOf:(Ljava/lang/String;)I
const #185 = Method	#181.#184;	//  java/lang/String.lastIndexOf:(Ljava/lang/String;)I
const #186 = Asciz	length;
const #187 = NameAndType	#186:#109;//  length:()I
const #188 = Method	#181.#187;	//  java/lang/String.length:()I
const #189 = Asciz	substring;
const #190 = Asciz	(II)Ljava/lang/String;;
const #191 = NameAndType	#189:#190;//  substring:(II)Ljava/lang/String;
const #192 = Method	#181.#191;	//  java/lang/String.substring:(II)Ljava/lang/String;
const #193 = Asciz	equals;
const #194 = Asciz	(Ljava/lang/Object;)Z;
const #195 = NameAndType	#193:#194;//  equals:(Ljava/lang/Object;)Z
const #196 = Method	#181.#195;	//  java/lang/String.equals:(Ljava/lang/Object;)Z
const #197 = Asciz	className;
const #198 = Asciz	classInx;
const #199 = Asciz	I;
const #200 = Asciz	methInx;
const #201 = Asciz	scala$mobile$Code$$boxValue;
const #202 = Asciz	(Ljava/lang/Object;)Lscala/Tuple2;;
const #203 = Asciz	java/lang/Byte;
const #204 = class	#203;	//  java/lang/Byte
const #205 = Asciz	scala/runtime/BoxesRunTime;
const #206 = class	#205;	//  scala/runtime/BoxesRunTime
const #207 = Asciz	unboxToByte;
const #208 = Asciz	(Ljava/lang/Object;)B;
const #209 = NameAndType	#207:#208;//  unboxToByte:(Ljava/lang/Object;)B
const #210 = Method	#206.#209;	//  scala/runtime/BoxesRunTime.unboxToByte:(Ljava/lang/Object;)B
const #211 = Asciz	scala/Tuple2;
const #212 = class	#211;	//  scala/Tuple2
const #213 = Asciz	valueOf;
const #214 = Asciz	(B)Ljava/lang/Byte;;
const #215 = NameAndType	#213:#214;//  valueOf:(B)Ljava/lang/Byte;
const #216 = Method	#204.#215;	//  java/lang/Byte.valueOf:(B)Ljava/lang/Byte;
const #217 = Asciz	TYPE;
const #218 = NameAndType	#217:#6;//  TYPE:Ljava/lang/Class;
const #219 = Field	#204.#218;	//  java/lang/Byte.TYPE:Ljava/lang/Class;
const #220 = Asciz	(Ljava/lang/Object;Ljava/lang/Object;)V;
const #221 = NameAndType	#9:#220;//  "<init>":(Ljava/lang/Object;Ljava/lang/Object;)V
const #222 = Method	#212.#221;	//  scala/Tuple2."<init>":(Ljava/lang/Object;Ljava/lang/Object;)V
const #223 = Asciz	java/lang/Boolean;
const #224 = class	#223;	//  java/lang/Boolean
const #225 = Asciz	unboxToBoolean;
const #226 = NameAndType	#225:#194;//  unboxToBoolean:(Ljava/lang/Object;)Z
const #227 = Method	#206.#226;	//  scala/runtime/BoxesRunTime.unboxToBoolean:(Ljava/lang/Object;)Z
const #228 = Asciz	(Z)Ljava/lang/Boolean;;
const #229 = NameAndType	#213:#228;//  valueOf:(Z)Ljava/lang/Boolean;
const #230 = Method	#224.#229;	//  java/lang/Boolean.valueOf:(Z)Ljava/lang/Boolean;
const #231 = Field	#224.#218;	//  java/lang/Boolean.TYPE:Ljava/lang/Class;
const #232 = Asciz	java/lang/Character;
const #233 = class	#232;	//  java/lang/Character
const #234 = Asciz	unboxToChar;
const #235 = Asciz	(Ljava/lang/Object;)C;
const #236 = NameAndType	#234:#235;//  unboxToChar:(Ljava/lang/Object;)C
const #237 = Method	#206.#236;	//  scala/runtime/BoxesRunTime.unboxToChar:(Ljava/lang/Object;)C
const #238 = Asciz	(C)Ljava/lang/Character;;
const #239 = NameAndType	#213:#238;//  valueOf:(C)Ljava/lang/Character;
const #240 = Method	#233.#239;	//  java/lang/Character.valueOf:(C)Ljava/lang/Character;
const #241 = Field	#233.#218;	//  java/lang/Character.TYPE:Ljava/lang/Class;
const #242 = Asciz	java/lang/Short;
const #243 = class	#242;	//  java/lang/Short
const #244 = Asciz	unboxToShort;
const #245 = Asciz	(Ljava/lang/Object;)S;
const #246 = NameAndType	#244:#245;//  unboxToShort:(Ljava/lang/Object;)S
const #247 = Method	#206.#246;	//  scala/runtime/BoxesRunTime.unboxToShort:(Ljava/lang/Object;)S
const #248 = Asciz	(S)Ljava/lang/Short;;
const #249 = NameAndType	#213:#248;//  valueOf:(S)Ljava/lang/Short;
const #250 = Method	#243.#249;	//  java/lang/Short.valueOf:(S)Ljava/lang/Short;
const #251 = Field	#243.#218;	//  java/lang/Short.TYPE:Ljava/lang/Class;
const #252 = Asciz	java/lang/Integer;
const #253 = class	#252;	//  java/lang/Integer
const #254 = Asciz	unboxToInt;
const #255 = Asciz	(Ljava/lang/Object;)I;
const #256 = NameAndType	#254:#255;//  unboxToInt:(Ljava/lang/Object;)I
const #257 = Method	#206.#256;	//  scala/runtime/BoxesRunTime.unboxToInt:(Ljava/lang/Object;)I
const #258 = Asciz	(I)Ljava/lang/Integer;;
const #259 = NameAndType	#213:#258;//  valueOf:(I)Ljava/lang/Integer;
const #260 = Method	#253.#259;	//  java/lang/Integer.valueOf:(I)Ljava/lang/Integer;
const #261 = Field	#253.#218;	//  java/lang/Integer.TYPE:Ljava/lang/Class;
const #262 = Asciz	java/lang/Long;
const #263 = class	#262;	//  java/lang/Long
const #264 = Asciz	unboxToLong;
const #265 = Asciz	(Ljava/lang/Object;)J;
const #266 = NameAndType	#264:#265;//  unboxToLong:(Ljava/lang/Object;)J
const #267 = Method	#206.#266;	//  scala/runtime/BoxesRunTime.unboxToLong:(Ljava/lang/Object;)J
const #268 = Asciz	(J)Ljava/lang/Long;;
const #269 = NameAndType	#213:#268;//  valueOf:(J)Ljava/lang/Long;
const #270 = Method	#263.#269;	//  java/lang/Long.valueOf:(J)Ljava/lang/Long;
const #271 = Field	#263.#218;	//  java/lang/Long.TYPE:Ljava/lang/Class;
const #272 = Asciz	java/lang/Float;
const #273 = class	#272;	//  java/lang/Float
const #274 = Asciz	unboxToFloat;
const #275 = Asciz	(Ljava/lang/Object;)F;
const #276 = NameAndType	#274:#275;//  unboxToFloat:(Ljava/lang/Object;)F
const #277 = Method	#206.#276;	//  scala/runtime/BoxesRunTime.unboxToFloat:(Ljava/lang/Object;)F
const #278 = Asciz	(F)Ljava/lang/Float;;
const #279 = NameAndType	#213:#278;//  valueOf:(F)Ljava/lang/Float;
const #280 = Method	#273.#279;	//  java/lang/Float.valueOf:(F)Ljava/lang/Float;
const #281 = Field	#273.#218;	//  java/lang/Float.TYPE:Ljava/lang/Class;
const #282 = Asciz	java/lang/Double;
const #283 = class	#282;	//  java/lang/Double
const #284 = Asciz	unboxToDouble;
const #285 = Asciz	(Ljava/lang/Object;)D;
const #286 = NameAndType	#284:#285;//  unboxToDouble:(Ljava/lang/Object;)D
const #287 = Method	#206.#286;	//  scala/runtime/BoxesRunTime.unboxToDouble:(Ljava/lang/Object;)D
const #288 = Asciz	(D)Ljava/lang/Double;;
const #289 = NameAndType	#213:#288;//  valueOf:(D)Ljava/lang/Double;
const #290 = Method	#283.#289;	//  java/lang/Double.valueOf:(D)Ljava/lang/Double;
const #291 = Field	#283.#218;	//  java/lang/Double.TYPE:Ljava/lang/Class;
const #292 = Asciz	getClass;
const #293 = Asciz	()Ljava/lang/Class;;
const #294 = NameAndType	#292:#293;//  getClass:()Ljava/lang/Class;
const #295 = Method	#18.#294;	//  java/lang/Object.getClass:()Ljava/lang/Class;
const #296 = Asciz	value;
const #297 = Asciz	temp1;
const #298 = Asciz	temp2;
const #299 = Asciz	B;
const #300 = Asciz	temp3;
const #301 = Asciz	Z;
const #302 = Asciz	temp4;
const #303 = Asciz	C;
const #304 = Asciz	temp5;
const #305 = Asciz	S;
const #306 = Asciz	temp6;
const #307 = Asciz	temp7;
const #308 = Asciz	J;
const #309 = Asciz	temp8;
const #310 = Asciz	F;
const #311 = Asciz	temp9;
const #312 = Asciz	D;
const #313 = Asciz	x;
const #314 = Asciz	apply;
const #315 = Asciz	(Ljava/lang/String;)Lscala/Function9;;
const #316 = Asciz	scala/mobile/Code$$anonfun$apply$10;
const #317 = class	#316;	//  scala/mobile/Code$$anonfun$apply$10
const #318 = Asciz	(Lscala/mobile/Code;Ljava/lang/String;)V;
const #319 = NameAndType	#9:#318;//  "<init>":(Lscala/mobile/Code;Ljava/lang/String;)V
const #320 = Method	#317.#319;	//  scala/mobile/Code$$anonfun$apply$10."<init>":(Lscala/mobile/Code;Ljava/lang/String;)V
const #321 = Asciz	funName$10;
const #322 = Asciz	<A0:Ljava/lang/Object;A1:Ljava/lang/Object;A2:Ljava/lang/Object;A3:Ljava/lang/Object;A4:Ljava/lang/Object;A5:Ljava/lang/Object;A6:Ljava/lang/Object;A7:Ljava/lang/Object;A8:Ljava/lang/Object;R:Ljava/lang/Object;>(Ljava/lang/String;)Lscala/Function9<TA0;TA1;TA2;TA3;TA4;TA5;TA6;TA7;TA8;TR;>;;
const #323 = Asciz	(Ljava/lang/String;)Lscala/Function8;;
const #324 = Asciz	scala/mobile/Code$$anonfun$apply$9;
const #325 = class	#324;	//  scala/mobile/Code$$anonfun$apply$9
const #326 = Method	#325.#319;	//  scala/mobile/Code$$anonfun$apply$9."<init>":(Lscala/mobile/Code;Ljava/lang/String;)V
const #327 = Asciz	funName$9;
const #328 = Asciz	<A0:Ljava/lang/Object;A1:Ljava/lang/Object;A2:Ljava/lang/Object;A3:Ljava/lang/Object;A4:Ljava/lang/Object;A5:Ljava/lang/Object;A6:Ljava/lang/Object;A7:Ljava/lang/Object;R:Ljava/lang/Object;>(Ljava/lang/String;)Lscala/Function8<TA0;TA1;TA2;TA3;TA4;TA5;TA6;TA7;TR;>;;
const #329 = Asciz	(Ljava/lang/String;)Lscala/Function7;;
const #330 = Asciz	scala/mobile/Code$$anonfun$apply$8;
const #331 = class	#330;	//  scala/mobile/Code$$anonfun$apply$8
const #332 = Method	#331.#319;	//  scala/mobile/Code$$anonfun$apply$8."<init>":(Lscala/mobile/Code;Ljava/lang/String;)V
const #333 = Asciz	funName$8;
const #334 = Asciz	<A0:Ljava/lang/Object;A1:Ljava/lang/Object;A2:Ljava/lang/Object;A3:Ljava/lang/Object;A4:Ljava/lang/Object;A5:Ljava/lang/Object;A6:Ljava/lang/Object;R:Ljava/lang/Object;>(Ljava/lang/String;)Lscala/Function7<TA0;TA1;TA2;TA3;TA4;TA5;TA6;TR;>;;
const #335 = Asciz	(Ljava/lang/String;)Lscala/Function6;;
const #336 = Asciz	scala/mobile/Code$$anonfun$apply$7;
const #337 = class	#336;	//  scala/mobile/Code$$anonfun$apply$7
const #338 = Method	#337.#319;	//  scala/mobile/Code$$anonfun$apply$7."<init>":(Lscala/mobile/Code;Ljava/lang/String;)V
const #339 = Asciz	funName$7;
const #340 = Asciz	<A0:Ljava/lang/Object;A1:Ljava/lang/Object;A2:Ljava/lang/Object;A3:Ljava/lang/Object;A4:Ljava/lang/Object;A5:Ljava/lang/Object;R:Ljava/lang/Object;>(Ljava/lang/String;)Lscala/Function6<TA0;TA1;TA2;TA3;TA4;TA5;TR;>;;
const #341 = Asciz	(Ljava/lang/String;)Lscala/Function5;;
const #342 = Asciz	scala/mobile/Code$$anonfun$apply$6;
const #343 = class	#342;	//  scala/mobile/Code$$anonfun$apply$6
const #344 = Method	#343.#319;	//  scala/mobile/Code$$anonfun$apply$6."<init>":(Lscala/mobile/Code;Ljava/lang/String;)V
const #345 = Asciz	funName$6;
const #346 = Asciz	<A0:Ljava/lang/Object;A1:Ljava/lang/Object;A2:Ljava/lang/Object;A3:Ljava/lang/Object;A4:Ljava/lang/Object;R:Ljava/lang/Object;>(Ljava/lang/String;)Lscala/Function5<TA0;TA1;TA2;TA3;TA4;TR;>;;
const #347 = Asciz	(Ljava/lang/String;)Lscala/Function4;;
const #348 = Asciz	scala/mobile/Code$$anonfun$apply$5;
const #349 = class	#348;	//  scala/mobile/Code$$anonfun$apply$5
const #350 = Method	#349.#319;	//  scala/mobile/Code$$anonfun$apply$5."<init>":(Lscala/mobile/Code;Ljava/lang/String;)V
const #351 = Asciz	funName$5;
const #352 = Asciz	<A0:Ljava/lang/Object;A1:Ljava/lang/Object;A2:Ljava/lang/Object;A3:Ljava/lang/Object;R:Ljava/lang/Object;>(Ljava/lang/String;)Lscala/Function4<TA0;TA1;TA2;TA3;TR;>;;
const #353 = Asciz	(Ljava/lang/String;)Lscala/Function3;;
const #354 = Asciz	scala/mobile/Code$$anonfun$apply$4;
const #355 = class	#354;	//  scala/mobile/Code$$anonfun$apply$4
const #356 = Method	#355.#319;	//  scala/mobile/Code$$anonfun$apply$4."<init>":(Lscala/mobile/Code;Ljava/lang/String;)V
const #357 = Asciz	funName$4;
const #358 = Asciz	<A0:Ljava/lang/Object;A1:Ljava/lang/Object;A2:Ljava/lang/Object;R:Ljava/lang/Object;>(Ljava/lang/String;)Lscala/Function3<TA0;TA1;TA2;TR;>;;
const #359 = Asciz	(Ljava/lang/String;)Lscala/Function2;;
const #360 = Asciz	scala/mobile/Code$$anonfun$apply$3;
const #361 = class	#360;	//  scala/mobile/Code$$anonfun$apply$3
const #362 = Method	#361.#319;	//  scala/mobile/Code$$anonfun$apply$3."<init>":(Lscala/mobile/Code;Ljava/lang/String;)V
const #363 = Asciz	funName$3;
const #364 = Asciz	<A0:Ljava/lang/Object;A1:Ljava/lang/Object;R:Ljava/lang/Object;>(Ljava/lang/String;)Lscala/Function2<TA0;TA1;TR;>;;
const #365 = Asciz	(Ljava/lang/String;)Lscala/Function1;;
const #366 = Asciz	scala/mobile/Code$$anonfun$apply$2;
const #367 = class	#366;	//  scala/mobile/Code$$anonfun$apply$2
const #368 = Method	#367.#319;	//  scala/mobile/Code$$anonfun$apply$2."<init>":(Lscala/mobile/Code;Ljava/lang/String;)V
const #369 = Asciz	funName$2;
const #370 = Asciz	<A0:Ljava/lang/Object;R:Ljava/lang/Object;>(Ljava/lang/String;)Lscala/Function1<TA0;TR;>;;
const #371 = Asciz	(Ljava/lang/String;)Lscala/Function0;;
const #372 = Asciz	scala/mobile/Code$$anonfun$apply$1;
const #373 = class	#372;	//  scala/mobile/Code$$anonfun$apply$1
const #374 = Method	#373.#319;	//  scala/mobile/Code$$anonfun$apply$1."<init>":(Lscala/mobile/Code;Ljava/lang/String;)V
const #375 = Asciz	funName$1;
const #376 = Asciz	<R:Ljava/lang/Object;>(Ljava/lang/String;)Lscala/Function0<TR;>;;
const #377 = NameAndType	#3:#4;//  instance:Ljava/lang/Object;
const #378 = Field	#14.#377;	//  scala/mobile/Code.instance:Ljava/lang/Object;
const #379 = Asciz	ScalaSig;
const #380 = Asciz	InnerClasses;
const #381 = Asciz	$anonfun$apply$8;
const #382 = Asciz	$anonfun$apply$4;
const #383 = Asciz	$anonfun$apply$6;
const #384 = Asciz	$anonfun$apply$2;
const #385 = Asciz	$anonfun$apply$7;
const #386 = Asciz	$anonfun$apply$3;
const #387 = Asciz	$anonfun$apply$5;
const #388 = Asciz	$anonfun$apply$9;
const #389 = Asciz	$anonfun$apply$1;
const #390 = Asciz	$anonfun$apply$10;
const #391 = Asciz	scala/ScalaObject;
const #392 = class	#391;	//  scala/ScalaObject

{
public scala.mobile.Code(java.lang.Class);
  Code:
   Stack=2, Locals=2, Args_size=2
   0:	aload_0
   1:	aload_1
   2:	putfield	#16; //Field clazz:Ljava/lang/Class;
   5:	aload_0
   6:	invokespecial	#21; //Method java/lang/Object."<init>":()V
   9:	return
  LineNumberTable: 
   line 35: 0

  LocalVariableTable: 
   Start  Length  Slot  Name   Signature
   0      10      0    this       Lscala/mobile/Code;
   0      10      1    clazz       Ljava/lang/Class;

  Signature: length = 0x2
   00 19 

public final java.lang.Object scala$mobile$Code$$applyFun(java.lang.String, java.lang.Object[], java.lang.Class[]);
  Code:
   Stack=5, Locals=17, Args_size=4
   0:	aconst_null
   1:	astore	4
   3:	aload_0
   4:	getfield	#16; //Field clazz:Ljava/lang/Class;
   7:	aload_1
   8:	getstatic	#83; //Field scala/runtime/ScalaRunTime$.MODULE$:Lscala/runtime/ScalaRunTime$;
   11:	getstatic	#83; //Field scala/runtime/ScalaRunTime$.MODULE$:Lscala/runtime/ScalaRunTime$;
   14:	aload_3
   15:	invokevirtual	#87; //Method scala/runtime/ScalaRunTime$.boxArray:(Ljava/lang/Object;)Lscala/runtime/BoxedArray;
   18:	invokeinterface	#93,  1; //InterfaceMethod scala/collection/generic/TraversableTemplate.toArray:()Lscala/runtime/BoxedArray;
   23:	ldc	#29; //class java/lang/Class
   25:	invokevirtual	#97; //Method scala/runtime/ScalaRunTime$.arrayValue:(Lscala/runtime/BoxedArray;Ljava/lang/Class;)Ljava/lang/Object;
   28:	astore	13
   30:	aload	13
   32:	instanceof	#99; //class scala/runtime/BoxedArray
   35:	ifeq	54
   38:	getstatic	#83; //Field scala/runtime/ScalaRunTime$.MODULE$:Lscala/runtime/ScalaRunTime$;
   41:	aload	13
   43:	checkcast	#99; //class scala/runtime/BoxedArray
   46:	ldc	#29; //class java/lang/Class
   48:	invokevirtual	#97; //Method scala/runtime/ScalaRunTime$.arrayValue:(Lscala/runtime/BoxedArray;Ljava/lang/Class;)Ljava/lang/Object;
   51:	goto	56
   54:	aload	13
   56:	checkcast	#101; //class "[Ljava/lang/Class;"
   59:	invokevirtual	#105; //Method java/lang/Class.getMethod:(Ljava/lang/String;[Ljava/lang/Class;)Ljava/lang/reflect/Method;
   62:	astore	12
   64:	aconst_null
   65:	pop
   66:	aconst_null
   67:	astore	14
   69:	aload	12
   71:	invokevirtual	#111; //Method java/lang/reflect/Method.getModifiers:()I
   74:	invokestatic	#117; //Method java/lang/reflect/Modifier.isStatic:(I)Z
   77:	ifne	101
   80:	aload_0
   81:	invokespecial	#119; //Method instance:()Ljava/lang/Object;
   84:	ifnonnull	95
   87:	aload_0
   88:	aload_0
   89:	invokespecial	#121; //Method liftedTree1$1:()Ljava/lang/Object;
   92:	invokespecial	#125; //Method instance_$eq:(Ljava/lang/Object;)V
   95:	aload_0
   96:	invokespecial	#119; //Method instance:()Ljava/lang/Object;
   99:	astore	14
   101:	aload	12
   103:	aload	14
   105:	getstatic	#83; //Field scala/runtime/ScalaRunTime$.MODULE$:Lscala/runtime/ScalaRunTime$;
   108:	getstatic	#83; //Field scala/runtime/ScalaRunTime$.MODULE$:Lscala/runtime/ScalaRunTime$;
   111:	aload_2
   112:	invokevirtual	#87; //Method scala/runtime/ScalaRunTime$.boxArray:(Ljava/lang/Object;)Lscala/runtime/BoxedArray;
   115:	invokeinterface	#93,  1; //InterfaceMethod scala/collection/generic/TraversableTemplate.toArray:()Lscala/runtime/BoxedArray;
   120:	ldc	#18; //class java/lang/Object
   122:	invokevirtual	#97; //Method scala/runtime/ScalaRunTime$.arrayValue:(Lscala/runtime/BoxedArray;Ljava/lang/Class;)Ljava/lang/Object;
   125:	astore	16
   127:	aload	16
   129:	instanceof	#99; //class scala/runtime/BoxedArray
   132:	ifeq	151
   135:	getstatic	#83; //Field scala/runtime/ScalaRunTime$.MODULE$:Lscala/runtime/ScalaRunTime$;
   138:	aload	16
   140:	checkcast	#99; //class scala/runtime/BoxedArray
   143:	ldc	#18; //class java/lang/Object
   145:	invokevirtual	#97; //Method scala/runtime/ScalaRunTime$.arrayValue:(Lscala/runtime/BoxedArray;Ljava/lang/Class;)Ljava/lang/Object;
   148:	goto	153
   151:	aload	16
   153:	checkcast	#127; //class "[Ljava/lang/Object;"
   156:	invokevirtual	#131; //Method java/lang/reflect/Method.invoke:(Ljava/lang/Object;[Ljava/lang/Object;)Ljava/lang/Object;
   159:	astore	15
   161:	aload	15
   163:	ifnonnull	172
   166:	getstatic	#137; //Field scala/runtime/BoxedUnit.UNIT:Lscala/runtime/BoxedUnit;
   169:	goto	174
   172:	aload	15
   174:	astore	4
   176:	goto	400
   179:	astore	5
   181:	getstatic	#142; //Field scala/Console$.MODULE$:Lscala/Console$;
   184:	aload	5
   186:	invokevirtual	#147; //Method java/lang/Exception.getMessage:()Ljava/lang/String;
   189:	invokevirtual	#150; //Method scala/Console$.println:(Ljava/lang/Object;)V
   192:	aload	5
   194:	invokevirtual	#153; //Method java/lang/Exception.printStackTrace:()V
   197:	aconst_null
   198:	pop
   199:	aconst_null
   200:	astore	4
   202:	goto	400
   205:	astore	6
   207:	aload_0
   208:	aload_1
   209:	invokespecial	#157; //Method isConstructorName:(Ljava/lang/String;)Z
   212:	ifeq	347
   215:	aconst_null
   216:	astore	7
   218:	aload_0
   219:	getfield	#16; //Field clazz:Ljava/lang/Class;
   222:	getstatic	#83; //Field scala/runtime/ScalaRunTime$.MODULE$:Lscala/runtime/ScalaRunTime$;
   225:	getstatic	#83; //Field scala/runtime/ScalaRunTime$.MODULE$:Lscala/runtime/ScalaRunTime$;
   228:	aload_3
   229:	invokevirtual	#87; //Method scala/runtime/ScalaRunTime$.boxArray:(Ljava/lang/Object;)Lscala/runtime/BoxedArray;
   232:	invokeinterface	#93,  1; //InterfaceMethod scala/collection/generic/TraversableTemplate.toArray:()Lscala/runtime/BoxedArray;
   237:	ldc	#29; //class java/lang/Class
   239:	invokevirtual	#97; //Method scala/runtime/ScalaRunTime$.arrayValue:(Lscala/runtime/BoxedArray;Ljava/lang/Class;)Ljava/lang/Object;
   242:	astore	10
   244:	aload	10
   246:	instanceof	#99; //class scala/runtime/BoxedArray
   249:	ifeq	268
   252:	getstatic	#83; //Field scala/runtime/ScalaRunTime$.MODULE$:Lscala/runtime/ScalaRunTime$;
   255:	aload	10
   257:	checkcast	#99; //class scala/runtime/BoxedArray
   260:	ldc	#29; //class java/lang/Class
   262:	invokevirtual	#97; //Method scala/runtime/ScalaRunTime$.arrayValue:(Lscala/runtime/BoxedArray;Ljava/lang/Class;)Ljava/lang/Object;
   265:	goto	270
   268:	aload	10
   270:	checkcast	#101; //class "[Ljava/lang/Class;"
   273:	invokevirtual	#161; //Method java/lang/Class.getConstructor:([Ljava/lang/Class;)Ljava/lang/reflect/Constructor;
   276:	astore	9
   278:	aload_0
   279:	aload	9
   281:	getstatic	#83; //Field scala/runtime/ScalaRunTime$.MODULE$:Lscala/runtime/ScalaRunTime$;
   284:	getstatic	#83; //Field scala/runtime/ScalaRunTime$.MODULE$:Lscala/runtime/ScalaRunTime$;
   287:	aload_2
   288:	invokevirtual	#87; //Method scala/runtime/ScalaRunTime$.boxArray:(Ljava/lang/Object;)Lscala/runtime/BoxedArray;
   291:	invokeinterface	#93,  1; //InterfaceMethod scala/collection/generic/TraversableTemplate.toArray:()Lscala/runtime/BoxedArray;
   296:	ldc	#18; //class java/lang/Object
   298:	invokevirtual	#97; //Method scala/runtime/ScalaRunTime$.arrayValue:(Lscala/runtime/BoxedArray;Ljava/lang/Class;)Ljava/lang/Object;
   301:	astore	11
   303:	aload	11
   305:	instanceof	#99; //class scala/runtime/BoxedArray
   308:	ifeq	327
   311:	getstatic	#83; //Field scala/runtime/ScalaRunTime$.MODULE$:Lscala/runtime/ScalaRunTime$;
   314:	aload	11
   316:	checkcast	#99; //class scala/runtime/BoxedArray
   319:	ldc	#18; //class java/lang/Object
   321:	invokevirtual	#97; //Method scala/runtime/ScalaRunTime$.arrayValue:(Lscala/runtime/BoxedArray;Ljava/lang/Class;)Ljava/lang/Object;
   324:	goto	329
   327:	aload	11
   329:	checkcast	#127; //class "[Ljava/lang/Object;"
   332:	invokevirtual	#43; //Method java/lang/reflect/Constructor.newInstance:([Ljava/lang/Object;)Ljava/lang/Object;
   335:	invokespecial	#125; //Method instance_$eq:(Ljava/lang/Object;)V
   338:	aload_0
   339:	invokespecial	#119; //Method instance:()Ljava/lang/Object;
   342:	astore	7
   344:	goto	392
   347:	getstatic	#142; //Field scala/Console$.MODULE$:Lscala/Console$;
   350:	aload	6
   352:	invokevirtual	#164; //Method java/lang/NoSuchMethodException.getMessage:()Ljava/lang/String;
   355:	invokevirtual	#150; //Method scala/Console$.println:(Ljava/lang/Object;)V
   358:	aload	6
   360:	invokevirtual	#165; //Method java/lang/NoSuchMethodException.printStackTrace:()V
   363:	getstatic	#137; //Field scala/runtime/BoxedUnit.UNIT:Lscala/runtime/BoxedUnit;
   366:	goto	394
   369:	astore	8
   371:	getstatic	#142; //Field scala/Console$.MODULE$:Lscala/Console$;
   374:	aload	8
   376:	invokevirtual	#147; //Method java/lang/Exception.getMessage:()Ljava/lang/String;
   379:	invokevirtual	#150; //Method scala/Console$.println:(Ljava/lang/Object;)V
   382:	aload	8
   384:	invokevirtual	#153; //Method java/lang/Exception.printStackTrace:()V
   387:	getstatic	#137; //Field scala/runtime/BoxedUnit.UNIT:Lscala/runtime/BoxedUnit;
   390:	astore	7
   392:	aload	7
   394:	pop
   395:	aconst_null
   396:	pop
   397:	aconst_null
   398:	astore	4
   400:	aload	4
   402:	areturn
  Exception table:
   from   to  target type
   218   347   369   Class java/lang/Exception

     3   179   205   Class java/lang/NoSuchMethodException

     3   179   179   Class java/lang/Exception

  LineNumberTable: 
   line 188: 0
   line 187: 1
   line 188: 3
   line 191: 38
   line 188: 59
   line 189: 64
   line 190: 69
   line 191: 80
   line 192: 87
   line 205: 95
   line 207: 101
   line 208: 135
   line 207: 156
   line 208: 161
   line 229: 174
   line 230: 181
   line 231: 192
   line 232: 197
   line 211: 205
   line 212: 207
   line 214: 215
   line 213: 216
   line 214: 218
   line 225: 252
   line 214: 273
   line 215: 278
   line 225: 311
   line 215: 332
   line 216: 338
   line 225: 347
   line 226: 358
   line 224: 363
   line 219: 369
   line 220: 371
   line 221: 382
   line 219: 387
   line 212: 392
   line 228: 395

  LocalVariableTable: 
   Start  Length  Slot  Name   Signature
   0      403      0    this       Lscala/mobile/Code;
   0      403      1    methName       Ljava/lang/String;
   0      403      2    args       [Ljava/lang/Object;
   0      403      3    argTypes       [Ljava/lang/Class;
   3      399      4    exceptionResult1       Ljava/lang/Object;
   218      129      7    exceptionResult2       Ljava/lang/Object;
   369      25      7    exceptionResult2       Ljava/lang/Object;
   278      64      9    cstr       Ljava/lang/reflect/Constructor;
   64      115      12    method       Ljava/lang/reflect/Method;
   69      110      14    obj       Ljava/lang/Object;
   161      18      15    result       Ljava/lang/Object;


public final scala.Tuple2 scala$mobile$Code$$boxValue(java.lang.Object);
  Code:
   Stack=4, Locals=14, Args_size=2
   0:	aload_1
   1:	astore_2
   2:	aload_2
   3:	instanceof	#204; //class java/lang/Byte
   6:	ifeq	31
   9:	aload_2
   10:	invokestatic	#210; //Method scala/runtime/BoxesRunTime.unboxToByte:(Ljava/lang/Object;)B
   13:	istore_3
   14:	new	#212; //class scala/Tuple2
   17:	dup
   18:	iload_3
   19:	invokestatic	#216; //Method java/lang/Byte.valueOf:(B)Ljava/lang/Byte;
   22:	getstatic	#219; //Field java/lang/Byte.TYPE:Ljava/lang/Class;
   25:	invokespecial	#222; //Method scala/Tuple2."<init>":(Ljava/lang/Object;Ljava/lang/Object;)V
   28:	goto	265
   31:	aload_2
   32:	instanceof	#224; //class java/lang/Boolean
   35:	ifeq	62
   38:	aload_2
   39:	invokestatic	#227; //Method scala/runtime/BoxesRunTime.unboxToBoolean:(Ljava/lang/Object;)Z
   42:	istore	4
   44:	new	#212; //class scala/Tuple2
   47:	dup
   48:	iload	4
   50:	invokestatic	#230; //Method java/lang/Boolean.valueOf:(Z)Ljava/lang/Boolean;
   53:	getstatic	#231; //Field java/lang/Boolean.TYPE:Ljava/lang/Class;
   56:	invokespecial	#222; //Method scala/Tuple2."<init>":(Ljava/lang/Object;Ljava/lang/Object;)V
   59:	goto	265
   62:	aload_2
   63:	instanceof	#233; //class java/lang/Character
   66:	ifeq	93
   69:	aload_2
   70:	invokestatic	#237; //Method scala/runtime/BoxesRunTime.unboxToChar:(Ljava/lang/Object;)C
   73:	istore	5
   75:	new	#212; //class scala/Tuple2
   78:	dup
   79:	iload	5
   81:	invokestatic	#240; //Method java/lang/Character.valueOf:(C)Ljava/lang/Character;
   84:	getstatic	#241; //Field java/lang/Character.TYPE:Ljava/lang/Class;
   87:	invokespecial	#222; //Method scala/Tuple2."<init>":(Ljava/lang/Object;Ljava/lang/Object;)V
   90:	goto	265
   93:	aload_2
   94:	instanceof	#243; //class java/lang/Short
   97:	ifeq	124
   100:	aload_2
   101:	invokestatic	#247; //Method scala/runtime/BoxesRunTime.unboxToShort:(Ljava/lang/Object;)S
   104:	istore	6
   106:	new	#212; //class scala/Tuple2
   109:	dup
   110:	iload	6
   112:	invokestatic	#250; //Method java/lang/Short.valueOf:(S)Ljava/lang/Short;
   115:	getstatic	#251; //Field java/lang/Short.TYPE:Ljava/lang/Class;
   118:	invokespecial	#222; //Method scala/Tuple2."<init>":(Ljava/lang/Object;Ljava/lang/Object;)V
   121:	goto	265
   124:	aload_2
   125:	instanceof	#253; //class java/lang/Integer
   128:	ifeq	155
   131:	aload_2
   132:	invokestatic	#257; //Method scala/runtime/BoxesRunTime.unboxToInt:(Ljava/lang/Object;)I
   135:	istore	7
   137:	new	#212; //class scala/Tuple2
   140:	dup
   141:	iload	7
   143:	invokestatic	#260; //Method java/lang/Integer.valueOf:(I)Ljava/lang/Integer;
   146:	getstatic	#261; //Field java/lang/Integer.TYPE:Ljava/lang/Class;
   149:	invokespecial	#222; //Method scala/Tuple2."<init>":(Ljava/lang/Object;Ljava/lang/Object;)V
   152:	goto	265
   155:	aload_2
   156:	instanceof	#263; //class java/lang/Long
   159:	ifeq	186
   162:	aload_2
   163:	invokestatic	#267; //Method scala/runtime/BoxesRunTime.unboxToLong:(Ljava/lang/Object;)J
   166:	lstore	8
   168:	new	#212; //class scala/Tuple2
   171:	dup
   172:	lload	8
   174:	invokestatic	#270; //Method java/lang/Long.valueOf:(J)Ljava/lang/Long;
   177:	getstatic	#271; //Field java/lang/Long.TYPE:Ljava/lang/Class;
   180:	invokespecial	#222; //Method scala/Tuple2."<init>":(Ljava/lang/Object;Ljava/lang/Object;)V
   183:	goto	265
   186:	aload_2
   187:	instanceof	#273; //class java/lang/Float
   190:	ifeq	217
   193:	aload_2
   194:	invokestatic	#277; //Method scala/runtime/BoxesRunTime.unboxToFloat:(Ljava/lang/Object;)F
   197:	fstore	10
   199:	new	#212; //class scala/Tuple2
   202:	dup
   203:	fload	10
   205:	invokestatic	#280; //Method java/lang/Float.valueOf:(F)Ljava/lang/Float;
   208:	getstatic	#281; //Field java/lang/Float.TYPE:Ljava/lang/Class;
   211:	invokespecial	#222; //Method scala/Tuple2."<init>":(Ljava/lang/Object;Ljava/lang/Object;)V
   214:	goto	265
   217:	aload_2
   218:	instanceof	#283; //class java/lang/Double
   221:	ifeq	248
   224:	aload_2
   225:	invokestatic	#287; //Method scala/runtime/BoxesRunTime.unboxToDouble:(Ljava/lang/Object;)D
   228:	dstore	11
   230:	new	#212; //class scala/Tuple2
   233:	dup
   234:	dload	11
   236:	invokestatic	#290; //Method java/lang/Double.valueOf:(D)Ljava/lang/Double;
   239:	getstatic	#291; //Field java/lang/Double.TYPE:Ljava/lang/Class;
   242:	invokespecial	#222; //Method scala/Tuple2."<init>":(Ljava/lang/Object;Ljava/lang/Object;)V
   245:	goto	265
   248:	aload_1
   249:	astore	13
   251:	new	#212; //class scala/Tuple2
   254:	dup
   255:	aload	13
   257:	aload	13
   259:	invokevirtual	#295; //Method java/lang/Object.getClass:()Ljava/lang/Class;
   262:	invokespecial	#222; //Method scala/Tuple2."<init>":(Ljava/lang/Object;Ljava/lang/Object;)V
   265:	areturn
  LineNumberTable: 
   line 162: 0
   line 163: 14
   line 162: 31
   line 164: 44
   line 162: 62
   line 165: 75
   line 162: 93
   line 166: 106
   line 162: 124
   line 167: 137
   line 162: 155
   line 168: 168
   line 162: 186
   line 169: 199
   line 162: 217
   line 170: 230
   line 172: 248
   line 173: 251
   line 162: 265

  LocalVariableTable: 
   Start  Length  Slot  Name   Signature
   0      266      0    this       Lscala/mobile/Code;
   0      266      1    value       Ljava/lang/Object;
   2      264      2    temp1       Ljava/lang/Object;
   14      14      3    temp2       B
   44      15      4    temp3       Z
   75      15      5    temp4       C
   106      15      6    temp5       S
   137      15      7    temp6       I
   168      15      8    temp7       J
   199      15      10    temp8       F
   230      15      11    temp9       D
   251      14      13    x       Ljava/lang/Object;


public scala.Function9 apply(java.lang.String);
  Code:
   Stack=4, Locals=2, Args_size=2
   0:	new	#317; //class scala/mobile/Code$$anonfun$apply$10
   3:	dup
   4:	aload_0
   5:	aload_1
   6:	invokespecial	#320; //Method scala/mobile/Code$$anonfun$apply$10."<init>":(Lscala/mobile/Code;Ljava/lang/String;)V
   9:	areturn
  LineNumberTable: 
   line 145: 0

  LocalVariableTable: 
   Start  Length  Slot  Name   Signature
   0      10      0    this       Lscala/mobile/Code;
   0      10      1    funName$10       Ljava/lang/String;

  Signature: length = 0x2
   01 42 

public scala.Function8 apply(java.lang.String);
  Code:
   Stack=4, Locals=2, Args_size=2
   0:	new	#325; //class scala/mobile/Code$$anonfun$apply$9
   3:	dup
   4:	aload_0
   5:	aload_1
   6:	invokespecial	#326; //Method scala/mobile/Code$$anonfun$apply$9."<init>":(Lscala/mobile/Code;Ljava/lang/String;)V
   9:	areturn
  LineNumberTable: 
   line 130: 0

  LocalVariableTable: 
   Start  Length  Slot  Name   Signature
   0      10      0    this       Lscala/mobile/Code;
   0      10      1    funName$9       Ljava/lang/String;

  Signature: length = 0x2
   01 48 

public scala.Function7 apply(java.lang.String);
  Code:
   Stack=4, Locals=2, Args_size=2
   0:	new	#331; //class scala/mobile/Code$$anonfun$apply$8
   3:	dup
   4:	aload_0
   5:	aload_1
   6:	invokespecial	#332; //Method scala/mobile/Code$$anonfun$apply$8."<init>":(Lscala/mobile/Code;Ljava/lang/String;)V
   9:	areturn
  LineNumberTable: 
   line 116: 0

  LocalVariableTable: 
   Start  Length  Slot  Name   Signature
   0      10      0    this       Lscala/mobile/Code;
   0      10      1    funName$8       Ljava/lang/String;

  Signature: length = 0x2
   01 4E 

public scala.Function6 apply(java.lang.String);
  Code:
   Stack=4, Locals=2, Args_size=2
   0:	new	#337; //class scala/mobile/Code$$anonfun$apply$7
   3:	dup
   4:	aload_0
   5:	aload_1
   6:	invokespecial	#338; //Method scala/mobile/Code$$anonfun$apply$7."<init>":(Lscala/mobile/Code;Ljava/lang/String;)V
   9:	areturn
  LineNumberTable: 
   line 103: 0

  LocalVariableTable: 
   Start  Length  Slot  Name   Signature
   0      10      0    this       Lscala/mobile/Code;
   0      10      1    funName$7       Ljava/lang/String;

  Signature: length = 0x2
   01 54 

public scala.Function5 apply(java.lang.String);
  Code:
   Stack=4, Locals=2, Args_size=2
   0:	new	#343; //class scala/mobile/Code$$anonfun$apply$6
   3:	dup
   4:	aload_0
   5:	aload_1
   6:	invokespecial	#344; //Method scala/mobile/Code$$anonfun$apply$6."<init>":(Lscala/mobile/Code;Ljava/lang/String;)V
   9:	areturn
  LineNumberTable: 
   line 91: 0

  LocalVariableTable: 
   Start  Length  Slot  Name   Signature
   0      10      0    this       Lscala/mobile/Code;
   0      10      1    funName$6       Ljava/lang/String;

  Signature: length = 0x2
   01 5A 

public scala.Function4 apply(java.lang.String);
  Code:
   Stack=4, Locals=2, Args_size=2
   0:	new	#349; //class scala/mobile/Code$$anonfun$apply$5
   3:	dup
   4:	aload_0
   5:	aload_1
   6:	invokespecial	#350; //Method scala/mobile/Code$$anonfun$apply$5."<init>":(Lscala/mobile/Code;Ljava/lang/String;)V
   9:	areturn
  LineNumberTable: 
   line 80: 0

  LocalVariableTable: 
   Start  Length  Slot  Name   Signature
   0      10      0    this       Lscala/mobile/Code;
   0      10      1    funName$5       Ljava/lang/String;

  Signature: length = 0x2
   01 60 

public scala.Function3 apply(java.lang.String);
  Code:
   Stack=4, Locals=2, Args_size=2
   0:	new	#355; //class scala/mobile/Code$$anonfun$apply$4
   3:	dup
   4:	aload_0
   5:	aload_1
   6:	invokespecial	#356; //Method scala/mobile/Code$$anonfun$apply$4."<init>":(Lscala/mobile/Code;Ljava/lang/String;)V
   9:	areturn
  LineNumberTable: 
   line 70: 0

  LocalVariableTable: 
   Start  Length  Slot  Name   Signature
   0      10      0    this       Lscala/mobile/Code;
   0      10      1    funName$4       Ljava/lang/String;

  Signature: length = 0x2
   01 66 

public scala.Function2 apply(java.lang.String);
  Code:
   Stack=4, Locals=2, Args_size=2
   0:	new	#361; //class scala/mobile/Code$$anonfun$apply$3
   3:	dup
   4:	aload_0
   5:	aload_1
   6:	invokespecial	#362; //Method scala/mobile/Code$$anonfun$apply$3."<init>":(Lscala/mobile/Code;Ljava/lang/String;)V
   9:	areturn
  LineNumberTable: 
   line 61: 0

  LocalVariableTable: 
   Start  Length  Slot  Name   Signature
   0      10      0    this       Lscala/mobile/Code;
   0      10      1    funName$3       Ljava/lang/String;

  Signature: length = 0x2
   01 6C 

public scala.Function1 apply(java.lang.String);
  Code:
   Stack=4, Locals=2, Args_size=2
   0:	new	#367; //class scala/mobile/Code$$anonfun$apply$2
   3:	dup
   4:	aload_0
   5:	aload_1
   6:	invokespecial	#368; //Method scala/mobile/Code$$anonfun$apply$2."<init>":(Lscala/mobile/Code;Ljava/lang/String;)V
   9:	areturn
  LineNumberTable: 
   line 53: 0

  LocalVariableTable: 
   Start  Length  Slot  Name   Signature
   0      10      0    this       Lscala/mobile/Code;
   0      10      1    funName$2       Ljava/lang/String;

  Signature: length = 0x2
   01 72 

public scala.Function0 apply(java.lang.String);
  Code:
   Stack=4, Locals=2, Args_size=2
   0:	new	#373; //class scala/mobile/Code$$anonfun$apply$1
   3:	dup
   4:	aload_0
   5:	aload_1
   6:	invokespecial	#374; //Method scala/mobile/Code$$anonfun$apply$1."<init>":(Lscala/mobile/Code;Ljava/lang/String;)V
   9:	areturn
  LineNumberTable: 
   line 46: 0

  LocalVariableTable: 
   Start  Length  Slot  Name   Signature
   0      10      0    this       Lscala/mobile/Code;
   0      10      1    funName$1       Ljava/lang/String;

  Signature: length = 0x2
   01 78 

}

