Compiled from "Code.scala"
public final class scala.mobile.Code$$anonfun$apply$9 extends java.lang.Object implements scala.Function8,scala.ScalaObject,java.io.Serializable
  SourceFile: "Code.scala"
  Scala: length = 0x
   
  InnerClass: 
   public final $anonfun$apply$9=class scala/mobile/Code$$anonfun$apply$9 of class scala/mobile/Code
  minor version: 0
  major version: 49
  Constant pool:
Asciz	SourceFile;
Asciz	Code.scala;
Asciz	<clinit>;
Asciz	()V;
Asciz	Code;
Asciz	serialVersionUID;
Asciz	J;
Asciz	scala/mobile/Code$$anonfun$apply$9;
class	scala/mobile/Code$$anonfun$apply$9
NameAndType	serialVersionUID:J
Field	scala/mobile/Code$$anonfun$apply$9.serialVersionUID:J
Asciz	funName$9;
Asciz	Ljava/lang/String;;
Asciz	$outer;
Asciz	Lscala/mobile/Code;;
Asciz	<init>;
Asciz	(Lscala/mobile/Code;Ljava/lang/String;)V;
Asciz	LineNumberTable;
Asciz	java/lang/NullPointerException;
class	java/lang/NullPointerException
NameAndType	"<init>":()V
Method	java/lang/NullPointerException."<init>":()V
NameAndType	$outer:Lscala/mobile/Code;
Field	scala/mobile/Code$$anonfun$apply$9.$outer:Lscala/mobile/Code;
NameAndType	funName$9:Ljava/lang/String;
Field	scala/mobile/Code$$anonfun$apply$9.funName$9:Ljava/lang/String;
Asciz	java/lang/Object;
class	java/lang/Object
Method	java/lang/Object."<init>":()V
Asciz	scala/Function8$class;
class	scala/Function8$class
Asciz	$init$;
Asciz	(Lscala/Function8;)V;
NameAndType	$init$:(Lscala/Function8;)V
Method	scala/Function8$class.$init$:(Lscala/Function8;)V
Asciz	this;
Asciz	Lscala/mobile/Code$$anonfun$apply$9;;
Asciz	LocalVariableTable;
Asciz	apply;
Asciz	(Ljava/lang/Object;Ljava/lang/Object;Ljava/lang/Object;Ljava/lang/Object;Ljava/lang/Object;Ljava/lang/Object;Ljava/lang/Object;Ljava/lang/Object;)Ljava/lang/Object;;
Asciz	scala/mobile/Code;
class	scala/mobile/Code
Asciz	scala$mobile$Code$$boxValue;
Asciz	(Ljava/lang/Object;)Lscala/Tuple2;;
NameAndType	scala$mobile$Code$$boxValue:(Ljava/lang/Object;)Lscala/Tuple2;
Method	scala/mobile/Code.scala$mobile$Code$$boxValue:(Ljava/lang/Object;)Lscala/Tuple2;
Asciz	scala/Array$;
class	scala/Array$
Asciz	MODULE$;
Asciz	Lscala/Array$;;
NameAndType	MODULE$:Lscala/Array$;
Field	scala/Array$.MODULE$:Lscala/Array$;
Asciz	scala/Predef$;
class	scala/Predef$
Asciz	Lscala/Predef$;;
NameAndType	MODULE$:Lscala/Predef$;
Field	scala/Predef$.MODULE$:Lscala/Predef$;
int	8;
Asciz	scala/Tuple2;
class	scala/Tuple2
Asciz	_1;
Asciz	()Ljava/lang/Object;;
NameAndType	_1:()Ljava/lang/Object;
Method	scala/Tuple2._1:()Ljava/lang/Object;
int	6;
int	7;
Asciz	wrapRefArray;
Asciz	([Ljava/lang/Object;)Lscala/collection/mutable/WrappedArray;;
NameAndType	wrapRefArray:([Ljava/lang/Object;)Lscala/collection/mutable/WrappedArray;
Method	scala/Predef$.wrapRefArray:([Ljava/lang/Object;)Lscala/collection/mutable/WrappedArray;
Asciz	scala/reflect/ClassManifest$;
class	scala/reflect/ClassManifest$
Asciz	Lscala/reflect/ClassManifest$;;
NameAndType	MODULE$:Lscala/reflect/ClassManifest$;
Field	scala/reflect/ClassManifest$.MODULE$:Lscala/reflect/ClassManifest$;
Asciz	classType;
Asciz	(Ljava/lang/Class;)Lscala/reflect/ClassManifest;;
NameAndType	classType:(Ljava/lang/Class;)Lscala/reflect/ClassManifest;
Method	scala/reflect/ClassManifest$.classType:(Ljava/lang/Class;)Lscala/reflect/ClassManifest;
Asciz	(Lscala/collection/Seq;Lscala/reflect/ClassManifest;)Ljava/lang/Object;;
NameAndType	apply:(Lscala/collection/Seq;Lscala/reflect/ClassManifest;)Ljava/lang/Object;
Method	scala/Array$.apply:(Lscala/collection/Seq;Lscala/reflect/ClassManifest;)Ljava/lang/Object;
Asciz	[Ljava/lang/Object;;
class	"[Ljava/lang/Object;"
Asciz	java/lang/Class;
class	java/lang/Class
Asciz	_2;
NameAndType	_2:()Ljava/lang/Object;
Method	scala/Tuple2._2:()Ljava/lang/Object;
Asciz	scala/reflect/NoManifest$;
class	scala/reflect/NoManifest$
Asciz	Lscala/reflect/NoManifest$;;
NameAndType	MODULE$:Lscala/reflect/NoManifest$;
Field	scala/reflect/NoManifest$.MODULE$:Lscala/reflect/NoManifest$;
Asciz	scala/reflect/OptManifest;
class	scala/reflect/OptManifest
Asciz	(Ljava/lang/Class;Lscala/reflect/OptManifest;Lscala/collection/Seq;)Lscala/reflect/ClassManifest;;
NameAndType	classType:(Ljava/lang/Class;Lscala/reflect/OptManifest;Lscala/collection/Seq;)Lscala/reflect/ClassManifest;
Method	scala/reflect/ClassManifest$.classType:(Ljava/lang/Class;Lscala/reflect/OptManifest;Lscala/collection/Seq;)Lscala/reflect/ClassManifest;
Asciz	[Ljava/lang/Class;;
class	"[Ljava/lang/Class;"
Asciz	scala$mobile$Code$$applyFun;
Asciz	(Ljava/lang/String;[Ljava/lang/Object;[Ljava/lang/Class;)Ljava/lang/Object;;
NameAndType	scala$mobile$Code$$applyFun:(Ljava/lang/String;[Ljava/lang/Object;[Ljava/lang/Class;)Ljava/lang/Object;
Method	scala/mobile/Code.scala$mobile$Code$$applyFun:(Ljava/lang/String;[Ljava/lang/Object;[Ljava/lang/Class;)Ljava/lang/Object;
Asciz	_0;
Asciz	Ljava/lang/Object;;
Asciz	_3;
Asciz	_4;
Asciz	_5;
Asciz	_6;
Asciz	_7;
Asciz	p0;
Asciz	Lscala/Tuple2;;
Asciz	p1;
Asciz	p2;
Asciz	p3;
Asciz	p4;
Asciz	p5;
Asciz	p6;
Asciz	p7;
Asciz	args;
Asciz	types;
Asciz	(TA0;TA1;TA2;TA3;TA4;TA5;TA6;TA7;)TR;;
Asciz	Signature;
Asciz	curry;
Asciz	()Lscala/Function1;;
Asciz	(Lscala/Function8;)Lscala/Function1;;
NameAndType	curry:(Lscala/Function8;)Lscala/Function1;
Method	scala/Function8$class.curry:(Lscala/Function8;)Lscala/Function1;
Asciz	toString;
Asciz	()Ljava/lang/String;;
Asciz	(Lscala/Function8;)Ljava/lang/String;;
NameAndType	toString:(Lscala/Function8;)Ljava/lang/String;
Method	scala/Function8$class.toString:(Lscala/Function8;)Ljava/lang/String;
Asciz	Scala;
Asciz	InnerClasses;
Asciz	$anonfun$apply$9;
Asciz	scala/Function8;
class	scala/Function8
Asciz	scala/ScalaObject;
class	scala/ScalaObject
Asciz	java/io/Serializable;
class	java/io/Serializable

{
public static final long serialVersionUID;
  Signature: J

private final java.lang.String funName$9;
  Signature: Ljava/lang/String;

private final scala.mobile.Code $outer;
  Signature: Lscala/mobile/Code;

public static {};
  Signature: ()V
  Code:
   Stack=2, Locals=0, Args_size=0
	lconst_0
	putstatic	Field serialVersionUID:J
	return
  Labels:

public scala.mobile.Code$$anonfun$apply$9(scala.mobile.Code, java.lang.String);
  Signature: (Lscala/mobile/Code;Ljava/lang/String;)V
  Code:
   Stack=2, Locals=3, Args_size=3
	aload_1
	ifnonnull	l1 // aload_0
	new	class java/lang/NullPointerException
	dup
	invokespecial	Method java/lang/NullPointerException."<init>":()V
	athrow
l1	aload_0
	aload_1
	putfield	Field $outer:Lscala/mobile/Code;
	aload_0
	aload_2
	putfield	Field funName$9:Ljava/lang/String;
	aload_0
	invokespecial	Method java/lang/Object."<init>":()V
	aload_0
	invokestatic	Method scala/Function8$class.$init$:(Lscala/Function8;)V
	return
  Labels:
   	l1 = 12 // aload_0
  LocalVariableTable: 
   Start  Length  Slot  Name   Signature
   0      31      0    this       Lscala/mobile/Code$$anonfun$apply$9;
   0      31      1    $outer       Lscala/mobile/Code;


public final java.lang.Object apply(java.lang.Object, java.lang.Object, java.lang.Object, java.lang.Object, java.lang.Object, java.lang.Object, java.lang.Object, java.lang.Object);
  Signature: (Ljava/lang/Object;Ljava/lang/Object;Ljava/lang/Object;Ljava/lang/Object;Ljava/lang/Object;Ljava/lang/Object;Ljava/lang/Object;Ljava/lang/Object;)Ljava/lang/Object;
  Code:
   Stack=7, Locals=20, Args_size=9
	aload_0
	getfield	Field $outer:Lscala/mobile/Code;
	astore	19
	aload_0
	getfield	Field $outer:Lscala/mobile/Code;
	aload_1
	invokevirtual	Method scala/mobile/Code.scala$mobile$Code$$boxValue:(Ljava/lang/Object;)Lscala/Tuple2;
	astore	9
	aload_0
	getfield	Field $outer:Lscala/mobile/Code;
	aload_2
	invokevirtual	Method scala/mobile/Code.scala$mobile$Code$$boxValue:(Ljava/lang/Object;)Lscala/Tuple2;
	astore	10
	aload_0
	getfield	Field $outer:Lscala/mobile/Code;
	aload_3
	invokevirtual	Method scala/mobile/Code.scala$mobile$Code$$boxValue:(Ljava/lang/Object;)Lscala/Tuple2;
	astore	11
	aload_0
	getfield	Field $outer:Lscala/mobile/Code;
	aload	4
	invokevirtual	Method scala/mobile/Code.scala$mobile$Code$$boxValue:(Ljava/lang/Object;)Lscala/Tuple2;
	astore	12
	aload_0
	getfield	Field $outer:Lscala/mobile/Code;
	aload	5
	invokevirtual	Method scala/mobile/Code.scala$mobile$Code$$boxValue:(Ljava/lang/Object;)Lscala/Tuple2;
	astore	13
	aload_0
	getfield	Field $outer:Lscala/mobile/Code;
	aload	6
	invokevirtual	Method scala/mobile/Code.scala$mobile$Code$$boxValue:(Ljava/lang/Object;)Lscala/Tuple2;
	astore	14
	aload_0
	getfield	Field $outer:Lscala/mobile/Code;
	aload	7
	invokevirtual	Method scala/mobile/Code.scala$mobile$Code$$boxValue:(Ljava/lang/Object;)Lscala/Tuple2;
	astore	15
	aload_0
	getfield	Field $outer:Lscala/mobile/Code;
	aload	8
	invokevirtual	Method scala/mobile/Code.scala$mobile$Code$$boxValue:(Ljava/lang/Object;)Lscala/Tuple2;
	astore	16
	getstatic	Field scala/Array$.MODULE$:Lscala/Array$;
	getstatic	Field scala/Predef$.MODULE$:Lscala/Predef$;
	ldc	int 8
	anewarray	class java/lang/Object
	dup
	iconst_0
	aload	9
	invokevirtual	Method scala/Tuple2._1:()Ljava/lang/Object;
	aastore
	dup
	iconst_1
	aload	10
	invokevirtual	Method scala/Tuple2._1:()Ljava/lang/Object;
	aastore
	dup
	iconst_2
	aload	11
	invokevirtual	Method scala/Tuple2._1:()Ljava/lang/Object;
	aastore
	dup
	iconst_3
	aload	12
	invokevirtual	Method scala/Tuple2._1:()Ljava/lang/Object;
	aastore
	dup
	iconst_4
	aload	13
	invokevirtual	Method scala/Tuple2._1:()Ljava/lang/Object;
	aastore
	dup
	iconst_5
	aload	14
	invokevirtual	Method scala/Tuple2._1:()Ljava/lang/Object;
	aastore
	dup
	ldc	int 6
	aload	15
	invokevirtual	Method scala/Tuple2._1:()Ljava/lang/Object;
	aastore
	dup
	ldc	int 7
	aload	16
	invokevirtual	Method scala/Tuple2._1:()Ljava/lang/Object;
	aastore
	invokevirtual	Method scala/Predef$.wrapRefArray:([Ljava/lang/Object;)Lscala/collection/mutable/WrappedArray;
	getstatic	Field scala/reflect/ClassManifest$.MODULE$:Lscala/reflect/ClassManifest$;
	ldc	class java/lang/Object
	invokevirtual	Method scala/reflect/ClassManifest$.classType:(Ljava/lang/Class;)Lscala/reflect/ClassManifest;
	invokevirtual	Method scala/Array$.apply:(Lscala/collection/Seq;Lscala/reflect/ClassManifest;)Ljava/lang/Object;
	checkcast	class "[Ljava/lang/Object;"
	astore	17
	getstatic	Field scala/Array$.MODULE$:Lscala/Array$;
	getstatic	Field scala/Predef$.MODULE$:Lscala/Predef$;
	ldc	int 8
	anewarray	class java/lang/Class
	dup
	iconst_0
	aload	9
	invokevirtual	Method scala/Tuple2._2:()Ljava/lang/Object;
	checkcast	class java/lang/Class
	aastore
	dup
	iconst_1
	aload	10
	invokevirtual	Method scala/Tuple2._2:()Ljava/lang/Object;
	checkcast	class java/lang/Class
	aastore
	dup
	iconst_2
	aload	11
	invokevirtual	Method scala/Tuple2._2:()Ljava/lang/Object;
	checkcast	class java/lang/Class
	aastore
	dup
	iconst_3
	aload	12
	invokevirtual	Method scala/Tuple2._2:()Ljava/lang/Object;
	checkcast	class java/lang/Class
	aastore
	dup
	iconst_4
	aload	13
	invokevirtual	Method scala/Tuple2._2:()Ljava/lang/Object;
	checkcast	class java/lang/Class
	aastore
	dup
	iconst_5
	aload	14
	invokevirtual	Method scala/Tuple2._2:()Ljava/lang/Object;
	checkcast	class java/lang/Class
	aastore
	dup
	ldc	int 6
	aload	15
	invokevirtual	Method scala/Tuple2._2:()Ljava/lang/Object;
	checkcast	class java/lang/Class
	aastore
	dup
	ldc	int 7
	aload	16
	invokevirtual	Method scala/Tuple2._2:()Ljava/lang/Object;
	checkcast	class java/lang/Class
	aastore
	checkcast	class "[Ljava/lang/Object;"
	invokevirtual	Method scala/Predef$.wrapRefArray:([Ljava/lang/Object;)Lscala/collection/mutable/WrappedArray;
	getstatic	Field scala/reflect/ClassManifest$.MODULE$:Lscala/reflect/ClassManifest$;
	ldc	class java/lang/Class
	getstatic	Field scala/reflect/NoManifest$.MODULE$:Lscala/reflect/NoManifest$;
	getstatic	Field scala/Predef$.MODULE$:Lscala/Predef$;
	iconst_0
	anewarray	class scala/reflect/OptManifest
	checkcast	class "[Ljava/lang/Object;"
	invokevirtual	Method scala/Predef$.wrapRefArray:([Ljava/lang/Object;)Lscala/collection/mutable/WrappedArray;
	invokevirtual	Method scala/reflect/ClassManifest$.classType:(Ljava/lang/Class;Lscala/reflect/OptManifest;Lscala/collection/Seq;)Lscala/reflect/ClassManifest;
	invokevirtual	Method scala/Array$.apply:(Lscala/collection/Seq;Lscala/reflect/ClassManifest;)Ljava/lang/Object;
	checkcast	class "[Ljava/lang/Class;"
	astore	18
	aload_0
	getfield	Field $outer:Lscala/mobile/Code;
	aload_0
	getfield	Field funName$9:Ljava/lang/String;
	aload	17
	aload	18
	invokevirtual	Method scala/mobile/Code.scala$mobile$Code$$applyFun:(Ljava/lang/String;[Ljava/lang/Object;[Ljava/lang/Class;)Ljava/lang/Object;
	areturn
  Labels:
  LocalVariableTable: 
   Start  Length  Slot  Name   Signature
   0      342      0    this       Lscala/mobile/Code$$anonfun$apply$9;
   6      336      1    _0       Ljava/lang/Object;
   6      336      2    _1       Ljava/lang/Object;
   6      336      3    _2       Ljava/lang/Object;
   6      336      4    _3       Ljava/lang/Object;
   6      336      5    _4       Ljava/lang/Object;
   6      336      6    _5       Ljava/lang/Object;
   6      336      7    _6       Ljava/lang/Object;
   6      336      8    _7       Ljava/lang/Object;
   16      325      9    p0       Lscala/Tuple2;
   26      315      10    p1       Lscala/Tuple2;
   36      305      11    p2       Lscala/Tuple2;
   47      294      12    p3       Lscala/Tuple2;
   58      283      13    p4       Lscala/Tuple2;
   69      272      14    p5       Lscala/Tuple2;
   80      261      15    p6       Lscala/Tuple2;
   91      250      16    p7       Lscala/Tuple2;
   187      154      17    args       [Ljava/lang/Object;
   326      15      18    types       [Ljava/lang/Class;

  Signature: length = 0x2
   00 7C 

public scala.Function1 curry();
  Signature: ()Lscala/Function1;
  Code:
   Stack=1, Locals=1, Args_size=1
	aload_0
	invokestatic	Method scala/Function8$class.curry:(Lscala/Function8;)Lscala/Function1;
	areturn
  Labels:

public java.lang.String toString();
  Signature: ()Ljava/lang/String;
  Code:
   Stack=1, Locals=1, Args_size=1
	aload_0
	invokestatic	Method scala/Function8$class.toString:(Lscala/Function8;)Ljava/lang/String;
	areturn
  Labels:

}

