Compiled from "Location.scala"
public class scala.mobile.Location extends java.lang.Object implements scala.ScalaObject
  SourceFile: "Location.scala"
  ScalaSig: length = 0x2D3
   05 00 78 06 08 01 02 FFFFFF84 FFFFFF80 FFFFFF80 FFFFFF80 00 07 02 08 4C
   6F 63 61 74 69 6F 6E 0A 02 03 04 01 06 6D 6F 62
   69 6C 65 0A 01 05 01 05 73 63 61 6C 61 03 00 13
   03 00 08 10 10 02 09 0E 0D 01 0A 0A 02 0B 0C 01
   04 6C 61 6E 67 0A 01 0D 01 04 6A 61 76 61 09 02
   0F 0A 02 06 4F 62 6A 65 63 74 10 02 11 12 0D 01
   04 09 02 13 04 02 0B 53 63 61 6C 61 4F 62 6A 65
   63 74 08 08 15 00 FFFFFF82 FFFFFF80 FFFFFFA0 FFFFFF80 04 16 01 03 75 72
   6C 10 02 17 1A 0D 01 18 0A 02 19 0C 01 03 6E 65
   74 09 02 1B 18 02 03 55 52 4C 08 05 1D 00 FFFFFF84 00
   1E 01 06 3C 69 6E 69 74 3E 14 02 1F 21 10 02 20
   00 0D 01 02 08 05 15 1C FFFFFFC0 00 16 08 07 23 00 FFFFFFC0
   FFFFFF80 FFFFFF84 04 24 01 06 6C 63 61 63 68 65 15 01 25 10
   04 26 2B 16 2D 0D 01 27 0A 02 28 29 01 07 6D 75
   74 61 62 6C 65 0A 02 2A 04 01 0A 63 6F 6C 6C 65
   63 74 69 6F 6E 09 02 2C 27 02 03 4D 61 70 10 02
   09 2E 09 02 2F 0A 02 0B 43 6C 61 73 73 4C 6F 61
   64 65 72 08 07 31 00 FFFFFFC0 FFFFFF80 FFFFFF84 04 32 01 0A 6C 63
   61 63 68 65 5F 24 65 71 14 02 33 36 10 02 11 34
   09 02 35 04 02 04 55 6E 69 74 08 07 37 30 FFFFFF81 FFFFFF80
   FFFFFFC0 00 25 01 03 78 24 31 08 06 39 00 FFFFFFA0 FFFFFFA0 04 25
   01 07 6C 63 61 63 68 65 20 08 07 3B 00 FFFFFFC2 FFFFFF80 FFFFFF84
   04 3C 01 06 6C 6F 61 64 65 72 15 01 2D 08 06 3E
   00 FFFFFFA0 FFFFFF80 04 2D 01 07 6C 6F 61 64 65 72 20 08 07
   40 00 FFFFFFC0 FFFFFF80 FFFFFF84 04 41 01 06 63 63 61 63 68 65 15
   01 42 10 04 26 2B 43 4A 10 02 44 47 0E 02 11 45
   09 02 46 04 01 06 50 72 65 64 65 66 09 02 48 49
   02 06 53 74 72 69 6E 67 0A 02 46 04 30 02 4B 50
   10 03 09 4C 4E 09 02 4D 0A 02 05 43 6C 61 73 73
   10 02 4F 50 0C 00 04 08 51 00 FFFFFF84 FFFFFF80 FFFFFF80 FFFFFF82 00 52
   02 01 54 11 02 53 56 10 02 11 54 09 02 55 04 02
   07 4E 6F 74 68 69 6E 67 10 02 11 57 09 02 58 04
   02 03 41 6E 79 08 07 5A 00 FFFFFFC0 FFFFFF80 FFFFFF84 04 5B 01 0A
   63 63 61 63 68 65 5F 24 65 71 14 02 33 5C 08 07
   37 59 FFFFFF81 FFFFFF80 FFFFFFC0 00 5D 10 04 26 2B 43 5E 30 02 5F
   61 10 03 09 4C 60 10 02 4F 61 04 08 51 00 FFFFFF84 FFFFFF80
   FFFFFF80 FFFFFF82 00 52 08 06 63 00 FFFFFFA0 FFFFFFA0 04 64 01 07 63 63
   61 63 68 65 20 10 04 26 2B 43 65 30 02 66 68 10
   03 09 4C 67 10 02 4F 68 04 08 51 00 FFFFFF84 FFFFFF80 FFFFFF80 FFFFFF82
   00 52 08 05 6A 00 FFFFFF84 00 6B 01 06 63 72 65 61 74
   65 14 02 6C 6F 10 02 20 6D 09 02 6E 02 02 04 43
   6F 64 65 08 05 70 69 FFFFFFC0 00 43 01 09 63 6C 61 73
   73 4E 61 6D 65 07 05 72 02 FFFFFF88 02 73 01 08 4C 6F
   63 61 74 69 6F 6E 10 02 20 74 06 08 01 02 FFFFFF84 FFFFFF80
   FFFFFF80 FFFFFF88 02 75 13 03 74 1F 10 08 05 1D 74 FFFFFF84 00 77
   14 01 73 
  minor version: 0
  major version: 49
  Constant pool:
const #1 = Asciz	SourceFile;
const #2 = Asciz	Location.scala;
const #3 = Asciz	ccache;
const #4 = Asciz	Lscala/collection/mutable/Map;;
const #5 = Asciz	Lscala/collection/mutable/Map<Ljava/lang/String;Ljava/lang/Class<*>;>;;
const #6 = Asciz	Signature;
const #7 = Asciz	loader;
const #8 = Asciz	Ljava/lang/ClassLoader;;
const #9 = Asciz	lcache;
const #10 = Asciz	Lscala/collection/mutable/Map<Ljava/net/URL;Ljava/lang/ClassLoader;>;;
const #11 = Asciz	<init>;
const #12 = Asciz	(Ljava/net/URL;)V;
const #13 = Asciz	Code;
const #14 = Asciz	LineNumberTable;
const #15 = Asciz	java/lang/Object;
const #16 = class	#15;	//  java/lang/Object
const #17 = Asciz	()V;
const #18 = NameAndType	#11:#17;//  "<init>":()V
const #19 = Method	#16.#18;	//  java/lang/Object."<init>":()V
const #20 = Asciz	scala/collection/mutable/HashMap;
const #21 = class	#20;	//  scala/collection/mutable/HashMap
const #22 = Method	#21.#18;	//  scala/collection/mutable/HashMap."<init>":()V
const #23 = Asciz	scala/mobile/Location;
const #24 = class	#23;	//  scala/mobile/Location
const #25 = NameAndType	#9:#4;//  lcache:Lscala/collection/mutable/Map;
const #26 = Field	#24.#25;	//  scala/mobile/Location.lcache:Lscala/collection/mutable/Map;
const #27 = Asciz	java/lang/ClassLoader;
const #28 = class	#27;	//  java/lang/ClassLoader
const #29 = Asciz	getSystemClassLoader;
const #30 = Asciz	()Ljava/lang/ClassLoader;;
const #31 = NameAndType	#29:#30;//  getSystemClassLoader:()Ljava/lang/ClassLoader;
const #32 = Method	#28.#31;	//  java/lang/ClassLoader.getSystemClassLoader:()Ljava/lang/ClassLoader;
const #33 = Asciz	()Lscala/collection/mutable/Map;;
const #34 = NameAndType	#9:#33;//  lcache:()Lscala/collection/mutable/Map;
const #35 = Method	#24.#34;	//  scala/mobile/Location.lcache:()Lscala/collection/mutable/Map;
const #36 = Asciz	scala/collection/MapLike;
const #37 = class	#36;	//  scala/collection/MapLike
const #38 = Asciz	get;
const #39 = Asciz	(Ljava/lang/Object;)Lscala/Option;;
const #40 = NameAndType	#38:#39;//  get:(Ljava/lang/Object;)Lscala/Option;
const #41 = InterfaceMethod	#37.#40;	//  scala/collection/MapLike.get:(Ljava/lang/Object;)Lscala/Option;
const #42 = Asciz	scala/Some;
const #43 = class	#42;	//  scala/Some
const #44 = Asciz	x;
const #45 = Asciz	()Ljava/lang/Object;;
const #46 = NameAndType	#44:#45;//  x:()Ljava/lang/Object;
const #47 = Method	#43.#46;	//  scala/Some.x:()Ljava/lang/Object;
const #48 = Asciz	scala/MatchError;
const #49 = class	#48;	//  scala/MatchError
const #50 = Asciz	scala/Option;
const #51 = class	#50;	//  scala/Option
const #52 = Asciz	toString;
const #53 = Asciz	()Ljava/lang/String;;
const #54 = NameAndType	#52:#53;//  toString:()Ljava/lang/String;
const #55 = Method	#51.#54;	//  scala/Option.toString:()Ljava/lang/String;
const #56 = Asciz	(Ljava/lang/String;)V;
const #57 = NameAndType	#11:#56;//  "<init>":(Ljava/lang/String;)V
const #58 = Method	#49.#57;	//  scala/MatchError."<init>":(Ljava/lang/String;)V
const #59 = Asciz	java/net/URLClassLoader;
const #60 = class	#59;	//  java/net/URLClassLoader
const #61 = Asciz	scala/Array$;
const #62 = class	#61;	//  scala/Array$
const #63 = Asciz	MODULE$;
const #64 = Asciz	Lscala/Array$;;
const #65 = NameAndType	#63:#64;//  MODULE$:Lscala/Array$;
const #66 = Field	#62.#65;	//  scala/Array$.MODULE$:Lscala/Array$;
const #67 = Asciz	scala/Predef$;
const #68 = class	#67;	//  scala/Predef$
const #69 = Asciz	Lscala/Predef$;;
const #70 = NameAndType	#63:#69;//  MODULE$:Lscala/Predef$;
const #71 = Field	#68.#70;	//  scala/Predef$.MODULE$:Lscala/Predef$;
const #72 = Asciz	java/net/URL;
const #73 = class	#72;	//  java/net/URL
const #74 = Asciz	[Ljava/lang/Object;;
const #75 = class	#74;	//  "[Ljava/lang/Object;"
const #76 = Asciz	wrapRefArray;
const #77 = Asciz	([Ljava/lang/Object;)Lscala/collection/mutable/WrappedArray;;
const #78 = NameAndType	#76:#77;//  wrapRefArray:([Ljava/lang/Object;)Lscala/collection/mutable/WrappedArray;
const #79 = Method	#68.#78;	//  scala/Predef$.wrapRefArray:([Ljava/lang/Object;)Lscala/collection/mutable/WrappedArray;
const #80 = Asciz	scala/reflect/ClassManifest$;
const #81 = class	#80;	//  scala/reflect/ClassManifest$
const #82 = Asciz	Lscala/reflect/ClassManifest$;;
const #83 = NameAndType	#63:#82;//  MODULE$:Lscala/reflect/ClassManifest$;
const #84 = Field	#81.#83;	//  scala/reflect/ClassManifest$.MODULE$:Lscala/reflect/ClassManifest$;
const #85 = Asciz	classType;
const #86 = Asciz	(Ljava/lang/Class;)Lscala/reflect/ClassManifest;;
const #87 = NameAndType	#85:#86;//  classType:(Ljava/lang/Class;)Lscala/reflect/ClassManifest;
const #88 = Method	#81.#87;	//  scala/reflect/ClassManifest$.classType:(Ljava/lang/Class;)Lscala/reflect/ClassManifest;
const #89 = Asciz	apply;
const #90 = Asciz	(Lscala/collection/Seq;Lscala/reflect/ClassManifest;)Ljava/lang/Object;;
const #91 = NameAndType	#89:#90;//  apply:(Lscala/collection/Seq;Lscala/reflect/ClassManifest;)Ljava/lang/Object;
const #92 = Method	#62.#91;	//  scala/Array$.apply:(Lscala/collection/Seq;Lscala/reflect/ClassManifest;)Ljava/lang/Object;
const #93 = Asciz	[Ljava/net/URL;;
const #94 = class	#93;	//  "[Ljava/net/URL;"
const #95 = Asciz	([Ljava/net/URL;)V;
const #96 = NameAndType	#11:#95;//  "<init>":([Ljava/net/URL;)V
const #97 = Method	#60.#96;	//  java/net/URLClassLoader."<init>":([Ljava/net/URL;)V
const #98 = Asciz	scala/collection/mutable/MapLike;
const #99 = class	#98;	//  scala/collection/mutable/MapLike
const #100 = Asciz	update;
const #101 = Asciz	(Ljava/lang/Object;Ljava/lang/Object;)V;
const #102 = NameAndType	#100:#101;//  update:(Ljava/lang/Object;Ljava/lang/Object;)V
const #103 = InterfaceMethod	#99.#102;	//  scala/collection/mutable/MapLike.update:(Ljava/lang/Object;Ljava/lang/Object;)V
const #104 = NameAndType	#7:#8;//  loader:Ljava/lang/ClassLoader;
const #105 = Field	#24.#104;	//  scala/mobile/Location.loader:Ljava/lang/ClassLoader;
const #106 = NameAndType	#3:#4;//  ccache:Lscala/collection/mutable/Map;
const #107 = Field	#24.#106;	//  scala/mobile/Location.ccache:Lscala/collection/mutable/Map;
const #108 = Asciz	this;
const #109 = Asciz	Lscala/mobile/Location;;
const #110 = Asciz	url;
const #111 = Asciz	Ljava/net/URL;;
const #112 = Asciz	temp2;
const #113 = Asciz	Lscala/Some;;
const #114 = Asciz	temp3;
const #115 = Asciz	cl;
const #116 = Asciz	Ljava/net/URLClassLoader;;
const #117 = Asciz	temp1;
const #118 = Asciz	Lscala/Option;;
const #119 = Asciz	LocalVariableTable;
const #120 = Asciz	create;
const #121 = Asciz	(Ljava/lang/String;)Lscala/mobile/Code;;
const #122 = Asciz	scala/mobile/Code;
const #123 = class	#122;	//  scala/mobile/Code
const #124 = NameAndType	#3:#33;//  ccache:()Lscala/collection/mutable/Map;
const #125 = Method	#24.#124;	//  scala/mobile/Location.ccache:()Lscala/collection/mutable/Map;
const #126 = Asciz	Ljava/lang/Object;;
const #127 = NameAndType	#44:#126;//  x:Ljava/lang/Object;
const #128 = Field	#43.#127;	//  scala/Some.x:Ljava/lang/Object;
const #129 = Asciz	java/lang/Class;
const #130 = class	#129;	//  java/lang/Class
const #131 = NameAndType	#7:#30;//  loader:()Ljava/lang/ClassLoader;
const #132 = Method	#24.#131;	//  scala/mobile/Location.loader:()Ljava/lang/ClassLoader;
const #133 = Asciz	loadClass;
const #134 = Asciz	(Ljava/lang/String;)Ljava/lang/Class;;
const #135 = NameAndType	#133:#134;//  loadClass:(Ljava/lang/String;)Ljava/lang/Class;
const #136 = Method	#28.#135;	//  java/lang/ClassLoader.loadClass:(Ljava/lang/String;)Ljava/lang/Class;
const #137 = Asciz	isInterface;
const #138 = Asciz	()Z;
const #139 = NameAndType	#137:#138;//  isInterface:()Z
const #140 = Method	#130.#139;	//  java/lang/Class.isInterface:()Z
const #141 = Asciz	scala/collection/mutable/StringBuilder;
const #142 = class	#141;	//  scala/collection/mutable/StringBuilder
const #143 = Method	#142.#18;	//  scala/collection/mutable/StringBuilder."<init>":()V
const #144 = Asciz	append;
const #145 = Asciz	(Ljava/lang/Object;)Lscala/collection/mutable/StringBuilder;;
const #146 = NameAndType	#144:#145;//  append:(Ljava/lang/Object;)Lscala/collection/mutable/StringBuilder;
const #147 = Method	#142.#146;	//  scala/collection/mutable/StringBuilder.append:(Ljava/lang/Object;)Lscala/collection/mutable/StringBuilder;
const #148 = Asciz	$class;
const #149 = String	#148;	//  $class
const #150 = Method	#142.#54;	//  scala/collection/mutable/StringBuilder.toString:()Ljava/lang/String;
const #151 = Asciz	$;
const #152 = String	#151;	//  $
const #153 = Asciz	(Ljava/lang/Class;)V;
const #154 = NameAndType	#11:#153;//  "<init>":(Ljava/lang/Class;)V
const #155 = Method	#123.#154;	//  scala/mobile/Code."<init>":(Ljava/lang/Class;)V
const #156 = Asciz	className;
const #157 = Asciz	Ljava/lang/String;;
const #158 = Asciz	temp5;
const #159 = Asciz	temp6;
const #160 = Asciz	Ljava/lang/Class;;
const #161 = Asciz	clazz;
const #162 = Asciz	temp4;
const #163 = Asciz	ccache_$eq;
const #164 = Asciz	(Lscala/collection/mutable/Map;)V;
const #165 = Asciz	(Lscala/collection/mutable/Map<Ljava/lang/String;Ljava/lang/Class<*>;>;)V;
const #166 = Asciz	()Lscala/collection/mutable/Map<Ljava/lang/String;Ljava/lang/Class<*>;>;;
const #167 = Asciz	lcache_$eq;
const #168 = Asciz	(Lscala/collection/mutable/Map<Ljava/net/URL;Ljava/lang/ClassLoader;>;)V;
const #169 = Asciz	()Lscala/collection/mutable/Map<Ljava/net/URL;Ljava/lang/ClassLoader;>;;
const #170 = Asciz	ScalaSig;
const #171 = Asciz	scala/ScalaObject;
const #172 = class	#171;	//  scala/ScalaObject

{
public scala.mobile.Location(java.net.URL);
  Code:
   Stack=9, Locals=6, Args_size=2
   0:	aload_0
   1:	invokespecial	#19; //Method java/lang/Object."<init>":()V
   4:	aload_0
   5:	new	#21; //class scala/collection/mutable/HashMap
   8:	dup
   9:	invokespecial	#22; //Method scala/collection/mutable/HashMap."<init>":()V
   12:	putfield	#26; //Field lcache:Lscala/collection/mutable/Map;
   15:	aload_0
   16:	aload_1
   17:	ifnonnull	26
   20:	invokestatic	#32; //Method java/lang/ClassLoader.getSystemClassLoader:()Ljava/lang/ClassLoader;
   23:	goto	142
   26:	aload_0
   27:	invokespecial	#35; //Method lcache:()Lscala/collection/mutable/Map;
   30:	aload_1
   31:	invokeinterface	#41,  2; //InterfaceMethod scala/collection/MapLike.get:(Ljava/lang/Object;)Lscala/Option;
   36:	astore	5
   38:	aload	5
   40:	instanceof	#43; //class scala/Some
   43:	ifeq	81
   46:	aload	5
   48:	checkcast	#43; //class scala/Some
   51:	astore_2
   52:	aload_2
   53:	invokevirtual	#47; //Method scala/Some.x:()Ljava/lang/Object;
   56:	checkcast	#28; //class java/lang/ClassLoader
   59:	astore_3
   60:	iconst_1
   61:	ifeq	68
   64:	aload_3
   65:	goto	142
   68:	new	#49; //class scala/MatchError
   71:	dup
   72:	aload	5
   74:	invokevirtual	#55; //Method scala/Option.toString:()Ljava/lang/String;
   77:	invokespecial	#58; //Method scala/MatchError."<init>":(Ljava/lang/String;)V
   80:	athrow
   81:	iconst_1
   82:	ifeq	157
   85:	new	#60; //class java/net/URLClassLoader
   88:	dup
   89:	getstatic	#66; //Field scala/Array$.MODULE$:Lscala/Array$;
   92:	getstatic	#71; //Field scala/Predef$.MODULE$:Lscala/Predef$;
   95:	iconst_1
   96:	anewarray	#73; //class java/net/URL
   99:	dup
   100:	iconst_0
   101:	aload_1
   102:	aastore
   103:	checkcast	#75; //class "[Ljava/lang/Object;"
   106:	invokevirtual	#79; //Method scala/Predef$.wrapRefArray:([Ljava/lang/Object;)Lscala/collection/mutable/WrappedArray;
   109:	getstatic	#84; //Field scala/reflect/ClassManifest$.MODULE$:Lscala/reflect/ClassManifest$;
   112:	ldc	#73; //class java/net/URL
   114:	invokevirtual	#88; //Method scala/reflect/ClassManifest$.classType:(Ljava/lang/Class;)Lscala/reflect/ClassManifest;
   117:	invokevirtual	#92; //Method scala/Array$.apply:(Lscala/collection/Seq;Lscala/reflect/ClassManifest;)Ljava/lang/Object;
   120:	checkcast	#94; //class "[Ljava/net/URL;"
   123:	invokespecial	#97; //Method java/net/URLClassLoader."<init>":([Ljava/net/URL;)V
   126:	astore	4
   128:	aload_0
   129:	invokespecial	#35; //Method lcache:()Lscala/collection/mutable/Map;
   132:	aload_1
   133:	aload	4
   135:	invokeinterface	#103,  3; //InterfaceMethod scala/collection/mutable/MapLike.update:(Ljava/lang/Object;Ljava/lang/Object;)V
   140:	aload	4
   142:	putfield	#105; //Field loader:Ljava/lang/ClassLoader;
   145:	aload_0
   146:	new	#21; //class scala/collection/mutable/HashMap
   149:	dup
   150:	invokespecial	#22; //Method scala/collection/mutable/HashMap."<init>":()V
   153:	putfield	#107; //Field ccache:Lscala/collection/mutable/Map;
   156:	return
   157:	new	#49; //class scala/MatchError
   160:	dup
   161:	aload	5
   163:	invokevirtual	#55; //Method scala/Option.toString:()Ljava/lang/String;
   166:	invokespecial	#58; //Method scala/MatchError."<init>":(Ljava/lang/String;)V
   169:	athrow
  LineNumberTable: 
   line 36: 0
   line 40: 4
   line 44: 15
   line 45: 20
   line 47: 26
   line 44: 46
   line 21: 60
   line 49: 64
   line 47: 68
   line 21: 81
   line 51: 85
   line 52: 128
   line 53: 133
   line 52: 135
   line 53: 140
   line 44: 142
   line 58: 145
   line 47: 157

  LocalVariableTable: 
   Start  Length  Slot  Name   Signature
   0      170      0    this       Lscala/mobile/Location;
   0      170      1    url       Ljava/net/URL;
   52      29      2    temp2       Lscala/Some;
   60      21      3    temp3       Ljava/lang/ClassLoader;
   128      14      4    cl       Ljava/net/URLClassLoader;
   38      104      5    temp1       Lscala/Option;
   157      13      5    temp1       Lscala/Option;


public scala.mobile.Code create(java.lang.String);
  Code:
   Stack=5, Locals=6, Args_size=2
   0:	new	#123; //class scala/mobile/Code
   3:	dup
   4:	aload_0
   5:	invokespecial	#125; //Method ccache:()Lscala/collection/mutable/Map;
   8:	aload_1
   9:	invokeinterface	#41,  2; //InterfaceMethod scala/collection/MapLike.get:(Ljava/lang/Object;)Lscala/Option;
   14:	astore	5
   16:	aload	5
   18:	instanceof	#43; //class scala/Some
   21:	ifeq	59
   24:	aload	5
   26:	checkcast	#43; //class scala/Some
   29:	astore_2
   30:	aload_2
   31:	getfield	#128; //Field scala/Some.x:Ljava/lang/Object;
   34:	checkcast	#130; //class java/lang/Class
   37:	astore_3
   38:	iconst_1
   39:	ifeq	46
   42:	aload_3
   43:	goto	148
   46:	new	#49; //class scala/MatchError
   49:	dup
   50:	aload	5
   52:	invokevirtual	#55; //Method scala/Option.toString:()Ljava/lang/String;
   55:	invokespecial	#58; //Method scala/MatchError."<init>":(Ljava/lang/String;)V
   58:	athrow
   59:	iconst_1
   60:	ifeq	152
   63:	aload_0
   64:	invokespecial	#132; //Method loader:()Ljava/lang/ClassLoader;
   67:	aload_1
   68:	invokevirtual	#136; //Method java/lang/ClassLoader.loadClass:(Ljava/lang/String;)Ljava/lang/Class;
   71:	invokevirtual	#140; //Method java/lang/Class.isInterface:()Z
   74:	ifeq	106
   77:	aload_0
   78:	invokespecial	#132; //Method loader:()Ljava/lang/ClassLoader;
   81:	new	#142; //class scala/collection/mutable/StringBuilder
   84:	dup
   85:	invokespecial	#143; //Method scala/collection/mutable/StringBuilder."<init>":()V
   88:	aload_1
   89:	invokevirtual	#147; //Method scala/collection/mutable/StringBuilder.append:(Ljava/lang/Object;)Lscala/collection/mutable/StringBuilder;
   92:	ldc	#149; //String $class
   94:	invokevirtual	#147; //Method scala/collection/mutable/StringBuilder.append:(Ljava/lang/Object;)Lscala/collection/mutable/StringBuilder;
   97:	invokevirtual	#150; //Method scala/collection/mutable/StringBuilder.toString:()Ljava/lang/String;
   100:	invokevirtual	#136; //Method java/lang/ClassLoader.loadClass:(Ljava/lang/String;)Ljava/lang/Class;
   103:	goto	132
   106:	aload_0
   107:	invokespecial	#132; //Method loader:()Ljava/lang/ClassLoader;
   110:	new	#142; //class scala/collection/mutable/StringBuilder
   113:	dup
   114:	invokespecial	#143; //Method scala/collection/mutable/StringBuilder."<init>":()V
   117:	aload_1
   118:	invokevirtual	#147; //Method scala/collection/mutable/StringBuilder.append:(Ljava/lang/Object;)Lscala/collection/mutable/StringBuilder;
   121:	ldc	#152; //String $
   123:	invokevirtual	#147; //Method scala/collection/mutable/StringBuilder.append:(Ljava/lang/Object;)Lscala/collection/mutable/StringBuilder;
   126:	invokevirtual	#150; //Method scala/collection/mutable/StringBuilder.toString:()Ljava/lang/String;
   129:	invokevirtual	#136; //Method java/lang/ClassLoader.loadClass:(Ljava/lang/String;)Ljava/lang/Class;
   132:	astore	4
   134:	aload_0
   135:	invokespecial	#125; //Method ccache:()Lscala/collection/mutable/Map;
   138:	aload_1
   139:	aload	4
   141:	invokeinterface	#103,  3; //InterfaceMethod scala/collection/mutable/MapLike.update:(Ljava/lang/Object;Ljava/lang/Object;)V
   146:	aload	4
   148:	invokespecial	#155; //Method scala/mobile/Code."<init>":(Ljava/lang/Class;)V
   151:	areturn
   152:	new	#49; //class scala/MatchError
   155:	dup
   156:	aload	5
   158:	invokevirtual	#55; //Method scala/Option.toString:()Ljava/lang/String;
   161:	invokespecial	#58; //Method scala/MatchError."<init>":(Ljava/lang/String;)V
   164:	athrow
  LineNumberTable: 
   line 67: 0
   line 68: 4
   line 67: 24
   line 21: 38
   line 70: 42
   line 68: 46
   line 21: 59
   line 72: 63
   line 75: 77
   line 80: 106
   line 72: 132
   line 82: 134
   line 83: 146
   line 67: 148
   line 68: 152

  LocalVariableTable: 
   Start  Length  Slot  Name   Signature
   0      165      0    this       Lscala/mobile/Location;
   0      165      1    className       Ljava/lang/String;
   30      29      2    temp5       Lscala/Some;
   38      21      3    temp6       Ljava/lang/Class;
   134      14      4    clazz       Ljava/lang/Class;
   16      149      5    temp4       Lscala/Option;


}

