Compiled from "Location.scala"
public class scala.mobile.Location extends java.lang.Object implements scala.ScalaObject
  SourceFile: "Location.scala"
  ScalaSig: length = 0x2D3
   05 00 78 06 08 01 02 FFFFFF84 FFFFFF80 FFFFFF80 FFFFFF80 00 07 02 08 4C
   6F 63 61 74 69 6F 6E 0A 02 03 04 01 06 6D 6F 62
   69 6C 65 0A 01 05 01 05 73 63 61 6C 61 03 00 13
   03 00 08 10 10 02 09 0E 0D 01 0A 0A 02 0B 0C 01
   04 6C 61 6E 67 0A 01 0D 01 04 6A 61 76 61 09 02
   0F 0A 02 06 4F 62 6A 65 63 74 10 02 11 12 0D 01
   04 09 02 13 04 02 0B 53 63 61 6C 61 4F 62 6A 65
   63 74 08 08 15 00 FFFFFF82 FFFFFF80 FFFFFFA0 FFFFFF80 04 16 01 03 75 72
   6C 10 02 17 1A 0D 01 18 0A 02 19 0C 01 03 6E 65
   74 09 02 1B 18 02 03 55 52 4C 08 05 1D 00 FFFFFF84 00
   1E 01 06 3C 69 6E 69 74 3E 14 02 1F 21 10 02 20
   00 0D 01 02 08 05 15 1C FFFFFFC0 00 16 08 07 23 00 FFFFFFC0
   FFFFFF80 FFFFFF84 04 24 01 06 6C 63 61 63 68 65 15 01 25 10
   04 26 2B 16 2D 0D 01 27 0A 02 28 29 01 07 6D 75
   74 61 62 6C 65 0A 02 2A 04 01 0A 63 6F 6C 6C 65
   63 74 69 6F 6E 09 02 2C 27 02 03 4D 61 70 10 02
   09 2E 09 02 2F 0A 02 0B 43 6C 61 73 73 4C 6F 61
   64 65 72 08 07 31 00 FFFFFFC0 FFFFFF80 FFFFFF84 04 32 01 0A 6C 63
   61 63 68 65 5F 24 65 71 14 02 33 36 10 02 11 34
   09 02 35 04 02 04 55 6E 69 74 08 07 37 30 FFFFFF81 FFFFFF80
   FFFFFFC0 00 25 01 03 78 24 31 08 06 39 00 FFFFFFA0 FFFFFFA0 04 25
   01 07 6C 63 61 63 68 65 20 08 07 3B 00 FFFFFFC2 FFFFFF80 FFFFFF84
   04 3C 01 06 6C 6F 61 64 65 72 15 01 2D 08 06 3E
   00 FFFFFFA0 FFFFFF80 04 2D 01 07 6C 6F 61 64 65 72 20 08 07
   40 00 FFFFFFC0 FFFFFF80 FFFFFF84 04 41 01 06 63 63 61 63 68 65 15
   01 42 10 04 26 2B 43 4A 10 02 44 47 0E 02 11 45
   09 02 46 04 01 06 50 72 65 64 65 66 09 02 48 49
   02 06 53 74 72 69 6E 67 0A 02 46 04 30 02 4B 50
   10 03 09 4C 4E 09 02 4D 0A 02 05 43 6C 61 73 73
   10 02 4F 50 0C 00 04 08 51 00 FFFFFF84 FFFFFF80 FFFFFF80 FFFFFF82 00 52
   02 01 54 11 02 53 56 10 02 11 54 09 02 55 04 02
   07 4E 6F 74 68 69 6E 67 10 02 11 57 09 02 58 04
   02 03 41 6E 79 08 07 5A 00 FFFFFFC0 FFFFFF80 FFFFFF84 04 5B 01 0A
   63 63 61 63 68 65 5F 24 65 71 14 02 33 5C 08 07
   37 59 FFFFFF81 FFFFFF80 FFFFFFC0 00 5D 10 04 26 2B 43 5E 30 02 5F
   61 10 03 09 4C 60 10 02 4F 61 04 08 51 00 FFFFFF84 FFFFFF80
   FFFFFF80 FFFFFF82 00 52 08 06 63 00 FFFFFFA0 FFFFFFA0 04 64 01 07 63 63
   61 63 68 65 20 10 04 26 2B 43 65 30 02 66 68 10
   03 09 4C 67 10 02 4F 68 04 08 51 00 FFFFFF84 FFFFFF80 FFFFFF80 FFFFFF82
   00 52 08 05 6A 00 FFFFFF84 00 6B 01 06 63 72 65 61 74
   65 14 02 6C 6F 10 02 20 6D 09 02 6E 02 02 04 43
   6F 64 65 08 05 70 69 FFFFFFC0 00 43 01 09 63 6C 61 73
   73 4E 61 6D 65 07 05 72 02 FFFFFF88 02 73 01 08 4C 6F
   63 61 74 69 6F 6E 10 02 20 74 06 08 01 02 FFFFFF84 FFFFFF80
   FFFFFF80 FFFFFF88 02 75 13 03 74 1F 10 08 05 1D 74 FFFFFF84 00 77
   14 01 73 
  minor version: 0
  major version: 49
  Constant pool:
Asciz	SourceFile;
Asciz	Location.scala;
Asciz	ccache;
Asciz	Lscala/collection/mutable/Map;;
Asciz	Lscala/collection/mutable/Map<Ljava/lang/String;Ljava/lang/Class<*>;>;;
Asciz	Signature;
Asciz	loader;
Asciz	Ljava/lang/ClassLoader;;
Asciz	lcache;
Asciz	Lscala/collection/mutable/Map<Ljava/net/URL;Ljava/lang/ClassLoader;>;;
Asciz	()Lscala/collection/mutable/Map;;
Asciz	Code;
Asciz	LineNumberTable;
Asciz	scala/mobile/Location;
class	scala/mobile/Location
NameAndType	lcache:Lscala/collection/mutable/Map;
Field	scala/mobile/Location.lcache:Lscala/collection/mutable/Map;
Asciz	()Lscala/collection/mutable/Map<Ljava/net/URL;Ljava/lang/ClassLoader;>;;
Asciz	lcache_$eq;
Asciz	(Lscala/collection/mutable/Map;)V;
Asciz	(Lscala/collection/mutable/Map<Ljava/net/URL;Ljava/lang/ClassLoader;>;)V;
Asciz	()Ljava/lang/ClassLoader;;
NameAndType	loader:Ljava/lang/ClassLoader;
Field	scala/mobile/Location.loader:Ljava/lang/ClassLoader;
NameAndType	ccache:Lscala/collection/mutable/Map;
Field	scala/mobile/Location.ccache:Lscala/collection/mutable/Map;
Asciz	()Lscala/collection/mutable/Map<Ljava/lang/String;Ljava/lang/Class<*>;>;;
Asciz	ccache_$eq;
Asciz	(Lscala/collection/mutable/Map<Ljava/lang/String;Ljava/lang/Class<*>;>;)V;
Asciz	create;
Asciz	(Ljava/lang/String;)Lscala/mobile/Code;;
Asciz	scala/mobile/Code;
class	scala/mobile/Code
NameAndType	ccache:()Lscala/collection/mutable/Map;
Method	scala/mobile/Location.ccache:()Lscala/collection/mutable/Map;
Asciz	scala/collection/MapLike;
class	scala/collection/MapLike
Asciz	get;
Asciz	(Ljava/lang/Object;)Lscala/Option;;
NameAndType	get:(Ljava/lang/Object;)Lscala/Option;
InterfaceMethod	scala/collection/MapLike.get:(Ljava/lang/Object;)Lscala/Option;
Asciz	scala/Some;
class	scala/Some
Asciz	x;
Asciz	()Ljava/lang/Object;;
NameAndType	x:()Ljava/lang/Object;
Method	scala/Some.x:()Ljava/lang/Object;
Asciz	java/lang/Class;
class	java/lang/Class
NameAndType	loader:()Ljava/lang/ClassLoader;
Method	scala/mobile/Location.loader:()Ljava/lang/ClassLoader;
Asciz	java/lang/ClassLoader;
class	java/lang/ClassLoader
Asciz	loadClass;
Asciz	(Ljava/lang/String;)Ljava/lang/Class;;
NameAndType	loadClass:(Ljava/lang/String;)Ljava/lang/Class;
Method	java/lang/ClassLoader.loadClass:(Ljava/lang/String;)Ljava/lang/Class;
Asciz	isInterface;
Asciz	()Z;
NameAndType	isInterface:()Z
Method	java/lang/Class.isInterface:()Z
Asciz	scala/collection/mutable/StringBuilder;
class	scala/collection/mutable/StringBuilder
Asciz	<init>;
Asciz	()V;
NameAndType	"<init>":()V
Method	scala/collection/mutable/StringBuilder."<init>":()V
Asciz	append;
Asciz	(Ljava/lang/Object;)Lscala/collection/mutable/StringBuilder;;
NameAndType	append:(Ljava/lang/Object;)Lscala/collection/mutable/StringBuilder;
Method	scala/collection/mutable/StringBuilder.append:(Ljava/lang/Object;)Lscala/collection/mutable/StringBuilder;
Asciz	$class;
String	$class
Asciz	toString;
Asciz	()Ljava/lang/String;;
NameAndType	toString:()Ljava/lang/String;
Method	scala/collection/mutable/StringBuilder.toString:()Ljava/lang/String;
Asciz	$;
String	$
Asciz	scala/collection/mutable/MapLike;
class	scala/collection/mutable/MapLike
Asciz	update;
Asciz	(Ljava/lang/Object;Ljava/lang/Object;)V;
NameAndType	update:(Ljava/lang/Object;Ljava/lang/Object;)V
InterfaceMethod	scala/collection/mutable/MapLike.update:(Ljava/lang/Object;Ljava/lang/Object;)V
Asciz	(Ljava/lang/Class;)V;
NameAndType	"<init>":(Ljava/lang/Class;)V
Method	scala/mobile/Code."<init>":(Ljava/lang/Class;)V
Asciz	this;
Asciz	Lscala/mobile/Location;;
Asciz	className;
Asciz	Ljava/lang/String;;
Asciz	temp4;
Asciz	Lscala/Option;;
Asciz	clazz;
Asciz	Ljava/lang/Class;;
Asciz	LocalVariableTable;
Asciz	(Ljava/net/URL;)V;
Asciz	java/lang/Object;
class	java/lang/Object
Method	java/lang/Object."<init>":()V
Asciz	scala/collection/mutable/HashMap;
class	scala/collection/mutable/HashMap
Method	scala/collection/mutable/HashMap."<init>":()V
Asciz	getSystemClassLoader;
NameAndType	getSystemClassLoader:()Ljava/lang/ClassLoader;
Method	java/lang/ClassLoader.getSystemClassLoader:()Ljava/lang/ClassLoader;
NameAndType	lcache:()Lscala/collection/mutable/Map;
Method	scala/mobile/Location.lcache:()Lscala/collection/mutable/Map;
Asciz	java/net/URLClassLoader;
class	java/net/URLClassLoader
Asciz	scala/Array$;
class	scala/Array$
Asciz	MODULE$;
Asciz	Lscala/Array$;;
NameAndType	MODULE$:Lscala/Array$;
Field	scala/Array$.MODULE$:Lscala/Array$;
Asciz	scala/Predef$;
class	scala/Predef$
Asciz	Lscala/Predef$;;
NameAndType	MODULE$:Lscala/Predef$;
Field	scala/Predef$.MODULE$:Lscala/Predef$;
Asciz	java/net/URL;
class	java/net/URL
Asciz	[Ljava/lang/Object;;
class	"[Ljava/lang/Object;"
Asciz	wrapRefArray;
Asciz	([Ljava/lang/Object;)Lscala/collection/mutable/WrappedArray;;
NameAndType	wrapRefArray:([Ljava/lang/Object;)Lscala/collection/mutable/WrappedArray;
Method	scala/Predef$.wrapRefArray:([Ljava/lang/Object;)Lscala/collection/mutable/WrappedArray;
Asciz	scala/reflect/ClassManifest$;
class	scala/reflect/ClassManifest$
Asciz	Lscala/reflect/ClassManifest$;;
NameAndType	MODULE$:Lscala/reflect/ClassManifest$;
Field	scala/reflect/ClassManifest$.MODULE$:Lscala/reflect/ClassManifest$;
Asciz	classType;
Asciz	(Ljava/lang/Class;)Lscala/reflect/ClassManifest;;
NameAndType	classType:(Ljava/lang/Class;)Lscala/reflect/ClassManifest;
Method	scala/reflect/ClassManifest$.classType:(Ljava/lang/Class;)Lscala/reflect/ClassManifest;
Asciz	apply;
Asciz	(Lscala/collection/Seq;Lscala/reflect/ClassManifest;)Ljava/lang/Object;;
NameAndType	apply:(Lscala/collection/Seq;Lscala/reflect/ClassManifest;)Ljava/lang/Object;
Method	scala/Array$.apply:(Lscala/collection/Seq;Lscala/reflect/ClassManifest;)Ljava/lang/Object;
Asciz	[Ljava/net/URL;;
class	"[Ljava/net/URL;"
Asciz	([Ljava/net/URL;)V;
NameAndType	"<init>":([Ljava/net/URL;)V
Method	java/net/URLClassLoader."<init>":([Ljava/net/URL;)V
Asciz	url;
Asciz	Ljava/net/URL;;
Asciz	temp1;
Asciz	cl;
Asciz	Ljava/net/URLClassLoader;;
Asciz	ScalaSig;
Asciz	scala/ScalaObject;
class	scala/ScalaObject

{
private scala.collection.mutable.Map ccache;
  Signature: Lscala/collection/mutable/Map;
  Signature: length = 0x2
   00 05 

private final java.lang.ClassLoader loader;
  Signature: Ljava/lang/ClassLoader;

private scala.collection.mutable.Map lcache;
  Signature: Lscala/collection/mutable/Map;
  Signature: length = 0x2
   00 0A 

private scala.collection.mutable.Map lcache();
  Signature: ()Lscala/collection/mutable/Map;
  Code:
   Stack=1, Locals=1, Args_size=1
	aload_0
	getfield	Field lcache:Lscala/collection/mutable/Map;
	areturn
  Labels:
  Signature: length = 0x2
   00 12 

private void lcache_$eq(scala.collection.mutable.Map);
  Signature: (Lscala/collection/mutable/Map;)V
  Code:
   Stack=2, Locals=2, Args_size=2
	aload_0
	aload_1
	putfield	Field lcache:Lscala/collection/mutable/Map;
	return
  Labels:
  Signature: length = 0x2
   00 15 

private java.lang.ClassLoader loader();
  Signature: ()Ljava/lang/ClassLoader;
  Code:
   Stack=1, Locals=1, Args_size=1
	aload_0
	getfield	Field loader:Ljava/lang/ClassLoader;
	areturn
  Labels:

private scala.collection.mutable.Map ccache();
  Signature: ()Lscala/collection/mutable/Map;
  Code:
   Stack=1, Locals=1, Args_size=1
	aload_0
	getfield	Field ccache:Lscala/collection/mutable/Map;
	areturn
  Labels:
  Signature: length = 0x2
   00 1B 

private void ccache_$eq(scala.collection.mutable.Map);
  Signature: (Lscala/collection/mutable/Map;)V
  Code:
   Stack=2, Locals=2, Args_size=2
	aload_0
	aload_1
	putfield	Field ccache:Lscala/collection/mutable/Map;
	return
  Labels:
  Signature: length = 0x2
   00 1D 

public scala.mobile.Code create(java.lang.String);
  Signature: (Ljava/lang/String;)Lscala/mobile/Code;
  Code:
   Stack=5, Locals=4, Args_size=2
	new	class scala/mobile/Code
	dup
	aload_0
	invokespecial	Method ccache:()Lscala/collection/mutable/Map;
	aload_1
	invokeinterface	InterfaceMethod scala/collection/MapLike.get:(Ljava/lang/Object;)Lscala/Option;
	astore_2
	aload_2
	instanceof	class scala/Some
	ifeq	l1 // aload_0
	aload_2
	checkcast	class scala/Some
	invokevirtual	Method scala/Some.x:()Ljava/lang/Object;
	checkcast	class java/lang/Class
	goto	l2 // invokespecial
l1	aload_0
	invokespecial	Method loader:()Ljava/lang/ClassLoader;
	aload_1
	invokevirtual	Method java/lang/ClassLoader.loadClass:(Ljava/lang/String;)Ljava/lang/Class;
	invokevirtual	Method java/lang/Class.isInterface:()Z
	ifeq	l3 // aload_0
	aload_0
	invokespecial	Method loader:()Ljava/lang/ClassLoader;
	new	class scala/collection/mutable/StringBuilder
	dup
	invokespecial	Method scala/collection/mutable/StringBuilder."<init>":()V
	aload_1
	invokevirtual	Method scala/collection/mutable/StringBuilder.append:(Ljava/lang/Object;)Lscala/collection/mutable/StringBuilder;
	ldc	String $class
	invokevirtual	Method scala/collection/mutable/StringBuilder.append:(Ljava/lang/Object;)Lscala/collection/mutable/StringBuilder;
	invokevirtual	Method scala/collection/mutable/StringBuilder.toString:()Ljava/lang/String;
	invokevirtual	Method java/lang/ClassLoader.loadClass:(Ljava/lang/String;)Ljava/lang/Class;
	goto	l4 // astore_3
l3	aload_0
	invokespecial	Method loader:()Ljava/lang/ClassLoader;
	new	class scala/collection/mutable/StringBuilder
	dup
	invokespecial	Method scala/collection/mutable/StringBuilder."<init>":()V
	aload_1
	invokevirtual	Method scala/collection/mutable/StringBuilder.append:(Ljava/lang/Object;)Lscala/collection/mutable/StringBuilder;
	ldc	String $
	invokevirtual	Method scala/collection/mutable/StringBuilder.append:(Ljava/lang/Object;)Lscala/collection/mutable/StringBuilder;
	invokevirtual	Method scala/collection/mutable/StringBuilder.toString:()Ljava/lang/String;
	invokevirtual	Method java/lang/ClassLoader.loadClass:(Ljava/lang/String;)Ljava/lang/Class;
l4	astore_3
	aload_0
	invokespecial	Method ccache:()Lscala/collection/mutable/Map;
	aload_1
	aload_3
	invokeinterface	InterfaceMethod scala/collection/mutable/MapLike.update:(Ljava/lang/Object;Ljava/lang/Object;)V
	aload_3
l2	invokespecial	Method scala/mobile/Code."<init>":(Ljava/lang/Class;)V
	areturn
  Labels:
   	l1 = 35 // aload_0
   	l3 = 78 // aload_0
   	l4 = 104 // astore_3
   	l2 = 117 // invokespecial
  LocalVariableTable: 
   Start  Length  Slot  Name   Signature
   0      121      0    this       Lscala/mobile/Location;
   0      121      1    className       Ljava/lang/String;
   15      106      2    temp4       Lscala/Option;
   105      12      3    clazz       Ljava/lang/Class;


public scala.mobile.Location(java.net.URL);
  Signature: (Ljava/net/URL;)V
  Code:
   Stack=9, Locals=4, Args_size=2
	aload_0
	invokespecial	Method java/lang/Object."<init>":()V
	aload_0
	new	class scala/collection/mutable/HashMap
	dup
	invokespecial	Method scala/collection/mutable/HashMap."<init>":()V
	putfield	Field lcache:Lscala/collection/mutable/Map;
	aload_0
	aload_1
	ifnonnull	l1 // aload_0
	invokestatic	Method java/lang/ClassLoader.getSystemClassLoader:()Ljava/lang/ClassLoader;
	goto	l2 // putfield
l1	aload_0
	invokespecial	Method lcache:()Lscala/collection/mutable/Map;
	aload_1
	invokeinterface	InterfaceMethod scala/collection/MapLike.get:(Ljava/lang/Object;)Lscala/Option;
	astore_2
	aload_2
	instanceof	class scala/Some
	ifeq	l3 // new
	aload_2
	checkcast	class scala/Some
	invokevirtual	Method scala/Some.x:()Ljava/lang/Object;
	checkcast	class java/lang/ClassLoader
	goto	l2 // putfield
l3	new	class java/net/URLClassLoader
	dup
	getstatic	Field scala/Array$.MODULE$:Lscala/Array$;
	getstatic	Field scala/Predef$.MODULE$:Lscala/Predef$;
	iconst_1
	anewarray	class java/net/URL
	dup
	iconst_0
	aload_1
	aastore
	checkcast	class "[Ljava/lang/Object;"
	invokevirtual	Method scala/Predef$.wrapRefArray:([Ljava/lang/Object;)Lscala/collection/mutable/WrappedArray;
	getstatic	Field scala/reflect/ClassManifest$.MODULE$:Lscala/reflect/ClassManifest$;
	ldc	class java/net/URL
	invokevirtual	Method scala/reflect/ClassManifest$.classType:(Ljava/lang/Class;)Lscala/reflect/ClassManifest;
	invokevirtual	Method scala/Array$.apply:(Lscala/collection/Seq;Lscala/reflect/ClassManifest;)Ljava/lang/Object;
	checkcast	class "[Ljava/net/URL;"
	invokespecial	Method java/net/URLClassLoader."<init>":([Ljava/net/URL;)V
	astore_3
	aload_0
	invokespecial	Method lcache:()Lscala/collection/mutable/Map;
	aload_1
	aload_3
	invokeinterface	InterfaceMethod scala/collection/mutable/MapLike.update:(Ljava/lang/Object;Ljava/lang/Object;)V
	aload_3
l2	putfield	Field loader:Ljava/lang/ClassLoader;
	aload_0
	new	class scala/collection/mutable/HashMap
	dup
	invokespecial	Method scala/collection/mutable/HashMap."<init>":()V
	putfield	Field ccache:Lscala/collection/mutable/Map;
	return
  Labels:
   	l1 = 26 // aload_0
   	l3 = 57 // new
   	l2 = 111 // putfield
  LocalVariableTable: 
   Start  Length  Slot  Name   Signature
   0      126      0    this       Lscala/mobile/Location;
   0      126      1    url       Ljava/net/URL;
   37      74      2    temp1       Lscala/Option;
   99      12      3    cl       Ljava/net/URLClassLoader;


}

