Compiled from "Location.scala"
public final class scala.mobile.Location$ extends scala.mobile.Location implements scala.ScalaObject
  SourceFile: "Location.scala"
  Scala: length = 0x
   
  minor version: 0
  major version: 49
  Constant pool:
const #1 = Asciz	SourceFile;
const #2 = Asciz	Location.scala;
const #3 = Asciz	Scala;
const #4 = Asciz	MODULE$;
const #5 = Asciz	Lscala/mobile/Location$;;
const #6 = Asciz	<clinit>;
const #7 = Asciz	()V;
const #8 = Asciz	Code;
const #9 = Asciz	scala/mobile/Location$;
const #10 = class	#9;	//  scala/mobile/Location$
const #11 = Asciz	<init>;
const #12 = NameAndType	#11:#7;//  "<init>":()V
const #13 = Method	#10.#12;	//  scala/mobile/Location$."<init>":()V
const #14 = Asciz	LineNumberTable;
const #15 = Asciz	scala/mobile/Location;
const #16 = class	#15;	//  scala/mobile/Location
const #17 = Asciz	(Ljava/net/URL;)V;
const #18 = NameAndType	#11:#17;//  "<init>":(Ljava/net/URL;)V
const #19 = Method	#16.#18;	//  scala/mobile/Location."<init>":(Ljava/net/URL;)V
const #20 = NameAndType	#4:#5;//  MODULE$:Lscala/mobile/Location$;
const #21 = Field	#10.#20;	//  scala/mobile/Location$.MODULE$:Lscala/mobile/Location$;
const #22 = Asciz	scala/ScalaObject;
const #23 = class	#22;	//  scala/ScalaObject

{
public static final scala.mobile.Location$ MODULE$;

public static {};
  Code:
   Stack=1, Locals=0, Args_size=0
   0:	new	#10; //class scala/mobile/Location$
   3:	invokespecial	#13; //Method "<init>":()V
   6:	return

}

