Compiled from "StdTokens.scala"
public class scala.util.parsing.syntax.StdTokens$NumericLit extends scala.util.parsing.syntax.Tokens$Token implements scala.ScalaObject,scala.Product,java.io.Serializable
  SourceFile: "StdTokens.scala"
  Scala: length = 0x
   
  InnerClass: 
   public abstract Token=class scala/util/parsing/syntax/Tokens$Token of class scala/util/parsing/syntax/Tokens
   public NumericLit=class scala/util/parsing/syntax/StdTokens$NumericLit of class scala/util/parsing/syntax/StdTokens
  minor version: 0
  major version: 49
  Constant pool:
Asciz	SourceFile;
Asciz	StdTokens.scala;
Asciz	$outer;
Asciz	Lscala/util/parsing/syntax/StdTokens;;
Asciz	chars;
Asciz	Ljava/lang/String;;
Asciz	productIterator;
Asciz	()Lscala/collection/Iterator;;
Asciz	Code;
Asciz	LineNumberTable;
Asciz	scala/Product$class;
class	scala/Product$class
Asciz	(Lscala/Product;)Lscala/collection/Iterator;;
NameAndType	productIterator:(Lscala/Product;)Lscala/collection/Iterator;
Method	scala/Product$class.productIterator:(Lscala/Product;)Lscala/collection/Iterator;
Asciz	productElements;
NameAndType	productElements:(Lscala/Product;)Lscala/collection/Iterator;
Method	scala/Product$class.productElements:(Lscala/Product;)Lscala/collection/Iterator;
Asciz	Deprecated;
Asciz	copy$default$1;
Asciz	()Ljava/lang/String;;
Asciz	scala/util/parsing/syntax/StdTokens$NumericLit;
class	scala/util/parsing/syntax/StdTokens$NumericLit
NameAndType	chars:()Ljava/lang/String;
Method	scala/util/parsing/syntax/StdTokens$NumericLit.chars:()Ljava/lang/String;
NameAndType	chars:Ljava/lang/String;
Field	scala/util/parsing/syntax/StdTokens$NumericLit.chars:Ljava/lang/String;
Asciz	toString;
Asciz	copy;
Asciz	(Ljava/lang/String;)Lscala/util/parsing/syntax/StdTokens$NumericLit;;
Asciz	scala$util$parsing$syntax$StdTokens$NumericLit$$$outer;
Asciz	()Lscala/util/parsing/syntax/StdTokens;;
NameAndType	scala$util$parsing$syntax$StdTokens$NumericLit$$$outer:()Lscala/util/parsing/syntax/StdTokens;
Method	scala/util/parsing/syntax/StdTokens$NumericLit.scala$util$parsing$syntax$StdTokens$NumericLit$$$outer:()Lscala/util/parsing/syntax/StdTokens;
Asciz	<init>;
Asciz	(Lscala/util/parsing/syntax/StdTokens;Ljava/lang/String;)V;
NameAndType	"<init>":(Lscala/util/parsing/syntax/StdTokens;Ljava/lang/String;)V
Method	scala/util/parsing/syntax/StdTokens$NumericLit."<init>":(Lscala/util/parsing/syntax/StdTokens;Ljava/lang/String;)V
Asciz	this;
Asciz	Lscala/util/parsing/syntax/StdTokens$NumericLit;;
Asciz	LocalVariableTable;
Asciz	hashCode;
Asciz	()I;
Asciz	scala/runtime/ScalaRunTime$;
class	scala/runtime/ScalaRunTime$
Asciz	MODULE$;
Asciz	Lscala/runtime/ScalaRunTime$;;
NameAndType	MODULE$:Lscala/runtime/ScalaRunTime$;
Field	scala/runtime/ScalaRunTime$.MODULE$:Lscala/runtime/ScalaRunTime$;
Asciz	_hashCode;
Asciz	(Lscala/Product;)I;
NameAndType	_hashCode:(Lscala/Product;)I
Method	scala/runtime/ScalaRunTime$._hashCode:(Lscala/Product;)I
Asciz	equals;
Asciz	(Ljava/lang/Object;)Z;
Asciz	gd2$1;
Asciz	(Ljava/lang/String;)Z;
NameAndType	gd2$1:(Ljava/lang/String;)Z
Method	scala/util/parsing/syntax/StdTokens$NumericLit.gd2$1:(Ljava/lang/String;)Z
Asciz	scala/Equals;
class	scala/Equals
Asciz	canEqual;
NameAndType	canEqual:(Ljava/lang/Object;)Z
InterfaceMethod	scala/Equals.canEqual:(Ljava/lang/Object;)Z
Asciz	temp6;
Asciz	temp7;
Asciz	productPrefix;
Asciz	NumericLit;
String	NumericLit
Asciz	productArity;
Asciz	productElement;
Asciz	(I)Ljava/lang/Object;;
Asciz	java/lang/IndexOutOfBoundsException;
class	java/lang/IndexOutOfBoundsException
Asciz	scala/runtime/BoxesRunTime;
class	scala/runtime/BoxesRunTime
Asciz	boxToInteger;
Asciz	(I)Ljava/lang/Integer;;
NameAndType	boxToInteger:(I)Ljava/lang/Integer;
Method	scala/runtime/BoxesRunTime.boxToInteger:(I)Ljava/lang/Integer;
Asciz	java/lang/Object;
class	java/lang/Object
NameAndType	toString:()Ljava/lang/String;
Method	java/lang/Object.toString:()Ljava/lang/String;
Asciz	(Ljava/lang/String;)V;
NameAndType	"<init>":(Ljava/lang/String;)V
Method	java/lang/IndexOutOfBoundsException."<init>":(Ljava/lang/String;)V
NameAndType	$outer:Lscala/util/parsing/syntax/StdTokens;
Field	scala/util/parsing/syntax/StdTokens$NumericLit.$outer:Lscala/util/parsing/syntax/StdTokens;
NameAndType	equals:(Ljava/lang/Object;)Z
Method	java/lang/Object.equals:(Ljava/lang/Object;)Z
Asciz	java/lang/NullPointerException;
class	java/lang/NullPointerException
Asciz	()V;
NameAndType	"<init>":()V
Method	java/lang/NullPointerException."<init>":()V
Asciz	scala/util/parsing/syntax/Tokens$Token;
class	scala/util/parsing/syntax/Tokens$Token
Asciz	(Lscala/util/parsing/syntax/Tokens;)V;
NameAndType	"<init>":(Lscala/util/parsing/syntax/Tokens;)V
Method	scala/util/parsing/syntax/Tokens$Token."<init>":(Lscala/util/parsing/syntax/Tokens;)V
Asciz	$init$;
Asciz	(Lscala/Product;)V;
NameAndType	$init$:(Lscala/Product;)V
Method	scala/Product$class.$init$:(Lscala/Product;)V
Asciz	Scala;
Asciz	InnerClasses;
Asciz	scala/util/parsing/syntax/Tokens;
class	scala/util/parsing/syntax/Tokens
Asciz	Token;
Asciz	scala/util/parsing/syntax/StdTokens;
class	scala/util/parsing/syntax/StdTokens
Asciz	scala/ScalaObject;
class	scala/ScalaObject
Asciz	scala/Product;
class	scala/Product
Asciz	java/io/Serializable;
class	java/io/Serializable

{
public final scala.util.parsing.syntax.StdTokens $outer;
  Signature: Lscala/util/parsing/syntax/StdTokens;

private final java.lang.String chars;
  Signature: Ljava/lang/String;

public scala.collection.Iterator productIterator();
  Signature: ()Lscala/collection/Iterator;
  Code:
   Stack=1, Locals=1, Args_size=1
	aload_0
	invokestatic	Method scala/Product$class.productIterator:(Lscala/Product;)Lscala/collection/Iterator;
	areturn
  Labels:

public scala.collection.Iterator productElements();
  Signature: ()Lscala/collection/Iterator;
  Code:
   Stack=1, Locals=1, Args_size=1
	aload_0
	invokestatic	Method scala/Product$class.productElements:(Lscala/Product;)Lscala/collection/Iterator;
	areturn
  Labels:
  Deprecated: true

public java.lang.String copy$default$1();
  Signature: ()Ljava/lang/String;
  Code:
   Stack=1, Locals=1, Args_size=1
	aload_0
	invokevirtual	Method chars:()Ljava/lang/String;
	areturn
  Labels:

public java.lang.String chars();
  Signature: ()Ljava/lang/String;
  Code:
   Stack=1, Locals=1, Args_size=1
	aload_0
	getfield	Field chars:Ljava/lang/String;
	areturn
  Labels:

public java.lang.String toString();
  Signature: ()Ljava/lang/String;
  Code:
   Stack=1, Locals=1, Args_size=1
	aload_0
	invokevirtual	Method chars:()Ljava/lang/String;
	areturn
  Labels:

public scala.util.parsing.syntax.StdTokens$NumericLit copy(java.lang.String);
  Signature: (Ljava/lang/String;)Lscala/util/parsing/syntax/StdTokens$NumericLit;
  Code:
   Stack=4, Locals=2, Args_size=2
	new	class scala/util/parsing/syntax/StdTokens$NumericLit
	dup
	aload_0
	invokevirtual	Method scala$util$parsing$syntax$StdTokens$NumericLit$$$outer:()Lscala/util/parsing/syntax/StdTokens;
	aload_1
	invokespecial	Method "<init>":(Lscala/util/parsing/syntax/StdTokens;Ljava/lang/String;)V
	areturn
  Labels:
  LocalVariableTable: 
   Start  Length  Slot  Name   Signature
   0      13      0    this       Lscala/util/parsing/syntax/StdTokens$NumericLit;
   0      13      1    chars       Ljava/lang/String;


public int hashCode();
  Signature: ()I
  Code:
   Stack=2, Locals=1, Args_size=1
	getstatic	Field scala/runtime/ScalaRunTime$.MODULE$:Lscala/runtime/ScalaRunTime$;
	aload_0
	invokevirtual	Method scala/runtime/ScalaRunTime$._hashCode:(Lscala/Product;)I
	ireturn
  Labels:

public boolean equals(java.lang.Object);
  Signature: (Ljava/lang/Object;)Z
  Code:
   Stack=2, Locals=4, Args_size=2
	aload_0
	aload_1
	if_acmpeq	l1 // iconst_1
	aload_1
	instanceof	class scala/util/parsing/syntax/StdTokens$NumericLit
	ifeq	l2 // iconst_0
	aload_1
	checkcast	class scala/util/parsing/syntax/StdTokens$NumericLit
	invokevirtual	Method scala$util$parsing$syntax$StdTokens$NumericLit$$$outer:()Lscala/util/parsing/syntax/StdTokens;
	aload_0
	invokevirtual	Method scala$util$parsing$syntax$StdTokens$NumericLit$$$outer:()Lscala/util/parsing/syntax/StdTokens;
	if_acmpne	l2 // iconst_0
	aload_1
	checkcast	class scala/util/parsing/syntax/StdTokens$NumericLit
	astore_2
	aload_2
	invokevirtual	Method chars:()Ljava/lang/String;
	astore_3
	aload_0
	aload_3
	invokespecial	Method gd2$1:(Ljava/lang/String;)Z
	ifeq	l3 // iconst_0
	aload_1
	checkcast	class scala/util/parsing/syntax/StdTokens$NumericLit
	aload_0
	invokeinterface	InterfaceMethod scala/Equals.canEqual:(Ljava/lang/Object;)Z
	goto	l4 // ifeq
l3	iconst_0
	goto	l4 // ifeq
l2	iconst_0
l4	ifeq	l5 // iconst_0
l1	iconst_1
	goto	l6 // ireturn
l5	iconst_0
l6	ireturn
  Labels:
   	l3 = 57 // iconst_0
   	l2 = 61 // iconst_0
   	l4 = 62 // ifeq
   	l1 = 65 // iconst_1
   	l5 = 69 // iconst_0
   	l6 = 70 // ireturn
  LocalVariableTable: 
   Start  Length  Slot  Name   Signature
   0      71      0    this       Lscala/util/parsing/syntax/StdTokens$NumericLit;
   31      30      2    temp6       Lscala/util/parsing/syntax/StdTokens$NumericLit;
   36      25      3    temp7       Ljava/lang/String;


public java.lang.String productPrefix();
  Signature: ()Ljava/lang/String;
  Code:
   Stack=1, Locals=1, Args_size=1
	ldc	String NumericLit
	areturn
  Labels:

public int productArity();
  Signature: ()I
  Code:
   Stack=1, Locals=1, Args_size=1
	iconst_1
	ireturn
  Labels:

public java.lang.Object productElement(int);
  Signature: (I)Ljava/lang/Object;
  Code:
   Stack=3, Locals=2, Args_size=2
	iload_1
	iconst_0
	if_icmpne	l1 // new
	aload_0
	invokevirtual	Method chars:()Ljava/lang/String;
	areturn
l1	new	class java/lang/IndexOutOfBoundsException
	dup
	iload_1
	invokestatic	Method scala/runtime/BoxesRunTime.boxToInteger:(I)Ljava/lang/Integer;
	invokevirtual	Method java/lang/Object.toString:()Ljava/lang/String;
	invokespecial	Method java/lang/IndexOutOfBoundsException."<init>":(Ljava/lang/String;)V
	athrow
  Labels:
   	l1 = 10 // new

public boolean canEqual(java.lang.Object);
  Signature: (Ljava/lang/Object;)Z
  Code:
   Stack=1, Locals=2, Args_size=2
	aload_1
	instanceof	class scala/util/parsing/syntax/StdTokens$NumericLit
	ireturn
  Labels:

public scala.util.parsing.syntax.StdTokens scala$util$parsing$syntax$StdTokens$NumericLit$$$outer();
  Signature: ()Lscala/util/parsing/syntax/StdTokens;
  Code:
   Stack=1, Locals=1, Args_size=1
	aload_0
	getfield	Field $outer:Lscala/util/parsing/syntax/StdTokens;
	areturn
  Labels:

private final boolean gd2$1(java.lang.String);
  Signature: (Ljava/lang/String;)Z
  Code:
   Stack=2, Locals=3, Args_size=2
	aload_1
	aload_0
	invokevirtual	Method chars:()Ljava/lang/String;
	astore_2
	dup
	ifnonnull	l1 // aload_2
	pop
	aload_2
	ifnull	l2 // iconst_1
	goto	l3 // iconst_0
l1	aload_2
	invokevirtual	Method java/lang/Object.equals:(Ljava/lang/Object;)Z
	ifeq	l3 // iconst_0
l2	iconst_1
	goto	l4 // ireturn
l3	iconst_0
l4	ireturn
  Labels:
   	l1 = 18 // aload_2
   	l2 = 25 // iconst_1
   	l3 = 29 // iconst_0
   	l4 = 30 // ireturn

public scala.util.parsing.syntax.StdTokens$NumericLit(scala.util.parsing.syntax.StdTokens, java.lang.String);
  Signature: (Lscala/util/parsing/syntax/StdTokens;Ljava/lang/String;)V
  Code:
   Stack=2, Locals=3, Args_size=3
	aload_0
	aload_2
	putfield	Field chars:Ljava/lang/String;
	aload_1
	ifnonnull	l1 // aload_0
	new	class java/lang/NullPointerException
	dup
	invokespecial	Method java/lang/NullPointerException."<init>":()V
	athrow
l1	aload_0
	aload_1
	putfield	Field $outer:Lscala/util/parsing/syntax/StdTokens;
	aload_0
	aload_1
	invokespecial	Method scala/util/parsing/syntax/Tokens$Token."<init>":(Lscala/util/parsing/syntax/Tokens;)V
	aload_0
	invokestatic	Method scala/Product$class.$init$:(Lscala/Product;)V
	return
  Labels:
   	l1 = 17 // aload_0
  LocalVariableTable: 
   Start  Length  Slot  Name   Signature
   0      32      0    this       Lscala/util/parsing/syntax/StdTokens$NumericLit;
   0      32      1    $outer       Lscala/util/parsing/syntax/StdTokens;
   0      32      2    chars       Ljava/lang/String;


}

