Compiled from "Tokens.scala"
public abstract class scala.util.parsing.syntax.Tokens$class extends java.lang.Object
  SourceFile: "Tokens.scala"
  Scala: length = 0x
   
  InnerClass: 
   public abstract #26= #23 of #25; //Token=class scala/util/parsing/syntax/Tokens$Token of class scala/util/parsing/syntax/Tokens
   public #27= #13 of #25; //ErrorToken=class scala/util/parsing/syntax/Tokens$ErrorToken of class scala/util/parsing/syntax/Tokens
  minor version: 0
  major version: 49
  Constant pool:
const #1 = Asciz	SourceFile;
const #2 = Asciz	Tokens.scala;
const #3 = Asciz	$init$;
const #4 = Asciz	(Lscala/util/parsing/syntax/Tokens;)V;
const #5 = Asciz	Code;
const #6 = Asciz	LineNumberTable;
const #7 = Asciz	$this;
const #8 = Asciz	Lscala/util/parsing/syntax/Tokens;;
const #9 = Asciz	LocalVariableTable;
const #10 = Asciz	errorToken;
const #11 = Asciz	(Lscala/util/parsing/syntax/Tokens;Ljava/lang/String;)Lscala/util/parsing/syntax/Tokens$Token;;
const #12 = Asciz	scala/util/parsing/syntax/Tokens$ErrorToken;
const #13 = class	#12;	//  scala/util/parsing/syntax/Tokens$ErrorToken
const #14 = Asciz	<init>;
const #15 = Asciz	(Lscala/util/parsing/syntax/Tokens;Ljava/lang/String;)V;
const #16 = NameAndType	#14:#15;//  "<init>":(Lscala/util/parsing/syntax/Tokens;Ljava/lang/String;)V
const #17 = Method	#13.#16;	//  scala/util/parsing/syntax/Tokens$ErrorToken."<init>":(Lscala/util/parsing/syntax/Tokens;Ljava/lang/String;)V
const #18 = Asciz	msg;
const #19 = Asciz	Ljava/lang/String;;
const #20 = Asciz	Scala;
const #21 = Asciz	InnerClasses;
const #22 = Asciz	scala/util/parsing/syntax/Tokens$Token;
const #23 = class	#22;	//  scala/util/parsing/syntax/Tokens$Token
const #24 = Asciz	scala/util/parsing/syntax/Tokens;
const #25 = class	#24;	//  scala/util/parsing/syntax/Tokens
const #26 = Asciz	Token;
const #27 = Asciz	ErrorToken;
const #28 = Asciz	scala/util/parsing/syntax/Tokens$class;
const #29 = class	#28;	//  scala/util/parsing/syntax/Tokens$class
const #30 = Asciz	java/lang/Object;
const #31 = class	#30;	//  java/lang/Object

{
public static void $init$(scala.util.parsing.syntax.Tokens);
  Code:
   Stack=0, Locals=1, Args_size=1
   0:	return
  LineNumberTable: 
   line 16: 0

  LocalVariableTable: 
   Start  Length  Slot  Name   Signature
   0      1      0    $this       Lscala/util/parsing/syntax/Tokens;


public static scala.util.parsing.syntax.Tokens$Token errorToken(scala.util.parsing.syntax.Tokens, java.lang.String);
  Code:
   Stack=4, Locals=2, Args_size=2
   0:	new	#13; //class scala/util/parsing/syntax/Tokens$ErrorToken
   3:	dup
   4:	aload_0
   5:	aload_1
   6:	invokespecial	#17; //Method scala/util/parsing/syntax/Tokens$ErrorToken."<init>":(Lscala/util/parsing/syntax/Tokens;Ljava/lang/String;)V
   9:	areturn
  LineNumberTable: 
   line 37: 0

  LocalVariableTable: 
   Start  Length  Slot  Name   Signature
   0      10      0    $this       Lscala/util/parsing/syntax/Tokens;
   0      10      1    msg       Ljava/lang/String;


}

