Compiled from "Benchmark.scala"
public final class scala.testing.Benchmark$$anonfun$main$1 extends java.lang.Object implements scala.Function1,scala.ScalaObject,java.io.Serializable
  SourceFile: "Benchmark.scala"
  Scala: length = 0x
   
  InnerClass: 
   public final $anonfun$main$1=class scala/testing/Benchmark$$anonfun$main$1 of class scala/testing/Benchmark
  minor version: 0
  major version: 49
  Constant pool:
Asciz	SourceFile;
Asciz	Benchmark.scala;
Asciz	<clinit>;
Asciz	()V;
Asciz	Code;
Asciz	serialVersionUID;
Asciz	J;
Asciz	scala/testing/Benchmark$$anonfun$main$1;
class	scala/testing/Benchmark$$anonfun$main$1
NameAndType	serialVersionUID:J
Field	scala/testing/Benchmark$$anonfun$main$1.serialVersionUID:J
Asciz	logFile$1;
Asciz	Ljava/io/OutputStreamWriter;;
Asciz	<init>;
Asciz	(Lscala/testing/Benchmark;Ljava/io/OutputStreamWriter;)V;
Asciz	LineNumberTable;
NameAndType	logFile$1:Ljava/io/OutputStreamWriter;
Field	scala/testing/Benchmark$$anonfun$main$1.logFile$1:Ljava/io/OutputStreamWriter;
Asciz	java/lang/Object;
class	java/lang/Object
NameAndType	"<init>":()V
Method	java/lang/Object."<init>":()V
Asciz	scala/Function1$class;
class	scala/Function1$class
Asciz	$init$;
Asciz	(Lscala/Function1;)V;
NameAndType	$init$:(Lscala/Function1;)V
Method	scala/Function1$class.$init$:(Lscala/Function1;)V
Asciz	this;
Asciz	Lscala/testing/Benchmark$$anonfun$main$1;;
Asciz	$outer;
Asciz	Lscala/testing/Benchmark;;
Asciz	LocalVariableTable;
Asciz	apply;
Asciz	(Ljava/lang/Object;)Ljava/lang/Object;;
Asciz	scala/runtime/BoxesRunTime;
class	scala/runtime/BoxesRunTime
Asciz	unboxToLong;
Asciz	(Ljava/lang/Object;)J;
NameAndType	unboxToLong:(Ljava/lang/Object;)J
Method	scala/runtime/BoxesRunTime.unboxToLong:(Ljava/lang/Object;)J
Asciz	(J)V;
NameAndType	apply:(J)V
Method	scala/testing/Benchmark$$anonfun$main$1.apply:(J)V
Asciz	scala/runtime/BoxedUnit;
class	scala/runtime/BoxedUnit
Asciz	UNIT;
Asciz	Lscala/runtime/BoxedUnit;;
NameAndType	UNIT:Lscala/runtime/BoxedUnit;
Field	scala/runtime/BoxedUnit.UNIT:Lscala/runtime/BoxedUnit;
Asciz	v1;
Asciz	Ljava/lang/Object;;
Asciz	scala/collection/mutable/StringBuilder;
class	scala/collection/mutable/StringBuilder
Method	scala/collection/mutable/StringBuilder."<init>":()V
Asciz	\t\t;
String	\t\t
Asciz	append;
Asciz	(Ljava/lang/Object;)Lscala/collection/mutable/StringBuilder;;
NameAndType	append:(Ljava/lang/Object;)Lscala/collection/mutable/StringBuilder;
Method	scala/collection/mutable/StringBuilder.append:(Ljava/lang/Object;)Lscala/collection/mutable/StringBuilder;
Asciz	boxToLong;
Asciz	(J)Ljava/lang/Long;;
NameAndType	boxToLong:(J)Ljava/lang/Long;
Method	scala/runtime/BoxesRunTime.boxToLong:(J)Ljava/lang/Long;
Asciz	toString;
Asciz	()Ljava/lang/String;;
NameAndType	toString:()Ljava/lang/String;
Method	scala/collection/mutable/StringBuilder.toString:()Ljava/lang/String;
Asciz	java/io/OutputStreamWriter;
class	java/io/OutputStreamWriter
Asciz	write;
Asciz	(Ljava/lang/String;)V;
NameAndType	write:(Ljava/lang/String;)V
Method	java/io/OutputStreamWriter.write:(Ljava/lang/String;)V
Asciz	t;
Asciz	andThen;
Asciz	(Lscala/Function1;)Lscala/Function1;;
Asciz	(Lscala/Function1;Lscala/Function1;)Lscala/Function1;;
NameAndType	andThen:(Lscala/Function1;Lscala/Function1;)Lscala/Function1;
Method	scala/Function1$class.andThen:(Lscala/Function1;Lscala/Function1;)Lscala/Function1;
Asciz	g;
Asciz	Lscala/Function1;;
Asciz	compose;
NameAndType	compose:(Lscala/Function1;Lscala/Function1;)Lscala/Function1;
Method	scala/Function1$class.compose:(Lscala/Function1;Lscala/Function1;)Lscala/Function1;
Asciz	(Lscala/Function1;)Ljava/lang/String;;
NameAndType	toString:(Lscala/Function1;)Ljava/lang/String;
Method	scala/Function1$class.toString:(Lscala/Function1;)Ljava/lang/String;
Asciz	Scala;
Asciz	InnerClasses;
Asciz	scala/testing/Benchmark;
class	scala/testing/Benchmark
Asciz	$anonfun$main$1;
Asciz	scala/Function1;
class	scala/Function1
Asciz	scala/ScalaObject;
class	scala/ScalaObject
Asciz	java/io/Serializable;
class	java/io/Serializable

{
public static final long serialVersionUID;
  Signature: J

private final java.io.OutputStreamWriter logFile$1;
  Signature: Ljava/io/OutputStreamWriter;

public static {};
  Signature: ()V
  Code:
   Stack=2, Locals=0, Args_size=0
	lconst_0
	putstatic	Field serialVersionUID:J
	return
  Labels:

public scala.testing.Benchmark$$anonfun$main$1(scala.testing.Benchmark, java.io.OutputStreamWriter);
  Signature: (Lscala/testing/Benchmark;Ljava/io/OutputStreamWriter;)V
  Code:
   Stack=2, Locals=3, Args_size=3
	aload_0
	aload_2
	putfield	Field logFile$1:Ljava/io/OutputStreamWriter;
	aload_0
	invokespecial	Method java/lang/Object."<init>":()V
	aload_0
	invokestatic	Method scala/Function1$class.$init$:(Lscala/Function1;)V
	return
  Labels:
  LocalVariableTable: 
   Start  Length  Slot  Name   Signature
   0      14      0    this       Lscala/testing/Benchmark$$anonfun$main$1;
   0      14      1    $outer       Lscala/testing/Benchmark;


public final java.lang.Object apply(java.lang.Object);
  Signature: (Ljava/lang/Object;)Ljava/lang/Object;
  Code:
   Stack=3, Locals=2, Args_size=2
	aload_0
	aload_1
	invokestatic	Method scala/runtime/BoxesRunTime.unboxToLong:(Ljava/lang/Object;)J
	invokevirtual	Method apply:(J)V
	getstatic	Field scala/runtime/BoxedUnit.UNIT:Lscala/runtime/BoxedUnit;
	areturn
  Labels:
  LocalVariableTable: 
   Start  Length  Slot  Name   Signature
   0      12      0    this       Lscala/testing/Benchmark$$anonfun$main$1;
   0      12      1    v1       Ljava/lang/Object;


public final void apply(long);
  Signature: (J)V
  Code:
   Stack=4, Locals=3, Args_size=2
	aload_0
	getfield	Field logFile$1:Ljava/io/OutputStreamWriter;
	new	class scala/collection/mutable/StringBuilder
	dup
	invokespecial	Method scala/collection/mutable/StringBuilder."<init>":()V
	ldc	String \t\t
	invokevirtual	Method scala/collection/mutable/StringBuilder.append:(Ljava/lang/Object;)Lscala/collection/mutable/StringBuilder;
	lload_1
	invokestatic	Method scala/runtime/BoxesRunTime.boxToLong:(J)Ljava/lang/Long;
	invokevirtual	Method scala/collection/mutable/StringBuilder.append:(Ljava/lang/Object;)Lscala/collection/mutable/StringBuilder;
	invokevirtual	Method scala/collection/mutable/StringBuilder.toString:()Ljava/lang/String;
	invokevirtual	Method java/io/OutputStreamWriter.write:(Ljava/lang/String;)V
	return
  Labels:
  LocalVariableTable: 
   Start  Length  Slot  Name   Signature
   0      30      0    this       Lscala/testing/Benchmark$$anonfun$main$1;
   0      30      1    t       J


public scala.Function1 andThen(scala.Function1);
  Signature: (Lscala/Function1;)Lscala/Function1;
  Code:
   Stack=2, Locals=2, Args_size=2
	aload_0
	aload_1
	invokestatic	Method scala/Function1$class.andThen:(Lscala/Function1;Lscala/Function1;)Lscala/Function1;
	areturn
  Labels:
  LocalVariableTable: 
   Start  Length  Slot  Name   Signature
   0      6      0    this       Lscala/testing/Benchmark$$anonfun$main$1;
   0      6      1    g       Lscala/Function1;


public scala.Function1 compose(scala.Function1);
  Signature: (Lscala/Function1;)Lscala/Function1;
  Code:
   Stack=2, Locals=2, Args_size=2
	aload_0
	aload_1
	invokestatic	Method scala/Function1$class.compose:(Lscala/Function1;Lscala/Function1;)Lscala/Function1;
	areturn
  Labels:
  LocalVariableTable: 
   Start  Length  Slot  Name   Signature
   0      6      0    this       Lscala/testing/Benchmark$$anonfun$main$1;
   0      6      1    g       Lscala/Function1;


public java.lang.String toString();
  Signature: ()Ljava/lang/String;
  Code:
   Stack=1, Locals=1, Args_size=1
	aload_0
	invokestatic	Method scala/Function1$class.toString:(Lscala/Function1;)Ljava/lang/String;
	areturn
  Labels:

}

