Compiled from "Benchmark.scala"
public final class scala.testing.Benchmark$$anonfun$main$1 extends java.lang.Object implements scala.Function1,scala.ScalaObject,java.io.Serializable
  SourceFile: "Benchmark.scala"
  Scala: length = 0x
   
  InnerClass: 
   public final #94= #9 of #93; //$anonfun$main$1=class scala/testing/Benchmark$$anonfun$main$1 of class scala/testing/Benchmark
  minor version: 0
  major version: 49
  Constant pool:
const #1 = Asciz	SourceFile;
const #2 = Asciz	Benchmark.scala;
const #3 = Asciz	<clinit>;
const #4 = Asciz	()V;
const #5 = Asciz	Code;
const #6 = Asciz	serialVersionUID;
const #7 = Asciz	J;
const #8 = Asciz	scala/testing/Benchmark$$anonfun$main$1;
const #9 = class	#8;	//  scala/testing/Benchmark$$anonfun$main$1
const #10 = NameAndType	#6:#7;//  serialVersionUID:J
const #11 = Field	#9.#10;	//  scala/testing/Benchmark$$anonfun$main$1.serialVersionUID:J
const #12 = Asciz	logFile$1;
const #13 = Asciz	Ljava/io/OutputStreamWriter;;
const #14 = Asciz	<init>;
const #15 = Asciz	(Lscala/testing/Benchmark;Ljava/io/OutputStreamWriter;)V;
const #16 = Asciz	LineNumberTable;
const #17 = NameAndType	#12:#13;//  logFile$1:Ljava/io/OutputStreamWriter;
const #18 = Field	#9.#17;	//  scala/testing/Benchmark$$anonfun$main$1.logFile$1:Ljava/io/OutputStreamWriter;
const #19 = Asciz	java/lang/Object;
const #20 = class	#19;	//  java/lang/Object
const #21 = NameAndType	#14:#4;//  "<init>":()V
const #22 = Method	#20.#21;	//  java/lang/Object."<init>":()V
const #23 = Asciz	scala/Function1$class;
const #24 = class	#23;	//  scala/Function1$class
const #25 = Asciz	$init$;
const #26 = Asciz	(Lscala/Function1;)V;
const #27 = NameAndType	#25:#26;//  $init$:(Lscala/Function1;)V
const #28 = Method	#24.#27;	//  scala/Function1$class.$init$:(Lscala/Function1;)V
const #29 = Asciz	this;
const #30 = Asciz	Lscala/testing/Benchmark$$anonfun$main$1;;
const #31 = Asciz	$outer;
const #32 = Asciz	Lscala/testing/Benchmark;;
const #33 = Asciz	LocalVariableTable;
const #34 = Asciz	apply;
const #35 = Asciz	(Ljava/lang/Object;)Ljava/lang/Object;;
const #36 = Asciz	scala/runtime/BoxesRunTime;
const #37 = class	#36;	//  scala/runtime/BoxesRunTime
const #38 = Asciz	unboxToLong;
const #39 = Asciz	(Ljava/lang/Object;)J;
const #40 = NameAndType	#38:#39;//  unboxToLong:(Ljava/lang/Object;)J
const #41 = Method	#37.#40;	//  scala/runtime/BoxesRunTime.unboxToLong:(Ljava/lang/Object;)J
const #42 = Asciz	(J)V;
const #43 = NameAndType	#34:#42;//  apply:(J)V
const #44 = Method	#9.#43;	//  scala/testing/Benchmark$$anonfun$main$1.apply:(J)V
const #45 = Asciz	scala/runtime/BoxedUnit;
const #46 = class	#45;	//  scala/runtime/BoxedUnit
const #47 = Asciz	UNIT;
const #48 = Asciz	Lscala/runtime/BoxedUnit;;
const #49 = NameAndType	#47:#48;//  UNIT:Lscala/runtime/BoxedUnit;
const #50 = Field	#46.#49;	//  scala/runtime/BoxedUnit.UNIT:Lscala/runtime/BoxedUnit;
const #51 = Asciz	v1;
const #52 = Asciz	Ljava/lang/Object;;
const #53 = Asciz	scala/collection/mutable/StringBuilder;
const #54 = class	#53;	//  scala/collection/mutable/StringBuilder
const #55 = Method	#54.#21;	//  scala/collection/mutable/StringBuilder."<init>":()V
const #56 = Asciz	\t\t;
const #57 = String	#56;	//  \t\t
const #58 = Asciz	append;
const #59 = Asciz	(Ljava/lang/Object;)Lscala/collection/mutable/StringBuilder;;
const #60 = NameAndType	#58:#59;//  append:(Ljava/lang/Object;)Lscala/collection/mutable/StringBuilder;
const #61 = Method	#54.#60;	//  scala/collection/mutable/StringBuilder.append:(Ljava/lang/Object;)Lscala/collection/mutable/StringBuilder;
const #62 = Asciz	boxToLong;
const #63 = Asciz	(J)Ljava/lang/Long;;
const #64 = NameAndType	#62:#63;//  boxToLong:(J)Ljava/lang/Long;
const #65 = Method	#37.#64;	//  scala/runtime/BoxesRunTime.boxToLong:(J)Ljava/lang/Long;
const #66 = Asciz	toString;
const #67 = Asciz	()Ljava/lang/String;;
const #68 = NameAndType	#66:#67;//  toString:()Ljava/lang/String;
const #69 = Method	#54.#68;	//  scala/collection/mutable/StringBuilder.toString:()Ljava/lang/String;
const #70 = Asciz	java/io/OutputStreamWriter;
const #71 = class	#70;	//  java/io/OutputStreamWriter
const #72 = Asciz	write;
const #73 = Asciz	(Ljava/lang/String;)V;
const #74 = NameAndType	#72:#73;//  write:(Ljava/lang/String;)V
const #75 = Method	#71.#74;	//  java/io/OutputStreamWriter.write:(Ljava/lang/String;)V
const #76 = Asciz	t;
const #77 = Asciz	andThen;
const #78 = Asciz	(Lscala/Function1;)Lscala/Function1;;
const #79 = Asciz	(Lscala/Function1;Lscala/Function1;)Lscala/Function1;;
const #80 = NameAndType	#77:#79;//  andThen:(Lscala/Function1;Lscala/Function1;)Lscala/Function1;
const #81 = Method	#24.#80;	//  scala/Function1$class.andThen:(Lscala/Function1;Lscala/Function1;)Lscala/Function1;
const #82 = Asciz	g;
const #83 = Asciz	Lscala/Function1;;
const #84 = Asciz	compose;
const #85 = NameAndType	#84:#79;//  compose:(Lscala/Function1;Lscala/Function1;)Lscala/Function1;
const #86 = Method	#24.#85;	//  scala/Function1$class.compose:(Lscala/Function1;Lscala/Function1;)Lscala/Function1;
const #87 = Asciz	(Lscala/Function1;)Ljava/lang/String;;
const #88 = NameAndType	#66:#87;//  toString:(Lscala/Function1;)Ljava/lang/String;
const #89 = Method	#24.#88;	//  scala/Function1$class.toString:(Lscala/Function1;)Ljava/lang/String;
const #90 = Asciz	Scala;
const #91 = Asciz	InnerClasses;
const #92 = Asciz	scala/testing/Benchmark;
const #93 = class	#92;	//  scala/testing/Benchmark
const #94 = Asciz	$anonfun$main$1;
const #95 = Asciz	scala/Function1;
const #96 = class	#95;	//  scala/Function1
const #97 = Asciz	scala/ScalaObject;
const #98 = class	#97;	//  scala/ScalaObject
const #99 = Asciz	java/io/Serializable;
const #100 = class	#99;	//  java/io/Serializable

{
public static final long serialVersionUID;

public static {};
  Code:
   Stack=2, Locals=0, Args_size=0
   0:	lconst_0
   1:	putstatic	#11; //Field serialVersionUID:J
   4:	return

public scala.testing.Benchmark$$anonfun$main$1(scala.testing.Benchmark, java.io.OutputStreamWriter);
  Code:
   Stack=2, Locals=3, Args_size=3
   0:	aload_0
   1:	aload_2
   2:	putfield	#18; //Field logFile$1:Ljava/io/OutputStreamWriter;
   5:	aload_0
   6:	invokespecial	#22; //Method java/lang/Object."<init>":()V
   9:	aload_0
   10:	invokestatic	#28; //Method scala/Function1$class.$init$:(Lscala/Function1;)V
   13:	return
  LineNumberTable: 
   line 84: 0

  LocalVariableTable: 
   Start  Length  Slot  Name   Signature
   0      14      0    this       Lscala/testing/Benchmark$$anonfun$main$1;
   0      14      1    $outer       Lscala/testing/Benchmark;


public final java.lang.Object apply(java.lang.Object);
  Code:
   Stack=3, Locals=2, Args_size=2
   0:	aload_0
   1:	aload_1
   2:	invokestatic	#41; //Method scala/runtime/BoxesRunTime.unboxToLong:(Ljava/lang/Object;)J
   5:	invokevirtual	#44; //Method apply:(J)V
   8:	getstatic	#50; //Field scala/runtime/BoxedUnit.UNIT:Lscala/runtime/BoxedUnit;
   11:	areturn
  LineNumberTable: 
   line 84: 0

  LocalVariableTable: 
   Start  Length  Slot  Name   Signature
   0      12      0    this       Lscala/testing/Benchmark$$anonfun$main$1;
   0      12      1    v1       Ljava/lang/Object;


public final void apply(long);
  Code:
   Stack=4, Locals=3, Args_size=2
   0:	aload_0
   1:	getfield	#18; //Field logFile$1:Ljava/io/OutputStreamWriter;
   4:	new	#54; //class scala/collection/mutable/StringBuilder
   7:	dup
   8:	invokespecial	#55; //Method scala/collection/mutable/StringBuilder."<init>":()V
   11:	ldc	#57; //String \t\t
   13:	invokevirtual	#61; //Method scala/collection/mutable/StringBuilder.append:(Ljava/lang/Object;)Lscala/collection/mutable/StringBuilder;
   16:	lload_1
   17:	invokestatic	#65; //Method scala/runtime/BoxesRunTime.boxToLong:(J)Ljava/lang/Long;
   20:	invokevirtual	#61; //Method scala/collection/mutable/StringBuilder.append:(Ljava/lang/Object;)Lscala/collection/mutable/StringBuilder;
   23:	invokevirtual	#69; //Method scala/collection/mutable/StringBuilder.toString:()Ljava/lang/String;
   26:	invokevirtual	#75; //Method java/io/OutputStreamWriter.write:(Ljava/lang/String;)V
   29:	return
  LineNumberTable: 
   line 85: 0

  LocalVariableTable: 
   Start  Length  Slot  Name   Signature
   0      30      0    this       Lscala/testing/Benchmark$$anonfun$main$1;
   0      30      1    t       J


public scala.Function1 andThen(scala.Function1);
  Code:
   Stack=2, Locals=2, Args_size=2
   0:	aload_0
   1:	aload_1
   2:	invokestatic	#81; //Method scala/Function1$class.andThen:(Lscala/Function1;Lscala/Function1;)Lscala/Function1;
   5:	areturn
  LineNumberTable: 
   line 84: 0

  LocalVariableTable: 
   Start  Length  Slot  Name   Signature
   0      6      0    this       Lscala/testing/Benchmark$$anonfun$main$1;
   0      6      1    g       Lscala/Function1;


public scala.Function1 compose(scala.Function1);
  Code:
   Stack=2, Locals=2, Args_size=2
   0:	aload_0
   1:	aload_1
   2:	invokestatic	#86; //Method scala/Function1$class.compose:(Lscala/Function1;Lscala/Function1;)Lscala/Function1;
   5:	areturn
  LineNumberTable: 
   line 84: 0

  LocalVariableTable: 
   Start  Length  Slot  Name   Signature
   0      6      0    this       Lscala/testing/Benchmark$$anonfun$main$1;
   0      6      1    g       Lscala/Function1;


public java.lang.String toString();
  Code:
   Stack=1, Locals=1, Args_size=1
   0:	aload_0
   1:	invokestatic	#89; //Method scala/Function1$class.toString:(Lscala/Function1;)Ljava/lang/String;
   4:	areturn
  LineNumberTable: 
   line 84: 0


}

