Compiled from "Benchmark.scala"
public final class scala.testing.Benchmark$$anonfun$runBenchmark$1 extends java.lang.Object implements scala.Function1,scala.ScalaObject,java.io.Serializable
  SourceFile: "Benchmark.scala"
  Scala: length = 0x
   
  InnerClass: 
   public final $anonfun$runBenchmark$1=class scala/testing/Benchmark$$anonfun$runBenchmark$1 of class scala/testing/Benchmark
  minor version: 0
  major version: 49
  Constant pool:
Asciz	SourceFile;
Asciz	Benchmark.scala;
Asciz	<clinit>;
Asciz	()V;
Asciz	Code;
Asciz	serialVersionUID;
Asciz	J;
Asciz	scala/testing/Benchmark$$anonfun$runBenchmark$1;
class	scala/testing/Benchmark$$anonfun$runBenchmark$1
NameAndType	serialVersionUID:J
Field	scala/testing/Benchmark$$anonfun$runBenchmark$1.serialVersionUID:J
Asciz	$outer;
Asciz	Lscala/testing/Benchmark;;
Asciz	<init>;
Asciz	(Lscala/testing/Benchmark;)V;
Asciz	LineNumberTable;
Asciz	java/lang/NullPointerException;
class	java/lang/NullPointerException
NameAndType	"<init>":()V
Method	java/lang/NullPointerException."<init>":()V
NameAndType	$outer:Lscala/testing/Benchmark;
Field	scala/testing/Benchmark$$anonfun$runBenchmark$1.$outer:Lscala/testing/Benchmark;
Asciz	java/lang/Object;
class	java/lang/Object
Method	java/lang/Object."<init>":()V
Asciz	scala/Function1$class;
class	scala/Function1$class
Asciz	$init$;
Asciz	(Lscala/Function1;)V;
NameAndType	$init$:(Lscala/Function1;)V
Method	scala/Function1$class.$init$:(Lscala/Function1;)V
Asciz	this;
Asciz	Lscala/testing/Benchmark$$anonfun$runBenchmark$1;;
Asciz	LocalVariableTable;
Asciz	apply;
Asciz	(Ljava/lang/Object;)Ljava/lang/Object;;
Asciz	scala/runtime/BoxesRunTime;
class	scala/runtime/BoxesRunTime
Asciz	unboxToInt;
Asciz	(Ljava/lang/Object;)I;
NameAndType	unboxToInt:(Ljava/lang/Object;)I
Method	scala/runtime/BoxesRunTime.unboxToInt:(Ljava/lang/Object;)I
Asciz	(I)J;
NameAndType	apply:(I)J
Method	scala/testing/Benchmark$$anonfun$runBenchmark$1.apply:(I)J
Asciz	boxToLong;
Asciz	(J)Ljava/lang/Long;;
NameAndType	boxToLong:(J)Ljava/lang/Long;
Method	scala/runtime/BoxesRunTime.boxToLong:(J)Ljava/lang/Long;
Asciz	v1;
Asciz	Ljava/lang/Object;;
Asciz	java/lang/System;
class	java/lang/System
Asciz	currentTimeMillis;
Asciz	()J;
NameAndType	currentTimeMillis:()J
Method	java/lang/System.currentTimeMillis:()J
Asciz	scala/testing/Benchmark;
class	scala/testing/Benchmark
Asciz	multiplier;
Asciz	()I;
NameAndType	multiplier:()I
InterfaceMethod	scala/testing/Benchmark.multiplier:()I
Asciz	run;
NameAndType	run:()V
InterfaceMethod	scala/testing/Benchmark.run:()V
Asciz	gc;
NameAndType	gc:()V
Method	java/lang/System.gc:()V
Asciz	i;
Asciz	I;
Asciz	stopTime;
Asciz	startTime;
Asciz	andThen;
Asciz	(Lscala/Function1;)Lscala/Function1;;
Asciz	(Lscala/Function1;Lscala/Function1;)Lscala/Function1;;
NameAndType	andThen:(Lscala/Function1;Lscala/Function1;)Lscala/Function1;
Method	scala/Function1$class.andThen:(Lscala/Function1;Lscala/Function1;)Lscala/Function1;
Asciz	g;
Asciz	Lscala/Function1;;
Asciz	compose;
NameAndType	compose:(Lscala/Function1;Lscala/Function1;)Lscala/Function1;
Method	scala/Function1$class.compose:(Lscala/Function1;Lscala/Function1;)Lscala/Function1;
Asciz	toString;
Asciz	()Ljava/lang/String;;
Asciz	(Lscala/Function1;)Ljava/lang/String;;
NameAndType	toString:(Lscala/Function1;)Ljava/lang/String;
Method	scala/Function1$class.toString:(Lscala/Function1;)Ljava/lang/String;
Asciz	Scala;
Asciz	InnerClasses;
Asciz	$anonfun$runBenchmark$1;
Asciz	scala/Function1;
class	scala/Function1
Asciz	scala/ScalaObject;
class	scala/ScalaObject
Asciz	java/io/Serializable;
class	java/io/Serializable

{
public static final long serialVersionUID;
  Signature: J

private final scala.testing.Benchmark $outer;
  Signature: Lscala/testing/Benchmark;

public static {};
  Signature: ()V
  Code:
   Stack=2, Locals=0, Args_size=0
	lconst_0
	putstatic	Field serialVersionUID:J
	return
  Labels:

public scala.testing.Benchmark$$anonfun$runBenchmark$1(scala.testing.Benchmark);
  Signature: (Lscala/testing/Benchmark;)V
  Code:
   Stack=2, Locals=2, Args_size=2
	aload_1
	ifnonnull	l1 // aload_0
	new	class java/lang/NullPointerException
	dup
	invokespecial	Method java/lang/NullPointerException."<init>":()V
	athrow
l1	aload_0
	aload_1
	putfield	Field $outer:Lscala/testing/Benchmark;
	aload_0
	invokespecial	Method java/lang/Object."<init>":()V
	aload_0
	invokestatic	Method scala/Function1$class.$init$:(Lscala/Function1;)V
	return
  Labels:
   	l1 = 12 // aload_0
  LocalVariableTable: 
   Start  Length  Slot  Name   Signature
   0      26      0    this       Lscala/testing/Benchmark$$anonfun$runBenchmark$1;
   0      26      1    $outer       Lscala/testing/Benchmark;


public final java.lang.Object apply(java.lang.Object);
  Signature: (Ljava/lang/Object;)Ljava/lang/Object;
  Code:
   Stack=2, Locals=5, Args_size=2
	aload_0
	getfield	Field $outer:Lscala/testing/Benchmark;
	astore	4
	aload_0
	aload_1
	invokestatic	Method scala/runtime/BoxesRunTime.unboxToInt:(Ljava/lang/Object;)I
	invokevirtual	Method apply:(I)J
	lstore_2
	lload_2
	invokestatic	Method scala/runtime/BoxesRunTime.boxToLong:(J)Ljava/lang/Long;
	areturn
  Labels:
  LocalVariableTable: 
   Start  Length  Slot  Name   Signature
   0      20      0    this       Lscala/testing/Benchmark$$anonfun$runBenchmark$1;
   6      14      1    v1       Ljava/lang/Object;


public final long apply(int);
  Signature: (I)J
  Code:
   Stack=4, Locals=8, Args_size=2
	aload_0
	getfield	Field $outer:Lscala/testing/Benchmark;
	astore	7
	invokestatic	Method java/lang/System.currentTimeMillis:()J
	lstore	5
	iconst_0
	istore_2
l2	iload_2
	aload_0
	getfield	Field $outer:Lscala/testing/Benchmark;
	invokeinterface	InterfaceMethod scala/testing/Benchmark.multiplier:()I
	if_icmpge	l1 // invokestatic
	aload_0
	getfield	Field $outer:Lscala/testing/Benchmark;
	invokeinterface	InterfaceMethod scala/testing/Benchmark.run:()V
	iload_2
	iconst_1
	iadd
	istore_2
	goto	l2 // iload_2
l1	invokestatic	Method java/lang/System.currentTimeMillis:()J
	lstore_3
	invokestatic	Method java/lang/System.gc:()V
	lload_3
	lload	5
	lsub
	lreturn
  Labels:
   	l2 = 13 // iload_2
   	l1 = 42 // invokestatic
  LocalVariableTable: 
   Start  Length  Slot  Name   Signature
   0      54      0    this       Lscala/testing/Benchmark$$anonfun$runBenchmark$1;
   6      48      1    i       I
   13      40      2    i       I
   46      7      3    stopTime       J
   11      42      5    startTime       J


public scala.Function1 andThen(scala.Function1);
  Signature: (Lscala/Function1;)Lscala/Function1;
  Code:
   Stack=2, Locals=2, Args_size=2
	aload_0
	aload_1
	invokestatic	Method scala/Function1$class.andThen:(Lscala/Function1;Lscala/Function1;)Lscala/Function1;
	areturn
  Labels:
  LocalVariableTable: 
   Start  Length  Slot  Name   Signature
   0      6      0    this       Lscala/testing/Benchmark$$anonfun$runBenchmark$1;
   0      6      1    g       Lscala/Function1;


public scala.Function1 compose(scala.Function1);
  Signature: (Lscala/Function1;)Lscala/Function1;
  Code:
   Stack=2, Locals=2, Args_size=2
	aload_0
	aload_1
	invokestatic	Method scala/Function1$class.compose:(Lscala/Function1;Lscala/Function1;)Lscala/Function1;
	areturn
  Labels:
  LocalVariableTable: 
   Start  Length  Slot  Name   Signature
   0      6      0    this       Lscala/testing/Benchmark$$anonfun$runBenchmark$1;
   0      6      1    g       Lscala/Function1;


public java.lang.String toString();
  Signature: ()Ljava/lang/String;
  Code:
   Stack=1, Locals=1, Args_size=1
	aload_0
	invokestatic	Method scala/Function1$class.toString:(Lscala/Function1;)Ljava/lang/String;
	areturn
  Labels:

}

