Compiled from "Benchmark.scala"
public final class scala.testing.Benchmark$$anonfun$runBenchmark$1 extends java.lang.Object implements scala.Function1,scala.ScalaObject,java.io.Serializable
  SourceFile: "Benchmark.scala"
  Scala: length = 0x
   
  InnerClass: 
   public final #91= #15 of #58; //$anonfun$runBenchmark$1=class scala/testing/Benchmark$$anonfun$runBenchmark$1 of class scala/testing/Benchmark
  minor version: 0
  major version: 49
  Constant pool:
const #1 = Asciz	SourceFile;
const #2 = Asciz	Benchmark.scala;
const #3 = Asciz	$outer;
const #4 = Asciz	Lscala/testing/Benchmark;;
const #5 = Asciz	<init>;
const #6 = Asciz	(Lscala/testing/Benchmark;)V;
const #7 = Asciz	Code;
const #8 = Asciz	LineNumberTable;
const #9 = Asciz	java/lang/NullPointerException;
const #10 = class	#9;	//  java/lang/NullPointerException
const #11 = Asciz	()V;
const #12 = NameAndType	#5:#11;//  "<init>":()V
const #13 = Method	#10.#12;	//  java/lang/NullPointerException."<init>":()V
const #14 = Asciz	scala/testing/Benchmark$$anonfun$runBenchmark$1;
const #15 = class	#14;	//  scala/testing/Benchmark$$anonfun$runBenchmark$1
const #16 = NameAndType	#3:#4;//  $outer:Lscala/testing/Benchmark;
const #17 = Field	#15.#16;	//  scala/testing/Benchmark$$anonfun$runBenchmark$1.$outer:Lscala/testing/Benchmark;
const #18 = Asciz	java/lang/Object;
const #19 = class	#18;	//  java/lang/Object
const #20 = Method	#19.#12;	//  java/lang/Object."<init>":()V
const #21 = Asciz	scala/Function1$class;
const #22 = class	#21;	//  scala/Function1$class
const #23 = Asciz	$init$;
const #24 = Asciz	(Lscala/Function1;)V;
const #25 = NameAndType	#23:#24;//  $init$:(Lscala/Function1;)V
const #26 = Method	#22.#25;	//  scala/Function1$class.$init$:(Lscala/Function1;)V
const #27 = Asciz	this;
const #28 = Asciz	Lscala/testing/Benchmark$$anonfun$runBenchmark$1;;
const #29 = Asciz	LocalVariableTable;
const #30 = Asciz	apply;
const #31 = Asciz	(Ljava/lang/Object;)Ljava/lang/Object;;
const #32 = Asciz	scala/runtime/BoxesRunTime;
const #33 = class	#32;	//  scala/runtime/BoxesRunTime
const #34 = Asciz	unboxToInt;
const #35 = Asciz	(Ljava/lang/Object;)I;
const #36 = NameAndType	#34:#35;//  unboxToInt:(Ljava/lang/Object;)I
const #37 = Method	#33.#36;	//  scala/runtime/BoxesRunTime.unboxToInt:(Ljava/lang/Object;)I
const #38 = Asciz	(I)J;
const #39 = NameAndType	#30:#38;//  apply:(I)J
const #40 = Method	#15.#39;	//  scala/testing/Benchmark$$anonfun$runBenchmark$1.apply:(I)J
const #41 = Asciz	boxToLong;
const #42 = Asciz	(J)Ljava/lang/Long;;
const #43 = NameAndType	#41:#42;//  boxToLong:(J)Ljava/lang/Long;
const #44 = Method	#33.#43;	//  scala/runtime/BoxesRunTime.boxToLong:(J)Ljava/lang/Long;
const #45 = Asciz	v1;
const #46 = Asciz	Ljava/lang/Object;;
const #47 = Asciz	scala/compat/Platform$;
const #48 = class	#47;	//  scala/compat/Platform$
const #49 = Asciz	MODULE$;
const #50 = Asciz	Lscala/compat/Platform$;;
const #51 = NameAndType	#49:#50;//  MODULE$:Lscala/compat/Platform$;
const #52 = Field	#48.#51;	//  scala/compat/Platform$.MODULE$:Lscala/compat/Platform$;
const #53 = Asciz	currentTime;
const #54 = Asciz	()J;
const #55 = NameAndType	#53:#54;//  currentTime:()J
const #56 = Method	#48.#55;	//  scala/compat/Platform$.currentTime:()J
const #57 = Asciz	scala/testing/Benchmark;
const #58 = class	#57;	//  scala/testing/Benchmark
const #59 = Asciz	multiplier;
const #60 = Asciz	()I;
const #61 = NameAndType	#59:#60;//  multiplier:()I
const #62 = InterfaceMethod	#58.#61;	//  scala/testing/Benchmark.multiplier:()I
const #63 = Asciz	run;
const #64 = NameAndType	#63:#11;//  run:()V
const #65 = InterfaceMethod	#58.#64;	//  scala/testing/Benchmark.run:()V
const #66 = Asciz	collectGarbage;
const #67 = NameAndType	#66:#11;//  collectGarbage:()V
const #68 = Method	#48.#67;	//  scala/compat/Platform$.collectGarbage:()V
const #69 = Asciz	i;
const #70 = Asciz	I;
const #71 = Asciz	startTime;
const #72 = Asciz	J;
const #73 = Asciz	stopTime;
const #74 = Asciz	andThen;
const #75 = Asciz	(Lscala/Function1;)Lscala/Function1;;
const #76 = Asciz	(Lscala/Function1;Lscala/Function1;)Lscala/Function1;;
const #77 = NameAndType	#74:#76;//  andThen:(Lscala/Function1;Lscala/Function1;)Lscala/Function1;
const #78 = Method	#22.#77;	//  scala/Function1$class.andThen:(Lscala/Function1;Lscala/Function1;)Lscala/Function1;
const #79 = Asciz	g;
const #80 = Asciz	Lscala/Function1;;
const #81 = Asciz	compose;
const #82 = NameAndType	#81:#76;//  compose:(Lscala/Function1;Lscala/Function1;)Lscala/Function1;
const #83 = Method	#22.#82;	//  scala/Function1$class.compose:(Lscala/Function1;Lscala/Function1;)Lscala/Function1;
const #84 = Asciz	toString;
const #85 = Asciz	()Ljava/lang/String;;
const #86 = Asciz	(Lscala/Function1;)Ljava/lang/String;;
const #87 = NameAndType	#84:#86;//  toString:(Lscala/Function1;)Ljava/lang/String;
const #88 = Method	#22.#87;	//  scala/Function1$class.toString:(Lscala/Function1;)Ljava/lang/String;
const #89 = Asciz	Scala;
const #90 = Asciz	InnerClasses;
const #91 = Asciz	$anonfun$runBenchmark$1;
const #92 = Asciz	scala/Function1;
const #93 = class	#92;	//  scala/Function1
const #94 = Asciz	scala/ScalaObject;
const #95 = class	#94;	//  scala/ScalaObject
const #96 = Asciz	java/io/Serializable;
const #97 = class	#96;	//  java/io/Serializable

{
public scala.testing.Benchmark$$anonfun$runBenchmark$1(scala.testing.Benchmark);
  Code:
   Stack=2, Locals=2, Args_size=2
   0:	aload_1
   1:	ifnonnull	12
   4:	new	#10; //class java/lang/NullPointerException
   7:	dup
   8:	invokespecial	#13; //Method java/lang/NullPointerException."<init>":()V
   11:	athrow
   12:	aload_0
   13:	aload_1
   14:	putfield	#17; //Field $outer:Lscala/testing/Benchmark;
   17:	aload_0
   18:	invokespecial	#20; //Method java/lang/Object."<init>":()V
   21:	aload_0
   22:	invokestatic	#26; //Method scala/Function1$class.$init$:(Lscala/Function1;)V
   25:	return
  LineNumberTable: 
   line 55: 0

  LocalVariableTable: 
   Start  Length  Slot  Name   Signature
   0      26      0    this       Lscala/testing/Benchmark$$anonfun$runBenchmark$1;
   0      26      1    $outer       Lscala/testing/Benchmark;


public final java.lang.Object apply(java.lang.Object);
  Code:
   Stack=2, Locals=3, Args_size=2
   0:	aload_0
   1:	getfield	#17; //Field $outer:Lscala/testing/Benchmark;
   4:	astore_2
   5:	aload_0
   6:	aload_1
   7:	invokestatic	#37; //Method scala/runtime/BoxesRunTime.unboxToInt:(Ljava/lang/Object;)I
   10:	invokevirtual	#40; //Method apply:(I)J
   13:	invokestatic	#44; //Method scala/runtime/BoxesRunTime.boxToLong:(J)Ljava/lang/Long;
   16:	areturn
  LineNumberTable: 
   line 55: 0

  LocalVariableTable: 
   Start  Length  Slot  Name   Signature
   0      17      0    this       Lscala/testing/Benchmark$$anonfun$runBenchmark$1;
   5      12      1    v1       Ljava/lang/Object;


public final long apply(int);
  Code:
   Stack=4, Locals=8, Args_size=2
   0:	aload_0
   1:	getfield	#17; //Field $outer:Lscala/testing/Benchmark;
   4:	astore	7
   6:	getstatic	#52; //Field scala/compat/Platform$.MODULE$:Lscala/compat/Platform$;
   9:	invokevirtual	#56; //Method scala/compat/Platform$.currentTime:()J
   12:	lstore_2
   13:	iconst_0
   14:	istore	4
   16:	iload	4
   18:	aload_0
   19:	getfield	#17; //Field $outer:Lscala/testing/Benchmark;
   22:	invokeinterface	#62,  1; //InterfaceMethod scala/testing/Benchmark.multiplier:()I
   27:	if_icmpge	48
   30:	aload_0
   31:	getfield	#17; //Field $outer:Lscala/testing/Benchmark;
   34:	invokeinterface	#65,  1; //InterfaceMethod scala/testing/Benchmark.run:()V
   39:	iload	4
   41:	iconst_1
   42:	iadd
   43:	istore	4
   45:	goto	16
   48:	getstatic	#52; //Field scala/compat/Platform$.MODULE$:Lscala/compat/Platform$;
   51:	invokevirtual	#56; //Method scala/compat/Platform$.currentTime:()J
   54:	lstore	5
   56:	getstatic	#52; //Field scala/compat/Platform$.MODULE$:Lscala/compat/Platform$;
   59:	invokevirtual	#68; //Method scala/compat/Platform$.collectGarbage:()V
   62:	lload	5
   64:	lload_2
   65:	lsub
   66:	lreturn
  LineNumberTable: 
   line 56: 0
   line 57: 13
   line 58: 30
   line 59: 39
   line 57: 45
   line 61: 48
   line 62: 56
   line 64: 62

  LocalVariableTable: 
   Start  Length  Slot  Name   Signature
   0      67      0    this       Lscala/testing/Benchmark$$anonfun$runBenchmark$1;
   6      61      1    i       I
   13      53      2    startTime       J
   16      50      4    i       I
   56      10      5    stopTime       J


public scala.Function1 andThen(scala.Function1);
  Code:
   Stack=2, Locals=2, Args_size=2
   0:	aload_0
   1:	aload_1
   2:	invokestatic	#78; //Method scala/Function1$class.andThen:(Lscala/Function1;Lscala/Function1;)Lscala/Function1;
   5:	areturn
  LineNumberTable: 
   line 55: 0

  LocalVariableTable: 
   Start  Length  Slot  Name   Signature
   0      6      0    this       Lscala/testing/Benchmark$$anonfun$runBenchmark$1;
   0      6      1    g       Lscala/Function1;


public scala.Function1 compose(scala.Function1);
  Code:
   Stack=2, Locals=2, Args_size=2
   0:	aload_0
   1:	aload_1
   2:	invokestatic	#83; //Method scala/Function1$class.compose:(Lscala/Function1;Lscala/Function1;)Lscala/Function1;
   5:	areturn
  LineNumberTable: 
   line 55: 0

  LocalVariableTable: 
   Start  Length  Slot  Name   Signature
   0      6      0    this       Lscala/testing/Benchmark$$anonfun$runBenchmark$1;
   0      6      1    g       Lscala/Function1;


public java.lang.String toString();
  Code:
   Stack=1, Locals=1, Args_size=1
   0:	aload_0
   1:	invokestatic	#88; //Method scala/Function1$class.toString:(Lscala/Function1;)Ljava/lang/String;
   4:	areturn
  LineNumberTable: 
   line 55: 0


}

