Compiled from "Show.scala"
public abstract class scala.testing.Show$class extends java.lang.Object
  SourceFile: "Show.scala"
  Scala: length = 0x
   
  InnerClass: 
   public SymApply=class scala/testing/Show$SymApply of class scala/testing/Show
   public ofRef=class scala/collection/mutable/ArrayOps$ofRef of class scala/collection/mutable/ArrayOps
   public final $anonfun$1=class scala/testing/Show$$anonfun$1 of class scala/testing/Show
   public final $anonfun$test$2=class scala/testing/Show$$anonfun$test$2 of class scala/testing/Show
   public final $anonfun$test$1=class scala/testing/Show$$anonfun$test$1 of class scala/testing/Show
   public GenericCanBuildFrom=class scala/collection/generic/TraversableFactory$GenericCanBuildFrom of class scala/collection/generic/TraversableFactory
  minor version: 0
  major version: 49
  Constant pool:
Asciz	SourceFile;
Asciz	Show.scala;
Asciz	$init$;
Asciz	(Lscala/testing/Show;)V;
Asciz	Code;
Asciz	LineNumberTable;
Asciz	$this;
Asciz	Lscala/testing/Show;;
Asciz	LocalVariableTable;
Asciz	testMethod$1;
Asciz	(Lscala/testing/Show;Ljava/lang/reflect/Method;Lscala/Symbol;Lscala/collection/Seq;Lscala/collection/Seq;)Ljava/lang/String;;
Asciz	scala/collection/mutable/StringBuilder;
class	scala/collection/mutable/StringBuilder
Asciz	<init>;
Asciz	()V;
NameAndType	"<init>":()V
Method	scala/collection/mutable/StringBuilder."<init>":()V
Asciz	scala/Symbol;
class	scala/Symbol
Asciz	name;
Asciz	()Ljava/lang/String;;
NameAndType	name:()Ljava/lang/String;
Method	scala/Symbol.name:()Ljava/lang/String;
Asciz	append;
Asciz	(Ljava/lang/Object;)Lscala/collection/mutable/StringBuilder;;
NameAndType	append:(Ljava/lang/Object;)Lscala/collection/mutable/StringBuilder;
Method	scala/collection/mutable/StringBuilder.append:(Ljava/lang/Object;)Lscala/collection/mutable/StringBuilder;
Asciz	(;
String	(
Asciz	,;
String	,
Asciz	scala/collection/TraversableLike;
class	scala/collection/TraversableLike
Asciz	mkString;
Asciz	(Ljava/lang/String;)Ljava/lang/String;;
NameAndType	mkString:(Ljava/lang/String;)Ljava/lang/String;
InterfaceMethod	scala/collection/TraversableLike.mkString:(Ljava/lang/String;)Ljava/lang/String;
Asciz	)  gives  ;
String	)  gives  
Asciz	scala/testing/Show$class;
class	scala/testing/Show$class
Asciz	liftedTree1$1;
Asciz	(Lscala/testing/Show;Lscala/collection/Seq;Ljava/lang/reflect/Method;)Ljava/lang/Object;;
NameAndType	liftedTree1$1:(Lscala/testing/Show;Lscala/collection/Seq;Ljava/lang/reflect/Method;)Ljava/lang/Object;
Method	scala/testing/Show$class.liftedTree1$1:(Lscala/testing/Show;Lscala/collection/Seq;Ljava/lang/reflect/Method;)Ljava/lang/Object;
Asciz	toString;
NameAndType	toString:()Ljava/lang/String;
Method	scala/collection/mutable/StringBuilder.toString:()Ljava/lang/String;
Asciz	meth$1;
Asciz	Ljava/lang/reflect/Method;;
Asciz	scala/reflect/Manifest$;
class	scala/reflect/Manifest$
Asciz	MODULE$;
Asciz	Lscala/reflect/Manifest$;;
NameAndType	MODULE$:Lscala/reflect/Manifest$;
Field	scala/reflect/Manifest$.MODULE$:Lscala/reflect/Manifest$;
Asciz	Object;
Asciz	()Lscala/reflect/Manifest;;
NameAndType	Object:()Lscala/reflect/Manifest;
Method	scala/reflect/Manifest$.Object:()Lscala/reflect/Manifest;
Asciz	toArray;
Asciz	(Lscala/reflect/ClassManifest;)Ljava/lang/Object;;
NameAndType	toArray:(Lscala/reflect/ClassManifest;)Ljava/lang/Object;
InterfaceMethod	scala/collection/TraversableLike.toArray:(Lscala/reflect/ClassManifest;)Ljava/lang/Object;
Asciz	[Ljava/lang/Object;;
class	"[Ljava/lang/Object;"
Asciz	java/lang/reflect/Method;
class	java/lang/reflect/Method
Asciz	invoke;
Asciz	(Ljava/lang/Object;[Ljava/lang/Object;)Ljava/lang/Object;;
NameAndType	invoke:(Ljava/lang/Object;[Ljava/lang/Object;)Ljava/lang/Object;
Method	java/lang/reflect/Method.invoke:(Ljava/lang/Object;[Ljava/lang/Object;)Ljava/lang/Object;
Asciz	java/lang/IllegalAccessException;
class	java/lang/IllegalAccessException
Asciz	java/lang/IllegalArgumentException;
class	java/lang/IllegalArgumentException
Asciz	java/lang/reflect/InvocationTargetException;
class	java/lang/reflect/InvocationTargetException
Asciz	exceptionResult1;
Asciz	Ljava/lang/Object;;
Asciz	test;
Asciz	(Lscala/testing/Show;Lscala/Symbol;Lscala/collection/Seq;)Ljava/lang/String;;
Asciz	scala/testing/Show$$anonfun$1;
class	scala/testing/Show$$anonfun$1
NameAndType	"<init>":(Lscala/testing/Show;)V
Method	scala/testing/Show$$anonfun$1."<init>":(Lscala/testing/Show;)V
Asciz	scala/collection/Seq$;
class	scala/collection/Seq$
Asciz	Lscala/collection/Seq$;;
NameAndType	MODULE$:Lscala/collection/Seq$;
Field	scala/collection/Seq$.MODULE$:Lscala/collection/Seq$;
Asciz	scala/collection/generic/TraversableFactory$GenericCanBuildFrom;
class	scala/collection/generic/TraversableFactory$GenericCanBuildFrom
Asciz	(Lscala/collection/generic/TraversableFactory;)V;
NameAndType	"<init>":(Lscala/collection/generic/TraversableFactory;)V
Method	scala/collection/generic/TraversableFactory$GenericCanBuildFrom."<init>":(Lscala/collection/generic/TraversableFactory;)V
Asciz	map;
Asciz	(Lscala/Function1;Lscala/collection/generic/CanBuildFrom;)Ljava/lang/Object;;
NameAndType	map:(Lscala/Function1;Lscala/collection/generic/CanBuildFrom;)Ljava/lang/Object;
InterfaceMethod	scala/collection/TraversableLike.map:(Lscala/Function1;Lscala/collection/generic/CanBuildFrom;)Ljava/lang/Object;
Asciz	scala/collection/Seq;
class	scala/collection/Seq
Asciz	java/lang/Object;
class	java/lang/Object
Asciz	getClass;
Asciz	()Ljava/lang/Class;;
NameAndType	getClass:()Ljava/lang/Class;
Method	java/lang/Object.getClass:()Ljava/lang/Class;
Asciz	java/lang/Class;
class	java/lang/Class
Asciz	getMethods;
Asciz	()[Ljava/lang/reflect/Method;;
NameAndType	getMethods:()[Ljava/lang/reflect/Method;
Method	java/lang/Class.getMethods:()[Ljava/lang/reflect/Method;
Asciz	scala/collection/mutable/ArrayOps$ofRef;
class	scala/collection/mutable/ArrayOps$ofRef
Asciz	([Ljava/lang/Object;)V;
NameAndType	"<init>":([Ljava/lang/Object;)V
Method	scala/collection/mutable/ArrayOps$ofRef."<init>":([Ljava/lang/Object;)V
Asciz	toList;
Asciz	()Lscala/collection/immutable/List;;
NameAndType	toList:()Lscala/collection/immutable/List;
InterfaceMethod	scala/collection/TraversableLike.toList:()Lscala/collection/immutable/List;
Asciz	scala/testing/Show$$anonfun$test$1;
class	scala/testing/Show$$anonfun$test$1
Asciz	(Lscala/testing/Show;Lscala/Symbol;)V;
NameAndType	"<init>":(Lscala/testing/Show;Lscala/Symbol;)V
Method	scala/testing/Show$$anonfun$test$1."<init>":(Lscala/testing/Show;Lscala/Symbol;)V
Asciz	filter;
Asciz	(Lscala/Function1;)Ljava/lang/Object;;
NameAndType	filter:(Lscala/Function1;)Ljava/lang/Object;
InterfaceMethod	scala/collection/TraversableLike.filter:(Lscala/Function1;)Ljava/lang/Object;
Asciz	scala/collection/immutable/List;
class	scala/collection/immutable/List
Asciz	scala/collection/immutable/Nil$;
class	scala/collection/immutable/Nil$
Asciz	Ljava/lang/String;;
NameAndType	name:Ljava/lang/String;
Field	scala/Symbol.name:Ljava/lang/String;
Asciz	 is not defined;
String	 is not defined
Asciz	scala/MatchError;
class	scala/MatchError
Asciz	scala/collection/SeqLike;
class	scala/collection/SeqLike
InterfaceMethod	scala/collection/SeqLike.toString:()Ljava/lang/String;
Asciz	(Ljava/lang/String;)V;
NameAndType	"<init>":(Ljava/lang/String;)V
Method	scala/MatchError."<init>":(Ljava/lang/String;)V
Asciz	scala/collection/immutable/$colon$colon;
class	scala/collection/immutable/$colon$colon
Asciz	scala$collection$immutable$$colon$colon$$hd;
NameAndType	scala$collection$immutable$$colon$colon$$hd:Ljava/lang/Object;
Field	scala/collection/immutable/$colon$colon.scala$collection$immutable$$colon$colon$$hd:Ljava/lang/Object;
Asciz	Lscala/collection/immutable/Nil$;;
NameAndType	MODULE$:Lscala/collection/immutable/Nil$;
Field	scala/collection/immutable/Nil$.MODULE$:Lscala/collection/immutable/Nil$;
Asciz	tl;
Asciz	Lscala/collection/immutable/List;;
NameAndType	tl:Lscala/collection/immutable/List;
Field	scala/collection/immutable/$colon$colon.tl:Lscala/collection/immutable/List;
Asciz	equals;
Asciz	(Ljava/lang/Object;)Z;
NameAndType	equals:(Ljava/lang/Object;)Z
Method	java/lang/Object.equals:(Ljava/lang/Object;)Z
NameAndType	testMethod$1:(Lscala/testing/Show;Ljava/lang/reflect/Method;Lscala/Symbol;Lscala/collection/Seq;Lscala/collection/Seq;)Ljava/lang/String;
Method	scala/testing/Show$class.testMethod$1:(Lscala/testing/Show;Ljava/lang/reflect/Method;Lscala/Symbol;Lscala/collection/Seq;Lscala/collection/Seq;)Ljava/lang/String;
Asciz	scala/testing/Show$$anonfun$test$2;
class	scala/testing/Show$$anonfun$test$2
Asciz	(Lscala/testing/Show;Lscala/collection/Seq;)V;
NameAndType	"<init>":(Lscala/testing/Show;Lscala/collection/Seq;)V
Method	scala/testing/Show$$anonfun$test$2."<init>":(Lscala/testing/Show;Lscala/collection/Seq;)V
Asciz	scala/collection/IterableLike;
class	scala/collection/IterableLike
Asciz	head;
Asciz	()Ljava/lang/Object;;
NameAndType	head:()Ljava/lang/Object;
InterfaceMethod	scala/collection/IterableLike.head:()Ljava/lang/Object;
Asciz	cannot disambiguate between multiple implementations of ;
String	cannot disambiguate between multiple implementations of 
Asciz	f$1;
Asciz	Lscala/Symbol;;
Asciz	args$1;
Asciz	Lscala/collection/Seq;;
Asciz	temp10;
Asciz	temp9;
Asciz	Lscala/collection/immutable/$colon$colon;;
Asciz	ms;
Asciz	temp3;
Asciz	temp4;
Asciz	args1$1;
Asciz	temp1;
Asciz	temp7;
Asciz	symApply;
Asciz	(Lscala/testing/Show;Lscala/Symbol;)Lscala/testing/Show$SymApply;;
Asciz	scala/testing/Show$SymApply;
class	scala/testing/Show$SymApply
Method	scala/testing/Show$SymApply."<init>":(Lscala/testing/Show;Lscala/Symbol;)V
Asciz	sym;
Asciz	Scala;
Asciz	InnerClasses;
Asciz	scala/testing/Show;
class	scala/testing/Show
Asciz	SymApply;
Asciz	scala/collection/mutable/ArrayOps;
class	scala/collection/mutable/ArrayOps
Asciz	ofRef;
Asciz	$anonfun$1;
Asciz	$anonfun$test$2;
Asciz	$anonfun$test$1;
Asciz	scala/collection/generic/TraversableFactory;
class	scala/collection/generic/TraversableFactory
Asciz	GenericCanBuildFrom;

{
public static void $init$(scala.testing.Show);
  Signature: (Lscala/testing/Show;)V
  Code:
   Stack=0, Locals=1, Args_size=1
	return
  Labels:
  LocalVariableTable: 
   Start  Length  Slot  Name   Signature
   0      1      0    $this       Lscala/testing/Show;


private static final java.lang.String testMethod$1(scala.testing.Show, java.lang.reflect.Method, scala.Symbol, scala.collection.Seq, scala.collection.Seq);
  Signature: (Lscala/testing/Show;Ljava/lang/reflect/Method;Lscala/Symbol;Lscala/collection/Seq;Lscala/collection/Seq;)Ljava/lang/String;
  Code:
   Stack=4, Locals=5, Args_size=5
	new	class scala/collection/mutable/StringBuilder
	dup
	invokespecial	Method scala/collection/mutable/StringBuilder."<init>":()V
	aload_2
	invokevirtual	Method scala/Symbol.name:()Ljava/lang/String;
	invokevirtual	Method scala/collection/mutable/StringBuilder.append:(Ljava/lang/Object;)Lscala/collection/mutable/StringBuilder;
	ldc	String (
	invokevirtual	Method scala/collection/mutable/StringBuilder.append:(Ljava/lang/Object;)Lscala/collection/mutable/StringBuilder;
	aload_3
	ldc	String ,
	invokeinterface	InterfaceMethod scala/collection/TraversableLike.mkString:(Ljava/lang/String;)Ljava/lang/String;
	invokevirtual	Method scala/collection/mutable/StringBuilder.append:(Ljava/lang/Object;)Lscala/collection/mutable/StringBuilder;
	ldc	String )  gives  
	invokevirtual	Method scala/collection/mutable/StringBuilder.append:(Ljava/lang/Object;)Lscala/collection/mutable/StringBuilder;
	aload_0
	aload	4
	aload_1
	invokestatic	Method liftedTree1$1:(Lscala/testing/Show;Lscala/collection/Seq;Ljava/lang/reflect/Method;)Ljava/lang/Object;
	invokevirtual	Method scala/collection/mutable/StringBuilder.append:(Ljava/lang/Object;)Lscala/collection/mutable/StringBuilder;
	invokevirtual	Method scala/collection/mutable/StringBuilder.toString:()Ljava/lang/String;
	areturn
  Labels:
  LocalVariableTable: 
   Start  Length  Slot  Name   Signature
   0      49      0    $this       Lscala/testing/Show;
   0      49      1    meth$1       Ljava/lang/reflect/Method;


private static final java.lang.Object liftedTree1$1(scala.testing.Show, scala.collection.Seq, java.lang.reflect.Method);
  Signature: (Lscala/testing/Show;Lscala/collection/Seq;Ljava/lang/reflect/Method;)Ljava/lang/Object;
  Code:
   Stack=4, Locals=7, Args_size=3
	aload_2
	aload_0
	aload_1
	getstatic	Field scala/reflect/Manifest$.MODULE$:Lscala/reflect/Manifest$;
	invokevirtual	Method scala/reflect/Manifest$.Object:()Lscala/reflect/Manifest;
	invokeinterface	InterfaceMethod scala/collection/TraversableLike.toArray:(Lscala/reflect/ClassManifest;)Ljava/lang/Object;
	checkcast	class "[Ljava/lang/Object;"
	invokevirtual	Method java/lang/reflect/Method.invoke:(Ljava/lang/Object;[Ljava/lang/Object;)Ljava/lang/Object;
	astore_3
	goto	l1 // aload_3
	astore	4
	aload	4
	astore_3
	goto	l1 // aload_3
	astore	5
	aload	5
	astore_3
	goto	l1 // aload_3
	astore	6
	aload	6
	astore_3
l1	aload_3
	areturn
  Labels:
   	l1 = 45 // aload_3
  Exception table:
   from   to  target type
     0    24    40   Class java/lang/IllegalAccessException

     0    24    32   Class java/lang/IllegalArgumentException

     0    24    24   Class java/lang/reflect/InvocationTargetException

  LocalVariableTable: 
   Start  Length  Slot  Name   Signature
   0      47      0    $this       Lscala/testing/Show;
   0      46      3    exceptionResult1       Ljava/lang/Object;


public static java.lang.String test(scala.testing.Show, scala.Symbol, scala.collection.Seq);
  Signature: (Lscala/testing/Show;Lscala/Symbol;Lscala/collection/Seq;)Ljava/lang/String;
  Code:
   Stack=5, Locals=15, Args_size=3
	aload_2
	new	class scala/testing/Show$$anonfun$1
	dup
	aload_0
	invokespecial	Method scala/testing/Show$$anonfun$1."<init>":(Lscala/testing/Show;)V
	getstatic	Field scala/collection/Seq$.MODULE$:Lscala/collection/Seq$;
	astore_3
	new	class scala/collection/generic/TraversableFactory$GenericCanBuildFrom
	dup
	aload_3
	invokespecial	Method scala/collection/generic/TraversableFactory$GenericCanBuildFrom."<init>":(Lscala/collection/generic/TraversableFactory;)V
	invokeinterface	InterfaceMethod scala/collection/TraversableLike.map:(Lscala/Function1;Lscala/collection/generic/CanBuildFrom;)Ljava/lang/Object;
	checkcast	class scala/collection/Seq
	astore	12
	aload_0
	invokevirtual	Method java/lang/Object.getClass:()Ljava/lang/Class;
	invokevirtual	Method java/lang/Class.getMethods:()[Ljava/lang/reflect/Method;
	checkcast	class "[Ljava/lang/Object;"
	astore	4
	new	class scala/collection/mutable/ArrayOps$ofRef
	dup
	aload	4
	invokespecial	Method scala/collection/mutable/ArrayOps$ofRef."<init>":([Ljava/lang/Object;)V
	invokeinterface	InterfaceMethod scala/collection/TraversableLike.toList:()Lscala/collection/immutable/List;
	new	class scala/testing/Show$$anonfun$test$1
	dup
	aload_0
	aload_1
	invokespecial	Method scala/testing/Show$$anonfun$test$1."<init>":(Lscala/testing/Show;Lscala/Symbol;)V
	invokeinterface	InterfaceMethod scala/collection/TraversableLike.filter:(Lscala/Function1;)Ljava/lang/Object;
	checkcast	class scala/collection/immutable/List
	astore	14
	aload	14
	instanceof	class scala/collection/immutable/Nil$
	ifeq	l1 // aload
	iconst_1
	ifeq	l2 // new
	new	class scala/collection/mutable/StringBuilder
	dup
	invokespecial	Method scala/collection/mutable/StringBuilder."<init>":()V
	aload_1
	getfield	Field scala/Symbol.name:Ljava/lang/String;
	invokevirtual	Method scala/collection/mutable/StringBuilder.append:(Ljava/lang/Object;)Lscala/collection/mutable/StringBuilder;
	ldc	String  is not defined
	invokevirtual	Method scala/collection/mutable/StringBuilder.append:(Ljava/lang/Object;)Lscala/collection/mutable/StringBuilder;
	invokevirtual	Method scala/collection/mutable/StringBuilder.toString:()Ljava/lang/String;
	goto	l3 // areturn
l2	new	class scala/MatchError
	dup
	aload	14
	invokeinterface	InterfaceMethod scala/collection/SeqLike.toString:()Ljava/lang/String;
	invokespecial	Method scala/MatchError."<init>":(Ljava/lang/String;)V
	athrow
l1	aload	14
	instanceof	class scala/collection/immutable/$colon$colon
	ifeq	l4 // iconst_1
	aload	14
	checkcast	class scala/collection/immutable/$colon$colon
	astore	7
	aload	7
	getfield	Field scala/collection/immutable/$colon$colon.scala$collection$immutable$$colon$colon$$hd:Ljava/lang/Object;
	checkcast	class java/lang/reflect/Method
	astore	6
	getstatic	Field scala/collection/immutable/Nil$.MODULE$:Lscala/collection/immutable/Nil$;
	aload	7
	getfield	Field scala/collection/immutable/$colon$colon.tl:Lscala/collection/immutable/List;
	astore	5
	dup
	ifnonnull	l5 // aload
	pop
	aload	5
	ifnull	l6 // iconst_1
	goto	l7 // iconst_1
l5	aload	5
	invokevirtual	Method java/lang/Object.equals:(Ljava/lang/Object;)Z
	ifeq	l7 // iconst_1
l6	iconst_1
	ifeq	l8 // new
	aload_0
	aload	6
	aload_1
	aload_2
	aload	12
	invokestatic	Method testMethod$1:(Lscala/testing/Show;Ljava/lang/reflect/Method;Lscala/Symbol;Lscala/collection/Seq;Lscala/collection/Seq;)Ljava/lang/String;
	goto	l3 // areturn
l8	new	class scala/MatchError
	dup
	aload	14
	invokeinterface	InterfaceMethod scala/collection/SeqLike.toString:()Ljava/lang/String;
	invokespecial	Method scala/MatchError."<init>":(Ljava/lang/String;)V
	athrow
l7	iconst_1
	ifeq	l9 // new
	aload	7
	astore	8
	goto	l10 // aload
l9	new	class scala/MatchError
	dup
	aload	14
	invokeinterface	InterfaceMethod scala/collection/SeqLike.toString:()Ljava/lang/String;
	invokespecial	Method scala/MatchError."<init>":(Ljava/lang/String;)V
	athrow
l4	iconst_1
	ifeq	l11 // new
	aload	14
	astore	8
l10	aload	8
	new	class scala/testing/Show$$anonfun$test$2
	dup
	aload_0
	aload_2
	invokespecial	Method scala/testing/Show$$anonfun$test$2."<init>":(Lscala/testing/Show;Lscala/collection/Seq;)V
	invokeinterface	InterfaceMethod scala/collection/TraversableLike.filter:(Lscala/Function1;)Ljava/lang/Object;
	checkcast	class scala/collection/immutable/List
	astore	13
	aload	13
	instanceof	class scala/collection/immutable/Nil$
	ifeq	l12 // aload
	iconst_1
	ifeq	l13 // new
	aload_0
	aload	8
	invokeinterface	InterfaceMethod scala/collection/IterableLike.head:()Ljava/lang/Object;
	checkcast	class java/lang/reflect/Method
	aload_1
	aload_2
	aload	12
	invokestatic	Method testMethod$1:(Lscala/testing/Show;Ljava/lang/reflect/Method;Lscala/Symbol;Lscala/collection/Seq;Lscala/collection/Seq;)Ljava/lang/String;
	goto	l3 // areturn
l13	new	class scala/MatchError
	dup
	aload	13
	invokeinterface	InterfaceMethod scala/collection/SeqLike.toString:()Ljava/lang/String;
	invokespecial	Method scala/MatchError."<init>":(Ljava/lang/String;)V
	athrow
l12	aload	13
	instanceof	class scala/collection/immutable/$colon$colon
	ifeq	l14 // iconst_1
	aload	13
	checkcast	class scala/collection/immutable/$colon$colon
	astore	9
	aload	9
	getfield	Field scala/collection/immutable/$colon$colon.scala$collection$immutable$$colon$colon$$hd:Ljava/lang/Object;
	checkcast	class java/lang/reflect/Method
	astore	11
	getstatic	Field scala/collection/immutable/Nil$.MODULE$:Lscala/collection/immutable/Nil$;
	aload	9
	getfield	Field scala/collection/immutable/$colon$colon.tl:Lscala/collection/immutable/List;
	astore	10
	dup
	ifnonnull	l15 // aload
	pop
	aload	10
	ifnull	l16 // iconst_1
	goto	l17 // iconst_1
l15	aload	10
	invokevirtual	Method java/lang/Object.equals:(Ljava/lang/Object;)Z
	ifeq	l17 // iconst_1
l16	iconst_1
	ifeq	l18 // new
	aload_0
	aload	11
	aload_1
	aload_2
	aload	12
	invokestatic	Method testMethod$1:(Lscala/testing/Show;Ljava/lang/reflect/Method;Lscala/Symbol;Lscala/collection/Seq;Lscala/collection/Seq;)Ljava/lang/String;
	goto	l3 // areturn
l18	new	class scala/MatchError
	dup
	aload	13
	invokeinterface	InterfaceMethod scala/collection/SeqLike.toString:()Ljava/lang/String;
	invokespecial	Method scala/MatchError."<init>":(Ljava/lang/String;)V
	athrow
l17	iconst_1
	ifeq	l19 // new
	goto	l20 // new
l19	new	class scala/MatchError
	dup
	aload	13
	invokeinterface	InterfaceMethod scala/collection/SeqLike.toString:()Ljava/lang/String;
	invokespecial	Method scala/MatchError."<init>":(Ljava/lang/String;)V
	athrow
l14	iconst_1
	ifeq	l21 // new
l20	new	class scala/collection/mutable/StringBuilder
	dup
	invokespecial	Method scala/collection/mutable/StringBuilder."<init>":()V
	ldc	String cannot disambiguate between multiple implementations of 
	invokevirtual	Method scala/collection/mutable/StringBuilder.append:(Ljava/lang/Object;)Lscala/collection/mutable/StringBuilder;
	aload_1
	getfield	Field scala/Symbol.name:Ljava/lang/String;
	invokevirtual	Method scala/collection/mutable/StringBuilder.append:(Ljava/lang/Object;)Lscala/collection/mutable/StringBuilder;
	invokevirtual	Method scala/collection/mutable/StringBuilder.toString:()Ljava/lang/String;
l3	areturn
l21	new	class scala/MatchError
	dup
	aload	13
	invokeinterface	InterfaceMethod scala/collection/SeqLike.toString:()Ljava/lang/String;
	invokespecial	Method scala/MatchError."<init>":(Ljava/lang/String;)V
	athrow
l11	new	class scala/MatchError
	dup
	aload	14
	invokeinterface	InterfaceMethod scala/collection/SeqLike.toString:()Ljava/lang/String;
	invokespecial	Method scala/MatchError."<init>":(Ljava/lang/String;)V
	athrow
  Labels:
   	l2 = 113 // new
   	l1 = 128 // aload
   	l5 = 176 // aload
   	l6 = 184 // iconst_1
   	l8 = 201 // new
   	l7 = 216 // iconst_1
   	l9 = 227 // new
   	l4 = 242 // iconst_1
   	l10 = 250 // aload
   	l13 = 304 // new
   	l12 = 319 // aload
   	l15 = 367 // aload
   	l16 = 375 // iconst_1
   	l18 = 392 // new
   	l17 = 407 // iconst_1
   	l19 = 414 // new
   	l14 = 429 // iconst_1
   	l20 = 433 // new
   	l3 = 455 // areturn
   	l21 = 456 // new
   	l11 = 471 // new
  LocalVariableTable: 
   Start  Length  Slot  Name   Signature
   0      486      0    $this       Lscala/testing/Show;
   0      486      1    f$1       Lscala/Symbol;
   0      486      2    args$1       Lscala/collection/Seq;
   153      89      6    temp10       Ljava/lang/reflect/Method;
   250      205      6    temp10       Ljava/lang/reflect/Method;
   456      15      6    temp10       Ljava/lang/reflect/Method;
   143      99      7    temp9       Lscala/collection/immutable/$colon$colon;
   250      205      7    temp9       Lscala/collection/immutable/$colon$colon;
   456      15      7    temp9       Lscala/collection/immutable/$colon$colon;
   216      4      8    ms       Lscala/collection/immutable/List;
   224      3      8    ms       Lscala/collection/immutable/List;
   220      22      8    ms       Lscala/collection/immutable/List;
   250      205      8    ms       Lscala/collection/immutable/List;
   456      15      8    ms       Lscala/collection/immutable/List;
   334      95      9    temp3       Lscala/collection/immutable/$colon$colon;
   433      22      9    temp3       Lscala/collection/immutable/$colon$colon;
   344      85      11    temp4       Ljava/lang/reflect/Method;
   433      22      11    temp4       Ljava/lang/reflect/Method;
   31      455      12    args1$1       Lscala/collection/Seq;
   271      184      13    temp1       Lscala/collection/immutable/List;
   456      15      13    temp1       Lscala/collection/immutable/List;
   76      410      14    temp7       Lscala/collection/immutable/List;


public static scala.testing.Show$SymApply symApply(scala.testing.Show, scala.Symbol);
  Signature: (Lscala/testing/Show;Lscala/Symbol;)Lscala/testing/Show$SymApply;
  Code:
   Stack=4, Locals=2, Args_size=2
	new	class scala/testing/Show$SymApply
	dup
	aload_0
	aload_1
	invokespecial	Method scala/testing/Show$SymApply."<init>":(Lscala/testing/Show;Lscala/Symbol;)V
	areturn
  Labels:
  LocalVariableTable: 
   Start  Length  Slot  Name   Signature
   0      10      0    $this       Lscala/testing/Show;
   0      10      1    sym       Lscala/Symbol;


}

