Compiled from "Show.scala"
public final class scala.testing.Show$$anonfun$test$1 extends scala.runtime.AbstractFunction1 implements java.io.Serializable
  SourceFile: "Show.scala"
  Scala: length = 0x
   
  InnerClass: 
   public final $anonfun$test$1=class scala/testing/Show$$anonfun$test$1 of class scala/testing/Show
  minor version: 0
  major version: 49
  Constant pool:
Asciz	SourceFile;
Asciz	Show.scala;
Asciz	<clinit>;
Asciz	()V;
Asciz	Code;
Asciz	serialVersionUID;
Asciz	J;
Asciz	scala/testing/Show$$anonfun$test$1;
class	scala/testing/Show$$anonfun$test$1
NameAndType	serialVersionUID:J
Field	scala/testing/Show$$anonfun$test$1.serialVersionUID:J
Asciz	f$1;
Asciz	Lscala/Symbol;;
Asciz	<init>;
Asciz	(Lscala/testing/Show;Lscala/Symbol;)V;
Asciz	LineNumberTable;
NameAndType	f$1:Lscala/Symbol;
Field	scala/testing/Show$$anonfun$test$1.f$1:Lscala/Symbol;
Asciz	scala/runtime/AbstractFunction1;
class	scala/runtime/AbstractFunction1
NameAndType	"<init>":()V
Method	scala/runtime/AbstractFunction1."<init>":()V
Asciz	this;
Asciz	Lscala/testing/Show$$anonfun$test$1;;
Asciz	$outer;
Asciz	Lscala/testing/Show;;
Asciz	LocalVariableTable;
Asciz	apply;
Asciz	(Ljava/lang/Object;)Ljava/lang/Object;;
Asciz	java/lang/reflect/Method;
class	java/lang/reflect/Method
Asciz	(Ljava/lang/reflect/Method;)Z;
NameAndType	apply:(Ljava/lang/reflect/Method;)Z
Method	scala/testing/Show$$anonfun$test$1.apply:(Ljava/lang/reflect/Method;)Z
Asciz	scala/runtime/BoxesRunTime;
class	scala/runtime/BoxesRunTime
Asciz	boxToBoolean;
Asciz	(Z)Ljava/lang/Boolean;;
NameAndType	boxToBoolean:(Z)Ljava/lang/Boolean;
Method	scala/runtime/BoxesRunTime.boxToBoolean:(Z)Ljava/lang/Boolean;
Asciz	v1;
Asciz	Ljava/lang/Object;;
Asciz	getName;
Asciz	()Ljava/lang/String;;
NameAndType	getName:()Ljava/lang/String;
Method	java/lang/reflect/Method.getName:()Ljava/lang/String;
Asciz	scala/Symbol;
class	scala/Symbol
Asciz	name;
Asciz	Ljava/lang/String;;
NameAndType	name:Ljava/lang/String;
Field	scala/Symbol.name:Ljava/lang/String;
Asciz	java/lang/Object;
class	java/lang/Object
Asciz	equals;
Asciz	(Ljava/lang/Object;)Z;
NameAndType	equals:(Ljava/lang/Object;)Z
Method	java/lang/Object.equals:(Ljava/lang/Object;)Z
Asciz	Scala;
Asciz	InnerClasses;
Asciz	scala/testing/Show;
class	scala/testing/Show
Asciz	$anonfun$test$1;
Asciz	java/io/Serializable;
class	java/io/Serializable

{
public static final long serialVersionUID;
  Signature: J

private final scala.Symbol f$1;
  Signature: Lscala/Symbol;

public static {};
  Signature: ()V
  Code:
   Stack=2, Locals=0, Args_size=0
	lconst_0
	putstatic	Field serialVersionUID:J
	return
  Labels:

public scala.testing.Show$$anonfun$test$1(scala.testing.Show, scala.Symbol);
  Signature: (Lscala/testing/Show;Lscala/Symbol;)V
  Code:
   Stack=2, Locals=3, Args_size=3
	aload_0
	aload_2
	putfield	Field f$1:Lscala/Symbol;
	aload_0
	invokespecial	Method scala/runtime/AbstractFunction1."<init>":()V
	return
  Labels:
  LocalVariableTable: 
   Start  Length  Slot  Name   Signature
   0      10      0    this       Lscala/testing/Show$$anonfun$test$1;
   0      10      1    $outer       Lscala/testing/Show;


public final java.lang.Object apply(java.lang.Object);
  Signature: (Ljava/lang/Object;)Ljava/lang/Object;
  Code:
   Stack=2, Locals=3, Args_size=2
	aload_0
	aload_1
	checkcast	class java/lang/reflect/Method
	invokevirtual	Method apply:(Ljava/lang/reflect/Method;)Z
	istore_2
	iload_2
	invokestatic	Method scala/runtime/BoxesRunTime.boxToBoolean:(Z)Ljava/lang/Boolean;
	areturn
  Labels:
  LocalVariableTable: 
   Start  Length  Slot  Name   Signature
   0      14      0    this       Lscala/testing/Show$$anonfun$test$1;
   0      14      1    v1       Ljava/lang/Object;


public final boolean apply(java.lang.reflect.Method);
  Signature: (Ljava/lang/reflect/Method;)Z
  Code:
   Stack=2, Locals=4, Args_size=2
	aload_1
	invokevirtual	Method java/lang/reflect/Method.getName:()Ljava/lang/String;
	aload_0
	getfield	Field f$1:Lscala/Symbol;
	astore_2
	aload_2
	getfield	Field scala/Symbol.name:Ljava/lang/String;
	astore_3
	dup
	ifnonnull	l1 // aload_3
	pop
	aload_3
	ifnull	l2 // iconst_1
	goto	l3 // iconst_0
l1	aload_3
	invokevirtual	Method java/lang/Object.equals:(Ljava/lang/Object;)Z
	ifeq	l3 // iconst_0
l2	iconst_1
	goto	l4 // ireturn
l3	iconst_0
l4	ireturn
  Labels:
   	l1 = 26 // aload_3
   	l2 = 33 // iconst_1
   	l3 = 37 // iconst_0
   	l4 = 38 // ireturn
  LocalVariableTable: 
   Start  Length  Slot  Name   Signature
   0      39      0    this       Lscala/testing/Show$$anonfun$test$1;


}

