Compiled from "Show.scala"
public final class scala.testing.Show$$anonfun$test$2 extends scala.runtime.AbstractFunction1 implements java.io.Serializable
  SourceFile: "Show.scala"
  Scala: length = 0x
   
  InnerClass: 
   public final $anonfun$test$2=class scala/testing/Show$$anonfun$test$2 of class scala/testing/Show
  minor version: 0
  major version: 49
  Constant pool:
Asciz	SourceFile;
Asciz	Show.scala;
Asciz	<clinit>;
Asciz	()V;
Asciz	Code;
Asciz	serialVersionUID;
Asciz	J;
Asciz	scala/testing/Show$$anonfun$test$2;
class	scala/testing/Show$$anonfun$test$2
NameAndType	serialVersionUID:J
Field	scala/testing/Show$$anonfun$test$2.serialVersionUID:J
Asciz	args$1;
Asciz	Lscala/collection/Seq;;
Asciz	<init>;
Asciz	(Lscala/testing/Show;Lscala/collection/Seq;)V;
Asciz	LineNumberTable;
NameAndType	args$1:Lscala/collection/Seq;
Field	scala/testing/Show$$anonfun$test$2.args$1:Lscala/collection/Seq;
Asciz	scala/runtime/AbstractFunction1;
class	scala/runtime/AbstractFunction1
NameAndType	"<init>":()V
Method	scala/runtime/AbstractFunction1."<init>":()V
Asciz	this;
Asciz	Lscala/testing/Show$$anonfun$test$2;;
Asciz	$outer;
Asciz	Lscala/testing/Show;;
Asciz	LocalVariableTable;
Asciz	apply;
Asciz	(Ljava/lang/Object;)Ljava/lang/Object;;
Asciz	java/lang/reflect/Method;
class	java/lang/reflect/Method
Asciz	(Ljava/lang/reflect/Method;)Z;
NameAndType	apply:(Ljava/lang/reflect/Method;)Z
Method	scala/testing/Show$$anonfun$test$2.apply:(Ljava/lang/reflect/Method;)Z
Asciz	scala/runtime/BoxesRunTime;
class	scala/runtime/BoxesRunTime
Asciz	boxToBoolean;
Asciz	(Z)Ljava/lang/Boolean;;
NameAndType	boxToBoolean:(Z)Ljava/lang/Boolean;
Method	scala/runtime/BoxesRunTime.boxToBoolean:(Z)Ljava/lang/Boolean;
Asciz	v1;
Asciz	Ljava/lang/Object;;
Asciz	getParameterTypes;
Asciz	()[Ljava/lang/Class;;
NameAndType	getParameterTypes:()[Ljava/lang/Class;
Method	java/lang/reflect/Method.getParameterTypes:()[Ljava/lang/Class;
Asciz	scala/collection/SeqLike;
class	scala/collection/SeqLike
Asciz	length;
Asciz	()I;
NameAndType	length:()I
InterfaceMethod	scala/collection/SeqLike.length:()I
Asciz	Scala;
Asciz	InnerClasses;
Asciz	scala/testing/Show;
class	scala/testing/Show
Asciz	$anonfun$test$2;
Asciz	java/io/Serializable;
class	java/io/Serializable

{
public static final long serialVersionUID;
  Signature: J

public final scala.collection.Seq args$1;
  Signature: Lscala/collection/Seq;

public static {};
  Signature: ()V
  Code:
   Stack=2, Locals=0, Args_size=0
	lconst_0
	putstatic	Field serialVersionUID:J
	return
  Labels:

public scala.testing.Show$$anonfun$test$2(scala.testing.Show, scala.collection.Seq);
  Signature: (Lscala/testing/Show;Lscala/collection/Seq;)V
  Code:
   Stack=2, Locals=3, Args_size=3
	aload_0
	aload_2
	putfield	Field args$1:Lscala/collection/Seq;
	aload_0
	invokespecial	Method scala/runtime/AbstractFunction1."<init>":()V
	return
  Labels:
  LocalVariableTable: 
   Start  Length  Slot  Name   Signature
   0      10      0    this       Lscala/testing/Show$$anonfun$test$2;
   0      10      1    $outer       Lscala/testing/Show;


public final java.lang.Object apply(java.lang.Object);
  Signature: (Ljava/lang/Object;)Ljava/lang/Object;
  Code:
   Stack=2, Locals=3, Args_size=2
	aload_0
	aload_1
	checkcast	class java/lang/reflect/Method
	invokevirtual	Method apply:(Ljava/lang/reflect/Method;)Z
	istore_2
	iload_2
	invokestatic	Method scala/runtime/BoxesRunTime.boxToBoolean:(Z)Ljava/lang/Boolean;
	areturn
  Labels:
  LocalVariableTable: 
   Start  Length  Slot  Name   Signature
   0      14      0    this       Lscala/testing/Show$$anonfun$test$2;
   0      14      1    v1       Ljava/lang/Object;


public final boolean apply(java.lang.reflect.Method);
  Signature: (Ljava/lang/reflect/Method;)Z
  Code:
   Stack=2, Locals=2, Args_size=2
	aload_1
	invokevirtual	Method java/lang/reflect/Method.getParameterTypes:()[Ljava/lang/Class;
	arraylength
	aload_0
	getfield	Field args$1:Lscala/collection/Seq;
	invokeinterface	InterfaceMethod scala/collection/SeqLike.length:()I
	if_icmpne	l1 // iconst_0
	iconst_1
	goto	l2 // ireturn
l1	iconst_0
l2	ireturn
  Labels:
   	l1 = 21 // iconst_0
   	l2 = 22 // ireturn

}

