Compiled from "SUnit.scala"
public class scala.testing.SUnit$TestSuite extends java.lang.Object implements scala.testing.SUnit$Test,scala.ScalaObject
  SourceFile: "SUnit.scala"
  Scala: length = 0x
   
  InnerClass: 
   public abstract #100= #97 of #99; //Test=class scala/testing/SUnit$Test of class scala/testing/SUnit
   public #101= #20 of #99; //TestSuite=class scala/testing/SUnit$TestSuite of class scala/testing/SUnit
   public #104= #103 of #99; //TestResult=class scala/testing/SUnit$TestResult of class scala/testing/SUnit
   public final #105= #39 of #20; //$anonfun$run$1=class scala/testing/SUnit$TestSuite$$anonfun$run$1 of class scala/testing/SUnit$TestSuite
  minor version: 0
  major version: 49
  Constant pool:
const #1 = Asciz	SourceFile;
const #2 = Asciz	SUnit.scala;
const #3 = Asciz	buf;
const #4 = Asciz	Lscala/collection/mutable/ArrayBuffer;;
const #5 = Asciz	Lscala/collection/mutable/ArrayBuffer<Lscala/testing/SUnit$Test;>;;
const #6 = Asciz	Signature;
const #7 = Asciz	<init>;
const #8 = Asciz	(Lscala/collection/Sequence;)V;
const #9 = Asciz	Code;
const #10 = Asciz	LineNumberTable;
const #11 = Asciz	java/lang/Object;
const #12 = class	#11;	//  java/lang/Object
const #13 = Asciz	()V;
const #14 = NameAndType	#7:#13;//  "<init>":()V
const #15 = Method	#12.#14;	//  java/lang/Object."<init>":()V
const #16 = Asciz	scala/collection/mutable/ArrayBuffer;
const #17 = class	#16;	//  scala/collection/mutable/ArrayBuffer
const #18 = Method	#17.#14;	//  scala/collection/mutable/ArrayBuffer."<init>":()V
const #19 = Asciz	scala/testing/SUnit$TestSuite;
const #20 = class	#19;	//  scala/testing/SUnit$TestSuite
const #21 = NameAndType	#3:#4;//  buf:Lscala/collection/mutable/ArrayBuffer;
const #22 = Field	#20.#21;	//  scala/testing/SUnit$TestSuite.buf:Lscala/collection/mutable/ArrayBuffer;
const #23 = Asciz	()Lscala/collection/mutable/ArrayBuffer;;
const #24 = NameAndType	#3:#23;//  buf:()Lscala/collection/mutable/ArrayBuffer;
const #25 = Method	#20.#24;	//  scala/testing/SUnit$TestSuite.buf:()Lscala/collection/mutable/ArrayBuffer;
const #26 = Asciz	$plus$plus$eq;
const #27 = Asciz	(Lscala/collection/Traversable;)Lscala/collection/mutable/ArrayBuffer;;
const #28 = NameAndType	#26:#27;//  $plus$plus$eq:(Lscala/collection/Traversable;)Lscala/collection/mutable/ArrayBuffer;
const #29 = Method	#17.#28;	//  scala/collection/mutable/ArrayBuffer.$plus$plus$eq:(Lscala/collection/Traversable;)Lscala/collection/mutable/ArrayBuffer;
const #30 = Asciz	this;
const #31 = Asciz	Lscala/testing/SUnit$TestSuite;;
const #32 = Asciz	tests;
const #33 = Asciz	Lscala/collection/Sequence;;
const #34 = Asciz	LocalVariableTable;
const #35 = Asciz	(Lscala/collection/Sequence<Lscala/testing/SUnit$Test;>;)V;
const #36 = Asciz	run;
const #37 = Asciz	(Lscala/testing/SUnit$TestResult;)V;
const #38 = Asciz	scala/testing/SUnit$TestSuite$$anonfun$run$1;
const #39 = class	#38;	//  scala/testing/SUnit$TestSuite$$anonfun$run$1
const #40 = Asciz	(Lscala/testing/SUnit$TestSuite;Lscala/testing/SUnit$TestResult;)V;
const #41 = NameAndType	#7:#40;//  "<init>":(Lscala/testing/SUnit$TestSuite;Lscala/testing/SUnit$TestResult;)V
const #42 = Method	#39.#41;	//  scala/testing/SUnit$TestSuite$$anonfun$run$1."<init>":(Lscala/testing/SUnit$TestSuite;Lscala/testing/SUnit$TestResult;)V
const #43 = Asciz	scala/collection/mutable/ResizableArray;
const #44 = class	#43;	//  scala/collection/mutable/ResizableArray
const #45 = Asciz	foreach;
const #46 = Asciz	(Lscala/Function1;)V;
const #47 = NameAndType	#45:#46;//  foreach:(Lscala/Function1;)V
const #48 = InterfaceMethod	#44.#47;	//  scala/collection/mutable/ResizableArray.foreach:(Lscala/Function1;)V
const #49 = Asciz	r$1;
const #50 = Asciz	Lscala/testing/SUnit$TestResult;;
const #51 = Asciz	addTest;
const #52 = Asciz	(Lscala/testing/SUnit$Test;)V;
const #53 = Asciz	$plus$eq;
const #54 = Asciz	(Ljava/lang/Object;)Lscala/collection/mutable/ArrayBuffer;;
const #55 = NameAndType	#53:#54;//  $plus$eq:(Ljava/lang/Object;)Lscala/collection/mutable/ArrayBuffer;
const #56 = Method	#17.#55;	//  scala/collection/mutable/ArrayBuffer.$plus$eq:(Ljava/lang/Object;)Lscala/collection/mutable/ArrayBuffer;
const #57 = Asciz	t;
const #58 = Asciz	Lscala/testing/SUnit$Test;;
const #59 = Asciz	()Lscala/collection/mutable/ArrayBuffer<Lscala/testing/SUnit$Test;>;;
const #60 = Asciz	(Lscala/collection/Sequence;Lscala/Function1;)V;
const #61 = Asciz	scala/collection/Sequence$;
const #62 = class	#61;	//  scala/collection/Sequence$
const #63 = Asciz	MODULE$;
const #64 = Asciz	Lscala/collection/Sequence$;;
const #65 = NameAndType	#63:#64;//  MODULE$:Lscala/collection/Sequence$;
const #66 = Field	#62.#65;	//  scala/collection/Sequence$.MODULE$:Lscala/collection/Sequence$;
const #67 = Asciz	builderFactory;
const #68 = Asciz	()Lscala/collection/generic/BuilderFactory;;
const #69 = NameAndType	#67:#68;//  builderFactory:()Lscala/collection/generic/BuilderFactory;
const #70 = Method	#62.#69;	//  scala/collection/Sequence$.builderFactory:()Lscala/collection/generic/BuilderFactory;
const #71 = Asciz	scala/collection/generic/TraversableTemplate;
const #72 = class	#71;	//  scala/collection/generic/TraversableTemplate
const #73 = Asciz	map;
const #74 = Asciz	(Lscala/Function1;Lscala/collection/generic/BuilderFactory;)Ljava/lang/Object;;
const #75 = NameAndType	#73:#74;//  map:(Lscala/Function1;Lscala/collection/generic/BuilderFactory;)Ljava/lang/Object;
const #76 = InterfaceMethod	#72.#75;	//  scala/collection/generic/TraversableTemplate.map:(Lscala/Function1;Lscala/collection/generic/BuilderFactory;)Ljava/lang/Object;
const #77 = Asciz	scala/collection/Sequence;
const #78 = class	#77;	//  scala/collection/Sequence
const #79 = Asciz	scala/runtime/ScalaRunTime$;
const #80 = class	#79;	//  scala/runtime/ScalaRunTime$
const #81 = Asciz	Lscala/runtime/ScalaRunTime$;;
const #82 = NameAndType	#63:#81;//  MODULE$:Lscala/runtime/ScalaRunTime$;
const #83 = Field	#80.#82;	//  scala/runtime/ScalaRunTime$.MODULE$:Lscala/runtime/ScalaRunTime$;
const #84 = Asciz	boxArray;
const #85 = Asciz	(Ljava/lang/Object;)Lscala/runtime/BoxedArray;;
const #86 = NameAndType	#84:#85;//  boxArray:(Ljava/lang/Object;)Lscala/runtime/BoxedArray;
const #87 = Method	#80.#86;	//  scala/runtime/ScalaRunTime$.boxArray:(Ljava/lang/Object;)Lscala/runtime/BoxedArray;
const #88 = NameAndType	#7:#8;//  "<init>":(Lscala/collection/Sequence;)V
const #89 = Method	#20.#88;	//  scala/testing/SUnit$TestSuite."<init>":(Lscala/collection/Sequence;)V
const #90 = Asciz	names;
const #91 = Asciz	constr;
const #92 = Asciz	Lscala/Function1;;
const #93 = Asciz	(Lscala/collection/Sequence<Ljava/lang/String;>;Lscala/Function1<Ljava/lang/String;Lscala/testing/SUnit$Test;>;)V;
const #94 = Asciz	Scala;
const #95 = Asciz	InnerClasses;
const #96 = Asciz	scala/testing/SUnit$Test;
const #97 = class	#96;	//  scala/testing/SUnit$Test
const #98 = Asciz	scala/testing/SUnit;
const #99 = class	#98;	//  scala/testing/SUnit
const #100 = Asciz	Test;
const #101 = Asciz	TestSuite;
const #102 = Asciz	scala/testing/SUnit$TestResult;
const #103 = class	#102;	//  scala/testing/SUnit$TestResult
const #104 = Asciz	TestResult;
const #105 = Asciz	$anonfun$run$1;
const #106 = Asciz	scala/ScalaObject;
const #107 = class	#106;	//  scala/ScalaObject

{
public scala.testing.SUnit$TestSuite(scala.collection.Sequence);
  Code:
   Stack=3, Locals=2, Args_size=2
   0:	aload_0
   1:	invokespecial	#15; //Method java/lang/Object."<init>":()V
   4:	aload_0
   5:	new	#17; //class scala/collection/mutable/ArrayBuffer
   8:	dup
   9:	invokespecial	#18; //Method scala/collection/mutable/ArrayBuffer."<init>":()V
   12:	putfield	#22; //Field buf:Lscala/collection/mutable/ArrayBuffer;
   15:	aload_0
   16:	invokevirtual	#25; //Method buf:()Lscala/collection/mutable/ArrayBuffer;
   19:	aload_1
   20:	invokevirtual	#29; //Method scala/collection/mutable/ArrayBuffer.$plus$plus$eq:(Lscala/collection/Traversable;)Lscala/collection/mutable/ArrayBuffer;
   23:	pop
   24:	return
  LineNumberTable: 
   line 133: 0
   line 138: 4
   line 140: 15

  LocalVariableTable: 
   Start  Length  Slot  Name   Signature
   0      25      0    this       Lscala/testing/SUnit$TestSuite;
   0      25      1    tests       Lscala/collection/Sequence;

  Signature: length = 0x2
   00 23 

public void run(scala.testing.SUnit$TestResult);
  Code:
   Stack=5, Locals=2, Args_size=2
   0:	aload_0
   1:	invokevirtual	#25; //Method buf:()Lscala/collection/mutable/ArrayBuffer;
   4:	new	#39; //class scala/testing/SUnit$TestSuite$$anonfun$run$1
   7:	dup
   8:	aload_0
   9:	aload_1
   10:	invokespecial	#42; //Method scala/testing/SUnit$TestSuite$$anonfun$run$1."<init>":(Lscala/testing/SUnit$TestSuite;Lscala/testing/SUnit$TestResult;)V
   13:	invokeinterface	#48,  2; //InterfaceMethod scala/collection/mutable/ResizableArray.foreach:(Lscala/Function1;)V
   18:	return
  LineNumberTable: 
   line 147: 0

  LocalVariableTable: 
   Start  Length  Slot  Name   Signature
   0      19      0    this       Lscala/testing/SUnit$TestSuite;
   0      19      1    r$1       Lscala/testing/SUnit$TestResult;


public void addTest(scala.testing.SUnit$Test);
  Code:
   Stack=2, Locals=2, Args_size=2
   0:	aload_0
   1:	invokevirtual	#25; //Method buf:()Lscala/collection/mutable/ArrayBuffer;
   4:	aload_1
   5:	invokevirtual	#56; //Method scala/collection/mutable/ArrayBuffer.$plus$eq:(Ljava/lang/Object;)Lscala/collection/mutable/ArrayBuffer;
   8:	pop
   9:	return
  LineNumberTable: 
   line 143: 0

  LocalVariableTable: 
   Start  Length  Slot  Name   Signature
   0      10      0    this       Lscala/testing/SUnit$TestSuite;
   0      10      1    t       Lscala/testing/SUnit$Test;


public scala.collection.mutable.ArrayBuffer buf();
  Code:
   Stack=1, Locals=1, Args_size=1
   0:	aload_0
   1:	getfield	#22; //Field buf:Lscala/collection/mutable/ArrayBuffer;
   4:	areturn
  LineNumberTable: 
   line 138: 0

  Signature: length = 0x2
   00 3B 

public scala.testing.SUnit$TestSuite(scala.collection.Sequence, scala.Function1);
  Code:
   Stack=4, Locals=4, Args_size=3
   0:	aload_0
   1:	aload_1
   2:	aload_2
   3:	getstatic	#66; //Field scala/collection/Sequence$.MODULE$:Lscala/collection/Sequence$;
   6:	invokevirtual	#70; //Method scala/collection/Sequence$.builderFactory:()Lscala/collection/generic/BuilderFactory;
   9:	invokeinterface	#76,  3; //InterfaceMethod scala/collection/generic/TraversableTemplate.map:(Lscala/Function1;Lscala/collection/generic/BuilderFactory;)Ljava/lang/Object;
   14:	astore_3
   15:	aload_3
   16:	instanceof	#78; //class scala/collection/Sequence
   19:	ifeq	26
   22:	aload_3
   23:	goto	33
   26:	getstatic	#83; //Field scala/runtime/ScalaRunTime$.MODULE$:Lscala/runtime/ScalaRunTime$;
   29:	aload_3
   30:	invokevirtual	#87; //Method scala/runtime/ScalaRunTime$.boxArray:(Ljava/lang/Object;)Lscala/runtime/BoxedArray;
   33:	checkcast	#78; //class scala/collection/Sequence
   36:	invokespecial	#89; //Method "<init>":(Lscala/collection/Sequence;)V
   39:	return
  LineNumberTable: 
   line 136: 0

  LocalVariableTable: 
   Start  Length  Slot  Name   Signature
   0      40      0    this       Lscala/testing/SUnit$TestSuite;
   0      40      1    names       Lscala/collection/Sequence;
   0      40      2    constr       Lscala/Function1;

  Signature: length = 0x2
   00 5D 

}

