Compiled from "SUnit.scala"
public final class scala.testing.SUnit$ extends java.lang.Object implements scala.ScalaObject
  SourceFile: "SUnit.scala"
  Scala: length = 0x
   
  Deprecated: length = 0x
   
  InnerClass: 
   public abstract #26= #23 of #25; //Test=class scala/testing/SUnit$Test of class scala/testing/SUnit
   public abstract #29= #28 of #25; //Assert=class scala/testing/SUnit$Assert of class scala/testing/SUnit
   public abstract #32= #31 of #25; //TestCase=class scala/testing/SUnit$TestCase of class scala/testing/SUnit
   public #35= #34 of #25; //TestSuite=class scala/testing/SUnit$TestSuite of class scala/testing/SUnit
   public #38= #37 of #25; //TestResult=class scala/testing/SUnit$TestResult of class scala/testing/SUnit
   public #41= #40 of #25; //TestFailure=class scala/testing/SUnit$TestFailure of class scala/testing/SUnit
   public abstract #44= #43 of #25; //Assert$class=class scala/testing/SUnit$Assert$class of class scala/testing/SUnit
   public #47= #46 of #25; //AssertFailed=class scala/testing/SUnit$AssertFailed of class scala/testing/SUnit
   public abstract #50= #49 of #25; //TestConsoleMain=class scala/testing/SUnit$TestConsoleMain of class scala/testing/SUnit
   public abstract #53= #52 of #25; //TestConsoleMain$class=class scala/testing/SUnit$TestConsoleMain$class of class scala/testing/SUnit
  minor version: 0
  major version: 49
  Constant pool:
const #1 = Asciz	SourceFile;
const #2 = Asciz	SUnit.scala;
const #3 = Asciz	Scala;
const #4 = Asciz	MODULE$;
const #5 = Asciz	Lscala/testing/SUnit$;;
const #6 = Asciz	<clinit>;
const #7 = Asciz	()V;
const #8 = Asciz	Code;
const #9 = Asciz	scala/testing/SUnit$;
const #10 = class	#9;	//  scala/testing/SUnit$
const #11 = Asciz	<init>;
const #12 = NameAndType	#11:#7;//  "<init>":()V
const #13 = Method	#10.#12;	//  scala/testing/SUnit$."<init>":()V
const #14 = Asciz	LineNumberTable;
const #15 = Asciz	java/lang/Object;
const #16 = class	#15;	//  java/lang/Object
const #17 = Method	#16.#12;	//  java/lang/Object."<init>":()V
const #18 = NameAndType	#4:#5;//  MODULE$:Lscala/testing/SUnit$;
const #19 = Field	#10.#18;	//  scala/testing/SUnit$.MODULE$:Lscala/testing/SUnit$;
const #20 = Asciz	Deprecated;
const #21 = Asciz	InnerClasses;
const #22 = Asciz	scala/testing/SUnit$Test;
const #23 = class	#22;	//  scala/testing/SUnit$Test
const #24 = Asciz	scala/testing/SUnit;
const #25 = class	#24;	//  scala/testing/SUnit
const #26 = Asciz	Test;
const #27 = Asciz	scala/testing/SUnit$Assert;
const #28 = class	#27;	//  scala/testing/SUnit$Assert
const #29 = Asciz	Assert;
const #30 = Asciz	scala/testing/SUnit$TestCase;
const #31 = class	#30;	//  scala/testing/SUnit$TestCase
const #32 = Asciz	TestCase;
const #33 = Asciz	scala/testing/SUnit$TestSuite;
const #34 = class	#33;	//  scala/testing/SUnit$TestSuite
const #35 = Asciz	TestSuite;
const #36 = Asciz	scala/testing/SUnit$TestResult;
const #37 = class	#36;	//  scala/testing/SUnit$TestResult
const #38 = Asciz	TestResult;
const #39 = Asciz	scala/testing/SUnit$TestFailure;
const #40 = class	#39;	//  scala/testing/SUnit$TestFailure
const #41 = Asciz	TestFailure;
const #42 = Asciz	scala/testing/SUnit$Assert$class;
const #43 = class	#42;	//  scala/testing/SUnit$Assert$class
const #44 = Asciz	Assert$class;
const #45 = Asciz	scala/testing/SUnit$AssertFailed;
const #46 = class	#45;	//  scala/testing/SUnit$AssertFailed
const #47 = Asciz	AssertFailed;
const #48 = Asciz	scala/testing/SUnit$TestConsoleMain;
const #49 = class	#48;	//  scala/testing/SUnit$TestConsoleMain
const #50 = Asciz	TestConsoleMain;
const #51 = Asciz	scala/testing/SUnit$TestConsoleMain$class;
const #52 = class	#51;	//  scala/testing/SUnit$TestConsoleMain$class
const #53 = Asciz	TestConsoleMain$class;
const #54 = Asciz	scala/ScalaObject;
const #55 = class	#54;	//  scala/ScalaObject

{
public static final scala.testing.SUnit$ MODULE$;

public static {};
  Code:
   Stack=1, Locals=0, Args_size=0
   0:	new	#10; //class scala/testing/SUnit$
   3:	invokespecial	#13; //Method "<init>":()V
   6:	return

}

