Compiled from "SUnit.scala"
public final class scala.testing.SUnit$TestConsoleMain$$anonfun$main$1 extends java.lang.Object implements scala.Function1,scala.ScalaObject,java.io.Serializable
  SourceFile: "SUnit.scala"
  Scala: length = 0x
   
  InnerClass: 
   public TestFailure=class scala/testing/SUnit$TestFailure of class scala/testing/SUnit
   public abstract TestConsoleMain=class scala/testing/SUnit$TestConsoleMain of class scala/testing/SUnit
   public final $anonfun$main$1=class scala/testing/SUnit$TestConsoleMain$$anonfun$main$1 of class scala/testing/SUnit$TestConsoleMain
  minor version: 0
  major version: 49
  Constant pool:
Asciz	SourceFile;
Asciz	SUnit.scala;
Asciz	<clinit>;
Asciz	()V;
Asciz	Code;
Asciz	serialVersionUID;
Asciz	J;
Asciz	scala/testing/SUnit$TestConsoleMain$$anonfun$main$1;
class	scala/testing/SUnit$TestConsoleMain$$anonfun$main$1
NameAndType	serialVersionUID:J
Field	scala/testing/SUnit$TestConsoleMain$$anonfun$main$1.serialVersionUID:J
Asciz	<init>;
Asciz	(Lscala/testing/SUnit$TestConsoleMain;)V;
Asciz	LineNumberTable;
Asciz	java/lang/Object;
class	java/lang/Object
NameAndType	"<init>":()V
Method	java/lang/Object."<init>":()V
Asciz	scala/Function1$class;
class	scala/Function1$class
Asciz	$init$;
Asciz	(Lscala/Function1;)V;
NameAndType	$init$:(Lscala/Function1;)V
Method	scala/Function1$class.$init$:(Lscala/Function1;)V
Asciz	this;
Asciz	Lscala/testing/SUnit$TestConsoleMain$$anonfun$main$1;;
Asciz	$outer;
Asciz	Lscala/testing/SUnit$TestConsoleMain;;
Asciz	LocalVariableTable;
Asciz	apply;
Asciz	(Ljava/lang/Object;)Ljava/lang/Object;;
Asciz	scala/testing/SUnit$TestFailure;
class	scala/testing/SUnit$TestFailure
Asciz	(Lscala/testing/SUnit$TestFailure;)V;
NameAndType	apply:(Lscala/testing/SUnit$TestFailure;)V
Method	scala/testing/SUnit$TestConsoleMain$$anonfun$main$1.apply:(Lscala/testing/SUnit$TestFailure;)V
Asciz	scala/runtime/BoxedUnit;
class	scala/runtime/BoxedUnit
Asciz	UNIT;
Asciz	Lscala/runtime/BoxedUnit;;
NameAndType	UNIT:Lscala/runtime/BoxedUnit;
Field	scala/runtime/BoxedUnit.UNIT:Lscala/runtime/BoxedUnit;
Asciz	v1;
Asciz	Ljava/lang/Object;;
Asciz	scala/Predef$;
class	scala/Predef$
Asciz	MODULE$;
Asciz	Lscala/Predef$;;
NameAndType	MODULE$:Lscala/Predef$;
Field	scala/Predef$.MODULE$:Lscala/Predef$;
Asciz	toString;
Asciz	()Ljava/lang/String;;
NameAndType	toString:()Ljava/lang/String;
Method	scala/testing/SUnit$TestFailure.toString:()Ljava/lang/String;
Asciz	println;
Asciz	(Ljava/lang/Object;)V;
NameAndType	println:(Ljava/lang/Object;)V
Method	scala/Predef$.println:(Ljava/lang/Object;)V
Asciz	tf;
Asciz	Lscala/testing/SUnit$TestFailure;;
Asciz	andThen;
Asciz	(Lscala/Function1;)Lscala/Function1;;
Asciz	(Lscala/Function1;Lscala/Function1;)Lscala/Function1;;
NameAndType	andThen:(Lscala/Function1;Lscala/Function1;)Lscala/Function1;
Method	scala/Function1$class.andThen:(Lscala/Function1;Lscala/Function1;)Lscala/Function1;
Asciz	g;
Asciz	Lscala/Function1;;
Asciz	compose;
NameAndType	compose:(Lscala/Function1;Lscala/Function1;)Lscala/Function1;
Method	scala/Function1$class.compose:(Lscala/Function1;Lscala/Function1;)Lscala/Function1;
Asciz	(Lscala/Function1;)Ljava/lang/String;;
NameAndType	toString:(Lscala/Function1;)Ljava/lang/String;
Method	scala/Function1$class.toString:(Lscala/Function1;)Ljava/lang/String;
Asciz	Scala;
Asciz	InnerClasses;
Asciz	scala/testing/SUnit;
class	scala/testing/SUnit
Asciz	TestFailure;
Asciz	scala/testing/SUnit$TestConsoleMain;
class	scala/testing/SUnit$TestConsoleMain
Asciz	TestConsoleMain;
Asciz	$anonfun$main$1;
Asciz	scala/Function1;
class	scala/Function1
Asciz	scala/ScalaObject;
class	scala/ScalaObject
Asciz	java/io/Serializable;
class	java/io/Serializable

{
public static final long serialVersionUID;
  Signature: J

public static {};
  Signature: ()V
  Code:
   Stack=2, Locals=0, Args_size=0
	lconst_0
	putstatic	Field serialVersionUID:J
	return
  Labels:

public scala.testing.SUnit$TestConsoleMain$$anonfun$main$1(scala.testing.SUnit$TestConsoleMain);
  Signature: (Lscala/testing/SUnit$TestConsoleMain;)V
  Code:
   Stack=1, Locals=2, Args_size=2
	aload_0
	invokespecial	Method java/lang/Object."<init>":()V
	aload_0
	invokestatic	Method scala/Function1$class.$init$:(Lscala/Function1;)V
	return
  Labels:
  LocalVariableTable: 
   Start  Length  Slot  Name   Signature
   0      9      0    this       Lscala/testing/SUnit$TestConsoleMain$$anonfun$main$1;
   0      9      1    $outer       Lscala/testing/SUnit$TestConsoleMain;


public final java.lang.Object apply(java.lang.Object);
  Signature: (Ljava/lang/Object;)Ljava/lang/Object;
  Code:
   Stack=2, Locals=2, Args_size=2
	aload_0
	aload_1
	checkcast	class scala/testing/SUnit$TestFailure
	invokevirtual	Method apply:(Lscala/testing/SUnit$TestFailure;)V
	getstatic	Field scala/runtime/BoxedUnit.UNIT:Lscala/runtime/BoxedUnit;
	areturn
  Labels:
  LocalVariableTable: 
   Start  Length  Slot  Name   Signature
   0      12      0    this       Lscala/testing/SUnit$TestConsoleMain$$anonfun$main$1;
   0      12      1    v1       Ljava/lang/Object;


public final void apply(scala.testing.SUnit$TestFailure);
  Signature: (Lscala/testing/SUnit$TestFailure;)V
  Code:
   Stack=2, Locals=2, Args_size=2
	getstatic	Field scala/Predef$.MODULE$:Lscala/Predef$;
	aload_1
	invokevirtual	Method scala/testing/SUnit$TestFailure.toString:()Ljava/lang/String;
	invokevirtual	Method scala/Predef$.println:(Ljava/lang/Object;)V
	return
  Labels:
  LocalVariableTable: 
   Start  Length  Slot  Name   Signature
   0      11      0    this       Lscala/testing/SUnit$TestConsoleMain$$anonfun$main$1;
   0      11      1    tf       Lscala/testing/SUnit$TestFailure;


public scala.Function1 andThen(scala.Function1);
  Signature: (Lscala/Function1;)Lscala/Function1;
  Code:
   Stack=2, Locals=2, Args_size=2
	aload_0
	aload_1
	invokestatic	Method scala/Function1$class.andThen:(Lscala/Function1;Lscala/Function1;)Lscala/Function1;
	areturn
  Labels:
  LocalVariableTable: 
   Start  Length  Slot  Name   Signature
   0      6      0    this       Lscala/testing/SUnit$TestConsoleMain$$anonfun$main$1;
   0      6      1    g       Lscala/Function1;


public scala.Function1 compose(scala.Function1);
  Signature: (Lscala/Function1;)Lscala/Function1;
  Code:
   Stack=2, Locals=2, Args_size=2
	aload_0
	aload_1
	invokestatic	Method scala/Function1$class.compose:(Lscala/Function1;Lscala/Function1;)Lscala/Function1;
	areturn
  Labels:
  LocalVariableTable: 
   Start  Length  Slot  Name   Signature
   0      6      0    this       Lscala/testing/SUnit$TestConsoleMain$$anonfun$main$1;
   0      6      1    g       Lscala/Function1;


public java.lang.String toString();
  Signature: ()Ljava/lang/String;
  Code:
   Stack=1, Locals=1, Args_size=1
	aload_0
	invokestatic	Method scala/Function1$class.toString:(Lscala/Function1;)Ljava/lang/String;
	areturn
  Labels:

}

