Compiled from "SUnit.scala"
public final class scala.testing.SUnit$TestResult$$anonfun$failures$1 extends java.lang.Object implements scala.Function1,scala.ScalaObject,java.io.Serializable
  SourceFile: "SUnit.scala"
  Scala: length = 0x
   
  InnerClass: 
   public TestResult=class scala/testing/SUnit$TestResult of class scala/testing/SUnit
   public TestFailure=class scala/testing/SUnit$TestFailure of class scala/testing/SUnit
   public final $anonfun$failures$1=class scala/testing/SUnit$TestResult$$anonfun$failures$1 of class scala/testing/SUnit$TestResult
  minor version: 0
  major version: 49
  Constant pool:
Asciz	SourceFile;
Asciz	SUnit.scala;
Asciz	<clinit>;
Asciz	()V;
Asciz	Code;
Asciz	serialVersionUID;
Asciz	J;
Asciz	scala/testing/SUnit$TestResult$$anonfun$failures$1;
class	scala/testing/SUnit$TestResult$$anonfun$failures$1
NameAndType	serialVersionUID:J
Field	scala/testing/SUnit$TestResult$$anonfun$failures$1.serialVersionUID:J
Asciz	<init>;
Asciz	(Lscala/testing/SUnit$TestResult;)V;
Asciz	LineNumberTable;
Asciz	java/lang/Object;
class	java/lang/Object
NameAndType	"<init>":()V
Method	java/lang/Object."<init>":()V
Asciz	scala/Function1$class;
class	scala/Function1$class
Asciz	$init$;
Asciz	(Lscala/Function1;)V;
NameAndType	$init$:(Lscala/Function1;)V
Method	scala/Function1$class.$init$:(Lscala/Function1;)V
Asciz	this;
Asciz	Lscala/testing/SUnit$TestResult$$anonfun$failures$1;;
Asciz	$outer;
Asciz	Lscala/testing/SUnit$TestResult;;
Asciz	LocalVariableTable;
Asciz	apply;
Asciz	(Ljava/lang/Object;)Ljava/lang/Object;;
Asciz	scala/Tuple2;
class	scala/Tuple2
Asciz	(Lscala/Tuple2;)Lscala/testing/SUnit$TestFailure;;
NameAndType	apply:(Lscala/Tuple2;)Lscala/testing/SUnit$TestFailure;
Method	scala/testing/SUnit$TestResult$$anonfun$failures$1.apply:(Lscala/Tuple2;)Lscala/testing/SUnit$TestFailure;
Asciz	v1;
Asciz	Ljava/lang/Object;;
Asciz	scala/testing/SUnit$TestFailure;
class	scala/testing/SUnit$TestFailure
Asciz	(Lscala/Tuple2;)V;
NameAndType	"<init>":(Lscala/Tuple2;)V
Method	scala/testing/SUnit$TestFailure."<init>":(Lscala/Tuple2;)V
Asciz	x;
Asciz	Lscala/Tuple2;;
Asciz	(Lscala/Tuple2<Lscala/testing/SUnit$Test;Ljava/lang/Throwable;>;)Lscala/testing/SUnit$TestFailure;;
Asciz	Signature;
Asciz	andThen;
Asciz	(Lscala/Function1;)Lscala/Function1;;
Asciz	(Lscala/Function1;Lscala/Function1;)Lscala/Function1;;
NameAndType	andThen:(Lscala/Function1;Lscala/Function1;)Lscala/Function1;
Method	scala/Function1$class.andThen:(Lscala/Function1;Lscala/Function1;)Lscala/Function1;
Asciz	g;
Asciz	Lscala/Function1;;
Asciz	compose;
NameAndType	compose:(Lscala/Function1;Lscala/Function1;)Lscala/Function1;
Method	scala/Function1$class.compose:(Lscala/Function1;Lscala/Function1;)Lscala/Function1;
Asciz	toString;
Asciz	()Ljava/lang/String;;
Asciz	(Lscala/Function1;)Ljava/lang/String;;
NameAndType	toString:(Lscala/Function1;)Ljava/lang/String;
Method	scala/Function1$class.toString:(Lscala/Function1;)Ljava/lang/String;
Asciz	Scala;
Asciz	InnerClasses;
Asciz	scala/testing/SUnit$TestResult;
class	scala/testing/SUnit$TestResult
Asciz	scala/testing/SUnit;
class	scala/testing/SUnit
Asciz	TestResult;
Asciz	TestFailure;
Asciz	$anonfun$failures$1;
Asciz	scala/Function1;
class	scala/Function1
Asciz	scala/ScalaObject;
class	scala/ScalaObject
Asciz	java/io/Serializable;
class	java/io/Serializable

{
public static final long serialVersionUID;
  Signature: J

public static {};
  Signature: ()V
  Code:
   Stack=2, Locals=0, Args_size=0
	lconst_0
	putstatic	Field serialVersionUID:J
	return
  Labels:

public scala.testing.SUnit$TestResult$$anonfun$failures$1(scala.testing.SUnit$TestResult);
  Signature: (Lscala/testing/SUnit$TestResult;)V
  Code:
   Stack=1, Locals=2, Args_size=2
	aload_0
	invokespecial	Method java/lang/Object."<init>":()V
	aload_0
	invokestatic	Method scala/Function1$class.$init$:(Lscala/Function1;)V
	return
  Labels:
  LocalVariableTable: 
   Start  Length  Slot  Name   Signature
   0      9      0    this       Lscala/testing/SUnit$TestResult$$anonfun$failures$1;
   0      9      1    $outer       Lscala/testing/SUnit$TestResult;


public final java.lang.Object apply(java.lang.Object);
  Signature: (Ljava/lang/Object;)Ljava/lang/Object;
  Code:
   Stack=2, Locals=2, Args_size=2
	aload_0
	aload_1
	checkcast	class scala/Tuple2
	invokevirtual	Method apply:(Lscala/Tuple2;)Lscala/testing/SUnit$TestFailure;
	areturn
  Labels:
  LocalVariableTable: 
   Start  Length  Slot  Name   Signature
   0      9      0    this       Lscala/testing/SUnit$TestResult$$anonfun$failures$1;
   0      9      1    v1       Ljava/lang/Object;


public final scala.testing.SUnit$TestFailure apply(scala.Tuple2);
  Signature: (Lscala/Tuple2;)Lscala/testing/SUnit$TestFailure;
  Code:
   Stack=3, Locals=2, Args_size=2
	new	class scala/testing/SUnit$TestFailure
	dup
	aload_1
	invokespecial	Method scala/testing/SUnit$TestFailure."<init>":(Lscala/Tuple2;)V
	areturn
  Labels:
  LocalVariableTable: 
   Start  Length  Slot  Name   Signature
   0      9      0    this       Lscala/testing/SUnit$TestResult$$anonfun$failures$1;
   0      9      1    x       Lscala/Tuple2;

  Signature: length = 0x2
   00 2E 

public scala.Function1 andThen(scala.Function1);
  Signature: (Lscala/Function1;)Lscala/Function1;
  Code:
   Stack=2, Locals=2, Args_size=2
	aload_0
	aload_1
	invokestatic	Method scala/Function1$class.andThen:(Lscala/Function1;Lscala/Function1;)Lscala/Function1;
	areturn
  Labels:
  LocalVariableTable: 
   Start  Length  Slot  Name   Signature
   0      6      0    this       Lscala/testing/SUnit$TestResult$$anonfun$failures$1;
   0      6      1    g       Lscala/Function1;


public scala.Function1 compose(scala.Function1);
  Signature: (Lscala/Function1;)Lscala/Function1;
  Code:
   Stack=2, Locals=2, Args_size=2
	aload_0
	aload_1
	invokestatic	Method scala/Function1$class.compose:(Lscala/Function1;Lscala/Function1;)Lscala/Function1;
	areturn
  Labels:
  LocalVariableTable: 
   Start  Length  Slot  Name   Signature
   0      6      0    this       Lscala/testing/SUnit$TestResult$$anonfun$failures$1;
   0      6      1    g       Lscala/Function1;


public java.lang.String toString();
  Signature: ()Ljava/lang/String;
  Code:
   Stack=1, Locals=1, Args_size=1
	aload_0
	invokestatic	Method scala/Function1$class.toString:(Lscala/Function1;)Ljava/lang/String;
	areturn
  Labels:

}

