Compiled from "SUnit.scala"
public abstract class scala.testing.SUnit$TestConsoleMain$class extends java.lang.Object
  SourceFile: "SUnit.scala"
  Scala: length = 0x
   
  InnerClass: 
   public TestSuite=class scala/testing/SUnit$TestSuite of class scala/testing/SUnit
   public TestResult=class scala/testing/SUnit$TestResult of class scala/testing/SUnit
   public abstract TestConsoleMain=class scala/testing/SUnit$TestConsoleMain of class scala/testing/SUnit
   public final $anonfun$main$1=class scala/testing/SUnit$TestConsoleMain$$anonfun$main$1 of class scala/testing/SUnit$TestConsoleMain
  minor version: 0
  major version: 49
  Constant pool:
Asciz	SourceFile;
Asciz	SUnit.scala;
Asciz	main;
Asciz	(Lscala/testing/SUnit$TestConsoleMain;[Ljava/lang/String;)V;
Asciz	Code;
Asciz	scala/testing/SUnit$TestResult;
class	scala/testing/SUnit$TestResult
Asciz	LineNumberTable;
Asciz	<init>;
Asciz	()V;
NameAndType	"<init>":()V
Method	scala/testing/SUnit$TestResult."<init>":()V
Asciz	scala/testing/SUnit$TestConsoleMain;
class	scala/testing/SUnit$TestConsoleMain
Asciz	suite;
Asciz	()Lscala/testing/SUnit$TestSuite;;
NameAndType	suite:()Lscala/testing/SUnit$TestSuite;
InterfaceMethod	scala/testing/SUnit$TestConsoleMain.suite:()Lscala/testing/SUnit$TestSuite;
Asciz	scala/testing/SUnit$TestSuite;
class	scala/testing/SUnit$TestSuite
Asciz	run;
Asciz	(Lscala/testing/SUnit$TestResult;)V;
NameAndType	run:(Lscala/testing/SUnit$TestResult;)V
Method	scala/testing/SUnit$TestSuite.run:(Lscala/testing/SUnit$TestResult;)V
Asciz	failures;
Asciz	()Lscala/collection/Iterator;;
NameAndType	failures:()Lscala/collection/Iterator;
Method	scala/testing/SUnit$TestResult.failures:()Lscala/collection/Iterator;
Asciz	scala/testing/SUnit$TestConsoleMain$$anonfun$main$1;
class	scala/testing/SUnit$TestConsoleMain$$anonfun$main$1
Asciz	(Lscala/testing/SUnit$TestConsoleMain;)V;
NameAndType	"<init>":(Lscala/testing/SUnit$TestConsoleMain;)V
Method	scala/testing/SUnit$TestConsoleMain$$anonfun$main$1."<init>":(Lscala/testing/SUnit$TestConsoleMain;)V
Asciz	scala/collection/Iterator;
class	scala/collection/Iterator
Asciz	foreach;
Asciz	(Lscala/Function1;)V;
NameAndType	foreach:(Lscala/Function1;)V
InterfaceMethod	scala/collection/Iterator.foreach:(Lscala/Function1;)V
Asciz	$this;
Asciz	Lscala/testing/SUnit$TestConsoleMain;;
Asciz	args;
Asciz	[Ljava/lang/String;;
Asciz	r;
Asciz	Lscala/testing/SUnit$TestResult;;
Asciz	LocalVariableTable;
Asciz	$init$;
Asciz	Scala;
Asciz	InnerClasses;
Asciz	scala/testing/SUnit;
class	scala/testing/SUnit
Asciz	TestSuite;
Asciz	TestResult;
Asciz	TestConsoleMain;
Asciz	$anonfun$main$1;
Asciz	scala/testing/SUnit$TestConsoleMain$class;
class	scala/testing/SUnit$TestConsoleMain$class
Asciz	java/lang/Object;
class	java/lang/Object

{
public static void main(scala.testing.SUnit$TestConsoleMain, java.lang.String[]);
  Signature: (Lscala/testing/SUnit$TestConsoleMain;[Ljava/lang/String;)V
  Code:
   Stack=4, Locals=3, Args_size=2
	new	class scala/testing/SUnit$TestResult
	dup
	invokespecial	Method scala/testing/SUnit$TestResult."<init>":()V
	astore_2
	aload_0
	invokeinterface	InterfaceMethod scala/testing/SUnit$TestConsoleMain.suite:()Lscala/testing/SUnit$TestSuite;
	aload_2
	invokevirtual	Method scala/testing/SUnit$TestSuite.run:(Lscala/testing/SUnit$TestResult;)V
	aload_2
	invokevirtual	Method scala/testing/SUnit$TestResult.failures:()Lscala/collection/Iterator;
	new	class scala/testing/SUnit$TestConsoleMain$$anonfun$main$1
	dup
	aload_0
	invokespecial	Method scala/testing/SUnit$TestConsoleMain$$anonfun$main$1."<init>":(Lscala/testing/SUnit$TestConsoleMain;)V
	invokeinterface	InterfaceMethod scala/collection/Iterator.foreach:(Lscala/Function1;)V
	return
  Labels:
  LocalVariableTable: 
   Start  Length  Slot  Name   Signature
   0      36      0    $this       Lscala/testing/SUnit$TestConsoleMain;
   0      36      1    args       [Ljava/lang/String;
   8      27      2    r       Lscala/testing/SUnit$TestResult;


public static void $init$(scala.testing.SUnit$TestConsoleMain);
  Signature: (Lscala/testing/SUnit$TestConsoleMain;)V
  Code:
   Stack=0, Locals=1, Args_size=1
	return
  Labels:
  LocalVariableTable: 
   Start  Length  Slot  Name   Signature
   0      1      0    $this       Lscala/testing/SUnit$TestConsoleMain;


}

