Compiled from "SUnit.scala"
public class scala.testing.SUnit$TestFailure extends java.lang.Object implements scala.ScalaObject
  SourceFile: "SUnit.scala"
  Scala: length = 0x
   
  InnerClass: 
   public abstract Test=class scala/testing/SUnit$Test of class scala/testing/SUnit
   public TestFailure=class scala/testing/SUnit$TestFailure of class scala/testing/SUnit
  minor version: 0
  major version: 49
  Constant pool:
Asciz	SourceFile;
Asciz	SUnit.scala;
Asciz	failedTest;
Asciz	Lscala/testing/SUnit$Test;;
Asciz	thrownException;
Asciz	Ljava/lang/Throwable;;
Asciz	()Lscala/testing/SUnit$Test;;
Asciz	Code;
Asciz	LineNumberTable;
Asciz	scala/testing/SUnit$TestFailure;
class	scala/testing/SUnit$TestFailure
NameAndType	failedTest:Lscala/testing/SUnit$Test;
Field	scala/testing/SUnit$TestFailure.failedTest:Lscala/testing/SUnit$Test;
Asciz	()Ljava/lang/Throwable;;
NameAndType	thrownException:Ljava/lang/Throwable;
Field	scala/testing/SUnit$TestFailure.thrownException:Ljava/lang/Throwable;
Asciz	<init>;
Asciz	(Lscala/Tuple2;)V;
Asciz	scala/Tuple2;
class	scala/Tuple2
Asciz	_1;
Asciz	()Ljava/lang/Object;;
NameAndType	_1:()Ljava/lang/Object;
Method	scala/Tuple2._1:()Ljava/lang/Object;
Asciz	scala/testing/SUnit$Test;
class	scala/testing/SUnit$Test
Asciz	_2;
NameAndType	_2:()Ljava/lang/Object;
Method	scala/Tuple2._2:()Ljava/lang/Object;
Asciz	java/lang/Throwable;
class	java/lang/Throwable
Asciz	(Lscala/testing/SUnit$Test;Ljava/lang/Throwable;)V;
NameAndType	"<init>":(Lscala/testing/SUnit$Test;Ljava/lang/Throwable;)V
Method	scala/testing/SUnit$TestFailure."<init>":(Lscala/testing/SUnit$Test;Ljava/lang/Throwable;)V
Asciz	this;
Asciz	Lscala/testing/SUnit$TestFailure;;
Asciz	p;
Asciz	Lscala/Tuple2;;
Asciz	LocalVariableTable;
Asciz	(Lscala/Tuple2<Lscala/testing/SUnit$Test;Ljava/lang/Throwable;>;)V;
Asciz	Signature;
Asciz	toString;
Asciz	()Ljava/lang/String;;
Asciz	scala/collection/mutable/StringBuilder;
class	scala/collection/mutable/StringBuilder
Asciz	()V;
NameAndType	"<init>":()V
Method	scala/collection/mutable/StringBuilder."<init>":()V
NameAndType	failedTest:()Lscala/testing/SUnit$Test;
Method	scala/testing/SUnit$TestFailure.failedTest:()Lscala/testing/SUnit$Test;
Asciz	java/lang/Object;
class	java/lang/Object
NameAndType	toString:()Ljava/lang/String;
Method	java/lang/Object.toString:()Ljava/lang/String;
Asciz	append;
Asciz	(Ljava/lang/Object;)Lscala/collection/mutable/StringBuilder;;
NameAndType	append:(Ljava/lang/Object;)Lscala/collection/mutable/StringBuilder;
Method	scala/collection/mutable/StringBuilder.append:(Ljava/lang/Object;)Lscala/collection/mutable/StringBuilder;
Asciz	 failed due to ;
String	 failed due to 
NameAndType	thrownException:()Ljava/lang/Throwable;
Method	scala/testing/SUnit$TestFailure.thrownException:()Ljava/lang/Throwable;
Method	java/lang/Throwable.toString:()Ljava/lang/String;
Method	scala/collection/mutable/StringBuilder.toString:()Ljava/lang/String;
Asciz	trace;
Asciz	scala/Predef$;
class	scala/Predef$
Asciz	MODULE$;
Asciz	Lscala/Predef$;;
NameAndType	MODULE$:Lscala/Predef$;
Field	scala/Predef$.MODULE$:Lscala/Predef$;
Asciz	exceptionWrapper;
Asciz	(Ljava/lang/Throwable;)Lscala/runtime/RichException;;
NameAndType	exceptionWrapper:(Ljava/lang/Throwable;)Lscala/runtime/RichException;
Method	scala/Predef$.exceptionWrapper:(Ljava/lang/Throwable;)Lscala/runtime/RichException;
Asciz	scala/runtime/RichException;
class	scala/runtime/RichException
Asciz	getStackTraceString;
NameAndType	getStackTraceString:()Ljava/lang/String;
Method	scala/runtime/RichException.getStackTraceString:()Ljava/lang/String;
Method	java/lang/Object."<init>":()V
Asciz	Scala;
Asciz	InnerClasses;
Asciz	scala/testing/SUnit;
class	scala/testing/SUnit
Asciz	Test;
Asciz	TestFailure;
Asciz	scala/ScalaObject;
class	scala/ScalaObject

{
private final scala.testing.SUnit$Test failedTest;
  Signature: Lscala/testing/SUnit$Test;

private final java.lang.Throwable thrownException;
  Signature: Ljava/lang/Throwable;

public scala.testing.SUnit$Test failedTest();
  Signature: ()Lscala/testing/SUnit$Test;
  Code:
   Stack=1, Locals=1, Args_size=1
	aload_0
	getfield	Field failedTest:Lscala/testing/SUnit$Test;
	areturn
  Labels:

public java.lang.Throwable thrownException();
  Signature: ()Ljava/lang/Throwable;
  Code:
   Stack=1, Locals=1, Args_size=1
	aload_0
	getfield	Field thrownException:Ljava/lang/Throwable;
	areturn
  Labels:

public scala.testing.SUnit$TestFailure(scala.Tuple2);
  Signature: (Lscala/Tuple2;)V
  Code:
   Stack=3, Locals=2, Args_size=2
	aload_0
	aload_1
	invokevirtual	Method scala/Tuple2._1:()Ljava/lang/Object;
	checkcast	class scala/testing/SUnit$Test
	aload_1
	invokevirtual	Method scala/Tuple2._2:()Ljava/lang/Object;
	checkcast	class java/lang/Throwable
	invokespecial	Method "<init>":(Lscala/testing/SUnit$Test;Ljava/lang/Throwable;)V
	return
  Labels:
  LocalVariableTable: 
   Start  Length  Slot  Name   Signature
   0      19      0    this       Lscala/testing/SUnit$TestFailure;
   0      19      1    p       Lscala/Tuple2;

  Signature: length = 0x2
   00 28 

public java.lang.String toString();
  Signature: ()Ljava/lang/String;
  Code:
   Stack=2, Locals=1, Args_size=1
	new	class scala/collection/mutable/StringBuilder
	dup
	invokespecial	Method scala/collection/mutable/StringBuilder."<init>":()V
	aload_0
	invokevirtual	Method failedTest:()Lscala/testing/SUnit$Test;
	invokevirtual	Method java/lang/Object.toString:()Ljava/lang/String;
	invokevirtual	Method scala/collection/mutable/StringBuilder.append:(Ljava/lang/Object;)Lscala/collection/mutable/StringBuilder;
	ldc	String  failed due to 
	invokevirtual	Method scala/collection/mutable/StringBuilder.append:(Ljava/lang/Object;)Lscala/collection/mutable/StringBuilder;
	aload_0
	invokevirtual	Method thrownException:()Ljava/lang/Throwable;
	invokevirtual	Method java/lang/Throwable.toString:()Ljava/lang/String;
	invokevirtual	Method scala/collection/mutable/StringBuilder.append:(Ljava/lang/Object;)Lscala/collection/mutable/StringBuilder;
	invokevirtual	Method scala/collection/mutable/StringBuilder.toString:()Ljava/lang/String;
	areturn
  Labels:

public java.lang.String trace();
  Signature: ()Ljava/lang/String;
  Code:
   Stack=2, Locals=1, Args_size=1
	getstatic	Field scala/Predef$.MODULE$:Lscala/Predef$;
	aload_0
	invokevirtual	Method thrownException:()Ljava/lang/Throwable;
	invokevirtual	Method scala/Predef$.exceptionWrapper:(Ljava/lang/Throwable;)Lscala/runtime/RichException;
	invokevirtual	Method scala/runtime/RichException.getStackTraceString:()Ljava/lang/String;
	areturn
  Labels:

public scala.testing.SUnit$TestFailure(scala.testing.SUnit$Test, java.lang.Throwable);
  Signature: (Lscala/testing/SUnit$Test;Ljava/lang/Throwable;)V
  Code:
   Stack=2, Locals=3, Args_size=3
	aload_0
	aload_1
	putfield	Field failedTest:Lscala/testing/SUnit$Test;
	aload_0
	aload_2
	putfield	Field thrownException:Ljava/lang/Throwable;
	aload_0
	invokespecial	Method java/lang/Object."<init>":()V
	return
  Labels:
  LocalVariableTable: 
   Start  Length  Slot  Name   Signature
   0      15      0    this       Lscala/testing/SUnit$TestFailure;
   0      15      1    failedTest       Lscala/testing/SUnit$Test;
   0      15      2    thrownException       Ljava/lang/Throwable;


}

