Compiled from "SUnit.scala"
public final class scala.testing.SUnit$TestSuite$$anonfun$run$1 extends java.lang.Object implements scala.Function1,scala.ScalaObject,java.io.Serializable
  SourceFile: "SUnit.scala"
  Scala: length = 0x
   
  InnerClass: 
   public abstract Test=class scala/testing/SUnit$Test of class scala/testing/SUnit
   public TestSuite=class scala/testing/SUnit$TestSuite of class scala/testing/SUnit
   public TestResult=class scala/testing/SUnit$TestResult of class scala/testing/SUnit
   public final $anonfun$run$1=class scala/testing/SUnit$TestSuite$$anonfun$run$1 of class scala/testing/SUnit$TestSuite
  minor version: 0
  major version: 49
  Constant pool:
Asciz	SourceFile;
Asciz	SUnit.scala;
Asciz	<clinit>;
Asciz	()V;
Asciz	Code;
Asciz	serialVersionUID;
Asciz	J;
Asciz	scala/testing/SUnit$TestSuite$$anonfun$run$1;
class	scala/testing/SUnit$TestSuite$$anonfun$run$1
NameAndType	serialVersionUID:J
Field	scala/testing/SUnit$TestSuite$$anonfun$run$1.serialVersionUID:J
Asciz	r$1;
Asciz	Lscala/testing/SUnit$TestResult;;
Asciz	<init>;
Asciz	(Lscala/testing/SUnit$TestSuite;Lscala/testing/SUnit$TestResult;)V;
Asciz	LineNumberTable;
NameAndType	r$1:Lscala/testing/SUnit$TestResult;
Field	scala/testing/SUnit$TestSuite$$anonfun$run$1.r$1:Lscala/testing/SUnit$TestResult;
Asciz	java/lang/Object;
class	java/lang/Object
NameAndType	"<init>":()V
Method	java/lang/Object."<init>":()V
Asciz	scala/Function1$class;
class	scala/Function1$class
Asciz	$init$;
Asciz	(Lscala/Function1;)V;
NameAndType	$init$:(Lscala/Function1;)V
Method	scala/Function1$class.$init$:(Lscala/Function1;)V
Asciz	this;
Asciz	Lscala/testing/SUnit$TestSuite$$anonfun$run$1;;
Asciz	$outer;
Asciz	Lscala/testing/SUnit$TestSuite;;
Asciz	LocalVariableTable;
Asciz	apply;
Asciz	(Ljava/lang/Object;)Ljava/lang/Object;;
Asciz	scala/testing/SUnit$Test;
class	scala/testing/SUnit$Test
Asciz	(Lscala/testing/SUnit$Test;)V;
NameAndType	apply:(Lscala/testing/SUnit$Test;)V
Method	scala/testing/SUnit$TestSuite$$anonfun$run$1.apply:(Lscala/testing/SUnit$Test;)V
Asciz	scala/runtime/BoxedUnit;
class	scala/runtime/BoxedUnit
Asciz	UNIT;
Asciz	Lscala/runtime/BoxedUnit;;
NameAndType	UNIT:Lscala/runtime/BoxedUnit;
Field	scala/runtime/BoxedUnit.UNIT:Lscala/runtime/BoxedUnit;
Asciz	v1;
Asciz	Ljava/lang/Object;;
Asciz	run;
Asciz	(Lscala/testing/SUnit$TestResult;)V;
NameAndType	run:(Lscala/testing/SUnit$TestResult;)V
InterfaceMethod	scala/testing/SUnit$Test.run:(Lscala/testing/SUnit$TestResult;)V
Asciz	t;
Asciz	Lscala/testing/SUnit$Test;;
Asciz	andThen;
Asciz	(Lscala/Function1;)Lscala/Function1;;
Asciz	(Lscala/Function1;Lscala/Function1;)Lscala/Function1;;
NameAndType	andThen:(Lscala/Function1;Lscala/Function1;)Lscala/Function1;
Method	scala/Function1$class.andThen:(Lscala/Function1;Lscala/Function1;)Lscala/Function1;
Asciz	g;
Asciz	Lscala/Function1;;
Asciz	compose;
NameAndType	compose:(Lscala/Function1;Lscala/Function1;)Lscala/Function1;
Method	scala/Function1$class.compose:(Lscala/Function1;Lscala/Function1;)Lscala/Function1;
Asciz	toString;
Asciz	()Ljava/lang/String;;
Asciz	(Lscala/Function1;)Ljava/lang/String;;
NameAndType	toString:(Lscala/Function1;)Ljava/lang/String;
Method	scala/Function1$class.toString:(Lscala/Function1;)Ljava/lang/String;
Asciz	Scala;
Asciz	InnerClasses;
Asciz	scala/testing/SUnit;
class	scala/testing/SUnit
Asciz	Test;
Asciz	scala/testing/SUnit$TestSuite;
class	scala/testing/SUnit$TestSuite
Asciz	TestSuite;
Asciz	scala/testing/SUnit$TestResult;
class	scala/testing/SUnit$TestResult
Asciz	TestResult;
Asciz	$anonfun$run$1;
Asciz	scala/Function1;
class	scala/Function1
Asciz	scala/ScalaObject;
class	scala/ScalaObject
Asciz	java/io/Serializable;
class	java/io/Serializable

{
public static final long serialVersionUID;
  Signature: J

private final scala.testing.SUnit$TestResult r$1;
  Signature: Lscala/testing/SUnit$TestResult;

public static {};
  Signature: ()V
  Code:
   Stack=2, Locals=0, Args_size=0
	lconst_0
	putstatic	Field serialVersionUID:J
	return
  Labels:

public scala.testing.SUnit$TestSuite$$anonfun$run$1(scala.testing.SUnit$TestSuite, scala.testing.SUnit$TestResult);
  Signature: (Lscala/testing/SUnit$TestSuite;Lscala/testing/SUnit$TestResult;)V
  Code:
   Stack=2, Locals=3, Args_size=3
	aload_0
	aload_2
	putfield	Field r$1:Lscala/testing/SUnit$TestResult;
	aload_0
	invokespecial	Method java/lang/Object."<init>":()V
	aload_0
	invokestatic	Method scala/Function1$class.$init$:(Lscala/Function1;)V
	return
  Labels:
  LocalVariableTable: 
   Start  Length  Slot  Name   Signature
   0      14      0    this       Lscala/testing/SUnit$TestSuite$$anonfun$run$1;
   0      14      1    $outer       Lscala/testing/SUnit$TestSuite;


public final java.lang.Object apply(java.lang.Object);
  Signature: (Ljava/lang/Object;)Ljava/lang/Object;
  Code:
   Stack=2, Locals=2, Args_size=2
	aload_0
	aload_1
	checkcast	class scala/testing/SUnit$Test
	invokevirtual	Method apply:(Lscala/testing/SUnit$Test;)V
	getstatic	Field scala/runtime/BoxedUnit.UNIT:Lscala/runtime/BoxedUnit;
	areturn
  Labels:
  LocalVariableTable: 
   Start  Length  Slot  Name   Signature
   0      12      0    this       Lscala/testing/SUnit$TestSuite$$anonfun$run$1;
   0      12      1    v1       Ljava/lang/Object;


public final void apply(scala.testing.SUnit$Test);
  Signature: (Lscala/testing/SUnit$Test;)V
  Code:
   Stack=2, Locals=2, Args_size=2
	aload_1
	aload_0
	getfield	Field r$1:Lscala/testing/SUnit$TestResult;
	invokeinterface	InterfaceMethod scala/testing/SUnit$Test.run:(Lscala/testing/SUnit$TestResult;)V
	return
  Labels:
  LocalVariableTable: 
   Start  Length  Slot  Name   Signature
   0      11      0    this       Lscala/testing/SUnit$TestSuite$$anonfun$run$1;
   0      11      1    t       Lscala/testing/SUnit$Test;


public scala.Function1 andThen(scala.Function1);
  Signature: (Lscala/Function1;)Lscala/Function1;
  Code:
   Stack=2, Locals=2, Args_size=2
	aload_0
	aload_1
	invokestatic	Method scala/Function1$class.andThen:(Lscala/Function1;Lscala/Function1;)Lscala/Function1;
	areturn
  Labels:
  LocalVariableTable: 
   Start  Length  Slot  Name   Signature
   0      6      0    this       Lscala/testing/SUnit$TestSuite$$anonfun$run$1;
   0      6      1    g       Lscala/Function1;


public scala.Function1 compose(scala.Function1);
  Signature: (Lscala/Function1;)Lscala/Function1;
  Code:
   Stack=2, Locals=2, Args_size=2
	aload_0
	aload_1
	invokestatic	Method scala/Function1$class.compose:(Lscala/Function1;Lscala/Function1;)Lscala/Function1;
	areturn
  Labels:
  LocalVariableTable: 
   Start  Length  Slot  Name   Signature
   0      6      0    this       Lscala/testing/SUnit$TestSuite$$anonfun$run$1;
   0      6      1    g       Lscala/Function1;


public java.lang.String toString();
  Signature: ()Ljava/lang/String;
  Code:
   Stack=1, Locals=1, Args_size=1
	aload_0
	invokestatic	Method scala/Function1$class.toString:(Lscala/Function1;)Ljava/lang/String;
	areturn
  Labels:

}

