Compiled from "SUnit.scala"
public abstract class scala.testing.SUnit$TestConsoleMain$class extends java.lang.Object
  SourceFile: "SUnit.scala"
  Scala: length = 0x
   
  InnerClass: 
   public #52= #25 of #51; //TestSuite=class scala/testing/SUnit$TestSuite of class scala/testing/SUnit
   public #53= #13 of #51; //TestResult=class scala/testing/SUnit$TestResult of class scala/testing/SUnit
   public abstract #54= #19 of #51; //TestConsoleMain=class scala/testing/SUnit$TestConsoleMain of class scala/testing/SUnit
   public final #55= #35 of #19; //$anonfun$main$1=class scala/testing/SUnit$TestConsoleMain$$anonfun$main$1 of class scala/testing/SUnit$TestConsoleMain
  minor version: 0
  major version: 49
  Constant pool:
const #1 = Asciz	SourceFile;
const #2 = Asciz	SUnit.scala;
const #3 = Asciz	$init$;
const #4 = Asciz	(Lscala/testing/SUnit$TestConsoleMain;)V;
const #5 = Asciz	Code;
const #6 = Asciz	LineNumberTable;
const #7 = Asciz	$this;
const #8 = Asciz	Lscala/testing/SUnit$TestConsoleMain;;
const #9 = Asciz	LocalVariableTable;
const #10 = Asciz	main;
const #11 = Asciz	(Lscala/testing/SUnit$TestConsoleMain;[Ljava/lang/String;)V;
const #12 = Asciz	scala/testing/SUnit$TestResult;
const #13 = class	#12;	//  scala/testing/SUnit$TestResult
const #14 = Asciz	<init>;
const #15 = Asciz	()V;
const #16 = NameAndType	#14:#15;//  "<init>":()V
const #17 = Method	#13.#16;	//  scala/testing/SUnit$TestResult."<init>":()V
const #18 = Asciz	scala/testing/SUnit$TestConsoleMain;
const #19 = class	#18;	//  scala/testing/SUnit$TestConsoleMain
const #20 = Asciz	suite;
const #21 = Asciz	()Lscala/testing/SUnit$TestSuite;;
const #22 = NameAndType	#20:#21;//  suite:()Lscala/testing/SUnit$TestSuite;
const #23 = InterfaceMethod	#19.#22;	//  scala/testing/SUnit$TestConsoleMain.suite:()Lscala/testing/SUnit$TestSuite;
const #24 = Asciz	scala/testing/SUnit$TestSuite;
const #25 = class	#24;	//  scala/testing/SUnit$TestSuite
const #26 = Asciz	run;
const #27 = Asciz	(Lscala/testing/SUnit$TestResult;)V;
const #28 = NameAndType	#26:#27;//  run:(Lscala/testing/SUnit$TestResult;)V
const #29 = Method	#25.#28;	//  scala/testing/SUnit$TestSuite.run:(Lscala/testing/SUnit$TestResult;)V
const #30 = Asciz	failures;
const #31 = Asciz	()Lscala/collection/Iterator;;
const #32 = NameAndType	#30:#31;//  failures:()Lscala/collection/Iterator;
const #33 = Method	#13.#32;	//  scala/testing/SUnit$TestResult.failures:()Lscala/collection/Iterator;
const #34 = Asciz	scala/testing/SUnit$TestConsoleMain$$anonfun$main$1;
const #35 = class	#34;	//  scala/testing/SUnit$TestConsoleMain$$anonfun$main$1
const #36 = NameAndType	#14:#4;//  "<init>":(Lscala/testing/SUnit$TestConsoleMain;)V
const #37 = Method	#35.#36;	//  scala/testing/SUnit$TestConsoleMain$$anonfun$main$1."<init>":(Lscala/testing/SUnit$TestConsoleMain;)V
const #38 = Asciz	scala/collection/Iterator;
const #39 = class	#38;	//  scala/collection/Iterator
const #40 = Asciz	foreach;
const #41 = Asciz	(Lscala/Function1;)V;
const #42 = NameAndType	#40:#41;//  foreach:(Lscala/Function1;)V
const #43 = InterfaceMethod	#39.#42;	//  scala/collection/Iterator.foreach:(Lscala/Function1;)V
const #44 = Asciz	args;
const #45 = Asciz	[Ljava/lang/String;;
const #46 = Asciz	r;
const #47 = Asciz	Lscala/testing/SUnit$TestResult;;
const #48 = Asciz	Scala;
const #49 = Asciz	InnerClasses;
const #50 = Asciz	scala/testing/SUnit;
const #51 = class	#50;	//  scala/testing/SUnit
const #52 = Asciz	TestSuite;
const #53 = Asciz	TestResult;
const #54 = Asciz	TestConsoleMain;
const #55 = Asciz	$anonfun$main$1;
const #56 = Asciz	scala/testing/SUnit$TestConsoleMain$class;
const #57 = class	#56;	//  scala/testing/SUnit$TestConsoleMain$class
const #58 = Asciz	java/lang/Object;
const #59 = class	#58;	//  java/lang/Object

{
public static void $init$(scala.testing.SUnit$TestConsoleMain);
  Code:
   Stack=0, Locals=1, Args_size=1
   0:	return
  LineNumberTable: 
   line 63: 0

  LocalVariableTable: 
   Start  Length  Slot  Name   Signature
   0      1      0    $this       Lscala/testing/SUnit$TestConsoleMain;


public static void main(scala.testing.SUnit$TestConsoleMain, java.lang.String[]);
  Code:
   Stack=4, Locals=3, Args_size=2
   0:	new	#13; //class scala/testing/SUnit$TestResult
   3:	dup
   4:	invokespecial	#17; //Method scala/testing/SUnit$TestResult."<init>":()V
   7:	astore_2
   8:	aload_0
   9:	invokeinterface	#23,  1; //InterfaceMethod scala/testing/SUnit$TestConsoleMain.suite:()Lscala/testing/SUnit$TestSuite;
   14:	aload_2
   15:	invokevirtual	#29; //Method scala/testing/SUnit$TestSuite.run:(Lscala/testing/SUnit$TestResult;)V
   18:	aload_2
   19:	invokevirtual	#33; //Method scala/testing/SUnit$TestResult.failures:()Lscala/collection/Iterator;
   22:	new	#35; //class scala/testing/SUnit$TestConsoleMain$$anonfun$main$1
   25:	dup
   26:	aload_0
   27:	invokespecial	#37; //Method scala/testing/SUnit$TestConsoleMain$$anonfun$main$1."<init>":(Lscala/testing/SUnit$TestConsoleMain;)V
   30:	invokeinterface	#43,  2; //InterfaceMethod scala/collection/Iterator.foreach:(Lscala/Function1;)V
   35:	return
  LineNumberTable: 
   line 66: 0
   line 67: 8
   line 68: 14
   line 67: 15
   line 68: 18

  LocalVariableTable: 
   Start  Length  Slot  Name   Signature
   0      36      0    $this       Lscala/testing/SUnit$TestConsoleMain;
   0      36      1    args       [Ljava/lang/String;
   8      27      2    r       Lscala/testing/SUnit$TestResult;


}

