Compiled from "SUnit.scala"
public class scala.testing.SUnit$TestResult extends java.lang.Object implements scala.ScalaObject
  SourceFile: "SUnit.scala"
  Scala: length = 0x
   
  InnerClass: 
   public abstract #76= #73 of #75; //Test=class scala/testing/SUnit$Test of class scala/testing/SUnit
   public #77= #19 of #75; //TestResult=class scala/testing/SUnit$TestResult of class scala/testing/SUnit
   public final #78= #33 of #19; //$anonfun$failures$1=class scala/testing/SUnit$TestResult$$anonfun$failures$1 of class scala/testing/SUnit$TestResult
  minor version: 0
  major version: 49
  Constant pool:
const #1 = Asciz	SourceFile;
const #2 = Asciz	SUnit.scala;
const #3 = Asciz	buf;
const #4 = Asciz	Lscala/collection/mutable/ArrayBuffer;;
const #5 = Asciz	Lscala/collection/mutable/ArrayBuffer<Lscala/Tuple2<Lscala/testing/SUnit$Test;Ljava/lang/Throwable;>;>;;
const #6 = Asciz	Signature;
const #7 = Asciz	<init>;
const #8 = Asciz	()V;
const #9 = Asciz	Code;
const #10 = Asciz	LineNumberTable;
const #11 = Asciz	java/lang/Object;
const #12 = class	#11;	//  java/lang/Object
const #13 = NameAndType	#7:#8;//  "<init>":()V
const #14 = Method	#12.#13;	//  java/lang/Object."<init>":()V
const #15 = Asciz	scala/collection/mutable/ArrayBuffer;
const #16 = class	#15;	//  scala/collection/mutable/ArrayBuffer
const #17 = Method	#16.#13;	//  scala/collection/mutable/ArrayBuffer."<init>":()V
const #18 = Asciz	scala/testing/SUnit$TestResult;
const #19 = class	#18;	//  scala/testing/SUnit$TestResult
const #20 = NameAndType	#3:#4;//  buf:Lscala/collection/mutable/ArrayBuffer;
const #21 = Field	#19.#20;	//  scala/testing/SUnit$TestResult.buf:Lscala/collection/mutable/ArrayBuffer;
const #22 = Asciz	failures;
const #23 = Asciz	()Lscala/collection/Iterator;;
const #24 = Asciz	()Lscala/collection/mutable/ArrayBuffer;;
const #25 = NameAndType	#3:#24;//  buf:()Lscala/collection/mutable/ArrayBuffer;
const #26 = Method	#19.#25;	//  scala/testing/SUnit$TestResult.buf:()Lscala/collection/mutable/ArrayBuffer;
const #27 = Asciz	scala/collection/generic/VectorTemplate;
const #28 = class	#27;	//  scala/collection/generic/VectorTemplate
const #29 = Asciz	iterator;
const #30 = NameAndType	#29:#23;//  iterator:()Lscala/collection/Iterator;
const #31 = InterfaceMethod	#28.#30;	//  scala/collection/generic/VectorTemplate.iterator:()Lscala/collection/Iterator;
const #32 = Asciz	scala/testing/SUnit$TestResult$$anonfun$failures$1;
const #33 = class	#32;	//  scala/testing/SUnit$TestResult$$anonfun$failures$1
const #34 = Asciz	(Lscala/testing/SUnit$TestResult;)V;
const #35 = NameAndType	#7:#34;//  "<init>":(Lscala/testing/SUnit$TestResult;)V
const #36 = Method	#33.#35;	//  scala/testing/SUnit$TestResult$$anonfun$failures$1."<init>":(Lscala/testing/SUnit$TestResult;)V
const #37 = Asciz	scala/collection/Iterator;
const #38 = class	#37;	//  scala/collection/Iterator
const #39 = Asciz	map;
const #40 = Asciz	(Lscala/Function1;)Lscala/collection/Iterator;;
const #41 = NameAndType	#39:#40;//  map:(Lscala/Function1;)Lscala/collection/Iterator;
const #42 = InterfaceMethod	#38.#41;	//  scala/collection/Iterator.map:(Lscala/Function1;)Lscala/collection/Iterator;
const #43 = Asciz	()Lscala/collection/Iterator<Lscala/testing/SUnit$TestFailure;>;;
const #44 = Asciz	failureCount;
const #45 = Asciz	()I;
const #46 = Asciz	scala/collection/mutable/ResizableArray;
const #47 = class	#46;	//  scala/collection/mutable/ResizableArray
const #48 = Asciz	length;
const #49 = NameAndType	#48:#45;//  length:()I
const #50 = InterfaceMethod	#47.#49;	//  scala/collection/mutable/ResizableArray.length:()I
const #51 = Asciz	addFailure;
const #52 = Asciz	(Lscala/testing/SUnit$Test;Ljava/lang/Throwable;)V;
const #53 = Asciz	scala/Tuple2;
const #54 = class	#53;	//  scala/Tuple2
const #55 = Asciz	(Ljava/lang/Object;Ljava/lang/Object;)V;
const #56 = NameAndType	#7:#55;//  "<init>":(Ljava/lang/Object;Ljava/lang/Object;)V
const #57 = Method	#54.#56;	//  scala/Tuple2."<init>":(Ljava/lang/Object;Ljava/lang/Object;)V
const #58 = Asciz	$plus$eq;
const #59 = Asciz	(Ljava/lang/Object;)Lscala/collection/mutable/ArrayBuffer;;
const #60 = NameAndType	#58:#59;//  $plus$eq:(Ljava/lang/Object;)Lscala/collection/mutable/ArrayBuffer;
const #61 = Method	#16.#60;	//  scala/collection/mutable/ArrayBuffer.$plus$eq:(Ljava/lang/Object;)Lscala/collection/mutable/ArrayBuffer;
const #62 = Asciz	this;
const #63 = Asciz	Lscala/testing/SUnit$TestResult;;
const #64 = Asciz	test;
const #65 = Asciz	Lscala/testing/SUnit$Test;;
const #66 = Asciz	t;
const #67 = Asciz	Ljava/lang/Throwable;;
const #68 = Asciz	LocalVariableTable;
const #69 = Asciz	()Lscala/collection/mutable/ArrayBuffer<Lscala/Tuple2<Lscala/testing/SUnit$Test;Ljava/lang/Throwable;>;>;;
const #70 = Asciz	Scala;
const #71 = Asciz	InnerClasses;
const #72 = Asciz	scala/testing/SUnit$Test;
const #73 = class	#72;	//  scala/testing/SUnit$Test
const #74 = Asciz	scala/testing/SUnit;
const #75 = class	#74;	//  scala/testing/SUnit
const #76 = Asciz	Test;
const #77 = Asciz	TestResult;
const #78 = Asciz	$anonfun$failures$1;
const #79 = Asciz	scala/ScalaObject;
const #80 = class	#79;	//  scala/ScalaObject

{
public scala.testing.SUnit$TestResult();
  Code:
   Stack=3, Locals=1, Args_size=1
   0:	aload_0
   1:	invokespecial	#14; //Method java/lang/Object."<init>":()V
   4:	aload_0
   5:	new	#16; //class scala/collection/mutable/ArrayBuffer
   8:	dup
   9:	invokespecial	#17; //Method scala/collection/mutable/ArrayBuffer."<init>":()V
   12:	putfield	#21; //Field buf:Lscala/collection/mutable/ArrayBuffer;
   15:	return
  LineNumberTable: 
   line 117: 0
   line 118: 4


public scala.collection.Iterator failures();
  Code:
   Stack=4, Locals=1, Args_size=1
   0:	aload_0
   1:	invokevirtual	#26; //Method buf:()Lscala/collection/mutable/ArrayBuffer;
   4:	invokeinterface	#31,  1; //InterfaceMethod scala/collection/generic/VectorTemplate.iterator:()Lscala/collection/Iterator;
   9:	new	#33; //class scala/testing/SUnit$TestResult$$anonfun$failures$1
   12:	dup
   13:	aload_0
   14:	invokespecial	#36; //Method scala/testing/SUnit$TestResult$$anonfun$failures$1."<init>":(Lscala/testing/SUnit$TestResult;)V
   17:	invokeinterface	#42,  2; //InterfaceMethod scala/collection/Iterator.map:(Lscala/Function1;)Lscala/collection/Iterator;
   22:	areturn
  LineNumberTable: 
   line 128: 0

  Signature: length = 0x2
   00 2B 

public int failureCount();
  Code:
   Stack=1, Locals=1, Args_size=1
   0:	aload_0
   1:	invokevirtual	#26; //Method buf:()Lscala/collection/mutable/ArrayBuffer;
   4:	invokeinterface	#50,  1; //InterfaceMethod scala/collection/mutable/ResizableArray.length:()I
   9:	ireturn
  LineNumberTable: 
   line 125: 0


public void addFailure(scala.testing.SUnit$Test, java.lang.Throwable);
  Code:
   Stack=5, Locals=3, Args_size=3
   0:	aload_0
   1:	invokevirtual	#26; //Method buf:()Lscala/collection/mutable/ArrayBuffer;
   4:	new	#54; //class scala/Tuple2
   7:	dup
   8:	aload_1
   9:	aload_2
   10:	invokespecial	#57; //Method scala/Tuple2."<init>":(Ljava/lang/Object;Ljava/lang/Object;)V
   13:	invokevirtual	#61; //Method scala/collection/mutable/ArrayBuffer.$plus$eq:(Ljava/lang/Object;)Lscala/collection/mutable/ArrayBuffer;
   16:	pop
   17:	return
  LineNumberTable: 
   line 121: 0

  LocalVariableTable: 
   Start  Length  Slot  Name   Signature
   0      18      0    this       Lscala/testing/SUnit$TestResult;
   0      18      1    test       Lscala/testing/SUnit$Test;
   0      18      2    t       Ljava/lang/Throwable;


public scala.collection.mutable.ArrayBuffer buf();
  Code:
   Stack=1, Locals=1, Args_size=1
   0:	aload_0
   1:	getfield	#21; //Field buf:Lscala/collection/mutable/ArrayBuffer;
   4:	areturn
  LineNumberTable: 
   line 118: 0

  Signature: length = 0x2
   00 45 

}

