Compiled from "SUnit.scala"
public final class scala.testing.SUnit$Assert$$anonfun$assertSameElementsXML$1 extends scala.runtime.AbstractFunction0 implements java.io.Serializable
  SourceFile: "SUnit.scala"
  Scala: length = 0x
   
  InnerClass: 
   public abstract Assert=class scala/testing/SUnit$Assert of class scala/testing/SUnit
   public final $anonfun$assertSameElementsXML$1=class scala/testing/SUnit$Assert$$anonfun$assertSameElementsXML$1 of class scala/testing/SUnit$Assert
  minor version: 0
  major version: 49
  Constant pool:
Asciz	SourceFile;
Asciz	SUnit.scala;
Asciz	<clinit>;
Asciz	()V;
Asciz	Code;
Asciz	serialVersionUID;
Asciz	J;
Asciz	scala/testing/SUnit$Assert$$anonfun$assertSameElementsXML$1;
class	scala/testing/SUnit$Assert$$anonfun$assertSameElementsXML$1
NameAndType	serialVersionUID:J
Field	scala/testing/SUnit$Assert$$anonfun$assertSameElementsXML$1.serialVersionUID:J
Asciz	actual$1;
Asciz	Lscala/collection/Seq;;
Asciz	expected$1;
Asciz	apply;
Asciz	()Ljava/lang/String;;
Asciz	scala/Predef$;
class	scala/Predef$
Asciz	MODULE$;
Asciz	Lscala/Predef$;;
NameAndType	MODULE$:Lscala/Predef$;
Field	scala/Predef$.MODULE$:Lscala/Predef$;
Asciz	LineNumberTable;
Asciz	\nassertSameElementsXML:\n  actual = %s\n  expected = %s;
String	\nassertSameElementsXML:\n  actual = %s\n  expected = %s
Asciz	augmentString;
Asciz	(Ljava/lang/String;)Lscala/collection/immutable/StringOps;;
NameAndType	augmentString:(Ljava/lang/String;)Lscala/collection/immutable/StringOps;
Method	scala/Predef$.augmentString:(Ljava/lang/String;)Lscala/collection/immutable/StringOps;
Asciz	java/lang/Object;
class	java/lang/Object
NameAndType	actual$1:Lscala/collection/Seq;
Field	scala/testing/SUnit$Assert$$anonfun$assertSameElementsXML$1.actual$1:Lscala/collection/Seq;
NameAndType	expected$1:Lscala/collection/Seq;
Field	scala/testing/SUnit$Assert$$anonfun$assertSameElementsXML$1.expected$1:Lscala/collection/Seq;
Asciz	genericWrapArray;
Asciz	(Ljava/lang/Object;)Lscala/collection/mutable/WrappedArray;;
NameAndType	genericWrapArray:(Ljava/lang/Object;)Lscala/collection/mutable/WrappedArray;
Method	scala/Predef$.genericWrapArray:(Ljava/lang/Object;)Lscala/collection/mutable/WrappedArray;
Asciz	scala/collection/immutable/StringLike;
class	scala/collection/immutable/StringLike
Asciz	format;
Asciz	(Lscala/collection/Seq;)Ljava/lang/String;;
NameAndType	format:(Lscala/collection/Seq;)Ljava/lang/String;
InterfaceMethod	scala/collection/immutable/StringLike.format:(Lscala/collection/Seq;)Ljava/lang/String;
Asciz	()Ljava/lang/Object;;
NameAndType	apply:()Ljava/lang/String;
Method	scala/testing/SUnit$Assert$$anonfun$assertSameElementsXML$1.apply:()Ljava/lang/String;
Asciz	<init>;
Asciz	(Lscala/testing/SUnit$Assert;Lscala/collection/Seq;Lscala/collection/Seq;)V;
Asciz	scala/runtime/AbstractFunction0;
class	scala/runtime/AbstractFunction0
NameAndType	"<init>":()V
Method	scala/runtime/AbstractFunction0."<init>":()V
Asciz	this;
Asciz	Lscala/testing/SUnit$Assert$$anonfun$assertSameElementsXML$1;;
Asciz	$outer;
Asciz	Lscala/testing/SUnit$Assert;;
Asciz	LocalVariableTable;
Asciz	Scala;
Asciz	InnerClasses;
Asciz	scala/testing/SUnit$Assert;
class	scala/testing/SUnit$Assert
Asciz	scala/testing/SUnit;
class	scala/testing/SUnit
Asciz	Assert;
Asciz	$anonfun$assertSameElementsXML$1;
Asciz	java/io/Serializable;
class	java/io/Serializable

{
public static final long serialVersionUID;
  Signature: J

public final scala.collection.Seq actual$1;
  Signature: Lscala/collection/Seq;

public final scala.collection.Seq expected$1;
  Signature: Lscala/collection/Seq;

public static {};
  Signature: ()V
  Code:
   Stack=2, Locals=0, Args_size=0
	lconst_0
	putstatic	Field serialVersionUID:J
	return
  Labels:

public final java.lang.String apply();
  Signature: ()Ljava/lang/String;
  Code:
   Stack=6, Locals=1, Args_size=1
	getstatic	Field scala/Predef$.MODULE$:Lscala/Predef$;
	ldc	String \nassertSameElementsXML:\n  actual = %s\n  expected = %s
	invokevirtual	Method scala/Predef$.augmentString:(Ljava/lang/String;)Lscala/collection/immutable/StringOps;
	getstatic	Field scala/Predef$.MODULE$:Lscala/Predef$;
	iconst_2
	anewarray	class java/lang/Object
	dup
	iconst_0
	aload_0
	getfield	Field actual$1:Lscala/collection/Seq;
	aastore
	dup
	iconst_1
	aload_0
	getfield	Field expected$1:Lscala/collection/Seq;
	aastore
	invokevirtual	Method scala/Predef$.genericWrapArray:(Ljava/lang/Object;)Lscala/collection/mutable/WrappedArray;
	invokeinterface	InterfaceMethod scala/collection/immutable/StringLike.format:(Lscala/collection/Seq;)Ljava/lang/String;
	areturn
  Labels:

public final java.lang.Object apply();
  Signature: ()Ljava/lang/Object;
  Code:
   Stack=1, Locals=1, Args_size=1
	aload_0
	invokevirtual	Method apply:()Ljava/lang/String;
	areturn
  Labels:

public scala.testing.SUnit$Assert$$anonfun$assertSameElementsXML$1(scala.testing.SUnit$Assert, scala.collection.Seq, scala.collection.Seq);
  Signature: (Lscala/testing/SUnit$Assert;Lscala/collection/Seq;Lscala/collection/Seq;)V
  Code:
   Stack=2, Locals=4, Args_size=4
	aload_0
	aload_2
	putfield	Field actual$1:Lscala/collection/Seq;
	aload_0
	aload_3
	putfield	Field expected$1:Lscala/collection/Seq;
	aload_0
	invokespecial	Method scala/runtime/AbstractFunction0."<init>":()V
	return
  Labels:
  LocalVariableTable: 
   Start  Length  Slot  Name   Signature
   0      15      0    this       Lscala/testing/SUnit$Assert$$anonfun$assertSameElementsXML$1;
   0      15      1    $outer       Lscala/testing/SUnit$Assert;


}

