Compiled from "SUnit.scala"
public class scala.testing.SUnit$TestFailure extends java.lang.Object implements scala.ScalaObject
  SourceFile: "SUnit.scala"
  Scala: length = 0x
   
  InnerClass: 
   public abstract #86= #72 of #85; //Test=class scala/testing/SUnit$Test of class scala/testing/SUnit
   public #87= #12 of #85; //TestFailure=class scala/testing/SUnit$TestFailure of class scala/testing/SUnit
  minor version: 0
  major version: 49
  Constant pool:
const #1 = Asciz	SourceFile;
const #2 = Asciz	SUnit.scala;
const #3 = Asciz	thrownException;
const #4 = Asciz	Ljava/lang/Throwable;;
const #5 = Asciz	failedTest;
const #6 = Asciz	Lscala/testing/SUnit$Test;;
const #7 = Asciz	<init>;
const #8 = Asciz	(Lscala/testing/SUnit$Test;Ljava/lang/Throwable;)V;
const #9 = Asciz	Code;
const #10 = Asciz	LineNumberTable;
const #11 = Asciz	scala/testing/SUnit$TestFailure;
const #12 = class	#11;	//  scala/testing/SUnit$TestFailure
const #13 = NameAndType	#5:#6;//  failedTest:Lscala/testing/SUnit$Test;
const #14 = Field	#12.#13;	//  scala/testing/SUnit$TestFailure.failedTest:Lscala/testing/SUnit$Test;
const #15 = NameAndType	#3:#4;//  thrownException:Ljava/lang/Throwable;
const #16 = Field	#12.#15;	//  scala/testing/SUnit$TestFailure.thrownException:Ljava/lang/Throwable;
const #17 = Asciz	java/lang/Object;
const #18 = class	#17;	//  java/lang/Object
const #19 = Asciz	()V;
const #20 = NameAndType	#7:#19;//  "<init>":()V
const #21 = Method	#18.#20;	//  java/lang/Object."<init>":()V
const #22 = Asciz	this;
const #23 = Asciz	Lscala/testing/SUnit$TestFailure;;
const #24 = Asciz	LocalVariableTable;
const #25 = Asciz	trace;
const #26 = Asciz	()Ljava/lang/String;;
const #27 = Asciz	scala/Predef$;
const #28 = class	#27;	//  scala/Predef$
const #29 = Asciz	MODULE$;
const #30 = Asciz	Lscala/Predef$;;
const #31 = NameAndType	#29:#30;//  MODULE$:Lscala/Predef$;
const #32 = Field	#28.#31;	//  scala/Predef$.MODULE$:Lscala/Predef$;
const #33 = Asciz	()Ljava/lang/Throwable;;
const #34 = NameAndType	#3:#33;//  thrownException:()Ljava/lang/Throwable;
const #35 = Method	#12.#34;	//  scala/testing/SUnit$TestFailure.thrownException:()Ljava/lang/Throwable;
const #36 = Asciz	exceptionWrapper;
const #37 = Asciz	(Ljava/lang/Throwable;)Lscala/runtime/RichException;;
const #38 = NameAndType	#36:#37;//  exceptionWrapper:(Ljava/lang/Throwable;)Lscala/runtime/RichException;
const #39 = Method	#28.#38;	//  scala/Predef$.exceptionWrapper:(Ljava/lang/Throwable;)Lscala/runtime/RichException;
const #40 = Asciz	scala/runtime/RichException;
const #41 = class	#40;	//  scala/runtime/RichException
const #42 = Asciz	getStackTraceString;
const #43 = NameAndType	#42:#26;//  getStackTraceString:()Ljava/lang/String;
const #44 = Method	#41.#43;	//  scala/runtime/RichException.getStackTraceString:()Ljava/lang/String;
const #45 = Asciz	toString;
const #46 = Asciz	scala/collection/mutable/StringBuilder;
const #47 = class	#46;	//  scala/collection/mutable/StringBuilder
const #48 = Method	#47.#20;	//  scala/collection/mutable/StringBuilder."<init>":()V
const #49 = Asciz	()Lscala/testing/SUnit$Test;;
const #50 = NameAndType	#5:#49;//  failedTest:()Lscala/testing/SUnit$Test;
const #51 = Method	#12.#50;	//  scala/testing/SUnit$TestFailure.failedTest:()Lscala/testing/SUnit$Test;
const #52 = NameAndType	#45:#26;//  toString:()Ljava/lang/String;
const #53 = Method	#18.#52;	//  java/lang/Object.toString:()Ljava/lang/String;
const #54 = Asciz	append;
const #55 = Asciz	(Ljava/lang/Object;)Lscala/collection/mutable/StringBuilder;;
const #56 = NameAndType	#54:#55;//  append:(Ljava/lang/Object;)Lscala/collection/mutable/StringBuilder;
const #57 = Method	#47.#56;	//  scala/collection/mutable/StringBuilder.append:(Ljava/lang/Object;)Lscala/collection/mutable/StringBuilder;
const #58 = Asciz	 failed due to ;
const #59 = String	#58;	//   failed due to 
const #60 = Asciz	java/lang/Throwable;
const #61 = class	#60;	//  java/lang/Throwable
const #62 = Method	#61.#52;	//  java/lang/Throwable.toString:()Ljava/lang/String;
const #63 = Method	#47.#52;	//  scala/collection/mutable/StringBuilder.toString:()Ljava/lang/String;
const #64 = Asciz	(Lscala/Tuple2;)V;
const #65 = Asciz	scala/Tuple2;
const #66 = class	#65;	//  scala/Tuple2
const #67 = Asciz	_1;
const #68 = Asciz	()Ljava/lang/Object;;
const #69 = NameAndType	#67:#68;//  _1:()Ljava/lang/Object;
const #70 = Method	#66.#69;	//  scala/Tuple2._1:()Ljava/lang/Object;
const #71 = Asciz	scala/testing/SUnit$Test;
const #72 = class	#71;	//  scala/testing/SUnit$Test
const #73 = Asciz	_2;
const #74 = NameAndType	#73:#68;//  _2:()Ljava/lang/Object;
const #75 = Method	#66.#74;	//  scala/Tuple2._2:()Ljava/lang/Object;
const #76 = NameAndType	#7:#8;//  "<init>":(Lscala/testing/SUnit$Test;Ljava/lang/Throwable;)V
const #77 = Method	#12.#76;	//  scala/testing/SUnit$TestFailure."<init>":(Lscala/testing/SUnit$Test;Ljava/lang/Throwable;)V
const #78 = Asciz	p;
const #79 = Asciz	Lscala/Tuple2;;
const #80 = Asciz	(Lscala/Tuple2<Lscala/testing/SUnit$Test;Ljava/lang/Throwable;>;)V;
const #81 = Asciz	Signature;
const #82 = Asciz	Scala;
const #83 = Asciz	InnerClasses;
const #84 = Asciz	scala/testing/SUnit;
const #85 = class	#84;	//  scala/testing/SUnit
const #86 = Asciz	Test;
const #87 = Asciz	TestFailure;
const #88 = Asciz	scala/ScalaObject;
const #89 = class	#88;	//  scala/ScalaObject

{
public scala.testing.SUnit$TestFailure(scala.testing.SUnit$Test, java.lang.Throwable);
  Code:
   Stack=2, Locals=3, Args_size=3
   0:	aload_0
   1:	aload_1
   2:	putfield	#14; //Field failedTest:Lscala/testing/SUnit$Test;
   5:	aload_0
   6:	aload_2
   7:	putfield	#16; //Field thrownException:Ljava/lang/Throwable;
   10:	aload_0
   11:	invokespecial	#21; //Method java/lang/Object."<init>":()V
   14:	return
  LineNumberTable: 
   line 105: 0

  LocalVariableTable: 
   Start  Length  Slot  Name   Signature
   0      15      0    this       Lscala/testing/SUnit$TestFailure;
   0      15      1    failedTest       Lscala/testing/SUnit$Test;
   0      15      2    thrownException       Ljava/lang/Throwable;


public java.lang.String trace();
  Code:
   Stack=2, Locals=1, Args_size=1
   0:	getstatic	#32; //Field scala/Predef$.MODULE$:Lscala/Predef$;
   3:	aload_0
   4:	invokevirtual	#35; //Method thrownException:()Ljava/lang/Throwable;
   7:	invokevirtual	#39; //Method scala/Predef$.exceptionWrapper:(Ljava/lang/Throwable;)Lscala/runtime/RichException;
   10:	invokevirtual	#44; //Method scala/runtime/RichException.getStackTraceString:()Ljava/lang/String;
   13:	areturn
  LineNumberTable: 
   line 112: 0


public java.lang.String toString();
  Code:
   Stack=2, Locals=1, Args_size=1
   0:	new	#47; //class scala/collection/mutable/StringBuilder
   3:	dup
   4:	invokespecial	#48; //Method scala/collection/mutable/StringBuilder."<init>":()V
   7:	aload_0
   8:	invokevirtual	#51; //Method failedTest:()Lscala/testing/SUnit$Test;
   11:	invokevirtual	#53; //Method java/lang/Object.toString:()Ljava/lang/String;
   14:	invokevirtual	#57; //Method scala/collection/mutable/StringBuilder.append:(Ljava/lang/Object;)Lscala/collection/mutable/StringBuilder;
   17:	ldc	#59; //String  failed due to 
   19:	invokevirtual	#57; //Method scala/collection/mutable/StringBuilder.append:(Ljava/lang/Object;)Lscala/collection/mutable/StringBuilder;
   22:	aload_0
   23:	invokevirtual	#35; //Method thrownException:()Ljava/lang/Throwable;
   26:	invokevirtual	#62; //Method java/lang/Throwable.toString:()Ljava/lang/String;
   29:	invokevirtual	#57; //Method scala/collection/mutable/StringBuilder.append:(Ljava/lang/Object;)Lscala/collection/mutable/StringBuilder;
   32:	invokevirtual	#63; //Method scala/collection/mutable/StringBuilder.toString:()Ljava/lang/String;
   35:	areturn
  LineNumberTable: 
   line 110: 0


public scala.testing.SUnit$TestFailure(scala.Tuple2);
  Code:
   Stack=3, Locals=2, Args_size=2
   0:	aload_0
   1:	aload_1
   2:	invokevirtual	#70; //Method scala/Tuple2._1:()Ljava/lang/Object;
   5:	checkcast	#72; //class scala/testing/SUnit$Test
   8:	aload_1
   9:	invokevirtual	#75; //Method scala/Tuple2._2:()Ljava/lang/Object;
   12:	checkcast	#61; //class java/lang/Throwable
   15:	invokespecial	#77; //Method "<init>":(Lscala/testing/SUnit$Test;Ljava/lang/Throwable;)V
   18:	return
  LineNumberTable: 
   line 107: 0

  LocalVariableTable: 
   Start  Length  Slot  Name   Signature
   0      19      0    this       Lscala/testing/SUnit$TestFailure;
   0      19      1    p       Lscala/Tuple2;

  Signature: length = 0x2
   00 50 

public java.lang.Throwable thrownException();
  Code:
   Stack=1, Locals=1, Args_size=1
   0:	aload_0
   1:	getfield	#16; //Field thrownException:Ljava/lang/Throwable;
   4:	areturn
  LineNumberTable: 
   line 105: 0


public scala.testing.SUnit$Test failedTest();
  Code:
   Stack=1, Locals=1, Args_size=1
   0:	aload_0
   1:	getfield	#14; //Field failedTest:Lscala/testing/SUnit$Test;
   4:	areturn
  LineNumberTable: 
   line 105: 0


}

