Compiled from "SUnit.scala"
public abstract class scala.testing.SUnit$TestCase extends java.lang.Object implements scala.testing.SUnit$Test,scala.testing.SUnit$Assert,scala.ScalaObject
  SourceFile: "SUnit.scala"
  Scala: length = 0x
   
  InnerClass: 
   public abstract #123= #120 of #122; //Test=class scala/testing/SUnit$Test of class scala/testing/SUnit
   public abstract #126= #125 of #122; //Assert=class scala/testing/SUnit$Assert of class scala/testing/SUnit
   public abstract #127= #10 of #122; //TestCase=class scala/testing/SUnit$TestCase of class scala/testing/SUnit
   public #128= #39 of #122; //TestResult=class scala/testing/SUnit$TestResult of class scala/testing/SUnit
  minor version: 0
  major version: 49
  Constant pool:
const #1 = Asciz	SourceFile;
const #2 = Asciz	SUnit.scala;
const #3 = Asciz	name;
const #4 = Asciz	Ljava/lang/String;;
const #5 = Asciz	<init>;
const #6 = Asciz	(Ljava/lang/String;)V;
const #7 = Asciz	Code;
const #8 = Asciz	LineNumberTable;
const #9 = Asciz	scala/testing/SUnit$TestCase;
const #10 = class	#9;	//  scala/testing/SUnit$TestCase
const #11 = NameAndType	#3:#4;//  name:Ljava/lang/String;
const #12 = Field	#10.#11;	//  scala/testing/SUnit$TestCase.name:Ljava/lang/String;
const #13 = Asciz	java/lang/Object;
const #14 = class	#13;	//  java/lang/Object
const #15 = Asciz	()V;
const #16 = NameAndType	#5:#15;//  "<init>":()V
const #17 = Method	#14.#16;	//  java/lang/Object."<init>":()V
const #18 = Asciz	scala/testing/SUnit$Assert$class;
const #19 = class	#18;	//  scala/testing/SUnit$Assert$class
const #20 = Asciz	$init$;
const #21 = Asciz	(Lscala/testing/SUnit$Assert;)V;
const #22 = NameAndType	#20:#21;//  $init$:(Lscala/testing/SUnit$Assert;)V
const #23 = Method	#19.#22;	//  scala/testing/SUnit$Assert$class.$init$:(Lscala/testing/SUnit$Assert;)V
const #24 = Asciz	this;
const #25 = Asciz	Lscala/testing/SUnit$TestCase;;
const #26 = Asciz	LocalVariableTable;
const #27 = Asciz	toString;
const #28 = Asciz	()Ljava/lang/String;;
const #29 = NameAndType	#3:#28;//  name:()Ljava/lang/String;
const #30 = Method	#10.#29;	//  scala/testing/SUnit$TestCase.name:()Ljava/lang/String;
const #31 = Asciz	tearDown;
const #32 = Asciz	setUp;
const #33 = Asciz	run;
const #34 = Asciz	(Lscala/testing/SUnit$TestResult;)V;
const #35 = Asciz	runTest;
const #36 = NameAndType	#35:#15;//  runTest:()V
const #37 = Method	#10.#36;	//  scala/testing/SUnit$TestCase.runTest:()V
const #38 = Asciz	scala/testing/SUnit$TestResult;
const #39 = class	#38;	//  scala/testing/SUnit$TestResult
const #40 = Asciz	addFailure;
const #41 = Asciz	(Lscala/testing/SUnit$Test;Ljava/lang/Throwable;)V;
const #42 = NameAndType	#40:#41;//  addFailure:(Lscala/testing/SUnit$Test;Ljava/lang/Throwable;)V
const #43 = Method	#39.#42;	//  scala/testing/SUnit$TestResult.addFailure:(Lscala/testing/SUnit$Test;Ljava/lang/Throwable;)V
const #44 = Asciz	java/lang/Throwable;
const #45 = class	#44;	//  java/lang/Throwable
const #46 = Asciz	r;
const #47 = Asciz	Lscala/testing/SUnit$TestResult;;
const #48 = Asciz	fail;
const #49 = Asciz	(Ljava/lang/String;Ljava/lang/Object;Ljava/lang/Object;)V;
const #50 = Asciz	(Lscala/testing/SUnit$Assert;Ljava/lang/String;Ljava/lang/Object;Ljava/lang/Object;)V;
const #51 = NameAndType	#48:#50;//  fail:(Lscala/testing/SUnit$Assert;Ljava/lang/String;Ljava/lang/Object;Ljava/lang/Object;)V
const #52 = Method	#19.#51;	//  scala/testing/SUnit$Assert$class.fail:(Lscala/testing/SUnit$Assert;Ljava/lang/String;Ljava/lang/Object;Ljava/lang/Object;)V
const #53 = Asciz	msg;
const #54 = Asciz	expected;
const #55 = Asciz	Ljava/lang/Object;;
const #56 = Asciz	actual;
const #57 = Asciz	(Lscala/testing/SUnit$Assert;Ljava/lang/String;)V;
const #58 = NameAndType	#48:#57;//  fail:(Lscala/testing/SUnit$Assert;Ljava/lang/String;)V
const #59 = Method	#19.#58;	//  scala/testing/SUnit$Assert$class.fail:(Lscala/testing/SUnit$Assert;Ljava/lang/String;)V
const #60 = Asciz	assertTrue;
const #61 = Asciz	(Z)V;
const #62 = Asciz	(Lscala/testing/SUnit$Assert;Z)V;
const #63 = NameAndType	#60:#62;//  assertTrue:(Lscala/testing/SUnit$Assert;Z)V
const #64 = Method	#19.#63;	//  scala/testing/SUnit$Assert$class.assertTrue:(Lscala/testing/SUnit$Assert;Z)V
const #65 = Asciz	Z;
const #66 = Asciz	(Ljava/lang/String;Z)V;
const #67 = Asciz	(Lscala/testing/SUnit$Assert;Ljava/lang/String;Z)V;
const #68 = NameAndType	#60:#67;//  assertTrue:(Lscala/testing/SUnit$Assert;Ljava/lang/String;Z)V
const #69 = Method	#19.#68;	//  scala/testing/SUnit$Assert$class.assertTrue:(Lscala/testing/SUnit$Assert;Ljava/lang/String;Z)V
const #70 = Asciz	assertEq;
const #71 = Asciz	(Ljava/lang/Object;Ljava/lang/Object;)V;
const #72 = Asciz	(Lscala/testing/SUnit$Assert;Ljava/lang/Object;Ljava/lang/Object;)V;
const #73 = NameAndType	#70:#72;//  assertEq:(Lscala/testing/SUnit$Assert;Ljava/lang/Object;Ljava/lang/Object;)V
const #74 = Method	#19.#73;	//  scala/testing/SUnit$Assert$class.assertEq:(Lscala/testing/SUnit$Assert;Ljava/lang/Object;Ljava/lang/Object;)V
const #75 = NameAndType	#70:#50;//  assertEq:(Lscala/testing/SUnit$Assert;Ljava/lang/String;Ljava/lang/Object;Ljava/lang/Object;)V
const #76 = Method	#19.#75;	//  scala/testing/SUnit$Assert$class.assertEq:(Lscala/testing/SUnit$Assert;Ljava/lang/String;Ljava/lang/Object;Ljava/lang/Object;)V
const #77 = Asciz	assertNull;
const #78 = Asciz	(Ljava/lang/Object;)V;
const #79 = Asciz	(Lscala/testing/SUnit$Assert;Ljava/lang/Object;)V;
const #80 = NameAndType	#77:#79;//  assertNull:(Lscala/testing/SUnit$Assert;Ljava/lang/Object;)V
const #81 = Method	#19.#80;	//  scala/testing/SUnit$Assert$class.assertNull:(Lscala/testing/SUnit$Assert;Ljava/lang/Object;)V
const #82 = Asciz	(Ljava/lang/String;Ljava/lang/Object;)V;
const #83 = Asciz	(Lscala/testing/SUnit$Assert;Ljava/lang/String;Ljava/lang/Object;)V;
const #84 = NameAndType	#77:#83;//  assertNull:(Lscala/testing/SUnit$Assert;Ljava/lang/String;Ljava/lang/Object;)V
const #85 = Method	#19.#84;	//  scala/testing/SUnit$Assert$class.assertNull:(Lscala/testing/SUnit$Assert;Ljava/lang/String;Ljava/lang/Object;)V
const #86 = Asciz	assertNotEq;
const #87 = NameAndType	#86:#72;//  assertNotEq:(Lscala/testing/SUnit$Assert;Ljava/lang/Object;Ljava/lang/Object;)V
const #88 = Method	#19.#87;	//  scala/testing/SUnit$Assert$class.assertNotEq:(Lscala/testing/SUnit$Assert;Ljava/lang/Object;Ljava/lang/Object;)V
const #89 = NameAndType	#86:#50;//  assertNotEq:(Lscala/testing/SUnit$Assert;Ljava/lang/String;Ljava/lang/Object;Ljava/lang/Object;)V
const #90 = Method	#19.#89;	//  scala/testing/SUnit$Assert$class.assertNotEq:(Lscala/testing/SUnit$Assert;Ljava/lang/String;Ljava/lang/Object;Ljava/lang/Object;)V
const #91 = Asciz	assertNotNull;
const #92 = NameAndType	#91:#79;//  assertNotNull:(Lscala/testing/SUnit$Assert;Ljava/lang/Object;)V
const #93 = Method	#19.#92;	//  scala/testing/SUnit$Assert$class.assertNotNull:(Lscala/testing/SUnit$Assert;Ljava/lang/Object;)V
const #94 = NameAndType	#91:#83;//  assertNotNull:(Lscala/testing/SUnit$Assert;Ljava/lang/String;Ljava/lang/Object;)V
const #95 = Method	#19.#94;	//  scala/testing/SUnit$Assert$class.assertNotNull:(Lscala/testing/SUnit$Assert;Ljava/lang/String;Ljava/lang/Object;)V
const #96 = Asciz	assertFalse;
const #97 = NameAndType	#96:#62;//  assertFalse:(Lscala/testing/SUnit$Assert;Z)V
const #98 = Method	#19.#97;	//  scala/testing/SUnit$Assert$class.assertFalse:(Lscala/testing/SUnit$Assert;Z)V
const #99 = NameAndType	#96:#67;//  assertFalse:(Lscala/testing/SUnit$Assert;Ljava/lang/String;Z)V
const #100 = Method	#19.#99;	//  scala/testing/SUnit$Assert$class.assertFalse:(Lscala/testing/SUnit$Assert;Ljava/lang/String;Z)V
const #101 = Asciz	assertEquals;
const #102 = NameAndType	#101:#72;//  assertEquals:(Lscala/testing/SUnit$Assert;Ljava/lang/Object;Ljava/lang/Object;)V
const #103 = Method	#19.#102;	//  scala/testing/SUnit$Assert$class.assertEquals:(Lscala/testing/SUnit$Assert;Ljava/lang/Object;Ljava/lang/Object;)V
const #104 = NameAndType	#101:#50;//  assertEquals:(Lscala/testing/SUnit$Assert;Ljava/lang/String;Ljava/lang/Object;Ljava/lang/Object;)V
const #105 = Method	#19.#104;	//  scala/testing/SUnit$Assert$class.assertEquals:(Lscala/testing/SUnit$Assert;Ljava/lang/String;Ljava/lang/Object;Ljava/lang/Object;)V
const #106 = Asciz	assertSameElements;
const #107 = Asciz	(Lscala/collection/Seq;Lscala/collection/Seq;)V;
const #108 = Asciz	(Lscala/testing/SUnit$Assert;Lscala/collection/Seq;Lscala/collection/Seq;)V;
const #109 = NameAndType	#106:#108;//  assertSameElements:(Lscala/testing/SUnit$Assert;Lscala/collection/Seq;Lscala/collection/Seq;)V
const #110 = Method	#19.#109;	//  scala/testing/SUnit$Assert$class.assertSameElements:(Lscala/testing/SUnit$Assert;Lscala/collection/Seq;Lscala/collection/Seq;)V
const #111 = Asciz	Lscala/collection/Seq;;
const #112 = Asciz	enableStackTrace;
const #113 = Asciz	()Z;
const #114 = Asciz	(Lscala/testing/SUnit$Assert;)Z;
const #115 = NameAndType	#112:#114;//  enableStackTrace:(Lscala/testing/SUnit$Assert;)Z
const #116 = Method	#19.#115;	//  scala/testing/SUnit$Assert$class.enableStackTrace:(Lscala/testing/SUnit$Assert;)Z
const #117 = Asciz	Scala;
const #118 = Asciz	InnerClasses;
const #119 = Asciz	scala/testing/SUnit$Test;
const #120 = class	#119;	//  scala/testing/SUnit$Test
const #121 = Asciz	scala/testing/SUnit;
const #122 = class	#121;	//  scala/testing/SUnit
const #123 = Asciz	Test;
const #124 = Asciz	scala/testing/SUnit$Assert;
const #125 = class	#124;	//  scala/testing/SUnit$Assert
const #126 = Asciz	Assert;
const #127 = Asciz	TestCase;
const #128 = Asciz	TestResult;
const #129 = Asciz	scala/ScalaObject;
const #130 = class	#129;	//  scala/ScalaObject

{
public scala.testing.SUnit$TestCase(java.lang.String);
  Code:
   Stack=2, Locals=2, Args_size=2
   0:	aload_0
   1:	aload_1
   2:	putfield	#12; //Field name:Ljava/lang/String;
   5:	aload_0
   6:	invokespecial	#17; //Method java/lang/Object."<init>":()V
   9:	aload_0
   10:	invokestatic	#23; //Method scala/testing/SUnit$Assert$class.$init$:(Lscala/testing/SUnit$Assert;)V
   13:	return
  LineNumberTable: 
   line 83: 0

  LocalVariableTable: 
   Start  Length  Slot  Name   Signature
   0      14      0    this       Lscala/testing/SUnit$TestCase;
   0      14      1    name       Ljava/lang/String;


public java.lang.String toString();
  Code:
   Stack=1, Locals=1, Args_size=1
   0:	aload_0
   1:	invokevirtual	#30; //Method name:()Ljava/lang/String;
   4:	areturn
  LineNumberTable: 
   line 99: 0


public void tearDown();
  Code:
   Stack=0, Locals=1, Args_size=1
   0:	return
  LineNumberTable: 
   line 97: 0


public void setUp();
  Code:
   Stack=0, Locals=1, Args_size=1
   0:	return
  LineNumberTable: 
   line 95: 0


public void run(scala.testing.SUnit$TestResult);
  Code:
   Stack=3, Locals=3, Args_size=2
   0:	aload_0
   1:	invokevirtual	#37; //Method runTest:()V
   4:	goto	14
   7:	astore_2
   8:	aload_1
   9:	aload_0
   10:	aload_2
   11:	invokevirtual	#43; //Method scala/testing/SUnit$TestResult.addFailure:(Lscala/testing/SUnit$Test;Ljava/lang/Throwable;)V
   14:	return
  Exception table:
   from   to  target type
     0     7     7   Class java/lang/Throwable

  LineNumberTable: 
   line 89: 0
   line 91: 7
   line 88: 14

  LocalVariableTable: 
   Start  Length  Slot  Name   Signature
   0      15      0    this       Lscala/testing/SUnit$TestCase;
   0      15      1    r       Lscala/testing/SUnit$TestResult;


public abstract void runTest();

public java.lang.String name();
  Code:
   Stack=1, Locals=1, Args_size=1
   0:	aload_0
   1:	getfield	#12; //Field name:Ljava/lang/String;
   4:	areturn
  LineNumberTable: 
   line 83: 0


public void fail(java.lang.String, java.lang.Object, java.lang.Object);
  Code:
   Stack=4, Locals=4, Args_size=4
   0:	aload_0
   1:	aload_1
   2:	aload_2
   3:	aload_3
   4:	invokestatic	#52; //Method scala/testing/SUnit$Assert$class.fail:(Lscala/testing/SUnit$Assert;Ljava/lang/String;Ljava/lang/Object;Ljava/lang/Object;)V
   7:	return
  LineNumberTable: 
   line 83: 0

  LocalVariableTable: 
   Start  Length  Slot  Name   Signature
   0      8      0    this       Lscala/testing/SUnit$TestCase;
   0      8      1    msg       Ljava/lang/String;
   0      8      2    expected       Ljava/lang/Object;
   0      8      3    actual       Ljava/lang/Object;


public void fail(java.lang.String);
  Code:
   Stack=2, Locals=2, Args_size=2
   0:	aload_0
   1:	aload_1
   2:	invokestatic	#59; //Method scala/testing/SUnit$Assert$class.fail:(Lscala/testing/SUnit$Assert;Ljava/lang/String;)V
   5:	return
  LineNumberTable: 
   line 83: 0

  LocalVariableTable: 
   Start  Length  Slot  Name   Signature
   0      6      0    this       Lscala/testing/SUnit$TestCase;
   0      6      1    msg       Ljava/lang/String;


public void assertTrue(boolean);
  Code:
   Stack=2, Locals=2, Args_size=2
   0:	aload_0
   1:	iload_1
   2:	invokestatic	#64; //Method scala/testing/SUnit$Assert$class.assertTrue:(Lscala/testing/SUnit$Assert;Z)V
   5:	return
  LineNumberTable: 
   line 83: 0

  LocalVariableTable: 
   Start  Length  Slot  Name   Signature
   0      6      0    this       Lscala/testing/SUnit$TestCase;
   0      6      1    actual       Z


public void assertTrue(java.lang.String, boolean);
  Code:
   Stack=3, Locals=3, Args_size=3
   0:	aload_0
   1:	aload_1
   2:	iload_2
   3:	invokestatic	#69; //Method scala/testing/SUnit$Assert$class.assertTrue:(Lscala/testing/SUnit$Assert;Ljava/lang/String;Z)V
   6:	return
  LineNumberTable: 
   line 83: 0

  LocalVariableTable: 
   Start  Length  Slot  Name   Signature
   0      7      0    this       Lscala/testing/SUnit$TestCase;
   0      7      1    msg       Ljava/lang/String;
   0      7      2    actual       Z


public void assertEq(java.lang.Object, java.lang.Object);
  Code:
   Stack=3, Locals=3, Args_size=3
   0:	aload_0
   1:	aload_1
   2:	aload_2
   3:	invokestatic	#74; //Method scala/testing/SUnit$Assert$class.assertEq:(Lscala/testing/SUnit$Assert;Ljava/lang/Object;Ljava/lang/Object;)V
   6:	return
  LineNumberTable: 
   line 83: 0

  LocalVariableTable: 
   Start  Length  Slot  Name   Signature
   0      7      0    this       Lscala/testing/SUnit$TestCase;
   0      7      1    expected       Ljava/lang/Object;
   0      7      2    actual       Ljava/lang/Object;


public void assertEq(java.lang.String, java.lang.Object, java.lang.Object);
  Code:
   Stack=4, Locals=4, Args_size=4
   0:	aload_0
   1:	aload_1
   2:	aload_2
   3:	aload_3
   4:	invokestatic	#76; //Method scala/testing/SUnit$Assert$class.assertEq:(Lscala/testing/SUnit$Assert;Ljava/lang/String;Ljava/lang/Object;Ljava/lang/Object;)V
   7:	return
  LineNumberTable: 
   line 83: 0

  LocalVariableTable: 
   Start  Length  Slot  Name   Signature
   0      8      0    this       Lscala/testing/SUnit$TestCase;
   0      8      1    msg       Ljava/lang/String;
   0      8      2    expected       Ljava/lang/Object;
   0      8      3    actual       Ljava/lang/Object;


public void assertNull(java.lang.Object);
  Code:
   Stack=2, Locals=2, Args_size=2
   0:	aload_0
   1:	aload_1
   2:	invokestatic	#81; //Method scala/testing/SUnit$Assert$class.assertNull:(Lscala/testing/SUnit$Assert;Ljava/lang/Object;)V
   5:	return
  LineNumberTable: 
   line 83: 0

  LocalVariableTable: 
   Start  Length  Slot  Name   Signature
   0      6      0    this       Lscala/testing/SUnit$TestCase;
   0      6      1    actual       Ljava/lang/Object;


public void assertNull(java.lang.String, java.lang.Object);
  Code:
   Stack=3, Locals=3, Args_size=3
   0:	aload_0
   1:	aload_1
   2:	aload_2
   3:	invokestatic	#85; //Method scala/testing/SUnit$Assert$class.assertNull:(Lscala/testing/SUnit$Assert;Ljava/lang/String;Ljava/lang/Object;)V
   6:	return
  LineNumberTable: 
   line 83: 0

  LocalVariableTable: 
   Start  Length  Slot  Name   Signature
   0      7      0    this       Lscala/testing/SUnit$TestCase;
   0      7      1    msg       Ljava/lang/String;
   0      7      2    actual       Ljava/lang/Object;


public void assertNotEq(java.lang.Object, java.lang.Object);
  Code:
   Stack=3, Locals=3, Args_size=3
   0:	aload_0
   1:	aload_1
   2:	aload_2
   3:	invokestatic	#88; //Method scala/testing/SUnit$Assert$class.assertNotEq:(Lscala/testing/SUnit$Assert;Ljava/lang/Object;Ljava/lang/Object;)V
   6:	return
  LineNumberTable: 
   line 83: 0

  LocalVariableTable: 
   Start  Length  Slot  Name   Signature
   0      7      0    this       Lscala/testing/SUnit$TestCase;
   0      7      1    expected       Ljava/lang/Object;
   0      7      2    actual       Ljava/lang/Object;


public void assertNotEq(java.lang.String, java.lang.Object, java.lang.Object);
  Code:
   Stack=4, Locals=4, Args_size=4
   0:	aload_0
   1:	aload_1
   2:	aload_2
   3:	aload_3
   4:	invokestatic	#90; //Method scala/testing/SUnit$Assert$class.assertNotEq:(Lscala/testing/SUnit$Assert;Ljava/lang/String;Ljava/lang/Object;Ljava/lang/Object;)V
   7:	return
  LineNumberTable: 
   line 83: 0

  LocalVariableTable: 
   Start  Length  Slot  Name   Signature
   0      8      0    this       Lscala/testing/SUnit$TestCase;
   0      8      1    msg       Ljava/lang/String;
   0      8      2    expected       Ljava/lang/Object;
   0      8      3    actual       Ljava/lang/Object;


public void assertNotNull(java.lang.Object);
  Code:
   Stack=2, Locals=2, Args_size=2
   0:	aload_0
   1:	aload_1
   2:	invokestatic	#93; //Method scala/testing/SUnit$Assert$class.assertNotNull:(Lscala/testing/SUnit$Assert;Ljava/lang/Object;)V
   5:	return
  LineNumberTable: 
   line 83: 0

  LocalVariableTable: 
   Start  Length  Slot  Name   Signature
   0      6      0    this       Lscala/testing/SUnit$TestCase;
   0      6      1    actual       Ljava/lang/Object;


public void assertNotNull(java.lang.String, java.lang.Object);
  Code:
   Stack=3, Locals=3, Args_size=3
   0:	aload_0
   1:	aload_1
   2:	aload_2
   3:	invokestatic	#95; //Method scala/testing/SUnit$Assert$class.assertNotNull:(Lscala/testing/SUnit$Assert;Ljava/lang/String;Ljava/lang/Object;)V
   6:	return
  LineNumberTable: 
   line 83: 0

  LocalVariableTable: 
   Start  Length  Slot  Name   Signature
   0      7      0    this       Lscala/testing/SUnit$TestCase;
   0      7      1    msg       Ljava/lang/String;
   0      7      2    actual       Ljava/lang/Object;


public void assertFalse(boolean);
  Code:
   Stack=2, Locals=2, Args_size=2
   0:	aload_0
   1:	iload_1
   2:	invokestatic	#98; //Method scala/testing/SUnit$Assert$class.assertFalse:(Lscala/testing/SUnit$Assert;Z)V
   5:	return
  LineNumberTable: 
   line 83: 0

  LocalVariableTable: 
   Start  Length  Slot  Name   Signature
   0      6      0    this       Lscala/testing/SUnit$TestCase;
   0      6      1    actual       Z


public void assertFalse(java.lang.String, boolean);
  Code:
   Stack=3, Locals=3, Args_size=3
   0:	aload_0
   1:	aload_1
   2:	iload_2
   3:	invokestatic	#100; //Method scala/testing/SUnit$Assert$class.assertFalse:(Lscala/testing/SUnit$Assert;Ljava/lang/String;Z)V
   6:	return
  LineNumberTable: 
   line 83: 0

  LocalVariableTable: 
   Start  Length  Slot  Name   Signature
   0      7      0    this       Lscala/testing/SUnit$TestCase;
   0      7      1    msg       Ljava/lang/String;
   0      7      2    actual       Z


public void assertEquals(java.lang.Object, java.lang.Object);
  Code:
   Stack=3, Locals=3, Args_size=3
   0:	aload_0
   1:	aload_1
   2:	aload_2
   3:	invokestatic	#103; //Method scala/testing/SUnit$Assert$class.assertEquals:(Lscala/testing/SUnit$Assert;Ljava/lang/Object;Ljava/lang/Object;)V
   6:	return
  LineNumberTable: 
   line 83: 0

  LocalVariableTable: 
   Start  Length  Slot  Name   Signature
   0      7      0    this       Lscala/testing/SUnit$TestCase;
   0      7      1    expected       Ljava/lang/Object;
   0      7      2    actual       Ljava/lang/Object;


public void assertEquals(java.lang.String, java.lang.Object, java.lang.Object);
  Code:
   Stack=4, Locals=4, Args_size=4
   0:	aload_0
   1:	aload_1
   2:	aload_2
   3:	aload_3
   4:	invokestatic	#105; //Method scala/testing/SUnit$Assert$class.assertEquals:(Lscala/testing/SUnit$Assert;Ljava/lang/String;Ljava/lang/Object;Ljava/lang/Object;)V
   7:	return
  LineNumberTable: 
   line 83: 0

  LocalVariableTable: 
   Start  Length  Slot  Name   Signature
   0      8      0    this       Lscala/testing/SUnit$TestCase;
   0      8      1    msg       Ljava/lang/String;
   0      8      2    expected       Ljava/lang/Object;
   0      8      3    actual       Ljava/lang/Object;


public void assertSameElements(scala.collection.Seq, scala.collection.Seq);
  Code:
   Stack=3, Locals=3, Args_size=3
   0:	aload_0
   1:	aload_1
   2:	aload_2
   3:	invokestatic	#110; //Method scala/testing/SUnit$Assert$class.assertSameElements:(Lscala/testing/SUnit$Assert;Lscala/collection/Seq;Lscala/collection/Seq;)V
   6:	return
  LineNumberTable: 
   line 83: 0

  LocalVariableTable: 
   Start  Length  Slot  Name   Signature
   0      7      0    this       Lscala/testing/SUnit$TestCase;
   0      7      1    actual       Lscala/collection/Seq;
   0      7      2    expected       Lscala/collection/Seq;


public boolean enableStackTrace();
  Code:
   Stack=1, Locals=1, Args_size=1
   0:	aload_0
   1:	invokestatic	#116; //Method scala/testing/SUnit$Assert$class.enableStackTrace:(Lscala/testing/SUnit$Assert;)Z
   4:	ireturn
  LineNumberTable: 
   line 83: 0


}

