Compiled from "SUnit.scala"
public final class scala.testing.SUnit$AssertFailed$ extends java.lang.Object implements scala.Function2,scala.ScalaObject
  SourceFile: "SUnit.scala"
  Scala: length = 0x
   
  InnerClass: 
   public AssertFailed=class scala/testing/SUnit$AssertFailed of class scala/testing/SUnit
   public final $anonfun$1=class scala/testing/SUnit$AssertFailed$$anonfun$1 of class scala/testing/SUnit$AssertFailed
  minor version: 0
  major version: 49
  Constant pool:
Asciz	SourceFile;
Asciz	SUnit.scala;
Asciz	Scala;
Asciz	MODULE$;
Asciz	Lscala/testing/SUnit$AssertFailed$;;
Asciz	<clinit>;
Asciz	()V;
Asciz	Code;
Asciz	scala/testing/SUnit$AssertFailed$;
class	scala/testing/SUnit$AssertFailed$
Asciz	<init>;
NameAndType	"<init>":()V
Method	scala/testing/SUnit$AssertFailed$."<init>":()V
Asciz	LineNumberTable;
Asciz	java/lang/Object;
class	java/lang/Object
Method	java/lang/Object."<init>":()V
NameAndType	MODULE$:Lscala/testing/SUnit$AssertFailed$;
Field	scala/testing/SUnit$AssertFailed$.MODULE$:Lscala/testing/SUnit$AssertFailed$;
Asciz	scala/Function2$class;
class	scala/Function2$class
Asciz	$init$;
Asciz	(Lscala/Function2;)V;
NameAndType	$init$:(Lscala/Function2;)V
Method	scala/Function2$class.$init$:(Lscala/Function2;)V
Asciz	apply;
Asciz	(Ljava/lang/Object;Ljava/lang/Object;)Ljava/lang/Object;;
Asciz	java/lang/String;
class	java/lang/String
Asciz	scala/runtime/BoxesRunTime;
class	scala/runtime/BoxesRunTime
Asciz	unboxToBoolean;
Asciz	(Ljava/lang/Object;)Z;
NameAndType	unboxToBoolean:(Ljava/lang/Object;)Z
Method	scala/runtime/BoxesRunTime.unboxToBoolean:(Ljava/lang/Object;)Z
Asciz	(Ljava/lang/String;Z)Lscala/testing/SUnit$AssertFailed;;
NameAndType	apply:(Ljava/lang/String;Z)Lscala/testing/SUnit$AssertFailed;
Method	scala/testing/SUnit$AssertFailed$.apply:(Ljava/lang/String;Z)Lscala/testing/SUnit$AssertFailed;
Asciz	this;
Asciz	v1;
Asciz	Ljava/lang/Object;;
Asciz	v2;
Asciz	LocalVariableTable;
Asciz	scala/testing/SUnit$AssertFailed;
class	scala/testing/SUnit$AssertFailed
Asciz	(Ljava/lang/String;Z)V;
NameAndType	"<init>":(Ljava/lang/String;Z)V
Method	scala/testing/SUnit$AssertFailed."<init>":(Ljava/lang/String;Z)V
Asciz	msg;
Asciz	Ljava/lang/String;;
Asciz	stackTrace;
Asciz	Z;
Asciz	unapply;
Asciz	(Lscala/testing/SUnit$AssertFailed;)Lscala/Some;;
Asciz	scala/Some;
class	scala/Some
Asciz	scala/Tuple2;
class	scala/Tuple2
Asciz	()Ljava/lang/String;;
NameAndType	msg:()Ljava/lang/String;
Method	scala/testing/SUnit$AssertFailed.msg:()Ljava/lang/String;
Asciz	()Z;
NameAndType	stackTrace:()Z
Method	scala/testing/SUnit$AssertFailed.stackTrace:()Z
Asciz	boxToBoolean;
Asciz	(Z)Ljava/lang/Boolean;;
NameAndType	boxToBoolean:(Z)Ljava/lang/Boolean;
Method	scala/runtime/BoxesRunTime.boxToBoolean:(Z)Ljava/lang/Boolean;
Asciz	(Ljava/lang/Object;Ljava/lang/Object;)V;
NameAndType	"<init>":(Ljava/lang/Object;Ljava/lang/Object;)V
Method	scala/Tuple2."<init>":(Ljava/lang/Object;Ljava/lang/Object;)V
Asciz	(Ljava/lang/Object;)V;
NameAndType	"<init>":(Ljava/lang/Object;)V
Method	scala/Some."<init>":(Ljava/lang/Object;)V
Asciz	x$0;
Asciz	Lscala/testing/SUnit$AssertFailed;;
Asciz	tupled;
Asciz	()Lscala/Function1;;
Asciz	(Lscala/Function2;)Lscala/Function1;;
NameAndType	tupled:(Lscala/Function2;)Lscala/Function1;
Method	scala/Function2$class.tupled:(Lscala/Function2;)Lscala/Function1;
Asciz	curry;
NameAndType	curry:(Lscala/Function2;)Lscala/Function1;
Method	scala/Function2$class.curry:(Lscala/Function2;)Lscala/Function1;
Asciz	Deprecated;
Asciz	curried;
NameAndType	curried:(Lscala/Function2;)Lscala/Function1;
Method	scala/Function2$class.curried:(Lscala/Function2;)Lscala/Function1;
Asciz	toString;
Asciz	(Lscala/Function2;)Ljava/lang/String;;
NameAndType	toString:(Lscala/Function2;)Ljava/lang/String;
Method	scala/Function2$class.toString:(Lscala/Function2;)Ljava/lang/String;
Asciz	InnerClasses;
Asciz	scala/testing/SUnit;
class	scala/testing/SUnit
Asciz	AssertFailed;
Asciz	scala/testing/SUnit$AssertFailed$$anonfun$1;
class	scala/testing/SUnit$AssertFailed$$anonfun$1
Asciz	$anonfun$1;
Asciz	scala/Function2;
class	scala/Function2
Asciz	scala/ScalaObject;
class	scala/ScalaObject

{
public static final scala.testing.SUnit$AssertFailed$ MODULE$;
  Signature: Lscala/testing/SUnit$AssertFailed$;

public static {};
  Signature: ()V
  Code:
   Stack=1, Locals=0, Args_size=0
	new	class scala/testing/SUnit$AssertFailed$
	invokespecial	Method "<init>":()V
	return
  Labels:

public scala.testing.SUnit$AssertFailed$();
  Signature: ()V
  Code:
   Stack=1, Locals=1, Args_size=1
	aload_0
	invokespecial	Method java/lang/Object."<init>":()V
	aload_0
	putstatic	Field MODULE$:Lscala/testing/SUnit$AssertFailed$;
	aload_0
	invokestatic	Method scala/Function2$class.$init$:(Lscala/Function2;)V
	return
  Labels:

public java.lang.Object apply(java.lang.Object, java.lang.Object);
  Signature: (Ljava/lang/Object;Ljava/lang/Object;)Ljava/lang/Object;
  Code:
   Stack=3, Locals=3, Args_size=3
	aload_0
	aload_1
	checkcast	class java/lang/String
	aload_2
	invokestatic	Method scala/runtime/BoxesRunTime.unboxToBoolean:(Ljava/lang/Object;)Z
	invokevirtual	Method apply:(Ljava/lang/String;Z)Lscala/testing/SUnit$AssertFailed;
	areturn
  Labels:
  LocalVariableTable: 
   Start  Length  Slot  Name   Signature
   0      13      0    this       Lscala/testing/SUnit$AssertFailed$;
   0      13      1    v1       Ljava/lang/Object;
   0      13      2    v2       Ljava/lang/Object;


public scala.testing.SUnit$AssertFailed apply(java.lang.String, boolean);
  Signature: (Ljava/lang/String;Z)Lscala/testing/SUnit$AssertFailed;
  Code:
   Stack=4, Locals=3, Args_size=3
	new	class scala/testing/SUnit$AssertFailed
	dup
	aload_1
	iload_2
	invokespecial	Method scala/testing/SUnit$AssertFailed."<init>":(Ljava/lang/String;Z)V
	areturn
  Labels:
  LocalVariableTable: 
   Start  Length  Slot  Name   Signature
   0      10      0    this       Lscala/testing/SUnit$AssertFailed$;
   0      10      1    msg       Ljava/lang/String;
   0      10      2    stackTrace       Z


public scala.Some unapply(scala.testing.SUnit$AssertFailed);
  Signature: (Lscala/testing/SUnit$AssertFailed;)Lscala/Some;
  Code:
   Stack=6, Locals=3, Args_size=2
	new	class scala/Some
	dup
	new	class scala/Tuple2
	dup
	aload_1
	invokevirtual	Method scala/testing/SUnit$AssertFailed.msg:()Ljava/lang/String;
	aload_1
	invokevirtual	Method scala/testing/SUnit$AssertFailed.stackTrace:()Z
	istore_2
	iload_2
	invokestatic	Method scala/runtime/BoxesRunTime.boxToBoolean:(Z)Ljava/lang/Boolean;
	invokespecial	Method scala/Tuple2."<init>":(Ljava/lang/Object;Ljava/lang/Object;)V
	invokespecial	Method scala/Some."<init>":(Ljava/lang/Object;)V
	areturn
  Labels:
  LocalVariableTable: 
   Start  Length  Slot  Name   Signature
   0      28      0    this       Lscala/testing/SUnit$AssertFailed$;
   0      28      1    x$0       Lscala/testing/SUnit$AssertFailed;


public scala.Function1 tupled();
  Signature: ()Lscala/Function1;
  Code:
   Stack=1, Locals=1, Args_size=1
	aload_0
	invokestatic	Method scala/Function2$class.tupled:(Lscala/Function2;)Lscala/Function1;
	areturn
  Labels:

public scala.Function1 curry();
  Signature: ()Lscala/Function1;
  Code:
   Stack=1, Locals=1, Args_size=1
	aload_0
	invokestatic	Method scala/Function2$class.curry:(Lscala/Function2;)Lscala/Function1;
	areturn
  Labels:
  Deprecated: true

public scala.Function1 curried();
  Signature: ()Lscala/Function1;
  Code:
   Stack=1, Locals=1, Args_size=1
	aload_0
	invokestatic	Method scala/Function2$class.curried:(Lscala/Function2;)Lscala/Function1;
	areturn
  Labels:

public java.lang.String toString();
  Signature: ()Ljava/lang/String;
  Code:
   Stack=1, Locals=1, Args_size=1
	aload_0
	invokestatic	Method scala/Function2$class.toString:(Lscala/Function2;)Ljava/lang/String;
	areturn
  Labels:

}

