Compiled from "SUnit.scala"
public class scala.testing.SUnit$AssertFailed extends java.lang.RuntimeException implements scala.ScalaObject,scala.Product,java.io.Serializable
  SourceFile: "SUnit.scala"
  Scala: length = 0x
   
  InnerClass: 
   public AssertFailed=class scala/testing/SUnit$AssertFailed of class scala/testing/SUnit
   public final $anonfun$1=class scala/testing/SUnit$AssertFailed$$anonfun$1 of class scala/testing/SUnit$AssertFailed
  minor version: 0
  major version: 49
  Constant pool:
Asciz	SourceFile;
Asciz	SUnit.scala;
Asciz	msg0;
Asciz	Ljava/lang/String;;
Asciz	stackTrace;
Asciz	Z;
Asciz	msg;
Asciz	<init>;
Asciz	(Ljava/lang/String;Z)V;
Asciz	Code;
Asciz	LineNumberTable;
Asciz	scala/testing/SUnit$AssertFailed;
class	scala/testing/SUnit$AssertFailed
NameAndType	msg:Ljava/lang/String;
Field	scala/testing/SUnit$AssertFailed.msg:Ljava/lang/String;
NameAndType	stackTrace:Z
Field	scala/testing/SUnit$AssertFailed.stackTrace:Z
Asciz	java/lang/RuntimeException;
class	java/lang/RuntimeException
Asciz	()V;
NameAndType	"<init>":()V
Method	java/lang/RuntimeException."<init>":()V
Asciz	scala/Product$class;
class	scala/Product$class
Asciz	$init$;
Asciz	(Lscala/Product;)V;
NameAndType	$init$:(Lscala/Product;)V
Method	scala/Product$class.$init$:(Lscala/Product;)V
Asciz	scala/Predef$;
class	scala/Predef$
Asciz	MODULE$;
Asciz	Lscala/Predef$;;
NameAndType	MODULE$:Lscala/Predef$;
Field	scala/Predef$.MODULE$:Lscala/Predef$;
Asciz	java/lang/Throwable;
class	java/lang/Throwable
Asciz	getStackTrace;
Asciz	()[Ljava/lang/StackTraceElement;;
NameAndType	getStackTrace:()[Ljava/lang/StackTraceElement;
Method	java/lang/Throwable.getStackTrace:()[Ljava/lang/StackTraceElement;
Asciz	[Ljava/lang/Object;;
class	"[Ljava/lang/Object;"
Asciz	refArrayOps;
Asciz	([Ljava/lang/Object;)Lscala/collection/mutable/ArrayOps;;
NameAndType	refArrayOps:([Ljava/lang/Object;)Lscala/collection/mutable/ArrayOps;
Method	scala/Predef$.refArrayOps:([Ljava/lang/Object;)Lscala/collection/mutable/ArrayOps;
Asciz	scala/testing/SUnit$AssertFailed$$anonfun$1;
class	scala/testing/SUnit$AssertFailed$$anonfun$1
Asciz	(Lscala/testing/SUnit$AssertFailed;)V;
NameAndType	"<init>":(Lscala/testing/SUnit$AssertFailed;)V
Method	scala/testing/SUnit$AssertFailed$$anonfun$1."<init>":(Lscala/testing/SUnit$AssertFailed;)V
Asciz	scala/Array$;
class	scala/Array$
Asciz	Lscala/Array$;;
NameAndType	MODULE$:Lscala/Array$;
Field	scala/Array$.MODULE$:Lscala/Array$;
Asciz	scala/reflect/ClassManifest$;
class	scala/reflect/ClassManifest$
Asciz	Lscala/reflect/ClassManifest$;;
NameAndType	MODULE$:Lscala/reflect/ClassManifest$;
Field	scala/reflect/ClassManifest$.MODULE$:Lscala/reflect/ClassManifest$;
Asciz	java/lang/String;
class	java/lang/String
Asciz	classType;
Asciz	(Ljava/lang/Class;)Lscala/reflect/ClassManifest;;
NameAndType	classType:(Ljava/lang/Class;)Lscala/reflect/ClassManifest;
Method	scala/reflect/ClassManifest$.classType:(Ljava/lang/Class;)Lscala/reflect/ClassManifest;
Asciz	canBuildFrom;
Asciz	(Lscala/reflect/ClassManifest;)Lscala/collection/generic/CanBuildFrom;;
NameAndType	canBuildFrom:(Lscala/reflect/ClassManifest;)Lscala/collection/generic/CanBuildFrom;
Method	scala/Array$.canBuildFrom:(Lscala/reflect/ClassManifest;)Lscala/collection/generic/CanBuildFrom;
Asciz	scala/collection/TraversableLike;
class	scala/collection/TraversableLike
Asciz	map;
Asciz	(Lscala/Function1;Lscala/collection/generic/CanBuildFrom;)Ljava/lang/Object;;
NameAndType	map:(Lscala/Function1;Lscala/collection/generic/CanBuildFrom;)Ljava/lang/Object;
InterfaceMethod	scala/collection/TraversableLike.map:(Lscala/Function1;Lscala/collection/generic/CanBuildFrom;)Ljava/lang/Object;
Asciz	mkString;
Asciz	()Ljava/lang/String;;
NameAndType	mkString:()Ljava/lang/String;
InterfaceMethod	scala/collection/TraversableLike.mkString:()Ljava/lang/String;
NameAndType	msg0:Ljava/lang/String;
Field	scala/testing/SUnit$AssertFailed.msg0:Ljava/lang/String;
Asciz	this;
Asciz	Lscala/testing/SUnit$AssertFailed;;
Asciz	LocalVariableTable;
Asciz	gd1$1;
Asciz	(Ljava/lang/String;Z)Z;
NameAndType	msg:()Ljava/lang/String;
Method	scala/testing/SUnit$AssertFailed.msg:()Ljava/lang/String;
Asciz	java/lang/Object;
class	java/lang/Object
Asciz	equals;
Asciz	(Ljava/lang/Object;)Z;
NameAndType	equals:(Ljava/lang/Object;)Z
Method	java/lang/Object.equals:(Ljava/lang/Object;)Z
Asciz	()Z;
NameAndType	stackTrace:()Z
Method	scala/testing/SUnit$AssertFailed.stackTrace:()Z
Asciz	canEqual;
Asciz	productElement;
Asciz	(I)Ljava/lang/Object;;
Asciz	java/lang/IndexOutOfBoundsException;
class	java/lang/IndexOutOfBoundsException
Asciz	scala/runtime/BoxesRunTime;
class	scala/runtime/BoxesRunTime
Asciz	boxToInteger;
Asciz	(I)Ljava/lang/Integer;;
NameAndType	boxToInteger:(I)Ljava/lang/Integer;
Method	scala/runtime/BoxesRunTime.boxToInteger:(I)Ljava/lang/Integer;
Asciz	toString;
NameAndType	toString:()Ljava/lang/String;
Method	java/lang/Object.toString:()Ljava/lang/String;
Asciz	(Ljava/lang/String;)V;
NameAndType	"<init>":(Ljava/lang/String;)V
Method	java/lang/IndexOutOfBoundsException."<init>":(Ljava/lang/String;)V
Asciz	boxToBoolean;
Asciz	(Z)Ljava/lang/Boolean;;
NameAndType	boxToBoolean:(Z)Ljava/lang/Boolean;
Method	scala/runtime/BoxesRunTime.boxToBoolean:(Z)Ljava/lang/Boolean;
Asciz	productArity;
Asciz	()I;
Asciz	productPrefix;
Asciz	AssertFailed;
String	AssertFailed
NameAndType	gd1$1:(Ljava/lang/String;Z)Z
Method	scala/testing/SUnit$AssertFailed.gd1$1:(Ljava/lang/String;Z)Z
Asciz	scala/Equals;
class	scala/Equals
NameAndType	canEqual:(Ljava/lang/Object;)Z
InterfaceMethod	scala/Equals.canEqual:(Ljava/lang/Object;)Z
Asciz	temp2;
Asciz	temp3;
Asciz	temp4;
Asciz	hashCode;
Asciz	scala/runtime/ScalaRunTime$;
class	scala/runtime/ScalaRunTime$
Asciz	Lscala/runtime/ScalaRunTime$;;
NameAndType	MODULE$:Lscala/runtime/ScalaRunTime$;
Field	scala/runtime/ScalaRunTime$.MODULE$:Lscala/runtime/ScalaRunTime$;
Asciz	_hashCode;
Asciz	(Lscala/Product;)I;
NameAndType	_hashCode:(Lscala/Product;)I
Method	scala/runtime/ScalaRunTime$._hashCode:(Lscala/Product;)I
Asciz	copy;
Asciz	(Ljava/lang/String;Z)Lscala/testing/SUnit$AssertFailed;;
NameAndType	"<init>":(Ljava/lang/String;Z)V
Method	scala/testing/SUnit$AssertFailed."<init>":(Ljava/lang/String;Z)V
NameAndType	msg0:()Ljava/lang/String;
Method	scala/testing/SUnit$AssertFailed.msg0:()Ljava/lang/String;
Asciz	scala/collection/mutable/StringBuilder;
class	scala/collection/mutable/StringBuilder
Method	scala/collection/mutable/StringBuilder."<init>":()V
Asciz	failed assertion: ;
String	failed assertion: 
Asciz	append;
Asciz	(Ljava/lang/Object;)Lscala/collection/mutable/StringBuilder;;
NameAndType	append:(Ljava/lang/Object;)Lscala/collection/mutable/StringBuilder;
Method	scala/collection/mutable/StringBuilder.append:(Ljava/lang/Object;)Lscala/collection/mutable/StringBuilder;
Method	scala/collection/mutable/StringBuilder.toString:()Ljava/lang/String;
Asciz	copy$default$1;
Asciz	copy$default$2;
Asciz	productElements;
Asciz	()Lscala/collection/Iterator;;
Asciz	(Lscala/Product;)Lscala/collection/Iterator;;
NameAndType	productElements:(Lscala/Product;)Lscala/collection/Iterator;
Method	scala/Product$class.productElements:(Lscala/Product;)Lscala/collection/Iterator;
Asciz	Deprecated;
Asciz	productIterator;
NameAndType	productIterator:(Lscala/Product;)Lscala/collection/Iterator;
Method	scala/Product$class.productIterator:(Lscala/Product;)Lscala/collection/Iterator;
Asciz	Scala;
Asciz	InnerClasses;
Asciz	scala/testing/SUnit;
class	scala/testing/SUnit
Asciz	$anonfun$1;
Asciz	scala/ScalaObject;
class	scala/ScalaObject
Asciz	scala/Product;
class	scala/Product
Asciz	java/io/Serializable;
class	java/io/Serializable

{
private final java.lang.String msg0;
  Signature: Ljava/lang/String;

private final boolean stackTrace;
  Signature: Z

private final java.lang.String msg;
  Signature: Ljava/lang/String;

public scala.testing.SUnit$AssertFailed(java.lang.String, boolean);
  Signature: (Ljava/lang/String;Z)V
  Code:
   Stack=7, Locals=3, Args_size=3
	aload_0
	aload_1
	putfield	Field msg:Ljava/lang/String;
	aload_0
	iload_2
	putfield	Field stackTrace:Z
	aload_0
	invokespecial	Method java/lang/RuntimeException."<init>":()V
	aload_0
	invokestatic	Method scala/Product$class.$init$:(Lscala/Product;)V
	aload_0
	iload_2
	ifeq	l1 // aload_1
	getstatic	Field scala/Predef$.MODULE$:Lscala/Predef$;
	getstatic	Field scala/Predef$.MODULE$:Lscala/Predef$;
	aload_0
	invokespecial	Method java/lang/Throwable.getStackTrace:()[Ljava/lang/StackTraceElement;
	checkcast	class "[Ljava/lang/Object;"
	invokevirtual	Method scala/Predef$.refArrayOps:([Ljava/lang/Object;)Lscala/collection/mutable/ArrayOps;
	new	class scala/testing/SUnit$AssertFailed$$anonfun$1
	dup
	aload_0
	invokespecial	Method scala/testing/SUnit$AssertFailed$$anonfun$1."<init>":(Lscala/testing/SUnit$AssertFailed;)V
	getstatic	Field scala/Array$.MODULE$:Lscala/Array$;
	getstatic	Field scala/reflect/ClassManifest$.MODULE$:Lscala/reflect/ClassManifest$;
	ldc	class java/lang/String
	invokevirtual	Method scala/reflect/ClassManifest$.classType:(Ljava/lang/Class;)Lscala/reflect/ClassManifest;
	invokevirtual	Method scala/Array$.canBuildFrom:(Lscala/reflect/ClassManifest;)Lscala/collection/generic/CanBuildFrom;
	invokeinterface	InterfaceMethod scala/collection/TraversableLike.map:(Lscala/Function1;Lscala/collection/generic/CanBuildFrom;)Ljava/lang/Object;
	checkcast	class "[Ljava/lang/Object;"
	invokevirtual	Method scala/Predef$.refArrayOps:([Ljava/lang/Object;)Lscala/collection/mutable/ArrayOps;
	invokeinterface	InterfaceMethod scala/collection/TraversableLike.mkString:()Ljava/lang/String;
	goto	l2 // putfield
l1	aload_1
l2	putfield	Field msg0:Ljava/lang/String;
	return
  Labels:
   	l1 = 80 // aload_1
   	l2 = 81 // putfield
  LocalVariableTable: 
   Start  Length  Slot  Name   Signature
   0      85      0    this       Lscala/testing/SUnit$AssertFailed;
   0      85      1    msg       Ljava/lang/String;
   0      85      2    stackTrace       Z


private final boolean gd1$1(java.lang.String, boolean);
  Signature: (Ljava/lang/String;Z)Z
  Code:
   Stack=2, Locals=4, Args_size=3
	aload_1
	aload_0
	invokevirtual	Method msg:()Ljava/lang/String;
	astore_3
	dup
	ifnonnull	l1 // aload_3
	pop
	aload_3
	ifnull	l2 // iload_2
	goto	l3 // iconst_0
l1	aload_3
	invokevirtual	Method java/lang/Object.equals:(Ljava/lang/Object;)Z
	ifeq	l3 // iconst_0
l2	iload_2
	aload_0
	invokevirtual	Method stackTrace:()Z
	if_icmpne	l3 // iconst_0
	iconst_1
	goto	l4 // ireturn
l3	iconst_0
l4	ireturn
  Labels:
   	l1 = 18 // aload_3
   	l2 = 25 // iload_2
   	l3 = 37 // iconst_0
   	l4 = 38 // ireturn

public boolean canEqual(java.lang.Object);
  Signature: (Ljava/lang/Object;)Z
  Code:
   Stack=1, Locals=2, Args_size=2
	aload_1
	instanceof	class scala/testing/SUnit$AssertFailed
	ireturn
  Labels:

public java.lang.Object productElement(int);
  Signature: (I)Ljava/lang/Object;
  Code:
   Stack=3, Locals=3, Args_size=2
	iload_1
	tableswitch{ //0 to 1
		0: 51;
		1: 39;
		default: 24 }
	new	class java/lang/IndexOutOfBoundsException
	dup
	iload_1
	invokestatic	Method scala/runtime/BoxesRunTime.boxToInteger:(I)Ljava/lang/Integer;
	invokevirtual	Method java/lang/Object.toString:()Ljava/lang/String;
	invokespecial	Method java/lang/IndexOutOfBoundsException."<init>":(Ljava/lang/String;)V
	athrow
	aload_0
	invokevirtual	Method stackTrace:()Z
	istore_2
	iload_2
	invokestatic	Method scala/runtime/BoxesRunTime.boxToBoolean:(Z)Ljava/lang/Boolean;
	goto	l1 // areturn
	aload_0
	invokevirtual	Method msg:()Ljava/lang/String;
l1	areturn
  Labels:
   	l1 = 55 // areturn

public int productArity();
  Signature: ()I
  Code:
   Stack=1, Locals=1, Args_size=1
	iconst_2
	ireturn
  Labels:

public java.lang.String productPrefix();
  Signature: ()Ljava/lang/String;
  Code:
   Stack=1, Locals=1, Args_size=1
	ldc	String AssertFailed
	areturn
  Labels:

public boolean equals(java.lang.Object);
  Signature: (Ljava/lang/Object;)Z
  Code:
   Stack=3, Locals=5, Args_size=2
	aload_0
	aload_1
	if_acmpeq	l1 // iconst_1
	aload_1
	instanceof	class scala/testing/SUnit$AssertFailed
	ifeq	l2 // iconst_0
	aload_1
	checkcast	class scala/testing/SUnit$AssertFailed
	astore_2
	aload_2
	invokevirtual	Method msg:()Ljava/lang/String;
	astore_3
	aload_2
	invokevirtual	Method stackTrace:()Z
	istore	4
	aload_0
	aload_3
	iload	4
	invokespecial	Method gd1$1:(Ljava/lang/String;Z)Z
	ifeq	l3 // iconst_0
	aload_1
	checkcast	class scala/testing/SUnit$AssertFailed
	aload_0
	invokeinterface	InterfaceMethod scala/Equals.canEqual:(Ljava/lang/Object;)Z
	goto	l4 // ifeq
l3	iconst_0
	goto	l4 // ifeq
l2	iconst_0
l4	ifeq	l5 // iconst_0
l1	iconst_1
	goto	l6 // ireturn
l5	iconst_0
l6	ireturn
  Labels:
   	l3 = 51 // iconst_0
   	l2 = 55 // iconst_0
   	l4 = 56 // ifeq
   	l1 = 59 // iconst_1
   	l5 = 63 // iconst_0
   	l6 = 64 // ireturn
  LocalVariableTable: 
   Start  Length  Slot  Name   Signature
   0      65      0    this       Lscala/testing/SUnit$AssertFailed;
   17      38      2    temp2       Lscala/testing/SUnit$AssertFailed;
   22      33      3    temp3       Ljava/lang/String;
   28      27      4    temp4       Z


public int hashCode();
  Signature: ()I
  Code:
   Stack=2, Locals=1, Args_size=1
	getstatic	Field scala/runtime/ScalaRunTime$.MODULE$:Lscala/runtime/ScalaRunTime$;
	aload_0
	invokevirtual	Method scala/runtime/ScalaRunTime$._hashCode:(Lscala/Product;)I
	ireturn
  Labels:

public scala.testing.SUnit$AssertFailed copy(java.lang.String, boolean);
  Signature: (Ljava/lang/String;Z)Lscala/testing/SUnit$AssertFailed;
  Code:
   Stack=4, Locals=3, Args_size=3
	new	class scala/testing/SUnit$AssertFailed
	dup
	aload_1
	iload_2
	invokespecial	Method "<init>":(Ljava/lang/String;Z)V
	areturn
  Labels:
  LocalVariableTable: 
   Start  Length  Slot  Name   Signature
   0      10      0    this       Lscala/testing/SUnit$AssertFailed;
   0      10      1    msg       Ljava/lang/String;
   0      10      2    stackTrace       Z


public java.lang.String toString();
  Signature: ()Ljava/lang/String;
  Code:
   Stack=2, Locals=1, Args_size=1
	aload_0
	invokespecial	Method msg0:()Ljava/lang/String;
	ifnonnull	l1 // aload_0
	new	class scala/collection/mutable/StringBuilder
	dup
	invokespecial	Method scala/collection/mutable/StringBuilder."<init>":()V
	ldc	String failed assertion: 
	invokevirtual	Method scala/collection/mutable/StringBuilder.append:(Ljava/lang/Object;)Lscala/collection/mutable/StringBuilder;
	aload_0
	invokevirtual	Method msg:()Ljava/lang/String;
	invokevirtual	Method scala/collection/mutable/StringBuilder.append:(Ljava/lang/Object;)Lscala/collection/mutable/StringBuilder;
	invokevirtual	Method scala/collection/mutable/StringBuilder.toString:()Ljava/lang/String;
	goto	l2 // areturn
l1	aload_0
	invokespecial	Method msg0:()Ljava/lang/String;
l2	areturn
  Labels:
   	l1 = 32 // aload_0
   	l2 = 36 // areturn

private java.lang.String msg0();
  Signature: ()Ljava/lang/String;
  Code:
   Stack=1, Locals=1, Args_size=1
	aload_0
	getfield	Field msg0:Ljava/lang/String;
	areturn
  Labels:

public boolean stackTrace();
  Signature: ()Z
  Code:
   Stack=1, Locals=1, Args_size=1
	aload_0
	getfield	Field stackTrace:Z
	ireturn
  Labels:

public java.lang.String msg();
  Signature: ()Ljava/lang/String;
  Code:
   Stack=1, Locals=1, Args_size=1
	aload_0
	getfield	Field msg:Ljava/lang/String;
	areturn
  Labels:

public java.lang.String copy$default$1();
  Signature: ()Ljava/lang/String;
  Code:
   Stack=1, Locals=1, Args_size=1
	aload_0
	invokevirtual	Method msg:()Ljava/lang/String;
	areturn
  Labels:

public boolean copy$default$2();
  Signature: ()Z
  Code:
   Stack=1, Locals=1, Args_size=1
	aload_0
	invokevirtual	Method stackTrace:()Z
	ireturn
  Labels:

public scala.collection.Iterator productElements();
  Signature: ()Lscala/collection/Iterator;
  Code:
   Stack=1, Locals=1, Args_size=1
	aload_0
	invokestatic	Method scala/Product$class.productElements:(Lscala/Product;)Lscala/collection/Iterator;
	areturn
  Labels:
  Deprecated: true

public scala.collection.Iterator productIterator();
  Signature: ()Lscala/collection/Iterator;
  Code:
   Stack=1, Locals=1, Args_size=1
	aload_0
	invokestatic	Method scala/Product$class.productIterator:(Lscala/Product;)Lscala/collection/Iterator;
	areturn
  Labels:

}

