Compiled from "SUnit.scala"
public class scala.testing.SUnit$TestResult extends java.lang.Object implements scala.ScalaObject
  SourceFile: "SUnit.scala"
  Scala: length = 0x
   
  InnerClass: 
   public abstract Test=class scala/testing/SUnit$Test of class scala/testing/SUnit
   public TestResult=class scala/testing/SUnit$TestResult of class scala/testing/SUnit
   public final $anonfun$failures$1=class scala/testing/SUnit$TestResult$$anonfun$failures$1 of class scala/testing/SUnit$TestResult
  minor version: 0
  major version: 49
  Constant pool:
Asciz	SourceFile;
Asciz	SUnit.scala;
Asciz	buf;
Asciz	Lscala/collection/mutable/ArrayBuffer;;
Asciz	Lscala/collection/mutable/ArrayBuffer<Lscala/Tuple2<Lscala/testing/SUnit$Test;Ljava/lang/Throwable;>;>;;
Asciz	Signature;
Asciz	<init>;
Asciz	()V;
Asciz	Code;
Asciz	LineNumberTable;
Asciz	java/lang/Object;
class	java/lang/Object
NameAndType	"<init>":()V
Method	java/lang/Object."<init>":()V
Asciz	scala/collection/mutable/ArrayBuffer;
class	scala/collection/mutable/ArrayBuffer
Method	scala/collection/mutable/ArrayBuffer."<init>":()V
Asciz	scala/testing/SUnit$TestResult;
class	scala/testing/SUnit$TestResult
NameAndType	buf:Lscala/collection/mutable/ArrayBuffer;
Field	scala/testing/SUnit$TestResult.buf:Lscala/collection/mutable/ArrayBuffer;
Asciz	failures;
Asciz	()Lscala/collection/Iterator;;
Asciz	()Lscala/collection/mutable/ArrayBuffer;;
NameAndType	buf:()Lscala/collection/mutable/ArrayBuffer;
Method	scala/testing/SUnit$TestResult.buf:()Lscala/collection/mutable/ArrayBuffer;
Asciz	scala/collection/IndexedSeqLike;
class	scala/collection/IndexedSeqLike
Asciz	iterator;
NameAndType	iterator:()Lscala/collection/Iterator;
InterfaceMethod	scala/collection/IndexedSeqLike.iterator:()Lscala/collection/Iterator;
Asciz	scala/testing/SUnit$TestResult$$anonfun$failures$1;
class	scala/testing/SUnit$TestResult$$anonfun$failures$1
Asciz	(Lscala/testing/SUnit$TestResult;)V;
NameAndType	"<init>":(Lscala/testing/SUnit$TestResult;)V
Method	scala/testing/SUnit$TestResult$$anonfun$failures$1."<init>":(Lscala/testing/SUnit$TestResult;)V
Asciz	scala/collection/Iterator;
class	scala/collection/Iterator
Asciz	map;
Asciz	(Lscala/Function1;)Lscala/collection/Iterator;;
NameAndType	map:(Lscala/Function1;)Lscala/collection/Iterator;
InterfaceMethod	scala/collection/Iterator.map:(Lscala/Function1;)Lscala/collection/Iterator;
Asciz	()Lscala/collection/Iterator<Lscala/testing/SUnit$TestFailure;>;;
Asciz	failureCount;
Asciz	()I;
Asciz	scala/collection/mutable/ResizableArray;
class	scala/collection/mutable/ResizableArray
Asciz	length;
NameAndType	length:()I
InterfaceMethod	scala/collection/mutable/ResizableArray.length:()I
Asciz	addFailure;
Asciz	(Lscala/testing/SUnit$Test;Ljava/lang/Throwable;)V;
Asciz	scala/Tuple2;
class	scala/Tuple2
Asciz	(Ljava/lang/Object;Ljava/lang/Object;)V;
NameAndType	"<init>":(Ljava/lang/Object;Ljava/lang/Object;)V
Method	scala/Tuple2."<init>":(Ljava/lang/Object;Ljava/lang/Object;)V
Asciz	$plus$eq;
Asciz	(Ljava/lang/Object;)Lscala/collection/mutable/ArrayBuffer;;
NameAndType	$plus$eq:(Ljava/lang/Object;)Lscala/collection/mutable/ArrayBuffer;
Method	scala/collection/mutable/ArrayBuffer.$plus$eq:(Ljava/lang/Object;)Lscala/collection/mutable/ArrayBuffer;
Asciz	this;
Asciz	Lscala/testing/SUnit$TestResult;;
Asciz	test;
Asciz	Lscala/testing/SUnit$Test;;
Asciz	t;
Asciz	Ljava/lang/Throwable;;
Asciz	LocalVariableTable;
Asciz	()Lscala/collection/mutable/ArrayBuffer<Lscala/Tuple2<Lscala/testing/SUnit$Test;Ljava/lang/Throwable;>;>;;
Asciz	Scala;
Asciz	InnerClasses;
Asciz	scala/testing/SUnit$Test;
class	scala/testing/SUnit$Test
Asciz	scala/testing/SUnit;
class	scala/testing/SUnit
Asciz	Test;
Asciz	TestResult;
Asciz	$anonfun$failures$1;
Asciz	scala/ScalaObject;
class	scala/ScalaObject

{
private final scala.collection.mutable.ArrayBuffer buf;
  Signature: Lscala/collection/mutable/ArrayBuffer;
  Signature: length = 0x2
   00 05 

public scala.testing.SUnit$TestResult();
  Signature: ()V
  Code:
   Stack=3, Locals=1, Args_size=1
	aload_0
	invokespecial	Method java/lang/Object."<init>":()V
	aload_0
	new	class scala/collection/mutable/ArrayBuffer
	dup
	invokespecial	Method scala/collection/mutable/ArrayBuffer."<init>":()V
	putfield	Field buf:Lscala/collection/mutable/ArrayBuffer;
	return
  Labels:

public scala.collection.Iterator failures();
  Signature: ()Lscala/collection/Iterator;
  Code:
   Stack=4, Locals=1, Args_size=1
	aload_0
	invokevirtual	Method buf:()Lscala/collection/mutable/ArrayBuffer;
	invokeinterface	InterfaceMethod scala/collection/IndexedSeqLike.iterator:()Lscala/collection/Iterator;
	new	class scala/testing/SUnit$TestResult$$anonfun$failures$1
	dup
	aload_0
	invokespecial	Method scala/testing/SUnit$TestResult$$anonfun$failures$1."<init>":(Lscala/testing/SUnit$TestResult;)V
	invokeinterface	InterfaceMethod scala/collection/Iterator.map:(Lscala/Function1;)Lscala/collection/Iterator;
	areturn
  Labels:
  Signature: length = 0x2
   00 2B 

public int failureCount();
  Signature: ()I
  Code:
   Stack=1, Locals=1, Args_size=1
	aload_0
	invokevirtual	Method buf:()Lscala/collection/mutable/ArrayBuffer;
	invokeinterface	InterfaceMethod scala/collection/mutable/ResizableArray.length:()I
	ireturn
  Labels:

public void addFailure(scala.testing.SUnit$Test, java.lang.Throwable);
  Signature: (Lscala/testing/SUnit$Test;Ljava/lang/Throwable;)V
  Code:
   Stack=5, Locals=3, Args_size=3
	aload_0
	invokevirtual	Method buf:()Lscala/collection/mutable/ArrayBuffer;
	new	class scala/Tuple2
	dup
	aload_1
	aload_2
	invokespecial	Method scala/Tuple2."<init>":(Ljava/lang/Object;Ljava/lang/Object;)V
	invokevirtual	Method scala/collection/mutable/ArrayBuffer.$plus$eq:(Ljava/lang/Object;)Lscala/collection/mutable/ArrayBuffer;
	pop
	return
  Labels:
  LocalVariableTable: 
   Start  Length  Slot  Name   Signature
   0      18      0    this       Lscala/testing/SUnit$TestResult;
   0      18      1    test       Lscala/testing/SUnit$Test;
   0      18      2    t       Ljava/lang/Throwable;


public scala.collection.mutable.ArrayBuffer buf();
  Signature: ()Lscala/collection/mutable/ArrayBuffer;
  Code:
   Stack=1, Locals=1, Args_size=1
	aload_0
	getfield	Field buf:Lscala/collection/mutable/ArrayBuffer;
	areturn
  Labels:
  Signature: length = 0x2
   00 45 

}

