Compiled from "ImplicitConversions.scala"
public abstract class scala.util.parsing.combinator.ImplicitConversions$class extends java.lang.Object
  SourceFile: "ImplicitConversions.scala"
  Scala: length = 0x
   
  InnerClass: 
   public final $anonfun$flatten5$1=class scala/util/parsing/combinator/ImplicitConversions$$anonfun$flatten5$1 of class scala/util/parsing/combinator/ImplicitConversions
   public final $anonfun$flatten4$1=class scala/util/parsing/combinator/ImplicitConversions$$anonfun$flatten4$1 of class scala/util/parsing/combinator/ImplicitConversions
   public final $anonfun$flatten3$1=class scala/util/parsing/combinator/ImplicitConversions$$anonfun$flatten3$1 of class scala/util/parsing/combinator/ImplicitConversions
   public final $anonfun$flatten2$1=class scala/util/parsing/combinator/ImplicitConversions$$anonfun$flatten2$1 of class scala/util/parsing/combinator/ImplicitConversions
   public final $anonfun$headOptionTailToFunList$1=class scala/util/parsing/combinator/ImplicitConversions$$anonfun$headOptionTailToFunList$1 of class scala/util/parsing/combinator/ImplicitConversions
  minor version: 0
  major version: 49
  Constant pool:
Asciz	SourceFile;
Asciz	ImplicitConversions.scala;
Asciz	flatten2;
Asciz	(Lscala/util/parsing/combinator/ImplicitConversions;Lscala/Function2;)Lscala/Function1;;
Asciz	Code;
Asciz	scala/util/parsing/combinator/ImplicitConversions$$anonfun$flatten2$1;
class	scala/util/parsing/combinator/ImplicitConversions$$anonfun$flatten2$1
Asciz	LineNumberTable;
Asciz	<init>;
Asciz	(Lscala/util/parsing/combinator/ImplicitConversions;Lscala/Function2;)V;
NameAndType	"<init>":(Lscala/util/parsing/combinator/ImplicitConversions;Lscala/Function2;)V
Method	scala/util/parsing/combinator/ImplicitConversions$$anonfun$flatten2$1."<init>":(Lscala/util/parsing/combinator/ImplicitConversions;Lscala/Function2;)V
Asciz	$this;
Asciz	Lscala/util/parsing/combinator/ImplicitConversions;;
Asciz	f$1;
Asciz	Lscala/Function2;;
Asciz	LocalVariableTable;
Asciz	flatten3;
Asciz	(Lscala/util/parsing/combinator/ImplicitConversions;Lscala/Function3;)Lscala/Function1;;
Asciz	scala/util/parsing/combinator/ImplicitConversions$$anonfun$flatten3$1;
class	scala/util/parsing/combinator/ImplicitConversions$$anonfun$flatten3$1
Asciz	(Lscala/util/parsing/combinator/ImplicitConversions;Lscala/Function3;)V;
NameAndType	"<init>":(Lscala/util/parsing/combinator/ImplicitConversions;Lscala/Function3;)V
Method	scala/util/parsing/combinator/ImplicitConversions$$anonfun$flatten3$1."<init>":(Lscala/util/parsing/combinator/ImplicitConversions;Lscala/Function3;)V
Asciz	f$2;
Asciz	Lscala/Function3;;
Asciz	flatten4;
Asciz	(Lscala/util/parsing/combinator/ImplicitConversions;Lscala/Function4;)Lscala/Function1;;
Asciz	scala/util/parsing/combinator/ImplicitConversions$$anonfun$flatten4$1;
class	scala/util/parsing/combinator/ImplicitConversions$$anonfun$flatten4$1
Asciz	(Lscala/util/parsing/combinator/ImplicitConversions;Lscala/Function4;)V;
NameAndType	"<init>":(Lscala/util/parsing/combinator/ImplicitConversions;Lscala/Function4;)V
Method	scala/util/parsing/combinator/ImplicitConversions$$anonfun$flatten4$1."<init>":(Lscala/util/parsing/combinator/ImplicitConversions;Lscala/Function4;)V
Asciz	f$3;
Asciz	Lscala/Function4;;
Asciz	flatten5;
Asciz	(Lscala/util/parsing/combinator/ImplicitConversions;Lscala/Function5;)Lscala/Function1;;
Asciz	scala/util/parsing/combinator/ImplicitConversions$$anonfun$flatten5$1;
class	scala/util/parsing/combinator/ImplicitConversions$$anonfun$flatten5$1
Asciz	(Lscala/util/parsing/combinator/ImplicitConversions;Lscala/Function5;)V;
NameAndType	"<init>":(Lscala/util/parsing/combinator/ImplicitConversions;Lscala/Function5;)V
Method	scala/util/parsing/combinator/ImplicitConversions$$anonfun$flatten5$1."<init>":(Lscala/util/parsing/combinator/ImplicitConversions;Lscala/Function5;)V
Asciz	f$4;
Asciz	Lscala/Function5;;
Asciz	headOptionTailToFunList;
Asciz	(Lscala/util/parsing/combinator/ImplicitConversions;Lscala/Function1;)Lscala/Function1;;
Asciz	scala/util/parsing/combinator/ImplicitConversions$$anonfun$headOptionTailToFunList$1;
class	scala/util/parsing/combinator/ImplicitConversions$$anonfun$headOptionTailToFunList$1
Asciz	(Lscala/util/parsing/combinator/ImplicitConversions;Lscala/Function1;)V;
NameAndType	"<init>":(Lscala/util/parsing/combinator/ImplicitConversions;Lscala/Function1;)V
Method	scala/util/parsing/combinator/ImplicitConversions$$anonfun$headOptionTailToFunList$1."<init>":(Lscala/util/parsing/combinator/ImplicitConversions;Lscala/Function1;)V
Asciz	f$5;
Asciz	Lscala/Function1;;
Asciz	$init$;
Asciz	(Lscala/util/parsing/combinator/ImplicitConversions;)V;
Asciz	Scala;
Asciz	InnerClasses;
Asciz	scala/util/parsing/combinator/ImplicitConversions;
class	scala/util/parsing/combinator/ImplicitConversions
Asciz	$anonfun$flatten5$1;
Asciz	$anonfun$flatten4$1;
Asciz	$anonfun$flatten3$1;
Asciz	$anonfun$flatten2$1;
Asciz	$anonfun$headOptionTailToFunList$1;
Asciz	scala/util/parsing/combinator/ImplicitConversions$class;
class	scala/util/parsing/combinator/ImplicitConversions$class
Asciz	java/lang/Object;
class	java/lang/Object

{
public static scala.Function1 flatten2(scala.util.parsing.combinator.ImplicitConversions, scala.Function2);
  Signature: (Lscala/util/parsing/combinator/ImplicitConversions;Lscala/Function2;)Lscala/Function1;
  Code:
   Stack=4, Locals=2, Args_size=2
	new	class scala/util/parsing/combinator/ImplicitConversions$$anonfun$flatten2$1
	dup
	aload_0
	aload_1
	invokespecial	Method scala/util/parsing/combinator/ImplicitConversions$$anonfun$flatten2$1."<init>":(Lscala/util/parsing/combinator/ImplicitConversions;Lscala/Function2;)V
	areturn
  Labels:
  LocalVariableTable: 
   Start  Length  Slot  Name   Signature
   0      10      0    $this       Lscala/util/parsing/combinator/ImplicitConversions;
   0      10      1    f$1       Lscala/Function2;


public static scala.Function1 flatten3(scala.util.parsing.combinator.ImplicitConversions, scala.Function3);
  Signature: (Lscala/util/parsing/combinator/ImplicitConversions;Lscala/Function3;)Lscala/Function1;
  Code:
   Stack=4, Locals=2, Args_size=2
	new	class scala/util/parsing/combinator/ImplicitConversions$$anonfun$flatten3$1
	dup
	aload_0
	aload_1
	invokespecial	Method scala/util/parsing/combinator/ImplicitConversions$$anonfun$flatten3$1."<init>":(Lscala/util/parsing/combinator/ImplicitConversions;Lscala/Function3;)V
	areturn
  Labels:
  LocalVariableTable: 
   Start  Length  Slot  Name   Signature
   0      10      0    $this       Lscala/util/parsing/combinator/ImplicitConversions;
   0      10      1    f$2       Lscala/Function3;


public static scala.Function1 flatten4(scala.util.parsing.combinator.ImplicitConversions, scala.Function4);
  Signature: (Lscala/util/parsing/combinator/ImplicitConversions;Lscala/Function4;)Lscala/Function1;
  Code:
   Stack=4, Locals=2, Args_size=2
	new	class scala/util/parsing/combinator/ImplicitConversions$$anonfun$flatten4$1
	dup
	aload_0
	aload_1
	invokespecial	Method scala/util/parsing/combinator/ImplicitConversions$$anonfun$flatten4$1."<init>":(Lscala/util/parsing/combinator/ImplicitConversions;Lscala/Function4;)V
	areturn
  Labels:
  LocalVariableTable: 
   Start  Length  Slot  Name   Signature
   0      10      0    $this       Lscala/util/parsing/combinator/ImplicitConversions;
   0      10      1    f$3       Lscala/Function4;


public static scala.Function1 flatten5(scala.util.parsing.combinator.ImplicitConversions, scala.Function5);
  Signature: (Lscala/util/parsing/combinator/ImplicitConversions;Lscala/Function5;)Lscala/Function1;
  Code:
   Stack=4, Locals=2, Args_size=2
	new	class scala/util/parsing/combinator/ImplicitConversions$$anonfun$flatten5$1
	dup
	aload_0
	aload_1
	invokespecial	Method scala/util/parsing/combinator/ImplicitConversions$$anonfun$flatten5$1."<init>":(Lscala/util/parsing/combinator/ImplicitConversions;Lscala/Function5;)V
	areturn
  Labels:
  LocalVariableTable: 
   Start  Length  Slot  Name   Signature
   0      10      0    $this       Lscala/util/parsing/combinator/ImplicitConversions;
   0      10      1    f$4       Lscala/Function5;


public static scala.Function1 headOptionTailToFunList(scala.util.parsing.combinator.ImplicitConversions, scala.Function1);
  Signature: (Lscala/util/parsing/combinator/ImplicitConversions;Lscala/Function1;)Lscala/Function1;
  Code:
   Stack=4, Locals=2, Args_size=2
	new	class scala/util/parsing/combinator/ImplicitConversions$$anonfun$headOptionTailToFunList$1
	dup
	aload_0
	aload_1
	invokespecial	Method scala/util/parsing/combinator/ImplicitConversions$$anonfun$headOptionTailToFunList$1."<init>":(Lscala/util/parsing/combinator/ImplicitConversions;Lscala/Function1;)V
	areturn
  Labels:
  LocalVariableTable: 
   Start  Length  Slot  Name   Signature
   0      10      0    $this       Lscala/util/parsing/combinator/ImplicitConversions;
   0      10      1    f$5       Lscala/Function1;


public static void $init$(scala.util.parsing.combinator.ImplicitConversions);
  Signature: (Lscala/util/parsing/combinator/ImplicitConversions;)V
  Code:
   Stack=0, Locals=1, Args_size=1
	return
  Labels:
  LocalVariableTable: 
   Start  Length  Slot  Name   Signature
   0      1      0    $this       Lscala/util/parsing/combinator/ImplicitConversions;


}

