Compiled from "ImplicitConversions.scala"
public final class scala.util.parsing.combinator.ImplicitConversions$$anonfun$flatten5$1 extends java.lang.Object implements scala.Function1,scala.ScalaObject,java.io.Serializable
  SourceFile: "ImplicitConversions.scala"
  Scala: length = 0x
   
  InnerClass: 
   public #93= #32 of #92; //$tilde=class scala/util/parsing/combinator/Parsers$$tilde of class scala/util/parsing/combinator/Parsers
   public final #96= #10 of #95; //$anonfun$flatten5$1=class scala/util/parsing/combinator/ImplicitConversions$$anonfun$flatten5$1 of class scala/util/parsing/combinator/ImplicitConversions
  minor version: 0
  major version: 49
  Constant pool:
const #1 = Asciz	SourceFile;
const #2 = Asciz	ImplicitConversions.scala;
const #3 = Asciz	f$4;
const #4 = Asciz	Lscala/Function5;;
const #5 = Asciz	<init>;
const #6 = Asciz	(Lscala/util/parsing/combinator/ImplicitConversions;Lscala/Function5;)V;
const #7 = Asciz	Code;
const #8 = Asciz	LineNumberTable;
const #9 = Asciz	scala/util/parsing/combinator/ImplicitConversions$$anonfun$flatten5$1;
const #10 = class	#9;	//  scala/util/parsing/combinator/ImplicitConversions$$anonfun$flatten5$1
const #11 = NameAndType	#3:#4;//  f$4:Lscala/Function5;
const #12 = Field	#10.#11;	//  scala/util/parsing/combinator/ImplicitConversions$$anonfun$flatten5$1.f$4:Lscala/Function5;
const #13 = Asciz	java/lang/Object;
const #14 = class	#13;	//  java/lang/Object
const #15 = Asciz	()V;
const #16 = NameAndType	#5:#15;//  "<init>":()V
const #17 = Method	#14.#16;	//  java/lang/Object."<init>":()V
const #18 = Asciz	scala/Function1$class;
const #19 = class	#18;	//  scala/Function1$class
const #20 = Asciz	$init$;
const #21 = Asciz	(Lscala/Function1;)V;
const #22 = NameAndType	#20:#21;//  $init$:(Lscala/Function1;)V
const #23 = Method	#19.#22;	//  scala/Function1$class.$init$:(Lscala/Function1;)V
const #24 = Asciz	this;
const #25 = Asciz	Lscala/util/parsing/combinator/ImplicitConversions$$anonfun$flatten5$1;;
const #26 = Asciz	$outer;
const #27 = Asciz	Lscala/util/parsing/combinator/ImplicitConversions;;
const #28 = Asciz	LocalVariableTable;
const #29 = Asciz	apply;
const #30 = Asciz	(Ljava/lang/Object;)Ljava/lang/Object;;
const #31 = Asciz	scala/util/parsing/combinator/Parsers$$tilde;
const #32 = class	#31;	//  scala/util/parsing/combinator/Parsers$$tilde
const #33 = Asciz	(Lscala/util/parsing/combinator/Parsers$$tilde;)Ljava/lang/Object;;
const #34 = NameAndType	#29:#33;//  apply:(Lscala/util/parsing/combinator/Parsers$$tilde;)Ljava/lang/Object;
const #35 = Method	#10.#34;	//  scala/util/parsing/combinator/ImplicitConversions$$anonfun$flatten5$1.apply:(Lscala/util/parsing/combinator/Parsers$$tilde;)Ljava/lang/Object;
const #36 = Asciz	v1;
const #37 = Asciz	Ljava/lang/Object;;
const #38 = Asciz	_1;
const #39 = Asciz	()Ljava/lang/Object;;
const #40 = NameAndType	#38:#39;//  _1:()Ljava/lang/Object;
const #41 = Method	#32.#40;	//  scala/util/parsing/combinator/Parsers$$tilde._1:()Ljava/lang/Object;
const #42 = Asciz	_2;
const #43 = NameAndType	#42:#39;//  _2:()Ljava/lang/Object;
const #44 = Method	#32.#43;	//  scala/util/parsing/combinator/Parsers$$tilde._2:()Ljava/lang/Object;
const #45 = Asciz	scala/Function5;
const #46 = class	#45;	//  scala/Function5
const #47 = Asciz	(Ljava/lang/Object;Ljava/lang/Object;Ljava/lang/Object;Ljava/lang/Object;Ljava/lang/Object;)Ljava/lang/Object;;
const #48 = NameAndType	#29:#47;//  apply:(Ljava/lang/Object;Ljava/lang/Object;Ljava/lang/Object;Ljava/lang/Object;Ljava/lang/Object;)Ljava/lang/Object;
const #49 = InterfaceMethod	#46.#48;	//  scala/Function5.apply:(Ljava/lang/Object;Ljava/lang/Object;Ljava/lang/Object;Ljava/lang/Object;Ljava/lang/Object;)Ljava/lang/Object;
const #50 = Asciz	scala/MatchError;
const #51 = class	#50;	//  scala/MatchError
const #52 = Asciz	toString;
const #53 = Asciz	()Ljava/lang/String;;
const #54 = NameAndType	#52:#53;//  toString:()Ljava/lang/String;
const #55 = Method	#32.#54;	//  scala/util/parsing/combinator/Parsers$$tilde.toString:()Ljava/lang/String;
const #56 = Asciz	(Ljava/lang/String;)V;
const #57 = NameAndType	#5:#56;//  "<init>":(Ljava/lang/String;)V
const #58 = Method	#51.#57;	//  scala/MatchError."<init>":(Ljava/lang/String;)V
const #59 = Asciz	p;
const #60 = Asciz	Lscala/util/parsing/combinator/Parsers$$tilde;;
const #61 = Asciz	temp16;
const #62 = Asciz	temp17;
const #63 = Asciz	temp18;
const #64 = Asciz	temp19;
const #65 = Asciz	temp20;
const #66 = Asciz	temp21;
const #67 = Asciz	temp22;
const #68 = Asciz	temp23;
const #69 = Asciz	temp24;
const #70 = Asciz	e;
const #71 = Asciz	d;
const #72 = Asciz	c;
const #73 = Asciz	b;
const #74 = Asciz	(Lscala/util/parsing/combinator/Parsers$$tilde<Lscala/util/parsing/combinator/Parsers$$tilde<Lscala/util/parsing/combinator/Parsers$$tilde<Lscala/util/parsing/combinator/Parsers$$tilde<TA;TB;>;TC;>;TD;>;TE;>;)TF;;
const #75 = Asciz	Signature;
const #76 = Asciz	andThen;
const #77 = Asciz	(Lscala/Function1;)Lscala/Function1;;
const #78 = Asciz	(Lscala/Function1;Lscala/Function1;)Lscala/Function1;;
const #79 = NameAndType	#76:#78;//  andThen:(Lscala/Function1;Lscala/Function1;)Lscala/Function1;
const #80 = Method	#19.#79;	//  scala/Function1$class.andThen:(Lscala/Function1;Lscala/Function1;)Lscala/Function1;
const #81 = Asciz	g;
const #82 = Asciz	Lscala/Function1;;
const #83 = Asciz	compose;
const #84 = NameAndType	#83:#78;//  compose:(Lscala/Function1;Lscala/Function1;)Lscala/Function1;
const #85 = Method	#19.#84;	//  scala/Function1$class.compose:(Lscala/Function1;Lscala/Function1;)Lscala/Function1;
const #86 = Asciz	(Lscala/Function1;)Ljava/lang/String;;
const #87 = NameAndType	#52:#86;//  toString:(Lscala/Function1;)Ljava/lang/String;
const #88 = Method	#19.#87;	//  scala/Function1$class.toString:(Lscala/Function1;)Ljava/lang/String;
const #89 = Asciz	Scala;
const #90 = Asciz	InnerClasses;
const #91 = Asciz	scala/util/parsing/combinator/Parsers;
const #92 = class	#91;	//  scala/util/parsing/combinator/Parsers
const #93 = Asciz	$tilde;
const #94 = Asciz	scala/util/parsing/combinator/ImplicitConversions;
const #95 = class	#94;	//  scala/util/parsing/combinator/ImplicitConversions
const #96 = Asciz	$anonfun$flatten5$1;
const #97 = Asciz	scala/Function1;
const #98 = class	#97;	//  scala/Function1
const #99 = Asciz	scala/ScalaObject;
const #100 = class	#99;	//  scala/ScalaObject
const #101 = Asciz	java/io/Serializable;
const #102 = class	#101;	//  java/io/Serializable

{
public scala.util.parsing.combinator.ImplicitConversions$$anonfun$flatten5$1(scala.util.parsing.combinator.ImplicitConversions, scala.Function5);
  Code:
   Stack=2, Locals=3, Args_size=3
   0:	aload_0
   1:	aload_2
   2:	putfield	#12; //Field f$4:Lscala/Function5;
   5:	aload_0
   6:	invokespecial	#17; //Method java/lang/Object."<init>":()V
   9:	aload_0
   10:	invokestatic	#23; //Method scala/Function1$class.$init$:(Lscala/Function1;)V
   13:	return
  LineNumberTable: 
   line 35: 0

  LocalVariableTable: 
   Start  Length  Slot  Name   Signature
   0      14      0    this       Lscala/util/parsing/combinator/ImplicitConversions$$anonfun$flatten5$1;
   0      14      1    $outer       Lscala/util/parsing/combinator/ImplicitConversions;


public final java.lang.Object apply(java.lang.Object);
  Code:
   Stack=2, Locals=2, Args_size=2
   0:	aload_0
   1:	aload_1
   2:	checkcast	#32; //class scala/util/parsing/combinator/Parsers$$tilde
   5:	invokevirtual	#35; //Method apply:(Lscala/util/parsing/combinator/Parsers$$tilde;)Ljava/lang/Object;
   8:	areturn
  LineNumberTable: 
   line 35: 0

  LocalVariableTable: 
   Start  Length  Slot  Name   Signature
   0      9      0    this       Lscala/util/parsing/combinator/ImplicitConversions$$anonfun$flatten5$1;
   0      9      1    v1       Ljava/lang/Object;


public final java.lang.Object apply(scala.util.parsing.combinator.Parsers$$tilde);
  Code:
   Stack=6, Locals=15, Args_size=2
   0:	aload_1
   1:	astore_2
   2:	aload_2
   3:	ifnull	152
   6:	aload_2
   7:	invokevirtual	#41; //Method scala/util/parsing/combinator/Parsers$$tilde._1:()Ljava/lang/Object;
   10:	checkcast	#32; //class scala/util/parsing/combinator/Parsers$$tilde
   13:	astore_3
   14:	aload_2
   15:	invokevirtual	#44; //Method scala/util/parsing/combinator/Parsers$$tilde._2:()Ljava/lang/Object;
   18:	astore	4
   20:	aload_3
   21:	ifnull	140
   24:	aload_3
   25:	invokevirtual	#41; //Method scala/util/parsing/combinator/Parsers$$tilde._1:()Ljava/lang/Object;
   28:	checkcast	#32; //class scala/util/parsing/combinator/Parsers$$tilde
   31:	astore	5
   33:	aload_3
   34:	invokevirtual	#44; //Method scala/util/parsing/combinator/Parsers$$tilde._2:()Ljava/lang/Object;
   37:	astore	6
   39:	aload	5
   41:	ifnull	128
   44:	aload	5
   46:	invokevirtual	#41; //Method scala/util/parsing/combinator/Parsers$$tilde._1:()Ljava/lang/Object;
   49:	checkcast	#32; //class scala/util/parsing/combinator/Parsers$$tilde
   52:	astore	7
   54:	aload	5
   56:	invokevirtual	#44; //Method scala/util/parsing/combinator/Parsers$$tilde._2:()Ljava/lang/Object;
   59:	astore	8
   61:	aload	7
   63:	ifnull	116
   66:	aload	7
   68:	invokevirtual	#41; //Method scala/util/parsing/combinator/Parsers$$tilde._1:()Ljava/lang/Object;
   71:	astore	9
   73:	aload	7
   75:	invokevirtual	#44; //Method scala/util/parsing/combinator/Parsers$$tilde._2:()Ljava/lang/Object;
   78:	astore	10
   80:	aload	4
   82:	astore	11
   84:	aload	6
   86:	astore	12
   88:	aload	8
   90:	astore	13
   92:	aload	10
   94:	astore	14
   96:	aload_0
   97:	getfield	#12; //Field f$4:Lscala/Function5;
   100:	aload	9
   102:	aload	14
   104:	aload	13
   106:	aload	12
   108:	aload	11
   110:	invokeinterface	#49,  6; //InterfaceMethod scala/Function5.apply:(Ljava/lang/Object;Ljava/lang/Object;Ljava/lang/Object;Ljava/lang/Object;Ljava/lang/Object;)Ljava/lang/Object;
   115:	areturn
   116:	new	#51; //class scala/MatchError
   119:	dup
   120:	aload_2
   121:	invokevirtual	#55; //Method scala/util/parsing/combinator/Parsers$$tilde.toString:()Ljava/lang/String;
   124:	invokespecial	#58; //Method scala/MatchError."<init>":(Ljava/lang/String;)V
   127:	athrow
   128:	new	#51; //class scala/MatchError
   131:	dup
   132:	aload_2
   133:	invokevirtual	#55; //Method scala/util/parsing/combinator/Parsers$$tilde.toString:()Ljava/lang/String;
   136:	invokespecial	#58; //Method scala/MatchError."<init>":(Ljava/lang/String;)V
   139:	athrow
   140:	new	#51; //class scala/MatchError
   143:	dup
   144:	aload_2
   145:	invokevirtual	#55; //Method scala/util/parsing/combinator/Parsers$$tilde.toString:()Ljava/lang/String;
   148:	invokespecial	#58; //Method scala/MatchError."<init>":(Ljava/lang/String;)V
   151:	athrow
   152:	new	#51; //class scala/MatchError
   155:	dup
   156:	aload_2
   157:	invokevirtual	#55; //Method scala/util/parsing/combinator/Parsers$$tilde.toString:()Ljava/lang/String;
   160:	invokespecial	#58; //Method scala/MatchError."<init>":(Ljava/lang/String;)V
   163:	athrow
  LineNumberTable: 
   line 35: 0

  LocalVariableTable: 
   Start  Length  Slot  Name   Signature
   0      164      0    this       Lscala/util/parsing/combinator/ImplicitConversions$$anonfun$flatten5$1;
   0      164      1    p       Lscala/util/parsing/combinator/Parsers$$tilde;
   2      162      2    temp16       Lscala/util/parsing/combinator/Parsers$$tilde;
   14      101      3    temp17       Lscala/util/parsing/combinator/Parsers$$tilde;
   116      36      3    temp17       Lscala/util/parsing/combinator/Parsers$$tilde;
   20      95      4    temp18       Ljava/lang/Object;
   116      36      4    temp18       Ljava/lang/Object;
   33      82      5    temp19       Lscala/util/parsing/combinator/Parsers$$tilde;
   116      24      5    temp19       Lscala/util/parsing/combinator/Parsers$$tilde;
   39      76      6    temp20       Ljava/lang/Object;
   116      24      6    temp20       Ljava/lang/Object;
   54      61      7    temp21       Lscala/util/parsing/combinator/Parsers$$tilde;
   116      12      7    temp21       Lscala/util/parsing/combinator/Parsers$$tilde;
   61      54      8    temp22       Ljava/lang/Object;
   116      12      8    temp22       Ljava/lang/Object;
   73      42      9    temp23       Ljava/lang/Object;
   80      35      10    temp24       Ljava/lang/Object;
   84      31      11    e       Ljava/lang/Object;
   88      27      12    d       Ljava/lang/Object;
   92      23      13    c       Ljava/lang/Object;
   96      19      14    b       Ljava/lang/Object;

  Signature: length = 0x2
   00 4A 

public scala.Function1 andThen(scala.Function1);
  Code:
   Stack=2, Locals=2, Args_size=2
   0:	aload_0
   1:	aload_1
   2:	invokestatic	#80; //Method scala/Function1$class.andThen:(Lscala/Function1;Lscala/Function1;)Lscala/Function1;
   5:	areturn
  LineNumberTable: 
   line 35: 0

  LocalVariableTable: 
   Start  Length  Slot  Name   Signature
   0      6      0    this       Lscala/util/parsing/combinator/ImplicitConversions$$anonfun$flatten5$1;
   0      6      1    g       Lscala/Function1;


public scala.Function1 compose(scala.Function1);
  Code:
   Stack=2, Locals=2, Args_size=2
   0:	aload_0
   1:	aload_1
   2:	invokestatic	#85; //Method scala/Function1$class.compose:(Lscala/Function1;Lscala/Function1;)Lscala/Function1;
   5:	areturn
  LineNumberTable: 
   line 35: 0

  LocalVariableTable: 
   Start  Length  Slot  Name   Signature
   0      6      0    this       Lscala/util/parsing/combinator/ImplicitConversions$$anonfun$flatten5$1;
   0      6      1    g       Lscala/Function1;


public java.lang.String toString();
  Code:
   Stack=1, Locals=1, Args_size=1
   0:	aload_0
   1:	invokestatic	#88; //Method scala/Function1$class.toString:(Lscala/Function1;)Ljava/lang/String;
   4:	areturn
  LineNumberTable: 
   line 35: 0


}

