Compiled from "ImplicitConversions.scala"
public final class scala.util.parsing.combinator.ImplicitConversions$$anonfun$headOptionTailToFunList$1 extends scala.runtime.AbstractFunction1 implements java.io.Serializable
  SourceFile: "ImplicitConversions.scala"
  Scala: length = 0x
   
  InnerClass: 
   public $tilde=class scala/util/parsing/combinator/Parsers$$tilde of class scala/util/parsing/combinator/Parsers
   public final $anonfun$headOptionTailToFunList$1=class scala/util/parsing/combinator/ImplicitConversions$$anonfun$headOptionTailToFunList$1 of class scala/util/parsing/combinator/ImplicitConversions
  minor version: 0
  major version: 49
  Constant pool:
Asciz	SourceFile;
Asciz	ImplicitConversions.scala;
Asciz	<clinit>;
Asciz	()V;
Asciz	Code;
Asciz	serialVersionUID;
Asciz	J;
Asciz	scala/util/parsing/combinator/ImplicitConversions$$anonfun$headOptionTailToFunList$1;
class	scala/util/parsing/combinator/ImplicitConversions$$anonfun$headOptionTailToFunList$1
NameAndType	serialVersionUID:J
Field	scala/util/parsing/combinator/ImplicitConversions$$anonfun$headOptionTailToFunList$1.serialVersionUID:J
Asciz	f$5;
Asciz	Lscala/Function1;;
Asciz	<init>;
Asciz	(Lscala/util/parsing/combinator/ImplicitConversions;Lscala/Function1;)V;
Asciz	LineNumberTable;
NameAndType	f$5:Lscala/Function1;
Field	scala/util/parsing/combinator/ImplicitConversions$$anonfun$headOptionTailToFunList$1.f$5:Lscala/Function1;
Asciz	scala/runtime/AbstractFunction1;
class	scala/runtime/AbstractFunction1
NameAndType	"<init>":()V
Method	scala/runtime/AbstractFunction1."<init>":()V
Asciz	this;
Asciz	Lscala/util/parsing/combinator/ImplicitConversions$$anonfun$headOptionTailToFunList$1;;
Asciz	$outer;
Asciz	Lscala/util/parsing/combinator/ImplicitConversions;;
Asciz	LocalVariableTable;
Asciz	apply;
Asciz	(Ljava/lang/Object;)Ljava/lang/Object;;
Asciz	scala/util/parsing/combinator/Parsers$$tilde;
class	scala/util/parsing/combinator/Parsers$$tilde
Asciz	(Lscala/util/parsing/combinator/Parsers$$tilde;)Ljava/lang/Object;;
NameAndType	apply:(Lscala/util/parsing/combinator/Parsers$$tilde;)Ljava/lang/Object;
Method	scala/util/parsing/combinator/ImplicitConversions$$anonfun$headOptionTailToFunList$1.apply:(Lscala/util/parsing/combinator/Parsers$$tilde;)Ljava/lang/Object;
Asciz	v1;
Asciz	Ljava/lang/Object;;
Asciz	_1;
Asciz	()Ljava/lang/Object;;
NameAndType	_1:()Ljava/lang/Object;
Method	scala/util/parsing/combinator/Parsers$$tilde._1:()Ljava/lang/Object;
Asciz	_2;
NameAndType	_2:()Ljava/lang/Object;
Method	scala/util/parsing/combinator/Parsers$$tilde._2:()Ljava/lang/Object;
Asciz	scala/Option;
class	scala/Option
Asciz	scala/Some;
class	scala/Some
Asciz	x;
NameAndType	x:Ljava/lang/Object;
Field	scala/Some.x:Ljava/lang/Object;
Asciz	scala/collection/immutable/List;
class	scala/collection/immutable/List
Asciz	scala/MatchError;
class	scala/MatchError
Asciz	toString;
Asciz	()Ljava/lang/String;;
NameAndType	toString:()Ljava/lang/String;
Method	scala/Option.toString:()Ljava/lang/String;
Asciz	(Ljava/lang/String;)V;
NameAndType	"<init>":(Ljava/lang/String;)V
Method	scala/MatchError."<init>":(Ljava/lang/String;)V
Asciz	scala/None$;
class	scala/None$
Asciz	MODULE$;
Asciz	Lscala/None$;;
NameAndType	MODULE$:Lscala/None$;
Field	scala/None$.MODULE$:Lscala/None$;
Asciz	java/lang/Object;
class	java/lang/Object
Asciz	equals;
Asciz	(Ljava/lang/Object;)Z;
NameAndType	equals:(Ljava/lang/Object;)Z
Method	java/lang/Object.equals:(Ljava/lang/Object;)Z
Asciz	scala/collection/immutable/Nil$;
class	scala/collection/immutable/Nil$
Asciz	Lscala/collection/immutable/Nil$;;
NameAndType	MODULE$:Lscala/collection/immutable/Nil$;
Field	scala/collection/immutable/Nil$.MODULE$:Lscala/collection/immutable/Nil$;
Asciz	$colon$colon;
Asciz	(Ljava/lang/Object;)Lscala/collection/immutable/List;;
NameAndType	$colon$colon:(Ljava/lang/Object;)Lscala/collection/immutable/List;
Method	scala/collection/immutable/List.$colon$colon:(Ljava/lang/Object;)Lscala/collection/immutable/List;
Asciz	scala/Function1;
class	scala/Function1
NameAndType	apply:(Ljava/lang/Object;)Ljava/lang/Object;
InterfaceMethod	scala/Function1.apply:(Ljava/lang/Object;)Ljava/lang/Object;
Asciz	p;
Asciz	Lscala/util/parsing/combinator/Parsers$$tilde;;
Asciz	temp26;
Asciz	Lscala/Some;;
Asciz	temp27;
Asciz	Lscala/collection/immutable/List;;
Asciz	temp25;
Asciz	Lscala/Option;;
Asciz	(Lscala/util/parsing/combinator/Parsers$$tilde<TA;Lscala/Option<Lscala/collection/immutable/List<TA;>;>;>;)TT;;
Asciz	Signature;
Asciz	Scala;
Asciz	InnerClasses;
Asciz	scala/util/parsing/combinator/Parsers;
class	scala/util/parsing/combinator/Parsers
Asciz	$tilde;
Asciz	scala/util/parsing/combinator/ImplicitConversions;
class	scala/util/parsing/combinator/ImplicitConversions
Asciz	$anonfun$headOptionTailToFunList$1;
Asciz	java/io/Serializable;
class	java/io/Serializable

{
public static final long serialVersionUID;
  Signature: J

private final scala.Function1 f$5;
  Signature: Lscala/Function1;

public static {};
  Signature: ()V
  Code:
   Stack=2, Locals=0, Args_size=0
	lconst_0
	putstatic	Field serialVersionUID:J
	return
  Labels:

public scala.util.parsing.combinator.ImplicitConversions$$anonfun$headOptionTailToFunList$1(scala.util.parsing.combinator.ImplicitConversions, scala.Function1);
  Signature: (Lscala/util/parsing/combinator/ImplicitConversions;Lscala/Function1;)V
  Code:
   Stack=2, Locals=3, Args_size=3
	aload_0
	aload_2
	putfield	Field f$5:Lscala/Function1;
	aload_0
	invokespecial	Method scala/runtime/AbstractFunction1."<init>":()V
	return
  Labels:
  LocalVariableTable: 
   Start  Length  Slot  Name   Signature
   0      10      0    this       Lscala/util/parsing/combinator/ImplicitConversions$$anonfun$headOptionTailToFunList$1;
   0      10      1    $outer       Lscala/util/parsing/combinator/ImplicitConversions;


public final java.lang.Object apply(java.lang.Object);
  Signature: (Ljava/lang/Object;)Ljava/lang/Object;
  Code:
   Stack=2, Locals=2, Args_size=2
	aload_0
	aload_1
	checkcast	class scala/util/parsing/combinator/Parsers$$tilde
	invokevirtual	Method apply:(Lscala/util/parsing/combinator/Parsers$$tilde;)Ljava/lang/Object;
	areturn
  Labels:
  LocalVariableTable: 
   Start  Length  Slot  Name   Signature
   0      9      0    this       Lscala/util/parsing/combinator/ImplicitConversions$$anonfun$headOptionTailToFunList$1;
   0      9      1    v1       Ljava/lang/Object;


public final java.lang.Object apply(scala.util.parsing.combinator.Parsers$$tilde);
  Signature: (Lscala/util/parsing/combinator/Parsers$$tilde;)Ljava/lang/Object;
  Code:
   Stack=4, Locals=6, Args_size=2
	aload_0
	getfield	Field f$5:Lscala/Function1;
	aload_1
	invokevirtual	Method scala/util/parsing/combinator/Parsers$$tilde._1:()Ljava/lang/Object;
	astore	4
	aload_1
	invokevirtual	Method scala/util/parsing/combinator/Parsers$$tilde._2:()Ljava/lang/Object;
	checkcast	class scala/Option
	astore	5
	aload	5
	instanceof	class scala/Some
	ifeq	l1 // getstatic
	aload	5
	checkcast	class scala/Some
	astore_2
	aload_2
	getfield	Field scala/Some.x:Ljava/lang/Object;
	checkcast	class scala/collection/immutable/List
	astore_3
	iconst_1
	ifeq	l2 // new
	aload_3
	goto	l3 // aload
l2	new	class scala/MatchError
	dup
	aload	5
	invokevirtual	Method scala/Option.toString:()Ljava/lang/String;
	invokespecial	Method scala/MatchError."<init>":(Ljava/lang/String;)V
	athrow
l1	getstatic	Field scala/None$.MODULE$:Lscala/None$;
	dup
	ifnonnull	l4 // aload
	pop
	aload	5
	ifnull	l5 // iconst_1
	goto	l6 // new
l4	aload	5
	invokevirtual	Method java/lang/Object.equals:(Ljava/lang/Object;)Z
	ifeq	l6 // new
l5	iconst_1
	ifeq	l7 // new
	getstatic	Field scala/collection/immutable/Nil$.MODULE$:Lscala/collection/immutable/Nil$;
l3	aload	4
	invokevirtual	Method scala/collection/immutable/List.$colon$colon:(Ljava/lang/Object;)Lscala/collection/immutable/List;
	invokeinterface	InterfaceMethod scala/Function1.apply:(Ljava/lang/Object;)Ljava/lang/Object;
	areturn
l7	new	class scala/MatchError
	dup
	aload	5
	invokevirtual	Method scala/Option.toString:()Ljava/lang/String;
	invokespecial	Method scala/MatchError."<init>":(Ljava/lang/String;)V
	athrow
l6	new	class scala/MatchError
	dup
	aload	5
	invokevirtual	Method scala/Option.toString:()Ljava/lang/String;
	invokespecial	Method scala/MatchError."<init>":(Ljava/lang/String;)V
	athrow
  Labels:
   	l2 = 49 // new
   	l1 = 62 // getstatic
   	l4 = 78 // aload
   	l5 = 86 // iconst_1
   	l3 = 93 // aload
   	l7 = 104 // new
   	l6 = 117 // new
  LocalVariableTable: 
   Start  Length  Slot  Name   Signature
   0      130      0    this       Lscala/util/parsing/combinator/ImplicitConversions$$anonfun$headOptionTailToFunList$1;
   0      130      1    p       Lscala/util/parsing/combinator/Parsers$$tilde;
   33      29      2    temp26       Lscala/Some;
   41      21      3    temp27       Lscala/collection/immutable/List;
   19      111      5    temp25       Lscala/Option;

  Signature: length = 0x2
   00 5F 

}

