Compiled from "ImplicitConversions.scala"
public abstract class scala.util.parsing.combinator.ImplicitConversions$class extends java.lang.Object
  SourceFile: "ImplicitConversions.scala"
  Scala: length = 0x
   
  InnerClass: 
   public final #60= #50 of #59; //$anonfun$flatten2$1=class scala/util/parsing/combinator/ImplicitConversions$$anonfun$flatten2$1 of class scala/util/parsing/combinator/ImplicitConversions
   public final #61= #41 of #59; //$anonfun$flatten3$1=class scala/util/parsing/combinator/ImplicitConversions$$anonfun$flatten3$1 of class scala/util/parsing/combinator/ImplicitConversions
   public final #62= #32 of #59; //$anonfun$flatten4$1=class scala/util/parsing/combinator/ImplicitConversions$$anonfun$flatten4$1 of class scala/util/parsing/combinator/ImplicitConversions
   public final #63= #23 of #59; //$anonfun$flatten5$1=class scala/util/parsing/combinator/ImplicitConversions$$anonfun$flatten5$1 of class scala/util/parsing/combinator/ImplicitConversions
   public final #64= #13 of #59; //$anonfun$headOptionTailToFunList$1=class scala/util/parsing/combinator/ImplicitConversions$$anonfun$headOptionTailToFunList$1 of class scala/util/parsing/combinator/ImplicitConversions
  minor version: 0
  major version: 49
  Constant pool:
const #1 = Asciz	SourceFile;
const #2 = Asciz	ImplicitConversions.scala;
const #3 = Asciz	$init$;
const #4 = Asciz	(Lscala/util/parsing/combinator/ImplicitConversions;)V;
const #5 = Asciz	Code;
const #6 = Asciz	LineNumberTable;
const #7 = Asciz	$this;
const #8 = Asciz	Lscala/util/parsing/combinator/ImplicitConversions;;
const #9 = Asciz	LocalVariableTable;
const #10 = Asciz	headOptionTailToFunList;
const #11 = Asciz	(Lscala/util/parsing/combinator/ImplicitConversions;Lscala/Function1;)Lscala/Function1;;
const #12 = Asciz	scala/util/parsing/combinator/ImplicitConversions$$anonfun$headOptionTailToFunList$1;
const #13 = class	#12;	//  scala/util/parsing/combinator/ImplicitConversions$$anonfun$headOptionTailToFunList$1
const #14 = Asciz	<init>;
const #15 = Asciz	(Lscala/util/parsing/combinator/ImplicitConversions;Lscala/Function1;)V;
const #16 = NameAndType	#14:#15;//  "<init>":(Lscala/util/parsing/combinator/ImplicitConversions;Lscala/Function1;)V
const #17 = Method	#13.#16;	//  scala/util/parsing/combinator/ImplicitConversions$$anonfun$headOptionTailToFunList$1."<init>":(Lscala/util/parsing/combinator/ImplicitConversions;Lscala/Function1;)V
const #18 = Asciz	f$5;
const #19 = Asciz	Lscala/Function1;;
const #20 = Asciz	flatten5;
const #21 = Asciz	(Lscala/util/parsing/combinator/ImplicitConversions;Lscala/Function5;)Lscala/Function1;;
const #22 = Asciz	scala/util/parsing/combinator/ImplicitConversions$$anonfun$flatten5$1;
const #23 = class	#22;	//  scala/util/parsing/combinator/ImplicitConversions$$anonfun$flatten5$1
const #24 = Asciz	(Lscala/util/parsing/combinator/ImplicitConversions;Lscala/Function5;)V;
const #25 = NameAndType	#14:#24;//  "<init>":(Lscala/util/parsing/combinator/ImplicitConversions;Lscala/Function5;)V
const #26 = Method	#23.#25;	//  scala/util/parsing/combinator/ImplicitConversions$$anonfun$flatten5$1."<init>":(Lscala/util/parsing/combinator/ImplicitConversions;Lscala/Function5;)V
const #27 = Asciz	f$4;
const #28 = Asciz	Lscala/Function5;;
const #29 = Asciz	flatten4;
const #30 = Asciz	(Lscala/util/parsing/combinator/ImplicitConversions;Lscala/Function4;)Lscala/Function1;;
const #31 = Asciz	scala/util/parsing/combinator/ImplicitConversions$$anonfun$flatten4$1;
const #32 = class	#31;	//  scala/util/parsing/combinator/ImplicitConversions$$anonfun$flatten4$1
const #33 = Asciz	(Lscala/util/parsing/combinator/ImplicitConversions;Lscala/Function4;)V;
const #34 = NameAndType	#14:#33;//  "<init>":(Lscala/util/parsing/combinator/ImplicitConversions;Lscala/Function4;)V
const #35 = Method	#32.#34;	//  scala/util/parsing/combinator/ImplicitConversions$$anonfun$flatten4$1."<init>":(Lscala/util/parsing/combinator/ImplicitConversions;Lscala/Function4;)V
const #36 = Asciz	f$3;
const #37 = Asciz	Lscala/Function4;;
const #38 = Asciz	flatten3;
const #39 = Asciz	(Lscala/util/parsing/combinator/ImplicitConversions;Lscala/Function3;)Lscala/Function1;;
const #40 = Asciz	scala/util/parsing/combinator/ImplicitConversions$$anonfun$flatten3$1;
const #41 = class	#40;	//  scala/util/parsing/combinator/ImplicitConversions$$anonfun$flatten3$1
const #42 = Asciz	(Lscala/util/parsing/combinator/ImplicitConversions;Lscala/Function3;)V;
const #43 = NameAndType	#14:#42;//  "<init>":(Lscala/util/parsing/combinator/ImplicitConversions;Lscala/Function3;)V
const #44 = Method	#41.#43;	//  scala/util/parsing/combinator/ImplicitConversions$$anonfun$flatten3$1."<init>":(Lscala/util/parsing/combinator/ImplicitConversions;Lscala/Function3;)V
const #45 = Asciz	f$2;
const #46 = Asciz	Lscala/Function3;;
const #47 = Asciz	flatten2;
const #48 = Asciz	(Lscala/util/parsing/combinator/ImplicitConversions;Lscala/Function2;)Lscala/Function1;;
const #49 = Asciz	scala/util/parsing/combinator/ImplicitConversions$$anonfun$flatten2$1;
const #50 = class	#49;	//  scala/util/parsing/combinator/ImplicitConversions$$anonfun$flatten2$1
const #51 = Asciz	(Lscala/util/parsing/combinator/ImplicitConversions;Lscala/Function2;)V;
const #52 = NameAndType	#14:#51;//  "<init>":(Lscala/util/parsing/combinator/ImplicitConversions;Lscala/Function2;)V
const #53 = Method	#50.#52;	//  scala/util/parsing/combinator/ImplicitConversions$$anonfun$flatten2$1."<init>":(Lscala/util/parsing/combinator/ImplicitConversions;Lscala/Function2;)V
const #54 = Asciz	f$1;
const #55 = Asciz	Lscala/Function2;;
const #56 = Asciz	Scala;
const #57 = Asciz	InnerClasses;
const #58 = Asciz	scala/util/parsing/combinator/ImplicitConversions;
const #59 = class	#58;	//  scala/util/parsing/combinator/ImplicitConversions
const #60 = Asciz	$anonfun$flatten2$1;
const #61 = Asciz	$anonfun$flatten3$1;
const #62 = Asciz	$anonfun$flatten4$1;
const #63 = Asciz	$anonfun$flatten5$1;
const #64 = Asciz	$anonfun$headOptionTailToFunList$1;
const #65 = Asciz	scala/util/parsing/combinator/ImplicitConversions$class;
const #66 = class	#65;	//  scala/util/parsing/combinator/ImplicitConversions$class
const #67 = Asciz	java/lang/Object;
const #68 = class	#67;	//  java/lang/Object

{
public static void $init$(scala.util.parsing.combinator.ImplicitConversions);
  Code:
   Stack=0, Locals=1, Args_size=1
   0:	return
  LineNumberTable: 
   line 27: 0

  LocalVariableTable: 
   Start  Length  Slot  Name   Signature
   0      1      0    $this       Lscala/util/parsing/combinator/ImplicitConversions;


public static scala.Function1 headOptionTailToFunList(scala.util.parsing.combinator.ImplicitConversions, scala.Function1);
  Code:
   Stack=4, Locals=2, Args_size=2
   0:	new	#13; //class scala/util/parsing/combinator/ImplicitConversions$$anonfun$headOptionTailToFunList$1
   3:	dup
   4:	aload_0
   5:	aload_1
   6:	invokespecial	#17; //Method scala/util/parsing/combinator/ImplicitConversions$$anonfun$headOptionTailToFunList$1."<init>":(Lscala/util/parsing/combinator/ImplicitConversions;Lscala/Function1;)V
   9:	areturn
  LineNumberTable: 
   line 37: 0

  LocalVariableTable: 
   Start  Length  Slot  Name   Signature
   0      10      0    $this       Lscala/util/parsing/combinator/ImplicitConversions;
   0      10      1    f$5       Lscala/Function1;


public static scala.Function1 flatten5(scala.util.parsing.combinator.ImplicitConversions, scala.Function5);
  Code:
   Stack=4, Locals=2, Args_size=2
   0:	new	#23; //class scala/util/parsing/combinator/ImplicitConversions$$anonfun$flatten5$1
   3:	dup
   4:	aload_0
   5:	aload_1
   6:	invokespecial	#26; //Method scala/util/parsing/combinator/ImplicitConversions$$anonfun$flatten5$1."<init>":(Lscala/util/parsing/combinator/ImplicitConversions;Lscala/Function5;)V
   9:	areturn
  LineNumberTable: 
   line 35: 0

  LocalVariableTable: 
   Start  Length  Slot  Name   Signature
   0      10      0    $this       Lscala/util/parsing/combinator/ImplicitConversions;
   0      10      1    f$4       Lscala/Function5;


public static scala.Function1 flatten4(scala.util.parsing.combinator.ImplicitConversions, scala.Function4);
  Code:
   Stack=4, Locals=2, Args_size=2
   0:	new	#32; //class scala/util/parsing/combinator/ImplicitConversions$$anonfun$flatten4$1
   3:	dup
   4:	aload_0
   5:	aload_1
   6:	invokespecial	#35; //Method scala/util/parsing/combinator/ImplicitConversions$$anonfun$flatten4$1."<init>":(Lscala/util/parsing/combinator/ImplicitConversions;Lscala/Function4;)V
   9:	areturn
  LineNumberTable: 
   line 33: 0

  LocalVariableTable: 
   Start  Length  Slot  Name   Signature
   0      10      0    $this       Lscala/util/parsing/combinator/ImplicitConversions;
   0      10      1    f$3       Lscala/Function4;


public static scala.Function1 flatten3(scala.util.parsing.combinator.ImplicitConversions, scala.Function3);
  Code:
   Stack=4, Locals=2, Args_size=2
   0:	new	#41; //class scala/util/parsing/combinator/ImplicitConversions$$anonfun$flatten3$1
   3:	dup
   4:	aload_0
   5:	aload_1
   6:	invokespecial	#44; //Method scala/util/parsing/combinator/ImplicitConversions$$anonfun$flatten3$1."<init>":(Lscala/util/parsing/combinator/ImplicitConversions;Lscala/Function3;)V
   9:	areturn
  LineNumberTable: 
   line 31: 0

  LocalVariableTable: 
   Start  Length  Slot  Name   Signature
   0      10      0    $this       Lscala/util/parsing/combinator/ImplicitConversions;
   0      10      1    f$2       Lscala/Function3;


public static scala.Function1 flatten2(scala.util.parsing.combinator.ImplicitConversions, scala.Function2);
  Code:
   Stack=4, Locals=2, Args_size=2
   0:	new	#50; //class scala/util/parsing/combinator/ImplicitConversions$$anonfun$flatten2$1
   3:	dup
   4:	aload_0
   5:	aload_1
   6:	invokespecial	#53; //Method scala/util/parsing/combinator/ImplicitConversions$$anonfun$flatten2$1."<init>":(Lscala/util/parsing/combinator/ImplicitConversions;Lscala/Function2;)V
   9:	areturn
  LineNumberTable: 
   line 29: 0

  LocalVariableTable: 
   Start  Length  Slot  Name   Signature
   0      10      0    $this       Lscala/util/parsing/combinator/ImplicitConversions;
   0      10      1    f$1       Lscala/Function2;


}

