Compiled from "PackratParsers.scala"
public class scala.util.parsing.combinator.PackratParsers$LR extends java.lang.Object implements scala.ScalaObject,scala.Product,java.io.Serializable
  SourceFile: "PackratParsers.scala"
  Scala: length = 0x
   
  InnerClass: 
   public abstract Parser=class scala/util/parsing/combinator/Parsers$Parser of class scala/util/parsing/combinator/Parsers
   public LR=class scala/util/parsing/combinator/PackratParsers$LR of class scala/util/parsing/combinator/PackratParsers
   public abstract ParseResult=class scala/util/parsing/combinator/Parsers$ParseResult of class scala/util/parsing/combinator/Parsers
  minor version: 0
  major version: 49
  Constant pool:
Asciz	SourceFile;
Asciz	PackratParsers.scala;
Asciz	$outer;
Asciz	Lscala/util/parsing/combinator/PackratParsers;;
Asciz	head;
Asciz	Lscala/Option;;
Asciz	Lscala/Option<Lscala/util/parsing/combinator/PackratParsers$Head;>;;
Asciz	Signature;
Asciz	rule;
Asciz	Lscala/util/parsing/combinator/Parsers$Parser;;
Asciz	Lscala/util/parsing/combinator/Parsers$Parser<*>;;
Asciz	seed;
Asciz	Lscala/util/parsing/combinator/Parsers$ParseResult;;
Asciz	Lscala/util/parsing/combinator/Parsers$ParseResult<*>;;
Asciz	<init>;
Asciz	(Lscala/util/parsing/combinator/PackratParsers;Lscala/util/parsing/combinator/Parsers$ParseResult;Lscala/util/parsing/combinator/Parsers$Parser;Lscala/Option;)V;
Asciz	Code;
Asciz	LineNumberTable;
Asciz	scala/util/parsing/combinator/PackratParsers$LR;
class	scala/util/parsing/combinator/PackratParsers$LR
NameAndType	seed:Lscala/util/parsing/combinator/Parsers$ParseResult;
Field	scala/util/parsing/combinator/PackratParsers$LR.seed:Lscala/util/parsing/combinator/Parsers$ParseResult;
NameAndType	rule:Lscala/util/parsing/combinator/Parsers$Parser;
Field	scala/util/parsing/combinator/PackratParsers$LR.rule:Lscala/util/parsing/combinator/Parsers$Parser;
NameAndType	head:Lscala/Option;
Field	scala/util/parsing/combinator/PackratParsers$LR.head:Lscala/Option;
Asciz	java/lang/NullPointerException;
class	java/lang/NullPointerException
Asciz	()V;
NameAndType	"<init>":()V
Method	java/lang/NullPointerException."<init>":()V
NameAndType	$outer:Lscala/util/parsing/combinator/PackratParsers;
Field	scala/util/parsing/combinator/PackratParsers$LR.$outer:Lscala/util/parsing/combinator/PackratParsers;
Asciz	java/lang/Object;
class	java/lang/Object
Method	java/lang/Object."<init>":()V
Asciz	scala/Product$class;
class	scala/Product$class
Asciz	$init$;
Asciz	(Lscala/Product;)V;
NameAndType	$init$:(Lscala/Product;)V
Method	scala/Product$class.$init$:(Lscala/Product;)V
Asciz	this;
Asciz	Lscala/util/parsing/combinator/PackratParsers$LR;;
Asciz	LocalVariableTable;
Asciz	(Lscala/util/parsing/combinator/PackratParsers;Lscala/util/parsing/combinator/Parsers$ParseResult<*>;Lscala/util/parsing/combinator/Parsers$Parser<*>;Lscala/Option<Lscala/util/parsing/combinator/PackratParsers$Head;>;)V;
Asciz	gd2$1;
Asciz	(Lscala/util/parsing/combinator/Parsers$ParseResult;Lscala/util/parsing/combinator/Parsers$Parser;Lscala/Option;)Z;
Asciz	()Lscala/util/parsing/combinator/Parsers$ParseResult;;
NameAndType	seed:()Lscala/util/parsing/combinator/Parsers$ParseResult;
Method	scala/util/parsing/combinator/PackratParsers$LR.seed:()Lscala/util/parsing/combinator/Parsers$ParseResult;
Asciz	equals;
Asciz	(Ljava/lang/Object;)Z;
NameAndType	equals:(Ljava/lang/Object;)Z
Method	java/lang/Object.equals:(Ljava/lang/Object;)Z
Asciz	()Lscala/util/parsing/combinator/Parsers$Parser;;
NameAndType	rule:()Lscala/util/parsing/combinator/Parsers$Parser;
Method	scala/util/parsing/combinator/PackratParsers$LR.rule:()Lscala/util/parsing/combinator/Parsers$Parser;
Asciz	()Lscala/Option;;
NameAndType	head:()Lscala/Option;
Method	scala/util/parsing/combinator/PackratParsers$LR.head:()Lscala/Option;
Asciz	scala$util$parsing$combinator$PackratParsers$LR$$$outer;
Asciz	()Lscala/util/parsing/combinator/PackratParsers;;
Asciz	canEqual;
Asciz	productElement;
Asciz	(I)Ljava/lang/Object;;
Asciz	java/lang/IndexOutOfBoundsException;
class	java/lang/IndexOutOfBoundsException
Asciz	scala/runtime/BoxesRunTime;
class	scala/runtime/BoxesRunTime
Asciz	boxToInteger;
Asciz	(I)Ljava/lang/Integer;;
NameAndType	boxToInteger:(I)Ljava/lang/Integer;
Method	scala/runtime/BoxesRunTime.boxToInteger:(I)Ljava/lang/Integer;
Asciz	toString;
Asciz	()Ljava/lang/String;;
NameAndType	toString:()Ljava/lang/String;
Method	java/lang/Object.toString:()Ljava/lang/String;
Asciz	(Ljava/lang/String;)V;
NameAndType	"<init>":(Ljava/lang/String;)V
Method	java/lang/IndexOutOfBoundsException."<init>":(Ljava/lang/String;)V
Asciz	scala/MatchError;
class	scala/MatchError
Method	scala/MatchError."<init>":(Ljava/lang/String;)V
Asciz	productArity;
Asciz	()I;
Asciz	productPrefix;
Asciz	LR;
String	LR
NameAndType	scala$util$parsing$combinator$PackratParsers$LR$$$outer:()Lscala/util/parsing/combinator/PackratParsers;
Method	scala/util/parsing/combinator/PackratParsers$LR.scala$util$parsing$combinator$PackratParsers$LR$$$outer:()Lscala/util/parsing/combinator/PackratParsers;
NameAndType	gd2$1:(Lscala/util/parsing/combinator/Parsers$ParseResult;Lscala/util/parsing/combinator/Parsers$Parser;Lscala/Option;)Z
Method	scala/util/parsing/combinator/PackratParsers$LR.gd2$1:(Lscala/util/parsing/combinator/Parsers$ParseResult;Lscala/util/parsing/combinator/Parsers$Parser;Lscala/Option;)Z
Asciz	scala/Equals;
class	scala/Equals
NameAndType	canEqual:(Ljava/lang/Object;)Z
InterfaceMethod	scala/Equals.canEqual:(Ljava/lang/Object;)Z
Asciz	temp16;
Asciz	temp17;
Asciz	temp18;
Asciz	temp19;
Asciz	scala/runtime/ScalaRunTime$;
class	scala/runtime/ScalaRunTime$
Asciz	MODULE$;
Asciz	Lscala/runtime/ScalaRunTime$;;
NameAndType	MODULE$:Lscala/runtime/ScalaRunTime$;
Field	scala/runtime/ScalaRunTime$.MODULE$:Lscala/runtime/ScalaRunTime$;
Asciz	_toString;
Asciz	(Lscala/Product;)Ljava/lang/String;;
NameAndType	_toString:(Lscala/Product;)Ljava/lang/String;
Method	scala/runtime/ScalaRunTime$._toString:(Lscala/Product;)Ljava/lang/String;
Asciz	hashCode;
Asciz	_hashCode;
Asciz	(Lscala/Product;)I;
NameAndType	_hashCode:(Lscala/Product;)I
Method	scala/runtime/ScalaRunTime$._hashCode:(Lscala/Product;)I
Asciz	copy;
Asciz	(Lscala/util/parsing/combinator/Parsers$ParseResult;Lscala/util/parsing/combinator/Parsers$Parser;Lscala/Option;)Lscala/util/parsing/combinator/PackratParsers$LR;;
NameAndType	"<init>":(Lscala/util/parsing/combinator/PackratParsers;Lscala/util/parsing/combinator/Parsers$ParseResult;Lscala/util/parsing/combinator/Parsers$Parser;Lscala/Option;)V
Method	scala/util/parsing/combinator/PackratParsers$LR."<init>":(Lscala/util/parsing/combinator/PackratParsers;Lscala/util/parsing/combinator/Parsers$ParseResult;Lscala/util/parsing/combinator/Parsers$Parser;Lscala/Option;)V
Asciz	getPos;
Asciz	()Lscala/util/parsing/input/Position;;
Asciz	scala/util/parsing/combinator/PackratParsers$class;
class	scala/util/parsing/combinator/PackratParsers$class
Asciz	scala$util$parsing$combinator$PackratParsers$$getPosFromResult;
Asciz	(Lscala/util/parsing/combinator/PackratParsers;Lscala/util/parsing/combinator/Parsers$ParseResult;)Lscala/util/parsing/input/Position;;
NameAndType	scala$util$parsing$combinator$PackratParsers$$getPosFromResult:(Lscala/util/parsing/combinator/PackratParsers;Lscala/util/parsing/combinator/Parsers$ParseResult;)Lscala/util/parsing/input/Position;
Method	scala/util/parsing/combinator/PackratParsers$class.scala$util$parsing$combinator$PackratParsers$$getPosFromResult:(Lscala/util/parsing/combinator/PackratParsers;Lscala/util/parsing/combinator/Parsers$ParseResult;)Lscala/util/parsing/input/Position;
Asciz	head_$eq;
Asciz	(Lscala/Option;)V;
Asciz	(Lscala/Option<Lscala/util/parsing/combinator/PackratParsers$Head;>;)V;
Asciz	()Lscala/Option<Lscala/util/parsing/combinator/PackratParsers$Head;>;;
Asciz	rule_$eq;
Asciz	(Lscala/util/parsing/combinator/Parsers$Parser;)V;
Asciz	(Lscala/util/parsing/combinator/Parsers$Parser<*>;)V;
Asciz	()Lscala/util/parsing/combinator/Parsers$Parser<*>;;
Asciz	seed_$eq;
Asciz	(Lscala/util/parsing/combinator/Parsers$ParseResult;)V;
Asciz	(Lscala/util/parsing/combinator/Parsers$ParseResult<*>;)V;
Asciz	()Lscala/util/parsing/combinator/Parsers$ParseResult<*>;;
Asciz	copy$default$1;
Asciz	copy$default$2;
Asciz	copy$default$3;
Asciz	productElements;
Asciz	()Lscala/collection/Iterator;;
Asciz	(Lscala/Product;)Lscala/collection/Iterator;;
NameAndType	productElements:(Lscala/Product;)Lscala/collection/Iterator;
Method	scala/Product$class.productElements:(Lscala/Product;)Lscala/collection/Iterator;
Asciz	Deprecated;
Asciz	productIterator;
NameAndType	productIterator:(Lscala/Product;)Lscala/collection/Iterator;
Method	scala/Product$class.productIterator:(Lscala/Product;)Lscala/collection/Iterator;
Asciz	Scala;
Asciz	InnerClasses;
Asciz	scala/util/parsing/combinator/Parsers$Parser;
class	scala/util/parsing/combinator/Parsers$Parser
Asciz	scala/util/parsing/combinator/Parsers;
class	scala/util/parsing/combinator/Parsers
Asciz	Parser;
Asciz	scala/util/parsing/combinator/PackratParsers;
class	scala/util/parsing/combinator/PackratParsers
Asciz	scala/util/parsing/combinator/Parsers$ParseResult;
class	scala/util/parsing/combinator/Parsers$ParseResult
Asciz	ParseResult;
Asciz	scala/ScalaObject;
class	scala/ScalaObject
Asciz	scala/Product;
class	scala/Product
Asciz	java/io/Serializable;
class	java/io/Serializable

{
public final scala.util.parsing.combinator.PackratParsers $outer;
  Signature: Lscala/util/parsing/combinator/PackratParsers;

private scala.Option head;
  Signature: Lscala/Option;
  Signature: length = 0x2
   00 07 

private scala.util.parsing.combinator.Parsers$Parser rule;
  Signature: Lscala/util/parsing/combinator/Parsers$Parser;
  Signature: length = 0x2
   00 0B 

private scala.util.parsing.combinator.Parsers$ParseResult seed;
  Signature: Lscala/util/parsing/combinator/Parsers$ParseResult;
  Signature: length = 0x2
   00 0E 

public scala.util.parsing.combinator.PackratParsers$LR(scala.util.parsing.combinator.PackratParsers, scala.util.parsing.combinator.Parsers$ParseResult, scala.util.parsing.combinator.Parsers$Parser, scala.Option);
  Signature: (Lscala/util/parsing/combinator/PackratParsers;Lscala/util/parsing/combinator/Parsers$ParseResult;Lscala/util/parsing/combinator/Parsers$Parser;Lscala/Option;)V
  Code:
   Stack=2, Locals=5, Args_size=5
	aload_0
	aload_2
	putfield	Field seed:Lscala/util/parsing/combinator/Parsers$ParseResult;
	aload_0
	aload_3
	putfield	Field rule:Lscala/util/parsing/combinator/Parsers$Parser;
	aload_0
	aload	4
	putfield	Field head:Lscala/Option;
	aload_1
	ifnonnull	l1 // aload_0
	new	class java/lang/NullPointerException
	dup
	invokespecial	Method java/lang/NullPointerException."<init>":()V
	athrow
l1	aload_0
	aload_1
	putfield	Field $outer:Lscala/util/parsing/combinator/PackratParsers;
	aload_0
	invokespecial	Method java/lang/Object."<init>":()V
	aload_0
	invokestatic	Method scala/Product$class.$init$:(Lscala/Product;)V
	return
  Labels:
   	l1 = 28 // aload_0
  LocalVariableTable: 
   Start  Length  Slot  Name   Signature
   0      42      0    this       Lscala/util/parsing/combinator/PackratParsers$LR;
   0      42      1    $outer       Lscala/util/parsing/combinator/PackratParsers;
   0      42      2    seed       Lscala/util/parsing/combinator/Parsers$ParseResult;
   0      42      3    rule       Lscala/util/parsing/combinator/Parsers$Parser;
   0      42      4    head       Lscala/Option;

  Signature: length = 0x2
   00 2E 

private final boolean gd2$1(scala.util.parsing.combinator.Parsers$ParseResult, scala.util.parsing.combinator.Parsers$Parser, scala.Option);
  Signature: (Lscala/util/parsing/combinator/Parsers$ParseResult;Lscala/util/parsing/combinator/Parsers$Parser;Lscala/Option;)Z
  Code:
   Stack=2, Locals=7, Args_size=4
	aload_1
	aload_0
	invokevirtual	Method seed:()Lscala/util/parsing/combinator/Parsers$ParseResult;
	astore	4
	dup
	ifnonnull	l1 // aload
	pop
	aload	4
	ifnull	l2 // aload_2
	goto	l3 // iconst_0
l1	aload	4
	invokevirtual	Method java/lang/Object.equals:(Ljava/lang/Object;)Z
	ifeq	l3 // iconst_0
l2	aload_2
	aload_0
	invokevirtual	Method rule:()Lscala/util/parsing/combinator/Parsers$Parser;
	astore	5
	dup
	ifnonnull	l4 // aload
	pop
	aload	5
	ifnull	l5 // aload_3
	goto	l3 // iconst_0
l4	aload	5
	invokevirtual	Method java/lang/Object.equals:(Ljava/lang/Object;)Z
	ifeq	l3 // iconst_0
l5	aload_3
	aload_0
	invokevirtual	Method head:()Lscala/Option;
	astore	6
	dup
	ifnonnull	l6 // aload
	pop
	aload	6
	ifnull	l7 // iconst_1
	goto	l3 // iconst_0
l6	aload	6
	invokevirtual	Method java/lang/Object.equals:(Ljava/lang/Object;)Z
	ifeq	l3 // iconst_0
l7	iconst_1
	goto	l8 // ireturn
l3	iconst_0
l8	ireturn
  Labels:
   	l1 = 20 // aload
   	l2 = 28 // aload_2
   	l4 = 48 // aload
   	l5 = 56 // aload_3
   	l6 = 76 // aload
   	l7 = 84 // iconst_1
   	l3 = 88 // iconst_0
   	l8 = 89 // ireturn

public scala.util.parsing.combinator.PackratParsers scala$util$parsing$combinator$PackratParsers$LR$$$outer();
  Signature: ()Lscala/util/parsing/combinator/PackratParsers;
  Code:
   Stack=1, Locals=1, Args_size=1
	aload_0
	getfield	Field $outer:Lscala/util/parsing/combinator/PackratParsers;
	areturn
  Labels:

public boolean canEqual(java.lang.Object);
  Signature: (Ljava/lang/Object;)Z
  Code:
   Stack=1, Locals=2, Args_size=2
	aload_1
	instanceof	class scala/util/parsing/combinator/PackratParsers$LR
	ireturn
  Labels:

public java.lang.Object productElement(int);
  Signature: (I)Ljava/lang/Object;
  Code:
   Stack=3, Locals=2, Args_size=2
	iload_1
	tableswitch{ //0 to 2
		0: 114;
		1: 88;
		2: 62;
		default: 28 }
	iconst_1
	ifeq	l1 // new
	new	class java/lang/IndexOutOfBoundsException
	dup
	iload_1
	invokestatic	Method scala/runtime/BoxesRunTime.boxToInteger:(I)Ljava/lang/Integer;
	invokevirtual	Method java/lang/Object.toString:()Ljava/lang/String;
	invokespecial	Method java/lang/IndexOutOfBoundsException."<init>":(Ljava/lang/String;)V
	athrow
l1	new	class scala/MatchError
	dup
	iload_1
	invokestatic	Method scala/runtime/BoxesRunTime.boxToInteger:(I)Ljava/lang/Integer;
	invokevirtual	Method java/lang/Object.toString:()Ljava/lang/String;
	invokespecial	Method scala/MatchError."<init>":(Ljava/lang/String;)V
	athrow
	iconst_1
	ifeq	l2 // new
	aload_0
	invokevirtual	Method head:()Lscala/Option;
	goto	l3 // areturn
l2	new	class scala/MatchError
	dup
	iload_1
	invokestatic	Method scala/runtime/BoxesRunTime.boxToInteger:(I)Ljava/lang/Integer;
	invokevirtual	Method java/lang/Object.toString:()Ljava/lang/String;
	invokespecial	Method scala/MatchError."<init>":(Ljava/lang/String;)V
	athrow
	iconst_1
	ifeq	l4 // new
	aload_0
	invokevirtual	Method rule:()Lscala/util/parsing/combinator/Parsers$Parser;
	goto	l3 // areturn
l4	new	class scala/MatchError
	dup
	iload_1
	invokestatic	Method scala/runtime/BoxesRunTime.boxToInteger:(I)Ljava/lang/Integer;
	invokevirtual	Method java/lang/Object.toString:()Ljava/lang/String;
	invokespecial	Method scala/MatchError."<init>":(Ljava/lang/String;)V
	athrow
	iconst_1
	ifeq	l5 // new
	aload_0
	invokevirtual	Method seed:()Lscala/util/parsing/combinator/Parsers$ParseResult;
l3	areturn
l5	new	class scala/MatchError
	dup
	iload_1
	invokestatic	Method scala/runtime/BoxesRunTime.boxToInteger:(I)Ljava/lang/Integer;
	invokevirtual	Method java/lang/Object.toString:()Ljava/lang/String;
	invokespecial	Method scala/MatchError."<init>":(Ljava/lang/String;)V
	athrow
  Labels:
   	l1 = 47 // new
   	l2 = 73 // new
   	l4 = 99 // new
   	l3 = 122 // areturn
   	l5 = 123 // new

public int productArity();
  Signature: ()I
  Code:
   Stack=1, Locals=1, Args_size=1
	iconst_3
	ireturn
  Labels:

public java.lang.String productPrefix();
  Signature: ()Ljava/lang/String;
  Code:
   Stack=1, Locals=1, Args_size=1
	ldc	String LR
	areturn
  Labels:

public boolean equals(java.lang.Object);
  Signature: (Ljava/lang/Object;)Z
  Code:
   Stack=4, Locals=6, Args_size=2
	aload_0
	aload_1
	if_acmpeq	l1 // iconst_1
	aload_1
	instanceof	class scala/util/parsing/combinator/PackratParsers$LR
	ifeq	l2 // iconst_1
	aload_1
	checkcast	class scala/util/parsing/combinator/PackratParsers$LR
	invokevirtual	Method scala$util$parsing$combinator$PackratParsers$LR$$$outer:()Lscala/util/parsing/combinator/PackratParsers;
	aload_0
	invokevirtual	Method scala$util$parsing$combinator$PackratParsers$LR$$$outer:()Lscala/util/parsing/combinator/PackratParsers;
	if_acmpne	l2 // iconst_1
	aload_1
	checkcast	class scala/util/parsing/combinator/PackratParsers$LR
	astore_2
	aload_2
	invokevirtual	Method seed:()Lscala/util/parsing/combinator/Parsers$ParseResult;
	astore_3
	aload_2
	invokevirtual	Method rule:()Lscala/util/parsing/combinator/Parsers$Parser;
	astore	4
	aload_2
	invokevirtual	Method head:()Lscala/Option;
	astore	5
	aload_0
	aload_3
	aload	4
	aload	5
	invokespecial	Method gd2$1:(Lscala/util/parsing/combinator/Parsers$ParseResult;Lscala/util/parsing/combinator/Parsers$Parser;Lscala/Option;)Z
	ifeq	l3 // iconst_1
	aload_1
	checkcast	class scala/util/parsing/combinator/PackratParsers$LR
	aload_0
	invokeinterface	InterfaceMethod scala/Equals.canEqual:(Ljava/lang/Object;)Z
	goto	l4 // ifeq
l3	iconst_1
	ifeq	l5 // new
	iconst_0
	goto	l4 // ifeq
l5	new	class scala/MatchError
	dup
	aload_1
	invokevirtual	Method java/lang/Object.toString:()Ljava/lang/String;
	invokespecial	Method scala/MatchError."<init>":(Ljava/lang/String;)V
	athrow
l2	iconst_1
	ifeq	l6 // new
	iconst_0
l4	ifeq	l7 // iconst_0
l1	iconst_1
	goto	l8 // ireturn
l7	iconst_0
l8	ireturn
l6	new	class scala/MatchError
	dup
	aload_1
	invokevirtual	Method java/lang/Object.toString:()Ljava/lang/String;
	invokespecial	Method scala/MatchError."<init>":(Ljava/lang/String;)V
	athrow
  Labels:
   	l3 = 73 // iconst_1
   	l5 = 81 // new
   	l2 = 93 // iconst_1
   	l4 = 98 // ifeq
   	l1 = 101 // iconst_1
   	l7 = 105 // iconst_0
   	l8 = 106 // ireturn
   	l6 = 107 // new
  LocalVariableTable: 
   Start  Length  Slot  Name   Signature
   0      119      0    this       Lscala/util/parsing/combinator/PackratParsers$LR;
   31      62      2    temp16       Lscala/util/parsing/combinator/PackratParsers$LR;
   36      57      3    temp17       Lscala/util/parsing/combinator/Parsers$ParseResult;
   42      51      4    temp18       Lscala/util/parsing/combinator/Parsers$Parser;
   48      45      5    temp19       Lscala/Option;


public java.lang.String toString();
  Signature: ()Ljava/lang/String;
  Code:
   Stack=2, Locals=1, Args_size=1
	getstatic	Field scala/runtime/ScalaRunTime$.MODULE$:Lscala/runtime/ScalaRunTime$;
	aload_0
	invokevirtual	Method scala/runtime/ScalaRunTime$._toString:(Lscala/Product;)Ljava/lang/String;
	areturn
  Labels:

public int hashCode();
  Signature: ()I
  Code:
   Stack=2, Locals=1, Args_size=1
	getstatic	Field scala/runtime/ScalaRunTime$.MODULE$:Lscala/runtime/ScalaRunTime$;
	aload_0
	invokevirtual	Method scala/runtime/ScalaRunTime$._hashCode:(Lscala/Product;)I
	ireturn
  Labels:

public scala.util.parsing.combinator.PackratParsers$LR copy(scala.util.parsing.combinator.Parsers$ParseResult, scala.util.parsing.combinator.Parsers$Parser, scala.Option);
  Signature: (Lscala/util/parsing/combinator/Parsers$ParseResult;Lscala/util/parsing/combinator/Parsers$Parser;Lscala/Option;)Lscala/util/parsing/combinator/PackratParsers$LR;
  Code:
   Stack=6, Locals=4, Args_size=4
	new	class scala/util/parsing/combinator/PackratParsers$LR
	dup
	aload_0
	invokevirtual	Method scala$util$parsing$combinator$PackratParsers$LR$$$outer:()Lscala/util/parsing/combinator/PackratParsers;
	aload_1
	aload_2
	aload_3
	invokespecial	Method "<init>":(Lscala/util/parsing/combinator/PackratParsers;Lscala/util/parsing/combinator/Parsers$ParseResult;Lscala/util/parsing/combinator/Parsers$Parser;Lscala/Option;)V
	areturn
  Labels:
  LocalVariableTable: 
   Start  Length  Slot  Name   Signature
   0      15      0    this       Lscala/util/parsing/combinator/PackratParsers$LR;
   0      15      1    seed       Lscala/util/parsing/combinator/Parsers$ParseResult;
   0      15      2    rule       Lscala/util/parsing/combinator/Parsers$Parser;
   0      15      3    head       Lscala/Option;


public scala.util.parsing.input.Position getPos();
  Signature: ()Lscala/util/parsing/input/Position;
  Code:
   Stack=2, Locals=1, Args_size=1
	aload_0
	invokevirtual	Method scala$util$parsing$combinator$PackratParsers$LR$$$outer:()Lscala/util/parsing/combinator/PackratParsers;
	aload_0
	invokevirtual	Method seed:()Lscala/util/parsing/combinator/Parsers$ParseResult;
	invokestatic	Method scala/util/parsing/combinator/PackratParsers$class.scala$util$parsing$combinator$PackratParsers$$getPosFromResult:(Lscala/util/parsing/combinator/PackratParsers;Lscala/util/parsing/combinator/Parsers$ParseResult;)Lscala/util/parsing/input/Position;
	areturn
  Labels:

public void head_$eq(scala.Option);
  Signature: (Lscala/Option;)V
  Code:
   Stack=2, Locals=2, Args_size=2
	aload_0
	aload_1
	putfield	Field head:Lscala/Option;
	return
  Labels:
  Signature: length = 0x2
   00 FFFFFF83 

public scala.Option head();
  Signature: ()Lscala/Option;
  Code:
   Stack=1, Locals=1, Args_size=1
	aload_0
	getfield	Field head:Lscala/Option;
	areturn
  Labels:
  Signature: length = 0x2
   00 FFFFFF84 

public void rule_$eq(scala.util.parsing.combinator.Parsers$Parser);
  Signature: (Lscala/util/parsing/combinator/Parsers$Parser;)V
  Code:
   Stack=2, Locals=2, Args_size=2
	aload_0
	aload_1
	putfield	Field rule:Lscala/util/parsing/combinator/Parsers$Parser;
	return
  Labels:
  Signature: length = 0x2
   00 FFFFFF87 

public scala.util.parsing.combinator.Parsers$Parser rule();
  Signature: ()Lscala/util/parsing/combinator/Parsers$Parser;
  Code:
   Stack=1, Locals=1, Args_size=1
	aload_0
	getfield	Field rule:Lscala/util/parsing/combinator/Parsers$Parser;
	areturn
  Labels:
  Signature: length = 0x2
   00 FFFFFF88 

public void seed_$eq(scala.util.parsing.combinator.Parsers$ParseResult);
  Signature: (Lscala/util/parsing/combinator/Parsers$ParseResult;)V
  Code:
   Stack=2, Locals=2, Args_size=2
	aload_0
	aload_1
	putfield	Field seed:Lscala/util/parsing/combinator/Parsers$ParseResult;
	return
  Labels:
  Signature: length = 0x2
   00 FFFFFF8B 

public scala.util.parsing.combinator.Parsers$ParseResult seed();
  Signature: ()Lscala/util/parsing/combinator/Parsers$ParseResult;
  Code:
   Stack=1, Locals=1, Args_size=1
	aload_0
	getfield	Field seed:Lscala/util/parsing/combinator/Parsers$ParseResult;
	areturn
  Labels:
  Signature: length = 0x2
   00 FFFFFF8C 

public scala.util.parsing.combinator.Parsers$ParseResult copy$default$1();
  Signature: ()Lscala/util/parsing/combinator/Parsers$ParseResult;
  Code:
   Stack=1, Locals=1, Args_size=1
	aload_0
	invokevirtual	Method seed:()Lscala/util/parsing/combinator/Parsers$ParseResult;
	areturn
  Labels:

public scala.util.parsing.combinator.Parsers$Parser copy$default$2();
  Signature: ()Lscala/util/parsing/combinator/Parsers$Parser;
  Code:
   Stack=1, Locals=1, Args_size=1
	aload_0
	invokevirtual	Method rule:()Lscala/util/parsing/combinator/Parsers$Parser;
	areturn
  Labels:

public scala.Option copy$default$3();
  Signature: ()Lscala/Option;
  Code:
   Stack=1, Locals=1, Args_size=1
	aload_0
	invokevirtual	Method head:()Lscala/Option;
	areturn
  Labels:

public scala.collection.Iterator productElements();
  Signature: ()Lscala/collection/Iterator;
  Code:
   Stack=1, Locals=1, Args_size=1
	aload_0
	invokestatic	Method scala/Product$class.productElements:(Lscala/Product;)Lscala/collection/Iterator;
	areturn
  Labels:
  Deprecated: true

public scala.collection.Iterator productIterator();
  Signature: ()Lscala/collection/Iterator;
  Code:
   Stack=1, Locals=1, Args_size=1
	aload_0
	invokestatic	Method scala/Product$class.productIterator:(Lscala/Product;)Lscala/collection/Iterator;
	areturn
  Labels:

}

