Compiled from "PackratParsers.scala"
public class scala.util.parsing.combinator.PackratParsers$Head extends java.lang.Object implements scala.ScalaObject,scala.Product,java.io.Serializable
  SourceFile: "PackratParsers.scala"
  Scala: length = 0x
   
  InnerClass: 
   public abstract #147= #144 of #146; //Parser=class scala/util/parsing/combinator/Parsers$Parser of class scala/util/parsing/combinator/Parsers
   public #85= #18 of #149; //Head=class scala/util/parsing/combinator/PackratParsers$Head of class scala/util/parsing/combinator/PackratParsers
  minor version: 0
  major version: 49
  Constant pool:
const #1 = Asciz	SourceFile;
const #2 = Asciz	PackratParsers.scala;
const #3 = Asciz	$outer;
const #4 = Asciz	Lscala/util/parsing/combinator/PackratParsers;;
const #5 = Asciz	evalSet;
const #6 = Asciz	Lscala/collection/immutable/List;;
const #7 = Asciz	Lscala/collection/immutable/List<Lscala/util/parsing/combinator/Parsers$Parser<*>;>;;
const #8 = Asciz	Signature;
const #9 = Asciz	involvedSet;
const #10 = Asciz	headParser;
const #11 = Asciz	Lscala/util/parsing/combinator/Parsers$Parser;;
const #12 = Asciz	Lscala/util/parsing/combinator/Parsers$Parser<*>;;
const #13 = Asciz	<init>;
const #14 = Asciz	(Lscala/util/parsing/combinator/PackratParsers;Lscala/util/parsing/combinator/Parsers$Parser;Lscala/collection/immutable/List;Lscala/collection/immutable/List;)V;
const #15 = Asciz	Code;
const #16 = Asciz	LineNumberTable;
const #17 = Asciz	scala/util/parsing/combinator/PackratParsers$Head;
const #18 = class	#17;	//  scala/util/parsing/combinator/PackratParsers$Head
const #19 = NameAndType	#10:#11;//  headParser:Lscala/util/parsing/combinator/Parsers$Parser;
const #20 = Field	#18.#19;	//  scala/util/parsing/combinator/PackratParsers$Head.headParser:Lscala/util/parsing/combinator/Parsers$Parser;
const #21 = NameAndType	#9:#6;//  involvedSet:Lscala/collection/immutable/List;
const #22 = Field	#18.#21;	//  scala/util/parsing/combinator/PackratParsers$Head.involvedSet:Lscala/collection/immutable/List;
const #23 = NameAndType	#5:#6;//  evalSet:Lscala/collection/immutable/List;
const #24 = Field	#18.#23;	//  scala/util/parsing/combinator/PackratParsers$Head.evalSet:Lscala/collection/immutable/List;
const #25 = Asciz	java/lang/NullPointerException;
const #26 = class	#25;	//  java/lang/NullPointerException
const #27 = Asciz	()V;
const #28 = NameAndType	#13:#27;//  "<init>":()V
const #29 = Method	#26.#28;	//  java/lang/NullPointerException."<init>":()V
const #30 = NameAndType	#3:#4;//  $outer:Lscala/util/parsing/combinator/PackratParsers;
const #31 = Field	#18.#30;	//  scala/util/parsing/combinator/PackratParsers$Head.$outer:Lscala/util/parsing/combinator/PackratParsers;
const #32 = Asciz	java/lang/Object;
const #33 = class	#32;	//  java/lang/Object
const #34 = Method	#33.#28;	//  java/lang/Object."<init>":()V
const #35 = Asciz	scala/Product$class;
const #36 = class	#35;	//  scala/Product$class
const #37 = Asciz	$init$;
const #38 = Asciz	(Lscala/Product;)V;
const #39 = NameAndType	#37:#38;//  $init$:(Lscala/Product;)V
const #40 = Method	#36.#39;	//  scala/Product$class.$init$:(Lscala/Product;)V
const #41 = Asciz	this;
const #42 = Asciz	Lscala/util/parsing/combinator/PackratParsers$Head;;
const #43 = Asciz	LocalVariableTable;
const #44 = Asciz	(Lscala/util/parsing/combinator/PackratParsers;Lscala/util/parsing/combinator/Parsers$Parser<*>;Lscala/collection/immutable/List<Lscala/util/parsing/combinator/Parsers$Parser<*>;>;Lscala/collection/immutable/List<Lscala/util/parsing/combinator/Parsers$Parser<*>;>;)V;
const #45 = Asciz	gd3$1;
const #46 = Asciz	(Lscala/util/parsing/combinator/Parsers$Parser;Lscala/collection/immutable/List;Lscala/collection/immutable/List;)Z;
const #47 = Asciz	()Lscala/util/parsing/combinator/Parsers$Parser;;
const #48 = NameAndType	#10:#47;//  headParser:()Lscala/util/parsing/combinator/Parsers$Parser;
const #49 = Method	#18.#48;	//  scala/util/parsing/combinator/PackratParsers$Head.headParser:()Lscala/util/parsing/combinator/Parsers$Parser;
const #50 = Asciz	equals;
const #51 = Asciz	(Ljava/lang/Object;)Z;
const #52 = NameAndType	#50:#51;//  equals:(Ljava/lang/Object;)Z
const #53 = Method	#33.#52;	//  java/lang/Object.equals:(Ljava/lang/Object;)Z
const #54 = Asciz	()Lscala/collection/immutable/List;;
const #55 = NameAndType	#9:#54;//  involvedSet:()Lscala/collection/immutable/List;
const #56 = Method	#18.#55;	//  scala/util/parsing/combinator/PackratParsers$Head.involvedSet:()Lscala/collection/immutable/List;
const #57 = NameAndType	#5:#54;//  evalSet:()Lscala/collection/immutable/List;
const #58 = Method	#18.#57;	//  scala/util/parsing/combinator/PackratParsers$Head.evalSet:()Lscala/collection/immutable/List;
const #59 = Asciz	scala$util$parsing$combinator$PackratParsers$Head$$$outer;
const #60 = Asciz	()Lscala/util/parsing/combinator/PackratParsers;;
const #61 = Asciz	canEqual;
const #62 = Asciz	productElement;
const #63 = Asciz	(I)Ljava/lang/Object;;
const #64 = Asciz	java/lang/IndexOutOfBoundsException;
const #65 = class	#64;	//  java/lang/IndexOutOfBoundsException
const #66 = Asciz	scala/runtime/BoxesRunTime;
const #67 = class	#66;	//  scala/runtime/BoxesRunTime
const #68 = Asciz	boxToInteger;
const #69 = Asciz	(I)Ljava/lang/Integer;;
const #70 = NameAndType	#68:#69;//  boxToInteger:(I)Ljava/lang/Integer;
const #71 = Method	#67.#70;	//  scala/runtime/BoxesRunTime.boxToInteger:(I)Ljava/lang/Integer;
const #72 = Asciz	toString;
const #73 = Asciz	()Ljava/lang/String;;
const #74 = NameAndType	#72:#73;//  toString:()Ljava/lang/String;
const #75 = Method	#33.#74;	//  java/lang/Object.toString:()Ljava/lang/String;
const #76 = Asciz	(Ljava/lang/String;)V;
const #77 = NameAndType	#13:#76;//  "<init>":(Ljava/lang/String;)V
const #78 = Method	#65.#77;	//  java/lang/IndexOutOfBoundsException."<init>":(Ljava/lang/String;)V
const #79 = Asciz	scala/MatchError;
const #80 = class	#79;	//  scala/MatchError
const #81 = Method	#80.#77;	//  scala/MatchError."<init>":(Ljava/lang/String;)V
const #82 = Asciz	productArity;
const #83 = Asciz	()I;
const #84 = Asciz	productPrefix;
const #85 = Asciz	Head;
const #86 = String	#85;	//  Head
const #87 = NameAndType	#59:#60;//  scala$util$parsing$combinator$PackratParsers$Head$$$outer:()Lscala/util/parsing/combinator/PackratParsers;
const #88 = Method	#18.#87;	//  scala/util/parsing/combinator/PackratParsers$Head.scala$util$parsing$combinator$PackratParsers$Head$$$outer:()Lscala/util/parsing/combinator/PackratParsers;
const #89 = NameAndType	#45:#46;//  gd3$1:(Lscala/util/parsing/combinator/Parsers$Parser;Lscala/collection/immutable/List;Lscala/collection/immutable/List;)Z
const #90 = Method	#18.#89;	//  scala/util/parsing/combinator/PackratParsers$Head.gd3$1:(Lscala/util/parsing/combinator/Parsers$Parser;Lscala/collection/immutable/List;Lscala/collection/immutable/List;)Z
const #91 = Asciz	scala/Equals;
const #92 = class	#91;	//  scala/Equals
const #93 = NameAndType	#61:#51;//  canEqual:(Ljava/lang/Object;)Z
const #94 = InterfaceMethod	#92.#93;	//  scala/Equals.canEqual:(Ljava/lang/Object;)Z
const #95 = Asciz	temp22;
const #96 = Asciz	temp23;
const #97 = Asciz	temp24;
const #98 = Asciz	temp25;
const #99 = Asciz	scala/runtime/ScalaRunTime$;
const #100 = class	#99;	//  scala/runtime/ScalaRunTime$
const #101 = Asciz	MODULE$;
const #102 = Asciz	Lscala/runtime/ScalaRunTime$;;
const #103 = NameAndType	#101:#102;//  MODULE$:Lscala/runtime/ScalaRunTime$;
const #104 = Field	#100.#103;	//  scala/runtime/ScalaRunTime$.MODULE$:Lscala/runtime/ScalaRunTime$;
const #105 = Asciz	_toString;
const #106 = Asciz	(Lscala/Product;)Ljava/lang/String;;
const #107 = NameAndType	#105:#106;//  _toString:(Lscala/Product;)Ljava/lang/String;
const #108 = Method	#100.#107;	//  scala/runtime/ScalaRunTime$._toString:(Lscala/Product;)Ljava/lang/String;
const #109 = Asciz	hashCode;
const #110 = Asciz	_hashCode;
const #111 = Asciz	(Lscala/Product;)I;
const #112 = NameAndType	#110:#111;//  _hashCode:(Lscala/Product;)I
const #113 = Method	#100.#112;	//  scala/runtime/ScalaRunTime$._hashCode:(Lscala/Product;)I
const #114 = Asciz	copy;
const #115 = Asciz	(Lscala/util/parsing/combinator/Parsers$Parser;Lscala/collection/immutable/List;Lscala/collection/immutable/List;)Lscala/util/parsing/combinator/PackratParsers$Head;;
const #116 = NameAndType	#13:#14;//  "<init>":(Lscala/util/parsing/combinator/PackratParsers;Lscala/util/parsing/combinator/Parsers$Parser;Lscala/collection/immutable/List;Lscala/collection/immutable/List;)V
const #117 = Method	#18.#116;	//  scala/util/parsing/combinator/PackratParsers$Head."<init>":(Lscala/util/parsing/combinator/PackratParsers;Lscala/util/parsing/combinator/Parsers$Parser;Lscala/collection/immutable/List;Lscala/collection/immutable/List;)V
const #118 = Asciz	getHead;
const #119 = Asciz	()Lscala/util/parsing/combinator/Parsers$Parser<Ljava/lang/Object;>;;
const #120 = Asciz	evalSet_$eq;
const #121 = Asciz	(Lscala/collection/immutable/List;)V;
const #122 = Asciz	(Lscala/collection/immutable/List<Lscala/util/parsing/combinator/Parsers$Parser<*>;>;)V;
const #123 = Asciz	()Lscala/collection/immutable/List<Lscala/util/parsing/combinator/Parsers$Parser<*>;>;;
const #124 = Asciz	involvedSet_$eq;
const #125 = Asciz	headParser_$eq;
const #126 = Asciz	(Lscala/util/parsing/combinator/Parsers$Parser;)V;
const #127 = Asciz	(Lscala/util/parsing/combinator/Parsers$Parser<*>;)V;
const #128 = Asciz	()Lscala/util/parsing/combinator/Parsers$Parser<*>;;
const #129 = Asciz	copy$default$1;
const #130 = Asciz	copy$default$2;
const #131 = Asciz	copy$default$3;
const #132 = Asciz	productElements;
const #133 = Asciz	()Lscala/collection/Iterator;;
const #134 = Asciz	(Lscala/Product;)Lscala/collection/Iterator;;
const #135 = NameAndType	#132:#134;//  productElements:(Lscala/Product;)Lscala/collection/Iterator;
const #136 = Method	#36.#135;	//  scala/Product$class.productElements:(Lscala/Product;)Lscala/collection/Iterator;
const #137 = Asciz	Deprecated;
const #138 = Asciz	productIterator;
const #139 = NameAndType	#138:#134;//  productIterator:(Lscala/Product;)Lscala/collection/Iterator;
const #140 = Method	#36.#139;	//  scala/Product$class.productIterator:(Lscala/Product;)Lscala/collection/Iterator;
const #141 = Asciz	Scala;
const #142 = Asciz	InnerClasses;
const #143 = Asciz	scala/util/parsing/combinator/Parsers$Parser;
const #144 = class	#143;	//  scala/util/parsing/combinator/Parsers$Parser
const #145 = Asciz	scala/util/parsing/combinator/Parsers;
const #146 = class	#145;	//  scala/util/parsing/combinator/Parsers
const #147 = Asciz	Parser;
const #148 = Asciz	scala/util/parsing/combinator/PackratParsers;
const #149 = class	#148;	//  scala/util/parsing/combinator/PackratParsers
const #150 = Asciz	scala/ScalaObject;
const #151 = class	#150;	//  scala/ScalaObject
const #152 = Asciz	scala/Product;
const #153 = class	#152;	//  scala/Product
const #154 = Asciz	java/io/Serializable;
const #155 = class	#154;	//  java/io/Serializable

{
public final scala.util.parsing.combinator.PackratParsers $outer;

public scala.util.parsing.combinator.PackratParsers$Head(scala.util.parsing.combinator.PackratParsers, scala.util.parsing.combinator.Parsers$Parser, scala.collection.immutable.List, scala.collection.immutable.List);
  Code:
   Stack=2, Locals=5, Args_size=5
   0:	aload_0
   1:	aload_2
   2:	putfield	#20; //Field headParser:Lscala/util/parsing/combinator/Parsers$Parser;
   5:	aload_0
   6:	aload_3
   7:	putfield	#22; //Field involvedSet:Lscala/collection/immutable/List;
   10:	aload_0
   11:	aload	4
   13:	putfield	#24; //Field evalSet:Lscala/collection/immutable/List;
   16:	aload_1
   17:	ifnonnull	28
   20:	new	#26; //class java/lang/NullPointerException
   23:	dup
   24:	invokespecial	#29; //Method java/lang/NullPointerException."<init>":()V
   27:	athrow
   28:	aload_0
   29:	aload_1
   30:	putfield	#31; //Field $outer:Lscala/util/parsing/combinator/PackratParsers;
   33:	aload_0
   34:	invokespecial	#34; //Method java/lang/Object."<init>":()V
   37:	aload_0
   38:	invokestatic	#40; //Method scala/Product$class.$init$:(Lscala/Product;)V
   41:	return
  LineNumberTable: 
   line 145: 0

  LocalVariableTable: 
   Start  Length  Slot  Name   Signature
   0      42      0    this       Lscala/util/parsing/combinator/PackratParsers$Head;
   0      42      1    $outer       Lscala/util/parsing/combinator/PackratParsers;
   0      42      2    headParser       Lscala/util/parsing/combinator/Parsers$Parser;
   0      42      3    involvedSet       Lscala/collection/immutable/List;
   0      42      4    evalSet       Lscala/collection/immutable/List;

  Signature: length = 0x2
   00 2C 

public scala.util.parsing.combinator.PackratParsers scala$util$parsing$combinator$PackratParsers$Head$$$outer();
  Code:
   Stack=1, Locals=1, Args_size=1
   0:	aload_0
   1:	getfield	#31; //Field $outer:Lscala/util/parsing/combinator/PackratParsers;
   4:	areturn
  LineNumberTable: 
   line 145: 0


public boolean canEqual(java.lang.Object);
  Code:
   Stack=1, Locals=2, Args_size=2
   0:	aload_1
   1:	instanceof	#18; //class scala/util/parsing/combinator/PackratParsers$Head
   4:	ireturn
  LineNumberTable: 
   line 145: 0


public java.lang.Object productElement(int);
  Code:
   Stack=3, Locals=2, Args_size=2
   0:	iload_1
   1:	tableswitch{ //0 to 2
		0: 114;
		1: 88;
		2: 62;
		default: 28 }
   28:	iconst_1
   29:	ifeq	47
   32:	new	#65; //class java/lang/IndexOutOfBoundsException
   35:	dup
   36:	iload_1
   37:	invokestatic	#71; //Method scala/runtime/BoxesRunTime.boxToInteger:(I)Ljava/lang/Integer;
   40:	invokevirtual	#75; //Method java/lang/Object.toString:()Ljava/lang/String;
   43:	invokespecial	#78; //Method java/lang/IndexOutOfBoundsException."<init>":(Ljava/lang/String;)V
   46:	athrow
   47:	new	#80; //class scala/MatchError
   50:	dup
   51:	iload_1
   52:	invokestatic	#71; //Method scala/runtime/BoxesRunTime.boxToInteger:(I)Ljava/lang/Integer;
   55:	invokevirtual	#75; //Method java/lang/Object.toString:()Ljava/lang/String;
   58:	invokespecial	#81; //Method scala/MatchError."<init>":(Ljava/lang/String;)V
   61:	athrow
   62:	iconst_1
   63:	ifeq	73
   66:	aload_0
   67:	invokevirtual	#58; //Method evalSet:()Lscala/collection/immutable/List;
   70:	goto	122
   73:	new	#80; //class scala/MatchError
   76:	dup
   77:	iload_1
   78:	invokestatic	#71; //Method scala/runtime/BoxesRunTime.boxToInteger:(I)Ljava/lang/Integer;
   81:	invokevirtual	#75; //Method java/lang/Object.toString:()Ljava/lang/String;
   84:	invokespecial	#81; //Method scala/MatchError."<init>":(Ljava/lang/String;)V
   87:	athrow
   88:	iconst_1
   89:	ifeq	99
   92:	aload_0
   93:	invokevirtual	#56; //Method involvedSet:()Lscala/collection/immutable/List;
   96:	goto	122
   99:	new	#80; //class scala/MatchError
   102:	dup
   103:	iload_1
   104:	invokestatic	#71; //Method scala/runtime/BoxesRunTime.boxToInteger:(I)Ljava/lang/Integer;
   107:	invokevirtual	#75; //Method java/lang/Object.toString:()Ljava/lang/String;
   110:	invokespecial	#81; //Method scala/MatchError."<init>":(Ljava/lang/String;)V
   113:	athrow
   114:	iconst_1
   115:	ifeq	123
   118:	aload_0
   119:	invokevirtual	#49; //Method headParser:()Lscala/util/parsing/combinator/Parsers$Parser;
   122:	areturn
   123:	new	#80; //class scala/MatchError
   126:	dup
   127:	iload_1
   128:	invokestatic	#71; //Method scala/runtime/BoxesRunTime.boxToInteger:(I)Ljava/lang/Integer;
   131:	invokevirtual	#75; //Method java/lang/Object.toString:()Ljava/lang/String;
   134:	invokespecial	#81; //Method scala/MatchError."<init>":(Ljava/lang/String;)V
   137:	athrow
  LineNumberTable: 
   line 145: 0
   line 21: 28
   line 145: 32
   line 21: 62
   line 145: 66
   line 21: 88
   line 145: 92
   line 21: 114
   line 145: 118


public int productArity();
  Code:
   Stack=1, Locals=1, Args_size=1
   0:	iconst_3
   1:	ireturn
  LineNumberTable: 
   line 145: 0


public java.lang.String productPrefix();
  Code:
   Stack=1, Locals=1, Args_size=1
   0:	ldc	#86; //String Head
   2:	areturn
  LineNumberTable: 
   line 145: 0


public boolean equals(java.lang.Object);
  Code:
   Stack=4, Locals=6, Args_size=2
   0:	aload_0
   1:	aload_1
   2:	if_acmpeq	101
   5:	aload_1
   6:	instanceof	#18; //class scala/util/parsing/combinator/PackratParsers$Head
   9:	ifeq	93
   12:	aload_1
   13:	checkcast	#18; //class scala/util/parsing/combinator/PackratParsers$Head
   16:	invokevirtual	#88; //Method scala$util$parsing$combinator$PackratParsers$Head$$$outer:()Lscala/util/parsing/combinator/PackratParsers;
   19:	aload_0
   20:	invokevirtual	#88; //Method scala$util$parsing$combinator$PackratParsers$Head$$$outer:()Lscala/util/parsing/combinator/PackratParsers;
   23:	if_acmpne	93
   26:	aload_1
   27:	checkcast	#18; //class scala/util/parsing/combinator/PackratParsers$Head
   30:	astore_2
   31:	aload_2
   32:	invokevirtual	#49; //Method headParser:()Lscala/util/parsing/combinator/Parsers$Parser;
   35:	astore_3
   36:	aload_2
   37:	invokevirtual	#56; //Method involvedSet:()Lscala/collection/immutable/List;
   40:	astore	4
   42:	aload_2
   43:	invokevirtual	#58; //Method evalSet:()Lscala/collection/immutable/List;
   46:	astore	5
   48:	aload_0
   49:	aload_3
   50:	aload	4
   52:	aload	5
   54:	invokespecial	#90; //Method gd3$1:(Lscala/util/parsing/combinator/Parsers$Parser;Lscala/collection/immutable/List;Lscala/collection/immutable/List;)Z
   57:	ifeq	73
   60:	aload_1
   61:	checkcast	#18; //class scala/util/parsing/combinator/PackratParsers$Head
   64:	aload_0
   65:	invokeinterface	#94,  2; //InterfaceMethod scala/Equals.canEqual:(Ljava/lang/Object;)Z
   70:	goto	98
   73:	iconst_1
   74:	ifeq	81
   77:	iconst_0
   78:	goto	98
   81:	new	#80; //class scala/MatchError
   84:	dup
   85:	aload_1
   86:	invokevirtual	#75; //Method java/lang/Object.toString:()Ljava/lang/String;
   89:	invokespecial	#81; //Method scala/MatchError."<init>":(Ljava/lang/String;)V
   92:	athrow
   93:	iconst_1
   94:	ifeq	107
   97:	iconst_0
   98:	ifeq	105
   101:	iconst_1
   102:	goto	106
   105:	iconst_0
   106:	ireturn
   107:	new	#80; //class scala/MatchError
   110:	dup
   111:	aload_1
   112:	invokevirtual	#75; //Method java/lang/Object.toString:()Ljava/lang/String;
   115:	invokespecial	#81; //Method scala/MatchError."<init>":(Ljava/lang/String;)V
   118:	athrow
  LineNumberTable: 
   line 145: 0
   line 21: 73
   line 145: 81
   line 21: 93
   line 145: 98

  LocalVariableTable: 
   Start  Length  Slot  Name   Signature
   0      119      0    this       Lscala/util/parsing/combinator/PackratParsers$Head;
   31      62      2    temp22       Lscala/util/parsing/combinator/PackratParsers$Head;
   36      57      3    temp23       Lscala/util/parsing/combinator/Parsers$Parser;
   42      51      4    temp24       Lscala/collection/immutable/List;
   48      45      5    temp25       Lscala/collection/immutable/List;


public java.lang.String toString();
  Code:
   Stack=2, Locals=1, Args_size=1
   0:	getstatic	#104; //Field scala/runtime/ScalaRunTime$.MODULE$:Lscala/runtime/ScalaRunTime$;
   3:	aload_0
   4:	invokevirtual	#108; //Method scala/runtime/ScalaRunTime$._toString:(Lscala/Product;)Ljava/lang/String;
   7:	areturn
  LineNumberTable: 
   line 145: 0


public int hashCode();
  Code:
   Stack=2, Locals=1, Args_size=1
   0:	getstatic	#104; //Field scala/runtime/ScalaRunTime$.MODULE$:Lscala/runtime/ScalaRunTime$;
   3:	aload_0
   4:	invokevirtual	#113; //Method scala/runtime/ScalaRunTime$._hashCode:(Lscala/Product;)I
   7:	ireturn
  LineNumberTable: 
   line 145: 0


public scala.util.parsing.combinator.PackratParsers$Head copy(scala.util.parsing.combinator.Parsers$Parser, scala.collection.immutable.List, scala.collection.immutable.List);
  Code:
   Stack=6, Locals=4, Args_size=4
   0:	new	#18; //class scala/util/parsing/combinator/PackratParsers$Head
   3:	dup
   4:	aload_0
   5:	invokevirtual	#88; //Method scala$util$parsing$combinator$PackratParsers$Head$$$outer:()Lscala/util/parsing/combinator/PackratParsers;
   8:	aload_1
   9:	aload_2
   10:	aload_3
   11:	invokespecial	#117; //Method "<init>":(Lscala/util/parsing/combinator/PackratParsers;Lscala/util/parsing/combinator/Parsers$Parser;Lscala/collection/immutable/List;Lscala/collection/immutable/List;)V
   14:	areturn
  LineNumberTable: 
   line 145: 0

  LocalVariableTable: 
   Start  Length  Slot  Name   Signature
   0      15      0    this       Lscala/util/parsing/combinator/PackratParsers$Head;
   0      15      1    headParser       Lscala/util/parsing/combinator/Parsers$Parser;
   0      15      2    involvedSet       Lscala/collection/immutable/List;
   0      15      3    evalSet       Lscala/collection/immutable/List;


public scala.util.parsing.combinator.Parsers$Parser getHead();
  Code:
   Stack=1, Locals=1, Args_size=1
   0:	aload_0
   1:	invokevirtual	#49; //Method headParser:()Lscala/util/parsing/combinator/Parsers$Parser;
   4:	areturn
  LineNumberTable: 
   line 146: 0

  Signature: length = 0x2
   00 77 

public void evalSet_$eq(scala.collection.immutable.List);
  Code:
   Stack=2, Locals=2, Args_size=2
   0:	aload_0
   1:	aload_1
   2:	putfield	#24; //Field evalSet:Lscala/collection/immutable/List;
   5:	return
  LineNumberTable: 
   line 145: 0

  Signature: length = 0x2
   00 7A 

public scala.collection.immutable.List evalSet();
  Code:
   Stack=1, Locals=1, Args_size=1
   0:	aload_0
   1:	getfield	#24; //Field evalSet:Lscala/collection/immutable/List;
   4:	areturn
  LineNumberTable: 
   line 145: 0

  Signature: length = 0x2
   00 7B 

public void involvedSet_$eq(scala.collection.immutable.List);
  Code:
   Stack=2, Locals=2, Args_size=2
   0:	aload_0
   1:	aload_1
   2:	putfield	#22; //Field involvedSet:Lscala/collection/immutable/List;
   5:	return
  LineNumberTable: 
   line 145: 0

  Signature: length = 0x2
   00 7A 

public scala.collection.immutable.List involvedSet();
  Code:
   Stack=1, Locals=1, Args_size=1
   0:	aload_0
   1:	getfield	#22; //Field involvedSet:Lscala/collection/immutable/List;
   4:	areturn
  LineNumberTable: 
   line 145: 0

  Signature: length = 0x2
   00 7B 

public void headParser_$eq(scala.util.parsing.combinator.Parsers$Parser);
  Code:
   Stack=2, Locals=2, Args_size=2
   0:	aload_0
   1:	aload_1
   2:	putfield	#20; //Field headParser:Lscala/util/parsing/combinator/Parsers$Parser;
   5:	return
  LineNumberTable: 
   line 145: 0

  Signature: length = 0x2
   00 7F 

public scala.util.parsing.combinator.Parsers$Parser headParser();
  Code:
   Stack=1, Locals=1, Args_size=1
   0:	aload_0
   1:	getfield	#20; //Field headParser:Lscala/util/parsing/combinator/Parsers$Parser;
   4:	areturn
  LineNumberTable: 
   line 145: 0

  Signature: length = 0x2
   00 FFFFFF80 

public scala.util.parsing.combinator.Parsers$Parser copy$default$1();
  Code:
   Stack=1, Locals=1, Args_size=1
   0:	aload_0
   1:	invokevirtual	#49; //Method headParser:()Lscala/util/parsing/combinator/Parsers$Parser;
   4:	areturn
  LineNumberTable: 
   line 145: 0


public scala.collection.immutable.List copy$default$2();
  Code:
   Stack=1, Locals=1, Args_size=1
   0:	aload_0
   1:	invokevirtual	#56; //Method involvedSet:()Lscala/collection/immutable/List;
   4:	areturn
  LineNumberTable: 
   line 145: 0


public scala.collection.immutable.List copy$default$3();
  Code:
   Stack=1, Locals=1, Args_size=1
   0:	aload_0
   1:	invokevirtual	#58; //Method evalSet:()Lscala/collection/immutable/List;
   4:	areturn
  LineNumberTable: 
   line 145: 0


public scala.collection.Iterator productElements();
  Code:
   Stack=1, Locals=1, Args_size=1
   0:	aload_0
   1:	invokestatic	#136; //Method scala/Product$class.productElements:(Lscala/Product;)Lscala/collection/Iterator;
   4:	areturn
  LineNumberTable: 
   line 145: 0

  Deprecated: true

public scala.collection.Iterator productIterator();
  Code:
   Stack=1, Locals=1, Args_size=1
   0:	aload_0
   1:	invokestatic	#140; //Method scala/Product$class.productIterator:(Lscala/Product;)Lscala/collection/Iterator;
   4:	areturn
  LineNumberTable: 
   line 145: 0


}

