Compiled from "PackratParsers.scala"
public class scala.util.parsing.combinator.PackratParsers$PackratReader extends scala.util.parsing.input.Reader implements scala.ScalaObject
  SourceFile: "PackratParsers.scala"
  Scala: length = 0x
   
  Signature: length = 0x2
   00 76 
  InnerClass: 
   public abstract Parser=class scala/util/parsing/combinator/Parsers$Parser of class scala/util/parsing/combinator/Parsers
   public MemoEntry=class scala/util/parsing/combinator/PackratParsers$MemoEntry of class scala/util/parsing/combinator/PackratParsers
   public PackratReader=class scala/util/parsing/combinator/PackratParsers$PackratReader of class scala/util/parsing/combinator/PackratParsers
   public final $anon$3=class scala/util/parsing/combinator/PackratParsers$PackratReader$$anon$3 of class scala/util/parsing/combinator/PackratParsers$PackratReader
  minor version: 0
  major version: 49
  Constant pool:
Asciz	SourceFile;
Asciz	PackratParsers.scala;
Asciz	scala$util$parsing$combinator$PackratParsers$PackratReader$$underlying;
Asciz	Lscala/util/parsing/input/Reader;;
Asciz	scala$util$parsing$combinator$PackratParsers$$cache;
Asciz	Lscala/collection/mutable/HashMap;;
Asciz	scala$util$parsing$combinator$PackratParsers$$recursionHeads;
Asciz	scala$util$parsing$combinator$PackratParsers$$lrStack;
Asciz	Lscala/collection/immutable/List;;
Asciz	$outer;
Asciz	Lscala/util/parsing/combinator/PackratParsers;;
Asciz	()Lscala/collection/mutable/HashMap;;
Asciz	Code;
Asciz	LineNumberTable;
Asciz	scala/util/parsing/combinator/PackratParsers$PackratReader;
class	scala/util/parsing/combinator/PackratParsers$PackratReader
NameAndType	scala$util$parsing$combinator$PackratParsers$$cache:Lscala/collection/mutable/HashMap;
Field	scala/util/parsing/combinator/PackratParsers$PackratReader.scala$util$parsing$combinator$PackratParsers$$cache:Lscala/collection/mutable/HashMap;
Asciz	scala$util$parsing$combinator$PackratParsers$$getFromCache;
Asciz	(Lscala/util/parsing/combinator/Parsers$Parser;)Lscala/Option;;
NameAndType	scala$util$parsing$combinator$PackratParsers$$cache:()Lscala/collection/mutable/HashMap;
Method	scala/util/parsing/combinator/PackratParsers$PackratReader.scala$util$parsing$combinator$PackratParsers$$cache:()Lscala/collection/mutable/HashMap;
Asciz	scala/Tuple2;
class	scala/Tuple2
Asciz	pos;
Asciz	()Lscala/util/parsing/input/Position;;
NameAndType	pos:()Lscala/util/parsing/input/Position;
Method	scala/util/parsing/combinator/PackratParsers$PackratReader.pos:()Lscala/util/parsing/input/Position;
Asciz	<init>;
Asciz	(Ljava/lang/Object;Ljava/lang/Object;)V;
NameAndType	"<init>":(Ljava/lang/Object;Ljava/lang/Object;)V
Method	scala/Tuple2."<init>":(Ljava/lang/Object;Ljava/lang/Object;)V
Asciz	scala/collection/mutable/HashMap;
class	scala/collection/mutable/HashMap
Asciz	get;
Asciz	(Ljava/lang/Object;)Lscala/Option;;
NameAndType	get:(Ljava/lang/Object;)Lscala/Option;
Method	scala/collection/mutable/HashMap.get:(Ljava/lang/Object;)Lscala/Option;
Asciz	this;
Asciz	Lscala/util/parsing/combinator/PackratParsers$PackratReader;;
Asciz	p;
Asciz	Lscala/util/parsing/combinator/Parsers$Parser;;
Asciz	LocalVariableTable;
Asciz	scala$util$parsing$combinator$PackratParsers$$updateCacheAndGet;
Asciz	(Lscala/util/parsing/combinator/Parsers$Parser;Lscala/util/parsing/combinator/PackratParsers$MemoEntry;)Lscala/util/parsing/combinator/PackratParsers$MemoEntry;;
Asciz	put;
Asciz	(Ljava/lang/Object;Ljava/lang/Object;)Lscala/Option;;
NameAndType	put:(Ljava/lang/Object;Ljava/lang/Object;)Lscala/Option;
Method	scala/collection/mutable/HashMap.put:(Ljava/lang/Object;Ljava/lang/Object;)Lscala/Option;
Asciz	w;
Asciz	Lscala/util/parsing/combinator/PackratParsers$MemoEntry;;
NameAndType	scala$util$parsing$combinator$PackratParsers$$recursionHeads:Lscala/collection/mutable/HashMap;
Field	scala/util/parsing/combinator/PackratParsers$PackratReader.scala$util$parsing$combinator$PackratParsers$$recursionHeads:Lscala/collection/mutable/HashMap;
Asciz	()Lscala/collection/immutable/List;;
NameAndType	scala$util$parsing$combinator$PackratParsers$$lrStack:Lscala/collection/immutable/List;
Field	scala/util/parsing/combinator/PackratParsers$PackratReader.scala$util$parsing$combinator$PackratParsers$$lrStack:Lscala/collection/immutable/List;
Asciz	scala$util$parsing$combinator$PackratParsers$$lrStack_$eq;
Asciz	(Lscala/collection/immutable/List;)V;
Asciz	source;
Asciz	()Ljava/lang/CharSequence;;
NameAndType	scala$util$parsing$combinator$PackratParsers$PackratReader$$underlying:Lscala/util/parsing/input/Reader;
Field	scala/util/parsing/combinator/PackratParsers$PackratReader.scala$util$parsing$combinator$PackratParsers$PackratReader$$underlying:Lscala/util/parsing/input/Reader;
Asciz	scala/util/parsing/input/Reader;
class	scala/util/parsing/input/Reader
NameAndType	source:()Ljava/lang/CharSequence;
Method	scala/util/parsing/input/Reader.source:()Ljava/lang/CharSequence;
Asciz	offset;
Asciz	()I;
NameAndType	offset:()I
Method	scala/util/parsing/input/Reader.offset:()I
Asciz	first;
Asciz	()Ljava/lang/Object;;
NameAndType	first:()Ljava/lang/Object;
Method	scala/util/parsing/input/Reader.first:()Ljava/lang/Object;
Asciz	()TT;;
Asciz	Signature;
Asciz	rest;
Asciz	()Lscala/util/parsing/input/Reader;;
Asciz	scala/util/parsing/combinator/PackratParsers$PackratReader$$anon$3;
class	scala/util/parsing/combinator/PackratParsers$PackratReader$$anon$3
Asciz	(Lscala/util/parsing/combinator/PackratParsers$PackratReader;)V;
NameAndType	"<init>":(Lscala/util/parsing/combinator/PackratParsers$PackratReader;)V
Method	scala/util/parsing/combinator/PackratParsers$PackratReader$$anon$3."<init>":(Lscala/util/parsing/combinator/PackratParsers$PackratReader;)V
Asciz	()Lscala/util/parsing/input/Reader<TT;>;;
Method	scala/util/parsing/input/Reader.pos:()Lscala/util/parsing/input/Position;
Asciz	atEnd;
Asciz	()Z;
NameAndType	atEnd:()Z
Method	scala/util/parsing/input/Reader.atEnd:()Z
Asciz	scala$util$parsing$combinator$PackratParsers$PackratReader$$$outer;
Asciz	()Lscala/util/parsing/combinator/PackratParsers;;
NameAndType	$outer:Lscala/util/parsing/combinator/PackratParsers;
Field	scala/util/parsing/combinator/PackratParsers$PackratReader.$outer:Lscala/util/parsing/combinator/PackratParsers;
Asciz	(Lscala/util/parsing/combinator/PackratParsers;Lscala/util/parsing/input/Reader;)V;
Asciz	java/lang/NullPointerException;
class	java/lang/NullPointerException
Asciz	()V;
NameAndType	"<init>":()V
Method	java/lang/NullPointerException."<init>":()V
Method	scala/util/parsing/input/Reader."<init>":()V
Asciz	scala/collection/mutable/HashMap$;
class	scala/collection/mutable/HashMap$
Asciz	MODULE$;
Asciz	Lscala/collection/mutable/HashMap$;;
NameAndType	MODULE$:Lscala/collection/mutable/HashMap$;
Field	scala/collection/mutable/HashMap$.MODULE$:Lscala/collection/mutable/HashMap$;
Asciz	empty;
NameAndType	empty:()Lscala/collection/mutable/HashMap;
Method	scala/collection/mutable/HashMap$.empty:()Lscala/collection/mutable/HashMap;
Asciz	scala/collection/immutable/Nil$;
class	scala/collection/immutable/Nil$
Asciz	Lscala/collection/immutable/Nil$;;
NameAndType	MODULE$:Lscala/collection/immutable/Nil$;
Field	scala/collection/immutable/Nil$.MODULE$:Lscala/collection/immutable/Nil$;
Asciz	underlying;
Asciz	(Lscala/util/parsing/combinator/PackratParsers;Lscala/util/parsing/input/Reader<TT;>;)V;
Asciz	Scala;
Asciz	<T:Ljava/lang/Object;>Lscala/util/parsing/input/Reader<TT;>;Lscala/ScalaObject;;
Asciz	InnerClasses;
Asciz	scala/util/parsing/combinator/Parsers$Parser;
class	scala/util/parsing/combinator/Parsers$Parser
Asciz	scala/util/parsing/combinator/Parsers;
class	scala/util/parsing/combinator/Parsers
Asciz	Parser;
Asciz	scala/util/parsing/combinator/PackratParsers$MemoEntry;
class	scala/util/parsing/combinator/PackratParsers$MemoEntry
Asciz	scala/util/parsing/combinator/PackratParsers;
class	scala/util/parsing/combinator/PackratParsers
Asciz	MemoEntry;
Asciz	PackratReader;
Asciz	$anon$3;
Asciz	scala/ScalaObject;
class	scala/ScalaObject

{
public final scala.util.parsing.input.Reader scala$util$parsing$combinator$PackratParsers$PackratReader$$underlying;
  Signature: Lscala/util/parsing/input/Reader;

private final scala.collection.mutable.HashMap scala$util$parsing$combinator$PackratParsers$$cache;
  Signature: Lscala/collection/mutable/HashMap;

private final scala.collection.mutable.HashMap scala$util$parsing$combinator$PackratParsers$$recursionHeads;
  Signature: Lscala/collection/mutable/HashMap;

private scala.collection.immutable.List scala$util$parsing$combinator$PackratParsers$$lrStack;
  Signature: Lscala/collection/immutable/List;

public final scala.util.parsing.combinator.PackratParsers $outer;
  Signature: Lscala/util/parsing/combinator/PackratParsers;

public scala.collection.mutable.HashMap scala$util$parsing$combinator$PackratParsers$$cache();
  Signature: ()Lscala/collection/mutable/HashMap;
  Code:
   Stack=1, Locals=1, Args_size=1
	aload_0
	getfield	Field scala$util$parsing$combinator$PackratParsers$$cache:Lscala/collection/mutable/HashMap;
	areturn
  Labels:

public scala.Option scala$util$parsing$combinator$PackratParsers$$getFromCache(scala.util.parsing.combinator.Parsers$Parser);
  Signature: (Lscala/util/parsing/combinator/Parsers$Parser;)Lscala/Option;
  Code:
   Stack=5, Locals=2, Args_size=2
	aload_0
	invokevirtual	Method scala$util$parsing$combinator$PackratParsers$$cache:()Lscala/collection/mutable/HashMap;
	new	class scala/Tuple2
	dup
	aload_1
	aload_0
	invokevirtual	Method pos:()Lscala/util/parsing/input/Position;
	invokespecial	Method scala/Tuple2."<init>":(Ljava/lang/Object;Ljava/lang/Object;)V
	invokevirtual	Method scala/collection/mutable/HashMap.get:(Ljava/lang/Object;)Lscala/Option;
	areturn
  Labels:
  LocalVariableTable: 
   Start  Length  Slot  Name   Signature
   0      20      0    this       Lscala/util/parsing/combinator/PackratParsers$PackratReader;
   0      20      1    p       Lscala/util/parsing/combinator/Parsers$Parser;


public scala.util.parsing.combinator.PackratParsers$MemoEntry scala$util$parsing$combinator$PackratParsers$$updateCacheAndGet(scala.util.parsing.combinator.Parsers$Parser, scala.util.parsing.combinator.PackratParsers$MemoEntry);
  Signature: (Lscala/util/parsing/combinator/Parsers$Parser;Lscala/util/parsing/combinator/PackratParsers$MemoEntry;)Lscala/util/parsing/combinator/PackratParsers$MemoEntry;
  Code:
   Stack=5, Locals=3, Args_size=3
	aload_0
	invokevirtual	Method scala$util$parsing$combinator$PackratParsers$$cache:()Lscala/collection/mutable/HashMap;
	new	class scala/Tuple2
	dup
	aload_1
	aload_0
	invokevirtual	Method pos:()Lscala/util/parsing/input/Position;
	invokespecial	Method scala/Tuple2."<init>":(Ljava/lang/Object;Ljava/lang/Object;)V
	aload_2
	invokevirtual	Method scala/collection/mutable/HashMap.put:(Ljava/lang/Object;Ljava/lang/Object;)Lscala/Option;
	pop
	aload_2
	areturn
  Labels:
  LocalVariableTable: 
   Start  Length  Slot  Name   Signature
   0      23      0    this       Lscala/util/parsing/combinator/PackratParsers$PackratReader;
   0      23      1    p       Lscala/util/parsing/combinator/Parsers$Parser;
   0      23      2    w       Lscala/util/parsing/combinator/PackratParsers$MemoEntry;


public scala.collection.mutable.HashMap scala$util$parsing$combinator$PackratParsers$$recursionHeads();
  Signature: ()Lscala/collection/mutable/HashMap;
  Code:
   Stack=1, Locals=1, Args_size=1
	aload_0
	getfield	Field scala$util$parsing$combinator$PackratParsers$$recursionHeads:Lscala/collection/mutable/HashMap;
	areturn
  Labels:

public scala.collection.immutable.List scala$util$parsing$combinator$PackratParsers$$lrStack();
  Signature: ()Lscala/collection/immutable/List;
  Code:
   Stack=1, Locals=1, Args_size=1
	aload_0
	getfield	Field scala$util$parsing$combinator$PackratParsers$$lrStack:Lscala/collection/immutable/List;
	areturn
  Labels:

public void scala$util$parsing$combinator$PackratParsers$$lrStack_$eq(scala.collection.immutable.List);
  Signature: (Lscala/collection/immutable/List;)V
  Code:
   Stack=2, Locals=2, Args_size=2
	aload_0
	aload_1
	putfield	Field scala$util$parsing$combinator$PackratParsers$$lrStack:Lscala/collection/immutable/List;
	return
  Labels:

public java.lang.CharSequence source();
  Signature: ()Ljava/lang/CharSequence;
  Code:
   Stack=1, Locals=1, Args_size=1
	aload_0
	getfield	Field scala$util$parsing$combinator$PackratParsers$PackratReader$$underlying:Lscala/util/parsing/input/Reader;
	invokevirtual	Method scala/util/parsing/input/Reader.source:()Ljava/lang/CharSequence;
	areturn
  Labels:

public int offset();
  Signature: ()I
  Code:
   Stack=1, Locals=1, Args_size=1
	aload_0
	getfield	Field scala$util$parsing$combinator$PackratParsers$PackratReader$$underlying:Lscala/util/parsing/input/Reader;
	invokevirtual	Method scala/util/parsing/input/Reader.offset:()I
	ireturn
  Labels:

public java.lang.Object first();
  Signature: ()Ljava/lang/Object;
  Code:
   Stack=1, Locals=1, Args_size=1
	aload_0
	getfield	Field scala$util$parsing$combinator$PackratParsers$PackratReader$$underlying:Lscala/util/parsing/input/Reader;
	invokevirtual	Method scala/util/parsing/input/Reader.first:()Ljava/lang/Object;
	areturn
  Labels:
  Signature: length = 0x2
   00 4B 

public scala.util.parsing.input.Reader rest();
  Signature: ()Lscala/util/parsing/input/Reader;
  Code:
   Stack=3, Locals=1, Args_size=1
	new	class scala/util/parsing/combinator/PackratParsers$PackratReader$$anon$3
	dup
	aload_0
	invokespecial	Method scala/util/parsing/combinator/PackratParsers$PackratReader$$anon$3."<init>":(Lscala/util/parsing/combinator/PackratParsers$PackratReader;)V
	areturn
  Labels:
  Signature: length = 0x2
   00 54 

public scala.util.parsing.input.Position pos();
  Signature: ()Lscala/util/parsing/input/Position;
  Code:
   Stack=1, Locals=1, Args_size=1
	aload_0
	getfield	Field scala$util$parsing$combinator$PackratParsers$PackratReader$$underlying:Lscala/util/parsing/input/Reader;
	invokevirtual	Method scala/util/parsing/input/Reader.pos:()Lscala/util/parsing/input/Position;
	areturn
  Labels:

public boolean atEnd();
  Signature: ()Z
  Code:
   Stack=1, Locals=1, Args_size=1
	aload_0
	getfield	Field scala$util$parsing$combinator$PackratParsers$PackratReader$$underlying:Lscala/util/parsing/input/Reader;
	invokevirtual	Method scala/util/parsing/input/Reader.atEnd:()Z
	ireturn
  Labels:

public scala.util.parsing.combinator.PackratParsers scala$util$parsing$combinator$PackratParsers$PackratReader$$$outer();
  Signature: ()Lscala/util/parsing/combinator/PackratParsers;
  Code:
   Stack=1, Locals=1, Args_size=1
	aload_0
	getfield	Field $outer:Lscala/util/parsing/combinator/PackratParsers;
	areturn
  Labels:

public scala.util.parsing.combinator.PackratParsers$PackratReader(scala.util.parsing.combinator.PackratParsers, scala.util.parsing.input.Reader);
  Signature: (Lscala/util/parsing/combinator/PackratParsers;Lscala/util/parsing/input/Reader;)V
  Code:
   Stack=2, Locals=3, Args_size=3
	aload_0
	aload_2
	putfield	Field scala$util$parsing$combinator$PackratParsers$PackratReader$$underlying:Lscala/util/parsing/input/Reader;
	aload_1
	ifnonnull	l1 // aload_0
	new	class java/lang/NullPointerException
	dup
	invokespecial	Method java/lang/NullPointerException."<init>":()V
	athrow
l1	aload_0
	aload_1
	putfield	Field $outer:Lscala/util/parsing/combinator/PackratParsers;
	aload_0
	invokespecial	Method scala/util/parsing/input/Reader."<init>":()V
	aload_0
	getstatic	Field scala/collection/mutable/HashMap$.MODULE$:Lscala/collection/mutable/HashMap$;
	invokevirtual	Method scala/collection/mutable/HashMap$.empty:()Lscala/collection/mutable/HashMap;
	putfield	Field scala$util$parsing$combinator$PackratParsers$$cache:Lscala/collection/mutable/HashMap;
	aload_0
	getstatic	Field scala/collection/mutable/HashMap$.MODULE$:Lscala/collection/mutable/HashMap$;
	invokevirtual	Method scala/collection/mutable/HashMap$.empty:()Lscala/collection/mutable/HashMap;
	putfield	Field scala$util$parsing$combinator$PackratParsers$$recursionHeads:Lscala/collection/mutable/HashMap;
	aload_0
	getstatic	Field scala/collection/immutable/Nil$.MODULE$:Lscala/collection/immutable/Nil$;
	putfield	Field scala$util$parsing$combinator$PackratParsers$$lrStack:Lscala/collection/immutable/List;
	return
  Labels:
   	l1 = 17 // aload_0
  LocalVariableTable: 
   Start  Length  Slot  Name   Signature
   0      54      0    this       Lscala/util/parsing/combinator/PackratParsers$PackratReader;
   0      54      1    $outer       Lscala/util/parsing/combinator/PackratParsers;
   0      54      2    underlying       Lscala/util/parsing/input/Reader;

  Signature: length = 0x2
   00 74 

}

