Compiled from "PackratParsers.scala"
public final class scala.util.parsing.combinator.PackratParsers$Head$ extends java.lang.Object implements scala.Function3,scala.ScalaObject
  SourceFile: "PackratParsers.scala"
  Scala: length = 0x
   
  InnerClass: 
   public abstract Parser=class scala/util/parsing/combinator/Parsers$Parser of class scala/util/parsing/combinator/Parsers
   public Head=class scala/util/parsing/combinator/PackratParsers$Head of class scala/util/parsing/combinator/PackratParsers
  minor version: 0
  major version: 49
  Constant pool:
Asciz	SourceFile;
Asciz	PackratParsers.scala;
Asciz	Scala;
Asciz	$outer;
Asciz	Lscala/util/parsing/combinator/PackratParsers;;
Asciz	<init>;
Asciz	(Lscala/util/parsing/combinator/PackratParsers;)V;
Asciz	Code;
Asciz	LineNumberTable;
Asciz	java/lang/NullPointerException;
class	java/lang/NullPointerException
Asciz	()V;
NameAndType	"<init>":()V
Method	java/lang/NullPointerException."<init>":()V
Asciz	scala/util/parsing/combinator/PackratParsers$Head$;
class	scala/util/parsing/combinator/PackratParsers$Head$
NameAndType	$outer:Lscala/util/parsing/combinator/PackratParsers;
Field	scala/util/parsing/combinator/PackratParsers$Head$.$outer:Lscala/util/parsing/combinator/PackratParsers;
Asciz	java/lang/Object;
class	java/lang/Object
Method	java/lang/Object."<init>":()V
Asciz	scala/Function3$class;
class	scala/Function3$class
Asciz	$init$;
Asciz	(Lscala/Function3;)V;
NameAndType	$init$:(Lscala/Function3;)V
Method	scala/Function3$class.$init$:(Lscala/Function3;)V
Asciz	this;
Asciz	Lscala/util/parsing/combinator/PackratParsers$Head$;;
Asciz	LocalVariableTable;
Asciz	apply;
Asciz	(Ljava/lang/Object;Ljava/lang/Object;Ljava/lang/Object;)Ljava/lang/Object;;
Asciz	scala/util/parsing/combinator/Parsers$Parser;
class	scala/util/parsing/combinator/Parsers$Parser
Asciz	scala/collection/immutable/List;
class	scala/collection/immutable/List
Asciz	(Lscala/util/parsing/combinator/Parsers$Parser;Lscala/collection/immutable/List;Lscala/collection/immutable/List;)Lscala/util/parsing/combinator/PackratParsers$Head;;
NameAndType	apply:(Lscala/util/parsing/combinator/Parsers$Parser;Lscala/collection/immutable/List;Lscala/collection/immutable/List;)Lscala/util/parsing/combinator/PackratParsers$Head;
Method	scala/util/parsing/combinator/PackratParsers$Head$.apply:(Lscala/util/parsing/combinator/Parsers$Parser;Lscala/collection/immutable/List;Lscala/collection/immutable/List;)Lscala/util/parsing/combinator/PackratParsers$Head;
Asciz	v1;
Asciz	Ljava/lang/Object;;
Asciz	v2;
Asciz	v3;
Asciz	scala/util/parsing/combinator/PackratParsers$Head;
class	scala/util/parsing/combinator/PackratParsers$Head
Asciz	(Lscala/util/parsing/combinator/PackratParsers;Lscala/util/parsing/combinator/Parsers$Parser;Lscala/collection/immutable/List;Lscala/collection/immutable/List;)V;
NameAndType	"<init>":(Lscala/util/parsing/combinator/PackratParsers;Lscala/util/parsing/combinator/Parsers$Parser;Lscala/collection/immutable/List;Lscala/collection/immutable/List;)V
Method	scala/util/parsing/combinator/PackratParsers$Head."<init>":(Lscala/util/parsing/combinator/PackratParsers;Lscala/util/parsing/combinator/Parsers$Parser;Lscala/collection/immutable/List;Lscala/collection/immutable/List;)V
Asciz	headParser;
Asciz	Lscala/util/parsing/combinator/Parsers$Parser;;
Asciz	involvedSet;
Asciz	Lscala/collection/immutable/List;;
Asciz	evalSet;
Asciz	unapply;
Asciz	(Lscala/util/parsing/combinator/PackratParsers$Head;)Lscala/Some;;
Asciz	scala/Some;
class	scala/Some
Asciz	scala/Tuple3;
class	scala/Tuple3
Asciz	()Lscala/util/parsing/combinator/Parsers$Parser;;
NameAndType	headParser:()Lscala/util/parsing/combinator/Parsers$Parser;
Method	scala/util/parsing/combinator/PackratParsers$Head.headParser:()Lscala/util/parsing/combinator/Parsers$Parser;
Asciz	()Lscala/collection/immutable/List;;
NameAndType	involvedSet:()Lscala/collection/immutable/List;
Method	scala/util/parsing/combinator/PackratParsers$Head.involvedSet:()Lscala/collection/immutable/List;
NameAndType	evalSet:()Lscala/collection/immutable/List;
Method	scala/util/parsing/combinator/PackratParsers$Head.evalSet:()Lscala/collection/immutable/List;
Asciz	(Ljava/lang/Object;Ljava/lang/Object;Ljava/lang/Object;)V;
NameAndType	"<init>":(Ljava/lang/Object;Ljava/lang/Object;Ljava/lang/Object;)V
Method	scala/Tuple3."<init>":(Ljava/lang/Object;Ljava/lang/Object;Ljava/lang/Object;)V
Asciz	(Ljava/lang/Object;)V;
NameAndType	"<init>":(Ljava/lang/Object;)V
Method	scala/Some."<init>":(Ljava/lang/Object;)V
Asciz	x$0;
Asciz	Lscala/util/parsing/combinator/PackratParsers$Head;;
Asciz	tupled;
Asciz	()Lscala/Function1;;
Asciz	(Lscala/Function3;)Lscala/Function1;;
NameAndType	tupled:(Lscala/Function3;)Lscala/Function1;
Method	scala/Function3$class.tupled:(Lscala/Function3;)Lscala/Function1;
Asciz	curry;
NameAndType	curry:(Lscala/Function3;)Lscala/Function1;
Method	scala/Function3$class.curry:(Lscala/Function3;)Lscala/Function1;
Asciz	Deprecated;
Asciz	curried;
NameAndType	curried:(Lscala/Function3;)Lscala/Function1;
Method	scala/Function3$class.curried:(Lscala/Function3;)Lscala/Function1;
Asciz	toString;
Asciz	()Ljava/lang/String;;
Asciz	(Lscala/Function3;)Ljava/lang/String;;
NameAndType	toString:(Lscala/Function3;)Ljava/lang/String;
Method	scala/Function3$class.toString:(Lscala/Function3;)Ljava/lang/String;
Asciz	InnerClasses;
Asciz	scala/util/parsing/combinator/Parsers;
class	scala/util/parsing/combinator/Parsers
Asciz	Parser;
Asciz	scala/util/parsing/combinator/PackratParsers;
class	scala/util/parsing/combinator/PackratParsers
Asciz	Head;
Asciz	scala/Function3;
class	scala/Function3
Asciz	scala/ScalaObject;
class	scala/ScalaObject

{
public final scala.util.parsing.combinator.PackratParsers $outer;
  Signature: Lscala/util/parsing/combinator/PackratParsers;

public scala.util.parsing.combinator.PackratParsers$Head$(scala.util.parsing.combinator.PackratParsers);
  Signature: (Lscala/util/parsing/combinator/PackratParsers;)V
  Code:
   Stack=2, Locals=2, Args_size=2
	aload_1
	ifnonnull	l1 // aload_0
	new	class java/lang/NullPointerException
	dup
	invokespecial	Method java/lang/NullPointerException."<init>":()V
	athrow
l1	aload_0
	aload_1
	putfield	Field $outer:Lscala/util/parsing/combinator/PackratParsers;
	aload_0
	invokespecial	Method java/lang/Object."<init>":()V
	aload_0
	invokestatic	Method scala/Function3$class.$init$:(Lscala/Function3;)V
	return
  Labels:
   	l1 = 12 // aload_0
  LocalVariableTable: 
   Start  Length  Slot  Name   Signature
   0      26      0    this       Lscala/util/parsing/combinator/PackratParsers$Head$;
   0      26      1    $outer       Lscala/util/parsing/combinator/PackratParsers;


public java.lang.Object apply(java.lang.Object, java.lang.Object, java.lang.Object);
  Signature: (Ljava/lang/Object;Ljava/lang/Object;Ljava/lang/Object;)Ljava/lang/Object;
  Code:
   Stack=4, Locals=5, Args_size=4
	aload_0
	getfield	Field $outer:Lscala/util/parsing/combinator/PackratParsers;
	astore	4
	aload_0
	aload_1
	checkcast	class scala/util/parsing/combinator/Parsers$Parser
	aload_2
	checkcast	class scala/collection/immutable/List
	aload_3
	checkcast	class scala/collection/immutable/List
	invokevirtual	Method apply:(Lscala/util/parsing/combinator/Parsers$Parser;Lscala/collection/immutable/List;Lscala/collection/immutable/List;)Lscala/util/parsing/combinator/PackratParsers$Head;
	areturn
  Labels:
  LocalVariableTable: 
   Start  Length  Slot  Name   Signature
   0      23      0    this       Lscala/util/parsing/combinator/PackratParsers$Head$;
   6      17      1    v1       Ljava/lang/Object;
   6      17      2    v2       Ljava/lang/Object;
   6      17      3    v3       Ljava/lang/Object;


public scala.util.parsing.combinator.PackratParsers$Head apply(scala.util.parsing.combinator.Parsers$Parser, scala.collection.immutable.List, scala.collection.immutable.List);
  Signature: (Lscala/util/parsing/combinator/Parsers$Parser;Lscala/collection/immutable/List;Lscala/collection/immutable/List;)Lscala/util/parsing/combinator/PackratParsers$Head;
  Code:
   Stack=6, Locals=5, Args_size=4
	aload_0
	getfield	Field $outer:Lscala/util/parsing/combinator/PackratParsers;
	astore	4
	new	class scala/util/parsing/combinator/PackratParsers$Head
	dup
	aload_0
	getfield	Field $outer:Lscala/util/parsing/combinator/PackratParsers;
	aload_1
	aload_2
	aload_3
	invokespecial	Method scala/util/parsing/combinator/PackratParsers$Head."<init>":(Lscala/util/parsing/combinator/PackratParsers;Lscala/util/parsing/combinator/Parsers$Parser;Lscala/collection/immutable/List;Lscala/collection/immutable/List;)V
	areturn
  Labels:
  LocalVariableTable: 
   Start  Length  Slot  Name   Signature
   0      21      0    this       Lscala/util/parsing/combinator/PackratParsers$Head$;
   6      15      1    headParser       Lscala/util/parsing/combinator/Parsers$Parser;
   6      15      2    involvedSet       Lscala/collection/immutable/List;
   6      15      3    evalSet       Lscala/collection/immutable/List;


public scala.Some unapply(scala.util.parsing.combinator.PackratParsers$Head);
  Signature: (Lscala/util/parsing/combinator/PackratParsers$Head;)Lscala/Some;
  Code:
   Stack=7, Locals=2, Args_size=2
	new	class scala/Some
	dup
	new	class scala/Tuple3
	dup
	aload_1
	invokevirtual	Method scala/util/parsing/combinator/PackratParsers$Head.headParser:()Lscala/util/parsing/combinator/Parsers$Parser;
	aload_1
	invokevirtual	Method scala/util/parsing/combinator/PackratParsers$Head.involvedSet:()Lscala/collection/immutable/List;
	aload_1
	invokevirtual	Method scala/util/parsing/combinator/PackratParsers$Head.evalSet:()Lscala/collection/immutable/List;
	invokespecial	Method scala/Tuple3."<init>":(Ljava/lang/Object;Ljava/lang/Object;Ljava/lang/Object;)V
	invokespecial	Method scala/Some."<init>":(Ljava/lang/Object;)V
	areturn
  Labels:
  LocalVariableTable: 
   Start  Length  Slot  Name   Signature
   0      27      0    this       Lscala/util/parsing/combinator/PackratParsers$Head$;
   0      27      1    x$0       Lscala/util/parsing/combinator/PackratParsers$Head;


public scala.Function1 tupled();
  Signature: ()Lscala/Function1;
  Code:
   Stack=1, Locals=1, Args_size=1
	aload_0
	invokestatic	Method scala/Function3$class.tupled:(Lscala/Function3;)Lscala/Function1;
	areturn
  Labels:

public scala.Function1 curry();
  Signature: ()Lscala/Function1;
  Code:
   Stack=1, Locals=1, Args_size=1
	aload_0
	invokestatic	Method scala/Function3$class.curry:(Lscala/Function3;)Lscala/Function1;
	areturn
  Labels:
  Deprecated: true

public scala.Function1 curried();
  Signature: ()Lscala/Function1;
  Code:
   Stack=1, Locals=1, Args_size=1
	aload_0
	invokestatic	Method scala/Function3$class.curried:(Lscala/Function3;)Lscala/Function1;
	areturn
  Labels:

public java.lang.String toString();
  Signature: ()Ljava/lang/String;
  Code:
   Stack=1, Locals=1, Args_size=1
	aload_0
	invokestatic	Method scala/Function3$class.toString:(Lscala/Function3;)Ljava/lang/String;
	areturn
  Labels:

}

