Compiled from "PackratParsers.scala"
public final class scala.util.parsing.combinator.PackratParsers$$anonfun$scala$util$parsing$combinator$PackratParsers$$setupLR$2$$anonfun$apply$1 extends java.lang.Object implements scala.Function1,scala.ScalaObject,java.io.Serializable
  SourceFile: "PackratParsers.scala"
  Scala: length = 0x
   
  InnerClass: 
   public abstract Parser=class scala/util/parsing/combinator/Parsers$Parser of class scala/util/parsing/combinator/Parsers
   public LR=class scala/util/parsing/combinator/PackratParsers$LR of class scala/util/parsing/combinator/PackratParsers
   public Head=class scala/util/parsing/combinator/PackratParsers$Head of class scala/util/parsing/combinator/PackratParsers
   public final $anonfun$scala$util$parsing$combinator$PackratParsers$$setupLR$2=class scala/util/parsing/combinator/PackratParsers$$anonfun$scala$util$parsing$combinator$PackratParsers$$setupLR$2 of class scala/util/parsing/combinator/PackratParsers
   public final $anonfun$apply$1=class scala/util/parsing/combinator/PackratParsers$$anonfun$scala$util$parsing$combinator$PackratParsers$$setupLR$2$$anonfun$apply$1 of class scala/util/parsing/combinator/PackratParsers$$anonfun$scala$util$parsing$combinator$PackratParsers$$setupLR$2
  minor version: 0
  major version: 49
  Constant pool:
Asciz	SourceFile;
Asciz	PackratParsers.scala;
Asciz	<clinit>;
Asciz	()V;
Asciz	Code;
Asciz	serialVersionUID;
Asciz	J;
Asciz	scala/util/parsing/combinator/PackratParsers$$anonfun$scala$util$parsing$combinator$PackratParsers$$setupLR$2$$anonfun$apply$1;
class	scala/util/parsing/combinator/PackratParsers$$anonfun$scala$util$parsing$combinator$PackratParsers$$setupLR$2$$anonfun$apply$1
NameAndType	serialVersionUID:J
Field	scala/util/parsing/combinator/PackratParsers$$anonfun$scala$util$parsing$combinator$PackratParsers$$setupLR$2$$anonfun$apply$1.serialVersionUID:J
Asciz	x$6;
Asciz	Lscala/util/parsing/combinator/PackratParsers$LR;;
Asciz	<init>;
Asciz	(Lscala/util/parsing/combinator/PackratParsers$$anonfun$scala$util$parsing$combinator$PackratParsers$$setupLR$2;Lscala/util/parsing/combinator/PackratParsers$LR;)V;
Asciz	LineNumberTable;
NameAndType	x$6:Lscala/util/parsing/combinator/PackratParsers$LR;
Field	scala/util/parsing/combinator/PackratParsers$$anonfun$scala$util$parsing$combinator$PackratParsers$$setupLR$2$$anonfun$apply$1.x$6:Lscala/util/parsing/combinator/PackratParsers$LR;
Asciz	java/lang/Object;
class	java/lang/Object
NameAndType	"<init>":()V
Method	java/lang/Object."<init>":()V
Asciz	scala/Function1$class;
class	scala/Function1$class
Asciz	$init$;
Asciz	(Lscala/Function1;)V;
NameAndType	$init$:(Lscala/Function1;)V
Method	scala/Function1$class.$init$:(Lscala/Function1;)V
Asciz	this;
Asciz	Lscala/util/parsing/combinator/PackratParsers$$anonfun$scala$util$parsing$combinator$PackratParsers$$setupLR$2$$anonfun$apply$1;;
Asciz	$outer;
Asciz	Lscala/util/parsing/combinator/PackratParsers$$anonfun$scala$util$parsing$combinator$PackratParsers$$setupLR$2;;
Asciz	LocalVariableTable;
Asciz	apply;
Asciz	(Ljava/lang/Object;)Ljava/lang/Object;;
Asciz	scala/util/parsing/combinator/PackratParsers$Head;
class	scala/util/parsing/combinator/PackratParsers$Head
Asciz	(Lscala/util/parsing/combinator/PackratParsers$Head;)V;
NameAndType	apply:(Lscala/util/parsing/combinator/PackratParsers$Head;)V
Method	scala/util/parsing/combinator/PackratParsers$$anonfun$scala$util$parsing$combinator$PackratParsers$$setupLR$2$$anonfun$apply$1.apply:(Lscala/util/parsing/combinator/PackratParsers$Head;)V
Asciz	scala/runtime/BoxedUnit;
class	scala/runtime/BoxedUnit
Asciz	UNIT;
Asciz	Lscala/runtime/BoxedUnit;;
NameAndType	UNIT:Lscala/runtime/BoxedUnit;
Field	scala/runtime/BoxedUnit.UNIT:Lscala/runtime/BoxedUnit;
Asciz	v1;
Asciz	Ljava/lang/Object;;
Asciz	scala/util/parsing/combinator/PackratParsers$LR;
class	scala/util/parsing/combinator/PackratParsers$LR
Asciz	rule;
Asciz	()Lscala/util/parsing/combinator/Parsers$Parser;;
NameAndType	rule:()Lscala/util/parsing/combinator/Parsers$Parser;
Method	scala/util/parsing/combinator/PackratParsers$LR.rule:()Lscala/util/parsing/combinator/Parsers$Parser;
Asciz	involvedSet;
Asciz	()Lscala/collection/immutable/List;;
NameAndType	involvedSet:()Lscala/collection/immutable/List;
Method	scala/util/parsing/combinator/PackratParsers$Head.involvedSet:()Lscala/collection/immutable/List;
Asciz	scala/collection/immutable/List;
class	scala/collection/immutable/List
Asciz	$colon$colon;
Asciz	(Ljava/lang/Object;)Lscala/collection/immutable/List;;
NameAndType	$colon$colon:(Ljava/lang/Object;)Lscala/collection/immutable/List;
Method	scala/collection/immutable/List.$colon$colon:(Ljava/lang/Object;)Lscala/collection/immutable/List;
Asciz	involvedSet_$eq;
Asciz	(Lscala/collection/immutable/List;)V;
NameAndType	involvedSet_$eq:(Lscala/collection/immutable/List;)V
Method	scala/util/parsing/combinator/PackratParsers$Head.involvedSet_$eq:(Lscala/collection/immutable/List;)V
Asciz	h;
Asciz	Lscala/util/parsing/combinator/PackratParsers$Head;;
Asciz	andThen;
Asciz	(Lscala/Function1;)Lscala/Function1;;
Asciz	(Lscala/Function1;Lscala/Function1;)Lscala/Function1;;
NameAndType	andThen:(Lscala/Function1;Lscala/Function1;)Lscala/Function1;
Method	scala/Function1$class.andThen:(Lscala/Function1;Lscala/Function1;)Lscala/Function1;
Asciz	g;
Asciz	Lscala/Function1;;
Asciz	compose;
NameAndType	compose:(Lscala/Function1;Lscala/Function1;)Lscala/Function1;
Method	scala/Function1$class.compose:(Lscala/Function1;Lscala/Function1;)Lscala/Function1;
Asciz	toString;
Asciz	()Ljava/lang/String;;
Asciz	(Lscala/Function1;)Ljava/lang/String;;
NameAndType	toString:(Lscala/Function1;)Ljava/lang/String;
Method	scala/Function1$class.toString:(Lscala/Function1;)Ljava/lang/String;
Asciz	Scala;
Asciz	InnerClasses;
Asciz	scala/util/parsing/combinator/Parsers$Parser;
class	scala/util/parsing/combinator/Parsers$Parser
Asciz	scala/util/parsing/combinator/Parsers;
class	scala/util/parsing/combinator/Parsers
Asciz	Parser;
Asciz	scala/util/parsing/combinator/PackratParsers;
class	scala/util/parsing/combinator/PackratParsers
Asciz	LR;
Asciz	Head;
Asciz	scala/util/parsing/combinator/PackratParsers$$anonfun$scala$util$parsing$combinator$PackratParsers$$setupLR$2;
class	scala/util/parsing/combinator/PackratParsers$$anonfun$scala$util$parsing$combinator$PackratParsers$$setupLR$2
Asciz	$anonfun$scala$util$parsing$combinator$PackratParsers$$setupLR$2;
Asciz	$anonfun$apply$1;
Asciz	scala/Function1;
class	scala/Function1
Asciz	scala/ScalaObject;
class	scala/ScalaObject
Asciz	java/io/Serializable;
class	java/io/Serializable

{
public static final long serialVersionUID;
  Signature: J

private final scala.util.parsing.combinator.PackratParsers$LR x$6;
  Signature: Lscala/util/parsing/combinator/PackratParsers$LR;

public static {};
  Signature: ()V
  Code:
   Stack=2, Locals=0, Args_size=0
	lconst_0
	putstatic	Field serialVersionUID:J
	return
  Labels:

public scala.util.parsing.combinator.PackratParsers$$anonfun$scala$util$parsing$combinator$PackratParsers$$setupLR$2$$anonfun$apply$1(scala.util.parsing.combinator.PackratParsers$$anonfun$scala$util$parsing$combinator$PackratParsers$$setupLR$2, scala.util.parsing.combinator.PackratParsers$LR);
  Signature: (Lscala/util/parsing/combinator/PackratParsers$$anonfun$scala$util$parsing$combinator$PackratParsers$$setupLR$2;Lscala/util/parsing/combinator/PackratParsers$LR;)V
  Code:
   Stack=2, Locals=3, Args_size=3
	aload_0
	aload_2
	putfield	Field x$6:Lscala/util/parsing/combinator/PackratParsers$LR;
	aload_0
	invokespecial	Method java/lang/Object."<init>":()V
	aload_0
	invokestatic	Method scala/Function1$class.$init$:(Lscala/Function1;)V
	return
  Labels:
  LocalVariableTable: 
   Start  Length  Slot  Name   Signature
   0      14      0    this       Lscala/util/parsing/combinator/PackratParsers$$anonfun$scala$util$parsing$combinator$PackratParsers$$setupLR$2$$anonfun$apply$1;
   0      14      1    $outer       Lscala/util/parsing/combinator/PackratParsers$$anonfun$scala$util$parsing$combinator$PackratParsers$$setupLR$2;


public final java.lang.Object apply(java.lang.Object);
  Signature: (Ljava/lang/Object;)Ljava/lang/Object;
  Code:
   Stack=2, Locals=2, Args_size=2
	aload_0
	aload_1
	checkcast	class scala/util/parsing/combinator/PackratParsers$Head
	invokevirtual	Method apply:(Lscala/util/parsing/combinator/PackratParsers$Head;)V
	getstatic	Field scala/runtime/BoxedUnit.UNIT:Lscala/runtime/BoxedUnit;
	areturn
  Labels:
  LocalVariableTable: 
   Start  Length  Slot  Name   Signature
   0      12      0    this       Lscala/util/parsing/combinator/PackratParsers$$anonfun$scala$util$parsing$combinator$PackratParsers$$setupLR$2$$anonfun$apply$1;
   0      12      1    v1       Ljava/lang/Object;


public final void apply(scala.util.parsing.combinator.PackratParsers$Head);
  Signature: (Lscala/util/parsing/combinator/PackratParsers$Head;)V
  Code:
   Stack=3, Locals=3, Args_size=2
	aload_1
	aload_0
	getfield	Field x$6:Lscala/util/parsing/combinator/PackratParsers$LR;
	invokevirtual	Method scala/util/parsing/combinator/PackratParsers$LR.rule:()Lscala/util/parsing/combinator/Parsers$Parser;
	astore_2
	aload_1
	invokevirtual	Method scala/util/parsing/combinator/PackratParsers$Head.involvedSet:()Lscala/collection/immutable/List;
	aload_2
	invokevirtual	Method scala/collection/immutable/List.$colon$colon:(Ljava/lang/Object;)Lscala/collection/immutable/List;
	invokevirtual	Method scala/util/parsing/combinator/PackratParsers$Head.involvedSet_$eq:(Lscala/collection/immutable/List;)V
	return
  Labels:
  LocalVariableTable: 
   Start  Length  Slot  Name   Signature
   0      21      0    this       Lscala/util/parsing/combinator/PackratParsers$$anonfun$scala$util$parsing$combinator$PackratParsers$$setupLR$2$$anonfun$apply$1;
   0      21      1    h       Lscala/util/parsing/combinator/PackratParsers$Head;


public scala.Function1 andThen(scala.Function1);
  Signature: (Lscala/Function1;)Lscala/Function1;
  Code:
   Stack=2, Locals=2, Args_size=2
	aload_0
	aload_1
	invokestatic	Method scala/Function1$class.andThen:(Lscala/Function1;Lscala/Function1;)Lscala/Function1;
	areturn
  Labels:
  LocalVariableTable: 
   Start  Length  Slot  Name   Signature
   0      6      0    this       Lscala/util/parsing/combinator/PackratParsers$$anonfun$scala$util$parsing$combinator$PackratParsers$$setupLR$2$$anonfun$apply$1;
   0      6      1    g       Lscala/Function1;


public scala.Function1 compose(scala.Function1);
  Signature: (Lscala/Function1;)Lscala/Function1;
  Code:
   Stack=2, Locals=2, Args_size=2
	aload_0
	aload_1
	invokestatic	Method scala/Function1$class.compose:(Lscala/Function1;Lscala/Function1;)Lscala/Function1;
	areturn
  Labels:
  LocalVariableTable: 
   Start  Length  Slot  Name   Signature
   0      6      0    this       Lscala/util/parsing/combinator/PackratParsers$$anonfun$scala$util$parsing$combinator$PackratParsers$$setupLR$2$$anonfun$apply$1;
   0      6      1    g       Lscala/Function1;


public java.lang.String toString();
  Signature: ()Ljava/lang/String;
  Code:
   Stack=1, Locals=1, Args_size=1
	aload_0
	invokestatic	Method scala/Function1$class.toString:(Lscala/Function1;)Ljava/lang/String;
	areturn
  Labels:

}

