Compiled from "PackratParsers.scala"
public final class scala.util.parsing.combinator.PackratParsers$MemoEntry$ extends java.lang.Object implements scala.ScalaObject
  SourceFile: "PackratParsers.scala"
  Scala: length = 0x
   
  InnerClass: 
   public #49= #28 of #48; //MemoEntry=class scala/util/parsing/combinator/PackratParsers$MemoEntry of class scala/util/parsing/combinator/PackratParsers
  minor version: 0
  major version: 49
  Constant pool:
const #1 = Asciz	SourceFile;
const #2 = Asciz	PackratParsers.scala;
const #3 = Asciz	Scala;
const #4 = Asciz	$outer;
const #5 = Asciz	Lscala/util/parsing/combinator/PackratParsers;;
const #6 = Asciz	<init>;
const #7 = Asciz	(Lscala/util/parsing/combinator/PackratParsers;)V;
const #8 = Asciz	Code;
const #9 = Asciz	LineNumberTable;
const #10 = Asciz	java/lang/NullPointerException;
const #11 = class	#10;	//  java/lang/NullPointerException
const #12 = Asciz	()V;
const #13 = NameAndType	#6:#12;//  "<init>":()V
const #14 = Method	#11.#13;	//  java/lang/NullPointerException."<init>":()V
const #15 = Asciz	scala/util/parsing/combinator/PackratParsers$MemoEntry$;
const #16 = class	#15;	//  scala/util/parsing/combinator/PackratParsers$MemoEntry$
const #17 = NameAndType	#4:#5;//  $outer:Lscala/util/parsing/combinator/PackratParsers;
const #18 = Field	#16.#17;	//  scala/util/parsing/combinator/PackratParsers$MemoEntry$.$outer:Lscala/util/parsing/combinator/PackratParsers;
const #19 = Asciz	java/lang/Object;
const #20 = class	#19;	//  java/lang/Object
const #21 = Method	#20.#13;	//  java/lang/Object."<init>":()V
const #22 = Asciz	this;
const #23 = Asciz	Lscala/util/parsing/combinator/PackratParsers$MemoEntry$;;
const #24 = Asciz	LocalVariableTable;
const #25 = Asciz	apply;
const #26 = Asciz	(Lscala/Either;)Lscala/util/parsing/combinator/PackratParsers$MemoEntry;;
const #27 = Asciz	scala/util/parsing/combinator/PackratParsers$MemoEntry;
const #28 = class	#27;	//  scala/util/parsing/combinator/PackratParsers$MemoEntry
const #29 = Asciz	(Lscala/util/parsing/combinator/PackratParsers;Lscala/Either;)V;
const #30 = NameAndType	#6:#29;//  "<init>":(Lscala/util/parsing/combinator/PackratParsers;Lscala/Either;)V
const #31 = Method	#28.#30;	//  scala/util/parsing/combinator/PackratParsers$MemoEntry."<init>":(Lscala/util/parsing/combinator/PackratParsers;Lscala/Either;)V
const #32 = Asciz	r;
const #33 = Asciz	Lscala/Either;;
const #34 = Asciz	unapply;
const #35 = Asciz	(Lscala/util/parsing/combinator/PackratParsers$MemoEntry;)Lscala/Some;;
const #36 = Asciz	scala/Some;
const #37 = class	#36;	//  scala/Some
const #38 = Asciz	()Lscala/Either;;
const #39 = NameAndType	#32:#38;//  r:()Lscala/Either;
const #40 = Method	#28.#39;	//  scala/util/parsing/combinator/PackratParsers$MemoEntry.r:()Lscala/Either;
const #41 = Asciz	(Ljava/lang/Object;)V;
const #42 = NameAndType	#6:#41;//  "<init>":(Ljava/lang/Object;)V
const #43 = Method	#37.#42;	//  scala/Some."<init>":(Ljava/lang/Object;)V
const #44 = Asciz	x$0;
const #45 = Asciz	Lscala/util/parsing/combinator/PackratParsers$MemoEntry;;
const #46 = Asciz	InnerClasses;
const #47 = Asciz	scala/util/parsing/combinator/PackratParsers;
const #48 = class	#47;	//  scala/util/parsing/combinator/PackratParsers
const #49 = Asciz	MemoEntry;
const #50 = Asciz	scala/ScalaObject;
const #51 = class	#50;	//  scala/ScalaObject

{
public scala.util.parsing.combinator.PackratParsers$MemoEntry$(scala.util.parsing.combinator.PackratParsers);
  Code:
   Stack=2, Locals=2, Args_size=2
   0:	aload_1
   1:	ifnonnull	12
   4:	new	#11; //class java/lang/NullPointerException
   7:	dup
   8:	invokespecial	#14; //Method java/lang/NullPointerException."<init>":()V
   11:	athrow
   12:	aload_0
   13:	aload_1
   14:	putfield	#18; //Field $outer:Lscala/util/parsing/combinator/PackratParsers;
   17:	aload_0
   18:	invokespecial	#21; //Method java/lang/Object."<init>":()V
   21:	return
  LineNumberTable: 
   line 134: 0

  LocalVariableTable: 
   Start  Length  Slot  Name   Signature
   0      22      0    this       Lscala/util/parsing/combinator/PackratParsers$MemoEntry$;
   0      22      1    $outer       Lscala/util/parsing/combinator/PackratParsers;


public scala.util.parsing.combinator.PackratParsers$MemoEntry apply(scala.Either);
  Code:
   Stack=4, Locals=2, Args_size=2
   0:	new	#28; //class scala/util/parsing/combinator/PackratParsers$MemoEntry
   3:	dup
   4:	aload_0
   5:	getfield	#18; //Field $outer:Lscala/util/parsing/combinator/PackratParsers;
   8:	aload_1
   9:	invokespecial	#31; //Method scala/util/parsing/combinator/PackratParsers$MemoEntry."<init>":(Lscala/util/parsing/combinator/PackratParsers;Lscala/Either;)V
   12:	areturn
  LineNumberTable: 
   line 134: 0

  LocalVariableTable: 
   Start  Length  Slot  Name   Signature
   0      13      0    this       Lscala/util/parsing/combinator/PackratParsers$MemoEntry$;
   0      13      1    r       Lscala/Either;


public scala.Some unapply(scala.util.parsing.combinator.PackratParsers$MemoEntry);
  Code:
   Stack=3, Locals=2, Args_size=2
   0:	new	#37; //class scala/Some
   3:	dup
   4:	aload_1
   5:	invokevirtual	#40; //Method scala/util/parsing/combinator/PackratParsers$MemoEntry.r:()Lscala/Either;
   8:	invokespecial	#43; //Method scala/Some."<init>":(Ljava/lang/Object;)V
   11:	areturn
  LineNumberTable: 
   line 134: 0

  LocalVariableTable: 
   Start  Length  Slot  Name   Signature
   0      12      0    this       Lscala/util/parsing/combinator/PackratParsers$MemoEntry$;
   0      12      1    x$0       Lscala/util/parsing/combinator/PackratParsers$MemoEntry;


}

