Compiled from "PackratParsers.scala"
public final class scala.util.parsing.combinator.PackratParsers$$anonfun$scala$util$parsing$combinator$PackratParsers$$setupLR$1 extends java.lang.Object implements scala.Function1,scala.ScalaObject,java.io.Serializable
  SourceFile: "PackratParsers.scala"
  Scala: length = 0x
   
  InnerClass: 
   public abstract Parser=class scala/util/parsing/combinator/Parsers$Parser of class scala/util/parsing/combinator/Parsers
   public LR=class scala/util/parsing/combinator/PackratParsers$LR of class scala/util/parsing/combinator/PackratParsers
   public final $anonfun$scala$util$parsing$combinator$PackratParsers$$setupLR$1=class scala/util/parsing/combinator/PackratParsers$$anonfun$scala$util$parsing$combinator$PackratParsers$$setupLR$1 of class scala/util/parsing/combinator/PackratParsers
  minor version: 0
  major version: 49
  Constant pool:
Asciz	SourceFile;
Asciz	PackratParsers.scala;
Asciz	<clinit>;
Asciz	()V;
Asciz	Code;
Asciz	serialVersionUID;
Asciz	J;
Asciz	scala/util/parsing/combinator/PackratParsers$$anonfun$scala$util$parsing$combinator$PackratParsers$$setupLR$1;
class	scala/util/parsing/combinator/PackratParsers$$anonfun$scala$util$parsing$combinator$PackratParsers$$setupLR$1
NameAndType	serialVersionUID:J
Field	scala/util/parsing/combinator/PackratParsers$$anonfun$scala$util$parsing$combinator$PackratParsers$$setupLR$1.serialVersionUID:J
Asciz	p$4;
Asciz	Lscala/util/parsing/combinator/Parsers$Parser;;
Asciz	<init>;
Asciz	(Lscala/util/parsing/combinator/PackratParsers;Lscala/util/parsing/combinator/Parsers$Parser;)V;
Asciz	LineNumberTable;
NameAndType	p$4:Lscala/util/parsing/combinator/Parsers$Parser;
Field	scala/util/parsing/combinator/PackratParsers$$anonfun$scala$util$parsing$combinator$PackratParsers$$setupLR$1.p$4:Lscala/util/parsing/combinator/Parsers$Parser;
Asciz	java/lang/Object;
class	java/lang/Object
NameAndType	"<init>":()V
Method	java/lang/Object."<init>":()V
Asciz	scala/Function1$class;
class	scala/Function1$class
Asciz	$init$;
Asciz	(Lscala/Function1;)V;
NameAndType	$init$:(Lscala/Function1;)V
Method	scala/Function1$class.$init$:(Lscala/Function1;)V
Asciz	this;
Asciz	Lscala/util/parsing/combinator/PackratParsers$$anonfun$scala$util$parsing$combinator$PackratParsers$$setupLR$1;;
Asciz	$outer;
Asciz	Lscala/util/parsing/combinator/PackratParsers;;
Asciz	LocalVariableTable;
Asciz	apply;
Asciz	(Ljava/lang/Object;)Ljava/lang/Object;;
Asciz	scala/util/parsing/combinator/PackratParsers$LR;
class	scala/util/parsing/combinator/PackratParsers$LR
Asciz	(Lscala/util/parsing/combinator/PackratParsers$LR;)Z;
NameAndType	apply:(Lscala/util/parsing/combinator/PackratParsers$LR;)Z
Method	scala/util/parsing/combinator/PackratParsers$$anonfun$scala$util$parsing$combinator$PackratParsers$$setupLR$1.apply:(Lscala/util/parsing/combinator/PackratParsers$LR;)Z
Asciz	scala/runtime/BoxesRunTime;
class	scala/runtime/BoxesRunTime
Asciz	boxToBoolean;
Asciz	(Z)Ljava/lang/Boolean;;
NameAndType	boxToBoolean:(Z)Ljava/lang/Boolean;
Method	scala/runtime/BoxesRunTime.boxToBoolean:(Z)Ljava/lang/Boolean;
Asciz	v1;
Asciz	Ljava/lang/Object;;
Asciz	rule;
Asciz	()Lscala/util/parsing/combinator/Parsers$Parser;;
NameAndType	rule:()Lscala/util/parsing/combinator/Parsers$Parser;
Method	scala/util/parsing/combinator/PackratParsers$LR.rule:()Lscala/util/parsing/combinator/Parsers$Parser;
Asciz	equals;
Asciz	(Ljava/lang/Object;)Z;
NameAndType	equals:(Ljava/lang/Object;)Z
Method	java/lang/Object.equals:(Ljava/lang/Object;)Z
Asciz	andThen;
Asciz	(Lscala/Function1;)Lscala/Function1;;
Asciz	(Lscala/Function1;Lscala/Function1;)Lscala/Function1;;
NameAndType	andThen:(Lscala/Function1;Lscala/Function1;)Lscala/Function1;
Method	scala/Function1$class.andThen:(Lscala/Function1;Lscala/Function1;)Lscala/Function1;
Asciz	g;
Asciz	Lscala/Function1;;
Asciz	compose;
NameAndType	compose:(Lscala/Function1;Lscala/Function1;)Lscala/Function1;
Method	scala/Function1$class.compose:(Lscala/Function1;Lscala/Function1;)Lscala/Function1;
Asciz	toString;
Asciz	()Ljava/lang/String;;
Asciz	(Lscala/Function1;)Ljava/lang/String;;
NameAndType	toString:(Lscala/Function1;)Ljava/lang/String;
Method	scala/Function1$class.toString:(Lscala/Function1;)Ljava/lang/String;
Asciz	Scala;
Asciz	InnerClasses;
Asciz	scala/util/parsing/combinator/Parsers$Parser;
class	scala/util/parsing/combinator/Parsers$Parser
Asciz	scala/util/parsing/combinator/Parsers;
class	scala/util/parsing/combinator/Parsers
Asciz	Parser;
Asciz	scala/util/parsing/combinator/PackratParsers;
class	scala/util/parsing/combinator/PackratParsers
Asciz	LR;
Asciz	$anonfun$scala$util$parsing$combinator$PackratParsers$$setupLR$1;
Asciz	scala/Function1;
class	scala/Function1
Asciz	scala/ScalaObject;
class	scala/ScalaObject
Asciz	java/io/Serializable;
class	java/io/Serializable

{
public static final long serialVersionUID;
  Signature: J

private final scala.util.parsing.combinator.Parsers$Parser p$4;
  Signature: Lscala/util/parsing/combinator/Parsers$Parser;

public static {};
  Signature: ()V
  Code:
   Stack=2, Locals=0, Args_size=0
	lconst_0
	putstatic	Field serialVersionUID:J
	return
  Labels:

public scala.util.parsing.combinator.PackratParsers$$anonfun$scala$util$parsing$combinator$PackratParsers$$setupLR$1(scala.util.parsing.combinator.PackratParsers, scala.util.parsing.combinator.Parsers$Parser);
  Signature: (Lscala/util/parsing/combinator/PackratParsers;Lscala/util/parsing/combinator/Parsers$Parser;)V
  Code:
   Stack=2, Locals=3, Args_size=3
	aload_0
	aload_2
	putfield	Field p$4:Lscala/util/parsing/combinator/Parsers$Parser;
	aload_0
	invokespecial	Method java/lang/Object."<init>":()V
	aload_0
	invokestatic	Method scala/Function1$class.$init$:(Lscala/Function1;)V
	return
  Labels:
  LocalVariableTable: 
   Start  Length  Slot  Name   Signature
   0      14      0    this       Lscala/util/parsing/combinator/PackratParsers$$anonfun$scala$util$parsing$combinator$PackratParsers$$setupLR$1;
   0      14      1    $outer       Lscala/util/parsing/combinator/PackratParsers;


public final java.lang.Object apply(java.lang.Object);
  Signature: (Ljava/lang/Object;)Ljava/lang/Object;
  Code:
   Stack=2, Locals=3, Args_size=2
	aload_0
	aload_1
	checkcast	class scala/util/parsing/combinator/PackratParsers$LR
	invokevirtual	Method apply:(Lscala/util/parsing/combinator/PackratParsers$LR;)Z
	istore_2
	iload_2
	invokestatic	Method scala/runtime/BoxesRunTime.boxToBoolean:(Z)Ljava/lang/Boolean;
	areturn
  Labels:
  LocalVariableTable: 
   Start  Length  Slot  Name   Signature
   0      14      0    this       Lscala/util/parsing/combinator/PackratParsers$$anonfun$scala$util$parsing$combinator$PackratParsers$$setupLR$1;
   0      14      1    v1       Ljava/lang/Object;


public final boolean apply(scala.util.parsing.combinator.PackratParsers$LR);
  Signature: (Lscala/util/parsing/combinator/PackratParsers$LR;)Z
  Code:
   Stack=2, Locals=3, Args_size=2
	aload_1
	invokevirtual	Method scala/util/parsing/combinator/PackratParsers$LR.rule:()Lscala/util/parsing/combinator/Parsers$Parser;
	aload_0
	getfield	Field p$4:Lscala/util/parsing/combinator/Parsers$Parser;
	astore_2
	dup
	ifnonnull	l1 // aload_2
	pop
	aload_2
	ifnull	l2 // iconst_0
	goto	l3 // iconst_1
l1	aload_2
	invokevirtual	Method java/lang/Object.equals:(Ljava/lang/Object;)Z
	ifeq	l3 // iconst_1
l2	iconst_0
	goto	l4 // ireturn
l3	iconst_1
l4	ireturn
  Labels:
   	l1 = 21 // aload_2
   	l2 = 28 // iconst_0
   	l3 = 32 // iconst_1
   	l4 = 33 // ireturn

public scala.Function1 andThen(scala.Function1);
  Signature: (Lscala/Function1;)Lscala/Function1;
  Code:
   Stack=2, Locals=2, Args_size=2
	aload_0
	aload_1
	invokestatic	Method scala/Function1$class.andThen:(Lscala/Function1;Lscala/Function1;)Lscala/Function1;
	areturn
  Labels:
  LocalVariableTable: 
   Start  Length  Slot  Name   Signature
   0      6      0    this       Lscala/util/parsing/combinator/PackratParsers$$anonfun$scala$util$parsing$combinator$PackratParsers$$setupLR$1;
   0      6      1    g       Lscala/Function1;


public scala.Function1 compose(scala.Function1);
  Signature: (Lscala/Function1;)Lscala/Function1;
  Code:
   Stack=2, Locals=2, Args_size=2
	aload_0
	aload_1
	invokestatic	Method scala/Function1$class.compose:(Lscala/Function1;Lscala/Function1;)Lscala/Function1;
	areturn
  Labels:
  LocalVariableTable: 
   Start  Length  Slot  Name   Signature
   0      6      0    this       Lscala/util/parsing/combinator/PackratParsers$$anonfun$scala$util$parsing$combinator$PackratParsers$$setupLR$1;
   0      6      1    g       Lscala/Function1;


public java.lang.String toString();
  Signature: ()Ljava/lang/String;
  Code:
   Stack=1, Locals=1, Args_size=1
	aload_0
	invokestatic	Method scala/Function1$class.toString:(Lscala/Function1;)Ljava/lang/String;
	areturn
  Labels:

}

