Compiled from "PackratParsers.scala"
public final class scala.util.parsing.combinator.PackratParsers$$anonfun$scala$util$parsing$combinator$PackratParsers$$setupLR$2$$anonfun$apply$1 extends java.lang.Object implements scala.Function1,scala.ScalaObject,java.io.Serializable
  SourceFile: "PackratParsers.scala"
  Scala: length = 0x
   
  InnerClass: 
   public abstract #92= #89 of #91; //Parser=class scala/util/parsing/combinator/Parsers$Parser of class scala/util/parsing/combinator/Parsers
   public #95= #50 of #94; //LR=class scala/util/parsing/combinator/PackratParsers$LR of class scala/util/parsing/combinator/PackratParsers
   public #96= #37 of #94; //Head=class scala/util/parsing/combinator/PackratParsers$Head of class scala/util/parsing/combinator/PackratParsers
   public final #99= #98 of #94; //$anonfun$scala$util$parsing$combinator$PackratParsers$$setupLR$2=class scala/util/parsing/combinator/PackratParsers$$anonfun$scala$util$parsing$combinator$PackratParsers$$setupLR$2 of class scala/util/parsing/combinator/PackratParsers
   public final #100= #9 of #98; //$anonfun$apply$1=class scala/util/parsing/combinator/PackratParsers$$anonfun$scala$util$parsing$combinator$PackratParsers$$setupLR$2$$anonfun$apply$1 of class scala/util/parsing/combinator/PackratParsers$$anonfun$scala$util$parsing$combinator$PackratParsers$$setupLR$2
  minor version: 0
  major version: 49
  Constant pool:
const #1 = Asciz	SourceFile;
const #2 = Asciz	PackratParsers.scala;
const #3 = Asciz	<clinit>;
const #4 = Asciz	()V;
const #5 = Asciz	Code;
const #6 = Asciz	serialVersionUID;
const #7 = Asciz	J;
const #8 = Asciz	scala/util/parsing/combinator/PackratParsers$$anonfun$scala$util$parsing$combinator$PackratParsers$$setupLR$2$$anonfun$apply$1;
const #9 = class	#8;	//  scala/util/parsing/combinator/PackratParsers$$anonfun$scala$util$parsing$combinator$PackratParsers$$setupLR$2$$anonfun$apply$1
const #10 = NameAndType	#6:#7;//  serialVersionUID:J
const #11 = Field	#9.#10;	//  scala/util/parsing/combinator/PackratParsers$$anonfun$scala$util$parsing$combinator$PackratParsers$$setupLR$2$$anonfun$apply$1.serialVersionUID:J
const #12 = Asciz	x$6;
const #13 = Asciz	Lscala/util/parsing/combinator/PackratParsers$LR;;
const #14 = Asciz	<init>;
const #15 = Asciz	(Lscala/util/parsing/combinator/PackratParsers$$anonfun$scala$util$parsing$combinator$PackratParsers$$setupLR$2;Lscala/util/parsing/combinator/PackratParsers$LR;)V;
const #16 = Asciz	LineNumberTable;
const #17 = NameAndType	#12:#13;//  x$6:Lscala/util/parsing/combinator/PackratParsers$LR;
const #18 = Field	#9.#17;	//  scala/util/parsing/combinator/PackratParsers$$anonfun$scala$util$parsing$combinator$PackratParsers$$setupLR$2$$anonfun$apply$1.x$6:Lscala/util/parsing/combinator/PackratParsers$LR;
const #19 = Asciz	java/lang/Object;
const #20 = class	#19;	//  java/lang/Object
const #21 = NameAndType	#14:#4;//  "<init>":()V
const #22 = Method	#20.#21;	//  java/lang/Object."<init>":()V
const #23 = Asciz	scala/Function1$class;
const #24 = class	#23;	//  scala/Function1$class
const #25 = Asciz	$init$;
const #26 = Asciz	(Lscala/Function1;)V;
const #27 = NameAndType	#25:#26;//  $init$:(Lscala/Function1;)V
const #28 = Method	#24.#27;	//  scala/Function1$class.$init$:(Lscala/Function1;)V
const #29 = Asciz	this;
const #30 = Asciz	Lscala/util/parsing/combinator/PackratParsers$$anonfun$scala$util$parsing$combinator$PackratParsers$$setupLR$2$$anonfun$apply$1;;
const #31 = Asciz	$outer;
const #32 = Asciz	Lscala/util/parsing/combinator/PackratParsers$$anonfun$scala$util$parsing$combinator$PackratParsers$$setupLR$2;;
const #33 = Asciz	LocalVariableTable;
const #34 = Asciz	apply;
const #35 = Asciz	(Ljava/lang/Object;)Ljava/lang/Object;;
const #36 = Asciz	scala/util/parsing/combinator/PackratParsers$Head;
const #37 = class	#36;	//  scala/util/parsing/combinator/PackratParsers$Head
const #38 = Asciz	(Lscala/util/parsing/combinator/PackratParsers$Head;)V;
const #39 = NameAndType	#34:#38;//  apply:(Lscala/util/parsing/combinator/PackratParsers$Head;)V
const #40 = Method	#9.#39;	//  scala/util/parsing/combinator/PackratParsers$$anonfun$scala$util$parsing$combinator$PackratParsers$$setupLR$2$$anonfun$apply$1.apply:(Lscala/util/parsing/combinator/PackratParsers$Head;)V
const #41 = Asciz	scala/runtime/BoxedUnit;
const #42 = class	#41;	//  scala/runtime/BoxedUnit
const #43 = Asciz	UNIT;
const #44 = Asciz	Lscala/runtime/BoxedUnit;;
const #45 = NameAndType	#43:#44;//  UNIT:Lscala/runtime/BoxedUnit;
const #46 = Field	#42.#45;	//  scala/runtime/BoxedUnit.UNIT:Lscala/runtime/BoxedUnit;
const #47 = Asciz	v1;
const #48 = Asciz	Ljava/lang/Object;;
const #49 = Asciz	scala/util/parsing/combinator/PackratParsers$LR;
const #50 = class	#49;	//  scala/util/parsing/combinator/PackratParsers$LR
const #51 = Asciz	rule;
const #52 = Asciz	()Lscala/util/parsing/combinator/Parsers$Parser;;
const #53 = NameAndType	#51:#52;//  rule:()Lscala/util/parsing/combinator/Parsers$Parser;
const #54 = Method	#50.#53;	//  scala/util/parsing/combinator/PackratParsers$LR.rule:()Lscala/util/parsing/combinator/Parsers$Parser;
const #55 = Asciz	involvedSet;
const #56 = Asciz	()Lscala/collection/immutable/List;;
const #57 = NameAndType	#55:#56;//  involvedSet:()Lscala/collection/immutable/List;
const #58 = Method	#37.#57;	//  scala/util/parsing/combinator/PackratParsers$Head.involvedSet:()Lscala/collection/immutable/List;
const #59 = Asciz	scala/collection/immutable/List;
const #60 = class	#59;	//  scala/collection/immutable/List
const #61 = Asciz	$colon$colon;
const #62 = Asciz	(Ljava/lang/Object;)Lscala/collection/immutable/List;;
const #63 = NameAndType	#61:#62;//  $colon$colon:(Ljava/lang/Object;)Lscala/collection/immutable/List;
const #64 = Method	#60.#63;	//  scala/collection/immutable/List.$colon$colon:(Ljava/lang/Object;)Lscala/collection/immutable/List;
const #65 = Asciz	involvedSet_$eq;
const #66 = Asciz	(Lscala/collection/immutable/List;)V;
const #67 = NameAndType	#65:#66;//  involvedSet_$eq:(Lscala/collection/immutable/List;)V
const #68 = Method	#37.#67;	//  scala/util/parsing/combinator/PackratParsers$Head.involvedSet_$eq:(Lscala/collection/immutable/List;)V
const #69 = Asciz	h;
const #70 = Asciz	Lscala/util/parsing/combinator/PackratParsers$Head;;
const #71 = Asciz	andThen;
const #72 = Asciz	(Lscala/Function1;)Lscala/Function1;;
const #73 = Asciz	(Lscala/Function1;Lscala/Function1;)Lscala/Function1;;
const #74 = NameAndType	#71:#73;//  andThen:(Lscala/Function1;Lscala/Function1;)Lscala/Function1;
const #75 = Method	#24.#74;	//  scala/Function1$class.andThen:(Lscala/Function1;Lscala/Function1;)Lscala/Function1;
const #76 = Asciz	g;
const #77 = Asciz	Lscala/Function1;;
const #78 = Asciz	compose;
const #79 = NameAndType	#78:#73;//  compose:(Lscala/Function1;Lscala/Function1;)Lscala/Function1;
const #80 = Method	#24.#79;	//  scala/Function1$class.compose:(Lscala/Function1;Lscala/Function1;)Lscala/Function1;
const #81 = Asciz	toString;
const #82 = Asciz	()Ljava/lang/String;;
const #83 = Asciz	(Lscala/Function1;)Ljava/lang/String;;
const #84 = NameAndType	#81:#83;//  toString:(Lscala/Function1;)Ljava/lang/String;
const #85 = Method	#24.#84;	//  scala/Function1$class.toString:(Lscala/Function1;)Ljava/lang/String;
const #86 = Asciz	Scala;
const #87 = Asciz	InnerClasses;
const #88 = Asciz	scala/util/parsing/combinator/Parsers$Parser;
const #89 = class	#88;	//  scala/util/parsing/combinator/Parsers$Parser
const #90 = Asciz	scala/util/parsing/combinator/Parsers;
const #91 = class	#90;	//  scala/util/parsing/combinator/Parsers
const #92 = Asciz	Parser;
const #93 = Asciz	scala/util/parsing/combinator/PackratParsers;
const #94 = class	#93;	//  scala/util/parsing/combinator/PackratParsers
const #95 = Asciz	LR;
const #96 = Asciz	Head;
const #97 = Asciz	scala/util/parsing/combinator/PackratParsers$$anonfun$scala$util$parsing$combinator$PackratParsers$$setupLR$2;
const #98 = class	#97;	//  scala/util/parsing/combinator/PackratParsers$$anonfun$scala$util$parsing$combinator$PackratParsers$$setupLR$2
const #99 = Asciz	$anonfun$scala$util$parsing$combinator$PackratParsers$$setupLR$2;
const #100 = Asciz	$anonfun$apply$1;
const #101 = Asciz	scala/Function1;
const #102 = class	#101;	//  scala/Function1
const #103 = Asciz	scala/ScalaObject;
const #104 = class	#103;	//  scala/ScalaObject
const #105 = Asciz	java/io/Serializable;
const #106 = class	#105;	//  java/io/Serializable

{
public static final long serialVersionUID;

public static {};
  Code:
   Stack=2, Locals=0, Args_size=0
   0:	lconst_0
   1:	putstatic	#11; //Field serialVersionUID:J
   4:	return

public scala.util.parsing.combinator.PackratParsers$$anonfun$scala$util$parsing$combinator$PackratParsers$$setupLR$2$$anonfun$apply$1(scala.util.parsing.combinator.PackratParsers$$anonfun$scala$util$parsing$combinator$PackratParsers$$setupLR$2, scala.util.parsing.combinator.PackratParsers$LR);
  Code:
   Stack=2, Locals=3, Args_size=3
   0:	aload_0
   1:	aload_2
   2:	putfield	#18; //Field x$6:Lscala/util/parsing/combinator/PackratParsers$LR;
   5:	aload_0
   6:	invokespecial	#22; //Method java/lang/Object."<init>":()V
   9:	aload_0
   10:	invokestatic	#28; //Method scala/Function1$class.$init$:(Lscala/Function1;)V
   13:	return
  LineNumberTable: 
   line 209: 0

  LocalVariableTable: 
   Start  Length  Slot  Name   Signature
   0      14      0    this       Lscala/util/parsing/combinator/PackratParsers$$anonfun$scala$util$parsing$combinator$PackratParsers$$setupLR$2$$anonfun$apply$1;
   0      14      1    $outer       Lscala/util/parsing/combinator/PackratParsers$$anonfun$scala$util$parsing$combinator$PackratParsers$$setupLR$2;


public final java.lang.Object apply(java.lang.Object);
  Code:
   Stack=2, Locals=2, Args_size=2
   0:	aload_0
   1:	aload_1
   2:	checkcast	#37; //class scala/util/parsing/combinator/PackratParsers$Head
   5:	invokevirtual	#40; //Method apply:(Lscala/util/parsing/combinator/PackratParsers$Head;)V
   8:	getstatic	#46; //Field scala/runtime/BoxedUnit.UNIT:Lscala/runtime/BoxedUnit;
   11:	areturn
  LineNumberTable: 
   line 209: 0

  LocalVariableTable: 
   Start  Length  Slot  Name   Signature
   0      12      0    this       Lscala/util/parsing/combinator/PackratParsers$$anonfun$scala$util$parsing$combinator$PackratParsers$$setupLR$2$$anonfun$apply$1;
   0      12      1    v1       Ljava/lang/Object;


public final void apply(scala.util.parsing.combinator.PackratParsers$Head);
  Code:
   Stack=3, Locals=3, Args_size=2
   0:	aload_1
   1:	aload_0
   2:	getfield	#18; //Field x$6:Lscala/util/parsing/combinator/PackratParsers$LR;
   5:	invokevirtual	#54; //Method scala/util/parsing/combinator/PackratParsers$LR.rule:()Lscala/util/parsing/combinator/Parsers$Parser;
   8:	astore_2
   9:	aload_1
   10:	invokevirtual	#58; //Method scala/util/parsing/combinator/PackratParsers$Head.involvedSet:()Lscala/collection/immutable/List;
   13:	aload_2
   14:	invokevirtual	#64; //Method scala/collection/immutable/List.$colon$colon:(Ljava/lang/Object;)Lscala/collection/immutable/List;
   17:	invokevirtual	#68; //Method scala/util/parsing/combinator/PackratParsers$Head.involvedSet_$eq:(Lscala/collection/immutable/List;)V
   20:	return
  LineNumberTable: 
   line 209: 0

  LocalVariableTable: 
   Start  Length  Slot  Name   Signature
   0      21      0    this       Lscala/util/parsing/combinator/PackratParsers$$anonfun$scala$util$parsing$combinator$PackratParsers$$setupLR$2$$anonfun$apply$1;
   0      21      1    h       Lscala/util/parsing/combinator/PackratParsers$Head;


public scala.Function1 andThen(scala.Function1);
  Code:
   Stack=2, Locals=2, Args_size=2
   0:	aload_0
   1:	aload_1
   2:	invokestatic	#75; //Method scala/Function1$class.andThen:(Lscala/Function1;Lscala/Function1;)Lscala/Function1;
   5:	areturn
  LineNumberTable: 
   line 209: 0

  LocalVariableTable: 
   Start  Length  Slot  Name   Signature
   0      6      0    this       Lscala/util/parsing/combinator/PackratParsers$$anonfun$scala$util$parsing$combinator$PackratParsers$$setupLR$2$$anonfun$apply$1;
   0      6      1    g       Lscala/Function1;


public scala.Function1 compose(scala.Function1);
  Code:
   Stack=2, Locals=2, Args_size=2
   0:	aload_0
   1:	aload_1
   2:	invokestatic	#80; //Method scala/Function1$class.compose:(Lscala/Function1;Lscala/Function1;)Lscala/Function1;
   5:	areturn
  LineNumberTable: 
   line 209: 0

  LocalVariableTable: 
   Start  Length  Slot  Name   Signature
   0      6      0    this       Lscala/util/parsing/combinator/PackratParsers$$anonfun$scala$util$parsing$combinator$PackratParsers$$setupLR$2$$anonfun$apply$1;
   0      6      1    g       Lscala/Function1;


public java.lang.String toString();
  Code:
   Stack=1, Locals=1, Args_size=1
   0:	aload_0
   1:	invokestatic	#85; //Method scala/Function1$class.toString:(Lscala/Function1;)Ljava/lang/String;
   4:	areturn
  LineNumberTable: 
   line 209: 0


}

