Compiled from "PackratParsers.scala"
public abstract class scala.util.parsing.combinator.PackratParsers$class extends java.lang.Object
  SourceFile: "PackratParsers.scala"
  Scala: length = 0x
   
  InnerClass: 
   public #360= #192 of #359; //Error=class scala/util/parsing/combinator/Parsers$Error of class scala/util/parsing/combinator/Parsers
   public abstract #361= #25 of #359; //Parser=class scala/util/parsing/combinator/Parsers$Parser of class scala/util/parsing/combinator/Parsers
   public #362= #190 of #359; //Failure=class scala/util/parsing/combinator/Parsers$Failure of class scala/util/parsing/combinator/Parsers
   public #363= #85 of #359; //Success=class scala/util/parsing/combinator/Parsers$Success of class scala/util/parsing/combinator/Parsers
   public #364= #163 of #326; //LR=class scala/util/parsing/combinator/PackratParsers$LR of class scala/util/parsing/combinator/PackratParsers
   public abstract #365= #70 of #359; //ParseResult=class scala/util/parsing/combinator/Parsers$ParseResult of class scala/util/parsing/combinator/Parsers
   public #366= #72 of #326; //Head=class scala/util/parsing/combinator/PackratParsers$Head of class scala/util/parsing/combinator/PackratParsers
   public final #367= #155 of #326; //$anon$2=class scala/util/parsing/combinator/PackratParsers$$anon$2 of class scala/util/parsing/combinator/PackratParsers
   public final #368= #353 of #326; //$anon$1=class scala/util/parsing/combinator/PackratParsers$$anon$1 of class scala/util/parsing/combinator/PackratParsers
   public #369= #59 of #326; //MemoEntry=class scala/util/parsing/combinator/PackratParsers$MemoEntry of class scala/util/parsing/combinator/PackratParsers
   public #370= #34 of #326; //PackratReader=class scala/util/parsing/combinator/PackratParsers$PackratReader of class scala/util/parsing/combinator/PackratParsers
   public abstract #373= #372 of #326; //PackratParser=class scala/util/parsing/combinator/PackratParsers$PackratParser of class scala/util/parsing/combinator/PackratParsers
   public final #374= #321 of #326; //$anonfun$parser2packrat$1=class scala/util/parsing/combinator/PackratParsers$$anonfun$parser2packrat$1 of class scala/util/parsing/combinator/PackratParsers
   public final #375= #288 of #326; //$anonfun$scala$util$parsing$combinator$PackratParsers$$recall$1=class scala/util/parsing/combinator/PackratParsers$$anonfun$scala$util$parsing$combinator$PackratParsers$$recall$1 of class scala/util/parsing/combinator/PackratParsers
   public final #376= #250 of #326; //$anonfun$scala$util$parsing$combinator$PackratParsers$$setupLR$2=class scala/util/parsing/combinator/PackratParsers$$anonfun$scala$util$parsing$combinator$PackratParsers$$setupLR$2 of class scala/util/parsing/combinator/PackratParsers
   public final #377= #241 of #326; //$anonfun$scala$util$parsing$combinator$PackratParsers$$setupLR$1=class scala/util/parsing/combinator/PackratParsers$$anonfun$scala$util$parsing$combinator$PackratParsers$$setupLR$1 of class scala/util/parsing/combinator/PackratParsers
  minor version: 0
  major version: 49
  Constant pool:
const #1 = Asciz	SourceFile;
const #2 = Asciz	PackratParsers.scala;
const #3 = Asciz	$init$;
const #4 = Asciz	(Lscala/util/parsing/combinator/PackratParsers;)V;
const #5 = Asciz	Code;
const #6 = Asciz	LineNumberTable;
const #7 = Asciz	$this;
const #8 = Asciz	Lscala/util/parsing/combinator/PackratParsers;;
const #9 = Asciz	LocalVariableTable;
const #10 = Asciz	q$2;
const #11 = Asciz	(Lscala/util/parsing/combinator/PackratParsers;Lscala/Function0;Lscala/runtime/ObjectRef;Lscala/runtime/IntRef;)Lscala/util/parsing/combinator/Parsers$Parser;;
const #12 = Asciz	scala/runtime/IntRef;
const #13 = class	#12;	//  scala/runtime/IntRef
const #14 = Asciz	elem;
const #15 = Asciz	I;
const #16 = NameAndType	#14:#15;//  elem:I
const #17 = Field	#13.#16;	//  scala/runtime/IntRef.elem:I
const #18 = Asciz	scala/Function0;
const #19 = class	#18;	//  scala/Function0
const #20 = Asciz	apply;
const #21 = Asciz	()Ljava/lang/Object;;
const #22 = NameAndType	#20:#21;//  apply:()Ljava/lang/Object;
const #23 = InterfaceMethod	#19.#22;	//  scala/Function0.apply:()Ljava/lang/Object;
const #24 = Asciz	scala/util/parsing/combinator/Parsers$Parser;
const #25 = class	#24;	//  scala/util/parsing/combinator/Parsers$Parser
const #26 = Asciz	scala/runtime/ObjectRef;
const #27 = class	#26;	//  scala/runtime/ObjectRef
const #28 = Asciz	Ljava/lang/Object;;
const #29 = NameAndType	#14:#28;//  elem:Ljava/lang/Object;
const #30 = Field	#27.#29;	//  scala/runtime/ObjectRef.elem:Ljava/lang/Object;
const #31 = Asciz	grow;
const #32 = Asciz	(Lscala/util/parsing/combinator/PackratParsers;Lscala/util/parsing/combinator/Parsers$Parser;Lscala/util/parsing/combinator/PackratParsers$PackratReader;Lscala/util/parsing/combinator/PackratParsers$Head;)Lscala/util/parsing/combinator/Parsers$ParseResult;;
const #33 = Asciz	scala/util/parsing/combinator/PackratParsers$PackratReader;
const #34 = class	#33;	//  scala/util/parsing/combinator/PackratParsers$PackratReader
const #35 = Asciz	scala$util$parsing$combinator$PackratParsers$$recursionHeads;
const #36 = Asciz	()Lscala/collection/mutable/HashMap;;
const #37 = NameAndType	#35:#36;//  scala$util$parsing$combinator$PackratParsers$$recursionHeads:()Lscala/collection/mutable/HashMap;
const #38 = Method	#34.#37;	//  scala/util/parsing/combinator/PackratParsers$PackratReader.scala$util$parsing$combinator$PackratParsers$$recursionHeads:()Lscala/collection/mutable/HashMap;
const #39 = Asciz	pos;
const #40 = Asciz	()Lscala/util/parsing/input/Position;;
const #41 = NameAndType	#39:#40;//  pos:()Lscala/util/parsing/input/Position;
const #42 = Method	#34.#41;	//  scala/util/parsing/combinator/PackratParsers$PackratReader.pos:()Lscala/util/parsing/input/Position;
const #43 = Asciz	scala/collection/mutable/HashMap;
const #44 = class	#43;	//  scala/collection/mutable/HashMap
const #45 = Asciz	put;
const #46 = Asciz	(Ljava/lang/Object;Ljava/lang/Object;)Lscala/Option;;
const #47 = NameAndType	#45:#46;//  put:(Ljava/lang/Object;Ljava/lang/Object;)Lscala/Option;
const #48 = Method	#44.#47;	//  scala/collection/mutable/HashMap.put:(Ljava/lang/Object;Ljava/lang/Object;)Lscala/Option;
const #49 = Asciz	scala$util$parsing$combinator$PackratParsers$$getFromCache;
const #50 = Asciz	(Lscala/util/parsing/combinator/Parsers$Parser;)Lscala/Option;;
const #51 = NameAndType	#49:#50;//  scala$util$parsing$combinator$PackratParsers$$getFromCache:(Lscala/util/parsing/combinator/Parsers$Parser;)Lscala/Option;
const #52 = Method	#34.#51;	//  scala/util/parsing/combinator/PackratParsers$PackratReader.scala$util$parsing$combinator$PackratParsers$$getFromCache:(Lscala/util/parsing/combinator/Parsers$Parser;)Lscala/Option;
const #53 = Asciz	scala/Option;
const #54 = class	#53;	//  scala/Option
const #55 = Asciz	get;
const #56 = NameAndType	#55:#21;//  get:()Ljava/lang/Object;
const #57 = Method	#54.#56;	//  scala/Option.get:()Ljava/lang/Object;
const #58 = Asciz	scala/util/parsing/combinator/PackratParsers$MemoEntry;
const #59 = class	#58;	//  scala/util/parsing/combinator/PackratParsers$MemoEntry
const #60 = Asciz	r;
const #61 = Asciz	()Lscala/Either;;
const #62 = NameAndType	#60:#61;//  r:()Lscala/Either;
const #63 = Method	#59.#62;	//  scala/util/parsing/combinator/PackratParsers$MemoEntry.r:()Lscala/Either;
const #64 = Asciz	scala/Right;
const #65 = class	#64;	//  scala/Right
const #66 = Asciz	b;
const #67 = NameAndType	#66:#21;//  b:()Ljava/lang/Object;
const #68 = Method	#65.#67;	//  scala/Right.b:()Ljava/lang/Object;
const #69 = Asciz	scala/util/parsing/combinator/Parsers$ParseResult;
const #70 = class	#69;	//  scala/util/parsing/combinator/Parsers$ParseResult
const #71 = Asciz	scala/util/parsing/combinator/PackratParsers$Head;
const #72 = class	#71;	//  scala/util/parsing/combinator/PackratParsers$Head
const #73 = Asciz	involvedSet;
const #74 = Asciz	()Lscala/collection/immutable/List;;
const #75 = NameAndType	#73:#74;//  involvedSet:()Lscala/collection/immutable/List;
const #76 = Method	#72.#75;	//  scala/util/parsing/combinator/PackratParsers$Head.involvedSet:()Lscala/collection/immutable/List;
const #77 = Asciz	evalSet_$eq;
const #78 = Asciz	(Lscala/collection/immutable/List;)V;
const #79 = NameAndType	#77:#78;//  evalSet_$eq:(Lscala/collection/immutable/List;)V
const #80 = Method	#72.#79;	//  scala/util/parsing/combinator/PackratParsers$Head.evalSet_$eq:(Lscala/collection/immutable/List;)V
const #81 = Asciz	(Lscala/util/parsing/input/Reader;)Lscala/util/parsing/combinator/Parsers$ParseResult;;
const #82 = NameAndType	#20:#81;//  apply:(Lscala/util/parsing/input/Reader;)Lscala/util/parsing/combinator/Parsers$ParseResult;
const #83 = Method	#25.#82;	//  scala/util/parsing/combinator/Parsers$Parser.apply:(Lscala/util/parsing/input/Reader;)Lscala/util/parsing/combinator/Parsers$ParseResult;
const #84 = Asciz	scala/util/parsing/combinator/Parsers$Success;
const #85 = class	#84;	//  scala/util/parsing/combinator/Parsers$Success
const #86 = Asciz	scala/util/parsing/combinator/PackratParsers$class;
const #87 = class	#86;	//  scala/util/parsing/combinator/PackratParsers$class
const #88 = Asciz	scala$util$parsing$combinator$PackratParsers$$getPosFromResult;
const #89 = Asciz	(Lscala/util/parsing/combinator/PackratParsers;Lscala/util/parsing/combinator/Parsers$ParseResult;)Lscala/util/parsing/input/Position;;
const #90 = NameAndType	#88:#89;//  scala$util$parsing$combinator$PackratParsers$$getPosFromResult:(Lscala/util/parsing/combinator/PackratParsers;Lscala/util/parsing/combinator/Parsers$ParseResult;)Lscala/util/parsing/input/Position;
const #91 = Method	#87.#90;	//  scala/util/parsing/combinator/PackratParsers$class.scala$util$parsing$combinator$PackratParsers$$getPosFromResult:(Lscala/util/parsing/combinator/PackratParsers;Lscala/util/parsing/combinator/Parsers$ParseResult;)Lscala/util/parsing/input/Position;
const #92 = Asciz	scala/util/parsing/input/Position;
const #93 = class	#92;	//  scala/util/parsing/input/Position
const #94 = Asciz	$less;
const #95 = Asciz	(Lscala/util/parsing/input/Position;)Z;
const #96 = NameAndType	#94:#95;//  $less:(Lscala/util/parsing/input/Position;)Z
const #97 = InterfaceMethod	#93.#96;	//  scala/util/parsing/input/Position.$less:(Lscala/util/parsing/input/Position;)Z
const #98 = Asciz	<init>;
const #99 = Asciz	(Ljava/lang/Object;)V;
const #100 = NameAndType	#98:#99;//  "<init>":(Ljava/lang/Object;)V
const #101 = Method	#65.#100;	//  scala/Right."<init>":(Ljava/lang/Object;)V
const #102 = Asciz	(Lscala/util/parsing/combinator/PackratParsers;Lscala/Either;)V;
const #103 = NameAndType	#98:#102;//  "<init>":(Lscala/util/parsing/combinator/PackratParsers;Lscala/Either;)V
const #104 = Method	#59.#103;	//  scala/util/parsing/combinator/PackratParsers$MemoEntry."<init>":(Lscala/util/parsing/combinator/PackratParsers;Lscala/Either;)V
const #105 = Asciz	scala$util$parsing$combinator$PackratParsers$$updateCacheAndGet;
const #106 = Asciz	(Lscala/util/parsing/combinator/Parsers$Parser;Lscala/util/parsing/combinator/PackratParsers$MemoEntry;)Lscala/util/parsing/combinator/PackratParsers$MemoEntry;;
const #107 = NameAndType	#105:#106;//  scala$util$parsing$combinator$PackratParsers$$updateCacheAndGet:(Lscala/util/parsing/combinator/Parsers$Parser;Lscala/util/parsing/combinator/PackratParsers$MemoEntry;)Lscala/util/parsing/combinator/PackratParsers$MemoEntry;
const #108 = Method	#34.#107;	//  scala/util/parsing/combinator/PackratParsers$PackratReader.scala$util$parsing$combinator$PackratParsers$$updateCacheAndGet:(Lscala/util/parsing/combinator/Parsers$Parser;Lscala/util/parsing/combinator/PackratParsers$MemoEntry;)Lscala/util/parsing/combinator/PackratParsers$MemoEntry;
const #109 = Asciz	$minus$eq;
const #110 = Asciz	(Ljava/lang/Object;)Lscala/collection/mutable/HashMap;;
const #111 = NameAndType	#109:#110;//  $minus$eq:(Ljava/lang/Object;)Lscala/collection/mutable/HashMap;
const #112 = Method	#44.#111;	//  scala/collection/mutable/HashMap.$minus$eq:(Ljava/lang/Object;)Lscala/collection/mutable/HashMap;
const #113 = Asciz	java/lang/Exception;
const #114 = class	#113;	//  java/lang/Exception
const #115 = Asciz	impossible match;
const #116 = String	#115;	//  impossible match
const #117 = Asciz	(Ljava/lang/String;)V;
const #118 = NameAndType	#98:#117;//  "<init>":(Ljava/lang/String;)V
const #119 = Method	#114.#118;	//  java/lang/Exception."<init>":(Ljava/lang/String;)V
const #120 = Asciz	scala/MatchError;
const #121 = class	#120;	//  scala/MatchError
const #122 = Asciz	toString;
const #123 = Asciz	()Ljava/lang/String;;
const #124 = NameAndType	#122:#123;//  toString:()Ljava/lang/String;
const #125 = Method	#59.#124;	//  scala/util/parsing/combinator/PackratParsers$MemoEntry.toString:()Ljava/lang/String;
const #126 = Method	#121.#118;	//  scala/MatchError."<init>":(Ljava/lang/String;)V
const #127 = Asciz	p;
const #128 = Asciz	Lscala/util/parsing/combinator/Parsers$Parser;;
const #129 = Asciz	rest;
const #130 = Asciz	Lscala/util/parsing/combinator/PackratParsers$PackratReader;;
const #131 = Asciz	head;
const #132 = Asciz	Lscala/util/parsing/combinator/PackratParsers$Head;;
const #133 = Asciz	oldRes;
const #134 = Asciz	Lscala/util/parsing/combinator/Parsers$ParseResult;;
const #135 = Asciz	temp68;
const #136 = Asciz	Lscala/util/parsing/combinator/PackratParsers$MemoEntry;;
const #137 = Asciz	temp69;
const #138 = Asciz	Lscala/Either;;
const #139 = Asciz	temp70;
const #140 = Asciz	Lscala/Right;;
const #141 = Asciz	temp71;
const #142 = Asciz	tempRes;
const #143 = Asciz	temp76;
const #144 = Asciz	temp77;
const #145 = Asciz	Lscala/util/parsing/combinator/Parsers$Success;;
const #146 = Asciz	temp72;
const #147 = Asciz	temp73;
const #148 = Asciz	temp74;
const #149 = Asciz	temp75;
const #150 = Asciz	<T:Ljava/lang/Object;>(Lscala/util/parsing/combinator/Parsers$Parser<TT;>;Lscala/util/parsing/combinator/PackratParsers$PackratReader<Ljava/lang/Object;>;Lscala/util/parsing/combinator/PackratParsers$Head;)Lscala/util/parsing/combinator/Parsers$ParseResult<TT;>;;
const #151 = Asciz	Signature;
const #152 = Asciz	memo;
const #153 = Asciz	(Lscala/util/parsing/combinator/PackratParsers;Lscala/util/parsing/combinator/Parsers$Parser;)Lscala/util/parsing/combinator/PackratParsers$PackratParser;;
const #154 = Asciz	scala/util/parsing/combinator/PackratParsers$$anon$2;
const #155 = class	#154;	//  scala/util/parsing/combinator/PackratParsers$$anon$2
const #156 = Asciz	(Lscala/util/parsing/combinator/PackratParsers;Lscala/util/parsing/combinator/Parsers$Parser;)V;
const #157 = NameAndType	#98:#156;//  "<init>":(Lscala/util/parsing/combinator/PackratParsers;Lscala/util/parsing/combinator/Parsers$Parser;)V
const #158 = Method	#155.#157;	//  scala/util/parsing/combinator/PackratParsers$$anon$2."<init>":(Lscala/util/parsing/combinator/PackratParsers;Lscala/util/parsing/combinator/Parsers$Parser;)V
const #159 = Asciz	p$2;
const #160 = Asciz	scala$util$parsing$combinator$PackratParsers$$lrAnswer;
const #161 = Asciz	(Lscala/util/parsing/combinator/PackratParsers;Lscala/util/parsing/combinator/Parsers$Parser;Lscala/util/parsing/combinator/PackratParsers$PackratReader;Lscala/util/parsing/combinator/PackratParsers$LR;)Lscala/util/parsing/combinator/Parsers$ParseResult;;
const #162 = Asciz	scala/util/parsing/combinator/PackratParsers$LR;
const #163 = class	#162;	//  scala/util/parsing/combinator/PackratParsers$LR
const #164 = Asciz	seed;
const #165 = Asciz	()Lscala/util/parsing/combinator/Parsers$ParseResult;;
const #166 = NameAndType	#164:#165;//  seed:()Lscala/util/parsing/combinator/Parsers$ParseResult;
const #167 = Method	#163.#166;	//  scala/util/parsing/combinator/PackratParsers$LR.seed:()Lscala/util/parsing/combinator/Parsers$ParseResult;
const #168 = Asciz	rule;
const #169 = Asciz	()Lscala/util/parsing/combinator/Parsers$Parser;;
const #170 = NameAndType	#168:#169;//  rule:()Lscala/util/parsing/combinator/Parsers$Parser;
const #171 = Method	#163.#170;	//  scala/util/parsing/combinator/PackratParsers$LR.rule:()Lscala/util/parsing/combinator/Parsers$Parser;
const #172 = Asciz	()Lscala/Option;;
const #173 = NameAndType	#131:#172;//  head:()Lscala/Option;
const #174 = Method	#163.#173;	//  scala/util/parsing/combinator/PackratParsers$LR.head:()Lscala/Option;
const #175 = Asciz	scala/Some;
const #176 = class	#175;	//  scala/Some
const #177 = Asciz	x;
const #178 = NameAndType	#177:#21;//  x:()Ljava/lang/Object;
const #179 = Method	#176.#178;	//  scala/Some.x:()Ljava/lang/Object;
const #180 = Asciz	getHead;
const #181 = NameAndType	#180:#169;//  getHead:()Lscala/util/parsing/combinator/Parsers$Parser;
const #182 = Method	#72.#181;	//  scala/util/parsing/combinator/PackratParsers$Head.getHead:()Lscala/util/parsing/combinator/Parsers$Parser;
const #183 = Asciz	java/lang/Object;
const #184 = class	#183;	//  java/lang/Object
const #185 = Asciz	equals;
const #186 = Asciz	(Ljava/lang/Object;)Z;
const #187 = NameAndType	#185:#186;//  equals:(Ljava/lang/Object;)Z
const #188 = Method	#184.#187;	//  java/lang/Object.equals:(Ljava/lang/Object;)Z
const #189 = Asciz	scala/util/parsing/combinator/Parsers$Failure;
const #190 = class	#189;	//  scala/util/parsing/combinator/Parsers$Failure
const #191 = Asciz	scala/util/parsing/combinator/Parsers$Error;
const #192 = class	#191;	//  scala/util/parsing/combinator/Parsers$Error
const #193 = NameAndType	#31:#32;//  grow:(Lscala/util/parsing/combinator/PackratParsers;Lscala/util/parsing/combinator/Parsers$Parser;Lscala/util/parsing/combinator/PackratParsers$PackratReader;Lscala/util/parsing/combinator/PackratParsers$Head;)Lscala/util/parsing/combinator/Parsers$ParseResult;
const #194 = Method	#87.#193;	//  scala/util/parsing/combinator/PackratParsers$class.grow:(Lscala/util/parsing/combinator/PackratParsers;Lscala/util/parsing/combinator/Parsers$Parser;Lscala/util/parsing/combinator/PackratParsers$PackratReader;Lscala/util/parsing/combinator/PackratParsers$Head;)Lscala/util/parsing/combinator/Parsers$ParseResult;
const #195 = Method	#70.#124;	//  scala/util/parsing/combinator/Parsers$ParseResult.toString:()Ljava/lang/String;
const #196 = Asciz	lrAnswer with no head !!;
const #197 = String	#196;	//  lrAnswer with no head !!
const #198 = Method	#163.#124;	//  scala/util/parsing/combinator/PackratParsers$LR.toString:()Ljava/lang/String;
const #199 = Asciz	in;
const #200 = Asciz	growable;
const #201 = Asciz	Lscala/util/parsing/combinator/PackratParsers$LR;;
const #202 = Asciz	temp44;
const #203 = Asciz	temp45;
const #204 = Asciz	temp46;
const #205 = Asciz	temp47;
const #206 = Asciz	Lscala/Option;;
const #207 = Asciz	temp48;
const #208 = Asciz	Lscala/Some;;
const #209 = Asciz	temp49;
const #210 = Asciz	temp34;
const #211 = Asciz	temp35;
const #212 = Asciz	Lscala/util/parsing/combinator/Parsers$Failure;;
const #213 = Asciz	temp38;
const #214 = Asciz	Lscala/util/parsing/combinator/Parsers$Error;;
const #215 = Asciz	temp41;
const #216 = Asciz	scala$util$parsing$combinator$PackratParsers$$setupLR;
const #217 = Asciz	(Lscala/util/parsing/combinator/PackratParsers;Lscala/util/parsing/combinator/Parsers$Parser;Lscala/util/parsing/combinator/PackratParsers$PackratReader;Lscala/util/parsing/combinator/PackratParsers$LR;)V;
const #218 = Asciz	scala/None$;
const #219 = class	#218;	//  scala/None$
const #220 = Asciz	MODULE$;
const #221 = Asciz	Lscala/None$;;
const #222 = NameAndType	#220:#221;//  MODULE$:Lscala/None$;
const #223 = Field	#219.#222;	//  scala/None$.MODULE$:Lscala/None$;
const #224 = Asciz	scala/collection/immutable/Nil$;
const #225 = class	#224;	//  scala/collection/immutable/Nil$
const #226 = Asciz	Lscala/collection/immutable/Nil$;;
const #227 = NameAndType	#220:#226;//  MODULE$:Lscala/collection/immutable/Nil$;
const #228 = Field	#225.#227;	//  scala/collection/immutable/Nil$.MODULE$:Lscala/collection/immutable/Nil$;
const #229 = Asciz	(Lscala/util/parsing/combinator/PackratParsers;Lscala/util/parsing/combinator/Parsers$Parser;Lscala/collection/immutable/List;Lscala/collection/immutable/List;)V;
const #230 = NameAndType	#98:#229;//  "<init>":(Lscala/util/parsing/combinator/PackratParsers;Lscala/util/parsing/combinator/Parsers$Parser;Lscala/collection/immutable/List;Lscala/collection/immutable/List;)V
const #231 = Method	#72.#230;	//  scala/util/parsing/combinator/PackratParsers$Head."<init>":(Lscala/util/parsing/combinator/PackratParsers;Lscala/util/parsing/combinator/Parsers$Parser;Lscala/collection/immutable/List;Lscala/collection/immutable/List;)V
const #232 = Method	#176.#100;	//  scala/Some."<init>":(Ljava/lang/Object;)V
const #233 = Asciz	head_$eq;
const #234 = Asciz	(Lscala/Option;)V;
const #235 = NameAndType	#233:#234;//  head_$eq:(Lscala/Option;)V
const #236 = Method	#163.#235;	//  scala/util/parsing/combinator/PackratParsers$LR.head_$eq:(Lscala/Option;)V
const #237 = Asciz	scala$util$parsing$combinator$PackratParsers$$lrStack;
const #238 = NameAndType	#237:#74;//  scala$util$parsing$combinator$PackratParsers$$lrStack:()Lscala/collection/immutable/List;
const #239 = Method	#34.#238;	//  scala/util/parsing/combinator/PackratParsers$PackratReader.scala$util$parsing$combinator$PackratParsers$$lrStack:()Lscala/collection/immutable/List;
const #240 = Asciz	scala/util/parsing/combinator/PackratParsers$$anonfun$scala$util$parsing$combinator$PackratParsers$$setupLR$1;
const #241 = class	#240;	//  scala/util/parsing/combinator/PackratParsers$$anonfun$scala$util$parsing$combinator$PackratParsers$$setupLR$1
const #242 = Method	#241.#157;	//  scala/util/parsing/combinator/PackratParsers$$anonfun$scala$util$parsing$combinator$PackratParsers$$setupLR$1."<init>":(Lscala/util/parsing/combinator/PackratParsers;Lscala/util/parsing/combinator/Parsers$Parser;)V
const #243 = Asciz	scala/collection/immutable/List;
const #244 = class	#243;	//  scala/collection/immutable/List
const #245 = Asciz	takeWhile;
const #246 = Asciz	(Lscala/Function1;)Lscala/collection/immutable/List;;
const #247 = NameAndType	#245:#246;//  takeWhile:(Lscala/Function1;)Lscala/collection/immutable/List;
const #248 = Method	#244.#247;	//  scala/collection/immutable/List.takeWhile:(Lscala/Function1;)Lscala/collection/immutable/List;
const #249 = Asciz	scala/util/parsing/combinator/PackratParsers$$anonfun$scala$util$parsing$combinator$PackratParsers$$setupLR$2;
const #250 = class	#249;	//  scala/util/parsing/combinator/PackratParsers$$anonfun$scala$util$parsing$combinator$PackratParsers$$setupLR$2
const #251 = Asciz	(Lscala/util/parsing/combinator/PackratParsers;Lscala/util/parsing/combinator/PackratParsers$LR;)V;
const #252 = NameAndType	#98:#251;//  "<init>":(Lscala/util/parsing/combinator/PackratParsers;Lscala/util/parsing/combinator/PackratParsers$LR;)V
const #253 = Method	#250.#252;	//  scala/util/parsing/combinator/PackratParsers$$anonfun$scala$util$parsing$combinator$PackratParsers$$setupLR$2."<init>":(Lscala/util/parsing/combinator/PackratParsers;Lscala/util/parsing/combinator/PackratParsers$LR;)V
const #254 = Asciz	scala/collection/generic/LinearSequenceTemplate;
const #255 = class	#254;	//  scala/collection/generic/LinearSequenceTemplate
const #256 = Asciz	foreach;
const #257 = Asciz	(Lscala/Function1;)V;
const #258 = NameAndType	#256:#257;//  foreach:(Lscala/Function1;)V
const #259 = InterfaceMethod	#255.#258;	//  scala/collection/generic/LinearSequenceTemplate.foreach:(Lscala/Function1;)V
const #260 = Asciz	p$4;
const #261 = Asciz	recDetect$1;
const #262 = Asciz	scala$util$parsing$combinator$PackratParsers$$recall;
const #263 = Asciz	(Lscala/util/parsing/combinator/PackratParsers;Lscala/util/parsing/combinator/Parsers$Parser;Lscala/util/parsing/combinator/PackratParsers$PackratReader;)Lscala/Option;;
const #264 = Asciz	(Ljava/lang/Object;)Lscala/Option;;
const #265 = NameAndType	#55:#264;//  get:(Ljava/lang/Object;)Lscala/Option;
const #266 = Method	#44.#265;	//  scala/collection/mutable/HashMap.get:(Ljava/lang/Object;)Lscala/Option;
const #267 = Asciz	headParser;
const #268 = NameAndType	#267:#169;//  headParser:()Lscala/util/parsing/combinator/Parsers$Parser;
const #269 = Method	#72.#268;	//  scala/util/parsing/combinator/PackratParsers$Head.headParser:()Lscala/util/parsing/combinator/Parsers$Parser;
const #270 = Asciz	evalSet;
const #271 = NameAndType	#270:#74;//  evalSet:()Lscala/collection/immutable/List;
const #272 = Method	#72.#271;	//  scala/util/parsing/combinator/PackratParsers$Head.evalSet:()Lscala/collection/immutable/List;
const #273 = Asciz	$colon$colon;
const #274 = Asciz	(Ljava/lang/Object;)Lscala/collection/immutable/List;;
const #275 = NameAndType	#273:#274;//  $colon$colon:(Ljava/lang/Object;)Lscala/collection/immutable/List;
const #276 = Method	#244.#275;	//  scala/collection/immutable/List.$colon$colon:(Ljava/lang/Object;)Lscala/collection/immutable/List;
const #277 = Asciz	scala/collection/generic/SequenceTemplate;
const #278 = class	#277;	//  scala/collection/generic/SequenceTemplate
const #279 = Asciz	contains;
const #280 = NameAndType	#279:#186;//  contains:(Ljava/lang/Object;)Z
const #281 = InterfaceMethod	#278.#280;	//  scala/collection/generic/SequenceTemplate.contains:(Ljava/lang/Object;)Z
const #282 = Asciz	dummy ;
const #283 = String	#282;	//  dummy 
const #284 = Asciz	(Lscala/util/parsing/combinator/Parsers;Ljava/lang/String;Lscala/util/parsing/input/Reader;)V;
const #285 = NameAndType	#98:#284;//  "<init>":(Lscala/util/parsing/combinator/Parsers;Ljava/lang/String;Lscala/util/parsing/input/Reader;)V
const #286 = Method	#190.#285;	//  scala/util/parsing/combinator/Parsers$Failure."<init>":(Lscala/util/parsing/combinator/Parsers;Ljava/lang/String;Lscala/util/parsing/input/Reader;)V
const #287 = Asciz	scala/util/parsing/combinator/PackratParsers$$anonfun$scala$util$parsing$combinator$PackratParsers$$recall$1;
const #288 = class	#287;	//  scala/util/parsing/combinator/PackratParsers$$anonfun$scala$util$parsing$combinator$PackratParsers$$recall$1
const #289 = Method	#288.#157;	//  scala/util/parsing/combinator/PackratParsers$$anonfun$scala$util$parsing$combinator$PackratParsers$$recall$1."<init>":(Lscala/util/parsing/combinator/PackratParsers;Lscala/util/parsing/combinator/Parsers$Parser;)V
const #290 = Asciz	scala/collection/generic/TraversableTemplate;
const #291 = class	#290;	//  scala/collection/generic/TraversableTemplate
const #292 = Asciz	filterNot;
const #293 = Asciz	(Lscala/Function1;)Lscala/collection/generic/TraversableTemplate;;
const #294 = NameAndType	#292:#293;//  filterNot:(Lscala/Function1;)Lscala/collection/generic/TraversableTemplate;
const #295 = InterfaceMethod	#291.#294;	//  scala/collection/generic/TraversableTemplate.filterNot:(Lscala/Function1;)Lscala/collection/generic/TraversableTemplate;
const #296 = Asciz	r_$eq;
const #297 = Asciz	(Lscala/Either;)V;
const #298 = NameAndType	#296:#297;//  r_$eq:(Lscala/Either;)V
const #299 = Method	#59.#298;	//  scala/util/parsing/combinator/PackratParsers$MemoEntry.r_$eq:(Lscala/Either;)V
const #300 = Method	#54.#124;	//  scala/Option.toString:()Ljava/lang/String;
const #301 = Asciz	p$3;
const #302 = Asciz	cached;
const #303 = Asciz	temp27;
const #304 = Asciz	temp29;
const #305 = Asciz	temp30;
const #306 = Asciz	temp31;
const #307 = Asciz	temp32;
const #308 = Asciz	Lscala/collection/immutable/List;;
const #309 = Asciz	temp33;
const #310 = Asciz	involved;
const #311 = Asciz	hp;
const #312 = Asciz	h;
const #313 = Asciz	tempEntry;
const #314 = Asciz	parser2packrat;
const #315 = Asciz	(Lscala/util/parsing/combinator/PackratParsers;Lscala/Function0;)Lscala/util/parsing/combinator/PackratParsers$PackratParser;;
const #316 = Asciz	(I)V;
const #317 = NameAndType	#98:#316;//  "<init>":(I)V
const #318 = Method	#13.#317;	//  scala/runtime/IntRef."<init>":(I)V
const #319 = Method	#27.#100;	//  scala/runtime/ObjectRef."<init>":(Ljava/lang/Object;)V
const #320 = Asciz	scala/util/parsing/combinator/PackratParsers$$anonfun$parser2packrat$1;
const #321 = class	#320;	//  scala/util/parsing/combinator/PackratParsers$$anonfun$parser2packrat$1
const #322 = Asciz	(Lscala/util/parsing/combinator/PackratParsers;Lscala/Function0;Lscala/runtime/ObjectRef;Lscala/runtime/IntRef;)V;
const #323 = NameAndType	#98:#322;//  "<init>":(Lscala/util/parsing/combinator/PackratParsers;Lscala/Function0;Lscala/runtime/ObjectRef;Lscala/runtime/IntRef;)V
const #324 = Method	#321.#323;	//  scala/util/parsing/combinator/PackratParsers$$anonfun$parser2packrat$1."<init>":(Lscala/util/parsing/combinator/PackratParsers;Lscala/Function0;Lscala/runtime/ObjectRef;Lscala/runtime/IntRef;)V
const #325 = Asciz	scala/util/parsing/combinator/PackratParsers;
const #326 = class	#325;	//  scala/util/parsing/combinator/PackratParsers
const #327 = Asciz	scala$util$parsing$combinator$PackratParsers$$super$Parser;
const #328 = Asciz	(Lscala/Function1;)Lscala/util/parsing/combinator/Parsers$Parser;;
const #329 = NameAndType	#327:#328;//  scala$util$parsing$combinator$PackratParsers$$super$Parser:(Lscala/Function1;)Lscala/util/parsing/combinator/Parsers$Parser;
const #330 = InterfaceMethod	#326.#329;	//  scala/util/parsing/combinator/PackratParsers.scala$util$parsing$combinator$PackratParsers$$super$Parser:(Lscala/Function1;)Lscala/util/parsing/combinator/Parsers$Parser;
const #331 = Asciz	(Lscala/util/parsing/combinator/Parsers$Parser;)Lscala/util/parsing/combinator/PackratParsers$PackratParser;;
const #332 = NameAndType	#152:#331;//  memo:(Lscala/util/parsing/combinator/Parsers$Parser;)Lscala/util/parsing/combinator/PackratParsers$PackratParser;
const #333 = InterfaceMethod	#326.#332;	//  scala/util/parsing/combinator/PackratParsers.memo:(Lscala/util/parsing/combinator/Parsers$Parser;)Lscala/util/parsing/combinator/PackratParsers$PackratParser;
const #334 = Asciz	p$1;
const #335 = Asciz	Lscala/Function0;;
const #336 = Asciz	bitmap$0$1;
const #337 = Asciz	Lscala/runtime/IntRef;;
const #338 = Asciz	q$lzy$1;
const #339 = Asciz	Lscala/runtime/ObjectRef;;
const #340 = Asciz	next;
const #341 = Asciz	()Lscala/util/parsing/input/Reader;;
const #342 = NameAndType	#340:#341;//  next:()Lscala/util/parsing/input/Reader;
const #343 = Method	#70.#342;	//  scala/util/parsing/combinator/Parsers$ParseResult.next:()Lscala/util/parsing/input/Reader;
const #344 = Asciz	scala/util/parsing/input/Reader;
const #345 = class	#344;	//  scala/util/parsing/input/Reader
const #346 = Method	#345.#41;	//  scala/util/parsing/input/Reader.pos:()Lscala/util/parsing/input/Position;
const #347 = Asciz	phrase;
const #348 = Asciz	scala$util$parsing$combinator$PackratParsers$$super$phrase;
const #349 = Asciz	(Lscala/util/parsing/combinator/Parsers$Parser;)Lscala/util/parsing/combinator/Parsers$Parser;;
const #350 = NameAndType	#348:#349;//  scala$util$parsing$combinator$PackratParsers$$super$phrase:(Lscala/util/parsing/combinator/Parsers$Parser;)Lscala/util/parsing/combinator/Parsers$Parser;
const #351 = InterfaceMethod	#326.#350;	//  scala/util/parsing/combinator/PackratParsers.scala$util$parsing$combinator$PackratParsers$$super$phrase:(Lscala/util/parsing/combinator/Parsers$Parser;)Lscala/util/parsing/combinator/Parsers$Parser;
const #352 = Asciz	scala/util/parsing/combinator/PackratParsers$$anon$1;
const #353 = class	#352;	//  scala/util/parsing/combinator/PackratParsers$$anon$1
const #354 = Method	#353.#157;	//  scala/util/parsing/combinator/PackratParsers$$anon$1."<init>":(Lscala/util/parsing/combinator/PackratParsers;Lscala/util/parsing/combinator/Parsers$Parser;)V
const #355 = Asciz	q$1;
const #356 = Asciz	Scala;
const #357 = Asciz	InnerClasses;
const #358 = Asciz	scala/util/parsing/combinator/Parsers;
const #359 = class	#358;	//  scala/util/parsing/combinator/Parsers
const #360 = Asciz	Error;
const #361 = Asciz	Parser;
const #362 = Asciz	Failure;
const #363 = Asciz	Success;
const #364 = Asciz	LR;
const #365 = Asciz	ParseResult;
const #366 = Asciz	Head;
const #367 = Asciz	$anon$2;
const #368 = Asciz	$anon$1;
const #369 = Asciz	MemoEntry;
const #370 = Asciz	PackratReader;
const #371 = Asciz	scala/util/parsing/combinator/PackratParsers$PackratParser;
const #372 = class	#371;	//  scala/util/parsing/combinator/PackratParsers$PackratParser
const #373 = Asciz	PackratParser;
const #374 = Asciz	$anonfun$parser2packrat$1;
const #375 = Asciz	$anonfun$scala$util$parsing$combinator$PackratParsers$$recall$1;
const #376 = Asciz	$anonfun$scala$util$parsing$combinator$PackratParsers$$setupLR$2;
const #377 = Asciz	$anonfun$scala$util$parsing$combinator$PackratParsers$$setupLR$1;

{
public static void $init$(scala.util.parsing.combinator.PackratParsers);
  Code:
   Stack=0, Locals=1, Args_size=1
   0:	return
  LineNumberTable: 
   line 59: 0

  LocalVariableTable: 
   Start  Length  Slot  Name   Signature
   0      1      0    $this       Lscala/util/parsing/combinator/PackratParsers;


public static final scala.util.parsing.combinator.Parsers$Parser q$2(scala.util.parsing.combinator.PackratParsers, scala.Function0, scala.runtime.ObjectRef, scala.runtime.IntRef);
  Code:
   Stack=3, Locals=4, Args_size=4
   0:	aload_3
   1:	getfield	#17; //Field scala/runtime/IntRef.elem:I
   4:	iconst_1
   5:	iand
   6:	iconst_0
   7:	if_icmpne	33
   10:	aload_2
   11:	aload_1
   12:	invokeinterface	#23,  1; //InterfaceMethod scala/Function0.apply:()Ljava/lang/Object;
   17:	checkcast	#25; //class scala/util/parsing/combinator/Parsers$Parser
   20:	putfield	#30; //Field scala/runtime/ObjectRef.elem:Ljava/lang/Object;
   23:	aload_3
   24:	aload_3
   25:	getfield	#17; //Field scala/runtime/IntRef.elem:I
   28:	iconst_1
   29:	ior
   30:	putfield	#17; //Field scala/runtime/IntRef.elem:I
   33:	aload_2
   34:	getfield	#30; //Field scala/runtime/ObjectRef.elem:Ljava/lang/Object;
   37:	checkcast	#25; //class scala/util/parsing/combinator/Parsers$Parser
   40:	areturn
  LineNumberTable: 
   line 160: 0

  LocalVariableTable: 
   Start  Length  Slot  Name   Signature
   0      41      0    $this       Lscala/util/parsing/combinator/PackratParsers;


public static scala.util.parsing.combinator.PackratParsers$PackratParser memo(scala.util.parsing.combinator.PackratParsers, scala.util.parsing.combinator.Parsers$Parser);
  Code:
   Stack=4, Locals=2, Args_size=2
   0:	new	#155; //class scala/util/parsing/combinator/PackratParsers$$anon$2
   3:	dup
   4:	aload_0
   5:	aload_1
   6:	invokespecial	#158; //Method scala/util/parsing/combinator/PackratParsers$$anon$2."<init>":(Lscala/util/parsing/combinator/PackratParsers;Lscala/util/parsing/combinator/Parsers$Parser;)V
   9:	areturn
  LineNumberTable: 
   line 250: 0

  LocalVariableTable: 
   Start  Length  Slot  Name   Signature
   0      10      0    $this       Lscala/util/parsing/combinator/PackratParsers;
   0      10      1    p$2       Lscala/util/parsing/combinator/Parsers$Parser;


public static final scala.util.parsing.combinator.Parsers$ParseResult scala$util$parsing$combinator$PackratParsers$$lrAnswer(scala.util.parsing.combinator.PackratParsers, scala.util.parsing.combinator.Parsers$Parser, scala.util.parsing.combinator.PackratParsers$PackratReader, scala.util.parsing.combinator.PackratParsers$LR);
  Code:
   Stack=8, Locals=18, Args_size=4
   0:	aload_3
   1:	astore	4
   3:	aload	4
   5:	ifnull	214
   8:	aload	4
   10:	invokevirtual	#167; //Method scala/util/parsing/combinator/PackratParsers$LR.seed:()Lscala/util/parsing/combinator/Parsers$ParseResult;
   13:	astore	5
   15:	aload	4
   17:	invokevirtual	#171; //Method scala/util/parsing/combinator/PackratParsers$LR.rule:()Lscala/util/parsing/combinator/Parsers$Parser;
   20:	astore	6
   22:	aload	4
   24:	invokevirtual	#174; //Method scala/util/parsing/combinator/PackratParsers$LR.head:()Lscala/Option;
   27:	astore	7
   29:	aload	7
   31:	instanceof	#176; //class scala/Some
   34:	ifeq	204
   37:	aload	7
   39:	checkcast	#176; //class scala/Some
   42:	astore	8
   44:	aload	8
   46:	invokevirtual	#179; //Method scala/Some.x:()Ljava/lang/Object;
   49:	checkcast	#72; //class scala/util/parsing/combinator/PackratParsers$Head
   52:	astore	9
   54:	aload	9
   56:	astore	10
   58:	aload	6
   60:	astore	11
   62:	aload	5
   64:	astore	12
   66:	aload	10
   68:	invokevirtual	#182; //Method scala/util/parsing/combinator/PackratParsers$Head.getHead:()Lscala/util/parsing/combinator/Parsers$Parser;
   71:	aload_1
   72:	astore	13
   74:	dup
   75:	ifnonnull	87
   78:	pop
   79:	aload	13
   81:	ifnull	95
   84:	goto	201
   87:	aload	13
   89:	invokevirtual	#188; //Method java/lang/Object.equals:(Ljava/lang/Object;)Z
   92:	ifeq	201
   95:	aload_2
   96:	aload_1
   97:	new	#59; //class scala/util/parsing/combinator/PackratParsers$MemoEntry
   100:	dup
   101:	aload_0
   102:	new	#65; //class scala/Right
   105:	dup
   106:	aload	12
   108:	invokespecial	#101; //Method scala/Right."<init>":(Ljava/lang/Object;)V
   111:	invokespecial	#104; //Method scala/util/parsing/combinator/PackratParsers$MemoEntry."<init>":(Lscala/util/parsing/combinator/PackratParsers;Lscala/Either;)V
   114:	invokevirtual	#108; //Method scala/util/parsing/combinator/PackratParsers$PackratReader.scala$util$parsing$combinator$PackratParsers$$updateCacheAndGet:(Lscala/util/parsing/combinator/Parsers$Parser;Lscala/util/parsing/combinator/PackratParsers$MemoEntry;)Lscala/util/parsing/combinator/PackratParsers$MemoEntry;
   117:	pop
   118:	aload	12
   120:	astore	14
   122:	aload	14
   124:	instanceof	#190; //class scala/util/parsing/combinator/Parsers$Failure
   127:	ifeq	142
   130:	aload	14
   132:	checkcast	#190; //class scala/util/parsing/combinator/Parsers$Failure
   135:	astore	15
   137:	aload	15
   139:	goto	203
   142:	aload	14
   144:	instanceof	#192; //class scala/util/parsing/combinator/Parsers$Error
   147:	ifeq	162
   150:	aload	14
   152:	checkcast	#192; //class scala/util/parsing/combinator/Parsers$Error
   155:	astore	16
   157:	aload	16
   159:	goto	203
   162:	aload	14
   164:	instanceof	#85; //class scala/util/parsing/combinator/Parsers$Success
   167:	ifeq	188
   170:	aload	14
   172:	checkcast	#85; //class scala/util/parsing/combinator/Parsers$Success
   175:	astore	17
   177:	aload_0
   178:	aload_1
   179:	aload_2
   180:	aload	10
   182:	invokestatic	#194; //Method grow:(Lscala/util/parsing/combinator/PackratParsers;Lscala/util/parsing/combinator/Parsers$Parser;Lscala/util/parsing/combinator/PackratParsers$PackratReader;Lscala/util/parsing/combinator/PackratParsers$Head;)Lscala/util/parsing/combinator/Parsers$ParseResult;
   185:	goto	203
   188:	new	#121; //class scala/MatchError
   191:	dup
   192:	aload	14
   194:	invokevirtual	#195; //Method scala/util/parsing/combinator/Parsers$ParseResult.toString:()Ljava/lang/String;
   197:	invokespecial	#126; //Method scala/MatchError."<init>":(Ljava/lang/String;)V
   200:	athrow
   201:	aload	12
   203:	areturn
   204:	new	#114; //class java/lang/Exception
   207:	dup
   208:	ldc	#197; //String lrAnswer with no head !!
   210:	invokespecial	#119; //Method java/lang/Exception."<init>":(Ljava/lang/String;)V
   213:	athrow
   214:	new	#121; //class scala/MatchError
   217:	dup
   218:	aload	4
   220:	invokevirtual	#198; //Method scala/util/parsing/combinator/PackratParsers$LR.toString:()Ljava/lang/String;
   223:	invokespecial	#126; //Method scala/MatchError."<init>":(Ljava/lang/String;)V
   226:	athrow
  LineNumberTable: 
   line 226: 0
   line 228: 54
   line 229: 66
   line 231: 95
   line 232: 118
   line 233: 137
   line 232: 142
   line 234: 157
   line 232: 162
   line 235: 177
   line 232: 188
   line 229: 201
   line 226: 203
   line 238: 204
   line 226: 214

  LocalVariableTable: 
   Start  Length  Slot  Name   Signature
   0      227      0    $this       Lscala/util/parsing/combinator/PackratParsers;
   0      227      1    p       Lscala/util/parsing/combinator/Parsers$Parser;
   0      227      2    in       Lscala/util/parsing/combinator/PackratParsers$PackratReader;
   0      227      3    growable       Lscala/util/parsing/combinator/PackratParsers$LR;
   3      224      4    temp44       Lscala/util/parsing/combinator/PackratParsers$LR;
   15      188      5    temp45       Lscala/util/parsing/combinator/Parsers$ParseResult;
   204      10      5    temp45       Lscala/util/parsing/combinator/Parsers$ParseResult;
   22      181      6    temp46       Lscala/util/parsing/combinator/Parsers$Parser;
   204      10      6    temp46       Lscala/util/parsing/combinator/Parsers$Parser;
   29      174      7    temp47       Lscala/Option;
   204      10      7    temp47       Lscala/Option;
   44      159      8    temp48       Lscala/Some;
   54      149      9    temp49       Lscala/util/parsing/combinator/PackratParsers$Head;
   58      145      10    head       Lscala/util/parsing/combinator/PackratParsers$Head;
   62      141      11    rule       Lscala/util/parsing/combinator/Parsers$Parser;
   66      137      12    seed       Lscala/util/parsing/combinator/Parsers$ParseResult;
   122      79      14    temp34       Lscala/util/parsing/combinator/Parsers$ParseResult;
   137      2      15    temp35       Lscala/util/parsing/combinator/Parsers$Failure;
   157      2      16    temp38       Lscala/util/parsing/combinator/Parsers$Error;
   177      8      17    temp41       Lscala/util/parsing/combinator/Parsers$Success;


public static final void scala$util$parsing$combinator$PackratParsers$$setupLR(scala.util.parsing.combinator.PackratParsers, scala.util.parsing.combinator.Parsers$Parser, scala.util.parsing.combinator.PackratParsers$PackratReader, scala.util.parsing.combinator.PackratParsers$LR);
  Code:
   Stack=9, Locals=5, Args_size=4
   0:	aload_3
   1:	invokevirtual	#174; //Method scala/util/parsing/combinator/PackratParsers$LR.head:()Lscala/Option;
   4:	getstatic	#223; //Field scala/None$.MODULE$:Lscala/None$;
   7:	astore	4
   9:	dup
   10:	ifnonnull	22
   13:	pop
   14:	aload	4
   16:	ifnull	30
   19:	goto	56
   22:	aload	4
   24:	invokevirtual	#188; //Method java/lang/Object.equals:(Ljava/lang/Object;)Z
   27:	ifeq	56
   30:	aload_3
   31:	new	#176; //class scala/Some
   34:	dup
   35:	new	#72; //class scala/util/parsing/combinator/PackratParsers$Head
   38:	dup
   39:	aload_0
   40:	aload_1
   41:	getstatic	#228; //Field scala/collection/immutable/Nil$.MODULE$:Lscala/collection/immutable/Nil$;
   44:	getstatic	#228; //Field scala/collection/immutable/Nil$.MODULE$:Lscala/collection/immutable/Nil$;
   47:	invokespecial	#231; //Method scala/util/parsing/combinator/PackratParsers$Head."<init>":(Lscala/util/parsing/combinator/PackratParsers;Lscala/util/parsing/combinator/Parsers$Parser;Lscala/collection/immutable/List;Lscala/collection/immutable/List;)V
   50:	invokespecial	#232; //Method scala/Some."<init>":(Ljava/lang/Object;)V
   53:	invokevirtual	#236; //Method scala/util/parsing/combinator/PackratParsers$LR.head_$eq:(Lscala/Option;)V
   56:	aload_2
   57:	invokevirtual	#239; //Method scala/util/parsing/combinator/PackratParsers$PackratReader.scala$util$parsing$combinator$PackratParsers$$lrStack:()Lscala/collection/immutable/List;
   60:	new	#241; //class scala/util/parsing/combinator/PackratParsers$$anonfun$scala$util$parsing$combinator$PackratParsers$$setupLR$1
   63:	dup
   64:	aload_0
   65:	aload_1
   66:	invokespecial	#242; //Method scala/util/parsing/combinator/PackratParsers$$anonfun$scala$util$parsing$combinator$PackratParsers$$setupLR$1."<init>":(Lscala/util/parsing/combinator/PackratParsers;Lscala/util/parsing/combinator/Parsers$Parser;)V
   69:	invokevirtual	#248; //Method scala/collection/immutable/List.takeWhile:(Lscala/Function1;)Lscala/collection/immutable/List;
   72:	new	#250; //class scala/util/parsing/combinator/PackratParsers$$anonfun$scala$util$parsing$combinator$PackratParsers$$setupLR$2
   75:	dup
   76:	aload_0
   77:	aload_3
   78:	invokespecial	#253; //Method scala/util/parsing/combinator/PackratParsers$$anonfun$scala$util$parsing$combinator$PackratParsers$$setupLR$2."<init>":(Lscala/util/parsing/combinator/PackratParsers;Lscala/util/parsing/combinator/PackratParsers$LR;)V
   81:	invokeinterface	#259,  2; //InterfaceMethod scala/collection/generic/LinearSequenceTemplate.foreach:(Lscala/Function1;)V
   86:	return
  LineNumberTable: 
   line 205: 0
   line 207: 56

  LocalVariableTable: 
   Start  Length  Slot  Name   Signature
   0      87      0    $this       Lscala/util/parsing/combinator/PackratParsers;
   0      87      1    p$4       Lscala/util/parsing/combinator/Parsers$Parser;
   0      87      2    in       Lscala/util/parsing/combinator/PackratParsers$PackratReader;
   0      87      3    recDetect$1       Lscala/util/parsing/combinator/PackratParsers$LR;


public static final scala.Option scala$util$parsing$combinator$PackratParsers$$recall(scala.util.parsing.combinator.PackratParsers, scala.util.parsing.combinator.Parsers$Parser, scala.util.parsing.combinator.PackratParsers$PackratReader);
  Code:
   Stack=12, Locals=20, Args_size=3
   0:	aload_2
   1:	aload_1
   2:	invokevirtual	#52; //Method scala/util/parsing/combinator/PackratParsers$PackratReader.scala$util$parsing$combinator$PackratParsers$$getFromCache:(Lscala/util/parsing/combinator/Parsers$Parser;)Lscala/Option;
   5:	astore_3
   6:	aload_2
   7:	invokevirtual	#38; //Method scala/util/parsing/combinator/PackratParsers$PackratReader.scala$util$parsing$combinator$PackratParsers$$recursionHeads:()Lscala/collection/mutable/HashMap;
   10:	aload_2
   11:	invokevirtual	#42; //Method scala/util/parsing/combinator/PackratParsers$PackratReader.pos:()Lscala/util/parsing/input/Position;
   14:	invokevirtual	#266; //Method scala/collection/mutable/HashMap.get:(Ljava/lang/Object;)Lscala/Option;
   17:	astore	4
   19:	aload	4
   21:	astore	5
   23:	getstatic	#223; //Field scala/None$.MODULE$:Lscala/None$;
   26:	aload	5
   28:	astore	6
   30:	dup
   31:	ifnonnull	43
   34:	pop
   35:	aload	6
   37:	ifnull	51
   40:	goto	63
   43:	aload	6
   45:	invokevirtual	#188; //Method java/lang/Object.equals:(Ljava/lang/Object;)Z
   48:	ifeq	63
   51:	aload	5
   53:	instanceof	#219; //class scala/None$
   56:	ifeq	63
   59:	aload_3
   60:	goto	281
   63:	aload	5
   65:	instanceof	#176; //class scala/Some
   68:	ifeq	295
   71:	aload	5
   73:	checkcast	#176; //class scala/Some
   76:	astore	7
   78:	aload	7
   80:	invokevirtual	#179; //Method scala/Some.x:()Ljava/lang/Object;
   83:	checkcast	#72; //class scala/util/parsing/combinator/PackratParsers$Head
   86:	astore	8
   88:	aload	8
   90:	ifnull	282
   93:	aload	8
   95:	invokevirtual	#269; //Method scala/util/parsing/combinator/PackratParsers$Head.headParser:()Lscala/util/parsing/combinator/Parsers$Parser;
   98:	astore	9
   100:	aload	8
   102:	invokevirtual	#76; //Method scala/util/parsing/combinator/PackratParsers$Head.involvedSet:()Lscala/collection/immutable/List;
   105:	astore	10
   107:	aload	8
   109:	invokevirtual	#272; //Method scala/util/parsing/combinator/PackratParsers$Head.evalSet:()Lscala/collection/immutable/List;
   112:	astore	11
   114:	aload	11
   116:	astore	12
   118:	aload	10
   120:	astore	13
   122:	aload	9
   124:	astore	14
   126:	aload	8
   128:	astore	15
   130:	aload_3
   131:	getstatic	#223; //Field scala/None$.MODULE$:Lscala/None$;
   134:	astore	16
   136:	dup
   137:	ifnonnull	149
   140:	pop
   141:	aload	16
   143:	ifnull	157
   146:	goto	212
   149:	aload	16
   151:	invokevirtual	#188; //Method java/lang/Object.equals:(Ljava/lang/Object;)Z
   154:	ifeq	212
   157:	aload	14
   159:	astore	17
   161:	aload	13
   163:	aload	17
   165:	invokevirtual	#276; //Method scala/collection/immutable/List.$colon$colon:(Ljava/lang/Object;)Lscala/collection/immutable/List;
   168:	aload_1
   169:	invokeinterface	#281,  2; //InterfaceMethod scala/collection/generic/SequenceTemplate.contains:(Ljava/lang/Object;)Z
   174:	ifne	212
   177:	new	#176; //class scala/Some
   180:	dup
   181:	new	#59; //class scala/util/parsing/combinator/PackratParsers$MemoEntry
   184:	dup
   185:	aload_0
   186:	new	#65; //class scala/Right
   189:	dup
   190:	new	#190; //class scala/util/parsing/combinator/Parsers$Failure
   193:	dup
   194:	aload_0
   195:	ldc_w	#283; //String dummy 
   198:	aload_2
   199:	invokespecial	#286; //Method scala/util/parsing/combinator/Parsers$Failure."<init>":(Lscala/util/parsing/combinator/Parsers;Ljava/lang/String;Lscala/util/parsing/input/Reader;)V
   202:	invokespecial	#101; //Method scala/Right."<init>":(Ljava/lang/Object;)V
   205:	invokespecial	#104; //Method scala/util/parsing/combinator/PackratParsers$MemoEntry."<init>":(Lscala/util/parsing/combinator/PackratParsers;Lscala/Either;)V
   208:	invokespecial	#232; //Method scala/Some."<init>":(Ljava/lang/Object;)V
   211:	areturn
   212:	aload	12
   214:	aload_1
   215:	invokeinterface	#281,  2; //InterfaceMethod scala/collection/generic/SequenceTemplate.contains:(Ljava/lang/Object;)Z
   220:	ifeq	280
   223:	aload	15
   225:	aload	15
   227:	invokevirtual	#272; //Method scala/util/parsing/combinator/PackratParsers$Head.evalSet:()Lscala/collection/immutable/List;
   230:	new	#288; //class scala/util/parsing/combinator/PackratParsers$$anonfun$scala$util$parsing$combinator$PackratParsers$$recall$1
   233:	dup
   234:	aload_0
   235:	aload_1
   236:	invokespecial	#289; //Method scala/util/parsing/combinator/PackratParsers$$anonfun$scala$util$parsing$combinator$PackratParsers$$recall$1."<init>":(Lscala/util/parsing/combinator/PackratParsers;Lscala/util/parsing/combinator/Parsers$Parser;)V
   239:	invokeinterface	#295,  2; //InterfaceMethod scala/collection/generic/TraversableTemplate.filterNot:(Lscala/Function1;)Lscala/collection/generic/TraversableTemplate;
   244:	checkcast	#244; //class scala/collection/immutable/List
   247:	invokevirtual	#80; //Method scala/util/parsing/combinator/PackratParsers$Head.evalSet_$eq:(Lscala/collection/immutable/List;)V
   250:	aload_1
   251:	aload_2
   252:	invokevirtual	#83; //Method scala/util/parsing/combinator/Parsers$Parser.apply:(Lscala/util/parsing/input/Reader;)Lscala/util/parsing/combinator/Parsers$ParseResult;
   255:	astore	18
   257:	aload_3
   258:	invokevirtual	#57; //Method scala/Option.get:()Ljava/lang/Object;
   261:	checkcast	#59; //class scala/util/parsing/combinator/PackratParsers$MemoEntry
   264:	astore	19
   266:	aload	19
   268:	new	#65; //class scala/Right
   271:	dup
   272:	aload	18
   274:	invokespecial	#101; //Method scala/Right."<init>":(Ljava/lang/Object;)V
   277:	invokevirtual	#299; //Method scala/util/parsing/combinator/PackratParsers$MemoEntry.r_$eq:(Lscala/Either;)V
   280:	aload_3
   281:	areturn
   282:	new	#121; //class scala/MatchError
   285:	dup
   286:	aload	5
   288:	invokevirtual	#300; //Method scala/Option.toString:()Ljava/lang/String;
   291:	invokespecial	#126; //Method scala/MatchError."<init>":(Ljava/lang/String;)V
   294:	athrow
   295:	new	#121; //class scala/MatchError
   298:	dup
   299:	aload	5
   301:	invokevirtual	#300; //Method scala/Option.toString:()Ljava/lang/String;
   304:	invokespecial	#126; //Method scala/MatchError."<init>":(Ljava/lang/String;)V
   307:	athrow
  LineNumberTable: 
   line 173: 0
   line 174: 6
   line 176: 19
   line 177: 59
   line 176: 63
   line 178: 114
   line 180: 130
   line 182: 177
   line 184: 212
   line 187: 223
   line 188: 250
   line 190: 257
   line 192: 266
   line 194: 280
   line 172: 281
   line 176: 282

  LocalVariableTable: 
   Start  Length  Slot  Name   Signature
   0      308      0    $this       Lscala/util/parsing/combinator/PackratParsers;
   0      308      1    p$3       Lscala/util/parsing/combinator/Parsers$Parser;
   0      308      2    in       Lscala/util/parsing/combinator/PackratParsers$PackratReader;
   6      302      3    cached       Lscala/Option;
   19      289      4    head       Lscala/Option;
   23      285      5    temp27       Lscala/Option;
   78      203      7    temp29       Lscala/Some;
   282      13      7    temp29       Lscala/Some;
   88      193      8    temp30       Lscala/util/parsing/combinator/PackratParsers$Head;
   282      13      8    temp30       Lscala/util/parsing/combinator/PackratParsers$Head;
   100      181      9    temp31       Lscala/util/parsing/combinator/Parsers$Parser;
   107      174      10    temp32       Lscala/collection/immutable/List;
   114      167      11    temp33       Lscala/collection/immutable/List;
   118      163      12    evalSet       Lscala/collection/immutable/List;
   122      159      13    involved       Lscala/collection/immutable/List;
   126      155      14    hp       Lscala/util/parsing/combinator/Parsers$Parser;
   130      151      15    h       Lscala/util/parsing/combinator/PackratParsers$Head;
   257      23      18    tempRes       Lscala/util/parsing/combinator/Parsers$ParseResult;
   266      14      19    tempEntry       Lscala/util/parsing/combinator/PackratParsers$MemoEntry;


public static scala.util.parsing.combinator.PackratParsers$PackratParser parser2packrat(scala.util.parsing.combinator.PackratParsers, scala.Function0);
  Code:
   Stack=8, Locals=4, Args_size=2
   0:	new	#13; //class scala/runtime/IntRef
   3:	dup
   4:	iconst_0
   5:	invokespecial	#318; //Method scala/runtime/IntRef."<init>":(I)V
   8:	astore_2
   9:	new	#27; //class scala/runtime/ObjectRef
   12:	dup
   13:	aconst_null
   14:	invokespecial	#319; //Method scala/runtime/ObjectRef."<init>":(Ljava/lang/Object;)V
   17:	astore_3
   18:	aload_0
   19:	aload_0
   20:	new	#321; //class scala/util/parsing/combinator/PackratParsers$$anonfun$parser2packrat$1
   23:	dup
   24:	aload_0
   25:	aload_1
   26:	aload_3
   27:	aload_2
   28:	invokespecial	#324; //Method scala/util/parsing/combinator/PackratParsers$$anonfun$parser2packrat$1."<init>":(Lscala/util/parsing/combinator/PackratParsers;Lscala/Function0;Lscala/runtime/ObjectRef;Lscala/runtime/IntRef;)V
   31:	invokeinterface	#330,  2; //InterfaceMethod scala/util/parsing/combinator/PackratParsers.scala$util$parsing$combinator$PackratParsers$$super$Parser:(Lscala/Function1;)Lscala/util/parsing/combinator/Parsers$Parser;
   36:	invokeinterface	#333,  2; //InterfaceMethod scala/util/parsing/combinator/PackratParsers.memo:(Lscala/util/parsing/combinator/Parsers$Parser;)Lscala/util/parsing/combinator/PackratParsers$PackratParser;
   41:	areturn
  LineNumberTable: 
   line 160: 0
   line 159: 8
   line 160: 17
   line 161: 18

  LocalVariableTable: 
   Start  Length  Slot  Name   Signature
   0      42      0    $this       Lscala/util/parsing/combinator/PackratParsers;
   0      42      1    p$1       Lscala/Function0;
   9      32      2    bitmap$0$1       Lscala/runtime/IntRef;
   18      23      3    q$lzy$1       Lscala/runtime/ObjectRef;


public static final scala.util.parsing.input.Position scala$util$parsing$combinator$PackratParsers$$getPosFromResult(scala.util.parsing.combinator.PackratParsers, scala.util.parsing.combinator.Parsers$ParseResult);
  Code:
   Stack=1, Locals=2, Args_size=2
   0:	aload_1
   1:	invokevirtual	#343; //Method scala/util/parsing/combinator/Parsers$ParseResult.next:()Lscala/util/parsing/input/Reader;
   4:	invokevirtual	#346; //Method scala/util/parsing/input/Reader.pos:()Lscala/util/parsing/input/Position;
   7:	areturn
  LineNumberTable: 
   line 130: 0

  LocalVariableTable: 
   Start  Length  Slot  Name   Signature
   0      8      0    $this       Lscala/util/parsing/combinator/PackratParsers;
   0      8      1    r       Lscala/util/parsing/combinator/Parsers$ParseResult;


public static scala.util.parsing.combinator.PackratParsers$PackratParser phrase(scala.util.parsing.combinator.PackratParsers, scala.util.parsing.combinator.Parsers$Parser);
  Code:
   Stack=4, Locals=3, Args_size=2
   0:	aload_0
   1:	aload_1
   2:	invokeinterface	#351,  2; //InterfaceMethod scala/util/parsing/combinator/PackratParsers.scala$util$parsing$combinator$PackratParsers$$super$phrase:(Lscala/util/parsing/combinator/Parsers$Parser;)Lscala/util/parsing/combinator/Parsers$Parser;
   7:	astore_2
   8:	new	#353; //class scala/util/parsing/combinator/PackratParsers$$anon$1
   11:	dup
   12:	aload_0
   13:	aload_2
   14:	invokespecial	#354; //Method scala/util/parsing/combinator/PackratParsers$$anon$1."<init>":(Lscala/util/parsing/combinator/PackratParsers;Lscala/util/parsing/combinator/Parsers$Parser;)V
   17:	areturn
  LineNumberTable: 
   line 120: 0
   line 121: 8

  LocalVariableTable: 
   Start  Length  Slot  Name   Signature
   0      18      0    $this       Lscala/util/parsing/combinator/PackratParsers;
   0      18      1    p       Lscala/util/parsing/combinator/Parsers$Parser;
   8      9      2    q$1       Lscala/util/parsing/combinator/Parsers$Parser;


}

