Compiled from "PackratParsers.scala"
public abstract class scala.util.parsing.combinator.PackratParsers$class extends java.lang.Object
  SourceFile: "PackratParsers.scala"
  Scala: length = 0x
   
  InnerClass: 
   public Error=class scala/util/parsing/combinator/Parsers$Error of class scala/util/parsing/combinator/Parsers
   public abstract Parser=class scala/util/parsing/combinator/Parsers$Parser of class scala/util/parsing/combinator/Parsers
   public Failure=class scala/util/parsing/combinator/Parsers$Failure of class scala/util/parsing/combinator/Parsers
   public Success=class scala/util/parsing/combinator/Parsers$Success of class scala/util/parsing/combinator/Parsers
   public LR=class scala/util/parsing/combinator/PackratParsers$LR of class scala/util/parsing/combinator/PackratParsers
   public Head=class scala/util/parsing/combinator/PackratParsers$Head of class scala/util/parsing/combinator/PackratParsers
   public abstract ParseResult=class scala/util/parsing/combinator/Parsers$ParseResult of class scala/util/parsing/combinator/Parsers
   public final $anon$1=class scala/util/parsing/combinator/PackratParsers$$anon$1 of class scala/util/parsing/combinator/PackratParsers
   public final $anon$2=class scala/util/parsing/combinator/PackratParsers$$anon$2 of class scala/util/parsing/combinator/PackratParsers
   public MemoEntry=class scala/util/parsing/combinator/PackratParsers$MemoEntry of class scala/util/parsing/combinator/PackratParsers
   public abstract PackratParser=class scala/util/parsing/combinator/PackratParsers$PackratParser of class scala/util/parsing/combinator/PackratParsers
   public PackratReader=class scala/util/parsing/combinator/PackratParsers$PackratReader of class scala/util/parsing/combinator/PackratParsers
   public final $anonfun$parser2packrat$1=class scala/util/parsing/combinator/PackratParsers$$anonfun$parser2packrat$1 of class scala/util/parsing/combinator/PackratParsers
   public final $anonfun$scala$util$parsing$combinator$PackratParsers$$recall$1=class scala/util/parsing/combinator/PackratParsers$$anonfun$scala$util$parsing$combinator$PackratParsers$$recall$1 of class scala/util/parsing/combinator/PackratParsers
   public final $anonfun$scala$util$parsing$combinator$PackratParsers$$setupLR$2=class scala/util/parsing/combinator/PackratParsers$$anonfun$scala$util$parsing$combinator$PackratParsers$$setupLR$2 of class scala/util/parsing/combinator/PackratParsers
   public final $anonfun$scala$util$parsing$combinator$PackratParsers$$setupLR$1=class scala/util/parsing/combinator/PackratParsers$$anonfun$scala$util$parsing$combinator$PackratParsers$$setupLR$1 of class scala/util/parsing/combinator/PackratParsers
  minor version: 0
  major version: 49
  Constant pool:
Asciz	SourceFile;
Asciz	PackratParsers.scala;
Asciz	$init$;
Asciz	(Lscala/util/parsing/combinator/PackratParsers;)V;
Asciz	Code;
Asciz	LineNumberTable;
Asciz	$this;
Asciz	Lscala/util/parsing/combinator/PackratParsers;;
Asciz	LocalVariableTable;
Asciz	q$2;
Asciz	(Lscala/util/parsing/combinator/PackratParsers;Lscala/Function0;Lscala/runtime/ObjectRef;Lscala/runtime/IntRef;)Lscala/util/parsing/combinator/Parsers$Parser;;
Asciz	scala/runtime/IntRef;
class	scala/runtime/IntRef
Asciz	elem;
Asciz	I;
NameAndType	elem:I
Field	scala/runtime/IntRef.elem:I
Asciz	scala/Function0;
class	scala/Function0
Asciz	apply;
Asciz	()Ljava/lang/Object;;
NameAndType	apply:()Ljava/lang/Object;
InterfaceMethod	scala/Function0.apply:()Ljava/lang/Object;
Asciz	scala/util/parsing/combinator/Parsers$Parser;
class	scala/util/parsing/combinator/Parsers$Parser
Asciz	scala/runtime/ObjectRef;
class	scala/runtime/ObjectRef
Asciz	Ljava/lang/Object;;
NameAndType	elem:Ljava/lang/Object;
Field	scala/runtime/ObjectRef.elem:Ljava/lang/Object;
Asciz	grow;
Asciz	(Lscala/util/parsing/combinator/PackratParsers;Lscala/util/parsing/combinator/Parsers$Parser;Lscala/util/parsing/combinator/PackratParsers$PackratReader;Lscala/util/parsing/combinator/PackratParsers$Head;)Lscala/util/parsing/combinator/Parsers$ParseResult;;
Asciz	scala/util/parsing/combinator/PackratParsers$PackratReader;
class	scala/util/parsing/combinator/PackratParsers$PackratReader
Asciz	scala$util$parsing$combinator$PackratParsers$$recursionHeads;
Asciz	()Lscala/collection/mutable/HashMap;;
NameAndType	scala$util$parsing$combinator$PackratParsers$$recursionHeads:()Lscala/collection/mutable/HashMap;
Method	scala/util/parsing/combinator/PackratParsers$PackratReader.scala$util$parsing$combinator$PackratParsers$$recursionHeads:()Lscala/collection/mutable/HashMap;
Asciz	pos;
Asciz	()Lscala/util/parsing/input/Position;;
NameAndType	pos:()Lscala/util/parsing/input/Position;
Method	scala/util/parsing/combinator/PackratParsers$PackratReader.pos:()Lscala/util/parsing/input/Position;
Asciz	scala/collection/mutable/HashMap;
class	scala/collection/mutable/HashMap
Asciz	put;
Asciz	(Ljava/lang/Object;Ljava/lang/Object;)Lscala/Option;;
NameAndType	put:(Ljava/lang/Object;Ljava/lang/Object;)Lscala/Option;
Method	scala/collection/mutable/HashMap.put:(Ljava/lang/Object;Ljava/lang/Object;)Lscala/Option;
Asciz	scala$util$parsing$combinator$PackratParsers$$getFromCache;
Asciz	(Lscala/util/parsing/combinator/Parsers$Parser;)Lscala/Option;;
NameAndType	scala$util$parsing$combinator$PackratParsers$$getFromCache:(Lscala/util/parsing/combinator/Parsers$Parser;)Lscala/Option;
Method	scala/util/parsing/combinator/PackratParsers$PackratReader.scala$util$parsing$combinator$PackratParsers$$getFromCache:(Lscala/util/parsing/combinator/Parsers$Parser;)Lscala/Option;
Asciz	scala/Option;
class	scala/Option
Asciz	get;
NameAndType	get:()Ljava/lang/Object;
Method	scala/Option.get:()Ljava/lang/Object;
Asciz	scala/util/parsing/combinator/PackratParsers$MemoEntry;
class	scala/util/parsing/combinator/PackratParsers$MemoEntry
Asciz	r;
Asciz	()Lscala/Either;;
NameAndType	r:()Lscala/Either;
Method	scala/util/parsing/combinator/PackratParsers$MemoEntry.r:()Lscala/Either;
Asciz	scala/Right;
class	scala/Right
Asciz	b;
NameAndType	b:Ljava/lang/Object;
Field	scala/Right.b:Ljava/lang/Object;
Asciz	scala/util/parsing/combinator/Parsers$ParseResult;
class	scala/util/parsing/combinator/Parsers$ParseResult
Asciz	scala/util/parsing/combinator/PackratParsers$Head;
class	scala/util/parsing/combinator/PackratParsers$Head
Asciz	involvedSet;
Asciz	()Lscala/collection/immutable/List;;
NameAndType	involvedSet:()Lscala/collection/immutable/List;
Method	scala/util/parsing/combinator/PackratParsers$Head.involvedSet:()Lscala/collection/immutable/List;
Asciz	evalSet_$eq;
Asciz	(Lscala/collection/immutable/List;)V;
NameAndType	evalSet_$eq:(Lscala/collection/immutable/List;)V
Method	scala/util/parsing/combinator/PackratParsers$Head.evalSet_$eq:(Lscala/collection/immutable/List;)V
Asciz	(Lscala/util/parsing/input/Reader;)Lscala/util/parsing/combinator/Parsers$ParseResult;;
NameAndType	apply:(Lscala/util/parsing/input/Reader;)Lscala/util/parsing/combinator/Parsers$ParseResult;
Method	scala/util/parsing/combinator/Parsers$Parser.apply:(Lscala/util/parsing/input/Reader;)Lscala/util/parsing/combinator/Parsers$ParseResult;
Asciz	scala/util/parsing/combinator/Parsers$Success;
class	scala/util/parsing/combinator/Parsers$Success
Asciz	scala/util/parsing/combinator/PackratParsers$class;
class	scala/util/parsing/combinator/PackratParsers$class
Asciz	scala$util$parsing$combinator$PackratParsers$$getPosFromResult;
Asciz	(Lscala/util/parsing/combinator/PackratParsers;Lscala/util/parsing/combinator/Parsers$ParseResult;)Lscala/util/parsing/input/Position;;
NameAndType	scala$util$parsing$combinator$PackratParsers$$getPosFromResult:(Lscala/util/parsing/combinator/PackratParsers;Lscala/util/parsing/combinator/Parsers$ParseResult;)Lscala/util/parsing/input/Position;
Method	scala/util/parsing/combinator/PackratParsers$class.scala$util$parsing$combinator$PackratParsers$$getPosFromResult:(Lscala/util/parsing/combinator/PackratParsers;Lscala/util/parsing/combinator/Parsers$ParseResult;)Lscala/util/parsing/input/Position;
Asciz	scala/util/parsing/input/Position;
class	scala/util/parsing/input/Position
Asciz	$less;
Asciz	(Lscala/util/parsing/input/Position;)Z;
NameAndType	$less:(Lscala/util/parsing/input/Position;)Z
InterfaceMethod	scala/util/parsing/input/Position.$less:(Lscala/util/parsing/input/Position;)Z
Asciz	<init>;
Asciz	(Ljava/lang/Object;)V;
NameAndType	"<init>":(Ljava/lang/Object;)V
Method	scala/Right."<init>":(Ljava/lang/Object;)V
Asciz	(Lscala/util/parsing/combinator/PackratParsers;Lscala/Either;)V;
NameAndType	"<init>":(Lscala/util/parsing/combinator/PackratParsers;Lscala/Either;)V
Method	scala/util/parsing/combinator/PackratParsers$MemoEntry."<init>":(Lscala/util/parsing/combinator/PackratParsers;Lscala/Either;)V
Asciz	scala$util$parsing$combinator$PackratParsers$$updateCacheAndGet;
Asciz	(Lscala/util/parsing/combinator/Parsers$Parser;Lscala/util/parsing/combinator/PackratParsers$MemoEntry;)Lscala/util/parsing/combinator/PackratParsers$MemoEntry;;
NameAndType	scala$util$parsing$combinator$PackratParsers$$updateCacheAndGet:(Lscala/util/parsing/combinator/Parsers$Parser;Lscala/util/parsing/combinator/PackratParsers$MemoEntry;)Lscala/util/parsing/combinator/PackratParsers$MemoEntry;
Method	scala/util/parsing/combinator/PackratParsers$PackratReader.scala$util$parsing$combinator$PackratParsers$$updateCacheAndGet:(Lscala/util/parsing/combinator/Parsers$Parser;Lscala/util/parsing/combinator/PackratParsers$MemoEntry;)Lscala/util/parsing/combinator/PackratParsers$MemoEntry;
Asciz	$minus$eq;
Asciz	(Ljava/lang/Object;)Lscala/collection/mutable/HashMap;;
NameAndType	$minus$eq:(Ljava/lang/Object;)Lscala/collection/mutable/HashMap;
Method	scala/collection/mutable/HashMap.$minus$eq:(Ljava/lang/Object;)Lscala/collection/mutable/HashMap;
Asciz	scala/MatchError;
class	scala/MatchError
Asciz	toString;
Asciz	()Ljava/lang/String;;
NameAndType	toString:()Ljava/lang/String;
Method	scala/util/parsing/combinator/PackratParsers$MemoEntry.toString:()Ljava/lang/String;
Asciz	(Ljava/lang/String;)V;
NameAndType	"<init>":(Ljava/lang/String;)V
Method	scala/MatchError."<init>":(Ljava/lang/String;)V
Asciz	java/lang/Exception;
class	java/lang/Exception
Asciz	impossible match;
String	impossible match
Method	java/lang/Exception."<init>":(Ljava/lang/String;)V
Method	scala/util/parsing/combinator/Parsers$ParseResult.toString:()Ljava/lang/String;
Asciz	p;
Asciz	Lscala/util/parsing/combinator/Parsers$Parser;;
Asciz	rest;
Asciz	Lscala/util/parsing/combinator/PackratParsers$PackratReader;;
Asciz	head;
Asciz	Lscala/util/parsing/combinator/PackratParsers$Head;;
Asciz	temp69;
Asciz	Lscala/Either;;
Asciz	temp70;
Asciz	Lscala/Right;;
Asciz	temp77;
Asciz	Lscala/util/parsing/combinator/Parsers$Success;;
Asciz	temp73;
Asciz	temp74;
Asciz	temp75;
Asciz	Lscala/util/parsing/combinator/Parsers$ParseResult;;
Asciz	temp72;
Asciz	Lscala/util/parsing/combinator/PackratParsers$MemoEntry;;
Asciz	temp71;
Asciz	tempRes;
Asciz	temp68;
Asciz	memo;
Asciz	(Lscala/util/parsing/combinator/PackratParsers;Lscala/util/parsing/combinator/Parsers$Parser;)Lscala/util/parsing/combinator/PackratParsers$PackratParser;;
Asciz	scala/util/parsing/combinator/PackratParsers$$anon$2;
class	scala/util/parsing/combinator/PackratParsers$$anon$2
Asciz	(Lscala/util/parsing/combinator/PackratParsers;Lscala/util/parsing/combinator/Parsers$Parser;)V;
NameAndType	"<init>":(Lscala/util/parsing/combinator/PackratParsers;Lscala/util/parsing/combinator/Parsers$Parser;)V
Method	scala/util/parsing/combinator/PackratParsers$$anon$2."<init>":(Lscala/util/parsing/combinator/PackratParsers;Lscala/util/parsing/combinator/Parsers$Parser;)V
Asciz	p$2;
Asciz	scala$util$parsing$combinator$PackratParsers$$lrAnswer;
Asciz	(Lscala/util/parsing/combinator/PackratParsers;Lscala/util/parsing/combinator/Parsers$Parser;Lscala/util/parsing/combinator/PackratParsers$PackratReader;Lscala/util/parsing/combinator/PackratParsers$LR;)Lscala/util/parsing/combinator/Parsers$ParseResult;;
Asciz	scala/util/parsing/combinator/PackratParsers$LR;
class	scala/util/parsing/combinator/PackratParsers$LR
Asciz	seed;
Asciz	()Lscala/util/parsing/combinator/Parsers$ParseResult;;
NameAndType	seed:()Lscala/util/parsing/combinator/Parsers$ParseResult;
Method	scala/util/parsing/combinator/PackratParsers$LR.seed:()Lscala/util/parsing/combinator/Parsers$ParseResult;
Asciz	()Lscala/Option;;
NameAndType	head:()Lscala/Option;
Method	scala/util/parsing/combinator/PackratParsers$LR.head:()Lscala/Option;
Asciz	scala/Some;
class	scala/Some
Asciz	x;
NameAndType	x:Ljava/lang/Object;
Field	scala/Some.x:Ljava/lang/Object;
Asciz	getHead;
Asciz	()Lscala/util/parsing/combinator/Parsers$Parser;;
NameAndType	getHead:()Lscala/util/parsing/combinator/Parsers$Parser;
Method	scala/util/parsing/combinator/PackratParsers$Head.getHead:()Lscala/util/parsing/combinator/Parsers$Parser;
Asciz	java/lang/Object;
class	java/lang/Object
Asciz	equals;
Asciz	(Ljava/lang/Object;)Z;
NameAndType	equals:(Ljava/lang/Object;)Z
Method	java/lang/Object.equals:(Ljava/lang/Object;)Z
Asciz	scala/util/parsing/combinator/Parsers$Failure;
class	scala/util/parsing/combinator/Parsers$Failure
Asciz	scala/util/parsing/combinator/Parsers$Error;
class	scala/util/parsing/combinator/Parsers$Error
NameAndType	grow:(Lscala/util/parsing/combinator/PackratParsers;Lscala/util/parsing/combinator/Parsers$Parser;Lscala/util/parsing/combinator/PackratParsers$PackratReader;Lscala/util/parsing/combinator/PackratParsers$Head;)Lscala/util/parsing/combinator/Parsers$ParseResult;
Method	scala/util/parsing/combinator/PackratParsers$class.grow:(Lscala/util/parsing/combinator/PackratParsers;Lscala/util/parsing/combinator/Parsers$Parser;Lscala/util/parsing/combinator/PackratParsers$PackratReader;Lscala/util/parsing/combinator/PackratParsers$Head;)Lscala/util/parsing/combinator/Parsers$ParseResult;
Method	scala/util/parsing/combinator/PackratParsers$LR.toString:()Ljava/lang/String;
Asciz	lrAnswer with no head !!;
String	lrAnswer with no head !!
Asciz	in;
Asciz	growable;
Asciz	Lscala/util/parsing/combinator/PackratParsers$LR;;
Asciz	temp47;
Asciz	Lscala/Option;;
Asciz	temp48;
Asciz	Lscala/Some;;
Asciz	temp35;
Asciz	Lscala/util/parsing/combinator/Parsers$Failure;;
Asciz	temp38;
Asciz	Lscala/util/parsing/combinator/Parsers$Error;;
Asciz	temp49;
Asciz	temp45;
Asciz	scala$util$parsing$combinator$PackratParsers$$setupLR;
Asciz	(Lscala/util/parsing/combinator/PackratParsers;Lscala/util/parsing/combinator/Parsers$Parser;Lscala/util/parsing/combinator/PackratParsers$PackratReader;Lscala/util/parsing/combinator/PackratParsers$LR;)V;
Asciz	scala/None$;
class	scala/None$
Asciz	MODULE$;
Asciz	Lscala/None$;;
NameAndType	MODULE$:Lscala/None$;
Field	scala/None$.MODULE$:Lscala/None$;
Asciz	scala/collection/immutable/Nil$;
class	scala/collection/immutable/Nil$
Asciz	Lscala/collection/immutable/Nil$;;
NameAndType	MODULE$:Lscala/collection/immutable/Nil$;
Field	scala/collection/immutable/Nil$.MODULE$:Lscala/collection/immutable/Nil$;
Asciz	(Lscala/util/parsing/combinator/PackratParsers;Lscala/util/parsing/combinator/Parsers$Parser;Lscala/collection/immutable/List;Lscala/collection/immutable/List;)V;
NameAndType	"<init>":(Lscala/util/parsing/combinator/PackratParsers;Lscala/util/parsing/combinator/Parsers$Parser;Lscala/collection/immutable/List;Lscala/collection/immutable/List;)V
Method	scala/util/parsing/combinator/PackratParsers$Head."<init>":(Lscala/util/parsing/combinator/PackratParsers;Lscala/util/parsing/combinator/Parsers$Parser;Lscala/collection/immutable/List;Lscala/collection/immutable/List;)V
Method	scala/Some."<init>":(Ljava/lang/Object;)V
Asciz	head_$eq;
Asciz	(Lscala/Option;)V;
NameAndType	head_$eq:(Lscala/Option;)V
Method	scala/util/parsing/combinator/PackratParsers$LR.head_$eq:(Lscala/Option;)V
Asciz	scala$util$parsing$combinator$PackratParsers$$lrStack;
NameAndType	scala$util$parsing$combinator$PackratParsers$$lrStack:()Lscala/collection/immutable/List;
Method	scala/util/parsing/combinator/PackratParsers$PackratReader.scala$util$parsing$combinator$PackratParsers$$lrStack:()Lscala/collection/immutable/List;
Asciz	scala/util/parsing/combinator/PackratParsers$$anonfun$scala$util$parsing$combinator$PackratParsers$$setupLR$1;
class	scala/util/parsing/combinator/PackratParsers$$anonfun$scala$util$parsing$combinator$PackratParsers$$setupLR$1
Method	scala/util/parsing/combinator/PackratParsers$$anonfun$scala$util$parsing$combinator$PackratParsers$$setupLR$1."<init>":(Lscala/util/parsing/combinator/PackratParsers;Lscala/util/parsing/combinator/Parsers$Parser;)V
Asciz	scala/collection/immutable/List;
class	scala/collection/immutable/List
Asciz	takeWhile;
Asciz	(Lscala/Function1;)Lscala/collection/immutable/List;;
NameAndType	takeWhile:(Lscala/Function1;)Lscala/collection/immutable/List;
Method	scala/collection/immutable/List.takeWhile:(Lscala/Function1;)Lscala/collection/immutable/List;
Asciz	scala/util/parsing/combinator/PackratParsers$$anonfun$scala$util$parsing$combinator$PackratParsers$$setupLR$2;
class	scala/util/parsing/combinator/PackratParsers$$anonfun$scala$util$parsing$combinator$PackratParsers$$setupLR$2
Asciz	(Lscala/util/parsing/combinator/PackratParsers;Lscala/util/parsing/combinator/PackratParsers$LR;)V;
NameAndType	"<init>":(Lscala/util/parsing/combinator/PackratParsers;Lscala/util/parsing/combinator/PackratParsers$LR;)V
Method	scala/util/parsing/combinator/PackratParsers$$anonfun$scala$util$parsing$combinator$PackratParsers$$setupLR$2."<init>":(Lscala/util/parsing/combinator/PackratParsers;Lscala/util/parsing/combinator/PackratParsers$LR;)V
Asciz	scala/collection/LinearSeqLike;
class	scala/collection/LinearSeqLike
Asciz	foreach;
Asciz	(Lscala/Function1;)V;
NameAndType	foreach:(Lscala/Function1;)V
InterfaceMethod	scala/collection/LinearSeqLike.foreach:(Lscala/Function1;)V
Asciz	p$4;
Asciz	recDetect$1;
Asciz	scala$util$parsing$combinator$PackratParsers$$recall;
Asciz	(Lscala/util/parsing/combinator/PackratParsers;Lscala/util/parsing/combinator/Parsers$Parser;Lscala/util/parsing/combinator/PackratParsers$PackratReader;)Lscala/Option;;
Asciz	(Ljava/lang/Object;)Lscala/Option;;
NameAndType	get:(Ljava/lang/Object;)Lscala/Option;
Method	scala/collection/mutable/HashMap.get:(Ljava/lang/Object;)Lscala/Option;
Method	scala/Option.toString:()Ljava/lang/String;
Asciz	headParser;
NameAndType	headParser:()Lscala/util/parsing/combinator/Parsers$Parser;
Method	scala/util/parsing/combinator/PackratParsers$Head.headParser:()Lscala/util/parsing/combinator/Parsers$Parser;
Asciz	evalSet;
NameAndType	evalSet:()Lscala/collection/immutable/List;
Method	scala/util/parsing/combinator/PackratParsers$Head.evalSet:()Lscala/collection/immutable/List;
Asciz	$colon$colon;
Asciz	(Ljava/lang/Object;)Lscala/collection/immutable/List;;
NameAndType	$colon$colon:(Ljava/lang/Object;)Lscala/collection/immutable/List;
Method	scala/collection/immutable/List.$colon$colon:(Ljava/lang/Object;)Lscala/collection/immutable/List;
Asciz	scala/collection/SeqLike;
class	scala/collection/SeqLike
Asciz	contains;
NameAndType	contains:(Ljava/lang/Object;)Z
InterfaceMethod	scala/collection/SeqLike.contains:(Ljava/lang/Object;)Z
Asciz	dummy ;
String	dummy 
Asciz	(Lscala/util/parsing/combinator/Parsers;Ljava/lang/String;Lscala/util/parsing/input/Reader;)V;
NameAndType	"<init>":(Lscala/util/parsing/combinator/Parsers;Ljava/lang/String;Lscala/util/parsing/input/Reader;)V
Method	scala/util/parsing/combinator/Parsers$Failure."<init>":(Lscala/util/parsing/combinator/Parsers;Ljava/lang/String;Lscala/util/parsing/input/Reader;)V
Asciz	scala/util/parsing/combinator/PackratParsers$$anonfun$scala$util$parsing$combinator$PackratParsers$$recall$1;
class	scala/util/parsing/combinator/PackratParsers$$anonfun$scala$util$parsing$combinator$PackratParsers$$recall$1
Method	scala/util/parsing/combinator/PackratParsers$$anonfun$scala$util$parsing$combinator$PackratParsers$$recall$1."<init>":(Lscala/util/parsing/combinator/PackratParsers;Lscala/util/parsing/combinator/Parsers$Parser;)V
Asciz	scala/collection/TraversableLike;
class	scala/collection/TraversableLike
Asciz	filterNot;
Asciz	(Lscala/Function1;)Ljava/lang/Object;;
NameAndType	filterNot:(Lscala/Function1;)Ljava/lang/Object;
InterfaceMethod	scala/collection/TraversableLike.filterNot:(Lscala/Function1;)Ljava/lang/Object;
Asciz	r_$eq;
Asciz	(Lscala/Either;)V;
NameAndType	r_$eq:(Lscala/Either;)V
Method	scala/util/parsing/combinator/PackratParsers$MemoEntry.r_$eq:(Lscala/Either;)V
Asciz	p$3;
Asciz	temp29;
Asciz	temp32;
Asciz	Lscala/collection/immutable/List;;
Asciz	temp31;
Asciz	temp33;
Asciz	temp30;
Asciz	tempEntry;
Asciz	cached;
Asciz	parser2packrat;
Asciz	(Lscala/util/parsing/combinator/PackratParsers;Lscala/Function0;)Lscala/util/parsing/combinator/PackratParsers$PackratParser;;
Asciz	(I)V;
NameAndType	"<init>":(I)V
Method	scala/runtime/IntRef."<init>":(I)V
Method	scala/runtime/ObjectRef."<init>":(Ljava/lang/Object;)V
Asciz	scala/util/parsing/combinator/PackratParsers$$anonfun$parser2packrat$1;
class	scala/util/parsing/combinator/PackratParsers$$anonfun$parser2packrat$1
Asciz	(Lscala/util/parsing/combinator/PackratParsers;Lscala/Function0;Lscala/runtime/ObjectRef;Lscala/runtime/IntRef;)V;
NameAndType	"<init>":(Lscala/util/parsing/combinator/PackratParsers;Lscala/Function0;Lscala/runtime/ObjectRef;Lscala/runtime/IntRef;)V
Method	scala/util/parsing/combinator/PackratParsers$$anonfun$parser2packrat$1."<init>":(Lscala/util/parsing/combinator/PackratParsers;Lscala/Function0;Lscala/runtime/ObjectRef;Lscala/runtime/IntRef;)V
Asciz	scala/util/parsing/combinator/PackratParsers;
class	scala/util/parsing/combinator/PackratParsers
Asciz	scala$util$parsing$combinator$PackratParsers$$super$Parser;
Asciz	(Lscala/Function1;)Lscala/util/parsing/combinator/Parsers$Parser;;
NameAndType	scala$util$parsing$combinator$PackratParsers$$super$Parser:(Lscala/Function1;)Lscala/util/parsing/combinator/Parsers$Parser;
InterfaceMethod	scala/util/parsing/combinator/PackratParsers.scala$util$parsing$combinator$PackratParsers$$super$Parser:(Lscala/Function1;)Lscala/util/parsing/combinator/Parsers$Parser;
Asciz	(Lscala/util/parsing/combinator/Parsers$Parser;)Lscala/util/parsing/combinator/PackratParsers$PackratParser;;
NameAndType	memo:(Lscala/util/parsing/combinator/Parsers$Parser;)Lscala/util/parsing/combinator/PackratParsers$PackratParser;
InterfaceMethod	scala/util/parsing/combinator/PackratParsers.memo:(Lscala/util/parsing/combinator/Parsers$Parser;)Lscala/util/parsing/combinator/PackratParsers$PackratParser;
Asciz	p$1;
Asciz	Lscala/Function0;;
Asciz	bitmap$0$1;
Asciz	Lscala/runtime/IntRef;;
Asciz	q$lzy$1;
Asciz	Lscala/runtime/ObjectRef;;
Asciz	next;
Asciz	()Lscala/util/parsing/input/Reader;;
NameAndType	next:()Lscala/util/parsing/input/Reader;
Method	scala/util/parsing/combinator/Parsers$ParseResult.next:()Lscala/util/parsing/input/Reader;
Asciz	scala/util/parsing/input/Reader;
class	scala/util/parsing/input/Reader
Method	scala/util/parsing/input/Reader.pos:()Lscala/util/parsing/input/Position;
Asciz	phrase;
Asciz	scala$util$parsing$combinator$PackratParsers$$super$phrase;
Asciz	(Lscala/util/parsing/combinator/Parsers$Parser;)Lscala/util/parsing/combinator/Parsers$Parser;;
NameAndType	scala$util$parsing$combinator$PackratParsers$$super$phrase:(Lscala/util/parsing/combinator/Parsers$Parser;)Lscala/util/parsing/combinator/Parsers$Parser;
InterfaceMethod	scala/util/parsing/combinator/PackratParsers.scala$util$parsing$combinator$PackratParsers$$super$phrase:(Lscala/util/parsing/combinator/Parsers$Parser;)Lscala/util/parsing/combinator/Parsers$Parser;
Asciz	scala/util/parsing/combinator/PackratParsers$$anon$1;
class	scala/util/parsing/combinator/PackratParsers$$anon$1
Method	scala/util/parsing/combinator/PackratParsers$$anon$1."<init>":(Lscala/util/parsing/combinator/PackratParsers;Lscala/util/parsing/combinator/Parsers$Parser;)V
Asciz	q$1;
Asciz	Scala;
Asciz	InnerClasses;
Asciz	scala/util/parsing/combinator/Parsers;
class	scala/util/parsing/combinator/Parsers
Asciz	Error;
Asciz	Parser;
Asciz	Failure;
Asciz	Success;
Asciz	LR;
Asciz	Head;
Asciz	ParseResult;
Asciz	$anon$1;
Asciz	$anon$2;
Asciz	MemoEntry;
Asciz	scala/util/parsing/combinator/PackratParsers$PackratParser;
class	scala/util/parsing/combinator/PackratParsers$PackratParser
Asciz	PackratParser;
Asciz	PackratReader;
Asciz	$anonfun$parser2packrat$1;
Asciz	$anonfun$scala$util$parsing$combinator$PackratParsers$$recall$1;
Asciz	$anonfun$scala$util$parsing$combinator$PackratParsers$$setupLR$2;
Asciz	$anonfun$scala$util$parsing$combinator$PackratParsers$$setupLR$1;

{
public static void $init$(scala.util.parsing.combinator.PackratParsers);
  Signature: (Lscala/util/parsing/combinator/PackratParsers;)V
  Code:
   Stack=0, Locals=1, Args_size=1
	return
  Labels:
  LocalVariableTable: 
   Start  Length  Slot  Name   Signature
   0      1      0    $this       Lscala/util/parsing/combinator/PackratParsers;


public static final scala.util.parsing.combinator.Parsers$Parser q$2(scala.util.parsing.combinator.PackratParsers, scala.Function0, scala.runtime.ObjectRef, scala.runtime.IntRef);
  Signature: (Lscala/util/parsing/combinator/PackratParsers;Lscala/Function0;Lscala/runtime/ObjectRef;Lscala/runtime/IntRef;)Lscala/util/parsing/combinator/Parsers$Parser;
  Code:
   Stack=3, Locals=4, Args_size=4
	aload_3
	getfield	Field scala/runtime/IntRef.elem:I
	iconst_1
	iand
	iconst_0
	if_icmpne	l1 // aload_2
	aload_2
	aload_1
	invokeinterface	InterfaceMethod scala/Function0.apply:()Ljava/lang/Object;
	checkcast	class scala/util/parsing/combinator/Parsers$Parser
	putfield	Field scala/runtime/ObjectRef.elem:Ljava/lang/Object;
	aload_3
	aload_3
	getfield	Field scala/runtime/IntRef.elem:I
	iconst_1
	ior
	putfield	Field scala/runtime/IntRef.elem:I
l1	aload_2
	getfield	Field scala/runtime/ObjectRef.elem:Ljava/lang/Object;
	checkcast	class scala/util/parsing/combinator/Parsers$Parser
	areturn
  Labels:
   	l1 = 33 // aload_2
  LocalVariableTable: 
   Start  Length  Slot  Name   Signature
   0      41      0    $this       Lscala/util/parsing/combinator/PackratParsers;


private static scala.util.parsing.combinator.Parsers$ParseResult grow(scala.util.parsing.combinator.PackratParsers, scala.util.parsing.combinator.Parsers$Parser, scala.util.parsing.combinator.PackratParsers$PackratReader, scala.util.parsing.combinator.PackratParsers$Head);
  Signature: (Lscala/util/parsing/combinator/PackratParsers;Lscala/util/parsing/combinator/Parsers$Parser;Lscala/util/parsing/combinator/PackratParsers$PackratReader;Lscala/util/parsing/combinator/PackratParsers$Head;)Lscala/util/parsing/combinator/Parsers$ParseResult;
  Code:
   Stack=8, Locals=14, Args_size=4
l7	aload_2
	invokevirtual	Method scala/util/parsing/combinator/PackratParsers$PackratReader.scala$util$parsing$combinator$PackratParsers$$recursionHeads:()Lscala/collection/mutable/HashMap;
	aload_2
	invokevirtual	Method scala/util/parsing/combinator/PackratParsers$PackratReader.pos:()Lscala/util/parsing/input/Position;
	aload_3
	invokevirtual	Method scala/collection/mutable/HashMap.put:(Ljava/lang/Object;Ljava/lang/Object;)Lscala/Option;
	pop
	aload_2
	aload_1
	invokevirtual	Method scala/util/parsing/combinator/PackratParsers$PackratReader.scala$util$parsing$combinator$PackratParsers$$getFromCache:(Lscala/util/parsing/combinator/Parsers$Parser;)Lscala/Option;
	invokevirtual	Method scala/Option.get:()Ljava/lang/Object;
	checkcast	class scala/util/parsing/combinator/PackratParsers$MemoEntry
	astore	13
	aload	13
	ifnull	l1 // iconst_1
	aload	13
	invokevirtual	Method scala/util/parsing/combinator/PackratParsers$MemoEntry.r:()Lscala/Either;
	astore	4
	aload	4
	instanceof	class scala/Right
	ifeq	l2 // iconst_1
	aload	4
	checkcast	class scala/Right
	astore	5
	aload	5
	getfield	Field scala/Right.b:Ljava/lang/Object;
	checkcast	class scala/util/parsing/combinator/Parsers$ParseResult
	astore	11
	iconst_1
	ifeq	l3 // new
	aload_3
	aload_3
	invokevirtual	Method scala/util/parsing/combinator/PackratParsers$Head.involvedSet:()Lscala/collection/immutable/List;
	invokevirtual	Method scala/util/parsing/combinator/PackratParsers$Head.evalSet_$eq:(Lscala/collection/immutable/List;)V
	aload_1
	aload_2
	invokevirtual	Method scala/util/parsing/combinator/Parsers$Parser.apply:(Lscala/util/parsing/input/Reader;)Lscala/util/parsing/combinator/Parsers$ParseResult;
	astore	12
	aload	12
	instanceof	class scala/util/parsing/combinator/Parsers$Success
	ifeq	l4 // iconst_1
	aload	12
	checkcast	class scala/util/parsing/combinator/Parsers$Success
	astore	6
	iconst_1
	ifeq	l5 // new
	aload_0
	aload	11
	invokestatic	Method scala$util$parsing$combinator$PackratParsers$$getPosFromResult:(Lscala/util/parsing/combinator/PackratParsers;Lscala/util/parsing/combinator/Parsers$ParseResult;)Lscala/util/parsing/input/Position;
	aload_0
	aload	12
	invokestatic	Method scala$util$parsing$combinator$PackratParsers$$getPosFromResult:(Lscala/util/parsing/combinator/PackratParsers;Lscala/util/parsing/combinator/Parsers$ParseResult;)Lscala/util/parsing/input/Position;
	invokeinterface	InterfaceMethod scala/util/parsing/input/Position.$less:(Lscala/util/parsing/input/Position;)Z
	ifeq	l6 // aload_2
	aload_2
	aload_1
	new	class scala/util/parsing/combinator/PackratParsers$MemoEntry
	dup
	aload_0
	new	class scala/Right
	dup
	aload	6
	invokespecial	Method scala/Right."<init>":(Ljava/lang/Object;)V
	invokespecial	Method scala/util/parsing/combinator/PackratParsers$MemoEntry."<init>":(Lscala/util/parsing/combinator/PackratParsers;Lscala/Either;)V
	invokevirtual	Method scala/util/parsing/combinator/PackratParsers$PackratReader.scala$util$parsing$combinator$PackratParsers$$updateCacheAndGet:(Lscala/util/parsing/combinator/Parsers$Parser;Lscala/util/parsing/combinator/PackratParsers$MemoEntry;)Lscala/util/parsing/combinator/PackratParsers$MemoEntry;
	pop
	aload_0
	astore_0
	goto	l7 // aload_2
l6	aload_2
	invokevirtual	Method scala/util/parsing/combinator/PackratParsers$PackratReader.scala$util$parsing$combinator$PackratParsers$$recursionHeads:()Lscala/collection/mutable/HashMap;
	aload_2
	invokevirtual	Method scala/util/parsing/combinator/PackratParsers$PackratReader.pos:()Lscala/util/parsing/input/Position;
	invokevirtual	Method scala/collection/mutable/HashMap.$minus$eq:(Ljava/lang/Object;)Lscala/collection/mutable/HashMap;
	pop
	aload_2
	aload_1
	invokevirtual	Method scala/util/parsing/combinator/PackratParsers$PackratReader.scala$util$parsing$combinator$PackratParsers$$getFromCache:(Lscala/util/parsing/combinator/Parsers$Parser;)Lscala/Option;
	invokevirtual	Method scala/Option.get:()Ljava/lang/Object;
	checkcast	class scala/util/parsing/combinator/PackratParsers$MemoEntry
	astore	10
	aload	10
	ifnull	l8 // iconst_1
	aload	10
	invokevirtual	Method scala/util/parsing/combinator/PackratParsers$MemoEntry.r:()Lscala/Either;
	astore	7
	aload	7
	instanceof	class scala/Right
	ifeq	l9 // iconst_1
	aload	7
	checkcast	class scala/Right
	astore	8
	aload	8
	getfield	Field scala/Right.b:Ljava/lang/Object;
	checkcast	class scala/util/parsing/combinator/Parsers$ParseResult
	astore	9
	aload	9
	ifnull	l10 // iconst_1
	iconst_1
	ifeq	l11 // new
	aload	9
	goto	l12 // areturn
l11	new	class scala/MatchError
	dup
	aload	10
	invokevirtual	Method scala/util/parsing/combinator/PackratParsers$MemoEntry.toString:()Ljava/lang/String;
	invokespecial	Method scala/MatchError."<init>":(Ljava/lang/String;)V
	athrow
l10	iconst_1
	ifeq	l13 // new
	new	class java/lang/Exception
	dup
	ldc	String impossible match
	invokespecial	Method java/lang/Exception."<init>":(Ljava/lang/String;)V
	athrow
l13	new	class scala/MatchError
	dup
	aload	10
	invokevirtual	Method scala/util/parsing/combinator/PackratParsers$MemoEntry.toString:()Ljava/lang/String;
	invokespecial	Method scala/MatchError."<init>":(Ljava/lang/String;)V
	athrow
l9	iconst_1
	ifeq	l14 // new
	new	class java/lang/Exception
	dup
	ldc	String impossible match
	invokespecial	Method java/lang/Exception."<init>":(Ljava/lang/String;)V
	athrow
l14	new	class scala/MatchError
	dup
	aload	10
	invokevirtual	Method scala/util/parsing/combinator/PackratParsers$MemoEntry.toString:()Ljava/lang/String;
	invokespecial	Method scala/MatchError."<init>":(Ljava/lang/String;)V
	athrow
l8	iconst_1
	ifeq	l15 // new
	new	class java/lang/Exception
	dup
	ldc	String impossible match
	invokespecial	Method java/lang/Exception."<init>":(Ljava/lang/String;)V
	athrow
l15	new	class scala/MatchError
	dup
	aload	10
	invokevirtual	Method scala/util/parsing/combinator/PackratParsers$MemoEntry.toString:()Ljava/lang/String;
	invokespecial	Method scala/MatchError."<init>":(Ljava/lang/String;)V
	athrow
l5	new	class scala/MatchError
	dup
	aload	12
	invokevirtual	Method scala/util/parsing/combinator/Parsers$ParseResult.toString:()Ljava/lang/String;
	invokespecial	Method scala/MatchError."<init>":(Ljava/lang/String;)V
	athrow
l4	iconst_1
	ifeq	l16 // new
	aload_2
	invokevirtual	Method scala/util/parsing/combinator/PackratParsers$PackratReader.scala$util$parsing$combinator$PackratParsers$$recursionHeads:()Lscala/collection/mutable/HashMap;
	aload_2
	invokevirtual	Method scala/util/parsing/combinator/PackratParsers$PackratReader.pos:()Lscala/util/parsing/input/Position;
	invokevirtual	Method scala/collection/mutable/HashMap.$minus$eq:(Ljava/lang/Object;)Lscala/collection/mutable/HashMap;
	pop
	aload	11
l12	areturn
l16	new	class scala/MatchError
	dup
	aload	12
	invokevirtual	Method scala/util/parsing/combinator/Parsers$ParseResult.toString:()Ljava/lang/String;
	invokespecial	Method scala/MatchError."<init>":(Ljava/lang/String;)V
	athrow
l3	new	class scala/MatchError
	dup
	aload	13
	invokevirtual	Method scala/util/parsing/combinator/PackratParsers$MemoEntry.toString:()Ljava/lang/String;
	invokespecial	Method scala/MatchError."<init>":(Ljava/lang/String;)V
	athrow
l2	iconst_1
	ifeq	l17 // new
	new	class java/lang/Exception
	dup
	ldc	String impossible match
	invokespecial	Method java/lang/Exception."<init>":(Ljava/lang/String;)V
	athrow
l17	new	class scala/MatchError
	dup
	aload	13
	invokevirtual	Method scala/util/parsing/combinator/PackratParsers$MemoEntry.toString:()Ljava/lang/String;
	invokespecial	Method scala/MatchError."<init>":(Ljava/lang/String;)V
	athrow
l1	iconst_1
	ifeq	l18 // new
	new	class java/lang/Exception
	dup
	ldc	String impossible match
	invokespecial	Method java/lang/Exception."<init>":(Ljava/lang/String;)V
	athrow
l18	new	class scala/MatchError
	dup
	aload	13
	invokevirtual	Method scala/util/parsing/combinator/PackratParsers$MemoEntry.toString:()Ljava/lang/String;
	invokespecial	Method scala/MatchError."<init>":(Ljava/lang/String;)V
	athrow
  Labels:
   	l7 = 0 // aload_2
   	l6 = 149 // aload_2
   	l11 = 225 // new
   	l10 = 238 // iconst_1
   	l13 = 252 // new
   	l9 = 265 // iconst_1
   	l14 = 279 // new
   	l8 = 292 // iconst_1
   	l15 = 306 // new
   	l5 = 319 // new
   	l4 = 332 // iconst_1
   	l12 = 350 // areturn
   	l16 = 351 // new
   	l3 = 364 // new
   	l2 = 377 // iconst_1
   	l17 = 391 // new
   	l1 = 404 // iconst_1
   	l18 = 418 // new
  LocalVariableTable: 
   Start  Length  Slot  Name   Signature
   0      431      0    $this       Lscala/util/parsing/combinator/PackratParsers;
   0      431      1    p       Lscala/util/parsing/combinator/Parsers$Parser;
   0      431      2    rest       Lscala/util/parsing/combinator/PackratParsers$PackratReader;
   0      431      3    head       Lscala/util/parsing/combinator/PackratParsers$Head;
   38      52      4    temp69       Lscala/Either;
   364      40      4    temp69       Lscala/Either;
   53      37      5    temp70       Lscala/Right;
   364      13      5    temp70       Lscala/Right;
   97      235      6    temp77       Lscala/util/parsing/combinator/Parsers$Success;
   186      106      7    temp73       Lscala/Either;
   201      64      8    temp74       Lscala/Right;
   211      54      9    temp75       Lscala/util/parsing/combinator/Parsers$ParseResult;
   174      145      10    temp72       Lscala/util/parsing/combinator/PackratParsers$MemoEntry;
   63      27      11    temp71       Lscala/util/parsing/combinator/Parsers$ParseResult;
   364      13      11    temp71       Lscala/util/parsing/combinator/Parsers$ParseResult;
   82      282      12    tempRes       Lscala/util/parsing/combinator/Parsers$ParseResult;
   26      64      13    temp68       Lscala/util/parsing/combinator/PackratParsers$MemoEntry;
   364      67      13    temp68       Lscala/util/parsing/combinator/PackratParsers$MemoEntry;


public static scala.util.parsing.combinator.PackratParsers$PackratParser memo(scala.util.parsing.combinator.PackratParsers, scala.util.parsing.combinator.Parsers$Parser);
  Signature: (Lscala/util/parsing/combinator/PackratParsers;Lscala/util/parsing/combinator/Parsers$Parser;)Lscala/util/parsing/combinator/PackratParsers$PackratParser;
  Code:
   Stack=4, Locals=2, Args_size=2
	new	class scala/util/parsing/combinator/PackratParsers$$anon$2
	dup
	aload_0
	aload_1
	invokespecial	Method scala/util/parsing/combinator/PackratParsers$$anon$2."<init>":(Lscala/util/parsing/combinator/PackratParsers;Lscala/util/parsing/combinator/Parsers$Parser;)V
	areturn
  Labels:
  LocalVariableTable: 
   Start  Length  Slot  Name   Signature
   0      10      0    $this       Lscala/util/parsing/combinator/PackratParsers;
   0      10      1    p$2       Lscala/util/parsing/combinator/Parsers$Parser;


public static final scala.util.parsing.combinator.Parsers$ParseResult scala$util$parsing$combinator$PackratParsers$$lrAnswer(scala.util.parsing.combinator.PackratParsers, scala.util.parsing.combinator.Parsers$Parser, scala.util.parsing.combinator.PackratParsers$PackratReader, scala.util.parsing.combinator.PackratParsers$LR);
  Signature: (Lscala/util/parsing/combinator/PackratParsers;Lscala/util/parsing/combinator/Parsers$Parser;Lscala/util/parsing/combinator/PackratParsers$PackratReader;Lscala/util/parsing/combinator/PackratParsers$LR;)Lscala/util/parsing/combinator/Parsers$ParseResult;
  Code:
   Stack=8, Locals=10, Args_size=4
	aload_3
	ifnull	l1 // iconst_1
	aload_3
	invokevirtual	Method scala/util/parsing/combinator/PackratParsers$LR.seed:()Lscala/util/parsing/combinator/Parsers$ParseResult;
	astore	9
	aload_3
	invokevirtual	Method scala/util/parsing/combinator/PackratParsers$LR.head:()Lscala/Option;
	astore	4
	aload	4
	instanceof	class scala/Some
	ifeq	l2 // iconst_1
	aload	4
	checkcast	class scala/Some
	astore	5
	aload	5
	getfield	Field scala/Some.x:Ljava/lang/Object;
	checkcast	class scala/util/parsing/combinator/PackratParsers$Head
	astore	8
	iconst_1
	ifeq	l3 // new
	aload	8
	invokevirtual	Method scala/util/parsing/combinator/PackratParsers$Head.getHead:()Lscala/util/parsing/combinator/Parsers$Parser;
	dup
	ifnonnull	l4 // aload_1
	pop
	aload_1
	ifnull	l5 // aload_2
	goto	l6 // aload
l4	aload_1
	invokevirtual	Method java/lang/Object.equals:(Ljava/lang/Object;)Z
	ifeq	l6 // aload
l5	aload_2
	aload_1
	new	class scala/util/parsing/combinator/PackratParsers$MemoEntry
	dup
	aload_0
	new	class scala/Right
	dup
	aload	9
	invokespecial	Method scala/Right."<init>":(Ljava/lang/Object;)V
	invokespecial	Method scala/util/parsing/combinator/PackratParsers$MemoEntry."<init>":(Lscala/util/parsing/combinator/PackratParsers;Lscala/Either;)V
	invokevirtual	Method scala/util/parsing/combinator/PackratParsers$PackratReader.scala$util$parsing$combinator$PackratParsers$$updateCacheAndGet:(Lscala/util/parsing/combinator/Parsers$Parser;Lscala/util/parsing/combinator/PackratParsers$MemoEntry;)Lscala/util/parsing/combinator/PackratParsers$MemoEntry;
	pop
	aload	9
	instanceof	class scala/util/parsing/combinator/Parsers$Failure
	ifeq	l7 // aload
	aload	9
	checkcast	class scala/util/parsing/combinator/Parsers$Failure
	astore	6
	iconst_1
	ifeq	l8 // new
	aload	6
	goto	l9 // areturn
l8	new	class scala/MatchError
	dup
	aload	9
	invokevirtual	Method scala/util/parsing/combinator/Parsers$ParseResult.toString:()Ljava/lang/String;
	invokespecial	Method scala/MatchError."<init>":(Ljava/lang/String;)V
	athrow
l7	aload	9
	instanceof	class scala/util/parsing/combinator/Parsers$Error
	ifeq	l10 // aload
	aload	9
	checkcast	class scala/util/parsing/combinator/Parsers$Error
	astore	7
	iconst_1
	ifeq	l11 // new
	aload	7
	goto	l9 // areturn
l11	new	class scala/MatchError
	dup
	aload	9
	invokevirtual	Method scala/util/parsing/combinator/Parsers$ParseResult.toString:()Ljava/lang/String;
	invokespecial	Method scala/MatchError."<init>":(Ljava/lang/String;)V
	athrow
l10	aload	9
	instanceof	class scala/util/parsing/combinator/Parsers$Success
	ifeq	l12 // new
	iconst_1
	ifeq	l13 // new
	aload_0
	aload_1
	aload_2
	aload	8
	invokestatic	Method grow:(Lscala/util/parsing/combinator/PackratParsers;Lscala/util/parsing/combinator/Parsers$Parser;Lscala/util/parsing/combinator/PackratParsers$PackratReader;Lscala/util/parsing/combinator/PackratParsers$Head;)Lscala/util/parsing/combinator/Parsers$ParseResult;
	goto	l9 // areturn
l13	new	class scala/MatchError
	dup
	aload	9
	invokevirtual	Method scala/util/parsing/combinator/Parsers$ParseResult.toString:()Ljava/lang/String;
	invokespecial	Method scala/MatchError."<init>":(Ljava/lang/String;)V
	athrow
l12	new	class scala/MatchError
	dup
	aload	9
	invokevirtual	Method scala/util/parsing/combinator/Parsers$ParseResult.toString:()Ljava/lang/String;
	invokespecial	Method scala/MatchError."<init>":(Ljava/lang/String;)V
	athrow
l6	aload	9
l9	areturn
l3	new	class scala/MatchError
	dup
	aload_3
	invokevirtual	Method scala/util/parsing/combinator/PackratParsers$LR.toString:()Ljava/lang/String;
	invokespecial	Method scala/MatchError."<init>":(Ljava/lang/String;)V
	athrow
l2	iconst_1
	ifeq	l14 // new
	new	class java/lang/Exception
	dup
	ldc	String lrAnswer with no head !!
	invokespecial	Method java/lang/Exception."<init>":(Ljava/lang/String;)V
	athrow
l14	new	class scala/MatchError
	dup
	aload_3
	invokevirtual	Method scala/util/parsing/combinator/PackratParsers$LR.toString:()Ljava/lang/String;
	invokespecial	Method scala/MatchError."<init>":(Ljava/lang/String;)V
	athrow
l1	iconst_1
	ifeq	l15 // new
	new	class java/lang/Exception
	dup
	ldc	String lrAnswer with no head !!
	invokespecial	Method java/lang/Exception."<init>":(Ljava/lang/String;)V
	athrow
l15	new	class scala/MatchError
	dup
	aload_3
	invokevirtual	Method scala/util/parsing/combinator/PackratParsers$LR.toString:()Ljava/lang/String;
	invokespecial	Method scala/MatchError."<init>":(Ljava/lang/String;)V
	athrow
  Labels:
   	l4 = 62 // aload_1
   	l5 = 69 // aload_2
   	l8 = 116 // new
   	l7 = 129 // aload
   	l11 = 153 // new
   	l10 = 166 // aload
   	l13 = 189 // new
   	l12 = 202 // new
   	l6 = 215 // aload
   	l9 = 217 // areturn
   	l3 = 218 // new
   	l2 = 230 // iconst_1
   	l14 = 244 // new
   	l1 = 256 // iconst_1
   	l15 = 270 // new
  LocalVariableTable: 
   Start  Length  Slot  Name   Signature
   0      282      0    $this       Lscala/util/parsing/combinator/PackratParsers;
   0      282      1    p       Lscala/util/parsing/combinator/Parsers$Parser;
   0      282      2    in       Lscala/util/parsing/combinator/PackratParsers$PackratReader;
   0      282      3    growable       Lscala/util/parsing/combinator/PackratParsers$LR;
   16      201      4    temp47       Lscala/Option;
   218      38      4    temp47       Lscala/Option;
   31      186      5    temp48       Lscala/Some;
   218      12      5    temp48       Lscala/Some;
   107      22      6    temp35       Lscala/util/parsing/combinator/Parsers$Failure;
   144      22      7    temp38       Lscala/util/parsing/combinator/Parsers$Error;
   41      176      8    temp49       Lscala/util/parsing/combinator/PackratParsers$Head;
   218      12      8    temp49       Lscala/util/parsing/combinator/PackratParsers$Head;
   10      207      9    temp45       Lscala/util/parsing/combinator/Parsers$ParseResult;
   218      38      9    temp45       Lscala/util/parsing/combinator/Parsers$ParseResult;


public static final void scala$util$parsing$combinator$PackratParsers$$setupLR(scala.util.parsing.combinator.PackratParsers, scala.util.parsing.combinator.Parsers$Parser, scala.util.parsing.combinator.PackratParsers$PackratReader, scala.util.parsing.combinator.PackratParsers$LR);
  Signature: (Lscala/util/parsing/combinator/PackratParsers;Lscala/util/parsing/combinator/Parsers$Parser;Lscala/util/parsing/combinator/PackratParsers$PackratReader;Lscala/util/parsing/combinator/PackratParsers$LR;)V
  Code:
   Stack=9, Locals=5, Args_size=4
	aload_3
	invokevirtual	Method scala/util/parsing/combinator/PackratParsers$LR.head:()Lscala/Option;
	getstatic	Field scala/None$.MODULE$:Lscala/None$;
	astore	4
	dup
	ifnonnull	l1 // aload
	pop
	aload	4
	ifnull	l2 // aload_3
	goto	l3 // aload_2
l1	aload	4
	invokevirtual	Method java/lang/Object.equals:(Ljava/lang/Object;)Z
	ifeq	l3 // aload_2
l2	aload_3
	new	class scala/Some
	dup
	new	class scala/util/parsing/combinator/PackratParsers$Head
	dup
	aload_0
	aload_1
	getstatic	Field scala/collection/immutable/Nil$.MODULE$:Lscala/collection/immutable/Nil$;
	getstatic	Field scala/collection/immutable/Nil$.MODULE$:Lscala/collection/immutable/Nil$;
	invokespecial	Method scala/util/parsing/combinator/PackratParsers$Head."<init>":(Lscala/util/parsing/combinator/PackratParsers;Lscala/util/parsing/combinator/Parsers$Parser;Lscala/collection/immutable/List;Lscala/collection/immutable/List;)V
	invokespecial	Method scala/Some."<init>":(Ljava/lang/Object;)V
	invokevirtual	Method scala/util/parsing/combinator/PackratParsers$LR.head_$eq:(Lscala/Option;)V
l3	aload_2
	invokevirtual	Method scala/util/parsing/combinator/PackratParsers$PackratReader.scala$util$parsing$combinator$PackratParsers$$lrStack:()Lscala/collection/immutable/List;
	new	class scala/util/parsing/combinator/PackratParsers$$anonfun$scala$util$parsing$combinator$PackratParsers$$setupLR$1
	dup
	aload_0
	aload_1
	invokespecial	Method scala/util/parsing/combinator/PackratParsers$$anonfun$scala$util$parsing$combinator$PackratParsers$$setupLR$1."<init>":(Lscala/util/parsing/combinator/PackratParsers;Lscala/util/parsing/combinator/Parsers$Parser;)V
	invokevirtual	Method scala/collection/immutable/List.takeWhile:(Lscala/Function1;)Lscala/collection/immutable/List;
	new	class scala/util/parsing/combinator/PackratParsers$$anonfun$scala$util$parsing$combinator$PackratParsers$$setupLR$2
	dup
	aload_0
	aload_3
	invokespecial	Method scala/util/parsing/combinator/PackratParsers$$anonfun$scala$util$parsing$combinator$PackratParsers$$setupLR$2."<init>":(Lscala/util/parsing/combinator/PackratParsers;Lscala/util/parsing/combinator/PackratParsers$LR;)V
	invokeinterface	InterfaceMethod scala/collection/LinearSeqLike.foreach:(Lscala/Function1;)V
	return
  Labels:
   	l1 = 22 // aload
   	l2 = 30 // aload_3
   	l3 = 56 // aload_2
  LocalVariableTable: 
   Start  Length  Slot  Name   Signature
   0      87      0    $this       Lscala/util/parsing/combinator/PackratParsers;
   0      87      1    p$4       Lscala/util/parsing/combinator/Parsers$Parser;
   0      87      2    in       Lscala/util/parsing/combinator/PackratParsers$PackratReader;
   0      87      3    recDetect$1       Lscala/util/parsing/combinator/PackratParsers$LR;


public static final scala.Option scala$util$parsing$combinator$PackratParsers$$recall(scala.util.parsing.combinator.PackratParsers, scala.util.parsing.combinator.Parsers$Parser, scala.util.parsing.combinator.PackratParsers$PackratReader);
  Signature: (Lscala/util/parsing/combinator/PackratParsers;Lscala/util/parsing/combinator/Parsers$Parser;Lscala/util/parsing/combinator/PackratParsers$PackratReader;)Lscala/Option;
  Code:
   Stack=12, Locals=13, Args_size=3
	aload_2
	aload_1
	invokevirtual	Method scala/util/parsing/combinator/PackratParsers$PackratReader.scala$util$parsing$combinator$PackratParsers$$getFromCache:(Lscala/util/parsing/combinator/Parsers$Parser;)Lscala/Option;
	astore	11
	aload_2
	invokevirtual	Method scala/util/parsing/combinator/PackratParsers$PackratReader.scala$util$parsing$combinator$PackratParsers$$recursionHeads:()Lscala/collection/mutable/HashMap;
	aload_2
	invokevirtual	Method scala/util/parsing/combinator/PackratParsers$PackratReader.pos:()Lscala/util/parsing/input/Position;
	invokevirtual	Method scala/collection/mutable/HashMap.get:(Ljava/lang/Object;)Lscala/Option;
	astore	12
	getstatic	Field scala/None$.MODULE$:Lscala/None$;
	dup
	ifnonnull	l1 // aload
	pop
	aload	12
	ifnull	l2 // iconst_1
	goto	l3 // aload
l1	aload	12
	invokevirtual	Method java/lang/Object.equals:(Ljava/lang/Object;)Z
	ifeq	l3 // aload
l2	iconst_1
	ifeq	l4 // new
	aload	11
	goto	l5 // areturn
l4	new	class scala/MatchError
	dup
	aload	12
	invokevirtual	Method scala/Option.toString:()Ljava/lang/String;
	invokespecial	Method scala/MatchError."<init>":(Ljava/lang/String;)V
	athrow
l3	aload	12
	instanceof	class scala/Some
	ifeq	l6 // new
	aload	12
	checkcast	class scala/Some
	astore_3
	aload_3
	getfield	Field scala/Some.x:Ljava/lang/Object;
	checkcast	class scala/util/parsing/combinator/PackratParsers$Head
	astore	8
	aload	8
	ifnull	l7 // new
	aload	8
	invokevirtual	Method scala/util/parsing/combinator/PackratParsers$Head.headParser:()Lscala/util/parsing/combinator/Parsers$Parser;
	astore	6
	aload	8
	invokevirtual	Method scala/util/parsing/combinator/PackratParsers$Head.involvedSet:()Lscala/collection/immutable/List;
	astore	5
	aload	8
	invokevirtual	Method scala/util/parsing/combinator/PackratParsers$Head.evalSet:()Lscala/collection/immutable/List;
	astore	7
	iconst_1
	ifeq	l8 // new
	aload	11
	getstatic	Field scala/None$.MODULE$:Lscala/None$;
	astore	4
	dup
	ifnonnull	l9 // aload
	pop
	aload	4
	ifnull	l10 // aload
	goto	l11 // aload
l9	aload	4
	invokevirtual	Method java/lang/Object.equals:(Ljava/lang/Object;)Z
	ifeq	l11 // aload
l10	aload	5
	aload	6
	invokevirtual	Method scala/collection/immutable/List.$colon$colon:(Ljava/lang/Object;)Lscala/collection/immutable/List;
	aload_1
	invokeinterface	InterfaceMethod scala/collection/SeqLike.contains:(Ljava/lang/Object;)Z
	ifne	l11 // aload
	new	class scala/Some
	dup
	new	class scala/util/parsing/combinator/PackratParsers$MemoEntry
	dup
	aload_0
	new	class scala/Right
	dup
	new	class scala/util/parsing/combinator/Parsers$Failure
	dup
	aload_0
	ldc_w	String dummy 
	aload_2
	invokespecial	Method scala/util/parsing/combinator/Parsers$Failure."<init>":(Lscala/util/parsing/combinator/Parsers;Ljava/lang/String;Lscala/util/parsing/input/Reader;)V
	invokespecial	Method scala/Right."<init>":(Ljava/lang/Object;)V
	invokespecial	Method scala/util/parsing/combinator/PackratParsers$MemoEntry."<init>":(Lscala/util/parsing/combinator/PackratParsers;Lscala/Either;)V
	invokespecial	Method scala/Some."<init>":(Ljava/lang/Object;)V
	areturn
l11	aload	7
	aload_1
	invokeinterface	InterfaceMethod scala/collection/SeqLike.contains:(Ljava/lang/Object;)Z
	ifeq	l12 // aload
	aload	8
	aload	8
	invokevirtual	Method scala/util/parsing/combinator/PackratParsers$Head.evalSet:()Lscala/collection/immutable/List;
	new	class scala/util/parsing/combinator/PackratParsers$$anonfun$scala$util$parsing$combinator$PackratParsers$$recall$1
	dup
	aload_0
	aload_1
	invokespecial	Method scala/util/parsing/combinator/PackratParsers$$anonfun$scala$util$parsing$combinator$PackratParsers$$recall$1."<init>":(Lscala/util/parsing/combinator/PackratParsers;Lscala/util/parsing/combinator/Parsers$Parser;)V
	invokeinterface	InterfaceMethod scala/collection/TraversableLike.filterNot:(Lscala/Function1;)Ljava/lang/Object;
	checkcast	class scala/collection/immutable/List
	invokevirtual	Method scala/util/parsing/combinator/PackratParsers$Head.evalSet_$eq:(Lscala/collection/immutable/List;)V
	aload_1
	aload_2
	invokevirtual	Method scala/util/parsing/combinator/Parsers$Parser.apply:(Lscala/util/parsing/input/Reader;)Lscala/util/parsing/combinator/Parsers$ParseResult;
	astore	10
	aload	11
	invokevirtual	Method scala/Option.get:()Ljava/lang/Object;
	checkcast	class scala/util/parsing/combinator/PackratParsers$MemoEntry
	astore	9
	aload	9
	new	class scala/Right
	dup
	aload	10
	invokespecial	Method scala/Right."<init>":(Ljava/lang/Object;)V
	invokevirtual	Method scala/util/parsing/combinator/PackratParsers$MemoEntry.r_$eq:(Lscala/Either;)V
l12	aload	11
l5	areturn
l8	new	class scala/MatchError
	dup
	aload	12
	invokevirtual	Method scala/Option.toString:()Ljava/lang/String;
	invokespecial	Method scala/MatchError."<init>":(Ljava/lang/String;)V
	athrow
l7	new	class scala/MatchError
	dup
	aload	12
	invokevirtual	Method scala/Option.toString:()Ljava/lang/String;
	invokespecial	Method scala/MatchError."<init>":(Ljava/lang/String;)V
	athrow
l6	new	class scala/MatchError
	dup
	aload	12
	invokevirtual	Method scala/Option.toString:()Ljava/lang/String;
	invokespecial	Method scala/MatchError."<init>":(Ljava/lang/String;)V
	athrow
  Labels:
   	l1 = 36 // aload
   	l2 = 44 // iconst_1
   	l4 = 53 // new
   	l3 = 66 // aload
   	l9 = 139 // aload
   	l10 = 147 // aload
   	l11 = 198 // aload
   	l12 = 267 // aload
   	l5 = 269 // areturn
   	l8 = 270 // new
   	l7 = 283 // new
   	l6 = 296 // new
  LocalVariableTable: 
   Start  Length  Slot  Name   Signature
   0      309      0    $this       Lscala/util/parsing/combinator/PackratParsers;
   0      309      1    p$3       Lscala/util/parsing/combinator/Parsers$Parser;
   0      309      2    in       Lscala/util/parsing/combinator/PackratParsers$PackratReader;
   80      189      3    temp29       Lscala/Some;
   270      26      3    temp29       Lscala/Some;
   108      161      5    temp32       Lscala/collection/immutable/List;
   270      13      5    temp32       Lscala/collection/immutable/List;
   101      168      6    temp31       Lscala/util/parsing/combinator/Parsers$Parser;
   270      13      6    temp31       Lscala/util/parsing/combinator/Parsers$Parser;
   115      154      7    temp33       Lscala/collection/immutable/List;
   270      13      7    temp33       Lscala/collection/immutable/List;
   89      180      8    temp30       Lscala/util/parsing/combinator/PackratParsers$Head;
   270      26      8    temp30       Lscala/util/parsing/combinator/PackratParsers$Head;
   253      14      9    tempEntry       Lscala/util/parsing/combinator/PackratParsers$MemoEntry;
   243      24      10    tempRes       Lscala/util/parsing/combinator/Parsers$ParseResult;
   7      302      11    cached       Lscala/Option;
   20      289      12    head       Lscala/Option;


public static scala.util.parsing.combinator.PackratParsers$PackratParser parser2packrat(scala.util.parsing.combinator.PackratParsers, scala.Function0);
  Signature: (Lscala/util/parsing/combinator/PackratParsers;Lscala/Function0;)Lscala/util/parsing/combinator/PackratParsers$PackratParser;
  Code:
   Stack=8, Locals=4, Args_size=2
	new	class scala/runtime/IntRef
	dup
	iconst_0
	invokespecial	Method scala/runtime/IntRef."<init>":(I)V
	astore_2
	new	class scala/runtime/ObjectRef
	dup
	aconst_null
	invokespecial	Method scala/runtime/ObjectRef."<init>":(Ljava/lang/Object;)V
	astore_3
	aload_0
	aload_0
	new	class scala/util/parsing/combinator/PackratParsers$$anonfun$parser2packrat$1
	dup
	aload_0
	aload_1
	aload_3
	aload_2
	invokespecial	Method scala/util/parsing/combinator/PackratParsers$$anonfun$parser2packrat$1."<init>":(Lscala/util/parsing/combinator/PackratParsers;Lscala/Function0;Lscala/runtime/ObjectRef;Lscala/runtime/IntRef;)V
	invokeinterface	InterfaceMethod scala/util/parsing/combinator/PackratParsers.scala$util$parsing$combinator$PackratParsers$$super$Parser:(Lscala/Function1;)Lscala/util/parsing/combinator/Parsers$Parser;
	invokeinterface	InterfaceMethod scala/util/parsing/combinator/PackratParsers.memo:(Lscala/util/parsing/combinator/Parsers$Parser;)Lscala/util/parsing/combinator/PackratParsers$PackratParser;
	areturn
  Labels:
  LocalVariableTable: 
   Start  Length  Slot  Name   Signature
   0      42      0    $this       Lscala/util/parsing/combinator/PackratParsers;
   0      42      1    p$1       Lscala/Function0;
   9      32      2    bitmap$0$1       Lscala/runtime/IntRef;
   18      23      3    q$lzy$1       Lscala/runtime/ObjectRef;


public static final scala.util.parsing.input.Position scala$util$parsing$combinator$PackratParsers$$getPosFromResult(scala.util.parsing.combinator.PackratParsers, scala.util.parsing.combinator.Parsers$ParseResult);
  Signature: (Lscala/util/parsing/combinator/PackratParsers;Lscala/util/parsing/combinator/Parsers$ParseResult;)Lscala/util/parsing/input/Position;
  Code:
   Stack=1, Locals=2, Args_size=2
	aload_1
	invokevirtual	Method scala/util/parsing/combinator/Parsers$ParseResult.next:()Lscala/util/parsing/input/Reader;
	invokevirtual	Method scala/util/parsing/input/Reader.pos:()Lscala/util/parsing/input/Position;
	areturn
  Labels:
  LocalVariableTable: 
   Start  Length  Slot  Name   Signature
   0      8      0    $this       Lscala/util/parsing/combinator/PackratParsers;
   0      8      1    r       Lscala/util/parsing/combinator/Parsers$ParseResult;


public static scala.util.parsing.combinator.PackratParsers$PackratParser phrase(scala.util.parsing.combinator.PackratParsers, scala.util.parsing.combinator.Parsers$Parser);
  Signature: (Lscala/util/parsing/combinator/PackratParsers;Lscala/util/parsing/combinator/Parsers$Parser;)Lscala/util/parsing/combinator/PackratParsers$PackratParser;
  Code:
   Stack=4, Locals=3, Args_size=2
	aload_0
	aload_1
	invokeinterface	InterfaceMethod scala/util/parsing/combinator/PackratParsers.scala$util$parsing$combinator$PackratParsers$$super$phrase:(Lscala/util/parsing/combinator/Parsers$Parser;)Lscala/util/parsing/combinator/Parsers$Parser;
	astore_2
	new	class scala/util/parsing/combinator/PackratParsers$$anon$1
	dup
	aload_0
	aload_2
	invokespecial	Method scala/util/parsing/combinator/PackratParsers$$anon$1."<init>":(Lscala/util/parsing/combinator/PackratParsers;Lscala/util/parsing/combinator/Parsers$Parser;)V
	areturn
  Labels:
  LocalVariableTable: 
   Start  Length  Slot  Name   Signature
   0      18      0    $this       Lscala/util/parsing/combinator/PackratParsers;
   0      18      1    p       Lscala/util/parsing/combinator/Parsers$Parser;
   8      9      2    q$1       Lscala/util/parsing/combinator/Parsers$Parser;


}

