Compiled from "PackratParsers.scala"
public final class scala.util.parsing.combinator.PackratParsers$$anon$2 extends scala.util.parsing.combinator.PackratParsers$PackratParser
  SourceFile: "PackratParsers.scala"
  Signature: length = 0x2
   00 FFFFFFBC 
  Scala: length = 0x
   
  InnerClass: 
   public abstract #193= #100 of #192; //Parser=class scala/util/parsing/combinator/Parsers$Parser of class scala/util/parsing/combinator/Parsers
   public #194= #62 of #192; //Failure=class scala/util/parsing/combinator/Parsers$Failure of class scala/util/parsing/combinator/Parsers
   public #197= #60 of #196; //LR=class scala/util/parsing/combinator/PackratParsers$LR of class scala/util/parsing/combinator/PackratParsers
   public abstract #198= #160 of #192; //ParseResult=class scala/util/parsing/combinator/Parsers$ParseResult of class scala/util/parsing/combinator/Parsers
   public final #199= #17 of #196; //$anon$2=class scala/util/parsing/combinator/PackratParsers$$anon$2 of class scala/util/parsing/combinator/PackratParsers
   public #200= #86 of #196; //MemoEntry=class scala/util/parsing/combinator/PackratParsers$MemoEntry of class scala/util/parsing/combinator/PackratParsers
   public #201= #40 of #196; //PackratReader=class scala/util/parsing/combinator/PackratParsers$PackratReader of class scala/util/parsing/combinator/PackratParsers
   public abstract #202= #23 of #196; //PackratParser=class scala/util/parsing/combinator/PackratParsers$PackratParser of class scala/util/parsing/combinator/PackratParsers
  minor version: 0
  major version: 49
  Constant pool:
const #1 = Asciz	SourceFile;
const #2 = Asciz	PackratParsers.scala;
const #3 = Asciz	p$2;
const #4 = Asciz	Lscala/util/parsing/combinator/Parsers$Parser;;
const #5 = Asciz	$outer;
const #6 = Asciz	Lscala/util/parsing/combinator/PackratParsers;;
const #7 = Asciz	<init>;
const #8 = Asciz	(Lscala/util/parsing/combinator/PackratParsers;Lscala/util/parsing/combinator/Parsers$Parser;)V;
const #9 = Asciz	Code;
const #10 = Asciz	LineNumberTable;
const #11 = Asciz	java/lang/NullPointerException;
const #12 = class	#11;	//  java/lang/NullPointerException
const #13 = Asciz	()V;
const #14 = NameAndType	#7:#13;//  "<init>":()V
const #15 = Method	#12.#14;	//  java/lang/NullPointerException."<init>":()V
const #16 = Asciz	scala/util/parsing/combinator/PackratParsers$$anon$2;
const #17 = class	#16;	//  scala/util/parsing/combinator/PackratParsers$$anon$2
const #18 = NameAndType	#5:#6;//  $outer:Lscala/util/parsing/combinator/PackratParsers;
const #19 = Field	#17.#18;	//  scala/util/parsing/combinator/PackratParsers$$anon$2.$outer:Lscala/util/parsing/combinator/PackratParsers;
const #20 = NameAndType	#3:#4;//  p$2:Lscala/util/parsing/combinator/Parsers$Parser;
const #21 = Field	#17.#20;	//  scala/util/parsing/combinator/PackratParsers$$anon$2.p$2:Lscala/util/parsing/combinator/Parsers$Parser;
const #22 = Asciz	scala/util/parsing/combinator/PackratParsers$PackratParser;
const #23 = class	#22;	//  scala/util/parsing/combinator/PackratParsers$PackratParser
const #24 = Asciz	(Lscala/util/parsing/combinator/PackratParsers;)V;
const #25 = NameAndType	#7:#24;//  "<init>":(Lscala/util/parsing/combinator/PackratParsers;)V
const #26 = Method	#23.#25;	//  scala/util/parsing/combinator/PackratParsers$PackratParser."<init>":(Lscala/util/parsing/combinator/PackratParsers;)V
const #27 = Asciz	this;
const #28 = Asciz	Lscala/util/parsing/combinator/PackratParsers$$anon$2;;
const #29 = Asciz	LocalVariableTable;
const #30 = Asciz	apply;
const #31 = Asciz	(Ljava/lang/Object;)Ljava/lang/Object;;
const #32 = Asciz	scala/util/parsing/input/Reader;
const #33 = class	#32;	//  scala/util/parsing/input/Reader
const #34 = Asciz	(Lscala/util/parsing/input/Reader;)Lscala/util/parsing/combinator/Parsers$ParseResult;;
const #35 = NameAndType	#30:#34;//  apply:(Lscala/util/parsing/input/Reader;)Lscala/util/parsing/combinator/Parsers$ParseResult;
const #36 = Method	#17.#35;	//  scala/util/parsing/combinator/PackratParsers$$anon$2.apply:(Lscala/util/parsing/input/Reader;)Lscala/util/parsing/combinator/Parsers$ParseResult;
const #37 = Asciz	v1;
const #38 = Asciz	Ljava/lang/Object;;
const #39 = Asciz	scala/util/parsing/combinator/PackratParsers$PackratReader;
const #40 = class	#39;	//  scala/util/parsing/combinator/PackratParsers$PackratReader
const #41 = Asciz	scala/util/parsing/combinator/PackratParsers$class;
const #42 = class	#41;	//  scala/util/parsing/combinator/PackratParsers$class
const #43 = Asciz	scala$util$parsing$combinator$PackratParsers$$recall;
const #44 = Asciz	(Lscala/util/parsing/combinator/PackratParsers;Lscala/util/parsing/combinator/Parsers$Parser;Lscala/util/parsing/combinator/PackratParsers$PackratReader;)Lscala/Option;;
const #45 = NameAndType	#43:#44;//  scala$util$parsing$combinator$PackratParsers$$recall:(Lscala/util/parsing/combinator/PackratParsers;Lscala/util/parsing/combinator/Parsers$Parser;Lscala/util/parsing/combinator/PackratParsers$PackratReader;)Lscala/Option;
const #46 = Method	#42.#45;	//  scala/util/parsing/combinator/PackratParsers$class.scala$util$parsing$combinator$PackratParsers$$recall:(Lscala/util/parsing/combinator/PackratParsers;Lscala/util/parsing/combinator/Parsers$Parser;Lscala/util/parsing/combinator/PackratParsers$PackratReader;)Lscala/Option;
const #47 = Asciz	scala/None$;
const #48 = class	#47;	//  scala/None$
const #49 = Asciz	MODULE$;
const #50 = Asciz	Lscala/None$;;
const #51 = NameAndType	#49:#50;//  MODULE$:Lscala/None$;
const #52 = Field	#48.#51;	//  scala/None$.MODULE$:Lscala/None$;
const #53 = Asciz	java/lang/Object;
const #54 = class	#53;	//  java/lang/Object
const #55 = Asciz	equals;
const #56 = Asciz	(Ljava/lang/Object;)Z;
const #57 = NameAndType	#55:#56;//  equals:(Ljava/lang/Object;)Z
const #58 = Method	#54.#57;	//  java/lang/Object.equals:(Ljava/lang/Object;)Z
const #59 = Asciz	scala/util/parsing/combinator/PackratParsers$LR;
const #60 = class	#59;	//  scala/util/parsing/combinator/PackratParsers$LR
const #61 = Asciz	scala/util/parsing/combinator/Parsers$Failure;
const #62 = class	#61;	//  scala/util/parsing/combinator/Parsers$Failure
const #63 = Asciz	Base Failure;
const #64 = String	#63;	//  Base Failure
const #65 = Asciz	(Lscala/util/parsing/combinator/Parsers;Ljava/lang/String;Lscala/util/parsing/input/Reader;)V;
const #66 = NameAndType	#7:#65;//  "<init>":(Lscala/util/parsing/combinator/Parsers;Ljava/lang/String;Lscala/util/parsing/input/Reader;)V
const #67 = Method	#62.#66;	//  scala/util/parsing/combinator/Parsers$Failure."<init>":(Lscala/util/parsing/combinator/Parsers;Ljava/lang/String;Lscala/util/parsing/input/Reader;)V
const #68 = Asciz	(Lscala/util/parsing/combinator/PackratParsers;Lscala/util/parsing/combinator/Parsers$ParseResult;Lscala/util/parsing/combinator/Parsers$Parser;Lscala/Option;)V;
const #69 = NameAndType	#7:#68;//  "<init>":(Lscala/util/parsing/combinator/PackratParsers;Lscala/util/parsing/combinator/Parsers$ParseResult;Lscala/util/parsing/combinator/Parsers$Parser;Lscala/Option;)V
const #70 = Method	#60.#69;	//  scala/util/parsing/combinator/PackratParsers$LR."<init>":(Lscala/util/parsing/combinator/PackratParsers;Lscala/util/parsing/combinator/Parsers$ParseResult;Lscala/util/parsing/combinator/Parsers$Parser;Lscala/Option;)V
const #71 = Asciz	scala$util$parsing$combinator$PackratParsers$$lrStack;
const #72 = Asciz	()Lscala/collection/immutable/List;;
const #73 = NameAndType	#71:#72;//  scala$util$parsing$combinator$PackratParsers$$lrStack:()Lscala/collection/immutable/List;
const #74 = Method	#40.#73;	//  scala/util/parsing/combinator/PackratParsers$PackratReader.scala$util$parsing$combinator$PackratParsers$$lrStack:()Lscala/collection/immutable/List;
const #75 = Asciz	scala/collection/immutable/List;
const #76 = class	#75;	//  scala/collection/immutable/List
const #77 = Asciz	$colon$colon;
const #78 = Asciz	(Ljava/lang/Object;)Lscala/collection/immutable/List;;
const #79 = NameAndType	#77:#78;//  $colon$colon:(Ljava/lang/Object;)Lscala/collection/immutable/List;
const #80 = Method	#76.#79;	//  scala/collection/immutable/List.$colon$colon:(Ljava/lang/Object;)Lscala/collection/immutable/List;
const #81 = Asciz	scala$util$parsing$combinator$PackratParsers$$lrStack_$eq;
const #82 = Asciz	(Lscala/collection/immutable/List;)V;
const #83 = NameAndType	#81:#82;//  scala$util$parsing$combinator$PackratParsers$$lrStack_$eq:(Lscala/collection/immutable/List;)V
const #84 = Method	#40.#83;	//  scala/util/parsing/combinator/PackratParsers$PackratReader.scala$util$parsing$combinator$PackratParsers$$lrStack_$eq:(Lscala/collection/immutable/List;)V
const #85 = Asciz	scala/util/parsing/combinator/PackratParsers$MemoEntry;
const #86 = class	#85;	//  scala/util/parsing/combinator/PackratParsers$MemoEntry
const #87 = Asciz	scala/Left;
const #88 = class	#87;	//  scala/Left
const #89 = Asciz	(Ljava/lang/Object;)V;
const #90 = NameAndType	#7:#89;//  "<init>":(Ljava/lang/Object;)V
const #91 = Method	#88.#90;	//  scala/Left."<init>":(Ljava/lang/Object;)V
const #92 = Asciz	(Lscala/util/parsing/combinator/PackratParsers;Lscala/Either;)V;
const #93 = NameAndType	#7:#92;//  "<init>":(Lscala/util/parsing/combinator/PackratParsers;Lscala/Either;)V
const #94 = Method	#86.#93;	//  scala/util/parsing/combinator/PackratParsers$MemoEntry."<init>":(Lscala/util/parsing/combinator/PackratParsers;Lscala/Either;)V
const #95 = Asciz	scala$util$parsing$combinator$PackratParsers$$updateCacheAndGet;
const #96 = Asciz	(Lscala/util/parsing/combinator/Parsers$Parser;Lscala/util/parsing/combinator/PackratParsers$MemoEntry;)Lscala/util/parsing/combinator/PackratParsers$MemoEntry;;
const #97 = NameAndType	#95:#96;//  scala$util$parsing$combinator$PackratParsers$$updateCacheAndGet:(Lscala/util/parsing/combinator/Parsers$Parser;Lscala/util/parsing/combinator/PackratParsers$MemoEntry;)Lscala/util/parsing/combinator/PackratParsers$MemoEntry;
const #98 = Method	#40.#97;	//  scala/util/parsing/combinator/PackratParsers$PackratReader.scala$util$parsing$combinator$PackratParsers$$updateCacheAndGet:(Lscala/util/parsing/combinator/Parsers$Parser;Lscala/util/parsing/combinator/PackratParsers$MemoEntry;)Lscala/util/parsing/combinator/PackratParsers$MemoEntry;
const #99 = Asciz	scala/util/parsing/combinator/Parsers$Parser;
const #100 = class	#99;	//  scala/util/parsing/combinator/Parsers$Parser
const #101 = Method	#100.#35;	//  scala/util/parsing/combinator/Parsers$Parser.apply:(Lscala/util/parsing/input/Reader;)Lscala/util/parsing/combinator/Parsers$ParseResult;
const #102 = Asciz	scala/collection/TraversableLike;
const #103 = class	#102;	//  scala/collection/TraversableLike
const #104 = Asciz	tail;
const #105 = Asciz	()Ljava/lang/Object;;
const #106 = NameAndType	#104:#105;//  tail:()Ljava/lang/Object;
const #107 = InterfaceMethod	#103.#106;	//  scala/collection/TraversableLike.tail:()Ljava/lang/Object;
const #108 = Asciz	head;
const #109 = Asciz	()Lscala/Option;;
const #110 = NameAndType	#108:#109;//  head:()Lscala/Option;
const #111 = Method	#60.#110;	//  scala/util/parsing/combinator/PackratParsers$LR.head:()Lscala/Option;
const #112 = Asciz	scala/Right;
const #113 = class	#112;	//  scala/Right
const #114 = Method	#113.#90;	//  scala/Right."<init>":(Ljava/lang/Object;)V
const #115 = Asciz	scala/MatchError;
const #116 = class	#115;	//  scala/MatchError
const #117 = Asciz	scala/Option;
const #118 = class	#117;	//  scala/Option
const #119 = Asciz	toString;
const #120 = Asciz	()Ljava/lang/String;;
const #121 = NameAndType	#119:#120;//  toString:()Ljava/lang/String;
const #122 = Method	#118.#121;	//  scala/Option.toString:()Ljava/lang/String;
const #123 = Asciz	(Ljava/lang/String;)V;
const #124 = NameAndType	#7:#123;//  "<init>":(Ljava/lang/String;)V
const #125 = Method	#116.#124;	//  scala/MatchError."<init>":(Ljava/lang/String;)V
const #126 = Asciz	scala/Some;
const #127 = class	#126;	//  scala/Some
const #128 = Asciz	seed_$eq;
const #129 = Asciz	(Lscala/util/parsing/combinator/Parsers$ParseResult;)V;
const #130 = NameAndType	#128:#129;//  seed_$eq:(Lscala/util/parsing/combinator/Parsers$ParseResult;)V
const #131 = Method	#60.#130;	//  scala/util/parsing/combinator/PackratParsers$LR.seed_$eq:(Lscala/util/parsing/combinator/Parsers$ParseResult;)V
const #132 = Asciz	scala$util$parsing$combinator$PackratParsers$$lrAnswer;
const #133 = Asciz	(Lscala/util/parsing/combinator/PackratParsers;Lscala/util/parsing/combinator/Parsers$Parser;Lscala/util/parsing/combinator/PackratParsers$PackratReader;Lscala/util/parsing/combinator/PackratParsers$LR;)Lscala/util/parsing/combinator/Parsers$ParseResult;;
const #134 = NameAndType	#132:#133;//  scala$util$parsing$combinator$PackratParsers$$lrAnswer:(Lscala/util/parsing/combinator/PackratParsers;Lscala/util/parsing/combinator/Parsers$Parser;Lscala/util/parsing/combinator/PackratParsers$PackratReader;Lscala/util/parsing/combinator/PackratParsers$LR;)Lscala/util/parsing/combinator/Parsers$ParseResult;
const #135 = Method	#42.#134;	//  scala/util/parsing/combinator/PackratParsers$class.scala$util$parsing$combinator$PackratParsers$$lrAnswer:(Lscala/util/parsing/combinator/PackratParsers;Lscala/util/parsing/combinator/Parsers$Parser;Lscala/util/parsing/combinator/PackratParsers$PackratReader;Lscala/util/parsing/combinator/PackratParsers$LR;)Lscala/util/parsing/combinator/Parsers$ParseResult;
const #136 = Asciz	x;
const #137 = NameAndType	#136:#38;//  x:Ljava/lang/Object;
const #138 = Field	#127.#137;	//  scala/Some.x:Ljava/lang/Object;
const #139 = Asciz	r;
const #140 = Asciz	()Lscala/Either;;
const #141 = NameAndType	#139:#140;//  r:()Lscala/Either;
const #142 = Method	#86.#141;	//  scala/util/parsing/combinator/PackratParsers$MemoEntry.r:()Lscala/Either;
const #143 = Asciz	a;
const #144 = NameAndType	#143:#38;//  a:Ljava/lang/Object;
const #145 = Field	#88.#144;	//  scala/Left.a:Ljava/lang/Object;
const #146 = Asciz	scala$util$parsing$combinator$PackratParsers$$setupLR;
const #147 = Asciz	(Lscala/util/parsing/combinator/PackratParsers;Lscala/util/parsing/combinator/Parsers$Parser;Lscala/util/parsing/combinator/PackratParsers$PackratReader;Lscala/util/parsing/combinator/PackratParsers$LR;)V;
const #148 = NameAndType	#146:#147;//  scala$util$parsing$combinator$PackratParsers$$setupLR:(Lscala/util/parsing/combinator/PackratParsers;Lscala/util/parsing/combinator/Parsers$Parser;Lscala/util/parsing/combinator/PackratParsers$PackratReader;Lscala/util/parsing/combinator/PackratParsers$LR;)V
const #149 = Method	#42.#148;	//  scala/util/parsing/combinator/PackratParsers$class.scala$util$parsing$combinator$PackratParsers$$setupLR:(Lscala/util/parsing/combinator/PackratParsers;Lscala/util/parsing/combinator/Parsers$Parser;Lscala/util/parsing/combinator/PackratParsers$PackratReader;Lscala/util/parsing/combinator/PackratParsers$LR;)V
const #150 = Asciz	seed;
const #151 = Asciz	()Lscala/util/parsing/combinator/Parsers$ParseResult;;
const #152 = NameAndType	#150:#151;//  seed:()Lscala/util/parsing/combinator/Parsers$ParseResult;
const #153 = Method	#60.#152;	//  scala/util/parsing/combinator/PackratParsers$LR.seed:()Lscala/util/parsing/combinator/Parsers$ParseResult;
const #154 = Method	#60.#121;	//  scala/util/parsing/combinator/PackratParsers$LR.toString:()Ljava/lang/String;
const #155 = Method	#86.#121;	//  scala/util/parsing/combinator/PackratParsers$MemoEntry.toString:()Ljava/lang/String;
const #156 = Asciz	b;
const #157 = NameAndType	#156:#38;//  b:Ljava/lang/Object;
const #158 = Field	#113.#157;	//  scala/Right.b:Ljava/lang/Object;
const #159 = Asciz	scala/util/parsing/combinator/Parsers$ParseResult;
const #160 = class	#159;	//  scala/util/parsing/combinator/Parsers$ParseResult
const #161 = Asciz	in;
const #162 = Asciz	Lscala/util/parsing/input/Reader;;
const #163 = Asciz	tempRes;
const #164 = Asciz	Lscala/util/parsing/combinator/Parsers$ParseResult;;
const #165 = Asciz	base;
const #166 = Asciz	Lscala/util/parsing/combinator/PackratParsers$LR;;
const #167 = Asciz	res;
const #168 = Asciz	temp50;
const #169 = Asciz	Lscala/Option;;
const #170 = Asciz	temp66;
const #171 = Asciz	Lscala/Some;;
const #172 = Asciz	temp60;
const #173 = Asciz	Lscala/Left;;
const #174 = Asciz	inMem;
const #175 = Asciz	Lscala/util/parsing/combinator/PackratParsers$PackratReader;;
const #176 = Asciz	temp55;
const #177 = Asciz	temp61;
const #178 = Asciz	temp59;
const #179 = Asciz	Lscala/Either;;
const #180 = Asciz	temp62;
const #181 = Asciz	Lscala/Right;;
const #182 = Asciz	temp63;
const #183 = Asciz	temp67;
const #184 = Asciz	Lscala/util/parsing/combinator/PackratParsers$MemoEntry;;
const #185 = Asciz	m;
const #186 = Asciz	(Lscala/util/parsing/input/Reader<Ljava/lang/Object;>;)Lscala/util/parsing/combinator/Parsers$ParseResult<TT;>;;
const #187 = Asciz	Signature;
const #188 = Asciz	Lscala/util/parsing/combinator/PackratParsers$PackratParser<TT;>;;
const #189 = Asciz	Scala;
const #190 = Asciz	InnerClasses;
const #191 = Asciz	scala/util/parsing/combinator/Parsers;
const #192 = class	#191;	//  scala/util/parsing/combinator/Parsers
const #193 = Asciz	Parser;
const #194 = Asciz	Failure;
const #195 = Asciz	scala/util/parsing/combinator/PackratParsers;
const #196 = class	#195;	//  scala/util/parsing/combinator/PackratParsers
const #197 = Asciz	LR;
const #198 = Asciz	ParseResult;
const #199 = Asciz	$anon$2;
const #200 = Asciz	MemoEntry;
const #201 = Asciz	PackratReader;
const #202 = Asciz	PackratParser;

{
public scala.util.parsing.combinator.PackratParsers$$anon$2(scala.util.parsing.combinator.PackratParsers, scala.util.parsing.combinator.Parsers$Parser);
  Code:
   Stack=2, Locals=3, Args_size=3
   0:	aload_1
   1:	ifnonnull	12
   4:	new	#12; //class java/lang/NullPointerException
   7:	dup
   8:	invokespecial	#15; //Method java/lang/NullPointerException."<init>":()V
   11:	athrow
   12:	aload_0
   13:	aload_1
   14:	putfield	#19; //Field $outer:Lscala/util/parsing/combinator/PackratParsers;
   17:	aload_0
   18:	aload_2
   19:	putfield	#21; //Field p$2:Lscala/util/parsing/combinator/Parsers$Parser;
   22:	aload_0
   23:	aload_1
   24:	invokespecial	#26; //Method scala/util/parsing/combinator/PackratParsers$PackratParser."<init>":(Lscala/util/parsing/combinator/PackratParsers;)V
   27:	return
  LineNumberTable: 
   line 250: 0

  LocalVariableTable: 
   Start  Length  Slot  Name   Signature
   0      28      0    this       Lscala/util/parsing/combinator/PackratParsers$$anon$2;
   0      28      1    $outer       Lscala/util/parsing/combinator/PackratParsers;


public java.lang.Object apply(java.lang.Object);
  Code:
   Stack=2, Locals=2, Args_size=2
   0:	aload_0
   1:	aload_1
   2:	checkcast	#33; //class scala/util/parsing/input/Reader
   5:	invokevirtual	#36; //Method apply:(Lscala/util/parsing/input/Reader;)Lscala/util/parsing/combinator/Parsers$ParseResult;
   8:	areturn
  LineNumberTable: 
   line 250: 0

  LocalVariableTable: 
   Start  Length  Slot  Name   Signature
   0      9      0    this       Lscala/util/parsing/combinator/PackratParsers$$anon$2;
   0      9      1    v1       Ljava/lang/Object;


public scala.util.parsing.combinator.Parsers$ParseResult apply(scala.util.parsing.input.Reader);
  Code:
   Stack=8, Locals=16, Args_size=2
   0:	aload_1
   1:	checkcast	#40; //class scala/util/parsing/combinator/PackratParsers$PackratReader
   4:	astore	8
   6:	aload_0
   7:	getfield	#19; //Field $outer:Lscala/util/parsing/combinator/PackratParsers;
   10:	aload_0
   11:	getfield	#21; //Field p$2:Lscala/util/parsing/combinator/Parsers$Parser;
   14:	aload	8
   16:	invokestatic	#46; //Method scala/util/parsing/combinator/PackratParsers$class.scala$util$parsing$combinator$PackratParsers$$recall:(Lscala/util/parsing/combinator/PackratParsers;Lscala/util/parsing/combinator/Parsers$Parser;Lscala/util/parsing/combinator/PackratParsers$PackratReader;)Lscala/Option;
   19:	astore	15
   21:	getstatic	#52; //Field scala/None$.MODULE$:Lscala/None$;
   24:	dup
   25:	ifnonnull	37
   28:	pop
   29:	aload	15
   31:	ifnull	45
   34:	goto	309
   37:	aload	15
   39:	invokevirtual	#58; //Method java/lang/Object.equals:(Ljava/lang/Object;)Z
   42:	ifeq	309
   45:	iconst_1
   46:	ifeq	296
   49:	new	#60; //class scala/util/parsing/combinator/PackratParsers$LR
   52:	dup
   53:	aload_0
   54:	getfield	#19; //Field $outer:Lscala/util/parsing/combinator/PackratParsers;
   57:	new	#62; //class scala/util/parsing/combinator/Parsers$Failure
   60:	dup
   61:	aload_0
   62:	getfield	#19; //Field $outer:Lscala/util/parsing/combinator/PackratParsers;
   65:	ldc	#64; //String Base Failure
   67:	aload_1
   68:	invokespecial	#67; //Method scala/util/parsing/combinator/Parsers$Failure."<init>":(Lscala/util/parsing/combinator/Parsers;Ljava/lang/String;Lscala/util/parsing/input/Reader;)V
   71:	aload_0
   72:	getfield	#21; //Field p$2:Lscala/util/parsing/combinator/Parsers$Parser;
   75:	getstatic	#52; //Field scala/None$.MODULE$:Lscala/None$;
   78:	invokespecial	#70; //Method scala/util/parsing/combinator/PackratParsers$LR."<init>":(Lscala/util/parsing/combinator/PackratParsers;Lscala/util/parsing/combinator/Parsers$ParseResult;Lscala/util/parsing/combinator/Parsers$Parser;Lscala/Option;)V
   81:	astore_3
   82:	aload	8
   84:	aload	8
   86:	invokevirtual	#74; //Method scala/util/parsing/combinator/PackratParsers$PackratReader.scala$util$parsing$combinator$PackratParsers$$lrStack:()Lscala/collection/immutable/List;
   89:	aload_3
   90:	invokevirtual	#80; //Method scala/collection/immutable/List.$colon$colon:(Ljava/lang/Object;)Lscala/collection/immutable/List;
   93:	invokevirtual	#84; //Method scala/util/parsing/combinator/PackratParsers$PackratReader.scala$util$parsing$combinator$PackratParsers$$lrStack_$eq:(Lscala/collection/immutable/List;)V
   96:	aload	8
   98:	aload_0
   99:	getfield	#21; //Field p$2:Lscala/util/parsing/combinator/Parsers$Parser;
   102:	new	#86; //class scala/util/parsing/combinator/PackratParsers$MemoEntry
   105:	dup
   106:	aload_0
   107:	getfield	#19; //Field $outer:Lscala/util/parsing/combinator/PackratParsers;
   110:	new	#88; //class scala/Left
   113:	dup
   114:	aload_3
   115:	invokespecial	#91; //Method scala/Left."<init>":(Ljava/lang/Object;)V
   118:	invokespecial	#94; //Method scala/util/parsing/combinator/PackratParsers$MemoEntry."<init>":(Lscala/util/parsing/combinator/PackratParsers;Lscala/Either;)V
   121:	invokevirtual	#98; //Method scala/util/parsing/combinator/PackratParsers$PackratReader.scala$util$parsing$combinator$PackratParsers$$updateCacheAndGet:(Lscala/util/parsing/combinator/Parsers$Parser;Lscala/util/parsing/combinator/PackratParsers$MemoEntry;)Lscala/util/parsing/combinator/PackratParsers$MemoEntry;
   124:	pop
   125:	aload_0
   126:	getfield	#21; //Field p$2:Lscala/util/parsing/combinator/Parsers$Parser;
   129:	aload_1
   130:	invokevirtual	#101; //Method scala/util/parsing/combinator/Parsers$Parser.apply:(Lscala/util/parsing/input/Reader;)Lscala/util/parsing/combinator/Parsers$ParseResult;
   133:	astore_2
   134:	aload	8
   136:	aload	8
   138:	invokevirtual	#74; //Method scala/util/parsing/combinator/PackratParsers$PackratReader.scala$util$parsing$combinator$PackratParsers$$lrStack:()Lscala/collection/immutable/List;
   141:	invokeinterface	#107,  1; //InterfaceMethod scala/collection/TraversableLike.tail:()Ljava/lang/Object;
   146:	checkcast	#76; //class scala/collection/immutable/List
   149:	invokevirtual	#84; //Method scala/util/parsing/combinator/PackratParsers$PackratReader.scala$util$parsing$combinator$PackratParsers$$lrStack_$eq:(Lscala/collection/immutable/List;)V
   152:	aload_3
   153:	invokevirtual	#111; //Method scala/util/parsing/combinator/PackratParsers$LR.head:()Lscala/Option;
   156:	astore	5
   158:	getstatic	#52; //Field scala/None$.MODULE$:Lscala/None$;
   161:	dup
   162:	ifnonnull	174
   165:	pop
   166:	aload	5
   168:	ifnull	182
   171:	goto	232
   174:	aload	5
   176:	invokevirtual	#58; //Method java/lang/Object.equals:(Ljava/lang/Object;)Z
   179:	ifeq	232
   182:	iconst_1
   183:	ifeq	219
   186:	aload	8
   188:	aload_0
   189:	getfield	#21; //Field p$2:Lscala/util/parsing/combinator/Parsers$Parser;
   192:	new	#86; //class scala/util/parsing/combinator/PackratParsers$MemoEntry
   195:	dup
   196:	aload_0
   197:	getfield	#19; //Field $outer:Lscala/util/parsing/combinator/PackratParsers;
   200:	new	#113; //class scala/Right
   203:	dup
   204:	aload_2
   205:	invokespecial	#114; //Method scala/Right."<init>":(Ljava/lang/Object;)V
   208:	invokespecial	#94; //Method scala/util/parsing/combinator/PackratParsers$MemoEntry."<init>":(Lscala/util/parsing/combinator/PackratParsers;Lscala/Either;)V
   211:	invokevirtual	#98; //Method scala/util/parsing/combinator/PackratParsers$PackratReader.scala$util$parsing$combinator$PackratParsers$$updateCacheAndGet:(Lscala/util/parsing/combinator/Parsers$Parser;Lscala/util/parsing/combinator/PackratParsers$MemoEntry;)Lscala/util/parsing/combinator/PackratParsers$MemoEntry;
   214:	pop
   215:	aload_2
   216:	goto	490
   219:	new	#116; //class scala/MatchError
   222:	dup
   223:	aload	5
   225:	invokevirtual	#122; //Method scala/Option.toString:()Ljava/lang/String;
   228:	invokespecial	#125; //Method scala/MatchError."<init>":(Ljava/lang/String;)V
   231:	athrow
   232:	aload	5
   234:	instanceof	#127; //class scala/Some
   237:	ifeq	283
   240:	iconst_1
   241:	ifeq	270
   244:	aload_3
   245:	aload_2
   246:	invokevirtual	#131; //Method scala/util/parsing/combinator/PackratParsers$LR.seed_$eq:(Lscala/util/parsing/combinator/Parsers$ParseResult;)V
   249:	aload_0
   250:	getfield	#19; //Field $outer:Lscala/util/parsing/combinator/PackratParsers;
   253:	aload_0
   254:	getfield	#21; //Field p$2:Lscala/util/parsing/combinator/Parsers$Parser;
   257:	aload	8
   259:	aload_3
   260:	invokestatic	#135; //Method scala/util/parsing/combinator/PackratParsers$class.scala$util$parsing$combinator$PackratParsers$$lrAnswer:(Lscala/util/parsing/combinator/PackratParsers;Lscala/util/parsing/combinator/Parsers$Parser;Lscala/util/parsing/combinator/PackratParsers$PackratReader;Lscala/util/parsing/combinator/PackratParsers$LR;)Lscala/util/parsing/combinator/Parsers$ParseResult;
   263:	astore	4
   265:	aload	4
   267:	goto	490
   270:	new	#116; //class scala/MatchError
   273:	dup
   274:	aload	5
   276:	invokevirtual	#122; //Method scala/Option.toString:()Ljava/lang/String;
   279:	invokespecial	#125; //Method scala/MatchError."<init>":(Ljava/lang/String;)V
   282:	athrow
   283:	new	#116; //class scala/MatchError
   286:	dup
   287:	aload	5
   289:	invokevirtual	#122; //Method scala/Option.toString:()Ljava/lang/String;
   292:	invokespecial	#125; //Method scala/MatchError."<init>":(Ljava/lang/String;)V
   295:	athrow
   296:	new	#116; //class scala/MatchError
   299:	dup
   300:	aload	15
   302:	invokevirtual	#122; //Method scala/Option.toString:()Ljava/lang/String;
   305:	invokespecial	#125; //Method scala/MatchError."<init>":(Ljava/lang/String;)V
   308:	athrow
   309:	aload	15
   311:	instanceof	#127; //class scala/Some
   314:	ifeq	556
   317:	aload	15
   319:	checkcast	#127; //class scala/Some
   322:	astore	6
   324:	aload	6
   326:	getfield	#138; //Field scala/Some.x:Ljava/lang/Object;
   329:	checkcast	#86; //class scala/util/parsing/combinator/PackratParsers$MemoEntry
   332:	astore	14
   334:	iconst_1
   335:	ifeq	543
   338:	aload	14
   340:	ifnull	530
   343:	aload	14
   345:	invokevirtual	#142; //Method scala/util/parsing/combinator/PackratParsers$MemoEntry.r:()Lscala/Either;
   348:	astore	11
   350:	aload	11
   352:	instanceof	#88; //class scala/Left
   355:	ifeq	454
   358:	aload	11
   360:	checkcast	#88; //class scala/Left
   363:	astore	7
   365:	aload	7
   367:	getfield	#145; //Field scala/Left.a:Ljava/lang/Object;
   370:	checkcast	#60; //class scala/util/parsing/combinator/PackratParsers$LR
   373:	astore	10
   375:	iconst_1
   376:	ifeq	441
   379:	aload_0
   380:	getfield	#19; //Field $outer:Lscala/util/parsing/combinator/PackratParsers;
   383:	aload_0
   384:	getfield	#21; //Field p$2:Lscala/util/parsing/combinator/Parsers$Parser;
   387:	aload	8
   389:	aload	10
   391:	invokestatic	#149; //Method scala/util/parsing/combinator/PackratParsers$class.scala$util$parsing$combinator$PackratParsers$$setupLR:(Lscala/util/parsing/combinator/PackratParsers;Lscala/util/parsing/combinator/Parsers$Parser;Lscala/util/parsing/combinator/PackratParsers$PackratReader;Lscala/util/parsing/combinator/PackratParsers$LR;)V
   394:	aload	10
   396:	ifnull	428
   399:	aload	10
   401:	invokevirtual	#153; //Method scala/util/parsing/combinator/PackratParsers$LR.seed:()Lscala/util/parsing/combinator/Parsers$ParseResult;
   404:	astore	9
   406:	iconst_1
   407:	ifeq	415
   410:	aload	9
   412:	goto	490
   415:	new	#116; //class scala/MatchError
   418:	dup
   419:	aload	10
   421:	invokevirtual	#154; //Method scala/util/parsing/combinator/PackratParsers$LR.toString:()Ljava/lang/String;
   424:	invokespecial	#125; //Method scala/MatchError."<init>":(Ljava/lang/String;)V
   427:	athrow
   428:	new	#116; //class scala/MatchError
   431:	dup
   432:	aload	10
   434:	invokevirtual	#154; //Method scala/util/parsing/combinator/PackratParsers$LR.toString:()Ljava/lang/String;
   437:	invokespecial	#125; //Method scala/MatchError."<init>":(Ljava/lang/String;)V
   440:	athrow
   441:	new	#116; //class scala/MatchError
   444:	dup
   445:	aload	14
   447:	invokevirtual	#155; //Method scala/util/parsing/combinator/PackratParsers$MemoEntry.toString:()Ljava/lang/String;
   450:	invokespecial	#125; //Method scala/MatchError."<init>":(Ljava/lang/String;)V
   453:	athrow
   454:	aload	11
   456:	instanceof	#113; //class scala/Right
   459:	ifeq	517
   462:	aload	11
   464:	checkcast	#113; //class scala/Right
   467:	astore	12
   469:	aload	12
   471:	getfield	#158; //Field scala/Right.b:Ljava/lang/Object;
   474:	checkcast	#160; //class scala/util/parsing/combinator/Parsers$ParseResult
   477:	astore	13
   479:	aload	13
   481:	ifnull	504
   484:	iconst_1
   485:	ifeq	491
   488:	aload	13
   490:	areturn
   491:	new	#116; //class scala/MatchError
   494:	dup
   495:	aload	14
   497:	invokevirtual	#155; //Method scala/util/parsing/combinator/PackratParsers$MemoEntry.toString:()Ljava/lang/String;
   500:	invokespecial	#125; //Method scala/MatchError."<init>":(Ljava/lang/String;)V
   503:	athrow
   504:	new	#116; //class scala/MatchError
   507:	dup
   508:	aload	14
   510:	invokevirtual	#155; //Method scala/util/parsing/combinator/PackratParsers$MemoEntry.toString:()Ljava/lang/String;
   513:	invokespecial	#125; //Method scala/MatchError."<init>":(Ljava/lang/String;)V
   516:	athrow
   517:	new	#116; //class scala/MatchError
   520:	dup
   521:	aload	14
   523:	invokevirtual	#155; //Method scala/util/parsing/combinator/PackratParsers$MemoEntry.toString:()Ljava/lang/String;
   526:	invokespecial	#125; //Method scala/MatchError."<init>":(Ljava/lang/String;)V
   529:	athrow
   530:	new	#116; //class scala/MatchError
   533:	dup
   534:	aload	14
   536:	invokevirtual	#155; //Method scala/util/parsing/combinator/PackratParsers$MemoEntry.toString:()Ljava/lang/String;
   539:	invokespecial	#125; //Method scala/MatchError."<init>":(Ljava/lang/String;)V
   542:	athrow
   543:	new	#116; //class scala/MatchError
   546:	dup
   547:	aload	15
   549:	invokevirtual	#122; //Method scala/Option.toString:()Ljava/lang/String;
   552:	invokespecial	#125; //Method scala/MatchError."<init>":(Ljava/lang/String;)V
   555:	athrow
   556:	new	#116; //class scala/MatchError
   559:	dup
   560:	aload	15
   562:	invokevirtual	#122; //Method scala/Option.toString:()Ljava/lang/String;
   565:	invokespecial	#125; //Method scala/MatchError."<init>":(Ljava/lang/String;)V
   568:	athrow
  LineNumberTable: 
   line 255: 0
   line 258: 6
   line 259: 21
   line 21: 45
   line 262: 49
   line 263: 82
   line 265: 96
   line 267: 125
   line 269: 134
   line 271: 152
   line 21: 182
   line 274: 186
   line 275: 215
   line 271: 219
   line 21: 240
   line 280: 244
   line 278: 245
   line 280: 249
   line 281: 265
   line 271: 270
   line 259: 296
   line 251: 317
   line 21: 334
   line 286: 338
   line 251: 343
   line 286: 350
   line 251: 358
   line 21: 375
   line 288: 379
   line 290: 394
   line 251: 399
   line 21: 406
   line 290: 410
   line 286: 441
   line 251: 462
   line 286: 479
   line 21: 484
   line 292: 488
   line 251: 490
   line 286: 491
   line 259: 543

  LocalVariableTable: 
   Start  Length  Slot  Name   Signature
   0      569      0    this       Lscala/util/parsing/combinator/PackratParsers$$anon$2;
   0      569      1    in       Lscala/util/parsing/input/Reader;
   134      162      2    tempRes       Lscala/util/parsing/combinator/Parsers$ParseResult;
   82      214      3    base       Lscala/util/parsing/combinator/PackratParsers$LR;
   265      2      4    res       Lscala/util/parsing/combinator/Parsers$ParseResult;
   158      138      5    temp50       Lscala/Option;
   324      166      6    temp66       Lscala/Some;
   491      65      6    temp66       Lscala/Some;
   365      89      7    temp60       Lscala/Left;
   6      563      8    inMem       Lscala/util/parsing/combinator/PackratParsers$PackratReader;
   406      22      9    temp55       Lscala/util/parsing/combinator/Parsers$ParseResult;
   375      79      10    temp61       Lscala/util/parsing/combinator/PackratParsers$LR;
   350      140      11    temp59       Lscala/Either;
   491      39      11    temp59       Lscala/Either;
   469      21      12    temp62       Lscala/Right;
   491      26      12    temp62       Lscala/Right;
   479      11      13    temp63       Lscala/util/parsing/combinator/Parsers$ParseResult;
   491      26      13    temp63       Lscala/util/parsing/combinator/Parsers$ParseResult;
   334      156      14    temp67       Lscala/util/parsing/combinator/PackratParsers$MemoEntry;
   491      65      14    temp67       Lscala/util/parsing/combinator/PackratParsers$MemoEntry;
   21      548      15    m       Lscala/Option;

  Signature: length = 0x2
   00 FFFFFFBA 

}

