Compiled from "PackratParsers.scala"
public abstract class scala.util.parsing.combinator.PackratParsers$PackratParser extends scala.util.parsing.combinator.Parsers$Parser implements scala.ScalaObject
  SourceFile: "PackratParsers.scala"
  Signature: length = 0x2
   00 1D 
  Scala: length = 0x
   
  InnerClass: 
   public abstract #34= #19 of #33; //Parser=class scala/util/parsing/combinator/Parsers$Parser of class scala/util/parsing/combinator/Parsers
   public abstract #37= #15 of #36; //PackratParser=class scala/util/parsing/combinator/PackratParsers$PackratParser of class scala/util/parsing/combinator/PackratParsers
  minor version: 0
  major version: 49
  Constant pool:
const #1 = Asciz	SourceFile;
const #2 = Asciz	PackratParsers.scala;
const #3 = Asciz	$outer;
const #4 = Asciz	Lscala/util/parsing/combinator/PackratParsers;;
const #5 = Asciz	<init>;
const #6 = Asciz	(Lscala/util/parsing/combinator/PackratParsers;)V;
const #7 = Asciz	Code;
const #8 = Asciz	LineNumberTable;
const #9 = Asciz	java/lang/NullPointerException;
const #10 = class	#9;	//  java/lang/NullPointerException
const #11 = Asciz	()V;
const #12 = NameAndType	#5:#11;//  "<init>":()V
const #13 = Method	#10.#12;	//  java/lang/NullPointerException."<init>":()V
const #14 = Asciz	scala/util/parsing/combinator/PackratParsers$PackratParser;
const #15 = class	#14;	//  scala/util/parsing/combinator/PackratParsers$PackratParser
const #16 = NameAndType	#3:#4;//  $outer:Lscala/util/parsing/combinator/PackratParsers;
const #17 = Field	#15.#16;	//  scala/util/parsing/combinator/PackratParsers$PackratParser.$outer:Lscala/util/parsing/combinator/PackratParsers;
const #18 = Asciz	scala/util/parsing/combinator/Parsers$Parser;
const #19 = class	#18;	//  scala/util/parsing/combinator/Parsers$Parser
const #20 = Asciz	(Lscala/util/parsing/combinator/Parsers;)V;
const #21 = NameAndType	#5:#20;//  "<init>":(Lscala/util/parsing/combinator/Parsers;)V
const #22 = Method	#19.#21;	//  scala/util/parsing/combinator/Parsers$Parser."<init>":(Lscala/util/parsing/combinator/Parsers;)V
const #23 = Asciz	this;
const #24 = Asciz	Lscala/util/parsing/combinator/PackratParsers$PackratParser;;
const #25 = Asciz	LocalVariableTable;
const #26 = Asciz	Signature;
const #27 = Asciz	scala$util$parsing$combinator$PackratParsers$PackratParser$$$outer;
const #28 = Asciz	()Lscala/util/parsing/combinator/PackratParsers;;
const #29 = Asciz	<T:Ljava/lang/Object;>Lscala/util/parsing/combinator/Parsers$Parser<TT;>;Lscala/ScalaObject;;
const #30 = Asciz	Scala;
const #31 = Asciz	InnerClasses;
const #32 = Asciz	scala/util/parsing/combinator/Parsers;
const #33 = class	#32;	//  scala/util/parsing/combinator/Parsers
const #34 = Asciz	Parser;
const #35 = Asciz	scala/util/parsing/combinator/PackratParsers;
const #36 = class	#35;	//  scala/util/parsing/combinator/PackratParsers
const #37 = Asciz	PackratParser;
const #38 = Asciz	scala/ScalaObject;
const #39 = class	#38;	//  scala/ScalaObject

{
public final scala.util.parsing.combinator.PackratParsers $outer;

public scala.util.parsing.combinator.PackratParsers$PackratParser(scala.util.parsing.combinator.PackratParsers);
  Code:
   Stack=2, Locals=2, Args_size=2
   0:	aload_1
   1:	ifnonnull	12
   4:	new	#10; //class java/lang/NullPointerException
   7:	dup
   8:	invokespecial	#13; //Method java/lang/NullPointerException."<init>":()V
   11:	athrow
   12:	aload_0
   13:	aload_1
   14:	putfield	#17; //Field $outer:Lscala/util/parsing/combinator/PackratParsers;
   17:	aload_0
   18:	aload_1
   19:	invokespecial	#22; //Method scala/util/parsing/combinator/Parsers$Parser."<init>":(Lscala/util/parsing/combinator/Parsers;)V
   22:	return
  LineNumberTable: 
   line 152: 0

  LocalVariableTable: 
   Start  Length  Slot  Name   Signature
   0      23      0    this       Lscala/util/parsing/combinator/PackratParsers$PackratParser;
   0      23      1    $outer       Lscala/util/parsing/combinator/PackratParsers;

  Signature: length = 0x2
   00 06 

public scala.util.parsing.combinator.PackratParsers scala$util$parsing$combinator$PackratParsers$PackratParser$$$outer();
  Code:
   Stack=1, Locals=1, Args_size=1
   0:	aload_0
   1:	getfield	#17; //Field $outer:Lscala/util/parsing/combinator/PackratParsers;
   4:	areturn
  LineNumberTable: 
   line 152: 0


}

