Compiled from "PackratParsers.scala"
public final class scala.util.parsing.combinator.PackratParsers$PackratReader$$anon$3 extends scala.util.parsing.combinator.PackratParsers$PackratReader
  SourceFile: "PackratParsers.scala"
  Signature: length = 0x2
   00 37 
  Scala: length = 0x
   
  InnerClass: 
   public PackratReader=class scala/util/parsing/combinator/PackratParsers$PackratReader of class scala/util/parsing/combinator/PackratParsers
   public final $anon$3=class scala/util/parsing/combinator/PackratParsers$PackratReader$$anon$3 of class scala/util/parsing/combinator/PackratParsers$PackratReader
  minor version: 0
  major version: 49
  Constant pool:
Asciz	SourceFile;
Asciz	PackratParsers.scala;
Asciz	scala$util$parsing$combinator$PackratParsers$$recursionHeads;
Asciz	Lscala/collection/mutable/HashMap;;
Asciz	scala$util$parsing$combinator$PackratParsers$$cache;
Asciz	()Lscala/collection/mutable/HashMap;;
Asciz	Code;
Asciz	LineNumberTable;
Asciz	scala/util/parsing/combinator/PackratParsers$PackratReader$$anon$3;
class	scala/util/parsing/combinator/PackratParsers$PackratReader$$anon$3
NameAndType	scala$util$parsing$combinator$PackratParsers$$cache:Lscala/collection/mutable/HashMap;
Field	scala/util/parsing/combinator/PackratParsers$PackratReader$$anon$3.scala$util$parsing$combinator$PackratParsers$$cache:Lscala/collection/mutable/HashMap;
NameAndType	scala$util$parsing$combinator$PackratParsers$$recursionHeads:Lscala/collection/mutable/HashMap;
Field	scala/util/parsing/combinator/PackratParsers$PackratReader$$anon$3.scala$util$parsing$combinator$PackratParsers$$recursionHeads:Lscala/collection/mutable/HashMap;
Asciz	<init>;
Asciz	(Lscala/util/parsing/combinator/PackratParsers$PackratReader;)V;
Asciz	scala/util/parsing/combinator/PackratParsers$PackratReader;
class	scala/util/parsing/combinator/PackratParsers$PackratReader
Asciz	scala$util$parsing$combinator$PackratParsers$PackratReader$$$outer;
Asciz	()Lscala/util/parsing/combinator/PackratParsers;;
NameAndType	scala$util$parsing$combinator$PackratParsers$PackratReader$$$outer:()Lscala/util/parsing/combinator/PackratParsers;
Method	scala/util/parsing/combinator/PackratParsers$PackratReader.scala$util$parsing$combinator$PackratParsers$PackratReader$$$outer:()Lscala/util/parsing/combinator/PackratParsers;
Asciz	scala$util$parsing$combinator$PackratParsers$PackratReader$$underlying;
Asciz	Lscala/util/parsing/input/Reader;;
NameAndType	scala$util$parsing$combinator$PackratParsers$PackratReader$$underlying:Lscala/util/parsing/input/Reader;
Field	scala/util/parsing/combinator/PackratParsers$PackratReader.scala$util$parsing$combinator$PackratParsers$PackratReader$$underlying:Lscala/util/parsing/input/Reader;
Asciz	scala/util/parsing/input/Reader;
class	scala/util/parsing/input/Reader
Asciz	rest;
Asciz	()Lscala/util/parsing/input/Reader;;
NameAndType	rest:()Lscala/util/parsing/input/Reader;
Method	scala/util/parsing/input/Reader.rest:()Lscala/util/parsing/input/Reader;
Asciz	(Lscala/util/parsing/combinator/PackratParsers;Lscala/util/parsing/input/Reader;)V;
NameAndType	"<init>":(Lscala/util/parsing/combinator/PackratParsers;Lscala/util/parsing/input/Reader;)V
Method	scala/util/parsing/combinator/PackratParsers$PackratReader."<init>":(Lscala/util/parsing/combinator/PackratParsers;Lscala/util/parsing/input/Reader;)V
NameAndType	scala$util$parsing$combinator$PackratParsers$$cache:()Lscala/collection/mutable/HashMap;
Method	scala/util/parsing/combinator/PackratParsers$PackratReader.scala$util$parsing$combinator$PackratParsers$$cache:()Lscala/collection/mutable/HashMap;
NameAndType	scala$util$parsing$combinator$PackratParsers$$recursionHeads:()Lscala/collection/mutable/HashMap;
Method	scala/util/parsing/combinator/PackratParsers$PackratReader.scala$util$parsing$combinator$PackratParsers$$recursionHeads:()Lscala/collection/mutable/HashMap;
Asciz	scala$util$parsing$combinator$PackratParsers$$lrStack;
Asciz	()Lscala/collection/immutable/List;;
NameAndType	scala$util$parsing$combinator$PackratParsers$$lrStack:()Lscala/collection/immutable/List;
Method	scala/util/parsing/combinator/PackratParsers$PackratReader.scala$util$parsing$combinator$PackratParsers$$lrStack:()Lscala/collection/immutable/List;
Asciz	scala$util$parsing$combinator$PackratParsers$$lrStack_$eq;
Asciz	(Lscala/collection/immutable/List;)V;
NameAndType	scala$util$parsing$combinator$PackratParsers$$lrStack_$eq:(Lscala/collection/immutable/List;)V
Method	scala/util/parsing/combinator/PackratParsers$PackratReader$$anon$3.scala$util$parsing$combinator$PackratParsers$$lrStack_$eq:(Lscala/collection/immutable/List;)V
Asciz	this;
Asciz	Lscala/util/parsing/combinator/PackratParsers$PackratReader$$anon$3;;
Asciz	$outer;
Asciz	Lscala/util/parsing/combinator/PackratParsers$PackratReader;;
Asciz	LocalVariableTable;
Asciz	(Lscala/util/parsing/combinator/PackratParsers$PackratReader<TT;>;)V;
Asciz	Signature;
Asciz	Lscala/util/parsing/combinator/PackratParsers$PackratReader<TT;>;;
Asciz	Scala;
Asciz	InnerClasses;
Asciz	scala/util/parsing/combinator/PackratParsers;
class	scala/util/parsing/combinator/PackratParsers
Asciz	PackratReader;
Asciz	$anon$3;

{
private final scala.collection.mutable.HashMap scala$util$parsing$combinator$PackratParsers$$recursionHeads;
  Signature: Lscala/collection/mutable/HashMap;

private final scala.collection.mutable.HashMap scala$util$parsing$combinator$PackratParsers$$cache;
  Signature: Lscala/collection/mutable/HashMap;

public scala.collection.mutable.HashMap scala$util$parsing$combinator$PackratParsers$$cache();
  Signature: ()Lscala/collection/mutable/HashMap;
  Code:
   Stack=1, Locals=1, Args_size=1
	aload_0
	getfield	Field scala$util$parsing$combinator$PackratParsers$$cache:Lscala/collection/mutable/HashMap;
	areturn
  Labels:

public scala.collection.mutable.HashMap scala$util$parsing$combinator$PackratParsers$$recursionHeads();
  Signature: ()Lscala/collection/mutable/HashMap;
  Code:
   Stack=1, Locals=1, Args_size=1
	aload_0
	getfield	Field scala$util$parsing$combinator$PackratParsers$$recursionHeads:Lscala/collection/mutable/HashMap;
	areturn
  Labels:

public scala.util.parsing.combinator.PackratParsers$PackratReader$$anon$3(scala.util.parsing.combinator.PackratParsers$PackratReader);
  Signature: (Lscala/util/parsing/combinator/PackratParsers$PackratReader;)V
  Code:
   Stack=3, Locals=2, Args_size=2
	aload_0
	aload_1
	invokevirtual	Method scala/util/parsing/combinator/PackratParsers$PackratReader.scala$util$parsing$combinator$PackratParsers$PackratReader$$$outer:()Lscala/util/parsing/combinator/PackratParsers;
	aload_1
	getfield	Field scala/util/parsing/combinator/PackratParsers$PackratReader.scala$util$parsing$combinator$PackratParsers$PackratReader$$underlying:Lscala/util/parsing/input/Reader;
	invokevirtual	Method scala/util/parsing/input/Reader.rest:()Lscala/util/parsing/input/Reader;
	invokespecial	Method scala/util/parsing/combinator/PackratParsers$PackratReader."<init>":(Lscala/util/parsing/combinator/PackratParsers;Lscala/util/parsing/input/Reader;)V
	aload_0
	aload_1
	invokevirtual	Method scala/util/parsing/combinator/PackratParsers$PackratReader.scala$util$parsing$combinator$PackratParsers$$cache:()Lscala/collection/mutable/HashMap;
	putfield	Field scala$util$parsing$combinator$PackratParsers$$cache:Lscala/collection/mutable/HashMap;
	aload_0
	aload_1
	invokevirtual	Method scala/util/parsing/combinator/PackratParsers$PackratReader.scala$util$parsing$combinator$PackratParsers$$recursionHeads:()Lscala/collection/mutable/HashMap;
	putfield	Field scala$util$parsing$combinator$PackratParsers$$recursionHeads:Lscala/collection/mutable/HashMap;
	aload_0
	aload_1
	invokevirtual	Method scala/util/parsing/combinator/PackratParsers$PackratReader.scala$util$parsing$combinator$PackratParsers$$lrStack:()Lscala/collection/immutable/List;
	invokevirtual	Method scala$util$parsing$combinator$PackratParsers$$lrStack_$eq:(Lscala/collection/immutable/List;)V
	return
  Labels:
  LocalVariableTable: 
   Start  Length  Slot  Name   Signature
   0      40      0    this       Lscala/util/parsing/combinator/PackratParsers$PackratReader$$anon$3;
   0      40      1    $outer       Lscala/util/parsing/combinator/PackratParsers$PackratReader;

  Signature: length = 0x2
   00 35 

}

