Compiled from "PackratParsers.scala"
public final class scala.util.parsing.combinator.PackratParsers$$anonfun$scala$util$parsing$combinator$PackratParsers$$recall$1 extends scala.runtime.AbstractFunction1 implements java.io.Serializable
  SourceFile: "PackratParsers.scala"
  Scala: length = 0x
   
  InnerClass: 
   public abstract Parser=class scala/util/parsing/combinator/Parsers$Parser of class scala/util/parsing/combinator/Parsers
   public final $anonfun$scala$util$parsing$combinator$PackratParsers$$recall$1=class scala/util/parsing/combinator/PackratParsers$$anonfun$scala$util$parsing$combinator$PackratParsers$$recall$1 of class scala/util/parsing/combinator/PackratParsers
  minor version: 0
  major version: 49
  Constant pool:
Asciz	SourceFile;
Asciz	PackratParsers.scala;
Asciz	<clinit>;
Asciz	()V;
Asciz	Code;
Asciz	serialVersionUID;
Asciz	J;
Asciz	scala/util/parsing/combinator/PackratParsers$$anonfun$scala$util$parsing$combinator$PackratParsers$$recall$1;
class	scala/util/parsing/combinator/PackratParsers$$anonfun$scala$util$parsing$combinator$PackratParsers$$recall$1
NameAndType	serialVersionUID:J
Field	scala/util/parsing/combinator/PackratParsers$$anonfun$scala$util$parsing$combinator$PackratParsers$$recall$1.serialVersionUID:J
Asciz	p$3;
Asciz	Lscala/util/parsing/combinator/Parsers$Parser;;
Asciz	apply;
Asciz	(Lscala/util/parsing/combinator/Parsers$Parser;)Z;
Asciz	LineNumberTable;
NameAndType	p$3:Lscala/util/parsing/combinator/Parsers$Parser;
Field	scala/util/parsing/combinator/PackratParsers$$anonfun$scala$util$parsing$combinator$PackratParsers$$recall$1.p$3:Lscala/util/parsing/combinator/Parsers$Parser;
Asciz	java/lang/Object;
class	java/lang/Object
Asciz	equals;
Asciz	(Ljava/lang/Object;)Z;
NameAndType	equals:(Ljava/lang/Object;)Z
Method	java/lang/Object.equals:(Ljava/lang/Object;)Z
Asciz	(Lscala/util/parsing/combinator/Parsers$Parser<*>;)Z;
Asciz	Signature;
Asciz	(Ljava/lang/Object;)Ljava/lang/Object;;
Asciz	scala/util/parsing/combinator/Parsers$Parser;
class	scala/util/parsing/combinator/Parsers$Parser
NameAndType	apply:(Lscala/util/parsing/combinator/Parsers$Parser;)Z
Method	scala/util/parsing/combinator/PackratParsers$$anonfun$scala$util$parsing$combinator$PackratParsers$$recall$1.apply:(Lscala/util/parsing/combinator/Parsers$Parser;)Z
Asciz	scala/runtime/BoxesRunTime;
class	scala/runtime/BoxesRunTime
Asciz	boxToBoolean;
Asciz	(Z)Ljava/lang/Boolean;;
NameAndType	boxToBoolean:(Z)Ljava/lang/Boolean;
Method	scala/runtime/BoxesRunTime.boxToBoolean:(Z)Ljava/lang/Boolean;
Asciz	this;
Asciz	Lscala/util/parsing/combinator/PackratParsers$$anonfun$scala$util$parsing$combinator$PackratParsers$$recall$1;;
Asciz	v1;
Asciz	Ljava/lang/Object;;
Asciz	LocalVariableTable;
Asciz	<init>;
Asciz	(Lscala/util/parsing/combinator/PackratParsers;Lscala/util/parsing/combinator/Parsers$Parser;)V;
Asciz	scala/runtime/AbstractFunction1;
class	scala/runtime/AbstractFunction1
NameAndType	"<init>":()V
Method	scala/runtime/AbstractFunction1."<init>":()V
Asciz	$outer;
Asciz	Lscala/util/parsing/combinator/PackratParsers;;
Asciz	Scala;
Asciz	InnerClasses;
Asciz	scala/util/parsing/combinator/Parsers;
class	scala/util/parsing/combinator/Parsers
Asciz	Parser;
Asciz	scala/util/parsing/combinator/PackratParsers;
class	scala/util/parsing/combinator/PackratParsers
Asciz	$anonfun$scala$util$parsing$combinator$PackratParsers$$recall$1;
Asciz	java/io/Serializable;
class	java/io/Serializable

{
public static final long serialVersionUID;
  Signature: J

private final scala.util.parsing.combinator.Parsers$Parser p$3;
  Signature: Lscala/util/parsing/combinator/Parsers$Parser;

public static {};
  Signature: ()V
  Code:
   Stack=2, Locals=0, Args_size=0
	lconst_0
	putstatic	Field serialVersionUID:J
	return
  Labels:

public final boolean apply(scala.util.parsing.combinator.Parsers$Parser);
  Signature: (Lscala/util/parsing/combinator/Parsers$Parser;)Z
  Code:
   Stack=2, Locals=3, Args_size=2
	aload_1
	aload_0
	getfield	Field p$3:Lscala/util/parsing/combinator/Parsers$Parser;
	astore_2
	dup
	ifnonnull	l1 // aload_2
	pop
	aload_2
	ifnull	l2 // iconst_1
	goto	l3 // iconst_0
l1	aload_2
	invokevirtual	Method java/lang/Object.equals:(Ljava/lang/Object;)Z
	ifeq	l3 // iconst_0
l2	iconst_1
	goto	l4 // ireturn
l3	iconst_0
l4	ireturn
  Labels:
   	l1 = 18 // aload_2
   	l2 = 25 // iconst_1
   	l3 = 29 // iconst_0
   	l4 = 30 // ireturn
  Signature: length = 0x2
   00 19 

public final java.lang.Object apply(java.lang.Object);
  Signature: (Ljava/lang/Object;)Ljava/lang/Object;
  Code:
   Stack=2, Locals=2, Args_size=2
	aload_0
	aload_1
	checkcast	class scala/util/parsing/combinator/Parsers$Parser
	invokevirtual	Method apply:(Lscala/util/parsing/combinator/Parsers$Parser;)Z
	invokestatic	Method scala/runtime/BoxesRunTime.boxToBoolean:(Z)Ljava/lang/Boolean;
	areturn
  Labels:
  LocalVariableTable: 
   Start  Length  Slot  Name   Signature
   0      12      0    this       Lscala/util/parsing/combinator/PackratParsers$$anonfun$scala$util$parsing$combinator$PackratParsers$$recall$1;
   0      12      1    v1       Ljava/lang/Object;


public scala.util.parsing.combinator.PackratParsers$$anonfun$scala$util$parsing$combinator$PackratParsers$$recall$1(scala.util.parsing.combinator.PackratParsers, scala.util.parsing.combinator.Parsers$Parser);
  Signature: (Lscala/util/parsing/combinator/PackratParsers;Lscala/util/parsing/combinator/Parsers$Parser;)V
  Code:
   Stack=2, Locals=3, Args_size=3
	aload_0
	aload_2
	putfield	Field p$3:Lscala/util/parsing/combinator/Parsers$Parser;
	aload_0
	invokespecial	Method scala/runtime/AbstractFunction1."<init>":()V
	return
  Labels:
  LocalVariableTable: 
   Start  Length  Slot  Name   Signature
   0      10      0    this       Lscala/util/parsing/combinator/PackratParsers$$anonfun$scala$util$parsing$combinator$PackratParsers$$recall$1;
   0      10      1    $outer       Lscala/util/parsing/combinator/PackratParsers;


}

