Compiled from "PackratParsers.scala"
public final class scala.util.parsing.combinator.PackratParsers$$anon$1 extends scala.util.parsing.combinator.PackratParsers$PackratParser
  SourceFile: "PackratParsers.scala"
  Signature: length = 0x2
   00 42 
  Scala: length = 0x
   
  InnerClass: 
   public abstract Parser=class scala/util/parsing/combinator/Parsers$Parser of class scala/util/parsing/combinator/Parsers
   public abstract ParseResult=class scala/util/parsing/combinator/Parsers$ParseResult of class scala/util/parsing/combinator/Parsers
   public final $anon$1=class scala/util/parsing/combinator/PackratParsers$$anon$1 of class scala/util/parsing/combinator/PackratParsers
   public PackratReader=class scala/util/parsing/combinator/PackratParsers$PackratReader of class scala/util/parsing/combinator/PackratParsers
   public abstract PackratParser=class scala/util/parsing/combinator/PackratParsers$PackratParser of class scala/util/parsing/combinator/PackratParsers
  minor version: 0
  major version: 49
  Constant pool:
Asciz	SourceFile;
Asciz	PackratParsers.scala;
Asciz	q$1;
Asciz	Lscala/util/parsing/combinator/Parsers$Parser;;
Asciz	$outer;
Asciz	Lscala/util/parsing/combinator/PackratParsers;;
Asciz	<init>;
Asciz	(Lscala/util/parsing/combinator/PackratParsers;Lscala/util/parsing/combinator/Parsers$Parser;)V;
Asciz	Code;
Asciz	LineNumberTable;
Asciz	java/lang/NullPointerException;
class	java/lang/NullPointerException
Asciz	()V;
NameAndType	"<init>":()V
Method	java/lang/NullPointerException."<init>":()V
Asciz	scala/util/parsing/combinator/PackratParsers$$anon$1;
class	scala/util/parsing/combinator/PackratParsers$$anon$1
NameAndType	$outer:Lscala/util/parsing/combinator/PackratParsers;
Field	scala/util/parsing/combinator/PackratParsers$$anon$1.$outer:Lscala/util/parsing/combinator/PackratParsers;
NameAndType	q$1:Lscala/util/parsing/combinator/Parsers$Parser;
Field	scala/util/parsing/combinator/PackratParsers$$anon$1.q$1:Lscala/util/parsing/combinator/Parsers$Parser;
Asciz	scala/util/parsing/combinator/PackratParsers$PackratParser;
class	scala/util/parsing/combinator/PackratParsers$PackratParser
Asciz	(Lscala/util/parsing/combinator/PackratParsers;)V;
NameAndType	"<init>":(Lscala/util/parsing/combinator/PackratParsers;)V
Method	scala/util/parsing/combinator/PackratParsers$PackratParser."<init>":(Lscala/util/parsing/combinator/PackratParsers;)V
Asciz	this;
Asciz	Lscala/util/parsing/combinator/PackratParsers$$anon$1;;
Asciz	LocalVariableTable;
Asciz	apply;
Asciz	(Ljava/lang/Object;)Ljava/lang/Object;;
Asciz	scala/util/parsing/input/Reader;
class	scala/util/parsing/input/Reader
Asciz	(Lscala/util/parsing/input/Reader;)Lscala/util/parsing/combinator/Parsers$ParseResult;;
NameAndType	apply:(Lscala/util/parsing/input/Reader;)Lscala/util/parsing/combinator/Parsers$ParseResult;
Method	scala/util/parsing/combinator/PackratParsers$$anon$1.apply:(Lscala/util/parsing/input/Reader;)Lscala/util/parsing/combinator/Parsers$ParseResult;
Asciz	v1;
Asciz	Ljava/lang/Object;;
Asciz	scala/util/parsing/combinator/PackratParsers$PackratReader;
class	scala/util/parsing/combinator/PackratParsers$PackratReader
Asciz	scala$util$parsing$combinator$PackratParsers$PackratReader$$$outer;
Asciz	()Lscala/util/parsing/combinator/PackratParsers;;
NameAndType	scala$util$parsing$combinator$PackratParsers$PackratReader$$$outer:()Lscala/util/parsing/combinator/PackratParsers;
Method	scala/util/parsing/combinator/PackratParsers$PackratReader.scala$util$parsing$combinator$PackratParsers$PackratReader$$$outer:()Lscala/util/parsing/combinator/PackratParsers;
Asciz	scala/util/parsing/combinator/Parsers$Parser;
class	scala/util/parsing/combinator/Parsers$Parser
Method	scala/util/parsing/combinator/Parsers$Parser.apply:(Lscala/util/parsing/input/Reader;)Lscala/util/parsing/combinator/Parsers$ParseResult;
Asciz	scala/MatchError;
class	scala/MatchError
Asciz	toString;
Asciz	()Ljava/lang/String;;
NameAndType	toString:()Ljava/lang/String;
Method	scala/util/parsing/input/Reader.toString:()Ljava/lang/String;
Asciz	(Ljava/lang/String;)V;
NameAndType	"<init>":(Ljava/lang/String;)V
Method	scala/MatchError."<init>":(Ljava/lang/String;)V
Asciz	(Lscala/util/parsing/combinator/PackratParsers;Lscala/util/parsing/input/Reader;)V;
NameAndType	"<init>":(Lscala/util/parsing/combinator/PackratParsers;Lscala/util/parsing/input/Reader;)V
Method	scala/util/parsing/combinator/PackratParsers$PackratReader."<init>":(Lscala/util/parsing/combinator/PackratParsers;Lscala/util/parsing/input/Reader;)V
Asciz	in;
Asciz	Lscala/util/parsing/input/Reader;;
Asciz	temp2;
Asciz	Lscala/util/parsing/combinator/PackratParsers$PackratReader;;
Asciz	(Lscala/util/parsing/input/Reader<Ljava/lang/Object;>;)Lscala/util/parsing/combinator/Parsers$ParseResult<TT;>;;
Asciz	Signature;
Asciz	Lscala/util/parsing/combinator/PackratParsers$PackratParser<TT;>;;
Asciz	Scala;
Asciz	InnerClasses;
Asciz	scala/util/parsing/combinator/Parsers;
class	scala/util/parsing/combinator/Parsers
Asciz	Parser;
Asciz	scala/util/parsing/combinator/Parsers$ParseResult;
class	scala/util/parsing/combinator/Parsers$ParseResult
Asciz	ParseResult;
Asciz	scala/util/parsing/combinator/PackratParsers;
class	scala/util/parsing/combinator/PackratParsers
Asciz	$anon$1;
Asciz	PackratReader;
Asciz	PackratParser;

{
private final scala.util.parsing.combinator.Parsers$Parser q$1;
  Signature: Lscala/util/parsing/combinator/Parsers$Parser;

private final scala.util.parsing.combinator.PackratParsers $outer;
  Signature: Lscala/util/parsing/combinator/PackratParsers;

public scala.util.parsing.combinator.PackratParsers$$anon$1(scala.util.parsing.combinator.PackratParsers, scala.util.parsing.combinator.Parsers$Parser);
  Signature: (Lscala/util/parsing/combinator/PackratParsers;Lscala/util/parsing/combinator/Parsers$Parser;)V
  Code:
   Stack=2, Locals=3, Args_size=3
	aload_1
	ifnonnull	l1 // aload_0
	new	class java/lang/NullPointerException
	dup
	invokespecial	Method java/lang/NullPointerException."<init>":()V
	athrow
l1	aload_0
	aload_1
	putfield	Field $outer:Lscala/util/parsing/combinator/PackratParsers;
	aload_0
	aload_2
	putfield	Field q$1:Lscala/util/parsing/combinator/Parsers$Parser;
	aload_0
	aload_1
	invokespecial	Method scala/util/parsing/combinator/PackratParsers$PackratParser."<init>":(Lscala/util/parsing/combinator/PackratParsers;)V
	return
  Labels:
   	l1 = 12 // aload_0
  LocalVariableTable: 
   Start  Length  Slot  Name   Signature
   0      28      0    this       Lscala/util/parsing/combinator/PackratParsers$$anon$1;
   0      28      1    $outer       Lscala/util/parsing/combinator/PackratParsers;


public java.lang.Object apply(java.lang.Object);
  Signature: (Ljava/lang/Object;)Ljava/lang/Object;
  Code:
   Stack=2, Locals=2, Args_size=2
	aload_0
	aload_1
	checkcast	class scala/util/parsing/input/Reader
	invokevirtual	Method apply:(Lscala/util/parsing/input/Reader;)Lscala/util/parsing/combinator/Parsers$ParseResult;
	areturn
  Labels:
  LocalVariableTable: 
   Start  Length  Slot  Name   Signature
   0      9      0    this       Lscala/util/parsing/combinator/PackratParsers$$anon$1;
   0      9      1    v1       Ljava/lang/Object;


public scala.util.parsing.combinator.Parsers$ParseResult apply(scala.util.parsing.input.Reader);
  Signature: (Lscala/util/parsing/input/Reader;)Lscala/util/parsing/combinator/Parsers$ParseResult;
  Code:
   Stack=5, Locals=3, Args_size=2
	aload_1
	instanceof	class scala/util/parsing/combinator/PackratParsers$PackratReader
	ifeq	l1 // iconst_1
	aload_1
	checkcast	class scala/util/parsing/combinator/PackratParsers$PackratReader
	invokevirtual	Method scala/util/parsing/combinator/PackratParsers$PackratReader.scala$util$parsing$combinator$PackratParsers$PackratReader$$$outer:()Lscala/util/parsing/combinator/PackratParsers;
	aload_0
	getfield	Field $outer:Lscala/util/parsing/combinator/PackratParsers;
	if_acmpne	l1 // iconst_1
	aload_1
	checkcast	class scala/util/parsing/combinator/PackratParsers$PackratReader
	astore_2
	iconst_1
	ifeq	l2 // new
	aload_0
	getfield	Field q$1:Lscala/util/parsing/combinator/Parsers$Parser;
	aload_2
	invokevirtual	Method scala/util/parsing/combinator/Parsers$Parser.apply:(Lscala/util/parsing/input/Reader;)Lscala/util/parsing/combinator/Parsers$ParseResult;
	goto	l3 // areturn
l2	new	class scala/MatchError
	dup
	aload_1
	invokevirtual	Method scala/util/parsing/input/Reader.toString:()Ljava/lang/String;
	invokespecial	Method scala/MatchError."<init>":(Ljava/lang/String;)V
	athrow
l1	iconst_1
	ifeq	l4 // new
	aload_0
	getfield	Field q$1:Lscala/util/parsing/combinator/Parsers$Parser;
	new	class scala/util/parsing/combinator/PackratParsers$PackratReader
	dup
	aload_0
	getfield	Field $outer:Lscala/util/parsing/combinator/PackratParsers;
	aload_1
	invokespecial	Method scala/util/parsing/combinator/PackratParsers$PackratReader."<init>":(Lscala/util/parsing/combinator/PackratParsers;Lscala/util/parsing/input/Reader;)V
	invokevirtual	Method scala/util/parsing/combinator/Parsers$Parser.apply:(Lscala/util/parsing/input/Reader;)Lscala/util/parsing/combinator/Parsers$ParseResult;
l3	areturn
l4	new	class scala/MatchError
	dup
	aload_1
	invokevirtual	Method scala/util/parsing/input/Reader.toString:()Ljava/lang/String;
	invokespecial	Method scala/MatchError."<init>":(Ljava/lang/String;)V
	athrow
  Labels:
   	l2 = 41 // new
   	l1 = 53 // iconst_1
   	l3 = 76 // areturn
   	l4 = 77 // new
  LocalVariableTable: 
   Start  Length  Slot  Name   Signature
   0      89      0    this       Lscala/util/parsing/combinator/PackratParsers$$anon$1;
   0      89      1    in       Lscala/util/parsing/input/Reader;
   26      27      2    temp2       Lscala/util/parsing/combinator/PackratParsers$PackratReader;

  Signature: length = 0x2
   00 40 

}

