Compiled from "PackratParsers.scala"
public final class scala.util.parsing.combinator.PackratParsers$$anonfun$scala$util$parsing$combinator$PackratParsers$$setupLR$2 extends java.lang.Object implements scala.Function1,scala.ScalaObject,java.io.Serializable
  SourceFile: "PackratParsers.scala"
  Scala: length = 0x
   
  InnerClass: 
   public LR=class scala/util/parsing/combinator/PackratParsers$LR of class scala/util/parsing/combinator/PackratParsers
   public final $anonfun$scala$util$parsing$combinator$PackratParsers$$setupLR$2=class scala/util/parsing/combinator/PackratParsers$$anonfun$scala$util$parsing$combinator$PackratParsers$$setupLR$2 of class scala/util/parsing/combinator/PackratParsers
   public final $anonfun$apply$1=class scala/util/parsing/combinator/PackratParsers$$anonfun$scala$util$parsing$combinator$PackratParsers$$setupLR$2$$anonfun$apply$1 of class scala/util/parsing/combinator/PackratParsers$$anonfun$scala$util$parsing$combinator$PackratParsers$$setupLR$2
  minor version: 0
  major version: 49
  Constant pool:
Asciz	SourceFile;
Asciz	PackratParsers.scala;
Asciz	<clinit>;
Asciz	()V;
Asciz	Code;
Asciz	serialVersionUID;
Asciz	J;
Asciz	scala/util/parsing/combinator/PackratParsers$$anonfun$scala$util$parsing$combinator$PackratParsers$$setupLR$2;
class	scala/util/parsing/combinator/PackratParsers$$anonfun$scala$util$parsing$combinator$PackratParsers$$setupLR$2
NameAndType	serialVersionUID:J
Field	scala/util/parsing/combinator/PackratParsers$$anonfun$scala$util$parsing$combinator$PackratParsers$$setupLR$2.serialVersionUID:J
Asciz	recDetect$1;
Asciz	Lscala/util/parsing/combinator/PackratParsers$LR;;
Asciz	<init>;
Asciz	(Lscala/util/parsing/combinator/PackratParsers;Lscala/util/parsing/combinator/PackratParsers$LR;)V;
Asciz	LineNumberTable;
NameAndType	recDetect$1:Lscala/util/parsing/combinator/PackratParsers$LR;
Field	scala/util/parsing/combinator/PackratParsers$$anonfun$scala$util$parsing$combinator$PackratParsers$$setupLR$2.recDetect$1:Lscala/util/parsing/combinator/PackratParsers$LR;
Asciz	java/lang/Object;
class	java/lang/Object
NameAndType	"<init>":()V
Method	java/lang/Object."<init>":()V
Asciz	scala/Function1$class;
class	scala/Function1$class
Asciz	$init$;
Asciz	(Lscala/Function1;)V;
NameAndType	$init$:(Lscala/Function1;)V
Method	scala/Function1$class.$init$:(Lscala/Function1;)V
Asciz	this;
Asciz	Lscala/util/parsing/combinator/PackratParsers$$anonfun$scala$util$parsing$combinator$PackratParsers$$setupLR$2;;
Asciz	$outer;
Asciz	Lscala/util/parsing/combinator/PackratParsers;;
Asciz	LocalVariableTable;
Asciz	apply;
Asciz	(Ljava/lang/Object;)Ljava/lang/Object;;
Asciz	scala/util/parsing/combinator/PackratParsers$LR;
class	scala/util/parsing/combinator/PackratParsers$LR
Asciz	(Lscala/util/parsing/combinator/PackratParsers$LR;)Lscala/Option;;
NameAndType	apply:(Lscala/util/parsing/combinator/PackratParsers$LR;)Lscala/Option;
Method	scala/util/parsing/combinator/PackratParsers$$anonfun$scala$util$parsing$combinator$PackratParsers$$setupLR$2.apply:(Lscala/util/parsing/combinator/PackratParsers$LR;)Lscala/Option;
Asciz	v1;
Asciz	Ljava/lang/Object;;
Asciz	head;
Asciz	()Lscala/Option;;
NameAndType	head:()Lscala/Option;
Method	scala/util/parsing/combinator/PackratParsers$LR.head:()Lscala/Option;
Asciz	head_$eq;
Asciz	(Lscala/Option;)V;
NameAndType	head_$eq:(Lscala/Option;)V
Method	scala/util/parsing/combinator/PackratParsers$LR.head_$eq:(Lscala/Option;)V
Asciz	scala/util/parsing/combinator/PackratParsers$$anonfun$scala$util$parsing$combinator$PackratParsers$$setupLR$2$$anonfun$apply$1;
class	scala/util/parsing/combinator/PackratParsers$$anonfun$scala$util$parsing$combinator$PackratParsers$$setupLR$2$$anonfun$apply$1
Asciz	(Lscala/util/parsing/combinator/PackratParsers$$anonfun$scala$util$parsing$combinator$PackratParsers$$setupLR$2;Lscala/util/parsing/combinator/PackratParsers$LR;)V;
NameAndType	"<init>":(Lscala/util/parsing/combinator/PackratParsers$$anonfun$scala$util$parsing$combinator$PackratParsers$$setupLR$2;Lscala/util/parsing/combinator/PackratParsers$LR;)V
Method	scala/util/parsing/combinator/PackratParsers$$anonfun$scala$util$parsing$combinator$PackratParsers$$setupLR$2$$anonfun$apply$1."<init>":(Lscala/util/parsing/combinator/PackratParsers$$anonfun$scala$util$parsing$combinator$PackratParsers$$setupLR$2;Lscala/util/parsing/combinator/PackratParsers$LR;)V
Asciz	scala/Option;
class	scala/Option
Asciz	map;
Asciz	(Lscala/Function1;)Lscala/Option;;
NameAndType	map:(Lscala/Function1;)Lscala/Option;
Method	scala/Option.map:(Lscala/Function1;)Lscala/Option;
Asciz	x$6;
Asciz	(Lscala/util/parsing/combinator/PackratParsers$LR;)Lscala/Option<Ljava/lang/Object;>;;
Asciz	Signature;
Asciz	andThen;
Asciz	(Lscala/Function1;)Lscala/Function1;;
Asciz	(Lscala/Function1;Lscala/Function1;)Lscala/Function1;;
NameAndType	andThen:(Lscala/Function1;Lscala/Function1;)Lscala/Function1;
Method	scala/Function1$class.andThen:(Lscala/Function1;Lscala/Function1;)Lscala/Function1;
Asciz	g;
Asciz	Lscala/Function1;;
Asciz	compose;
NameAndType	compose:(Lscala/Function1;Lscala/Function1;)Lscala/Function1;
Method	scala/Function1$class.compose:(Lscala/Function1;Lscala/Function1;)Lscala/Function1;
Asciz	toString;
Asciz	()Ljava/lang/String;;
Asciz	(Lscala/Function1;)Ljava/lang/String;;
NameAndType	toString:(Lscala/Function1;)Ljava/lang/String;
Method	scala/Function1$class.toString:(Lscala/Function1;)Ljava/lang/String;
Asciz	Scala;
Asciz	InnerClasses;
Asciz	scala/util/parsing/combinator/PackratParsers;
class	scala/util/parsing/combinator/PackratParsers
Asciz	LR;
Asciz	$anonfun$scala$util$parsing$combinator$PackratParsers$$setupLR$2;
Asciz	$anonfun$apply$1;
Asciz	scala/Function1;
class	scala/Function1
Asciz	scala/ScalaObject;
class	scala/ScalaObject
Asciz	java/io/Serializable;
class	java/io/Serializable

{
public static final long serialVersionUID;
  Signature: J

private final scala.util.parsing.combinator.PackratParsers$LR recDetect$1;
  Signature: Lscala/util/parsing/combinator/PackratParsers$LR;

public static {};
  Signature: ()V
  Code:
   Stack=2, Locals=0, Args_size=0
	lconst_0
	putstatic	Field serialVersionUID:J
	return
  Labels:

public scala.util.parsing.combinator.PackratParsers$$anonfun$scala$util$parsing$combinator$PackratParsers$$setupLR$2(scala.util.parsing.combinator.PackratParsers, scala.util.parsing.combinator.PackratParsers$LR);
  Signature: (Lscala/util/parsing/combinator/PackratParsers;Lscala/util/parsing/combinator/PackratParsers$LR;)V
  Code:
   Stack=2, Locals=3, Args_size=3
	aload_0
	aload_2
	putfield	Field recDetect$1:Lscala/util/parsing/combinator/PackratParsers$LR;
	aload_0
	invokespecial	Method java/lang/Object."<init>":()V
	aload_0
	invokestatic	Method scala/Function1$class.$init$:(Lscala/Function1;)V
	return
  Labels:
  LocalVariableTable: 
   Start  Length  Slot  Name   Signature
   0      14      0    this       Lscala/util/parsing/combinator/PackratParsers$$anonfun$scala$util$parsing$combinator$PackratParsers$$setupLR$2;
   0      14      1    $outer       Lscala/util/parsing/combinator/PackratParsers;


public final java.lang.Object apply(java.lang.Object);
  Signature: (Ljava/lang/Object;)Ljava/lang/Object;
  Code:
   Stack=2, Locals=2, Args_size=2
	aload_0
	aload_1
	checkcast	class scala/util/parsing/combinator/PackratParsers$LR
	invokevirtual	Method apply:(Lscala/util/parsing/combinator/PackratParsers$LR;)Lscala/Option;
	areturn
  Labels:
  LocalVariableTable: 
   Start  Length  Slot  Name   Signature
   0      9      0    this       Lscala/util/parsing/combinator/PackratParsers$$anonfun$scala$util$parsing$combinator$PackratParsers$$setupLR$2;
   0      9      1    v1       Ljava/lang/Object;


public final scala.Option apply(scala.util.parsing.combinator.PackratParsers$LR);
  Signature: (Lscala/util/parsing/combinator/PackratParsers$LR;)Lscala/Option;
  Code:
   Stack=5, Locals=2, Args_size=2
	aload_1
	aload_0
	getfield	Field recDetect$1:Lscala/util/parsing/combinator/PackratParsers$LR;
	invokevirtual	Method scala/util/parsing/combinator/PackratParsers$LR.head:()Lscala/Option;
	invokevirtual	Method scala/util/parsing/combinator/PackratParsers$LR.head_$eq:(Lscala/Option;)V
	aload_0
	getfield	Field recDetect$1:Lscala/util/parsing/combinator/PackratParsers$LR;
	invokevirtual	Method scala/util/parsing/combinator/PackratParsers$LR.head:()Lscala/Option;
	new	class scala/util/parsing/combinator/PackratParsers$$anonfun$scala$util$parsing$combinator$PackratParsers$$setupLR$2$$anonfun$apply$1
	dup
	aload_0
	aload_1
	invokespecial	Method scala/util/parsing/combinator/PackratParsers$$anonfun$scala$util$parsing$combinator$PackratParsers$$setupLR$2$$anonfun$apply$1."<init>":(Lscala/util/parsing/combinator/PackratParsers$$anonfun$scala$util$parsing$combinator$PackratParsers$$setupLR$2;Lscala/util/parsing/combinator/PackratParsers$LR;)V
	invokevirtual	Method scala/Option.map:(Lscala/Function1;)Lscala/Option;
	areturn
  Labels:
  LocalVariableTable: 
   Start  Length  Slot  Name   Signature
   0      31      0    this       Lscala/util/parsing/combinator/PackratParsers$$anonfun$scala$util$parsing$combinator$PackratParsers$$setupLR$2;
   0      31      1    x$6       Lscala/util/parsing/combinator/PackratParsers$LR;

  Signature: length = 0x2
   00 3F 

public scala.Function1 andThen(scala.Function1);
  Signature: (Lscala/Function1;)Lscala/Function1;
  Code:
   Stack=2, Locals=2, Args_size=2
	aload_0
	aload_1
	invokestatic	Method scala/Function1$class.andThen:(Lscala/Function1;Lscala/Function1;)Lscala/Function1;
	areturn
  Labels:
  LocalVariableTable: 
   Start  Length  Slot  Name   Signature
   0      6      0    this       Lscala/util/parsing/combinator/PackratParsers$$anonfun$scala$util$parsing$combinator$PackratParsers$$setupLR$2;
   0      6      1    g       Lscala/Function1;


public scala.Function1 compose(scala.Function1);
  Signature: (Lscala/Function1;)Lscala/Function1;
  Code:
   Stack=2, Locals=2, Args_size=2
	aload_0
	aload_1
	invokestatic	Method scala/Function1$class.compose:(Lscala/Function1;Lscala/Function1;)Lscala/Function1;
	areturn
  Labels:
  LocalVariableTable: 
   Start  Length  Slot  Name   Signature
   0      6      0    this       Lscala/util/parsing/combinator/PackratParsers$$anonfun$scala$util$parsing$combinator$PackratParsers$$setupLR$2;
   0      6      1    g       Lscala/Function1;


public java.lang.String toString();
  Signature: ()Ljava/lang/String;
  Code:
   Stack=1, Locals=1, Args_size=1
	aload_0
	invokestatic	Method scala/Function1$class.toString:(Lscala/Function1;)Ljava/lang/String;
	areturn
  Labels:

}

