Compiled from "PackratParsers.scala"
public class scala.util.parsing.combinator.PackratParsers$MemoEntry extends java.lang.Object implements scala.ScalaObject,scala.Product,java.io.Serializable
  SourceFile: "PackratParsers.scala"
  Signature: length = 0x2
   00 FFFFFF95 
  Scala: length = 0x
   
  InnerClass: 
   public LR=class scala/util/parsing/combinator/PackratParsers$LR of class scala/util/parsing/combinator/PackratParsers
   public abstract ParseResult=class scala/util/parsing/combinator/Parsers$ParseResult of class scala/util/parsing/combinator/Parsers
   public MemoEntry=class scala/util/parsing/combinator/PackratParsers$MemoEntry of class scala/util/parsing/combinator/PackratParsers
  minor version: 0
  major version: 49
  Constant pool:
Asciz	SourceFile;
Asciz	PackratParsers.scala;
Asciz	$outer;
Asciz	Lscala/util/parsing/combinator/PackratParsers;;
Asciz	r;
Asciz	Lscala/Either;;
Asciz	Lscala/Either<Lscala/util/parsing/combinator/PackratParsers$LR;Lscala/util/parsing/combinator/Parsers$ParseResult<*>;>;;
Asciz	Signature;
Asciz	productIterator;
Asciz	()Lscala/collection/Iterator;;
Asciz	Code;
Asciz	LineNumberTable;
Asciz	scala/Product$class;
class	scala/Product$class
Asciz	(Lscala/Product;)Lscala/collection/Iterator;;
NameAndType	productIterator:(Lscala/Product;)Lscala/collection/Iterator;
Method	scala/Product$class.productIterator:(Lscala/Product;)Lscala/collection/Iterator;
Asciz	productElements;
NameAndType	productElements:(Lscala/Product;)Lscala/collection/Iterator;
Method	scala/Product$class.productElements:(Lscala/Product;)Lscala/collection/Iterator;
Asciz	Deprecated;
Asciz	copy$default$1;
Asciz	()Lscala/Either;;
Asciz	scala/util/parsing/combinator/PackratParsers$MemoEntry;
class	scala/util/parsing/combinator/PackratParsers$MemoEntry
NameAndType	r:()Lscala/Either;
Method	scala/util/parsing/combinator/PackratParsers$MemoEntry.r:()Lscala/Either;
NameAndType	r:Lscala/Either;
Field	scala/util/parsing/combinator/PackratParsers$MemoEntry.r:Lscala/Either;
Asciz	()Lscala/Either<Lscala/util/parsing/combinator/PackratParsers$LR;Lscala/util/parsing/combinator/Parsers$ParseResult<*>;>;;
Asciz	r_$eq;
Asciz	(Lscala/Either;)V;
Asciz	(Lscala/Either<Lscala/util/parsing/combinator/PackratParsers$LR;Lscala/util/parsing/combinator/Parsers$ParseResult<*>;>;)V;
Asciz	getResult;
Asciz	()Lscala/util/parsing/combinator/Parsers$ParseResult;;
Asciz	scala/Left;
class	scala/Left
Asciz	a;
Asciz	Ljava/lang/Object;;
NameAndType	a:Ljava/lang/Object;
Field	scala/Left.a:Ljava/lang/Object;
Asciz	scala/util/parsing/combinator/PackratParsers$LR;
class	scala/util/parsing/combinator/PackratParsers$LR
Asciz	seed;
NameAndType	seed:()Lscala/util/parsing/combinator/Parsers$ParseResult;
Method	scala/util/parsing/combinator/PackratParsers$LR.seed:()Lscala/util/parsing/combinator/Parsers$ParseResult;
Asciz	scala/MatchError;
class	scala/MatchError
Asciz	scala/Either;
class	scala/Either
Asciz	toString;
Asciz	()Ljava/lang/String;;
NameAndType	toString:()Ljava/lang/String;
Method	scala/Either.toString:()Ljava/lang/String;
Asciz	<init>;
Asciz	(Ljava/lang/String;)V;
NameAndType	"<init>":(Ljava/lang/String;)V
Method	scala/MatchError."<init>":(Ljava/lang/String;)V
Asciz	scala/Right;
class	scala/Right
Asciz	b;
NameAndType	b:Ljava/lang/Object;
Field	scala/Right.b:Ljava/lang/Object;
Asciz	scala/util/parsing/combinator/Parsers$ParseResult;
class	scala/util/parsing/combinator/Parsers$ParseResult
Asciz	this;
Asciz	Lscala/util/parsing/combinator/PackratParsers$MemoEntry;;
Asciz	temp4;
Asciz	Lscala/Left;;
Asciz	temp5;
Asciz	Lscala/util/parsing/combinator/PackratParsers$LR;;
Asciz	temp3;
Asciz	LocalVariableTable;
Asciz	()Lscala/util/parsing/combinator/Parsers$ParseResult<TT;>;;
Asciz	copy;
Asciz	(Lscala/Either;)Lscala/util/parsing/combinator/PackratParsers$MemoEntry;;
Asciz	scala$util$parsing$combinator$PackratParsers$MemoEntry$$$outer;
Asciz	()Lscala/util/parsing/combinator/PackratParsers;;
NameAndType	scala$util$parsing$combinator$PackratParsers$MemoEntry$$$outer:()Lscala/util/parsing/combinator/PackratParsers;
Method	scala/util/parsing/combinator/PackratParsers$MemoEntry.scala$util$parsing$combinator$PackratParsers$MemoEntry$$$outer:()Lscala/util/parsing/combinator/PackratParsers;
Asciz	(Lscala/util/parsing/combinator/PackratParsers;Lscala/Either;)V;
NameAndType	"<init>":(Lscala/util/parsing/combinator/PackratParsers;Lscala/Either;)V
Method	scala/util/parsing/combinator/PackratParsers$MemoEntry."<init>":(Lscala/util/parsing/combinator/PackratParsers;Lscala/Either;)V
Asciz	hashCode;
Asciz	()I;
Asciz	scala/runtime/ScalaRunTime$;
class	scala/runtime/ScalaRunTime$
Asciz	MODULE$;
Asciz	Lscala/runtime/ScalaRunTime$;;
NameAndType	MODULE$:Lscala/runtime/ScalaRunTime$;
Field	scala/runtime/ScalaRunTime$.MODULE$:Lscala/runtime/ScalaRunTime$;
Asciz	_hashCode;
Asciz	(Lscala/Product;)I;
NameAndType	_hashCode:(Lscala/Product;)I
Method	scala/runtime/ScalaRunTime$._hashCode:(Lscala/Product;)I
Asciz	_toString;
Asciz	(Lscala/Product;)Ljava/lang/String;;
NameAndType	_toString:(Lscala/Product;)Ljava/lang/String;
Method	scala/runtime/ScalaRunTime$._toString:(Lscala/Product;)Ljava/lang/String;
Asciz	equals;
Asciz	(Ljava/lang/Object;)Z;
Asciz	gd1$1;
Asciz	(Lscala/Either;)Z;
NameAndType	gd1$1:(Lscala/Either;)Z
Method	scala/util/parsing/combinator/PackratParsers$MemoEntry.gd1$1:(Lscala/Either;)Z
Asciz	scala/Equals;
class	scala/Equals
Asciz	canEqual;
NameAndType	canEqual:(Ljava/lang/Object;)Z
InterfaceMethod	scala/Equals.canEqual:(Ljava/lang/Object;)Z
Asciz	temp12;
Asciz	temp13;
Asciz	productPrefix;
Asciz	MemoEntry;
String	MemoEntry
Asciz	productArity;
Asciz	productElement;
Asciz	(I)Ljava/lang/Object;;
Asciz	java/lang/IndexOutOfBoundsException;
class	java/lang/IndexOutOfBoundsException
Asciz	scala/runtime/BoxesRunTime;
class	scala/runtime/BoxesRunTime
Asciz	boxToInteger;
Asciz	(I)Ljava/lang/Integer;;
NameAndType	boxToInteger:(I)Ljava/lang/Integer;
Method	scala/runtime/BoxesRunTime.boxToInteger:(I)Ljava/lang/Integer;
Asciz	java/lang/Object;
class	java/lang/Object
Method	java/lang/Object.toString:()Ljava/lang/String;
Method	java/lang/IndexOutOfBoundsException."<init>":(Ljava/lang/String;)V
Asciz	productElementName;
Asciz	(I)Ljava/lang/String;;
String	r
NameAndType	$outer:Lscala/util/parsing/combinator/PackratParsers;
Field	scala/util/parsing/combinator/PackratParsers$MemoEntry.$outer:Lscala/util/parsing/combinator/PackratParsers;
NameAndType	equals:(Ljava/lang/Object;)Z
Method	java/lang/Object.equals:(Ljava/lang/Object;)Z
Asciz	java/lang/NullPointerException;
class	java/lang/NullPointerException
Asciz	()V;
NameAndType	"<init>":()V
Method	java/lang/NullPointerException."<init>":()V
Method	java/lang/Object."<init>":()V
Asciz	$init$;
Asciz	(Lscala/Product;)V;
NameAndType	$init$:(Lscala/Product;)V
Method	scala/Product$class.$init$:(Lscala/Product;)V
Asciz	(Lscala/util/parsing/combinator/PackratParsers;Lscala/Either<Lscala/util/parsing/combinator/PackratParsers$LR;Lscala/util/parsing/combinator/Parsers$ParseResult<*>;>;)V;
Asciz	<T:Ljava/lang/Object;>Ljava/lang/Object;Lscala/ScalaObject;Lscala/Product;;
Asciz	Scala;
Asciz	InnerClasses;
Asciz	scala/util/parsing/combinator/PackratParsers;
class	scala/util/parsing/combinator/PackratParsers
Asciz	LR;
Asciz	scala/util/parsing/combinator/Parsers;
class	scala/util/parsing/combinator/Parsers
Asciz	ParseResult;
Asciz	scala/ScalaObject;
class	scala/ScalaObject
Asciz	scala/Product;
class	scala/Product
Asciz	java/io/Serializable;
class	java/io/Serializable

{
public final scala.util.parsing.combinator.PackratParsers $outer;
  Signature: Lscala/util/parsing/combinator/PackratParsers;

private scala.Either r;
  Signature: Lscala/Either;
  Signature: length = 0x2
   00 07 

public scala.collection.Iterator productIterator();
  Signature: ()Lscala/collection/Iterator;
  Code:
   Stack=1, Locals=1, Args_size=1
	aload_0
	invokestatic	Method scala/Product$class.productIterator:(Lscala/Product;)Lscala/collection/Iterator;
	areturn
  Labels:

public scala.collection.Iterator productElements();
  Signature: ()Lscala/collection/Iterator;
  Code:
   Stack=1, Locals=1, Args_size=1
	aload_0
	invokestatic	Method scala/Product$class.productElements:(Lscala/Product;)Lscala/collection/Iterator;
	areturn
  Labels:
  Deprecated: true

public scala.Either copy$default$1();
  Signature: ()Lscala/Either;
  Code:
   Stack=1, Locals=1, Args_size=1
	aload_0
	invokevirtual	Method r:()Lscala/Either;
	areturn
  Labels:

public scala.Either r();
  Signature: ()Lscala/Either;
  Code:
   Stack=1, Locals=1, Args_size=1
	aload_0
	getfield	Field r:Lscala/Either;
	areturn
  Labels:
  Signature: length = 0x2
   00 1E 

public void r_$eq(scala.Either);
  Signature: (Lscala/Either;)V
  Code:
   Stack=2, Locals=2, Args_size=2
	aload_0
	aload_1
	putfield	Field r:Lscala/Either;
	return
  Labels:
  Signature: length = 0x2
   00 21 

public scala.util.parsing.combinator.Parsers$ParseResult getResult();
  Signature: ()Lscala/util/parsing/combinator/Parsers$ParseResult;
  Code:
   Stack=3, Locals=5, Args_size=1
	aload_0
	invokevirtual	Method r:()Lscala/Either;
	astore	4
	aload	4
	instanceof	class scala/Left
	ifeq	l1 // aload
	aload	4
	checkcast	class scala/Left
	astore_1
	aload_1
	getfield	Field scala/Left.a:Ljava/lang/Object;
	checkcast	class scala/util/parsing/combinator/PackratParsers$LR
	astore_2
	aload_2
	ifnull	l2 // new
	aload_2
	invokevirtual	Method scala/util/parsing/combinator/PackratParsers$LR.seed:()Lscala/util/parsing/combinator/Parsers$ParseResult;
	goto	l3 // areturn
l2	new	class scala/MatchError
	dup
	aload	4
	invokevirtual	Method scala/Either.toString:()Ljava/lang/String;
	invokespecial	Method scala/MatchError."<init>":(Ljava/lang/String;)V
	athrow
l1	aload	4
	instanceof	class scala/Right
	ifeq	l4 // new
	aload	4
	checkcast	class scala/Right
	astore_3
	aload_3
	getfield	Field scala/Right.b:Ljava/lang/Object;
	checkcast	class scala/util/parsing/combinator/Parsers$ParseResult
l3	areturn
l4	new	class scala/MatchError
	dup
	aload	4
	invokevirtual	Method scala/Either.toString:()Ljava/lang/String;
	invokespecial	Method scala/MatchError."<init>":(Ljava/lang/String;)V
	athrow
  Labels:
   	l2 = 39 // new
   	l1 = 52 // aload
   	l3 = 73 // areturn
   	l4 = 74 // new
  LocalVariableTable: 
   Start  Length  Slot  Name   Signature
   0      87      0    this       Lscala/util/parsing/combinator/PackratParsers$MemoEntry;
   20      32      1    temp4       Lscala/Left;
   28      24      2    temp5       Lscala/util/parsing/combinator/PackratParsers$LR;
   6      81      4    temp3       Lscala/Either;

  Signature: length = 0x2
   00 4A 

public scala.util.parsing.combinator.PackratParsers$MemoEntry copy(scala.Either);
  Signature: (Lscala/Either;)Lscala/util/parsing/combinator/PackratParsers$MemoEntry;
  Code:
   Stack=4, Locals=2, Args_size=2
	new	class scala/util/parsing/combinator/PackratParsers$MemoEntry
	dup
	aload_0
	invokevirtual	Method scala$util$parsing$combinator$PackratParsers$MemoEntry$$$outer:()Lscala/util/parsing/combinator/PackratParsers;
	aload_1
	invokespecial	Method "<init>":(Lscala/util/parsing/combinator/PackratParsers;Lscala/Either;)V
	areturn
  Labels:
  LocalVariableTable: 
   Start  Length  Slot  Name   Signature
   0      13      0    this       Lscala/util/parsing/combinator/PackratParsers$MemoEntry;
   0      13      1    r       Lscala/Either;


public int hashCode();
  Signature: ()I
  Code:
   Stack=2, Locals=1, Args_size=1
	getstatic	Field scala/runtime/ScalaRunTime$.MODULE$:Lscala/runtime/ScalaRunTime$;
	aload_0
	invokevirtual	Method scala/runtime/ScalaRunTime$._hashCode:(Lscala/Product;)I
	ireturn
  Labels:

public java.lang.String toString();
  Signature: ()Ljava/lang/String;
  Code:
   Stack=2, Locals=1, Args_size=1
	getstatic	Field scala/runtime/ScalaRunTime$.MODULE$:Lscala/runtime/ScalaRunTime$;
	aload_0
	invokevirtual	Method scala/runtime/ScalaRunTime$._toString:(Lscala/Product;)Ljava/lang/String;
	areturn
  Labels:

public boolean equals(java.lang.Object);
  Signature: (Ljava/lang/Object;)Z
  Code:
   Stack=2, Locals=4, Args_size=2
	aload_0
	aload_1
	if_acmpeq	l1 // iconst_1
	aload_1
	instanceof	class scala/util/parsing/combinator/PackratParsers$MemoEntry
	ifeq	l2 // iconst_0
	aload_1
	checkcast	class scala/util/parsing/combinator/PackratParsers$MemoEntry
	invokevirtual	Method scala$util$parsing$combinator$PackratParsers$MemoEntry$$$outer:()Lscala/util/parsing/combinator/PackratParsers;
	aload_0
	invokevirtual	Method scala$util$parsing$combinator$PackratParsers$MemoEntry$$$outer:()Lscala/util/parsing/combinator/PackratParsers;
	if_acmpne	l2 // iconst_0
	aload_1
	checkcast	class scala/util/parsing/combinator/PackratParsers$MemoEntry
	astore_2
	aload_2
	invokevirtual	Method r:()Lscala/Either;
	astore_3
	aload_0
	aload_3
	invokespecial	Method gd1$1:(Lscala/Either;)Z
	ifeq	l3 // iconst_0
	aload_1
	checkcast	class scala/util/parsing/combinator/PackratParsers$MemoEntry
	aload_0
	invokeinterface	InterfaceMethod scala/Equals.canEqual:(Ljava/lang/Object;)Z
	goto	l4 // ifeq
l3	iconst_0
	goto	l4 // ifeq
l2	iconst_0
l4	ifeq	l5 // iconst_0
l1	iconst_1
	goto	l6 // ireturn
l5	iconst_0
l6	ireturn
  Labels:
   	l3 = 57 // iconst_0
   	l2 = 61 // iconst_0
   	l4 = 62 // ifeq
   	l1 = 65 // iconst_1
   	l5 = 69 // iconst_0
   	l6 = 70 // ireturn
  LocalVariableTable: 
   Start  Length  Slot  Name   Signature
   0      71      0    this       Lscala/util/parsing/combinator/PackratParsers$MemoEntry;
   31      30      2    temp12       Lscala/util/parsing/combinator/PackratParsers$MemoEntry;
   36      25      3    temp13       Lscala/Either;


public java.lang.String productPrefix();
  Signature: ()Ljava/lang/String;
  Code:
   Stack=1, Locals=1, Args_size=1
	ldc	String MemoEntry
	areturn
  Labels:

public int productArity();
  Signature: ()I
  Code:
   Stack=1, Locals=1, Args_size=1
	iconst_1
	ireturn
  Labels:

public java.lang.Object productElement(int);
  Signature: (I)Ljava/lang/Object;
  Code:
   Stack=3, Locals=2, Args_size=2
	iload_1
	iconst_0
	if_icmpne	l1 // new
	aload_0
	invokevirtual	Method r:()Lscala/Either;
	areturn
l1	new	class java/lang/IndexOutOfBoundsException
	dup
	iload_1
	invokestatic	Method scala/runtime/BoxesRunTime.boxToInteger:(I)Ljava/lang/Integer;
	invokevirtual	Method java/lang/Object.toString:()Ljava/lang/String;
	invokespecial	Method java/lang/IndexOutOfBoundsException."<init>":(Ljava/lang/String;)V
	athrow
  Labels:
   	l1 = 10 // new

public java.lang.String productElementName(int);
  Signature: (I)Ljava/lang/String;
  Code:
   Stack=3, Locals=2, Args_size=2
	iload_1
	iconst_0
	if_icmpne	l1 // new
	ldc	String r
	areturn
l1	new	class java/lang/IndexOutOfBoundsException
	dup
	iload_1
	invokestatic	Method scala/runtime/BoxesRunTime.boxToInteger:(I)Ljava/lang/Integer;
	invokevirtual	Method java/lang/Object.toString:()Ljava/lang/String;
	invokespecial	Method java/lang/IndexOutOfBoundsException."<init>":(Ljava/lang/String;)V
	athrow
  Labels:
   	l1 = 8 // new

public boolean canEqual(java.lang.Object);
  Signature: (Ljava/lang/Object;)Z
  Code:
   Stack=1, Locals=2, Args_size=2
	aload_1
	instanceof	class scala/util/parsing/combinator/PackratParsers$MemoEntry
	ireturn
  Labels:

public scala.util.parsing.combinator.PackratParsers scala$util$parsing$combinator$PackratParsers$MemoEntry$$$outer();
  Signature: ()Lscala/util/parsing/combinator/PackratParsers;
  Code:
   Stack=1, Locals=1, Args_size=1
	aload_0
	getfield	Field $outer:Lscala/util/parsing/combinator/PackratParsers;
	areturn
  Labels:

private final boolean gd1$1(scala.Either);
  Signature: (Lscala/Either;)Z
  Code:
   Stack=2, Locals=3, Args_size=2
	aload_1
	aload_0
	invokevirtual	Method r:()Lscala/Either;
	astore_2
	dup
	ifnonnull	l1 // aload_2
	pop
	aload_2
	ifnull	l2 // iconst_1
	goto	l3 // iconst_0
l1	aload_2
	invokevirtual	Method java/lang/Object.equals:(Ljava/lang/Object;)Z
	ifeq	l3 // iconst_0
l2	iconst_1
	goto	l4 // ireturn
l3	iconst_0
l4	ireturn
  Labels:
   	l1 = 18 // aload_2
   	l2 = 25 // iconst_1
   	l3 = 29 // iconst_0
   	l4 = 30 // ireturn

public scala.util.parsing.combinator.PackratParsers$MemoEntry(scala.util.parsing.combinator.PackratParsers, scala.Either);
  Signature: (Lscala/util/parsing/combinator/PackratParsers;Lscala/Either;)V
  Code:
   Stack=2, Locals=3, Args_size=3
	aload_0
	aload_2
	putfield	Field r:Lscala/Either;
	aload_1
	ifnonnull	l1 // aload_0
	new	class java/lang/NullPointerException
	dup
	invokespecial	Method java/lang/NullPointerException."<init>":()V
	athrow
l1	aload_0
	aload_1
	putfield	Field $outer:Lscala/util/parsing/combinator/PackratParsers;
	aload_0
	invokespecial	Method java/lang/Object."<init>":()V
	aload_0
	invokestatic	Method scala/Product$class.$init$:(Lscala/Product;)V
	return
  Labels:
   	l1 = 17 // aload_0
  LocalVariableTable: 
   Start  Length  Slot  Name   Signature
   0      31      0    this       Lscala/util/parsing/combinator/PackratParsers$MemoEntry;
   0      31      1    $outer       Lscala/util/parsing/combinator/PackratParsers;
   0      31      2    r       Lscala/Either;

  Signature: length = 0x2
   00 FFFFFF94 

}

