Compiled from "PackratParsers.scala"
public final class scala.util.parsing.combinator.PackratParsers$MemoEntry$ extends java.lang.Object implements scala.ScalaObject
  SourceFile: "PackratParsers.scala"
  Scala: length = 0x
   
  InnerClass: 
   public MemoEntry=class scala/util/parsing/combinator/PackratParsers$MemoEntry of class scala/util/parsing/combinator/PackratParsers
  minor version: 0
  major version: 49
  Constant pool:
Asciz	SourceFile;
Asciz	PackratParsers.scala;
Asciz	Scala;
Asciz	$outer;
Asciz	Lscala/util/parsing/combinator/PackratParsers;;
Asciz	unapply;
Asciz	(Lscala/util/parsing/combinator/PackratParsers$MemoEntry;)Lscala/Option;;
Asciz	Code;
Asciz	LineNumberTable;
Asciz	java/lang/Object;
class	java/lang/Object
Asciz	equals;
Asciz	(Ljava/lang/Object;)Z;
NameAndType	equals:(Ljava/lang/Object;)Z
Method	java/lang/Object.equals:(Ljava/lang/Object;)Z
Asciz	scala/None$;
class	scala/None$
Asciz	MODULE$;
Asciz	Lscala/None$;;
NameAndType	MODULE$:Lscala/None$;
Field	scala/None$.MODULE$:Lscala/None$;
Asciz	scala/Some;
class	scala/Some
Asciz	scala/util/parsing/combinator/PackratParsers$MemoEntry;
class	scala/util/parsing/combinator/PackratParsers$MemoEntry
Asciz	r;
Asciz	()Lscala/Either;;
NameAndType	r:()Lscala/Either;
Method	scala/util/parsing/combinator/PackratParsers$MemoEntry.r:()Lscala/Either;
Asciz	<init>;
Asciz	(Ljava/lang/Object;)V;
NameAndType	"<init>":(Ljava/lang/Object;)V
Method	scala/Some."<init>":(Ljava/lang/Object;)V
Asciz	this;
Asciz	Lscala/util/parsing/combinator/PackratParsers$MemoEntry$;;
Asciz	x$0;
Asciz	Lscala/util/parsing/combinator/PackratParsers$MemoEntry;;
Asciz	LocalVariableTable;
Asciz	apply;
Asciz	(Lscala/Either;)Lscala/util/parsing/combinator/PackratParsers$MemoEntry;;
Asciz	scala/util/parsing/combinator/PackratParsers$MemoEntry$;
class	scala/util/parsing/combinator/PackratParsers$MemoEntry$
NameAndType	$outer:Lscala/util/parsing/combinator/PackratParsers;
Field	scala/util/parsing/combinator/PackratParsers$MemoEntry$.$outer:Lscala/util/parsing/combinator/PackratParsers;
Asciz	(Lscala/util/parsing/combinator/PackratParsers;Lscala/Either;)V;
NameAndType	"<init>":(Lscala/util/parsing/combinator/PackratParsers;Lscala/Either;)V
Method	scala/util/parsing/combinator/PackratParsers$MemoEntry."<init>":(Lscala/util/parsing/combinator/PackratParsers;Lscala/Either;)V
Asciz	Lscala/Either;;
Asciz	(Lscala/util/parsing/combinator/PackratParsers;)V;
Asciz	java/lang/NullPointerException;
class	java/lang/NullPointerException
Asciz	()V;
NameAndType	"<init>":()V
Method	java/lang/NullPointerException."<init>":()V
Method	java/lang/Object."<init>":()V
Asciz	InnerClasses;
Asciz	scala/util/parsing/combinator/PackratParsers;
class	scala/util/parsing/combinator/PackratParsers
Asciz	MemoEntry;
Asciz	scala/ScalaObject;
class	scala/ScalaObject

{
private final scala.util.parsing.combinator.PackratParsers $outer;
  Signature: Lscala/util/parsing/combinator/PackratParsers;

public scala.Option unapply(scala.util.parsing.combinator.PackratParsers$MemoEntry);
  Signature: (Lscala/util/parsing/combinator/PackratParsers$MemoEntry;)Lscala/Option;
  Code:
   Stack=3, Locals=2, Args_size=2
	aload_1
	dup
	pop
	ifnull	l1 // getstatic
	aload_1
	aconst_null
	invokevirtual	Method java/lang/Object.equals:(Ljava/lang/Object;)Z
	ifeq	l2 // new
l1	getstatic	Field scala/None$.MODULE$:Lscala/None$;
	goto	l3 // areturn
l2	new	class scala/Some
	dup
	aload_1
	invokevirtual	Method scala/util/parsing/combinator/PackratParsers$MemoEntry.r:()Lscala/Either;
	invokespecial	Method scala/Some."<init>":(Ljava/lang/Object;)V
l3	areturn
  Labels:
   	l1 = 14 // getstatic
   	l2 = 20 // new
   	l3 = 31 // areturn
  LocalVariableTable: 
   Start  Length  Slot  Name   Signature
   0      32      0    this       Lscala/util/parsing/combinator/PackratParsers$MemoEntry$;
   0      32      1    x$0       Lscala/util/parsing/combinator/PackratParsers$MemoEntry;


public scala.util.parsing.combinator.PackratParsers$MemoEntry apply(scala.Either);
  Signature: (Lscala/Either;)Lscala/util/parsing/combinator/PackratParsers$MemoEntry;
  Code:
   Stack=4, Locals=2, Args_size=2
	new	class scala/util/parsing/combinator/PackratParsers$MemoEntry
	dup
	aload_0
	getfield	Field $outer:Lscala/util/parsing/combinator/PackratParsers;
	aload_1
	invokespecial	Method scala/util/parsing/combinator/PackratParsers$MemoEntry."<init>":(Lscala/util/parsing/combinator/PackratParsers;Lscala/Either;)V
	areturn
  Labels:
  LocalVariableTable: 
   Start  Length  Slot  Name   Signature
   0      13      0    this       Lscala/util/parsing/combinator/PackratParsers$MemoEntry$;
   0      13      1    r       Lscala/Either;


public scala.util.parsing.combinator.PackratParsers$MemoEntry$(scala.util.parsing.combinator.PackratParsers);
  Signature: (Lscala/util/parsing/combinator/PackratParsers;)V
  Code:
   Stack=2, Locals=2, Args_size=2
	aload_1
	ifnonnull	l1 // aload_0
	new	class java/lang/NullPointerException
	dup
	invokespecial	Method java/lang/NullPointerException."<init>":()V
	athrow
l1	aload_0
	aload_1
	putfield	Field $outer:Lscala/util/parsing/combinator/PackratParsers;
	aload_0
	invokespecial	Method java/lang/Object."<init>":()V
	return
  Labels:
   	l1 = 12 // aload_0
  LocalVariableTable: 
   Start  Length  Slot  Name   Signature
   0      22      0    this       Lscala/util/parsing/combinator/PackratParsers$MemoEntry$;
   0      22      1    $outer       Lscala/util/parsing/combinator/PackratParsers;


}

