Compiled from "PackratParsers.scala"
public class scala.util.parsing.combinator.PackratParsers$PackratReader extends scala.util.parsing.input.Reader implements scala.ScalaObject
  SourceFile: "PackratParsers.scala"
  Signature: length = 0x2
   00 75 
  Scala: length = 0x
   
  InnerClass: 
   public abstract #124= #121 of #123; //Parser=class scala/util/parsing/combinator/Parsers$Parser of class scala/util/parsing/combinator/Parsers
   public #129= #126 of #128; //MemoEntry=class scala/util/parsing/combinator/PackratParsers$MemoEntry of class scala/util/parsing/combinator/PackratParsers
   public #130= #17 of #128; //PackratReader=class scala/util/parsing/combinator/PackratParsers$PackratReader of class scala/util/parsing/combinator/PackratParsers
   public final #131= #70 of #17; //$anon$3=class scala/util/parsing/combinator/PackratParsers$PackratReader$$anon$3 of class scala/util/parsing/combinator/PackratParsers$PackratReader
  minor version: 0
  major version: 49
  Constant pool:
const #1 = Asciz	SourceFile;
const #2 = Asciz	PackratParsers.scala;
const #3 = Asciz	$outer;
const #4 = Asciz	Lscala/util/parsing/combinator/PackratParsers;;
const #5 = Asciz	scala$util$parsing$combinator$PackratParsers$$lrStack;
const #6 = Asciz	Lscala/collection/immutable/List;;
const #7 = Asciz	scala$util$parsing$combinator$PackratParsers$$recursionHeads;
const #8 = Asciz	Lscala/collection/mutable/HashMap;;
const #9 = Asciz	scala$util$parsing$combinator$PackratParsers$$cache;
const #10 = Asciz	scala$util$parsing$combinator$PackratParsers$PackratReader$$underlying;
const #11 = Asciz	Lscala/util/parsing/input/Reader;;
const #12 = Asciz	<init>;
const #13 = Asciz	(Lscala/util/parsing/combinator/PackratParsers;Lscala/util/parsing/input/Reader;)V;
const #14 = Asciz	Code;
const #15 = Asciz	LineNumberTable;
const #16 = Asciz	scala/util/parsing/combinator/PackratParsers$PackratReader;
const #17 = class	#16;	//  scala/util/parsing/combinator/PackratParsers$PackratReader
const #18 = NameAndType	#10:#11;//  scala$util$parsing$combinator$PackratParsers$PackratReader$$underlying:Lscala/util/parsing/input/Reader;
const #19 = Field	#17.#18;	//  scala/util/parsing/combinator/PackratParsers$PackratReader.scala$util$parsing$combinator$PackratParsers$PackratReader$$underlying:Lscala/util/parsing/input/Reader;
const #20 = Asciz	java/lang/NullPointerException;
const #21 = class	#20;	//  java/lang/NullPointerException
const #22 = Asciz	()V;
const #23 = NameAndType	#12:#22;//  "<init>":()V
const #24 = Method	#21.#23;	//  java/lang/NullPointerException."<init>":()V
const #25 = NameAndType	#3:#4;//  $outer:Lscala/util/parsing/combinator/PackratParsers;
const #26 = Field	#17.#25;	//  scala/util/parsing/combinator/PackratParsers$PackratReader.$outer:Lscala/util/parsing/combinator/PackratParsers;
const #27 = Asciz	scala/util/parsing/input/Reader;
const #28 = class	#27;	//  scala/util/parsing/input/Reader
const #29 = Method	#28.#23;	//  scala/util/parsing/input/Reader."<init>":()V
const #30 = Asciz	scala/collection/mutable/HashMap$;
const #31 = class	#30;	//  scala/collection/mutable/HashMap$
const #32 = Asciz	MODULE$;
const #33 = Asciz	Lscala/collection/mutable/HashMap$;;
const #34 = NameAndType	#32:#33;//  MODULE$:Lscala/collection/mutable/HashMap$;
const #35 = Field	#31.#34;	//  scala/collection/mutable/HashMap$.MODULE$:Lscala/collection/mutable/HashMap$;
const #36 = Asciz	empty;
const #37 = Asciz	()Lscala/collection/mutable/HashMap;;
const #38 = NameAndType	#36:#37;//  empty:()Lscala/collection/mutable/HashMap;
const #39 = Method	#31.#38;	//  scala/collection/mutable/HashMap$.empty:()Lscala/collection/mutable/HashMap;
const #40 = NameAndType	#9:#8;//  scala$util$parsing$combinator$PackratParsers$$cache:Lscala/collection/mutable/HashMap;
const #41 = Field	#17.#40;	//  scala/util/parsing/combinator/PackratParsers$PackratReader.scala$util$parsing$combinator$PackratParsers$$cache:Lscala/collection/mutable/HashMap;
const #42 = NameAndType	#7:#8;//  scala$util$parsing$combinator$PackratParsers$$recursionHeads:Lscala/collection/mutable/HashMap;
const #43 = Field	#17.#42;	//  scala/util/parsing/combinator/PackratParsers$PackratReader.scala$util$parsing$combinator$PackratParsers$$recursionHeads:Lscala/collection/mutable/HashMap;
const #44 = Asciz	scala/collection/immutable/Nil$;
const #45 = class	#44;	//  scala/collection/immutable/Nil$
const #46 = Asciz	Lscala/collection/immutable/Nil$;;
const #47 = NameAndType	#32:#46;//  MODULE$:Lscala/collection/immutable/Nil$;
const #48 = Field	#45.#47;	//  scala/collection/immutable/Nil$.MODULE$:Lscala/collection/immutable/Nil$;
const #49 = NameAndType	#5:#6;//  scala$util$parsing$combinator$PackratParsers$$lrStack:Lscala/collection/immutable/List;
const #50 = Field	#17.#49;	//  scala/util/parsing/combinator/PackratParsers$PackratReader.scala$util$parsing$combinator$PackratParsers$$lrStack:Lscala/collection/immutable/List;
const #51 = Asciz	this;
const #52 = Asciz	Lscala/util/parsing/combinator/PackratParsers$PackratReader;;
const #53 = Asciz	underlying;
const #54 = Asciz	LocalVariableTable;
const #55 = Asciz	(Lscala/util/parsing/combinator/PackratParsers;Lscala/util/parsing/input/Reader<TT;>;)V;
const #56 = Asciz	Signature;
const #57 = Asciz	scala$util$parsing$combinator$PackratParsers$PackratReader$$$outer;
const #58 = Asciz	()Lscala/util/parsing/combinator/PackratParsers;;
const #59 = Asciz	atEnd;
const #60 = Asciz	()Z;
const #61 = NameAndType	#59:#60;//  atEnd:()Z
const #62 = Method	#28.#61;	//  scala/util/parsing/input/Reader.atEnd:()Z
const #63 = Asciz	pos;
const #64 = Asciz	()Lscala/util/parsing/input/Position;;
const #65 = NameAndType	#63:#64;//  pos:()Lscala/util/parsing/input/Position;
const #66 = Method	#28.#65;	//  scala/util/parsing/input/Reader.pos:()Lscala/util/parsing/input/Position;
const #67 = Asciz	rest;
const #68 = Asciz	()Lscala/util/parsing/input/Reader;;
const #69 = Asciz	scala/util/parsing/combinator/PackratParsers$PackratReader$$anon$3;
const #70 = class	#69;	//  scala/util/parsing/combinator/PackratParsers$PackratReader$$anon$3
const #71 = Asciz	(Lscala/util/parsing/combinator/PackratParsers$PackratReader;)V;
const #72 = NameAndType	#12:#71;//  "<init>":(Lscala/util/parsing/combinator/PackratParsers$PackratReader;)V
const #73 = Method	#70.#72;	//  scala/util/parsing/combinator/PackratParsers$PackratReader$$anon$3."<init>":(Lscala/util/parsing/combinator/PackratParsers$PackratReader;)V
const #74 = Asciz	()Lscala/util/parsing/input/Reader<TT;>;;
const #75 = Asciz	first;
const #76 = Asciz	()Ljava/lang/Object;;
const #77 = NameAndType	#75:#76;//  first:()Ljava/lang/Object;
const #78 = Method	#28.#77;	//  scala/util/parsing/input/Reader.first:()Ljava/lang/Object;
const #79 = Asciz	()TT;;
const #80 = Asciz	offset;
const #81 = Asciz	()I;
const #82 = NameAndType	#80:#81;//  offset:()I
const #83 = Method	#28.#82;	//  scala/util/parsing/input/Reader.offset:()I
const #84 = Asciz	source;
const #85 = Asciz	()Ljava/lang/CharSequence;;
const #86 = NameAndType	#84:#85;//  source:()Ljava/lang/CharSequence;
const #87 = Method	#28.#86;	//  scala/util/parsing/input/Reader.source:()Ljava/lang/CharSequence;
const #88 = Asciz	scala$util$parsing$combinator$PackratParsers$$lrStack_$eq;
const #89 = Asciz	(Lscala/collection/immutable/List;)V;
const #90 = Asciz	()Lscala/collection/immutable/List;;
const #91 = Asciz	scala$util$parsing$combinator$PackratParsers$$updateCacheAndGet;
const #92 = Asciz	(Lscala/util/parsing/combinator/Parsers$Parser;Lscala/util/parsing/combinator/PackratParsers$MemoEntry;)Lscala/util/parsing/combinator/PackratParsers$MemoEntry;;
const #93 = NameAndType	#9:#37;//  scala$util$parsing$combinator$PackratParsers$$cache:()Lscala/collection/mutable/HashMap;
const #94 = Method	#17.#93;	//  scala/util/parsing/combinator/PackratParsers$PackratReader.scala$util$parsing$combinator$PackratParsers$$cache:()Lscala/collection/mutable/HashMap;
const #95 = Asciz	scala/Tuple2;
const #96 = class	#95;	//  scala/Tuple2
const #97 = Method	#17.#65;	//  scala/util/parsing/combinator/PackratParsers$PackratReader.pos:()Lscala/util/parsing/input/Position;
const #98 = Asciz	(Ljava/lang/Object;Ljava/lang/Object;)V;
const #99 = NameAndType	#12:#98;//  "<init>":(Ljava/lang/Object;Ljava/lang/Object;)V
const #100 = Method	#96.#99;	//  scala/Tuple2."<init>":(Ljava/lang/Object;Ljava/lang/Object;)V
const #101 = Asciz	scala/collection/mutable/HashMap;
const #102 = class	#101;	//  scala/collection/mutable/HashMap
const #103 = Asciz	put;
const #104 = Asciz	(Ljava/lang/Object;Ljava/lang/Object;)Lscala/Option;;
const #105 = NameAndType	#103:#104;//  put:(Ljava/lang/Object;Ljava/lang/Object;)Lscala/Option;
const #106 = Method	#102.#105;	//  scala/collection/mutable/HashMap.put:(Ljava/lang/Object;Ljava/lang/Object;)Lscala/Option;
const #107 = Asciz	p;
const #108 = Asciz	Lscala/util/parsing/combinator/Parsers$Parser;;
const #109 = Asciz	w;
const #110 = Asciz	Lscala/util/parsing/combinator/PackratParsers$MemoEntry;;
const #111 = Asciz	scala$util$parsing$combinator$PackratParsers$$getFromCache;
const #112 = Asciz	(Lscala/util/parsing/combinator/Parsers$Parser;)Lscala/Option;;
const #113 = Asciz	get;
const #114 = Asciz	(Ljava/lang/Object;)Lscala/Option;;
const #115 = NameAndType	#113:#114;//  get:(Ljava/lang/Object;)Lscala/Option;
const #116 = Method	#102.#115;	//  scala/collection/mutable/HashMap.get:(Ljava/lang/Object;)Lscala/Option;
const #117 = Asciz	<T:Ljava/lang/Object;>Lscala/util/parsing/input/Reader<TT;>;Lscala/ScalaObject;;
const #118 = Asciz	Scala;
const #119 = Asciz	InnerClasses;
const #120 = Asciz	scala/util/parsing/combinator/Parsers$Parser;
const #121 = class	#120;	//  scala/util/parsing/combinator/Parsers$Parser
const #122 = Asciz	scala/util/parsing/combinator/Parsers;
const #123 = class	#122;	//  scala/util/parsing/combinator/Parsers
const #124 = Asciz	Parser;
const #125 = Asciz	scala/util/parsing/combinator/PackratParsers$MemoEntry;
const #126 = class	#125;	//  scala/util/parsing/combinator/PackratParsers$MemoEntry
const #127 = Asciz	scala/util/parsing/combinator/PackratParsers;
const #128 = class	#127;	//  scala/util/parsing/combinator/PackratParsers
const #129 = Asciz	MemoEntry;
const #130 = Asciz	PackratReader;
const #131 = Asciz	$anon$3;
const #132 = Asciz	scala/ScalaObject;
const #133 = class	#132;	//  scala/ScalaObject

{
public final scala.util.parsing.combinator.PackratParsers $outer;

public final scala.util.parsing.input.Reader scala$util$parsing$combinator$PackratParsers$PackratReader$$underlying;

public scala.util.parsing.combinator.PackratParsers$PackratReader(scala.util.parsing.combinator.PackratParsers, scala.util.parsing.input.Reader);
  Code:
   Stack=2, Locals=3, Args_size=3
   0:	aload_0
   1:	aload_2
   2:	putfield	#19; //Field scala$util$parsing$combinator$PackratParsers$PackratReader$$underlying:Lscala/util/parsing/input/Reader;
   5:	aload_1
   6:	ifnonnull	17
   9:	new	#21; //class java/lang/NullPointerException
   12:	dup
   13:	invokespecial	#24; //Method java/lang/NullPointerException."<init>":()V
   16:	athrow
   17:	aload_0
   18:	aload_1
   19:	putfield	#26; //Field $outer:Lscala/util/parsing/combinator/PackratParsers;
   22:	aload_0
   23:	invokespecial	#29; //Method scala/util/parsing/input/Reader."<init>":()V
   26:	aload_0
   27:	getstatic	#35; //Field scala/collection/mutable/HashMap$.MODULE$:Lscala/collection/mutable/HashMap$;
   30:	invokevirtual	#39; //Method scala/collection/mutable/HashMap$.empty:()Lscala/collection/mutable/HashMap;
   33:	putfield	#41; //Field scala$util$parsing$combinator$PackratParsers$$cache:Lscala/collection/mutable/HashMap;
   36:	aload_0
   37:	getstatic	#35; //Field scala/collection/mutable/HashMap$.MODULE$:Lscala/collection/mutable/HashMap$;
   40:	invokevirtual	#39; //Method scala/collection/mutable/HashMap$.empty:()Lscala/collection/mutable/HashMap;
   43:	putfield	#43; //Field scala$util$parsing$combinator$PackratParsers$$recursionHeads:Lscala/collection/mutable/HashMap;
   46:	aload_0
   47:	getstatic	#48; //Field scala/collection/immutable/Nil$.MODULE$:Lscala/collection/immutable/Nil$;
   50:	putfield	#50; //Field scala$util$parsing$combinator$PackratParsers$$lrStack:Lscala/collection/immutable/List;
   53:	return
  LineNumberTable: 
   line 67: 0
   line 73: 26
   line 87: 36
   line 90: 46

  LocalVariableTable: 
   Start  Length  Slot  Name   Signature
   0      54      0    this       Lscala/util/parsing/combinator/PackratParsers$PackratReader;
   0      54      1    $outer       Lscala/util/parsing/combinator/PackratParsers;
   0      54      2    underlying       Lscala/util/parsing/input/Reader;

  Signature: length = 0x2
   00 37 

public scala.util.parsing.combinator.PackratParsers scala$util$parsing$combinator$PackratParsers$PackratReader$$$outer();
  Code:
   Stack=1, Locals=1, Args_size=1
   0:	aload_0
   1:	getfield	#26; //Field $outer:Lscala/util/parsing/combinator/PackratParsers;
   4:	areturn
  LineNumberTable: 
   line 67: 0


public boolean atEnd();
  Code:
   Stack=1, Locals=1, Args_size=1
   0:	aload_0
   1:	getfield	#19; //Field scala$util$parsing$combinator$PackratParsers$PackratReader$$underlying:Lscala/util/parsing/input/Reader;
   4:	invokevirtual	#62; //Method scala/util/parsing/input/Reader.atEnd:()Z
   7:	ireturn
  LineNumberTable: 
   line 106: 0


public scala.util.parsing.input.Position pos();
  Code:
   Stack=1, Locals=1, Args_size=1
   0:	aload_0
   1:	getfield	#19; //Field scala$util$parsing$combinator$PackratParsers$PackratReader$$underlying:Lscala/util/parsing/input/Reader;
   4:	invokevirtual	#66; //Method scala/util/parsing/input/Reader.pos:()Lscala/util/parsing/input/Position;
   7:	areturn
  LineNumberTable: 
   line 105: 0


public scala.util.parsing.input.Reader rest();
  Code:
   Stack=3, Locals=1, Args_size=1
   0:	new	#70; //class scala/util/parsing/combinator/PackratParsers$PackratReader$$anon$3
   3:	dup
   4:	aload_0
   5:	invokespecial	#73; //Method scala/util/parsing/combinator/PackratParsers$PackratReader$$anon$3."<init>":(Lscala/util/parsing/combinator/PackratParsers$PackratReader;)V
   8:	areturn
  LineNumberTable: 
   line 99: 0

  Signature: length = 0x2
   00 4A 

public java.lang.Object first();
  Code:
   Stack=1, Locals=1, Args_size=1
   0:	aload_0
   1:	getfield	#19; //Field scala$util$parsing$combinator$PackratParsers$PackratReader$$underlying:Lscala/util/parsing/input/Reader;
   4:	invokevirtual	#78; //Method scala/util/parsing/input/Reader.first:()Ljava/lang/Object;
   7:	areturn
  LineNumberTable: 
   line 98: 0

  Signature: length = 0x2
   00 4F 

public int offset();
  Code:
   Stack=1, Locals=1, Args_size=1
   0:	aload_0
   1:	getfield	#19; //Field scala$util$parsing$combinator$PackratParsers$PackratReader$$underlying:Lscala/util/parsing/input/Reader;
   4:	invokevirtual	#83; //Method scala/util/parsing/input/Reader.offset:()I
   7:	ireturn
  LineNumberTable: 
   line 96: 0


public java.lang.CharSequence source();
  Code:
   Stack=1, Locals=1, Args_size=1
   0:	aload_0
   1:	getfield	#19; //Field scala$util$parsing$combinator$PackratParsers$PackratReader$$underlying:Lscala/util/parsing/input/Reader;
   4:	invokevirtual	#87; //Method scala/util/parsing/input/Reader.source:()Ljava/lang/CharSequence;
   7:	areturn
  LineNumberTable: 
   line 95: 0


public void scala$util$parsing$combinator$PackratParsers$$lrStack_$eq(scala.collection.immutable.List);
  Code:
   Stack=2, Locals=2, Args_size=2
   0:	aload_0
   1:	aload_1
   2:	putfield	#50; //Field scala$util$parsing$combinator$PackratParsers$$lrStack:Lscala/collection/immutable/List;
   5:	return
  LineNumberTable: 
   line 90: 0


public scala.collection.immutable.List scala$util$parsing$combinator$PackratParsers$$lrStack();
  Code:
   Stack=1, Locals=1, Args_size=1
   0:	aload_0
   1:	getfield	#50; //Field scala$util$parsing$combinator$PackratParsers$$lrStack:Lscala/collection/immutable/List;
   4:	areturn
  LineNumberTable: 
   line 90: 0


public scala.collection.mutable.HashMap scala$util$parsing$combinator$PackratParsers$$recursionHeads();
  Code:
   Stack=1, Locals=1, Args_size=1
   0:	aload_0
   1:	getfield	#43; //Field scala$util$parsing$combinator$PackratParsers$$recursionHeads:Lscala/collection/mutable/HashMap;
   4:	areturn
  LineNumberTable: 
   line 87: 0


public scala.util.parsing.combinator.PackratParsers$MemoEntry scala$util$parsing$combinator$PackratParsers$$updateCacheAndGet(scala.util.parsing.combinator.Parsers$Parser, scala.util.parsing.combinator.PackratParsers$MemoEntry);
  Code:
   Stack=5, Locals=3, Args_size=3
   0:	aload_0
   1:	invokevirtual	#94; //Method scala$util$parsing$combinator$PackratParsers$$cache:()Lscala/collection/mutable/HashMap;
   4:	new	#96; //class scala/Tuple2
   7:	dup
   8:	aload_1
   9:	aload_0
   10:	invokevirtual	#97; //Method pos:()Lscala/util/parsing/input/Position;
   13:	invokespecial	#100; //Method scala/Tuple2."<init>":(Ljava/lang/Object;Ljava/lang/Object;)V
   16:	aload_2
   17:	invokevirtual	#106; //Method scala/collection/mutable/HashMap.put:(Ljava/lang/Object;Ljava/lang/Object;)Lscala/Option;
   20:	pop
   21:	aload_2
   22:	areturn
  LineNumberTable: 
   line 81: 0
   line 82: 21

  LocalVariableTable: 
   Start  Length  Slot  Name   Signature
   0      23      0    this       Lscala/util/parsing/combinator/PackratParsers$PackratReader;
   0      23      1    p       Lscala/util/parsing/combinator/Parsers$Parser;
   0      23      2    w       Lscala/util/parsing/combinator/PackratParsers$MemoEntry;


public scala.Option scala$util$parsing$combinator$PackratParsers$$getFromCache(scala.util.parsing.combinator.Parsers$Parser);
  Code:
   Stack=5, Locals=2, Args_size=2
   0:	aload_0
   1:	invokevirtual	#94; //Method scala$util$parsing$combinator$PackratParsers$$cache:()Lscala/collection/mutable/HashMap;
   4:	new	#96; //class scala/Tuple2
   7:	dup
   8:	aload_1
   9:	aload_0
   10:	invokevirtual	#97; //Method pos:()Lscala/util/parsing/input/Position;
   13:	invokespecial	#100; //Method scala/Tuple2."<init>":(Ljava/lang/Object;Ljava/lang/Object;)V
   16:	invokevirtual	#116; //Method scala/collection/mutable/HashMap.get:(Ljava/lang/Object;)Lscala/Option;
   19:	areturn
  LineNumberTable: 
   line 77: 0

  LocalVariableTable: 
   Start  Length  Slot  Name   Signature
   0      20      0    this       Lscala/util/parsing/combinator/PackratParsers$PackratReader;
   0      20      1    p       Lscala/util/parsing/combinator/Parsers$Parser;


public scala.collection.mutable.HashMap scala$util$parsing$combinator$PackratParsers$$cache();
  Code:
   Stack=1, Locals=1, Args_size=1
   0:	aload_0
   1:	getfield	#41; //Field scala$util$parsing$combinator$PackratParsers$$cache:Lscala/collection/mutable/HashMap;
   4:	areturn
  LineNumberTable: 
   line 73: 0


}

