Compiled from "PackratParsers.scala"
public final class scala.util.parsing.combinator.PackratParsers$LR$ extends java.lang.Object implements scala.Function3,scala.ScalaObject
  SourceFile: "PackratParsers.scala"
  Scala: length = 0x
   
  InnerClass: 
   public abstract Parser=class scala/util/parsing/combinator/Parsers$Parser of class scala/util/parsing/combinator/Parsers
   public LR=class scala/util/parsing/combinator/PackratParsers$LR of class scala/util/parsing/combinator/PackratParsers
   public abstract ParseResult=class scala/util/parsing/combinator/Parsers$ParseResult of class scala/util/parsing/combinator/Parsers
  minor version: 0
  major version: 49
  Constant pool:
Asciz	SourceFile;
Asciz	PackratParsers.scala;
Asciz	Scala;
Asciz	$outer;
Asciz	Lscala/util/parsing/combinator/PackratParsers;;
Asciz	toString;
Asciz	()Ljava/lang/String;;
Asciz	Code;
Asciz	LineNumberTable;
Asciz	scala/Function3$class;
class	scala/Function3$class
Asciz	(Lscala/Function3;)Ljava/lang/String;;
NameAndType	toString:(Lscala/Function3;)Ljava/lang/String;
Method	scala/Function3$class.toString:(Lscala/Function3;)Ljava/lang/String;
Asciz	curried;
Asciz	()Lscala/Function1;;
Asciz	(Lscala/Function3;)Lscala/Function1;;
NameAndType	curried:(Lscala/Function3;)Lscala/Function1;
Method	scala/Function3$class.curried:(Lscala/Function3;)Lscala/Function1;
Asciz	curry;
NameAndType	curry:(Lscala/Function3;)Lscala/Function1;
Method	scala/Function3$class.curry:(Lscala/Function3;)Lscala/Function1;
Asciz	Deprecated;
Asciz	tupled;
NameAndType	tupled:(Lscala/Function3;)Lscala/Function1;
Method	scala/Function3$class.tupled:(Lscala/Function3;)Lscala/Function1;
Asciz	unapply;
Asciz	(Lscala/util/parsing/combinator/PackratParsers$LR;)Lscala/Option;;
Asciz	java/lang/Object;
class	java/lang/Object
Asciz	equals;
Asciz	(Ljava/lang/Object;)Z;
NameAndType	equals:(Ljava/lang/Object;)Z
Method	java/lang/Object.equals:(Ljava/lang/Object;)Z
Asciz	scala/None$;
class	scala/None$
Asciz	MODULE$;
Asciz	Lscala/None$;;
NameAndType	MODULE$:Lscala/None$;
Field	scala/None$.MODULE$:Lscala/None$;
Asciz	scala/Some;
class	scala/Some
Asciz	scala/Tuple3;
class	scala/Tuple3
Asciz	scala/util/parsing/combinator/PackratParsers$LR;
class	scala/util/parsing/combinator/PackratParsers$LR
Asciz	seed;
Asciz	()Lscala/util/parsing/combinator/Parsers$ParseResult;;
NameAndType	seed:()Lscala/util/parsing/combinator/Parsers$ParseResult;
Method	scala/util/parsing/combinator/PackratParsers$LR.seed:()Lscala/util/parsing/combinator/Parsers$ParseResult;
Asciz	rule;
Asciz	()Lscala/util/parsing/combinator/Parsers$Parser;;
NameAndType	rule:()Lscala/util/parsing/combinator/Parsers$Parser;
Method	scala/util/parsing/combinator/PackratParsers$LR.rule:()Lscala/util/parsing/combinator/Parsers$Parser;
Asciz	head;
Asciz	()Lscala/Option;;
NameAndType	head:()Lscala/Option;
Method	scala/util/parsing/combinator/PackratParsers$LR.head:()Lscala/Option;
Asciz	<init>;
Asciz	(Ljava/lang/Object;Ljava/lang/Object;Ljava/lang/Object;)V;
NameAndType	"<init>":(Ljava/lang/Object;Ljava/lang/Object;Ljava/lang/Object;)V
Method	scala/Tuple3."<init>":(Ljava/lang/Object;Ljava/lang/Object;Ljava/lang/Object;)V
Asciz	(Ljava/lang/Object;)V;
NameAndType	"<init>":(Ljava/lang/Object;)V
Method	scala/Some."<init>":(Ljava/lang/Object;)V
Asciz	this;
Asciz	Lscala/util/parsing/combinator/PackratParsers$LR$;;
Asciz	x$0;
Asciz	Lscala/util/parsing/combinator/PackratParsers$LR;;
Asciz	LocalVariableTable;
Asciz	apply;
Asciz	(Lscala/util/parsing/combinator/Parsers$ParseResult;Lscala/util/parsing/combinator/Parsers$Parser;Lscala/Option;)Lscala/util/parsing/combinator/PackratParsers$LR;;
Asciz	scala/util/parsing/combinator/PackratParsers$LR$;
class	scala/util/parsing/combinator/PackratParsers$LR$
NameAndType	$outer:Lscala/util/parsing/combinator/PackratParsers;
Field	scala/util/parsing/combinator/PackratParsers$LR$.$outer:Lscala/util/parsing/combinator/PackratParsers;
Asciz	(Lscala/util/parsing/combinator/PackratParsers;Lscala/util/parsing/combinator/Parsers$ParseResult;Lscala/util/parsing/combinator/Parsers$Parser;Lscala/Option;)V;
NameAndType	"<init>":(Lscala/util/parsing/combinator/PackratParsers;Lscala/util/parsing/combinator/Parsers$ParseResult;Lscala/util/parsing/combinator/Parsers$Parser;Lscala/Option;)V
Method	scala/util/parsing/combinator/PackratParsers$LR."<init>":(Lscala/util/parsing/combinator/PackratParsers;Lscala/util/parsing/combinator/Parsers$ParseResult;Lscala/util/parsing/combinator/Parsers$Parser;Lscala/Option;)V
Asciz	Lscala/util/parsing/combinator/Parsers$ParseResult;;
Asciz	Lscala/util/parsing/combinator/Parsers$Parser;;
Asciz	Lscala/Option;;
Asciz	(Ljava/lang/Object;Ljava/lang/Object;Ljava/lang/Object;)Ljava/lang/Object;;
Asciz	scala/util/parsing/combinator/Parsers$ParseResult;
class	scala/util/parsing/combinator/Parsers$ParseResult
Asciz	scala/util/parsing/combinator/Parsers$Parser;
class	scala/util/parsing/combinator/Parsers$Parser
Asciz	scala/Option;
class	scala/Option
NameAndType	apply:(Lscala/util/parsing/combinator/Parsers$ParseResult;Lscala/util/parsing/combinator/Parsers$Parser;Lscala/Option;)Lscala/util/parsing/combinator/PackratParsers$LR;
Method	scala/util/parsing/combinator/PackratParsers$LR$.apply:(Lscala/util/parsing/combinator/Parsers$ParseResult;Lscala/util/parsing/combinator/Parsers$Parser;Lscala/Option;)Lscala/util/parsing/combinator/PackratParsers$LR;
Asciz	v1;
Asciz	Ljava/lang/Object;;
Asciz	v2;
Asciz	v3;
Asciz	(Lscala/util/parsing/combinator/PackratParsers;)V;
Asciz	java/lang/NullPointerException;
class	java/lang/NullPointerException
Asciz	()V;
NameAndType	"<init>":()V
Method	java/lang/NullPointerException."<init>":()V
Method	java/lang/Object."<init>":()V
Asciz	$init$;
Asciz	(Lscala/Function3;)V;
NameAndType	$init$:(Lscala/Function3;)V
Method	scala/Function3$class.$init$:(Lscala/Function3;)V
Asciz	InnerClasses;
Asciz	scala/util/parsing/combinator/Parsers;
class	scala/util/parsing/combinator/Parsers
Asciz	Parser;
Asciz	scala/util/parsing/combinator/PackratParsers;
class	scala/util/parsing/combinator/PackratParsers
Asciz	LR;
Asciz	ParseResult;
Asciz	scala/Function3;
class	scala/Function3
Asciz	scala/ScalaObject;
class	scala/ScalaObject

{
public final scala.util.parsing.combinator.PackratParsers $outer;
  Signature: Lscala/util/parsing/combinator/PackratParsers;

public java.lang.String toString();
  Signature: ()Ljava/lang/String;
  Code:
   Stack=1, Locals=1, Args_size=1
	aload_0
	invokestatic	Method scala/Function3$class.toString:(Lscala/Function3;)Ljava/lang/String;
	areturn
  Labels:

public scala.Function1 curried();
  Signature: ()Lscala/Function1;
  Code:
   Stack=1, Locals=1, Args_size=1
	aload_0
	invokestatic	Method scala/Function3$class.curried:(Lscala/Function3;)Lscala/Function1;
	areturn
  Labels:

public scala.Function1 curry();
  Signature: ()Lscala/Function1;
  Code:
   Stack=1, Locals=1, Args_size=1
	aload_0
	invokestatic	Method scala/Function3$class.curry:(Lscala/Function3;)Lscala/Function1;
	areturn
  Labels:
  Deprecated: true

public scala.Function1 tupled();
  Signature: ()Lscala/Function1;
  Code:
   Stack=1, Locals=1, Args_size=1
	aload_0
	invokestatic	Method scala/Function3$class.tupled:(Lscala/Function3;)Lscala/Function1;
	areturn
  Labels:

public scala.Option unapply(scala.util.parsing.combinator.PackratParsers$LR);
  Signature: (Lscala/util/parsing/combinator/PackratParsers$LR;)Lscala/Option;
  Code:
   Stack=7, Locals=2, Args_size=2
	aload_1
	dup
	pop
	ifnull	l1 // getstatic
	aload_1
	aconst_null
	invokevirtual	Method java/lang/Object.equals:(Ljava/lang/Object;)Z
	ifeq	l2 // new
l1	getstatic	Field scala/None$.MODULE$:Lscala/None$;
	goto	l3 // areturn
l2	new	class scala/Some
	dup
	new	class scala/Tuple3
	dup
	aload_1
	invokevirtual	Method scala/util/parsing/combinator/PackratParsers$LR.seed:()Lscala/util/parsing/combinator/Parsers$ParseResult;
	aload_1
	invokevirtual	Method scala/util/parsing/combinator/PackratParsers$LR.rule:()Lscala/util/parsing/combinator/Parsers$Parser;
	aload_1
	invokevirtual	Method scala/util/parsing/combinator/PackratParsers$LR.head:()Lscala/Option;
	invokespecial	Method scala/Tuple3."<init>":(Ljava/lang/Object;Ljava/lang/Object;Ljava/lang/Object;)V
	invokespecial	Method scala/Some."<init>":(Ljava/lang/Object;)V
l3	areturn
  Labels:
   	l1 = 14 // getstatic
   	l2 = 20 // new
   	l3 = 46 // areturn
  LocalVariableTable: 
   Start  Length  Slot  Name   Signature
   0      47      0    this       Lscala/util/parsing/combinator/PackratParsers$LR$;
   0      47      1    x$0       Lscala/util/parsing/combinator/PackratParsers$LR;


public scala.util.parsing.combinator.PackratParsers$LR apply(scala.util.parsing.combinator.Parsers$ParseResult, scala.util.parsing.combinator.Parsers$Parser, scala.Option);
  Signature: (Lscala/util/parsing/combinator/Parsers$ParseResult;Lscala/util/parsing/combinator/Parsers$Parser;Lscala/Option;)Lscala/util/parsing/combinator/PackratParsers$LR;
  Code:
   Stack=6, Locals=5, Args_size=4
	aload_0
	getfield	Field $outer:Lscala/util/parsing/combinator/PackratParsers;
	astore	4
	new	class scala/util/parsing/combinator/PackratParsers$LR
	dup
	aload_0
	getfield	Field $outer:Lscala/util/parsing/combinator/PackratParsers;
	aload_1
	aload_2
	aload_3
	invokespecial	Method scala/util/parsing/combinator/PackratParsers$LR."<init>":(Lscala/util/parsing/combinator/PackratParsers;Lscala/util/parsing/combinator/Parsers$ParseResult;Lscala/util/parsing/combinator/Parsers$Parser;Lscala/Option;)V
	areturn
  Labels:
  LocalVariableTable: 
   Start  Length  Slot  Name   Signature
   0      21      0    this       Lscala/util/parsing/combinator/PackratParsers$LR$;
   6      15      1    seed       Lscala/util/parsing/combinator/Parsers$ParseResult;
   6      15      2    rule       Lscala/util/parsing/combinator/Parsers$Parser;
   6      15      3    head       Lscala/Option;


public java.lang.Object apply(java.lang.Object, java.lang.Object, java.lang.Object);
  Signature: (Ljava/lang/Object;Ljava/lang/Object;Ljava/lang/Object;)Ljava/lang/Object;
  Code:
   Stack=4, Locals=5, Args_size=4
	aload_0
	getfield	Field $outer:Lscala/util/parsing/combinator/PackratParsers;
	astore	4
	aload_0
	aload_1
	checkcast	class scala/util/parsing/combinator/Parsers$ParseResult
	aload_2
	checkcast	class scala/util/parsing/combinator/Parsers$Parser
	aload_3
	checkcast	class scala/Option
	invokevirtual	Method apply:(Lscala/util/parsing/combinator/Parsers$ParseResult;Lscala/util/parsing/combinator/Parsers$Parser;Lscala/Option;)Lscala/util/parsing/combinator/PackratParsers$LR;
	areturn
  Labels:
  LocalVariableTable: 
   Start  Length  Slot  Name   Signature
   0      23      0    this       Lscala/util/parsing/combinator/PackratParsers$LR$;
   6      17      1    v1       Ljava/lang/Object;
   6      17      2    v2       Ljava/lang/Object;
   6      17      3    v3       Ljava/lang/Object;


public scala.util.parsing.combinator.PackratParsers$LR$(scala.util.parsing.combinator.PackratParsers);
  Signature: (Lscala/util/parsing/combinator/PackratParsers;)V
  Code:
   Stack=2, Locals=2, Args_size=2
	aload_1
	ifnonnull	l1 // aload_0
	new	class java/lang/NullPointerException
	dup
	invokespecial	Method java/lang/NullPointerException."<init>":()V
	athrow
l1	aload_0
	aload_1
	putfield	Field $outer:Lscala/util/parsing/combinator/PackratParsers;
	aload_0
	invokespecial	Method java/lang/Object."<init>":()V
	aload_0
	invokestatic	Method scala/Function3$class.$init$:(Lscala/Function3;)V
	return
  Labels:
   	l1 = 12 // aload_0
  LocalVariableTable: 
   Start  Length  Slot  Name   Signature
   0      26      0    this       Lscala/util/parsing/combinator/PackratParsers$LR$;
   0      26      1    $outer       Lscala/util/parsing/combinator/PackratParsers;


}

