Compiled from "PackratParsers.scala"
public final class scala.util.parsing.combinator.PackratParsers$$anon$2 extends scala.util.parsing.combinator.PackratParsers$PackratParser
  SourceFile: "PackratParsers.scala"
  Signature: length = 0x2
   00 FFFFFFBB 
  Scala: length = 0x
   
  InnerClass: 
   public abstract Parser=class scala/util/parsing/combinator/Parsers$Parser of class scala/util/parsing/combinator/Parsers
   public Failure=class scala/util/parsing/combinator/Parsers$Failure of class scala/util/parsing/combinator/Parsers
   public LR=class scala/util/parsing/combinator/PackratParsers$LR of class scala/util/parsing/combinator/PackratParsers
   public abstract ParseResult=class scala/util/parsing/combinator/Parsers$ParseResult of class scala/util/parsing/combinator/Parsers
   public final $anon$2=class scala/util/parsing/combinator/PackratParsers$$anon$2 of class scala/util/parsing/combinator/PackratParsers
   public MemoEntry=class scala/util/parsing/combinator/PackratParsers$MemoEntry of class scala/util/parsing/combinator/PackratParsers
   public PackratReader=class scala/util/parsing/combinator/PackratParsers$PackratReader of class scala/util/parsing/combinator/PackratParsers
   public abstract PackratParser=class scala/util/parsing/combinator/PackratParsers$PackratParser of class scala/util/parsing/combinator/PackratParsers
  minor version: 0
  major version: 49
  Constant pool:
Asciz	SourceFile;
Asciz	PackratParsers.scala;
Asciz	p$2;
Asciz	Lscala/util/parsing/combinator/Parsers$Parser;;
Asciz	$outer;
Asciz	Lscala/util/parsing/combinator/PackratParsers;;
Asciz	apply;
Asciz	(Lscala/util/parsing/input/Reader;)Lscala/util/parsing/combinator/Parsers$ParseResult;;
Asciz	Code;
Asciz	LineNumberTable;
Asciz	scala/util/parsing/combinator/PackratParsers$PackratReader;
class	scala/util/parsing/combinator/PackratParsers$PackratReader
Asciz	scala/util/parsing/combinator/PackratParsers$$anon$2;
class	scala/util/parsing/combinator/PackratParsers$$anon$2
NameAndType	$outer:Lscala/util/parsing/combinator/PackratParsers;
Field	scala/util/parsing/combinator/PackratParsers$$anon$2.$outer:Lscala/util/parsing/combinator/PackratParsers;
NameAndType	p$2:Lscala/util/parsing/combinator/Parsers$Parser;
Field	scala/util/parsing/combinator/PackratParsers$$anon$2.p$2:Lscala/util/parsing/combinator/Parsers$Parser;
Asciz	scala/util/parsing/combinator/PackratParsers$class;
class	scala/util/parsing/combinator/PackratParsers$class
Asciz	scala$util$parsing$combinator$PackratParsers$$recall;
Asciz	(Lscala/util/parsing/combinator/PackratParsers;Lscala/util/parsing/combinator/Parsers$Parser;Lscala/util/parsing/combinator/PackratParsers$PackratReader;)Lscala/Option;;
NameAndType	scala$util$parsing$combinator$PackratParsers$$recall:(Lscala/util/parsing/combinator/PackratParsers;Lscala/util/parsing/combinator/Parsers$Parser;Lscala/util/parsing/combinator/PackratParsers$PackratReader;)Lscala/Option;
Method	scala/util/parsing/combinator/PackratParsers$class.scala$util$parsing$combinator$PackratParsers$$recall:(Lscala/util/parsing/combinator/PackratParsers;Lscala/util/parsing/combinator/Parsers$Parser;Lscala/util/parsing/combinator/PackratParsers$PackratReader;)Lscala/Option;
Asciz	scala/None$;
class	scala/None$
Asciz	MODULE$;
Asciz	Lscala/None$;;
NameAndType	MODULE$:Lscala/None$;
Field	scala/None$.MODULE$:Lscala/None$;
Asciz	java/lang/Object;
class	java/lang/Object
Asciz	equals;
Asciz	(Ljava/lang/Object;)Z;
NameAndType	equals:(Ljava/lang/Object;)Z
Method	java/lang/Object.equals:(Ljava/lang/Object;)Z
Asciz	scala/util/parsing/combinator/PackratParsers$LR;
class	scala/util/parsing/combinator/PackratParsers$LR
Asciz	scala/util/parsing/combinator/Parsers$Failure;
class	scala/util/parsing/combinator/Parsers$Failure
Asciz	Base Failure;
String	Base Failure
Asciz	<init>;
Asciz	(Lscala/util/parsing/combinator/Parsers;Ljava/lang/String;Lscala/util/parsing/input/Reader;)V;
NameAndType	"<init>":(Lscala/util/parsing/combinator/Parsers;Ljava/lang/String;Lscala/util/parsing/input/Reader;)V
Method	scala/util/parsing/combinator/Parsers$Failure."<init>":(Lscala/util/parsing/combinator/Parsers;Ljava/lang/String;Lscala/util/parsing/input/Reader;)V
Asciz	(Lscala/util/parsing/combinator/PackratParsers;Lscala/util/parsing/combinator/Parsers$ParseResult;Lscala/util/parsing/combinator/Parsers$Parser;Lscala/Option;)V;
NameAndType	"<init>":(Lscala/util/parsing/combinator/PackratParsers;Lscala/util/parsing/combinator/Parsers$ParseResult;Lscala/util/parsing/combinator/Parsers$Parser;Lscala/Option;)V
Method	scala/util/parsing/combinator/PackratParsers$LR."<init>":(Lscala/util/parsing/combinator/PackratParsers;Lscala/util/parsing/combinator/Parsers$ParseResult;Lscala/util/parsing/combinator/Parsers$Parser;Lscala/Option;)V
Asciz	scala$util$parsing$combinator$PackratParsers$$lrStack;
Asciz	()Lscala/collection/immutable/List;;
NameAndType	scala$util$parsing$combinator$PackratParsers$$lrStack:()Lscala/collection/immutable/List;
Method	scala/util/parsing/combinator/PackratParsers$PackratReader.scala$util$parsing$combinator$PackratParsers$$lrStack:()Lscala/collection/immutable/List;
Asciz	scala/collection/immutable/List;
class	scala/collection/immutable/List
Asciz	$colon$colon;
Asciz	(Ljava/lang/Object;)Lscala/collection/immutable/List;;
NameAndType	$colon$colon:(Ljava/lang/Object;)Lscala/collection/immutable/List;
Method	scala/collection/immutable/List.$colon$colon:(Ljava/lang/Object;)Lscala/collection/immutable/List;
Asciz	scala$util$parsing$combinator$PackratParsers$$lrStack_$eq;
Asciz	(Lscala/collection/immutable/List;)V;
NameAndType	scala$util$parsing$combinator$PackratParsers$$lrStack_$eq:(Lscala/collection/immutable/List;)V
Method	scala/util/parsing/combinator/PackratParsers$PackratReader.scala$util$parsing$combinator$PackratParsers$$lrStack_$eq:(Lscala/collection/immutable/List;)V
Asciz	scala/util/parsing/combinator/PackratParsers$MemoEntry;
class	scala/util/parsing/combinator/PackratParsers$MemoEntry
Asciz	scala/Left;
class	scala/Left
Asciz	(Ljava/lang/Object;)V;
NameAndType	"<init>":(Ljava/lang/Object;)V
Method	scala/Left."<init>":(Ljava/lang/Object;)V
Asciz	(Lscala/util/parsing/combinator/PackratParsers;Lscala/Either;)V;
NameAndType	"<init>":(Lscala/util/parsing/combinator/PackratParsers;Lscala/Either;)V
Method	scala/util/parsing/combinator/PackratParsers$MemoEntry."<init>":(Lscala/util/parsing/combinator/PackratParsers;Lscala/Either;)V
Asciz	scala$util$parsing$combinator$PackratParsers$$updateCacheAndGet;
Asciz	(Lscala/util/parsing/combinator/Parsers$Parser;Lscala/util/parsing/combinator/PackratParsers$MemoEntry;)Lscala/util/parsing/combinator/PackratParsers$MemoEntry;;
NameAndType	scala$util$parsing$combinator$PackratParsers$$updateCacheAndGet:(Lscala/util/parsing/combinator/Parsers$Parser;Lscala/util/parsing/combinator/PackratParsers$MemoEntry;)Lscala/util/parsing/combinator/PackratParsers$MemoEntry;
Method	scala/util/parsing/combinator/PackratParsers$PackratReader.scala$util$parsing$combinator$PackratParsers$$updateCacheAndGet:(Lscala/util/parsing/combinator/Parsers$Parser;Lscala/util/parsing/combinator/PackratParsers$MemoEntry;)Lscala/util/parsing/combinator/PackratParsers$MemoEntry;
Asciz	scala/util/parsing/combinator/Parsers$Parser;
class	scala/util/parsing/combinator/Parsers$Parser
NameAndType	apply:(Lscala/util/parsing/input/Reader;)Lscala/util/parsing/combinator/Parsers$ParseResult;
Method	scala/util/parsing/combinator/Parsers$Parser.apply:(Lscala/util/parsing/input/Reader;)Lscala/util/parsing/combinator/Parsers$ParseResult;
Asciz	scala/collection/TraversableLike;
class	scala/collection/TraversableLike
Asciz	tail;
Asciz	()Ljava/lang/Object;;
NameAndType	tail:()Ljava/lang/Object;
InterfaceMethod	scala/collection/TraversableLike.tail:()Ljava/lang/Object;
Asciz	head;
Asciz	()Lscala/Option;;
NameAndType	head:()Lscala/Option;
Method	scala/util/parsing/combinator/PackratParsers$LR.head:()Lscala/Option;
Asciz	scala/Right;
class	scala/Right
Method	scala/Right."<init>":(Ljava/lang/Object;)V
Asciz	scala/Some;
class	scala/Some
Asciz	seed_$eq;
Asciz	(Lscala/util/parsing/combinator/Parsers$ParseResult;)V;
NameAndType	seed_$eq:(Lscala/util/parsing/combinator/Parsers$ParseResult;)V
Method	scala/util/parsing/combinator/PackratParsers$LR.seed_$eq:(Lscala/util/parsing/combinator/Parsers$ParseResult;)V
Asciz	scala$util$parsing$combinator$PackratParsers$$lrAnswer;
Asciz	(Lscala/util/parsing/combinator/PackratParsers;Lscala/util/parsing/combinator/Parsers$Parser;Lscala/util/parsing/combinator/PackratParsers$PackratReader;Lscala/util/parsing/combinator/PackratParsers$LR;)Lscala/util/parsing/combinator/Parsers$ParseResult;;
NameAndType	scala$util$parsing$combinator$PackratParsers$$lrAnswer:(Lscala/util/parsing/combinator/PackratParsers;Lscala/util/parsing/combinator/Parsers$Parser;Lscala/util/parsing/combinator/PackratParsers$PackratReader;Lscala/util/parsing/combinator/PackratParsers$LR;)Lscala/util/parsing/combinator/Parsers$ParseResult;
Method	scala/util/parsing/combinator/PackratParsers$class.scala$util$parsing$combinator$PackratParsers$$lrAnswer:(Lscala/util/parsing/combinator/PackratParsers;Lscala/util/parsing/combinator/Parsers$Parser;Lscala/util/parsing/combinator/PackratParsers$PackratReader;Lscala/util/parsing/combinator/PackratParsers$LR;)Lscala/util/parsing/combinator/Parsers$ParseResult;
Asciz	scala/MatchError;
class	scala/MatchError
Asciz	scala/Option;
class	scala/Option
Asciz	toString;
Asciz	()Ljava/lang/String;;
NameAndType	toString:()Ljava/lang/String;
Method	scala/Option.toString:()Ljava/lang/String;
Asciz	(Ljava/lang/String;)V;
NameAndType	"<init>":(Ljava/lang/String;)V
Method	scala/MatchError."<init>":(Ljava/lang/String;)V
Asciz	x;
Asciz	Ljava/lang/Object;;
NameAndType	x:Ljava/lang/Object;
Field	scala/Some.x:Ljava/lang/Object;
Asciz	r;
Asciz	()Lscala/Either;;
NameAndType	r:()Lscala/Either;
Method	scala/util/parsing/combinator/PackratParsers$MemoEntry.r:()Lscala/Either;
Asciz	a;
NameAndType	a:Ljava/lang/Object;
Field	scala/Left.a:Ljava/lang/Object;
Asciz	scala$util$parsing$combinator$PackratParsers$$setupLR;
Asciz	(Lscala/util/parsing/combinator/PackratParsers;Lscala/util/parsing/combinator/Parsers$Parser;Lscala/util/parsing/combinator/PackratParsers$PackratReader;Lscala/util/parsing/combinator/PackratParsers$LR;)V;
NameAndType	scala$util$parsing$combinator$PackratParsers$$setupLR:(Lscala/util/parsing/combinator/PackratParsers;Lscala/util/parsing/combinator/Parsers$Parser;Lscala/util/parsing/combinator/PackratParsers$PackratReader;Lscala/util/parsing/combinator/PackratParsers$LR;)V
Method	scala/util/parsing/combinator/PackratParsers$class.scala$util$parsing$combinator$PackratParsers$$setupLR:(Lscala/util/parsing/combinator/PackratParsers;Lscala/util/parsing/combinator/Parsers$Parser;Lscala/util/parsing/combinator/PackratParsers$PackratReader;Lscala/util/parsing/combinator/PackratParsers$LR;)V
Asciz	seed;
Asciz	()Lscala/util/parsing/combinator/Parsers$ParseResult;;
NameAndType	seed:()Lscala/util/parsing/combinator/Parsers$ParseResult;
Method	scala/util/parsing/combinator/PackratParsers$LR.seed:()Lscala/util/parsing/combinator/Parsers$ParseResult;
Method	scala/util/parsing/combinator/PackratParsers$LR.toString:()Ljava/lang/String;
Asciz	b;
NameAndType	b:Ljava/lang/Object;
Field	scala/Right.b:Ljava/lang/Object;
Asciz	scala/util/parsing/combinator/Parsers$ParseResult;
class	scala/util/parsing/combinator/Parsers$ParseResult
Method	scala/util/parsing/combinator/PackratParsers$MemoEntry.toString:()Ljava/lang/String;
Asciz	this;
Asciz	Lscala/util/parsing/combinator/PackratParsers$$anon$2;;
Asciz	in;
Asciz	Lscala/util/parsing/input/Reader;;
Asciz	tempRes;
Asciz	Lscala/util/parsing/combinator/Parsers$ParseResult;;
Asciz	base;
Asciz	Lscala/util/parsing/combinator/PackratParsers$LR;;
Asciz	res;
Asciz	temp53;
Asciz	Lscala/Option;;
Asciz	temp69;
Asciz	Lscala/Some;;
Asciz	temp63;
Asciz	Lscala/Left;;
Asciz	inMem;
Asciz	Lscala/util/parsing/combinator/PackratParsers$PackratReader;;
Asciz	temp64;
Asciz	temp62;
Asciz	Lscala/Either;;
Asciz	temp65;
Asciz	Lscala/Right;;
Asciz	temp66;
Asciz	temp70;
Asciz	Lscala/util/parsing/combinator/PackratParsers$MemoEntry;;
Asciz	m;
Asciz	LocalVariableTable;
Asciz	(Lscala/util/parsing/input/Reader<Ljava/lang/Object;>;)Lscala/util/parsing/combinator/Parsers$ParseResult<TT;>;;
Asciz	Signature;
Asciz	(Ljava/lang/Object;)Ljava/lang/Object;;
Asciz	scala/util/parsing/input/Reader;
class	scala/util/parsing/input/Reader
Method	scala/util/parsing/combinator/PackratParsers$$anon$2.apply:(Lscala/util/parsing/input/Reader;)Lscala/util/parsing/combinator/Parsers$ParseResult;
Asciz	v1;
Asciz	(Lscala/util/parsing/combinator/PackratParsers;Lscala/util/parsing/combinator/Parsers$Parser;)V;
Asciz	java/lang/NullPointerException;
class	java/lang/NullPointerException
Asciz	()V;
NameAndType	"<init>":()V
Method	java/lang/NullPointerException."<init>":()V
Asciz	scala/util/parsing/combinator/PackratParsers$PackratParser;
class	scala/util/parsing/combinator/PackratParsers$PackratParser
Asciz	(Lscala/util/parsing/combinator/PackratParsers;)V;
NameAndType	"<init>":(Lscala/util/parsing/combinator/PackratParsers;)V
Method	scala/util/parsing/combinator/PackratParsers$PackratParser."<init>":(Lscala/util/parsing/combinator/PackratParsers;)V
Asciz	Lscala/util/parsing/combinator/PackratParsers$PackratParser<TT;>;;
Asciz	Scala;
Asciz	InnerClasses;
Asciz	scala/util/parsing/combinator/Parsers;
class	scala/util/parsing/combinator/Parsers
Asciz	Parser;
Asciz	Failure;
Asciz	scala/util/parsing/combinator/PackratParsers;
class	scala/util/parsing/combinator/PackratParsers
Asciz	LR;
Asciz	ParseResult;
Asciz	$anon$2;
Asciz	MemoEntry;
Asciz	PackratReader;
Asciz	PackratParser;

{
public final scala.util.parsing.combinator.Parsers$Parser p$2;
  Signature: Lscala/util/parsing/combinator/Parsers$Parser;

public final scala.util.parsing.combinator.PackratParsers $outer;
  Signature: Lscala/util/parsing/combinator/PackratParsers;

public scala.util.parsing.combinator.Parsers$ParseResult apply(scala.util.parsing.input.Reader);
  Signature: (Lscala/util/parsing/input/Reader;)Lscala/util/parsing/combinator/Parsers$ParseResult;
  Code:
   Stack=8, Locals=15, Args_size=2
	aload_1
	checkcast	class scala/util/parsing/combinator/PackratParsers$PackratReader
	astore	8
	aload_0
	getfield	Field $outer:Lscala/util/parsing/combinator/PackratParsers;
	aload_0
	getfield	Field p$2:Lscala/util/parsing/combinator/Parsers$Parser;
	aload	8
	invokestatic	Method scala/util/parsing/combinator/PackratParsers$class.scala$util$parsing$combinator$PackratParsers$$recall:(Lscala/util/parsing/combinator/PackratParsers;Lscala/util/parsing/combinator/Parsers$Parser;Lscala/util/parsing/combinator/PackratParsers$PackratReader;)Lscala/Option;
	astore	14
	getstatic	Field scala/None$.MODULE$:Lscala/None$;
	dup
	ifnonnull	l1 // aload
	pop
	aload	14
	ifnull	l2 // new
	goto	l3 // aload
l1	aload	14
	invokevirtual	Method java/lang/Object.equals:(Ljava/lang/Object;)Z
	ifeq	l3 // aload
l2	new	class scala/util/parsing/combinator/PackratParsers$LR
	dup
	aload_0
	getfield	Field $outer:Lscala/util/parsing/combinator/PackratParsers;
	new	class scala/util/parsing/combinator/Parsers$Failure
	dup
	aload_0
	getfield	Field $outer:Lscala/util/parsing/combinator/PackratParsers;
	ldc	String Base Failure
	aload_1
	invokespecial	Method scala/util/parsing/combinator/Parsers$Failure."<init>":(Lscala/util/parsing/combinator/Parsers;Ljava/lang/String;Lscala/util/parsing/input/Reader;)V
	aload_0
	getfield	Field p$2:Lscala/util/parsing/combinator/Parsers$Parser;
	getstatic	Field scala/None$.MODULE$:Lscala/None$;
	invokespecial	Method scala/util/parsing/combinator/PackratParsers$LR."<init>":(Lscala/util/parsing/combinator/PackratParsers;Lscala/util/parsing/combinator/Parsers$ParseResult;Lscala/util/parsing/combinator/Parsers$Parser;Lscala/Option;)V
	astore_3
	aload	8
	aload	8
	invokevirtual	Method scala/util/parsing/combinator/PackratParsers$PackratReader.scala$util$parsing$combinator$PackratParsers$$lrStack:()Lscala/collection/immutable/List;
	aload_3
	invokevirtual	Method scala/collection/immutable/List.$colon$colon:(Ljava/lang/Object;)Lscala/collection/immutable/List;
	invokevirtual	Method scala/util/parsing/combinator/PackratParsers$PackratReader.scala$util$parsing$combinator$PackratParsers$$lrStack_$eq:(Lscala/collection/immutable/List;)V
	aload	8
	aload_0
	getfield	Field p$2:Lscala/util/parsing/combinator/Parsers$Parser;
	new	class scala/util/parsing/combinator/PackratParsers$MemoEntry
	dup
	aload_0
	getfield	Field $outer:Lscala/util/parsing/combinator/PackratParsers;
	new	class scala/Left
	dup
	aload_3
	invokespecial	Method scala/Left."<init>":(Ljava/lang/Object;)V
	invokespecial	Method scala/util/parsing/combinator/PackratParsers$MemoEntry."<init>":(Lscala/util/parsing/combinator/PackratParsers;Lscala/Either;)V
	invokevirtual	Method scala/util/parsing/combinator/PackratParsers$PackratReader.scala$util$parsing$combinator$PackratParsers$$updateCacheAndGet:(Lscala/util/parsing/combinator/Parsers$Parser;Lscala/util/parsing/combinator/PackratParsers$MemoEntry;)Lscala/util/parsing/combinator/PackratParsers$MemoEntry;
	pop
	aload_0
	getfield	Field p$2:Lscala/util/parsing/combinator/Parsers$Parser;
	aload_1
	invokevirtual	Method scala/util/parsing/combinator/Parsers$Parser.apply:(Lscala/util/parsing/input/Reader;)Lscala/util/parsing/combinator/Parsers$ParseResult;
	astore_2
	aload	8
	aload	8
	invokevirtual	Method scala/util/parsing/combinator/PackratParsers$PackratReader.scala$util$parsing$combinator$PackratParsers$$lrStack:()Lscala/collection/immutable/List;
	invokeinterface	InterfaceMethod scala/collection/TraversableLike.tail:()Ljava/lang/Object;
	checkcast	class scala/collection/immutable/List
	invokevirtual	Method scala/util/parsing/combinator/PackratParsers$PackratReader.scala$util$parsing$combinator$PackratParsers$$lrStack_$eq:(Lscala/collection/immutable/List;)V
	aload_3
	invokevirtual	Method scala/util/parsing/combinator/PackratParsers$LR.head:()Lscala/Option;
	astore	5
	getstatic	Field scala/None$.MODULE$:Lscala/None$;
	dup
	ifnonnull	l4 // aload
	pop
	aload	5
	ifnull	l5 // aload
	goto	l6 // aload
l4	aload	5
	invokevirtual	Method java/lang/Object.equals:(Ljava/lang/Object;)Z
	ifeq	l6 // aload
l5	aload	8
	aload_0
	getfield	Field p$2:Lscala/util/parsing/combinator/Parsers$Parser;
	new	class scala/util/parsing/combinator/PackratParsers$MemoEntry
	dup
	aload_0
	getfield	Field $outer:Lscala/util/parsing/combinator/PackratParsers;
	new	class scala/Right
	dup
	aload_2
	invokespecial	Method scala/Right."<init>":(Ljava/lang/Object;)V
	invokespecial	Method scala/util/parsing/combinator/PackratParsers$MemoEntry."<init>":(Lscala/util/parsing/combinator/PackratParsers;Lscala/Either;)V
	invokevirtual	Method scala/util/parsing/combinator/PackratParsers$PackratReader.scala$util$parsing$combinator$PackratParsers$$updateCacheAndGet:(Lscala/util/parsing/combinator/Parsers$Parser;Lscala/util/parsing/combinator/PackratParsers$MemoEntry;)Lscala/util/parsing/combinator/PackratParsers$MemoEntry;
	pop
	aload_2
	goto	l7 // areturn
l6	aload	5
	instanceof	class scala/Some
	ifeq	l8 // new
	aload_3
	aload_2
	invokevirtual	Method scala/util/parsing/combinator/PackratParsers$LR.seed_$eq:(Lscala/util/parsing/combinator/Parsers$ParseResult;)V
	aload_0
	getfield	Field $outer:Lscala/util/parsing/combinator/PackratParsers;
	aload_0
	getfield	Field p$2:Lscala/util/parsing/combinator/Parsers$Parser;
	aload	8
	aload_3
	invokestatic	Method scala/util/parsing/combinator/PackratParsers$class.scala$util$parsing$combinator$PackratParsers$$lrAnswer:(Lscala/util/parsing/combinator/PackratParsers;Lscala/util/parsing/combinator/Parsers$Parser;Lscala/util/parsing/combinator/PackratParsers$PackratReader;Lscala/util/parsing/combinator/PackratParsers$LR;)Lscala/util/parsing/combinator/Parsers$ParseResult;
	astore	4
	aload	4
	goto	l7 // areturn
l8	new	class scala/MatchError
	dup
	aload	5
	invokevirtual	Method scala/Option.toString:()Ljava/lang/String;
	invokespecial	Method scala/MatchError."<init>":(Ljava/lang/String;)V
	athrow
l3	aload	14
	instanceof	class scala/Some
	ifeq	l9 // new
	aload	14
	checkcast	class scala/Some
	astore	6
	aload	6
	getfield	Field scala/Some.x:Ljava/lang/Object;
	checkcast	class scala/util/parsing/combinator/PackratParsers$MemoEntry
	astore	13
	aload	13
	ifnull	l10 // new
	aload	13
	invokevirtual	Method scala/util/parsing/combinator/PackratParsers$MemoEntry.r:()Lscala/Either;
	astore	10
	aload	10
	instanceof	class scala/Left
	ifeq	l11 // aload
	aload	10
	checkcast	class scala/Left
	astore	7
	aload	7
	getfield	Field scala/Left.a:Ljava/lang/Object;
	checkcast	class scala/util/parsing/combinator/PackratParsers$LR
	astore	9
	aload_0
	getfield	Field $outer:Lscala/util/parsing/combinator/PackratParsers;
	aload_0
	getfield	Field p$2:Lscala/util/parsing/combinator/Parsers$Parser;
	aload	8
	aload	9
	invokestatic	Method scala/util/parsing/combinator/PackratParsers$class.scala$util$parsing$combinator$PackratParsers$$setupLR:(Lscala/util/parsing/combinator/PackratParsers;Lscala/util/parsing/combinator/Parsers$Parser;Lscala/util/parsing/combinator/PackratParsers$PackratReader;Lscala/util/parsing/combinator/PackratParsers$LR;)V
	aload	9
	ifnull	l12 // new
	aload	9
	invokevirtual	Method scala/util/parsing/combinator/PackratParsers$LR.seed:()Lscala/util/parsing/combinator/Parsers$ParseResult;
	goto	l7 // areturn
l12	new	class scala/MatchError
	dup
	aload	9
	invokevirtual	Method scala/util/parsing/combinator/PackratParsers$LR.toString:()Ljava/lang/String;
	invokespecial	Method scala/MatchError."<init>":(Ljava/lang/String;)V
	athrow
l11	aload	10
	instanceof	class scala/Right
	ifeq	l13 // new
	aload	10
	checkcast	class scala/Right
	astore	11
	aload	11
	getfield	Field scala/Right.b:Ljava/lang/Object;
	checkcast	class scala/util/parsing/combinator/Parsers$ParseResult
	astore	12
	aload	12
	ifnull	l14 // new
	aload	12
l7	areturn
l14	new	class scala/MatchError
	dup
	aload	13
	invokevirtual	Method scala/util/parsing/combinator/PackratParsers$MemoEntry.toString:()Ljava/lang/String;
	invokespecial	Method scala/MatchError."<init>":(Ljava/lang/String;)V
	athrow
l13	new	class scala/MatchError
	dup
	aload	13
	invokevirtual	Method scala/util/parsing/combinator/PackratParsers$MemoEntry.toString:()Ljava/lang/String;
	invokespecial	Method scala/MatchError."<init>":(Ljava/lang/String;)V
	athrow
l10	new	class scala/MatchError
	dup
	aload	13
	invokevirtual	Method scala/util/parsing/combinator/PackratParsers$MemoEntry.toString:()Ljava/lang/String;
	invokespecial	Method scala/MatchError."<init>":(Ljava/lang/String;)V
	athrow
l9	new	class scala/MatchError
	dup
	aload	14
	invokevirtual	Method scala/Option.toString:()Ljava/lang/String;
	invokespecial	Method scala/MatchError."<init>":(Ljava/lang/String;)V
	athrow
  Labels:
   	l1 = 37 // aload
   	l2 = 45 // new
   	l4 = 170 // aload
   	l5 = 178 // aload
   	l6 = 211 // aload
   	l8 = 245 // new
   	l3 = 258 // aload
   	l12 = 348 // new
   	l11 = 361 // aload
   	l7 = 393 // areturn
   	l14 = 394 // new
   	l13 = 407 // new
   	l10 = 420 // new
   	l9 = 433 // new
  LocalVariableTable: 
   Start  Length  Slot  Name   Signature
   0      446      0    this       Lscala/util/parsing/combinator/PackratParsers$$anon$2;
   0      446      1    in       Lscala/util/parsing/input/Reader;
   130      128      2    tempRes       Lscala/util/parsing/combinator/Parsers$ParseResult;
   78      180      3    base       Lscala/util/parsing/combinator/PackratParsers$LR;
   240      2      4    res       Lscala/util/parsing/combinator/Parsers$ParseResult;
   154      104      5    temp53       Lscala/Option;
   273      120      6    temp69       Lscala/Some;
   394      39      6    temp69       Lscala/Some;
   310      51      7    temp63       Lscala/Left;
   6      440      8    inMem       Lscala/util/parsing/combinator/PackratParsers$PackratReader;
   320      41      9    temp64       Lscala/util/parsing/combinator/PackratParsers$LR;
   295      98      10    temp62       Lscala/Either;
   394      26      10    temp62       Lscala/Either;
   376      17      11    temp65       Lscala/Right;
   394      13      11    temp65       Lscala/Right;
   386      7      12    temp66       Lscala/util/parsing/combinator/Parsers$ParseResult;
   394      13      12    temp66       Lscala/util/parsing/combinator/Parsers$ParseResult;
   283      110      13    temp70       Lscala/util/parsing/combinator/PackratParsers$MemoEntry;
   394      39      13    temp70       Lscala/util/parsing/combinator/PackratParsers$MemoEntry;
   21      425      14    m       Lscala/Option;

  Signature: length = 0x2
   00 FFFFFFA9 

public java.lang.Object apply(java.lang.Object);
  Signature: (Ljava/lang/Object;)Ljava/lang/Object;
  Code:
   Stack=2, Locals=2, Args_size=2
	aload_0
	aload_1
	checkcast	class scala/util/parsing/input/Reader
	invokevirtual	Method apply:(Lscala/util/parsing/input/Reader;)Lscala/util/parsing/combinator/Parsers$ParseResult;
	areturn
  Labels:
  LocalVariableTable: 
   Start  Length  Slot  Name   Signature
   0      9      0    this       Lscala/util/parsing/combinator/PackratParsers$$anon$2;
   0      9      1    v1       Ljava/lang/Object;


public scala.util.parsing.combinator.PackratParsers$$anon$2(scala.util.parsing.combinator.PackratParsers, scala.util.parsing.combinator.Parsers$Parser);
  Signature: (Lscala/util/parsing/combinator/PackratParsers;Lscala/util/parsing/combinator/Parsers$Parser;)V
  Code:
   Stack=2, Locals=3, Args_size=3
	aload_1
	ifnonnull	l1 // aload_0
	new	class java/lang/NullPointerException
	dup
	invokespecial	Method java/lang/NullPointerException."<init>":()V
	athrow
l1	aload_0
	aload_1
	putfield	Field $outer:Lscala/util/parsing/combinator/PackratParsers;
	aload_0
	aload_2
	putfield	Field p$2:Lscala/util/parsing/combinator/Parsers$Parser;
	aload_0
	aload_1
	invokespecial	Method scala/util/parsing/combinator/PackratParsers$PackratParser."<init>":(Lscala/util/parsing/combinator/PackratParsers;)V
	return
  Labels:
   	l1 = 12 // aload_0
  LocalVariableTable: 
   Start  Length  Slot  Name   Signature
   0      28      0    this       Lscala/util/parsing/combinator/PackratParsers$$anon$2;
   0      28      1    $outer       Lscala/util/parsing/combinator/PackratParsers;


}

