Compiled from "Parsers.scala"
public final class scala.util.parsing.combinator.Parsers$Parser$$anonfun$$tilde$bang$1 extends java.lang.Object implements scala.Function1,scala.ScalaObject,java.io.Serializable
  SourceFile: "Parsers.scala"
  Scala: length = 0x
   
  InnerClass: 
   public abstract Parser=class scala/util/parsing/combinator/Parsers$Parser of class scala/util/parsing/combinator/Parsers
   public final $anonfun$$tilde$bang$1=class scala/util/parsing/combinator/Parsers$Parser$$anonfun$$tilde$bang$1 of class scala/util/parsing/combinator/Parsers$Parser
   public final $anonfun$apply$5=class scala/util/parsing/combinator/Parsers$Parser$$anonfun$$tilde$bang$1$$anonfun$apply$5 of class scala/util/parsing/combinator/Parsers$Parser$$anonfun$$tilde$bang$1
  minor version: 0
  major version: 49
  Constant pool:
Asciz	SourceFile;
Asciz	Parsers.scala;
Asciz	<clinit>;
Asciz	()V;
Asciz	Code;
Asciz	serialVersionUID;
Asciz	J;
Asciz	scala/util/parsing/combinator/Parsers$Parser$$anonfun$$tilde$bang$1;
class	scala/util/parsing/combinator/Parsers$Parser$$anonfun$$tilde$bang$1
NameAndType	serialVersionUID:J
Field	scala/util/parsing/combinator/Parsers$Parser$$anonfun$$tilde$bang$1.serialVersionUID:J
Asciz	p$7;
Asciz	Lscala/Function0;;
Asciz	$outer;
Asciz	Lscala/util/parsing/combinator/Parsers$Parser;;
Asciz	<init>;
Asciz	(Lscala/util/parsing/combinator/Parsers$Parser;Lscala/Function0;)V;
Asciz	LineNumberTable;
Asciz	java/lang/NullPointerException;
class	java/lang/NullPointerException
NameAndType	"<init>":()V
Method	java/lang/NullPointerException."<init>":()V
NameAndType	$outer:Lscala/util/parsing/combinator/Parsers$Parser;
Field	scala/util/parsing/combinator/Parsers$Parser$$anonfun$$tilde$bang$1.$outer:Lscala/util/parsing/combinator/Parsers$Parser;
NameAndType	p$7:Lscala/Function0;
Field	scala/util/parsing/combinator/Parsers$Parser$$anonfun$$tilde$bang$1.p$7:Lscala/Function0;
Asciz	java/lang/Object;
class	java/lang/Object
Method	java/lang/Object."<init>":()V
Asciz	scala/Function1$class;
class	scala/Function1$class
Asciz	$init$;
Asciz	(Lscala/Function1;)V;
NameAndType	$init$:(Lscala/Function1;)V
Method	scala/Function1$class.$init$:(Lscala/Function1;)V
Asciz	this;
Asciz	Lscala/util/parsing/combinator/Parsers$Parser$$anonfun$$tilde$bang$1;;
Asciz	LocalVariableTable;
Asciz	(Lscala/util/parsing/combinator/Parsers$Parser<TT;>;)V;
Asciz	Signature;
Asciz	apply;
Asciz	(Ljava/lang/Object;)Ljava/lang/Object;;
Asciz	(Ljava/lang/Object;)Lscala/util/parsing/combinator/Parsers$Parser;;
NameAndType	apply:(Ljava/lang/Object;)Lscala/util/parsing/combinator/Parsers$Parser;
Method	scala/util/parsing/combinator/Parsers$Parser$$anonfun$$tilde$bang$1.apply:(Ljava/lang/Object;)Lscala/util/parsing/combinator/Parsers$Parser;
Asciz	v1;
Asciz	Ljava/lang/Object;;
Asciz	scala$util$parsing$combinator$Parsers$Parser$$anonfun$$$outer;
Asciz	()Lscala/util/parsing/combinator/Parsers$Parser;;
Asciz	scala/util/parsing/combinator/Parsers$Parser;
class	scala/util/parsing/combinator/Parsers$Parser
Asciz	scala$util$parsing$combinator$Parsers$Parser$$$outer;
Asciz	()Lscala/util/parsing/combinator/Parsers;;
NameAndType	scala$util$parsing$combinator$Parsers$Parser$$$outer:()Lscala/util/parsing/combinator/Parsers;
Method	scala/util/parsing/combinator/Parsers$Parser.scala$util$parsing$combinator$Parsers$Parser$$$outer:()Lscala/util/parsing/combinator/Parsers;
Asciz	scala/util/parsing/combinator/Parsers;
class	scala/util/parsing/combinator/Parsers
Asciz	commit;
Asciz	(Lscala/Function0;)Lscala/util/parsing/combinator/Parsers$Parser;;
NameAndType	commit:(Lscala/Function0;)Lscala/util/parsing/combinator/Parsers$Parser;
InterfaceMethod	scala/util/parsing/combinator/Parsers.commit:(Lscala/Function0;)Lscala/util/parsing/combinator/Parsers$Parser;
Asciz	scala/util/parsing/combinator/Parsers$Parser$$anonfun$$tilde$bang$1$$anonfun$apply$5;
class	scala/util/parsing/combinator/Parsers$Parser$$anonfun$$tilde$bang$1$$anonfun$apply$5
Asciz	(Lscala/util/parsing/combinator/Parsers$Parser$$anonfun$$tilde$bang$1;Ljava/lang/Object;)V;
NameAndType	"<init>":(Lscala/util/parsing/combinator/Parsers$Parser$$anonfun$$tilde$bang$1;Ljava/lang/Object;)V
Method	scala/util/parsing/combinator/Parsers$Parser$$anonfun$$tilde$bang$1$$anonfun$apply$5."<init>":(Lscala/util/parsing/combinator/Parsers$Parser$$anonfun$$tilde$bang$1;Ljava/lang/Object;)V
Asciz	map;
Asciz	(Lscala/Function1;)Lscala/util/parsing/combinator/Parsers$Parser;;
NameAndType	map:(Lscala/Function1;)Lscala/util/parsing/combinator/Parsers$Parser;
Method	scala/util/parsing/combinator/Parsers$Parser.map:(Lscala/Function1;)Lscala/util/parsing/combinator/Parsers$Parser;
Asciz	a$3;
Asciz	(TT;)Lscala/util/parsing/combinator/Parsers$Parser<Lscala/util/parsing/combinator/Parsers$$tilde<TT;TU;>;>;;
Asciz	andThen;
Asciz	(Lscala/Function1;)Lscala/Function1;;
Asciz	(Lscala/Function1;Lscala/Function1;)Lscala/Function1;;
NameAndType	andThen:(Lscala/Function1;Lscala/Function1;)Lscala/Function1;
Method	scala/Function1$class.andThen:(Lscala/Function1;Lscala/Function1;)Lscala/Function1;
Asciz	g;
Asciz	Lscala/Function1;;
Asciz	compose;
NameAndType	compose:(Lscala/Function1;Lscala/Function1;)Lscala/Function1;
Method	scala/Function1$class.compose:(Lscala/Function1;Lscala/Function1;)Lscala/Function1;
Asciz	toString;
Asciz	()Ljava/lang/String;;
Asciz	(Lscala/Function1;)Ljava/lang/String;;
NameAndType	toString:(Lscala/Function1;)Ljava/lang/String;
Method	scala/Function1$class.toString:(Lscala/Function1;)Ljava/lang/String;
Asciz	Scala;
Asciz	InnerClasses;
Asciz	Parser;
Asciz	$anonfun$$tilde$bang$1;
Asciz	$anonfun$apply$5;
Asciz	scala/Function1;
class	scala/Function1
Asciz	scala/ScalaObject;
class	scala/ScalaObject
Asciz	java/io/Serializable;
class	java/io/Serializable

{
public static final long serialVersionUID;
  Signature: J

private final scala.Function0 p$7;
  Signature: Lscala/Function0;

public final scala.util.parsing.combinator.Parsers$Parser $outer;
  Signature: Lscala/util/parsing/combinator/Parsers$Parser;

public static {};
  Signature: ()V
  Code:
   Stack=2, Locals=0, Args_size=0
	lconst_0
	putstatic	Field serialVersionUID:J
	return
  Labels:

public scala.util.parsing.combinator.Parsers$Parser$$anonfun$$tilde$bang$1(scala.util.parsing.combinator.Parsers$Parser, scala.Function0);
  Signature: (Lscala/util/parsing/combinator/Parsers$Parser;Lscala/Function0;)V
  Code:
   Stack=2, Locals=3, Args_size=3
	aload_1
	ifnonnull	l1 // aload_0
	new	class java/lang/NullPointerException
	dup
	invokespecial	Method java/lang/NullPointerException."<init>":()V
	athrow
l1	aload_0
	aload_1
	putfield	Field $outer:Lscala/util/parsing/combinator/Parsers$Parser;
	aload_0
	aload_2
	putfield	Field p$7:Lscala/Function0;
	aload_0
	invokespecial	Method java/lang/Object."<init>":()V
	aload_0
	invokestatic	Method scala/Function1$class.$init$:(Lscala/Function1;)V
	return
  Labels:
   	l1 = 12 // aload_0
  LocalVariableTable: 
   Start  Length  Slot  Name   Signature
   0      31      0    this       Lscala/util/parsing/combinator/Parsers$Parser$$anonfun$$tilde$bang$1;
   0      31      1    $outer       Lscala/util/parsing/combinator/Parsers$Parser;

  Signature: length = 0x2
   00 27 

public final java.lang.Object apply(java.lang.Object);
  Signature: (Ljava/lang/Object;)Ljava/lang/Object;
  Code:
   Stack=2, Locals=3, Args_size=2
	aload_0
	getfield	Field $outer:Lscala/util/parsing/combinator/Parsers$Parser;
	astore_2
	aload_0
	aload_1
	invokevirtual	Method apply:(Ljava/lang/Object;)Lscala/util/parsing/combinator/Parsers$Parser;
	areturn
  Labels:
  LocalVariableTable: 
   Start  Length  Slot  Name   Signature
   0      11      0    this       Lscala/util/parsing/combinator/Parsers$Parser$$anonfun$$tilde$bang$1;
   5      6      1    v1       Ljava/lang/Object;


public scala.util.parsing.combinator.Parsers$Parser scala$util$parsing$combinator$Parsers$Parser$$anonfun$$$outer();
  Signature: ()Lscala/util/parsing/combinator/Parsers$Parser;
  Code:
   Stack=1, Locals=1, Args_size=1
	aload_0
	getfield	Field $outer:Lscala/util/parsing/combinator/Parsers$Parser;
	areturn
  Labels:

public final scala.util.parsing.combinator.Parsers$Parser apply(java.lang.Object);
  Signature: (Ljava/lang/Object;)Lscala/util/parsing/combinator/Parsers$Parser;
  Code:
   Stack=5, Locals=3, Args_size=2
	aload_0
	getfield	Field $outer:Lscala/util/parsing/combinator/Parsers$Parser;
	astore_2
	aload_0
	getfield	Field $outer:Lscala/util/parsing/combinator/Parsers$Parser;
	invokevirtual	Method scala/util/parsing/combinator/Parsers$Parser.scala$util$parsing$combinator$Parsers$Parser$$$outer:()Lscala/util/parsing/combinator/Parsers;
	aload_0
	getfield	Field p$7:Lscala/Function0;
	invokeinterface	InterfaceMethod scala/util/parsing/combinator/Parsers.commit:(Lscala/Function0;)Lscala/util/parsing/combinator/Parsers$Parser;
	new	class scala/util/parsing/combinator/Parsers$Parser$$anonfun$$tilde$bang$1$$anonfun$apply$5
	dup
	aload_0
	aload_1
	invokespecial	Method scala/util/parsing/combinator/Parsers$Parser$$anonfun$$tilde$bang$1$$anonfun$apply$5."<init>":(Lscala/util/parsing/combinator/Parsers$Parser$$anonfun$$tilde$bang$1;Ljava/lang/Object;)V
	invokevirtual	Method scala/util/parsing/combinator/Parsers$Parser.map:(Lscala/Function1;)Lscala/util/parsing/combinator/Parsers$Parser;
	areturn
  Labels:
  LocalVariableTable: 
   Start  Length  Slot  Name   Signature
   0      34      0    this       Lscala/util/parsing/combinator/Parsers$Parser$$anonfun$$tilde$bang$1;
   5      29      1    a$3       Ljava/lang/Object;

  Signature: length = 0x2
   00 48 

public scala.Function1 andThen(scala.Function1);
  Signature: (Lscala/Function1;)Lscala/Function1;
  Code:
   Stack=2, Locals=2, Args_size=2
	aload_0
	aload_1
	invokestatic	Method scala/Function1$class.andThen:(Lscala/Function1;Lscala/Function1;)Lscala/Function1;
	areturn
  Labels:
  LocalVariableTable: 
   Start  Length  Slot  Name   Signature
   0      6      0    this       Lscala/util/parsing/combinator/Parsers$Parser$$anonfun$$tilde$bang$1;
   0      6      1    g       Lscala/Function1;


public scala.Function1 compose(scala.Function1);
  Signature: (Lscala/Function1;)Lscala/Function1;
  Code:
   Stack=2, Locals=2, Args_size=2
	aload_0
	aload_1
	invokestatic	Method scala/Function1$class.compose:(Lscala/Function1;Lscala/Function1;)Lscala/Function1;
	areturn
  Labels:
  LocalVariableTable: 
   Start  Length  Slot  Name   Signature
   0      6      0    this       Lscala/util/parsing/combinator/Parsers$Parser$$anonfun$$tilde$bang$1;
   0      6      1    g       Lscala/Function1;


public java.lang.String toString();
  Signature: ()Ljava/lang/String;
  Code:
   Stack=1, Locals=1, Args_size=1
	aload_0
	invokestatic	Method scala/Function1$class.toString:(Lscala/Function1;)Ljava/lang/String;
	areturn
  Labels:

}

