Compiled from "Parsers.scala"
public final class scala.util.parsing.combinator.Parsers$$anonfun$positioned$1 extends java.lang.Object implements scala.Function1,scala.ScalaObject,java.io.Serializable
  SourceFile: "Parsers.scala"
  Scala: length = 0x
   
  InnerClass: 
   public abstract Parser=class scala/util/parsing/combinator/Parsers$Parser of class scala/util/parsing/combinator/Parsers
   public Success=class scala/util/parsing/combinator/Parsers$Success of class scala/util/parsing/combinator/Parsers
   public abstract NoSuccess=class scala/util/parsing/combinator/Parsers$NoSuccess of class scala/util/parsing/combinator/Parsers
   public abstract ParseResult=class scala/util/parsing/combinator/Parsers$ParseResult of class scala/util/parsing/combinator/Parsers
   public final $anonfun$positioned$1=class scala/util/parsing/combinator/Parsers$$anonfun$positioned$1 of class scala/util/parsing/combinator/Parsers
  minor version: 0
  major version: 49
  Constant pool:
Asciz	SourceFile;
Asciz	Parsers.scala;
Asciz	<clinit>;
Asciz	()V;
Asciz	Code;
Asciz	serialVersionUID;
Asciz	J;
Asciz	scala/util/parsing/combinator/Parsers$$anonfun$positioned$1;
class	scala/util/parsing/combinator/Parsers$$anonfun$positioned$1
NameAndType	serialVersionUID:J
Field	scala/util/parsing/combinator/Parsers$$anonfun$positioned$1.serialVersionUID:J
Asciz	p$18;
Asciz	Lscala/Function0;;
Asciz	$outer;
Asciz	Lscala/util/parsing/combinator/Parsers;;
Asciz	<init>;
Asciz	(Lscala/util/parsing/combinator/Parsers;Lscala/Function0;)V;
Asciz	LineNumberTable;
Asciz	java/lang/NullPointerException;
class	java/lang/NullPointerException
NameAndType	"<init>":()V
Method	java/lang/NullPointerException."<init>":()V
NameAndType	$outer:Lscala/util/parsing/combinator/Parsers;
Field	scala/util/parsing/combinator/Parsers$$anonfun$positioned$1.$outer:Lscala/util/parsing/combinator/Parsers;
NameAndType	p$18:Lscala/Function0;
Field	scala/util/parsing/combinator/Parsers$$anonfun$positioned$1.p$18:Lscala/Function0;
Asciz	java/lang/Object;
class	java/lang/Object
Method	java/lang/Object."<init>":()V
Asciz	scala/Function1$class;
class	scala/Function1$class
Asciz	$init$;
Asciz	(Lscala/Function1;)V;
NameAndType	$init$:(Lscala/Function1;)V
Method	scala/Function1$class.$init$:(Lscala/Function1;)V
Asciz	this;
Asciz	Lscala/util/parsing/combinator/Parsers$$anonfun$positioned$1;;
Asciz	LocalVariableTable;
Asciz	apply;
Asciz	(Ljava/lang/Object;)Ljava/lang/Object;;
Asciz	scala/util/parsing/input/Reader;
class	scala/util/parsing/input/Reader
Asciz	(Lscala/util/parsing/input/Reader;)Lscala/util/parsing/combinator/Parsers$ParseResult;;
NameAndType	apply:(Lscala/util/parsing/input/Reader;)Lscala/util/parsing/combinator/Parsers$ParseResult;
Method	scala/util/parsing/combinator/Parsers$$anonfun$positioned$1.apply:(Lscala/util/parsing/input/Reader;)Lscala/util/parsing/combinator/Parsers$ParseResult;
Asciz	v1;
Asciz	Ljava/lang/Object;;
Asciz	scala/Function0;
class	scala/Function0
Asciz	()Ljava/lang/Object;;
NameAndType	apply:()Ljava/lang/Object;
InterfaceMethod	scala/Function0.apply:()Ljava/lang/Object;
Asciz	scala/util/parsing/combinator/Parsers$Parser;
class	scala/util/parsing/combinator/Parsers$Parser
Method	scala/util/parsing/combinator/Parsers$Parser.apply:(Lscala/util/parsing/input/Reader;)Lscala/util/parsing/combinator/Parsers$ParseResult;
Asciz	scala/util/parsing/combinator/Parsers$Success;
class	scala/util/parsing/combinator/Parsers$Success
Asciz	result;
NameAndType	result:()Ljava/lang/Object;
Method	scala/util/parsing/combinator/Parsers$Success.result:()Ljava/lang/Object;
Asciz	scala/util/parsing/input/Positional;
class	scala/util/parsing/input/Positional
Asciz	next;
Asciz	()Lscala/util/parsing/input/Reader;;
NameAndType	next:()Lscala/util/parsing/input/Reader;
Method	scala/util/parsing/combinator/Parsers$Success.next:()Lscala/util/parsing/input/Reader;
Asciz	pos;
Asciz	()Lscala/util/parsing/input/Position;;
NameAndType	pos:()Lscala/util/parsing/input/Position;
InterfaceMethod	scala/util/parsing/input/Positional.pos:()Lscala/util/parsing/input/Position;
Asciz	scala/util/parsing/input/NoPosition$;
class	scala/util/parsing/input/NoPosition$
Asciz	MODULE$;
Asciz	Lscala/util/parsing/input/NoPosition$;;
NameAndType	MODULE$:Lscala/util/parsing/input/NoPosition$;
Field	scala/util/parsing/input/NoPosition$.MODULE$:Lscala/util/parsing/input/NoPosition$;
Asciz	equals;
Asciz	(Ljava/lang/Object;)Z;
NameAndType	equals:(Ljava/lang/Object;)Z
Method	java/lang/Object.equals:(Ljava/lang/Object;)Z
Method	scala/util/parsing/input/Reader.pos:()Lscala/util/parsing/input/Position;
Asciz	setPos;
Asciz	(Lscala/util/parsing/input/Position;)Lscala/util/parsing/input/Positional;;
NameAndType	setPos:(Lscala/util/parsing/input/Position;)Lscala/util/parsing/input/Positional;
InterfaceMethod	scala/util/parsing/input/Positional.setPos:(Lscala/util/parsing/input/Position;)Lscala/util/parsing/input/Positional;
Asciz	(Lscala/util/parsing/combinator/Parsers;Ljava/lang/Object;Lscala/util/parsing/input/Reader;)V;
NameAndType	"<init>":(Lscala/util/parsing/combinator/Parsers;Ljava/lang/Object;Lscala/util/parsing/input/Reader;)V
Method	scala/util/parsing/combinator/Parsers$Success."<init>":(Lscala/util/parsing/combinator/Parsers;Ljava/lang/Object;Lscala/util/parsing/input/Reader;)V
Asciz	scala/MatchError;
class	scala/MatchError
Asciz	scala/util/parsing/combinator/Parsers$ParseResult;
class	scala/util/parsing/combinator/Parsers$ParseResult
Asciz	toString;
Asciz	()Ljava/lang/String;;
NameAndType	toString:()Ljava/lang/String;
Method	scala/util/parsing/combinator/Parsers$ParseResult.toString:()Ljava/lang/String;
Asciz	(Ljava/lang/String;)V;
NameAndType	"<init>":(Ljava/lang/String;)V
Method	scala/MatchError."<init>":(Ljava/lang/String;)V
Asciz	scala/util/parsing/combinator/Parsers$NoSuccess;
class	scala/util/parsing/combinator/Parsers$NoSuccess
Asciz	in;
Asciz	Lscala/util/parsing/input/Reader;;
Asciz	temp96;
Asciz	Lscala/util/parsing/combinator/Parsers$Success;;
Asciz	temp97;
Asciz	Lscala/util/parsing/input/Positional;;
Asciz	temp98;
Asciz	temp99;
Asciz	Lscala/util/parsing/combinator/Parsers$NoSuccess;;
Asciz	temp95;
Asciz	Lscala/util/parsing/combinator/Parsers$ParseResult;;
Asciz	(Lscala/util/parsing/input/Reader<Ljava/lang/Object;>;)Lscala/util/parsing/combinator/Parsers$ParseResult<TT;>;;
Asciz	Signature;
Asciz	andThen;
Asciz	(Lscala/Function1;)Lscala/Function1;;
Asciz	(Lscala/Function1;Lscala/Function1;)Lscala/Function1;;
NameAndType	andThen:(Lscala/Function1;Lscala/Function1;)Lscala/Function1;
Method	scala/Function1$class.andThen:(Lscala/Function1;Lscala/Function1;)Lscala/Function1;
Asciz	g;
Asciz	Lscala/Function1;;
Asciz	compose;
NameAndType	compose:(Lscala/Function1;Lscala/Function1;)Lscala/Function1;
Method	scala/Function1$class.compose:(Lscala/Function1;Lscala/Function1;)Lscala/Function1;
Asciz	(Lscala/Function1;)Ljava/lang/String;;
NameAndType	toString:(Lscala/Function1;)Ljava/lang/String;
Method	scala/Function1$class.toString:(Lscala/Function1;)Ljava/lang/String;
Asciz	Scala;
Asciz	InnerClasses;
Asciz	scala/util/parsing/combinator/Parsers;
class	scala/util/parsing/combinator/Parsers
Asciz	Parser;
Asciz	Success;
Asciz	NoSuccess;
Asciz	ParseResult;
Asciz	$anonfun$positioned$1;
Asciz	scala/Function1;
class	scala/Function1
Asciz	scala/ScalaObject;
class	scala/ScalaObject
Asciz	java/io/Serializable;
class	java/io/Serializable

{
public static final long serialVersionUID;
  Signature: J

private final scala.Function0 p$18;
  Signature: Lscala/Function0;

private final scala.util.parsing.combinator.Parsers $outer;
  Signature: Lscala/util/parsing/combinator/Parsers;

public static {};
  Signature: ()V
  Code:
   Stack=2, Locals=0, Args_size=0
	lconst_0
	putstatic	Field serialVersionUID:J
	return
  Labels:

public scala.util.parsing.combinator.Parsers$$anonfun$positioned$1(scala.util.parsing.combinator.Parsers, scala.Function0);
  Signature: (Lscala/util/parsing/combinator/Parsers;Lscala/Function0;)V
  Code:
   Stack=2, Locals=3, Args_size=3
	aload_1
	ifnonnull	l1 // aload_0
	new	class java/lang/NullPointerException
	dup
	invokespecial	Method java/lang/NullPointerException."<init>":()V
	athrow
l1	aload_0
	aload_1
	putfield	Field $outer:Lscala/util/parsing/combinator/Parsers;
	aload_0
	aload_2
	putfield	Field p$18:Lscala/Function0;
	aload_0
	invokespecial	Method java/lang/Object."<init>":()V
	aload_0
	invokestatic	Method scala/Function1$class.$init$:(Lscala/Function1;)V
	return
  Labels:
   	l1 = 12 // aload_0
  LocalVariableTable: 
   Start  Length  Slot  Name   Signature
   0      31      0    this       Lscala/util/parsing/combinator/Parsers$$anonfun$positioned$1;
   0      31      1    $outer       Lscala/util/parsing/combinator/Parsers;


public final java.lang.Object apply(java.lang.Object);
  Signature: (Ljava/lang/Object;)Ljava/lang/Object;
  Code:
   Stack=2, Locals=3, Args_size=2
	aload_0
	getfield	Field $outer:Lscala/util/parsing/combinator/Parsers;
	astore_2
	aload_0
	aload_1
	checkcast	class scala/util/parsing/input/Reader
	invokevirtual	Method apply:(Lscala/util/parsing/input/Reader;)Lscala/util/parsing/combinator/Parsers$ParseResult;
	areturn
  Labels:
  LocalVariableTable: 
   Start  Length  Slot  Name   Signature
   0      14      0    this       Lscala/util/parsing/combinator/Parsers$$anonfun$positioned$1;
   5      9      1    v1       Ljava/lang/Object;


public final scala.util.parsing.combinator.Parsers$ParseResult apply(scala.util.parsing.input.Reader);
  Signature: (Lscala/util/parsing/input/Reader;)Lscala/util/parsing/combinator/Parsers$ParseResult;
  Code:
   Stack=5, Locals=9, Args_size=2
	aload_0
	getfield	Field $outer:Lscala/util/parsing/combinator/Parsers;
	astore	8
	aload_0
	getfield	Field p$18:Lscala/Function0;
	invokeinterface	InterfaceMethod scala/Function0.apply:()Ljava/lang/Object;
	checkcast	class scala/util/parsing/combinator/Parsers$Parser
	aload_1
	invokevirtual	Method scala/util/parsing/combinator/Parsers$Parser.apply:(Lscala/util/parsing/input/Reader;)Lscala/util/parsing/combinator/Parsers$ParseResult;
	astore	7
	aload	7
	instanceof	class scala/util/parsing/combinator/Parsers$Success
	ifeq	l1 // aload
	aload	7
	checkcast	class scala/util/parsing/combinator/Parsers$Success
	astore_2
	aload_2
	invokevirtual	Method scala/util/parsing/combinator/Parsers$Success.result:()Ljava/lang/Object;
	checkcast	class scala/util/parsing/input/Positional
	astore	4
	aload_2
	invokevirtual	Method scala/util/parsing/combinator/Parsers$Success.next:()Lscala/util/parsing/input/Reader;
	astore	5
	iconst_1
	ifeq	l2 // new
	new	class scala/util/parsing/combinator/Parsers$Success
	dup
	aload_0
	getfield	Field $outer:Lscala/util/parsing/combinator/Parsers;
	aload	4
	invokeinterface	InterfaceMethod scala/util/parsing/input/Positional.pos:()Lscala/util/parsing/input/Position;
	getstatic	Field scala/util/parsing/input/NoPosition$.MODULE$:Lscala/util/parsing/input/NoPosition$;
	astore_3
	dup
	ifnonnull	l3 // aload_3
	pop
	aload_3
	ifnull	l4 // aload
	goto	l5 // aload
l3	aload_3
	invokevirtual	Method java/lang/Object.equals:(Ljava/lang/Object;)Z
	ifeq	l5 // aload
l4	aload	4
	aload_1
	invokevirtual	Method scala/util/parsing/input/Reader.pos:()Lscala/util/parsing/input/Position;
	invokeinterface	InterfaceMethod scala/util/parsing/input/Positional.setPos:(Lscala/util/parsing/input/Position;)Lscala/util/parsing/input/Positional;
	goto	l6 // aload
l5	aload	4
l6	aload	5
	invokespecial	Method scala/util/parsing/combinator/Parsers$Success."<init>":(Lscala/util/parsing/combinator/Parsers;Ljava/lang/Object;Lscala/util/parsing/input/Reader;)V
	goto	l7 // areturn
l2	new	class scala/MatchError
	dup
	aload	7
	invokevirtual	Method scala/util/parsing/combinator/Parsers$ParseResult.toString:()Ljava/lang/String;
	invokespecial	Method scala/MatchError."<init>":(Ljava/lang/String;)V
	athrow
l1	aload	7
	instanceof	class scala/util/parsing/combinator/Parsers$NoSuccess
	ifeq	l8 // new
	aload	7
	checkcast	class scala/util/parsing/combinator/Parsers$NoSuccess
	astore	6
	iconst_1
	ifeq	l9 // new
	aload	6
l7	areturn
l9	new	class scala/MatchError
	dup
	aload	7
	invokevirtual	Method scala/util/parsing/combinator/Parsers$ParseResult.toString:()Ljava/lang/String;
	invokespecial	Method scala/MatchError."<init>":(Ljava/lang/String;)V
	athrow
l8	new	class scala/MatchError
	dup
	aload	7
	invokevirtual	Method scala/util/parsing/combinator/Parsers$ParseResult.toString:()Ljava/lang/String;
	invokespecial	Method scala/MatchError."<init>":(Ljava/lang/String;)V
	athrow
  Labels:
   	l3 = 88 // aload_3
   	l4 = 95 // aload
   	l5 = 109 // aload
   	l6 = 111 // aload
   	l2 = 119 // new
   	l1 = 132 // aload
   	l7 = 153 // areturn
   	l9 = 154 // new
   	l8 = 167 // new
  LocalVariableTable: 
   Start  Length  Slot  Name   Signature
   0      180      0    this       Lscala/util/parsing/combinator/Parsers$$anonfun$positioned$1;
   6      174      1    in       Lscala/util/parsing/input/Reader;
   38      94      2    temp96       Lscala/util/parsing/combinator/Parsers$Success;
   47      85      4    temp97       Lscala/util/parsing/input/Positional;
   53      79      5    temp98       Lscala/util/parsing/input/Reader;
   147      6      6    temp99       Lscala/util/parsing/combinator/Parsers$NoSuccess;
   154      13      6    temp99       Lscala/util/parsing/combinator/Parsers$NoSuccess;
   24      156      7    temp95       Lscala/util/parsing/combinator/Parsers$ParseResult;

  Signature: length = 0x2
   00 71 

public scala.Function1 andThen(scala.Function1);
  Signature: (Lscala/Function1;)Lscala/Function1;
  Code:
   Stack=2, Locals=2, Args_size=2
	aload_0
	aload_1
	invokestatic	Method scala/Function1$class.andThen:(Lscala/Function1;Lscala/Function1;)Lscala/Function1;
	areturn
  Labels:
  LocalVariableTable: 
   Start  Length  Slot  Name   Signature
   0      6      0    this       Lscala/util/parsing/combinator/Parsers$$anonfun$positioned$1;
   0      6      1    g       Lscala/Function1;


public scala.Function1 compose(scala.Function1);
  Signature: (Lscala/Function1;)Lscala/Function1;
  Code:
   Stack=2, Locals=2, Args_size=2
	aload_0
	aload_1
	invokestatic	Method scala/Function1$class.compose:(Lscala/Function1;Lscala/Function1;)Lscala/Function1;
	areturn
  Labels:
  LocalVariableTable: 
   Start  Length  Slot  Name   Signature
   0      6      0    this       Lscala/util/parsing/combinator/Parsers$$anonfun$positioned$1;
   0      6      1    g       Lscala/Function1;


public java.lang.String toString();
  Signature: ()Ljava/lang/String;
  Code:
   Stack=1, Locals=1, Args_size=1
	aload_0
	invokestatic	Method scala/Function1$class.toString:(Lscala/Function1;)Ljava/lang/String;
	areturn
  Labels:

}

