Compiled from "Parsers.scala"
public final class scala.util.parsing.combinator.Parsers$$anonfun$chainl1$2 extends java.lang.Object implements scala.Function1,scala.ScalaObject,java.io.Serializable
  SourceFile: "Parsers.scala"
  Scala: length = 0x
   
  InnerClass: 
   public $tilde=class scala/util/parsing/combinator/Parsers$$tilde of class scala/util/parsing/combinator/Parsers
   public final $anonfun$chainl1$2=class scala/util/parsing/combinator/Parsers$$anonfun$chainl1$2 of class scala/util/parsing/combinator/Parsers
   public final $anonfun$apply$9=class scala/util/parsing/combinator/Parsers$$anonfun$chainl1$2$$anonfun$apply$9 of class scala/util/parsing/combinator/Parsers$$anonfun$chainl1$2
  minor version: 0
  major version: 49
  Constant pool:
Asciz	SourceFile;
Asciz	Parsers.scala;
Asciz	<clinit>;
Asciz	()V;
Asciz	Code;
Asciz	serialVersionUID;
Asciz	J;
Asciz	scala/util/parsing/combinator/Parsers$$anonfun$chainl1$2;
class	scala/util/parsing/combinator/Parsers$$anonfun$chainl1$2
NameAndType	serialVersionUID:J
Field	scala/util/parsing/combinator/Parsers$$anonfun$chainl1$2.serialVersionUID:J
Asciz	<init>;
Asciz	(Lscala/util/parsing/combinator/Parsers;)V;
Asciz	LineNumberTable;
Asciz	java/lang/Object;
class	java/lang/Object
NameAndType	"<init>":()V
Method	java/lang/Object."<init>":()V
Asciz	scala/Function1$class;
class	scala/Function1$class
Asciz	$init$;
Asciz	(Lscala/Function1;)V;
NameAndType	$init$:(Lscala/Function1;)V
Method	scala/Function1$class.$init$:(Lscala/Function1;)V
Asciz	this;
Asciz	Lscala/util/parsing/combinator/Parsers$$anonfun$chainl1$2;;
Asciz	$outer;
Asciz	Lscala/util/parsing/combinator/Parsers;;
Asciz	LocalVariableTable;
Asciz	apply;
Asciz	(Ljava/lang/Object;)Ljava/lang/Object;;
Asciz	scala/util/parsing/combinator/Parsers$$tilde;
class	scala/util/parsing/combinator/Parsers$$tilde
Asciz	(Lscala/util/parsing/combinator/Parsers$$tilde;)Ljava/lang/Object;;
NameAndType	apply:(Lscala/util/parsing/combinator/Parsers$$tilde;)Ljava/lang/Object;
Method	scala/util/parsing/combinator/Parsers$$anonfun$chainl1$2.apply:(Lscala/util/parsing/combinator/Parsers$$tilde;)Ljava/lang/Object;
Asciz	v1;
Asciz	Ljava/lang/Object;;
Asciz	_1;
Asciz	()Ljava/lang/Object;;
NameAndType	_1:()Ljava/lang/Object;
Method	scala/util/parsing/combinator/Parsers$$tilde._1:()Ljava/lang/Object;
Asciz	_2;
NameAndType	_2:()Ljava/lang/Object;
Method	scala/util/parsing/combinator/Parsers$$tilde._2:()Ljava/lang/Object;
Asciz	scala/collection/immutable/List;
class	scala/collection/immutable/List
Asciz	scala/util/parsing/combinator/Parsers$$anonfun$chainl1$2$$anonfun$apply$9;
class	scala/util/parsing/combinator/Parsers$$anonfun$chainl1$2$$anonfun$apply$9
Asciz	(Lscala/util/parsing/combinator/Parsers$$anonfun$chainl1$2;)V;
NameAndType	"<init>":(Lscala/util/parsing/combinator/Parsers$$anonfun$chainl1$2;)V
Method	scala/util/parsing/combinator/Parsers$$anonfun$chainl1$2$$anonfun$apply$9."<init>":(Lscala/util/parsing/combinator/Parsers$$anonfun$chainl1$2;)V
Asciz	scala/collection/LinearSeqLike;
class	scala/collection/LinearSeqLike
Asciz	foldLeft;
Asciz	(Ljava/lang/Object;Lscala/Function2;)Ljava/lang/Object;;
NameAndType	foldLeft:(Ljava/lang/Object;Lscala/Function2;)Ljava/lang/Object;
InterfaceMethod	scala/collection/LinearSeqLike.foldLeft:(Ljava/lang/Object;Lscala/Function2;)Ljava/lang/Object;
Asciz	scala/MatchError;
class	scala/MatchError
Asciz	toString;
Asciz	()Ljava/lang/String;;
NameAndType	toString:()Ljava/lang/String;
Method	scala/util/parsing/combinator/Parsers$$tilde.toString:()Ljava/lang/String;
Asciz	(Ljava/lang/String;)V;
NameAndType	"<init>":(Ljava/lang/String;)V
Method	scala/MatchError."<init>":(Ljava/lang/String;)V
Asciz	temp81;
Asciz	Lscala/collection/immutable/List;;
Asciz	temp80;
Asciz	(Lscala/util/parsing/combinator/Parsers$$tilde<TT;Lscala/collection/immutable/List<Lscala/util/parsing/combinator/Parsers$$tilde<Lscala/Function2<TT;TU;TT;>;TU;>;>;>;)TT;;
Asciz	Signature;
Asciz	andThen;
Asciz	(Lscala/Function1;)Lscala/Function1;;
Asciz	(Lscala/Function1;Lscala/Function1;)Lscala/Function1;;
NameAndType	andThen:(Lscala/Function1;Lscala/Function1;)Lscala/Function1;
Method	scala/Function1$class.andThen:(Lscala/Function1;Lscala/Function1;)Lscala/Function1;
Asciz	g;
Asciz	Lscala/Function1;;
Asciz	compose;
NameAndType	compose:(Lscala/Function1;Lscala/Function1;)Lscala/Function1;
Method	scala/Function1$class.compose:(Lscala/Function1;Lscala/Function1;)Lscala/Function1;
Asciz	(Lscala/Function1;)Ljava/lang/String;;
NameAndType	toString:(Lscala/Function1;)Ljava/lang/String;
Method	scala/Function1$class.toString:(Lscala/Function1;)Ljava/lang/String;
Asciz	Scala;
Asciz	InnerClasses;
Asciz	scala/util/parsing/combinator/Parsers;
class	scala/util/parsing/combinator/Parsers
Asciz	$tilde;
Asciz	$anonfun$chainl1$2;
Asciz	$anonfun$apply$9;
Asciz	scala/Function1;
class	scala/Function1
Asciz	scala/ScalaObject;
class	scala/ScalaObject
Asciz	java/io/Serializable;
class	java/io/Serializable

{
public static final long serialVersionUID;
  Signature: J

public static {};
  Signature: ()V
  Code:
   Stack=2, Locals=0, Args_size=0
	lconst_0
	putstatic	Field serialVersionUID:J
	return
  Labels:

public scala.util.parsing.combinator.Parsers$$anonfun$chainl1$2(scala.util.parsing.combinator.Parsers);
  Signature: (Lscala/util/parsing/combinator/Parsers;)V
  Code:
   Stack=1, Locals=2, Args_size=2
	aload_0
	invokespecial	Method java/lang/Object."<init>":()V
	aload_0
	invokestatic	Method scala/Function1$class.$init$:(Lscala/Function1;)V
	return
  Labels:
  LocalVariableTable: 
   Start  Length  Slot  Name   Signature
   0      9      0    this       Lscala/util/parsing/combinator/Parsers$$anonfun$chainl1$2;
   0      9      1    $outer       Lscala/util/parsing/combinator/Parsers;


public final java.lang.Object apply(java.lang.Object);
  Signature: (Ljava/lang/Object;)Ljava/lang/Object;
  Code:
   Stack=2, Locals=2, Args_size=2
	aload_0
	aload_1
	checkcast	class scala/util/parsing/combinator/Parsers$$tilde
	invokevirtual	Method apply:(Lscala/util/parsing/combinator/Parsers$$tilde;)Ljava/lang/Object;
	areturn
  Labels:
  LocalVariableTable: 
   Start  Length  Slot  Name   Signature
   0      9      0    this       Lscala/util/parsing/combinator/Parsers$$anonfun$chainl1$2;
   0      9      1    v1       Ljava/lang/Object;


public final java.lang.Object apply(scala.util.parsing.combinator.Parsers$$tilde);
  Signature: (Lscala/util/parsing/combinator/Parsers$$tilde;)Ljava/lang/Object;
  Code:
   Stack=5, Locals=4, Args_size=2
	aload_1
	ifnull	l1 // new
	aload_1
	invokevirtual	Method scala/util/parsing/combinator/Parsers$$tilde._1:()Ljava/lang/Object;
	astore_3
	aload_1
	invokevirtual	Method scala/util/parsing/combinator/Parsers$$tilde._2:()Ljava/lang/Object;
	checkcast	class scala/collection/immutable/List
	astore_2
	iconst_1
	ifeq	l2 // new
	aload_2
	aload_3
	new	class scala/util/parsing/combinator/Parsers$$anonfun$chainl1$2$$anonfun$apply$9
	dup
	aload_0
	invokespecial	Method scala/util/parsing/combinator/Parsers$$anonfun$chainl1$2$$anonfun$apply$9."<init>":(Lscala/util/parsing/combinator/Parsers$$anonfun$chainl1$2;)V
	invokeinterface	InterfaceMethod scala/collection/LinearSeqLike.foldLeft:(Ljava/lang/Object;Lscala/Function2;)Ljava/lang/Object;
	areturn
l2	new	class scala/MatchError
	dup
	aload_1
	invokevirtual	Method scala/util/parsing/combinator/Parsers$$tilde.toString:()Ljava/lang/String;
	invokespecial	Method scala/MatchError."<init>":(Ljava/lang/String;)V
	athrow
l1	new	class scala/MatchError
	dup
	aload_1
	invokevirtual	Method scala/util/parsing/combinator/Parsers$$tilde.toString:()Ljava/lang/String;
	invokespecial	Method scala/MatchError."<init>":(Ljava/lang/String;)V
	athrow
  Labels:
   	l2 = 37 // new
   	l1 = 49 // new
  LocalVariableTable: 
   Start  Length  Slot  Name   Signature
   0      61      0    this       Lscala/util/parsing/combinator/Parsers$$anonfun$chainl1$2;
   17      32      2    temp81       Lscala/collection/immutable/List;
   9      40      3    temp80       Ljava/lang/Object;

  Signature: length = 0x2
   00 47 

public scala.Function1 andThen(scala.Function1);
  Signature: (Lscala/Function1;)Lscala/Function1;
  Code:
   Stack=2, Locals=2, Args_size=2
	aload_0
	aload_1
	invokestatic	Method scala/Function1$class.andThen:(Lscala/Function1;Lscala/Function1;)Lscala/Function1;
	areturn
  Labels:
  LocalVariableTable: 
   Start  Length  Slot  Name   Signature
   0      6      0    this       Lscala/util/parsing/combinator/Parsers$$anonfun$chainl1$2;
   0      6      1    g       Lscala/Function1;


public scala.Function1 compose(scala.Function1);
  Signature: (Lscala/Function1;)Lscala/Function1;
  Code:
   Stack=2, Locals=2, Args_size=2
	aload_0
	aload_1
	invokestatic	Method scala/Function1$class.compose:(Lscala/Function1;Lscala/Function1;)Lscala/Function1;
	areturn
  Labels:
  LocalVariableTable: 
   Start  Length  Slot  Name   Signature
   0      6      0    this       Lscala/util/parsing/combinator/Parsers$$anonfun$chainl1$2;
   0      6      1    g       Lscala/Function1;


public java.lang.String toString();
  Signature: ()Ljava/lang/String;
  Code:
   Stack=1, Locals=1, Args_size=1
	aload_0
	invokestatic	Method scala/Function1$class.toString:(Lscala/Function1;)Ljava/lang/String;
	areturn
  Labels:

}

