Compiled from "Parsers.scala"
public class scala.util.parsing.combinator.Parsers$Success extends scala.util.parsing.combinator.Parsers$ParseResult implements scala.ScalaObject,scala.Product,java.io.Serializable
  SourceFile: "Parsers.scala"
  Signature: length = 0x2
   00 FFFFFFBF 
  Scala: length = 0x
   
  InnerClass: 
   public Failure=class scala/util/parsing/combinator/Parsers$Failure of class scala/util/parsing/combinator/Parsers
   public Success=class scala/util/parsing/combinator/Parsers$Success of class scala/util/parsing/combinator/Parsers
   public abstract ParseResult=class scala/util/parsing/combinator/Parsers$ParseResult of class scala/util/parsing/combinator/Parsers
  minor version: 0
  major version: 49
  Constant pool:
Asciz	SourceFile;
Asciz	Parsers.scala;
Asciz	successful;
Asciz	Z;
Asciz	next;
Asciz	Lscala/util/parsing/input/Reader;;
Asciz	Lscala/util/parsing/input/Reader<Ljava/lang/Object;>;;
Asciz	Signature;
Asciz	result;
Asciz	Ljava/lang/Object;;
Asciz	TT;;
Asciz	<init>;
Asciz	(Lscala/util/parsing/combinator/Parsers;Ljava/lang/Object;Lscala/util/parsing/input/Reader;)V;
Asciz	Code;
Asciz	LineNumberTable;
Asciz	scala/util/parsing/combinator/Parsers$Success;
class	scala/util/parsing/combinator/Parsers$Success
NameAndType	result:Ljava/lang/Object;
Field	scala/util/parsing/combinator/Parsers$Success.result:Ljava/lang/Object;
NameAndType	next:Lscala/util/parsing/input/Reader;
Field	scala/util/parsing/combinator/Parsers$Success.next:Lscala/util/parsing/input/Reader;
Asciz	scala/util/parsing/combinator/Parsers$ParseResult;
class	scala/util/parsing/combinator/Parsers$ParseResult
Asciz	(Lscala/util/parsing/combinator/Parsers;)V;
NameAndType	"<init>":(Lscala/util/parsing/combinator/Parsers;)V
Method	scala/util/parsing/combinator/Parsers$ParseResult."<init>":(Lscala/util/parsing/combinator/Parsers;)V
Asciz	scala/Product$class;
class	scala/Product$class
Asciz	$init$;
Asciz	(Lscala/Product;)V;
NameAndType	$init$:(Lscala/Product;)V
Method	scala/Product$class.$init$:(Lscala/Product;)V
NameAndType	successful:Z
Field	scala/util/parsing/combinator/Parsers$Success.successful:Z
Asciz	this;
Asciz	Lscala/util/parsing/combinator/Parsers$Success;;
Asciz	$outer;
Asciz	Lscala/util/parsing/combinator/Parsers;;
Asciz	LocalVariableTable;
Asciz	(Lscala/util/parsing/combinator/Parsers;TT;Lscala/util/parsing/input/Reader<Ljava/lang/Object;>;)V;
Asciz	gd1$1;
Asciz	(Ljava/lang/Object;Lscala/util/parsing/input/Reader;)Z;
Asciz	()Ljava/lang/Object;;
NameAndType	result:()Ljava/lang/Object;
Method	scala/util/parsing/combinator/Parsers$Success.result:()Ljava/lang/Object;
Asciz	java/lang/Number;
class	java/lang/Number
Asciz	java/lang/Character;
class	java/lang/Character
Asciz	scala/runtime/BoxesRunTime;
class	scala/runtime/BoxesRunTime
Asciz	equals2;
Asciz	(Ljava/lang/Object;Ljava/lang/Object;)Z;
NameAndType	equals2:(Ljava/lang/Object;Ljava/lang/Object;)Z
Method	scala/runtime/BoxesRunTime.equals2:(Ljava/lang/Object;Ljava/lang/Object;)Z
Asciz	java/lang/Object;
class	java/lang/Object
Asciz	equals;
Asciz	(Ljava/lang/Object;)Z;
NameAndType	equals:(Ljava/lang/Object;)Z
Method	java/lang/Object.equals:(Ljava/lang/Object;)Z
Asciz	()Lscala/util/parsing/input/Reader;;
NameAndType	next:()Lscala/util/parsing/input/Reader;
Method	scala/util/parsing/combinator/Parsers$Success.next:()Lscala/util/parsing/input/Reader;
Asciz	y0;
Asciz	map;
Asciz	(Lscala/Function1;)Lscala/util/parsing/combinator/Parsers$ParseResult;;
Asciz	(Lscala/Function1;)Lscala/util/parsing/combinator/Parsers$Success;;
NameAndType	map:(Lscala/Function1;)Lscala/util/parsing/combinator/Parsers$Success;
Method	scala/util/parsing/combinator/Parsers$Success.map:(Lscala/Function1;)Lscala/util/parsing/combinator/Parsers$Success;
Asciz	f;
Asciz	Lscala/Function1;;
Asciz	scala$util$parsing$combinator$Parsers$Success$$$outer;
Asciz	()Lscala/util/parsing/combinator/Parsers;;
NameAndType	$outer:Lscala/util/parsing/combinator/Parsers;
Field	scala/util/parsing/combinator/Parsers$ParseResult.$outer:Lscala/util/parsing/combinator/Parsers;
Asciz	canEqual;
Asciz	productElement;
Asciz	(I)Ljava/lang/Object;;
Asciz	java/lang/IndexOutOfBoundsException;
class	java/lang/IndexOutOfBoundsException
Asciz	boxToInteger;
Asciz	(I)Ljava/lang/Integer;;
NameAndType	boxToInteger:(I)Ljava/lang/Integer;
Method	scala/runtime/BoxesRunTime.boxToInteger:(I)Ljava/lang/Integer;
Asciz	toString;
Asciz	()Ljava/lang/String;;
NameAndType	toString:()Ljava/lang/String;
Method	java/lang/Object.toString:()Ljava/lang/String;
Asciz	(Ljava/lang/String;)V;
NameAndType	"<init>":(Ljava/lang/String;)V
Method	java/lang/IndexOutOfBoundsException."<init>":(Ljava/lang/String;)V
Asciz	scala/MatchError;
class	scala/MatchError
Method	scala/MatchError."<init>":(Ljava/lang/String;)V
Asciz	productArity;
Asciz	()I;
Asciz	productPrefix;
Asciz	Success;
String	Success
NameAndType	scala$util$parsing$combinator$Parsers$Success$$$outer:()Lscala/util/parsing/combinator/Parsers;
Method	scala/util/parsing/combinator/Parsers$Success.scala$util$parsing$combinator$Parsers$Success$$$outer:()Lscala/util/parsing/combinator/Parsers;
NameAndType	gd1$1:(Ljava/lang/Object;Lscala/util/parsing/input/Reader;)Z
Method	scala/util/parsing/combinator/Parsers$Success.gd1$1:(Ljava/lang/Object;Lscala/util/parsing/input/Reader;)Z
Asciz	scala/Equals;
class	scala/Equals
NameAndType	canEqual:(Ljava/lang/Object;)Z
InterfaceMethod	scala/Equals.canEqual:(Ljava/lang/Object;)Z
Asciz	temp2;
Asciz	temp3;
Asciz	temp4;
Asciz	hashCode;
Asciz	scala/runtime/ScalaRunTime$;
class	scala/runtime/ScalaRunTime$
Asciz	MODULE$;
Asciz	Lscala/runtime/ScalaRunTime$;;
NameAndType	MODULE$:Lscala/runtime/ScalaRunTime$;
Field	scala/runtime/ScalaRunTime$.MODULE$:Lscala/runtime/ScalaRunTime$;
Asciz	_hashCode;
Asciz	(Lscala/Product;)I;
NameAndType	_hashCode:(Lscala/Product;)I
Method	scala/runtime/ScalaRunTime$._hashCode:(Lscala/Product;)I
Asciz	copy;
Asciz	(Ljava/lang/Object;Lscala/util/parsing/input/Reader;)Lscala/util/parsing/combinator/Parsers$Success;;
NameAndType	"<init>":(Lscala/util/parsing/combinator/Parsers;Ljava/lang/Object;Lscala/util/parsing/input/Reader;)V
Method	scala/util/parsing/combinator/Parsers$Success."<init>":(Lscala/util/parsing/combinator/Parsers;Ljava/lang/Object;Lscala/util/parsing/input/Reader;)V
Asciz	()Z;
Asciz	scala/collection/mutable/StringBuilder;
class	scala/collection/mutable/StringBuilder
Asciz	()V;
NameAndType	"<init>":()V
Method	scala/collection/mutable/StringBuilder."<init>":()V
Asciz	[;
String	[
Asciz	append;
Asciz	(Ljava/lang/Object;)Lscala/collection/mutable/StringBuilder;;
NameAndType	append:(Ljava/lang/Object;)Lscala/collection/mutable/StringBuilder;
Method	scala/collection/mutable/StringBuilder.append:(Ljava/lang/Object;)Lscala/collection/mutable/StringBuilder;
Asciz	scala/util/parsing/input/Reader;
class	scala/util/parsing/input/Reader
Asciz	pos;
Asciz	()Lscala/util/parsing/input/Position;;
NameAndType	pos:()Lscala/util/parsing/input/Position;
Method	scala/util/parsing/input/Reader.pos:()Lscala/util/parsing/input/Position;
Asciz	] parsed: ;
String	] parsed: 
Method	scala/collection/mutable/StringBuilder.toString:()Ljava/lang/String;
Asciz	get;
Asciz	()TT;;
Asciz	(Lscala/Function0;)Lscala/util/parsing/combinator/Parsers$ParseResult;;
Asciz	a;
Asciz	Lscala/Function0;;
Asciz	<U:Ljava/lang/Object;>(Lscala/Function0<Lscala/util/parsing/combinator/Parsers$ParseResult<TU;>;>;)Lscala/util/parsing/combinator/Parsers$ParseResult<TU;>;;
Asciz	flatMapWithNext;
Asciz	scala/Function1;
class	scala/Function1
Asciz	apply;
Asciz	(Ljava/lang/Object;)Ljava/lang/Object;;
NameAndType	apply:(Ljava/lang/Object;)Ljava/lang/Object;
InterfaceMethod	scala/Function1.apply:(Ljava/lang/Object;)Ljava/lang/Object;
Asciz	<U:Ljava/lang/Object;>(Lscala/Function1<TT;Lscala/Function1<Lscala/util/parsing/input/Reader<Ljava/lang/Object;>;Lscala/util/parsing/combinator/Parsers$ParseResult<TU;>;>;>;)Lscala/util/parsing/combinator/Parsers$ParseResult<TU;>;;
Asciz	mapPartial;
Asciz	(Lscala/PartialFunction;Lscala/Function1;)Lscala/util/parsing/combinator/Parsers$ParseResult;;
Asciz	scala/PartialFunction;
class	scala/PartialFunction
Asciz	isDefinedAt;
NameAndType	isDefinedAt:(Ljava/lang/Object;)Z
InterfaceMethod	scala/PartialFunction.isDefinedAt:(Ljava/lang/Object;)Z
Asciz	scala/util/parsing/combinator/Parsers$Failure;
class	scala/util/parsing/combinator/Parsers$Failure
Asciz	java/lang/String;
class	java/lang/String
Asciz	(Lscala/util/parsing/combinator/Parsers;Ljava/lang/String;Lscala/util/parsing/input/Reader;)V;
NameAndType	"<init>":(Lscala/util/parsing/combinator/Parsers;Ljava/lang/String;Lscala/util/parsing/input/Reader;)V
Method	scala/util/parsing/combinator/Parsers$Failure."<init>":(Lscala/util/parsing/combinator/Parsers;Ljava/lang/String;Lscala/util/parsing/input/Reader;)V
Asciz	Lscala/PartialFunction;;
Asciz	error;
Asciz	<U:Ljava/lang/Object;>(Lscala/PartialFunction<TT;TU;>;Lscala/Function1<TT;Ljava/lang/String;>;)Lscala/util/parsing/combinator/Parsers$ParseResult<TU;>;;
Asciz	<U:Ljava/lang/Object;>(Lscala/Function1<TT;TU;>;)Lscala/util/parsing/combinator/Parsers$Success<TU;>;;
Asciz	()Lscala/util/parsing/input/Reader<Ljava/lang/Object;>;;
Asciz	copy$default$1;
Asciz	copy$default$2;
Asciz	productElements;
Asciz	()Lscala/collection/Iterator;;
Asciz	(Lscala/Product;)Lscala/collection/Iterator;;
NameAndType	productElements:(Lscala/Product;)Lscala/collection/Iterator;
Method	scala/Product$class.productElements:(Lscala/Product;)Lscala/collection/Iterator;
Asciz	productIterator;
NameAndType	productIterator:(Lscala/Product;)Lscala/collection/Iterator;
Method	scala/Product$class.productIterator:(Lscala/Product;)Lscala/collection/Iterator;
Asciz	<T:Ljava/lang/Object;>Lscala/util/parsing/combinator/Parsers$ParseResult<TT;>;Lscala/ScalaObject;Lscala/Product;;
Asciz	Scala;
Asciz	InnerClasses;
Asciz	scala/util/parsing/combinator/Parsers;
class	scala/util/parsing/combinator/Parsers
Asciz	Failure;
Asciz	ParseResult;
Asciz	scala/ScalaObject;
class	scala/ScalaObject
Asciz	scala/Product;
class	scala/Product
Asciz	java/io/Serializable;
class	java/io/Serializable

{
private final boolean successful;
  Signature: Z

private final scala.util.parsing.input.Reader next;
  Signature: Lscala/util/parsing/input/Reader;
  Signature: length = 0x2
   00 07 

private final java.lang.Object result;
  Signature: Ljava/lang/Object;
  Signature: length = 0x2
   00 0B 

public scala.util.parsing.combinator.Parsers$Success(scala.util.parsing.combinator.Parsers, java.lang.Object, scala.util.parsing.input.Reader);
  Signature: (Lscala/util/parsing/combinator/Parsers;Ljava/lang/Object;Lscala/util/parsing/input/Reader;)V
  Code:
   Stack=2, Locals=4, Args_size=4
	aload_0
	aload_2
	putfield	Field result:Ljava/lang/Object;
	aload_0
	aload_3
	putfield	Field next:Lscala/util/parsing/input/Reader;
	aload_0
	aload_1
	invokespecial	Method scala/util/parsing/combinator/Parsers$ParseResult."<init>":(Lscala/util/parsing/combinator/Parsers;)V
	aload_0
	invokestatic	Method scala/Product$class.$init$:(Lscala/Product;)V
	aload_0
	iconst_1
	putfield	Field successful:Z
	return
  Labels:
  LocalVariableTable: 
   Start  Length  Slot  Name   Signature
   0      25      0    this       Lscala/util/parsing/combinator/Parsers$Success;
   0      25      1    $outer       Lscala/util/parsing/combinator/Parsers;
   0      25      2    result       Ljava/lang/Object;
   0      25      3    next       Lscala/util/parsing/input/Reader;

  Signature: length = 0x2
   00 28 

private final boolean gd1$1(java.lang.Object, scala.util.parsing.input.Reader);
  Signature: (Ljava/lang/Object;Lscala/util/parsing/input/Reader;)Z
  Code:
   Stack=2, Locals=5, Args_size=3
	aload_0
	invokevirtual	Method result:()Ljava/lang/Object;
	astore_3
	aload_1
	aload_3
	if_acmpne	l1 // aload_1
	iconst_1
	goto	l2 // ifeq
l1	aload_1
	ifnonnull	l3 // aload_1
	iconst_0
	goto	l2 // ifeq
l3	aload_1
	instanceof	class java/lang/Number
	ifne	l4 // aload_1
	aload_1
	instanceof	class java/lang/Character
	ifeq	l5 // aload_1
l4	aload_1
	aload_3
	invokestatic	Method scala/runtime/BoxesRunTime.equals2:(Ljava/lang/Object;Ljava/lang/Object;)Z
	goto	l2 // ifeq
l5	aload_1
	aload_3
	invokevirtual	Method java/lang/Object.equals:(Ljava/lang/Object;)Z
l2	ifeq	l6 // iconst_0
	aload_2
	aload_0
	invokevirtual	Method next:()Lscala/util/parsing/input/Reader;
	astore	4
	dup
	ifnonnull	l7 // aload
	pop
	aload	4
	ifnull	l8 // iconst_1
	goto	l6 // iconst_0
l7	aload	4
	invokevirtual	Method java/lang/Object.equals:(Ljava/lang/Object;)Z
	ifeq	l6 // iconst_0
l8	iconst_1
	goto	l9 // ireturn
l6	iconst_0
l9	ireturn
  Labels:
   	l1 = 14 // aload_1
   	l3 = 22 // aload_1
   	l4 = 36 // aload_1
   	l5 = 44 // aload_1
   	l2 = 49 // ifeq
   	l7 = 72 // aload
   	l8 = 80 // iconst_1
   	l6 = 84 // iconst_0
   	l9 = 85 // ireturn
  LocalVariableTable: 
   Start  Length  Slot  Name   Signature
   0      86      0    this       Lscala/util/parsing/combinator/Parsers$Success;
   10      42      3    y0       Ljava/lang/Object;


public scala.util.parsing.combinator.Parsers$ParseResult map(scala.Function1);
  Signature: (Lscala/Function1;)Lscala/util/parsing/combinator/Parsers$ParseResult;
  Code:
   Stack=2, Locals=2, Args_size=2
	aload_0
	aload_1
	invokevirtual	Method map:(Lscala/Function1;)Lscala/util/parsing/combinator/Parsers$Success;
	areturn
  Labels:
  LocalVariableTable: 
   Start  Length  Slot  Name   Signature
   0      6      0    this       Lscala/util/parsing/combinator/Parsers$Success;
   0      6      1    f       Lscala/Function1;


public scala.util.parsing.combinator.Parsers scala$util$parsing$combinator$Parsers$Success$$$outer();
  Signature: ()Lscala/util/parsing/combinator/Parsers;
  Code:
   Stack=1, Locals=1, Args_size=1
	aload_0
	getfield	Field scala/util/parsing/combinator/Parsers$ParseResult.$outer:Lscala/util/parsing/combinator/Parsers;
	areturn
  Labels:

public boolean canEqual(java.lang.Object);
  Signature: (Ljava/lang/Object;)Z
  Code:
   Stack=1, Locals=2, Args_size=2
	aload_1
	instanceof	class scala/util/parsing/combinator/Parsers$Success
	ireturn
  Labels:

public java.lang.Object productElement(int);
  Signature: (I)Ljava/lang/Object;
  Code:
   Stack=3, Locals=2, Args_size=2
	iload_1
	tableswitch{ //0 to 1
		0: 84;
		1: 58;
		default: 24 }
	iconst_1
	ifeq	l1 // new
	new	class java/lang/IndexOutOfBoundsException
	dup
	iload_1
	invokestatic	Method scala/runtime/BoxesRunTime.boxToInteger:(I)Ljava/lang/Integer;
	invokevirtual	Method java/lang/Object.toString:()Ljava/lang/String;
	invokespecial	Method java/lang/IndexOutOfBoundsException."<init>":(Ljava/lang/String;)V
	athrow
l1	new	class scala/MatchError
	dup
	iload_1
	invokestatic	Method scala/runtime/BoxesRunTime.boxToInteger:(I)Ljava/lang/Integer;
	invokevirtual	Method java/lang/Object.toString:()Ljava/lang/String;
	invokespecial	Method scala/MatchError."<init>":(Ljava/lang/String;)V
	athrow
	iconst_1
	ifeq	l2 // new
	aload_0
	invokevirtual	Method next:()Lscala/util/parsing/input/Reader;
	goto	l3 // areturn
l2	new	class scala/MatchError
	dup
	iload_1
	invokestatic	Method scala/runtime/BoxesRunTime.boxToInteger:(I)Ljava/lang/Integer;
	invokevirtual	Method java/lang/Object.toString:()Ljava/lang/String;
	invokespecial	Method scala/MatchError."<init>":(Ljava/lang/String;)V
	athrow
	iconst_1
	ifeq	l4 // new
	aload_0
	invokevirtual	Method result:()Ljava/lang/Object;
l3	areturn
l4	new	class scala/MatchError
	dup
	iload_1
	invokestatic	Method scala/runtime/BoxesRunTime.boxToInteger:(I)Ljava/lang/Integer;
	invokevirtual	Method java/lang/Object.toString:()Ljava/lang/String;
	invokespecial	Method scala/MatchError."<init>":(Ljava/lang/String;)V
	athrow
  Labels:
   	l1 = 43 // new
   	l2 = 69 // new
   	l3 = 92 // areturn
   	l4 = 93 // new

public int productArity();
  Signature: ()I
  Code:
   Stack=1, Locals=1, Args_size=1
	iconst_2
	ireturn
  Labels:

public java.lang.String productPrefix();
  Signature: ()Ljava/lang/String;
  Code:
   Stack=1, Locals=1, Args_size=1
	ldc	String Success
	areturn
  Labels:

public boolean equals(java.lang.Object);
  Signature: (Ljava/lang/Object;)Z
  Code:
   Stack=3, Locals=5, Args_size=2
	aload_0
	aload_1
	if_acmpeq	l1 // iconst_1
	aload_1
	instanceof	class scala/util/parsing/combinator/Parsers$Success
	ifeq	l2 // iconst_1
	aload_1
	checkcast	class scala/util/parsing/combinator/Parsers$Success
	invokevirtual	Method scala$util$parsing$combinator$Parsers$Success$$$outer:()Lscala/util/parsing/combinator/Parsers;
	aload_0
	invokevirtual	Method scala$util$parsing$combinator$Parsers$Success$$$outer:()Lscala/util/parsing/combinator/Parsers;
	if_acmpne	l2 // iconst_1
	aload_1
	checkcast	class scala/util/parsing/combinator/Parsers$Success
	astore_2
	aload_2
	invokevirtual	Method result:()Ljava/lang/Object;
	astore_3
	aload_2
	invokevirtual	Method next:()Lscala/util/parsing/input/Reader;
	astore	4
	aload_0
	aload_3
	aload	4
	invokespecial	Method gd1$1:(Ljava/lang/Object;Lscala/util/parsing/input/Reader;)Z
	ifeq	l3 // iconst_1
	aload_1
	checkcast	class scala/util/parsing/combinator/Parsers$Success
	aload_0
	invokeinterface	InterfaceMethod scala/Equals.canEqual:(Ljava/lang/Object;)Z
	goto	l4 // ifeq
l3	iconst_1
	ifeq	l5 // new
	iconst_0
	goto	l4 // ifeq
l5	new	class scala/MatchError
	dup
	aload_1
	invokevirtual	Method java/lang/Object.toString:()Ljava/lang/String;
	invokespecial	Method scala/MatchError."<init>":(Ljava/lang/String;)V
	athrow
l2	iconst_1
	ifeq	l6 // new
	iconst_0
l4	ifeq	l7 // iconst_0
l1	iconst_1
	goto	l8 // ireturn
l7	iconst_0
l8	ireturn
l6	new	class scala/MatchError
	dup
	aload_1
	invokevirtual	Method java/lang/Object.toString:()Ljava/lang/String;
	invokespecial	Method scala/MatchError."<init>":(Ljava/lang/String;)V
	athrow
  Labels:
   	l3 = 65 // iconst_1
   	l5 = 73 // new
   	l2 = 85 // iconst_1
   	l4 = 90 // ifeq
   	l1 = 93 // iconst_1
   	l7 = 97 // iconst_0
   	l8 = 98 // ireturn
   	l6 = 99 // new
  LocalVariableTable: 
   Start  Length  Slot  Name   Signature
   0      111      0    this       Lscala/util/parsing/combinator/Parsers$Success;
   31      54      2    temp2       Lscala/util/parsing/combinator/Parsers$Success;
   36      49      3    temp3       Ljava/lang/Object;
   42      43      4    temp4       Lscala/util/parsing/input/Reader;


public int hashCode();
  Signature: ()I
  Code:
   Stack=2, Locals=1, Args_size=1
	getstatic	Field scala/runtime/ScalaRunTime$.MODULE$:Lscala/runtime/ScalaRunTime$;
	aload_0
	invokevirtual	Method scala/runtime/ScalaRunTime$._hashCode:(Lscala/Product;)I
	ireturn
  Labels:

public scala.util.parsing.combinator.Parsers$Success copy(java.lang.Object, scala.util.parsing.input.Reader);
  Signature: (Ljava/lang/Object;Lscala/util/parsing/input/Reader;)Lscala/util/parsing/combinator/Parsers$Success;
  Code:
   Stack=5, Locals=3, Args_size=3
	new	class scala/util/parsing/combinator/Parsers$Success
	dup
	aload_0
	invokevirtual	Method scala$util$parsing$combinator$Parsers$Success$$$outer:()Lscala/util/parsing/combinator/Parsers;
	aload_1
	aload_2
	invokespecial	Method "<init>":(Lscala/util/parsing/combinator/Parsers;Ljava/lang/Object;Lscala/util/parsing/input/Reader;)V
	areturn
  Labels:
  LocalVariableTable: 
   Start  Length  Slot  Name   Signature
   0      14      0    this       Lscala/util/parsing/combinator/Parsers$Success;
   0      14      1    result       Ljava/lang/Object;
   0      14      2    next       Lscala/util/parsing/input/Reader;


public boolean successful();
  Signature: ()Z
  Code:
   Stack=1, Locals=1, Args_size=1
	aload_0
	getfield	Field successful:Z
	ireturn
  Labels:

public java.lang.String toString();
  Signature: ()Ljava/lang/String;
  Code:
   Stack=2, Locals=1, Args_size=1
	new	class scala/collection/mutable/StringBuilder
	dup
	invokespecial	Method scala/collection/mutable/StringBuilder."<init>":()V
	ldc	String [
	invokevirtual	Method scala/collection/mutable/StringBuilder.append:(Ljava/lang/Object;)Lscala/collection/mutable/StringBuilder;
	aload_0
	invokevirtual	Method next:()Lscala/util/parsing/input/Reader;
	invokevirtual	Method scala/util/parsing/input/Reader.pos:()Lscala/util/parsing/input/Position;
	invokevirtual	Method scala/collection/mutable/StringBuilder.append:(Ljava/lang/Object;)Lscala/collection/mutable/StringBuilder;
	ldc	String ] parsed: 
	invokevirtual	Method scala/collection/mutable/StringBuilder.append:(Ljava/lang/Object;)Lscala/collection/mutable/StringBuilder;
	aload_0
	invokevirtual	Method result:()Ljava/lang/Object;
	invokevirtual	Method scala/collection/mutable/StringBuilder.append:(Ljava/lang/Object;)Lscala/collection/mutable/StringBuilder;
	invokevirtual	Method scala/collection/mutable/StringBuilder.toString:()Ljava/lang/String;
	areturn
  Labels:

public java.lang.Object get();
  Signature: ()Ljava/lang/Object;
  Code:
   Stack=1, Locals=1, Args_size=1
	aload_0
	invokevirtual	Method result:()Ljava/lang/Object;
	areturn
  Labels:
  Signature: length = 0x2
   00 FFFFFF95 

public scala.util.parsing.combinator.Parsers$ParseResult append(scala.Function0);
  Signature: (Lscala/Function0;)Lscala/util/parsing/combinator/Parsers$ParseResult;
  Code:
   Stack=1, Locals=2, Args_size=2
	aload_0
	areturn
  Labels:
  LocalVariableTable: 
   Start  Length  Slot  Name   Signature
   0      2      0    this       Lscala/util/parsing/combinator/Parsers$Success;
   0      2      1    a       Lscala/Function0;

  Signature: length = 0x2
   00 FFFFFF99 

public scala.util.parsing.combinator.Parsers$ParseResult flatMapWithNext(scala.Function1);
  Signature: (Lscala/Function1;)Lscala/util/parsing/combinator/Parsers$ParseResult;
  Code:
   Stack=2, Locals=2, Args_size=2
	aload_1
	aload_0
	invokevirtual	Method result:()Ljava/lang/Object;
	invokeinterface	InterfaceMethod scala/Function1.apply:(Ljava/lang/Object;)Ljava/lang/Object;
	checkcast	class scala/Function1
	aload_0
	invokevirtual	Method next:()Lscala/util/parsing/input/Reader;
	invokeinterface	InterfaceMethod scala/Function1.apply:(Ljava/lang/Object;)Ljava/lang/Object;
	checkcast	class scala/util/parsing/combinator/Parsers$ParseResult
	areturn
  Labels:
  LocalVariableTable: 
   Start  Length  Slot  Name   Signature
   0      26      0    this       Lscala/util/parsing/combinator/Parsers$Success;
   0      26      1    f       Lscala/Function1;

  Signature: length = 0x2
   00 FFFFFFA1 

public scala.util.parsing.combinator.Parsers$ParseResult mapPartial(scala.PartialFunction, scala.Function1);
  Signature: (Lscala/PartialFunction;Lscala/Function1;)Lscala/util/parsing/combinator/Parsers$ParseResult;
  Code:
   Stack=5, Locals=3, Args_size=3
	aload_1
	aload_0
	invokevirtual	Method result:()Ljava/lang/Object;
	invokeinterface	InterfaceMethod scala/PartialFunction.isDefinedAt:(Ljava/lang/Object;)Z
	ifeq	l1 // new
	new	class scala/util/parsing/combinator/Parsers$Success
	dup
	aload_0
	invokevirtual	Method scala$util$parsing$combinator$Parsers$Success$$$outer:()Lscala/util/parsing/combinator/Parsers;
	aload_1
	aload_0
	invokevirtual	Method result:()Ljava/lang/Object;
	invokeinterface	InterfaceMethod scala/Function1.apply:(Ljava/lang/Object;)Ljava/lang/Object;
	aload_0
	invokevirtual	Method next:()Lscala/util/parsing/input/Reader;
	invokespecial	Method "<init>":(Lscala/util/parsing/combinator/Parsers;Ljava/lang/Object;Lscala/util/parsing/input/Reader;)V
	goto	l2 // areturn
l1	new	class scala/util/parsing/combinator/Parsers$Failure
	dup
	aload_0
	invokevirtual	Method scala$util$parsing$combinator$Parsers$Success$$$outer:()Lscala/util/parsing/combinator/Parsers;
	aload_2
	aload_0
	invokevirtual	Method result:()Ljava/lang/Object;
	invokeinterface	InterfaceMethod scala/Function1.apply:(Ljava/lang/Object;)Ljava/lang/Object;
	checkcast	class java/lang/String
	aload_0
	invokevirtual	Method next:()Lscala/util/parsing/input/Reader;
	invokespecial	Method scala/util/parsing/combinator/Parsers$Failure."<init>":(Lscala/util/parsing/combinator/Parsers;Ljava/lang/String;Lscala/util/parsing/input/Reader;)V
l2	areturn
  Labels:
   	l1 = 41 // new
   	l2 = 69 // areturn
  LocalVariableTable: 
   Start  Length  Slot  Name   Signature
   0      70      0    this       Lscala/util/parsing/combinator/Parsers$Success;
   0      70      1    f       Lscala/PartialFunction;
   0      70      2    error       Lscala/Function1;

  Signature: length = 0x2
   00 FFFFFFB2 

public scala.util.parsing.combinator.Parsers$Success map(scala.Function1);
  Signature: (Lscala/Function1;)Lscala/util/parsing/combinator/Parsers$Success;
  Code:
   Stack=5, Locals=2, Args_size=2
	new	class scala/util/parsing/combinator/Parsers$Success
	dup
	aload_0
	invokevirtual	Method scala$util$parsing$combinator$Parsers$Success$$$outer:()Lscala/util/parsing/combinator/Parsers;
	aload_1
	aload_0
	invokevirtual	Method result:()Ljava/lang/Object;
	invokeinterface	InterfaceMethod scala/Function1.apply:(Ljava/lang/Object;)Ljava/lang/Object;
	aload_0
	invokevirtual	Method next:()Lscala/util/parsing/input/Reader;
	invokespecial	Method "<init>":(Lscala/util/parsing/combinator/Parsers;Ljava/lang/Object;Lscala/util/parsing/input/Reader;)V
	areturn
  Labels:
  LocalVariableTable: 
   Start  Length  Slot  Name   Signature
   0      26      0    this       Lscala/util/parsing/combinator/Parsers$Success;
   0      26      1    f       Lscala/Function1;

  Signature: length = 0x2
   00 FFFFFFB3 

public scala.util.parsing.input.Reader next();
  Signature: ()Lscala/util/parsing/input/Reader;
  Code:
   Stack=1, Locals=1, Args_size=1
	aload_0
	getfield	Field next:Lscala/util/parsing/input/Reader;
	areturn
  Labels:
  Signature: length = 0x2
   00 FFFFFFB4 

public java.lang.Object result();
  Signature: ()Ljava/lang/Object;
  Code:
   Stack=1, Locals=1, Args_size=1
	aload_0
	getfield	Field result:Ljava/lang/Object;
	areturn
  Labels:
  Signature: length = 0x2
   00 FFFFFF95 

public java.lang.Object copy$default$1();
  Signature: ()Ljava/lang/Object;
  Code:
   Stack=1, Locals=1, Args_size=1
	aload_0
	invokevirtual	Method result:()Ljava/lang/Object;
	areturn
  Labels:

public scala.util.parsing.input.Reader copy$default$2();
  Signature: ()Lscala/util/parsing/input/Reader;
  Code:
   Stack=1, Locals=1, Args_size=1
	aload_0
	invokevirtual	Method next:()Lscala/util/parsing/input/Reader;
	areturn
  Labels:

public scala.collection.Iterator productElements();
  Signature: ()Lscala/collection/Iterator;
  Code:
   Stack=1, Locals=1, Args_size=1
	aload_0
	invokestatic	Method scala/Product$class.productElements:(Lscala/Product;)Lscala/collection/Iterator;
	areturn
  Labels:

public scala.collection.Iterator productIterator();
  Signature: ()Lscala/collection/Iterator;
  Code:
   Stack=1, Locals=1, Args_size=1
	aload_0
	invokestatic	Method scala/Product$class.productIterator:(Lscala/Product;)Lscala/collection/Iterator;
	areturn
  Labels:

}

