Compiled from "Parsers.scala"
public final class scala.util.parsing.combinator.Parsers$$anonfun$log$1 extends scala.runtime.AbstractFunction1 implements java.io.Serializable
  SourceFile: "Parsers.scala"
  Scala: length = 0x
   
  InnerClass: 
   public abstract Parser=class scala/util/parsing/combinator/Parsers$Parser of class scala/util/parsing/combinator/Parsers
   public abstract ParseResult=class scala/util/parsing/combinator/Parsers$ParseResult of class scala/util/parsing/combinator/Parsers
   public final $anonfun$log$1=class scala/util/parsing/combinator/Parsers$$anonfun$log$1 of class scala/util/parsing/combinator/Parsers
  minor version: 0
  major version: 49
  Constant pool:
Asciz	SourceFile;
Asciz	Parsers.scala;
Asciz	<clinit>;
Asciz	()V;
Asciz	Code;
Asciz	serialVersionUID;
Asciz	J;
Asciz	scala/util/parsing/combinator/Parsers$$anonfun$log$1;
class	scala/util/parsing/combinator/Parsers$$anonfun$log$1
NameAndType	serialVersionUID:J
Field	scala/util/parsing/combinator/Parsers$$anonfun$log$1.serialVersionUID:J
Asciz	name$1;
Asciz	Ljava/lang/String;;
Asciz	p$12;
Asciz	Lscala/Function0;;
Asciz	<init>;
Asciz	(Lscala/util/parsing/combinator/Parsers;Lscala/Function0;Ljava/lang/String;)V;
Asciz	LineNumberTable;
NameAndType	p$12:Lscala/Function0;
Field	scala/util/parsing/combinator/Parsers$$anonfun$log$1.p$12:Lscala/Function0;
NameAndType	name$1:Ljava/lang/String;
Field	scala/util/parsing/combinator/Parsers$$anonfun$log$1.name$1:Ljava/lang/String;
Asciz	scala/runtime/AbstractFunction1;
class	scala/runtime/AbstractFunction1
NameAndType	"<init>":()V
Method	scala/runtime/AbstractFunction1."<init>":()V
Asciz	this;
Asciz	Lscala/util/parsing/combinator/Parsers$$anonfun$log$1;;
Asciz	$outer;
Asciz	Lscala/util/parsing/combinator/Parsers;;
Asciz	LocalVariableTable;
Asciz	apply;
Asciz	(Ljava/lang/Object;)Ljava/lang/Object;;
Asciz	scala/util/parsing/input/Reader;
class	scala/util/parsing/input/Reader
Asciz	(Lscala/util/parsing/input/Reader;)Lscala/util/parsing/combinator/Parsers$ParseResult;;
NameAndType	apply:(Lscala/util/parsing/input/Reader;)Lscala/util/parsing/combinator/Parsers$ParseResult;
Method	scala/util/parsing/combinator/Parsers$$anonfun$log$1.apply:(Lscala/util/parsing/input/Reader;)Lscala/util/parsing/combinator/Parsers$ParseResult;
Asciz	v1;
Asciz	Ljava/lang/Object;;
Asciz	scala/Predef$;
class	scala/Predef$
Asciz	MODULE$;
Asciz	Lscala/Predef$;;
NameAndType	MODULE$:Lscala/Predef$;
Field	scala/Predef$.MODULE$:Lscala/Predef$;
Asciz	scala/collection/mutable/StringBuilder;
class	scala/collection/mutable/StringBuilder
Method	scala/collection/mutable/StringBuilder."<init>":()V
Asciz	trying ;
String	trying 
Asciz	append;
Asciz	(Ljava/lang/Object;)Lscala/collection/mutable/StringBuilder;;
NameAndType	append:(Ljava/lang/Object;)Lscala/collection/mutable/StringBuilder;
Method	scala/collection/mutable/StringBuilder.append:(Ljava/lang/Object;)Lscala/collection/mutable/StringBuilder;
Asciz	 at ;
String	 at 
Asciz	toString;
Asciz	()Ljava/lang/String;;
NameAndType	toString:()Ljava/lang/String;
Method	scala/collection/mutable/StringBuilder.toString:()Ljava/lang/String;
Asciz	println;
Asciz	(Ljava/lang/Object;)V;
NameAndType	println:(Ljava/lang/Object;)V
Method	scala/Predef$.println:(Ljava/lang/Object;)V
Asciz	scala/Function0;
class	scala/Function0
Asciz	()Ljava/lang/Object;;
NameAndType	apply:()Ljava/lang/Object;
InterfaceMethod	scala/Function0.apply:()Ljava/lang/Object;
Asciz	scala/util/parsing/combinator/Parsers$Parser;
class	scala/util/parsing/combinator/Parsers$Parser
Method	scala/util/parsing/combinator/Parsers$Parser.apply:(Lscala/util/parsing/input/Reader;)Lscala/util/parsing/combinator/Parsers$ParseResult;
Asciz	 --> ;
String	 --> 
Asciz	in;
Asciz	Lscala/util/parsing/input/Reader;;
Asciz	r;
Asciz	Lscala/util/parsing/combinator/Parsers$ParseResult;;
Asciz	(Lscala/util/parsing/input/Reader<Ljava/lang/Object;>;)Lscala/util/parsing/combinator/Parsers$ParseResult<TT;>;;
Asciz	Signature;
Asciz	Scala;
Asciz	InnerClasses;
Asciz	scala/util/parsing/combinator/Parsers;
class	scala/util/parsing/combinator/Parsers
Asciz	Parser;
Asciz	scala/util/parsing/combinator/Parsers$ParseResult;
class	scala/util/parsing/combinator/Parsers$ParseResult
Asciz	ParseResult;
Asciz	$anonfun$log$1;
Asciz	java/io/Serializable;
class	java/io/Serializable

{
public static final long serialVersionUID;
  Signature: J

public final java.lang.String name$1;
  Signature: Ljava/lang/String;

public final scala.Function0 p$12;
  Signature: Lscala/Function0;

public static {};
  Signature: ()V
  Code:
   Stack=2, Locals=0, Args_size=0
	lconst_0
	putstatic	Field serialVersionUID:J
	return
  Labels:

public scala.util.parsing.combinator.Parsers$$anonfun$log$1(scala.util.parsing.combinator.Parsers, scala.Function0, java.lang.String);
  Signature: (Lscala/util/parsing/combinator/Parsers;Lscala/Function0;Ljava/lang/String;)V
  Code:
   Stack=2, Locals=4, Args_size=4
	aload_0
	aload_2
	putfield	Field p$12:Lscala/Function0;
	aload_0
	aload_3
	putfield	Field name$1:Ljava/lang/String;
	aload_0
	invokespecial	Method scala/runtime/AbstractFunction1."<init>":()V
	return
  Labels:
  LocalVariableTable: 
   Start  Length  Slot  Name   Signature
   0      15      0    this       Lscala/util/parsing/combinator/Parsers$$anonfun$log$1;
   0      15      1    $outer       Lscala/util/parsing/combinator/Parsers;


public final java.lang.Object apply(java.lang.Object);
  Signature: (Ljava/lang/Object;)Ljava/lang/Object;
  Code:
   Stack=2, Locals=2, Args_size=2
	aload_0
	aload_1
	checkcast	class scala/util/parsing/input/Reader
	invokevirtual	Method apply:(Lscala/util/parsing/input/Reader;)Lscala/util/parsing/combinator/Parsers$ParseResult;
	areturn
  Labels:
  LocalVariableTable: 
   Start  Length  Slot  Name   Signature
   0      9      0    this       Lscala/util/parsing/combinator/Parsers$$anonfun$log$1;
   0      9      1    v1       Ljava/lang/Object;


public final scala.util.parsing.combinator.Parsers$ParseResult apply(scala.util.parsing.input.Reader);
  Signature: (Lscala/util/parsing/input/Reader;)Lscala/util/parsing/combinator/Parsers$ParseResult;
  Code:
   Stack=3, Locals=3, Args_size=2
	getstatic	Field scala/Predef$.MODULE$:Lscala/Predef$;
	new	class scala/collection/mutable/StringBuilder
	dup
	invokespecial	Method scala/collection/mutable/StringBuilder."<init>":()V
	ldc	String trying 
	invokevirtual	Method scala/collection/mutable/StringBuilder.append:(Ljava/lang/Object;)Lscala/collection/mutable/StringBuilder;
	aload_0
	getfield	Field name$1:Ljava/lang/String;
	invokevirtual	Method scala/collection/mutable/StringBuilder.append:(Ljava/lang/Object;)Lscala/collection/mutable/StringBuilder;
	ldc	String  at 
	invokevirtual	Method scala/collection/mutable/StringBuilder.append:(Ljava/lang/Object;)Lscala/collection/mutable/StringBuilder;
	aload_1
	invokevirtual	Method scala/collection/mutable/StringBuilder.append:(Ljava/lang/Object;)Lscala/collection/mutable/StringBuilder;
	invokevirtual	Method scala/collection/mutable/StringBuilder.toString:()Ljava/lang/String;
	invokevirtual	Method scala/Predef$.println:(Ljava/lang/Object;)V
	aload_0
	getfield	Field p$12:Lscala/Function0;
	invokeinterface	InterfaceMethod scala/Function0.apply:()Ljava/lang/Object;
	checkcast	class scala/util/parsing/combinator/Parsers$Parser
	aload_1
	invokevirtual	Method scala/util/parsing/combinator/Parsers$Parser.apply:(Lscala/util/parsing/input/Reader;)Lscala/util/parsing/combinator/Parsers$ParseResult;
	astore_2
	getstatic	Field scala/Predef$.MODULE$:Lscala/Predef$;
	new	class scala/collection/mutable/StringBuilder
	dup
	invokespecial	Method scala/collection/mutable/StringBuilder."<init>":()V
	aload_0
	getfield	Field name$1:Ljava/lang/String;
	invokevirtual	Method scala/collection/mutable/StringBuilder.append:(Ljava/lang/Object;)Lscala/collection/mutable/StringBuilder;
	ldc	String  --> 
	invokevirtual	Method scala/collection/mutable/StringBuilder.append:(Ljava/lang/Object;)Lscala/collection/mutable/StringBuilder;
	aload_2
	invokevirtual	Method scala/collection/mutable/StringBuilder.append:(Ljava/lang/Object;)Lscala/collection/mutable/StringBuilder;
	invokevirtual	Method scala/collection/mutable/StringBuilder.toString:()Ljava/lang/String;
	invokevirtual	Method scala/Predef$.println:(Ljava/lang/Object;)V
	aload_2
	areturn
  Labels:
  LocalVariableTable: 
   Start  Length  Slot  Name   Signature
   0      88      0    this       Lscala/util/parsing/combinator/Parsers$$anonfun$log$1;
   0      88      1    in       Lscala/util/parsing/input/Reader;
   54      33      2    r       Lscala/util/parsing/combinator/Parsers$ParseResult;

  Signature: length = 0x2
   00 50 

}

