Compiled from "Parsers.scala"
public final class scala.util.parsing.combinator.Parsers$Parser$$anonfun$append$1 extends scala.runtime.AbstractFunction1 implements java.io.Serializable
  SourceFile: "Parsers.scala"
  Scala: length = 0x
   
  InnerClass: 
   public abstract Parser=class scala/util/parsing/combinator/Parsers$Parser of class scala/util/parsing/combinator/Parsers
   public abstract ParseResult=class scala/util/parsing/combinator/Parsers$ParseResult of class scala/util/parsing/combinator/Parsers
   public final $anonfun$append$1=class scala/util/parsing/combinator/Parsers$Parser$$anonfun$append$1 of class scala/util/parsing/combinator/Parsers$Parser
   public final $anonfun$apply$1=class scala/util/parsing/combinator/Parsers$Parser$$anonfun$append$1$$anonfun$apply$1 of class scala/util/parsing/combinator/Parsers$Parser$$anonfun$append$1
  minor version: 0
  major version: 49
  Constant pool:
Asciz	SourceFile;
Asciz	Parsers.scala;
Asciz	<clinit>;
Asciz	()V;
Asciz	Code;
Asciz	serialVersionUID;
Asciz	J;
Asciz	scala/util/parsing/combinator/Parsers$Parser$$anonfun$append$1;
class	scala/util/parsing/combinator/Parsers$Parser$$anonfun$append$1
NameAndType	serialVersionUID:J
Field	scala/util/parsing/combinator/Parsers$Parser$$anonfun$append$1.serialVersionUID:J
Asciz	p$4;
Asciz	Lscala/Function0;;
Asciz	$outer;
Asciz	Lscala/util/parsing/combinator/Parsers$Parser;;
Asciz	<init>;
Asciz	(Lscala/util/parsing/combinator/Parsers$Parser;Lscala/Function0;)V;
Asciz	LineNumberTable;
Asciz	java/lang/NullPointerException;
class	java/lang/NullPointerException
NameAndType	"<init>":()V
Method	java/lang/NullPointerException."<init>":()V
NameAndType	$outer:Lscala/util/parsing/combinator/Parsers$Parser;
Field	scala/util/parsing/combinator/Parsers$Parser$$anonfun$append$1.$outer:Lscala/util/parsing/combinator/Parsers$Parser;
NameAndType	p$4:Lscala/Function0;
Field	scala/util/parsing/combinator/Parsers$Parser$$anonfun$append$1.p$4:Lscala/Function0;
Asciz	scala/runtime/AbstractFunction1;
class	scala/runtime/AbstractFunction1
Method	scala/runtime/AbstractFunction1."<init>":()V
Asciz	this;
Asciz	Lscala/util/parsing/combinator/Parsers$Parser$$anonfun$append$1;;
Asciz	LocalVariableTable;
Asciz	(Lscala/util/parsing/combinator/Parsers$Parser<TT;>;)V;
Asciz	Signature;
Asciz	apply;
Asciz	(Ljava/lang/Object;)Ljava/lang/Object;;
Asciz	scala/util/parsing/input/Reader;
class	scala/util/parsing/input/Reader
Asciz	(Lscala/util/parsing/input/Reader;)Lscala/util/parsing/combinator/Parsers$ParseResult;;
NameAndType	apply:(Lscala/util/parsing/input/Reader;)Lscala/util/parsing/combinator/Parsers$ParseResult;
Method	scala/util/parsing/combinator/Parsers$Parser$$anonfun$append$1.apply:(Lscala/util/parsing/input/Reader;)Lscala/util/parsing/combinator/Parsers$ParseResult;
Asciz	v1;
Asciz	Ljava/lang/Object;;
Asciz	scala/util/parsing/combinator/Parsers$Parser;
class	scala/util/parsing/combinator/Parsers$Parser
Method	scala/util/parsing/combinator/Parsers$Parser.apply:(Lscala/util/parsing/input/Reader;)Lscala/util/parsing/combinator/Parsers$ParseResult;
Asciz	scala/util/parsing/combinator/Parsers$Parser$$anonfun$append$1$$anonfun$apply$1;
class	scala/util/parsing/combinator/Parsers$Parser$$anonfun$append$1$$anonfun$apply$1
Asciz	(Lscala/util/parsing/combinator/Parsers$Parser$$anonfun$append$1;Lscala/util/parsing/input/Reader;)V;
NameAndType	"<init>":(Lscala/util/parsing/combinator/Parsers$Parser$$anonfun$append$1;Lscala/util/parsing/input/Reader;)V
Method	scala/util/parsing/combinator/Parsers$Parser$$anonfun$append$1$$anonfun$apply$1."<init>":(Lscala/util/parsing/combinator/Parsers$Parser$$anonfun$append$1;Lscala/util/parsing/input/Reader;)V
Asciz	scala/util/parsing/combinator/Parsers$ParseResult;
class	scala/util/parsing/combinator/Parsers$ParseResult
Asciz	append;
Asciz	(Lscala/Function0;)Lscala/util/parsing/combinator/Parsers$ParseResult;;
NameAndType	append:(Lscala/Function0;)Lscala/util/parsing/combinator/Parsers$ParseResult;
Method	scala/util/parsing/combinator/Parsers$ParseResult.append:(Lscala/Function0;)Lscala/util/parsing/combinator/Parsers$ParseResult;
Asciz	in$1;
Asciz	Lscala/util/parsing/input/Reader;;
Asciz	(Lscala/util/parsing/input/Reader<Ljava/lang/Object;>;)Lscala/util/parsing/combinator/Parsers$ParseResult<TU;>;;
Asciz	Scala;
Asciz	InnerClasses;
Asciz	scala/util/parsing/combinator/Parsers;
class	scala/util/parsing/combinator/Parsers
Asciz	Parser;
Asciz	ParseResult;
Asciz	$anonfun$append$1;
Asciz	$anonfun$apply$1;
Asciz	java/io/Serializable;
class	java/io/Serializable

{
public static final long serialVersionUID;
  Signature: J

public final scala.Function0 p$4;
  Signature: Lscala/Function0;

public final scala.util.parsing.combinator.Parsers$Parser $outer;
  Signature: Lscala/util/parsing/combinator/Parsers$Parser;

public static {};
  Signature: ()V
  Code:
   Stack=2, Locals=0, Args_size=0
	lconst_0
	putstatic	Field serialVersionUID:J
	return
  Labels:

public scala.util.parsing.combinator.Parsers$Parser$$anonfun$append$1(scala.util.parsing.combinator.Parsers$Parser, scala.Function0);
  Signature: (Lscala/util/parsing/combinator/Parsers$Parser;Lscala/Function0;)V
  Code:
   Stack=2, Locals=3, Args_size=3
	aload_1
	ifnonnull	l1 // aload_0
	new	class java/lang/NullPointerException
	dup
	invokespecial	Method java/lang/NullPointerException."<init>":()V
	athrow
l1	aload_0
	aload_1
	putfield	Field $outer:Lscala/util/parsing/combinator/Parsers$Parser;
	aload_0
	aload_2
	putfield	Field p$4:Lscala/Function0;
	aload_0
	invokespecial	Method scala/runtime/AbstractFunction1."<init>":()V
	return
  Labels:
   	l1 = 12 // aload_0
  LocalVariableTable: 
   Start  Length  Slot  Name   Signature
   0      27      0    this       Lscala/util/parsing/combinator/Parsers$Parser$$anonfun$append$1;
   0      27      1    $outer       Lscala/util/parsing/combinator/Parsers$Parser;

  Signature: length = 0x2
   00 21 

public final java.lang.Object apply(java.lang.Object);
  Signature: (Ljava/lang/Object;)Ljava/lang/Object;
  Code:
   Stack=2, Locals=2, Args_size=2
	aload_0
	aload_1
	checkcast	class scala/util/parsing/input/Reader
	invokevirtual	Method apply:(Lscala/util/parsing/input/Reader;)Lscala/util/parsing/combinator/Parsers$ParseResult;
	areturn
  Labels:
  LocalVariableTable: 
   Start  Length  Slot  Name   Signature
   0      9      0    this       Lscala/util/parsing/combinator/Parsers$Parser$$anonfun$append$1;
   0      9      1    v1       Ljava/lang/Object;


public final scala.util.parsing.combinator.Parsers$ParseResult apply(scala.util.parsing.input.Reader);
  Signature: (Lscala/util/parsing/input/Reader;)Lscala/util/parsing/combinator/Parsers$ParseResult;
  Code:
   Stack=5, Locals=2, Args_size=2
	aload_0
	getfield	Field $outer:Lscala/util/parsing/combinator/Parsers$Parser;
	aload_1
	invokevirtual	Method scala/util/parsing/combinator/Parsers$Parser.apply:(Lscala/util/parsing/input/Reader;)Lscala/util/parsing/combinator/Parsers$ParseResult;
	new	class scala/util/parsing/combinator/Parsers$Parser$$anonfun$append$1$$anonfun$apply$1
	dup
	aload_0
	aload_1
	invokespecial	Method scala/util/parsing/combinator/Parsers$Parser$$anonfun$append$1$$anonfun$apply$1."<init>":(Lscala/util/parsing/combinator/Parsers$Parser$$anonfun$append$1;Lscala/util/parsing/input/Reader;)V
	invokevirtual	Method scala/util/parsing/combinator/Parsers$ParseResult.append:(Lscala/Function0;)Lscala/util/parsing/combinator/Parsers$ParseResult;
	areturn
  Labels:
  LocalVariableTable: 
   Start  Length  Slot  Name   Signature
   0      21      0    this       Lscala/util/parsing/combinator/Parsers$Parser$$anonfun$append$1;
   0      21      1    in$1       Lscala/util/parsing/input/Reader;

  Signature: length = 0x2
   00 3C 

}

