Compiled from "Parsers.scala"
public final class scala.util.parsing.combinator.Parsers$NoSuccess$ extends java.lang.Object implements scala.ScalaObject
  SourceFile: "Parsers.scala"
  Scala: length = 0x
   
  InnerClass: 
   public #77= #51 of #76; //Error=class scala/util/parsing/combinator/Parsers$Error of class scala/util/parsing/combinator/Parsers
   public #78= #21 of #76; //Failure=class scala/util/parsing/combinator/Parsers$Failure of class scala/util/parsing/combinator/Parsers
   public abstract #79= #43 of #76; //ParseResult=class scala/util/parsing/combinator/Parsers$ParseResult of class scala/util/parsing/combinator/Parsers
  minor version: 0
  major version: 49
  Constant pool:
const #1 = Asciz	SourceFile;
const #2 = Asciz	Parsers.scala;
const #3 = Asciz	Scala;
const #4 = Asciz	<init>;
const #5 = Asciz	(Lscala/util/parsing/combinator/Parsers;)V;
const #6 = Asciz	Code;
const #7 = Asciz	LineNumberTable;
const #8 = Asciz	java/lang/Object;
const #9 = class	#8;	//  java/lang/Object
const #10 = Asciz	()V;
const #11 = NameAndType	#4:#10;//  "<init>":()V
const #12 = Method	#9.#11;	//  java/lang/Object."<init>":()V
const #13 = Asciz	this;
const #14 = Asciz	Lscala/util/parsing/combinator/Parsers$NoSuccess$;;
const #15 = Asciz	$outer;
const #16 = Asciz	Lscala/util/parsing/combinator/Parsers;;
const #17 = Asciz	LocalVariableTable;
const #18 = Asciz	unapply;
const #19 = Asciz	(Lscala/util/parsing/combinator/Parsers$ParseResult;)Lscala/Option;;
const #20 = Asciz	scala/util/parsing/combinator/Parsers$Failure;
const #21 = class	#20;	//  scala/util/parsing/combinator/Parsers$Failure
const #22 = Asciz	msg;
const #23 = Asciz	()Ljava/lang/String;;
const #24 = NameAndType	#22:#23;//  msg:()Ljava/lang/String;
const #25 = Method	#21.#24;	//  scala/util/parsing/combinator/Parsers$Failure.msg:()Ljava/lang/String;
const #26 = Asciz	next;
const #27 = Asciz	()Lscala/util/parsing/input/Reader;;
const #28 = NameAndType	#26:#27;//  next:()Lscala/util/parsing/input/Reader;
const #29 = Method	#21.#28;	//  scala/util/parsing/combinator/Parsers$Failure.next:()Lscala/util/parsing/input/Reader;
const #30 = Asciz	scala/Some;
const #31 = class	#30;	//  scala/Some
const #32 = Asciz	scala/Tuple2;
const #33 = class	#32;	//  scala/Tuple2
const #34 = Asciz	(Ljava/lang/Object;Ljava/lang/Object;)V;
const #35 = NameAndType	#4:#34;//  "<init>":(Ljava/lang/Object;Ljava/lang/Object;)V
const #36 = Method	#33.#35;	//  scala/Tuple2."<init>":(Ljava/lang/Object;Ljava/lang/Object;)V
const #37 = Asciz	(Ljava/lang/Object;)V;
const #38 = NameAndType	#4:#37;//  "<init>":(Ljava/lang/Object;)V
const #39 = Method	#31.#38;	//  scala/Some."<init>":(Ljava/lang/Object;)V
const #40 = Asciz	scala/MatchError;
const #41 = class	#40;	//  scala/MatchError
const #42 = Asciz	scala/util/parsing/combinator/Parsers$ParseResult;
const #43 = class	#42;	//  scala/util/parsing/combinator/Parsers$ParseResult
const #44 = Asciz	toString;
const #45 = NameAndType	#44:#23;//  toString:()Ljava/lang/String;
const #46 = Method	#43.#45;	//  scala/util/parsing/combinator/Parsers$ParseResult.toString:()Ljava/lang/String;
const #47 = Asciz	(Ljava/lang/String;)V;
const #48 = NameAndType	#4:#47;//  "<init>":(Ljava/lang/String;)V
const #49 = Method	#41.#48;	//  scala/MatchError."<init>":(Ljava/lang/String;)V
const #50 = Asciz	scala/util/parsing/combinator/Parsers$Error;
const #51 = class	#50;	//  scala/util/parsing/combinator/Parsers$Error
const #52 = Method	#51.#24;	//  scala/util/parsing/combinator/Parsers$Error.msg:()Ljava/lang/String;
const #53 = Method	#51.#28;	//  scala/util/parsing/combinator/Parsers$Error.next:()Lscala/util/parsing/input/Reader;
const #54 = Asciz	scala/None$;
const #55 = class	#54;	//  scala/None$
const #56 = Asciz	MODULE$;
const #57 = Asciz	Lscala/None$;;
const #58 = NameAndType	#56:#57;//  MODULE$:Lscala/None$;
const #59 = Field	#55.#58;	//  scala/None$.MODULE$:Lscala/None$;
const #60 = Asciz	x;
const #61 = Asciz	Lscala/util/parsing/combinator/Parsers$ParseResult;;
const #62 = Asciz	temp7;
const #63 = Asciz	Lscala/util/parsing/combinator/Parsers$Failure;;
const #64 = Asciz	temp8;
const #65 = Asciz	Ljava/lang/String;;
const #66 = Asciz	temp9;
const #67 = Asciz	Lscala/util/parsing/input/Reader;;
const #68 = Asciz	temp10;
const #69 = Asciz	Lscala/util/parsing/combinator/Parsers$Error;;
const #70 = Asciz	temp11;
const #71 = Asciz	temp12;
const #72 = Asciz	<T:Ljava/lang/Object;>(Lscala/util/parsing/combinator/Parsers$ParseResult<TT;>;)Lscala/Option<Lscala/Tuple2<Ljava/lang/String;Lscala/util/parsing/input/Reader<Ljava/lang/Object;>;>;>;;
const #73 = Asciz	Signature;
const #74 = Asciz	InnerClasses;
const #75 = Asciz	scala/util/parsing/combinator/Parsers;
const #76 = class	#75;	//  scala/util/parsing/combinator/Parsers
const #77 = Asciz	Error;
const #78 = Asciz	Failure;
const #79 = Asciz	ParseResult;
const #80 = Asciz	scala/util/parsing/combinator/Parsers$NoSuccess$;
const #81 = class	#80;	//  scala/util/parsing/combinator/Parsers$NoSuccess$
const #82 = Asciz	scala/ScalaObject;
const #83 = class	#82;	//  scala/ScalaObject

{
public scala.util.parsing.combinator.Parsers$NoSuccess$(scala.util.parsing.combinator.Parsers);
  Code:
   Stack=1, Locals=2, Args_size=2
   0:	aload_0
   1:	invokespecial	#12; //Method java/lang/Object."<init>":()V
   4:	return
  LineNumberTable: 
   line 158: 0

  LocalVariableTable: 
   Start  Length  Slot  Name   Signature
   0      5      0    this       Lscala/util/parsing/combinator/Parsers$NoSuccess$;
   0      5      1    $outer       Lscala/util/parsing/combinator/Parsers;


public scala.Option unapply(scala.util.parsing.combinator.Parsers$ParseResult);
  Code:
   Stack=6, Locals=8, Args_size=2
   0:	aload_1
   1:	instanceof	#21; //class scala/util/parsing/combinator/Parsers$Failure
   4:	ifeq	59
   7:	aload_1
   8:	checkcast	#21; //class scala/util/parsing/combinator/Parsers$Failure
   11:	astore_2
   12:	aload_2
   13:	invokevirtual	#25; //Method scala/util/parsing/combinator/Parsers$Failure.msg:()Ljava/lang/String;
   16:	astore_3
   17:	aload_2
   18:	invokevirtual	#29; //Method scala/util/parsing/combinator/Parsers$Failure.next:()Lscala/util/parsing/input/Reader;
   21:	astore	4
   23:	iconst_1
   24:	ifeq	47
   27:	new	#31; //class scala/Some
   30:	dup
   31:	new	#33; //class scala/Tuple2
   34:	dup
   35:	aload_3
   36:	aload	4
   38:	invokespecial	#36; //Method scala/Tuple2."<init>":(Ljava/lang/Object;Ljava/lang/Object;)V
   41:	invokespecial	#39; //Method scala/Some."<init>":(Ljava/lang/Object;)V
   44:	goto	130
   47:	new	#41; //class scala/MatchError
   50:	dup
   51:	aload_1
   52:	invokevirtual	#46; //Method scala/util/parsing/combinator/Parsers$ParseResult.toString:()Ljava/lang/String;
   55:	invokespecial	#49; //Method scala/MatchError."<init>":(Ljava/lang/String;)V
   58:	athrow
   59:	aload_1
   60:	instanceof	#51; //class scala/util/parsing/combinator/Parsers$Error
   63:	ifeq	123
   66:	aload_1
   67:	checkcast	#51; //class scala/util/parsing/combinator/Parsers$Error
   70:	astore	5
   72:	aload	5
   74:	invokevirtual	#52; //Method scala/util/parsing/combinator/Parsers$Error.msg:()Ljava/lang/String;
   77:	astore	6
   79:	aload	5
   81:	invokevirtual	#53; //Method scala/util/parsing/combinator/Parsers$Error.next:()Lscala/util/parsing/input/Reader;
   84:	astore	7
   86:	iconst_1
   87:	ifeq	111
   90:	new	#31; //class scala/Some
   93:	dup
   94:	new	#33; //class scala/Tuple2
   97:	dup
   98:	aload	6
   100:	aload	7
   102:	invokespecial	#36; //Method scala/Tuple2."<init>":(Ljava/lang/Object;Ljava/lang/Object;)V
   105:	invokespecial	#39; //Method scala/Some."<init>":(Ljava/lang/Object;)V
   108:	goto	130
   111:	new	#41; //class scala/MatchError
   114:	dup
   115:	aload_1
   116:	invokevirtual	#46; //Method scala/util/parsing/combinator/Parsers$ParseResult.toString:()Ljava/lang/String;
   119:	invokespecial	#49; //Method scala/MatchError."<init>":(Ljava/lang/String;)V
   122:	athrow
   123:	iconst_1
   124:	ifeq	131
   127:	getstatic	#59; //Field scala/None$.MODULE$:Lscala/None$;
   130:	areturn
   131:	new	#41; //class scala/MatchError
   134:	dup
   135:	aload_1
   136:	invokevirtual	#46; //Method scala/util/parsing/combinator/Parsers$ParseResult.toString:()Ljava/lang/String;
   139:	invokespecial	#49; //Method scala/MatchError."<init>":(Ljava/lang/String;)V
   142:	athrow
  LineNumberTable: 
   line 159: 0
   line 21: 23
   line 160: 27
   line 159: 47
   line 21: 86
   line 161: 90
   line 159: 111
   line 21: 123
   line 162: 127
   line 159: 130

  LocalVariableTable: 
   Start  Length  Slot  Name   Signature
   0      143      0    this       Lscala/util/parsing/combinator/Parsers$NoSuccess$;
   0      143      1    x       Lscala/util/parsing/combinator/Parsers$ParseResult;
   12      47      2    temp7       Lscala/util/parsing/combinator/Parsers$Failure;
   17      42      3    temp8       Ljava/lang/String;
   23      36      4    temp9       Lscala/util/parsing/input/Reader;
   72      51      5    temp10       Lscala/util/parsing/combinator/Parsers$Error;
   79      44      6    temp11       Ljava/lang/String;
   86      37      7    temp12       Lscala/util/parsing/input/Reader;

  Signature: length = 0x2
   00 48 

}

