Compiled from "Parsers.scala"
public abstract class scala.util.parsing.combinator.Parsers$ParseResult extends java.lang.Object implements scala.ScalaObject
  SourceFile: "Parsers.scala"
  Signature: length = 0x2
   00 3F 
  Scala: length = 0x
   
  InnerClass: 
   public abstract ParseResult=class scala/util/parsing/combinator/Parsers$ParseResult of class scala/util/parsing/combinator/Parsers
  minor version: 0
  major version: 49
  Constant pool:
Asciz	SourceFile;
Asciz	Parsers.scala;
Asciz	$outer;
Asciz	Lscala/util/parsing/combinator/Parsers;;
Asciz	<init>;
Asciz	(Lscala/util/parsing/combinator/Parsers;)V;
Asciz	Code;
Asciz	LineNumberTable;
Asciz	java/lang/NullPointerException;
class	java/lang/NullPointerException
Asciz	()V;
NameAndType	"<init>":()V
Method	java/lang/NullPointerException."<init>":()V
Asciz	scala/util/parsing/combinator/Parsers$ParseResult;
class	scala/util/parsing/combinator/Parsers$ParseResult
NameAndType	$outer:Lscala/util/parsing/combinator/Parsers;
Field	scala/util/parsing/combinator/Parsers$ParseResult.$outer:Lscala/util/parsing/combinator/Parsers;
Asciz	java/lang/Object;
class	java/lang/Object
Method	java/lang/Object."<init>":()V
Asciz	this;
Asciz	Lscala/util/parsing/combinator/Parsers$ParseResult;;
Asciz	LocalVariableTable;
Asciz	Signature;
Asciz	scala$util$parsing$combinator$Parsers$ParseResult$$$outer;
Asciz	()Lscala/util/parsing/combinator/Parsers;;
Asciz	successful;
Asciz	()Z;
Asciz	next;
Asciz	()Lscala/util/parsing/input/Reader;;
Asciz	()Lscala/util/parsing/input/Reader<Ljava/lang/Object;>;;
Asciz	getOrElse;
Asciz	(Lscala/Function0;)Ljava/lang/Object;;
Asciz	isEmpty;
NameAndType	isEmpty:()Z
Method	scala/util/parsing/combinator/Parsers$ParseResult.isEmpty:()Z
Asciz	scala/Function0;
class	scala/Function0
Asciz	apply;
Asciz	()Ljava/lang/Object;;
NameAndType	apply:()Ljava/lang/Object;
InterfaceMethod	scala/Function0.apply:()Ljava/lang/Object;
Asciz	get;
NameAndType	get:()Ljava/lang/Object;
Method	scala/util/parsing/combinator/Parsers$ParseResult.get:()Ljava/lang/Object;
Asciz	default;
Asciz	Lscala/Function0;;
Asciz	<B:Ljava/lang/Object;>(Lscala/Function0<TB;>;)TB;;
Asciz	()TT;;
NameAndType	successful:()Z
Method	scala/util/parsing/combinator/Parsers$ParseResult.successful:()Z
Asciz	append;
Asciz	(Lscala/Function0;)Lscala/util/parsing/combinator/Parsers$ParseResult;;
Asciz	<U:Ljava/lang/Object;>(Lscala/Function0<Lscala/util/parsing/combinator/Parsers$ParseResult<TU;>;>;)Lscala/util/parsing/combinator/Parsers$ParseResult<TU;>;;
Asciz	flatMapWithNext;
Asciz	(Lscala/Function1;)Lscala/util/parsing/combinator/Parsers$ParseResult;;
Asciz	<U:Ljava/lang/Object;>(Lscala/Function1<TT;Lscala/Function1<Lscala/util/parsing/input/Reader<Ljava/lang/Object;>;Lscala/util/parsing/combinator/Parsers$ParseResult<TU;>;>;>;)Lscala/util/parsing/combinator/Parsers$ParseResult<TU;>;;
Asciz	mapPartial;
Asciz	(Lscala/PartialFunction;Lscala/Function1;)Lscala/util/parsing/combinator/Parsers$ParseResult;;
Asciz	<U:Ljava/lang/Object;>(Lscala/PartialFunction<TT;TU;>;Lscala/Function1<TT;Ljava/lang/String;>;)Lscala/util/parsing/combinator/Parsers$ParseResult<TU;>;;
Asciz	map;
Asciz	<U:Ljava/lang/Object;>(Lscala/Function1<TT;TU;>;)Lscala/util/parsing/combinator/Parsers$ParseResult<TU;>;;
Asciz	<T:Ljava/lang/Object;>Ljava/lang/Object;Lscala/ScalaObject;;
Asciz	Scala;
Asciz	InnerClasses;
Asciz	scala/util/parsing/combinator/Parsers;
class	scala/util/parsing/combinator/Parsers
Asciz	ParseResult;
Asciz	scala/ScalaObject;
class	scala/ScalaObject

{
public final scala.util.parsing.combinator.Parsers $outer;
  Signature: Lscala/util/parsing/combinator/Parsers;

public scala.util.parsing.combinator.Parsers$ParseResult(scala.util.parsing.combinator.Parsers);
  Signature: (Lscala/util/parsing/combinator/Parsers;)V
  Code:
   Stack=2, Locals=2, Args_size=2
	aload_1
	ifnonnull	l1 // aload_0
	new	class java/lang/NullPointerException
	dup
	invokespecial	Method java/lang/NullPointerException."<init>":()V
	athrow
l1	aload_0
	aload_1
	putfield	Field $outer:Lscala/util/parsing/combinator/Parsers;
	aload_0
	invokespecial	Method java/lang/Object."<init>":()V
	return
  Labels:
   	l1 = 12 // aload_0
  LocalVariableTable: 
   Start  Length  Slot  Name   Signature
   0      22      0    this       Lscala/util/parsing/combinator/Parsers$ParseResult;
   0      22      1    $outer       Lscala/util/parsing/combinator/Parsers;

  Signature: length = 0x2
   00 06 

public scala.util.parsing.combinator.Parsers scala$util$parsing$combinator$Parsers$ParseResult$$$outer();
  Signature: ()Lscala/util/parsing/combinator/Parsers;
  Code:
   Stack=1, Locals=1, Args_size=1
	aload_0
	getfield	Field $outer:Lscala/util/parsing/combinator/Parsers;
	areturn
  Labels:

public abstract boolean successful();
  Signature: ()Z

public abstract scala.util.parsing.input.Reader next();
  Signature: ()Lscala/util/parsing/input/Reader;
  Signature: length = 0x2
   00 1F 

public java.lang.Object getOrElse(scala.Function0);
  Signature: (Lscala/Function0;)Ljava/lang/Object;
  Code:
   Stack=1, Locals=2, Args_size=2
	aload_0
	invokevirtual	Method isEmpty:()Z
	ifeq	l1 // aload_0
	aload_1
	invokeinterface	InterfaceMethod scala/Function0.apply:()Ljava/lang/Object;
	goto	l2 // areturn
l1	aload_0
	invokevirtual	Method get:()Ljava/lang/Object;
l2	areturn
  Labels:
   	l1 = 16 // aload_0
   	l2 = 20 // areturn
  LocalVariableTable: 
   Start  Length  Slot  Name   Signature
   0      21      0    this       Lscala/util/parsing/combinator/Parsers$ParseResult;
   0      21      1    default       Lscala/Function0;

  Signature: length = 0x2
   00 30 

public abstract java.lang.Object get();
  Signature: ()Ljava/lang/Object;
  Signature: length = 0x2
   00 31 

public boolean isEmpty();
  Signature: ()Z
  Code:
   Stack=1, Locals=1, Args_size=1
	aload_0
	invokevirtual	Method successful:()Z
	ifeq	l1 // iconst_1
	iconst_0
	goto	l2 // ireturn
l1	iconst_1
l2	ireturn
  Labels:
   	l1 = 11 // iconst_1
   	l2 = 12 // ireturn

public abstract scala.util.parsing.combinator.Parsers$ParseResult append(scala.Function0);
  Signature: (Lscala/Function0;)Lscala/util/parsing/combinator/Parsers$ParseResult;
  Signature: length = 0x2
   00 36 

public abstract scala.util.parsing.combinator.Parsers$ParseResult flatMapWithNext(scala.Function1);
  Signature: (Lscala/Function1;)Lscala/util/parsing/combinator/Parsers$ParseResult;
  Signature: length = 0x2
   00 39 

public abstract scala.util.parsing.combinator.Parsers$ParseResult mapPartial(scala.PartialFunction, scala.Function1);
  Signature: (Lscala/PartialFunction;Lscala/Function1;)Lscala/util/parsing/combinator/Parsers$ParseResult;
  Signature: length = 0x2
   00 3C 

public abstract scala.util.parsing.combinator.Parsers$ParseResult map(scala.Function1);
  Signature: (Lscala/Function1;)Lscala/util/parsing/combinator/Parsers$ParseResult;
  Signature: length = 0x2
   00 3E 

}

