Compiled from "Parsers.scala"
public final class scala.util.parsing.combinator.Parsers$Parser$$anon$4 extends scala.util.parsing.combinator.Parsers$Parser
  SourceFile: "Parsers.scala"
  Signature: length = 0x2
   00 FFFFFF86 
  Scala: length = 0x
   
  InnerClass: 
   public #137= #84 of #89; //Error=class scala/util/parsing/combinator/Parsers$Error of class scala/util/parsing/combinator/Parsers
   public abstract #138= #23 of #89; //Parser=class scala/util/parsing/combinator/Parsers$Parser of class scala/util/parsing/combinator/Parsers
   public #139= #86 of #89; //Failure=class scala/util/parsing/combinator/Parsers$Failure of class scala/util/parsing/combinator/Parsers
   public #140= #56 of #89; //Success=class scala/util/parsing/combinator/Parsers$Success of class scala/util/parsing/combinator/Parsers
   public abstract #143= #142 of #89; //ParseResult=class scala/util/parsing/combinator/Parsers$ParseResult of class scala/util/parsing/combinator/Parsers
   public final #144= #17 of #23; //$anon$4=class scala/util/parsing/combinator/Parsers$Parser$$anon$4 of class scala/util/parsing/combinator/Parsers$Parser
  minor version: 0
  major version: 49
  Constant pool:
const #1 = Asciz	SourceFile;
const #2 = Asciz	Parsers.scala;
const #3 = Asciz	q$1;
const #4 = Asciz	Lscala/Function0;;
const #5 = Asciz	$outer;
const #6 = Asciz	Lscala/util/parsing/combinator/Parsers$Parser;;
const #7 = Asciz	<init>;
const #8 = Asciz	(Lscala/util/parsing/combinator/Parsers$Parser;Lscala/Function0;)V;
const #9 = Asciz	Code;
const #10 = Asciz	LineNumberTable;
const #11 = Asciz	java/lang/NullPointerException;
const #12 = class	#11;	//  java/lang/NullPointerException
const #13 = Asciz	()V;
const #14 = NameAndType	#7:#13;//  "<init>":()V
const #15 = Method	#12.#14;	//  java/lang/NullPointerException."<init>":()V
const #16 = Asciz	scala/util/parsing/combinator/Parsers$Parser$$anon$4;
const #17 = class	#16;	//  scala/util/parsing/combinator/Parsers$Parser$$anon$4
const #18 = NameAndType	#5:#6;//  $outer:Lscala/util/parsing/combinator/Parsers$Parser;
const #19 = Field	#17.#18;	//  scala/util/parsing/combinator/Parsers$Parser$$anon$4.$outer:Lscala/util/parsing/combinator/Parsers$Parser;
const #20 = NameAndType	#3:#4;//  q$1:Lscala/Function0;
const #21 = Field	#17.#20;	//  scala/util/parsing/combinator/Parsers$Parser$$anon$4.q$1:Lscala/Function0;
const #22 = Asciz	scala/util/parsing/combinator/Parsers$Parser;
const #23 = class	#22;	//  scala/util/parsing/combinator/Parsers$Parser
const #24 = Asciz	scala$util$parsing$combinator$Parsers$Parser$$$outer;
const #25 = Asciz	()Lscala/util/parsing/combinator/Parsers;;
const #26 = NameAndType	#24:#25;//  scala$util$parsing$combinator$Parsers$Parser$$$outer:()Lscala/util/parsing/combinator/Parsers;
const #27 = Method	#23.#26;	//  scala/util/parsing/combinator/Parsers$Parser.scala$util$parsing$combinator$Parsers$Parser$$$outer:()Lscala/util/parsing/combinator/Parsers;
const #28 = Asciz	(Lscala/util/parsing/combinator/Parsers;)V;
const #29 = NameAndType	#7:#28;//  "<init>":(Lscala/util/parsing/combinator/Parsers;)V
const #30 = Method	#23.#29;	//  scala/util/parsing/combinator/Parsers$Parser."<init>":(Lscala/util/parsing/combinator/Parsers;)V
const #31 = Asciz	this;
const #32 = Asciz	Lscala/util/parsing/combinator/Parsers$Parser$$anon$4;;
const #33 = Asciz	LocalVariableTable;
const #34 = Asciz	(Lscala/util/parsing/combinator/Parsers$Parser<TT;>;)V;
const #35 = Asciz	Signature;
const #36 = Asciz	apply;
const #37 = Asciz	(Ljava/lang/Object;)Ljava/lang/Object;;
const #38 = Asciz	scala/util/parsing/input/Reader;
const #39 = class	#38;	//  scala/util/parsing/input/Reader
const #40 = Asciz	(Lscala/util/parsing/input/Reader;)Lscala/util/parsing/combinator/Parsers$ParseResult;;
const #41 = NameAndType	#36:#40;//  apply:(Lscala/util/parsing/input/Reader;)Lscala/util/parsing/combinator/Parsers$ParseResult;
const #42 = Method	#17.#41;	//  scala/util/parsing/combinator/Parsers$Parser$$anon$4.apply:(Lscala/util/parsing/input/Reader;)Lscala/util/parsing/combinator/Parsers$ParseResult;
const #43 = Asciz	v1;
const #44 = Asciz	Ljava/lang/Object;;
const #45 = Asciz	toString;
const #46 = Asciz	()Ljava/lang/String;;
const #47 = Asciz	|||;
const #48 = String	#47;	//  |||
const #49 = Method	#23.#41;	//  scala/util/parsing/combinator/Parsers$Parser.apply:(Lscala/util/parsing/input/Reader;)Lscala/util/parsing/combinator/Parsers$ParseResult;
const #50 = Asciz	scala/Function0;
const #51 = class	#50;	//  scala/Function0
const #52 = Asciz	()Ljava/lang/Object;;
const #53 = NameAndType	#36:#52;//  apply:()Ljava/lang/Object;
const #54 = InterfaceMethod	#51.#53;	//  scala/Function0.apply:()Ljava/lang/Object;
const #55 = Asciz	scala/util/parsing/combinator/Parsers$Success;
const #56 = class	#55;	//  scala/util/parsing/combinator/Parsers$Success
const #57 = Asciz	next;
const #58 = Asciz	()Lscala/util/parsing/input/Reader;;
const #59 = NameAndType	#57:#58;//  next:()Lscala/util/parsing/input/Reader;
const #60 = Method	#56.#59;	//  scala/util/parsing/combinator/Parsers$Success.next:()Lscala/util/parsing/input/Reader;
const #61 = Asciz	pos;
const #62 = Asciz	()Lscala/util/parsing/input/Position;;
const #63 = NameAndType	#61:#62;//  pos:()Lscala/util/parsing/input/Position;
const #64 = Method	#39.#63;	//  scala/util/parsing/input/Reader.pos:()Lscala/util/parsing/input/Position;
const #65 = Asciz	scala/util/parsing/input/Position;
const #66 = class	#65;	//  scala/util/parsing/input/Position
const #67 = Asciz	$less;
const #68 = Asciz	(Lscala/util/parsing/input/Position;)Z;
const #69 = NameAndType	#67:#68;//  $less:(Lscala/util/parsing/input/Position;)Z
const #70 = InterfaceMethod	#66.#69;	//  scala/util/parsing/input/Position.$less:(Lscala/util/parsing/input/Position;)Z
const #71 = Asciz	scala/MatchError;
const #72 = class	#71;	//  scala/MatchError
const #73 = Asciz	scala/Tuple2;
const #74 = class	#73;	//  scala/Tuple2
const #75 = Asciz	(Ljava/lang/Object;Ljava/lang/Object;)V;
const #76 = NameAndType	#7:#75;//  "<init>":(Ljava/lang/Object;Ljava/lang/Object;)V
const #77 = Method	#74.#76;	//  scala/Tuple2."<init>":(Ljava/lang/Object;Ljava/lang/Object;)V
const #78 = NameAndType	#45:#46;//  toString:()Ljava/lang/String;
const #79 = Method	#74.#78;	//  scala/Tuple2.toString:()Ljava/lang/String;
const #80 = Asciz	(Ljava/lang/String;)V;
const #81 = NameAndType	#7:#80;//  "<init>":(Ljava/lang/String;)V
const #82 = Method	#72.#81;	//  scala/MatchError."<init>":(Ljava/lang/String;)V
const #83 = Asciz	scala/util/parsing/combinator/Parsers$Error;
const #84 = class	#83;	//  scala/util/parsing/combinator/Parsers$Error
const #85 = Asciz	scala/util/parsing/combinator/Parsers$Failure;
const #86 = class	#85;	//  scala/util/parsing/combinator/Parsers$Failure
const #87 = Method	#86.#59;	//  scala/util/parsing/combinator/Parsers$Failure.next:()Lscala/util/parsing/input/Reader;
const #88 = Asciz	scala/util/parsing/combinator/Parsers;
const #89 = class	#88;	//  scala/util/parsing/combinator/Parsers
const #90 = Asciz	NoSuccess;
const #91 = Asciz	()Lscala/util/parsing/combinator/Parsers$NoSuccess$;;
const #92 = NameAndType	#90:#91;//  NoSuccess:()Lscala/util/parsing/combinator/Parsers$NoSuccess$;
const #93 = InterfaceMethod	#89.#92;	//  scala/util/parsing/combinator/Parsers.NoSuccess:()Lscala/util/parsing/combinator/Parsers$NoSuccess$;
const #94 = Asciz	scala/util/parsing/combinator/Parsers$NoSuccess$;
const #95 = class	#94;	//  scala/util/parsing/combinator/Parsers$NoSuccess$
const #96 = Asciz	unapply;
const #97 = Asciz	(Lscala/util/parsing/combinator/Parsers$ParseResult;)Lscala/Option;;
const #98 = NameAndType	#96:#97;//  unapply:(Lscala/util/parsing/combinator/Parsers$ParseResult;)Lscala/Option;
const #99 = Method	#95.#98;	//  scala/util/parsing/combinator/Parsers$NoSuccess$.unapply:(Lscala/util/parsing/combinator/Parsers$ParseResult;)Lscala/Option;
const #100 = Asciz	scala/Option;
const #101 = class	#100;	//  scala/Option
const #102 = Asciz	isEmpty;
const #103 = Asciz	()Z;
const #104 = NameAndType	#102:#103;//  isEmpty:()Z
const #105 = Method	#101.#104;	//  scala/Option.isEmpty:()Z
const #106 = Asciz	get;
const #107 = NameAndType	#106:#52;//  get:()Ljava/lang/Object;
const #108 = Method	#101.#107;	//  scala/Option.get:()Ljava/lang/Object;
const #109 = Asciz	_2;
const #110 = NameAndType	#109:#52;//  _2:()Ljava/lang/Object;
const #111 = Method	#74.#110;	//  scala/Tuple2._2:()Ljava/lang/Object;
const #112 = Asciz	in;
const #113 = Asciz	Lscala/util/parsing/input/Reader;;
const #114 = Asciz	temp33;
const #115 = Asciz	temp30;
const #116 = Asciz	temp31;
const #117 = Asciz	Lscala/util/parsing/combinator/Parsers$Success;;
const #118 = Asciz	temp28;
const #119 = Asciz	temp34;
const #120 = Asciz	temp37;
const #121 = Asciz	Lscala/util/parsing/combinator/Parsers$Error;;
const #122 = Asciz	temp43;
const #123 = Asciz	Lscala/Option;;
const #124 = Asciz	temp44;
const #125 = Asciz	Lscala/Tuple2;;
const #126 = Asciz	temp46;
const #127 = Asciz	temp42;
const #128 = Asciz	temp40;
const #129 = Asciz	Lscala/util/parsing/combinator/Parsers$Failure;;
const #130 = Asciz	res1;
const #131 = Asciz	Lscala/util/parsing/combinator/Parsers$ParseResult;;
const #132 = Asciz	res2;
const #133 = Asciz	(Lscala/util/parsing/input/Reader<Ljava/lang/Object;>;)Lscala/util/parsing/combinator/Parsers$ParseResult<TU;>;;
const #134 = Asciz	Lscala/util/parsing/combinator/Parsers$Parser<TU;>;;
const #135 = Asciz	Scala;
const #136 = Asciz	InnerClasses;
const #137 = Asciz	Error;
const #138 = Asciz	Parser;
const #139 = Asciz	Failure;
const #140 = Asciz	Success;
const #141 = Asciz	scala/util/parsing/combinator/Parsers$ParseResult;
const #142 = class	#141;	//  scala/util/parsing/combinator/Parsers$ParseResult
const #143 = Asciz	ParseResult;
const #144 = Asciz	$anon$4;

{
public scala.util.parsing.combinator.Parsers$Parser$$anon$4(scala.util.parsing.combinator.Parsers$Parser, scala.Function0);
  Code:
   Stack=2, Locals=3, Args_size=3
   0:	aload_1
   1:	ifnonnull	12
   4:	new	#12; //class java/lang/NullPointerException
   7:	dup
   8:	invokespecial	#15; //Method java/lang/NullPointerException."<init>":()V
   11:	athrow
   12:	aload_0
   13:	aload_1
   14:	putfield	#19; //Field $outer:Lscala/util/parsing/combinator/Parsers$Parser;
   17:	aload_0
   18:	aload_2
   19:	putfield	#21; //Field q$1:Lscala/Function0;
   22:	aload_0
   23:	aload_1
   24:	invokevirtual	#27; //Method scala/util/parsing/combinator/Parsers$Parser.scala$util$parsing$combinator$Parsers$Parser$$$outer:()Lscala/util/parsing/combinator/Parsers;
   27:	invokespecial	#30; //Method scala/util/parsing/combinator/Parsers$Parser."<init>":(Lscala/util/parsing/combinator/Parsers;)V
   30:	return
  LineNumberTable: 
   line 306: 0

  LocalVariableTable: 
   Start  Length  Slot  Name   Signature
   0      31      0    this       Lscala/util/parsing/combinator/Parsers$Parser$$anon$4;
   0      31      1    $outer       Lscala/util/parsing/combinator/Parsers$Parser;

  Signature: length = 0x2
   00 22 

public java.lang.Object apply(java.lang.Object);
  Code:
   Stack=2, Locals=2, Args_size=2
   0:	aload_0
   1:	aload_1
   2:	checkcast	#39; //class scala/util/parsing/input/Reader
   5:	invokevirtual	#42; //Method apply:(Lscala/util/parsing/input/Reader;)Lscala/util/parsing/combinator/Parsers$ParseResult;
   8:	areturn
  LineNumberTable: 
   line 306: 0

  LocalVariableTable: 
   Start  Length  Slot  Name   Signature
   0      9      0    this       Lscala/util/parsing/combinator/Parsers$Parser$$anon$4;
   0      9      1    v1       Ljava/lang/Object;


public java.lang.String toString();
  Code:
   Stack=1, Locals=1, Args_size=1
   0:	ldc	#48; //String |||
   2:	areturn
  LineNumberTable: 
   line 319: 0


public scala.util.parsing.combinator.Parsers$ParseResult apply(scala.util.parsing.input.Reader);
  Code:
   Stack=6, Locals=15, Args_size=2
   0:	aload_0
   1:	getfield	#19; //Field $outer:Lscala/util/parsing/combinator/Parsers$Parser;
   4:	aload_1
   5:	invokevirtual	#49; //Method scala/util/parsing/combinator/Parsers$Parser.apply:(Lscala/util/parsing/input/Reader;)Lscala/util/parsing/combinator/Parsers$ParseResult;
   8:	astore	13
   10:	aload_0
   11:	getfield	#21; //Field q$1:Lscala/Function0;
   14:	invokeinterface	#54,  1; //InterfaceMethod scala/Function0.apply:()Ljava/lang/Object;
   19:	checkcast	#23; //class scala/util/parsing/combinator/Parsers$Parser
   22:	aload_1
   23:	invokevirtual	#49; //Method scala/util/parsing/combinator/Parsers$Parser.apply:(Lscala/util/parsing/input/Reader;)Lscala/util/parsing/combinator/Parsers$ParseResult;
   26:	astore	14
   28:	aload	13
   30:	instanceof	#56; //class scala/util/parsing/combinator/Parsers$Success
   33:	ifeq	153
   36:	aload	13
   38:	checkcast	#56; //class scala/util/parsing/combinator/Parsers$Success
   41:	astore	5
   43:	aload	5
   45:	invokevirtual	#60; //Method scala/util/parsing/combinator/Parsers$Success.next:()Lscala/util/parsing/input/Reader;
   48:	astore_3
   49:	aload	14
   51:	instanceof	#56; //class scala/util/parsing/combinator/Parsers$Success
   54:	ifeq	122
   57:	aload	14
   59:	checkcast	#56; //class scala/util/parsing/combinator/Parsers$Success
   62:	astore	4
   64:	aload	4
   66:	invokevirtual	#60; //Method scala/util/parsing/combinator/Parsers$Success.next:()Lscala/util/parsing/input/Reader;
   69:	astore_2
   70:	iconst_1
   71:	ifeq	100
   74:	aload_2
   75:	invokevirtual	#64; //Method scala/util/parsing/input/Reader.pos:()Lscala/util/parsing/input/Position;
   78:	aload_3
   79:	invokevirtual	#64; //Method scala/util/parsing/input/Reader.pos:()Lscala/util/parsing/input/Position;
   82:	invokeinterface	#70,  2; //InterfaceMethod scala/util/parsing/input/Position.$less:(Lscala/util/parsing/input/Position;)Z
   87:	ifeq	95
   90:	aload	5
   92:	goto	365
   95:	aload	4
   97:	goto	365
   100:	new	#72; //class scala/MatchError
   103:	dup
   104:	new	#74; //class scala/Tuple2
   107:	dup
   108:	aload	13
   110:	aload	14
   112:	invokespecial	#77; //Method scala/Tuple2."<init>":(Ljava/lang/Object;Ljava/lang/Object;)V
   115:	invokevirtual	#79; //Method scala/Tuple2.toString:()Ljava/lang/String;
   118:	invokespecial	#82; //Method scala/MatchError."<init>":(Ljava/lang/String;)V
   121:	athrow
   122:	iconst_1
   123:	ifeq	131
   126:	aload	5
   128:	goto	365
   131:	new	#72; //class scala/MatchError
   134:	dup
   135:	new	#74; //class scala/Tuple2
   138:	dup
   139:	aload	13
   141:	aload	14
   143:	invokespecial	#77; //Method scala/Tuple2."<init>":(Ljava/lang/Object;Ljava/lang/Object;)V
   146:	invokevirtual	#79; //Method scala/Tuple2.toString:()Ljava/lang/String;
   149:	invokespecial	#82; //Method scala/MatchError."<init>":(Ljava/lang/String;)V
   152:	athrow
   153:	aload	14
   155:	instanceof	#56; //class scala/util/parsing/combinator/Parsers$Success
   158:	ifeq	199
   161:	aload	14
   163:	checkcast	#56; //class scala/util/parsing/combinator/Parsers$Success
   166:	astore	6
   168:	iconst_1
   169:	ifeq	177
   172:	aload	6
   174:	goto	365
   177:	new	#72; //class scala/MatchError
   180:	dup
   181:	new	#74; //class scala/Tuple2
   184:	dup
   185:	aload	13
   187:	aload	14
   189:	invokespecial	#77; //Method scala/Tuple2."<init>":(Ljava/lang/Object;Ljava/lang/Object;)V
   192:	invokevirtual	#79; //Method scala/Tuple2.toString:()Ljava/lang/String;
   195:	invokespecial	#82; //Method scala/MatchError."<init>":(Ljava/lang/String;)V
   198:	athrow
   199:	aload	13
   201:	instanceof	#84; //class scala/util/parsing/combinator/Parsers$Error
   204:	ifeq	245
   207:	aload	13
   209:	checkcast	#84; //class scala/util/parsing/combinator/Parsers$Error
   212:	astore	7
   214:	iconst_1
   215:	ifeq	223
   218:	aload	7
   220:	goto	365
   223:	new	#72; //class scala/MatchError
   226:	dup
   227:	new	#74; //class scala/Tuple2
   230:	dup
   231:	aload	13
   233:	aload	14
   235:	invokespecial	#77; //Method scala/Tuple2."<init>":(Ljava/lang/Object;Ljava/lang/Object;)V
   238:	invokevirtual	#79; //Method scala/Tuple2.toString:()Ljava/lang/String;
   241:	invokespecial	#82; //Method scala/MatchError."<init>":(Ljava/lang/String;)V
   244:	athrow
   245:	aload	13
   247:	instanceof	#86; //class scala/util/parsing/combinator/Parsers$Failure
   250:	ifeq	388
   253:	aload	13
   255:	checkcast	#86; //class scala/util/parsing/combinator/Parsers$Failure
   258:	astore	12
   260:	aload	12
   262:	invokevirtual	#87; //Method scala/util/parsing/combinator/Parsers$Failure.next:()Lscala/util/parsing/input/Reader;
   265:	astore	11
   267:	aload_0
   268:	getfield	#19; //Field $outer:Lscala/util/parsing/combinator/Parsers$Parser;
   271:	invokevirtual	#27; //Method scala/util/parsing/combinator/Parsers$Parser.scala$util$parsing$combinator$Parsers$Parser$$$outer:()Lscala/util/parsing/combinator/Parsers;
   274:	invokeinterface	#93,  1; //InterfaceMethod scala/util/parsing/combinator/Parsers.NoSuccess:()Lscala/util/parsing/combinator/Parsers$NoSuccess$;
   279:	aload	14
   281:	invokevirtual	#99; //Method scala/util/parsing/combinator/Parsers$NoSuccess$.unapply:(Lscala/util/parsing/combinator/Parsers$ParseResult;)Lscala/Option;
   284:	astore	8
   286:	aload	8
   288:	invokevirtual	#105; //Method scala/Option.isEmpty:()Z
   291:	ifeq	316
   294:	new	#72; //class scala/MatchError
   297:	dup
   298:	new	#74; //class scala/Tuple2
   301:	dup
   302:	aload	13
   304:	aload	14
   306:	invokespecial	#77; //Method scala/Tuple2."<init>":(Ljava/lang/Object;Ljava/lang/Object;)V
   309:	invokevirtual	#79; //Method scala/Tuple2.toString:()Ljava/lang/String;
   312:	invokespecial	#82; //Method scala/MatchError."<init>":(Ljava/lang/String;)V
   315:	athrow
   316:	aload	8
   318:	invokevirtual	#108; //Method scala/Option.get:()Ljava/lang/Object;
   321:	checkcast	#74; //class scala/Tuple2
   324:	astore	9
   326:	aload	9
   328:	invokevirtual	#111; //Method scala/Tuple2._2:()Ljava/lang/Object;
   331:	checkcast	#39; //class scala/util/parsing/input/Reader
   334:	astore	10
   336:	iconst_1
   337:	ifeq	366
   340:	aload	10
   342:	invokevirtual	#64; //Method scala/util/parsing/input/Reader.pos:()Lscala/util/parsing/input/Position;
   345:	aload	11
   347:	invokevirtual	#64; //Method scala/util/parsing/input/Reader.pos:()Lscala/util/parsing/input/Position;
   350:	invokeinterface	#70,  2; //InterfaceMethod scala/util/parsing/input/Position.$less:(Lscala/util/parsing/input/Position;)Z
   355:	ifeq	363
   358:	aload	12
   360:	goto	365
   363:	aload	14
   365:	areturn
   366:	new	#72; //class scala/MatchError
   369:	dup
   370:	new	#74; //class scala/Tuple2
   373:	dup
   374:	aload	13
   376:	aload	14
   378:	invokespecial	#77; //Method scala/Tuple2."<init>":(Ljava/lang/Object;Ljava/lang/Object;)V
   381:	invokevirtual	#79; //Method scala/Tuple2.toString:()Ljava/lang/String;
   384:	invokespecial	#82; //Method scala/MatchError."<init>":(Ljava/lang/String;)V
   387:	athrow
   388:	new	#72; //class scala/MatchError
   391:	dup
   392:	new	#74; //class scala/Tuple2
   395:	dup
   396:	aload	13
   398:	aload	14
   400:	invokespecial	#77; //Method scala/Tuple2."<init>":(Ljava/lang/Object;Ljava/lang/Object;)V
   403:	invokevirtual	#79; //Method scala/Tuple2.toString:()Ljava/lang/String;
   406:	invokespecial	#82; //Method scala/MatchError."<init>":(Ljava/lang/String;)V
   409:	athrow
  LineNumberTable: 
   line 308: 0
   line 309: 10
   line 311: 28
   line 307: 36
   line 311: 49
   line 307: 57
   line 21: 70
   line 312: 74
   line 311: 100
   line 21: 122
   line 313: 126
   line 311: 131
   line 307: 161
   line 21: 168
   line 314: 172
   line 311: 177
   line 307: 207
   line 21: 214
   line 315: 218
   line 311: 223
   line 307: 253
   line 316: 267
   line 307: 279
   line 311: 286
   line 307: 316
   line 21: 336
   line 316: 340
   line 307: 365
   line 311: 366

  LocalVariableTable: 
   Start  Length  Slot  Name   Signature
   0      410      0    this       Lscala/util/parsing/combinator/Parsers$Parser$$anon$4;
   0      410      1    in       Lscala/util/parsing/input/Reader;
   70      52      2    temp33       Lscala/util/parsing/input/Reader;
   49      104      3    temp30       Lscala/util/parsing/input/Reader;
   64      58      4    temp31       Lscala/util/parsing/combinator/Parsers$Success;
   43      110      5    temp28       Lscala/util/parsing/combinator/Parsers$Success;
   168      31      6    temp34       Lscala/util/parsing/combinator/Parsers$Success;
   214      31      7    temp37       Lscala/util/parsing/combinator/Parsers$Error;
   286      79      8    temp43       Lscala/Option;
   366      22      8    temp43       Lscala/Option;
   326      39      9    temp44       Lscala/Tuple2;
   366      22      9    temp44       Lscala/Tuple2;
   336      29      10    temp46       Lscala/util/parsing/input/Reader;
   366      22      10    temp46       Lscala/util/parsing/input/Reader;
   267      98      11    temp42       Lscala/util/parsing/input/Reader;
   366      22      11    temp42       Lscala/util/parsing/input/Reader;
   260      105      12    temp40       Lscala/util/parsing/combinator/Parsers$Failure;
   366      22      12    temp40       Lscala/util/parsing/combinator/Parsers$Failure;
   10      400      13    res1       Lscala/util/parsing/combinator/Parsers$ParseResult;
   28      382      14    res2       Lscala/util/parsing/combinator/Parsers$ParseResult;

  Signature: length = 0x2
   00 FFFFFF85 

}

