Compiled from "Parsers.scala"
public class scala.util.parsing.combinator.Parsers$$tilde extends java.lang.Object implements scala.ScalaObject,scala.Product,java.io.Serializable
  SourceFile: "Parsers.scala"
  Signature: length = 0x2
   00 FFFFFF8C 
  Scala: length = 0x
   
  InnerClass: 
   public $tilde=class scala/util/parsing/combinator/Parsers$$tilde of class scala/util/parsing/combinator/Parsers
  minor version: 0
  major version: 49
  Constant pool:
Asciz	SourceFile;
Asciz	Parsers.scala;
Asciz	$outer;
Asciz	Lscala/util/parsing/combinator/Parsers;;
Asciz	_2;
Asciz	Ljava/lang/Object;;
Asciz	Tb;;
Asciz	Signature;
Asciz	_1;
Asciz	Ta;;
Asciz	<init>;
Asciz	(Lscala/util/parsing/combinator/Parsers;Ljava/lang/Object;Ljava/lang/Object;)V;
Asciz	Code;
Asciz	LineNumberTable;
Asciz	scala/util/parsing/combinator/Parsers$$tilde;
class	scala/util/parsing/combinator/Parsers$$tilde
NameAndType	_1:Ljava/lang/Object;
Field	scala/util/parsing/combinator/Parsers$$tilde._1:Ljava/lang/Object;
NameAndType	_2:Ljava/lang/Object;
Field	scala/util/parsing/combinator/Parsers$$tilde._2:Ljava/lang/Object;
Asciz	java/lang/NullPointerException;
class	java/lang/NullPointerException
Asciz	()V;
NameAndType	"<init>":()V
Method	java/lang/NullPointerException."<init>":()V
NameAndType	$outer:Lscala/util/parsing/combinator/Parsers;
Field	scala/util/parsing/combinator/Parsers$$tilde.$outer:Lscala/util/parsing/combinator/Parsers;
Asciz	java/lang/Object;
class	java/lang/Object
Method	java/lang/Object."<init>":()V
Asciz	scala/Product$class;
class	scala/Product$class
Asciz	$init$;
Asciz	(Lscala/Product;)V;
NameAndType	$init$:(Lscala/Product;)V
Method	scala/Product$class.$init$:(Lscala/Product;)V
Asciz	this;
Asciz	Lscala/util/parsing/combinator/Parsers$$tilde;;
Asciz	LocalVariableTable;
Asciz	(Lscala/util/parsing/combinator/Parsers;Ta;Tb;)V;
Asciz	gd4$1;
Asciz	(Ljava/lang/Object;Ljava/lang/Object;)Z;
Asciz	()Ljava/lang/Object;;
NameAndType	_1:()Ljava/lang/Object;
Method	scala/util/parsing/combinator/Parsers$$tilde._1:()Ljava/lang/Object;
Asciz	java/lang/Number;
class	java/lang/Number
Asciz	java/lang/Character;
class	java/lang/Character
Asciz	scala/runtime/BoxesRunTime;
class	scala/runtime/BoxesRunTime
Asciz	equals2;
NameAndType	equals2:(Ljava/lang/Object;Ljava/lang/Object;)Z
Method	scala/runtime/BoxesRunTime.equals2:(Ljava/lang/Object;Ljava/lang/Object;)Z
Asciz	equals;
Asciz	(Ljava/lang/Object;)Z;
NameAndType	equals:(Ljava/lang/Object;)Z
Method	java/lang/Object.equals:(Ljava/lang/Object;)Z
NameAndType	_2:()Ljava/lang/Object;
Method	scala/util/parsing/combinator/Parsers$$tilde._2:()Ljava/lang/Object;
Asciz	y0;
Asciz	y1;
Asciz	scala$util$parsing$combinator$Parsers$$tilde$$$outer;
Asciz	()Lscala/util/parsing/combinator/Parsers;;
Asciz	canEqual;
Asciz	productElement;
Asciz	(I)Ljava/lang/Object;;
Asciz	java/lang/IndexOutOfBoundsException;
class	java/lang/IndexOutOfBoundsException
Asciz	boxToInteger;
Asciz	(I)Ljava/lang/Integer;;
NameAndType	boxToInteger:(I)Ljava/lang/Integer;
Method	scala/runtime/BoxesRunTime.boxToInteger:(I)Ljava/lang/Integer;
Asciz	toString;
Asciz	()Ljava/lang/String;;
NameAndType	toString:()Ljava/lang/String;
Method	java/lang/Object.toString:()Ljava/lang/String;
Asciz	(Ljava/lang/String;)V;
NameAndType	"<init>":(Ljava/lang/String;)V
Method	java/lang/IndexOutOfBoundsException."<init>":(Ljava/lang/String;)V
Asciz	scala/MatchError;
class	scala/MatchError
Method	scala/MatchError."<init>":(Ljava/lang/String;)V
Asciz	productArity;
Asciz	()I;
Asciz	productPrefix;
Asciz	~;
String	~
NameAndType	scala$util$parsing$combinator$Parsers$$tilde$$$outer:()Lscala/util/parsing/combinator/Parsers;
Method	scala/util/parsing/combinator/Parsers$$tilde.scala$util$parsing$combinator$Parsers$$tilde$$$outer:()Lscala/util/parsing/combinator/Parsers;
NameAndType	gd4$1:(Ljava/lang/Object;Ljava/lang/Object;)Z
Method	scala/util/parsing/combinator/Parsers$$tilde.gd4$1:(Ljava/lang/Object;Ljava/lang/Object;)Z
Asciz	scala/Equals;
class	scala/Equals
NameAndType	canEqual:(Ljava/lang/Object;)Z
InterfaceMethod	scala/Equals.canEqual:(Ljava/lang/Object;)Z
Asciz	temp108;
Asciz	temp109;
Asciz	temp110;
Asciz	hashCode;
Asciz	scala/runtime/ScalaRunTime$;
class	scala/runtime/ScalaRunTime$
Asciz	MODULE$;
Asciz	Lscala/runtime/ScalaRunTime$;;
NameAndType	MODULE$:Lscala/runtime/ScalaRunTime$;
Field	scala/runtime/ScalaRunTime$.MODULE$:Lscala/runtime/ScalaRunTime$;
Asciz	_hashCode;
Asciz	(Lscala/Product;)I;
NameAndType	_hashCode:(Lscala/Product;)I
Method	scala/runtime/ScalaRunTime$._hashCode:(Lscala/Product;)I
Asciz	copy;
Asciz	(Ljava/lang/Object;Ljava/lang/Object;)Lscala/util/parsing/combinator/Parsers$$tilde;;
NameAndType	"<init>":(Lscala/util/parsing/combinator/Parsers;Ljava/lang/Object;Ljava/lang/Object;)V
Method	scala/util/parsing/combinator/Parsers$$tilde."<init>":(Lscala/util/parsing/combinator/Parsers;Ljava/lang/Object;Ljava/lang/Object;)V
Asciz	scala/collection/mutable/StringBuilder;
class	scala/collection/mutable/StringBuilder
Method	scala/collection/mutable/StringBuilder."<init>":()V
Asciz	(;
String	(
Asciz	append;
Asciz	(Ljava/lang/Object;)Lscala/collection/mutable/StringBuilder;;
NameAndType	append:(Ljava/lang/Object;)Lscala/collection/mutable/StringBuilder;
Method	scala/collection/mutable/StringBuilder.append:(Ljava/lang/Object;)Lscala/collection/mutable/StringBuilder;
Asciz	);
String	)
Method	scala/collection/mutable/StringBuilder.toString:()Ljava/lang/String;
Asciz	()Tb;;
Asciz	()Ta;;
Asciz	copy$default$1;
Asciz	copy$default$2;
Asciz	productElements;
Asciz	()Lscala/collection/Iterator;;
Asciz	(Lscala/Product;)Lscala/collection/Iterator;;
NameAndType	productElements:(Lscala/Product;)Lscala/collection/Iterator;
Method	scala/Product$class.productElements:(Lscala/Product;)Lscala/collection/Iterator;
Asciz	Deprecated;
Asciz	productIterator;
NameAndType	productIterator:(Lscala/Product;)Lscala/collection/Iterator;
Method	scala/Product$class.productIterator:(Lscala/Product;)Lscala/collection/Iterator;
Asciz	<a:Ljava/lang/Object;b:Ljava/lang/Object;>Ljava/lang/Object;Lscala/ScalaObject;Lscala/Product;;
Asciz	Scala;
Asciz	InnerClasses;
Asciz	scala/util/parsing/combinator/Parsers;
class	scala/util/parsing/combinator/Parsers
Asciz	$tilde;
Asciz	scala/ScalaObject;
class	scala/ScalaObject
Asciz	scala/Product;
class	scala/Product
Asciz	java/io/Serializable;
class	java/io/Serializable

{
public final scala.util.parsing.combinator.Parsers $outer;
  Signature: Lscala/util/parsing/combinator/Parsers;

private final java.lang.Object _2;
  Signature: Ljava/lang/Object;
  Signature: length = 0x2
   00 07 

private final java.lang.Object _1;
  Signature: Ljava/lang/Object;
  Signature: length = 0x2
   00 0A 

public scala.util.parsing.combinator.Parsers$$tilde(scala.util.parsing.combinator.Parsers, java.lang.Object, java.lang.Object);
  Signature: (Lscala/util/parsing/combinator/Parsers;Ljava/lang/Object;Ljava/lang/Object;)V
  Code:
   Stack=2, Locals=4, Args_size=4
	aload_0
	aload_2
	putfield	Field _1:Ljava/lang/Object;
	aload_0
	aload_3
	putfield	Field _2:Ljava/lang/Object;
	aload_1
	ifnonnull	l1 // aload_0
	new	class java/lang/NullPointerException
	dup
	invokespecial	Method java/lang/NullPointerException."<init>":()V
	athrow
l1	aload_0
	aload_1
	putfield	Field $outer:Lscala/util/parsing/combinator/Parsers;
	aload_0
	invokespecial	Method java/lang/Object."<init>":()V
	aload_0
	invokestatic	Method scala/Product$class.$init$:(Lscala/Product;)V
	return
  Labels:
   	l1 = 22 // aload_0
  LocalVariableTable: 
   Start  Length  Slot  Name   Signature
   0      36      0    this       Lscala/util/parsing/combinator/Parsers$$tilde;
   0      36      1    $outer       Lscala/util/parsing/combinator/Parsers;
   0      36      2    _1       Ljava/lang/Object;
   0      36      3    _2       Ljava/lang/Object;

  Signature: length = 0x2
   00 28 

private final boolean gd4$1(java.lang.Object, java.lang.Object);
  Signature: (Ljava/lang/Object;Ljava/lang/Object;)Z
  Code:
   Stack=2, Locals=5, Args_size=3
	aload_0
	invokevirtual	Method _1:()Ljava/lang/Object;
	astore_3
	aload_1
	aload_3
	if_acmpne	l1 // aload_1
	iconst_1
	goto	l2 // ifeq
l1	aload_1
	ifnonnull	l3 // aload_1
	iconst_0
	goto	l2 // ifeq
l3	aload_1
	instanceof	class java/lang/Number
	ifne	l4 // aload_1
	aload_1
	instanceof	class java/lang/Character
	ifeq	l5 // aload_1
l4	aload_1
	aload_3
	invokestatic	Method scala/runtime/BoxesRunTime.equals2:(Ljava/lang/Object;Ljava/lang/Object;)Z
	goto	l2 // ifeq
l5	aload_1
	aload_3
	invokevirtual	Method java/lang/Object.equals:(Ljava/lang/Object;)Z
l2	ifeq	l6 // iconst_0
	aload_0
	invokevirtual	Method _2:()Ljava/lang/Object;
	astore	4
	aload_2
	aload	4
	if_acmpne	l7 // aload_2
	iconst_1
	goto	l8 // ifeq
l7	aload_2
	ifnonnull	l9 // aload_2
	iconst_0
	goto	l8 // ifeq
l9	aload_2
	instanceof	class java/lang/Number
	ifne	l10 // aload_2
	aload_2
	instanceof	class java/lang/Character
	ifeq	l11 // aload_2
l10	aload_2
	aload	4
	invokestatic	Method scala/runtime/BoxesRunTime.equals2:(Ljava/lang/Object;Ljava/lang/Object;)Z
	goto	l8 // ifeq
l11	aload_2
	aload	4
	invokevirtual	Method java/lang/Object.equals:(Ljava/lang/Object;)Z
l8	ifeq	l6 // iconst_0
	iconst_1
	goto	l12 // ireturn
l6	iconst_0
l12	ireturn
  Labels:
   	l1 = 14 // aload_1
   	l3 = 22 // aload_1
   	l4 = 36 // aload_1
   	l5 = 44 // aload_1
   	l2 = 49 // ifeq
   	l7 = 68 // aload_2
   	l9 = 76 // aload_2
   	l10 = 90 // aload_2
   	l11 = 99 // aload_2
   	l8 = 105 // ifeq
   	l6 = 112 // iconst_0
   	l12 = 113 // ireturn
  LocalVariableTable: 
   Start  Length  Slot  Name   Signature
   0      114      0    this       Lscala/util/parsing/combinator/Parsers$$tilde;
   10      42      3    y0       Ljava/lang/Object;
   64      44      4    y1       Ljava/lang/Object;


public scala.util.parsing.combinator.Parsers scala$util$parsing$combinator$Parsers$$tilde$$$outer();
  Signature: ()Lscala/util/parsing/combinator/Parsers;
  Code:
   Stack=1, Locals=1, Args_size=1
	aload_0
	getfield	Field $outer:Lscala/util/parsing/combinator/Parsers;
	areturn
  Labels:

public boolean canEqual(java.lang.Object);
  Signature: (Ljava/lang/Object;)Z
  Code:
   Stack=1, Locals=2, Args_size=2
	aload_1
	instanceof	class scala/util/parsing/combinator/Parsers$$tilde
	ireturn
  Labels:

public java.lang.Object productElement(int);
  Signature: (I)Ljava/lang/Object;
  Code:
   Stack=3, Locals=2, Args_size=2
	iload_1
	tableswitch{ //0 to 1
		0: 84;
		1: 58;
		default: 24 }
	iconst_1
	ifeq	l1 // new
	new	class java/lang/IndexOutOfBoundsException
	dup
	iload_1
	invokestatic	Method scala/runtime/BoxesRunTime.boxToInteger:(I)Ljava/lang/Integer;
	invokevirtual	Method java/lang/Object.toString:()Ljava/lang/String;
	invokespecial	Method java/lang/IndexOutOfBoundsException."<init>":(Ljava/lang/String;)V
	athrow
l1	new	class scala/MatchError
	dup
	iload_1
	invokestatic	Method scala/runtime/BoxesRunTime.boxToInteger:(I)Ljava/lang/Integer;
	invokevirtual	Method java/lang/Object.toString:()Ljava/lang/String;
	invokespecial	Method scala/MatchError."<init>":(Ljava/lang/String;)V
	athrow
	iconst_1
	ifeq	l2 // new
	aload_0
	invokevirtual	Method _2:()Ljava/lang/Object;
	goto	l3 // areturn
l2	new	class scala/MatchError
	dup
	iload_1
	invokestatic	Method scala/runtime/BoxesRunTime.boxToInteger:(I)Ljava/lang/Integer;
	invokevirtual	Method java/lang/Object.toString:()Ljava/lang/String;
	invokespecial	Method scala/MatchError."<init>":(Ljava/lang/String;)V
	athrow
	iconst_1
	ifeq	l4 // new
	aload_0
	invokevirtual	Method _1:()Ljava/lang/Object;
l3	areturn
l4	new	class scala/MatchError
	dup
	iload_1
	invokestatic	Method scala/runtime/BoxesRunTime.boxToInteger:(I)Ljava/lang/Integer;
	invokevirtual	Method java/lang/Object.toString:()Ljava/lang/String;
	invokespecial	Method scala/MatchError."<init>":(Ljava/lang/String;)V
	athrow
  Labels:
   	l1 = 43 // new
   	l2 = 69 // new
   	l3 = 92 // areturn
   	l4 = 93 // new

public int productArity();
  Signature: ()I
  Code:
   Stack=1, Locals=1, Args_size=1
	iconst_2
	ireturn
  Labels:

public java.lang.String productPrefix();
  Signature: ()Ljava/lang/String;
  Code:
   Stack=1, Locals=1, Args_size=1
	ldc	String ~
	areturn
  Labels:

public boolean equals(java.lang.Object);
  Signature: (Ljava/lang/Object;)Z
  Code:
   Stack=3, Locals=5, Args_size=2
	aload_0
	aload_1
	if_acmpeq	l1 // iconst_1
	aload_1
	instanceof	class scala/util/parsing/combinator/Parsers$$tilde
	ifeq	l2 // iconst_1
	aload_1
	checkcast	class scala/util/parsing/combinator/Parsers$$tilde
	invokevirtual	Method scala$util$parsing$combinator$Parsers$$tilde$$$outer:()Lscala/util/parsing/combinator/Parsers;
	aload_0
	invokevirtual	Method scala$util$parsing$combinator$Parsers$$tilde$$$outer:()Lscala/util/parsing/combinator/Parsers;
	if_acmpne	l2 // iconst_1
	aload_1
	checkcast	class scala/util/parsing/combinator/Parsers$$tilde
	astore_2
	aload_2
	invokevirtual	Method _1:()Ljava/lang/Object;
	astore_3
	aload_2
	invokevirtual	Method _2:()Ljava/lang/Object;
	astore	4
	aload_0
	aload_3
	aload	4
	invokespecial	Method gd4$1:(Ljava/lang/Object;Ljava/lang/Object;)Z
	ifeq	l3 // iconst_1
	aload_1
	checkcast	class scala/util/parsing/combinator/Parsers$$tilde
	aload_0
	invokeinterface	InterfaceMethod scala/Equals.canEqual:(Ljava/lang/Object;)Z
	goto	l4 // ifeq
l3	iconst_1
	ifeq	l5 // new
	iconst_0
	goto	l4 // ifeq
l5	new	class scala/MatchError
	dup
	aload_1
	invokevirtual	Method java/lang/Object.toString:()Ljava/lang/String;
	invokespecial	Method scala/MatchError."<init>":(Ljava/lang/String;)V
	athrow
l2	iconst_1
	ifeq	l6 // new
	iconst_0
l4	ifeq	l7 // iconst_0
l1	iconst_1
	goto	l8 // ireturn
l7	iconst_0
l8	ireturn
l6	new	class scala/MatchError
	dup
	aload_1
	invokevirtual	Method java/lang/Object.toString:()Ljava/lang/String;
	invokespecial	Method scala/MatchError."<init>":(Ljava/lang/String;)V
	athrow
  Labels:
   	l3 = 65 // iconst_1
   	l5 = 73 // new
   	l2 = 85 // iconst_1
   	l4 = 90 // ifeq
   	l1 = 93 // iconst_1
   	l7 = 97 // iconst_0
   	l8 = 98 // ireturn
   	l6 = 99 // new
  LocalVariableTable: 
   Start  Length  Slot  Name   Signature
   0      111      0    this       Lscala/util/parsing/combinator/Parsers$$tilde;
   31      54      2    temp108       Lscala/util/parsing/combinator/Parsers$$tilde;
   36      49      3    temp109       Ljava/lang/Object;
   42      43      4    temp110       Ljava/lang/Object;


public int hashCode();
  Signature: ()I
  Code:
   Stack=2, Locals=1, Args_size=1
	getstatic	Field scala/runtime/ScalaRunTime$.MODULE$:Lscala/runtime/ScalaRunTime$;
	aload_0
	invokevirtual	Method scala/runtime/ScalaRunTime$._hashCode:(Lscala/Product;)I
	ireturn
  Labels:

public scala.util.parsing.combinator.Parsers$$tilde copy(java.lang.Object, java.lang.Object);
  Signature: (Ljava/lang/Object;Ljava/lang/Object;)Lscala/util/parsing/combinator/Parsers$$tilde;
  Code:
   Stack=5, Locals=3, Args_size=3
	new	class scala/util/parsing/combinator/Parsers$$tilde
	dup
	aload_0
	invokevirtual	Method scala$util$parsing$combinator$Parsers$$tilde$$$outer:()Lscala/util/parsing/combinator/Parsers;
	aload_1
	aload_2
	invokespecial	Method "<init>":(Lscala/util/parsing/combinator/Parsers;Ljava/lang/Object;Ljava/lang/Object;)V
	areturn
  Labels:
  LocalVariableTable: 
   Start  Length  Slot  Name   Signature
   0      14      0    this       Lscala/util/parsing/combinator/Parsers$$tilde;
   0      14      1    _1       Ljava/lang/Object;
   0      14      2    _2       Ljava/lang/Object;


public java.lang.String toString();
  Signature: ()Ljava/lang/String;
  Code:
   Stack=2, Locals=1, Args_size=1
	new	class scala/collection/mutable/StringBuilder
	dup
	invokespecial	Method scala/collection/mutable/StringBuilder."<init>":()V
	ldc	String (
	invokevirtual	Method scala/collection/mutable/StringBuilder.append:(Ljava/lang/Object;)Lscala/collection/mutable/StringBuilder;
	aload_0
	invokevirtual	Method _1:()Ljava/lang/Object;
	invokevirtual	Method scala/collection/mutable/StringBuilder.append:(Ljava/lang/Object;)Lscala/collection/mutable/StringBuilder;
	ldc	String ~
	invokevirtual	Method scala/collection/mutable/StringBuilder.append:(Ljava/lang/Object;)Lscala/collection/mutable/StringBuilder;
	aload_0
	invokevirtual	Method _2:()Ljava/lang/Object;
	invokevirtual	Method scala/collection/mutable/StringBuilder.append:(Ljava/lang/Object;)Lscala/collection/mutable/StringBuilder;
	ldc	String )
	invokevirtual	Method scala/collection/mutable/StringBuilder.append:(Ljava/lang/Object;)Lscala/collection/mutable/StringBuilder;
	invokevirtual	Method scala/collection/mutable/StringBuilder.toString:()Ljava/lang/String;
	areturn
  Labels:

public java.lang.Object _2();
  Signature: ()Ljava/lang/Object;
  Code:
   Stack=1, Locals=1, Args_size=1
	aload_0
	getfield	Field _2:Ljava/lang/Object;
	areturn
  Labels:
  Signature: length = 0x2
   00 7F 

public java.lang.Object _1();
  Signature: ()Ljava/lang/Object;
  Code:
   Stack=1, Locals=1, Args_size=1
	aload_0
	getfield	Field _1:Ljava/lang/Object;
	areturn
  Labels:
  Signature: length = 0x2
   00 FFFFFF80 

public java.lang.Object copy$default$1();
  Signature: ()Ljava/lang/Object;
  Code:
   Stack=1, Locals=1, Args_size=1
	aload_0
	invokevirtual	Method _1:()Ljava/lang/Object;
	areturn
  Labels:

public java.lang.Object copy$default$2();
  Signature: ()Ljava/lang/Object;
  Code:
   Stack=1, Locals=1, Args_size=1
	aload_0
	invokevirtual	Method _2:()Ljava/lang/Object;
	areturn
  Labels:

public scala.collection.Iterator productElements();
  Signature: ()Lscala/collection/Iterator;
  Code:
   Stack=1, Locals=1, Args_size=1
	aload_0
	invokestatic	Method scala/Product$class.productElements:(Lscala/Product;)Lscala/collection/Iterator;
	areturn
  Labels:
  Deprecated: true

public scala.collection.Iterator productIterator();
  Signature: ()Lscala/collection/Iterator;
  Code:
   Stack=1, Locals=1, Args_size=1
	aload_0
	invokestatic	Method scala/Product$class.productIterator:(Lscala/Product;)Lscala/collection/Iterator;
	areturn
  Labels:

}

