Compiled from "Parsers.scala"
public final class scala.util.parsing.combinator.Parsers$$anonfun$acceptSeq$1 extends java.lang.Object implements scala.Function2,scala.ScalaObject,java.io.Serializable
  SourceFile: "Parsers.scala"
  Scala: length = 0x
   
  InnerClass: 
   public abstract Parser=class scala/util/parsing/combinator/Parsers$Parser of class scala/util/parsing/combinator/Parsers
   public final $anonfun$acceptSeq$1=class scala/util/parsing/combinator/Parsers$$anonfun$acceptSeq$1 of class scala/util/parsing/combinator/Parsers
   public final $anonfun$apply$6=class scala/util/parsing/combinator/Parsers$$anonfun$acceptSeq$1$$anonfun$apply$6 of class scala/util/parsing/combinator/Parsers$$anonfun$acceptSeq$1
  minor version: 0
  major version: 49
  Constant pool:
Asciz	SourceFile;
Asciz	Parsers.scala;
Asciz	<clinit>;
Asciz	()V;
Asciz	Code;
Asciz	serialVersionUID;
Asciz	J;
Asciz	scala/util/parsing/combinator/Parsers$$anonfun$acceptSeq$1;
class	scala/util/parsing/combinator/Parsers$$anonfun$acceptSeq$1
NameAndType	serialVersionUID:J
Field	scala/util/parsing/combinator/Parsers$$anonfun$acceptSeq$1.serialVersionUID:J
Asciz	$outer;
Asciz	Lscala/util/parsing/combinator/Parsers;;
Asciz	<init>;
Asciz	(Lscala/util/parsing/combinator/Parsers;)V;
Asciz	LineNumberTable;
Asciz	java/lang/NullPointerException;
class	java/lang/NullPointerException
NameAndType	"<init>":()V
Method	java/lang/NullPointerException."<init>":()V
NameAndType	$outer:Lscala/util/parsing/combinator/Parsers;
Field	scala/util/parsing/combinator/Parsers$$anonfun$acceptSeq$1.$outer:Lscala/util/parsing/combinator/Parsers;
Asciz	java/lang/Object;
class	java/lang/Object
Method	java/lang/Object."<init>":()V
Asciz	scala/Function2$class;
class	scala/Function2$class
Asciz	$init$;
Asciz	(Lscala/Function2;)V;
NameAndType	$init$:(Lscala/Function2;)V
Method	scala/Function2$class.$init$:(Lscala/Function2;)V
Asciz	this;
Asciz	Lscala/util/parsing/combinator/Parsers$$anonfun$acceptSeq$1;;
Asciz	LocalVariableTable;
Asciz	apply;
Asciz	(Ljava/lang/Object;Ljava/lang/Object;)Ljava/lang/Object;;
Asciz	scala/util/parsing/combinator/Parsers$Parser;
class	scala/util/parsing/combinator/Parsers$Parser
Asciz	(Ljava/lang/Object;Lscala/util/parsing/combinator/Parsers$Parser;)Lscala/util/parsing/combinator/Parsers$Parser;;
NameAndType	apply:(Ljava/lang/Object;Lscala/util/parsing/combinator/Parsers$Parser;)Lscala/util/parsing/combinator/Parsers$Parser;
Method	scala/util/parsing/combinator/Parsers$$anonfun$acceptSeq$1.apply:(Ljava/lang/Object;Lscala/util/parsing/combinator/Parsers$Parser;)Lscala/util/parsing/combinator/Parsers$Parser;
Asciz	v1;
Asciz	Ljava/lang/Object;;
Asciz	v2;
Asciz	scala/util/parsing/combinator/Parsers;
class	scala/util/parsing/combinator/Parsers
Asciz	accept;
Asciz	(Ljava/lang/Object;)Lscala/util/parsing/combinator/Parsers$Parser;;
NameAndType	accept:(Ljava/lang/Object;)Lscala/util/parsing/combinator/Parsers$Parser;
InterfaceMethod	scala/util/parsing/combinator/Parsers.accept:(Ljava/lang/Object;)Lscala/util/parsing/combinator/Parsers$Parser;
Asciz	scala/util/parsing/combinator/Parsers$$anonfun$acceptSeq$1$$anonfun$apply$6;
class	scala/util/parsing/combinator/Parsers$$anonfun$acceptSeq$1$$anonfun$apply$6
Asciz	(Lscala/util/parsing/combinator/Parsers$$anonfun$acceptSeq$1;Lscala/util/parsing/combinator/Parsers$Parser;)V;
NameAndType	"<init>":(Lscala/util/parsing/combinator/Parsers$$anonfun$acceptSeq$1;Lscala/util/parsing/combinator/Parsers$Parser;)V
Method	scala/util/parsing/combinator/Parsers$$anonfun$acceptSeq$1$$anonfun$apply$6."<init>":(Lscala/util/parsing/combinator/Parsers$$anonfun$acceptSeq$1;Lscala/util/parsing/combinator/Parsers$Parser;)V
Asciz	$tilde;
Asciz	(Lscala/Function0;)Lscala/util/parsing/combinator/Parsers$Parser;;
NameAndType	$tilde:(Lscala/Function0;)Lscala/util/parsing/combinator/Parsers$Parser;
Method	scala/util/parsing/combinator/Parsers$Parser.$tilde:(Lscala/Function0;)Lscala/util/parsing/combinator/Parsers$Parser;
Asciz	mkList;
Asciz	()Lscala/Function1;;
NameAndType	mkList:()Lscala/Function1;
InterfaceMethod	scala/util/parsing/combinator/Parsers.mkList:()Lscala/Function1;
Asciz	$up$up;
Asciz	(Lscala/Function1;)Lscala/util/parsing/combinator/Parsers$Parser;;
NameAndType	$up$up:(Lscala/Function1;)Lscala/util/parsing/combinator/Parsers$Parser;
Method	scala/util/parsing/combinator/Parsers$Parser.$up$up:(Lscala/Function1;)Lscala/util/parsing/combinator/Parsers$Parser;
Asciz	x;
Asciz	pxs$1;
Asciz	Lscala/util/parsing/combinator/Parsers$Parser;;
Asciz	(Ljava/lang/Object;Lscala/util/parsing/combinator/Parsers$Parser<Lscala/collection/immutable/List<Ljava/lang/Object;>;>;)Lscala/util/parsing/combinator/Parsers$Parser<Lscala/collection/immutable/List<Ljava/lang/Object;>;>;;
Asciz	Signature;
Asciz	curry;
Asciz	(Lscala/Function2;)Lscala/Function1;;
NameAndType	curry:(Lscala/Function2;)Lscala/Function1;
Method	scala/Function2$class.curry:(Lscala/Function2;)Lscala/Function1;
Asciz	toString;
Asciz	()Ljava/lang/String;;
Asciz	(Lscala/Function2;)Ljava/lang/String;;
NameAndType	toString:(Lscala/Function2;)Ljava/lang/String;
Method	scala/Function2$class.toString:(Lscala/Function2;)Ljava/lang/String;
Asciz	Scala;
Asciz	InnerClasses;
Asciz	Parser;
Asciz	$anonfun$acceptSeq$1;
Asciz	$anonfun$apply$6;
Asciz	scala/Function2;
class	scala/Function2
Asciz	scala/ScalaObject;
class	scala/ScalaObject
Asciz	java/io/Serializable;
class	java/io/Serializable

{
public static final long serialVersionUID;
  Signature: J

private final scala.util.parsing.combinator.Parsers $outer;
  Signature: Lscala/util/parsing/combinator/Parsers;

public static {};
  Signature: ()V
  Code:
   Stack=2, Locals=0, Args_size=0
	lconst_0
	putstatic	Field serialVersionUID:J
	return
  Labels:

public scala.util.parsing.combinator.Parsers$$anonfun$acceptSeq$1(scala.util.parsing.combinator.Parsers);
  Signature: (Lscala/util/parsing/combinator/Parsers;)V
  Code:
   Stack=2, Locals=2, Args_size=2
	aload_1
	ifnonnull	l1 // aload_0
	new	class java/lang/NullPointerException
	dup
	invokespecial	Method java/lang/NullPointerException."<init>":()V
	athrow
l1	aload_0
	aload_1
	putfield	Field $outer:Lscala/util/parsing/combinator/Parsers;
	aload_0
	invokespecial	Method java/lang/Object."<init>":()V
	aload_0
	invokestatic	Method scala/Function2$class.$init$:(Lscala/Function2;)V
	return
  Labels:
   	l1 = 12 // aload_0
  LocalVariableTable: 
   Start  Length  Slot  Name   Signature
   0      26      0    this       Lscala/util/parsing/combinator/Parsers$$anonfun$acceptSeq$1;
   0      26      1    $outer       Lscala/util/parsing/combinator/Parsers;


public final java.lang.Object apply(java.lang.Object, java.lang.Object);
  Signature: (Ljava/lang/Object;Ljava/lang/Object;)Ljava/lang/Object;
  Code:
   Stack=3, Locals=4, Args_size=3
	aload_0
	getfield	Field $outer:Lscala/util/parsing/combinator/Parsers;
	astore_3
	aload_0
	aload_1
	aload_2
	checkcast	class scala/util/parsing/combinator/Parsers$Parser
	invokevirtual	Method apply:(Ljava/lang/Object;Lscala/util/parsing/combinator/Parsers$Parser;)Lscala/util/parsing/combinator/Parsers$Parser;
	areturn
  Labels:
  LocalVariableTable: 
   Start  Length  Slot  Name   Signature
   0      15      0    this       Lscala/util/parsing/combinator/Parsers$$anonfun$acceptSeq$1;
   5      10      1    v1       Ljava/lang/Object;
   5      10      2    v2       Ljava/lang/Object;


public final scala.util.parsing.combinator.Parsers$Parser apply(java.lang.Object, scala.util.parsing.combinator.Parsers$Parser);
  Signature: (Ljava/lang/Object;Lscala/util/parsing/combinator/Parsers$Parser;)Lscala/util/parsing/combinator/Parsers$Parser;
  Code:
   Stack=5, Locals=4, Args_size=3
	aload_0
	getfield	Field $outer:Lscala/util/parsing/combinator/Parsers;
	astore_3
	aload_0
	getfield	Field $outer:Lscala/util/parsing/combinator/Parsers;
	aload_1
	invokeinterface	InterfaceMethod scala/util/parsing/combinator/Parsers.accept:(Ljava/lang/Object;)Lscala/util/parsing/combinator/Parsers$Parser;
	new	class scala/util/parsing/combinator/Parsers$$anonfun$acceptSeq$1$$anonfun$apply$6
	dup
	aload_0
	aload_2
	invokespecial	Method scala/util/parsing/combinator/Parsers$$anonfun$acceptSeq$1$$anonfun$apply$6."<init>":(Lscala/util/parsing/combinator/Parsers$$anonfun$acceptSeq$1;Lscala/util/parsing/combinator/Parsers$Parser;)V
	invokevirtual	Method scala/util/parsing/combinator/Parsers$Parser.$tilde:(Lscala/Function0;)Lscala/util/parsing/combinator/Parsers$Parser;
	aload_0
	getfield	Field $outer:Lscala/util/parsing/combinator/Parsers;
	invokeinterface	InterfaceMethod scala/util/parsing/combinator/Parsers.mkList:()Lscala/Function1;
	invokevirtual	Method scala/util/parsing/combinator/Parsers$Parser.$up$up:(Lscala/Function1;)Lscala/util/parsing/combinator/Parsers$Parser;
	areturn
  Labels:
  LocalVariableTable: 
   Start  Length  Slot  Name   Signature
   0      40      0    this       Lscala/util/parsing/combinator/Parsers$$anonfun$acceptSeq$1;
   5      35      1    x       Ljava/lang/Object;
   5      35      2    pxs$1       Lscala/util/parsing/combinator/Parsers$Parser;

  Signature: length = 0x2
   00 47 

public scala.Function1 curry();
  Signature: ()Lscala/Function1;
  Code:
   Stack=1, Locals=1, Args_size=1
	aload_0
	invokestatic	Method scala/Function2$class.curry:(Lscala/Function2;)Lscala/Function1;
	areturn
  Labels:

public java.lang.String toString();
  Signature: ()Ljava/lang/String;
  Code:
   Stack=1, Locals=1, Args_size=1
	aload_0
	invokestatic	Method scala/Function2$class.toString:(Lscala/Function2;)Ljava/lang/String;
	areturn
  Labels:

}

