Compiled from "Parsers.scala"
public final class scala.util.parsing.combinator.Parsers$Success$ extends java.lang.Object implements scala.ScalaObject
  SourceFile: "Parsers.scala"
  Scala: length = 0x
   
  InnerClass: 
   public Success=class scala/util/parsing/combinator/Parsers$Success of class scala/util/parsing/combinator/Parsers
  minor version: 0
  major version: 49
  Constant pool:
Asciz	SourceFile;
Asciz	Parsers.scala;
Asciz	Scala;
Asciz	$outer;
Asciz	Lscala/util/parsing/combinator/Parsers;;
Asciz	<init>;
Asciz	(Lscala/util/parsing/combinator/Parsers;)V;
Asciz	Code;
Asciz	LineNumberTable;
Asciz	java/lang/NullPointerException;
class	java/lang/NullPointerException
Asciz	()V;
NameAndType	"<init>":()V
Method	java/lang/NullPointerException."<init>":()V
Asciz	scala/util/parsing/combinator/Parsers$Success$;
class	scala/util/parsing/combinator/Parsers$Success$
NameAndType	$outer:Lscala/util/parsing/combinator/Parsers;
Field	scala/util/parsing/combinator/Parsers$Success$.$outer:Lscala/util/parsing/combinator/Parsers;
Asciz	java/lang/Object;
class	java/lang/Object
Method	java/lang/Object."<init>":()V
Asciz	this;
Asciz	Lscala/util/parsing/combinator/Parsers$Success$;;
Asciz	LocalVariableTable;
Asciz	apply;
Asciz	(Ljava/lang/Object;Lscala/util/parsing/input/Reader;)Lscala/util/parsing/combinator/Parsers$Success;;
Asciz	scala/util/parsing/combinator/Parsers$Success;
class	scala/util/parsing/combinator/Parsers$Success
Asciz	(Lscala/util/parsing/combinator/Parsers;Ljava/lang/Object;Lscala/util/parsing/input/Reader;)V;
NameAndType	"<init>":(Lscala/util/parsing/combinator/Parsers;Ljava/lang/Object;Lscala/util/parsing/input/Reader;)V
Method	scala/util/parsing/combinator/Parsers$Success."<init>":(Lscala/util/parsing/combinator/Parsers;Ljava/lang/Object;Lscala/util/parsing/input/Reader;)V
Asciz	result;
Asciz	Ljava/lang/Object;;
Asciz	next;
Asciz	Lscala/util/parsing/input/Reader;;
Asciz	unapply;
Asciz	(Lscala/util/parsing/combinator/Parsers$Success;)Lscala/Some;;
Asciz	scala/Some;
class	scala/Some
Asciz	scala/Tuple2;
class	scala/Tuple2
Asciz	()Ljava/lang/Object;;
NameAndType	result:()Ljava/lang/Object;
Method	scala/util/parsing/combinator/Parsers$Success.result:()Ljava/lang/Object;
Asciz	()Lscala/util/parsing/input/Reader;;
NameAndType	next:()Lscala/util/parsing/input/Reader;
Method	scala/util/parsing/combinator/Parsers$Success.next:()Lscala/util/parsing/input/Reader;
Asciz	(Ljava/lang/Object;Ljava/lang/Object;)V;
NameAndType	"<init>":(Ljava/lang/Object;Ljava/lang/Object;)V
Method	scala/Tuple2."<init>":(Ljava/lang/Object;Ljava/lang/Object;)V
Asciz	(Ljava/lang/Object;)V;
NameAndType	"<init>":(Ljava/lang/Object;)V
Method	scala/Some."<init>":(Ljava/lang/Object;)V
Asciz	x$0;
Asciz	Lscala/util/parsing/combinator/Parsers$Success;;
Asciz	InnerClasses;
Asciz	scala/util/parsing/combinator/Parsers;
class	scala/util/parsing/combinator/Parsers
Asciz	Success;
Asciz	scala/ScalaObject;
class	scala/ScalaObject

{
private final scala.util.parsing.combinator.Parsers $outer;
  Signature: Lscala/util/parsing/combinator/Parsers;

public scala.util.parsing.combinator.Parsers$Success$(scala.util.parsing.combinator.Parsers);
  Signature: (Lscala/util/parsing/combinator/Parsers;)V
  Code:
   Stack=2, Locals=2, Args_size=2
	aload_1
	ifnonnull	l1 // aload_0
	new	class java/lang/NullPointerException
	dup
	invokespecial	Method java/lang/NullPointerException."<init>":()V
	athrow
l1	aload_0
	aload_1
	putfield	Field $outer:Lscala/util/parsing/combinator/Parsers;
	aload_0
	invokespecial	Method java/lang/Object."<init>":()V
	return
  Labels:
   	l1 = 12 // aload_0
  LocalVariableTable: 
   Start  Length  Slot  Name   Signature
   0      22      0    this       Lscala/util/parsing/combinator/Parsers$Success$;
   0      22      1    $outer       Lscala/util/parsing/combinator/Parsers;


public scala.util.parsing.combinator.Parsers$Success apply(java.lang.Object, scala.util.parsing.input.Reader);
  Signature: (Ljava/lang/Object;Lscala/util/parsing/input/Reader;)Lscala/util/parsing/combinator/Parsers$Success;
  Code:
   Stack=5, Locals=3, Args_size=3
	new	class scala/util/parsing/combinator/Parsers$Success
	dup
	aload_0
	getfield	Field $outer:Lscala/util/parsing/combinator/Parsers;
	aload_1
	aload_2
	invokespecial	Method scala/util/parsing/combinator/Parsers$Success."<init>":(Lscala/util/parsing/combinator/Parsers;Ljava/lang/Object;Lscala/util/parsing/input/Reader;)V
	areturn
  Labels:
  LocalVariableTable: 
   Start  Length  Slot  Name   Signature
   0      14      0    this       Lscala/util/parsing/combinator/Parsers$Success$;
   0      14      1    result       Ljava/lang/Object;
   0      14      2    next       Lscala/util/parsing/input/Reader;


public scala.Some unapply(scala.util.parsing.combinator.Parsers$Success);
  Signature: (Lscala/util/parsing/combinator/Parsers$Success;)Lscala/Some;
  Code:
   Stack=6, Locals=2, Args_size=2
	new	class scala/Some
	dup
	new	class scala/Tuple2
	dup
	aload_1
	invokevirtual	Method scala/util/parsing/combinator/Parsers$Success.result:()Ljava/lang/Object;
	aload_1
	invokevirtual	Method scala/util/parsing/combinator/Parsers$Success.next:()Lscala/util/parsing/input/Reader;
	invokespecial	Method scala/Tuple2."<init>":(Ljava/lang/Object;Ljava/lang/Object;)V
	invokespecial	Method scala/Some."<init>":(Ljava/lang/Object;)V
	areturn
  Labels:
  LocalVariableTable: 
   Start  Length  Slot  Name   Signature
   0      23      0    this       Lscala/util/parsing/combinator/Parsers$Success$;
   0      23      1    x$0       Lscala/util/parsing/combinator/Parsers$Success;


}

