Compiled from "Parsers.scala"
public abstract class scala.util.parsing.combinator.Parsers$NoSuccess extends scala.util.parsing.combinator.Parsers$ParseResult implements scala.ScalaObject
  SourceFile: "Parsers.scala"
  Signature: length = 0x2
   00 67 
  Scala: length = 0x
   
  InnerClass: 
   public abstract NoSuccess=class scala/util/parsing/combinator/Parsers$NoSuccess of class scala/util/parsing/combinator/Parsers
   public abstract ParseResult=class scala/util/parsing/combinator/Parsers$ParseResult of class scala/util/parsing/combinator/Parsers
  minor version: 0
  major version: 49
  Constant pool:
Asciz	SourceFile;
Asciz	Parsers.scala;
Asciz	successful;
Asciz	Z;
Asciz	next;
Asciz	Lscala/util/parsing/input/Reader;;
Asciz	Lscala/util/parsing/input/Reader<Ljava/lang/Object;>;;
Asciz	Signature;
Asciz	msg;
Asciz	Ljava/lang/String;;
Asciz	<init>;
Asciz	(Lscala/util/parsing/combinator/Parsers;Ljava/lang/String;Lscala/util/parsing/input/Reader;)V;
Asciz	Code;
Asciz	LineNumberTable;
Asciz	scala/util/parsing/combinator/Parsers$NoSuccess;
class	scala/util/parsing/combinator/Parsers$NoSuccess
NameAndType	msg:Ljava/lang/String;
Field	scala/util/parsing/combinator/Parsers$NoSuccess.msg:Ljava/lang/String;
NameAndType	next:Lscala/util/parsing/input/Reader;
Field	scala/util/parsing/combinator/Parsers$NoSuccess.next:Lscala/util/parsing/input/Reader;
Asciz	scala/util/parsing/combinator/Parsers$ParseResult;
class	scala/util/parsing/combinator/Parsers$ParseResult
Asciz	(Lscala/util/parsing/combinator/Parsers;)V;
NameAndType	"<init>":(Lscala/util/parsing/combinator/Parsers;)V
Method	scala/util/parsing/combinator/Parsers$ParseResult."<init>":(Lscala/util/parsing/combinator/Parsers;)V
NameAndType	successful:Z
Field	scala/util/parsing/combinator/Parsers$NoSuccess.successful:Z
Asciz	scala/util/parsing/combinator/Parsers;
class	scala/util/parsing/combinator/Parsers
Asciz	lastNoSuccess;
Asciz	()Lscala/util/parsing/combinator/Parsers$NoSuccess;;
NameAndType	lastNoSuccess:()Lscala/util/parsing/combinator/Parsers$NoSuccess;
InterfaceMethod	scala/util/parsing/combinator/Parsers.lastNoSuccess:()Lscala/util/parsing/combinator/Parsers$NoSuccess;
Asciz	java/lang/Object;
class	java/lang/Object
Asciz	equals;
Asciz	(Ljava/lang/Object;)Z;
NameAndType	equals:(Ljava/lang/Object;)Z
Method	java/lang/Object.equals:(Ljava/lang/Object;)Z
Asciz	scala/util/parsing/input/Reader;
class	scala/util/parsing/input/Reader
Asciz	pos;
Asciz	()Lscala/util/parsing/input/Position;;
NameAndType	pos:()Lscala/util/parsing/input/Position;
Method	scala/util/parsing/input/Reader.pos:()Lscala/util/parsing/input/Position;
Asciz	()Lscala/util/parsing/input/Reader;;
NameAndType	next:()Lscala/util/parsing/input/Reader;
Method	scala/util/parsing/combinator/Parsers$NoSuccess.next:()Lscala/util/parsing/input/Reader;
Asciz	scala/util/parsing/input/Position;
class	scala/util/parsing/input/Position
Asciz	$less;
Asciz	(Lscala/util/parsing/input/Position;)Z;
NameAndType	$less:(Lscala/util/parsing/input/Position;)Z
InterfaceMethod	scala/util/parsing/input/Position.$less:(Lscala/util/parsing/input/Position;)Z
Asciz	lastNoSuccess_$eq;
Asciz	(Lscala/util/parsing/combinator/Parsers$NoSuccess;)V;
NameAndType	lastNoSuccess_$eq:(Lscala/util/parsing/combinator/Parsers$NoSuccess;)V
InterfaceMethod	scala/util/parsing/combinator/Parsers.lastNoSuccess_$eq:(Lscala/util/parsing/combinator/Parsers$NoSuccess;)V
Asciz	this;
Asciz	Lscala/util/parsing/combinator/Parsers$NoSuccess;;
Asciz	$outer;
Asciz	Lscala/util/parsing/combinator/Parsers;;
Asciz	LocalVariableTable;
Asciz	(Lscala/util/parsing/combinator/Parsers;Ljava/lang/String;Lscala/util/parsing/input/Reader<Ljava/lang/Object;>;)V;
Asciz	map;
Asciz	(Lscala/Function1;)Lscala/util/parsing/combinator/Parsers$ParseResult;;
Asciz	(Lscala/Function1;)Lscala/util/parsing/combinator/Parsers$NoSuccess;;
NameAndType	map:(Lscala/Function1;)Lscala/util/parsing/combinator/Parsers$NoSuccess;
Method	scala/util/parsing/combinator/Parsers$NoSuccess.map:(Lscala/Function1;)Lscala/util/parsing/combinator/Parsers$NoSuccess;
Asciz	f;
Asciz	Lscala/Function1;;
Asciz	get;
Asciz	()Ljava/lang/Object;;
Asciz	()Lscala/runtime/Nothing$;;
NameAndType	get:()Lscala/runtime/Nothing$;
Method	scala/util/parsing/combinator/Parsers$NoSuccess.get:()Lscala/runtime/Nothing$;
Asciz	scala$util$parsing$combinator$Parsers$NoSuccess$$$outer;
Asciz	()Lscala/util/parsing/combinator/Parsers;;
NameAndType	$outer:Lscala/util/parsing/combinator/Parsers;
Field	scala/util/parsing/combinator/Parsers$ParseResult.$outer:Lscala/util/parsing/combinator/Parsers;
Asciz	scala/Predef$;
class	scala/Predef$
Asciz	MODULE$;
Asciz	Lscala/Predef$;;
NameAndType	MODULE$:Lscala/Predef$;
Field	scala/Predef$.MODULE$:Lscala/Predef$;
Asciz	No result when parsing failed;
String	No result when parsing failed
Asciz	error;
Asciz	(Ljava/lang/String;)Lscala/runtime/Nothing$;;
NameAndType	error:(Ljava/lang/String;)Lscala/runtime/Nothing$;
Method	scala/Predef$.error:(Ljava/lang/String;)Lscala/runtime/Nothing$;
Asciz	flatMapWithNext;
Asciz	<U:Ljava/lang/Object;>(Lscala/Function1<Lscala/runtime/Nothing$;Lscala/Function1<Lscala/util/parsing/input/Reader<Ljava/lang/Object;>;Lscala/util/parsing/combinator/Parsers$ParseResult<TU;>;>;>;)Lscala/util/parsing/combinator/Parsers$ParseResult<TU;>;;
Asciz	mapPartial;
Asciz	(Lscala/PartialFunction;Lscala/Function1;)Lscala/util/parsing/combinator/Parsers$ParseResult;;
Asciz	Lscala/PartialFunction;;
Asciz	<U:Ljava/lang/Object;>(Lscala/PartialFunction<Lscala/runtime/Nothing$;TU;>;Lscala/Function1<Lscala/runtime/Nothing$;Ljava/lang/String;>;)Lscala/util/parsing/combinator/Parsers$ParseResult<TU;>;;
Asciz	<U:Ljava/lang/Object;>(Lscala/Function1<Lscala/runtime/Nothing$;TU;>;)Lscala/util/parsing/combinator/Parsers$NoSuccess;;
Asciz	()Z;
Asciz	()Lscala/util/parsing/input/Reader<Ljava/lang/Object;>;;
Asciz	()Ljava/lang/String;;
Asciz	Lscala/util/parsing/combinator/Parsers$ParseResult<Lscala/runtime/Nothing$;>;Lscala/ScalaObject;;
Asciz	Scala;
Asciz	InnerClasses;
Asciz	NoSuccess;
Asciz	ParseResult;
Asciz	scala/ScalaObject;
class	scala/ScalaObject

{
private final boolean successful;
  Signature: Z

private final scala.util.parsing.input.Reader next;
  Signature: Lscala/util/parsing/input/Reader;
  Signature: length = 0x2
   00 07 

private final java.lang.String msg;
  Signature: Ljava/lang/String;

public scala.util.parsing.combinator.Parsers$NoSuccess(scala.util.parsing.combinator.Parsers, java.lang.String, scala.util.parsing.input.Reader);
  Signature: (Lscala/util/parsing/combinator/Parsers;Ljava/lang/String;Lscala/util/parsing/input/Reader;)V
  Code:
   Stack=2, Locals=5, Args_size=4
	aload_0
	aload_2
	putfield	Field msg:Ljava/lang/String;
	aload_0
	aload_3
	putfield	Field next:Lscala/util/parsing/input/Reader;
	aload_0
	aload_1
	invokespecial	Method scala/util/parsing/combinator/Parsers$ParseResult."<init>":(Lscala/util/parsing/combinator/Parsers;)V
	aload_0
	iconst_0
	putfield	Field successful:Z
	aload_1
	invokeinterface	InterfaceMethod scala/util/parsing/combinator/Parsers.lastNoSuccess:()Lscala/util/parsing/combinator/Parsers$NoSuccess;
	dup
	astore	4
	ifnull	l1 // aload_1
	aload	4
	aconst_null
	invokevirtual	Method java/lang/Object.equals:(Ljava/lang/Object;)Z
	ifne	l1 // aload_1
	aload_3
	invokevirtual	Method scala/util/parsing/input/Reader.pos:()Lscala/util/parsing/input/Position;
	aload_1
	invokeinterface	InterfaceMethod scala/util/parsing/combinator/Parsers.lastNoSuccess:()Lscala/util/parsing/combinator/Parsers$NoSuccess;
	invokevirtual	Method next:()Lscala/util/parsing/input/Reader;
	invokevirtual	Method scala/util/parsing/input/Reader.pos:()Lscala/util/parsing/input/Position;
	invokeinterface	InterfaceMethod scala/util/parsing/input/Position.$less:(Lscala/util/parsing/input/Position;)Z
	ifne	l2 // return
l1	aload_1
	aload_0
	invokeinterface	InterfaceMethod scala/util/parsing/combinator/Parsers.lastNoSuccess_$eq:(Lscala/util/parsing/combinator/Parsers$NoSuccess;)V
l2	return
  Labels:
   	l1 = 65 // aload_1
   	l2 = 72 // return
  LocalVariableTable: 
   Start  Length  Slot  Name   Signature
   0      73      0    this       Lscala/util/parsing/combinator/Parsers$NoSuccess;
   0      73      1    $outer       Lscala/util/parsing/combinator/Parsers;
   0      73      2    msg       Ljava/lang/String;
   0      73      3    next       Lscala/util/parsing/input/Reader;

  Signature: length = 0x2
   00 40 

public scala.util.parsing.combinator.Parsers$ParseResult map(scala.Function1);
  Signature: (Lscala/Function1;)Lscala/util/parsing/combinator/Parsers$ParseResult;
  Code:
   Stack=2, Locals=2, Args_size=2
	aload_0
	aload_1
	invokevirtual	Method map:(Lscala/Function1;)Lscala/util/parsing/combinator/Parsers$NoSuccess;
	areturn
  Labels:
  LocalVariableTable: 
   Start  Length  Slot  Name   Signature
   0      6      0    this       Lscala/util/parsing/combinator/Parsers$NoSuccess;
   0      6      1    f       Lscala/Function1;


public java.lang.Object get();
  Signature: ()Ljava/lang/Object;
  Code:
   Stack=1, Locals=1, Args_size=1
	aload_0
	invokevirtual	Method get:()Lscala/runtime/Nothing$;
	athrow
  Labels:

public scala.util.parsing.combinator.Parsers scala$util$parsing$combinator$Parsers$NoSuccess$$$outer();
  Signature: ()Lscala/util/parsing/combinator/Parsers;
  Code:
   Stack=1, Locals=1, Args_size=1
	aload_0
	getfield	Field scala/util/parsing/combinator/Parsers$ParseResult.$outer:Lscala/util/parsing/combinator/Parsers;
	areturn
  Labels:

public scala.runtime.Nothing$ get();
  Signature: ()Lscala/runtime/Nothing$;
  Code:
   Stack=2, Locals=1, Args_size=1
	getstatic	Field scala/Predef$.MODULE$:Lscala/Predef$;
	ldc	String No result when parsing failed
	invokevirtual	Method scala/Predef$.error:(Ljava/lang/String;)Lscala/runtime/Nothing$;
	areturn
  Labels:

public scala.util.parsing.combinator.Parsers$ParseResult flatMapWithNext(scala.Function1);
  Signature: (Lscala/Function1;)Lscala/util/parsing/combinator/Parsers$ParseResult;
  Code:
   Stack=1, Locals=2, Args_size=2
	aload_0
	areturn
  Labels:
  LocalVariableTable: 
   Start  Length  Slot  Name   Signature
   0      2      0    this       Lscala/util/parsing/combinator/Parsers$NoSuccess;
   0      2      1    f       Lscala/Function1;

  Signature: length = 0x2
   00 5E 

public scala.util.parsing.combinator.Parsers$ParseResult mapPartial(scala.PartialFunction, scala.Function1);
  Signature: (Lscala/PartialFunction;Lscala/Function1;)Lscala/util/parsing/combinator/Parsers$ParseResult;
  Code:
   Stack=1, Locals=3, Args_size=3
	aload_0
	areturn
  Labels:
  LocalVariableTable: 
   Start  Length  Slot  Name   Signature
   0      2      0    this       Lscala/util/parsing/combinator/Parsers$NoSuccess;
   0      2      1    f       Lscala/PartialFunction;
   0      2      2    error       Lscala/Function1;

  Signature: length = 0x2
   00 62 

public scala.util.parsing.combinator.Parsers$NoSuccess map(scala.Function1);
  Signature: (Lscala/Function1;)Lscala/util/parsing/combinator/Parsers$NoSuccess;
  Code:
   Stack=1, Locals=2, Args_size=2
	aload_0
	areturn
  Labels:
  LocalVariableTable: 
   Start  Length  Slot  Name   Signature
   0      2      0    this       Lscala/util/parsing/combinator/Parsers$NoSuccess;
   0      2      1    f       Lscala/Function1;

  Signature: length = 0x2
   00 63 

public boolean successful();
  Signature: ()Z
  Code:
   Stack=1, Locals=1, Args_size=1
	aload_0
	getfield	Field successful:Z
	ireturn
  Labels:

public scala.util.parsing.input.Reader next();
  Signature: ()Lscala/util/parsing/input/Reader;
  Code:
   Stack=1, Locals=1, Args_size=1
	aload_0
	getfield	Field next:Lscala/util/parsing/input/Reader;
	areturn
  Labels:
  Signature: length = 0x2
   00 65 

public java.lang.String msg();
  Signature: ()Ljava/lang/String;
  Code:
   Stack=1, Locals=1, Args_size=1
	aload_0
	getfield	Field msg:Ljava/lang/String;
	areturn
  Labels:

}

