Compiled from "Parsers.scala"
public final class scala.util.parsing.combinator.Parsers$Failure$ extends java.lang.Object implements scala.Function2,scala.ScalaObject
  SourceFile: "Parsers.scala"
  Scala: length = 0x
   
  InnerClass: 
   public Failure=class scala/util/parsing/combinator/Parsers$Failure of class scala/util/parsing/combinator/Parsers
  minor version: 0
  major version: 49
  Constant pool:
Asciz	SourceFile;
Asciz	Parsers.scala;
Asciz	Scala;
Asciz	$outer;
Asciz	Lscala/util/parsing/combinator/Parsers;;
Asciz	<init>;
Asciz	(Lscala/util/parsing/combinator/Parsers;)V;
Asciz	Code;
Asciz	LineNumberTable;
Asciz	java/lang/NullPointerException;
class	java/lang/NullPointerException
Asciz	()V;
NameAndType	"<init>":()V
Method	java/lang/NullPointerException."<init>":()V
Asciz	scala/util/parsing/combinator/Parsers$Failure$;
class	scala/util/parsing/combinator/Parsers$Failure$
NameAndType	$outer:Lscala/util/parsing/combinator/Parsers;
Field	scala/util/parsing/combinator/Parsers$Failure$.$outer:Lscala/util/parsing/combinator/Parsers;
Asciz	java/lang/Object;
class	java/lang/Object
Method	java/lang/Object."<init>":()V
Asciz	scala/Function2$class;
class	scala/Function2$class
Asciz	$init$;
Asciz	(Lscala/Function2;)V;
NameAndType	$init$:(Lscala/Function2;)V
Method	scala/Function2$class.$init$:(Lscala/Function2;)V
Asciz	this;
Asciz	Lscala/util/parsing/combinator/Parsers$Failure$;;
Asciz	LocalVariableTable;
Asciz	apply;
Asciz	(Ljava/lang/Object;Ljava/lang/Object;)Ljava/lang/Object;;
Asciz	java/lang/String;
class	java/lang/String
Asciz	scala/util/parsing/input/Reader;
class	scala/util/parsing/input/Reader
Asciz	(Ljava/lang/String;Lscala/util/parsing/input/Reader;)Lscala/util/parsing/combinator/Parsers$Failure;;
NameAndType	apply:(Ljava/lang/String;Lscala/util/parsing/input/Reader;)Lscala/util/parsing/combinator/Parsers$Failure;
Method	scala/util/parsing/combinator/Parsers$Failure$.apply:(Ljava/lang/String;Lscala/util/parsing/input/Reader;)Lscala/util/parsing/combinator/Parsers$Failure;
Asciz	v1;
Asciz	Ljava/lang/Object;;
Asciz	v2;
Asciz	scala/util/parsing/combinator/Parsers$Failure;
class	scala/util/parsing/combinator/Parsers$Failure
Asciz	(Lscala/util/parsing/combinator/Parsers;Ljava/lang/String;Lscala/util/parsing/input/Reader;)V;
NameAndType	"<init>":(Lscala/util/parsing/combinator/Parsers;Ljava/lang/String;Lscala/util/parsing/input/Reader;)V
Method	scala/util/parsing/combinator/Parsers$Failure."<init>":(Lscala/util/parsing/combinator/Parsers;Ljava/lang/String;Lscala/util/parsing/input/Reader;)V
Asciz	msg;
Asciz	Ljava/lang/String;;
Asciz	next;
Asciz	Lscala/util/parsing/input/Reader;;
Asciz	unapply;
Asciz	(Lscala/util/parsing/combinator/Parsers$Failure;)Lscala/Some;;
Asciz	scala/Some;
class	scala/Some
Asciz	scala/Tuple2;
class	scala/Tuple2
Asciz	()Ljava/lang/String;;
NameAndType	msg:()Ljava/lang/String;
Method	scala/util/parsing/combinator/Parsers$Failure.msg:()Ljava/lang/String;
Asciz	()Lscala/util/parsing/input/Reader;;
NameAndType	next:()Lscala/util/parsing/input/Reader;
Method	scala/util/parsing/combinator/Parsers$Failure.next:()Lscala/util/parsing/input/Reader;
Asciz	(Ljava/lang/Object;Ljava/lang/Object;)V;
NameAndType	"<init>":(Ljava/lang/Object;Ljava/lang/Object;)V
Method	scala/Tuple2."<init>":(Ljava/lang/Object;Ljava/lang/Object;)V
Asciz	(Ljava/lang/Object;)V;
NameAndType	"<init>":(Ljava/lang/Object;)V
Method	scala/Some."<init>":(Ljava/lang/Object;)V
Asciz	x$0;
Asciz	Lscala/util/parsing/combinator/Parsers$Failure;;
Asciz	curry;
Asciz	()Lscala/Function1;;
Asciz	(Lscala/Function2;)Lscala/Function1;;
NameAndType	curry:(Lscala/Function2;)Lscala/Function1;
Method	scala/Function2$class.curry:(Lscala/Function2;)Lscala/Function1;
Asciz	toString;
Asciz	(Lscala/Function2;)Ljava/lang/String;;
NameAndType	toString:(Lscala/Function2;)Ljava/lang/String;
Method	scala/Function2$class.toString:(Lscala/Function2;)Ljava/lang/String;
Asciz	InnerClasses;
Asciz	scala/util/parsing/combinator/Parsers;
class	scala/util/parsing/combinator/Parsers
Asciz	Failure;
Asciz	scala/Function2;
class	scala/Function2
Asciz	scala/ScalaObject;
class	scala/ScalaObject

{
private final scala.util.parsing.combinator.Parsers $outer;
  Signature: Lscala/util/parsing/combinator/Parsers;

public scala.util.parsing.combinator.Parsers$Failure$(scala.util.parsing.combinator.Parsers);
  Signature: (Lscala/util/parsing/combinator/Parsers;)V
  Code:
   Stack=2, Locals=2, Args_size=2
	aload_1
	ifnonnull	l1 // aload_0
	new	class java/lang/NullPointerException
	dup
	invokespecial	Method java/lang/NullPointerException."<init>":()V
	athrow
l1	aload_0
	aload_1
	putfield	Field $outer:Lscala/util/parsing/combinator/Parsers;
	aload_0
	invokespecial	Method java/lang/Object."<init>":()V
	aload_0
	invokestatic	Method scala/Function2$class.$init$:(Lscala/Function2;)V
	return
  Labels:
   	l1 = 12 // aload_0
  LocalVariableTable: 
   Start  Length  Slot  Name   Signature
   0      26      0    this       Lscala/util/parsing/combinator/Parsers$Failure$;
   0      26      1    $outer       Lscala/util/parsing/combinator/Parsers;


public java.lang.Object apply(java.lang.Object, java.lang.Object);
  Signature: (Ljava/lang/Object;Ljava/lang/Object;)Ljava/lang/Object;
  Code:
   Stack=3, Locals=4, Args_size=3
	aload_0
	getfield	Field $outer:Lscala/util/parsing/combinator/Parsers;
	astore_3
	aload_0
	aload_1
	checkcast	class java/lang/String
	aload_2
	checkcast	class scala/util/parsing/input/Reader
	invokevirtual	Method apply:(Ljava/lang/String;Lscala/util/parsing/input/Reader;)Lscala/util/parsing/combinator/Parsers$Failure;
	areturn
  Labels:
  LocalVariableTable: 
   Start  Length  Slot  Name   Signature
   0      18      0    this       Lscala/util/parsing/combinator/Parsers$Failure$;
   5      13      1    v1       Ljava/lang/Object;
   5      13      2    v2       Ljava/lang/Object;


public scala.util.parsing.combinator.Parsers$Failure apply(java.lang.String, scala.util.parsing.input.Reader);
  Signature: (Ljava/lang/String;Lscala/util/parsing/input/Reader;)Lscala/util/parsing/combinator/Parsers$Failure;
  Code:
   Stack=5, Locals=4, Args_size=3
	aload_0
	getfield	Field $outer:Lscala/util/parsing/combinator/Parsers;
	astore_3
	new	class scala/util/parsing/combinator/Parsers$Failure
	dup
	aload_0
	getfield	Field $outer:Lscala/util/parsing/combinator/Parsers;
	aload_1
	aload_2
	invokespecial	Method scala/util/parsing/combinator/Parsers$Failure."<init>":(Lscala/util/parsing/combinator/Parsers;Ljava/lang/String;Lscala/util/parsing/input/Reader;)V
	areturn
  Labels:
  LocalVariableTable: 
   Start  Length  Slot  Name   Signature
   0      19      0    this       Lscala/util/parsing/combinator/Parsers$Failure$;
   5      14      1    msg       Ljava/lang/String;
   5      14      2    next       Lscala/util/parsing/input/Reader;


public scala.Some unapply(scala.util.parsing.combinator.Parsers$Failure);
  Signature: (Lscala/util/parsing/combinator/Parsers$Failure;)Lscala/Some;
  Code:
   Stack=6, Locals=2, Args_size=2
	new	class scala/Some
	dup
	new	class scala/Tuple2
	dup
	aload_1
	invokevirtual	Method scala/util/parsing/combinator/Parsers$Failure.msg:()Ljava/lang/String;
	aload_1
	invokevirtual	Method scala/util/parsing/combinator/Parsers$Failure.next:()Lscala/util/parsing/input/Reader;
	invokespecial	Method scala/Tuple2."<init>":(Ljava/lang/Object;Ljava/lang/Object;)V
	invokespecial	Method scala/Some."<init>":(Ljava/lang/Object;)V
	areturn
  Labels:
  LocalVariableTable: 
   Start  Length  Slot  Name   Signature
   0      23      0    this       Lscala/util/parsing/combinator/Parsers$Failure$;
   0      23      1    x$0       Lscala/util/parsing/combinator/Parsers$Failure;


public scala.Function1 curry();
  Signature: ()Lscala/Function1;
  Code:
   Stack=1, Locals=1, Args_size=1
	aload_0
	invokestatic	Method scala/Function2$class.curry:(Lscala/Function2;)Lscala/Function1;
	areturn
  Labels:

public java.lang.String toString();
  Signature: ()Ljava/lang/String;
  Code:
   Stack=1, Locals=1, Args_size=1
	aload_0
	invokestatic	Method scala/Function2$class.toString:(Lscala/Function2;)Ljava/lang/String;
	areturn
  Labels:

}

