Compiled from "Parsers.scala"
public final class scala.util.parsing.combinator.Parsers$$anonfun$accept$1 extends scala.runtime.AbstractFunction1 implements java.io.Serializable
  SourceFile: "Parsers.scala"
  Scala: length = 0x
   
  InnerClass: 
   public final $anonfun$accept$1=class scala/util/parsing/combinator/Parsers$$anonfun$accept$1 of class scala/util/parsing/combinator/Parsers
  minor version: 0
  major version: 49
  Constant pool:
Asciz	SourceFile;
Asciz	Parsers.scala;
Asciz	<clinit>;
Asciz	()V;
Asciz	Code;
Asciz	serialVersionUID;
Asciz	J;
Asciz	scala/util/parsing/combinator/Parsers$$anonfun$accept$1;
class	scala/util/parsing/combinator/Parsers$$anonfun$accept$1
NameAndType	serialVersionUID:J
Field	scala/util/parsing/combinator/Parsers$$anonfun$accept$1.serialVersionUID:J
Asciz	e$1;
Asciz	Ljava/lang/Object;;
Asciz	apply;
Asciz	(Ljava/lang/Object;)Z;
Asciz	LineNumberTable;
NameAndType	e$1:Ljava/lang/Object;
Field	scala/util/parsing/combinator/Parsers$$anonfun$accept$1.e$1:Ljava/lang/Object;
Asciz	java/lang/Number;
class	java/lang/Number
Asciz	scala/runtime/BoxesRunTime;
class	scala/runtime/BoxesRunTime
Asciz	equalsNumObject;
Asciz	(Ljava/lang/Number;Ljava/lang/Object;)Z;
NameAndType	equalsNumObject:(Ljava/lang/Number;Ljava/lang/Object;)Z
Method	scala/runtime/BoxesRunTime.equalsNumObject:(Ljava/lang/Number;Ljava/lang/Object;)Z
Asciz	java/lang/Character;
class	java/lang/Character
Asciz	equalsCharObject;
Asciz	(Ljava/lang/Character;Ljava/lang/Object;)Z;
NameAndType	equalsCharObject:(Ljava/lang/Character;Ljava/lang/Object;)Z
Method	scala/runtime/BoxesRunTime.equalsCharObject:(Ljava/lang/Character;Ljava/lang/Object;)Z
Asciz	java/lang/Object;
class	java/lang/Object
Asciz	equals;
NameAndType	equals:(Ljava/lang/Object;)Z
Method	java/lang/Object.equals:(Ljava/lang/Object;)Z
Asciz	this;
Asciz	Lscala/util/parsing/combinator/Parsers$$anonfun$accept$1;;
Asciz	y0;
Asciz	LocalVariableTable;
Asciz	(Ljava/lang/Object;)Ljava/lang/Object;;
NameAndType	apply:(Ljava/lang/Object;)Z
Method	scala/util/parsing/combinator/Parsers$$anonfun$accept$1.apply:(Ljava/lang/Object;)Z
Asciz	boxToBoolean;
Asciz	(Z)Ljava/lang/Boolean;;
NameAndType	boxToBoolean:(Z)Ljava/lang/Boolean;
Method	scala/runtime/BoxesRunTime.boxToBoolean:(Z)Ljava/lang/Boolean;
Asciz	v1;
Asciz	<init>;
Asciz	(Lscala/util/parsing/combinator/Parsers;Ljava/lang/Object;)V;
Asciz	scala/runtime/AbstractFunction1;
class	scala/runtime/AbstractFunction1
NameAndType	"<init>":()V
Method	scala/runtime/AbstractFunction1."<init>":()V
Asciz	$outer;
Asciz	Lscala/util/parsing/combinator/Parsers;;
Asciz	Scala;
Asciz	InnerClasses;
Asciz	scala/util/parsing/combinator/Parsers;
class	scala/util/parsing/combinator/Parsers
Asciz	$anonfun$accept$1;
Asciz	java/io/Serializable;
class	java/io/Serializable

{
public static final long serialVersionUID;
  Signature: J

public final java.lang.Object e$1;
  Signature: Ljava/lang/Object;

public static {};
  Signature: ()V
  Code:
   Stack=2, Locals=0, Args_size=0
	lconst_0
	putstatic	Field serialVersionUID:J
	return
  Labels:

public final boolean apply(java.lang.Object);
  Signature: (Ljava/lang/Object;)Z
  Code:
   Stack=2, Locals=3, Args_size=2
	aload_0
	getfield	Field e$1:Ljava/lang/Object;
	astore_2
	aload_1
	aload_2
	if_acmpne	l1 // aload_1
	iconst_1
	goto	l2 // ifeq
l1	aload_1
	ifnonnull	l3 // aload_1
	iconst_0
	goto	l2 // ifeq
l3	aload_1
	instanceof	class java/lang/Number
	ifeq	l4 // aload_1
	aload_1
	checkcast	class java/lang/Number
	aload_2
	invokestatic	Method scala/runtime/BoxesRunTime.equalsNumObject:(Ljava/lang/Number;Ljava/lang/Object;)Z
	goto	l2 // ifeq
l4	aload_1
	instanceof	class java/lang/Character
	ifeq	l5 // aload_1
	aload_1
	checkcast	class java/lang/Character
	aload_2
	invokestatic	Method scala/runtime/BoxesRunTime.equalsCharObject:(Ljava/lang/Character;Ljava/lang/Object;)Z
	goto	l2 // ifeq
l5	aload_1
	aload_2
	invokevirtual	Method java/lang/Object.equals:(Ljava/lang/Object;)Z
l2	ifeq	l6 // iconst_0
	iconst_1
	goto	l7 // ireturn
l6	iconst_0
l7	ireturn
  Labels:
   	l1 = 14 // aload_1
   	l3 = 22 // aload_1
   	l4 = 40 // aload_1
   	l5 = 58 // aload_1
   	l2 = 63 // ifeq
   	l6 = 70 // iconst_0
   	l7 = 71 // ireturn
  LocalVariableTable: 
   Start  Length  Slot  Name   Signature
   0      72      0    this       Lscala/util/parsing/combinator/Parsers$$anonfun$accept$1;
   10      56      2    y0       Ljava/lang/Object;


public final java.lang.Object apply(java.lang.Object);
  Signature: (Ljava/lang/Object;)Ljava/lang/Object;
  Code:
   Stack=2, Locals=3, Args_size=2
	aload_0
	aload_1
	invokevirtual	Method apply:(Ljava/lang/Object;)Z
	istore_2
	iload_2
	invokestatic	Method scala/runtime/BoxesRunTime.boxToBoolean:(Z)Ljava/lang/Boolean;
	areturn
  Labels:
  LocalVariableTable: 
   Start  Length  Slot  Name   Signature
   0      11      0    this       Lscala/util/parsing/combinator/Parsers$$anonfun$accept$1;
   0      11      1    v1       Ljava/lang/Object;


public scala.util.parsing.combinator.Parsers$$anonfun$accept$1(scala.util.parsing.combinator.Parsers, java.lang.Object);
  Signature: (Lscala/util/parsing/combinator/Parsers;Ljava/lang/Object;)V
  Code:
   Stack=2, Locals=3, Args_size=3
	aload_0
	aload_2
	putfield	Field e$1:Ljava/lang/Object;
	aload_0
	invokespecial	Method scala/runtime/AbstractFunction1."<init>":()V
	return
  Labels:
  LocalVariableTable: 
   Start  Length  Slot  Name   Signature
   0      10      0    this       Lscala/util/parsing/combinator/Parsers$$anonfun$accept$1;
   0      10      1    $outer       Lscala/util/parsing/combinator/Parsers;


}

