Compiled from "Parsers.scala"
public abstract class scala.util.parsing.combinator.Parsers$class extends java.lang.Object
  SourceFile: "Parsers.scala"
  Scala: length = 0x
   
  InnerClass: 
   public abstract Parser=class scala/util/parsing/combinator/Parsers$Parser of class scala/util/parsing/combinator/Parsers
   public final $anon$2=class scala/util/parsing/combinator/Parsers$$anon$2 of class scala/util/parsing/combinator/Parsers
   public Success=class scala/util/parsing/combinator/Parsers$Success of class scala/util/parsing/combinator/Parsers
   public final $anon$1=class scala/util/parsing/combinator/Parsers$$anon$1 of class scala/util/parsing/combinator/Parsers
   public final $anon$3=class scala/util/parsing/combinator/Parsers$$anon$3 of class scala/util/parsing/combinator/Parsers
   public abstract NoSuccess=class scala/util/parsing/combinator/Parsers$NoSuccess of class scala/util/parsing/combinator/Parsers
   public abstract OnceParser=class scala/util/parsing/combinator/Parsers$OnceParser of class scala/util/parsing/combinator/Parsers
   public abstract ParseResult=class scala/util/parsing/combinator/Parsers$ParseResult of class scala/util/parsing/combinator/Parsers
   public final $anonfun$not$1=class scala/util/parsing/combinator/Parsers$$anonfun$not$1 of class scala/util/parsing/combinator/Parsers
   public final $anonfun$opt$2=class scala/util/parsing/combinator/Parsers$$anonfun$opt$2 of class scala/util/parsing/combinator/Parsers
   public final $anonfun$opt$1=class scala/util/parsing/combinator/Parsers$$anonfun$opt$1 of class scala/util/parsing/combinator/Parsers
   public final $anonfun$rep$1=class scala/util/parsing/combinator/Parsers$$anonfun$rep$1 of class scala/util/parsing/combinator/Parsers
   public final $anonfun$log$1=class scala/util/parsing/combinator/Parsers$$anonfun$log$1 of class scala/util/parsing/combinator/Parsers
   public final $anonfun$err$1=class scala/util/parsing/combinator/Parsers$$anonfun$err$1 of class scala/util/parsing/combinator/Parsers
   public final $anonfun$repN$1=class scala/util/parsing/combinator/Parsers$$anonfun$repN$1 of class scala/util/parsing/combinator/Parsers
   public final $anonfun$rep1$1=class scala/util/parsing/combinator/Parsers$$anonfun$rep1$1 of class scala/util/parsing/combinator/Parsers
   public final $anonfun$elem$1=class scala/util/parsing/combinator/Parsers$$anonfun$elem$1 of class scala/util/parsing/combinator/Parsers
   public final $anonfun$guard$1=class scala/util/parsing/combinator/Parsers$$anonfun$guard$1 of class scala/util/parsing/combinator/Parsers
   public final $anonfun$mkList$1=class scala/util/parsing/combinator/Parsers$$anonfun$mkList$1 of class scala/util/parsing/combinator/Parsers
   public final $anonfun$repsep$1=class scala/util/parsing/combinator/Parsers$$anonfun$repsep$1 of class scala/util/parsing/combinator/Parsers
   public final $anonfun$accept$2=class scala/util/parsing/combinator/Parsers$$anonfun$accept$2 of class scala/util/parsing/combinator/Parsers
   public final $anonfun$accept$1=class scala/util/parsing/combinator/Parsers$$anonfun$accept$1 of class scala/util/parsing/combinator/Parsers
   public final $anonfun$commit$1=class scala/util/parsing/combinator/Parsers$$anonfun$commit$1 of class scala/util/parsing/combinator/Parsers
   public final $anonfun$chainr1$2=class scala/util/parsing/combinator/Parsers$$anonfun$chainr1$2 of class scala/util/parsing/combinator/Parsers
   public final $anonfun$chainr1$1=class scala/util/parsing/combinator/Parsers$$anonfun$chainr1$1 of class scala/util/parsing/combinator/Parsers
   public final $anonfun$chainl1$2=class scala/util/parsing/combinator/Parsers$$anonfun$chainl1$2 of class scala/util/parsing/combinator/Parsers
   public final $anonfun$chainl1$1=class scala/util/parsing/combinator/Parsers$$anonfun$chainl1$1 of class scala/util/parsing/combinator/Parsers
   public final $anonfun$rep1sep$2=class scala/util/parsing/combinator/Parsers$$anonfun$rep1sep$2 of class scala/util/parsing/combinator/Parsers
   public final $anonfun$rep1sep$1=class scala/util/parsing/combinator/Parsers$$anonfun$rep1sep$1 of class scala/util/parsing/combinator/Parsers
   public final $anonfun$success$1=class scala/util/parsing/combinator/Parsers$$anonfun$success$1 of class scala/util/parsing/combinator/Parsers
   public final $anonfun$failure$1=class scala/util/parsing/combinator/Parsers$$anonfun$failure$1 of class scala/util/parsing/combinator/Parsers
   public final $anonfun$acceptIf$1=class scala/util/parsing/combinator/Parsers$$anonfun$acceptIf$1 of class scala/util/parsing/combinator/Parsers
   public final $anonfun$acceptSeq$1=class scala/util/parsing/combinator/Parsers$$anonfun$acceptSeq$1 of class scala/util/parsing/combinator/Parsers
   public final $anonfun$positioned$1=class scala/util/parsing/combinator/Parsers$$anonfun$positioned$1 of class scala/util/parsing/combinator/Parsers
   public final $anonfun$acceptMatch$1=class scala/util/parsing/combinator/Parsers$$anonfun$acceptMatch$1 of class scala/util/parsing/combinator/Parsers
  minor version: 0
  major version: 49
  Constant pool:
Asciz	SourceFile;
Asciz	Parsers.scala;
Asciz	Parser;
Asciz	(Lscala/util/parsing/combinator/Parsers;Lscala/Function1;)Lscala/util/parsing/combinator/Parsers$Parser;;
Asciz	Code;
Asciz	scala/util/parsing/combinator/Parsers$$anon$3;
class	scala/util/parsing/combinator/Parsers$$anon$3
Asciz	LineNumberTable;
Asciz	<init>;
Asciz	(Lscala/util/parsing/combinator/Parsers;Lscala/Function1;)V;
NameAndType	"<init>":(Lscala/util/parsing/combinator/Parsers;Lscala/Function1;)V
Method	scala/util/parsing/combinator/Parsers$$anon$3."<init>":(Lscala/util/parsing/combinator/Parsers;Lscala/Function1;)V
Asciz	$this;
Asciz	Lscala/util/parsing/combinator/Parsers;;
Asciz	f$1;
Asciz	Lscala/Function1;;
Asciz	LocalVariableTable;
Asciz	OnceParser;
Asciz	(Lscala/util/parsing/combinator/Parsers;Lscala/Function1;)Lscala/util/parsing/combinator/Parsers$OnceParser;;
Asciz	scala/util/parsing/combinator/Parsers$$anon$1;
class	scala/util/parsing/combinator/Parsers$$anon$1
Method	scala/util/parsing/combinator/Parsers$$anon$1."<init>":(Lscala/util/parsing/combinator/Parsers;Lscala/Function1;)V
Asciz	f$2;
Asciz	seq;
Asciz	(Lscala/util/parsing/combinator/Parsers;Lscala/Function0;Lscala/Function0;Lscala/Function2;Lscala/util/parsing/input/Reader;)Lscala/util/parsing/combinator/Parsers$ParseResult;;
Asciz	scala/Function0;
class	scala/Function0
Asciz	apply;
Asciz	()Ljava/lang/Object;;
NameAndType	apply:()Ljava/lang/Object;
InterfaceMethod	scala/Function0.apply:()Ljava/lang/Object;
Asciz	scala/Function1;
class	scala/Function1
Asciz	(Ljava/lang/Object;)Ljava/lang/Object;;
NameAndType	apply:(Ljava/lang/Object;)Ljava/lang/Object;
InterfaceMethod	scala/Function1.apply:(Ljava/lang/Object;)Ljava/lang/Object;
Asciz	scala/util/parsing/combinator/Parsers$ParseResult;
class	scala/util/parsing/combinator/Parsers$ParseResult
Asciz	scala/util/parsing/combinator/Parsers$Success;
class	scala/util/parsing/combinator/Parsers$Success
Asciz	next;
Asciz	()Lscala/util/parsing/input/Reader;;
NameAndType	next:()Lscala/util/parsing/input/Reader;
Method	scala/util/parsing/combinator/Parsers$Success.next:()Lscala/util/parsing/input/Reader;
Asciz	result;
NameAndType	result:()Ljava/lang/Object;
Method	scala/util/parsing/combinator/Parsers$Success.result:()Ljava/lang/Object;
Asciz	scala/Function2;
class	scala/Function2
Asciz	(Ljava/lang/Object;Ljava/lang/Object;)Ljava/lang/Object;;
NameAndType	apply:(Ljava/lang/Object;Ljava/lang/Object;)Ljava/lang/Object;
InterfaceMethod	scala/Function2.apply:(Ljava/lang/Object;Ljava/lang/Object;)Ljava/lang/Object;
Asciz	(Lscala/util/parsing/combinator/Parsers;Ljava/lang/Object;Lscala/util/parsing/input/Reader;)V;
NameAndType	"<init>":(Lscala/util/parsing/combinator/Parsers;Ljava/lang/Object;Lscala/util/parsing/input/Reader;)V
Method	scala/util/parsing/combinator/Parsers$Success."<init>":(Lscala/util/parsing/combinator/Parsers;Ljava/lang/Object;Lscala/util/parsing/input/Reader;)V
Asciz	scala/util/parsing/combinator/Parsers$NoSuccess;
class	scala/util/parsing/combinator/Parsers$NoSuccess
Asciz	scala/MatchError;
class	scala/MatchError
Asciz	(Ljava/lang/Object;)V;
NameAndType	"<init>":(Ljava/lang/Object;)V
Method	scala/MatchError."<init>":(Ljava/lang/Object;)V
Asciz	p;
Asciz	Lscala/Function0;;
Asciz	q;
Asciz	compose;
Asciz	Lscala/Function2;;
Asciz	in;
Asciz	Lscala/util/parsing/input/Reader;;
Asciz	temp55;
Asciz	temp53;
Asciz	Lscala/util/parsing/combinator/Parsers$Success;;
Asciz	temp48;
Asciz	temp47;
Asciz	Lscala/util/parsing/combinator/Parsers$ParseResult;;
Asciz	temp52;
Asciz	commit;
Asciz	(Lscala/util/parsing/combinator/Parsers;Lscala/Function0;)Lscala/util/parsing/combinator/Parsers$Parser;;
Asciz	scala/util/parsing/combinator/Parsers$$anonfun$commit$1;
class	scala/util/parsing/combinator/Parsers$$anonfun$commit$1
Asciz	(Lscala/util/parsing/combinator/Parsers;Lscala/Function0;)V;
NameAndType	"<init>":(Lscala/util/parsing/combinator/Parsers;Lscala/Function0;)V
Method	scala/util/parsing/combinator/Parsers$$anonfun$commit$1."<init>":(Lscala/util/parsing/combinator/Parsers;Lscala/Function0;)V
Asciz	scala/util/parsing/combinator/Parsers;
class	scala/util/parsing/combinator/Parsers
Asciz	(Lscala/Function1;)Lscala/util/parsing/combinator/Parsers$Parser;;
NameAndType	Parser:(Lscala/Function1;)Lscala/util/parsing/combinator/Parsers$Parser;
InterfaceMethod	scala/util/parsing/combinator/Parsers.Parser:(Lscala/Function1;)Lscala/util/parsing/combinator/Parsers$Parser;
Asciz	p$8;
Asciz	elem;
Asciz	(Lscala/util/parsing/combinator/Parsers;Ljava/lang/String;Lscala/Function1;)Lscala/util/parsing/combinator/Parsers$Parser;;
Asciz	scala/util/parsing/combinator/Parsers$$anonfun$elem$1;
class	scala/util/parsing/combinator/Parsers$$anonfun$elem$1
Asciz	(Lscala/util/parsing/combinator/Parsers;Ljava/lang/String;)V;
NameAndType	"<init>":(Lscala/util/parsing/combinator/Parsers;Ljava/lang/String;)V
Method	scala/util/parsing/combinator/Parsers$$anonfun$elem$1."<init>":(Lscala/util/parsing/combinator/Parsers;Ljava/lang/String;)V
Asciz	acceptIf;
Asciz	(Lscala/Function1;Lscala/Function1;)Lscala/util/parsing/combinator/Parsers$Parser;;
NameAndType	acceptIf:(Lscala/Function1;Lscala/Function1;)Lscala/util/parsing/combinator/Parsers$Parser;
InterfaceMethod	scala/util/parsing/combinator/Parsers.acceptIf:(Lscala/Function1;Lscala/Function1;)Lscala/util/parsing/combinator/Parsers$Parser;
Asciz	kind$1;
Asciz	Ljava/lang/String;;
Asciz	(Lscala/util/parsing/combinator/Parsers;Ljava/lang/Object;)Lscala/util/parsing/combinator/Parsers$Parser;;
Asciz	accept;
Asciz	(Ljava/lang/Object;)Lscala/util/parsing/combinator/Parsers$Parser;;
NameAndType	accept:(Ljava/lang/Object;)Lscala/util/parsing/combinator/Parsers$Parser;
InterfaceMethod	scala/util/parsing/combinator/Parsers.accept:(Ljava/lang/Object;)Lscala/util/parsing/combinator/Parsers$Parser;
Asciz	e;
Asciz	Ljava/lang/Object;;
Asciz	scala/util/parsing/combinator/Parsers$$anonfun$accept$1;
class	scala/util/parsing/combinator/Parsers$$anonfun$accept$1
Asciz	(Lscala/util/parsing/combinator/Parsers;Ljava/lang/Object;)V;
NameAndType	"<init>":(Lscala/util/parsing/combinator/Parsers;Ljava/lang/Object;)V
Method	scala/util/parsing/combinator/Parsers$$anonfun$accept$1."<init>":(Lscala/util/parsing/combinator/Parsers;Ljava/lang/Object;)V
Asciz	scala/util/parsing/combinator/Parsers$$anonfun$accept$2;
class	scala/util/parsing/combinator/Parsers$$anonfun$accept$2
Method	scala/util/parsing/combinator/Parsers$$anonfun$accept$2."<init>":(Lscala/util/parsing/combinator/Parsers;Ljava/lang/Object;)V
Asciz	e$1;
Asciz	(Lscala/util/parsing/combinator/Parsers;Ljava/lang/Object;Lscala/Function1;)Lscala/util/parsing/combinator/Parsers$Parser;;
Asciz	acceptSeq;
Asciz	(Ljava/lang/Object;Lscala/Function1;)Lscala/util/parsing/combinator/Parsers$Parser;;
NameAndType	acceptSeq:(Ljava/lang/Object;Lscala/Function1;)Lscala/util/parsing/combinator/Parsers$Parser;
InterfaceMethod	scala/util/parsing/combinator/Parsers.acceptSeq:(Ljava/lang/Object;Lscala/Function1;)Lscala/util/parsing/combinator/Parsers$Parser;
Asciz	es;
Asciz	evidence$1;
Asciz	(Lscala/util/parsing/combinator/Parsers;Ljava/lang/String;Lscala/PartialFunction;)Lscala/util/parsing/combinator/Parsers$Parser;;
Asciz	acceptMatch;
Asciz	(Ljava/lang/String;Lscala/PartialFunction;)Lscala/util/parsing/combinator/Parsers$Parser;;
NameAndType	acceptMatch:(Ljava/lang/String;Lscala/PartialFunction;)Lscala/util/parsing/combinator/Parsers$Parser;
InterfaceMethod	scala/util/parsing/combinator/Parsers.acceptMatch:(Ljava/lang/String;Lscala/PartialFunction;)Lscala/util/parsing/combinator/Parsers$Parser;
Asciz	expected;
Asciz	f;
Asciz	Lscala/PartialFunction;;
Asciz	(Lscala/util/parsing/combinator/Parsers;Lscala/Function1;Lscala/Function1;)Lscala/util/parsing/combinator/Parsers$Parser;;
Asciz	scala/util/parsing/combinator/Parsers$$anonfun$acceptIf$1;
class	scala/util/parsing/combinator/Parsers$$anonfun$acceptIf$1
Asciz	(Lscala/util/parsing/combinator/Parsers;Lscala/Function1;Lscala/Function1;)V;
NameAndType	"<init>":(Lscala/util/parsing/combinator/Parsers;Lscala/Function1;Lscala/Function1;)V
Method	scala/util/parsing/combinator/Parsers$$anonfun$acceptIf$1."<init>":(Lscala/util/parsing/combinator/Parsers;Lscala/Function1;Lscala/Function1;)V
Asciz	p$11;
Asciz	err$1;
Asciz	scala/util/parsing/combinator/Parsers$$anonfun$acceptMatch$1;
class	scala/util/parsing/combinator/Parsers$$anonfun$acceptMatch$1
Asciz	(Lscala/util/parsing/combinator/Parsers;Ljava/lang/String;Lscala/PartialFunction;)V;
NameAndType	"<init>":(Lscala/util/parsing/combinator/Parsers;Ljava/lang/String;Lscala/PartialFunction;)V
Method	scala/util/parsing/combinator/Parsers$$anonfun$acceptMatch$1."<init>":(Lscala/util/parsing/combinator/Parsers;Ljava/lang/String;Lscala/PartialFunction;)V
Asciz	expected$1;
Asciz	f$6;
Asciz	scala/collection/IterableLike;
class	scala/collection/IterableLike
Asciz	scala/collection/immutable/Nil$;
class	scala/collection/immutable/Nil$
Asciz	MODULE$;
Asciz	Lscala/collection/immutable/Nil$;;
NameAndType	MODULE$:Lscala/collection/immutable/Nil$;
Field	scala/collection/immutable/Nil$.MODULE$:Lscala/collection/immutable/Nil$;
Asciz	success;
NameAndType	success:(Ljava/lang/Object;)Lscala/util/parsing/combinator/Parsers$Parser;
InterfaceMethod	scala/util/parsing/combinator/Parsers.success:(Ljava/lang/Object;)Lscala/util/parsing/combinator/Parsers$Parser;
Asciz	scala/util/parsing/combinator/Parsers$$anonfun$acceptSeq$1;
class	scala/util/parsing/combinator/Parsers$$anonfun$acceptSeq$1
Asciz	(Lscala/util/parsing/combinator/Parsers;)V;
NameAndType	"<init>":(Lscala/util/parsing/combinator/Parsers;)V
Method	scala/util/parsing/combinator/Parsers$$anonfun$acceptSeq$1."<init>":(Lscala/util/parsing/combinator/Parsers;)V
Asciz	foldRight;
Asciz	(Ljava/lang/Object;Lscala/Function2;)Ljava/lang/Object;;
NameAndType	foldRight:(Ljava/lang/Object;Lscala/Function2;)Ljava/lang/Object;
InterfaceMethod	scala/collection/IterableLike.foldRight:(Ljava/lang/Object;Lscala/Function2;)Ljava/lang/Object;
Asciz	scala/util/parsing/combinator/Parsers$Parser;
class	scala/util/parsing/combinator/Parsers$Parser
Asciz	evidence$2;
Asciz	failure;
Asciz	(Lscala/util/parsing/combinator/Parsers;Ljava/lang/String;)Lscala/util/parsing/combinator/Parsers$Parser;;
Asciz	scala/util/parsing/combinator/Parsers$$anonfun$failure$1;
class	scala/util/parsing/combinator/Parsers$$anonfun$failure$1
Method	scala/util/parsing/combinator/Parsers$$anonfun$failure$1."<init>":(Lscala/util/parsing/combinator/Parsers;Ljava/lang/String;)V
Asciz	msg$3;
Asciz	err;
Asciz	scala/util/parsing/combinator/Parsers$$anonfun$err$1;
class	scala/util/parsing/combinator/Parsers$$anonfun$err$1
Method	scala/util/parsing/combinator/Parsers$$anonfun$err$1."<init>":(Lscala/util/parsing/combinator/Parsers;Ljava/lang/String;)V
Asciz	msg$4;
Asciz	scala/util/parsing/combinator/Parsers$$anonfun$success$1;
class	scala/util/parsing/combinator/Parsers$$anonfun$success$1
Method	scala/util/parsing/combinator/Parsers$$anonfun$success$1."<init>":(Lscala/util/parsing/combinator/Parsers;Ljava/lang/Object;)V
Asciz	v$1;
Asciz	log;
Asciz	(Lscala/util/parsing/combinator/Parsers;Lscala/Function0;Ljava/lang/String;)Lscala/util/parsing/combinator/Parsers$Parser;;
Asciz	scala/util/parsing/combinator/Parsers$$anonfun$log$1;
class	scala/util/parsing/combinator/Parsers$$anonfun$log$1
Asciz	(Lscala/util/parsing/combinator/Parsers;Lscala/Function0;Ljava/lang/String;)V;
NameAndType	"<init>":(Lscala/util/parsing/combinator/Parsers;Lscala/Function0;Ljava/lang/String;)V
Method	scala/util/parsing/combinator/Parsers$$anonfun$log$1."<init>":(Lscala/util/parsing/combinator/Parsers;Lscala/Function0;Ljava/lang/String;)V
Asciz	p$12;
Asciz	name$1;
Asciz	rep;
Asciz	rep1;
Asciz	(Lscala/Function0;)Lscala/util/parsing/combinator/Parsers$Parser;;
NameAndType	rep1:(Lscala/Function0;)Lscala/util/parsing/combinator/Parsers$Parser;
InterfaceMethod	scala/util/parsing/combinator/Parsers.rep1:(Lscala/Function0;)Lscala/util/parsing/combinator/Parsers$Parser;
Asciz	scala/util/parsing/combinator/Parsers$$anonfun$rep$1;
class	scala/util/parsing/combinator/Parsers$$anonfun$rep$1
Method	scala/util/parsing/combinator/Parsers$$anonfun$rep$1."<init>":(Lscala/util/parsing/combinator/Parsers;)V
Asciz	$bar;
NameAndType	$bar:(Lscala/Function0;)Lscala/util/parsing/combinator/Parsers$Parser;
Method	scala/util/parsing/combinator/Parsers$Parser.$bar:(Lscala/Function0;)Lscala/util/parsing/combinator/Parsers$Parser;
Asciz	repsep;
Asciz	(Lscala/util/parsing/combinator/Parsers;Lscala/Function0;Lscala/Function0;)Lscala/util/parsing/combinator/Parsers$Parser;;
Asciz	rep1sep;
Asciz	(Lscala/Function0;Lscala/Function0;)Lscala/util/parsing/combinator/Parsers$Parser;;
NameAndType	rep1sep:(Lscala/Function0;Lscala/Function0;)Lscala/util/parsing/combinator/Parsers$Parser;
InterfaceMethod	scala/util/parsing/combinator/Parsers.rep1sep:(Lscala/Function0;Lscala/Function0;)Lscala/util/parsing/combinator/Parsers$Parser;
Asciz	scala/util/parsing/combinator/Parsers$$anonfun$repsep$1;
class	scala/util/parsing/combinator/Parsers$$anonfun$repsep$1
Method	scala/util/parsing/combinator/Parsers$$anonfun$repsep$1."<init>":(Lscala/util/parsing/combinator/Parsers;)V
NameAndType	rep1:(Lscala/Function0;Lscala/Function0;)Lscala/util/parsing/combinator/Parsers$Parser;
InterfaceMethod	scala/util/parsing/combinator/Parsers.rep1:(Lscala/Function0;Lscala/Function0;)Lscala/util/parsing/combinator/Parsers$Parser;
Asciz	scala/util/parsing/combinator/Parsers$$anonfun$rep1$1;
class	scala/util/parsing/combinator/Parsers$$anonfun$rep1$1
Asciz	(Lscala/util/parsing/combinator/Parsers;Lscala/Function0;Lscala/Function0;)V;
NameAndType	"<init>":(Lscala/util/parsing/combinator/Parsers;Lscala/Function0;Lscala/Function0;)V
Method	scala/util/parsing/combinator/Parsers$$anonfun$rep1$1."<init>":(Lscala/util/parsing/combinator/Parsers;Lscala/Function0;Lscala/Function0;)V
Asciz	first$1;
Asciz	p$10;
Asciz	repN;
Asciz	(Lscala/util/parsing/combinator/Parsers;ILscala/Function0;)Lscala/util/parsing/combinator/Parsers$Parser;;
Asciz	scala/util/parsing/combinator/Parsers$$anonfun$repN$1;
class	scala/util/parsing/combinator/Parsers$$anonfun$repN$1
Asciz	(Lscala/util/parsing/combinator/Parsers;ILscala/Function0;)V;
NameAndType	"<init>":(Lscala/util/parsing/combinator/Parsers;ILscala/Function0;)V
Method	scala/util/parsing/combinator/Parsers$$anonfun$repN$1."<init>":(Lscala/util/parsing/combinator/Parsers;ILscala/Function0;)V
Asciz	num$1;
Asciz	I;
Asciz	p$14;
Asciz	scala/util/parsing/combinator/Parsers$$anonfun$rep1sep$1;
class	scala/util/parsing/combinator/Parsers$$anonfun$rep1sep$1
Method	scala/util/parsing/combinator/Parsers$$anonfun$rep1sep$1."<init>":(Lscala/util/parsing/combinator/Parsers;Lscala/Function0;Lscala/Function0;)V
Asciz	$tilde;
NameAndType	$tilde:(Lscala/Function0;)Lscala/util/parsing/combinator/Parsers$Parser;
Method	scala/util/parsing/combinator/Parsers$Parser.$tilde:(Lscala/Function0;)Lscala/util/parsing/combinator/Parsers$Parser;
Asciz	scala/util/parsing/combinator/Parsers$$anonfun$rep1sep$2;
class	scala/util/parsing/combinator/Parsers$$anonfun$rep1sep$2
Method	scala/util/parsing/combinator/Parsers$$anonfun$rep1sep$2."<init>":(Lscala/util/parsing/combinator/Parsers;)V
Asciz	$up$up;
NameAndType	$up$up:(Lscala/Function1;)Lscala/util/parsing/combinator/Parsers$Parser;
Method	scala/util/parsing/combinator/Parsers$Parser.$up$up:(Lscala/Function1;)Lscala/util/parsing/combinator/Parsers$Parser;
Asciz	p$13;
Asciz	q$3;
Asciz	chainl1;
Asciz	(Lscala/Function0;Lscala/Function0;Lscala/Function0;)Lscala/util/parsing/combinator/Parsers$Parser;;
NameAndType	chainl1:(Lscala/Function0;Lscala/Function0;Lscala/Function0;)Lscala/util/parsing/combinator/Parsers$Parser;
InterfaceMethod	scala/util/parsing/combinator/Parsers.chainl1:(Lscala/Function0;Lscala/Function0;Lscala/Function0;)Lscala/util/parsing/combinator/Parsers$Parser;
Asciz	(Lscala/util/parsing/combinator/Parsers;Lscala/Function0;Lscala/Function0;Lscala/Function0;)Lscala/util/parsing/combinator/Parsers$Parser;;
Asciz	scala/util/parsing/combinator/Parsers$$anonfun$chainl1$1;
class	scala/util/parsing/combinator/Parsers$$anonfun$chainl1$1
Method	scala/util/parsing/combinator/Parsers$$anonfun$chainl1$1."<init>":(Lscala/util/parsing/combinator/Parsers;Lscala/Function0;Lscala/Function0;)V
Asciz	scala/util/parsing/combinator/Parsers$$anonfun$chainl1$2;
class	scala/util/parsing/combinator/Parsers$$anonfun$chainl1$2
Method	scala/util/parsing/combinator/Parsers$$anonfun$chainl1$2."<init>":(Lscala/util/parsing/combinator/Parsers;)V
Asciz	first;
Asciz	p$9;
Asciz	q$2;
Asciz	chainr1;
Asciz	(Lscala/util/parsing/combinator/Parsers;Lscala/Function0;Lscala/Function0;Lscala/Function2;Ljava/lang/Object;)Lscala/util/parsing/combinator/Parsers$Parser;;
Asciz	scala/util/parsing/combinator/Parsers$$anonfun$chainr1$1;
class	scala/util/parsing/combinator/Parsers$$anonfun$chainr1$1
Method	scala/util/parsing/combinator/Parsers$$anonfun$chainr1$1."<init>":(Lscala/util/parsing/combinator/Parsers;Lscala/Function0;Lscala/Function0;)V
Asciz	scala/util/parsing/combinator/Parsers$$anonfun$chainr1$2;
class	scala/util/parsing/combinator/Parsers$$anonfun$chainr1$2
Asciz	(Lscala/util/parsing/combinator/Parsers;Lscala/Function2;Ljava/lang/Object;)V;
NameAndType	"<init>":(Lscala/util/parsing/combinator/Parsers;Lscala/Function2;Ljava/lang/Object;)V
Method	scala/util/parsing/combinator/Parsers$$anonfun$chainr1$2."<init>":(Lscala/util/parsing/combinator/Parsers;Lscala/Function2;Ljava/lang/Object;)V
Asciz	p$15;
Asciz	q$4;
Asciz	combine$1;
Asciz	first$2;
Asciz	opt;
Asciz	scala/util/parsing/combinator/Parsers$$anonfun$opt$1;
class	scala/util/parsing/combinator/Parsers$$anonfun$opt$1
Method	scala/util/parsing/combinator/Parsers$$anonfun$opt$1."<init>":(Lscala/util/parsing/combinator/Parsers;)V
Asciz	scala/util/parsing/combinator/Parsers$$anonfun$opt$2;
class	scala/util/parsing/combinator/Parsers$$anonfun$opt$2
Method	scala/util/parsing/combinator/Parsers$$anonfun$opt$2."<init>":(Lscala/util/parsing/combinator/Parsers;)V
Asciz	not;
Asciz	scala/util/parsing/combinator/Parsers$$anonfun$not$1;
class	scala/util/parsing/combinator/Parsers$$anonfun$not$1
Method	scala/util/parsing/combinator/Parsers$$anonfun$not$1."<init>":(Lscala/util/parsing/combinator/Parsers;Lscala/Function0;)V
Asciz	p$16;
Asciz	guard;
Asciz	scala/util/parsing/combinator/Parsers$$anonfun$guard$1;
class	scala/util/parsing/combinator/Parsers$$anonfun$guard$1
Method	scala/util/parsing/combinator/Parsers$$anonfun$guard$1."<init>":(Lscala/util/parsing/combinator/Parsers;Lscala/Function0;)V
Asciz	p$17;
Asciz	positioned;
Asciz	scala/util/parsing/combinator/Parsers$$anonfun$positioned$1;
class	scala/util/parsing/combinator/Parsers$$anonfun$positioned$1
Method	scala/util/parsing/combinator/Parsers$$anonfun$positioned$1."<init>":(Lscala/util/parsing/combinator/Parsers;Lscala/Function0;)V
Asciz	p$18;
Asciz	phrase;
Asciz	(Lscala/util/parsing/combinator/Parsers;Lscala/util/parsing/combinator/Parsers$Parser;)Lscala/util/parsing/combinator/Parsers$Parser;;
Asciz	scala/util/parsing/combinator/Parsers$$anon$2;
class	scala/util/parsing/combinator/Parsers$$anon$2
Asciz	(Lscala/util/parsing/combinator/Parsers;Lscala/util/parsing/combinator/Parsers$Parser;)V;
NameAndType	"<init>":(Lscala/util/parsing/combinator/Parsers;Lscala/util/parsing/combinator/Parsers$Parser;)V
Method	scala/util/parsing/combinator/Parsers$$anon$2."<init>":(Lscala/util/parsing/combinator/Parsers;Lscala/util/parsing/combinator/Parsers$Parser;)V
Asciz	p$1;
Asciz	Lscala/util/parsing/combinator/Parsers$Parser;;
Asciz	mkList;
Asciz	(Lscala/util/parsing/combinator/Parsers;)Lscala/Function1;;
Asciz	scala/util/parsing/combinator/Parsers$$anonfun$mkList$1;
class	scala/util/parsing/combinator/Parsers$$anonfun$mkList$1
Method	scala/util/parsing/combinator/Parsers$$anonfun$mkList$1."<init>":(Lscala/util/parsing/combinator/Parsers;)V
Asciz	$init$;
Asciz	lastNoSuccess_$eq;
Asciz	(Lscala/util/parsing/combinator/Parsers$NoSuccess;)V;
NameAndType	lastNoSuccess_$eq:(Lscala/util/parsing/combinator/Parsers$NoSuccess;)V
InterfaceMethod	scala/util/parsing/combinator/Parsers.lastNoSuccess_$eq:(Lscala/util/parsing/combinator/Parsers$NoSuccess;)V
Asciz	Scala;
Asciz	InnerClasses;
Asciz	$anon$2;
Asciz	Success;
Asciz	$anon$1;
Asciz	$anon$3;
Asciz	NoSuccess;
Asciz	scala/util/parsing/combinator/Parsers$OnceParser;
class	scala/util/parsing/combinator/Parsers$OnceParser
Asciz	ParseResult;
Asciz	$anonfun$not$1;
Asciz	$anonfun$opt$2;
Asciz	$anonfun$opt$1;
Asciz	$anonfun$rep$1;
Asciz	$anonfun$log$1;
Asciz	$anonfun$err$1;
Asciz	$anonfun$repN$1;
Asciz	$anonfun$rep1$1;
Asciz	$anonfun$elem$1;
Asciz	$anonfun$guard$1;
Asciz	$anonfun$mkList$1;
Asciz	$anonfun$repsep$1;
Asciz	$anonfun$accept$2;
Asciz	$anonfun$accept$1;
Asciz	$anonfun$commit$1;
Asciz	$anonfun$chainr1$2;
Asciz	$anonfun$chainr1$1;
Asciz	$anonfun$chainl1$2;
Asciz	$anonfun$chainl1$1;
Asciz	$anonfun$rep1sep$2;
Asciz	$anonfun$rep1sep$1;
Asciz	$anonfun$success$1;
Asciz	$anonfun$failure$1;
Asciz	$anonfun$acceptIf$1;
Asciz	$anonfun$acceptSeq$1;
Asciz	$anonfun$positioned$1;
Asciz	$anonfun$acceptMatch$1;
Asciz	scala/util/parsing/combinator/Parsers$class;
class	scala/util/parsing/combinator/Parsers$class
Asciz	java/lang/Object;
class	java/lang/Object

{
public static scala.util.parsing.combinator.Parsers$Parser Parser(scala.util.parsing.combinator.Parsers, scala.Function1);
  Signature: (Lscala/util/parsing/combinator/Parsers;Lscala/Function1;)Lscala/util/parsing/combinator/Parsers$Parser;
  Code:
   Stack=4, Locals=2, Args_size=2
	new	class scala/util/parsing/combinator/Parsers$$anon$3
	dup
	aload_0
	aload_1
	invokespecial	Method scala/util/parsing/combinator/Parsers$$anon$3."<init>":(Lscala/util/parsing/combinator/Parsers;Lscala/Function1;)V
	areturn
  Labels:
  LocalVariableTable: 
   Start  Length  Slot  Name   Signature
   0      10      0    $this       Lscala/util/parsing/combinator/Parsers;
   0      10      1    f$1       Lscala/Function1;


public static scala.util.parsing.combinator.Parsers$OnceParser OnceParser(scala.util.parsing.combinator.Parsers, scala.Function1);
  Signature: (Lscala/util/parsing/combinator/Parsers;Lscala/Function1;)Lscala/util/parsing/combinator/Parsers$OnceParser;
  Code:
   Stack=4, Locals=2, Args_size=2
	new	class scala/util/parsing/combinator/Parsers$$anon$1
	dup
	aload_0
	aload_1
	invokespecial	Method scala/util/parsing/combinator/Parsers$$anon$1."<init>":(Lscala/util/parsing/combinator/Parsers;Lscala/Function1;)V
	areturn
  Labels:
  LocalVariableTable: 
   Start  Length  Slot  Name   Signature
   0      10      0    $this       Lscala/util/parsing/combinator/Parsers;
   0      10      1    f$2       Lscala/Function1;


private static scala.util.parsing.combinator.Parsers$ParseResult seq(scala.util.parsing.combinator.Parsers, scala.Function0, scala.Function0, scala.Function2, scala.util.parsing.input.Reader);
  Signature: (Lscala/util/parsing/combinator/Parsers;Lscala/Function0;Lscala/Function0;Lscala/Function2;Lscala/util/parsing/input/Reader;)Lscala/util/parsing/combinator/Parsers$ParseResult;
  Code:
   Stack=6, Locals=10, Args_size=5
	aload_1
	invokeinterface	InterfaceMethod scala/Function0.apply:()Ljava/lang/Object;
	checkcast	class scala/Function1
	aload	4
	invokeinterface	InterfaceMethod scala/Function1.apply:(Ljava/lang/Object;)Ljava/lang/Object;
	checkcast	class scala/util/parsing/combinator/Parsers$ParseResult
	astore	9
	aload	9
	instanceof	class scala/util/parsing/combinator/Parsers$Success
	ifeq	l1 // aload
	aload	9
	checkcast	class scala/util/parsing/combinator/Parsers$Success
	astore	6
	aload	6
	invokevirtual	Method scala/util/parsing/combinator/Parsers$Success.next:()Lscala/util/parsing/input/Reader;
	astore	5
	aload_2
	invokeinterface	InterfaceMethod scala/Function0.apply:()Ljava/lang/Object;
	checkcast	class scala/Function1
	aload	5
	invokeinterface	InterfaceMethod scala/Function1.apply:(Ljava/lang/Object;)Ljava/lang/Object;
	checkcast	class scala/util/parsing/combinator/Parsers$ParseResult
	astore	8
	aload	8
	instanceof	class scala/util/parsing/combinator/Parsers$Success
	ifeq	l2 // aload
	aload	8
	checkcast	class scala/util/parsing/combinator/Parsers$Success
	astore	7
	new	class scala/util/parsing/combinator/Parsers$Success
	dup
	aload_0
	aload_3
	aload	6
	invokevirtual	Method scala/util/parsing/combinator/Parsers$Success.result:()Ljava/lang/Object;
	aload	7
	invokevirtual	Method scala/util/parsing/combinator/Parsers$Success.result:()Ljava/lang/Object;
	invokeinterface	InterfaceMethod scala/Function2.apply:(Ljava/lang/Object;Ljava/lang/Object;)Ljava/lang/Object;
	aload	7
	invokevirtual	Method scala/util/parsing/combinator/Parsers$Success.next:()Lscala/util/parsing/input/Reader;
	invokespecial	Method scala/util/parsing/combinator/Parsers$Success."<init>":(Lscala/util/parsing/combinator/Parsers;Ljava/lang/Object;Lscala/util/parsing/input/Reader;)V
	goto	l3 // areturn
l2	aload	8
	instanceof	class scala/util/parsing/combinator/Parsers$NoSuccess
	ifeq	l4 // new
	aload	8
	checkcast	class scala/util/parsing/combinator/Parsers$NoSuccess
	goto	l3 // areturn
l4	new	class scala/MatchError
	dup
	aload	8
	invokespecial	Method scala/MatchError."<init>":(Ljava/lang/Object;)V
	athrow
l1	aload	9
	instanceof	class scala/util/parsing/combinator/Parsers$NoSuccess
	ifeq	l5 // new
	aload	9
	checkcast	class scala/util/parsing/combinator/Parsers$NoSuccess
l3	areturn
l5	new	class scala/MatchError
	dup
	aload	9
	invokespecial	Method scala/MatchError."<init>":(Ljava/lang/Object;)V
	athrow
  Labels:
   	l2 = 111 // aload
   	l4 = 127 // new
   	l1 = 137 // aload
   	l3 = 150 // areturn
   	l5 = 151 // new
  LocalVariableTable: 
   Start  Length  Slot  Name   Signature
   0      161      0    $this       Lscala/util/parsing/combinator/Parsers;
   0      161      1    p       Lscala/Function0;
   0      161      2    q       Lscala/Function0;
   0      161      3    compose       Lscala/Function2;
   0      161      4    in       Lscala/util/parsing/input/Reader;
   43      94      5    temp55       Lscala/util/parsing/input/Reader;
   36      101      6    temp53       Lscala/util/parsing/combinator/Parsers$Success;
   79      29      7    temp48       Lscala/util/parsing/combinator/Parsers$Success;
   64      73      8    temp47       Lscala/util/parsing/combinator/Parsers$ParseResult;
   21      140      9    temp52       Lscala/util/parsing/combinator/Parsers$ParseResult;


public static scala.util.parsing.combinator.Parsers$Parser commit(scala.util.parsing.combinator.Parsers, scala.Function0);
  Signature: (Lscala/util/parsing/combinator/Parsers;Lscala/Function0;)Lscala/util/parsing/combinator/Parsers$Parser;
  Code:
   Stack=5, Locals=2, Args_size=2
	aload_0
	new	class scala/util/parsing/combinator/Parsers$$anonfun$commit$1
	dup
	aload_0
	aload_1
	invokespecial	Method scala/util/parsing/combinator/Parsers$$anonfun$commit$1."<init>":(Lscala/util/parsing/combinator/Parsers;Lscala/Function0;)V
	invokeinterface	InterfaceMethod scala/util/parsing/combinator/Parsers.Parser:(Lscala/Function1;)Lscala/util/parsing/combinator/Parsers$Parser;
	areturn
  Labels:
  LocalVariableTable: 
   Start  Length  Slot  Name   Signature
   0      16      0    $this       Lscala/util/parsing/combinator/Parsers;
   0      16      1    p$8       Lscala/Function0;


public static scala.util.parsing.combinator.Parsers$Parser elem(scala.util.parsing.combinator.Parsers, java.lang.String, scala.Function1);
  Signature: (Lscala/util/parsing/combinator/Parsers;Ljava/lang/String;Lscala/Function1;)Lscala/util/parsing/combinator/Parsers$Parser;
  Code:
   Stack=6, Locals=3, Args_size=3
	aload_0
	aload_2
	new	class scala/util/parsing/combinator/Parsers$$anonfun$elem$1
	dup
	aload_0
	aload_1
	invokespecial	Method scala/util/parsing/combinator/Parsers$$anonfun$elem$1."<init>":(Lscala/util/parsing/combinator/Parsers;Ljava/lang/String;)V
	invokeinterface	InterfaceMethod scala/util/parsing/combinator/Parsers.acceptIf:(Lscala/Function1;Lscala/Function1;)Lscala/util/parsing/combinator/Parsers$Parser;
	areturn
  Labels:
  LocalVariableTable: 
   Start  Length  Slot  Name   Signature
   0      17      0    $this       Lscala/util/parsing/combinator/Parsers;
   0      17      1    kind$1       Ljava/lang/String;
   0      17      2    p       Lscala/Function1;


public static scala.util.parsing.combinator.Parsers$Parser elem(scala.util.parsing.combinator.Parsers, java.lang.Object);
  Signature: (Lscala/util/parsing/combinator/Parsers;Ljava/lang/Object;)Lscala/util/parsing/combinator/Parsers$Parser;
  Code:
   Stack=2, Locals=2, Args_size=2
	aload_0
	aload_1
	invokeinterface	InterfaceMethod scala/util/parsing/combinator/Parsers.accept:(Ljava/lang/Object;)Lscala/util/parsing/combinator/Parsers$Parser;
	areturn
  Labels:
  LocalVariableTable: 
   Start  Length  Slot  Name   Signature
   0      8      0    $this       Lscala/util/parsing/combinator/Parsers;
   0      8      1    e       Ljava/lang/Object;


public static scala.util.parsing.combinator.Parsers$Parser accept(scala.util.parsing.combinator.Parsers, java.lang.Object);
  Signature: (Lscala/util/parsing/combinator/Parsers;Ljava/lang/Object;)Lscala/util/parsing/combinator/Parsers$Parser;
  Code:
   Stack=6, Locals=2, Args_size=2
	aload_0
	new	class scala/util/parsing/combinator/Parsers$$anonfun$accept$1
	dup
	aload_0
	aload_1
	invokespecial	Method scala/util/parsing/combinator/Parsers$$anonfun$accept$1."<init>":(Lscala/util/parsing/combinator/Parsers;Ljava/lang/Object;)V
	new	class scala/util/parsing/combinator/Parsers$$anonfun$accept$2
	dup
	aload_0
	aload_1
	invokespecial	Method scala/util/parsing/combinator/Parsers$$anonfun$accept$2."<init>":(Lscala/util/parsing/combinator/Parsers;Ljava/lang/Object;)V
	invokeinterface	InterfaceMethod scala/util/parsing/combinator/Parsers.acceptIf:(Lscala/Function1;Lscala/Function1;)Lscala/util/parsing/combinator/Parsers$Parser;
	areturn
  Labels:
  LocalVariableTable: 
   Start  Length  Slot  Name   Signature
   0      25      0    $this       Lscala/util/parsing/combinator/Parsers;
   0      25      1    e$1       Ljava/lang/Object;


public static scala.util.parsing.combinator.Parsers$Parser accept(scala.util.parsing.combinator.Parsers, java.lang.Object, scala.Function1);
  Signature: (Lscala/util/parsing/combinator/Parsers;Ljava/lang/Object;Lscala/Function1;)Lscala/util/parsing/combinator/Parsers$Parser;
  Code:
   Stack=3, Locals=3, Args_size=3
	aload_0
	aload_1
	aload_2
	invokeinterface	InterfaceMethod scala/util/parsing/combinator/Parsers.acceptSeq:(Ljava/lang/Object;Lscala/Function1;)Lscala/util/parsing/combinator/Parsers$Parser;
	areturn
  Labels:
  LocalVariableTable: 
   Start  Length  Slot  Name   Signature
   0      9      0    $this       Lscala/util/parsing/combinator/Parsers;
   0      9      1    es       Ljava/lang/Object;
   0      9      2    evidence$1       Lscala/Function1;


public static scala.util.parsing.combinator.Parsers$Parser accept(scala.util.parsing.combinator.Parsers, java.lang.String, scala.PartialFunction);
  Signature: (Lscala/util/parsing/combinator/Parsers;Ljava/lang/String;Lscala/PartialFunction;)Lscala/util/parsing/combinator/Parsers$Parser;
  Code:
   Stack=3, Locals=3, Args_size=3
	aload_0
	aload_1
	aload_2
	invokeinterface	InterfaceMethod scala/util/parsing/combinator/Parsers.acceptMatch:(Ljava/lang/String;Lscala/PartialFunction;)Lscala/util/parsing/combinator/Parsers$Parser;
	areturn
  Labels:
  LocalVariableTable: 
   Start  Length  Slot  Name   Signature
   0      9      0    $this       Lscala/util/parsing/combinator/Parsers;
   0      9      1    expected       Ljava/lang/String;
   0      9      2    f       Lscala/PartialFunction;


public static scala.util.parsing.combinator.Parsers$Parser acceptIf(scala.util.parsing.combinator.Parsers, scala.Function1, scala.Function1);
  Signature: (Lscala/util/parsing/combinator/Parsers;Lscala/Function1;Lscala/Function1;)Lscala/util/parsing/combinator/Parsers$Parser;
  Code:
   Stack=6, Locals=3, Args_size=3
	aload_0
	new	class scala/util/parsing/combinator/Parsers$$anonfun$acceptIf$1
	dup
	aload_0
	aload_1
	aload_2
	invokespecial	Method scala/util/parsing/combinator/Parsers$$anonfun$acceptIf$1."<init>":(Lscala/util/parsing/combinator/Parsers;Lscala/Function1;Lscala/Function1;)V
	invokeinterface	InterfaceMethod scala/util/parsing/combinator/Parsers.Parser:(Lscala/Function1;)Lscala/util/parsing/combinator/Parsers$Parser;
	areturn
  Labels:
  LocalVariableTable: 
   Start  Length  Slot  Name   Signature
   0      17      0    $this       Lscala/util/parsing/combinator/Parsers;
   0      17      1    p$11       Lscala/Function1;
   0      17      2    err$1       Lscala/Function1;


public static scala.util.parsing.combinator.Parsers$Parser acceptMatch(scala.util.parsing.combinator.Parsers, java.lang.String, scala.PartialFunction);
  Signature: (Lscala/util/parsing/combinator/Parsers;Ljava/lang/String;Lscala/PartialFunction;)Lscala/util/parsing/combinator/Parsers$Parser;
  Code:
   Stack=6, Locals=3, Args_size=3
	aload_0
	new	class scala/util/parsing/combinator/Parsers$$anonfun$acceptMatch$1
	dup
	aload_0
	aload_1
	aload_2
	invokespecial	Method scala/util/parsing/combinator/Parsers$$anonfun$acceptMatch$1."<init>":(Lscala/util/parsing/combinator/Parsers;Ljava/lang/String;Lscala/PartialFunction;)V
	invokeinterface	InterfaceMethod scala/util/parsing/combinator/Parsers.Parser:(Lscala/Function1;)Lscala/util/parsing/combinator/Parsers$Parser;
	areturn
  Labels:
  LocalVariableTable: 
   Start  Length  Slot  Name   Signature
   0      17      0    $this       Lscala/util/parsing/combinator/Parsers;
   0      17      1    expected$1       Ljava/lang/String;
   0      17      2    f$6       Lscala/PartialFunction;


public static scala.util.parsing.combinator.Parsers$Parser acceptSeq(scala.util.parsing.combinator.Parsers, java.lang.Object, scala.Function1);
  Signature: (Lscala/util/parsing/combinator/Parsers;Ljava/lang/Object;Lscala/Function1;)Lscala/util/parsing/combinator/Parsers$Parser;
  Code:
   Stack=5, Locals=3, Args_size=3
	aload_2
	aload_1
	invokeinterface	InterfaceMethod scala/Function1.apply:(Ljava/lang/Object;)Ljava/lang/Object;
	checkcast	class scala/collection/IterableLike
	aload_0
	getstatic	Field scala/collection/immutable/Nil$.MODULE$:Lscala/collection/immutable/Nil$;
	invokeinterface	InterfaceMethod scala/util/parsing/combinator/Parsers.success:(Ljava/lang/Object;)Lscala/util/parsing/combinator/Parsers$Parser;
	new	class scala/util/parsing/combinator/Parsers$$anonfun$acceptSeq$1
	dup
	aload_0
	invokespecial	Method scala/util/parsing/combinator/Parsers$$anonfun$acceptSeq$1."<init>":(Lscala/util/parsing/combinator/Parsers;)V
	invokeinterface	InterfaceMethod scala/collection/IterableLike.foldRight:(Ljava/lang/Object;Lscala/Function2;)Ljava/lang/Object;
	checkcast	class scala/util/parsing/combinator/Parsers$Parser
	areturn
  Labels:
  LocalVariableTable: 
   Start  Length  Slot  Name   Signature
   0      36      0    $this       Lscala/util/parsing/combinator/Parsers;
   0      36      1    es       Ljava/lang/Object;
   0      36      2    evidence$2       Lscala/Function1;


public static scala.util.parsing.combinator.Parsers$Parser failure(scala.util.parsing.combinator.Parsers, java.lang.String);
  Signature: (Lscala/util/parsing/combinator/Parsers;Ljava/lang/String;)Lscala/util/parsing/combinator/Parsers$Parser;
  Code:
   Stack=5, Locals=2, Args_size=2
	aload_0
	new	class scala/util/parsing/combinator/Parsers$$anonfun$failure$1
	dup
	aload_0
	aload_1
	invokespecial	Method scala/util/parsing/combinator/Parsers$$anonfun$failure$1."<init>":(Lscala/util/parsing/combinator/Parsers;Ljava/lang/String;)V
	invokeinterface	InterfaceMethod scala/util/parsing/combinator/Parsers.Parser:(Lscala/Function1;)Lscala/util/parsing/combinator/Parsers$Parser;
	areturn
  Labels:
  LocalVariableTable: 
   Start  Length  Slot  Name   Signature
   0      16      0    $this       Lscala/util/parsing/combinator/Parsers;
   0      16      1    msg$3       Ljava/lang/String;


public static scala.util.parsing.combinator.Parsers$Parser err(scala.util.parsing.combinator.Parsers, java.lang.String);
  Signature: (Lscala/util/parsing/combinator/Parsers;Ljava/lang/String;)Lscala/util/parsing/combinator/Parsers$Parser;
  Code:
   Stack=5, Locals=2, Args_size=2
	aload_0
	new	class scala/util/parsing/combinator/Parsers$$anonfun$err$1
	dup
	aload_0
	aload_1
	invokespecial	Method scala/util/parsing/combinator/Parsers$$anonfun$err$1."<init>":(Lscala/util/parsing/combinator/Parsers;Ljava/lang/String;)V
	invokeinterface	InterfaceMethod scala/util/parsing/combinator/Parsers.Parser:(Lscala/Function1;)Lscala/util/parsing/combinator/Parsers$Parser;
	areturn
  Labels:
  LocalVariableTable: 
   Start  Length  Slot  Name   Signature
   0      16      0    $this       Lscala/util/parsing/combinator/Parsers;
   0      16      1    msg$4       Ljava/lang/String;


public static scala.util.parsing.combinator.Parsers$Parser success(scala.util.parsing.combinator.Parsers, java.lang.Object);
  Signature: (Lscala/util/parsing/combinator/Parsers;Ljava/lang/Object;)Lscala/util/parsing/combinator/Parsers$Parser;
  Code:
   Stack=5, Locals=2, Args_size=2
	aload_0
	new	class scala/util/parsing/combinator/Parsers$$anonfun$success$1
	dup
	aload_0
	aload_1
	invokespecial	Method scala/util/parsing/combinator/Parsers$$anonfun$success$1."<init>":(Lscala/util/parsing/combinator/Parsers;Ljava/lang/Object;)V
	invokeinterface	InterfaceMethod scala/util/parsing/combinator/Parsers.Parser:(Lscala/Function1;)Lscala/util/parsing/combinator/Parsers$Parser;
	areturn
  Labels:
  LocalVariableTable: 
   Start  Length  Slot  Name   Signature
   0      16      0    $this       Lscala/util/parsing/combinator/Parsers;
   0      16      1    v$1       Ljava/lang/Object;


public static scala.util.parsing.combinator.Parsers$Parser log(scala.util.parsing.combinator.Parsers, scala.Function0, java.lang.String);
  Signature: (Lscala/util/parsing/combinator/Parsers;Lscala/Function0;Ljava/lang/String;)Lscala/util/parsing/combinator/Parsers$Parser;
  Code:
   Stack=6, Locals=3, Args_size=3
	aload_0
	new	class scala/util/parsing/combinator/Parsers$$anonfun$log$1
	dup
	aload_0
	aload_1
	aload_2
	invokespecial	Method scala/util/parsing/combinator/Parsers$$anonfun$log$1."<init>":(Lscala/util/parsing/combinator/Parsers;Lscala/Function0;Ljava/lang/String;)V
	invokeinterface	InterfaceMethod scala/util/parsing/combinator/Parsers.Parser:(Lscala/Function1;)Lscala/util/parsing/combinator/Parsers$Parser;
	areturn
  Labels:
  LocalVariableTable: 
   Start  Length  Slot  Name   Signature
   0      17      0    $this       Lscala/util/parsing/combinator/Parsers;
   0      17      1    p$12       Lscala/Function0;
   0      17      2    name$1       Ljava/lang/String;


public static scala.util.parsing.combinator.Parsers$Parser rep(scala.util.parsing.combinator.Parsers, scala.Function0);
  Signature: (Lscala/util/parsing/combinator/Parsers;Lscala/Function0;)Lscala/util/parsing/combinator/Parsers$Parser;
  Code:
   Stack=4, Locals=2, Args_size=2
	aload_0
	aload_1
	invokeinterface	InterfaceMethod scala/util/parsing/combinator/Parsers.rep1:(Lscala/Function0;)Lscala/util/parsing/combinator/Parsers$Parser;
	new	class scala/util/parsing/combinator/Parsers$$anonfun$rep$1
	dup
	aload_0
	invokespecial	Method scala/util/parsing/combinator/Parsers$$anonfun$rep$1."<init>":(Lscala/util/parsing/combinator/Parsers;)V
	invokevirtual	Method scala/util/parsing/combinator/Parsers$Parser.$bar:(Lscala/Function0;)Lscala/util/parsing/combinator/Parsers$Parser;
	areturn
  Labels:
  LocalVariableTable: 
   Start  Length  Slot  Name   Signature
   0      19      0    $this       Lscala/util/parsing/combinator/Parsers;
   0      19      1    p       Lscala/Function0;


public static scala.util.parsing.combinator.Parsers$Parser repsep(scala.util.parsing.combinator.Parsers, scala.Function0, scala.Function0);
  Signature: (Lscala/util/parsing/combinator/Parsers;Lscala/Function0;Lscala/Function0;)Lscala/util/parsing/combinator/Parsers$Parser;
  Code:
   Stack=4, Locals=3, Args_size=3
	aload_0
	aload_1
	aload_2
	invokeinterface	InterfaceMethod scala/util/parsing/combinator/Parsers.rep1sep:(Lscala/Function0;Lscala/Function0;)Lscala/util/parsing/combinator/Parsers$Parser;
	new	class scala/util/parsing/combinator/Parsers$$anonfun$repsep$1
	dup
	aload_0
	invokespecial	Method scala/util/parsing/combinator/Parsers$$anonfun$repsep$1."<init>":(Lscala/util/parsing/combinator/Parsers;)V
	invokevirtual	Method scala/util/parsing/combinator/Parsers$Parser.$bar:(Lscala/Function0;)Lscala/util/parsing/combinator/Parsers$Parser;
	areturn
  Labels:
  LocalVariableTable: 
   Start  Length  Slot  Name   Signature
   0      20      0    $this       Lscala/util/parsing/combinator/Parsers;
   0      20      1    p       Lscala/Function0;
   0      20      2    q       Lscala/Function0;


public static scala.util.parsing.combinator.Parsers$Parser rep1(scala.util.parsing.combinator.Parsers, scala.Function0);
  Signature: (Lscala/util/parsing/combinator/Parsers;Lscala/Function0;)Lscala/util/parsing/combinator/Parsers$Parser;
  Code:
   Stack=3, Locals=2, Args_size=2
	aload_0
	aload_1
	aload_1
	invokeinterface	InterfaceMethod scala/util/parsing/combinator/Parsers.rep1:(Lscala/Function0;Lscala/Function0;)Lscala/util/parsing/combinator/Parsers$Parser;
	areturn
  Labels:
  LocalVariableTable: 
   Start  Length  Slot  Name   Signature
   0      9      0    $this       Lscala/util/parsing/combinator/Parsers;
   0      9      1    p       Lscala/Function0;


public static scala.util.parsing.combinator.Parsers$Parser rep1(scala.util.parsing.combinator.Parsers, scala.Function0, scala.Function0);
  Signature: (Lscala/util/parsing/combinator/Parsers;Lscala/Function0;Lscala/Function0;)Lscala/util/parsing/combinator/Parsers$Parser;
  Code:
   Stack=6, Locals=3, Args_size=3
	aload_0
	new	class scala/util/parsing/combinator/Parsers$$anonfun$rep1$1
	dup
	aload_0
	aload_1
	aload_2
	invokespecial	Method scala/util/parsing/combinator/Parsers$$anonfun$rep1$1."<init>":(Lscala/util/parsing/combinator/Parsers;Lscala/Function0;Lscala/Function0;)V
	invokeinterface	InterfaceMethod scala/util/parsing/combinator/Parsers.Parser:(Lscala/Function1;)Lscala/util/parsing/combinator/Parsers$Parser;
	areturn
  Labels:
  LocalVariableTable: 
   Start  Length  Slot  Name   Signature
   0      17      0    $this       Lscala/util/parsing/combinator/Parsers;
   0      17      1    first$1       Lscala/Function0;
   0      17      2    p$10       Lscala/Function0;


public static scala.util.parsing.combinator.Parsers$Parser repN(scala.util.parsing.combinator.Parsers, int, scala.Function0);
  Signature: (Lscala/util/parsing/combinator/Parsers;ILscala/Function0;)Lscala/util/parsing/combinator/Parsers$Parser;
  Code:
   Stack=6, Locals=3, Args_size=3
	iload_1
	iconst_0
	if_icmpne	l1 // aload_0
	aload_0
	getstatic	Field scala/collection/immutable/Nil$.MODULE$:Lscala/collection/immutable/Nil$;
	invokeinterface	InterfaceMethod scala/util/parsing/combinator/Parsers.success:(Ljava/lang/Object;)Lscala/util/parsing/combinator/Parsers$Parser;
	goto	l2 // areturn
l1	aload_0
	new	class scala/util/parsing/combinator/Parsers$$anonfun$repN$1
	dup
	aload_0
	iload_1
	aload_2
	invokespecial	Method scala/util/parsing/combinator/Parsers$$anonfun$repN$1."<init>":(Lscala/util/parsing/combinator/Parsers;ILscala/Function0;)V
	invokeinterface	InterfaceMethod scala/util/parsing/combinator/Parsers.Parser:(Lscala/Function1;)Lscala/util/parsing/combinator/Parsers$Parser;
l2	areturn
  Labels:
   	l1 = 17 // aload_0
   	l2 = 33 // areturn
  LocalVariableTable: 
   Start  Length  Slot  Name   Signature
   0      34      0    $this       Lscala/util/parsing/combinator/Parsers;
   0      34      1    num$1       I
   0      34      2    p$14       Lscala/Function0;


public static scala.util.parsing.combinator.Parsers$Parser rep1sep(scala.util.parsing.combinator.Parsers, scala.Function0, scala.Function0);
  Signature: (Lscala/util/parsing/combinator/Parsers;Lscala/Function0;Lscala/Function0;)Lscala/util/parsing/combinator/Parsers$Parser;
  Code:
   Stack=6, Locals=3, Args_size=3
	aload_1
	invokeinterface	InterfaceMethod scala/Function0.apply:()Ljava/lang/Object;
	checkcast	class scala/util/parsing/combinator/Parsers$Parser
	new	class scala/util/parsing/combinator/Parsers$$anonfun$rep1sep$1
	dup
	aload_0
	aload_1
	aload_2
	invokespecial	Method scala/util/parsing/combinator/Parsers$$anonfun$rep1sep$1."<init>":(Lscala/util/parsing/combinator/Parsers;Lscala/Function0;Lscala/Function0;)V
	invokevirtual	Method scala/util/parsing/combinator/Parsers$Parser.$tilde:(Lscala/Function0;)Lscala/util/parsing/combinator/Parsers$Parser;
	new	class scala/util/parsing/combinator/Parsers$$anonfun$rep1sep$2
	dup
	aload_0
	invokespecial	Method scala/util/parsing/combinator/Parsers$$anonfun$rep1sep$2."<init>":(Lscala/util/parsing/combinator/Parsers;)V
	invokevirtual	Method scala/util/parsing/combinator/Parsers$Parser.$up$up:(Lscala/Function1;)Lscala/util/parsing/combinator/Parsers$Parser;
	areturn
  Labels:
  LocalVariableTable: 
   Start  Length  Slot  Name   Signature
   0      34      0    $this       Lscala/util/parsing/combinator/Parsers;
   0      34      1    p$13       Lscala/Function0;
   0      34      2    q$3       Lscala/Function0;


public static scala.util.parsing.combinator.Parsers$Parser chainl1(scala.util.parsing.combinator.Parsers, scala.Function0, scala.Function0);
  Signature: (Lscala/util/parsing/combinator/Parsers;Lscala/Function0;Lscala/Function0;)Lscala/util/parsing/combinator/Parsers$Parser;
  Code:
   Stack=4, Locals=3, Args_size=3
	aload_0
	aload_1
	aload_1
	aload_2
	invokeinterface	InterfaceMethod scala/util/parsing/combinator/Parsers.chainl1:(Lscala/Function0;Lscala/Function0;Lscala/Function0;)Lscala/util/parsing/combinator/Parsers$Parser;
	areturn
  Labels:
  LocalVariableTable: 
   Start  Length  Slot  Name   Signature
   0      10      0    $this       Lscala/util/parsing/combinator/Parsers;
   0      10      1    p       Lscala/Function0;
   0      10      2    q       Lscala/Function0;


public static scala.util.parsing.combinator.Parsers$Parser chainl1(scala.util.parsing.combinator.Parsers, scala.Function0, scala.Function0, scala.Function0);
  Signature: (Lscala/util/parsing/combinator/Parsers;Lscala/Function0;Lscala/Function0;Lscala/Function0;)Lscala/util/parsing/combinator/Parsers$Parser;
  Code:
   Stack=6, Locals=4, Args_size=4
	aload_1
	invokeinterface	InterfaceMethod scala/Function0.apply:()Ljava/lang/Object;
	checkcast	class scala/util/parsing/combinator/Parsers$Parser
	new	class scala/util/parsing/combinator/Parsers$$anonfun$chainl1$1
	dup
	aload_0
	aload_2
	aload_3
	invokespecial	Method scala/util/parsing/combinator/Parsers$$anonfun$chainl1$1."<init>":(Lscala/util/parsing/combinator/Parsers;Lscala/Function0;Lscala/Function0;)V
	invokevirtual	Method scala/util/parsing/combinator/Parsers$Parser.$tilde:(Lscala/Function0;)Lscala/util/parsing/combinator/Parsers$Parser;
	new	class scala/util/parsing/combinator/Parsers$$anonfun$chainl1$2
	dup
	aload_0
	invokespecial	Method scala/util/parsing/combinator/Parsers$$anonfun$chainl1$2."<init>":(Lscala/util/parsing/combinator/Parsers;)V
	invokevirtual	Method scala/util/parsing/combinator/Parsers$Parser.$up$up:(Lscala/Function1;)Lscala/util/parsing/combinator/Parsers$Parser;
	areturn
  Labels:
  LocalVariableTable: 
   Start  Length  Slot  Name   Signature
   0      34      0    $this       Lscala/util/parsing/combinator/Parsers;
   0      34      1    first       Lscala/Function0;
   0      34      2    p$9       Lscala/Function0;
   0      34      3    q$2       Lscala/Function0;


public static scala.util.parsing.combinator.Parsers$Parser chainr1(scala.util.parsing.combinator.Parsers, scala.Function0, scala.Function0, scala.Function2, java.lang.Object);
  Signature: (Lscala/util/parsing/combinator/Parsers;Lscala/Function0;Lscala/Function0;Lscala/Function2;Ljava/lang/Object;)Lscala/util/parsing/combinator/Parsers$Parser;
  Code:
   Stack=6, Locals=5, Args_size=5
	aload_1
	invokeinterface	InterfaceMethod scala/Function0.apply:()Ljava/lang/Object;
	checkcast	class scala/util/parsing/combinator/Parsers$Parser
	new	class scala/util/parsing/combinator/Parsers$$anonfun$chainr1$1
	dup
	aload_0
	aload_1
	aload_2
	invokespecial	Method scala/util/parsing/combinator/Parsers$$anonfun$chainr1$1."<init>":(Lscala/util/parsing/combinator/Parsers;Lscala/Function0;Lscala/Function0;)V
	invokevirtual	Method scala/util/parsing/combinator/Parsers$Parser.$tilde:(Lscala/Function0;)Lscala/util/parsing/combinator/Parsers$Parser;
	new	class scala/util/parsing/combinator/Parsers$$anonfun$chainr1$2
	dup
	aload_0
	aload_3
	aload	4
	invokespecial	Method scala/util/parsing/combinator/Parsers$$anonfun$chainr1$2."<init>":(Lscala/util/parsing/combinator/Parsers;Lscala/Function2;Ljava/lang/Object;)V
	invokevirtual	Method scala/util/parsing/combinator/Parsers$Parser.$up$up:(Lscala/Function1;)Lscala/util/parsing/combinator/Parsers$Parser;
	areturn
  Labels:
  LocalVariableTable: 
   Start  Length  Slot  Name   Signature
   0      37      0    $this       Lscala/util/parsing/combinator/Parsers;
   0      37      1    p$15       Lscala/Function0;
   0      37      2    q$4       Lscala/Function0;
   0      37      3    combine$1       Lscala/Function2;
   0      37      4    first$2       Ljava/lang/Object;


public static scala.util.parsing.combinator.Parsers$Parser opt(scala.util.parsing.combinator.Parsers, scala.Function0);
  Signature: (Lscala/util/parsing/combinator/Parsers;Lscala/Function0;)Lscala/util/parsing/combinator/Parsers$Parser;
  Code:
   Stack=4, Locals=2, Args_size=2
	aload_1
	invokeinterface	InterfaceMethod scala/Function0.apply:()Ljava/lang/Object;
	checkcast	class scala/util/parsing/combinator/Parsers$Parser
	new	class scala/util/parsing/combinator/Parsers$$anonfun$opt$1
	dup
	aload_0
	invokespecial	Method scala/util/parsing/combinator/Parsers$$anonfun$opt$1."<init>":(Lscala/util/parsing/combinator/Parsers;)V
	invokevirtual	Method scala/util/parsing/combinator/Parsers$Parser.$up$up:(Lscala/Function1;)Lscala/util/parsing/combinator/Parsers$Parser;
	new	class scala/util/parsing/combinator/Parsers$$anonfun$opt$2
	dup
	aload_0
	invokespecial	Method scala/util/parsing/combinator/Parsers$$anonfun$opt$2."<init>":(Lscala/util/parsing/combinator/Parsers;)V
	invokevirtual	Method scala/util/parsing/combinator/Parsers$Parser.$bar:(Lscala/Function0;)Lscala/util/parsing/combinator/Parsers$Parser;
	areturn
  Labels:
  LocalVariableTable: 
   Start  Length  Slot  Name   Signature
   0      32      0    $this       Lscala/util/parsing/combinator/Parsers;
   0      32      1    p       Lscala/Function0;


public static scala.util.parsing.combinator.Parsers$Parser not(scala.util.parsing.combinator.Parsers, scala.Function0);
  Signature: (Lscala/util/parsing/combinator/Parsers;Lscala/Function0;)Lscala/util/parsing/combinator/Parsers$Parser;
  Code:
   Stack=5, Locals=2, Args_size=2
	aload_0
	new	class scala/util/parsing/combinator/Parsers$$anonfun$not$1
	dup
	aload_0
	aload_1
	invokespecial	Method scala/util/parsing/combinator/Parsers$$anonfun$not$1."<init>":(Lscala/util/parsing/combinator/Parsers;Lscala/Function0;)V
	invokeinterface	InterfaceMethod scala/util/parsing/combinator/Parsers.Parser:(Lscala/Function1;)Lscala/util/parsing/combinator/Parsers$Parser;
	areturn
  Labels:
  LocalVariableTable: 
   Start  Length  Slot  Name   Signature
   0      16      0    $this       Lscala/util/parsing/combinator/Parsers;
   0      16      1    p$16       Lscala/Function0;


public static scala.util.parsing.combinator.Parsers$Parser guard(scala.util.parsing.combinator.Parsers, scala.Function0);
  Signature: (Lscala/util/parsing/combinator/Parsers;Lscala/Function0;)Lscala/util/parsing/combinator/Parsers$Parser;
  Code:
   Stack=5, Locals=2, Args_size=2
	aload_0
	new	class scala/util/parsing/combinator/Parsers$$anonfun$guard$1
	dup
	aload_0
	aload_1
	invokespecial	Method scala/util/parsing/combinator/Parsers$$anonfun$guard$1."<init>":(Lscala/util/parsing/combinator/Parsers;Lscala/Function0;)V
	invokeinterface	InterfaceMethod scala/util/parsing/combinator/Parsers.Parser:(Lscala/Function1;)Lscala/util/parsing/combinator/Parsers$Parser;
	areturn
  Labels:
  LocalVariableTable: 
   Start  Length  Slot  Name   Signature
   0      16      0    $this       Lscala/util/parsing/combinator/Parsers;
   0      16      1    p$17       Lscala/Function0;


public static scala.util.parsing.combinator.Parsers$Parser positioned(scala.util.parsing.combinator.Parsers, scala.Function0);
  Signature: (Lscala/util/parsing/combinator/Parsers;Lscala/Function0;)Lscala/util/parsing/combinator/Parsers$Parser;
  Code:
   Stack=5, Locals=2, Args_size=2
	aload_0
	new	class scala/util/parsing/combinator/Parsers$$anonfun$positioned$1
	dup
	aload_0
	aload_1
	invokespecial	Method scala/util/parsing/combinator/Parsers$$anonfun$positioned$1."<init>":(Lscala/util/parsing/combinator/Parsers;Lscala/Function0;)V
	invokeinterface	InterfaceMethod scala/util/parsing/combinator/Parsers.Parser:(Lscala/Function1;)Lscala/util/parsing/combinator/Parsers$Parser;
	areturn
  Labels:
  LocalVariableTable: 
   Start  Length  Slot  Name   Signature
   0      16      0    $this       Lscala/util/parsing/combinator/Parsers;
   0      16      1    p$18       Lscala/Function0;


public static scala.util.parsing.combinator.Parsers$Parser phrase(scala.util.parsing.combinator.Parsers, scala.util.parsing.combinator.Parsers$Parser);
  Signature: (Lscala/util/parsing/combinator/Parsers;Lscala/util/parsing/combinator/Parsers$Parser;)Lscala/util/parsing/combinator/Parsers$Parser;
  Code:
   Stack=4, Locals=2, Args_size=2
	new	class scala/util/parsing/combinator/Parsers$$anon$2
	dup
	aload_0
	aload_1
	invokespecial	Method scala/util/parsing/combinator/Parsers$$anon$2."<init>":(Lscala/util/parsing/combinator/Parsers;Lscala/util/parsing/combinator/Parsers$Parser;)V
	areturn
  Labels:
  LocalVariableTable: 
   Start  Length  Slot  Name   Signature
   0      10      0    $this       Lscala/util/parsing/combinator/Parsers;
   0      10      1    p$1       Lscala/util/parsing/combinator/Parsers$Parser;


public static scala.Function1 mkList(scala.util.parsing.combinator.Parsers);
  Signature: (Lscala/util/parsing/combinator/Parsers;)Lscala/Function1;
  Code:
   Stack=3, Locals=1, Args_size=1
	new	class scala/util/parsing/combinator/Parsers$$anonfun$mkList$1
	dup
	aload_0
	invokespecial	Method scala/util/parsing/combinator/Parsers$$anonfun$mkList$1."<init>":(Lscala/util/parsing/combinator/Parsers;)V
	areturn
  Labels:
  LocalVariableTable: 
   Start  Length  Slot  Name   Signature
   0      9      0    $this       Lscala/util/parsing/combinator/Parsers;


public static void $init$(scala.util.parsing.combinator.Parsers);
  Signature: (Lscala/util/parsing/combinator/Parsers;)V
  Code:
   Stack=2, Locals=1, Args_size=1
	aload_0
	aconst_null
	invokeinterface	InterfaceMethod scala/util/parsing/combinator/Parsers.lastNoSuccess_$eq:(Lscala/util/parsing/combinator/Parsers$NoSuccess;)V
	return
  Labels:
  LocalVariableTable: 
   Start  Length  Slot  Name   Signature
   0      8      0    $this       Lscala/util/parsing/combinator/Parsers;


}

