Compiled from "Parsers.scala"
public final class scala.util.parsing.combinator.Parsers$$anon$1 extends scala.util.parsing.combinator.Parsers$Parser implements scala.util.parsing.combinator.Parsers$OnceParser
  SourceFile: "Parsers.scala"
  Signature: length = 0x2
   00 40 
  Scala: length = 0x
   
  InnerClass: 
   public abstract Parser=class scala/util/parsing/combinator/Parsers$Parser of class scala/util/parsing/combinator/Parsers
   public final $anon$1=class scala/util/parsing/combinator/Parsers$$anon$1 of class scala/util/parsing/combinator/Parsers
   public abstract OnceParser=class scala/util/parsing/combinator/Parsers$OnceParser of class scala/util/parsing/combinator/Parsers
   public abstract ParseResult=class scala/util/parsing/combinator/Parsers$ParseResult of class scala/util/parsing/combinator/Parsers
  minor version: 0
  major version: 49
  Constant pool:
Asciz	SourceFile;
Asciz	Parsers.scala;
Asciz	f$2;
Asciz	Lscala/Function1;;
Asciz	$outer;
Asciz	Lscala/util/parsing/combinator/Parsers;;
Asciz	$tilde;
Asciz	(Lscala/Function0;)Lscala/util/parsing/combinator/Parsers$Parser;;
Asciz	Code;
Asciz	LineNumberTable;
Asciz	scala/util/parsing/combinator/Parsers$OnceParser$class;
class	scala/util/parsing/combinator/Parsers$OnceParser$class
Asciz	(Lscala/util/parsing/combinator/Parsers$OnceParser;Lscala/Function0;)Lscala/util/parsing/combinator/Parsers$Parser;;
NameAndType	$tilde:(Lscala/util/parsing/combinator/Parsers$OnceParser;Lscala/Function0;)Lscala/util/parsing/combinator/Parsers$Parser;
Method	scala/util/parsing/combinator/Parsers$OnceParser$class.$tilde:(Lscala/util/parsing/combinator/Parsers$OnceParser;Lscala/Function0;)Lscala/util/parsing/combinator/Parsers$Parser;
Asciz	this;
Asciz	Lscala/util/parsing/combinator/Parsers$$anon$1;;
Asciz	p;
Asciz	Lscala/Function0;;
Asciz	LocalVariableTable;
Asciz	apply;
Asciz	(Lscala/util/parsing/input/Reader;)Lscala/util/parsing/combinator/Parsers$ParseResult;;
Asciz	scala/util/parsing/combinator/Parsers$$anon$1;
class	scala/util/parsing/combinator/Parsers$$anon$1
NameAndType	f$2:Lscala/Function1;
Field	scala/util/parsing/combinator/Parsers$$anon$1.f$2:Lscala/Function1;
Asciz	scala/Function1;
class	scala/Function1
Asciz	(Ljava/lang/Object;)Ljava/lang/Object;;
NameAndType	apply:(Ljava/lang/Object;)Ljava/lang/Object;
InterfaceMethod	scala/Function1.apply:(Ljava/lang/Object;)Ljava/lang/Object;
Asciz	scala/util/parsing/combinator/Parsers$ParseResult;
class	scala/util/parsing/combinator/Parsers$ParseResult
Asciz	in;
Asciz	Lscala/util/parsing/input/Reader;;
Asciz	(Lscala/util/parsing/input/Reader<Ljava/lang/Object;>;)Lscala/util/parsing/combinator/Parsers$ParseResult<TT;>;;
Asciz	Signature;
Asciz	scala$util$parsing$combinator$Parsers$OnceParser$$$outer;
Asciz	()Lscala/util/parsing/combinator/Parsers;;
NameAndType	$outer:Lscala/util/parsing/combinator/Parsers;
Field	scala/util/parsing/combinator/Parsers$$anon$1.$outer:Lscala/util/parsing/combinator/Parsers;
Asciz	scala/util/parsing/input/Reader;
class	scala/util/parsing/input/Reader
NameAndType	apply:(Lscala/util/parsing/input/Reader;)Lscala/util/parsing/combinator/Parsers$ParseResult;
Method	scala/util/parsing/combinator/Parsers$$anon$1.apply:(Lscala/util/parsing/input/Reader;)Lscala/util/parsing/combinator/Parsers$ParseResult;
Asciz	v1;
Asciz	Ljava/lang/Object;;
Asciz	<init>;
Asciz	(Lscala/util/parsing/combinator/Parsers;Lscala/Function1;)V;
Asciz	java/lang/NullPointerException;
class	java/lang/NullPointerException
Asciz	()V;
NameAndType	"<init>":()V
Method	java/lang/NullPointerException."<init>":()V
Asciz	scala/util/parsing/combinator/Parsers$Parser;
class	scala/util/parsing/combinator/Parsers$Parser
Asciz	(Lscala/util/parsing/combinator/Parsers;)V;
NameAndType	"<init>":(Lscala/util/parsing/combinator/Parsers;)V
Method	scala/util/parsing/combinator/Parsers$Parser."<init>":(Lscala/util/parsing/combinator/Parsers;)V
Asciz	$init$;
Asciz	(Lscala/util/parsing/combinator/Parsers$OnceParser;)V;
NameAndType	$init$:(Lscala/util/parsing/combinator/Parsers$OnceParser;)V
Method	scala/util/parsing/combinator/Parsers$OnceParser$class.$init$:(Lscala/util/parsing/combinator/Parsers$OnceParser;)V
Asciz	Lscala/util/parsing/combinator/Parsers$Parser<TT;>;Lscala/util/parsing/combinator/Parsers$OnceParser<TT;>;;
Asciz	Scala;
Asciz	InnerClasses;
Asciz	scala/util/parsing/combinator/Parsers;
class	scala/util/parsing/combinator/Parsers
Asciz	Parser;
Asciz	$anon$1;
Asciz	scala/util/parsing/combinator/Parsers$OnceParser;
class	scala/util/parsing/combinator/Parsers$OnceParser
Asciz	OnceParser;
Asciz	ParseResult;

{
public final scala.Function1 f$2;
  Signature: Lscala/Function1;

private final scala.util.parsing.combinator.Parsers $outer;
  Signature: Lscala/util/parsing/combinator/Parsers;

public scala.util.parsing.combinator.Parsers$Parser $tilde(scala.Function0);
  Signature: (Lscala/Function0;)Lscala/util/parsing/combinator/Parsers$Parser;
  Code:
   Stack=2, Locals=2, Args_size=2
	aload_0
	aload_1
	invokestatic	Method scala/util/parsing/combinator/Parsers$OnceParser$class.$tilde:(Lscala/util/parsing/combinator/Parsers$OnceParser;Lscala/Function0;)Lscala/util/parsing/combinator/Parsers$Parser;
	areturn
  Labels:
  LocalVariableTable: 
   Start  Length  Slot  Name   Signature
   0      6      0    this       Lscala/util/parsing/combinator/Parsers$$anon$1;
   0      6      1    p       Lscala/Function0;


public scala.util.parsing.combinator.Parsers$ParseResult apply(scala.util.parsing.input.Reader);
  Signature: (Lscala/util/parsing/input/Reader;)Lscala/util/parsing/combinator/Parsers$ParseResult;
  Code:
   Stack=2, Locals=2, Args_size=2
	aload_0
	getfield	Field f$2:Lscala/Function1;
	aload_1
	invokeinterface	InterfaceMethod scala/Function1.apply:(Ljava/lang/Object;)Ljava/lang/Object;
	checkcast	class scala/util/parsing/combinator/Parsers$ParseResult
	areturn
  Labels:
  LocalVariableTable: 
   Start  Length  Slot  Name   Signature
   0      14      0    this       Lscala/util/parsing/combinator/Parsers$$anon$1;
   0      14      1    in       Lscala/util/parsing/input/Reader;

  Signature: length = 0x2
   00 24 

public scala.util.parsing.combinator.Parsers scala$util$parsing$combinator$Parsers$OnceParser$$$outer();
  Signature: ()Lscala/util/parsing/combinator/Parsers;
  Code:
   Stack=1, Locals=1, Args_size=1
	aload_0
	getfield	Field $outer:Lscala/util/parsing/combinator/Parsers;
	areturn
  Labels:

public java.lang.Object apply(java.lang.Object);
  Signature: (Ljava/lang/Object;)Ljava/lang/Object;
  Code:
   Stack=2, Locals=2, Args_size=2
	aload_0
	aload_1
	checkcast	class scala/util/parsing/input/Reader
	invokevirtual	Method apply:(Lscala/util/parsing/input/Reader;)Lscala/util/parsing/combinator/Parsers$ParseResult;
	areturn
  Labels:
  LocalVariableTable: 
   Start  Length  Slot  Name   Signature
   0      9      0    this       Lscala/util/parsing/combinator/Parsers$$anon$1;
   0      9      1    v1       Ljava/lang/Object;


public scala.util.parsing.combinator.Parsers$$anon$1(scala.util.parsing.combinator.Parsers, scala.Function1);
  Signature: (Lscala/util/parsing/combinator/Parsers;Lscala/Function1;)V
  Code:
   Stack=2, Locals=3, Args_size=3
	aload_1
	ifnonnull	l1 // aload_0
	new	class java/lang/NullPointerException
	dup
	invokespecial	Method java/lang/NullPointerException."<init>":()V
	athrow
l1	aload_0
	aload_1
	putfield	Field $outer:Lscala/util/parsing/combinator/Parsers;
	aload_0
	aload_2
	putfield	Field f$2:Lscala/Function1;
	aload_0
	aload_1
	invokespecial	Method scala/util/parsing/combinator/Parsers$Parser."<init>":(Lscala/util/parsing/combinator/Parsers;)V
	aload_0
	invokestatic	Method scala/util/parsing/combinator/Parsers$OnceParser$class.$init$:(Lscala/util/parsing/combinator/Parsers$OnceParser;)V
	return
  Labels:
   	l1 = 12 // aload_0
  LocalVariableTable: 
   Start  Length  Slot  Name   Signature
   0      32      0    this       Lscala/util/parsing/combinator/Parsers$$anon$1;
   0      32      1    $outer       Lscala/util/parsing/combinator/Parsers;


}

