Compiled from "Parsers.scala"
public final class scala.util.parsing.combinator.Parsers$$anonfun$chainr1$2$$anonfun$apply$11 extends scala.runtime.AbstractFunction2 implements java.io.Serializable
  SourceFile: "Parsers.scala"
  Scala: length = 0x
   
  InnerClass: 
   public $tilde=class scala/util/parsing/combinator/Parsers$$tilde of class scala/util/parsing/combinator/Parsers
   public final $anonfun$chainr1$2=class scala/util/parsing/combinator/Parsers$$anonfun$chainr1$2 of class scala/util/parsing/combinator/Parsers
   public final $anonfun$apply$11=class scala/util/parsing/combinator/Parsers$$anonfun$chainr1$2$$anonfun$apply$11 of class scala/util/parsing/combinator/Parsers$$anonfun$chainr1$2
  minor version: 0
  major version: 49
  Constant pool:
Asciz	SourceFile;
Asciz	Parsers.scala;
Asciz	<clinit>;
Asciz	()V;
Asciz	Code;
Asciz	serialVersionUID;
Asciz	J;
Asciz	scala/util/parsing/combinator/Parsers$$anonfun$chainr1$2$$anonfun$apply$11;
class	scala/util/parsing/combinator/Parsers$$anonfun$chainr1$2$$anonfun$apply$11
NameAndType	serialVersionUID:J
Field	scala/util/parsing/combinator/Parsers$$anonfun$chainr1$2$$anonfun$apply$11.serialVersionUID:J
Asciz	apply;
Asciz	(Lscala/util/parsing/combinator/Parsers$$tilde;Ljava/lang/Object;)Ljava/lang/Object;;
Asciz	LineNumberTable;
Asciz	scala/util/parsing/combinator/Parsers$$tilde;
class	scala/util/parsing/combinator/Parsers$$tilde
Asciz	_1;
Asciz	()Ljava/lang/Object;;
NameAndType	_1:()Ljava/lang/Object;
Method	scala/util/parsing/combinator/Parsers$$tilde._1:()Ljava/lang/Object;
Asciz	scala/Function2;
class	scala/Function2
Asciz	_2;
NameAndType	_2:()Ljava/lang/Object;
Method	scala/util/parsing/combinator/Parsers$$tilde._2:()Ljava/lang/Object;
Asciz	(Ljava/lang/Object;Ljava/lang/Object;)Ljava/lang/Object;;
NameAndType	apply:(Ljava/lang/Object;Ljava/lang/Object;)Ljava/lang/Object;
InterfaceMethod	scala/Function2.apply:(Ljava/lang/Object;Ljava/lang/Object;)Ljava/lang/Object;
Asciz	scala/MatchError;
class	scala/MatchError
Asciz	scala/Tuple2;
class	scala/Tuple2
Asciz	<init>;
Asciz	(Ljava/lang/Object;Ljava/lang/Object;)V;
NameAndType	"<init>":(Ljava/lang/Object;Ljava/lang/Object;)V
Method	scala/Tuple2."<init>":(Ljava/lang/Object;Ljava/lang/Object;)V
Asciz	toString;
Asciz	()Ljava/lang/String;;
NameAndType	toString:()Ljava/lang/String;
Method	scala/Tuple2.toString:()Ljava/lang/String;
Asciz	(Ljava/lang/String;)V;
NameAndType	"<init>":(Ljava/lang/String;)V
Method	scala/MatchError."<init>":(Ljava/lang/String;)V
Asciz	this;
Asciz	Lscala/util/parsing/combinator/Parsers$$anonfun$chainr1$2$$anonfun$apply$11;;
Asciz	temp89;
Asciz	Lscala/Function2;;
Asciz	temp90;
Asciz	Ljava/lang/Object;;
Asciz	LocalVariableTable;
Asciz	(Lscala/util/parsing/combinator/Parsers$$tilde<Lscala/Function2<TT;TU;TU;>;TT;>;TU;)TU;;
Asciz	Signature;
NameAndType	apply:(Lscala/util/parsing/combinator/Parsers$$tilde;Ljava/lang/Object;)Ljava/lang/Object;
Method	scala/util/parsing/combinator/Parsers$$anonfun$chainr1$2$$anonfun$apply$11.apply:(Lscala/util/parsing/combinator/Parsers$$tilde;Ljava/lang/Object;)Ljava/lang/Object;
Asciz	v1;
Asciz	v2;
Asciz	(Lscala/util/parsing/combinator/Parsers$$anonfun$chainr1$2;)V;
Asciz	scala/runtime/AbstractFunction2;
class	scala/runtime/AbstractFunction2
NameAndType	"<init>":()V
Method	scala/runtime/AbstractFunction2."<init>":()V
Asciz	$outer;
Asciz	Lscala/util/parsing/combinator/Parsers$$anonfun$chainr1$2;;
Asciz	Scala;
Asciz	InnerClasses;
Asciz	scala/util/parsing/combinator/Parsers;
class	scala/util/parsing/combinator/Parsers
Asciz	$tilde;
Asciz	scala/util/parsing/combinator/Parsers$$anonfun$chainr1$2;
class	scala/util/parsing/combinator/Parsers$$anonfun$chainr1$2
Asciz	$anonfun$chainr1$2;
Asciz	$anonfun$apply$11;
Asciz	java/io/Serializable;
class	java/io/Serializable

{
public static final long serialVersionUID;
  Signature: J

public static {};
  Signature: ()V
  Code:
   Stack=2, Locals=0, Args_size=0
	lconst_0
	putstatic	Field serialVersionUID:J
	return
  Labels:

public final java.lang.Object apply(scala.util.parsing.combinator.Parsers$$tilde, java.lang.Object);
  Signature: (Lscala/util/parsing/combinator/Parsers$$tilde;Ljava/lang/Object;)Ljava/lang/Object;
  Code:
   Stack=6, Locals=5, Args_size=3
	aload_1
	ifnull	l1 // new
	aload_1
	invokevirtual	Method scala/util/parsing/combinator/Parsers$$tilde._1:()Ljava/lang/Object;
	checkcast	class scala/Function2
	astore_3
	aload_1
	invokevirtual	Method scala/util/parsing/combinator/Parsers$$tilde._2:()Ljava/lang/Object;
	astore	4
	aload_3
	aload	4
	aload_2
	invokeinterface	InterfaceMethod scala/Function2.apply:(Ljava/lang/Object;Ljava/lang/Object;)Ljava/lang/Object;
	areturn
l1	new	class scala/MatchError
	dup
	new	class scala/Tuple2
	dup
	aload_1
	aload_2
	invokespecial	Method scala/Tuple2."<init>":(Ljava/lang/Object;Ljava/lang/Object;)V
	invokevirtual	Method scala/Tuple2.toString:()Ljava/lang/String;
	invokespecial	Method scala/MatchError."<init>":(Ljava/lang/String;)V
	athrow
  Labels:
   	l1 = 28 // new
  LocalVariableTable: 
   Start  Length  Slot  Name   Signature
   0      48      0    this       Lscala/util/parsing/combinator/Parsers$$anonfun$chainr1$2$$anonfun$apply$11;
   12      15      3    temp89       Lscala/Function2;
   18      9      4    temp90       Ljava/lang/Object;

  Signature: length = 0x2
   00 33 

public final java.lang.Object apply(java.lang.Object, java.lang.Object);
  Signature: (Ljava/lang/Object;Ljava/lang/Object;)Ljava/lang/Object;
  Code:
   Stack=3, Locals=3, Args_size=3
	aload_0
	aload_1
	checkcast	class scala/util/parsing/combinator/Parsers$$tilde
	aload_2
	invokevirtual	Method apply:(Lscala/util/parsing/combinator/Parsers$$tilde;Ljava/lang/Object;)Ljava/lang/Object;
	areturn
  Labels:
  LocalVariableTable: 
   Start  Length  Slot  Name   Signature
   0      10      0    this       Lscala/util/parsing/combinator/Parsers$$anonfun$chainr1$2$$anonfun$apply$11;
   0      10      1    v1       Ljava/lang/Object;
   0      10      2    v2       Ljava/lang/Object;


public scala.util.parsing.combinator.Parsers$$anonfun$chainr1$2$$anonfun$apply$11(scala.util.parsing.combinator.Parsers$$anonfun$chainr1$2);
  Signature: (Lscala/util/parsing/combinator/Parsers$$anonfun$chainr1$2;)V
  Code:
   Stack=1, Locals=2, Args_size=2
	aload_0
	invokespecial	Method scala/runtime/AbstractFunction2."<init>":()V
	return
  Labels:
  LocalVariableTable: 
   Start  Length  Slot  Name   Signature
   0      5      0    this       Lscala/util/parsing/combinator/Parsers$$anonfun$chainr1$2$$anonfun$apply$11;
   0      5      1    $outer       Lscala/util/parsing/combinator/Parsers$$anonfun$chainr1$2;


}

