Compiled from "Parsers.scala"
public final class scala.util.parsing.combinator.Parsers$$anon$1 extends scala.util.parsing.combinator.Parsers$Parser implements scala.util.parsing.combinator.Parsers$OnceParser
  SourceFile: "Parsers.scala"
  Signature: length = 0x2
   00 40 
  Scala: length = 0x
   
  InnerClass: 
   public abstract #69= #23 of #68; //Parser=class scala/util/parsing/combinator/Parsers$Parser of class scala/util/parsing/combinator/Parsers
   public final #70= #17 of #68; //$anon$1=class scala/util/parsing/combinator/Parsers$$anon$1 of class scala/util/parsing/combinator/Parsers
   public abstract #73= #72 of #68; //OnceParser=class scala/util/parsing/combinator/Parsers$OnceParser of class scala/util/parsing/combinator/Parsers
   public abstract #74= #52 of #68; //ParseResult=class scala/util/parsing/combinator/Parsers$ParseResult of class scala/util/parsing/combinator/Parsers
  minor version: 0
  major version: 49
  Constant pool:
const #1 = Asciz	SourceFile;
const #2 = Asciz	Parsers.scala;
const #3 = Asciz	f$2;
const #4 = Asciz	Lscala/Function1;;
const #5 = Asciz	$outer;
const #6 = Asciz	Lscala/util/parsing/combinator/Parsers;;
const #7 = Asciz	<init>;
const #8 = Asciz	(Lscala/util/parsing/combinator/Parsers;Lscala/Function1;)V;
const #9 = Asciz	Code;
const #10 = Asciz	LineNumberTable;
const #11 = Asciz	java/lang/NullPointerException;
const #12 = class	#11;	//  java/lang/NullPointerException
const #13 = Asciz	()V;
const #14 = NameAndType	#7:#13;//  "<init>":()V
const #15 = Method	#12.#14;	//  java/lang/NullPointerException."<init>":()V
const #16 = Asciz	scala/util/parsing/combinator/Parsers$$anon$1;
const #17 = class	#16;	//  scala/util/parsing/combinator/Parsers$$anon$1
const #18 = NameAndType	#5:#6;//  $outer:Lscala/util/parsing/combinator/Parsers;
const #19 = Field	#17.#18;	//  scala/util/parsing/combinator/Parsers$$anon$1.$outer:Lscala/util/parsing/combinator/Parsers;
const #20 = NameAndType	#3:#4;//  f$2:Lscala/Function1;
const #21 = Field	#17.#20;	//  scala/util/parsing/combinator/Parsers$$anon$1.f$2:Lscala/Function1;
const #22 = Asciz	scala/util/parsing/combinator/Parsers$Parser;
const #23 = class	#22;	//  scala/util/parsing/combinator/Parsers$Parser
const #24 = Asciz	(Lscala/util/parsing/combinator/Parsers;)V;
const #25 = NameAndType	#7:#24;//  "<init>":(Lscala/util/parsing/combinator/Parsers;)V
const #26 = Method	#23.#25;	//  scala/util/parsing/combinator/Parsers$Parser."<init>":(Lscala/util/parsing/combinator/Parsers;)V
const #27 = Asciz	scala/util/parsing/combinator/Parsers$OnceParser$class;
const #28 = class	#27;	//  scala/util/parsing/combinator/Parsers$OnceParser$class
const #29 = Asciz	$init$;
const #30 = Asciz	(Lscala/util/parsing/combinator/Parsers$OnceParser;)V;
const #31 = NameAndType	#29:#30;//  $init$:(Lscala/util/parsing/combinator/Parsers$OnceParser;)V
const #32 = Method	#28.#31;	//  scala/util/parsing/combinator/Parsers$OnceParser$class.$init$:(Lscala/util/parsing/combinator/Parsers$OnceParser;)V
const #33 = Asciz	this;
const #34 = Asciz	Lscala/util/parsing/combinator/Parsers$$anon$1;;
const #35 = Asciz	LocalVariableTable;
const #36 = Asciz	apply;
const #37 = Asciz	(Ljava/lang/Object;)Ljava/lang/Object;;
const #38 = Asciz	scala/util/parsing/input/Reader;
const #39 = class	#38;	//  scala/util/parsing/input/Reader
const #40 = Asciz	(Lscala/util/parsing/input/Reader;)Lscala/util/parsing/combinator/Parsers$ParseResult;;
const #41 = NameAndType	#36:#40;//  apply:(Lscala/util/parsing/input/Reader;)Lscala/util/parsing/combinator/Parsers$ParseResult;
const #42 = Method	#17.#41;	//  scala/util/parsing/combinator/Parsers$$anon$1.apply:(Lscala/util/parsing/input/Reader;)Lscala/util/parsing/combinator/Parsers$ParseResult;
const #43 = Asciz	v1;
const #44 = Asciz	Ljava/lang/Object;;
const #45 = Asciz	scala$util$parsing$combinator$Parsers$OnceParser$$$outer;
const #46 = Asciz	()Lscala/util/parsing/combinator/Parsers;;
const #47 = Asciz	scala/Function1;
const #48 = class	#47;	//  scala/Function1
const #49 = NameAndType	#36:#37;//  apply:(Ljava/lang/Object;)Ljava/lang/Object;
const #50 = InterfaceMethod	#48.#49;	//  scala/Function1.apply:(Ljava/lang/Object;)Ljava/lang/Object;
const #51 = Asciz	scala/util/parsing/combinator/Parsers$ParseResult;
const #52 = class	#51;	//  scala/util/parsing/combinator/Parsers$ParseResult
const #53 = Asciz	in;
const #54 = Asciz	Lscala/util/parsing/input/Reader;;
const #55 = Asciz	(Lscala/util/parsing/input/Reader<Ljava/lang/Object;>;)Lscala/util/parsing/combinator/Parsers$ParseResult<TT;>;;
const #56 = Asciz	Signature;
const #57 = Asciz	$tilde;
const #58 = Asciz	(Lscala/Function0;)Lscala/util/parsing/combinator/Parsers$Parser;;
const #59 = Asciz	(Lscala/util/parsing/combinator/Parsers$OnceParser;Lscala/Function0;)Lscala/util/parsing/combinator/Parsers$Parser;;
const #60 = NameAndType	#57:#59;//  $tilde:(Lscala/util/parsing/combinator/Parsers$OnceParser;Lscala/Function0;)Lscala/util/parsing/combinator/Parsers$Parser;
const #61 = Method	#28.#60;	//  scala/util/parsing/combinator/Parsers$OnceParser$class.$tilde:(Lscala/util/parsing/combinator/Parsers$OnceParser;Lscala/Function0;)Lscala/util/parsing/combinator/Parsers$Parser;
const #62 = Asciz	p;
const #63 = Asciz	Lscala/Function0;;
const #64 = Asciz	Lscala/util/parsing/combinator/Parsers$Parser<TT;>;Lscala/util/parsing/combinator/Parsers$OnceParser<TT;>;;
const #65 = Asciz	Scala;
const #66 = Asciz	InnerClasses;
const #67 = Asciz	scala/util/parsing/combinator/Parsers;
const #68 = class	#67;	//  scala/util/parsing/combinator/Parsers
const #69 = Asciz	Parser;
const #70 = Asciz	$anon$1;
const #71 = Asciz	scala/util/parsing/combinator/Parsers$OnceParser;
const #72 = class	#71;	//  scala/util/parsing/combinator/Parsers$OnceParser
const #73 = Asciz	OnceParser;
const #74 = Asciz	ParseResult;

{
public scala.util.parsing.combinator.Parsers$$anon$1(scala.util.parsing.combinator.Parsers, scala.Function1);
  Code:
   Stack=2, Locals=3, Args_size=3
   0:	aload_1
   1:	ifnonnull	12
   4:	new	#12; //class java/lang/NullPointerException
   7:	dup
   8:	invokespecial	#15; //Method java/lang/NullPointerException."<init>":()V
   11:	athrow
   12:	aload_0
   13:	aload_1
   14:	putfield	#19; //Field $outer:Lscala/util/parsing/combinator/Parsers;
   17:	aload_0
   18:	aload_2
   19:	putfield	#21; //Field f$2:Lscala/Function1;
   22:	aload_0
   23:	aload_1
   24:	invokespecial	#26; //Method scala/util/parsing/combinator/Parsers$Parser."<init>":(Lscala/util/parsing/combinator/Parsers;)V
   27:	aload_0
   28:	invokestatic	#32; //Method scala/util/parsing/combinator/Parsers$OnceParser$class.$init$:(Lscala/util/parsing/combinator/Parsers$OnceParser;)V
   31:	return
  LineNumberTable: 
   line 199: 0

  LocalVariableTable: 
   Start  Length  Slot  Name   Signature
   0      32      0    this       Lscala/util/parsing/combinator/Parsers$$anon$1;
   0      32      1    $outer       Lscala/util/parsing/combinator/Parsers;


public java.lang.Object apply(java.lang.Object);
  Code:
   Stack=2, Locals=2, Args_size=2
   0:	aload_0
   1:	aload_1
   2:	checkcast	#39; //class scala/util/parsing/input/Reader
   5:	invokevirtual	#42; //Method apply:(Lscala/util/parsing/input/Reader;)Lscala/util/parsing/combinator/Parsers$ParseResult;
   8:	areturn
  LineNumberTable: 
   line 199: 0

  LocalVariableTable: 
   Start  Length  Slot  Name   Signature
   0      9      0    this       Lscala/util/parsing/combinator/Parsers$$anon$1;
   0      9      1    v1       Ljava/lang/Object;


public scala.util.parsing.combinator.Parsers scala$util$parsing$combinator$Parsers$OnceParser$$$outer();
  Code:
   Stack=1, Locals=1, Args_size=1
   0:	aload_0
   1:	getfield	#19; //Field $outer:Lscala/util/parsing/combinator/Parsers;
   4:	areturn
  LineNumberTable: 
   line 199: 1


public scala.util.parsing.combinator.Parsers$ParseResult apply(scala.util.parsing.input.Reader);
  Code:
   Stack=2, Locals=2, Args_size=2
   0:	aload_0
   1:	getfield	#21; //Field f$2:Lscala/Function1;
   4:	aload_1
   5:	invokeinterface	#50,  2; //InterfaceMethod scala/Function1.apply:(Ljava/lang/Object;)Ljava/lang/Object;
   10:	checkcast	#52; //class scala/util/parsing/combinator/Parsers$ParseResult
   13:	areturn
  LineNumberTable: 
   line 199: 0

  LocalVariableTable: 
   Start  Length  Slot  Name   Signature
   0      14      0    this       Lscala/util/parsing/combinator/Parsers$$anon$1;
   0      14      1    in       Lscala/util/parsing/input/Reader;

  Signature: length = 0x2
   00 37 

public scala.util.parsing.combinator.Parsers$Parser $tilde(scala.Function0);
  Code:
   Stack=2, Locals=2, Args_size=2
   0:	aload_0
   1:	aload_1
   2:	invokestatic	#61; //Method scala/util/parsing/combinator/Parsers$OnceParser$class.$tilde:(Lscala/util/parsing/combinator/Parsers$OnceParser;Lscala/Function0;)Lscala/util/parsing/combinator/Parsers$Parser;
   5:	areturn
  LineNumberTable: 
   line 199: 0

  LocalVariableTable: 
   Start  Length  Slot  Name   Signature
   0      6      0    this       Lscala/util/parsing/combinator/Parsers$$anon$1;
   0      6      1    p       Lscala/Function0;


}

