Compiled from "Parsers.scala"
public final class scala.util.parsing.combinator.Parsers$$anonfun$accept$2 extends scala.runtime.AbstractFunction1 implements java.io.Serializable
  SourceFile: "Parsers.scala"
  Scala: length = 0x
   
  InnerClass: 
   public final $anonfun$accept$2=class scala/util/parsing/combinator/Parsers$$anonfun$accept$2 of class scala/util/parsing/combinator/Parsers
  minor version: 0
  major version: 49
  Constant pool:
Asciz	SourceFile;
Asciz	Parsers.scala;
Asciz	<clinit>;
Asciz	()V;
Asciz	Code;
Asciz	serialVersionUID;
Asciz	J;
Asciz	scala/util/parsing/combinator/Parsers$$anonfun$accept$2;
class	scala/util/parsing/combinator/Parsers$$anonfun$accept$2
NameAndType	serialVersionUID:J
Field	scala/util/parsing/combinator/Parsers$$anonfun$accept$2.serialVersionUID:J
Asciz	e$1;
Asciz	Ljava/lang/Object;;
Asciz	<init>;
Asciz	(Lscala/util/parsing/combinator/Parsers;Ljava/lang/Object;)V;
Asciz	LineNumberTable;
NameAndType	e$1:Ljava/lang/Object;
Field	scala/util/parsing/combinator/Parsers$$anonfun$accept$2.e$1:Ljava/lang/Object;
Asciz	scala/runtime/AbstractFunction1;
class	scala/runtime/AbstractFunction1
NameAndType	"<init>":()V
Method	scala/runtime/AbstractFunction1."<init>":()V
Asciz	this;
Asciz	Lscala/util/parsing/combinator/Parsers$$anonfun$accept$2;;
Asciz	$outer;
Asciz	Lscala/util/parsing/combinator/Parsers;;
Asciz	LocalVariableTable;
Asciz	apply;
Asciz	(Ljava/lang/Object;)Ljava/lang/Object;;
Asciz	(Ljava/lang/Object;)Ljava/lang/String;;
NameAndType	apply:(Ljava/lang/Object;)Ljava/lang/String;
Method	scala/util/parsing/combinator/Parsers$$anonfun$accept$2.apply:(Ljava/lang/Object;)Ljava/lang/String;
Asciz	v1;
Asciz	scala/collection/mutable/StringBuilder;
class	scala/collection/mutable/StringBuilder
Method	scala/collection/mutable/StringBuilder."<init>":()V
Asciz	`;
String	`
Asciz	append;
Asciz	(Ljava/lang/Object;)Lscala/collection/mutable/StringBuilder;;
NameAndType	append:(Ljava/lang/Object;)Lscala/collection/mutable/StringBuilder;
Method	scala/collection/mutable/StringBuilder.append:(Ljava/lang/Object;)Lscala/collection/mutable/StringBuilder;
Asciz	' expected but ;
String	' expected but 
Asciz	 found;
String	 found
Asciz	toString;
Asciz	()Ljava/lang/String;;
NameAndType	toString:()Ljava/lang/String;
Method	scala/collection/mutable/StringBuilder.toString:()Ljava/lang/String;
Asciz	Scala;
Asciz	InnerClasses;
Asciz	scala/util/parsing/combinator/Parsers;
class	scala/util/parsing/combinator/Parsers
Asciz	$anonfun$accept$2;
Asciz	java/io/Serializable;
class	java/io/Serializable

{
public static final long serialVersionUID;
  Signature: J

private final java.lang.Object e$1;
  Signature: Ljava/lang/Object;

public static {};
  Signature: ()V
  Code:
   Stack=2, Locals=0, Args_size=0
	lconst_0
	putstatic	Field serialVersionUID:J
	return
  Labels:

public scala.util.parsing.combinator.Parsers$$anonfun$accept$2(scala.util.parsing.combinator.Parsers, java.lang.Object);
  Signature: (Lscala/util/parsing/combinator/Parsers;Ljava/lang/Object;)V
  Code:
   Stack=2, Locals=3, Args_size=3
	aload_0
	aload_2
	putfield	Field e$1:Ljava/lang/Object;
	aload_0
	invokespecial	Method scala/runtime/AbstractFunction1."<init>":()V
	return
  Labels:
  LocalVariableTable: 
   Start  Length  Slot  Name   Signature
   0      10      0    this       Lscala/util/parsing/combinator/Parsers$$anonfun$accept$2;
   0      10      1    $outer       Lscala/util/parsing/combinator/Parsers;


public final java.lang.Object apply(java.lang.Object);
  Signature: (Ljava/lang/Object;)Ljava/lang/Object;
  Code:
   Stack=2, Locals=2, Args_size=2
	aload_0
	aload_1
	invokevirtual	Method apply:(Ljava/lang/Object;)Ljava/lang/String;
	areturn
  Labels:
  LocalVariableTable: 
   Start  Length  Slot  Name   Signature
   0      6      0    this       Lscala/util/parsing/combinator/Parsers$$anonfun$accept$2;
   0      6      1    v1       Ljava/lang/Object;


public final java.lang.String apply(java.lang.Object);
  Signature: (Ljava/lang/Object;)Ljava/lang/String;
  Code:
   Stack=2, Locals=2, Args_size=2
	new	class scala/collection/mutable/StringBuilder
	dup
	invokespecial	Method scala/collection/mutable/StringBuilder."<init>":()V
	ldc	String `
	invokevirtual	Method scala/collection/mutable/StringBuilder.append:(Ljava/lang/Object;)Lscala/collection/mutable/StringBuilder;
	aload_0
	getfield	Field e$1:Ljava/lang/Object;
	invokevirtual	Method scala/collection/mutable/StringBuilder.append:(Ljava/lang/Object;)Lscala/collection/mutable/StringBuilder;
	ldc	String ' expected but 
	invokevirtual	Method scala/collection/mutable/StringBuilder.append:(Ljava/lang/Object;)Lscala/collection/mutable/StringBuilder;
	aload_1
	invokevirtual	Method scala/collection/mutable/StringBuilder.append:(Ljava/lang/Object;)Lscala/collection/mutable/StringBuilder;
	ldc	String  found
	invokevirtual	Method scala/collection/mutable/StringBuilder.append:(Ljava/lang/Object;)Lscala/collection/mutable/StringBuilder;
	invokevirtual	Method scala/collection/mutable/StringBuilder.toString:()Ljava/lang/String;
	areturn
  Labels:

}

