Compiled from "Parsers.scala"
public abstract class scala.util.parsing.combinator.Parsers$Parser extends java.lang.Object implements scala.Function1,scala.ScalaObject
  SourceFile: "Parsers.scala"
  Scala: length = 0x
   
  Signature: length = 0x2
   01 FFFFFF96 
  InnerClass: 
   public abstract Parser=class scala/util/parsing/combinator/Parsers$Parser of class scala/util/parsing/combinator/Parsers
   public abstract OnceParser=class scala/util/parsing/combinator/Parsers$OnceParser of class scala/util/parsing/combinator/Parsers
   public abstract ParseResult=class scala/util/parsing/combinator/Parsers$ParseResult of class scala/util/parsing/combinator/Parsers
   public final $anon$4=class scala/util/parsing/combinator/Parsers$Parser$$anon$4 of class scala/util/parsing/combinator/Parsers$Parser
   public final $anonfun$map$1=class scala/util/parsing/combinator/Parsers$Parser$$anonfun$map$1 of class scala/util/parsing/combinator/Parsers$Parser
   public final $anonfun$$plus$1=class scala/util/parsing/combinator/Parsers$Parser$$anonfun$$plus$1 of class scala/util/parsing/combinator/Parsers$Parser
   public final $anonfun$$qmark$1=class scala/util/parsing/combinator/Parsers$Parser$$anonfun$$qmark$1 of class scala/util/parsing/combinator/Parsers$Parser
   public final $anonfun$$times$2=class scala/util/parsing/combinator/Parsers$Parser$$anonfun$$times$2 of class scala/util/parsing/combinator/Parsers$Parser
   public final $anonfun$$times$1=class scala/util/parsing/combinator/Parsers$Parser$$anonfun$$times$1 of class scala/util/parsing/combinator/Parsers$Parser
   public final $anonfun$$tilde$1=class scala/util/parsing/combinator/Parsers$Parser$$anonfun$$tilde$1 of class scala/util/parsing/combinator/Parsers$Parser
   public final $anonfun$append$1=class scala/util/parsing/combinator/Parsers$Parser$$anonfun$append$1 of class scala/util/parsing/combinator/Parsers$Parser
   public final $anonfun$flatMap$1=class scala/util/parsing/combinator/Parsers$Parser$$anonfun$flatMap$1 of class scala/util/parsing/combinator/Parsers$Parser
   public final $anonfun$$up$qmark$2=class scala/util/parsing/combinator/Parsers$Parser$$anonfun$$up$qmark$2 of class scala/util/parsing/combinator/Parsers$Parser
   public final $anonfun$$up$qmark$1=class scala/util/parsing/combinator/Parsers$Parser$$anonfun$$up$qmark$1 of class scala/util/parsing/combinator/Parsers$Parser
   public final $anonfun$$up$up$up$1=class scala/util/parsing/combinator/Parsers$Parser$$anonfun$$up$up$up$1 of class scala/util/parsing/combinator/Parsers$Parser
   public final $anonfun$$tilde$bang$1=class scala/util/parsing/combinator/Parsers$Parser$$anonfun$$tilde$bang$1 of class scala/util/parsing/combinator/Parsers$Parser
   public final $anonfun$$less$tilde$1=class scala/util/parsing/combinator/Parsers$Parser$$anonfun$$less$tilde$1 of class scala/util/parsing/combinator/Parsers$Parser
   public final $anonfun$$tilde$greater$1=class scala/util/parsing/combinator/Parsers$Parser$$anonfun$$tilde$greater$1 of class scala/util/parsing/combinator/Parsers$Parser
  minor version: 0
  major version: 49
  Constant pool:
Asciz	SourceFile;
Asciz	Parsers.scala;
Asciz	name;
Asciz	Ljava/lang/String;;
Asciz	$outer;
Asciz	Lscala/util/parsing/combinator/Parsers;;
Asciz	apply$mcVI$sp;
Asciz	(I)V;
Asciz	Code;
Asciz	LineNumberTable;
Asciz	scala/Function1$class;
class	scala/Function1$class
Asciz	(Lscala/Function1;I)V;
NameAndType	apply$mcVI$sp:(Lscala/Function1;I)V
Method	scala/Function1$class.apply$mcVI$sp:(Lscala/Function1;I)V
Asciz	this;
Asciz	Lscala/util/parsing/combinator/Parsers$Parser;;
Asciz	v1;
Asciz	I;
Asciz	LocalVariableTable;
Asciz	apply$mcZI$sp;
Asciz	(I)Z;
Asciz	(Lscala/Function1;I)Z;
NameAndType	apply$mcZI$sp:(Lscala/Function1;I)Z
Method	scala/Function1$class.apply$mcZI$sp:(Lscala/Function1;I)Z
Asciz	apply$mcII$sp;
Asciz	(I)I;
Asciz	(Lscala/Function1;I)I;
NameAndType	apply$mcII$sp:(Lscala/Function1;I)I
Method	scala/Function1$class.apply$mcII$sp:(Lscala/Function1;I)I
Asciz	apply$mcLI$sp;
Asciz	(I)J;
Asciz	(Lscala/Function1;I)J;
NameAndType	apply$mcLI$sp:(Lscala/Function1;I)J
Method	scala/Function1$class.apply$mcLI$sp:(Lscala/Function1;I)J
Asciz	apply$mcDI$sp;
Asciz	(I)D;
Asciz	(Lscala/Function1;I)D;
NameAndType	apply$mcDI$sp:(Lscala/Function1;I)D
Method	scala/Function1$class.apply$mcDI$sp:(Lscala/Function1;I)D
Asciz	apply$mcVL$sp;
Asciz	(J)V;
Asciz	(Lscala/Function1;J)V;
NameAndType	apply$mcVL$sp:(Lscala/Function1;J)V
Method	scala/Function1$class.apply$mcVL$sp:(Lscala/Function1;J)V
Asciz	J;
Asciz	apply$mcZL$sp;
Asciz	(J)Z;
Asciz	(Lscala/Function1;J)Z;
NameAndType	apply$mcZL$sp:(Lscala/Function1;J)Z
Method	scala/Function1$class.apply$mcZL$sp:(Lscala/Function1;J)Z
Asciz	apply$mcIL$sp;
Asciz	(J)I;
Asciz	(Lscala/Function1;J)I;
NameAndType	apply$mcIL$sp:(Lscala/Function1;J)I
Method	scala/Function1$class.apply$mcIL$sp:(Lscala/Function1;J)I
Asciz	apply$mcLL$sp;
Asciz	(J)J;
Asciz	(Lscala/Function1;J)J;
NameAndType	apply$mcLL$sp:(Lscala/Function1;J)J
Method	scala/Function1$class.apply$mcLL$sp:(Lscala/Function1;J)J
Asciz	apply$mcDL$sp;
Asciz	(J)D;
Asciz	(Lscala/Function1;J)D;
NameAndType	apply$mcDL$sp:(Lscala/Function1;J)D
Method	scala/Function1$class.apply$mcDL$sp:(Lscala/Function1;J)D
Asciz	apply$mcVD$sp;
Asciz	(D)V;
Asciz	(Lscala/Function1;D)V;
NameAndType	apply$mcVD$sp:(Lscala/Function1;D)V
Method	scala/Function1$class.apply$mcVD$sp:(Lscala/Function1;D)V
Asciz	D;
Asciz	apply$mcZD$sp;
Asciz	(D)Z;
Asciz	(Lscala/Function1;D)Z;
NameAndType	apply$mcZD$sp:(Lscala/Function1;D)Z
Method	scala/Function1$class.apply$mcZD$sp:(Lscala/Function1;D)Z
Asciz	apply$mcID$sp;
Asciz	(D)I;
Asciz	(Lscala/Function1;D)I;
NameAndType	apply$mcID$sp:(Lscala/Function1;D)I
Method	scala/Function1$class.apply$mcID$sp:(Lscala/Function1;D)I
Asciz	apply$mcLD$sp;
Asciz	(D)J;
Asciz	(Lscala/Function1;D)J;
NameAndType	apply$mcLD$sp:(Lscala/Function1;D)J
Method	scala/Function1$class.apply$mcLD$sp:(Lscala/Function1;D)J
Asciz	apply$mcDD$sp;
Asciz	(D)D;
Asciz	(Lscala/Function1;D)D;
NameAndType	apply$mcDD$sp:(Lscala/Function1;D)D
Method	scala/Function1$class.apply$mcDD$sp:(Lscala/Function1;D)D
Asciz	compose;
Asciz	(Lscala/Function1;)Lscala/Function1;;
Asciz	(Lscala/Function1;Lscala/Function1;)Lscala/Function1;;
NameAndType	compose:(Lscala/Function1;Lscala/Function1;)Lscala/Function1;
Method	scala/Function1$class.compose:(Lscala/Function1;Lscala/Function1;)Lscala/Function1;
Asciz	g;
Asciz	Lscala/Function1;;
Asciz	compose$mcVI$sp;
NameAndType	compose$mcVI$sp:(Lscala/Function1;Lscala/Function1;)Lscala/Function1;
Method	scala/Function1$class.compose$mcVI$sp:(Lscala/Function1;Lscala/Function1;)Lscala/Function1;
Asciz	compose$mcZI$sp;
NameAndType	compose$mcZI$sp:(Lscala/Function1;Lscala/Function1;)Lscala/Function1;
Method	scala/Function1$class.compose$mcZI$sp:(Lscala/Function1;Lscala/Function1;)Lscala/Function1;
Asciz	compose$mcII$sp;
NameAndType	compose$mcII$sp:(Lscala/Function1;Lscala/Function1;)Lscala/Function1;
Method	scala/Function1$class.compose$mcII$sp:(Lscala/Function1;Lscala/Function1;)Lscala/Function1;
Asciz	compose$mcLI$sp;
NameAndType	compose$mcLI$sp:(Lscala/Function1;Lscala/Function1;)Lscala/Function1;
Method	scala/Function1$class.compose$mcLI$sp:(Lscala/Function1;Lscala/Function1;)Lscala/Function1;
Asciz	compose$mcDI$sp;
NameAndType	compose$mcDI$sp:(Lscala/Function1;Lscala/Function1;)Lscala/Function1;
Method	scala/Function1$class.compose$mcDI$sp:(Lscala/Function1;Lscala/Function1;)Lscala/Function1;
Asciz	compose$mcVL$sp;
NameAndType	compose$mcVL$sp:(Lscala/Function1;Lscala/Function1;)Lscala/Function1;
Method	scala/Function1$class.compose$mcVL$sp:(Lscala/Function1;Lscala/Function1;)Lscala/Function1;
Asciz	compose$mcZL$sp;
NameAndType	compose$mcZL$sp:(Lscala/Function1;Lscala/Function1;)Lscala/Function1;
Method	scala/Function1$class.compose$mcZL$sp:(Lscala/Function1;Lscala/Function1;)Lscala/Function1;
Asciz	compose$mcIL$sp;
NameAndType	compose$mcIL$sp:(Lscala/Function1;Lscala/Function1;)Lscala/Function1;
Method	scala/Function1$class.compose$mcIL$sp:(Lscala/Function1;Lscala/Function1;)Lscala/Function1;
Asciz	compose$mcLL$sp;
NameAndType	compose$mcLL$sp:(Lscala/Function1;Lscala/Function1;)Lscala/Function1;
Method	scala/Function1$class.compose$mcLL$sp:(Lscala/Function1;Lscala/Function1;)Lscala/Function1;
Asciz	compose$mcDL$sp;
NameAndType	compose$mcDL$sp:(Lscala/Function1;Lscala/Function1;)Lscala/Function1;
Method	scala/Function1$class.compose$mcDL$sp:(Lscala/Function1;Lscala/Function1;)Lscala/Function1;
Asciz	compose$mcVD$sp;
NameAndType	compose$mcVD$sp:(Lscala/Function1;Lscala/Function1;)Lscala/Function1;
Method	scala/Function1$class.compose$mcVD$sp:(Lscala/Function1;Lscala/Function1;)Lscala/Function1;
Asciz	compose$mcZD$sp;
NameAndType	compose$mcZD$sp:(Lscala/Function1;Lscala/Function1;)Lscala/Function1;
Method	scala/Function1$class.compose$mcZD$sp:(Lscala/Function1;Lscala/Function1;)Lscala/Function1;
Asciz	compose$mcID$sp;
NameAndType	compose$mcID$sp:(Lscala/Function1;Lscala/Function1;)Lscala/Function1;
Method	scala/Function1$class.compose$mcID$sp:(Lscala/Function1;Lscala/Function1;)Lscala/Function1;
Asciz	compose$mcLD$sp;
NameAndType	compose$mcLD$sp:(Lscala/Function1;Lscala/Function1;)Lscala/Function1;
Method	scala/Function1$class.compose$mcLD$sp:(Lscala/Function1;Lscala/Function1;)Lscala/Function1;
Asciz	compose$mcDD$sp;
NameAndType	compose$mcDD$sp:(Lscala/Function1;Lscala/Function1;)Lscala/Function1;
Method	scala/Function1$class.compose$mcDD$sp:(Lscala/Function1;Lscala/Function1;)Lscala/Function1;
Asciz	andThen;
NameAndType	andThen:(Lscala/Function1;Lscala/Function1;)Lscala/Function1;
Method	scala/Function1$class.andThen:(Lscala/Function1;Lscala/Function1;)Lscala/Function1;
Asciz	andThen$mcVI$sp;
NameAndType	andThen$mcVI$sp:(Lscala/Function1;Lscala/Function1;)Lscala/Function1;
Method	scala/Function1$class.andThen$mcVI$sp:(Lscala/Function1;Lscala/Function1;)Lscala/Function1;
Asciz	andThen$mcZI$sp;
NameAndType	andThen$mcZI$sp:(Lscala/Function1;Lscala/Function1;)Lscala/Function1;
Method	scala/Function1$class.andThen$mcZI$sp:(Lscala/Function1;Lscala/Function1;)Lscala/Function1;
Asciz	andThen$mcII$sp;
NameAndType	andThen$mcII$sp:(Lscala/Function1;Lscala/Function1;)Lscala/Function1;
Method	scala/Function1$class.andThen$mcII$sp:(Lscala/Function1;Lscala/Function1;)Lscala/Function1;
Asciz	andThen$mcLI$sp;
NameAndType	andThen$mcLI$sp:(Lscala/Function1;Lscala/Function1;)Lscala/Function1;
Method	scala/Function1$class.andThen$mcLI$sp:(Lscala/Function1;Lscala/Function1;)Lscala/Function1;
Asciz	andThen$mcDI$sp;
NameAndType	andThen$mcDI$sp:(Lscala/Function1;Lscala/Function1;)Lscala/Function1;
Method	scala/Function1$class.andThen$mcDI$sp:(Lscala/Function1;Lscala/Function1;)Lscala/Function1;
Asciz	andThen$mcVL$sp;
NameAndType	andThen$mcVL$sp:(Lscala/Function1;Lscala/Function1;)Lscala/Function1;
Method	scala/Function1$class.andThen$mcVL$sp:(Lscala/Function1;Lscala/Function1;)Lscala/Function1;
Asciz	andThen$mcZL$sp;
NameAndType	andThen$mcZL$sp:(Lscala/Function1;Lscala/Function1;)Lscala/Function1;
Method	scala/Function1$class.andThen$mcZL$sp:(Lscala/Function1;Lscala/Function1;)Lscala/Function1;
Asciz	andThen$mcIL$sp;
NameAndType	andThen$mcIL$sp:(Lscala/Function1;Lscala/Function1;)Lscala/Function1;
Method	scala/Function1$class.andThen$mcIL$sp:(Lscala/Function1;Lscala/Function1;)Lscala/Function1;
Asciz	andThen$mcLL$sp;
NameAndType	andThen$mcLL$sp:(Lscala/Function1;Lscala/Function1;)Lscala/Function1;
Method	scala/Function1$class.andThen$mcLL$sp:(Lscala/Function1;Lscala/Function1;)Lscala/Function1;
Asciz	andThen$mcDL$sp;
NameAndType	andThen$mcDL$sp:(Lscala/Function1;Lscala/Function1;)Lscala/Function1;
Method	scala/Function1$class.andThen$mcDL$sp:(Lscala/Function1;Lscala/Function1;)Lscala/Function1;
Asciz	andThen$mcVD$sp;
NameAndType	andThen$mcVD$sp:(Lscala/Function1;Lscala/Function1;)Lscala/Function1;
Method	scala/Function1$class.andThen$mcVD$sp:(Lscala/Function1;Lscala/Function1;)Lscala/Function1;
Asciz	andThen$mcZD$sp;
NameAndType	andThen$mcZD$sp:(Lscala/Function1;Lscala/Function1;)Lscala/Function1;
Method	scala/Function1$class.andThen$mcZD$sp:(Lscala/Function1;Lscala/Function1;)Lscala/Function1;
Asciz	andThen$mcID$sp;
NameAndType	andThen$mcID$sp:(Lscala/Function1;Lscala/Function1;)Lscala/Function1;
Method	scala/Function1$class.andThen$mcID$sp:(Lscala/Function1;Lscala/Function1;)Lscala/Function1;
Asciz	andThen$mcLD$sp;
NameAndType	andThen$mcLD$sp:(Lscala/Function1;Lscala/Function1;)Lscala/Function1;
Method	scala/Function1$class.andThen$mcLD$sp:(Lscala/Function1;Lscala/Function1;)Lscala/Function1;
Asciz	andThen$mcDD$sp;
NameAndType	andThen$mcDD$sp:(Lscala/Function1;Lscala/Function1;)Lscala/Function1;
Method	scala/Function1$class.andThen$mcDD$sp:(Lscala/Function1;Lscala/Function1;)Lscala/Function1;
Asciz	()Ljava/lang/String;;
Asciz	scala/util/parsing/combinator/Parsers$Parser;
class	scala/util/parsing/combinator/Parsers$Parser
NameAndType	name:Ljava/lang/String;
Field	scala/util/parsing/combinator/Parsers$Parser.name:Ljava/lang/String;
Asciz	name_$eq;
Asciz	(Ljava/lang/String;)V;
Asciz	named;
Asciz	(Ljava/lang/String;)Lscala/util/parsing/combinator/Parsers$Parser;;
NameAndType	name_$eq:(Ljava/lang/String;)V
Method	scala/util/parsing/combinator/Parsers$Parser.name_$eq:(Ljava/lang/String;)V
Asciz	n;
Asciz	(Ljava/lang/String;)Lscala/util/parsing/combinator/Parsers$Parser<TT;>;;
Asciz	Signature;
Asciz	toString;
Asciz	scala/collection/mutable/StringBuilder;
class	scala/collection/mutable/StringBuilder
Asciz	<init>;
Asciz	()V;
NameAndType	"<init>":()V
Method	scala/collection/mutable/StringBuilder."<init>":()V
Asciz	Parser (;
String	Parser (
Asciz	append;
Asciz	(Ljava/lang/Object;)Lscala/collection/mutable/StringBuilder;;
NameAndType	append:(Ljava/lang/Object;)Lscala/collection/mutable/StringBuilder;
Method	scala/collection/mutable/StringBuilder.append:(Ljava/lang/Object;)Lscala/collection/mutable/StringBuilder;
NameAndType	name:()Ljava/lang/String;
Method	scala/util/parsing/combinator/Parsers$Parser.name:()Ljava/lang/String;
Asciz	);
String	)
NameAndType	toString:()Ljava/lang/String;
Method	scala/collection/mutable/StringBuilder.toString:()Ljava/lang/String;
Asciz	apply;
Asciz	(Lscala/util/parsing/input/Reader;)Lscala/util/parsing/combinator/Parsers$ParseResult;;
Asciz	(Lscala/util/parsing/input/Reader<Ljava/lang/Object;>;)Lscala/util/parsing/combinator/Parsers$ParseResult<TT;>;;
Asciz	flatMap;
Asciz	(Lscala/Function1;)Lscala/util/parsing/combinator/Parsers$Parser;;
Asciz	scala$util$parsing$combinator$Parsers$Parser$$$outer;
Asciz	()Lscala/util/parsing/combinator/Parsers;;
NameAndType	scala$util$parsing$combinator$Parsers$Parser$$$outer:()Lscala/util/parsing/combinator/Parsers;
Method	scala/util/parsing/combinator/Parsers$Parser.scala$util$parsing$combinator$Parsers$Parser$$$outer:()Lscala/util/parsing/combinator/Parsers;
Asciz	scala/util/parsing/combinator/Parsers$Parser$$anonfun$flatMap$1;
class	scala/util/parsing/combinator/Parsers$Parser$$anonfun$flatMap$1
Asciz	(Lscala/util/parsing/combinator/Parsers$Parser;Lscala/Function1;)V;
NameAndType	"<init>":(Lscala/util/parsing/combinator/Parsers$Parser;Lscala/Function1;)V
Method	scala/util/parsing/combinator/Parsers$Parser$$anonfun$flatMap$1."<init>":(Lscala/util/parsing/combinator/Parsers$Parser;Lscala/Function1;)V
Asciz	scala/util/parsing/combinator/Parsers;
class	scala/util/parsing/combinator/Parsers
Asciz	Parser;
NameAndType	Parser:(Lscala/Function1;)Lscala/util/parsing/combinator/Parsers$Parser;
InterfaceMethod	scala/util/parsing/combinator/Parsers.Parser:(Lscala/Function1;)Lscala/util/parsing/combinator/Parsers$Parser;
Asciz	f$3;
Asciz	<U:Ljava/lang/Object;>(Lscala/Function1<TT;Lscala/util/parsing/combinator/Parsers$Parser<TU;>;>;)Lscala/util/parsing/combinator/Parsers$Parser<TU;>;;
Asciz	map;
Asciz	scala/util/parsing/combinator/Parsers$Parser$$anonfun$map$1;
class	scala/util/parsing/combinator/Parsers$Parser$$anonfun$map$1
Method	scala/util/parsing/combinator/Parsers$Parser$$anonfun$map$1."<init>":(Lscala/util/parsing/combinator/Parsers$Parser;Lscala/Function1;)V
Asciz	f$4;
Asciz	<U:Ljava/lang/Object;>(Lscala/Function1<TT;TU;>;)Lscala/util/parsing/combinator/Parsers$Parser<TU;>;;
Asciz	(Lscala/Function0;)Lscala/util/parsing/combinator/Parsers$Parser;;
Asciz	scala/util/parsing/combinator/Parsers$Parser$$anonfun$append$1;
class	scala/util/parsing/combinator/Parsers$Parser$$anonfun$append$1
Asciz	(Lscala/util/parsing/combinator/Parsers$Parser;Lscala/Function0;)V;
NameAndType	"<init>":(Lscala/util/parsing/combinator/Parsers$Parser;Lscala/Function0;)V
Method	scala/util/parsing/combinator/Parsers$Parser$$anonfun$append$1."<init>":(Lscala/util/parsing/combinator/Parsers$Parser;Lscala/Function0;)V
Asciz	p$4;
Asciz	Lscala/Function0;;
Asciz	<U:Ljava/lang/Object;>(Lscala/Function0<Lscala/util/parsing/combinator/Parsers$Parser<TU;>;>;)Lscala/util/parsing/combinator/Parsers$Parser<TU;>;;
Asciz	$tilde;
Asciz	scala/util/parsing/combinator/Parsers$Parser$$anonfun$$tilde$1;
class	scala/util/parsing/combinator/Parsers$Parser$$anonfun$$tilde$1
Method	scala/util/parsing/combinator/Parsers$Parser$$anonfun$$tilde$1."<init>":(Lscala/util/parsing/combinator/Parsers$Parser;Lscala/Function0;)V
NameAndType	flatMap:(Lscala/Function1;)Lscala/util/parsing/combinator/Parsers$Parser;
Method	scala/util/parsing/combinator/Parsers$Parser.flatMap:(Lscala/Function1;)Lscala/util/parsing/combinator/Parsers$Parser;
Asciz	~;
String	~
NameAndType	named:(Ljava/lang/String;)Lscala/util/parsing/combinator/Parsers$Parser;
Method	scala/util/parsing/combinator/Parsers$Parser.named:(Ljava/lang/String;)Lscala/util/parsing/combinator/Parsers$Parser;
Asciz	p$3;
Asciz	<U:Ljava/lang/Object;>(Lscala/Function0<Lscala/util/parsing/combinator/Parsers$Parser<TU;>;>;)Lscala/util/parsing/combinator/Parsers$Parser<Lscala/util/parsing/combinator/Parsers$$tilde<TT;TU;>;>;;
Asciz	$tilde$greater;
Asciz	scala/util/parsing/combinator/Parsers$Parser$$anonfun$$tilde$greater$1;
class	scala/util/parsing/combinator/Parsers$Parser$$anonfun$$tilde$greater$1
Method	scala/util/parsing/combinator/Parsers$Parser$$anonfun$$tilde$greater$1."<init>":(Lscala/util/parsing/combinator/Parsers$Parser;Lscala/Function0;)V
Asciz	~>;
String	~>
Asciz	p$5;
Asciz	$less$tilde;
Asciz	scala/util/parsing/combinator/Parsers$Parser$$anonfun$$less$tilde$1;
class	scala/util/parsing/combinator/Parsers$Parser$$anonfun$$less$tilde$1
Method	scala/util/parsing/combinator/Parsers$Parser$$anonfun$$less$tilde$1."<init>":(Lscala/util/parsing/combinator/Parsers$Parser;Lscala/Function0;)V
Asciz	<~;
String	<~
Asciz	p$6;
Asciz	<U:Ljava/lang/Object;>(Lscala/Function0<Lscala/util/parsing/combinator/Parsers$Parser<TU;>;>;)Lscala/util/parsing/combinator/Parsers$Parser<TT;>;;
Asciz	$tilde$bang;
Asciz	scala/util/parsing/combinator/Parsers$Parser$$anonfun$$tilde$bang$1;
class	scala/util/parsing/combinator/Parsers$Parser$$anonfun$$tilde$bang$1
Method	scala/util/parsing/combinator/Parsers$Parser$$anonfun$$tilde$bang$1."<init>":(Lscala/util/parsing/combinator/Parsers$Parser;Lscala/Function0;)V
Asciz	~!;
String	~!
Asciz	OnceParser;
Asciz	(Lscala/Function1;)Lscala/util/parsing/combinator/Parsers$OnceParser;;
NameAndType	OnceParser:(Lscala/Function1;)Lscala/util/parsing/combinator/Parsers$OnceParser;
InterfaceMethod	scala/util/parsing/combinator/Parsers.OnceParser:(Lscala/Function1;)Lscala/util/parsing/combinator/Parsers$OnceParser;
Asciz	p$7;
Asciz	$bar;
NameAndType	append:(Lscala/Function0;)Lscala/util/parsing/combinator/Parsers$Parser;
Method	scala/util/parsing/combinator/Parsers$Parser.append:(Lscala/Function0;)Lscala/util/parsing/combinator/Parsers$Parser;
Asciz	|;
String	|
Asciz	q;
Asciz	$bar$bar$bar;
Asciz	scala/util/parsing/combinator/Parsers$Parser$$anon$4;
class	scala/util/parsing/combinator/Parsers$Parser$$anon$4
Method	scala/util/parsing/combinator/Parsers$Parser$$anon$4."<init>":(Lscala/util/parsing/combinator/Parsers$Parser;Lscala/Function0;)V
Asciz	q$1;
Asciz	$up$up;
NameAndType	map:(Lscala/Function1;)Lscala/util/parsing/combinator/Parsers$Parser;
Method	scala/util/parsing/combinator/Parsers$Parser.map:(Lscala/Function1;)Lscala/util/parsing/combinator/Parsers$Parser;
Method	scala/util/parsing/combinator/Parsers$Parser.toString:()Ljava/lang/String;
Asciz	^^;
String	^^
Asciz	f;
Asciz	$up$up$up;
Asciz	(Ljava/lang/Object;)Lscala/util/parsing/combinator/Parsers$Parser;;
Asciz	scala/util/parsing/combinator/Parsers$Parser$$anonfun$$up$up$up$1;
class	scala/util/parsing/combinator/Parsers$Parser$$anonfun$$up$up$up$1
Asciz	(Lscala/util/parsing/combinator/Parsers$Parser;Ljava/lang/Object;)V;
NameAndType	"<init>":(Lscala/util/parsing/combinator/Parsers$Parser;Ljava/lang/Object;)V
Method	scala/util/parsing/combinator/Parsers$Parser$$anonfun$$up$up$up$1."<init>":(Lscala/util/parsing/combinator/Parsers$Parser;Ljava/lang/Object;)V
NameAndType	$up$up:(Lscala/Function1;)Lscala/util/parsing/combinator/Parsers$Parser;
Method	scala/util/parsing/combinator/Parsers$Parser.$up$up:(Lscala/Function1;)Lscala/util/parsing/combinator/Parsers$Parser;
Asciz	r$1;
Asciz	Ljava/lang/Object;;
Asciz	<U:Ljava/lang/Object;>(TU;)Lscala/util/parsing/combinator/Parsers$Parser<TU;>;;
Asciz	$up$qmark;
Asciz	(Lscala/PartialFunction;Lscala/Function1;)Lscala/util/parsing/combinator/Parsers$Parser;;
Asciz	scala/util/parsing/combinator/Parsers$Parser$$anonfun$$up$qmark$1;
class	scala/util/parsing/combinator/Parsers$Parser$$anonfun$$up$qmark$1
Asciz	(Lscala/util/parsing/combinator/Parsers$Parser;Lscala/PartialFunction;Lscala/Function1;)V;
NameAndType	"<init>":(Lscala/util/parsing/combinator/Parsers$Parser;Lscala/PartialFunction;Lscala/Function1;)V
Method	scala/util/parsing/combinator/Parsers$Parser$$anonfun$$up$qmark$1."<init>":(Lscala/util/parsing/combinator/Parsers$Parser;Lscala/PartialFunction;Lscala/Function1;)V
Asciz	^?;
String	^?
Asciz	f$5;
Asciz	Lscala/PartialFunction;;
Asciz	error$1;
Asciz	<U:Ljava/lang/Object;>(Lscala/PartialFunction<TT;TU;>;Lscala/Function1<TT;Ljava/lang/String;>;)Lscala/util/parsing/combinator/Parsers$Parser<TU;>;;
Asciz	(Lscala/PartialFunction;)Lscala/util/parsing/combinator/Parsers$Parser;;
Asciz	scala/util/parsing/combinator/Parsers$Parser$$anonfun$$up$qmark$2;
class	scala/util/parsing/combinator/Parsers$Parser$$anonfun$$up$qmark$2
Asciz	(Lscala/util/parsing/combinator/Parsers$Parser;)V;
NameAndType	"<init>":(Lscala/util/parsing/combinator/Parsers$Parser;)V
Method	scala/util/parsing/combinator/Parsers$Parser$$anonfun$$up$qmark$2."<init>":(Lscala/util/parsing/combinator/Parsers$Parser;)V
NameAndType	$up$qmark:(Lscala/PartialFunction;Lscala/Function1;)Lscala/util/parsing/combinator/Parsers$Parser;
Method	scala/util/parsing/combinator/Parsers$Parser.$up$qmark:(Lscala/PartialFunction;Lscala/Function1;)Lscala/util/parsing/combinator/Parsers$Parser;
Asciz	<U:Ljava/lang/Object;>(Lscala/PartialFunction<TT;TU;>;)Lscala/util/parsing/combinator/Parsers$Parser<TU;>;;
Asciz	into;
Asciz	fq;
Asciz	$greater$greater;
NameAndType	into:(Lscala/Function1;)Lscala/util/parsing/combinator/Parsers$Parser;
Method	scala/util/parsing/combinator/Parsers$Parser.into:(Lscala/Function1;)Lscala/util/parsing/combinator/Parsers$Parser;
Asciz	$times;
Asciz	()Lscala/util/parsing/combinator/Parsers$Parser;;
Asciz	scala/util/parsing/combinator/Parsers$Parser$$anonfun$$times$1;
class	scala/util/parsing/combinator/Parsers$Parser$$anonfun$$times$1
Method	scala/util/parsing/combinator/Parsers$Parser$$anonfun$$times$1."<init>":(Lscala/util/parsing/combinator/Parsers$Parser;)V
Asciz	rep;
NameAndType	rep:(Lscala/Function0;)Lscala/util/parsing/combinator/Parsers$Parser;
InterfaceMethod	scala/util/parsing/combinator/Parsers.rep:(Lscala/Function0;)Lscala/util/parsing/combinator/Parsers$Parser;
Asciz	()Lscala/util/parsing/combinator/Parsers$Parser<Lscala/collection/immutable/List<TT;>;>;;
Asciz	scala/util/parsing/combinator/Parsers$Parser$$anonfun$$times$2;
class	scala/util/parsing/combinator/Parsers$Parser$$anonfun$$times$2
Method	scala/util/parsing/combinator/Parsers$Parser$$anonfun$$times$2."<init>":(Lscala/util/parsing/combinator/Parsers$Parser;)V
Asciz	chainl1;
Asciz	(Lscala/Function0;Lscala/Function0;)Lscala/util/parsing/combinator/Parsers$Parser;;
NameAndType	chainl1:(Lscala/Function0;Lscala/Function0;)Lscala/util/parsing/combinator/Parsers$Parser;
InterfaceMethod	scala/util/parsing/combinator/Parsers.chainl1:(Lscala/Function0;Lscala/Function0;)Lscala/util/parsing/combinator/Parsers$Parser;
Asciz	sep;
Asciz	<U:Ljava/lang/Object;>(Lscala/Function0<Lscala/util/parsing/combinator/Parsers$Parser<Lscala/Function2<TU;TU;TU;>;>;>;)Lscala/util/parsing/combinator/Parsers$Parser<TU;>;;
Asciz	$plus;
Asciz	scala/util/parsing/combinator/Parsers$Parser$$anonfun$$plus$1;
class	scala/util/parsing/combinator/Parsers$Parser$$anonfun$$plus$1
Method	scala/util/parsing/combinator/Parsers$Parser$$anonfun$$plus$1."<init>":(Lscala/util/parsing/combinator/Parsers$Parser;)V
Asciz	rep1;
NameAndType	rep1:(Lscala/Function0;)Lscala/util/parsing/combinator/Parsers$Parser;
InterfaceMethod	scala/util/parsing/combinator/Parsers.rep1:(Lscala/Function0;)Lscala/util/parsing/combinator/Parsers$Parser;
Asciz	$qmark;
Asciz	scala/util/parsing/combinator/Parsers$Parser$$anonfun$$qmark$1;
class	scala/util/parsing/combinator/Parsers$Parser$$anonfun$$qmark$1
Method	scala/util/parsing/combinator/Parsers$Parser$$anonfun$$qmark$1."<init>":(Lscala/util/parsing/combinator/Parsers$Parser;)V
Asciz	opt;
NameAndType	opt:(Lscala/Function0;)Lscala/util/parsing/combinator/Parsers$Parser;
InterfaceMethod	scala/util/parsing/combinator/Parsers.opt:(Lscala/Function0;)Lscala/util/parsing/combinator/Parsers$Parser;
Asciz	()Lscala/util/parsing/combinator/Parsers$Parser<Lscala/Option<TT;>;>;;
NameAndType	$outer:Lscala/util/parsing/combinator/Parsers;
Field	scala/util/parsing/combinator/Parsers$Parser.$outer:Lscala/util/parsing/combinator/Parsers;
Asciz	(Lscala/util/parsing/combinator/Parsers;)V;
Asciz	java/lang/NullPointerException;
class	java/lang/NullPointerException
Method	java/lang/NullPointerException."<init>":()V
Asciz	java/lang/Object;
class	java/lang/Object
Method	java/lang/Object."<init>":()V
Asciz	$init$;
Asciz	(Lscala/Function1;)V;
NameAndType	$init$:(Lscala/Function1;)V
Method	scala/Function1$class.$init$:(Lscala/Function1;)V
Asciz	;
String	
Asciz	Scala;
Asciz	<T:Ljava/lang/Object;>Ljava/lang/Object;Lscala/Function1<Lscala/util/parsing/input/Reader<Ljava/lang/Object;>;Lscala/util/parsing/combinator/Parsers$ParseResult<TT;>;>;Lscala/ScalaObject;;
Asciz	InnerClasses;
Asciz	scala/util/parsing/combinator/Parsers$OnceParser;
class	scala/util/parsing/combinator/Parsers$OnceParser
Asciz	scala/util/parsing/combinator/Parsers$ParseResult;
class	scala/util/parsing/combinator/Parsers$ParseResult
Asciz	ParseResult;
Asciz	$anon$4;
Asciz	$anonfun$map$1;
Asciz	$anonfun$$plus$1;
Asciz	$anonfun$$qmark$1;
Asciz	$anonfun$$times$2;
Asciz	$anonfun$$times$1;
Asciz	$anonfun$$tilde$1;
Asciz	$anonfun$append$1;
Asciz	$anonfun$flatMap$1;
Asciz	$anonfun$$up$qmark$2;
Asciz	$anonfun$$up$qmark$1;
Asciz	$anonfun$$up$up$up$1;
Asciz	$anonfun$$tilde$bang$1;
Asciz	$anonfun$$less$tilde$1;
Asciz	$anonfun$$tilde$greater$1;
Asciz	scala/Function1;
class	scala/Function1
Asciz	scala/ScalaObject;
class	scala/ScalaObject

{
private java.lang.String name;
  Signature: Ljava/lang/String;

public final scala.util.parsing.combinator.Parsers $outer;
  Signature: Lscala/util/parsing/combinator/Parsers;

public void apply$mcVI$sp(int);
  Signature: (I)V
  Code:
   Stack=2, Locals=2, Args_size=2
	aload_0
	iload_1
	invokestatic	Method scala/Function1$class.apply$mcVI$sp:(Lscala/Function1;I)V
	return
  Labels:
  LocalVariableTable: 
   Start  Length  Slot  Name   Signature
   0      6      0    this       Lscala/util/parsing/combinator/Parsers$Parser;
   0      6      1    v1       I


public boolean apply$mcZI$sp(int);
  Signature: (I)Z
  Code:
   Stack=2, Locals=2, Args_size=2
	aload_0
	iload_1
	invokestatic	Method scala/Function1$class.apply$mcZI$sp:(Lscala/Function1;I)Z
	ireturn
  Labels:
  LocalVariableTable: 
   Start  Length  Slot  Name   Signature
   0      6      0    this       Lscala/util/parsing/combinator/Parsers$Parser;
   0      6      1    v1       I


public int apply$mcII$sp(int);
  Signature: (I)I
  Code:
   Stack=2, Locals=2, Args_size=2
	aload_0
	iload_1
	invokestatic	Method scala/Function1$class.apply$mcII$sp:(Lscala/Function1;I)I
	ireturn
  Labels:
  LocalVariableTable: 
   Start  Length  Slot  Name   Signature
   0      6      0    this       Lscala/util/parsing/combinator/Parsers$Parser;
   0      6      1    v1       I


public long apply$mcLI$sp(int);
  Signature: (I)J
  Code:
   Stack=2, Locals=2, Args_size=2
	aload_0
	iload_1
	invokestatic	Method scala/Function1$class.apply$mcLI$sp:(Lscala/Function1;I)J
	lreturn
  Labels:
  LocalVariableTable: 
   Start  Length  Slot  Name   Signature
   0      6      0    this       Lscala/util/parsing/combinator/Parsers$Parser;
   0      6      1    v1       I


public double apply$mcDI$sp(int);
  Signature: (I)D
  Code:
   Stack=2, Locals=2, Args_size=2
	aload_0
	iload_1
	invokestatic	Method scala/Function1$class.apply$mcDI$sp:(Lscala/Function1;I)D
	dreturn
  Labels:
  LocalVariableTable: 
   Start  Length  Slot  Name   Signature
   0      6      0    this       Lscala/util/parsing/combinator/Parsers$Parser;
   0      6      1    v1       I


public void apply$mcVL$sp(long);
  Signature: (J)V
  Code:
   Stack=3, Locals=3, Args_size=2
	aload_0
	lload_1
	invokestatic	Method scala/Function1$class.apply$mcVL$sp:(Lscala/Function1;J)V
	return
  Labels:
  LocalVariableTable: 
   Start  Length  Slot  Name   Signature
   0      6      0    this       Lscala/util/parsing/combinator/Parsers$Parser;
   0      6      1    v1       J


public boolean apply$mcZL$sp(long);
  Signature: (J)Z
  Code:
   Stack=3, Locals=3, Args_size=2
	aload_0
	lload_1
	invokestatic	Method scala/Function1$class.apply$mcZL$sp:(Lscala/Function1;J)Z
	ireturn
  Labels:
  LocalVariableTable: 
   Start  Length  Slot  Name   Signature
   0      6      0    this       Lscala/util/parsing/combinator/Parsers$Parser;
   0      6      1    v1       J


public int apply$mcIL$sp(long);
  Signature: (J)I
  Code:
   Stack=3, Locals=3, Args_size=2
	aload_0
	lload_1
	invokestatic	Method scala/Function1$class.apply$mcIL$sp:(Lscala/Function1;J)I
	ireturn
  Labels:
  LocalVariableTable: 
   Start  Length  Slot  Name   Signature
   0      6      0    this       Lscala/util/parsing/combinator/Parsers$Parser;
   0      6      1    v1       J


public long apply$mcLL$sp(long);
  Signature: (J)J
  Code:
   Stack=3, Locals=3, Args_size=2
	aload_0
	lload_1
	invokestatic	Method scala/Function1$class.apply$mcLL$sp:(Lscala/Function1;J)J
	lreturn
  Labels:
  LocalVariableTable: 
   Start  Length  Slot  Name   Signature
   0      6      0    this       Lscala/util/parsing/combinator/Parsers$Parser;
   0      6      1    v1       J


public double apply$mcDL$sp(long);
  Signature: (J)D
  Code:
   Stack=3, Locals=3, Args_size=2
	aload_0
	lload_1
	invokestatic	Method scala/Function1$class.apply$mcDL$sp:(Lscala/Function1;J)D
	dreturn
  Labels:
  LocalVariableTable: 
   Start  Length  Slot  Name   Signature
   0      6      0    this       Lscala/util/parsing/combinator/Parsers$Parser;
   0      6      1    v1       J


public void apply$mcVD$sp(double);
  Signature: (D)V
  Code:
   Stack=3, Locals=3, Args_size=2
	aload_0
	dload_1
	invokestatic	Method scala/Function1$class.apply$mcVD$sp:(Lscala/Function1;D)V
	return
  Labels:
  LocalVariableTable: 
   Start  Length  Slot  Name   Signature
   0      6      0    this       Lscala/util/parsing/combinator/Parsers$Parser;
   0      6      1    v1       D


public boolean apply$mcZD$sp(double);
  Signature: (D)Z
  Code:
   Stack=3, Locals=3, Args_size=2
	aload_0
	dload_1
	invokestatic	Method scala/Function1$class.apply$mcZD$sp:(Lscala/Function1;D)Z
	ireturn
  Labels:
  LocalVariableTable: 
   Start  Length  Slot  Name   Signature
   0      6      0    this       Lscala/util/parsing/combinator/Parsers$Parser;
   0      6      1    v1       D


public int apply$mcID$sp(double);
  Signature: (D)I
  Code:
   Stack=3, Locals=3, Args_size=2
	aload_0
	dload_1
	invokestatic	Method scala/Function1$class.apply$mcID$sp:(Lscala/Function1;D)I
	ireturn
  Labels:
  LocalVariableTable: 
   Start  Length  Slot  Name   Signature
   0      6      0    this       Lscala/util/parsing/combinator/Parsers$Parser;
   0      6      1    v1       D


public long apply$mcLD$sp(double);
  Signature: (D)J
  Code:
   Stack=3, Locals=3, Args_size=2
	aload_0
	dload_1
	invokestatic	Method scala/Function1$class.apply$mcLD$sp:(Lscala/Function1;D)J
	lreturn
  Labels:
  LocalVariableTable: 
   Start  Length  Slot  Name   Signature
   0      6      0    this       Lscala/util/parsing/combinator/Parsers$Parser;
   0      6      1    v1       D


public double apply$mcDD$sp(double);
  Signature: (D)D
  Code:
   Stack=3, Locals=3, Args_size=2
	aload_0
	dload_1
	invokestatic	Method scala/Function1$class.apply$mcDD$sp:(Lscala/Function1;D)D
	dreturn
  Labels:
  LocalVariableTable: 
   Start  Length  Slot  Name   Signature
   0      6      0    this       Lscala/util/parsing/combinator/Parsers$Parser;
   0      6      1    v1       D


public scala.Function1 compose(scala.Function1);
  Signature: (Lscala/Function1;)Lscala/Function1;
  Code:
   Stack=2, Locals=2, Args_size=2
	aload_0
	aload_1
	invokestatic	Method scala/Function1$class.compose:(Lscala/Function1;Lscala/Function1;)Lscala/Function1;
	areturn
  Labels:
  LocalVariableTable: 
   Start  Length  Slot  Name   Signature
   0      6      0    this       Lscala/util/parsing/combinator/Parsers$Parser;
   0      6      1    g       Lscala/Function1;


public scala.Function1 compose$mcVI$sp(scala.Function1);
  Signature: (Lscala/Function1;)Lscala/Function1;
  Code:
   Stack=2, Locals=2, Args_size=2
	aload_0
	aload_1
	invokestatic	Method scala/Function1$class.compose$mcVI$sp:(Lscala/Function1;Lscala/Function1;)Lscala/Function1;
	areturn
  Labels:
  LocalVariableTable: 
   Start  Length  Slot  Name   Signature
   0      6      0    this       Lscala/util/parsing/combinator/Parsers$Parser;
   0      6      1    g       Lscala/Function1;


public scala.Function1 compose$mcZI$sp(scala.Function1);
  Signature: (Lscala/Function1;)Lscala/Function1;
  Code:
   Stack=2, Locals=2, Args_size=2
	aload_0
	aload_1
	invokestatic	Method scala/Function1$class.compose$mcZI$sp:(Lscala/Function1;Lscala/Function1;)Lscala/Function1;
	areturn
  Labels:
  LocalVariableTable: 
   Start  Length  Slot  Name   Signature
   0      6      0    this       Lscala/util/parsing/combinator/Parsers$Parser;
   0      6      1    g       Lscala/Function1;


public scala.Function1 compose$mcII$sp(scala.Function1);
  Signature: (Lscala/Function1;)Lscala/Function1;
  Code:
   Stack=2, Locals=2, Args_size=2
	aload_0
	aload_1
	invokestatic	Method scala/Function1$class.compose$mcII$sp:(Lscala/Function1;Lscala/Function1;)Lscala/Function1;
	areturn
  Labels:
  LocalVariableTable: 
   Start  Length  Slot  Name   Signature
   0      6      0    this       Lscala/util/parsing/combinator/Parsers$Parser;
   0      6      1    g       Lscala/Function1;


public scala.Function1 compose$mcLI$sp(scala.Function1);
  Signature: (Lscala/Function1;)Lscala/Function1;
  Code:
   Stack=2, Locals=2, Args_size=2
	aload_0
	aload_1
	invokestatic	Method scala/Function1$class.compose$mcLI$sp:(Lscala/Function1;Lscala/Function1;)Lscala/Function1;
	areturn
  Labels:
  LocalVariableTable: 
   Start  Length  Slot  Name   Signature
   0      6      0    this       Lscala/util/parsing/combinator/Parsers$Parser;
   0      6      1    g       Lscala/Function1;


public scala.Function1 compose$mcDI$sp(scala.Function1);
  Signature: (Lscala/Function1;)Lscala/Function1;
  Code:
   Stack=2, Locals=2, Args_size=2
	aload_0
	aload_1
	invokestatic	Method scala/Function1$class.compose$mcDI$sp:(Lscala/Function1;Lscala/Function1;)Lscala/Function1;
	areturn
  Labels:
  LocalVariableTable: 
   Start  Length  Slot  Name   Signature
   0      6      0    this       Lscala/util/parsing/combinator/Parsers$Parser;
   0      6      1    g       Lscala/Function1;


public scala.Function1 compose$mcVL$sp(scala.Function1);
  Signature: (Lscala/Function1;)Lscala/Function1;
  Code:
   Stack=2, Locals=2, Args_size=2
	aload_0
	aload_1
	invokestatic	Method scala/Function1$class.compose$mcVL$sp:(Lscala/Function1;Lscala/Function1;)Lscala/Function1;
	areturn
  Labels:
  LocalVariableTable: 
   Start  Length  Slot  Name   Signature
   0      6      0    this       Lscala/util/parsing/combinator/Parsers$Parser;
   0      6      1    g       Lscala/Function1;


public scala.Function1 compose$mcZL$sp(scala.Function1);
  Signature: (Lscala/Function1;)Lscala/Function1;
  Code:
   Stack=2, Locals=2, Args_size=2
	aload_0
	aload_1
	invokestatic	Method scala/Function1$class.compose$mcZL$sp:(Lscala/Function1;Lscala/Function1;)Lscala/Function1;
	areturn
  Labels:
  LocalVariableTable: 
   Start  Length  Slot  Name   Signature
   0      6      0    this       Lscala/util/parsing/combinator/Parsers$Parser;
   0      6      1    g       Lscala/Function1;


public scala.Function1 compose$mcIL$sp(scala.Function1);
  Signature: (Lscala/Function1;)Lscala/Function1;
  Code:
   Stack=2, Locals=2, Args_size=2
	aload_0
	aload_1
	invokestatic	Method scala/Function1$class.compose$mcIL$sp:(Lscala/Function1;Lscala/Function1;)Lscala/Function1;
	areturn
  Labels:
  LocalVariableTable: 
   Start  Length  Slot  Name   Signature
   0      6      0    this       Lscala/util/parsing/combinator/Parsers$Parser;
   0      6      1    g       Lscala/Function1;


public scala.Function1 compose$mcLL$sp(scala.Function1);
  Signature: (Lscala/Function1;)Lscala/Function1;
  Code:
   Stack=2, Locals=2, Args_size=2
	aload_0
	aload_1
	invokestatic	Method scala/Function1$class.compose$mcLL$sp:(Lscala/Function1;Lscala/Function1;)Lscala/Function1;
	areturn
  Labels:
  LocalVariableTable: 
   Start  Length  Slot  Name   Signature
   0      6      0    this       Lscala/util/parsing/combinator/Parsers$Parser;
   0      6      1    g       Lscala/Function1;


public scala.Function1 compose$mcDL$sp(scala.Function1);
  Signature: (Lscala/Function1;)Lscala/Function1;
  Code:
   Stack=2, Locals=2, Args_size=2
	aload_0
	aload_1
	invokestatic	Method scala/Function1$class.compose$mcDL$sp:(Lscala/Function1;Lscala/Function1;)Lscala/Function1;
	areturn
  Labels:
  LocalVariableTable: 
   Start  Length  Slot  Name   Signature
   0      6      0    this       Lscala/util/parsing/combinator/Parsers$Parser;
   0      6      1    g       Lscala/Function1;


public scala.Function1 compose$mcVD$sp(scala.Function1);
  Signature: (Lscala/Function1;)Lscala/Function1;
  Code:
   Stack=2, Locals=2, Args_size=2
	aload_0
	aload_1
	invokestatic	Method scala/Function1$class.compose$mcVD$sp:(Lscala/Function1;Lscala/Function1;)Lscala/Function1;
	areturn
  Labels:
  LocalVariableTable: 
   Start  Length  Slot  Name   Signature
   0      6      0    this       Lscala/util/parsing/combinator/Parsers$Parser;
   0      6      1    g       Lscala/Function1;


public scala.Function1 compose$mcZD$sp(scala.Function1);
  Signature: (Lscala/Function1;)Lscala/Function1;
  Code:
   Stack=2, Locals=2, Args_size=2
	aload_0
	aload_1
	invokestatic	Method scala/Function1$class.compose$mcZD$sp:(Lscala/Function1;Lscala/Function1;)Lscala/Function1;
	areturn
  Labels:
  LocalVariableTable: 
   Start  Length  Slot  Name   Signature
   0      6      0    this       Lscala/util/parsing/combinator/Parsers$Parser;
   0      6      1    g       Lscala/Function1;


public scala.Function1 compose$mcID$sp(scala.Function1);
  Signature: (Lscala/Function1;)Lscala/Function1;
  Code:
   Stack=2, Locals=2, Args_size=2
	aload_0
	aload_1
	invokestatic	Method scala/Function1$class.compose$mcID$sp:(Lscala/Function1;Lscala/Function1;)Lscala/Function1;
	areturn
  Labels:
  LocalVariableTable: 
   Start  Length  Slot  Name   Signature
   0      6      0    this       Lscala/util/parsing/combinator/Parsers$Parser;
   0      6      1    g       Lscala/Function1;


public scala.Function1 compose$mcLD$sp(scala.Function1);
  Signature: (Lscala/Function1;)Lscala/Function1;
  Code:
   Stack=2, Locals=2, Args_size=2
	aload_0
	aload_1
	invokestatic	Method scala/Function1$class.compose$mcLD$sp:(Lscala/Function1;Lscala/Function1;)Lscala/Function1;
	areturn
  Labels:
  LocalVariableTable: 
   Start  Length  Slot  Name   Signature
   0      6      0    this       Lscala/util/parsing/combinator/Parsers$Parser;
   0      6      1    g       Lscala/Function1;


public scala.Function1 compose$mcDD$sp(scala.Function1);
  Signature: (Lscala/Function1;)Lscala/Function1;
  Code:
   Stack=2, Locals=2, Args_size=2
	aload_0
	aload_1
	invokestatic	Method scala/Function1$class.compose$mcDD$sp:(Lscala/Function1;Lscala/Function1;)Lscala/Function1;
	areturn
  Labels:
  LocalVariableTable: 
   Start  Length  Slot  Name   Signature
   0      6      0    this       Lscala/util/parsing/combinator/Parsers$Parser;
   0      6      1    g       Lscala/Function1;


public scala.Function1 andThen(scala.Function1);
  Signature: (Lscala/Function1;)Lscala/Function1;
  Code:
   Stack=2, Locals=2, Args_size=2
	aload_0
	aload_1
	invokestatic	Method scala/Function1$class.andThen:(Lscala/Function1;Lscala/Function1;)Lscala/Function1;
	areturn
  Labels:
  LocalVariableTable: 
   Start  Length  Slot  Name   Signature
   0      6      0    this       Lscala/util/parsing/combinator/Parsers$Parser;
   0      6      1    g       Lscala/Function1;


public scala.Function1 andThen$mcVI$sp(scala.Function1);
  Signature: (Lscala/Function1;)Lscala/Function1;
  Code:
   Stack=2, Locals=2, Args_size=2
	aload_0
	aload_1
	invokestatic	Method scala/Function1$class.andThen$mcVI$sp:(Lscala/Function1;Lscala/Function1;)Lscala/Function1;
	areturn
  Labels:
  LocalVariableTable: 
   Start  Length  Slot  Name   Signature
   0      6      0    this       Lscala/util/parsing/combinator/Parsers$Parser;
   0      6      1    g       Lscala/Function1;


public scala.Function1 andThen$mcZI$sp(scala.Function1);
  Signature: (Lscala/Function1;)Lscala/Function1;
  Code:
   Stack=2, Locals=2, Args_size=2
	aload_0
	aload_1
	invokestatic	Method scala/Function1$class.andThen$mcZI$sp:(Lscala/Function1;Lscala/Function1;)Lscala/Function1;
	areturn
  Labels:
  LocalVariableTable: 
   Start  Length  Slot  Name   Signature
   0      6      0    this       Lscala/util/parsing/combinator/Parsers$Parser;
   0      6      1    g       Lscala/Function1;


public scala.Function1 andThen$mcII$sp(scala.Function1);
  Signature: (Lscala/Function1;)Lscala/Function1;
  Code:
   Stack=2, Locals=2, Args_size=2
	aload_0
	aload_1
	invokestatic	Method scala/Function1$class.andThen$mcII$sp:(Lscala/Function1;Lscala/Function1;)Lscala/Function1;
	areturn
  Labels:
  LocalVariableTable: 
   Start  Length  Slot  Name   Signature
   0      6      0    this       Lscala/util/parsing/combinator/Parsers$Parser;
   0      6      1    g       Lscala/Function1;


public scala.Function1 andThen$mcLI$sp(scala.Function1);
  Signature: (Lscala/Function1;)Lscala/Function1;
  Code:
   Stack=2, Locals=2, Args_size=2
	aload_0
	aload_1
	invokestatic	Method scala/Function1$class.andThen$mcLI$sp:(Lscala/Function1;Lscala/Function1;)Lscala/Function1;
	areturn
  Labels:
  LocalVariableTable: 
   Start  Length  Slot  Name   Signature
   0      6      0    this       Lscala/util/parsing/combinator/Parsers$Parser;
   0      6      1    g       Lscala/Function1;


public scala.Function1 andThen$mcDI$sp(scala.Function1);
  Signature: (Lscala/Function1;)Lscala/Function1;
  Code:
   Stack=2, Locals=2, Args_size=2
	aload_0
	aload_1
	invokestatic	Method scala/Function1$class.andThen$mcDI$sp:(Lscala/Function1;Lscala/Function1;)Lscala/Function1;
	areturn
  Labels:
  LocalVariableTable: 
   Start  Length  Slot  Name   Signature
   0      6      0    this       Lscala/util/parsing/combinator/Parsers$Parser;
   0      6      1    g       Lscala/Function1;


public scala.Function1 andThen$mcVL$sp(scala.Function1);
  Signature: (Lscala/Function1;)Lscala/Function1;
  Code:
   Stack=2, Locals=2, Args_size=2
	aload_0
	aload_1
	invokestatic	Method scala/Function1$class.andThen$mcVL$sp:(Lscala/Function1;Lscala/Function1;)Lscala/Function1;
	areturn
  Labels:
  LocalVariableTable: 
   Start  Length  Slot  Name   Signature
   0      6      0    this       Lscala/util/parsing/combinator/Parsers$Parser;
   0      6      1    g       Lscala/Function1;


public scala.Function1 andThen$mcZL$sp(scala.Function1);
  Signature: (Lscala/Function1;)Lscala/Function1;
  Code:
   Stack=2, Locals=2, Args_size=2
	aload_0
	aload_1
	invokestatic	Method scala/Function1$class.andThen$mcZL$sp:(Lscala/Function1;Lscala/Function1;)Lscala/Function1;
	areturn
  Labels:
  LocalVariableTable: 
   Start  Length  Slot  Name   Signature
   0      6      0    this       Lscala/util/parsing/combinator/Parsers$Parser;
   0      6      1    g       Lscala/Function1;


public scala.Function1 andThen$mcIL$sp(scala.Function1);
  Signature: (Lscala/Function1;)Lscala/Function1;
  Code:
   Stack=2, Locals=2, Args_size=2
	aload_0
	aload_1
	invokestatic	Method scala/Function1$class.andThen$mcIL$sp:(Lscala/Function1;Lscala/Function1;)Lscala/Function1;
	areturn
  Labels:
  LocalVariableTable: 
   Start  Length  Slot  Name   Signature
   0      6      0    this       Lscala/util/parsing/combinator/Parsers$Parser;
   0      6      1    g       Lscala/Function1;


public scala.Function1 andThen$mcLL$sp(scala.Function1);
  Signature: (Lscala/Function1;)Lscala/Function1;
  Code:
   Stack=2, Locals=2, Args_size=2
	aload_0
	aload_1
	invokestatic	Method scala/Function1$class.andThen$mcLL$sp:(Lscala/Function1;Lscala/Function1;)Lscala/Function1;
	areturn
  Labels:
  LocalVariableTable: 
   Start  Length  Slot  Name   Signature
   0      6      0    this       Lscala/util/parsing/combinator/Parsers$Parser;
   0      6      1    g       Lscala/Function1;


public scala.Function1 andThen$mcDL$sp(scala.Function1);
  Signature: (Lscala/Function1;)Lscala/Function1;
  Code:
   Stack=2, Locals=2, Args_size=2
	aload_0
	aload_1
	invokestatic	Method scala/Function1$class.andThen$mcDL$sp:(Lscala/Function1;Lscala/Function1;)Lscala/Function1;
	areturn
  Labels:
  LocalVariableTable: 
   Start  Length  Slot  Name   Signature
   0      6      0    this       Lscala/util/parsing/combinator/Parsers$Parser;
   0      6      1    g       Lscala/Function1;


public scala.Function1 andThen$mcVD$sp(scala.Function1);
  Signature: (Lscala/Function1;)Lscala/Function1;
  Code:
   Stack=2, Locals=2, Args_size=2
	aload_0
	aload_1
	invokestatic	Method scala/Function1$class.andThen$mcVD$sp:(Lscala/Function1;Lscala/Function1;)Lscala/Function1;
	areturn
  Labels:
  LocalVariableTable: 
   Start  Length  Slot  Name   Signature
   0      6      0    this       Lscala/util/parsing/combinator/Parsers$Parser;
   0      6      1    g       Lscala/Function1;


public scala.Function1 andThen$mcZD$sp(scala.Function1);
  Signature: (Lscala/Function1;)Lscala/Function1;
  Code:
   Stack=2, Locals=2, Args_size=2
	aload_0
	aload_1
	invokestatic	Method scala/Function1$class.andThen$mcZD$sp:(Lscala/Function1;Lscala/Function1;)Lscala/Function1;
	areturn
  Labels:
  LocalVariableTable: 
   Start  Length  Slot  Name   Signature
   0      6      0    this       Lscala/util/parsing/combinator/Parsers$Parser;
   0      6      1    g       Lscala/Function1;


public scala.Function1 andThen$mcID$sp(scala.Function1);
  Signature: (Lscala/Function1;)Lscala/Function1;
  Code:
   Stack=2, Locals=2, Args_size=2
	aload_0
	aload_1
	invokestatic	Method scala/Function1$class.andThen$mcID$sp:(Lscala/Function1;Lscala/Function1;)Lscala/Function1;
	areturn
  Labels:
  LocalVariableTable: 
   Start  Length  Slot  Name   Signature
   0      6      0    this       Lscala/util/parsing/combinator/Parsers$Parser;
   0      6      1    g       Lscala/Function1;


public scala.Function1 andThen$mcLD$sp(scala.Function1);
  Signature: (Lscala/Function1;)Lscala/Function1;
  Code:
   Stack=2, Locals=2, Args_size=2
	aload_0
	aload_1
	invokestatic	Method scala/Function1$class.andThen$mcLD$sp:(Lscala/Function1;Lscala/Function1;)Lscala/Function1;
	areturn
  Labels:
  LocalVariableTable: 
   Start  Length  Slot  Name   Signature
   0      6      0    this       Lscala/util/parsing/combinator/Parsers$Parser;
   0      6      1    g       Lscala/Function1;


public scala.Function1 andThen$mcDD$sp(scala.Function1);
  Signature: (Lscala/Function1;)Lscala/Function1;
  Code:
   Stack=2, Locals=2, Args_size=2
	aload_0
	aload_1
	invokestatic	Method scala/Function1$class.andThen$mcDD$sp:(Lscala/Function1;Lscala/Function1;)Lscala/Function1;
	areturn
  Labels:
  LocalVariableTable: 
   Start  Length  Slot  Name   Signature
   0      6      0    this       Lscala/util/parsing/combinator/Parsers$Parser;
   0      6      1    g       Lscala/Function1;


private java.lang.String name();
  Signature: ()Ljava/lang/String;
  Code:
   Stack=1, Locals=1, Args_size=1
	aload_0
	getfield	Field name:Ljava/lang/String;
	areturn
  Labels:

private void name_$eq(java.lang.String);
  Signature: (Ljava/lang/String;)V
  Code:
   Stack=2, Locals=2, Args_size=2
	aload_0
	aload_1
	putfield	Field name:Ljava/lang/String;
	return
  Labels:

public scala.util.parsing.combinator.Parsers$Parser named(java.lang.String);
  Signature: (Ljava/lang/String;)Lscala/util/parsing/combinator/Parsers$Parser;
  Code:
   Stack=2, Locals=2, Args_size=2
	aload_0
	aload_1
	invokespecial	Method name_$eq:(Ljava/lang/String;)V
	aload_0
	areturn
  Labels:
  LocalVariableTable: 
   Start  Length  Slot  Name   Signature
   0      7      0    this       Lscala/util/parsing/combinator/Parsers$Parser;
   0      7      1    n       Ljava/lang/String;

  Signature: length = 0x2
   00 FFFFFFCD 

public java.lang.String toString();
  Signature: ()Ljava/lang/String;
  Code:
   Stack=2, Locals=1, Args_size=1
	new	class scala/collection/mutable/StringBuilder
	dup
	invokespecial	Method scala/collection/mutable/StringBuilder."<init>":()V
	ldc	String Parser (
	invokevirtual	Method scala/collection/mutable/StringBuilder.append:(Ljava/lang/Object;)Lscala/collection/mutable/StringBuilder;
	aload_0
	invokespecial	Method name:()Ljava/lang/String;
	invokevirtual	Method scala/collection/mutable/StringBuilder.append:(Ljava/lang/Object;)Lscala/collection/mutable/StringBuilder;
	ldc	String )
	invokevirtual	Method scala/collection/mutable/StringBuilder.append:(Ljava/lang/Object;)Lscala/collection/mutable/StringBuilder;
	invokevirtual	Method scala/collection/mutable/StringBuilder.toString:()Ljava/lang/String;
	areturn
  Labels:

public abstract scala.util.parsing.combinator.Parsers$ParseResult apply(scala.util.parsing.input.Reader);
  Signature: (Lscala/util/parsing/input/Reader;)Lscala/util/parsing/combinator/Parsers$ParseResult;
  Signature: length = 0x2
   00 FFFFFFE4 

public scala.util.parsing.combinator.Parsers$Parser flatMap(scala.Function1);
  Signature: (Lscala/Function1;)Lscala/util/parsing/combinator/Parsers$Parser;
  Code:
   Stack=5, Locals=2, Args_size=2
	aload_0
	invokevirtual	Method scala$util$parsing$combinator$Parsers$Parser$$$outer:()Lscala/util/parsing/combinator/Parsers;
	new	class scala/util/parsing/combinator/Parsers$Parser$$anonfun$flatMap$1
	dup
	aload_0
	aload_1
	invokespecial	Method scala/util/parsing/combinator/Parsers$Parser$$anonfun$flatMap$1."<init>":(Lscala/util/parsing/combinator/Parsers$Parser;Lscala/Function1;)V
	invokeinterface	InterfaceMethod scala/util/parsing/combinator/Parsers.Parser:(Lscala/Function1;)Lscala/util/parsing/combinator/Parsers$Parser;
	areturn
  Labels:
  LocalVariableTable: 
   Start  Length  Slot  Name   Signature
   0      19      0    this       Lscala/util/parsing/combinator/Parsers$Parser;
   0      19      1    f$3       Lscala/Function1;

  Signature: length = 0x2
   00 FFFFFFF6 

public scala.util.parsing.combinator.Parsers$Parser map(scala.Function1);
  Signature: (Lscala/Function1;)Lscala/util/parsing/combinator/Parsers$Parser;
  Code:
   Stack=5, Locals=2, Args_size=2
	aload_0
	invokevirtual	Method scala$util$parsing$combinator$Parsers$Parser$$$outer:()Lscala/util/parsing/combinator/Parsers;
	new	class scala/util/parsing/combinator/Parsers$Parser$$anonfun$map$1
	dup
	aload_0
	aload_1
	invokespecial	Method scala/util/parsing/combinator/Parsers$Parser$$anonfun$map$1."<init>":(Lscala/util/parsing/combinator/Parsers$Parser;Lscala/Function1;)V
	invokeinterface	InterfaceMethod scala/util/parsing/combinator/Parsers.Parser:(Lscala/Function1;)Lscala/util/parsing/combinator/Parsers$Parser;
	areturn
  Labels:
  LocalVariableTable: 
   Start  Length  Slot  Name   Signature
   0      19      0    this       Lscala/util/parsing/combinator/Parsers$Parser;
   0      19      1    f$4       Lscala/Function1;

  Signature: length = 0x2
   00 FFFFFFFC 

public scala.util.parsing.combinator.Parsers$Parser append(scala.Function0);
  Signature: (Lscala/Function0;)Lscala/util/parsing/combinator/Parsers$Parser;
  Code:
   Stack=5, Locals=2, Args_size=2
	aload_0
	invokevirtual	Method scala$util$parsing$combinator$Parsers$Parser$$$outer:()Lscala/util/parsing/combinator/Parsers;
	new	class scala/util/parsing/combinator/Parsers$Parser$$anonfun$append$1
	dup
	aload_0
	aload_1
	invokespecial	Method scala/util/parsing/combinator/Parsers$Parser$$anonfun$append$1."<init>":(Lscala/util/parsing/combinator/Parsers$Parser;Lscala/Function0;)V
	invokeinterface	InterfaceMethod scala/util/parsing/combinator/Parsers.Parser:(Lscala/Function1;)Lscala/util/parsing/combinator/Parsers$Parser;
	areturn
  Labels:
  LocalVariableTable: 
   Start  Length  Slot  Name   Signature
   0      19      0    this       Lscala/util/parsing/combinator/Parsers$Parser;
   0      19      1    p$4       Lscala/Function0;

  Signature: length = 0x2
   01 05 

public scala.util.parsing.combinator.Parsers$Parser $tilde(scala.Function0);
  Signature: (Lscala/Function0;)Lscala/util/parsing/combinator/Parsers$Parser;
  Code:
   Stack=5, Locals=2, Args_size=2
	aload_0
	new	class scala/util/parsing/combinator/Parsers$Parser$$anonfun$$tilde$1
	dup
	aload_0
	aload_1
	invokespecial	Method scala/util/parsing/combinator/Parsers$Parser$$anonfun$$tilde$1."<init>":(Lscala/util/parsing/combinator/Parsers$Parser;Lscala/Function0;)V
	invokevirtual	Method flatMap:(Lscala/Function1;)Lscala/util/parsing/combinator/Parsers$Parser;
	ldc_w	String ~
	invokevirtual	Method named:(Ljava/lang/String;)Lscala/util/parsing/combinator/Parsers$Parser;
	areturn
  Labels:
  LocalVariableTable: 
   Start  Length  Slot  Name   Signature
   0      20      0    this       Lscala/util/parsing/combinator/Parsers$Parser;
   0      20      1    p$3       Lscala/Function0;

  Signature: length = 0x2
   01 11 

public scala.util.parsing.combinator.Parsers$Parser $tilde$greater(scala.Function0);
  Signature: (Lscala/Function0;)Lscala/util/parsing/combinator/Parsers$Parser;
  Code:
   Stack=5, Locals=2, Args_size=2
	aload_0
	new	class scala/util/parsing/combinator/Parsers$Parser$$anonfun$$tilde$greater$1
	dup
	aload_0
	aload_1
	invokespecial	Method scala/util/parsing/combinator/Parsers$Parser$$anonfun$$tilde$greater$1."<init>":(Lscala/util/parsing/combinator/Parsers$Parser;Lscala/Function0;)V
	invokevirtual	Method flatMap:(Lscala/Function1;)Lscala/util/parsing/combinator/Parsers$Parser;
	ldc_w	String ~>
	invokevirtual	Method named:(Ljava/lang/String;)Lscala/util/parsing/combinator/Parsers$Parser;
	areturn
  Labels:
  LocalVariableTable: 
   Start  Length  Slot  Name   Signature
   0      20      0    this       Lscala/util/parsing/combinator/Parsers$Parser;
   0      20      1    p$5       Lscala/Function0;

  Signature: length = 0x2
   01 05 

public scala.util.parsing.combinator.Parsers$Parser $less$tilde(scala.Function0);
  Signature: (Lscala/Function0;)Lscala/util/parsing/combinator/Parsers$Parser;
  Code:
   Stack=5, Locals=2, Args_size=2
	aload_0
	new	class scala/util/parsing/combinator/Parsers$Parser$$anonfun$$less$tilde$1
	dup
	aload_0
	aload_1
	invokespecial	Method scala/util/parsing/combinator/Parsers$Parser$$anonfun$$less$tilde$1."<init>":(Lscala/util/parsing/combinator/Parsers$Parser;Lscala/Function0;)V
	invokevirtual	Method flatMap:(Lscala/Function1;)Lscala/util/parsing/combinator/Parsers$Parser;
	ldc_w	String <~
	invokevirtual	Method named:(Ljava/lang/String;)Lscala/util/parsing/combinator/Parsers$Parser;
	areturn
  Labels:
  LocalVariableTable: 
   Start  Length  Slot  Name   Signature
   0      20      0    this       Lscala/util/parsing/combinator/Parsers$Parser;
   0      20      1    p$6       Lscala/Function0;

  Signature: length = 0x2
   01 20 

public scala.util.parsing.combinator.Parsers$Parser $tilde$bang(scala.Function0);
  Signature: (Lscala/Function0;)Lscala/util/parsing/combinator/Parsers$Parser;
  Code:
   Stack=6, Locals=2, Args_size=2
	aload_0
	invokevirtual	Method scala$util$parsing$combinator$Parsers$Parser$$$outer:()Lscala/util/parsing/combinator/Parsers;
	aload_0
	new	class scala/util/parsing/combinator/Parsers$Parser$$anonfun$$tilde$bang$1
	dup
	aload_0
	aload_1
	invokespecial	Method scala/util/parsing/combinator/Parsers$Parser$$anonfun$$tilde$bang$1."<init>":(Lscala/util/parsing/combinator/Parsers$Parser;Lscala/Function0;)V
	invokevirtual	Method flatMap:(Lscala/Function1;)Lscala/util/parsing/combinator/Parsers$Parser;
	ldc_w	String ~!
	invokevirtual	Method named:(Ljava/lang/String;)Lscala/util/parsing/combinator/Parsers$Parser;
	invokeinterface	InterfaceMethod scala/util/parsing/combinator/Parsers.OnceParser:(Lscala/Function1;)Lscala/util/parsing/combinator/Parsers$OnceParser;
	checkcast	class scala/util/parsing/combinator/Parsers$Parser
	areturn
  Labels:
  LocalVariableTable: 
   Start  Length  Slot  Name   Signature
   0      32      0    this       Lscala/util/parsing/combinator/Parsers$Parser;
   0      32      1    p$7       Lscala/Function0;

  Signature: length = 0x2
   01 11 

public scala.util.parsing.combinator.Parsers$Parser $bar(scala.Function0);
  Signature: (Lscala/Function0;)Lscala/util/parsing/combinator/Parsers$Parser;
  Code:
   Stack=2, Locals=2, Args_size=2
	aload_0
	aload_1
	invokevirtual	Method append:(Lscala/Function0;)Lscala/util/parsing/combinator/Parsers$Parser;
	ldc_w	String |
	invokevirtual	Method named:(Ljava/lang/String;)Lscala/util/parsing/combinator/Parsers$Parser;
	areturn
  Labels:
  LocalVariableTable: 
   Start  Length  Slot  Name   Signature
   0      12      0    this       Lscala/util/parsing/combinator/Parsers$Parser;
   0      12      1    q       Lscala/Function0;

  Signature: length = 0x2
   01 05 

public scala.util.parsing.combinator.Parsers$Parser $bar$bar$bar(scala.Function0);
  Signature: (Lscala/Function0;)Lscala/util/parsing/combinator/Parsers$Parser;
  Code:
   Stack=4, Locals=2, Args_size=2
	new	class scala/util/parsing/combinator/Parsers$Parser$$anon$4
	dup
	aload_0
	aload_1
	invokespecial	Method scala/util/parsing/combinator/Parsers$Parser$$anon$4."<init>":(Lscala/util/parsing/combinator/Parsers$Parser;Lscala/Function0;)V
	areturn
  Labels:
  LocalVariableTable: 
   Start  Length  Slot  Name   Signature
   0      10      0    this       Lscala/util/parsing/combinator/Parsers$Parser;
   0      10      1    q$1       Lscala/Function0;

  Signature: length = 0x2
   01 05 

public scala.util.parsing.combinator.Parsers$Parser $up$up(scala.Function1);
  Signature: (Lscala/Function1;)Lscala/util/parsing/combinator/Parsers$Parser;
  Code:
   Stack=3, Locals=2, Args_size=2
	aload_0
	aload_1
	invokevirtual	Method map:(Lscala/Function1;)Lscala/util/parsing/combinator/Parsers$Parser;
	new	class scala/collection/mutable/StringBuilder
	dup
	invokespecial	Method scala/collection/mutable/StringBuilder."<init>":()V
	aload_0
	invokevirtual	Method toString:()Ljava/lang/String;
	invokevirtual	Method scala/collection/mutable/StringBuilder.append:(Ljava/lang/Object;)Lscala/collection/mutable/StringBuilder;
	ldc_w	String ^^
	invokevirtual	Method scala/collection/mutable/StringBuilder.append:(Ljava/lang/Object;)Lscala/collection/mutable/StringBuilder;
	invokevirtual	Method scala/collection/mutable/StringBuilder.toString:()Ljava/lang/String;
	invokevirtual	Method named:(Ljava/lang/String;)Lscala/util/parsing/combinator/Parsers$Parser;
	areturn
  Labels:
  LocalVariableTable: 
   Start  Length  Slot  Name   Signature
   0      32      0    this       Lscala/util/parsing/combinator/Parsers$Parser;
   0      32      1    f       Lscala/Function1;

  Signature: length = 0x2
   00 FFFFFFFC 

public scala.util.parsing.combinator.Parsers$Parser $up$up$up(java.lang.Object);
  Signature: (Ljava/lang/Object;)Lscala/util/parsing/combinator/Parsers$Parser;
  Code:
   Stack=5, Locals=2, Args_size=2
	aload_0
	new	class scala/util/parsing/combinator/Parsers$Parser$$anonfun$$up$up$up$1
	dup
	aload_0
	aload_1
	invokespecial	Method scala/util/parsing/combinator/Parsers$Parser$$anonfun$$up$up$up$1."<init>":(Lscala/util/parsing/combinator/Parsers$Parser;Ljava/lang/Object;)V
	invokevirtual	Method $up$up:(Lscala/Function1;)Lscala/util/parsing/combinator/Parsers$Parser;
	areturn
  Labels:
  LocalVariableTable: 
   Start  Length  Slot  Name   Signature
   0      14      0    this       Lscala/util/parsing/combinator/Parsers$Parser;
   0      14      1    r$1       Ljava/lang/Object;

  Signature: length = 0x2
   01 49 

public scala.util.parsing.combinator.Parsers$Parser $up$qmark(scala.PartialFunction, scala.Function1);
  Signature: (Lscala/PartialFunction;Lscala/Function1;)Lscala/util/parsing/combinator/Parsers$Parser;
  Code:
   Stack=6, Locals=3, Args_size=3
	aload_0
	invokevirtual	Method scala$util$parsing$combinator$Parsers$Parser$$$outer:()Lscala/util/parsing/combinator/Parsers;
	new	class scala/util/parsing/combinator/Parsers$Parser$$anonfun$$up$qmark$1
	dup
	aload_0
	aload_1
	aload_2
	invokespecial	Method scala/util/parsing/combinator/Parsers$Parser$$anonfun$$up$qmark$1."<init>":(Lscala/util/parsing/combinator/Parsers$Parser;Lscala/PartialFunction;Lscala/Function1;)V
	invokeinterface	InterfaceMethod scala/util/parsing/combinator/Parsers.Parser:(Lscala/Function1;)Lscala/util/parsing/combinator/Parsers$Parser;
	new	class scala/collection/mutable/StringBuilder
	dup
	invokespecial	Method scala/collection/mutable/StringBuilder."<init>":()V
	aload_0
	invokevirtual	Method toString:()Ljava/lang/String;
	invokevirtual	Method scala/collection/mutable/StringBuilder.append:(Ljava/lang/Object;)Lscala/collection/mutable/StringBuilder;
	ldc_w	String ^?
	invokevirtual	Method scala/collection/mutable/StringBuilder.append:(Ljava/lang/Object;)Lscala/collection/mutable/StringBuilder;
	invokevirtual	Method scala/collection/mutable/StringBuilder.toString:()Ljava/lang/String;
	invokevirtual	Method named:(Ljava/lang/String;)Lscala/util/parsing/combinator/Parsers$Parser;
	areturn
  Labels:
  LocalVariableTable: 
   Start  Length  Slot  Name   Signature
   0      46      0    this       Lscala/util/parsing/combinator/Parsers$Parser;
   0      46      1    f$5       Lscala/PartialFunction;
   0      46      2    error$1       Lscala/Function1;

  Signature: length = 0x2
   01 56 

public scala.util.parsing.combinator.Parsers$Parser $up$qmark(scala.PartialFunction);
  Signature: (Lscala/PartialFunction;)Lscala/util/parsing/combinator/Parsers$Parser;
  Code:
   Stack=5, Locals=2, Args_size=2
	aload_0
	aload_1
	new	class scala/util/parsing/combinator/Parsers$Parser$$anonfun$$up$qmark$2
	dup
	aload_0
	invokespecial	Method scala/util/parsing/combinator/Parsers$Parser$$anonfun$$up$qmark$2."<init>":(Lscala/util/parsing/combinator/Parsers$Parser;)V
	invokevirtual	Method $up$qmark:(Lscala/PartialFunction;Lscala/Function1;)Lscala/util/parsing/combinator/Parsers$Parser;
	areturn
  Labels:
  LocalVariableTable: 
   Start  Length  Slot  Name   Signature
   0      14      0    this       Lscala/util/parsing/combinator/Parsers$Parser;
   0      14      1    f       Lscala/PartialFunction;

  Signature: length = 0x2
   01 5F 

public scala.util.parsing.combinator.Parsers$Parser into(scala.Function1);
  Signature: (Lscala/Function1;)Lscala/util/parsing/combinator/Parsers$Parser;
  Code:
   Stack=2, Locals=2, Args_size=2
	aload_0
	aload_1
	invokevirtual	Method flatMap:(Lscala/Function1;)Lscala/util/parsing/combinator/Parsers$Parser;
	areturn
  Labels:
  LocalVariableTable: 
   Start  Length  Slot  Name   Signature
   0      6      0    this       Lscala/util/parsing/combinator/Parsers$Parser;
   0      6      1    fq       Lscala/Function1;

  Signature: length = 0x2
   00 FFFFFFF6 

public scala.util.parsing.combinator.Parsers$Parser $greater$greater(scala.Function1);
  Signature: (Lscala/Function1;)Lscala/util/parsing/combinator/Parsers$Parser;
  Code:
   Stack=2, Locals=2, Args_size=2
	aload_0
	aload_1
	invokevirtual	Method into:(Lscala/Function1;)Lscala/util/parsing/combinator/Parsers$Parser;
	areturn
  Labels:
  LocalVariableTable: 
   Start  Length  Slot  Name   Signature
   0      6      0    this       Lscala/util/parsing/combinator/Parsers$Parser;
   0      6      1    fq       Lscala/Function1;

  Signature: length = 0x2
   00 FFFFFFF6 

public scala.util.parsing.combinator.Parsers$Parser $times();
  Signature: ()Lscala/util/parsing/combinator/Parsers$Parser;
  Code:
   Stack=4, Locals=1, Args_size=1
	aload_0
	invokevirtual	Method scala$util$parsing$combinator$Parsers$Parser$$$outer:()Lscala/util/parsing/combinator/Parsers;
	new	class scala/util/parsing/combinator/Parsers$Parser$$anonfun$$times$1
	dup
	aload_0
	invokespecial	Method scala/util/parsing/combinator/Parsers$Parser$$anonfun$$times$1."<init>":(Lscala/util/parsing/combinator/Parsers$Parser;)V
	invokeinterface	InterfaceMethod scala/util/parsing/combinator/Parsers.rep:(Lscala/Function0;)Lscala/util/parsing/combinator/Parsers$Parser;
	areturn
  Labels:
  Signature: length = 0x2
   01 6D 

public scala.util.parsing.combinator.Parsers$Parser $times(scala.Function0);
  Signature: (Lscala/Function0;)Lscala/util/parsing/combinator/Parsers$Parser;
  Code:
   Stack=4, Locals=2, Args_size=2
	aload_0
	invokevirtual	Method scala$util$parsing$combinator$Parsers$Parser$$$outer:()Lscala/util/parsing/combinator/Parsers;
	new	class scala/util/parsing/combinator/Parsers$Parser$$anonfun$$times$2
	dup
	aload_0
	invokespecial	Method scala/util/parsing/combinator/Parsers$Parser$$anonfun$$times$2."<init>":(Lscala/util/parsing/combinator/Parsers$Parser;)V
	aload_1
	invokeinterface	InterfaceMethod scala/util/parsing/combinator/Parsers.chainl1:(Lscala/Function0;Lscala/Function0;)Lscala/util/parsing/combinator/Parsers$Parser;
	areturn
  Labels:
  LocalVariableTable: 
   Start  Length  Slot  Name   Signature
   0      19      0    this       Lscala/util/parsing/combinator/Parsers$Parser;
   0      19      1    sep       Lscala/Function0;

  Signature: length = 0x2
   01 76 

public scala.util.parsing.combinator.Parsers$Parser $plus();
  Signature: ()Lscala/util/parsing/combinator/Parsers$Parser;
  Code:
   Stack=4, Locals=1, Args_size=1
	aload_0
	invokevirtual	Method scala$util$parsing$combinator$Parsers$Parser$$$outer:()Lscala/util/parsing/combinator/Parsers;
	new	class scala/util/parsing/combinator/Parsers$Parser$$anonfun$$plus$1
	dup
	aload_0
	invokespecial	Method scala/util/parsing/combinator/Parsers$Parser$$anonfun$$plus$1."<init>":(Lscala/util/parsing/combinator/Parsers$Parser;)V
	invokeinterface	InterfaceMethod scala/util/parsing/combinator/Parsers.rep1:(Lscala/Function0;)Lscala/util/parsing/combinator/Parsers$Parser;
	areturn
  Labels:
  Signature: length = 0x2
   01 6D 

public scala.util.parsing.combinator.Parsers$Parser $qmark();
  Signature: ()Lscala/util/parsing/combinator/Parsers$Parser;
  Code:
   Stack=4, Locals=1, Args_size=1
	aload_0
	invokevirtual	Method scala$util$parsing$combinator$Parsers$Parser$$$outer:()Lscala/util/parsing/combinator/Parsers;
	new	class scala/util/parsing/combinator/Parsers$Parser$$anonfun$$qmark$1
	dup
	aload_0
	invokespecial	Method scala/util/parsing/combinator/Parsers$Parser$$anonfun$$qmark$1."<init>":(Lscala/util/parsing/combinator/Parsers$Parser;)V
	invokeinterface	InterfaceMethod scala/util/parsing/combinator/Parsers.opt:(Lscala/Function0;)Lscala/util/parsing/combinator/Parsers$Parser;
	areturn
  Labels:
  Signature: length = 0x2
   01 FFFFFF85 

public scala.util.parsing.combinator.Parsers scala$util$parsing$combinator$Parsers$Parser$$$outer();
  Signature: ()Lscala/util/parsing/combinator/Parsers;
  Code:
   Stack=1, Locals=1, Args_size=1
	aload_0
	getfield	Field $outer:Lscala/util/parsing/combinator/Parsers;
	areturn
  Labels:

public scala.util.parsing.combinator.Parsers$Parser(scala.util.parsing.combinator.Parsers);
  Signature: (Lscala/util/parsing/combinator/Parsers;)V
  Code:
   Stack=2, Locals=2, Args_size=2
	aload_1
	ifnonnull	l1 // aload_0
	new	class java/lang/NullPointerException
	dup
	invokespecial	Method java/lang/NullPointerException."<init>":()V
	athrow
l1	aload_0
	aload_1
	putfield	Field $outer:Lscala/util/parsing/combinator/Parsers;
	aload_0
	invokespecial	Method java/lang/Object."<init>":()V
	aload_0
	invokestatic	Method scala/Function1$class.$init$:(Lscala/Function1;)V
	aload_0
	ldc_w	String 
	putfield	Field name:Ljava/lang/String;
	return
  Labels:
   	l1 = 12 // aload_0
  LocalVariableTable: 
   Start  Length  Slot  Name   Signature
   0      33      0    this       Lscala/util/parsing/combinator/Parsers$Parser;
   0      33      1    $outer       Lscala/util/parsing/combinator/Parsers;

  Signature: length = 0x2
   01 FFFFFF88 

}

