Compiled from "Parsers.scala"
public final class scala.util.parsing.combinator.Parsers$$anon$2 extends scala.util.parsing.combinator.Parsers$Parser
  SourceFile: "Parsers.scala"
  Signature: length = 0x2
   00 6A 
  Scala: length = 0x
   
  InnerClass: 
   public abstract Parser=class scala/util/parsing/combinator/Parsers$Parser of class scala/util/parsing/combinator/Parsers
   public Failure=class scala/util/parsing/combinator/Parsers$Failure of class scala/util/parsing/combinator/Parsers
   public Success=class scala/util/parsing/combinator/Parsers$Success of class scala/util/parsing/combinator/Parsers
   public final $anon$2=class scala/util/parsing/combinator/Parsers$$anon$2 of class scala/util/parsing/combinator/Parsers
   public abstract NoSuccess=class scala/util/parsing/combinator/Parsers$NoSuccess of class scala/util/parsing/combinator/Parsers
   public abstract ParseResult=class scala/util/parsing/combinator/Parsers$ParseResult of class scala/util/parsing/combinator/Parsers
  minor version: 0
  major version: 49
  Constant pool:
Asciz	SourceFile;
Asciz	Parsers.scala;
Asciz	p$1;
Asciz	Lscala/util/parsing/combinator/Parsers$Parser;;
Asciz	$outer;
Asciz	Lscala/util/parsing/combinator/Parsers;;
Asciz	<init>;
Asciz	(Lscala/util/parsing/combinator/Parsers;Lscala/util/parsing/combinator/Parsers$Parser;)V;
Asciz	Code;
Asciz	LineNumberTable;
Asciz	java/lang/NullPointerException;
class	java/lang/NullPointerException
Asciz	()V;
NameAndType	"<init>":()V
Method	java/lang/NullPointerException."<init>":()V
Asciz	scala/util/parsing/combinator/Parsers$$anon$2;
class	scala/util/parsing/combinator/Parsers$$anon$2
NameAndType	$outer:Lscala/util/parsing/combinator/Parsers;
Field	scala/util/parsing/combinator/Parsers$$anon$2.$outer:Lscala/util/parsing/combinator/Parsers;
NameAndType	p$1:Lscala/util/parsing/combinator/Parsers$Parser;
Field	scala/util/parsing/combinator/Parsers$$anon$2.p$1:Lscala/util/parsing/combinator/Parsers$Parser;
Asciz	scala/util/parsing/combinator/Parsers$Parser;
class	scala/util/parsing/combinator/Parsers$Parser
Asciz	(Lscala/util/parsing/combinator/Parsers;)V;
NameAndType	"<init>":(Lscala/util/parsing/combinator/Parsers;)V
Method	scala/util/parsing/combinator/Parsers$Parser."<init>":(Lscala/util/parsing/combinator/Parsers;)V
Asciz	scala/util/parsing/combinator/Parsers;
class	scala/util/parsing/combinator/Parsers
Asciz	lastNoSuccess_$eq;
Asciz	(Lscala/util/parsing/combinator/Parsers$NoSuccess;)V;
NameAndType	lastNoSuccess_$eq:(Lscala/util/parsing/combinator/Parsers$NoSuccess;)V
InterfaceMethod	scala/util/parsing/combinator/Parsers.lastNoSuccess_$eq:(Lscala/util/parsing/combinator/Parsers$NoSuccess;)V
Asciz	this;
Asciz	Lscala/util/parsing/combinator/Parsers$$anon$2;;
Asciz	LocalVariableTable;
Asciz	apply;
Asciz	(Ljava/lang/Object;)Ljava/lang/Object;;
Asciz	scala/util/parsing/input/Reader;
class	scala/util/parsing/input/Reader
Asciz	(Lscala/util/parsing/input/Reader;)Lscala/util/parsing/combinator/Parsers$ParseResult;;
NameAndType	apply:(Lscala/util/parsing/input/Reader;)Lscala/util/parsing/combinator/Parsers$ParseResult;
Method	scala/util/parsing/combinator/Parsers$$anon$2.apply:(Lscala/util/parsing/input/Reader;)Lscala/util/parsing/combinator/Parsers$ParseResult;
Asciz	v1;
Asciz	Ljava/lang/Object;;
Method	scala/util/parsing/combinator/Parsers$Parser.apply:(Lscala/util/parsing/input/Reader;)Lscala/util/parsing/combinator/Parsers$ParseResult;
Asciz	scala/util/parsing/combinator/Parsers$Success;
class	scala/util/parsing/combinator/Parsers$Success
Asciz	next;
Asciz	()Lscala/util/parsing/input/Reader;;
NameAndType	next:()Lscala/util/parsing/input/Reader;
Method	scala/util/parsing/combinator/Parsers$Success.next:()Lscala/util/parsing/input/Reader;
Asciz	atEnd;
Asciz	()Z;
NameAndType	atEnd:()Z
Method	scala/util/parsing/input/Reader.atEnd:()Z
Asciz	lastNoSuccess;
Asciz	()Lscala/util/parsing/combinator/Parsers$NoSuccess;;
NameAndType	lastNoSuccess:()Lscala/util/parsing/combinator/Parsers$NoSuccess;
InterfaceMethod	scala/util/parsing/combinator/Parsers.lastNoSuccess:()Lscala/util/parsing/combinator/Parsers$NoSuccess;
Asciz	java/lang/Object;
class	java/lang/Object
Asciz	equals;
Asciz	(Ljava/lang/Object;)Z;
NameAndType	equals:(Ljava/lang/Object;)Z
Method	java/lang/Object.equals:(Ljava/lang/Object;)Z
Asciz	scala/util/parsing/combinator/Parsers$NoSuccess;
class	scala/util/parsing/combinator/Parsers$NoSuccess
Method	scala/util/parsing/combinator/Parsers$NoSuccess.next:()Lscala/util/parsing/input/Reader;
Asciz	pos;
Asciz	()Lscala/util/parsing/input/Position;;
NameAndType	pos:()Lscala/util/parsing/input/Position;
Method	scala/util/parsing/input/Reader.pos:()Lscala/util/parsing/input/Position;
Asciz	scala/util/parsing/input/Position;
class	scala/util/parsing/input/Position
Asciz	$less;
Asciz	(Lscala/util/parsing/input/Position;)Z;
NameAndType	$less:(Lscala/util/parsing/input/Position;)Z
InterfaceMethod	scala/util/parsing/input/Position.$less:(Lscala/util/parsing/input/Position;)Z
Asciz	scala/util/parsing/combinator/Parsers$Failure;
class	scala/util/parsing/combinator/Parsers$Failure
Asciz	end of input expected;
String	end of input expected
Asciz	(Lscala/util/parsing/combinator/Parsers;Ljava/lang/String;Lscala/util/parsing/input/Reader;)V;
NameAndType	"<init>":(Lscala/util/parsing/combinator/Parsers;Ljava/lang/String;Lscala/util/parsing/input/Reader;)V
Method	scala/util/parsing/combinator/Parsers$Failure."<init>":(Lscala/util/parsing/combinator/Parsers;Ljava/lang/String;Lscala/util/parsing/input/Reader;)V
Asciz	scala/MatchError;
class	scala/MatchError
Asciz	scala/util/parsing/combinator/Parsers$ParseResult;
class	scala/util/parsing/combinator/Parsers$ParseResult
Asciz	toString;
Asciz	()Ljava/lang/String;;
NameAndType	toString:()Ljava/lang/String;
Method	scala/util/parsing/combinator/Parsers$ParseResult.toString:()Ljava/lang/String;
Asciz	(Ljava/lang/String;)V;
NameAndType	"<init>":(Ljava/lang/String;)V
Method	scala/MatchError."<init>":(Ljava/lang/String;)V
Asciz	in;
Asciz	Lscala/util/parsing/input/Reader;;
Asciz	temp101;
Asciz	Lscala/util/parsing/combinator/Parsers$Success;;
Asciz	temp103;
Asciz	temp100;
Asciz	Lscala/util/parsing/combinator/Parsers$ParseResult;;
Asciz	(Lscala/util/parsing/input/Reader<Ljava/lang/Object;>;)Lscala/util/parsing/combinator/Parsers$ParseResult<TT;>;;
Asciz	Signature;
Asciz	Lscala/util/parsing/combinator/Parsers$Parser<TT;>;;
Asciz	Scala;
Asciz	InnerClasses;
Asciz	Parser;
Asciz	Failure;
Asciz	Success;
Asciz	$anon$2;
Asciz	NoSuccess;
Asciz	ParseResult;

{
public final scala.util.parsing.combinator.Parsers$Parser p$1;
  Signature: Lscala/util/parsing/combinator/Parsers$Parser;

public final scala.util.parsing.combinator.Parsers $outer;
  Signature: Lscala/util/parsing/combinator/Parsers;

public scala.util.parsing.combinator.Parsers$$anon$2(scala.util.parsing.combinator.Parsers, scala.util.parsing.combinator.Parsers$Parser);
  Signature: (Lscala/util/parsing/combinator/Parsers;Lscala/util/parsing/combinator/Parsers$Parser;)V
  Code:
   Stack=2, Locals=3, Args_size=3
	aload_1
	ifnonnull	l1 // aload_0
	new	class java/lang/NullPointerException
	dup
	invokespecial	Method java/lang/NullPointerException."<init>":()V
	athrow
l1	aload_0
	aload_1
	putfield	Field $outer:Lscala/util/parsing/combinator/Parsers;
	aload_0
	aload_2
	putfield	Field p$1:Lscala/util/parsing/combinator/Parsers$Parser;
	aload_0
	aload_1
	invokespecial	Method scala/util/parsing/combinator/Parsers$Parser."<init>":(Lscala/util/parsing/combinator/Parsers;)V
	aload_1
	aconst_null
	invokeinterface	InterfaceMethod scala/util/parsing/combinator/Parsers.lastNoSuccess_$eq:(Lscala/util/parsing/combinator/Parsers$NoSuccess;)V
	return
  Labels:
   	l1 = 12 // aload_0
  LocalVariableTable: 
   Start  Length  Slot  Name   Signature
   0      35      0    this       Lscala/util/parsing/combinator/Parsers$$anon$2;
   0      35      1    $outer       Lscala/util/parsing/combinator/Parsers;


public java.lang.Object apply(java.lang.Object);
  Signature: (Ljava/lang/Object;)Ljava/lang/Object;
  Code:
   Stack=2, Locals=2, Args_size=2
	aload_0
	aload_1
	checkcast	class scala/util/parsing/input/Reader
	invokevirtual	Method apply:(Lscala/util/parsing/input/Reader;)Lscala/util/parsing/combinator/Parsers$ParseResult;
	areturn
  Labels:
  LocalVariableTable: 
   Start  Length  Slot  Name   Signature
   0      9      0    this       Lscala/util/parsing/combinator/Parsers$$anon$2;
   0      9      1    v1       Ljava/lang/Object;


public scala.util.parsing.combinator.Parsers$ParseResult apply(scala.util.parsing.input.Reader);
  Signature: (Lscala/util/parsing/input/Reader;)Lscala/util/parsing/combinator/Parsers$ParseResult;
  Code:
   Stack=5, Locals=6, Args_size=2
	aload_0
	getfield	Field p$1:Lscala/util/parsing/combinator/Parsers$Parser;
	aload_1
	invokevirtual	Method scala/util/parsing/combinator/Parsers$Parser.apply:(Lscala/util/parsing/input/Reader;)Lscala/util/parsing/combinator/Parsers$ParseResult;
	astore	5
	aload	5
	instanceof	class scala/util/parsing/combinator/Parsers$Success
	ifeq	l1 // iconst_1
	aload	5
	checkcast	class scala/util/parsing/combinator/Parsers$Success
	astore_2
	aload_2
	invokevirtual	Method scala/util/parsing/combinator/Parsers$Success.next:()Lscala/util/parsing/input/Reader;
	astore	4
	iconst_1
	ifeq	l2 // new
	aload	4
	invokevirtual	Method scala/util/parsing/input/Reader.atEnd:()Z
	ifeq	l3 // aload_0
	aload_2
	goto	l4 // areturn
l3	aload_0
	getfield	Field $outer:Lscala/util/parsing/combinator/Parsers;
	invokeinterface	InterfaceMethod scala/util/parsing/combinator/Parsers.lastNoSuccess:()Lscala/util/parsing/combinator/Parsers$NoSuccess;
	dup
	astore_3
	ifnull	l5 // new
	aload_3
	aconst_null
	invokevirtual	Method java/lang/Object.equals:(Ljava/lang/Object;)Z
	ifne	l5 // new
	aload_0
	getfield	Field $outer:Lscala/util/parsing/combinator/Parsers;
	invokeinterface	InterfaceMethod scala/util/parsing/combinator/Parsers.lastNoSuccess:()Lscala/util/parsing/combinator/Parsers$NoSuccess;
	invokevirtual	Method scala/util/parsing/combinator/Parsers$NoSuccess.next:()Lscala/util/parsing/input/Reader;
	invokevirtual	Method scala/util/parsing/input/Reader.pos:()Lscala/util/parsing/input/Position;
	aload	4
	invokevirtual	Method scala/util/parsing/input/Reader.pos:()Lscala/util/parsing/input/Position;
	invokeinterface	InterfaceMethod scala/util/parsing/input/Position.$less:(Lscala/util/parsing/input/Position;)Z
	ifeq	l6 // aload_0
l5	new	class scala/util/parsing/combinator/Parsers$Failure
	dup
	aload_0
	getfield	Field $outer:Lscala/util/parsing/combinator/Parsers;
	ldc	String end of input expected
	aload	4
	invokespecial	Method scala/util/parsing/combinator/Parsers$Failure."<init>":(Lscala/util/parsing/combinator/Parsers;Ljava/lang/String;Lscala/util/parsing/input/Reader;)V
	goto	l4 // areturn
l6	aload_0
	getfield	Field $outer:Lscala/util/parsing/combinator/Parsers;
	invokeinterface	InterfaceMethod scala/util/parsing/combinator/Parsers.lastNoSuccess:()Lscala/util/parsing/combinator/Parsers$NoSuccess;
	goto	l4 // areturn
l2	new	class scala/MatchError
	dup
	aload	5
	invokevirtual	Method scala/util/parsing/combinator/Parsers$ParseResult.toString:()Ljava/lang/String;
	invokespecial	Method scala/MatchError."<init>":(Ljava/lang/String;)V
	athrow
l1	iconst_1
	ifeq	l7 // new
	aload_0
	getfield	Field $outer:Lscala/util/parsing/combinator/Parsers;
	invokeinterface	InterfaceMethod scala/util/parsing/combinator/Parsers.lastNoSuccess:()Lscala/util/parsing/combinator/Parsers$NoSuccess;
l4	areturn
l7	new	class scala/MatchError
	dup
	aload	5
	invokevirtual	Method scala/util/parsing/combinator/Parsers$ParseResult.toString:()Ljava/lang/String;
	invokespecial	Method scala/MatchError."<init>":(Ljava/lang/String;)V
	athrow
  Labels:
   	l3 = 46 // aload_0
   	l5 = 96 // new
   	l6 = 114 // aload_0
   	l2 = 126 // new
   	l1 = 139 // iconst_1
   	l4 = 152 // areturn
   	l7 = 153 // new
  LocalVariableTable: 
   Start  Length  Slot  Name   Signature
   0      166      0    this       Lscala/util/parsing/combinator/Parsers$$anon$2;
   0      166      1    in       Lscala/util/parsing/input/Reader;
   24      115      2    temp101       Lscala/util/parsing/combinator/Parsers$Success;
   30      109      4    temp103       Lscala/util/parsing/input/Reader;
   10      156      5    temp100       Lscala/util/parsing/combinator/Parsers$ParseResult;

  Signature: length = 0x2
   00 68 

}

