Compiled from "Parsers.scala"
public final class scala.util.parsing.combinator.Parsers$$anonfun$rep1$1 extends scala.runtime.AbstractFunction1 implements java.io.Serializable
  SourceFile: "Parsers.scala"
  Scala: length = 0x
   
  InnerClass: 
   public abstract Parser=class scala/util/parsing/combinator/Parsers$Parser of class scala/util/parsing/combinator/Parsers
   public Success=class scala/util/parsing/combinator/Parsers$Success of class scala/util/parsing/combinator/Parsers
   public abstract NoSuccess=class scala/util/parsing/combinator/Parsers$NoSuccess of class scala/util/parsing/combinator/Parsers
   public abstract ParseResult=class scala/util/parsing/combinator/Parsers$ParseResult of class scala/util/parsing/combinator/Parsers
   public final $anonfun$rep1$1=class scala/util/parsing/combinator/Parsers$$anonfun$rep1$1 of class scala/util/parsing/combinator/Parsers
  minor version: 0
  major version: 49
  Constant pool:
Asciz	SourceFile;
Asciz	Parsers.scala;
Asciz	<clinit>;
Asciz	()V;
Asciz	Code;
Asciz	serialVersionUID;
Asciz	J;
Asciz	scala/util/parsing/combinator/Parsers$$anonfun$rep1$1;
class	scala/util/parsing/combinator/Parsers$$anonfun$rep1$1
NameAndType	serialVersionUID:J
Field	scala/util/parsing/combinator/Parsers$$anonfun$rep1$1.serialVersionUID:J
Asciz	p$10;
Asciz	Lscala/Function0;;
Asciz	first$1;
Asciz	$outer;
Asciz	Lscala/util/parsing/combinator/Parsers;;
Asciz	apply;
Asciz	(Lscala/util/parsing/input/Reader;)Lscala/util/parsing/combinator/Parsers$ParseResult;;
Asciz	scala/collection/mutable/ListBuffer;
class	scala/collection/mutable/ListBuffer
Asciz	LineNumberTable;
Asciz	<init>;
NameAndType	"<init>":()V
Method	scala/collection/mutable/ListBuffer."<init>":()V
NameAndType	first$1:Lscala/Function0;
Field	scala/util/parsing/combinator/Parsers$$anonfun$rep1$1.first$1:Lscala/Function0;
Asciz	scala/Function0;
class	scala/Function0
Asciz	()Ljava/lang/Object;;
NameAndType	apply:()Ljava/lang/Object;
InterfaceMethod	scala/Function0.apply:()Ljava/lang/Object;
Asciz	scala/util/parsing/combinator/Parsers$Parser;
class	scala/util/parsing/combinator/Parsers$Parser
NameAndType	apply:(Lscala/util/parsing/input/Reader;)Lscala/util/parsing/combinator/Parsers$ParseResult;
Method	scala/util/parsing/combinator/Parsers$Parser.apply:(Lscala/util/parsing/input/Reader;)Lscala/util/parsing/combinator/Parsers$ParseResult;
Asciz	scala/util/parsing/combinator/Parsers$Success;
class	scala/util/parsing/combinator/Parsers$Success
Asciz	result;
NameAndType	result:()Ljava/lang/Object;
Method	scala/util/parsing/combinator/Parsers$Success.result:()Ljava/lang/Object;
Asciz	next;
Asciz	()Lscala/util/parsing/input/Reader;;
NameAndType	next:()Lscala/util/parsing/input/Reader;
Method	scala/util/parsing/combinator/Parsers$Success.next:()Lscala/util/parsing/input/Reader;
Asciz	$plus$eq;
Asciz	(Ljava/lang/Object;)Lscala/collection/mutable/ListBuffer;;
NameAndType	$plus$eq:(Ljava/lang/Object;)Lscala/collection/mutable/ListBuffer;
Method	scala/collection/mutable/ListBuffer.$plus$eq:(Ljava/lang/Object;)Lscala/collection/mutable/ListBuffer;
Asciz	continue$1;
Asciz	(Lscala/util/parsing/input/Reader;Lscala/collection/mutable/ListBuffer;)Lscala/util/parsing/combinator/Parsers$ParseResult;;
NameAndType	continue$1:(Lscala/util/parsing/input/Reader;Lscala/collection/mutable/ListBuffer;)Lscala/util/parsing/combinator/Parsers$ParseResult;
Method	scala/util/parsing/combinator/Parsers$$anonfun$rep1$1.continue$1:(Lscala/util/parsing/input/Reader;Lscala/collection/mutable/ListBuffer;)Lscala/util/parsing/combinator/Parsers$ParseResult;
Asciz	scala/util/parsing/combinator/Parsers$NoSuccess;
class	scala/util/parsing/combinator/Parsers$NoSuccess
Asciz	scala/MatchError;
class	scala/MatchError
Asciz	scala/util/parsing/combinator/Parsers$ParseResult;
class	scala/util/parsing/combinator/Parsers$ParseResult
Asciz	toString;
Asciz	()Ljava/lang/String;;
NameAndType	toString:()Ljava/lang/String;
Method	scala/util/parsing/combinator/Parsers$ParseResult.toString:()Ljava/lang/String;
Asciz	(Ljava/lang/String;)V;
NameAndType	"<init>":(Ljava/lang/String;)V
Method	scala/MatchError."<init>":(Ljava/lang/String;)V
Asciz	this;
Asciz	Lscala/util/parsing/combinator/Parsers$$anonfun$rep1$1;;
Asciz	in;
Asciz	Lscala/util/parsing/input/Reader;;
Asciz	temp75;
Asciz	Lscala/util/parsing/combinator/Parsers$Success;;
Asciz	temp76;
Asciz	Ljava/lang/Object;;
Asciz	temp77;
Asciz	elems$1;
Asciz	Lscala/collection/mutable/ListBuffer;;
Asciz	temp78;
Asciz	Lscala/util/parsing/combinator/Parsers$NoSuccess;;
Asciz	temp74;
Asciz	Lscala/util/parsing/combinator/Parsers$ParseResult;;
Asciz	LocalVariableTable;
Asciz	(Lscala/util/parsing/input/Reader<Ljava/lang/Object;>;)Lscala/util/parsing/combinator/Parsers$ParseResult<Lscala/collection/immutable/List<TT;>;>;;
Asciz	Signature;
Asciz	(Ljava/lang/Object;)Ljava/lang/Object;;
Asciz	scala/util/parsing/input/Reader;
class	scala/util/parsing/input/Reader
Method	scala/util/parsing/combinator/Parsers$$anonfun$rep1$1.apply:(Lscala/util/parsing/input/Reader;)Lscala/util/parsing/combinator/Parsers$ParseResult;
Asciz	v1;
Asciz	applyp$1;
Asciz	(Lscala/util/parsing/input/Reader;Lscala/collection/mutable/ListBuffer;Lscala/util/parsing/combinator/Parsers$Parser;)Lscala/util/parsing/combinator/Parsers$ParseResult;;
NameAndType	$outer:Lscala/util/parsing/combinator/Parsers;
Field	scala/util/parsing/combinator/Parsers$$anonfun$rep1$1.$outer:Lscala/util/parsing/combinator/Parsers;
Asciz	toList;
Asciz	()Lscala/collection/immutable/List;;
NameAndType	toList:()Lscala/collection/immutable/List;
Method	scala/collection/mutable/ListBuffer.toList:()Lscala/collection/immutable/List;
Asciz	(Lscala/util/parsing/combinator/Parsers;Ljava/lang/Object;Lscala/util/parsing/input/Reader;)V;
NameAndType	"<init>":(Lscala/util/parsing/combinator/Parsers;Ljava/lang/Object;Lscala/util/parsing/input/Reader;)V
Method	scala/util/parsing/combinator/Parsers$Success."<init>":(Lscala/util/parsing/combinator/Parsers;Ljava/lang/Object;Lscala/util/parsing/input/Reader;)V
Asciz	in0;
Asciz	temp70;
Asciz	temp71;
Asciz	temp72;
Asciz	temp73;
NameAndType	p$10:Lscala/Function0;
Field	scala/util/parsing/combinator/Parsers$$anonfun$rep1$1.p$10:Lscala/Function0;
NameAndType	applyp$1:(Lscala/util/parsing/input/Reader;Lscala/collection/mutable/ListBuffer;Lscala/util/parsing/combinator/Parsers$Parser;)Lscala/util/parsing/combinator/Parsers$ParseResult;
Method	scala/util/parsing/combinator/Parsers$$anonfun$rep1$1.applyp$1:(Lscala/util/parsing/input/Reader;Lscala/collection/mutable/ListBuffer;Lscala/util/parsing/combinator/Parsers$Parser;)Lscala/util/parsing/combinator/Parsers$ParseResult;
Asciz	p0$1;
Asciz	Lscala/util/parsing/combinator/Parsers$Parser;;
Asciz	(Lscala/util/parsing/combinator/Parsers;Lscala/Function0;Lscala/Function0;)V;
Asciz	java/lang/NullPointerException;
class	java/lang/NullPointerException
Method	java/lang/NullPointerException."<init>":()V
Asciz	scala/runtime/AbstractFunction1;
class	scala/runtime/AbstractFunction1
Method	scala/runtime/AbstractFunction1."<init>":()V
Asciz	Scala;
Asciz	InnerClasses;
Asciz	scala/util/parsing/combinator/Parsers;
class	scala/util/parsing/combinator/Parsers
Asciz	Parser;
Asciz	Success;
Asciz	NoSuccess;
Asciz	ParseResult;
Asciz	$anonfun$rep1$1;
Asciz	java/io/Serializable;
class	java/io/Serializable

{
public static final long serialVersionUID;
  Signature: J

private final scala.Function0 p$10;
  Signature: Lscala/Function0;

public final scala.Function0 first$1;
  Signature: Lscala/Function0;

private final scala.util.parsing.combinator.Parsers $outer;
  Signature: Lscala/util/parsing/combinator/Parsers;

public static {};
  Signature: ()V
  Code:
   Stack=2, Locals=0, Args_size=0
	lconst_0
	putstatic	Field serialVersionUID:J
	return
  Labels:

public final scala.util.parsing.combinator.Parsers$ParseResult apply(scala.util.parsing.input.Reader);
  Signature: (Lscala/util/parsing/input/Reader;)Lscala/util/parsing/combinator/Parsers$ParseResult;
  Code:
   Stack=3, Locals=8, Args_size=2
	new	class scala/collection/mutable/ListBuffer
	dup
	invokespecial	Method scala/collection/mutable/ListBuffer."<init>":()V
	astore	5
	aload_0
	getfield	Field first$1:Lscala/Function0;
	invokeinterface	InterfaceMethod scala/Function0.apply:()Ljava/lang/Object;
	checkcast	class scala/util/parsing/combinator/Parsers$Parser
	aload_1
	invokevirtual	Method scala/util/parsing/combinator/Parsers$Parser.apply:(Lscala/util/parsing/input/Reader;)Lscala/util/parsing/combinator/Parsers$ParseResult;
	astore	7
	aload	7
	instanceof	class scala/util/parsing/combinator/Parsers$Success
	ifeq	l1 // aload
	aload	7
	checkcast	class scala/util/parsing/combinator/Parsers$Success
	astore_2
	aload_2
	invokevirtual	Method scala/util/parsing/combinator/Parsers$Success.result:()Ljava/lang/Object;
	astore_3
	aload_2
	invokevirtual	Method scala/util/parsing/combinator/Parsers$Success.next:()Lscala/util/parsing/input/Reader;
	astore	4
	aload	5
	aload_3
	invokevirtual	Method scala/collection/mutable/ListBuffer.$plus$eq:(Ljava/lang/Object;)Lscala/collection/mutable/ListBuffer;
	pop
	aload_0
	aload	4
	aload	5
	invokespecial	Method continue$1:(Lscala/util/parsing/input/Reader;Lscala/collection/mutable/ListBuffer;)Lscala/util/parsing/combinator/Parsers$ParseResult;
	goto	l2 // areturn
l1	aload	7
	instanceof	class scala/util/parsing/combinator/Parsers$NoSuccess
	ifeq	l3 // new
	aload	7
	checkcast	class scala/util/parsing/combinator/Parsers$NoSuccess
	astore	6
	aload	6
l2	areturn
l3	new	class scala/MatchError
	dup
	aload	7
	invokevirtual	Method scala/util/parsing/combinator/Parsers$ParseResult.toString:()Ljava/lang/String;
	invokespecial	Method scala/MatchError."<init>":(Ljava/lang/String;)V
	athrow
  Labels:
   	l1 = 70 // aload
   	l2 = 87 // areturn
   	l3 = 88 // new
  LocalVariableTable: 
   Start  Length  Slot  Name   Signature
   0      101      0    this       Lscala/util/parsing/combinator/Parsers$$anonfun$rep1$1;
   0      101      1    in       Lscala/util/parsing/input/Reader;
   41      26      2    temp75       Lscala/util/parsing/combinator/Parsers$Success;
   46      21      3    temp76       Ljava/lang/Object;
   52      15      4    temp77       Lscala/util/parsing/input/Reader;
   9      92      5    elems$1       Lscala/collection/mutable/ListBuffer;
   85      2      6    temp78       Lscala/util/parsing/combinator/Parsers$NoSuccess;
   27      74      7    temp74       Lscala/util/parsing/combinator/Parsers$ParseResult;

  Signature: length = 0x2
   00 52 

public final java.lang.Object apply(java.lang.Object);
  Signature: (Ljava/lang/Object;)Ljava/lang/Object;
  Code:
   Stack=2, Locals=2, Args_size=2
	aload_0
	aload_1
	checkcast	class scala/util/parsing/input/Reader
	invokevirtual	Method apply:(Lscala/util/parsing/input/Reader;)Lscala/util/parsing/combinator/Parsers$ParseResult;
	areturn
  Labels:
  LocalVariableTable: 
   Start  Length  Slot  Name   Signature
   0      9      0    this       Lscala/util/parsing/combinator/Parsers$$anonfun$rep1$1;
   0      9      1    v1       Ljava/lang/Object;


private final scala.util.parsing.combinator.Parsers$ParseResult applyp$1(scala.util.parsing.input.Reader, scala.collection.mutable.ListBuffer, scala.util.parsing.combinator.Parsers$Parser);
  Signature: (Lscala/util/parsing/input/Reader;Lscala/collection/mutable/ListBuffer;Lscala/util/parsing/combinator/Parsers$Parser;)Lscala/util/parsing/combinator/Parsers$ParseResult;
  Code:
   Stack=5, Locals=8, Args_size=4
l2	aload_3
	aload_1
	invokevirtual	Method scala/util/parsing/combinator/Parsers$Parser.apply:(Lscala/util/parsing/input/Reader;)Lscala/util/parsing/combinator/Parsers$ParseResult;
	astore	4
	aload	4
	instanceof	class scala/util/parsing/combinator/Parsers$Success
	ifeq	l1 // new
	aload	4
	checkcast	class scala/util/parsing/combinator/Parsers$Success
	astore	5
	aload	5
	invokevirtual	Method scala/util/parsing/combinator/Parsers$Success.result:()Ljava/lang/Object;
	astore	6
	aload	5
	invokevirtual	Method scala/util/parsing/combinator/Parsers$Success.next:()Lscala/util/parsing/input/Reader;
	astore	7
	aload_2
	aload	6
	invokevirtual	Method scala/collection/mutable/ListBuffer.$plus$eq:(Ljava/lang/Object;)Lscala/collection/mutable/ListBuffer;
	pop
	aload	7
	astore_1
	goto	l2 // aload_3
l1	new	class scala/util/parsing/combinator/Parsers$Success
	dup
	aload_0
	getfield	Field $outer:Lscala/util/parsing/combinator/Parsers;
	aload_2
	invokevirtual	Method scala/collection/mutable/ListBuffer.toList:()Lscala/collection/immutable/List;
	aload_1
	invokespecial	Method scala/util/parsing/combinator/Parsers$Success."<init>":(Lscala/util/parsing/combinator/Parsers;Ljava/lang/Object;Lscala/util/parsing/input/Reader;)V
	areturn
  Labels:
   	l2 = 0 // aload_3
   	l1 = 49 // new
  LocalVariableTable: 
   Start  Length  Slot  Name   Signature
   0      66      0    this       Lscala/util/parsing/combinator/Parsers$$anonfun$rep1$1;
   0      66      1    in0       Lscala/util/parsing/input/Reader;
   7      59      4    temp70       Lscala/util/parsing/combinator/Parsers$ParseResult;
   22      27      5    temp71       Lscala/util/parsing/combinator/Parsers$Success;
   29      20      6    temp72       Ljava/lang/Object;
   36      13      7    temp73       Lscala/util/parsing/input/Reader;


private final scala.util.parsing.combinator.Parsers$ParseResult continue$1(scala.util.parsing.input.Reader, scala.collection.mutable.ListBuffer);
  Signature: (Lscala/util/parsing/input/Reader;Lscala/collection/mutable/ListBuffer;)Lscala/util/parsing/combinator/Parsers$ParseResult;
  Code:
   Stack=4, Locals=4, Args_size=3
	aload_0
	getfield	Field p$10:Lscala/Function0;
	invokeinterface	InterfaceMethod scala/Function0.apply:()Ljava/lang/Object;
	checkcast	class scala/util/parsing/combinator/Parsers$Parser
	astore_3
	aload_0
	aload_1
	aload_2
	aload_3
	invokespecial	Method applyp$1:(Lscala/util/parsing/input/Reader;Lscala/collection/mutable/ListBuffer;Lscala/util/parsing/combinator/Parsers$Parser;)Lscala/util/parsing/combinator/Parsers$ParseResult;
	areturn
  Labels:
  LocalVariableTable: 
   Start  Length  Slot  Name   Signature
   0      21      0    this       Lscala/util/parsing/combinator/Parsers$$anonfun$rep1$1;
   0      21      1    in       Lscala/util/parsing/input/Reader;
   13      7      3    p0$1       Lscala/util/parsing/combinator/Parsers$Parser;


public scala.util.parsing.combinator.Parsers$$anonfun$rep1$1(scala.util.parsing.combinator.Parsers, scala.Function0, scala.Function0);
  Signature: (Lscala/util/parsing/combinator/Parsers;Lscala/Function0;Lscala/Function0;)V
  Code:
   Stack=2, Locals=4, Args_size=4
	aload_1
	ifnonnull	l1 // aload_0
	new	class java/lang/NullPointerException
	dup
	invokespecial	Method java/lang/NullPointerException."<init>":()V
	athrow
l1	aload_0
	aload_1
	putfield	Field $outer:Lscala/util/parsing/combinator/Parsers;
	aload_0
	aload_2
	putfield	Field first$1:Lscala/Function0;
	aload_0
	aload_3
	putfield	Field p$10:Lscala/Function0;
	aload_0
	invokespecial	Method scala/runtime/AbstractFunction1."<init>":()V
	return
  Labels:
   	l1 = 12 // aload_0
  LocalVariableTable: 
   Start  Length  Slot  Name   Signature
   0      32      0    this       Lscala/util/parsing/combinator/Parsers$$anonfun$rep1$1;
   0      32      1    $outer       Lscala/util/parsing/combinator/Parsers;


}

