Compiled from "Parsers.scala"
public abstract class scala.util.parsing.combinator.Parsers$Parser extends java.lang.Object implements scala.Function1,scala.ScalaObject
  SourceFile: "Parsers.scala"
  Signature: length = 0x2
   00 FFFFFFEB 
  Scala: length = 0x
   
  InnerClass: 
   public abstract #107= #17 of #49; //Parser=class scala/util/parsing/combinator/Parsers$Parser of class scala/util/parsing/combinator/Parsers
   public abstract #240= #239 of #49; //ParseResult=class scala/util/parsing/combinator/Parsers$ParseResult of class scala/util/parsing/combinator/Parsers
   public final #241= #152 of #17; //$anon$4=class scala/util/parsing/combinator/Parsers$Parser$$anon$4 of class scala/util/parsing/combinator/Parsers$Parser
   public final #242= #202 of #17; //$anonfun$map$1=class scala/util/parsing/combinator/Parsers$Parser$$anonfun$map$1 of class scala/util/parsing/combinator/Parsers$Parser
   public final #243= #57 of #17; //$anonfun$$plus$1=class scala/util/parsing/combinator/Parsers$Parser$$anonfun$$plus$1 of class scala/util/parsing/combinator/Parsers$Parser
   public final #244= #198 of #17; //$anonfun$append$1=class scala/util/parsing/combinator/Parsers$Parser$$anonfun$append$1 of class scala/util/parsing/combinator/Parsers$Parser
   public final #245= #192 of #17; //$anonfun$$tilde$1=class scala/util/parsing/combinator/Parsers$Parser$$anonfun$$tilde$1 of class scala/util/parsing/combinator/Parsers$Parser
   public final #246= #75 of #17; //$anonfun$$times$1=class scala/util/parsing/combinator/Parsers$Parser$$anonfun$$times$1 of class scala/util/parsing/combinator/Parsers$Parser
   public final #247= #65 of #17; //$anonfun$$times$2=class scala/util/parsing/combinator/Parsers$Parser$$anonfun$$times$2 of class scala/util/parsing/combinator/Parsers$Parser
   public final #248= #44 of #17; //$anonfun$$qmark$1=class scala/util/parsing/combinator/Parsers$Parser$$anonfun$$qmark$1 of class scala/util/parsing/combinator/Parsers$Parser
   public final #249= #208 of #17; //$anonfun$flatMap$1=class scala/util/parsing/combinator/Parsers$Parser$$anonfun$flatMap$1 of class scala/util/parsing/combinator/Parsers$Parser
   public final #250= #134 of #17; //$anonfun$$up$up$up$1=class scala/util/parsing/combinator/Parsers$Parser$$anonfun$$up$up$up$1 of class scala/util/parsing/combinator/Parsers$Parser
   public final #251= #103 of #17; //$anonfun$$up$qmark$1=class scala/util/parsing/combinator/Parsers$Parser$$anonfun$$up$qmark$1 of class scala/util/parsing/combinator/Parsers$Parser
   public final #252= #94 of #17; //$anonfun$$up$qmark$2=class scala/util/parsing/combinator/Parsers$Parser$$anonfun$$up$qmark$2 of class scala/util/parsing/combinator/Parsers$Parser
   public final #253= #177 of #17; //$anonfun$$less$tilde$1=class scala/util/parsing/combinator/Parsers$Parser$$anonfun$$less$tilde$1 of class scala/util/parsing/combinator/Parsers$Parser
   public final #254= #166 of #17; //$anonfun$$tilde$bang$1=class scala/util/parsing/combinator/Parsers$Parser$$anonfun$$tilde$bang$1 of class scala/util/parsing/combinator/Parsers$Parser
   public final #255= #185 of #17; //$anonfun$$tilde$greater$1=class scala/util/parsing/combinator/Parsers$Parser$$anonfun$$tilde$greater$1 of class scala/util/parsing/combinator/Parsers$Parser
  minor version: 0
  major version: 49
  Constant pool:
const #1 = Asciz	SourceFile;
const #2 = Asciz	Parsers.scala;
const #3 = Asciz	$outer;
const #4 = Asciz	Lscala/util/parsing/combinator/Parsers;;
const #5 = Asciz	name;
const #6 = Asciz	Ljava/lang/String;;
const #7 = Asciz	<init>;
const #8 = Asciz	(Lscala/util/parsing/combinator/Parsers;)V;
const #9 = Asciz	Code;
const #10 = Asciz	LineNumberTable;
const #11 = Asciz	java/lang/NullPointerException;
const #12 = class	#11;	//  java/lang/NullPointerException
const #13 = Asciz	()V;
const #14 = NameAndType	#7:#13;//  "<init>":()V
const #15 = Method	#12.#14;	//  java/lang/NullPointerException."<init>":()V
const #16 = Asciz	scala/util/parsing/combinator/Parsers$Parser;
const #17 = class	#16;	//  scala/util/parsing/combinator/Parsers$Parser
const #18 = NameAndType	#3:#4;//  $outer:Lscala/util/parsing/combinator/Parsers;
const #19 = Field	#17.#18;	//  scala/util/parsing/combinator/Parsers$Parser.$outer:Lscala/util/parsing/combinator/Parsers;
const #20 = Asciz	java/lang/Object;
const #21 = class	#20;	//  java/lang/Object
const #22 = Method	#21.#14;	//  java/lang/Object."<init>":()V
const #23 = Asciz	scala/Function1$class;
const #24 = class	#23;	//  scala/Function1$class
const #25 = Asciz	$init$;
const #26 = Asciz	(Lscala/Function1;)V;
const #27 = NameAndType	#25:#26;//  $init$:(Lscala/Function1;)V
const #28 = Method	#24.#27;	//  scala/Function1$class.$init$:(Lscala/Function1;)V
const #29 = Asciz	;
const #30 = String	#29;	//  
const #31 = NameAndType	#5:#6;//  name:Ljava/lang/String;
const #32 = Field	#17.#31;	//  scala/util/parsing/combinator/Parsers$Parser.name:Ljava/lang/String;
const #33 = Asciz	this;
const #34 = Asciz	Lscala/util/parsing/combinator/Parsers$Parser;;
const #35 = Asciz	LocalVariableTable;
const #36 = Asciz	Signature;
const #37 = Asciz	scala$util$parsing$combinator$Parsers$Parser$$$outer;
const #38 = Asciz	()Lscala/util/parsing/combinator/Parsers;;
const #39 = Asciz	$qmark;
const #40 = Asciz	()Lscala/util/parsing/combinator/Parsers$Parser;;
const #41 = NameAndType	#37:#38;//  scala$util$parsing$combinator$Parsers$Parser$$$outer:()Lscala/util/parsing/combinator/Parsers;
const #42 = Method	#17.#41;	//  scala/util/parsing/combinator/Parsers$Parser.scala$util$parsing$combinator$Parsers$Parser$$$outer:()Lscala/util/parsing/combinator/Parsers;
const #43 = Asciz	scala/util/parsing/combinator/Parsers$Parser$$anonfun$$qmark$1;
const #44 = class	#43;	//  scala/util/parsing/combinator/Parsers$Parser$$anonfun$$qmark$1
const #45 = Asciz	(Lscala/util/parsing/combinator/Parsers$Parser;)V;
const #46 = NameAndType	#7:#45;//  "<init>":(Lscala/util/parsing/combinator/Parsers$Parser;)V
const #47 = Method	#44.#46;	//  scala/util/parsing/combinator/Parsers$Parser$$anonfun$$qmark$1."<init>":(Lscala/util/parsing/combinator/Parsers$Parser;)V
const #48 = Asciz	scala/util/parsing/combinator/Parsers;
const #49 = class	#48;	//  scala/util/parsing/combinator/Parsers
const #50 = Asciz	opt;
const #51 = Asciz	(Lscala/Function0;)Lscala/util/parsing/combinator/Parsers$Parser;;
const #52 = NameAndType	#50:#51;//  opt:(Lscala/Function0;)Lscala/util/parsing/combinator/Parsers$Parser;
const #53 = InterfaceMethod	#49.#52;	//  scala/util/parsing/combinator/Parsers.opt:(Lscala/Function0;)Lscala/util/parsing/combinator/Parsers$Parser;
const #54 = Asciz	()Lscala/util/parsing/combinator/Parsers$Parser<Lscala/Option<TT;>;>;;
const #55 = Asciz	$plus;
const #56 = Asciz	scala/util/parsing/combinator/Parsers$Parser$$anonfun$$plus$1;
const #57 = class	#56;	//  scala/util/parsing/combinator/Parsers$Parser$$anonfun$$plus$1
const #58 = Method	#57.#46;	//  scala/util/parsing/combinator/Parsers$Parser$$anonfun$$plus$1."<init>":(Lscala/util/parsing/combinator/Parsers$Parser;)V
const #59 = Asciz	rep1;
const #60 = NameAndType	#59:#51;//  rep1:(Lscala/Function0;)Lscala/util/parsing/combinator/Parsers$Parser;
const #61 = InterfaceMethod	#49.#60;	//  scala/util/parsing/combinator/Parsers.rep1:(Lscala/Function0;)Lscala/util/parsing/combinator/Parsers$Parser;
const #62 = Asciz	()Lscala/util/parsing/combinator/Parsers$Parser<Lscala/collection/immutable/List<TT;>;>;;
const #63 = Asciz	$times;
const #64 = Asciz	scala/util/parsing/combinator/Parsers$Parser$$anonfun$$times$2;
const #65 = class	#64;	//  scala/util/parsing/combinator/Parsers$Parser$$anonfun$$times$2
const #66 = Method	#65.#46;	//  scala/util/parsing/combinator/Parsers$Parser$$anonfun$$times$2."<init>":(Lscala/util/parsing/combinator/Parsers$Parser;)V
const #67 = Asciz	chainl1;
const #68 = Asciz	(Lscala/Function0;Lscala/Function0;)Lscala/util/parsing/combinator/Parsers$Parser;;
const #69 = NameAndType	#67:#68;//  chainl1:(Lscala/Function0;Lscala/Function0;)Lscala/util/parsing/combinator/Parsers$Parser;
const #70 = InterfaceMethod	#49.#69;	//  scala/util/parsing/combinator/Parsers.chainl1:(Lscala/Function0;Lscala/Function0;)Lscala/util/parsing/combinator/Parsers$Parser;
const #71 = Asciz	sep;
const #72 = Asciz	Lscala/Function0;;
const #73 = Asciz	<U:Ljava/lang/Object;>(Lscala/Function0<Lscala/util/parsing/combinator/Parsers$Parser<Lscala/Function2<TU;TU;TU;>;>;>;)Lscala/util/parsing/combinator/Parsers$Parser<TU;>;;
const #74 = Asciz	scala/util/parsing/combinator/Parsers$Parser$$anonfun$$times$1;
const #75 = class	#74;	//  scala/util/parsing/combinator/Parsers$Parser$$anonfun$$times$1
const #76 = Method	#75.#46;	//  scala/util/parsing/combinator/Parsers$Parser$$anonfun$$times$1."<init>":(Lscala/util/parsing/combinator/Parsers$Parser;)V
const #77 = Asciz	rep;
const #78 = NameAndType	#77:#51;//  rep:(Lscala/Function0;)Lscala/util/parsing/combinator/Parsers$Parser;
const #79 = InterfaceMethod	#49.#78;	//  scala/util/parsing/combinator/Parsers.rep:(Lscala/Function0;)Lscala/util/parsing/combinator/Parsers$Parser;
const #80 = Asciz	$greater$greater;
const #81 = Asciz	(Lscala/Function1;)Lscala/util/parsing/combinator/Parsers$Parser;;
const #82 = Asciz	into;
const #83 = NameAndType	#82:#81;//  into:(Lscala/Function1;)Lscala/util/parsing/combinator/Parsers$Parser;
const #84 = Method	#17.#83;	//  scala/util/parsing/combinator/Parsers$Parser.into:(Lscala/Function1;)Lscala/util/parsing/combinator/Parsers$Parser;
const #85 = Asciz	fq;
const #86 = Asciz	Lscala/Function1;;
const #87 = Asciz	<U:Ljava/lang/Object;>(Lscala/Function1<TT;Lscala/util/parsing/combinator/Parsers$Parser<TU;>;>;)Lscala/util/parsing/combinator/Parsers$Parser<TU;>;;
const #88 = Asciz	flatMap;
const #89 = NameAndType	#88:#81;//  flatMap:(Lscala/Function1;)Lscala/util/parsing/combinator/Parsers$Parser;
const #90 = Method	#17.#89;	//  scala/util/parsing/combinator/Parsers$Parser.flatMap:(Lscala/Function1;)Lscala/util/parsing/combinator/Parsers$Parser;
const #91 = Asciz	$up$qmark;
const #92 = Asciz	(Lscala/PartialFunction;)Lscala/util/parsing/combinator/Parsers$Parser;;
const #93 = Asciz	scala/util/parsing/combinator/Parsers$Parser$$anonfun$$up$qmark$2;
const #94 = class	#93;	//  scala/util/parsing/combinator/Parsers$Parser$$anonfun$$up$qmark$2
const #95 = Method	#94.#46;	//  scala/util/parsing/combinator/Parsers$Parser$$anonfun$$up$qmark$2."<init>":(Lscala/util/parsing/combinator/Parsers$Parser;)V
const #96 = Asciz	(Lscala/PartialFunction;Lscala/Function1;)Lscala/util/parsing/combinator/Parsers$Parser;;
const #97 = NameAndType	#91:#96;//  $up$qmark:(Lscala/PartialFunction;Lscala/Function1;)Lscala/util/parsing/combinator/Parsers$Parser;
const #98 = Method	#17.#97;	//  scala/util/parsing/combinator/Parsers$Parser.$up$qmark:(Lscala/PartialFunction;Lscala/Function1;)Lscala/util/parsing/combinator/Parsers$Parser;
const #99 = Asciz	f;
const #100 = Asciz	Lscala/PartialFunction;;
const #101 = Asciz	<U:Ljava/lang/Object;>(Lscala/PartialFunction<TT;TU;>;)Lscala/util/parsing/combinator/Parsers$Parser<TU;>;;
const #102 = Asciz	scala/util/parsing/combinator/Parsers$Parser$$anonfun$$up$qmark$1;
const #103 = class	#102;	//  scala/util/parsing/combinator/Parsers$Parser$$anonfun$$up$qmark$1
const #104 = Asciz	(Lscala/util/parsing/combinator/Parsers$Parser;Lscala/PartialFunction;Lscala/Function1;)V;
const #105 = NameAndType	#7:#104;//  "<init>":(Lscala/util/parsing/combinator/Parsers$Parser;Lscala/PartialFunction;Lscala/Function1;)V
const #106 = Method	#103.#105;	//  scala/util/parsing/combinator/Parsers$Parser$$anonfun$$up$qmark$1."<init>":(Lscala/util/parsing/combinator/Parsers$Parser;Lscala/PartialFunction;Lscala/Function1;)V
const #107 = Asciz	Parser;
const #108 = NameAndType	#107:#81;//  Parser:(Lscala/Function1;)Lscala/util/parsing/combinator/Parsers$Parser;
const #109 = InterfaceMethod	#49.#108;	//  scala/util/parsing/combinator/Parsers.Parser:(Lscala/Function1;)Lscala/util/parsing/combinator/Parsers$Parser;
const #110 = Asciz	scala/collection/mutable/StringBuilder;
const #111 = class	#110;	//  scala/collection/mutable/StringBuilder
const #112 = Method	#111.#14;	//  scala/collection/mutable/StringBuilder."<init>":()V
const #113 = Asciz	toString;
const #114 = Asciz	()Ljava/lang/String;;
const #115 = NameAndType	#113:#114;//  toString:()Ljava/lang/String;
const #116 = Method	#17.#115;	//  scala/util/parsing/combinator/Parsers$Parser.toString:()Ljava/lang/String;
const #117 = Asciz	append;
const #118 = Asciz	(Ljava/lang/Object;)Lscala/collection/mutable/StringBuilder;;
const #119 = NameAndType	#117:#118;//  append:(Ljava/lang/Object;)Lscala/collection/mutable/StringBuilder;
const #120 = Method	#111.#119;	//  scala/collection/mutable/StringBuilder.append:(Ljava/lang/Object;)Lscala/collection/mutable/StringBuilder;
const #121 = Asciz	^?;
const #122 = String	#121;	//  ^?
const #123 = Method	#111.#115;	//  scala/collection/mutable/StringBuilder.toString:()Ljava/lang/String;
const #124 = Asciz	named;
const #125 = Asciz	(Ljava/lang/String;)Lscala/util/parsing/combinator/Parsers$Parser;;
const #126 = NameAndType	#124:#125;//  named:(Ljava/lang/String;)Lscala/util/parsing/combinator/Parsers$Parser;
const #127 = Method	#17.#126;	//  scala/util/parsing/combinator/Parsers$Parser.named:(Ljava/lang/String;)Lscala/util/parsing/combinator/Parsers$Parser;
const #128 = Asciz	f$5;
const #129 = Asciz	error$1;
const #130 = Asciz	<U:Ljava/lang/Object;>(Lscala/PartialFunction<TT;TU;>;Lscala/Function1<TT;Ljava/lang/String;>;)Lscala/util/parsing/combinator/Parsers$Parser<TU;>;;
const #131 = Asciz	$up$up$up;
const #132 = Asciz	(Ljava/lang/Object;)Lscala/util/parsing/combinator/Parsers$Parser;;
const #133 = Asciz	scala/util/parsing/combinator/Parsers$Parser$$anonfun$$up$up$up$1;
const #134 = class	#133;	//  scala/util/parsing/combinator/Parsers$Parser$$anonfun$$up$up$up$1
const #135 = Asciz	(Lscala/util/parsing/combinator/Parsers$Parser;Ljava/lang/Object;)V;
const #136 = NameAndType	#7:#135;//  "<init>":(Lscala/util/parsing/combinator/Parsers$Parser;Ljava/lang/Object;)V
const #137 = Method	#134.#136;	//  scala/util/parsing/combinator/Parsers$Parser$$anonfun$$up$up$up$1."<init>":(Lscala/util/parsing/combinator/Parsers$Parser;Ljava/lang/Object;)V
const #138 = Asciz	$up$up;
const #139 = NameAndType	#138:#81;//  $up$up:(Lscala/Function1;)Lscala/util/parsing/combinator/Parsers$Parser;
const #140 = Method	#17.#139;	//  scala/util/parsing/combinator/Parsers$Parser.$up$up:(Lscala/Function1;)Lscala/util/parsing/combinator/Parsers$Parser;
const #141 = Asciz	r$1;
const #142 = Asciz	Ljava/lang/Object;;
const #143 = Asciz	<U:Ljava/lang/Object;>(TU;)Lscala/util/parsing/combinator/Parsers$Parser<TU;>;;
const #144 = Asciz	map;
const #145 = NameAndType	#144:#81;//  map:(Lscala/Function1;)Lscala/util/parsing/combinator/Parsers$Parser;
const #146 = Method	#17.#145;	//  scala/util/parsing/combinator/Parsers$Parser.map:(Lscala/Function1;)Lscala/util/parsing/combinator/Parsers$Parser;
const #147 = Asciz	^^;
const #148 = String	#147;	//  ^^
const #149 = Asciz	<U:Ljava/lang/Object;>(Lscala/Function1<TT;TU;>;)Lscala/util/parsing/combinator/Parsers$Parser<TU;>;;
const #150 = Asciz	$bar$bar$bar;
const #151 = Asciz	scala/util/parsing/combinator/Parsers$Parser$$anon$4;
const #152 = class	#151;	//  scala/util/parsing/combinator/Parsers$Parser$$anon$4
const #153 = Asciz	(Lscala/util/parsing/combinator/Parsers$Parser;Lscala/Function0;)V;
const #154 = NameAndType	#7:#153;//  "<init>":(Lscala/util/parsing/combinator/Parsers$Parser;Lscala/Function0;)V
const #155 = Method	#152.#154;	//  scala/util/parsing/combinator/Parsers$Parser$$anon$4."<init>":(Lscala/util/parsing/combinator/Parsers$Parser;Lscala/Function0;)V
const #156 = Asciz	q$1;
const #157 = Asciz	<U:Ljava/lang/Object;>(Lscala/Function0<Lscala/util/parsing/combinator/Parsers$Parser<TU;>;>;)Lscala/util/parsing/combinator/Parsers$Parser<TU;>;;
const #158 = Asciz	$bar;
const #159 = NameAndType	#117:#51;//  append:(Lscala/Function0;)Lscala/util/parsing/combinator/Parsers$Parser;
const #160 = Method	#17.#159;	//  scala/util/parsing/combinator/Parsers$Parser.append:(Lscala/Function0;)Lscala/util/parsing/combinator/Parsers$Parser;
const #161 = Asciz	|;
const #162 = String	#161;	//  |
const #163 = Asciz	q;
const #164 = Asciz	$tilde$bang;
const #165 = Asciz	scala/util/parsing/combinator/Parsers$Parser$$anonfun$$tilde$bang$1;
const #166 = class	#165;	//  scala/util/parsing/combinator/Parsers$Parser$$anonfun$$tilde$bang$1
const #167 = Method	#166.#154;	//  scala/util/parsing/combinator/Parsers$Parser$$anonfun$$tilde$bang$1."<init>":(Lscala/util/parsing/combinator/Parsers$Parser;Lscala/Function0;)V
const #168 = Asciz	~!;
const #169 = String	#168;	//  ~!
const #170 = Asciz	OnceParser;
const #171 = NameAndType	#170:#81;//  OnceParser:(Lscala/Function1;)Lscala/util/parsing/combinator/Parsers$Parser;
const #172 = InterfaceMethod	#49.#171;	//  scala/util/parsing/combinator/Parsers.OnceParser:(Lscala/Function1;)Lscala/util/parsing/combinator/Parsers$Parser;
const #173 = Asciz	p$7;
const #174 = Asciz	<U:Ljava/lang/Object;>(Lscala/Function0<Lscala/util/parsing/combinator/Parsers$Parser<TU;>;>;)Lscala/util/parsing/combinator/Parsers$Parser<Lscala/util/parsing/combinator/Parsers$$tilde<TT;TU;>;>;;
const #175 = Asciz	$less$tilde;
const #176 = Asciz	scala/util/parsing/combinator/Parsers$Parser$$anonfun$$less$tilde$1;
const #177 = class	#176;	//  scala/util/parsing/combinator/Parsers$Parser$$anonfun$$less$tilde$1
const #178 = Method	#177.#154;	//  scala/util/parsing/combinator/Parsers$Parser$$anonfun$$less$tilde$1."<init>":(Lscala/util/parsing/combinator/Parsers$Parser;Lscala/Function0;)V
const #179 = Asciz	<~;
const #180 = String	#179;	//  <~
const #181 = Asciz	p$6;
const #182 = Asciz	<U:Ljava/lang/Object;>(Lscala/Function0<Lscala/util/parsing/combinator/Parsers$Parser<TU;>;>;)Lscala/util/parsing/combinator/Parsers$Parser<TT;>;;
const #183 = Asciz	$tilde$greater;
const #184 = Asciz	scala/util/parsing/combinator/Parsers$Parser$$anonfun$$tilde$greater$1;
const #185 = class	#184;	//  scala/util/parsing/combinator/Parsers$Parser$$anonfun$$tilde$greater$1
const #186 = Method	#185.#154;	//  scala/util/parsing/combinator/Parsers$Parser$$anonfun$$tilde$greater$1."<init>":(Lscala/util/parsing/combinator/Parsers$Parser;Lscala/Function0;)V
const #187 = Asciz	~>;
const #188 = String	#187;	//  ~>
const #189 = Asciz	p$5;
const #190 = Asciz	$tilde;
const #191 = Asciz	scala/util/parsing/combinator/Parsers$Parser$$anonfun$$tilde$1;
const #192 = class	#191;	//  scala/util/parsing/combinator/Parsers$Parser$$anonfun$$tilde$1
const #193 = Method	#192.#154;	//  scala/util/parsing/combinator/Parsers$Parser$$anonfun$$tilde$1."<init>":(Lscala/util/parsing/combinator/Parsers$Parser;Lscala/Function0;)V
const #194 = Asciz	~;
const #195 = String	#194;	//  ~
const #196 = Asciz	p$3;
const #197 = Asciz	scala/util/parsing/combinator/Parsers$Parser$$anonfun$append$1;
const #198 = class	#197;	//  scala/util/parsing/combinator/Parsers$Parser$$anonfun$append$1
const #199 = Method	#198.#154;	//  scala/util/parsing/combinator/Parsers$Parser$$anonfun$append$1."<init>":(Lscala/util/parsing/combinator/Parsers$Parser;Lscala/Function0;)V
const #200 = Asciz	p$4;
const #201 = Asciz	scala/util/parsing/combinator/Parsers$Parser$$anonfun$map$1;
const #202 = class	#201;	//  scala/util/parsing/combinator/Parsers$Parser$$anonfun$map$1
const #203 = Asciz	(Lscala/util/parsing/combinator/Parsers$Parser;Lscala/Function1;)V;
const #204 = NameAndType	#7:#203;//  "<init>":(Lscala/util/parsing/combinator/Parsers$Parser;Lscala/Function1;)V
const #205 = Method	#202.#204;	//  scala/util/parsing/combinator/Parsers$Parser$$anonfun$map$1."<init>":(Lscala/util/parsing/combinator/Parsers$Parser;Lscala/Function1;)V
const #206 = Asciz	f$4;
const #207 = Asciz	scala/util/parsing/combinator/Parsers$Parser$$anonfun$flatMap$1;
const #208 = class	#207;	//  scala/util/parsing/combinator/Parsers$Parser$$anonfun$flatMap$1
const #209 = Method	#208.#204;	//  scala/util/parsing/combinator/Parsers$Parser$$anonfun$flatMap$1."<init>":(Lscala/util/parsing/combinator/Parsers$Parser;Lscala/Function1;)V
const #210 = Asciz	f$3;
const #211 = Asciz	apply;
const #212 = Asciz	(Lscala/util/parsing/input/Reader;)Lscala/util/parsing/combinator/Parsers$ParseResult;;
const #213 = Asciz	(Lscala/util/parsing/input/Reader<Ljava/lang/Object;>;)Lscala/util/parsing/combinator/Parsers$ParseResult<TT;>;;
const #214 = Asciz	Parser (;
const #215 = String	#214;	//  Parser (
const #216 = NameAndType	#5:#114;//  name:()Ljava/lang/String;
const #217 = Method	#17.#216;	//  scala/util/parsing/combinator/Parsers$Parser.name:()Ljava/lang/String;
const #218 = Asciz	);
const #219 = String	#218;	//  )
const #220 = Asciz	name_$eq;
const #221 = Asciz	(Ljava/lang/String;)V;
const #222 = NameAndType	#220:#221;//  name_$eq:(Ljava/lang/String;)V
const #223 = Method	#17.#222;	//  scala/util/parsing/combinator/Parsers$Parser.name_$eq:(Ljava/lang/String;)V
const #224 = Asciz	n;
const #225 = Asciz	(Ljava/lang/String;)Lscala/util/parsing/combinator/Parsers$Parser<TT;>;;
const #226 = Asciz	andThen;
const #227 = Asciz	(Lscala/Function1;)Lscala/Function1;;
const #228 = Asciz	(Lscala/Function1;Lscala/Function1;)Lscala/Function1;;
const #229 = NameAndType	#226:#228;//  andThen:(Lscala/Function1;Lscala/Function1;)Lscala/Function1;
const #230 = Method	#24.#229;	//  scala/Function1$class.andThen:(Lscala/Function1;Lscala/Function1;)Lscala/Function1;
const #231 = Asciz	g;
const #232 = Asciz	compose;
const #233 = NameAndType	#232:#228;//  compose:(Lscala/Function1;Lscala/Function1;)Lscala/Function1;
const #234 = Method	#24.#233;	//  scala/Function1$class.compose:(Lscala/Function1;Lscala/Function1;)Lscala/Function1;
const #235 = Asciz	<T:Ljava/lang/Object;>Ljava/lang/Object;Lscala/Function1<Lscala/util/parsing/input/Reader<Ljava/lang/Object;>;Lscala/util/parsing/combinator/Parsers$ParseResult<TT;>;>;Lscala/ScalaObject;;
const #236 = Asciz	Scala;
const #237 = Asciz	InnerClasses;
const #238 = Asciz	scala/util/parsing/combinator/Parsers$ParseResult;
const #239 = class	#238;	//  scala/util/parsing/combinator/Parsers$ParseResult
const #240 = Asciz	ParseResult;
const #241 = Asciz	$anon$4;
const #242 = Asciz	$anonfun$map$1;
const #243 = Asciz	$anonfun$$plus$1;
const #244 = Asciz	$anonfun$append$1;
const #245 = Asciz	$anonfun$$tilde$1;
const #246 = Asciz	$anonfun$$times$1;
const #247 = Asciz	$anonfun$$times$2;
const #248 = Asciz	$anonfun$$qmark$1;
const #249 = Asciz	$anonfun$flatMap$1;
const #250 = Asciz	$anonfun$$up$up$up$1;
const #251 = Asciz	$anonfun$$up$qmark$1;
const #252 = Asciz	$anonfun$$up$qmark$2;
const #253 = Asciz	$anonfun$$less$tilde$1;
const #254 = Asciz	$anonfun$$tilde$bang$1;
const #255 = Asciz	$anonfun$$tilde$greater$1;
const #256 = Asciz	scala/Function1;
const #257 = class	#256;	//  scala/Function1
const #258 = Asciz	scala/ScalaObject;
const #259 = class	#258;	//  scala/ScalaObject

{
public final scala.util.parsing.combinator.Parsers $outer;

public scala.util.parsing.combinator.Parsers$Parser(scala.util.parsing.combinator.Parsers);
  Code:
   Stack=2, Locals=2, Args_size=2
   0:	aload_1
   1:	ifnonnull	12
   4:	new	#12; //class java/lang/NullPointerException
   7:	dup
   8:	invokespecial	#15; //Method java/lang/NullPointerException."<init>":()V
   11:	athrow
   12:	aload_0
   13:	aload_1
   14:	putfield	#19; //Field $outer:Lscala/util/parsing/combinator/Parsers;
   17:	aload_0
   18:	invokespecial	#22; //Method java/lang/Object."<init>":()V
   21:	aload_0
   22:	invokestatic	#28; //Method scala/Function1$class.$init$:(Lscala/Function1;)V
   25:	aload_0
   26:	ldc	#30; //String 
   28:	putfield	#32; //Field name:Ljava/lang/String;
   31:	return
  LineNumberTable: 
   line 204: 0
   line 205: 25

  LocalVariableTable: 
   Start  Length  Slot  Name   Signature
   0      32      0    this       Lscala/util/parsing/combinator/Parsers$Parser;
   0      32      1    $outer       Lscala/util/parsing/combinator/Parsers;

  Signature: length = 0x2
   00 08 

public scala.util.parsing.combinator.Parsers scala$util$parsing$combinator$Parsers$Parser$$$outer();
  Code:
   Stack=1, Locals=1, Args_size=1
   0:	aload_0
   1:	getfield	#19; //Field $outer:Lscala/util/parsing/combinator/Parsers;
   4:	areturn
  LineNumberTable: 
   line 204: 0


public scala.util.parsing.combinator.Parsers$Parser $qmark();
  Code:
   Stack=4, Locals=1, Args_size=1
   0:	aload_0
   1:	invokevirtual	#42; //Method scala$util$parsing$combinator$Parsers$Parser$$$outer:()Lscala/util/parsing/combinator/Parsers;
   4:	new	#44; //class scala/util/parsing/combinator/Parsers$Parser$$anonfun$$qmark$1
   7:	dup
   8:	aload_0
   9:	invokespecial	#47; //Method scala/util/parsing/combinator/Parsers$Parser$$anonfun$$qmark$1."<init>":(Lscala/util/parsing/combinator/Parsers$Parser;)V
   12:	invokeinterface	#53,  2; //InterfaceMethod scala/util/parsing/combinator/Parsers.opt:(Lscala/Function0;)Lscala/util/parsing/combinator/Parsers$Parser;
   17:	areturn
  LineNumberTable: 
   line 411: 0

  Signature: length = 0x2
   00 36 

public scala.util.parsing.combinator.Parsers$Parser $plus();
  Code:
   Stack=4, Locals=1, Args_size=1
   0:	aload_0
   1:	invokevirtual	#42; //Method scala$util$parsing$combinator$Parsers$Parser$$$outer:()Lscala/util/parsing/combinator/Parsers;
   4:	new	#57; //class scala/util/parsing/combinator/Parsers$Parser$$anonfun$$plus$1
   7:	dup
   8:	aload_0
   9:	invokespecial	#58; //Method scala/util/parsing/combinator/Parsers$Parser$$anonfun$$plus$1."<init>":(Lscala/util/parsing/combinator/Parsers$Parser;)V
   12:	invokeinterface	#61,  2; //InterfaceMethod scala/util/parsing/combinator/Parsers.rep1:(Lscala/Function0;)Lscala/util/parsing/combinator/Parsers$Parser;
   17:	areturn
  LineNumberTable: 
   line 405: 0

  Signature: length = 0x2
   00 3E 

public scala.util.parsing.combinator.Parsers$Parser $times(scala.Function0);
  Code:
   Stack=4, Locals=2, Args_size=2
   0:	aload_0
   1:	invokevirtual	#42; //Method scala$util$parsing$combinator$Parsers$Parser$$$outer:()Lscala/util/parsing/combinator/Parsers;
   4:	new	#65; //class scala/util/parsing/combinator/Parsers$Parser$$anonfun$$times$2
   7:	dup
   8:	aload_0
   9:	invokespecial	#66; //Method scala/util/parsing/combinator/Parsers$Parser$$anonfun$$times$2."<init>":(Lscala/util/parsing/combinator/Parsers$Parser;)V
   12:	aload_1
   13:	invokeinterface	#70,  3; //InterfaceMethod scala/util/parsing/combinator/Parsers.chainl1:(Lscala/Function0;Lscala/Function0;)Lscala/util/parsing/combinator/Parsers$Parser;
   18:	areturn
  LineNumberTable: 
   line 397: 0

  LocalVariableTable: 
   Start  Length  Slot  Name   Signature
   0      19      0    this       Lscala/util/parsing/combinator/Parsers$Parser;
   0      19      1    sep       Lscala/Function0;

  Signature: length = 0x2
   00 49 

public scala.util.parsing.combinator.Parsers$Parser $times();
  Code:
   Stack=4, Locals=1, Args_size=1
   0:	aload_0
   1:	invokevirtual	#42; //Method scala$util$parsing$combinator$Parsers$Parser$$$outer:()Lscala/util/parsing/combinator/Parsers;
   4:	new	#75; //class scala/util/parsing/combinator/Parsers$Parser$$anonfun$$times$1
   7:	dup
   8:	aload_0
   9:	invokespecial	#76; //Method scala/util/parsing/combinator/Parsers$Parser$$anonfun$$times$1."<init>":(Lscala/util/parsing/combinator/Parsers$Parser;)V
   12:	invokeinterface	#79,  2; //InterfaceMethod scala/util/parsing/combinator/Parsers.rep:(Lscala/Function0;)Lscala/util/parsing/combinator/Parsers$Parser;
   17:	areturn
  LineNumberTable: 
   line 390: 0

  Signature: length = 0x2
   00 3E 

public scala.util.parsing.combinator.Parsers$Parser $greater$greater(scala.Function1);
  Code:
   Stack=2, Locals=2, Args_size=2
   0:	aload_0
   1:	aload_1
   2:	invokevirtual	#84; //Method into:(Lscala/Function1;)Lscala/util/parsing/combinator/Parsers$Parser;
   5:	areturn
  LineNumberTable: 
   line 383: 0

  LocalVariableTable: 
   Start  Length  Slot  Name   Signature
   0      6      0    this       Lscala/util/parsing/combinator/Parsers$Parser;
   0      6      1    fq       Lscala/Function1;

  Signature: length = 0x2
   00 57 

public scala.util.parsing.combinator.Parsers$Parser into(scala.Function1);
  Code:
   Stack=2, Locals=2, Args_size=2
   0:	aload_0
   1:	aload_1
   2:	invokevirtual	#90; //Method flatMap:(Lscala/Function1;)Lscala/util/parsing/combinator/Parsers$Parser;
   5:	areturn
  LineNumberTable: 
   line 378: 0

  LocalVariableTable: 
   Start  Length  Slot  Name   Signature
   0      6      0    this       Lscala/util/parsing/combinator/Parsers$Parser;
   0      6      1    fq       Lscala/Function1;

  Signature: length = 0x2
   00 57 

public scala.util.parsing.combinator.Parsers$Parser $up$qmark(scala.PartialFunction);
  Code:
   Stack=5, Locals=2, Args_size=2
   0:	aload_0
   1:	aload_1
   2:	new	#94; //class scala/util/parsing/combinator/Parsers$Parser$$anonfun$$up$qmark$2
   5:	dup
   6:	aload_0
   7:	invokespecial	#95; //Method scala/util/parsing/combinator/Parsers$Parser$$anonfun$$up$qmark$2."<init>":(Lscala/util/parsing/combinator/Parsers$Parser;)V
   10:	invokevirtual	#98; //Method $up$qmark:(Lscala/PartialFunction;Lscala/Function1;)Lscala/util/parsing/combinator/Parsers$Parser;
   13:	areturn
  LineNumberTable: 
   line 361: 0

  LocalVariableTable: 
   Start  Length  Slot  Name   Signature
   0      14      0    this       Lscala/util/parsing/combinator/Parsers$Parser;
   0      14      1    f       Lscala/PartialFunction;

  Signature: length = 0x2
   00 65 

public scala.util.parsing.combinator.Parsers$Parser $up$qmark(scala.PartialFunction, scala.Function1);
  Code:
   Stack=6, Locals=3, Args_size=3
   0:	aload_0
   1:	invokevirtual	#42; //Method scala$util$parsing$combinator$Parsers$Parser$$$outer:()Lscala/util/parsing/combinator/Parsers;
   4:	new	#103; //class scala/util/parsing/combinator/Parsers$Parser$$anonfun$$up$qmark$1
   7:	dup
   8:	aload_0
   9:	aload_1
   10:	aload_2
   11:	invokespecial	#106; //Method scala/util/parsing/combinator/Parsers$Parser$$anonfun$$up$qmark$1."<init>":(Lscala/util/parsing/combinator/Parsers$Parser;Lscala/PartialFunction;Lscala/Function1;)V
   14:	invokeinterface	#109,  2; //InterfaceMethod scala/util/parsing/combinator/Parsers.Parser:(Lscala/Function1;)Lscala/util/parsing/combinator/Parsers$Parser;
   19:	new	#111; //class scala/collection/mutable/StringBuilder
   22:	dup
   23:	invokespecial	#112; //Method scala/collection/mutable/StringBuilder."<init>":()V
   26:	aload_0
   27:	invokevirtual	#116; //Method toString:()Ljava/lang/String;
   30:	invokevirtual	#120; //Method scala/collection/mutable/StringBuilder.append:(Ljava/lang/Object;)Lscala/collection/mutable/StringBuilder;
   33:	ldc	#122; //String ^?
   35:	invokevirtual	#120; //Method scala/collection/mutable/StringBuilder.append:(Ljava/lang/Object;)Lscala/collection/mutable/StringBuilder;
   38:	invokevirtual	#123; //Method scala/collection/mutable/StringBuilder.toString:()Ljava/lang/String;
   41:	invokevirtual	#127; //Method named:(Ljava/lang/String;)Lscala/util/parsing/combinator/Parsers$Parser;
   44:	areturn
  LineNumberTable: 
   line 348: 0
   line 349: 19

  LocalVariableTable: 
   Start  Length  Slot  Name   Signature
   0      45      0    this       Lscala/util/parsing/combinator/Parsers$Parser;
   0      45      1    f$5       Lscala/PartialFunction;
   0      45      2    error$1       Lscala/Function1;

  Signature: length = 0x2
   00 FFFFFF82 

public scala.util.parsing.combinator.Parsers$Parser $up$up$up(java.lang.Object);
  Code:
   Stack=5, Locals=2, Args_size=2
   0:	aload_0
   1:	new	#134; //class scala/util/parsing/combinator/Parsers$Parser$$anonfun$$up$up$up$1
   4:	dup
   5:	aload_0
   6:	aload_1
   7:	invokespecial	#137; //Method scala/util/parsing/combinator/Parsers$Parser$$anonfun$$up$up$up$1."<init>":(Lscala/util/parsing/combinator/Parsers$Parser;Ljava/lang/Object;)V
   10:	invokevirtual	#140; //Method $up$up:(Lscala/Function1;)Lscala/util/parsing/combinator/Parsers$Parser;
   13:	areturn
  LineNumberTable: 
   line 333: 0

  LocalVariableTable: 
   Start  Length  Slot  Name   Signature
   0      14      0    this       Lscala/util/parsing/combinator/Parsers$Parser;
   0      14      1    r$1       Ljava/lang/Object;

  Signature: length = 0x2
   00 FFFFFF8F 

public scala.util.parsing.combinator.Parsers$Parser $up$up(scala.Function1);
  Code:
   Stack=3, Locals=2, Args_size=2
   0:	aload_0
   1:	aload_1
   2:	invokevirtual	#146; //Method map:(Lscala/Function1;)Lscala/util/parsing/combinator/Parsers$Parser;
   5:	new	#111; //class scala/collection/mutable/StringBuilder
   8:	dup
   9:	invokespecial	#112; //Method scala/collection/mutable/StringBuilder."<init>":()V
   12:	aload_0
   13:	invokevirtual	#116; //Method toString:()Ljava/lang/String;
   16:	invokevirtual	#120; //Method scala/collection/mutable/StringBuilder.append:(Ljava/lang/Object;)Lscala/collection/mutable/StringBuilder;
   19:	ldc	#148; //String ^^
   21:	invokevirtual	#120; //Method scala/collection/mutable/StringBuilder.append:(Ljava/lang/Object;)Lscala/collection/mutable/StringBuilder;
   24:	invokevirtual	#123; //Method scala/collection/mutable/StringBuilder.toString:()Ljava/lang/String;
   27:	invokevirtual	#127; //Method named:(Ljava/lang/String;)Lscala/util/parsing/combinator/Parsers$Parser;
   30:	areturn
  LineNumberTable: 
   line 330: 0

  LocalVariableTable: 
   Start  Length  Slot  Name   Signature
   0      31      0    this       Lscala/util/parsing/combinator/Parsers$Parser;
   0      31      1    f       Lscala/Function1;

  Signature: length = 0x2
   00 FFFFFF95 

public scala.util.parsing.combinator.Parsers$Parser $bar$bar$bar(scala.Function0);
  Code:
   Stack=4, Locals=2, Args_size=2
   0:	new	#152; //class scala/util/parsing/combinator/Parsers$Parser$$anon$4
   3:	dup
   4:	aload_0
   5:	aload_1
   6:	invokespecial	#155; //Method scala/util/parsing/combinator/Parsers$Parser$$anon$4."<init>":(Lscala/util/parsing/combinator/Parsers$Parser;Lscala/Function0;)V
   9:	areturn
  LineNumberTable: 
   line 306: 0

  LocalVariableTable: 
   Start  Length  Slot  Name   Signature
   0      10      0    this       Lscala/util/parsing/combinator/Parsers$Parser;
   0      10      1    q$1       Lscala/Function0;

  Signature: length = 0x2
   00 FFFFFF9D 

public scala.util.parsing.combinator.Parsers$Parser $bar(scala.Function0);
  Code:
   Stack=2, Locals=2, Args_size=2
   0:	aload_0
   1:	aload_1
   2:	invokevirtual	#160; //Method append:(Lscala/Function0;)Lscala/util/parsing/combinator/Parsers$Parser;
   5:	ldc	#162; //String |
   7:	invokevirtual	#127; //Method named:(Ljava/lang/String;)Lscala/util/parsing/combinator/Parsers$Parser;
   10:	areturn
  LineNumberTable: 
   line 294: 0

  LocalVariableTable: 
   Start  Length  Slot  Name   Signature
   0      11      0    this       Lscala/util/parsing/combinator/Parsers$Parser;
   0      11      1    q       Lscala/Function0;

  Signature: length = 0x2
   00 FFFFFF9D 

public scala.util.parsing.combinator.Parsers$Parser $tilde$bang(scala.Function0);
  Code:
   Stack=6, Locals=2, Args_size=2
   0:	aload_0
   1:	invokevirtual	#42; //Method scala$util$parsing$combinator$Parsers$Parser$$$outer:()Lscala/util/parsing/combinator/Parsers;
   4:	aload_0
   5:	new	#166; //class scala/util/parsing/combinator/Parsers$Parser$$anonfun$$tilde$bang$1
   8:	dup
   9:	aload_0
   10:	aload_1
   11:	invokespecial	#167; //Method scala/util/parsing/combinator/Parsers$Parser$$anonfun$$tilde$bang$1."<init>":(Lscala/util/parsing/combinator/Parsers$Parser;Lscala/Function0;)V
   14:	invokevirtual	#90; //Method flatMap:(Lscala/Function1;)Lscala/util/parsing/combinator/Parsers$Parser;
   17:	ldc	#169; //String ~!
   19:	invokevirtual	#127; //Method named:(Ljava/lang/String;)Lscala/util/parsing/combinator/Parsers$Parser;
   22:	invokeinterface	#172,  2; //InterfaceMethod scala/util/parsing/combinator/Parsers.OnceParser:(Lscala/Function1;)Lscala/util/parsing/combinator/Parsers$Parser;
   27:	areturn
  LineNumberTable: 
   line 280: 0

  LocalVariableTable: 
   Start  Length  Slot  Name   Signature
   0      28      0    this       Lscala/util/parsing/combinator/Parsers$Parser;
   0      28      1    p$7       Lscala/Function0;

  Signature: length = 0x2
   00 FFFFFFAE 

public scala.util.parsing.combinator.Parsers$Parser $less$tilde(scala.Function0);
  Code:
   Stack=5, Locals=2, Args_size=2
   0:	aload_0
   1:	new	#177; //class scala/util/parsing/combinator/Parsers$Parser$$anonfun$$less$tilde$1
   4:	dup
   5:	aload_0
   6:	aload_1
   7:	invokespecial	#178; //Method scala/util/parsing/combinator/Parsers$Parser$$anonfun$$less$tilde$1."<init>":(Lscala/util/parsing/combinator/Parsers$Parser;Lscala/Function0;)V
   10:	invokevirtual	#90; //Method flatMap:(Lscala/Function1;)Lscala/util/parsing/combinator/Parsers$Parser;
   13:	ldc	#180; //String <~
   15:	invokevirtual	#127; //Method named:(Ljava/lang/String;)Lscala/util/parsing/combinator/Parsers$Parser;
   18:	areturn
  LineNumberTable: 
   line 261: 0

  LocalVariableTable: 
   Start  Length  Slot  Name   Signature
   0      19      0    this       Lscala/util/parsing/combinator/Parsers$Parser;
   0      19      1    p$6       Lscala/Function0;

  Signature: length = 0x2
   00 FFFFFFB6 

public scala.util.parsing.combinator.Parsers$Parser $tilde$greater(scala.Function0);
  Code:
   Stack=5, Locals=2, Args_size=2
   0:	aload_0
   1:	new	#185; //class scala/util/parsing/combinator/Parsers$Parser$$anonfun$$tilde$greater$1
   4:	dup
   5:	aload_0
   6:	aload_1
   7:	invokespecial	#186; //Method scala/util/parsing/combinator/Parsers$Parser$$anonfun$$tilde$greater$1."<init>":(Lscala/util/parsing/combinator/Parsers$Parser;Lscala/Function0;)V
   10:	invokevirtual	#90; //Method flatMap:(Lscala/Function1;)Lscala/util/parsing/combinator/Parsers$Parser;
   13:	ldc	#188; //String ~>
   15:	invokevirtual	#127; //Method named:(Ljava/lang/String;)Lscala/util/parsing/combinator/Parsers$Parser;
   18:	areturn
  LineNumberTable: 
   line 249: 0

  LocalVariableTable: 
   Start  Length  Slot  Name   Signature
   0      19      0    this       Lscala/util/parsing/combinator/Parsers$Parser;
   0      19      1    p$5       Lscala/Function0;

  Signature: length = 0x2
   00 FFFFFF9D 

public scala.util.parsing.combinator.Parsers$Parser $tilde(scala.Function0);
  Code:
   Stack=5, Locals=2, Args_size=2
   0:	aload_0
   1:	new	#192; //class scala/util/parsing/combinator/Parsers$Parser$$anonfun$$tilde$1
   4:	dup
   5:	aload_0
   6:	aload_1
   7:	invokespecial	#193; //Method scala/util/parsing/combinator/Parsers$Parser$$anonfun$$tilde$1."<init>":(Lscala/util/parsing/combinator/Parsers$Parser;Lscala/Function0;)V
   10:	invokevirtual	#90; //Method flatMap:(Lscala/Function1;)Lscala/util/parsing/combinator/Parsers$Parser;
   13:	ldc	#195; //String ~
   15:	invokevirtual	#127; //Method named:(Ljava/lang/String;)Lscala/util/parsing/combinator/Parsers$Parser;
   18:	areturn
  LineNumberTable: 
   line 239: 0

  LocalVariableTable: 
   Start  Length  Slot  Name   Signature
   0      19      0    this       Lscala/util/parsing/combinator/Parsers$Parser;
   0      19      1    p$3       Lscala/Function0;

  Signature: length = 0x2
   00 FFFFFFAE 

public scala.util.parsing.combinator.Parsers$Parser append(scala.Function0);
  Code:
   Stack=5, Locals=2, Args_size=2
   0:	aload_0
   1:	invokevirtual	#42; //Method scala$util$parsing$combinator$Parsers$Parser$$$outer:()Lscala/util/parsing/combinator/Parsers;
   4:	new	#198; //class scala/util/parsing/combinator/Parsers$Parser$$anonfun$append$1
   7:	dup
   8:	aload_0
   9:	aload_1
   10:	invokespecial	#199; //Method scala/util/parsing/combinator/Parsers$Parser$$anonfun$append$1."<init>":(Lscala/util/parsing/combinator/Parsers$Parser;Lscala/Function0;)V
   13:	invokeinterface	#109,  2; //InterfaceMethod scala/util/parsing/combinator/Parsers.Parser:(Lscala/Function1;)Lscala/util/parsing/combinator/Parsers$Parser;
   18:	areturn
  LineNumberTable: 
   line 222: 0

  LocalVariableTable: 
   Start  Length  Slot  Name   Signature
   0      19      0    this       Lscala/util/parsing/combinator/Parsers$Parser;
   0      19      1    p$4       Lscala/Function0;

  Signature: length = 0x2
   00 FFFFFF9D 

public scala.util.parsing.combinator.Parsers$Parser map(scala.Function1);
  Code:
   Stack=5, Locals=2, Args_size=2
   0:	aload_0
   1:	invokevirtual	#42; //Method scala$util$parsing$combinator$Parsers$Parser$$$outer:()Lscala/util/parsing/combinator/Parsers;
   4:	new	#202; //class scala/util/parsing/combinator/Parsers$Parser$$anonfun$map$1
   7:	dup
   8:	aload_0
   9:	aload_1
   10:	invokespecial	#205; //Method scala/util/parsing/combinator/Parsers$Parser$$anonfun$map$1."<init>":(Lscala/util/parsing/combinator/Parsers$Parser;Lscala/Function1;)V
   13:	invokeinterface	#109,  2; //InterfaceMethod scala/util/parsing/combinator/Parsers.Parser:(Lscala/Function1;)Lscala/util/parsing/combinator/Parsers$Parser;
   18:	areturn
  LineNumberTable: 
   line 217: 0

  LocalVariableTable: 
   Start  Length  Slot  Name   Signature
   0      19      0    this       Lscala/util/parsing/combinator/Parsers$Parser;
   0      19      1    f$4       Lscala/Function1;

  Signature: length = 0x2
   00 FFFFFF95 

public scala.util.parsing.combinator.Parsers$Parser flatMap(scala.Function1);
  Code:
   Stack=5, Locals=2, Args_size=2
   0:	aload_0
   1:	invokevirtual	#42; //Method scala$util$parsing$combinator$Parsers$Parser$$$outer:()Lscala/util/parsing/combinator/Parsers;
   4:	new	#208; //class scala/util/parsing/combinator/Parsers$Parser$$anonfun$flatMap$1
   7:	dup
   8:	aload_0
   9:	aload_1
   10:	invokespecial	#209; //Method scala/util/parsing/combinator/Parsers$Parser$$anonfun$flatMap$1."<init>":(Lscala/util/parsing/combinator/Parsers$Parser;Lscala/Function1;)V
   13:	invokeinterface	#109,  2; //InterfaceMethod scala/util/parsing/combinator/Parsers.Parser:(Lscala/Function1;)Lscala/util/parsing/combinator/Parsers$Parser;
   18:	areturn
  LineNumberTable: 
   line 214: 0

  LocalVariableTable: 
   Start  Length  Slot  Name   Signature
   0      19      0    this       Lscala/util/parsing/combinator/Parsers$Parser;
   0      19      1    f$3       Lscala/Function1;

  Signature: length = 0x2
   00 57 

public abstract scala.util.parsing.combinator.Parsers$ParseResult apply(scala.util.parsing.input.Reader);
  Signature: length = 0x2
   00 FFFFFFD5 

public java.lang.String toString();
  Code:
   Stack=2, Locals=1, Args_size=1
   0:	new	#111; //class scala/collection/mutable/StringBuilder
   3:	dup
   4:	invokespecial	#112; //Method scala/collection/mutable/StringBuilder."<init>":()V
   7:	ldc	#215; //String Parser (
   9:	invokevirtual	#120; //Method scala/collection/mutable/StringBuilder.append:(Ljava/lang/Object;)Lscala/collection/mutable/StringBuilder;
   12:	aload_0
   13:	invokespecial	#217; //Method name:()Ljava/lang/String;
   16:	invokevirtual	#120; //Method scala/collection/mutable/StringBuilder.append:(Ljava/lang/Object;)Lscala/collection/mutable/StringBuilder;
   19:	ldc	#219; //String )
   21:	invokevirtual	#120; //Method scala/collection/mutable/StringBuilder.append:(Ljava/lang/Object;)Lscala/collection/mutable/StringBuilder;
   24:	invokevirtual	#123; //Method scala/collection/mutable/StringBuilder.toString:()Ljava/lang/String;
   27:	areturn
  LineNumberTable: 
   line 207: 0


public scala.util.parsing.combinator.Parsers$Parser named(java.lang.String);
  Code:
   Stack=2, Locals=2, Args_size=2
   0:	aload_0
   1:	aload_1
   2:	invokespecial	#223; //Method name_$eq:(Ljava/lang/String;)V
   5:	aload_0
   6:	areturn
  LineNumberTable: 
   line 206: 0

  LocalVariableTable: 
   Start  Length  Slot  Name   Signature
   0      7      0    this       Lscala/util/parsing/combinator/Parsers$Parser;
   0      7      1    n       Ljava/lang/String;

  Signature: length = 0x2
   00 FFFFFFE1 

public scala.Function1 andThen(scala.Function1);
  Code:
   Stack=2, Locals=2, Args_size=2
   0:	aload_0
   1:	aload_1
   2:	invokestatic	#230; //Method scala/Function1$class.andThen:(Lscala/Function1;Lscala/Function1;)Lscala/Function1;
   5:	areturn
  LineNumberTable: 
   line 204: 0

  LocalVariableTable: 
   Start  Length  Slot  Name   Signature
   0      6      0    this       Lscala/util/parsing/combinator/Parsers$Parser;
   0      6      1    g       Lscala/Function1;


public scala.Function1 compose(scala.Function1);
  Code:
   Stack=2, Locals=2, Args_size=2
   0:	aload_0
   1:	aload_1
   2:	invokestatic	#234; //Method scala/Function1$class.compose:(Lscala/Function1;Lscala/Function1;)Lscala/Function1;
   5:	areturn
  LineNumberTable: 
   line 204: 0

  LocalVariableTable: 
   Start  Length  Slot  Name   Signature
   0      6      0    this       Lscala/util/parsing/combinator/Parsers$Parser;
   0      6      1    g       Lscala/Function1;


}

