Compiled from "Parsers.scala"
public final class scala.util.parsing.combinator.Parsers$$anonfun$acceptIf$1 extends java.lang.Object implements scala.Function1,scala.ScalaObject,java.io.Serializable
  SourceFile: "Parsers.scala"
  Scala: length = 0x
   
  InnerClass: 
   public #103= #75 of #102; //Failure=class scala/util/parsing/combinator/Parsers$Failure of class scala/util/parsing/combinator/Parsers
   public #104= #66 of #102; //Success=class scala/util/parsing/combinator/Parsers$Success of class scala/util/parsing/combinator/Parsers
   public abstract #107= #106 of #102; //ParseResult=class scala/util/parsing/combinator/Parsers$ParseResult of class scala/util/parsing/combinator/Parsers
   public final #108= #9 of #102; //$anonfun$acceptIf$1=class scala/util/parsing/combinator/Parsers$$anonfun$acceptIf$1 of class scala/util/parsing/combinator/Parsers
  minor version: 0
  major version: 49
  Constant pool:
const #1 = Asciz	SourceFile;
const #2 = Asciz	Parsers.scala;
const #3 = Asciz	<clinit>;
const #4 = Asciz	()V;
const #5 = Asciz	Code;
const #6 = Asciz	serialVersionUID;
const #7 = Asciz	J;
const #8 = Asciz	scala/util/parsing/combinator/Parsers$$anonfun$acceptIf$1;
const #9 = class	#8;	//  scala/util/parsing/combinator/Parsers$$anonfun$acceptIf$1
const #10 = NameAndType	#6:#7;//  serialVersionUID:J
const #11 = Field	#9.#10;	//  scala/util/parsing/combinator/Parsers$$anonfun$acceptIf$1.serialVersionUID:J
const #12 = Asciz	err$1;
const #13 = Asciz	Lscala/Function1;;
const #14 = Asciz	p$11;
const #15 = Asciz	$outer;
const #16 = Asciz	Lscala/util/parsing/combinator/Parsers;;
const #17 = Asciz	<init>;
const #18 = Asciz	(Lscala/util/parsing/combinator/Parsers;Lscala/Function1;Lscala/Function1;)V;
const #19 = Asciz	LineNumberTable;
const #20 = Asciz	java/lang/NullPointerException;
const #21 = class	#20;	//  java/lang/NullPointerException
const #22 = NameAndType	#17:#4;//  "<init>":()V
const #23 = Method	#21.#22;	//  java/lang/NullPointerException."<init>":()V
const #24 = NameAndType	#15:#16;//  $outer:Lscala/util/parsing/combinator/Parsers;
const #25 = Field	#9.#24;	//  scala/util/parsing/combinator/Parsers$$anonfun$acceptIf$1.$outer:Lscala/util/parsing/combinator/Parsers;
const #26 = NameAndType	#14:#13;//  p$11:Lscala/Function1;
const #27 = Field	#9.#26;	//  scala/util/parsing/combinator/Parsers$$anonfun$acceptIf$1.p$11:Lscala/Function1;
const #28 = NameAndType	#12:#13;//  err$1:Lscala/Function1;
const #29 = Field	#9.#28;	//  scala/util/parsing/combinator/Parsers$$anonfun$acceptIf$1.err$1:Lscala/Function1;
const #30 = Asciz	java/lang/Object;
const #31 = class	#30;	//  java/lang/Object
const #32 = Method	#31.#22;	//  java/lang/Object."<init>":()V
const #33 = Asciz	scala/Function1$class;
const #34 = class	#33;	//  scala/Function1$class
const #35 = Asciz	$init$;
const #36 = Asciz	(Lscala/Function1;)V;
const #37 = NameAndType	#35:#36;//  $init$:(Lscala/Function1;)V
const #38 = Method	#34.#37;	//  scala/Function1$class.$init$:(Lscala/Function1;)V
const #39 = Asciz	this;
const #40 = Asciz	Lscala/util/parsing/combinator/Parsers$$anonfun$acceptIf$1;;
const #41 = Asciz	LocalVariableTable;
const #42 = Asciz	apply;
const #43 = Asciz	(Ljava/lang/Object;)Ljava/lang/Object;;
const #44 = Asciz	scala/util/parsing/input/Reader;
const #45 = class	#44;	//  scala/util/parsing/input/Reader
const #46 = Asciz	(Lscala/util/parsing/input/Reader;)Lscala/util/parsing/combinator/Parsers$ParseResult;;
const #47 = NameAndType	#42:#46;//  apply:(Lscala/util/parsing/input/Reader;)Lscala/util/parsing/combinator/Parsers$ParseResult;
const #48 = Method	#9.#47;	//  scala/util/parsing/combinator/Parsers$$anonfun$acceptIf$1.apply:(Lscala/util/parsing/input/Reader;)Lscala/util/parsing/combinator/Parsers$ParseResult;
const #49 = Asciz	v1;
const #50 = Asciz	Ljava/lang/Object;;
const #51 = Asciz	first;
const #52 = Asciz	()Ljava/lang/Object;;
const #53 = NameAndType	#51:#52;//  first:()Ljava/lang/Object;
const #54 = Method	#45.#53;	//  scala/util/parsing/input/Reader.first:()Ljava/lang/Object;
const #55 = Asciz	scala/Function1;
const #56 = class	#55;	//  scala/Function1
const #57 = NameAndType	#42:#43;//  apply:(Ljava/lang/Object;)Ljava/lang/Object;
const #58 = InterfaceMethod	#56.#57;	//  scala/Function1.apply:(Ljava/lang/Object;)Ljava/lang/Object;
const #59 = Asciz	scala/runtime/BoxesRunTime;
const #60 = class	#59;	//  scala/runtime/BoxesRunTime
const #61 = Asciz	unboxToBoolean;
const #62 = Asciz	(Ljava/lang/Object;)Z;
const #63 = NameAndType	#61:#62;//  unboxToBoolean:(Ljava/lang/Object;)Z
const #64 = Method	#60.#63;	//  scala/runtime/BoxesRunTime.unboxToBoolean:(Ljava/lang/Object;)Z
const #65 = Asciz	scala/util/parsing/combinator/Parsers$Success;
const #66 = class	#65;	//  scala/util/parsing/combinator/Parsers$Success
const #67 = Asciz	rest;
const #68 = Asciz	()Lscala/util/parsing/input/Reader;;
const #69 = NameAndType	#67:#68;//  rest:()Lscala/util/parsing/input/Reader;
const #70 = Method	#45.#69;	//  scala/util/parsing/input/Reader.rest:()Lscala/util/parsing/input/Reader;
const #71 = Asciz	(Lscala/util/parsing/combinator/Parsers;Ljava/lang/Object;Lscala/util/parsing/input/Reader;)V;
const #72 = NameAndType	#17:#71;//  "<init>":(Lscala/util/parsing/combinator/Parsers;Ljava/lang/Object;Lscala/util/parsing/input/Reader;)V
const #73 = Method	#66.#72;	//  scala/util/parsing/combinator/Parsers$Success."<init>":(Lscala/util/parsing/combinator/Parsers;Ljava/lang/Object;Lscala/util/parsing/input/Reader;)V
const #74 = Asciz	scala/util/parsing/combinator/Parsers$Failure;
const #75 = class	#74;	//  scala/util/parsing/combinator/Parsers$Failure
const #76 = Asciz	java/lang/String;
const #77 = class	#76;	//  java/lang/String
const #78 = Asciz	(Lscala/util/parsing/combinator/Parsers;Ljava/lang/String;Lscala/util/parsing/input/Reader;)V;
const #79 = NameAndType	#17:#78;//  "<init>":(Lscala/util/parsing/combinator/Parsers;Ljava/lang/String;Lscala/util/parsing/input/Reader;)V
const #80 = Method	#75.#79;	//  scala/util/parsing/combinator/Parsers$Failure."<init>":(Lscala/util/parsing/combinator/Parsers;Ljava/lang/String;Lscala/util/parsing/input/Reader;)V
const #81 = Asciz	in;
const #82 = Asciz	Lscala/util/parsing/input/Reader;;
const #83 = Asciz	(Lscala/util/parsing/input/Reader<Ljava/lang/Object;>;)Lscala/util/parsing/combinator/Parsers$ParseResult<Ljava/lang/Object;>;;
const #84 = Asciz	Signature;
const #85 = Asciz	andThen;
const #86 = Asciz	(Lscala/Function1;)Lscala/Function1;;
const #87 = Asciz	(Lscala/Function1;Lscala/Function1;)Lscala/Function1;;
const #88 = NameAndType	#85:#87;//  andThen:(Lscala/Function1;Lscala/Function1;)Lscala/Function1;
const #89 = Method	#34.#88;	//  scala/Function1$class.andThen:(Lscala/Function1;Lscala/Function1;)Lscala/Function1;
const #90 = Asciz	g;
const #91 = Asciz	compose;
const #92 = NameAndType	#91:#87;//  compose:(Lscala/Function1;Lscala/Function1;)Lscala/Function1;
const #93 = Method	#34.#92;	//  scala/Function1$class.compose:(Lscala/Function1;Lscala/Function1;)Lscala/Function1;
const #94 = Asciz	toString;
const #95 = Asciz	()Ljava/lang/String;;
const #96 = Asciz	(Lscala/Function1;)Ljava/lang/String;;
const #97 = NameAndType	#94:#96;//  toString:(Lscala/Function1;)Ljava/lang/String;
const #98 = Method	#34.#97;	//  scala/Function1$class.toString:(Lscala/Function1;)Ljava/lang/String;
const #99 = Asciz	Scala;
const #100 = Asciz	InnerClasses;
const #101 = Asciz	scala/util/parsing/combinator/Parsers;
const #102 = class	#101;	//  scala/util/parsing/combinator/Parsers
const #103 = Asciz	Failure;
const #104 = Asciz	Success;
const #105 = Asciz	scala/util/parsing/combinator/Parsers$ParseResult;
const #106 = class	#105;	//  scala/util/parsing/combinator/Parsers$ParseResult
const #107 = Asciz	ParseResult;
const #108 = Asciz	$anonfun$acceptIf$1;
const #109 = Asciz	scala/ScalaObject;
const #110 = class	#109;	//  scala/ScalaObject
const #111 = Asciz	java/io/Serializable;
const #112 = class	#111;	//  java/io/Serializable

{
public static final long serialVersionUID;

public static {};
  Code:
   Stack=2, Locals=0, Args_size=0
   0:	lconst_0
   1:	putstatic	#11; //Field serialVersionUID:J
   4:	return

public scala.util.parsing.combinator.Parsers$$anonfun$acceptIf$1(scala.util.parsing.combinator.Parsers, scala.Function1, scala.Function1);
  Code:
   Stack=2, Locals=4, Args_size=4
   0:	aload_1
   1:	ifnonnull	12
   4:	new	#21; //class java/lang/NullPointerException
   7:	dup
   8:	invokespecial	#23; //Method java/lang/NullPointerException."<init>":()V
   11:	athrow
   12:	aload_0
   13:	aload_1
   14:	putfield	#25; //Field $outer:Lscala/util/parsing/combinator/Parsers;
   17:	aload_0
   18:	aload_2
   19:	putfield	#27; //Field p$11:Lscala/Function1;
   22:	aload_0
   23:	aload_3
   24:	putfield	#29; //Field err$1:Lscala/Function1;
   27:	aload_0
   28:	invokespecial	#32; //Method java/lang/Object."<init>":()V
   31:	aload_0
   32:	invokestatic	#38; //Method scala/Function1$class.$init$:(Lscala/Function1;)V
   35:	return
  LineNumberTable: 
   line 501: 0

  LocalVariableTable: 
   Start  Length  Slot  Name   Signature
   0      36      0    this       Lscala/util/parsing/combinator/Parsers$$anonfun$acceptIf$1;
   0      36      1    $outer       Lscala/util/parsing/combinator/Parsers;


public final java.lang.Object apply(java.lang.Object);
  Code:
   Stack=2, Locals=3, Args_size=2
   0:	aload_0
   1:	getfield	#25; //Field $outer:Lscala/util/parsing/combinator/Parsers;
   4:	astore_2
   5:	aload_0
   6:	aload_1
   7:	checkcast	#45; //class scala/util/parsing/input/Reader
   10:	invokevirtual	#48; //Method apply:(Lscala/util/parsing/input/Reader;)Lscala/util/parsing/combinator/Parsers$ParseResult;
   13:	areturn
  LineNumberTable: 
   line 501: 0

  LocalVariableTable: 
   Start  Length  Slot  Name   Signature
   0      14      0    this       Lscala/util/parsing/combinator/Parsers$$anonfun$acceptIf$1;
   5      9      1    v1       Ljava/lang/Object;


public final scala.util.parsing.combinator.Parsers$ParseResult apply(scala.util.parsing.input.Reader);
  Code:
   Stack=5, Locals=3, Args_size=2
   0:	aload_0
   1:	getfield	#25; //Field $outer:Lscala/util/parsing/combinator/Parsers;
   4:	astore_2
   5:	aload_0
   6:	getfield	#27; //Field p$11:Lscala/Function1;
   9:	aload_1
   10:	invokevirtual	#54; //Method scala/util/parsing/input/Reader.first:()Ljava/lang/Object;
   13:	invokeinterface	#58,  2; //InterfaceMethod scala/Function1.apply:(Ljava/lang/Object;)Ljava/lang/Object;
   18:	invokestatic	#64; //Method scala/runtime/BoxesRunTime.unboxToBoolean:(Ljava/lang/Object;)Z
   21:	ifeq	46
   24:	new	#66; //class scala/util/parsing/combinator/Parsers$Success
   27:	dup
   28:	aload_0
   29:	getfield	#25; //Field $outer:Lscala/util/parsing/combinator/Parsers;
   32:	aload_1
   33:	invokevirtual	#54; //Method scala/util/parsing/input/Reader.first:()Ljava/lang/Object;
   36:	aload_1
   37:	invokevirtual	#70; //Method scala/util/parsing/input/Reader.rest:()Lscala/util/parsing/input/Reader;
   40:	invokespecial	#73; //Method scala/util/parsing/combinator/Parsers$Success."<init>":(Lscala/util/parsing/combinator/Parsers;Ljava/lang/Object;Lscala/util/parsing/input/Reader;)V
   43:	goto	74
   46:	new	#75; //class scala/util/parsing/combinator/Parsers$Failure
   49:	dup
   50:	aload_0
   51:	getfield	#25; //Field $outer:Lscala/util/parsing/combinator/Parsers;
   54:	aload_0
   55:	getfield	#29; //Field err$1:Lscala/Function1;
   58:	aload_1
   59:	invokevirtual	#54; //Method scala/util/parsing/input/Reader.first:()Ljava/lang/Object;
   62:	invokeinterface	#58,  2; //InterfaceMethod scala/Function1.apply:(Ljava/lang/Object;)Ljava/lang/Object;
   67:	checkcast	#77; //class java/lang/String
   70:	aload_1
   71:	invokespecial	#80; //Method scala/util/parsing/combinator/Parsers$Failure."<init>":(Lscala/util/parsing/combinator/Parsers;Ljava/lang/String;Lscala/util/parsing/input/Reader;)V
   74:	areturn
  LineNumberTable: 
   line 502: 0
   line 503: 46
   line 502: 74

  LocalVariableTable: 
   Start  Length  Slot  Name   Signature
   0      75      0    this       Lscala/util/parsing/combinator/Parsers$$anonfun$acceptIf$1;
   5      70      1    in       Lscala/util/parsing/input/Reader;

  Signature: length = 0x2
   00 53 

public scala.Function1 andThen(scala.Function1);
  Code:
   Stack=2, Locals=2, Args_size=2
   0:	aload_0
   1:	aload_1
   2:	invokestatic	#89; //Method scala/Function1$class.andThen:(Lscala/Function1;Lscala/Function1;)Lscala/Function1;
   5:	areturn
  LineNumberTable: 
   line 501: 0

  LocalVariableTable: 
   Start  Length  Slot  Name   Signature
   0      6      0    this       Lscala/util/parsing/combinator/Parsers$$anonfun$acceptIf$1;
   0      6      1    g       Lscala/Function1;


public scala.Function1 compose(scala.Function1);
  Code:
   Stack=2, Locals=2, Args_size=2
   0:	aload_0
   1:	aload_1
   2:	invokestatic	#93; //Method scala/Function1$class.compose:(Lscala/Function1;Lscala/Function1;)Lscala/Function1;
   5:	areturn
  LineNumberTable: 
   line 501: 0

  LocalVariableTable: 
   Start  Length  Slot  Name   Signature
   0      6      0    this       Lscala/util/parsing/combinator/Parsers$$anonfun$acceptIf$1;
   0      6      1    g       Lscala/Function1;


public java.lang.String toString();
  Code:
   Stack=1, Locals=1, Args_size=1
   0:	aload_0
   1:	invokestatic	#98; //Method scala/Function1$class.toString:(Lscala/Function1;)Ljava/lang/String;
   4:	areturn
  LineNumberTable: 
   line 501: 0


}

