Compiled from "Parsers.scala"
public final class scala.util.parsing.combinator.Parsers$NoSuccess$ extends java.lang.Object implements scala.ScalaObject
  SourceFile: "Parsers.scala"
  Scala: length = 0x
   
  InnerClass: 
   public Error=class scala/util/parsing/combinator/Parsers$Error of class scala/util/parsing/combinator/Parsers
   public Failure=class scala/util/parsing/combinator/Parsers$Failure of class scala/util/parsing/combinator/Parsers
   public abstract ParseResult=class scala/util/parsing/combinator/Parsers$ParseResult of class scala/util/parsing/combinator/Parsers
  minor version: 0
  major version: 49
  Constant pool:
Asciz	SourceFile;
Asciz	Parsers.scala;
Asciz	Scala;
Asciz	<init>;
Asciz	(Lscala/util/parsing/combinator/Parsers;)V;
Asciz	Code;
Asciz	LineNumberTable;
Asciz	java/lang/Object;
class	java/lang/Object
Asciz	()V;
NameAndType	"<init>":()V
Method	java/lang/Object."<init>":()V
Asciz	this;
Asciz	Lscala/util/parsing/combinator/Parsers$NoSuccess$;;
Asciz	$outer;
Asciz	Lscala/util/parsing/combinator/Parsers;;
Asciz	LocalVariableTable;
Asciz	unapply;
Asciz	(Lscala/util/parsing/combinator/Parsers$ParseResult;)Lscala/Option;;
Asciz	scala/util/parsing/combinator/Parsers$Failure;
class	scala/util/parsing/combinator/Parsers$Failure
Asciz	msg;
Asciz	()Ljava/lang/String;;
NameAndType	msg:()Ljava/lang/String;
Method	scala/util/parsing/combinator/Parsers$Failure.msg:()Ljava/lang/String;
Asciz	next;
Asciz	()Lscala/util/parsing/input/Reader;;
NameAndType	next:()Lscala/util/parsing/input/Reader;
Method	scala/util/parsing/combinator/Parsers$Failure.next:()Lscala/util/parsing/input/Reader;
Asciz	scala/Some;
class	scala/Some
Asciz	scala/Tuple2;
class	scala/Tuple2
Asciz	(Ljava/lang/Object;Ljava/lang/Object;)V;
NameAndType	"<init>":(Ljava/lang/Object;Ljava/lang/Object;)V
Method	scala/Tuple2."<init>":(Ljava/lang/Object;Ljava/lang/Object;)V
Asciz	(Ljava/lang/Object;)V;
NameAndType	"<init>":(Ljava/lang/Object;)V
Method	scala/Some."<init>":(Ljava/lang/Object;)V
Asciz	scala/MatchError;
class	scala/MatchError
Asciz	scala/util/parsing/combinator/Parsers$ParseResult;
class	scala/util/parsing/combinator/Parsers$ParseResult
Asciz	toString;
NameAndType	toString:()Ljava/lang/String;
Method	scala/util/parsing/combinator/Parsers$ParseResult.toString:()Ljava/lang/String;
Asciz	(Ljava/lang/String;)V;
NameAndType	"<init>":(Ljava/lang/String;)V
Method	scala/MatchError."<init>":(Ljava/lang/String;)V
Asciz	scala/util/parsing/combinator/Parsers$Error;
class	scala/util/parsing/combinator/Parsers$Error
Method	scala/util/parsing/combinator/Parsers$Error.msg:()Ljava/lang/String;
Method	scala/util/parsing/combinator/Parsers$Error.next:()Lscala/util/parsing/input/Reader;
Asciz	scala/None$;
class	scala/None$
Asciz	MODULE$;
Asciz	Lscala/None$;;
NameAndType	MODULE$:Lscala/None$;
Field	scala/None$.MODULE$:Lscala/None$;
Asciz	x;
Asciz	Lscala/util/parsing/combinator/Parsers$ParseResult;;
Asciz	temp7;
Asciz	Lscala/util/parsing/combinator/Parsers$Failure;;
Asciz	temp8;
Asciz	Ljava/lang/String;;
Asciz	temp9;
Asciz	Lscala/util/parsing/input/Reader;;
Asciz	temp10;
Asciz	Lscala/util/parsing/combinator/Parsers$Error;;
Asciz	temp11;
Asciz	temp12;
Asciz	<T:Ljava/lang/Object;>(Lscala/util/parsing/combinator/Parsers$ParseResult<TT;>;)Lscala/Option<Lscala/Tuple2<Ljava/lang/String;Lscala/util/parsing/input/Reader<Ljava/lang/Object;>;>;>;;
Asciz	Signature;
Asciz	InnerClasses;
Asciz	scala/util/parsing/combinator/Parsers;
class	scala/util/parsing/combinator/Parsers
Asciz	Error;
Asciz	Failure;
Asciz	ParseResult;
Asciz	scala/util/parsing/combinator/Parsers$NoSuccess$;
class	scala/util/parsing/combinator/Parsers$NoSuccess$
Asciz	scala/ScalaObject;
class	scala/ScalaObject

{
public scala.util.parsing.combinator.Parsers$NoSuccess$(scala.util.parsing.combinator.Parsers);
  Signature: (Lscala/util/parsing/combinator/Parsers;)V
  Code:
   Stack=1, Locals=2, Args_size=2
	aload_0
	invokespecial	Method java/lang/Object."<init>":()V
	return
  Labels:
  LocalVariableTable: 
   Start  Length  Slot  Name   Signature
   0      5      0    this       Lscala/util/parsing/combinator/Parsers$NoSuccess$;
   0      5      1    $outer       Lscala/util/parsing/combinator/Parsers;


public scala.Option unapply(scala.util.parsing.combinator.Parsers$ParseResult);
  Signature: (Lscala/util/parsing/combinator/Parsers$ParseResult;)Lscala/Option;
  Code:
   Stack=6, Locals=8, Args_size=2
	aload_1
	instanceof	class scala/util/parsing/combinator/Parsers$Failure
	ifeq	l1 // aload_1
	aload_1
	checkcast	class scala/util/parsing/combinator/Parsers$Failure
	astore_2
	aload_2
	invokevirtual	Method scala/util/parsing/combinator/Parsers$Failure.msg:()Ljava/lang/String;
	astore_3
	aload_2
	invokevirtual	Method scala/util/parsing/combinator/Parsers$Failure.next:()Lscala/util/parsing/input/Reader;
	astore	4
	iconst_1
	ifeq	l2 // new
	new	class scala/Some
	dup
	new	class scala/Tuple2
	dup
	aload_3
	aload	4
	invokespecial	Method scala/Tuple2."<init>":(Ljava/lang/Object;Ljava/lang/Object;)V
	invokespecial	Method scala/Some."<init>":(Ljava/lang/Object;)V
	goto	l3 // areturn
l2	new	class scala/MatchError
	dup
	aload_1
	invokevirtual	Method scala/util/parsing/combinator/Parsers$ParseResult.toString:()Ljava/lang/String;
	invokespecial	Method scala/MatchError."<init>":(Ljava/lang/String;)V
	athrow
l1	aload_1
	instanceof	class scala/util/parsing/combinator/Parsers$Error
	ifeq	l4 // iconst_1
	aload_1
	checkcast	class scala/util/parsing/combinator/Parsers$Error
	astore	5
	aload	5
	invokevirtual	Method scala/util/parsing/combinator/Parsers$Error.msg:()Ljava/lang/String;
	astore	6
	aload	5
	invokevirtual	Method scala/util/parsing/combinator/Parsers$Error.next:()Lscala/util/parsing/input/Reader;
	astore	7
	iconst_1
	ifeq	l5 // new
	new	class scala/Some
	dup
	new	class scala/Tuple2
	dup
	aload	6
	aload	7
	invokespecial	Method scala/Tuple2."<init>":(Ljava/lang/Object;Ljava/lang/Object;)V
	invokespecial	Method scala/Some."<init>":(Ljava/lang/Object;)V
	goto	l3 // areturn
l5	new	class scala/MatchError
	dup
	aload_1
	invokevirtual	Method scala/util/parsing/combinator/Parsers$ParseResult.toString:()Ljava/lang/String;
	invokespecial	Method scala/MatchError."<init>":(Ljava/lang/String;)V
	athrow
l4	iconst_1
	ifeq	l6 // new
	getstatic	Field scala/None$.MODULE$:Lscala/None$;
l3	areturn
l6	new	class scala/MatchError
	dup
	aload_1
	invokevirtual	Method scala/util/parsing/combinator/Parsers$ParseResult.toString:()Ljava/lang/String;
	invokespecial	Method scala/MatchError."<init>":(Ljava/lang/String;)V
	athrow
  Labels:
   	l2 = 47 // new
   	l1 = 59 // aload_1
   	l5 = 111 // new
   	l4 = 123 // iconst_1
   	l3 = 130 // areturn
   	l6 = 131 // new
  LocalVariableTable: 
   Start  Length  Slot  Name   Signature
   0      143      0    this       Lscala/util/parsing/combinator/Parsers$NoSuccess$;
   0      143      1    x       Lscala/util/parsing/combinator/Parsers$ParseResult;
   12      47      2    temp7       Lscala/util/parsing/combinator/Parsers$Failure;
   17      42      3    temp8       Ljava/lang/String;
   23      36      4    temp9       Lscala/util/parsing/input/Reader;
   72      51      5    temp10       Lscala/util/parsing/combinator/Parsers$Error;
   79      44      6    temp11       Ljava/lang/String;
   86      37      7    temp12       Lscala/util/parsing/input/Reader;

  Signature: length = 0x2
   00 48 

}

