Compiled from "Parsers.scala"
public final class scala.util.parsing.combinator.Parsers$Parser$$anonfun$$tilde$bang$1$$anonfun$apply$5 extends scala.runtime.AbstractFunction1 implements java.io.Serializable
  SourceFile: "Parsers.scala"
  Scala: length = 0x
   
  InnerClass: 
   public abstract Parser=class scala/util/parsing/combinator/Parsers$Parser of class scala/util/parsing/combinator/Parsers
   public $tilde=class scala/util/parsing/combinator/Parsers$$tilde of class scala/util/parsing/combinator/Parsers
   public final $anonfun$$tilde$bang$1=class scala/util/parsing/combinator/Parsers$Parser$$anonfun$$tilde$bang$1 of class scala/util/parsing/combinator/Parsers$Parser
   public final $anonfun$apply$5=class scala/util/parsing/combinator/Parsers$Parser$$anonfun$$tilde$bang$1$$anonfun$apply$5 of class scala/util/parsing/combinator/Parsers$Parser$$anonfun$$tilde$bang$1
  minor version: 0
  major version: 49
  Constant pool:
Asciz	SourceFile;
Asciz	Parsers.scala;
Asciz	<clinit>;
Asciz	()V;
Asciz	Code;
Asciz	serialVersionUID;
Asciz	J;
Asciz	scala/util/parsing/combinator/Parsers$Parser$$anonfun$$tilde$bang$1$$anonfun$apply$5;
class	scala/util/parsing/combinator/Parsers$Parser$$anonfun$$tilde$bang$1$$anonfun$apply$5
NameAndType	serialVersionUID:J
Field	scala/util/parsing/combinator/Parsers$Parser$$anonfun$$tilde$bang$1$$anonfun$apply$5.serialVersionUID:J
Asciz	a$3;
Asciz	Ljava/lang/Object;;
Asciz	$outer;
Asciz	Lscala/util/parsing/combinator/Parsers$Parser$$anonfun$$tilde$bang$1;;
Asciz	<init>;
Asciz	(Lscala/util/parsing/combinator/Parsers$Parser$$anonfun$$tilde$bang$1;Ljava/lang/Object;)V;
Asciz	LineNumberTable;
Asciz	java/lang/NullPointerException;
class	java/lang/NullPointerException
NameAndType	"<init>":()V
Method	java/lang/NullPointerException."<init>":()V
NameAndType	$outer:Lscala/util/parsing/combinator/Parsers$Parser$$anonfun$$tilde$bang$1;
Field	scala/util/parsing/combinator/Parsers$Parser$$anonfun$$tilde$bang$1$$anonfun$apply$5.$outer:Lscala/util/parsing/combinator/Parsers$Parser$$anonfun$$tilde$bang$1;
NameAndType	a$3:Ljava/lang/Object;
Field	scala/util/parsing/combinator/Parsers$Parser$$anonfun$$tilde$bang$1$$anonfun$apply$5.a$3:Ljava/lang/Object;
Asciz	scala/runtime/AbstractFunction1;
class	scala/runtime/AbstractFunction1
Method	scala/runtime/AbstractFunction1."<init>":()V
Asciz	this;
Asciz	Lscala/util/parsing/combinator/Parsers$Parser$$anonfun$$tilde$bang$1$$anonfun$apply$5;;
Asciz	LocalVariableTable;
Asciz	(Lscala/util/parsing/combinator/Parsers$Parser<TT;>.$anonfun$$tilde$bang$1;)V;
Asciz	Signature;
Asciz	apply;
Asciz	(Ljava/lang/Object;)Ljava/lang/Object;;
Asciz	(Ljava/lang/Object;)Lscala/util/parsing/combinator/Parsers$$tilde;;
NameAndType	apply:(Ljava/lang/Object;)Lscala/util/parsing/combinator/Parsers$$tilde;
Method	scala/util/parsing/combinator/Parsers$Parser$$anonfun$$tilde$bang$1$$anonfun$apply$5.apply:(Ljava/lang/Object;)Lscala/util/parsing/combinator/Parsers$$tilde;
Asciz	v1;
Asciz	scala/util/parsing/combinator/Parsers$$tilde;
class	scala/util/parsing/combinator/Parsers$$tilde
Asciz	scala/util/parsing/combinator/Parsers$Parser$$anonfun$$tilde$bang$1;
class	scala/util/parsing/combinator/Parsers$Parser$$anonfun$$tilde$bang$1
Asciz	scala$util$parsing$combinator$Parsers$Parser$$anonfun$$$outer;
Asciz	()Lscala/util/parsing/combinator/Parsers$Parser;;
NameAndType	scala$util$parsing$combinator$Parsers$Parser$$anonfun$$$outer:()Lscala/util/parsing/combinator/Parsers$Parser;
Method	scala/util/parsing/combinator/Parsers$Parser$$anonfun$$tilde$bang$1.scala$util$parsing$combinator$Parsers$Parser$$anonfun$$$outer:()Lscala/util/parsing/combinator/Parsers$Parser;
Asciz	scala/util/parsing/combinator/Parsers$Parser;
class	scala/util/parsing/combinator/Parsers$Parser
Asciz	scala$util$parsing$combinator$Parsers$Parser$$$outer;
Asciz	()Lscala/util/parsing/combinator/Parsers;;
NameAndType	scala$util$parsing$combinator$Parsers$Parser$$$outer:()Lscala/util/parsing/combinator/Parsers;
Method	scala/util/parsing/combinator/Parsers$Parser.scala$util$parsing$combinator$Parsers$Parser$$$outer:()Lscala/util/parsing/combinator/Parsers;
Asciz	(Lscala/util/parsing/combinator/Parsers;Ljava/lang/Object;Ljava/lang/Object;)V;
NameAndType	"<init>":(Lscala/util/parsing/combinator/Parsers;Ljava/lang/Object;Ljava/lang/Object;)V
Method	scala/util/parsing/combinator/Parsers$$tilde."<init>":(Lscala/util/parsing/combinator/Parsers;Ljava/lang/Object;Ljava/lang/Object;)V
Asciz	b;
Asciz	(TU;)Lscala/util/parsing/combinator/Parsers$$tilde<TT;TU;>;;
Asciz	Scala;
Asciz	InnerClasses;
Asciz	scala/util/parsing/combinator/Parsers;
class	scala/util/parsing/combinator/Parsers
Asciz	Parser;
Asciz	$tilde;
Asciz	$anonfun$$tilde$bang$1;
Asciz	$anonfun$apply$5;
Asciz	java/io/Serializable;
class	java/io/Serializable

{
public static final long serialVersionUID;
  Signature: J

public final java.lang.Object a$3;
  Signature: Ljava/lang/Object;

public final scala.util.parsing.combinator.Parsers$Parser$$anonfun$$tilde$bang$1 $outer;
  Signature: Lscala/util/parsing/combinator/Parsers$Parser$$anonfun$$tilde$bang$1;

public static {};
  Signature: ()V
  Code:
   Stack=2, Locals=0, Args_size=0
	lconst_0
	putstatic	Field serialVersionUID:J
	return
  Labels:

public scala.util.parsing.combinator.Parsers$Parser$$anonfun$$tilde$bang$1$$anonfun$apply$5(scala.util.parsing.combinator.Parsers$Parser$$anonfun$$tilde$bang$1, java.lang.Object);
  Signature: (Lscala/util/parsing/combinator/Parsers$Parser$$anonfun$$tilde$bang$1;Ljava/lang/Object;)V
  Code:
   Stack=2, Locals=3, Args_size=3
	aload_1
	ifnonnull	l1 // aload_0
	new	class java/lang/NullPointerException
	dup
	invokespecial	Method java/lang/NullPointerException."<init>":()V
	athrow
l1	aload_0
	aload_1
	putfield	Field $outer:Lscala/util/parsing/combinator/Parsers$Parser$$anonfun$$tilde$bang$1;
	aload_0
	aload_2
	putfield	Field a$3:Ljava/lang/Object;
	aload_0
	invokespecial	Method scala/runtime/AbstractFunction1."<init>":()V
	return
  Labels:
   	l1 = 12 // aload_0
  LocalVariableTable: 
   Start  Length  Slot  Name   Signature
   0      27      0    this       Lscala/util/parsing/combinator/Parsers$Parser$$anonfun$$tilde$bang$1$$anonfun$apply$5;
   0      27      1    $outer       Lscala/util/parsing/combinator/Parsers$Parser$$anonfun$$tilde$bang$1;

  Signature: length = 0x2
   00 21 

public final java.lang.Object apply(java.lang.Object);
  Signature: (Ljava/lang/Object;)Ljava/lang/Object;
  Code:
   Stack=2, Locals=2, Args_size=2
	aload_0
	aload_1
	invokevirtual	Method apply:(Ljava/lang/Object;)Lscala/util/parsing/combinator/Parsers$$tilde;
	areturn
  Labels:
  LocalVariableTable: 
   Start  Length  Slot  Name   Signature
   0      6      0    this       Lscala/util/parsing/combinator/Parsers$Parser$$anonfun$$tilde$bang$1$$anonfun$apply$5;
   0      6      1    v1       Ljava/lang/Object;


public final scala.util.parsing.combinator.Parsers$$tilde apply(java.lang.Object);
  Signature: (Ljava/lang/Object;)Lscala/util/parsing/combinator/Parsers$$tilde;
  Code:
   Stack=5, Locals=2, Args_size=2
	new	class scala/util/parsing/combinator/Parsers$$tilde
	dup
	aload_0
	getfield	Field $outer:Lscala/util/parsing/combinator/Parsers$Parser$$anonfun$$tilde$bang$1;
	invokevirtual	Method scala/util/parsing/combinator/Parsers$Parser$$anonfun$$tilde$bang$1.scala$util$parsing$combinator$Parsers$Parser$$anonfun$$$outer:()Lscala/util/parsing/combinator/Parsers$Parser;
	invokevirtual	Method scala/util/parsing/combinator/Parsers$Parser.scala$util$parsing$combinator$Parsers$Parser$$$outer:()Lscala/util/parsing/combinator/Parsers;
	aload_0
	getfield	Field a$3:Ljava/lang/Object;
	aload_1
	invokespecial	Method scala/util/parsing/combinator/Parsers$$tilde."<init>":(Lscala/util/parsing/combinator/Parsers;Ljava/lang/Object;Ljava/lang/Object;)V
	areturn
  Labels:
  LocalVariableTable: 
   Start  Length  Slot  Name   Signature
   0      23      0    this       Lscala/util/parsing/combinator/Parsers$Parser$$anonfun$$tilde$bang$1$$anonfun$apply$5;
   0      23      1    b       Ljava/lang/Object;

  Signature: length = 0x2
   00 3B 

}

