Compiled from "Parsers.scala"
public final class scala.util.parsing.combinator.Parsers$$anonfun$chainr1$2 extends java.lang.Object implements scala.Function1,scala.ScalaObject,java.io.Serializable
  SourceFile: "Parsers.scala"
  Scala: length = 0x
   
  InnerClass: 
   public $tilde=class scala/util/parsing/combinator/Parsers$$tilde of class scala/util/parsing/combinator/Parsers
   public final $anonfun$chainr1$2=class scala/util/parsing/combinator/Parsers$$anonfun$chainr1$2 of class scala/util/parsing/combinator/Parsers
   public final $anonfun$apply$11=class scala/util/parsing/combinator/Parsers$$anonfun$chainr1$2$$anonfun$apply$11 of class scala/util/parsing/combinator/Parsers$$anonfun$chainr1$2
  minor version: 0
  major version: 49
  Constant pool:
Asciz	SourceFile;
Asciz	Parsers.scala;
Asciz	<clinit>;
Asciz	()V;
Asciz	Code;
Asciz	serialVersionUID;
Asciz	J;
Asciz	scala/util/parsing/combinator/Parsers$$anonfun$chainr1$2;
class	scala/util/parsing/combinator/Parsers$$anonfun$chainr1$2
NameAndType	serialVersionUID:J
Field	scala/util/parsing/combinator/Parsers$$anonfun$chainr1$2.serialVersionUID:J
Asciz	first$2;
Asciz	Ljava/lang/Object;;
Asciz	combine$1;
Asciz	Lscala/Function2;;
Asciz	$outer;
Asciz	Lscala/util/parsing/combinator/Parsers;;
Asciz	<init>;
Asciz	(Lscala/util/parsing/combinator/Parsers;Lscala/Function2;Ljava/lang/Object;)V;
Asciz	LineNumberTable;
Asciz	java/lang/NullPointerException;
class	java/lang/NullPointerException
NameAndType	"<init>":()V
Method	java/lang/NullPointerException."<init>":()V
NameAndType	$outer:Lscala/util/parsing/combinator/Parsers;
Field	scala/util/parsing/combinator/Parsers$$anonfun$chainr1$2.$outer:Lscala/util/parsing/combinator/Parsers;
NameAndType	combine$1:Lscala/Function2;
Field	scala/util/parsing/combinator/Parsers$$anonfun$chainr1$2.combine$1:Lscala/Function2;
NameAndType	first$2:Ljava/lang/Object;
Field	scala/util/parsing/combinator/Parsers$$anonfun$chainr1$2.first$2:Ljava/lang/Object;
Asciz	java/lang/Object;
class	java/lang/Object
Method	java/lang/Object."<init>":()V
Asciz	scala/Function1$class;
class	scala/Function1$class
Asciz	$init$;
Asciz	(Lscala/Function1;)V;
NameAndType	$init$:(Lscala/Function1;)V
Method	scala/Function1$class.$init$:(Lscala/Function1;)V
Asciz	this;
Asciz	Lscala/util/parsing/combinator/Parsers$$anonfun$chainr1$2;;
Asciz	LocalVariableTable;
Asciz	apply;
Asciz	(Ljava/lang/Object;)Ljava/lang/Object;;
Asciz	scala/util/parsing/combinator/Parsers$$tilde;
class	scala/util/parsing/combinator/Parsers$$tilde
Asciz	(Lscala/util/parsing/combinator/Parsers$$tilde;)Ljava/lang/Object;;
NameAndType	apply:(Lscala/util/parsing/combinator/Parsers$$tilde;)Ljava/lang/Object;
Method	scala/util/parsing/combinator/Parsers$$anonfun$chainr1$2.apply:(Lscala/util/parsing/combinator/Parsers$$tilde;)Ljava/lang/Object;
Asciz	v1;
Asciz	_1;
Asciz	()Ljava/lang/Object;;
NameAndType	_1:()Ljava/lang/Object;
Method	scala/util/parsing/combinator/Parsers$$tilde._1:()Ljava/lang/Object;
Asciz	_2;
NameAndType	_2:()Ljava/lang/Object;
Method	scala/util/parsing/combinator/Parsers$$tilde._2:()Ljava/lang/Object;
Asciz	scala/collection/immutable/List;
class	scala/collection/immutable/List
Asciz	(Lscala/util/parsing/combinator/Parsers;Ljava/lang/Object;Ljava/lang/Object;)V;
NameAndType	"<init>":(Lscala/util/parsing/combinator/Parsers;Ljava/lang/Object;Ljava/lang/Object;)V
Method	scala/util/parsing/combinator/Parsers$$tilde."<init>":(Lscala/util/parsing/combinator/Parsers;Ljava/lang/Object;Ljava/lang/Object;)V
Asciz	$colon$colon;
Asciz	(Ljava/lang/Object;)Lscala/collection/immutable/List;;
NameAndType	$colon$colon:(Ljava/lang/Object;)Lscala/collection/immutable/List;
Method	scala/collection/immutable/List.$colon$colon:(Ljava/lang/Object;)Lscala/collection/immutable/List;
Asciz	scala/util/parsing/combinator/Parsers$$anonfun$chainr1$2$$anonfun$apply$11;
class	scala/util/parsing/combinator/Parsers$$anonfun$chainr1$2$$anonfun$apply$11
Asciz	(Lscala/util/parsing/combinator/Parsers$$anonfun$chainr1$2;)V;
NameAndType	"<init>":(Lscala/util/parsing/combinator/Parsers$$anonfun$chainr1$2;)V
Method	scala/util/parsing/combinator/Parsers$$anonfun$chainr1$2$$anonfun$apply$11."<init>":(Lscala/util/parsing/combinator/Parsers$$anonfun$chainr1$2;)V
Asciz	scala/collection/LinearSeqLike;
class	scala/collection/LinearSeqLike
Asciz	foldRight;
Asciz	(Ljava/lang/Object;Lscala/Function2;)Ljava/lang/Object;;
NameAndType	foldRight:(Ljava/lang/Object;Lscala/Function2;)Ljava/lang/Object;
InterfaceMethod	scala/collection/LinearSeqLike.foldRight:(Ljava/lang/Object;Lscala/Function2;)Ljava/lang/Object;
Asciz	scala/MatchError;
class	scala/MatchError
Asciz	toString;
Asciz	()Ljava/lang/String;;
NameAndType	toString:()Ljava/lang/String;
Method	scala/util/parsing/combinator/Parsers$$tilde.toString:()Ljava/lang/String;
Asciz	(Ljava/lang/String;)V;
NameAndType	"<init>":(Ljava/lang/String;)V
Method	scala/MatchError."<init>":(Ljava/lang/String;)V
Asciz	temp85;
Asciz	temp86;
Asciz	Lscala/collection/immutable/List;;
Asciz	(Lscala/util/parsing/combinator/Parsers$$tilde<TT;Lscala/collection/immutable/List<Lscala/util/parsing/combinator/Parsers$$tilde<Lscala/Function2<TT;TU;TU;>;TT;>;>;>;)TU;;
Asciz	Signature;
Asciz	andThen;
Asciz	(Lscala/Function1;)Lscala/Function1;;
Asciz	(Lscala/Function1;Lscala/Function1;)Lscala/Function1;;
NameAndType	andThen:(Lscala/Function1;Lscala/Function1;)Lscala/Function1;
Method	scala/Function1$class.andThen:(Lscala/Function1;Lscala/Function1;)Lscala/Function1;
Asciz	g;
Asciz	Lscala/Function1;;
Asciz	compose;
NameAndType	compose:(Lscala/Function1;Lscala/Function1;)Lscala/Function1;
Method	scala/Function1$class.compose:(Lscala/Function1;Lscala/Function1;)Lscala/Function1;
Asciz	(Lscala/Function1;)Ljava/lang/String;;
NameAndType	toString:(Lscala/Function1;)Ljava/lang/String;
Method	scala/Function1$class.toString:(Lscala/Function1;)Ljava/lang/String;
Asciz	Scala;
Asciz	InnerClasses;
Asciz	scala/util/parsing/combinator/Parsers;
class	scala/util/parsing/combinator/Parsers
Asciz	$tilde;
Asciz	$anonfun$chainr1$2;
Asciz	$anonfun$apply$11;
Asciz	scala/Function1;
class	scala/Function1
Asciz	scala/ScalaObject;
class	scala/ScalaObject
Asciz	java/io/Serializable;
class	java/io/Serializable

{
public static final long serialVersionUID;
  Signature: J

private final java.lang.Object first$2;
  Signature: Ljava/lang/Object;

private final scala.Function2 combine$1;
  Signature: Lscala/Function2;

private final scala.util.parsing.combinator.Parsers $outer;
  Signature: Lscala/util/parsing/combinator/Parsers;

public static {};
  Signature: ()V
  Code:
   Stack=2, Locals=0, Args_size=0
	lconst_0
	putstatic	Field serialVersionUID:J
	return
  Labels:

public scala.util.parsing.combinator.Parsers$$anonfun$chainr1$2(scala.util.parsing.combinator.Parsers, scala.Function2, java.lang.Object);
  Signature: (Lscala/util/parsing/combinator/Parsers;Lscala/Function2;Ljava/lang/Object;)V
  Code:
   Stack=2, Locals=4, Args_size=4
	aload_1
	ifnonnull	l1 // aload_0
	new	class java/lang/NullPointerException
	dup
	invokespecial	Method java/lang/NullPointerException."<init>":()V
	athrow
l1	aload_0
	aload_1
	putfield	Field $outer:Lscala/util/parsing/combinator/Parsers;
	aload_0
	aload_2
	putfield	Field combine$1:Lscala/Function2;
	aload_0
	aload_3
	putfield	Field first$2:Ljava/lang/Object;
	aload_0
	invokespecial	Method java/lang/Object."<init>":()V
	aload_0
	invokestatic	Method scala/Function1$class.$init$:(Lscala/Function1;)V
	return
  Labels:
   	l1 = 12 // aload_0
  LocalVariableTable: 
   Start  Length  Slot  Name   Signature
   0      36      0    this       Lscala/util/parsing/combinator/Parsers$$anonfun$chainr1$2;
   0      36      1    $outer       Lscala/util/parsing/combinator/Parsers;


public final java.lang.Object apply(java.lang.Object);
  Signature: (Ljava/lang/Object;)Ljava/lang/Object;
  Code:
   Stack=2, Locals=3, Args_size=2
	aload_0
	getfield	Field $outer:Lscala/util/parsing/combinator/Parsers;
	astore_2
	aload_0
	aload_1
	checkcast	class scala/util/parsing/combinator/Parsers$$tilde
	invokevirtual	Method apply:(Lscala/util/parsing/combinator/Parsers$$tilde;)Ljava/lang/Object;
	areturn
  Labels:
  LocalVariableTable: 
   Start  Length  Slot  Name   Signature
   0      14      0    this       Lscala/util/parsing/combinator/Parsers$$anonfun$chainr1$2;
   5      9      1    v1       Ljava/lang/Object;


public final java.lang.Object apply(scala.util.parsing.combinator.Parsers$$tilde);
  Signature: (Lscala/util/parsing/combinator/Parsers$$tilde;)Ljava/lang/Object;
  Code:
   Stack=5, Locals=6, Args_size=2
	aload_0
	getfield	Field $outer:Lscala/util/parsing/combinator/Parsers;
	astore	5
	aload_1
	ifnull	l1 // new
	aload_1
	invokevirtual	Method scala/util/parsing/combinator/Parsers$$tilde._1:()Ljava/lang/Object;
	astore_2
	aload_1
	invokevirtual	Method scala/util/parsing/combinator/Parsers$$tilde._2:()Ljava/lang/Object;
	checkcast	class scala/collection/immutable/List
	astore_3
	iconst_1
	ifeq	l2 // new
	new	class scala/util/parsing/combinator/Parsers$$tilde
	dup
	aload_0
	getfield	Field $outer:Lscala/util/parsing/combinator/Parsers;
	aload_0
	getfield	Field combine$1:Lscala/Function2;
	aload_2
	invokespecial	Method scala/util/parsing/combinator/Parsers$$tilde."<init>":(Lscala/util/parsing/combinator/Parsers;Ljava/lang/Object;Ljava/lang/Object;)V
	astore	4
	aload_3
	aload	4
	invokevirtual	Method scala/collection/immutable/List.$colon$colon:(Ljava/lang/Object;)Lscala/collection/immutable/List;
	aload_0
	getfield	Field first$2:Ljava/lang/Object;
	new	class scala/util/parsing/combinator/Parsers$$anonfun$chainr1$2$$anonfun$apply$11
	dup
	aload_0
	invokespecial	Method scala/util/parsing/combinator/Parsers$$anonfun$chainr1$2$$anonfun$apply$11."<init>":(Lscala/util/parsing/combinator/Parsers$$anonfun$chainr1$2;)V
	invokeinterface	InterfaceMethod scala/collection/LinearSeqLike.foldRight:(Ljava/lang/Object;Lscala/Function2;)Ljava/lang/Object;
	areturn
l2	new	class scala/MatchError
	dup
	aload_1
	invokevirtual	Method scala/util/parsing/combinator/Parsers$$tilde.toString:()Ljava/lang/String;
	invokespecial	Method scala/MatchError."<init>":(Ljava/lang/String;)V
	athrow
l1	new	class scala/MatchError
	dup
	aload_1
	invokevirtual	Method scala/util/parsing/combinator/Parsers$$tilde.toString:()Ljava/lang/String;
	invokespecial	Method scala/MatchError."<init>":(Ljava/lang/String;)V
	athrow
  Labels:
   	l2 = 69 // new
   	l1 = 81 // new
  LocalVariableTable: 
   Start  Length  Slot  Name   Signature
   0      93      0    this       Lscala/util/parsing/combinator/Parsers$$anonfun$chainr1$2;
   15      66      2    temp85       Ljava/lang/Object;
   23      58      3    temp86       Lscala/collection/immutable/List;

  Signature: length = 0x2
   00 5A 

public scala.Function1 andThen(scala.Function1);
  Signature: (Lscala/Function1;)Lscala/Function1;
  Code:
   Stack=2, Locals=2, Args_size=2
	aload_0
	aload_1
	invokestatic	Method scala/Function1$class.andThen:(Lscala/Function1;Lscala/Function1;)Lscala/Function1;
	areturn
  Labels:
  LocalVariableTable: 
   Start  Length  Slot  Name   Signature
   0      6      0    this       Lscala/util/parsing/combinator/Parsers$$anonfun$chainr1$2;
   0      6      1    g       Lscala/Function1;


public scala.Function1 compose(scala.Function1);
  Signature: (Lscala/Function1;)Lscala/Function1;
  Code:
   Stack=2, Locals=2, Args_size=2
	aload_0
	aload_1
	invokestatic	Method scala/Function1$class.compose:(Lscala/Function1;Lscala/Function1;)Lscala/Function1;
	areturn
  Labels:
  LocalVariableTable: 
   Start  Length  Slot  Name   Signature
   0      6      0    this       Lscala/util/parsing/combinator/Parsers$$anonfun$chainr1$2;
   0      6      1    g       Lscala/Function1;


public java.lang.String toString();
  Signature: ()Ljava/lang/String;
  Code:
   Stack=1, Locals=1, Args_size=1
	aload_0
	invokestatic	Method scala/Function1$class.toString:(Lscala/Function1;)Ljava/lang/String;
	areturn
  Labels:

}

