Compiled from "Parsers.scala"
public final class scala.util.parsing.combinator.Parsers$Parser$$anonfun$append$1$$anonfun$apply$1 extends java.lang.Object implements scala.Function0,scala.ScalaObject,java.io.Serializable
  SourceFile: "Parsers.scala"
  Scala: length = 0x
   
  InnerClass: 
   public abstract Parser=class scala/util/parsing/combinator/Parsers$Parser of class scala/util/parsing/combinator/Parsers
   public abstract ParseResult=class scala/util/parsing/combinator/Parsers$ParseResult of class scala/util/parsing/combinator/Parsers
   public final $anonfun$append$1=class scala/util/parsing/combinator/Parsers$Parser$$anonfun$append$1 of class scala/util/parsing/combinator/Parsers$Parser
   public final $anonfun$apply$1=class scala/util/parsing/combinator/Parsers$Parser$$anonfun$append$1$$anonfun$apply$1 of class scala/util/parsing/combinator/Parsers$Parser$$anonfun$append$1
  minor version: 0
  major version: 49
  Constant pool:
Asciz	SourceFile;
Asciz	Parsers.scala;
Asciz	<clinit>;
Asciz	()V;
Asciz	Code;
Asciz	serialVersionUID;
Asciz	J;
Asciz	scala/util/parsing/combinator/Parsers$Parser$$anonfun$append$1$$anonfun$apply$1;
class	scala/util/parsing/combinator/Parsers$Parser$$anonfun$append$1$$anonfun$apply$1
NameAndType	serialVersionUID:J
Field	scala/util/parsing/combinator/Parsers$Parser$$anonfun$append$1$$anonfun$apply$1.serialVersionUID:J
Asciz	in$1;
Asciz	Lscala/util/parsing/input/Reader;;
Asciz	$outer;
Asciz	Lscala/util/parsing/combinator/Parsers$Parser$$anonfun$append$1;;
Asciz	<init>;
Asciz	(Lscala/util/parsing/combinator/Parsers$Parser$$anonfun$append$1;Lscala/util/parsing/input/Reader;)V;
Asciz	LineNumberTable;
Asciz	java/lang/NullPointerException;
class	java/lang/NullPointerException
NameAndType	"<init>":()V
Method	java/lang/NullPointerException."<init>":()V
NameAndType	$outer:Lscala/util/parsing/combinator/Parsers$Parser$$anonfun$append$1;
Field	scala/util/parsing/combinator/Parsers$Parser$$anonfun$append$1$$anonfun$apply$1.$outer:Lscala/util/parsing/combinator/Parsers$Parser$$anonfun$append$1;
NameAndType	in$1:Lscala/util/parsing/input/Reader;
Field	scala/util/parsing/combinator/Parsers$Parser$$anonfun$append$1$$anonfun$apply$1.in$1:Lscala/util/parsing/input/Reader;
Asciz	java/lang/Object;
class	java/lang/Object
Method	java/lang/Object."<init>":()V
Asciz	scala/Function0$class;
class	scala/Function0$class
Asciz	$init$;
Asciz	(Lscala/Function0;)V;
NameAndType	$init$:(Lscala/Function0;)V
Method	scala/Function0$class.$init$:(Lscala/Function0;)V
Asciz	this;
Asciz	Lscala/util/parsing/combinator/Parsers$Parser$$anonfun$append$1$$anonfun$apply$1;;
Asciz	LocalVariableTable;
Asciz	(Lscala/util/parsing/combinator/Parsers$Parser<TT;>.$anonfun$append$1;)V;
Asciz	Signature;
Asciz	apply;
Asciz	()Ljava/lang/Object;;
Asciz	()Lscala/util/parsing/combinator/Parsers$ParseResult;;
NameAndType	apply:()Lscala/util/parsing/combinator/Parsers$ParseResult;
Method	scala/util/parsing/combinator/Parsers$Parser$$anonfun$append$1$$anonfun$apply$1.apply:()Lscala/util/parsing/combinator/Parsers$ParseResult;
Asciz	scala/util/parsing/combinator/Parsers$Parser$$anonfun$append$1;
class	scala/util/parsing/combinator/Parsers$Parser$$anonfun$append$1
Asciz	p$4;
Asciz	Lscala/Function0;;
NameAndType	p$4:Lscala/Function0;
Field	scala/util/parsing/combinator/Parsers$Parser$$anonfun$append$1.p$4:Lscala/Function0;
Asciz	scala/Function0;
class	scala/Function0
NameAndType	apply:()Ljava/lang/Object;
InterfaceMethod	scala/Function0.apply:()Ljava/lang/Object;
Asciz	scala/util/parsing/combinator/Parsers$Parser;
class	scala/util/parsing/combinator/Parsers$Parser
Asciz	(Lscala/util/parsing/input/Reader;)Lscala/util/parsing/combinator/Parsers$ParseResult;;
NameAndType	apply:(Lscala/util/parsing/input/Reader;)Lscala/util/parsing/combinator/Parsers$ParseResult;
Method	scala/util/parsing/combinator/Parsers$Parser.apply:(Lscala/util/parsing/input/Reader;)Lscala/util/parsing/combinator/Parsers$ParseResult;
Asciz	()Lscala/util/parsing/combinator/Parsers$ParseResult<TU;>;;
Asciz	toString;
Asciz	()Ljava/lang/String;;
Asciz	(Lscala/Function0;)Ljava/lang/String;;
NameAndType	toString:(Lscala/Function0;)Ljava/lang/String;
Method	scala/Function0$class.toString:(Lscala/Function0;)Ljava/lang/String;
Asciz	Scala;
Asciz	InnerClasses;
Asciz	scala/util/parsing/combinator/Parsers;
class	scala/util/parsing/combinator/Parsers
Asciz	Parser;
Asciz	scala/util/parsing/combinator/Parsers$ParseResult;
class	scala/util/parsing/combinator/Parsers$ParseResult
Asciz	ParseResult;
Asciz	$anonfun$append$1;
Asciz	$anonfun$apply$1;
Asciz	scala/ScalaObject;
class	scala/ScalaObject
Asciz	java/io/Serializable;
class	java/io/Serializable

{
public static final long serialVersionUID;
  Signature: J

private final scala.util.parsing.input.Reader in$1;
  Signature: Lscala/util/parsing/input/Reader;

private final scala.util.parsing.combinator.Parsers$Parser$$anonfun$append$1 $outer;
  Signature: Lscala/util/parsing/combinator/Parsers$Parser$$anonfun$append$1;

public static {};
  Signature: ()V
  Code:
   Stack=2, Locals=0, Args_size=0
	lconst_0
	putstatic	Field serialVersionUID:J
	return
  Labels:

public scala.util.parsing.combinator.Parsers$Parser$$anonfun$append$1$$anonfun$apply$1(scala.util.parsing.combinator.Parsers$Parser$$anonfun$append$1, scala.util.parsing.input.Reader);
  Signature: (Lscala/util/parsing/combinator/Parsers$Parser$$anonfun$append$1;Lscala/util/parsing/input/Reader;)V
  Code:
   Stack=2, Locals=3, Args_size=3
	aload_1
	ifnonnull	l1 // aload_0
	new	class java/lang/NullPointerException
	dup
	invokespecial	Method java/lang/NullPointerException."<init>":()V
	athrow
l1	aload_0
	aload_1
	putfield	Field $outer:Lscala/util/parsing/combinator/Parsers$Parser$$anonfun$append$1;
	aload_0
	aload_2
	putfield	Field in$1:Lscala/util/parsing/input/Reader;
	aload_0
	invokespecial	Method java/lang/Object."<init>":()V
	aload_0
	invokestatic	Method scala/Function0$class.$init$:(Lscala/Function0;)V
	return
  Labels:
   	l1 = 12 // aload_0
  LocalVariableTable: 
   Start  Length  Slot  Name   Signature
   0      31      0    this       Lscala/util/parsing/combinator/Parsers$Parser$$anonfun$append$1$$anonfun$apply$1;
   0      31      1    $outer       Lscala/util/parsing/combinator/Parsers$Parser$$anonfun$append$1;

  Signature: length = 0x2
   00 27 

public final java.lang.Object apply();
  Signature: ()Ljava/lang/Object;
  Code:
   Stack=1, Locals=2, Args_size=1
	aload_0
	getfield	Field $outer:Lscala/util/parsing/combinator/Parsers$Parser$$anonfun$append$1;
	astore_1
	aload_0
	invokevirtual	Method apply:()Lscala/util/parsing/combinator/Parsers$ParseResult;
	areturn
  Labels:
  LocalVariableTable: 
   Start  Length  Slot  Name   Signature
   0      10      0    this       Lscala/util/parsing/combinator/Parsers$Parser$$anonfun$append$1$$anonfun$apply$1;


public final scala.util.parsing.combinator.Parsers$ParseResult apply();
  Signature: ()Lscala/util/parsing/combinator/Parsers$ParseResult;
  Code:
   Stack=2, Locals=2, Args_size=1
	aload_0
	getfield	Field $outer:Lscala/util/parsing/combinator/Parsers$Parser$$anonfun$append$1;
	astore_1
	aload_0
	getfield	Field $outer:Lscala/util/parsing/combinator/Parsers$Parser$$anonfun$append$1;
	getfield	Field scala/util/parsing/combinator/Parsers$Parser$$anonfun$append$1.p$4:Lscala/Function0;
	invokeinterface	InterfaceMethod scala/Function0.apply:()Ljava/lang/Object;
	checkcast	class scala/util/parsing/combinator/Parsers$Parser
	aload_0
	getfield	Field in$1:Lscala/util/parsing/input/Reader;
	invokevirtual	Method scala/util/parsing/combinator/Parsers$Parser.apply:(Lscala/util/parsing/input/Reader;)Lscala/util/parsing/combinator/Parsers$ParseResult;
	areturn
  Labels:
  LocalVariableTable: 
   Start  Length  Slot  Name   Signature
   0      28      0    this       Lscala/util/parsing/combinator/Parsers$Parser$$anonfun$append$1$$anonfun$apply$1;

  Signature: length = 0x2
   00 3D 

public java.lang.String toString();
  Signature: ()Ljava/lang/String;
  Code:
   Stack=1, Locals=1, Args_size=1
	aload_0
	invokestatic	Method scala/Function0$class.toString:(Lscala/Function0;)Ljava/lang/String;
	areturn
  Labels:

}

