Compiled from "Parsers.scala"
public final class scala.util.parsing.combinator.Parsers$Parser$$anon$4 extends scala.util.parsing.combinator.Parsers$Parser
  SourceFile: "Parsers.scala"
  Signature: length = 0x2
   00 FFFFFF86 
  Scala: length = 0x
   
  InnerClass: 
   public Error=class scala/util/parsing/combinator/Parsers$Error of class scala/util/parsing/combinator/Parsers
   public abstract Parser=class scala/util/parsing/combinator/Parsers$Parser of class scala/util/parsing/combinator/Parsers
   public Failure=class scala/util/parsing/combinator/Parsers$Failure of class scala/util/parsing/combinator/Parsers
   public Success=class scala/util/parsing/combinator/Parsers$Success of class scala/util/parsing/combinator/Parsers
   public abstract ParseResult=class scala/util/parsing/combinator/Parsers$ParseResult of class scala/util/parsing/combinator/Parsers
   public final $anon$4=class scala/util/parsing/combinator/Parsers$Parser$$anon$4 of class scala/util/parsing/combinator/Parsers$Parser
  minor version: 0
  major version: 49
  Constant pool:
Asciz	SourceFile;
Asciz	Parsers.scala;
Asciz	q$1;
Asciz	Lscala/Function0;;
Asciz	$outer;
Asciz	Lscala/util/parsing/combinator/Parsers$Parser;;
Asciz	<init>;
Asciz	(Lscala/util/parsing/combinator/Parsers$Parser;Lscala/Function0;)V;
Asciz	Code;
Asciz	LineNumberTable;
Asciz	java/lang/NullPointerException;
class	java/lang/NullPointerException
Asciz	()V;
NameAndType	"<init>":()V
Method	java/lang/NullPointerException."<init>":()V
Asciz	scala/util/parsing/combinator/Parsers$Parser$$anon$4;
class	scala/util/parsing/combinator/Parsers$Parser$$anon$4
NameAndType	$outer:Lscala/util/parsing/combinator/Parsers$Parser;
Field	scala/util/parsing/combinator/Parsers$Parser$$anon$4.$outer:Lscala/util/parsing/combinator/Parsers$Parser;
NameAndType	q$1:Lscala/Function0;
Field	scala/util/parsing/combinator/Parsers$Parser$$anon$4.q$1:Lscala/Function0;
Asciz	scala/util/parsing/combinator/Parsers$Parser;
class	scala/util/parsing/combinator/Parsers$Parser
Asciz	scala$util$parsing$combinator$Parsers$Parser$$$outer;
Asciz	()Lscala/util/parsing/combinator/Parsers;;
NameAndType	scala$util$parsing$combinator$Parsers$Parser$$$outer:()Lscala/util/parsing/combinator/Parsers;
Method	scala/util/parsing/combinator/Parsers$Parser.scala$util$parsing$combinator$Parsers$Parser$$$outer:()Lscala/util/parsing/combinator/Parsers;
Asciz	(Lscala/util/parsing/combinator/Parsers;)V;
NameAndType	"<init>":(Lscala/util/parsing/combinator/Parsers;)V
Method	scala/util/parsing/combinator/Parsers$Parser."<init>":(Lscala/util/parsing/combinator/Parsers;)V
Asciz	this;
Asciz	Lscala/util/parsing/combinator/Parsers$Parser$$anon$4;;
Asciz	LocalVariableTable;
Asciz	(Lscala/util/parsing/combinator/Parsers$Parser<TT;>;)V;
Asciz	Signature;
Asciz	apply;
Asciz	(Ljava/lang/Object;)Ljava/lang/Object;;
Asciz	scala/util/parsing/input/Reader;
class	scala/util/parsing/input/Reader
Asciz	(Lscala/util/parsing/input/Reader;)Lscala/util/parsing/combinator/Parsers$ParseResult;;
NameAndType	apply:(Lscala/util/parsing/input/Reader;)Lscala/util/parsing/combinator/Parsers$ParseResult;
Method	scala/util/parsing/combinator/Parsers$Parser$$anon$4.apply:(Lscala/util/parsing/input/Reader;)Lscala/util/parsing/combinator/Parsers$ParseResult;
Asciz	v1;
Asciz	Ljava/lang/Object;;
Asciz	toString;
Asciz	()Ljava/lang/String;;
Asciz	|||;
String	|||
Method	scala/util/parsing/combinator/Parsers$Parser.apply:(Lscala/util/parsing/input/Reader;)Lscala/util/parsing/combinator/Parsers$ParseResult;
Asciz	scala/Function0;
class	scala/Function0
Asciz	()Ljava/lang/Object;;
NameAndType	apply:()Ljava/lang/Object;
InterfaceMethod	scala/Function0.apply:()Ljava/lang/Object;
Asciz	scala/util/parsing/combinator/Parsers$Success;
class	scala/util/parsing/combinator/Parsers$Success
Asciz	next;
Asciz	()Lscala/util/parsing/input/Reader;;
NameAndType	next:()Lscala/util/parsing/input/Reader;
Method	scala/util/parsing/combinator/Parsers$Success.next:()Lscala/util/parsing/input/Reader;
Asciz	pos;
Asciz	()Lscala/util/parsing/input/Position;;
NameAndType	pos:()Lscala/util/parsing/input/Position;
Method	scala/util/parsing/input/Reader.pos:()Lscala/util/parsing/input/Position;
Asciz	scala/util/parsing/input/Position;
class	scala/util/parsing/input/Position
Asciz	$less;
Asciz	(Lscala/util/parsing/input/Position;)Z;
NameAndType	$less:(Lscala/util/parsing/input/Position;)Z
InterfaceMethod	scala/util/parsing/input/Position.$less:(Lscala/util/parsing/input/Position;)Z
Asciz	scala/MatchError;
class	scala/MatchError
Asciz	scala/Tuple2;
class	scala/Tuple2
Asciz	(Ljava/lang/Object;Ljava/lang/Object;)V;
NameAndType	"<init>":(Ljava/lang/Object;Ljava/lang/Object;)V
Method	scala/Tuple2."<init>":(Ljava/lang/Object;Ljava/lang/Object;)V
NameAndType	toString:()Ljava/lang/String;
Method	scala/Tuple2.toString:()Ljava/lang/String;
Asciz	(Ljava/lang/String;)V;
NameAndType	"<init>":(Ljava/lang/String;)V
Method	scala/MatchError."<init>":(Ljava/lang/String;)V
Asciz	scala/util/parsing/combinator/Parsers$Error;
class	scala/util/parsing/combinator/Parsers$Error
Asciz	scala/util/parsing/combinator/Parsers$Failure;
class	scala/util/parsing/combinator/Parsers$Failure
Method	scala/util/parsing/combinator/Parsers$Failure.next:()Lscala/util/parsing/input/Reader;
Asciz	scala/util/parsing/combinator/Parsers;
class	scala/util/parsing/combinator/Parsers
Asciz	NoSuccess;
Asciz	()Lscala/util/parsing/combinator/Parsers$NoSuccess$;;
NameAndType	NoSuccess:()Lscala/util/parsing/combinator/Parsers$NoSuccess$;
InterfaceMethod	scala/util/parsing/combinator/Parsers.NoSuccess:()Lscala/util/parsing/combinator/Parsers$NoSuccess$;
Asciz	scala/util/parsing/combinator/Parsers$NoSuccess$;
class	scala/util/parsing/combinator/Parsers$NoSuccess$
Asciz	unapply;
Asciz	(Lscala/util/parsing/combinator/Parsers$ParseResult;)Lscala/Option;;
NameAndType	unapply:(Lscala/util/parsing/combinator/Parsers$ParseResult;)Lscala/Option;
Method	scala/util/parsing/combinator/Parsers$NoSuccess$.unapply:(Lscala/util/parsing/combinator/Parsers$ParseResult;)Lscala/Option;
Asciz	scala/Option;
class	scala/Option
Asciz	isEmpty;
Asciz	()Z;
NameAndType	isEmpty:()Z
Method	scala/Option.isEmpty:()Z
Asciz	get;
NameAndType	get:()Ljava/lang/Object;
Method	scala/Option.get:()Ljava/lang/Object;
Asciz	_2;
NameAndType	_2:()Ljava/lang/Object;
Method	scala/Tuple2._2:()Ljava/lang/Object;
Asciz	in;
Asciz	Lscala/util/parsing/input/Reader;;
Asciz	temp33;
Asciz	temp30;
Asciz	temp31;
Asciz	Lscala/util/parsing/combinator/Parsers$Success;;
Asciz	temp28;
Asciz	temp34;
Asciz	temp37;
Asciz	Lscala/util/parsing/combinator/Parsers$Error;;
Asciz	temp43;
Asciz	Lscala/Option;;
Asciz	temp44;
Asciz	Lscala/Tuple2;;
Asciz	temp46;
Asciz	temp42;
Asciz	temp40;
Asciz	Lscala/util/parsing/combinator/Parsers$Failure;;
Asciz	res1;
Asciz	Lscala/util/parsing/combinator/Parsers$ParseResult;;
Asciz	res2;
Asciz	(Lscala/util/parsing/input/Reader<Ljava/lang/Object;>;)Lscala/util/parsing/combinator/Parsers$ParseResult<TU;>;;
Asciz	Lscala/util/parsing/combinator/Parsers$Parser<TU;>;;
Asciz	Scala;
Asciz	InnerClasses;
Asciz	Error;
Asciz	Parser;
Asciz	Failure;
Asciz	Success;
Asciz	scala/util/parsing/combinator/Parsers$ParseResult;
class	scala/util/parsing/combinator/Parsers$ParseResult
Asciz	ParseResult;
Asciz	$anon$4;

{
private final scala.Function0 q$1;
  Signature: Lscala/Function0;

private final scala.util.parsing.combinator.Parsers$Parser $outer;
  Signature: Lscala/util/parsing/combinator/Parsers$Parser;

public scala.util.parsing.combinator.Parsers$Parser$$anon$4(scala.util.parsing.combinator.Parsers$Parser, scala.Function0);
  Signature: (Lscala/util/parsing/combinator/Parsers$Parser;Lscala/Function0;)V
  Code:
   Stack=2, Locals=3, Args_size=3
	aload_1
	ifnonnull	l1 // aload_0
	new	class java/lang/NullPointerException
	dup
	invokespecial	Method java/lang/NullPointerException."<init>":()V
	athrow
l1	aload_0
	aload_1
	putfield	Field $outer:Lscala/util/parsing/combinator/Parsers$Parser;
	aload_0
	aload_2
	putfield	Field q$1:Lscala/Function0;
	aload_0
	aload_1
	invokevirtual	Method scala/util/parsing/combinator/Parsers$Parser.scala$util$parsing$combinator$Parsers$Parser$$$outer:()Lscala/util/parsing/combinator/Parsers;
	invokespecial	Method scala/util/parsing/combinator/Parsers$Parser."<init>":(Lscala/util/parsing/combinator/Parsers;)V
	return
  Labels:
   	l1 = 12 // aload_0
  LocalVariableTable: 
   Start  Length  Slot  Name   Signature
   0      31      0    this       Lscala/util/parsing/combinator/Parsers$Parser$$anon$4;
   0      31      1    $outer       Lscala/util/parsing/combinator/Parsers$Parser;

  Signature: length = 0x2
   00 22 

public java.lang.Object apply(java.lang.Object);
  Signature: (Ljava/lang/Object;)Ljava/lang/Object;
  Code:
   Stack=2, Locals=2, Args_size=2
	aload_0
	aload_1
	checkcast	class scala/util/parsing/input/Reader
	invokevirtual	Method apply:(Lscala/util/parsing/input/Reader;)Lscala/util/parsing/combinator/Parsers$ParseResult;
	areturn
  Labels:
  LocalVariableTable: 
   Start  Length  Slot  Name   Signature
   0      9      0    this       Lscala/util/parsing/combinator/Parsers$Parser$$anon$4;
   0      9      1    v1       Ljava/lang/Object;


public java.lang.String toString();
  Signature: ()Ljava/lang/String;
  Code:
   Stack=1, Locals=1, Args_size=1
	ldc	String |||
	areturn
  Labels:

public scala.util.parsing.combinator.Parsers$ParseResult apply(scala.util.parsing.input.Reader);
  Signature: (Lscala/util/parsing/input/Reader;)Lscala/util/parsing/combinator/Parsers$ParseResult;
  Code:
   Stack=6, Locals=15, Args_size=2
	aload_0
	getfield	Field $outer:Lscala/util/parsing/combinator/Parsers$Parser;
	aload_1
	invokevirtual	Method scala/util/parsing/combinator/Parsers$Parser.apply:(Lscala/util/parsing/input/Reader;)Lscala/util/parsing/combinator/Parsers$ParseResult;
	astore	13
	aload_0
	getfield	Field q$1:Lscala/Function0;
	invokeinterface	InterfaceMethod scala/Function0.apply:()Ljava/lang/Object;
	checkcast	class scala/util/parsing/combinator/Parsers$Parser
	aload_1
	invokevirtual	Method scala/util/parsing/combinator/Parsers$Parser.apply:(Lscala/util/parsing/input/Reader;)Lscala/util/parsing/combinator/Parsers$ParseResult;
	astore	14
	aload	13
	instanceof	class scala/util/parsing/combinator/Parsers$Success
	ifeq	l1 // aload
	aload	13
	checkcast	class scala/util/parsing/combinator/Parsers$Success
	astore	5
	aload	5
	invokevirtual	Method scala/util/parsing/combinator/Parsers$Success.next:()Lscala/util/parsing/input/Reader;
	astore_3
	aload	14
	instanceof	class scala/util/parsing/combinator/Parsers$Success
	ifeq	l2 // iconst_1
	aload	14
	checkcast	class scala/util/parsing/combinator/Parsers$Success
	astore	4
	aload	4
	invokevirtual	Method scala/util/parsing/combinator/Parsers$Success.next:()Lscala/util/parsing/input/Reader;
	astore_2
	iconst_1
	ifeq	l3 // new
	aload_2
	invokevirtual	Method scala/util/parsing/input/Reader.pos:()Lscala/util/parsing/input/Position;
	aload_3
	invokevirtual	Method scala/util/parsing/input/Reader.pos:()Lscala/util/parsing/input/Position;
	invokeinterface	InterfaceMethod scala/util/parsing/input/Position.$less:(Lscala/util/parsing/input/Position;)Z
	ifeq	l4 // aload
	aload	5
	goto	l5 // areturn
l4	aload	4
	goto	l5 // areturn
l3	new	class scala/MatchError
	dup
	new	class scala/Tuple2
	dup
	aload	13
	aload	14
	invokespecial	Method scala/Tuple2."<init>":(Ljava/lang/Object;Ljava/lang/Object;)V
	invokevirtual	Method scala/Tuple2.toString:()Ljava/lang/String;
	invokespecial	Method scala/MatchError."<init>":(Ljava/lang/String;)V
	athrow
l2	iconst_1
	ifeq	l6 // new
	aload	5
	goto	l5 // areturn
l6	new	class scala/MatchError
	dup
	new	class scala/Tuple2
	dup
	aload	13
	aload	14
	invokespecial	Method scala/Tuple2."<init>":(Ljava/lang/Object;Ljava/lang/Object;)V
	invokevirtual	Method scala/Tuple2.toString:()Ljava/lang/String;
	invokespecial	Method scala/MatchError."<init>":(Ljava/lang/String;)V
	athrow
l1	aload	14
	instanceof	class scala/util/parsing/combinator/Parsers$Success
	ifeq	l7 // aload
	aload	14
	checkcast	class scala/util/parsing/combinator/Parsers$Success
	astore	6
	iconst_1
	ifeq	l8 // new
	aload	6
	goto	l5 // areturn
l8	new	class scala/MatchError
	dup
	new	class scala/Tuple2
	dup
	aload	13
	aload	14
	invokespecial	Method scala/Tuple2."<init>":(Ljava/lang/Object;Ljava/lang/Object;)V
	invokevirtual	Method scala/Tuple2.toString:()Ljava/lang/String;
	invokespecial	Method scala/MatchError."<init>":(Ljava/lang/String;)V
	athrow
l7	aload	13
	instanceof	class scala/util/parsing/combinator/Parsers$Error
	ifeq	l9 // aload
	aload	13
	checkcast	class scala/util/parsing/combinator/Parsers$Error
	astore	7
	iconst_1
	ifeq	l10 // new
	aload	7
	goto	l5 // areturn
l10	new	class scala/MatchError
	dup
	new	class scala/Tuple2
	dup
	aload	13
	aload	14
	invokespecial	Method scala/Tuple2."<init>":(Ljava/lang/Object;Ljava/lang/Object;)V
	invokevirtual	Method scala/Tuple2.toString:()Ljava/lang/String;
	invokespecial	Method scala/MatchError."<init>":(Ljava/lang/String;)V
	athrow
l9	aload	13
	instanceof	class scala/util/parsing/combinator/Parsers$Failure
	ifeq	l11 // new
	aload	13
	checkcast	class scala/util/parsing/combinator/Parsers$Failure
	astore	12
	aload	12
	invokevirtual	Method scala/util/parsing/combinator/Parsers$Failure.next:()Lscala/util/parsing/input/Reader;
	astore	11
	aload_0
	getfield	Field $outer:Lscala/util/parsing/combinator/Parsers$Parser;
	invokevirtual	Method scala/util/parsing/combinator/Parsers$Parser.scala$util$parsing$combinator$Parsers$Parser$$$outer:()Lscala/util/parsing/combinator/Parsers;
	invokeinterface	InterfaceMethod scala/util/parsing/combinator/Parsers.NoSuccess:()Lscala/util/parsing/combinator/Parsers$NoSuccess$;
	aload	14
	invokevirtual	Method scala/util/parsing/combinator/Parsers$NoSuccess$.unapply:(Lscala/util/parsing/combinator/Parsers$ParseResult;)Lscala/Option;
	astore	8
	aload	8
	invokevirtual	Method scala/Option.isEmpty:()Z
	ifeq	l12 // aload
	new	class scala/MatchError
	dup
	new	class scala/Tuple2
	dup
	aload	13
	aload	14
	invokespecial	Method scala/Tuple2."<init>":(Ljava/lang/Object;Ljava/lang/Object;)V
	invokevirtual	Method scala/Tuple2.toString:()Ljava/lang/String;
	invokespecial	Method scala/MatchError."<init>":(Ljava/lang/String;)V
	athrow
l12	aload	8
	invokevirtual	Method scala/Option.get:()Ljava/lang/Object;
	checkcast	class scala/Tuple2
	astore	9
	aload	9
	invokevirtual	Method scala/Tuple2._2:()Ljava/lang/Object;
	checkcast	class scala/util/parsing/input/Reader
	astore	10
	iconst_1
	ifeq	l13 // new
	aload	10
	invokevirtual	Method scala/util/parsing/input/Reader.pos:()Lscala/util/parsing/input/Position;
	aload	11
	invokevirtual	Method scala/util/parsing/input/Reader.pos:()Lscala/util/parsing/input/Position;
	invokeinterface	InterfaceMethod scala/util/parsing/input/Position.$less:(Lscala/util/parsing/input/Position;)Z
	ifeq	l14 // aload
	aload	12
	goto	l5 // areturn
l14	aload	14
l5	areturn
l13	new	class scala/MatchError
	dup
	new	class scala/Tuple2
	dup
	aload	13
	aload	14
	invokespecial	Method scala/Tuple2."<init>":(Ljava/lang/Object;Ljava/lang/Object;)V
	invokevirtual	Method scala/Tuple2.toString:()Ljava/lang/String;
	invokespecial	Method scala/MatchError."<init>":(Ljava/lang/String;)V
	athrow
l11	new	class scala/MatchError
	dup
	new	class scala/Tuple2
	dup
	aload	13
	aload	14
	invokespecial	Method scala/Tuple2."<init>":(Ljava/lang/Object;Ljava/lang/Object;)V
	invokevirtual	Method scala/Tuple2.toString:()Ljava/lang/String;
	invokespecial	Method scala/MatchError."<init>":(Ljava/lang/String;)V
	athrow
  Labels:
   	l4 = 95 // aload
   	l3 = 100 // new
   	l2 = 122 // iconst_1
   	l6 = 131 // new
   	l1 = 153 // aload
   	l8 = 177 // new
   	l7 = 199 // aload
   	l10 = 223 // new
   	l9 = 245 // aload
   	l12 = 316 // aload
   	l14 = 363 // aload
   	l5 = 365 // areturn
   	l13 = 366 // new
   	l11 = 388 // new
  LocalVariableTable: 
   Start  Length  Slot  Name   Signature
   0      410      0    this       Lscala/util/parsing/combinator/Parsers$Parser$$anon$4;
   0      410      1    in       Lscala/util/parsing/input/Reader;
   70      52      2    temp33       Lscala/util/parsing/input/Reader;
   49      104      3    temp30       Lscala/util/parsing/input/Reader;
   64      58      4    temp31       Lscala/util/parsing/combinator/Parsers$Success;
   43      110      5    temp28       Lscala/util/parsing/combinator/Parsers$Success;
   168      31      6    temp34       Lscala/util/parsing/combinator/Parsers$Success;
   214      31      7    temp37       Lscala/util/parsing/combinator/Parsers$Error;
   286      79      8    temp43       Lscala/Option;
   366      22      8    temp43       Lscala/Option;
   326      39      9    temp44       Lscala/Tuple2;
   366      22      9    temp44       Lscala/Tuple2;
   336      29      10    temp46       Lscala/util/parsing/input/Reader;
   366      22      10    temp46       Lscala/util/parsing/input/Reader;
   267      98      11    temp42       Lscala/util/parsing/input/Reader;
   366      22      11    temp42       Lscala/util/parsing/input/Reader;
   260      105      12    temp40       Lscala/util/parsing/combinator/Parsers$Failure;
   366      22      12    temp40       Lscala/util/parsing/combinator/Parsers$Failure;
   10      400      13    res1       Lscala/util/parsing/combinator/Parsers$ParseResult;
   28      382      14    res2       Lscala/util/parsing/combinator/Parsers$ParseResult;

  Signature: length = 0x2
   00 FFFFFF85 

}

