Compiled from "Parsers.scala"
public final class scala.util.parsing.combinator.Parsers$Parser$$anonfun$$less$tilde$1 extends scala.runtime.AbstractFunction1 implements java.io.Serializable
  SourceFile: "Parsers.scala"
  Scala: length = 0x
   
  InnerClass: 
   public abstract Parser=class scala/util/parsing/combinator/Parsers$Parser of class scala/util/parsing/combinator/Parsers
   public final $anonfun$$less$tilde$1=class scala/util/parsing/combinator/Parsers$Parser$$anonfun$$less$tilde$1 of class scala/util/parsing/combinator/Parsers$Parser
   public final $anonfun$apply$4=class scala/util/parsing/combinator/Parsers$Parser$$anonfun$$less$tilde$1$$anonfun$apply$4 of class scala/util/parsing/combinator/Parsers$Parser$$anonfun$$less$tilde$1
  minor version: 0
  major version: 49
  Constant pool:
Asciz	SourceFile;
Asciz	Parsers.scala;
Asciz	<clinit>;
Asciz	()V;
Asciz	Code;
Asciz	serialVersionUID;
Asciz	J;
Asciz	scala/util/parsing/combinator/Parsers$Parser$$anonfun$$less$tilde$1;
class	scala/util/parsing/combinator/Parsers$Parser$$anonfun$$less$tilde$1
NameAndType	serialVersionUID:J
Field	scala/util/parsing/combinator/Parsers$Parser$$anonfun$$less$tilde$1.serialVersionUID:J
Asciz	p$6;
Asciz	Lscala/Function0;;
Asciz	<init>;
Asciz	(Lscala/util/parsing/combinator/Parsers$Parser;Lscala/Function0;)V;
Asciz	LineNumberTable;
NameAndType	p$6:Lscala/Function0;
Field	scala/util/parsing/combinator/Parsers$Parser$$anonfun$$less$tilde$1.p$6:Lscala/Function0;
Asciz	scala/runtime/AbstractFunction1;
class	scala/runtime/AbstractFunction1
NameAndType	"<init>":()V
Method	scala/runtime/AbstractFunction1."<init>":()V
Asciz	this;
Asciz	Lscala/util/parsing/combinator/Parsers$Parser$$anonfun$$less$tilde$1;;
Asciz	$outer;
Asciz	Lscala/util/parsing/combinator/Parsers$Parser;;
Asciz	LocalVariableTable;
Asciz	(Lscala/util/parsing/combinator/Parsers$Parser<TT;>;)V;
Asciz	Signature;
Asciz	apply;
Asciz	(Ljava/lang/Object;)Ljava/lang/Object;;
Asciz	(Ljava/lang/Object;)Lscala/util/parsing/combinator/Parsers$Parser;;
NameAndType	apply:(Ljava/lang/Object;)Lscala/util/parsing/combinator/Parsers$Parser;
Method	scala/util/parsing/combinator/Parsers$Parser$$anonfun$$less$tilde$1.apply:(Ljava/lang/Object;)Lscala/util/parsing/combinator/Parsers$Parser;
Asciz	v1;
Asciz	Ljava/lang/Object;;
Asciz	scala/Function0;
class	scala/Function0
Asciz	()Ljava/lang/Object;;
NameAndType	apply:()Ljava/lang/Object;
InterfaceMethod	scala/Function0.apply:()Ljava/lang/Object;
Asciz	scala/util/parsing/combinator/Parsers$Parser;
class	scala/util/parsing/combinator/Parsers$Parser
Asciz	scala/util/parsing/combinator/Parsers$Parser$$anonfun$$less$tilde$1$$anonfun$apply$4;
class	scala/util/parsing/combinator/Parsers$Parser$$anonfun$$less$tilde$1$$anonfun$apply$4
Asciz	(Lscala/util/parsing/combinator/Parsers$Parser$$anonfun$$less$tilde$1;Ljava/lang/Object;)V;
NameAndType	"<init>":(Lscala/util/parsing/combinator/Parsers$Parser$$anonfun$$less$tilde$1;Ljava/lang/Object;)V
Method	scala/util/parsing/combinator/Parsers$Parser$$anonfun$$less$tilde$1$$anonfun$apply$4."<init>":(Lscala/util/parsing/combinator/Parsers$Parser$$anonfun$$less$tilde$1;Ljava/lang/Object;)V
Asciz	map;
Asciz	(Lscala/Function1;)Lscala/util/parsing/combinator/Parsers$Parser;;
NameAndType	map:(Lscala/Function1;)Lscala/util/parsing/combinator/Parsers$Parser;
Method	scala/util/parsing/combinator/Parsers$Parser.map:(Lscala/Function1;)Lscala/util/parsing/combinator/Parsers$Parser;
Asciz	a$2;
Asciz	(TT;)Lscala/util/parsing/combinator/Parsers$Parser<TT;>;;
Asciz	Scala;
Asciz	InnerClasses;
Asciz	scala/util/parsing/combinator/Parsers;
class	scala/util/parsing/combinator/Parsers
Asciz	Parser;
Asciz	$anonfun$$less$tilde$1;
Asciz	$anonfun$apply$4;
Asciz	java/io/Serializable;
class	java/io/Serializable

{
public static final long serialVersionUID;
  Signature: J

public final scala.Function0 p$6;
  Signature: Lscala/Function0;

public static {};
  Signature: ()V
  Code:
   Stack=2, Locals=0, Args_size=0
	lconst_0
	putstatic	Field serialVersionUID:J
	return
  Labels:

public scala.util.parsing.combinator.Parsers$Parser$$anonfun$$less$tilde$1(scala.util.parsing.combinator.Parsers$Parser, scala.Function0);
  Signature: (Lscala/util/parsing/combinator/Parsers$Parser;Lscala/Function0;)V
  Code:
   Stack=2, Locals=3, Args_size=3
	aload_0
	aload_2
	putfield	Field p$6:Lscala/Function0;
	aload_0
	invokespecial	Method scala/runtime/AbstractFunction1."<init>":()V
	return
  Labels:
  LocalVariableTable: 
   Start  Length  Slot  Name   Signature
   0      10      0    this       Lscala/util/parsing/combinator/Parsers$Parser$$anonfun$$less$tilde$1;
   0      10      1    $outer       Lscala/util/parsing/combinator/Parsers$Parser;

  Signature: length = 0x2
   00 1C 

public final java.lang.Object apply(java.lang.Object);
  Signature: (Ljava/lang/Object;)Ljava/lang/Object;
  Code:
   Stack=2, Locals=2, Args_size=2
	aload_0
	aload_1
	invokevirtual	Method apply:(Ljava/lang/Object;)Lscala/util/parsing/combinator/Parsers$Parser;
	areturn
  Labels:
  LocalVariableTable: 
   Start  Length  Slot  Name   Signature
   0      6      0    this       Lscala/util/parsing/combinator/Parsers$Parser$$anonfun$$less$tilde$1;
   0      6      1    v1       Ljava/lang/Object;


public final scala.util.parsing.combinator.Parsers$Parser apply(java.lang.Object);
  Signature: (Ljava/lang/Object;)Lscala/util/parsing/combinator/Parsers$Parser;
  Code:
   Stack=5, Locals=2, Args_size=2
	aload_0
	getfield	Field p$6:Lscala/Function0;
	invokeinterface	InterfaceMethod scala/Function0.apply:()Ljava/lang/Object;
	checkcast	class scala/util/parsing/combinator/Parsers$Parser
	new	class scala/util/parsing/combinator/Parsers$Parser$$anonfun$$less$tilde$1$$anonfun$apply$4
	dup
	aload_0
	aload_1
	invokespecial	Method scala/util/parsing/combinator/Parsers$Parser$$anonfun$$less$tilde$1$$anonfun$apply$4."<init>":(Lscala/util/parsing/combinator/Parsers$Parser$$anonfun$$less$tilde$1;Ljava/lang/Object;)V
	invokevirtual	Method scala/util/parsing/combinator/Parsers$Parser.map:(Lscala/Function1;)Lscala/util/parsing/combinator/Parsers$Parser;
	areturn
  Labels:
  LocalVariableTable: 
   Start  Length  Slot  Name   Signature
   0      25      0    this       Lscala/util/parsing/combinator/Parsers$Parser$$anonfun$$less$tilde$1;
   0      25      1    a$2       Ljava/lang/Object;

  Signature: length = 0x2
   00 36 

}

