Compiled from "Parsers.scala"
public class scala.util.parsing.combinator.Parsers$Failure extends scala.util.parsing.combinator.Parsers$NoSuccess implements scala.ScalaObject,scala.Product,java.io.Serializable
  SourceFile: "Parsers.scala"
  Scala: length = 0x
   
  InnerClass: 
   public Success=class scala/util/parsing/combinator/Parsers$Success of class scala/util/parsing/combinator/Parsers
   public Failure=class scala/util/parsing/combinator/Parsers$Failure of class scala/util/parsing/combinator/Parsers
   public abstract NoSuccess=class scala/util/parsing/combinator/Parsers$NoSuccess of class scala/util/parsing/combinator/Parsers
   public abstract ParseResult=class scala/util/parsing/combinator/Parsers$ParseResult of class scala/util/parsing/combinator/Parsers
  minor version: 0
  major version: 49
  Constant pool:
Asciz	SourceFile;
Asciz	Parsers.scala;
Asciz	productIterator;
Asciz	()Lscala/collection/Iterator;;
Asciz	Code;
Asciz	LineNumberTable;
Asciz	scala/Product$class;
class	scala/Product$class
Asciz	(Lscala/Product;)Lscala/collection/Iterator;;
NameAndType	productIterator:(Lscala/Product;)Lscala/collection/Iterator;
Method	scala/Product$class.productIterator:(Lscala/Product;)Lscala/collection/Iterator;
Asciz	productElements;
NameAndType	productElements:(Lscala/Product;)Lscala/collection/Iterator;
Method	scala/Product$class.productElements:(Lscala/Product;)Lscala/collection/Iterator;
Asciz	Deprecated;
Asciz	copy$default$2;
Asciz	()Lscala/util/parsing/input/Reader;;
Asciz	scala/util/parsing/combinator/Parsers$Failure;
class	scala/util/parsing/combinator/Parsers$Failure
Asciz	next;
NameAndType	next:()Lscala/util/parsing/input/Reader;
Method	scala/util/parsing/combinator/Parsers$Failure.next:()Lscala/util/parsing/input/Reader;
Asciz	copy$default$1;
Asciz	()Ljava/lang/String;;
Asciz	msg;
NameAndType	msg:()Ljava/lang/String;
Method	scala/util/parsing/combinator/Parsers$Failure.msg:()Ljava/lang/String;
Asciz	scala/util/parsing/combinator/Parsers$NoSuccess;
class	scala/util/parsing/combinator/Parsers$NoSuccess
Method	scala/util/parsing/combinator/Parsers$NoSuccess.msg:()Ljava/lang/String;
Method	scala/util/parsing/combinator/Parsers$NoSuccess.next:()Lscala/util/parsing/input/Reader;
Asciz	()Lscala/util/parsing/input/Reader<Ljava/lang/Object;>;;
Asciz	Signature;
Asciz	toString;
Asciz	scala/collection/mutable/StringBuilder;
class	scala/collection/mutable/StringBuilder
Asciz	<init>;
Asciz	()V;
NameAndType	"<init>":()V
Method	scala/collection/mutable/StringBuilder."<init>":()V
Asciz	[;
String	[
Asciz	append;
Asciz	(Ljava/lang/Object;)Lscala/collection/mutable/StringBuilder;;
NameAndType	append:(Ljava/lang/Object;)Lscala/collection/mutable/StringBuilder;
Method	scala/collection/mutable/StringBuilder.append:(Ljava/lang/Object;)Lscala/collection/mutable/StringBuilder;
Asciz	scala/util/parsing/input/Reader;
class	scala/util/parsing/input/Reader
Asciz	pos;
Asciz	()Lscala/util/parsing/input/Position;;
NameAndType	pos:()Lscala/util/parsing/input/Position;
Method	scala/util/parsing/input/Reader.pos:()Lscala/util/parsing/input/Position;
Asciz	] failure: ;
String	] failure: 
Asciz	\n\n;
String	\n\n
Asciz	scala/util/parsing/input/Position;
class	scala/util/parsing/input/Position
Asciz	longString;
NameAndType	longString:()Ljava/lang/String;
InterfaceMethod	scala/util/parsing/input/Position.longString:()Ljava/lang/String;
NameAndType	toString:()Ljava/lang/String;
Method	scala/collection/mutable/StringBuilder.toString:()Ljava/lang/String;
Asciz	(Lscala/Function0;)Lscala/util/parsing/combinator/Parsers$ParseResult;;
Asciz	scala/Function0;
class	scala/Function0
Asciz	apply;
Asciz	()Ljava/lang/Object;;
NameAndType	apply:()Ljava/lang/Object;
InterfaceMethod	scala/Function0.apply:()Ljava/lang/Object;
Asciz	scala/util/parsing/combinator/Parsers$ParseResult;
class	scala/util/parsing/combinator/Parsers$ParseResult
Asciz	scala/util/parsing/combinator/Parsers$Success;
class	scala/util/parsing/combinator/Parsers$Success
Method	scala/util/parsing/combinator/Parsers$ParseResult.next:()Lscala/util/parsing/input/Reader;
Asciz	$less;
Asciz	(Lscala/util/parsing/input/Position;)Z;
NameAndType	$less:(Lscala/util/parsing/input/Position;)Z
InterfaceMethod	scala/util/parsing/input/Position.$less:(Lscala/util/parsing/input/Position;)Z
Asciz	scala/MatchError;
class	scala/MatchError
Method	scala/util/parsing/combinator/Parsers$ParseResult.toString:()Ljava/lang/String;
Asciz	(Ljava/lang/String;)V;
NameAndType	"<init>":(Ljava/lang/String;)V
Method	scala/MatchError."<init>":(Ljava/lang/String;)V
Asciz	this;
Asciz	Lscala/util/parsing/combinator/Parsers$Failure;;
Asciz	a;
Asciz	Lscala/Function0;;
Asciz	alt;
Asciz	Lscala/util/parsing/combinator/Parsers$ParseResult;;
Asciz	LocalVariableTable;
Asciz	<U:Ljava/lang/Object;>(Lscala/Function0<Lscala/util/parsing/combinator/Parsers$ParseResult<TU;>;>;)Lscala/util/parsing/combinator/Parsers$ParseResult<TU;>;;
Asciz	copy;
Asciz	(Ljava/lang/String;Lscala/util/parsing/input/Reader;)Lscala/util/parsing/combinator/Parsers$Failure;;
Asciz	scala$util$parsing$combinator$Parsers$Failure$$$outer;
Asciz	()Lscala/util/parsing/combinator/Parsers;;
NameAndType	scala$util$parsing$combinator$Parsers$Failure$$$outer:()Lscala/util/parsing/combinator/Parsers;
Method	scala/util/parsing/combinator/Parsers$Failure.scala$util$parsing$combinator$Parsers$Failure$$$outer:()Lscala/util/parsing/combinator/Parsers;
Asciz	(Lscala/util/parsing/combinator/Parsers;Ljava/lang/String;Lscala/util/parsing/input/Reader;)V;
NameAndType	"<init>":(Lscala/util/parsing/combinator/Parsers;Ljava/lang/String;Lscala/util/parsing/input/Reader;)V
Method	scala/util/parsing/combinator/Parsers$Failure."<init>":(Lscala/util/parsing/combinator/Parsers;Ljava/lang/String;Lscala/util/parsing/input/Reader;)V
Asciz	Ljava/lang/String;;
Asciz	Lscala/util/parsing/input/Reader;;
Asciz	hashCode;
Asciz	()I;
Asciz	scala/runtime/ScalaRunTime$;
class	scala/runtime/ScalaRunTime$
Asciz	MODULE$;
Asciz	Lscala/runtime/ScalaRunTime$;;
NameAndType	MODULE$:Lscala/runtime/ScalaRunTime$;
Field	scala/runtime/ScalaRunTime$.MODULE$:Lscala/runtime/ScalaRunTime$;
Asciz	_hashCode;
Asciz	(Lscala/Product;)I;
NameAndType	_hashCode:(Lscala/Product;)I
Method	scala/runtime/ScalaRunTime$._hashCode:(Lscala/Product;)I
Asciz	equals;
Asciz	(Ljava/lang/Object;)Z;
Asciz	gd2$1;
Asciz	(Ljava/lang/String;Lscala/util/parsing/input/Reader;)Z;
NameAndType	gd2$1:(Ljava/lang/String;Lscala/util/parsing/input/Reader;)Z
Method	scala/util/parsing/combinator/Parsers$Failure.gd2$1:(Ljava/lang/String;Lscala/util/parsing/input/Reader;)Z
Asciz	scala/Equals;
class	scala/Equals
Asciz	canEqual;
NameAndType	canEqual:(Ljava/lang/Object;)Z
InterfaceMethod	scala/Equals.canEqual:(Ljava/lang/Object;)Z
Asciz	temp19;
Asciz	temp20;
Asciz	temp21;
Asciz	productPrefix;
Asciz	Failure;
String	Failure
Asciz	productArity;
Asciz	productElement;
Asciz	(I)Ljava/lang/Object;;
Asciz	java/lang/IndexOutOfBoundsException;
class	java/lang/IndexOutOfBoundsException
Asciz	scala/runtime/BoxesRunTime;
class	scala/runtime/BoxesRunTime
Asciz	boxToInteger;
Asciz	(I)Ljava/lang/Integer;;
NameAndType	boxToInteger:(I)Ljava/lang/Integer;
Method	scala/runtime/BoxesRunTime.boxToInteger:(I)Ljava/lang/Integer;
Asciz	java/lang/Object;
class	java/lang/Object
Method	java/lang/Object.toString:()Ljava/lang/String;
Method	java/lang/IndexOutOfBoundsException."<init>":(Ljava/lang/String;)V
Asciz	$outer;
Asciz	Lscala/util/parsing/combinator/Parsers;;
NameAndType	$outer:Lscala/util/parsing/combinator/Parsers;
Field	scala/util/parsing/combinator/Parsers$ParseResult.$outer:Lscala/util/parsing/combinator/Parsers;
NameAndType	equals:(Ljava/lang/Object;)Z
Method	java/lang/Object.equals:(Ljava/lang/Object;)Z
Method	scala/util/parsing/combinator/Parsers$NoSuccess."<init>":(Lscala/util/parsing/combinator/Parsers;Ljava/lang/String;Lscala/util/parsing/input/Reader;)V
Asciz	$init$;
Asciz	(Lscala/Product;)V;
NameAndType	$init$:(Lscala/Product;)V
Method	scala/Product$class.$init$:(Lscala/Product;)V
Asciz	(Lscala/util/parsing/combinator/Parsers;Ljava/lang/String;Lscala/util/parsing/input/Reader<Ljava/lang/Object;>;)V;
Asciz	Scala;
Asciz	InnerClasses;
Asciz	scala/util/parsing/combinator/Parsers;
class	scala/util/parsing/combinator/Parsers
Asciz	Success;
Asciz	NoSuccess;
Asciz	ParseResult;
Asciz	scala/ScalaObject;
class	scala/ScalaObject
Asciz	scala/Product;
class	scala/Product
Asciz	java/io/Serializable;
class	java/io/Serializable

{
public scala.collection.Iterator productIterator();
  Signature: ()Lscala/collection/Iterator;
  Code:
   Stack=1, Locals=1, Args_size=1
	aload_0
	invokestatic	Method scala/Product$class.productIterator:(Lscala/Product;)Lscala/collection/Iterator;
	areturn
  Labels:

public scala.collection.Iterator productElements();
  Signature: ()Lscala/collection/Iterator;
  Code:
   Stack=1, Locals=1, Args_size=1
	aload_0
	invokestatic	Method scala/Product$class.productElements:(Lscala/Product;)Lscala/collection/Iterator;
	areturn
  Labels:
  Deprecated: true

public scala.util.parsing.input.Reader copy$default$2();
  Signature: ()Lscala/util/parsing/input/Reader;
  Code:
   Stack=1, Locals=1, Args_size=1
	aload_0
	invokevirtual	Method next:()Lscala/util/parsing/input/Reader;
	areturn
  Labels:

public java.lang.String copy$default$1();
  Signature: ()Ljava/lang/String;
  Code:
   Stack=1, Locals=1, Args_size=1
	aload_0
	invokevirtual	Method msg:()Ljava/lang/String;
	areturn
  Labels:

public java.lang.String msg();
  Signature: ()Ljava/lang/String;
  Code:
   Stack=1, Locals=1, Args_size=1
	aload_0
	invokespecial	Method scala/util/parsing/combinator/Parsers$NoSuccess.msg:()Ljava/lang/String;
	areturn
  Labels:

public scala.util.parsing.input.Reader next();
  Signature: ()Lscala/util/parsing/input/Reader;
  Code:
   Stack=1, Locals=1, Args_size=1
	aload_0
	invokespecial	Method scala/util/parsing/combinator/Parsers$NoSuccess.next:()Lscala/util/parsing/input/Reader;
	areturn
  Labels:
  Signature: length = 0x2
   00 20 

public java.lang.String toString();
  Signature: ()Ljava/lang/String;
  Code:
   Stack=2, Locals=1, Args_size=1
	new	class scala/collection/mutable/StringBuilder
	dup
	invokespecial	Method scala/collection/mutable/StringBuilder."<init>":()V
	ldc	String [
	invokevirtual	Method scala/collection/mutable/StringBuilder.append:(Ljava/lang/Object;)Lscala/collection/mutable/StringBuilder;
	aload_0
	invokevirtual	Method next:()Lscala/util/parsing/input/Reader;
	invokevirtual	Method scala/util/parsing/input/Reader.pos:()Lscala/util/parsing/input/Position;
	invokevirtual	Method scala/collection/mutable/StringBuilder.append:(Ljava/lang/Object;)Lscala/collection/mutable/StringBuilder;
	ldc	String ] failure: 
	invokevirtual	Method scala/collection/mutable/StringBuilder.append:(Ljava/lang/Object;)Lscala/collection/mutable/StringBuilder;
	aload_0
	invokevirtual	Method msg:()Ljava/lang/String;
	invokevirtual	Method scala/collection/mutable/StringBuilder.append:(Ljava/lang/Object;)Lscala/collection/mutable/StringBuilder;
	ldc	String \n\n
	invokevirtual	Method scala/collection/mutable/StringBuilder.append:(Ljava/lang/Object;)Lscala/collection/mutable/StringBuilder;
	aload_0
	invokevirtual	Method next:()Lscala/util/parsing/input/Reader;
	invokevirtual	Method scala/util/parsing/input/Reader.pos:()Lscala/util/parsing/input/Position;
	invokeinterface	InterfaceMethod scala/util/parsing/input/Position.longString:()Ljava/lang/String;
	invokevirtual	Method scala/collection/mutable/StringBuilder.append:(Ljava/lang/Object;)Lscala/collection/mutable/StringBuilder;
	invokevirtual	Method scala/collection/mutable/StringBuilder.toString:()Ljava/lang/String;
	areturn
  Labels:

public scala.util.parsing.combinator.Parsers$ParseResult append(scala.Function0);
  Signature: (Lscala/Function0;)Lscala/util/parsing/combinator/Parsers$ParseResult;
  Code:
   Stack=3, Locals=3, Args_size=2
	aload_1
	invokeinterface	InterfaceMethod scala/Function0.apply:()Ljava/lang/Object;
	checkcast	class scala/util/parsing/combinator/Parsers$ParseResult
	astore_2
	aload_2
	instanceof	class scala/util/parsing/combinator/Parsers$Success
	ifeq	l1 // aload_2
	aload_2
	goto	l2 // areturn
l1	aload_2
	instanceof	class scala/util/parsing/combinator/Parsers$NoSuccess
	ifeq	l3 // new
	aload_2
	invokevirtual	Method scala/util/parsing/combinator/Parsers$ParseResult.next:()Lscala/util/parsing/input/Reader;
	invokevirtual	Method scala/util/parsing/input/Reader.pos:()Lscala/util/parsing/input/Position;
	aload_0
	invokevirtual	Method next:()Lscala/util/parsing/input/Reader;
	invokevirtual	Method scala/util/parsing/input/Reader.pos:()Lscala/util/parsing/input/Position;
	invokeinterface	InterfaceMethod scala/util/parsing/input/Position.$less:(Lscala/util/parsing/input/Position;)Z
	ifeq	l4 // aload_2
	aload_0
	goto	l2 // areturn
l4	aload_2
l2	areturn
l3	new	class scala/MatchError
	dup
	aload_2
	invokevirtual	Method scala/util/parsing/combinator/Parsers$ParseResult.toString:()Ljava/lang/String;
	invokespecial	Method scala/MatchError."<init>":(Ljava/lang/String;)V
	athrow
  Labels:
   	l1 = 21 // aload_2
   	l4 = 54 // aload_2
   	l2 = 55 // areturn
   	l3 = 56 // new
  LocalVariableTable: 
   Start  Length  Slot  Name   Signature
   0      68      0    this       Lscala/util/parsing/combinator/Parsers$Failure;
   0      68      1    a       Lscala/Function0;
   10      58      2    alt       Lscala/util/parsing/combinator/Parsers$ParseResult;

  Signature: length = 0x2
   00 5D 

public scala.util.parsing.combinator.Parsers$Failure copy(java.lang.String, scala.util.parsing.input.Reader);
  Signature: (Ljava/lang/String;Lscala/util/parsing/input/Reader;)Lscala/util/parsing/combinator/Parsers$Failure;
  Code:
   Stack=5, Locals=3, Args_size=3
	new	class scala/util/parsing/combinator/Parsers$Failure
	dup
	aload_0
	invokevirtual	Method scala$util$parsing$combinator$Parsers$Failure$$$outer:()Lscala/util/parsing/combinator/Parsers;
	aload_1
	aload_2
	invokespecial	Method "<init>":(Lscala/util/parsing/combinator/Parsers;Ljava/lang/String;Lscala/util/parsing/input/Reader;)V
	areturn
  Labels:
  LocalVariableTable: 
   Start  Length  Slot  Name   Signature
   0      14      0    this       Lscala/util/parsing/combinator/Parsers$Failure;
   0      14      1    msg       Ljava/lang/String;
   0      14      2    next       Lscala/util/parsing/input/Reader;


public int hashCode();
  Signature: ()I
  Code:
   Stack=2, Locals=1, Args_size=1
	getstatic	Field scala/runtime/ScalaRunTime$.MODULE$:Lscala/runtime/ScalaRunTime$;
	aload_0
	invokevirtual	Method scala/runtime/ScalaRunTime$._hashCode:(Lscala/Product;)I
	ireturn
  Labels:

public boolean equals(java.lang.Object);
  Signature: (Ljava/lang/Object;)Z
  Code:
   Stack=3, Locals=5, Args_size=2
	aload_0
	aload_1
	if_acmpeq	l1 // iconst_1
	aload_1
	instanceof	class scala/util/parsing/combinator/Parsers$Failure
	ifeq	l2 // iconst_0
	aload_1
	checkcast	class scala/util/parsing/combinator/Parsers$Failure
	invokevirtual	Method scala$util$parsing$combinator$Parsers$Failure$$$outer:()Lscala/util/parsing/combinator/Parsers;
	aload_0
	invokevirtual	Method scala$util$parsing$combinator$Parsers$Failure$$$outer:()Lscala/util/parsing/combinator/Parsers;
	if_acmpne	l2 // iconst_0
	aload_1
	checkcast	class scala/util/parsing/combinator/Parsers$Failure
	astore_2
	aload_2
	invokevirtual	Method msg:()Ljava/lang/String;
	astore_3
	aload_2
	invokevirtual	Method next:()Lscala/util/parsing/input/Reader;
	astore	4
	aload_0
	aload_3
	aload	4
	invokespecial	Method gd2$1:(Ljava/lang/String;Lscala/util/parsing/input/Reader;)Z
	ifeq	l3 // iconst_0
	aload_1
	checkcast	class scala/util/parsing/combinator/Parsers$Failure
	aload_0
	invokeinterface	InterfaceMethod scala/Equals.canEqual:(Ljava/lang/Object;)Z
	goto	l4 // ifeq
l3	iconst_0
	goto	l4 // ifeq
l2	iconst_0
l4	ifeq	l5 // iconst_0
l1	iconst_1
	goto	l6 // ireturn
l5	iconst_0
l6	ireturn
  Labels:
   	l3 = 65 // iconst_0
   	l2 = 69 // iconst_0
   	l4 = 70 // ifeq
   	l1 = 73 // iconst_1
   	l5 = 77 // iconst_0
   	l6 = 78 // ireturn
  LocalVariableTable: 
   Start  Length  Slot  Name   Signature
   0      79      0    this       Lscala/util/parsing/combinator/Parsers$Failure;
   31      38      2    temp19       Lscala/util/parsing/combinator/Parsers$Failure;
   36      33      3    temp20       Ljava/lang/String;
   42      27      4    temp21       Lscala/util/parsing/input/Reader;


public java.lang.String productPrefix();
  Signature: ()Ljava/lang/String;
  Code:
   Stack=1, Locals=1, Args_size=1
	ldc	String Failure
	areturn
  Labels:

public int productArity();
  Signature: ()I
  Code:
   Stack=1, Locals=1, Args_size=1
	iconst_2
	ireturn
  Labels:

public java.lang.Object productElement(int);
  Signature: (I)Ljava/lang/Object;
  Code:
   Stack=3, Locals=2, Args_size=2
	iload_1
	tableswitch{ //0 to 1
		0: 46;
		1: 39;
		default: 24 }
	new	class java/lang/IndexOutOfBoundsException
	dup
	iload_1
	invokestatic	Method scala/runtime/BoxesRunTime.boxToInteger:(I)Ljava/lang/Integer;
	invokevirtual	Method java/lang/Object.toString:()Ljava/lang/String;
	invokespecial	Method java/lang/IndexOutOfBoundsException."<init>":(Ljava/lang/String;)V
	athrow
	aload_0
	invokevirtual	Method next:()Lscala/util/parsing/input/Reader;
	goto	l1 // areturn
	aload_0
	invokevirtual	Method msg:()Ljava/lang/String;
l1	areturn
  Labels:
   	l1 = 50 // areturn

public boolean canEqual(java.lang.Object);
  Signature: (Ljava/lang/Object;)Z
  Code:
   Stack=1, Locals=2, Args_size=2
	aload_1
	instanceof	class scala/util/parsing/combinator/Parsers$Failure
	ireturn
  Labels:

public scala.util.parsing.combinator.Parsers scala$util$parsing$combinator$Parsers$Failure$$$outer();
  Signature: ()Lscala/util/parsing/combinator/Parsers;
  Code:
   Stack=1, Locals=1, Args_size=1
	aload_0
	getfield	Field scala/util/parsing/combinator/Parsers$ParseResult.$outer:Lscala/util/parsing/combinator/Parsers;
	areturn
  Labels:

private final boolean gd2$1(java.lang.String, scala.util.parsing.input.Reader);
  Signature: (Ljava/lang/String;Lscala/util/parsing/input/Reader;)Z
  Code:
   Stack=2, Locals=5, Args_size=3
	aload_1
	aload_0
	invokevirtual	Method msg:()Ljava/lang/String;
	astore_3
	dup
	ifnonnull	l1 // aload_3
	pop
	aload_3
	ifnull	l2 // aload_2
	goto	l3 // iconst_0
l1	aload_3
	invokevirtual	Method java/lang/Object.equals:(Ljava/lang/Object;)Z
	ifeq	l3 // iconst_0
l2	aload_2
	aload_0
	invokevirtual	Method next:()Lscala/util/parsing/input/Reader;
	astore	4
	dup
	ifnonnull	l4 // aload
	pop
	aload	4
	ifnull	l5 // iconst_1
	goto	l3 // iconst_0
l4	aload	4
	invokevirtual	Method java/lang/Object.equals:(Ljava/lang/Object;)Z
	ifeq	l3 // iconst_0
l5	iconst_1
	goto	l6 // ireturn
l3	iconst_0
l6	ireturn
  Labels:
   	l1 = 18 // aload_3
   	l2 = 25 // aload_2
   	l4 = 45 // aload
   	l5 = 53 // iconst_1
   	l3 = 57 // iconst_0
   	l6 = 58 // ireturn

public scala.util.parsing.combinator.Parsers$Failure(scala.util.parsing.combinator.Parsers, java.lang.String, scala.util.parsing.input.Reader);
  Signature: (Lscala/util/parsing/combinator/Parsers;Ljava/lang/String;Lscala/util/parsing/input/Reader;)V
  Code:
   Stack=4, Locals=4, Args_size=4
	aload_0
	aload_1
	aload_2
	aload_3
	invokespecial	Method scala/util/parsing/combinator/Parsers$NoSuccess."<init>":(Lscala/util/parsing/combinator/Parsers;Ljava/lang/String;Lscala/util/parsing/input/Reader;)V
	aload_0
	invokestatic	Method scala/Product$class.$init$:(Lscala/Product;)V
	return
  Labels:
  LocalVariableTable: 
   Start  Length  Slot  Name   Signature
   0      12      0    this       Lscala/util/parsing/combinator/Parsers$Failure;
   0      12      1    $outer       Lscala/util/parsing/combinator/Parsers;
   0      12      2    msg       Ljava/lang/String;
   0      12      3    next       Lscala/util/parsing/input/Reader;

  Signature: length = 0x2
   00 FFFFFFA0 

}

