Compiled from "Parsers.scala"
public final class scala.util.parsing.combinator.Parsers$OnceParser$$anonfun$$tilde$2$$anonfun$apply$12 extends java.lang.Object implements scala.Function1,scala.ScalaObject,java.io.Serializable
  SourceFile: "Parsers.scala"
  Scala: length = 0x
   
  InnerClass: 
   public $tilde=class scala/util/parsing/combinator/Parsers$$tilde of class scala/util/parsing/combinator/Parsers
   public abstract OnceParser=class scala/util/parsing/combinator/Parsers$OnceParser of class scala/util/parsing/combinator/Parsers
   public final $anonfun$$tilde$2=class scala/util/parsing/combinator/Parsers$OnceParser$$anonfun$$tilde$2 of class scala/util/parsing/combinator/Parsers$OnceParser
   public final $anonfun$apply$12=class scala/util/parsing/combinator/Parsers$OnceParser$$anonfun$$tilde$2$$anonfun$apply$12 of class scala/util/parsing/combinator/Parsers$OnceParser$$anonfun$$tilde$2
  minor version: 0
  major version: 49
  Constant pool:
Asciz	SourceFile;
Asciz	Parsers.scala;
Asciz	<clinit>;
Asciz	()V;
Asciz	Code;
Asciz	serialVersionUID;
Asciz	J;
Asciz	scala/util/parsing/combinator/Parsers$OnceParser$$anonfun$$tilde$2$$anonfun$apply$12;
class	scala/util/parsing/combinator/Parsers$OnceParser$$anonfun$$tilde$2$$anonfun$apply$12
NameAndType	serialVersionUID:J
Field	scala/util/parsing/combinator/Parsers$OnceParser$$anonfun$$tilde$2$$anonfun$apply$12.serialVersionUID:J
Asciz	a$4;
Asciz	Ljava/lang/Object;;
Asciz	$outer;
Asciz	Lscala/util/parsing/combinator/Parsers$OnceParser$$anonfun$$tilde$2;;
Asciz	<init>;
Asciz	(Lscala/util/parsing/combinator/Parsers$OnceParser$$anonfun$$tilde$2;Ljava/lang/Object;)V;
Asciz	LineNumberTable;
Asciz	java/lang/NullPointerException;
class	java/lang/NullPointerException
NameAndType	"<init>":()V
Method	java/lang/NullPointerException."<init>":()V
NameAndType	$outer:Lscala/util/parsing/combinator/Parsers$OnceParser$$anonfun$$tilde$2;
Field	scala/util/parsing/combinator/Parsers$OnceParser$$anonfun$$tilde$2$$anonfun$apply$12.$outer:Lscala/util/parsing/combinator/Parsers$OnceParser$$anonfun$$tilde$2;
NameAndType	a$4:Ljava/lang/Object;
Field	scala/util/parsing/combinator/Parsers$OnceParser$$anonfun$$tilde$2$$anonfun$apply$12.a$4:Ljava/lang/Object;
Asciz	java/lang/Object;
class	java/lang/Object
Method	java/lang/Object."<init>":()V
Asciz	scala/Function1$class;
class	scala/Function1$class
Asciz	$init$;
Asciz	(Lscala/Function1;)V;
NameAndType	$init$:(Lscala/Function1;)V
Method	scala/Function1$class.$init$:(Lscala/Function1;)V
Asciz	this;
Asciz	Lscala/util/parsing/combinator/Parsers$OnceParser$$anonfun$$tilde$2$$anonfun$apply$12;;
Asciz	LocalVariableTable;
Asciz	(Lscala/util/parsing/combinator/Parsers$OnceParser<TT;>.$anonfun$$tilde$2;)V;
Asciz	Signature;
Asciz	apply;
Asciz	(Ljava/lang/Object;)Ljava/lang/Object;;
Asciz	(Ljava/lang/Object;)Lscala/util/parsing/combinator/Parsers$$tilde;;
NameAndType	apply:(Ljava/lang/Object;)Lscala/util/parsing/combinator/Parsers$$tilde;
Method	scala/util/parsing/combinator/Parsers$OnceParser$$anonfun$$tilde$2$$anonfun$apply$12.apply:(Ljava/lang/Object;)Lscala/util/parsing/combinator/Parsers$$tilde;
Asciz	v1;
Asciz	scala/util/parsing/combinator/Parsers$$tilde;
class	scala/util/parsing/combinator/Parsers$$tilde
Asciz	scala/util/parsing/combinator/Parsers$OnceParser$$anonfun$$tilde$2;
class	scala/util/parsing/combinator/Parsers$OnceParser$$anonfun$$tilde$2
Asciz	Lscala/util/parsing/combinator/Parsers$OnceParser;;
NameAndType	$outer:Lscala/util/parsing/combinator/Parsers$OnceParser;
Field	scala/util/parsing/combinator/Parsers$OnceParser$$anonfun$$tilde$2.$outer:Lscala/util/parsing/combinator/Parsers$OnceParser;
Asciz	scala/util/parsing/combinator/Parsers$OnceParser;
class	scala/util/parsing/combinator/Parsers$OnceParser
Asciz	scala$util$parsing$combinator$Parsers$OnceParser$$$outer;
Asciz	()Lscala/util/parsing/combinator/Parsers;;
NameAndType	scala$util$parsing$combinator$Parsers$OnceParser$$$outer:()Lscala/util/parsing/combinator/Parsers;
InterfaceMethod	scala/util/parsing/combinator/Parsers$OnceParser.scala$util$parsing$combinator$Parsers$OnceParser$$$outer:()Lscala/util/parsing/combinator/Parsers;
Asciz	(Lscala/util/parsing/combinator/Parsers;Ljava/lang/Object;Ljava/lang/Object;)V;
NameAndType	"<init>":(Lscala/util/parsing/combinator/Parsers;Ljava/lang/Object;Ljava/lang/Object;)V
Method	scala/util/parsing/combinator/Parsers$$tilde."<init>":(Lscala/util/parsing/combinator/Parsers;Ljava/lang/Object;Ljava/lang/Object;)V
Asciz	b;
Asciz	(TU;)Lscala/util/parsing/combinator/Parsers$$tilde<TT;TU;>;;
Asciz	andThen;
Asciz	(Lscala/Function1;)Lscala/Function1;;
Asciz	(Lscala/Function1;Lscala/Function1;)Lscala/Function1;;
NameAndType	andThen:(Lscala/Function1;Lscala/Function1;)Lscala/Function1;
Method	scala/Function1$class.andThen:(Lscala/Function1;Lscala/Function1;)Lscala/Function1;
Asciz	g;
Asciz	Lscala/Function1;;
Asciz	compose;
NameAndType	compose:(Lscala/Function1;Lscala/Function1;)Lscala/Function1;
Method	scala/Function1$class.compose:(Lscala/Function1;Lscala/Function1;)Lscala/Function1;
Asciz	toString;
Asciz	()Ljava/lang/String;;
Asciz	(Lscala/Function1;)Ljava/lang/String;;
NameAndType	toString:(Lscala/Function1;)Ljava/lang/String;
Method	scala/Function1$class.toString:(Lscala/Function1;)Ljava/lang/String;
Asciz	Scala;
Asciz	InnerClasses;
Asciz	scala/util/parsing/combinator/Parsers;
class	scala/util/parsing/combinator/Parsers
Asciz	$tilde;
Asciz	OnceParser;
Asciz	$anonfun$$tilde$2;
Asciz	$anonfun$apply$12;
Asciz	scala/Function1;
class	scala/Function1
Asciz	scala/ScalaObject;
class	scala/ScalaObject
Asciz	java/io/Serializable;
class	java/io/Serializable

{
public static final long serialVersionUID;
  Signature: J

private final java.lang.Object a$4;
  Signature: Ljava/lang/Object;

private final scala.util.parsing.combinator.Parsers$OnceParser$$anonfun$$tilde$2 $outer;
  Signature: Lscala/util/parsing/combinator/Parsers$OnceParser$$anonfun$$tilde$2;

public static {};
  Signature: ()V
  Code:
   Stack=2, Locals=0, Args_size=0
	lconst_0
	putstatic	Field serialVersionUID:J
	return
  Labels:

public scala.util.parsing.combinator.Parsers$OnceParser$$anonfun$$tilde$2$$anonfun$apply$12(scala.util.parsing.combinator.Parsers$OnceParser$$anonfun$$tilde$2, java.lang.Object);
  Signature: (Lscala/util/parsing/combinator/Parsers$OnceParser$$anonfun$$tilde$2;Ljava/lang/Object;)V
  Code:
   Stack=2, Locals=3, Args_size=3
	aload_1
	ifnonnull	l1 // aload_0
	new	class java/lang/NullPointerException
	dup
	invokespecial	Method java/lang/NullPointerException."<init>":()V
	athrow
l1	aload_0
	aload_1
	putfield	Field $outer:Lscala/util/parsing/combinator/Parsers$OnceParser$$anonfun$$tilde$2;
	aload_0
	aload_2
	putfield	Field a$4:Ljava/lang/Object;
	aload_0
	invokespecial	Method java/lang/Object."<init>":()V
	aload_0
	invokestatic	Method scala/Function1$class.$init$:(Lscala/Function1;)V
	return
  Labels:
   	l1 = 12 // aload_0
  LocalVariableTable: 
   Start  Length  Slot  Name   Signature
   0      31      0    this       Lscala/util/parsing/combinator/Parsers$OnceParser$$anonfun$$tilde$2$$anonfun$apply$12;
   0      31      1    $outer       Lscala/util/parsing/combinator/Parsers$OnceParser$$anonfun$$tilde$2;

  Signature: length = 0x2
   00 27 

public final java.lang.Object apply(java.lang.Object);
  Signature: (Ljava/lang/Object;)Ljava/lang/Object;
  Code:
   Stack=2, Locals=3, Args_size=2
	aload_0
	getfield	Field $outer:Lscala/util/parsing/combinator/Parsers$OnceParser$$anonfun$$tilde$2;
	astore_2
	aload_0
	aload_1
	invokevirtual	Method apply:(Ljava/lang/Object;)Lscala/util/parsing/combinator/Parsers$$tilde;
	areturn
  Labels:
  LocalVariableTable: 
   Start  Length  Slot  Name   Signature
   0      11      0    this       Lscala/util/parsing/combinator/Parsers$OnceParser$$anonfun$$tilde$2$$anonfun$apply$12;
   5      6      1    v1       Ljava/lang/Object;


public final scala.util.parsing.combinator.Parsers$$tilde apply(java.lang.Object);
  Signature: (Ljava/lang/Object;)Lscala/util/parsing/combinator/Parsers$$tilde;
  Code:
   Stack=5, Locals=4, Args_size=2
	aload_0
	getfield	Field $outer:Lscala/util/parsing/combinator/Parsers$OnceParser$$anonfun$$tilde$2;
	astore_3
	new	class scala/util/parsing/combinator/Parsers$$tilde
	dup
	aload_0
	getfield	Field $outer:Lscala/util/parsing/combinator/Parsers$OnceParser$$anonfun$$tilde$2;
	astore_2
	aload_2
	getfield	Field scala/util/parsing/combinator/Parsers$OnceParser$$anonfun$$tilde$2.$outer:Lscala/util/parsing/combinator/Parsers$OnceParser;
	invokeinterface	InterfaceMethod scala/util/parsing/combinator/Parsers$OnceParser.scala$util$parsing$combinator$Parsers$OnceParser$$$outer:()Lscala/util/parsing/combinator/Parsers;
	aload_0
	getfield	Field a$4:Ljava/lang/Object;
	aload_1
	invokespecial	Method scala/util/parsing/combinator/Parsers$$tilde."<init>":(Lscala/util/parsing/combinator/Parsers;Ljava/lang/Object;Ljava/lang/Object;)V
	areturn
  Labels:
  LocalVariableTable: 
   Start  Length  Slot  Name   Signature
   0      32      0    this       Lscala/util/parsing/combinator/Parsers$OnceParser$$anonfun$$tilde$2$$anonfun$apply$12;
   5      27      1    b       Ljava/lang/Object;

  Signature: length = 0x2
   00 40 

public scala.Function1 andThen(scala.Function1);
  Signature: (Lscala/Function1;)Lscala/Function1;
  Code:
   Stack=2, Locals=2, Args_size=2
	aload_0
	aload_1
	invokestatic	Method scala/Function1$class.andThen:(Lscala/Function1;Lscala/Function1;)Lscala/Function1;
	areturn
  Labels:
  LocalVariableTable: 
   Start  Length  Slot  Name   Signature
   0      6      0    this       Lscala/util/parsing/combinator/Parsers$OnceParser$$anonfun$$tilde$2$$anonfun$apply$12;
   0      6      1    g       Lscala/Function1;


public scala.Function1 compose(scala.Function1);
  Signature: (Lscala/Function1;)Lscala/Function1;
  Code:
   Stack=2, Locals=2, Args_size=2
	aload_0
	aload_1
	invokestatic	Method scala/Function1$class.compose:(Lscala/Function1;Lscala/Function1;)Lscala/Function1;
	areturn
  Labels:
  LocalVariableTable: 
   Start  Length  Slot  Name   Signature
   0      6      0    this       Lscala/util/parsing/combinator/Parsers$OnceParser$$anonfun$$tilde$2$$anonfun$apply$12;
   0      6      1    g       Lscala/Function1;


public java.lang.String toString();
  Signature: ()Ljava/lang/String;
  Code:
   Stack=1, Locals=1, Args_size=1
	aload_0
	invokestatic	Method scala/Function1$class.toString:(Lscala/Function1;)Ljava/lang/String;
	areturn
  Labels:

}

