Compiled from "Parsers.scala"
public class scala.util.parsing.combinator.Parsers$Success extends scala.util.parsing.combinator.Parsers$ParseResult implements scala.ScalaObject,scala.Product,java.io.Serializable
  SourceFile: "Parsers.scala"
  Signature: length = 0x2
   00 FFFFFFC0 
  Scala: length = 0x
   
  InnerClass: 
   public #197= #170 of #196; //Failure=class scala/util/parsing/combinator/Parsers$Failure of class scala/util/parsing/combinator/Parsers
   public #99= #17 of #196; //Success=class scala/util/parsing/combinator/Parsers$Success of class scala/util/parsing/combinator/Parsers
   public abstract #198= #23 of #196; //ParseResult=class scala/util/parsing/combinator/Parsers$ParseResult of class scala/util/parsing/combinator/Parsers
  minor version: 0
  major version: 49
  Constant pool:
const #1 = Asciz	SourceFile;
const #2 = Asciz	Parsers.scala;
const #3 = Asciz	successful;
const #4 = Asciz	Z;
const #5 = Asciz	next;
const #6 = Asciz	Lscala/util/parsing/input/Reader;;
const #7 = Asciz	Lscala/util/parsing/input/Reader<Ljava/lang/Object;>;;
const #8 = Asciz	Signature;
const #9 = Asciz	result;
const #10 = Asciz	Ljava/lang/Object;;
const #11 = Asciz	TT;;
const #12 = Asciz	<init>;
const #13 = Asciz	(Lscala/util/parsing/combinator/Parsers;Ljava/lang/Object;Lscala/util/parsing/input/Reader;)V;
const #14 = Asciz	Code;
const #15 = Asciz	LineNumberTable;
const #16 = Asciz	scala/util/parsing/combinator/Parsers$Success;
const #17 = class	#16;	//  scala/util/parsing/combinator/Parsers$Success
const #18 = NameAndType	#9:#10;//  result:Ljava/lang/Object;
const #19 = Field	#17.#18;	//  scala/util/parsing/combinator/Parsers$Success.result:Ljava/lang/Object;
const #20 = NameAndType	#5:#6;//  next:Lscala/util/parsing/input/Reader;
const #21 = Field	#17.#20;	//  scala/util/parsing/combinator/Parsers$Success.next:Lscala/util/parsing/input/Reader;
const #22 = Asciz	scala/util/parsing/combinator/Parsers$ParseResult;
const #23 = class	#22;	//  scala/util/parsing/combinator/Parsers$ParseResult
const #24 = Asciz	(Lscala/util/parsing/combinator/Parsers;)V;
const #25 = NameAndType	#12:#24;//  "<init>":(Lscala/util/parsing/combinator/Parsers;)V
const #26 = Method	#23.#25;	//  scala/util/parsing/combinator/Parsers$ParseResult."<init>":(Lscala/util/parsing/combinator/Parsers;)V
const #27 = Asciz	scala/Product$class;
const #28 = class	#27;	//  scala/Product$class
const #29 = Asciz	$init$;
const #30 = Asciz	(Lscala/Product;)V;
const #31 = NameAndType	#29:#30;//  $init$:(Lscala/Product;)V
const #32 = Method	#28.#31;	//  scala/Product$class.$init$:(Lscala/Product;)V
const #33 = NameAndType	#3:#4;//  successful:Z
const #34 = Field	#17.#33;	//  scala/util/parsing/combinator/Parsers$Success.successful:Z
const #35 = Asciz	this;
const #36 = Asciz	Lscala/util/parsing/combinator/Parsers$Success;;
const #37 = Asciz	$outer;
const #38 = Asciz	Lscala/util/parsing/combinator/Parsers;;
const #39 = Asciz	LocalVariableTable;
const #40 = Asciz	(Lscala/util/parsing/combinator/Parsers;TT;Lscala/util/parsing/input/Reader<Ljava/lang/Object;>;)V;
const #41 = Asciz	gd1$1;
const #42 = Asciz	(Ljava/lang/Object;Lscala/util/parsing/input/Reader;)Z;
const #43 = Asciz	()Ljava/lang/Object;;
const #44 = NameAndType	#9:#43;//  result:()Ljava/lang/Object;
const #45 = Method	#17.#44;	//  scala/util/parsing/combinator/Parsers$Success.result:()Ljava/lang/Object;
const #46 = Asciz	java/lang/Number;
const #47 = class	#46;	//  java/lang/Number
const #48 = Asciz	java/lang/Character;
const #49 = class	#48;	//  java/lang/Character
const #50 = Asciz	scala/runtime/BoxesRunTime;
const #51 = class	#50;	//  scala/runtime/BoxesRunTime
const #52 = Asciz	equals2;
const #53 = Asciz	(Ljava/lang/Object;Ljava/lang/Object;)Z;
const #54 = NameAndType	#52:#53;//  equals2:(Ljava/lang/Object;Ljava/lang/Object;)Z
const #55 = Method	#51.#54;	//  scala/runtime/BoxesRunTime.equals2:(Ljava/lang/Object;Ljava/lang/Object;)Z
const #56 = Asciz	java/lang/Object;
const #57 = class	#56;	//  java/lang/Object
const #58 = Asciz	equals;
const #59 = Asciz	(Ljava/lang/Object;)Z;
const #60 = NameAndType	#58:#59;//  equals:(Ljava/lang/Object;)Z
const #61 = Method	#57.#60;	//  java/lang/Object.equals:(Ljava/lang/Object;)Z
const #62 = Asciz	()Lscala/util/parsing/input/Reader;;
const #63 = NameAndType	#5:#62;//  next:()Lscala/util/parsing/input/Reader;
const #64 = Method	#17.#63;	//  scala/util/parsing/combinator/Parsers$Success.next:()Lscala/util/parsing/input/Reader;
const #65 = Asciz	y0;
const #66 = Asciz	map;
const #67 = Asciz	(Lscala/Function1;)Lscala/util/parsing/combinator/Parsers$ParseResult;;
const #68 = Asciz	(Lscala/Function1;)Lscala/util/parsing/combinator/Parsers$Success;;
const #69 = NameAndType	#66:#68;//  map:(Lscala/Function1;)Lscala/util/parsing/combinator/Parsers$Success;
const #70 = Method	#17.#69;	//  scala/util/parsing/combinator/Parsers$Success.map:(Lscala/Function1;)Lscala/util/parsing/combinator/Parsers$Success;
const #71 = Asciz	f;
const #72 = Asciz	Lscala/Function1;;
const #73 = Asciz	scala$util$parsing$combinator$Parsers$Success$$$outer;
const #74 = Asciz	()Lscala/util/parsing/combinator/Parsers;;
const #75 = NameAndType	#37:#38;//  $outer:Lscala/util/parsing/combinator/Parsers;
const #76 = Field	#23.#75;	//  scala/util/parsing/combinator/Parsers$ParseResult.$outer:Lscala/util/parsing/combinator/Parsers;
const #77 = Asciz	canEqual;
const #78 = Asciz	productElement;
const #79 = Asciz	(I)Ljava/lang/Object;;
const #80 = Asciz	java/lang/IndexOutOfBoundsException;
const #81 = class	#80;	//  java/lang/IndexOutOfBoundsException
const #82 = Asciz	boxToInteger;
const #83 = Asciz	(I)Ljava/lang/Integer;;
const #84 = NameAndType	#82:#83;//  boxToInteger:(I)Ljava/lang/Integer;
const #85 = Method	#51.#84;	//  scala/runtime/BoxesRunTime.boxToInteger:(I)Ljava/lang/Integer;
const #86 = Asciz	toString;
const #87 = Asciz	()Ljava/lang/String;;
const #88 = NameAndType	#86:#87;//  toString:()Ljava/lang/String;
const #89 = Method	#57.#88;	//  java/lang/Object.toString:()Ljava/lang/String;
const #90 = Asciz	(Ljava/lang/String;)V;
const #91 = NameAndType	#12:#90;//  "<init>":(Ljava/lang/String;)V
const #92 = Method	#81.#91;	//  java/lang/IndexOutOfBoundsException."<init>":(Ljava/lang/String;)V
const #93 = Asciz	scala/MatchError;
const #94 = class	#93;	//  scala/MatchError
const #95 = Method	#94.#91;	//  scala/MatchError."<init>":(Ljava/lang/String;)V
const #96 = Asciz	productArity;
const #97 = Asciz	()I;
const #98 = Asciz	productPrefix;
const #99 = Asciz	Success;
const #100 = String	#99;	//  Success
const #101 = NameAndType	#73:#74;//  scala$util$parsing$combinator$Parsers$Success$$$outer:()Lscala/util/parsing/combinator/Parsers;
const #102 = Method	#17.#101;	//  scala/util/parsing/combinator/Parsers$Success.scala$util$parsing$combinator$Parsers$Success$$$outer:()Lscala/util/parsing/combinator/Parsers;
const #103 = NameAndType	#41:#42;//  gd1$1:(Ljava/lang/Object;Lscala/util/parsing/input/Reader;)Z
const #104 = Method	#17.#103;	//  scala/util/parsing/combinator/Parsers$Success.gd1$1:(Ljava/lang/Object;Lscala/util/parsing/input/Reader;)Z
const #105 = Asciz	scala/Equals;
const #106 = class	#105;	//  scala/Equals
const #107 = NameAndType	#77:#59;//  canEqual:(Ljava/lang/Object;)Z
const #108 = InterfaceMethod	#106.#107;	//  scala/Equals.canEqual:(Ljava/lang/Object;)Z
const #109 = Asciz	temp2;
const #110 = Asciz	temp3;
const #111 = Asciz	temp4;
const #112 = Asciz	hashCode;
const #113 = Asciz	scala/runtime/ScalaRunTime$;
const #114 = class	#113;	//  scala/runtime/ScalaRunTime$
const #115 = Asciz	MODULE$;
const #116 = Asciz	Lscala/runtime/ScalaRunTime$;;
const #117 = NameAndType	#115:#116;//  MODULE$:Lscala/runtime/ScalaRunTime$;
const #118 = Field	#114.#117;	//  scala/runtime/ScalaRunTime$.MODULE$:Lscala/runtime/ScalaRunTime$;
const #119 = Asciz	_hashCode;
const #120 = Asciz	(Lscala/Product;)I;
const #121 = NameAndType	#119:#120;//  _hashCode:(Lscala/Product;)I
const #122 = Method	#114.#121;	//  scala/runtime/ScalaRunTime$._hashCode:(Lscala/Product;)I
const #123 = Asciz	copy;
const #124 = Asciz	(Ljava/lang/Object;Lscala/util/parsing/input/Reader;)Lscala/util/parsing/combinator/Parsers$Success;;
const #125 = NameAndType	#12:#13;//  "<init>":(Lscala/util/parsing/combinator/Parsers;Ljava/lang/Object;Lscala/util/parsing/input/Reader;)V
const #126 = Method	#17.#125;	//  scala/util/parsing/combinator/Parsers$Success."<init>":(Lscala/util/parsing/combinator/Parsers;Ljava/lang/Object;Lscala/util/parsing/input/Reader;)V
const #127 = Asciz	()Z;
const #128 = Asciz	scala/collection/mutable/StringBuilder;
const #129 = class	#128;	//  scala/collection/mutable/StringBuilder
const #130 = Asciz	()V;
const #131 = NameAndType	#12:#130;//  "<init>":()V
const #132 = Method	#129.#131;	//  scala/collection/mutable/StringBuilder."<init>":()V
const #133 = Asciz	[;
const #134 = String	#133;	//  [
const #135 = Asciz	append;
const #136 = Asciz	(Ljava/lang/Object;)Lscala/collection/mutable/StringBuilder;;
const #137 = NameAndType	#135:#136;//  append:(Ljava/lang/Object;)Lscala/collection/mutable/StringBuilder;
const #138 = Method	#129.#137;	//  scala/collection/mutable/StringBuilder.append:(Ljava/lang/Object;)Lscala/collection/mutable/StringBuilder;
const #139 = Asciz	scala/util/parsing/input/Reader;
const #140 = class	#139;	//  scala/util/parsing/input/Reader
const #141 = Asciz	pos;
const #142 = Asciz	()Lscala/util/parsing/input/Position;;
const #143 = NameAndType	#141:#142;//  pos:()Lscala/util/parsing/input/Position;
const #144 = Method	#140.#143;	//  scala/util/parsing/input/Reader.pos:()Lscala/util/parsing/input/Position;
const #145 = Asciz	] parsed: ;
const #146 = String	#145;	//  ] parsed: 
const #147 = Method	#129.#88;	//  scala/collection/mutable/StringBuilder.toString:()Ljava/lang/String;
const #148 = Asciz	get;
const #149 = Asciz	()TT;;
const #150 = Asciz	(Lscala/Function0;)Lscala/util/parsing/combinator/Parsers$ParseResult;;
const #151 = Asciz	a;
const #152 = Asciz	Lscala/Function0;;
const #153 = Asciz	<U:Ljava/lang/Object;>(Lscala/Function0<Lscala/util/parsing/combinator/Parsers$ParseResult<TU;>;>;)Lscala/util/parsing/combinator/Parsers$ParseResult<TU;>;;
const #154 = Asciz	flatMapWithNext;
const #155 = Asciz	scala/Function1;
const #156 = class	#155;	//  scala/Function1
const #157 = Asciz	apply;
const #158 = Asciz	(Ljava/lang/Object;)Ljava/lang/Object;;
const #159 = NameAndType	#157:#158;//  apply:(Ljava/lang/Object;)Ljava/lang/Object;
const #160 = InterfaceMethod	#156.#159;	//  scala/Function1.apply:(Ljava/lang/Object;)Ljava/lang/Object;
const #161 = Asciz	<U:Ljava/lang/Object;>(Lscala/Function1<TT;Lscala/Function1<Lscala/util/parsing/input/Reader<Ljava/lang/Object;>;Lscala/util/parsing/combinator/Parsers$ParseResult<TU;>;>;>;)Lscala/util/parsing/combinator/Parsers$ParseResult<TU;>;;
const #162 = Asciz	mapPartial;
const #163 = Asciz	(Lscala/PartialFunction;Lscala/Function1;)Lscala/util/parsing/combinator/Parsers$ParseResult;;
const #164 = Asciz	scala/PartialFunction;
const #165 = class	#164;	//  scala/PartialFunction
const #166 = Asciz	isDefinedAt;
const #167 = NameAndType	#166:#59;//  isDefinedAt:(Ljava/lang/Object;)Z
const #168 = InterfaceMethod	#165.#167;	//  scala/PartialFunction.isDefinedAt:(Ljava/lang/Object;)Z
const #169 = Asciz	scala/util/parsing/combinator/Parsers$Failure;
const #170 = class	#169;	//  scala/util/parsing/combinator/Parsers$Failure
const #171 = Asciz	java/lang/String;
const #172 = class	#171;	//  java/lang/String
const #173 = Asciz	(Lscala/util/parsing/combinator/Parsers;Ljava/lang/String;Lscala/util/parsing/input/Reader;)V;
const #174 = NameAndType	#12:#173;//  "<init>":(Lscala/util/parsing/combinator/Parsers;Ljava/lang/String;Lscala/util/parsing/input/Reader;)V
const #175 = Method	#170.#174;	//  scala/util/parsing/combinator/Parsers$Failure."<init>":(Lscala/util/parsing/combinator/Parsers;Ljava/lang/String;Lscala/util/parsing/input/Reader;)V
const #176 = Asciz	Lscala/PartialFunction;;
const #177 = Asciz	error;
const #178 = Asciz	<U:Ljava/lang/Object;>(Lscala/PartialFunction<TT;TU;>;Lscala/Function1<TT;Ljava/lang/String;>;)Lscala/util/parsing/combinator/Parsers$ParseResult<TU;>;;
const #179 = Asciz	<U:Ljava/lang/Object;>(Lscala/Function1<TT;TU;>;)Lscala/util/parsing/combinator/Parsers$Success<TU;>;;
const #180 = Asciz	()Lscala/util/parsing/input/Reader<Ljava/lang/Object;>;;
const #181 = Asciz	copy$default$1;
const #182 = Asciz	copy$default$2;
const #183 = Asciz	productElements;
const #184 = Asciz	()Lscala/collection/Iterator;;
const #185 = Asciz	(Lscala/Product;)Lscala/collection/Iterator;;
const #186 = NameAndType	#183:#185;//  productElements:(Lscala/Product;)Lscala/collection/Iterator;
const #187 = Method	#28.#186;	//  scala/Product$class.productElements:(Lscala/Product;)Lscala/collection/Iterator;
const #188 = Asciz	Deprecated;
const #189 = Asciz	productIterator;
const #190 = NameAndType	#189:#185;//  productIterator:(Lscala/Product;)Lscala/collection/Iterator;
const #191 = Method	#28.#190;	//  scala/Product$class.productIterator:(Lscala/Product;)Lscala/collection/Iterator;
const #192 = Asciz	<T:Ljava/lang/Object;>Lscala/util/parsing/combinator/Parsers$ParseResult<TT;>;Lscala/ScalaObject;Lscala/Product;;
const #193 = Asciz	Scala;
const #194 = Asciz	InnerClasses;
const #195 = Asciz	scala/util/parsing/combinator/Parsers;
const #196 = class	#195;	//  scala/util/parsing/combinator/Parsers
const #197 = Asciz	Failure;
const #198 = Asciz	ParseResult;
const #199 = Asciz	scala/ScalaObject;
const #200 = class	#199;	//  scala/ScalaObject
const #201 = Asciz	scala/Product;
const #202 = class	#201;	//  scala/Product
const #203 = Asciz	java/io/Serializable;
const #204 = class	#203;	//  java/io/Serializable

{
public scala.util.parsing.combinator.Parsers$Success(scala.util.parsing.combinator.Parsers, java.lang.Object, scala.util.parsing.input.Reader);
  Code:
   Stack=2, Locals=4, Args_size=4
   0:	aload_0
   1:	aload_2
   2:	putfield	#19; //Field result:Ljava/lang/Object;
   5:	aload_0
   6:	aload_3
   7:	putfield	#21; //Field next:Lscala/util/parsing/input/Reader;
   10:	aload_0
   11:	aload_1
   12:	invokespecial	#26; //Method scala/util/parsing/combinator/Parsers$ParseResult."<init>":(Lscala/util/parsing/combinator/Parsers;)V
   15:	aload_0
   16:	invokestatic	#32; //Method scala/Product$class.$init$:(Lscala/Product;)V
   19:	aload_0
   20:	iconst_1
   21:	putfield	#34; //Field successful:Z
   24:	return
  LineNumberTable: 
   line 120: 0
   line 136: 19

  LocalVariableTable: 
   Start  Length  Slot  Name   Signature
   0      25      0    this       Lscala/util/parsing/combinator/Parsers$Success;
   0      25      1    $outer       Lscala/util/parsing/combinator/Parsers;
   0      25      2    result       Ljava/lang/Object;
   0      25      3    next       Lscala/util/parsing/input/Reader;

  Signature: length = 0x2
   00 28 

public scala.util.parsing.combinator.Parsers$ParseResult map(scala.Function1);
  Code:
   Stack=2, Locals=2, Args_size=2
   0:	aload_0
   1:	aload_1
   2:	invokevirtual	#70; //Method map:(Lscala/Function1;)Lscala/util/parsing/combinator/Parsers$Success;
   5:	areturn
  LineNumberTable: 
   line 120: 0

  LocalVariableTable: 
   Start  Length  Slot  Name   Signature
   0      6      0    this       Lscala/util/parsing/combinator/Parsers$Success;
   0      6      1    f       Lscala/Function1;


public scala.util.parsing.combinator.Parsers scala$util$parsing$combinator$Parsers$Success$$$outer();
  Code:
   Stack=1, Locals=1, Args_size=1
   0:	aload_0
   1:	getfield	#76; //Field scala/util/parsing/combinator/Parsers$ParseResult.$outer:Lscala/util/parsing/combinator/Parsers;
   4:	areturn
  LineNumberTable: 
   line 120: 0


public boolean canEqual(java.lang.Object);
  Code:
   Stack=1, Locals=2, Args_size=2
   0:	aload_1
   1:	instanceof	#17; //class scala/util/parsing/combinator/Parsers$Success
   4:	ireturn
  LineNumberTable: 
   line 120: 0


public java.lang.Object productElement(int);
  Code:
   Stack=3, Locals=2, Args_size=2
   0:	iload_1
   1:	tableswitch{ //0 to 1
		0: 84;
		1: 58;
		default: 24 }
   24:	iconst_1
   25:	ifeq	43
   28:	new	#81; //class java/lang/IndexOutOfBoundsException
   31:	dup
   32:	iload_1
   33:	invokestatic	#85; //Method scala/runtime/BoxesRunTime.boxToInteger:(I)Ljava/lang/Integer;
   36:	invokevirtual	#89; //Method java/lang/Object.toString:()Ljava/lang/String;
   39:	invokespecial	#92; //Method java/lang/IndexOutOfBoundsException."<init>":(Ljava/lang/String;)V
   42:	athrow
   43:	new	#94; //class scala/MatchError
   46:	dup
   47:	iload_1
   48:	invokestatic	#85; //Method scala/runtime/BoxesRunTime.boxToInteger:(I)Ljava/lang/Integer;
   51:	invokevirtual	#89; //Method java/lang/Object.toString:()Ljava/lang/String;
   54:	invokespecial	#95; //Method scala/MatchError."<init>":(Ljava/lang/String;)V
   57:	athrow
   58:	iconst_1
   59:	ifeq	69
   62:	aload_0
   63:	invokevirtual	#64; //Method next:()Lscala/util/parsing/input/Reader;
   66:	goto	92
   69:	new	#94; //class scala/MatchError
   72:	dup
   73:	iload_1
   74:	invokestatic	#85; //Method scala/runtime/BoxesRunTime.boxToInteger:(I)Ljava/lang/Integer;
   77:	invokevirtual	#89; //Method java/lang/Object.toString:()Ljava/lang/String;
   80:	invokespecial	#95; //Method scala/MatchError."<init>":(Ljava/lang/String;)V
   83:	athrow
   84:	iconst_1
   85:	ifeq	93
   88:	aload_0
   89:	invokevirtual	#45; //Method result:()Ljava/lang/Object;
   92:	areturn
   93:	new	#94; //class scala/MatchError
   96:	dup
   97:	iload_1
   98:	invokestatic	#85; //Method scala/runtime/BoxesRunTime.boxToInteger:(I)Ljava/lang/Integer;
   101:	invokevirtual	#89; //Method java/lang/Object.toString:()Ljava/lang/String;
   104:	invokespecial	#95; //Method scala/MatchError."<init>":(Ljava/lang/String;)V
   107:	athrow
  LineNumberTable: 
   line 120: 0
   line 21: 24
   line 120: 28
   line 21: 58
   line 120: 62
   line 21: 84
   line 120: 88


public int productArity();
  Code:
   Stack=1, Locals=1, Args_size=1
   0:	iconst_2
   1:	ireturn
  LineNumberTable: 
   line 120: 0


public java.lang.String productPrefix();
  Code:
   Stack=1, Locals=1, Args_size=1
   0:	ldc	#100; //String Success
   2:	areturn
  LineNumberTable: 
   line 120: 0


public boolean equals(java.lang.Object);
  Code:
   Stack=3, Locals=5, Args_size=2
   0:	aload_0
   1:	aload_1
   2:	if_acmpeq	93
   5:	aload_1
   6:	instanceof	#17; //class scala/util/parsing/combinator/Parsers$Success
   9:	ifeq	85
   12:	aload_1
   13:	checkcast	#17; //class scala/util/parsing/combinator/Parsers$Success
   16:	invokevirtual	#102; //Method scala$util$parsing$combinator$Parsers$Success$$$outer:()Lscala/util/parsing/combinator/Parsers;
   19:	aload_0
   20:	invokevirtual	#102; //Method scala$util$parsing$combinator$Parsers$Success$$$outer:()Lscala/util/parsing/combinator/Parsers;
   23:	if_acmpne	85
   26:	aload_1
   27:	checkcast	#17; //class scala/util/parsing/combinator/Parsers$Success
   30:	astore_2
   31:	aload_2
   32:	invokevirtual	#45; //Method result:()Ljava/lang/Object;
   35:	astore_3
   36:	aload_2
   37:	invokevirtual	#64; //Method next:()Lscala/util/parsing/input/Reader;
   40:	astore	4
   42:	aload_0
   43:	aload_3
   44:	aload	4
   46:	invokespecial	#104; //Method gd1$1:(Ljava/lang/Object;Lscala/util/parsing/input/Reader;)Z
   49:	ifeq	65
   52:	aload_1
   53:	checkcast	#17; //class scala/util/parsing/combinator/Parsers$Success
   56:	aload_0
   57:	invokeinterface	#108,  2; //InterfaceMethod scala/Equals.canEqual:(Ljava/lang/Object;)Z
   62:	goto	90
   65:	iconst_1
   66:	ifeq	73
   69:	iconst_0
   70:	goto	90
   73:	new	#94; //class scala/MatchError
   76:	dup
   77:	aload_1
   78:	invokevirtual	#89; //Method java/lang/Object.toString:()Ljava/lang/String;
   81:	invokespecial	#95; //Method scala/MatchError."<init>":(Ljava/lang/String;)V
   84:	athrow
   85:	iconst_1
   86:	ifeq	99
   89:	iconst_0
   90:	ifeq	97
   93:	iconst_1
   94:	goto	98
   97:	iconst_0
   98:	ireturn
   99:	new	#94; //class scala/MatchError
   102:	dup
   103:	aload_1
   104:	invokevirtual	#89; //Method java/lang/Object.toString:()Ljava/lang/String;
   107:	invokespecial	#95; //Method scala/MatchError."<init>":(Ljava/lang/String;)V
   110:	athrow
  LineNumberTable: 
   line 120: 0
   line 21: 65
   line 120: 73
   line 21: 85
   line 120: 90

  LocalVariableTable: 
   Start  Length  Slot  Name   Signature
   0      111      0    this       Lscala/util/parsing/combinator/Parsers$Success;
   31      54      2    temp2       Lscala/util/parsing/combinator/Parsers$Success;
   36      49      3    temp3       Ljava/lang/Object;
   42      43      4    temp4       Lscala/util/parsing/input/Reader;


public int hashCode();
  Code:
   Stack=2, Locals=1, Args_size=1
   0:	getstatic	#118; //Field scala/runtime/ScalaRunTime$.MODULE$:Lscala/runtime/ScalaRunTime$;
   3:	aload_0
   4:	invokevirtual	#122; //Method scala/runtime/ScalaRunTime$._hashCode:(Lscala/Product;)I
   7:	ireturn
  LineNumberTable: 
   line 120: 0


public scala.util.parsing.combinator.Parsers$Success copy(java.lang.Object, scala.util.parsing.input.Reader);
  Code:
   Stack=5, Locals=3, Args_size=3
   0:	new	#17; //class scala/util/parsing/combinator/Parsers$Success
   3:	dup
   4:	aload_0
   5:	invokevirtual	#102; //Method scala$util$parsing$combinator$Parsers$Success$$$outer:()Lscala/util/parsing/combinator/Parsers;
   8:	aload_1
   9:	aload_2
   10:	invokespecial	#126; //Method "<init>":(Lscala/util/parsing/combinator/Parsers;Ljava/lang/Object;Lscala/util/parsing/input/Reader;)V
   13:	areturn
  LineNumberTable: 
   line 120: 0

  LocalVariableTable: 
   Start  Length  Slot  Name   Signature
   0      14      0    this       Lscala/util/parsing/combinator/Parsers$Success;
   0      14      1    result       Ljava/lang/Object;
   0      14      2    next       Lscala/util/parsing/input/Reader;


public boolean successful();
  Code:
   Stack=1, Locals=1, Args_size=1
   0:	aload_0
   1:	getfield	#34; //Field successful:Z
   4:	ireturn
  LineNumberTable: 
   line 136: 0


public java.lang.String toString();
  Code:
   Stack=2, Locals=1, Args_size=1
   0:	new	#129; //class scala/collection/mutable/StringBuilder
   3:	dup
   4:	invokespecial	#132; //Method scala/collection/mutable/StringBuilder."<init>":()V
   7:	ldc	#134; //String [
   9:	invokevirtual	#138; //Method scala/collection/mutable/StringBuilder.append:(Ljava/lang/Object;)Lscala/collection/mutable/StringBuilder;
   12:	aload_0
   13:	invokevirtual	#64; //Method next:()Lscala/util/parsing/input/Reader;
   16:	invokevirtual	#144; //Method scala/util/parsing/input/Reader.pos:()Lscala/util/parsing/input/Position;
   19:	invokevirtual	#138; //Method scala/collection/mutable/StringBuilder.append:(Ljava/lang/Object;)Lscala/collection/mutable/StringBuilder;
   22:	ldc	#146; //String ] parsed: 
   24:	invokevirtual	#138; //Method scala/collection/mutable/StringBuilder.append:(Ljava/lang/Object;)Lscala/collection/mutable/StringBuilder;
   27:	aload_0
   28:	invokevirtual	#45; //Method result:()Ljava/lang/Object;
   31:	invokevirtual	#138; //Method scala/collection/mutable/StringBuilder.append:(Ljava/lang/Object;)Lscala/collection/mutable/StringBuilder;
   34:	invokevirtual	#147; //Method scala/collection/mutable/StringBuilder.toString:()Ljava/lang/String;
   37:	areturn
  LineNumberTable: 
   line 134: 0


public java.lang.Object get();
  Code:
   Stack=1, Locals=1, Args_size=1
   0:	aload_0
   1:	invokevirtual	#45; //Method result:()Ljava/lang/Object;
   4:	areturn
  LineNumberTable: 
   line 131: 0

  Signature: length = 0x2
   00 FFFFFF95 

public scala.util.parsing.combinator.Parsers$ParseResult append(scala.Function0);
  Code:
   Stack=1, Locals=2, Args_size=2
   0:	aload_0
   1:	areturn
  LineNumberTable: 
   line 129: 0

  LocalVariableTable: 
   Start  Length  Slot  Name   Signature
   0      2      0    this       Lscala/util/parsing/combinator/Parsers$Success;
   0      2      1    a       Lscala/Function0;

  Signature: length = 0x2
   00 FFFFFF99 

public scala.util.parsing.combinator.Parsers$ParseResult flatMapWithNext(scala.Function1);
  Code:
   Stack=2, Locals=2, Args_size=2
   0:	aload_1
   1:	aload_0
   2:	invokevirtual	#45; //Method result:()Ljava/lang/Object;
   5:	invokeinterface	#160,  2; //InterfaceMethod scala/Function1.apply:(Ljava/lang/Object;)Ljava/lang/Object;
   10:	checkcast	#156; //class scala/Function1
   13:	aload_0
   14:	invokevirtual	#64; //Method next:()Lscala/util/parsing/input/Reader;
   17:	invokeinterface	#160,  2; //InterfaceMethod scala/Function1.apply:(Ljava/lang/Object;)Ljava/lang/Object;
   22:	checkcast	#23; //class scala/util/parsing/combinator/Parsers$ParseResult
   25:	areturn
  LineNumberTable: 
   line 127: 0

  LocalVariableTable: 
   Start  Length  Slot  Name   Signature
   0      26      0    this       Lscala/util/parsing/combinator/Parsers$Success;
   0      26      1    f       Lscala/Function1;

  Signature: length = 0x2
   00 FFFFFFA1 

public scala.util.parsing.combinator.Parsers$ParseResult mapPartial(scala.PartialFunction, scala.Function1);
  Code:
   Stack=5, Locals=3, Args_size=3
   0:	aload_1
   1:	aload_0
   2:	invokevirtual	#45; //Method result:()Ljava/lang/Object;
   5:	invokeinterface	#168,  2; //InterfaceMethod scala/PartialFunction.isDefinedAt:(Ljava/lang/Object;)Z
   10:	ifeq	41
   13:	new	#17; //class scala/util/parsing/combinator/Parsers$Success
   16:	dup
   17:	aload_0
   18:	invokevirtual	#102; //Method scala$util$parsing$combinator$Parsers$Success$$$outer:()Lscala/util/parsing/combinator/Parsers;
   21:	aload_1
   22:	aload_0
   23:	invokevirtual	#45; //Method result:()Ljava/lang/Object;
   26:	invokeinterface	#160,  2; //InterfaceMethod scala/Function1.apply:(Ljava/lang/Object;)Ljava/lang/Object;
   31:	aload_0
   32:	invokevirtual	#64; //Method next:()Lscala/util/parsing/input/Reader;
   35:	invokespecial	#126; //Method "<init>":(Lscala/util/parsing/combinator/Parsers;Ljava/lang/Object;Lscala/util/parsing/input/Reader;)V
   38:	goto	69
   41:	new	#170; //class scala/util/parsing/combinator/Parsers$Failure
   44:	dup
   45:	aload_0
   46:	invokevirtual	#102; //Method scala$util$parsing$combinator$Parsers$Success$$$outer:()Lscala/util/parsing/combinator/Parsers;
   49:	aload_2
   50:	aload_0
   51:	invokevirtual	#45; //Method result:()Ljava/lang/Object;
   54:	invokeinterface	#160,  2; //InterfaceMethod scala/Function1.apply:(Ljava/lang/Object;)Ljava/lang/Object;
   59:	checkcast	#172; //class java/lang/String
   62:	aload_0
   63:	invokevirtual	#64; //Method next:()Lscala/util/parsing/input/Reader;
   66:	invokespecial	#175; //Method scala/util/parsing/combinator/Parsers$Failure."<init>":(Lscala/util/parsing/combinator/Parsers;Ljava/lang/String;Lscala/util/parsing/input/Reader;)V
   69:	areturn
  LineNumberTable: 
   line 123: 0
   line 124: 41
   line 123: 69

  LocalVariableTable: 
   Start  Length  Slot  Name   Signature
   0      70      0    this       Lscala/util/parsing/combinator/Parsers$Success;
   0      70      1    f       Lscala/PartialFunction;
   0      70      2    error       Lscala/Function1;

  Signature: length = 0x2
   00 FFFFFFB2 

public scala.util.parsing.combinator.Parsers$Success map(scala.Function1);
  Code:
   Stack=5, Locals=2, Args_size=2
   0:	new	#17; //class scala/util/parsing/combinator/Parsers$Success
   3:	dup
   4:	aload_0
   5:	invokevirtual	#102; //Method scala$util$parsing$combinator$Parsers$Success$$$outer:()Lscala/util/parsing/combinator/Parsers;
   8:	aload_1
   9:	aload_0
   10:	invokevirtual	#45; //Method result:()Ljava/lang/Object;
   13:	invokeinterface	#160,  2; //InterfaceMethod scala/Function1.apply:(Ljava/lang/Object;)Ljava/lang/Object;
   18:	aload_0
   19:	invokevirtual	#64; //Method next:()Lscala/util/parsing/input/Reader;
   22:	invokespecial	#126; //Method "<init>":(Lscala/util/parsing/combinator/Parsers;Ljava/lang/Object;Lscala/util/parsing/input/Reader;)V
   25:	areturn
  LineNumberTable: 
   line 121: 0

  LocalVariableTable: 
   Start  Length  Slot  Name   Signature
   0      26      0    this       Lscala/util/parsing/combinator/Parsers$Success;
   0      26      1    f       Lscala/Function1;

  Signature: length = 0x2
   00 FFFFFFB3 

public scala.util.parsing.input.Reader next();
  Code:
   Stack=1, Locals=1, Args_size=1
   0:	aload_0
   1:	getfield	#21; //Field next:Lscala/util/parsing/input/Reader;
   4:	areturn
  LineNumberTable: 
   line 120: 0

  Signature: length = 0x2
   00 FFFFFFB4 

public java.lang.Object result();
  Code:
   Stack=1, Locals=1, Args_size=1
   0:	aload_0
   1:	getfield	#19; //Field result:Ljava/lang/Object;
   4:	areturn
  LineNumberTable: 
   line 120: 0

  Signature: length = 0x2
   00 FFFFFF95 

public java.lang.Object copy$default$1();
  Code:
   Stack=1, Locals=1, Args_size=1
   0:	aload_0
   1:	invokevirtual	#45; //Method result:()Ljava/lang/Object;
   4:	areturn
  LineNumberTable: 
   line 120: 0


public scala.util.parsing.input.Reader copy$default$2();
  Code:
   Stack=1, Locals=1, Args_size=1
   0:	aload_0
   1:	invokevirtual	#64; //Method next:()Lscala/util/parsing/input/Reader;
   4:	areturn
  LineNumberTable: 
   line 120: 0


public scala.collection.Iterator productElements();
  Code:
   Stack=1, Locals=1, Args_size=1
   0:	aload_0
   1:	invokestatic	#187; //Method scala/Product$class.productElements:(Lscala/Product;)Lscala/collection/Iterator;
   4:	areturn
  LineNumberTable: 
   line 120: 0

  Deprecated: true

public scala.collection.Iterator productIterator();
  Code:
   Stack=1, Locals=1, Args_size=1
   0:	aload_0
   1:	invokestatic	#191; //Method scala/Product$class.productIterator:(Lscala/Product;)Lscala/collection/Iterator;
   4:	areturn
  LineNumberTable: 
   line 120: 0


}

