Compiled from "Parsers.scala"
public final class scala.util.parsing.combinator.Parsers$$tilde$ extends java.lang.Object implements scala.ScalaObject
  SourceFile: "Parsers.scala"
  Scala: length = 0x
   
  InnerClass: 
   public $tilde=class scala/util/parsing/combinator/Parsers$$tilde of class scala/util/parsing/combinator/Parsers
  minor version: 0
  major version: 49
  Constant pool:
Asciz	SourceFile;
Asciz	Parsers.scala;
Asciz	Scala;
Asciz	$outer;
Asciz	Lscala/util/parsing/combinator/Parsers;;
Asciz	unapply;
Asciz	(Lscala/util/parsing/combinator/Parsers$$tilde;)Lscala/Option;;
Asciz	Code;
Asciz	LineNumberTable;
Asciz	java/lang/Object;
class	java/lang/Object
Asciz	equals;
Asciz	(Ljava/lang/Object;)Z;
NameAndType	equals:(Ljava/lang/Object;)Z
Method	java/lang/Object.equals:(Ljava/lang/Object;)Z
Asciz	scala/None$;
class	scala/None$
Asciz	MODULE$;
Asciz	Lscala/None$;;
NameAndType	MODULE$:Lscala/None$;
Field	scala/None$.MODULE$:Lscala/None$;
Asciz	scala/Some;
class	scala/Some
Asciz	scala/Tuple2;
class	scala/Tuple2
Asciz	scala/util/parsing/combinator/Parsers$$tilde;
class	scala/util/parsing/combinator/Parsers$$tilde
Asciz	_1;
Asciz	()Ljava/lang/Object;;
NameAndType	_1:()Ljava/lang/Object;
Method	scala/util/parsing/combinator/Parsers$$tilde._1:()Ljava/lang/Object;
Asciz	_2;
NameAndType	_2:()Ljava/lang/Object;
Method	scala/util/parsing/combinator/Parsers$$tilde._2:()Ljava/lang/Object;
Asciz	<init>;
Asciz	(Ljava/lang/Object;Ljava/lang/Object;)V;
NameAndType	"<init>":(Ljava/lang/Object;Ljava/lang/Object;)V
Method	scala/Tuple2."<init>":(Ljava/lang/Object;Ljava/lang/Object;)V
Asciz	(Ljava/lang/Object;)V;
NameAndType	"<init>":(Ljava/lang/Object;)V
Method	scala/Some."<init>":(Ljava/lang/Object;)V
Asciz	this;
Asciz	Lscala/util/parsing/combinator/Parsers$$tilde$;;
Asciz	x$0;
Asciz	Lscala/util/parsing/combinator/Parsers$$tilde;;
Asciz	LocalVariableTable;
Asciz	apply;
Asciz	(Ljava/lang/Object;Ljava/lang/Object;)Lscala/util/parsing/combinator/Parsers$$tilde;;
Asciz	scala/util/parsing/combinator/Parsers$$tilde$;
class	scala/util/parsing/combinator/Parsers$$tilde$
NameAndType	$outer:Lscala/util/parsing/combinator/Parsers;
Field	scala/util/parsing/combinator/Parsers$$tilde$.$outer:Lscala/util/parsing/combinator/Parsers;
Asciz	(Lscala/util/parsing/combinator/Parsers;Ljava/lang/Object;Ljava/lang/Object;)V;
NameAndType	"<init>":(Lscala/util/parsing/combinator/Parsers;Ljava/lang/Object;Ljava/lang/Object;)V
Method	scala/util/parsing/combinator/Parsers$$tilde."<init>":(Lscala/util/parsing/combinator/Parsers;Ljava/lang/Object;Ljava/lang/Object;)V
Asciz	Ljava/lang/Object;;
Asciz	(Lscala/util/parsing/combinator/Parsers;)V;
Asciz	java/lang/NullPointerException;
class	java/lang/NullPointerException
Asciz	()V;
NameAndType	"<init>":()V
Method	java/lang/NullPointerException."<init>":()V
Method	java/lang/Object."<init>":()V
Asciz	InnerClasses;
Asciz	scala/util/parsing/combinator/Parsers;
class	scala/util/parsing/combinator/Parsers
Asciz	$tilde;
Asciz	scala/ScalaObject;
class	scala/ScalaObject

{
private final scala.util.parsing.combinator.Parsers $outer;
  Signature: Lscala/util/parsing/combinator/Parsers;

public scala.Option unapply(scala.util.parsing.combinator.Parsers$$tilde);
  Signature: (Lscala/util/parsing/combinator/Parsers$$tilde;)Lscala/Option;
  Code:
   Stack=6, Locals=2, Args_size=2
	aload_1
	dup
	pop
	ifnull	l1 // getstatic
	aload_1
	aconst_null
	invokevirtual	Method java/lang/Object.equals:(Ljava/lang/Object;)Z
	ifeq	l2 // new
l1	getstatic	Field scala/None$.MODULE$:Lscala/None$;
	goto	l3 // areturn
l2	new	class scala/Some
	dup
	new	class scala/Tuple2
	dup
	aload_1
	invokevirtual	Method scala/util/parsing/combinator/Parsers$$tilde._1:()Ljava/lang/Object;
	aload_1
	invokevirtual	Method scala/util/parsing/combinator/Parsers$$tilde._2:()Ljava/lang/Object;
	invokespecial	Method scala/Tuple2."<init>":(Ljava/lang/Object;Ljava/lang/Object;)V
	invokespecial	Method scala/Some."<init>":(Ljava/lang/Object;)V
l3	areturn
  Labels:
   	l1 = 14 // getstatic
   	l2 = 20 // new
   	l3 = 42 // areturn
  LocalVariableTable: 
   Start  Length  Slot  Name   Signature
   0      43      0    this       Lscala/util/parsing/combinator/Parsers$$tilde$;
   0      43      1    x$0       Lscala/util/parsing/combinator/Parsers$$tilde;


public scala.util.parsing.combinator.Parsers$$tilde apply(java.lang.Object, java.lang.Object);
  Signature: (Ljava/lang/Object;Ljava/lang/Object;)Lscala/util/parsing/combinator/Parsers$$tilde;
  Code:
   Stack=5, Locals=3, Args_size=3
	new	class scala/util/parsing/combinator/Parsers$$tilde
	dup
	aload_0
	getfield	Field $outer:Lscala/util/parsing/combinator/Parsers;
	aload_1
	aload_2
	invokespecial	Method scala/util/parsing/combinator/Parsers$$tilde."<init>":(Lscala/util/parsing/combinator/Parsers;Ljava/lang/Object;Ljava/lang/Object;)V
	areturn
  Labels:
  LocalVariableTable: 
   Start  Length  Slot  Name   Signature
   0      14      0    this       Lscala/util/parsing/combinator/Parsers$$tilde$;
   0      14      1    _1       Ljava/lang/Object;
   0      14      2    _2       Ljava/lang/Object;


public scala.util.parsing.combinator.Parsers$$tilde$(scala.util.parsing.combinator.Parsers);
  Signature: (Lscala/util/parsing/combinator/Parsers;)V
  Code:
   Stack=2, Locals=2, Args_size=2
	aload_1
	ifnonnull	l1 // aload_0
	new	class java/lang/NullPointerException
	dup
	invokespecial	Method java/lang/NullPointerException."<init>":()V
	athrow
l1	aload_0
	aload_1
	putfield	Field $outer:Lscala/util/parsing/combinator/Parsers;
	aload_0
	invokespecial	Method java/lang/Object."<init>":()V
	return
  Labels:
   	l1 = 12 // aload_0
  LocalVariableTable: 
   Start  Length  Slot  Name   Signature
   0      22      0    this       Lscala/util/parsing/combinator/Parsers$$tilde$;
   0      22      1    $outer       Lscala/util/parsing/combinator/Parsers;


}

