Compiled from "RegexParsers.scala"
public final class scala.util.parsing.combinator.RegexParsers$$anon$1 extends scala.util.parsing.combinator.Parsers$Parser
  SourceFile: "RegexParsers.scala"
  Scala: length = 0x
   
  Signature: length = 0x2
   00 76 
  InnerClass: 
   public abstract Parser=class scala/util/parsing/combinator/Parsers$Parser of class scala/util/parsing/combinator/Parsers
   public Failure=class scala/util/parsing/combinator/Parsers$Failure of class scala/util/parsing/combinator/Parsers
   public Success=class scala/util/parsing/combinator/Parsers$Success of class scala/util/parsing/combinator/Parsers
   public abstract ParseResult=class scala/util/parsing/combinator/Parsers$ParseResult of class scala/util/parsing/combinator/Parsers
   public final $anon$1=class scala/util/parsing/combinator/RegexParsers$$anon$1 of class scala/util/parsing/combinator/RegexParsers
  minor version: 0
  major version: 49
  Constant pool:
Asciz	SourceFile;
Asciz	RegexParsers.scala;
Asciz	$outer;
Asciz	Lscala/util/parsing/combinator/RegexParsers;;
Asciz	s$1;
Asciz	Ljava/lang/String;;
Asciz	apply;
Asciz	(Lscala/util/parsing/input/Reader;)Lscala/util/parsing/combinator/Parsers$ParseResult;;
Asciz	Code;
Asciz	LineNumberTable;
Asciz	scala/util/parsing/input/Reader;
class	scala/util/parsing/input/Reader
Asciz	source;
Asciz	()Ljava/lang/CharSequence;;
NameAndType	source:()Ljava/lang/CharSequence;
Method	scala/util/parsing/input/Reader.source:()Ljava/lang/CharSequence;
Asciz	offset;
Asciz	()I;
NameAndType	offset:()I
Method	scala/util/parsing/input/Reader.offset:()I
Asciz	scala/util/parsing/combinator/RegexParsers$$anon$1;
class	scala/util/parsing/combinator/RegexParsers$$anon$1
NameAndType	$outer:Lscala/util/parsing/combinator/RegexParsers;
Field	scala/util/parsing/combinator/RegexParsers$$anon$1.$outer:Lscala/util/parsing/combinator/RegexParsers;
Asciz	scala/util/parsing/combinator/RegexParsers;
class	scala/util/parsing/combinator/RegexParsers
Asciz	handleWhiteSpace;
Asciz	(Ljava/lang/CharSequence;I)I;
NameAndType	handleWhiteSpace:(Ljava/lang/CharSequence;I)I
InterfaceMethod	scala/util/parsing/combinator/RegexParsers.handleWhiteSpace:(Ljava/lang/CharSequence;I)I
NameAndType	s$1:Ljava/lang/String;
Field	scala/util/parsing/combinator/RegexParsers$$anon$1.s$1:Ljava/lang/String;
Asciz	java/lang/String;
class	java/lang/String
Asciz	length;
NameAndType	length:()I
Method	java/lang/String.length:()I
Asciz	java/lang/CharSequence;
class	java/lang/CharSequence
InterfaceMethod	java/lang/CharSequence.length:()I
Asciz	charAt;
Asciz	(I)C;
NameAndType	charAt:(I)C
Method	java/lang/String.charAt:(I)C
InterfaceMethod	java/lang/CharSequence.charAt:(I)C
Asciz	scala/util/parsing/combinator/Parsers$Success;
class	scala/util/parsing/combinator/Parsers$Success
Asciz	subSequence;
Asciz	(II)Ljava/lang/CharSequence;;
NameAndType	subSequence:(II)Ljava/lang/CharSequence;
InterfaceMethod	java/lang/CharSequence.subSequence:(II)Ljava/lang/CharSequence;
Asciz	java/lang/Object;
class	java/lang/Object
Asciz	toString;
Asciz	()Ljava/lang/String;;
NameAndType	toString:()Ljava/lang/String;
Method	java/lang/Object.toString:()Ljava/lang/String;
Asciz	drop;
Asciz	(I)Lscala/util/parsing/input/Reader;;
NameAndType	drop:(I)Lscala/util/parsing/input/Reader;
Method	scala/util/parsing/input/Reader.drop:(I)Lscala/util/parsing/input/Reader;
Asciz	<init>;
Asciz	(Lscala/util/parsing/combinator/Parsers;Ljava/lang/Object;Lscala/util/parsing/input/Reader;)V;
NameAndType	"<init>":(Lscala/util/parsing/combinator/Parsers;Ljava/lang/Object;Lscala/util/parsing/input/Reader;)V
Method	scala/util/parsing/combinator/Parsers$Success."<init>":(Lscala/util/parsing/combinator/Parsers;Ljava/lang/Object;Lscala/util/parsing/input/Reader;)V
Asciz	scala/util/parsing/combinator/Parsers$Failure;
class	scala/util/parsing/combinator/Parsers$Failure
Asciz	scala/collection/mutable/StringBuilder;
class	scala/collection/mutable/StringBuilder
Asciz	()V;
NameAndType	"<init>":()V
Method	scala/collection/mutable/StringBuilder."<init>":()V
Asciz	`;
String	`
Asciz	append;
Asciz	(Ljava/lang/Object;)Lscala/collection/mutable/StringBuilder;;
NameAndType	append:(Ljava/lang/Object;)Lscala/collection/mutable/StringBuilder;
Method	scala/collection/mutable/StringBuilder.append:(Ljava/lang/Object;)Lscala/collection/mutable/StringBuilder;
Asciz	' expected but `;
String	' expected but `
Asciz	first;
Asciz	()Ljava/lang/Object;;
NameAndType	first:()Ljava/lang/Object;
Method	scala/util/parsing/input/Reader.first:()Ljava/lang/Object;
Asciz	' found;
String	' found
Method	scala/collection/mutable/StringBuilder.toString:()Ljava/lang/String;
Asciz	(Lscala/util/parsing/combinator/Parsers;Ljava/lang/String;Lscala/util/parsing/input/Reader;)V;
NameAndType	"<init>":(Lscala/util/parsing/combinator/Parsers;Ljava/lang/String;Lscala/util/parsing/input/Reader;)V
Method	scala/util/parsing/combinator/Parsers$Failure."<init>":(Lscala/util/parsing/combinator/Parsers;Ljava/lang/String;Lscala/util/parsing/input/Reader;)V
Asciz	this;
Asciz	Lscala/util/parsing/combinator/RegexParsers$$anon$1;;
Asciz	in;
Asciz	Lscala/util/parsing/input/Reader;;
Asciz	Ljava/lang/CharSequence;;
Asciz	I;
Asciz	start;
Asciz	i;
Asciz	j;
Asciz	LocalVariableTable;
Asciz	(Lscala/util/parsing/input/Reader<Ljava/lang/Character;>;)Lscala/util/parsing/combinator/Parsers$ParseResult<Ljava/lang/String;>;;
Asciz	Signature;
Asciz	(Ljava/lang/Object;)Ljava/lang/Object;;
NameAndType	apply:(Lscala/util/parsing/input/Reader;)Lscala/util/parsing/combinator/Parsers$ParseResult;
Method	scala/util/parsing/combinator/RegexParsers$$anon$1.apply:(Lscala/util/parsing/input/Reader;)Lscala/util/parsing/combinator/Parsers$ParseResult;
Asciz	v1;
Asciz	Ljava/lang/Object;;
Asciz	(Lscala/util/parsing/combinator/RegexParsers;Ljava/lang/String;)V;
Asciz	java/lang/NullPointerException;
class	java/lang/NullPointerException
Method	java/lang/NullPointerException."<init>":()V
Asciz	scala/util/parsing/combinator/Parsers$Parser;
class	scala/util/parsing/combinator/Parsers$Parser
Asciz	(Lscala/util/parsing/combinator/Parsers;)V;
NameAndType	"<init>":(Lscala/util/parsing/combinator/Parsers;)V
Method	scala/util/parsing/combinator/Parsers$Parser."<init>":(Lscala/util/parsing/combinator/Parsers;)V
Asciz	Scala;
Asciz	Lscala/util/parsing/combinator/Parsers$Parser<Ljava/lang/String;>;;
Asciz	InnerClasses;
Asciz	scala/util/parsing/combinator/Parsers;
class	scala/util/parsing/combinator/Parsers
Asciz	Parser;
Asciz	Failure;
Asciz	Success;
Asciz	scala/util/parsing/combinator/Parsers$ParseResult;
class	scala/util/parsing/combinator/Parsers$ParseResult
Asciz	ParseResult;
Asciz	$anon$1;

{
public final scala.util.parsing.combinator.RegexParsers $outer;
  Signature: Lscala/util/parsing/combinator/RegexParsers;

public final java.lang.String s$1;
  Signature: Ljava/lang/String;

public scala.util.parsing.combinator.Parsers$ParseResult apply(scala.util.parsing.input.Reader);
  Signature: (Lscala/util/parsing/input/Reader;)Lscala/util/parsing/combinator/Parsers$ParseResult;
  Code:
   Stack=7, Locals=7, Args_size=2
	aload_1
	invokevirtual	Method scala/util/parsing/input/Reader.source:()Ljava/lang/CharSequence;
	astore_2
	aload_1
	invokevirtual	Method scala/util/parsing/input/Reader.offset:()I
	istore_3
	aload_0
	getfield	Field $outer:Lscala/util/parsing/combinator/RegexParsers;
	aload_2
	iload_3
	invokeinterface	InterfaceMethod scala/util/parsing/combinator/RegexParsers.handleWhiteSpace:(Ljava/lang/CharSequence;I)I
	istore	4
	iconst_0
	istore	5
	iload	4
	istore	6
l2	iload	5
	aload_0
	getfield	Field s$1:Ljava/lang/String;
	invokevirtual	Method java/lang/String.length:()I
	if_icmpge	l1 // iload
	iload	6
	aload_2
	invokeinterface	InterfaceMethod java/lang/CharSequence.length:()I
	if_icmpge	l1 // iload
	aload_0
	getfield	Field s$1:Ljava/lang/String;
	iload	5
	invokevirtual	Method java/lang/String.charAt:(I)C
	aload_2
	iload	6
	invokeinterface	InterfaceMethod java/lang/CharSequence.charAt:(I)C
	if_icmpne	l1 // iload
	iload	5
	iconst_1
	iadd
	istore	5
	iload	6
	iconst_1
	iadd
	istore	6
	goto	l2 // iload
l1	iload	5
	aload_0
	getfield	Field s$1:Ljava/lang/String;
	invokevirtual	Method java/lang/String.length:()I
	if_icmpne	l3 // new
	new	class scala/util/parsing/combinator/Parsers$Success
	dup
	aload_0
	getfield	Field $outer:Lscala/util/parsing/combinator/RegexParsers;
	aload_2
	iload	4
	iload	6
	invokeinterface	InterfaceMethod java/lang/CharSequence.subSequence:(II)Ljava/lang/CharSequence;
	invokevirtual	Method java/lang/Object.toString:()Ljava/lang/String;
	aload_1
	iload	6
	iload_3
	isub
	invokevirtual	Method scala/util/parsing/input/Reader.drop:(I)Lscala/util/parsing/input/Reader;
	invokespecial	Method scala/util/parsing/combinator/Parsers$Success."<init>":(Lscala/util/parsing/combinator/Parsers;Ljava/lang/Object;Lscala/util/parsing/input/Reader;)V
	goto	l4 // areturn
l3	new	class scala/util/parsing/combinator/Parsers$Failure
	dup
	aload_0
	getfield	Field $outer:Lscala/util/parsing/combinator/RegexParsers;
	new	class scala/collection/mutable/StringBuilder
	dup
	invokespecial	Method scala/collection/mutable/StringBuilder."<init>":()V
	ldc	String `
	invokevirtual	Method scala/collection/mutable/StringBuilder.append:(Ljava/lang/Object;)Lscala/collection/mutable/StringBuilder;
	aload_0
	getfield	Field s$1:Ljava/lang/String;
	invokevirtual	Method scala/collection/mutable/StringBuilder.append:(Ljava/lang/Object;)Lscala/collection/mutable/StringBuilder;
	ldc	String ' expected but `
	invokevirtual	Method scala/collection/mutable/StringBuilder.append:(Ljava/lang/Object;)Lscala/collection/mutable/StringBuilder;
	aload_1
	invokevirtual	Method scala/util/parsing/input/Reader.first:()Ljava/lang/Object;
	invokevirtual	Method scala/collection/mutable/StringBuilder.append:(Ljava/lang/Object;)Lscala/collection/mutable/StringBuilder;
	ldc	String ' found
	invokevirtual	Method scala/collection/mutable/StringBuilder.append:(Ljava/lang/Object;)Lscala/collection/mutable/StringBuilder;
	invokevirtual	Method scala/collection/mutable/StringBuilder.toString:()Ljava/lang/String;
	aload_1
	iload	4
	iload_3
	isub
	invokevirtual	Method scala/util/parsing/input/Reader.drop:(I)Lscala/util/parsing/input/Reader;
	invokespecial	Method scala/util/parsing/combinator/Parsers$Failure."<init>":(Lscala/util/parsing/combinator/Parsers;Ljava/lang/String;Lscala/util/parsing/input/Reader;)V
l4	areturn
  Labels:
   	l2 = 30 // iload
   	l1 = 88 // iload
   	l3 = 135 // new
   	l4 = 193 // areturn
  LocalVariableTable: 
   Start  Length  Slot  Name   Signature
   0      194      0    this       Lscala/util/parsing/combinator/RegexParsers$$anon$1;
   0      194      1    in       Lscala/util/parsing/input/Reader;
   5      189      2    source       Ljava/lang/CharSequence;
   10      184      3    offset       I
   23      171      4    start       I
   26      168      5    i       I
   30      164      6    j       I

  Signature: length = 0x2
   00 65 

public java.lang.Object apply(java.lang.Object);
  Signature: (Ljava/lang/Object;)Ljava/lang/Object;
  Code:
   Stack=2, Locals=2, Args_size=2
	aload_0
	aload_1
	checkcast	class scala/util/parsing/input/Reader
	invokevirtual	Method apply:(Lscala/util/parsing/input/Reader;)Lscala/util/parsing/combinator/Parsers$ParseResult;
	areturn
  Labels:
  LocalVariableTable: 
   Start  Length  Slot  Name   Signature
   0      9      0    this       Lscala/util/parsing/combinator/RegexParsers$$anon$1;
   0      9      1    v1       Ljava/lang/Object;


public scala.util.parsing.combinator.RegexParsers$$anon$1(scala.util.parsing.combinator.RegexParsers, java.lang.String);
  Signature: (Lscala/util/parsing/combinator/RegexParsers;Ljava/lang/String;)V
  Code:
   Stack=2, Locals=3, Args_size=3
	aload_1
	ifnonnull	l1 // aload_0
	new	class java/lang/NullPointerException
	dup
	invokespecial	Method java/lang/NullPointerException."<init>":()V
	athrow
l1	aload_0
	aload_1
	putfield	Field $outer:Lscala/util/parsing/combinator/RegexParsers;
	aload_0
	aload_2
	putfield	Field s$1:Ljava/lang/String;
	aload_0
	aload_1
	invokespecial	Method scala/util/parsing/combinator/Parsers$Parser."<init>":(Lscala/util/parsing/combinator/Parsers;)V
	return
  Labels:
   	l1 = 12 // aload_0
  LocalVariableTable: 
   Start  Length  Slot  Name   Signature
   0      28      0    this       Lscala/util/parsing/combinator/RegexParsers$$anon$1;
   0      28      1    $outer       Lscala/util/parsing/combinator/RegexParsers;


}

