Compiled from "RegexParsers.scala"
public final class scala.util.parsing.combinator.RegexParsers$$anon$2 extends scala.util.parsing.combinator.Parsers$Parser
  SourceFile: "RegexParsers.scala"
  Signature: length = 0x2
   00 FFFFFF93 
  Scala: length = 0x
   
  InnerClass: 
   public Match=class scala/util/matching/Regex$Match of class scala/util/matching/Regex
   public abstract Parser=class scala/util/parsing/combinator/Parsers$Parser of class scala/util/parsing/combinator/Parsers
   public Failure=class scala/util/parsing/combinator/Parsers$Failure of class scala/util/parsing/combinator/Parsers
   public Success=class scala/util/parsing/combinator/Parsers$Success of class scala/util/parsing/combinator/Parsers
   public abstract ParseResult=class scala/util/parsing/combinator/Parsers$ParseResult of class scala/util/parsing/combinator/Parsers
   public final $anon$2=class scala/util/parsing/combinator/RegexParsers$$anon$2 of class scala/util/parsing/combinator/RegexParsers
  minor version: 0
  major version: 49
  Constant pool:
Asciz	SourceFile;
Asciz	RegexParsers.scala;
Asciz	r$1;
Asciz	Lscala/util/matching/Regex;;
Asciz	$outer;
Asciz	Lscala/util/parsing/combinator/RegexParsers;;
Asciz	apply;
Asciz	(Lscala/util/parsing/input/Reader;)Lscala/util/parsing/combinator/Parsers$ParseResult;;
Asciz	Code;
Asciz	LineNumberTable;
Asciz	scala/util/parsing/input/Reader;
class	scala/util/parsing/input/Reader
Asciz	source;
Asciz	()Ljava/lang/CharSequence;;
NameAndType	source:()Ljava/lang/CharSequence;
Method	scala/util/parsing/input/Reader.source:()Ljava/lang/CharSequence;
Asciz	offset;
Asciz	()I;
NameAndType	offset:()I
Method	scala/util/parsing/input/Reader.offset:()I
Asciz	scala/util/parsing/combinator/RegexParsers$$anon$2;
class	scala/util/parsing/combinator/RegexParsers$$anon$2
NameAndType	$outer:Lscala/util/parsing/combinator/RegexParsers;
Field	scala/util/parsing/combinator/RegexParsers$$anon$2.$outer:Lscala/util/parsing/combinator/RegexParsers;
Asciz	scala/util/parsing/combinator/RegexParsers;
class	scala/util/parsing/combinator/RegexParsers
Asciz	handleWhiteSpace;
Asciz	(Ljava/lang/CharSequence;I)I;
NameAndType	handleWhiteSpace:(Ljava/lang/CharSequence;I)I
InterfaceMethod	scala/util/parsing/combinator/RegexParsers.handleWhiteSpace:(Ljava/lang/CharSequence;I)I
NameAndType	r$1:Lscala/util/matching/Regex;
Field	scala/util/parsing/combinator/RegexParsers$$anon$2.r$1:Lscala/util/matching/Regex;
Asciz	java/lang/CharSequence;
class	java/lang/CharSequence
Asciz	length;
NameAndType	length:()I
InterfaceMethod	java/lang/CharSequence.length:()I
Asciz	subSequence;
Asciz	(II)Ljava/lang/CharSequence;;
NameAndType	subSequence:(II)Ljava/lang/CharSequence;
InterfaceMethod	java/lang/CharSequence.subSequence:(II)Ljava/lang/CharSequence;
Asciz	scala/util/matching/Regex;
class	scala/util/matching/Regex
Asciz	findPrefixMatchOf;
Asciz	(Ljava/lang/CharSequence;)Lscala/Option;;
NameAndType	findPrefixMatchOf:(Ljava/lang/CharSequence;)Lscala/Option;
Method	scala/util/matching/Regex.findPrefixMatchOf:(Ljava/lang/CharSequence;)Lscala/Option;
Asciz	scala/Some;
class	scala/Some
Asciz	x;
Asciz	Ljava/lang/Object;;
NameAndType	x:Ljava/lang/Object;
Field	scala/Some.x:Ljava/lang/Object;
Asciz	scala/util/matching/Regex$Match;
class	scala/util/matching/Regex$Match
Asciz	scala/util/parsing/combinator/Parsers$Success;
class	scala/util/parsing/combinator/Parsers$Success
Asciz	end;
NameAndType	end:()I
Method	scala/util/matching/Regex$Match.end:()I
Asciz	java/lang/Object;
class	java/lang/Object
Asciz	toString;
Asciz	()Ljava/lang/String;;
NameAndType	toString:()Ljava/lang/String;
Method	java/lang/Object.toString:()Ljava/lang/String;
Asciz	drop;
Asciz	(I)Lscala/util/parsing/input/Reader;;
NameAndType	drop:(I)Lscala/util/parsing/input/Reader;
Method	scala/util/parsing/input/Reader.drop:(I)Lscala/util/parsing/input/Reader;
Asciz	<init>;
Asciz	(Lscala/util/parsing/combinator/Parsers;Ljava/lang/Object;Lscala/util/parsing/input/Reader;)V;
NameAndType	"<init>":(Lscala/util/parsing/combinator/Parsers;Ljava/lang/Object;Lscala/util/parsing/input/Reader;)V
Method	scala/util/parsing/combinator/Parsers$Success."<init>":(Lscala/util/parsing/combinator/Parsers;Ljava/lang/Object;Lscala/util/parsing/input/Reader;)V
Asciz	scala/None$;
class	scala/None$
Asciz	MODULE$;
Asciz	Lscala/None$;;
NameAndType	MODULE$:Lscala/None$;
Field	scala/None$.MODULE$:Lscala/None$;
Asciz	equals;
Asciz	(Ljava/lang/Object;)Z;
NameAndType	equals:(Ljava/lang/Object;)Z
Method	java/lang/Object.equals:(Ljava/lang/Object;)Z
Asciz	scala/util/parsing/combinator/Parsers$Failure;
class	scala/util/parsing/combinator/Parsers$Failure
Asciz	scala/collection/mutable/StringBuilder;
class	scala/collection/mutable/StringBuilder
Asciz	()V;
NameAndType	"<init>":()V
Method	scala/collection/mutable/StringBuilder."<init>":()V
Asciz	string matching regex `;
String	string matching regex `
Asciz	append;
Asciz	(Ljava/lang/Object;)Lscala/collection/mutable/StringBuilder;;
NameAndType	append:(Ljava/lang/Object;)Lscala/collection/mutable/StringBuilder;
Method	scala/collection/mutable/StringBuilder.append:(Ljava/lang/Object;)Lscala/collection/mutable/StringBuilder;
Asciz	' expected but `;
String	' expected but `
Asciz	first;
Asciz	()Ljava/lang/Object;;
NameAndType	first:()Ljava/lang/Object;
Method	scala/util/parsing/input/Reader.first:()Ljava/lang/Object;
Asciz	' found;
String	' found
Method	scala/collection/mutable/StringBuilder.toString:()Ljava/lang/String;
Asciz	(Lscala/util/parsing/combinator/Parsers;Ljava/lang/String;Lscala/util/parsing/input/Reader;)V;
NameAndType	"<init>":(Lscala/util/parsing/combinator/Parsers;Ljava/lang/String;Lscala/util/parsing/input/Reader;)V
Method	scala/util/parsing/combinator/Parsers$Failure."<init>":(Lscala/util/parsing/combinator/Parsers;Ljava/lang/String;Lscala/util/parsing/input/Reader;)V
Asciz	scala/MatchError;
class	scala/MatchError
Asciz	scala/Option;
class	scala/Option
Method	scala/Option.toString:()Ljava/lang/String;
Asciz	(Ljava/lang/String;)V;
NameAndType	"<init>":(Ljava/lang/String;)V
Method	scala/MatchError."<init>":(Ljava/lang/String;)V
Asciz	this;
Asciz	Lscala/util/parsing/combinator/RegexParsers$$anon$2;;
Asciz	in;
Asciz	Lscala/util/parsing/input/Reader;;
Asciz	temp6;
Asciz	Lscala/Some;;
Asciz	Ljava/lang/CharSequence;;
Asciz	temp7;
Asciz	Lscala/util/matching/Regex$Match;;
Asciz	start;
Asciz	I;
Asciz	temp5;
Asciz	Lscala/Option;;
Asciz	LocalVariableTable;
Asciz	(Lscala/util/parsing/input/Reader<Ljava/lang/Character;>;)Lscala/util/parsing/combinator/Parsers$ParseResult<Ljava/lang/String;>;;
Asciz	Signature;
Asciz	(Ljava/lang/Object;)Ljava/lang/Object;;
NameAndType	apply:(Lscala/util/parsing/input/Reader;)Lscala/util/parsing/combinator/Parsers$ParseResult;
Method	scala/util/parsing/combinator/RegexParsers$$anon$2.apply:(Lscala/util/parsing/input/Reader;)Lscala/util/parsing/combinator/Parsers$ParseResult;
Asciz	v1;
Asciz	(Lscala/util/parsing/combinator/RegexParsers;Lscala/util/matching/Regex;)V;
Asciz	java/lang/NullPointerException;
class	java/lang/NullPointerException
Method	java/lang/NullPointerException."<init>":()V
Asciz	scala/util/parsing/combinator/Parsers$Parser;
class	scala/util/parsing/combinator/Parsers$Parser
Asciz	(Lscala/util/parsing/combinator/Parsers;)V;
NameAndType	"<init>":(Lscala/util/parsing/combinator/Parsers;)V
Method	scala/util/parsing/combinator/Parsers$Parser."<init>":(Lscala/util/parsing/combinator/Parsers;)V
Asciz	Lscala/util/parsing/combinator/Parsers$Parser<Ljava/lang/String;>;;
Asciz	Scala;
Asciz	InnerClasses;
Asciz	Match;
Asciz	scala/util/parsing/combinator/Parsers;
class	scala/util/parsing/combinator/Parsers
Asciz	Parser;
Asciz	Failure;
Asciz	Success;
Asciz	scala/util/parsing/combinator/Parsers$ParseResult;
class	scala/util/parsing/combinator/Parsers$ParseResult
Asciz	ParseResult;
Asciz	$anon$2;

{
public final scala.util.matching.Regex r$1;
  Signature: Lscala/util/matching/Regex;

public final scala.util.parsing.combinator.RegexParsers $outer;
  Signature: Lscala/util/parsing/combinator/RegexParsers;

public scala.util.parsing.combinator.Parsers$ParseResult apply(scala.util.parsing.input.Reader);
  Signature: (Lscala/util/parsing/input/Reader;)Lscala/util/parsing/combinator/Parsers$ParseResult;
  Code:
   Stack=7, Locals=8, Args_size=2
	aload_1
	invokevirtual	Method scala/util/parsing/input/Reader.source:()Ljava/lang/CharSequence;
	astore_3
	aload_1
	invokevirtual	Method scala/util/parsing/input/Reader.offset:()I
	istore	6
	aload_0
	getfield	Field $outer:Lscala/util/parsing/combinator/RegexParsers;
	aload_3
	iload	6
	invokeinterface	InterfaceMethod scala/util/parsing/combinator/RegexParsers.handleWhiteSpace:(Ljava/lang/CharSequence;I)I
	istore	5
	aload_0
	getfield	Field r$1:Lscala/util/matching/Regex;
	aload_3
	iload	5
	aload_3
	invokeinterface	InterfaceMethod java/lang/CharSequence.length:()I
	invokeinterface	InterfaceMethod java/lang/CharSequence.subSequence:(II)Ljava/lang/CharSequence;
	invokevirtual	Method scala/util/matching/Regex.findPrefixMatchOf:(Ljava/lang/CharSequence;)Lscala/Option;
	astore	7
	aload	7
	instanceof	class scala/Some
	ifeq	l1 // getstatic
	aload	7
	checkcast	class scala/Some
	astore_2
	aload_2
	getfield	Field scala/Some.x:Ljava/lang/Object;
	checkcast	class scala/util/matching/Regex$Match
	astore	4
	new	class scala/util/parsing/combinator/Parsers$Success
	dup
	aload_0
	getfield	Field $outer:Lscala/util/parsing/combinator/RegexParsers;
	aload_3
	iload	5
	iload	5
	aload	4
	invokevirtual	Method scala/util/matching/Regex$Match.end:()I
	iadd
	invokeinterface	InterfaceMethod java/lang/CharSequence.subSequence:(II)Ljava/lang/CharSequence;
	invokevirtual	Method java/lang/Object.toString:()Ljava/lang/String;
	aload_1
	iload	5
	aload	4
	invokevirtual	Method scala/util/matching/Regex$Match.end:()I
	iadd
	iload	6
	isub
	invokevirtual	Method scala/util/parsing/input/Reader.drop:(I)Lscala/util/parsing/input/Reader;
	invokespecial	Method scala/util/parsing/combinator/Parsers$Success."<init>":(Lscala/util/parsing/combinator/Parsers;Ljava/lang/Object;Lscala/util/parsing/input/Reader;)V
	goto	l2 // areturn
l1	getstatic	Field scala/None$.MODULE$:Lscala/None$;
	dup
	ifnonnull	l3 // aload
	pop
	aload	7
	ifnull	l4 // new
	goto	l5 // new
l3	aload	7
	invokevirtual	Method java/lang/Object.equals:(Ljava/lang/Object;)Z
	ifeq	l5 // new
l4	new	class scala/util/parsing/combinator/Parsers$Failure
	dup
	aload_0
	getfield	Field $outer:Lscala/util/parsing/combinator/RegexParsers;
	new	class scala/collection/mutable/StringBuilder
	dup
	invokespecial	Method scala/collection/mutable/StringBuilder."<init>":()V
	ldc	String string matching regex `
	invokevirtual	Method scala/collection/mutable/StringBuilder.append:(Ljava/lang/Object;)Lscala/collection/mutable/StringBuilder;
	aload_0
	getfield	Field r$1:Lscala/util/matching/Regex;
	invokevirtual	Method scala/collection/mutable/StringBuilder.append:(Ljava/lang/Object;)Lscala/collection/mutable/StringBuilder;
	ldc	String ' expected but `
	invokevirtual	Method scala/collection/mutable/StringBuilder.append:(Ljava/lang/Object;)Lscala/collection/mutable/StringBuilder;
	aload_1
	invokevirtual	Method scala/util/parsing/input/Reader.first:()Ljava/lang/Object;
	invokevirtual	Method scala/collection/mutable/StringBuilder.append:(Ljava/lang/Object;)Lscala/collection/mutable/StringBuilder;
	ldc	String ' found
	invokevirtual	Method scala/collection/mutable/StringBuilder.append:(Ljava/lang/Object;)Lscala/collection/mutable/StringBuilder;
	invokevirtual	Method scala/collection/mutable/StringBuilder.toString:()Ljava/lang/String;
	aload_1
	iload	5
	iload	6
	isub
	invokevirtual	Method scala/util/parsing/input/Reader.drop:(I)Lscala/util/parsing/input/Reader;
	invokespecial	Method scala/util/parsing/combinator/Parsers$Failure."<init>":(Lscala/util/parsing/combinator/Parsers;Ljava/lang/String;Lscala/util/parsing/input/Reader;)V
l2	areturn
l5	new	class scala/MatchError
	dup
	aload	7
	invokevirtual	Method scala/Option.toString:()Ljava/lang/String;
	invokespecial	Method scala/MatchError."<init>":(Ljava/lang/String;)V
	athrow
  Labels:
   	l1 = 119 // getstatic
   	l3 = 135 // aload
   	l4 = 143 // new
   	l2 = 202 // areturn
   	l5 = 203 // new
  LocalVariableTable: 
   Start  Length  Slot  Name   Signature
   0      216      0    this       Lscala/util/parsing/combinator/RegexParsers$$anon$2;
   0      216      1    in       Lscala/util/parsing/input/Reader;
   62      54      2    temp6       Lscala/Some;
   5      211      3    source       Ljava/lang/CharSequence;
   71      45      4    temp7       Lscala/util/matching/Regex$Match;
   25      191      5    start       I
   11      205      6    offset       I
   48      168      7    temp5       Lscala/Option;

  Signature: length = 0x2
   00 FFFFFF84 

public java.lang.Object apply(java.lang.Object);
  Signature: (Ljava/lang/Object;)Ljava/lang/Object;
  Code:
   Stack=2, Locals=2, Args_size=2
	aload_0
	aload_1
	checkcast	class scala/util/parsing/input/Reader
	invokevirtual	Method apply:(Lscala/util/parsing/input/Reader;)Lscala/util/parsing/combinator/Parsers$ParseResult;
	areturn
  Labels:
  LocalVariableTable: 
   Start  Length  Slot  Name   Signature
   0      9      0    this       Lscala/util/parsing/combinator/RegexParsers$$anon$2;
   0      9      1    v1       Ljava/lang/Object;


public scala.util.parsing.combinator.RegexParsers$$anon$2(scala.util.parsing.combinator.RegexParsers, scala.util.matching.Regex);
  Signature: (Lscala/util/parsing/combinator/RegexParsers;Lscala/util/matching/Regex;)V
  Code:
   Stack=2, Locals=3, Args_size=3
	aload_1
	ifnonnull	l1 // aload_0
	new	class java/lang/NullPointerException
	dup
	invokespecial	Method java/lang/NullPointerException."<init>":()V
	athrow
l1	aload_0
	aload_1
	putfield	Field $outer:Lscala/util/parsing/combinator/RegexParsers;
	aload_0
	aload_2
	putfield	Field r$1:Lscala/util/matching/Regex;
	aload_0
	aload_1
	invokespecial	Method scala/util/parsing/combinator/Parsers$Parser."<init>":(Lscala/util/parsing/combinator/Parsers;)V
	return
  Labels:
   	l1 = 12 // aload_0
  LocalVariableTable: 
   Start  Length  Slot  Name   Signature
   0      28      0    this       Lscala/util/parsing/combinator/RegexParsers$$anon$2;
   0      28      1    $outer       Lscala/util/parsing/combinator/RegexParsers;


}

