Compiled from "RegexParsers.scala"
public final class scala.util.parsing.combinator.RegexParsers$$anon$2 extends scala.util.parsing.combinator.Parsers$Parser
  SourceFile: "RegexParsers.scala"
  Signature: length = 0x2
   00 FFFFFF93 
  Scala: length = 0x
   
  InnerClass: 
   public #150= #74 of #63; //Match=class scala/util/matching/Regex$Match of class scala/util/matching/Regex
   public abstract #153= #23 of #152; //Parser=class scala/util/parsing/combinator/Parsers$Parser of class scala/util/parsing/combinator/Parsers
   public #154= #112 of #152; //Failure=class scala/util/parsing/combinator/Parsers$Failure of class scala/util/parsing/combinator/Parsers
   public #155= #76 of #152; //Success=class scala/util/parsing/combinator/Parsers$Success of class scala/util/parsing/combinator/Parsers
   public abstract #158= #157 of #152; //ParseResult=class scala/util/parsing/combinator/Parsers$ParseResult of class scala/util/parsing/combinator/Parsers
   public final #159= #17 of #48; //$anon$2=class scala/util/parsing/combinator/RegexParsers$$anon$2 of class scala/util/parsing/combinator/RegexParsers
  minor version: 0
  major version: 49
  Constant pool:
const #1 = Asciz	SourceFile;
const #2 = Asciz	RegexParsers.scala;
const #3 = Asciz	r$1;
const #4 = Asciz	Lscala/util/matching/Regex;;
const #5 = Asciz	$outer;
const #6 = Asciz	Lscala/util/parsing/combinator/RegexParsers;;
const #7 = Asciz	<init>;
const #8 = Asciz	(Lscala/util/parsing/combinator/RegexParsers;Lscala/util/matching/Regex;)V;
const #9 = Asciz	Code;
const #10 = Asciz	LineNumberTable;
const #11 = Asciz	java/lang/NullPointerException;
const #12 = class	#11;	//  java/lang/NullPointerException
const #13 = Asciz	()V;
const #14 = NameAndType	#7:#13;//  "<init>":()V
const #15 = Method	#12.#14;	//  java/lang/NullPointerException."<init>":()V
const #16 = Asciz	scala/util/parsing/combinator/RegexParsers$$anon$2;
const #17 = class	#16;	//  scala/util/parsing/combinator/RegexParsers$$anon$2
const #18 = NameAndType	#5:#6;//  $outer:Lscala/util/parsing/combinator/RegexParsers;
const #19 = Field	#17.#18;	//  scala/util/parsing/combinator/RegexParsers$$anon$2.$outer:Lscala/util/parsing/combinator/RegexParsers;
const #20 = NameAndType	#3:#4;//  r$1:Lscala/util/matching/Regex;
const #21 = Field	#17.#20;	//  scala/util/parsing/combinator/RegexParsers$$anon$2.r$1:Lscala/util/matching/Regex;
const #22 = Asciz	scala/util/parsing/combinator/Parsers$Parser;
const #23 = class	#22;	//  scala/util/parsing/combinator/Parsers$Parser
const #24 = Asciz	(Lscala/util/parsing/combinator/Parsers;)V;
const #25 = NameAndType	#7:#24;//  "<init>":(Lscala/util/parsing/combinator/Parsers;)V
const #26 = Method	#23.#25;	//  scala/util/parsing/combinator/Parsers$Parser."<init>":(Lscala/util/parsing/combinator/Parsers;)V
const #27 = Asciz	this;
const #28 = Asciz	Lscala/util/parsing/combinator/RegexParsers$$anon$2;;
const #29 = Asciz	LocalVariableTable;
const #30 = Asciz	apply;
const #31 = Asciz	(Ljava/lang/Object;)Ljava/lang/Object;;
const #32 = Asciz	scala/util/parsing/input/Reader;
const #33 = class	#32;	//  scala/util/parsing/input/Reader
const #34 = Asciz	(Lscala/util/parsing/input/Reader;)Lscala/util/parsing/combinator/Parsers$ParseResult;;
const #35 = NameAndType	#30:#34;//  apply:(Lscala/util/parsing/input/Reader;)Lscala/util/parsing/combinator/Parsers$ParseResult;
const #36 = Method	#17.#35;	//  scala/util/parsing/combinator/RegexParsers$$anon$2.apply:(Lscala/util/parsing/input/Reader;)Lscala/util/parsing/combinator/Parsers$ParseResult;
const #37 = Asciz	v1;
const #38 = Asciz	Ljava/lang/Object;;
const #39 = Asciz	source;
const #40 = Asciz	()Ljava/lang/CharSequence;;
const #41 = NameAndType	#39:#40;//  source:()Ljava/lang/CharSequence;
const #42 = Method	#33.#41;	//  scala/util/parsing/input/Reader.source:()Ljava/lang/CharSequence;
const #43 = Asciz	offset;
const #44 = Asciz	()I;
const #45 = NameAndType	#43:#44;//  offset:()I
const #46 = Method	#33.#45;	//  scala/util/parsing/input/Reader.offset:()I
const #47 = Asciz	scala/util/parsing/combinator/RegexParsers;
const #48 = class	#47;	//  scala/util/parsing/combinator/RegexParsers
const #49 = Asciz	handleWhiteSpace;
const #50 = Asciz	(Ljava/lang/CharSequence;I)I;
const #51 = NameAndType	#49:#50;//  handleWhiteSpace:(Ljava/lang/CharSequence;I)I
const #52 = InterfaceMethod	#48.#51;	//  scala/util/parsing/combinator/RegexParsers.handleWhiteSpace:(Ljava/lang/CharSequence;I)I
const #53 = Asciz	java/lang/CharSequence;
const #54 = class	#53;	//  java/lang/CharSequence
const #55 = Asciz	length;
const #56 = NameAndType	#55:#44;//  length:()I
const #57 = InterfaceMethod	#54.#56;	//  java/lang/CharSequence.length:()I
const #58 = Asciz	subSequence;
const #59 = Asciz	(II)Ljava/lang/CharSequence;;
const #60 = NameAndType	#58:#59;//  subSequence:(II)Ljava/lang/CharSequence;
const #61 = InterfaceMethod	#54.#60;	//  java/lang/CharSequence.subSequence:(II)Ljava/lang/CharSequence;
const #62 = Asciz	scala/util/matching/Regex;
const #63 = class	#62;	//  scala/util/matching/Regex
const #64 = Asciz	findPrefixMatchOf;
const #65 = Asciz	(Ljava/lang/CharSequence;)Lscala/Option;;
const #66 = NameAndType	#64:#65;//  findPrefixMatchOf:(Ljava/lang/CharSequence;)Lscala/Option;
const #67 = Method	#63.#66;	//  scala/util/matching/Regex.findPrefixMatchOf:(Ljava/lang/CharSequence;)Lscala/Option;
const #68 = Asciz	scala/Some;
const #69 = class	#68;	//  scala/Some
const #70 = Asciz	x;
const #71 = NameAndType	#70:#38;//  x:Ljava/lang/Object;
const #72 = Field	#69.#71;	//  scala/Some.x:Ljava/lang/Object;
const #73 = Asciz	scala/util/matching/Regex$Match;
const #74 = class	#73;	//  scala/util/matching/Regex$Match
const #75 = Asciz	scala/util/parsing/combinator/Parsers$Success;
const #76 = class	#75;	//  scala/util/parsing/combinator/Parsers$Success
const #77 = Asciz	end;
const #78 = NameAndType	#77:#44;//  end:()I
const #79 = Method	#74.#78;	//  scala/util/matching/Regex$Match.end:()I
const #80 = Asciz	java/lang/Object;
const #81 = class	#80;	//  java/lang/Object
const #82 = Asciz	toString;
const #83 = Asciz	()Ljava/lang/String;;
const #84 = NameAndType	#82:#83;//  toString:()Ljava/lang/String;
const #85 = Method	#81.#84;	//  java/lang/Object.toString:()Ljava/lang/String;
const #86 = Asciz	drop;
const #87 = Asciz	(I)Lscala/util/parsing/input/Reader;;
const #88 = NameAndType	#86:#87;//  drop:(I)Lscala/util/parsing/input/Reader;
const #89 = Method	#33.#88;	//  scala/util/parsing/input/Reader.drop:(I)Lscala/util/parsing/input/Reader;
const #90 = Asciz	(Lscala/util/parsing/combinator/Parsers;Ljava/lang/Object;Lscala/util/parsing/input/Reader;)V;
const #91 = NameAndType	#7:#90;//  "<init>":(Lscala/util/parsing/combinator/Parsers;Ljava/lang/Object;Lscala/util/parsing/input/Reader;)V
const #92 = Method	#76.#91;	//  scala/util/parsing/combinator/Parsers$Success."<init>":(Lscala/util/parsing/combinator/Parsers;Ljava/lang/Object;Lscala/util/parsing/input/Reader;)V
const #93 = Asciz	scala/MatchError;
const #94 = class	#93;	//  scala/MatchError
const #95 = Asciz	scala/Option;
const #96 = class	#95;	//  scala/Option
const #97 = Method	#96.#84;	//  scala/Option.toString:()Ljava/lang/String;
const #98 = Asciz	(Ljava/lang/String;)V;
const #99 = NameAndType	#7:#98;//  "<init>":(Ljava/lang/String;)V
const #100 = Method	#94.#99;	//  scala/MatchError."<init>":(Ljava/lang/String;)V
const #101 = Asciz	scala/None$;
const #102 = class	#101;	//  scala/None$
const #103 = Asciz	MODULE$;
const #104 = Asciz	Lscala/None$;;
const #105 = NameAndType	#103:#104;//  MODULE$:Lscala/None$;
const #106 = Field	#102.#105;	//  scala/None$.MODULE$:Lscala/None$;
const #107 = Asciz	equals;
const #108 = Asciz	(Ljava/lang/Object;)Z;
const #109 = NameAndType	#107:#108;//  equals:(Ljava/lang/Object;)Z
const #110 = Method	#81.#109;	//  java/lang/Object.equals:(Ljava/lang/Object;)Z
const #111 = Asciz	scala/util/parsing/combinator/Parsers$Failure;
const #112 = class	#111;	//  scala/util/parsing/combinator/Parsers$Failure
const #113 = Asciz	scala/collection/mutable/StringBuilder;
const #114 = class	#113;	//  scala/collection/mutable/StringBuilder
const #115 = Method	#114.#14;	//  scala/collection/mutable/StringBuilder."<init>":()V
const #116 = Asciz	string matching regex `;
const #117 = String	#116;	//  string matching regex `
const #118 = Asciz	append;
const #119 = Asciz	(Ljava/lang/Object;)Lscala/collection/mutable/StringBuilder;;
const #120 = NameAndType	#118:#119;//  append:(Ljava/lang/Object;)Lscala/collection/mutable/StringBuilder;
const #121 = Method	#114.#120;	//  scala/collection/mutable/StringBuilder.append:(Ljava/lang/Object;)Lscala/collection/mutable/StringBuilder;
const #122 = Asciz	' expected but `;
const #123 = String	#122;	//  ' expected but `
const #124 = Asciz	first;
const #125 = Asciz	()Ljava/lang/Object;;
const #126 = NameAndType	#124:#125;//  first:()Ljava/lang/Object;
const #127 = Method	#33.#126;	//  scala/util/parsing/input/Reader.first:()Ljava/lang/Object;
const #128 = Asciz	' found;
const #129 = String	#128;	//  ' found
const #130 = Method	#114.#84;	//  scala/collection/mutable/StringBuilder.toString:()Ljava/lang/String;
const #131 = Asciz	(Lscala/util/parsing/combinator/Parsers;Ljava/lang/String;Lscala/util/parsing/input/Reader;)V;
const #132 = NameAndType	#7:#131;//  "<init>":(Lscala/util/parsing/combinator/Parsers;Ljava/lang/String;Lscala/util/parsing/input/Reader;)V
const #133 = Method	#112.#132;	//  scala/util/parsing/combinator/Parsers$Failure."<init>":(Lscala/util/parsing/combinator/Parsers;Ljava/lang/String;Lscala/util/parsing/input/Reader;)V
const #134 = Asciz	in;
const #135 = Asciz	Lscala/util/parsing/input/Reader;;
const #136 = Asciz	temp6;
const #137 = Asciz	Lscala/Some;;
const #138 = Asciz	Ljava/lang/CharSequence;;
const #139 = Asciz	temp7;
const #140 = Asciz	Lscala/util/matching/Regex$Match;;
const #141 = Asciz	start;
const #142 = Asciz	I;
const #143 = Asciz	temp5;
const #144 = Asciz	Lscala/Option;;
const #145 = Asciz	(Lscala/util/parsing/input/Reader<Ljava/lang/Character;>;)Lscala/util/parsing/combinator/Parsers$ParseResult<Ljava/lang/String;>;;
const #146 = Asciz	Signature;
const #147 = Asciz	Lscala/util/parsing/combinator/Parsers$Parser<Ljava/lang/String;>;;
const #148 = Asciz	Scala;
const #149 = Asciz	InnerClasses;
const #150 = Asciz	Match;
const #151 = Asciz	scala/util/parsing/combinator/Parsers;
const #152 = class	#151;	//  scala/util/parsing/combinator/Parsers
const #153 = Asciz	Parser;
const #154 = Asciz	Failure;
const #155 = Asciz	Success;
const #156 = Asciz	scala/util/parsing/combinator/Parsers$ParseResult;
const #157 = class	#156;	//  scala/util/parsing/combinator/Parsers$ParseResult
const #158 = Asciz	ParseResult;
const #159 = Asciz	$anon$2;

{
public scala.util.parsing.combinator.RegexParsers$$anon$2(scala.util.parsing.combinator.RegexParsers, scala.util.matching.Regex);
  Code:
   Stack=2, Locals=3, Args_size=3
   0:	aload_1
   1:	ifnonnull	12
   4:	new	#12; //class java/lang/NullPointerException
   7:	dup
   8:	invokespecial	#15; //Method java/lang/NullPointerException."<init>":()V
   11:	athrow
   12:	aload_0
   13:	aload_1
   14:	putfield	#19; //Field $outer:Lscala/util/parsing/combinator/RegexParsers;
   17:	aload_0
   18:	aload_2
   19:	putfield	#21; //Field r$1:Lscala/util/matching/Regex;
   22:	aload_0
   23:	aload_1
   24:	invokespecial	#26; //Method scala/util/parsing/combinator/Parsers$Parser."<init>":(Lscala/util/parsing/combinator/Parsers;)V
   27:	return
  LineNumberTable: 
   line 55: 0

  LocalVariableTable: 
   Start  Length  Slot  Name   Signature
   0      28      0    this       Lscala/util/parsing/combinator/RegexParsers$$anon$2;
   0      28      1    $outer       Lscala/util/parsing/combinator/RegexParsers;


public java.lang.Object apply(java.lang.Object);
  Code:
   Stack=2, Locals=2, Args_size=2
   0:	aload_0
   1:	aload_1
   2:	checkcast	#33; //class scala/util/parsing/input/Reader
   5:	invokevirtual	#36; //Method apply:(Lscala/util/parsing/input/Reader;)Lscala/util/parsing/combinator/Parsers$ParseResult;
   8:	areturn
  LineNumberTable: 
   line 55: 0

  LocalVariableTable: 
   Start  Length  Slot  Name   Signature
   0      9      0    this       Lscala/util/parsing/combinator/RegexParsers$$anon$2;
   0      9      1    v1       Ljava/lang/Object;


public scala.util.parsing.combinator.Parsers$ParseResult apply(scala.util.parsing.input.Reader);
  Code:
   Stack=7, Locals=8, Args_size=2
   0:	aload_1
   1:	invokevirtual	#42; //Method scala/util/parsing/input/Reader.source:()Ljava/lang/CharSequence;
   4:	astore_3
   5:	aload_1
   6:	invokevirtual	#46; //Method scala/util/parsing/input/Reader.offset:()I
   9:	istore	6
   11:	aload_0
   12:	getfield	#19; //Field $outer:Lscala/util/parsing/combinator/RegexParsers;
   15:	aload_3
   16:	iload	6
   18:	invokeinterface	#52,  3; //InterfaceMethod scala/util/parsing/combinator/RegexParsers.handleWhiteSpace:(Ljava/lang/CharSequence;I)I
   23:	istore	5
   25:	aload_0
   26:	getfield	#21; //Field r$1:Lscala/util/matching/Regex;
   29:	aload_3
   30:	iload	5
   32:	aload_3
   33:	invokeinterface	#57,  1; //InterfaceMethod java/lang/CharSequence.length:()I
   38:	invokeinterface	#61,  3; //InterfaceMethod java/lang/CharSequence.subSequence:(II)Ljava/lang/CharSequence;
   43:	invokevirtual	#67; //Method scala/util/matching/Regex.findPrefixMatchOf:(Ljava/lang/CharSequence;)Lscala/Option;
   46:	astore	7
   48:	aload	7
   50:	instanceof	#69; //class scala/Some
   53:	ifeq	136
   56:	aload	7
   58:	checkcast	#69; //class scala/Some
   61:	astore_2
   62:	aload_2
   63:	getfield	#72; //Field scala/Some.x:Ljava/lang/Object;
   66:	checkcast	#74; //class scala/util/matching/Regex$Match
   69:	astore	4
   71:	iconst_1
   72:	ifeq	123
   75:	new	#76; //class scala/util/parsing/combinator/Parsers$Success
   78:	dup
   79:	aload_0
   80:	getfield	#19; //Field $outer:Lscala/util/parsing/combinator/RegexParsers;
   83:	aload_3
   84:	iload	5
   86:	iload	5
   88:	aload	4
   90:	invokevirtual	#79; //Method scala/util/matching/Regex$Match.end:()I
   93:	iadd
   94:	invokeinterface	#61,  3; //InterfaceMethod java/lang/CharSequence.subSequence:(II)Ljava/lang/CharSequence;
   99:	invokevirtual	#85; //Method java/lang/Object.toString:()Ljava/lang/String;
   102:	aload_1
   103:	iload	5
   105:	aload	4
   107:	invokevirtual	#79; //Method scala/util/matching/Regex$Match.end:()I
   110:	iadd
   111:	iload	6
   113:	isub
   114:	invokevirtual	#89; //Method scala/util/parsing/input/Reader.drop:(I)Lscala/util/parsing/input/Reader;
   117:	invokespecial	#92; //Method scala/util/parsing/combinator/Parsers$Success."<init>":(Lscala/util/parsing/combinator/Parsers;Ljava/lang/Object;Lscala/util/parsing/input/Reader;)V
   120:	goto	223
   123:	new	#94; //class scala/MatchError
   126:	dup
   127:	aload	7
   129:	invokevirtual	#97; //Method scala/Option.toString:()Ljava/lang/String;
   132:	invokespecial	#100; //Method scala/MatchError."<init>":(Ljava/lang/String;)V
   135:	athrow
   136:	getstatic	#106; //Field scala/None$.MODULE$:Lscala/None$;
   139:	dup
   140:	ifnonnull	152
   143:	pop
   144:	aload	7
   146:	ifnull	160
   149:	goto	237
   152:	aload	7
   154:	invokevirtual	#110; //Method java/lang/Object.equals:(Ljava/lang/Object;)Z
   157:	ifeq	237
   160:	iconst_1
   161:	ifeq	224
   164:	new	#112; //class scala/util/parsing/combinator/Parsers$Failure
   167:	dup
   168:	aload_0
   169:	getfield	#19; //Field $outer:Lscala/util/parsing/combinator/RegexParsers;
   172:	new	#114; //class scala/collection/mutable/StringBuilder
   175:	dup
   176:	invokespecial	#115; //Method scala/collection/mutable/StringBuilder."<init>":()V
   179:	ldc	#117; //String string matching regex `
   181:	invokevirtual	#121; //Method scala/collection/mutable/StringBuilder.append:(Ljava/lang/Object;)Lscala/collection/mutable/StringBuilder;
   184:	aload_0
   185:	getfield	#21; //Field r$1:Lscala/util/matching/Regex;
   188:	invokevirtual	#121; //Method scala/collection/mutable/StringBuilder.append:(Ljava/lang/Object;)Lscala/collection/mutable/StringBuilder;
   191:	ldc	#123; //String ' expected but `
   193:	invokevirtual	#121; //Method scala/collection/mutable/StringBuilder.append:(Ljava/lang/Object;)Lscala/collection/mutable/StringBuilder;
   196:	aload_1
   197:	invokevirtual	#127; //Method scala/util/parsing/input/Reader.first:()Ljava/lang/Object;
   200:	invokevirtual	#121; //Method scala/collection/mutable/StringBuilder.append:(Ljava/lang/Object;)Lscala/collection/mutable/StringBuilder;
   203:	ldc	#129; //String ' found
   205:	invokevirtual	#121; //Method scala/collection/mutable/StringBuilder.append:(Ljava/lang/Object;)Lscala/collection/mutable/StringBuilder;
   208:	invokevirtual	#130; //Method scala/collection/mutable/StringBuilder.toString:()Ljava/lang/String;
   211:	aload_1
   212:	iload	5
   214:	iload	6
   216:	isub
   217:	invokevirtual	#89; //Method scala/util/parsing/input/Reader.drop:(I)Lscala/util/parsing/input/Reader;
   220:	invokespecial	#133; //Method scala/util/parsing/combinator/Parsers$Failure."<init>":(Lscala/util/parsing/combinator/Parsers;Ljava/lang/String;Lscala/util/parsing/input/Reader;)V
   223:	areturn
   224:	new	#94; //class scala/MatchError
   227:	dup
   228:	aload	7
   230:	invokevirtual	#97; //Method scala/Option.toString:()Ljava/lang/String;
   233:	invokespecial	#100; //Method scala/MatchError."<init>":(Ljava/lang/String;)V
   236:	athrow
   237:	new	#94; //class scala/MatchError
   240:	dup
   241:	aload	7
   243:	invokevirtual	#97; //Method scala/Option.toString:()Ljava/lang/String;
   246:	invokespecial	#100; //Method scala/MatchError."<init>":(Ljava/lang/String;)V
   249:	athrow
  LineNumberTable: 
   line 57: 0
   line 58: 5
   line 59: 11
   line 60: 25
   line 56: 56
   line 21: 71
   line 62: 75
   line 63: 102
   line 62: 117
   line 60: 123
   line 21: 160
   line 65: 164
   line 56: 223
   line 60: 224

  LocalVariableTable: 
   Start  Length  Slot  Name   Signature
   0      250      0    this       Lscala/util/parsing/combinator/RegexParsers$$anon$2;
   0      250      1    in       Lscala/util/parsing/input/Reader;
   62      74      2    temp6       Lscala/Some;
   5      245      3    source       Ljava/lang/CharSequence;
   71      65      4    temp7       Lscala/util/matching/Regex$Match;
   25      225      5    start       I
   11      239      6    offset       I
   48      202      7    temp5       Lscala/Option;

  Signature: length = 0x2
   00 FFFFFF91 

}

