Compiled from "JSON.scala"
public final class scala.util.parsing.json.JSON$$anonfun$resolveType$2 extends java.lang.Object implements scala.Function1,scala.ScalaObject,java.io.Serializable
  SourceFile: "JSON.scala"
  Scala: length = 0x
   
  InnerClass: 
   public final $anonfun$resolveType$2=class scala/util/parsing/json/JSON$$anonfun$resolveType$2 of class scala/util/parsing/json/JSON
  minor version: 0
  major version: 49
  Constant pool:
Asciz	SourceFile;
Asciz	JSON.scala;
Asciz	<clinit>;
Asciz	()V;
Asciz	Code;
Asciz	serialVersionUID;
Asciz	J;
Asciz	scala/util/parsing/json/JSON$$anonfun$resolveType$2;
class	scala/util/parsing/json/JSON$$anonfun$resolveType$2
NameAndType	serialVersionUID:J
Field	scala/util/parsing/json/JSON$$anonfun$resolveType$2.serialVersionUID:J
Asciz	<init>;
Asciz	LineNumberTable;
Asciz	java/lang/Object;
class	java/lang/Object
NameAndType	"<init>":()V
Method	java/lang/Object."<init>":()V
Asciz	scala/Function1$class;
class	scala/Function1$class
Asciz	$init$;
Asciz	(Lscala/Function1;)V;
NameAndType	$init$:(Lscala/Function1;)V
Method	scala/Function1$class.$init$:(Lscala/Function1;)V
Asciz	apply;
Asciz	(Ljava/lang/Object;)Ljava/lang/Object;;
Asciz	scala/collection/immutable/List;
class	scala/collection/immutable/List
Asciz	scala/util/parsing/json/JSON$;
class	scala/util/parsing/json/JSON$
Asciz	MODULE$;
Asciz	Lscala/util/parsing/json/JSON$;;
NameAndType	MODULE$:Lscala/util/parsing/json/JSON$;
Field	scala/util/parsing/json/JSON$.MODULE$:Lscala/util/parsing/json/JSON$;
Asciz	resolveType;
Asciz	(Lscala/collection/immutable/List;)Ljava/lang/Object;;
NameAndType	resolveType:(Lscala/collection/immutable/List;)Ljava/lang/Object;
Method	scala/util/parsing/json/JSON$.resolveType:(Lscala/collection/immutable/List;)Ljava/lang/Object;
Asciz	scala/MatchError;
class	scala/MatchError
Asciz	toString;
Asciz	()Ljava/lang/String;;
NameAndType	toString:()Ljava/lang/String;
Method	java/lang/Object.toString:()Ljava/lang/String;
Asciz	(Ljava/lang/String;)V;
NameAndType	"<init>":(Ljava/lang/String;)V
Method	scala/MatchError."<init>":(Ljava/lang/String;)V
Asciz	this;
Asciz	Lscala/util/parsing/json/JSON$$anonfun$resolveType$2;;
Asciz	temp16;
Asciz	Lscala/collection/immutable/List;;
Asciz	LocalVariableTable;
Asciz	Signature;
Asciz	andThen;
Asciz	(Lscala/Function1;)Lscala/Function1;;
Asciz	(Lscala/Function1;Lscala/Function1;)Lscala/Function1;;
NameAndType	andThen:(Lscala/Function1;Lscala/Function1;)Lscala/Function1;
Method	scala/Function1$class.andThen:(Lscala/Function1;Lscala/Function1;)Lscala/Function1;
Asciz	g;
Asciz	Lscala/Function1;;
Asciz	compose;
NameAndType	compose:(Lscala/Function1;Lscala/Function1;)Lscala/Function1;
Method	scala/Function1$class.compose:(Lscala/Function1;Lscala/Function1;)Lscala/Function1;
Asciz	(Lscala/Function1;)Ljava/lang/String;;
NameAndType	toString:(Lscala/Function1;)Ljava/lang/String;
Method	scala/Function1$class.toString:(Lscala/Function1;)Ljava/lang/String;
Asciz	Scala;
Asciz	InnerClasses;
Asciz	scala/util/parsing/json/JSON;
class	scala/util/parsing/json/JSON
Asciz	$anonfun$resolveType$2;
Asciz	scala/Function1;
class	scala/Function1
Asciz	scala/ScalaObject;
class	scala/ScalaObject
Asciz	java/io/Serializable;
class	java/io/Serializable

{
public static final long serialVersionUID;
  Signature: J

public static {};
  Signature: ()V
  Code:
   Stack=2, Locals=0, Args_size=0
	lconst_0
	putstatic	Field serialVersionUID:J
	return
  Labels:

public scala.util.parsing.json.JSON$$anonfun$resolveType$2();
  Signature: ()V
  Code:
   Stack=1, Locals=1, Args_size=1
	aload_0
	invokespecial	Method java/lang/Object."<init>":()V
	aload_0
	invokestatic	Method scala/Function1$class.$init$:(Lscala/Function1;)V
	return
  Labels:

public final java.lang.Object apply(java.lang.Object);
  Signature: (Ljava/lang/Object;)Ljava/lang/Object;
  Code:
   Stack=3, Locals=3, Args_size=2
	aload_1
	instanceof	class scala/collection/immutable/List
	ifeq	l1 // iconst_1
	aload_1
	checkcast	class scala/collection/immutable/List
	astore_2
	iconst_1
	ifeq	l2 // new
	getstatic	Field scala/util/parsing/json/JSON$.MODULE$:Lscala/util/parsing/json/JSON$;
	aload_2
	invokevirtual	Method scala/util/parsing/json/JSON$.resolveType:(Lscala/collection/immutable/List;)Ljava/lang/Object;
	goto	l3 // areturn
l2	new	class scala/MatchError
	dup
	aload_1
	invokevirtual	Method java/lang/Object.toString:()Ljava/lang/String;
	invokespecial	Method scala/MatchError."<init>":(Ljava/lang/String;)V
	athrow
l1	iconst_1
	ifeq	l4 // new
	aload_1
l3	areturn
l4	new	class scala/MatchError
	dup
	aload_1
	invokevirtual	Method java/lang/Object.toString:()Ljava/lang/String;
	invokespecial	Method scala/MatchError."<init>":(Ljava/lang/String;)V
	athrow
  Labels:
   	l2 = 26 // new
   	l1 = 38 // iconst_1
   	l3 = 43 // areturn
   	l4 = 44 // new
  LocalVariableTable: 
   Start  Length  Slot  Name   Signature
   0      56      0    this       Lscala/util/parsing/json/JSON$$anonfun$resolveType$2;
   12      26      2    temp16       Lscala/collection/immutable/List;

  Signature: length = 0x2
   00 19 

public scala.Function1 andThen(scala.Function1);
  Signature: (Lscala/Function1;)Lscala/Function1;
  Code:
   Stack=2, Locals=2, Args_size=2
	aload_0
	aload_1
	invokestatic	Method scala/Function1$class.andThen:(Lscala/Function1;Lscala/Function1;)Lscala/Function1;
	areturn
  Labels:
  LocalVariableTable: 
   Start  Length  Slot  Name   Signature
   0      6      0    this       Lscala/util/parsing/json/JSON$$anonfun$resolveType$2;
   0      6      1    g       Lscala/Function1;


public scala.Function1 compose(scala.Function1);
  Signature: (Lscala/Function1;)Lscala/Function1;
  Code:
   Stack=2, Locals=2, Args_size=2
	aload_0
	aload_1
	invokestatic	Method scala/Function1$class.compose:(Lscala/Function1;Lscala/Function1;)Lscala/Function1;
	areturn
  Labels:
  LocalVariableTable: 
   Start  Length  Slot  Name   Signature
   0      6      0    this       Lscala/util/parsing/json/JSON$$anonfun$resolveType$2;
   0      6      1    g       Lscala/Function1;


public java.lang.String toString();
  Signature: ()Ljava/lang/String;
  Code:
   Stack=1, Locals=1, Args_size=1
	aload_0
	invokestatic	Method scala/Function1$class.toString:(Lscala/Function1;)Ljava/lang/String;
	areturn
  Labels:

}

