Compiled from "JSON.scala"
public final class scala.util.parsing.json.JSON extends java.lang.Object
  SourceFile: "JSON.scala"
  ScalaSig: length = 0x261
   05 00 60 07 05 01 02 FFFFFF88 02 0B 01 04 4A 53 4F 4E
   0A 02 03 04 01 04 6A 73 6F 6E 0A 02 05 06 01 07
   70 61 72 73 69 6E 67 0A 02 07 08 01 04 75 74 69
   6C 0A 01 09 01 05 73 63 61 6C 61 03 00 10 02 0C
   0D 0D 01 02 06 08 0E 02 FFFFFF84 FFFFFF80 FFFFFF80 FFFFFF88 02 0F 02 04
   4A 53 4F 4E 13 03 0D 10 13 10 02 0C 11 09 02 12
   02 02 06 50 61 72 73 65 72 10 02 14 15 0D 01 08
   09 02 16 08 02 0B 53 63 61 6C 61 4F 62 6A 65 63
   74 08 05 18 0D FFFFFF84 00 19 01 06 3C 69 6E 69 74 3E
   14 01 0B 08 05 1B 0D FFFFFF84 00 1C 01 05 70 61 72 73
   65 14 02 1D 2F 10 03 14 1E 20 09 02 1F 08 02 06
   4F 70 74 69 6F 6E 10 03 21 29 2C 0E 02 22 27 0E
   02 23 26 0D 01 24 0A 02 25 0A 01 06 3C 72 6F 6F
   74 3E 09 01 09 09 02 28 08 01 07 70 61 63 6B 61
   67 65 09 02 2A 2B 02 04 4C 69 73 74 0A 02 28 08
   10 02 14 2D 09 02 2E 08 02 03 41 6E 79 08 05 30
   1A FFFFFFC0 00 31 01 05 69 6E 70 75 74 10 02 32 35 0E
   02 14 33 09 02 34 08 01 06 50 72 65 64 65 66 09
   02 36 37 02 06 53 74 72 69 6E 67 0A 02 34 08 08
   05 39 0D FFFFFF84 00 3A 01 09 70 61 72 73 65 46 75 6C
   6C 14 02 3B 3C 10 03 14 1E 2C 08 05 30 38 FFFFFFC0 00
   31 08 05 3E 0D FFFFFF84 00 3F 01 0B 72 65 73 6F 6C 76
   65 54 79 70 65 14 02 2C 40 08 05 30 3D FFFFFFC0 00 41
   30 02 42 45 10 03 21 29 43 10 02 44 45 0C 00 04
   08 46 00 FFFFFF84 FFFFFF80 FFFFFF80 FFFFFF82 00 47 02 03 5F 24 31 11 02
   48 2C 10 02 14 49 09 02 4A 08 02 07 4E 6F 74 68
   69 6E 67 08 05 4C 0D FFFFFF84 00 4D 01 16 67 6C 6F 62
   61 6C 4E 75 6D 62 65 72 50 61 72 73 65 72 5F 24
   65 71 14 02 4E 51 10 02 14 4F 09 02 50 08 02 04
   55 6E 69 74 08 05 52 4B FFFFFFC0 00 53 01 01 66 10 02
   54 55 0D 01 0D 09 02 56 11 02 0D 4E 75 6D 65 72
   69 63 50 61 72 73 65 72 08 05 58 0D FFFFFF84 00 59 01
   12 67 6C 6F 62 61 6C 4E 75 6D 62 65 72 50 61 72
   73 65 72 15 01 53 08 05 5B 0D FFFFFF84 00 5C 01 19 70
   65 72 54 68 72 65 61 64 4E 75 6D 62 65 72 50 61
   72 73 65 72 5F 24 65 71 14 02 4E 5D 08 05 52 5A
   FFFFFFC0 00 53 08 05 5F 0D FFFFFF84 00 59 01 15 70 65 72 54
   68 72 65 61 64 4E 75 6D 62 65 72 50 61 72 73 65
   72 
  InnerClass: 
   public abstract #137= #221 of #223; //Parser=class scala/util/parsing/combinator/Parsers$Parser of class scala/util/parsing/combinator/Parsers
   public abstract #226= #225 of #223; //NoSuccess=class scala/util/parsing/combinator/Parsers$NoSuccess of class scala/util/parsing/combinator/Parsers
   public final #231= #228 of #230; //$anonfun$resolveType$1=class scala/util/parsing/json/JSON$$anonfun$resolveType$1 of class scala/util/parsing/json/JSON
  minor version: 0
  major version: 49
  Constant pool:
const #1 = Asciz	SourceFile;
const #2 = Asciz	JSON.scala;
const #3 = Asciz	perThreadNumberParser;
const #4 = Asciz	()Lscala/Function1;;
const #5 = Asciz	Code;
const #6 = Asciz	scala/util/parsing/json/JSON$;
const #7 = class	#6;	//  scala/util/parsing/json/JSON$
const #8 = Asciz	MODULE$;
const #9 = Asciz	Lscala/util/parsing/json/JSON$;;
const #10 = NameAndType	#8:#9;//  MODULE$:Lscala/util/parsing/json/JSON$;
const #11 = Field	#7.#10;	//  scala/util/parsing/json/JSON$.MODULE$:Lscala/util/parsing/json/JSON$;
const #12 = NameAndType	#3:#4;//  perThreadNumberParser:()Lscala/Function1;
const #13 = Method	#7.#12;	//  scala/util/parsing/json/JSON$.perThreadNumberParser:()Lscala/Function1;
const #14 = Asciz	()Lscala/Function1<Ljava/lang/String;Ljava/lang/Object;>;;
const #15 = Asciz	Signature;
const #16 = Asciz	perThreadNumberParser_$eq;
const #17 = Asciz	(Lscala/Function1;)V;
const #18 = NameAndType	#16:#17;//  perThreadNumberParser_$eq:(Lscala/Function1;)V
const #19 = Method	#7.#18;	//  scala/util/parsing/json/JSON$.perThreadNumberParser_$eq:(Lscala/Function1;)V
const #20 = Asciz	(Lscala/Function1<Ljava/lang/String;Ljava/lang/Object;>;)V;
const #21 = Asciz	globalNumberParser;
const #22 = NameAndType	#21:#4;//  globalNumberParser:()Lscala/Function1;
const #23 = Method	#7.#22;	//  scala/util/parsing/json/JSON$.globalNumberParser:()Lscala/Function1;
const #24 = Asciz	globalNumberParser_$eq;
const #25 = NameAndType	#24:#17;//  globalNumberParser_$eq:(Lscala/Function1;)V
const #26 = Method	#7.#25;	//  scala/util/parsing/json/JSON$.globalNumberParser_$eq:(Lscala/Function1;)V
const #27 = Asciz	resolveType;
const #28 = Asciz	(Lscala/collection/immutable/List;)Ljava/lang/Object;;
const #29 = NameAndType	#27:#28;//  resolveType:(Lscala/collection/immutable/List;)Ljava/lang/Object;
const #30 = Method	#7.#29;	//  scala/util/parsing/json/JSON$.resolveType:(Lscala/collection/immutable/List;)Ljava/lang/Object;
const #31 = Asciz	(Lscala/collection/immutable/List<Ljava/lang/Object;>;)Ljava/lang/Object;;
const #32 = Asciz	parseFull;
const #33 = Asciz	(Ljava/lang/String;)Lscala/Option;;
const #34 = NameAndType	#32:#33;//  parseFull:(Ljava/lang/String;)Lscala/Option;
const #35 = Method	#7.#34;	//  scala/util/parsing/json/JSON$.parseFull:(Ljava/lang/String;)Lscala/Option;
const #36 = Asciz	(Ljava/lang/String;)Lscala/Option<Ljava/lang/Object;>;;
const #37 = Asciz	parse;
const #38 = NameAndType	#37:#33;//  parse:(Ljava/lang/String;)Lscala/Option;
const #39 = Method	#7.#38;	//  scala/util/parsing/json/JSON$.parse:(Ljava/lang/String;)Lscala/Option;
const #40 = Asciz	(Ljava/lang/String;)Lscala/Option<Lscala/collection/immutable/List<Ljava/lang/Object;>;>;;
const #41 = Asciz	mkList;
const #42 = NameAndType	#41:#4;//  mkList:()Lscala/Function1;
const #43 = Method	#7.#42;	//  scala/util/parsing/json/JSON$.mkList:()Lscala/Function1;
const #44 = Asciz	phrase;
const #45 = Asciz	(Lscala/util/parsing/combinator/Parsers$Parser;)Lscala/util/parsing/combinator/Parsers$Parser;;
const #46 = NameAndType	#44:#45;//  phrase:(Lscala/util/parsing/combinator/Parsers$Parser;)Lscala/util/parsing/combinator/Parsers$Parser;
const #47 = Method	#7.#46;	//  scala/util/parsing/json/JSON$.phrase:(Lscala/util/parsing/combinator/Parsers$Parser;)Lscala/util/parsing/combinator/Parsers$Parser;
const #48 = Asciz	positioned;
const #49 = Asciz	(Lscala/Function0;)Lscala/util/parsing/combinator/Parsers$Parser;;
const #50 = NameAndType	#48:#49;//  positioned:(Lscala/Function0;)Lscala/util/parsing/combinator/Parsers$Parser;
const #51 = Method	#7.#50;	//  scala/util/parsing/json/JSON$.positioned:(Lscala/Function0;)Lscala/util/parsing/combinator/Parsers$Parser;
const #52 = Asciz	guard;
const #53 = NameAndType	#52:#49;//  guard:(Lscala/Function0;)Lscala/util/parsing/combinator/Parsers$Parser;
const #54 = Method	#7.#53;	//  scala/util/parsing/json/JSON$.guard:(Lscala/Function0;)Lscala/util/parsing/combinator/Parsers$Parser;
const #55 = Asciz	not;
const #56 = NameAndType	#55:#49;//  not:(Lscala/Function0;)Lscala/util/parsing/combinator/Parsers$Parser;
const #57 = Method	#7.#56;	//  scala/util/parsing/json/JSON$.not:(Lscala/Function0;)Lscala/util/parsing/combinator/Parsers$Parser;
const #58 = Asciz	opt;
const #59 = NameAndType	#58:#49;//  opt:(Lscala/Function0;)Lscala/util/parsing/combinator/Parsers$Parser;
const #60 = Method	#7.#59;	//  scala/util/parsing/json/JSON$.opt:(Lscala/Function0;)Lscala/util/parsing/combinator/Parsers$Parser;
const #61 = Asciz	chainr1;
const #62 = Asciz	(Lscala/Function0;Lscala/Function0;Lscala/Function2;Ljava/lang/Object;)Lscala/util/parsing/combinator/Parsers$Parser;;
const #63 = NameAndType	#61:#62;//  chainr1:(Lscala/Function0;Lscala/Function0;Lscala/Function2;Ljava/lang/Object;)Lscala/util/parsing/combinator/Parsers$Parser;
const #64 = Method	#7.#63;	//  scala/util/parsing/json/JSON$.chainr1:(Lscala/Function0;Lscala/Function0;Lscala/Function2;Ljava/lang/Object;)Lscala/util/parsing/combinator/Parsers$Parser;
const #65 = Asciz	chainl1;
const #66 = Asciz	(Lscala/Function0;Lscala/Function0;Lscala/Function0;)Lscala/util/parsing/combinator/Parsers$Parser;;
const #67 = NameAndType	#65:#66;//  chainl1:(Lscala/Function0;Lscala/Function0;Lscala/Function0;)Lscala/util/parsing/combinator/Parsers$Parser;
const #68 = Method	#7.#67;	//  scala/util/parsing/json/JSON$.chainl1:(Lscala/Function0;Lscala/Function0;Lscala/Function0;)Lscala/util/parsing/combinator/Parsers$Parser;
const #69 = Asciz	(Lscala/Function0;Lscala/Function0;)Lscala/util/parsing/combinator/Parsers$Parser;;
const #70 = NameAndType	#65:#69;//  chainl1:(Lscala/Function0;Lscala/Function0;)Lscala/util/parsing/combinator/Parsers$Parser;
const #71 = Method	#7.#70;	//  scala/util/parsing/json/JSON$.chainl1:(Lscala/Function0;Lscala/Function0;)Lscala/util/parsing/combinator/Parsers$Parser;
const #72 = Asciz	rep1sep;
const #73 = NameAndType	#72:#69;//  rep1sep:(Lscala/Function0;Lscala/Function0;)Lscala/util/parsing/combinator/Parsers$Parser;
const #74 = Method	#7.#73;	//  scala/util/parsing/json/JSON$.rep1sep:(Lscala/Function0;Lscala/Function0;)Lscala/util/parsing/combinator/Parsers$Parser;
const #75 = Asciz	repN;
const #76 = Asciz	(ILscala/Function0;)Lscala/util/parsing/combinator/Parsers$Parser;;
const #77 = NameAndType	#75:#76;//  repN:(ILscala/Function0;)Lscala/util/parsing/combinator/Parsers$Parser;
const #78 = Method	#7.#77;	//  scala/util/parsing/json/JSON$.repN:(ILscala/Function0;)Lscala/util/parsing/combinator/Parsers$Parser;
const #79 = Asciz	rep1;
const #80 = NameAndType	#79:#69;//  rep1:(Lscala/Function0;Lscala/Function0;)Lscala/util/parsing/combinator/Parsers$Parser;
const #81 = Method	#7.#80;	//  scala/util/parsing/json/JSON$.rep1:(Lscala/Function0;Lscala/Function0;)Lscala/util/parsing/combinator/Parsers$Parser;
const #82 = NameAndType	#79:#49;//  rep1:(Lscala/Function0;)Lscala/util/parsing/combinator/Parsers$Parser;
const #83 = Method	#7.#82;	//  scala/util/parsing/json/JSON$.rep1:(Lscala/Function0;)Lscala/util/parsing/combinator/Parsers$Parser;
const #84 = Asciz	repsep;
const #85 = NameAndType	#84:#69;//  repsep:(Lscala/Function0;Lscala/Function0;)Lscala/util/parsing/combinator/Parsers$Parser;
const #86 = Method	#7.#85;	//  scala/util/parsing/json/JSON$.repsep:(Lscala/Function0;Lscala/Function0;)Lscala/util/parsing/combinator/Parsers$Parser;
const #87 = Asciz	rep;
const #88 = NameAndType	#87:#49;//  rep:(Lscala/Function0;)Lscala/util/parsing/combinator/Parsers$Parser;
const #89 = Method	#7.#88;	//  scala/util/parsing/json/JSON$.rep:(Lscala/Function0;)Lscala/util/parsing/combinator/Parsers$Parser;
const #90 = Asciz	log;
const #91 = Asciz	(Lscala/Function0;Ljava/lang/String;)Lscala/util/parsing/combinator/Parsers$Parser;;
const #92 = NameAndType	#90:#91;//  log:(Lscala/Function0;Ljava/lang/String;)Lscala/util/parsing/combinator/Parsers$Parser;
const #93 = Method	#7.#92;	//  scala/util/parsing/json/JSON$.log:(Lscala/Function0;Ljava/lang/String;)Lscala/util/parsing/combinator/Parsers$Parser;
const #94 = Asciz	success;
const #95 = Asciz	(Ljava/lang/Object;)Lscala/util/parsing/combinator/Parsers$Parser;;
const #96 = NameAndType	#94:#95;//  success:(Ljava/lang/Object;)Lscala/util/parsing/combinator/Parsers$Parser;
const #97 = Method	#7.#96;	//  scala/util/parsing/json/JSON$.success:(Ljava/lang/Object;)Lscala/util/parsing/combinator/Parsers$Parser;
const #98 = Asciz	err;
const #99 = Asciz	(Ljava/lang/String;)Lscala/util/parsing/combinator/Parsers$Parser;;
const #100 = NameAndType	#98:#99;//  err:(Ljava/lang/String;)Lscala/util/parsing/combinator/Parsers$Parser;
const #101 = Method	#7.#100;	//  scala/util/parsing/json/JSON$.err:(Ljava/lang/String;)Lscala/util/parsing/combinator/Parsers$Parser;
const #102 = Asciz	failure;
const #103 = NameAndType	#102:#99;//  failure:(Ljava/lang/String;)Lscala/util/parsing/combinator/Parsers$Parser;
const #104 = Method	#7.#103;	//  scala/util/parsing/json/JSON$.failure:(Ljava/lang/String;)Lscala/util/parsing/combinator/Parsers$Parser;
const #105 = Asciz	acceptSeq;
const #106 = Asciz	(Ljava/lang/Object;Lscala/Function1;)Lscala/util/parsing/combinator/Parsers$Parser;;
const #107 = NameAndType	#105:#106;//  acceptSeq:(Ljava/lang/Object;Lscala/Function1;)Lscala/util/parsing/combinator/Parsers$Parser;
const #108 = Method	#7.#107;	//  scala/util/parsing/json/JSON$.acceptSeq:(Ljava/lang/Object;Lscala/Function1;)Lscala/util/parsing/combinator/Parsers$Parser;
const #109 = Asciz	acceptMatch;
const #110 = Asciz	(Ljava/lang/String;Lscala/PartialFunction;)Lscala/util/parsing/combinator/Parsers$Parser;;
const #111 = NameAndType	#109:#110;//  acceptMatch:(Ljava/lang/String;Lscala/PartialFunction;)Lscala/util/parsing/combinator/Parsers$Parser;
const #112 = Method	#7.#111;	//  scala/util/parsing/json/JSON$.acceptMatch:(Ljava/lang/String;Lscala/PartialFunction;)Lscala/util/parsing/combinator/Parsers$Parser;
const #113 = Asciz	acceptIf;
const #114 = Asciz	(Lscala/Function1;Lscala/Function1;)Lscala/util/parsing/combinator/Parsers$Parser;;
const #115 = NameAndType	#113:#114;//  acceptIf:(Lscala/Function1;Lscala/Function1;)Lscala/util/parsing/combinator/Parsers$Parser;
const #116 = Method	#7.#115;	//  scala/util/parsing/json/JSON$.acceptIf:(Lscala/Function1;Lscala/Function1;)Lscala/util/parsing/combinator/Parsers$Parser;
const #117 = Asciz	accept;
const #118 = NameAndType	#117:#110;//  accept:(Ljava/lang/String;Lscala/PartialFunction;)Lscala/util/parsing/combinator/Parsers$Parser;
const #119 = Method	#7.#118;	//  scala/util/parsing/json/JSON$.accept:(Ljava/lang/String;Lscala/PartialFunction;)Lscala/util/parsing/combinator/Parsers$Parser;
const #120 = NameAndType	#117:#106;//  accept:(Ljava/lang/Object;Lscala/Function1;)Lscala/util/parsing/combinator/Parsers$Parser;
const #121 = Method	#7.#120;	//  scala/util/parsing/json/JSON$.accept:(Ljava/lang/Object;Lscala/Function1;)Lscala/util/parsing/combinator/Parsers$Parser;
const #122 = NameAndType	#117:#95;//  accept:(Ljava/lang/Object;)Lscala/util/parsing/combinator/Parsers$Parser;
const #123 = Method	#7.#122;	//  scala/util/parsing/json/JSON$.accept:(Ljava/lang/Object;)Lscala/util/parsing/combinator/Parsers$Parser;
const #124 = Asciz	elem;
const #125 = NameAndType	#124:#95;//  elem:(Ljava/lang/Object;)Lscala/util/parsing/combinator/Parsers$Parser;
const #126 = Method	#7.#125;	//  scala/util/parsing/json/JSON$.elem:(Ljava/lang/Object;)Lscala/util/parsing/combinator/Parsers$Parser;
const #127 = Asciz	(Ljava/lang/String;Lscala/Function1;)Lscala/util/parsing/combinator/Parsers$Parser;;
const #128 = NameAndType	#124:#127;//  elem:(Ljava/lang/String;Lscala/Function1;)Lscala/util/parsing/combinator/Parsers$Parser;
const #129 = Method	#7.#128;	//  scala/util/parsing/json/JSON$.elem:(Ljava/lang/String;Lscala/Function1;)Lscala/util/parsing/combinator/Parsers$Parser;
const #130 = Asciz	commit;
const #131 = NameAndType	#130:#49;//  commit:(Lscala/Function0;)Lscala/util/parsing/combinator/Parsers$Parser;
const #132 = Method	#7.#131;	//  scala/util/parsing/json/JSON$.commit:(Lscala/Function0;)Lscala/util/parsing/combinator/Parsers$Parser;
const #133 = Asciz	OnceParser;
const #134 = Asciz	(Lscala/Function1;)Lscala/util/parsing/combinator/Parsers$Parser;;
const #135 = NameAndType	#133:#134;//  OnceParser:(Lscala/Function1;)Lscala/util/parsing/combinator/Parsers$Parser;
const #136 = Method	#7.#135;	//  scala/util/parsing/json/JSON$.OnceParser:(Lscala/Function1;)Lscala/util/parsing/combinator/Parsers$Parser;
const #137 = Asciz	Parser;
const #138 = NameAndType	#137:#134;//  Parser:(Lscala/Function1;)Lscala/util/parsing/combinator/Parsers$Parser;
const #139 = Method	#7.#138;	//  scala/util/parsing/json/JSON$.Parser:(Lscala/Function1;)Lscala/util/parsing/combinator/Parsers$Parser;
const #140 = Asciz	lastNoSuccess_$eq;
const #141 = Asciz	(Lscala/util/parsing/combinator/Parsers$NoSuccess;)V;
const #142 = NameAndType	#140:#141;//  lastNoSuccess_$eq:(Lscala/util/parsing/combinator/Parsers$NoSuccess;)V
const #143 = Method	#7.#142;	//  scala/util/parsing/json/JSON$.lastNoSuccess_$eq:(Lscala/util/parsing/combinator/Parsers$NoSuccess;)V
const #144 = Asciz	lastNoSuccess;
const #145 = Asciz	()Lscala/util/parsing/combinator/Parsers$NoSuccess;;
const #146 = NameAndType	#144:#145;//  lastNoSuccess:()Lscala/util/parsing/combinator/Parsers$NoSuccess;
const #147 = Method	#7.#146;	//  scala/util/parsing/json/JSON$.lastNoSuccess:()Lscala/util/parsing/combinator/Parsers$NoSuccess;
const #148 = Asciz	ident;
const #149 = Asciz	()Lscala/util/parsing/combinator/Parsers$Parser;;
const #150 = NameAndType	#148:#149;//  ident:()Lscala/util/parsing/combinator/Parsers$Parser;
const #151 = Method	#7.#150;	//  scala/util/parsing/json/JSON$.ident:()Lscala/util/parsing/combinator/Parsers$Parser;
const #152 = Asciz	stringLit;
const #153 = NameAndType	#152:#149;//  stringLit:()Lscala/util/parsing/combinator/Parsers$Parser;
const #154 = Method	#7.#153;	//  scala/util/parsing/json/JSON$.stringLit:()Lscala/util/parsing/combinator/Parsers$Parser;
const #155 = Asciz	numericLit;
const #156 = NameAndType	#155:#149;//  numericLit:()Lscala/util/parsing/combinator/Parsers$Parser;
const #157 = Method	#7.#156;	//  scala/util/parsing/json/JSON$.numericLit:()Lscala/util/parsing/combinator/Parsers$Parser;
const #158 = Asciz	keyword;
const #159 = NameAndType	#158:#99;//  keyword:(Ljava/lang/String;)Lscala/util/parsing/combinator/Parsers$Parser;
const #160 = Method	#7.#159;	//  scala/util/parsing/json/JSON$.keyword:(Ljava/lang/String;)Lscala/util/parsing/combinator/Parsers$Parser;
const #161 = Asciz	scala$util$parsing$combinator$syntactical$StdTokenParsers$_setter_$keywordCache_$eq;
const #162 = Asciz	(Lscala/collection/mutable/HashMap;)V;
const #163 = NameAndType	#161:#162;//  scala$util$parsing$combinator$syntactical$StdTokenParsers$_setter_$keywordCache_$eq:(Lscala/collection/mutable/HashMap;)V
const #164 = Method	#7.#163;	//  scala/util/parsing/json/JSON$.scala$util$parsing$combinator$syntactical$StdTokenParsers$_setter_$keywordCache_$eq:(Lscala/collection/mutable/HashMap;)V
const #165 = Asciz	headOptionTailToFunList;
const #166 = Asciz	(Lscala/Function1;)Lscala/Function1;;
const #167 = NameAndType	#165:#166;//  headOptionTailToFunList:(Lscala/Function1;)Lscala/Function1;
const #168 = Method	#7.#167;	//  scala/util/parsing/json/JSON$.headOptionTailToFunList:(Lscala/Function1;)Lscala/Function1;
const #169 = Asciz	flatten5;
const #170 = Asciz	(Lscala/Function5;)Lscala/Function1;;
const #171 = NameAndType	#169:#170;//  flatten5:(Lscala/Function5;)Lscala/Function1;
const #172 = Method	#7.#171;	//  scala/util/parsing/json/JSON$.flatten5:(Lscala/Function5;)Lscala/Function1;
const #173 = Asciz	flatten4;
const #174 = Asciz	(Lscala/Function4;)Lscala/Function1;;
const #175 = NameAndType	#173:#174;//  flatten4:(Lscala/Function4;)Lscala/Function1;
const #176 = Method	#7.#175;	//  scala/util/parsing/json/JSON$.flatten4:(Lscala/Function4;)Lscala/Function1;
const #177 = Asciz	flatten3;
const #178 = Asciz	(Lscala/Function3;)Lscala/Function1;;
const #179 = NameAndType	#177:#178;//  flatten3:(Lscala/Function3;)Lscala/Function1;
const #180 = Method	#7.#179;	//  scala/util/parsing/json/JSON$.flatten3:(Lscala/Function3;)Lscala/Function1;
const #181 = Asciz	flatten2;
const #182 = Asciz	(Lscala/Function2;)Lscala/Function1;;
const #183 = NameAndType	#181:#182;//  flatten2:(Lscala/Function2;)Lscala/Function1;
const #184 = Method	#7.#183;	//  scala/util/parsing/json/JSON$.flatten2:(Lscala/Function2;)Lscala/Function1;
const #185 = Asciz	number;
const #186 = NameAndType	#185:#149;//  number:()Lscala/util/parsing/combinator/Parsers$Parser;
const #187 = Method	#7.#186;	//  scala/util/parsing/json/JSON$.number:()Lscala/util/parsing/combinator/Parsers$Parser;
const #188 = Asciz	()Lscala/util/parsing/combinator/Parsers$Parser<Ljava/lang/Object;>;;
const #189 = Asciz	stringVal;
const #190 = NameAndType	#189:#149;//  stringVal:()Lscala/util/parsing/combinator/Parsers$Parser;
const #191 = Method	#7.#190;	//  scala/util/parsing/json/JSON$.stringVal:()Lscala/util/parsing/combinator/Parsers$Parser;
const #192 = Asciz	()Lscala/util/parsing/combinator/Parsers$Parser<Ljava/lang/String;>;;
const #193 = Asciz	value;
const #194 = NameAndType	#193:#149;//  value:()Lscala/util/parsing/combinator/Parsers$Parser;
const #195 = Method	#7.#194;	//  scala/util/parsing/json/JSON$.value:()Lscala/util/parsing/combinator/Parsers$Parser;
const #196 = Asciz	objEntry;
const #197 = NameAndType	#196:#149;//  objEntry:()Lscala/util/parsing/combinator/Parsers$Parser;
const #198 = Method	#7.#197;	//  scala/util/parsing/json/JSON$.objEntry:()Lscala/util/parsing/combinator/Parsers$Parser;
const #199 = Asciz	()Lscala/util/parsing/combinator/Parsers$Parser<Lscala/Tuple2<Ljava/lang/String;Ljava/lang/Object;>;>;;
const #200 = Asciz	jsonArray;
const #201 = NameAndType	#200:#149;//  jsonArray:()Lscala/util/parsing/combinator/Parsers$Parser;
const #202 = Method	#7.#201;	//  scala/util/parsing/json/JSON$.jsonArray:()Lscala/util/parsing/combinator/Parsers$Parser;
const #203 = Asciz	()Lscala/util/parsing/combinator/Parsers$Parser<Lscala/collection/immutable/List<Ljava/lang/Object;>;>;;
const #204 = Asciz	jsonObj;
const #205 = NameAndType	#204:#149;//  jsonObj:()Lscala/util/parsing/combinator/Parsers$Parser;
const #206 = Method	#7.#205;	//  scala/util/parsing/json/JSON$.jsonObj:()Lscala/util/parsing/combinator/Parsers$Parser;
const #207 = Asciz	()Lscala/util/parsing/combinator/Parsers$Parser<Lscala/collection/immutable/List<Lscala/Tuple2<Ljava/lang/String;Ljava/lang/Object;>;>;>;;
const #208 = Asciz	root;
const #209 = NameAndType	#208:#149;//  root:()Lscala/util/parsing/combinator/Parsers$Parser;
const #210 = Method	#7.#209;	//  scala/util/parsing/json/JSON$.root:()Lscala/util/parsing/combinator/Parsers$Parser;
const #211 = Asciz	lexical;
const #212 = Asciz	()Lscala/util/parsing/json/Lexer;;
const #213 = NameAndType	#211:#212;//  lexical:()Lscala/util/parsing/json/Lexer;
const #214 = Method	#7.#213;	//  scala/util/parsing/json/JSON$.lexical:()Lscala/util/parsing/json/Lexer;
const #215 = Asciz	()Lscala/util/parsing/syntax/Tokens;;
const #216 = NameAndType	#211:#215;//  lexical:()Lscala/util/parsing/syntax/Tokens;
const #217 = Method	#7.#216;	//  scala/util/parsing/json/JSON$.lexical:()Lscala/util/parsing/syntax/Tokens;
const #218 = Asciz	ScalaSig;
const #219 = Asciz	InnerClasses;
const #220 = Asciz	scala/util/parsing/combinator/Parsers$Parser;
const #221 = class	#220;	//  scala/util/parsing/combinator/Parsers$Parser
const #222 = Asciz	scala/util/parsing/combinator/Parsers;
const #223 = class	#222;	//  scala/util/parsing/combinator/Parsers
const #224 = Asciz	scala/util/parsing/combinator/Parsers$NoSuccess;
const #225 = class	#224;	//  scala/util/parsing/combinator/Parsers$NoSuccess
const #226 = Asciz	NoSuccess;
const #227 = Asciz	scala/util/parsing/json/JSON$$anonfun$resolveType$1;
const #228 = class	#227;	//  scala/util/parsing/json/JSON$$anonfun$resolveType$1
const #229 = Asciz	scala/util/parsing/json/JSON;
const #230 = class	#229;	//  scala/util/parsing/json/JSON
const #231 = Asciz	$anonfun$resolveType$1;
const #232 = Asciz	java/lang/Object;
const #233 = class	#232;	//  java/lang/Object

{
public static final scala.Function1 perThreadNumberParser();
  Code:
   Stack=1, Locals=0, Args_size=0
   0:	getstatic	#11; //Field scala/util/parsing/json/JSON$.MODULE$:Lscala/util/parsing/json/JSON$;
   3:	invokevirtual	#13; //Method scala/util/parsing/json/JSON$.perThreadNumberParser:()Lscala/Function1;
   6:	areturn
  Signature: length = 0x2
   00 0E 

public static final void perThreadNumberParser_$eq(scala.Function1);
  Code:
   Stack=2, Locals=1, Args_size=1
   0:	getstatic	#11; //Field scala/util/parsing/json/JSON$.MODULE$:Lscala/util/parsing/json/JSON$;
   3:	aload_0
   4:	invokevirtual	#19; //Method scala/util/parsing/json/JSON$.perThreadNumberParser_$eq:(Lscala/Function1;)V
   7:	return
  Signature: length = 0x2
   00 14 

public static final scala.Function1 globalNumberParser();
  Code:
   Stack=1, Locals=0, Args_size=0
   0:	getstatic	#11; //Field scala/util/parsing/json/JSON$.MODULE$:Lscala/util/parsing/json/JSON$;
   3:	invokevirtual	#23; //Method scala/util/parsing/json/JSON$.globalNumberParser:()Lscala/Function1;
   6:	areturn
  Signature: length = 0x2
   00 0E 

public static final void globalNumberParser_$eq(scala.Function1);
  Code:
   Stack=2, Locals=1, Args_size=1
   0:	getstatic	#11; //Field scala/util/parsing/json/JSON$.MODULE$:Lscala/util/parsing/json/JSON$;
   3:	aload_0
   4:	invokevirtual	#26; //Method scala/util/parsing/json/JSON$.globalNumberParser_$eq:(Lscala/Function1;)V
   7:	return
  Signature: length = 0x2
   00 14 

public static final java.lang.Object resolveType(scala.collection.immutable.List);
  Code:
   Stack=2, Locals=1, Args_size=1
   0:	getstatic	#11; //Field scala/util/parsing/json/JSON$.MODULE$:Lscala/util/parsing/json/JSON$;
   3:	aload_0
   4:	invokevirtual	#30; //Method scala/util/parsing/json/JSON$.resolveType:(Lscala/collection/immutable/List;)Ljava/lang/Object;
   7:	areturn
  Signature: length = 0x2
   00 1F 

public static final scala.Option parseFull(java.lang.String);
  Code:
   Stack=2, Locals=1, Args_size=1
   0:	getstatic	#11; //Field scala/util/parsing/json/JSON$.MODULE$:Lscala/util/parsing/json/JSON$;
   3:	aload_0
   4:	invokevirtual	#35; //Method scala/util/parsing/json/JSON$.parseFull:(Ljava/lang/String;)Lscala/Option;
   7:	areturn
  Signature: length = 0x2
   00 24 

public static final scala.Option parse(java.lang.String);
  Code:
   Stack=2, Locals=1, Args_size=1
   0:	getstatic	#11; //Field scala/util/parsing/json/JSON$.MODULE$:Lscala/util/parsing/json/JSON$;
   3:	aload_0
   4:	invokevirtual	#39; //Method scala/util/parsing/json/JSON$.parse:(Ljava/lang/String;)Lscala/Option;
   7:	areturn
  Signature: length = 0x2
   00 28 

public static final scala.Function1 mkList();
  Code:
   Stack=1, Locals=0, Args_size=0
   0:	getstatic	#11; //Field scala/util/parsing/json/JSON$.MODULE$:Lscala/util/parsing/json/JSON$;
   3:	invokevirtual	#43; //Method scala/util/parsing/json/JSON$.mkList:()Lscala/Function1;
   6:	areturn

public static final scala.util.parsing.combinator.Parsers$Parser phrase(scala.util.parsing.combinator.Parsers$Parser);
  Code:
   Stack=2, Locals=1, Args_size=1
   0:	getstatic	#11; //Field scala/util/parsing/json/JSON$.MODULE$:Lscala/util/parsing/json/JSON$;
   3:	aload_0
   4:	invokevirtual	#47; //Method scala/util/parsing/json/JSON$.phrase:(Lscala/util/parsing/combinator/Parsers$Parser;)Lscala/util/parsing/combinator/Parsers$Parser;
   7:	areturn

public static final scala.util.parsing.combinator.Parsers$Parser positioned(scala.Function0);
  Code:
   Stack=2, Locals=1, Args_size=1
   0:	getstatic	#11; //Field scala/util/parsing/json/JSON$.MODULE$:Lscala/util/parsing/json/JSON$;
   3:	aload_0
   4:	invokevirtual	#51; //Method scala/util/parsing/json/JSON$.positioned:(Lscala/Function0;)Lscala/util/parsing/combinator/Parsers$Parser;
   7:	areturn

public static final scala.util.parsing.combinator.Parsers$Parser guard(scala.Function0);
  Code:
   Stack=2, Locals=1, Args_size=1
   0:	getstatic	#11; //Field scala/util/parsing/json/JSON$.MODULE$:Lscala/util/parsing/json/JSON$;
   3:	aload_0
   4:	invokevirtual	#54; //Method scala/util/parsing/json/JSON$.guard:(Lscala/Function0;)Lscala/util/parsing/combinator/Parsers$Parser;
   7:	areturn

public static final scala.util.parsing.combinator.Parsers$Parser not(scala.Function0);
  Code:
   Stack=2, Locals=1, Args_size=1
   0:	getstatic	#11; //Field scala/util/parsing/json/JSON$.MODULE$:Lscala/util/parsing/json/JSON$;
   3:	aload_0
   4:	invokevirtual	#57; //Method scala/util/parsing/json/JSON$.not:(Lscala/Function0;)Lscala/util/parsing/combinator/Parsers$Parser;
   7:	areturn

public static final scala.util.parsing.combinator.Parsers$Parser opt(scala.Function0);
  Code:
   Stack=2, Locals=1, Args_size=1
   0:	getstatic	#11; //Field scala/util/parsing/json/JSON$.MODULE$:Lscala/util/parsing/json/JSON$;
   3:	aload_0
   4:	invokevirtual	#60; //Method scala/util/parsing/json/JSON$.opt:(Lscala/Function0;)Lscala/util/parsing/combinator/Parsers$Parser;
   7:	areturn

public static final scala.util.parsing.combinator.Parsers$Parser chainr1(scala.Function0, scala.Function0, scala.Function2, java.lang.Object);
  Code:
   Stack=5, Locals=4, Args_size=4
   0:	getstatic	#11; //Field scala/util/parsing/json/JSON$.MODULE$:Lscala/util/parsing/json/JSON$;
   3:	aload_0
   4:	aload_1
   5:	aload_2
   6:	aload_3
   7:	invokevirtual	#64; //Method scala/util/parsing/json/JSON$.chainr1:(Lscala/Function0;Lscala/Function0;Lscala/Function2;Ljava/lang/Object;)Lscala/util/parsing/combinator/Parsers$Parser;
   10:	areturn

public static final scala.util.parsing.combinator.Parsers$Parser chainl1(scala.Function0, scala.Function0, scala.Function0);
  Code:
   Stack=4, Locals=3, Args_size=3
   0:	getstatic	#11; //Field scala/util/parsing/json/JSON$.MODULE$:Lscala/util/parsing/json/JSON$;
   3:	aload_0
   4:	aload_1
   5:	aload_2
   6:	invokevirtual	#68; //Method scala/util/parsing/json/JSON$.chainl1:(Lscala/Function0;Lscala/Function0;Lscala/Function0;)Lscala/util/parsing/combinator/Parsers$Parser;
   9:	areturn

public static final scala.util.parsing.combinator.Parsers$Parser chainl1(scala.Function0, scala.Function0);
  Code:
   Stack=3, Locals=2, Args_size=2
   0:	getstatic	#11; //Field scala/util/parsing/json/JSON$.MODULE$:Lscala/util/parsing/json/JSON$;
   3:	aload_0
   4:	aload_1
   5:	invokevirtual	#71; //Method scala/util/parsing/json/JSON$.chainl1:(Lscala/Function0;Lscala/Function0;)Lscala/util/parsing/combinator/Parsers$Parser;
   8:	areturn

public static final scala.util.parsing.combinator.Parsers$Parser rep1sep(scala.Function0, scala.Function0);
  Code:
   Stack=3, Locals=2, Args_size=2
   0:	getstatic	#11; //Field scala/util/parsing/json/JSON$.MODULE$:Lscala/util/parsing/json/JSON$;
   3:	aload_0
   4:	aload_1
   5:	invokevirtual	#74; //Method scala/util/parsing/json/JSON$.rep1sep:(Lscala/Function0;Lscala/Function0;)Lscala/util/parsing/combinator/Parsers$Parser;
   8:	areturn

public static final scala.util.parsing.combinator.Parsers$Parser repN(int, scala.Function0);
  Code:
   Stack=3, Locals=2, Args_size=2
   0:	getstatic	#11; //Field scala/util/parsing/json/JSON$.MODULE$:Lscala/util/parsing/json/JSON$;
   3:	iload_0
   4:	aload_1
   5:	invokevirtual	#78; //Method scala/util/parsing/json/JSON$.repN:(ILscala/Function0;)Lscala/util/parsing/combinator/Parsers$Parser;
   8:	areturn

public static final scala.util.parsing.combinator.Parsers$Parser rep1(scala.Function0, scala.Function0);
  Code:
   Stack=3, Locals=2, Args_size=2
   0:	getstatic	#11; //Field scala/util/parsing/json/JSON$.MODULE$:Lscala/util/parsing/json/JSON$;
   3:	aload_0
   4:	aload_1
   5:	invokevirtual	#81; //Method scala/util/parsing/json/JSON$.rep1:(Lscala/Function0;Lscala/Function0;)Lscala/util/parsing/combinator/Parsers$Parser;
   8:	areturn

public static final scala.util.parsing.combinator.Parsers$Parser rep1(scala.Function0);
  Code:
   Stack=2, Locals=1, Args_size=1
   0:	getstatic	#11; //Field scala/util/parsing/json/JSON$.MODULE$:Lscala/util/parsing/json/JSON$;
   3:	aload_0
   4:	invokevirtual	#83; //Method scala/util/parsing/json/JSON$.rep1:(Lscala/Function0;)Lscala/util/parsing/combinator/Parsers$Parser;
   7:	areturn

public static final scala.util.parsing.combinator.Parsers$Parser repsep(scala.Function0, scala.Function0);
  Code:
   Stack=3, Locals=2, Args_size=2
   0:	getstatic	#11; //Field scala/util/parsing/json/JSON$.MODULE$:Lscala/util/parsing/json/JSON$;
   3:	aload_0
   4:	aload_1
   5:	invokevirtual	#86; //Method scala/util/parsing/json/JSON$.repsep:(Lscala/Function0;Lscala/Function0;)Lscala/util/parsing/combinator/Parsers$Parser;
   8:	areturn

public static final scala.util.parsing.combinator.Parsers$Parser rep(scala.Function0);
  Code:
   Stack=2, Locals=1, Args_size=1
   0:	getstatic	#11; //Field scala/util/parsing/json/JSON$.MODULE$:Lscala/util/parsing/json/JSON$;
   3:	aload_0
   4:	invokevirtual	#89; //Method scala/util/parsing/json/JSON$.rep:(Lscala/Function0;)Lscala/util/parsing/combinator/Parsers$Parser;
   7:	areturn

public static final scala.util.parsing.combinator.Parsers$Parser log(scala.Function0, java.lang.String);
  Code:
   Stack=3, Locals=2, Args_size=2
   0:	getstatic	#11; //Field scala/util/parsing/json/JSON$.MODULE$:Lscala/util/parsing/json/JSON$;
   3:	aload_0
   4:	aload_1
   5:	invokevirtual	#93; //Method scala/util/parsing/json/JSON$.log:(Lscala/Function0;Ljava/lang/String;)Lscala/util/parsing/combinator/Parsers$Parser;
   8:	areturn

public static final scala.util.parsing.combinator.Parsers$Parser success(java.lang.Object);
  Code:
   Stack=2, Locals=1, Args_size=1
   0:	getstatic	#11; //Field scala/util/parsing/json/JSON$.MODULE$:Lscala/util/parsing/json/JSON$;
   3:	aload_0
   4:	invokevirtual	#97; //Method scala/util/parsing/json/JSON$.success:(Ljava/lang/Object;)Lscala/util/parsing/combinator/Parsers$Parser;
   7:	areturn

public static final scala.util.parsing.combinator.Parsers$Parser err(java.lang.String);
  Code:
   Stack=2, Locals=1, Args_size=1
   0:	getstatic	#11; //Field scala/util/parsing/json/JSON$.MODULE$:Lscala/util/parsing/json/JSON$;
   3:	aload_0
   4:	invokevirtual	#101; //Method scala/util/parsing/json/JSON$.err:(Ljava/lang/String;)Lscala/util/parsing/combinator/Parsers$Parser;
   7:	areturn

public static final scala.util.parsing.combinator.Parsers$Parser failure(java.lang.String);
  Code:
   Stack=2, Locals=1, Args_size=1
   0:	getstatic	#11; //Field scala/util/parsing/json/JSON$.MODULE$:Lscala/util/parsing/json/JSON$;
   3:	aload_0
   4:	invokevirtual	#104; //Method scala/util/parsing/json/JSON$.failure:(Ljava/lang/String;)Lscala/util/parsing/combinator/Parsers$Parser;
   7:	areturn

public static final scala.util.parsing.combinator.Parsers$Parser acceptSeq(java.lang.Object, scala.Function1);
  Code:
   Stack=3, Locals=2, Args_size=2
   0:	getstatic	#11; //Field scala/util/parsing/json/JSON$.MODULE$:Lscala/util/parsing/json/JSON$;
   3:	aload_0
   4:	aload_1
   5:	invokevirtual	#108; //Method scala/util/parsing/json/JSON$.acceptSeq:(Ljava/lang/Object;Lscala/Function1;)Lscala/util/parsing/combinator/Parsers$Parser;
   8:	areturn

public static final scala.util.parsing.combinator.Parsers$Parser acceptMatch(java.lang.String, scala.PartialFunction);
  Code:
   Stack=3, Locals=2, Args_size=2
   0:	getstatic	#11; //Field scala/util/parsing/json/JSON$.MODULE$:Lscala/util/parsing/json/JSON$;
   3:	aload_0
   4:	aload_1
   5:	invokevirtual	#112; //Method scala/util/parsing/json/JSON$.acceptMatch:(Ljava/lang/String;Lscala/PartialFunction;)Lscala/util/parsing/combinator/Parsers$Parser;
   8:	areturn

public static final scala.util.parsing.combinator.Parsers$Parser acceptIf(scala.Function1, scala.Function1);
  Code:
   Stack=3, Locals=2, Args_size=2
   0:	getstatic	#11; //Field scala/util/parsing/json/JSON$.MODULE$:Lscala/util/parsing/json/JSON$;
   3:	aload_0
   4:	aload_1
   5:	invokevirtual	#116; //Method scala/util/parsing/json/JSON$.acceptIf:(Lscala/Function1;Lscala/Function1;)Lscala/util/parsing/combinator/Parsers$Parser;
   8:	areturn

public static final scala.util.parsing.combinator.Parsers$Parser accept(java.lang.String, scala.PartialFunction);
  Code:
   Stack=3, Locals=2, Args_size=2
   0:	getstatic	#11; //Field scala/util/parsing/json/JSON$.MODULE$:Lscala/util/parsing/json/JSON$;
   3:	aload_0
   4:	aload_1
   5:	invokevirtual	#119; //Method scala/util/parsing/json/JSON$.accept:(Ljava/lang/String;Lscala/PartialFunction;)Lscala/util/parsing/combinator/Parsers$Parser;
   8:	areturn

public static final scala.util.parsing.combinator.Parsers$Parser accept(java.lang.Object, scala.Function1);
  Code:
   Stack=3, Locals=2, Args_size=2
   0:	getstatic	#11; //Field scala/util/parsing/json/JSON$.MODULE$:Lscala/util/parsing/json/JSON$;
   3:	aload_0
   4:	aload_1
   5:	invokevirtual	#121; //Method scala/util/parsing/json/JSON$.accept:(Ljava/lang/Object;Lscala/Function1;)Lscala/util/parsing/combinator/Parsers$Parser;
   8:	areturn

public static final scala.util.parsing.combinator.Parsers$Parser accept(java.lang.Object);
  Code:
   Stack=2, Locals=1, Args_size=1
   0:	getstatic	#11; //Field scala/util/parsing/json/JSON$.MODULE$:Lscala/util/parsing/json/JSON$;
   3:	aload_0
   4:	invokevirtual	#123; //Method scala/util/parsing/json/JSON$.accept:(Ljava/lang/Object;)Lscala/util/parsing/combinator/Parsers$Parser;
   7:	areturn

public static final scala.util.parsing.combinator.Parsers$Parser elem(java.lang.Object);
  Code:
   Stack=2, Locals=1, Args_size=1
   0:	getstatic	#11; //Field scala/util/parsing/json/JSON$.MODULE$:Lscala/util/parsing/json/JSON$;
   3:	aload_0
   4:	invokevirtual	#126; //Method scala/util/parsing/json/JSON$.elem:(Ljava/lang/Object;)Lscala/util/parsing/combinator/Parsers$Parser;
   7:	areturn

public static final scala.util.parsing.combinator.Parsers$Parser elem(java.lang.String, scala.Function1);
  Code:
   Stack=3, Locals=2, Args_size=2
   0:	getstatic	#11; //Field scala/util/parsing/json/JSON$.MODULE$:Lscala/util/parsing/json/JSON$;
   3:	aload_0
   4:	aload_1
   5:	invokevirtual	#129; //Method scala/util/parsing/json/JSON$.elem:(Ljava/lang/String;Lscala/Function1;)Lscala/util/parsing/combinator/Parsers$Parser;
   8:	areturn

public static final scala.util.parsing.combinator.Parsers$Parser commit(scala.Function0);
  Code:
   Stack=2, Locals=1, Args_size=1
   0:	getstatic	#11; //Field scala/util/parsing/json/JSON$.MODULE$:Lscala/util/parsing/json/JSON$;
   3:	aload_0
   4:	invokevirtual	#132; //Method scala/util/parsing/json/JSON$.commit:(Lscala/Function0;)Lscala/util/parsing/combinator/Parsers$Parser;
   7:	areturn

public static final scala.util.parsing.combinator.Parsers$Parser OnceParser(scala.Function1);
  Code:
   Stack=2, Locals=1, Args_size=1
   0:	getstatic	#11; //Field scala/util/parsing/json/JSON$.MODULE$:Lscala/util/parsing/json/JSON$;
   3:	aload_0
   4:	invokevirtual	#136; //Method scala/util/parsing/json/JSON$.OnceParser:(Lscala/Function1;)Lscala/util/parsing/combinator/Parsers$Parser;
   7:	areturn

public static final scala.util.parsing.combinator.Parsers$Parser Parser(scala.Function1);
  Code:
   Stack=2, Locals=1, Args_size=1
   0:	getstatic	#11; //Field scala/util/parsing/json/JSON$.MODULE$:Lscala/util/parsing/json/JSON$;
   3:	aload_0
   4:	invokevirtual	#139; //Method scala/util/parsing/json/JSON$.Parser:(Lscala/Function1;)Lscala/util/parsing/combinator/Parsers$Parser;
   7:	areturn

public static final void lastNoSuccess_$eq(scala.util.parsing.combinator.Parsers$NoSuccess);
  Code:
   Stack=2, Locals=1, Args_size=1
   0:	getstatic	#11; //Field scala/util/parsing/json/JSON$.MODULE$:Lscala/util/parsing/json/JSON$;
   3:	aload_0
   4:	invokevirtual	#143; //Method scala/util/parsing/json/JSON$.lastNoSuccess_$eq:(Lscala/util/parsing/combinator/Parsers$NoSuccess;)V
   7:	return

public static final scala.util.parsing.combinator.Parsers$NoSuccess lastNoSuccess();
  Code:
   Stack=1, Locals=0, Args_size=0
   0:	getstatic	#11; //Field scala/util/parsing/json/JSON$.MODULE$:Lscala/util/parsing/json/JSON$;
   3:	invokevirtual	#147; //Method scala/util/parsing/json/JSON$.lastNoSuccess:()Lscala/util/parsing/combinator/Parsers$NoSuccess;
   6:	areturn

public static final scala.util.parsing.combinator.Parsers$Parser ident();
  Code:
   Stack=1, Locals=0, Args_size=0
   0:	getstatic	#11; //Field scala/util/parsing/json/JSON$.MODULE$:Lscala/util/parsing/json/JSON$;
   3:	invokevirtual	#151; //Method scala/util/parsing/json/JSON$.ident:()Lscala/util/parsing/combinator/Parsers$Parser;
   6:	areturn

public static final scala.util.parsing.combinator.Parsers$Parser stringLit();
  Code:
   Stack=1, Locals=0, Args_size=0
   0:	getstatic	#11; //Field scala/util/parsing/json/JSON$.MODULE$:Lscala/util/parsing/json/JSON$;
   3:	invokevirtual	#154; //Method scala/util/parsing/json/JSON$.stringLit:()Lscala/util/parsing/combinator/Parsers$Parser;
   6:	areturn

public static final scala.util.parsing.combinator.Parsers$Parser numericLit();
  Code:
   Stack=1, Locals=0, Args_size=0
   0:	getstatic	#11; //Field scala/util/parsing/json/JSON$.MODULE$:Lscala/util/parsing/json/JSON$;
   3:	invokevirtual	#157; //Method scala/util/parsing/json/JSON$.numericLit:()Lscala/util/parsing/combinator/Parsers$Parser;
   6:	areturn

public static final scala.util.parsing.combinator.Parsers$Parser keyword(java.lang.String);
  Code:
   Stack=2, Locals=1, Args_size=1
   0:	getstatic	#11; //Field scala/util/parsing/json/JSON$.MODULE$:Lscala/util/parsing/json/JSON$;
   3:	aload_0
   4:	invokevirtual	#160; //Method scala/util/parsing/json/JSON$.keyword:(Ljava/lang/String;)Lscala/util/parsing/combinator/Parsers$Parser;
   7:	areturn

public static final void scala$util$parsing$combinator$syntactical$StdTokenParsers$_setter_$keywordCache_$eq(scala.collection.mutable.HashMap);
  Code:
   Stack=2, Locals=1, Args_size=1
   0:	getstatic	#11; //Field scala/util/parsing/json/JSON$.MODULE$:Lscala/util/parsing/json/JSON$;
   3:	aload_0
   4:	invokevirtual	#164; //Method scala/util/parsing/json/JSON$.scala$util$parsing$combinator$syntactical$StdTokenParsers$_setter_$keywordCache_$eq:(Lscala/collection/mutable/HashMap;)V
   7:	return

public static final scala.Function1 headOptionTailToFunList(scala.Function1);
  Code:
   Stack=2, Locals=1, Args_size=1
   0:	getstatic	#11; //Field scala/util/parsing/json/JSON$.MODULE$:Lscala/util/parsing/json/JSON$;
   3:	aload_0
   4:	invokevirtual	#168; //Method scala/util/parsing/json/JSON$.headOptionTailToFunList:(Lscala/Function1;)Lscala/Function1;
   7:	areturn

public static final scala.Function1 flatten5(scala.Function5);
  Code:
   Stack=2, Locals=1, Args_size=1
   0:	getstatic	#11; //Field scala/util/parsing/json/JSON$.MODULE$:Lscala/util/parsing/json/JSON$;
   3:	aload_0
   4:	invokevirtual	#172; //Method scala/util/parsing/json/JSON$.flatten5:(Lscala/Function5;)Lscala/Function1;
   7:	areturn

public static final scala.Function1 flatten4(scala.Function4);
  Code:
   Stack=2, Locals=1, Args_size=1
   0:	getstatic	#11; //Field scala/util/parsing/json/JSON$.MODULE$:Lscala/util/parsing/json/JSON$;
   3:	aload_0
   4:	invokevirtual	#176; //Method scala/util/parsing/json/JSON$.flatten4:(Lscala/Function4;)Lscala/Function1;
   7:	areturn

public static final scala.Function1 flatten3(scala.Function3);
  Code:
   Stack=2, Locals=1, Args_size=1
   0:	getstatic	#11; //Field scala/util/parsing/json/JSON$.MODULE$:Lscala/util/parsing/json/JSON$;
   3:	aload_0
   4:	invokevirtual	#180; //Method scala/util/parsing/json/JSON$.flatten3:(Lscala/Function3;)Lscala/Function1;
   7:	areturn

public static final scala.Function1 flatten2(scala.Function2);
  Code:
   Stack=2, Locals=1, Args_size=1
   0:	getstatic	#11; //Field scala/util/parsing/json/JSON$.MODULE$:Lscala/util/parsing/json/JSON$;
   3:	aload_0
   4:	invokevirtual	#184; //Method scala/util/parsing/json/JSON$.flatten2:(Lscala/Function2;)Lscala/Function1;
   7:	areturn

public static final scala.util.parsing.combinator.Parsers$Parser number();
  Code:
   Stack=1, Locals=0, Args_size=0
   0:	getstatic	#11; //Field scala/util/parsing/json/JSON$.MODULE$:Lscala/util/parsing/json/JSON$;
   3:	invokevirtual	#187; //Method scala/util/parsing/json/JSON$.number:()Lscala/util/parsing/combinator/Parsers$Parser;
   6:	areturn
  Signature: length = 0x2
   00 FFFFFFBC 

public static final scala.util.parsing.combinator.Parsers$Parser stringVal();
  Code:
   Stack=1, Locals=0, Args_size=0
   0:	getstatic	#11; //Field scala/util/parsing/json/JSON$.MODULE$:Lscala/util/parsing/json/JSON$;
   3:	invokevirtual	#191; //Method scala/util/parsing/json/JSON$.stringVal:()Lscala/util/parsing/combinator/Parsers$Parser;
   6:	areturn
  Signature: length = 0x2
   00 FFFFFFC0 

public static final scala.util.parsing.combinator.Parsers$Parser value();
  Code:
   Stack=1, Locals=0, Args_size=0
   0:	getstatic	#11; //Field scala/util/parsing/json/JSON$.MODULE$:Lscala/util/parsing/json/JSON$;
   3:	invokevirtual	#195; //Method scala/util/parsing/json/JSON$.value:()Lscala/util/parsing/combinator/Parsers$Parser;
   6:	areturn
  Signature: length = 0x2
   00 FFFFFFBC 

public static final scala.util.parsing.combinator.Parsers$Parser objEntry();
  Code:
   Stack=1, Locals=0, Args_size=0
   0:	getstatic	#11; //Field scala/util/parsing/json/JSON$.MODULE$:Lscala/util/parsing/json/JSON$;
   3:	invokevirtual	#198; //Method scala/util/parsing/json/JSON$.objEntry:()Lscala/util/parsing/combinator/Parsers$Parser;
   6:	areturn
  Signature: length = 0x2
   00 FFFFFFC7 

public static final scala.util.parsing.combinator.Parsers$Parser jsonArray();
  Code:
   Stack=1, Locals=0, Args_size=0
   0:	getstatic	#11; //Field scala/util/parsing/json/JSON$.MODULE$:Lscala/util/parsing/json/JSON$;
   3:	invokevirtual	#202; //Method scala/util/parsing/json/JSON$.jsonArray:()Lscala/util/parsing/combinator/Parsers$Parser;
   6:	areturn
  Signature: length = 0x2
   00 FFFFFFCB 

public static final scala.util.parsing.combinator.Parsers$Parser jsonObj();
  Code:
   Stack=1, Locals=0, Args_size=0
   0:	getstatic	#11; //Field scala/util/parsing/json/JSON$.MODULE$:Lscala/util/parsing/json/JSON$;
   3:	invokevirtual	#206; //Method scala/util/parsing/json/JSON$.jsonObj:()Lscala/util/parsing/combinator/Parsers$Parser;
   6:	areturn
  Signature: length = 0x2
   00 FFFFFFCF 

public static final scala.util.parsing.combinator.Parsers$Parser root();
  Code:
   Stack=1, Locals=0, Args_size=0
   0:	getstatic	#11; //Field scala/util/parsing/json/JSON$.MODULE$:Lscala/util/parsing/json/JSON$;
   3:	invokevirtual	#210; //Method scala/util/parsing/json/JSON$.root:()Lscala/util/parsing/combinator/Parsers$Parser;
   6:	areturn
  Signature: length = 0x2
   00 FFFFFFCB 

public static final scala.util.parsing.json.Lexer lexical();
  Code:
   Stack=1, Locals=0, Args_size=0
   0:	getstatic	#11; //Field scala/util/parsing/json/JSON$.MODULE$:Lscala/util/parsing/json/JSON$;
   3:	invokevirtual	#214; //Method scala/util/parsing/json/JSON$.lexical:()Lscala/util/parsing/json/Lexer;
   6:	areturn

public static final scala.util.parsing.syntax.Tokens lexical();
  Code:
   Stack=1, Locals=0, Args_size=0
   0:	getstatic	#11; //Field scala/util/parsing/json/JSON$.MODULE$:Lscala/util/parsing/json/JSON$;
   3:	invokevirtual	#217; //Method scala/util/parsing/json/JSON$.lexical:()Lscala/util/parsing/syntax/Tokens;
   6:	areturn

}

