Compiled from "JSON.scala"
public final class scala.util.parsing.json.JSON$ extends scala.util.parsing.json.Parser implements scala.ScalaObject
  SourceFile: "JSON.scala"
  Scala: length = 0x
   
  InnerClass: 
   public abstract Parser=class scala/util/parsing/combinator/Parsers$Parser of class scala/util/parsing/combinator/Parsers
   public Success=class scala/util/parsing/combinator/Parsers$Success of class scala/util/parsing/combinator/Parsers
   public Scanner=class scala/util/parsing/combinator/lexical/Scanners$Scanner of class scala/util/parsing/combinator/lexical/Scanners
   public abstract NoSuccess=class scala/util/parsing/combinator/Parsers$NoSuccess of class scala/util/parsing/combinator/Parsers
   public abstract OnceParser=class scala/util/parsing/combinator/Parsers$OnceParser of class scala/util/parsing/combinator/Parsers
   public abstract ParseResult=class scala/util/parsing/combinator/Parsers$ParseResult of class scala/util/parsing/combinator/Parsers
   public final $anonfun$resolveType$2=class scala/util/parsing/json/JSON$$anonfun$resolveType$2 of class scala/util/parsing/json/JSON
   public final $anonfun$resolveType$1=class scala/util/parsing/json/JSON$$anonfun$resolveType$1 of class scala/util/parsing/json/JSON
   public GenericCanBuildFrom=class scala/collection/generic/TraversableFactory$GenericCanBuildFrom of class scala/collection/generic/TraversableFactory
  minor version: 0
  major version: 49
  Constant pool:
Asciz	SourceFile;
Asciz	JSON.scala;
Asciz	Scala;
Asciz	MODULE$;
Asciz	Lscala/util/parsing/json/JSON$;;
Asciz	<clinit>;
Asciz	()V;
Asciz	Code;
Asciz	scala/util/parsing/json/JSON$;
class	scala/util/parsing/json/JSON$
Asciz	<init>;
NameAndType	"<init>":()V
Method	scala/util/parsing/json/JSON$."<init>":()V
Asciz	parse;
Asciz	(Ljava/lang/String;)Lscala/Option;;
Asciz	LineNumberTable;
Asciz	root;
Asciz	()Lscala/util/parsing/combinator/Parsers$Parser;;
NameAndType	root:()Lscala/util/parsing/combinator/Parsers$Parser;
Method	scala/util/parsing/json/JSON$.root:()Lscala/util/parsing/combinator/Parsers$Parser;
Asciz	scala/util/parsing/combinator/Parsers;
class	scala/util/parsing/combinator/Parsers
Asciz	phrase;
Asciz	(Lscala/util/parsing/combinator/Parsers$Parser;)Lscala/util/parsing/combinator/Parsers$Parser;;
NameAndType	phrase:(Lscala/util/parsing/combinator/Parsers$Parser;)Lscala/util/parsing/combinator/Parsers$Parser;
InterfaceMethod	scala/util/parsing/combinator/Parsers.phrase:(Lscala/util/parsing/combinator/Parsers$Parser;)Lscala/util/parsing/combinator/Parsers$Parser;
Asciz	scala/util/parsing/combinator/lexical/Scanners$Scanner;
class	scala/util/parsing/combinator/lexical/Scanners$Scanner
Asciz	lexical;
Asciz	()Lscala/util/parsing/json/Lexer;;
NameAndType	lexical:()Lscala/util/parsing/json/Lexer;
Method	scala/util/parsing/json/JSON$.lexical:()Lscala/util/parsing/json/Lexer;
Asciz	(Lscala/util/parsing/combinator/lexical/Scanners;Ljava/lang/String;)V;
NameAndType	"<init>":(Lscala/util/parsing/combinator/lexical/Scanners;Ljava/lang/String;)V
Method	scala/util/parsing/combinator/lexical/Scanners$Scanner."<init>":(Lscala/util/parsing/combinator/lexical/Scanners;Ljava/lang/String;)V
Asciz	scala/util/parsing/combinator/Parsers$Parser;
class	scala/util/parsing/combinator/Parsers$Parser
Asciz	apply;
Asciz	(Lscala/util/parsing/input/Reader;)Lscala/util/parsing/combinator/Parsers$ParseResult;;
NameAndType	apply:(Lscala/util/parsing/input/Reader;)Lscala/util/parsing/combinator/Parsers$ParseResult;
Method	scala/util/parsing/combinator/Parsers$Parser.apply:(Lscala/util/parsing/input/Reader;)Lscala/util/parsing/combinator/Parsers$ParseResult;
Asciz	scala/util/parsing/combinator/Parsers$Success;
class	scala/util/parsing/combinator/Parsers$Success
Asciz	result;
Asciz	()Ljava/lang/Object;;
NameAndType	result:()Ljava/lang/Object;
Method	scala/util/parsing/combinator/Parsers$Success.result:()Ljava/lang/Object;
Asciz	scala/collection/immutable/List;
class	scala/collection/immutable/List
Asciz	scala/Some;
class	scala/Some
Asciz	(Ljava/lang/Object;)V;
NameAndType	"<init>":(Ljava/lang/Object;)V
Method	scala/Some."<init>":(Ljava/lang/Object;)V
Asciz	scala/None$;
class	scala/None$
Asciz	Lscala/None$;;
NameAndType	MODULE$:Lscala/None$;
Field	scala/None$.MODULE$:Lscala/None$;
Asciz	this;
Asciz	input;
Asciz	Ljava/lang/String;;
Asciz	temp1;
Asciz	Lscala/util/parsing/combinator/Parsers$ParseResult;;
Asciz	temp2;
Asciz	Lscala/util/parsing/combinator/Parsers$Success;;
Asciz	temp3;
Asciz	Lscala/collection/immutable/List;;
Asciz	LocalVariableTable;
Asciz	(Ljava/lang/String;)Lscala/Option<Lscala/collection/immutable/List<Ljava/lang/Object;>;>;;
Asciz	Signature;
Asciz	parseFull;
NameAndType	parse:(Ljava/lang/String;)Lscala/Option;
Method	scala/util/parsing/json/JSON$.parse:(Ljava/lang/String;)Lscala/Option;
Asciz	x;
Asciz	Ljava/lang/Object;;
NameAndType	x:Ljava/lang/Object;
Field	scala/Some.x:Ljava/lang/Object;
Asciz	resolveType;
Asciz	(Lscala/collection/immutable/List;)Ljava/lang/Object;;
NameAndType	resolveType:(Lscala/collection/immutable/List;)Ljava/lang/Object;
Method	scala/util/parsing/json/JSON$.resolveType:(Lscala/collection/immutable/List;)Ljava/lang/Object;
Asciz	java/lang/Object;
class	java/lang/Object
Asciz	equals;
Asciz	(Ljava/lang/Object;)Z;
NameAndType	equals:(Ljava/lang/Object;)Z
Method	java/lang/Object.equals:(Ljava/lang/Object;)Z
Asciz	scala/MatchError;
class	scala/MatchError
Asciz	scala/Option;
class	scala/Option
Asciz	toString;
Asciz	()Ljava/lang/String;;
NameAndType	toString:()Ljava/lang/String;
Method	scala/Option.toString:()Ljava/lang/String;
Asciz	(Ljava/lang/String;)V;
NameAndType	"<init>":(Ljava/lang/String;)V
Method	scala/MatchError."<init>":(Ljava/lang/String;)V
Asciz	temp6;
Asciz	Lscala/Some;;
Asciz	temp7;
Asciz	temp5;
Asciz	Lscala/Option;;
Asciz	(Ljava/lang/String;)Lscala/Option<Ljava/lang/Object;>;;
Asciz	scala/runtime/ObjectRef;
class	scala/runtime/ObjectRef
Asciz	scala/Predef$;
class	scala/Predef$
Asciz	Lscala/Predef$;;
NameAndType	MODULE$:Lscala/Predef$;
Field	scala/Predef$.MODULE$:Lscala/Predef$;
Asciz	Map;
Asciz	()Lscala/collection/immutable/Map$;;
NameAndType	Map:()Lscala/collection/immutable/Map$;
Method	scala/Predef$.Map:()Lscala/collection/immutable/Map$;
Asciz	scala/Tuple2;
class	scala/Tuple2
Asciz	[Ljava/lang/Object;;
class	"[Ljava/lang/Object;"
Asciz	wrapRefArray;
Asciz	([Ljava/lang/Object;)Lscala/collection/mutable/WrappedArray;;
NameAndType	wrapRefArray:([Ljava/lang/Object;)Lscala/collection/mutable/WrappedArray;
Method	scala/Predef$.wrapRefArray:([Ljava/lang/Object;)Lscala/collection/mutable/WrappedArray;
Asciz	scala/collection/immutable/Map$;
class	scala/collection/immutable/Map$
Asciz	(Lscala/collection/Seq;)Lscala/collection/Map;;
NameAndType	apply:(Lscala/collection/Seq;)Lscala/collection/Map;
Method	scala/collection/immutable/Map$.apply:(Lscala/collection/Seq;)Lscala/collection/Map;
Asciz	scala/collection/immutable/Map;
class	scala/collection/immutable/Map
Method	scala/runtime/ObjectRef."<init>":(Ljava/lang/Object;)V
Asciz	scala/util/parsing/json/JSON$$anonfun$resolveType$1;
class	scala/util/parsing/json/JSON$$anonfun$resolveType$1
Asciz	(Lscala/runtime/ObjectRef;)V;
NameAndType	"<init>":(Lscala/runtime/ObjectRef;)V
Method	scala/util/parsing/json/JSON$$anonfun$resolveType$1."<init>":(Lscala/runtime/ObjectRef;)V
Asciz	scala/collection/LinearSeqLike;
class	scala/collection/LinearSeqLike
Asciz	forall;
Asciz	(Lscala/Function1;)Z;
NameAndType	forall:(Lscala/Function1;)Z
InterfaceMethod	scala/collection/LinearSeqLike.forall:(Lscala/Function1;)Z
Asciz	elem;
NameAndType	elem:Ljava/lang/Object;
Field	scala/runtime/ObjectRef.elem:Ljava/lang/Object;
Asciz	scala/util/parsing/json/JSON$$anonfun$resolveType$2;
class	scala/util/parsing/json/JSON$$anonfun$resolveType$2
Method	scala/util/parsing/json/JSON$$anonfun$resolveType$2."<init>":()V
Asciz	scala/collection/immutable/List$;
class	scala/collection/immutable/List$
Asciz	Lscala/collection/immutable/List$;;
NameAndType	MODULE$:Lscala/collection/immutable/List$;
Field	scala/collection/immutable/List$.MODULE$:Lscala/collection/immutable/List$;
Asciz	scala/collection/generic/TraversableFactory$GenericCanBuildFrom;
class	scala/collection/generic/TraversableFactory$GenericCanBuildFrom
Asciz	(Lscala/collection/generic/TraversableFactory;)V;
NameAndType	"<init>":(Lscala/collection/generic/TraversableFactory;)V
Method	scala/collection/generic/TraversableFactory$GenericCanBuildFrom."<init>":(Lscala/collection/generic/TraversableFactory;)V
Asciz	scala/collection/TraversableLike;
class	scala/collection/TraversableLike
Asciz	map;
Asciz	(Lscala/Function1;Lscala/collection/generic/CanBuildFrom;)Ljava/lang/Object;;
NameAndType	map:(Lscala/Function1;Lscala/collection/generic/CanBuildFrom;)Ljava/lang/Object;
InterfaceMethod	scala/collection/TraversableLike.map:(Lscala/Function1;Lscala/collection/generic/CanBuildFrom;)Ljava/lang/Object;
Asciz	objMap$1;
Asciz	Lscala/runtime/ObjectRef;;
Asciz	(Lscala/collection/immutable/List<Ljava/lang/Object;>;)Ljava/lang/Object;;
Asciz	globalNumberParser_$eq;
Asciz	(Lscala/Function1;)V;
Asciz	defaultNumberParser_$eq;
NameAndType	defaultNumberParser_$eq:(Lscala/Function1;)V
Method	scala/util/parsing/json/JSON$.defaultNumberParser_$eq:(Lscala/Function1;)V
Asciz	f;
Asciz	Lscala/Function1;;
Asciz	(Lscala/Function1<Ljava/lang/String;Ljava/lang/Object;>;)V;
Asciz	globalNumberParser;
Asciz	()Lscala/Function1;;
Asciz	defaultNumberParser;
NameAndType	defaultNumberParser:()Lscala/Function1;
Method	scala/util/parsing/json/JSON$.defaultNumberParser:()Lscala/Function1;
Asciz	()Lscala/Function1<Ljava/lang/String;Ljava/lang/Object;>;;
Asciz	perThreadNumberParser_$eq;
Asciz	numberParser;
Asciz	()Ljava/lang/ThreadLocal;;
NameAndType	numberParser:()Ljava/lang/ThreadLocal;
Method	scala/util/parsing/json/JSON$.numberParser:()Ljava/lang/ThreadLocal;
Asciz	java/lang/ThreadLocal;
class	java/lang/ThreadLocal
Asciz	set;
NameAndType	set:(Ljava/lang/Object;)V
Method	java/lang/ThreadLocal.set:(Ljava/lang/Object;)V
Asciz	perThreadNumberParser;
Asciz	get;
NameAndType	get:()Ljava/lang/Object;
Method	java/lang/ThreadLocal.get:()Ljava/lang/Object;
Asciz	scala/Function1;
class	scala/Function1
Asciz	scala/util/parsing/json/Parser;
class	scala/util/parsing/json/Parser
Method	scala/util/parsing/json/Parser."<init>":()V
NameAndType	MODULE$:Lscala/util/parsing/json/JSON$;
Field	scala/util/parsing/json/JSON$.MODULE$:Lscala/util/parsing/json/JSON$;
Asciz	InnerClasses;
Asciz	Parser;
Asciz	Success;
Asciz	scala/util/parsing/combinator/lexical/Scanners;
class	scala/util/parsing/combinator/lexical/Scanners
Asciz	Scanner;
Asciz	scala/util/parsing/combinator/Parsers$NoSuccess;
class	scala/util/parsing/combinator/Parsers$NoSuccess
Asciz	NoSuccess;
Asciz	scala/util/parsing/combinator/Parsers$OnceParser;
class	scala/util/parsing/combinator/Parsers$OnceParser
Asciz	OnceParser;
Asciz	scala/util/parsing/combinator/Parsers$ParseResult;
class	scala/util/parsing/combinator/Parsers$ParseResult
Asciz	ParseResult;
Asciz	scala/util/parsing/json/JSON;
class	scala/util/parsing/json/JSON
Asciz	$anonfun$resolveType$2;
Asciz	$anonfun$resolveType$1;
Asciz	scala/collection/generic/TraversableFactory;
class	scala/collection/generic/TraversableFactory
Asciz	GenericCanBuildFrom;
Asciz	scala/ScalaObject;
class	scala/ScalaObject

{
public static final scala.util.parsing.json.JSON$ MODULE$;
  Signature: Lscala/util/parsing/json/JSON$;

public static {};
  Signature: ()V
  Code:
   Stack=1, Locals=0, Args_size=0
	new	class scala/util/parsing/json/JSON$
	invokespecial	Method "<init>":()V
	return
  Labels:

public scala.Option parse(java.lang.String);
  Signature: (Ljava/lang/String;)Lscala/Option;
  Code:
   Stack=5, Locals=5, Args_size=2
	aload_0
	aload_0
	invokevirtual	Method root:()Lscala/util/parsing/combinator/Parsers$Parser;
	invokeinterface	InterfaceMethod scala/util/parsing/combinator/Parsers.phrase:(Lscala/util/parsing/combinator/Parsers$Parser;)Lscala/util/parsing/combinator/Parsers$Parser;
	new	class scala/util/parsing/combinator/lexical/Scanners$Scanner
	dup
	aload_0
	invokevirtual	Method lexical:()Lscala/util/parsing/json/Lexer;
	aload_1
	invokespecial	Method scala/util/parsing/combinator/lexical/Scanners$Scanner."<init>":(Lscala/util/parsing/combinator/lexical/Scanners;Ljava/lang/String;)V
	invokevirtual	Method scala/util/parsing/combinator/Parsers$Parser.apply:(Lscala/util/parsing/input/Reader;)Lscala/util/parsing/combinator/Parsers$ParseResult;
	astore_2
	aload_2
	instanceof	class scala/util/parsing/combinator/Parsers$Success
	ifeq	l1 // getstatic
	aload_2
	checkcast	class scala/util/parsing/combinator/Parsers$Success
	astore_3
	aload_3
	invokevirtual	Method scala/util/parsing/combinator/Parsers$Success.result:()Ljava/lang/Object;
	checkcast	class scala/collection/immutable/List
	astore	4
	new	class scala/Some
	dup
	aload	4
	invokespecial	Method scala/Some."<init>":(Ljava/lang/Object;)V
	goto	l2 // areturn
l1	getstatic	Field scala/None$.MODULE$:Lscala/None$;
l2	areturn
  Labels:
   	l1 = 59 // getstatic
   	l2 = 62 // areturn
  LocalVariableTable: 
   Start  Length  Slot  Name   Signature
   0      63      0    this       Lscala/util/parsing/json/JSON$;
   0      63      1    input       Ljava/lang/String;
   26      37      2    temp1       Lscala/util/parsing/combinator/Parsers$ParseResult;
   38      18      3    temp2       Lscala/util/parsing/combinator/Parsers$Success;
   47      9      4    temp3       Lscala/collection/immutable/List;

  Signature: length = 0x2
   00 46 

public scala.Option parseFull(java.lang.String);
  Signature: (Ljava/lang/String;)Lscala/Option;
  Code:
   Stack=4, Locals=5, Args_size=2
	aload_0
	aload_1
	invokevirtual	Method parse:(Ljava/lang/String;)Lscala/Option;
	astore	4
	aload	4
	instanceof	class scala/Some
	ifeq	l1 // getstatic
	aload	4
	checkcast	class scala/Some
	astore_2
	aload_2
	getfield	Field scala/Some.x:Ljava/lang/Object;
	checkcast	class scala/collection/immutable/List
	astore_3
	new	class scala/Some
	dup
	aload_0
	aload_3
	invokevirtual	Method resolveType:(Lscala/collection/immutable/List;)Ljava/lang/Object;
	invokespecial	Method scala/Some."<init>":(Ljava/lang/Object;)V
	goto	l2 // areturn
l1	getstatic	Field scala/None$.MODULE$:Lscala/None$;
	dup
	ifnonnull	l3 // aload
	pop
	aload	4
	ifnull	l4 // getstatic
	goto	l5 // new
l3	aload	4
	invokevirtual	Method java/lang/Object.equals:(Ljava/lang/Object;)Z
	ifeq	l5 // new
l4	getstatic	Field scala/None$.MODULE$:Lscala/None$;
l2	areturn
l5	new	class scala/MatchError
	dup
	aload	4
	invokevirtual	Method scala/Option.toString:()Ljava/lang/String;
	invokespecial	Method scala/MatchError."<init>":(Ljava/lang/String;)V
	athrow
  Labels:
   	l1 = 44 // getstatic
   	l3 = 60 // aload
   	l4 = 68 // getstatic
   	l2 = 71 // areturn
   	l5 = 72 // new
  LocalVariableTable: 
   Start  Length  Slot  Name   Signature
   0      85      0    this       Lscala/util/parsing/json/JSON$;
   0      85      1    input       Ljava/lang/String;
   21      20      2    temp6       Lscala/Some;
   29      12      3    temp7       Lscala/collection/immutable/List;
   7      78      4    temp5       Lscala/Option;

  Signature: length = 0x2
   00 69 

public java.lang.Object resolveType(scala.collection.immutable.List);
  Signature: (Lscala/collection/immutable/List;)Ljava/lang/Object;
  Code:
   Stack=5, Locals=4, Args_size=2
	new	class scala/runtime/ObjectRef
	dup
	getstatic	Field scala/Predef$.MODULE$:Lscala/Predef$;
	invokevirtual	Method scala/Predef$.Map:()Lscala/collection/immutable/Map$;
	getstatic	Field scala/Predef$.MODULE$:Lscala/Predef$;
	iconst_0
	anewarray	class scala/Tuple2
	checkcast	class "[Ljava/lang/Object;"
	invokevirtual	Method scala/Predef$.wrapRefArray:([Ljava/lang/Object;)Lscala/collection/mutable/WrappedArray;
	invokevirtual	Method scala/collection/immutable/Map$.apply:(Lscala/collection/Seq;)Lscala/collection/Map;
	checkcast	class scala/collection/immutable/Map
	invokespecial	Method scala/runtime/ObjectRef."<init>":(Ljava/lang/Object;)V
	astore_2
	aload_1
	new	class scala/util/parsing/json/JSON$$anonfun$resolveType$1
	dup
	aload_2
	invokespecial	Method scala/util/parsing/json/JSON$$anonfun$resolveType$1."<init>":(Lscala/runtime/ObjectRef;)V
	invokeinterface	InterfaceMethod scala/collection/LinearSeqLike.forall:(Lscala/Function1;)Z
	ifeq	l1 // aload_1
	aload_2
	getfield	Field scala/runtime/ObjectRef.elem:Ljava/lang/Object;
	checkcast	class scala/collection/immutable/Map
	goto	l2 // areturn
l1	aload_1
	new	class scala/util/parsing/json/JSON$$anonfun$resolveType$2
	dup
	invokespecial	Method scala/util/parsing/json/JSON$$anonfun$resolveType$2."<init>":()V
	getstatic	Field scala/collection/immutable/List$.MODULE$:Lscala/collection/immutable/List$;
	astore_3
	new	class scala/collection/generic/TraversableFactory$GenericCanBuildFrom
	dup
	aload_3
	invokespecial	Method scala/collection/generic/TraversableFactory$GenericCanBuildFrom."<init>":(Lscala/collection/generic/TraversableFactory;)V
	invokeinterface	InterfaceMethod scala/collection/TraversableLike.map:(Lscala/Function1;Lscala/collection/generic/CanBuildFrom;)Ljava/lang/Object;
l2	areturn
  Labels:
   	l1 = 60 // aload_1
   	l2 = 85 // areturn
  LocalVariableTable: 
   Start  Length  Slot  Name   Signature
   0      86      0    this       Lscala/util/parsing/json/JSON$;
   0      86      1    input       Lscala/collection/immutable/List;
   33      53      2    objMap$1       Lscala/runtime/ObjectRef;

  Signature: length = 0x2
   00 FFFFFFA8 

public void globalNumberParser_$eq(scala.Function1);
  Signature: (Lscala/Function1;)V
  Code:
   Stack=2, Locals=2, Args_size=2
	aload_0
	aload_1
	invokevirtual	Method defaultNumberParser_$eq:(Lscala/Function1;)V
	return
  Labels:
  LocalVariableTable: 
   Start  Length  Slot  Name   Signature
   0      6      0    this       Lscala/util/parsing/json/JSON$;
   0      6      1    f       Lscala/Function1;

  Signature: length = 0x2
   00 FFFFFFB0 

public scala.Function1 globalNumberParser();
  Signature: ()Lscala/Function1;
  Code:
   Stack=1, Locals=1, Args_size=1
	aload_0
	invokevirtual	Method defaultNumberParser:()Lscala/Function1;
	areturn
  Labels:
  Signature: length = 0x2
   00 FFFFFFB6 

public void perThreadNumberParser_$eq(scala.Function1);
  Signature: (Lscala/Function1;)V
  Code:
   Stack=2, Locals=2, Args_size=2
	aload_0
	invokevirtual	Method numberParser:()Ljava/lang/ThreadLocal;
	aload_1
	invokevirtual	Method java/lang/ThreadLocal.set:(Ljava/lang/Object;)V
	return
  Labels:
  LocalVariableTable: 
   Start  Length  Slot  Name   Signature
   0      9      0    this       Lscala/util/parsing/json/JSON$;
   0      9      1    f       Lscala/Function1;

  Signature: length = 0x2
   00 FFFFFFB0 

public scala.Function1 perThreadNumberParser();
  Signature: ()Lscala/Function1;
  Code:
   Stack=1, Locals=1, Args_size=1
	aload_0
	invokevirtual	Method numberParser:()Ljava/lang/ThreadLocal;
	invokevirtual	Method java/lang/ThreadLocal.get:()Ljava/lang/Object;
	checkcast	class scala/Function1
	areturn
  Labels:
  Signature: length = 0x2
   00 FFFFFFB6 

private scala.util.parsing.json.JSON$();
  Signature: ()V
  Code:
   Stack=1, Locals=1, Args_size=1
	aload_0
	invokespecial	Method scala/util/parsing/json/Parser."<init>":()V
	aload_0
	putstatic	Field MODULE$:Lscala/util/parsing/json/JSON$;
	return
  Labels:

}

