Compiled from "JSON.scala"
public final class scala.util.parsing.json.JSON$$anonfun$resolveType$1 extends scala.runtime.AbstractFunction1 implements java.io.Serializable
  SourceFile: "JSON.scala"
  Scala: length = 0x
   
  InnerClass: 
   public ArrowAssoc=class scala/Predef$ArrowAssoc of class scala/Predef
   public final $anonfun$resolveType$1=class scala/util/parsing/json/JSON$$anonfun$resolveType$1 of class scala/util/parsing/json/JSON
  minor version: 0
  major version: 49
  Constant pool:
Asciz	SourceFile;
Asciz	JSON.scala;
Asciz	<clinit>;
Asciz	()V;
Asciz	Code;
Asciz	serialVersionUID;
Asciz	J;
Asciz	scala/util/parsing/json/JSON$$anonfun$resolveType$1;
class	scala/util/parsing/json/JSON$$anonfun$resolveType$1
NameAndType	serialVersionUID:J
Field	scala/util/parsing/json/JSON$$anonfun$resolveType$1.serialVersionUID:J
Asciz	objMap$1;
Asciz	Lscala/runtime/ObjectRef;;
Asciz	<init>;
Asciz	(Lscala/runtime/ObjectRef;)V;
Asciz	LineNumberTable;
NameAndType	objMap$1:Lscala/runtime/ObjectRef;
Field	scala/util/parsing/json/JSON$$anonfun$resolveType$1.objMap$1:Lscala/runtime/ObjectRef;
Asciz	scala/runtime/AbstractFunction1;
class	scala/runtime/AbstractFunction1
NameAndType	"<init>":()V
Method	scala/runtime/AbstractFunction1."<init>":()V
Asciz	apply;
Asciz	(Ljava/lang/Object;)Ljava/lang/Object;;
Asciz	(Ljava/lang/Object;)Z;
NameAndType	apply:(Ljava/lang/Object;)Z
Method	scala/util/parsing/json/JSON$$anonfun$resolveType$1.apply:(Ljava/lang/Object;)Z
Asciz	scala/runtime/BoxesRunTime;
class	scala/runtime/BoxesRunTime
Asciz	boxToBoolean;
Asciz	(Z)Ljava/lang/Boolean;;
NameAndType	boxToBoolean:(Z)Ljava/lang/Boolean;
Method	scala/runtime/BoxesRunTime.boxToBoolean:(Z)Ljava/lang/Boolean;
Asciz	this;
Asciz	Lscala/util/parsing/json/JSON$$anonfun$resolveType$1;;
Asciz	v1;
Asciz	Ljava/lang/Object;;
Asciz	LocalVariableTable;
Asciz	scala/Tuple2;
class	scala/Tuple2
Asciz	_1;
Asciz	()Ljava/lang/Object;;
NameAndType	_1:()Ljava/lang/Object;
Method	scala/Tuple2._1:()Ljava/lang/Object;
Asciz	_2;
NameAndType	_2:()Ljava/lang/Object;
Method	scala/Tuple2._2:()Ljava/lang/Object;
Asciz	java/lang/String;
class	java/lang/String
Asciz	scala/collection/immutable/List;
class	scala/collection/immutable/List
Asciz	scala/runtime/ObjectRef;
class	scala/runtime/ObjectRef
Asciz	elem;
NameAndType	elem:Ljava/lang/Object;
Field	scala/runtime/ObjectRef.elem:Ljava/lang/Object;
Asciz	scala/collection/immutable/Map;
class	scala/collection/immutable/Map
Asciz	scala/Predef$ArrowAssoc;
class	scala/Predef$ArrowAssoc
Asciz	(Ljava/lang/Object;)V;
NameAndType	"<init>":(Ljava/lang/Object;)V
Method	scala/Predef$ArrowAssoc."<init>":(Ljava/lang/Object;)V
Asciz	scala/util/parsing/json/JSON$;
class	scala/util/parsing/json/JSON$
Asciz	MODULE$;
Asciz	Lscala/util/parsing/json/JSON$;;
NameAndType	MODULE$:Lscala/util/parsing/json/JSON$;
Field	scala/util/parsing/json/JSON$.MODULE$:Lscala/util/parsing/json/JSON$;
Asciz	resolveType;
Asciz	(Lscala/collection/immutable/List;)Ljava/lang/Object;;
NameAndType	resolveType:(Lscala/collection/immutable/List;)Ljava/lang/Object;
Method	scala/util/parsing/json/JSON$.resolveType:(Lscala/collection/immutable/List;)Ljava/lang/Object;
Asciz	$minus$greater;
Asciz	(Ljava/lang/Object;)Lscala/Tuple2;;
NameAndType	$minus$greater:(Ljava/lang/Object;)Lscala/Tuple2;
Method	scala/Predef$ArrowAssoc.$minus$greater:(Ljava/lang/Object;)Lscala/Tuple2;
Asciz	$plus;
Asciz	(Lscala/Tuple2;)Lscala/collection/immutable/Map;;
NameAndType	$plus:(Lscala/Tuple2;)Lscala/collection/immutable/Map;
InterfaceMethod	scala/collection/immutable/Map.$plus:(Lscala/Tuple2;)Lscala/collection/immutable/Map;
Asciz	scala/MatchError;
class	scala/MatchError
Asciz	java/lang/Object;
class	java/lang/Object
Asciz	toString;
Asciz	()Ljava/lang/String;;
NameAndType	toString:()Ljava/lang/String;
Method	java/lang/Object.toString:()Ljava/lang/String;
Asciz	(Ljava/lang/String;)V;
NameAndType	"<init>":(Ljava/lang/String;)V
Method	scala/MatchError."<init>":(Ljava/lang/String;)V
Asciz	temp10;
Asciz	Lscala/Tuple2;;
Asciz	temp11;
Asciz	temp14;
Asciz	Lscala/collection/immutable/List;;
Asciz	temp13;
Asciz	Ljava/lang/String;;
Asciz	temp12;
Asciz	Scala;
Asciz	InnerClasses;
Asciz	scala/Predef;
class	scala/Predef
Asciz	ArrowAssoc;
Asciz	scala/util/parsing/json/JSON;
class	scala/util/parsing/json/JSON
Asciz	$anonfun$resolveType$1;
Asciz	java/io/Serializable;
class	java/io/Serializable

{
public static final long serialVersionUID;
  Signature: J

private final scala.runtime.ObjectRef objMap$1;
  Signature: Lscala/runtime/ObjectRef;

public static {};
  Signature: ()V
  Code:
   Stack=2, Locals=0, Args_size=0
	lconst_0
	putstatic	Field serialVersionUID:J
	return
  Labels:

public scala.util.parsing.json.JSON$$anonfun$resolveType$1(scala.runtime.ObjectRef);
  Signature: (Lscala/runtime/ObjectRef;)V
  Code:
   Stack=2, Locals=2, Args_size=2
	aload_0
	aload_1
	putfield	Field objMap$1:Lscala/runtime/ObjectRef;
	aload_0
	invokespecial	Method scala/runtime/AbstractFunction1."<init>":()V
	return
  Labels:

public final java.lang.Object apply(java.lang.Object);
  Signature: (Ljava/lang/Object;)Ljava/lang/Object;
  Code:
   Stack=2, Locals=3, Args_size=2
	aload_0
	aload_1
	invokevirtual	Method apply:(Ljava/lang/Object;)Z
	istore_2
	iload_2
	invokestatic	Method scala/runtime/BoxesRunTime.boxToBoolean:(Z)Ljava/lang/Boolean;
	areturn
  Labels:
  LocalVariableTable: 
   Start  Length  Slot  Name   Signature
   0      11      0    this       Lscala/util/parsing/json/JSON$$anonfun$resolveType$1;
   0      11      1    v1       Ljava/lang/Object;


public final boolean apply(java.lang.Object);
  Signature: (Ljava/lang/Object;)Z
  Code:
   Stack=5, Locals=7, Args_size=2
	aload_1
	instanceof	class scala/Tuple2
	ifeq	l1 // iconst_1
	aload_1
	checkcast	class scala/Tuple2
	astore_2
	aload_2
	invokevirtual	Method scala/Tuple2._1:()Ljava/lang/Object;
	astore_3
	aload_2
	invokevirtual	Method scala/Tuple2._2:()Ljava/lang/Object;
	astore	6
	aload_3
	instanceof	class java/lang/String
	ifeq	l2 // iconst_1
	aload_3
	checkcast	class java/lang/String
	astore	5
	aload	6
	instanceof	class scala/collection/immutable/List
	ifeq	l3 // iconst_1
	aload	6
	checkcast	class scala/collection/immutable/List
	astore	4
	iconst_1
	ifeq	l4 // new
	aload_0
	getfield	Field objMap$1:Lscala/runtime/ObjectRef;
	aload_0
	getfield	Field objMap$1:Lscala/runtime/ObjectRef;
	getfield	Field scala/runtime/ObjectRef.elem:Ljava/lang/Object;
	checkcast	class scala/collection/immutable/Map
	new	class scala/Predef$ArrowAssoc
	dup
	aload	5
	invokespecial	Method scala/Predef$ArrowAssoc."<init>":(Ljava/lang/Object;)V
	getstatic	Field scala/util/parsing/json/JSON$.MODULE$:Lscala/util/parsing/json/JSON$;
	aload	4
	invokevirtual	Method scala/util/parsing/json/JSON$.resolveType:(Lscala/collection/immutable/List;)Ljava/lang/Object;
	invokevirtual	Method scala/Predef$ArrowAssoc.$minus$greater:(Ljava/lang/Object;)Lscala/Tuple2;
	invokeinterface	InterfaceMethod scala/collection/immutable/Map.$plus:(Lscala/Tuple2;)Lscala/collection/immutable/Map;
	putfield	Field scala/runtime/ObjectRef.elem:Ljava/lang/Object;
	iconst_1
	goto	l5 // ireturn
l4	new	class scala/MatchError
	dup
	aload_1
	invokevirtual	Method java/lang/Object.toString:()Ljava/lang/String;
	invokespecial	Method scala/MatchError."<init>":(Ljava/lang/String;)V
	athrow
l3	iconst_1
	ifeq	l6 // new
	aload_0
	getfield	Field objMap$1:Lscala/runtime/ObjectRef;
	aload_0
	getfield	Field objMap$1:Lscala/runtime/ObjectRef;
	getfield	Field scala/runtime/ObjectRef.elem:Ljava/lang/Object;
	checkcast	class scala/collection/immutable/Map
	new	class scala/Predef$ArrowAssoc
	dup
	aload	5
	invokespecial	Method scala/Predef$ArrowAssoc."<init>":(Ljava/lang/Object;)V
	aload	6
	invokevirtual	Method scala/Predef$ArrowAssoc.$minus$greater:(Ljava/lang/Object;)Lscala/Tuple2;
	invokeinterface	InterfaceMethod scala/collection/immutable/Map.$plus:(Lscala/Tuple2;)Lscala/collection/immutable/Map;
	putfield	Field scala/runtime/ObjectRef.elem:Ljava/lang/Object;
	iconst_1
	goto	l5 // ireturn
l6	new	class scala/MatchError
	dup
	aload_1
	invokevirtual	Method java/lang/Object.toString:()Ljava/lang/String;
	invokespecial	Method scala/MatchError."<init>":(Ljava/lang/String;)V
	athrow
l2	iconst_1
	ifeq	l7 // new
	iconst_0
	goto	l5 // ireturn
l7	new	class scala/MatchError
	dup
	aload_1
	invokevirtual	Method java/lang/Object.toString:()Ljava/lang/String;
	invokespecial	Method scala/MatchError."<init>":(Ljava/lang/String;)V
	athrow
l1	iconst_1
	ifeq	l8 // new
	iconst_0
l5	ireturn
l8	new	class scala/MatchError
	dup
	aload_1
	invokevirtual	Method java/lang/Object.toString:()Ljava/lang/String;
	invokespecial	Method scala/MatchError."<init>":(Ljava/lang/String;)V
	athrow
  Labels:
   	l4 = 101 // new
   	l3 = 113 // iconst_1
   	l6 = 157 // new
   	l2 = 169 // iconst_1
   	l7 = 177 // new
   	l1 = 189 // iconst_1
   	l5 = 194 // ireturn
   	l8 = 195 // new
  LocalVariableTable: 
   Start  Length  Slot  Name   Signature
   0      207      0    this       Lscala/util/parsing/json/JSON$$anonfun$resolveType$1;
   12      177      2    temp10       Lscala/Tuple2;
   17      172      3    temp11       Ljava/lang/Object;
   51      62      4    temp14       Lscala/collection/immutable/List;
   36      133      5    temp13       Ljava/lang/String;
   23      166      6    temp12       Ljava/lang/Object;


}

