Compiled from "Lexer.scala"
public final class scala.util.parsing.json.Lexer$$anonfun$token$1 extends scala.runtime.AbstractFunction0 implements java.io.Serializable
  SourceFile: "Lexer.scala"
  Scala: length = 0x
   
  InnerClass: 
   public abstract Parser=class scala/util/parsing/combinator/Parsers$Parser of class scala/util/parsing/combinator/Parsers
   public final $anonfun$token$1=class scala/util/parsing/json/Lexer$$anonfun$token$1 of class scala/util/parsing/json/Lexer
   public final $anonfun$apply$2=class scala/util/parsing/json/Lexer$$anonfun$token$1$$anonfun$apply$2 of class scala/util/parsing/json/Lexer$$anonfun$token$1
   public final $anonfun$apply$1=class scala/util/parsing/json/Lexer$$anonfun$token$1$$anonfun$apply$1 of class scala/util/parsing/json/Lexer$$anonfun$token$1
  minor version: 0
  major version: 49
  Constant pool:
Asciz	SourceFile;
Asciz	Lexer.scala;
Asciz	<clinit>;
Asciz	()V;
Asciz	Code;
Asciz	serialVersionUID;
Asciz	J;
Asciz	scala/util/parsing/json/Lexer$$anonfun$token$1;
class	scala/util/parsing/json/Lexer$$anonfun$token$1
NameAndType	serialVersionUID:J
Field	scala/util/parsing/json/Lexer$$anonfun$token$1.serialVersionUID:J
Asciz	$outer;
Asciz	Lscala/util/parsing/json/Lexer;;
Asciz	apply;
Asciz	()Lscala/util/parsing/combinator/Parsers$Parser;;
Asciz	LineNumberTable;
NameAndType	$outer:Lscala/util/parsing/json/Lexer;
Field	scala/util/parsing/json/Lexer$$anonfun$token$1.$outer:Lscala/util/parsing/json/Lexer;
Asciz	scala/util/parsing/json/Lexer;
class	scala/util/parsing/json/Lexer
Asciz	number;
NameAndType	number:()Lscala/util/parsing/combinator/Parsers$Parser;
Method	scala/util/parsing/json/Lexer.number:()Lscala/util/parsing/combinator/Parsers$Parser;
Asciz	scala/util/parsing/json/Lexer$$anonfun$token$1$$anonfun$apply$1;
class	scala/util/parsing/json/Lexer$$anonfun$token$1$$anonfun$apply$1
Asciz	<init>;
Asciz	(Lscala/util/parsing/json/Lexer$$anonfun$token$1;)V;
NameAndType	"<init>":(Lscala/util/parsing/json/Lexer$$anonfun$token$1;)V
Method	scala/util/parsing/json/Lexer$$anonfun$token$1$$anonfun$apply$1."<init>":(Lscala/util/parsing/json/Lexer$$anonfun$token$1;)V
Asciz	scala/util/parsing/combinator/Parsers$Parser;
class	scala/util/parsing/combinator/Parsers$Parser
Asciz	$tilde;
Asciz	(Lscala/Function0;)Lscala/util/parsing/combinator/Parsers$Parser;;
NameAndType	$tilde:(Lscala/Function0;)Lscala/util/parsing/combinator/Parsers$Parser;
Method	scala/util/parsing/combinator/Parsers$Parser.$tilde:(Lscala/Function0;)Lscala/util/parsing/combinator/Parsers$Parser;
Asciz	scala/util/parsing/json/Lexer$$anonfun$token$1$$anonfun$apply$2;
class	scala/util/parsing/json/Lexer$$anonfun$token$1$$anonfun$apply$2
Method	scala/util/parsing/json/Lexer$$anonfun$token$1$$anonfun$apply$2."<init>":(Lscala/util/parsing/json/Lexer$$anonfun$token$1;)V
Asciz	$up$up;
Asciz	(Lscala/Function1;)Lscala/util/parsing/combinator/Parsers$Parser;;
NameAndType	$up$up:(Lscala/Function1;)Lscala/util/parsing/combinator/Parsers$Parser;
Method	scala/util/parsing/combinator/Parsers$Parser.$up$up:(Lscala/Function1;)Lscala/util/parsing/combinator/Parsers$Parser;
Asciz	()Lscala/util/parsing/combinator/Parsers$Parser<Lscala/util/parsing/combinator/token/Tokens$ErrorToken;>;;
Asciz	Signature;
Asciz	scala$util$parsing$json$Lexer$$anonfun$$$outer;
Asciz	()Lscala/util/parsing/json/Lexer;;
Asciz	()Ljava/lang/Object;;
NameAndType	apply:()Lscala/util/parsing/combinator/Parsers$Parser;
Method	scala/util/parsing/json/Lexer$$anonfun$token$1.apply:()Lscala/util/parsing/combinator/Parsers$Parser;
Asciz	(Lscala/util/parsing/json/Lexer;)V;
Asciz	java/lang/NullPointerException;
class	java/lang/NullPointerException
NameAndType	"<init>":()V
Method	java/lang/NullPointerException."<init>":()V
Asciz	scala/runtime/AbstractFunction0;
class	scala/runtime/AbstractFunction0
Method	scala/runtime/AbstractFunction0."<init>":()V
Asciz	this;
Asciz	Lscala/util/parsing/json/Lexer$$anonfun$token$1;;
Asciz	LocalVariableTable;
Asciz	Scala;
Asciz	InnerClasses;
Asciz	scala/util/parsing/combinator/Parsers;
class	scala/util/parsing/combinator/Parsers
Asciz	Parser;
Asciz	$anonfun$token$1;
Asciz	$anonfun$apply$2;
Asciz	$anonfun$apply$1;
Asciz	java/io/Serializable;
class	java/io/Serializable

{
public static final long serialVersionUID;
  Signature: J

private final scala.util.parsing.json.Lexer $outer;
  Signature: Lscala/util/parsing/json/Lexer;

public static {};
  Signature: ()V
  Code:
   Stack=2, Locals=0, Args_size=0
	lconst_0
	putstatic	Field serialVersionUID:J
	return
  Labels:

public final scala.util.parsing.combinator.Parsers$Parser apply();
  Signature: ()Lscala/util/parsing/combinator/Parsers$Parser;
  Code:
   Stack=4, Locals=1, Args_size=1
	aload_0
	getfield	Field $outer:Lscala/util/parsing/json/Lexer;
	invokevirtual	Method scala/util/parsing/json/Lexer.number:()Lscala/util/parsing/combinator/Parsers$Parser;
	new	class scala/util/parsing/json/Lexer$$anonfun$token$1$$anonfun$apply$1
	dup
	aload_0
	invokespecial	Method scala/util/parsing/json/Lexer$$anonfun$token$1$$anonfun$apply$1."<init>":(Lscala/util/parsing/json/Lexer$$anonfun$token$1;)V
	invokevirtual	Method scala/util/parsing/combinator/Parsers$Parser.$tilde:(Lscala/Function0;)Lscala/util/parsing/combinator/Parsers$Parser;
	new	class scala/util/parsing/json/Lexer$$anonfun$token$1$$anonfun$apply$2
	dup
	aload_0
	invokespecial	Method scala/util/parsing/json/Lexer$$anonfun$token$1$$anonfun$apply$2."<init>":(Lscala/util/parsing/json/Lexer$$anonfun$token$1;)V
	invokevirtual	Method scala/util/parsing/combinator/Parsers$Parser.$up$up:(Lscala/Function1;)Lscala/util/parsing/combinator/Parsers$Parser;
	areturn
  Labels:
  Signature: length = 0x2
   00 2B 

public scala.util.parsing.json.Lexer scala$util$parsing$json$Lexer$$anonfun$$$outer();
  Signature: ()Lscala/util/parsing/json/Lexer;
  Code:
   Stack=1, Locals=1, Args_size=1
	aload_0
	getfield	Field $outer:Lscala/util/parsing/json/Lexer;
	areturn
  Labels:

public final java.lang.Object apply();
  Signature: ()Ljava/lang/Object;
  Code:
   Stack=1, Locals=1, Args_size=1
	aload_0
	invokevirtual	Method apply:()Lscala/util/parsing/combinator/Parsers$Parser;
	areturn
  Labels:

public scala.util.parsing.json.Lexer$$anonfun$token$1(scala.util.parsing.json.Lexer);
  Signature: (Lscala/util/parsing/json/Lexer;)V
  Code:
   Stack=2, Locals=2, Args_size=2
	aload_1
	ifnonnull	l1 // aload_0
	new	class java/lang/NullPointerException
	dup
	invokespecial	Method java/lang/NullPointerException."<init>":()V
	athrow
l1	aload_0
	aload_1
	putfield	Field $outer:Lscala/util/parsing/json/Lexer;
	aload_0
	invokespecial	Method scala/runtime/AbstractFunction0."<init>":()V
	return
  Labels:
   	l1 = 12 // aload_0
  LocalVariableTable: 
   Start  Length  Slot  Name   Signature
   0      22      0    this       Lscala/util/parsing/json/Lexer$$anonfun$token$1;
   0      22      1    $outer       Lscala/util/parsing/json/Lexer;


}

