Compiled from "Lexer.scala"
public class scala.util.parsing.json.Lexer extends scala.util.parsing.combinator.lexical.StdLexical implements scala.util.parsing.combinator.ImplicitConversions,scala.ScalaObject
  SourceFile: "Lexer.scala"
  ScalaSig: length = 0x44E
   05 00 FFFFFF81 2C 06 08 01 02 FFFFFF84 FFFFFF80 FFFFFF80 FFFFFF80 00 0B 02 05
   4C 65 78 65 72 0A 02 03 04 01 04 6A 73 6F 6E 0A
   02 05 06 01 07 70 61 72 73 69 6E 67 0A 02 07 08
   01 04 75 74 69 6C 0A 01 09 01 05 73 63 61 6C 61
   03 00 13 04 00 0C 14 18 10 02 0D 12 0D 01 0E 0A
   02 0F 10 01 07 6C 65 78 69 63 61 6C 0A 02 11 04
   01 0A 63 6F 6D 62 69 6E 61 74 6F 72 09 02 13 0E
   02 0A 53 74 64 4C 65 78 69 63 61 6C 10 02 15 16
   0D 01 10 09 02 17 10 02 13 49 6D 70 6C 69 63 69
   74 43 6F 6E 76 65 72 73 69 6F 6E 73 10 02 19 1A
   0D 01 08 09 02 1B 08 02 0B 53 63 61 6C 61 4F 62
   6A 65 63 74 08 05 1D 00 FFFFFF84 00 1E 01 06 3C 69 6E
   69 74 3E 14 01 1F 10 02 20 00 0D 01 02 08 05 22
   00 FFFFFF84 20 23 01 05 74 6F 6B 65 6E 15 01 24 10 03
   25 26 2A 0D 01 00 09 02 27 28 02 06 50 61 72 73
   65 72 09 02 29 10 02 07 50 61 72 73 65 72 73 10
   02 25 2B 09 02 2C 2D 02 05 54 6F 6B 65 6E 09 02
   2E 2F 02 06 54 6F 6B 65 6E 73 0A 02 30 04 01 06
   73 79 6E 74 61 78 08 05 32 00 FFFFFF84 00 33 01 0C 63
   68 65 63 6B 4B 65 79 77 6F 72 64 14 02 34 3A 12
   03 35 37 2A 06 08 36 00 FFFFFF84 FFFFFF80 FFFFFF80 FFFFFF80 00 34 02 0C
   3C 72 65 66 69 6E 65 6D 65 6E 74 3E 10 02 19 38
   09 02 39 08 02 07 50 72 6F 64 75 63 74 08 05 3B
   31 FFFFFFC0 00 3C 01 02 78 73 10 03 3D 45 48 0E 02 3E
   43 0E 02 3F 42 0D 01 40 0A 02 41 0A 01 06 3C 72
   6F 6F 74 3E 09 01 09 09 02 44 08 01 07 70 61 63
   6B 61 67 65 09 02 46 47 02 04 4C 69 73 74 0A 02
   44 08 10 02 19 49 09 02 4A 08 02 03 41 6E 79 08
   05 4C 00 FFFFFF84 00 4D 01 06 73 74 72 69 6E 67 15 01
   4E 10 03 25 26 4F 10 02 50 53 0E 02 19 51 09 02
   52 08 01 06 50 72 65 64 65 66 09 02 54 55 02 06
   53 74 72 69 6E 67 0A 02 52 08 08 05 57 00 FFFFFF84 20
   58 01 0A 77 68 69 74 65 73 70 61 63 65 15 01 59
   10 03 25 26 5A 10 03 3D 45 5B 10 02 25 5C 09 02
   5D 5E 02 04 45 6C 65 6D 09 02 5F 0E 02 08 53 63
   61 6E 6E 65 72 73 08 05 61 00 FFFFFF84 00 62 01 06 6E
   75 6D 62 65 72 15 01 63 10 03 25 26 64 10 02 65
   6A 0D 01 66 0A 02 67 68 01 04 6C 61 6E 67 0A 01
   69 01 04 6A 61 76 61 09 02 54 66 08 05 6C 00 FFFFFF84
   00 4D 01 07 69 6E 74 50 61 72 74 08 05 6E 00 FFFFFF84
   00 4D 01 07 69 6E 74 4C 69 73 74 08 05 70 00 FFFFFF84
   00 4D 01 08 66 72 61 63 50 61 72 74 08 05 72 00
   FFFFFF84 00 62 01 07 65 78 70 50 61 72 74 08 05 74 00
   FFFFFF84 04 75 01 09 6F 70 74 53 74 72 69 6E 67 15 03
   76 FFFFFF81 00 14 03 64 77 79 08 05 78 73 FFFFFFC0 00 4F 01
   03 70 72 65 08 05 7A 73 FFFFFFC0 00 7B 01 01 61 10 03
   19 7C 7E 09 02 7D 08 02 06 4F 70 74 69 6F 6E 10
   03 7F FFFFFF81 00 0C 00 04 0A FFFFFF81 01 73 FFFFFF84 FFFFFF80 FFFFFF80 FFFFFFC2 00
   FFFFFF81 02 02 01 41 11 03 FFFFFF81 03 48 10 03 19 FFFFFF81 04 09
   03 FFFFFF81 05 08 02 07 4E 6F 74 68 69 6E 67 08 06 FFFFFF81
   07 00 FFFFFF84 00 4D 01 04 7A 65 72 6F 08 07 FFFFFF81 09 00
   FFFFFF84 00 FFFFFF81 0A 01 07 6E 6F 6E 7A 65 72 6F 15 02 FFFFFF81
   0B 10 03 25 26 5B 08 07 FFFFFF81 0D 00 FFFFFF84 00 FFFFFF81 0A 01
   08 65 78 70 6F 6E 65 6E 74 08 07 FFFFFF81 0F 00 FFFFFF84 00
   FFFFFF81 0A 01 04 73 69 67 6E 08 06 FFFFFF81 11 00 FFFFFF84 00 4D
   01 07 63 68 61 72 53 65 71 08 09 FFFFFF81 13 00 FFFFFFC2 FFFFFF80
   FFFFFF84 00 FFFFFF81 14 01 09 68 65 78 44 69 67 69 74 73 15
   02 FFFFFF81 15 10 06 FFFFFF81 16 FFFFFF81 1B FFFFFF81 1D 0D 02 FFFFFF81 17 0A
   04 FFFFFF81 18 FFFFFF81 19 01 09 69 6D 6D 75 74 61 62 6C 65
   0A 03 FFFFFF81 1A 08 01 0A 63 6F 6C 6C 65 63 74 69 6F
   6E 09 04 FFFFFF81 1C FFFFFF81 17 02 03 53 65 74 10 03 19 FFFFFF81
   1E 09 03 FFFFFF81 1F 08 02 04 43 68 61 72 08 08 FFFFFF81 21
   00 FFFFFFA0 FFFFFF80 04 FFFFFF81 15 01 0A 68 65 78 44 69 67 69 74
   73 20 08 07 FFFFFF81 23 00 FFFFFF84 00 FFFFFF81 0A 01 08 68 65 78
   44 69 67 69 74 08 06 FFFFFF81 25 00 FFFFFF84 04 62 01 0C 75
   6E 69 63 6F 64 65 42 6C 6F 63 6B 08 07 FFFFFF81 27 00
   FFFFFF84 00 FFFFFF81 28 01 0F 70 72 6F 74 65 63 74 65 64 24
   64 65 6C 69 6D 15 02 FFFFFF81 29 14 03 24 FFFFFF81 2A 08 09
   FFFFFF81 2B FFFFFF81 26 FFFFFF81 FFFFFF80 FFFFFFC0 00 25 01 03 78 24 31 
  InnerClass: 
   public abstract #421= #89 of #113; //Parser=class scala/util/parsing/combinator/Parsers$Parser of class scala/util/parsing/combinator/Parsers
   public #424= #335 of #423; //ErrorToken=class scala/util/parsing/syntax/Tokens$ErrorToken of class scala/util/parsing/syntax/Tokens
   public #425= #330 of #349; //Keyword=class scala/util/parsing/syntax/StdTokens$Keyword of class scala/util/parsing/syntax/StdTokens
   public final #426= #173 of #75; //$anonfun$sign$1=class scala/util/parsing/json/Lexer$$anonfun$sign$1 of class scala/util/parsing/json/Lexer
   public final #427= #379 of #75; //$anonfun$token$9=class scala/util/parsing/json/Lexer$$anonfun$token$9 of class scala/util/parsing/json/Lexer
   public final #428= #376 of #75; //$anonfun$token$8=class scala/util/parsing/json/Lexer$$anonfun$token$8 of class scala/util/parsing/json/Lexer
   public final #429= #373 of #75; //$anonfun$token$7=class scala/util/parsing/json/Lexer$$anonfun$token$7 of class scala/util/parsing/json/Lexer
   public final #430= #370 of #75; //$anonfun$token$6=class scala/util/parsing/json/Lexer$$anonfun$token$6 of class scala/util/parsing/json/Lexer
   public final #431= #367 of #75; //$anonfun$token$5=class scala/util/parsing/json/Lexer$$anonfun$token$5 of class scala/util/parsing/json/Lexer
   public final #432= #364 of #75; //$anonfun$token$4=class scala/util/parsing/json/Lexer$$anonfun$token$4 of class scala/util/parsing/json/Lexer
   public final #433= #361 of #75; //$anonfun$token$3=class scala/util/parsing/json/Lexer$$anonfun$token$3 of class scala/util/parsing/json/Lexer
   public final #434= #358 of #75; //$anonfun$token$2=class scala/util/parsing/json/Lexer$$anonfun$token$2 of class scala/util/parsing/json/Lexer
   public final #435= #355 of #75; //$anonfun$token$1=class scala/util/parsing/json/Lexer$$anonfun$token$1 of class scala/util/parsing/json/Lexer
   public final #436= #312 of #75; //$anonfun$string$3=class scala/util/parsing/json/Lexer$$anonfun$string$3 of class scala/util/parsing/json/Lexer
   public final #437= #306 of #75; //$anonfun$string$2=class scala/util/parsing/json/Lexer$$anonfun$string$2 of class scala/util/parsing/json/Lexer
   public final #438= #303 of #75; //$anonfun$string$1=class scala/util/parsing/json/Lexer$$anonfun$string$1 of class scala/util/parsing/json/Lexer
   public final #439= #290 of #75; //$anonfun$number$3=class scala/util/parsing/json/Lexer$$anonfun$number$3 of class scala/util/parsing/json/Lexer
   public final #440= #287 of #75; //$anonfun$number$2=class scala/util/parsing/json/Lexer$$anonfun$number$2 of class scala/util/parsing/json/Lexer
   public final #441= #284 of #75; //$anonfun$number$1=class scala/util/parsing/json/Lexer$$anonfun$number$1 of class scala/util/parsing/json/Lexer
   public final #442= #278 of #75; //$anonfun$intPart$1=class scala/util/parsing/json/Lexer$$anonfun$intPart$1 of class scala/util/parsing/json/Lexer
   public final #443= #272 of #75; //$anonfun$intList$2=class scala/util/parsing/json/Lexer$$anonfun$intList$2 of class scala/util/parsing/json/Lexer
   public final #444= #269 of #75; //$anonfun$intList$1=class scala/util/parsing/json/Lexer$$anonfun$intList$1 of class scala/util/parsing/json/Lexer
   public final #445= #252 of #75; //$anonfun$expPart$3=class scala/util/parsing/json/Lexer$$anonfun$expPart$3 of class scala/util/parsing/json/Lexer
   public final #446= #249 of #75; //$anonfun$expPart$2=class scala/util/parsing/json/Lexer$$anonfun$expPart$2 of class scala/util/parsing/json/Lexer
   public final #447= #246 of #75; //$anonfun$expPart$1=class scala/util/parsing/json/Lexer$$anonfun$expPart$1 of class scala/util/parsing/json/Lexer
   public final #448= #185 of #75; //$anonfun$nonzero$1=class scala/util/parsing/json/Lexer$$anonfun$nonzero$1 of class scala/util/parsing/json/Lexer
   public final #449= #166 of #75; //$anonfun$charSeq$9=class scala/util/parsing/json/Lexer$$anonfun$charSeq$9 of class scala/util/parsing/json/Lexer
   public final #450= #163 of #75; //$anonfun$charSeq$8=class scala/util/parsing/json/Lexer$$anonfun$charSeq$8 of class scala/util/parsing/json/Lexer
   public final #451= #160 of #75; //$anonfun$charSeq$7=class scala/util/parsing/json/Lexer$$anonfun$charSeq$7 of class scala/util/parsing/json/Lexer
   public final #452= #157 of #75; //$anonfun$charSeq$6=class scala/util/parsing/json/Lexer$$anonfun$charSeq$6 of class scala/util/parsing/json/Lexer
   public final #453= #154 of #75; //$anonfun$charSeq$5=class scala/util/parsing/json/Lexer$$anonfun$charSeq$5 of class scala/util/parsing/json/Lexer
   public final #454= #151 of #75; //$anonfun$charSeq$4=class scala/util/parsing/json/Lexer$$anonfun$charSeq$4 of class scala/util/parsing/json/Lexer
   public final #455= #148 of #75; //$anonfun$charSeq$3=class scala/util/parsing/json/Lexer$$anonfun$charSeq$3 of class scala/util/parsing/json/Lexer
   public final #456= #142 of #75; //$anonfun$charSeq$2=class scala/util/parsing/json/Lexer$$anonfun$charSeq$2 of class scala/util/parsing/json/Lexer
   public final #457= #134 of #75; //$anonfun$charSeq$1=class scala/util/parsing/json/Lexer$$anonfun$charSeq$1 of class scala/util/parsing/json/Lexer
   public final #458= #263 of #75; //$anonfun$fracPart$2=class scala/util/parsing/json/Lexer$$anonfun$fracPart$2 of class scala/util/parsing/json/Lexer
   public final #459= #257 of #75; //$anonfun$fracPart$1=class scala/util/parsing/json/Lexer$$anonfun$fracPart$1 of class scala/util/parsing/json/Lexer
   public final #460= #179 of #75; //$anonfun$exponent$1=class scala/util/parsing/json/Lexer$$anonfun$exponent$1 of class scala/util/parsing/json/Lexer
   public final #461= #110 of #75; //$anonfun$hexDigit$1=class scala/util/parsing/json/Lexer$$anonfun$hexDigit$1 of class scala/util/parsing/json/Lexer
   public final #462= #294 of #75; //$anonfun$whitespace$1=class scala/util/parsing/json/Lexer$$anonfun$whitespace$1 of class scala/util/parsing/json/Lexer
   public final #463= #101 of #75; //$anonfun$scala$util$parsing$json$Lexer$$unicodeBlock$4=class scala/util/parsing/json/Lexer$$anonfun$scala$util$parsing$json$Lexer$$unicodeBlock$4 of class scala/util/parsing/json/Lexer
   public final #464= #98 of #75; //$anonfun$scala$util$parsing$json$Lexer$$unicodeBlock$3=class scala/util/parsing/json/Lexer$$anonfun$scala$util$parsing$json$Lexer$$unicodeBlock$3 of class scala/util/parsing/json/Lexer
   public final #465= #95 of #75; //$anonfun$scala$util$parsing$json$Lexer$$unicodeBlock$2=class scala/util/parsing/json/Lexer$$anonfun$scala$util$parsing$json$Lexer$$unicodeBlock$2 of class scala/util/parsing/json/Lexer
   public final #466= #84 of #75; //$anonfun$scala$util$parsing$json$Lexer$$unicodeBlock$1=class scala/util/parsing/json/Lexer$$anonfun$scala$util$parsing$json$Lexer$$unicodeBlock$1 of class scala/util/parsing/json/Lexer
  minor version: 0
  major version: 49
  Constant pool:
const #1 = Asciz	SourceFile;
const #2 = Asciz	Lexer.scala;
const #3 = Asciz	hexDigits;
const #4 = Asciz	Lscala/collection/immutable/Set;;
const #5 = Asciz	Lscala/collection/immutable/Set<Ljava/lang/Character;>;;
const #6 = Asciz	Signature;
const #7 = Asciz	<init>;
const #8 = Asciz	()V;
const #9 = Asciz	Code;
const #10 = Asciz	LineNumberTable;
const #11 = Asciz	scala/util/parsing/combinator/lexical/StdLexical;
const #12 = class	#11;	//  scala/util/parsing/combinator/lexical/StdLexical
const #13 = NameAndType	#7:#8;//  "<init>":()V
const #14 = Method	#12.#13;	//  scala/util/parsing/combinator/lexical/StdLexical."<init>":()V
const #15 = Asciz	scala/util/parsing/combinator/ImplicitConversions$class;
const #16 = class	#15;	//  scala/util/parsing/combinator/ImplicitConversions$class
const #17 = Asciz	$init$;
const #18 = Asciz	(Lscala/util/parsing/combinator/ImplicitConversions;)V;
const #19 = NameAndType	#17:#18;//  $init$:(Lscala/util/parsing/combinator/ImplicitConversions;)V
const #20 = Method	#16.#19;	//  scala/util/parsing/combinator/ImplicitConversions$class.$init$:(Lscala/util/parsing/combinator/ImplicitConversions;)V
const #21 = Asciz	scala/Predef$;
const #22 = class	#21;	//  scala/Predef$
const #23 = Asciz	MODULE$;
const #24 = Asciz	Lscala/Predef$;;
const #25 = NameAndType	#23:#24;//  MODULE$:Lscala/Predef$;
const #26 = Field	#22.#25;	//  scala/Predef$.MODULE$:Lscala/Predef$;
const #27 = Asciz	Set;
const #28 = Asciz	()Lscala/collection/immutable/Set$;;
const #29 = NameAndType	#27:#28;//  Set:()Lscala/collection/immutable/Set$;
const #30 = Method	#22.#29;	//  scala/Predef$.Set:()Lscala/collection/immutable/Set$;
const #31 = Asciz	wrapCharArray;
const #32 = Asciz	([C)Lscala/collection/mutable/WrappedArray;;
const #33 = NameAndType	#31:#32;//  wrapCharArray:([C)Lscala/collection/mutable/WrappedArray;
const #34 = Method	#22.#33;	//  scala/Predef$.wrapCharArray:([C)Lscala/collection/mutable/WrappedArray;
const #35 = Asciz	scala/collection/immutable/Set$;
const #36 = class	#35;	//  scala/collection/immutable/Set$
const #37 = Asciz	apply;
const #38 = Asciz	(Lscala/collection/Seq;)Lscala/collection/Traversable;;
const #39 = NameAndType	#37:#38;//  apply:(Lscala/collection/Seq;)Lscala/collection/Traversable;
const #40 = Method	#36.#39;	//  scala/collection/immutable/Set$.apply:(Lscala/collection/Seq;)Lscala/collection/Traversable;
const #41 = Asciz	scala/collection/generic/Addable;
const #42 = class	#41;	//  scala/collection/generic/Addable
const #43 = Asciz	0123456789abcdefABCDEF;
const #44 = String	#43;	//  0123456789abcdefABCDEF
const #45 = Asciz	augmentString;
const #46 = Asciz	(Ljava/lang/String;)Lscala/collection/immutable/StringOps;;
const #47 = NameAndType	#45:#46;//  augmentString:(Ljava/lang/String;)Lscala/collection/immutable/StringOps;
const #48 = Method	#22.#47;	//  scala/Predef$.augmentString:(Ljava/lang/String;)Lscala/collection/immutable/StringOps;
const #49 = Asciz	scala/reflect/Manifest$;
const #50 = class	#49;	//  scala/reflect/Manifest$
const #51 = Asciz	Lscala/reflect/Manifest$;;
const #52 = NameAndType	#23:#51;//  MODULE$:Lscala/reflect/Manifest$;
const #53 = Field	#50.#52;	//  scala/reflect/Manifest$.MODULE$:Lscala/reflect/Manifest$;
const #54 = Asciz	Char;
const #55 = Asciz	()Ljava/lang/Object;;
const #56 = NameAndType	#54:#55;//  Char:()Ljava/lang/Object;
const #57 = Method	#50.#56;	//  scala/reflect/Manifest$.Char:()Ljava/lang/Object;
const #58 = Asciz	scala/reflect/ClassManifest;
const #59 = class	#58;	//  scala/reflect/ClassManifest
const #60 = Asciz	scala/collection/TraversableLike;
const #61 = class	#60;	//  scala/collection/TraversableLike
const #62 = Asciz	toArray;
const #63 = Asciz	(Lscala/reflect/ClassManifest;)Ljava/lang/Object;;
const #64 = NameAndType	#62:#63;//  toArray:(Lscala/reflect/ClassManifest;)Ljava/lang/Object;
const #65 = InterfaceMethod	#61.#64;	//  scala/collection/TraversableLike.toArray:(Lscala/reflect/ClassManifest;)Ljava/lang/Object;
const #66 = Asciz	[C;
const #67 = class	#66;	//  "[C"
const #68 = Asciz	$plus$plus;
const #69 = Asciz	(Lscala/collection/Traversable;)Lscala/collection/generic/Addable;;
const #70 = NameAndType	#68:#69;//  $plus$plus:(Lscala/collection/Traversable;)Lscala/collection/generic/Addable;
const #71 = InterfaceMethod	#42.#70;	//  scala/collection/generic/Addable.$plus$plus:(Lscala/collection/Traversable;)Lscala/collection/generic/Addable;
const #72 = Asciz	scala/collection/immutable/Set;
const #73 = class	#72;	//  scala/collection/immutable/Set
const #74 = Asciz	scala/util/parsing/json/Lexer;
const #75 = class	#74;	//  scala/util/parsing/json/Lexer
const #76 = NameAndType	#3:#4;//  hexDigits:Lscala/collection/immutable/Set;
const #77 = Field	#75.#76;	//  scala/util/parsing/json/Lexer.hexDigits:Lscala/collection/immutable/Set;
const #78 = Asciz	scala$util$parsing$json$Lexer$$unicodeBlock;
const #79 = Asciz	()Lscala/util/parsing/combinator/Parsers$Parser;;
const #80 = Asciz	hexDigit;
const #81 = NameAndType	#80:#79;//  hexDigit:()Lscala/util/parsing/combinator/Parsers$Parser;
const #82 = Method	#75.#81;	//  scala/util/parsing/json/Lexer.hexDigit:()Lscala/util/parsing/combinator/Parsers$Parser;
const #83 = Asciz	scala/util/parsing/json/Lexer$$anonfun$scala$util$parsing$json$Lexer$$unicodeBlock$1;
const #84 = class	#83;	//  scala/util/parsing/json/Lexer$$anonfun$scala$util$parsing$json$Lexer$$unicodeBlock$1
const #85 = Asciz	(Lscala/util/parsing/json/Lexer;)V;
const #86 = NameAndType	#7:#85;//  "<init>":(Lscala/util/parsing/json/Lexer;)V
const #87 = Method	#84.#86;	//  scala/util/parsing/json/Lexer$$anonfun$scala$util$parsing$json$Lexer$$unicodeBlock$1."<init>":(Lscala/util/parsing/json/Lexer;)V
const #88 = Asciz	scala/util/parsing/combinator/Parsers$Parser;
const #89 = class	#88;	//  scala/util/parsing/combinator/Parsers$Parser
const #90 = Asciz	$tilde;
const #91 = Asciz	(Lscala/Function0;)Lscala/util/parsing/combinator/Parsers$Parser;;
const #92 = NameAndType	#90:#91;//  $tilde:(Lscala/Function0;)Lscala/util/parsing/combinator/Parsers$Parser;
const #93 = Method	#89.#92;	//  scala/util/parsing/combinator/Parsers$Parser.$tilde:(Lscala/Function0;)Lscala/util/parsing/combinator/Parsers$Parser;
const #94 = Asciz	scala/util/parsing/json/Lexer$$anonfun$scala$util$parsing$json$Lexer$$unicodeBlock$2;
const #95 = class	#94;	//  scala/util/parsing/json/Lexer$$anonfun$scala$util$parsing$json$Lexer$$unicodeBlock$2
const #96 = Method	#95.#86;	//  scala/util/parsing/json/Lexer$$anonfun$scala$util$parsing$json$Lexer$$unicodeBlock$2."<init>":(Lscala/util/parsing/json/Lexer;)V
const #97 = Asciz	scala/util/parsing/json/Lexer$$anonfun$scala$util$parsing$json$Lexer$$unicodeBlock$3;
const #98 = class	#97;	//  scala/util/parsing/json/Lexer$$anonfun$scala$util$parsing$json$Lexer$$unicodeBlock$3
const #99 = Method	#98.#86;	//  scala/util/parsing/json/Lexer$$anonfun$scala$util$parsing$json$Lexer$$unicodeBlock$3."<init>":(Lscala/util/parsing/json/Lexer;)V
const #100 = Asciz	scala/util/parsing/json/Lexer$$anonfun$scala$util$parsing$json$Lexer$$unicodeBlock$4;
const #101 = class	#100;	//  scala/util/parsing/json/Lexer$$anonfun$scala$util$parsing$json$Lexer$$unicodeBlock$4
const #102 = Method	#101.#86;	//  scala/util/parsing/json/Lexer$$anonfun$scala$util$parsing$json$Lexer$$unicodeBlock$4."<init>":(Lscala/util/parsing/json/Lexer;)V
const #103 = Asciz	$up$up;
const #104 = Asciz	(Lscala/Function1;)Lscala/util/parsing/combinator/Parsers$Parser;;
const #105 = NameAndType	#103:#104;//  $up$up:(Lscala/Function1;)Lscala/util/parsing/combinator/Parsers$Parser;
const #106 = Method	#89.#105;	//  scala/util/parsing/combinator/Parsers$Parser.$up$up:(Lscala/Function1;)Lscala/util/parsing/combinator/Parsers$Parser;
const #107 = Asciz	hex digit;
const #108 = String	#107;	//  hex digit
const #109 = Asciz	scala/util/parsing/json/Lexer$$anonfun$hexDigit$1;
const #110 = class	#109;	//  scala/util/parsing/json/Lexer$$anonfun$hexDigit$1
const #111 = Method	#110.#86;	//  scala/util/parsing/json/Lexer$$anonfun$hexDigit$1."<init>":(Lscala/util/parsing/json/Lexer;)V
const #112 = Asciz	scala/util/parsing/combinator/Parsers;
const #113 = class	#112;	//  scala/util/parsing/combinator/Parsers
const #114 = Asciz	elem;
const #115 = Asciz	(Ljava/lang/String;Lscala/Function1;)Lscala/util/parsing/combinator/Parsers$Parser;;
const #116 = NameAndType	#114:#115;//  elem:(Ljava/lang/String;Lscala/Function1;)Lscala/util/parsing/combinator/Parsers$Parser;
const #117 = InterfaceMethod	#113.#116;	//  scala/util/parsing/combinator/Parsers.elem:(Ljava/lang/String;Lscala/Function1;)Lscala/util/parsing/combinator/Parsers$Parser;
const #118 = Asciz	()Lscala/util/parsing/combinator/Parsers$Parser<Ljava/lang/Character;>;;
const #119 = Asciz	()Lscala/collection/immutable/Set;;
const #120 = Asciz	()Lscala/collection/immutable/Set<Ljava/lang/Character;>;;
const #121 = Asciz	charSeq;
const #122 = int	92;
const #123 = Asciz	scala/runtime/BoxesRunTime;
const #124 = class	#123;	//  scala/runtime/BoxesRunTime
const #125 = Asciz	boxToCharacter;
const #126 = Asciz	(C)Ljava/lang/Character;;
const #127 = NameAndType	#125:#126;//  boxToCharacter:(C)Ljava/lang/Character;
const #128 = Method	#124.#127;	//  scala/runtime/BoxesRunTime.boxToCharacter:(C)Ljava/lang/Character;
const #129 = Asciz	accept;
const #130 = Asciz	(Ljava/lang/Object;)Lscala/util/parsing/combinator/Parsers$Parser;;
const #131 = NameAndType	#129:#130;//  accept:(Ljava/lang/Object;)Lscala/util/parsing/combinator/Parsers$Parser;
const #132 = InterfaceMethod	#113.#131;	//  scala/util/parsing/combinator/Parsers.accept:(Ljava/lang/Object;)Lscala/util/parsing/combinator/Parsers$Parser;
const #133 = Asciz	scala/util/parsing/json/Lexer$$anonfun$charSeq$1;
const #134 = class	#133;	//  scala/util/parsing/json/Lexer$$anonfun$charSeq$1
const #135 = Method	#134.#86;	//  scala/util/parsing/json/Lexer$$anonfun$charSeq$1."<init>":(Lscala/util/parsing/json/Lexer;)V
const #136 = Asciz	\";
const #137 = String	#136;	//  \"
const #138 = Asciz	$up$up$up;
const #139 = NameAndType	#138:#130;//  $up$up$up:(Ljava/lang/Object;)Lscala/util/parsing/combinator/Parsers$Parser;
const #140 = Method	#89.#139;	//  scala/util/parsing/combinator/Parsers$Parser.$up$up$up:(Ljava/lang/Object;)Lscala/util/parsing/combinator/Parsers$Parser;
const #141 = Asciz	scala/util/parsing/json/Lexer$$anonfun$charSeq$2;
const #142 = class	#141;	//  scala/util/parsing/json/Lexer$$anonfun$charSeq$2
const #143 = Method	#142.#86;	//  scala/util/parsing/json/Lexer$$anonfun$charSeq$2."<init>":(Lscala/util/parsing/json/Lexer;)V
const #144 = Asciz	$bar;
const #145 = NameAndType	#144:#91;//  $bar:(Lscala/Function0;)Lscala/util/parsing/combinator/Parsers$Parser;
const #146 = Method	#89.#145;	//  scala/util/parsing/combinator/Parsers$Parser.$bar:(Lscala/Function0;)Lscala/util/parsing/combinator/Parsers$Parser;
const #147 = Asciz	scala/util/parsing/json/Lexer$$anonfun$charSeq$3;
const #148 = class	#147;	//  scala/util/parsing/json/Lexer$$anonfun$charSeq$3
const #149 = Method	#148.#86;	//  scala/util/parsing/json/Lexer$$anonfun$charSeq$3."<init>":(Lscala/util/parsing/json/Lexer;)V
const #150 = Asciz	scala/util/parsing/json/Lexer$$anonfun$charSeq$4;
const #151 = class	#150;	//  scala/util/parsing/json/Lexer$$anonfun$charSeq$4
const #152 = Method	#151.#86;	//  scala/util/parsing/json/Lexer$$anonfun$charSeq$4."<init>":(Lscala/util/parsing/json/Lexer;)V
const #153 = Asciz	scala/util/parsing/json/Lexer$$anonfun$charSeq$5;
const #154 = class	#153;	//  scala/util/parsing/json/Lexer$$anonfun$charSeq$5
const #155 = Method	#154.#86;	//  scala/util/parsing/json/Lexer$$anonfun$charSeq$5."<init>":(Lscala/util/parsing/json/Lexer;)V
const #156 = Asciz	scala/util/parsing/json/Lexer$$anonfun$charSeq$6;
const #157 = class	#156;	//  scala/util/parsing/json/Lexer$$anonfun$charSeq$6
const #158 = Method	#157.#86;	//  scala/util/parsing/json/Lexer$$anonfun$charSeq$6."<init>":(Lscala/util/parsing/json/Lexer;)V
const #159 = Asciz	scala/util/parsing/json/Lexer$$anonfun$charSeq$7;
const #160 = class	#159;	//  scala/util/parsing/json/Lexer$$anonfun$charSeq$7
const #161 = Method	#160.#86;	//  scala/util/parsing/json/Lexer$$anonfun$charSeq$7."<init>":(Lscala/util/parsing/json/Lexer;)V
const #162 = Asciz	scala/util/parsing/json/Lexer$$anonfun$charSeq$8;
const #163 = class	#162;	//  scala/util/parsing/json/Lexer$$anonfun$charSeq$8
const #164 = Method	#163.#86;	//  scala/util/parsing/json/Lexer$$anonfun$charSeq$8."<init>":(Lscala/util/parsing/json/Lexer;)V
const #165 = Asciz	scala/util/parsing/json/Lexer$$anonfun$charSeq$9;
const #166 = class	#165;	//  scala/util/parsing/json/Lexer$$anonfun$charSeq$9
const #167 = Method	#166.#86;	//  scala/util/parsing/json/Lexer$$anonfun$charSeq$9."<init>":(Lscala/util/parsing/json/Lexer;)V
const #168 = Asciz	()Lscala/util/parsing/combinator/Parsers$Parser<Ljava/lang/String;>;;
const #169 = Asciz	sign;
const #170 = Asciz	sign character;
const #171 = String	#170;	//  sign character
const #172 = Asciz	scala/util/parsing/json/Lexer$$anonfun$sign$1;
const #173 = class	#172;	//  scala/util/parsing/json/Lexer$$anonfun$sign$1
const #174 = Method	#173.#86;	//  scala/util/parsing/json/Lexer$$anonfun$sign$1."<init>":(Lscala/util/parsing/json/Lexer;)V
const #175 = Asciz	exponent;
const #176 = Asciz	exponent character;
const #177 = String	#176;	//  exponent character
const #178 = Asciz	scala/util/parsing/json/Lexer$$anonfun$exponent$1;
const #179 = class	#178;	//  scala/util/parsing/json/Lexer$$anonfun$exponent$1
const #180 = Method	#179.#86;	//  scala/util/parsing/json/Lexer$$anonfun$exponent$1."<init>":(Lscala/util/parsing/json/Lexer;)V
const #181 = Asciz	nonzero;
const #182 = Asciz	nonzero digit;
const #183 = String	#182;	//  nonzero digit
const #184 = Asciz	scala/util/parsing/json/Lexer$$anonfun$nonzero$1;
const #185 = class	#184;	//  scala/util/parsing/json/Lexer$$anonfun$nonzero$1
const #186 = Method	#185.#86;	//  scala/util/parsing/json/Lexer$$anonfun$nonzero$1."<init>":(Lscala/util/parsing/json/Lexer;)V
const #187 = Asciz	zero;
const #188 = int	48;
const #189 = Asciz	0;
const #190 = String	#189;	//  0
const #191 = Asciz	scala$util$parsing$json$Lexer$$optString;
const #192 = Asciz	(Ljava/lang/String;Lscala/Option;)Ljava/lang/String;;
const #193 = Asciz	scala/Some;
const #194 = class	#193;	//  scala/Some
const #195 = Asciz	x;
const #196 = Asciz	Ljava/lang/Object;;
const #197 = NameAndType	#195:#196;//  x:Ljava/lang/Object;
const #198 = Field	#194.#197;	//  scala/Some.x:Ljava/lang/Object;
const #199 = Asciz	scala/collection/mutable/StringBuilder;
const #200 = class	#199;	//  scala/collection/mutable/StringBuilder
const #201 = Method	#200.#13;	//  scala/collection/mutable/StringBuilder."<init>":()V
const #202 = Asciz	append;
const #203 = Asciz	(Ljava/lang/Object;)Lscala/collection/mutable/StringBuilder;;
const #204 = NameAndType	#202:#203;//  append:(Ljava/lang/Object;)Lscala/collection/mutable/StringBuilder;
const #205 = Method	#200.#204;	//  scala/collection/mutable/StringBuilder.append:(Ljava/lang/Object;)Lscala/collection/mutable/StringBuilder;
const #206 = Asciz	java/lang/Object;
const #207 = class	#206;	//  java/lang/Object
const #208 = Asciz	toString;
const #209 = Asciz	()Ljava/lang/String;;
const #210 = NameAndType	#208:#209;//  toString:()Ljava/lang/String;
const #211 = Method	#207.#210;	//  java/lang/Object.toString:()Ljava/lang/String;
const #212 = Method	#200.#210;	//  scala/collection/mutable/StringBuilder.toString:()Ljava/lang/String;
const #213 = Asciz	scala/MatchError;
const #214 = class	#213;	//  scala/MatchError
const #215 = Asciz	scala/Option;
const #216 = class	#215;	//  scala/Option
const #217 = Method	#216.#210;	//  scala/Option.toString:()Ljava/lang/String;
const #218 = Asciz	(Ljava/lang/String;)V;
const #219 = NameAndType	#7:#218;//  "<init>":(Ljava/lang/String;)V
const #220 = Method	#214.#219;	//  scala/MatchError."<init>":(Ljava/lang/String;)V
const #221 = Asciz	scala/None$;
const #222 = class	#221;	//  scala/None$
const #223 = Asciz	Lscala/None$;;
const #224 = NameAndType	#23:#223;//  MODULE$:Lscala/None$;
const #225 = Field	#222.#224;	//  scala/None$.MODULE$:Lscala/None$;
const #226 = Asciz	equals;
const #227 = Asciz	(Ljava/lang/Object;)Z;
const #228 = NameAndType	#226:#227;//  equals:(Ljava/lang/Object;)Z
const #229 = Method	#207.#228;	//  java/lang/Object.equals:(Ljava/lang/Object;)Z
const #230 = Asciz	;
const #231 = String	#230;	//  
const #232 = Asciz	this;
const #233 = Asciz	Lscala/util/parsing/json/Lexer;;
const #234 = Asciz	pre;
const #235 = Asciz	Ljava/lang/String;;
const #236 = Asciz	a;
const #237 = Asciz	Lscala/Option;;
const #238 = Asciz	temp26;
const #239 = Asciz	Lscala/Some;;
const #240 = Asciz	temp27;
const #241 = Asciz	LocalVariableTable;
const #242 = Asciz	expPart;
const #243 = NameAndType	#175:#79;//  exponent:()Lscala/util/parsing/combinator/Parsers$Parser;
const #244 = Method	#75.#243;	//  scala/util/parsing/json/Lexer.exponent:()Lscala/util/parsing/combinator/Parsers$Parser;
const #245 = Asciz	scala/util/parsing/json/Lexer$$anonfun$expPart$1;
const #246 = class	#245;	//  scala/util/parsing/json/Lexer$$anonfun$expPart$1
const #247 = Method	#246.#86;	//  scala/util/parsing/json/Lexer$$anonfun$expPart$1."<init>":(Lscala/util/parsing/json/Lexer;)V
const #248 = Asciz	scala/util/parsing/json/Lexer$$anonfun$expPart$2;
const #249 = class	#248;	//  scala/util/parsing/json/Lexer$$anonfun$expPart$2
const #250 = Method	#249.#86;	//  scala/util/parsing/json/Lexer$$anonfun$expPart$2."<init>":(Lscala/util/parsing/json/Lexer;)V
const #251 = Asciz	scala/util/parsing/json/Lexer$$anonfun$expPart$3;
const #252 = class	#251;	//  scala/util/parsing/json/Lexer$$anonfun$expPart$3
const #253 = Method	#252.#86;	//  scala/util/parsing/json/Lexer$$anonfun$expPart$3."<init>":(Lscala/util/parsing/json/Lexer;)V
const #254 = Asciz	fracPart;
const #255 = int	46;
const #256 = Asciz	scala/util/parsing/json/Lexer$$anonfun$fracPart$1;
const #257 = class	#256;	//  scala/util/parsing/json/Lexer$$anonfun$fracPart$1
const #258 = Method	#257.#86;	//  scala/util/parsing/json/Lexer$$anonfun$fracPart$1."<init>":(Lscala/util/parsing/json/Lexer;)V
const #259 = Asciz	$tilde$greater;
const #260 = NameAndType	#259:#91;//  $tilde$greater:(Lscala/Function0;)Lscala/util/parsing/combinator/Parsers$Parser;
const #261 = Method	#89.#260;	//  scala/util/parsing/combinator/Parsers$Parser.$tilde$greater:(Lscala/Function0;)Lscala/util/parsing/combinator/Parsers$Parser;
const #262 = Asciz	scala/util/parsing/json/Lexer$$anonfun$fracPart$2;
const #263 = class	#262;	//  scala/util/parsing/json/Lexer$$anonfun$fracPart$2
const #264 = Method	#263.#86;	//  scala/util/parsing/json/Lexer$$anonfun$fracPart$2."<init>":(Lscala/util/parsing/json/Lexer;)V
const #265 = Asciz	intList;
const #266 = NameAndType	#181:#79;//  nonzero:()Lscala/util/parsing/combinator/Parsers$Parser;
const #267 = Method	#75.#266;	//  scala/util/parsing/json/Lexer.nonzero:()Lscala/util/parsing/combinator/Parsers$Parser;
const #268 = Asciz	scala/util/parsing/json/Lexer$$anonfun$intList$1;
const #269 = class	#268;	//  scala/util/parsing/json/Lexer$$anonfun$intList$1
const #270 = Method	#269.#86;	//  scala/util/parsing/json/Lexer$$anonfun$intList$1."<init>":(Lscala/util/parsing/json/Lexer;)V
const #271 = Asciz	scala/util/parsing/json/Lexer$$anonfun$intList$2;
const #272 = class	#271;	//  scala/util/parsing/json/Lexer$$anonfun$intList$2
const #273 = Method	#272.#86;	//  scala/util/parsing/json/Lexer$$anonfun$intList$2."<init>":(Lscala/util/parsing/json/Lexer;)V
const #274 = Asciz	intPart;
const #275 = NameAndType	#187:#79;//  zero:()Lscala/util/parsing/combinator/Parsers$Parser;
const #276 = Method	#75.#275;	//  scala/util/parsing/json/Lexer.zero:()Lscala/util/parsing/combinator/Parsers$Parser;
const #277 = Asciz	scala/util/parsing/json/Lexer$$anonfun$intPart$1;
const #278 = class	#277;	//  scala/util/parsing/json/Lexer$$anonfun$intPart$1
const #279 = Method	#278.#86;	//  scala/util/parsing/json/Lexer$$anonfun$intPart$1."<init>":(Lscala/util/parsing/json/Lexer;)V
const #280 = Asciz	number;
const #281 = NameAndType	#274:#79;//  intPart:()Lscala/util/parsing/combinator/Parsers$Parser;
const #282 = Method	#75.#281;	//  scala/util/parsing/json/Lexer.intPart:()Lscala/util/parsing/combinator/Parsers$Parser;
const #283 = Asciz	scala/util/parsing/json/Lexer$$anonfun$number$1;
const #284 = class	#283;	//  scala/util/parsing/json/Lexer$$anonfun$number$1
const #285 = Method	#284.#86;	//  scala/util/parsing/json/Lexer$$anonfun$number$1."<init>":(Lscala/util/parsing/json/Lexer;)V
const #286 = Asciz	scala/util/parsing/json/Lexer$$anonfun$number$2;
const #287 = class	#286;	//  scala/util/parsing/json/Lexer$$anonfun$number$2
const #288 = Method	#287.#86;	//  scala/util/parsing/json/Lexer$$anonfun$number$2."<init>":(Lscala/util/parsing/json/Lexer;)V
const #289 = Asciz	scala/util/parsing/json/Lexer$$anonfun$number$3;
const #290 = class	#289;	//  scala/util/parsing/json/Lexer$$anonfun$number$3
const #291 = Method	#290.#86;	//  scala/util/parsing/json/Lexer$$anonfun$number$3."<init>":(Lscala/util/parsing/json/Lexer;)V
const #292 = Asciz	whitespace;
const #293 = Asciz	scala/util/parsing/json/Lexer$$anonfun$whitespace$1;
const #294 = class	#293;	//  scala/util/parsing/json/Lexer$$anonfun$whitespace$1
const #295 = Method	#294.#86;	//  scala/util/parsing/json/Lexer$$anonfun$whitespace$1."<init>":(Lscala/util/parsing/json/Lexer;)V
const #296 = Asciz	rep;
const #297 = NameAndType	#296:#91;//  rep:(Lscala/Function0;)Lscala/util/parsing/combinator/Parsers$Parser;
const #298 = InterfaceMethod	#113.#297;	//  scala/util/parsing/combinator/Parsers.rep:(Lscala/Function0;)Lscala/util/parsing/combinator/Parsers$Parser;
const #299 = Asciz	()Lscala/util/parsing/combinator/Parsers$Parser<Lscala/collection/immutable/List<Ljava/lang/Character;>;>;;
const #300 = Asciz	string;
const #301 = int	34;
const #302 = Asciz	scala/util/parsing/json/Lexer$$anonfun$string$1;
const #303 = class	#302;	//  scala/util/parsing/json/Lexer$$anonfun$string$1
const #304 = Method	#303.#86;	//  scala/util/parsing/json/Lexer$$anonfun$string$1."<init>":(Lscala/util/parsing/json/Lexer;)V
const #305 = Asciz	scala/util/parsing/json/Lexer$$anonfun$string$2;
const #306 = class	#305;	//  scala/util/parsing/json/Lexer$$anonfun$string$2
const #307 = Method	#306.#86;	//  scala/util/parsing/json/Lexer$$anonfun$string$2."<init>":(Lscala/util/parsing/json/Lexer;)V
const #308 = Asciz	$less$tilde;
const #309 = NameAndType	#308:#91;//  $less$tilde:(Lscala/Function0;)Lscala/util/parsing/combinator/Parsers$Parser;
const #310 = Method	#89.#309;	//  scala/util/parsing/combinator/Parsers$Parser.$less$tilde:(Lscala/Function0;)Lscala/util/parsing/combinator/Parsers$Parser;
const #311 = Asciz	scala/util/parsing/json/Lexer$$anonfun$string$3;
const #312 = class	#311;	//  scala/util/parsing/json/Lexer$$anonfun$string$3
const #313 = Method	#312.#86;	//  scala/util/parsing/json/Lexer$$anonfun$string$3."<init>":(Lscala/util/parsing/json/Lexer;)V
const #314 = Asciz	checkKeyword;
const #315 = Asciz	(Lscala/collection/immutable/List;)Lscala/Product;;
const #316 = Asciz	mkString;
const #317 = Asciz	(Ljava/lang/String;)Ljava/lang/String;;
const #318 = NameAndType	#316:#317;//  mkString:(Ljava/lang/String;)Ljava/lang/String;
const #319 = InterfaceMethod	#61.#318;	//  scala/collection/TraversableLike.mkString:(Ljava/lang/String;)Ljava/lang/String;
const #320 = Asciz	reserved;
const #321 = Asciz	()Lscala/collection/mutable/HashSet;;
const #322 = NameAndType	#320:#321;//  reserved:()Lscala/collection/mutable/HashSet;
const #323 = Method	#75.#322;	//  scala/util/parsing/json/Lexer.reserved:()Lscala/collection/mutable/HashSet;
const #324 = Asciz	scala/collection/mutable/HashSet;
const #325 = class	#324;	//  scala/collection/mutable/HashSet
const #326 = Asciz	contains;
const #327 = NameAndType	#326:#227;//  contains:(Ljava/lang/Object;)Z
const #328 = Method	#325.#327;	//  scala/collection/mutable/HashSet.contains:(Ljava/lang/Object;)Z
const #329 = Asciz	scala/util/parsing/syntax/StdTokens$Keyword;
const #330 = class	#329;	//  scala/util/parsing/syntax/StdTokens$Keyword
const #331 = Asciz	(Lscala/util/parsing/syntax/StdTokens;Ljava/lang/String;)V;
const #332 = NameAndType	#7:#331;//  "<init>":(Lscala/util/parsing/syntax/StdTokens;Ljava/lang/String;)V
const #333 = Method	#330.#332;	//  scala/util/parsing/syntax/StdTokens$Keyword."<init>":(Lscala/util/parsing/syntax/StdTokens;Ljava/lang/String;)V
const #334 = Asciz	scala/util/parsing/syntax/Tokens$ErrorToken;
const #335 = class	#334;	//  scala/util/parsing/syntax/Tokens$ErrorToken
const #336 = Asciz	Not a keyword: ;
const #337 = String	#336;	//  Not a keyword: 
const #338 = Asciz	(Lscala/util/parsing/syntax/Tokens;Ljava/lang/String;)V;
const #339 = NameAndType	#7:#338;//  "<init>":(Lscala/util/parsing/syntax/Tokens;Ljava/lang/String;)V
const #340 = Method	#335.#339;	//  scala/util/parsing/syntax/Tokens$ErrorToken."<init>":(Lscala/util/parsing/syntax/Tokens;Ljava/lang/String;)V
const #341 = Asciz	xs;
const #342 = Asciz	Lscala/collection/immutable/List;;
const #343 = Asciz	strRep;
const #344 = Asciz	(Lscala/collection/immutable/List<Ljava/lang/Object;>;)Lscala/Product;;
const #345 = Asciz	token;
const #346 = NameAndType	#300:#79;//  string:()Lscala/util/parsing/combinator/Parsers$Parser;
const #347 = Method	#75.#346;	//  scala/util/parsing/json/Lexer.string:()Lscala/util/parsing/combinator/Parsers$Parser;
const #348 = Asciz	scala/util/parsing/syntax/StdTokens;
const #349 = class	#348;	//  scala/util/parsing/syntax/StdTokens
const #350 = Asciz	StringLit;
const #351 = Asciz	()Lscala/util/parsing/syntax/StdTokens$StringLit$;;
const #352 = NameAndType	#350:#351;//  StringLit:()Lscala/util/parsing/syntax/StdTokens$StringLit$;
const #353 = InterfaceMethod	#349.#352;	//  scala/util/parsing/syntax/StdTokens.StringLit:()Lscala/util/parsing/syntax/StdTokens$StringLit$;
const #354 = Asciz	scala/util/parsing/json/Lexer$$anonfun$token$1;
const #355 = class	#354;	//  scala/util/parsing/json/Lexer$$anonfun$token$1
const #356 = Method	#355.#86;	//  scala/util/parsing/json/Lexer$$anonfun$token$1."<init>":(Lscala/util/parsing/json/Lexer;)V
const #357 = Asciz	scala/util/parsing/json/Lexer$$anonfun$token$2;
const #358 = class	#357;	//  scala/util/parsing/json/Lexer$$anonfun$token$2
const #359 = Method	#358.#86;	//  scala/util/parsing/json/Lexer$$anonfun$token$2."<init>":(Lscala/util/parsing/json/Lexer;)V
const #360 = Asciz	scala/util/parsing/json/Lexer$$anonfun$token$3;
const #361 = class	#360;	//  scala/util/parsing/json/Lexer$$anonfun$token$3
const #362 = Method	#361.#86;	//  scala/util/parsing/json/Lexer$$anonfun$token$3."<init>":(Lscala/util/parsing/json/Lexer;)V
const #363 = Asciz	scala/util/parsing/json/Lexer$$anonfun$token$4;
const #364 = class	#363;	//  scala/util/parsing/json/Lexer$$anonfun$token$4
const #365 = Method	#364.#86;	//  scala/util/parsing/json/Lexer$$anonfun$token$4."<init>":(Lscala/util/parsing/json/Lexer;)V
const #366 = Asciz	scala/util/parsing/json/Lexer$$anonfun$token$5;
const #367 = class	#366;	//  scala/util/parsing/json/Lexer$$anonfun$token$5
const #368 = Method	#367.#86;	//  scala/util/parsing/json/Lexer$$anonfun$token$5."<init>":(Lscala/util/parsing/json/Lexer;)V
const #369 = Asciz	scala/util/parsing/json/Lexer$$anonfun$token$6;
const #370 = class	#369;	//  scala/util/parsing/json/Lexer$$anonfun$token$6
const #371 = Method	#370.#86;	//  scala/util/parsing/json/Lexer$$anonfun$token$6."<init>":(Lscala/util/parsing/json/Lexer;)V
const #372 = Asciz	scala/util/parsing/json/Lexer$$anonfun$token$7;
const #373 = class	#372;	//  scala/util/parsing/json/Lexer$$anonfun$token$7
const #374 = Method	#373.#86;	//  scala/util/parsing/json/Lexer$$anonfun$token$7."<init>":(Lscala/util/parsing/json/Lexer;)V
const #375 = Asciz	scala/util/parsing/json/Lexer$$anonfun$token$8;
const #376 = class	#375;	//  scala/util/parsing/json/Lexer$$anonfun$token$8
const #377 = Method	#376.#86;	//  scala/util/parsing/json/Lexer$$anonfun$token$8."<init>":(Lscala/util/parsing/json/Lexer;)V
const #378 = Asciz	scala/util/parsing/json/Lexer$$anonfun$token$9;
const #379 = class	#378;	//  scala/util/parsing/json/Lexer$$anonfun$token$9
const #380 = Method	#379.#86;	//  scala/util/parsing/json/Lexer$$anonfun$token$9."<init>":(Lscala/util/parsing/json/Lexer;)V
const #381 = Asciz	()Lscala/util/parsing/combinator/Parsers$Parser<Lscala/util/parsing/syntax/Tokens$Token;>;;
const #382 = Asciz	protected$delim;
const #383 = Asciz	(Lscala/util/parsing/json/Lexer;)Lscala/util/parsing/combinator/Parsers$Parser;;
const #384 = Asciz	delim;
const #385 = NameAndType	#384:#79;//  delim:()Lscala/util/parsing/combinator/Parsers$Parser;
const #386 = Method	#75.#385;	//  scala/util/parsing/json/Lexer.delim:()Lscala/util/parsing/combinator/Parsers$Parser;
const #387 = Asciz	(Lscala/util/parsing/json/Lexer;)Lscala/util/parsing/combinator/Parsers$Parser<Lscala/util/parsing/syntax/Tokens$Token;>;;
const #388 = Asciz	headOptionTailToFunList;
const #389 = Asciz	(Lscala/Function1;)Lscala/Function1;;
const #390 = Asciz	(Lscala/util/parsing/combinator/ImplicitConversions;Lscala/Function1;)Lscala/Function1;;
const #391 = NameAndType	#388:#390;//  headOptionTailToFunList:(Lscala/util/parsing/combinator/ImplicitConversions;Lscala/Function1;)Lscala/Function1;
const #392 = Method	#16.#391;	//  scala/util/parsing/combinator/ImplicitConversions$class.headOptionTailToFunList:(Lscala/util/parsing/combinator/ImplicitConversions;Lscala/Function1;)Lscala/Function1;
const #393 = Asciz	f;
const #394 = Asciz	Lscala/Function1;;
const #395 = Asciz	flatten5;
const #396 = Asciz	(Lscala/Function5;)Lscala/Function1;;
const #397 = Asciz	(Lscala/util/parsing/combinator/ImplicitConversions;Lscala/Function5;)Lscala/Function1;;
const #398 = NameAndType	#395:#397;//  flatten5:(Lscala/util/parsing/combinator/ImplicitConversions;Lscala/Function5;)Lscala/Function1;
const #399 = Method	#16.#398;	//  scala/util/parsing/combinator/ImplicitConversions$class.flatten5:(Lscala/util/parsing/combinator/ImplicitConversions;Lscala/Function5;)Lscala/Function1;
const #400 = Asciz	Lscala/Function5;;
const #401 = Asciz	flatten4;
const #402 = Asciz	(Lscala/Function4;)Lscala/Function1;;
const #403 = Asciz	(Lscala/util/parsing/combinator/ImplicitConversions;Lscala/Function4;)Lscala/Function1;;
const #404 = NameAndType	#401:#403;//  flatten4:(Lscala/util/parsing/combinator/ImplicitConversions;Lscala/Function4;)Lscala/Function1;
const #405 = Method	#16.#404;	//  scala/util/parsing/combinator/ImplicitConversions$class.flatten4:(Lscala/util/parsing/combinator/ImplicitConversions;Lscala/Function4;)Lscala/Function1;
const #406 = Asciz	Lscala/Function4;;
const #407 = Asciz	flatten3;
const #408 = Asciz	(Lscala/Function3;)Lscala/Function1;;
const #409 = Asciz	(Lscala/util/parsing/combinator/ImplicitConversions;Lscala/Function3;)Lscala/Function1;;
const #410 = NameAndType	#407:#409;//  flatten3:(Lscala/util/parsing/combinator/ImplicitConversions;Lscala/Function3;)Lscala/Function1;
const #411 = Method	#16.#410;	//  scala/util/parsing/combinator/ImplicitConversions$class.flatten3:(Lscala/util/parsing/combinator/ImplicitConversions;Lscala/Function3;)Lscala/Function1;
const #412 = Asciz	Lscala/Function3;;
const #413 = Asciz	flatten2;
const #414 = Asciz	(Lscala/Function2;)Lscala/Function1;;
const #415 = Asciz	(Lscala/util/parsing/combinator/ImplicitConversions;Lscala/Function2;)Lscala/Function1;;
const #416 = NameAndType	#413:#415;//  flatten2:(Lscala/util/parsing/combinator/ImplicitConversions;Lscala/Function2;)Lscala/Function1;
const #417 = Method	#16.#416;	//  scala/util/parsing/combinator/ImplicitConversions$class.flatten2:(Lscala/util/parsing/combinator/ImplicitConversions;Lscala/Function2;)Lscala/Function1;
const #418 = Asciz	Lscala/Function2;;
const #419 = Asciz	ScalaSig;
const #420 = Asciz	InnerClasses;
const #421 = Asciz	Parser;
const #422 = Asciz	scala/util/parsing/syntax/Tokens;
const #423 = class	#422;	//  scala/util/parsing/syntax/Tokens
const #424 = Asciz	ErrorToken;
const #425 = Asciz	Keyword;
const #426 = Asciz	$anonfun$sign$1;
const #427 = Asciz	$anonfun$token$9;
const #428 = Asciz	$anonfun$token$8;
const #429 = Asciz	$anonfun$token$7;
const #430 = Asciz	$anonfun$token$6;
const #431 = Asciz	$anonfun$token$5;
const #432 = Asciz	$anonfun$token$4;
const #433 = Asciz	$anonfun$token$3;
const #434 = Asciz	$anonfun$token$2;
const #435 = Asciz	$anonfun$token$1;
const #436 = Asciz	$anonfun$string$3;
const #437 = Asciz	$anonfun$string$2;
const #438 = Asciz	$anonfun$string$1;
const #439 = Asciz	$anonfun$number$3;
const #440 = Asciz	$anonfun$number$2;
const #441 = Asciz	$anonfun$number$1;
const #442 = Asciz	$anonfun$intPart$1;
const #443 = Asciz	$anonfun$intList$2;
const #444 = Asciz	$anonfun$intList$1;
const #445 = Asciz	$anonfun$expPart$3;
const #446 = Asciz	$anonfun$expPart$2;
const #447 = Asciz	$anonfun$expPart$1;
const #448 = Asciz	$anonfun$nonzero$1;
const #449 = Asciz	$anonfun$charSeq$9;
const #450 = Asciz	$anonfun$charSeq$8;
const #451 = Asciz	$anonfun$charSeq$7;
const #452 = Asciz	$anonfun$charSeq$6;
const #453 = Asciz	$anonfun$charSeq$5;
const #454 = Asciz	$anonfun$charSeq$4;
const #455 = Asciz	$anonfun$charSeq$3;
const #456 = Asciz	$anonfun$charSeq$2;
const #457 = Asciz	$anonfun$charSeq$1;
const #458 = Asciz	$anonfun$fracPart$2;
const #459 = Asciz	$anonfun$fracPart$1;
const #460 = Asciz	$anonfun$exponent$1;
const #461 = Asciz	$anonfun$hexDigit$1;
const #462 = Asciz	$anonfun$whitespace$1;
const #463 = Asciz	$anonfun$scala$util$parsing$json$Lexer$$unicodeBlock$4;
const #464 = Asciz	$anonfun$scala$util$parsing$json$Lexer$$unicodeBlock$3;
const #465 = Asciz	$anonfun$scala$util$parsing$json$Lexer$$unicodeBlock$2;
const #466 = Asciz	$anonfun$scala$util$parsing$json$Lexer$$unicodeBlock$1;
const #467 = Asciz	scala/util/parsing/combinator/ImplicitConversions;
const #468 = class	#467;	//  scala/util/parsing/combinator/ImplicitConversions
const #469 = Asciz	scala/ScalaObject;
const #470 = class	#469;	//  scala/ScalaObject

{
public scala.util.parsing.json.Lexer();
  Code:
   Stack=5, Locals=1, Args_size=1
   0:	aload_0
   1:	invokespecial	#14; //Method scala/util/parsing/combinator/lexical/StdLexical."<init>":()V
   4:	aload_0
   5:	invokestatic	#20; //Method scala/util/parsing/combinator/ImplicitConversions$class.$init$:(Lscala/util/parsing/combinator/ImplicitConversions;)V
   8:	aload_0
   9:	getstatic	#26; //Field scala/Predef$.MODULE$:Lscala/Predef$;
   12:	invokevirtual	#30; //Method scala/Predef$.Set:()Lscala/collection/immutable/Set$;
   15:	getstatic	#26; //Field scala/Predef$.MODULE$:Lscala/Predef$;
   18:	iconst_0
   19:	newarray char
   21:	invokevirtual	#34; //Method scala/Predef$.wrapCharArray:([C)Lscala/collection/mutable/WrappedArray;
   24:	invokevirtual	#40; //Method scala/collection/immutable/Set$.apply:(Lscala/collection/Seq;)Lscala/collection/Traversable;
   27:	checkcast	#42; //class scala/collection/generic/Addable
   30:	getstatic	#26; //Field scala/Predef$.MODULE$:Lscala/Predef$;
   33:	getstatic	#26; //Field scala/Predef$.MODULE$:Lscala/Predef$;
   36:	ldc	#44; //String 0123456789abcdefABCDEF
   38:	invokevirtual	#48; //Method scala/Predef$.augmentString:(Ljava/lang/String;)Lscala/collection/immutable/StringOps;
   41:	getstatic	#53; //Field scala/reflect/Manifest$.MODULE$:Lscala/reflect/Manifest$;
   44:	invokevirtual	#57; //Method scala/reflect/Manifest$.Char:()Ljava/lang/Object;
   47:	checkcast	#59; //class scala/reflect/ClassManifest
   50:	invokeinterface	#65,  2; //InterfaceMethod scala/collection/TraversableLike.toArray:(Lscala/reflect/ClassManifest;)Ljava/lang/Object;
   55:	checkcast	#67; //class "[C"
   58:	invokevirtual	#34; //Method scala/Predef$.wrapCharArray:([C)Lscala/collection/mutable/WrappedArray;
   61:	invokeinterface	#71,  2; //InterfaceMethod scala/collection/generic/Addable.$plus$plus:(Lscala/collection/Traversable;)Lscala/collection/generic/Addable;
   66:	checkcast	#73; //class scala/collection/immutable/Set
   69:	putfield	#77; //Field hexDigits:Lscala/collection/immutable/Set;
   72:	return
  LineNumberTable: 
   line 22: 0
   line 81: 8


public final scala.util.parsing.combinator.Parsers$Parser scala$util$parsing$json$Lexer$$unicodeBlock();
  Code:
   Stack=4, Locals=1, Args_size=1
   0:	aload_0
   1:	invokevirtual	#82; //Method hexDigit:()Lscala/util/parsing/combinator/Parsers$Parser;
   4:	new	#84; //class scala/util/parsing/json/Lexer$$anonfun$scala$util$parsing$json$Lexer$$unicodeBlock$1
   7:	dup
   8:	aload_0
   9:	invokespecial	#87; //Method scala/util/parsing/json/Lexer$$anonfun$scala$util$parsing$json$Lexer$$unicodeBlock$1."<init>":(Lscala/util/parsing/json/Lexer;)V
   12:	invokevirtual	#93; //Method scala/util/parsing/combinator/Parsers$Parser.$tilde:(Lscala/Function0;)Lscala/util/parsing/combinator/Parsers$Parser;
   15:	new	#95; //class scala/util/parsing/json/Lexer$$anonfun$scala$util$parsing$json$Lexer$$unicodeBlock$2
   18:	dup
   19:	aload_0
   20:	invokespecial	#96; //Method scala/util/parsing/json/Lexer$$anonfun$scala$util$parsing$json$Lexer$$unicodeBlock$2."<init>":(Lscala/util/parsing/json/Lexer;)V
   23:	invokevirtual	#93; //Method scala/util/parsing/combinator/Parsers$Parser.$tilde:(Lscala/Function0;)Lscala/util/parsing/combinator/Parsers$Parser;
   26:	new	#98; //class scala/util/parsing/json/Lexer$$anonfun$scala$util$parsing$json$Lexer$$unicodeBlock$3
   29:	dup
   30:	aload_0
   31:	invokespecial	#99; //Method scala/util/parsing/json/Lexer$$anonfun$scala$util$parsing$json$Lexer$$unicodeBlock$3."<init>":(Lscala/util/parsing/json/Lexer;)V
   34:	invokevirtual	#93; //Method scala/util/parsing/combinator/Parsers$Parser.$tilde:(Lscala/Function0;)Lscala/util/parsing/combinator/Parsers$Parser;
   37:	new	#101; //class scala/util/parsing/json/Lexer$$anonfun$scala$util$parsing$json$Lexer$$unicodeBlock$4
   40:	dup
   41:	aload_0
   42:	invokespecial	#102; //Method scala/util/parsing/json/Lexer$$anonfun$scala$util$parsing$json$Lexer$$unicodeBlock$4."<init>":(Lscala/util/parsing/json/Lexer;)V
   45:	invokevirtual	#106; //Method scala/util/parsing/combinator/Parsers$Parser.$up$up:(Lscala/Function1;)Lscala/util/parsing/combinator/Parsers$Parser;
   48:	areturn
  LineNumberTable: 
   line 84: 0


public scala.util.parsing.combinator.Parsers$Parser hexDigit();
  Code:
   Stack=5, Locals=1, Args_size=1
   0:	aload_0
   1:	ldc	#108; //String hex digit
   3:	new	#110; //class scala/util/parsing/json/Lexer$$anonfun$hexDigit$1
   6:	dup
   7:	aload_0
   8:	invokespecial	#111; //Method scala/util/parsing/json/Lexer$$anonfun$hexDigit$1."<init>":(Lscala/util/parsing/json/Lexer;)V
   11:	invokeinterface	#117,  3; //InterfaceMethod scala/util/parsing/combinator/Parsers.elem:(Ljava/lang/String;Lscala/Function1;)Lscala/util/parsing/combinator/Parsers$Parser;
   16:	areturn
  LineNumberTable: 
   line 82: 0

  Signature: length = 0x2
   00 76 

public scala.collection.immutable.Set hexDigits();
  Code:
   Stack=1, Locals=1, Args_size=1
   0:	aload_0
   1:	getfield	#77; //Field hexDigits:Lscala/collection/immutable/Set;
   4:	areturn
  LineNumberTable: 
   line 81: 0

  Signature: length = 0x2
   00 78 

public scala.util.parsing.combinator.Parsers$Parser charSeq();
  Code:
   Stack=4, Locals=2, Args_size=1
   0:	aload_0
   1:	ldc	#122; //int 92
   3:	istore_1
   4:	iload_1
   5:	invokestatic	#128; //Method scala/runtime/BoxesRunTime.boxToCharacter:(C)Ljava/lang/Character;
   8:	invokeinterface	#132,  2; //InterfaceMethod scala/util/parsing/combinator/Parsers.accept:(Ljava/lang/Object;)Lscala/util/parsing/combinator/Parsers$Parser;
   13:	new	#134; //class scala/util/parsing/json/Lexer$$anonfun$charSeq$1
   16:	dup
   17:	aload_0
   18:	invokespecial	#135; //Method scala/util/parsing/json/Lexer$$anonfun$charSeq$1."<init>":(Lscala/util/parsing/json/Lexer;)V
   21:	invokevirtual	#93; //Method scala/util/parsing/combinator/Parsers$Parser.$tilde:(Lscala/Function0;)Lscala/util/parsing/combinator/Parsers$Parser;
   24:	ldc	#137; //String \"
   26:	invokevirtual	#140; //Method scala/util/parsing/combinator/Parsers$Parser.$up$up$up:(Ljava/lang/Object;)Lscala/util/parsing/combinator/Parsers$Parser;
   29:	new	#142; //class scala/util/parsing/json/Lexer$$anonfun$charSeq$2
   32:	dup
   33:	aload_0
   34:	invokespecial	#143; //Method scala/util/parsing/json/Lexer$$anonfun$charSeq$2."<init>":(Lscala/util/parsing/json/Lexer;)V
   37:	invokevirtual	#146; //Method scala/util/parsing/combinator/Parsers$Parser.$bar:(Lscala/Function0;)Lscala/util/parsing/combinator/Parsers$Parser;
   40:	new	#148; //class scala/util/parsing/json/Lexer$$anonfun$charSeq$3
   43:	dup
   44:	aload_0
   45:	invokespecial	#149; //Method scala/util/parsing/json/Lexer$$anonfun$charSeq$3."<init>":(Lscala/util/parsing/json/Lexer;)V
   48:	invokevirtual	#146; //Method scala/util/parsing/combinator/Parsers$Parser.$bar:(Lscala/Function0;)Lscala/util/parsing/combinator/Parsers$Parser;
   51:	new	#151; //class scala/util/parsing/json/Lexer$$anonfun$charSeq$4
   54:	dup
   55:	aload_0
   56:	invokespecial	#152; //Method scala/util/parsing/json/Lexer$$anonfun$charSeq$4."<init>":(Lscala/util/parsing/json/Lexer;)V
   59:	invokevirtual	#146; //Method scala/util/parsing/combinator/Parsers$Parser.$bar:(Lscala/Function0;)Lscala/util/parsing/combinator/Parsers$Parser;
   62:	new	#154; //class scala/util/parsing/json/Lexer$$anonfun$charSeq$5
   65:	dup
   66:	aload_0
   67:	invokespecial	#155; //Method scala/util/parsing/json/Lexer$$anonfun$charSeq$5."<init>":(Lscala/util/parsing/json/Lexer;)V
   70:	invokevirtual	#146; //Method scala/util/parsing/combinator/Parsers$Parser.$bar:(Lscala/Function0;)Lscala/util/parsing/combinator/Parsers$Parser;
   73:	new	#157; //class scala/util/parsing/json/Lexer$$anonfun$charSeq$6
   76:	dup
   77:	aload_0
   78:	invokespecial	#158; //Method scala/util/parsing/json/Lexer$$anonfun$charSeq$6."<init>":(Lscala/util/parsing/json/Lexer;)V
   81:	invokevirtual	#146; //Method scala/util/parsing/combinator/Parsers$Parser.$bar:(Lscala/Function0;)Lscala/util/parsing/combinator/Parsers$Parser;
   84:	new	#160; //class scala/util/parsing/json/Lexer$$anonfun$charSeq$7
   87:	dup
   88:	aload_0
   89:	invokespecial	#161; //Method scala/util/parsing/json/Lexer$$anonfun$charSeq$7."<init>":(Lscala/util/parsing/json/Lexer;)V
   92:	invokevirtual	#146; //Method scala/util/parsing/combinator/Parsers$Parser.$bar:(Lscala/Function0;)Lscala/util/parsing/combinator/Parsers$Parser;
   95:	new	#163; //class scala/util/parsing/json/Lexer$$anonfun$charSeq$8
   98:	dup
   99:	aload_0
   100:	invokespecial	#164; //Method scala/util/parsing/json/Lexer$$anonfun$charSeq$8."<init>":(Lscala/util/parsing/json/Lexer;)V
   103:	invokevirtual	#146; //Method scala/util/parsing/combinator/Parsers$Parser.$bar:(Lscala/Function0;)Lscala/util/parsing/combinator/Parsers$Parser;
   106:	new	#166; //class scala/util/parsing/json/Lexer$$anonfun$charSeq$9
   109:	dup
   110:	aload_0
   111:	invokespecial	#167; //Method scala/util/parsing/json/Lexer$$anonfun$charSeq$9."<init>":(Lscala/util/parsing/json/Lexer;)V
   114:	invokevirtual	#146; //Method scala/util/parsing/combinator/Parsers$Parser.$bar:(Lscala/Function0;)Lscala/util/parsing/combinator/Parsers$Parser;
   117:	areturn
  LineNumberTable: 
   line 71: 0
   line 72: 29
   line 73: 40
   line 74: 51
   line 75: 62
   line 76: 73
   line 77: 84
   line 78: 95
   line 79: 106

  Signature: length = 0x2
   00 FFFFFFA8 

public scala.util.parsing.combinator.Parsers$Parser sign();
  Code:
   Stack=5, Locals=1, Args_size=1
   0:	aload_0
   1:	ldc	#171; //String sign character
   3:	new	#173; //class scala/util/parsing/json/Lexer$$anonfun$sign$1
   6:	dup
   7:	aload_0
   8:	invokespecial	#174; //Method scala/util/parsing/json/Lexer$$anonfun$sign$1."<init>":(Lscala/util/parsing/json/Lexer;)V
   11:	invokeinterface	#117,  3; //InterfaceMethod scala/util/parsing/combinator/Parsers.elem:(Ljava/lang/String;Lscala/Function1;)Lscala/util/parsing/combinator/Parsers$Parser;
   16:	areturn
  LineNumberTable: 
   line 68: 0

  Signature: length = 0x2
   00 76 

public scala.util.parsing.combinator.Parsers$Parser exponent();
  Code:
   Stack=5, Locals=1, Args_size=1
   0:	aload_0
   1:	ldc	#177; //String exponent character
   3:	new	#179; //class scala/util/parsing/json/Lexer$$anonfun$exponent$1
   6:	dup
   7:	aload_0
   8:	invokespecial	#180; //Method scala/util/parsing/json/Lexer$$anonfun$exponent$1."<init>":(Lscala/util/parsing/json/Lexer;)V
   11:	invokeinterface	#117,  3; //InterfaceMethod scala/util/parsing/combinator/Parsers.elem:(Ljava/lang/String;Lscala/Function1;)Lscala/util/parsing/combinator/Parsers$Parser;
   16:	areturn
  LineNumberTable: 
   line 67: 0

  Signature: length = 0x2
   00 76 

public scala.util.parsing.combinator.Parsers$Parser nonzero();
  Code:
   Stack=5, Locals=1, Args_size=1
   0:	aload_0
   1:	ldc	#183; //String nonzero digit
   3:	new	#185; //class scala/util/parsing/json/Lexer$$anonfun$nonzero$1
   6:	dup
   7:	aload_0
   8:	invokespecial	#186; //Method scala/util/parsing/json/Lexer$$anonfun$nonzero$1."<init>":(Lscala/util/parsing/json/Lexer;)V
   11:	invokeinterface	#117,  3; //InterfaceMethod scala/util/parsing/combinator/Parsers.elem:(Ljava/lang/String;Lscala/Function1;)Lscala/util/parsing/combinator/Parsers$Parser;
   16:	areturn
  LineNumberTable: 
   line 66: 0

  Signature: length = 0x2
   00 76 

public scala.util.parsing.combinator.Parsers$Parser zero();
  Code:
   Stack=2, Locals=2, Args_size=1
   0:	aload_0
   1:	ldc	#188; //int 48
   3:	istore_1
   4:	iload_1
   5:	invokestatic	#128; //Method scala/runtime/BoxesRunTime.boxToCharacter:(C)Ljava/lang/Character;
   8:	invokeinterface	#132,  2; //InterfaceMethod scala/util/parsing/combinator/Parsers.accept:(Ljava/lang/Object;)Lscala/util/parsing/combinator/Parsers$Parser;
   13:	ldc	#190; //String 0
   15:	invokevirtual	#140; //Method scala/util/parsing/combinator/Parsers$Parser.$up$up$up:(Ljava/lang/Object;)Lscala/util/parsing/combinator/Parsers$Parser;
   18:	areturn
  LineNumberTable: 
   line 65: 0

  Signature: length = 0x2
   00 FFFFFFA8 

public final java.lang.String scala$util$parsing$json$Lexer$$optString(java.lang.String, scala.Option);
  Code:
   Stack=3, Locals=5, Args_size=3
   0:	aload_2
   1:	instanceof	#194; //class scala/Some
   4:	ifeq	59
   7:	aload_2
   8:	checkcast	#194; //class scala/Some
   11:	astore_3
   12:	aload_3
   13:	getfield	#198; //Field scala/Some.x:Ljava/lang/Object;
   16:	astore	4
   18:	iconst_1
   19:	ifeq	47
   22:	new	#200; //class scala/collection/mutable/StringBuilder
   25:	dup
   26:	invokespecial	#201; //Method scala/collection/mutable/StringBuilder."<init>":()V
   29:	aload_1
   30:	invokevirtual	#205; //Method scala/collection/mutable/StringBuilder.append:(Ljava/lang/Object;)Lscala/collection/mutable/StringBuilder;
   33:	aload	4
   35:	invokevirtual	#211; //Method java/lang/Object.toString:()Ljava/lang/String;
   38:	invokevirtual	#205; //Method scala/collection/mutable/StringBuilder.append:(Ljava/lang/Object;)Lscala/collection/mutable/StringBuilder;
   41:	invokevirtual	#212; //Method scala/collection/mutable/StringBuilder.toString:()Ljava/lang/String;
   44:	goto	87
   47:	new	#214; //class scala/MatchError
   50:	dup
   51:	aload_2
   52:	invokevirtual	#217; //Method scala/Option.toString:()Ljava/lang/String;
   55:	invokespecial	#220; //Method scala/MatchError."<init>":(Ljava/lang/String;)V
   58:	athrow
   59:	getstatic	#225; //Field scala/None$.MODULE$:Lscala/None$;
   62:	dup
   63:	ifnonnull	74
   66:	pop
   67:	aload_2
   68:	ifnull	81
   71:	goto	100
   74:	aload_2
   75:	invokevirtual	#229; //Method java/lang/Object.equals:(Ljava/lang/Object;)Z
   78:	ifeq	100
   81:	iconst_1
   82:	ifeq	88
   85:	ldc	#231; //String 
   87:	areturn
   88:	new	#214; //class scala/MatchError
   91:	dup
   92:	aload_2
   93:	invokevirtual	#217; //Method scala/Option.toString:()Ljava/lang/String;
   96:	invokespecial	#220; //Method scala/MatchError."<init>":(Ljava/lang/String;)V
   99:	athrow
   100:	new	#214; //class scala/MatchError
   103:	dup
   104:	aload_2
   105:	invokevirtual	#217; //Method scala/Option.toString:()Ljava/lang/String;
   108:	invokespecial	#220; //Method scala/MatchError."<init>":(Ljava/lang/String;)V
   111:	athrow
  LineNumberTable: 
   line 60: 0
   line 21: 18
   line 61: 22
   line 60: 47
   line 21: 81
   line 62: 85
   line 60: 87

  LocalVariableTable: 
   Start  Length  Slot  Name   Signature
   0      112      0    this       Lscala/util/parsing/json/Lexer;
   0      112      1    pre       Ljava/lang/String;
   0      112      2    a       Lscala/Option;
   12      47      3    temp26       Lscala/Some;
   18      41      4    temp27       Ljava/lang/Object;


public scala.util.parsing.combinator.Parsers$Parser expPart();
  Code:
   Stack=4, Locals=1, Args_size=1
   0:	aload_0
   1:	invokevirtual	#244; //Method exponent:()Lscala/util/parsing/combinator/Parsers$Parser;
   4:	new	#246; //class scala/util/parsing/json/Lexer$$anonfun$expPart$1
   7:	dup
   8:	aload_0
   9:	invokespecial	#247; //Method scala/util/parsing/json/Lexer$$anonfun$expPart$1."<init>":(Lscala/util/parsing/json/Lexer;)V
   12:	invokevirtual	#93; //Method scala/util/parsing/combinator/Parsers$Parser.$tilde:(Lscala/Function0;)Lscala/util/parsing/combinator/Parsers$Parser;
   15:	new	#249; //class scala/util/parsing/json/Lexer$$anonfun$expPart$2
   18:	dup
   19:	aload_0
   20:	invokespecial	#250; //Method scala/util/parsing/json/Lexer$$anonfun$expPart$2."<init>":(Lscala/util/parsing/json/Lexer;)V
   23:	invokevirtual	#93; //Method scala/util/parsing/combinator/Parsers$Parser.$tilde:(Lscala/Function0;)Lscala/util/parsing/combinator/Parsers$Parser;
   26:	new	#252; //class scala/util/parsing/json/Lexer$$anonfun$expPart$3
   29:	dup
   30:	aload_0
   31:	invokespecial	#253; //Method scala/util/parsing/json/Lexer$$anonfun$expPart$3."<init>":(Lscala/util/parsing/json/Lexer;)V
   34:	invokevirtual	#106; //Method scala/util/parsing/combinator/Parsers$Parser.$up$up:(Lscala/Function1;)Lscala/util/parsing/combinator/Parsers$Parser;
   37:	areturn
  LineNumberTable: 
   line 56: 0

  Signature: length = 0x2
   00 FFFFFFA8 

public scala.util.parsing.combinator.Parsers$Parser fracPart();
  Code:
   Stack=4, Locals=2, Args_size=1
   0:	aload_0
   1:	ldc	#255; //int 46
   3:	istore_1
   4:	iload_1
   5:	invokestatic	#128; //Method scala/runtime/BoxesRunTime.boxToCharacter:(C)Ljava/lang/Character;
   8:	invokeinterface	#132,  2; //InterfaceMethod scala/util/parsing/combinator/Parsers.accept:(Ljava/lang/Object;)Lscala/util/parsing/combinator/Parsers$Parser;
   13:	new	#257; //class scala/util/parsing/json/Lexer$$anonfun$fracPart$1
   16:	dup
   17:	aload_0
   18:	invokespecial	#258; //Method scala/util/parsing/json/Lexer$$anonfun$fracPart$1."<init>":(Lscala/util/parsing/json/Lexer;)V
   21:	invokevirtual	#261; //Method scala/util/parsing/combinator/Parsers$Parser.$tilde$greater:(Lscala/Function0;)Lscala/util/parsing/combinator/Parsers$Parser;
   24:	new	#263; //class scala/util/parsing/json/Lexer$$anonfun$fracPart$2
   27:	dup
   28:	aload_0
   29:	invokespecial	#264; //Method scala/util/parsing/json/Lexer$$anonfun$fracPart$2."<init>":(Lscala/util/parsing/json/Lexer;)V
   32:	invokevirtual	#106; //Method scala/util/parsing/combinator/Parsers$Parser.$up$up:(Lscala/Function1;)Lscala/util/parsing/combinator/Parsers$Parser;
   35:	areturn
  LineNumberTable: 
   line 55: 0

  Signature: length = 0x2
   00 FFFFFFA8 

public scala.util.parsing.combinator.Parsers$Parser intList();
  Code:
   Stack=4, Locals=1, Args_size=1
   0:	aload_0
   1:	invokevirtual	#267; //Method nonzero:()Lscala/util/parsing/combinator/Parsers$Parser;
   4:	new	#269; //class scala/util/parsing/json/Lexer$$anonfun$intList$1
   7:	dup
   8:	aload_0
   9:	invokespecial	#270; //Method scala/util/parsing/json/Lexer$$anonfun$intList$1."<init>":(Lscala/util/parsing/json/Lexer;)V
   12:	invokevirtual	#93; //Method scala/util/parsing/combinator/Parsers$Parser.$tilde:(Lscala/Function0;)Lscala/util/parsing/combinator/Parsers$Parser;
   15:	new	#272; //class scala/util/parsing/json/Lexer$$anonfun$intList$2
   18:	dup
   19:	aload_0
   20:	invokespecial	#273; //Method scala/util/parsing/json/Lexer$$anonfun$intList$2."<init>":(Lscala/util/parsing/json/Lexer;)V
   23:	invokevirtual	#106; //Method scala/util/parsing/combinator/Parsers$Parser.$up$up:(Lscala/Function1;)Lscala/util/parsing/combinator/Parsers$Parser;
   26:	areturn
  LineNumberTable: 
   line 54: 0

  Signature: length = 0x2
   00 FFFFFFA8 

public scala.util.parsing.combinator.Parsers$Parser intPart();
  Code:
   Stack=4, Locals=1, Args_size=1
   0:	aload_0
   1:	invokevirtual	#276; //Method zero:()Lscala/util/parsing/combinator/Parsers$Parser;
   4:	new	#278; //class scala/util/parsing/json/Lexer$$anonfun$intPart$1
   7:	dup
   8:	aload_0
   9:	invokespecial	#279; //Method scala/util/parsing/json/Lexer$$anonfun$intPart$1."<init>":(Lscala/util/parsing/json/Lexer;)V
   12:	invokevirtual	#146; //Method scala/util/parsing/combinator/Parsers$Parser.$bar:(Lscala/Function0;)Lscala/util/parsing/combinator/Parsers$Parser;
   15:	areturn
  LineNumberTable: 
   line 53: 0

  Signature: length = 0x2
   00 FFFFFFA8 

public scala.util.parsing.combinator.Parsers$Parser number();
  Code:
   Stack=4, Locals=1, Args_size=1
   0:	aload_0
   1:	invokevirtual	#282; //Method intPart:()Lscala/util/parsing/combinator/Parsers$Parser;
   4:	new	#284; //class scala/util/parsing/json/Lexer$$anonfun$number$1
   7:	dup
   8:	aload_0
   9:	invokespecial	#285; //Method scala/util/parsing/json/Lexer$$anonfun$number$1."<init>":(Lscala/util/parsing/json/Lexer;)V
   12:	invokevirtual	#93; //Method scala/util/parsing/combinator/Parsers$Parser.$tilde:(Lscala/Function0;)Lscala/util/parsing/combinator/Parsers$Parser;
   15:	new	#287; //class scala/util/parsing/json/Lexer$$anonfun$number$2
   18:	dup
   19:	aload_0
   20:	invokespecial	#288; //Method scala/util/parsing/json/Lexer$$anonfun$number$2."<init>":(Lscala/util/parsing/json/Lexer;)V
   23:	invokevirtual	#93; //Method scala/util/parsing/combinator/Parsers$Parser.$tilde:(Lscala/Function0;)Lscala/util/parsing/combinator/Parsers$Parser;
   26:	new	#290; //class scala/util/parsing/json/Lexer$$anonfun$number$3
   29:	dup
   30:	aload_0
   31:	invokespecial	#291; //Method scala/util/parsing/json/Lexer$$anonfun$number$3."<init>":(Lscala/util/parsing/json/Lexer;)V
   34:	invokevirtual	#106; //Method scala/util/parsing/combinator/Parsers$Parser.$up$up:(Lscala/Function1;)Lscala/util/parsing/combinator/Parsers$Parser;
   37:	areturn
  LineNumberTable: 
   line 50: 0

  Signature: length = 0x2
   00 FFFFFFA8 

public scala.util.parsing.combinator.Parsers$Parser whitespace();
  Code:
   Stack=4, Locals=1, Args_size=1
   0:	aload_0
   1:	new	#294; //class scala/util/parsing/json/Lexer$$anonfun$whitespace$1
   4:	dup
   5:	aload_0
   6:	invokespecial	#295; //Method scala/util/parsing/json/Lexer$$anonfun$whitespace$1."<init>":(Lscala/util/parsing/json/Lexer;)V
   9:	invokeinterface	#298,  2; //InterfaceMethod scala/util/parsing/combinator/Parsers.rep:(Lscala/Function0;)Lscala/util/parsing/combinator/Parsers$Parser;
   14:	areturn
  LineNumberTable: 
   line 48: 0

  Signature: length = 0x2
   01 2B 

public scala.util.parsing.combinator.Parsers$Parser string();
  Code:
   Stack=4, Locals=2, Args_size=1
   0:	aload_0
   1:	ldc_w	#301; //int 34
   4:	istore_1
   5:	iload_1
   6:	invokestatic	#128; //Method scala/runtime/BoxesRunTime.boxToCharacter:(C)Ljava/lang/Character;
   9:	invokeinterface	#132,  2; //InterfaceMethod scala/util/parsing/combinator/Parsers.accept:(Ljava/lang/Object;)Lscala/util/parsing/combinator/Parsers$Parser;
   14:	new	#303; //class scala/util/parsing/json/Lexer$$anonfun$string$1
   17:	dup
   18:	aload_0
   19:	invokespecial	#304; //Method scala/util/parsing/json/Lexer$$anonfun$string$1."<init>":(Lscala/util/parsing/json/Lexer;)V
   22:	invokevirtual	#261; //Method scala/util/parsing/combinator/Parsers$Parser.$tilde$greater:(Lscala/Function0;)Lscala/util/parsing/combinator/Parsers$Parser;
   25:	new	#306; //class scala/util/parsing/json/Lexer$$anonfun$string$2
   28:	dup
   29:	aload_0
   30:	invokespecial	#307; //Method scala/util/parsing/json/Lexer$$anonfun$string$2."<init>":(Lscala/util/parsing/json/Lexer;)V
   33:	invokevirtual	#310; //Method scala/util/parsing/combinator/Parsers$Parser.$less$tilde:(Lscala/Function0;)Lscala/util/parsing/combinator/Parsers$Parser;
   36:	new	#312; //class scala/util/parsing/json/Lexer$$anonfun$string$3
   39:	dup
   40:	aload_0
   41:	invokespecial	#313; //Method scala/util/parsing/json/Lexer$$anonfun$string$3."<init>":(Lscala/util/parsing/json/Lexer;)V
   44:	invokevirtual	#106; //Method scala/util/parsing/combinator/Parsers$Parser.$up$up:(Lscala/Function1;)Lscala/util/parsing/combinator/Parsers$Parser;
   47:	areturn
  LineNumberTable: 
   line 46: 0

  Signature: length = 0x2
   00 FFFFFFA8 

public scala.Product checkKeyword(scala.collection.immutable.List);
  Code:
   Stack=5, Locals=3, Args_size=2
   0:	aload_1
   1:	ldc	#231; //String 
   3:	invokeinterface	#319,  2; //InterfaceMethod scala/collection/TraversableLike.mkString:(Ljava/lang/String;)Ljava/lang/String;
   8:	astore_2
   9:	aload_0
   10:	invokevirtual	#323; //Method reserved:()Lscala/collection/mutable/HashSet;
   13:	aload_2
   14:	invokevirtual	#328; //Method scala/collection/mutable/HashSet.contains:(Ljava/lang/Object;)Z
   17:	ifeq	32
   20:	new	#330; //class scala/util/parsing/syntax/StdTokens$Keyword
   23:	dup
   24:	aload_0
   25:	aload_2
   26:	invokespecial	#333; //Method scala/util/parsing/syntax/StdTokens$Keyword."<init>":(Lscala/util/parsing/syntax/StdTokens;Ljava/lang/String;)V
   29:	goto	60
   32:	new	#335; //class scala/util/parsing/syntax/Tokens$ErrorToken
   35:	dup
   36:	aload_0
   37:	new	#200; //class scala/collection/mutable/StringBuilder
   40:	dup
   41:	invokespecial	#201; //Method scala/collection/mutable/StringBuilder."<init>":()V
   44:	ldc_w	#337; //String Not a keyword: 
   47:	invokevirtual	#205; //Method scala/collection/mutable/StringBuilder.append:(Ljava/lang/Object;)Lscala/collection/mutable/StringBuilder;
   50:	aload_2
   51:	invokevirtual	#205; //Method scala/collection/mutable/StringBuilder.append:(Ljava/lang/Object;)Lscala/collection/mutable/StringBuilder;
   54:	invokevirtual	#212; //Method scala/collection/mutable/StringBuilder.toString:()Ljava/lang/String;
   57:	invokespecial	#340; //Method scala/util/parsing/syntax/Tokens$ErrorToken."<init>":(Lscala/util/parsing/syntax/Tokens;Ljava/lang/String;)V
   60:	areturn
  LineNumberTable: 
   line 39: 0
   line 40: 9
   line 38: 60

  LocalVariableTable: 
   Start  Length  Slot  Name   Signature
   0      61      0    this       Lscala/util/parsing/json/Lexer;
   0      61      1    xs       Lscala/collection/immutable/List;
   9      52      2    strRep       Ljava/lang/String;

  Signature: length = 0x2
   01 58 

public scala.util.parsing.combinator.Parsers$Parser token();
  Code:
   Stack=4, Locals=1, Args_size=1
   0:	aload_0
   1:	invokevirtual	#347; //Method string:()Lscala/util/parsing/combinator/Parsers$Parser;
   4:	aload_0
   5:	invokeinterface	#353,  1; //InterfaceMethod scala/util/parsing/syntax/StdTokens.StringLit:()Lscala/util/parsing/syntax/StdTokens$StringLit$;
   10:	invokevirtual	#106; //Method scala/util/parsing/combinator/Parsers$Parser.$up$up:(Lscala/Function1;)Lscala/util/parsing/combinator/Parsers$Parser;
   13:	new	#355; //class scala/util/parsing/json/Lexer$$anonfun$token$1
   16:	dup
   17:	aload_0
   18:	invokespecial	#356; //Method scala/util/parsing/json/Lexer$$anonfun$token$1."<init>":(Lscala/util/parsing/json/Lexer;)V
   21:	invokevirtual	#146; //Method scala/util/parsing/combinator/Parsers$Parser.$bar:(Lscala/Function0;)Lscala/util/parsing/combinator/Parsers$Parser;
   24:	new	#358; //class scala/util/parsing/json/Lexer$$anonfun$token$2
   27:	dup
   28:	aload_0
   29:	invokespecial	#359; //Method scala/util/parsing/json/Lexer$$anonfun$token$2."<init>":(Lscala/util/parsing/json/Lexer;)V
   32:	invokevirtual	#146; //Method scala/util/parsing/combinator/Parsers$Parser.$bar:(Lscala/Function0;)Lscala/util/parsing/combinator/Parsers$Parser;
   35:	new	#361; //class scala/util/parsing/json/Lexer$$anonfun$token$3
   38:	dup
   39:	aload_0
   40:	invokespecial	#362; //Method scala/util/parsing/json/Lexer$$anonfun$token$3."<init>":(Lscala/util/parsing/json/Lexer;)V
   43:	invokevirtual	#146; //Method scala/util/parsing/combinator/Parsers$Parser.$bar:(Lscala/Function0;)Lscala/util/parsing/combinator/Parsers$Parser;
   46:	new	#364; //class scala/util/parsing/json/Lexer$$anonfun$token$4
   49:	dup
   50:	aload_0
   51:	invokespecial	#365; //Method scala/util/parsing/json/Lexer$$anonfun$token$4."<init>":(Lscala/util/parsing/json/Lexer;)V
   54:	invokevirtual	#146; //Method scala/util/parsing/combinator/Parsers$Parser.$bar:(Lscala/Function0;)Lscala/util/parsing/combinator/Parsers$Parser;
   57:	new	#367; //class scala/util/parsing/json/Lexer$$anonfun$token$5
   60:	dup
   61:	aload_0
   62:	invokespecial	#368; //Method scala/util/parsing/json/Lexer$$anonfun$token$5."<init>":(Lscala/util/parsing/json/Lexer;)V
   65:	invokevirtual	#146; //Method scala/util/parsing/combinator/Parsers$Parser.$bar:(Lscala/Function0;)Lscala/util/parsing/combinator/Parsers$Parser;
   68:	new	#370; //class scala/util/parsing/json/Lexer$$anonfun$token$6
   71:	dup
   72:	aload_0
   73:	invokespecial	#371; //Method scala/util/parsing/json/Lexer$$anonfun$token$6."<init>":(Lscala/util/parsing/json/Lexer;)V
   76:	invokevirtual	#146; //Method scala/util/parsing/combinator/Parsers$Parser.$bar:(Lscala/Function0;)Lscala/util/parsing/combinator/Parsers$Parser;
   79:	new	#373; //class scala/util/parsing/json/Lexer$$anonfun$token$7
   82:	dup
   83:	aload_0
   84:	invokespecial	#374; //Method scala/util/parsing/json/Lexer$$anonfun$token$7."<init>":(Lscala/util/parsing/json/Lexer;)V
   87:	invokevirtual	#146; //Method scala/util/parsing/combinator/Parsers$Parser.$bar:(Lscala/Function0;)Lscala/util/parsing/combinator/Parsers$Parser;
   90:	new	#376; //class scala/util/parsing/json/Lexer$$anonfun$token$8
   93:	dup
   94:	aload_0
   95:	invokespecial	#377; //Method scala/util/parsing/json/Lexer$$anonfun$token$8."<init>":(Lscala/util/parsing/json/Lexer;)V
   98:	invokevirtual	#146; //Method scala/util/parsing/combinator/Parsers$Parser.$bar:(Lscala/Function0;)Lscala/util/parsing/combinator/Parsers$Parser;
   101:	new	#379; //class scala/util/parsing/json/Lexer$$anonfun$token$9
   104:	dup
   105:	aload_0
   106:	invokespecial	#380; //Method scala/util/parsing/json/Lexer$$anonfun$token$9."<init>":(Lscala/util/parsing/json/Lexer;)V
   109:	invokevirtual	#146; //Method scala/util/parsing/combinator/Parsers$Parser.$bar:(Lscala/Function0;)Lscala/util/parsing/combinator/Parsers$Parser;
   112:	areturn
  LineNumberTable: 
   line 26: 0
   line 27: 13
   line 28: 24
   line 29: 35
   line 30: 46
   line 31: 57
   line 32: 68
   line 33: 79
   line 34: 90
   line 35: 101

  Signature: length = 0x2
   01 7D 

public scala.util.parsing.combinator.Parsers$Parser protected$delim(scala.util.parsing.json.Lexer);
  Code:
   Stack=1, Locals=2, Args_size=2
   0:	aload_1
   1:	invokevirtual	#386; //Method delim:()Lscala/util/parsing/combinator/Parsers$Parser;
   4:	areturn
  LineNumberTable: 
   line 32: 0

  Signature: length = 0x2
   01 FFFFFF83 

public scala.Function1 headOptionTailToFunList(scala.Function1);
  Code:
   Stack=2, Locals=2, Args_size=2
   0:	aload_0
   1:	aload_1
   2:	invokestatic	#392; //Method scala/util/parsing/combinator/ImplicitConversions$class.headOptionTailToFunList:(Lscala/util/parsing/combinator/ImplicitConversions;Lscala/Function1;)Lscala/Function1;
   5:	areturn
  LineNumberTable: 
   line 22: 0

  LocalVariableTable: 
   Start  Length  Slot  Name   Signature
   0      6      0    this       Lscala/util/parsing/json/Lexer;
   0      6      1    f       Lscala/Function1;


public scala.Function1 flatten5(scala.Function5);
  Code:
   Stack=2, Locals=2, Args_size=2
   0:	aload_0
   1:	aload_1
   2:	invokestatic	#399; //Method scala/util/parsing/combinator/ImplicitConversions$class.flatten5:(Lscala/util/parsing/combinator/ImplicitConversions;Lscala/Function5;)Lscala/Function1;
   5:	areturn
  LineNumberTable: 
   line 22: 0

  LocalVariableTable: 
   Start  Length  Slot  Name   Signature
   0      6      0    this       Lscala/util/parsing/json/Lexer;
   0      6      1    f       Lscala/Function5;


public scala.Function1 flatten4(scala.Function4);
  Code:
   Stack=2, Locals=2, Args_size=2
   0:	aload_0
   1:	aload_1
   2:	invokestatic	#405; //Method scala/util/parsing/combinator/ImplicitConversions$class.flatten4:(Lscala/util/parsing/combinator/ImplicitConversions;Lscala/Function4;)Lscala/Function1;
   5:	areturn
  LineNumberTable: 
   line 22: 0

  LocalVariableTable: 
   Start  Length  Slot  Name   Signature
   0      6      0    this       Lscala/util/parsing/json/Lexer;
   0      6      1    f       Lscala/Function4;


public scala.Function1 flatten3(scala.Function3);
  Code:
   Stack=2, Locals=2, Args_size=2
   0:	aload_0
   1:	aload_1
   2:	invokestatic	#411; //Method scala/util/parsing/combinator/ImplicitConversions$class.flatten3:(Lscala/util/parsing/combinator/ImplicitConversions;Lscala/Function3;)Lscala/Function1;
   5:	areturn
  LineNumberTable: 
   line 22: 0

  LocalVariableTable: 
   Start  Length  Slot  Name   Signature
   0      6      0    this       Lscala/util/parsing/json/Lexer;
   0      6      1    f       Lscala/Function3;


public scala.Function1 flatten2(scala.Function2);
  Code:
   Stack=2, Locals=2, Args_size=2
   0:	aload_0
   1:	aload_1
   2:	invokestatic	#417; //Method scala/util/parsing/combinator/ImplicitConversions$class.flatten2:(Lscala/util/parsing/combinator/ImplicitConversions;Lscala/Function2;)Lscala/Function1;
   5:	areturn
  LineNumberTable: 
   line 22: 0

  LocalVariableTable: 
   Start  Length  Slot  Name   Signature
   0      6      0    this       Lscala/util/parsing/json/Lexer;
   0      6      1    f       Lscala/Function2;


}

