Compiled from "Lexer.scala"
public class scala.util.parsing.json.Lexer extends scala.util.parsing.combinator.lexical.StdLexical implements scala.util.parsing.combinator.ImplicitConversions,scala.ScalaObject
  SourceFile: "Lexer.scala"
  ScalaSig: length = 0x44E
   05 00 FFFFFF81 2C 06 08 01 02 FFFFFF84 FFFFFF80 FFFFFF80 FFFFFF80 00 0B 02 05
   4C 65 78 65 72 0A 02 03 04 01 04 6A 73 6F 6E 0A
   02 05 06 01 07 70 61 72 73 69 6E 67 0A 02 07 08
   01 04 75 74 69 6C 0A 01 09 01 05 73 63 61 6C 61
   03 00 13 04 00 0C 14 18 10 02 0D 12 0D 01 0E 0A
   02 0F 10 01 07 6C 65 78 69 63 61 6C 0A 02 11 04
   01 0A 63 6F 6D 62 69 6E 61 74 6F 72 09 02 13 0E
   02 0A 53 74 64 4C 65 78 69 63 61 6C 10 02 15 16
   0D 01 10 09 02 17 10 02 13 49 6D 70 6C 69 63 69
   74 43 6F 6E 76 65 72 73 69 6F 6E 73 10 02 19 1A
   0D 01 08 09 02 1B 08 02 0B 53 63 61 6C 61 4F 62
   6A 65 63 74 08 05 1D 00 FFFFFF84 00 1E 01 06 3C 69 6E
   69 74 3E 14 01 1F 10 02 20 00 0D 01 02 08 05 22
   00 FFFFFF84 20 23 01 05 74 6F 6B 65 6E 15 01 24 10 03
   25 26 2A 0D 01 00 09 02 27 28 02 06 50 61 72 73
   65 72 09 02 29 10 02 07 50 61 72 73 65 72 73 10
   02 25 2B 09 02 2C 2D 02 05 54 6F 6B 65 6E 09 02
   2E 2F 02 06 54 6F 6B 65 6E 73 0A 02 30 04 01 06
   73 79 6E 74 61 78 08 05 32 00 FFFFFF84 00 33 01 0C 63
   68 65 63 6B 4B 65 79 77 6F 72 64 14 02 34 3A 12
   03 35 37 2A 06 08 36 00 FFFFFF84 FFFFFF80 FFFFFF80 FFFFFF80 00 34 02 0C
   3C 72 65 66 69 6E 65 6D 65 6E 74 3E 10 02 19 38
   09 02 39 08 02 07 50 72 6F 64 75 63 74 08 05 3B
   31 FFFFFFC0 00 3C 01 02 78 73 10 03 3D 45 48 0E 02 3E
   43 0E 02 3F 42 0D 01 40 0A 02 41 0A 01 06 3C 72
   6F 6F 74 3E 09 01 09 09 02 44 08 01 07 70 61 63
   6B 61 67 65 09 02 46 47 02 04 4C 69 73 74 0A 02
   44 08 10 02 19 49 09 02 4A 08 02 03 41 6E 79 08
   05 4C 00 FFFFFF84 00 4D 01 06 73 74 72 69 6E 67 15 01
   4E 10 03 25 26 4F 10 02 50 53 0E 02 19 51 09 02
   52 08 01 06 50 72 65 64 65 66 09 02 54 55 02 06
   53 74 72 69 6E 67 0A 02 52 08 08 05 57 00 FFFFFF84 20
   58 01 0A 77 68 69 74 65 73 70 61 63 65 15 01 59
   10 03 25 26 5A 10 03 3D 45 5B 10 02 25 5C 09 02
   5D 5E 02 04 45 6C 65 6D 09 02 5F 0E 02 08 53 63
   61 6E 6E 65 72 73 08 05 61 00 FFFFFF84 00 62 01 06 6E
   75 6D 62 65 72 15 01 63 10 03 25 26 64 10 02 65
   6A 0D 01 66 0A 02 67 68 01 04 6C 61 6E 67 0A 01
   69 01 04 6A 61 76 61 09 02 54 66 08 05 6C 00 FFFFFF84
   00 4D 01 07 69 6E 74 50 61 72 74 08 05 6E 00 FFFFFF84
   00 4D 01 07 69 6E 74 4C 69 73 74 08 05 70 00 FFFFFF84
   00 4D 01 08 66 72 61 63 50 61 72 74 08 05 72 00
   FFFFFF84 00 62 01 07 65 78 70 50 61 72 74 08 05 74 00
   FFFFFF84 04 75 01 09 6F 70 74 53 74 72 69 6E 67 15 03
   76 FFFFFF81 00 14 03 64 77 79 08 05 78 73 FFFFFFC0 00 4F 01
   03 70 72 65 08 05 7A 73 FFFFFFC0 00 7B 01 01 61 10 03
   19 7C 7E 09 02 7D 08 02 06 4F 70 74 69 6F 6E 10
   03 7F FFFFFF81 00 0C 00 04 0A FFFFFF81 01 73 FFFFFF84 FFFFFF80 FFFFFF80 FFFFFFC2 00
   FFFFFF81 02 02 01 41 11 03 FFFFFF81 03 48 10 03 19 FFFFFF81 04 09
   03 FFFFFF81 05 08 02 07 4E 6F 74 68 69 6E 67 08 06 FFFFFF81
   07 00 FFFFFF84 00 4D 01 04 7A 65 72 6F 08 07 FFFFFF81 09 00
   FFFFFF84 00 FFFFFF81 0A 01 07 6E 6F 6E 7A 65 72 6F 15 02 FFFFFF81
   0B 10 03 25 26 5B 08 07 FFFFFF81 0D 00 FFFFFF84 00 FFFFFF81 0A 01
   08 65 78 70 6F 6E 65 6E 74 08 07 FFFFFF81 0F 00 FFFFFF84 00
   FFFFFF81 0A 01 04 73 69 67 6E 08 06 FFFFFF81 11 00 FFFFFF84 00 4D
   01 07 63 68 61 72 53 65 71 08 09 FFFFFF81 13 00 FFFFFFC2 FFFFFF80
   FFFFFF84 00 FFFFFF81 14 01 09 68 65 78 44 69 67 69 74 73 15
   02 FFFFFF81 15 10 06 FFFFFF81 16 FFFFFF81 1B FFFFFF81 1D 0D 02 FFFFFF81 17 0A
   04 FFFFFF81 18 FFFFFF81 19 01 09 69 6D 6D 75 74 61 62 6C 65
   0A 03 FFFFFF81 1A 08 01 0A 63 6F 6C 6C 65 63 74 69 6F
   6E 09 04 FFFFFF81 1C FFFFFF81 17 02 03 53 65 74 10 03 19 FFFFFF81
   1E 09 03 FFFFFF81 1F 08 02 04 43 68 61 72 08 08 FFFFFF81 21
   00 FFFFFFA0 FFFFFF80 04 FFFFFF81 15 01 0A 68 65 78 44 69 67 69 74
   73 20 08 07 FFFFFF81 23 00 FFFFFF84 00 FFFFFF81 0A 01 08 68 65 78
   44 69 67 69 74 08 06 FFFFFF81 25 00 FFFFFF84 04 62 01 0C 75
   6E 69 63 6F 64 65 42 6C 6F 63 6B 08 07 FFFFFF81 27 00
   FFFFFF84 00 FFFFFF81 28 01 0F 70 72 6F 74 65 63 74 65 64 24
   64 65 6C 69 6D 15 02 FFFFFF81 29 14 03 24 FFFFFF81 2A 08 09
   FFFFFF81 2B FFFFFF81 26 FFFFFF81 FFFFFF80 FFFFFFC0 00 25 01 03 78 24 31 
  InnerClass: 
   public abstract Token=class scala/util/parsing/syntax/Tokens$Token of class scala/util/parsing/syntax/Tokens
   public abstract Parser=class scala/util/parsing/combinator/Parsers$Parser of class scala/util/parsing/combinator/Parsers
   public ErrorToken=class scala/util/parsing/syntax/Tokens$ErrorToken of class scala/util/parsing/syntax/Tokens
   public Keyword=class scala/util/parsing/syntax/StdTokens$Keyword of class scala/util/parsing/syntax/StdTokens
   public final $anonfun$sign$1=class scala/util/parsing/json/Lexer$$anonfun$sign$1 of class scala/util/parsing/json/Lexer
   public final $anonfun$token$9=class scala/util/parsing/json/Lexer$$anonfun$token$9 of class scala/util/parsing/json/Lexer
   public final $anonfun$token$8=class scala/util/parsing/json/Lexer$$anonfun$token$8 of class scala/util/parsing/json/Lexer
   public final $anonfun$token$7=class scala/util/parsing/json/Lexer$$anonfun$token$7 of class scala/util/parsing/json/Lexer
   public final $anonfun$token$6=class scala/util/parsing/json/Lexer$$anonfun$token$6 of class scala/util/parsing/json/Lexer
   public final $anonfun$token$5=class scala/util/parsing/json/Lexer$$anonfun$token$5 of class scala/util/parsing/json/Lexer
   public final $anonfun$token$4=class scala/util/parsing/json/Lexer$$anonfun$token$4 of class scala/util/parsing/json/Lexer
   public final $anonfun$token$3=class scala/util/parsing/json/Lexer$$anonfun$token$3 of class scala/util/parsing/json/Lexer
   public final $anonfun$token$2=class scala/util/parsing/json/Lexer$$anonfun$token$2 of class scala/util/parsing/json/Lexer
   public final $anonfun$token$1=class scala/util/parsing/json/Lexer$$anonfun$token$1 of class scala/util/parsing/json/Lexer
   public final $anonfun$number$3=class scala/util/parsing/json/Lexer$$anonfun$number$3 of class scala/util/parsing/json/Lexer
   public final $anonfun$number$2=class scala/util/parsing/json/Lexer$$anonfun$number$2 of class scala/util/parsing/json/Lexer
   public final $anonfun$number$1=class scala/util/parsing/json/Lexer$$anonfun$number$1 of class scala/util/parsing/json/Lexer
   public final $anonfun$string$3=class scala/util/parsing/json/Lexer$$anonfun$string$3 of class scala/util/parsing/json/Lexer
   public final $anonfun$string$2=class scala/util/parsing/json/Lexer$$anonfun$string$2 of class scala/util/parsing/json/Lexer
   public final $anonfun$string$1=class scala/util/parsing/json/Lexer$$anonfun$string$1 of class scala/util/parsing/json/Lexer
   public final $anonfun$charSeq$9=class scala/util/parsing/json/Lexer$$anonfun$charSeq$9 of class scala/util/parsing/json/Lexer
   public final $anonfun$charSeq$8=class scala/util/parsing/json/Lexer$$anonfun$charSeq$8 of class scala/util/parsing/json/Lexer
   public final $anonfun$charSeq$7=class scala/util/parsing/json/Lexer$$anonfun$charSeq$7 of class scala/util/parsing/json/Lexer
   public final $anonfun$charSeq$6=class scala/util/parsing/json/Lexer$$anonfun$charSeq$6 of class scala/util/parsing/json/Lexer
   public final $anonfun$charSeq$5=class scala/util/parsing/json/Lexer$$anonfun$charSeq$5 of class scala/util/parsing/json/Lexer
   public final $anonfun$charSeq$4=class scala/util/parsing/json/Lexer$$anonfun$charSeq$4 of class scala/util/parsing/json/Lexer
   public final $anonfun$charSeq$3=class scala/util/parsing/json/Lexer$$anonfun$charSeq$3 of class scala/util/parsing/json/Lexer
   public final $anonfun$charSeq$2=class scala/util/parsing/json/Lexer$$anonfun$charSeq$2 of class scala/util/parsing/json/Lexer
   public final $anonfun$charSeq$1=class scala/util/parsing/json/Lexer$$anonfun$charSeq$1 of class scala/util/parsing/json/Lexer
   public final $anonfun$nonzero$1=class scala/util/parsing/json/Lexer$$anonfun$nonzero$1 of class scala/util/parsing/json/Lexer
   public final $anonfun$expPart$3=class scala/util/parsing/json/Lexer$$anonfun$expPart$3 of class scala/util/parsing/json/Lexer
   public final $anonfun$expPart$2=class scala/util/parsing/json/Lexer$$anonfun$expPart$2 of class scala/util/parsing/json/Lexer
   public final $anonfun$expPart$1=class scala/util/parsing/json/Lexer$$anonfun$expPart$1 of class scala/util/parsing/json/Lexer
   public final $anonfun$intList$2=class scala/util/parsing/json/Lexer$$anonfun$intList$2 of class scala/util/parsing/json/Lexer
   public final $anonfun$intList$1=class scala/util/parsing/json/Lexer$$anonfun$intList$1 of class scala/util/parsing/json/Lexer
   public final $anonfun$intPart$1=class scala/util/parsing/json/Lexer$$anonfun$intPart$1 of class scala/util/parsing/json/Lexer
   public final $anonfun$hexDigit$1=class scala/util/parsing/json/Lexer$$anonfun$hexDigit$1 of class scala/util/parsing/json/Lexer
   public final $anonfun$exponent$1=class scala/util/parsing/json/Lexer$$anonfun$exponent$1 of class scala/util/parsing/json/Lexer
   public final $anonfun$fracPart$2=class scala/util/parsing/json/Lexer$$anonfun$fracPart$2 of class scala/util/parsing/json/Lexer
   public final $anonfun$fracPart$1=class scala/util/parsing/json/Lexer$$anonfun$fracPart$1 of class scala/util/parsing/json/Lexer
   public final $anonfun$whitespace$1=class scala/util/parsing/json/Lexer$$anonfun$whitespace$1 of class scala/util/parsing/json/Lexer
   public final $anonfun$scala$util$parsing$json$Lexer$$unicodeBlock$4=class scala/util/parsing/json/Lexer$$anonfun$scala$util$parsing$json$Lexer$$unicodeBlock$4 of class scala/util/parsing/json/Lexer
   public final $anonfun$scala$util$parsing$json$Lexer$$unicodeBlock$3=class scala/util/parsing/json/Lexer$$anonfun$scala$util$parsing$json$Lexer$$unicodeBlock$3 of class scala/util/parsing/json/Lexer
   public final $anonfun$scala$util$parsing$json$Lexer$$unicodeBlock$2=class scala/util/parsing/json/Lexer$$anonfun$scala$util$parsing$json$Lexer$$unicodeBlock$2 of class scala/util/parsing/json/Lexer
   public final $anonfun$scala$util$parsing$json$Lexer$$unicodeBlock$1=class scala/util/parsing/json/Lexer$$anonfun$scala$util$parsing$json$Lexer$$unicodeBlock$1 of class scala/util/parsing/json/Lexer
  minor version: 0
  major version: 49
  Constant pool:
Asciz	SourceFile;
Asciz	Lexer.scala;
Asciz	hexDigits;
Asciz	Lscala/collection/immutable/Set;;
Asciz	Lscala/collection/immutable/Set<Ljava/lang/Character;>;;
Asciz	Signature;
Asciz	flatten2;
Asciz	(Lscala/Function2;)Lscala/Function1;;
Asciz	Code;
Asciz	LineNumberTable;
Asciz	scala/util/parsing/combinator/ImplicitConversions$class;
class	scala/util/parsing/combinator/ImplicitConversions$class
Asciz	(Lscala/util/parsing/combinator/ImplicitConversions;Lscala/Function2;)Lscala/Function1;;
NameAndType	flatten2:(Lscala/util/parsing/combinator/ImplicitConversions;Lscala/Function2;)Lscala/Function1;
Method	scala/util/parsing/combinator/ImplicitConversions$class.flatten2:(Lscala/util/parsing/combinator/ImplicitConversions;Lscala/Function2;)Lscala/Function1;
Asciz	this;
Asciz	Lscala/util/parsing/json/Lexer;;
Asciz	f;
Asciz	Lscala/Function2;;
Asciz	LocalVariableTable;
Asciz	flatten3;
Asciz	(Lscala/Function3;)Lscala/Function1;;
Asciz	(Lscala/util/parsing/combinator/ImplicitConversions;Lscala/Function3;)Lscala/Function1;;
NameAndType	flatten3:(Lscala/util/parsing/combinator/ImplicitConversions;Lscala/Function3;)Lscala/Function1;
Method	scala/util/parsing/combinator/ImplicitConversions$class.flatten3:(Lscala/util/parsing/combinator/ImplicitConversions;Lscala/Function3;)Lscala/Function1;
Asciz	Lscala/Function3;;
Asciz	flatten4;
Asciz	(Lscala/Function4;)Lscala/Function1;;
Asciz	(Lscala/util/parsing/combinator/ImplicitConversions;Lscala/Function4;)Lscala/Function1;;
NameAndType	flatten4:(Lscala/util/parsing/combinator/ImplicitConversions;Lscala/Function4;)Lscala/Function1;
Method	scala/util/parsing/combinator/ImplicitConversions$class.flatten4:(Lscala/util/parsing/combinator/ImplicitConversions;Lscala/Function4;)Lscala/Function1;
Asciz	Lscala/Function4;;
Asciz	flatten5;
Asciz	(Lscala/Function5;)Lscala/Function1;;
Asciz	(Lscala/util/parsing/combinator/ImplicitConversions;Lscala/Function5;)Lscala/Function1;;
NameAndType	flatten5:(Lscala/util/parsing/combinator/ImplicitConversions;Lscala/Function5;)Lscala/Function1;
Method	scala/util/parsing/combinator/ImplicitConversions$class.flatten5:(Lscala/util/parsing/combinator/ImplicitConversions;Lscala/Function5;)Lscala/Function1;
Asciz	Lscala/Function5;;
Asciz	headOptionTailToFunList;
Asciz	(Lscala/Function1;)Lscala/Function1;;
Asciz	(Lscala/util/parsing/combinator/ImplicitConversions;Lscala/Function1;)Lscala/Function1;;
NameAndType	headOptionTailToFunList:(Lscala/util/parsing/combinator/ImplicitConversions;Lscala/Function1;)Lscala/Function1;
Method	scala/util/parsing/combinator/ImplicitConversions$class.headOptionTailToFunList:(Lscala/util/parsing/combinator/ImplicitConversions;Lscala/Function1;)Lscala/Function1;
Asciz	Lscala/Function1;;
Asciz	protected$delim;
Asciz	(Lscala/util/parsing/json/Lexer;)Lscala/util/parsing/combinator/Parsers$Parser;;
Asciz	scala/util/parsing/json/Lexer;
class	scala/util/parsing/json/Lexer
Asciz	delim;
Asciz	()Lscala/util/parsing/combinator/Parsers$Parser;;
NameAndType	delim:()Lscala/util/parsing/combinator/Parsers$Parser;
Method	scala/util/parsing/json/Lexer.delim:()Lscala/util/parsing/combinator/Parsers$Parser;
Asciz	(Lscala/util/parsing/json/Lexer;)Lscala/util/parsing/combinator/Parsers$Parser<Lscala/util/parsing/syntax/Tokens$Token;>;;
Asciz	token;
Asciz	string;
NameAndType	string:()Lscala/util/parsing/combinator/Parsers$Parser;
Method	scala/util/parsing/json/Lexer.string:()Lscala/util/parsing/combinator/Parsers$Parser;
Asciz	scala/util/parsing/syntax/StdTokens;
class	scala/util/parsing/syntax/StdTokens
Asciz	StringLit;
Asciz	()Lscala/util/parsing/syntax/StdTokens$StringLit$;;
NameAndType	StringLit:()Lscala/util/parsing/syntax/StdTokens$StringLit$;
InterfaceMethod	scala/util/parsing/syntax/StdTokens.StringLit:()Lscala/util/parsing/syntax/StdTokens$StringLit$;
Asciz	scala/util/parsing/combinator/Parsers$Parser;
class	scala/util/parsing/combinator/Parsers$Parser
Asciz	$up$up;
Asciz	(Lscala/Function1;)Lscala/util/parsing/combinator/Parsers$Parser;;
NameAndType	$up$up:(Lscala/Function1;)Lscala/util/parsing/combinator/Parsers$Parser;
Method	scala/util/parsing/combinator/Parsers$Parser.$up$up:(Lscala/Function1;)Lscala/util/parsing/combinator/Parsers$Parser;
Asciz	scala/util/parsing/json/Lexer$$anonfun$token$1;
class	scala/util/parsing/json/Lexer$$anonfun$token$1
Asciz	<init>;
Asciz	(Lscala/util/parsing/json/Lexer;)V;
NameAndType	"<init>":(Lscala/util/parsing/json/Lexer;)V
Method	scala/util/parsing/json/Lexer$$anonfun$token$1."<init>":(Lscala/util/parsing/json/Lexer;)V
Asciz	$bar;
Asciz	(Lscala/Function0;)Lscala/util/parsing/combinator/Parsers$Parser;;
NameAndType	$bar:(Lscala/Function0;)Lscala/util/parsing/combinator/Parsers$Parser;
Method	scala/util/parsing/combinator/Parsers$Parser.$bar:(Lscala/Function0;)Lscala/util/parsing/combinator/Parsers$Parser;
Asciz	scala/util/parsing/json/Lexer$$anonfun$token$2;
class	scala/util/parsing/json/Lexer$$anonfun$token$2
Method	scala/util/parsing/json/Lexer$$anonfun$token$2."<init>":(Lscala/util/parsing/json/Lexer;)V
Asciz	scala/util/parsing/json/Lexer$$anonfun$token$3;
class	scala/util/parsing/json/Lexer$$anonfun$token$3
Method	scala/util/parsing/json/Lexer$$anonfun$token$3."<init>":(Lscala/util/parsing/json/Lexer;)V
Asciz	scala/util/parsing/json/Lexer$$anonfun$token$4;
class	scala/util/parsing/json/Lexer$$anonfun$token$4
Method	scala/util/parsing/json/Lexer$$anonfun$token$4."<init>":(Lscala/util/parsing/json/Lexer;)V
Asciz	scala/util/parsing/json/Lexer$$anonfun$token$5;
class	scala/util/parsing/json/Lexer$$anonfun$token$5
Method	scala/util/parsing/json/Lexer$$anonfun$token$5."<init>":(Lscala/util/parsing/json/Lexer;)V
Asciz	scala/util/parsing/json/Lexer$$anonfun$token$6;
class	scala/util/parsing/json/Lexer$$anonfun$token$6
Method	scala/util/parsing/json/Lexer$$anonfun$token$6."<init>":(Lscala/util/parsing/json/Lexer;)V
Asciz	scala/util/parsing/json/Lexer$$anonfun$token$7;
class	scala/util/parsing/json/Lexer$$anonfun$token$7
Method	scala/util/parsing/json/Lexer$$anonfun$token$7."<init>":(Lscala/util/parsing/json/Lexer;)V
Asciz	scala/util/parsing/json/Lexer$$anonfun$token$8;
class	scala/util/parsing/json/Lexer$$anonfun$token$8
Method	scala/util/parsing/json/Lexer$$anonfun$token$8."<init>":(Lscala/util/parsing/json/Lexer;)V
Asciz	scala/util/parsing/json/Lexer$$anonfun$token$9;
class	scala/util/parsing/json/Lexer$$anonfun$token$9
Method	scala/util/parsing/json/Lexer$$anonfun$token$9."<init>":(Lscala/util/parsing/json/Lexer;)V
Asciz	()Lscala/util/parsing/combinator/Parsers$Parser<Lscala/util/parsing/syntax/Tokens$Token;>;;
Asciz	checkKeyword;
Asciz	(Lscala/collection/immutable/List;)Lscala/util/parsing/syntax/Tokens$Token;;
Asciz	;
String	
Asciz	scala/collection/TraversableLike;
class	scala/collection/TraversableLike
Asciz	mkString;
Asciz	(Ljava/lang/String;)Ljava/lang/String;;
NameAndType	mkString:(Ljava/lang/String;)Ljava/lang/String;
InterfaceMethod	scala/collection/TraversableLike.mkString:(Ljava/lang/String;)Ljava/lang/String;
Asciz	reserved;
Asciz	()Lscala/collection/mutable/HashSet;;
NameAndType	reserved:()Lscala/collection/mutable/HashSet;
Method	scala/util/parsing/json/Lexer.reserved:()Lscala/collection/mutable/HashSet;
Asciz	scala/collection/mutable/HashSet;
class	scala/collection/mutable/HashSet
Asciz	contains;
Asciz	(Ljava/lang/Object;)Z;
NameAndType	contains:(Ljava/lang/Object;)Z
Method	scala/collection/mutable/HashSet.contains:(Ljava/lang/Object;)Z
Asciz	scala/util/parsing/syntax/StdTokens$Keyword;
class	scala/util/parsing/syntax/StdTokens$Keyword
Asciz	(Lscala/util/parsing/syntax/StdTokens;Ljava/lang/String;)V;
NameAndType	"<init>":(Lscala/util/parsing/syntax/StdTokens;Ljava/lang/String;)V
Method	scala/util/parsing/syntax/StdTokens$Keyword."<init>":(Lscala/util/parsing/syntax/StdTokens;Ljava/lang/String;)V
Asciz	scala/util/parsing/syntax/Tokens$ErrorToken;
class	scala/util/parsing/syntax/Tokens$ErrorToken
Asciz	scala/collection/mutable/StringBuilder;
class	scala/collection/mutable/StringBuilder
Asciz	()V;
NameAndType	"<init>":()V
Method	scala/collection/mutable/StringBuilder."<init>":()V
Asciz	Not a keyword: ;
String	Not a keyword: 
Asciz	append;
Asciz	(Ljava/lang/Object;)Lscala/collection/mutable/StringBuilder;;
NameAndType	append:(Ljava/lang/Object;)Lscala/collection/mutable/StringBuilder;
Method	scala/collection/mutable/StringBuilder.append:(Ljava/lang/Object;)Lscala/collection/mutable/StringBuilder;
Asciz	toString;
Asciz	()Ljava/lang/String;;
NameAndType	toString:()Ljava/lang/String;
Method	scala/collection/mutable/StringBuilder.toString:()Ljava/lang/String;
Asciz	(Lscala/util/parsing/syntax/Tokens;Ljava/lang/String;)V;
NameAndType	"<init>":(Lscala/util/parsing/syntax/Tokens;Ljava/lang/String;)V
Method	scala/util/parsing/syntax/Tokens$ErrorToken."<init>":(Lscala/util/parsing/syntax/Tokens;Ljava/lang/String;)V
Asciz	xs;
Asciz	Lscala/collection/immutable/List;;
Asciz	strRep;
Asciz	Ljava/lang/String;;
Asciz	(Lscala/collection/immutable/List<Ljava/lang/Object;>;)Lscala/Product;;
int	34;
Asciz	scala/runtime/BoxesRunTime;
class	scala/runtime/BoxesRunTime
Asciz	boxToCharacter;
Asciz	(C)Ljava/lang/Character;;
NameAndType	boxToCharacter:(C)Ljava/lang/Character;
Method	scala/runtime/BoxesRunTime.boxToCharacter:(C)Ljava/lang/Character;
Asciz	scala/util/parsing/combinator/Parsers;
class	scala/util/parsing/combinator/Parsers
Asciz	accept;
Asciz	(Ljava/lang/Object;)Lscala/util/parsing/combinator/Parsers$Parser;;
NameAndType	accept:(Ljava/lang/Object;)Lscala/util/parsing/combinator/Parsers$Parser;
InterfaceMethod	scala/util/parsing/combinator/Parsers.accept:(Ljava/lang/Object;)Lscala/util/parsing/combinator/Parsers$Parser;
Asciz	scala/util/parsing/json/Lexer$$anonfun$string$1;
class	scala/util/parsing/json/Lexer$$anonfun$string$1
Method	scala/util/parsing/json/Lexer$$anonfun$string$1."<init>":(Lscala/util/parsing/json/Lexer;)V
Asciz	$tilde$greater;
NameAndType	$tilde$greater:(Lscala/Function0;)Lscala/util/parsing/combinator/Parsers$Parser;
Method	scala/util/parsing/combinator/Parsers$Parser.$tilde$greater:(Lscala/Function0;)Lscala/util/parsing/combinator/Parsers$Parser;
Asciz	scala/util/parsing/json/Lexer$$anonfun$string$2;
class	scala/util/parsing/json/Lexer$$anonfun$string$2
Method	scala/util/parsing/json/Lexer$$anonfun$string$2."<init>":(Lscala/util/parsing/json/Lexer;)V
Asciz	$less$tilde;
NameAndType	$less$tilde:(Lscala/Function0;)Lscala/util/parsing/combinator/Parsers$Parser;
Method	scala/util/parsing/combinator/Parsers$Parser.$less$tilde:(Lscala/Function0;)Lscala/util/parsing/combinator/Parsers$Parser;
Asciz	scala/util/parsing/json/Lexer$$anonfun$string$3;
class	scala/util/parsing/json/Lexer$$anonfun$string$3
Method	scala/util/parsing/json/Lexer$$anonfun$string$3."<init>":(Lscala/util/parsing/json/Lexer;)V
Asciz	()Lscala/util/parsing/combinator/Parsers$Parser<Ljava/lang/String;>;;
Asciz	whitespace;
Asciz	scala/util/parsing/json/Lexer$$anonfun$whitespace$1;
class	scala/util/parsing/json/Lexer$$anonfun$whitespace$1
Method	scala/util/parsing/json/Lexer$$anonfun$whitespace$1."<init>":(Lscala/util/parsing/json/Lexer;)V
Asciz	rep;
NameAndType	rep:(Lscala/Function0;)Lscala/util/parsing/combinator/Parsers$Parser;
InterfaceMethod	scala/util/parsing/combinator/Parsers.rep:(Lscala/Function0;)Lscala/util/parsing/combinator/Parsers$Parser;
Asciz	()Lscala/util/parsing/combinator/Parsers$Parser<Lscala/collection/immutable/List<Ljava/lang/Character;>;>;;
Asciz	number;
Asciz	intPart;
NameAndType	intPart:()Lscala/util/parsing/combinator/Parsers$Parser;
Method	scala/util/parsing/json/Lexer.intPart:()Lscala/util/parsing/combinator/Parsers$Parser;
Asciz	scala/util/parsing/json/Lexer$$anonfun$number$1;
class	scala/util/parsing/json/Lexer$$anonfun$number$1
Method	scala/util/parsing/json/Lexer$$anonfun$number$1."<init>":(Lscala/util/parsing/json/Lexer;)V
Asciz	$tilde;
NameAndType	$tilde:(Lscala/Function0;)Lscala/util/parsing/combinator/Parsers$Parser;
Method	scala/util/parsing/combinator/Parsers$Parser.$tilde:(Lscala/Function0;)Lscala/util/parsing/combinator/Parsers$Parser;
Asciz	scala/util/parsing/json/Lexer$$anonfun$number$2;
class	scala/util/parsing/json/Lexer$$anonfun$number$2
Method	scala/util/parsing/json/Lexer$$anonfun$number$2."<init>":(Lscala/util/parsing/json/Lexer;)V
Asciz	scala/util/parsing/json/Lexer$$anonfun$number$3;
class	scala/util/parsing/json/Lexer$$anonfun$number$3
Method	scala/util/parsing/json/Lexer$$anonfun$number$3."<init>":(Lscala/util/parsing/json/Lexer;)V
Asciz	zero;
NameAndType	zero:()Lscala/util/parsing/combinator/Parsers$Parser;
Method	scala/util/parsing/json/Lexer.zero:()Lscala/util/parsing/combinator/Parsers$Parser;
Asciz	scala/util/parsing/json/Lexer$$anonfun$intPart$1;
class	scala/util/parsing/json/Lexer$$anonfun$intPart$1
Method	scala/util/parsing/json/Lexer$$anonfun$intPart$1."<init>":(Lscala/util/parsing/json/Lexer;)V
Asciz	intList;
Asciz	nonzero;
NameAndType	nonzero:()Lscala/util/parsing/combinator/Parsers$Parser;
Method	scala/util/parsing/json/Lexer.nonzero:()Lscala/util/parsing/combinator/Parsers$Parser;
Asciz	scala/util/parsing/json/Lexer$$anonfun$intList$1;
class	scala/util/parsing/json/Lexer$$anonfun$intList$1
Method	scala/util/parsing/json/Lexer$$anonfun$intList$1."<init>":(Lscala/util/parsing/json/Lexer;)V
Asciz	scala/util/parsing/json/Lexer$$anonfun$intList$2;
class	scala/util/parsing/json/Lexer$$anonfun$intList$2
Method	scala/util/parsing/json/Lexer$$anonfun$intList$2."<init>":(Lscala/util/parsing/json/Lexer;)V
Asciz	fracPart;
int	46;
Asciz	scala/util/parsing/json/Lexer$$anonfun$fracPart$1;
class	scala/util/parsing/json/Lexer$$anonfun$fracPart$1
Method	scala/util/parsing/json/Lexer$$anonfun$fracPart$1."<init>":(Lscala/util/parsing/json/Lexer;)V
Asciz	scala/util/parsing/json/Lexer$$anonfun$fracPart$2;
class	scala/util/parsing/json/Lexer$$anonfun$fracPart$2
Method	scala/util/parsing/json/Lexer$$anonfun$fracPart$2."<init>":(Lscala/util/parsing/json/Lexer;)V
Asciz	expPart;
Asciz	exponent;
NameAndType	exponent:()Lscala/util/parsing/combinator/Parsers$Parser;
Method	scala/util/parsing/json/Lexer.exponent:()Lscala/util/parsing/combinator/Parsers$Parser;
Asciz	scala/util/parsing/json/Lexer$$anonfun$expPart$1;
class	scala/util/parsing/json/Lexer$$anonfun$expPart$1
Method	scala/util/parsing/json/Lexer$$anonfun$expPart$1."<init>":(Lscala/util/parsing/json/Lexer;)V
Asciz	scala/util/parsing/json/Lexer$$anonfun$expPart$2;
class	scala/util/parsing/json/Lexer$$anonfun$expPart$2
Method	scala/util/parsing/json/Lexer$$anonfun$expPart$2."<init>":(Lscala/util/parsing/json/Lexer;)V
Asciz	scala/util/parsing/json/Lexer$$anonfun$expPart$3;
class	scala/util/parsing/json/Lexer$$anonfun$expPart$3
Method	scala/util/parsing/json/Lexer$$anonfun$expPart$3."<init>":(Lscala/util/parsing/json/Lexer;)V
Asciz	scala$util$parsing$json$Lexer$$optString;
Asciz	(Ljava/lang/String;Lscala/Option;)Ljava/lang/String;;
Asciz	scala/Some;
class	scala/Some
Asciz	x;
Asciz	Ljava/lang/Object;;
NameAndType	x:Ljava/lang/Object;
Field	scala/Some.x:Ljava/lang/Object;
Asciz	java/lang/Object;
class	java/lang/Object
Method	java/lang/Object.toString:()Ljava/lang/String;
Asciz	scala/None$;
class	scala/None$
Asciz	MODULE$;
Asciz	Lscala/None$;;
NameAndType	MODULE$:Lscala/None$;
Field	scala/None$.MODULE$:Lscala/None$;
Asciz	equals;
NameAndType	equals:(Ljava/lang/Object;)Z
Method	java/lang/Object.equals:(Ljava/lang/Object;)Z
Asciz	scala/MatchError;
class	scala/MatchError
Asciz	scala/Option;
class	scala/Option
Method	scala/Option.toString:()Ljava/lang/String;
Asciz	(Ljava/lang/String;)V;
NameAndType	"<init>":(Ljava/lang/String;)V
Method	scala/MatchError."<init>":(Ljava/lang/String;)V
Asciz	pre;
Asciz	a;
Asciz	Lscala/Option;;
Asciz	temp26;
Asciz	Lscala/Some;;
Asciz	temp27;
int	48;
Asciz	0;
String	0
Asciz	$up$up$up;
NameAndType	$up$up$up:(Ljava/lang/Object;)Lscala/util/parsing/combinator/Parsers$Parser;
Method	scala/util/parsing/combinator/Parsers$Parser.$up$up$up:(Ljava/lang/Object;)Lscala/util/parsing/combinator/Parsers$Parser;
Asciz	nonzero digit;
String	nonzero digit
Asciz	scala/util/parsing/json/Lexer$$anonfun$nonzero$1;
class	scala/util/parsing/json/Lexer$$anonfun$nonzero$1
Method	scala/util/parsing/json/Lexer$$anonfun$nonzero$1."<init>":(Lscala/util/parsing/json/Lexer;)V
Asciz	elem;
Asciz	(Ljava/lang/String;Lscala/Function1;)Lscala/util/parsing/combinator/Parsers$Parser;;
NameAndType	elem:(Ljava/lang/String;Lscala/Function1;)Lscala/util/parsing/combinator/Parsers$Parser;
InterfaceMethod	scala/util/parsing/combinator/Parsers.elem:(Ljava/lang/String;Lscala/Function1;)Lscala/util/parsing/combinator/Parsers$Parser;
Asciz	()Lscala/util/parsing/combinator/Parsers$Parser<Ljava/lang/Character;>;;
Asciz	exponent character;
String	exponent character
Asciz	scala/util/parsing/json/Lexer$$anonfun$exponent$1;
class	scala/util/parsing/json/Lexer$$anonfun$exponent$1
Method	scala/util/parsing/json/Lexer$$anonfun$exponent$1."<init>":(Lscala/util/parsing/json/Lexer;)V
Asciz	sign;
Asciz	sign character;
String	sign character
Asciz	scala/util/parsing/json/Lexer$$anonfun$sign$1;
class	scala/util/parsing/json/Lexer$$anonfun$sign$1
Method	scala/util/parsing/json/Lexer$$anonfun$sign$1."<init>":(Lscala/util/parsing/json/Lexer;)V
Asciz	charSeq;
int	92;
Asciz	scala/util/parsing/json/Lexer$$anonfun$charSeq$1;
class	scala/util/parsing/json/Lexer$$anonfun$charSeq$1
Method	scala/util/parsing/json/Lexer$$anonfun$charSeq$1."<init>":(Lscala/util/parsing/json/Lexer;)V
Asciz	\";
String	\"
Asciz	scala/util/parsing/json/Lexer$$anonfun$charSeq$2;
class	scala/util/parsing/json/Lexer$$anonfun$charSeq$2
Method	scala/util/parsing/json/Lexer$$anonfun$charSeq$2."<init>":(Lscala/util/parsing/json/Lexer;)V
Asciz	scala/util/parsing/json/Lexer$$anonfun$charSeq$3;
class	scala/util/parsing/json/Lexer$$anonfun$charSeq$3
Method	scala/util/parsing/json/Lexer$$anonfun$charSeq$3."<init>":(Lscala/util/parsing/json/Lexer;)V
Asciz	scala/util/parsing/json/Lexer$$anonfun$charSeq$4;
class	scala/util/parsing/json/Lexer$$anonfun$charSeq$4
Method	scala/util/parsing/json/Lexer$$anonfun$charSeq$4."<init>":(Lscala/util/parsing/json/Lexer;)V
Asciz	scala/util/parsing/json/Lexer$$anonfun$charSeq$5;
class	scala/util/parsing/json/Lexer$$anonfun$charSeq$5
Method	scala/util/parsing/json/Lexer$$anonfun$charSeq$5."<init>":(Lscala/util/parsing/json/Lexer;)V
Asciz	scala/util/parsing/json/Lexer$$anonfun$charSeq$6;
class	scala/util/parsing/json/Lexer$$anonfun$charSeq$6
Method	scala/util/parsing/json/Lexer$$anonfun$charSeq$6."<init>":(Lscala/util/parsing/json/Lexer;)V
Asciz	scala/util/parsing/json/Lexer$$anonfun$charSeq$7;
class	scala/util/parsing/json/Lexer$$anonfun$charSeq$7
Method	scala/util/parsing/json/Lexer$$anonfun$charSeq$7."<init>":(Lscala/util/parsing/json/Lexer;)V
Asciz	scala/util/parsing/json/Lexer$$anonfun$charSeq$8;
class	scala/util/parsing/json/Lexer$$anonfun$charSeq$8
Method	scala/util/parsing/json/Lexer$$anonfun$charSeq$8."<init>":(Lscala/util/parsing/json/Lexer;)V
Asciz	scala/util/parsing/json/Lexer$$anonfun$charSeq$9;
class	scala/util/parsing/json/Lexer$$anonfun$charSeq$9
Method	scala/util/parsing/json/Lexer$$anonfun$charSeq$9."<init>":(Lscala/util/parsing/json/Lexer;)V
Asciz	()Lscala/collection/immutable/Set;;
NameAndType	hexDigits:Lscala/collection/immutable/Set;
Field	scala/util/parsing/json/Lexer.hexDigits:Lscala/collection/immutable/Set;
Asciz	()Lscala/collection/immutable/Set<Ljava/lang/Character;>;;
Asciz	hexDigit;
Asciz	hex digit;
String	hex digit
Asciz	scala/util/parsing/json/Lexer$$anonfun$hexDigit$1;
class	scala/util/parsing/json/Lexer$$anonfun$hexDigit$1
Method	scala/util/parsing/json/Lexer$$anonfun$hexDigit$1."<init>":(Lscala/util/parsing/json/Lexer;)V
Asciz	scala$util$parsing$json$Lexer$$unicodeBlock;
NameAndType	hexDigit:()Lscala/util/parsing/combinator/Parsers$Parser;
Method	scala/util/parsing/json/Lexer.hexDigit:()Lscala/util/parsing/combinator/Parsers$Parser;
Asciz	scala/util/parsing/json/Lexer$$anonfun$scala$util$parsing$json$Lexer$$unicodeBlock$1;
class	scala/util/parsing/json/Lexer$$anonfun$scala$util$parsing$json$Lexer$$unicodeBlock$1
Method	scala/util/parsing/json/Lexer$$anonfun$scala$util$parsing$json$Lexer$$unicodeBlock$1."<init>":(Lscala/util/parsing/json/Lexer;)V
Asciz	scala/util/parsing/json/Lexer$$anonfun$scala$util$parsing$json$Lexer$$unicodeBlock$2;
class	scala/util/parsing/json/Lexer$$anonfun$scala$util$parsing$json$Lexer$$unicodeBlock$2
Method	scala/util/parsing/json/Lexer$$anonfun$scala$util$parsing$json$Lexer$$unicodeBlock$2."<init>":(Lscala/util/parsing/json/Lexer;)V
Asciz	scala/util/parsing/json/Lexer$$anonfun$scala$util$parsing$json$Lexer$$unicodeBlock$3;
class	scala/util/parsing/json/Lexer$$anonfun$scala$util$parsing$json$Lexer$$unicodeBlock$3
Method	scala/util/parsing/json/Lexer$$anonfun$scala$util$parsing$json$Lexer$$unicodeBlock$3."<init>":(Lscala/util/parsing/json/Lexer;)V
Asciz	scala/util/parsing/json/Lexer$$anonfun$scala$util$parsing$json$Lexer$$unicodeBlock$4;
class	scala/util/parsing/json/Lexer$$anonfun$scala$util$parsing$json$Lexer$$unicodeBlock$4
Method	scala/util/parsing/json/Lexer$$anonfun$scala$util$parsing$json$Lexer$$unicodeBlock$4."<init>":(Lscala/util/parsing/json/Lexer;)V
Asciz	scala/util/parsing/combinator/lexical/StdLexical;
class	scala/util/parsing/combinator/lexical/StdLexical
Method	scala/util/parsing/combinator/lexical/StdLexical."<init>":()V
Asciz	$init$;
Asciz	(Lscala/util/parsing/combinator/ImplicitConversions;)V;
NameAndType	$init$:(Lscala/util/parsing/combinator/ImplicitConversions;)V
Method	scala/util/parsing/combinator/ImplicitConversions$class.$init$:(Lscala/util/parsing/combinator/ImplicitConversions;)V
Asciz	scala/Predef$;
class	scala/Predef$
Asciz	Lscala/Predef$;;
NameAndType	MODULE$:Lscala/Predef$;
Field	scala/Predef$.MODULE$:Lscala/Predef$;
Asciz	Set;
Asciz	()Lscala/collection/immutable/Set$;;
NameAndType	Set:()Lscala/collection/immutable/Set$;
Method	scala/Predef$.Set:()Lscala/collection/immutable/Set$;
Asciz	wrapCharArray;
Asciz	([C)Lscala/collection/mutable/WrappedArray;;
NameAndType	wrapCharArray:([C)Lscala/collection/mutable/WrappedArray;
Method	scala/Predef$.wrapCharArray:([C)Lscala/collection/mutable/WrappedArray;
Asciz	scala/collection/immutable/Set$;
class	scala/collection/immutable/Set$
Asciz	apply;
Asciz	(Lscala/collection/Seq;)Lscala/collection/Traversable;;
NameAndType	apply:(Lscala/collection/Seq;)Lscala/collection/Traversable;
Method	scala/collection/immutable/Set$.apply:(Lscala/collection/Seq;)Lscala/collection/Traversable;
Asciz	scala/collection/generic/Addable;
class	scala/collection/generic/Addable
Asciz	0123456789abcdefABCDEF;
String	0123456789abcdefABCDEF
Asciz	augmentString;
Asciz	(Ljava/lang/String;)Lscala/collection/immutable/StringOps;;
NameAndType	augmentString:(Ljava/lang/String;)Lscala/collection/immutable/StringOps;
Method	scala/Predef$.augmentString:(Ljava/lang/String;)Lscala/collection/immutable/StringOps;
Asciz	scala/reflect/Manifest$;
class	scala/reflect/Manifest$
Asciz	Lscala/reflect/Manifest$;;
NameAndType	MODULE$:Lscala/reflect/Manifest$;
Field	scala/reflect/Manifest$.MODULE$:Lscala/reflect/Manifest$;
Asciz	Char;
Asciz	()Lscala/reflect/AnyValManifest;;
NameAndType	Char:()Lscala/reflect/AnyValManifest;
Method	scala/reflect/Manifest$.Char:()Lscala/reflect/AnyValManifest;
Asciz	toArray;
Asciz	(Lscala/reflect/ClassManifest;)Ljava/lang/Object;;
NameAndType	toArray:(Lscala/reflect/ClassManifest;)Ljava/lang/Object;
InterfaceMethod	scala/collection/TraversableLike.toArray:(Lscala/reflect/ClassManifest;)Ljava/lang/Object;
Asciz	[C;
class	"[C"
Asciz	$plus$plus;
Asciz	(Lscala/collection/Traversable;)Lscala/collection/generic/Addable;;
NameAndType	$plus$plus:(Lscala/collection/Traversable;)Lscala/collection/generic/Addable;
InterfaceMethod	scala/collection/generic/Addable.$plus$plus:(Lscala/collection/Traversable;)Lscala/collection/generic/Addable;
Asciz	scala/collection/immutable/Set;
class	scala/collection/immutable/Set
Asciz	ScalaSig;
Asciz	InnerClasses;
Asciz	scala/util/parsing/syntax/Tokens$Token;
class	scala/util/parsing/syntax/Tokens$Token
Asciz	scala/util/parsing/syntax/Tokens;
class	scala/util/parsing/syntax/Tokens
Asciz	Token;
Asciz	Parser;
Asciz	ErrorToken;
Asciz	Keyword;
Asciz	$anonfun$sign$1;
Asciz	$anonfun$token$9;
Asciz	$anonfun$token$8;
Asciz	$anonfun$token$7;
Asciz	$anonfun$token$6;
Asciz	$anonfun$token$5;
Asciz	$anonfun$token$4;
Asciz	$anonfun$token$3;
Asciz	$anonfun$token$2;
Asciz	$anonfun$token$1;
Asciz	$anonfun$number$3;
Asciz	$anonfun$number$2;
Asciz	$anonfun$number$1;
Asciz	$anonfun$string$3;
Asciz	$anonfun$string$2;
Asciz	$anonfun$string$1;
Asciz	$anonfun$charSeq$9;
Asciz	$anonfun$charSeq$8;
Asciz	$anonfun$charSeq$7;
Asciz	$anonfun$charSeq$6;
Asciz	$anonfun$charSeq$5;
Asciz	$anonfun$charSeq$4;
Asciz	$anonfun$charSeq$3;
Asciz	$anonfun$charSeq$2;
Asciz	$anonfun$charSeq$1;
Asciz	$anonfun$nonzero$1;
Asciz	$anonfun$expPart$3;
Asciz	$anonfun$expPart$2;
Asciz	$anonfun$expPart$1;
Asciz	$anonfun$intList$2;
Asciz	$anonfun$intList$1;
Asciz	$anonfun$intPart$1;
Asciz	$anonfun$hexDigit$1;
Asciz	$anonfun$exponent$1;
Asciz	$anonfun$fracPart$2;
Asciz	$anonfun$fracPart$1;
Asciz	$anonfun$whitespace$1;
Asciz	$anonfun$scala$util$parsing$json$Lexer$$unicodeBlock$4;
Asciz	$anonfun$scala$util$parsing$json$Lexer$$unicodeBlock$3;
Asciz	$anonfun$scala$util$parsing$json$Lexer$$unicodeBlock$2;
Asciz	$anonfun$scala$util$parsing$json$Lexer$$unicodeBlock$1;
Asciz	scala/util/parsing/combinator/ImplicitConversions;
class	scala/util/parsing/combinator/ImplicitConversions
Asciz	scala/ScalaObject;
class	scala/ScalaObject

{
private final scala.collection.immutable.Set hexDigits;
  Signature: Lscala/collection/immutable/Set;
  Signature: length = 0x2
   00 05 

public scala.Function1 flatten2(scala.Function2);
  Signature: (Lscala/Function2;)Lscala/Function1;
  Code:
   Stack=2, Locals=2, Args_size=2
	aload_0
	aload_1
	invokestatic	Method scala/util/parsing/combinator/ImplicitConversions$class.flatten2:(Lscala/util/parsing/combinator/ImplicitConversions;Lscala/Function2;)Lscala/Function1;
	areturn
  Labels:
  LocalVariableTable: 
   Start  Length  Slot  Name   Signature
   0      6      0    this       Lscala/util/parsing/json/Lexer;
   0      6      1    f       Lscala/Function2;


public scala.Function1 flatten3(scala.Function3);
  Signature: (Lscala/Function3;)Lscala/Function1;
  Code:
   Stack=2, Locals=2, Args_size=2
	aload_0
	aload_1
	invokestatic	Method scala/util/parsing/combinator/ImplicitConversions$class.flatten3:(Lscala/util/parsing/combinator/ImplicitConversions;Lscala/Function3;)Lscala/Function1;
	areturn
  Labels:
  LocalVariableTable: 
   Start  Length  Slot  Name   Signature
   0      6      0    this       Lscala/util/parsing/json/Lexer;
   0      6      1    f       Lscala/Function3;


public scala.Function1 flatten4(scala.Function4);
  Signature: (Lscala/Function4;)Lscala/Function1;
  Code:
   Stack=2, Locals=2, Args_size=2
	aload_0
	aload_1
	invokestatic	Method scala/util/parsing/combinator/ImplicitConversions$class.flatten4:(Lscala/util/parsing/combinator/ImplicitConversions;Lscala/Function4;)Lscala/Function1;
	areturn
  Labels:
  LocalVariableTable: 
   Start  Length  Slot  Name   Signature
   0      6      0    this       Lscala/util/parsing/json/Lexer;
   0      6      1    f       Lscala/Function4;


public scala.Function1 flatten5(scala.Function5);
  Signature: (Lscala/Function5;)Lscala/Function1;
  Code:
   Stack=2, Locals=2, Args_size=2
	aload_0
	aload_1
	invokestatic	Method scala/util/parsing/combinator/ImplicitConversions$class.flatten5:(Lscala/util/parsing/combinator/ImplicitConversions;Lscala/Function5;)Lscala/Function1;
	areturn
  Labels:
  LocalVariableTable: 
   Start  Length  Slot  Name   Signature
   0      6      0    this       Lscala/util/parsing/json/Lexer;
   0      6      1    f       Lscala/Function5;


public scala.Function1 headOptionTailToFunList(scala.Function1);
  Signature: (Lscala/Function1;)Lscala/Function1;
  Code:
   Stack=2, Locals=2, Args_size=2
	aload_0
	aload_1
	invokestatic	Method scala/util/parsing/combinator/ImplicitConversions$class.headOptionTailToFunList:(Lscala/util/parsing/combinator/ImplicitConversions;Lscala/Function1;)Lscala/Function1;
	areturn
  Labels:
  LocalVariableTable: 
   Start  Length  Slot  Name   Signature
   0      6      0    this       Lscala/util/parsing/json/Lexer;
   0      6      1    f       Lscala/Function1;


public scala.util.parsing.combinator.Parsers$Parser protected$delim(scala.util.parsing.json.Lexer);
  Signature: (Lscala/util/parsing/json/Lexer;)Lscala/util/parsing/combinator/Parsers$Parser;
  Code:
   Stack=1, Locals=2, Args_size=2
	aload_1
	invokevirtual	Method delim:()Lscala/util/parsing/combinator/Parsers$Parser;
	areturn
  Labels:
  Signature: length = 0x2
   00 35 

public scala.util.parsing.combinator.Parsers$Parser token();
  Signature: ()Lscala/util/parsing/combinator/Parsers$Parser;
  Code:
   Stack=4, Locals=1, Args_size=1
	aload_0
	invokevirtual	Method string:()Lscala/util/parsing/combinator/Parsers$Parser;
	aload_0
	invokeinterface	InterfaceMethod scala/util/parsing/syntax/StdTokens.StringLit:()Lscala/util/parsing/syntax/StdTokens$StringLit$;
	invokevirtual	Method scala/util/parsing/combinator/Parsers$Parser.$up$up:(Lscala/Function1;)Lscala/util/parsing/combinator/Parsers$Parser;
	new	class scala/util/parsing/json/Lexer$$anonfun$token$1
	dup
	aload_0
	invokespecial	Method scala/util/parsing/json/Lexer$$anonfun$token$1."<init>":(Lscala/util/parsing/json/Lexer;)V
	invokevirtual	Method scala/util/parsing/combinator/Parsers$Parser.$bar:(Lscala/Function0;)Lscala/util/parsing/combinator/Parsers$Parser;
	new	class scala/util/parsing/json/Lexer$$anonfun$token$2
	dup
	aload_0
	invokespecial	Method scala/util/parsing/json/Lexer$$anonfun$token$2."<init>":(Lscala/util/parsing/json/Lexer;)V
	invokevirtual	Method scala/util/parsing/combinator/Parsers$Parser.$bar:(Lscala/Function0;)Lscala/util/parsing/combinator/Parsers$Parser;
	new	class scala/util/parsing/json/Lexer$$anonfun$token$3
	dup
	aload_0
	invokespecial	Method scala/util/parsing/json/Lexer$$anonfun$token$3."<init>":(Lscala/util/parsing/json/Lexer;)V
	invokevirtual	Method scala/util/parsing/combinator/Parsers$Parser.$bar:(Lscala/Function0;)Lscala/util/parsing/combinator/Parsers$Parser;
	new	class scala/util/parsing/json/Lexer$$anonfun$token$4
	dup
	aload_0
	invokespecial	Method scala/util/parsing/json/Lexer$$anonfun$token$4."<init>":(Lscala/util/parsing/json/Lexer;)V
	invokevirtual	Method scala/util/parsing/combinator/Parsers$Parser.$bar:(Lscala/Function0;)Lscala/util/parsing/combinator/Parsers$Parser;
	new	class scala/util/parsing/json/Lexer$$anonfun$token$5
	dup
	aload_0
	invokespecial	Method scala/util/parsing/json/Lexer$$anonfun$token$5."<init>":(Lscala/util/parsing/json/Lexer;)V
	invokevirtual	Method scala/util/parsing/combinator/Parsers$Parser.$bar:(Lscala/Function0;)Lscala/util/parsing/combinator/Parsers$Parser;
	new	class scala/util/parsing/json/Lexer$$anonfun$token$6
	dup
	aload_0
	invokespecial	Method scala/util/parsing/json/Lexer$$anonfun$token$6."<init>":(Lscala/util/parsing/json/Lexer;)V
	invokevirtual	Method scala/util/parsing/combinator/Parsers$Parser.$bar:(Lscala/Function0;)Lscala/util/parsing/combinator/Parsers$Parser;
	new	class scala/util/parsing/json/Lexer$$anonfun$token$7
	dup
	aload_0
	invokespecial	Method scala/util/parsing/json/Lexer$$anonfun$token$7."<init>":(Lscala/util/parsing/json/Lexer;)V
	invokevirtual	Method scala/util/parsing/combinator/Parsers$Parser.$bar:(Lscala/Function0;)Lscala/util/parsing/combinator/Parsers$Parser;
	new	class scala/util/parsing/json/Lexer$$anonfun$token$8
	dup
	aload_0
	invokespecial	Method scala/util/parsing/json/Lexer$$anonfun$token$8."<init>":(Lscala/util/parsing/json/Lexer;)V
	invokevirtual	Method scala/util/parsing/combinator/Parsers$Parser.$bar:(Lscala/Function0;)Lscala/util/parsing/combinator/Parsers$Parser;
	new	class scala/util/parsing/json/Lexer$$anonfun$token$9
	dup
	aload_0
	invokespecial	Method scala/util/parsing/json/Lexer$$anonfun$token$9."<init>":(Lscala/util/parsing/json/Lexer;)V
	invokevirtual	Method scala/util/parsing/combinator/Parsers$Parser.$bar:(Lscala/Function0;)Lscala/util/parsing/combinator/Parsers$Parser;
	areturn
  Labels:
  Signature: length = 0x2
   00 68 

public scala.util.parsing.syntax.Tokens$Token checkKeyword(scala.collection.immutable.List);
  Signature: (Lscala/collection/immutable/List;)Lscala/util/parsing/syntax/Tokens$Token;
  Code:
   Stack=5, Locals=3, Args_size=2
	aload_1
	ldc	String 
	invokeinterface	InterfaceMethod scala/collection/TraversableLike.mkString:(Ljava/lang/String;)Ljava/lang/String;
	astore_2
	aload_0
	invokevirtual	Method reserved:()Lscala/collection/mutable/HashSet;
	aload_2
	invokevirtual	Method scala/collection/mutable/HashSet.contains:(Ljava/lang/Object;)Z
	ifeq	l1 // new
	new	class scala/util/parsing/syntax/StdTokens$Keyword
	dup
	aload_0
	aload_2
	invokespecial	Method scala/util/parsing/syntax/StdTokens$Keyword."<init>":(Lscala/util/parsing/syntax/StdTokens;Ljava/lang/String;)V
	goto	l2 // areturn
l1	new	class scala/util/parsing/syntax/Tokens$ErrorToken
	dup
	aload_0
	new	class scala/collection/mutable/StringBuilder
	dup
	invokespecial	Method scala/collection/mutable/StringBuilder."<init>":()V
	ldc	String Not a keyword: 
	invokevirtual	Method scala/collection/mutable/StringBuilder.append:(Ljava/lang/Object;)Lscala/collection/mutable/StringBuilder;
	aload_2
	invokevirtual	Method scala/collection/mutable/StringBuilder.append:(Ljava/lang/Object;)Lscala/collection/mutable/StringBuilder;
	invokevirtual	Method scala/collection/mutable/StringBuilder.toString:()Ljava/lang/String;
	invokespecial	Method scala/util/parsing/syntax/Tokens$ErrorToken."<init>":(Lscala/util/parsing/syntax/Tokens;Ljava/lang/String;)V
l2	areturn
  Labels:
   	l1 = 32 // new
   	l2 = 59 // areturn
  LocalVariableTable: 
   Start  Length  Slot  Name   Signature
   0      60      0    this       Lscala/util/parsing/json/Lexer;
   0      60      1    xs       Lscala/collection/immutable/List;
   9      51      2    strRep       Ljava/lang/String;

  Signature: length = 0x2
   00 FFFFFF9A 

public scala.util.parsing.combinator.Parsers$Parser string();
  Signature: ()Lscala/util/parsing/combinator/Parsers$Parser;
  Code:
   Stack=4, Locals=2, Args_size=1
	aload_0
	ldc	int 34
	istore_1
	iload_1
	invokestatic	Method scala/runtime/BoxesRunTime.boxToCharacter:(C)Ljava/lang/Character;
	invokeinterface	InterfaceMethod scala/util/parsing/combinator/Parsers.accept:(Ljava/lang/Object;)Lscala/util/parsing/combinator/Parsers$Parser;
	new	class scala/util/parsing/json/Lexer$$anonfun$string$1
	dup
	aload_0
	invokespecial	Method scala/util/parsing/json/Lexer$$anonfun$string$1."<init>":(Lscala/util/parsing/json/Lexer;)V
	invokevirtual	Method scala/util/parsing/combinator/Parsers$Parser.$tilde$greater:(Lscala/Function0;)Lscala/util/parsing/combinator/Parsers$Parser;
	new	class scala/util/parsing/json/Lexer$$anonfun$string$2
	dup
	aload_0
	invokespecial	Method scala/util/parsing/json/Lexer$$anonfun$string$2."<init>":(Lscala/util/parsing/json/Lexer;)V
	invokevirtual	Method scala/util/parsing/combinator/Parsers$Parser.$less$tilde:(Lscala/Function0;)Lscala/util/parsing/combinator/Parsers$Parser;
	new	class scala/util/parsing/json/Lexer$$anonfun$string$3
	dup
	aload_0
	invokespecial	Method scala/util/parsing/json/Lexer$$anonfun$string$3."<init>":(Lscala/util/parsing/json/Lexer;)V
	invokevirtual	Method scala/util/parsing/combinator/Parsers$Parser.$up$up:(Lscala/Function1;)Lscala/util/parsing/combinator/Parsers$Parser;
	areturn
  Labels:
  Signature: length = 0x2
   00 FFFFFFB7 

public scala.util.parsing.combinator.Parsers$Parser whitespace();
  Signature: ()Lscala/util/parsing/combinator/Parsers$Parser;
  Code:
   Stack=4, Locals=1, Args_size=1
	aload_0
	new	class scala/util/parsing/json/Lexer$$anonfun$whitespace$1
	dup
	aload_0
	invokespecial	Method scala/util/parsing/json/Lexer$$anonfun$whitespace$1."<init>":(Lscala/util/parsing/json/Lexer;)V
	invokeinterface	InterfaceMethod scala/util/parsing/combinator/Parsers.rep:(Lscala/Function0;)Lscala/util/parsing/combinator/Parsers$Parser;
	areturn
  Labels:
  Signature: length = 0x2
   00 FFFFFFBF 

public scala.util.parsing.combinator.Parsers$Parser number();
  Signature: ()Lscala/util/parsing/combinator/Parsers$Parser;
  Code:
   Stack=4, Locals=1, Args_size=1
	aload_0
	invokevirtual	Method intPart:()Lscala/util/parsing/combinator/Parsers$Parser;
	new	class scala/util/parsing/json/Lexer$$anonfun$number$1
	dup
	aload_0
	invokespecial	Method scala/util/parsing/json/Lexer$$anonfun$number$1."<init>":(Lscala/util/parsing/json/Lexer;)V
	invokevirtual	Method scala/util/parsing/combinator/Parsers$Parser.$tilde:(Lscala/Function0;)Lscala/util/parsing/combinator/Parsers$Parser;
	new	class scala/util/parsing/json/Lexer$$anonfun$number$2
	dup
	aload_0
	invokespecial	Method scala/util/parsing/json/Lexer$$anonfun$number$2."<init>":(Lscala/util/parsing/json/Lexer;)V
	invokevirtual	Method scala/util/parsing/combinator/Parsers$Parser.$tilde:(Lscala/Function0;)Lscala/util/parsing/combinator/Parsers$Parser;
	new	class scala/util/parsing/json/Lexer$$anonfun$number$3
	dup
	aload_0
	invokespecial	Method scala/util/parsing/json/Lexer$$anonfun$number$3."<init>":(Lscala/util/parsing/json/Lexer;)V
	invokevirtual	Method scala/util/parsing/combinator/Parsers$Parser.$up$up:(Lscala/Function1;)Lscala/util/parsing/combinator/Parsers$Parser;
	areturn
  Labels:
  Signature: length = 0x2
   00 FFFFFFB7 

public scala.util.parsing.combinator.Parsers$Parser intPart();
  Signature: ()Lscala/util/parsing/combinator/Parsers$Parser;
  Code:
   Stack=4, Locals=1, Args_size=1
	aload_0
	invokevirtual	Method zero:()Lscala/util/parsing/combinator/Parsers$Parser;
	new	class scala/util/parsing/json/Lexer$$anonfun$intPart$1
	dup
	aload_0
	invokespecial	Method scala/util/parsing/json/Lexer$$anonfun$intPart$1."<init>":(Lscala/util/parsing/json/Lexer;)V
	invokevirtual	Method scala/util/parsing/combinator/Parsers$Parser.$bar:(Lscala/Function0;)Lscala/util/parsing/combinator/Parsers$Parser;
	areturn
  Labels:
  Signature: length = 0x2
   00 FFFFFFB7 

public scala.util.parsing.combinator.Parsers$Parser intList();
  Signature: ()Lscala/util/parsing/combinator/Parsers$Parser;
  Code:
   Stack=4, Locals=1, Args_size=1
	aload_0
	invokevirtual	Method nonzero:()Lscala/util/parsing/combinator/Parsers$Parser;
	new	class scala/util/parsing/json/Lexer$$anonfun$intList$1
	dup
	aload_0
	invokespecial	Method scala/util/parsing/json/Lexer$$anonfun$intList$1."<init>":(Lscala/util/parsing/json/Lexer;)V
	invokevirtual	Method scala/util/parsing/combinator/Parsers$Parser.$tilde:(Lscala/Function0;)Lscala/util/parsing/combinator/Parsers$Parser;
	new	class scala/util/parsing/json/Lexer$$anonfun$intList$2
	dup
	aload_0
	invokespecial	Method scala/util/parsing/json/Lexer$$anonfun$intList$2."<init>":(Lscala/util/parsing/json/Lexer;)V
	invokevirtual	Method scala/util/parsing/combinator/Parsers$Parser.$up$up:(Lscala/Function1;)Lscala/util/parsing/combinator/Parsers$Parser;
	areturn
  Labels:
  Signature: length = 0x2
   00 FFFFFFB7 

public scala.util.parsing.combinator.Parsers$Parser fracPart();
  Signature: ()Lscala/util/parsing/combinator/Parsers$Parser;
  Code:
   Stack=4, Locals=2, Args_size=1
	aload_0
	ldc	int 46
	istore_1
	iload_1
	invokestatic	Method scala/runtime/BoxesRunTime.boxToCharacter:(C)Ljava/lang/Character;
	invokeinterface	InterfaceMethod scala/util/parsing/combinator/Parsers.accept:(Ljava/lang/Object;)Lscala/util/parsing/combinator/Parsers$Parser;
	new	class scala/util/parsing/json/Lexer$$anonfun$fracPart$1
	dup
	aload_0
	invokespecial	Method scala/util/parsing/json/Lexer$$anonfun$fracPart$1."<init>":(Lscala/util/parsing/json/Lexer;)V
	invokevirtual	Method scala/util/parsing/combinator/Parsers$Parser.$tilde$greater:(Lscala/Function0;)Lscala/util/parsing/combinator/Parsers$Parser;
	new	class scala/util/parsing/json/Lexer$$anonfun$fracPart$2
	dup
	aload_0
	invokespecial	Method scala/util/parsing/json/Lexer$$anonfun$fracPart$2."<init>":(Lscala/util/parsing/json/Lexer;)V
	invokevirtual	Method scala/util/parsing/combinator/Parsers$Parser.$up$up:(Lscala/Function1;)Lscala/util/parsing/combinator/Parsers$Parser;
	areturn
  Labels:
  Signature: length = 0x2
   00 FFFFFFB7 

public scala.util.parsing.combinator.Parsers$Parser expPart();
  Signature: ()Lscala/util/parsing/combinator/Parsers$Parser;
  Code:
   Stack=4, Locals=1, Args_size=1
	aload_0
	invokevirtual	Method exponent:()Lscala/util/parsing/combinator/Parsers$Parser;
	new	class scala/util/parsing/json/Lexer$$anonfun$expPart$1
	dup
	aload_0
	invokespecial	Method scala/util/parsing/json/Lexer$$anonfun$expPart$1."<init>":(Lscala/util/parsing/json/Lexer;)V
	invokevirtual	Method scala/util/parsing/combinator/Parsers$Parser.$tilde:(Lscala/Function0;)Lscala/util/parsing/combinator/Parsers$Parser;
	new	class scala/util/parsing/json/Lexer$$anonfun$expPart$2
	dup
	aload_0
	invokespecial	Method scala/util/parsing/json/Lexer$$anonfun$expPart$2."<init>":(Lscala/util/parsing/json/Lexer;)V
	invokevirtual	Method scala/util/parsing/combinator/Parsers$Parser.$tilde:(Lscala/Function0;)Lscala/util/parsing/combinator/Parsers$Parser;
	new	class scala/util/parsing/json/Lexer$$anonfun$expPart$3
	dup
	aload_0
	invokespecial	Method scala/util/parsing/json/Lexer$$anonfun$expPart$3."<init>":(Lscala/util/parsing/json/Lexer;)V
	invokevirtual	Method scala/util/parsing/combinator/Parsers$Parser.$up$up:(Lscala/Function1;)Lscala/util/parsing/combinator/Parsers$Parser;
	areturn
  Labels:
  Signature: length = 0x2
   00 FFFFFFB7 

public final java.lang.String scala$util$parsing$json$Lexer$$optString(java.lang.String, scala.Option);
  Signature: (Ljava/lang/String;Lscala/Option;)Ljava/lang/String;
  Code:
   Stack=3, Locals=5, Args_size=3
	aload_2
	instanceof	class scala/Some
	ifeq	l1 // getstatic
	aload_2
	checkcast	class scala/Some
	astore_3
	aload_3
	getfield	Field scala/Some.x:Ljava/lang/Object;
	astore	4
	new	class scala/collection/mutable/StringBuilder
	dup
	invokespecial	Method scala/collection/mutable/StringBuilder."<init>":()V
	aload_1
	invokevirtual	Method scala/collection/mutable/StringBuilder.append:(Ljava/lang/Object;)Lscala/collection/mutable/StringBuilder;
	aload	4
	invokevirtual	Method java/lang/Object.toString:()Ljava/lang/String;
	invokevirtual	Method scala/collection/mutable/StringBuilder.append:(Ljava/lang/Object;)Lscala/collection/mutable/StringBuilder;
	invokevirtual	Method scala/collection/mutable/StringBuilder.toString:()Ljava/lang/String;
	goto	l2 // areturn
l1	getstatic	Field scala/None$.MODULE$:Lscala/None$;
	dup
	ifnonnull	l3 // aload_2
	pop
	aload_2
	ifnull	l4 // ldc
	goto	l5 // new
l3	aload_2
	invokevirtual	Method java/lang/Object.equals:(Ljava/lang/Object;)Z
	ifeq	l5 // new
l4	ldc	String 
l2	areturn
l5	new	class scala/MatchError
	dup
	aload_2
	invokevirtual	Method scala/Option.toString:()Ljava/lang/String;
	invokespecial	Method scala/MatchError."<init>":(Ljava/lang/String;)V
	athrow
  Labels:
   	l1 = 43 // getstatic
   	l3 = 58 // aload_2
   	l4 = 65 // ldc
   	l2 = 67 // areturn
   	l5 = 68 // new
  LocalVariableTable: 
   Start  Length  Slot  Name   Signature
   0      80      0    this       Lscala/util/parsing/json/Lexer;
   0      80      1    pre       Ljava/lang/String;
   0      80      2    a       Lscala/Option;
   12      28      3    temp26       Lscala/Some;
   18      22      4    temp27       Ljava/lang/Object;


public scala.util.parsing.combinator.Parsers$Parser zero();
  Signature: ()Lscala/util/parsing/combinator/Parsers$Parser;
  Code:
   Stack=2, Locals=2, Args_size=1
	aload_0
	ldc_w	int 48
	istore_1
	iload_1
	invokestatic	Method scala/runtime/BoxesRunTime.boxToCharacter:(C)Ljava/lang/Character;
	invokeinterface	InterfaceMethod scala/util/parsing/combinator/Parsers.accept:(Ljava/lang/Object;)Lscala/util/parsing/combinator/Parsers$Parser;
	ldc_w	String 0
	invokevirtual	Method scala/util/parsing/combinator/Parsers$Parser.$up$up$up:(Ljava/lang/Object;)Lscala/util/parsing/combinator/Parsers$Parser;
	areturn
  Labels:
  Signature: length = 0x2
   00 FFFFFFB7 

public scala.util.parsing.combinator.Parsers$Parser nonzero();
  Signature: ()Lscala/util/parsing/combinator/Parsers$Parser;
  Code:
   Stack=5, Locals=1, Args_size=1
	aload_0
	ldc_w	String nonzero digit
	new	class scala/util/parsing/json/Lexer$$anonfun$nonzero$1
	dup
	aload_0
	invokespecial	Method scala/util/parsing/json/Lexer$$anonfun$nonzero$1."<init>":(Lscala/util/parsing/json/Lexer;)V
	invokeinterface	InterfaceMethod scala/util/parsing/combinator/Parsers.elem:(Ljava/lang/String;Lscala/Function1;)Lscala/util/parsing/combinator/Parsers$Parser;
	areturn
  Labels:
  Signature: length = 0x2
   01 26 

public scala.util.parsing.combinator.Parsers$Parser exponent();
  Signature: ()Lscala/util/parsing/combinator/Parsers$Parser;
  Code:
   Stack=5, Locals=1, Args_size=1
	aload_0
	ldc_w	String exponent character
	new	class scala/util/parsing/json/Lexer$$anonfun$exponent$1
	dup
	aload_0
	invokespecial	Method scala/util/parsing/json/Lexer$$anonfun$exponent$1."<init>":(Lscala/util/parsing/json/Lexer;)V
	invokeinterface	InterfaceMethod scala/util/parsing/combinator/Parsers.elem:(Ljava/lang/String;Lscala/Function1;)Lscala/util/parsing/combinator/Parsers$Parser;
	areturn
  Labels:
  Signature: length = 0x2
   01 26 

public scala.util.parsing.combinator.Parsers$Parser sign();
  Signature: ()Lscala/util/parsing/combinator/Parsers$Parser;
  Code:
   Stack=5, Locals=1, Args_size=1
	aload_0
	ldc_w	String sign character
	new	class scala/util/parsing/json/Lexer$$anonfun$sign$1
	dup
	aload_0
	invokespecial	Method scala/util/parsing/json/Lexer$$anonfun$sign$1."<init>":(Lscala/util/parsing/json/Lexer;)V
	invokeinterface	InterfaceMethod scala/util/parsing/combinator/Parsers.elem:(Ljava/lang/String;Lscala/Function1;)Lscala/util/parsing/combinator/Parsers$Parser;
	areturn
  Labels:
  Signature: length = 0x2
   01 26 

public scala.util.parsing.combinator.Parsers$Parser charSeq();
  Signature: ()Lscala/util/parsing/combinator/Parsers$Parser;
  Code:
   Stack=4, Locals=2, Args_size=1
	aload_0
	ldc_w	int 92
	istore_1
	iload_1
	invokestatic	Method scala/runtime/BoxesRunTime.boxToCharacter:(C)Ljava/lang/Character;
	invokeinterface	InterfaceMethod scala/util/parsing/combinator/Parsers.accept:(Ljava/lang/Object;)Lscala/util/parsing/combinator/Parsers$Parser;
	new	class scala/util/parsing/json/Lexer$$anonfun$charSeq$1
	dup
	aload_0
	invokespecial	Method scala/util/parsing/json/Lexer$$anonfun$charSeq$1."<init>":(Lscala/util/parsing/json/Lexer;)V
	invokevirtual	Method scala/util/parsing/combinator/Parsers$Parser.$tilde:(Lscala/Function0;)Lscala/util/parsing/combinator/Parsers$Parser;
	ldc_w	String \"
	invokevirtual	Method scala/util/parsing/combinator/Parsers$Parser.$up$up$up:(Ljava/lang/Object;)Lscala/util/parsing/combinator/Parsers$Parser;
	new	class scala/util/parsing/json/Lexer$$anonfun$charSeq$2
	dup
	aload_0
	invokespecial	Method scala/util/parsing/json/Lexer$$anonfun$charSeq$2."<init>":(Lscala/util/parsing/json/Lexer;)V
	invokevirtual	Method scala/util/parsing/combinator/Parsers$Parser.$bar:(Lscala/Function0;)Lscala/util/parsing/combinator/Parsers$Parser;
	new	class scala/util/parsing/json/Lexer$$anonfun$charSeq$3
	dup
	aload_0
	invokespecial	Method scala/util/parsing/json/Lexer$$anonfun$charSeq$3."<init>":(Lscala/util/parsing/json/Lexer;)V
	invokevirtual	Method scala/util/parsing/combinator/Parsers$Parser.$bar:(Lscala/Function0;)Lscala/util/parsing/combinator/Parsers$Parser;
	new	class scala/util/parsing/json/Lexer$$anonfun$charSeq$4
	dup
	aload_0
	invokespecial	Method scala/util/parsing/json/Lexer$$anonfun$charSeq$4."<init>":(Lscala/util/parsing/json/Lexer;)V
	invokevirtual	Method scala/util/parsing/combinator/Parsers$Parser.$bar:(Lscala/Function0;)Lscala/util/parsing/combinator/Parsers$Parser;
	new	class scala/util/parsing/json/Lexer$$anonfun$charSeq$5
	dup
	aload_0
	invokespecial	Method scala/util/parsing/json/Lexer$$anonfun$charSeq$5."<init>":(Lscala/util/parsing/json/Lexer;)V
	invokevirtual	Method scala/util/parsing/combinator/Parsers$Parser.$bar:(Lscala/Function0;)Lscala/util/parsing/combinator/Parsers$Parser;
	new	class scala/util/parsing/json/Lexer$$anonfun$charSeq$6
	dup
	aload_0
	invokespecial	Method scala/util/parsing/json/Lexer$$anonfun$charSeq$6."<init>":(Lscala/util/parsing/json/Lexer;)V
	invokevirtual	Method scala/util/parsing/combinator/Parsers$Parser.$bar:(Lscala/Function0;)Lscala/util/parsing/combinator/Parsers$Parser;
	new	class scala/util/parsing/json/Lexer$$anonfun$charSeq$7
	dup
	aload_0
	invokespecial	Method scala/util/parsing/json/Lexer$$anonfun$charSeq$7."<init>":(Lscala/util/parsing/json/Lexer;)V
	invokevirtual	Method scala/util/parsing/combinator/Parsers$Parser.$bar:(Lscala/Function0;)Lscala/util/parsing/combinator/Parsers$Parser;
	new	class scala/util/parsing/json/Lexer$$anonfun$charSeq$8
	dup
	aload_0
	invokespecial	Method scala/util/parsing/json/Lexer$$anonfun$charSeq$8."<init>":(Lscala/util/parsing/json/Lexer;)V
	invokevirtual	Method scala/util/parsing/combinator/Parsers$Parser.$bar:(Lscala/Function0;)Lscala/util/parsing/combinator/Parsers$Parser;
	new	class scala/util/parsing/json/Lexer$$anonfun$charSeq$9
	dup
	aload_0
	invokespecial	Method scala/util/parsing/json/Lexer$$anonfun$charSeq$9."<init>":(Lscala/util/parsing/json/Lexer;)V
	invokevirtual	Method scala/util/parsing/combinator/Parsers$Parser.$bar:(Lscala/Function0;)Lscala/util/parsing/combinator/Parsers$Parser;
	areturn
  Labels:
  Signature: length = 0x2
   00 FFFFFFB7 

public scala.collection.immutable.Set hexDigits();
  Signature: ()Lscala/collection/immutable/Set;
  Code:
   Stack=1, Locals=1, Args_size=1
	aload_0
	getfield	Field hexDigits:Lscala/collection/immutable/Set;
	areturn
  Labels:
  Signature: length = 0x2
   01 54 

public scala.util.parsing.combinator.Parsers$Parser hexDigit();
  Signature: ()Lscala/util/parsing/combinator/Parsers$Parser;
  Code:
   Stack=5, Locals=1, Args_size=1
	aload_0
	ldc_w	String hex digit
	new	class scala/util/parsing/json/Lexer$$anonfun$hexDigit$1
	dup
	aload_0
	invokespecial	Method scala/util/parsing/json/Lexer$$anonfun$hexDigit$1."<init>":(Lscala/util/parsing/json/Lexer;)V
	invokeinterface	InterfaceMethod scala/util/parsing/combinator/Parsers.elem:(Ljava/lang/String;Lscala/Function1;)Lscala/util/parsing/combinator/Parsers$Parser;
	areturn
  Labels:
  Signature: length = 0x2
   01 26 

public final scala.util.parsing.combinator.Parsers$Parser scala$util$parsing$json$Lexer$$unicodeBlock();
  Signature: ()Lscala/util/parsing/combinator/Parsers$Parser;
  Code:
   Stack=4, Locals=1, Args_size=1
	aload_0
	invokevirtual	Method hexDigit:()Lscala/util/parsing/combinator/Parsers$Parser;
	new	class scala/util/parsing/json/Lexer$$anonfun$scala$util$parsing$json$Lexer$$unicodeBlock$1
	dup
	aload_0
	invokespecial	Method scala/util/parsing/json/Lexer$$anonfun$scala$util$parsing$json$Lexer$$unicodeBlock$1."<init>":(Lscala/util/parsing/json/Lexer;)V
	invokevirtual	Method scala/util/parsing/combinator/Parsers$Parser.$tilde:(Lscala/Function0;)Lscala/util/parsing/combinator/Parsers$Parser;
	new	class scala/util/parsing/json/Lexer$$anonfun$scala$util$parsing$json$Lexer$$unicodeBlock$2
	dup
	aload_0
	invokespecial	Method scala/util/parsing/json/Lexer$$anonfun$scala$util$parsing$json$Lexer$$unicodeBlock$2."<init>":(Lscala/util/parsing/json/Lexer;)V
	invokevirtual	Method scala/util/parsing/combinator/Parsers$Parser.$tilde:(Lscala/Function0;)Lscala/util/parsing/combinator/Parsers$Parser;
	new	class scala/util/parsing/json/Lexer$$anonfun$scala$util$parsing$json$Lexer$$unicodeBlock$3
	dup
	aload_0
	invokespecial	Method scala/util/parsing/json/Lexer$$anonfun$scala$util$parsing$json$Lexer$$unicodeBlock$3."<init>":(Lscala/util/parsing/json/Lexer;)V
	invokevirtual	Method scala/util/parsing/combinator/Parsers$Parser.$tilde:(Lscala/Function0;)Lscala/util/parsing/combinator/Parsers$Parser;
	new	class scala/util/parsing/json/Lexer$$anonfun$scala$util$parsing$json$Lexer$$unicodeBlock$4
	dup
	aload_0
	invokespecial	Method scala/util/parsing/json/Lexer$$anonfun$scala$util$parsing$json$Lexer$$unicodeBlock$4."<init>":(Lscala/util/parsing/json/Lexer;)V
	invokevirtual	Method scala/util/parsing/combinator/Parsers$Parser.$up$up:(Lscala/Function1;)Lscala/util/parsing/combinator/Parsers$Parser;
	areturn
  Labels:

public scala.util.parsing.json.Lexer();
  Signature: ()V
  Code:
   Stack=5, Locals=1, Args_size=1
	aload_0
	invokespecial	Method scala/util/parsing/combinator/lexical/StdLexical."<init>":()V
	aload_0
	invokestatic	Method scala/util/parsing/combinator/ImplicitConversions$class.$init$:(Lscala/util/parsing/combinator/ImplicitConversions;)V
	aload_0
	getstatic	Field scala/Predef$.MODULE$:Lscala/Predef$;
	invokevirtual	Method scala/Predef$.Set:()Lscala/collection/immutable/Set$;
	getstatic	Field scala/Predef$.MODULE$:Lscala/Predef$;
	iconst_0
	newarray char
	invokevirtual	Method scala/Predef$.wrapCharArray:([C)Lscala/collection/mutable/WrappedArray;
	invokevirtual	Method scala/collection/immutable/Set$.apply:(Lscala/collection/Seq;)Lscala/collection/Traversable;
	checkcast	class scala/collection/generic/Addable
	getstatic	Field scala/Predef$.MODULE$:Lscala/Predef$;
	getstatic	Field scala/Predef$.MODULE$:Lscala/Predef$;
	ldc_w	String 0123456789abcdefABCDEF
	invokevirtual	Method scala/Predef$.augmentString:(Ljava/lang/String;)Lscala/collection/immutable/StringOps;
	getstatic	Field scala/reflect/Manifest$.MODULE$:Lscala/reflect/Manifest$;
	invokevirtual	Method scala/reflect/Manifest$.Char:()Lscala/reflect/AnyValManifest;
	invokeinterface	InterfaceMethod scala/collection/TraversableLike.toArray:(Lscala/reflect/ClassManifest;)Ljava/lang/Object;
	checkcast	class "[C"
	invokevirtual	Method scala/Predef$.wrapCharArray:([C)Lscala/collection/mutable/WrappedArray;
	invokeinterface	InterfaceMethod scala/collection/generic/Addable.$plus$plus:(Lscala/collection/Traversable;)Lscala/collection/generic/Addable;
	checkcast	class scala/collection/immutable/Set
	putfield	Field hexDigits:Lscala/collection/immutable/Set;
	return
  Labels:

}

