Compiled from "Lexer.scala"
public final class scala.util.parsing.json.Lexer$$anonfun$sign$1 extends scala.runtime.AbstractFunction1 implements java.io.Serializable
  SourceFile: "Lexer.scala"
  Scala: length = 0x
   
  InnerClass: 
   public final $anonfun$sign$1=class scala/util/parsing/json/Lexer$$anonfun$sign$1 of class scala/util/parsing/json/Lexer
  minor version: 0
  major version: 49
  Constant pool:
Asciz	SourceFile;
Asciz	Lexer.scala;
Asciz	<clinit>;
Asciz	()V;
Asciz	Code;
Asciz	serialVersionUID;
Asciz	J;
Asciz	scala/util/parsing/json/Lexer$$anonfun$sign$1;
class	scala/util/parsing/json/Lexer$$anonfun$sign$1
NameAndType	serialVersionUID:J
Field	scala/util/parsing/json/Lexer$$anonfun$sign$1.serialVersionUID:J
Asciz	apply;
Asciz	(C)Z;
Asciz	LineNumberTable;
int	45;
int	43;
Asciz	this;
Asciz	Lscala/util/parsing/json/Lexer$$anonfun$sign$1;;
Asciz	d;
Asciz	C;
Asciz	LocalVariableTable;
Asciz	(Ljava/lang/Object;)Ljava/lang/Object;;
Asciz	scala/runtime/BoxesRunTime;
class	scala/runtime/BoxesRunTime
Asciz	unboxToChar;
Asciz	(Ljava/lang/Object;)C;
NameAndType	unboxToChar:(Ljava/lang/Object;)C
Method	scala/runtime/BoxesRunTime.unboxToChar:(Ljava/lang/Object;)C
NameAndType	apply:(C)Z
Method	scala/util/parsing/json/Lexer$$anonfun$sign$1.apply:(C)Z
Asciz	boxToBoolean;
Asciz	(Z)Ljava/lang/Boolean;;
NameAndType	boxToBoolean:(Z)Ljava/lang/Boolean;
Method	scala/runtime/BoxesRunTime.boxToBoolean:(Z)Ljava/lang/Boolean;
Asciz	v1;
Asciz	Ljava/lang/Object;;
Asciz	<init>;
Asciz	(Lscala/util/parsing/json/Lexer;)V;
Asciz	scala/runtime/AbstractFunction1;
class	scala/runtime/AbstractFunction1
NameAndType	"<init>":()V
Method	scala/runtime/AbstractFunction1."<init>":()V
Asciz	$outer;
Asciz	Lscala/util/parsing/json/Lexer;;
Asciz	Scala;
Asciz	InnerClasses;
Asciz	scala/util/parsing/json/Lexer;
class	scala/util/parsing/json/Lexer
Asciz	$anonfun$sign$1;
Asciz	java/io/Serializable;
class	java/io/Serializable

{
public static final long serialVersionUID;
  Signature: J

public static {};
  Signature: ()V
  Code:
   Stack=2, Locals=0, Args_size=0
	lconst_0
	putstatic	Field serialVersionUID:J
	return
  Labels:

public final boolean apply(char);
  Signature: (C)Z
  Code:
   Stack=2, Locals=2, Args_size=2
	iload_1
	ldc	int 45
	if_icmpeq	l1 // iconst_1
	iload_1
	ldc	int 43
	if_icmpne	l2 // iconst_0
l1	iconst_1
	goto	l3 // ireturn
l2	iconst_0
l3	ireturn
  Labels:
   	l1 = 12 // iconst_1
   	l2 = 16 // iconst_0
   	l3 = 17 // ireturn
  LocalVariableTable: 
   Start  Length  Slot  Name   Signature
   0      18      0    this       Lscala/util/parsing/json/Lexer$$anonfun$sign$1;
   0      18      1    d       C


public final java.lang.Object apply(java.lang.Object);
  Signature: (Ljava/lang/Object;)Ljava/lang/Object;
  Code:
   Stack=2, Locals=3, Args_size=2
	aload_0
	aload_1
	invokestatic	Method scala/runtime/BoxesRunTime.unboxToChar:(Ljava/lang/Object;)C
	invokevirtual	Method apply:(C)Z
	istore_2
	iload_2
	invokestatic	Method scala/runtime/BoxesRunTime.boxToBoolean:(Z)Ljava/lang/Boolean;
	areturn
  Labels:
  LocalVariableTable: 
   Start  Length  Slot  Name   Signature
   0      14      0    this       Lscala/util/parsing/json/Lexer$$anonfun$sign$1;
   0      14      1    v1       Ljava/lang/Object;


public scala.util.parsing.json.Lexer$$anonfun$sign$1(scala.util.parsing.json.Lexer);
  Signature: (Lscala/util/parsing/json/Lexer;)V
  Code:
   Stack=1, Locals=2, Args_size=2
	aload_0
	invokespecial	Method scala/runtime/AbstractFunction1."<init>":()V
	return
  Labels:
  LocalVariableTable: 
   Start  Length  Slot  Name   Signature
   0      5      0    this       Lscala/util/parsing/json/Lexer$$anonfun$sign$1;
   0      5      1    $outer       Lscala/util/parsing/json/Lexer;


}

