Compiled from "Lexer.scala"
public final class scala.util.parsing.json.Lexer$$anonfun$expPart$3 extends java.lang.Object implements scala.Function1,scala.ScalaObject,java.io.Serializable
  SourceFile: "Lexer.scala"
  Scala: length = 0x
   
  InnerClass: 
   public #122= #38 of #121; //$tilde=class scala/util/parsing/combinator/Parsers$$tilde of class scala/util/parsing/combinator/Parsers
   public final #123= #9 of #71; //$anonfun$expPart$3=class scala/util/parsing/json/Lexer$$anonfun$expPart$3 of class scala/util/parsing/json/Lexer
  minor version: 0
  major version: 49
  Constant pool:
const #1 = Asciz	SourceFile;
const #2 = Asciz	Lexer.scala;
const #3 = Asciz	<clinit>;
const #4 = Asciz	()V;
const #5 = Asciz	Code;
const #6 = Asciz	serialVersionUID;
const #7 = Asciz	J;
const #8 = Asciz	scala/util/parsing/json/Lexer$$anonfun$expPart$3;
const #9 = class	#8;	//  scala/util/parsing/json/Lexer$$anonfun$expPart$3
const #10 = NameAndType	#6:#7;//  serialVersionUID:J
const #11 = Field	#9.#10;	//  scala/util/parsing/json/Lexer$$anonfun$expPart$3.serialVersionUID:J
const #12 = Asciz	$outer;
const #13 = Asciz	Lscala/util/parsing/json/Lexer;;
const #14 = Asciz	<init>;
const #15 = Asciz	(Lscala/util/parsing/json/Lexer;)V;
const #16 = Asciz	LineNumberTable;
const #17 = Asciz	java/lang/NullPointerException;
const #18 = class	#17;	//  java/lang/NullPointerException
const #19 = NameAndType	#14:#4;//  "<init>":()V
const #20 = Method	#18.#19;	//  java/lang/NullPointerException."<init>":()V
const #21 = NameAndType	#12:#13;//  $outer:Lscala/util/parsing/json/Lexer;
const #22 = Field	#9.#21;	//  scala/util/parsing/json/Lexer$$anonfun$expPart$3.$outer:Lscala/util/parsing/json/Lexer;
const #23 = Asciz	java/lang/Object;
const #24 = class	#23;	//  java/lang/Object
const #25 = Method	#24.#19;	//  java/lang/Object."<init>":()V
const #26 = Asciz	scala/Function1$class;
const #27 = class	#26;	//  scala/Function1$class
const #28 = Asciz	$init$;
const #29 = Asciz	(Lscala/Function1;)V;
const #30 = NameAndType	#28:#29;//  $init$:(Lscala/Function1;)V
const #31 = Method	#27.#30;	//  scala/Function1$class.$init$:(Lscala/Function1;)V
const #32 = Asciz	this;
const #33 = Asciz	Lscala/util/parsing/json/Lexer$$anonfun$expPart$3;;
const #34 = Asciz	LocalVariableTable;
const #35 = Asciz	apply;
const #36 = Asciz	(Ljava/lang/Object;)Ljava/lang/Object;;
const #37 = Asciz	scala/util/parsing/combinator/Parsers$$tilde;
const #38 = class	#37;	//  scala/util/parsing/combinator/Parsers$$tilde
const #39 = Asciz	(Lscala/util/parsing/combinator/Parsers$$tilde;)Ljava/lang/String;;
const #40 = NameAndType	#35:#39;//  apply:(Lscala/util/parsing/combinator/Parsers$$tilde;)Ljava/lang/String;
const #41 = Method	#9.#40;	//  scala/util/parsing/json/Lexer$$anonfun$expPart$3.apply:(Lscala/util/parsing/combinator/Parsers$$tilde;)Ljava/lang/String;
const #42 = Asciz	v1;
const #43 = Asciz	Ljava/lang/Object;;
const #44 = Asciz	_1;
const #45 = Asciz	()Ljava/lang/Object;;
const #46 = NameAndType	#44:#45;//  _1:()Ljava/lang/Object;
const #47 = Method	#38.#46;	//  scala/util/parsing/combinator/Parsers$$tilde._1:()Ljava/lang/Object;
const #48 = Asciz	_2;
const #49 = NameAndType	#48:#45;//  _2:()Ljava/lang/Object;
const #50 = Method	#38.#49;	//  scala/util/parsing/combinator/Parsers$$tilde._2:()Ljava/lang/Object;
const #51 = Asciz	scala/collection/immutable/List;
const #52 = class	#51;	//  scala/collection/immutable/List
const #53 = Asciz	scala/runtime/BoxesRunTime;
const #54 = class	#53;	//  scala/runtime/BoxesRunTime
const #55 = Asciz	unboxToChar;
const #56 = Asciz	(Ljava/lang/Object;)C;
const #57 = NameAndType	#55:#56;//  unboxToChar:(Ljava/lang/Object;)C
const #58 = Method	#54.#57;	//  scala/runtime/BoxesRunTime.unboxToChar:(Ljava/lang/Object;)C
const #59 = Asciz	scala/Option;
const #60 = class	#59;	//  scala/Option
const #61 = Asciz	scala/collection/mutable/StringBuilder;
const #62 = class	#61;	//  scala/collection/mutable/StringBuilder
const #63 = Method	#62.#19;	//  scala/collection/mutable/StringBuilder."<init>":()V
const #64 = Asciz	append;
const #65 = Asciz	(C)Lscala/collection/mutable/StringBuilder;;
const #66 = NameAndType	#64:#65;//  append:(C)Lscala/collection/mutable/StringBuilder;
const #67 = Method	#62.#66;	//  scala/collection/mutable/StringBuilder.append:(C)Lscala/collection/mutable/StringBuilder;
const #68 = Asciz	;
const #69 = String	#68;	//  
const #70 = Asciz	scala/util/parsing/json/Lexer;
const #71 = class	#70;	//  scala/util/parsing/json/Lexer
const #72 = Asciz	scala$util$parsing$json$Lexer$$optString;
const #73 = Asciz	(Ljava/lang/String;Lscala/Option;)Ljava/lang/String;;
const #74 = NameAndType	#72:#73;//  scala$util$parsing$json$Lexer$$optString:(Ljava/lang/String;Lscala/Option;)Ljava/lang/String;
const #75 = Method	#71.#74;	//  scala/util/parsing/json/Lexer.scala$util$parsing$json$Lexer$$optString:(Ljava/lang/String;Lscala/Option;)Ljava/lang/String;
const #76 = Asciz	(Ljava/lang/Object;)Lscala/collection/mutable/StringBuilder;;
const #77 = NameAndType	#64:#76;//  append:(Ljava/lang/Object;)Lscala/collection/mutable/StringBuilder;
const #78 = Method	#62.#77;	//  scala/collection/mutable/StringBuilder.append:(Ljava/lang/Object;)Lscala/collection/mutable/StringBuilder;
const #79 = Asciz	scala/collection/TraversableLike;
const #80 = class	#79;	//  scala/collection/TraversableLike
const #81 = Asciz	mkString;
const #82 = Asciz	(Ljava/lang/String;)Ljava/lang/String;;
const #83 = NameAndType	#81:#82;//  mkString:(Ljava/lang/String;)Ljava/lang/String;
const #84 = InterfaceMethod	#80.#83;	//  scala/collection/TraversableLike.mkString:(Ljava/lang/String;)Ljava/lang/String;
const #85 = Asciz	toString;
const #86 = Asciz	()Ljava/lang/String;;
const #87 = NameAndType	#85:#86;//  toString:()Ljava/lang/String;
const #88 = Method	#62.#87;	//  scala/collection/mutable/StringBuilder.toString:()Ljava/lang/String;
const #89 = Asciz	scala/MatchError;
const #90 = class	#89;	//  scala/MatchError
const #91 = Method	#38.#87;	//  scala/util/parsing/combinator/Parsers$$tilde.toString:()Ljava/lang/String;
const #92 = Asciz	(Ljava/lang/String;)V;
const #93 = NameAndType	#14:#92;//  "<init>":(Ljava/lang/String;)V
const #94 = Method	#90.#93;	//  scala/MatchError."<init>":(Ljava/lang/String;)V
const #95 = Asciz	temp21;
const #96 = Asciz	Lscala/util/parsing/combinator/Parsers$$tilde;;
const #97 = Asciz	temp23;
const #98 = Asciz	C;
const #99 = Asciz	temp24;
const #100 = Asciz	Lscala/Option;;
const #101 = Asciz	temp22;
const #102 = Asciz	Lscala/collection/immutable/List;;
const #103 = Asciz	(Lscala/util/parsing/combinator/Parsers$$tilde<Lscala/util/parsing/combinator/Parsers$$tilde<Ljava/lang/Character;Lscala/Option<Ljava/lang/Character;>;>;Lscala/collection/immutable/List<Ljava/lang/Character;>;>;)Ljava/lang/String;;
const #104 = Asciz	Signature;
const #105 = Asciz	andThen;
const #106 = Asciz	(Lscala/Function1;)Lscala/Function1;;
const #107 = Asciz	(Lscala/Function1;Lscala/Function1;)Lscala/Function1;;
const #108 = NameAndType	#105:#107;//  andThen:(Lscala/Function1;Lscala/Function1;)Lscala/Function1;
const #109 = Method	#27.#108;	//  scala/Function1$class.andThen:(Lscala/Function1;Lscala/Function1;)Lscala/Function1;
const #110 = Asciz	g;
const #111 = Asciz	Lscala/Function1;;
const #112 = Asciz	compose;
const #113 = NameAndType	#112:#107;//  compose:(Lscala/Function1;Lscala/Function1;)Lscala/Function1;
const #114 = Method	#27.#113;	//  scala/Function1$class.compose:(Lscala/Function1;Lscala/Function1;)Lscala/Function1;
const #115 = Asciz	(Lscala/Function1;)Ljava/lang/String;;
const #116 = NameAndType	#85:#115;//  toString:(Lscala/Function1;)Ljava/lang/String;
const #117 = Method	#27.#116;	//  scala/Function1$class.toString:(Lscala/Function1;)Ljava/lang/String;
const #118 = Asciz	Scala;
const #119 = Asciz	InnerClasses;
const #120 = Asciz	scala/util/parsing/combinator/Parsers;
const #121 = class	#120;	//  scala/util/parsing/combinator/Parsers
const #122 = Asciz	$tilde;
const #123 = Asciz	$anonfun$expPart$3;
const #124 = Asciz	scala/Function1;
const #125 = class	#124;	//  scala/Function1
const #126 = Asciz	scala/ScalaObject;
const #127 = class	#126;	//  scala/ScalaObject
const #128 = Asciz	java/io/Serializable;
const #129 = class	#128;	//  java/io/Serializable

{
public static final long serialVersionUID;

public static {};
  Code:
   Stack=2, Locals=0, Args_size=0
   0:	lconst_0
   1:	putstatic	#11; //Field serialVersionUID:J
   4:	return

public scala.util.parsing.json.Lexer$$anonfun$expPart$3(scala.util.parsing.json.Lexer);
  Code:
   Stack=2, Locals=2, Args_size=2
   0:	aload_1
   1:	ifnonnull	12
   4:	new	#18; //class java/lang/NullPointerException
   7:	dup
   8:	invokespecial	#20; //Method java/lang/NullPointerException."<init>":()V
   11:	athrow
   12:	aload_0
   13:	aload_1
   14:	putfield	#22; //Field $outer:Lscala/util/parsing/json/Lexer;
   17:	aload_0
   18:	invokespecial	#25; //Method java/lang/Object."<init>":()V
   21:	aload_0
   22:	invokestatic	#31; //Method scala/Function1$class.$init$:(Lscala/Function1;)V
   25:	return
  LineNumberTable: 
   line 56: 0

  LocalVariableTable: 
   Start  Length  Slot  Name   Signature
   0      26      0    this       Lscala/util/parsing/json/Lexer$$anonfun$expPart$3;
   0      26      1    $outer       Lscala/util/parsing/json/Lexer;


public final java.lang.Object apply(java.lang.Object);
  Code:
   Stack=2, Locals=3, Args_size=2
   0:	aload_0
   1:	getfield	#22; //Field $outer:Lscala/util/parsing/json/Lexer;
   4:	astore_2
   5:	aload_0
   6:	aload_1
   7:	checkcast	#38; //class scala/util/parsing/combinator/Parsers$$tilde
   10:	invokevirtual	#41; //Method apply:(Lscala/util/parsing/combinator/Parsers$$tilde;)Ljava/lang/String;
   13:	areturn
  LineNumberTable: 
   line 56: 0

  LocalVariableTable: 
   Start  Length  Slot  Name   Signature
   0      14      0    this       Lscala/util/parsing/json/Lexer$$anonfun$expPart$3;
   5      9      1    v1       Ljava/lang/Object;


public final java.lang.String apply(scala.util.parsing.combinator.Parsers$$tilde);
  Code:
   Stack=4, Locals=7, Args_size=2
   0:	aload_0
   1:	getfield	#22; //Field $outer:Lscala/util/parsing/json/Lexer;
   4:	astore	6
   6:	aload_1
   7:	ifnull	117
   10:	aload_1
   11:	invokevirtual	#47; //Method scala/util/parsing/combinator/Parsers$$tilde._1:()Ljava/lang/Object;
   14:	checkcast	#38; //class scala/util/parsing/combinator/Parsers$$tilde
   17:	astore_2
   18:	aload_1
   19:	invokevirtual	#50; //Method scala/util/parsing/combinator/Parsers$$tilde._2:()Ljava/lang/Object;
   22:	checkcast	#52; //class scala/collection/immutable/List
   25:	astore	5
   27:	aload_2
   28:	ifnull	105
   31:	aload_2
   32:	invokevirtual	#47; //Method scala/util/parsing/combinator/Parsers$$tilde._1:()Ljava/lang/Object;
   35:	invokestatic	#58; //Method scala/runtime/BoxesRunTime.unboxToChar:(Ljava/lang/Object;)C
   38:	istore_3
   39:	aload_2
   40:	invokevirtual	#50; //Method scala/util/parsing/combinator/Parsers$$tilde._2:()Ljava/lang/Object;
   43:	checkcast	#60; //class scala/Option
   46:	astore	4
   48:	iconst_1
   49:	ifeq	93
   52:	new	#62; //class scala/collection/mutable/StringBuilder
   55:	dup
   56:	invokespecial	#63; //Method scala/collection/mutable/StringBuilder."<init>":()V
   59:	iload_3
   60:	invokevirtual	#67; //Method scala/collection/mutable/StringBuilder.append:(C)Lscala/collection/mutable/StringBuilder;
   63:	aload_0
   64:	getfield	#22; //Field $outer:Lscala/util/parsing/json/Lexer;
   67:	ldc	#69; //String 
   69:	aload	4
   71:	invokevirtual	#75; //Method scala/util/parsing/json/Lexer.scala$util$parsing$json$Lexer$$optString:(Ljava/lang/String;Lscala/Option;)Ljava/lang/String;
   74:	invokevirtual	#78; //Method scala/collection/mutable/StringBuilder.append:(Ljava/lang/Object;)Lscala/collection/mutable/StringBuilder;
   77:	aload	5
   79:	ldc	#69; //String 
   81:	invokeinterface	#84,  2; //InterfaceMethod scala/collection/TraversableLike.mkString:(Ljava/lang/String;)Ljava/lang/String;
   86:	invokevirtual	#78; //Method scala/collection/mutable/StringBuilder.append:(Ljava/lang/Object;)Lscala/collection/mutable/StringBuilder;
   89:	invokevirtual	#88; //Method scala/collection/mutable/StringBuilder.toString:()Ljava/lang/String;
   92:	areturn
   93:	new	#90; //class scala/MatchError
   96:	dup
   97:	aload_1
   98:	invokevirtual	#91; //Method scala/util/parsing/combinator/Parsers$$tilde.toString:()Ljava/lang/String;
   101:	invokespecial	#94; //Method scala/MatchError."<init>":(Ljava/lang/String;)V
   104:	athrow
   105:	new	#90; //class scala/MatchError
   108:	dup
   109:	aload_1
   110:	invokevirtual	#91; //Method scala/util/parsing/combinator/Parsers$$tilde.toString:()Ljava/lang/String;
   113:	invokespecial	#94; //Method scala/MatchError."<init>":(Ljava/lang/String;)V
   116:	athrow
   117:	new	#90; //class scala/MatchError
   120:	dup
   121:	aload_1
   122:	invokevirtual	#91; //Method scala/util/parsing/combinator/Parsers$$tilde.toString:()Ljava/lang/String;
   125:	invokespecial	#94; //Method scala/MatchError."<init>":(Ljava/lang/String;)V
   128:	athrow
  LineNumberTable: 
   line 56: 0
   line 21: 48
   line 57: 52
   line 56: 92

  LocalVariableTable: 
   Start  Length  Slot  Name   Signature
   0      129      0    this       Lscala/util/parsing/json/Lexer$$anonfun$expPart$3;
   18      99      2    temp21       Lscala/util/parsing/combinator/Parsers$$tilde;
   39      66      3    temp23       C
   48      57      4    temp24       Lscala/Option;
   27      90      5    temp22       Lscala/collection/immutable/List;

  Signature: length = 0x2
   00 67 

public scala.Function1 andThen(scala.Function1);
  Code:
   Stack=2, Locals=2, Args_size=2
   0:	aload_0
   1:	aload_1
   2:	invokestatic	#109; //Method scala/Function1$class.andThen:(Lscala/Function1;Lscala/Function1;)Lscala/Function1;
   5:	areturn
  LineNumberTable: 
   line 56: 0

  LocalVariableTable: 
   Start  Length  Slot  Name   Signature
   0      6      0    this       Lscala/util/parsing/json/Lexer$$anonfun$expPart$3;
   0      6      1    g       Lscala/Function1;


public scala.Function1 compose(scala.Function1);
  Code:
   Stack=2, Locals=2, Args_size=2
   0:	aload_0
   1:	aload_1
   2:	invokestatic	#114; //Method scala/Function1$class.compose:(Lscala/Function1;Lscala/Function1;)Lscala/Function1;
   5:	areturn
  LineNumberTable: 
   line 56: 0

  LocalVariableTable: 
   Start  Length  Slot  Name   Signature
   0      6      0    this       Lscala/util/parsing/json/Lexer$$anonfun$expPart$3;
   0      6      1    g       Lscala/Function1;


public java.lang.String toString();
  Code:
   Stack=1, Locals=1, Args_size=1
   0:	aload_0
   1:	invokestatic	#117; //Method scala/Function1$class.toString:(Lscala/Function1;)Ljava/lang/String;
   4:	areturn
  LineNumberTable: 
   line 56: 0


}

