Compiled from "Lexer.scala"
public final class scala.util.parsing.json.Lexer$$anonfun$scala$util$parsing$json$Lexer$$unicodeBlock$4 extends java.lang.Object implements scala.Function1,scala.ScalaObject,java.io.Serializable
  SourceFile: "Lexer.scala"
  Scala: length = 0x
   
  InnerClass: 
   public #157= #33 of #156; //$tilde=class scala/util/parsing/combinator/Parsers$$tilde of class scala/util/parsing/combinator/Parsers
   public final #160= #105 of #159; //$anonfun$apply$6=class scala/Array$$anonfun$apply$6 of class scala/Array
   public final #163= #9 of #162; //$anonfun$scala$util$parsing$json$Lexer$$unicodeBlock$4=class scala/util/parsing/json/Lexer$$anonfun$scala$util$parsing$json$Lexer$$unicodeBlock$4 of class scala/util/parsing/json/Lexer
  minor version: 0
  major version: 49
  Constant pool:
const #1 = Asciz	SourceFile;
const #2 = Asciz	Lexer.scala;
const #3 = Asciz	<clinit>;
const #4 = Asciz	()V;
const #5 = Asciz	Code;
const #6 = Asciz	serialVersionUID;
const #7 = Asciz	J;
const #8 = Asciz	scala/util/parsing/json/Lexer$$anonfun$scala$util$parsing$json$Lexer$$unicodeBlock$4;
const #9 = class	#8;	//  scala/util/parsing/json/Lexer$$anonfun$scala$util$parsing$json$Lexer$$unicodeBlock$4
const #10 = NameAndType	#6:#7;//  serialVersionUID:J
const #11 = Field	#9.#10;	//  scala/util/parsing/json/Lexer$$anonfun$scala$util$parsing$json$Lexer$$unicodeBlock$4.serialVersionUID:J
const #12 = Asciz	<init>;
const #13 = Asciz	(Lscala/util/parsing/json/Lexer;)V;
const #14 = Asciz	LineNumberTable;
const #15 = Asciz	java/lang/Object;
const #16 = class	#15;	//  java/lang/Object
const #17 = NameAndType	#12:#4;//  "<init>":()V
const #18 = Method	#16.#17;	//  java/lang/Object."<init>":()V
const #19 = Asciz	scala/Function1$class;
const #20 = class	#19;	//  scala/Function1$class
const #21 = Asciz	$init$;
const #22 = Asciz	(Lscala/Function1;)V;
const #23 = NameAndType	#21:#22;//  $init$:(Lscala/Function1;)V
const #24 = Method	#20.#23;	//  scala/Function1$class.$init$:(Lscala/Function1;)V
const #25 = Asciz	this;
const #26 = Asciz	Lscala/util/parsing/json/Lexer$$anonfun$scala$util$parsing$json$Lexer$$unicodeBlock$4;;
const #27 = Asciz	$outer;
const #28 = Asciz	Lscala/util/parsing/json/Lexer;;
const #29 = Asciz	LocalVariableTable;
const #30 = Asciz	apply;
const #31 = Asciz	(Ljava/lang/Object;)Ljava/lang/Object;;
const #32 = Asciz	scala/util/parsing/combinator/Parsers$$tilde;
const #33 = class	#32;	//  scala/util/parsing/combinator/Parsers$$tilde
const #34 = Asciz	(Lscala/util/parsing/combinator/Parsers$$tilde;)Ljava/lang/String;;
const #35 = NameAndType	#30:#34;//  apply:(Lscala/util/parsing/combinator/Parsers$$tilde;)Ljava/lang/String;
const #36 = Method	#9.#35;	//  scala/util/parsing/json/Lexer$$anonfun$scala$util$parsing$json$Lexer$$unicodeBlock$4.apply:(Lscala/util/parsing/combinator/Parsers$$tilde;)Ljava/lang/String;
const #37 = Asciz	v1;
const #38 = Asciz	Ljava/lang/Object;;
const #39 = Asciz	_1;
const #40 = Asciz	()Ljava/lang/Object;;
const #41 = NameAndType	#39:#40;//  _1:()Ljava/lang/Object;
const #42 = Method	#33.#41;	//  scala/util/parsing/combinator/Parsers$$tilde._1:()Ljava/lang/Object;
const #43 = Asciz	_2;
const #44 = NameAndType	#43:#40;//  _2:()Ljava/lang/Object;
const #45 = Method	#33.#44;	//  scala/util/parsing/combinator/Parsers$$tilde._2:()Ljava/lang/Object;
const #46 = Asciz	scala/runtime/BoxesRunTime;
const #47 = class	#46;	//  scala/runtime/BoxesRunTime
const #48 = Asciz	unboxToChar;
const #49 = Asciz	(Ljava/lang/Object;)C;
const #50 = NameAndType	#48:#49;//  unboxToChar:(Ljava/lang/Object;)C
const #51 = Method	#47.#50;	//  scala/runtime/BoxesRunTime.unboxToChar:(Ljava/lang/Object;)C
const #52 = Asciz	java/lang/String;
const #53 = class	#52;	//  java/lang/String
const #54 = Asciz	scala/Predef$;
const #55 = class	#54;	//  scala/Predef$
const #56 = Asciz	MODULE$;
const #57 = Asciz	Lscala/Predef$;;
const #58 = NameAndType	#56:#57;//  MODULE$:Lscala/Predef$;
const #59 = Field	#55.#58;	//  scala/Predef$.MODULE$:Lscala/Predef$;
const #60 = Asciz	wrapCharArray;
const #61 = Asciz	([C)Lscala/collection/mutable/WrappedArray;;
const #62 = NameAndType	#60:#61;//  wrapCharArray:([C)Lscala/collection/mutable/WrappedArray;
const #63 = Method	#55.#62;	//  scala/Predef$.wrapCharArray:([C)Lscala/collection/mutable/WrappedArray;
const #64 = Asciz	scala/collection/TraversableLike;
const #65 = class	#64;	//  scala/collection/TraversableLike
const #66 = Asciz	toList;
const #67 = Asciz	()Lscala/collection/immutable/List;;
const #68 = NameAndType	#66:#67;//  toList:()Lscala/collection/immutable/List;
const #69 = InterfaceMethod	#65.#68;	//  scala/collection/TraversableLike.toList:()Lscala/collection/immutable/List;
const #70 = Asciz	;
const #71 = String	#70;	//  
const #72 = Asciz	mkString;
const #73 = Asciz	(Ljava/lang/String;)Ljava/lang/String;;
const #74 = NameAndType	#72:#73;//  mkString:(Ljava/lang/String;)Ljava/lang/String;
const #75 = InterfaceMethod	#65.#74;	//  scala/collection/TraversableLike.mkString:(Ljava/lang/String;)Ljava/lang/String;
const #76 = int	16;
const #77 = Asciz	java/lang/Integer;
const #78 = class	#77;	//  java/lang/Integer
const #79 = Asciz	parseInt;
const #80 = Asciz	(Ljava/lang/String;I)I;
const #81 = NameAndType	#79:#80;//  parseInt:(Ljava/lang/String;I)I
const #82 = Method	#78.#81;	//  java/lang/Integer.parseInt:(Ljava/lang/String;I)I
const #83 = Asciz	wrapIntArray;
const #84 = Asciz	([I)Lscala/collection/mutable/WrappedArray;;
const #85 = NameAndType	#83:#84;//  wrapIntArray:([I)Lscala/collection/mutable/WrappedArray;
const #86 = Method	#55.#85;	//  scala/Predef$.wrapIntArray:([I)Lscala/collection/mutable/WrappedArray;
const #87 = Asciz	scala/collection/SeqLike;
const #88 = class	#87;	//  scala/collection/SeqLike
const #89 = Asciz	length;
const #90 = Asciz	()I;
const #91 = NameAndType	#89:#90;//  length:()I
const #92 = InterfaceMethod	#88.#91;	//  scala/collection/SeqLike.length:()I
const #93 = Asciz	scala/runtime/IntRef;
const #94 = class	#93;	//  scala/runtime/IntRef
const #95 = Asciz	(I)V;
const #96 = NameAndType	#12:#95;//  "<init>":(I)V
const #97 = Method	#94.#96;	//  scala/runtime/IntRef."<init>":(I)V
const #98 = Asciz	scala/collection/IterableLike;
const #99 = class	#98;	//  scala/collection/IterableLike
const #100 = Asciz	iterator;
const #101 = Asciz	()Lscala/collection/Iterator;;
const #102 = NameAndType	#100:#101;//  iterator:()Lscala/collection/Iterator;
const #103 = InterfaceMethod	#99.#102;	//  scala/collection/IterableLike.iterator:()Lscala/collection/Iterator;
const #104 = Asciz	scala/Array$$anonfun$apply$6;
const #105 = class	#104;	//  scala/Array$$anonfun$apply$6
const #106 = Asciz	([ILscala/runtime/IntRef;)V;
const #107 = NameAndType	#12:#106;//  "<init>":([ILscala/runtime/IntRef;)V
const #108 = Method	#105.#107;	//  scala/Array$$anonfun$apply$6."<init>":([ILscala/runtime/IntRef;)V
const #109 = Asciz	scala/collection/Iterator;
const #110 = class	#109;	//  scala/collection/Iterator
const #111 = Asciz	foreach;
const #112 = NameAndType	#111:#22;//  foreach:(Lscala/Function1;)V
const #113 = InterfaceMethod	#110.#112;	//  scala/collection/Iterator.foreach:(Lscala/Function1;)V
const #114 = Asciz	([III)V;
const #115 = NameAndType	#12:#114;//  "<init>":([III)V
const #116 = Method	#53.#115;	//  java/lang/String."<init>":([III)V
const #117 = Asciz	scala/MatchError;
const #118 = class	#117;	//  scala/MatchError
const #119 = Asciz	toString;
const #120 = Asciz	()Ljava/lang/String;;
const #121 = NameAndType	#119:#120;//  toString:()Ljava/lang/String;
const #122 = Method	#33.#121;	//  scala/util/parsing/combinator/Parsers$$tilde.toString:()Ljava/lang/String;
const #123 = Asciz	(Ljava/lang/String;)V;
const #124 = NameAndType	#12:#123;//  "<init>":(Ljava/lang/String;)V
const #125 = Method	#118.#124;	//  scala/MatchError."<init>":(Ljava/lang/String;)V
const #126 = Asciz	temp30;
const #127 = Asciz	Lscala/util/parsing/combinator/Parsers$$tilde;;
const #128 = Asciz	temp32;
const #129 = Asciz	temp34;
const #130 = Asciz	C;
const #131 = Asciz	temp35;
const #132 = Asciz	temp33;
const #133 = Asciz	temp31;
const #134 = Asciz	i$60;
const #135 = Asciz	Lscala/runtime/IntRef;;
const #136 = Asciz	array$60;
const #137 = Asciz	[I;
const #138 = Asciz	(Lscala/util/parsing/combinator/Parsers$$tilde<Lscala/util/parsing/combinator/Parsers$$tilde<Lscala/util/parsing/combinator/Parsers$$tilde<Ljava/lang/Character;Ljava/lang/Character;>;Ljava/lang/Character;>;Ljava/lang/Character;>;)Ljava/lang/String;;
const #139 = Asciz	Signature;
const #140 = Asciz	andThen;
const #141 = Asciz	(Lscala/Function1;)Lscala/Function1;;
const #142 = Asciz	(Lscala/Function1;Lscala/Function1;)Lscala/Function1;;
const #143 = NameAndType	#140:#142;//  andThen:(Lscala/Function1;Lscala/Function1;)Lscala/Function1;
const #144 = Method	#20.#143;	//  scala/Function1$class.andThen:(Lscala/Function1;Lscala/Function1;)Lscala/Function1;
const #145 = Asciz	g;
const #146 = Asciz	Lscala/Function1;;
const #147 = Asciz	compose;
const #148 = NameAndType	#147:#142;//  compose:(Lscala/Function1;Lscala/Function1;)Lscala/Function1;
const #149 = Method	#20.#148;	//  scala/Function1$class.compose:(Lscala/Function1;Lscala/Function1;)Lscala/Function1;
const #150 = Asciz	(Lscala/Function1;)Ljava/lang/String;;
const #151 = NameAndType	#119:#150;//  toString:(Lscala/Function1;)Ljava/lang/String;
const #152 = Method	#20.#151;	//  scala/Function1$class.toString:(Lscala/Function1;)Ljava/lang/String;
const #153 = Asciz	Scala;
const #154 = Asciz	InnerClasses;
const #155 = Asciz	scala/util/parsing/combinator/Parsers;
const #156 = class	#155;	//  scala/util/parsing/combinator/Parsers
const #157 = Asciz	$tilde;
const #158 = Asciz	scala/Array;
const #159 = class	#158;	//  scala/Array
const #160 = Asciz	$anonfun$apply$6;
const #161 = Asciz	scala/util/parsing/json/Lexer;
const #162 = class	#161;	//  scala/util/parsing/json/Lexer
const #163 = Asciz	$anonfun$scala$util$parsing$json$Lexer$$unicodeBlock$4;
const #164 = Asciz	scala/Function1;
const #165 = class	#164;	//  scala/Function1
const #166 = Asciz	scala/ScalaObject;
const #167 = class	#166;	//  scala/ScalaObject
const #168 = Asciz	java/io/Serializable;
const #169 = class	#168;	//  java/io/Serializable

{
public static final long serialVersionUID;

public static {};
  Code:
   Stack=2, Locals=0, Args_size=0
   0:	lconst_0
   1:	putstatic	#11; //Field serialVersionUID:J
   4:	return

public scala.util.parsing.json.Lexer$$anonfun$scala$util$parsing$json$Lexer$$unicodeBlock$4(scala.util.parsing.json.Lexer);
  Code:
   Stack=1, Locals=2, Args_size=2
   0:	aload_0
   1:	invokespecial	#18; //Method java/lang/Object."<init>":()V
   4:	aload_0
   5:	invokestatic	#24; //Method scala/Function1$class.$init$:(Lscala/Function1;)V
   8:	return
  LineNumberTable: 
   line 84: 0

  LocalVariableTable: 
   Start  Length  Slot  Name   Signature
   0      9      0    this       Lscala/util/parsing/json/Lexer$$anonfun$scala$util$parsing$json$Lexer$$unicodeBlock$4;
   0      9      1    $outer       Lscala/util/parsing/json/Lexer;


public final java.lang.Object apply(java.lang.Object);
  Code:
   Stack=2, Locals=2, Args_size=2
   0:	aload_0
   1:	aload_1
   2:	checkcast	#33; //class scala/util/parsing/combinator/Parsers$$tilde
   5:	invokevirtual	#36; //Method apply:(Lscala/util/parsing/combinator/Parsers$$tilde;)Ljava/lang/String;
   8:	areturn
  LineNumberTable: 
   line 84: 0

  LocalVariableTable: 
   Start  Length  Slot  Name   Signature
   0      9      0    this       Lscala/util/parsing/json/Lexer$$anonfun$scala$util$parsing$json$Lexer$$unicodeBlock$4;
   0      9      1    v1       Ljava/lang/Object;


public final java.lang.String apply(scala.util.parsing.combinator.Parsers$$tilde);
  Code:
   Stack=7, Locals=13, Args_size=2
   0:	aload_1
   1:	ifnull	231
   4:	aload_1
   5:	invokevirtual	#42; //Method scala/util/parsing/combinator/Parsers$$tilde._1:()Ljava/lang/Object;
   8:	checkcast	#33; //class scala/util/parsing/combinator/Parsers$$tilde
   11:	astore_2
   12:	aload_1
   13:	invokevirtual	#45; //Method scala/util/parsing/combinator/Parsers$$tilde._2:()Ljava/lang/Object;
   16:	invokestatic	#51; //Method scala/runtime/BoxesRunTime.unboxToChar:(Ljava/lang/Object;)C
   19:	istore	7
   21:	aload_2
   22:	ifnull	219
   25:	aload_2
   26:	invokevirtual	#42; //Method scala/util/parsing/combinator/Parsers$$tilde._1:()Ljava/lang/Object;
   29:	checkcast	#33; //class scala/util/parsing/combinator/Parsers$$tilde
   32:	astore_3
   33:	aload_2
   34:	invokevirtual	#45; //Method scala/util/parsing/combinator/Parsers$$tilde._2:()Ljava/lang/Object;
   37:	invokestatic	#51; //Method scala/runtime/BoxesRunTime.unboxToChar:(Ljava/lang/Object;)C
   40:	istore	6
   42:	aload_3
   43:	ifnull	207
   46:	aload_3
   47:	invokevirtual	#42; //Method scala/util/parsing/combinator/Parsers$$tilde._1:()Ljava/lang/Object;
   50:	invokestatic	#51; //Method scala/runtime/BoxesRunTime.unboxToChar:(Ljava/lang/Object;)C
   53:	istore	4
   55:	aload_3
   56:	invokevirtual	#45; //Method scala/util/parsing/combinator/Parsers$$tilde._2:()Ljava/lang/Object;
   59:	invokestatic	#51; //Method scala/runtime/BoxesRunTime.unboxToChar:(Ljava/lang/Object;)C
   62:	istore	5
   64:	iconst_1
   65:	ifeq	195
   68:	new	#53; //class java/lang/String
   71:	dup
   72:	getstatic	#59; //Field scala/Predef$.MODULE$:Lscala/Predef$;
   75:	iconst_4
   76:	newarray char
   78:	dup
   79:	iconst_0
   80:	iload	4
   82:	castore
   83:	dup
   84:	iconst_1
   85:	iload	5
   87:	castore
   88:	dup
   89:	iconst_2
   90:	iload	6
   92:	castore
   93:	dup
   94:	iconst_3
   95:	iload	7
   97:	castore
   98:	invokevirtual	#63; //Method scala/Predef$.wrapCharArray:([C)Lscala/collection/mutable/WrappedArray;
   101:	astore	8
   103:	aload	8
   105:	invokeinterface	#69,  1; //InterfaceMethod scala/collection/TraversableLike.toList:()Lscala/collection/immutable/List;
   110:	ldc	#71; //String 
   112:	invokeinterface	#75,  2; //InterfaceMethod scala/collection/TraversableLike.mkString:(Ljava/lang/String;)Ljava/lang/String;
   117:	ldc	#76; //int 16
   119:	invokestatic	#82; //Method java/lang/Integer.parseInt:(Ljava/lang/String;I)I
   122:	getstatic	#59; //Field scala/Predef$.MODULE$:Lscala/Predef$;
   125:	iconst_0
   126:	newarray int
   128:	invokevirtual	#86; //Method scala/Predef$.wrapIntArray:([I)Lscala/collection/mutable/WrappedArray;
   131:	astore	10
   133:	istore	9
   135:	aload	10
   137:	invokeinterface	#92,  1; //InterfaceMethod scala/collection/SeqLike.length:()I
   142:	iconst_1
   143:	iadd
   144:	newarray int
   146:	astore	12
   148:	aload	12
   150:	iconst_0
   151:	iload	9
   153:	iastore
   154:	new	#94; //class scala/runtime/IntRef
   157:	dup
   158:	iconst_1
   159:	invokespecial	#97; //Method scala/runtime/IntRef."<init>":(I)V
   162:	astore	11
   164:	aload	10
   166:	invokeinterface	#103,  1; //InterfaceMethod scala/collection/IterableLike.iterator:()Lscala/collection/Iterator;
   171:	new	#105; //class scala/Array$$anonfun$apply$6
   174:	dup
   175:	aload	12
   177:	aload	11
   179:	invokespecial	#108; //Method scala/Array$$anonfun$apply$6."<init>":([ILscala/runtime/IntRef;)V
   182:	invokeinterface	#113,  2; //InterfaceMethod scala/collection/Iterator.foreach:(Lscala/Function1;)V
   187:	aload	12
   189:	iconst_0
   190:	iconst_1
   191:	invokespecial	#116; //Method java/lang/String."<init>":([III)V
   194:	areturn
   195:	new	#118; //class scala/MatchError
   198:	dup
   199:	aload_1
   200:	invokevirtual	#122; //Method scala/util/parsing/combinator/Parsers$$tilde.toString:()Ljava/lang/String;
   203:	invokespecial	#125; //Method scala/MatchError."<init>":(Ljava/lang/String;)V
   206:	athrow
   207:	new	#118; //class scala/MatchError
   210:	dup
   211:	aload_1
   212:	invokevirtual	#122; //Method scala/util/parsing/combinator/Parsers$$tilde.toString:()Ljava/lang/String;
   215:	invokespecial	#125; //Method scala/MatchError."<init>":(Ljava/lang/String;)V
   218:	athrow
   219:	new	#118; //class scala/MatchError
   222:	dup
   223:	aload_1
   224:	invokevirtual	#122; //Method scala/util/parsing/combinator/Parsers$$tilde.toString:()Ljava/lang/String;
   227:	invokespecial	#125; //Method scala/MatchError."<init>":(Ljava/lang/String;)V
   230:	athrow
   231:	new	#118; //class scala/MatchError
   234:	dup
   235:	aload_1
   236:	invokevirtual	#122; //Method scala/util/parsing/combinator/Parsers$$tilde.toString:()Ljava/lang/String;
   239:	invokespecial	#125; //Method scala/MatchError."<init>":(Ljava/lang/String;)V
   242:	athrow
  LineNumberTable: 
   line 84: 0
   line 21: 64
   line 86: 68
   line 84: 194

  LocalVariableTable: 
   Start  Length  Slot  Name   Signature
   0      243      0    this       Lscala/util/parsing/json/Lexer$$anonfun$scala$util$parsing$json$Lexer$$unicodeBlock$4;
   12      219      2    temp30       Lscala/util/parsing/combinator/Parsers$$tilde;
   33      186      3    temp32       Lscala/util/parsing/combinator/Parsers$$tilde;
   55      152      4    temp34       C
   64      143      5    temp35       C
   42      177      6    temp33       C
   21      210      7    temp31       C
   164      25      11    i$60       Lscala/runtime/IntRef;
   148      41      12    array$60       [I

  Signature: length = 0x2
   00 FFFFFF8A 

public scala.Function1 andThen(scala.Function1);
  Code:
   Stack=2, Locals=2, Args_size=2
   0:	aload_0
   1:	aload_1
   2:	invokestatic	#144; //Method scala/Function1$class.andThen:(Lscala/Function1;Lscala/Function1;)Lscala/Function1;
   5:	areturn
  LineNumberTable: 
   line 84: 0

  LocalVariableTable: 
   Start  Length  Slot  Name   Signature
   0      6      0    this       Lscala/util/parsing/json/Lexer$$anonfun$scala$util$parsing$json$Lexer$$unicodeBlock$4;
   0      6      1    g       Lscala/Function1;


public scala.Function1 compose(scala.Function1);
  Code:
   Stack=2, Locals=2, Args_size=2
   0:	aload_0
   1:	aload_1
   2:	invokestatic	#149; //Method scala/Function1$class.compose:(Lscala/Function1;Lscala/Function1;)Lscala/Function1;
   5:	areturn
  LineNumberTable: 
   line 84: 0

  LocalVariableTable: 
   Start  Length  Slot  Name   Signature
   0      6      0    this       Lscala/util/parsing/json/Lexer$$anonfun$scala$util$parsing$json$Lexer$$unicodeBlock$4;
   0      6      1    g       Lscala/Function1;


public java.lang.String toString();
  Code:
   Stack=1, Locals=1, Args_size=1
   0:	aload_0
   1:	invokestatic	#152; //Method scala/Function1$class.toString:(Lscala/Function1;)Ljava/lang/String;
   4:	areturn
  LineNumberTable: 
   line 84: 0


}

