Compiled from "Lexer.scala"
public final class scala.util.parsing.json.Lexer$$anonfun$token$2$$anonfun$apply$6 extends scala.runtime.AbstractFunction1 implements java.io.Serializable
  SourceFile: "Lexer.scala"
  Scala: length = 0x
   
  InnerClass: 
   public $tilde=class scala/util/parsing/combinator/Parsers$$tilde of class scala/util/parsing/combinator/Parsers
   public ErrorToken=class scala/util/parsing/combinator/token/Tokens$ErrorToken of class scala/util/parsing/combinator/token/Tokens
   public final $anonfun$token$2=class scala/util/parsing/json/Lexer$$anonfun$token$2 of class scala/util/parsing/json/Lexer
   public final $anonfun$apply$6=class scala/util/parsing/json/Lexer$$anonfun$token$2$$anonfun$apply$6 of class scala/util/parsing/json/Lexer$$anonfun$token$2
  minor version: 0
  major version: 49
  Constant pool:
Asciz	SourceFile;
Asciz	Lexer.scala;
Asciz	<clinit>;
Asciz	()V;
Asciz	Code;
Asciz	serialVersionUID;
Asciz	J;
Asciz	scala/util/parsing/json/Lexer$$anonfun$token$2$$anonfun$apply$6;
class	scala/util/parsing/json/Lexer$$anonfun$token$2$$anonfun$apply$6
NameAndType	serialVersionUID:J
Field	scala/util/parsing/json/Lexer$$anonfun$token$2$$anonfun$apply$6.serialVersionUID:J
Asciz	$outer;
Asciz	Lscala/util/parsing/json/Lexer$$anonfun$token$2;;
Asciz	apply;
Asciz	(Lscala/util/parsing/combinator/Parsers$$tilde;)Lscala/util/parsing/combinator/token/Tokens$ErrorToken;;
Asciz	LineNumberTable;
Asciz	scala/util/parsing/combinator/Parsers$$tilde;
class	scala/util/parsing/combinator/Parsers$$tilde
Asciz	_1;
Asciz	()Ljava/lang/Object;;
NameAndType	_1:()Ljava/lang/Object;
Method	scala/util/parsing/combinator/Parsers$$tilde._1:()Ljava/lang/Object;
Asciz	_2;
NameAndType	_2:()Ljava/lang/Object;
Method	scala/util/parsing/combinator/Parsers$$tilde._2:()Ljava/lang/Object;
Asciz	scala/runtime/BoxesRunTime;
class	scala/runtime/BoxesRunTime
Asciz	unboxToChar;
Asciz	(Ljava/lang/Object;)C;
NameAndType	unboxToChar:(Ljava/lang/Object;)C
Method	scala/runtime/BoxesRunTime.unboxToChar:(Ljava/lang/Object;)C
Asciz	scala/util/parsing/combinator/token/Tokens$ErrorToken;
class	scala/util/parsing/combinator/token/Tokens$ErrorToken
NameAndType	$outer:Lscala/util/parsing/json/Lexer$$anonfun$token$2;
Field	scala/util/parsing/json/Lexer$$anonfun$token$2$$anonfun$apply$6.$outer:Lscala/util/parsing/json/Lexer$$anonfun$token$2;
Asciz	scala/util/parsing/json/Lexer$$anonfun$token$2;
class	scala/util/parsing/json/Lexer$$anonfun$token$2
Asciz	scala$util$parsing$json$Lexer$$anonfun$$$outer;
Asciz	()Lscala/util/parsing/json/Lexer;;
NameAndType	scala$util$parsing$json$Lexer$$anonfun$$$outer:()Lscala/util/parsing/json/Lexer;
Method	scala/util/parsing/json/Lexer$$anonfun$token$2.scala$util$parsing$json$Lexer$$anonfun$$$outer:()Lscala/util/parsing/json/Lexer;
Asciz	scala/collection/mutable/StringBuilder;
class	scala/collection/mutable/StringBuilder
Asciz	<init>;
NameAndType	"<init>":()V
Method	scala/collection/mutable/StringBuilder."<init>":()V
Asciz	Invalid number format : -;
String	Invalid number format : -
Asciz	append;
Asciz	(Ljava/lang/Object;)Lscala/collection/mutable/StringBuilder;;
NameAndType	append:(Ljava/lang/Object;)Lscala/collection/mutable/StringBuilder;
Method	scala/collection/mutable/StringBuilder.append:(Ljava/lang/Object;)Lscala/collection/mutable/StringBuilder;
Asciz	boxToCharacter;
Asciz	(C)Ljava/lang/Character;;
NameAndType	boxToCharacter:(C)Ljava/lang/Character;
Method	scala/runtime/BoxesRunTime.boxToCharacter:(C)Ljava/lang/Character;
Asciz	toString;
Asciz	()Ljava/lang/String;;
NameAndType	toString:()Ljava/lang/String;
Method	scala/collection/mutable/StringBuilder.toString:()Ljava/lang/String;
Asciz	(Lscala/util/parsing/combinator/token/Tokens;Ljava/lang/String;)V;
NameAndType	"<init>":(Lscala/util/parsing/combinator/token/Tokens;Ljava/lang/String;)V
Method	scala/util/parsing/combinator/token/Tokens$ErrorToken."<init>":(Lscala/util/parsing/combinator/token/Tokens;Ljava/lang/String;)V
Asciz	scala/MatchError;
class	scala/MatchError
Asciz	(Ljava/lang/Object;)V;
NameAndType	"<init>":(Ljava/lang/Object;)V
Method	scala/MatchError."<init>":(Ljava/lang/Object;)V
Asciz	this;
Asciz	Lscala/util/parsing/json/Lexer$$anonfun$token$2$$anonfun$apply$6;;
Asciz	temp4;
Asciz	Lscala/util/parsing/combinator/Parsers$$tilde;;
Asciz	temp5;
Asciz	temp6;
Asciz	C;
Asciz	LocalVariableTable;
Asciz	(Lscala/util/parsing/combinator/Parsers$$tilde<Lscala/util/parsing/combinator/Parsers$$tilde<Lscala/collection/immutable/List<Ljava/lang/Character;>;Ljava/lang/String;>;Ljava/lang/Character;>;)Lscala/util/parsing/combinator/token/Tokens$ErrorToken;;
Asciz	Signature;
Asciz	(Ljava/lang/Object;)Ljava/lang/Object;;
NameAndType	apply:(Lscala/util/parsing/combinator/Parsers$$tilde;)Lscala/util/parsing/combinator/token/Tokens$ErrorToken;
Method	scala/util/parsing/json/Lexer$$anonfun$token$2$$anonfun$apply$6.apply:(Lscala/util/parsing/combinator/Parsers$$tilde;)Lscala/util/parsing/combinator/token/Tokens$ErrorToken;
Asciz	v1;
Asciz	Ljava/lang/Object;;
Asciz	(Lscala/util/parsing/json/Lexer$$anonfun$token$2;)V;
Asciz	java/lang/NullPointerException;
class	java/lang/NullPointerException
Method	java/lang/NullPointerException."<init>":()V
Asciz	scala/runtime/AbstractFunction1;
class	scala/runtime/AbstractFunction1
Method	scala/runtime/AbstractFunction1."<init>":()V
Asciz	Scala;
Asciz	InnerClasses;
Asciz	scala/util/parsing/combinator/Parsers;
class	scala/util/parsing/combinator/Parsers
Asciz	$tilde;
Asciz	scala/util/parsing/combinator/token/Tokens;
class	scala/util/parsing/combinator/token/Tokens
Asciz	ErrorToken;
Asciz	scala/util/parsing/json/Lexer;
class	scala/util/parsing/json/Lexer
Asciz	$anonfun$token$2;
Asciz	$anonfun$apply$6;
Asciz	java/io/Serializable;
class	java/io/Serializable

{
public static final long serialVersionUID;
  Signature: J

private final scala.util.parsing.json.Lexer$$anonfun$token$2 $outer;
  Signature: Lscala/util/parsing/json/Lexer$$anonfun$token$2;

public static {};
  Signature: ()V
  Code:
   Stack=2, Locals=0, Args_size=0
	lconst_0
	putstatic	Field serialVersionUID:J
	return
  Labels:

public final scala.util.parsing.combinator.token.Tokens$ErrorToken apply(scala.util.parsing.combinator.Parsers$$tilde);
  Signature: (Lscala/util/parsing/combinator/Parsers$$tilde;)Lscala/util/parsing/combinator/token/Tokens$ErrorToken;
  Code:
   Stack=5, Locals=5, Args_size=2
	aload_1
	astore_2
	aload_2
	ifnull	l1 // new
	aload_2
	invokevirtual	Method scala/util/parsing/combinator/Parsers$$tilde._1:()Ljava/lang/Object;
	checkcast	class scala/util/parsing/combinator/Parsers$$tilde
	astore_3
	aload_2
	invokevirtual	Method scala/util/parsing/combinator/Parsers$$tilde._2:()Ljava/lang/Object;
	invokestatic	Method scala/runtime/BoxesRunTime.unboxToChar:(Ljava/lang/Object;)C
	istore	4
	aload_3
	ifnull	l2 // new
	new	class scala/util/parsing/combinator/token/Tokens$ErrorToken
	dup
	aload_0
	getfield	Field $outer:Lscala/util/parsing/json/Lexer$$anonfun$token$2;
	invokevirtual	Method scala/util/parsing/json/Lexer$$anonfun$token$2.scala$util$parsing$json$Lexer$$anonfun$$$outer:()Lscala/util/parsing/json/Lexer;
	new	class scala/collection/mutable/StringBuilder
	dup
	invokespecial	Method scala/collection/mutable/StringBuilder."<init>":()V
	ldc	String Invalid number format : -
	invokevirtual	Method scala/collection/mutable/StringBuilder.append:(Ljava/lang/Object;)Lscala/collection/mutable/StringBuilder;
	aload_3
	invokevirtual	Method scala/util/parsing/combinator/Parsers$$tilde._2:()Ljava/lang/Object;
	invokevirtual	Method scala/collection/mutable/StringBuilder.append:(Ljava/lang/Object;)Lscala/collection/mutable/StringBuilder;
	iload	4
	invokestatic	Method scala/runtime/BoxesRunTime.boxToCharacter:(C)Ljava/lang/Character;
	invokevirtual	Method scala/collection/mutable/StringBuilder.append:(Ljava/lang/Object;)Lscala/collection/mutable/StringBuilder;
	invokevirtual	Method scala/collection/mutable/StringBuilder.toString:()Ljava/lang/String;
	invokespecial	Method scala/util/parsing/combinator/token/Tokens$ErrorToken."<init>":(Lscala/util/parsing/combinator/token/Tokens;Ljava/lang/String;)V
	areturn
l2	new	class scala/MatchError
	dup
	aload_2
	invokespecial	Method scala/MatchError."<init>":(Ljava/lang/Object;)V
	athrow
l1	new	class scala/MatchError
	dup
	aload_2
	invokespecial	Method scala/MatchError."<init>":(Ljava/lang/Object;)V
	athrow
  Labels:
   	l2 = 72 // new
   	l1 = 81 // new
  LocalVariableTable: 
   Start  Length  Slot  Name   Signature
   0      90      0    this       Lscala/util/parsing/json/Lexer$$anonfun$token$2$$anonfun$apply$6;
   2      88      2    temp4       Lscala/util/parsing/combinator/Parsers$$tilde;
   14      57      3    temp5       Lscala/util/parsing/combinator/Parsers$$tilde;
   72      9      3    temp5       Lscala/util/parsing/combinator/Parsers$$tilde;
   23      48      4    temp6       C
   72      9      4    temp6       C

  Signature: length = 0x2
   00 4D 

public final java.lang.Object apply(java.lang.Object);
  Signature: (Ljava/lang/Object;)Ljava/lang/Object;
  Code:
   Stack=2, Locals=2, Args_size=2
	aload_0
	aload_1
	checkcast	class scala/util/parsing/combinator/Parsers$$tilde
	invokevirtual	Method apply:(Lscala/util/parsing/combinator/Parsers$$tilde;)Lscala/util/parsing/combinator/token/Tokens$ErrorToken;
	areturn
  Labels:
  LocalVariableTable: 
   Start  Length  Slot  Name   Signature
   0      9      0    this       Lscala/util/parsing/json/Lexer$$anonfun$token$2$$anonfun$apply$6;
   0      9      1    v1       Ljava/lang/Object;


public scala.util.parsing.json.Lexer$$anonfun$token$2$$anonfun$apply$6(scala.util.parsing.json.Lexer$$anonfun$token$2);
  Signature: (Lscala/util/parsing/json/Lexer$$anonfun$token$2;)V
  Code:
   Stack=2, Locals=2, Args_size=2
	aload_1
	ifnonnull	l1 // aload_0
	new	class java/lang/NullPointerException
	dup
	invokespecial	Method java/lang/NullPointerException."<init>":()V
	athrow
l1	aload_0
	aload_1
	putfield	Field $outer:Lscala/util/parsing/json/Lexer$$anonfun$token$2;
	aload_0
	invokespecial	Method scala/runtime/AbstractFunction1."<init>":()V
	return
  Labels:
   	l1 = 12 // aload_0
  LocalVariableTable: 
   Start  Length  Slot  Name   Signature
   0      22      0    this       Lscala/util/parsing/json/Lexer$$anonfun$token$2$$anonfun$apply$6;
   0      22      1    $outer       Lscala/util/parsing/json/Lexer$$anonfun$token$2;


}

