Compiled from "Lexer.scala"
public final class scala.util.parsing.json.Lexer$$anonfun$number$3 extends java.lang.Object implements scala.Function1,scala.ScalaObject,java.io.Serializable
  SourceFile: "Lexer.scala"
  Scala: length = 0x
   
  InnerClass: 
   public $tilde=class scala/util/parsing/combinator/Parsers$$tilde of class scala/util/parsing/combinator/Parsers
   public final $anonfun$number$3=class scala/util/parsing/json/Lexer$$anonfun$number$3 of class scala/util/parsing/json/Lexer
  minor version: 0
  major version: 49
  Constant pool:
Asciz	SourceFile;
Asciz	Lexer.scala;
Asciz	<clinit>;
Asciz	()V;
Asciz	Code;
Asciz	serialVersionUID;
Asciz	J;
Asciz	scala/util/parsing/json/Lexer$$anonfun$number$3;
class	scala/util/parsing/json/Lexer$$anonfun$number$3
NameAndType	serialVersionUID:J
Field	scala/util/parsing/json/Lexer$$anonfun$number$3.serialVersionUID:J
Asciz	$outer;
Asciz	Lscala/util/parsing/json/Lexer;;
Asciz	<init>;
Asciz	(Lscala/util/parsing/json/Lexer;)V;
Asciz	LineNumberTable;
Asciz	java/lang/NullPointerException;
class	java/lang/NullPointerException
NameAndType	"<init>":()V
Method	java/lang/NullPointerException."<init>":()V
NameAndType	$outer:Lscala/util/parsing/json/Lexer;
Field	scala/util/parsing/json/Lexer$$anonfun$number$3.$outer:Lscala/util/parsing/json/Lexer;
Asciz	java/lang/Object;
class	java/lang/Object
Method	java/lang/Object."<init>":()V
Asciz	scala/Function1$class;
class	scala/Function1$class
Asciz	$init$;
Asciz	(Lscala/Function1;)V;
NameAndType	$init$:(Lscala/Function1;)V
Method	scala/Function1$class.$init$:(Lscala/Function1;)V
Asciz	this;
Asciz	Lscala/util/parsing/json/Lexer$$anonfun$number$3;;
Asciz	LocalVariableTable;
Asciz	apply;
Asciz	(Ljava/lang/Object;)Ljava/lang/Object;;
Asciz	scala/util/parsing/combinator/Parsers$$tilde;
class	scala/util/parsing/combinator/Parsers$$tilde
Asciz	(Lscala/util/parsing/combinator/Parsers$$tilde;)Ljava/lang/String;;
NameAndType	apply:(Lscala/util/parsing/combinator/Parsers$$tilde;)Ljava/lang/String;
Method	scala/util/parsing/json/Lexer$$anonfun$number$3.apply:(Lscala/util/parsing/combinator/Parsers$$tilde;)Ljava/lang/String;
Asciz	v1;
Asciz	Ljava/lang/Object;;
Asciz	_1;
Asciz	()Ljava/lang/Object;;
NameAndType	_1:()Ljava/lang/Object;
Method	scala/util/parsing/combinator/Parsers$$tilde._1:()Ljava/lang/Object;
Asciz	_2;
NameAndType	_2:()Ljava/lang/Object;
Method	scala/util/parsing/combinator/Parsers$$tilde._2:()Ljava/lang/Object;
Asciz	scala/Option;
class	scala/Option
Asciz	java/lang/String;
class	java/lang/String
Asciz	scala/collection/mutable/StringBuilder;
class	scala/collection/mutable/StringBuilder
Method	scala/collection/mutable/StringBuilder."<init>":()V
Asciz	append;
Asciz	(Ljava/lang/Object;)Lscala/collection/mutable/StringBuilder;;
NameAndType	append:(Ljava/lang/Object;)Lscala/collection/mutable/StringBuilder;
Method	scala/collection/mutable/StringBuilder.append:(Ljava/lang/Object;)Lscala/collection/mutable/StringBuilder;
Asciz	.;
String	.
Asciz	scala/util/parsing/json/Lexer;
class	scala/util/parsing/json/Lexer
Asciz	scala$util$parsing$json$Lexer$$optString;
Asciz	(Ljava/lang/String;Lscala/Option;)Ljava/lang/String;;
NameAndType	scala$util$parsing$json$Lexer$$optString:(Ljava/lang/String;Lscala/Option;)Ljava/lang/String;
Method	scala/util/parsing/json/Lexer.scala$util$parsing$json$Lexer$$optString:(Ljava/lang/String;Lscala/Option;)Ljava/lang/String;
Asciz	;
String	
Asciz	toString;
Asciz	()Ljava/lang/String;;
NameAndType	toString:()Ljava/lang/String;
Method	scala/collection/mutable/StringBuilder.toString:()Ljava/lang/String;
Asciz	scala/MatchError;
class	scala/MatchError
Method	scala/util/parsing/combinator/Parsers$$tilde.toString:()Ljava/lang/String;
Asciz	(Ljava/lang/String;)V;
NameAndType	"<init>":(Ljava/lang/String;)V
Method	scala/MatchError."<init>":(Ljava/lang/String;)V
Asciz	temp13;
Asciz	Lscala/util/parsing/combinator/Parsers$$tilde;;
Asciz	temp15;
Asciz	Ljava/lang/String;;
Asciz	temp16;
Asciz	Lscala/Option;;
Asciz	temp14;
Asciz	(Lscala/util/parsing/combinator/Parsers$$tilde<Lscala/util/parsing/combinator/Parsers$$tilde<Ljava/lang/String;Lscala/Option<Ljava/lang/String;>;>;Lscala/Option<Ljava/lang/String;>;>;)Ljava/lang/String;;
Asciz	Signature;
Asciz	andThen;
Asciz	(Lscala/Function1;)Lscala/Function1;;
Asciz	(Lscala/Function1;Lscala/Function1;)Lscala/Function1;;
NameAndType	andThen:(Lscala/Function1;Lscala/Function1;)Lscala/Function1;
Method	scala/Function1$class.andThen:(Lscala/Function1;Lscala/Function1;)Lscala/Function1;
Asciz	g;
Asciz	Lscala/Function1;;
Asciz	compose;
NameAndType	compose:(Lscala/Function1;Lscala/Function1;)Lscala/Function1;
Method	scala/Function1$class.compose:(Lscala/Function1;Lscala/Function1;)Lscala/Function1;
Asciz	(Lscala/Function1;)Ljava/lang/String;;
NameAndType	toString:(Lscala/Function1;)Ljava/lang/String;
Method	scala/Function1$class.toString:(Lscala/Function1;)Ljava/lang/String;
Asciz	Scala;
Asciz	InnerClasses;
Asciz	scala/util/parsing/combinator/Parsers;
class	scala/util/parsing/combinator/Parsers
Asciz	$tilde;
Asciz	$anonfun$number$3;
Asciz	scala/Function1;
class	scala/Function1
Asciz	scala/ScalaObject;
class	scala/ScalaObject
Asciz	java/io/Serializable;
class	java/io/Serializable

{
public static final long serialVersionUID;
  Signature: J

private final scala.util.parsing.json.Lexer $outer;
  Signature: Lscala/util/parsing/json/Lexer;

public static {};
  Signature: ()V
  Code:
   Stack=2, Locals=0, Args_size=0
	lconst_0
	putstatic	Field serialVersionUID:J
	return
  Labels:

public scala.util.parsing.json.Lexer$$anonfun$number$3(scala.util.parsing.json.Lexer);
  Signature: (Lscala/util/parsing/json/Lexer;)V
  Code:
   Stack=2, Locals=2, Args_size=2
	aload_1
	ifnonnull	l1 // aload_0
	new	class java/lang/NullPointerException
	dup
	invokespecial	Method java/lang/NullPointerException."<init>":()V
	athrow
l1	aload_0
	aload_1
	putfield	Field $outer:Lscala/util/parsing/json/Lexer;
	aload_0
	invokespecial	Method java/lang/Object."<init>":()V
	aload_0
	invokestatic	Method scala/Function1$class.$init$:(Lscala/Function1;)V
	return
  Labels:
   	l1 = 12 // aload_0
  LocalVariableTable: 
   Start  Length  Slot  Name   Signature
   0      26      0    this       Lscala/util/parsing/json/Lexer$$anonfun$number$3;
   0      26      1    $outer       Lscala/util/parsing/json/Lexer;


public final java.lang.Object apply(java.lang.Object);
  Signature: (Ljava/lang/Object;)Ljava/lang/Object;
  Code:
   Stack=2, Locals=3, Args_size=2
	aload_0
	getfield	Field $outer:Lscala/util/parsing/json/Lexer;
	astore_2
	aload_0
	aload_1
	checkcast	class scala/util/parsing/combinator/Parsers$$tilde
	invokevirtual	Method apply:(Lscala/util/parsing/combinator/Parsers$$tilde;)Ljava/lang/String;
	areturn
  Labels:
  LocalVariableTable: 
   Start  Length  Slot  Name   Signature
   0      14      0    this       Lscala/util/parsing/json/Lexer$$anonfun$number$3;
   5      9      1    v1       Ljava/lang/Object;


public final java.lang.String apply(scala.util.parsing.combinator.Parsers$$tilde);
  Signature: (Lscala/util/parsing/combinator/Parsers$$tilde;)Ljava/lang/String;
  Code:
   Stack=4, Locals=7, Args_size=2
	aload_0
	getfield	Field $outer:Lscala/util/parsing/json/Lexer;
	astore	6
	aload_1
	ifnull	l1 // new
	aload_1
	invokevirtual	Method scala/util/parsing/combinator/Parsers$$tilde._1:()Ljava/lang/Object;
	checkcast	class scala/util/parsing/combinator/Parsers$$tilde
	astore_2
	aload_1
	invokevirtual	Method scala/util/parsing/combinator/Parsers$$tilde._2:()Ljava/lang/Object;
	checkcast	class scala/Option
	astore	5
	aload_2
	ifnull	l2 // new
	aload_2
	invokevirtual	Method scala/util/parsing/combinator/Parsers$$tilde._1:()Ljava/lang/Object;
	checkcast	class java/lang/String
	astore_3
	aload_2
	invokevirtual	Method scala/util/parsing/combinator/Parsers$$tilde._2:()Ljava/lang/Object;
	checkcast	class scala/Option
	astore	4
	iconst_1
	ifeq	l3 // new
	new	class scala/collection/mutable/StringBuilder
	dup
	invokespecial	Method scala/collection/mutable/StringBuilder."<init>":()V
	aload_3
	invokevirtual	Method scala/collection/mutable/StringBuilder.append:(Ljava/lang/Object;)Lscala/collection/mutable/StringBuilder;
	aload_0
	getfield	Field $outer:Lscala/util/parsing/json/Lexer;
	ldc	String .
	aload	4
	invokevirtual	Method scala/util/parsing/json/Lexer.scala$util$parsing$json$Lexer$$optString:(Ljava/lang/String;Lscala/Option;)Ljava/lang/String;
	invokevirtual	Method scala/collection/mutable/StringBuilder.append:(Ljava/lang/Object;)Lscala/collection/mutable/StringBuilder;
	aload_0
	getfield	Field $outer:Lscala/util/parsing/json/Lexer;
	ldc	String 
	aload	5
	invokevirtual	Method scala/util/parsing/json/Lexer.scala$util$parsing$json$Lexer$$optString:(Ljava/lang/String;Lscala/Option;)Ljava/lang/String;
	invokevirtual	Method scala/collection/mutable/StringBuilder.append:(Ljava/lang/Object;)Lscala/collection/mutable/StringBuilder;
	invokevirtual	Method scala/collection/mutable/StringBuilder.toString:()Ljava/lang/String;
	areturn
l3	new	class scala/MatchError
	dup
	aload_1
	invokevirtual	Method scala/util/parsing/combinator/Parsers$$tilde.toString:()Ljava/lang/String;
	invokespecial	Method scala/MatchError."<init>":(Ljava/lang/String;)V
	athrow
l2	new	class scala/MatchError
	dup
	aload_1
	invokevirtual	Method scala/util/parsing/combinator/Parsers$$tilde.toString:()Ljava/lang/String;
	invokespecial	Method scala/MatchError."<init>":(Ljava/lang/String;)V
	athrow
l1	new	class scala/MatchError
	dup
	aload_1
	invokevirtual	Method scala/util/parsing/combinator/Parsers$$tilde.toString:()Ljava/lang/String;
	invokespecial	Method scala/MatchError."<init>":(Ljava/lang/String;)V
	athrow
  Labels:
   	l3 = 95 // new
   	l2 = 107 // new
   	l1 = 119 // new
  LocalVariableTable: 
   Start  Length  Slot  Name   Signature
   0      131      0    this       Lscala/util/parsing/json/Lexer$$anonfun$number$3;
   18      101      2    temp13       Lscala/util/parsing/combinator/Parsers$$tilde;
   39      68      3    temp15       Ljava/lang/String;
   48      59      4    temp16       Lscala/Option;
   27      92      5    temp14       Lscala/Option;

  Signature: length = 0x2
   00 59 

public scala.Function1 andThen(scala.Function1);
  Signature: (Lscala/Function1;)Lscala/Function1;
  Code:
   Stack=2, Locals=2, Args_size=2
	aload_0
	aload_1
	invokestatic	Method scala/Function1$class.andThen:(Lscala/Function1;Lscala/Function1;)Lscala/Function1;
	areturn
  Labels:
  LocalVariableTable: 
   Start  Length  Slot  Name   Signature
   0      6      0    this       Lscala/util/parsing/json/Lexer$$anonfun$number$3;
   0      6      1    g       Lscala/Function1;


public scala.Function1 compose(scala.Function1);
  Signature: (Lscala/Function1;)Lscala/Function1;
  Code:
   Stack=2, Locals=2, Args_size=2
	aload_0
	aload_1
	invokestatic	Method scala/Function1$class.compose:(Lscala/Function1;Lscala/Function1;)Lscala/Function1;
	areturn
  Labels:
  LocalVariableTable: 
   Start  Length  Slot  Name   Signature
   0      6      0    this       Lscala/util/parsing/json/Lexer$$anonfun$number$3;
   0      6      1    g       Lscala/Function1;


public java.lang.String toString();
  Signature: ()Ljava/lang/String;
  Code:
   Stack=1, Locals=1, Args_size=1
	aload_0
	invokestatic	Method scala/Function1$class.toString:(Lscala/Function1;)Ljava/lang/String;
	areturn
  Labels:

}

