Compiled from "Lexer.scala"
public final class scala.util.parsing.json.Lexer$$anonfun$expPart$3 extends scala.runtime.AbstractFunction1 implements java.io.Serializable
  SourceFile: "Lexer.scala"
  Scala: length = 0x
   
  InnerClass: 
   public $tilde=class scala/util/parsing/combinator/Parsers$$tilde of class scala/util/parsing/combinator/Parsers
   public final $anonfun$expPart$3=class scala/util/parsing/json/Lexer$$anonfun$expPart$3 of class scala/util/parsing/json/Lexer
  minor version: 0
  major version: 49
  Constant pool:
Asciz	SourceFile;
Asciz	Lexer.scala;
Asciz	<clinit>;
Asciz	()V;
Asciz	Code;
Asciz	serialVersionUID;
Asciz	J;
Asciz	scala/util/parsing/json/Lexer$$anonfun$expPart$3;
class	scala/util/parsing/json/Lexer$$anonfun$expPart$3
NameAndType	serialVersionUID:J
Field	scala/util/parsing/json/Lexer$$anonfun$expPart$3.serialVersionUID:J
Asciz	$outer;
Asciz	Lscala/util/parsing/json/Lexer;;
Asciz	<init>;
Asciz	(Lscala/util/parsing/json/Lexer;)V;
Asciz	LineNumberTable;
Asciz	java/lang/NullPointerException;
class	java/lang/NullPointerException
NameAndType	"<init>":()V
Method	java/lang/NullPointerException."<init>":()V
NameAndType	$outer:Lscala/util/parsing/json/Lexer;
Field	scala/util/parsing/json/Lexer$$anonfun$expPart$3.$outer:Lscala/util/parsing/json/Lexer;
Asciz	scala/runtime/AbstractFunction1;
class	scala/runtime/AbstractFunction1
Method	scala/runtime/AbstractFunction1."<init>":()V
Asciz	this;
Asciz	Lscala/util/parsing/json/Lexer$$anonfun$expPart$3;;
Asciz	LocalVariableTable;
Asciz	apply;
Asciz	(Ljava/lang/Object;)Ljava/lang/Object;;
Asciz	scala/util/parsing/combinator/Parsers$$tilde;
class	scala/util/parsing/combinator/Parsers$$tilde
Asciz	(Lscala/util/parsing/combinator/Parsers$$tilde;)Ljava/lang/String;;
NameAndType	apply:(Lscala/util/parsing/combinator/Parsers$$tilde;)Ljava/lang/String;
Method	scala/util/parsing/json/Lexer$$anonfun$expPart$3.apply:(Lscala/util/parsing/combinator/Parsers$$tilde;)Ljava/lang/String;
Asciz	v1;
Asciz	Ljava/lang/Object;;
Asciz	_1;
Asciz	()Ljava/lang/Object;;
NameAndType	_1:()Ljava/lang/Object;
Method	scala/util/parsing/combinator/Parsers$$tilde._1:()Ljava/lang/Object;
Asciz	_2;
NameAndType	_2:()Ljava/lang/Object;
Method	scala/util/parsing/combinator/Parsers$$tilde._2:()Ljava/lang/Object;
Asciz	scala/collection/immutable/List;
class	scala/collection/immutable/List
Asciz	scala/runtime/BoxesRunTime;
class	scala/runtime/BoxesRunTime
Asciz	unboxToChar;
Asciz	(Ljava/lang/Object;)C;
NameAndType	unboxToChar:(Ljava/lang/Object;)C
Method	scala/runtime/BoxesRunTime.unboxToChar:(Ljava/lang/Object;)C
Asciz	scala/Option;
class	scala/Option
Asciz	scala/collection/mutable/StringBuilder;
class	scala/collection/mutable/StringBuilder
Method	scala/collection/mutable/StringBuilder."<init>":()V
Asciz	append;
Asciz	(C)Lscala/collection/mutable/StringBuilder;;
NameAndType	append:(C)Lscala/collection/mutable/StringBuilder;
Method	scala/collection/mutable/StringBuilder.append:(C)Lscala/collection/mutable/StringBuilder;
Asciz	;
String	
Asciz	scala/util/parsing/json/Lexer;
class	scala/util/parsing/json/Lexer
Asciz	scala$util$parsing$json$Lexer$$optString;
Asciz	(Ljava/lang/String;Lscala/Option;)Ljava/lang/String;;
NameAndType	scala$util$parsing$json$Lexer$$optString:(Ljava/lang/String;Lscala/Option;)Ljava/lang/String;
Method	scala/util/parsing/json/Lexer.scala$util$parsing$json$Lexer$$optString:(Ljava/lang/String;Lscala/Option;)Ljava/lang/String;
Asciz	(Ljava/lang/Object;)Lscala/collection/mutable/StringBuilder;;
NameAndType	append:(Ljava/lang/Object;)Lscala/collection/mutable/StringBuilder;
Method	scala/collection/mutable/StringBuilder.append:(Ljava/lang/Object;)Lscala/collection/mutable/StringBuilder;
Asciz	scala/collection/TraversableLike;
class	scala/collection/TraversableLike
Asciz	mkString;
Asciz	(Ljava/lang/String;)Ljava/lang/String;;
NameAndType	mkString:(Ljava/lang/String;)Ljava/lang/String;
InterfaceMethod	scala/collection/TraversableLike.mkString:(Ljava/lang/String;)Ljava/lang/String;
Asciz	toString;
Asciz	()Ljava/lang/String;;
NameAndType	toString:()Ljava/lang/String;
Method	scala/collection/mutable/StringBuilder.toString:()Ljava/lang/String;
Asciz	scala/MatchError;
class	scala/MatchError
Method	scala/util/parsing/combinator/Parsers$$tilde.toString:()Ljava/lang/String;
Asciz	(Ljava/lang/String;)V;
NameAndType	"<init>":(Ljava/lang/String;)V
Method	scala/MatchError."<init>":(Ljava/lang/String;)V
Asciz	temp21;
Asciz	Lscala/util/parsing/combinator/Parsers$$tilde;;
Asciz	temp23;
Asciz	C;
Asciz	temp24;
Asciz	Lscala/Option;;
Asciz	temp22;
Asciz	Lscala/collection/immutable/List;;
Asciz	(Lscala/util/parsing/combinator/Parsers$$tilde<Lscala/util/parsing/combinator/Parsers$$tilde<Ljava/lang/Character;Lscala/Option<Ljava/lang/Character;>;>;Lscala/collection/immutable/List<Ljava/lang/Character;>;>;)Ljava/lang/String;;
Asciz	Signature;
Asciz	Scala;
Asciz	InnerClasses;
Asciz	scala/util/parsing/combinator/Parsers;
class	scala/util/parsing/combinator/Parsers
Asciz	$tilde;
Asciz	$anonfun$expPart$3;
Asciz	java/io/Serializable;
class	java/io/Serializable

{
public static final long serialVersionUID;
  Signature: J

public final scala.util.parsing.json.Lexer $outer;
  Signature: Lscala/util/parsing/json/Lexer;

public static {};
  Signature: ()V
  Code:
   Stack=2, Locals=0, Args_size=0
	lconst_0
	putstatic	Field serialVersionUID:J
	return
  Labels:

public scala.util.parsing.json.Lexer$$anonfun$expPart$3(scala.util.parsing.json.Lexer);
  Signature: (Lscala/util/parsing/json/Lexer;)V
  Code:
   Stack=2, Locals=2, Args_size=2
	aload_1
	ifnonnull	l1 // aload_0
	new	class java/lang/NullPointerException
	dup
	invokespecial	Method java/lang/NullPointerException."<init>":()V
	athrow
l1	aload_0
	aload_1
	putfield	Field $outer:Lscala/util/parsing/json/Lexer;
	aload_0
	invokespecial	Method scala/runtime/AbstractFunction1."<init>":()V
	return
  Labels:
   	l1 = 12 // aload_0
  LocalVariableTable: 
   Start  Length  Slot  Name   Signature
   0      22      0    this       Lscala/util/parsing/json/Lexer$$anonfun$expPart$3;
   0      22      1    $outer       Lscala/util/parsing/json/Lexer;


public final java.lang.Object apply(java.lang.Object);
  Signature: (Ljava/lang/Object;)Ljava/lang/Object;
  Code:
   Stack=2, Locals=2, Args_size=2
	aload_0
	aload_1
	checkcast	class scala/util/parsing/combinator/Parsers$$tilde
	invokevirtual	Method apply:(Lscala/util/parsing/combinator/Parsers$$tilde;)Ljava/lang/String;
	areturn
  Labels:
  LocalVariableTable: 
   Start  Length  Slot  Name   Signature
   0      9      0    this       Lscala/util/parsing/json/Lexer$$anonfun$expPart$3;
   0      9      1    v1       Ljava/lang/Object;


public final java.lang.String apply(scala.util.parsing.combinator.Parsers$$tilde);
  Signature: (Lscala/util/parsing/combinator/Parsers$$tilde;)Ljava/lang/String;
  Code:
   Stack=4, Locals=6, Args_size=2
	aload_1
	ifnull	l1 // new
	aload_1
	invokevirtual	Method scala/util/parsing/combinator/Parsers$$tilde._1:()Ljava/lang/Object;
	checkcast	class scala/util/parsing/combinator/Parsers$$tilde
	astore_2
	aload_1
	invokevirtual	Method scala/util/parsing/combinator/Parsers$$tilde._2:()Ljava/lang/Object;
	checkcast	class scala/collection/immutable/List
	astore	5
	aload_2
	ifnull	l2 // new
	aload_2
	invokevirtual	Method scala/util/parsing/combinator/Parsers$$tilde._1:()Ljava/lang/Object;
	invokestatic	Method scala/runtime/BoxesRunTime.unboxToChar:(Ljava/lang/Object;)C
	istore_3
	aload_2
	invokevirtual	Method scala/util/parsing/combinator/Parsers$$tilde._2:()Ljava/lang/Object;
	checkcast	class scala/Option
	astore	4
	iconst_1
	ifeq	l3 // new
	new	class scala/collection/mutable/StringBuilder
	dup
	invokespecial	Method scala/collection/mutable/StringBuilder."<init>":()V
	iload_3
	invokevirtual	Method scala/collection/mutable/StringBuilder.append:(C)Lscala/collection/mutable/StringBuilder;
	aload_0
	getfield	Field $outer:Lscala/util/parsing/json/Lexer;
	ldc	String 
	aload	4
	invokevirtual	Method scala/util/parsing/json/Lexer.scala$util$parsing$json$Lexer$$optString:(Ljava/lang/String;Lscala/Option;)Ljava/lang/String;
	invokevirtual	Method scala/collection/mutable/StringBuilder.append:(Ljava/lang/Object;)Lscala/collection/mutable/StringBuilder;
	aload	5
	ldc	String 
	invokeinterface	InterfaceMethod scala/collection/TraversableLike.mkString:(Ljava/lang/String;)Ljava/lang/String;
	invokevirtual	Method scala/collection/mutable/StringBuilder.append:(Ljava/lang/Object;)Lscala/collection/mutable/StringBuilder;
	invokevirtual	Method scala/collection/mutable/StringBuilder.toString:()Ljava/lang/String;
	areturn
l3	new	class scala/MatchError
	dup
	aload_1
	invokevirtual	Method scala/util/parsing/combinator/Parsers$$tilde.toString:()Ljava/lang/String;
	invokespecial	Method scala/MatchError."<init>":(Ljava/lang/String;)V
	athrow
l2	new	class scala/MatchError
	dup
	aload_1
	invokevirtual	Method scala/util/parsing/combinator/Parsers$$tilde.toString:()Ljava/lang/String;
	invokespecial	Method scala/MatchError."<init>":(Ljava/lang/String;)V
	athrow
l1	new	class scala/MatchError
	dup
	aload_1
	invokevirtual	Method scala/util/parsing/combinator/Parsers$$tilde.toString:()Ljava/lang/String;
	invokespecial	Method scala/MatchError."<init>":(Ljava/lang/String;)V
	athrow
  Labels:
   	l3 = 87 // new
   	l2 = 99 // new
   	l1 = 111 // new
  LocalVariableTable: 
   Start  Length  Slot  Name   Signature
   0      123      0    this       Lscala/util/parsing/json/Lexer$$anonfun$expPart$3;
   12      99      2    temp21       Lscala/util/parsing/combinator/Parsers$$tilde;
   33      66      3    temp23       C
   42      57      4    temp24       Lscala/Option;
   21      90      5    temp22       Lscala/collection/immutable/List;

  Signature: length = 0x2
   00 61 

}

