Compiled from "Lexer.scala"
public final class scala.util.parsing.json.Lexer$$anonfun$scala$util$parsing$json$Lexer$$unicodeBlock$4 extends scala.runtime.AbstractFunction1 implements java.io.Serializable
  SourceFile: "Lexer.scala"
  Scala: length = 0x
   
  InnerClass: 
   public $tilde=class scala/util/parsing/combinator/Parsers$$tilde of class scala/util/parsing/combinator/Parsers
   public final $anonfun$apply$6=class scala/Array$$anonfun$apply$6 of class scala/Array
   public final $anonfun$scala$util$parsing$json$Lexer$$unicodeBlock$4=class scala/util/parsing/json/Lexer$$anonfun$scala$util$parsing$json$Lexer$$unicodeBlock$4 of class scala/util/parsing/json/Lexer
  minor version: 0
  major version: 49
  Constant pool:
Asciz	SourceFile;
Asciz	Lexer.scala;
Asciz	<clinit>;
Asciz	()V;
Asciz	Code;
Asciz	serialVersionUID;
Asciz	J;
Asciz	scala/util/parsing/json/Lexer$$anonfun$scala$util$parsing$json$Lexer$$unicodeBlock$4;
class	scala/util/parsing/json/Lexer$$anonfun$scala$util$parsing$json$Lexer$$unicodeBlock$4
NameAndType	serialVersionUID:J
Field	scala/util/parsing/json/Lexer$$anonfun$scala$util$parsing$json$Lexer$$unicodeBlock$4.serialVersionUID:J
Asciz	apply;
Asciz	(Lscala/util/parsing/combinator/Parsers$$tilde;)Ljava/lang/String;;
Asciz	LineNumberTable;
Asciz	scala/util/parsing/combinator/Parsers$$tilde;
class	scala/util/parsing/combinator/Parsers$$tilde
Asciz	_1;
Asciz	()Ljava/lang/Object;;
NameAndType	_1:()Ljava/lang/Object;
Method	scala/util/parsing/combinator/Parsers$$tilde._1:()Ljava/lang/Object;
Asciz	_2;
NameAndType	_2:()Ljava/lang/Object;
Method	scala/util/parsing/combinator/Parsers$$tilde._2:()Ljava/lang/Object;
Asciz	scala/runtime/BoxesRunTime;
class	scala/runtime/BoxesRunTime
Asciz	unboxToChar;
Asciz	(Ljava/lang/Object;)C;
NameAndType	unboxToChar:(Ljava/lang/Object;)C
Method	scala/runtime/BoxesRunTime.unboxToChar:(Ljava/lang/Object;)C
Asciz	java/lang/String;
class	java/lang/String
Asciz	scala/Predef$;
class	scala/Predef$
Asciz	MODULE$;
Asciz	Lscala/Predef$;;
NameAndType	MODULE$:Lscala/Predef$;
Field	scala/Predef$.MODULE$:Lscala/Predef$;
Asciz	wrapCharArray;
Asciz	([C)Lscala/collection/mutable/WrappedArray;;
NameAndType	wrapCharArray:([C)Lscala/collection/mutable/WrappedArray;
Method	scala/Predef$.wrapCharArray:([C)Lscala/collection/mutable/WrappedArray;
Asciz	scala/collection/TraversableLike;
class	scala/collection/TraversableLike
Asciz	toList;
Asciz	()Lscala/collection/immutable/List;;
NameAndType	toList:()Lscala/collection/immutable/List;
InterfaceMethod	scala/collection/TraversableLike.toList:()Lscala/collection/immutable/List;
Asciz	;
String	
Asciz	mkString;
Asciz	(Ljava/lang/String;)Ljava/lang/String;;
NameAndType	mkString:(Ljava/lang/String;)Ljava/lang/String;
InterfaceMethod	scala/collection/TraversableLike.mkString:(Ljava/lang/String;)Ljava/lang/String;
int	16;
Asciz	java/lang/Integer;
class	java/lang/Integer
Asciz	parseInt;
Asciz	(Ljava/lang/String;I)I;
NameAndType	parseInt:(Ljava/lang/String;I)I
Method	java/lang/Integer.parseInt:(Ljava/lang/String;I)I
Asciz	wrapIntArray;
Asciz	([I)Lscala/collection/mutable/WrappedArray;;
NameAndType	wrapIntArray:([I)Lscala/collection/mutable/WrappedArray;
Method	scala/Predef$.wrapIntArray:([I)Lscala/collection/mutable/WrappedArray;
Asciz	scala/collection/SeqLike;
class	scala/collection/SeqLike
Asciz	length;
Asciz	()I;
NameAndType	length:()I
InterfaceMethod	scala/collection/SeqLike.length:()I
Asciz	scala/runtime/IntRef;
class	scala/runtime/IntRef
Asciz	<init>;
Asciz	(I)V;
NameAndType	"<init>":(I)V
Method	scala/runtime/IntRef."<init>":(I)V
Asciz	scala/collection/IterableLike;
class	scala/collection/IterableLike
Asciz	iterator;
Asciz	()Lscala/collection/Iterator;;
NameAndType	iterator:()Lscala/collection/Iterator;
InterfaceMethod	scala/collection/IterableLike.iterator:()Lscala/collection/Iterator;
Asciz	scala/Array$$anonfun$apply$6;
class	scala/Array$$anonfun$apply$6
Asciz	([ILscala/runtime/IntRef;)V;
NameAndType	"<init>":([ILscala/runtime/IntRef;)V
Method	scala/Array$$anonfun$apply$6."<init>":([ILscala/runtime/IntRef;)V
Asciz	scala/collection/Iterator;
class	scala/collection/Iterator
Asciz	foreach;
Asciz	(Lscala/Function1;)V;
NameAndType	foreach:(Lscala/Function1;)V
InterfaceMethod	scala/collection/Iterator.foreach:(Lscala/Function1;)V
Asciz	([III)V;
NameAndType	"<init>":([III)V
Method	java/lang/String."<init>":([III)V
Asciz	scala/MatchError;
class	scala/MatchError
Asciz	toString;
Asciz	()Ljava/lang/String;;
NameAndType	toString:()Ljava/lang/String;
Method	scala/util/parsing/combinator/Parsers$$tilde.toString:()Ljava/lang/String;
Asciz	(Ljava/lang/String;)V;
NameAndType	"<init>":(Ljava/lang/String;)V
Method	scala/MatchError."<init>":(Ljava/lang/String;)V
Asciz	this;
Asciz	Lscala/util/parsing/json/Lexer$$anonfun$scala$util$parsing$json$Lexer$$unicodeBlock$4;;
Asciz	temp30;
Asciz	Lscala/util/parsing/combinator/Parsers$$tilde;;
Asciz	temp32;
Asciz	temp34;
Asciz	C;
Asciz	temp35;
Asciz	temp33;
Asciz	temp31;
Asciz	i$60;
Asciz	Lscala/runtime/IntRef;;
Asciz	array$60;
Asciz	[I;
Asciz	LocalVariableTable;
Asciz	(Lscala/util/parsing/combinator/Parsers$$tilde<Lscala/util/parsing/combinator/Parsers$$tilde<Lscala/util/parsing/combinator/Parsers$$tilde<Ljava/lang/Character;Ljava/lang/Character;>;Ljava/lang/Character;>;Ljava/lang/Character;>;)Ljava/lang/String;;
Asciz	Signature;
Asciz	(Ljava/lang/Object;)Ljava/lang/Object;;
NameAndType	apply:(Lscala/util/parsing/combinator/Parsers$$tilde;)Ljava/lang/String;
Method	scala/util/parsing/json/Lexer$$anonfun$scala$util$parsing$json$Lexer$$unicodeBlock$4.apply:(Lscala/util/parsing/combinator/Parsers$$tilde;)Ljava/lang/String;
Asciz	v1;
Asciz	Ljava/lang/Object;;
Asciz	(Lscala/util/parsing/json/Lexer;)V;
Asciz	scala/runtime/AbstractFunction1;
class	scala/runtime/AbstractFunction1
NameAndType	"<init>":()V
Method	scala/runtime/AbstractFunction1."<init>":()V
Asciz	$outer;
Asciz	Lscala/util/parsing/json/Lexer;;
Asciz	Scala;
Asciz	InnerClasses;
Asciz	scala/util/parsing/combinator/Parsers;
class	scala/util/parsing/combinator/Parsers
Asciz	$tilde;
Asciz	scala/Array;
class	scala/Array
Asciz	$anonfun$apply$6;
Asciz	scala/util/parsing/json/Lexer;
class	scala/util/parsing/json/Lexer
Asciz	$anonfun$scala$util$parsing$json$Lexer$$unicodeBlock$4;
Asciz	java/io/Serializable;
class	java/io/Serializable

{
public static final long serialVersionUID;
  Signature: J

public static {};
  Signature: ()V
  Code:
   Stack=2, Locals=0, Args_size=0
	lconst_0
	putstatic	Field serialVersionUID:J
	return
  Labels:

public final java.lang.String apply(scala.util.parsing.combinator.Parsers$$tilde);
  Signature: (Lscala/util/parsing/combinator/Parsers$$tilde;)Ljava/lang/String;
  Code:
   Stack=7, Locals=13, Args_size=2
	aload_1
	ifnull	l1 // new
	aload_1
	invokevirtual	Method scala/util/parsing/combinator/Parsers$$tilde._1:()Ljava/lang/Object;
	checkcast	class scala/util/parsing/combinator/Parsers$$tilde
	astore_2
	aload_1
	invokevirtual	Method scala/util/parsing/combinator/Parsers$$tilde._2:()Ljava/lang/Object;
	invokestatic	Method scala/runtime/BoxesRunTime.unboxToChar:(Ljava/lang/Object;)C
	istore	7
	aload_2
	ifnull	l2 // new
	aload_2
	invokevirtual	Method scala/util/parsing/combinator/Parsers$$tilde._1:()Ljava/lang/Object;
	checkcast	class scala/util/parsing/combinator/Parsers$$tilde
	astore_3
	aload_2
	invokevirtual	Method scala/util/parsing/combinator/Parsers$$tilde._2:()Ljava/lang/Object;
	invokestatic	Method scala/runtime/BoxesRunTime.unboxToChar:(Ljava/lang/Object;)C
	istore	6
	aload_3
	ifnull	l3 // new
	aload_3
	invokevirtual	Method scala/util/parsing/combinator/Parsers$$tilde._1:()Ljava/lang/Object;
	invokestatic	Method scala/runtime/BoxesRunTime.unboxToChar:(Ljava/lang/Object;)C
	istore	4
	aload_3
	invokevirtual	Method scala/util/parsing/combinator/Parsers$$tilde._2:()Ljava/lang/Object;
	invokestatic	Method scala/runtime/BoxesRunTime.unboxToChar:(Ljava/lang/Object;)C
	istore	5
	new	class java/lang/String
	dup
	getstatic	Field scala/Predef$.MODULE$:Lscala/Predef$;
	iconst_4
	newarray char
	dup
	iconst_0
	iload	4
	castore
	dup
	iconst_1
	iload	5
	castore
	dup
	iconst_2
	iload	6
	castore
	dup
	iconst_3
	iload	7
	castore
	invokevirtual	Method scala/Predef$.wrapCharArray:([C)Lscala/collection/mutable/WrappedArray;
	astore	8
	aload	8
	invokeinterface	InterfaceMethod scala/collection/TraversableLike.toList:()Lscala/collection/immutable/List;
	ldc	String 
	invokeinterface	InterfaceMethod scala/collection/TraversableLike.mkString:(Ljava/lang/String;)Ljava/lang/String;
	ldc	int 16
	invokestatic	Method java/lang/Integer.parseInt:(Ljava/lang/String;I)I
	getstatic	Field scala/Predef$.MODULE$:Lscala/Predef$;
	iconst_0
	newarray int
	invokevirtual	Method scala/Predef$.wrapIntArray:([I)Lscala/collection/mutable/WrappedArray;
	astore	10
	istore	9
	aload	10
	invokeinterface	InterfaceMethod scala/collection/SeqLike.length:()I
	iconst_1
	iadd
	newarray int
	astore	12
	aload	12
	iconst_0
	iload	9
	iastore
	new	class scala/runtime/IntRef
	dup
	iconst_1
	invokespecial	Method scala/runtime/IntRef."<init>":(I)V
	astore	11
	aload	10
	invokeinterface	InterfaceMethod scala/collection/IterableLike.iterator:()Lscala/collection/Iterator;
	new	class scala/Array$$anonfun$apply$6
	dup
	aload	12
	aload	11
	invokespecial	Method scala/Array$$anonfun$apply$6."<init>":([ILscala/runtime/IntRef;)V
	invokeinterface	InterfaceMethod scala/collection/Iterator.foreach:(Lscala/Function1;)V
	aload	12
	iconst_0
	iconst_1
	invokespecial	Method java/lang/String."<init>":([III)V
	areturn
l3	new	class scala/MatchError
	dup
	aload_1
	invokevirtual	Method scala/util/parsing/combinator/Parsers$$tilde.toString:()Ljava/lang/String;
	invokespecial	Method scala/MatchError."<init>":(Ljava/lang/String;)V
	athrow
l2	new	class scala/MatchError
	dup
	aload_1
	invokevirtual	Method scala/util/parsing/combinator/Parsers$$tilde.toString:()Ljava/lang/String;
	invokespecial	Method scala/MatchError."<init>":(Ljava/lang/String;)V
	athrow
l1	new	class scala/MatchError
	dup
	aload_1
	invokevirtual	Method scala/util/parsing/combinator/Parsers$$tilde.toString:()Ljava/lang/String;
	invokespecial	Method scala/MatchError."<init>":(Ljava/lang/String;)V
	athrow
  Labels:
   	l3 = 191 // new
   	l2 = 203 // new
   	l1 = 215 // new
  LocalVariableTable: 
   Start  Length  Slot  Name   Signature
   0      227      0    this       Lscala/util/parsing/json/Lexer$$anonfun$scala$util$parsing$json$Lexer$$unicodeBlock$4;
   12      203      2    temp30       Lscala/util/parsing/combinator/Parsers$$tilde;
   33      170      3    temp32       Lscala/util/parsing/combinator/Parsers$$tilde;
   55      135      4    temp34       C
   64      126      5    temp35       C
   42      161      6    temp33       C
   21      194      7    temp31       C
   160      25      11    i$60       Lscala/runtime/IntRef;
   144      41      12    array$60       [I

  Signature: length = 0x2
   00 79 

public final java.lang.Object apply(java.lang.Object);
  Signature: (Ljava/lang/Object;)Ljava/lang/Object;
  Code:
   Stack=2, Locals=2, Args_size=2
	aload_0
	aload_1
	checkcast	class scala/util/parsing/combinator/Parsers$$tilde
	invokevirtual	Method apply:(Lscala/util/parsing/combinator/Parsers$$tilde;)Ljava/lang/String;
	areturn
  Labels:
  LocalVariableTable: 
   Start  Length  Slot  Name   Signature
   0      9      0    this       Lscala/util/parsing/json/Lexer$$anonfun$scala$util$parsing$json$Lexer$$unicodeBlock$4;
   0      9      1    v1       Ljava/lang/Object;


public scala.util.parsing.json.Lexer$$anonfun$scala$util$parsing$json$Lexer$$unicodeBlock$4(scala.util.parsing.json.Lexer);
  Signature: (Lscala/util/parsing/json/Lexer;)V
  Code:
   Stack=1, Locals=2, Args_size=2
	aload_0
	invokespecial	Method scala/runtime/AbstractFunction1."<init>":()V
	return
  Labels:
  LocalVariableTable: 
   Start  Length  Slot  Name   Signature
   0      5      0    this       Lscala/util/parsing/json/Lexer$$anonfun$scala$util$parsing$json$Lexer$$unicodeBlock$4;
   0      5      1    $outer       Lscala/util/parsing/json/Lexer;


}

