Compiled from "Lexer.scala"
public final class scala.util.parsing.json.Lexer$$anonfun$token$1$$anonfun$apply$2 extends scala.runtime.AbstractFunction1 implements java.io.Serializable
  SourceFile: "Lexer.scala"
  Scala: length = 0x
   
  InnerClass: 
   public $tilde=class scala/util/parsing/combinator/Parsers$$tilde of class scala/util/parsing/combinator/Parsers
   public ErrorToken=class scala/util/parsing/syntax/Tokens$ErrorToken of class scala/util/parsing/syntax/Tokens
   public final $anonfun$token$1=class scala/util/parsing/json/Lexer$$anonfun$token$1 of class scala/util/parsing/json/Lexer
   public final $anonfun$apply$2=class scala/util/parsing/json/Lexer$$anonfun$token$1$$anonfun$apply$2 of class scala/util/parsing/json/Lexer$$anonfun$token$1
  minor version: 0
  major version: 49
  Constant pool:
Asciz	SourceFile;
Asciz	Lexer.scala;
Asciz	<clinit>;
Asciz	()V;
Asciz	Code;
Asciz	serialVersionUID;
Asciz	J;
Asciz	scala/util/parsing/json/Lexer$$anonfun$token$1$$anonfun$apply$2;
class	scala/util/parsing/json/Lexer$$anonfun$token$1$$anonfun$apply$2
NameAndType	serialVersionUID:J
Field	scala/util/parsing/json/Lexer$$anonfun$token$1$$anonfun$apply$2.serialVersionUID:J
Asciz	$outer;
Asciz	Lscala/util/parsing/json/Lexer$$anonfun$token$1;;
Asciz	<init>;
Asciz	(Lscala/util/parsing/json/Lexer$$anonfun$token$1;)V;
Asciz	LineNumberTable;
Asciz	java/lang/NullPointerException;
class	java/lang/NullPointerException
NameAndType	"<init>":()V
Method	java/lang/NullPointerException."<init>":()V
NameAndType	$outer:Lscala/util/parsing/json/Lexer$$anonfun$token$1;
Field	scala/util/parsing/json/Lexer$$anonfun$token$1$$anonfun$apply$2.$outer:Lscala/util/parsing/json/Lexer$$anonfun$token$1;
Asciz	scala/runtime/AbstractFunction1;
class	scala/runtime/AbstractFunction1
Method	scala/runtime/AbstractFunction1."<init>":()V
Asciz	this;
Asciz	Lscala/util/parsing/json/Lexer$$anonfun$token$1$$anonfun$apply$2;;
Asciz	LocalVariableTable;
Asciz	apply;
Asciz	(Ljava/lang/Object;)Ljava/lang/Object;;
Asciz	scala/util/parsing/combinator/Parsers$$tilde;
class	scala/util/parsing/combinator/Parsers$$tilde
Asciz	(Lscala/util/parsing/combinator/Parsers$$tilde;)Lscala/util/parsing/syntax/Tokens$ErrorToken;;
NameAndType	apply:(Lscala/util/parsing/combinator/Parsers$$tilde;)Lscala/util/parsing/syntax/Tokens$ErrorToken;
Method	scala/util/parsing/json/Lexer$$anonfun$token$1$$anonfun$apply$2.apply:(Lscala/util/parsing/combinator/Parsers$$tilde;)Lscala/util/parsing/syntax/Tokens$ErrorToken;
Asciz	v1;
Asciz	Ljava/lang/Object;;
Asciz	_1;
Asciz	()Ljava/lang/Object;;
NameAndType	_1:()Ljava/lang/Object;
Method	scala/util/parsing/combinator/Parsers$$tilde._1:()Ljava/lang/Object;
Asciz	java/lang/String;
class	java/lang/String
Asciz	_2;
NameAndType	_2:()Ljava/lang/Object;
Method	scala/util/parsing/combinator/Parsers$$tilde._2:()Ljava/lang/Object;
Asciz	scala/runtime/BoxesRunTime;
class	scala/runtime/BoxesRunTime
Asciz	unboxToChar;
Asciz	(Ljava/lang/Object;)C;
NameAndType	unboxToChar:(Ljava/lang/Object;)C
Method	scala/runtime/BoxesRunTime.unboxToChar:(Ljava/lang/Object;)C
Asciz	scala/util/parsing/syntax/Tokens$ErrorToken;
class	scala/util/parsing/syntax/Tokens$ErrorToken
Asciz	scala/util/parsing/json/Lexer$$anonfun$token$1;
class	scala/util/parsing/json/Lexer$$anonfun$token$1
Asciz	Lscala/util/parsing/json/Lexer;;
NameAndType	$outer:Lscala/util/parsing/json/Lexer;
Field	scala/util/parsing/json/Lexer$$anonfun$token$1.$outer:Lscala/util/parsing/json/Lexer;
Asciz	scala/collection/mutable/StringBuilder;
class	scala/collection/mutable/StringBuilder
Method	scala/collection/mutable/StringBuilder."<init>":()V
Asciz	Invalid number format : ;
String	Invalid number format : 
Asciz	append;
Asciz	(Ljava/lang/Object;)Lscala/collection/mutable/StringBuilder;;
NameAndType	append:(Ljava/lang/Object;)Lscala/collection/mutable/StringBuilder;
Method	scala/collection/mutable/StringBuilder.append:(Ljava/lang/Object;)Lscala/collection/mutable/StringBuilder;
Asciz	boxToCharacter;
Asciz	(C)Ljava/lang/Character;;
NameAndType	boxToCharacter:(C)Ljava/lang/Character;
Method	scala/runtime/BoxesRunTime.boxToCharacter:(C)Ljava/lang/Character;
Asciz	toString;
Asciz	()Ljava/lang/String;;
NameAndType	toString:()Ljava/lang/String;
Method	scala/collection/mutable/StringBuilder.toString:()Ljava/lang/String;
Asciz	(Lscala/util/parsing/syntax/Tokens;Ljava/lang/String;)V;
NameAndType	"<init>":(Lscala/util/parsing/syntax/Tokens;Ljava/lang/String;)V
Method	scala/util/parsing/syntax/Tokens$ErrorToken."<init>":(Lscala/util/parsing/syntax/Tokens;Ljava/lang/String;)V
Asciz	scala/MatchError;
class	scala/MatchError
Method	scala/util/parsing/combinator/Parsers$$tilde.toString:()Ljava/lang/String;
Asciz	(Ljava/lang/String;)V;
NameAndType	"<init>":(Ljava/lang/String;)V
Method	scala/MatchError."<init>":(Ljava/lang/String;)V
Asciz	temp2;
Asciz	Ljava/lang/String;;
Asciz	temp3;
Asciz	C;
Asciz	(Lscala/util/parsing/combinator/Parsers$$tilde<Ljava/lang/String;Ljava/lang/Character;>;)Lscala/util/parsing/syntax/Tokens$ErrorToken;;
Asciz	Signature;
Asciz	Scala;
Asciz	InnerClasses;
Asciz	scala/util/parsing/combinator/Parsers;
class	scala/util/parsing/combinator/Parsers
Asciz	$tilde;
Asciz	scala/util/parsing/syntax/Tokens;
class	scala/util/parsing/syntax/Tokens
Asciz	ErrorToken;
Asciz	scala/util/parsing/json/Lexer;
class	scala/util/parsing/json/Lexer
Asciz	$anonfun$token$1;
Asciz	$anonfun$apply$2;
Asciz	java/io/Serializable;
class	java/io/Serializable

{
public static final long serialVersionUID;
  Signature: J

private final scala.util.parsing.json.Lexer$$anonfun$token$1 $outer;
  Signature: Lscala/util/parsing/json/Lexer$$anonfun$token$1;

public static {};
  Signature: ()V
  Code:
   Stack=2, Locals=0, Args_size=0
	lconst_0
	putstatic	Field serialVersionUID:J
	return
  Labels:

public scala.util.parsing.json.Lexer$$anonfun$token$1$$anonfun$apply$2(scala.util.parsing.json.Lexer$$anonfun$token$1);
  Signature: (Lscala/util/parsing/json/Lexer$$anonfun$token$1;)V
  Code:
   Stack=2, Locals=2, Args_size=2
	aload_1
	ifnonnull	l1 // aload_0
	new	class java/lang/NullPointerException
	dup
	invokespecial	Method java/lang/NullPointerException."<init>":()V
	athrow
l1	aload_0
	aload_1
	putfield	Field $outer:Lscala/util/parsing/json/Lexer$$anonfun$token$1;
	aload_0
	invokespecial	Method scala/runtime/AbstractFunction1."<init>":()V
	return
  Labels:
   	l1 = 12 // aload_0
  LocalVariableTable: 
   Start  Length  Slot  Name   Signature
   0      22      0    this       Lscala/util/parsing/json/Lexer$$anonfun$token$1$$anonfun$apply$2;
   0      22      1    $outer       Lscala/util/parsing/json/Lexer$$anonfun$token$1;


public final java.lang.Object apply(java.lang.Object);
  Signature: (Ljava/lang/Object;)Ljava/lang/Object;
  Code:
   Stack=2, Locals=2, Args_size=2
	aload_0
	aload_1
	checkcast	class scala/util/parsing/combinator/Parsers$$tilde
	invokevirtual	Method apply:(Lscala/util/parsing/combinator/Parsers$$tilde;)Lscala/util/parsing/syntax/Tokens$ErrorToken;
	areturn
  Labels:
  LocalVariableTable: 
   Start  Length  Slot  Name   Signature
   0      9      0    this       Lscala/util/parsing/json/Lexer$$anonfun$token$1$$anonfun$apply$2;
   0      9      1    v1       Ljava/lang/Object;


public final scala.util.parsing.syntax.Tokens$ErrorToken apply(scala.util.parsing.combinator.Parsers$$tilde);
  Signature: (Lscala/util/parsing/combinator/Parsers$$tilde;)Lscala/util/parsing/syntax/Tokens$ErrorToken;
  Code:
   Stack=5, Locals=5, Args_size=2
	aload_1
	ifnull	l1 // new
	aload_1
	invokevirtual	Method scala/util/parsing/combinator/Parsers$$tilde._1:()Ljava/lang/Object;
	checkcast	class java/lang/String
	astore_3
	aload_1
	invokevirtual	Method scala/util/parsing/combinator/Parsers$$tilde._2:()Ljava/lang/Object;
	invokestatic	Method scala/runtime/BoxesRunTime.unboxToChar:(Ljava/lang/Object;)C
	istore	4
	iconst_1
	ifeq	l2 // new
	new	class scala/util/parsing/syntax/Tokens$ErrorToken
	dup
	aload_0
	getfield	Field $outer:Lscala/util/parsing/json/Lexer$$anonfun$token$1;
	astore_2
	aload_2
	getfield	Field scala/util/parsing/json/Lexer$$anonfun$token$1.$outer:Lscala/util/parsing/json/Lexer;
	new	class scala/collection/mutable/StringBuilder
	dup
	invokespecial	Method scala/collection/mutable/StringBuilder."<init>":()V
	ldc	String Invalid number format : 
	invokevirtual	Method scala/collection/mutable/StringBuilder.append:(Ljava/lang/Object;)Lscala/collection/mutable/StringBuilder;
	aload_3
	invokevirtual	Method scala/collection/mutable/StringBuilder.append:(Ljava/lang/Object;)Lscala/collection/mutable/StringBuilder;
	iload	4
	invokestatic	Method scala/runtime/BoxesRunTime.boxToCharacter:(C)Ljava/lang/Character;
	invokevirtual	Method scala/collection/mutable/StringBuilder.append:(Ljava/lang/Object;)Lscala/collection/mutable/StringBuilder;
	invokevirtual	Method scala/collection/mutable/StringBuilder.toString:()Ljava/lang/String;
	invokespecial	Method scala/util/parsing/syntax/Tokens$ErrorToken."<init>":(Lscala/util/parsing/syntax/Tokens;Ljava/lang/String;)V
	areturn
l2	new	class scala/MatchError
	dup
	aload_1
	invokevirtual	Method scala/util/parsing/combinator/Parsers$$tilde.toString:()Ljava/lang/String;
	invokespecial	Method scala/MatchError."<init>":(Ljava/lang/String;)V
	athrow
l1	new	class scala/MatchError
	dup
	aload_1
	invokevirtual	Method scala/util/parsing/combinator/Parsers$$tilde.toString:()Ljava/lang/String;
	invokespecial	Method scala/MatchError."<init>":(Ljava/lang/String;)V
	athrow
  Labels:
   	l2 = 69 // new
   	l1 = 81 // new
  LocalVariableTable: 
   Start  Length  Slot  Name   Signature
   0      93      0    this       Lscala/util/parsing/json/Lexer$$anonfun$token$1$$anonfun$apply$2;
   12      69      3    temp2       Ljava/lang/String;
   21      60      4    temp3       C

  Signature: length = 0x2
   00 5A 

}

