Compiled from "Parser.scala"
public class scala.util.parsing.json.Parser extends java.lang.Object implements scala.util.parsing.combinator.syntactical.StdTokenParsers,scala.util.parsing.combinator.ImplicitConversions,scala.ScalaObject
  SourceFile: "Parser.scala"
  ScalaSig: length = 0x370
   05 00 FFFFFF81 04 06 08 01 02 FFFFFF84 FFFFFF80 FFFFFF80 FFFFFF80 00 0B 02 06
   50 61 72 73 65 72 0A 02 03 04 01 04 6A 73 6F 6E
   0A 02 05 06 01 07 70 61 72 73 69 6E 67 0A 02 07
   08 01 04 75 74 69 6C 0A 01 09 01 05 73 63 61 6C
   61 03 00 13 05 00 0C 14 1C 20 10 02 0D 12 0D 01
   0E 0A 02 0F 10 01 04 6C 61 6E 67 0A 01 11 01 04
   6A 61 76 61 09 02 13 0E 02 06 4F 62 6A 65 63 74
   10 02 15 1A 0D 01 16 0A 02 17 18 01 0B 73 79 6E
   74 61 63 74 69 63 61 6C 0A 02 19 04 01 0A 63 6F
   6D 62 69 6E 61 74 6F 72 09 02 1B 16 02 0F 53 74
   64 54 6F 6B 65 6E 50 61 72 73 65 72 73 10 02 1D
   1E 0D 01 18 09 02 1F 18 02 13 49 6D 70 6C 69 63
   69 74 43 6F 6E 76 65 72 73 69 6F 6E 73 10 02 21
   22 0D 01 08 09 02 23 08 02 0B 53 63 61 6C 61 4F
   62 6A 65 63 74 08 05 25 00 FFFFFF84 00 26 01 06 3C 69
   6E 69 74 3E 14 01 27 10 02 28 00 0D 01 02 05 08
   2A 00 FFFFFF84 FFFFFF80 FFFFFF80 FFFFFF80 00 2B 02 06 54 6F 6B 65 6E 73
   10 02 28 2C 09 02 2D 02 02 05 4C 65 78 65 72 08
   07 2F 00 FFFFFFC2 FFFFFF80 FFFFFF84 00 30 01 07 6C 65 78 69 63 61
   6C 15 01 2B 08 06 32 00 FFFFFFA0 FFFFFF80 04 2B 01 08 6C 65
   78 69 63 61 6C 20 05 08 34 00 FFFFFF84 FFFFFF80 FFFFFF80 FFFFFF80 00 35
   02 0D 4E 75 6D 65 72 69 63 50 61 72 73 65 72 10
   04 21 36 38 3F 09 02 37 08 02 09 46 75 6E 63 74
   69 6F 6E 31 10 02 39 3C 0E 02 21 3A 09 02 3B 08
   01 06 50 72 65 64 65 66 09 02 3D 3E 02 06 53 74
   72 69 6E 67 0A 02 3B 08 10 02 21 40 09 02 41 08
   02 03 41 6E 79 08 07 43 00 FFFFFFC0 FFFFFF80 FFFFFF84 08 44 01 13
   64 65 66 61 75 6C 74 4E 75 6D 62 65 72 50 61 72
   73 65 72 15 01 45 10 02 46 33 0D 01 00 08 07 48
   00 FFFFFFC0 FFFFFF80 FFFFFF84 08 49 01 17 64 65 66 61 75 6C 74 4E
   75 6D 62 65 72 50 61 72 73 65 72 5F 24 65 71 14
   02 4A 4D 10 02 21 4B 09 02 4C 08 02 04 55 6E 69
   74 08 07 4E 47 FFFFFF81 FFFFFF80 FFFFFFC0 00 45 01 03 78 24 31 08
   06 50 00 FFFFFFA0 FFFFFFA0 04 45 01 14 64 65 66 61 75 6C 74
   4E 75 6D 62 65 72 50 61 72 73 65 72 20 08 07 52
   00 FFFFFFC2 FFFFFF80 FFFFFF84 08 53 01 0C 6E 75 6D 62 65 72 50 61
   72 73 65 72 15 01 54 10 03 0D 55 45 09 02 56 0E
   02 0B 54 68 72 65 61 64 4C 6F 63 61 6C 08 06 58
   00 FFFFFFA0 FFFFFF80 04 54 01 0D 6E 75 6D 62 65 72 50 61 72
   73 65 72 20 08 05 5A 00 FFFFFF84 00 5B 01 04 72 6F 6F
   74 15 01 5C 10 03 46 5D 60 09 02 01 5E 09 02 5F
   18 02 07 50 61 72 73 65 72 73 10 03 61 69 3F 0E
   02 62 67 0E 02 63 66 0D 01 64 0A 02 65 0A 01 06
   3C 72 6F 6F 74 3E 09 01 09 09 02 68 08 01 07 70
   61 63 6B 61 67 65 09 02 6A 6B 02 04 4C 69 73 74
   0A 02 68 08 08 05 6D 00 FFFFFF84 00 6E 01 07 6A 73 6F
   6E 4F 62 6A 15 01 6F 10 03 46 5D 70 10 03 61 69
   71 10 04 21 72 38 3F 09 02 73 08 02 06 54 75 70
   6C 65 32 08 05 75 00 FFFFFF84 00 5B 01 09 6A 73 6F 6E
   41 72 72 61 79 08 05 77 00 FFFFFF84 00 78 01 08 6F 62
   6A 45 6E 74 72 79 15 01 79 10 03 46 5D 71 08 05
   7B 00 FFFFFF84 00 7C 01 05 76 61 6C 75 65 15 01 7D 10
   03 46 5D 3F 08 06 7F 00 FFFFFF84 00 FFFFFF81 00 01 09 73 74
   72 69 6E 67 56 61 6C 15 02 FFFFFF81 01 10 03 46 5D 38
   08 06 FFFFFF81 03 00 FFFFFF84 00 7C 01 06 6E 75 6D 62 65 72
   
  InnerClass: 
   public abstract #362= #156 of #135; //Parser=class scala/util/parsing/combinator/Parsers$Parser of class scala/util/parsing/combinator/Parsers
   public final #454= #123 of #54; //$anon$1=class scala/util/parsing/json/Parser$$anon$1 of class scala/util/parsing/json/Parser
   public final #455= #116 of #54; //$anonfun$1=class scala/util/parsing/json/Parser$$anonfun$1 of class scala/util/parsing/json/Parser
   public abstract #386= #457 of #135; //NoSuccess=class scala/util/parsing/combinator/Parsers$NoSuccess of class scala/util/parsing/combinator/Parsers
   public final #458= #222 of #54; //$anonfun$root$1=class scala/util/parsing/json/Parser$$anonfun$root$1 of class scala/util/parsing/json/Parser
   public final #459= #174 of #54; //$anonfun$value$6=class scala/util/parsing/json/Parser$$anonfun$value$6 of class scala/util/parsing/json/Parser
   public final #460= #171 of #54; //$anonfun$value$5=class scala/util/parsing/json/Parser$$anonfun$value$5 of class scala/util/parsing/json/Parser
   public final #461= #168 of #54; //$anonfun$value$4=class scala/util/parsing/json/Parser$$anonfun$value$4 of class scala/util/parsing/json/Parser
   public final #462= #165 of #54; //$anonfun$value$3=class scala/util/parsing/json/Parser$$anonfun$value$3 of class scala/util/parsing/json/Parser
   public final #463= #162 of #54; //$anonfun$value$2=class scala/util/parsing/json/Parser$$anonfun$value$2 of class scala/util/parsing/json/Parser
   public final #464= #153 of #54; //$anonfun$value$1=class scala/util/parsing/json/Parser$$anonfun$value$1 of class scala/util/parsing/json/Parser
   public final #465= #132 of #54; //$anonfun$number$1=class scala/util/parsing/json/Parser$$anonfun$number$1 of class scala/util/parsing/json/Parser
   public final #466= #217 of #54; //$anonfun$jsonObj$2=class scala/util/parsing/json/Parser$$anonfun$jsonObj$2 of class scala/util/parsing/json/Parser
   public final #467= #214 of #54; //$anonfun$jsonObj$1=class scala/util/parsing/json/Parser$$anonfun$jsonObj$1 of class scala/util/parsing/json/Parser
   public final #468= #186 of #54; //$anonfun$objEntry$2=class scala/util/parsing/json/Parser$$anonfun$objEntry$2 of class scala/util/parsing/json/Parser
   public final #469= #180 of #54; //$anonfun$objEntry$1=class scala/util/parsing/json/Parser$$anonfun$objEntry$1 of class scala/util/parsing/json/Parser
   public final #470= #207 of #54; //$anonfun$jsonArray$2=class scala/util/parsing/json/Parser$$anonfun$jsonArray$2 of class scala/util/parsing/json/Parser
   public final #471= #201 of #54; //$anonfun$jsonArray$1=class scala/util/parsing/json/Parser$$anonfun$jsonArray$1 of class scala/util/parsing/json/Parser
   public final #472= #145 of #54; //$anonfun$stringVal$1=class scala/util/parsing/json/Parser$$anonfun$stringVal$1 of class scala/util/parsing/json/Parser
  minor version: 0
  major version: 49
  Constant pool:
const #1 = Asciz	SourceFile;
const #2 = Asciz	Parser.scala;
const #3 = Asciz	$tilde$module;
const #4 = Asciz	Lscala/util/parsing/combinator/Parsers$$tilde$;;
const #5 = Asciz	Error$module;
const #6 = Asciz	Lscala/util/parsing/combinator/Parsers$Error$;;
const #7 = Asciz	Failure$module;
const #8 = Asciz	Lscala/util/parsing/combinator/Parsers$Failure$;;
const #9 = Asciz	NoSuccess$module;
const #10 = Asciz	Lscala/util/parsing/combinator/Parsers$NoSuccess$;;
const #11 = Asciz	Success$module;
const #12 = Asciz	Lscala/util/parsing/combinator/Parsers$Success$;;
const #13 = Asciz	lastNoSuccess;
const #14 = Asciz	Lscala/util/parsing/combinator/Parsers$NoSuccess;;
const #15 = Asciz	keywordCache;
const #16 = Asciz	Lscala/collection/mutable/HashMap;;
const #17 = Asciz	numberParser;
const #18 = Asciz	Ljava/lang/ThreadLocal;;
const #19 = Asciz	Ljava/lang/ThreadLocal<Lscala/Function1<Ljava/lang/String;Ljava/lang/Object;>;>;;
const #20 = Asciz	Signature;
const #21 = Asciz	defaultNumberParser;
const #22 = Asciz	Lscala/Function1;;
const #23 = Asciz	Lscala/Function1<Ljava/lang/String;Ljava/lang/Object;>;;
const #24 = Asciz	lexical;
const #25 = Asciz	Lscala/util/parsing/json/Lexer;;
const #26 = Asciz	<init>;
const #27 = Asciz	()V;
const #28 = Asciz	Code;
const #29 = Asciz	LineNumberTable;
const #30 = Asciz	java/lang/Object;
const #31 = class	#30;	//  java/lang/Object
const #32 = NameAndType	#26:#27;//  "<init>":()V
const #33 = Method	#31.#32;	//  java/lang/Object."<init>":()V
const #34 = Asciz	scala/util/parsing/combinator/Parsers$class;
const #35 = class	#34;	//  scala/util/parsing/combinator/Parsers$class
const #36 = Asciz	$init$;
const #37 = Asciz	(Lscala/util/parsing/combinator/Parsers;)V;
const #38 = NameAndType	#36:#37;//  $init$:(Lscala/util/parsing/combinator/Parsers;)V
const #39 = Method	#35.#38;	//  scala/util/parsing/combinator/Parsers$class.$init$:(Lscala/util/parsing/combinator/Parsers;)V
const #40 = Asciz	scala/util/parsing/combinator/syntactical/StdTokenParsers$class;
const #41 = class	#40;	//  scala/util/parsing/combinator/syntactical/StdTokenParsers$class
const #42 = Asciz	(Lscala/util/parsing/combinator/syntactical/StdTokenParsers;)V;
const #43 = NameAndType	#36:#42;//  $init$:(Lscala/util/parsing/combinator/syntactical/StdTokenParsers;)V
const #44 = Method	#41.#43;	//  scala/util/parsing/combinator/syntactical/StdTokenParsers$class.$init$:(Lscala/util/parsing/combinator/syntactical/StdTokenParsers;)V
const #45 = Asciz	scala/util/parsing/combinator/ImplicitConversions$class;
const #46 = class	#45;	//  scala/util/parsing/combinator/ImplicitConversions$class
const #47 = Asciz	(Lscala/util/parsing/combinator/ImplicitConversions;)V;
const #48 = NameAndType	#36:#47;//  $init$:(Lscala/util/parsing/combinator/ImplicitConversions;)V
const #49 = Method	#46.#48;	//  scala/util/parsing/combinator/ImplicitConversions$class.$init$:(Lscala/util/parsing/combinator/ImplicitConversions;)V
const #50 = Asciz	scala/util/parsing/json/Lexer;
const #51 = class	#50;	//  scala/util/parsing/json/Lexer
const #52 = Method	#51.#32;	//  scala/util/parsing/json/Lexer."<init>":()V
const #53 = Asciz	scala/util/parsing/json/Parser;
const #54 = class	#53;	//  scala/util/parsing/json/Parser
const #55 = NameAndType	#24:#25;//  lexical:Lscala/util/parsing/json/Lexer;
const #56 = Field	#54.#55;	//  scala/util/parsing/json/Parser.lexical:Lscala/util/parsing/json/Lexer;
const #57 = Asciz	()Lscala/util/parsing/json/Lexer;;
const #58 = NameAndType	#24:#57;//  lexical:()Lscala/util/parsing/json/Lexer;
const #59 = Method	#54.#58;	//  scala/util/parsing/json/Parser.lexical:()Lscala/util/parsing/json/Lexer;
const #60 = Asciz	reserved;
const #61 = Asciz	()Lscala/collection/mutable/HashSet;;
const #62 = NameAndType	#60:#61;//  reserved:()Lscala/collection/mutable/HashSet;
const #63 = Method	#51.#62;	//  scala/util/parsing/json/Lexer.reserved:()Lscala/collection/mutable/HashSet;
const #64 = Asciz	scala/collection/immutable/List$;
const #65 = class	#64;	//  scala/collection/immutable/List$
const #66 = Asciz	MODULE$;
const #67 = Asciz	Lscala/collection/immutable/List$;;
const #68 = NameAndType	#66:#67;//  MODULE$:Lscala/collection/immutable/List$;
const #69 = Field	#65.#68;	//  scala/collection/immutable/List$.MODULE$:Lscala/collection/immutable/List$;
const #70 = Asciz	scala/Predef$;
const #71 = class	#70;	//  scala/Predef$
const #72 = Asciz	Lscala/Predef$;;
const #73 = NameAndType	#66:#72;//  MODULE$:Lscala/Predef$;
const #74 = Field	#71.#73;	//  scala/Predef$.MODULE$:Lscala/Predef$;
const #75 = Asciz	java/lang/String;
const #76 = class	#75;	//  java/lang/String
const #77 = Asciz	true;
const #78 = String	#77;	//  true
const #79 = Asciz	false;
const #80 = String	#79;	//  false
const #81 = Asciz	null;
const #82 = String	#81;	//  null
const #83 = Asciz	[Ljava/lang/Object;;
const #84 = class	#83;	//  "[Ljava/lang/Object;"
const #85 = Asciz	wrapRefArray;
const #86 = Asciz	([Ljava/lang/Object;)Lscala/collection/mutable/WrappedArray;;
const #87 = NameAndType	#85:#86;//  wrapRefArray:([Ljava/lang/Object;)Lscala/collection/mutable/WrappedArray;
const #88 = Method	#71.#87;	//  scala/Predef$.wrapRefArray:([Ljava/lang/Object;)Lscala/collection/mutable/WrappedArray;
const #89 = Asciz	apply;
const #90 = Asciz	(Lscala/collection/Seq;)Lscala/collection/immutable/List;;
const #91 = NameAndType	#89:#90;//  apply:(Lscala/collection/Seq;)Lscala/collection/immutable/List;
const #92 = Method	#65.#91;	//  scala/collection/immutable/List$.apply:(Lscala/collection/Seq;)Lscala/collection/immutable/List;
const #93 = Asciz	scala/collection/generic/Growable;
const #94 = class	#93;	//  scala/collection/generic/Growable
const #95 = Asciz	$plus$plus$eq;
const #96 = Asciz	(Lscala/collection/Traversable;)Lscala/collection/generic/Growable;;
const #97 = NameAndType	#95:#96;//  $plus$plus$eq:(Lscala/collection/Traversable;)Lscala/collection/generic/Growable;
const #98 = InterfaceMethod	#94.#97;	//  scala/collection/generic/Growable.$plus$plus$eq:(Lscala/collection/Traversable;)Lscala/collection/generic/Growable;
const #99 = Asciz	delimiters;
const #100 = NameAndType	#99:#61;//  delimiters:()Lscala/collection/mutable/HashSet;
const #101 = Method	#51.#100;	//  scala/util/parsing/json/Lexer.delimiters:()Lscala/collection/mutable/HashSet;
const #102 = int	6;
const #103 = Asciz	{;
const #104 = String	#103;	//  {
const #105 = Asciz	};
const #106 = String	#105;	//  }
const #107 = Asciz	[;
const #108 = String	#107;	//  [
const #109 = Asciz	];
const #110 = String	#109;	//  ]
const #111 = Asciz	:;
const #112 = String	#111;	//  :
const #113 = Asciz	,;
const #114 = String	#113;	//  ,
const #115 = Asciz	scala/util/parsing/json/Parser$$anonfun$1;
const #116 = class	#115;	//  scala/util/parsing/json/Parser$$anonfun$1
const #117 = Asciz	(Lscala/util/parsing/json/Parser;)V;
const #118 = NameAndType	#26:#117;//  "<init>":(Lscala/util/parsing/json/Parser;)V
const #119 = Method	#116.#118;	//  scala/util/parsing/json/Parser$$anonfun$1."<init>":(Lscala/util/parsing/json/Parser;)V
const #120 = NameAndType	#21:#22;//  defaultNumberParser:Lscala/Function1;
const #121 = Field	#54.#120;	//  scala/util/parsing/json/Parser.defaultNumberParser:Lscala/Function1;
const #122 = Asciz	scala/util/parsing/json/Parser$$anon$1;
const #123 = class	#122;	//  scala/util/parsing/json/Parser$$anon$1
const #124 = Method	#123.#118;	//  scala/util/parsing/json/Parser$$anon$1."<init>":(Lscala/util/parsing/json/Parser;)V
const #125 = NameAndType	#17:#18;//  numberParser:Ljava/lang/ThreadLocal;
const #126 = Field	#54.#125;	//  scala/util/parsing/json/Parser.numberParser:Ljava/lang/ThreadLocal;
const #127 = Asciz	()Lscala/util/parsing/syntax/Tokens;;
const #128 = Asciz	number;
const #129 = Asciz	()Lscala/util/parsing/combinator/Parsers$Parser;;
const #130 = String	#128;	//  number
const #131 = Asciz	scala/util/parsing/json/Parser$$anonfun$number$1;
const #132 = class	#131;	//  scala/util/parsing/json/Parser$$anonfun$number$1
const #133 = Method	#132.#118;	//  scala/util/parsing/json/Parser$$anonfun$number$1."<init>":(Lscala/util/parsing/json/Parser;)V
const #134 = Asciz	scala/util/parsing/combinator/Parsers;
const #135 = class	#134;	//  scala/util/parsing/combinator/Parsers
const #136 = Asciz	accept;
const #137 = Asciz	(Ljava/lang/String;Lscala/PartialFunction;)Lscala/util/parsing/combinator/Parsers$Parser;;
const #138 = NameAndType	#136:#137;//  accept:(Ljava/lang/String;Lscala/PartialFunction;)Lscala/util/parsing/combinator/Parsers$Parser;
const #139 = InterfaceMethod	#135.#138;	//  scala/util/parsing/combinator/Parsers.accept:(Ljava/lang/String;Lscala/PartialFunction;)Lscala/util/parsing/combinator/Parsers$Parser;
const #140 = Asciz	()Lscala/util/parsing/combinator/Parsers$Parser<Ljava/lang/Object;>;;
const #141 = Asciz	stringVal;
const #142 = Asciz	string;
const #143 = String	#142;	//  string
const #144 = Asciz	scala/util/parsing/json/Parser$$anonfun$stringVal$1;
const #145 = class	#144;	//  scala/util/parsing/json/Parser$$anonfun$stringVal$1
const #146 = Method	#145.#118;	//  scala/util/parsing/json/Parser$$anonfun$stringVal$1."<init>":(Lscala/util/parsing/json/Parser;)V
const #147 = Asciz	()Lscala/util/parsing/combinator/Parsers$Parser<Ljava/lang/String;>;;
const #148 = Asciz	value;
const #149 = Asciz	jsonObj;
const #150 = NameAndType	#149:#129;//  jsonObj:()Lscala/util/parsing/combinator/Parsers$Parser;
const #151 = Method	#54.#150;	//  scala/util/parsing/json/Parser.jsonObj:()Lscala/util/parsing/combinator/Parsers$Parser;
const #152 = Asciz	scala/util/parsing/json/Parser$$anonfun$value$1;
const #153 = class	#152;	//  scala/util/parsing/json/Parser$$anonfun$value$1
const #154 = Method	#153.#118;	//  scala/util/parsing/json/Parser$$anonfun$value$1."<init>":(Lscala/util/parsing/json/Parser;)V
const #155 = Asciz	scala/util/parsing/combinator/Parsers$Parser;
const #156 = class	#155;	//  scala/util/parsing/combinator/Parsers$Parser
const #157 = Asciz	$bar;
const #158 = Asciz	(Lscala/Function0;)Lscala/util/parsing/combinator/Parsers$Parser;;
const #159 = NameAndType	#157:#158;//  $bar:(Lscala/Function0;)Lscala/util/parsing/combinator/Parsers$Parser;
const #160 = Method	#156.#159;	//  scala/util/parsing/combinator/Parsers$Parser.$bar:(Lscala/Function0;)Lscala/util/parsing/combinator/Parsers$Parser;
const #161 = Asciz	scala/util/parsing/json/Parser$$anonfun$value$2;
const #162 = class	#161;	//  scala/util/parsing/json/Parser$$anonfun$value$2
const #163 = Method	#162.#118;	//  scala/util/parsing/json/Parser$$anonfun$value$2."<init>":(Lscala/util/parsing/json/Parser;)V
const #164 = Asciz	scala/util/parsing/json/Parser$$anonfun$value$3;
const #165 = class	#164;	//  scala/util/parsing/json/Parser$$anonfun$value$3
const #166 = Method	#165.#118;	//  scala/util/parsing/json/Parser$$anonfun$value$3."<init>":(Lscala/util/parsing/json/Parser;)V
const #167 = Asciz	scala/util/parsing/json/Parser$$anonfun$value$4;
const #168 = class	#167;	//  scala/util/parsing/json/Parser$$anonfun$value$4
const #169 = Method	#168.#118;	//  scala/util/parsing/json/Parser$$anonfun$value$4."<init>":(Lscala/util/parsing/json/Parser;)V
const #170 = Asciz	scala/util/parsing/json/Parser$$anonfun$value$5;
const #171 = class	#170;	//  scala/util/parsing/json/Parser$$anonfun$value$5
const #172 = Method	#171.#118;	//  scala/util/parsing/json/Parser$$anonfun$value$5."<init>":(Lscala/util/parsing/json/Parser;)V
const #173 = Asciz	scala/util/parsing/json/Parser$$anonfun$value$6;
const #174 = class	#173;	//  scala/util/parsing/json/Parser$$anonfun$value$6
const #175 = Method	#174.#118;	//  scala/util/parsing/json/Parser$$anonfun$value$6."<init>":(Lscala/util/parsing/json/Parser;)V
const #176 = Asciz	objEntry;
const #177 = NameAndType	#141:#129;//  stringVal:()Lscala/util/parsing/combinator/Parsers$Parser;
const #178 = Method	#54.#177;	//  scala/util/parsing/json/Parser.stringVal:()Lscala/util/parsing/combinator/Parsers$Parser;
const #179 = Asciz	scala/util/parsing/json/Parser$$anonfun$objEntry$1;
const #180 = class	#179;	//  scala/util/parsing/json/Parser$$anonfun$objEntry$1
const #181 = Method	#180.#118;	//  scala/util/parsing/json/Parser$$anonfun$objEntry$1."<init>":(Lscala/util/parsing/json/Parser;)V
const #182 = Asciz	$tilde;
const #183 = NameAndType	#182:#158;//  $tilde:(Lscala/Function0;)Lscala/util/parsing/combinator/Parsers$Parser;
const #184 = Method	#156.#183;	//  scala/util/parsing/combinator/Parsers$Parser.$tilde:(Lscala/Function0;)Lscala/util/parsing/combinator/Parsers$Parser;
const #185 = Asciz	scala/util/parsing/json/Parser$$anonfun$objEntry$2;
const #186 = class	#185;	//  scala/util/parsing/json/Parser$$anonfun$objEntry$2
const #187 = Method	#186.#118;	//  scala/util/parsing/json/Parser$$anonfun$objEntry$2."<init>":(Lscala/util/parsing/json/Parser;)V
const #188 = Asciz	$up$up;
const #189 = Asciz	(Lscala/Function1;)Lscala/util/parsing/combinator/Parsers$Parser;;
const #190 = NameAndType	#188:#189;//  $up$up:(Lscala/Function1;)Lscala/util/parsing/combinator/Parsers$Parser;
const #191 = Method	#156.#190;	//  scala/util/parsing/combinator/Parsers$Parser.$up$up:(Lscala/Function1;)Lscala/util/parsing/combinator/Parsers$Parser;
const #192 = Asciz	()Lscala/util/parsing/combinator/Parsers$Parser<Lscala/Tuple2<Ljava/lang/String;Ljava/lang/Object;>;>;;
const #193 = Asciz	jsonArray;
const #194 = Asciz	scala/util/parsing/combinator/syntactical/StdTokenParsers;
const #195 = class	#194;	//  scala/util/parsing/combinator/syntactical/StdTokenParsers
const #196 = Asciz	keyword;
const #197 = Asciz	(Ljava/lang/String;)Lscala/util/parsing/combinator/Parsers$Parser;;
const #198 = NameAndType	#196:#197;//  keyword:(Ljava/lang/String;)Lscala/util/parsing/combinator/Parsers$Parser;
const #199 = InterfaceMethod	#195.#198;	//  scala/util/parsing/combinator/syntactical/StdTokenParsers.keyword:(Ljava/lang/String;)Lscala/util/parsing/combinator/Parsers$Parser;
const #200 = Asciz	scala/util/parsing/json/Parser$$anonfun$jsonArray$1;
const #201 = class	#200;	//  scala/util/parsing/json/Parser$$anonfun$jsonArray$1
const #202 = Method	#201.#118;	//  scala/util/parsing/json/Parser$$anonfun$jsonArray$1."<init>":(Lscala/util/parsing/json/Parser;)V
const #203 = Asciz	$tilde$greater;
const #204 = NameAndType	#203:#158;//  $tilde$greater:(Lscala/Function0;)Lscala/util/parsing/combinator/Parsers$Parser;
const #205 = Method	#156.#204;	//  scala/util/parsing/combinator/Parsers$Parser.$tilde$greater:(Lscala/Function0;)Lscala/util/parsing/combinator/Parsers$Parser;
const #206 = Asciz	scala/util/parsing/json/Parser$$anonfun$jsonArray$2;
const #207 = class	#206;	//  scala/util/parsing/json/Parser$$anonfun$jsonArray$2
const #208 = Method	#207.#118;	//  scala/util/parsing/json/Parser$$anonfun$jsonArray$2."<init>":(Lscala/util/parsing/json/Parser;)V
const #209 = Asciz	$less$tilde;
const #210 = NameAndType	#209:#158;//  $less$tilde:(Lscala/Function0;)Lscala/util/parsing/combinator/Parsers$Parser;
const #211 = Method	#156.#210;	//  scala/util/parsing/combinator/Parsers$Parser.$less$tilde:(Lscala/Function0;)Lscala/util/parsing/combinator/Parsers$Parser;
const #212 = Asciz	()Lscala/util/parsing/combinator/Parsers$Parser<Lscala/collection/immutable/List<Ljava/lang/Object;>;>;;
const #213 = Asciz	scala/util/parsing/json/Parser$$anonfun$jsonObj$1;
const #214 = class	#213;	//  scala/util/parsing/json/Parser$$anonfun$jsonObj$1
const #215 = Method	#214.#118;	//  scala/util/parsing/json/Parser$$anonfun$jsonObj$1."<init>":(Lscala/util/parsing/json/Parser;)V
const #216 = Asciz	scala/util/parsing/json/Parser$$anonfun$jsonObj$2;
const #217 = class	#216;	//  scala/util/parsing/json/Parser$$anonfun$jsonObj$2
const #218 = Method	#217.#118;	//  scala/util/parsing/json/Parser$$anonfun$jsonObj$2."<init>":(Lscala/util/parsing/json/Parser;)V
const #219 = Asciz	()Lscala/util/parsing/combinator/Parsers$Parser<Lscala/collection/immutable/List<Lscala/Tuple2<Ljava/lang/String;Ljava/lang/Object;>;>;>;;
const #220 = Asciz	root;
const #221 = Asciz	scala/util/parsing/json/Parser$$anonfun$root$1;
const #222 = class	#221;	//  scala/util/parsing/json/Parser$$anonfun$root$1
const #223 = Method	#222.#118;	//  scala/util/parsing/json/Parser$$anonfun$root$1."<init>":(Lscala/util/parsing/json/Parser;)V
const #224 = Asciz	()Ljava/lang/ThreadLocal;;
const #225 = Asciz	()Ljava/lang/ThreadLocal<Lscala/Function1<Ljava/lang/String;Ljava/lang/Object;>;>;;
const #226 = Asciz	defaultNumberParser_$eq;
const #227 = Asciz	(Lscala/Function1;)V;
const #228 = Asciz	(Lscala/Function1<Ljava/lang/String;Ljava/lang/Object;>;)V;
const #229 = Asciz	()Lscala/Function1;;
const #230 = Asciz	()Lscala/Function1<Ljava/lang/String;Ljava/lang/Object;>;;
const #231 = Asciz	mkList;
const #232 = Asciz	(Lscala/util/parsing/combinator/Parsers;)Lscala/Function1;;
const #233 = NameAndType	#231:#232;//  mkList:(Lscala/util/parsing/combinator/Parsers;)Lscala/Function1;
const #234 = Method	#35.#233;	//  scala/util/parsing/combinator/Parsers$class.mkList:(Lscala/util/parsing/combinator/Parsers;)Lscala/Function1;
const #235 = Asciz	phrase;
const #236 = Asciz	(Lscala/util/parsing/combinator/Parsers$Parser;)Lscala/util/parsing/combinator/Parsers$Parser;;
const #237 = Asciz	(Lscala/util/parsing/combinator/Parsers;Lscala/util/parsing/combinator/Parsers$Parser;)Lscala/util/parsing/combinator/Parsers$Parser;;
const #238 = NameAndType	#235:#237;//  phrase:(Lscala/util/parsing/combinator/Parsers;Lscala/util/parsing/combinator/Parsers$Parser;)Lscala/util/parsing/combinator/Parsers$Parser;
const #239 = Method	#35.#238;	//  scala/util/parsing/combinator/Parsers$class.phrase:(Lscala/util/parsing/combinator/Parsers;Lscala/util/parsing/combinator/Parsers$Parser;)Lscala/util/parsing/combinator/Parsers$Parser;
const #240 = Asciz	this;
const #241 = Asciz	Lscala/util/parsing/json/Parser;;
const #242 = Asciz	p;
const #243 = Asciz	Lscala/util/parsing/combinator/Parsers$Parser;;
const #244 = Asciz	LocalVariableTable;
const #245 = Asciz	positioned;
const #246 = Asciz	(Lscala/util/parsing/combinator/Parsers;Lscala/Function0;)Lscala/util/parsing/combinator/Parsers$Parser;;
const #247 = NameAndType	#245:#246;//  positioned:(Lscala/util/parsing/combinator/Parsers;Lscala/Function0;)Lscala/util/parsing/combinator/Parsers$Parser;
const #248 = Method	#35.#247;	//  scala/util/parsing/combinator/Parsers$class.positioned:(Lscala/util/parsing/combinator/Parsers;Lscala/Function0;)Lscala/util/parsing/combinator/Parsers$Parser;
const #249 = Asciz	Lscala/Function0;;
const #250 = Asciz	guard;
const #251 = NameAndType	#250:#246;//  guard:(Lscala/util/parsing/combinator/Parsers;Lscala/Function0;)Lscala/util/parsing/combinator/Parsers$Parser;
const #252 = Method	#35.#251;	//  scala/util/parsing/combinator/Parsers$class.guard:(Lscala/util/parsing/combinator/Parsers;Lscala/Function0;)Lscala/util/parsing/combinator/Parsers$Parser;
const #253 = Asciz	not;
const #254 = NameAndType	#253:#246;//  not:(Lscala/util/parsing/combinator/Parsers;Lscala/Function0;)Lscala/util/parsing/combinator/Parsers$Parser;
const #255 = Method	#35.#254;	//  scala/util/parsing/combinator/Parsers$class.not:(Lscala/util/parsing/combinator/Parsers;Lscala/Function0;)Lscala/util/parsing/combinator/Parsers$Parser;
const #256 = Asciz	opt;
const #257 = NameAndType	#256:#246;//  opt:(Lscala/util/parsing/combinator/Parsers;Lscala/Function0;)Lscala/util/parsing/combinator/Parsers$Parser;
const #258 = Method	#35.#257;	//  scala/util/parsing/combinator/Parsers$class.opt:(Lscala/util/parsing/combinator/Parsers;Lscala/Function0;)Lscala/util/parsing/combinator/Parsers$Parser;
const #259 = Asciz	chainr1;
const #260 = Asciz	(Lscala/Function0;Lscala/Function0;Lscala/Function2;Ljava/lang/Object;)Lscala/util/parsing/combinator/Parsers$Parser;;
const #261 = Asciz	(Lscala/util/parsing/combinator/Parsers;Lscala/Function0;Lscala/Function0;Lscala/Function2;Ljava/lang/Object;)Lscala/util/parsing/combinator/Parsers$Parser;;
const #262 = NameAndType	#259:#261;//  chainr1:(Lscala/util/parsing/combinator/Parsers;Lscala/Function0;Lscala/Function0;Lscala/Function2;Ljava/lang/Object;)Lscala/util/parsing/combinator/Parsers$Parser;
const #263 = Method	#35.#262;	//  scala/util/parsing/combinator/Parsers$class.chainr1:(Lscala/util/parsing/combinator/Parsers;Lscala/Function0;Lscala/Function0;Lscala/Function2;Ljava/lang/Object;)Lscala/util/parsing/combinator/Parsers$Parser;
const #264 = Asciz	q;
const #265 = Asciz	combine;
const #266 = Asciz	Lscala/Function2;;
const #267 = Asciz	first;
const #268 = Asciz	Ljava/lang/Object;;
const #269 = Asciz	chainl1;
const #270 = Asciz	(Lscala/Function0;Lscala/Function0;Lscala/Function0;)Lscala/util/parsing/combinator/Parsers$Parser;;
const #271 = Asciz	(Lscala/util/parsing/combinator/Parsers;Lscala/Function0;Lscala/Function0;Lscala/Function0;)Lscala/util/parsing/combinator/Parsers$Parser;;
const #272 = NameAndType	#269:#271;//  chainl1:(Lscala/util/parsing/combinator/Parsers;Lscala/Function0;Lscala/Function0;Lscala/Function0;)Lscala/util/parsing/combinator/Parsers$Parser;
const #273 = Method	#35.#272;	//  scala/util/parsing/combinator/Parsers$class.chainl1:(Lscala/util/parsing/combinator/Parsers;Lscala/Function0;Lscala/Function0;Lscala/Function0;)Lscala/util/parsing/combinator/Parsers$Parser;
const #274 = Asciz	(Lscala/Function0;Lscala/Function0;)Lscala/util/parsing/combinator/Parsers$Parser;;
const #275 = Asciz	(Lscala/util/parsing/combinator/Parsers;Lscala/Function0;Lscala/Function0;)Lscala/util/parsing/combinator/Parsers$Parser;;
const #276 = NameAndType	#269:#275;//  chainl1:(Lscala/util/parsing/combinator/Parsers;Lscala/Function0;Lscala/Function0;)Lscala/util/parsing/combinator/Parsers$Parser;
const #277 = Method	#35.#276;	//  scala/util/parsing/combinator/Parsers$class.chainl1:(Lscala/util/parsing/combinator/Parsers;Lscala/Function0;Lscala/Function0;)Lscala/util/parsing/combinator/Parsers$Parser;
const #278 = Asciz	rep1sep;
const #279 = NameAndType	#278:#275;//  rep1sep:(Lscala/util/parsing/combinator/Parsers;Lscala/Function0;Lscala/Function0;)Lscala/util/parsing/combinator/Parsers$Parser;
const #280 = Method	#35.#279;	//  scala/util/parsing/combinator/Parsers$class.rep1sep:(Lscala/util/parsing/combinator/Parsers;Lscala/Function0;Lscala/Function0;)Lscala/util/parsing/combinator/Parsers$Parser;
const #281 = Asciz	repN;
const #282 = Asciz	(ILscala/Function0;)Lscala/util/parsing/combinator/Parsers$Parser;;
const #283 = Asciz	(Lscala/util/parsing/combinator/Parsers;ILscala/Function0;)Lscala/util/parsing/combinator/Parsers$Parser;;
const #284 = NameAndType	#281:#283;//  repN:(Lscala/util/parsing/combinator/Parsers;ILscala/Function0;)Lscala/util/parsing/combinator/Parsers$Parser;
const #285 = Method	#35.#284;	//  scala/util/parsing/combinator/Parsers$class.repN:(Lscala/util/parsing/combinator/Parsers;ILscala/Function0;)Lscala/util/parsing/combinator/Parsers$Parser;
const #286 = Asciz	n;
const #287 = Asciz	I;
const #288 = Asciz	rep1;
const #289 = NameAndType	#288:#275;//  rep1:(Lscala/util/parsing/combinator/Parsers;Lscala/Function0;Lscala/Function0;)Lscala/util/parsing/combinator/Parsers$Parser;
const #290 = Method	#35.#289;	//  scala/util/parsing/combinator/Parsers$class.rep1:(Lscala/util/parsing/combinator/Parsers;Lscala/Function0;Lscala/Function0;)Lscala/util/parsing/combinator/Parsers$Parser;
const #291 = NameAndType	#288:#246;//  rep1:(Lscala/util/parsing/combinator/Parsers;Lscala/Function0;)Lscala/util/parsing/combinator/Parsers$Parser;
const #292 = Method	#35.#291;	//  scala/util/parsing/combinator/Parsers$class.rep1:(Lscala/util/parsing/combinator/Parsers;Lscala/Function0;)Lscala/util/parsing/combinator/Parsers$Parser;
const #293 = Asciz	repsep;
const #294 = NameAndType	#293:#275;//  repsep:(Lscala/util/parsing/combinator/Parsers;Lscala/Function0;Lscala/Function0;)Lscala/util/parsing/combinator/Parsers$Parser;
const #295 = Method	#35.#294;	//  scala/util/parsing/combinator/Parsers$class.repsep:(Lscala/util/parsing/combinator/Parsers;Lscala/Function0;Lscala/Function0;)Lscala/util/parsing/combinator/Parsers$Parser;
const #296 = Asciz	rep;
const #297 = NameAndType	#296:#246;//  rep:(Lscala/util/parsing/combinator/Parsers;Lscala/Function0;)Lscala/util/parsing/combinator/Parsers$Parser;
const #298 = Method	#35.#297;	//  scala/util/parsing/combinator/Parsers$class.rep:(Lscala/util/parsing/combinator/Parsers;Lscala/Function0;)Lscala/util/parsing/combinator/Parsers$Parser;
const #299 = Asciz	log;
const #300 = Asciz	(Lscala/Function0;Ljava/lang/String;)Lscala/util/parsing/combinator/Parsers$Parser;;
const #301 = Asciz	(Lscala/util/parsing/combinator/Parsers;Lscala/Function0;Ljava/lang/String;)Lscala/util/parsing/combinator/Parsers$Parser;;
const #302 = NameAndType	#299:#301;//  log:(Lscala/util/parsing/combinator/Parsers;Lscala/Function0;Ljava/lang/String;)Lscala/util/parsing/combinator/Parsers$Parser;
const #303 = Method	#35.#302;	//  scala/util/parsing/combinator/Parsers$class.log:(Lscala/util/parsing/combinator/Parsers;Lscala/Function0;Ljava/lang/String;)Lscala/util/parsing/combinator/Parsers$Parser;
const #304 = Asciz	name;
const #305 = Asciz	Ljava/lang/String;;
const #306 = Asciz	success;
const #307 = Asciz	(Ljava/lang/Object;)Lscala/util/parsing/combinator/Parsers$Parser;;
const #308 = Asciz	(Lscala/util/parsing/combinator/Parsers;Ljava/lang/Object;)Lscala/util/parsing/combinator/Parsers$Parser;;
const #309 = NameAndType	#306:#308;//  success:(Lscala/util/parsing/combinator/Parsers;Ljava/lang/Object;)Lscala/util/parsing/combinator/Parsers$Parser;
const #310 = Method	#35.#309;	//  scala/util/parsing/combinator/Parsers$class.success:(Lscala/util/parsing/combinator/Parsers;Ljava/lang/Object;)Lscala/util/parsing/combinator/Parsers$Parser;
const #311 = Asciz	v;
const #312 = Asciz	err;
const #313 = Asciz	(Lscala/util/parsing/combinator/Parsers;Ljava/lang/String;)Lscala/util/parsing/combinator/Parsers$Parser;;
const #314 = NameAndType	#312:#313;//  err:(Lscala/util/parsing/combinator/Parsers;Ljava/lang/String;)Lscala/util/parsing/combinator/Parsers$Parser;
const #315 = Method	#35.#314;	//  scala/util/parsing/combinator/Parsers$class.err:(Lscala/util/parsing/combinator/Parsers;Ljava/lang/String;)Lscala/util/parsing/combinator/Parsers$Parser;
const #316 = Asciz	msg;
const #317 = Asciz	failure;
const #318 = NameAndType	#317:#313;//  failure:(Lscala/util/parsing/combinator/Parsers;Ljava/lang/String;)Lscala/util/parsing/combinator/Parsers$Parser;
const #319 = Method	#35.#318;	//  scala/util/parsing/combinator/Parsers$class.failure:(Lscala/util/parsing/combinator/Parsers;Ljava/lang/String;)Lscala/util/parsing/combinator/Parsers$Parser;
const #320 = Asciz	acceptSeq;
const #321 = Asciz	(Ljava/lang/Object;Lscala/Function1;)Lscala/util/parsing/combinator/Parsers$Parser;;
const #322 = Asciz	(Lscala/util/parsing/combinator/Parsers;Ljava/lang/Object;Lscala/Function1;)Lscala/util/parsing/combinator/Parsers$Parser;;
const #323 = NameAndType	#320:#322;//  acceptSeq:(Lscala/util/parsing/combinator/Parsers;Ljava/lang/Object;Lscala/Function1;)Lscala/util/parsing/combinator/Parsers$Parser;
const #324 = Method	#35.#323;	//  scala/util/parsing/combinator/Parsers$class.acceptSeq:(Lscala/util/parsing/combinator/Parsers;Ljava/lang/Object;Lscala/Function1;)Lscala/util/parsing/combinator/Parsers$Parser;
const #325 = Asciz	es;
const #326 = Asciz	evidence$2;
const #327 = Asciz	acceptMatch;
const #328 = Asciz	(Lscala/util/parsing/combinator/Parsers;Ljava/lang/String;Lscala/PartialFunction;)Lscala/util/parsing/combinator/Parsers$Parser;;
const #329 = NameAndType	#327:#328;//  acceptMatch:(Lscala/util/parsing/combinator/Parsers;Ljava/lang/String;Lscala/PartialFunction;)Lscala/util/parsing/combinator/Parsers$Parser;
const #330 = Method	#35.#329;	//  scala/util/parsing/combinator/Parsers$class.acceptMatch:(Lscala/util/parsing/combinator/Parsers;Ljava/lang/String;Lscala/PartialFunction;)Lscala/util/parsing/combinator/Parsers$Parser;
const #331 = Asciz	expected;
const #332 = Asciz	f;
const #333 = Asciz	Lscala/PartialFunction;;
const #334 = Asciz	acceptIf;
const #335 = Asciz	(Lscala/Function1;Lscala/Function1;)Lscala/util/parsing/combinator/Parsers$Parser;;
const #336 = Asciz	(Lscala/util/parsing/combinator/Parsers;Lscala/Function1;Lscala/Function1;)Lscala/util/parsing/combinator/Parsers$Parser;;
const #337 = NameAndType	#334:#336;//  acceptIf:(Lscala/util/parsing/combinator/Parsers;Lscala/Function1;Lscala/Function1;)Lscala/util/parsing/combinator/Parsers$Parser;
const #338 = Method	#35.#337;	//  scala/util/parsing/combinator/Parsers$class.acceptIf:(Lscala/util/parsing/combinator/Parsers;Lscala/Function1;Lscala/Function1;)Lscala/util/parsing/combinator/Parsers$Parser;
const #339 = NameAndType	#136:#328;//  accept:(Lscala/util/parsing/combinator/Parsers;Ljava/lang/String;Lscala/PartialFunction;)Lscala/util/parsing/combinator/Parsers$Parser;
const #340 = Method	#35.#339;	//  scala/util/parsing/combinator/Parsers$class.accept:(Lscala/util/parsing/combinator/Parsers;Ljava/lang/String;Lscala/PartialFunction;)Lscala/util/parsing/combinator/Parsers$Parser;
const #341 = NameAndType	#136:#322;//  accept:(Lscala/util/parsing/combinator/Parsers;Ljava/lang/Object;Lscala/Function1;)Lscala/util/parsing/combinator/Parsers$Parser;
const #342 = Method	#35.#341;	//  scala/util/parsing/combinator/Parsers$class.accept:(Lscala/util/parsing/combinator/Parsers;Ljava/lang/Object;Lscala/Function1;)Lscala/util/parsing/combinator/Parsers$Parser;
const #343 = Asciz	evidence$1;
const #344 = NameAndType	#136:#308;//  accept:(Lscala/util/parsing/combinator/Parsers;Ljava/lang/Object;)Lscala/util/parsing/combinator/Parsers$Parser;
const #345 = Method	#35.#344;	//  scala/util/parsing/combinator/Parsers$class.accept:(Lscala/util/parsing/combinator/Parsers;Ljava/lang/Object;)Lscala/util/parsing/combinator/Parsers$Parser;
const #346 = Asciz	e;
const #347 = Asciz	elem;
const #348 = NameAndType	#347:#308;//  elem:(Lscala/util/parsing/combinator/Parsers;Ljava/lang/Object;)Lscala/util/parsing/combinator/Parsers$Parser;
const #349 = Method	#35.#348;	//  scala/util/parsing/combinator/Parsers$class.elem:(Lscala/util/parsing/combinator/Parsers;Ljava/lang/Object;)Lscala/util/parsing/combinator/Parsers$Parser;
const #350 = Asciz	(Ljava/lang/String;Lscala/Function1;)Lscala/util/parsing/combinator/Parsers$Parser;;
const #351 = Asciz	(Lscala/util/parsing/combinator/Parsers;Ljava/lang/String;Lscala/Function1;)Lscala/util/parsing/combinator/Parsers$Parser;;
const #352 = NameAndType	#347:#351;//  elem:(Lscala/util/parsing/combinator/Parsers;Ljava/lang/String;Lscala/Function1;)Lscala/util/parsing/combinator/Parsers$Parser;
const #353 = Method	#35.#352;	//  scala/util/parsing/combinator/Parsers$class.elem:(Lscala/util/parsing/combinator/Parsers;Ljava/lang/String;Lscala/Function1;)Lscala/util/parsing/combinator/Parsers$Parser;
const #354 = Asciz	kind;
const #355 = Asciz	commit;
const #356 = NameAndType	#355:#246;//  commit:(Lscala/util/parsing/combinator/Parsers;Lscala/Function0;)Lscala/util/parsing/combinator/Parsers$Parser;
const #357 = Method	#35.#356;	//  scala/util/parsing/combinator/Parsers$class.commit:(Lscala/util/parsing/combinator/Parsers;Lscala/Function0;)Lscala/util/parsing/combinator/Parsers$Parser;
const #358 = Asciz	OnceParser;
const #359 = Asciz	(Lscala/util/parsing/combinator/Parsers;Lscala/Function1;)Lscala/util/parsing/combinator/Parsers$Parser;;
const #360 = NameAndType	#358:#359;//  OnceParser:(Lscala/util/parsing/combinator/Parsers;Lscala/Function1;)Lscala/util/parsing/combinator/Parsers$Parser;
const #361 = Method	#35.#360;	//  scala/util/parsing/combinator/Parsers$class.OnceParser:(Lscala/util/parsing/combinator/Parsers;Lscala/Function1;)Lscala/util/parsing/combinator/Parsers$Parser;
const #362 = Asciz	Parser;
const #363 = NameAndType	#362:#359;//  Parser:(Lscala/util/parsing/combinator/Parsers;Lscala/Function1;)Lscala/util/parsing/combinator/Parsers$Parser;
const #364 = Method	#35.#363;	//  scala/util/parsing/combinator/Parsers$class.Parser:(Lscala/util/parsing/combinator/Parsers;Lscala/Function1;)Lscala/util/parsing/combinator/Parsers$Parser;
const #365 = Asciz	()Lscala/util/parsing/combinator/Parsers$$tilde$;;
const #366 = NameAndType	#3:#4;//  $tilde$module:Lscala/util/parsing/combinator/Parsers$$tilde$;
const #367 = Field	#54.#366;	//  scala/util/parsing/json/Parser.$tilde$module:Lscala/util/parsing/combinator/Parsers$$tilde$;
const #368 = Asciz	scala/util/parsing/combinator/Parsers$$tilde$;
const #369 = class	#368;	//  scala/util/parsing/combinator/Parsers$$tilde$
const #370 = NameAndType	#26:#37;//  "<init>":(Lscala/util/parsing/combinator/Parsers;)V
const #371 = Method	#369.#370;	//  scala/util/parsing/combinator/Parsers$$tilde$."<init>":(Lscala/util/parsing/combinator/Parsers;)V
const #372 = Asciz	Error;
const #373 = Asciz	()Lscala/util/parsing/combinator/Parsers$Error$;;
const #374 = NameAndType	#5:#6;//  Error$module:Lscala/util/parsing/combinator/Parsers$Error$;
const #375 = Field	#54.#374;	//  scala/util/parsing/json/Parser.Error$module:Lscala/util/parsing/combinator/Parsers$Error$;
const #376 = Asciz	scala/util/parsing/combinator/Parsers$Error$;
const #377 = class	#376;	//  scala/util/parsing/combinator/Parsers$Error$
const #378 = Method	#377.#370;	//  scala/util/parsing/combinator/Parsers$Error$."<init>":(Lscala/util/parsing/combinator/Parsers;)V
const #379 = Asciz	Failure;
const #380 = Asciz	()Lscala/util/parsing/combinator/Parsers$Failure$;;
const #381 = NameAndType	#7:#8;//  Failure$module:Lscala/util/parsing/combinator/Parsers$Failure$;
const #382 = Field	#54.#381;	//  scala/util/parsing/json/Parser.Failure$module:Lscala/util/parsing/combinator/Parsers$Failure$;
const #383 = Asciz	scala/util/parsing/combinator/Parsers$Failure$;
const #384 = class	#383;	//  scala/util/parsing/combinator/Parsers$Failure$
const #385 = Method	#384.#370;	//  scala/util/parsing/combinator/Parsers$Failure$."<init>":(Lscala/util/parsing/combinator/Parsers;)V
const #386 = Asciz	NoSuccess;
const #387 = Asciz	()Lscala/util/parsing/combinator/Parsers$NoSuccess$;;
const #388 = NameAndType	#9:#10;//  NoSuccess$module:Lscala/util/parsing/combinator/Parsers$NoSuccess$;
const #389 = Field	#54.#388;	//  scala/util/parsing/json/Parser.NoSuccess$module:Lscala/util/parsing/combinator/Parsers$NoSuccess$;
const #390 = Asciz	scala/util/parsing/combinator/Parsers$NoSuccess$;
const #391 = class	#390;	//  scala/util/parsing/combinator/Parsers$NoSuccess$
const #392 = Method	#391.#370;	//  scala/util/parsing/combinator/Parsers$NoSuccess$."<init>":(Lscala/util/parsing/combinator/Parsers;)V
const #393 = Asciz	lastNoSuccess_$eq;
const #394 = Asciz	(Lscala/util/parsing/combinator/Parsers$NoSuccess;)V;
const #395 = NameAndType	#13:#14;//  lastNoSuccess:Lscala/util/parsing/combinator/Parsers$NoSuccess;
const #396 = Field	#54.#395;	//  scala/util/parsing/json/Parser.lastNoSuccess:Lscala/util/parsing/combinator/Parsers$NoSuccess;
const #397 = Asciz	()Lscala/util/parsing/combinator/Parsers$NoSuccess;;
const #398 = Asciz	Success;
const #399 = Asciz	()Lscala/util/parsing/combinator/Parsers$Success$;;
const #400 = NameAndType	#11:#12;//  Success$module:Lscala/util/parsing/combinator/Parsers$Success$;
const #401 = Field	#54.#400;	//  scala/util/parsing/json/Parser.Success$module:Lscala/util/parsing/combinator/Parsers$Success$;
const #402 = Asciz	scala/util/parsing/combinator/Parsers$Success$;
const #403 = class	#402;	//  scala/util/parsing/combinator/Parsers$Success$
const #404 = Method	#403.#370;	//  scala/util/parsing/combinator/Parsers$Success$."<init>":(Lscala/util/parsing/combinator/Parsers;)V
const #405 = Asciz	ident;
const #406 = Asciz	(Lscala/util/parsing/combinator/syntactical/StdTokenParsers;)Lscala/util/parsing/combinator/Parsers$Parser;;
const #407 = NameAndType	#405:#406;//  ident:(Lscala/util/parsing/combinator/syntactical/StdTokenParsers;)Lscala/util/parsing/combinator/Parsers$Parser;
const #408 = Method	#41.#407;	//  scala/util/parsing/combinator/syntactical/StdTokenParsers$class.ident:(Lscala/util/parsing/combinator/syntactical/StdTokenParsers;)Lscala/util/parsing/combinator/Parsers$Parser;
const #409 = Asciz	stringLit;
const #410 = NameAndType	#409:#406;//  stringLit:(Lscala/util/parsing/combinator/syntactical/StdTokenParsers;)Lscala/util/parsing/combinator/Parsers$Parser;
const #411 = Method	#41.#410;	//  scala/util/parsing/combinator/syntactical/StdTokenParsers$class.stringLit:(Lscala/util/parsing/combinator/syntactical/StdTokenParsers;)Lscala/util/parsing/combinator/Parsers$Parser;
const #412 = Asciz	numericLit;
const #413 = NameAndType	#412:#406;//  numericLit:(Lscala/util/parsing/combinator/syntactical/StdTokenParsers;)Lscala/util/parsing/combinator/Parsers$Parser;
const #414 = Method	#41.#413;	//  scala/util/parsing/combinator/syntactical/StdTokenParsers$class.numericLit:(Lscala/util/parsing/combinator/syntactical/StdTokenParsers;)Lscala/util/parsing/combinator/Parsers$Parser;
const #415 = Asciz	(Lscala/util/parsing/combinator/syntactical/StdTokenParsers;Ljava/lang/String;)Lscala/util/parsing/combinator/Parsers$Parser;;
const #416 = NameAndType	#196:#415;//  keyword:(Lscala/util/parsing/combinator/syntactical/StdTokenParsers;Ljava/lang/String;)Lscala/util/parsing/combinator/Parsers$Parser;
const #417 = Method	#41.#416;	//  scala/util/parsing/combinator/syntactical/StdTokenParsers$class.keyword:(Lscala/util/parsing/combinator/syntactical/StdTokenParsers;Ljava/lang/String;)Lscala/util/parsing/combinator/Parsers$Parser;
const #418 = Asciz	chars;
const #419 = Asciz	scala$util$parsing$combinator$syntactical$StdTokenParsers$_setter_$keywordCache_$eq;
const #420 = Asciz	(Lscala/collection/mutable/HashMap;)V;
const #421 = NameAndType	#15:#16;//  keywordCache:Lscala/collection/mutable/HashMap;
const #422 = Field	#54.#421;	//  scala/util/parsing/json/Parser.keywordCache:Lscala/collection/mutable/HashMap;
const #423 = Asciz	()Lscala/collection/mutable/HashMap;;
const #424 = Asciz	headOptionTailToFunList;
const #425 = Asciz	(Lscala/Function1;)Lscala/Function1;;
const #426 = Asciz	(Lscala/util/parsing/combinator/ImplicitConversions;Lscala/Function1;)Lscala/Function1;;
const #427 = NameAndType	#424:#426;//  headOptionTailToFunList:(Lscala/util/parsing/combinator/ImplicitConversions;Lscala/Function1;)Lscala/Function1;
const #428 = Method	#46.#427;	//  scala/util/parsing/combinator/ImplicitConversions$class.headOptionTailToFunList:(Lscala/util/parsing/combinator/ImplicitConversions;Lscala/Function1;)Lscala/Function1;
const #429 = Asciz	flatten5;
const #430 = Asciz	(Lscala/Function5;)Lscala/Function1;;
const #431 = Asciz	(Lscala/util/parsing/combinator/ImplicitConversions;Lscala/Function5;)Lscala/Function1;;
const #432 = NameAndType	#429:#431;//  flatten5:(Lscala/util/parsing/combinator/ImplicitConversions;Lscala/Function5;)Lscala/Function1;
const #433 = Method	#46.#432;	//  scala/util/parsing/combinator/ImplicitConversions$class.flatten5:(Lscala/util/parsing/combinator/ImplicitConversions;Lscala/Function5;)Lscala/Function1;
const #434 = Asciz	Lscala/Function5;;
const #435 = Asciz	flatten4;
const #436 = Asciz	(Lscala/Function4;)Lscala/Function1;;
const #437 = Asciz	(Lscala/util/parsing/combinator/ImplicitConversions;Lscala/Function4;)Lscala/Function1;;
const #438 = NameAndType	#435:#437;//  flatten4:(Lscala/util/parsing/combinator/ImplicitConversions;Lscala/Function4;)Lscala/Function1;
const #439 = Method	#46.#438;	//  scala/util/parsing/combinator/ImplicitConversions$class.flatten4:(Lscala/util/parsing/combinator/ImplicitConversions;Lscala/Function4;)Lscala/Function1;
const #440 = Asciz	Lscala/Function4;;
const #441 = Asciz	flatten3;
const #442 = Asciz	(Lscala/Function3;)Lscala/Function1;;
const #443 = Asciz	(Lscala/util/parsing/combinator/ImplicitConversions;Lscala/Function3;)Lscala/Function1;;
const #444 = NameAndType	#441:#443;//  flatten3:(Lscala/util/parsing/combinator/ImplicitConversions;Lscala/Function3;)Lscala/Function1;
const #445 = Method	#46.#444;	//  scala/util/parsing/combinator/ImplicitConversions$class.flatten3:(Lscala/util/parsing/combinator/ImplicitConversions;Lscala/Function3;)Lscala/Function1;
const #446 = Asciz	Lscala/Function3;;
const #447 = Asciz	flatten2;
const #448 = Asciz	(Lscala/Function2;)Lscala/Function1;;
const #449 = Asciz	(Lscala/util/parsing/combinator/ImplicitConversions;Lscala/Function2;)Lscala/Function1;;
const #450 = NameAndType	#447:#449;//  flatten2:(Lscala/util/parsing/combinator/ImplicitConversions;Lscala/Function2;)Lscala/Function1;
const #451 = Method	#46.#450;	//  scala/util/parsing/combinator/ImplicitConversions$class.flatten2:(Lscala/util/parsing/combinator/ImplicitConversions;Lscala/Function2;)Lscala/Function1;
const #452 = Asciz	ScalaSig;
const #453 = Asciz	InnerClasses;
const #454 = Asciz	$anon$1;
const #455 = Asciz	$anonfun$1;
const #456 = Asciz	scala/util/parsing/combinator/Parsers$NoSuccess;
const #457 = class	#456;	//  scala/util/parsing/combinator/Parsers$NoSuccess
const #458 = Asciz	$anonfun$root$1;
const #459 = Asciz	$anonfun$value$6;
const #460 = Asciz	$anonfun$value$5;
const #461 = Asciz	$anonfun$value$4;
const #462 = Asciz	$anonfun$value$3;
const #463 = Asciz	$anonfun$value$2;
const #464 = Asciz	$anonfun$value$1;
const #465 = Asciz	$anonfun$number$1;
const #466 = Asciz	$anonfun$jsonObj$2;
const #467 = Asciz	$anonfun$jsonObj$1;
const #468 = Asciz	$anonfun$objEntry$2;
const #469 = Asciz	$anonfun$objEntry$1;
const #470 = Asciz	$anonfun$jsonArray$2;
const #471 = Asciz	$anonfun$jsonArray$1;
const #472 = Asciz	$anonfun$stringVal$1;
const #473 = Asciz	scala/util/parsing/combinator/ImplicitConversions;
const #474 = class	#473;	//  scala/util/parsing/combinator/ImplicitConversions
const #475 = Asciz	scala/ScalaObject;
const #476 = class	#475;	//  scala/ScalaObject

{
public scala.util.parsing.json.Parser();
  Code:
   Stack=7, Locals=1, Args_size=1
   0:	aload_0
   1:	invokespecial	#33; //Method java/lang/Object."<init>":()V
   4:	aload_0
   5:	invokestatic	#39; //Method scala/util/parsing/combinator/Parsers$class.$init$:(Lscala/util/parsing/combinator/Parsers;)V
   8:	aload_0
   9:	invokestatic	#44; //Method scala/util/parsing/combinator/syntactical/StdTokenParsers$class.$init$:(Lscala/util/parsing/combinator/syntactical/StdTokenParsers;)V
   12:	aload_0
   13:	invokestatic	#49; //Method scala/util/parsing/combinator/ImplicitConversions$class.$init$:(Lscala/util/parsing/combinator/ImplicitConversions;)V
   16:	aload_0
   17:	new	#51; //class scala/util/parsing/json/Lexer
   20:	dup
   21:	invokespecial	#52; //Method scala/util/parsing/json/Lexer."<init>":()V
   24:	putfield	#56; //Field lexical:Lscala/util/parsing/json/Lexer;
   27:	aload_0
   28:	invokevirtual	#59; //Method lexical:()Lscala/util/parsing/json/Lexer;
   31:	invokevirtual	#63; //Method scala/util/parsing/json/Lexer.reserved:()Lscala/collection/mutable/HashSet;
   34:	getstatic	#69; //Field scala/collection/immutable/List$.MODULE$:Lscala/collection/immutable/List$;
   37:	getstatic	#74; //Field scala/Predef$.MODULE$:Lscala/Predef$;
   40:	iconst_3
   41:	anewarray	#76; //class java/lang/String
   44:	dup
   45:	iconst_0
   46:	ldc	#78; //String true
   48:	aastore
   49:	dup
   50:	iconst_1
   51:	ldc	#80; //String false
   53:	aastore
   54:	dup
   55:	iconst_2
   56:	ldc	#82; //String null
   58:	aastore
   59:	checkcast	#84; //class "[Ljava/lang/Object;"
   62:	invokevirtual	#88; //Method scala/Predef$.wrapRefArray:([Ljava/lang/Object;)Lscala/collection/mutable/WrappedArray;
   65:	invokevirtual	#92; //Method scala/collection/immutable/List$.apply:(Lscala/collection/Seq;)Lscala/collection/immutable/List;
   68:	invokeinterface	#98,  2; //InterfaceMethod scala/collection/generic/Growable.$plus$plus$eq:(Lscala/collection/Traversable;)Lscala/collection/generic/Growable;
   73:	pop
   74:	aload_0
   75:	invokevirtual	#59; //Method lexical:()Lscala/util/parsing/json/Lexer;
   78:	invokevirtual	#101; //Method scala/util/parsing/json/Lexer.delimiters:()Lscala/collection/mutable/HashSet;
   81:	getstatic	#69; //Field scala/collection/immutable/List$.MODULE$:Lscala/collection/immutable/List$;
   84:	getstatic	#74; //Field scala/Predef$.MODULE$:Lscala/Predef$;
   87:	ldc	#102; //int 6
   89:	anewarray	#76; //class java/lang/String
   92:	dup
   93:	iconst_0
   94:	ldc	#104; //String {
   96:	aastore
   97:	dup
   98:	iconst_1
   99:	ldc	#106; //String }
   101:	aastore
   102:	dup
   103:	iconst_2
   104:	ldc	#108; //String [
   106:	aastore
   107:	dup
   108:	iconst_3
   109:	ldc	#110; //String ]
   111:	aastore
   112:	dup
   113:	iconst_4
   114:	ldc	#112; //String :
   116:	aastore
   117:	dup
   118:	iconst_5
   119:	ldc	#114; //String ,
   121:	aastore
   122:	checkcast	#84; //class "[Ljava/lang/Object;"
   125:	invokevirtual	#88; //Method scala/Predef$.wrapRefArray:([Ljava/lang/Object;)Lscala/collection/mutable/WrappedArray;
   128:	invokevirtual	#92; //Method scala/collection/immutable/List$.apply:(Lscala/collection/Seq;)Lscala/collection/immutable/List;
   131:	invokeinterface	#98,  2; //InterfaceMethod scala/collection/generic/Growable.$plus$plus$eq:(Lscala/collection/Traversable;)Lscala/collection/generic/Growable;
   136:	pop
   137:	aload_0
   138:	new	#116; //class scala/util/parsing/json/Parser$$anonfun$1
   141:	dup
   142:	aload_0
   143:	invokespecial	#119; //Method scala/util/parsing/json/Parser$$anonfun$1."<init>":(Lscala/util/parsing/json/Parser;)V
   146:	putfield	#121; //Field defaultNumberParser:Lscala/Function1;
   149:	aload_0
   150:	new	#123; //class scala/util/parsing/json/Parser$$anon$1
   153:	dup
   154:	aload_0
   155:	invokespecial	#124; //Method scala/util/parsing/json/Parser$$anon$1."<init>":(Lscala/util/parsing/json/Parser;)V
   158:	putfield	#126; //Field numberParser:Ljava/lang/ThreadLocal;
   161:	return
  LineNumberTable: 
   line 21: 0
   line 24: 16
   line 27: 27
   line 28: 74
   line 34: 137
   line 37: 149


public scala.util.parsing.syntax.Tokens lexical();
  Code:
   Stack=1, Locals=1, Args_size=1
   0:	aload_0
   1:	invokevirtual	#59; //Method lexical:()Lscala/util/parsing/json/Lexer;
   4:	areturn
  LineNumberTable: 
   line 21: 0


public scala.util.parsing.combinator.Parsers$Parser number();
  Code:
   Stack=5, Locals=1, Args_size=1
   0:	aload_0
   1:	ldc	#130; //String number
   3:	new	#132; //class scala/util/parsing/json/Parser$$anonfun$number$1
   6:	dup
   7:	aload_0
   8:	invokespecial	#133; //Method scala/util/parsing/json/Parser$$anonfun$number$1."<init>":(Lscala/util/parsing/json/Parser;)V
   11:	invokeinterface	#139,  3; //InterfaceMethod scala/util/parsing/combinator/Parsers.accept:(Ljava/lang/String;Lscala/PartialFunction;)Lscala/util/parsing/combinator/Parsers$Parser;
   16:	areturn
  LineNumberTable: 
   line 48: 0

  Signature: length = 0x2
   00 FFFFFF8C 

public scala.util.parsing.combinator.Parsers$Parser stringVal();
  Code:
   Stack=5, Locals=1, Args_size=1
   0:	aload_0
   1:	ldc	#143; //String string
   3:	new	#145; //class scala/util/parsing/json/Parser$$anonfun$stringVal$1
   6:	dup
   7:	aload_0
   8:	invokespecial	#146; //Method scala/util/parsing/json/Parser$$anonfun$stringVal$1."<init>":(Lscala/util/parsing/json/Parser;)V
   11:	invokeinterface	#139,  3; //InterfaceMethod scala/util/parsing/combinator/Parsers.accept:(Ljava/lang/String;Lscala/PartialFunction;)Lscala/util/parsing/combinator/Parsers$Parser;
   16:	areturn
  LineNumberTable: 
   line 47: 0

  Signature: length = 0x2
   00 FFFFFF93 

public scala.util.parsing.combinator.Parsers$Parser value();
  Code:
   Stack=4, Locals=1, Args_size=1
   0:	aload_0
   1:	invokevirtual	#151; //Method jsonObj:()Lscala/util/parsing/combinator/Parsers$Parser;
   4:	new	#153; //class scala/util/parsing/json/Parser$$anonfun$value$1
   7:	dup
   8:	aload_0
   9:	invokespecial	#154; //Method scala/util/parsing/json/Parser$$anonfun$value$1."<init>":(Lscala/util/parsing/json/Parser;)V
   12:	invokevirtual	#160; //Method scala/util/parsing/combinator/Parsers$Parser.$bar:(Lscala/Function0;)Lscala/util/parsing/combinator/Parsers$Parser;
   15:	new	#162; //class scala/util/parsing/json/Parser$$anonfun$value$2
   18:	dup
   19:	aload_0
   20:	invokespecial	#163; //Method scala/util/parsing/json/Parser$$anonfun$value$2."<init>":(Lscala/util/parsing/json/Parser;)V
   23:	invokevirtual	#160; //Method scala/util/parsing/combinator/Parsers$Parser.$bar:(Lscala/Function0;)Lscala/util/parsing/combinator/Parsers$Parser;
   26:	new	#165; //class scala/util/parsing/json/Parser$$anonfun$value$3
   29:	dup
   30:	aload_0
   31:	invokespecial	#166; //Method scala/util/parsing/json/Parser$$anonfun$value$3."<init>":(Lscala/util/parsing/json/Parser;)V
   34:	invokevirtual	#160; //Method scala/util/parsing/combinator/Parsers$Parser.$bar:(Lscala/Function0;)Lscala/util/parsing/combinator/Parsers$Parser;
   37:	new	#168; //class scala/util/parsing/json/Parser$$anonfun$value$4
   40:	dup
   41:	aload_0
   42:	invokespecial	#169; //Method scala/util/parsing/json/Parser$$anonfun$value$4."<init>":(Lscala/util/parsing/json/Parser;)V
   45:	invokevirtual	#160; //Method scala/util/parsing/combinator/Parsers$Parser.$bar:(Lscala/Function0;)Lscala/util/parsing/combinator/Parsers$Parser;
   48:	new	#171; //class scala/util/parsing/json/Parser$$anonfun$value$5
   51:	dup
   52:	aload_0
   53:	invokespecial	#172; //Method scala/util/parsing/json/Parser$$anonfun$value$5."<init>":(Lscala/util/parsing/json/Parser;)V
   56:	invokevirtual	#160; //Method scala/util/parsing/combinator/Parsers$Parser.$bar:(Lscala/Function0;)Lscala/util/parsing/combinator/Parsers$Parser;
   59:	new	#174; //class scala/util/parsing/json/Parser$$anonfun$value$6
   62:	dup
   63:	aload_0
   64:	invokespecial	#175; //Method scala/util/parsing/json/Parser$$anonfun$value$6."<init>":(Lscala/util/parsing/json/Parser;)V
   67:	invokevirtual	#160; //Method scala/util/parsing/combinator/Parsers$Parser.$bar:(Lscala/Function0;)Lscala/util/parsing/combinator/Parsers$Parser;
   70:	areturn
  LineNumberTable: 
   line 46: 0

  Signature: length = 0x2
   00 FFFFFF8C 

public scala.util.parsing.combinator.Parsers$Parser objEntry();
  Code:
   Stack=4, Locals=1, Args_size=1
   0:	aload_0
   1:	invokevirtual	#178; //Method stringVal:()Lscala/util/parsing/combinator/Parsers$Parser;
   4:	new	#180; //class scala/util/parsing/json/Parser$$anonfun$objEntry$1
   7:	dup
   8:	aload_0
   9:	invokespecial	#181; //Method scala/util/parsing/json/Parser$$anonfun$objEntry$1."<init>":(Lscala/util/parsing/json/Parser;)V
   12:	invokevirtual	#184; //Method scala/util/parsing/combinator/Parsers$Parser.$tilde:(Lscala/Function0;)Lscala/util/parsing/combinator/Parsers$Parser;
   15:	new	#186; //class scala/util/parsing/json/Parser$$anonfun$objEntry$2
   18:	dup
   19:	aload_0
   20:	invokespecial	#187; //Method scala/util/parsing/json/Parser$$anonfun$objEntry$2."<init>":(Lscala/util/parsing/json/Parser;)V
   23:	invokevirtual	#191; //Method scala/util/parsing/combinator/Parsers$Parser.$up$up:(Lscala/Function1;)Lscala/util/parsing/combinator/Parsers$Parser;
   26:	areturn
  LineNumberTable: 
   line 45: 0

  Signature: length = 0x2
   00 FFFFFFC0 

public scala.util.parsing.combinator.Parsers$Parser jsonArray();
  Code:
   Stack=4, Locals=1, Args_size=1
   0:	aload_0
   1:	ldc	#108; //String [
   3:	invokeinterface	#199,  2; //InterfaceMethod scala/util/parsing/combinator/syntactical/StdTokenParsers.keyword:(Ljava/lang/String;)Lscala/util/parsing/combinator/Parsers$Parser;
   8:	new	#201; //class scala/util/parsing/json/Parser$$anonfun$jsonArray$1
   11:	dup
   12:	aload_0
   13:	invokespecial	#202; //Method scala/util/parsing/json/Parser$$anonfun$jsonArray$1."<init>":(Lscala/util/parsing/json/Parser;)V
   16:	invokevirtual	#205; //Method scala/util/parsing/combinator/Parsers$Parser.$tilde$greater:(Lscala/Function0;)Lscala/util/parsing/combinator/Parsers$Parser;
   19:	new	#207; //class scala/util/parsing/json/Parser$$anonfun$jsonArray$2
   22:	dup
   23:	aload_0
   24:	invokespecial	#208; //Method scala/util/parsing/json/Parser$$anonfun$jsonArray$2."<init>":(Lscala/util/parsing/json/Parser;)V
   27:	invokevirtual	#211; //Method scala/util/parsing/combinator/Parsers$Parser.$less$tilde:(Lscala/Function0;)Lscala/util/parsing/combinator/Parsers$Parser;
   30:	areturn
  LineNumberTable: 
   line 44: 0

  Signature: length = 0x2
   00 FFFFFFD4 

public scala.util.parsing.combinator.Parsers$Parser jsonObj();
  Code:
   Stack=4, Locals=1, Args_size=1
   0:	aload_0
   1:	ldc	#104; //String {
   3:	invokeinterface	#199,  2; //InterfaceMethod scala/util/parsing/combinator/syntactical/StdTokenParsers.keyword:(Ljava/lang/String;)Lscala/util/parsing/combinator/Parsers$Parser;
   8:	new	#214; //class scala/util/parsing/json/Parser$$anonfun$jsonObj$1
   11:	dup
   12:	aload_0
   13:	invokespecial	#215; //Method scala/util/parsing/json/Parser$$anonfun$jsonObj$1."<init>":(Lscala/util/parsing/json/Parser;)V
   16:	invokevirtual	#205; //Method scala/util/parsing/combinator/Parsers$Parser.$tilde$greater:(Lscala/Function0;)Lscala/util/parsing/combinator/Parsers$Parser;
   19:	new	#217; //class scala/util/parsing/json/Parser$$anonfun$jsonObj$2
   22:	dup
   23:	aload_0
   24:	invokespecial	#218; //Method scala/util/parsing/json/Parser$$anonfun$jsonObj$2."<init>":(Lscala/util/parsing/json/Parser;)V
   27:	invokevirtual	#211; //Method scala/util/parsing/combinator/Parsers$Parser.$less$tilde:(Lscala/Function0;)Lscala/util/parsing/combinator/Parsers$Parser;
   30:	areturn
  LineNumberTable: 
   line 43: 0

  Signature: length = 0x2
   00 FFFFFFDB 

public scala.util.parsing.combinator.Parsers$Parser root();
  Code:
   Stack=4, Locals=1, Args_size=1
   0:	aload_0
   1:	invokevirtual	#151; //Method jsonObj:()Lscala/util/parsing/combinator/Parsers$Parser;
   4:	new	#222; //class scala/util/parsing/json/Parser$$anonfun$root$1
   7:	dup
   8:	aload_0
   9:	invokespecial	#223; //Method scala/util/parsing/json/Parser$$anonfun$root$1."<init>":(Lscala/util/parsing/json/Parser;)V
   12:	invokevirtual	#160; //Method scala/util/parsing/combinator/Parsers$Parser.$bar:(Lscala/Function0;)Lscala/util/parsing/combinator/Parsers$Parser;
   15:	areturn
  LineNumberTable: 
   line 42: 0

  Signature: length = 0x2
   00 FFFFFFD4 

public java.lang.ThreadLocal numberParser();
  Code:
   Stack=1, Locals=1, Args_size=1
   0:	aload_0
   1:	getfield	#126; //Field numberParser:Ljava/lang/ThreadLocal;
   4:	areturn
  LineNumberTable: 
   line 37: 0

  Signature: length = 0x2
   00 FFFFFFE1 

public void defaultNumberParser_$eq(scala.Function1);
  Code:
   Stack=2, Locals=2, Args_size=2
   0:	aload_0
   1:	aload_1
   2:	putfield	#121; //Field defaultNumberParser:Lscala/Function1;
   5:	return
  LineNumberTable: 
   line 34: 0

  Signature: length = 0x2
   00 FFFFFFE4 

public scala.Function1 defaultNumberParser();
  Code:
   Stack=1, Locals=1, Args_size=1
   0:	aload_0
   1:	getfield	#121; //Field defaultNumberParser:Lscala/Function1;
   4:	areturn
  LineNumberTable: 
   line 34: 0

  Signature: length = 0x2
   00 FFFFFFE6 

public scala.util.parsing.json.Lexer lexical();
  Code:
   Stack=1, Locals=1, Args_size=1
   0:	aload_0
   1:	getfield	#56; //Field lexical:Lscala/util/parsing/json/Lexer;
   4:	areturn
  LineNumberTable: 
   line 24: 0


public scala.Function1 mkList();
  Code:
   Stack=1, Locals=1, Args_size=1
   0:	aload_0
   1:	invokestatic	#234; //Method scala/util/parsing/combinator/Parsers$class.mkList:(Lscala/util/parsing/combinator/Parsers;)Lscala/Function1;
   4:	areturn
  LineNumberTable: 
   line 21: 0


public scala.util.parsing.combinator.Parsers$Parser phrase(scala.util.parsing.combinator.Parsers$Parser);
  Code:
   Stack=2, Locals=2, Args_size=2
   0:	aload_0
   1:	aload_1
   2:	invokestatic	#239; //Method scala/util/parsing/combinator/Parsers$class.phrase:(Lscala/util/parsing/combinator/Parsers;Lscala/util/parsing/combinator/Parsers$Parser;)Lscala/util/parsing/combinator/Parsers$Parser;
   5:	areturn
  LineNumberTable: 
   line 21: 0

  LocalVariableTable: 
   Start  Length  Slot  Name   Signature
   0      6      0    this       Lscala/util/parsing/json/Parser;
   0      6      1    p       Lscala/util/parsing/combinator/Parsers$Parser;


public scala.util.parsing.combinator.Parsers$Parser positioned(scala.Function0);
  Code:
   Stack=2, Locals=2, Args_size=2
   0:	aload_0
   1:	aload_1
   2:	invokestatic	#248; //Method scala/util/parsing/combinator/Parsers$class.positioned:(Lscala/util/parsing/combinator/Parsers;Lscala/Function0;)Lscala/util/parsing/combinator/Parsers$Parser;
   5:	areturn
  LineNumberTable: 
   line 21: 0

  LocalVariableTable: 
   Start  Length  Slot  Name   Signature
   0      6      0    this       Lscala/util/parsing/json/Parser;
   0      6      1    p       Lscala/Function0;


public scala.util.parsing.combinator.Parsers$Parser guard(scala.Function0);
  Code:
   Stack=2, Locals=2, Args_size=2
   0:	aload_0
   1:	aload_1
   2:	invokestatic	#252; //Method scala/util/parsing/combinator/Parsers$class.guard:(Lscala/util/parsing/combinator/Parsers;Lscala/Function0;)Lscala/util/parsing/combinator/Parsers$Parser;
   5:	areturn
  LineNumberTable: 
   line 21: 0

  LocalVariableTable: 
   Start  Length  Slot  Name   Signature
   0      6      0    this       Lscala/util/parsing/json/Parser;
   0      6      1    p       Lscala/Function0;


public scala.util.parsing.combinator.Parsers$Parser not(scala.Function0);
  Code:
   Stack=2, Locals=2, Args_size=2
   0:	aload_0
   1:	aload_1
   2:	invokestatic	#255; //Method scala/util/parsing/combinator/Parsers$class.not:(Lscala/util/parsing/combinator/Parsers;Lscala/Function0;)Lscala/util/parsing/combinator/Parsers$Parser;
   5:	areturn
  LineNumberTable: 
   line 21: 0

  LocalVariableTable: 
   Start  Length  Slot  Name   Signature
   0      6      0    this       Lscala/util/parsing/json/Parser;
   0      6      1    p       Lscala/Function0;


public scala.util.parsing.combinator.Parsers$Parser opt(scala.Function0);
  Code:
   Stack=2, Locals=2, Args_size=2
   0:	aload_0
   1:	aload_1
   2:	invokestatic	#258; //Method scala/util/parsing/combinator/Parsers$class.opt:(Lscala/util/parsing/combinator/Parsers;Lscala/Function0;)Lscala/util/parsing/combinator/Parsers$Parser;
   5:	areturn
  LineNumberTable: 
   line 21: 0

  LocalVariableTable: 
   Start  Length  Slot  Name   Signature
   0      6      0    this       Lscala/util/parsing/json/Parser;
   0      6      1    p       Lscala/Function0;


public scala.util.parsing.combinator.Parsers$Parser chainr1(scala.Function0, scala.Function0, scala.Function2, java.lang.Object);
  Code:
   Stack=5, Locals=5, Args_size=5
   0:	aload_0
   1:	aload_1
   2:	aload_2
   3:	aload_3
   4:	aload	4
   6:	invokestatic	#263; //Method scala/util/parsing/combinator/Parsers$class.chainr1:(Lscala/util/parsing/combinator/Parsers;Lscala/Function0;Lscala/Function0;Lscala/Function2;Ljava/lang/Object;)Lscala/util/parsing/combinator/Parsers$Parser;
   9:	areturn
  LineNumberTable: 
   line 21: 0

  LocalVariableTable: 
   Start  Length  Slot  Name   Signature
   0      10      0    this       Lscala/util/parsing/json/Parser;
   0      10      1    p       Lscala/Function0;
   0      10      2    q       Lscala/Function0;
   0      10      3    combine       Lscala/Function2;
   0      10      4    first       Ljava/lang/Object;


public scala.util.parsing.combinator.Parsers$Parser chainl1(scala.Function0, scala.Function0, scala.Function0);
  Code:
   Stack=4, Locals=4, Args_size=4
   0:	aload_0
   1:	aload_1
   2:	aload_2
   3:	aload_3
   4:	invokestatic	#273; //Method scala/util/parsing/combinator/Parsers$class.chainl1:(Lscala/util/parsing/combinator/Parsers;Lscala/Function0;Lscala/Function0;Lscala/Function0;)Lscala/util/parsing/combinator/Parsers$Parser;
   7:	areturn
  LineNumberTable: 
   line 21: 0

  LocalVariableTable: 
   Start  Length  Slot  Name   Signature
   0      8      0    this       Lscala/util/parsing/json/Parser;
   0      8      1    first       Lscala/Function0;
   0      8      2    p       Lscala/Function0;
   0      8      3    q       Lscala/Function0;


public scala.util.parsing.combinator.Parsers$Parser chainl1(scala.Function0, scala.Function0);
  Code:
   Stack=3, Locals=3, Args_size=3
   0:	aload_0
   1:	aload_1
   2:	aload_2
   3:	invokestatic	#277; //Method scala/util/parsing/combinator/Parsers$class.chainl1:(Lscala/util/parsing/combinator/Parsers;Lscala/Function0;Lscala/Function0;)Lscala/util/parsing/combinator/Parsers$Parser;
   6:	areturn
  LineNumberTable: 
   line 21: 0

  LocalVariableTable: 
   Start  Length  Slot  Name   Signature
   0      7      0    this       Lscala/util/parsing/json/Parser;
   0      7      1    p       Lscala/Function0;
   0      7      2    q       Lscala/Function0;


public scala.util.parsing.combinator.Parsers$Parser rep1sep(scala.Function0, scala.Function0);
  Code:
   Stack=3, Locals=3, Args_size=3
   0:	aload_0
   1:	aload_1
   2:	aload_2
   3:	invokestatic	#280; //Method scala/util/parsing/combinator/Parsers$class.rep1sep:(Lscala/util/parsing/combinator/Parsers;Lscala/Function0;Lscala/Function0;)Lscala/util/parsing/combinator/Parsers$Parser;
   6:	areturn
  LineNumberTable: 
   line 21: 0

  LocalVariableTable: 
   Start  Length  Slot  Name   Signature
   0      7      0    this       Lscala/util/parsing/json/Parser;
   0      7      1    p       Lscala/Function0;
   0      7      2    q       Lscala/Function0;


public scala.util.parsing.combinator.Parsers$Parser repN(int, scala.Function0);
  Code:
   Stack=3, Locals=3, Args_size=3
   0:	aload_0
   1:	iload_1
   2:	aload_2
   3:	invokestatic	#285; //Method scala/util/parsing/combinator/Parsers$class.repN:(Lscala/util/parsing/combinator/Parsers;ILscala/Function0;)Lscala/util/parsing/combinator/Parsers$Parser;
   6:	areturn
  LineNumberTable: 
   line 21: 0

  LocalVariableTable: 
   Start  Length  Slot  Name   Signature
   0      7      0    this       Lscala/util/parsing/json/Parser;
   0      7      1    n       I
   0      7      2    p       Lscala/Function0;


public scala.util.parsing.combinator.Parsers$Parser rep1(scala.Function0, scala.Function0);
  Code:
   Stack=3, Locals=3, Args_size=3
   0:	aload_0
   1:	aload_1
   2:	aload_2
   3:	invokestatic	#290; //Method scala/util/parsing/combinator/Parsers$class.rep1:(Lscala/util/parsing/combinator/Parsers;Lscala/Function0;Lscala/Function0;)Lscala/util/parsing/combinator/Parsers$Parser;
   6:	areturn
  LineNumberTable: 
   line 21: 0

  LocalVariableTable: 
   Start  Length  Slot  Name   Signature
   0      7      0    this       Lscala/util/parsing/json/Parser;
   0      7      1    first       Lscala/Function0;
   0      7      2    p       Lscala/Function0;


public scala.util.parsing.combinator.Parsers$Parser rep1(scala.Function0);
  Code:
   Stack=2, Locals=2, Args_size=2
   0:	aload_0
   1:	aload_1
   2:	invokestatic	#292; //Method scala/util/parsing/combinator/Parsers$class.rep1:(Lscala/util/parsing/combinator/Parsers;Lscala/Function0;)Lscala/util/parsing/combinator/Parsers$Parser;
   5:	areturn
  LineNumberTable: 
   line 21: 0

  LocalVariableTable: 
   Start  Length  Slot  Name   Signature
   0      6      0    this       Lscala/util/parsing/json/Parser;
   0      6      1    p       Lscala/Function0;


public scala.util.parsing.combinator.Parsers$Parser repsep(scala.Function0, scala.Function0);
  Code:
   Stack=3, Locals=3, Args_size=3
   0:	aload_0
   1:	aload_1
   2:	aload_2
   3:	invokestatic	#295; //Method scala/util/parsing/combinator/Parsers$class.repsep:(Lscala/util/parsing/combinator/Parsers;Lscala/Function0;Lscala/Function0;)Lscala/util/parsing/combinator/Parsers$Parser;
   6:	areturn
  LineNumberTable: 
   line 21: 0

  LocalVariableTable: 
   Start  Length  Slot  Name   Signature
   0      7      0    this       Lscala/util/parsing/json/Parser;
   0      7      1    p       Lscala/Function0;
   0      7      2    q       Lscala/Function0;


public scala.util.parsing.combinator.Parsers$Parser rep(scala.Function0);
  Code:
   Stack=2, Locals=2, Args_size=2
   0:	aload_0
   1:	aload_1
   2:	invokestatic	#298; //Method scala/util/parsing/combinator/Parsers$class.rep:(Lscala/util/parsing/combinator/Parsers;Lscala/Function0;)Lscala/util/parsing/combinator/Parsers$Parser;
   5:	areturn
  LineNumberTable: 
   line 21: 0

  LocalVariableTable: 
   Start  Length  Slot  Name   Signature
   0      6      0    this       Lscala/util/parsing/json/Parser;
   0      6      1    p       Lscala/Function0;


public scala.util.parsing.combinator.Parsers$Parser log(scala.Function0, java.lang.String);
  Code:
   Stack=3, Locals=3, Args_size=3
   0:	aload_0
   1:	aload_1
   2:	aload_2
   3:	invokestatic	#303; //Method scala/util/parsing/combinator/Parsers$class.log:(Lscala/util/parsing/combinator/Parsers;Lscala/Function0;Ljava/lang/String;)Lscala/util/parsing/combinator/Parsers$Parser;
   6:	areturn
  LineNumberTable: 
   line 21: 0

  LocalVariableTable: 
   Start  Length  Slot  Name   Signature
   0      7      0    this       Lscala/util/parsing/json/Parser;
   0      7      1    p       Lscala/Function0;
   0      7      2    name       Ljava/lang/String;


public scala.util.parsing.combinator.Parsers$Parser success(java.lang.Object);
  Code:
   Stack=2, Locals=2, Args_size=2
   0:	aload_0
   1:	aload_1
   2:	invokestatic	#310; //Method scala/util/parsing/combinator/Parsers$class.success:(Lscala/util/parsing/combinator/Parsers;Ljava/lang/Object;)Lscala/util/parsing/combinator/Parsers$Parser;
   5:	areturn
  LineNumberTable: 
   line 21: 0

  LocalVariableTable: 
   Start  Length  Slot  Name   Signature
   0      6      0    this       Lscala/util/parsing/json/Parser;
   0      6      1    v       Ljava/lang/Object;


public scala.util.parsing.combinator.Parsers$Parser err(java.lang.String);
  Code:
   Stack=2, Locals=2, Args_size=2
   0:	aload_0
   1:	aload_1
   2:	invokestatic	#315; //Method scala/util/parsing/combinator/Parsers$class.err:(Lscala/util/parsing/combinator/Parsers;Ljava/lang/String;)Lscala/util/parsing/combinator/Parsers$Parser;
   5:	areturn
  LineNumberTable: 
   line 21: 0

  LocalVariableTable: 
   Start  Length  Slot  Name   Signature
   0      6      0    this       Lscala/util/parsing/json/Parser;
   0      6      1    msg       Ljava/lang/String;


public scala.util.parsing.combinator.Parsers$Parser failure(java.lang.String);
  Code:
   Stack=2, Locals=2, Args_size=2
   0:	aload_0
   1:	aload_1
   2:	invokestatic	#319; //Method scala/util/parsing/combinator/Parsers$class.failure:(Lscala/util/parsing/combinator/Parsers;Ljava/lang/String;)Lscala/util/parsing/combinator/Parsers$Parser;
   5:	areturn
  LineNumberTable: 
   line 21: 0

  LocalVariableTable: 
   Start  Length  Slot  Name   Signature
   0      6      0    this       Lscala/util/parsing/json/Parser;
   0      6      1    msg       Ljava/lang/String;


public scala.util.parsing.combinator.Parsers$Parser acceptSeq(java.lang.Object, scala.Function1);
  Code:
   Stack=3, Locals=3, Args_size=3
   0:	aload_0
   1:	aload_1
   2:	aload_2
   3:	invokestatic	#324; //Method scala/util/parsing/combinator/Parsers$class.acceptSeq:(Lscala/util/parsing/combinator/Parsers;Ljava/lang/Object;Lscala/Function1;)Lscala/util/parsing/combinator/Parsers$Parser;
   6:	areturn
  LineNumberTable: 
   line 21: 0

  LocalVariableTable: 
   Start  Length  Slot  Name   Signature
   0      7      0    this       Lscala/util/parsing/json/Parser;
   0      7      1    es       Ljava/lang/Object;
   0      7      2    evidence$2       Lscala/Function1;


public scala.util.parsing.combinator.Parsers$Parser acceptMatch(java.lang.String, scala.PartialFunction);
  Code:
   Stack=3, Locals=3, Args_size=3
   0:	aload_0
   1:	aload_1
   2:	aload_2
   3:	invokestatic	#330; //Method scala/util/parsing/combinator/Parsers$class.acceptMatch:(Lscala/util/parsing/combinator/Parsers;Ljava/lang/String;Lscala/PartialFunction;)Lscala/util/parsing/combinator/Parsers$Parser;
   6:	areturn
  LineNumberTable: 
   line 21: 0

  LocalVariableTable: 
   Start  Length  Slot  Name   Signature
   0      7      0    this       Lscala/util/parsing/json/Parser;
   0      7      1    expected       Ljava/lang/String;
   0      7      2    f       Lscala/PartialFunction;


public scala.util.parsing.combinator.Parsers$Parser acceptIf(scala.Function1, scala.Function1);
  Code:
   Stack=3, Locals=3, Args_size=3
   0:	aload_0
   1:	aload_1
   2:	aload_2
   3:	invokestatic	#338; //Method scala/util/parsing/combinator/Parsers$class.acceptIf:(Lscala/util/parsing/combinator/Parsers;Lscala/Function1;Lscala/Function1;)Lscala/util/parsing/combinator/Parsers$Parser;
   6:	areturn
  LineNumberTable: 
   line 21: 0

  LocalVariableTable: 
   Start  Length  Slot  Name   Signature
   0      7      0    this       Lscala/util/parsing/json/Parser;
   0      7      1    p       Lscala/Function1;
   0      7      2    err       Lscala/Function1;


public scala.util.parsing.combinator.Parsers$Parser accept(java.lang.String, scala.PartialFunction);
  Code:
   Stack=3, Locals=3, Args_size=3
   0:	aload_0
   1:	aload_1
   2:	aload_2
   3:	invokestatic	#340; //Method scala/util/parsing/combinator/Parsers$class.accept:(Lscala/util/parsing/combinator/Parsers;Ljava/lang/String;Lscala/PartialFunction;)Lscala/util/parsing/combinator/Parsers$Parser;
   6:	areturn
  LineNumberTable: 
   line 21: 0

  LocalVariableTable: 
   Start  Length  Slot  Name   Signature
   0      7      0    this       Lscala/util/parsing/json/Parser;
   0      7      1    expected       Ljava/lang/String;
   0      7      2    f       Lscala/PartialFunction;


public scala.util.parsing.combinator.Parsers$Parser accept(java.lang.Object, scala.Function1);
  Code:
   Stack=3, Locals=3, Args_size=3
   0:	aload_0
   1:	aload_1
   2:	aload_2
   3:	invokestatic	#342; //Method scala/util/parsing/combinator/Parsers$class.accept:(Lscala/util/parsing/combinator/Parsers;Ljava/lang/Object;Lscala/Function1;)Lscala/util/parsing/combinator/Parsers$Parser;
   6:	areturn
  LineNumberTable: 
   line 21: 0

  LocalVariableTable: 
   Start  Length  Slot  Name   Signature
   0      7      0    this       Lscala/util/parsing/json/Parser;
   0      7      1    es       Ljava/lang/Object;
   0      7      2    evidence$1       Lscala/Function1;


public scala.util.parsing.combinator.Parsers$Parser accept(java.lang.Object);
  Code:
   Stack=2, Locals=2, Args_size=2
   0:	aload_0
   1:	aload_1
   2:	invokestatic	#345; //Method scala/util/parsing/combinator/Parsers$class.accept:(Lscala/util/parsing/combinator/Parsers;Ljava/lang/Object;)Lscala/util/parsing/combinator/Parsers$Parser;
   5:	areturn
  LineNumberTable: 
   line 21: 0

  LocalVariableTable: 
   Start  Length  Slot  Name   Signature
   0      6      0    this       Lscala/util/parsing/json/Parser;
   0      6      1    e       Ljava/lang/Object;


public scala.util.parsing.combinator.Parsers$Parser elem(java.lang.Object);
  Code:
   Stack=2, Locals=2, Args_size=2
   0:	aload_0
   1:	aload_1
   2:	invokestatic	#349; //Method scala/util/parsing/combinator/Parsers$class.elem:(Lscala/util/parsing/combinator/Parsers;Ljava/lang/Object;)Lscala/util/parsing/combinator/Parsers$Parser;
   5:	areturn
  LineNumberTable: 
   line 21: 0

  LocalVariableTable: 
   Start  Length  Slot  Name   Signature
   0      6      0    this       Lscala/util/parsing/json/Parser;
   0      6      1    e       Ljava/lang/Object;


public scala.util.parsing.combinator.Parsers$Parser elem(java.lang.String, scala.Function1);
  Code:
   Stack=3, Locals=3, Args_size=3
   0:	aload_0
   1:	aload_1
   2:	aload_2
   3:	invokestatic	#353; //Method scala/util/parsing/combinator/Parsers$class.elem:(Lscala/util/parsing/combinator/Parsers;Ljava/lang/String;Lscala/Function1;)Lscala/util/parsing/combinator/Parsers$Parser;
   6:	areturn
  LineNumberTable: 
   line 21: 0

  LocalVariableTable: 
   Start  Length  Slot  Name   Signature
   0      7      0    this       Lscala/util/parsing/json/Parser;
   0      7      1    kind       Ljava/lang/String;
   0      7      2    p       Lscala/Function1;


public scala.util.parsing.combinator.Parsers$Parser commit(scala.Function0);
  Code:
   Stack=2, Locals=2, Args_size=2
   0:	aload_0
   1:	aload_1
   2:	invokestatic	#357; //Method scala/util/parsing/combinator/Parsers$class.commit:(Lscala/util/parsing/combinator/Parsers;Lscala/Function0;)Lscala/util/parsing/combinator/Parsers$Parser;
   5:	areturn
  LineNumberTable: 
   line 21: 0

  LocalVariableTable: 
   Start  Length  Slot  Name   Signature
   0      6      0    this       Lscala/util/parsing/json/Parser;
   0      6      1    p       Lscala/Function0;


public scala.util.parsing.combinator.Parsers$Parser OnceParser(scala.Function1);
  Code:
   Stack=2, Locals=2, Args_size=2
   0:	aload_0
   1:	aload_1
   2:	invokestatic	#361; //Method scala/util/parsing/combinator/Parsers$class.OnceParser:(Lscala/util/parsing/combinator/Parsers;Lscala/Function1;)Lscala/util/parsing/combinator/Parsers$Parser;
   5:	areturn
  LineNumberTable: 
   line 21: 0

  LocalVariableTable: 
   Start  Length  Slot  Name   Signature
   0      6      0    this       Lscala/util/parsing/json/Parser;
   0      6      1    f       Lscala/Function1;


public scala.util.parsing.combinator.Parsers$Parser Parser(scala.Function1);
  Code:
   Stack=2, Locals=2, Args_size=2
   0:	aload_0
   1:	aload_1
   2:	invokestatic	#364; //Method scala/util/parsing/combinator/Parsers$class.Parser:(Lscala/util/parsing/combinator/Parsers;Lscala/Function1;)Lscala/util/parsing/combinator/Parsers$Parser;
   5:	areturn
  LineNumberTable: 
   line 21: 0

  LocalVariableTable: 
   Start  Length  Slot  Name   Signature
   0      6      0    this       Lscala/util/parsing/json/Parser;
   0      6      1    f       Lscala/Function1;


public final scala.util.parsing.combinator.Parsers$$tilde$ $tilde();
  Code:
   Stack=4, Locals=1, Args_size=1
   0:	aload_0
   1:	getfield	#367; //Field $tilde$module:Lscala/util/parsing/combinator/Parsers$$tilde$;
   4:	ifnonnull	19
   7:	aload_0
   8:	new	#369; //class scala/util/parsing/combinator/Parsers$$tilde$
   11:	dup
   12:	aload_0
   13:	invokespecial	#371; //Method scala/util/parsing/combinator/Parsers$$tilde$."<init>":(Lscala/util/parsing/combinator/Parsers;)V
   16:	putfield	#367; //Field $tilde$module:Lscala/util/parsing/combinator/Parsers$$tilde$;
   19:	aload_0
   20:	getfield	#367; //Field $tilde$module:Lscala/util/parsing/combinator/Parsers$$tilde$;
   23:	areturn
  LineNumberTable: 
   line 21: 0


public final scala.util.parsing.combinator.Parsers$Error$ Error();
  Code:
   Stack=4, Locals=1, Args_size=1
   0:	aload_0
   1:	getfield	#375; //Field Error$module:Lscala/util/parsing/combinator/Parsers$Error$;
   4:	ifnonnull	19
   7:	aload_0
   8:	new	#377; //class scala/util/parsing/combinator/Parsers$Error$
   11:	dup
   12:	aload_0
   13:	invokespecial	#378; //Method scala/util/parsing/combinator/Parsers$Error$."<init>":(Lscala/util/parsing/combinator/Parsers;)V
   16:	putfield	#375; //Field Error$module:Lscala/util/parsing/combinator/Parsers$Error$;
   19:	aload_0
   20:	getfield	#375; //Field Error$module:Lscala/util/parsing/combinator/Parsers$Error$;
   23:	areturn
  LineNumberTable: 
   line 21: 0


public final scala.util.parsing.combinator.Parsers$Failure$ Failure();
  Code:
   Stack=4, Locals=1, Args_size=1
   0:	aload_0
   1:	getfield	#382; //Field Failure$module:Lscala/util/parsing/combinator/Parsers$Failure$;
   4:	ifnonnull	19
   7:	aload_0
   8:	new	#384; //class scala/util/parsing/combinator/Parsers$Failure$
   11:	dup
   12:	aload_0
   13:	invokespecial	#385; //Method scala/util/parsing/combinator/Parsers$Failure$."<init>":(Lscala/util/parsing/combinator/Parsers;)V
   16:	putfield	#382; //Field Failure$module:Lscala/util/parsing/combinator/Parsers$Failure$;
   19:	aload_0
   20:	getfield	#382; //Field Failure$module:Lscala/util/parsing/combinator/Parsers$Failure$;
   23:	areturn
  LineNumberTable: 
   line 21: 0


public final scala.util.parsing.combinator.Parsers$NoSuccess$ NoSuccess();
  Code:
   Stack=4, Locals=1, Args_size=1
   0:	aload_0
   1:	getfield	#389; //Field NoSuccess$module:Lscala/util/parsing/combinator/Parsers$NoSuccess$;
   4:	ifnonnull	19
   7:	aload_0
   8:	new	#391; //class scala/util/parsing/combinator/Parsers$NoSuccess$
   11:	dup
   12:	aload_0
   13:	invokespecial	#392; //Method scala/util/parsing/combinator/Parsers$NoSuccess$."<init>":(Lscala/util/parsing/combinator/Parsers;)V
   16:	putfield	#389; //Field NoSuccess$module:Lscala/util/parsing/combinator/Parsers$NoSuccess$;
   19:	aload_0
   20:	getfield	#389; //Field NoSuccess$module:Lscala/util/parsing/combinator/Parsers$NoSuccess$;
   23:	areturn
  LineNumberTable: 
   line 21: 0


public void lastNoSuccess_$eq(scala.util.parsing.combinator.Parsers$NoSuccess);
  Code:
   Stack=2, Locals=2, Args_size=2
   0:	aload_0
   1:	aload_1
   2:	putfield	#396; //Field lastNoSuccess:Lscala/util/parsing/combinator/Parsers$NoSuccess;
   5:	return
  LineNumberTable: 
   line 21: 0


public scala.util.parsing.combinator.Parsers$NoSuccess lastNoSuccess();
  Code:
   Stack=1, Locals=1, Args_size=1
   0:	aload_0
   1:	getfield	#396; //Field lastNoSuccess:Lscala/util/parsing/combinator/Parsers$NoSuccess;
   4:	areturn
  LineNumberTable: 
   line 21: 0


public final scala.util.parsing.combinator.Parsers$Success$ Success();
  Code:
   Stack=4, Locals=1, Args_size=1
   0:	aload_0
   1:	getfield	#401; //Field Success$module:Lscala/util/parsing/combinator/Parsers$Success$;
   4:	ifnonnull	19
   7:	aload_0
   8:	new	#403; //class scala/util/parsing/combinator/Parsers$Success$
   11:	dup
   12:	aload_0
   13:	invokespecial	#404; //Method scala/util/parsing/combinator/Parsers$Success$."<init>":(Lscala/util/parsing/combinator/Parsers;)V
   16:	putfield	#401; //Field Success$module:Lscala/util/parsing/combinator/Parsers$Success$;
   19:	aload_0
   20:	getfield	#401; //Field Success$module:Lscala/util/parsing/combinator/Parsers$Success$;
   23:	areturn
  LineNumberTable: 
   line 21: 0


public scala.util.parsing.combinator.Parsers$Parser ident();
  Code:
   Stack=1, Locals=1, Args_size=1
   0:	aload_0
   1:	invokestatic	#408; //Method scala/util/parsing/combinator/syntactical/StdTokenParsers$class.ident:(Lscala/util/parsing/combinator/syntactical/StdTokenParsers;)Lscala/util/parsing/combinator/Parsers$Parser;
   4:	areturn
  LineNumberTable: 
   line 21: 0


public scala.util.parsing.combinator.Parsers$Parser stringLit();
  Code:
   Stack=1, Locals=1, Args_size=1
   0:	aload_0
   1:	invokestatic	#411; //Method scala/util/parsing/combinator/syntactical/StdTokenParsers$class.stringLit:(Lscala/util/parsing/combinator/syntactical/StdTokenParsers;)Lscala/util/parsing/combinator/Parsers$Parser;
   4:	areturn
  LineNumberTable: 
   line 21: 0


public scala.util.parsing.combinator.Parsers$Parser numericLit();
  Code:
   Stack=1, Locals=1, Args_size=1
   0:	aload_0
   1:	invokestatic	#414; //Method scala/util/parsing/combinator/syntactical/StdTokenParsers$class.numericLit:(Lscala/util/parsing/combinator/syntactical/StdTokenParsers;)Lscala/util/parsing/combinator/Parsers$Parser;
   4:	areturn
  LineNumberTable: 
   line 21: 0


public scala.util.parsing.combinator.Parsers$Parser keyword(java.lang.String);
  Code:
   Stack=2, Locals=2, Args_size=2
   0:	aload_0
   1:	aload_1
   2:	invokestatic	#417; //Method scala/util/parsing/combinator/syntactical/StdTokenParsers$class.keyword:(Lscala/util/parsing/combinator/syntactical/StdTokenParsers;Ljava/lang/String;)Lscala/util/parsing/combinator/Parsers$Parser;
   5:	areturn
  LineNumberTable: 
   line 21: 0

  LocalVariableTable: 
   Start  Length  Slot  Name   Signature
   0      6      0    this       Lscala/util/parsing/json/Parser;
   0      6      1    chars       Ljava/lang/String;


public void scala$util$parsing$combinator$syntactical$StdTokenParsers$_setter_$keywordCache_$eq(scala.collection.mutable.HashMap);
  Code:
   Stack=2, Locals=2, Args_size=2
   0:	aload_0
   1:	aload_1
   2:	putfield	#422; //Field keywordCache:Lscala/collection/mutable/HashMap;
   5:	return
  LineNumberTable: 
   line 21: 0


public scala.collection.mutable.HashMap keywordCache();
  Code:
   Stack=1, Locals=1, Args_size=1
   0:	aload_0
   1:	getfield	#422; //Field keywordCache:Lscala/collection/mutable/HashMap;
   4:	areturn
  LineNumberTable: 
   line 21: 0


public scala.Function1 headOptionTailToFunList(scala.Function1);
  Code:
   Stack=2, Locals=2, Args_size=2
   0:	aload_0
   1:	aload_1
   2:	invokestatic	#428; //Method scala/util/parsing/combinator/ImplicitConversions$class.headOptionTailToFunList:(Lscala/util/parsing/combinator/ImplicitConversions;Lscala/Function1;)Lscala/Function1;
   5:	areturn
  LineNumberTable: 
   line 21: 0

  LocalVariableTable: 
   Start  Length  Slot  Name   Signature
   0      6      0    this       Lscala/util/parsing/json/Parser;
   0      6      1    f       Lscala/Function1;


public scala.Function1 flatten5(scala.Function5);
  Code:
   Stack=2, Locals=2, Args_size=2
   0:	aload_0
   1:	aload_1
   2:	invokestatic	#433; //Method scala/util/parsing/combinator/ImplicitConversions$class.flatten5:(Lscala/util/parsing/combinator/ImplicitConversions;Lscala/Function5;)Lscala/Function1;
   5:	areturn
  LineNumberTable: 
   line 21: 0

  LocalVariableTable: 
   Start  Length  Slot  Name   Signature
   0      6      0    this       Lscala/util/parsing/json/Parser;
   0      6      1    f       Lscala/Function5;


public scala.Function1 flatten4(scala.Function4);
  Code:
   Stack=2, Locals=2, Args_size=2
   0:	aload_0
   1:	aload_1
   2:	invokestatic	#439; //Method scala/util/parsing/combinator/ImplicitConversions$class.flatten4:(Lscala/util/parsing/combinator/ImplicitConversions;Lscala/Function4;)Lscala/Function1;
   5:	areturn
  LineNumberTable: 
   line 21: 0

  LocalVariableTable: 
   Start  Length  Slot  Name   Signature
   0      6      0    this       Lscala/util/parsing/json/Parser;
   0      6      1    f       Lscala/Function4;


public scala.Function1 flatten3(scala.Function3);
  Code:
   Stack=2, Locals=2, Args_size=2
   0:	aload_0
   1:	aload_1
   2:	invokestatic	#445; //Method scala/util/parsing/combinator/ImplicitConversions$class.flatten3:(Lscala/util/parsing/combinator/ImplicitConversions;Lscala/Function3;)Lscala/Function1;
   5:	areturn
  LineNumberTable: 
   line 21: 0

  LocalVariableTable: 
   Start  Length  Slot  Name   Signature
   0      6      0    this       Lscala/util/parsing/json/Parser;
   0      6      1    f       Lscala/Function3;


public scala.Function1 flatten2(scala.Function2);
  Code:
   Stack=2, Locals=2, Args_size=2
   0:	aload_0
   1:	aload_1
   2:	invokestatic	#451; //Method scala/util/parsing/combinator/ImplicitConversions$class.flatten2:(Lscala/util/parsing/combinator/ImplicitConversions;Lscala/Function2;)Lscala/Function1;
   5:	areturn
  LineNumberTable: 
   line 21: 0

  LocalVariableTable: 
   Start  Length  Slot  Name   Signature
   0      6      0    this       Lscala/util/parsing/json/Parser;
   0      6      1    f       Lscala/Function2;


}

