Compiled from "Parser.scala"
public final class scala.util.parsing.json.Parser$$anonfun$number$1 extends java.lang.Object implements scala.PartialFunction,java.io.Serializable
  SourceFile: "Parser.scala"
  Scala: length = 0x
   
  InnerClass: 
   public abstract Token=class scala/util/parsing/syntax/Tokens$Token of class scala/util/parsing/syntax/Tokens
   public NumericLit=class scala/util/parsing/syntax/StdTokens$NumericLit of class scala/util/parsing/syntax/StdTokens
   public final $anonfun$number$1=class scala/util/parsing/json/Parser$$anonfun$number$1 of class scala/util/parsing/json/Parser
  minor version: 0
  major version: 49
  Constant pool:
Asciz	SourceFile;
Asciz	Parser.scala;
Asciz	<clinit>;
Asciz	()V;
Asciz	Code;
Asciz	serialVersionUID;
Asciz	J;
Asciz	scala/util/parsing/json/Parser$$anonfun$number$1;
class	scala/util/parsing/json/Parser$$anonfun$number$1
NameAndType	serialVersionUID:J
Field	scala/util/parsing/json/Parser$$anonfun$number$1.serialVersionUID:J
Asciz	$outer;
Asciz	Lscala/util/parsing/json/Parser;;
Asciz	<init>;
Asciz	(Lscala/util/parsing/json/Parser;)V;
Asciz	LineNumberTable;
Asciz	java/lang/NullPointerException;
class	java/lang/NullPointerException
NameAndType	"<init>":()V
Method	java/lang/NullPointerException."<init>":()V
NameAndType	$outer:Lscala/util/parsing/json/Parser;
Field	scala/util/parsing/json/Parser$$anonfun$number$1.$outer:Lscala/util/parsing/json/Parser;
Asciz	java/lang/Object;
class	java/lang/Object
Method	java/lang/Object."<init>":()V
Asciz	scala/Function1$class;
class	scala/Function1$class
Asciz	$init$;
Asciz	(Lscala/Function1;)V;
NameAndType	$init$:(Lscala/Function1;)V
Method	scala/Function1$class.$init$:(Lscala/Function1;)V
Asciz	scala/PartialFunction$class;
class	scala/PartialFunction$class
Asciz	(Lscala/PartialFunction;)V;
NameAndType	$init$:(Lscala/PartialFunction;)V
Method	scala/PartialFunction$class.$init$:(Lscala/PartialFunction;)V
Asciz	this;
Asciz	Lscala/util/parsing/json/Parser$$anonfun$number$1;;
Asciz	LocalVariableTable;
Asciz	apply;
Asciz	(Ljava/lang/Object;)Ljava/lang/Object;;
Asciz	scala/util/parsing/syntax/Tokens$Token;
class	scala/util/parsing/syntax/Tokens$Token
Asciz	(Lscala/util/parsing/syntax/Tokens$Token;)Ljava/lang/Object;;
NameAndType	apply:(Lscala/util/parsing/syntax/Tokens$Token;)Ljava/lang/Object;
Method	scala/util/parsing/json/Parser$$anonfun$number$1.apply:(Lscala/util/parsing/syntax/Tokens$Token;)Ljava/lang/Object;
Asciz	v1;
Asciz	Ljava/lang/Object;;
Asciz	isDefinedAt;
Asciz	(Ljava/lang/Object;)Z;
Asciz	(Lscala/util/parsing/syntax/Tokens$Token;)Z;
NameAndType	isDefinedAt:(Lscala/util/parsing/syntax/Tokens$Token;)Z
Method	scala/util/parsing/json/Parser$$anonfun$number$1.isDefinedAt:(Lscala/util/parsing/syntax/Tokens$Token;)Z
Asciz	x;
Asciz	andThen;
Asciz	(Lscala/Function1;)Lscala/Function1;;
Asciz	scala/PartialFunction;
class	scala/PartialFunction
Asciz	(Lscala/Function1;)Lscala/PartialFunction;;
NameAndType	andThen:(Lscala/Function1;)Lscala/PartialFunction;
InterfaceMethod	scala/PartialFunction.andThen:(Lscala/Function1;)Lscala/PartialFunction;
Asciz	g;
Asciz	Lscala/Function1;;
Asciz	scala/util/parsing/syntax/StdTokens$NumericLit;
class	scala/util/parsing/syntax/StdTokens$NumericLit
Asciz	scala/MatchError;
class	scala/MatchError
Asciz	toString;
Asciz	()Ljava/lang/String;;
NameAndType	toString:()Ljava/lang/String;
Method	scala/util/parsing/syntax/Tokens$Token.toString:()Ljava/lang/String;
Asciz	(Ljava/lang/String;)V;
NameAndType	"<init>":(Ljava/lang/String;)V
Method	scala/MatchError."<init>":(Ljava/lang/String;)V
Asciz	chars;
NameAndType	chars:()Ljava/lang/String;
Method	scala/util/parsing/syntax/StdTokens$NumericLit.chars:()Ljava/lang/String;
Asciz	scala/util/parsing/json/Parser;
class	scala/util/parsing/json/Parser
Asciz	numberParser;
Asciz	()Ljava/lang/ThreadLocal;;
NameAndType	numberParser:()Ljava/lang/ThreadLocal;
Method	scala/util/parsing/json/Parser.numberParser:()Ljava/lang/ThreadLocal;
Asciz	java/lang/ThreadLocal;
class	java/lang/ThreadLocal
Asciz	get;
Asciz	()Ljava/lang/Object;;
NameAndType	get:()Ljava/lang/Object;
Method	java/lang/ThreadLocal.get:()Ljava/lang/Object;
Asciz	scala/Function1;
class	scala/Function1
NameAndType	apply:(Ljava/lang/Object;)Ljava/lang/Object;
InterfaceMethod	scala/Function1.apply:(Ljava/lang/Object;)Ljava/lang/Object;
Asciz	temp11;
Asciz	Lscala/util/parsing/syntax/StdTokens$NumericLit;;
Asciz	temp12;
Asciz	Ljava/lang/String;;
Asciz	compose;
Asciz	(Lscala/Function1;Lscala/Function1;)Lscala/Function1;;
NameAndType	compose:(Lscala/Function1;Lscala/Function1;)Lscala/Function1;
Method	scala/Function1$class.compose:(Lscala/Function1;Lscala/Function1;)Lscala/Function1;
Asciz	(Lscala/Function1;)Ljava/lang/String;;
NameAndType	toString:(Lscala/Function1;)Ljava/lang/String;
Method	scala/Function1$class.toString:(Lscala/Function1;)Ljava/lang/String;
Asciz	(Lscala/PartialFunction;Lscala/Function1;)Lscala/PartialFunction;;
NameAndType	andThen:(Lscala/PartialFunction;Lscala/Function1;)Lscala/PartialFunction;
Method	scala/PartialFunction$class.andThen:(Lscala/PartialFunction;Lscala/Function1;)Lscala/PartialFunction;
Asciz	k;
Asciz	orElse;
Asciz	(Lscala/PartialFunction;)Lscala/PartialFunction;;
Asciz	(Lscala/PartialFunction;Lscala/PartialFunction;)Lscala/PartialFunction;;
NameAndType	orElse:(Lscala/PartialFunction;Lscala/PartialFunction;)Lscala/PartialFunction;
Method	scala/PartialFunction$class.orElse:(Lscala/PartialFunction;Lscala/PartialFunction;)Lscala/PartialFunction;
Asciz	that;
Asciz	Lscala/PartialFunction;;
Asciz	Scala;
Asciz	InnerClasses;
Asciz	scala/util/parsing/syntax/Tokens;
class	scala/util/parsing/syntax/Tokens
Asciz	Token;
Asciz	scala/util/parsing/syntax/StdTokens;
class	scala/util/parsing/syntax/StdTokens
Asciz	NumericLit;
Asciz	$anonfun$number$1;
Asciz	java/io/Serializable;
class	java/io/Serializable

{
public static final long serialVersionUID;
  Signature: J

private final scala.util.parsing.json.Parser $outer;
  Signature: Lscala/util/parsing/json/Parser;

public static {};
  Signature: ()V
  Code:
   Stack=2, Locals=0, Args_size=0
	lconst_0
	putstatic	Field serialVersionUID:J
	return
  Labels:

public scala.util.parsing.json.Parser$$anonfun$number$1(scala.util.parsing.json.Parser);
  Signature: (Lscala/util/parsing/json/Parser;)V
  Code:
   Stack=2, Locals=2, Args_size=2
	aload_1
	ifnonnull	l1 // aload_0
	new	class java/lang/NullPointerException
	dup
	invokespecial	Method java/lang/NullPointerException."<init>":()V
	athrow
l1	aload_0
	aload_1
	putfield	Field $outer:Lscala/util/parsing/json/Parser;
	aload_0
	invokespecial	Method java/lang/Object."<init>":()V
	aload_0
	invokestatic	Method scala/Function1$class.$init$:(Lscala/Function1;)V
	aload_0
	invokestatic	Method scala/PartialFunction$class.$init$:(Lscala/PartialFunction;)V
	return
  Labels:
   	l1 = 12 // aload_0
  LocalVariableTable: 
   Start  Length  Slot  Name   Signature
   0      30      0    this       Lscala/util/parsing/json/Parser$$anonfun$number$1;
   0      30      1    $outer       Lscala/util/parsing/json/Parser;


public final java.lang.Object apply(java.lang.Object);
  Signature: (Ljava/lang/Object;)Ljava/lang/Object;
  Code:
   Stack=2, Locals=2, Args_size=2
	aload_0
	aload_1
	checkcast	class scala/util/parsing/syntax/Tokens$Token
	invokevirtual	Method apply:(Lscala/util/parsing/syntax/Tokens$Token;)Ljava/lang/Object;
	areturn
  Labels:
  LocalVariableTable: 
   Start  Length  Slot  Name   Signature
   0      9      0    this       Lscala/util/parsing/json/Parser$$anonfun$number$1;
   0      9      1    v1       Ljava/lang/Object;


public final boolean isDefinedAt(java.lang.Object);
  Signature: (Ljava/lang/Object;)Z
  Code:
   Stack=2, Locals=2, Args_size=2
	aload_0
	aload_1
	checkcast	class scala/util/parsing/syntax/Tokens$Token
	invokevirtual	Method isDefinedAt:(Lscala/util/parsing/syntax/Tokens$Token;)Z
	ireturn
  Labels:
  LocalVariableTable: 
   Start  Length  Slot  Name   Signature
   0      9      0    this       Lscala/util/parsing/json/Parser$$anonfun$number$1;
   0      9      1    x       Ljava/lang/Object;


public scala.Function1 andThen(scala.Function1);
  Signature: (Lscala/Function1;)Lscala/Function1;
  Code:
   Stack=2, Locals=2, Args_size=2
	aload_0
	aload_1
	invokeinterface	InterfaceMethod scala/PartialFunction.andThen:(Lscala/Function1;)Lscala/PartialFunction;
	areturn
  Labels:
  LocalVariableTable: 
   Start  Length  Slot  Name   Signature
   0      8      0    this       Lscala/util/parsing/json/Parser$$anonfun$number$1;
   0      8      1    g       Lscala/Function1;


public final boolean isDefinedAt(scala.util.parsing.syntax.Tokens$Token);
  Signature: (Lscala/util/parsing/syntax/Tokens$Token;)Z
  Code:
   Stack=3, Locals=2, Args_size=2
	aload_1
	instanceof	class scala/util/parsing/syntax/StdTokens$NumericLit
	ifeq	l1 // iconst_1
	iconst_1
	ifeq	l2 // new
	iconst_1
	goto	l3 // ireturn
l2	new	class scala/MatchError
	dup
	aload_1
	invokevirtual	Method scala/util/parsing/syntax/Tokens$Token.toString:()Ljava/lang/String;
	invokespecial	Method scala/MatchError."<init>":(Ljava/lang/String;)V
	athrow
l1	iconst_1
	ifeq	l4 // new
	iconst_0
l3	ireturn
l4	new	class scala/MatchError
	dup
	aload_1
	invokevirtual	Method scala/util/parsing/syntax/Tokens$Token.toString:()Ljava/lang/String;
	invokespecial	Method scala/MatchError."<init>":(Ljava/lang/String;)V
	athrow
  Labels:
   	l2 = 15 // new
   	l1 = 27 // iconst_1
   	l3 = 32 // ireturn
   	l4 = 33 // new

public final java.lang.Object apply(scala.util.parsing.syntax.Tokens$Token);
  Signature: (Lscala/util/parsing/syntax/Tokens$Token;)Ljava/lang/Object;
  Code:
   Stack=3, Locals=4, Args_size=2
	aload_1
	instanceof	class scala/util/parsing/syntax/StdTokens$NumericLit
	ifeq	l1 // new
	aload_1
	checkcast	class scala/util/parsing/syntax/StdTokens$NumericLit
	astore_2
	aload_2
	invokevirtual	Method scala/util/parsing/syntax/StdTokens$NumericLit.chars:()Ljava/lang/String;
	astore_3
	iconst_1
	ifeq	l2 // new
	aload_0
	getfield	Field $outer:Lscala/util/parsing/json/Parser;
	invokevirtual	Method scala/util/parsing/json/Parser.numberParser:()Ljava/lang/ThreadLocal;
	invokevirtual	Method java/lang/ThreadLocal.get:()Ljava/lang/Object;
	checkcast	class scala/Function1
	aload_3
	invokeinterface	InterfaceMethod scala/Function1.apply:(Ljava/lang/Object;)Ljava/lang/Object;
	areturn
l2	new	class scala/MatchError
	dup
	aload_1
	invokevirtual	Method scala/util/parsing/syntax/Tokens$Token.toString:()Ljava/lang/String;
	invokespecial	Method scala/MatchError."<init>":(Ljava/lang/String;)V
	athrow
l1	new	class scala/MatchError
	dup
	aload_1
	invokevirtual	Method scala/util/parsing/syntax/Tokens$Token.toString:()Ljava/lang/String;
	invokespecial	Method scala/MatchError."<init>":(Ljava/lang/String;)V
	athrow
  Labels:
   	l2 = 41 // new
   	l1 = 53 // new
  LocalVariableTable: 
   Start  Length  Slot  Name   Signature
   0      65      0    this       Lscala/util/parsing/json/Parser$$anonfun$number$1;
   12      41      2    temp11       Lscala/util/parsing/syntax/StdTokens$NumericLit;
   17      36      3    temp12       Ljava/lang/String;


public scala.Function1 compose(scala.Function1);
  Signature: (Lscala/Function1;)Lscala/Function1;
  Code:
   Stack=2, Locals=2, Args_size=2
	aload_0
	aload_1
	invokestatic	Method scala/Function1$class.compose:(Lscala/Function1;Lscala/Function1;)Lscala/Function1;
	areturn
  Labels:
  LocalVariableTable: 
   Start  Length  Slot  Name   Signature
   0      6      0    this       Lscala/util/parsing/json/Parser$$anonfun$number$1;
   0      6      1    g       Lscala/Function1;


public java.lang.String toString();
  Signature: ()Ljava/lang/String;
  Code:
   Stack=1, Locals=1, Args_size=1
	aload_0
	invokestatic	Method scala/Function1$class.toString:(Lscala/Function1;)Ljava/lang/String;
	areturn
  Labels:

public scala.PartialFunction andThen(scala.Function1);
  Signature: (Lscala/Function1;)Lscala/PartialFunction;
  Code:
   Stack=2, Locals=2, Args_size=2
	aload_0
	aload_1
	invokestatic	Method scala/PartialFunction$class.andThen:(Lscala/PartialFunction;Lscala/Function1;)Lscala/PartialFunction;
	areturn
  Labels:
  LocalVariableTable: 
   Start  Length  Slot  Name   Signature
   0      6      0    this       Lscala/util/parsing/json/Parser$$anonfun$number$1;
   0      6      1    k       Lscala/Function1;


public scala.PartialFunction orElse(scala.PartialFunction);
  Signature: (Lscala/PartialFunction;)Lscala/PartialFunction;
  Code:
   Stack=2, Locals=2, Args_size=2
	aload_0
	aload_1
	invokestatic	Method scala/PartialFunction$class.orElse:(Lscala/PartialFunction;Lscala/PartialFunction;)Lscala/PartialFunction;
	areturn
  Labels:
  LocalVariableTable: 
   Start  Length  Slot  Name   Signature
   0      6      0    this       Lscala/util/parsing/json/Parser$$anonfun$number$1;
   0      6      1    that       Lscala/PartialFunction;


}

