Compiled from "Parser.scala"
public final class scala.util.parsing.json.Parser$$anonfun$1 extends scala.runtime.AbstractFunction1 implements java.io.Serializable
  SourceFile: "Parser.scala"
  Scala: length = 0x
   
  InnerClass: 
   public final $anonfun$1=class scala/util/parsing/json/Parser$$anonfun$1 of class scala/util/parsing/json/Parser
  minor version: 0
  major version: 49
  Constant pool:
Asciz	SourceFile;
Asciz	Parser.scala;
Asciz	<clinit>;
Asciz	()V;
Asciz	Code;
Asciz	serialVersionUID;
Asciz	J;
Asciz	scala/util/parsing/json/Parser$$anonfun$1;
class	scala/util/parsing/json/Parser$$anonfun$1
NameAndType	serialVersionUID:J
Field	scala/util/parsing/json/Parser$$anonfun$1.serialVersionUID:J
Asciz	apply;
Asciz	(Ljava/lang/String;)D;
Asciz	scala/Predef$;
class	scala/Predef$
Asciz	MODULE$;
Asciz	Lscala/Predef$;;
NameAndType	MODULE$:Lscala/Predef$;
Field	scala/Predef$.MODULE$:Lscala/Predef$;
Asciz	LineNumberTable;
Asciz	augmentString;
Asciz	(Ljava/lang/String;)Lscala/collection/immutable/StringOps;;
NameAndType	augmentString:(Ljava/lang/String;)Lscala/collection/immutable/StringOps;
Method	scala/Predef$.augmentString:(Ljava/lang/String;)Lscala/collection/immutable/StringOps;
Asciz	scala/collection/immutable/StringLike;
class	scala/collection/immutable/StringLike
Asciz	toDouble;
Asciz	()D;
NameAndType	toDouble:()D
InterfaceMethod	scala/collection/immutable/StringLike.toDouble:()D
Asciz	(Ljava/lang/Object;)Ljava/lang/Object;;
Asciz	java/lang/String;
class	java/lang/String
NameAndType	apply:(Ljava/lang/String;)D
Method	scala/util/parsing/json/Parser$$anonfun$1.apply:(Ljava/lang/String;)D
Asciz	scala/runtime/BoxesRunTime;
class	scala/runtime/BoxesRunTime
Asciz	boxToDouble;
Asciz	(D)Ljava/lang/Double;;
NameAndType	boxToDouble:(D)Ljava/lang/Double;
Method	scala/runtime/BoxesRunTime.boxToDouble:(D)Ljava/lang/Double;
Asciz	this;
Asciz	Lscala/util/parsing/json/Parser$$anonfun$1;;
Asciz	v1;
Asciz	Ljava/lang/Object;;
Asciz	LocalVariableTable;
Asciz	<init>;
Asciz	(Lscala/util/parsing/json/Parser;)V;
Asciz	scala/runtime/AbstractFunction1;
class	scala/runtime/AbstractFunction1
NameAndType	"<init>":()V
Method	scala/runtime/AbstractFunction1."<init>":()V
Asciz	$outer;
Asciz	Lscala/util/parsing/json/Parser;;
Asciz	Scala;
Asciz	InnerClasses;
Asciz	scala/util/parsing/json/Parser;
class	scala/util/parsing/json/Parser
Asciz	$anonfun$1;
Asciz	java/io/Serializable;
class	java/io/Serializable

{
public static final long serialVersionUID;
  Signature: J

public static {};
  Signature: ()V
  Code:
   Stack=2, Locals=0, Args_size=0
	lconst_0
	putstatic	Field serialVersionUID:J
	return
  Labels:

public final double apply(java.lang.String);
  Signature: (Ljava/lang/String;)D
  Code:
   Stack=2, Locals=2, Args_size=2
	getstatic	Field scala/Predef$.MODULE$:Lscala/Predef$;
	aload_1
	invokevirtual	Method scala/Predef$.augmentString:(Ljava/lang/String;)Lscala/collection/immutable/StringOps;
	invokeinterface	InterfaceMethod scala/collection/immutable/StringLike.toDouble:()D
	dreturn
  Labels:

public final java.lang.Object apply(java.lang.Object);
  Signature: (Ljava/lang/Object;)Ljava/lang/Object;
  Code:
   Stack=2, Locals=4, Args_size=2
	aload_0
	aload_1
	checkcast	class java/lang/String
	invokevirtual	Method apply:(Ljava/lang/String;)D
	dstore_2
	dload_2
	invokestatic	Method scala/runtime/BoxesRunTime.boxToDouble:(D)Ljava/lang/Double;
	areturn
  Labels:
  LocalVariableTable: 
   Start  Length  Slot  Name   Signature
   0      14      0    this       Lscala/util/parsing/json/Parser$$anonfun$1;
   0      14      1    v1       Ljava/lang/Object;


public scala.util.parsing.json.Parser$$anonfun$1(scala.util.parsing.json.Parser);
  Signature: (Lscala/util/parsing/json/Parser;)V
  Code:
   Stack=1, Locals=2, Args_size=2
	aload_0
	invokespecial	Method scala/runtime/AbstractFunction1."<init>":()V
	return
  Labels:
  LocalVariableTable: 
   Start  Length  Slot  Name   Signature
   0      5      0    this       Lscala/util/parsing/json/Parser$$anonfun$1;
   0      5      1    $outer       Lscala/util/parsing/json/Parser;


}

