Compiled from "Parser.scala"
public class scala.util.parsing.json.Parser extends java.lang.Object implements scala.util.parsing.combinator.syntactical.StdTokenParsers,scala.util.parsing.combinator.ImplicitConversions,scala.ScalaObject
  SourceFile: "Parser.scala"
  ScalaSig: length = 0x370
   05 00 FFFFFF81 04 06 08 01 02 FFFFFF84 FFFFFF80 FFFFFF80 FFFFFF80 00 0B 02 06
   50 61 72 73 65 72 0A 02 03 04 01 04 6A 73 6F 6E
   0A 02 05 06 01 07 70 61 72 73 69 6E 67 0A 02 07
   08 01 04 75 74 69 6C 0A 01 09 01 05 73 63 61 6C
   61 03 00 13 05 00 0C 14 1C 20 10 02 0D 12 0D 01
   0E 0A 02 0F 10 01 04 6C 61 6E 67 0A 01 11 01 04
   6A 61 76 61 09 02 13 0E 02 06 4F 62 6A 65 63 74
   10 02 15 1A 0D 01 16 0A 02 17 18 01 0B 73 79 6E
   74 61 63 74 69 63 61 6C 0A 02 19 04 01 0A 63 6F
   6D 62 69 6E 61 74 6F 72 09 02 1B 16 02 0F 53 74
   64 54 6F 6B 65 6E 50 61 72 73 65 72 73 10 02 1D
   1E 0D 01 18 09 02 1F 18 02 13 49 6D 70 6C 69 63
   69 74 43 6F 6E 76 65 72 73 69 6F 6E 73 10 02 21
   22 0D 01 08 09 02 23 08 02 0B 53 63 61 6C 61 4F
   62 6A 65 63 74 08 05 25 00 FFFFFF84 00 26 01 06 3C 69
   6E 69 74 3E 14 01 27 10 02 28 00 0D 01 02 05 08
   2A 00 FFFFFF84 FFFFFF80 FFFFFF80 FFFFFF80 00 2B 02 06 54 6F 6B 65 6E 73
   10 02 28 2C 09 02 2D 02 02 05 4C 65 78 65 72 08
   07 2F 00 FFFFFFC2 FFFFFF80 FFFFFF84 00 30 01 07 6C 65 78 69 63 61
   6C 15 01 2B 08 06 32 00 FFFFFFA0 FFFFFF80 04 2B 01 08 6C 65
   78 69 63 61 6C 20 05 08 34 00 FFFFFF84 FFFFFF80 FFFFFF80 FFFFFF80 00 35
   02 0D 4E 75 6D 65 72 69 63 50 61 72 73 65 72 10
   04 21 36 38 3F 09 02 37 08 02 09 46 75 6E 63 74
   69 6F 6E 31 10 02 39 3C 0E 02 21 3A 09 02 3B 08
   01 06 50 72 65 64 65 66 09 02 3D 3E 02 06 53 74
   72 69 6E 67 0A 02 3B 08 10 02 21 40 09 02 41 08
   02 03 41 6E 79 08 07 43 00 FFFFFFC0 FFFFFF80 FFFFFF84 08 44 01 13
   64 65 66 61 75 6C 74 4E 75 6D 62 65 72 50 61 72
   73 65 72 15 01 45 10 02 46 33 0D 01 00 08 07 48
   00 FFFFFFC0 FFFFFF80 FFFFFF84 08 49 01 17 64 65 66 61 75 6C 74 4E
   75 6D 62 65 72 50 61 72 73 65 72 5F 24 65 71 14
   02 4A 4D 10 02 21 4B 09 02 4C 08 02 04 55 6E 69
   74 08 07 4E 47 FFFFFF81 FFFFFF80 FFFFFFC0 00 45 01 03 78 24 31 08
   06 50 00 FFFFFFA0 FFFFFFA0 04 45 01 14 64 65 66 61 75 6C 74
   4E 75 6D 62 65 72 50 61 72 73 65 72 20 08 07 52
   00 FFFFFFC2 FFFFFF80 FFFFFF84 08 53 01 0C 6E 75 6D 62 65 72 50 61
   72 73 65 72 15 01 54 10 03 0D 55 45 09 02 56 0E
   02 0B 54 68 72 65 61 64 4C 6F 63 61 6C 08 06 58
   00 FFFFFFA0 FFFFFF80 04 54 01 0D 6E 75 6D 62 65 72 50 61 72
   73 65 72 20 08 05 5A 00 FFFFFF84 00 5B 01 04 72 6F 6F
   74 15 01 5C 10 03 46 5D 60 09 02 01 5E 09 02 5F
   18 02 07 50 61 72 73 65 72 73 10 03 61 69 3F 0E
   02 62 67 0E 02 63 66 0D 01 64 0A 02 65 0A 01 06
   3C 72 6F 6F 74 3E 09 01 09 09 02 68 08 01 07 70
   61 63 6B 61 67 65 09 02 6A 6B 02 04 4C 69 73 74
   0A 02 68 08 08 05 6D 00 FFFFFF84 00 6E 01 07 6A 73 6F
   6E 4F 62 6A 15 01 6F 10 03 46 5D 70 10 03 61 69
   71 10 04 21 72 38 3F 09 02 73 08 02 06 54 75 70
   6C 65 32 08 05 75 00 FFFFFF84 00 5B 01 09 6A 73 6F 6E
   41 72 72 61 79 08 05 77 00 FFFFFF84 00 78 01 08 6F 62
   6A 45 6E 74 72 79 15 01 79 10 03 46 5D 71 08 05
   7B 00 FFFFFF84 00 7C 01 05 76 61 6C 75 65 15 01 7D 10
   03 46 5D 3F 08 06 7F 00 FFFFFF84 00 FFFFFF81 00 01 09 73 74
   72 69 6E 67 56 61 6C 15 02 FFFFFF81 01 10 03 46 5D 38
   08 06 FFFFFF81 03 00 FFFFFF84 00 7C 01 06 6E 75 6D 62 65 72
   
  InnerClass: 
   public abstract Parser=class scala/util/parsing/combinator/Parsers$Parser of class scala/util/parsing/combinator/Parsers
   public final $anon$1=class scala/util/parsing/json/Parser$$anon$1 of class scala/util/parsing/json/Parser
   public final $anonfun$1=class scala/util/parsing/json/Parser$$anonfun$1 of class scala/util/parsing/json/Parser
   public abstract NoSuccess=class scala/util/parsing/combinator/Parsers$NoSuccess of class scala/util/parsing/combinator/Parsers
   public final $anonfun$root$1=class scala/util/parsing/json/Parser$$anonfun$root$1 of class scala/util/parsing/json/Parser
   public final $anonfun$value$6=class scala/util/parsing/json/Parser$$anonfun$value$6 of class scala/util/parsing/json/Parser
   public final $anonfun$value$5=class scala/util/parsing/json/Parser$$anonfun$value$5 of class scala/util/parsing/json/Parser
   public final $anonfun$value$4=class scala/util/parsing/json/Parser$$anonfun$value$4 of class scala/util/parsing/json/Parser
   public final $anonfun$value$3=class scala/util/parsing/json/Parser$$anonfun$value$3 of class scala/util/parsing/json/Parser
   public final $anonfun$value$2=class scala/util/parsing/json/Parser$$anonfun$value$2 of class scala/util/parsing/json/Parser
   public final $anonfun$value$1=class scala/util/parsing/json/Parser$$anonfun$value$1 of class scala/util/parsing/json/Parser
   public final $anonfun$number$1=class scala/util/parsing/json/Parser$$anonfun$number$1 of class scala/util/parsing/json/Parser
   public final $anonfun$jsonObj$2=class scala/util/parsing/json/Parser$$anonfun$jsonObj$2 of class scala/util/parsing/json/Parser
   public final $anonfun$jsonObj$1=class scala/util/parsing/json/Parser$$anonfun$jsonObj$1 of class scala/util/parsing/json/Parser
   public final $anonfun$objEntry$2=class scala/util/parsing/json/Parser$$anonfun$objEntry$2 of class scala/util/parsing/json/Parser
   public final $anonfun$objEntry$1=class scala/util/parsing/json/Parser$$anonfun$objEntry$1 of class scala/util/parsing/json/Parser
   public final $anonfun$jsonArray$2=class scala/util/parsing/json/Parser$$anonfun$jsonArray$2 of class scala/util/parsing/json/Parser
   public final $anonfun$jsonArray$1=class scala/util/parsing/json/Parser$$anonfun$jsonArray$1 of class scala/util/parsing/json/Parser
   public final $anonfun$stringVal$1=class scala/util/parsing/json/Parser$$anonfun$stringVal$1 of class scala/util/parsing/json/Parser
  minor version: 0
  major version: 49
  Constant pool:
Asciz	SourceFile;
Asciz	Parser.scala;
Asciz	$tilde$module;
Asciz	Lscala/util/parsing/combinator/Parsers$$tilde$;;
Asciz	Error$module;
Asciz	Lscala/util/parsing/combinator/Parsers$Error$;;
Asciz	Failure$module;
Asciz	Lscala/util/parsing/combinator/Parsers$Failure$;;
Asciz	NoSuccess$module;
Asciz	Lscala/util/parsing/combinator/Parsers$NoSuccess$;;
Asciz	Success$module;
Asciz	Lscala/util/parsing/combinator/Parsers$Success$;;
Asciz	lastNoSuccess;
Asciz	Lscala/util/parsing/combinator/Parsers$NoSuccess;;
Asciz	keywordCache;
Asciz	Lscala/collection/mutable/HashMap;;
Asciz	numberParser;
Asciz	Ljava/lang/ThreadLocal;;
Asciz	Ljava/lang/ThreadLocal<Lscala/Function1<Ljava/lang/String;Ljava/lang/Object;>;>;;
Asciz	Signature;
Asciz	defaultNumberParser;
Asciz	Lscala/Function1;;
Asciz	Lscala/Function1<Ljava/lang/String;Ljava/lang/Object;>;;
Asciz	lexical;
Asciz	Lscala/util/parsing/json/Lexer;;
Asciz	<init>;
Asciz	()V;
Asciz	Code;
Asciz	LineNumberTable;
Asciz	java/lang/Object;
class	java/lang/Object
NameAndType	"<init>":()V
Method	java/lang/Object."<init>":()V
Asciz	scala/util/parsing/combinator/Parsers$class;
class	scala/util/parsing/combinator/Parsers$class
Asciz	$init$;
Asciz	(Lscala/util/parsing/combinator/Parsers;)V;
NameAndType	$init$:(Lscala/util/parsing/combinator/Parsers;)V
Method	scala/util/parsing/combinator/Parsers$class.$init$:(Lscala/util/parsing/combinator/Parsers;)V
Asciz	scala/util/parsing/combinator/syntactical/StdTokenParsers$class;
class	scala/util/parsing/combinator/syntactical/StdTokenParsers$class
Asciz	(Lscala/util/parsing/combinator/syntactical/StdTokenParsers;)V;
NameAndType	$init$:(Lscala/util/parsing/combinator/syntactical/StdTokenParsers;)V
Method	scala/util/parsing/combinator/syntactical/StdTokenParsers$class.$init$:(Lscala/util/parsing/combinator/syntactical/StdTokenParsers;)V
Asciz	scala/util/parsing/combinator/ImplicitConversions$class;
class	scala/util/parsing/combinator/ImplicitConversions$class
Asciz	(Lscala/util/parsing/combinator/ImplicitConversions;)V;
NameAndType	$init$:(Lscala/util/parsing/combinator/ImplicitConversions;)V
Method	scala/util/parsing/combinator/ImplicitConversions$class.$init$:(Lscala/util/parsing/combinator/ImplicitConversions;)V
Asciz	scala/util/parsing/json/Lexer;
class	scala/util/parsing/json/Lexer
Method	scala/util/parsing/json/Lexer."<init>":()V
Asciz	scala/util/parsing/json/Parser;
class	scala/util/parsing/json/Parser
NameAndType	lexical:Lscala/util/parsing/json/Lexer;
Field	scala/util/parsing/json/Parser.lexical:Lscala/util/parsing/json/Lexer;
Asciz	()Lscala/util/parsing/json/Lexer;;
NameAndType	lexical:()Lscala/util/parsing/json/Lexer;
Method	scala/util/parsing/json/Parser.lexical:()Lscala/util/parsing/json/Lexer;
Asciz	reserved;
Asciz	()Lscala/collection/mutable/HashSet;;
NameAndType	reserved:()Lscala/collection/mutable/HashSet;
Method	scala/util/parsing/json/Lexer.reserved:()Lscala/collection/mutable/HashSet;
Asciz	scala/collection/immutable/List$;
class	scala/collection/immutable/List$
Asciz	MODULE$;
Asciz	Lscala/collection/immutable/List$;;
NameAndType	MODULE$:Lscala/collection/immutable/List$;
Field	scala/collection/immutable/List$.MODULE$:Lscala/collection/immutable/List$;
Asciz	scala/Predef$;
class	scala/Predef$
Asciz	Lscala/Predef$;;
NameAndType	MODULE$:Lscala/Predef$;
Field	scala/Predef$.MODULE$:Lscala/Predef$;
Asciz	java/lang/String;
class	java/lang/String
Asciz	true;
String	true
Asciz	false;
String	false
Asciz	null;
String	null
Asciz	[Ljava/lang/Object;;
class	"[Ljava/lang/Object;"
Asciz	wrapRefArray;
Asciz	([Ljava/lang/Object;)Lscala/collection/mutable/WrappedArray;;
NameAndType	wrapRefArray:([Ljava/lang/Object;)Lscala/collection/mutable/WrappedArray;
Method	scala/Predef$.wrapRefArray:([Ljava/lang/Object;)Lscala/collection/mutable/WrappedArray;
Asciz	apply;
Asciz	(Lscala/collection/Seq;)Lscala/collection/immutable/List;;
NameAndType	apply:(Lscala/collection/Seq;)Lscala/collection/immutable/List;
Method	scala/collection/immutable/List$.apply:(Lscala/collection/Seq;)Lscala/collection/immutable/List;
Asciz	scala/collection/generic/Growable;
class	scala/collection/generic/Growable
Asciz	$plus$plus$eq;
Asciz	(Lscala/collection/Traversable;)Lscala/collection/generic/Growable;;
NameAndType	$plus$plus$eq:(Lscala/collection/Traversable;)Lscala/collection/generic/Growable;
InterfaceMethod	scala/collection/generic/Growable.$plus$plus$eq:(Lscala/collection/Traversable;)Lscala/collection/generic/Growable;
Asciz	delimiters;
NameAndType	delimiters:()Lscala/collection/mutable/HashSet;
Method	scala/util/parsing/json/Lexer.delimiters:()Lscala/collection/mutable/HashSet;
int	6;
Asciz	{;
String	{
Asciz	};
String	}
Asciz	[;
String	[
Asciz	];
String	]
Asciz	:;
String	:
Asciz	,;
String	,
Asciz	scala/util/parsing/json/Parser$$anonfun$1;
class	scala/util/parsing/json/Parser$$anonfun$1
Asciz	(Lscala/util/parsing/json/Parser;)V;
NameAndType	"<init>":(Lscala/util/parsing/json/Parser;)V
Method	scala/util/parsing/json/Parser$$anonfun$1."<init>":(Lscala/util/parsing/json/Parser;)V
NameAndType	defaultNumberParser:Lscala/Function1;
Field	scala/util/parsing/json/Parser.defaultNumberParser:Lscala/Function1;
Asciz	scala/util/parsing/json/Parser$$anon$1;
class	scala/util/parsing/json/Parser$$anon$1
Method	scala/util/parsing/json/Parser$$anon$1."<init>":(Lscala/util/parsing/json/Parser;)V
NameAndType	numberParser:Ljava/lang/ThreadLocal;
Field	scala/util/parsing/json/Parser.numberParser:Ljava/lang/ThreadLocal;
Asciz	()Lscala/util/parsing/syntax/Tokens;;
Asciz	number;
Asciz	()Lscala/util/parsing/combinator/Parsers$Parser;;
String	number
Asciz	scala/util/parsing/json/Parser$$anonfun$number$1;
class	scala/util/parsing/json/Parser$$anonfun$number$1
Method	scala/util/parsing/json/Parser$$anonfun$number$1."<init>":(Lscala/util/parsing/json/Parser;)V
Asciz	scala/util/parsing/combinator/Parsers;
class	scala/util/parsing/combinator/Parsers
Asciz	accept;
Asciz	(Ljava/lang/String;Lscala/PartialFunction;)Lscala/util/parsing/combinator/Parsers$Parser;;
NameAndType	accept:(Ljava/lang/String;Lscala/PartialFunction;)Lscala/util/parsing/combinator/Parsers$Parser;
InterfaceMethod	scala/util/parsing/combinator/Parsers.accept:(Ljava/lang/String;Lscala/PartialFunction;)Lscala/util/parsing/combinator/Parsers$Parser;
Asciz	()Lscala/util/parsing/combinator/Parsers$Parser<Ljava/lang/Object;>;;
Asciz	stringVal;
Asciz	string;
String	string
Asciz	scala/util/parsing/json/Parser$$anonfun$stringVal$1;
class	scala/util/parsing/json/Parser$$anonfun$stringVal$1
Method	scala/util/parsing/json/Parser$$anonfun$stringVal$1."<init>":(Lscala/util/parsing/json/Parser;)V
Asciz	()Lscala/util/parsing/combinator/Parsers$Parser<Ljava/lang/String;>;;
Asciz	value;
Asciz	jsonObj;
NameAndType	jsonObj:()Lscala/util/parsing/combinator/Parsers$Parser;
Method	scala/util/parsing/json/Parser.jsonObj:()Lscala/util/parsing/combinator/Parsers$Parser;
Asciz	scala/util/parsing/json/Parser$$anonfun$value$1;
class	scala/util/parsing/json/Parser$$anonfun$value$1
Method	scala/util/parsing/json/Parser$$anonfun$value$1."<init>":(Lscala/util/parsing/json/Parser;)V
Asciz	scala/util/parsing/combinator/Parsers$Parser;
class	scala/util/parsing/combinator/Parsers$Parser
Asciz	$bar;
Asciz	(Lscala/Function0;)Lscala/util/parsing/combinator/Parsers$Parser;;
NameAndType	$bar:(Lscala/Function0;)Lscala/util/parsing/combinator/Parsers$Parser;
Method	scala/util/parsing/combinator/Parsers$Parser.$bar:(Lscala/Function0;)Lscala/util/parsing/combinator/Parsers$Parser;
Asciz	scala/util/parsing/json/Parser$$anonfun$value$2;
class	scala/util/parsing/json/Parser$$anonfun$value$2
Method	scala/util/parsing/json/Parser$$anonfun$value$2."<init>":(Lscala/util/parsing/json/Parser;)V
Asciz	scala/util/parsing/json/Parser$$anonfun$value$3;
class	scala/util/parsing/json/Parser$$anonfun$value$3
Method	scala/util/parsing/json/Parser$$anonfun$value$3."<init>":(Lscala/util/parsing/json/Parser;)V
Asciz	scala/util/parsing/json/Parser$$anonfun$value$4;
class	scala/util/parsing/json/Parser$$anonfun$value$4
Method	scala/util/parsing/json/Parser$$anonfun$value$4."<init>":(Lscala/util/parsing/json/Parser;)V
Asciz	scala/util/parsing/json/Parser$$anonfun$value$5;
class	scala/util/parsing/json/Parser$$anonfun$value$5
Method	scala/util/parsing/json/Parser$$anonfun$value$5."<init>":(Lscala/util/parsing/json/Parser;)V
Asciz	scala/util/parsing/json/Parser$$anonfun$value$6;
class	scala/util/parsing/json/Parser$$anonfun$value$6
Method	scala/util/parsing/json/Parser$$anonfun$value$6."<init>":(Lscala/util/parsing/json/Parser;)V
Asciz	objEntry;
NameAndType	stringVal:()Lscala/util/parsing/combinator/Parsers$Parser;
Method	scala/util/parsing/json/Parser.stringVal:()Lscala/util/parsing/combinator/Parsers$Parser;
Asciz	scala/util/parsing/json/Parser$$anonfun$objEntry$1;
class	scala/util/parsing/json/Parser$$anonfun$objEntry$1
Method	scala/util/parsing/json/Parser$$anonfun$objEntry$1."<init>":(Lscala/util/parsing/json/Parser;)V
Asciz	$tilde;
NameAndType	$tilde:(Lscala/Function0;)Lscala/util/parsing/combinator/Parsers$Parser;
Method	scala/util/parsing/combinator/Parsers$Parser.$tilde:(Lscala/Function0;)Lscala/util/parsing/combinator/Parsers$Parser;
Asciz	scala/util/parsing/json/Parser$$anonfun$objEntry$2;
class	scala/util/parsing/json/Parser$$anonfun$objEntry$2
Method	scala/util/parsing/json/Parser$$anonfun$objEntry$2."<init>":(Lscala/util/parsing/json/Parser;)V
Asciz	$up$up;
Asciz	(Lscala/Function1;)Lscala/util/parsing/combinator/Parsers$Parser;;
NameAndType	$up$up:(Lscala/Function1;)Lscala/util/parsing/combinator/Parsers$Parser;
Method	scala/util/parsing/combinator/Parsers$Parser.$up$up:(Lscala/Function1;)Lscala/util/parsing/combinator/Parsers$Parser;
Asciz	()Lscala/util/parsing/combinator/Parsers$Parser<Lscala/Tuple2<Ljava/lang/String;Ljava/lang/Object;>;>;;
Asciz	jsonArray;
Asciz	scala/util/parsing/combinator/syntactical/StdTokenParsers;
class	scala/util/parsing/combinator/syntactical/StdTokenParsers
Asciz	keyword;
Asciz	(Ljava/lang/String;)Lscala/util/parsing/combinator/Parsers$Parser;;
NameAndType	keyword:(Ljava/lang/String;)Lscala/util/parsing/combinator/Parsers$Parser;
InterfaceMethod	scala/util/parsing/combinator/syntactical/StdTokenParsers.keyword:(Ljava/lang/String;)Lscala/util/parsing/combinator/Parsers$Parser;
Asciz	scala/util/parsing/json/Parser$$anonfun$jsonArray$1;
class	scala/util/parsing/json/Parser$$anonfun$jsonArray$1
Method	scala/util/parsing/json/Parser$$anonfun$jsonArray$1."<init>":(Lscala/util/parsing/json/Parser;)V
Asciz	$tilde$greater;
NameAndType	$tilde$greater:(Lscala/Function0;)Lscala/util/parsing/combinator/Parsers$Parser;
Method	scala/util/parsing/combinator/Parsers$Parser.$tilde$greater:(Lscala/Function0;)Lscala/util/parsing/combinator/Parsers$Parser;
Asciz	scala/util/parsing/json/Parser$$anonfun$jsonArray$2;
class	scala/util/parsing/json/Parser$$anonfun$jsonArray$2
Method	scala/util/parsing/json/Parser$$anonfun$jsonArray$2."<init>":(Lscala/util/parsing/json/Parser;)V
Asciz	$less$tilde;
NameAndType	$less$tilde:(Lscala/Function0;)Lscala/util/parsing/combinator/Parsers$Parser;
Method	scala/util/parsing/combinator/Parsers$Parser.$less$tilde:(Lscala/Function0;)Lscala/util/parsing/combinator/Parsers$Parser;
Asciz	()Lscala/util/parsing/combinator/Parsers$Parser<Lscala/collection/immutable/List<Ljava/lang/Object;>;>;;
Asciz	scala/util/parsing/json/Parser$$anonfun$jsonObj$1;
class	scala/util/parsing/json/Parser$$anonfun$jsonObj$1
Method	scala/util/parsing/json/Parser$$anonfun$jsonObj$1."<init>":(Lscala/util/parsing/json/Parser;)V
Asciz	scala/util/parsing/json/Parser$$anonfun$jsonObj$2;
class	scala/util/parsing/json/Parser$$anonfun$jsonObj$2
Method	scala/util/parsing/json/Parser$$anonfun$jsonObj$2."<init>":(Lscala/util/parsing/json/Parser;)V
Asciz	()Lscala/util/parsing/combinator/Parsers$Parser<Lscala/collection/immutable/List<Lscala/Tuple2<Ljava/lang/String;Ljava/lang/Object;>;>;>;;
Asciz	root;
Asciz	scala/util/parsing/json/Parser$$anonfun$root$1;
class	scala/util/parsing/json/Parser$$anonfun$root$1
Method	scala/util/parsing/json/Parser$$anonfun$root$1."<init>":(Lscala/util/parsing/json/Parser;)V
Asciz	()Ljava/lang/ThreadLocal;;
Asciz	()Ljava/lang/ThreadLocal<Lscala/Function1<Ljava/lang/String;Ljava/lang/Object;>;>;;
Asciz	defaultNumberParser_$eq;
Asciz	(Lscala/Function1;)V;
Asciz	(Lscala/Function1<Ljava/lang/String;Ljava/lang/Object;>;)V;
Asciz	()Lscala/Function1;;
Asciz	()Lscala/Function1<Ljava/lang/String;Ljava/lang/Object;>;;
Asciz	mkList;
Asciz	(Lscala/util/parsing/combinator/Parsers;)Lscala/Function1;;
NameAndType	mkList:(Lscala/util/parsing/combinator/Parsers;)Lscala/Function1;
Method	scala/util/parsing/combinator/Parsers$class.mkList:(Lscala/util/parsing/combinator/Parsers;)Lscala/Function1;
Asciz	phrase;
Asciz	(Lscala/util/parsing/combinator/Parsers$Parser;)Lscala/util/parsing/combinator/Parsers$Parser;;
Asciz	(Lscala/util/parsing/combinator/Parsers;Lscala/util/parsing/combinator/Parsers$Parser;)Lscala/util/parsing/combinator/Parsers$Parser;;
NameAndType	phrase:(Lscala/util/parsing/combinator/Parsers;Lscala/util/parsing/combinator/Parsers$Parser;)Lscala/util/parsing/combinator/Parsers$Parser;
Method	scala/util/parsing/combinator/Parsers$class.phrase:(Lscala/util/parsing/combinator/Parsers;Lscala/util/parsing/combinator/Parsers$Parser;)Lscala/util/parsing/combinator/Parsers$Parser;
Asciz	this;
Asciz	Lscala/util/parsing/json/Parser;;
Asciz	p;
Asciz	Lscala/util/parsing/combinator/Parsers$Parser;;
Asciz	LocalVariableTable;
Asciz	positioned;
Asciz	(Lscala/util/parsing/combinator/Parsers;Lscala/Function0;)Lscala/util/parsing/combinator/Parsers$Parser;;
NameAndType	positioned:(Lscala/util/parsing/combinator/Parsers;Lscala/Function0;)Lscala/util/parsing/combinator/Parsers$Parser;
Method	scala/util/parsing/combinator/Parsers$class.positioned:(Lscala/util/parsing/combinator/Parsers;Lscala/Function0;)Lscala/util/parsing/combinator/Parsers$Parser;
Asciz	Lscala/Function0;;
Asciz	guard;
NameAndType	guard:(Lscala/util/parsing/combinator/Parsers;Lscala/Function0;)Lscala/util/parsing/combinator/Parsers$Parser;
Method	scala/util/parsing/combinator/Parsers$class.guard:(Lscala/util/parsing/combinator/Parsers;Lscala/Function0;)Lscala/util/parsing/combinator/Parsers$Parser;
Asciz	not;
NameAndType	not:(Lscala/util/parsing/combinator/Parsers;Lscala/Function0;)Lscala/util/parsing/combinator/Parsers$Parser;
Method	scala/util/parsing/combinator/Parsers$class.not:(Lscala/util/parsing/combinator/Parsers;Lscala/Function0;)Lscala/util/parsing/combinator/Parsers$Parser;
Asciz	opt;
NameAndType	opt:(Lscala/util/parsing/combinator/Parsers;Lscala/Function0;)Lscala/util/parsing/combinator/Parsers$Parser;
Method	scala/util/parsing/combinator/Parsers$class.opt:(Lscala/util/parsing/combinator/Parsers;Lscala/Function0;)Lscala/util/parsing/combinator/Parsers$Parser;
Asciz	chainr1;
Asciz	(Lscala/Function0;Lscala/Function0;Lscala/Function2;Ljava/lang/Object;)Lscala/util/parsing/combinator/Parsers$Parser;;
Asciz	(Lscala/util/parsing/combinator/Parsers;Lscala/Function0;Lscala/Function0;Lscala/Function2;Ljava/lang/Object;)Lscala/util/parsing/combinator/Parsers$Parser;;
NameAndType	chainr1:(Lscala/util/parsing/combinator/Parsers;Lscala/Function0;Lscala/Function0;Lscala/Function2;Ljava/lang/Object;)Lscala/util/parsing/combinator/Parsers$Parser;
Method	scala/util/parsing/combinator/Parsers$class.chainr1:(Lscala/util/parsing/combinator/Parsers;Lscala/Function0;Lscala/Function0;Lscala/Function2;Ljava/lang/Object;)Lscala/util/parsing/combinator/Parsers$Parser;
Asciz	q;
Asciz	combine;
Asciz	Lscala/Function2;;
Asciz	first;
Asciz	Ljava/lang/Object;;
Asciz	chainl1;
Asciz	(Lscala/Function0;Lscala/Function0;Lscala/Function0;)Lscala/util/parsing/combinator/Parsers$Parser;;
Asciz	(Lscala/util/parsing/combinator/Parsers;Lscala/Function0;Lscala/Function0;Lscala/Function0;)Lscala/util/parsing/combinator/Parsers$Parser;;
NameAndType	chainl1:(Lscala/util/parsing/combinator/Parsers;Lscala/Function0;Lscala/Function0;Lscala/Function0;)Lscala/util/parsing/combinator/Parsers$Parser;
Method	scala/util/parsing/combinator/Parsers$class.chainl1:(Lscala/util/parsing/combinator/Parsers;Lscala/Function0;Lscala/Function0;Lscala/Function0;)Lscala/util/parsing/combinator/Parsers$Parser;
Asciz	(Lscala/Function0;Lscala/Function0;)Lscala/util/parsing/combinator/Parsers$Parser;;
Asciz	(Lscala/util/parsing/combinator/Parsers;Lscala/Function0;Lscala/Function0;)Lscala/util/parsing/combinator/Parsers$Parser;;
NameAndType	chainl1:(Lscala/util/parsing/combinator/Parsers;Lscala/Function0;Lscala/Function0;)Lscala/util/parsing/combinator/Parsers$Parser;
Method	scala/util/parsing/combinator/Parsers$class.chainl1:(Lscala/util/parsing/combinator/Parsers;Lscala/Function0;Lscala/Function0;)Lscala/util/parsing/combinator/Parsers$Parser;
Asciz	rep1sep;
NameAndType	rep1sep:(Lscala/util/parsing/combinator/Parsers;Lscala/Function0;Lscala/Function0;)Lscala/util/parsing/combinator/Parsers$Parser;
Method	scala/util/parsing/combinator/Parsers$class.rep1sep:(Lscala/util/parsing/combinator/Parsers;Lscala/Function0;Lscala/Function0;)Lscala/util/parsing/combinator/Parsers$Parser;
Asciz	repN;
Asciz	(ILscala/Function0;)Lscala/util/parsing/combinator/Parsers$Parser;;
Asciz	(Lscala/util/parsing/combinator/Parsers;ILscala/Function0;)Lscala/util/parsing/combinator/Parsers$Parser;;
NameAndType	repN:(Lscala/util/parsing/combinator/Parsers;ILscala/Function0;)Lscala/util/parsing/combinator/Parsers$Parser;
Method	scala/util/parsing/combinator/Parsers$class.repN:(Lscala/util/parsing/combinator/Parsers;ILscala/Function0;)Lscala/util/parsing/combinator/Parsers$Parser;
Asciz	n;
Asciz	I;
Asciz	rep1;
NameAndType	rep1:(Lscala/util/parsing/combinator/Parsers;Lscala/Function0;Lscala/Function0;)Lscala/util/parsing/combinator/Parsers$Parser;
Method	scala/util/parsing/combinator/Parsers$class.rep1:(Lscala/util/parsing/combinator/Parsers;Lscala/Function0;Lscala/Function0;)Lscala/util/parsing/combinator/Parsers$Parser;
NameAndType	rep1:(Lscala/util/parsing/combinator/Parsers;Lscala/Function0;)Lscala/util/parsing/combinator/Parsers$Parser;
Method	scala/util/parsing/combinator/Parsers$class.rep1:(Lscala/util/parsing/combinator/Parsers;Lscala/Function0;)Lscala/util/parsing/combinator/Parsers$Parser;
Asciz	repsep;
NameAndType	repsep:(Lscala/util/parsing/combinator/Parsers;Lscala/Function0;Lscala/Function0;)Lscala/util/parsing/combinator/Parsers$Parser;
Method	scala/util/parsing/combinator/Parsers$class.repsep:(Lscala/util/parsing/combinator/Parsers;Lscala/Function0;Lscala/Function0;)Lscala/util/parsing/combinator/Parsers$Parser;
Asciz	rep;
NameAndType	rep:(Lscala/util/parsing/combinator/Parsers;Lscala/Function0;)Lscala/util/parsing/combinator/Parsers$Parser;
Method	scala/util/parsing/combinator/Parsers$class.rep:(Lscala/util/parsing/combinator/Parsers;Lscala/Function0;)Lscala/util/parsing/combinator/Parsers$Parser;
Asciz	log;
Asciz	(Lscala/Function0;Ljava/lang/String;)Lscala/util/parsing/combinator/Parsers$Parser;;
Asciz	(Lscala/util/parsing/combinator/Parsers;Lscala/Function0;Ljava/lang/String;)Lscala/util/parsing/combinator/Parsers$Parser;;
NameAndType	log:(Lscala/util/parsing/combinator/Parsers;Lscala/Function0;Ljava/lang/String;)Lscala/util/parsing/combinator/Parsers$Parser;
Method	scala/util/parsing/combinator/Parsers$class.log:(Lscala/util/parsing/combinator/Parsers;Lscala/Function0;Ljava/lang/String;)Lscala/util/parsing/combinator/Parsers$Parser;
Asciz	name;
Asciz	Ljava/lang/String;;
Asciz	success;
Asciz	(Ljava/lang/Object;)Lscala/util/parsing/combinator/Parsers$Parser;;
Asciz	(Lscala/util/parsing/combinator/Parsers;Ljava/lang/Object;)Lscala/util/parsing/combinator/Parsers$Parser;;
NameAndType	success:(Lscala/util/parsing/combinator/Parsers;Ljava/lang/Object;)Lscala/util/parsing/combinator/Parsers$Parser;
Method	scala/util/parsing/combinator/Parsers$class.success:(Lscala/util/parsing/combinator/Parsers;Ljava/lang/Object;)Lscala/util/parsing/combinator/Parsers$Parser;
Asciz	v;
Asciz	err;
Asciz	(Lscala/util/parsing/combinator/Parsers;Ljava/lang/String;)Lscala/util/parsing/combinator/Parsers$Parser;;
NameAndType	err:(Lscala/util/parsing/combinator/Parsers;Ljava/lang/String;)Lscala/util/parsing/combinator/Parsers$Parser;
Method	scala/util/parsing/combinator/Parsers$class.err:(Lscala/util/parsing/combinator/Parsers;Ljava/lang/String;)Lscala/util/parsing/combinator/Parsers$Parser;
Asciz	msg;
Asciz	failure;
NameAndType	failure:(Lscala/util/parsing/combinator/Parsers;Ljava/lang/String;)Lscala/util/parsing/combinator/Parsers$Parser;
Method	scala/util/parsing/combinator/Parsers$class.failure:(Lscala/util/parsing/combinator/Parsers;Ljava/lang/String;)Lscala/util/parsing/combinator/Parsers$Parser;
Asciz	acceptSeq;
Asciz	(Ljava/lang/Object;Lscala/Function1;)Lscala/util/parsing/combinator/Parsers$Parser;;
Asciz	(Lscala/util/parsing/combinator/Parsers;Ljava/lang/Object;Lscala/Function1;)Lscala/util/parsing/combinator/Parsers$Parser;;
NameAndType	acceptSeq:(Lscala/util/parsing/combinator/Parsers;Ljava/lang/Object;Lscala/Function1;)Lscala/util/parsing/combinator/Parsers$Parser;
Method	scala/util/parsing/combinator/Parsers$class.acceptSeq:(Lscala/util/parsing/combinator/Parsers;Ljava/lang/Object;Lscala/Function1;)Lscala/util/parsing/combinator/Parsers$Parser;
Asciz	es;
Asciz	evidence$2;
Asciz	acceptMatch;
Asciz	(Lscala/util/parsing/combinator/Parsers;Ljava/lang/String;Lscala/PartialFunction;)Lscala/util/parsing/combinator/Parsers$Parser;;
NameAndType	acceptMatch:(Lscala/util/parsing/combinator/Parsers;Ljava/lang/String;Lscala/PartialFunction;)Lscala/util/parsing/combinator/Parsers$Parser;
Method	scala/util/parsing/combinator/Parsers$class.acceptMatch:(Lscala/util/parsing/combinator/Parsers;Ljava/lang/String;Lscala/PartialFunction;)Lscala/util/parsing/combinator/Parsers$Parser;
Asciz	expected;
Asciz	f;
Asciz	Lscala/PartialFunction;;
Asciz	acceptIf;
Asciz	(Lscala/Function1;Lscala/Function1;)Lscala/util/parsing/combinator/Parsers$Parser;;
Asciz	(Lscala/util/parsing/combinator/Parsers;Lscala/Function1;Lscala/Function1;)Lscala/util/parsing/combinator/Parsers$Parser;;
NameAndType	acceptIf:(Lscala/util/parsing/combinator/Parsers;Lscala/Function1;Lscala/Function1;)Lscala/util/parsing/combinator/Parsers$Parser;
Method	scala/util/parsing/combinator/Parsers$class.acceptIf:(Lscala/util/parsing/combinator/Parsers;Lscala/Function1;Lscala/Function1;)Lscala/util/parsing/combinator/Parsers$Parser;
NameAndType	accept:(Lscala/util/parsing/combinator/Parsers;Ljava/lang/String;Lscala/PartialFunction;)Lscala/util/parsing/combinator/Parsers$Parser;
Method	scala/util/parsing/combinator/Parsers$class.accept:(Lscala/util/parsing/combinator/Parsers;Ljava/lang/String;Lscala/PartialFunction;)Lscala/util/parsing/combinator/Parsers$Parser;
NameAndType	accept:(Lscala/util/parsing/combinator/Parsers;Ljava/lang/Object;Lscala/Function1;)Lscala/util/parsing/combinator/Parsers$Parser;
Method	scala/util/parsing/combinator/Parsers$class.accept:(Lscala/util/parsing/combinator/Parsers;Ljava/lang/Object;Lscala/Function1;)Lscala/util/parsing/combinator/Parsers$Parser;
Asciz	evidence$1;
NameAndType	accept:(Lscala/util/parsing/combinator/Parsers;Ljava/lang/Object;)Lscala/util/parsing/combinator/Parsers$Parser;
Method	scala/util/parsing/combinator/Parsers$class.accept:(Lscala/util/parsing/combinator/Parsers;Ljava/lang/Object;)Lscala/util/parsing/combinator/Parsers$Parser;
Asciz	e;
Asciz	elem;
NameAndType	elem:(Lscala/util/parsing/combinator/Parsers;Ljava/lang/Object;)Lscala/util/parsing/combinator/Parsers$Parser;
Method	scala/util/parsing/combinator/Parsers$class.elem:(Lscala/util/parsing/combinator/Parsers;Ljava/lang/Object;)Lscala/util/parsing/combinator/Parsers$Parser;
Asciz	(Ljava/lang/String;Lscala/Function1;)Lscala/util/parsing/combinator/Parsers$Parser;;
Asciz	(Lscala/util/parsing/combinator/Parsers;Ljava/lang/String;Lscala/Function1;)Lscala/util/parsing/combinator/Parsers$Parser;;
NameAndType	elem:(Lscala/util/parsing/combinator/Parsers;Ljava/lang/String;Lscala/Function1;)Lscala/util/parsing/combinator/Parsers$Parser;
Method	scala/util/parsing/combinator/Parsers$class.elem:(Lscala/util/parsing/combinator/Parsers;Ljava/lang/String;Lscala/Function1;)Lscala/util/parsing/combinator/Parsers$Parser;
Asciz	kind;
Asciz	commit;
NameAndType	commit:(Lscala/util/parsing/combinator/Parsers;Lscala/Function0;)Lscala/util/parsing/combinator/Parsers$Parser;
Method	scala/util/parsing/combinator/Parsers$class.commit:(Lscala/util/parsing/combinator/Parsers;Lscala/Function0;)Lscala/util/parsing/combinator/Parsers$Parser;
Asciz	OnceParser;
Asciz	(Lscala/util/parsing/combinator/Parsers;Lscala/Function1;)Lscala/util/parsing/combinator/Parsers$Parser;;
NameAndType	OnceParser:(Lscala/util/parsing/combinator/Parsers;Lscala/Function1;)Lscala/util/parsing/combinator/Parsers$Parser;
Method	scala/util/parsing/combinator/Parsers$class.OnceParser:(Lscala/util/parsing/combinator/Parsers;Lscala/Function1;)Lscala/util/parsing/combinator/Parsers$Parser;
Asciz	Parser;
NameAndType	Parser:(Lscala/util/parsing/combinator/Parsers;Lscala/Function1;)Lscala/util/parsing/combinator/Parsers$Parser;
Method	scala/util/parsing/combinator/Parsers$class.Parser:(Lscala/util/parsing/combinator/Parsers;Lscala/Function1;)Lscala/util/parsing/combinator/Parsers$Parser;
Asciz	()Lscala/util/parsing/combinator/Parsers$$tilde$;;
NameAndType	$tilde$module:Lscala/util/parsing/combinator/Parsers$$tilde$;
Field	scala/util/parsing/json/Parser.$tilde$module:Lscala/util/parsing/combinator/Parsers$$tilde$;
Asciz	scala/util/parsing/combinator/Parsers$$tilde$;
class	scala/util/parsing/combinator/Parsers$$tilde$
NameAndType	"<init>":(Lscala/util/parsing/combinator/Parsers;)V
Method	scala/util/parsing/combinator/Parsers$$tilde$."<init>":(Lscala/util/parsing/combinator/Parsers;)V
Asciz	Error;
Asciz	()Lscala/util/parsing/combinator/Parsers$Error$;;
NameAndType	Error$module:Lscala/util/parsing/combinator/Parsers$Error$;
Field	scala/util/parsing/json/Parser.Error$module:Lscala/util/parsing/combinator/Parsers$Error$;
Asciz	scala/util/parsing/combinator/Parsers$Error$;
class	scala/util/parsing/combinator/Parsers$Error$
Method	scala/util/parsing/combinator/Parsers$Error$."<init>":(Lscala/util/parsing/combinator/Parsers;)V
Asciz	Failure;
Asciz	()Lscala/util/parsing/combinator/Parsers$Failure$;;
NameAndType	Failure$module:Lscala/util/parsing/combinator/Parsers$Failure$;
Field	scala/util/parsing/json/Parser.Failure$module:Lscala/util/parsing/combinator/Parsers$Failure$;
Asciz	scala/util/parsing/combinator/Parsers$Failure$;
class	scala/util/parsing/combinator/Parsers$Failure$
Method	scala/util/parsing/combinator/Parsers$Failure$."<init>":(Lscala/util/parsing/combinator/Parsers;)V
Asciz	NoSuccess;
Asciz	()Lscala/util/parsing/combinator/Parsers$NoSuccess$;;
NameAndType	NoSuccess$module:Lscala/util/parsing/combinator/Parsers$NoSuccess$;
Field	scala/util/parsing/json/Parser.NoSuccess$module:Lscala/util/parsing/combinator/Parsers$NoSuccess$;
Asciz	scala/util/parsing/combinator/Parsers$NoSuccess$;
class	scala/util/parsing/combinator/Parsers$NoSuccess$
Method	scala/util/parsing/combinator/Parsers$NoSuccess$."<init>":(Lscala/util/parsing/combinator/Parsers;)V
Asciz	lastNoSuccess_$eq;
Asciz	(Lscala/util/parsing/combinator/Parsers$NoSuccess;)V;
NameAndType	lastNoSuccess:Lscala/util/parsing/combinator/Parsers$NoSuccess;
Field	scala/util/parsing/json/Parser.lastNoSuccess:Lscala/util/parsing/combinator/Parsers$NoSuccess;
Asciz	()Lscala/util/parsing/combinator/Parsers$NoSuccess;;
Asciz	Success;
Asciz	()Lscala/util/parsing/combinator/Parsers$Success$;;
NameAndType	Success$module:Lscala/util/parsing/combinator/Parsers$Success$;
Field	scala/util/parsing/json/Parser.Success$module:Lscala/util/parsing/combinator/Parsers$Success$;
Asciz	scala/util/parsing/combinator/Parsers$Success$;
class	scala/util/parsing/combinator/Parsers$Success$
Method	scala/util/parsing/combinator/Parsers$Success$."<init>":(Lscala/util/parsing/combinator/Parsers;)V
Asciz	ident;
Asciz	(Lscala/util/parsing/combinator/syntactical/StdTokenParsers;)Lscala/util/parsing/combinator/Parsers$Parser;;
NameAndType	ident:(Lscala/util/parsing/combinator/syntactical/StdTokenParsers;)Lscala/util/parsing/combinator/Parsers$Parser;
Method	scala/util/parsing/combinator/syntactical/StdTokenParsers$class.ident:(Lscala/util/parsing/combinator/syntactical/StdTokenParsers;)Lscala/util/parsing/combinator/Parsers$Parser;
Asciz	stringLit;
NameAndType	stringLit:(Lscala/util/parsing/combinator/syntactical/StdTokenParsers;)Lscala/util/parsing/combinator/Parsers$Parser;
Method	scala/util/parsing/combinator/syntactical/StdTokenParsers$class.stringLit:(Lscala/util/parsing/combinator/syntactical/StdTokenParsers;)Lscala/util/parsing/combinator/Parsers$Parser;
Asciz	numericLit;
NameAndType	numericLit:(Lscala/util/parsing/combinator/syntactical/StdTokenParsers;)Lscala/util/parsing/combinator/Parsers$Parser;
Method	scala/util/parsing/combinator/syntactical/StdTokenParsers$class.numericLit:(Lscala/util/parsing/combinator/syntactical/StdTokenParsers;)Lscala/util/parsing/combinator/Parsers$Parser;
Asciz	(Lscala/util/parsing/combinator/syntactical/StdTokenParsers;Ljava/lang/String;)Lscala/util/parsing/combinator/Parsers$Parser;;
NameAndType	keyword:(Lscala/util/parsing/combinator/syntactical/StdTokenParsers;Ljava/lang/String;)Lscala/util/parsing/combinator/Parsers$Parser;
Method	scala/util/parsing/combinator/syntactical/StdTokenParsers$class.keyword:(Lscala/util/parsing/combinator/syntactical/StdTokenParsers;Ljava/lang/String;)Lscala/util/parsing/combinator/Parsers$Parser;
Asciz	chars;
Asciz	scala$util$parsing$combinator$syntactical$StdTokenParsers$_setter_$keywordCache_$eq;
Asciz	(Lscala/collection/mutable/HashMap;)V;
NameAndType	keywordCache:Lscala/collection/mutable/HashMap;
Field	scala/util/parsing/json/Parser.keywordCache:Lscala/collection/mutable/HashMap;
Asciz	()Lscala/collection/mutable/HashMap;;
Asciz	headOptionTailToFunList;
Asciz	(Lscala/Function1;)Lscala/Function1;;
Asciz	(Lscala/util/parsing/combinator/ImplicitConversions;Lscala/Function1;)Lscala/Function1;;
NameAndType	headOptionTailToFunList:(Lscala/util/parsing/combinator/ImplicitConversions;Lscala/Function1;)Lscala/Function1;
Method	scala/util/parsing/combinator/ImplicitConversions$class.headOptionTailToFunList:(Lscala/util/parsing/combinator/ImplicitConversions;Lscala/Function1;)Lscala/Function1;
Asciz	flatten5;
Asciz	(Lscala/Function5;)Lscala/Function1;;
Asciz	(Lscala/util/parsing/combinator/ImplicitConversions;Lscala/Function5;)Lscala/Function1;;
NameAndType	flatten5:(Lscala/util/parsing/combinator/ImplicitConversions;Lscala/Function5;)Lscala/Function1;
Method	scala/util/parsing/combinator/ImplicitConversions$class.flatten5:(Lscala/util/parsing/combinator/ImplicitConversions;Lscala/Function5;)Lscala/Function1;
Asciz	Lscala/Function5;;
Asciz	flatten4;
Asciz	(Lscala/Function4;)Lscala/Function1;;
Asciz	(Lscala/util/parsing/combinator/ImplicitConversions;Lscala/Function4;)Lscala/Function1;;
NameAndType	flatten4:(Lscala/util/parsing/combinator/ImplicitConversions;Lscala/Function4;)Lscala/Function1;
Method	scala/util/parsing/combinator/ImplicitConversions$class.flatten4:(Lscala/util/parsing/combinator/ImplicitConversions;Lscala/Function4;)Lscala/Function1;
Asciz	Lscala/Function4;;
Asciz	flatten3;
Asciz	(Lscala/Function3;)Lscala/Function1;;
Asciz	(Lscala/util/parsing/combinator/ImplicitConversions;Lscala/Function3;)Lscala/Function1;;
NameAndType	flatten3:(Lscala/util/parsing/combinator/ImplicitConversions;Lscala/Function3;)Lscala/Function1;
Method	scala/util/parsing/combinator/ImplicitConversions$class.flatten3:(Lscala/util/parsing/combinator/ImplicitConversions;Lscala/Function3;)Lscala/Function1;
Asciz	Lscala/Function3;;
Asciz	flatten2;
Asciz	(Lscala/Function2;)Lscala/Function1;;
Asciz	(Lscala/util/parsing/combinator/ImplicitConversions;Lscala/Function2;)Lscala/Function1;;
NameAndType	flatten2:(Lscala/util/parsing/combinator/ImplicitConversions;Lscala/Function2;)Lscala/Function1;
Method	scala/util/parsing/combinator/ImplicitConversions$class.flatten2:(Lscala/util/parsing/combinator/ImplicitConversions;Lscala/Function2;)Lscala/Function1;
Asciz	ScalaSig;
Asciz	InnerClasses;
Asciz	$anon$1;
Asciz	$anonfun$1;
Asciz	scala/util/parsing/combinator/Parsers$NoSuccess;
class	scala/util/parsing/combinator/Parsers$NoSuccess
Asciz	$anonfun$root$1;
Asciz	$anonfun$value$6;
Asciz	$anonfun$value$5;
Asciz	$anonfun$value$4;
Asciz	$anonfun$value$3;
Asciz	$anonfun$value$2;
Asciz	$anonfun$value$1;
Asciz	$anonfun$number$1;
Asciz	$anonfun$jsonObj$2;
Asciz	$anonfun$jsonObj$1;
Asciz	$anonfun$objEntry$2;
Asciz	$anonfun$objEntry$1;
Asciz	$anonfun$jsonArray$2;
Asciz	$anonfun$jsonArray$1;
Asciz	$anonfun$stringVal$1;
Asciz	scala/util/parsing/combinator/ImplicitConversions;
class	scala/util/parsing/combinator/ImplicitConversions
Asciz	scala/ScalaObject;
class	scala/ScalaObject

{
private scala.util.parsing.combinator.Parsers$$tilde$ $tilde$module;
  Signature: Lscala/util/parsing/combinator/Parsers$$tilde$;

private scala.util.parsing.combinator.Parsers$Error$ Error$module;
  Signature: Lscala/util/parsing/combinator/Parsers$Error$;

private scala.util.parsing.combinator.Parsers$Failure$ Failure$module;
  Signature: Lscala/util/parsing/combinator/Parsers$Failure$;

private scala.util.parsing.combinator.Parsers$NoSuccess$ NoSuccess$module;
  Signature: Lscala/util/parsing/combinator/Parsers$NoSuccess$;

private scala.util.parsing.combinator.Parsers$Success$ Success$module;
  Signature: Lscala/util/parsing/combinator/Parsers$Success$;

private scala.util.parsing.combinator.Parsers$NoSuccess lastNoSuccess;
  Signature: Lscala/util/parsing/combinator/Parsers$NoSuccess;

private final scala.collection.mutable.HashMap keywordCache;
  Signature: Lscala/collection/mutable/HashMap;

private final java.lang.ThreadLocal numberParser;
  Signature: Ljava/lang/ThreadLocal;
  Signature: length = 0x2
   00 13 

private scala.Function1 defaultNumberParser;
  Signature: Lscala/Function1;
  Signature: length = 0x2
   00 17 

private final scala.util.parsing.json.Lexer lexical;
  Signature: Lscala/util/parsing/json/Lexer;

public scala.util.parsing.json.Parser();
  Signature: ()V
  Code:
   Stack=7, Locals=1, Args_size=1
	aload_0
	invokespecial	Method java/lang/Object."<init>":()V
	aload_0
	invokestatic	Method scala/util/parsing/combinator/Parsers$class.$init$:(Lscala/util/parsing/combinator/Parsers;)V
	aload_0
	invokestatic	Method scala/util/parsing/combinator/syntactical/StdTokenParsers$class.$init$:(Lscala/util/parsing/combinator/syntactical/StdTokenParsers;)V
	aload_0
	invokestatic	Method scala/util/parsing/combinator/ImplicitConversions$class.$init$:(Lscala/util/parsing/combinator/ImplicitConversions;)V
	aload_0
	new	class scala/util/parsing/json/Lexer
	dup
	invokespecial	Method scala/util/parsing/json/Lexer."<init>":()V
	putfield	Field lexical:Lscala/util/parsing/json/Lexer;
	aload_0
	invokevirtual	Method lexical:()Lscala/util/parsing/json/Lexer;
	invokevirtual	Method scala/util/parsing/json/Lexer.reserved:()Lscala/collection/mutable/HashSet;
	getstatic	Field scala/collection/immutable/List$.MODULE$:Lscala/collection/immutable/List$;
	getstatic	Field scala/Predef$.MODULE$:Lscala/Predef$;
	iconst_3
	anewarray	class java/lang/String
	dup
	iconst_0
	ldc	String true
	aastore
	dup
	iconst_1
	ldc	String false
	aastore
	dup
	iconst_2
	ldc	String null
	aastore
	checkcast	class "[Ljava/lang/Object;"
	invokevirtual	Method scala/Predef$.wrapRefArray:([Ljava/lang/Object;)Lscala/collection/mutable/WrappedArray;
	invokevirtual	Method scala/collection/immutable/List$.apply:(Lscala/collection/Seq;)Lscala/collection/immutable/List;
	invokeinterface	InterfaceMethod scala/collection/generic/Growable.$plus$plus$eq:(Lscala/collection/Traversable;)Lscala/collection/generic/Growable;
	pop
	aload_0
	invokevirtual	Method lexical:()Lscala/util/parsing/json/Lexer;
	invokevirtual	Method scala/util/parsing/json/Lexer.delimiters:()Lscala/collection/mutable/HashSet;
	getstatic	Field scala/collection/immutable/List$.MODULE$:Lscala/collection/immutable/List$;
	getstatic	Field scala/Predef$.MODULE$:Lscala/Predef$;
	ldc	int 6
	anewarray	class java/lang/String
	dup
	iconst_0
	ldc	String {
	aastore
	dup
	iconst_1
	ldc	String }
	aastore
	dup
	iconst_2
	ldc	String [
	aastore
	dup
	iconst_3
	ldc	String ]
	aastore
	dup
	iconst_4
	ldc	String :
	aastore
	dup
	iconst_5
	ldc	String ,
	aastore
	checkcast	class "[Ljava/lang/Object;"
	invokevirtual	Method scala/Predef$.wrapRefArray:([Ljava/lang/Object;)Lscala/collection/mutable/WrappedArray;
	invokevirtual	Method scala/collection/immutable/List$.apply:(Lscala/collection/Seq;)Lscala/collection/immutable/List;
	invokeinterface	InterfaceMethod scala/collection/generic/Growable.$plus$plus$eq:(Lscala/collection/Traversable;)Lscala/collection/generic/Growable;
	pop
	aload_0
	new	class scala/util/parsing/json/Parser$$anonfun$1
	dup
	aload_0
	invokespecial	Method scala/util/parsing/json/Parser$$anonfun$1."<init>":(Lscala/util/parsing/json/Parser;)V
	putfield	Field defaultNumberParser:Lscala/Function1;
	aload_0
	new	class scala/util/parsing/json/Parser$$anon$1
	dup
	aload_0
	invokespecial	Method scala/util/parsing/json/Parser$$anon$1."<init>":(Lscala/util/parsing/json/Parser;)V
	putfield	Field numberParser:Ljava/lang/ThreadLocal;
	return
  Labels:

public scala.util.parsing.syntax.Tokens lexical();
  Signature: ()Lscala/util/parsing/syntax/Tokens;
  Code:
   Stack=1, Locals=1, Args_size=1
	aload_0
	invokevirtual	Method lexical:()Lscala/util/parsing/json/Lexer;
	areturn
  Labels:

public scala.util.parsing.combinator.Parsers$Parser number();
  Signature: ()Lscala/util/parsing/combinator/Parsers$Parser;
  Code:
   Stack=5, Locals=1, Args_size=1
	aload_0
	ldc	String number
	new	class scala/util/parsing/json/Parser$$anonfun$number$1
	dup
	aload_0
	invokespecial	Method scala/util/parsing/json/Parser$$anonfun$number$1."<init>":(Lscala/util/parsing/json/Parser;)V
	invokeinterface	InterfaceMethod scala/util/parsing/combinator/Parsers.accept:(Ljava/lang/String;Lscala/PartialFunction;)Lscala/util/parsing/combinator/Parsers$Parser;
	areturn
  Labels:
  Signature: length = 0x2
   00 FFFFFF8C 

public scala.util.parsing.combinator.Parsers$Parser stringVal();
  Signature: ()Lscala/util/parsing/combinator/Parsers$Parser;
  Code:
   Stack=5, Locals=1, Args_size=1
	aload_0
	ldc	String string
	new	class scala/util/parsing/json/Parser$$anonfun$stringVal$1
	dup
	aload_0
	invokespecial	Method scala/util/parsing/json/Parser$$anonfun$stringVal$1."<init>":(Lscala/util/parsing/json/Parser;)V
	invokeinterface	InterfaceMethod scala/util/parsing/combinator/Parsers.accept:(Ljava/lang/String;Lscala/PartialFunction;)Lscala/util/parsing/combinator/Parsers$Parser;
	areturn
  Labels:
  Signature: length = 0x2
   00 FFFFFF93 

public scala.util.parsing.combinator.Parsers$Parser value();
  Signature: ()Lscala/util/parsing/combinator/Parsers$Parser;
  Code:
   Stack=4, Locals=1, Args_size=1
	aload_0
	invokevirtual	Method jsonObj:()Lscala/util/parsing/combinator/Parsers$Parser;
	new	class scala/util/parsing/json/Parser$$anonfun$value$1
	dup
	aload_0
	invokespecial	Method scala/util/parsing/json/Parser$$anonfun$value$1."<init>":(Lscala/util/parsing/json/Parser;)V
	invokevirtual	Method scala/util/parsing/combinator/Parsers$Parser.$bar:(Lscala/Function0;)Lscala/util/parsing/combinator/Parsers$Parser;
	new	class scala/util/parsing/json/Parser$$anonfun$value$2
	dup
	aload_0
	invokespecial	Method scala/util/parsing/json/Parser$$anonfun$value$2."<init>":(Lscala/util/parsing/json/Parser;)V
	invokevirtual	Method scala/util/parsing/combinator/Parsers$Parser.$bar:(Lscala/Function0;)Lscala/util/parsing/combinator/Parsers$Parser;
	new	class scala/util/parsing/json/Parser$$anonfun$value$3
	dup
	aload_0
	invokespecial	Method scala/util/parsing/json/Parser$$anonfun$value$3."<init>":(Lscala/util/parsing/json/Parser;)V
	invokevirtual	Method scala/util/parsing/combinator/Parsers$Parser.$bar:(Lscala/Function0;)Lscala/util/parsing/combinator/Parsers$Parser;
	new	class scala/util/parsing/json/Parser$$anonfun$value$4
	dup
	aload_0
	invokespecial	Method scala/util/parsing/json/Parser$$anonfun$value$4."<init>":(Lscala/util/parsing/json/Parser;)V
	invokevirtual	Method scala/util/parsing/combinator/Parsers$Parser.$bar:(Lscala/Function0;)Lscala/util/parsing/combinator/Parsers$Parser;
	new	class scala/util/parsing/json/Parser$$anonfun$value$5
	dup
	aload_0
	invokespecial	Method scala/util/parsing/json/Parser$$anonfun$value$5."<init>":(Lscala/util/parsing/json/Parser;)V
	invokevirtual	Method scala/util/parsing/combinator/Parsers$Parser.$bar:(Lscala/Function0;)Lscala/util/parsing/combinator/Parsers$Parser;
	new	class scala/util/parsing/json/Parser$$anonfun$value$6
	dup
	aload_0
	invokespecial	Method scala/util/parsing/json/Parser$$anonfun$value$6."<init>":(Lscala/util/parsing/json/Parser;)V
	invokevirtual	Method scala/util/parsing/combinator/Parsers$Parser.$bar:(Lscala/Function0;)Lscala/util/parsing/combinator/Parsers$Parser;
	areturn
  Labels:
  Signature: length = 0x2
   00 FFFFFF8C 

public scala.util.parsing.combinator.Parsers$Parser objEntry();
  Signature: ()Lscala/util/parsing/combinator/Parsers$Parser;
  Code:
   Stack=4, Locals=1, Args_size=1
	aload_0
	invokevirtual	Method stringVal:()Lscala/util/parsing/combinator/Parsers$Parser;
	new	class scala/util/parsing/json/Parser$$anonfun$objEntry$1
	dup
	aload_0
	invokespecial	Method scala/util/parsing/json/Parser$$anonfun$objEntry$1."<init>":(Lscala/util/parsing/json/Parser;)V
	invokevirtual	Method scala/util/parsing/combinator/Parsers$Parser.$tilde:(Lscala/Function0;)Lscala/util/parsing/combinator/Parsers$Parser;
	new	class scala/util/parsing/json/Parser$$anonfun$objEntry$2
	dup
	aload_0
	invokespecial	Method scala/util/parsing/json/Parser$$anonfun$objEntry$2."<init>":(Lscala/util/parsing/json/Parser;)V
	invokevirtual	Method scala/util/parsing/combinator/Parsers$Parser.$up$up:(Lscala/Function1;)Lscala/util/parsing/combinator/Parsers$Parser;
	areturn
  Labels:
  Signature: length = 0x2
   00 FFFFFFC0 

public scala.util.parsing.combinator.Parsers$Parser jsonArray();
  Signature: ()Lscala/util/parsing/combinator/Parsers$Parser;
  Code:
   Stack=4, Locals=1, Args_size=1
	aload_0
	ldc	String [
	invokeinterface	InterfaceMethod scala/util/parsing/combinator/syntactical/StdTokenParsers.keyword:(Ljava/lang/String;)Lscala/util/parsing/combinator/Parsers$Parser;
	new	class scala/util/parsing/json/Parser$$anonfun$jsonArray$1
	dup
	aload_0
	invokespecial	Method scala/util/parsing/json/Parser$$anonfun$jsonArray$1."<init>":(Lscala/util/parsing/json/Parser;)V
	invokevirtual	Method scala/util/parsing/combinator/Parsers$Parser.$tilde$greater:(Lscala/Function0;)Lscala/util/parsing/combinator/Parsers$Parser;
	new	class scala/util/parsing/json/Parser$$anonfun$jsonArray$2
	dup
	aload_0
	invokespecial	Method scala/util/parsing/json/Parser$$anonfun$jsonArray$2."<init>":(Lscala/util/parsing/json/Parser;)V
	invokevirtual	Method scala/util/parsing/combinator/Parsers$Parser.$less$tilde:(Lscala/Function0;)Lscala/util/parsing/combinator/Parsers$Parser;
	areturn
  Labels:
  Signature: length = 0x2
   00 FFFFFFD4 

public scala.util.parsing.combinator.Parsers$Parser jsonObj();
  Signature: ()Lscala/util/parsing/combinator/Parsers$Parser;
  Code:
   Stack=4, Locals=1, Args_size=1
	aload_0
	ldc	String {
	invokeinterface	InterfaceMethod scala/util/parsing/combinator/syntactical/StdTokenParsers.keyword:(Ljava/lang/String;)Lscala/util/parsing/combinator/Parsers$Parser;
	new	class scala/util/parsing/json/Parser$$anonfun$jsonObj$1
	dup
	aload_0
	invokespecial	Method scala/util/parsing/json/Parser$$anonfun$jsonObj$1."<init>":(Lscala/util/parsing/json/Parser;)V
	invokevirtual	Method scala/util/parsing/combinator/Parsers$Parser.$tilde$greater:(Lscala/Function0;)Lscala/util/parsing/combinator/Parsers$Parser;
	new	class scala/util/parsing/json/Parser$$anonfun$jsonObj$2
	dup
	aload_0
	invokespecial	Method scala/util/parsing/json/Parser$$anonfun$jsonObj$2."<init>":(Lscala/util/parsing/json/Parser;)V
	invokevirtual	Method scala/util/parsing/combinator/Parsers$Parser.$less$tilde:(Lscala/Function0;)Lscala/util/parsing/combinator/Parsers$Parser;
	areturn
  Labels:
  Signature: length = 0x2
   00 FFFFFFDB 

public scala.util.parsing.combinator.Parsers$Parser root();
  Signature: ()Lscala/util/parsing/combinator/Parsers$Parser;
  Code:
   Stack=4, Locals=1, Args_size=1
	aload_0
	invokevirtual	Method jsonObj:()Lscala/util/parsing/combinator/Parsers$Parser;
	new	class scala/util/parsing/json/Parser$$anonfun$root$1
	dup
	aload_0
	invokespecial	Method scala/util/parsing/json/Parser$$anonfun$root$1."<init>":(Lscala/util/parsing/json/Parser;)V
	invokevirtual	Method scala/util/parsing/combinator/Parsers$Parser.$bar:(Lscala/Function0;)Lscala/util/parsing/combinator/Parsers$Parser;
	areturn
  Labels:
  Signature: length = 0x2
   00 FFFFFFD4 

public java.lang.ThreadLocal numberParser();
  Signature: ()Ljava/lang/ThreadLocal;
  Code:
   Stack=1, Locals=1, Args_size=1
	aload_0
	getfield	Field numberParser:Ljava/lang/ThreadLocal;
	areturn
  Labels:
  Signature: length = 0x2
   00 FFFFFFE1 

public void defaultNumberParser_$eq(scala.Function1);
  Signature: (Lscala/Function1;)V
  Code:
   Stack=2, Locals=2, Args_size=2
	aload_0
	aload_1
	putfield	Field defaultNumberParser:Lscala/Function1;
	return
  Labels:
  Signature: length = 0x2
   00 FFFFFFE4 

public scala.Function1 defaultNumberParser();
  Signature: ()Lscala/Function1;
  Code:
   Stack=1, Locals=1, Args_size=1
	aload_0
	getfield	Field defaultNumberParser:Lscala/Function1;
	areturn
  Labels:
  Signature: length = 0x2
   00 FFFFFFE6 

public scala.util.parsing.json.Lexer lexical();
  Signature: ()Lscala/util/parsing/json/Lexer;
  Code:
   Stack=1, Locals=1, Args_size=1
	aload_0
	getfield	Field lexical:Lscala/util/parsing/json/Lexer;
	areturn
  Labels:

public scala.Function1 mkList();
  Signature: ()Lscala/Function1;
  Code:
   Stack=1, Locals=1, Args_size=1
	aload_0
	invokestatic	Method scala/util/parsing/combinator/Parsers$class.mkList:(Lscala/util/parsing/combinator/Parsers;)Lscala/Function1;
	areturn
  Labels:

public scala.util.parsing.combinator.Parsers$Parser phrase(scala.util.parsing.combinator.Parsers$Parser);
  Signature: (Lscala/util/parsing/combinator/Parsers$Parser;)Lscala/util/parsing/combinator/Parsers$Parser;
  Code:
   Stack=2, Locals=2, Args_size=2
	aload_0
	aload_1
	invokestatic	Method scala/util/parsing/combinator/Parsers$class.phrase:(Lscala/util/parsing/combinator/Parsers;Lscala/util/parsing/combinator/Parsers$Parser;)Lscala/util/parsing/combinator/Parsers$Parser;
	areturn
  Labels:
  LocalVariableTable: 
   Start  Length  Slot  Name   Signature
   0      6      0    this       Lscala/util/parsing/json/Parser;
   0      6      1    p       Lscala/util/parsing/combinator/Parsers$Parser;


public scala.util.parsing.combinator.Parsers$Parser positioned(scala.Function0);
  Signature: (Lscala/Function0;)Lscala/util/parsing/combinator/Parsers$Parser;
  Code:
   Stack=2, Locals=2, Args_size=2
	aload_0
	aload_1
	invokestatic	Method scala/util/parsing/combinator/Parsers$class.positioned:(Lscala/util/parsing/combinator/Parsers;Lscala/Function0;)Lscala/util/parsing/combinator/Parsers$Parser;
	areturn
  Labels:
  LocalVariableTable: 
   Start  Length  Slot  Name   Signature
   0      6      0    this       Lscala/util/parsing/json/Parser;
   0      6      1    p       Lscala/Function0;


public scala.util.parsing.combinator.Parsers$Parser guard(scala.Function0);
  Signature: (Lscala/Function0;)Lscala/util/parsing/combinator/Parsers$Parser;
  Code:
   Stack=2, Locals=2, Args_size=2
	aload_0
	aload_1
	invokestatic	Method scala/util/parsing/combinator/Parsers$class.guard:(Lscala/util/parsing/combinator/Parsers;Lscala/Function0;)Lscala/util/parsing/combinator/Parsers$Parser;
	areturn
  Labels:
  LocalVariableTable: 
   Start  Length  Slot  Name   Signature
   0      6      0    this       Lscala/util/parsing/json/Parser;
   0      6      1    p       Lscala/Function0;


public scala.util.parsing.combinator.Parsers$Parser not(scala.Function0);
  Signature: (Lscala/Function0;)Lscala/util/parsing/combinator/Parsers$Parser;
  Code:
   Stack=2, Locals=2, Args_size=2
	aload_0
	aload_1
	invokestatic	Method scala/util/parsing/combinator/Parsers$class.not:(Lscala/util/parsing/combinator/Parsers;Lscala/Function0;)Lscala/util/parsing/combinator/Parsers$Parser;
	areturn
  Labels:
  LocalVariableTable: 
   Start  Length  Slot  Name   Signature
   0      6      0    this       Lscala/util/parsing/json/Parser;
   0      6      1    p       Lscala/Function0;


public scala.util.parsing.combinator.Parsers$Parser opt(scala.Function0);
  Signature: (Lscala/Function0;)Lscala/util/parsing/combinator/Parsers$Parser;
  Code:
   Stack=2, Locals=2, Args_size=2
	aload_0
	aload_1
	invokestatic	Method scala/util/parsing/combinator/Parsers$class.opt:(Lscala/util/parsing/combinator/Parsers;Lscala/Function0;)Lscala/util/parsing/combinator/Parsers$Parser;
	areturn
  Labels:
  LocalVariableTable: 
   Start  Length  Slot  Name   Signature
   0      6      0    this       Lscala/util/parsing/json/Parser;
   0      6      1    p       Lscala/Function0;


public scala.util.parsing.combinator.Parsers$Parser chainr1(scala.Function0, scala.Function0, scala.Function2, java.lang.Object);
  Signature: (Lscala/Function0;Lscala/Function0;Lscala/Function2;Ljava/lang/Object;)Lscala/util/parsing/combinator/Parsers$Parser;
  Code:
   Stack=5, Locals=5, Args_size=5
	aload_0
	aload_1
	aload_2
	aload_3
	aload	4
	invokestatic	Method scala/util/parsing/combinator/Parsers$class.chainr1:(Lscala/util/parsing/combinator/Parsers;Lscala/Function0;Lscala/Function0;Lscala/Function2;Ljava/lang/Object;)Lscala/util/parsing/combinator/Parsers$Parser;
	areturn
  Labels:
  LocalVariableTable: 
   Start  Length  Slot  Name   Signature
   0      10      0    this       Lscala/util/parsing/json/Parser;
   0      10      1    p       Lscala/Function0;
   0      10      2    q       Lscala/Function0;
   0      10      3    combine       Lscala/Function2;
   0      10      4    first       Ljava/lang/Object;


public scala.util.parsing.combinator.Parsers$Parser chainl1(scala.Function0, scala.Function0, scala.Function0);
  Signature: (Lscala/Function0;Lscala/Function0;Lscala/Function0;)Lscala/util/parsing/combinator/Parsers$Parser;
  Code:
   Stack=4, Locals=4, Args_size=4
	aload_0
	aload_1
	aload_2
	aload_3
	invokestatic	Method scala/util/parsing/combinator/Parsers$class.chainl1:(Lscala/util/parsing/combinator/Parsers;Lscala/Function0;Lscala/Function0;Lscala/Function0;)Lscala/util/parsing/combinator/Parsers$Parser;
	areturn
  Labels:
  LocalVariableTable: 
   Start  Length  Slot  Name   Signature
   0      8      0    this       Lscala/util/parsing/json/Parser;
   0      8      1    first       Lscala/Function0;
   0      8      2    p       Lscala/Function0;
   0      8      3    q       Lscala/Function0;


public scala.util.parsing.combinator.Parsers$Parser chainl1(scala.Function0, scala.Function0);
  Signature: (Lscala/Function0;Lscala/Function0;)Lscala/util/parsing/combinator/Parsers$Parser;
  Code:
   Stack=3, Locals=3, Args_size=3
	aload_0
	aload_1
	aload_2
	invokestatic	Method scala/util/parsing/combinator/Parsers$class.chainl1:(Lscala/util/parsing/combinator/Parsers;Lscala/Function0;Lscala/Function0;)Lscala/util/parsing/combinator/Parsers$Parser;
	areturn
  Labels:
  LocalVariableTable: 
   Start  Length  Slot  Name   Signature
   0      7      0    this       Lscala/util/parsing/json/Parser;
   0      7      1    p       Lscala/Function0;
   0      7      2    q       Lscala/Function0;


public scala.util.parsing.combinator.Parsers$Parser rep1sep(scala.Function0, scala.Function0);
  Signature: (Lscala/Function0;Lscala/Function0;)Lscala/util/parsing/combinator/Parsers$Parser;
  Code:
   Stack=3, Locals=3, Args_size=3
	aload_0
	aload_1
	aload_2
	invokestatic	Method scala/util/parsing/combinator/Parsers$class.rep1sep:(Lscala/util/parsing/combinator/Parsers;Lscala/Function0;Lscala/Function0;)Lscala/util/parsing/combinator/Parsers$Parser;
	areturn
  Labels:
  LocalVariableTable: 
   Start  Length  Slot  Name   Signature
   0      7      0    this       Lscala/util/parsing/json/Parser;
   0      7      1    p       Lscala/Function0;
   0      7      2    q       Lscala/Function0;


public scala.util.parsing.combinator.Parsers$Parser repN(int, scala.Function0);
  Signature: (ILscala/Function0;)Lscala/util/parsing/combinator/Parsers$Parser;
  Code:
   Stack=3, Locals=3, Args_size=3
	aload_0
	iload_1
	aload_2
	invokestatic	Method scala/util/parsing/combinator/Parsers$class.repN:(Lscala/util/parsing/combinator/Parsers;ILscala/Function0;)Lscala/util/parsing/combinator/Parsers$Parser;
	areturn
  Labels:
  LocalVariableTable: 
   Start  Length  Slot  Name   Signature
   0      7      0    this       Lscala/util/parsing/json/Parser;
   0      7      1    n       I
   0      7      2    p       Lscala/Function0;


public scala.util.parsing.combinator.Parsers$Parser rep1(scala.Function0, scala.Function0);
  Signature: (Lscala/Function0;Lscala/Function0;)Lscala/util/parsing/combinator/Parsers$Parser;
  Code:
   Stack=3, Locals=3, Args_size=3
	aload_0
	aload_1
	aload_2
	invokestatic	Method scala/util/parsing/combinator/Parsers$class.rep1:(Lscala/util/parsing/combinator/Parsers;Lscala/Function0;Lscala/Function0;)Lscala/util/parsing/combinator/Parsers$Parser;
	areturn
  Labels:
  LocalVariableTable: 
   Start  Length  Slot  Name   Signature
   0      7      0    this       Lscala/util/parsing/json/Parser;
   0      7      1    first       Lscala/Function0;
   0      7      2    p       Lscala/Function0;


public scala.util.parsing.combinator.Parsers$Parser rep1(scala.Function0);
  Signature: (Lscala/Function0;)Lscala/util/parsing/combinator/Parsers$Parser;
  Code:
   Stack=2, Locals=2, Args_size=2
	aload_0
	aload_1
	invokestatic	Method scala/util/parsing/combinator/Parsers$class.rep1:(Lscala/util/parsing/combinator/Parsers;Lscala/Function0;)Lscala/util/parsing/combinator/Parsers$Parser;
	areturn
  Labels:
  LocalVariableTable: 
   Start  Length  Slot  Name   Signature
   0      6      0    this       Lscala/util/parsing/json/Parser;
   0      6      1    p       Lscala/Function0;


public scala.util.parsing.combinator.Parsers$Parser repsep(scala.Function0, scala.Function0);
  Signature: (Lscala/Function0;Lscala/Function0;)Lscala/util/parsing/combinator/Parsers$Parser;
  Code:
   Stack=3, Locals=3, Args_size=3
	aload_0
	aload_1
	aload_2
	invokestatic	Method scala/util/parsing/combinator/Parsers$class.repsep:(Lscala/util/parsing/combinator/Parsers;Lscala/Function0;Lscala/Function0;)Lscala/util/parsing/combinator/Parsers$Parser;
	areturn
  Labels:
  LocalVariableTable: 
   Start  Length  Slot  Name   Signature
   0      7      0    this       Lscala/util/parsing/json/Parser;
   0      7      1    p       Lscala/Function0;
   0      7      2    q       Lscala/Function0;


public scala.util.parsing.combinator.Parsers$Parser rep(scala.Function0);
  Signature: (Lscala/Function0;)Lscala/util/parsing/combinator/Parsers$Parser;
  Code:
   Stack=2, Locals=2, Args_size=2
	aload_0
	aload_1
	invokestatic	Method scala/util/parsing/combinator/Parsers$class.rep:(Lscala/util/parsing/combinator/Parsers;Lscala/Function0;)Lscala/util/parsing/combinator/Parsers$Parser;
	areturn
  Labels:
  LocalVariableTable: 
   Start  Length  Slot  Name   Signature
   0      6      0    this       Lscala/util/parsing/json/Parser;
   0      6      1    p       Lscala/Function0;


public scala.util.parsing.combinator.Parsers$Parser log(scala.Function0, java.lang.String);
  Signature: (Lscala/Function0;Ljava/lang/String;)Lscala/util/parsing/combinator/Parsers$Parser;
  Code:
   Stack=3, Locals=3, Args_size=3
	aload_0
	aload_1
	aload_2
	invokestatic	Method scala/util/parsing/combinator/Parsers$class.log:(Lscala/util/parsing/combinator/Parsers;Lscala/Function0;Ljava/lang/String;)Lscala/util/parsing/combinator/Parsers$Parser;
	areturn
  Labels:
  LocalVariableTable: 
   Start  Length  Slot  Name   Signature
   0      7      0    this       Lscala/util/parsing/json/Parser;
   0      7      1    p       Lscala/Function0;
   0      7      2    name       Ljava/lang/String;


public scala.util.parsing.combinator.Parsers$Parser success(java.lang.Object);
  Signature: (Ljava/lang/Object;)Lscala/util/parsing/combinator/Parsers$Parser;
  Code:
   Stack=2, Locals=2, Args_size=2
	aload_0
	aload_1
	invokestatic	Method scala/util/parsing/combinator/Parsers$class.success:(Lscala/util/parsing/combinator/Parsers;Ljava/lang/Object;)Lscala/util/parsing/combinator/Parsers$Parser;
	areturn
  Labels:
  LocalVariableTable: 
   Start  Length  Slot  Name   Signature
   0      6      0    this       Lscala/util/parsing/json/Parser;
   0      6      1    v       Ljava/lang/Object;


public scala.util.parsing.combinator.Parsers$Parser err(java.lang.String);
  Signature: (Ljava/lang/String;)Lscala/util/parsing/combinator/Parsers$Parser;
  Code:
   Stack=2, Locals=2, Args_size=2
	aload_0
	aload_1
	invokestatic	Method scala/util/parsing/combinator/Parsers$class.err:(Lscala/util/parsing/combinator/Parsers;Ljava/lang/String;)Lscala/util/parsing/combinator/Parsers$Parser;
	areturn
  Labels:
  LocalVariableTable: 
   Start  Length  Slot  Name   Signature
   0      6      0    this       Lscala/util/parsing/json/Parser;
   0      6      1    msg       Ljava/lang/String;


public scala.util.parsing.combinator.Parsers$Parser failure(java.lang.String);
  Signature: (Ljava/lang/String;)Lscala/util/parsing/combinator/Parsers$Parser;
  Code:
   Stack=2, Locals=2, Args_size=2
	aload_0
	aload_1
	invokestatic	Method scala/util/parsing/combinator/Parsers$class.failure:(Lscala/util/parsing/combinator/Parsers;Ljava/lang/String;)Lscala/util/parsing/combinator/Parsers$Parser;
	areturn
  Labels:
  LocalVariableTable: 
   Start  Length  Slot  Name   Signature
   0      6      0    this       Lscala/util/parsing/json/Parser;
   0      6      1    msg       Ljava/lang/String;


public scala.util.parsing.combinator.Parsers$Parser acceptSeq(java.lang.Object, scala.Function1);
  Signature: (Ljava/lang/Object;Lscala/Function1;)Lscala/util/parsing/combinator/Parsers$Parser;
  Code:
   Stack=3, Locals=3, Args_size=3
	aload_0
	aload_1
	aload_2
	invokestatic	Method scala/util/parsing/combinator/Parsers$class.acceptSeq:(Lscala/util/parsing/combinator/Parsers;Ljava/lang/Object;Lscala/Function1;)Lscala/util/parsing/combinator/Parsers$Parser;
	areturn
  Labels:
  LocalVariableTable: 
   Start  Length  Slot  Name   Signature
   0      7      0    this       Lscala/util/parsing/json/Parser;
   0      7      1    es       Ljava/lang/Object;
   0      7      2    evidence$2       Lscala/Function1;


public scala.util.parsing.combinator.Parsers$Parser acceptMatch(java.lang.String, scala.PartialFunction);
  Signature: (Ljava/lang/String;Lscala/PartialFunction;)Lscala/util/parsing/combinator/Parsers$Parser;
  Code:
   Stack=3, Locals=3, Args_size=3
	aload_0
	aload_1
	aload_2
	invokestatic	Method scala/util/parsing/combinator/Parsers$class.acceptMatch:(Lscala/util/parsing/combinator/Parsers;Ljava/lang/String;Lscala/PartialFunction;)Lscala/util/parsing/combinator/Parsers$Parser;
	areturn
  Labels:
  LocalVariableTable: 
   Start  Length  Slot  Name   Signature
   0      7      0    this       Lscala/util/parsing/json/Parser;
   0      7      1    expected       Ljava/lang/String;
   0      7      2    f       Lscala/PartialFunction;


public scala.util.parsing.combinator.Parsers$Parser acceptIf(scala.Function1, scala.Function1);
  Signature: (Lscala/Function1;Lscala/Function1;)Lscala/util/parsing/combinator/Parsers$Parser;
  Code:
   Stack=3, Locals=3, Args_size=3
	aload_0
	aload_1
	aload_2
	invokestatic	Method scala/util/parsing/combinator/Parsers$class.acceptIf:(Lscala/util/parsing/combinator/Parsers;Lscala/Function1;Lscala/Function1;)Lscala/util/parsing/combinator/Parsers$Parser;
	areturn
  Labels:
  LocalVariableTable: 
   Start  Length  Slot  Name   Signature
   0      7      0    this       Lscala/util/parsing/json/Parser;
   0      7      1    p       Lscala/Function1;
   0      7      2    err       Lscala/Function1;


public scala.util.parsing.combinator.Parsers$Parser accept(java.lang.String, scala.PartialFunction);
  Signature: (Ljava/lang/String;Lscala/PartialFunction;)Lscala/util/parsing/combinator/Parsers$Parser;
  Code:
   Stack=3, Locals=3, Args_size=3
	aload_0
	aload_1
	aload_2
	invokestatic	Method scala/util/parsing/combinator/Parsers$class.accept:(Lscala/util/parsing/combinator/Parsers;Ljava/lang/String;Lscala/PartialFunction;)Lscala/util/parsing/combinator/Parsers$Parser;
	areturn
  Labels:
  LocalVariableTable: 
   Start  Length  Slot  Name   Signature
   0      7      0    this       Lscala/util/parsing/json/Parser;
   0      7      1    expected       Ljava/lang/String;
   0      7      2    f       Lscala/PartialFunction;


public scala.util.parsing.combinator.Parsers$Parser accept(java.lang.Object, scala.Function1);
  Signature: (Ljava/lang/Object;Lscala/Function1;)Lscala/util/parsing/combinator/Parsers$Parser;
  Code:
   Stack=3, Locals=3, Args_size=3
	aload_0
	aload_1
	aload_2
	invokestatic	Method scala/util/parsing/combinator/Parsers$class.accept:(Lscala/util/parsing/combinator/Parsers;Ljava/lang/Object;Lscala/Function1;)Lscala/util/parsing/combinator/Parsers$Parser;
	areturn
  Labels:
  LocalVariableTable: 
   Start  Length  Slot  Name   Signature
   0      7      0    this       Lscala/util/parsing/json/Parser;
   0      7      1    es       Ljava/lang/Object;
   0      7      2    evidence$1       Lscala/Function1;


public scala.util.parsing.combinator.Parsers$Parser accept(java.lang.Object);
  Signature: (Ljava/lang/Object;)Lscala/util/parsing/combinator/Parsers$Parser;
  Code:
   Stack=2, Locals=2, Args_size=2
	aload_0
	aload_1
	invokestatic	Method scala/util/parsing/combinator/Parsers$class.accept:(Lscala/util/parsing/combinator/Parsers;Ljava/lang/Object;)Lscala/util/parsing/combinator/Parsers$Parser;
	areturn
  Labels:
  LocalVariableTable: 
   Start  Length  Slot  Name   Signature
   0      6      0    this       Lscala/util/parsing/json/Parser;
   0      6      1    e       Ljava/lang/Object;


public scala.util.parsing.combinator.Parsers$Parser elem(java.lang.Object);
  Signature: (Ljava/lang/Object;)Lscala/util/parsing/combinator/Parsers$Parser;
  Code:
   Stack=2, Locals=2, Args_size=2
	aload_0
	aload_1
	invokestatic	Method scala/util/parsing/combinator/Parsers$class.elem:(Lscala/util/parsing/combinator/Parsers;Ljava/lang/Object;)Lscala/util/parsing/combinator/Parsers$Parser;
	areturn
  Labels:
  LocalVariableTable: 
   Start  Length  Slot  Name   Signature
   0      6      0    this       Lscala/util/parsing/json/Parser;
   0      6      1    e       Ljava/lang/Object;


public scala.util.parsing.combinator.Parsers$Parser elem(java.lang.String, scala.Function1);
  Signature: (Ljava/lang/String;Lscala/Function1;)Lscala/util/parsing/combinator/Parsers$Parser;
  Code:
   Stack=3, Locals=3, Args_size=3
	aload_0
	aload_1
	aload_2
	invokestatic	Method scala/util/parsing/combinator/Parsers$class.elem:(Lscala/util/parsing/combinator/Parsers;Ljava/lang/String;Lscala/Function1;)Lscala/util/parsing/combinator/Parsers$Parser;
	areturn
  Labels:
  LocalVariableTable: 
   Start  Length  Slot  Name   Signature
   0      7      0    this       Lscala/util/parsing/json/Parser;
   0      7      1    kind       Ljava/lang/String;
   0      7      2    p       Lscala/Function1;


public scala.util.parsing.combinator.Parsers$Parser commit(scala.Function0);
  Signature: (Lscala/Function0;)Lscala/util/parsing/combinator/Parsers$Parser;
  Code:
   Stack=2, Locals=2, Args_size=2
	aload_0
	aload_1
	invokestatic	Method scala/util/parsing/combinator/Parsers$class.commit:(Lscala/util/parsing/combinator/Parsers;Lscala/Function0;)Lscala/util/parsing/combinator/Parsers$Parser;
	areturn
  Labels:
  LocalVariableTable: 
   Start  Length  Slot  Name   Signature
   0      6      0    this       Lscala/util/parsing/json/Parser;
   0      6      1    p       Lscala/Function0;


public scala.util.parsing.combinator.Parsers$Parser OnceParser(scala.Function1);
  Signature: (Lscala/Function1;)Lscala/util/parsing/combinator/Parsers$Parser;
  Code:
   Stack=2, Locals=2, Args_size=2
	aload_0
	aload_1
	invokestatic	Method scala/util/parsing/combinator/Parsers$class.OnceParser:(Lscala/util/parsing/combinator/Parsers;Lscala/Function1;)Lscala/util/parsing/combinator/Parsers$Parser;
	areturn
  Labels:
  LocalVariableTable: 
   Start  Length  Slot  Name   Signature
   0      6      0    this       Lscala/util/parsing/json/Parser;
   0      6      1    f       Lscala/Function1;


public scala.util.parsing.combinator.Parsers$Parser Parser(scala.Function1);
  Signature: (Lscala/Function1;)Lscala/util/parsing/combinator/Parsers$Parser;
  Code:
   Stack=2, Locals=2, Args_size=2
	aload_0
	aload_1
	invokestatic	Method scala/util/parsing/combinator/Parsers$class.Parser:(Lscala/util/parsing/combinator/Parsers;Lscala/Function1;)Lscala/util/parsing/combinator/Parsers$Parser;
	areturn
  Labels:
  LocalVariableTable: 
   Start  Length  Slot  Name   Signature
   0      6      0    this       Lscala/util/parsing/json/Parser;
   0      6      1    f       Lscala/Function1;


public final scala.util.parsing.combinator.Parsers$$tilde$ $tilde();
  Signature: ()Lscala/util/parsing/combinator/Parsers$$tilde$;
  Code:
   Stack=4, Locals=1, Args_size=1
	aload_0
	getfield	Field $tilde$module:Lscala/util/parsing/combinator/Parsers$$tilde$;
	ifnonnull	l1 // aload_0
	aload_0
	new	class scala/util/parsing/combinator/Parsers$$tilde$
	dup
	aload_0
	invokespecial	Method scala/util/parsing/combinator/Parsers$$tilde$."<init>":(Lscala/util/parsing/combinator/Parsers;)V
	putfield	Field $tilde$module:Lscala/util/parsing/combinator/Parsers$$tilde$;
l1	aload_0
	getfield	Field $tilde$module:Lscala/util/parsing/combinator/Parsers$$tilde$;
	areturn
  Labels:
   	l1 = 19 // aload_0

public final scala.util.parsing.combinator.Parsers$Error$ Error();
  Signature: ()Lscala/util/parsing/combinator/Parsers$Error$;
  Code:
   Stack=4, Locals=1, Args_size=1
	aload_0
	getfield	Field Error$module:Lscala/util/parsing/combinator/Parsers$Error$;
	ifnonnull	l1 // aload_0
	aload_0
	new	class scala/util/parsing/combinator/Parsers$Error$
	dup
	aload_0
	invokespecial	Method scala/util/parsing/combinator/Parsers$Error$."<init>":(Lscala/util/parsing/combinator/Parsers;)V
	putfield	Field Error$module:Lscala/util/parsing/combinator/Parsers$Error$;
l1	aload_0
	getfield	Field Error$module:Lscala/util/parsing/combinator/Parsers$Error$;
	areturn
  Labels:
   	l1 = 19 // aload_0

public final scala.util.parsing.combinator.Parsers$Failure$ Failure();
  Signature: ()Lscala/util/parsing/combinator/Parsers$Failure$;
  Code:
   Stack=4, Locals=1, Args_size=1
	aload_0
	getfield	Field Failure$module:Lscala/util/parsing/combinator/Parsers$Failure$;
	ifnonnull	l1 // aload_0
	aload_0
	new	class scala/util/parsing/combinator/Parsers$Failure$
	dup
	aload_0
	invokespecial	Method scala/util/parsing/combinator/Parsers$Failure$."<init>":(Lscala/util/parsing/combinator/Parsers;)V
	putfield	Field Failure$module:Lscala/util/parsing/combinator/Parsers$Failure$;
l1	aload_0
	getfield	Field Failure$module:Lscala/util/parsing/combinator/Parsers$Failure$;
	areturn
  Labels:
   	l1 = 19 // aload_0

public final scala.util.parsing.combinator.Parsers$NoSuccess$ NoSuccess();
  Signature: ()Lscala/util/parsing/combinator/Parsers$NoSuccess$;
  Code:
   Stack=4, Locals=1, Args_size=1
	aload_0
	getfield	Field NoSuccess$module:Lscala/util/parsing/combinator/Parsers$NoSuccess$;
	ifnonnull	l1 // aload_0
	aload_0
	new	class scala/util/parsing/combinator/Parsers$NoSuccess$
	dup
	aload_0
	invokespecial	Method scala/util/parsing/combinator/Parsers$NoSuccess$."<init>":(Lscala/util/parsing/combinator/Parsers;)V
	putfield	Field NoSuccess$module:Lscala/util/parsing/combinator/Parsers$NoSuccess$;
l1	aload_0
	getfield	Field NoSuccess$module:Lscala/util/parsing/combinator/Parsers$NoSuccess$;
	areturn
  Labels:
   	l1 = 19 // aload_0

public void lastNoSuccess_$eq(scala.util.parsing.combinator.Parsers$NoSuccess);
  Signature: (Lscala/util/parsing/combinator/Parsers$NoSuccess;)V
  Code:
   Stack=2, Locals=2, Args_size=2
	aload_0
	aload_1
	putfield	Field lastNoSuccess:Lscala/util/parsing/combinator/Parsers$NoSuccess;
	return
  Labels:

public scala.util.parsing.combinator.Parsers$NoSuccess lastNoSuccess();
  Signature: ()Lscala/util/parsing/combinator/Parsers$NoSuccess;
  Code:
   Stack=1, Locals=1, Args_size=1
	aload_0
	getfield	Field lastNoSuccess:Lscala/util/parsing/combinator/Parsers$NoSuccess;
	areturn
  Labels:

public final scala.util.parsing.combinator.Parsers$Success$ Success();
  Signature: ()Lscala/util/parsing/combinator/Parsers$Success$;
  Code:
   Stack=4, Locals=1, Args_size=1
	aload_0
	getfield	Field Success$module:Lscala/util/parsing/combinator/Parsers$Success$;
	ifnonnull	l1 // aload_0
	aload_0
	new	class scala/util/parsing/combinator/Parsers$Success$
	dup
	aload_0
	invokespecial	Method scala/util/parsing/combinator/Parsers$Success$."<init>":(Lscala/util/parsing/combinator/Parsers;)V
	putfield	Field Success$module:Lscala/util/parsing/combinator/Parsers$Success$;
l1	aload_0
	getfield	Field Success$module:Lscala/util/parsing/combinator/Parsers$Success$;
	areturn
  Labels:
   	l1 = 19 // aload_0

public scala.util.parsing.combinator.Parsers$Parser ident();
  Signature: ()Lscala/util/parsing/combinator/Parsers$Parser;
  Code:
   Stack=1, Locals=1, Args_size=1
	aload_0
	invokestatic	Method scala/util/parsing/combinator/syntactical/StdTokenParsers$class.ident:(Lscala/util/parsing/combinator/syntactical/StdTokenParsers;)Lscala/util/parsing/combinator/Parsers$Parser;
	areturn
  Labels:

public scala.util.parsing.combinator.Parsers$Parser stringLit();
  Signature: ()Lscala/util/parsing/combinator/Parsers$Parser;
  Code:
   Stack=1, Locals=1, Args_size=1
	aload_0
	invokestatic	Method scala/util/parsing/combinator/syntactical/StdTokenParsers$class.stringLit:(Lscala/util/parsing/combinator/syntactical/StdTokenParsers;)Lscala/util/parsing/combinator/Parsers$Parser;
	areturn
  Labels:

public scala.util.parsing.combinator.Parsers$Parser numericLit();
  Signature: ()Lscala/util/parsing/combinator/Parsers$Parser;
  Code:
   Stack=1, Locals=1, Args_size=1
	aload_0
	invokestatic	Method scala/util/parsing/combinator/syntactical/StdTokenParsers$class.numericLit:(Lscala/util/parsing/combinator/syntactical/StdTokenParsers;)Lscala/util/parsing/combinator/Parsers$Parser;
	areturn
  Labels:

public scala.util.parsing.combinator.Parsers$Parser keyword(java.lang.String);
  Signature: (Ljava/lang/String;)Lscala/util/parsing/combinator/Parsers$Parser;
  Code:
   Stack=2, Locals=2, Args_size=2
	aload_0
	aload_1
	invokestatic	Method scala/util/parsing/combinator/syntactical/StdTokenParsers$class.keyword:(Lscala/util/parsing/combinator/syntactical/StdTokenParsers;Ljava/lang/String;)Lscala/util/parsing/combinator/Parsers$Parser;
	areturn
  Labels:
  LocalVariableTable: 
   Start  Length  Slot  Name   Signature
   0      6      0    this       Lscala/util/parsing/json/Parser;
   0      6      1    chars       Ljava/lang/String;


public void scala$util$parsing$combinator$syntactical$StdTokenParsers$_setter_$keywordCache_$eq(scala.collection.mutable.HashMap);
  Signature: (Lscala/collection/mutable/HashMap;)V
  Code:
   Stack=2, Locals=2, Args_size=2
	aload_0
	aload_1
	putfield	Field keywordCache:Lscala/collection/mutable/HashMap;
	return
  Labels:

public scala.collection.mutable.HashMap keywordCache();
  Signature: ()Lscala/collection/mutable/HashMap;
  Code:
   Stack=1, Locals=1, Args_size=1
	aload_0
	getfield	Field keywordCache:Lscala/collection/mutable/HashMap;
	areturn
  Labels:

public scala.Function1 headOptionTailToFunList(scala.Function1);
  Signature: (Lscala/Function1;)Lscala/Function1;
  Code:
   Stack=2, Locals=2, Args_size=2
	aload_0
	aload_1
	invokestatic	Method scala/util/parsing/combinator/ImplicitConversions$class.headOptionTailToFunList:(Lscala/util/parsing/combinator/ImplicitConversions;Lscala/Function1;)Lscala/Function1;
	areturn
  Labels:
  LocalVariableTable: 
   Start  Length  Slot  Name   Signature
   0      6      0    this       Lscala/util/parsing/json/Parser;
   0      6      1    f       Lscala/Function1;


public scala.Function1 flatten5(scala.Function5);
  Signature: (Lscala/Function5;)Lscala/Function1;
  Code:
   Stack=2, Locals=2, Args_size=2
	aload_0
	aload_1
	invokestatic	Method scala/util/parsing/combinator/ImplicitConversions$class.flatten5:(Lscala/util/parsing/combinator/ImplicitConversions;Lscala/Function5;)Lscala/Function1;
	areturn
  Labels:
  LocalVariableTable: 
   Start  Length  Slot  Name   Signature
   0      6      0    this       Lscala/util/parsing/json/Parser;
   0      6      1    f       Lscala/Function5;


public scala.Function1 flatten4(scala.Function4);
  Signature: (Lscala/Function4;)Lscala/Function1;
  Code:
   Stack=2, Locals=2, Args_size=2
	aload_0
	aload_1
	invokestatic	Method scala/util/parsing/combinator/ImplicitConversions$class.flatten4:(Lscala/util/parsing/combinator/ImplicitConversions;Lscala/Function4;)Lscala/Function1;
	areturn
  Labels:
  LocalVariableTable: 
   Start  Length  Slot  Name   Signature
   0      6      0    this       Lscala/util/parsing/json/Parser;
   0      6      1    f       Lscala/Function4;


public scala.Function1 flatten3(scala.Function3);
  Signature: (Lscala/Function3;)Lscala/Function1;
  Code:
   Stack=2, Locals=2, Args_size=2
	aload_0
	aload_1
	invokestatic	Method scala/util/parsing/combinator/ImplicitConversions$class.flatten3:(Lscala/util/parsing/combinator/ImplicitConversions;Lscala/Function3;)Lscala/Function1;
	areturn
  Labels:
  LocalVariableTable: 
   Start  Length  Slot  Name   Signature
   0      6      0    this       Lscala/util/parsing/json/Parser;
   0      6      1    f       Lscala/Function3;


public scala.Function1 flatten2(scala.Function2);
  Signature: (Lscala/Function2;)Lscala/Function1;
  Code:
   Stack=2, Locals=2, Args_size=2
	aload_0
	aload_1
	invokestatic	Method scala/util/parsing/combinator/ImplicitConversions$class.flatten2:(Lscala/util/parsing/combinator/ImplicitConversions;Lscala/Function2;)Lscala/Function1;
	areturn
  Labels:
  LocalVariableTable: 
   Start  Length  Slot  Name   Signature
   0      6      0    this       Lscala/util/parsing/json/Parser;
   0      6      1    f       Lscala/Function2;


}

