Compiled from "Parser.scala"
public final class scala.util.parsing.json.Parser$$anonfun$number$1 extends java.lang.Object implements scala.PartialFunction,scala.ScalaObject,java.io.Serializable
  SourceFile: "Parser.scala"
  Scala: length = 0x
   
  InnerClass: 
   public abstract #128= #38 of #127; //Token=class scala/util/parsing/syntax/Tokens$Token of class scala/util/parsing/syntax/Tokens
   public #131= #60 of #130; //NumericLit=class scala/util/parsing/syntax/StdTokens$NumericLit of class scala/util/parsing/syntax/StdTokens
   public final #132= #15 of #68; //$anonfun$number$1=class scala/util/parsing/json/Parser$$anonfun$number$1 of class scala/util/parsing/json/Parser
  minor version: 0
  major version: 49
  Constant pool:
const #1 = Asciz	SourceFile;
const #2 = Asciz	Parser.scala;
const #3 = Asciz	$outer;
const #4 = Asciz	Lscala/util/parsing/json/Parser;;
const #5 = Asciz	<init>;
const #6 = Asciz	(Lscala/util/parsing/json/Parser;)V;
const #7 = Asciz	Code;
const #8 = Asciz	LineNumberTable;
const #9 = Asciz	java/lang/NullPointerException;
const #10 = class	#9;	//  java/lang/NullPointerException
const #11 = Asciz	()V;
const #12 = NameAndType	#5:#11;//  "<init>":()V
const #13 = Method	#10.#12;	//  java/lang/NullPointerException."<init>":()V
const #14 = Asciz	scala/util/parsing/json/Parser$$anonfun$number$1;
const #15 = class	#14;	//  scala/util/parsing/json/Parser$$anonfun$number$1
const #16 = NameAndType	#3:#4;//  $outer:Lscala/util/parsing/json/Parser;
const #17 = Field	#15.#16;	//  scala/util/parsing/json/Parser$$anonfun$number$1.$outer:Lscala/util/parsing/json/Parser;
const #18 = Asciz	java/lang/Object;
const #19 = class	#18;	//  java/lang/Object
const #20 = Method	#19.#12;	//  java/lang/Object."<init>":()V
const #21 = Asciz	scala/Function1$class;
const #22 = class	#21;	//  scala/Function1$class
const #23 = Asciz	$init$;
const #24 = Asciz	(Lscala/Function1;)V;
const #25 = NameAndType	#23:#24;//  $init$:(Lscala/Function1;)V
const #26 = Method	#22.#25;	//  scala/Function1$class.$init$:(Lscala/Function1;)V
const #27 = Asciz	scala/PartialFunction$class;
const #28 = class	#27;	//  scala/PartialFunction$class
const #29 = Asciz	(Lscala/PartialFunction;)V;
const #30 = NameAndType	#23:#29;//  $init$:(Lscala/PartialFunction;)V
const #31 = Method	#28.#30;	//  scala/PartialFunction$class.$init$:(Lscala/PartialFunction;)V
const #32 = Asciz	this;
const #33 = Asciz	Lscala/util/parsing/json/Parser$$anonfun$number$1;;
const #34 = Asciz	LocalVariableTable;
const #35 = Asciz	apply;
const #36 = Asciz	(Ljava/lang/Object;)Ljava/lang/Object;;
const #37 = Asciz	scala/util/parsing/syntax/Tokens$Token;
const #38 = class	#37;	//  scala/util/parsing/syntax/Tokens$Token
const #39 = Asciz	(Lscala/util/parsing/syntax/Tokens$Token;)Ljava/lang/Object;;
const #40 = NameAndType	#35:#39;//  apply:(Lscala/util/parsing/syntax/Tokens$Token;)Ljava/lang/Object;
const #41 = Method	#15.#40;	//  scala/util/parsing/json/Parser$$anonfun$number$1.apply:(Lscala/util/parsing/syntax/Tokens$Token;)Ljava/lang/Object;
const #42 = Asciz	v1;
const #43 = Asciz	Ljava/lang/Object;;
const #44 = Asciz	isDefinedAt;
const #45 = Asciz	(Ljava/lang/Object;)Z;
const #46 = Asciz	(Lscala/util/parsing/syntax/Tokens$Token;)Z;
const #47 = NameAndType	#44:#46;//  isDefinedAt:(Lscala/util/parsing/syntax/Tokens$Token;)Z
const #48 = Method	#15.#47;	//  scala/util/parsing/json/Parser$$anonfun$number$1.isDefinedAt:(Lscala/util/parsing/syntax/Tokens$Token;)Z
const #49 = Asciz	x;
const #50 = Asciz	andThen;
const #51 = Asciz	(Lscala/Function1;)Lscala/Function1;;
const #52 = Asciz	scala/PartialFunction;
const #53 = class	#52;	//  scala/PartialFunction
const #54 = Asciz	(Lscala/Function1;)Lscala/PartialFunction;;
const #55 = NameAndType	#50:#54;//  andThen:(Lscala/Function1;)Lscala/PartialFunction;
const #56 = InterfaceMethod	#53.#55;	//  scala/PartialFunction.andThen:(Lscala/Function1;)Lscala/PartialFunction;
const #57 = Asciz	g;
const #58 = Asciz	Lscala/Function1;;
const #59 = Asciz	scala/util/parsing/syntax/StdTokens$NumericLit;
const #60 = class	#59;	//  scala/util/parsing/syntax/StdTokens$NumericLit
const #61 = Asciz	temp13;
const #62 = Asciz	Lscala/util/parsing/syntax/Tokens$Token;;
const #63 = Asciz	chars;
const #64 = Asciz	()Ljava/lang/String;;
const #65 = NameAndType	#63:#64;//  chars:()Ljava/lang/String;
const #66 = Method	#60.#65;	//  scala/util/parsing/syntax/StdTokens$NumericLit.chars:()Ljava/lang/String;
const #67 = Asciz	scala/util/parsing/json/Parser;
const #68 = class	#67;	//  scala/util/parsing/json/Parser
const #69 = Asciz	numberParser;
const #70 = Asciz	()Ljava/lang/ThreadLocal;;
const #71 = NameAndType	#69:#70;//  numberParser:()Ljava/lang/ThreadLocal;
const #72 = Method	#68.#71;	//  scala/util/parsing/json/Parser.numberParser:()Ljava/lang/ThreadLocal;
const #73 = Asciz	java/lang/ThreadLocal;
const #74 = class	#73;	//  java/lang/ThreadLocal
const #75 = Asciz	get;
const #76 = Asciz	()Ljava/lang/Object;;
const #77 = NameAndType	#75:#76;//  get:()Ljava/lang/Object;
const #78 = Method	#74.#77;	//  java/lang/ThreadLocal.get:()Ljava/lang/Object;
const #79 = Asciz	scala/Function1;
const #80 = class	#79;	//  scala/Function1
const #81 = Asciz	scala/runtime/ScalaRunTime$;
const #82 = class	#81;	//  scala/runtime/ScalaRunTime$
const #83 = Asciz	MODULE$;
const #84 = Asciz	Lscala/runtime/ScalaRunTime$;;
const #85 = NameAndType	#83:#84;//  MODULE$:Lscala/runtime/ScalaRunTime$;
const #86 = Field	#82.#85;	//  scala/runtime/ScalaRunTime$.MODULE$:Lscala/runtime/ScalaRunTime$;
const #87 = Asciz	boxArray;
const #88 = Asciz	(Ljava/lang/Object;)Lscala/runtime/BoxedArray;;
const #89 = NameAndType	#87:#88;//  boxArray:(Ljava/lang/Object;)Lscala/runtime/BoxedArray;
const #90 = Method	#82.#89;	//  scala/runtime/ScalaRunTime$.boxArray:(Ljava/lang/Object;)Lscala/runtime/BoxedArray;
const #91 = NameAndType	#35:#36;//  apply:(Ljava/lang/Object;)Ljava/lang/Object;
const #92 = InterfaceMethod	#80.#91;	//  scala/Function1.apply:(Ljava/lang/Object;)Ljava/lang/Object;
const #93 = Asciz	scala/MatchError;
const #94 = class	#93;	//  scala/MatchError
const #95 = Asciz	toString;
const #96 = NameAndType	#95:#64;//  toString:()Ljava/lang/String;
const #97 = Method	#38.#96;	//  scala/util/parsing/syntax/Tokens$Token.toString:()Ljava/lang/String;
const #98 = Asciz	(Ljava/lang/String;)V;
const #99 = NameAndType	#5:#98;//  "<init>":(Ljava/lang/String;)V
const #100 = Method	#94.#99;	//  scala/MatchError."<init>":(Ljava/lang/String;)V
const #101 = Asciz	temp10;
const #102 = Asciz	temp11;
const #103 = Asciz	Lscala/util/parsing/syntax/StdTokens$NumericLit;;
const #104 = Asciz	temp12;
const #105 = Asciz	Ljava/lang/String;;
const #106 = Asciz	compose;
const #107 = Asciz	(Lscala/Function1;Lscala/Function1;)Lscala/Function1;;
const #108 = NameAndType	#106:#107;//  compose:(Lscala/Function1;Lscala/Function1;)Lscala/Function1;
const #109 = Method	#22.#108;	//  scala/Function1$class.compose:(Lscala/Function1;Lscala/Function1;)Lscala/Function1;
const #110 = Asciz	(Lscala/Function1;)Ljava/lang/String;;
const #111 = NameAndType	#95:#110;//  toString:(Lscala/Function1;)Ljava/lang/String;
const #112 = Method	#22.#111;	//  scala/Function1$class.toString:(Lscala/Function1;)Ljava/lang/String;
const #113 = Asciz	(Lscala/PartialFunction;Lscala/Function1;)Lscala/PartialFunction;;
const #114 = NameAndType	#50:#113;//  andThen:(Lscala/PartialFunction;Lscala/Function1;)Lscala/PartialFunction;
const #115 = Method	#28.#114;	//  scala/PartialFunction$class.andThen:(Lscala/PartialFunction;Lscala/Function1;)Lscala/PartialFunction;
const #116 = Asciz	k;
const #117 = Asciz	orElse;
const #118 = Asciz	(Lscala/PartialFunction;)Lscala/PartialFunction;;
const #119 = Asciz	(Lscala/PartialFunction;Lscala/PartialFunction;)Lscala/PartialFunction;;
const #120 = NameAndType	#117:#119;//  orElse:(Lscala/PartialFunction;Lscala/PartialFunction;)Lscala/PartialFunction;
const #121 = Method	#28.#120;	//  scala/PartialFunction$class.orElse:(Lscala/PartialFunction;Lscala/PartialFunction;)Lscala/PartialFunction;
const #122 = Asciz	that;
const #123 = Asciz	Lscala/PartialFunction;;
const #124 = Asciz	Scala;
const #125 = Asciz	InnerClasses;
const #126 = Asciz	scala/util/parsing/syntax/Tokens;
const #127 = class	#126;	//  scala/util/parsing/syntax/Tokens
const #128 = Asciz	Token;
const #129 = Asciz	scala/util/parsing/syntax/StdTokens;
const #130 = class	#129;	//  scala/util/parsing/syntax/StdTokens
const #131 = Asciz	NumericLit;
const #132 = Asciz	$anonfun$number$1;
const #133 = Asciz	scala/ScalaObject;
const #134 = class	#133;	//  scala/ScalaObject
const #135 = Asciz	java/io/Serializable;
const #136 = class	#135;	//  java/io/Serializable

{
public scala.util.parsing.json.Parser$$anonfun$number$1(scala.util.parsing.json.Parser);
  Code:
   Stack=2, Locals=2, Args_size=2
   0:	aload_1
   1:	ifnonnull	12
   4:	new	#10; //class java/lang/NullPointerException
   7:	dup
   8:	invokespecial	#13; //Method java/lang/NullPointerException."<init>":()V
   11:	athrow
   12:	aload_0
   13:	aload_1
   14:	putfield	#17; //Field $outer:Lscala/util/parsing/json/Parser;
   17:	aload_0
   18:	invokespecial	#20; //Method java/lang/Object."<init>":()V
   21:	aload_0
   22:	invokestatic	#26; //Method scala/Function1$class.$init$:(Lscala/Function1;)V
   25:	aload_0
   26:	invokestatic	#31; //Method scala/PartialFunction$class.$init$:(Lscala/PartialFunction;)V
   29:	return
  LineNumberTable: 
   line 48: 0

  LocalVariableTable: 
   Start  Length  Slot  Name   Signature
   0      30      0    this       Lscala/util/parsing/json/Parser$$anonfun$number$1;
   0      30      1    $outer       Lscala/util/parsing/json/Parser;


public final java.lang.Object apply(java.lang.Object);
  Code:
   Stack=2, Locals=2, Args_size=2
   0:	aload_0
   1:	aload_1
   2:	checkcast	#38; //class scala/util/parsing/syntax/Tokens$Token
   5:	invokevirtual	#41; //Method apply:(Lscala/util/parsing/syntax/Tokens$Token;)Ljava/lang/Object;
   8:	areturn
  LineNumberTable: 
   line 48: 0

  LocalVariableTable: 
   Start  Length  Slot  Name   Signature
   0      9      0    this       Lscala/util/parsing/json/Parser$$anonfun$number$1;
   0      9      1    v1       Ljava/lang/Object;


public final boolean isDefinedAt(java.lang.Object);
  Code:
   Stack=2, Locals=2, Args_size=2
   0:	aload_0
   1:	aload_1
   2:	checkcast	#38; //class scala/util/parsing/syntax/Tokens$Token
   5:	invokevirtual	#48; //Method isDefinedAt:(Lscala/util/parsing/syntax/Tokens$Token;)Z
   8:	ireturn
  LineNumberTable: 
   line 48: 0

  LocalVariableTable: 
   Start  Length  Slot  Name   Signature
   0      9      0    this       Lscala/util/parsing/json/Parser$$anonfun$number$1;
   0      9      1    x       Ljava/lang/Object;


public scala.Function1 andThen(scala.Function1);
  Code:
   Stack=2, Locals=2, Args_size=2
   0:	aload_0
   1:	aload_1
   2:	invokeinterface	#56,  2; //InterfaceMethod scala/PartialFunction.andThen:(Lscala/Function1;)Lscala/PartialFunction;
   7:	areturn
  LineNumberTable: 
   line 48: 0

  LocalVariableTable: 
   Start  Length  Slot  Name   Signature
   0      8      0    this       Lscala/util/parsing/json/Parser$$anonfun$number$1;
   0      8      1    g       Lscala/Function1;


public final boolean isDefinedAt(scala.util.parsing.syntax.Tokens$Token);
  Code:
   Stack=1, Locals=3, Args_size=2
   0:	aload_1
   1:	astore_2
   2:	aload_2
   3:	instanceof	#60; //class scala/util/parsing/syntax/StdTokens$NumericLit
   6:	ireturn
  LineNumberTable: 
   line 48: 0

  LocalVariableTable: 
   Start  Length  Slot  Name   Signature
   0      7      0    this       Lscala/util/parsing/json/Parser$$anonfun$number$1;
   2      4      2    temp13       Lscala/util/parsing/syntax/Tokens$Token;


public final java.lang.Object apply(scala.util.parsing.syntax.Tokens$Token);
  Code:
   Stack=3, Locals=6, Args_size=2
   0:	aload_1
   1:	astore_2
   2:	aload_2
   3:	instanceof	#60; //class scala/util/parsing/syntax/StdTokens$NumericLit
   6:	ifeq	64
   9:	aload_2
   10:	checkcast	#60; //class scala/util/parsing/syntax/StdTokens$NumericLit
   13:	astore_3
   14:	aload_3
   15:	invokevirtual	#66; //Method scala/util/parsing/syntax/StdTokens$NumericLit.chars:()Ljava/lang/String;
   18:	astore	4
   20:	aload_0
   21:	getfield	#17; //Field $outer:Lscala/util/parsing/json/Parser;
   24:	invokevirtual	#72; //Method scala/util/parsing/json/Parser.numberParser:()Ljava/lang/ThreadLocal;
   27:	invokevirtual	#78; //Method java/lang/ThreadLocal.get:()Ljava/lang/Object;
   30:	astore	5
   32:	aload	5
   34:	instanceof	#80; //class scala/Function1
   37:	ifeq	45
   40:	aload	5
   42:	goto	53
   45:	getstatic	#86; //Field scala/runtime/ScalaRunTime$.MODULE$:Lscala/runtime/ScalaRunTime$;
   48:	aload	5
   50:	invokevirtual	#90; //Method scala/runtime/ScalaRunTime$.boxArray:(Ljava/lang/Object;)Lscala/runtime/BoxedArray;
   53:	checkcast	#80; //class scala/Function1
   56:	aload	4
   58:	invokeinterface	#92,  2; //InterfaceMethod scala/Function1.apply:(Ljava/lang/Object;)Ljava/lang/Object;
   63:	areturn
   64:	new	#94; //class scala/MatchError
   67:	dup
   68:	aload_2
   69:	invokevirtual	#97; //Method scala/util/parsing/syntax/Tokens$Token.toString:()Ljava/lang/String;
   72:	invokespecial	#100; //Method scala/MatchError."<init>":(Ljava/lang/String;)V
   75:	athrow
  LineNumberTable: 
   line 48: 0

  LocalVariableTable: 
   Start  Length  Slot  Name   Signature
   0      76      0    this       Lscala/util/parsing/json/Parser$$anonfun$number$1;
   2      74      2    temp10       Lscala/util/parsing/syntax/Tokens$Token;
   14      49      3    temp11       Lscala/util/parsing/syntax/StdTokens$NumericLit;
   20      43      4    temp12       Ljava/lang/String;


public scala.Function1 compose(scala.Function1);
  Code:
   Stack=2, Locals=2, Args_size=2
   0:	aload_0
   1:	aload_1
   2:	invokestatic	#109; //Method scala/Function1$class.compose:(Lscala/Function1;Lscala/Function1;)Lscala/Function1;
   5:	areturn
  LineNumberTable: 
   line 48: 0

  LocalVariableTable: 
   Start  Length  Slot  Name   Signature
   0      6      0    this       Lscala/util/parsing/json/Parser$$anonfun$number$1;
   0      6      1    g       Lscala/Function1;


public java.lang.String toString();
  Code:
   Stack=1, Locals=1, Args_size=1
   0:	aload_0
   1:	invokestatic	#112; //Method scala/Function1$class.toString:(Lscala/Function1;)Ljava/lang/String;
   4:	areturn
  LineNumberTable: 
   line 48: 0


public scala.PartialFunction andThen(scala.Function1);
  Code:
   Stack=2, Locals=2, Args_size=2
   0:	aload_0
   1:	aload_1
   2:	invokestatic	#115; //Method scala/PartialFunction$class.andThen:(Lscala/PartialFunction;Lscala/Function1;)Lscala/PartialFunction;
   5:	areturn
  LineNumberTable: 
   line 48: 0

  LocalVariableTable: 
   Start  Length  Slot  Name   Signature
   0      6      0    this       Lscala/util/parsing/json/Parser$$anonfun$number$1;
   0      6      1    k       Lscala/Function1;


public scala.PartialFunction orElse(scala.PartialFunction);
  Code:
   Stack=2, Locals=2, Args_size=2
   0:	aload_0
   1:	aload_1
   2:	invokestatic	#121; //Method scala/PartialFunction$class.orElse:(Lscala/PartialFunction;Lscala/PartialFunction;)Lscala/PartialFunction;
   5:	areturn
  LineNumberTable: 
   line 48: 0

  LocalVariableTable: 
   Start  Length  Slot  Name   Signature
   0      6      0    this       Lscala/util/parsing/json/Parser$$anonfun$number$1;
   0      6      1    that       Lscala/PartialFunction;


}

