Compiled from "Transformed.scala"
public final class scala.collection.views.IndexedSeqTransformations$$anon$6 extends scala.collection.views.IndexedSeqLike implements scala.collection.IndexedSeqViewLike$DroppedWhile
  SourceFile: "Transformed.scala"
  Signature: length = 0x2
   00 75 
  Scala: length = 0x
   
  InnerClass: 
   public abstract DroppedWhile=class scala/collection/SeqViewLike$DroppedWhile of class scala/collection/SeqViewLike
   public abstract DroppedWhile=class scala/collection/IterableViewLike$DroppedWhile of class scala/collection/IterableViewLike
   public abstract Transformed=class scala/collection/TraversableViewLike$Transformed of class scala/collection/TraversableViewLike
   public abstract DroppedWhile=class scala/collection/IndexedSeqViewLike$DroppedWhile of class scala/collection/IndexedSeqViewLike
   public abstract DroppedWhile=class scala/collection/TraversableViewLike$DroppedWhile of class scala/collection/TraversableViewLike
   public final $anon$6=class scala/collection/views/IndexedSeqTransformations$$anon$6 of class scala/collection/views/IndexedSeqTransformations
  minor version: 0
  major version: 49
  Constant pool:
Asciz	SourceFile;
Asciz	Transformed.scala;
Asciz	bitmap$0;
Asciz	I;
Asciz	underlying;
Asciz	Ljava/lang/Object;;
Asciz	start;
Asciz	$outer;
Asciz	Lscala/collection/IndexedSeqViewLike;;
Asciz	pred;
Asciz	Lscala/Function1;;
Asciz	Lscala/Function1<TA;Ljava/lang/Boolean;>;;
Asciz	Signature;
Asciz	<init>;
Asciz	(Lscala/collection/IndexedSeqViewLike;Lscala/Function1;)V;
Asciz	Code;
Asciz	LineNumberTable;
Asciz	java/lang/NullPointerException;
class	java/lang/NullPointerException
Asciz	()V;
NameAndType	"<init>":()V
Method	java/lang/NullPointerException."<init>":()V
Asciz	scala/collection/views/IndexedSeqTransformations$$anon$6;
class	scala/collection/views/IndexedSeqTransformations$$anon$6
NameAndType	$outer:Lscala/collection/IndexedSeqViewLike;
Field	scala/collection/views/IndexedSeqTransformations$$anon$6.$outer:Lscala/collection/IndexedSeqViewLike;
Asciz	scala/collection/views/IndexedSeqLike;
class	scala/collection/views/IndexedSeqLike
Method	scala/collection/views/IndexedSeqLike."<init>":()V
Asciz	scala/collection/TraversableViewLike$Transformed$class;
class	scala/collection/TraversableViewLike$Transformed$class
Asciz	$init$;
Asciz	(Lscala/collection/TraversableViewLike$Transformed;)V;
NameAndType	$init$:(Lscala/collection/TraversableViewLike$Transformed;)V
Method	scala/collection/TraversableViewLike$Transformed$class.$init$:(Lscala/collection/TraversableViewLike$Transformed;)V
Asciz	scala/collection/TraversableViewLike$DroppedWhile$class;
class	scala/collection/TraversableViewLike$DroppedWhile$class
Asciz	(Lscala/collection/TraversableViewLike$DroppedWhile;)V;
NameAndType	$init$:(Lscala/collection/TraversableViewLike$DroppedWhile;)V
Method	scala/collection/TraversableViewLike$DroppedWhile$class.$init$:(Lscala/collection/TraversableViewLike$DroppedWhile;)V
Asciz	scala/collection/IterableViewLike$DroppedWhile$class;
class	scala/collection/IterableViewLike$DroppedWhile$class
Asciz	(Lscala/collection/IterableViewLike$DroppedWhile;)V;
NameAndType	$init$:(Lscala/collection/IterableViewLike$DroppedWhile;)V
Method	scala/collection/IterableViewLike$DroppedWhile$class.$init$:(Lscala/collection/IterableViewLike$DroppedWhile;)V
Asciz	scala/collection/SeqViewLike$DroppedWhile$class;
class	scala/collection/SeqViewLike$DroppedWhile$class
Asciz	(Lscala/collection/SeqViewLike$DroppedWhile;)V;
NameAndType	$init$:(Lscala/collection/SeqViewLike$DroppedWhile;)V
Method	scala/collection/SeqViewLike$DroppedWhile$class.$init$:(Lscala/collection/SeqViewLike$DroppedWhile;)V
NameAndType	pred:Lscala/Function1;
Field	scala/collection/views/IndexedSeqTransformations$$anon$6.pred:Lscala/Function1;
Asciz	this;
Asciz	Lscala/collection/views/IndexedSeqTransformations$$anon$6;;
Asciz	LocalVariableTable;
Asciz	(Lscala/collection/IndexedSeqViewLike<TA;TColl;TThis;>;)V;
Asciz	apply;
Asciz	(Ljava/lang/Object;)Ljava/lang/Object;;
Asciz	scala/runtime/BoxesRunTime;
class	scala/runtime/BoxesRunTime
Asciz	unboxToInt;
Asciz	(Ljava/lang/Object;)I;
NameAndType	unboxToInt:(Ljava/lang/Object;)I
Method	scala/runtime/BoxesRunTime.unboxToInt:(Ljava/lang/Object;)I
Asciz	scala/collection/SeqViewLike$DroppedWhile;
class	scala/collection/SeqViewLike$DroppedWhile
Asciz	(I)Ljava/lang/Object;;
NameAndType	apply:(I)Ljava/lang/Object;
InterfaceMethod	scala/collection/SeqViewLike$DroppedWhile.apply:(I)Ljava/lang/Object;
Asciz	v1;
Asciz	scala$collection$TraversableViewLike$Transformed$$$outer;
Asciz	()Lscala/collection/TraversableViewLike;;
Asciz	scala$collection$TraversableViewLike$DroppedWhile$$$outer;
Asciz	scala$collection$IterableViewLike$DroppedWhile$$$outer;
Asciz	()Lscala/collection/IterableViewLike;;
Asciz	scala$collection$SeqViewLike$DroppedWhile$$$outer;
Asciz	()Lscala/collection/SeqViewLike;;
Asciz	()Lscala/Function1;;
Asciz	()Lscala/Function1<TA;Ljava/lang/Boolean;>;;
Asciz	()Ljava/lang/Object;;
NameAndType	bitmap$0:I
Field	scala/collection/views/IndexedSeqTransformations$$anon$6.bitmap$0:I
Asciz	(Lscala/collection/TraversableViewLike$Transformed;)Ljava/lang/Object;;
NameAndType	underlying:(Lscala/collection/TraversableViewLike$Transformed;)Ljava/lang/Object;
Method	scala/collection/TraversableViewLike$Transformed$class.underlying:(Lscala/collection/TraversableViewLike$Transformed;)Ljava/lang/Object;
NameAndType	underlying:Ljava/lang/Object;
Field	scala/collection/views/IndexedSeqTransformations$$anon$6.underlying:Ljava/lang/Object;
Asciz	stringPrefix;
Asciz	()Ljava/lang/String;;
Asciz	(Lscala/collection/TraversableViewLike$DroppedWhile;)Ljava/lang/String;;
NameAndType	stringPrefix:(Lscala/collection/TraversableViewLike$DroppedWhile;)Ljava/lang/String;
Method	scala/collection/TraversableViewLike$DroppedWhile$class.stringPrefix:(Lscala/collection/TraversableViewLike$DroppedWhile;)Ljava/lang/String;
Asciz	foreach;
Asciz	(Lscala/Function1;)V;
Asciz	(Lscala/collection/TraversableViewLike$DroppedWhile;Lscala/Function1;)V;
NameAndType	foreach:(Lscala/collection/TraversableViewLike$DroppedWhile;Lscala/Function1;)V
Method	scala/collection/TraversableViewLike$DroppedWhile$class.foreach:(Lscala/collection/TraversableViewLike$DroppedWhile;Lscala/Function1;)V
Asciz	f;
Asciz	iterator;
Asciz	()Lscala/collection/Iterator;;
Asciz	(Lscala/collection/IterableViewLike$DroppedWhile;)Lscala/collection/Iterator;;
NameAndType	iterator:(Lscala/collection/IterableViewLike$DroppedWhile;)Lscala/collection/Iterator;
Method	scala/collection/IterableViewLike$DroppedWhile$class.iterator:(Lscala/collection/IterableViewLike$DroppedWhile;)Lscala/collection/Iterator;
Asciz	(Lscala/collection/SeqViewLike$DroppedWhile;I)Ljava/lang/Object;;
NameAndType	apply:(Lscala/collection/SeqViewLike$DroppedWhile;I)Ljava/lang/Object;
Method	scala/collection/SeqViewLike$DroppedWhile$class.apply:(Lscala/collection/SeqViewLike$DroppedWhile;I)Ljava/lang/Object;
Asciz	idx;
Asciz	length;
Asciz	()I;
Asciz	(Lscala/collection/SeqViewLike$DroppedWhile;)I;
NameAndType	length:(Lscala/collection/SeqViewLike$DroppedWhile;)I
Method	scala/collection/SeqViewLike$DroppedWhile$class.length:(Lscala/collection/SeqViewLike$DroppedWhile;)I
NameAndType	start:(Lscala/collection/SeqViewLike$DroppedWhile;)I
Method	scala/collection/SeqViewLike$DroppedWhile$class.start:(Lscala/collection/SeqViewLike$DroppedWhile;)I
NameAndType	start:I
Field	scala/collection/views/IndexedSeqTransformations$$anon$6.start:I
Asciz	Lscala/collection/views/IndexedSeqLike<TA;TColl;>;Lscala/collection/IndexedSeqViewLike<TA;TColl;TThis;>.DroppedWhile;;
Asciz	Scala;
Asciz	InnerClasses;
Asciz	scala/collection/SeqViewLike;
class	scala/collection/SeqViewLike
Asciz	DroppedWhile;
Asciz	scala/collection/IterableViewLike$DroppedWhile;
class	scala/collection/IterableViewLike$DroppedWhile
Asciz	scala/collection/IterableViewLike;
class	scala/collection/IterableViewLike
Asciz	scala/collection/TraversableViewLike$Transformed;
class	scala/collection/TraversableViewLike$Transformed
Asciz	scala/collection/TraversableViewLike;
class	scala/collection/TraversableViewLike
Asciz	Transformed;
Asciz	scala/collection/IndexedSeqViewLike$DroppedWhile;
class	scala/collection/IndexedSeqViewLike$DroppedWhile
Asciz	scala/collection/IndexedSeqViewLike;
class	scala/collection/IndexedSeqViewLike
Asciz	scala/collection/TraversableViewLike$DroppedWhile;
class	scala/collection/TraversableViewLike$DroppedWhile
Asciz	scala/collection/views/IndexedSeqTransformations;
class	scala/collection/views/IndexedSeqTransformations
Asciz	$anon$6;

{
public volatile int bitmap$0;
  Signature: I

private final java.lang.Object underlying;
  Signature: Ljava/lang/Object;

private final int start;
  Signature: I

private final scala.collection.IndexedSeqViewLike $outer;
  Signature: Lscala/collection/IndexedSeqViewLike;

private final scala.Function1 pred;
  Signature: Lscala/Function1;
  Signature: length = 0x2
   00 0C 

public scala.collection.views.IndexedSeqTransformations$$anon$6(scala.collection.IndexedSeqViewLike, scala.Function1);
  Signature: (Lscala/collection/IndexedSeqViewLike;Lscala/Function1;)V
  Code:
   Stack=2, Locals=3, Args_size=3
	aload_1
	ifnonnull	l1 // aload_0
	new	class java/lang/NullPointerException
	dup
	invokespecial	Method java/lang/NullPointerException."<init>":()V
	athrow
l1	aload_0
	aload_1
	putfield	Field $outer:Lscala/collection/IndexedSeqViewLike;
	aload_0
	invokespecial	Method scala/collection/views/IndexedSeqLike."<init>":()V
	aload_0
	invokestatic	Method scala/collection/TraversableViewLike$Transformed$class.$init$:(Lscala/collection/TraversableViewLike$Transformed;)V
	aload_0
	invokestatic	Method scala/collection/TraversableViewLike$DroppedWhile$class.$init$:(Lscala/collection/TraversableViewLike$DroppedWhile;)V
	aload_0
	invokestatic	Method scala/collection/IterableViewLike$DroppedWhile$class.$init$:(Lscala/collection/IterableViewLike$DroppedWhile;)V
	aload_0
	invokestatic	Method scala/collection/SeqViewLike$DroppedWhile$class.$init$:(Lscala/collection/SeqViewLike$DroppedWhile;)V
	aload_0
	aload_2
	putfield	Field pred:Lscala/Function1;
	return
  Labels:
   	l1 = 12 // aload_0
  LocalVariableTable: 
   Start  Length  Slot  Name   Signature
   0      43      0    this       Lscala/collection/views/IndexedSeqTransformations$$anon$6;
   0      43      1    $outer       Lscala/collection/IndexedSeqViewLike;

  Signature: length = 0x2
   00 38 

public java.lang.Object apply(java.lang.Object);
  Signature: (Ljava/lang/Object;)Ljava/lang/Object;
  Code:
   Stack=2, Locals=2, Args_size=2
	aload_0
	aload_1
	invokestatic	Method scala/runtime/BoxesRunTime.unboxToInt:(Ljava/lang/Object;)I
	invokeinterface	InterfaceMethod scala/collection/SeqViewLike$DroppedWhile.apply:(I)Ljava/lang/Object;
	areturn
  Labels:
  LocalVariableTable: 
   Start  Length  Slot  Name   Signature
   0      11      0    this       Lscala/collection/views/IndexedSeqTransformations$$anon$6;
   0      11      1    v1       Ljava/lang/Object;


public scala.collection.TraversableViewLike scala$collection$TraversableViewLike$Transformed$$$outer();
  Signature: ()Lscala/collection/TraversableViewLike;
  Code:
   Stack=1, Locals=1, Args_size=1
	aload_0
	getfield	Field $outer:Lscala/collection/IndexedSeqViewLike;
	areturn
  Labels:

public scala.collection.TraversableViewLike scala$collection$TraversableViewLike$DroppedWhile$$$outer();
  Signature: ()Lscala/collection/TraversableViewLike;
  Code:
   Stack=1, Locals=1, Args_size=1
	aload_0
	getfield	Field $outer:Lscala/collection/IndexedSeqViewLike;
	areturn
  Labels:

public scala.collection.IterableViewLike scala$collection$IterableViewLike$DroppedWhile$$$outer();
  Signature: ()Lscala/collection/IterableViewLike;
  Code:
   Stack=1, Locals=1, Args_size=1
	aload_0
	getfield	Field $outer:Lscala/collection/IndexedSeqViewLike;
	areturn
  Labels:

public scala.collection.SeqViewLike scala$collection$SeqViewLike$DroppedWhile$$$outer();
  Signature: ()Lscala/collection/SeqViewLike;
  Code:
   Stack=1, Locals=1, Args_size=1
	aload_0
	getfield	Field $outer:Lscala/collection/IndexedSeqViewLike;
	areturn
  Labels:

public scala.Function1 pred();
  Signature: ()Lscala/Function1;
  Code:
   Stack=1, Locals=1, Args_size=1
	aload_0
	getfield	Field pred:Lscala/Function1;
	areturn
  Labels:
  Signature: length = 0x2
   00 4F 

public java.lang.Object underlying();
  Signature: ()Ljava/lang/Object;
  Code:
   Stack=3, Locals=1, Args_size=1
	aload_0
	getfield	Field bitmap$0:I
	iconst_4
	iand
	iconst_0
	if_icmpne	l1 // aload_0
	aload_0
	dup
	pop
	monitorenter
	aload_0
	getfield	Field bitmap$0:I
	iconst_4
	iand
	iconst_0
	if_icmpne	l2 // aload_0
	aload_0
	aload_0
	invokestatic	Method scala/collection/TraversableViewLike$Transformed$class.underlying:(Lscala/collection/TraversableViewLike$Transformed;)Ljava/lang/Object;
	putfield	Field underlying:Ljava/lang/Object;
	aload_0
	aload_0
	getfield	Field bitmap$0:I
	iconst_4
	ior
	putfield	Field bitmap$0:I
l2	aload_0
	monitorexit
l1	aload_0
	getfield	Field underlying:Ljava/lang/Object;
	areturn
	aload_0
	monitorexit
	athrow
  Labels:
   	l2 = 42 // aload_0
   	l1 = 44 // aload_0
  Exception table:
   from   to  target type
    14    44    49   any

public java.lang.String stringPrefix();
  Signature: ()Ljava/lang/String;
  Code:
   Stack=1, Locals=1, Args_size=1
	aload_0
	invokestatic	Method scala/collection/TraversableViewLike$DroppedWhile$class.stringPrefix:(Lscala/collection/TraversableViewLike$DroppedWhile;)Ljava/lang/String;
	areturn
  Labels:

public void foreach(scala.Function1);
  Signature: (Lscala/Function1;)V
  Code:
   Stack=2, Locals=2, Args_size=2
	aload_0
	aload_1
	invokestatic	Method scala/collection/TraversableViewLike$DroppedWhile$class.foreach:(Lscala/collection/TraversableViewLike$DroppedWhile;Lscala/Function1;)V
	return
  Labels:
  LocalVariableTable: 
   Start  Length  Slot  Name   Signature
   0      6      0    this       Lscala/collection/views/IndexedSeqTransformations$$anon$6;
   0      6      1    f       Lscala/Function1;


public scala.collection.Iterator iterator();
  Signature: ()Lscala/collection/Iterator;
  Code:
   Stack=1, Locals=1, Args_size=1
	aload_0
	invokestatic	Method scala/collection/IterableViewLike$DroppedWhile$class.iterator:(Lscala/collection/IterableViewLike$DroppedWhile;)Lscala/collection/Iterator;
	areturn
  Labels:

public java.lang.Object apply(int);
  Signature: (I)Ljava/lang/Object;
  Code:
   Stack=2, Locals=2, Args_size=2
	aload_0
	iload_1
	invokestatic	Method scala/collection/SeqViewLike$DroppedWhile$class.apply:(Lscala/collection/SeqViewLike$DroppedWhile;I)Ljava/lang/Object;
	areturn
  Labels:
  LocalVariableTable: 
   Start  Length  Slot  Name   Signature
   0      6      0    this       Lscala/collection/views/IndexedSeqTransformations$$anon$6;
   0      6      1    idx       I


public int length();
  Signature: ()I
  Code:
   Stack=1, Locals=1, Args_size=1
	aload_0
	invokestatic	Method scala/collection/SeqViewLike$DroppedWhile$class.length:(Lscala/collection/SeqViewLike$DroppedWhile;)I
	ireturn
  Labels:

public int start();
  Signature: ()I
  Code:
   Stack=3, Locals=1, Args_size=1
	aload_0
	getfield	Field bitmap$0:I
	iconst_1
	iand
	iconst_0
	if_icmpne	l1 // aload_0
	aload_0
	dup
	pop
	monitorenter
	aload_0
	getfield	Field bitmap$0:I
	iconst_1
	iand
	iconst_0
	if_icmpne	l2 // aload_0
	aload_0
	aload_0
	invokestatic	Method scala/collection/SeqViewLike$DroppedWhile$class.start:(Lscala/collection/SeqViewLike$DroppedWhile;)I
	putfield	Field start:I
	aload_0
	aload_0
	getfield	Field bitmap$0:I
	iconst_1
	ior
	putfield	Field bitmap$0:I
l2	aload_0
	monitorexit
l1	aload_0
	getfield	Field start:I
	ireturn
	aload_0
	monitorexit
	athrow
  Labels:
   	l2 = 42 // aload_0
   	l1 = 44 // aload_0
  Exception table:
   from   to  target type
    14    44    49   any

}

