Compiled from "Transformed.scala"
public final class scala.collection.views.IndexedSeqTransformations$$anon$10 extends scala.collection.views.IndexedSeqLike implements scala.collection.IndexedSeqViewLike$Zipped
  SourceFile: "Transformed.scala"
  Signature: length = 0x2
   00 59 
  Scala: length = 0x
   
  InnerClass: 
   public abstract Zipped=class scala/collection/IndexedSeqViewLike$Zipped of class scala/collection/IndexedSeqViewLike
   public abstract Transformed=class scala/collection/TraversableViewLike$Transformed of class scala/collection/TraversableViewLike
   public final $anon$10=class scala/collection/views/IndexedSeqTransformations$$anon$10 of class scala/collection/views/IndexedSeqTransformations
  minor version: 0
  major version: 49
  Constant pool:
Asciz	SourceFile;
Asciz	Transformed.scala;
Asciz	bitmap$0;
Asciz	I;
Asciz	underlying;
Asciz	Ljava/lang/Object;;
Asciz	$outer;
Asciz	Lscala/collection/IndexedSeqViewLike;;
Asciz	other;
Asciz	Lscala/collection/Iterable;;
Asciz	Lscala/collection/Iterable<TB;>;;
Asciz	Signature;
Asciz	<init>;
Asciz	(Lscala/collection/IndexedSeqViewLike;Lscala/collection/Iterable;)V;
Asciz	Code;
Asciz	LineNumberTable;
Asciz	java/lang/NullPointerException;
class	java/lang/NullPointerException
Asciz	()V;
NameAndType	"<init>":()V
Method	java/lang/NullPointerException."<init>":()V
Asciz	scala/collection/views/IndexedSeqTransformations$$anon$10;
class	scala/collection/views/IndexedSeqTransformations$$anon$10
NameAndType	$outer:Lscala/collection/IndexedSeqViewLike;
Field	scala/collection/views/IndexedSeqTransformations$$anon$10.$outer:Lscala/collection/IndexedSeqViewLike;
Asciz	scala/collection/views/IndexedSeqLike;
class	scala/collection/views/IndexedSeqLike
Method	scala/collection/views/IndexedSeqLike."<init>":()V
Asciz	scala/collection/TraversableViewLike$Transformed$class;
class	scala/collection/TraversableViewLike$Transformed$class
Asciz	$init$;
Asciz	(Lscala/collection/TraversableViewLike$Transformed;)V;
NameAndType	$init$:(Lscala/collection/TraversableViewLike$Transformed;)V
Method	scala/collection/TraversableViewLike$Transformed$class.$init$:(Lscala/collection/TraversableViewLike$Transformed;)V
Asciz	scala/collection/IndexedSeqViewLike$Zipped$class;
class	scala/collection/IndexedSeqViewLike$Zipped$class
Asciz	(Lscala/collection/IndexedSeqViewLike$Zipped;)V;
NameAndType	$init$:(Lscala/collection/IndexedSeqViewLike$Zipped;)V
Method	scala/collection/IndexedSeqViewLike$Zipped$class.$init$:(Lscala/collection/IndexedSeqViewLike$Zipped;)V
NameAndType	other:Lscala/collection/Iterable;
Field	scala/collection/views/IndexedSeqTransformations$$anon$10.other:Lscala/collection/Iterable;
Asciz	this;
Asciz	Lscala/collection/views/IndexedSeqTransformations$$anon$10;;
Asciz	LocalVariableTable;
Asciz	(Lscala/collection/IndexedSeqViewLike<TA;TColl;TThis;>;)V;
Asciz	apply;
Asciz	(I)Ljava/lang/Object;;
Asciz	scala/collection/IndexedSeqViewLike$Zipped;
class	scala/collection/IndexedSeqViewLike$Zipped
Asciz	(I)Lscala/Tuple2;;
NameAndType	apply:(I)Lscala/Tuple2;
InterfaceMethod	scala/collection/IndexedSeqViewLike$Zipped.apply:(I)Lscala/Tuple2;
Asciz	idx;
Asciz	(Ljava/lang/Object;)Ljava/lang/Object;;
Asciz	scala/runtime/BoxesRunTime;
class	scala/runtime/BoxesRunTime
Asciz	unboxToInt;
Asciz	(Ljava/lang/Object;)I;
NameAndType	unboxToInt:(Ljava/lang/Object;)I
Method	scala/runtime/BoxesRunTime.unboxToInt:(Ljava/lang/Object;)I
Asciz	v1;
Asciz	scala$collection$TraversableViewLike$Transformed$$$outer;
Asciz	()Lscala/collection/TraversableViewLike;;
Asciz	scala$collection$IndexedSeqViewLike$Zipped$$$outer;
Asciz	()Lscala/collection/IndexedSeqViewLike;;
Asciz	()Lscala/collection/Iterable;;
Asciz	()Lscala/collection/Iterable<TB;>;;
Asciz	()Ljava/lang/Object;;
NameAndType	bitmap$0:I
Field	scala/collection/views/IndexedSeqTransformations$$anon$10.bitmap$0:I
Asciz	(Lscala/collection/TraversableViewLike$Transformed;)Ljava/lang/Object;;
NameAndType	underlying:(Lscala/collection/TraversableViewLike$Transformed;)Ljava/lang/Object;
Method	scala/collection/TraversableViewLike$Transformed$class.underlying:(Lscala/collection/TraversableViewLike$Transformed;)Ljava/lang/Object;
NameAndType	underlying:Ljava/lang/Object;
Field	scala/collection/views/IndexedSeqTransformations$$anon$10.underlying:Ljava/lang/Object;
Asciz	stringPrefix;
Asciz	()Ljava/lang/String;;
Asciz	(Lscala/collection/IndexedSeqViewLike$Zipped;)Ljava/lang/String;;
NameAndType	stringPrefix:(Lscala/collection/IndexedSeqViewLike$Zipped;)Ljava/lang/String;
Method	scala/collection/IndexedSeqViewLike$Zipped$class.stringPrefix:(Lscala/collection/IndexedSeqViewLike$Zipped;)Ljava/lang/String;
Asciz	(Lscala/collection/IndexedSeqViewLike$Zipped;I)Lscala/Tuple2;;
NameAndType	apply:(Lscala/collection/IndexedSeqViewLike$Zipped;I)Lscala/Tuple2;
Method	scala/collection/IndexedSeqViewLike$Zipped$class.apply:(Lscala/collection/IndexedSeqViewLike$Zipped;I)Lscala/Tuple2;
Asciz	length;
Asciz	()I;
Asciz	(Lscala/collection/IndexedSeqViewLike$Zipped;)I;
NameAndType	length:(Lscala/collection/IndexedSeqViewLike$Zipped;)I
Method	scala/collection/IndexedSeqViewLike$Zipped$class.length:(Lscala/collection/IndexedSeqViewLike$Zipped;)I
Asciz	Lscala/collection/views/IndexedSeqLike<Lscala/Tuple2<TA;TB;>;TColl;>;Lscala/collection/IndexedSeqViewLike<TA;TColl;TThis;>.Zipped<TB;>;;
Asciz	Scala;
Asciz	InnerClasses;
Asciz	scala/collection/IndexedSeqViewLike;
class	scala/collection/IndexedSeqViewLike
Asciz	Zipped;
Asciz	scala/collection/TraversableViewLike$Transformed;
class	scala/collection/TraversableViewLike$Transformed
Asciz	scala/collection/TraversableViewLike;
class	scala/collection/TraversableViewLike
Asciz	Transformed;
Asciz	scala/collection/views/IndexedSeqTransformations;
class	scala/collection/views/IndexedSeqTransformations
Asciz	$anon$10;

{
public volatile int bitmap$0;
  Signature: I

private final java.lang.Object underlying;
  Signature: Ljava/lang/Object;

private final scala.collection.IndexedSeqViewLike $outer;
  Signature: Lscala/collection/IndexedSeqViewLike;

private final scala.collection.Iterable other;
  Signature: Lscala/collection/Iterable;
  Signature: length = 0x2
   00 0B 

public scala.collection.views.IndexedSeqTransformations$$anon$10(scala.collection.IndexedSeqViewLike, scala.collection.Iterable);
  Signature: (Lscala/collection/IndexedSeqViewLike;Lscala/collection/Iterable;)V
  Code:
   Stack=2, Locals=3, Args_size=3
	aload_1
	ifnonnull	l1 // aload_0
	new	class java/lang/NullPointerException
	dup
	invokespecial	Method java/lang/NullPointerException."<init>":()V
	athrow
l1	aload_0
	aload_1
	putfield	Field $outer:Lscala/collection/IndexedSeqViewLike;
	aload_0
	invokespecial	Method scala/collection/views/IndexedSeqLike."<init>":()V
	aload_0
	invokestatic	Method scala/collection/TraversableViewLike$Transformed$class.$init$:(Lscala/collection/TraversableViewLike$Transformed;)V
	aload_0
	invokestatic	Method scala/collection/IndexedSeqViewLike$Zipped$class.$init$:(Lscala/collection/IndexedSeqViewLike$Zipped;)V
	aload_0
	aload_2
	putfield	Field other:Lscala/collection/Iterable;
	return
  Labels:
   	l1 = 12 // aload_0
  LocalVariableTable: 
   Start  Length  Slot  Name   Signature
   0      35      0    this       Lscala/collection/views/IndexedSeqTransformations$$anon$10;
   0      35      1    $outer       Lscala/collection/IndexedSeqViewLike;

  Signature: length = 0x2
   00 2D 

public java.lang.Object apply(int);
  Signature: (I)Ljava/lang/Object;
  Code:
   Stack=2, Locals=2, Args_size=2
	aload_0
	iload_1
	invokeinterface	InterfaceMethod scala/collection/IndexedSeqViewLike$Zipped.apply:(I)Lscala/Tuple2;
	areturn
  Labels:
  LocalVariableTable: 
   Start  Length  Slot  Name   Signature
   0      8      0    this       Lscala/collection/views/IndexedSeqTransformations$$anon$10;
   0      8      1    idx       I


public java.lang.Object apply(java.lang.Object);
  Signature: (Ljava/lang/Object;)Ljava/lang/Object;
  Code:
   Stack=2, Locals=2, Args_size=2
	aload_0
	aload_1
	invokestatic	Method scala/runtime/BoxesRunTime.unboxToInt:(Ljava/lang/Object;)I
	invokeinterface	InterfaceMethod scala/collection/IndexedSeqViewLike$Zipped.apply:(I)Lscala/Tuple2;
	areturn
  Labels:
  LocalVariableTable: 
   Start  Length  Slot  Name   Signature
   0      11      0    this       Lscala/collection/views/IndexedSeqTransformations$$anon$10;
   0      11      1    v1       Ljava/lang/Object;


public scala.collection.TraversableViewLike scala$collection$TraversableViewLike$Transformed$$$outer();
  Signature: ()Lscala/collection/TraversableViewLike;
  Code:
   Stack=1, Locals=1, Args_size=1
	aload_0
	getfield	Field $outer:Lscala/collection/IndexedSeqViewLike;
	areturn
  Labels:

public scala.collection.IndexedSeqViewLike scala$collection$IndexedSeqViewLike$Zipped$$$outer();
  Signature: ()Lscala/collection/IndexedSeqViewLike;
  Code:
   Stack=1, Locals=1, Args_size=1
	aload_0
	getfield	Field $outer:Lscala/collection/IndexedSeqViewLike;
	areturn
  Labels:

public scala.collection.Iterable other();
  Signature: ()Lscala/collection/Iterable;
  Code:
   Stack=1, Locals=1, Args_size=1
	aload_0
	getfield	Field other:Lscala/collection/Iterable;
	areturn
  Labels:
  Signature: length = 0x2
   00 43 

public java.lang.Object underlying();
  Signature: ()Ljava/lang/Object;
  Code:
   Stack=3, Locals=1, Args_size=1
	aload_0
	getfield	Field bitmap$0:I
	iconst_1
	iand
	iconst_0
	if_icmpne	l1 // aload_0
	aload_0
	dup
	pop
	monitorenter
	aload_0
	getfield	Field bitmap$0:I
	iconst_1
	iand
	iconst_0
	if_icmpne	l2 // aload_0
	aload_0
	aload_0
	invokestatic	Method scala/collection/TraversableViewLike$Transformed$class.underlying:(Lscala/collection/TraversableViewLike$Transformed;)Ljava/lang/Object;
	putfield	Field underlying:Ljava/lang/Object;
	aload_0
	aload_0
	getfield	Field bitmap$0:I
	iconst_1
	ior
	putfield	Field bitmap$0:I
l2	aload_0
	monitorexit
l1	aload_0
	getfield	Field underlying:Ljava/lang/Object;
	areturn
	aload_0
	monitorexit
	athrow
  Labels:
   	l2 = 42 // aload_0
   	l1 = 44 // aload_0
  Exception table:
   from   to  target type
    14    44    49   any

public java.lang.String stringPrefix();
  Signature: ()Ljava/lang/String;
  Code:
   Stack=1, Locals=1, Args_size=1
	aload_0
	invokestatic	Method scala/collection/IndexedSeqViewLike$Zipped$class.stringPrefix:(Lscala/collection/IndexedSeqViewLike$Zipped;)Ljava/lang/String;
	areturn
  Labels:

public scala.Tuple2 apply(int);
  Signature: (I)Lscala/Tuple2;
  Code:
   Stack=2, Locals=2, Args_size=2
	aload_0
	iload_1
	invokestatic	Method scala/collection/IndexedSeqViewLike$Zipped$class.apply:(Lscala/collection/IndexedSeqViewLike$Zipped;I)Lscala/Tuple2;
	areturn
  Labels:
  LocalVariableTable: 
   Start  Length  Slot  Name   Signature
   0      6      0    this       Lscala/collection/views/IndexedSeqTransformations$$anon$10;
   0      6      1    idx       I


public int length();
  Signature: ()I
  Code:
   Stack=1, Locals=1, Args_size=1
	aload_0
	invokestatic	Method scala/collection/IndexedSeqViewLike$Zipped$class.length:(Lscala/collection/IndexedSeqViewLike$Zipped;)I
	ireturn
  Labels:

}

