Compiled from "Transformed.scala"
public abstract class scala.collection.views.IndexedSeqLike extends scala.collection.views.SeqLike implements scala.collection.IndexedSeqView,scala.ScalaObject
  SourceFile: "Transformed.scala"
  Signature: length = 0x2
   01 FFFFFFB3 
  ScalaSig: length = 0x14F
   05 00 38 06 06 01 02 FFFFFF81 00 04 08 02 0E 49 6E 64
   65 78 65 64 53 65 71 4C 69 6B 65 0A 02 03 04 01
   05 76 69 65 77 73 0A 02 05 06 01 0A 63 6F 6C 6C
   65 63 74 69 6F 6E 0A 01 07 01 05 73 63 61 6C 61
   15 03 09 10 1C 13 04 00 0A 1E 22 10 04 0B 0C 0E
   1B 0D 01 02 09 02 0D 02 02 07 53 65 71 4C 69 6B
   65 10 02 0F 10 0C 00 04 08 11 00 FFFFFF84 FFFFFF80 FFFFFF84 FFFFFFC2 00
   13 02 01 42 03 00 11 02 14 18 10 02 15 16 0D 01
   06 09 02 17 06 02 07 4E 6F 74 68 69 6E 67 10 02
   15 19 09 02 1A 06 02 03 41 6E 79 10 02 0F 1C 04
   08 1D 00 FFFFFF84 FFFFFF80 FFFFFF84 FFFFFFC2 00 13 02 04 43 6F 6C 6C 10
   04 1F 20 0E 1B 0D 01 04 09 02 21 04 02 0E 49 6E
   64 65 78 65 64 53 65 71 56 69 65 77 10 02 15 23
   09 02 24 06 02 0B 53 63 61 6C 61 4F 62 6A 65 63
   74 08 05 26 00 FFFFFF84 00 27 01 06 3C 69 6E 69 74 3E
   14 01 28 10 04 0B 00 0E 1B 08 05 2A 00 FFFFFF84 20 2B
   01 07 66 6F 72 65 61 63 68 15 02 2C 36 14 02 2D
   30 10 02 15 2E 09 02 2F 06 02 04 55 6E 69 74 08
   05 31 29 FFFFFFC0 00 32 01 01 66 10 04 15 33 0E 35 09
   02 34 06 02 09 46 75 6E 63 74 69 6F 6E 31 10 02
   0F 36 04 08 37 29 FFFFFF84 FFFFFF80 FFFFFF80 FFFFFFC2 00 13 02 01 55 
  InnerClass: 
   public abstract Transformed=class scala/collection/SeqViewLike$Transformed of class scala/collection/SeqViewLike
   public abstract Transformed=class scala/collection/IterableViewLike$Transformed of class scala/collection/IterableViewLike
   public abstract Transformed=class scala/collection/IndexedSeqViewLike$Transformed of class scala/collection/IndexedSeqViewLike
   public abstract Transformed=class scala/collection/TraversableViewLike$Transformed of class scala/collection/TraversableViewLike
  minor version: 0
  major version: 49
  Constant pool:
Asciz	SourceFile;
Asciz	Transformed.scala;
Asciz	<init>;
Asciz	()V;
Asciz	Code;
Asciz	LineNumberTable;
Asciz	scala/collection/views/SeqLike;
class	scala/collection/views/SeqLike
NameAndType	"<init>":()V
Method	scala/collection/views/SeqLike."<init>":()V
Asciz	scala/collection/IndexedSeqLike$class;
class	scala/collection/IndexedSeqLike$class
Asciz	$init$;
Asciz	(Lscala/collection/IndexedSeqLike;)V;
NameAndType	$init$:(Lscala/collection/IndexedSeqLike;)V
Method	scala/collection/IndexedSeqLike$class.$init$:(Lscala/collection/IndexedSeqLike;)V
Asciz	scala/collection/IndexedSeq$class;
class	scala/collection/IndexedSeq$class
Asciz	(Lscala/collection/IndexedSeq;)V;
NameAndType	$init$:(Lscala/collection/IndexedSeq;)V
Method	scala/collection/IndexedSeq$class.$init$:(Lscala/collection/IndexedSeq;)V
Asciz	scala/collection/views/IndexedSeqTransformations$class;
class	scala/collection/views/IndexedSeqTransformations$class
Asciz	(Lscala/collection/IndexedSeqViewLike;)V;
NameAndType	$init$:(Lscala/collection/IndexedSeqViewLike;)V
Method	scala/collection/views/IndexedSeqTransformations$class.$init$:(Lscala/collection/IndexedSeqViewLike;)V
Asciz	scala/collection/IndexedSeqViewLike$class;
class	scala/collection/IndexedSeqViewLike$class
Method	scala/collection/IndexedSeqViewLike$class.$init$:(Lscala/collection/IndexedSeqViewLike;)V
Asciz	Signature;
Asciz	newAppended;
Asciz	(Lscala/collection/Traversable;)Lscala/collection/SeqViewLike$Transformed;;
Asciz	scala/collection/views/IndexedSeqTransformations;
class	scala/collection/views/IndexedSeqTransformations
Asciz	(Lscala/collection/Traversable;)Lscala/collection/IndexedSeqViewLike$Transformed;;
NameAndType	newAppended:(Lscala/collection/Traversable;)Lscala/collection/IndexedSeqViewLike$Transformed;
InterfaceMethod	scala/collection/views/IndexedSeqTransformations.newAppended:(Lscala/collection/Traversable;)Lscala/collection/IndexedSeqViewLike$Transformed;
Asciz	this;
Asciz	Lscala/collection/views/IndexedSeqLike;;
Asciz	that;
Asciz	Lscala/collection/Traversable;;
Asciz	LocalVariableTable;
Asciz	(Lscala/collection/Traversable;)Lscala/collection/IterableViewLike$Transformed;;
Asciz	(Lscala/collection/Traversable;)Lscala/collection/TraversableViewLike$Transformed;;
Asciz	newMapped;
Asciz	(Lscala/Function1;)Lscala/collection/SeqViewLike$Transformed;;
Asciz	(Lscala/Function1;)Lscala/collection/IndexedSeqViewLike$Transformed;;
NameAndType	newMapped:(Lscala/Function1;)Lscala/collection/IndexedSeqViewLike$Transformed;
InterfaceMethod	scala/collection/views/IndexedSeqTransformations.newMapped:(Lscala/Function1;)Lscala/collection/IndexedSeqViewLike$Transformed;
Asciz	f;
Asciz	Lscala/Function1;;
Asciz	(Lscala/Function1;)Lscala/collection/IterableViewLike$Transformed;;
Asciz	(Lscala/Function1;)Lscala/collection/TraversableViewLike$Transformed;;
Asciz	newFlatMapped;
NameAndType	newFlatMapped:(Lscala/Function1;)Lscala/collection/IndexedSeqViewLike$Transformed;
InterfaceMethod	scala/collection/views/IndexedSeqTransformations.newFlatMapped:(Lscala/Function1;)Lscala/collection/IndexedSeqViewLike$Transformed;
Asciz	newFiltered;
NameAndType	newFiltered:(Lscala/Function1;)Lscala/collection/IndexedSeqViewLike$Transformed;
InterfaceMethod	scala/collection/views/IndexedSeqTransformations.newFiltered:(Lscala/Function1;)Lscala/collection/IndexedSeqViewLike$Transformed;
Asciz	p;
Asciz	newSliced;
Asciz	(II)Lscala/collection/SeqViewLike$Transformed;;
Asciz	(II)Lscala/collection/IndexedSeqViewLike$Transformed;;
NameAndType	newSliced:(II)Lscala/collection/IndexedSeqViewLike$Transformed;
InterfaceMethod	scala/collection/views/IndexedSeqTransformations.newSliced:(II)Lscala/collection/IndexedSeqViewLike$Transformed;
Asciz	_from;
Asciz	I;
Asciz	_until;
Asciz	(II)Lscala/collection/IterableViewLike$Transformed;;
Asciz	(II)Lscala/collection/TraversableViewLike$Transformed;;
Asciz	newDroppedWhile;
NameAndType	newDroppedWhile:(Lscala/Function1;)Lscala/collection/IndexedSeqViewLike$Transformed;
InterfaceMethod	scala/collection/views/IndexedSeqTransformations.newDroppedWhile:(Lscala/Function1;)Lscala/collection/IndexedSeqViewLike$Transformed;
Asciz	newTakenWhile;
NameAndType	newTakenWhile:(Lscala/Function1;)Lscala/collection/IndexedSeqViewLike$Transformed;
InterfaceMethod	scala/collection/views/IndexedSeqTransformations.newTakenWhile:(Lscala/Function1;)Lscala/collection/IndexedSeqViewLike$Transformed;
Asciz	newZipped;
Asciz	(Lscala/collection/Iterable;)Lscala/collection/SeqViewLike$Transformed;;
Asciz	(Lscala/collection/Iterable;)Lscala/collection/IndexedSeqViewLike$Transformed;;
NameAndType	newZipped:(Lscala/collection/Iterable;)Lscala/collection/IndexedSeqViewLike$Transformed;
InterfaceMethod	scala/collection/views/IndexedSeqTransformations.newZipped:(Lscala/collection/Iterable;)Lscala/collection/IndexedSeqViewLike$Transformed;
Asciz	Lscala/collection/Iterable;;
Asciz	(Lscala/collection/Iterable;)Lscala/collection/IterableViewLike$Transformed;;
Asciz	newZippedAll;
Asciz	(Lscala/collection/Iterable;Ljava/lang/Object;Ljava/lang/Object;)Lscala/collection/SeqViewLike$Transformed;;
Asciz	(Lscala/collection/Iterable;Ljava/lang/Object;Ljava/lang/Object;)Lscala/collection/IndexedSeqViewLike$Transformed;;
NameAndType	newZippedAll:(Lscala/collection/Iterable;Ljava/lang/Object;Ljava/lang/Object;)Lscala/collection/IndexedSeqViewLike$Transformed;
InterfaceMethod	scala/collection/views/IndexedSeqTransformations.newZippedAll:(Lscala/collection/Iterable;Ljava/lang/Object;Ljava/lang/Object;)Lscala/collection/IndexedSeqViewLike$Transformed;
Asciz	_thisElem;
Asciz	Ljava/lang/Object;;
Asciz	_thatElem;
Asciz	(Lscala/collection/Iterable;Ljava/lang/Object;Ljava/lang/Object;)Lscala/collection/IterableViewLike$Transformed;;
Asciz	newReversed;
Asciz	()Lscala/collection/SeqViewLike$Transformed;;
Asciz	()Lscala/collection/IndexedSeqViewLike$Transformed;;
NameAndType	newReversed:()Lscala/collection/IndexedSeqViewLike$Transformed;
InterfaceMethod	scala/collection/views/IndexedSeqTransformations.newReversed:()Lscala/collection/IndexedSeqViewLike$Transformed;
Asciz	newPatched;
Asciz	(ILscala/collection/Seq;I)Lscala/collection/SeqViewLike$Transformed;;
Asciz	(ILscala/collection/Seq;I)Lscala/collection/IndexedSeqViewLike$Transformed;;
NameAndType	newPatched:(ILscala/collection/Seq;I)Lscala/collection/IndexedSeqViewLike$Transformed;
InterfaceMethod	scala/collection/views/IndexedSeqTransformations.newPatched:(ILscala/collection/Seq;I)Lscala/collection/IndexedSeqViewLike$Transformed;
Asciz	_patch;
Asciz	Lscala/collection/Seq;;
Asciz	_replaced;
Asciz	thisCollection;
Asciz	()Lscala/collection/Seq;;
Asciz	scala/collection/IndexedSeqLike;
class	scala/collection/IndexedSeqLike
Asciz	()Lscala/collection/IndexedSeq;;
NameAndType	thisCollection:()Lscala/collection/IndexedSeq;
InterfaceMethod	scala/collection/IndexedSeqLike.thisCollection:()Lscala/collection/IndexedSeq;
Asciz	()Lscala/collection/Iterable;;
Asciz	()Lscala/collection/Traversable;;
Asciz	toCollection;
Asciz	(Ljava/lang/Object;)Lscala/collection/Seq;;
Asciz	(Ljava/lang/Object;)Lscala/collection/IndexedSeq;;
NameAndType	toCollection:(Ljava/lang/Object;)Lscala/collection/IndexedSeq;
InterfaceMethod	scala/collection/IndexedSeqLike.toCollection:(Ljava/lang/Object;)Lscala/collection/IndexedSeq;
Asciz	repr;
Asciz	(Ljava/lang/Object;)Lscala/collection/Iterable;;
Asciz	(Ljava/lang/Object;)Lscala/collection/Traversable;;
Asciz	slice;
Asciz	(II)Lscala/collection/TraversableView;;
Asciz	(II)Ljava/lang/Object;;
NameAndType	slice:(II)Ljava/lang/Object;
InterfaceMethod	scala/collection/IndexedSeqLike.slice:(II)Ljava/lang/Object;
Asciz	scala/collection/TraversableView;
class	scala/collection/TraversableView
Asciz	from;
Asciz	until;
Asciz	init;
Asciz	()Lscala/collection/TraversableView;;
Asciz	()Ljava/lang/Object;;
NameAndType	init:()Ljava/lang/Object;
InterfaceMethod	scala/collection/IndexedSeqLike.init:()Ljava/lang/Object;
Asciz	take;
Asciz	(I)Lscala/collection/TraversableView;;
Asciz	(I)Ljava/lang/Object;;
NameAndType	take:(I)Ljava/lang/Object;
InterfaceMethod	scala/collection/IndexedSeqLike.take:(I)Ljava/lang/Object;
Asciz	n;
Asciz	drop;
NameAndType	drop:(I)Ljava/lang/Object;
InterfaceMethod	scala/collection/IndexedSeqLike.drop:(I)Ljava/lang/Object;
Asciz	takeWhile;
Asciz	(Lscala/Function1;)Lscala/collection/TraversableView;;
Asciz	(Lscala/Function1;)Ljava/lang/Object;;
NameAndType	takeWhile:(Lscala/Function1;)Ljava/lang/Object;
InterfaceMethod	scala/collection/IndexedSeqLike.takeWhile:(Lscala/Function1;)Ljava/lang/Object;
Asciz	dropWhile;
NameAndType	dropWhile:(Lscala/Function1;)Ljava/lang/Object;
InterfaceMethod	scala/collection/IndexedSeqLike.dropWhile:(Lscala/Function1;)Ljava/lang/Object;
Asciz	reverse;
Asciz	()Lscala/collection/SeqView;;
NameAndType	reverse:()Ljava/lang/Object;
InterfaceMethod	scala/collection/IndexedSeqLike.reverse:()Ljava/lang/Object;
Asciz	scala/collection/SeqView;
class	scala/collection/SeqView
Asciz	view;
Asciz	()Lscala/collection/IndexedSeqView;;
NameAndType	view:()Lscala/collection/IndexedSeqView;
InterfaceMethod	scala/collection/IndexedSeqLike.view:()Lscala/collection/IndexedSeqView;
Asciz	()Lscala/collection/IterableView;;
Asciz	(II)Lscala/collection/SeqView;;
Asciz	(II)Lscala/collection/IndexedSeqView;;
NameAndType	view:(II)Lscala/collection/IndexedSeqView;
InterfaceMethod	scala/collection/IndexedSeqLike.view:(II)Lscala/collection/IndexedSeqView;
Asciz	(II)Lscala/collection/IterableView;;
Asciz	isDefinedAt;
Asciz	(Ljava/lang/Object;)Z;
Asciz	scala/runtime/BoxesRunTime;
class	scala/runtime/BoxesRunTime
Asciz	unboxToInt;
Asciz	(Ljava/lang/Object;)I;
NameAndType	unboxToInt:(Ljava/lang/Object;)I
Method	scala/runtime/BoxesRunTime.unboxToInt:(Ljava/lang/Object;)I
Asciz	scala/collection/SeqLike;
class	scala/collection/SeqLike
Asciz	(I)Z;
NameAndType	isDefinedAt:(I)Z
InterfaceMethod	scala/collection/SeqLike.isDefinedAt:(I)Z
Asciz	x;
Asciz	projection;
NameAndType	projection:()Lscala/collection/SeqView;
InterfaceMethod	scala/collection/SeqLike.projection:()Lscala/collection/SeqView;
Asciz	filter;
Asciz	scala/collection/TraversableViewLike;
class	scala/collection/TraversableViewLike
NameAndType	filter:(Lscala/Function1;)Lscala/collection/TraversableView;
InterfaceMethod	scala/collection/TraversableViewLike.filter:(Lscala/Function1;)Lscala/collection/TraversableView;
Asciz	foreach;
Asciz	(Lscala/Function1;)V;
Asciz	(Lscala/collection/IndexedSeqLike;Lscala/Function1;)V;
NameAndType	foreach:(Lscala/collection/IndexedSeqLike;Lscala/Function1;)V
Method	scala/collection/IndexedSeqLike$class.foreach:(Lscala/collection/IndexedSeqLike;Lscala/Function1;)V
Asciz	<U:Ljava/lang/Object;>(Lscala/Function1<TB;TU;>;)V;
Asciz	(Lscala/collection/IndexedSeqLike;II)Lscala/collection/IndexedSeqView;;
NameAndType	view:(Lscala/collection/IndexedSeqLike;II)Lscala/collection/IndexedSeqView;
Method	scala/collection/IndexedSeqLike$class.view:(Lscala/collection/IndexedSeqLike;II)Lscala/collection/IndexedSeqView;
Asciz	(Lscala/collection/IndexedSeqLike;)Lscala/collection/IndexedSeqView;;
NameAndType	view:(Lscala/collection/IndexedSeqLike;)Lscala/collection/IndexedSeqView;
Method	scala/collection/IndexedSeqLike$class.view:(Lscala/collection/IndexedSeqLike;)Lscala/collection/IndexedSeqView;
Asciz	endsWith;
Asciz	(Lscala/collection/Seq;)Z;
Asciz	(Lscala/collection/IndexedSeqLike;Lscala/collection/Seq;)Z;
NameAndType	endsWith:(Lscala/collection/IndexedSeqLike;Lscala/collection/Seq;)Z
Method	scala/collection/IndexedSeqLike$class.endsWith:(Lscala/collection/IndexedSeqLike;Lscala/collection/Seq;)Z
Asciz	startsWith;
Asciz	(Lscala/collection/Seq;I)Z;
Asciz	(Lscala/collection/IndexedSeqLike;Lscala/collection/Seq;I)Z;
NameAndType	startsWith:(Lscala/collection/IndexedSeqLike;Lscala/collection/Seq;I)Z
Method	scala/collection/IndexedSeqLike$class.startsWith:(Lscala/collection/IndexedSeqLike;Lscala/collection/Seq;I)Z
Asciz	offset;
Asciz	reverseIterator;
Asciz	()Lscala/collection/Iterator;;
Asciz	(Lscala/collection/IndexedSeqLike;)Lscala/collection/Iterator;;
NameAndType	reverseIterator:(Lscala/collection/IndexedSeqLike;)Lscala/collection/Iterator;
Method	scala/collection/IndexedSeqLike$class.reverseIterator:(Lscala/collection/IndexedSeqLike;)Lscala/collection/Iterator;
Asciz	(Lscala/collection/IndexedSeqLike;)Ljava/lang/Object;;
NameAndType	reverse:(Lscala/collection/IndexedSeqLike;)Ljava/lang/Object;
Method	scala/collection/IndexedSeqLike$class.reverse:(Lscala/collection/IndexedSeqLike;)Ljava/lang/Object;
Asciz	lastIndexWhere;
Asciz	(Lscala/Function1;I)I;
Asciz	(Lscala/collection/IndexedSeqLike;Lscala/Function1;I)I;
NameAndType	lastIndexWhere:(Lscala/collection/IndexedSeqLike;Lscala/Function1;I)I
Method	scala/collection/IndexedSeqLike$class.lastIndexWhere:(Lscala/collection/IndexedSeqLike;Lscala/Function1;I)I
Asciz	end;
Asciz	indexWhere;
NameAndType	indexWhere:(Lscala/collection/IndexedSeqLike;Lscala/Function1;I)I
Method	scala/collection/IndexedSeqLike$class.indexWhere:(Lscala/collection/IndexedSeqLike;Lscala/Function1;I)I
Asciz	segmentLength;
NameAndType	segmentLength:(Lscala/collection/IndexedSeqLike;Lscala/Function1;I)I
Method	scala/collection/IndexedSeqLike$class.segmentLength:(Lscala/collection/IndexedSeqLike;Lscala/Function1;I)I
Asciz	lengthCompare;
Asciz	(I)I;
Asciz	(Lscala/collection/IndexedSeqLike;I)I;
NameAndType	lengthCompare:(Lscala/collection/IndexedSeqLike;I)I
Method	scala/collection/IndexedSeqLike$class.lengthCompare:(Lscala/collection/IndexedSeqLike;I)I
Asciz	len;
Asciz	copyToArray;
Asciz	(Ljava/lang/Object;II)V;
Asciz	(Lscala/collection/IndexedSeqLike;Ljava/lang/Object;II)V;
NameAndType	copyToArray:(Lscala/collection/IndexedSeqLike;Ljava/lang/Object;II)V
Method	scala/collection/IndexedSeqLike$class.copyToArray:(Lscala/collection/IndexedSeqLike;Ljava/lang/Object;II)V
Asciz	xs;
Asciz	start;
Asciz	sameElements;
Asciz	(Lscala/collection/Iterable;)Z;
Asciz	(Lscala/collection/IndexedSeqLike;Lscala/collection/Iterable;)Z;
NameAndType	sameElements:(Lscala/collection/IndexedSeqLike;Lscala/collection/Iterable;)Z
Method	scala/collection/IndexedSeqLike$class.sameElements:(Lscala/collection/IndexedSeqLike;Lscala/collection/Iterable;)Z
Asciz	span;
Asciz	(Lscala/Function1;)Lscala/Tuple2;;
Asciz	(Lscala/collection/IndexedSeqLike;Lscala/Function1;)Lscala/Tuple2;;
NameAndType	span:(Lscala/collection/IndexedSeqLike;Lscala/Function1;)Lscala/Tuple2;
Method	scala/collection/IndexedSeqLike$class.span:(Lscala/collection/IndexedSeqLike;Lscala/Function1;)Lscala/Tuple2;
Asciz	(Lscala/collection/IndexedSeqLike;Lscala/Function1;)Ljava/lang/Object;;
NameAndType	dropWhile:(Lscala/collection/IndexedSeqLike;Lscala/Function1;)Ljava/lang/Object;
Method	scala/collection/IndexedSeqLike$class.dropWhile:(Lscala/collection/IndexedSeqLike;Lscala/Function1;)Ljava/lang/Object;
NameAndType	takeWhile:(Lscala/collection/IndexedSeqLike;Lscala/Function1;)Ljava/lang/Object;
Method	scala/collection/IndexedSeqLike$class.takeWhile:(Lscala/collection/IndexedSeqLike;Lscala/Function1;)Ljava/lang/Object;
Asciz	splitAt;
Asciz	(I)Lscala/Tuple2;;
Asciz	(Lscala/collection/IndexedSeqLike;I)Lscala/Tuple2;;
NameAndType	splitAt:(Lscala/collection/IndexedSeqLike;I)Lscala/Tuple2;
Method	scala/collection/IndexedSeqLike$class.splitAt:(Lscala/collection/IndexedSeqLike;I)Lscala/Tuple2;
Asciz	dropRight;
Asciz	(Lscala/collection/IndexedSeqLike;I)Ljava/lang/Object;;
NameAndType	dropRight:(Lscala/collection/IndexedSeqLike;I)Ljava/lang/Object;
Method	scala/collection/IndexedSeqLike$class.dropRight:(Lscala/collection/IndexedSeqLike;I)Ljava/lang/Object;
Asciz	takeRight;
NameAndType	takeRight:(Lscala/collection/IndexedSeqLike;I)Ljava/lang/Object;
Method	scala/collection/IndexedSeqLike$class.takeRight:(Lscala/collection/IndexedSeqLike;I)Ljava/lang/Object;
NameAndType	drop:(Lscala/collection/IndexedSeqLike;I)Ljava/lang/Object;
Method	scala/collection/IndexedSeqLike$class.drop:(Lscala/collection/IndexedSeqLike;I)Ljava/lang/Object;
NameAndType	take:(Lscala/collection/IndexedSeqLike;I)Ljava/lang/Object;
Method	scala/collection/IndexedSeqLike$class.take:(Lscala/collection/IndexedSeqLike;I)Ljava/lang/Object;
NameAndType	init:(Lscala/collection/IndexedSeqLike;)Ljava/lang/Object;
Method	scala/collection/IndexedSeqLike$class.init:(Lscala/collection/IndexedSeqLike;)Ljava/lang/Object;
Asciz	last;
NameAndType	last:(Lscala/collection/IndexedSeqLike;)Ljava/lang/Object;
Method	scala/collection/IndexedSeqLike$class.last:(Lscala/collection/IndexedSeqLike;)Ljava/lang/Object;
Asciz	tail;
NameAndType	tail:(Lscala/collection/IndexedSeqLike;)Ljava/lang/Object;
Method	scala/collection/IndexedSeqLike$class.tail:(Lscala/collection/IndexedSeqLike;)Ljava/lang/Object;
Asciz	head;
NameAndType	head:(Lscala/collection/IndexedSeqLike;)Ljava/lang/Object;
Method	scala/collection/IndexedSeqLike$class.head:(Lscala/collection/IndexedSeqLike;)Ljava/lang/Object;
Asciz	(Lscala/collection/IndexedSeqLike;II)Ljava/lang/Object;;
NameAndType	slice:(Lscala/collection/IndexedSeqLike;II)Ljava/lang/Object;
Method	scala/collection/IndexedSeqLike$class.slice:(Lscala/collection/IndexedSeqLike;II)Ljava/lang/Object;
Asciz	zipWithIndex;
Asciz	(Lscala/collection/generic/CanBuildFrom;)Ljava/lang/Object;;
Asciz	(Lscala/collection/IndexedSeqLike;Lscala/collection/generic/CanBuildFrom;)Ljava/lang/Object;;
NameAndType	zipWithIndex:(Lscala/collection/IndexedSeqLike;Lscala/collection/generic/CanBuildFrom;)Ljava/lang/Object;
Method	scala/collection/IndexedSeqLike$class.zipWithIndex:(Lscala/collection/IndexedSeqLike;Lscala/collection/generic/CanBuildFrom;)Ljava/lang/Object;
Asciz	bf;
Asciz	Lscala/collection/generic/CanBuildFrom;;
Asciz	zip;
Asciz	(Lscala/collection/Iterable;Lscala/collection/generic/CanBuildFrom;)Ljava/lang/Object;;
Asciz	(Lscala/collection/IndexedSeqLike;Lscala/collection/Iterable;Lscala/collection/generic/CanBuildFrom;)Ljava/lang/Object;;
NameAndType	zip:(Lscala/collection/IndexedSeqLike;Lscala/collection/Iterable;Lscala/collection/generic/CanBuildFrom;)Ljava/lang/Object;
Method	scala/collection/IndexedSeqLike$class.zip:(Lscala/collection/IndexedSeqLike;Lscala/collection/Iterable;Lscala/collection/generic/CanBuildFrom;)Ljava/lang/Object;
Asciz	reduceRight;
Asciz	(Lscala/Function2;)Ljava/lang/Object;;
Asciz	(Lscala/collection/IndexedSeqLike;Lscala/Function2;)Ljava/lang/Object;;
NameAndType	reduceRight:(Lscala/collection/IndexedSeqLike;Lscala/Function2;)Ljava/lang/Object;
Method	scala/collection/IndexedSeqLike$class.reduceRight:(Lscala/collection/IndexedSeqLike;Lscala/Function2;)Ljava/lang/Object;
Asciz	op;
Asciz	Lscala/Function2;;
Asciz	reduceLeft;
NameAndType	reduceLeft:(Lscala/collection/IndexedSeqLike;Lscala/Function2;)Ljava/lang/Object;
Method	scala/collection/IndexedSeqLike$class.reduceLeft:(Lscala/collection/IndexedSeqLike;Lscala/Function2;)Ljava/lang/Object;
Asciz	foldRight;
Asciz	(Ljava/lang/Object;Lscala/Function2;)Ljava/lang/Object;;
Asciz	(Lscala/collection/IndexedSeqLike;Ljava/lang/Object;Lscala/Function2;)Ljava/lang/Object;;
NameAndType	foldRight:(Lscala/collection/IndexedSeqLike;Ljava/lang/Object;Lscala/Function2;)Ljava/lang/Object;
Method	scala/collection/IndexedSeqLike$class.foldRight:(Lscala/collection/IndexedSeqLike;Ljava/lang/Object;Lscala/Function2;)Ljava/lang/Object;
Asciz	z;
Asciz	foldLeft;
NameAndType	foldLeft:(Lscala/collection/IndexedSeqLike;Ljava/lang/Object;Lscala/Function2;)Ljava/lang/Object;
Method	scala/collection/IndexedSeqLike$class.foldLeft:(Lscala/collection/IndexedSeqLike;Ljava/lang/Object;Lscala/Function2;)Ljava/lang/Object;
Asciz	find;
Asciz	(Lscala/Function1;)Lscala/Option;;
Asciz	(Lscala/collection/IndexedSeqLike;Lscala/Function1;)Lscala/Option;;
NameAndType	find:(Lscala/collection/IndexedSeqLike;Lscala/Function1;)Lscala/Option;
Method	scala/collection/IndexedSeqLike$class.find:(Lscala/collection/IndexedSeqLike;Lscala/Function1;)Lscala/Option;
Asciz	exists;
Asciz	(Lscala/Function1;)Z;
Asciz	(Lscala/collection/IndexedSeqLike;Lscala/Function1;)Z;
NameAndType	exists:(Lscala/collection/IndexedSeqLike;Lscala/Function1;)Z
Method	scala/collection/IndexedSeqLike$class.exists:(Lscala/collection/IndexedSeqLike;Lscala/Function1;)Z
Asciz	forall;
NameAndType	forall:(Lscala/collection/IndexedSeqLike;Lscala/Function1;)Z
Method	scala/collection/IndexedSeqLike$class.forall:(Lscala/collection/IndexedSeqLike;Lscala/Function1;)Z
Asciz	isEmpty;
Asciz	()Z;
Asciz	(Lscala/collection/IndexedSeqLike;)Z;
NameAndType	isEmpty:(Lscala/collection/IndexedSeqLike;)Z
Method	scala/collection/IndexedSeqLike$class.isEmpty:(Lscala/collection/IndexedSeqLike;)Z
Asciz	iterator;
NameAndType	iterator:(Lscala/collection/IndexedSeqLike;)Lscala/collection/Iterator;
Method	scala/collection/IndexedSeqLike$class.iterator:(Lscala/collection/IndexedSeqLike;)Lscala/collection/Iterator;
Asciz	(Lscala/collection/IndexedSeqLike;Ljava/lang/Object;)Lscala/collection/IndexedSeq;;
NameAndType	toCollection:(Lscala/collection/IndexedSeqLike;Ljava/lang/Object;)Lscala/collection/IndexedSeq;
Method	scala/collection/IndexedSeqLike$class.toCollection:(Lscala/collection/IndexedSeqLike;Ljava/lang/Object;)Lscala/collection/IndexedSeq;
Asciz	(Lscala/collection/IndexedSeqLike;)Lscala/collection/IndexedSeq;;
NameAndType	thisCollection:(Lscala/collection/IndexedSeqLike;)Lscala/collection/IndexedSeq;
Method	scala/collection/IndexedSeqLike$class.thisCollection:(Lscala/collection/IndexedSeqLike;)Lscala/collection/IndexedSeq;
Asciz	scala$collection$IndexedSeqLike$$super$endsWith;
Asciz	scala/collection/SeqLike$class;
class	scala/collection/SeqLike$class
Asciz	(Lscala/collection/SeqLike;Lscala/collection/Seq;)Z;
NameAndType	endsWith:(Lscala/collection/SeqLike;Lscala/collection/Seq;)Z
Method	scala/collection/SeqLike$class.endsWith:(Lscala/collection/SeqLike;Lscala/collection/Seq;)Z
Asciz	scala$collection$IndexedSeqLike$$super$sameElements;
Asciz	scala/collection/IterableLike$class;
class	scala/collection/IterableLike$class
Asciz	(Lscala/collection/IterableLike;Lscala/collection/Iterable;)Z;
NameAndType	sameElements:(Lscala/collection/IterableLike;Lscala/collection/Iterable;)Z
Method	scala/collection/IterableLike$class.sameElements:(Lscala/collection/IterableLike;Lscala/collection/Iterable;)Z
Asciz	scala$collection$IndexedSeqLike$$super$init;
Asciz	scala/collection/TraversableViewLike$class;
class	scala/collection/TraversableViewLike$class
Asciz	(Lscala/collection/TraversableViewLike;)Lscala/collection/TraversableView;;
NameAndType	init:(Lscala/collection/TraversableViewLike;)Lscala/collection/TraversableView;
Method	scala/collection/TraversableViewLike$class.init:(Lscala/collection/TraversableViewLike;)Lscala/collection/TraversableView;
Asciz	scala$collection$IndexedSeqLike$$super$last;
Asciz	scala/collection/TraversableLike$class;
class	scala/collection/TraversableLike$class
Asciz	(Lscala/collection/TraversableLike;)Ljava/lang/Object;;
NameAndType	last:(Lscala/collection/TraversableLike;)Ljava/lang/Object;
Method	scala/collection/TraversableLike$class.last:(Lscala/collection/TraversableLike;)Ljava/lang/Object;
Asciz	scala$collection$IndexedSeqLike$$super$tail;
NameAndType	tail:(Lscala/collection/TraversableLike;)Ljava/lang/Object;
Method	scala/collection/TraversableLike$class.tail:(Lscala/collection/TraversableLike;)Ljava/lang/Object;
Asciz	scala$collection$IndexedSeqLike$$super$head;
Asciz	(Lscala/collection/IterableLike;)Ljava/lang/Object;;
NameAndType	head:(Lscala/collection/IterableLike;)Ljava/lang/Object;
Method	scala/collection/IterableLike$class.head:(Lscala/collection/IterableLike;)Ljava/lang/Object;
Asciz	scala$collection$IndexedSeqLike$$super$zip;
Asciz	scala/collection/IterableViewLike$class;
class	scala/collection/IterableViewLike$class
Asciz	(Lscala/collection/IterableViewLike;Lscala/collection/Iterable;Lscala/collection/generic/CanBuildFrom;)Ljava/lang/Object;;
NameAndType	zip:(Lscala/collection/IterableViewLike;Lscala/collection/Iterable;Lscala/collection/generic/CanBuildFrom;)Ljava/lang/Object;
Method	scala/collection/IterableViewLike$class.zip:(Lscala/collection/IterableViewLike;Lscala/collection/Iterable;Lscala/collection/generic/CanBuildFrom;)Ljava/lang/Object;
Asciz	scala$collection$IndexedSeqLike$$super$reduceRight;
Asciz	(Lscala/collection/IterableLike;Lscala/Function2;)Ljava/lang/Object;;
NameAndType	reduceRight:(Lscala/collection/IterableLike;Lscala/Function2;)Ljava/lang/Object;
Method	scala/collection/IterableLike$class.reduceRight:(Lscala/collection/IterableLike;Lscala/Function2;)Ljava/lang/Object;
Asciz	scala$collection$IndexedSeqLike$$super$reduceLeft;
Asciz	(Lscala/collection/TraversableLike;Lscala/Function2;)Ljava/lang/Object;;
NameAndType	reduceLeft:(Lscala/collection/TraversableLike;Lscala/Function2;)Ljava/lang/Object;
Method	scala/collection/TraversableLike$class.reduceLeft:(Lscala/collection/TraversableLike;Lscala/Function2;)Ljava/lang/Object;
Asciz	companion;
Asciz	()Lscala/collection/generic/GenericCompanion;;
Asciz	(Lscala/collection/IndexedSeq;)Lscala/collection/generic/GenericCompanion;;
NameAndType	companion:(Lscala/collection/IndexedSeq;)Lscala/collection/generic/GenericCompanion;
Method	scala/collection/IndexedSeq$class.companion:(Lscala/collection/IndexedSeq;)Lscala/collection/generic/GenericCompanion;
Asciz	(Lscala/collection/IndexedSeqViewLike;ILscala/collection/Seq;I)Lscala/collection/IndexedSeqViewLike$Transformed;;
NameAndType	newPatched:(Lscala/collection/IndexedSeqViewLike;ILscala/collection/Seq;I)Lscala/collection/IndexedSeqViewLike$Transformed;
Method	scala/collection/views/IndexedSeqTransformations$class.newPatched:(Lscala/collection/IndexedSeqViewLike;ILscala/collection/Seq;I)Lscala/collection/IndexedSeqViewLike$Transformed;
Asciz	(Lscala/collection/IndexedSeqViewLike;)Lscala/collection/IndexedSeqViewLike$Transformed;;
NameAndType	newReversed:(Lscala/collection/IndexedSeqViewLike;)Lscala/collection/IndexedSeqViewLike$Transformed;
Method	scala/collection/views/IndexedSeqTransformations$class.newReversed:(Lscala/collection/IndexedSeqViewLike;)Lscala/collection/IndexedSeqViewLike$Transformed;
Asciz	(Lscala/collection/IndexedSeqViewLike;Lscala/collection/Iterable;Ljava/lang/Object;Ljava/lang/Object;)Lscala/collection/IndexedSeqViewLike$Transformed;;
NameAndType	newZippedAll:(Lscala/collection/IndexedSeqViewLike;Lscala/collection/Iterable;Ljava/lang/Object;Ljava/lang/Object;)Lscala/collection/IndexedSeqViewLike$Transformed;
Method	scala/collection/views/IndexedSeqTransformations$class.newZippedAll:(Lscala/collection/IndexedSeqViewLike;Lscala/collection/Iterable;Ljava/lang/Object;Ljava/lang/Object;)Lscala/collection/IndexedSeqViewLike$Transformed;
Asciz	(Lscala/collection/IndexedSeqViewLike;Lscala/collection/Iterable;)Lscala/collection/IndexedSeqViewLike$Transformed;;
NameAndType	newZipped:(Lscala/collection/IndexedSeqViewLike;Lscala/collection/Iterable;)Lscala/collection/IndexedSeqViewLike$Transformed;
Method	scala/collection/views/IndexedSeqTransformations$class.newZipped:(Lscala/collection/IndexedSeqViewLike;Lscala/collection/Iterable;)Lscala/collection/IndexedSeqViewLike$Transformed;
Asciz	(Lscala/collection/IndexedSeqViewLike;Lscala/Function1;)Lscala/collection/IndexedSeqViewLike$Transformed;;
NameAndType	newTakenWhile:(Lscala/collection/IndexedSeqViewLike;Lscala/Function1;)Lscala/collection/IndexedSeqViewLike$Transformed;
Method	scala/collection/views/IndexedSeqTransformations$class.newTakenWhile:(Lscala/collection/IndexedSeqViewLike;Lscala/Function1;)Lscala/collection/IndexedSeqViewLike$Transformed;
NameAndType	newDroppedWhile:(Lscala/collection/IndexedSeqViewLike;Lscala/Function1;)Lscala/collection/IndexedSeqViewLike$Transformed;
Method	scala/collection/views/IndexedSeqTransformations$class.newDroppedWhile:(Lscala/collection/IndexedSeqViewLike;Lscala/Function1;)Lscala/collection/IndexedSeqViewLike$Transformed;
Asciz	(Lscala/collection/IndexedSeqViewLike;II)Lscala/collection/IndexedSeqViewLike$Transformed;;
NameAndType	newSliced:(Lscala/collection/IndexedSeqViewLike;II)Lscala/collection/IndexedSeqViewLike$Transformed;
Method	scala/collection/views/IndexedSeqTransformations$class.newSliced:(Lscala/collection/IndexedSeqViewLike;II)Lscala/collection/IndexedSeqViewLike$Transformed;
NameAndType	newFiltered:(Lscala/collection/IndexedSeqViewLike;Lscala/Function1;)Lscala/collection/IndexedSeqViewLike$Transformed;
Method	scala/collection/views/IndexedSeqTransformations$class.newFiltered:(Lscala/collection/IndexedSeqViewLike;Lscala/Function1;)Lscala/collection/IndexedSeqViewLike$Transformed;
NameAndType	newFlatMapped:(Lscala/collection/IndexedSeqViewLike;Lscala/Function1;)Lscala/collection/IndexedSeqViewLike$Transformed;
Method	scala/collection/views/IndexedSeqTransformations$class.newFlatMapped:(Lscala/collection/IndexedSeqViewLike;Lscala/Function1;)Lscala/collection/IndexedSeqViewLike$Transformed;
NameAndType	newMapped:(Lscala/collection/IndexedSeqViewLike;Lscala/Function1;)Lscala/collection/IndexedSeqViewLike$Transformed;
Method	scala/collection/views/IndexedSeqTransformations$class.newMapped:(Lscala/collection/IndexedSeqViewLike;Lscala/Function1;)Lscala/collection/IndexedSeqViewLike$Transformed;
Asciz	(Lscala/collection/IndexedSeqViewLike;Lscala/collection/Traversable;)Lscala/collection/IndexedSeqViewLike$Transformed;;
NameAndType	newAppended:(Lscala/collection/IndexedSeqViewLike;Lscala/collection/Traversable;)Lscala/collection/IndexedSeqViewLike$Transformed;
Method	scala/collection/views/IndexedSeqTransformations$class.newAppended:(Lscala/collection/IndexedSeqViewLike;Lscala/collection/Traversable;)Lscala/collection/IndexedSeqViewLike$Transformed;
Asciz	stringPrefix;
Asciz	()Ljava/lang/String;;
Asciz	(Lscala/collection/IndexedSeqViewLike;)Ljava/lang/String;;
NameAndType	stringPrefix:(Lscala/collection/IndexedSeqViewLike;)Ljava/lang/String;
Method	scala/collection/IndexedSeqViewLike$class.stringPrefix:(Lscala/collection/IndexedSeqViewLike;)Ljava/lang/String;
Asciz	<B:Ljava/lang/Object;Coll:Ljava/lang/Object;>Lscala/collection/views/SeqLike<TB;TColl;>;Lscala/collection/IndexedSeqView<TB;TColl;>;Lscala/ScalaObject;;
Asciz	ScalaSig;
Asciz	InnerClasses;
Asciz	scala/collection/SeqViewLike$Transformed;
class	scala/collection/SeqViewLike$Transformed
Asciz	scala/collection/SeqViewLike;
class	scala/collection/SeqViewLike
Asciz	Transformed;
Asciz	scala/collection/IterableViewLike$Transformed;
class	scala/collection/IterableViewLike$Transformed
Asciz	scala/collection/IterableViewLike;
class	scala/collection/IterableViewLike
Asciz	scala/collection/IndexedSeqViewLike$Transformed;
class	scala/collection/IndexedSeqViewLike$Transformed
Asciz	scala/collection/IndexedSeqViewLike;
class	scala/collection/IndexedSeqViewLike
Asciz	scala/collection/TraversableViewLike$Transformed;
class	scala/collection/TraversableViewLike$Transformed
Asciz	scala/collection/views/IndexedSeqLike;
class	scala/collection/views/IndexedSeqLike
Asciz	scala/collection/IndexedSeqView;
class	scala/collection/IndexedSeqView
Asciz	scala/ScalaObject;
class	scala/ScalaObject

{
public scala.collection.views.IndexedSeqLike();
  Signature: ()V
  Code:
   Stack=1, Locals=1, Args_size=1
	aload_0
	invokespecial	Method scala/collection/views/SeqLike."<init>":()V
	aload_0
	invokestatic	Method scala/collection/IndexedSeqLike$class.$init$:(Lscala/collection/IndexedSeqLike;)V
	aload_0
	invokestatic	Method scala/collection/IndexedSeq$class.$init$:(Lscala/collection/IndexedSeq;)V
	aload_0
	invokestatic	Method scala/collection/views/IndexedSeqTransformations$class.$init$:(Lscala/collection/IndexedSeqViewLike;)V
	aload_0
	invokestatic	Method scala/collection/IndexedSeqViewLike$class.$init$:(Lscala/collection/IndexedSeqViewLike;)V
	return
  Labels:
  Signature: length = 0x2
   00 04 

public scala.collection.SeqViewLike$Transformed newAppended(scala.collection.Traversable);
  Signature: (Lscala/collection/Traversable;)Lscala/collection/SeqViewLike$Transformed;
  Code:
   Stack=2, Locals=2, Args_size=2
	aload_0
	aload_1
	invokeinterface	InterfaceMethod scala/collection/views/IndexedSeqTransformations.newAppended:(Lscala/collection/Traversable;)Lscala/collection/IndexedSeqViewLike$Transformed;
	areturn
  Labels:
  LocalVariableTable: 
   Start  Length  Slot  Name   Signature
   0      8      0    this       Lscala/collection/views/IndexedSeqLike;
   0      8      1    that       Lscala/collection/Traversable;

  Signature: length = 0x2
   00 20 

public scala.collection.IterableViewLike$Transformed newAppended(scala.collection.Traversable);
  Signature: (Lscala/collection/Traversable;)Lscala/collection/IterableViewLike$Transformed;
  Code:
   Stack=2, Locals=2, Args_size=2
	aload_0
	aload_1
	invokeinterface	InterfaceMethod scala/collection/views/IndexedSeqTransformations.newAppended:(Lscala/collection/Traversable;)Lscala/collection/IndexedSeqViewLike$Transformed;
	areturn
  Labels:
  LocalVariableTable: 
   Start  Length  Slot  Name   Signature
   0      8      0    this       Lscala/collection/views/IndexedSeqLike;
   0      8      1    that       Lscala/collection/Traversable;

  Signature: length = 0x2
   00 2B 

public scala.collection.TraversableViewLike$Transformed newAppended(scala.collection.Traversable);
  Signature: (Lscala/collection/Traversable;)Lscala/collection/TraversableViewLike$Transformed;
  Code:
   Stack=2, Locals=2, Args_size=2
	aload_0
	aload_1
	invokeinterface	InterfaceMethod scala/collection/views/IndexedSeqTransformations.newAppended:(Lscala/collection/Traversable;)Lscala/collection/IndexedSeqViewLike$Transformed;
	areturn
  Labels:
  LocalVariableTable: 
   Start  Length  Slot  Name   Signature
   0      8      0    this       Lscala/collection/views/IndexedSeqLike;
   0      8      1    that       Lscala/collection/Traversable;

  Signature: length = 0x2
   00 2C 

public scala.collection.SeqViewLike$Transformed newMapped(scala.Function1);
  Signature: (Lscala/Function1;)Lscala/collection/SeqViewLike$Transformed;
  Code:
   Stack=2, Locals=2, Args_size=2
	aload_0
	aload_1
	invokeinterface	InterfaceMethod scala/collection/views/IndexedSeqTransformations.newMapped:(Lscala/Function1;)Lscala/collection/IndexedSeqViewLike$Transformed;
	areturn
  Labels:
  LocalVariableTable: 
   Start  Length  Slot  Name   Signature
   0      8      0    this       Lscala/collection/views/IndexedSeqLike;
   0      8      1    f       Lscala/Function1;

  Signature: length = 0x2
   00 2E 

public scala.collection.IterableViewLike$Transformed newMapped(scala.Function1);
  Signature: (Lscala/Function1;)Lscala/collection/IterableViewLike$Transformed;
  Code:
   Stack=2, Locals=2, Args_size=2
	aload_0
	aload_1
	invokeinterface	InterfaceMethod scala/collection/views/IndexedSeqTransformations.newMapped:(Lscala/Function1;)Lscala/collection/IndexedSeqViewLike$Transformed;
	areturn
  Labels:
  LocalVariableTable: 
   Start  Length  Slot  Name   Signature
   0      8      0    this       Lscala/collection/views/IndexedSeqLike;
   0      8      1    f       Lscala/Function1;

  Signature: length = 0x2
   00 34 

public scala.collection.TraversableViewLike$Transformed newMapped(scala.Function1);
  Signature: (Lscala/Function1;)Lscala/collection/TraversableViewLike$Transformed;
  Code:
   Stack=2, Locals=2, Args_size=2
	aload_0
	aload_1
	invokeinterface	InterfaceMethod scala/collection/views/IndexedSeqTransformations.newMapped:(Lscala/Function1;)Lscala/collection/IndexedSeqViewLike$Transformed;
	areturn
  Labels:
  LocalVariableTable: 
   Start  Length  Slot  Name   Signature
   0      8      0    this       Lscala/collection/views/IndexedSeqLike;
   0      8      1    f       Lscala/Function1;

  Signature: length = 0x2
   00 35 

public scala.collection.SeqViewLike$Transformed newFlatMapped(scala.Function1);
  Signature: (Lscala/Function1;)Lscala/collection/SeqViewLike$Transformed;
  Code:
   Stack=2, Locals=2, Args_size=2
	aload_0
	aload_1
	invokeinterface	InterfaceMethod scala/collection/views/IndexedSeqTransformations.newFlatMapped:(Lscala/Function1;)Lscala/collection/IndexedSeqViewLike$Transformed;
	areturn
  Labels:
  LocalVariableTable: 
   Start  Length  Slot  Name   Signature
   0      8      0    this       Lscala/collection/views/IndexedSeqLike;
   0      8      1    f       Lscala/Function1;

  Signature: length = 0x2
   00 2E 

public scala.collection.IterableViewLike$Transformed newFlatMapped(scala.Function1);
  Signature: (Lscala/Function1;)Lscala/collection/IterableViewLike$Transformed;
  Code:
   Stack=2, Locals=2, Args_size=2
	aload_0
	aload_1
	invokeinterface	InterfaceMethod scala/collection/views/IndexedSeqTransformations.newFlatMapped:(Lscala/Function1;)Lscala/collection/IndexedSeqViewLike$Transformed;
	areturn
  Labels:
  LocalVariableTable: 
   Start  Length  Slot  Name   Signature
   0      8      0    this       Lscala/collection/views/IndexedSeqLike;
   0      8      1    f       Lscala/Function1;

  Signature: length = 0x2
   00 34 

public scala.collection.TraversableViewLike$Transformed newFlatMapped(scala.Function1);
  Signature: (Lscala/Function1;)Lscala/collection/TraversableViewLike$Transformed;
  Code:
   Stack=2, Locals=2, Args_size=2
	aload_0
	aload_1
	invokeinterface	InterfaceMethod scala/collection/views/IndexedSeqTransformations.newFlatMapped:(Lscala/Function1;)Lscala/collection/IndexedSeqViewLike$Transformed;
	areturn
  Labels:
  LocalVariableTable: 
   Start  Length  Slot  Name   Signature
   0      8      0    this       Lscala/collection/views/IndexedSeqLike;
   0      8      1    f       Lscala/Function1;

  Signature: length = 0x2
   00 35 

public scala.collection.SeqViewLike$Transformed newFiltered(scala.Function1);
  Signature: (Lscala/Function1;)Lscala/collection/SeqViewLike$Transformed;
  Code:
   Stack=2, Locals=2, Args_size=2
	aload_0
	aload_1
	invokeinterface	InterfaceMethod scala/collection/views/IndexedSeqTransformations.newFiltered:(Lscala/Function1;)Lscala/collection/IndexedSeqViewLike$Transformed;
	areturn
  Labels:
  LocalVariableTable: 
   Start  Length  Slot  Name   Signature
   0      8      0    this       Lscala/collection/views/IndexedSeqLike;
   0      8      1    p       Lscala/Function1;

  Signature: length = 0x2
   00 2E 

public scala.collection.IterableViewLike$Transformed newFiltered(scala.Function1);
  Signature: (Lscala/Function1;)Lscala/collection/IterableViewLike$Transformed;
  Code:
   Stack=2, Locals=2, Args_size=2
	aload_0
	aload_1
	invokeinterface	InterfaceMethod scala/collection/views/IndexedSeqTransformations.newFiltered:(Lscala/Function1;)Lscala/collection/IndexedSeqViewLike$Transformed;
	areturn
  Labels:
  LocalVariableTable: 
   Start  Length  Slot  Name   Signature
   0      8      0    this       Lscala/collection/views/IndexedSeqLike;
   0      8      1    p       Lscala/Function1;

  Signature: length = 0x2
   00 34 

public scala.collection.TraversableViewLike$Transformed newFiltered(scala.Function1);
  Signature: (Lscala/Function1;)Lscala/collection/TraversableViewLike$Transformed;
  Code:
   Stack=2, Locals=2, Args_size=2
	aload_0
	aload_1
	invokeinterface	InterfaceMethod scala/collection/views/IndexedSeqTransformations.newFiltered:(Lscala/Function1;)Lscala/collection/IndexedSeqViewLike$Transformed;
	areturn
  Labels:
  LocalVariableTable: 
   Start  Length  Slot  Name   Signature
   0      8      0    this       Lscala/collection/views/IndexedSeqLike;
   0      8      1    p       Lscala/Function1;

  Signature: length = 0x2
   00 35 

public scala.collection.SeqViewLike$Transformed newSliced(int, int);
  Signature: (II)Lscala/collection/SeqViewLike$Transformed;
  Code:
   Stack=3, Locals=3, Args_size=3
	aload_0
	iload_1
	iload_2
	invokeinterface	InterfaceMethod scala/collection/views/IndexedSeqTransformations.newSliced:(II)Lscala/collection/IndexedSeqViewLike$Transformed;
	areturn
  Labels:
  LocalVariableTable: 
   Start  Length  Slot  Name   Signature
   0      9      0    this       Lscala/collection/views/IndexedSeqLike;
   0      9      1    _from       I
   0      9      2    _until       I

  Signature: length = 0x2
   00 3E 

public scala.collection.IterableViewLike$Transformed newSliced(int, int);
  Signature: (II)Lscala/collection/IterableViewLike$Transformed;
  Code:
   Stack=3, Locals=3, Args_size=3
	aload_0
	iload_1
	iload_2
	invokeinterface	InterfaceMethod scala/collection/views/IndexedSeqTransformations.newSliced:(II)Lscala/collection/IndexedSeqViewLike$Transformed;
	areturn
  Labels:
  LocalVariableTable: 
   Start  Length  Slot  Name   Signature
   0      9      0    this       Lscala/collection/views/IndexedSeqLike;
   0      9      1    _from       I
   0      9      2    _until       I

  Signature: length = 0x2
   00 45 

public scala.collection.TraversableViewLike$Transformed newSliced(int, int);
  Signature: (II)Lscala/collection/TraversableViewLike$Transformed;
  Code:
   Stack=3, Locals=3, Args_size=3
	aload_0
	iload_1
	iload_2
	invokeinterface	InterfaceMethod scala/collection/views/IndexedSeqTransformations.newSliced:(II)Lscala/collection/IndexedSeqViewLike$Transformed;
	areturn
  Labels:
  LocalVariableTable: 
   Start  Length  Slot  Name   Signature
   0      9      0    this       Lscala/collection/views/IndexedSeqLike;
   0      9      1    _from       I
   0      9      2    _until       I

  Signature: length = 0x2
   00 46 

public scala.collection.SeqViewLike$Transformed newDroppedWhile(scala.Function1);
  Signature: (Lscala/Function1;)Lscala/collection/SeqViewLike$Transformed;
  Code:
   Stack=2, Locals=2, Args_size=2
	aload_0
	aload_1
	invokeinterface	InterfaceMethod scala/collection/views/IndexedSeqTransformations.newDroppedWhile:(Lscala/Function1;)Lscala/collection/IndexedSeqViewLike$Transformed;
	areturn
  Labels:
  LocalVariableTable: 
   Start  Length  Slot  Name   Signature
   0      8      0    this       Lscala/collection/views/IndexedSeqLike;
   0      8      1    p       Lscala/Function1;

  Signature: length = 0x2
   00 2E 

public scala.collection.IterableViewLike$Transformed newDroppedWhile(scala.Function1);
  Signature: (Lscala/Function1;)Lscala/collection/IterableViewLike$Transformed;
  Code:
   Stack=2, Locals=2, Args_size=2
	aload_0
	aload_1
	invokeinterface	InterfaceMethod scala/collection/views/IndexedSeqTransformations.newDroppedWhile:(Lscala/Function1;)Lscala/collection/IndexedSeqViewLike$Transformed;
	areturn
  Labels:
  LocalVariableTable: 
   Start  Length  Slot  Name   Signature
   0      8      0    this       Lscala/collection/views/IndexedSeqLike;
   0      8      1    p       Lscala/Function1;

  Signature: length = 0x2
   00 34 

public scala.collection.TraversableViewLike$Transformed newDroppedWhile(scala.Function1);
  Signature: (Lscala/Function1;)Lscala/collection/TraversableViewLike$Transformed;
  Code:
   Stack=2, Locals=2, Args_size=2
	aload_0
	aload_1
	invokeinterface	InterfaceMethod scala/collection/views/IndexedSeqTransformations.newDroppedWhile:(Lscala/Function1;)Lscala/collection/IndexedSeqViewLike$Transformed;
	areturn
  Labels:
  LocalVariableTable: 
   Start  Length  Slot  Name   Signature
   0      8      0    this       Lscala/collection/views/IndexedSeqLike;
   0      8      1    p       Lscala/Function1;

  Signature: length = 0x2
   00 35 

public scala.collection.SeqViewLike$Transformed newTakenWhile(scala.Function1);
  Signature: (Lscala/Function1;)Lscala/collection/SeqViewLike$Transformed;
  Code:
   Stack=2, Locals=2, Args_size=2
	aload_0
	aload_1
	invokeinterface	InterfaceMethod scala/collection/views/IndexedSeqTransformations.newTakenWhile:(Lscala/Function1;)Lscala/collection/IndexedSeqViewLike$Transformed;
	areturn
  Labels:
  LocalVariableTable: 
   Start  Length  Slot  Name   Signature
   0      8      0    this       Lscala/collection/views/IndexedSeqLike;
   0      8      1    p       Lscala/Function1;

  Signature: length = 0x2
   00 2E 

public scala.collection.IterableViewLike$Transformed newTakenWhile(scala.Function1);
  Signature: (Lscala/Function1;)Lscala/collection/IterableViewLike$Transformed;
  Code:
   Stack=2, Locals=2, Args_size=2
	aload_0
	aload_1
	invokeinterface	InterfaceMethod scala/collection/views/IndexedSeqTransformations.newTakenWhile:(Lscala/Function1;)Lscala/collection/IndexedSeqViewLike$Transformed;
	areturn
  Labels:
  LocalVariableTable: 
   Start  Length  Slot  Name   Signature
   0      8      0    this       Lscala/collection/views/IndexedSeqLike;
   0      8      1    p       Lscala/Function1;

  Signature: length = 0x2
   00 34 

public scala.collection.TraversableViewLike$Transformed newTakenWhile(scala.Function1);
  Signature: (Lscala/Function1;)Lscala/collection/TraversableViewLike$Transformed;
  Code:
   Stack=2, Locals=2, Args_size=2
	aload_0
	aload_1
	invokeinterface	InterfaceMethod scala/collection/views/IndexedSeqTransformations.newTakenWhile:(Lscala/Function1;)Lscala/collection/IndexedSeqViewLike$Transformed;
	areturn
  Labels:
  LocalVariableTable: 
   Start  Length  Slot  Name   Signature
   0      8      0    this       Lscala/collection/views/IndexedSeqLike;
   0      8      1    p       Lscala/Function1;

  Signature: length = 0x2
   00 35 

public scala.collection.SeqViewLike$Transformed newZipped(scala.collection.Iterable);
  Signature: (Lscala/collection/Iterable;)Lscala/collection/SeqViewLike$Transformed;
  Code:
   Stack=2, Locals=2, Args_size=2
	aload_0
	aload_1
	invokeinterface	InterfaceMethod scala/collection/views/IndexedSeqTransformations.newZipped:(Lscala/collection/Iterable;)Lscala/collection/IndexedSeqViewLike$Transformed;
	areturn
  Labels:
  LocalVariableTable: 
   Start  Length  Slot  Name   Signature
   0      8      0    this       Lscala/collection/views/IndexedSeqLike;
   0      8      1    that       Lscala/collection/Iterable;

  Signature: length = 0x2
   00 4E 

public scala.collection.IterableViewLike$Transformed newZipped(scala.collection.Iterable);
  Signature: (Lscala/collection/Iterable;)Lscala/collection/IterableViewLike$Transformed;
  Code:
   Stack=2, Locals=2, Args_size=2
	aload_0
	aload_1
	invokeinterface	InterfaceMethod scala/collection/views/IndexedSeqTransformations.newZipped:(Lscala/collection/Iterable;)Lscala/collection/IndexedSeqViewLike$Transformed;
	areturn
  Labels:
  LocalVariableTable: 
   Start  Length  Slot  Name   Signature
   0      8      0    this       Lscala/collection/views/IndexedSeqLike;
   0      8      1    that       Lscala/collection/Iterable;

  Signature: length = 0x2
   00 53 

public scala.collection.SeqViewLike$Transformed newZippedAll(scala.collection.Iterable, java.lang.Object, java.lang.Object);
  Signature: (Lscala/collection/Iterable;Ljava/lang/Object;Ljava/lang/Object;)Lscala/collection/SeqViewLike$Transformed;
  Code:
   Stack=4, Locals=4, Args_size=4
	aload_0
	aload_1
	aload_2
	aload_3
	invokeinterface	InterfaceMethod scala/collection/views/IndexedSeqTransformations.newZippedAll:(Lscala/collection/Iterable;Ljava/lang/Object;Ljava/lang/Object;)Lscala/collection/IndexedSeqViewLike$Transformed;
	areturn
  Labels:
  LocalVariableTable: 
   Start  Length  Slot  Name   Signature
   0      10      0    this       Lscala/collection/views/IndexedSeqLike;
   0      10      1    that       Lscala/collection/Iterable;
   0      10      2    _thisElem       Ljava/lang/Object;
   0      10      3    _thatElem       Ljava/lang/Object;

  Signature: length = 0x2
   00 55 

public scala.collection.IterableViewLike$Transformed newZippedAll(scala.collection.Iterable, java.lang.Object, java.lang.Object);
  Signature: (Lscala/collection/Iterable;Ljava/lang/Object;Ljava/lang/Object;)Lscala/collection/IterableViewLike$Transformed;
  Code:
   Stack=4, Locals=4, Args_size=4
	aload_0
	aload_1
	aload_2
	aload_3
	invokeinterface	InterfaceMethod scala/collection/views/IndexedSeqTransformations.newZippedAll:(Lscala/collection/Iterable;Ljava/lang/Object;Ljava/lang/Object;)Lscala/collection/IndexedSeqViewLike$Transformed;
	areturn
  Labels:
  LocalVariableTable: 
   Start  Length  Slot  Name   Signature
   0      10      0    this       Lscala/collection/views/IndexedSeqLike;
   0      10      1    that       Lscala/collection/Iterable;
   0      10      2    _thisElem       Ljava/lang/Object;
   0      10      3    _thatElem       Ljava/lang/Object;

  Signature: length = 0x2
   00 5C 

public scala.collection.SeqViewLike$Transformed newReversed();
  Signature: ()Lscala/collection/SeqViewLike$Transformed;
  Code:
   Stack=1, Locals=1, Args_size=1
	aload_0
	invokeinterface	InterfaceMethod scala/collection/views/IndexedSeqTransformations.newReversed:()Lscala/collection/IndexedSeqViewLike$Transformed;
	areturn
  Labels:
  Signature: length = 0x2
   00 5E 

public scala.collection.SeqViewLike$Transformed newPatched(int, scala.collection.Seq, int);
  Signature: (ILscala/collection/Seq;I)Lscala/collection/SeqViewLike$Transformed;
  Code:
   Stack=4, Locals=4, Args_size=4
	aload_0
	iload_1
	aload_2
	iload_3
	invokeinterface	InterfaceMethod scala/collection/views/IndexedSeqTransformations.newPatched:(ILscala/collection/Seq;I)Lscala/collection/IndexedSeqViewLike$Transformed;
	areturn
  Labels:
  LocalVariableTable: 
   Start  Length  Slot  Name   Signature
   0      10      0    this       Lscala/collection/views/IndexedSeqLike;
   0      10      1    _from       I
   0      10      2    _patch       Lscala/collection/Seq;
   0      10      3    _replaced       I

  Signature: length = 0x2
   00 63 

public scala.collection.Seq thisCollection();
  Signature: ()Lscala/collection/Seq;
  Code:
   Stack=1, Locals=1, Args_size=1
	aload_0
	invokeinterface	InterfaceMethod scala/collection/IndexedSeqLike.thisCollection:()Lscala/collection/IndexedSeq;
	areturn
  Labels:

public scala.collection.Iterable thisCollection();
  Signature: ()Lscala/collection/Iterable;
  Code:
   Stack=1, Locals=1, Args_size=1
	aload_0
	invokeinterface	InterfaceMethod scala/collection/IndexedSeqLike.thisCollection:()Lscala/collection/IndexedSeq;
	areturn
  Labels:

public scala.collection.Traversable thisCollection();
  Signature: ()Lscala/collection/Traversable;
  Code:
   Stack=1, Locals=1, Args_size=1
	aload_0
	invokeinterface	InterfaceMethod scala/collection/IndexedSeqLike.thisCollection:()Lscala/collection/IndexedSeq;
	areturn
  Labels:

public scala.collection.Seq toCollection(java.lang.Object);
  Signature: (Ljava/lang/Object;)Lscala/collection/Seq;
  Code:
   Stack=2, Locals=2, Args_size=2
	aload_0
	aload_1
	invokeinterface	InterfaceMethod scala/collection/IndexedSeqLike.toCollection:(Ljava/lang/Object;)Lscala/collection/IndexedSeq;
	areturn
  Labels:
  LocalVariableTable: 
   Start  Length  Slot  Name   Signature
   0      8      0    this       Lscala/collection/views/IndexedSeqLike;
   0      8      1    repr       Ljava/lang/Object;


public scala.collection.Iterable toCollection(java.lang.Object);
  Signature: (Ljava/lang/Object;)Lscala/collection/Iterable;
  Code:
   Stack=2, Locals=2, Args_size=2
	aload_0
	aload_1
	invokeinterface	InterfaceMethod scala/collection/IndexedSeqLike.toCollection:(Ljava/lang/Object;)Lscala/collection/IndexedSeq;
	areturn
  Labels:
  LocalVariableTable: 
   Start  Length  Slot  Name   Signature
   0      8      0    this       Lscala/collection/views/IndexedSeqLike;
   0      8      1    repr       Ljava/lang/Object;


public scala.collection.Traversable toCollection(java.lang.Object);
  Signature: (Ljava/lang/Object;)Lscala/collection/Traversable;
  Code:
   Stack=2, Locals=2, Args_size=2
	aload_0
	aload_1
	invokeinterface	InterfaceMethod scala/collection/IndexedSeqLike.toCollection:(Ljava/lang/Object;)Lscala/collection/IndexedSeq;
	areturn
  Labels:
  LocalVariableTable: 
   Start  Length  Slot  Name   Signature
   0      8      0    this       Lscala/collection/views/IndexedSeqLike;
   0      8      1    repr       Ljava/lang/Object;


public scala.collection.TraversableView slice(int, int);
  Signature: (II)Lscala/collection/TraversableView;
  Code:
   Stack=3, Locals=3, Args_size=3
	aload_0
	iload_1
	iload_2
	invokeinterface	InterfaceMethod scala/collection/IndexedSeqLike.slice:(II)Ljava/lang/Object;
	checkcast	class scala/collection/TraversableView
	areturn
  Labels:
  LocalVariableTable: 
   Start  Length  Slot  Name   Signature
   0      12      0    this       Lscala/collection/views/IndexedSeqLike;
   0      12      1    from       I
   0      12      2    until       I


public scala.collection.TraversableView init();
  Signature: ()Lscala/collection/TraversableView;
  Code:
   Stack=1, Locals=1, Args_size=1
	aload_0
	invokeinterface	InterfaceMethod scala/collection/IndexedSeqLike.init:()Ljava/lang/Object;
	checkcast	class scala/collection/TraversableView
	areturn
  Labels:

public scala.collection.TraversableView take(int);
  Signature: (I)Lscala/collection/TraversableView;
  Code:
   Stack=2, Locals=2, Args_size=2
	aload_0
	iload_1
	invokeinterface	InterfaceMethod scala/collection/IndexedSeqLike.take:(I)Ljava/lang/Object;
	checkcast	class scala/collection/TraversableView
	areturn
  Labels:
  LocalVariableTable: 
   Start  Length  Slot  Name   Signature
   0      11      0    this       Lscala/collection/views/IndexedSeqLike;
   0      11      1    n       I


public scala.collection.TraversableView drop(int);
  Signature: (I)Lscala/collection/TraversableView;
  Code:
   Stack=2, Locals=2, Args_size=2
	aload_0
	iload_1
	invokeinterface	InterfaceMethod scala/collection/IndexedSeqLike.drop:(I)Ljava/lang/Object;
	checkcast	class scala/collection/TraversableView
	areturn
  Labels:
  LocalVariableTable: 
   Start  Length  Slot  Name   Signature
   0      11      0    this       Lscala/collection/views/IndexedSeqLike;
   0      11      1    n       I


public scala.collection.TraversableView takeWhile(scala.Function1);
  Signature: (Lscala/Function1;)Lscala/collection/TraversableView;
  Code:
   Stack=2, Locals=2, Args_size=2
	aload_0
	aload_1
	invokeinterface	InterfaceMethod scala/collection/IndexedSeqLike.takeWhile:(Lscala/Function1;)Ljava/lang/Object;
	checkcast	class scala/collection/TraversableView
	areturn
  Labels:
  LocalVariableTable: 
   Start  Length  Slot  Name   Signature
   0      11      0    this       Lscala/collection/views/IndexedSeqLike;
   0      11      1    p       Lscala/Function1;


public scala.collection.TraversableView dropWhile(scala.Function1);
  Signature: (Lscala/Function1;)Lscala/collection/TraversableView;
  Code:
   Stack=2, Locals=2, Args_size=2
	aload_0
	aload_1
	invokeinterface	InterfaceMethod scala/collection/IndexedSeqLike.dropWhile:(Lscala/Function1;)Ljava/lang/Object;
	checkcast	class scala/collection/TraversableView
	areturn
  Labels:
  LocalVariableTable: 
   Start  Length  Slot  Name   Signature
   0      11      0    this       Lscala/collection/views/IndexedSeqLike;
   0      11      1    p       Lscala/Function1;


public scala.collection.SeqView reverse();
  Signature: ()Lscala/collection/SeqView;
  Code:
   Stack=1, Locals=1, Args_size=1
	aload_0
	invokeinterface	InterfaceMethod scala/collection/IndexedSeqLike.reverse:()Ljava/lang/Object;
	checkcast	class scala/collection/SeqView
	areturn
  Labels:

public scala.collection.SeqView view();
  Signature: ()Lscala/collection/SeqView;
  Code:
   Stack=1, Locals=1, Args_size=1
	aload_0
	invokeinterface	InterfaceMethod scala/collection/IndexedSeqLike.view:()Lscala/collection/IndexedSeqView;
	areturn
  Labels:

public scala.collection.IterableView view();
  Signature: ()Lscala/collection/IterableView;
  Code:
   Stack=1, Locals=1, Args_size=1
	aload_0
	invokeinterface	InterfaceMethod scala/collection/IndexedSeqLike.view:()Lscala/collection/IndexedSeqView;
	areturn
  Labels:

public scala.collection.TraversableView view();
  Signature: ()Lscala/collection/TraversableView;
  Code:
   Stack=1, Locals=1, Args_size=1
	aload_0
	invokeinterface	InterfaceMethod scala/collection/IndexedSeqLike.view:()Lscala/collection/IndexedSeqView;
	areturn
  Labels:

public scala.collection.SeqView view(int, int);
  Signature: (II)Lscala/collection/SeqView;
  Code:
   Stack=3, Locals=3, Args_size=3
	aload_0
	iload_1
	iload_2
	invokeinterface	InterfaceMethod scala/collection/IndexedSeqLike.view:(II)Lscala/collection/IndexedSeqView;
	areturn
  Labels:
  LocalVariableTable: 
   Start  Length  Slot  Name   Signature
   0      9      0    this       Lscala/collection/views/IndexedSeqLike;
   0      9      1    from       I
   0      9      2    until       I


public scala.collection.IterableView view(int, int);
  Signature: (II)Lscala/collection/IterableView;
  Code:
   Stack=3, Locals=3, Args_size=3
	aload_0
	iload_1
	iload_2
	invokeinterface	InterfaceMethod scala/collection/IndexedSeqLike.view:(II)Lscala/collection/IndexedSeqView;
	areturn
  Labels:
  LocalVariableTable: 
   Start  Length  Slot  Name   Signature
   0      9      0    this       Lscala/collection/views/IndexedSeqLike;
   0      9      1    from       I
   0      9      2    until       I


public scala.collection.TraversableView view(int, int);
  Signature: (II)Lscala/collection/TraversableView;
  Code:
   Stack=3, Locals=3, Args_size=3
	aload_0
	iload_1
	iload_2
	invokeinterface	InterfaceMethod scala/collection/IndexedSeqLike.view:(II)Lscala/collection/IndexedSeqView;
	areturn
  Labels:
  LocalVariableTable: 
   Start  Length  Slot  Name   Signature
   0      9      0    this       Lscala/collection/views/IndexedSeqLike;
   0      9      1    from       I
   0      9      2    until       I


public boolean isDefinedAt(java.lang.Object);
  Signature: (Ljava/lang/Object;)Z
  Code:
   Stack=2, Locals=2, Args_size=2
	aload_0
	aload_1
	invokestatic	Method scala/runtime/BoxesRunTime.unboxToInt:(Ljava/lang/Object;)I
	invokeinterface	InterfaceMethod scala/collection/SeqLike.isDefinedAt:(I)Z
	ireturn
  Labels:
  LocalVariableTable: 
   Start  Length  Slot  Name   Signature
   0      11      0    this       Lscala/collection/views/IndexedSeqLike;
   0      11      1    x       Ljava/lang/Object;


public scala.collection.IterableView projection();
  Signature: ()Lscala/collection/IterableView;
  Code:
   Stack=1, Locals=1, Args_size=1
	aload_0
	invokeinterface	InterfaceMethod scala/collection/SeqLike.projection:()Lscala/collection/SeqView;
	areturn
  Labels:

public java.lang.Object filter(scala.Function1);
  Signature: (Lscala/Function1;)Ljava/lang/Object;
  Code:
   Stack=2, Locals=2, Args_size=2
	aload_0
	aload_1
	invokeinterface	InterfaceMethod scala/collection/TraversableViewLike.filter:(Lscala/Function1;)Lscala/collection/TraversableView;
	areturn
  Labels:
  LocalVariableTable: 
   Start  Length  Slot  Name   Signature
   0      8      0    this       Lscala/collection/views/IndexedSeqLike;
   0      8      1    p       Lscala/Function1;


public void foreach(scala.Function1);
  Signature: (Lscala/Function1;)V
  Code:
   Stack=2, Locals=2, Args_size=2
	aload_0
	aload_1
	invokestatic	Method scala/collection/IndexedSeqLike$class.foreach:(Lscala/collection/IndexedSeqLike;Lscala/Function1;)V
	return
  Labels:
  LocalVariableTable: 
   Start  Length  Slot  Name   Signature
   0      6      0    this       Lscala/collection/views/IndexedSeqLike;
   0      6      1    f       Lscala/Function1;

  Signature: length = 0x2
   00 FFFFFFC5 

public scala.collection.IndexedSeqView view(int, int);
  Signature: (II)Lscala/collection/IndexedSeqView;
  Code:
   Stack=3, Locals=3, Args_size=3
	aload_0
	iload_1
	iload_2
	invokestatic	Method scala/collection/IndexedSeqLike$class.view:(Lscala/collection/IndexedSeqLike;II)Lscala/collection/IndexedSeqView;
	areturn
  Labels:
  LocalVariableTable: 
   Start  Length  Slot  Name   Signature
   0      7      0    this       Lscala/collection/views/IndexedSeqLike;
   0      7      1    from       I
   0      7      2    until       I


public scala.collection.IndexedSeqView view();
  Signature: ()Lscala/collection/IndexedSeqView;
  Code:
   Stack=1, Locals=1, Args_size=1
	aload_0
	invokestatic	Method scala/collection/IndexedSeqLike$class.view:(Lscala/collection/IndexedSeqLike;)Lscala/collection/IndexedSeqView;
	areturn
  Labels:

public boolean endsWith(scala.collection.Seq);
  Signature: (Lscala/collection/Seq;)Z
  Code:
   Stack=2, Locals=2, Args_size=2
	aload_0
	aload_1
	invokestatic	Method scala/collection/IndexedSeqLike$class.endsWith:(Lscala/collection/IndexedSeqLike;Lscala/collection/Seq;)Z
	ireturn
  Labels:
  LocalVariableTable: 
   Start  Length  Slot  Name   Signature
   0      6      0    this       Lscala/collection/views/IndexedSeqLike;
   0      6      1    that       Lscala/collection/Seq;


public boolean startsWith(scala.collection.Seq, int);
  Signature: (Lscala/collection/Seq;I)Z
  Code:
   Stack=3, Locals=3, Args_size=3
	aload_0
	aload_1
	iload_2
	invokestatic	Method scala/collection/IndexedSeqLike$class.startsWith:(Lscala/collection/IndexedSeqLike;Lscala/collection/Seq;I)Z
	ireturn
  Labels:
  LocalVariableTable: 
   Start  Length  Slot  Name   Signature
   0      7      0    this       Lscala/collection/views/IndexedSeqLike;
   0      7      1    that       Lscala/collection/Seq;
   0      7      2    offset       I


public scala.collection.Iterator reverseIterator();
  Signature: ()Lscala/collection/Iterator;
  Code:
   Stack=1, Locals=1, Args_size=1
	aload_0
	invokestatic	Method scala/collection/IndexedSeqLike$class.reverseIterator:(Lscala/collection/IndexedSeqLike;)Lscala/collection/Iterator;
	areturn
  Labels:

public java.lang.Object reverse();
  Signature: ()Ljava/lang/Object;
  Code:
   Stack=1, Locals=1, Args_size=1
	aload_0
	invokestatic	Method scala/collection/IndexedSeqLike$class.reverse:(Lscala/collection/IndexedSeqLike;)Ljava/lang/Object;
	areturn
  Labels:

public int lastIndexWhere(scala.Function1, int);
  Signature: (Lscala/Function1;I)I
  Code:
   Stack=3, Locals=3, Args_size=3
	aload_0
	aload_1
	iload_2
	invokestatic	Method scala/collection/IndexedSeqLike$class.lastIndexWhere:(Lscala/collection/IndexedSeqLike;Lscala/Function1;I)I
	ireturn
  Labels:
  LocalVariableTable: 
   Start  Length  Slot  Name   Signature
   0      7      0    this       Lscala/collection/views/IndexedSeqLike;
   0      7      1    p       Lscala/Function1;
   0      7      2    end       I


public int indexWhere(scala.Function1, int);
  Signature: (Lscala/Function1;I)I
  Code:
   Stack=3, Locals=3, Args_size=3
	aload_0
	aload_1
	iload_2
	invokestatic	Method scala/collection/IndexedSeqLike$class.indexWhere:(Lscala/collection/IndexedSeqLike;Lscala/Function1;I)I
	ireturn
  Labels:
  LocalVariableTable: 
   Start  Length  Slot  Name   Signature
   0      7      0    this       Lscala/collection/views/IndexedSeqLike;
   0      7      1    p       Lscala/Function1;
   0      7      2    from       I


public int segmentLength(scala.Function1, int);
  Signature: (Lscala/Function1;I)I
  Code:
   Stack=3, Locals=3, Args_size=3
	aload_0
	aload_1
	iload_2
	invokestatic	Method scala/collection/IndexedSeqLike$class.segmentLength:(Lscala/collection/IndexedSeqLike;Lscala/Function1;I)I
	ireturn
  Labels:
  LocalVariableTable: 
   Start  Length  Slot  Name   Signature
   0      7      0    this       Lscala/collection/views/IndexedSeqLike;
   0      7      1    p       Lscala/Function1;
   0      7      2    from       I


public int lengthCompare(int);
  Signature: (I)I
  Code:
   Stack=2, Locals=2, Args_size=2
	aload_0
	iload_1
	invokestatic	Method scala/collection/IndexedSeqLike$class.lengthCompare:(Lscala/collection/IndexedSeqLike;I)I
	ireturn
  Labels:
  LocalVariableTable: 
   Start  Length  Slot  Name   Signature
   0      6      0    this       Lscala/collection/views/IndexedSeqLike;
   0      6      1    len       I


public void copyToArray(java.lang.Object, int, int);
  Signature: (Ljava/lang/Object;II)V
  Code:
   Stack=4, Locals=4, Args_size=4
	aload_0
	aload_1
	iload_2
	iload_3
	invokestatic	Method scala/collection/IndexedSeqLike$class.copyToArray:(Lscala/collection/IndexedSeqLike;Ljava/lang/Object;II)V
	return
  Labels:
  LocalVariableTable: 
   Start  Length  Slot  Name   Signature
   0      8      0    this       Lscala/collection/views/IndexedSeqLike;
   0      8      1    xs       Ljava/lang/Object;
   0      8      2    start       I
   0      8      3    len       I


public boolean sameElements(scala.collection.Iterable);
  Signature: (Lscala/collection/Iterable;)Z
  Code:
   Stack=2, Locals=2, Args_size=2
	aload_0
	aload_1
	invokestatic	Method scala/collection/IndexedSeqLike$class.sameElements:(Lscala/collection/IndexedSeqLike;Lscala/collection/Iterable;)Z
	ireturn
  Labels:
  LocalVariableTable: 
   Start  Length  Slot  Name   Signature
   0      6      0    this       Lscala/collection/views/IndexedSeqLike;
   0      6      1    that       Lscala/collection/Iterable;


public scala.Tuple2 span(scala.Function1);
  Signature: (Lscala/Function1;)Lscala/Tuple2;
  Code:
   Stack=2, Locals=2, Args_size=2
	aload_0
	aload_1
	invokestatic	Method scala/collection/IndexedSeqLike$class.span:(Lscala/collection/IndexedSeqLike;Lscala/Function1;)Lscala/Tuple2;
	areturn
  Labels:
  LocalVariableTable: 
   Start  Length  Slot  Name   Signature
   0      6      0    this       Lscala/collection/views/IndexedSeqLike;
   0      6      1    p       Lscala/Function1;


public java.lang.Object dropWhile(scala.Function1);
  Signature: (Lscala/Function1;)Ljava/lang/Object;
  Code:
   Stack=2, Locals=2, Args_size=2
	aload_0
	aload_1
	invokestatic	Method scala/collection/IndexedSeqLike$class.dropWhile:(Lscala/collection/IndexedSeqLike;Lscala/Function1;)Ljava/lang/Object;
	areturn
  Labels:
  LocalVariableTable: 
   Start  Length  Slot  Name   Signature
   0      6      0    this       Lscala/collection/views/IndexedSeqLike;
   0      6      1    p       Lscala/Function1;


public java.lang.Object takeWhile(scala.Function1);
  Signature: (Lscala/Function1;)Ljava/lang/Object;
  Code:
   Stack=2, Locals=2, Args_size=2
	aload_0
	aload_1
	invokestatic	Method scala/collection/IndexedSeqLike$class.takeWhile:(Lscala/collection/IndexedSeqLike;Lscala/Function1;)Ljava/lang/Object;
	areturn
  Labels:
  LocalVariableTable: 
   Start  Length  Slot  Name   Signature
   0      6      0    this       Lscala/collection/views/IndexedSeqLike;
   0      6      1    p       Lscala/Function1;


public scala.Tuple2 splitAt(int);
  Signature: (I)Lscala/Tuple2;
  Code:
   Stack=2, Locals=2, Args_size=2
	aload_0
	iload_1
	invokestatic	Method scala/collection/IndexedSeqLike$class.splitAt:(Lscala/collection/IndexedSeqLike;I)Lscala/Tuple2;
	areturn
  Labels:
  LocalVariableTable: 
   Start  Length  Slot  Name   Signature
   0      6      0    this       Lscala/collection/views/IndexedSeqLike;
   0      6      1    n       I


public java.lang.Object dropRight(int);
  Signature: (I)Ljava/lang/Object;
  Code:
   Stack=2, Locals=2, Args_size=2
	aload_0
	iload_1
	invokestatic	Method scala/collection/IndexedSeqLike$class.dropRight:(Lscala/collection/IndexedSeqLike;I)Ljava/lang/Object;
	areturn
  Labels:
  LocalVariableTable: 
   Start  Length  Slot  Name   Signature
   0      6      0    this       Lscala/collection/views/IndexedSeqLike;
   0      6      1    n       I


public java.lang.Object takeRight(int);
  Signature: (I)Ljava/lang/Object;
  Code:
   Stack=2, Locals=2, Args_size=2
	aload_0
	iload_1
	invokestatic	Method scala/collection/IndexedSeqLike$class.takeRight:(Lscala/collection/IndexedSeqLike;I)Ljava/lang/Object;
	areturn
  Labels:
  LocalVariableTable: 
   Start  Length  Slot  Name   Signature
   0      6      0    this       Lscala/collection/views/IndexedSeqLike;
   0      6      1    n       I


public java.lang.Object drop(int);
  Signature: (I)Ljava/lang/Object;
  Code:
   Stack=2, Locals=2, Args_size=2
	aload_0
	iload_1
	invokestatic	Method scala/collection/IndexedSeqLike$class.drop:(Lscala/collection/IndexedSeqLike;I)Ljava/lang/Object;
	areturn
  Labels:
  LocalVariableTable: 
   Start  Length  Slot  Name   Signature
   0      6      0    this       Lscala/collection/views/IndexedSeqLike;
   0      6      1    n       I


public java.lang.Object take(int);
  Signature: (I)Ljava/lang/Object;
  Code:
   Stack=2, Locals=2, Args_size=2
	aload_0
	iload_1
	invokestatic	Method scala/collection/IndexedSeqLike$class.take:(Lscala/collection/IndexedSeqLike;I)Ljava/lang/Object;
	areturn
  Labels:
  LocalVariableTable: 
   Start  Length  Slot  Name   Signature
   0      6      0    this       Lscala/collection/views/IndexedSeqLike;
   0      6      1    n       I


public java.lang.Object init();
  Signature: ()Ljava/lang/Object;
  Code:
   Stack=1, Locals=1, Args_size=1
	aload_0
	invokestatic	Method scala/collection/IndexedSeqLike$class.init:(Lscala/collection/IndexedSeqLike;)Ljava/lang/Object;
	areturn
  Labels:

public java.lang.Object last();
  Signature: ()Ljava/lang/Object;
  Code:
   Stack=1, Locals=1, Args_size=1
	aload_0
	invokestatic	Method scala/collection/IndexedSeqLike$class.last:(Lscala/collection/IndexedSeqLike;)Ljava/lang/Object;
	areturn
  Labels:

public java.lang.Object tail();
  Signature: ()Ljava/lang/Object;
  Code:
   Stack=1, Locals=1, Args_size=1
	aload_0
	invokestatic	Method scala/collection/IndexedSeqLike$class.tail:(Lscala/collection/IndexedSeqLike;)Ljava/lang/Object;
	areturn
  Labels:

public java.lang.Object head();
  Signature: ()Ljava/lang/Object;
  Code:
   Stack=1, Locals=1, Args_size=1
	aload_0
	invokestatic	Method scala/collection/IndexedSeqLike$class.head:(Lscala/collection/IndexedSeqLike;)Ljava/lang/Object;
	areturn
  Labels:

public java.lang.Object slice(int, int);
  Signature: (II)Ljava/lang/Object;
  Code:
   Stack=3, Locals=3, Args_size=3
	aload_0
	iload_1
	iload_2
	invokestatic	Method scala/collection/IndexedSeqLike$class.slice:(Lscala/collection/IndexedSeqLike;II)Ljava/lang/Object;
	areturn
  Labels:
  LocalVariableTable: 
   Start  Length  Slot  Name   Signature
   0      7      0    this       Lscala/collection/views/IndexedSeqLike;
   0      7      1    from       I
   0      7      2    until       I


public java.lang.Object zipWithIndex(scala.collection.generic.CanBuildFrom);
  Signature: (Lscala/collection/generic/CanBuildFrom;)Ljava/lang/Object;
  Code:
   Stack=2, Locals=2, Args_size=2
	aload_0
	aload_1
	invokestatic	Method scala/collection/IndexedSeqLike$class.zipWithIndex:(Lscala/collection/IndexedSeqLike;Lscala/collection/generic/CanBuildFrom;)Ljava/lang/Object;
	areturn
  Labels:
  LocalVariableTable: 
   Start  Length  Slot  Name   Signature
   0      6      0    this       Lscala/collection/views/IndexedSeqLike;
   0      6      1    bf       Lscala/collection/generic/CanBuildFrom;


public java.lang.Object zip(scala.collection.Iterable, scala.collection.generic.CanBuildFrom);
  Signature: (Lscala/collection/Iterable;Lscala/collection/generic/CanBuildFrom;)Ljava/lang/Object;
  Code:
   Stack=3, Locals=3, Args_size=3
	aload_0
	aload_1
	aload_2
	invokestatic	Method scala/collection/IndexedSeqLike$class.zip:(Lscala/collection/IndexedSeqLike;Lscala/collection/Iterable;Lscala/collection/generic/CanBuildFrom;)Ljava/lang/Object;
	areturn
  Labels:
  LocalVariableTable: 
   Start  Length  Slot  Name   Signature
   0      7      0    this       Lscala/collection/views/IndexedSeqLike;
   0      7      1    that       Lscala/collection/Iterable;
   0      7      2    bf       Lscala/collection/generic/CanBuildFrom;


public java.lang.Object reduceRight(scala.Function2);
  Signature: (Lscala/Function2;)Ljava/lang/Object;
  Code:
   Stack=2, Locals=2, Args_size=2
	aload_0
	aload_1
	invokestatic	Method scala/collection/IndexedSeqLike$class.reduceRight:(Lscala/collection/IndexedSeqLike;Lscala/Function2;)Ljava/lang/Object;
	areturn
  Labels:
  LocalVariableTable: 
   Start  Length  Slot  Name   Signature
   0      6      0    this       Lscala/collection/views/IndexedSeqLike;
   0      6      1    op       Lscala/Function2;


public java.lang.Object reduceLeft(scala.Function2);
  Signature: (Lscala/Function2;)Ljava/lang/Object;
  Code:
   Stack=2, Locals=2, Args_size=2
	aload_0
	aload_1
	invokestatic	Method scala/collection/IndexedSeqLike$class.reduceLeft:(Lscala/collection/IndexedSeqLike;Lscala/Function2;)Ljava/lang/Object;
	areturn
  Labels:
  LocalVariableTable: 
   Start  Length  Slot  Name   Signature
   0      6      0    this       Lscala/collection/views/IndexedSeqLike;
   0      6      1    op       Lscala/Function2;


public java.lang.Object foldRight(java.lang.Object, scala.Function2);
  Signature: (Ljava/lang/Object;Lscala/Function2;)Ljava/lang/Object;
  Code:
   Stack=3, Locals=3, Args_size=3
	aload_0
	aload_1
	aload_2
	invokestatic	Method scala/collection/IndexedSeqLike$class.foldRight:(Lscala/collection/IndexedSeqLike;Ljava/lang/Object;Lscala/Function2;)Ljava/lang/Object;
	areturn
  Labels:
  LocalVariableTable: 
   Start  Length  Slot  Name   Signature
   0      7      0    this       Lscala/collection/views/IndexedSeqLike;
   0      7      1    z       Ljava/lang/Object;
   0      7      2    op       Lscala/Function2;


public java.lang.Object foldLeft(java.lang.Object, scala.Function2);
  Signature: (Ljava/lang/Object;Lscala/Function2;)Ljava/lang/Object;
  Code:
   Stack=3, Locals=3, Args_size=3
	aload_0
	aload_1
	aload_2
	invokestatic	Method scala/collection/IndexedSeqLike$class.foldLeft:(Lscala/collection/IndexedSeqLike;Ljava/lang/Object;Lscala/Function2;)Ljava/lang/Object;
	areturn
  Labels:
  LocalVariableTable: 
   Start  Length  Slot  Name   Signature
   0      7      0    this       Lscala/collection/views/IndexedSeqLike;
   0      7      1    z       Ljava/lang/Object;
   0      7      2    op       Lscala/Function2;


public scala.Option find(scala.Function1);
  Signature: (Lscala/Function1;)Lscala/Option;
  Code:
   Stack=2, Locals=2, Args_size=2
	aload_0
	aload_1
	invokestatic	Method scala/collection/IndexedSeqLike$class.find:(Lscala/collection/IndexedSeqLike;Lscala/Function1;)Lscala/Option;
	areturn
  Labels:
  LocalVariableTable: 
   Start  Length  Slot  Name   Signature
   0      6      0    this       Lscala/collection/views/IndexedSeqLike;
   0      6      1    p       Lscala/Function1;


public boolean exists(scala.Function1);
  Signature: (Lscala/Function1;)Z
  Code:
   Stack=2, Locals=2, Args_size=2
	aload_0
	aload_1
	invokestatic	Method scala/collection/IndexedSeqLike$class.exists:(Lscala/collection/IndexedSeqLike;Lscala/Function1;)Z
	ireturn
  Labels:
  LocalVariableTable: 
   Start  Length  Slot  Name   Signature
   0      6      0    this       Lscala/collection/views/IndexedSeqLike;
   0      6      1    p       Lscala/Function1;


public boolean forall(scala.Function1);
  Signature: (Lscala/Function1;)Z
  Code:
   Stack=2, Locals=2, Args_size=2
	aload_0
	aload_1
	invokestatic	Method scala/collection/IndexedSeqLike$class.forall:(Lscala/collection/IndexedSeqLike;Lscala/Function1;)Z
	ireturn
  Labels:
  LocalVariableTable: 
   Start  Length  Slot  Name   Signature
   0      6      0    this       Lscala/collection/views/IndexedSeqLike;
   0      6      1    p       Lscala/Function1;


public boolean isEmpty();
  Signature: ()Z
  Code:
   Stack=1, Locals=1, Args_size=1
	aload_0
	invokestatic	Method scala/collection/IndexedSeqLike$class.isEmpty:(Lscala/collection/IndexedSeqLike;)Z
	ireturn
  Labels:

public scala.collection.Iterator iterator();
  Signature: ()Lscala/collection/Iterator;
  Code:
   Stack=1, Locals=1, Args_size=1
	aload_0
	invokestatic	Method scala/collection/IndexedSeqLike$class.iterator:(Lscala/collection/IndexedSeqLike;)Lscala/collection/Iterator;
	areturn
  Labels:

public scala.collection.IndexedSeq toCollection(java.lang.Object);
  Signature: (Ljava/lang/Object;)Lscala/collection/IndexedSeq;
  Code:
   Stack=2, Locals=2, Args_size=2
	aload_0
	aload_1
	invokestatic	Method scala/collection/IndexedSeqLike$class.toCollection:(Lscala/collection/IndexedSeqLike;Ljava/lang/Object;)Lscala/collection/IndexedSeq;
	areturn
  Labels:
  LocalVariableTable: 
   Start  Length  Slot  Name   Signature
   0      6      0    this       Lscala/collection/views/IndexedSeqLike;
   0      6      1    repr       Ljava/lang/Object;


public scala.collection.IndexedSeq thisCollection();
  Signature: ()Lscala/collection/IndexedSeq;
  Code:
   Stack=1, Locals=1, Args_size=1
	aload_0
	invokestatic	Method scala/collection/IndexedSeqLike$class.thisCollection:(Lscala/collection/IndexedSeqLike;)Lscala/collection/IndexedSeq;
	areturn
  Labels:

public final boolean scala$collection$IndexedSeqLike$$super$endsWith(scala.collection.Seq);
  Signature: (Lscala/collection/Seq;)Z
  Code:
   Stack=2, Locals=2, Args_size=2
	aload_0
	aload_1
	invokestatic	Method scala/collection/SeqLike$class.endsWith:(Lscala/collection/SeqLike;Lscala/collection/Seq;)Z
	ireturn
  Labels:
  LocalVariableTable: 
   Start  Length  Slot  Name   Signature
   0      6      0    this       Lscala/collection/views/IndexedSeqLike;
   0      6      1    that       Lscala/collection/Seq;


public final boolean scala$collection$IndexedSeqLike$$super$sameElements(scala.collection.Iterable);
  Signature: (Lscala/collection/Iterable;)Z
  Code:
   Stack=2, Locals=2, Args_size=2
	aload_0
	aload_1
	invokestatic	Method scala/collection/IterableLike$class.sameElements:(Lscala/collection/IterableLike;Lscala/collection/Iterable;)Z
	ireturn
  Labels:
  LocalVariableTable: 
   Start  Length  Slot  Name   Signature
   0      6      0    this       Lscala/collection/views/IndexedSeqLike;
   0      6      1    that       Lscala/collection/Iterable;


public final java.lang.Object scala$collection$IndexedSeqLike$$super$init();
  Signature: ()Ljava/lang/Object;
  Code:
   Stack=1, Locals=1, Args_size=1
	aload_0
	invokestatic	Method scala/collection/TraversableViewLike$class.init:(Lscala/collection/TraversableViewLike;)Lscala/collection/TraversableView;
	areturn
  Labels:

public final java.lang.Object scala$collection$IndexedSeqLike$$super$last();
  Signature: ()Ljava/lang/Object;
  Code:
   Stack=1, Locals=1, Args_size=1
	aload_0
	invokestatic	Method scala/collection/TraversableLike$class.last:(Lscala/collection/TraversableLike;)Ljava/lang/Object;
	areturn
  Labels:

public final java.lang.Object scala$collection$IndexedSeqLike$$super$tail();
  Signature: ()Ljava/lang/Object;
  Code:
   Stack=1, Locals=1, Args_size=1
	aload_0
	invokestatic	Method scala/collection/TraversableLike$class.tail:(Lscala/collection/TraversableLike;)Ljava/lang/Object;
	areturn
  Labels:

public final java.lang.Object scala$collection$IndexedSeqLike$$super$head();
  Signature: ()Ljava/lang/Object;
  Code:
   Stack=1, Locals=1, Args_size=1
	aload_0
	invokestatic	Method scala/collection/IterableLike$class.head:(Lscala/collection/IterableLike;)Ljava/lang/Object;
	areturn
  Labels:

public final java.lang.Object scala$collection$IndexedSeqLike$$super$zip(scala.collection.Iterable, scala.collection.generic.CanBuildFrom);
  Signature: (Lscala/collection/Iterable;Lscala/collection/generic/CanBuildFrom;)Ljava/lang/Object;
  Code:
   Stack=3, Locals=3, Args_size=3
	aload_0
	aload_1
	aload_2
	invokestatic	Method scala/collection/IterableViewLike$class.zip:(Lscala/collection/IterableViewLike;Lscala/collection/Iterable;Lscala/collection/generic/CanBuildFrom;)Ljava/lang/Object;
	areturn
  Labels:
  LocalVariableTable: 
   Start  Length  Slot  Name   Signature
   0      7      0    this       Lscala/collection/views/IndexedSeqLike;
   0      7      1    that       Lscala/collection/Iterable;
   0      7      2    bf       Lscala/collection/generic/CanBuildFrom;


public final java.lang.Object scala$collection$IndexedSeqLike$$super$reduceRight(scala.Function2);
  Signature: (Lscala/Function2;)Ljava/lang/Object;
  Code:
   Stack=2, Locals=2, Args_size=2
	aload_0
	aload_1
	invokestatic	Method scala/collection/IterableLike$class.reduceRight:(Lscala/collection/IterableLike;Lscala/Function2;)Ljava/lang/Object;
	areturn
  Labels:
  LocalVariableTable: 
   Start  Length  Slot  Name   Signature
   0      6      0    this       Lscala/collection/views/IndexedSeqLike;
   0      6      1    op       Lscala/Function2;


public final java.lang.Object scala$collection$IndexedSeqLike$$super$reduceLeft(scala.Function2);
  Signature: (Lscala/Function2;)Ljava/lang/Object;
  Code:
   Stack=2, Locals=2, Args_size=2
	aload_0
	aload_1
	invokestatic	Method scala/collection/TraversableLike$class.reduceLeft:(Lscala/collection/TraversableLike;Lscala/Function2;)Ljava/lang/Object;
	areturn
  Labels:
  LocalVariableTable: 
   Start  Length  Slot  Name   Signature
   0      6      0    this       Lscala/collection/views/IndexedSeqLike;
   0      6      1    op       Lscala/Function2;


public scala.collection.generic.GenericCompanion companion();
  Signature: ()Lscala/collection/generic/GenericCompanion;
  Code:
   Stack=1, Locals=1, Args_size=1
	aload_0
	invokestatic	Method scala/collection/IndexedSeq$class.companion:(Lscala/collection/IndexedSeq;)Lscala/collection/generic/GenericCompanion;
	areturn
  Labels:

public scala.collection.IndexedSeqViewLike$Transformed newPatched(int, scala.collection.Seq, int);
  Signature: (ILscala/collection/Seq;I)Lscala/collection/IndexedSeqViewLike$Transformed;
  Code:
   Stack=4, Locals=4, Args_size=4
	aload_0
	iload_1
	aload_2
	iload_3
	invokestatic	Method scala/collection/views/IndexedSeqTransformations$class.newPatched:(Lscala/collection/IndexedSeqViewLike;ILscala/collection/Seq;I)Lscala/collection/IndexedSeqViewLike$Transformed;
	areturn
  Labels:
  LocalVariableTable: 
   Start  Length  Slot  Name   Signature
   0      8      0    this       Lscala/collection/views/IndexedSeqLike;
   0      8      1    _from       I
   0      8      2    _patch       Lscala/collection/Seq;
   0      8      3    _replaced       I

  Signature: length = 0x2
   00 64 

public scala.collection.IndexedSeqViewLike$Transformed newReversed();
  Signature: ()Lscala/collection/IndexedSeqViewLike$Transformed;
  Code:
   Stack=1, Locals=1, Args_size=1
	aload_0
	invokestatic	Method scala/collection/views/IndexedSeqTransformations$class.newReversed:(Lscala/collection/IndexedSeqViewLike;)Lscala/collection/IndexedSeqViewLike$Transformed;
	areturn
  Labels:
  Signature: length = 0x2
   00 5F 

public scala.collection.IndexedSeqViewLike$Transformed newZippedAll(scala.collection.Iterable, java.lang.Object, java.lang.Object);
  Signature: (Lscala/collection/Iterable;Ljava/lang/Object;Ljava/lang/Object;)Lscala/collection/IndexedSeqViewLike$Transformed;
  Code:
   Stack=4, Locals=4, Args_size=4
	aload_0
	aload_1
	aload_2
	aload_3
	invokestatic	Method scala/collection/views/IndexedSeqTransformations$class.newZippedAll:(Lscala/collection/IndexedSeqViewLike;Lscala/collection/Iterable;Ljava/lang/Object;Ljava/lang/Object;)Lscala/collection/IndexedSeqViewLike$Transformed;
	areturn
  Labels:
  LocalVariableTable: 
   Start  Length  Slot  Name   Signature
   0      8      0    this       Lscala/collection/views/IndexedSeqLike;
   0      8      1    that       Lscala/collection/Iterable;
   0      8      2    _thisElem       Ljava/lang/Object;
   0      8      3    _thatElem       Ljava/lang/Object;

  Signature: length = 0x2
   00 56 

public scala.collection.IndexedSeqViewLike$Transformed newZipped(scala.collection.Iterable);
  Signature: (Lscala/collection/Iterable;)Lscala/collection/IndexedSeqViewLike$Transformed;
  Code:
   Stack=2, Locals=2, Args_size=2
	aload_0
	aload_1
	invokestatic	Method scala/collection/views/IndexedSeqTransformations$class.newZipped:(Lscala/collection/IndexedSeqViewLike;Lscala/collection/Iterable;)Lscala/collection/IndexedSeqViewLike$Transformed;
	areturn
  Labels:
  LocalVariableTable: 
   Start  Length  Slot  Name   Signature
   0      6      0    this       Lscala/collection/views/IndexedSeqLike;
   0      6      1    that       Lscala/collection/Iterable;

  Signature: length = 0x2
   00 4F 

public scala.collection.IndexedSeqViewLike$Transformed newTakenWhile(scala.Function1);
  Signature: (Lscala/Function1;)Lscala/collection/IndexedSeqViewLike$Transformed;
  Code:
   Stack=2, Locals=2, Args_size=2
	aload_0
	aload_1
	invokestatic	Method scala/collection/views/IndexedSeqTransformations$class.newTakenWhile:(Lscala/collection/IndexedSeqViewLike;Lscala/Function1;)Lscala/collection/IndexedSeqViewLike$Transformed;
	areturn
  Labels:
  LocalVariableTable: 
   Start  Length  Slot  Name   Signature
   0      6      0    this       Lscala/collection/views/IndexedSeqLike;
   0      6      1    p       Lscala/Function1;

  Signature: length = 0x2
   00 2F 

public scala.collection.IndexedSeqViewLike$Transformed newDroppedWhile(scala.Function1);
  Signature: (Lscala/Function1;)Lscala/collection/IndexedSeqViewLike$Transformed;
  Code:
   Stack=2, Locals=2, Args_size=2
	aload_0
	aload_1
	invokestatic	Method scala/collection/views/IndexedSeqTransformations$class.newDroppedWhile:(Lscala/collection/IndexedSeqViewLike;Lscala/Function1;)Lscala/collection/IndexedSeqViewLike$Transformed;
	areturn
  Labels:
  LocalVariableTable: 
   Start  Length  Slot  Name   Signature
   0      6      0    this       Lscala/collection/views/IndexedSeqLike;
   0      6      1    p       Lscala/Function1;

  Signature: length = 0x2
   00 2F 

public scala.collection.IndexedSeqViewLike$Transformed newSliced(int, int);
  Signature: (II)Lscala/collection/IndexedSeqViewLike$Transformed;
  Code:
   Stack=3, Locals=3, Args_size=3
	aload_0
	iload_1
	iload_2
	invokestatic	Method scala/collection/views/IndexedSeqTransformations$class.newSliced:(Lscala/collection/IndexedSeqViewLike;II)Lscala/collection/IndexedSeqViewLike$Transformed;
	areturn
  Labels:
  LocalVariableTable: 
   Start  Length  Slot  Name   Signature
   0      7      0    this       Lscala/collection/views/IndexedSeqLike;
   0      7      1    _from       I
   0      7      2    _until       I

  Signature: length = 0x2
   00 3F 

public scala.collection.IndexedSeqViewLike$Transformed newFiltered(scala.Function1);
  Signature: (Lscala/Function1;)Lscala/collection/IndexedSeqViewLike$Transformed;
  Code:
   Stack=2, Locals=2, Args_size=2
	aload_0
	aload_1
	invokestatic	Method scala/collection/views/IndexedSeqTransformations$class.newFiltered:(Lscala/collection/IndexedSeqViewLike;Lscala/Function1;)Lscala/collection/IndexedSeqViewLike$Transformed;
	areturn
  Labels:
  LocalVariableTable: 
   Start  Length  Slot  Name   Signature
   0      6      0    this       Lscala/collection/views/IndexedSeqLike;
   0      6      1    p       Lscala/Function1;

  Signature: length = 0x2
   00 2F 

public scala.collection.IndexedSeqViewLike$Transformed newFlatMapped(scala.Function1);
  Signature: (Lscala/Function1;)Lscala/collection/IndexedSeqViewLike$Transformed;
  Code:
   Stack=2, Locals=2, Args_size=2
	aload_0
	aload_1
	invokestatic	Method scala/collection/views/IndexedSeqTransformations$class.newFlatMapped:(Lscala/collection/IndexedSeqViewLike;Lscala/Function1;)Lscala/collection/IndexedSeqViewLike$Transformed;
	areturn
  Labels:
  LocalVariableTable: 
   Start  Length  Slot  Name   Signature
   0      6      0    this       Lscala/collection/views/IndexedSeqLike;
   0      6      1    f       Lscala/Function1;

  Signature: length = 0x2
   00 2F 

public scala.collection.IndexedSeqViewLike$Transformed newMapped(scala.Function1);
  Signature: (Lscala/Function1;)Lscala/collection/IndexedSeqViewLike$Transformed;
  Code:
   Stack=2, Locals=2, Args_size=2
	aload_0
	aload_1
	invokestatic	Method scala/collection/views/IndexedSeqTransformations$class.newMapped:(Lscala/collection/IndexedSeqViewLike;Lscala/Function1;)Lscala/collection/IndexedSeqViewLike$Transformed;
	areturn
  Labels:
  LocalVariableTable: 
   Start  Length  Slot  Name   Signature
   0      6      0    this       Lscala/collection/views/IndexedSeqLike;
   0      6      1    f       Lscala/Function1;

  Signature: length = 0x2
   00 2F 

public scala.collection.IndexedSeqViewLike$Transformed newAppended(scala.collection.Traversable);
  Signature: (Lscala/collection/Traversable;)Lscala/collection/IndexedSeqViewLike$Transformed;
  Code:
   Stack=2, Locals=2, Args_size=2
	aload_0
	aload_1
	invokestatic	Method scala/collection/views/IndexedSeqTransformations$class.newAppended:(Lscala/collection/IndexedSeqViewLike;Lscala/collection/Traversable;)Lscala/collection/IndexedSeqViewLike$Transformed;
	areturn
  Labels:
  LocalVariableTable: 
   Start  Length  Slot  Name   Signature
   0      6      0    this       Lscala/collection/views/IndexedSeqLike;
   0      6      1    that       Lscala/collection/Traversable;

  Signature: length = 0x2
   00 23 

public java.lang.String stringPrefix();
  Signature: ()Ljava/lang/String;
  Code:
   Stack=1, Locals=1, Args_size=1
	aload_0
	invokestatic	Method scala/collection/IndexedSeqViewLike$class.stringPrefix:(Lscala/collection/IndexedSeqViewLike;)Ljava/lang/String;
	areturn
  Labels:

}

