Compiled from "Transformed.scala"
public final class scala.collection.views.IndexedSeqTransformations$$anon$9 extends scala.collection.views.IndexedSeqLike implements scala.collection.IndexedSeqViewLike$Patched
  SourceFile: "Transformed.scala"
  Signature: length = 0x2
   00 68 
  Scala: length = 0x
   
  InnerClass: 
   public abstract Patched=class scala/collection/SeqViewLike$Patched of class scala/collection/SeqViewLike
   public abstract Patched=class scala/collection/IndexedSeqViewLike$Patched of class scala/collection/IndexedSeqViewLike
   public abstract Transformed=class scala/collection/TraversableViewLike$Transformed of class scala/collection/TraversableViewLike
   public final $anon$9=class scala/collection/views/IndexedSeqTransformations$$anon$9 of class scala/collection/views/IndexedSeqTransformations
  minor version: 0
  major version: 49
  Constant pool:
Asciz	SourceFile;
Asciz	Transformed.scala;
Asciz	bitmap$0;
Asciz	I;
Asciz	underlying;
Asciz	Ljava/lang/Object;;
Asciz	scala$collection$SeqViewLike$Patched$$plen;
Asciz	$outer;
Asciz	Lscala/collection/IndexedSeqViewLike;;
Asciz	replaced;
Asciz	patch;
Asciz	Lscala/collection/Seq;;
Asciz	Lscala/collection/Seq<TB;>;;
Asciz	Signature;
Asciz	from;
Asciz	<init>;
Asciz	(Lscala/collection/IndexedSeqViewLike;ILscala/collection/Seq;I)V;
Asciz	Code;
Asciz	LineNumberTable;
Asciz	java/lang/NullPointerException;
class	java/lang/NullPointerException
Asciz	()V;
NameAndType	"<init>":()V
Method	java/lang/NullPointerException."<init>":()V
Asciz	scala/collection/views/IndexedSeqTransformations$$anon$9;
class	scala/collection/views/IndexedSeqTransformations$$anon$9
NameAndType	$outer:Lscala/collection/IndexedSeqViewLike;
Field	scala/collection/views/IndexedSeqTransformations$$anon$9.$outer:Lscala/collection/IndexedSeqViewLike;
Asciz	scala/collection/views/IndexedSeqLike;
class	scala/collection/views/IndexedSeqLike
Method	scala/collection/views/IndexedSeqLike."<init>":()V
Asciz	scala/collection/TraversableViewLike$Transformed$class;
class	scala/collection/TraversableViewLike$Transformed$class
Asciz	$init$;
Asciz	(Lscala/collection/TraversableViewLike$Transformed;)V;
NameAndType	$init$:(Lscala/collection/TraversableViewLike$Transformed;)V
Method	scala/collection/TraversableViewLike$Transformed$class.$init$:(Lscala/collection/TraversableViewLike$Transformed;)V
Asciz	scala/collection/SeqViewLike$Patched$class;
class	scala/collection/SeqViewLike$Patched$class
Asciz	(Lscala/collection/SeqViewLike$Patched;)V;
NameAndType	$init$:(Lscala/collection/SeqViewLike$Patched;)V
Method	scala/collection/SeqViewLike$Patched$class.$init$:(Lscala/collection/SeqViewLike$Patched;)V
NameAndType	from:I
Field	scala/collection/views/IndexedSeqTransformations$$anon$9.from:I
NameAndType	patch:Lscala/collection/Seq;
Field	scala/collection/views/IndexedSeqTransformations$$anon$9.patch:Lscala/collection/Seq;
NameAndType	replaced:I
Field	scala/collection/views/IndexedSeqTransformations$$anon$9.replaced:I
Asciz	this;
Asciz	Lscala/collection/views/IndexedSeqTransformations$$anon$9;;
Asciz	LocalVariableTable;
Asciz	(Lscala/collection/IndexedSeqViewLike<TA;TColl;TThis;>;)V;
Asciz	apply;
Asciz	(Ljava/lang/Object;)Ljava/lang/Object;;
Asciz	scala/runtime/BoxesRunTime;
class	scala/runtime/BoxesRunTime
Asciz	unboxToInt;
Asciz	(Ljava/lang/Object;)I;
NameAndType	unboxToInt:(Ljava/lang/Object;)I
Method	scala/runtime/BoxesRunTime.unboxToInt:(Ljava/lang/Object;)I
Asciz	scala/collection/SeqViewLike$Patched;
class	scala/collection/SeqViewLike$Patched
Asciz	(I)Ljava/lang/Object;;
NameAndType	apply:(I)Ljava/lang/Object;
InterfaceMethod	scala/collection/SeqViewLike$Patched.apply:(I)Ljava/lang/Object;
Asciz	v1;
Asciz	scala$collection$TraversableViewLike$Transformed$$$outer;
Asciz	()Lscala/collection/TraversableViewLike;;
Asciz	scala$collection$SeqViewLike$Patched$$$outer;
Asciz	()Lscala/collection/SeqViewLike;;
Asciz	()I;
Asciz	()Lscala/collection/Seq;;
Asciz	()Lscala/collection/Seq<TB;>;;
Asciz	()Ljava/lang/Object;;
NameAndType	bitmap$0:I
Field	scala/collection/views/IndexedSeqTransformations$$anon$9.bitmap$0:I
Asciz	(Lscala/collection/TraversableViewLike$Transformed;)Ljava/lang/Object;;
NameAndType	underlying:(Lscala/collection/TraversableViewLike$Transformed;)Ljava/lang/Object;
Method	scala/collection/TraversableViewLike$Transformed$class.underlying:(Lscala/collection/TraversableViewLike$Transformed;)Ljava/lang/Object;
NameAndType	underlying:Ljava/lang/Object;
Field	scala/collection/views/IndexedSeqTransformations$$anon$9.underlying:Ljava/lang/Object;
Asciz	stringPrefix;
Asciz	()Ljava/lang/String;;
Asciz	(Lscala/collection/SeqViewLike$Patched;)Ljava/lang/String;;
NameAndType	stringPrefix:(Lscala/collection/SeqViewLike$Patched;)Ljava/lang/String;
Method	scala/collection/SeqViewLike$Patched$class.stringPrefix:(Lscala/collection/SeqViewLike$Patched;)Ljava/lang/String;
Asciz	(Lscala/collection/SeqViewLike$Patched;I)Ljava/lang/Object;;
NameAndType	apply:(Lscala/collection/SeqViewLike$Patched;I)Ljava/lang/Object;
Method	scala/collection/SeqViewLike$Patched$class.apply:(Lscala/collection/SeqViewLike$Patched;I)Ljava/lang/Object;
Asciz	idx;
Asciz	length;
Asciz	(Lscala/collection/SeqViewLike$Patched;)I;
NameAndType	length:(Lscala/collection/SeqViewLike$Patched;)I
Method	scala/collection/SeqViewLike$Patched$class.length:(Lscala/collection/SeqViewLike$Patched;)I
Asciz	iterator;
Asciz	()Lscala/collection/Iterator;;
Asciz	(Lscala/collection/SeqViewLike$Patched;)Lscala/collection/Iterator;;
NameAndType	iterator:(Lscala/collection/SeqViewLike$Patched;)Lscala/collection/Iterator;
Method	scala/collection/SeqViewLike$Patched$class.iterator:(Lscala/collection/SeqViewLike$Patched;)Lscala/collection/Iterator;
NameAndType	scala$collection$SeqViewLike$Patched$$plen:(Lscala/collection/SeqViewLike$Patched;)I
Method	scala/collection/SeqViewLike$Patched$class.scala$collection$SeqViewLike$Patched$$plen:(Lscala/collection/SeqViewLike$Patched;)I
NameAndType	scala$collection$SeqViewLike$Patched$$plen:I
Field	scala/collection/views/IndexedSeqTransformations$$anon$9.scala$collection$SeqViewLike$Patched$$plen:I
Asciz	Lscala/collection/views/IndexedSeqLike<TB;TColl;>;Lscala/collection/IndexedSeqViewLike<TA;TColl;TThis;>.Patched<TB;>;;
Asciz	Scala;
Asciz	InnerClasses;
Asciz	scala/collection/SeqViewLike;
class	scala/collection/SeqViewLike
Asciz	Patched;
Asciz	scala/collection/IndexedSeqViewLike$Patched;
class	scala/collection/IndexedSeqViewLike$Patched
Asciz	scala/collection/IndexedSeqViewLike;
class	scala/collection/IndexedSeqViewLike
Asciz	scala/collection/TraversableViewLike$Transformed;
class	scala/collection/TraversableViewLike$Transformed
Asciz	scala/collection/TraversableViewLike;
class	scala/collection/TraversableViewLike
Asciz	Transformed;
Asciz	scala/collection/views/IndexedSeqTransformations;
class	scala/collection/views/IndexedSeqTransformations
Asciz	$anon$9;

{
public volatile int bitmap$0;
  Signature: I

private final java.lang.Object underlying;
  Signature: Ljava/lang/Object;

private final int scala$collection$SeqViewLike$Patched$$plen;
  Signature: I

private final scala.collection.IndexedSeqViewLike $outer;
  Signature: Lscala/collection/IndexedSeqViewLike;

private final int replaced;
  Signature: I

private final scala.collection.Seq patch;
  Signature: Lscala/collection/Seq;
  Signature: length = 0x2
   00 0D 

private final int from;
  Signature: I

public scala.collection.views.IndexedSeqTransformations$$anon$9(scala.collection.IndexedSeqViewLike, int, scala.collection.Seq, int);
  Signature: (Lscala/collection/IndexedSeqViewLike;ILscala/collection/Seq;I)V
  Code:
   Stack=2, Locals=5, Args_size=5
	aload_1
	ifnonnull	l1 // aload_0
	new	class java/lang/NullPointerException
	dup
	invokespecial	Method java/lang/NullPointerException."<init>":()V
	athrow
l1	aload_0
	aload_1
	putfield	Field $outer:Lscala/collection/IndexedSeqViewLike;
	aload_0
	invokespecial	Method scala/collection/views/IndexedSeqLike."<init>":()V
	aload_0
	invokestatic	Method scala/collection/TraversableViewLike$Transformed$class.$init$:(Lscala/collection/TraversableViewLike$Transformed;)V
	aload_0
	invokestatic	Method scala/collection/SeqViewLike$Patched$class.$init$:(Lscala/collection/SeqViewLike$Patched;)V
	aload_0
	iload_2
	putfield	Field from:I
	aload_0
	aload_3
	putfield	Field patch:Lscala/collection/Seq;
	aload_0
	iload	4
	putfield	Field replaced:I
	return
  Labels:
   	l1 = 12 // aload_0
  LocalVariableTable: 
   Start  Length  Slot  Name   Signature
   0      46      0    this       Lscala/collection/views/IndexedSeqTransformations$$anon$9;
   0      46      1    $outer       Lscala/collection/IndexedSeqViewLike;

  Signature: length = 0x2
   00 34 

public java.lang.Object apply(java.lang.Object);
  Signature: (Ljava/lang/Object;)Ljava/lang/Object;
  Code:
   Stack=2, Locals=2, Args_size=2
	aload_0
	aload_1
	invokestatic	Method scala/runtime/BoxesRunTime.unboxToInt:(Ljava/lang/Object;)I
	invokeinterface	InterfaceMethod scala/collection/SeqViewLike$Patched.apply:(I)Ljava/lang/Object;
	areturn
  Labels:
  LocalVariableTable: 
   Start  Length  Slot  Name   Signature
   0      11      0    this       Lscala/collection/views/IndexedSeqTransformations$$anon$9;
   0      11      1    v1       Ljava/lang/Object;


public scala.collection.TraversableViewLike scala$collection$TraversableViewLike$Transformed$$$outer();
  Signature: ()Lscala/collection/TraversableViewLike;
  Code:
   Stack=1, Locals=1, Args_size=1
	aload_0
	getfield	Field $outer:Lscala/collection/IndexedSeqViewLike;
	areturn
  Labels:

public scala.collection.SeqViewLike scala$collection$SeqViewLike$Patched$$$outer();
  Signature: ()Lscala/collection/SeqViewLike;
  Code:
   Stack=1, Locals=1, Args_size=1
	aload_0
	getfield	Field $outer:Lscala/collection/IndexedSeqViewLike;
	areturn
  Labels:

public int replaced();
  Signature: ()I
  Code:
   Stack=1, Locals=1, Args_size=1
	aload_0
	getfield	Field replaced:I
	ireturn
  Labels:

public scala.collection.Seq patch();
  Signature: ()Lscala/collection/Seq;
  Code:
   Stack=1, Locals=1, Args_size=1
	aload_0
	getfield	Field patch:Lscala/collection/Seq;
	areturn
  Labels:
  Signature: length = 0x2
   00 49 

public int from();
  Signature: ()I
  Code:
   Stack=1, Locals=1, Args_size=1
	aload_0
	getfield	Field from:I
	ireturn
  Labels:

public java.lang.Object underlying();
  Signature: ()Ljava/lang/Object;
  Code:
   Stack=3, Locals=1, Args_size=1
	aload_0
	getfield	Field bitmap$0:I
	iconst_4
	iand
	iconst_0
	if_icmpne	l1 // aload_0
	aload_0
	dup
	pop
	monitorenter
	aload_0
	getfield	Field bitmap$0:I
	iconst_4
	iand
	iconst_0
	if_icmpne	l2 // aload_0
	aload_0
	aload_0
	invokestatic	Method scala/collection/TraversableViewLike$Transformed$class.underlying:(Lscala/collection/TraversableViewLike$Transformed;)Ljava/lang/Object;
	putfield	Field underlying:Ljava/lang/Object;
	aload_0
	aload_0
	getfield	Field bitmap$0:I
	iconst_4
	ior
	putfield	Field bitmap$0:I
l2	aload_0
	monitorexit
l1	aload_0
	getfield	Field underlying:Ljava/lang/Object;
	areturn
	aload_0
	monitorexit
	athrow
  Labels:
   	l2 = 42 // aload_0
   	l1 = 44 // aload_0
  Exception table:
   from   to  target type
    14    44    49   any

public java.lang.String stringPrefix();
  Signature: ()Ljava/lang/String;
  Code:
   Stack=1, Locals=1, Args_size=1
	aload_0
	invokestatic	Method scala/collection/SeqViewLike$Patched$class.stringPrefix:(Lscala/collection/SeqViewLike$Patched;)Ljava/lang/String;
	areturn
  Labels:

public java.lang.Object apply(int);
  Signature: (I)Ljava/lang/Object;
  Code:
   Stack=2, Locals=2, Args_size=2
	aload_0
	iload_1
	invokestatic	Method scala/collection/SeqViewLike$Patched$class.apply:(Lscala/collection/SeqViewLike$Patched;I)Ljava/lang/Object;
	areturn
  Labels:
  LocalVariableTable: 
   Start  Length  Slot  Name   Signature
   0      6      0    this       Lscala/collection/views/IndexedSeqTransformations$$anon$9;
   0      6      1    idx       I


public int length();
  Signature: ()I
  Code:
   Stack=1, Locals=1, Args_size=1
	aload_0
	invokestatic	Method scala/collection/SeqViewLike$Patched$class.length:(Lscala/collection/SeqViewLike$Patched;)I
	ireturn
  Labels:

public scala.collection.Iterator iterator();
  Signature: ()Lscala/collection/Iterator;
  Code:
   Stack=1, Locals=1, Args_size=1
	aload_0
	invokestatic	Method scala/collection/SeqViewLike$Patched$class.iterator:(Lscala/collection/SeqViewLike$Patched;)Lscala/collection/Iterator;
	areturn
  Labels:

public final int scala$collection$SeqViewLike$Patched$$plen();
  Signature: ()I
  Code:
   Stack=3, Locals=1, Args_size=1
	aload_0
	getfield	Field bitmap$0:I
	iconst_1
	iand
	iconst_0
	if_icmpne	l1 // aload_0
	aload_0
	dup
	pop
	monitorenter
	aload_0
	getfield	Field bitmap$0:I
	iconst_1
	iand
	iconst_0
	if_icmpne	l2 // aload_0
	aload_0
	aload_0
	invokestatic	Method scala/collection/SeqViewLike$Patched$class.scala$collection$SeqViewLike$Patched$$plen:(Lscala/collection/SeqViewLike$Patched;)I
	putfield	Field scala$collection$SeqViewLike$Patched$$plen:I
	aload_0
	aload_0
	getfield	Field bitmap$0:I
	iconst_1
	ior
	putfield	Field bitmap$0:I
l2	aload_0
	monitorexit
l1	aload_0
	getfield	Field scala$collection$SeqViewLike$Patched$$plen:I
	ireturn
	aload_0
	monitorexit
	athrow
  Labels:
   	l2 = 42 // aload_0
   	l1 = 44 // aload_0
  Exception table:
   from   to  target type
    14    44    49   any

}

