Compiled from "Transformed.scala"
public abstract class scala.collection.views.IterableTransformations$class extends java.lang.Object
  SourceFile: "Transformed.scala"
  Scala: length = 0x
   
  InnerClass: 
   public abstract Transformed=class scala/collection/IterableViewLike$Transformed of class scala/collection/IterableViewLike
   public final $anon$23=class scala/collection/views/IterableTransformations$$anon$23 of class scala/collection/views/IterableTransformations
   public final $anon$24=class scala/collection/views/IterableTransformations$$anon$24 of class scala/collection/views/IterableTransformations
   public final $anon$25=class scala/collection/views/IterableTransformations$$anon$25 of class scala/collection/views/IterableTransformations
   public final $anon$26=class scala/collection/views/IterableTransformations$$anon$26 of class scala/collection/views/IterableTransformations
   public final $anon$27=class scala/collection/views/IterableTransformations$$anon$27 of class scala/collection/views/IterableTransformations
   public final $anon$28=class scala/collection/views/IterableTransformations$$anon$28 of class scala/collection/views/IterableTransformations
   public final $anon$29=class scala/collection/views/IterableTransformations$$anon$29 of class scala/collection/views/IterableTransformations
   public final $anon$30=class scala/collection/views/IterableTransformations$$anon$30 of class scala/collection/views/IterableTransformations
   public final $anon$31=class scala/collection/views/IterableTransformations$$anon$31 of class scala/collection/views/IterableTransformations
  minor version: 0
  major version: 49
  Constant pool:
Asciz	SourceFile;
Asciz	Transformed.scala;
Asciz	$init$;
Asciz	(Lscala/collection/IterableViewLike;)V;
Asciz	Code;
Asciz	LineNumberTable;
Asciz	$this;
Asciz	Lscala/collection/IterableViewLike;;
Asciz	LocalVariableTable;
Asciz	newZippedAll;
Asciz	(Lscala/collection/IterableViewLike;Lscala/collection/Iterable;Ljava/lang/Object;Ljava/lang/Object;)Lscala/collection/IterableViewLike$Transformed;;
Asciz	scala/collection/views/IterableTransformations$$anon$31;
class	scala/collection/views/IterableTransformations$$anon$31
Asciz	<init>;
Asciz	(Lscala/collection/IterableViewLike;Lscala/collection/Iterable;Ljava/lang/Object;Ljava/lang/Object;)V;
NameAndType	"<init>":(Lscala/collection/IterableViewLike;Lscala/collection/Iterable;Ljava/lang/Object;Ljava/lang/Object;)V
Method	scala/collection/views/IterableTransformations$$anon$31."<init>":(Lscala/collection/IterableViewLike;Lscala/collection/Iterable;Ljava/lang/Object;Ljava/lang/Object;)V
Asciz	that$4;
Asciz	Lscala/collection/Iterable;;
Asciz	_thisElem$2;
Asciz	Ljava/lang/Object;;
Asciz	_thatElem$2;
Asciz	newZipped;
Asciz	(Lscala/collection/IterableViewLike;Lscala/collection/Iterable;)Lscala/collection/IterableViewLike$Transformed;;
Asciz	scala/collection/views/IterableTransformations$$anon$30;
class	scala/collection/views/IterableTransformations$$anon$30
Asciz	(Lscala/collection/IterableViewLike;Lscala/collection/Iterable;)V;
NameAndType	"<init>":(Lscala/collection/IterableViewLike;Lscala/collection/Iterable;)V
Method	scala/collection/views/IterableTransformations$$anon$30."<init>":(Lscala/collection/IterableViewLike;Lscala/collection/Iterable;)V
Asciz	that$6;
Asciz	newTakenWhile;
Asciz	(Lscala/collection/IterableViewLike;Lscala/Function1;)Lscala/collection/IterableViewLike$Transformed;;
Asciz	scala/collection/views/IterableTransformations$$anon$29;
class	scala/collection/views/IterableTransformations$$anon$29
Asciz	(Lscala/collection/IterableViewLike;Lscala/Function1;)V;
NameAndType	"<init>":(Lscala/collection/IterableViewLike;Lscala/Function1;)V
Method	scala/collection/views/IterableTransformations$$anon$29."<init>":(Lscala/collection/IterableViewLike;Lscala/Function1;)V
Asciz	p$1;
Asciz	Lscala/Function1;;
Asciz	newDroppedWhile;
Asciz	scala/collection/views/IterableTransformations$$anon$28;
class	scala/collection/views/IterableTransformations$$anon$28
Method	scala/collection/views/IterableTransformations$$anon$28."<init>":(Lscala/collection/IterableViewLike;Lscala/Function1;)V
Asciz	p$3;
Asciz	newSliced;
Asciz	(Lscala/collection/IterableViewLike;II)Lscala/collection/IterableViewLike$Transformed;;
Asciz	scala/collection/views/IterableTransformations$$anon$27;
class	scala/collection/views/IterableTransformations$$anon$27
Asciz	(Lscala/collection/IterableViewLike;II)V;
NameAndType	"<init>":(Lscala/collection/IterableViewLike;II)V
Method	scala/collection/views/IterableTransformations$$anon$27."<init>":(Lscala/collection/IterableViewLike;II)V
Asciz	_from$1;
Asciz	I;
Asciz	_until$1;
Asciz	newFiltered;
Asciz	scala/collection/views/IterableTransformations$$anon$26;
class	scala/collection/views/IterableTransformations$$anon$26
Method	scala/collection/views/IterableTransformations$$anon$26."<init>":(Lscala/collection/IterableViewLike;Lscala/Function1;)V
Asciz	p$5;
Asciz	newFlatMapped;
Asciz	scala/collection/views/IterableTransformations$$anon$25;
class	scala/collection/views/IterableTransformations$$anon$25
Method	scala/collection/views/IterableTransformations$$anon$25."<init>":(Lscala/collection/IterableViewLike;Lscala/Function1;)V
Asciz	f$1;
Asciz	newMapped;
Asciz	scala/collection/views/IterableTransformations$$anon$24;
class	scala/collection/views/IterableTransformations$$anon$24
Method	scala/collection/views/IterableTransformations$$anon$24."<init>":(Lscala/collection/IterableViewLike;Lscala/Function1;)V
Asciz	f$3;
Asciz	newAppended;
Asciz	(Lscala/collection/IterableViewLike;Lscala/collection/Traversable;)Lscala/collection/IterableViewLike$Transformed;;
Asciz	scala/collection/views/IterableTransformations$$anon$23;
class	scala/collection/views/IterableTransformations$$anon$23
Asciz	(Lscala/collection/IterableViewLike;Lscala/collection/Traversable;)V;
NameAndType	"<init>":(Lscala/collection/IterableViewLike;Lscala/collection/Traversable;)V
Method	scala/collection/views/IterableTransformations$$anon$23."<init>":(Lscala/collection/IterableViewLike;Lscala/collection/Traversable;)V
Asciz	that$1;
Asciz	Lscala/collection/Traversable;;
Asciz	Scala;
Asciz	InnerClasses;
Asciz	scala/collection/IterableViewLike$Transformed;
class	scala/collection/IterableViewLike$Transformed
Asciz	scala/collection/IterableViewLike;
class	scala/collection/IterableViewLike
Asciz	Transformed;
Asciz	scala/collection/views/IterableTransformations;
class	scala/collection/views/IterableTransformations
Asciz	$anon$23;
Asciz	$anon$24;
Asciz	$anon$25;
Asciz	$anon$26;
Asciz	$anon$27;
Asciz	$anon$28;
Asciz	$anon$29;
Asciz	$anon$30;
Asciz	$anon$31;
Asciz	scala/collection/views/IterableTransformations$class;
class	scala/collection/views/IterableTransformations$class
Asciz	java/lang/Object;
class	java/lang/Object

{
public static void $init$(scala.collection.IterableViewLike);
  Signature: (Lscala/collection/IterableViewLike;)V
  Code:
   Stack=0, Locals=1, Args_size=1
	return
  Labels:
  LocalVariableTable: 
   Start  Length  Slot  Name   Signature
   0      1      0    $this       Lscala/collection/IterableViewLike;


public static scala.collection.IterableViewLike$Transformed newZippedAll(scala.collection.IterableViewLike, scala.collection.Iterable, java.lang.Object, java.lang.Object);
  Signature: (Lscala/collection/IterableViewLike;Lscala/collection/Iterable;Ljava/lang/Object;Ljava/lang/Object;)Lscala/collection/IterableViewLike$Transformed;
  Code:
   Stack=6, Locals=4, Args_size=4
	new	class scala/collection/views/IterableTransformations$$anon$31
	dup
	aload_0
	aload_1
	aload_2
	aload_3
	invokespecial	Method scala/collection/views/IterableTransformations$$anon$31."<init>":(Lscala/collection/IterableViewLike;Lscala/collection/Iterable;Ljava/lang/Object;Ljava/lang/Object;)V
	areturn
  Labels:
  LocalVariableTable: 
   Start  Length  Slot  Name   Signature
   0      12      0    $this       Lscala/collection/IterableViewLike;
   0      12      1    that$4       Lscala/collection/Iterable;
   0      12      2    _thisElem$2       Ljava/lang/Object;
   0      12      3    _thatElem$2       Ljava/lang/Object;


public static scala.collection.IterableViewLike$Transformed newZipped(scala.collection.IterableViewLike, scala.collection.Iterable);
  Signature: (Lscala/collection/IterableViewLike;Lscala/collection/Iterable;)Lscala/collection/IterableViewLike$Transformed;
  Code:
   Stack=4, Locals=2, Args_size=2
	new	class scala/collection/views/IterableTransformations$$anon$30
	dup
	aload_0
	aload_1
	invokespecial	Method scala/collection/views/IterableTransformations$$anon$30."<init>":(Lscala/collection/IterableViewLike;Lscala/collection/Iterable;)V
	areturn
  Labels:
  LocalVariableTable: 
   Start  Length  Slot  Name   Signature
   0      10      0    $this       Lscala/collection/IterableViewLike;
   0      10      1    that$6       Lscala/collection/Iterable;


public static scala.collection.IterableViewLike$Transformed newTakenWhile(scala.collection.IterableViewLike, scala.Function1);
  Signature: (Lscala/collection/IterableViewLike;Lscala/Function1;)Lscala/collection/IterableViewLike$Transformed;
  Code:
   Stack=4, Locals=2, Args_size=2
	new	class scala/collection/views/IterableTransformations$$anon$29
	dup
	aload_0
	aload_1
	invokespecial	Method scala/collection/views/IterableTransformations$$anon$29."<init>":(Lscala/collection/IterableViewLike;Lscala/Function1;)V
	areturn
  Labels:
  LocalVariableTable: 
   Start  Length  Slot  Name   Signature
   0      10      0    $this       Lscala/collection/IterableViewLike;
   0      10      1    p$1       Lscala/Function1;


public static scala.collection.IterableViewLike$Transformed newDroppedWhile(scala.collection.IterableViewLike, scala.Function1);
  Signature: (Lscala/collection/IterableViewLike;Lscala/Function1;)Lscala/collection/IterableViewLike$Transformed;
  Code:
   Stack=4, Locals=2, Args_size=2
	new	class scala/collection/views/IterableTransformations$$anon$28
	dup
	aload_0
	aload_1
	invokespecial	Method scala/collection/views/IterableTransformations$$anon$28."<init>":(Lscala/collection/IterableViewLike;Lscala/Function1;)V
	areturn
  Labels:
  LocalVariableTable: 
   Start  Length  Slot  Name   Signature
   0      10      0    $this       Lscala/collection/IterableViewLike;
   0      10      1    p$3       Lscala/Function1;


public static scala.collection.IterableViewLike$Transformed newSliced(scala.collection.IterableViewLike, int, int);
  Signature: (Lscala/collection/IterableViewLike;II)Lscala/collection/IterableViewLike$Transformed;
  Code:
   Stack=5, Locals=3, Args_size=3
	new	class scala/collection/views/IterableTransformations$$anon$27
	dup
	aload_0
	iload_1
	iload_2
	invokespecial	Method scala/collection/views/IterableTransformations$$anon$27."<init>":(Lscala/collection/IterableViewLike;II)V
	areturn
  Labels:
  LocalVariableTable: 
   Start  Length  Slot  Name   Signature
   0      11      0    $this       Lscala/collection/IterableViewLike;
   0      11      1    _from$1       I
   0      11      2    _until$1       I


public static scala.collection.IterableViewLike$Transformed newFiltered(scala.collection.IterableViewLike, scala.Function1);
  Signature: (Lscala/collection/IterableViewLike;Lscala/Function1;)Lscala/collection/IterableViewLike$Transformed;
  Code:
   Stack=4, Locals=2, Args_size=2
	new	class scala/collection/views/IterableTransformations$$anon$26
	dup
	aload_0
	aload_1
	invokespecial	Method scala/collection/views/IterableTransformations$$anon$26."<init>":(Lscala/collection/IterableViewLike;Lscala/Function1;)V
	areturn
  Labels:
  LocalVariableTable: 
   Start  Length  Slot  Name   Signature
   0      10      0    $this       Lscala/collection/IterableViewLike;
   0      10      1    p$5       Lscala/Function1;


public static scala.collection.IterableViewLike$Transformed newFlatMapped(scala.collection.IterableViewLike, scala.Function1);
  Signature: (Lscala/collection/IterableViewLike;Lscala/Function1;)Lscala/collection/IterableViewLike$Transformed;
  Code:
   Stack=4, Locals=2, Args_size=2
	new	class scala/collection/views/IterableTransformations$$anon$25
	dup
	aload_0
	aload_1
	invokespecial	Method scala/collection/views/IterableTransformations$$anon$25."<init>":(Lscala/collection/IterableViewLike;Lscala/Function1;)V
	areturn
  Labels:
  LocalVariableTable: 
   Start  Length  Slot  Name   Signature
   0      10      0    $this       Lscala/collection/IterableViewLike;
   0      10      1    f$1       Lscala/Function1;


public static scala.collection.IterableViewLike$Transformed newMapped(scala.collection.IterableViewLike, scala.Function1);
  Signature: (Lscala/collection/IterableViewLike;Lscala/Function1;)Lscala/collection/IterableViewLike$Transformed;
  Code:
   Stack=4, Locals=2, Args_size=2
	new	class scala/collection/views/IterableTransformations$$anon$24
	dup
	aload_0
	aload_1
	invokespecial	Method scala/collection/views/IterableTransformations$$anon$24."<init>":(Lscala/collection/IterableViewLike;Lscala/Function1;)V
	areturn
  Labels:
  LocalVariableTable: 
   Start  Length  Slot  Name   Signature
   0      10      0    $this       Lscala/collection/IterableViewLike;
   0      10      1    f$3       Lscala/Function1;


public static scala.collection.IterableViewLike$Transformed newAppended(scala.collection.IterableViewLike, scala.collection.Traversable);
  Signature: (Lscala/collection/IterableViewLike;Lscala/collection/Traversable;)Lscala/collection/IterableViewLike$Transformed;
  Code:
   Stack=4, Locals=2, Args_size=2
	new	class scala/collection/views/IterableTransformations$$anon$23
	dup
	aload_0
	aload_1
	invokespecial	Method scala/collection/views/IterableTransformations$$anon$23."<init>":(Lscala/collection/IterableViewLike;Lscala/collection/Traversable;)V
	areturn
  Labels:
  LocalVariableTable: 
   Start  Length  Slot  Name   Signature
   0      10      0    $this       Lscala/collection/IterableViewLike;
   0      10      1    that$1       Lscala/collection/Traversable;


}

