Compiled from "Transformed.scala"
public abstract class scala.collection.views.IterableLike extends scala.collection.views.TraversableLike implements scala.collection.IterableView,scala.ScalaObject
  SourceFile: "Transformed.scala"
  Signature: length = 0x2
   01 2B 
  ScalaSig: length = 0x124
   05 00 2F 06 06 01 02 FFFFFF81 00 04 08 02 0C 49 74 65
   72 61 62 6C 65 4C 69 6B 65 0A 02 03 04 01 05 76
   69 65 77 73 0A 02 05 06 01 0A 63 6F 6C 6C 65 63
   74 69 6F 6E 0A 01 07 01 05 73 63 61 6C 61 15 03
   09 10 1C 13 04 00 0A 1E 22 10 04 0B 0C 0E 1B 0D
   01 02 09 02 0D 02 02 0F 54 72 61 76 65 72 73 61
   62 6C 65 4C 69 6B 65 10 02 0F 10 0C 00 04 08 11
   00 FFFFFF84 FFFFFF80 FFFFFF84 FFFFFFC2 00 13 02 01 42 03 00 11 02 14 18
   10 02 15 16 0D 01 06 09 02 17 06 02 07 4E 6F 74
   68 69 6E 67 10 02 15 19 09 02 1A 06 02 03 41 6E
   79 10 02 0F 1C 04 08 1D 00 FFFFFF84 FFFFFF80 FFFFFF84 FFFFFFC2 00 13 02
   04 43 6F 6C 6C 10 04 1F 20 0E 1B 0D 01 04 09 02
   21 04 02 0C 49 74 65 72 61 62 6C 65 56 69 65 77
   10 02 15 23 09 02 24 06 02 0B 53 63 61 6C 61 4F
   62 6A 65 63 74 08 05 26 00 FFFFFF84 00 27 01 06 3C 69
   6E 69 74 3E 14 01 28 10 04 0B 00 0E 1B 08 05 2A
   00 FFFFFF86 20 2B 01 08 69 74 65 72 61 74 6F 72 15 01
   2C 10 03 1F 2D 0E 09 02 2E 04 02 08 49 74 65 72
   61 74 6F 72 
  InnerClass: 
   public abstract Transformed=class scala/collection/IterableViewLike$Transformed of class scala/collection/IterableViewLike
   public abstract Transformed=class scala/collection/TraversableViewLike$Transformed of class scala/collection/TraversableViewLike
  minor version: 0
  major version: 49
  Constant pool:
Asciz	SourceFile;
Asciz	Transformed.scala;
Asciz	<init>;
Asciz	()V;
Asciz	Code;
Asciz	LineNumberTable;
Asciz	scala/collection/views/TraversableLike;
class	scala/collection/views/TraversableLike
NameAndType	"<init>":()V
Method	scala/collection/views/TraversableLike."<init>":()V
Asciz	scala/collection/IterableLike$class;
class	scala/collection/IterableLike$class
Asciz	$init$;
Asciz	(Lscala/collection/IterableLike;)V;
NameAndType	$init$:(Lscala/collection/IterableLike;)V
Method	scala/collection/IterableLike$class.$init$:(Lscala/collection/IterableLike;)V
Asciz	scala/collection/Iterable$class;
class	scala/collection/Iterable$class
Asciz	(Lscala/collection/Iterable;)V;
NameAndType	$init$:(Lscala/collection/Iterable;)V
Method	scala/collection/Iterable$class.$init$:(Lscala/collection/Iterable;)V
Asciz	scala/collection/views/IterableTransformations$class;
class	scala/collection/views/IterableTransformations$class
Asciz	(Lscala/collection/IterableViewLike;)V;
NameAndType	$init$:(Lscala/collection/IterableViewLike;)V
Method	scala/collection/views/IterableTransformations$class.$init$:(Lscala/collection/IterableViewLike;)V
Asciz	scala/collection/IterableViewLike$class;
class	scala/collection/IterableViewLike$class
Method	scala/collection/IterableViewLike$class.$init$:(Lscala/collection/IterableViewLike;)V
Asciz	Signature;
Asciz	newAppended;
Asciz	(Lscala/collection/Traversable;)Lscala/collection/TraversableViewLike$Transformed;;
Asciz	scala/collection/views/IterableTransformations;
class	scala/collection/views/IterableTransformations
Asciz	(Lscala/collection/Traversable;)Lscala/collection/IterableViewLike$Transformed;;
NameAndType	newAppended:(Lscala/collection/Traversable;)Lscala/collection/IterableViewLike$Transformed;
InterfaceMethod	scala/collection/views/IterableTransformations.newAppended:(Lscala/collection/Traversable;)Lscala/collection/IterableViewLike$Transformed;
Asciz	this;
Asciz	Lscala/collection/views/IterableLike;;
Asciz	that;
Asciz	Lscala/collection/Traversable;;
Asciz	LocalVariableTable;
Asciz	newMapped;
Asciz	(Lscala/Function1;)Lscala/collection/TraversableViewLike$Transformed;;
Asciz	(Lscala/Function1;)Lscala/collection/IterableViewLike$Transformed;;
NameAndType	newMapped:(Lscala/Function1;)Lscala/collection/IterableViewLike$Transformed;
InterfaceMethod	scala/collection/views/IterableTransformations.newMapped:(Lscala/Function1;)Lscala/collection/IterableViewLike$Transformed;
Asciz	f;
Asciz	Lscala/Function1;;
Asciz	newFlatMapped;
NameAndType	newFlatMapped:(Lscala/Function1;)Lscala/collection/IterableViewLike$Transformed;
InterfaceMethod	scala/collection/views/IterableTransformations.newFlatMapped:(Lscala/Function1;)Lscala/collection/IterableViewLike$Transformed;
Asciz	newFiltered;
NameAndType	newFiltered:(Lscala/Function1;)Lscala/collection/IterableViewLike$Transformed;
InterfaceMethod	scala/collection/views/IterableTransformations.newFiltered:(Lscala/Function1;)Lscala/collection/IterableViewLike$Transformed;
Asciz	p;
Asciz	newSliced;
Asciz	(II)Lscala/collection/TraversableViewLike$Transformed;;
Asciz	(II)Lscala/collection/IterableViewLike$Transformed;;
NameAndType	newSliced:(II)Lscala/collection/IterableViewLike$Transformed;
InterfaceMethod	scala/collection/views/IterableTransformations.newSliced:(II)Lscala/collection/IterableViewLike$Transformed;
Asciz	_from;
Asciz	I;
Asciz	_until;
Asciz	newDroppedWhile;
NameAndType	newDroppedWhile:(Lscala/Function1;)Lscala/collection/IterableViewLike$Transformed;
InterfaceMethod	scala/collection/views/IterableTransformations.newDroppedWhile:(Lscala/Function1;)Lscala/collection/IterableViewLike$Transformed;
Asciz	newTakenWhile;
NameAndType	newTakenWhile:(Lscala/Function1;)Lscala/collection/IterableViewLike$Transformed;
InterfaceMethod	scala/collection/views/IterableTransformations.newTakenWhile:(Lscala/Function1;)Lscala/collection/IterableViewLike$Transformed;
Asciz	thisCollection;
Asciz	()Lscala/collection/Traversable;;
Asciz	scala/collection/IterableLike;
class	scala/collection/IterableLike
Asciz	()Lscala/collection/Iterable;;
NameAndType	thisCollection:()Lscala/collection/Iterable;
InterfaceMethod	scala/collection/IterableLike.thisCollection:()Lscala/collection/Iterable;
Asciz	toCollection;
Asciz	(Ljava/lang/Object;)Lscala/collection/Traversable;;
Asciz	(Ljava/lang/Object;)Lscala/collection/Iterable;;
NameAndType	toCollection:(Ljava/lang/Object;)Lscala/collection/Iterable;
InterfaceMethod	scala/collection/IterableLike.toCollection:(Ljava/lang/Object;)Lscala/collection/Iterable;
Asciz	repr;
Asciz	Ljava/lang/Object;;
Asciz	take;
Asciz	(I)Lscala/collection/TraversableView;;
Asciz	(I)Ljava/lang/Object;;
NameAndType	take:(I)Ljava/lang/Object;
InterfaceMethod	scala/collection/IterableLike.take:(I)Ljava/lang/Object;
Asciz	scala/collection/TraversableView;
class	scala/collection/TraversableView
Asciz	n;
Asciz	slice;
Asciz	(II)Lscala/collection/TraversableView;;
Asciz	(II)Ljava/lang/Object;;
NameAndType	slice:(II)Ljava/lang/Object;
InterfaceMethod	scala/collection/IterableLike.slice:(II)Ljava/lang/Object;
Asciz	from;
Asciz	until;
Asciz	takeWhile;
Asciz	(Lscala/Function1;)Lscala/collection/TraversableView;;
Asciz	(Lscala/Function1;)Ljava/lang/Object;;
NameAndType	takeWhile:(Lscala/Function1;)Ljava/lang/Object;
InterfaceMethod	scala/collection/IterableLike.takeWhile:(Lscala/Function1;)Ljava/lang/Object;
Asciz	view;
Asciz	()Lscala/collection/TraversableView;;
Asciz	()Lscala/collection/IterableView;;
NameAndType	view:()Lscala/collection/IterableView;
InterfaceMethod	scala/collection/IterableLike.view:()Lscala/collection/IterableView;
Asciz	(II)Lscala/collection/IterableView;;
NameAndType	view:(II)Lscala/collection/IterableView;
InterfaceMethod	scala/collection/IterableLike.view:(II)Lscala/collection/IterableView;
Asciz	filter;
Asciz	scala/collection/TraversableViewLike;
class	scala/collection/TraversableViewLike
NameAndType	filter:(Lscala/Function1;)Lscala/collection/TraversableView;
InterfaceMethod	scala/collection/TraversableViewLike.filter:(Lscala/Function1;)Lscala/collection/TraversableView;
Asciz	init;
Asciz	()Ljava/lang/Object;;
NameAndType	init:()Lscala/collection/TraversableView;
InterfaceMethod	scala/collection/TraversableViewLike.init:()Lscala/collection/TraversableView;
Asciz	drop;
NameAndType	drop:(I)Lscala/collection/TraversableView;
InterfaceMethod	scala/collection/TraversableViewLike.drop:(I)Lscala/collection/TraversableView;
Asciz	dropWhile;
NameAndType	dropWhile:(Lscala/Function1;)Lscala/collection/TraversableView;
InterfaceMethod	scala/collection/TraversableViewLike.dropWhile:(Lscala/Function1;)Lscala/collection/TraversableView;
Asciz	iterator;
Asciz	()Lscala/collection/Iterator;;
Asciz	()Lscala/collection/Iterator<TB;>;;
Asciz	projection;
Asciz	(Lscala/collection/IterableLike;)Lscala/collection/IterableView;;
NameAndType	projection:(Lscala/collection/IterableLike;)Lscala/collection/IterableView;
Method	scala/collection/IterableLike$class.projection:(Lscala/collection/IterableLike;)Lscala/collection/IterableView;
Asciz	Deprecated;
Asciz	firstOption;
Asciz	()Lscala/Option;;
Asciz	(Lscala/collection/IterableLike;)Lscala/Option;;
NameAndType	firstOption:(Lscala/collection/IterableLike;)Lscala/Option;
Method	scala/collection/IterableLike$class.firstOption:(Lscala/collection/IterableLike;)Lscala/Option;
Asciz	first;
Asciz	(Lscala/collection/IterableLike;)Ljava/lang/Object;;
NameAndType	first:(Lscala/collection/IterableLike;)Ljava/lang/Object;
Method	scala/collection/IterableLike$class.first:(Lscala/collection/IterableLike;)Ljava/lang/Object;
Asciz	(Lscala/collection/IterableLike;II)Lscala/collection/IterableView;;
NameAndType	view:(Lscala/collection/IterableLike;II)Lscala/collection/IterableView;
Method	scala/collection/IterableLike$class.view:(Lscala/collection/IterableLike;II)Lscala/collection/IterableView;
NameAndType	view:(Lscala/collection/IterableLike;)Lscala/collection/IterableView;
Method	scala/collection/IterableLike$class.view:(Lscala/collection/IterableLike;)Lscala/collection/IterableView;
Asciz	canEqual;
Asciz	(Ljava/lang/Object;)Z;
Asciz	(Lscala/collection/IterableLike;Ljava/lang/Object;)Z;
NameAndType	canEqual:(Lscala/collection/IterableLike;Ljava/lang/Object;)Z
Method	scala/collection/IterableLike$class.canEqual:(Lscala/collection/IterableLike;Ljava/lang/Object;)Z
Asciz	toStream;
Asciz	()Lscala/collection/immutable/Stream;;
Asciz	(Lscala/collection/IterableLike;)Lscala/collection/immutable/Stream;;
NameAndType	toStream:(Lscala/collection/IterableLike;)Lscala/collection/immutable/Stream;
Method	scala/collection/IterableLike$class.toStream:(Lscala/collection/IterableLike;)Lscala/collection/immutable/Stream;
Asciz	sameElements;
Asciz	(Lscala/collection/Iterable;)Z;
Asciz	(Lscala/collection/IterableLike;Lscala/collection/Iterable;)Z;
NameAndType	sameElements:(Lscala/collection/IterableLike;Lscala/collection/Iterable;)Z
Method	scala/collection/IterableLike$class.sameElements:(Lscala/collection/IterableLike;Lscala/collection/Iterable;)Z
Asciz	Lscala/collection/Iterable;;
Asciz	copyToArray;
Asciz	(Ljava/lang/Object;II)V;
Asciz	(Lscala/collection/IterableLike;Ljava/lang/Object;II)V;
NameAndType	copyToArray:(Lscala/collection/IterableLike;Ljava/lang/Object;II)V
Method	scala/collection/IterableLike$class.copyToArray:(Lscala/collection/IterableLike;Ljava/lang/Object;II)V
Asciz	xs;
Asciz	start;
Asciz	len;
Asciz	dropRight;
Asciz	(Lscala/collection/IterableLike;I)Ljava/lang/Object;;
NameAndType	dropRight:(Lscala/collection/IterableLike;I)Ljava/lang/Object;
Method	scala/collection/IterableLike$class.dropRight:(Lscala/collection/IterableLike;I)Ljava/lang/Object;
Asciz	takeRight;
NameAndType	takeRight:(Lscala/collection/IterableLike;I)Ljava/lang/Object;
Method	scala/collection/IterableLike$class.takeRight:(Lscala/collection/IterableLike;I)Ljava/lang/Object;
Asciz	(Lscala/collection/IterableLike;Lscala/Function1;)Ljava/lang/Object;;
NameAndType	takeWhile:(Lscala/collection/IterableLike;Lscala/Function1;)Ljava/lang/Object;
Method	scala/collection/IterableLike$class.takeWhile:(Lscala/collection/IterableLike;Lscala/Function1;)Ljava/lang/Object;
Asciz	(Lscala/collection/IterableLike;II)Ljava/lang/Object;;
NameAndType	slice:(Lscala/collection/IterableLike;II)Ljava/lang/Object;
Method	scala/collection/IterableLike$class.slice:(Lscala/collection/IterableLike;II)Ljava/lang/Object;
NameAndType	take:(Lscala/collection/IterableLike;I)Ljava/lang/Object;
Method	scala/collection/IterableLike$class.take:(Lscala/collection/IterableLike;I)Ljava/lang/Object;
Asciz	head;
NameAndType	head:(Lscala/collection/IterableLike;)Ljava/lang/Object;
Method	scala/collection/IterableLike$class.head:(Lscala/collection/IterableLike;)Ljava/lang/Object;
Asciz	toIterable;
Asciz	(Lscala/collection/IterableLike;)Lscala/collection/Iterable;;
NameAndType	toIterable:(Lscala/collection/IterableLike;)Lscala/collection/Iterable;
Method	scala/collection/IterableLike$class.toIterable:(Lscala/collection/IterableLike;)Lscala/collection/Iterable;
Asciz	reduceRight;
Asciz	(Lscala/Function2;)Ljava/lang/Object;;
Asciz	(Lscala/collection/IterableLike;Lscala/Function2;)Ljava/lang/Object;;
NameAndType	reduceRight:(Lscala/collection/IterableLike;Lscala/Function2;)Ljava/lang/Object;
Method	scala/collection/IterableLike$class.reduceRight:(Lscala/collection/IterableLike;Lscala/Function2;)Ljava/lang/Object;
Asciz	op;
Asciz	Lscala/Function2;;
Asciz	foldRight;
Asciz	(Ljava/lang/Object;Lscala/Function2;)Ljava/lang/Object;;
Asciz	(Lscala/collection/IterableLike;Ljava/lang/Object;Lscala/Function2;)Ljava/lang/Object;;
NameAndType	foldRight:(Lscala/collection/IterableLike;Ljava/lang/Object;Lscala/Function2;)Ljava/lang/Object;
Method	scala/collection/IterableLike$class.foldRight:(Lscala/collection/IterableLike;Ljava/lang/Object;Lscala/Function2;)Ljava/lang/Object;
Asciz	z;
Asciz	isEmpty;
Asciz	()Z;
Asciz	(Lscala/collection/IterableLike;)Z;
NameAndType	isEmpty:(Lscala/collection/IterableLike;)Z
Method	scala/collection/IterableLike$class.isEmpty:(Lscala/collection/IterableLike;)Z
Asciz	find;
Asciz	(Lscala/Function1;)Lscala/Option;;
Asciz	(Lscala/collection/IterableLike;Lscala/Function1;)Lscala/Option;;
NameAndType	find:(Lscala/collection/IterableLike;Lscala/Function1;)Lscala/Option;
Method	scala/collection/IterableLike$class.find:(Lscala/collection/IterableLike;Lscala/Function1;)Lscala/Option;
Asciz	exists;
Asciz	(Lscala/Function1;)Z;
Asciz	(Lscala/collection/IterableLike;Lscala/Function1;)Z;
NameAndType	exists:(Lscala/collection/IterableLike;Lscala/Function1;)Z
Method	scala/collection/IterableLike$class.exists:(Lscala/collection/IterableLike;Lscala/Function1;)Z
Asciz	forall;
NameAndType	forall:(Lscala/collection/IterableLike;Lscala/Function1;)Z
Method	scala/collection/IterableLike$class.forall:(Lscala/collection/IterableLike;Lscala/Function1;)Z
Asciz	foreach;
Asciz	(Lscala/Function1;)V;
Asciz	(Lscala/collection/IterableLike;Lscala/Function1;)V;
NameAndType	foreach:(Lscala/collection/IterableLike;Lscala/Function1;)V
Method	scala/collection/IterableLike$class.foreach:(Lscala/collection/IterableLike;Lscala/Function1;)V
Asciz	elements;
Asciz	(Lscala/collection/IterableLike;)Lscala/collection/Iterator;;
NameAndType	elements:(Lscala/collection/IterableLike;)Lscala/collection/Iterator;
Method	scala/collection/IterableLike$class.elements:(Lscala/collection/IterableLike;)Lscala/collection/Iterator;
Asciz	(Lscala/collection/IterableLike;Ljava/lang/Object;)Lscala/collection/Iterable;;
NameAndType	toCollection:(Lscala/collection/IterableLike;Ljava/lang/Object;)Lscala/collection/Iterable;
Method	scala/collection/IterableLike$class.toCollection:(Lscala/collection/IterableLike;Ljava/lang/Object;)Lscala/collection/Iterable;
NameAndType	thisCollection:(Lscala/collection/IterableLike;)Lscala/collection/Iterable;
Method	scala/collection/IterableLike$class.thisCollection:(Lscala/collection/IterableLike;)Lscala/collection/Iterable;
Asciz	companion;
Asciz	()Lscala/collection/generic/GenericCompanion;;
Asciz	(Lscala/collection/Iterable;)Lscala/collection/generic/GenericCompanion;;
NameAndType	companion:(Lscala/collection/Iterable;)Lscala/collection/generic/GenericCompanion;
Method	scala/collection/Iterable$class.companion:(Lscala/collection/Iterable;)Lscala/collection/generic/GenericCompanion;
Asciz	newZippedAll;
Asciz	(Lscala/collection/Iterable;Ljava/lang/Object;Ljava/lang/Object;)Lscala/collection/IterableViewLike$Transformed;;
Asciz	(Lscala/collection/IterableViewLike;Lscala/collection/Iterable;Ljava/lang/Object;Ljava/lang/Object;)Lscala/collection/IterableViewLike$Transformed;;
NameAndType	newZippedAll:(Lscala/collection/IterableViewLike;Lscala/collection/Iterable;Ljava/lang/Object;Ljava/lang/Object;)Lscala/collection/IterableViewLike$Transformed;
Method	scala/collection/views/IterableTransformations$class.newZippedAll:(Lscala/collection/IterableViewLike;Lscala/collection/Iterable;Ljava/lang/Object;Ljava/lang/Object;)Lscala/collection/IterableViewLike$Transformed;
Asciz	_thisElem;
Asciz	_thatElem;
Asciz	newZipped;
Asciz	(Lscala/collection/Iterable;)Lscala/collection/IterableViewLike$Transformed;;
Asciz	(Lscala/collection/IterableViewLike;Lscala/collection/Iterable;)Lscala/collection/IterableViewLike$Transformed;;
NameAndType	newZipped:(Lscala/collection/IterableViewLike;Lscala/collection/Iterable;)Lscala/collection/IterableViewLike$Transformed;
Method	scala/collection/views/IterableTransformations$class.newZipped:(Lscala/collection/IterableViewLike;Lscala/collection/Iterable;)Lscala/collection/IterableViewLike$Transformed;
Asciz	(Lscala/collection/IterableViewLike;Lscala/Function1;)Lscala/collection/IterableViewLike$Transformed;;
NameAndType	newTakenWhile:(Lscala/collection/IterableViewLike;Lscala/Function1;)Lscala/collection/IterableViewLike$Transformed;
Method	scala/collection/views/IterableTransformations$class.newTakenWhile:(Lscala/collection/IterableViewLike;Lscala/Function1;)Lscala/collection/IterableViewLike$Transformed;
NameAndType	newDroppedWhile:(Lscala/collection/IterableViewLike;Lscala/Function1;)Lscala/collection/IterableViewLike$Transformed;
Method	scala/collection/views/IterableTransformations$class.newDroppedWhile:(Lscala/collection/IterableViewLike;Lscala/Function1;)Lscala/collection/IterableViewLike$Transformed;
Asciz	(Lscala/collection/IterableViewLike;II)Lscala/collection/IterableViewLike$Transformed;;
NameAndType	newSliced:(Lscala/collection/IterableViewLike;II)Lscala/collection/IterableViewLike$Transformed;
Method	scala/collection/views/IterableTransformations$class.newSliced:(Lscala/collection/IterableViewLike;II)Lscala/collection/IterableViewLike$Transformed;
NameAndType	newFiltered:(Lscala/collection/IterableViewLike;Lscala/Function1;)Lscala/collection/IterableViewLike$Transformed;
Method	scala/collection/views/IterableTransformations$class.newFiltered:(Lscala/collection/IterableViewLike;Lscala/Function1;)Lscala/collection/IterableViewLike$Transformed;
NameAndType	newFlatMapped:(Lscala/collection/IterableViewLike;Lscala/Function1;)Lscala/collection/IterableViewLike$Transformed;
Method	scala/collection/views/IterableTransformations$class.newFlatMapped:(Lscala/collection/IterableViewLike;Lscala/Function1;)Lscala/collection/IterableViewLike$Transformed;
NameAndType	newMapped:(Lscala/collection/IterableViewLike;Lscala/Function1;)Lscala/collection/IterableViewLike$Transformed;
Method	scala/collection/views/IterableTransformations$class.newMapped:(Lscala/collection/IterableViewLike;Lscala/Function1;)Lscala/collection/IterableViewLike$Transformed;
Asciz	(Lscala/collection/IterableViewLike;Lscala/collection/Traversable;)Lscala/collection/IterableViewLike$Transformed;;
NameAndType	newAppended:(Lscala/collection/IterableViewLike;Lscala/collection/Traversable;)Lscala/collection/IterableViewLike$Transformed;
Method	scala/collection/views/IterableTransformations$class.newAppended:(Lscala/collection/IterableViewLike;Lscala/collection/Traversable;)Lscala/collection/IterableViewLike$Transformed;
Asciz	stringPrefix;
Asciz	()Ljava/lang/String;;
Asciz	(Lscala/collection/IterableViewLike;)Ljava/lang/String;;
NameAndType	stringPrefix:(Lscala/collection/IterableViewLike;)Ljava/lang/String;
Method	scala/collection/IterableViewLike$class.stringPrefix:(Lscala/collection/IterableViewLike;)Ljava/lang/String;
Asciz	zipAll;
Asciz	(Lscala/collection/Iterable;Ljava/lang/Object;Ljava/lang/Object;Lscala/collection/generic/CanBuildFrom;)Ljava/lang/Object;;
Asciz	(Lscala/collection/IterableViewLike;Lscala/collection/Iterable;Ljava/lang/Object;Ljava/lang/Object;Lscala/collection/generic/CanBuildFrom;)Ljava/lang/Object;;
NameAndType	zipAll:(Lscala/collection/IterableViewLike;Lscala/collection/Iterable;Ljava/lang/Object;Ljava/lang/Object;Lscala/collection/generic/CanBuildFrom;)Ljava/lang/Object;
Method	scala/collection/IterableViewLike$class.zipAll:(Lscala/collection/IterableViewLike;Lscala/collection/Iterable;Ljava/lang/Object;Ljava/lang/Object;Lscala/collection/generic/CanBuildFrom;)Ljava/lang/Object;
Asciz	thisElem;
Asciz	thatElem;
Asciz	bf;
Asciz	Lscala/collection/generic/CanBuildFrom;;
Asciz	zipWithIndex;
Asciz	(Lscala/collection/generic/CanBuildFrom;)Ljava/lang/Object;;
Asciz	(Lscala/collection/IterableViewLike;Lscala/collection/generic/CanBuildFrom;)Ljava/lang/Object;;
NameAndType	zipWithIndex:(Lscala/collection/IterableViewLike;Lscala/collection/generic/CanBuildFrom;)Ljava/lang/Object;
Method	scala/collection/IterableViewLike$class.zipWithIndex:(Lscala/collection/IterableViewLike;Lscala/collection/generic/CanBuildFrom;)Ljava/lang/Object;
Asciz	zip;
Asciz	(Lscala/collection/Iterable;Lscala/collection/generic/CanBuildFrom;)Ljava/lang/Object;;
Asciz	(Lscala/collection/IterableViewLike;Lscala/collection/Iterable;Lscala/collection/generic/CanBuildFrom;)Ljava/lang/Object;;
NameAndType	zip:(Lscala/collection/IterableViewLike;Lscala/collection/Iterable;Lscala/collection/generic/CanBuildFrom;)Ljava/lang/Object;
Method	scala/collection/IterableViewLike$class.zip:(Lscala/collection/IterableViewLike;Lscala/collection/Iterable;Lscala/collection/generic/CanBuildFrom;)Ljava/lang/Object;
Asciz	<B:Ljava/lang/Object;Coll:Ljava/lang/Object;>Lscala/collection/views/TraversableLike<TB;TColl;>;Lscala/collection/IterableView<TB;TColl;>;Lscala/ScalaObject;;
Asciz	ScalaSig;
Asciz	InnerClasses;
Asciz	scala/collection/IterableViewLike$Transformed;
class	scala/collection/IterableViewLike$Transformed
Asciz	scala/collection/IterableViewLike;
class	scala/collection/IterableViewLike
Asciz	Transformed;
Asciz	scala/collection/TraversableViewLike$Transformed;
class	scala/collection/TraversableViewLike$Transformed
Asciz	scala/collection/views/IterableLike;
class	scala/collection/views/IterableLike
Asciz	scala/collection/IterableView;
class	scala/collection/IterableView
Asciz	scala/ScalaObject;
class	scala/ScalaObject

{
public scala.collection.views.IterableLike();
  Signature: ()V
  Code:
   Stack=1, Locals=1, Args_size=1
	aload_0
	invokespecial	Method scala/collection/views/TraversableLike."<init>":()V
	aload_0
	invokestatic	Method scala/collection/IterableLike$class.$init$:(Lscala/collection/IterableLike;)V
	aload_0
	invokestatic	Method scala/collection/Iterable$class.$init$:(Lscala/collection/Iterable;)V
	aload_0
	invokestatic	Method scala/collection/views/IterableTransformations$class.$init$:(Lscala/collection/IterableViewLike;)V
	aload_0
	invokestatic	Method scala/collection/IterableViewLike$class.$init$:(Lscala/collection/IterableViewLike;)V
	return
  Labels:
  Signature: length = 0x2
   00 04 

public scala.collection.TraversableViewLike$Transformed newAppended(scala.collection.Traversable);
  Signature: (Lscala/collection/Traversable;)Lscala/collection/TraversableViewLike$Transformed;
  Code:
   Stack=2, Locals=2, Args_size=2
	aload_0
	aload_1
	invokeinterface	InterfaceMethod scala/collection/views/IterableTransformations.newAppended:(Lscala/collection/Traversable;)Lscala/collection/IterableViewLike$Transformed;
	areturn
  Labels:
  LocalVariableTable: 
   Start  Length  Slot  Name   Signature
   0      8      0    this       Lscala/collection/views/IterableLike;
   0      8      1    that       Lscala/collection/Traversable;

  Signature: length = 0x2
   00 20 

public scala.collection.TraversableViewLike$Transformed newMapped(scala.Function1);
  Signature: (Lscala/Function1;)Lscala/collection/TraversableViewLike$Transformed;
  Code:
   Stack=2, Locals=2, Args_size=2
	aload_0
	aload_1
	invokeinterface	InterfaceMethod scala/collection/views/IterableTransformations.newMapped:(Lscala/Function1;)Lscala/collection/IterableViewLike$Transformed;
	areturn
  Labels:
  LocalVariableTable: 
   Start  Length  Slot  Name   Signature
   0      8      0    this       Lscala/collection/views/IterableLike;
   0      8      1    f       Lscala/Function1;

  Signature: length = 0x2
   00 2C 

public scala.collection.TraversableViewLike$Transformed newFlatMapped(scala.Function1);
  Signature: (Lscala/Function1;)Lscala/collection/TraversableViewLike$Transformed;
  Code:
   Stack=2, Locals=2, Args_size=2
	aload_0
	aload_1
	invokeinterface	InterfaceMethod scala/collection/views/IterableTransformations.newFlatMapped:(Lscala/Function1;)Lscala/collection/IterableViewLike$Transformed;
	areturn
  Labels:
  LocalVariableTable: 
   Start  Length  Slot  Name   Signature
   0      8      0    this       Lscala/collection/views/IterableLike;
   0      8      1    f       Lscala/Function1;

  Signature: length = 0x2
   00 2C 

public scala.collection.TraversableViewLike$Transformed newFiltered(scala.Function1);
  Signature: (Lscala/Function1;)Lscala/collection/TraversableViewLike$Transformed;
  Code:
   Stack=2, Locals=2, Args_size=2
	aload_0
	aload_1
	invokeinterface	InterfaceMethod scala/collection/views/IterableTransformations.newFiltered:(Lscala/Function1;)Lscala/collection/IterableViewLike$Transformed;
	areturn
  Labels:
  LocalVariableTable: 
   Start  Length  Slot  Name   Signature
   0      8      0    this       Lscala/collection/views/IterableLike;
   0      8      1    p       Lscala/Function1;

  Signature: length = 0x2
   00 2C 

public scala.collection.TraversableViewLike$Transformed newSliced(int, int);
  Signature: (II)Lscala/collection/TraversableViewLike$Transformed;
  Code:
   Stack=3, Locals=3, Args_size=3
	aload_0
	iload_1
	iload_2
	invokeinterface	InterfaceMethod scala/collection/views/IterableTransformations.newSliced:(II)Lscala/collection/IterableViewLike$Transformed;
	areturn
  Labels:
  LocalVariableTable: 
   Start  Length  Slot  Name   Signature
   0      9      0    this       Lscala/collection/views/IterableLike;
   0      9      1    _from       I
   0      9      2    _until       I

  Signature: length = 0x2
   00 3A 

public scala.collection.TraversableViewLike$Transformed newDroppedWhile(scala.Function1);
  Signature: (Lscala/Function1;)Lscala/collection/TraversableViewLike$Transformed;
  Code:
   Stack=2, Locals=2, Args_size=2
	aload_0
	aload_1
	invokeinterface	InterfaceMethod scala/collection/views/IterableTransformations.newDroppedWhile:(Lscala/Function1;)Lscala/collection/IterableViewLike$Transformed;
	areturn
  Labels:
  LocalVariableTable: 
   Start  Length  Slot  Name   Signature
   0      8      0    this       Lscala/collection/views/IterableLike;
   0      8      1    p       Lscala/Function1;

  Signature: length = 0x2
   00 2C 

public scala.collection.TraversableViewLike$Transformed newTakenWhile(scala.Function1);
  Signature: (Lscala/Function1;)Lscala/collection/TraversableViewLike$Transformed;
  Code:
   Stack=2, Locals=2, Args_size=2
	aload_0
	aload_1
	invokeinterface	InterfaceMethod scala/collection/views/IterableTransformations.newTakenWhile:(Lscala/Function1;)Lscala/collection/IterableViewLike$Transformed;
	areturn
  Labels:
  LocalVariableTable: 
   Start  Length  Slot  Name   Signature
   0      8      0    this       Lscala/collection/views/IterableLike;
   0      8      1    p       Lscala/Function1;

  Signature: length = 0x2
   00 2C 

public scala.collection.Traversable thisCollection();
  Signature: ()Lscala/collection/Traversable;
  Code:
   Stack=1, Locals=1, Args_size=1
	aload_0
	invokeinterface	InterfaceMethod scala/collection/IterableLike.thisCollection:()Lscala/collection/Iterable;
	areturn
  Labels:

public scala.collection.Traversable toCollection(java.lang.Object);
  Signature: (Ljava/lang/Object;)Lscala/collection/Traversable;
  Code:
   Stack=2, Locals=2, Args_size=2
	aload_0
	aload_1
	invokeinterface	InterfaceMethod scala/collection/IterableLike.toCollection:(Ljava/lang/Object;)Lscala/collection/Iterable;
	areturn
  Labels:
  LocalVariableTable: 
   Start  Length  Slot  Name   Signature
   0      8      0    this       Lscala/collection/views/IterableLike;
   0      8      1    repr       Ljava/lang/Object;


public scala.collection.TraversableView take(int);
  Signature: (I)Lscala/collection/TraversableView;
  Code:
   Stack=2, Locals=2, Args_size=2
	aload_0
	iload_1
	invokeinterface	InterfaceMethod scala/collection/IterableLike.take:(I)Ljava/lang/Object;
	checkcast	class scala/collection/TraversableView
	areturn
  Labels:
  LocalVariableTable: 
   Start  Length  Slot  Name   Signature
   0      11      0    this       Lscala/collection/views/IterableLike;
   0      11      1    n       I


public scala.collection.TraversableView slice(int, int);
  Signature: (II)Lscala/collection/TraversableView;
  Code:
   Stack=3, Locals=3, Args_size=3
	aload_0
	iload_1
	iload_2
	invokeinterface	InterfaceMethod scala/collection/IterableLike.slice:(II)Ljava/lang/Object;
	checkcast	class scala/collection/TraversableView
	areturn
  Labels:
  LocalVariableTable: 
   Start  Length  Slot  Name   Signature
   0      12      0    this       Lscala/collection/views/IterableLike;
   0      12      1    from       I
   0      12      2    until       I


public scala.collection.TraversableView takeWhile(scala.Function1);
  Signature: (Lscala/Function1;)Lscala/collection/TraversableView;
  Code:
   Stack=2, Locals=2, Args_size=2
	aload_0
	aload_1
	invokeinterface	InterfaceMethod scala/collection/IterableLike.takeWhile:(Lscala/Function1;)Ljava/lang/Object;
	checkcast	class scala/collection/TraversableView
	areturn
  Labels:
  LocalVariableTable: 
   Start  Length  Slot  Name   Signature
   0      11      0    this       Lscala/collection/views/IterableLike;
   0      11      1    p       Lscala/Function1;


public scala.collection.TraversableView view();
  Signature: ()Lscala/collection/TraversableView;
  Code:
   Stack=1, Locals=1, Args_size=1
	aload_0
	invokeinterface	InterfaceMethod scala/collection/IterableLike.view:()Lscala/collection/IterableView;
	areturn
  Labels:

public scala.collection.TraversableView view(int, int);
  Signature: (II)Lscala/collection/TraversableView;
  Code:
   Stack=3, Locals=3, Args_size=3
	aload_0
	iload_1
	iload_2
	invokeinterface	InterfaceMethod scala/collection/IterableLike.view:(II)Lscala/collection/IterableView;
	areturn
  Labels:
  LocalVariableTable: 
   Start  Length  Slot  Name   Signature
   0      9      0    this       Lscala/collection/views/IterableLike;
   0      9      1    from       I
   0      9      2    until       I


public java.lang.Object filter(scala.Function1);
  Signature: (Lscala/Function1;)Ljava/lang/Object;
  Code:
   Stack=2, Locals=2, Args_size=2
	aload_0
	aload_1
	invokeinterface	InterfaceMethod scala/collection/TraversableViewLike.filter:(Lscala/Function1;)Lscala/collection/TraversableView;
	areturn
  Labels:
  LocalVariableTable: 
   Start  Length  Slot  Name   Signature
   0      8      0    this       Lscala/collection/views/IterableLike;
   0      8      1    p       Lscala/Function1;


public java.lang.Object init();
  Signature: ()Ljava/lang/Object;
  Code:
   Stack=1, Locals=1, Args_size=1
	aload_0
	invokeinterface	InterfaceMethod scala/collection/TraversableViewLike.init:()Lscala/collection/TraversableView;
	areturn
  Labels:

public java.lang.Object drop(int);
  Signature: (I)Ljava/lang/Object;
  Code:
   Stack=2, Locals=2, Args_size=2
	aload_0
	iload_1
	invokeinterface	InterfaceMethod scala/collection/TraversableViewLike.drop:(I)Lscala/collection/TraversableView;
	areturn
  Labels:
  LocalVariableTable: 
   Start  Length  Slot  Name   Signature
   0      8      0    this       Lscala/collection/views/IterableLike;
   0      8      1    n       I


public java.lang.Object dropWhile(scala.Function1);
  Signature: (Lscala/Function1;)Ljava/lang/Object;
  Code:
   Stack=2, Locals=2, Args_size=2
	aload_0
	aload_1
	invokeinterface	InterfaceMethod scala/collection/TraversableViewLike.dropWhile:(Lscala/Function1;)Lscala/collection/TraversableView;
	areturn
  Labels:
  LocalVariableTable: 
   Start  Length  Slot  Name   Signature
   0      8      0    this       Lscala/collection/views/IterableLike;
   0      8      1    p       Lscala/Function1;


public abstract scala.collection.Iterator iterator();
  Signature: ()Lscala/collection/Iterator;
  Signature: length = 0x2
   00 FFFFFF82 

public scala.collection.IterableView projection();
  Signature: ()Lscala/collection/IterableView;
  Code:
   Stack=1, Locals=1, Args_size=1
	aload_0
	invokestatic	Method scala/collection/IterableLike$class.projection:(Lscala/collection/IterableLike;)Lscala/collection/IterableView;
	areturn
  Labels:
  Deprecated: true

public scala.Option firstOption();
  Signature: ()Lscala/Option;
  Code:
   Stack=1, Locals=1, Args_size=1
	aload_0
	invokestatic	Method scala/collection/IterableLike$class.firstOption:(Lscala/collection/IterableLike;)Lscala/Option;
	areturn
  Labels:
  Deprecated: true

public java.lang.Object first();
  Signature: ()Ljava/lang/Object;
  Code:
   Stack=1, Locals=1, Args_size=1
	aload_0
	invokestatic	Method scala/collection/IterableLike$class.first:(Lscala/collection/IterableLike;)Ljava/lang/Object;
	areturn
  Labels:
  Deprecated: true

public scala.collection.IterableView view(int, int);
  Signature: (II)Lscala/collection/IterableView;
  Code:
   Stack=3, Locals=3, Args_size=3
	aload_0
	iload_1
	iload_2
	invokestatic	Method scala/collection/IterableLike$class.view:(Lscala/collection/IterableLike;II)Lscala/collection/IterableView;
	areturn
  Labels:
  LocalVariableTable: 
   Start  Length  Slot  Name   Signature
   0      7      0    this       Lscala/collection/views/IterableLike;
   0      7      1    from       I
   0      7      2    until       I


public scala.collection.IterableView view();
  Signature: ()Lscala/collection/IterableView;
  Code:
   Stack=1, Locals=1, Args_size=1
	aload_0
	invokestatic	Method scala/collection/IterableLike$class.view:(Lscala/collection/IterableLike;)Lscala/collection/IterableView;
	areturn
  Labels:

public boolean canEqual(java.lang.Object);
  Signature: (Ljava/lang/Object;)Z
  Code:
   Stack=2, Locals=2, Args_size=2
	aload_0
	aload_1
	invokestatic	Method scala/collection/IterableLike$class.canEqual:(Lscala/collection/IterableLike;Ljava/lang/Object;)Z
	ireturn
  Labels:
  LocalVariableTable: 
   Start  Length  Slot  Name   Signature
   0      6      0    this       Lscala/collection/views/IterableLike;
   0      6      1    that       Ljava/lang/Object;


public scala.collection.immutable.Stream toStream();
  Signature: ()Lscala/collection/immutable/Stream;
  Code:
   Stack=1, Locals=1, Args_size=1
	aload_0
	invokestatic	Method scala/collection/IterableLike$class.toStream:(Lscala/collection/IterableLike;)Lscala/collection/immutable/Stream;
	areturn
  Labels:

public boolean sameElements(scala.collection.Iterable);
  Signature: (Lscala/collection/Iterable;)Z
  Code:
   Stack=2, Locals=2, Args_size=2
	aload_0
	aload_1
	invokestatic	Method scala/collection/IterableLike$class.sameElements:(Lscala/collection/IterableLike;Lscala/collection/Iterable;)Z
	ireturn
  Labels:
  LocalVariableTable: 
   Start  Length  Slot  Name   Signature
   0      6      0    this       Lscala/collection/views/IterableLike;
   0      6      1    that       Lscala/collection/Iterable;


public void copyToArray(java.lang.Object, int, int);
  Signature: (Ljava/lang/Object;II)V
  Code:
   Stack=4, Locals=4, Args_size=4
	aload_0
	aload_1
	iload_2
	iload_3
	invokestatic	Method scala/collection/IterableLike$class.copyToArray:(Lscala/collection/IterableLike;Ljava/lang/Object;II)V
	return
  Labels:
  LocalVariableTable: 
   Start  Length  Slot  Name   Signature
   0      8      0    this       Lscala/collection/views/IterableLike;
   0      8      1    xs       Ljava/lang/Object;
   0      8      2    start       I
   0      8      3    len       I


public java.lang.Object dropRight(int);
  Signature: (I)Ljava/lang/Object;
  Code:
   Stack=2, Locals=2, Args_size=2
	aload_0
	iload_1
	invokestatic	Method scala/collection/IterableLike$class.dropRight:(Lscala/collection/IterableLike;I)Ljava/lang/Object;
	areturn
  Labels:
  LocalVariableTable: 
   Start  Length  Slot  Name   Signature
   0      6      0    this       Lscala/collection/views/IterableLike;
   0      6      1    n       I


public java.lang.Object takeRight(int);
  Signature: (I)Ljava/lang/Object;
  Code:
   Stack=2, Locals=2, Args_size=2
	aload_0
	iload_1
	invokestatic	Method scala/collection/IterableLike$class.takeRight:(Lscala/collection/IterableLike;I)Ljava/lang/Object;
	areturn
  Labels:
  LocalVariableTable: 
   Start  Length  Slot  Name   Signature
   0      6      0    this       Lscala/collection/views/IterableLike;
   0      6      1    n       I


public java.lang.Object takeWhile(scala.Function1);
  Signature: (Lscala/Function1;)Ljava/lang/Object;
  Code:
   Stack=2, Locals=2, Args_size=2
	aload_0
	aload_1
	invokestatic	Method scala/collection/IterableLike$class.takeWhile:(Lscala/collection/IterableLike;Lscala/Function1;)Ljava/lang/Object;
	areturn
  Labels:
  LocalVariableTable: 
   Start  Length  Slot  Name   Signature
   0      6      0    this       Lscala/collection/views/IterableLike;
   0      6      1    p       Lscala/Function1;


public java.lang.Object slice(int, int);
  Signature: (II)Ljava/lang/Object;
  Code:
   Stack=3, Locals=3, Args_size=3
	aload_0
	iload_1
	iload_2
	invokestatic	Method scala/collection/IterableLike$class.slice:(Lscala/collection/IterableLike;II)Ljava/lang/Object;
	areturn
  Labels:
  LocalVariableTable: 
   Start  Length  Slot  Name   Signature
   0      7      0    this       Lscala/collection/views/IterableLike;
   0      7      1    from       I
   0      7      2    until       I


public java.lang.Object take(int);
  Signature: (I)Ljava/lang/Object;
  Code:
   Stack=2, Locals=2, Args_size=2
	aload_0
	iload_1
	invokestatic	Method scala/collection/IterableLike$class.take:(Lscala/collection/IterableLike;I)Ljava/lang/Object;
	areturn
  Labels:
  LocalVariableTable: 
   Start  Length  Slot  Name   Signature
   0      6      0    this       Lscala/collection/views/IterableLike;
   0      6      1    n       I


public java.lang.Object head();
  Signature: ()Ljava/lang/Object;
  Code:
   Stack=1, Locals=1, Args_size=1
	aload_0
	invokestatic	Method scala/collection/IterableLike$class.head:(Lscala/collection/IterableLike;)Ljava/lang/Object;
	areturn
  Labels:

public scala.collection.Iterable toIterable();
  Signature: ()Lscala/collection/Iterable;
  Code:
   Stack=1, Locals=1, Args_size=1
	aload_0
	invokestatic	Method scala/collection/IterableLike$class.toIterable:(Lscala/collection/IterableLike;)Lscala/collection/Iterable;
	areturn
  Labels:

public java.lang.Object reduceRight(scala.Function2);
  Signature: (Lscala/Function2;)Ljava/lang/Object;
  Code:
   Stack=2, Locals=2, Args_size=2
	aload_0
	aload_1
	invokestatic	Method scala/collection/IterableLike$class.reduceRight:(Lscala/collection/IterableLike;Lscala/Function2;)Ljava/lang/Object;
	areturn
  Labels:
  LocalVariableTable: 
   Start  Length  Slot  Name   Signature
   0      6      0    this       Lscala/collection/views/IterableLike;
   0      6      1    op       Lscala/Function2;


public java.lang.Object foldRight(java.lang.Object, scala.Function2);
  Signature: (Ljava/lang/Object;Lscala/Function2;)Ljava/lang/Object;
  Code:
   Stack=3, Locals=3, Args_size=3
	aload_0
	aload_1
	aload_2
	invokestatic	Method scala/collection/IterableLike$class.foldRight:(Lscala/collection/IterableLike;Ljava/lang/Object;Lscala/Function2;)Ljava/lang/Object;
	areturn
  Labels:
  LocalVariableTable: 
   Start  Length  Slot  Name   Signature
   0      7      0    this       Lscala/collection/views/IterableLike;
   0      7      1    z       Ljava/lang/Object;
   0      7      2    op       Lscala/Function2;


public boolean isEmpty();
  Signature: ()Z
  Code:
   Stack=1, Locals=1, Args_size=1
	aload_0
	invokestatic	Method scala/collection/IterableLike$class.isEmpty:(Lscala/collection/IterableLike;)Z
	ireturn
  Labels:

public scala.Option find(scala.Function1);
  Signature: (Lscala/Function1;)Lscala/Option;
  Code:
   Stack=2, Locals=2, Args_size=2
	aload_0
	aload_1
	invokestatic	Method scala/collection/IterableLike$class.find:(Lscala/collection/IterableLike;Lscala/Function1;)Lscala/Option;
	areturn
  Labels:
  LocalVariableTable: 
   Start  Length  Slot  Name   Signature
   0      6      0    this       Lscala/collection/views/IterableLike;
   0      6      1    p       Lscala/Function1;


public boolean exists(scala.Function1);
  Signature: (Lscala/Function1;)Z
  Code:
   Stack=2, Locals=2, Args_size=2
	aload_0
	aload_1
	invokestatic	Method scala/collection/IterableLike$class.exists:(Lscala/collection/IterableLike;Lscala/Function1;)Z
	ireturn
  Labels:
  LocalVariableTable: 
   Start  Length  Slot  Name   Signature
   0      6      0    this       Lscala/collection/views/IterableLike;
   0      6      1    p       Lscala/Function1;


public boolean forall(scala.Function1);
  Signature: (Lscala/Function1;)Z
  Code:
   Stack=2, Locals=2, Args_size=2
	aload_0
	aload_1
	invokestatic	Method scala/collection/IterableLike$class.forall:(Lscala/collection/IterableLike;Lscala/Function1;)Z
	ireturn
  Labels:
  LocalVariableTable: 
   Start  Length  Slot  Name   Signature
   0      6      0    this       Lscala/collection/views/IterableLike;
   0      6      1    p       Lscala/Function1;


public void foreach(scala.Function1);
  Signature: (Lscala/Function1;)V
  Code:
   Stack=2, Locals=2, Args_size=2
	aload_0
	aload_1
	invokestatic	Method scala/collection/IterableLike$class.foreach:(Lscala/collection/IterableLike;Lscala/Function1;)V
	return
  Labels:
  LocalVariableTable: 
   Start  Length  Slot  Name   Signature
   0      6      0    this       Lscala/collection/views/IterableLike;
   0      6      1    f       Lscala/Function1;


public scala.collection.Iterator elements();
  Signature: ()Lscala/collection/Iterator;
  Code:
   Stack=1, Locals=1, Args_size=1
	aload_0
	invokestatic	Method scala/collection/IterableLike$class.elements:(Lscala/collection/IterableLike;)Lscala/collection/Iterator;
	areturn
  Labels:
  Deprecated: true

public scala.collection.Iterable toCollection(java.lang.Object);
  Signature: (Ljava/lang/Object;)Lscala/collection/Iterable;
  Code:
   Stack=2, Locals=2, Args_size=2
	aload_0
	aload_1
	invokestatic	Method scala/collection/IterableLike$class.toCollection:(Lscala/collection/IterableLike;Ljava/lang/Object;)Lscala/collection/Iterable;
	areturn
  Labels:
  LocalVariableTable: 
   Start  Length  Slot  Name   Signature
   0      6      0    this       Lscala/collection/views/IterableLike;
   0      6      1    repr       Ljava/lang/Object;


public scala.collection.Iterable thisCollection();
  Signature: ()Lscala/collection/Iterable;
  Code:
   Stack=1, Locals=1, Args_size=1
	aload_0
	invokestatic	Method scala/collection/IterableLike$class.thisCollection:(Lscala/collection/IterableLike;)Lscala/collection/Iterable;
	areturn
  Labels:

public scala.collection.generic.GenericCompanion companion();
  Signature: ()Lscala/collection/generic/GenericCompanion;
  Code:
   Stack=1, Locals=1, Args_size=1
	aload_0
	invokestatic	Method scala/collection/Iterable$class.companion:(Lscala/collection/Iterable;)Lscala/collection/generic/GenericCompanion;
	areturn
  Labels:

public scala.collection.IterableViewLike$Transformed newZippedAll(scala.collection.Iterable, java.lang.Object, java.lang.Object);
  Signature: (Lscala/collection/Iterable;Ljava/lang/Object;Ljava/lang/Object;)Lscala/collection/IterableViewLike$Transformed;
  Code:
   Stack=4, Locals=4, Args_size=4
	aload_0
	aload_1
	aload_2
	aload_3
	invokestatic	Method scala/collection/views/IterableTransformations$class.newZippedAll:(Lscala/collection/IterableViewLike;Lscala/collection/Iterable;Ljava/lang/Object;Ljava/lang/Object;)Lscala/collection/IterableViewLike$Transformed;
	areturn
  Labels:
  LocalVariableTable: 
   Start  Length  Slot  Name   Signature
   0      8      0    this       Lscala/collection/views/IterableLike;
   0      8      1    that       Lscala/collection/Iterable;
   0      8      2    _thisElem       Ljava/lang/Object;
   0      8      3    _thatElem       Ljava/lang/Object;

  Signature: length = 0x2
   00 FFFFFFF7 

public scala.collection.IterableViewLike$Transformed newZipped(scala.collection.Iterable);
  Signature: (Lscala/collection/Iterable;)Lscala/collection/IterableViewLike$Transformed;
  Code:
   Stack=2, Locals=2, Args_size=2
	aload_0
	aload_1
	invokestatic	Method scala/collection/views/IterableTransformations$class.newZipped:(Lscala/collection/IterableViewLike;Lscala/collection/Iterable;)Lscala/collection/IterableViewLike$Transformed;
	areturn
  Labels:
  LocalVariableTable: 
   Start  Length  Slot  Name   Signature
   0      6      0    this       Lscala/collection/views/IterableLike;
   0      6      1    that       Lscala/collection/Iterable;

  Signature: length = 0x2
   00 FFFFFFFE 

public scala.collection.IterableViewLike$Transformed newTakenWhile(scala.Function1);
  Signature: (Lscala/Function1;)Lscala/collection/IterableViewLike$Transformed;
  Code:
   Stack=2, Locals=2, Args_size=2
	aload_0
	aload_1
	invokestatic	Method scala/collection/views/IterableTransformations$class.newTakenWhile:(Lscala/collection/IterableViewLike;Lscala/Function1;)Lscala/collection/IterableViewLike$Transformed;
	areturn
  Labels:
  LocalVariableTable: 
   Start  Length  Slot  Name   Signature
   0      6      0    this       Lscala/collection/views/IterableLike;
   0      6      1    p       Lscala/Function1;

  Signature: length = 0x2
   00 2D 

public scala.collection.IterableViewLike$Transformed newDroppedWhile(scala.Function1);
  Signature: (Lscala/Function1;)Lscala/collection/IterableViewLike$Transformed;
  Code:
   Stack=2, Locals=2, Args_size=2
	aload_0
	aload_1
	invokestatic	Method scala/collection/views/IterableTransformations$class.newDroppedWhile:(Lscala/collection/IterableViewLike;Lscala/Function1;)Lscala/collection/IterableViewLike$Transformed;
	areturn
  Labels:
  LocalVariableTable: 
   Start  Length  Slot  Name   Signature
   0      6      0    this       Lscala/collection/views/IterableLike;
   0      6      1    p       Lscala/Function1;

  Signature: length = 0x2
   00 2D 

public scala.collection.IterableViewLike$Transformed newSliced(int, int);
  Signature: (II)Lscala/collection/IterableViewLike$Transformed;
  Code:
   Stack=3, Locals=3, Args_size=3
	aload_0
	iload_1
	iload_2
	invokestatic	Method scala/collection/views/IterableTransformations$class.newSliced:(Lscala/collection/IterableViewLike;II)Lscala/collection/IterableViewLike$Transformed;
	areturn
  Labels:
  LocalVariableTable: 
   Start  Length  Slot  Name   Signature
   0      7      0    this       Lscala/collection/views/IterableLike;
   0      7      1    _from       I
   0      7      2    _until       I

  Signature: length = 0x2
   00 3B 

public scala.collection.IterableViewLike$Transformed newFiltered(scala.Function1);
  Signature: (Lscala/Function1;)Lscala/collection/IterableViewLike$Transformed;
  Code:
   Stack=2, Locals=2, Args_size=2
	aload_0
	aload_1
	invokestatic	Method scala/collection/views/IterableTransformations$class.newFiltered:(Lscala/collection/IterableViewLike;Lscala/Function1;)Lscala/collection/IterableViewLike$Transformed;
	areturn
  Labels:
  LocalVariableTable: 
   Start  Length  Slot  Name   Signature
   0      6      0    this       Lscala/collection/views/IterableLike;
   0      6      1    p       Lscala/Function1;

  Signature: length = 0x2
   00 2D 

public scala.collection.IterableViewLike$Transformed newFlatMapped(scala.Function1);
  Signature: (Lscala/Function1;)Lscala/collection/IterableViewLike$Transformed;
  Code:
   Stack=2, Locals=2, Args_size=2
	aload_0
	aload_1
	invokestatic	Method scala/collection/views/IterableTransformations$class.newFlatMapped:(Lscala/collection/IterableViewLike;Lscala/Function1;)Lscala/collection/IterableViewLike$Transformed;
	areturn
  Labels:
  LocalVariableTable: 
   Start  Length  Slot  Name   Signature
   0      6      0    this       Lscala/collection/views/IterableLike;
   0      6      1    f       Lscala/Function1;

  Signature: length = 0x2
   00 2D 

public scala.collection.IterableViewLike$Transformed newMapped(scala.Function1);
  Signature: (Lscala/Function1;)Lscala/collection/IterableViewLike$Transformed;
  Code:
   Stack=2, Locals=2, Args_size=2
	aload_0
	aload_1
	invokestatic	Method scala/collection/views/IterableTransformations$class.newMapped:(Lscala/collection/IterableViewLike;Lscala/Function1;)Lscala/collection/IterableViewLike$Transformed;
	areturn
  Labels:
  LocalVariableTable: 
   Start  Length  Slot  Name   Signature
   0      6      0    this       Lscala/collection/views/IterableLike;
   0      6      1    f       Lscala/Function1;

  Signature: length = 0x2
   00 2D 

public scala.collection.IterableViewLike$Transformed newAppended(scala.collection.Traversable);
  Signature: (Lscala/collection/Traversable;)Lscala/collection/IterableViewLike$Transformed;
  Code:
   Stack=2, Locals=2, Args_size=2
	aload_0
	aload_1
	invokestatic	Method scala/collection/views/IterableTransformations$class.newAppended:(Lscala/collection/IterableViewLike;Lscala/collection/Traversable;)Lscala/collection/IterableViewLike$Transformed;
	areturn
  Labels:
  LocalVariableTable: 
   Start  Length  Slot  Name   Signature
   0      6      0    this       Lscala/collection/views/IterableLike;
   0      6      1    that       Lscala/collection/Traversable;

  Signature: length = 0x2
   00 23 

public java.lang.String stringPrefix();
  Signature: ()Ljava/lang/String;
  Code:
   Stack=1, Locals=1, Args_size=1
	aload_0
	invokestatic	Method scala/collection/IterableViewLike$class.stringPrefix:(Lscala/collection/IterableViewLike;)Ljava/lang/String;
	areturn
  Labels:

public java.lang.Object zipAll(scala.collection.Iterable, java.lang.Object, java.lang.Object, scala.collection.generic.CanBuildFrom);
  Signature: (Lscala/collection/Iterable;Ljava/lang/Object;Ljava/lang/Object;Lscala/collection/generic/CanBuildFrom;)Ljava/lang/Object;
  Code:
   Stack=5, Locals=5, Args_size=5
	aload_0
	aload_1
	aload_2
	aload_3
	aload	4
	invokestatic	Method scala/collection/IterableViewLike$class.zipAll:(Lscala/collection/IterableViewLike;Lscala/collection/Iterable;Ljava/lang/Object;Ljava/lang/Object;Lscala/collection/generic/CanBuildFrom;)Ljava/lang/Object;
	areturn
  Labels:
  LocalVariableTable: 
   Start  Length  Slot  Name   Signature
   0      10      0    this       Lscala/collection/views/IterableLike;
   0      10      1    that       Lscala/collection/Iterable;
   0      10      2    thisElem       Ljava/lang/Object;
   0      10      3    thatElem       Ljava/lang/Object;
   0      10      4    bf       Lscala/collection/generic/CanBuildFrom;


public java.lang.Object zipWithIndex(scala.collection.generic.CanBuildFrom);
  Signature: (Lscala/collection/generic/CanBuildFrom;)Ljava/lang/Object;
  Code:
   Stack=2, Locals=2, Args_size=2
	aload_0
	aload_1
	invokestatic	Method scala/collection/IterableViewLike$class.zipWithIndex:(Lscala/collection/IterableViewLike;Lscala/collection/generic/CanBuildFrom;)Ljava/lang/Object;
	areturn
  Labels:
  LocalVariableTable: 
   Start  Length  Slot  Name   Signature
   0      6      0    this       Lscala/collection/views/IterableLike;
   0      6      1    bf       Lscala/collection/generic/CanBuildFrom;


public java.lang.Object zip(scala.collection.Iterable, scala.collection.generic.CanBuildFrom);
  Signature: (Lscala/collection/Iterable;Lscala/collection/generic/CanBuildFrom;)Ljava/lang/Object;
  Code:
   Stack=3, Locals=3, Args_size=3
	aload_0
	aload_1
	aload_2
	invokestatic	Method scala/collection/IterableViewLike$class.zip:(Lscala/collection/IterableViewLike;Lscala/collection/Iterable;Lscala/collection/generic/CanBuildFrom;)Ljava/lang/Object;
	areturn
  Labels:
  LocalVariableTable: 
   Start  Length  Slot  Name   Signature
   0      7      0    this       Lscala/collection/views/IterableLike;
   0      7      1    that       Lscala/collection/Iterable;
   0      7      2    bf       Lscala/collection/generic/CanBuildFrom;


}

