Compiled from "Transformed.scala"
public abstract class scala.collection.views.SeqLike extends scala.collection.views.IterableLike implements scala.collection.SeqView,scala.ScalaObject
  SourceFile: "Transformed.scala"
  Signature: length = 0x2
   01 FFFFFFD0 
  ScalaSig: length = 0x12D
   05 00 34 06 06 01 02 FFFFFF81 00 04 08 02 07 53 65 71
   4C 69 6B 65 0A 02 03 04 01 05 76 69 65 77 73 0A
   02 05 06 01 0A 63 6F 6C 6C 65 63 74 69 6F 6E 0A
   01 07 01 05 73 63 61 6C 61 15 03 09 10 1C 13 04
   00 0A 1E 22 10 04 0B 0C 0E 1B 0D 01 02 09 02 0D
   02 02 0C 49 74 65 72 61 62 6C 65 4C 69 6B 65 10
   02 0F 10 0C 00 04 08 11 00 FFFFFF84 FFFFFF80 FFFFFF84 FFFFFFC2 00 13 02
   01 42 03 00 11 02 14 18 10 02 15 16 0D 01 06 09
   02 17 06 02 07 4E 6F 74 68 69 6E 67 10 02 15 19
   09 02 1A 06 02 03 41 6E 79 10 02 0F 1C 04 08 1D
   00 FFFFFF84 FFFFFF80 FFFFFF84 FFFFFFC2 00 13 02 04 43 6F 6C 6C 10 04 1F
   20 0E 1B 0D 01 04 09 02 21 04 02 07 53 65 71 56
   69 65 77 10 02 15 23 09 02 24 06 02 0B 53 63 61
   6C 61 4F 62 6A 65 63 74 08 05 26 00 FFFFFF84 00 27 01
   06 3C 69 6E 69 74 3E 14 01 28 10 04 0B 00 0E 1B
   08 05 2A 00 FFFFFF86 20 2B 01 06 6C 65 6E 67 74 68 15
   01 2C 10 02 15 2D 09 02 2E 06 02 03 49 6E 74 08
   05 30 00 FFFFFF86 20 31 01 05 61 70 70 6C 79 14 02 0E
   32 08 05 33 2F FFFFFFC0 00 2C 01 03 69 64 78 
  InnerClass: 
   public abstract Transformed=class scala/collection/SeqViewLike$Transformed of class scala/collection/SeqViewLike
   public abstract Transformed=class scala/collection/IterableViewLike$Transformed of class scala/collection/IterableViewLike
   public abstract Transformed=class scala/collection/TraversableViewLike$Transformed of class scala/collection/TraversableViewLike
  minor version: 0
  major version: 49
  Constant pool:
Asciz	SourceFile;
Asciz	Transformed.scala;
Asciz	<init>;
Asciz	()V;
Asciz	Code;
Asciz	LineNumberTable;
Asciz	scala/collection/views/IterableLike;
class	scala/collection/views/IterableLike
NameAndType	"<init>":()V
Method	scala/collection/views/IterableLike."<init>":()V
Asciz	scala/Function1$class;
class	scala/Function1$class
Asciz	$init$;
Asciz	(Lscala/Function1;)V;
NameAndType	$init$:(Lscala/Function1;)V
Method	scala/Function1$class.$init$:(Lscala/Function1;)V
Asciz	scala/PartialFunction$class;
class	scala/PartialFunction$class
Asciz	(Lscala/PartialFunction;)V;
NameAndType	$init$:(Lscala/PartialFunction;)V
Method	scala/PartialFunction$class.$init$:(Lscala/PartialFunction;)V
Asciz	scala/collection/SeqLike$class;
class	scala/collection/SeqLike$class
Asciz	(Lscala/collection/SeqLike;)V;
NameAndType	$init$:(Lscala/collection/SeqLike;)V
Method	scala/collection/SeqLike$class.$init$:(Lscala/collection/SeqLike;)V
Asciz	scala/collection/Seq$class;
class	scala/collection/Seq$class
Asciz	(Lscala/collection/Seq;)V;
NameAndType	$init$:(Lscala/collection/Seq;)V
Method	scala/collection/Seq$class.$init$:(Lscala/collection/Seq;)V
Asciz	scala/collection/views/SeqTransformations$class;
class	scala/collection/views/SeqTransformations$class
Asciz	(Lscala/collection/SeqViewLike;)V;
NameAndType	$init$:(Lscala/collection/SeqViewLike;)V
Method	scala/collection/views/SeqTransformations$class.$init$:(Lscala/collection/SeqViewLike;)V
Asciz	scala/collection/SeqViewLike$class;
class	scala/collection/SeqViewLike$class
Method	scala/collection/SeqViewLike$class.$init$:(Lscala/collection/SeqViewLike;)V
Asciz	Signature;
Asciz	reverse;
Asciz	()Ljava/lang/Object;;
Asciz	scala/collection/SeqViewLike;
class	scala/collection/SeqViewLike
Asciz	()Lscala/collection/SeqView;;
NameAndType	reverse:()Lscala/collection/SeqView;
InterfaceMethod	scala/collection/SeqViewLike.reverse:()Lscala/collection/SeqView;
Asciz	newAppended;
Asciz	(Lscala/collection/Traversable;)Lscala/collection/IterableViewLike$Transformed;;
Asciz	scala/collection/views/SeqTransformations;
class	scala/collection/views/SeqTransformations
Asciz	(Lscala/collection/Traversable;)Lscala/collection/SeqViewLike$Transformed;;
NameAndType	newAppended:(Lscala/collection/Traversable;)Lscala/collection/SeqViewLike$Transformed;
InterfaceMethod	scala/collection/views/SeqTransformations.newAppended:(Lscala/collection/Traversable;)Lscala/collection/SeqViewLike$Transformed;
Asciz	this;
Asciz	Lscala/collection/views/SeqLike;;
Asciz	that;
Asciz	Lscala/collection/Traversable;;
Asciz	LocalVariableTable;
Asciz	(Lscala/collection/Traversable;)Lscala/collection/TraversableViewLike$Transformed;;
Asciz	newMapped;
Asciz	(Lscala/Function1;)Lscala/collection/IterableViewLike$Transformed;;
Asciz	(Lscala/Function1;)Lscala/collection/SeqViewLike$Transformed;;
NameAndType	newMapped:(Lscala/Function1;)Lscala/collection/SeqViewLike$Transformed;
InterfaceMethod	scala/collection/views/SeqTransformations.newMapped:(Lscala/Function1;)Lscala/collection/SeqViewLike$Transformed;
Asciz	f;
Asciz	Lscala/Function1;;
Asciz	(Lscala/Function1;)Lscala/collection/TraversableViewLike$Transformed;;
Asciz	newFlatMapped;
NameAndType	newFlatMapped:(Lscala/Function1;)Lscala/collection/SeqViewLike$Transformed;
InterfaceMethod	scala/collection/views/SeqTransformations.newFlatMapped:(Lscala/Function1;)Lscala/collection/SeqViewLike$Transformed;
Asciz	newFiltered;
NameAndType	newFiltered:(Lscala/Function1;)Lscala/collection/SeqViewLike$Transformed;
InterfaceMethod	scala/collection/views/SeqTransformations.newFiltered:(Lscala/Function1;)Lscala/collection/SeqViewLike$Transformed;
Asciz	p;
Asciz	newSliced;
Asciz	(II)Lscala/collection/IterableViewLike$Transformed;;
Asciz	(II)Lscala/collection/SeqViewLike$Transformed;;
NameAndType	newSliced:(II)Lscala/collection/SeqViewLike$Transformed;
InterfaceMethod	scala/collection/views/SeqTransformations.newSliced:(II)Lscala/collection/SeqViewLike$Transformed;
Asciz	_from;
Asciz	I;
Asciz	_until;
Asciz	(II)Lscala/collection/TraversableViewLike$Transformed;;
Asciz	newDroppedWhile;
NameAndType	newDroppedWhile:(Lscala/Function1;)Lscala/collection/SeqViewLike$Transformed;
InterfaceMethod	scala/collection/views/SeqTransformations.newDroppedWhile:(Lscala/Function1;)Lscala/collection/SeqViewLike$Transformed;
Asciz	newTakenWhile;
NameAndType	newTakenWhile:(Lscala/Function1;)Lscala/collection/SeqViewLike$Transformed;
InterfaceMethod	scala/collection/views/SeqTransformations.newTakenWhile:(Lscala/Function1;)Lscala/collection/SeqViewLike$Transformed;
Asciz	newZipped;
Asciz	(Lscala/collection/Iterable;)Lscala/collection/IterableViewLike$Transformed;;
Asciz	(Lscala/collection/Iterable;)Lscala/collection/SeqViewLike$Transformed;;
NameAndType	newZipped:(Lscala/collection/Iterable;)Lscala/collection/SeqViewLike$Transformed;
InterfaceMethod	scala/collection/views/SeqTransformations.newZipped:(Lscala/collection/Iterable;)Lscala/collection/SeqViewLike$Transformed;
Asciz	Lscala/collection/Iterable;;
Asciz	newZippedAll;
Asciz	(Lscala/collection/Iterable;Ljava/lang/Object;Ljava/lang/Object;)Lscala/collection/IterableViewLike$Transformed;;
Asciz	(Lscala/collection/Iterable;Ljava/lang/Object;Ljava/lang/Object;)Lscala/collection/SeqViewLike$Transformed;;
NameAndType	newZippedAll:(Lscala/collection/Iterable;Ljava/lang/Object;Ljava/lang/Object;)Lscala/collection/SeqViewLike$Transformed;
InterfaceMethod	scala/collection/views/SeqTransformations.newZippedAll:(Lscala/collection/Iterable;Ljava/lang/Object;Ljava/lang/Object;)Lscala/collection/SeqViewLike$Transformed;
Asciz	_thisElem;
Asciz	Ljava/lang/Object;;
Asciz	_thatElem;
Asciz	thisCollection;
Asciz	()Lscala/collection/Iterable;;
Asciz	scala/collection/SeqLike;
class	scala/collection/SeqLike
Asciz	()Lscala/collection/Seq;;
NameAndType	thisCollection:()Lscala/collection/Seq;
InterfaceMethod	scala/collection/SeqLike.thisCollection:()Lscala/collection/Seq;
Asciz	()Lscala/collection/Traversable;;
Asciz	toCollection;
Asciz	(Ljava/lang/Object;)Lscala/collection/Iterable;;
Asciz	(Ljava/lang/Object;)Lscala/collection/Seq;;
NameAndType	toCollection:(Ljava/lang/Object;)Lscala/collection/Seq;
InterfaceMethod	scala/collection/SeqLike.toCollection:(Ljava/lang/Object;)Lscala/collection/Seq;
Asciz	repr;
Asciz	(Ljava/lang/Object;)Lscala/collection/Traversable;;
Asciz	isDefinedAt;
Asciz	(Ljava/lang/Object;)Z;
Asciz	scala/runtime/BoxesRunTime;
class	scala/runtime/BoxesRunTime
Asciz	unboxToInt;
Asciz	(Ljava/lang/Object;)I;
NameAndType	unboxToInt:(Ljava/lang/Object;)I
Method	scala/runtime/BoxesRunTime.unboxToInt:(Ljava/lang/Object;)I
Asciz	(I)Z;
NameAndType	isDefinedAt:(I)Z
InterfaceMethod	scala/collection/SeqLike.isDefinedAt:(I)Z
Asciz	x;
Asciz	view;
Asciz	()Lscala/collection/IterableView;;
NameAndType	view:()Lscala/collection/SeqView;
InterfaceMethod	scala/collection/SeqLike.view:()Lscala/collection/SeqView;
Asciz	()Lscala/collection/TraversableView;;
Asciz	(II)Lscala/collection/IterableView;;
Asciz	(II)Lscala/collection/SeqView;;
NameAndType	view:(II)Lscala/collection/SeqView;
InterfaceMethod	scala/collection/SeqLike.view:(II)Lscala/collection/SeqView;
Asciz	from;
Asciz	until;
Asciz	(II)Lscala/collection/TraversableView;;
Asciz	projection;
NameAndType	projection:()Lscala/collection/SeqView;
InterfaceMethod	scala/collection/SeqLike.projection:()Lscala/collection/SeqView;
Asciz	andThen;
Asciz	(Lscala/Function1;)Lscala/Function1;;
Asciz	scala/PartialFunction;
class	scala/PartialFunction
Asciz	(Lscala/Function1;)Lscala/PartialFunction;;
NameAndType	andThen:(Lscala/Function1;)Lscala/PartialFunction;
InterfaceMethod	scala/PartialFunction.andThen:(Lscala/Function1;)Lscala/PartialFunction;
Asciz	g;
Asciz	take;
Asciz	(I)Lscala/collection/TraversableView;;
Asciz	scala/collection/IterableLike;
class	scala/collection/IterableLike
Asciz	(I)Ljava/lang/Object;;
NameAndType	take:(I)Ljava/lang/Object;
InterfaceMethod	scala/collection/IterableLike.take:(I)Ljava/lang/Object;
Asciz	scala/collection/TraversableView;
class	scala/collection/TraversableView
Asciz	n;
Asciz	slice;
Asciz	(II)Ljava/lang/Object;;
NameAndType	slice:(II)Ljava/lang/Object;
InterfaceMethod	scala/collection/IterableLike.slice:(II)Ljava/lang/Object;
Asciz	takeWhile;
Asciz	(Lscala/Function1;)Lscala/collection/TraversableView;;
Asciz	(Lscala/Function1;)Ljava/lang/Object;;
NameAndType	takeWhile:(Lscala/Function1;)Ljava/lang/Object;
InterfaceMethod	scala/collection/IterableLike.takeWhile:(Lscala/Function1;)Ljava/lang/Object;
Asciz	filter;
Asciz	scala/collection/TraversableViewLike;
class	scala/collection/TraversableViewLike
NameAndType	filter:(Lscala/Function1;)Lscala/collection/TraversableView;
InterfaceMethod	scala/collection/TraversableViewLike.filter:(Lscala/Function1;)Lscala/collection/TraversableView;
Asciz	init;
NameAndType	init:()Lscala/collection/TraversableView;
InterfaceMethod	scala/collection/TraversableViewLike.init:()Lscala/collection/TraversableView;
Asciz	drop;
NameAndType	drop:(I)Lscala/collection/TraversableView;
InterfaceMethod	scala/collection/TraversableViewLike.drop:(I)Lscala/collection/TraversableView;
Asciz	dropWhile;
NameAndType	dropWhile:(Lscala/Function1;)Lscala/collection/TraversableView;
InterfaceMethod	scala/collection/TraversableViewLike.dropWhile:(Lscala/Function1;)Lscala/collection/TraversableView;
Asciz	apply;
Asciz	(I)TB;;
Asciz	length;
Asciz	()I;
Asciz	compose;
Asciz	(Lscala/Function1;Lscala/Function1;)Lscala/Function1;;
NameAndType	compose:(Lscala/Function1;Lscala/Function1;)Lscala/Function1;
Method	scala/Function1$class.compose:(Lscala/Function1;Lscala/Function1;)Lscala/Function1;
Asciz	lift;
Asciz	()Lscala/Function1;;
Asciz	(Lscala/PartialFunction;)Lscala/Function1;;
NameAndType	lift:(Lscala/PartialFunction;)Lscala/Function1;
Method	scala/PartialFunction$class.lift:(Lscala/PartialFunction;)Lscala/Function1;
Asciz	(Lscala/PartialFunction;Lscala/Function1;)Lscala/PartialFunction;;
NameAndType	andThen:(Lscala/PartialFunction;Lscala/Function1;)Lscala/PartialFunction;
Method	scala/PartialFunction$class.andThen:(Lscala/PartialFunction;Lscala/Function1;)Lscala/PartialFunction;
Asciz	k;
Asciz	orElse;
Asciz	(Lscala/PartialFunction;)Lscala/PartialFunction;;
Asciz	(Lscala/PartialFunction;Lscala/PartialFunction;)Lscala/PartialFunction;;
NameAndType	orElse:(Lscala/PartialFunction;Lscala/PartialFunction;)Lscala/PartialFunction;
Method	scala/PartialFunction$class.orElse:(Lscala/PartialFunction;Lscala/PartialFunction;)Lscala/PartialFunction;
Asciz	Lscala/PartialFunction;;
Asciz	(Lscala/collection/SeqLike;)Lscala/collection/SeqView;;
NameAndType	projection:(Lscala/collection/SeqLike;)Lscala/collection/SeqView;
Method	scala/collection/SeqLike$class.projection:(Lscala/collection/SeqLike;)Lscala/collection/SeqView;
Asciz	Deprecated;
Asciz	equalsWith;
Asciz	(Lscala/collection/Seq;Lscala/Function2;)Z;
Asciz	(Lscala/collection/SeqLike;Lscala/collection/Seq;Lscala/Function2;)Z;
NameAndType	equalsWith:(Lscala/collection/SeqLike;Lscala/collection/Seq;Lscala/Function2;)Z
Method	scala/collection/SeqLike$class.equalsWith:(Lscala/collection/SeqLike;Lscala/collection/Seq;Lscala/Function2;)Z
Asciz	Lscala/collection/Seq;;
Asciz	Lscala/Function2;;
Asciz	findLastIndexOf;
Asciz	(Lscala/Function1;)I;
Asciz	(Lscala/collection/SeqLike;Lscala/Function1;)I;
NameAndType	findLastIndexOf:(Lscala/collection/SeqLike;Lscala/Function1;)I
Method	scala/collection/SeqLike$class.findLastIndexOf:(Lscala/collection/SeqLike;Lscala/Function1;)I
Asciz	toString;
Asciz	()Ljava/lang/String;;
Asciz	(Lscala/collection/SeqLike;)Ljava/lang/String;;
NameAndType	toString:(Lscala/collection/SeqLike;)Ljava/lang/String;
Method	scala/collection/SeqLike$class.toString:(Lscala/collection/SeqLike;)Ljava/lang/String;
Asciz	equals;
Asciz	(Lscala/collection/SeqLike;Ljava/lang/Object;)Z;
NameAndType	equals:(Lscala/collection/SeqLike;Ljava/lang/Object;)Z
Method	scala/collection/SeqLike$class.equals:(Lscala/collection/SeqLike;Ljava/lang/Object;)Z
Asciz	hashCode;
Asciz	(Lscala/collection/SeqLike;)I;
NameAndType	hashCode:(Lscala/collection/SeqLike;)I
Method	scala/collection/SeqLike$class.hashCode:(Lscala/collection/SeqLike;)I
Asciz	(Lscala/collection/SeqLike;II)Lscala/collection/SeqView;;
NameAndType	view:(Lscala/collection/SeqLike;II)Lscala/collection/SeqView;
Method	scala/collection/SeqLike$class.view:(Lscala/collection/SeqLike;II)Lscala/collection/SeqView;
NameAndType	view:(Lscala/collection/SeqLike;)Lscala/collection/SeqView;
Method	scala/collection/SeqLike$class.view:(Lscala/collection/SeqLike;)Lscala/collection/SeqView;
Asciz	indices;
Asciz	()Lscala/collection/immutable/Range;;
Asciz	(Lscala/collection/SeqLike;)Lscala/collection/immutable/Range;;
NameAndType	indices:(Lscala/collection/SeqLike;)Lscala/collection/immutable/Range;
Method	scala/collection/SeqLike$class.indices:(Lscala/collection/SeqLike;)Lscala/collection/immutable/Range;
Asciz	toSeq;
Asciz	(Lscala/collection/SeqLike;)Lscala/collection/Seq;;
NameAndType	toSeq:(Lscala/collection/SeqLike;)Lscala/collection/Seq;
Method	scala/collection/SeqLike$class.toSeq:(Lscala/collection/SeqLike;)Lscala/collection/Seq;
Asciz	sortBy;
Asciz	(Lscala/Function1;Lscala/math/Ordering;)Ljava/lang/Object;;
Asciz	(Lscala/collection/SeqLike;Lscala/Function1;Lscala/math/Ordering;)Ljava/lang/Object;;
NameAndType	sortBy:(Lscala/collection/SeqLike;Lscala/Function1;Lscala/math/Ordering;)Ljava/lang/Object;
Method	scala/collection/SeqLike$class.sortBy:(Lscala/collection/SeqLike;Lscala/Function1;Lscala/math/Ordering;)Ljava/lang/Object;
Asciz	ord;
Asciz	Lscala/math/Ordering;;
Asciz	sortWith;
Asciz	(Lscala/math/Ordering;)Ljava/lang/Object;;
Asciz	(Lscala/collection/SeqLike;Lscala/math/Ordering;)Ljava/lang/Object;;
NameAndType	sortWith:(Lscala/collection/SeqLike;Lscala/math/Ordering;)Ljava/lang/Object;
Method	scala/collection/SeqLike$class.sortWith:(Lscala/collection/SeqLike;Lscala/math/Ordering;)Ljava/lang/Object;
Asciz	(Lscala/Function2;)Ljava/lang/Object;;
Asciz	(Lscala/collection/SeqLike;Lscala/Function2;)Ljava/lang/Object;;
NameAndType	sortWith:(Lscala/collection/SeqLike;Lscala/Function2;)Ljava/lang/Object;
Method	scala/collection/SeqLike$class.sortWith:(Lscala/collection/SeqLike;Lscala/Function2;)Ljava/lang/Object;
Asciz	lt;
Asciz	corresponds;
NameAndType	corresponds:(Lscala/collection/SeqLike;Lscala/collection/Seq;Lscala/Function2;)Z
Method	scala/collection/SeqLike$class.corresponds:(Lscala/collection/SeqLike;Lscala/collection/Seq;Lscala/Function2;)Z
Asciz	$colon$plus;
Asciz	(Ljava/lang/Object;Lscala/collection/generic/CanBuildFrom;)Ljava/lang/Object;;
Asciz	(Lscala/collection/SeqLike;Ljava/lang/Object;Lscala/collection/generic/CanBuildFrom;)Ljava/lang/Object;;
NameAndType	$colon$plus:(Lscala/collection/SeqLike;Ljava/lang/Object;Lscala/collection/generic/CanBuildFrom;)Ljava/lang/Object;
Method	scala/collection/SeqLike$class.$colon$plus:(Lscala/collection/SeqLike;Ljava/lang/Object;Lscala/collection/generic/CanBuildFrom;)Ljava/lang/Object;
Asciz	elem;
Asciz	bf;
Asciz	Lscala/collection/generic/CanBuildFrom;;
Asciz	$plus$colon;
NameAndType	$plus$colon:(Lscala/collection/SeqLike;Ljava/lang/Object;Lscala/collection/generic/CanBuildFrom;)Ljava/lang/Object;
Method	scala/collection/SeqLike$class.$plus$colon:(Lscala/collection/SeqLike;Ljava/lang/Object;Lscala/collection/generic/CanBuildFrom;)Ljava/lang/Object;
Asciz	updated;
Asciz	(ILjava/lang/Object;Lscala/collection/generic/CanBuildFrom;)Ljava/lang/Object;;
Asciz	(Lscala/collection/SeqLike;ILjava/lang/Object;Lscala/collection/generic/CanBuildFrom;)Ljava/lang/Object;;
NameAndType	updated:(Lscala/collection/SeqLike;ILjava/lang/Object;Lscala/collection/generic/CanBuildFrom;)Ljava/lang/Object;
Method	scala/collection/SeqLike$class.updated:(Lscala/collection/SeqLike;ILjava/lang/Object;Lscala/collection/generic/CanBuildFrom;)Ljava/lang/Object;
Asciz	index;
Asciz	removeDuplicates;
Asciz	(Lscala/collection/SeqLike;)Ljava/lang/Object;;
NameAndType	removeDuplicates:(Lscala/collection/SeqLike;)Ljava/lang/Object;
Method	scala/collection/SeqLike$class.removeDuplicates:(Lscala/collection/SeqLike;)Ljava/lang/Object;
Asciz	intersect;
Asciz	(Lscala/collection/Seq;)Ljava/lang/Object;;
Asciz	(Lscala/collection/SeqLike;Lscala/collection/Seq;)Ljava/lang/Object;;
NameAndType	intersect:(Lscala/collection/SeqLike;Lscala/collection/Seq;)Ljava/lang/Object;
Method	scala/collection/SeqLike$class.intersect:(Lscala/collection/SeqLike;Lscala/collection/Seq;)Ljava/lang/Object;
Asciz	diff;
NameAndType	diff:(Lscala/collection/SeqLike;Lscala/collection/Seq;)Ljava/lang/Object;
Method	scala/collection/SeqLike$class.diff:(Lscala/collection/SeqLike;Lscala/collection/Seq;)Ljava/lang/Object;
Asciz	union;
Asciz	(Lscala/collection/Seq;Lscala/collection/generic/CanBuildFrom;)Ljava/lang/Object;;
Asciz	(Lscala/collection/SeqLike;Lscala/collection/Seq;Lscala/collection/generic/CanBuildFrom;)Ljava/lang/Object;;
NameAndType	union:(Lscala/collection/SeqLike;Lscala/collection/Seq;Lscala/collection/generic/CanBuildFrom;)Ljava/lang/Object;
Method	scala/collection/SeqLike$class.union:(Lscala/collection/SeqLike;Lscala/collection/Seq;Lscala/collection/generic/CanBuildFrom;)Ljava/lang/Object;
Asciz	contains;
NameAndType	contains:(Lscala/collection/SeqLike;Ljava/lang/Object;)Z
Method	scala/collection/SeqLike$class.contains:(Lscala/collection/SeqLike;Ljava/lang/Object;)Z
Asciz	containsSlice;
Asciz	(Lscala/collection/Seq;)Z;
Asciz	(Lscala/collection/SeqLike;Lscala/collection/Seq;)Z;
NameAndType	containsSlice:(Lscala/collection/SeqLike;Lscala/collection/Seq;)Z
Method	scala/collection/SeqLike$class.containsSlice:(Lscala/collection/SeqLike;Lscala/collection/Seq;)Z
Asciz	lastIndexOfSlice;
Asciz	(Lscala/collection/Seq;I)I;
Asciz	(Lscala/collection/SeqLike;Lscala/collection/Seq;I)I;
NameAndType	lastIndexOfSlice:(Lscala/collection/SeqLike;Lscala/collection/Seq;I)I
Method	scala/collection/SeqLike$class.lastIndexOfSlice:(Lscala/collection/SeqLike;Lscala/collection/Seq;I)I
Asciz	end;
Asciz	(Lscala/collection/Seq;)I;
Asciz	(Lscala/collection/SeqLike;Lscala/collection/Seq;)I;
NameAndType	lastIndexOfSlice:(Lscala/collection/SeqLike;Lscala/collection/Seq;)I
Method	scala/collection/SeqLike$class.lastIndexOfSlice:(Lscala/collection/SeqLike;Lscala/collection/Seq;)I
Asciz	indexOfSlice;
NameAndType	indexOfSlice:(Lscala/collection/SeqLike;Lscala/collection/Seq;I)I
Method	scala/collection/SeqLike$class.indexOfSlice:(Lscala/collection/SeqLike;Lscala/collection/Seq;I)I
NameAndType	indexOfSlice:(Lscala/collection/SeqLike;Lscala/collection/Seq;)I
Method	scala/collection/SeqLike$class.indexOfSlice:(Lscala/collection/SeqLike;Lscala/collection/Seq;)I
Asciz	endsWith;
NameAndType	endsWith:(Lscala/collection/SeqLike;Lscala/collection/Seq;)Z
Method	scala/collection/SeqLike$class.endsWith:(Lscala/collection/SeqLike;Lscala/collection/Seq;)Z
Asciz	startsWith;
NameAndType	startsWith:(Lscala/collection/SeqLike;Lscala/collection/Seq;)Z
Method	scala/collection/SeqLike$class.startsWith:(Lscala/collection/SeqLike;Lscala/collection/Seq;)Z
Asciz	(Lscala/collection/Seq;I)Z;
Asciz	(Lscala/collection/SeqLike;Lscala/collection/Seq;I)Z;
NameAndType	startsWith:(Lscala/collection/SeqLike;Lscala/collection/Seq;I)Z
Method	scala/collection/SeqLike$class.startsWith:(Lscala/collection/SeqLike;Lscala/collection/Seq;I)Z
Asciz	offset;
Asciz	reversedElements;
Asciz	()Lscala/collection/Iterator;;
Asciz	(Lscala/collection/SeqLike;)Lscala/collection/Iterator;;
NameAndType	reversedElements:(Lscala/collection/SeqLike;)Lscala/collection/Iterator;
Method	scala/collection/SeqLike$class.reversedElements:(Lscala/collection/SeqLike;)Lscala/collection/Iterator;
Asciz	reverseIterator;
NameAndType	reverseIterator:(Lscala/collection/SeqLike;)Lscala/collection/Iterator;
Method	scala/collection/SeqLike$class.reverseIterator:(Lscala/collection/SeqLike;)Lscala/collection/Iterator;
Asciz	lastIndexWhere;
Asciz	(Lscala/Function1;I)I;
Asciz	(Lscala/collection/SeqLike;Lscala/Function1;I)I;
NameAndType	lastIndexWhere:(Lscala/collection/SeqLike;Lscala/Function1;I)I
Method	scala/collection/SeqLike$class.lastIndexWhere:(Lscala/collection/SeqLike;Lscala/Function1;I)I
NameAndType	lastIndexWhere:(Lscala/collection/SeqLike;Lscala/Function1;)I
Method	scala/collection/SeqLike$class.lastIndexWhere:(Lscala/collection/SeqLike;Lscala/Function1;)I
Asciz	lastIndexOf;
Asciz	(Ljava/lang/Object;I)I;
Asciz	(Lscala/collection/SeqLike;Ljava/lang/Object;I)I;
NameAndType	lastIndexOf:(Lscala/collection/SeqLike;Ljava/lang/Object;I)I
Method	scala/collection/SeqLike$class.lastIndexOf:(Lscala/collection/SeqLike;Ljava/lang/Object;I)I
Asciz	(Lscala/collection/SeqLike;Ljava/lang/Object;)I;
NameAndType	lastIndexOf:(Lscala/collection/SeqLike;Ljava/lang/Object;)I
Method	scala/collection/SeqLike$class.lastIndexOf:(Lscala/collection/SeqLike;Ljava/lang/Object;)I
Asciz	indexOf;
NameAndType	indexOf:(Lscala/collection/SeqLike;Ljava/lang/Object;I)I
Method	scala/collection/SeqLike$class.indexOf:(Lscala/collection/SeqLike;Ljava/lang/Object;I)I
NameAndType	indexOf:(Lscala/collection/SeqLike;Ljava/lang/Object;)I
Method	scala/collection/SeqLike$class.indexOf:(Lscala/collection/SeqLike;Ljava/lang/Object;)I
Asciz	findIndexOf;
NameAndType	findIndexOf:(Lscala/collection/SeqLike;Lscala/Function1;)I
Method	scala/collection/SeqLike$class.findIndexOf:(Lscala/collection/SeqLike;Lscala/Function1;)I
Asciz	indexWhere;
NameAndType	indexWhere:(Lscala/collection/SeqLike;Lscala/Function1;I)I
Method	scala/collection/SeqLike$class.indexWhere:(Lscala/collection/SeqLike;Lscala/Function1;I)I
NameAndType	indexWhere:(Lscala/collection/SeqLike;Lscala/Function1;)I
Method	scala/collection/SeqLike$class.indexWhere:(Lscala/collection/SeqLike;Lscala/Function1;)I
Asciz	prefixLength;
NameAndType	prefixLength:(Lscala/collection/SeqLike;Lscala/Function1;)I
Method	scala/collection/SeqLike$class.prefixLength:(Lscala/collection/SeqLike;Lscala/Function1;)I
Asciz	segmentLength;
NameAndType	segmentLength:(Lscala/collection/SeqLike;Lscala/Function1;I)I
Method	scala/collection/SeqLike$class.segmentLength:(Lscala/collection/SeqLike;Lscala/Function1;I)I
Asciz	(Lscala/collection/SeqLike;I)Z;
NameAndType	isDefinedAt:(Lscala/collection/SeqLike;I)Z
Method	scala/collection/SeqLike$class.isDefinedAt:(Lscala/collection/SeqLike;I)Z
Asciz	idx;
Asciz	size;
NameAndType	size:(Lscala/collection/SeqLike;)I
Method	scala/collection/SeqLike$class.size:(Lscala/collection/SeqLike;)I
Asciz	lengthCompare;
Asciz	(I)I;
Asciz	(Lscala/collection/SeqLike;I)I;
NameAndType	lengthCompare:(Lscala/collection/SeqLike;I)I
Method	scala/collection/SeqLike$class.lengthCompare:(Lscala/collection/SeqLike;I)I
Asciz	len;
Asciz	(Lscala/collection/SeqLike;Ljava/lang/Object;)Lscala/collection/Seq;;
NameAndType	toCollection:(Lscala/collection/SeqLike;Ljava/lang/Object;)Lscala/collection/Seq;
Method	scala/collection/SeqLike$class.toCollection:(Lscala/collection/SeqLike;Ljava/lang/Object;)Lscala/collection/Seq;
NameAndType	thisCollection:(Lscala/collection/SeqLike;)Lscala/collection/Seq;
Method	scala/collection/SeqLike$class.thisCollection:(Lscala/collection/SeqLike;)Lscala/collection/Seq;
Asciz	companion;
Asciz	()Lscala/collection/generic/GenericCompanion;;
Asciz	(Lscala/collection/Seq;)Lscala/collection/generic/GenericCompanion;;
NameAndType	companion:(Lscala/collection/Seq;)Lscala/collection/generic/GenericCompanion;
Method	scala/collection/Seq$class.companion:(Lscala/collection/Seq;)Lscala/collection/generic/GenericCompanion;
Asciz	newPatched;
Asciz	(ILscala/collection/Seq;I)Lscala/collection/SeqViewLike$Transformed;;
Asciz	(Lscala/collection/SeqViewLike;ILscala/collection/Seq;I)Lscala/collection/SeqViewLike$Transformed;;
NameAndType	newPatched:(Lscala/collection/SeqViewLike;ILscala/collection/Seq;I)Lscala/collection/SeqViewLike$Transformed;
Method	scala/collection/views/SeqTransformations$class.newPatched:(Lscala/collection/SeqViewLike;ILscala/collection/Seq;I)Lscala/collection/SeqViewLike$Transformed;
Asciz	_patch;
Asciz	_replaced;
Asciz	newReversed;
Asciz	()Lscala/collection/SeqViewLike$Transformed;;
Asciz	(Lscala/collection/SeqViewLike;)Lscala/collection/SeqViewLike$Transformed;;
NameAndType	newReversed:(Lscala/collection/SeqViewLike;)Lscala/collection/SeqViewLike$Transformed;
Method	scala/collection/views/SeqTransformations$class.newReversed:(Lscala/collection/SeqViewLike;)Lscala/collection/SeqViewLike$Transformed;
Asciz	(Lscala/collection/SeqViewLike;Lscala/collection/Iterable;Ljava/lang/Object;Ljava/lang/Object;)Lscala/collection/SeqViewLike$Transformed;;
NameAndType	newZippedAll:(Lscala/collection/SeqViewLike;Lscala/collection/Iterable;Ljava/lang/Object;Ljava/lang/Object;)Lscala/collection/SeqViewLike$Transformed;
Method	scala/collection/views/SeqTransformations$class.newZippedAll:(Lscala/collection/SeqViewLike;Lscala/collection/Iterable;Ljava/lang/Object;Ljava/lang/Object;)Lscala/collection/SeqViewLike$Transformed;
Asciz	(Lscala/collection/SeqViewLike;Lscala/collection/Iterable;)Lscala/collection/SeqViewLike$Transformed;;
NameAndType	newZipped:(Lscala/collection/SeqViewLike;Lscala/collection/Iterable;)Lscala/collection/SeqViewLike$Transformed;
Method	scala/collection/views/SeqTransformations$class.newZipped:(Lscala/collection/SeqViewLike;Lscala/collection/Iterable;)Lscala/collection/SeqViewLike$Transformed;
Asciz	(Lscala/collection/SeqViewLike;Lscala/Function1;)Lscala/collection/SeqViewLike$Transformed;;
NameAndType	newTakenWhile:(Lscala/collection/SeqViewLike;Lscala/Function1;)Lscala/collection/SeqViewLike$Transformed;
Method	scala/collection/views/SeqTransformations$class.newTakenWhile:(Lscala/collection/SeqViewLike;Lscala/Function1;)Lscala/collection/SeqViewLike$Transformed;
NameAndType	newDroppedWhile:(Lscala/collection/SeqViewLike;Lscala/Function1;)Lscala/collection/SeqViewLike$Transformed;
Method	scala/collection/views/SeqTransformations$class.newDroppedWhile:(Lscala/collection/SeqViewLike;Lscala/Function1;)Lscala/collection/SeqViewLike$Transformed;
Asciz	(Lscala/collection/SeqViewLike;II)Lscala/collection/SeqViewLike$Transformed;;
NameAndType	newSliced:(Lscala/collection/SeqViewLike;II)Lscala/collection/SeqViewLike$Transformed;
Method	scala/collection/views/SeqTransformations$class.newSliced:(Lscala/collection/SeqViewLike;II)Lscala/collection/SeqViewLike$Transformed;
NameAndType	newFiltered:(Lscala/collection/SeqViewLike;Lscala/Function1;)Lscala/collection/SeqViewLike$Transformed;
Method	scala/collection/views/SeqTransformations$class.newFiltered:(Lscala/collection/SeqViewLike;Lscala/Function1;)Lscala/collection/SeqViewLike$Transformed;
NameAndType	newFlatMapped:(Lscala/collection/SeqViewLike;Lscala/Function1;)Lscala/collection/SeqViewLike$Transformed;
Method	scala/collection/views/SeqTransformations$class.newFlatMapped:(Lscala/collection/SeqViewLike;Lscala/Function1;)Lscala/collection/SeqViewLike$Transformed;
NameAndType	newMapped:(Lscala/collection/SeqViewLike;Lscala/Function1;)Lscala/collection/SeqViewLike$Transformed;
Method	scala/collection/views/SeqTransformations$class.newMapped:(Lscala/collection/SeqViewLike;Lscala/Function1;)Lscala/collection/SeqViewLike$Transformed;
Asciz	(Lscala/collection/SeqViewLike;Lscala/collection/Traversable;)Lscala/collection/SeqViewLike$Transformed;;
NameAndType	newAppended:(Lscala/collection/SeqViewLike;Lscala/collection/Traversable;)Lscala/collection/SeqViewLike$Transformed;
Method	scala/collection/views/SeqTransformations$class.newAppended:(Lscala/collection/SeqViewLike;Lscala/collection/Traversable;)Lscala/collection/SeqViewLike$Transformed;
Asciz	stringPrefix;
Asciz	(Lscala/collection/SeqViewLike;)Ljava/lang/String;;
NameAndType	stringPrefix:(Lscala/collection/SeqViewLike;)Ljava/lang/String;
Method	scala/collection/SeqViewLike$class.stringPrefix:(Lscala/collection/SeqViewLike;)Ljava/lang/String;
Asciz	reverseMap;
Asciz	(Lscala/Function1;Lscala/collection/generic/CanBuildFrom;)Ljava/lang/Object;;
Asciz	(Lscala/collection/SeqViewLike;Lscala/Function1;Lscala/collection/generic/CanBuildFrom;)Ljava/lang/Object;;
NameAndType	reverseMap:(Lscala/collection/SeqViewLike;Lscala/Function1;Lscala/collection/generic/CanBuildFrom;)Ljava/lang/Object;
Method	scala/collection/SeqViewLike$class.reverseMap:(Lscala/collection/SeqViewLike;Lscala/Function1;Lscala/collection/generic/CanBuildFrom;)Ljava/lang/Object;
Asciz	padTo;
Asciz	(Lscala/collection/SeqViewLike;ILjava/lang/Object;Lscala/collection/generic/CanBuildFrom;)Ljava/lang/Object;;
NameAndType	padTo:(Lscala/collection/SeqViewLike;ILjava/lang/Object;Lscala/collection/generic/CanBuildFrom;)Ljava/lang/Object;
Method	scala/collection/SeqViewLike$class.padTo:(Lscala/collection/SeqViewLike;ILjava/lang/Object;Lscala/collection/generic/CanBuildFrom;)Ljava/lang/Object;
Asciz	patch;
Asciz	(ILscala/collection/Seq;ILscala/collection/generic/CanBuildFrom;)Ljava/lang/Object;;
Asciz	(Lscala/collection/SeqViewLike;ILscala/collection/Seq;ILscala/collection/generic/CanBuildFrom;)Ljava/lang/Object;;
NameAndType	patch:(Lscala/collection/SeqViewLike;ILscala/collection/Seq;ILscala/collection/generic/CanBuildFrom;)Ljava/lang/Object;
Method	scala/collection/SeqViewLike$class.patch:(Lscala/collection/SeqViewLike;ILscala/collection/Seq;ILscala/collection/generic/CanBuildFrom;)Ljava/lang/Object;
Asciz	replaced;
Asciz	(Lscala/collection/SeqViewLike;)Lscala/collection/SeqView;;
NameAndType	reverse:(Lscala/collection/SeqViewLike;)Lscala/collection/SeqView;
Method	scala/collection/SeqViewLike$class.reverse:(Lscala/collection/SeqViewLike;)Lscala/collection/SeqView;
Asciz	<B:Ljava/lang/Object;Coll:Ljava/lang/Object;>Lscala/collection/views/IterableLike<TB;TColl;>;Lscala/collection/SeqView<TB;TColl;>;Lscala/ScalaObject;;
Asciz	ScalaSig;
Asciz	InnerClasses;
Asciz	scala/collection/SeqViewLike$Transformed;
class	scala/collection/SeqViewLike$Transformed
Asciz	Transformed;
Asciz	scala/collection/IterableViewLike$Transformed;
class	scala/collection/IterableViewLike$Transformed
Asciz	scala/collection/IterableViewLike;
class	scala/collection/IterableViewLike
Asciz	scala/collection/TraversableViewLike$Transformed;
class	scala/collection/TraversableViewLike$Transformed
Asciz	scala/collection/views/SeqLike;
class	scala/collection/views/SeqLike
Asciz	scala/collection/SeqView;
class	scala/collection/SeqView
Asciz	scala/ScalaObject;
class	scala/ScalaObject

{
public scala.collection.views.SeqLike();
  Signature: ()V
  Code:
   Stack=1, Locals=1, Args_size=1
	aload_0
	invokespecial	Method scala/collection/views/IterableLike."<init>":()V
	aload_0
	invokestatic	Method scala/Function1$class.$init$:(Lscala/Function1;)V
	aload_0
	invokestatic	Method scala/PartialFunction$class.$init$:(Lscala/PartialFunction;)V
	aload_0
	invokestatic	Method scala/collection/SeqLike$class.$init$:(Lscala/collection/SeqLike;)V
	aload_0
	invokestatic	Method scala/collection/Seq$class.$init$:(Lscala/collection/Seq;)V
	aload_0
	invokestatic	Method scala/collection/views/SeqTransformations$class.$init$:(Lscala/collection/SeqViewLike;)V
	aload_0
	invokestatic	Method scala/collection/SeqViewLike$class.$init$:(Lscala/collection/SeqViewLike;)V
	return
  Labels:
  Signature: length = 0x2
   00 04 

public java.lang.Object reverse();
  Signature: ()Ljava/lang/Object;
  Code:
   Stack=1, Locals=1, Args_size=1
	aload_0
	invokeinterface	InterfaceMethod scala/collection/SeqViewLike.reverse:()Lscala/collection/SeqView;
	areturn
  Labels:

public scala.collection.IterableViewLike$Transformed newAppended(scala.collection.Traversable);
  Signature: (Lscala/collection/Traversable;)Lscala/collection/IterableViewLike$Transformed;
  Code:
   Stack=2, Locals=2, Args_size=2
	aload_0
	aload_1
	invokeinterface	InterfaceMethod scala/collection/views/SeqTransformations.newAppended:(Lscala/collection/Traversable;)Lscala/collection/SeqViewLike$Transformed;
	areturn
  Labels:
  LocalVariableTable: 
   Start  Length  Slot  Name   Signature
   0      8      0    this       Lscala/collection/views/SeqLike;
   0      8      1    that       Lscala/collection/Traversable;

  Signature: length = 0x2
   00 31 

public scala.collection.TraversableViewLike$Transformed newAppended(scala.collection.Traversable);
  Signature: (Lscala/collection/Traversable;)Lscala/collection/TraversableViewLike$Transformed;
  Code:
   Stack=2, Locals=2, Args_size=2
	aload_0
	aload_1
	invokeinterface	InterfaceMethod scala/collection/views/SeqTransformations.newAppended:(Lscala/collection/Traversable;)Lscala/collection/SeqViewLike$Transformed;
	areturn
  Labels:
  LocalVariableTable: 
   Start  Length  Slot  Name   Signature
   0      8      0    this       Lscala/collection/views/SeqLike;
   0      8      1    that       Lscala/collection/Traversable;

  Signature: length = 0x2
   00 3C 

public scala.collection.IterableViewLike$Transformed newMapped(scala.Function1);
  Signature: (Lscala/Function1;)Lscala/collection/IterableViewLike$Transformed;
  Code:
   Stack=2, Locals=2, Args_size=2
	aload_0
	aload_1
	invokeinterface	InterfaceMethod scala/collection/views/SeqTransformations.newMapped:(Lscala/Function1;)Lscala/collection/SeqViewLike$Transformed;
	areturn
  Labels:
  LocalVariableTable: 
   Start  Length  Slot  Name   Signature
   0      8      0    this       Lscala/collection/views/SeqLike;
   0      8      1    f       Lscala/Function1;

  Signature: length = 0x2
   00 3E 

public scala.collection.TraversableViewLike$Transformed newMapped(scala.Function1);
  Signature: (Lscala/Function1;)Lscala/collection/TraversableViewLike$Transformed;
  Code:
   Stack=2, Locals=2, Args_size=2
	aload_0
	aload_1
	invokeinterface	InterfaceMethod scala/collection/views/SeqTransformations.newMapped:(Lscala/Function1;)Lscala/collection/SeqViewLike$Transformed;
	areturn
  Labels:
  LocalVariableTable: 
   Start  Length  Slot  Name   Signature
   0      8      0    this       Lscala/collection/views/SeqLike;
   0      8      1    f       Lscala/Function1;

  Signature: length = 0x2
   00 44 

public scala.collection.IterableViewLike$Transformed newFlatMapped(scala.Function1);
  Signature: (Lscala/Function1;)Lscala/collection/IterableViewLike$Transformed;
  Code:
   Stack=2, Locals=2, Args_size=2
	aload_0
	aload_1
	invokeinterface	InterfaceMethod scala/collection/views/SeqTransformations.newFlatMapped:(Lscala/Function1;)Lscala/collection/SeqViewLike$Transformed;
	areturn
  Labels:
  LocalVariableTable: 
   Start  Length  Slot  Name   Signature
   0      8      0    this       Lscala/collection/views/SeqLike;
   0      8      1    f       Lscala/Function1;

  Signature: length = 0x2
   00 3E 

public scala.collection.TraversableViewLike$Transformed newFlatMapped(scala.Function1);
  Signature: (Lscala/Function1;)Lscala/collection/TraversableViewLike$Transformed;
  Code:
   Stack=2, Locals=2, Args_size=2
	aload_0
	aload_1
	invokeinterface	InterfaceMethod scala/collection/views/SeqTransformations.newFlatMapped:(Lscala/Function1;)Lscala/collection/SeqViewLike$Transformed;
	areturn
  Labels:
  LocalVariableTable: 
   Start  Length  Slot  Name   Signature
   0      8      0    this       Lscala/collection/views/SeqLike;
   0      8      1    f       Lscala/Function1;

  Signature: length = 0x2
   00 44 

public scala.collection.IterableViewLike$Transformed newFiltered(scala.Function1);
  Signature: (Lscala/Function1;)Lscala/collection/IterableViewLike$Transformed;
  Code:
   Stack=2, Locals=2, Args_size=2
	aload_0
	aload_1
	invokeinterface	InterfaceMethod scala/collection/views/SeqTransformations.newFiltered:(Lscala/Function1;)Lscala/collection/SeqViewLike$Transformed;
	areturn
  Labels:
  LocalVariableTable: 
   Start  Length  Slot  Name   Signature
   0      8      0    this       Lscala/collection/views/SeqLike;
   0      8      1    p       Lscala/Function1;

  Signature: length = 0x2
   00 3E 

public scala.collection.TraversableViewLike$Transformed newFiltered(scala.Function1);
  Signature: (Lscala/Function1;)Lscala/collection/TraversableViewLike$Transformed;
  Code:
   Stack=2, Locals=2, Args_size=2
	aload_0
	aload_1
	invokeinterface	InterfaceMethod scala/collection/views/SeqTransformations.newFiltered:(Lscala/Function1;)Lscala/collection/SeqViewLike$Transformed;
	areturn
  Labels:
  LocalVariableTable: 
   Start  Length  Slot  Name   Signature
   0      8      0    this       Lscala/collection/views/SeqLike;
   0      8      1    p       Lscala/Function1;

  Signature: length = 0x2
   00 44 

public scala.collection.IterableViewLike$Transformed newSliced(int, int);
  Signature: (II)Lscala/collection/IterableViewLike$Transformed;
  Code:
   Stack=3, Locals=3, Args_size=3
	aload_0
	iload_1
	iload_2
	invokeinterface	InterfaceMethod scala/collection/views/SeqTransformations.newSliced:(II)Lscala/collection/SeqViewLike$Transformed;
	areturn
  Labels:
  LocalVariableTable: 
   Start  Length  Slot  Name   Signature
   0      9      0    this       Lscala/collection/views/SeqLike;
   0      9      1    _from       I
   0      9      2    _until       I

  Signature: length = 0x2
   00 4D 

public scala.collection.TraversableViewLike$Transformed newSliced(int, int);
  Signature: (II)Lscala/collection/TraversableViewLike$Transformed;
  Code:
   Stack=3, Locals=3, Args_size=3
	aload_0
	iload_1
	iload_2
	invokeinterface	InterfaceMethod scala/collection/views/SeqTransformations.newSliced:(II)Lscala/collection/SeqViewLike$Transformed;
	areturn
  Labels:
  LocalVariableTable: 
   Start  Length  Slot  Name   Signature
   0      9      0    this       Lscala/collection/views/SeqLike;
   0      9      1    _from       I
   0      9      2    _until       I

  Signature: length = 0x2
   00 54 

public scala.collection.IterableViewLike$Transformed newDroppedWhile(scala.Function1);
  Signature: (Lscala/Function1;)Lscala/collection/IterableViewLike$Transformed;
  Code:
   Stack=2, Locals=2, Args_size=2
	aload_0
	aload_1
	invokeinterface	InterfaceMethod scala/collection/views/SeqTransformations.newDroppedWhile:(Lscala/Function1;)Lscala/collection/SeqViewLike$Transformed;
	areturn
  Labels:
  LocalVariableTable: 
   Start  Length  Slot  Name   Signature
   0      8      0    this       Lscala/collection/views/SeqLike;
   0      8      1    p       Lscala/Function1;

  Signature: length = 0x2
   00 3E 

public scala.collection.TraversableViewLike$Transformed newDroppedWhile(scala.Function1);
  Signature: (Lscala/Function1;)Lscala/collection/TraversableViewLike$Transformed;
  Code:
   Stack=2, Locals=2, Args_size=2
	aload_0
	aload_1
	invokeinterface	InterfaceMethod scala/collection/views/SeqTransformations.newDroppedWhile:(Lscala/Function1;)Lscala/collection/SeqViewLike$Transformed;
	areturn
  Labels:
  LocalVariableTable: 
   Start  Length  Slot  Name   Signature
   0      8      0    this       Lscala/collection/views/SeqLike;
   0      8      1    p       Lscala/Function1;

  Signature: length = 0x2
   00 44 

public scala.collection.IterableViewLike$Transformed newTakenWhile(scala.Function1);
  Signature: (Lscala/Function1;)Lscala/collection/IterableViewLike$Transformed;
  Code:
   Stack=2, Locals=2, Args_size=2
	aload_0
	aload_1
	invokeinterface	InterfaceMethod scala/collection/views/SeqTransformations.newTakenWhile:(Lscala/Function1;)Lscala/collection/SeqViewLike$Transformed;
	areturn
  Labels:
  LocalVariableTable: 
   Start  Length  Slot  Name   Signature
   0      8      0    this       Lscala/collection/views/SeqLike;
   0      8      1    p       Lscala/Function1;

  Signature: length = 0x2
   00 3E 

public scala.collection.TraversableViewLike$Transformed newTakenWhile(scala.Function1);
  Signature: (Lscala/Function1;)Lscala/collection/TraversableViewLike$Transformed;
  Code:
   Stack=2, Locals=2, Args_size=2
	aload_0
	aload_1
	invokeinterface	InterfaceMethod scala/collection/views/SeqTransformations.newTakenWhile:(Lscala/Function1;)Lscala/collection/SeqViewLike$Transformed;
	areturn
  Labels:
  LocalVariableTable: 
   Start  Length  Slot  Name   Signature
   0      8      0    this       Lscala/collection/views/SeqLike;
   0      8      1    p       Lscala/Function1;

  Signature: length = 0x2
   00 44 

public scala.collection.IterableViewLike$Transformed newZipped(scala.collection.Iterable);
  Signature: (Lscala/collection/Iterable;)Lscala/collection/IterableViewLike$Transformed;
  Code:
   Stack=2, Locals=2, Args_size=2
	aload_0
	aload_1
	invokeinterface	InterfaceMethod scala/collection/views/SeqTransformations.newZipped:(Lscala/collection/Iterable;)Lscala/collection/SeqViewLike$Transformed;
	areturn
  Labels:
  LocalVariableTable: 
   Start  Length  Slot  Name   Signature
   0      8      0    this       Lscala/collection/views/SeqLike;
   0      8      1    that       Lscala/collection/Iterable;

  Signature: length = 0x2
   00 5C 

public scala.collection.IterableViewLike$Transformed newZippedAll(scala.collection.Iterable, java.lang.Object, java.lang.Object);
  Signature: (Lscala/collection/Iterable;Ljava/lang/Object;Ljava/lang/Object;)Lscala/collection/IterableViewLike$Transformed;
  Code:
   Stack=4, Locals=4, Args_size=4
	aload_0
	aload_1
	aload_2
	aload_3
	invokeinterface	InterfaceMethod scala/collection/views/SeqTransformations.newZippedAll:(Lscala/collection/Iterable;Ljava/lang/Object;Ljava/lang/Object;)Lscala/collection/SeqViewLike$Transformed;
	areturn
  Labels:
  LocalVariableTable: 
   Start  Length  Slot  Name   Signature
   0      10      0    this       Lscala/collection/views/SeqLike;
   0      10      1    that       Lscala/collection/Iterable;
   0      10      2    _thisElem       Ljava/lang/Object;
   0      10      3    _thatElem       Ljava/lang/Object;

  Signature: length = 0x2
   00 62 

public scala.collection.Iterable thisCollection();
  Signature: ()Lscala/collection/Iterable;
  Code:
   Stack=1, Locals=1, Args_size=1
	aload_0
	invokeinterface	InterfaceMethod scala/collection/SeqLike.thisCollection:()Lscala/collection/Seq;
	areturn
  Labels:

public scala.collection.Traversable thisCollection();
  Signature: ()Lscala/collection/Traversable;
  Code:
   Stack=1, Locals=1, Args_size=1
	aload_0
	invokeinterface	InterfaceMethod scala/collection/SeqLike.thisCollection:()Lscala/collection/Seq;
	areturn
  Labels:

public scala.collection.Iterable toCollection(java.lang.Object);
  Signature: (Ljava/lang/Object;)Lscala/collection/Iterable;
  Code:
   Stack=2, Locals=2, Args_size=2
	aload_0
	aload_1
	invokeinterface	InterfaceMethod scala/collection/SeqLike.toCollection:(Ljava/lang/Object;)Lscala/collection/Seq;
	areturn
  Labels:
  LocalVariableTable: 
   Start  Length  Slot  Name   Signature
   0      8      0    this       Lscala/collection/views/SeqLike;
   0      8      1    repr       Ljava/lang/Object;


public scala.collection.Traversable toCollection(java.lang.Object);
  Signature: (Ljava/lang/Object;)Lscala/collection/Traversable;
  Code:
   Stack=2, Locals=2, Args_size=2
	aload_0
	aload_1
	invokeinterface	InterfaceMethod scala/collection/SeqLike.toCollection:(Ljava/lang/Object;)Lscala/collection/Seq;
	areturn
  Labels:
  LocalVariableTable: 
   Start  Length  Slot  Name   Signature
   0      8      0    this       Lscala/collection/views/SeqLike;
   0      8      1    repr       Ljava/lang/Object;


public boolean isDefinedAt(java.lang.Object);
  Signature: (Ljava/lang/Object;)Z
  Code:
   Stack=2, Locals=2, Args_size=2
	aload_0
	aload_1
	invokestatic	Method scala/runtime/BoxesRunTime.unboxToInt:(Ljava/lang/Object;)I
	invokeinterface	InterfaceMethod scala/collection/SeqLike.isDefinedAt:(I)Z
	ireturn
  Labels:
  LocalVariableTable: 
   Start  Length  Slot  Name   Signature
   0      11      0    this       Lscala/collection/views/SeqLike;
   0      11      1    x       Ljava/lang/Object;


public scala.collection.IterableView view();
  Signature: ()Lscala/collection/IterableView;
  Code:
   Stack=1, Locals=1, Args_size=1
	aload_0
	invokeinterface	InterfaceMethod scala/collection/SeqLike.view:()Lscala/collection/SeqView;
	areturn
  Labels:

public scala.collection.TraversableView view();
  Signature: ()Lscala/collection/TraversableView;
  Code:
   Stack=1, Locals=1, Args_size=1
	aload_0
	invokeinterface	InterfaceMethod scala/collection/SeqLike.view:()Lscala/collection/SeqView;
	areturn
  Labels:

public scala.collection.IterableView view(int, int);
  Signature: (II)Lscala/collection/IterableView;
  Code:
   Stack=3, Locals=3, Args_size=3
	aload_0
	iload_1
	iload_2
	invokeinterface	InterfaceMethod scala/collection/SeqLike.view:(II)Lscala/collection/SeqView;
	areturn
  Labels:
  LocalVariableTable: 
   Start  Length  Slot  Name   Signature
   0      9      0    this       Lscala/collection/views/SeqLike;
   0      9      1    from       I
   0      9      2    until       I


public scala.collection.TraversableView view(int, int);
  Signature: (II)Lscala/collection/TraversableView;
  Code:
   Stack=3, Locals=3, Args_size=3
	aload_0
	iload_1
	iload_2
	invokeinterface	InterfaceMethod scala/collection/SeqLike.view:(II)Lscala/collection/SeqView;
	areturn
  Labels:
  LocalVariableTable: 
   Start  Length  Slot  Name   Signature
   0      9      0    this       Lscala/collection/views/SeqLike;
   0      9      1    from       I
   0      9      2    until       I


public scala.collection.IterableView projection();
  Signature: ()Lscala/collection/IterableView;
  Code:
   Stack=1, Locals=1, Args_size=1
	aload_0
	invokeinterface	InterfaceMethod scala/collection/SeqLike.projection:()Lscala/collection/SeqView;
	areturn
  Labels:

public scala.Function1 andThen(scala.Function1);
  Signature: (Lscala/Function1;)Lscala/Function1;
  Code:
   Stack=2, Locals=2, Args_size=2
	aload_0
	aload_1
	invokeinterface	InterfaceMethod scala/PartialFunction.andThen:(Lscala/Function1;)Lscala/PartialFunction;
	areturn
  Labels:
  LocalVariableTable: 
   Start  Length  Slot  Name   Signature
   0      8      0    this       Lscala/collection/views/SeqLike;
   0      8      1    g       Lscala/Function1;


public scala.collection.TraversableView take(int);
  Signature: (I)Lscala/collection/TraversableView;
  Code:
   Stack=2, Locals=2, Args_size=2
	aload_0
	iload_1
	invokeinterface	InterfaceMethod scala/collection/IterableLike.take:(I)Ljava/lang/Object;
	checkcast	class scala/collection/TraversableView
	areturn
  Labels:
  LocalVariableTable: 
   Start  Length  Slot  Name   Signature
   0      11      0    this       Lscala/collection/views/SeqLike;
   0      11      1    n       I


public scala.collection.TraversableView slice(int, int);
  Signature: (II)Lscala/collection/TraversableView;
  Code:
   Stack=3, Locals=3, Args_size=3
	aload_0
	iload_1
	iload_2
	invokeinterface	InterfaceMethod scala/collection/IterableLike.slice:(II)Ljava/lang/Object;
	checkcast	class scala/collection/TraversableView
	areturn
  Labels:
  LocalVariableTable: 
   Start  Length  Slot  Name   Signature
   0      12      0    this       Lscala/collection/views/SeqLike;
   0      12      1    from       I
   0      12      2    until       I


public scala.collection.TraversableView takeWhile(scala.Function1);
  Signature: (Lscala/Function1;)Lscala/collection/TraversableView;
  Code:
   Stack=2, Locals=2, Args_size=2
	aload_0
	aload_1
	invokeinterface	InterfaceMethod scala/collection/IterableLike.takeWhile:(Lscala/Function1;)Ljava/lang/Object;
	checkcast	class scala/collection/TraversableView
	areturn
  Labels:
  LocalVariableTable: 
   Start  Length  Slot  Name   Signature
   0      11      0    this       Lscala/collection/views/SeqLike;
   0      11      1    p       Lscala/Function1;


public java.lang.Object filter(scala.Function1);
  Signature: (Lscala/Function1;)Ljava/lang/Object;
  Code:
   Stack=2, Locals=2, Args_size=2
	aload_0
	aload_1
	invokeinterface	InterfaceMethod scala/collection/TraversableViewLike.filter:(Lscala/Function1;)Lscala/collection/TraversableView;
	areturn
  Labels:
  LocalVariableTable: 
   Start  Length  Slot  Name   Signature
   0      8      0    this       Lscala/collection/views/SeqLike;
   0      8      1    p       Lscala/Function1;


public java.lang.Object init();
  Signature: ()Ljava/lang/Object;
  Code:
   Stack=1, Locals=1, Args_size=1
	aload_0
	invokeinterface	InterfaceMethod scala/collection/TraversableViewLike.init:()Lscala/collection/TraversableView;
	areturn
  Labels:

public java.lang.Object drop(int);
  Signature: (I)Ljava/lang/Object;
  Code:
   Stack=2, Locals=2, Args_size=2
	aload_0
	iload_1
	invokeinterface	InterfaceMethod scala/collection/TraversableViewLike.drop:(I)Lscala/collection/TraversableView;
	areturn
  Labels:
  LocalVariableTable: 
   Start  Length  Slot  Name   Signature
   0      8      0    this       Lscala/collection/views/SeqLike;
   0      8      1    n       I


public java.lang.Object dropWhile(scala.Function1);
  Signature: (Lscala/Function1;)Ljava/lang/Object;
  Code:
   Stack=2, Locals=2, Args_size=2
	aload_0
	aload_1
	invokeinterface	InterfaceMethod scala/collection/TraversableViewLike.dropWhile:(Lscala/Function1;)Lscala/collection/TraversableView;
	areturn
  Labels:
  LocalVariableTable: 
   Start  Length  Slot  Name   Signature
   0      8      0    this       Lscala/collection/views/SeqLike;
   0      8      1    p       Lscala/Function1;


public abstract java.lang.Object apply(int);
  Signature: (I)Ljava/lang/Object;
  Signature: length = 0x2
   00 FFFFFFBD 

public abstract int length();
  Signature: ()I

public scala.Function1 compose(scala.Function1);
  Signature: (Lscala/Function1;)Lscala/Function1;
  Code:
   Stack=2, Locals=2, Args_size=2
	aload_0
	aload_1
	invokestatic	Method scala/Function1$class.compose:(Lscala/Function1;Lscala/Function1;)Lscala/Function1;
	areturn
  Labels:
  LocalVariableTable: 
   Start  Length  Slot  Name   Signature
   0      6      0    this       Lscala/collection/views/SeqLike;
   0      6      1    g       Lscala/Function1;


public scala.Function1 lift();
  Signature: ()Lscala/Function1;
  Code:
   Stack=1, Locals=1, Args_size=1
	aload_0
	invokestatic	Method scala/PartialFunction$class.lift:(Lscala/PartialFunction;)Lscala/Function1;
	areturn
  Labels:

public scala.PartialFunction andThen(scala.Function1);
  Signature: (Lscala/Function1;)Lscala/PartialFunction;
  Code:
   Stack=2, Locals=2, Args_size=2
	aload_0
	aload_1
	invokestatic	Method scala/PartialFunction$class.andThen:(Lscala/PartialFunction;Lscala/Function1;)Lscala/PartialFunction;
	areturn
  Labels:
  LocalVariableTable: 
   Start  Length  Slot  Name   Signature
   0      6      0    this       Lscala/collection/views/SeqLike;
   0      6      1    k       Lscala/Function1;


public scala.PartialFunction orElse(scala.PartialFunction);
  Signature: (Lscala/PartialFunction;)Lscala/PartialFunction;
  Code:
   Stack=2, Locals=2, Args_size=2
	aload_0
	aload_1
	invokestatic	Method scala/PartialFunction$class.orElse:(Lscala/PartialFunction;Lscala/PartialFunction;)Lscala/PartialFunction;
	areturn
  Labels:
  LocalVariableTable: 
   Start  Length  Slot  Name   Signature
   0      6      0    this       Lscala/collection/views/SeqLike;
   0      6      1    that       Lscala/PartialFunction;


public scala.collection.SeqView projection();
  Signature: ()Lscala/collection/SeqView;
  Code:
   Stack=1, Locals=1, Args_size=1
	aload_0
	invokestatic	Method scala/collection/SeqLike$class.projection:(Lscala/collection/SeqLike;)Lscala/collection/SeqView;
	areturn
  Labels:
  Deprecated: true

public boolean equalsWith(scala.collection.Seq, scala.Function2);
  Signature: (Lscala/collection/Seq;Lscala/Function2;)Z
  Code:
   Stack=3, Locals=3, Args_size=3
	aload_0
	aload_1
	aload_2
	invokestatic	Method scala/collection/SeqLike$class.equalsWith:(Lscala/collection/SeqLike;Lscala/collection/Seq;Lscala/Function2;)Z
	ireturn
  Labels:
  LocalVariableTable: 
   Start  Length  Slot  Name   Signature
   0      7      0    this       Lscala/collection/views/SeqLike;
   0      7      1    that       Lscala/collection/Seq;
   0      7      2    f       Lscala/Function2;

  Deprecated: true

public int findLastIndexOf(scala.Function1);
  Signature: (Lscala/Function1;)I
  Code:
   Stack=2, Locals=2, Args_size=2
	aload_0
	aload_1
	invokestatic	Method scala/collection/SeqLike$class.findLastIndexOf:(Lscala/collection/SeqLike;Lscala/Function1;)I
	ireturn
  Labels:
  LocalVariableTable: 
   Start  Length  Slot  Name   Signature
   0      6      0    this       Lscala/collection/views/SeqLike;
   0      6      1    p       Lscala/Function1;


public java.lang.String toString();
  Signature: ()Ljava/lang/String;
  Code:
   Stack=1, Locals=1, Args_size=1
	aload_0
	invokestatic	Method scala/collection/SeqLike$class.toString:(Lscala/collection/SeqLike;)Ljava/lang/String;
	areturn
  Labels:

public boolean equals(java.lang.Object);
  Signature: (Ljava/lang/Object;)Z
  Code:
   Stack=2, Locals=2, Args_size=2
	aload_0
	aload_1
	invokestatic	Method scala/collection/SeqLike$class.equals:(Lscala/collection/SeqLike;Ljava/lang/Object;)Z
	ireturn
  Labels:
  LocalVariableTable: 
   Start  Length  Slot  Name   Signature
   0      6      0    this       Lscala/collection/views/SeqLike;
   0      6      1    that       Ljava/lang/Object;


public int hashCode();
  Signature: ()I
  Code:
   Stack=1, Locals=1, Args_size=1
	aload_0
	invokestatic	Method scala/collection/SeqLike$class.hashCode:(Lscala/collection/SeqLike;)I
	ireturn
  Labels:

public scala.collection.SeqView view(int, int);
  Signature: (II)Lscala/collection/SeqView;
  Code:
   Stack=3, Locals=3, Args_size=3
	aload_0
	iload_1
	iload_2
	invokestatic	Method scala/collection/SeqLike$class.view:(Lscala/collection/SeqLike;II)Lscala/collection/SeqView;
	areturn
  Labels:
  LocalVariableTable: 
   Start  Length  Slot  Name   Signature
   0      7      0    this       Lscala/collection/views/SeqLike;
   0      7      1    from       I
   0      7      2    until       I


public scala.collection.SeqView view();
  Signature: ()Lscala/collection/SeqView;
  Code:
   Stack=1, Locals=1, Args_size=1
	aload_0
	invokestatic	Method scala/collection/SeqLike$class.view:(Lscala/collection/SeqLike;)Lscala/collection/SeqView;
	areturn
  Labels:

public scala.collection.immutable.Range indices();
  Signature: ()Lscala/collection/immutable/Range;
  Code:
   Stack=1, Locals=1, Args_size=1
	aload_0
	invokestatic	Method scala/collection/SeqLike$class.indices:(Lscala/collection/SeqLike;)Lscala/collection/immutable/Range;
	areturn
  Labels:

public scala.collection.Seq toSeq();
  Signature: ()Lscala/collection/Seq;
  Code:
   Stack=1, Locals=1, Args_size=1
	aload_0
	invokestatic	Method scala/collection/SeqLike$class.toSeq:(Lscala/collection/SeqLike;)Lscala/collection/Seq;
	areturn
  Labels:

public java.lang.Object sortBy(scala.Function1, scala.math.Ordering);
  Signature: (Lscala/Function1;Lscala/math/Ordering;)Ljava/lang/Object;
  Code:
   Stack=3, Locals=3, Args_size=3
	aload_0
	aload_1
	aload_2
	invokestatic	Method scala/collection/SeqLike$class.sortBy:(Lscala/collection/SeqLike;Lscala/Function1;Lscala/math/Ordering;)Ljava/lang/Object;
	areturn
  Labels:
  LocalVariableTable: 
   Start  Length  Slot  Name   Signature
   0      7      0    this       Lscala/collection/views/SeqLike;
   0      7      1    f       Lscala/Function1;
   0      7      2    ord       Lscala/math/Ordering;


public java.lang.Object sortWith(scala.math.Ordering);
  Signature: (Lscala/math/Ordering;)Ljava/lang/Object;
  Code:
   Stack=2, Locals=2, Args_size=2
	aload_0
	aload_1
	invokestatic	Method scala/collection/SeqLike$class.sortWith:(Lscala/collection/SeqLike;Lscala/math/Ordering;)Ljava/lang/Object;
	areturn
  Labels:
  LocalVariableTable: 
   Start  Length  Slot  Name   Signature
   0      6      0    this       Lscala/collection/views/SeqLike;
   0      6      1    ord       Lscala/math/Ordering;


public java.lang.Object sortWith(scala.Function2);
  Signature: (Lscala/Function2;)Ljava/lang/Object;
  Code:
   Stack=2, Locals=2, Args_size=2
	aload_0
	aload_1
	invokestatic	Method scala/collection/SeqLike$class.sortWith:(Lscala/collection/SeqLike;Lscala/Function2;)Ljava/lang/Object;
	areturn
  Labels:
  LocalVariableTable: 
   Start  Length  Slot  Name   Signature
   0      6      0    this       Lscala/collection/views/SeqLike;
   0      6      1    lt       Lscala/Function2;


public boolean corresponds(scala.collection.Seq, scala.Function2);
  Signature: (Lscala/collection/Seq;Lscala/Function2;)Z
  Code:
   Stack=3, Locals=3, Args_size=3
	aload_0
	aload_1
	aload_2
	invokestatic	Method scala/collection/SeqLike$class.corresponds:(Lscala/collection/SeqLike;Lscala/collection/Seq;Lscala/Function2;)Z
	ireturn
  Labels:
  LocalVariableTable: 
   Start  Length  Slot  Name   Signature
   0      7      0    this       Lscala/collection/views/SeqLike;
   0      7      1    that       Lscala/collection/Seq;
   0      7      2    p       Lscala/Function2;


public java.lang.Object $colon$plus(java.lang.Object, scala.collection.generic.CanBuildFrom);
  Signature: (Ljava/lang/Object;Lscala/collection/generic/CanBuildFrom;)Ljava/lang/Object;
  Code:
   Stack=3, Locals=3, Args_size=3
	aload_0
	aload_1
	aload_2
	invokestatic	Method scala/collection/SeqLike$class.$colon$plus:(Lscala/collection/SeqLike;Ljava/lang/Object;Lscala/collection/generic/CanBuildFrom;)Ljava/lang/Object;
	areturn
  Labels:
  LocalVariableTable: 
   Start  Length  Slot  Name   Signature
   0      7      0    this       Lscala/collection/views/SeqLike;
   0      7      1    elem       Ljava/lang/Object;
   0      7      2    bf       Lscala/collection/generic/CanBuildFrom;


public java.lang.Object $plus$colon(java.lang.Object, scala.collection.generic.CanBuildFrom);
  Signature: (Ljava/lang/Object;Lscala/collection/generic/CanBuildFrom;)Ljava/lang/Object;
  Code:
   Stack=3, Locals=3, Args_size=3
	aload_0
	aload_1
	aload_2
	invokestatic	Method scala/collection/SeqLike$class.$plus$colon:(Lscala/collection/SeqLike;Ljava/lang/Object;Lscala/collection/generic/CanBuildFrom;)Ljava/lang/Object;
	areturn
  Labels:
  LocalVariableTable: 
   Start  Length  Slot  Name   Signature
   0      7      0    this       Lscala/collection/views/SeqLike;
   0      7      1    elem       Ljava/lang/Object;
   0      7      2    bf       Lscala/collection/generic/CanBuildFrom;


public java.lang.Object updated(int, java.lang.Object, scala.collection.generic.CanBuildFrom);
  Signature: (ILjava/lang/Object;Lscala/collection/generic/CanBuildFrom;)Ljava/lang/Object;
  Code:
   Stack=4, Locals=4, Args_size=4
	aload_0
	iload_1
	aload_2
	aload_3
	invokestatic	Method scala/collection/SeqLike$class.updated:(Lscala/collection/SeqLike;ILjava/lang/Object;Lscala/collection/generic/CanBuildFrom;)Ljava/lang/Object;
	areturn
  Labels:
  LocalVariableTable: 
   Start  Length  Slot  Name   Signature
   0      8      0    this       Lscala/collection/views/SeqLike;
   0      8      1    index       I
   0      8      2    elem       Ljava/lang/Object;
   0      8      3    bf       Lscala/collection/generic/CanBuildFrom;


public java.lang.Object removeDuplicates();
  Signature: ()Ljava/lang/Object;
  Code:
   Stack=1, Locals=1, Args_size=1
	aload_0
	invokestatic	Method scala/collection/SeqLike$class.removeDuplicates:(Lscala/collection/SeqLike;)Ljava/lang/Object;
	areturn
  Labels:

public java.lang.Object intersect(scala.collection.Seq);
  Signature: (Lscala/collection/Seq;)Ljava/lang/Object;
  Code:
   Stack=2, Locals=2, Args_size=2
	aload_0
	aload_1
	invokestatic	Method scala/collection/SeqLike$class.intersect:(Lscala/collection/SeqLike;Lscala/collection/Seq;)Ljava/lang/Object;
	areturn
  Labels:
  LocalVariableTable: 
   Start  Length  Slot  Name   Signature
   0      6      0    this       Lscala/collection/views/SeqLike;
   0      6      1    that       Lscala/collection/Seq;


public java.lang.Object diff(scala.collection.Seq);
  Signature: (Lscala/collection/Seq;)Ljava/lang/Object;
  Code:
   Stack=2, Locals=2, Args_size=2
	aload_0
	aload_1
	invokestatic	Method scala/collection/SeqLike$class.diff:(Lscala/collection/SeqLike;Lscala/collection/Seq;)Ljava/lang/Object;
	areturn
  Labels:
  LocalVariableTable: 
   Start  Length  Slot  Name   Signature
   0      6      0    this       Lscala/collection/views/SeqLike;
   0      6      1    that       Lscala/collection/Seq;


public java.lang.Object union(scala.collection.Seq, scala.collection.generic.CanBuildFrom);
  Signature: (Lscala/collection/Seq;Lscala/collection/generic/CanBuildFrom;)Ljava/lang/Object;
  Code:
   Stack=3, Locals=3, Args_size=3
	aload_0
	aload_1
	aload_2
	invokestatic	Method scala/collection/SeqLike$class.union:(Lscala/collection/SeqLike;Lscala/collection/Seq;Lscala/collection/generic/CanBuildFrom;)Ljava/lang/Object;
	areturn
  Labels:
  LocalVariableTable: 
   Start  Length  Slot  Name   Signature
   0      7      0    this       Lscala/collection/views/SeqLike;
   0      7      1    that       Lscala/collection/Seq;
   0      7      2    bf       Lscala/collection/generic/CanBuildFrom;


public boolean contains(java.lang.Object);
  Signature: (Ljava/lang/Object;)Z
  Code:
   Stack=2, Locals=2, Args_size=2
	aload_0
	aload_1
	invokestatic	Method scala/collection/SeqLike$class.contains:(Lscala/collection/SeqLike;Ljava/lang/Object;)Z
	ireturn
  Labels:
  LocalVariableTable: 
   Start  Length  Slot  Name   Signature
   0      6      0    this       Lscala/collection/views/SeqLike;
   0      6      1    elem       Ljava/lang/Object;


public boolean containsSlice(scala.collection.Seq);
  Signature: (Lscala/collection/Seq;)Z
  Code:
   Stack=2, Locals=2, Args_size=2
	aload_0
	aload_1
	invokestatic	Method scala/collection/SeqLike$class.containsSlice:(Lscala/collection/SeqLike;Lscala/collection/Seq;)Z
	ireturn
  Labels:
  LocalVariableTable: 
   Start  Length  Slot  Name   Signature
   0      6      0    this       Lscala/collection/views/SeqLike;
   0      6      1    that       Lscala/collection/Seq;


public int lastIndexOfSlice(scala.collection.Seq, int);
  Signature: (Lscala/collection/Seq;I)I
  Code:
   Stack=3, Locals=3, Args_size=3
	aload_0
	aload_1
	iload_2
	invokestatic	Method scala/collection/SeqLike$class.lastIndexOfSlice:(Lscala/collection/SeqLike;Lscala/collection/Seq;I)I
	ireturn
  Labels:
  LocalVariableTable: 
   Start  Length  Slot  Name   Signature
   0      7      0    this       Lscala/collection/views/SeqLike;
   0      7      1    that       Lscala/collection/Seq;
   0      7      2    end       I


public int lastIndexOfSlice(scala.collection.Seq);
  Signature: (Lscala/collection/Seq;)I
  Code:
   Stack=2, Locals=2, Args_size=2
	aload_0
	aload_1
	invokestatic	Method scala/collection/SeqLike$class.lastIndexOfSlice:(Lscala/collection/SeqLike;Lscala/collection/Seq;)I
	ireturn
  Labels:
  LocalVariableTable: 
   Start  Length  Slot  Name   Signature
   0      6      0    this       Lscala/collection/views/SeqLike;
   0      6      1    that       Lscala/collection/Seq;


public int indexOfSlice(scala.collection.Seq, int);
  Signature: (Lscala/collection/Seq;I)I
  Code:
   Stack=3, Locals=3, Args_size=3
	aload_0
	aload_1
	iload_2
	invokestatic	Method scala/collection/SeqLike$class.indexOfSlice:(Lscala/collection/SeqLike;Lscala/collection/Seq;I)I
	ireturn
  Labels:
  LocalVariableTable: 
   Start  Length  Slot  Name   Signature
   0      7      0    this       Lscala/collection/views/SeqLike;
   0      7      1    that       Lscala/collection/Seq;
   0      7      2    from       I


public int indexOfSlice(scala.collection.Seq);
  Signature: (Lscala/collection/Seq;)I
  Code:
   Stack=2, Locals=2, Args_size=2
	aload_0
	aload_1
	invokestatic	Method scala/collection/SeqLike$class.indexOfSlice:(Lscala/collection/SeqLike;Lscala/collection/Seq;)I
	ireturn
  Labels:
  LocalVariableTable: 
   Start  Length  Slot  Name   Signature
   0      6      0    this       Lscala/collection/views/SeqLike;
   0      6      1    that       Lscala/collection/Seq;


public boolean endsWith(scala.collection.Seq);
  Signature: (Lscala/collection/Seq;)Z
  Code:
   Stack=2, Locals=2, Args_size=2
	aload_0
	aload_1
	invokestatic	Method scala/collection/SeqLike$class.endsWith:(Lscala/collection/SeqLike;Lscala/collection/Seq;)Z
	ireturn
  Labels:
  LocalVariableTable: 
   Start  Length  Slot  Name   Signature
   0      6      0    this       Lscala/collection/views/SeqLike;
   0      6      1    that       Lscala/collection/Seq;


public boolean startsWith(scala.collection.Seq);
  Signature: (Lscala/collection/Seq;)Z
  Code:
   Stack=2, Locals=2, Args_size=2
	aload_0
	aload_1
	invokestatic	Method scala/collection/SeqLike$class.startsWith:(Lscala/collection/SeqLike;Lscala/collection/Seq;)Z
	ireturn
  Labels:
  LocalVariableTable: 
   Start  Length  Slot  Name   Signature
   0      6      0    this       Lscala/collection/views/SeqLike;
   0      6      1    that       Lscala/collection/Seq;


public boolean startsWith(scala.collection.Seq, int);
  Signature: (Lscala/collection/Seq;I)Z
  Code:
   Stack=3, Locals=3, Args_size=3
	aload_0
	aload_1
	iload_2
	invokestatic	Method scala/collection/SeqLike$class.startsWith:(Lscala/collection/SeqLike;Lscala/collection/Seq;I)Z
	ireturn
  Labels:
  LocalVariableTable: 
   Start  Length  Slot  Name   Signature
   0      7      0    this       Lscala/collection/views/SeqLike;
   0      7      1    that       Lscala/collection/Seq;
   0      7      2    offset       I


public scala.collection.Iterator reversedElements();
  Signature: ()Lscala/collection/Iterator;
  Code:
   Stack=1, Locals=1, Args_size=1
	aload_0
	invokestatic	Method scala/collection/SeqLike$class.reversedElements:(Lscala/collection/SeqLike;)Lscala/collection/Iterator;
	areturn
  Labels:
  Deprecated: true

public scala.collection.Iterator reverseIterator();
  Signature: ()Lscala/collection/Iterator;
  Code:
   Stack=1, Locals=1, Args_size=1
	aload_0
	invokestatic	Method scala/collection/SeqLike$class.reverseIterator:(Lscala/collection/SeqLike;)Lscala/collection/Iterator;
	areturn
  Labels:

public int lastIndexWhere(scala.Function1, int);
  Signature: (Lscala/Function1;I)I
  Code:
   Stack=3, Locals=3, Args_size=3
	aload_0
	aload_1
	iload_2
	invokestatic	Method scala/collection/SeqLike$class.lastIndexWhere:(Lscala/collection/SeqLike;Lscala/Function1;I)I
	ireturn
  Labels:
  LocalVariableTable: 
   Start  Length  Slot  Name   Signature
   0      7      0    this       Lscala/collection/views/SeqLike;
   0      7      1    p       Lscala/Function1;
   0      7      2    end       I


public int lastIndexWhere(scala.Function1);
  Signature: (Lscala/Function1;)I
  Code:
   Stack=2, Locals=2, Args_size=2
	aload_0
	aload_1
	invokestatic	Method scala/collection/SeqLike$class.lastIndexWhere:(Lscala/collection/SeqLike;Lscala/Function1;)I
	ireturn
  Labels:
  LocalVariableTable: 
   Start  Length  Slot  Name   Signature
   0      6      0    this       Lscala/collection/views/SeqLike;
   0      6      1    p       Lscala/Function1;


public int lastIndexOf(java.lang.Object, int);
  Signature: (Ljava/lang/Object;I)I
  Code:
   Stack=3, Locals=3, Args_size=3
	aload_0
	aload_1
	iload_2
	invokestatic	Method scala/collection/SeqLike$class.lastIndexOf:(Lscala/collection/SeqLike;Ljava/lang/Object;I)I
	ireturn
  Labels:
  LocalVariableTable: 
   Start  Length  Slot  Name   Signature
   0      7      0    this       Lscala/collection/views/SeqLike;
   0      7      1    elem       Ljava/lang/Object;
   0      7      2    end       I


public int lastIndexOf(java.lang.Object);
  Signature: (Ljava/lang/Object;)I
  Code:
   Stack=2, Locals=2, Args_size=2
	aload_0
	aload_1
	invokestatic	Method scala/collection/SeqLike$class.lastIndexOf:(Lscala/collection/SeqLike;Ljava/lang/Object;)I
	ireturn
  Labels:
  LocalVariableTable: 
   Start  Length  Slot  Name   Signature
   0      6      0    this       Lscala/collection/views/SeqLike;
   0      6      1    elem       Ljava/lang/Object;


public int indexOf(java.lang.Object, int);
  Signature: (Ljava/lang/Object;I)I
  Code:
   Stack=3, Locals=3, Args_size=3
	aload_0
	aload_1
	iload_2
	invokestatic	Method scala/collection/SeqLike$class.indexOf:(Lscala/collection/SeqLike;Ljava/lang/Object;I)I
	ireturn
  Labels:
  LocalVariableTable: 
   Start  Length  Slot  Name   Signature
   0      7      0    this       Lscala/collection/views/SeqLike;
   0      7      1    elem       Ljava/lang/Object;
   0      7      2    from       I


public int indexOf(java.lang.Object);
  Signature: (Ljava/lang/Object;)I
  Code:
   Stack=2, Locals=2, Args_size=2
	aload_0
	aload_1
	invokestatic	Method scala/collection/SeqLike$class.indexOf:(Lscala/collection/SeqLike;Ljava/lang/Object;)I
	ireturn
  Labels:
  LocalVariableTable: 
   Start  Length  Slot  Name   Signature
   0      6      0    this       Lscala/collection/views/SeqLike;
   0      6      1    elem       Ljava/lang/Object;


public int findIndexOf(scala.Function1);
  Signature: (Lscala/Function1;)I
  Code:
   Stack=2, Locals=2, Args_size=2
	aload_0
	aload_1
	invokestatic	Method scala/collection/SeqLike$class.findIndexOf:(Lscala/collection/SeqLike;Lscala/Function1;)I
	ireturn
  Labels:
  LocalVariableTable: 
   Start  Length  Slot  Name   Signature
   0      6      0    this       Lscala/collection/views/SeqLike;
   0      6      1    p       Lscala/Function1;


public int indexWhere(scala.Function1, int);
  Signature: (Lscala/Function1;I)I
  Code:
   Stack=3, Locals=3, Args_size=3
	aload_0
	aload_1
	iload_2
	invokestatic	Method scala/collection/SeqLike$class.indexWhere:(Lscala/collection/SeqLike;Lscala/Function1;I)I
	ireturn
  Labels:
  LocalVariableTable: 
   Start  Length  Slot  Name   Signature
   0      7      0    this       Lscala/collection/views/SeqLike;
   0      7      1    p       Lscala/Function1;
   0      7      2    from       I


public int indexWhere(scala.Function1);
  Signature: (Lscala/Function1;)I
  Code:
   Stack=2, Locals=2, Args_size=2
	aload_0
	aload_1
	invokestatic	Method scala/collection/SeqLike$class.indexWhere:(Lscala/collection/SeqLike;Lscala/Function1;)I
	ireturn
  Labels:
  LocalVariableTable: 
   Start  Length  Slot  Name   Signature
   0      6      0    this       Lscala/collection/views/SeqLike;
   0      6      1    p       Lscala/Function1;


public int prefixLength(scala.Function1);
  Signature: (Lscala/Function1;)I
  Code:
   Stack=2, Locals=2, Args_size=2
	aload_0
	aload_1
	invokestatic	Method scala/collection/SeqLike$class.prefixLength:(Lscala/collection/SeqLike;Lscala/Function1;)I
	ireturn
  Labels:
  LocalVariableTable: 
   Start  Length  Slot  Name   Signature
   0      6      0    this       Lscala/collection/views/SeqLike;
   0      6      1    p       Lscala/Function1;


public int segmentLength(scala.Function1, int);
  Signature: (Lscala/Function1;I)I
  Code:
   Stack=3, Locals=3, Args_size=3
	aload_0
	aload_1
	iload_2
	invokestatic	Method scala/collection/SeqLike$class.segmentLength:(Lscala/collection/SeqLike;Lscala/Function1;I)I
	ireturn
  Labels:
  LocalVariableTable: 
   Start  Length  Slot  Name   Signature
   0      7      0    this       Lscala/collection/views/SeqLike;
   0      7      1    p       Lscala/Function1;
   0      7      2    from       I


public boolean isDefinedAt(int);
  Signature: (I)Z
  Code:
   Stack=2, Locals=2, Args_size=2
	aload_0
	iload_1
	invokestatic	Method scala/collection/SeqLike$class.isDefinedAt:(Lscala/collection/SeqLike;I)Z
	ireturn
  Labels:
  LocalVariableTable: 
   Start  Length  Slot  Name   Signature
   0      6      0    this       Lscala/collection/views/SeqLike;
   0      6      1    idx       I


public int size();
  Signature: ()I
  Code:
   Stack=1, Locals=1, Args_size=1
	aload_0
	invokestatic	Method scala/collection/SeqLike$class.size:(Lscala/collection/SeqLike;)I
	ireturn
  Labels:

public int lengthCompare(int);
  Signature: (I)I
  Code:
   Stack=2, Locals=2, Args_size=2
	aload_0
	iload_1
	invokestatic	Method scala/collection/SeqLike$class.lengthCompare:(Lscala/collection/SeqLike;I)I
	ireturn
  Labels:
  LocalVariableTable: 
   Start  Length  Slot  Name   Signature
   0      6      0    this       Lscala/collection/views/SeqLike;
   0      6      1    len       I


public scala.collection.Seq toCollection(java.lang.Object);
  Signature: (Ljava/lang/Object;)Lscala/collection/Seq;
  Code:
   Stack=2, Locals=2, Args_size=2
	aload_0
	aload_1
	invokestatic	Method scala/collection/SeqLike$class.toCollection:(Lscala/collection/SeqLike;Ljava/lang/Object;)Lscala/collection/Seq;
	areturn
  Labels:
  LocalVariableTable: 
   Start  Length  Slot  Name   Signature
   0      6      0    this       Lscala/collection/views/SeqLike;
   0      6      1    repr       Ljava/lang/Object;


public scala.collection.Seq thisCollection();
  Signature: ()Lscala/collection/Seq;
  Code:
   Stack=1, Locals=1, Args_size=1
	aload_0
	invokestatic	Method scala/collection/SeqLike$class.thisCollection:(Lscala/collection/SeqLike;)Lscala/collection/Seq;
	areturn
  Labels:

public scala.collection.generic.GenericCompanion companion();
  Signature: ()Lscala/collection/generic/GenericCompanion;
  Code:
   Stack=1, Locals=1, Args_size=1
	aload_0
	invokestatic	Method scala/collection/Seq$class.companion:(Lscala/collection/Seq;)Lscala/collection/generic/GenericCompanion;
	areturn
  Labels:

public scala.collection.SeqViewLike$Transformed newPatched(int, scala.collection.Seq, int);
  Signature: (ILscala/collection/Seq;I)Lscala/collection/SeqViewLike$Transformed;
  Code:
   Stack=4, Locals=4, Args_size=4
	aload_0
	iload_1
	aload_2
	iload_3
	invokestatic	Method scala/collection/views/SeqTransformations$class.newPatched:(Lscala/collection/SeqViewLike;ILscala/collection/Seq;I)Lscala/collection/SeqViewLike$Transformed;
	areturn
  Labels:
  LocalVariableTable: 
   Start  Length  Slot  Name   Signature
   0      8      0    this       Lscala/collection/views/SeqLike;
   0      8      1    _from       I
   0      8      2    _patch       Lscala/collection/Seq;
   0      8      3    _replaced       I

  Signature: length = 0x2
   01 FFFFFF98 

public scala.collection.SeqViewLike$Transformed newReversed();
  Signature: ()Lscala/collection/SeqViewLike$Transformed;
  Code:
   Stack=1, Locals=1, Args_size=1
	aload_0
	invokestatic	Method scala/collection/views/SeqTransformations$class.newReversed:(Lscala/collection/SeqViewLike;)Lscala/collection/SeqViewLike$Transformed;
	areturn
  Labels:
  Signature: length = 0x2
   01 FFFFFF9F 

public scala.collection.SeqViewLike$Transformed newZippedAll(scala.collection.Iterable, java.lang.Object, java.lang.Object);
  Signature: (Lscala/collection/Iterable;Ljava/lang/Object;Ljava/lang/Object;)Lscala/collection/SeqViewLike$Transformed;
  Code:
   Stack=4, Locals=4, Args_size=4
	aload_0
	aload_1
	aload_2
	aload_3
	invokestatic	Method scala/collection/views/SeqTransformations$class.newZippedAll:(Lscala/collection/SeqViewLike;Lscala/collection/Iterable;Ljava/lang/Object;Ljava/lang/Object;)Lscala/collection/SeqViewLike$Transformed;
	areturn
  Labels:
  LocalVariableTable: 
   Start  Length  Slot  Name   Signature
   0      8      0    this       Lscala/collection/views/SeqLike;
   0      8      1    that       Lscala/collection/Iterable;
   0      8      2    _thisElem       Ljava/lang/Object;
   0      8      3    _thatElem       Ljava/lang/Object;

  Signature: length = 0x2
   00 63 

public scala.collection.SeqViewLike$Transformed newZipped(scala.collection.Iterable);
  Signature: (Lscala/collection/Iterable;)Lscala/collection/SeqViewLike$Transformed;
  Code:
   Stack=2, Locals=2, Args_size=2
	aload_0
	aload_1
	invokestatic	Method scala/collection/views/SeqTransformations$class.newZipped:(Lscala/collection/SeqViewLike;Lscala/collection/Iterable;)Lscala/collection/SeqViewLike$Transformed;
	areturn
  Labels:
  LocalVariableTable: 
   Start  Length  Slot  Name   Signature
   0      6      0    this       Lscala/collection/views/SeqLike;
   0      6      1    that       Lscala/collection/Iterable;

  Signature: length = 0x2
   00 5D 

public scala.collection.SeqViewLike$Transformed newTakenWhile(scala.Function1);
  Signature: (Lscala/Function1;)Lscala/collection/SeqViewLike$Transformed;
  Code:
   Stack=2, Locals=2, Args_size=2
	aload_0
	aload_1
	invokestatic	Method scala/collection/views/SeqTransformations$class.newTakenWhile:(Lscala/collection/SeqViewLike;Lscala/Function1;)Lscala/collection/SeqViewLike$Transformed;
	areturn
  Labels:
  LocalVariableTable: 
   Start  Length  Slot  Name   Signature
   0      6      0    this       Lscala/collection/views/SeqLike;
   0      6      1    p       Lscala/Function1;

  Signature: length = 0x2
   00 3F 

public scala.collection.SeqViewLike$Transformed newDroppedWhile(scala.Function1);
  Signature: (Lscala/Function1;)Lscala/collection/SeqViewLike$Transformed;
  Code:
   Stack=2, Locals=2, Args_size=2
	aload_0
	aload_1
	invokestatic	Method scala/collection/views/SeqTransformations$class.newDroppedWhile:(Lscala/collection/SeqViewLike;Lscala/Function1;)Lscala/collection/SeqViewLike$Transformed;
	areturn
  Labels:
  LocalVariableTable: 
   Start  Length  Slot  Name   Signature
   0      6      0    this       Lscala/collection/views/SeqLike;
   0      6      1    p       Lscala/Function1;

  Signature: length = 0x2
   00 3F 

public scala.collection.SeqViewLike$Transformed newSliced(int, int);
  Signature: (II)Lscala/collection/SeqViewLike$Transformed;
  Code:
   Stack=3, Locals=3, Args_size=3
	aload_0
	iload_1
	iload_2
	invokestatic	Method scala/collection/views/SeqTransformations$class.newSliced:(Lscala/collection/SeqViewLike;II)Lscala/collection/SeqViewLike$Transformed;
	areturn
  Labels:
  LocalVariableTable: 
   Start  Length  Slot  Name   Signature
   0      7      0    this       Lscala/collection/views/SeqLike;
   0      7      1    _from       I
   0      7      2    _until       I

  Signature: length = 0x2
   00 4E 

public scala.collection.SeqViewLike$Transformed newFiltered(scala.Function1);
  Signature: (Lscala/Function1;)Lscala/collection/SeqViewLike$Transformed;
  Code:
   Stack=2, Locals=2, Args_size=2
	aload_0
	aload_1
	invokestatic	Method scala/collection/views/SeqTransformations$class.newFiltered:(Lscala/collection/SeqViewLike;Lscala/Function1;)Lscala/collection/SeqViewLike$Transformed;
	areturn
  Labels:
  LocalVariableTable: 
   Start  Length  Slot  Name   Signature
   0      6      0    this       Lscala/collection/views/SeqLike;
   0      6      1    p       Lscala/Function1;

  Signature: length = 0x2
   00 3F 

public scala.collection.SeqViewLike$Transformed newFlatMapped(scala.Function1);
  Signature: (Lscala/Function1;)Lscala/collection/SeqViewLike$Transformed;
  Code:
   Stack=2, Locals=2, Args_size=2
	aload_0
	aload_1
	invokestatic	Method scala/collection/views/SeqTransformations$class.newFlatMapped:(Lscala/collection/SeqViewLike;Lscala/Function1;)Lscala/collection/SeqViewLike$Transformed;
	areturn
  Labels:
  LocalVariableTable: 
   Start  Length  Slot  Name   Signature
   0      6      0    this       Lscala/collection/views/SeqLike;
   0      6      1    f       Lscala/Function1;

  Signature: length = 0x2
   00 3F 

public scala.collection.SeqViewLike$Transformed newMapped(scala.Function1);
  Signature: (Lscala/Function1;)Lscala/collection/SeqViewLike$Transformed;
  Code:
   Stack=2, Locals=2, Args_size=2
	aload_0
	aload_1
	invokestatic	Method scala/collection/views/SeqTransformations$class.newMapped:(Lscala/collection/SeqViewLike;Lscala/Function1;)Lscala/collection/SeqViewLike$Transformed;
	areturn
  Labels:
  LocalVariableTable: 
   Start  Length  Slot  Name   Signature
   0      6      0    this       Lscala/collection/views/SeqLike;
   0      6      1    f       Lscala/Function1;

  Signature: length = 0x2
   00 3F 

public scala.collection.SeqViewLike$Transformed newAppended(scala.collection.Traversable);
  Signature: (Lscala/collection/Traversable;)Lscala/collection/SeqViewLike$Transformed;
  Code:
   Stack=2, Locals=2, Args_size=2
	aload_0
	aload_1
	invokestatic	Method scala/collection/views/SeqTransformations$class.newAppended:(Lscala/collection/SeqViewLike;Lscala/collection/Traversable;)Lscala/collection/SeqViewLike$Transformed;
	areturn
  Labels:
  LocalVariableTable: 
   Start  Length  Slot  Name   Signature
   0      6      0    this       Lscala/collection/views/SeqLike;
   0      6      1    that       Lscala/collection/Traversable;

  Signature: length = 0x2
   00 34 

public java.lang.String stringPrefix();
  Signature: ()Ljava/lang/String;
  Code:
   Stack=1, Locals=1, Args_size=1
	aload_0
	invokestatic	Method scala/collection/SeqViewLike$class.stringPrefix:(Lscala/collection/SeqViewLike;)Ljava/lang/String;
	areturn
  Labels:

public java.lang.Object reverseMap(scala.Function1, scala.collection.generic.CanBuildFrom);
  Signature: (Lscala/Function1;Lscala/collection/generic/CanBuildFrom;)Ljava/lang/Object;
  Code:
   Stack=3, Locals=3, Args_size=3
	aload_0
	aload_1
	aload_2
	invokestatic	Method scala/collection/SeqViewLike$class.reverseMap:(Lscala/collection/SeqViewLike;Lscala/Function1;Lscala/collection/generic/CanBuildFrom;)Ljava/lang/Object;
	areturn
  Labels:
  LocalVariableTable: 
   Start  Length  Slot  Name   Signature
   0      7      0    this       Lscala/collection/views/SeqLike;
   0      7      1    f       Lscala/Function1;
   0      7      2    bf       Lscala/collection/generic/CanBuildFrom;


public java.lang.Object padTo(int, java.lang.Object, scala.collection.generic.CanBuildFrom);
  Signature: (ILjava/lang/Object;Lscala/collection/generic/CanBuildFrom;)Ljava/lang/Object;
  Code:
   Stack=4, Locals=4, Args_size=4
	aload_0
	iload_1
	aload_2
	aload_3
	invokestatic	Method scala/collection/SeqViewLike$class.padTo:(Lscala/collection/SeqViewLike;ILjava/lang/Object;Lscala/collection/generic/CanBuildFrom;)Ljava/lang/Object;
	areturn
  Labels:
  LocalVariableTable: 
   Start  Length  Slot  Name   Signature
   0      8      0    this       Lscala/collection/views/SeqLike;
   0      8      1    len       I
   0      8      2    elem       Ljava/lang/Object;
   0      8      3    bf       Lscala/collection/generic/CanBuildFrom;


public java.lang.Object patch(int, scala.collection.Seq, int, scala.collection.generic.CanBuildFrom);
  Signature: (ILscala/collection/Seq;ILscala/collection/generic/CanBuildFrom;)Ljava/lang/Object;
  Code:
   Stack=5, Locals=5, Args_size=5
	aload_0
	iload_1
	aload_2
	iload_3
	aload	4
	invokestatic	Method scala/collection/SeqViewLike$class.patch:(Lscala/collection/SeqViewLike;ILscala/collection/Seq;ILscala/collection/generic/CanBuildFrom;)Ljava/lang/Object;
	areturn
  Labels:
  LocalVariableTable: 
   Start  Length  Slot  Name   Signature
   0      10      0    this       Lscala/collection/views/SeqLike;
   0      10      1    from       I
   0      10      2    patch       Lscala/collection/Seq;
   0      10      3    replaced       I
   0      10      4    bf       Lscala/collection/generic/CanBuildFrom;


public scala.collection.SeqView reverse();
  Signature: ()Lscala/collection/SeqView;
  Code:
   Stack=1, Locals=1, Args_size=1
	aload_0
	invokestatic	Method scala/collection/SeqViewLike$class.reverse:(Lscala/collection/SeqViewLike;)Lscala/collection/SeqView;
	areturn
  Labels:

}

