Compiled from "Transformed.scala"
public abstract class scala.collection.views.SeqTransformations$class extends java.lang.Object
  SourceFile: "Transformed.scala"
  Scala: length = 0x
   
  InnerClass: 
   public abstract Transformed=class scala/collection/SeqViewLike$Transformed of class scala/collection/SeqViewLike
   public final $anon$12=class scala/collection/views/SeqTransformations$$anon$12 of class scala/collection/views/SeqTransformations
   public final $anon$13=class scala/collection/views/SeqTransformations$$anon$13 of class scala/collection/views/SeqTransformations
   public final $anon$14=class scala/collection/views/SeqTransformations$$anon$14 of class scala/collection/views/SeqTransformations
   public final $anon$15=class scala/collection/views/SeqTransformations$$anon$15 of class scala/collection/views/SeqTransformations
   public final $anon$16=class scala/collection/views/SeqTransformations$$anon$16 of class scala/collection/views/SeqTransformations
   public final $anon$17=class scala/collection/views/SeqTransformations$$anon$17 of class scala/collection/views/SeqTransformations
   public final $anon$18=class scala/collection/views/SeqTransformations$$anon$18 of class scala/collection/views/SeqTransformations
   public final $anon$19=class scala/collection/views/SeqTransformations$$anon$19 of class scala/collection/views/SeqTransformations
   public final $anon$20=class scala/collection/views/SeqTransformations$$anon$20 of class scala/collection/views/SeqTransformations
   public final $anon$21=class scala/collection/views/SeqTransformations$$anon$21 of class scala/collection/views/SeqTransformations
   public final $anon$22=class scala/collection/views/SeqTransformations$$anon$22 of class scala/collection/views/SeqTransformations
  minor version: 0
  major version: 49
  Constant pool:
Asciz	SourceFile;
Asciz	Transformed.scala;
Asciz	$init$;
Asciz	(Lscala/collection/SeqViewLike;)V;
Asciz	Code;
Asciz	LineNumberTable;
Asciz	$this;
Asciz	Lscala/collection/SeqViewLike;;
Asciz	LocalVariableTable;
Asciz	newPatched;
Asciz	(Lscala/collection/SeqViewLike;ILscala/collection/Seq;I)Lscala/collection/SeqViewLike$Transformed;;
Asciz	scala/collection/views/SeqTransformations$$anon$22;
class	scala/collection/views/SeqTransformations$$anon$22
Asciz	<init>;
Asciz	(Lscala/collection/SeqViewLike;ILscala/collection/Seq;I)V;
NameAndType	"<init>":(Lscala/collection/SeqViewLike;ILscala/collection/Seq;I)V
Method	scala/collection/views/SeqTransformations$$anon$22."<init>":(Lscala/collection/SeqViewLike;ILscala/collection/Seq;I)V
Asciz	_from$4;
Asciz	I;
Asciz	_patch$1;
Asciz	Lscala/collection/Seq;;
Asciz	_replaced$1;
Asciz	newReversed;
Asciz	(Lscala/collection/SeqViewLike;)Lscala/collection/SeqViewLike$Transformed;;
Asciz	scala/collection/views/SeqTransformations$$anon$21;
class	scala/collection/views/SeqTransformations$$anon$21
NameAndType	"<init>":(Lscala/collection/SeqViewLike;)V
Method	scala/collection/views/SeqTransformations$$anon$21."<init>":(Lscala/collection/SeqViewLike;)V
Asciz	newZippedAll;
Asciz	(Lscala/collection/SeqViewLike;Lscala/collection/Iterable;Ljava/lang/Object;Ljava/lang/Object;)Lscala/collection/SeqViewLike$Transformed;;
Asciz	scala/collection/views/SeqTransformations$$anon$20;
class	scala/collection/views/SeqTransformations$$anon$20
Asciz	(Lscala/collection/SeqViewLike;Lscala/collection/Iterable;Ljava/lang/Object;Ljava/lang/Object;)V;
NameAndType	"<init>":(Lscala/collection/SeqViewLike;Lscala/collection/Iterable;Ljava/lang/Object;Ljava/lang/Object;)V
Method	scala/collection/views/SeqTransformations$$anon$20."<init>":(Lscala/collection/SeqViewLike;Lscala/collection/Iterable;Ljava/lang/Object;Ljava/lang/Object;)V
Asciz	that$3;
Asciz	Lscala/collection/Iterable;;
Asciz	_thisElem$1;
Asciz	Ljava/lang/Object;;
Asciz	_thatElem$1;
Asciz	newZipped;
Asciz	(Lscala/collection/SeqViewLike;Lscala/collection/Iterable;)Lscala/collection/SeqViewLike$Transformed;;
Asciz	scala/collection/views/SeqTransformations$$anon$19;
class	scala/collection/views/SeqTransformations$$anon$19
Asciz	(Lscala/collection/SeqViewLike;Lscala/collection/Iterable;)V;
NameAndType	"<init>":(Lscala/collection/SeqViewLike;Lscala/collection/Iterable;)V
Method	scala/collection/views/SeqTransformations$$anon$19."<init>":(Lscala/collection/SeqViewLike;Lscala/collection/Iterable;)V
Asciz	that$5;
Asciz	newTakenWhile;
Asciz	(Lscala/collection/SeqViewLike;Lscala/Function1;)Lscala/collection/SeqViewLike$Transformed;;
Asciz	scala/collection/views/SeqTransformations$$anon$18;
class	scala/collection/views/SeqTransformations$$anon$18
Asciz	(Lscala/collection/SeqViewLike;Lscala/Function1;)V;
NameAndType	"<init>":(Lscala/collection/SeqViewLike;Lscala/Function1;)V
Method	scala/collection/views/SeqTransformations$$anon$18."<init>":(Lscala/collection/SeqViewLike;Lscala/Function1;)V
Asciz	p$7;
Asciz	Lscala/Function1;;
Asciz	newDroppedWhile;
Asciz	scala/collection/views/SeqTransformations$$anon$17;
class	scala/collection/views/SeqTransformations$$anon$17
Method	scala/collection/views/SeqTransformations$$anon$17."<init>":(Lscala/collection/SeqViewLike;Lscala/Function1;)V
Asciz	p$8;
Asciz	newSliced;
Asciz	(Lscala/collection/SeqViewLike;II)Lscala/collection/SeqViewLike$Transformed;;
Asciz	scala/collection/views/SeqTransformations$$anon$16;
class	scala/collection/views/SeqTransformations$$anon$16
Asciz	(Lscala/collection/SeqViewLike;II)V;
NameAndType	"<init>":(Lscala/collection/SeqViewLike;II)V
Method	scala/collection/views/SeqTransformations$$anon$16."<init>":(Lscala/collection/SeqViewLike;II)V
Asciz	_from$3;
Asciz	_until$3;
Asciz	newFiltered;
Asciz	scala/collection/views/SeqTransformations$$anon$15;
class	scala/collection/views/SeqTransformations$$anon$15
Method	scala/collection/views/SeqTransformations$$anon$15."<init>":(Lscala/collection/SeqViewLike;Lscala/Function1;)V
Asciz	p$9;
Asciz	newFlatMapped;
Asciz	scala/collection/views/SeqTransformations$$anon$14;
class	scala/collection/views/SeqTransformations$$anon$14
Method	scala/collection/views/SeqTransformations$$anon$14."<init>":(Lscala/collection/SeqViewLike;Lscala/Function1;)V
Asciz	f$5;
Asciz	newMapped;
Asciz	scala/collection/views/SeqTransformations$$anon$13;
class	scala/collection/views/SeqTransformations$$anon$13
Method	scala/collection/views/SeqTransformations$$anon$13."<init>":(Lscala/collection/SeqViewLike;Lscala/Function1;)V
Asciz	f$6;
Asciz	newAppended;
Asciz	(Lscala/collection/SeqViewLike;Lscala/collection/Traversable;)Lscala/collection/SeqViewLike$Transformed;;
Asciz	scala/collection/views/SeqTransformations$$anon$12;
class	scala/collection/views/SeqTransformations$$anon$12
Asciz	(Lscala/collection/SeqViewLike;Lscala/collection/Traversable;)V;
NameAndType	"<init>":(Lscala/collection/SeqViewLike;Lscala/collection/Traversable;)V
Method	scala/collection/views/SeqTransformations$$anon$12."<init>":(Lscala/collection/SeqViewLike;Lscala/collection/Traversable;)V
Asciz	that$7;
Asciz	Lscala/collection/Traversable;;
Asciz	Scala;
Asciz	InnerClasses;
Asciz	scala/collection/SeqViewLike$Transformed;
class	scala/collection/SeqViewLike$Transformed
Asciz	scala/collection/SeqViewLike;
class	scala/collection/SeqViewLike
Asciz	Transformed;
Asciz	scala/collection/views/SeqTransformations;
class	scala/collection/views/SeqTransformations
Asciz	$anon$12;
Asciz	$anon$13;
Asciz	$anon$14;
Asciz	$anon$15;
Asciz	$anon$16;
Asciz	$anon$17;
Asciz	$anon$18;
Asciz	$anon$19;
Asciz	$anon$20;
Asciz	$anon$21;
Asciz	$anon$22;
Asciz	scala/collection/views/SeqTransformations$class;
class	scala/collection/views/SeqTransformations$class
Asciz	java/lang/Object;
class	java/lang/Object

{
public static void $init$(scala.collection.SeqViewLike);
  Signature: (Lscala/collection/SeqViewLike;)V
  Code:
   Stack=0, Locals=1, Args_size=1
	return
  Labels:
  LocalVariableTable: 
   Start  Length  Slot  Name   Signature
   0      1      0    $this       Lscala/collection/SeqViewLike;


public static scala.collection.SeqViewLike$Transformed newPatched(scala.collection.SeqViewLike, int, scala.collection.Seq, int);
  Signature: (Lscala/collection/SeqViewLike;ILscala/collection/Seq;I)Lscala/collection/SeqViewLike$Transformed;
  Code:
   Stack=6, Locals=4, Args_size=4
	new	class scala/collection/views/SeqTransformations$$anon$22
	dup
	aload_0
	iload_1
	aload_2
	iload_3
	invokespecial	Method scala/collection/views/SeqTransformations$$anon$22."<init>":(Lscala/collection/SeqViewLike;ILscala/collection/Seq;I)V
	areturn
  Labels:
  LocalVariableTable: 
   Start  Length  Slot  Name   Signature
   0      12      0    $this       Lscala/collection/SeqViewLike;
   0      12      1    _from$4       I
   0      12      2    _patch$1       Lscala/collection/Seq;
   0      12      3    _replaced$1       I


public static scala.collection.SeqViewLike$Transformed newReversed(scala.collection.SeqViewLike);
  Signature: (Lscala/collection/SeqViewLike;)Lscala/collection/SeqViewLike$Transformed;
  Code:
   Stack=3, Locals=1, Args_size=1
	new	class scala/collection/views/SeqTransformations$$anon$21
	dup
	aload_0
	invokespecial	Method scala/collection/views/SeqTransformations$$anon$21."<init>":(Lscala/collection/SeqViewLike;)V
	areturn
  Labels:
  LocalVariableTable: 
   Start  Length  Slot  Name   Signature
   0      9      0    $this       Lscala/collection/SeqViewLike;


public static scala.collection.SeqViewLike$Transformed newZippedAll(scala.collection.SeqViewLike, scala.collection.Iterable, java.lang.Object, java.lang.Object);
  Signature: (Lscala/collection/SeqViewLike;Lscala/collection/Iterable;Ljava/lang/Object;Ljava/lang/Object;)Lscala/collection/SeqViewLike$Transformed;
  Code:
   Stack=6, Locals=4, Args_size=4
	new	class scala/collection/views/SeqTransformations$$anon$20
	dup
	aload_0
	aload_1
	aload_2
	aload_3
	invokespecial	Method scala/collection/views/SeqTransformations$$anon$20."<init>":(Lscala/collection/SeqViewLike;Lscala/collection/Iterable;Ljava/lang/Object;Ljava/lang/Object;)V
	areturn
  Labels:
  LocalVariableTable: 
   Start  Length  Slot  Name   Signature
   0      12      0    $this       Lscala/collection/SeqViewLike;
   0      12      1    that$3       Lscala/collection/Iterable;
   0      12      2    _thisElem$1       Ljava/lang/Object;
   0      12      3    _thatElem$1       Ljava/lang/Object;


public static scala.collection.SeqViewLike$Transformed newZipped(scala.collection.SeqViewLike, scala.collection.Iterable);
  Signature: (Lscala/collection/SeqViewLike;Lscala/collection/Iterable;)Lscala/collection/SeqViewLike$Transformed;
  Code:
   Stack=4, Locals=2, Args_size=2
	new	class scala/collection/views/SeqTransformations$$anon$19
	dup
	aload_0
	aload_1
	invokespecial	Method scala/collection/views/SeqTransformations$$anon$19."<init>":(Lscala/collection/SeqViewLike;Lscala/collection/Iterable;)V
	areturn
  Labels:
  LocalVariableTable: 
   Start  Length  Slot  Name   Signature
   0      10      0    $this       Lscala/collection/SeqViewLike;
   0      10      1    that$5       Lscala/collection/Iterable;


public static scala.collection.SeqViewLike$Transformed newTakenWhile(scala.collection.SeqViewLike, scala.Function1);
  Signature: (Lscala/collection/SeqViewLike;Lscala/Function1;)Lscala/collection/SeqViewLike$Transformed;
  Code:
   Stack=4, Locals=2, Args_size=2
	new	class scala/collection/views/SeqTransformations$$anon$18
	dup
	aload_0
	aload_1
	invokespecial	Method scala/collection/views/SeqTransformations$$anon$18."<init>":(Lscala/collection/SeqViewLike;Lscala/Function1;)V
	areturn
  Labels:
  LocalVariableTable: 
   Start  Length  Slot  Name   Signature
   0      10      0    $this       Lscala/collection/SeqViewLike;
   0      10      1    p$7       Lscala/Function1;


public static scala.collection.SeqViewLike$Transformed newDroppedWhile(scala.collection.SeqViewLike, scala.Function1);
  Signature: (Lscala/collection/SeqViewLike;Lscala/Function1;)Lscala/collection/SeqViewLike$Transformed;
  Code:
   Stack=4, Locals=2, Args_size=2
	new	class scala/collection/views/SeqTransformations$$anon$17
	dup
	aload_0
	aload_1
	invokespecial	Method scala/collection/views/SeqTransformations$$anon$17."<init>":(Lscala/collection/SeqViewLike;Lscala/Function1;)V
	areturn
  Labels:
  LocalVariableTable: 
   Start  Length  Slot  Name   Signature
   0      10      0    $this       Lscala/collection/SeqViewLike;
   0      10      1    p$8       Lscala/Function1;


public static scala.collection.SeqViewLike$Transformed newSliced(scala.collection.SeqViewLike, int, int);
  Signature: (Lscala/collection/SeqViewLike;II)Lscala/collection/SeqViewLike$Transformed;
  Code:
   Stack=5, Locals=3, Args_size=3
	new	class scala/collection/views/SeqTransformations$$anon$16
	dup
	aload_0
	iload_1
	iload_2
	invokespecial	Method scala/collection/views/SeqTransformations$$anon$16."<init>":(Lscala/collection/SeqViewLike;II)V
	areturn
  Labels:
  LocalVariableTable: 
   Start  Length  Slot  Name   Signature
   0      11      0    $this       Lscala/collection/SeqViewLike;
   0      11      1    _from$3       I
   0      11      2    _until$3       I


public static scala.collection.SeqViewLike$Transformed newFiltered(scala.collection.SeqViewLike, scala.Function1);
  Signature: (Lscala/collection/SeqViewLike;Lscala/Function1;)Lscala/collection/SeqViewLike$Transformed;
  Code:
   Stack=4, Locals=2, Args_size=2
	new	class scala/collection/views/SeqTransformations$$anon$15
	dup
	aload_0
	aload_1
	invokespecial	Method scala/collection/views/SeqTransformations$$anon$15."<init>":(Lscala/collection/SeqViewLike;Lscala/Function1;)V
	areturn
  Labels:
  LocalVariableTable: 
   Start  Length  Slot  Name   Signature
   0      10      0    $this       Lscala/collection/SeqViewLike;
   0      10      1    p$9       Lscala/Function1;


public static scala.collection.SeqViewLike$Transformed newFlatMapped(scala.collection.SeqViewLike, scala.Function1);
  Signature: (Lscala/collection/SeqViewLike;Lscala/Function1;)Lscala/collection/SeqViewLike$Transformed;
  Code:
   Stack=4, Locals=2, Args_size=2
	new	class scala/collection/views/SeqTransformations$$anon$14
	dup
	aload_0
	aload_1
	invokespecial	Method scala/collection/views/SeqTransformations$$anon$14."<init>":(Lscala/collection/SeqViewLike;Lscala/Function1;)V
	areturn
  Labels:
  LocalVariableTable: 
   Start  Length  Slot  Name   Signature
   0      10      0    $this       Lscala/collection/SeqViewLike;
   0      10      1    f$5       Lscala/Function1;


public static scala.collection.SeqViewLike$Transformed newMapped(scala.collection.SeqViewLike, scala.Function1);
  Signature: (Lscala/collection/SeqViewLike;Lscala/Function1;)Lscala/collection/SeqViewLike$Transformed;
  Code:
   Stack=4, Locals=2, Args_size=2
	new	class scala/collection/views/SeqTransformations$$anon$13
	dup
	aload_0
	aload_1
	invokespecial	Method scala/collection/views/SeqTransformations$$anon$13."<init>":(Lscala/collection/SeqViewLike;Lscala/Function1;)V
	areturn
  Labels:
  LocalVariableTable: 
   Start  Length  Slot  Name   Signature
   0      10      0    $this       Lscala/collection/SeqViewLike;
   0      10      1    f$6       Lscala/Function1;


public static scala.collection.SeqViewLike$Transformed newAppended(scala.collection.SeqViewLike, scala.collection.Traversable);
  Signature: (Lscala/collection/SeqViewLike;Lscala/collection/Traversable;)Lscala/collection/SeqViewLike$Transformed;
  Code:
   Stack=4, Locals=2, Args_size=2
	new	class scala/collection/views/SeqTransformations$$anon$12
	dup
	aload_0
	aload_1
	invokespecial	Method scala/collection/views/SeqTransformations$$anon$12."<init>":(Lscala/collection/SeqViewLike;Lscala/collection/Traversable;)V
	areturn
  Labels:
  LocalVariableTable: 
   Start  Length  Slot  Name   Signature
   0      10      0    $this       Lscala/collection/SeqViewLike;
   0      10      1    that$7       Lscala/collection/Traversable;


}

