Compiled from "Transformed.scala"
public final class scala.collection.views.SeqTransformations$$anon$16 extends scala.collection.views.SeqLike implements scala.collection.SeqViewLike$Sliced
  SourceFile: "Transformed.scala"
  Signature: length = 0x2
   00 7C 
  Scala: length = 0x
   
  InnerClass: 
   public abstract Sliced=class scala/collection/SeqViewLike$Sliced of class scala/collection/SeqViewLike
   public abstract Sliced=class scala/collection/IterableViewLike$Sliced of class scala/collection/IterableViewLike
   public abstract Sliced=class scala/collection/TraversableViewLike$Sliced of class scala/collection/TraversableViewLike
   public final $anon$16=class scala/collection/views/SeqTransformations$$anon$16 of class scala/collection/views/SeqTransformations
   public abstract Transformed=class scala/collection/TraversableViewLike$Transformed of class scala/collection/TraversableViewLike
  minor version: 0
  major version: 49
  Constant pool:
Asciz	SourceFile;
Asciz	Transformed.scala;
Asciz	bitmap$0;
Asciz	I;
Asciz	underlying;
Asciz	Ljava/lang/Object;;
Asciz	$outer;
Asciz	Lscala/collection/SeqViewLike;;
Asciz	until;
Asciz	from;
Asciz	<init>;
Asciz	(Lscala/collection/SeqViewLike;II)V;
Asciz	Code;
Asciz	LineNumberTable;
Asciz	java/lang/NullPointerException;
class	java/lang/NullPointerException
Asciz	()V;
NameAndType	"<init>":()V
Method	java/lang/NullPointerException."<init>":()V
Asciz	scala/collection/views/SeqTransformations$$anon$16;
class	scala/collection/views/SeqTransformations$$anon$16
NameAndType	$outer:Lscala/collection/SeqViewLike;
Field	scala/collection/views/SeqTransformations$$anon$16.$outer:Lscala/collection/SeqViewLike;
Asciz	scala/collection/views/SeqLike;
class	scala/collection/views/SeqLike
Method	scala/collection/views/SeqLike."<init>":()V
Asciz	scala/collection/TraversableViewLike$Transformed$class;
class	scala/collection/TraversableViewLike$Transformed$class
Asciz	$init$;
Asciz	(Lscala/collection/TraversableViewLike$Transformed;)V;
NameAndType	$init$:(Lscala/collection/TraversableViewLike$Transformed;)V
Method	scala/collection/TraversableViewLike$Transformed$class.$init$:(Lscala/collection/TraversableViewLike$Transformed;)V
Asciz	scala/collection/TraversableViewLike$Sliced$class;
class	scala/collection/TraversableViewLike$Sliced$class
Asciz	(Lscala/collection/TraversableViewLike$Sliced;)V;
NameAndType	$init$:(Lscala/collection/TraversableViewLike$Sliced;)V
Method	scala/collection/TraversableViewLike$Sliced$class.$init$:(Lscala/collection/TraversableViewLike$Sliced;)V
Asciz	scala/collection/IterableViewLike$Sliced$class;
class	scala/collection/IterableViewLike$Sliced$class
Asciz	(Lscala/collection/IterableViewLike$Sliced;)V;
NameAndType	$init$:(Lscala/collection/IterableViewLike$Sliced;)V
Method	scala/collection/IterableViewLike$Sliced$class.$init$:(Lscala/collection/IterableViewLike$Sliced;)V
Asciz	scala/collection/SeqViewLike$Sliced$class;
class	scala/collection/SeqViewLike$Sliced$class
Asciz	(Lscala/collection/SeqViewLike$Sliced;)V;
NameAndType	$init$:(Lscala/collection/SeqViewLike$Sliced;)V
Method	scala/collection/SeqViewLike$Sliced$class.$init$:(Lscala/collection/SeqViewLike$Sliced;)V
NameAndType	from:I
Field	scala/collection/views/SeqTransformations$$anon$16.from:I
NameAndType	until:I
Field	scala/collection/views/SeqTransformations$$anon$16.until:I
Asciz	this;
Asciz	Lscala/collection/views/SeqTransformations$$anon$16;;
Asciz	LocalVariableTable;
Asciz	(Lscala/collection/SeqViewLike<TA;TColl;TThis;>;)V;
Asciz	Signature;
Asciz	apply;
Asciz	(Ljava/lang/Object;)Ljava/lang/Object;;
Asciz	scala/runtime/BoxesRunTime;
class	scala/runtime/BoxesRunTime
Asciz	unboxToInt;
Asciz	(Ljava/lang/Object;)I;
NameAndType	unboxToInt:(Ljava/lang/Object;)I
Method	scala/runtime/BoxesRunTime.unboxToInt:(Ljava/lang/Object;)I
Asciz	scala/collection/SeqViewLike$Sliced;
class	scala/collection/SeqViewLike$Sliced
Asciz	(I)Ljava/lang/Object;;
NameAndType	apply:(I)Ljava/lang/Object;
InterfaceMethod	scala/collection/SeqViewLike$Sliced.apply:(I)Ljava/lang/Object;
Asciz	v1;
Asciz	slice;
Asciz	(II)Ljava/lang/Object;;
Asciz	scala/collection/TraversableViewLike$Sliced;
class	scala/collection/TraversableViewLike$Sliced
Asciz	(II)Lscala/collection/TraversableView;;
NameAndType	slice:(II)Lscala/collection/TraversableView;
InterfaceMethod	scala/collection/TraversableViewLike$Sliced.slice:(II)Lscala/collection/TraversableView;
Asciz	scala$collection$TraversableViewLike$Transformed$$$outer;
Asciz	()Lscala/collection/TraversableViewLike;;
Asciz	scala$collection$TraversableViewLike$Sliced$$$outer;
Asciz	scala$collection$IterableViewLike$Sliced$$$outer;
Asciz	()Lscala/collection/IterableViewLike;;
Asciz	scala$collection$SeqViewLike$Sliced$$$outer;
Asciz	()Lscala/collection/SeqViewLike;;
Asciz	()I;
Asciz	()Ljava/lang/Object;;
NameAndType	bitmap$0:I
Field	scala/collection/views/SeqTransformations$$anon$16.bitmap$0:I
Asciz	(Lscala/collection/TraversableViewLike$Transformed;)Ljava/lang/Object;;
NameAndType	underlying:(Lscala/collection/TraversableViewLike$Transformed;)Ljava/lang/Object;
Method	scala/collection/TraversableViewLike$Transformed$class.underlying:(Lscala/collection/TraversableViewLike$Transformed;)Ljava/lang/Object;
NameAndType	underlying:Ljava/lang/Object;
Field	scala/collection/views/SeqTransformations$$anon$16.underlying:Ljava/lang/Object;
Asciz	(Lscala/collection/TraversableViewLike$Sliced;II)Lscala/collection/TraversableView;;
NameAndType	slice:(Lscala/collection/TraversableViewLike$Sliced;II)Lscala/collection/TraversableView;
Method	scala/collection/TraversableViewLike$Sliced$class.slice:(Lscala/collection/TraversableViewLike$Sliced;II)Lscala/collection/TraversableView;
Asciz	from1;
Asciz	until1;
Asciz	stringPrefix;
Asciz	()Ljava/lang/String;;
Asciz	(Lscala/collection/TraversableViewLike$Sliced;)Ljava/lang/String;;
NameAndType	stringPrefix:(Lscala/collection/TraversableViewLike$Sliced;)Ljava/lang/String;
Method	scala/collection/TraversableViewLike$Sliced$class.stringPrefix:(Lscala/collection/TraversableViewLike$Sliced;)Ljava/lang/String;
Asciz	foreach;
Asciz	(Lscala/Function1;)V;
Asciz	(Lscala/collection/TraversableViewLike$Sliced;Lscala/Function1;)V;
NameAndType	foreach:(Lscala/collection/TraversableViewLike$Sliced;Lscala/Function1;)V
Method	scala/collection/TraversableViewLike$Sliced$class.foreach:(Lscala/collection/TraversableViewLike$Sliced;Lscala/Function1;)V
Asciz	f;
Asciz	Lscala/Function1;;
Asciz	iterator;
Asciz	()Lscala/collection/Iterator;;
Asciz	(Lscala/collection/IterableViewLike$Sliced;)Lscala/collection/Iterator;;
NameAndType	iterator:(Lscala/collection/IterableViewLike$Sliced;)Lscala/collection/Iterator;
Method	scala/collection/IterableViewLike$Sliced$class.iterator:(Lscala/collection/IterableViewLike$Sliced;)Lscala/collection/Iterator;
Asciz	(Lscala/collection/SeqViewLike$Sliced;I)Ljava/lang/Object;;
NameAndType	apply:(Lscala/collection/SeqViewLike$Sliced;I)Ljava/lang/Object;
Method	scala/collection/SeqViewLike$Sliced$class.apply:(Lscala/collection/SeqViewLike$Sliced;I)Ljava/lang/Object;
Asciz	idx;
Asciz	length;
Asciz	(Lscala/collection/SeqViewLike$Sliced;)I;
NameAndType	length:(Lscala/collection/SeqViewLike$Sliced;)I
Method	scala/collection/SeqViewLike$Sliced$class.length:(Lscala/collection/SeqViewLike$Sliced;)I
Asciz	Lscala/collection/views/SeqLike<TA;TColl;>;Lscala/collection/SeqViewLike<TA;TColl;TThis;>.Sliced;;
Asciz	Scala;
Asciz	InnerClasses;
Asciz	scala/collection/SeqViewLike;
class	scala/collection/SeqViewLike
Asciz	Sliced;
Asciz	scala/collection/IterableViewLike$Sliced;
class	scala/collection/IterableViewLike$Sliced
Asciz	scala/collection/IterableViewLike;
class	scala/collection/IterableViewLike
Asciz	scala/collection/TraversableViewLike;
class	scala/collection/TraversableViewLike
Asciz	scala/collection/views/SeqTransformations;
class	scala/collection/views/SeqTransformations
Asciz	$anon$16;
Asciz	scala/collection/TraversableViewLike$Transformed;
class	scala/collection/TraversableViewLike$Transformed
Asciz	Transformed;

{
public volatile int bitmap$0;
  Signature: I

private final java.lang.Object underlying;
  Signature: Ljava/lang/Object;

private final scala.collection.SeqViewLike $outer;
  Signature: Lscala/collection/SeqViewLike;

private final int until;
  Signature: I

private final int from;
  Signature: I

public scala.collection.views.SeqTransformations$$anon$16(scala.collection.SeqViewLike, int, int);
  Signature: (Lscala/collection/SeqViewLike;II)V
  Code:
   Stack=2, Locals=4, Args_size=4
	aload_1
	ifnonnull	l1 // aload_0
	new	class java/lang/NullPointerException
	dup
	invokespecial	Method java/lang/NullPointerException."<init>":()V
	athrow
l1	aload_0
	aload_1
	putfield	Field $outer:Lscala/collection/SeqViewLike;
	aload_0
	invokespecial	Method scala/collection/views/SeqLike."<init>":()V
	aload_0
	invokestatic	Method scala/collection/TraversableViewLike$Transformed$class.$init$:(Lscala/collection/TraversableViewLike$Transformed;)V
	aload_0
	invokestatic	Method scala/collection/TraversableViewLike$Sliced$class.$init$:(Lscala/collection/TraversableViewLike$Sliced;)V
	aload_0
	invokestatic	Method scala/collection/IterableViewLike$Sliced$class.$init$:(Lscala/collection/IterableViewLike$Sliced;)V
	aload_0
	invokestatic	Method scala/collection/SeqViewLike$Sliced$class.$init$:(Lscala/collection/SeqViewLike$Sliced;)V
	aload_0
	iload_2
	putfield	Field from:I
	aload_0
	iload_3
	putfield	Field until:I
	return
  Labels:
   	l1 = 12 // aload_0
  LocalVariableTable: 
   Start  Length  Slot  Name   Signature
   0      48      0    this       Lscala/collection/views/SeqTransformations$$anon$16;
   0      48      1    $outer       Lscala/collection/SeqViewLike;

  Signature: length = 0x2
   00 37 

public java.lang.Object apply(java.lang.Object);
  Signature: (Ljava/lang/Object;)Ljava/lang/Object;
  Code:
   Stack=2, Locals=2, Args_size=2
	aload_0
	aload_1
	invokestatic	Method scala/runtime/BoxesRunTime.unboxToInt:(Ljava/lang/Object;)I
	invokeinterface	InterfaceMethod scala/collection/SeqViewLike$Sliced.apply:(I)Ljava/lang/Object;
	areturn
  Labels:
  LocalVariableTable: 
   Start  Length  Slot  Name   Signature
   0      11      0    this       Lscala/collection/views/SeqTransformations$$anon$16;
   0      11      1    v1       Ljava/lang/Object;


public java.lang.Object slice(int, int);
  Signature: (II)Ljava/lang/Object;
  Code:
   Stack=3, Locals=3, Args_size=3
	aload_0
	iload_1
	iload_2
	invokeinterface	InterfaceMethod scala/collection/TraversableViewLike$Sliced.slice:(II)Lscala/collection/TraversableView;
	areturn
  Labels:
  LocalVariableTable: 
   Start  Length  Slot  Name   Signature
   0      9      0    this       Lscala/collection/views/SeqTransformations$$anon$16;
   0      9      1    from       I
   0      9      2    until       I


public scala.collection.TraversableViewLike scala$collection$TraversableViewLike$Transformed$$$outer();
  Signature: ()Lscala/collection/TraversableViewLike;
  Code:
   Stack=1, Locals=1, Args_size=1
	aload_0
	getfield	Field $outer:Lscala/collection/SeqViewLike;
	areturn
  Labels:

public scala.collection.TraversableViewLike scala$collection$TraversableViewLike$Sliced$$$outer();
  Signature: ()Lscala/collection/TraversableViewLike;
  Code:
   Stack=1, Locals=1, Args_size=1
	aload_0
	getfield	Field $outer:Lscala/collection/SeqViewLike;
	areturn
  Labels:

public scala.collection.IterableViewLike scala$collection$IterableViewLike$Sliced$$$outer();
  Signature: ()Lscala/collection/IterableViewLike;
  Code:
   Stack=1, Locals=1, Args_size=1
	aload_0
	getfield	Field $outer:Lscala/collection/SeqViewLike;
	areturn
  Labels:

public scala.collection.SeqViewLike scala$collection$SeqViewLike$Sliced$$$outer();
  Signature: ()Lscala/collection/SeqViewLike;
  Code:
   Stack=1, Locals=1, Args_size=1
	aload_0
	getfield	Field $outer:Lscala/collection/SeqViewLike;
	areturn
  Labels:

public int until();
  Signature: ()I
  Code:
   Stack=1, Locals=1, Args_size=1
	aload_0
	getfield	Field until:I
	ireturn
  Labels:

public int from();
  Signature: ()I
  Code:
   Stack=1, Locals=1, Args_size=1
	aload_0
	getfield	Field from:I
	ireturn
  Labels:

public java.lang.Object underlying();
  Signature: ()Ljava/lang/Object;
  Code:
   Stack=3, Locals=1, Args_size=1
	aload_0
	getfield	Field bitmap$0:I
	iconst_1
	iand
	iconst_0
	if_icmpne	l1 // aload_0
	aload_0
	dup
	pop
	monitorenter
	aload_0
	getfield	Field bitmap$0:I
	iconst_1
	iand
	iconst_0
	if_icmpne	l2 // aload_0
	aload_0
	aload_0
	invokestatic	Method scala/collection/TraversableViewLike$Transformed$class.underlying:(Lscala/collection/TraversableViewLike$Transformed;)Ljava/lang/Object;
	putfield	Field underlying:Ljava/lang/Object;
	aload_0
	aload_0
	getfield	Field bitmap$0:I
	iconst_1
	ior
	putfield	Field bitmap$0:I
l2	aload_0
	monitorexit
l1	aload_0
	getfield	Field underlying:Ljava/lang/Object;
	areturn
	aload_0
	monitorexit
	athrow
  Labels:
   	l2 = 42 // aload_0
   	l1 = 44 // aload_0
  Exception table:
   from   to  target type
    14    44    49   any

public scala.collection.TraversableView slice(int, int);
  Signature: (II)Lscala/collection/TraversableView;
  Code:
   Stack=3, Locals=3, Args_size=3
	aload_0
	iload_1
	iload_2
	invokestatic	Method scala/collection/TraversableViewLike$Sliced$class.slice:(Lscala/collection/TraversableViewLike$Sliced;II)Lscala/collection/TraversableView;
	areturn
  Labels:
  LocalVariableTable: 
   Start  Length  Slot  Name   Signature
   0      7      0    this       Lscala/collection/views/SeqTransformations$$anon$16;
   0      7      1    from1       I
   0      7      2    until1       I


public java.lang.String stringPrefix();
  Signature: ()Ljava/lang/String;
  Code:
   Stack=1, Locals=1, Args_size=1
	aload_0
	invokestatic	Method scala/collection/TraversableViewLike$Sliced$class.stringPrefix:(Lscala/collection/TraversableViewLike$Sliced;)Ljava/lang/String;
	areturn
  Labels:

public void foreach(scala.Function1);
  Signature: (Lscala/Function1;)V
  Code:
   Stack=2, Locals=2, Args_size=2
	aload_0
	aload_1
	invokestatic	Method scala/collection/TraversableViewLike$Sliced$class.foreach:(Lscala/collection/TraversableViewLike$Sliced;Lscala/Function1;)V
	return
  Labels:
  LocalVariableTable: 
   Start  Length  Slot  Name   Signature
   0      6      0    this       Lscala/collection/views/SeqTransformations$$anon$16;
   0      6      1    f       Lscala/Function1;


public scala.collection.Iterator iterator();
  Signature: ()Lscala/collection/Iterator;
  Code:
   Stack=1, Locals=1, Args_size=1
	aload_0
	invokestatic	Method scala/collection/IterableViewLike$Sliced$class.iterator:(Lscala/collection/IterableViewLike$Sliced;)Lscala/collection/Iterator;
	areturn
  Labels:

public java.lang.Object apply(int);
  Signature: (I)Ljava/lang/Object;
  Code:
   Stack=2, Locals=2, Args_size=2
	aload_0
	iload_1
	invokestatic	Method scala/collection/SeqViewLike$Sliced$class.apply:(Lscala/collection/SeqViewLike$Sliced;I)Ljava/lang/Object;
	areturn
  Labels:
  LocalVariableTable: 
   Start  Length  Slot  Name   Signature
   0      6      0    this       Lscala/collection/views/SeqTransformations$$anon$16;
   0      6      1    idx       I


public int length();
  Signature: ()I
  Code:
   Stack=1, Locals=1, Args_size=1
	aload_0
	invokestatic	Method scala/collection/SeqViewLike$Sliced$class.length:(Lscala/collection/SeqViewLike$Sliced;)I
	ireturn
  Labels:

}

