Compiled from "Transformed.scala"
public final class scala.collection.views.SeqTransformations$$anon$20 extends scala.collection.views.SeqLike implements scala.collection.SeqViewLike$ZippedAll
  SourceFile: "Transformed.scala"
  Signature: length = 0x2
   00 72 
  Scala: length = 0x
   
  InnerClass: 
   public abstract ZippedAll=class scala/collection/SeqViewLike$ZippedAll of class scala/collection/SeqViewLike
   public abstract ZippedAll=class scala/collection/IterableViewLike$ZippedAll of class scala/collection/IterableViewLike
   public final $anon$20=class scala/collection/views/SeqTransformations$$anon$20 of class scala/collection/views/SeqTransformations
   public abstract Transformed=class scala/collection/TraversableViewLike$Transformed of class scala/collection/TraversableViewLike
  minor version: 0
  major version: 49
  Constant pool:
Asciz	SourceFile;
Asciz	Transformed.scala;
Asciz	bitmap$0;
Asciz	I;
Asciz	underlying;
Asciz	Ljava/lang/Object;;
Asciz	thatSeq;
Asciz	Lscala/collection/Seq;;
Asciz	$outer;
Asciz	Lscala/collection/SeqViewLike;;
Asciz	thatElem;
Asciz	TB;;
Asciz	Signature;
Asciz	thisElem;
Asciz	TA1;;
Asciz	other;
Asciz	Lscala/collection/Iterable;;
Asciz	Lscala/collection/Iterable<TB;>;;
Asciz	<init>;
Asciz	(Lscala/collection/SeqViewLike;Lscala/collection/Iterable;Ljava/lang/Object;Ljava/lang/Object;)V;
Asciz	Code;
Asciz	LineNumberTable;
Asciz	java/lang/NullPointerException;
class	java/lang/NullPointerException
Asciz	()V;
NameAndType	"<init>":()V
Method	java/lang/NullPointerException."<init>":()V
Asciz	scala/collection/views/SeqTransformations$$anon$20;
class	scala/collection/views/SeqTransformations$$anon$20
NameAndType	$outer:Lscala/collection/SeqViewLike;
Field	scala/collection/views/SeqTransformations$$anon$20.$outer:Lscala/collection/SeqViewLike;
Asciz	scala/collection/views/SeqLike;
class	scala/collection/views/SeqLike
Method	scala/collection/views/SeqLike."<init>":()V
Asciz	scala/collection/TraversableViewLike$Transformed$class;
class	scala/collection/TraversableViewLike$Transformed$class
Asciz	$init$;
Asciz	(Lscala/collection/TraversableViewLike$Transformed;)V;
NameAndType	$init$:(Lscala/collection/TraversableViewLike$Transformed;)V
Method	scala/collection/TraversableViewLike$Transformed$class.$init$:(Lscala/collection/TraversableViewLike$Transformed;)V
Asciz	scala/collection/IterableViewLike$ZippedAll$class;
class	scala/collection/IterableViewLike$ZippedAll$class
Asciz	(Lscala/collection/IterableViewLike$ZippedAll;)V;
NameAndType	$init$:(Lscala/collection/IterableViewLike$ZippedAll;)V
Method	scala/collection/IterableViewLike$ZippedAll$class.$init$:(Lscala/collection/IterableViewLike$ZippedAll;)V
Asciz	scala/collection/SeqViewLike$ZippedAll$class;
class	scala/collection/SeqViewLike$ZippedAll$class
Asciz	(Lscala/collection/SeqViewLike$ZippedAll;)V;
NameAndType	$init$:(Lscala/collection/SeqViewLike$ZippedAll;)V
Method	scala/collection/SeqViewLike$ZippedAll$class.$init$:(Lscala/collection/SeqViewLike$ZippedAll;)V
NameAndType	other:Lscala/collection/Iterable;
Field	scala/collection/views/SeqTransformations$$anon$20.other:Lscala/collection/Iterable;
NameAndType	thisElem:Ljava/lang/Object;
Field	scala/collection/views/SeqTransformations$$anon$20.thisElem:Ljava/lang/Object;
NameAndType	thatElem:Ljava/lang/Object;
Field	scala/collection/views/SeqTransformations$$anon$20.thatElem:Ljava/lang/Object;
Asciz	this;
Asciz	Lscala/collection/views/SeqTransformations$$anon$20;;
Asciz	LocalVariableTable;
Asciz	(Lscala/collection/SeqViewLike<TA;TColl;TThis;>;)V;
Asciz	apply;
Asciz	(I)Ljava/lang/Object;;
Asciz	scala/collection/SeqViewLike$ZippedAll;
class	scala/collection/SeqViewLike$ZippedAll
Asciz	(I)Lscala/Tuple2;;
NameAndType	apply:(I)Lscala/Tuple2;
InterfaceMethod	scala/collection/SeqViewLike$ZippedAll.apply:(I)Lscala/Tuple2;
Asciz	idx;
Asciz	(Ljava/lang/Object;)Ljava/lang/Object;;
Asciz	scala/runtime/BoxesRunTime;
class	scala/runtime/BoxesRunTime
Asciz	unboxToInt;
Asciz	(Ljava/lang/Object;)I;
NameAndType	unboxToInt:(Ljava/lang/Object;)I
Method	scala/runtime/BoxesRunTime.unboxToInt:(Ljava/lang/Object;)I
Asciz	v1;
Asciz	scala$collection$TraversableViewLike$Transformed$$$outer;
Asciz	()Lscala/collection/TraversableViewLike;;
Asciz	scala$collection$IterableViewLike$ZippedAll$$$outer;
Asciz	()Lscala/collection/IterableViewLike;;
Asciz	scala$collection$SeqViewLike$ZippedAll$$$outer;
Asciz	()Lscala/collection/SeqViewLike;;
Asciz	()Ljava/lang/Object;;
Asciz	()TB;;
Asciz	()TA1;;
Asciz	()Lscala/collection/Iterable;;
Asciz	()Lscala/collection/Iterable<TB;>;;
NameAndType	bitmap$0:I
Field	scala/collection/views/SeqTransformations$$anon$20.bitmap$0:I
Asciz	(Lscala/collection/TraversableViewLike$Transformed;)Ljava/lang/Object;;
NameAndType	underlying:(Lscala/collection/TraversableViewLike$Transformed;)Ljava/lang/Object;
Method	scala/collection/TraversableViewLike$Transformed$class.underlying:(Lscala/collection/TraversableViewLike$Transformed;)Ljava/lang/Object;
NameAndType	underlying:Ljava/lang/Object;
Field	scala/collection/views/SeqTransformations$$anon$20.underlying:Ljava/lang/Object;
Asciz	iterator;
Asciz	()Lscala/collection/Iterator;;
Asciz	(Lscala/collection/IterableViewLike$ZippedAll;)Lscala/collection/Iterator;;
NameAndType	iterator:(Lscala/collection/IterableViewLike$ZippedAll;)Lscala/collection/Iterator;
Method	scala/collection/IterableViewLike$ZippedAll$class.iterator:(Lscala/collection/IterableViewLike$ZippedAll;)Lscala/collection/Iterator;
Asciz	(Lscala/collection/SeqViewLike$ZippedAll;I)Lscala/Tuple2;;
NameAndType	apply:(Lscala/collection/SeqViewLike$ZippedAll;I)Lscala/Tuple2;
Method	scala/collection/SeqViewLike$ZippedAll$class.apply:(Lscala/collection/SeqViewLike$ZippedAll;I)Lscala/Tuple2;
Asciz	length;
Asciz	()I;
Asciz	(Lscala/collection/SeqViewLike$ZippedAll;)I;
NameAndType	length:(Lscala/collection/SeqViewLike$ZippedAll;)I
Method	scala/collection/SeqViewLike$ZippedAll$class.length:(Lscala/collection/SeqViewLike$ZippedAll;)I
Asciz	()Lscala/collection/Seq;;
Asciz	(Lscala/collection/SeqViewLike$ZippedAll;)Lscala/collection/Seq;;
NameAndType	thatSeq:(Lscala/collection/SeqViewLike$ZippedAll;)Lscala/collection/Seq;
Method	scala/collection/SeqViewLike$ZippedAll$class.thatSeq:(Lscala/collection/SeqViewLike$ZippedAll;)Lscala/collection/Seq;
NameAndType	thatSeq:Lscala/collection/Seq;
Field	scala/collection/views/SeqTransformations$$anon$20.thatSeq:Lscala/collection/Seq;
Asciz	Lscala/collection/views/SeqLike<Lscala/Tuple2<TA1;TB;>;TColl;>;Lscala/collection/SeqViewLike<TA;TColl;TThis;>.ZippedAll<TA1;TB;>;;
Asciz	Scala;
Asciz	InnerClasses;
Asciz	scala/collection/SeqViewLike;
class	scala/collection/SeqViewLike
Asciz	ZippedAll;
Asciz	scala/collection/IterableViewLike$ZippedAll;
class	scala/collection/IterableViewLike$ZippedAll
Asciz	scala/collection/IterableViewLike;
class	scala/collection/IterableViewLike
Asciz	scala/collection/views/SeqTransformations;
class	scala/collection/views/SeqTransformations
Asciz	$anon$20;
Asciz	scala/collection/TraversableViewLike$Transformed;
class	scala/collection/TraversableViewLike$Transformed
Asciz	scala/collection/TraversableViewLike;
class	scala/collection/TraversableViewLike
Asciz	Transformed;

{
public volatile int bitmap$0;
  Signature: I

private final java.lang.Object underlying;
  Signature: Ljava/lang/Object;

private final scala.collection.Seq thatSeq;
  Signature: Lscala/collection/Seq;

private final scala.collection.SeqViewLike $outer;
  Signature: Lscala/collection/SeqViewLike;

private final java.lang.Object thatElem;
  Signature: Ljava/lang/Object;
  Signature: length = 0x2
   00 0C 

private final java.lang.Object thisElem;
  Signature: Ljava/lang/Object;
  Signature: length = 0x2
   00 0F 

private final scala.collection.Iterable other;
  Signature: Lscala/collection/Iterable;
  Signature: length = 0x2
   00 12 

public scala.collection.views.SeqTransformations$$anon$20(scala.collection.SeqViewLike, scala.collection.Iterable, java.lang.Object, java.lang.Object);
  Signature: (Lscala/collection/SeqViewLike;Lscala/collection/Iterable;Ljava/lang/Object;Ljava/lang/Object;)V
  Code:
   Stack=2, Locals=5, Args_size=5
	aload_1
	ifnonnull	l1 // aload_0
	new	class java/lang/NullPointerException
	dup
	invokespecial	Method java/lang/NullPointerException."<init>":()V
	athrow
l1	aload_0
	aload_1
	putfield	Field $outer:Lscala/collection/SeqViewLike;
	aload_0
	invokespecial	Method scala/collection/views/SeqLike."<init>":()V
	aload_0
	invokestatic	Method scala/collection/TraversableViewLike$Transformed$class.$init$:(Lscala/collection/TraversableViewLike$Transformed;)V
	aload_0
	invokestatic	Method scala/collection/IterableViewLike$ZippedAll$class.$init$:(Lscala/collection/IterableViewLike$ZippedAll;)V
	aload_0
	invokestatic	Method scala/collection/SeqViewLike$ZippedAll$class.$init$:(Lscala/collection/SeqViewLike$ZippedAll;)V
	aload_0
	aload_2
	putfield	Field other:Lscala/collection/Iterable;
	aload_0
	aload_3
	putfield	Field thisElem:Ljava/lang/Object;
	aload_0
	aload	4
	putfield	Field thatElem:Ljava/lang/Object;
	return
  Labels:
   	l1 = 12 // aload_0
  LocalVariableTable: 
   Start  Length  Slot  Name   Signature
   0      50      0    this       Lscala/collection/views/SeqTransformations$$anon$20;
   0      50      1    $outer       Lscala/collection/SeqViewLike;

  Signature: length = 0x2
   00 3C 

public java.lang.Object apply(int);
  Signature: (I)Ljava/lang/Object;
  Code:
   Stack=2, Locals=2, Args_size=2
	aload_0
	iload_1
	invokeinterface	InterfaceMethod scala/collection/SeqViewLike$ZippedAll.apply:(I)Lscala/Tuple2;
	areturn
  Labels:
  LocalVariableTable: 
   Start  Length  Slot  Name   Signature
   0      8      0    this       Lscala/collection/views/SeqTransformations$$anon$20;
   0      8      1    idx       I


public java.lang.Object apply(java.lang.Object);
  Signature: (Ljava/lang/Object;)Ljava/lang/Object;
  Code:
   Stack=2, Locals=2, Args_size=2
	aload_0
	aload_1
	invokestatic	Method scala/runtime/BoxesRunTime.unboxToInt:(Ljava/lang/Object;)I
	invokeinterface	InterfaceMethod scala/collection/SeqViewLike$ZippedAll.apply:(I)Lscala/Tuple2;
	areturn
  Labels:
  LocalVariableTable: 
   Start  Length  Slot  Name   Signature
   0      11      0    this       Lscala/collection/views/SeqTransformations$$anon$20;
   0      11      1    v1       Ljava/lang/Object;


public scala.collection.TraversableViewLike scala$collection$TraversableViewLike$Transformed$$$outer();
  Signature: ()Lscala/collection/TraversableViewLike;
  Code:
   Stack=1, Locals=1, Args_size=1
	aload_0
	getfield	Field $outer:Lscala/collection/SeqViewLike;
	areturn
  Labels:

public scala.collection.IterableViewLike scala$collection$IterableViewLike$ZippedAll$$$outer();
  Signature: ()Lscala/collection/IterableViewLike;
  Code:
   Stack=1, Locals=1, Args_size=1
	aload_0
	getfield	Field $outer:Lscala/collection/SeqViewLike;
	areturn
  Labels:

public scala.collection.SeqViewLike scala$collection$SeqViewLike$ZippedAll$$$outer();
  Signature: ()Lscala/collection/SeqViewLike;
  Code:
   Stack=1, Locals=1, Args_size=1
	aload_0
	getfield	Field $outer:Lscala/collection/SeqViewLike;
	areturn
  Labels:

public java.lang.Object thatElem();
  Signature: ()Ljava/lang/Object;
  Code:
   Stack=1, Locals=1, Args_size=1
	aload_0
	getfield	Field thatElem:Ljava/lang/Object;
	areturn
  Labels:
  Signature: length = 0x2
   00 54 

public java.lang.Object thisElem();
  Signature: ()Ljava/lang/Object;
  Code:
   Stack=1, Locals=1, Args_size=1
	aload_0
	getfield	Field thisElem:Ljava/lang/Object;
	areturn
  Labels:
  Signature: length = 0x2
   00 55 

public scala.collection.Iterable other();
  Signature: ()Lscala/collection/Iterable;
  Code:
   Stack=1, Locals=1, Args_size=1
	aload_0
	getfield	Field other:Lscala/collection/Iterable;
	areturn
  Labels:
  Signature: length = 0x2
   00 57 

public java.lang.Object underlying();
  Signature: ()Ljava/lang/Object;
  Code:
   Stack=3, Locals=1, Args_size=1
	aload_0
	getfield	Field bitmap$0:I
	iconst_4
	iand
	iconst_0
	if_icmpne	l1 // aload_0
	aload_0
	dup
	pop
	monitorenter
	aload_0
	getfield	Field bitmap$0:I
	iconst_4
	iand
	iconst_0
	if_icmpne	l2 // aload_0
	aload_0
	aload_0
	invokestatic	Method scala/collection/TraversableViewLike$Transformed$class.underlying:(Lscala/collection/TraversableViewLike$Transformed;)Ljava/lang/Object;
	putfield	Field underlying:Ljava/lang/Object;
	aload_0
	aload_0
	getfield	Field bitmap$0:I
	iconst_4
	ior
	putfield	Field bitmap$0:I
l2	aload_0
	monitorexit
l1	aload_0
	getfield	Field underlying:Ljava/lang/Object;
	areturn
	aload_0
	monitorexit
	athrow
  Labels:
   	l2 = 42 // aload_0
   	l1 = 44 // aload_0
  Exception table:
   from   to  target type
    14    44    49   any

public scala.collection.Iterator iterator();
  Signature: ()Lscala/collection/Iterator;
  Code:
   Stack=1, Locals=1, Args_size=1
	aload_0
	invokestatic	Method scala/collection/IterableViewLike$ZippedAll$class.iterator:(Lscala/collection/IterableViewLike$ZippedAll;)Lscala/collection/Iterator;
	areturn
  Labels:

public scala.Tuple2 apply(int);
  Signature: (I)Lscala/Tuple2;
  Code:
   Stack=2, Locals=2, Args_size=2
	aload_0
	iload_1
	invokestatic	Method scala/collection/SeqViewLike$ZippedAll$class.apply:(Lscala/collection/SeqViewLike$ZippedAll;I)Lscala/Tuple2;
	areturn
  Labels:
  LocalVariableTable: 
   Start  Length  Slot  Name   Signature
   0      6      0    this       Lscala/collection/views/SeqTransformations$$anon$20;
   0      6      1    idx       I


public int length();
  Signature: ()I
  Code:
   Stack=1, Locals=1, Args_size=1
	aload_0
	invokestatic	Method scala/collection/SeqViewLike$ZippedAll$class.length:(Lscala/collection/SeqViewLike$ZippedAll;)I
	ireturn
  Labels:

public scala.collection.Seq thatSeq();
  Signature: ()Lscala/collection/Seq;
  Code:
   Stack=3, Locals=1, Args_size=1
	aload_0
	getfield	Field bitmap$0:I
	iconst_1
	iand
	iconst_0
	if_icmpne	l1 // aload_0
	aload_0
	dup
	pop
	monitorenter
	aload_0
	getfield	Field bitmap$0:I
	iconst_1
	iand
	iconst_0
	if_icmpne	l2 // aload_0
	aload_0
	aload_0
	invokestatic	Method scala/collection/SeqViewLike$ZippedAll$class.thatSeq:(Lscala/collection/SeqViewLike$ZippedAll;)Lscala/collection/Seq;
	putfield	Field thatSeq:Lscala/collection/Seq;
	aload_0
	aload_0
	getfield	Field bitmap$0:I
	iconst_1
	ior
	putfield	Field bitmap$0:I
l2	aload_0
	monitorexit
l1	aload_0
	getfield	Field thatSeq:Lscala/collection/Seq;
	areturn
	aload_0
	monitorexit
	athrow
  Labels:
   	l2 = 42 // aload_0
   	l1 = 44 // aload_0
  Exception table:
   from   to  target type
    14    44    49   any

}

