Compiled from "Transformed.scala"
public abstract class scala.collection.views.TraversableLike extends java.lang.Object implements scala.collection.TraversableView,scala.collection.views.Transformed,scala.ScalaObject
  SourceFile: "Transformed.scala"
  Signature: length = 0x2
   01 FFFFFFC0 
  ScalaSig: length = 0x17A
   05 00 40 06 06 01 02 FFFFFF81 00 04 08 02 0F 54 72 61
   76 65 72 73 61 62 6C 65 4C 69 6B 65 0A 02 03 04
   01 05 76 69 65 77 73 0A 02 05 06 01 0A 63 6F 6C
   6C 65 63 74 69 6F 6E 0A 01 07 01 05 73 63 61 6C
   61 15 03 09 18 24 13 05 00 0A 12 26 2A 10 02 0B
   10 0D 01 0C 0A 02 0D 0E 01 04 6C 61 6E 67 0A 01
   0F 01 04 6A 61 76 61 09 02 11 0C 02 06 4F 62 6A
   65 63 74 10 04 13 14 16 23 0D 01 04 09 02 15 04
   02 0F 54 72 61 76 65 72 73 61 62 6C 65 56 69 65
   77 10 02 17 18 0C 00 04 08 19 00 FFFFFF84 FFFFFF80 FFFFFF84 FFFFFFC2 00
   1B 02 01 42 03 00 11 02 1C 20 10 02 1D 1E 0D 01
   06 09 02 1F 06 02 07 4E 6F 74 68 69 6E 67 10 02
   1D 21 09 02 22 06 02 03 41 6E 79 10 02 17 24 04
   08 25 00 FFFFFF84 FFFFFF80 FFFFFF84 FFFFFFC2 00 1B 02 04 43 6F 6C 6C 10
   02 27 28 0D 01 02 09 02 29 02 02 0B 54 72 61 6E
   73 66 6F 72 6D 65 64 10 02 1D 2B 09 02 2C 06 02
   0B 53 63 61 6C 61 4F 62 6A 65 63 74 08 05 2E 00
   FFFFFF84 00 2F 01 06 3C 69 6E 69 74 3E 14 01 30 10 04
   27 00 16 23 08 05 32 00 FFFFFF86 20 33 01 07 66 6F 72
   65 61 63 68 15 02 34 3E 14 02 35 38 10 02 1D 36
   09 02 37 06 02 04 55 6E 69 74 08 05 39 31 FFFFFFC0 00
   3A 01 01 66 10 04 1D 3B 16 3D 09 02 3C 06 02 09
   46 75 6E 63 74 69 6F 6E 31 10 02 17 3E 04 08 3F
   31 FFFFFF84 FFFFFF80 FFFFFF80 FFFFFFC2 00 1B 02 01 43 
  InnerClass: 
   public abstract $less$colon$less=class scala/Predef$$less$colon$less of class scala/Predef
   public WithFilter=class scala/collection/TraversableLike$WithFilter of class scala/collection/TraversableLike
   public abstract Transformed=class scala/collection/TraversableViewLike$Transformed of class scala/collection/TraversableViewLike
  minor version: 0
  major version: 49
  Constant pool:
Asciz	SourceFile;
Asciz	Transformed.scala;
Asciz	<init>;
Asciz	()V;
Asciz	Code;
Asciz	LineNumberTable;
Asciz	java/lang/Object;
class	java/lang/Object
NameAndType	"<init>":()V
Method	java/lang/Object."<init>":()V
Asciz	scala/collection/TraversableLike$class;
class	scala/collection/TraversableLike$class
Asciz	$init$;
Asciz	(Lscala/collection/TraversableLike;)V;
NameAndType	$init$:(Lscala/collection/TraversableLike;)V
Method	scala/collection/TraversableLike$class.$init$:(Lscala/collection/TraversableLike;)V
Asciz	scala/collection/generic/GenericTraversableTemplate$class;
class	scala/collection/generic/GenericTraversableTemplate$class
Asciz	(Lscala/collection/generic/GenericTraversableTemplate;)V;
NameAndType	$init$:(Lscala/collection/generic/GenericTraversableTemplate;)V
Method	scala/collection/generic/GenericTraversableTemplate$class.$init$:(Lscala/collection/generic/GenericTraversableTemplate;)V
Asciz	scala/collection/Traversable$class;
class	scala/collection/Traversable$class
Asciz	(Lscala/collection/Traversable;)V;
NameAndType	$init$:(Lscala/collection/Traversable;)V
Method	scala/collection/Traversable$class.$init$:(Lscala/collection/Traversable;)V
Asciz	scala/collection/views/TraversableTransformations$class;
class	scala/collection/views/TraversableTransformations$class
Asciz	(Lscala/collection/TraversableViewLike;)V;
NameAndType	$init$:(Lscala/collection/TraversableViewLike;)V
Method	scala/collection/views/TraversableTransformations$class.$init$:(Lscala/collection/TraversableViewLike;)V
Asciz	scala/collection/TraversableViewLike$class;
class	scala/collection/TraversableViewLike$class
Method	scala/collection/TraversableViewLike$class.$init$:(Lscala/collection/TraversableViewLike;)V
Asciz	Signature;
Asciz	filter;
Asciz	(Lscala/Function1;)Ljava/lang/Object;;
Asciz	scala/collection/TraversableViewLike;
class	scala/collection/TraversableViewLike
Asciz	(Lscala/Function1;)Lscala/collection/TraversableView;;
NameAndType	filter:(Lscala/Function1;)Lscala/collection/TraversableView;
InterfaceMethod	scala/collection/TraversableViewLike.filter:(Lscala/Function1;)Lscala/collection/TraversableView;
Asciz	this;
Asciz	Lscala/collection/views/TraversableLike;;
Asciz	p;
Asciz	Lscala/Function1;;
Asciz	LocalVariableTable;
Asciz	init;
Asciz	()Ljava/lang/Object;;
Asciz	()Lscala/collection/TraversableView;;
NameAndType	init:()Lscala/collection/TraversableView;
InterfaceMethod	scala/collection/TraversableViewLike.init:()Lscala/collection/TraversableView;
Asciz	drop;
Asciz	(I)Ljava/lang/Object;;
Asciz	(I)Lscala/collection/TraversableView;;
NameAndType	drop:(I)Lscala/collection/TraversableView;
InterfaceMethod	scala/collection/TraversableViewLike.drop:(I)Lscala/collection/TraversableView;
Asciz	n;
Asciz	I;
Asciz	take;
NameAndType	take:(I)Lscala/collection/TraversableView;
InterfaceMethod	scala/collection/TraversableViewLike.take:(I)Lscala/collection/TraversableView;
Asciz	slice;
Asciz	(II)Ljava/lang/Object;;
Asciz	(II)Lscala/collection/TraversableView;;
NameAndType	slice:(II)Lscala/collection/TraversableView;
InterfaceMethod	scala/collection/TraversableViewLike.slice:(II)Lscala/collection/TraversableView;
Asciz	from;
Asciz	until;
Asciz	dropWhile;
NameAndType	dropWhile:(Lscala/Function1;)Lscala/collection/TraversableView;
InterfaceMethod	scala/collection/TraversableViewLike.dropWhile:(Lscala/Function1;)Lscala/collection/TraversableView;
Asciz	takeWhile;
NameAndType	takeWhile:(Lscala/Function1;)Lscala/collection/TraversableView;
InterfaceMethod	scala/collection/TraversableViewLike.takeWhile:(Lscala/Function1;)Lscala/collection/TraversableView;
Asciz	foreach;
Asciz	(Lscala/Function1;)V;
Asciz	<C:Ljava/lang/Object;>(Lscala/Function1<TB;TC;>;)V;
Asciz	withFilter;
Asciz	(Lscala/Function1;)Lscala/collection/TraversableLike$WithFilter;;
Asciz	(Lscala/collection/TraversableLike;Lscala/Function1;)Lscala/collection/TraversableLike$WithFilter;;
NameAndType	withFilter:(Lscala/collection/TraversableLike;Lscala/Function1;)Lscala/collection/TraversableLike$WithFilter;
Method	scala/collection/TraversableLike$class.withFilter:(Lscala/collection/TraversableLike;Lscala/Function1;)Lscala/collection/TraversableLike$WithFilter;
Asciz	view;
Asciz	(Lscala/collection/TraversableLike;II)Lscala/collection/TraversableView;;
NameAndType	view:(Lscala/collection/TraversableLike;II)Lscala/collection/TraversableView;
Method	scala/collection/TraversableLike$class.view:(Lscala/collection/TraversableLike;II)Lscala/collection/TraversableView;
Asciz	(Lscala/collection/TraversableLike;)Lscala/collection/TraversableView;;
NameAndType	view:(Lscala/collection/TraversableLike;)Lscala/collection/TraversableView;
Method	scala/collection/TraversableLike$class.view:(Lscala/collection/TraversableLike;)Lscala/collection/TraversableView;
Asciz	toString;
Asciz	()Ljava/lang/String;;
Asciz	(Lscala/collection/TraversableLike;)Ljava/lang/String;;
NameAndType	toString:(Lscala/collection/TraversableLike;)Ljava/lang/String;
Method	scala/collection/TraversableLike$class.toString:(Lscala/collection/TraversableLike;)Ljava/lang/String;
Asciz	addString;
Asciz	(Lscala/collection/mutable/StringBuilder;)Lscala/collection/mutable/StringBuilder;;
Asciz	(Lscala/collection/TraversableLike;Lscala/collection/mutable/StringBuilder;)Lscala/collection/mutable/StringBuilder;;
NameAndType	addString:(Lscala/collection/TraversableLike;Lscala/collection/mutable/StringBuilder;)Lscala/collection/mutable/StringBuilder;
Method	scala/collection/TraversableLike$class.addString:(Lscala/collection/TraversableLike;Lscala/collection/mutable/StringBuilder;)Lscala/collection/mutable/StringBuilder;
Asciz	b;
Asciz	Lscala/collection/mutable/StringBuilder;;
Asciz	(Lscala/collection/mutable/StringBuilder;Ljava/lang/String;)Lscala/collection/mutable/StringBuilder;;
Asciz	(Lscala/collection/TraversableLike;Lscala/collection/mutable/StringBuilder;Ljava/lang/String;)Lscala/collection/mutable/StringBuilder;;
NameAndType	addString:(Lscala/collection/TraversableLike;Lscala/collection/mutable/StringBuilder;Ljava/lang/String;)Lscala/collection/mutable/StringBuilder;
Method	scala/collection/TraversableLike$class.addString:(Lscala/collection/TraversableLike;Lscala/collection/mutable/StringBuilder;Ljava/lang/String;)Lscala/collection/mutable/StringBuilder;
Asciz	sep;
Asciz	Ljava/lang/String;;
Asciz	(Lscala/collection/mutable/StringBuilder;Ljava/lang/String;Ljava/lang/String;Ljava/lang/String;)Lscala/collection/mutable/StringBuilder;;
Asciz	(Lscala/collection/TraversableLike;Lscala/collection/mutable/StringBuilder;Ljava/lang/String;Ljava/lang/String;Ljava/lang/String;)Lscala/collection/mutable/StringBuilder;;
NameAndType	addString:(Lscala/collection/TraversableLike;Lscala/collection/mutable/StringBuilder;Ljava/lang/String;Ljava/lang/String;Ljava/lang/String;)Lscala/collection/mutable/StringBuilder;
Method	scala/collection/TraversableLike$class.addString:(Lscala/collection/TraversableLike;Lscala/collection/mutable/StringBuilder;Ljava/lang/String;Ljava/lang/String;Ljava/lang/String;)Lscala/collection/mutable/StringBuilder;
Asciz	start;
Asciz	end;
Asciz	mkString;
NameAndType	mkString:(Lscala/collection/TraversableLike;)Ljava/lang/String;
Method	scala/collection/TraversableLike$class.mkString:(Lscala/collection/TraversableLike;)Ljava/lang/String;
Asciz	(Ljava/lang/String;)Ljava/lang/String;;
Asciz	(Lscala/collection/TraversableLike;Ljava/lang/String;)Ljava/lang/String;;
NameAndType	mkString:(Lscala/collection/TraversableLike;Ljava/lang/String;)Ljava/lang/String;
Method	scala/collection/TraversableLike$class.mkString:(Lscala/collection/TraversableLike;Ljava/lang/String;)Ljava/lang/String;
Asciz	(Ljava/lang/String;Ljava/lang/String;Ljava/lang/String;)Ljava/lang/String;;
Asciz	(Lscala/collection/TraversableLike;Ljava/lang/String;Ljava/lang/String;Ljava/lang/String;)Ljava/lang/String;;
NameAndType	mkString:(Lscala/collection/TraversableLike;Ljava/lang/String;Ljava/lang/String;Ljava/lang/String;)Ljava/lang/String;
Method	scala/collection/TraversableLike$class.mkString:(Lscala/collection/TraversableLike;Ljava/lang/String;Ljava/lang/String;Ljava/lang/String;)Ljava/lang/String;
Asciz	toMap;
Asciz	(Lscala/Predef$$less$colon$less;)Lscala/collection/immutable/Map;;
Asciz	(Lscala/collection/TraversableLike;Lscala/Predef$$less$colon$less;)Lscala/collection/immutable/Map;;
NameAndType	toMap:(Lscala/collection/TraversableLike;Lscala/Predef$$less$colon$less;)Lscala/collection/immutable/Map;
Method	scala/collection/TraversableLike$class.toMap:(Lscala/collection/TraversableLike;Lscala/Predef$$less$colon$less;)Lscala/collection/immutable/Map;
Asciz	ev;
Asciz	Lscala/Predef$$less$colon$less;;
Asciz	toSet;
Asciz	()Lscala/collection/immutable/Set;;
Asciz	(Lscala/collection/TraversableLike;)Lscala/collection/immutable/Set;;
NameAndType	toSet:(Lscala/collection/TraversableLike;)Lscala/collection/immutable/Set;
Method	scala/collection/TraversableLike$class.toSet:(Lscala/collection/TraversableLike;)Lscala/collection/immutable/Set;
Asciz	toStream;
Asciz	()Lscala/collection/immutable/Stream;;
Asciz	(Lscala/collection/TraversableLike;)Lscala/collection/immutable/Stream;;
NameAndType	toStream:(Lscala/collection/TraversableLike;)Lscala/collection/immutable/Stream;
Method	scala/collection/TraversableLike$class.toStream:(Lscala/collection/TraversableLike;)Lscala/collection/immutable/Stream;
Asciz	toIndexedSeq;
Asciz	()Lscala/collection/mutable/IndexedSeq;;
Asciz	(Lscala/collection/TraversableLike;)Lscala/collection/mutable/IndexedSeq;;
NameAndType	toIndexedSeq:(Lscala/collection/TraversableLike;)Lscala/collection/mutable/IndexedSeq;
Method	scala/collection/TraversableLike$class.toIndexedSeq:(Lscala/collection/TraversableLike;)Lscala/collection/mutable/IndexedSeq;
Asciz	toSeq;
Asciz	()Lscala/collection/Seq;;
Asciz	(Lscala/collection/TraversableLike;)Lscala/collection/Seq;;
NameAndType	toSeq:(Lscala/collection/TraversableLike;)Lscala/collection/Seq;
Method	scala/collection/TraversableLike$class.toSeq:(Lscala/collection/TraversableLike;)Lscala/collection/Seq;
Asciz	toIterable;
Asciz	()Lscala/collection/Iterable;;
Asciz	(Lscala/collection/TraversableLike;)Lscala/collection/Iterable;;
NameAndType	toIterable:(Lscala/collection/TraversableLike;)Lscala/collection/Iterable;
Method	scala/collection/TraversableLike$class.toIterable:(Lscala/collection/TraversableLike;)Lscala/collection/Iterable;
Asciz	toList;
Asciz	()Lscala/collection/immutable/List;;
Asciz	(Lscala/collection/TraversableLike;)Lscala/collection/immutable/List;;
NameAndType	toList:(Lscala/collection/TraversableLike;)Lscala/collection/immutable/List;
Method	scala/collection/TraversableLike$class.toList:(Lscala/collection/TraversableLike;)Lscala/collection/immutable/List;
Asciz	toArray;
Asciz	(Lscala/reflect/ClassManifest;)Ljava/lang/Object;;
Asciz	(Lscala/collection/TraversableLike;Lscala/reflect/ClassManifest;)Ljava/lang/Object;;
NameAndType	toArray:(Lscala/collection/TraversableLike;Lscala/reflect/ClassManifest;)Ljava/lang/Object;
Method	scala/collection/TraversableLike$class.toArray:(Lscala/collection/TraversableLike;Lscala/reflect/ClassManifest;)Ljava/lang/Object;
Asciz	evidence$1;
Asciz	Lscala/reflect/ClassManifest;;
Asciz	copyToArray;
Asciz	(Ljava/lang/Object;)V;
Asciz	(Lscala/collection/TraversableLike;Ljava/lang/Object;)V;
NameAndType	copyToArray:(Lscala/collection/TraversableLike;Ljava/lang/Object;)V
Method	scala/collection/TraversableLike$class.copyToArray:(Lscala/collection/TraversableLike;Ljava/lang/Object;)V
Asciz	xs;
Asciz	Ljava/lang/Object;;
Asciz	(Ljava/lang/Object;I)V;
Asciz	(Lscala/collection/TraversableLike;Ljava/lang/Object;I)V;
NameAndType	copyToArray:(Lscala/collection/TraversableLike;Ljava/lang/Object;I)V
Method	scala/collection/TraversableLike$class.copyToArray:(Lscala/collection/TraversableLike;Ljava/lang/Object;I)V
Asciz	(Ljava/lang/Object;II)V;
Asciz	(Lscala/collection/TraversableLike;Ljava/lang/Object;II)V;
NameAndType	copyToArray:(Lscala/collection/TraversableLike;Ljava/lang/Object;II)V
Method	scala/collection/TraversableLike$class.copyToArray:(Lscala/collection/TraversableLike;Ljava/lang/Object;II)V
Asciz	len;
Asciz	copyToBuffer;
Asciz	(Lscala/collection/mutable/Buffer;)V;
Asciz	(Lscala/collection/TraversableLike;Lscala/collection/mutable/Buffer;)V;
NameAndType	copyToBuffer:(Lscala/collection/TraversableLike;Lscala/collection/mutable/Buffer;)V
Method	scala/collection/TraversableLike$class.copyToBuffer:(Lscala/collection/TraversableLike;Lscala/collection/mutable/Buffer;)V
Asciz	dest;
Asciz	Lscala/collection/mutable/Buffer;;
Asciz	lastOption;
Asciz	()Lscala/Option;;
Asciz	(Lscala/collection/TraversableLike;)Lscala/Option;;
NameAndType	lastOption:(Lscala/collection/TraversableLike;)Lscala/Option;
Method	scala/collection/TraversableLike$class.lastOption:(Lscala/collection/TraversableLike;)Lscala/Option;
Asciz	last;
Asciz	(Lscala/collection/TraversableLike;)Ljava/lang/Object;;
NameAndType	last:(Lscala/collection/TraversableLike;)Ljava/lang/Object;
Method	scala/collection/TraversableLike$class.last:(Lscala/collection/TraversableLike;)Ljava/lang/Object;
Asciz	tail;
NameAndType	tail:(Lscala/collection/TraversableLike;)Ljava/lang/Object;
Method	scala/collection/TraversableLike$class.tail:(Lscala/collection/TraversableLike;)Ljava/lang/Object;
Asciz	headOption;
NameAndType	headOption:(Lscala/collection/TraversableLike;)Lscala/Option;
Method	scala/collection/TraversableLike$class.headOption:(Lscala/collection/TraversableLike;)Lscala/Option;
Asciz	head;
NameAndType	head:(Lscala/collection/TraversableLike;)Ljava/lang/Object;
Method	scala/collection/TraversableLike$class.head:(Lscala/collection/TraversableLike;)Ljava/lang/Object;
Asciz	max;
Asciz	(Lscala/math/Ordering;)Ljava/lang/Object;;
Asciz	(Lscala/collection/TraversableLike;Lscala/math/Ordering;)Ljava/lang/Object;;
NameAndType	max:(Lscala/collection/TraversableLike;Lscala/math/Ordering;)Ljava/lang/Object;
Method	scala/collection/TraversableLike$class.max:(Lscala/collection/TraversableLike;Lscala/math/Ordering;)Ljava/lang/Object;
Asciz	cmp;
Asciz	Lscala/math/Ordering;;
Asciz	min;
NameAndType	min:(Lscala/collection/TraversableLike;Lscala/math/Ordering;)Ljava/lang/Object;
Method	scala/collection/TraversableLike$class.min:(Lscala/collection/TraversableLike;Lscala/math/Ordering;)Ljava/lang/Object;
Asciz	product;
Asciz	(Lscala/math/Numeric;)Ljava/lang/Object;;
Asciz	(Lscala/collection/TraversableLike;Lscala/math/Numeric;)Ljava/lang/Object;;
NameAndType	product:(Lscala/collection/TraversableLike;Lscala/math/Numeric;)Ljava/lang/Object;
Method	scala/collection/TraversableLike$class.product:(Lscala/collection/TraversableLike;Lscala/math/Numeric;)Ljava/lang/Object;
Asciz	num;
Asciz	Lscala/math/Numeric;;
Asciz	sum;
NameAndType	sum:(Lscala/collection/TraversableLike;Lscala/math/Numeric;)Ljava/lang/Object;
Method	scala/collection/TraversableLike$class.sum:(Lscala/collection/TraversableLike;Lscala/math/Numeric;)Ljava/lang/Object;
Asciz	reduceRightOption;
Asciz	(Lscala/Function2;)Lscala/Option;;
Asciz	(Lscala/collection/TraversableLike;Lscala/Function2;)Lscala/Option;;
NameAndType	reduceRightOption:(Lscala/collection/TraversableLike;Lscala/Function2;)Lscala/Option;
Method	scala/collection/TraversableLike$class.reduceRightOption:(Lscala/collection/TraversableLike;Lscala/Function2;)Lscala/Option;
Asciz	op;
Asciz	Lscala/Function2;;
Asciz	reduceRight;
Asciz	(Lscala/Function2;)Ljava/lang/Object;;
Asciz	(Lscala/collection/TraversableLike;Lscala/Function2;)Ljava/lang/Object;;
NameAndType	reduceRight:(Lscala/collection/TraversableLike;Lscala/Function2;)Ljava/lang/Object;
Method	scala/collection/TraversableLike$class.reduceRight:(Lscala/collection/TraversableLike;Lscala/Function2;)Ljava/lang/Object;
Asciz	reduceLeftOption;
NameAndType	reduceLeftOption:(Lscala/collection/TraversableLike;Lscala/Function2;)Lscala/Option;
Method	scala/collection/TraversableLike$class.reduceLeftOption:(Lscala/collection/TraversableLike;Lscala/Function2;)Lscala/Option;
Asciz	reduceLeft;
NameAndType	reduceLeft:(Lscala/collection/TraversableLike;Lscala/Function2;)Ljava/lang/Object;
Method	scala/collection/TraversableLike$class.reduceLeft:(Lscala/collection/TraversableLike;Lscala/Function2;)Ljava/lang/Object;
Asciz	$colon$bslash;
Asciz	(Ljava/lang/Object;Lscala/Function2;)Ljava/lang/Object;;
Asciz	(Lscala/collection/TraversableLike;Ljava/lang/Object;Lscala/Function2;)Ljava/lang/Object;;
NameAndType	$colon$bslash:(Lscala/collection/TraversableLike;Ljava/lang/Object;Lscala/Function2;)Ljava/lang/Object;
Method	scala/collection/TraversableLike$class.$colon$bslash:(Lscala/collection/TraversableLike;Ljava/lang/Object;Lscala/Function2;)Ljava/lang/Object;
Asciz	z;
Asciz	foldRight;
NameAndType	foldRight:(Lscala/collection/TraversableLike;Ljava/lang/Object;Lscala/Function2;)Ljava/lang/Object;
Method	scala/collection/TraversableLike$class.foldRight:(Lscala/collection/TraversableLike;Ljava/lang/Object;Lscala/Function2;)Ljava/lang/Object;
Asciz	$div$colon;
NameAndType	$div$colon:(Lscala/collection/TraversableLike;Ljava/lang/Object;Lscala/Function2;)Ljava/lang/Object;
Method	scala/collection/TraversableLike$class.$div$colon:(Lscala/collection/TraversableLike;Ljava/lang/Object;Lscala/Function2;)Ljava/lang/Object;
Asciz	foldLeft;
NameAndType	foldLeft:(Lscala/collection/TraversableLike;Ljava/lang/Object;Lscala/Function2;)Ljava/lang/Object;
Method	scala/collection/TraversableLike$class.foldLeft:(Lscala/collection/TraversableLike;Ljava/lang/Object;Lscala/Function2;)Ljava/lang/Object;
Asciz	find;
Asciz	(Lscala/Function1;)Lscala/Option;;
Asciz	(Lscala/collection/TraversableLike;Lscala/Function1;)Lscala/Option;;
NameAndType	find:(Lscala/collection/TraversableLike;Lscala/Function1;)Lscala/Option;
Method	scala/collection/TraversableLike$class.find:(Lscala/collection/TraversableLike;Lscala/Function1;)Lscala/Option;
Asciz	count;
Asciz	(Lscala/Function1;)I;
Asciz	(Lscala/collection/TraversableLike;Lscala/Function1;)I;
NameAndType	count:(Lscala/collection/TraversableLike;Lscala/Function1;)I
Method	scala/collection/TraversableLike$class.count:(Lscala/collection/TraversableLike;Lscala/Function1;)I
Asciz	exists;
Asciz	(Lscala/Function1;)Z;
Asciz	(Lscala/collection/TraversableLike;Lscala/Function1;)Z;
NameAndType	exists:(Lscala/collection/TraversableLike;Lscala/Function1;)Z
Method	scala/collection/TraversableLike$class.exists:(Lscala/collection/TraversableLike;Lscala/Function1;)Z
Asciz	forall;
NameAndType	forall:(Lscala/collection/TraversableLike;Lscala/Function1;)Z
Method	scala/collection/TraversableLike$class.forall:(Lscala/collection/TraversableLike;Lscala/Function1;)Z
Asciz	groupBy;
Asciz	(Lscala/Function1;)Lscala/collection/Map;;
Asciz	(Lscala/collection/TraversableLike;Lscala/Function1;)Lscala/collection/Map;;
NameAndType	groupBy:(Lscala/collection/TraversableLike;Lscala/Function1;)Lscala/collection/Map;
Method	scala/collection/TraversableLike$class.groupBy:(Lscala/collection/TraversableLike;Lscala/Function1;)Lscala/collection/Map;
Asciz	f;
Asciz	partition;
Asciz	(Lscala/Function1;)Lscala/Tuple2;;
Asciz	(Lscala/collection/TraversableLike;Lscala/Function1;)Lscala/Tuple2;;
NameAndType	partition:(Lscala/collection/TraversableLike;Lscala/Function1;)Lscala/Tuple2;
Method	scala/collection/TraversableLike$class.partition:(Lscala/collection/TraversableLike;Lscala/Function1;)Lscala/Tuple2;
Asciz	partialMap;
Asciz	(Lscala/PartialFunction;Lscala/collection/generic/CanBuildFrom;)Ljava/lang/Object;;
Asciz	(Lscala/collection/TraversableLike;Lscala/PartialFunction;Lscala/collection/generic/CanBuildFrom;)Ljava/lang/Object;;
NameAndType	partialMap:(Lscala/collection/TraversableLike;Lscala/PartialFunction;Lscala/collection/generic/CanBuildFrom;)Ljava/lang/Object;
Method	scala/collection/TraversableLike$class.partialMap:(Lscala/collection/TraversableLike;Lscala/PartialFunction;Lscala/collection/generic/CanBuildFrom;)Ljava/lang/Object;
Asciz	pf;
Asciz	Lscala/PartialFunction;;
Asciz	bf;
Asciz	Lscala/collection/generic/CanBuildFrom;;
Asciz	filterNot;
Asciz	(Lscala/collection/TraversableLike;Lscala/Function1;)Ljava/lang/Object;;
NameAndType	filterNot:(Lscala/collection/TraversableLike;Lscala/Function1;)Ljava/lang/Object;
Method	scala/collection/TraversableLike$class.filterNot:(Lscala/collection/TraversableLike;Lscala/Function1;)Ljava/lang/Object;
Asciz	hasDefiniteSize;
Asciz	()Z;
Asciz	(Lscala/collection/TraversableLike;)Z;
NameAndType	hasDefiniteSize:(Lscala/collection/TraversableLike;)Z
Method	scala/collection/TraversableLike$class.hasDefiniteSize:(Lscala/collection/TraversableLike;)Z
Asciz	size;
Asciz	()I;
Asciz	(Lscala/collection/TraversableLike;)I;
NameAndType	size:(Lscala/collection/TraversableLike;)I
Method	scala/collection/TraversableLike$class.size:(Lscala/collection/TraversableLike;)I
Asciz	nonEmpty;
NameAndType	nonEmpty:(Lscala/collection/TraversableLike;)Z
Method	scala/collection/TraversableLike$class.nonEmpty:(Lscala/collection/TraversableLike;)Z
Asciz	isEmpty;
NameAndType	isEmpty:(Lscala/collection/TraversableLike;)Z
Method	scala/collection/TraversableLike$class.isEmpty:(Lscala/collection/TraversableLike;)Z
Asciz	toCollection;
Asciz	(Ljava/lang/Object;)Lscala/collection/Traversable;;
Asciz	(Lscala/collection/TraversableLike;Ljava/lang/Object;)Lscala/collection/Traversable;;
NameAndType	toCollection:(Lscala/collection/TraversableLike;Ljava/lang/Object;)Lscala/collection/Traversable;
Method	scala/collection/TraversableLike$class.toCollection:(Lscala/collection/TraversableLike;Ljava/lang/Object;)Lscala/collection/Traversable;
Asciz	repr;
Asciz	thisCollection;
Asciz	()Lscala/collection/Traversable;;
Asciz	(Lscala/collection/TraversableLike;)Lscala/collection/Traversable;;
NameAndType	thisCollection:(Lscala/collection/TraversableLike;)Lscala/collection/Traversable;
Method	scala/collection/TraversableLike$class.thisCollection:(Lscala/collection/TraversableLike;)Lscala/collection/Traversable;
NameAndType	repr:(Lscala/collection/TraversableLike;)Ljava/lang/Object;
Method	scala/collection/TraversableLike$class.repr:(Lscala/collection/TraversableLike;)Ljava/lang/Object;
Asciz	transpose;
Asciz	(Lscala/Function1;)Lscala/collection/Traversable;;
Asciz	(Lscala/collection/generic/GenericTraversableTemplate;Lscala/Function1;)Lscala/collection/Traversable;;
NameAndType	transpose:(Lscala/collection/generic/GenericTraversableTemplate;Lscala/Function1;)Lscala/collection/Traversable;
Method	scala/collection/generic/GenericTraversableTemplate$class.transpose:(Lscala/collection/generic/GenericTraversableTemplate;Lscala/Function1;)Lscala/collection/Traversable;
Asciz	asTraversable;
Asciz	flatten;
NameAndType	flatten:(Lscala/collection/generic/GenericTraversableTemplate;Lscala/Function1;)Lscala/collection/Traversable;
Method	scala/collection/generic/GenericTraversableTemplate$class.flatten:(Lscala/collection/generic/GenericTraversableTemplate;Lscala/Function1;)Lscala/collection/Traversable;
Asciz	unzip;
Asciz	(Lscala/collection/generic/GenericTraversableTemplate;Lscala/Function1;)Lscala/Tuple2;;
NameAndType	unzip:(Lscala/collection/generic/GenericTraversableTemplate;Lscala/Function1;)Lscala/Tuple2;
Method	scala/collection/generic/GenericTraversableTemplate$class.unzip:(Lscala/collection/generic/GenericTraversableTemplate;Lscala/Function1;)Lscala/Tuple2;
Asciz	asPair;
Asciz	genericBuilder;
Asciz	()Lscala/collection/mutable/Builder;;
Asciz	(Lscala/collection/generic/GenericTraversableTemplate;)Lscala/collection/mutable/Builder;;
NameAndType	genericBuilder:(Lscala/collection/generic/GenericTraversableTemplate;)Lscala/collection/mutable/Builder;
Method	scala/collection/generic/GenericTraversableTemplate$class.genericBuilder:(Lscala/collection/generic/GenericTraversableTemplate;)Lscala/collection/mutable/Builder;
Asciz	companion;
Asciz	()Lscala/collection/generic/GenericCompanion;;
Asciz	(Lscala/collection/Traversable;)Lscala/collection/generic/GenericCompanion;;
NameAndType	companion:(Lscala/collection/Traversable;)Lscala/collection/generic/GenericCompanion;
Method	scala/collection/Traversable$class.companion:(Lscala/collection/Traversable;)Lscala/collection/generic/GenericCompanion;
Asciz	newTakenWhile;
Asciz	(Lscala/Function1;)Lscala/collection/TraversableViewLike$Transformed;;
Asciz	(Lscala/collection/TraversableViewLike;Lscala/Function1;)Lscala/collection/TraversableViewLike$Transformed;;
NameAndType	newTakenWhile:(Lscala/collection/TraversableViewLike;Lscala/Function1;)Lscala/collection/TraversableViewLike$Transformed;
Method	scala/collection/views/TraversableTransformations$class.newTakenWhile:(Lscala/collection/TraversableViewLike;Lscala/Function1;)Lscala/collection/TraversableViewLike$Transformed;
Asciz	newDroppedWhile;
NameAndType	newDroppedWhile:(Lscala/collection/TraversableViewLike;Lscala/Function1;)Lscala/collection/TraversableViewLike$Transformed;
Method	scala/collection/views/TraversableTransformations$class.newDroppedWhile:(Lscala/collection/TraversableViewLike;Lscala/Function1;)Lscala/collection/TraversableViewLike$Transformed;
Asciz	newSliced;
Asciz	(II)Lscala/collection/TraversableViewLike$Transformed;;
Asciz	(Lscala/collection/TraversableViewLike;II)Lscala/collection/TraversableViewLike$Transformed;;
NameAndType	newSliced:(Lscala/collection/TraversableViewLike;II)Lscala/collection/TraversableViewLike$Transformed;
Method	scala/collection/views/TraversableTransformations$class.newSliced:(Lscala/collection/TraversableViewLike;II)Lscala/collection/TraversableViewLike$Transformed;
Asciz	_from;
Asciz	_until;
Asciz	newFiltered;
NameAndType	newFiltered:(Lscala/collection/TraversableViewLike;Lscala/Function1;)Lscala/collection/TraversableViewLike$Transformed;
Method	scala/collection/views/TraversableTransformations$class.newFiltered:(Lscala/collection/TraversableViewLike;Lscala/Function1;)Lscala/collection/TraversableViewLike$Transformed;
Asciz	newFlatMapped;
NameAndType	newFlatMapped:(Lscala/collection/TraversableViewLike;Lscala/Function1;)Lscala/collection/TraversableViewLike$Transformed;
Method	scala/collection/views/TraversableTransformations$class.newFlatMapped:(Lscala/collection/TraversableViewLike;Lscala/Function1;)Lscala/collection/TraversableViewLike$Transformed;
Asciz	newMapped;
NameAndType	newMapped:(Lscala/collection/TraversableViewLike;Lscala/Function1;)Lscala/collection/TraversableViewLike$Transformed;
Method	scala/collection/views/TraversableTransformations$class.newMapped:(Lscala/collection/TraversableViewLike;Lscala/Function1;)Lscala/collection/TraversableViewLike$Transformed;
Asciz	newAppended;
Asciz	(Lscala/collection/Traversable;)Lscala/collection/TraversableViewLike$Transformed;;
Asciz	(Lscala/collection/TraversableViewLike;Lscala/collection/Traversable;)Lscala/collection/TraversableViewLike$Transformed;;
NameAndType	newAppended:(Lscala/collection/TraversableViewLike;Lscala/collection/Traversable;)Lscala/collection/TraversableViewLike$Transformed;
Method	scala/collection/views/TraversableTransformations$class.newAppended:(Lscala/collection/TraversableViewLike;Lscala/collection/Traversable;)Lscala/collection/TraversableViewLike$Transformed;
Asciz	that;
Asciz	Lscala/collection/Traversable;;
Asciz	stringPrefix;
Asciz	(Lscala/collection/TraversableViewLike;)Ljava/lang/String;;
NameAndType	stringPrefix:(Lscala/collection/TraversableViewLike;)Ljava/lang/String;
Method	scala/collection/TraversableViewLike$class.stringPrefix:(Lscala/collection/TraversableViewLike;)Ljava/lang/String;
Asciz	splitAt;
Asciz	(I)Lscala/Tuple2;;
Asciz	(Lscala/collection/TraversableViewLike;I)Lscala/Tuple2;;
NameAndType	splitAt:(Lscala/collection/TraversableViewLike;I)Lscala/Tuple2;
Method	scala/collection/TraversableViewLike$class.splitAt:(Lscala/collection/TraversableViewLike;I)Lscala/Tuple2;
Asciz	span;
Asciz	(Lscala/collection/TraversableViewLike;Lscala/Function1;)Lscala/Tuple2;;
NameAndType	span:(Lscala/collection/TraversableViewLike;Lscala/Function1;)Lscala/Tuple2;
Method	scala/collection/TraversableViewLike$class.span:(Lscala/collection/TraversableViewLike;Lscala/Function1;)Lscala/Tuple2;
Asciz	(Lscala/collection/TraversableViewLike;Lscala/Function1;)Lscala/collection/TraversableView;;
NameAndType	takeWhile:(Lscala/collection/TraversableViewLike;Lscala/Function1;)Lscala/collection/TraversableView;
Method	scala/collection/TraversableViewLike$class.takeWhile:(Lscala/collection/TraversableViewLike;Lscala/Function1;)Lscala/collection/TraversableView;
NameAndType	dropWhile:(Lscala/collection/TraversableViewLike;Lscala/Function1;)Lscala/collection/TraversableView;
Method	scala/collection/TraversableViewLike$class.dropWhile:(Lscala/collection/TraversableViewLike;Lscala/Function1;)Lscala/collection/TraversableView;
Asciz	(Lscala/collection/TraversableViewLike;II)Lscala/collection/TraversableView;;
NameAndType	slice:(Lscala/collection/TraversableViewLike;II)Lscala/collection/TraversableView;
Method	scala/collection/TraversableViewLike$class.slice:(Lscala/collection/TraversableViewLike;II)Lscala/collection/TraversableView;
Asciz	(Lscala/collection/TraversableViewLike;I)Lscala/collection/TraversableView;;
NameAndType	take:(Lscala/collection/TraversableViewLike;I)Lscala/collection/TraversableView;
Method	scala/collection/TraversableViewLike$class.take:(Lscala/collection/TraversableViewLike;I)Lscala/collection/TraversableView;
NameAndType	drop:(Lscala/collection/TraversableViewLike;I)Lscala/collection/TraversableView;
Method	scala/collection/TraversableViewLike$class.drop:(Lscala/collection/TraversableViewLike;I)Lscala/collection/TraversableView;
Asciz	(Lscala/collection/TraversableViewLike;)Lscala/collection/TraversableView;;
NameAndType	init:(Lscala/collection/TraversableViewLike;)Lscala/collection/TraversableView;
Method	scala/collection/TraversableViewLike$class.init:(Lscala/collection/TraversableViewLike;)Lscala/collection/TraversableView;
NameAndType	filter:(Lscala/collection/TraversableViewLike;Lscala/Function1;)Lscala/collection/TraversableView;
Method	scala/collection/TraversableViewLike$class.filter:(Lscala/collection/TraversableViewLike;Lscala/Function1;)Lscala/collection/TraversableView;
Asciz	flatMap;
Asciz	(Lscala/Function1;Lscala/collection/generic/CanBuildFrom;)Ljava/lang/Object;;
Asciz	(Lscala/collection/TraversableViewLike;Lscala/Function1;Lscala/collection/generic/CanBuildFrom;)Ljava/lang/Object;;
NameAndType	flatMap:(Lscala/collection/TraversableViewLike;Lscala/Function1;Lscala/collection/generic/CanBuildFrom;)Ljava/lang/Object;
Method	scala/collection/TraversableViewLike$class.flatMap:(Lscala/collection/TraversableViewLike;Lscala/Function1;Lscala/collection/generic/CanBuildFrom;)Ljava/lang/Object;
Asciz	map;
NameAndType	map:(Lscala/collection/TraversableViewLike;Lscala/Function1;Lscala/collection/generic/CanBuildFrom;)Ljava/lang/Object;
Method	scala/collection/TraversableViewLike$class.map:(Lscala/collection/TraversableViewLike;Lscala/Function1;Lscala/collection/generic/CanBuildFrom;)Ljava/lang/Object;
Asciz	$plus$plus;
Asciz	(Lscala/collection/Iterator;Lscala/collection/generic/CanBuildFrom;)Ljava/lang/Object;;
Asciz	(Lscala/collection/TraversableViewLike;Lscala/collection/Iterator;Lscala/collection/generic/CanBuildFrom;)Ljava/lang/Object;;
NameAndType	$plus$plus:(Lscala/collection/TraversableViewLike;Lscala/collection/Iterator;Lscala/collection/generic/CanBuildFrom;)Ljava/lang/Object;
Method	scala/collection/TraversableViewLike$class.$plus$plus:(Lscala/collection/TraversableViewLike;Lscala/collection/Iterator;Lscala/collection/generic/CanBuildFrom;)Ljava/lang/Object;
Asciz	Lscala/collection/Iterator;;
Asciz	(Lscala/collection/Traversable;Lscala/collection/generic/CanBuildFrom;)Ljava/lang/Object;;
Asciz	(Lscala/collection/TraversableViewLike;Lscala/collection/Traversable;Lscala/collection/generic/CanBuildFrom;)Ljava/lang/Object;;
NameAndType	$plus$plus:(Lscala/collection/TraversableViewLike;Lscala/collection/Traversable;Lscala/collection/generic/CanBuildFrom;)Ljava/lang/Object;
Method	scala/collection/TraversableViewLike$class.$plus$plus:(Lscala/collection/TraversableViewLike;Lscala/collection/Traversable;Lscala/collection/generic/CanBuildFrom;)Ljava/lang/Object;
Asciz	force;
Asciz	(Lscala/collection/generic/CanBuildFrom;)Ljava/lang/Object;;
Asciz	(Lscala/collection/TraversableViewLike;Lscala/collection/generic/CanBuildFrom;)Ljava/lang/Object;;
NameAndType	force:(Lscala/collection/TraversableViewLike;Lscala/collection/generic/CanBuildFrom;)Ljava/lang/Object;
Method	scala/collection/TraversableViewLike$class.force:(Lscala/collection/TraversableViewLike;Lscala/collection/generic/CanBuildFrom;)Ljava/lang/Object;
Asciz	newBuilder;
Asciz	(Lscala/collection/TraversableViewLike;)Lscala/collection/mutable/Builder;;
NameAndType	newBuilder:(Lscala/collection/TraversableViewLike;)Lscala/collection/mutable/Builder;
Method	scala/collection/TraversableViewLike$class.newBuilder:(Lscala/collection/TraversableViewLike;)Lscala/collection/mutable/Builder;
Asciz	<B:Ljava/lang/Object;Coll:Ljava/lang/Object;>Ljava/lang/Object;Lscala/collection/TraversableView<TB;TColl;>;Lscala/collection/views/Transformed;Lscala/ScalaObject;;
Asciz	ScalaSig;
Asciz	InnerClasses;
Asciz	scala/Predef$$less$colon$less;
class	scala/Predef$$less$colon$less
Asciz	scala/Predef;
class	scala/Predef
Asciz	$less$colon$less;
Asciz	scala/collection/TraversableLike$WithFilter;
class	scala/collection/TraversableLike$WithFilter
Asciz	scala/collection/TraversableLike;
class	scala/collection/TraversableLike
Asciz	WithFilter;
Asciz	scala/collection/TraversableViewLike$Transformed;
class	scala/collection/TraversableViewLike$Transformed
Asciz	Transformed;
Asciz	scala/collection/views/TraversableLike;
class	scala/collection/views/TraversableLike
Asciz	scala/collection/TraversableView;
class	scala/collection/TraversableView
Asciz	scala/collection/views/Transformed;
class	scala/collection/views/Transformed
Asciz	scala/ScalaObject;
class	scala/ScalaObject

{
public scala.collection.views.TraversableLike();
  Signature: ()V
  Code:
   Stack=1, Locals=1, Args_size=1
	aload_0
	invokespecial	Method java/lang/Object."<init>":()V
	aload_0
	invokestatic	Method scala/collection/TraversableLike$class.$init$:(Lscala/collection/TraversableLike;)V
	aload_0
	invokestatic	Method scala/collection/generic/GenericTraversableTemplate$class.$init$:(Lscala/collection/generic/GenericTraversableTemplate;)V
	aload_0
	invokestatic	Method scala/collection/Traversable$class.$init$:(Lscala/collection/Traversable;)V
	aload_0
	invokestatic	Method scala/collection/views/TraversableTransformations$class.$init$:(Lscala/collection/TraversableViewLike;)V
	aload_0
	invokestatic	Method scala/collection/TraversableViewLike$class.$init$:(Lscala/collection/TraversableViewLike;)V
	return
  Labels:
  Signature: length = 0x2
   00 04 

public java.lang.Object filter(scala.Function1);
  Signature: (Lscala/Function1;)Ljava/lang/Object;
  Code:
   Stack=2, Locals=2, Args_size=2
	aload_0
	aload_1
	invokeinterface	InterfaceMethod scala/collection/TraversableViewLike.filter:(Lscala/Function1;)Lscala/collection/TraversableView;
	areturn
  Labels:
  LocalVariableTable: 
   Start  Length  Slot  Name   Signature
   0      8      0    this       Lscala/collection/views/TraversableLike;
   0      8      1    p       Lscala/Function1;


public java.lang.Object init();
  Signature: ()Ljava/lang/Object;
  Code:
   Stack=1, Locals=1, Args_size=1
	aload_0
	invokeinterface	InterfaceMethod scala/collection/TraversableViewLike.init:()Lscala/collection/TraversableView;
	areturn
  Labels:

public java.lang.Object drop(int);
  Signature: (I)Ljava/lang/Object;
  Code:
   Stack=2, Locals=2, Args_size=2
	aload_0
	iload_1
	invokeinterface	InterfaceMethod scala/collection/TraversableViewLike.drop:(I)Lscala/collection/TraversableView;
	areturn
  Labels:
  LocalVariableTable: 
   Start  Length  Slot  Name   Signature
   0      8      0    this       Lscala/collection/views/TraversableLike;
   0      8      1    n       I


public java.lang.Object take(int);
  Signature: (I)Ljava/lang/Object;
  Code:
   Stack=2, Locals=2, Args_size=2
	aload_0
	iload_1
	invokeinterface	InterfaceMethod scala/collection/TraversableViewLike.take:(I)Lscala/collection/TraversableView;
	areturn
  Labels:
  LocalVariableTable: 
   Start  Length  Slot  Name   Signature
   0      8      0    this       Lscala/collection/views/TraversableLike;
   0      8      1    n       I


public java.lang.Object slice(int, int);
  Signature: (II)Ljava/lang/Object;
  Code:
   Stack=3, Locals=3, Args_size=3
	aload_0
	iload_1
	iload_2
	invokeinterface	InterfaceMethod scala/collection/TraversableViewLike.slice:(II)Lscala/collection/TraversableView;
	areturn
  Labels:
  LocalVariableTable: 
   Start  Length  Slot  Name   Signature
   0      9      0    this       Lscala/collection/views/TraversableLike;
   0      9      1    from       I
   0      9      2    until       I


public java.lang.Object dropWhile(scala.Function1);
  Signature: (Lscala/Function1;)Ljava/lang/Object;
  Code:
   Stack=2, Locals=2, Args_size=2
	aload_0
	aload_1
	invokeinterface	InterfaceMethod scala/collection/TraversableViewLike.dropWhile:(Lscala/Function1;)Lscala/collection/TraversableView;
	areturn
  Labels:
  LocalVariableTable: 
   Start  Length  Slot  Name   Signature
   0      8      0    this       Lscala/collection/views/TraversableLike;
   0      8      1    p       Lscala/Function1;


public java.lang.Object takeWhile(scala.Function1);
  Signature: (Lscala/Function1;)Ljava/lang/Object;
  Code:
   Stack=2, Locals=2, Args_size=2
	aload_0
	aload_1
	invokeinterface	InterfaceMethod scala/collection/TraversableViewLike.takeWhile:(Lscala/Function1;)Lscala/collection/TraversableView;
	areturn
  Labels:
  LocalVariableTable: 
   Start  Length  Slot  Name   Signature
   0      8      0    this       Lscala/collection/views/TraversableLike;
   0      8      1    p       Lscala/Function1;


public abstract void foreach(scala.Function1);
  Signature: (Lscala/Function1;)V
  Signature: length = 0x2
   00 4E 

public scala.collection.TraversableLike$WithFilter withFilter(scala.Function1);
  Signature: (Lscala/Function1;)Lscala/collection/TraversableLike$WithFilter;
  Code:
   Stack=2, Locals=2, Args_size=2
	aload_0
	aload_1
	invokestatic	Method scala/collection/TraversableLike$class.withFilter:(Lscala/collection/TraversableLike;Lscala/Function1;)Lscala/collection/TraversableLike$WithFilter;
	areturn
  Labels:
  LocalVariableTable: 
   Start  Length  Slot  Name   Signature
   0      6      0    this       Lscala/collection/views/TraversableLike;
   0      6      1    p       Lscala/Function1;

  Signature: length = 0x2
   00 50 

public scala.collection.TraversableView view(int, int);
  Signature: (II)Lscala/collection/TraversableView;
  Code:
   Stack=3, Locals=3, Args_size=3
	aload_0
	iload_1
	iload_2
	invokestatic	Method scala/collection/TraversableLike$class.view:(Lscala/collection/TraversableLike;II)Lscala/collection/TraversableView;
	areturn
  Labels:
  LocalVariableTable: 
   Start  Length  Slot  Name   Signature
   0      7      0    this       Lscala/collection/views/TraversableLike;
   0      7      1    from       I
   0      7      2    until       I


public scala.collection.TraversableView view();
  Signature: ()Lscala/collection/TraversableView;
  Code:
   Stack=1, Locals=1, Args_size=1
	aload_0
	invokestatic	Method scala/collection/TraversableLike$class.view:(Lscala/collection/TraversableLike;)Lscala/collection/TraversableView;
	areturn
  Labels:

public java.lang.String toString();
  Signature: ()Ljava/lang/String;
  Code:
   Stack=1, Locals=1, Args_size=1
	aload_0
	invokestatic	Method scala/collection/TraversableLike$class.toString:(Lscala/collection/TraversableLike;)Ljava/lang/String;
	areturn
  Labels:

public scala.collection.mutable.StringBuilder addString(scala.collection.mutable.StringBuilder);
  Signature: (Lscala/collection/mutable/StringBuilder;)Lscala/collection/mutable/StringBuilder;
  Code:
   Stack=2, Locals=2, Args_size=2
	aload_0
	aload_1
	invokestatic	Method scala/collection/TraversableLike$class.addString:(Lscala/collection/TraversableLike;Lscala/collection/mutable/StringBuilder;)Lscala/collection/mutable/StringBuilder;
	areturn
  Labels:
  LocalVariableTable: 
   Start  Length  Slot  Name   Signature
   0      6      0    this       Lscala/collection/views/TraversableLike;
   0      6      1    b       Lscala/collection/mutable/StringBuilder;


public scala.collection.mutable.StringBuilder addString(scala.collection.mutable.StringBuilder, java.lang.String);
  Signature: (Lscala/collection/mutable/StringBuilder;Ljava/lang/String;)Lscala/collection/mutable/StringBuilder;
  Code:
   Stack=3, Locals=3, Args_size=3
	aload_0
	aload_1
	aload_2
	invokestatic	Method scala/collection/TraversableLike$class.addString:(Lscala/collection/TraversableLike;Lscala/collection/mutable/StringBuilder;Ljava/lang/String;)Lscala/collection/mutable/StringBuilder;
	areturn
  Labels:
  LocalVariableTable: 
   Start  Length  Slot  Name   Signature
   0      7      0    this       Lscala/collection/views/TraversableLike;
   0      7      1    b       Lscala/collection/mutable/StringBuilder;
   0      7      2    sep       Ljava/lang/String;


public scala.collection.mutable.StringBuilder addString(scala.collection.mutable.StringBuilder, java.lang.String, java.lang.String, java.lang.String);
  Signature: (Lscala/collection/mutable/StringBuilder;Ljava/lang/String;Ljava/lang/String;Ljava/lang/String;)Lscala/collection/mutable/StringBuilder;
  Code:
   Stack=5, Locals=5, Args_size=5
	aload_0
	aload_1
	aload_2
	aload_3
	aload	4
	invokestatic	Method scala/collection/TraversableLike$class.addString:(Lscala/collection/TraversableLike;Lscala/collection/mutable/StringBuilder;Ljava/lang/String;Ljava/lang/String;Ljava/lang/String;)Lscala/collection/mutable/StringBuilder;
	areturn
  Labels:
  LocalVariableTable: 
   Start  Length  Slot  Name   Signature
   0      10      0    this       Lscala/collection/views/TraversableLike;
   0      10      1    b       Lscala/collection/mutable/StringBuilder;
   0      10      2    start       Ljava/lang/String;
   0      10      3    sep       Ljava/lang/String;
   0      10      4    end       Ljava/lang/String;


public java.lang.String mkString();
  Signature: ()Ljava/lang/String;
  Code:
   Stack=1, Locals=1, Args_size=1
	aload_0
	invokestatic	Method scala/collection/TraversableLike$class.mkString:(Lscala/collection/TraversableLike;)Ljava/lang/String;
	areturn
  Labels:

public java.lang.String mkString(java.lang.String);
  Signature: (Ljava/lang/String;)Ljava/lang/String;
  Code:
   Stack=2, Locals=2, Args_size=2
	aload_0
	aload_1
	invokestatic	Method scala/collection/TraversableLike$class.mkString:(Lscala/collection/TraversableLike;Ljava/lang/String;)Ljava/lang/String;
	areturn
  Labels:
  LocalVariableTable: 
   Start  Length  Slot  Name   Signature
   0      6      0    this       Lscala/collection/views/TraversableLike;
   0      6      1    sep       Ljava/lang/String;


public java.lang.String mkString(java.lang.String, java.lang.String, java.lang.String);
  Signature: (Ljava/lang/String;Ljava/lang/String;Ljava/lang/String;)Ljava/lang/String;
  Code:
   Stack=4, Locals=4, Args_size=4
	aload_0
	aload_1
	aload_2
	aload_3
	invokestatic	Method scala/collection/TraversableLike$class.mkString:(Lscala/collection/TraversableLike;Ljava/lang/String;Ljava/lang/String;Ljava/lang/String;)Ljava/lang/String;
	areturn
  Labels:
  LocalVariableTable: 
   Start  Length  Slot  Name   Signature
   0      8      0    this       Lscala/collection/views/TraversableLike;
   0      8      1    start       Ljava/lang/String;
   0      8      2    sep       Ljava/lang/String;
   0      8      3    end       Ljava/lang/String;


public scala.collection.immutable.Map toMap(scala.Predef$$less$colon$less);
  Signature: (Lscala/Predef$$less$colon$less;)Lscala/collection/immutable/Map;
  Code:
   Stack=2, Locals=2, Args_size=2
	aload_0
	aload_1
	invokestatic	Method scala/collection/TraversableLike$class.toMap:(Lscala/collection/TraversableLike;Lscala/Predef$$less$colon$less;)Lscala/collection/immutable/Map;
	areturn
  Labels:
  LocalVariableTable: 
   Start  Length  Slot  Name   Signature
   0      6      0    this       Lscala/collection/views/TraversableLike;
   0      6      1    ev       Lscala/Predef$$less$colon$less;


public scala.collection.immutable.Set toSet();
  Signature: ()Lscala/collection/immutable/Set;
  Code:
   Stack=1, Locals=1, Args_size=1
	aload_0
	invokestatic	Method scala/collection/TraversableLike$class.toSet:(Lscala/collection/TraversableLike;)Lscala/collection/immutable/Set;
	areturn
  Labels:

public scala.collection.immutable.Stream toStream();
  Signature: ()Lscala/collection/immutable/Stream;
  Code:
   Stack=1, Locals=1, Args_size=1
	aload_0
	invokestatic	Method scala/collection/TraversableLike$class.toStream:(Lscala/collection/TraversableLike;)Lscala/collection/immutable/Stream;
	areturn
  Labels:

public scala.collection.mutable.IndexedSeq toIndexedSeq();
  Signature: ()Lscala/collection/mutable/IndexedSeq;
  Code:
   Stack=1, Locals=1, Args_size=1
	aload_0
	invokestatic	Method scala/collection/TraversableLike$class.toIndexedSeq:(Lscala/collection/TraversableLike;)Lscala/collection/mutable/IndexedSeq;
	areturn
  Labels:

public scala.collection.Seq toSeq();
  Signature: ()Lscala/collection/Seq;
  Code:
   Stack=1, Locals=1, Args_size=1
	aload_0
	invokestatic	Method scala/collection/TraversableLike$class.toSeq:(Lscala/collection/TraversableLike;)Lscala/collection/Seq;
	areturn
  Labels:

public scala.collection.Iterable toIterable();
  Signature: ()Lscala/collection/Iterable;
  Code:
   Stack=1, Locals=1, Args_size=1
	aload_0
	invokestatic	Method scala/collection/TraversableLike$class.toIterable:(Lscala/collection/TraversableLike;)Lscala/collection/Iterable;
	areturn
  Labels:

public scala.collection.immutable.List toList();
  Signature: ()Lscala/collection/immutable/List;
  Code:
   Stack=1, Locals=1, Args_size=1
	aload_0
	invokestatic	Method scala/collection/TraversableLike$class.toList:(Lscala/collection/TraversableLike;)Lscala/collection/immutable/List;
	areturn
  Labels:

public java.lang.Object toArray(scala.reflect.ClassManifest);
  Signature: (Lscala/reflect/ClassManifest;)Ljava/lang/Object;
  Code:
   Stack=2, Locals=2, Args_size=2
	aload_0
	aload_1
	invokestatic	Method scala/collection/TraversableLike$class.toArray:(Lscala/collection/TraversableLike;Lscala/reflect/ClassManifest;)Ljava/lang/Object;
	areturn
  Labels:
  LocalVariableTable: 
   Start  Length  Slot  Name   Signature
   0      6      0    this       Lscala/collection/views/TraversableLike;
   0      6      1    evidence$1       Lscala/reflect/ClassManifest;


public void copyToArray(java.lang.Object);
  Signature: (Ljava/lang/Object;)V
  Code:
   Stack=2, Locals=2, Args_size=2
	aload_0
	aload_1
	invokestatic	Method scala/collection/TraversableLike$class.copyToArray:(Lscala/collection/TraversableLike;Ljava/lang/Object;)V
	return
  Labels:
  LocalVariableTable: 
   Start  Length  Slot  Name   Signature
   0      6      0    this       Lscala/collection/views/TraversableLike;
   0      6      1    xs       Ljava/lang/Object;


public void copyToArray(java.lang.Object, int);
  Signature: (Ljava/lang/Object;I)V
  Code:
   Stack=3, Locals=3, Args_size=3
	aload_0
	aload_1
	iload_2
	invokestatic	Method scala/collection/TraversableLike$class.copyToArray:(Lscala/collection/TraversableLike;Ljava/lang/Object;I)V
	return
  Labels:
  LocalVariableTable: 
   Start  Length  Slot  Name   Signature
   0      7      0    this       Lscala/collection/views/TraversableLike;
   0      7      1    xs       Ljava/lang/Object;
   0      7      2    start       I


public void copyToArray(java.lang.Object, int, int);
  Signature: (Ljava/lang/Object;II)V
  Code:
   Stack=4, Locals=4, Args_size=4
	aload_0
	aload_1
	iload_2
	iload_3
	invokestatic	Method scala/collection/TraversableLike$class.copyToArray:(Lscala/collection/TraversableLike;Ljava/lang/Object;II)V
	return
  Labels:
  LocalVariableTable: 
   Start  Length  Slot  Name   Signature
   0      8      0    this       Lscala/collection/views/TraversableLike;
   0      8      1    xs       Ljava/lang/Object;
   0      8      2    start       I
   0      8      3    len       I


public void copyToBuffer(scala.collection.mutable.Buffer);
  Signature: (Lscala/collection/mutable/Buffer;)V
  Code:
   Stack=2, Locals=2, Args_size=2
	aload_0
	aload_1
	invokestatic	Method scala/collection/TraversableLike$class.copyToBuffer:(Lscala/collection/TraversableLike;Lscala/collection/mutable/Buffer;)V
	return
  Labels:
  LocalVariableTable: 
   Start  Length  Slot  Name   Signature
   0      6      0    this       Lscala/collection/views/TraversableLike;
   0      6      1    dest       Lscala/collection/mutable/Buffer;


public scala.Option lastOption();
  Signature: ()Lscala/Option;
  Code:
   Stack=1, Locals=1, Args_size=1
	aload_0
	invokestatic	Method scala/collection/TraversableLike$class.lastOption:(Lscala/collection/TraversableLike;)Lscala/Option;
	areturn
  Labels:

public java.lang.Object last();
  Signature: ()Ljava/lang/Object;
  Code:
   Stack=1, Locals=1, Args_size=1
	aload_0
	invokestatic	Method scala/collection/TraversableLike$class.last:(Lscala/collection/TraversableLike;)Ljava/lang/Object;
	areturn
  Labels:

public java.lang.Object tail();
  Signature: ()Ljava/lang/Object;
  Code:
   Stack=1, Locals=1, Args_size=1
	aload_0
	invokestatic	Method scala/collection/TraversableLike$class.tail:(Lscala/collection/TraversableLike;)Ljava/lang/Object;
	areturn
  Labels:

public scala.Option headOption();
  Signature: ()Lscala/Option;
  Code:
   Stack=1, Locals=1, Args_size=1
	aload_0
	invokestatic	Method scala/collection/TraversableLike$class.headOption:(Lscala/collection/TraversableLike;)Lscala/Option;
	areturn
  Labels:

public java.lang.Object head();
  Signature: ()Ljava/lang/Object;
  Code:
   Stack=1, Locals=1, Args_size=1
	aload_0
	invokestatic	Method scala/collection/TraversableLike$class.head:(Lscala/collection/TraversableLike;)Ljava/lang/Object;
	areturn
  Labels:

public java.lang.Object max(scala.math.Ordering);
  Signature: (Lscala/math/Ordering;)Ljava/lang/Object;
  Code:
   Stack=2, Locals=2, Args_size=2
	aload_0
	aload_1
	invokestatic	Method scala/collection/TraversableLike$class.max:(Lscala/collection/TraversableLike;Lscala/math/Ordering;)Ljava/lang/Object;
	areturn
  Labels:
  LocalVariableTable: 
   Start  Length  Slot  Name   Signature
   0      6      0    this       Lscala/collection/views/TraversableLike;
   0      6      1    cmp       Lscala/math/Ordering;


public java.lang.Object min(scala.math.Ordering);
  Signature: (Lscala/math/Ordering;)Ljava/lang/Object;
  Code:
   Stack=2, Locals=2, Args_size=2
	aload_0
	aload_1
	invokestatic	Method scala/collection/TraversableLike$class.min:(Lscala/collection/TraversableLike;Lscala/math/Ordering;)Ljava/lang/Object;
	areturn
  Labels:
  LocalVariableTable: 
   Start  Length  Slot  Name   Signature
   0      6      0    this       Lscala/collection/views/TraversableLike;
   0      6      1    cmp       Lscala/math/Ordering;


public java.lang.Object product(scala.math.Numeric);
  Signature: (Lscala/math/Numeric;)Ljava/lang/Object;
  Code:
   Stack=2, Locals=2, Args_size=2
	aload_0
	aload_1
	invokestatic	Method scala/collection/TraversableLike$class.product:(Lscala/collection/TraversableLike;Lscala/math/Numeric;)Ljava/lang/Object;
	areturn
  Labels:
  LocalVariableTable: 
   Start  Length  Slot  Name   Signature
   0      6      0    this       Lscala/collection/views/TraversableLike;
   0      6      1    num       Lscala/math/Numeric;


public java.lang.Object sum(scala.math.Numeric);
  Signature: (Lscala/math/Numeric;)Ljava/lang/Object;
  Code:
   Stack=2, Locals=2, Args_size=2
	aload_0
	aload_1
	invokestatic	Method scala/collection/TraversableLike$class.sum:(Lscala/collection/TraversableLike;Lscala/math/Numeric;)Ljava/lang/Object;
	areturn
  Labels:
  LocalVariableTable: 
   Start  Length  Slot  Name   Signature
   0      6      0    this       Lscala/collection/views/TraversableLike;
   0      6      1    num       Lscala/math/Numeric;


public scala.Option reduceRightOption(scala.Function2);
  Signature: (Lscala/Function2;)Lscala/Option;
  Code:
   Stack=2, Locals=2, Args_size=2
	aload_0
	aload_1
	invokestatic	Method scala/collection/TraversableLike$class.reduceRightOption:(Lscala/collection/TraversableLike;Lscala/Function2;)Lscala/Option;
	areturn
  Labels:
  LocalVariableTable: 
   Start  Length  Slot  Name   Signature
   0      6      0    this       Lscala/collection/views/TraversableLike;
   0      6      1    op       Lscala/Function2;


public java.lang.Object reduceRight(scala.Function2);
  Signature: (Lscala/Function2;)Ljava/lang/Object;
  Code:
   Stack=2, Locals=2, Args_size=2
	aload_0
	aload_1
	invokestatic	Method scala/collection/TraversableLike$class.reduceRight:(Lscala/collection/TraversableLike;Lscala/Function2;)Ljava/lang/Object;
	areturn
  Labels:
  LocalVariableTable: 
   Start  Length  Slot  Name   Signature
   0      6      0    this       Lscala/collection/views/TraversableLike;
   0      6      1    op       Lscala/Function2;


public scala.Option reduceLeftOption(scala.Function2);
  Signature: (Lscala/Function2;)Lscala/Option;
  Code:
   Stack=2, Locals=2, Args_size=2
	aload_0
	aload_1
	invokestatic	Method scala/collection/TraversableLike$class.reduceLeftOption:(Lscala/collection/TraversableLike;Lscala/Function2;)Lscala/Option;
	areturn
  Labels:
  LocalVariableTable: 
   Start  Length  Slot  Name   Signature
   0      6      0    this       Lscala/collection/views/TraversableLike;
   0      6      1    op       Lscala/Function2;


public java.lang.Object reduceLeft(scala.Function2);
  Signature: (Lscala/Function2;)Ljava/lang/Object;
  Code:
   Stack=2, Locals=2, Args_size=2
	aload_0
	aload_1
	invokestatic	Method scala/collection/TraversableLike$class.reduceLeft:(Lscala/collection/TraversableLike;Lscala/Function2;)Ljava/lang/Object;
	areturn
  Labels:
  LocalVariableTable: 
   Start  Length  Slot  Name   Signature
   0      6      0    this       Lscala/collection/views/TraversableLike;
   0      6      1    op       Lscala/Function2;


public java.lang.Object $colon$bslash(java.lang.Object, scala.Function2);
  Signature: (Ljava/lang/Object;Lscala/Function2;)Ljava/lang/Object;
  Code:
   Stack=3, Locals=3, Args_size=3
	aload_0
	aload_1
	aload_2
	invokestatic	Method scala/collection/TraversableLike$class.$colon$bslash:(Lscala/collection/TraversableLike;Ljava/lang/Object;Lscala/Function2;)Ljava/lang/Object;
	areturn
  Labels:
  LocalVariableTable: 
   Start  Length  Slot  Name   Signature
   0      7      0    this       Lscala/collection/views/TraversableLike;
   0      7      1    z       Ljava/lang/Object;
   0      7      2    op       Lscala/Function2;


public java.lang.Object foldRight(java.lang.Object, scala.Function2);
  Signature: (Ljava/lang/Object;Lscala/Function2;)Ljava/lang/Object;
  Code:
   Stack=3, Locals=3, Args_size=3
	aload_0
	aload_1
	aload_2
	invokestatic	Method scala/collection/TraversableLike$class.foldRight:(Lscala/collection/TraversableLike;Ljava/lang/Object;Lscala/Function2;)Ljava/lang/Object;
	areturn
  Labels:
  LocalVariableTable: 
   Start  Length  Slot  Name   Signature
   0      7      0    this       Lscala/collection/views/TraversableLike;
   0      7      1    z       Ljava/lang/Object;
   0      7      2    op       Lscala/Function2;


public java.lang.Object $div$colon(java.lang.Object, scala.Function2);
  Signature: (Ljava/lang/Object;Lscala/Function2;)Ljava/lang/Object;
  Code:
   Stack=3, Locals=3, Args_size=3
	aload_0
	aload_1
	aload_2
	invokestatic	Method scala/collection/TraversableLike$class.$div$colon:(Lscala/collection/TraversableLike;Ljava/lang/Object;Lscala/Function2;)Ljava/lang/Object;
	areturn
  Labels:
  LocalVariableTable: 
   Start  Length  Slot  Name   Signature
   0      7      0    this       Lscala/collection/views/TraversableLike;
   0      7      1    z       Ljava/lang/Object;
   0      7      2    op       Lscala/Function2;


public java.lang.Object foldLeft(java.lang.Object, scala.Function2);
  Signature: (Ljava/lang/Object;Lscala/Function2;)Ljava/lang/Object;
  Code:
   Stack=3, Locals=3, Args_size=3
	aload_0
	aload_1
	aload_2
	invokestatic	Method scala/collection/TraversableLike$class.foldLeft:(Lscala/collection/TraversableLike;Ljava/lang/Object;Lscala/Function2;)Ljava/lang/Object;
	areturn
  Labels:
  LocalVariableTable: 
   Start  Length  Slot  Name   Signature
   0      7      0    this       Lscala/collection/views/TraversableLike;
   0      7      1    z       Ljava/lang/Object;
   0      7      2    op       Lscala/Function2;


public scala.Option find(scala.Function1);
  Signature: (Lscala/Function1;)Lscala/Option;
  Code:
   Stack=2, Locals=2, Args_size=2
	aload_0
	aload_1
	invokestatic	Method scala/collection/TraversableLike$class.find:(Lscala/collection/TraversableLike;Lscala/Function1;)Lscala/Option;
	areturn
  Labels:
  LocalVariableTable: 
   Start  Length  Slot  Name   Signature
   0      6      0    this       Lscala/collection/views/TraversableLike;
   0      6      1    p       Lscala/Function1;


public int count(scala.Function1);
  Signature: (Lscala/Function1;)I
  Code:
   Stack=2, Locals=2, Args_size=2
	aload_0
	aload_1
	invokestatic	Method scala/collection/TraversableLike$class.count:(Lscala/collection/TraversableLike;Lscala/Function1;)I
	ireturn
  Labels:
  LocalVariableTable: 
   Start  Length  Slot  Name   Signature
   0      6      0    this       Lscala/collection/views/TraversableLike;
   0      6      1    p       Lscala/Function1;


public boolean exists(scala.Function1);
  Signature: (Lscala/Function1;)Z
  Code:
   Stack=2, Locals=2, Args_size=2
	aload_0
	aload_1
	invokestatic	Method scala/collection/TraversableLike$class.exists:(Lscala/collection/TraversableLike;Lscala/Function1;)Z
	ireturn
  Labels:
  LocalVariableTable: 
   Start  Length  Slot  Name   Signature
   0      6      0    this       Lscala/collection/views/TraversableLike;
   0      6      1    p       Lscala/Function1;


public boolean forall(scala.Function1);
  Signature: (Lscala/Function1;)Z
  Code:
   Stack=2, Locals=2, Args_size=2
	aload_0
	aload_1
	invokestatic	Method scala/collection/TraversableLike$class.forall:(Lscala/collection/TraversableLike;Lscala/Function1;)Z
	ireturn
  Labels:
  LocalVariableTable: 
   Start  Length  Slot  Name   Signature
   0      6      0    this       Lscala/collection/views/TraversableLike;
   0      6      1    p       Lscala/Function1;


public scala.collection.Map groupBy(scala.Function1);
  Signature: (Lscala/Function1;)Lscala/collection/Map;
  Code:
   Stack=2, Locals=2, Args_size=2
	aload_0
	aload_1
	invokestatic	Method scala/collection/TraversableLike$class.groupBy:(Lscala/collection/TraversableLike;Lscala/Function1;)Lscala/collection/Map;
	areturn
  Labels:
  LocalVariableTable: 
   Start  Length  Slot  Name   Signature
   0      6      0    this       Lscala/collection/views/TraversableLike;
   0      6      1    f       Lscala/Function1;


public scala.Tuple2 partition(scala.Function1);
  Signature: (Lscala/Function1;)Lscala/Tuple2;
  Code:
   Stack=2, Locals=2, Args_size=2
	aload_0
	aload_1
	invokestatic	Method scala/collection/TraversableLike$class.partition:(Lscala/collection/TraversableLike;Lscala/Function1;)Lscala/Tuple2;
	areturn
  Labels:
  LocalVariableTable: 
   Start  Length  Slot  Name   Signature
   0      6      0    this       Lscala/collection/views/TraversableLike;
   0      6      1    p       Lscala/Function1;


public java.lang.Object partialMap(scala.PartialFunction, scala.collection.generic.CanBuildFrom);
  Signature: (Lscala/PartialFunction;Lscala/collection/generic/CanBuildFrom;)Ljava/lang/Object;
  Code:
   Stack=3, Locals=3, Args_size=3
	aload_0
	aload_1
	aload_2
	invokestatic	Method scala/collection/TraversableLike$class.partialMap:(Lscala/collection/TraversableLike;Lscala/PartialFunction;Lscala/collection/generic/CanBuildFrom;)Ljava/lang/Object;
	areturn
  Labels:
  LocalVariableTable: 
   Start  Length  Slot  Name   Signature
   0      7      0    this       Lscala/collection/views/TraversableLike;
   0      7      1    pf       Lscala/PartialFunction;
   0      7      2    bf       Lscala/collection/generic/CanBuildFrom;


public java.lang.Object filterNot(scala.Function1);
  Signature: (Lscala/Function1;)Ljava/lang/Object;
  Code:
   Stack=2, Locals=2, Args_size=2
	aload_0
	aload_1
	invokestatic	Method scala/collection/TraversableLike$class.filterNot:(Lscala/collection/TraversableLike;Lscala/Function1;)Ljava/lang/Object;
	areturn
  Labels:
  LocalVariableTable: 
   Start  Length  Slot  Name   Signature
   0      6      0    this       Lscala/collection/views/TraversableLike;
   0      6      1    p       Lscala/Function1;


public boolean hasDefiniteSize();
  Signature: ()Z
  Code:
   Stack=1, Locals=1, Args_size=1
	aload_0
	invokestatic	Method scala/collection/TraversableLike$class.hasDefiniteSize:(Lscala/collection/TraversableLike;)Z
	ireturn
  Labels:

public int size();
  Signature: ()I
  Code:
   Stack=1, Locals=1, Args_size=1
	aload_0
	invokestatic	Method scala/collection/TraversableLike$class.size:(Lscala/collection/TraversableLike;)I
	ireturn
  Labels:

public boolean nonEmpty();
  Signature: ()Z
  Code:
   Stack=1, Locals=1, Args_size=1
	aload_0
	invokestatic	Method scala/collection/TraversableLike$class.nonEmpty:(Lscala/collection/TraversableLike;)Z
	ireturn
  Labels:

public boolean isEmpty();
  Signature: ()Z
  Code:
   Stack=1, Locals=1, Args_size=1
	aload_0
	invokestatic	Method scala/collection/TraversableLike$class.isEmpty:(Lscala/collection/TraversableLike;)Z
	ireturn
  Labels:

public scala.collection.Traversable toCollection(java.lang.Object);
  Signature: (Ljava/lang/Object;)Lscala/collection/Traversable;
  Code:
   Stack=2, Locals=2, Args_size=2
	aload_0
	aload_1
	invokestatic	Method scala/collection/TraversableLike$class.toCollection:(Lscala/collection/TraversableLike;Ljava/lang/Object;)Lscala/collection/Traversable;
	areturn
  Labels:
  LocalVariableTable: 
   Start  Length  Slot  Name   Signature
   0      6      0    this       Lscala/collection/views/TraversableLike;
   0      6      1    repr       Ljava/lang/Object;


public scala.collection.Traversable thisCollection();
  Signature: ()Lscala/collection/Traversable;
  Code:
   Stack=1, Locals=1, Args_size=1
	aload_0
	invokestatic	Method scala/collection/TraversableLike$class.thisCollection:(Lscala/collection/TraversableLike;)Lscala/collection/Traversable;
	areturn
  Labels:

public java.lang.Object repr();
  Signature: ()Ljava/lang/Object;
  Code:
   Stack=1, Locals=1, Args_size=1
	aload_0
	invokestatic	Method scala/collection/TraversableLike$class.repr:(Lscala/collection/TraversableLike;)Ljava/lang/Object;
	areturn
  Labels:

public scala.collection.Traversable transpose(scala.Function1);
  Signature: (Lscala/Function1;)Lscala/collection/Traversable;
  Code:
   Stack=2, Locals=2, Args_size=2
	aload_0
	aload_1
	invokestatic	Method scala/collection/generic/GenericTraversableTemplate$class.transpose:(Lscala/collection/generic/GenericTraversableTemplate;Lscala/Function1;)Lscala/collection/Traversable;
	areturn
  Labels:
  LocalVariableTable: 
   Start  Length  Slot  Name   Signature
   0      6      0    this       Lscala/collection/views/TraversableLike;
   0      6      1    asTraversable       Lscala/Function1;


public scala.collection.Traversable flatten(scala.Function1);
  Signature: (Lscala/Function1;)Lscala/collection/Traversable;
  Code:
   Stack=2, Locals=2, Args_size=2
	aload_0
	aload_1
	invokestatic	Method scala/collection/generic/GenericTraversableTemplate$class.flatten:(Lscala/collection/generic/GenericTraversableTemplate;Lscala/Function1;)Lscala/collection/Traversable;
	areturn
  Labels:
  LocalVariableTable: 
   Start  Length  Slot  Name   Signature
   0      6      0    this       Lscala/collection/views/TraversableLike;
   0      6      1    asTraversable       Lscala/Function1;


public scala.Tuple2 unzip(scala.Function1);
  Signature: (Lscala/Function1;)Lscala/Tuple2;
  Code:
   Stack=2, Locals=2, Args_size=2
	aload_0
	aload_1
	invokestatic	Method scala/collection/generic/GenericTraversableTemplate$class.unzip:(Lscala/collection/generic/GenericTraversableTemplate;Lscala/Function1;)Lscala/Tuple2;
	areturn
  Labels:
  LocalVariableTable: 
   Start  Length  Slot  Name   Signature
   0      6      0    this       Lscala/collection/views/TraversableLike;
   0      6      1    asPair       Lscala/Function1;


public scala.collection.mutable.Builder genericBuilder();
  Signature: ()Lscala/collection/mutable/Builder;
  Code:
   Stack=1, Locals=1, Args_size=1
	aload_0
	invokestatic	Method scala/collection/generic/GenericTraversableTemplate$class.genericBuilder:(Lscala/collection/generic/GenericTraversableTemplate;)Lscala/collection/mutable/Builder;
	areturn
  Labels:

public scala.collection.generic.GenericCompanion companion();
  Signature: ()Lscala/collection/generic/GenericCompanion;
  Code:
   Stack=1, Locals=1, Args_size=1
	aload_0
	invokestatic	Method scala/collection/Traversable$class.companion:(Lscala/collection/Traversable;)Lscala/collection/generic/GenericCompanion;
	areturn
  Labels:

public scala.collection.TraversableViewLike$Transformed newTakenWhile(scala.Function1);
  Signature: (Lscala/Function1;)Lscala/collection/TraversableViewLike$Transformed;
  Code:
   Stack=2, Locals=2, Args_size=2
	aload_0
	aload_1
	invokestatic	Method scala/collection/views/TraversableTransformations$class.newTakenWhile:(Lscala/collection/TraversableViewLike;Lscala/Function1;)Lscala/collection/TraversableViewLike$Transformed;
	areturn
  Labels:
  LocalVariableTable: 
   Start  Length  Slot  Name   Signature
   0      6      0    this       Lscala/collection/views/TraversableLike;
   0      6      1    p       Lscala/Function1;

  Signature: length = 0x2
   01 68 

public scala.collection.TraversableViewLike$Transformed newDroppedWhile(scala.Function1);
  Signature: (Lscala/Function1;)Lscala/collection/TraversableViewLike$Transformed;
  Code:
   Stack=2, Locals=2, Args_size=2
	aload_0
	aload_1
	invokestatic	Method scala/collection/views/TraversableTransformations$class.newDroppedWhile:(Lscala/collection/TraversableViewLike;Lscala/Function1;)Lscala/collection/TraversableViewLike$Transformed;
	areturn
  Labels:
  LocalVariableTable: 
   Start  Length  Slot  Name   Signature
   0      6      0    this       Lscala/collection/views/TraversableLike;
   0      6      1    p       Lscala/Function1;

  Signature: length = 0x2
   01 68 

public scala.collection.TraversableViewLike$Transformed newSliced(int, int);
  Signature: (II)Lscala/collection/TraversableViewLike$Transformed;
  Code:
   Stack=3, Locals=3, Args_size=3
	aload_0
	iload_1
	iload_2
	invokestatic	Method scala/collection/views/TraversableTransformations$class.newSliced:(Lscala/collection/TraversableViewLike;II)Lscala/collection/TraversableViewLike$Transformed;
	areturn
  Labels:
  LocalVariableTable: 
   Start  Length  Slot  Name   Signature
   0      7      0    this       Lscala/collection/views/TraversableLike;
   0      7      1    _from       I
   0      7      2    _until       I

  Signature: length = 0x2
   01 70 

public scala.collection.TraversableViewLike$Transformed newFiltered(scala.Function1);
  Signature: (Lscala/Function1;)Lscala/collection/TraversableViewLike$Transformed;
  Code:
   Stack=2, Locals=2, Args_size=2
	aload_0
	aload_1
	invokestatic	Method scala/collection/views/TraversableTransformations$class.newFiltered:(Lscala/collection/TraversableViewLike;Lscala/Function1;)Lscala/collection/TraversableViewLike$Transformed;
	areturn
  Labels:
  LocalVariableTable: 
   Start  Length  Slot  Name   Signature
   0      6      0    this       Lscala/collection/views/TraversableLike;
   0      6      1    p       Lscala/Function1;

  Signature: length = 0x2
   01 68 

public scala.collection.TraversableViewLike$Transformed newFlatMapped(scala.Function1);
  Signature: (Lscala/Function1;)Lscala/collection/TraversableViewLike$Transformed;
  Code:
   Stack=2, Locals=2, Args_size=2
	aload_0
	aload_1
	invokestatic	Method scala/collection/views/TraversableTransformations$class.newFlatMapped:(Lscala/collection/TraversableViewLike;Lscala/Function1;)Lscala/collection/TraversableViewLike$Transformed;
	areturn
  Labels:
  LocalVariableTable: 
   Start  Length  Slot  Name   Signature
   0      6      0    this       Lscala/collection/views/TraversableLike;
   0      6      1    f       Lscala/Function1;

  Signature: length = 0x2
   01 68 

public scala.collection.TraversableViewLike$Transformed newMapped(scala.Function1);
  Signature: (Lscala/Function1;)Lscala/collection/TraversableViewLike$Transformed;
  Code:
   Stack=2, Locals=2, Args_size=2
	aload_0
	aload_1
	invokestatic	Method scala/collection/views/TraversableTransformations$class.newMapped:(Lscala/collection/TraversableViewLike;Lscala/Function1;)Lscala/collection/TraversableViewLike$Transformed;
	areturn
  Labels:
  LocalVariableTable: 
   Start  Length  Slot  Name   Signature
   0      6      0    this       Lscala/collection/views/TraversableLike;
   0      6      1    f       Lscala/Function1;

  Signature: length = 0x2
   01 68 

public scala.collection.TraversableViewLike$Transformed newAppended(scala.collection.Traversable);
  Signature: (Lscala/collection/Traversable;)Lscala/collection/TraversableViewLike$Transformed;
  Code:
   Stack=2, Locals=2, Args_size=2
	aload_0
	aload_1
	invokestatic	Method scala/collection/views/TraversableTransformations$class.newAppended:(Lscala/collection/TraversableViewLike;Lscala/collection/Traversable;)Lscala/collection/TraversableViewLike$Transformed;
	areturn
  Labels:
  LocalVariableTable: 
   Start  Length  Slot  Name   Signature
   0      6      0    this       Lscala/collection/views/TraversableLike;
   0      6      1    that       Lscala/collection/Traversable;

  Signature: length = 0x2
   01 FFFFFF80 

public java.lang.String stringPrefix();
  Signature: ()Ljava/lang/String;
  Code:
   Stack=1, Locals=1, Args_size=1
	aload_0
	invokestatic	Method scala/collection/TraversableViewLike$class.stringPrefix:(Lscala/collection/TraversableViewLike;)Ljava/lang/String;
	areturn
  Labels:

public scala.Tuple2 splitAt(int);
  Signature: (I)Lscala/Tuple2;
  Code:
   Stack=2, Locals=2, Args_size=2
	aload_0
	iload_1
	invokestatic	Method scala/collection/TraversableViewLike$class.splitAt:(Lscala/collection/TraversableViewLike;I)Lscala/Tuple2;
	areturn
  Labels:
  LocalVariableTable: 
   Start  Length  Slot  Name   Signature
   0      6      0    this       Lscala/collection/views/TraversableLike;
   0      6      1    n       I


public scala.Tuple2 span(scala.Function1);
  Signature: (Lscala/Function1;)Lscala/Tuple2;
  Code:
   Stack=2, Locals=2, Args_size=2
	aload_0
	aload_1
	invokestatic	Method scala/collection/TraversableViewLike$class.span:(Lscala/collection/TraversableViewLike;Lscala/Function1;)Lscala/Tuple2;
	areturn
  Labels:
  LocalVariableTable: 
   Start  Length  Slot  Name   Signature
   0      6      0    this       Lscala/collection/views/TraversableLike;
   0      6      1    p       Lscala/Function1;


public scala.collection.TraversableView takeWhile(scala.Function1);
  Signature: (Lscala/Function1;)Lscala/collection/TraversableView;
  Code:
   Stack=2, Locals=2, Args_size=2
	aload_0
	aload_1
	invokestatic	Method scala/collection/TraversableViewLike$class.takeWhile:(Lscala/collection/TraversableViewLike;Lscala/Function1;)Lscala/collection/TraversableView;
	areturn
  Labels:
  LocalVariableTable: 
   Start  Length  Slot  Name   Signature
   0      6      0    this       Lscala/collection/views/TraversableLike;
   0      6      1    p       Lscala/Function1;


public scala.collection.TraversableView dropWhile(scala.Function1);
  Signature: (Lscala/Function1;)Lscala/collection/TraversableView;
  Code:
   Stack=2, Locals=2, Args_size=2
	aload_0
	aload_1
	invokestatic	Method scala/collection/TraversableViewLike$class.dropWhile:(Lscala/collection/TraversableViewLike;Lscala/Function1;)Lscala/collection/TraversableView;
	areturn
  Labels:
  LocalVariableTable: 
   Start  Length  Slot  Name   Signature
   0      6      0    this       Lscala/collection/views/TraversableLike;
   0      6      1    p       Lscala/Function1;


public scala.collection.TraversableView slice(int, int);
  Signature: (II)Lscala/collection/TraversableView;
  Code:
   Stack=3, Locals=3, Args_size=3
	aload_0
	iload_1
	iload_2
	invokestatic	Method scala/collection/TraversableViewLike$class.slice:(Lscala/collection/TraversableViewLike;II)Lscala/collection/TraversableView;
	areturn
  Labels:
  LocalVariableTable: 
   Start  Length  Slot  Name   Signature
   0      7      0    this       Lscala/collection/views/TraversableLike;
   0      7      1    from       I
   0      7      2    until       I


public scala.collection.TraversableView take(int);
  Signature: (I)Lscala/collection/TraversableView;
  Code:
   Stack=2, Locals=2, Args_size=2
	aload_0
	iload_1
	invokestatic	Method scala/collection/TraversableViewLike$class.take:(Lscala/collection/TraversableViewLike;I)Lscala/collection/TraversableView;
	areturn
  Labels:
  LocalVariableTable: 
   Start  Length  Slot  Name   Signature
   0      6      0    this       Lscala/collection/views/TraversableLike;
   0      6      1    n       I


public scala.collection.TraversableView drop(int);
  Signature: (I)Lscala/collection/TraversableView;
  Code:
   Stack=2, Locals=2, Args_size=2
	aload_0
	iload_1
	invokestatic	Method scala/collection/TraversableViewLike$class.drop:(Lscala/collection/TraversableViewLike;I)Lscala/collection/TraversableView;
	areturn
  Labels:
  LocalVariableTable: 
   Start  Length  Slot  Name   Signature
   0      6      0    this       Lscala/collection/views/TraversableLike;
   0      6      1    n       I


public scala.collection.TraversableView init();
  Signature: ()Lscala/collection/TraversableView;
  Code:
   Stack=1, Locals=1, Args_size=1
	aload_0
	invokestatic	Method scala/collection/TraversableViewLike$class.init:(Lscala/collection/TraversableViewLike;)Lscala/collection/TraversableView;
	areturn
  Labels:

public scala.collection.TraversableView filter(scala.Function1);
  Signature: (Lscala/Function1;)Lscala/collection/TraversableView;
  Code:
   Stack=2, Locals=2, Args_size=2
	aload_0
	aload_1
	invokestatic	Method scala/collection/TraversableViewLike$class.filter:(Lscala/collection/TraversableViewLike;Lscala/Function1;)Lscala/collection/TraversableView;
	areturn
  Labels:
  LocalVariableTable: 
   Start  Length  Slot  Name   Signature
   0      6      0    this       Lscala/collection/views/TraversableLike;
   0      6      1    p       Lscala/Function1;


public java.lang.Object flatMap(scala.Function1, scala.collection.generic.CanBuildFrom);
  Signature: (Lscala/Function1;Lscala/collection/generic/CanBuildFrom;)Ljava/lang/Object;
  Code:
   Stack=3, Locals=3, Args_size=3
	aload_0
	aload_1
	aload_2
	invokestatic	Method scala/collection/TraversableViewLike$class.flatMap:(Lscala/collection/TraversableViewLike;Lscala/Function1;Lscala/collection/generic/CanBuildFrom;)Ljava/lang/Object;
	areturn
  Labels:
  LocalVariableTable: 
   Start  Length  Slot  Name   Signature
   0      7      0    this       Lscala/collection/views/TraversableLike;
   0      7      1    f       Lscala/Function1;
   0      7      2    bf       Lscala/collection/generic/CanBuildFrom;


public java.lang.Object map(scala.Function1, scala.collection.generic.CanBuildFrom);
  Signature: (Lscala/Function1;Lscala/collection/generic/CanBuildFrom;)Ljava/lang/Object;
  Code:
   Stack=3, Locals=3, Args_size=3
	aload_0
	aload_1
	aload_2
	invokestatic	Method scala/collection/TraversableViewLike$class.map:(Lscala/collection/TraversableViewLike;Lscala/Function1;Lscala/collection/generic/CanBuildFrom;)Ljava/lang/Object;
	areturn
  Labels:
  LocalVariableTable: 
   Start  Length  Slot  Name   Signature
   0      7      0    this       Lscala/collection/views/TraversableLike;
   0      7      1    f       Lscala/Function1;
   0      7      2    bf       Lscala/collection/generic/CanBuildFrom;


public java.lang.Object $plus$plus(scala.collection.Iterator, scala.collection.generic.CanBuildFrom);
  Signature: (Lscala/collection/Iterator;Lscala/collection/generic/CanBuildFrom;)Ljava/lang/Object;
  Code:
   Stack=3, Locals=3, Args_size=3
	aload_0
	aload_1
	aload_2
	invokestatic	Method scala/collection/TraversableViewLike$class.$plus$plus:(Lscala/collection/TraversableViewLike;Lscala/collection/Iterator;Lscala/collection/generic/CanBuildFrom;)Ljava/lang/Object;
	areturn
  Labels:
  LocalVariableTable: 
   Start  Length  Slot  Name   Signature
   0      7      0    this       Lscala/collection/views/TraversableLike;
   0      7      1    that       Lscala/collection/Iterator;
   0      7      2    bf       Lscala/collection/generic/CanBuildFrom;


public java.lang.Object $plus$plus(scala.collection.Traversable, scala.collection.generic.CanBuildFrom);
  Signature: (Lscala/collection/Traversable;Lscala/collection/generic/CanBuildFrom;)Ljava/lang/Object;
  Code:
   Stack=3, Locals=3, Args_size=3
	aload_0
	aload_1
	aload_2
	invokestatic	Method scala/collection/TraversableViewLike$class.$plus$plus:(Lscala/collection/TraversableViewLike;Lscala/collection/Traversable;Lscala/collection/generic/CanBuildFrom;)Ljava/lang/Object;
	areturn
  Labels:
  LocalVariableTable: 
   Start  Length  Slot  Name   Signature
   0      7      0    this       Lscala/collection/views/TraversableLike;
   0      7      1    that       Lscala/collection/Traversable;
   0      7      2    bf       Lscala/collection/generic/CanBuildFrom;


public java.lang.Object force(scala.collection.generic.CanBuildFrom);
  Signature: (Lscala/collection/generic/CanBuildFrom;)Ljava/lang/Object;
  Code:
   Stack=2, Locals=2, Args_size=2
	aload_0
	aload_1
	invokestatic	Method scala/collection/TraversableViewLike$class.force:(Lscala/collection/TraversableViewLike;Lscala/collection/generic/CanBuildFrom;)Ljava/lang/Object;
	areturn
  Labels:
  LocalVariableTable: 
   Start  Length  Slot  Name   Signature
   0      6      0    this       Lscala/collection/views/TraversableLike;
   0      6      1    bf       Lscala/collection/generic/CanBuildFrom;


public scala.collection.mutable.Builder newBuilder();
  Signature: ()Lscala/collection/mutable/Builder;
  Code:
   Stack=1, Locals=1, Args_size=1
	aload_0
	invokestatic	Method scala/collection/TraversableViewLike$class.newBuilder:(Lscala/collection/TraversableViewLike;)Lscala/collection/mutable/Builder;
	areturn
  Labels:

}

