Compiled from "Transformed.scala"
public abstract class scala.collection.views.TraversableTransformations$class extends java.lang.Object
  SourceFile: "Transformed.scala"
  Scala: length = 0x
   
  InnerClass: 
   public abstract Transformed=class scala/collection/TraversableViewLike$Transformed of class scala/collection/TraversableViewLike
   public final $anon$32=class scala/collection/views/TraversableTransformations$$anon$32 of class scala/collection/views/TraversableTransformations
   public final $anon$33=class scala/collection/views/TraversableTransformations$$anon$33 of class scala/collection/views/TraversableTransformations
   public final $anon$34=class scala/collection/views/TraversableTransformations$$anon$34 of class scala/collection/views/TraversableTransformations
   public final $anon$35=class scala/collection/views/TraversableTransformations$$anon$35 of class scala/collection/views/TraversableTransformations
   public final $anon$36=class scala/collection/views/TraversableTransformations$$anon$36 of class scala/collection/views/TraversableTransformations
   public final $anon$37=class scala/collection/views/TraversableTransformations$$anon$37 of class scala/collection/views/TraversableTransformations
   public final $anon$38=class scala/collection/views/TraversableTransformations$$anon$38 of class scala/collection/views/TraversableTransformations
  minor version: 0
  major version: 49
  Constant pool:
Asciz	SourceFile;
Asciz	Transformed.scala;
Asciz	$init$;
Asciz	(Lscala/collection/TraversableViewLike;)V;
Asciz	Code;
Asciz	LineNumberTable;
Asciz	$this;
Asciz	Lscala/collection/TraversableViewLike;;
Asciz	LocalVariableTable;
Asciz	newTakenWhile;
Asciz	(Lscala/collection/TraversableViewLike;Lscala/Function1;)Lscala/collection/TraversableViewLike$Transformed;;
Asciz	scala/collection/views/TraversableTransformations$$anon$38;
class	scala/collection/views/TraversableTransformations$$anon$38
Asciz	<init>;
Asciz	(Lscala/collection/TraversableViewLike;Lscala/Function1;)V;
NameAndType	"<init>":(Lscala/collection/TraversableViewLike;Lscala/Function1;)V
Method	scala/collection/views/TraversableTransformations$$anon$38."<init>":(Lscala/collection/TraversableViewLike;Lscala/Function1;)V
Asciz	p$2;
Asciz	Lscala/Function1;;
Asciz	newDroppedWhile;
Asciz	scala/collection/views/TraversableTransformations$$anon$37;
class	scala/collection/views/TraversableTransformations$$anon$37
Method	scala/collection/views/TraversableTransformations$$anon$37."<init>":(Lscala/collection/TraversableViewLike;Lscala/Function1;)V
Asciz	p$4;
Asciz	newSliced;
Asciz	(Lscala/collection/TraversableViewLike;II)Lscala/collection/TraversableViewLike$Transformed;;
Asciz	scala/collection/views/TraversableTransformations$$anon$36;
class	scala/collection/views/TraversableTransformations$$anon$36
Asciz	(Lscala/collection/TraversableViewLike;II)V;
NameAndType	"<init>":(Lscala/collection/TraversableViewLike;II)V
Method	scala/collection/views/TraversableTransformations$$anon$36."<init>":(Lscala/collection/TraversableViewLike;II)V
Asciz	_from$2;
Asciz	I;
Asciz	_until$2;
Asciz	newFiltered;
Asciz	scala/collection/views/TraversableTransformations$$anon$35;
class	scala/collection/views/TraversableTransformations$$anon$35
Method	scala/collection/views/TraversableTransformations$$anon$35."<init>":(Lscala/collection/TraversableViewLike;Lscala/Function1;)V
Asciz	p$6;
Asciz	newFlatMapped;
Asciz	scala/collection/views/TraversableTransformations$$anon$34;
class	scala/collection/views/TraversableTransformations$$anon$34
Method	scala/collection/views/TraversableTransformations$$anon$34."<init>":(Lscala/collection/TraversableViewLike;Lscala/Function1;)V
Asciz	f$2;
Asciz	newMapped;
Asciz	scala/collection/views/TraversableTransformations$$anon$33;
class	scala/collection/views/TraversableTransformations$$anon$33
Method	scala/collection/views/TraversableTransformations$$anon$33."<init>":(Lscala/collection/TraversableViewLike;Lscala/Function1;)V
Asciz	f$4;
Asciz	newAppended;
Asciz	(Lscala/collection/TraversableViewLike;Lscala/collection/Traversable;)Lscala/collection/TraversableViewLike$Transformed;;
Asciz	scala/collection/views/TraversableTransformations$$anon$32;
class	scala/collection/views/TraversableTransformations$$anon$32
Asciz	(Lscala/collection/TraversableViewLike;Lscala/collection/Traversable;)V;
NameAndType	"<init>":(Lscala/collection/TraversableViewLike;Lscala/collection/Traversable;)V
Method	scala/collection/views/TraversableTransformations$$anon$32."<init>":(Lscala/collection/TraversableViewLike;Lscala/collection/Traversable;)V
Asciz	that$2;
Asciz	Lscala/collection/Traversable;;
Asciz	Scala;
Asciz	InnerClasses;
Asciz	scala/collection/TraversableViewLike$Transformed;
class	scala/collection/TraversableViewLike$Transformed
Asciz	scala/collection/TraversableViewLike;
class	scala/collection/TraversableViewLike
Asciz	Transformed;
Asciz	scala/collection/views/TraversableTransformations;
class	scala/collection/views/TraversableTransformations
Asciz	$anon$32;
Asciz	$anon$33;
Asciz	$anon$34;
Asciz	$anon$35;
Asciz	$anon$36;
Asciz	$anon$37;
Asciz	$anon$38;
Asciz	scala/collection/views/TraversableTransformations$class;
class	scala/collection/views/TraversableTransformations$class
Asciz	java/lang/Object;
class	java/lang/Object

{
public static void $init$(scala.collection.TraversableViewLike);
  Signature: (Lscala/collection/TraversableViewLike;)V
  Code:
   Stack=0, Locals=1, Args_size=1
	return
  Labels:
  LocalVariableTable: 
   Start  Length  Slot  Name   Signature
   0      1      0    $this       Lscala/collection/TraversableViewLike;


public static scala.collection.TraversableViewLike$Transformed newTakenWhile(scala.collection.TraversableViewLike, scala.Function1);
  Signature: (Lscala/collection/TraversableViewLike;Lscala/Function1;)Lscala/collection/TraversableViewLike$Transformed;
  Code:
   Stack=4, Locals=2, Args_size=2
	new	class scala/collection/views/TraversableTransformations$$anon$38
	dup
	aload_0
	aload_1
	invokespecial	Method scala/collection/views/TraversableTransformations$$anon$38."<init>":(Lscala/collection/TraversableViewLike;Lscala/Function1;)V
	areturn
  Labels:
  LocalVariableTable: 
   Start  Length  Slot  Name   Signature
   0      10      0    $this       Lscala/collection/TraversableViewLike;
   0      10      1    p$2       Lscala/Function1;


public static scala.collection.TraversableViewLike$Transformed newDroppedWhile(scala.collection.TraversableViewLike, scala.Function1);
  Signature: (Lscala/collection/TraversableViewLike;Lscala/Function1;)Lscala/collection/TraversableViewLike$Transformed;
  Code:
   Stack=4, Locals=2, Args_size=2
	new	class scala/collection/views/TraversableTransformations$$anon$37
	dup
	aload_0
	aload_1
	invokespecial	Method scala/collection/views/TraversableTransformations$$anon$37."<init>":(Lscala/collection/TraversableViewLike;Lscala/Function1;)V
	areturn
  Labels:
  LocalVariableTable: 
   Start  Length  Slot  Name   Signature
   0      10      0    $this       Lscala/collection/TraversableViewLike;
   0      10      1    p$4       Lscala/Function1;


public static scala.collection.TraversableViewLike$Transformed newSliced(scala.collection.TraversableViewLike, int, int);
  Signature: (Lscala/collection/TraversableViewLike;II)Lscala/collection/TraversableViewLike$Transformed;
  Code:
   Stack=5, Locals=3, Args_size=3
	new	class scala/collection/views/TraversableTransformations$$anon$36
	dup
	aload_0
	iload_1
	iload_2
	invokespecial	Method scala/collection/views/TraversableTransformations$$anon$36."<init>":(Lscala/collection/TraversableViewLike;II)V
	areturn
  Labels:
  LocalVariableTable: 
   Start  Length  Slot  Name   Signature
   0      11      0    $this       Lscala/collection/TraversableViewLike;
   0      11      1    _from$2       I
   0      11      2    _until$2       I


public static scala.collection.TraversableViewLike$Transformed newFiltered(scala.collection.TraversableViewLike, scala.Function1);
  Signature: (Lscala/collection/TraversableViewLike;Lscala/Function1;)Lscala/collection/TraversableViewLike$Transformed;
  Code:
   Stack=4, Locals=2, Args_size=2
	new	class scala/collection/views/TraversableTransformations$$anon$35
	dup
	aload_0
	aload_1
	invokespecial	Method scala/collection/views/TraversableTransformations$$anon$35."<init>":(Lscala/collection/TraversableViewLike;Lscala/Function1;)V
	areturn
  Labels:
  LocalVariableTable: 
   Start  Length  Slot  Name   Signature
   0      10      0    $this       Lscala/collection/TraversableViewLike;
   0      10      1    p$6       Lscala/Function1;


public static scala.collection.TraversableViewLike$Transformed newFlatMapped(scala.collection.TraversableViewLike, scala.Function1);
  Signature: (Lscala/collection/TraversableViewLike;Lscala/Function1;)Lscala/collection/TraversableViewLike$Transformed;
  Code:
   Stack=4, Locals=2, Args_size=2
	new	class scala/collection/views/TraversableTransformations$$anon$34
	dup
	aload_0
	aload_1
	invokespecial	Method scala/collection/views/TraversableTransformations$$anon$34."<init>":(Lscala/collection/TraversableViewLike;Lscala/Function1;)V
	areturn
  Labels:
  LocalVariableTable: 
   Start  Length  Slot  Name   Signature
   0      10      0    $this       Lscala/collection/TraversableViewLike;
   0      10      1    f$2       Lscala/Function1;


public static scala.collection.TraversableViewLike$Transformed newMapped(scala.collection.TraversableViewLike, scala.Function1);
  Signature: (Lscala/collection/TraversableViewLike;Lscala/Function1;)Lscala/collection/TraversableViewLike$Transformed;
  Code:
   Stack=4, Locals=2, Args_size=2
	new	class scala/collection/views/TraversableTransformations$$anon$33
	dup
	aload_0
	aload_1
	invokespecial	Method scala/collection/views/TraversableTransformations$$anon$33."<init>":(Lscala/collection/TraversableViewLike;Lscala/Function1;)V
	areturn
  Labels:
  LocalVariableTable: 
   Start  Length  Slot  Name   Signature
   0      10      0    $this       Lscala/collection/TraversableViewLike;
   0      10      1    f$4       Lscala/Function1;


public static scala.collection.TraversableViewLike$Transformed newAppended(scala.collection.TraversableViewLike, scala.collection.Traversable);
  Signature: (Lscala/collection/TraversableViewLike;Lscala/collection/Traversable;)Lscala/collection/TraversableViewLike$Transformed;
  Code:
   Stack=4, Locals=2, Args_size=2
	new	class scala/collection/views/TraversableTransformations$$anon$32
	dup
	aload_0
	aload_1
	invokespecial	Method scala/collection/views/TraversableTransformations$$anon$32."<init>":(Lscala/collection/TraversableViewLike;Lscala/collection/Traversable;)V
	areturn
  Labels:
  LocalVariableTable: 
   Start  Length  Slot  Name   Signature
   0      10      0    $this       Lscala/collection/TraversableViewLike;
   0      10      1    that$2       Lscala/collection/Traversable;


}

