Compiled from "Transformed.scala"
public final class scala.collection.views.TraversableTransformations$$anon$36 extends scala.collection.views.TraversableLike implements scala.collection.TraversableViewLike$Sliced
  SourceFile: "Transformed.scala"
  Signature: length = 0x2
   00 53 
  Scala: length = 0x
   
  InnerClass: 
   public abstract Sliced=class scala/collection/TraversableViewLike$Sliced of class scala/collection/TraversableViewLike
   public abstract Transformed=class scala/collection/TraversableViewLike$Transformed of class scala/collection/TraversableViewLike
   public final $anon$36=class scala/collection/views/TraversableTransformations$$anon$36 of class scala/collection/views/TraversableTransformations
  minor version: 0
  major version: 49
  Constant pool:
Asciz	SourceFile;
Asciz	Transformed.scala;
Asciz	bitmap$0;
Asciz	I;
Asciz	underlying;
Asciz	Ljava/lang/Object;;
Asciz	$outer;
Asciz	Lscala/collection/TraversableViewLike;;
Asciz	until;
Asciz	from;
Asciz	<init>;
Asciz	(Lscala/collection/TraversableViewLike;II)V;
Asciz	Code;
Asciz	LineNumberTable;
Asciz	java/lang/NullPointerException;
class	java/lang/NullPointerException
Asciz	()V;
NameAndType	"<init>":()V
Method	java/lang/NullPointerException."<init>":()V
Asciz	scala/collection/views/TraversableTransformations$$anon$36;
class	scala/collection/views/TraversableTransformations$$anon$36
NameAndType	$outer:Lscala/collection/TraversableViewLike;
Field	scala/collection/views/TraversableTransformations$$anon$36.$outer:Lscala/collection/TraversableViewLike;
Asciz	scala/collection/views/TraversableLike;
class	scala/collection/views/TraversableLike
Method	scala/collection/views/TraversableLike."<init>":()V
Asciz	scala/collection/TraversableViewLike$Transformed$class;
class	scala/collection/TraversableViewLike$Transformed$class
Asciz	$init$;
Asciz	(Lscala/collection/TraversableViewLike$Transformed;)V;
NameAndType	$init$:(Lscala/collection/TraversableViewLike$Transformed;)V
Method	scala/collection/TraversableViewLike$Transformed$class.$init$:(Lscala/collection/TraversableViewLike$Transformed;)V
Asciz	scala/collection/TraversableViewLike$Sliced$class;
class	scala/collection/TraversableViewLike$Sliced$class
Asciz	(Lscala/collection/TraversableViewLike$Sliced;)V;
NameAndType	$init$:(Lscala/collection/TraversableViewLike$Sliced;)V
Method	scala/collection/TraversableViewLike$Sliced$class.$init$:(Lscala/collection/TraversableViewLike$Sliced;)V
NameAndType	from:I
Field	scala/collection/views/TraversableTransformations$$anon$36.from:I
NameAndType	until:I
Field	scala/collection/views/TraversableTransformations$$anon$36.until:I
Asciz	this;
Asciz	Lscala/collection/views/TraversableTransformations$$anon$36;;
Asciz	LocalVariableTable;
Asciz	(Lscala/collection/TraversableViewLike<TA;TColl;TThis;>;)V;
Asciz	Signature;
Asciz	slice;
Asciz	(II)Ljava/lang/Object;;
Asciz	scala/collection/TraversableViewLike$Sliced;
class	scala/collection/TraversableViewLike$Sliced
Asciz	(II)Lscala/collection/TraversableView;;
NameAndType	slice:(II)Lscala/collection/TraversableView;
InterfaceMethod	scala/collection/TraversableViewLike$Sliced.slice:(II)Lscala/collection/TraversableView;
Asciz	scala$collection$TraversableViewLike$Transformed$$$outer;
Asciz	()Lscala/collection/TraversableViewLike;;
Asciz	scala$collection$TraversableViewLike$Sliced$$$outer;
Asciz	()I;
Asciz	()Ljava/lang/Object;;
NameAndType	bitmap$0:I
Field	scala/collection/views/TraversableTransformations$$anon$36.bitmap$0:I
Asciz	(Lscala/collection/TraversableViewLike$Transformed;)Ljava/lang/Object;;
NameAndType	underlying:(Lscala/collection/TraversableViewLike$Transformed;)Ljava/lang/Object;
Method	scala/collection/TraversableViewLike$Transformed$class.underlying:(Lscala/collection/TraversableViewLike$Transformed;)Ljava/lang/Object;
NameAndType	underlying:Ljava/lang/Object;
Field	scala/collection/views/TraversableTransformations$$anon$36.underlying:Ljava/lang/Object;
Asciz	(Lscala/collection/TraversableViewLike$Sliced;II)Lscala/collection/TraversableView;;
NameAndType	slice:(Lscala/collection/TraversableViewLike$Sliced;II)Lscala/collection/TraversableView;
Method	scala/collection/TraversableViewLike$Sliced$class.slice:(Lscala/collection/TraversableViewLike$Sliced;II)Lscala/collection/TraversableView;
Asciz	from1;
Asciz	until1;
Asciz	stringPrefix;
Asciz	()Ljava/lang/String;;
Asciz	(Lscala/collection/TraversableViewLike$Sliced;)Ljava/lang/String;;
NameAndType	stringPrefix:(Lscala/collection/TraversableViewLike$Sliced;)Ljava/lang/String;
Method	scala/collection/TraversableViewLike$Sliced$class.stringPrefix:(Lscala/collection/TraversableViewLike$Sliced;)Ljava/lang/String;
Asciz	foreach;
Asciz	(Lscala/Function1;)V;
Asciz	(Lscala/collection/TraversableViewLike$Sliced;Lscala/Function1;)V;
NameAndType	foreach:(Lscala/collection/TraversableViewLike$Sliced;Lscala/Function1;)V
Method	scala/collection/TraversableViewLike$Sliced$class.foreach:(Lscala/collection/TraversableViewLike$Sliced;Lscala/Function1;)V
Asciz	f;
Asciz	Lscala/Function1;;
Asciz	Lscala/collection/views/TraversableLike<TA;TColl;>;Lscala/collection/TraversableViewLike<TA;TColl;TThis;>.Sliced;;
Asciz	Scala;
Asciz	InnerClasses;
Asciz	scala/collection/TraversableViewLike;
class	scala/collection/TraversableViewLike
Asciz	Sliced;
Asciz	scala/collection/TraversableViewLike$Transformed;
class	scala/collection/TraversableViewLike$Transformed
Asciz	Transformed;
Asciz	scala/collection/views/TraversableTransformations;
class	scala/collection/views/TraversableTransformations
Asciz	$anon$36;

{
public volatile int bitmap$0;
  Signature: I

private final java.lang.Object underlying;
  Signature: Ljava/lang/Object;

private final scala.collection.TraversableViewLike $outer;
  Signature: Lscala/collection/TraversableViewLike;

private final int until;
  Signature: I

private final int from;
  Signature: I

public scala.collection.views.TraversableTransformations$$anon$36(scala.collection.TraversableViewLike, int, int);
  Signature: (Lscala/collection/TraversableViewLike;II)V
  Code:
   Stack=2, Locals=4, Args_size=4
	aload_1
	ifnonnull	l1 // aload_0
	new	class java/lang/NullPointerException
	dup
	invokespecial	Method java/lang/NullPointerException."<init>":()V
	athrow
l1	aload_0
	aload_1
	putfield	Field $outer:Lscala/collection/TraversableViewLike;
	aload_0
	invokespecial	Method scala/collection/views/TraversableLike."<init>":()V
	aload_0
	invokestatic	Method scala/collection/TraversableViewLike$Transformed$class.$init$:(Lscala/collection/TraversableViewLike$Transformed;)V
	aload_0
	invokestatic	Method scala/collection/TraversableViewLike$Sliced$class.$init$:(Lscala/collection/TraversableViewLike$Sliced;)V
	aload_0
	iload_2
	putfield	Field from:I
	aload_0
	iload_3
	putfield	Field until:I
	return
  Labels:
   	l1 = 12 // aload_0
  LocalVariableTable: 
   Start  Length  Slot  Name   Signature
   0      40      0    this       Lscala/collection/views/TraversableTransformations$$anon$36;
   0      40      1    $outer       Lscala/collection/TraversableViewLike;

  Signature: length = 0x2
   00 2D 

public java.lang.Object slice(int, int);
  Signature: (II)Ljava/lang/Object;
  Code:
   Stack=3, Locals=3, Args_size=3
	aload_0
	iload_1
	iload_2
	invokeinterface	InterfaceMethod scala/collection/TraversableViewLike$Sliced.slice:(II)Lscala/collection/TraversableView;
	areturn
  Labels:
  LocalVariableTable: 
   Start  Length  Slot  Name   Signature
   0      9      0    this       Lscala/collection/views/TraversableTransformations$$anon$36;
   0      9      1    from       I
   0      9      2    until       I


public scala.collection.TraversableViewLike scala$collection$TraversableViewLike$Transformed$$$outer();
  Signature: ()Lscala/collection/TraversableViewLike;
  Code:
   Stack=1, Locals=1, Args_size=1
	aload_0
	getfield	Field $outer:Lscala/collection/TraversableViewLike;
	areturn
  Labels:

public scala.collection.TraversableViewLike scala$collection$TraversableViewLike$Sliced$$$outer();
  Signature: ()Lscala/collection/TraversableViewLike;
  Code:
   Stack=1, Locals=1, Args_size=1
	aload_0
	getfield	Field $outer:Lscala/collection/TraversableViewLike;
	areturn
  Labels:

public int until();
  Signature: ()I
  Code:
   Stack=1, Locals=1, Args_size=1
	aload_0
	getfield	Field until:I
	ireturn
  Labels:

public int from();
  Signature: ()I
  Code:
   Stack=1, Locals=1, Args_size=1
	aload_0
	getfield	Field from:I
	ireturn
  Labels:

public java.lang.Object underlying();
  Signature: ()Ljava/lang/Object;
  Code:
   Stack=3, Locals=1, Args_size=1
	aload_0
	getfield	Field bitmap$0:I
	iconst_1
	iand
	iconst_0
	if_icmpne	l1 // aload_0
	aload_0
	dup
	pop
	monitorenter
	aload_0
	getfield	Field bitmap$0:I
	iconst_1
	iand
	iconst_0
	if_icmpne	l2 // aload_0
	aload_0
	aload_0
	invokestatic	Method scala/collection/TraversableViewLike$Transformed$class.underlying:(Lscala/collection/TraversableViewLike$Transformed;)Ljava/lang/Object;
	putfield	Field underlying:Ljava/lang/Object;
	aload_0
	aload_0
	getfield	Field bitmap$0:I
	iconst_1
	ior
	putfield	Field bitmap$0:I
l2	aload_0
	monitorexit
l1	aload_0
	getfield	Field underlying:Ljava/lang/Object;
	areturn
	aload_0
	monitorexit
	athrow
  Labels:
   	l2 = 42 // aload_0
   	l1 = 44 // aload_0
  Exception table:
   from   to  target type
    14    44    49   any

public scala.collection.TraversableView slice(int, int);
  Signature: (II)Lscala/collection/TraversableView;
  Code:
   Stack=3, Locals=3, Args_size=3
	aload_0
	iload_1
	iload_2
	invokestatic	Method scala/collection/TraversableViewLike$Sliced$class.slice:(Lscala/collection/TraversableViewLike$Sliced;II)Lscala/collection/TraversableView;
	areturn
  Labels:
  LocalVariableTable: 
   Start  Length  Slot  Name   Signature
   0      7      0    this       Lscala/collection/views/TraversableTransformations$$anon$36;
   0      7      1    from1       I
   0      7      2    until1       I


public java.lang.String stringPrefix();
  Signature: ()Ljava/lang/String;
  Code:
   Stack=1, Locals=1, Args_size=1
	aload_0
	invokestatic	Method scala/collection/TraversableViewLike$Sliced$class.stringPrefix:(Lscala/collection/TraversableViewLike$Sliced;)Ljava/lang/String;
	areturn
  Labels:

public void foreach(scala.Function1);
  Signature: (Lscala/Function1;)V
  Code:
   Stack=2, Locals=2, Args_size=2
	aload_0
	aload_1
	invokestatic	Method scala/collection/TraversableViewLike$Sliced$class.foreach:(Lscala/collection/TraversableViewLike$Sliced;Lscala/Function1;)V
	return
  Labels:
  LocalVariableTable: 
   Start  Length  Slot  Name   Signature
   0      6      0    this       Lscala/collection/views/TraversableTransformations$$anon$36;
   0      6      1    f       Lscala/Function1;


}

