Compiled from "Binder.scala"
public abstract class scala.xml.factory.Binder extends scala.xml.parsing.ValidatingMarkupHandler implements scala.ScalaObject
  SourceFile: "Binder.scala"
  ScalaSig: length = 0x2F0
   05 00 73 06 08 01 02 FFFFFF84 FFFFFF80 FFFFFF80 FFFFFF81 00 09 02 06 42
   69 6E 64 65 72 0A 02 03 04 01 07 66 61 63 74 6F
   72 79 0A 02 05 06 01 03 78 6D 6C 0A 01 07 01 05
   73 63 61 6C 61 03 00 13 03 00 0A 10 10 02 0B 0E
   0D 01 0C 0A 02 0D 04 01 07 70 61 72 73 69 6E 67
   09 02 0F 0C 02 17 56 61 6C 69 64 61 74 69 6E 67
   4D 61 72 6B 75 70 48 61 6E 64 6C 65 72 10 02 11
   12 0D 01 06 09 02 13 06 02 0B 53 63 61 6C 61 4F
   62 6A 65 63 74 08 08 15 00 FFFFFF82 FFFFFFC2 FFFFFF80 FFFFFF84 00 16 01
   0A 70 72 65 73 65 72 76 65 57 53 15 01 17 10 02
   11 18 09 02 19 06 02 07 42 6F 6F 6C 65 61 6E 08
   08 1B 00 FFFFFF82 FFFFFF80 FFFFFFA0 FFFFFF80 04 17 01 0B 70 72 65 73 65
   72 76 65 57 53 20 08 05 1D 00 FFFFFF84 00 1E 01 06 3C
   69 6E 69 74 3E 14 02 1F 21 10 02 20 00 0D 01 02
   08 05 15 1C FFFFFFC0 00 17 08 07 23 00 FFFFFFC0 FFFFFF80 FFFFFF84 00 24
   01 06 72 65 73 75 6C 74 15 01 25 10 02 26 27 0D
   01 04 09 02 28 04 02 0A 4E 6F 64 65 42 75 66 66
   65 72 08 07 2A 00 FFFFFFC0 FFFFFF80 FFFFFF84 00 2B 01 0A 72 65 73
   75 6C 74 5F 24 65 71 14 02 2C 2F 10 02 11 2D 09
   02 2E 06 02 04 55 6E 69 74 08 07 30 29 FFFFFF81 FFFFFF80 FFFFFFC0
   00 25 01 03 78 24 31 08 06 32 00 FFFFFFA0 FFFFFFA0 04 25 01
   07 72 65 73 75 6C 74 20 08 05 34 00 FFFFFF84 00 35 01
   11 72 65 70 6F 72 74 53 79 6E 74 61 78 45 72 72
   6F 72 14 03 2C 36 3B 08 05 37 33 FFFFFFC0 00 38 01 03
   70 6F 73 10 02 11 39 09 02 3A 06 02 03 49 6E 74
   08 05 3C 33 FFFFFFC0 00 3D 01 03 73 74 72 10 02 3E 41
   0E 02 11 3F 09 02 40 06 01 06 50 72 65 64 65 66
   09 02 42 43 02 06 53 74 72 69 6E 67 0A 02 40 06
   08 05 45 00 FFFFFF84 02 46 01 09 70 72 6F 63 49 6E 73
   74 72 14 04 47 4A 4B 4D 10 02 26 48 09 02 49 04
   02 09 50 72 6F 63 49 6E 73 74 72 08 05 37 44 FFFFFFC0
   00 38 08 05 4C 44 FFFFFFC0 00 3D 01 06 74 61 72 67 65
   74 08 05 4E 44 FFFFFFC0 00 3D 01 03 74 78 74 08 05 50
   00 FFFFFF84 02 51 01 07 63 6F 6D 6D 65 6E 74 14 03 52
   55 56 10 02 26 53 09 02 54 04 02 07 43 6F 6D 6D
   65 6E 74 08 05 37 4F FFFFFFC0 00 38 08 05 4E 4F FFFFFFC0 00
   3D 08 05 58 00 FFFFFF84 02 59 01 09 65 6E 74 69 74 79
   52 65 66 14 03 5A 5D 5E 10 02 26 5B 09 02 5C 04
   02 09 45 6E 74 69 74 79 52 65 66 08 05 37 57 FFFFFFC0
   00 38 08 05 5F 57 FFFFFFC0 00 3D 01 01 6E 08 05 61 00
   FFFFFF84 02 62 01 04 74 65 78 74 14 03 63 66 67 10 02
   26 64 09 02 65 04 02 04 54 65 78 74 08 05 37 60
   FFFFFFC0 00 38 08 05 4E 60 FFFFFFC0 00 3D 08 05 69 00 FFFFFF84 02
   6A 01 08 74 72 61 76 65 72 73 65 14 02 2C 6B 08
   05 5F 68 FFFFFFC0 00 6C 10 02 26 6D 09 02 6E 04 02 04
   4E 6F 64 65 08 05 70 00 FFFFFF84 02 71 01 08 76 61 6C
   69 64 61 74 65 14 02 6C 72 08 05 5F 6F FFFFFFC0 00 6C
   
  InnerClass: 
   public final $anonfun$traverse$1=class scala/xml/factory/Binder$$anonfun$traverse$1 of class scala/xml/factory/Binder
  minor version: 0
  major version: 49
  Constant pool:
Asciz	SourceFile;
Asciz	Binder.scala;
Asciz	result;
Asciz	Lscala/xml/NodeBuffer;;
Asciz	preserveWS;
Asciz	Z;
Asciz	()Z;
Asciz	Code;
Asciz	LineNumberTable;
Asciz	scala/xml/factory/Binder;
class	scala/xml/factory/Binder
NameAndType	preserveWS:Z
Field	scala/xml/factory/Binder.preserveWS:Z
Asciz	()Lscala/xml/NodeBuffer;;
NameAndType	result:Lscala/xml/NodeBuffer;
Field	scala/xml/factory/Binder.result:Lscala/xml/NodeBuffer;
Asciz	result_$eq;
Asciz	(Lscala/xml/NodeBuffer;)V;
Asciz	reportSyntaxError;
Asciz	(ILjava/lang/String;)V;
Asciz	this;
Asciz	Lscala/xml/factory/Binder;;
Asciz	pos;
Asciz	I;
Asciz	str;
Asciz	Ljava/lang/String;;
Asciz	LocalVariableTable;
Asciz	procInstr;
Asciz	(ILjava/lang/String;Ljava/lang/String;)Lscala/xml/ProcInstr;;
Asciz	scala/xml/ProcInstr;
class	scala/xml/ProcInstr
Asciz	<init>;
Asciz	(Ljava/lang/String;Ljava/lang/String;)V;
NameAndType	"<init>":(Ljava/lang/String;Ljava/lang/String;)V
Method	scala/xml/ProcInstr."<init>":(Ljava/lang/String;Ljava/lang/String;)V
Asciz	target;
Asciz	txt;
Asciz	comment;
Asciz	(ILjava/lang/String;)Lscala/xml/Comment;;
Asciz	scala/xml/Comment;
class	scala/xml/Comment
Asciz	(Ljava/lang/String;)V;
NameAndType	"<init>":(Ljava/lang/String;)V
Method	scala/xml/Comment."<init>":(Ljava/lang/String;)V
Asciz	entityRef;
Asciz	(ILjava/lang/String;)Lscala/xml/EntityRef;;
Asciz	scala/xml/EntityRef;
class	scala/xml/EntityRef
Method	scala/xml/EntityRef."<init>":(Ljava/lang/String;)V
Asciz	n;
Asciz	text;
Asciz	(ILjava/lang/String;)Lscala/xml/Text;;
Asciz	scala/xml/Text;
class	scala/xml/Text
Method	scala/xml/Text."<init>":(Ljava/lang/String;)V
Asciz	traverse;
Asciz	(Lscala/xml/Node;)V;
NameAndType	result:()Lscala/xml/NodeBuffer;
Method	scala/xml/factory/Binder.result:()Lscala/xml/NodeBuffer;
Asciz	()Ljava/lang/String;;
NameAndType	target:()Ljava/lang/String;
Method	scala/xml/ProcInstr.target:()Ljava/lang/String;
NameAndType	text:()Ljava/lang/String;
Method	scala/xml/ProcInstr.text:()Ljava/lang/String;
NameAndType	procInstr:(ILjava/lang/String;Ljava/lang/String;)Lscala/xml/ProcInstr;
Method	scala/xml/factory/Binder.procInstr:(ILjava/lang/String;Ljava/lang/String;)Lscala/xml/ProcInstr;
Asciz	scala/xml/NodeBuffer;
class	scala/xml/NodeBuffer
Asciz	$amp$plus;
Asciz	(Ljava/lang/Object;)Lscala/xml/NodeBuffer;;
NameAndType	$amp$plus:(Ljava/lang/Object;)Lscala/xml/NodeBuffer;
Method	scala/xml/NodeBuffer.$amp$plus:(Ljava/lang/Object;)Lscala/xml/NodeBuffer;
Method	scala/xml/Comment.text:()Ljava/lang/String;
NameAndType	comment:(ILjava/lang/String;)Lscala/xml/Comment;
Method	scala/xml/factory/Binder.comment:(ILjava/lang/String;)Lscala/xml/Comment;
Asciz	data;
Asciz	()Ljava/lang/Object;;
NameAndType	data:()Ljava/lang/Object;
Method	scala/xml/Text.data:()Ljava/lang/Object;
Asciz	java/lang/String;
class	java/lang/String
NameAndType	text:(ILjava/lang/String;)Lscala/xml/Text;
Method	scala/xml/factory/Binder.text:(ILjava/lang/String;)Lscala/xml/Text;
Asciz	entityName;
NameAndType	entityName:()Ljava/lang/String;
Method	scala/xml/EntityRef.entityName:()Ljava/lang/String;
NameAndType	entityRef:(ILjava/lang/String;)Lscala/xml/EntityRef;
Method	scala/xml/factory/Binder.entityRef:(ILjava/lang/String;)Lscala/xml/EntityRef;
Asciz	scala/xml/Node;
class	scala/xml/Node
Asciz	prefix;
NameAndType	prefix:()Ljava/lang/String;
Method	scala/xml/Node.prefix:()Ljava/lang/String;
Asciz	label;
NameAndType	label:()Ljava/lang/String;
Method	scala/xml/Node.label:()Ljava/lang/String;
Asciz	attributes;
Asciz	()Lscala/xml/MetaData;;
NameAndType	attributes:()Lscala/xml/MetaData;
Method	scala/xml/Node.attributes:()Lscala/xml/MetaData;
Asciz	scope;
Asciz	()Lscala/xml/NamespaceBinding;;
NameAndType	scope:()Lscala/xml/NamespaceBinding;
Method	scala/xml/Node.scope:()Lscala/xml/NamespaceBinding;
Asciz	elemStart;
Asciz	(ILjava/lang/String;Ljava/lang/String;Lscala/xml/MetaData;Lscala/xml/NamespaceBinding;)V;
NameAndType	elemStart:(ILjava/lang/String;Ljava/lang/String;Lscala/xml/MetaData;Lscala/xml/NamespaceBinding;)V
Method	scala/xml/factory/Binder.elemStart:(ILjava/lang/String;Ljava/lang/String;Lscala/xml/MetaData;Lscala/xml/NamespaceBinding;)V
Asciz	()V;
NameAndType	"<init>":()V
Method	scala/xml/NodeBuffer."<init>":()V
NameAndType	result_$eq:(Lscala/xml/NodeBuffer;)V
Method	scala/xml/factory/Binder.result_$eq:(Lscala/xml/NodeBuffer;)V
Asciz	child;
Asciz	()Lscala/collection/Seq;;
NameAndType	child:()Lscala/collection/Seq;
Method	scala/xml/Node.child:()Lscala/collection/Seq;
Asciz	scala/xml/factory/Binder$$anonfun$traverse$1;
class	scala/xml/factory/Binder$$anonfun$traverse$1
Asciz	(Lscala/xml/factory/Binder;)V;
NameAndType	"<init>":(Lscala/xml/factory/Binder;)V
Method	scala/xml/factory/Binder$$anonfun$traverse$1."<init>":(Lscala/xml/factory/Binder;)V
Asciz	scala/collection/IterableLike;
class	scala/collection/IterableLike
Asciz	foreach;
Asciz	(Lscala/Function1;)V;
NameAndType	foreach:(Lscala/Function1;)V
InterfaceMethod	scala/collection/IterableLike.foreach:(Lscala/Function1;)V
Asciz	scala/xml/NodeSeq$;
class	scala/xml/NodeSeq$
Asciz	MODULE$;
Asciz	Lscala/xml/NodeSeq$;;
NameAndType	MODULE$:Lscala/xml/NodeSeq$;
Field	scala/xml/NodeSeq$.MODULE$:Lscala/xml/NodeSeq$;
Asciz	fromSeq;
Asciz	(Lscala/collection/Seq;)Lscala/xml/NodeSeq;;
NameAndType	fromSeq:(Lscala/collection/Seq;)Lscala/xml/NodeSeq;
Method	scala/xml/NodeSeq$.fromSeq:(Lscala/collection/Seq;)Lscala/xml/NodeSeq;
Asciz	elem;
Asciz	(ILjava/lang/String;Ljava/lang/String;Lscala/xml/MetaData;Lscala/xml/NamespaceBinding;Lscala/xml/NodeSeq;)Lscala/xml/NodeSeq;;
NameAndType	elem:(ILjava/lang/String;Ljava/lang/String;Lscala/xml/MetaData;Lscala/xml/NamespaceBinding;Lscala/xml/NodeSeq;)Lscala/xml/NodeSeq;
Method	scala/xml/factory/Binder.elem:(ILjava/lang/String;Ljava/lang/String;Lscala/xml/MetaData;Lscala/xml/NamespaceBinding;Lscala/xml/NodeSeq;)Lscala/xml/NodeSeq;
Asciz	scala/collection/TraversableLike;
class	scala/collection/TraversableLike
Asciz	toList;
Asciz	()Lscala/collection/immutable/List;;
NameAndType	toList:()Lscala/collection/immutable/List;
InterfaceMethod	scala/collection/TraversableLike.toList:()Lscala/collection/immutable/List;
Asciz	elemEnd;
Asciz	(ILjava/lang/String;Ljava/lang/String;)V;
NameAndType	elemEnd:(ILjava/lang/String;Ljava/lang/String;)V
Method	scala/xml/factory/Binder.elemEnd:(ILjava/lang/String;Ljava/lang/String;)V
Asciz	Lscala/xml/Node;;
Asciz	temp1;
Asciz	temp2;
Asciz	Lscala/xml/ProcInstr;;
Asciz	x;
Asciz	old;
Asciz	validate;
Asciz	(Lscala/xml/Node;)Lscala/xml/Node;;
Asciz	rootLabel_$eq;
NameAndType	rootLabel_$eq:(Ljava/lang/String;)V
Method	scala/xml/factory/Binder.rootLabel_$eq:(Ljava/lang/String;)V
NameAndType	traverse:(Lscala/xml/Node;)V
Method	scala/xml/factory/Binder.traverse:(Lscala/xml/Node;)V
Asciz	scala/collection/mutable/ResizableArray;
class	scala/collection/mutable/ResizableArray
Asciz	apply;
Asciz	(I)Ljava/lang/Object;;
NameAndType	apply:(I)Ljava/lang/Object;
InterfaceMethod	scala/collection/mutable/ResizableArray.apply:(I)Ljava/lang/Object;
Asciz	(ILjava/lang/String;)Lscala/xml/NodeSeq;;
Asciz	(ILjava/lang/String;Ljava/lang/String;)Lscala/xml/NodeSeq;;
Asciz	(Z)V;
Asciz	scala/xml/parsing/ValidatingMarkupHandler;
class	scala/xml/parsing/ValidatingMarkupHandler
Method	scala/xml/parsing/ValidatingMarkupHandler."<init>":()V
Asciz	ScalaSig;
Asciz	InnerClasses;
Asciz	$anonfun$traverse$1;
Asciz	scala/ScalaObject;
class	scala/ScalaObject

{
private scala.xml.NodeBuffer result;
  Signature: Lscala/xml/NodeBuffer;

private final boolean preserveWS;
  Signature: Z

public boolean preserveWS();
  Signature: ()Z
  Code:
   Stack=1, Locals=1, Args_size=1
	aload_0
	getfield	Field preserveWS:Z
	ireturn
  Labels:

public scala.xml.NodeBuffer result();
  Signature: ()Lscala/xml/NodeBuffer;
  Code:
   Stack=1, Locals=1, Args_size=1
	aload_0
	getfield	Field result:Lscala/xml/NodeBuffer;
	areturn
  Labels:

public void result_$eq(scala.xml.NodeBuffer);
  Signature: (Lscala/xml/NodeBuffer;)V
  Code:
   Stack=2, Locals=2, Args_size=2
	aload_0
	aload_1
	putfield	Field result:Lscala/xml/NodeBuffer;
	return
  Labels:

public void reportSyntaxError(int, java.lang.String);
  Signature: (ILjava/lang/String;)V
  Code:
   Stack=0, Locals=3, Args_size=3
	return
  Labels:
  LocalVariableTable: 
   Start  Length  Slot  Name   Signature
   0      1      0    this       Lscala/xml/factory/Binder;
   0      1      1    pos       I
   0      1      2    str       Ljava/lang/String;


public final scala.xml.ProcInstr procInstr(int, java.lang.String, java.lang.String);
  Signature: (ILjava/lang/String;Ljava/lang/String;)Lscala/xml/ProcInstr;
  Code:
   Stack=4, Locals=4, Args_size=4
	new	class scala/xml/ProcInstr
	dup
	aload_2
	aload_3
	invokespecial	Method scala/xml/ProcInstr."<init>":(Ljava/lang/String;Ljava/lang/String;)V
	areturn
  Labels:
  LocalVariableTable: 
   Start  Length  Slot  Name   Signature
   0      10      0    this       Lscala/xml/factory/Binder;
   0      10      1    pos       I
   0      10      2    target       Ljava/lang/String;
   0      10      3    txt       Ljava/lang/String;


public final scala.xml.Comment comment(int, java.lang.String);
  Signature: (ILjava/lang/String;)Lscala/xml/Comment;
  Code:
   Stack=3, Locals=3, Args_size=3
	new	class scala/xml/Comment
	dup
	aload_2
	invokespecial	Method scala/xml/Comment."<init>":(Ljava/lang/String;)V
	areturn
  Labels:
  LocalVariableTable: 
   Start  Length  Slot  Name   Signature
   0      9      0    this       Lscala/xml/factory/Binder;
   0      9      1    pos       I
   0      9      2    txt       Ljava/lang/String;


public final scala.xml.EntityRef entityRef(int, java.lang.String);
  Signature: (ILjava/lang/String;)Lscala/xml/EntityRef;
  Code:
   Stack=3, Locals=3, Args_size=3
	new	class scala/xml/EntityRef
	dup
	aload_2
	invokespecial	Method scala/xml/EntityRef."<init>":(Ljava/lang/String;)V
	areturn
  Labels:
  LocalVariableTable: 
   Start  Length  Slot  Name   Signature
   0      9      0    this       Lscala/xml/factory/Binder;
   0      9      1    pos       I
   0      9      2    n       Ljava/lang/String;


public final scala.xml.Text text(int, java.lang.String);
  Signature: (ILjava/lang/String;)Lscala/xml/Text;
  Code:
   Stack=3, Locals=3, Args_size=3
	new	class scala/xml/Text
	dup
	aload_2
	invokespecial	Method scala/xml/Text."<init>":(Ljava/lang/String;)V
	areturn
  Labels:
  LocalVariableTable: 
   Start  Length  Slot  Name   Signature
   0      9      0    this       Lscala/xml/factory/Binder;
   0      9      1    pos       I
   0      9      2    txt       Ljava/lang/String;


public final void traverse(scala.xml.Node);
  Signature: (Lscala/xml/Node;)V
  Code:
   Stack=10, Locals=6, Args_size=2
	aload_1
	astore_2
	aload_2
	instanceof	class scala/xml/ProcInstr
	ifeq	l1 // aload_2
	aload_2
	checkcast	class scala/xml/ProcInstr
	astore_3
	aload_3
	astore	4
	aload_0
	invokevirtual	Method result:()Lscala/xml/NodeBuffer;
	aload_0
	iconst_0
	aload	4
	invokevirtual	Method scala/xml/ProcInstr.target:()Ljava/lang/String;
	aload	4
	invokevirtual	Method scala/xml/ProcInstr.text:()Ljava/lang/String;
	invokevirtual	Method procInstr:(ILjava/lang/String;Ljava/lang/String;)Lscala/xml/ProcInstr;
	invokevirtual	Method scala/xml/NodeBuffer.$amp$plus:(Ljava/lang/Object;)Lscala/xml/NodeBuffer;
	pop
	goto	l2 // return
l1	aload_2
	instanceof	class scala/xml/Comment
	ifeq	l3 // aload_2
	aload_0
	invokevirtual	Method result:()Lscala/xml/NodeBuffer;
	aload_0
	iconst_0
	aload_2
	checkcast	class scala/xml/Comment
	invokevirtual	Method scala/xml/Comment.text:()Ljava/lang/String;
	invokevirtual	Method comment:(ILjava/lang/String;)Lscala/xml/Comment;
	invokevirtual	Method scala/xml/NodeBuffer.$amp$plus:(Ljava/lang/Object;)Lscala/xml/NodeBuffer;
	pop
	goto	l2 // return
l3	aload_2
	instanceof	class scala/xml/Text
	ifeq	l4 // aload_2
	aload_0
	invokevirtual	Method result:()Lscala/xml/NodeBuffer;
	aload_0
	iconst_0
	aload_2
	checkcast	class scala/xml/Text
	invokevirtual	Method scala/xml/Text.data:()Ljava/lang/Object;
	checkcast	class java/lang/String
	invokevirtual	Method text:(ILjava/lang/String;)Lscala/xml/Text;
	invokevirtual	Method scala/xml/NodeBuffer.$amp$plus:(Ljava/lang/Object;)Lscala/xml/NodeBuffer;
	pop
	goto	l2 // return
l4	aload_2
	instanceof	class scala/xml/EntityRef
	ifeq	l5 // aload_0
	aload_0
	invokevirtual	Method result:()Lscala/xml/NodeBuffer;
	aload_0
	iconst_0
	aload_2
	checkcast	class scala/xml/EntityRef
	invokevirtual	Method scala/xml/EntityRef.entityName:()Ljava/lang/String;
	invokevirtual	Method entityRef:(ILjava/lang/String;)Lscala/xml/EntityRef;
	invokevirtual	Method scala/xml/NodeBuffer.$amp$plus:(Ljava/lang/Object;)Lscala/xml/NodeBuffer;
	pop
	goto	l2 // return
l5	aload_0
	iconst_0
	aload_1
	invokevirtual	Method scala/xml/Node.prefix:()Ljava/lang/String;
	aload_1
	invokevirtual	Method scala/xml/Node.label:()Ljava/lang/String;
	aload_1
	invokevirtual	Method scala/xml/Node.attributes:()Lscala/xml/MetaData;
	aload_1
	invokevirtual	Method scala/xml/Node.scope:()Lscala/xml/NamespaceBinding;
	invokevirtual	Method elemStart:(ILjava/lang/String;Ljava/lang/String;Lscala/xml/MetaData;Lscala/xml/NamespaceBinding;)V
	aload_0
	invokevirtual	Method result:()Lscala/xml/NodeBuffer;
	astore	5
	aload_0
	new	class scala/xml/NodeBuffer
	dup
	invokespecial	Method scala/xml/NodeBuffer."<init>":()V
	invokevirtual	Method result_$eq:(Lscala/xml/NodeBuffer;)V
	aload_1
	invokevirtual	Method scala/xml/Node.child:()Lscala/collection/Seq;
	new	class scala/xml/factory/Binder$$anonfun$traverse$1
	dup
	aload_0
	invokespecial	Method scala/xml/factory/Binder$$anonfun$traverse$1."<init>":(Lscala/xml/factory/Binder;)V
	invokeinterface	InterfaceMethod scala/collection/IterableLike.foreach:(Lscala/Function1;)V
	aload_0
	aload	5
	aload_0
	iconst_0
	aload_1
	invokevirtual	Method scala/xml/Node.prefix:()Ljava/lang/String;
	aload_1
	invokevirtual	Method scala/xml/Node.label:()Ljava/lang/String;
	aload_1
	invokevirtual	Method scala/xml/Node.attributes:()Lscala/xml/MetaData;
	aload_1
	invokevirtual	Method scala/xml/Node.scope:()Lscala/xml/NamespaceBinding;
	getstatic	Field scala/xml/NodeSeq$.MODULE$:Lscala/xml/NodeSeq$;
	aload_0
	invokevirtual	Method result:()Lscala/xml/NodeBuffer;
	invokevirtual	Method scala/xml/NodeSeq$.fromSeq:(Lscala/collection/Seq;)Lscala/xml/NodeSeq;
	invokevirtual	Method elem:(ILjava/lang/String;Ljava/lang/String;Lscala/xml/MetaData;Lscala/xml/NamespaceBinding;Lscala/xml/NodeSeq;)Lscala/xml/NodeSeq;
	invokeinterface	InterfaceMethod scala/collection/TraversableLike.toList:()Lscala/collection/immutable/List;
	invokevirtual	Method scala/xml/NodeBuffer.$amp$plus:(Ljava/lang/Object;)Lscala/xml/NodeBuffer;
	invokevirtual	Method result_$eq:(Lscala/xml/NodeBuffer;)V
	aload_0
	iconst_0
	aload_1
	invokevirtual	Method scala/xml/Node.prefix:()Ljava/lang/String;
	aload_1
	invokevirtual	Method scala/xml/Node.label:()Ljava/lang/String;
	invokevirtual	Method elemEnd:(ILjava/lang/String;Ljava/lang/String;)V
l2	return
  Labels:
   	l1 = 43 // aload_2
   	l3 = 73 // aload_2
   	l4 = 106 // aload_2
   	l5 = 136 // aload_0
   	l2 = 249 // return
  LocalVariableTable: 
   Start  Length  Slot  Name   Signature
   0      250      0    this       Lscala/xml/factory/Binder;
   0      250      1    n       Lscala/xml/Node;
   2      248      2    temp1       Lscala/xml/Node;
   14      26      3    temp2       Lscala/xml/ProcInstr;
   17      23      4    x       Lscala/xml/ProcInstr;
   163      86      5    old       Lscala/xml/NodeBuffer;


public final scala.xml.Node validate(scala.xml.Node);
  Signature: (Lscala/xml/Node;)Lscala/xml/Node;
  Code:
   Stack=2, Locals=2, Args_size=2
	aload_0
	aload_1
	invokevirtual	Method scala/xml/Node.label:()Ljava/lang/String;
	invokevirtual	Method rootLabel_$eq:(Ljava/lang/String;)V
	aload_0
	aload_1
	invokevirtual	Method traverse:(Lscala/xml/Node;)V
	aload_0
	invokevirtual	Method result:()Lscala/xml/NodeBuffer;
	iconst_0
	invokeinterface	InterfaceMethod scala/collection/mutable/ResizableArray.apply:(I)Ljava/lang/Object;
	checkcast	class scala/xml/Node
	areturn
  Labels:
  LocalVariableTable: 
   Start  Length  Slot  Name   Signature
   0      27      0    this       Lscala/xml/factory/Binder;
   0      27      1    n       Lscala/xml/Node;


public final scala.xml.NodeSeq text(int, java.lang.String);
  Signature: (ILjava/lang/String;)Lscala/xml/NodeSeq;
  Code:
   Stack=3, Locals=3, Args_size=3
	aload_0
	iload_1
	aload_2
	invokevirtual	Method text:(ILjava/lang/String;)Lscala/xml/Text;
	areturn
  Labels:
  LocalVariableTable: 
   Start  Length  Slot  Name   Signature
   0      7      0    this       Lscala/xml/factory/Binder;
   0      7      1    pos       I
   0      7      2    txt       Ljava/lang/String;


public final scala.xml.NodeSeq entityRef(int, java.lang.String);
  Signature: (ILjava/lang/String;)Lscala/xml/NodeSeq;
  Code:
   Stack=3, Locals=3, Args_size=3
	aload_0
	iload_1
	aload_2
	invokevirtual	Method entityRef:(ILjava/lang/String;)Lscala/xml/EntityRef;
	areturn
  Labels:
  LocalVariableTable: 
   Start  Length  Slot  Name   Signature
   0      7      0    this       Lscala/xml/factory/Binder;
   0      7      1    pos       I
   0      7      2    n       Ljava/lang/String;


public final scala.xml.NodeSeq comment(int, java.lang.String);
  Signature: (ILjava/lang/String;)Lscala/xml/NodeSeq;
  Code:
   Stack=3, Locals=3, Args_size=3
	aload_0
	iload_1
	aload_2
	invokevirtual	Method comment:(ILjava/lang/String;)Lscala/xml/Comment;
	areturn
  Labels:
  LocalVariableTable: 
   Start  Length  Slot  Name   Signature
   0      7      0    this       Lscala/xml/factory/Binder;
   0      7      1    pos       I
   0      7      2    comment       Ljava/lang/String;


public final scala.xml.NodeSeq procInstr(int, java.lang.String, java.lang.String);
  Signature: (ILjava/lang/String;Ljava/lang/String;)Lscala/xml/NodeSeq;
  Code:
   Stack=4, Locals=4, Args_size=4
	aload_0
	iload_1
	aload_2
	aload_3
	invokevirtual	Method procInstr:(ILjava/lang/String;Ljava/lang/String;)Lscala/xml/ProcInstr;
	areturn
  Labels:
  LocalVariableTable: 
   Start  Length  Slot  Name   Signature
   0      8      0    this       Lscala/xml/factory/Binder;
   0      8      1    pos       I
   0      8      2    target       Ljava/lang/String;
   0      8      3    txt       Ljava/lang/String;


public scala.xml.factory.Binder(boolean);
  Signature: (Z)V
  Code:
   Stack=3, Locals=2, Args_size=2
	aload_0
	iload_1
	putfield	Field preserveWS:Z
	aload_0
	invokespecial	Method scala/xml/parsing/ValidatingMarkupHandler."<init>":()V
	aload_0
	new	class scala/xml/NodeBuffer
	dup
	invokespecial	Method scala/xml/NodeBuffer."<init>":()V
	putfield	Field result:Lscala/xml/NodeBuffer;
	return
  Labels:
  LocalVariableTable: 
   Start  Length  Slot  Name   Signature
   0      21      0    this       Lscala/xml/factory/Binder;
   0      21      1    preserveWS       Z


}

