Compiled from "LoggedNodeFactory.scala"
public abstract class scala.xml.factory.LoggedNodeFactory extends java.lang.Object implements scala.xml.factory.NodeFactory,scala.util.logging.Logged,scala.ScalaObject
  SourceFile: "LoggedNodeFactory.scala"
  Signature: length = 0x2
   00 FFFFFFD0 
  ScalaSig: length = 0x448
   05 00 FFFFFF81 24 06 05 01 02 FFFFFF81 00 09 02 11 4C 6F 67
   67 65 64 4E 6F 64 65 46 61 63 74 6F 72 79 0A 02
   03 04 01 07 66 61 63 74 6F 72 79 0A 02 05 06 01
   03 78 6D 6C 0A 01 07 01 05 73 63 61 6C 61 03 00
   15 02 0A 19 13 05 00 0B 13 24 2C 10 02 0C 11 0D
   01 0D 0A 02 0E 0F 01 04 6C 61 6E 67 0A 01 10 01
   04 6A 61 76 61 09 02 12 0D 02 06 4F 62 6A 65 63
   74 10 03 14 15 17 0D 01 02 09 02 16 02 02 0B 4E
   6F 64 65 46 61 63 74 6F 72 79 10 02 18 19 0C 00
   04 08 1A 00 FFFFFF84 FFFFFF80 FFFFFF80 FFFFFFC2 00 1B 02 01 41 11 02 1C
   20 10 02 1D 1E 0D 01 06 09 02 1F 06 02 07 4E 6F
   74 68 69 6E 67 10 02 21 22 0D 01 04 09 02 23 04
   02 04 4E 6F 64 65 10 02 25 2A 0D 01 26 0A 02 27
   28 01 07 6C 6F 67 67 69 6E 67 0A 02 29 06 01 04
   75 74 69 6C 09 02 2B 26 02 06 4C 6F 67 67 65 64
   10 02 1D 2D 09 02 2E 06 02 0B 53 63 61 6C 61 4F
   62 6A 65 63 74 08 05 30 00 FFFFFF84 00 31 01 06 3C 69
   6E 69 74 3E 14 01 32 10 03 14 00 17 08 07 34 00
   FFFFFFC2 FFFFFF80 FFFFFF84 00 35 01 07 6C 6F 67 4E 6F 64 65 15 01
   36 10 02 1D 37 09 02 38 06 02 07 42 6F 6F 6C 65
   61 6E 08 06 3A 00 FFFFFFA0 FFFFFF80 04 36 01 08 6C 6F 67 4E
   6F 64 65 20 08 07 3C 00 FFFFFFC2 FFFFFF80 FFFFFF84 00 35 01 07 6C
   6F 67 54 65 78 74 08 06 3E 00 FFFFFFA0 FFFFFF80 04 36 01 08
   6C 6F 67 54 65 78 74 20 08 07 40 00 FFFFFFC2 FFFFFF80 FFFFFF84 00
   35 01 0A 6C 6F 67 43 6F 6D 6D 65 6E 74 08 06 42
   00 FFFFFFA0 FFFFFF80 04 36 01 0B 6C 6F 67 43 6F 6D 6D 65 6E
   74 20 08 07 44 00 FFFFFFC2 FFFFFF80 FFFFFF84 00 35 01 0C 6C 6F 67
   50 72 6F 63 49 6E 73 74 72 08 06 46 00 FFFFFFA0 FFFFFF80 04
   36 01 0D 6C 6F 67 50 72 6F 63 49 6E 73 74 72 20
   08 07 48 00 FFFFFFC2 FFFFFF80 FFFFFF84 02 49 01 04 4E 4F 4E 45 15
   01 4A 0F 01 4B 1D 01 00 08 06 4D 00 FFFFFFA0 FFFFFF80 06 4A
   01 05 4E 4F 4E 45 20 08 07 4F 00 FFFFFFC2 FFFFFF80 FFFFFF84 02 50
   01 05 43 41 43 48 45 15 01 51 0F 01 52 1D 01 01
   08 06 54 00 FFFFFFA0 FFFFFF80 06 51 01 06 43 41 43 48 45 20
   08 07 56 00 FFFFFFC2 FFFFFF80 FFFFFF84 02 57 01 04 46 55 4C 4C 15
   01 58 0F 01 59 1D 01 02 08 06 5B 00 FFFFFFA0 FFFFFF80 06 58
   01 05 46 55 4C 4C 20 08 07 5D 00 FFFFFFC2 FFFFFF80 FFFFFF84 00 5E
   01 10 6C 6F 67 43 6F 6D 70 72 65 73 73 4C 65 76
   65 6C 15 01 5F 10 02 1D 60 09 02 61 06 02 03 49
   6E 74 08 06 63 00 FFFFFFA0 FFFFFF80 04 5F 01 11 6C 6F 67 43
   6F 6D 70 72 65 73 73 4C 65 76 65 6C 20 08 05 65
   00 FFFFFF84 20 66 01 08 6D 61 6B 65 4E 6F 64 65 14 06
   17 67 70 72 77 7C 08 05 68 64 FFFFFFC0 00 69 01 03 70
   72 65 10 02 6A 6D 0E 02 1D 6B 09 02 6C 06 01 06
   50 72 65 64 65 66 09 02 6E 6F 02 06 53 74 72 69
   6E 67 0A 02 6C 06 08 05 71 64 FFFFFFC0 00 69 01 05 6C
   61 62 65 6C 08 05 73 64 FFFFFFC0 00 74 01 07 61 74 74
   72 53 65 71 10 02 21 75 09 02 76 04 02 08 4D 65
   74 61 44 61 74 61 08 05 78 64 FFFFFFC0 00 79 01 05 73
   63 6F 70 65 10 02 21 7A 09 02 7B 04 02 10 4E 61
   6D 65 73 70 61 63 65 42 69 6E 64 69 6E 67 08 05
   7D 64 FFFFFFC0 00 7E 01 08 63 68 69 6C 64 72 65 6E 10
   04 7F FFFFFF81 07 20 0E 04 FFFFFF81 00 FFFFFF81 05 0E 04 FFFFFF81 01 FFFFFF81
   04 0D 02 FFFFFF81 02 0A 03 FFFFFF81 03 08 01 06 3C 72 6F 6F
   74 3E 09 01 07 09 03 FFFFFF81 06 06 01 07 70 61 63 6B
   61 67 65 09 04 FFFFFF81 08 FFFFFF81 09 02 03 53 65 71 0A 03
   FFFFFF81 06 06 08 07 FFFFFF81 0B 00 FFFFFF84 20 FFFFFF81 0C 01 08 6D 61
   6B 65 54 65 78 74 14 04 FFFFFF81 0D FFFFFF81 10 10 03 21 FFFFFF81
   0E 09 03 FFFFFF81 0F 04 02 04 54 65 78 74 08 07 FFFFFF81 11
   FFFFFF81 0A FFFFFFC0 00 69 01 01 73 08 07 FFFFFF81 13 00 FFFFFF84 20 FFFFFF81
   14 01 0B 6D 61 6B 65 43 6F 6D 6D 65 6E 74 14 04
   FFFFFF81 15 FFFFFF81 19 10 05 7F FFFFFF81 07 FFFFFF81 16 10 03 21 FFFFFF81 17
   09 03 FFFFFF81 18 04 02 07 43 6F 6D 6D 65 6E 74 08 07
   FFFFFF81 11 FFFFFF81 12 FFFFFFC0 00 69 08 07 FFFFFF81 1B 00 FFFFFF84 20 FFFFFF81 1C
   01 0D 6D 61 6B 65 50 72 6F 63 49 6E 73 74 72 14
   06 FFFFFF81 1D FFFFFF81 21 FFFFFF81 23 10 05 7F FFFFFF81 07 FFFFFF81 1E 10 03
   21 FFFFFF81 1F 09 03 FFFFFF81 20 04 02 09 50 72 6F 63 49 6E
   73 74 72 08 07 FFFFFF81 22 FFFFFF81 1A FFFFFFC0 00 69 01 01 74 08
   07 FFFFFF81 11 FFFFFF81 1A FFFFFFC0 00 69 
  minor version: 0
  major version: 49
  Constant pool:
Asciz	SourceFile;
Asciz	LoggedNodeFactory.scala;
Asciz	cache;
Asciz	Lscala/collection/mutable/HashMap;;
Asciz	ignoreProcInstr;
Asciz	Z;
Asciz	ignoreComments;
Asciz	logCompressLevel;
Asciz	I;
Asciz	FULL;
Asciz	CACHE;
Asciz	NONE;
Asciz	logProcInstr;
Asciz	logComment;
Asciz	logText;
Asciz	logNode;
Asciz	log;
Asciz	(Ljava/lang/String;)V;
Asciz	Code;
Asciz	LineNumberTable;
Asciz	scala/util/logging/Logged$class;
class	scala/util/logging/Logged$class
Asciz	(Lscala/util/logging/Logged;Ljava/lang/String;)V;
NameAndType	log:(Lscala/util/logging/Logged;Ljava/lang/String;)V
Method	scala/util/logging/Logged$class.log:(Lscala/util/logging/Logged;Ljava/lang/String;)V
Asciz	this;
Asciz	Lscala/xml/factory/LoggedNodeFactory;;
Asciz	msg;
Asciz	Ljava/lang/String;;
Asciz	LocalVariableTable;
Asciz	()Z;
Asciz	scala/xml/factory/LoggedNodeFactory;
class	scala/xml/factory/LoggedNodeFactory
NameAndType	ignoreComments:Z
Field	scala/xml/factory/LoggedNodeFactory.ignoreComments:Z
NameAndType	ignoreProcInstr:Z
Field	scala/xml/factory/LoggedNodeFactory.ignoreProcInstr:Z
Asciz	()Lscala/collection/mutable/HashMap;;
NameAndType	cache:Lscala/collection/mutable/HashMap;
Field	scala/xml/factory/LoggedNodeFactory.cache:Lscala/collection/mutable/HashMap;
Asciz	scala$xml$factory$NodeFactory$_setter_$ignoreComments_$eq;
Asciz	(Z)V;
Asciz	scala$xml$factory$NodeFactory$_setter_$ignoreProcInstr_$eq;
Asciz	scala$xml$factory$NodeFactory$_setter_$cache_$eq;
Asciz	(Lscala/collection/mutable/HashMap;)V;
Asciz	construct;
Asciz	(ILscala/collection/immutable/List;Ljava/lang/String;Ljava/lang/String;Lscala/xml/MetaData;Lscala/xml/NamespaceBinding;Lscala/collection/Seq;)Lscala/xml/Node;;
Asciz	scala/xml/factory/NodeFactory$class;
class	scala/xml/factory/NodeFactory$class
Asciz	(Lscala/xml/factory/NodeFactory;ILscala/collection/immutable/List;Ljava/lang/String;Ljava/lang/String;Lscala/xml/MetaData;Lscala/xml/NamespaceBinding;Lscala/collection/Seq;)Lscala/xml/Node;;
NameAndType	construct:(Lscala/xml/factory/NodeFactory;ILscala/collection/immutable/List;Ljava/lang/String;Ljava/lang/String;Lscala/xml/MetaData;Lscala/xml/NamespaceBinding;Lscala/collection/Seq;)Lscala/xml/Node;
Method	scala/xml/factory/NodeFactory$class.construct:(Lscala/xml/factory/NodeFactory;ILscala/collection/immutable/List;Ljava/lang/String;Ljava/lang/String;Lscala/xml/MetaData;Lscala/xml/NamespaceBinding;Lscala/collection/Seq;)Lscala/xml/Node;
Asciz	hash;
Asciz	old;
Asciz	Lscala/collection/immutable/List;;
Asciz	pre;
Asciz	name;
Asciz	attrSeq;
Asciz	Lscala/xml/MetaData;;
Asciz	scope;
Asciz	Lscala/xml/NamespaceBinding;;
Asciz	children;
Asciz	Lscala/collection/Seq;;
Asciz	eqElements;
Asciz	(Lscala/collection/Seq;Lscala/collection/Seq;)Z;
Asciz	(Lscala/xml/factory/NodeFactory;Lscala/collection/Seq;Lscala/collection/Seq;)Z;
NameAndType	eqElements:(Lscala/xml/factory/NodeFactory;Lscala/collection/Seq;Lscala/collection/Seq;)Z
Method	scala/xml/factory/NodeFactory$class.eqElements:(Lscala/xml/factory/NodeFactory;Lscala/collection/Seq;Lscala/collection/Seq;)Z
Asciz	ch1;
Asciz	ch2;
Asciz	nodeEquals;
Asciz	(Lscala/xml/Node;Ljava/lang/String;Ljava/lang/String;Lscala/xml/MetaData;Lscala/xml/NamespaceBinding;Lscala/collection/Seq;)Z;
Asciz	(Lscala/xml/factory/NodeFactory;Lscala/xml/Node;Ljava/lang/String;Ljava/lang/String;Lscala/xml/MetaData;Lscala/xml/NamespaceBinding;Lscala/collection/Seq;)Z;
NameAndType	nodeEquals:(Lscala/xml/factory/NodeFactory;Lscala/xml/Node;Ljava/lang/String;Ljava/lang/String;Lscala/xml/MetaData;Lscala/xml/NamespaceBinding;Lscala/collection/Seq;)Z
Method	scala/xml/factory/NodeFactory$class.nodeEquals:(Lscala/xml/factory/NodeFactory;Lscala/xml/Node;Ljava/lang/String;Ljava/lang/String;Lscala/xml/MetaData;Lscala/xml/NamespaceBinding;Lscala/collection/Seq;)Z
Asciz	n;
Asciz	Lscala/xml/Node;;
NameAndType	logNode:Z
Field	scala/xml/factory/LoggedNodeFactory.logNode:Z
NameAndType	logText:Z
Field	scala/xml/factory/LoggedNodeFactory.logText:Z
NameAndType	logComment:Z
Field	scala/xml/factory/LoggedNodeFactory.logComment:Z
NameAndType	logProcInstr:Z
Field	scala/xml/factory/LoggedNodeFactory.logProcInstr:Z
Asciz	()I;
NameAndType	logCompressLevel:I
Field	scala/xml/factory/LoggedNodeFactory.logCompressLevel:I
Asciz	makeNode;
Asciz	(Ljava/lang/String;Ljava/lang/String;Lscala/xml/MetaData;Lscala/xml/NamespaceBinding;Lscala/collection/Seq;)Lscala/xml/Node;;
NameAndType	logNode:()Z
Method	scala/xml/factory/LoggedNodeFactory.logNode:()Z
Asciz	scala/collection/mutable/StringBuilder;
class	scala/collection/mutable/StringBuilder
Asciz	<init>;
Asciz	()V;
NameAndType	"<init>":()V
Method	scala/collection/mutable/StringBuilder."<init>":()V
Asciz	[makeNode for ;
String	[makeNode for 
Asciz	append;
Asciz	(Ljava/lang/Object;)Lscala/collection/mutable/StringBuilder;;
NameAndType	append:(Ljava/lang/Object;)Lscala/collection/mutable/StringBuilder;
Method	scala/collection/mutable/StringBuilder.append:(Ljava/lang/Object;)Lscala/collection/mutable/StringBuilder;
Asciz	];
String	]
Asciz	toString;
Asciz	()Ljava/lang/String;;
NameAndType	toString:()Ljava/lang/String;
Method	scala/collection/mutable/StringBuilder.toString:()Ljava/lang/String;
Asciz	scala/util/logging/Logged;
class	scala/util/logging/Logged
NameAndType	log:(Ljava/lang/String;)V
InterfaceMethod	scala/util/logging/Logged.log:(Ljava/lang/String;)V
Asciz	scala/xml/Utility$;
class	scala/xml/Utility$
Asciz	MODULE$;
Asciz	Lscala/xml/Utility$;;
NameAndType	MODULE$:Lscala/xml/Utility$;
Field	scala/xml/Utility$.MODULE$:Lscala/xml/Utility$;
Asciz	scala/xml/MetaData;
class	scala/xml/MetaData
Asciz	hashCode;
NameAndType	hashCode:()I
Method	scala/xml/MetaData.hashCode:()I
Asciz	scala/xml/NamespaceBinding;
class	scala/xml/NamespaceBinding
Method	scala/xml/NamespaceBinding.hashCode:()I
Asciz	(Ljava/lang/String;Ljava/lang/String;IILscala/collection/Seq;)I;
NameAndType	hashCode:(Ljava/lang/String;Ljava/lang/String;IILscala/collection/Seq;)I
Method	scala/xml/Utility$.hashCode:(Ljava/lang/String;Ljava/lang/String;IILscala/collection/Seq;)I
Asciz	scala/xml/factory/NodeFactory;
class	scala/xml/factory/NodeFactory
NameAndType	cache:()Lscala/collection/mutable/HashMap;
InterfaceMethod	scala/xml/factory/NodeFactory.cache:()Lscala/collection/mutable/HashMap;
Asciz	scala/runtime/BoxesRunTime;
class	scala/runtime/BoxesRunTime
Asciz	boxToInteger;
Asciz	(I)Ljava/lang/Integer;;
NameAndType	boxToInteger:(I)Ljava/lang/Integer;
Method	scala/runtime/BoxesRunTime.boxToInteger:(I)Ljava/lang/Integer;
Asciz	scala/collection/mutable/HashMap;
class	scala/collection/mutable/HashMap
Asciz	get;
Asciz	(Ljava/lang/Object;)Lscala/Option;;
NameAndType	get:(Ljava/lang/Object;)Lscala/Option;
Method	scala/collection/mutable/HashMap.get:(Ljava/lang/Object;)Lscala/Option;
Asciz	scala/Option;
class	scala/Option
Asciz	isEmpty;
NameAndType	isEmpty:()Z
Method	scala/Option.isEmpty:()Z
NameAndType	logCompressLevel:()I
Method	scala/xml/factory/LoggedNodeFactory.logCompressLevel:()I
Asciz	[cache hit !];
String	[cache hit !]
Asciz	(Lscala/xml/factory/NodeFactory;Ljava/lang/String;Ljava/lang/String;Lscala/xml/MetaData;Lscala/xml/NamespaceBinding;Lscala/collection/Seq;)Lscala/xml/Node;;
NameAndType	makeNode:(Lscala/xml/factory/NodeFactory;Ljava/lang/String;Ljava/lang/String;Lscala/xml/MetaData;Lscala/xml/NamespaceBinding;Lscala/collection/Seq;)Lscala/xml/Node;
Method	scala/xml/factory/NodeFactory$class.makeNode:(Lscala/xml/factory/NodeFactory;Ljava/lang/String;Ljava/lang/String;Lscala/xml/MetaData;Lscala/xml/NamespaceBinding;Lscala/collection/Seq;)Lscala/xml/Node;
Asciz	label;
Asciz	(Ljava/lang/String;Ljava/lang/String;Lscala/xml/MetaData;Lscala/xml/NamespaceBinding;Lscala/collection/Seq<Lscala/xml/Node;>;)TA;;
Asciz	Signature;
Asciz	makeText;
Asciz	(Ljava/lang/String;)Lscala/xml/Text;;
NameAndType	logText:()Z
Method	scala/xml/factory/LoggedNodeFactory.logText:()Z
Asciz	[makeText:\";
String	[makeText:\"
Asciz	\"];
String	\"]
Asciz	(Lscala/xml/factory/NodeFactory;Ljava/lang/String;)Lscala/xml/Text;;
NameAndType	makeText:(Lscala/xml/factory/NodeFactory;Ljava/lang/String;)Lscala/xml/Text;
Method	scala/xml/factory/NodeFactory$class.makeText:(Lscala/xml/factory/NodeFactory;Ljava/lang/String;)Lscala/xml/Text;
Asciz	s;
Asciz	makeComment;
Asciz	(Ljava/lang/String;)Lscala/collection/Seq;;
NameAndType	logComment:()Z
Method	scala/xml/factory/LoggedNodeFactory.logComment:()Z
Asciz	[makeComment:\";
String	[makeComment:\"
Asciz	(Lscala/xml/factory/NodeFactory;Ljava/lang/String;)Lscala/collection/Seq;;
NameAndType	makeComment:(Lscala/xml/factory/NodeFactory;Ljava/lang/String;)Lscala/collection/Seq;
Method	scala/xml/factory/NodeFactory$class.makeComment:(Lscala/xml/factory/NodeFactory;Ljava/lang/String;)Lscala/collection/Seq;
Asciz	(Ljava/lang/String;)Lscala/collection/Seq<Lscala/xml/Comment;>;;
Asciz	makeProcInstr;
Asciz	(Ljava/lang/String;Ljava/lang/String;)Lscala/collection/Seq;;
NameAndType	logProcInstr:()Z
Method	scala/xml/factory/LoggedNodeFactory.logProcInstr:()Z
Asciz	[makeProcInstr:\";
String	[makeProcInstr:\"
Asciz	 ;
String	 
Asciz	(Lscala/xml/factory/NodeFactory;Ljava/lang/String;Ljava/lang/String;)Lscala/collection/Seq;;
NameAndType	makeProcInstr:(Lscala/xml/factory/NodeFactory;Ljava/lang/String;Ljava/lang/String;)Lscala/collection/Seq;
Method	scala/xml/factory/NodeFactory$class.makeProcInstr:(Lscala/xml/factory/NodeFactory;Ljava/lang/String;Ljava/lang/String;)Lscala/collection/Seq;
Asciz	t;
Asciz	(Ljava/lang/String;Ljava/lang/String;)Lscala/collection/Seq<Lscala/xml/ProcInstr;>;;
Asciz	java/lang/Object;
class	java/lang/Object
Method	java/lang/Object."<init>":()V
Asciz	$init$;
Asciz	(Lscala/xml/factory/NodeFactory;)V;
NameAndType	$init$:(Lscala/xml/factory/NodeFactory;)V
Method	scala/xml/factory/NodeFactory$class.$init$:(Lscala/xml/factory/NodeFactory;)V
Asciz	(Lscala/util/logging/Logged;)V;
NameAndType	$init$:(Lscala/util/logging/Logged;)V
Method	scala/util/logging/Logged$class.$init$:(Lscala/util/logging/Logged;)V
Asciz	<A:Lscala/xml/Node;>Ljava/lang/Object;Lscala/xml/factory/NodeFactory<TA;>;Lscala/util/logging/Logged;Lscala/ScalaObject;;
Asciz	ScalaSig;
Asciz	scala/ScalaObject;
class	scala/ScalaObject

{
private final scala.collection.mutable.HashMap cache;
  Signature: Lscala/collection/mutable/HashMap;

private final boolean ignoreProcInstr;
  Signature: Z

private final boolean ignoreComments;
  Signature: Z

private final int logCompressLevel;
  Signature: I

private final int FULL;
  Signature: I

private final int CACHE;
  Signature: I

private final int NONE;
  Signature: I

private final boolean logProcInstr;
  Signature: Z

private final boolean logComment;
  Signature: Z

private final boolean logText;
  Signature: Z

private final boolean logNode;
  Signature: Z

public void log(java.lang.String);
  Signature: (Ljava/lang/String;)V
  Code:
   Stack=2, Locals=2, Args_size=2
	aload_0
	aload_1
	invokestatic	Method scala/util/logging/Logged$class.log:(Lscala/util/logging/Logged;Ljava/lang/String;)V
	return
  Labels:
  LocalVariableTable: 
   Start  Length  Slot  Name   Signature
   0      6      0    this       Lscala/xml/factory/LoggedNodeFactory;
   0      6      1    msg       Ljava/lang/String;


public boolean ignoreComments();
  Signature: ()Z
  Code:
   Stack=1, Locals=1, Args_size=1
	aload_0
	getfield	Field ignoreComments:Z
	ireturn
  Labels:

public boolean ignoreProcInstr();
  Signature: ()Z
  Code:
   Stack=1, Locals=1, Args_size=1
	aload_0
	getfield	Field ignoreProcInstr:Z
	ireturn
  Labels:

public scala.collection.mutable.HashMap cache();
  Signature: ()Lscala/collection/mutable/HashMap;
  Code:
   Stack=1, Locals=1, Args_size=1
	aload_0
	getfield	Field cache:Lscala/collection/mutable/HashMap;
	areturn
  Labels:

public void scala$xml$factory$NodeFactory$_setter_$ignoreComments_$eq(boolean);
  Signature: (Z)V
  Code:
   Stack=2, Locals=2, Args_size=2
	aload_0
	iload_1
	putfield	Field ignoreComments:Z
	return
  Labels:

public void scala$xml$factory$NodeFactory$_setter_$ignoreProcInstr_$eq(boolean);
  Signature: (Z)V
  Code:
   Stack=2, Locals=2, Args_size=2
	aload_0
	iload_1
	putfield	Field ignoreProcInstr:Z
	return
  Labels:

public void scala$xml$factory$NodeFactory$_setter_$cache_$eq(scala.collection.mutable.HashMap);
  Signature: (Lscala/collection/mutable/HashMap;)V
  Code:
   Stack=2, Locals=2, Args_size=2
	aload_0
	aload_1
	putfield	Field cache:Lscala/collection/mutable/HashMap;
	return
  Labels:

public scala.xml.Node construct(int, scala.collection.immutable.List, java.lang.String, java.lang.String, scala.xml.MetaData, scala.xml.NamespaceBinding, scala.collection.Seq);
  Signature: (ILscala/collection/immutable/List;Ljava/lang/String;Ljava/lang/String;Lscala/xml/MetaData;Lscala/xml/NamespaceBinding;Lscala/collection/Seq;)Lscala/xml/Node;
  Code:
   Stack=8, Locals=8, Args_size=8
	aload_0
	iload_1
	aload_2
	aload_3
	aload	4
	aload	5
	aload	6
	aload	7
	invokestatic	Method scala/xml/factory/NodeFactory$class.construct:(Lscala/xml/factory/NodeFactory;ILscala/collection/immutable/List;Ljava/lang/String;Ljava/lang/String;Lscala/xml/MetaData;Lscala/xml/NamespaceBinding;Lscala/collection/Seq;)Lscala/xml/Node;
	areturn
  Labels:
  LocalVariableTable: 
   Start  Length  Slot  Name   Signature
   0      16      0    this       Lscala/xml/factory/LoggedNodeFactory;
   0      16      1    hash       I
   0      16      2    old       Lscala/collection/immutable/List;
   0      16      3    pre       Ljava/lang/String;
   0      16      4    name       Ljava/lang/String;
   0      16      5    attrSeq       Lscala/xml/MetaData;
   0      16      6    scope       Lscala/xml/NamespaceBinding;
   0      16      7    children       Lscala/collection/Seq;


public boolean eqElements(scala.collection.Seq, scala.collection.Seq);
  Signature: (Lscala/collection/Seq;Lscala/collection/Seq;)Z
  Code:
   Stack=3, Locals=3, Args_size=3
	aload_0
	aload_1
	aload_2
	invokestatic	Method scala/xml/factory/NodeFactory$class.eqElements:(Lscala/xml/factory/NodeFactory;Lscala/collection/Seq;Lscala/collection/Seq;)Z
	ireturn
  Labels:
  LocalVariableTable: 
   Start  Length  Slot  Name   Signature
   0      7      0    this       Lscala/xml/factory/LoggedNodeFactory;
   0      7      1    ch1       Lscala/collection/Seq;
   0      7      2    ch2       Lscala/collection/Seq;


public boolean nodeEquals(scala.xml.Node, java.lang.String, java.lang.String, scala.xml.MetaData, scala.xml.NamespaceBinding, scala.collection.Seq);
  Signature: (Lscala/xml/Node;Ljava/lang/String;Ljava/lang/String;Lscala/xml/MetaData;Lscala/xml/NamespaceBinding;Lscala/collection/Seq;)Z
  Code:
   Stack=7, Locals=7, Args_size=7
	aload_0
	aload_1
	aload_2
	aload_3
	aload	4
	aload	5
	aload	6
	invokestatic	Method scala/xml/factory/NodeFactory$class.nodeEquals:(Lscala/xml/factory/NodeFactory;Lscala/xml/Node;Ljava/lang/String;Ljava/lang/String;Lscala/xml/MetaData;Lscala/xml/NamespaceBinding;Lscala/collection/Seq;)Z
	ireturn
  Labels:
  LocalVariableTable: 
   Start  Length  Slot  Name   Signature
   0      14      0    this       Lscala/xml/factory/LoggedNodeFactory;
   0      14      1    n       Lscala/xml/Node;
   0      14      2    pre       Ljava/lang/String;
   0      14      3    name       Ljava/lang/String;
   0      14      4    attrSeq       Lscala/xml/MetaData;
   0      14      5    scope       Lscala/xml/NamespaceBinding;
   0      14      6    children       Lscala/collection/Seq;


public boolean logNode();
  Signature: ()Z
  Code:
   Stack=1, Locals=1, Args_size=1
	aload_0
	getfield	Field logNode:Z
	ireturn
  Labels:

public boolean logText();
  Signature: ()Z
  Code:
   Stack=1, Locals=1, Args_size=1
	aload_0
	getfield	Field logText:Z
	ireturn
  Labels:

public boolean logComment();
  Signature: ()Z
  Code:
   Stack=1, Locals=1, Args_size=1
	aload_0
	getfield	Field logComment:Z
	ireturn
  Labels:

public boolean logProcInstr();
  Signature: ()Z
  Code:
   Stack=1, Locals=1, Args_size=1
	aload_0
	getfield	Field logProcInstr:Z
	ireturn
  Labels:

public final int NONE();
  Signature: ()I
  Code:
   Stack=1, Locals=1, Args_size=1
	iconst_0
	ireturn
  Labels:

public final int CACHE();
  Signature: ()I
  Code:
   Stack=1, Locals=1, Args_size=1
	iconst_1
	ireturn
  Labels:

public final int FULL();
  Signature: ()I
  Code:
   Stack=1, Locals=1, Args_size=1
	iconst_2
	ireturn
  Labels:

public int logCompressLevel();
  Signature: ()I
  Code:
   Stack=1, Locals=1, Args_size=1
	aload_0
	getfield	Field logCompressLevel:I
	ireturn
  Labels:

public scala.xml.Node makeNode(java.lang.String, java.lang.String, scala.xml.MetaData, scala.xml.NamespaceBinding, scala.collection.Seq);
  Signature: (Ljava/lang/String;Ljava/lang/String;Lscala/xml/MetaData;Lscala/xml/NamespaceBinding;Lscala/collection/Seq;)Lscala/xml/Node;
  Code:
   Stack=6, Locals=7, Args_size=6
	aload_0
	invokevirtual	Method logNode:()Z
	ifeq	l1 // getstatic
	aload_0
	new	class scala/collection/mutable/StringBuilder
	dup
	invokespecial	Method scala/collection/mutable/StringBuilder."<init>":()V
	ldc	String [makeNode for 
	invokevirtual	Method scala/collection/mutable/StringBuilder.append:(Ljava/lang/Object;)Lscala/collection/mutable/StringBuilder;
	aload_2
	invokevirtual	Method scala/collection/mutable/StringBuilder.append:(Ljava/lang/Object;)Lscala/collection/mutable/StringBuilder;
	ldc	String ]
	invokevirtual	Method scala/collection/mutable/StringBuilder.append:(Ljava/lang/Object;)Lscala/collection/mutable/StringBuilder;
	invokevirtual	Method scala/collection/mutable/StringBuilder.toString:()Ljava/lang/String;
	invokeinterface	InterfaceMethod scala/util/logging/Logged.log:(Ljava/lang/String;)V
l1	getstatic	Field scala/xml/Utility$.MODULE$:Lscala/xml/Utility$;
	aload_1
	aload_2
	aload_3
	invokevirtual	Method scala/xml/MetaData.hashCode:()I
	aload	4
	invokevirtual	Method scala/xml/NamespaceBinding.hashCode:()I
	aload	5
	invokevirtual	Method scala/xml/Utility$.hashCode:(Ljava/lang/String;Ljava/lang/String;IILscala/collection/Seq;)I
	istore	6
	aload_0
	invokeinterface	InterfaceMethod scala/xml/factory/NodeFactory.cache:()Lscala/collection/mutable/HashMap;
	iload	6
	invokestatic	Method scala/runtime/BoxesRunTime.boxToInteger:(I)Ljava/lang/Integer;
	invokevirtual	Method scala/collection/mutable/HashMap.get:(Ljava/lang/Object;)Lscala/Option;
	invokevirtual	Method scala/Option.isEmpty:()Z
	ifne	l2 // aload_0
	aload_0
	invokevirtual	Method logCompressLevel:()I
	iconst_1
	if_icmplt	l2 // aload_0
	aload_0
	ldc	String [cache hit !]
	invokeinterface	InterfaceMethod scala/util/logging/Logged.log:(Ljava/lang/String;)V
l2	aload_0
	aload_1
	aload_2
	aload_3
	aload	4
	aload	5
	invokestatic	Method scala/xml/factory/NodeFactory$class.makeNode:(Lscala/xml/factory/NodeFactory;Ljava/lang/String;Ljava/lang/String;Lscala/xml/MetaData;Lscala/xml/NamespaceBinding;Lscala/collection/Seq;)Lscala/xml/Node;
	areturn
  Labels:
   	l1 = 37 // getstatic
   	l2 = 94 // aload_0
  LocalVariableTable: 
   Start  Length  Slot  Name   Signature
   0      106      0    this       Lscala/xml/factory/LoggedNodeFactory;
   0      106      1    pre       Ljava/lang/String;
   0      106      2    label       Ljava/lang/String;
   0      106      3    attrSeq       Lscala/xml/MetaData;
   0      106      4    scope       Lscala/xml/NamespaceBinding;
   0      106      5    children       Lscala/collection/Seq;
   58      47      6    hash       I

  Signature: length = 0x2
   00 FFFFFFA1 

public scala.xml.Text makeText(java.lang.String);
  Signature: (Ljava/lang/String;)Lscala/xml/Text;
  Code:
   Stack=3, Locals=2, Args_size=2
	aload_0
	invokevirtual	Method logText:()Z
	ifeq	l1 // aload_0
	aload_0
	new	class scala/collection/mutable/StringBuilder
	dup
	invokespecial	Method scala/collection/mutable/StringBuilder."<init>":()V
	ldc	String [makeText:\"
	invokevirtual	Method scala/collection/mutable/StringBuilder.append:(Ljava/lang/Object;)Lscala/collection/mutable/StringBuilder;
	aload_1
	invokevirtual	Method scala/collection/mutable/StringBuilder.append:(Ljava/lang/Object;)Lscala/collection/mutable/StringBuilder;
	ldc	String \"]
	invokevirtual	Method scala/collection/mutable/StringBuilder.append:(Ljava/lang/Object;)Lscala/collection/mutable/StringBuilder;
	invokevirtual	Method scala/collection/mutable/StringBuilder.toString:()Ljava/lang/String;
	invokeinterface	InterfaceMethod scala/util/logging/Logged.log:(Ljava/lang/String;)V
l1	aload_0
	aload_1
	invokestatic	Method scala/xml/factory/NodeFactory$class.makeText:(Lscala/xml/factory/NodeFactory;Ljava/lang/String;)Lscala/xml/Text;
	areturn
  Labels:
   	l1 = 37 // aload_0
  LocalVariableTable: 
   Start  Length  Slot  Name   Signature
   0      43      0    this       Lscala/xml/factory/LoggedNodeFactory;
   0      43      1    s       Ljava/lang/String;


public scala.collection.Seq makeComment(java.lang.String);
  Signature: (Ljava/lang/String;)Lscala/collection/Seq;
  Code:
   Stack=3, Locals=2, Args_size=2
	aload_0
	invokevirtual	Method logComment:()Z
	ifeq	l1 // aload_0
	aload_0
	new	class scala/collection/mutable/StringBuilder
	dup
	invokespecial	Method scala/collection/mutable/StringBuilder."<init>":()V
	ldc	String [makeComment:\"
	invokevirtual	Method scala/collection/mutable/StringBuilder.append:(Ljava/lang/Object;)Lscala/collection/mutable/StringBuilder;
	aload_1
	invokevirtual	Method scala/collection/mutable/StringBuilder.append:(Ljava/lang/Object;)Lscala/collection/mutable/StringBuilder;
	ldc	String \"]
	invokevirtual	Method scala/collection/mutable/StringBuilder.append:(Ljava/lang/Object;)Lscala/collection/mutable/StringBuilder;
	invokevirtual	Method scala/collection/mutable/StringBuilder.toString:()Ljava/lang/String;
	invokeinterface	InterfaceMethod scala/util/logging/Logged.log:(Ljava/lang/String;)V
l1	aload_0
	aload_1
	invokestatic	Method scala/xml/factory/NodeFactory$class.makeComment:(Lscala/xml/factory/NodeFactory;Ljava/lang/String;)Lscala/collection/Seq;
	areturn
  Labels:
   	l1 = 37 // aload_0
  LocalVariableTable: 
   Start  Length  Slot  Name   Signature
   0      43      0    this       Lscala/xml/factory/LoggedNodeFactory;
   0      43      1    s       Ljava/lang/String;

  Signature: length = 0x2
   00 FFFFFFB8 

public scala.collection.Seq makeProcInstr(java.lang.String, java.lang.String);
  Signature: (Ljava/lang/String;Ljava/lang/String;)Lscala/collection/Seq;
  Code:
   Stack=3, Locals=3, Args_size=3
	aload_0
	invokevirtual	Method logProcInstr:()Z
	ifeq	l1 // aload_0
	aload_0
	new	class scala/collection/mutable/StringBuilder
	dup
	invokespecial	Method scala/collection/mutable/StringBuilder."<init>":()V
	ldc	String [makeProcInstr:\"
	invokevirtual	Method scala/collection/mutable/StringBuilder.append:(Ljava/lang/Object;)Lscala/collection/mutable/StringBuilder;
	aload_1
	invokevirtual	Method scala/collection/mutable/StringBuilder.append:(Ljava/lang/Object;)Lscala/collection/mutable/StringBuilder;
	ldc	String  
	invokevirtual	Method scala/collection/mutable/StringBuilder.append:(Ljava/lang/Object;)Lscala/collection/mutable/StringBuilder;
	aload_2
	invokevirtual	Method scala/collection/mutable/StringBuilder.append:(Ljava/lang/Object;)Lscala/collection/mutable/StringBuilder;
	ldc	String \"]
	invokevirtual	Method scala/collection/mutable/StringBuilder.append:(Ljava/lang/Object;)Lscala/collection/mutable/StringBuilder;
	invokevirtual	Method scala/collection/mutable/StringBuilder.toString:()Ljava/lang/String;
	invokeinterface	InterfaceMethod scala/util/logging/Logged.log:(Ljava/lang/String;)V
l1	aload_0
	aload_1
	aload_2
	invokestatic	Method scala/xml/factory/NodeFactory$class.makeProcInstr:(Lscala/xml/factory/NodeFactory;Ljava/lang/String;Ljava/lang/String;)Lscala/collection/Seq;
	areturn
  Labels:
   	l1 = 46 // aload_0
  LocalVariableTable: 
   Start  Length  Slot  Name   Signature
   0      53      0    this       Lscala/xml/factory/LoggedNodeFactory;
   0      53      1    t       Ljava/lang/String;
   0      53      2    s       Ljava/lang/String;

  Signature: length = 0x2
   00 FFFFFFC5 

public scala.xml.factory.LoggedNodeFactory();
  Signature: ()V
  Code:
   Stack=2, Locals=1, Args_size=1
	aload_0
	invokespecial	Method java/lang/Object."<init>":()V
	aload_0
	invokestatic	Method scala/xml/factory/NodeFactory$class.$init$:(Lscala/xml/factory/NodeFactory;)V
	aload_0
	invokestatic	Method scala/util/logging/Logged$class.$init$:(Lscala/util/logging/Logged;)V
	aload_0
	iconst_1
	putfield	Field logNode:Z
	aload_0
	iconst_0
	putfield	Field logText:Z
	aload_0
	iconst_0
	putfield	Field logComment:Z
	aload_0
	iconst_0
	putfield	Field logProcInstr:Z
	aload_0
	iconst_1
	putfield	Field logCompressLevel:I
	return
  Labels:
  Signature: length = 0x2
   00 60 

}

