Compiled from "LoggedNodeFactory.scala"
public abstract class scala.xml.factory.LoggedNodeFactory extends java.lang.Object implements scala.xml.factory.NodeFactory,scala.util.logging.Logged,scala.ScalaObject
  SourceFile: "LoggedNodeFactory.scala"
  Signature: length = 0x2
   00 FFFFFFD0 
  ScalaSig: length = 0x448
   05 00 FFFFFF81 24 06 05 01 02 FFFFFF81 00 09 02 11 4C 6F 67
   67 65 64 4E 6F 64 65 46 61 63 74 6F 72 79 0A 02
   03 04 01 07 66 61 63 74 6F 72 79 0A 02 05 06 01
   03 78 6D 6C 0A 01 07 01 05 73 63 61 6C 61 03 00
   15 02 0A 19 13 05 00 0B 13 24 2C 10 02 0C 11 0D
   01 0D 0A 02 0E 0F 01 04 6C 61 6E 67 0A 01 10 01
   04 6A 61 76 61 09 02 12 0D 02 06 4F 62 6A 65 63
   74 10 03 14 15 17 0D 01 02 09 02 16 02 02 0B 4E
   6F 64 65 46 61 63 74 6F 72 79 10 02 18 19 0C 00
   04 08 1A 00 FFFFFF84 FFFFFF80 FFFFFF80 FFFFFFC2 00 1B 02 01 41 11 02 1C
   20 10 02 1D 1E 0D 01 06 09 02 1F 06 02 07 4E 6F
   74 68 69 6E 67 10 02 21 22 0D 01 04 09 02 23 04
   02 04 4E 6F 64 65 10 02 25 2A 0D 01 26 0A 02 27
   28 01 07 6C 6F 67 67 69 6E 67 0A 02 29 06 01 04
   75 74 69 6C 09 02 2B 26 02 06 4C 6F 67 67 65 64
   10 02 1D 2D 09 02 2E 06 02 0B 53 63 61 6C 61 4F
   62 6A 65 63 74 08 05 30 00 FFFFFF84 00 31 01 06 3C 69
   6E 69 74 3E 14 01 32 10 03 14 00 17 08 07 34 00
   FFFFFFC2 FFFFFF80 FFFFFF84 00 35 01 07 6C 6F 67 4E 6F 64 65 15 01
   36 10 02 1D 37 09 02 38 06 02 07 42 6F 6F 6C 65
   61 6E 08 06 3A 00 FFFFFFA0 FFFFFF80 04 36 01 08 6C 6F 67 4E
   6F 64 65 20 08 07 3C 00 FFFFFFC2 FFFFFF80 FFFFFF84 00 35 01 07 6C
   6F 67 54 65 78 74 08 06 3E 00 FFFFFFA0 FFFFFF80 04 36 01 08
   6C 6F 67 54 65 78 74 20 08 07 40 00 FFFFFFC2 FFFFFF80 FFFFFF84 00
   35 01 0A 6C 6F 67 43 6F 6D 6D 65 6E 74 08 06 42
   00 FFFFFFA0 FFFFFF80 04 36 01 0B 6C 6F 67 43 6F 6D 6D 65 6E
   74 20 08 07 44 00 FFFFFFC2 FFFFFF80 FFFFFF84 00 35 01 0C 6C 6F 67
   50 72 6F 63 49 6E 73 74 72 08 06 46 00 FFFFFFA0 FFFFFF80 04
   36 01 0D 6C 6F 67 50 72 6F 63 49 6E 73 74 72 20
   08 07 48 00 FFFFFFC2 FFFFFF80 FFFFFF84 02 49 01 04 4E 4F 4E 45 15
   01 4A 0F 01 4B 1D 01 00 08 06 4D 00 FFFFFFA0 FFFFFF80 06 4A
   01 05 4E 4F 4E 45 20 08 07 4F 00 FFFFFFC2 FFFFFF80 FFFFFF84 02 50
   01 05 43 41 43 48 45 15 01 51 0F 01 52 1D 01 01
   08 06 54 00 FFFFFFA0 FFFFFF80 06 51 01 06 43 41 43 48 45 20
   08 07 56 00 FFFFFFC2 FFFFFF80 FFFFFF84 02 57 01 04 46 55 4C 4C 15
   01 58 0F 01 59 1D 01 02 08 06 5B 00 FFFFFFA0 FFFFFF80 06 58
   01 05 46 55 4C 4C 20 08 07 5D 00 FFFFFFC2 FFFFFF80 FFFFFF84 00 5E
   01 10 6C 6F 67 43 6F 6D 70 72 65 73 73 4C 65 76
   65 6C 15 01 5F 10 02 1D 60 09 02 61 06 02 03 49
   6E 74 08 06 63 00 FFFFFFA0 FFFFFF80 04 5F 01 11 6C 6F 67 43
   6F 6D 70 72 65 73 73 4C 65 76 65 6C 20 08 05 65
   00 FFFFFF84 20 66 01 08 6D 61 6B 65 4E 6F 64 65 14 06
   17 67 70 72 77 7C 08 05 68 64 FFFFFFC0 00 69 01 03 70
   72 65 10 02 6A 6D 0E 02 1D 6B 09 02 6C 06 01 06
   50 72 65 64 65 66 09 02 6E 6F 02 06 53 74 72 69
   6E 67 0A 02 6C 06 08 05 71 64 FFFFFFC0 00 69 01 05 6C
   61 62 65 6C 08 05 73 64 FFFFFFC0 00 74 01 07 61 74 74
   72 53 65 71 10 02 21 75 09 02 76 04 02 08 4D 65
   74 61 44 61 74 61 08 05 78 64 FFFFFFC0 00 79 01 05 73
   63 6F 70 65 10 02 21 7A 09 02 7B 04 02 10 4E 61
   6D 65 73 70 61 63 65 42 69 6E 64 69 6E 67 08 05
   7D 64 FFFFFFC0 00 7E 01 08 63 68 69 6C 64 72 65 6E 10
   04 7F FFFFFF81 07 20 0E 04 FFFFFF81 00 FFFFFF81 05 0E 04 FFFFFF81 01 FFFFFF81
   04 0D 02 FFFFFF81 02 0A 03 FFFFFF81 03 08 01 06 3C 72 6F 6F
   74 3E 09 01 07 09 03 FFFFFF81 06 06 01 07 70 61 63 6B
   61 67 65 09 04 FFFFFF81 08 FFFFFF81 09 02 03 53 65 71 0A 03
   FFFFFF81 06 06 08 07 FFFFFF81 0B 00 FFFFFF84 20 FFFFFF81 0C 01 08 6D 61
   6B 65 54 65 78 74 14 04 FFFFFF81 0D FFFFFF81 10 10 03 21 FFFFFF81
   0E 09 03 FFFFFF81 0F 04 02 04 54 65 78 74 08 07 FFFFFF81 11
   FFFFFF81 0A FFFFFFC0 00 69 01 01 73 08 07 FFFFFF81 13 00 FFFFFF84 20 FFFFFF81
   14 01 0B 6D 61 6B 65 43 6F 6D 6D 65 6E 74 14 04
   FFFFFF81 15 FFFFFF81 19 10 05 7F FFFFFF81 07 FFFFFF81 16 10 03 21 FFFFFF81 17
   09 03 FFFFFF81 18 04 02 07 43 6F 6D 6D 65 6E 74 08 07
   FFFFFF81 11 FFFFFF81 12 FFFFFFC0 00 69 08 07 FFFFFF81 1B 00 FFFFFF84 20 FFFFFF81 1C
   01 0D 6D 61 6B 65 50 72 6F 63 49 6E 73 74 72 14
   06 FFFFFF81 1D FFFFFF81 21 FFFFFF81 23 10 05 7F FFFFFF81 07 FFFFFF81 1E 10 03
   21 FFFFFF81 1F 09 03 FFFFFF81 20 04 02 09 50 72 6F 63 49 6E
   73 74 72 08 07 FFFFFF81 22 FFFFFF81 1A FFFFFFC0 00 69 01 01 74 08
   07 FFFFFF81 11 FFFFFF81 1A FFFFFFC0 00 69 
  minor version: 0
  major version: 49
  Constant pool:
const #1 = Asciz	SourceFile;
const #2 = Asciz	LoggedNodeFactory.scala;
const #3 = Asciz	cache;
const #4 = Asciz	Lscala/collection/mutable/HashMap;;
const #5 = Asciz	ignoreProcInstr;
const #6 = Asciz	Z;
const #7 = Asciz	ignoreComments;
const #8 = Asciz	logCompressLevel;
const #9 = Asciz	I;
const #10 = Asciz	FULL;
const #11 = Asciz	CACHE;
const #12 = Asciz	NONE;
const #13 = Asciz	logProcInstr;
const #14 = Asciz	logComment;
const #15 = Asciz	logText;
const #16 = Asciz	logNode;
const #17 = Asciz	<init>;
const #18 = Asciz	()V;
const #19 = Asciz	Code;
const #20 = Asciz	LineNumberTable;
const #21 = Asciz	java/lang/Object;
const #22 = class	#21;	//  java/lang/Object
const #23 = NameAndType	#17:#18;//  "<init>":()V
const #24 = Method	#22.#23;	//  java/lang/Object."<init>":()V
const #25 = Asciz	scala/xml/factory/NodeFactory$class;
const #26 = class	#25;	//  scala/xml/factory/NodeFactory$class
const #27 = Asciz	$init$;
const #28 = Asciz	(Lscala/xml/factory/NodeFactory;)V;
const #29 = NameAndType	#27:#28;//  $init$:(Lscala/xml/factory/NodeFactory;)V
const #30 = Method	#26.#29;	//  scala/xml/factory/NodeFactory$class.$init$:(Lscala/xml/factory/NodeFactory;)V
const #31 = Asciz	scala/util/logging/Logged$class;
const #32 = class	#31;	//  scala/util/logging/Logged$class
const #33 = Asciz	(Lscala/util/logging/Logged;)V;
const #34 = NameAndType	#27:#33;//  $init$:(Lscala/util/logging/Logged;)V
const #35 = Method	#32.#34;	//  scala/util/logging/Logged$class.$init$:(Lscala/util/logging/Logged;)V
const #36 = Asciz	scala/xml/factory/LoggedNodeFactory;
const #37 = class	#36;	//  scala/xml/factory/LoggedNodeFactory
const #38 = NameAndType	#16:#6;//  logNode:Z
const #39 = Field	#37.#38;	//  scala/xml/factory/LoggedNodeFactory.logNode:Z
const #40 = NameAndType	#15:#6;//  logText:Z
const #41 = Field	#37.#40;	//  scala/xml/factory/LoggedNodeFactory.logText:Z
const #42 = NameAndType	#14:#6;//  logComment:Z
const #43 = Field	#37.#42;	//  scala/xml/factory/LoggedNodeFactory.logComment:Z
const #44 = NameAndType	#13:#6;//  logProcInstr:Z
const #45 = Field	#37.#44;	//  scala/xml/factory/LoggedNodeFactory.logProcInstr:Z
const #46 = NameAndType	#8:#9;//  logCompressLevel:I
const #47 = Field	#37.#46;	//  scala/xml/factory/LoggedNodeFactory.logCompressLevel:I
const #48 = Asciz	Signature;
const #49 = Asciz	makeProcInstr;
const #50 = Asciz	(Ljava/lang/String;Ljava/lang/String;)Lscala/collection/Seq;;
const #51 = Asciz	()Z;
const #52 = NameAndType	#13:#51;//  logProcInstr:()Z
const #53 = Method	#37.#52;	//  scala/xml/factory/LoggedNodeFactory.logProcInstr:()Z
const #54 = Asciz	scala/collection/mutable/StringBuilder;
const #55 = class	#54;	//  scala/collection/mutable/StringBuilder
const #56 = Method	#55.#23;	//  scala/collection/mutable/StringBuilder."<init>":()V
const #57 = Asciz	[makeProcInstr:\";
const #58 = String	#57;	//  [makeProcInstr:\"
const #59 = Asciz	append;
const #60 = Asciz	(Ljava/lang/Object;)Lscala/collection/mutable/StringBuilder;;
const #61 = NameAndType	#59:#60;//  append:(Ljava/lang/Object;)Lscala/collection/mutable/StringBuilder;
const #62 = Method	#55.#61;	//  scala/collection/mutable/StringBuilder.append:(Ljava/lang/Object;)Lscala/collection/mutable/StringBuilder;
const #63 = Asciz	 ;
const #64 = String	#63;	//   
const #65 = Asciz	\"];
const #66 = String	#65;	//  \"]
const #67 = Asciz	toString;
const #68 = Asciz	()Ljava/lang/String;;
const #69 = NameAndType	#67:#68;//  toString:()Ljava/lang/String;
const #70 = Method	#55.#69;	//  scala/collection/mutable/StringBuilder.toString:()Ljava/lang/String;
const #71 = Asciz	scala/util/logging/Logged;
const #72 = class	#71;	//  scala/util/logging/Logged
const #73 = Asciz	log;
const #74 = Asciz	(Ljava/lang/String;)V;
const #75 = NameAndType	#73:#74;//  log:(Ljava/lang/String;)V
const #76 = InterfaceMethod	#72.#75;	//  scala/util/logging/Logged.log:(Ljava/lang/String;)V
const #77 = Asciz	(Lscala/xml/factory/NodeFactory;Ljava/lang/String;Ljava/lang/String;)Lscala/collection/Seq;;
const #78 = NameAndType	#49:#77;//  makeProcInstr:(Lscala/xml/factory/NodeFactory;Ljava/lang/String;Ljava/lang/String;)Lscala/collection/Seq;
const #79 = Method	#26.#78;	//  scala/xml/factory/NodeFactory$class.makeProcInstr:(Lscala/xml/factory/NodeFactory;Ljava/lang/String;Ljava/lang/String;)Lscala/collection/Seq;
const #80 = Asciz	this;
const #81 = Asciz	Lscala/xml/factory/LoggedNodeFactory;;
const #82 = Asciz	t;
const #83 = Asciz	Ljava/lang/String;;
const #84 = Asciz	s;
const #85 = Asciz	LocalVariableTable;
const #86 = Asciz	(Ljava/lang/String;Ljava/lang/String;)Lscala/collection/Seq<Lscala/xml/ProcInstr;>;;
const #87 = Asciz	makeComment;
const #88 = Asciz	(Ljava/lang/String;)Lscala/collection/Seq;;
const #89 = NameAndType	#14:#51;//  logComment:()Z
const #90 = Method	#37.#89;	//  scala/xml/factory/LoggedNodeFactory.logComment:()Z
const #91 = Asciz	[makeComment:\";
const #92 = String	#91;	//  [makeComment:\"
const #93 = Asciz	(Lscala/xml/factory/NodeFactory;Ljava/lang/String;)Lscala/collection/Seq;;
const #94 = NameAndType	#87:#93;//  makeComment:(Lscala/xml/factory/NodeFactory;Ljava/lang/String;)Lscala/collection/Seq;
const #95 = Method	#26.#94;	//  scala/xml/factory/NodeFactory$class.makeComment:(Lscala/xml/factory/NodeFactory;Ljava/lang/String;)Lscala/collection/Seq;
const #96 = Asciz	(Ljava/lang/String;)Lscala/collection/Seq<Lscala/xml/Comment;>;;
const #97 = Asciz	makeText;
const #98 = Asciz	(Ljava/lang/String;)Lscala/xml/Text;;
const #99 = NameAndType	#15:#51;//  logText:()Z
const #100 = Method	#37.#99;	//  scala/xml/factory/LoggedNodeFactory.logText:()Z
const #101 = Asciz	[makeText:\";
const #102 = String	#101;	//  [makeText:\"
const #103 = Asciz	(Lscala/xml/factory/NodeFactory;Ljava/lang/String;)Lscala/xml/Text;;
const #104 = NameAndType	#97:#103;//  makeText:(Lscala/xml/factory/NodeFactory;Ljava/lang/String;)Lscala/xml/Text;
const #105 = Method	#26.#104;	//  scala/xml/factory/NodeFactory$class.makeText:(Lscala/xml/factory/NodeFactory;Ljava/lang/String;)Lscala/xml/Text;
const #106 = Asciz	makeNode;
const #107 = Asciz	(Ljava/lang/String;Ljava/lang/String;Lscala/xml/MetaData;Lscala/xml/NamespaceBinding;Lscala/collection/Seq;)Lscala/xml/Node;;
const #108 = NameAndType	#16:#51;//  logNode:()Z
const #109 = Method	#37.#108;	//  scala/xml/factory/LoggedNodeFactory.logNode:()Z
const #110 = Asciz	[makeNode for ;
const #111 = String	#110;	//  [makeNode for 
const #112 = Asciz	];
const #113 = String	#112;	//  ]
const #114 = Asciz	scala/xml/Utility$;
const #115 = class	#114;	//  scala/xml/Utility$
const #116 = Asciz	MODULE$;
const #117 = Asciz	Lscala/xml/Utility$;;
const #118 = NameAndType	#116:#117;//  MODULE$:Lscala/xml/Utility$;
const #119 = Field	#115.#118;	//  scala/xml/Utility$.MODULE$:Lscala/xml/Utility$;
const #120 = Asciz	scala/xml/MetaData;
const #121 = class	#120;	//  scala/xml/MetaData
const #122 = Asciz	hashCode;
const #123 = Asciz	()I;
const #124 = NameAndType	#122:#123;//  hashCode:()I
const #125 = Method	#121.#124;	//  scala/xml/MetaData.hashCode:()I
const #126 = Asciz	scala/xml/NamespaceBinding;
const #127 = class	#126;	//  scala/xml/NamespaceBinding
const #128 = Method	#127.#124;	//  scala/xml/NamespaceBinding.hashCode:()I
const #129 = Asciz	(Ljava/lang/String;Ljava/lang/String;IILscala/collection/Seq;)I;
const #130 = NameAndType	#122:#129;//  hashCode:(Ljava/lang/String;Ljava/lang/String;IILscala/collection/Seq;)I
const #131 = Method	#115.#130;	//  scala/xml/Utility$.hashCode:(Ljava/lang/String;Ljava/lang/String;IILscala/collection/Seq;)I
const #132 = Asciz	scala/xml/factory/NodeFactory;
const #133 = class	#132;	//  scala/xml/factory/NodeFactory
const #134 = Asciz	()Lscala/collection/mutable/HashMap;;
const #135 = NameAndType	#3:#134;//  cache:()Lscala/collection/mutable/HashMap;
const #136 = InterfaceMethod	#133.#135;	//  scala/xml/factory/NodeFactory.cache:()Lscala/collection/mutable/HashMap;
const #137 = Asciz	scala/runtime/BoxesRunTime;
const #138 = class	#137;	//  scala/runtime/BoxesRunTime
const #139 = Asciz	boxToInteger;
const #140 = Asciz	(I)Ljava/lang/Integer;;
const #141 = NameAndType	#139:#140;//  boxToInteger:(I)Ljava/lang/Integer;
const #142 = Method	#138.#141;	//  scala/runtime/BoxesRunTime.boxToInteger:(I)Ljava/lang/Integer;
const #143 = Asciz	scala/collection/mutable/HashMap;
const #144 = class	#143;	//  scala/collection/mutable/HashMap
const #145 = Asciz	get;
const #146 = Asciz	(Ljava/lang/Object;)Lscala/Option;;
const #147 = NameAndType	#145:#146;//  get:(Ljava/lang/Object;)Lscala/Option;
const #148 = Method	#144.#147;	//  scala/collection/mutable/HashMap.get:(Ljava/lang/Object;)Lscala/Option;
const #149 = Asciz	scala/Option;
const #150 = class	#149;	//  scala/Option
const #151 = Asciz	isEmpty;
const #152 = NameAndType	#151:#51;//  isEmpty:()Z
const #153 = Method	#150.#152;	//  scala/Option.isEmpty:()Z
const #154 = NameAndType	#8:#123;//  logCompressLevel:()I
const #155 = Method	#37.#154;	//  scala/xml/factory/LoggedNodeFactory.logCompressLevel:()I
const #156 = Asciz	[cache hit !];
const #157 = String	#156;	//  [cache hit !]
const #158 = Asciz	(Lscala/xml/factory/NodeFactory;Ljava/lang/String;Ljava/lang/String;Lscala/xml/MetaData;Lscala/xml/NamespaceBinding;Lscala/collection/Seq;)Lscala/xml/Node;;
const #159 = NameAndType	#106:#158;//  makeNode:(Lscala/xml/factory/NodeFactory;Ljava/lang/String;Ljava/lang/String;Lscala/xml/MetaData;Lscala/xml/NamespaceBinding;Lscala/collection/Seq;)Lscala/xml/Node;
const #160 = Method	#26.#159;	//  scala/xml/factory/NodeFactory$class.makeNode:(Lscala/xml/factory/NodeFactory;Ljava/lang/String;Ljava/lang/String;Lscala/xml/MetaData;Lscala/xml/NamespaceBinding;Lscala/collection/Seq;)Lscala/xml/Node;
const #161 = Asciz	pre;
const #162 = Asciz	label;
const #163 = Asciz	attrSeq;
const #164 = Asciz	Lscala/xml/MetaData;;
const #165 = Asciz	scope;
const #166 = Asciz	Lscala/xml/NamespaceBinding;;
const #167 = Asciz	children;
const #168 = Asciz	Lscala/collection/Seq;;
const #169 = Asciz	hash;
const #170 = Asciz	(Ljava/lang/String;Ljava/lang/String;Lscala/xml/MetaData;Lscala/xml/NamespaceBinding;Lscala/collection/Seq<Lscala/xml/Node;>;)TA;;
const #171 = Asciz	nodeEquals;
const #172 = Asciz	(Lscala/xml/Node;Ljava/lang/String;Ljava/lang/String;Lscala/xml/MetaData;Lscala/xml/NamespaceBinding;Lscala/collection/Seq;)Z;
const #173 = Asciz	(Lscala/xml/factory/NodeFactory;Lscala/xml/Node;Ljava/lang/String;Ljava/lang/String;Lscala/xml/MetaData;Lscala/xml/NamespaceBinding;Lscala/collection/Seq;)Z;
const #174 = NameAndType	#171:#173;//  nodeEquals:(Lscala/xml/factory/NodeFactory;Lscala/xml/Node;Ljava/lang/String;Ljava/lang/String;Lscala/xml/MetaData;Lscala/xml/NamespaceBinding;Lscala/collection/Seq;)Z
const #175 = Method	#26.#174;	//  scala/xml/factory/NodeFactory$class.nodeEquals:(Lscala/xml/factory/NodeFactory;Lscala/xml/Node;Ljava/lang/String;Ljava/lang/String;Lscala/xml/MetaData;Lscala/xml/NamespaceBinding;Lscala/collection/Seq;)Z
const #176 = Asciz	n;
const #177 = Asciz	Lscala/xml/Node;;
const #178 = Asciz	name;
const #179 = Asciz	eqElements;
const #180 = Asciz	(Lscala/collection/Seq;Lscala/collection/Seq;)Z;
const #181 = Asciz	(Lscala/xml/factory/NodeFactory;Lscala/collection/Seq;Lscala/collection/Seq;)Z;
const #182 = NameAndType	#179:#181;//  eqElements:(Lscala/xml/factory/NodeFactory;Lscala/collection/Seq;Lscala/collection/Seq;)Z
const #183 = Method	#26.#182;	//  scala/xml/factory/NodeFactory$class.eqElements:(Lscala/xml/factory/NodeFactory;Lscala/collection/Seq;Lscala/collection/Seq;)Z
const #184 = Asciz	ch1;
const #185 = Asciz	ch2;
const #186 = Asciz	construct;
const #187 = Asciz	(ILscala/collection/immutable/List;Ljava/lang/String;Ljava/lang/String;Lscala/xml/MetaData;Lscala/xml/NamespaceBinding;Lscala/collection/Seq;)Lscala/xml/Node;;
const #188 = Asciz	(Lscala/xml/factory/NodeFactory;ILscala/collection/immutable/List;Ljava/lang/String;Ljava/lang/String;Lscala/xml/MetaData;Lscala/xml/NamespaceBinding;Lscala/collection/Seq;)Lscala/xml/Node;;
const #189 = NameAndType	#186:#188;//  construct:(Lscala/xml/factory/NodeFactory;ILscala/collection/immutable/List;Ljava/lang/String;Ljava/lang/String;Lscala/xml/MetaData;Lscala/xml/NamespaceBinding;Lscala/collection/Seq;)Lscala/xml/Node;
const #190 = Method	#26.#189;	//  scala/xml/factory/NodeFactory$class.construct:(Lscala/xml/factory/NodeFactory;ILscala/collection/immutable/List;Ljava/lang/String;Ljava/lang/String;Lscala/xml/MetaData;Lscala/xml/NamespaceBinding;Lscala/collection/Seq;)Lscala/xml/Node;
const #191 = Asciz	old;
const #192 = Asciz	Lscala/collection/immutable/List;;
const #193 = Asciz	scala$xml$factory$NodeFactory$_setter_$cache_$eq;
const #194 = Asciz	(Lscala/collection/mutable/HashMap;)V;
const #195 = NameAndType	#3:#4;//  cache:Lscala/collection/mutable/HashMap;
const #196 = Field	#37.#195;	//  scala/xml/factory/LoggedNodeFactory.cache:Lscala/collection/mutable/HashMap;
const #197 = Asciz	scala$xml$factory$NodeFactory$_setter_$ignoreProcInstr_$eq;
const #198 = Asciz	(Z)V;
const #199 = NameAndType	#5:#6;//  ignoreProcInstr:Z
const #200 = Field	#37.#199;	//  scala/xml/factory/LoggedNodeFactory.ignoreProcInstr:Z
const #201 = Asciz	scala$xml$factory$NodeFactory$_setter_$ignoreComments_$eq;
const #202 = NameAndType	#7:#6;//  ignoreComments:Z
const #203 = Field	#37.#202;	//  scala/xml/factory/LoggedNodeFactory.ignoreComments:Z
const #204 = Asciz	(Lscala/util/logging/Logged;Ljava/lang/String;)V;
const #205 = NameAndType	#73:#204;//  log:(Lscala/util/logging/Logged;Ljava/lang/String;)V
const #206 = Method	#32.#205;	//  scala/util/logging/Logged$class.log:(Lscala/util/logging/Logged;Ljava/lang/String;)V
const #207 = Asciz	msg;
const #208 = Asciz	<A:Lscala/xml/Node;>Ljava/lang/Object;Lscala/xml/factory/NodeFactory<TA;>;Lscala/util/logging/Logged;Lscala/ScalaObject;;
const #209 = Asciz	ScalaSig;
const #210 = Asciz	scala/ScalaObject;
const #211 = class	#210;	//  scala/ScalaObject

{
public scala.xml.factory.LoggedNodeFactory();
  Code:
   Stack=2, Locals=1, Args_size=1
   0:	aload_0
   1:	invokespecial	#24; //Method java/lang/Object."<init>":()V
   4:	aload_0
   5:	invokestatic	#30; //Method scala/xml/factory/NodeFactory$class.$init$:(Lscala/xml/factory/NodeFactory;)V
   8:	aload_0
   9:	invokestatic	#35; //Method scala/util/logging/Logged$class.$init$:(Lscala/util/logging/Logged;)V
   12:	aload_0
   13:	iconst_1
   14:	putfield	#39; //Field logNode:Z
   17:	aload_0
   18:	iconst_0
   19:	putfield	#41; //Field logText:Z
   22:	aload_0
   23:	iconst_0
   24:	putfield	#43; //Field logComment:Z
   27:	aload_0
   28:	iconst_0
   29:	putfield	#45; //Field logProcInstr:Z
   32:	aload_0
   33:	iconst_1
   34:	putfield	#47; //Field logCompressLevel:I
   37:	return
  LineNumberTable: 
   line 39: 0
   line 43: 12
   line 44: 17
   line 45: 22
   line 46: 27
   line 52: 32

  Signature: length = 0x2
   00 12 

public scala.collection.Seq makeProcInstr(java.lang.String, java.lang.String);
  Code:
   Stack=3, Locals=3, Args_size=3
   0:	aload_0
   1:	invokevirtual	#53; //Method logProcInstr:()Z
   4:	ifeq	46
   7:	aload_0
   8:	new	#55; //class scala/collection/mutable/StringBuilder
   11:	dup
   12:	invokespecial	#56; //Method scala/collection/mutable/StringBuilder."<init>":()V
   15:	ldc	#58; //String [makeProcInstr:\"
   17:	invokevirtual	#62; //Method scala/collection/mutable/StringBuilder.append:(Ljava/lang/Object;)Lscala/collection/mutable/StringBuilder;
   20:	aload_1
   21:	invokevirtual	#62; //Method scala/collection/mutable/StringBuilder.append:(Ljava/lang/Object;)Lscala/collection/mutable/StringBuilder;
   24:	ldc	#64; //String  
   26:	invokevirtual	#62; //Method scala/collection/mutable/StringBuilder.append:(Ljava/lang/Object;)Lscala/collection/mutable/StringBuilder;
   29:	aload_2
   30:	invokevirtual	#62; //Method scala/collection/mutable/StringBuilder.append:(Ljava/lang/Object;)Lscala/collection/mutable/StringBuilder;
   33:	ldc	#66; //String \"]
   35:	invokevirtual	#62; //Method scala/collection/mutable/StringBuilder.append:(Ljava/lang/Object;)Lscala/collection/mutable/StringBuilder;
   38:	invokevirtual	#70; //Method scala/collection/mutable/StringBuilder.toString:()Ljava/lang/String;
   41:	invokeinterface	#76,  2; //InterfaceMethod scala/util/logging/Logged.log:(Ljava/lang/String;)V
   46:	aload_0
   47:	aload_1
   48:	aload_2
   49:	invokestatic	#79; //Method scala/xml/factory/NodeFactory$class.makeProcInstr:(Lscala/xml/factory/NodeFactory;Ljava/lang/String;Ljava/lang/String;)Lscala/collection/Seq;
   52:	areturn
  LineNumberTable: 
   line 91: 0
   line 92: 7
   line 93: 46

  LocalVariableTable: 
   Start  Length  Slot  Name   Signature
   0      53      0    this       Lscala/xml/factory/LoggedNodeFactory;
   0      53      1    t       Ljava/lang/String;
   0      53      2    s       Ljava/lang/String;

  Signature: length = 0x2
   00 56 

public scala.collection.Seq makeComment(java.lang.String);
  Code:
   Stack=3, Locals=2, Args_size=2
   0:	aload_0
   1:	invokevirtual	#90; //Method logComment:()Z
   4:	ifeq	37
   7:	aload_0
   8:	new	#55; //class scala/collection/mutable/StringBuilder
   11:	dup
   12:	invokespecial	#56; //Method scala/collection/mutable/StringBuilder."<init>":()V
   15:	ldc	#92; //String [makeComment:\"
   17:	invokevirtual	#62; //Method scala/collection/mutable/StringBuilder.append:(Ljava/lang/Object;)Lscala/collection/mutable/StringBuilder;
   20:	aload_1
   21:	invokevirtual	#62; //Method scala/collection/mutable/StringBuilder.append:(Ljava/lang/Object;)Lscala/collection/mutable/StringBuilder;
   24:	ldc	#66; //String \"]
   26:	invokevirtual	#62; //Method scala/collection/mutable/StringBuilder.append:(Ljava/lang/Object;)Lscala/collection/mutable/StringBuilder;
   29:	invokevirtual	#70; //Method scala/collection/mutable/StringBuilder.toString:()Ljava/lang/String;
   32:	invokeinterface	#76,  2; //InterfaceMethod scala/util/logging/Logged.log:(Ljava/lang/String;)V
   37:	aload_0
   38:	aload_1
   39:	invokestatic	#95; //Method scala/xml/factory/NodeFactory$class.makeComment:(Lscala/xml/factory/NodeFactory;Ljava/lang/String;)Lscala/collection/Seq;
   42:	areturn
  LineNumberTable: 
   line 85: 0
   line 86: 7
   line 87: 37

  LocalVariableTable: 
   Start  Length  Slot  Name   Signature
   0      43      0    this       Lscala/xml/factory/LoggedNodeFactory;
   0      43      1    s       Ljava/lang/String;

  Signature: length = 0x2
   00 60 

public scala.xml.Text makeText(java.lang.String);
  Code:
   Stack=3, Locals=2, Args_size=2
   0:	aload_0
   1:	invokevirtual	#100; //Method logText:()Z
   4:	ifeq	37
   7:	aload_0
   8:	new	#55; //class scala/collection/mutable/StringBuilder
   11:	dup
   12:	invokespecial	#56; //Method scala/collection/mutable/StringBuilder."<init>":()V
   15:	ldc	#102; //String [makeText:\"
   17:	invokevirtual	#62; //Method scala/collection/mutable/StringBuilder.append:(Ljava/lang/Object;)Lscala/collection/mutable/StringBuilder;
   20:	aload_1
   21:	invokevirtual	#62; //Method scala/collection/mutable/StringBuilder.append:(Ljava/lang/Object;)Lscala/collection/mutable/StringBuilder;
   24:	ldc	#66; //String \"]
   26:	invokevirtual	#62; //Method scala/collection/mutable/StringBuilder.append:(Ljava/lang/Object;)Lscala/collection/mutable/StringBuilder;
   29:	invokevirtual	#70; //Method scala/collection/mutable/StringBuilder.toString:()Ljava/lang/String;
   32:	invokeinterface	#76,  2; //InterfaceMethod scala/util/logging/Logged.log:(Ljava/lang/String;)V
   37:	aload_0
   38:	aload_1
   39:	invokestatic	#105; //Method scala/xml/factory/NodeFactory$class.makeText:(Lscala/xml/factory/NodeFactory;Ljava/lang/String;)Lscala/xml/Text;
   42:	areturn
  LineNumberTable: 
   line 79: 0
   line 80: 7
   line 81: 37

  LocalVariableTable: 
   Start  Length  Slot  Name   Signature
   0      43      0    this       Lscala/xml/factory/LoggedNodeFactory;
   0      43      1    s       Ljava/lang/String;


public scala.xml.Node makeNode(java.lang.String, java.lang.String, scala.xml.MetaData, scala.xml.NamespaceBinding, scala.collection.Seq);
  Code:
   Stack=6, Locals=7, Args_size=6
   0:	aload_0
   1:	invokevirtual	#109; //Method logNode:()Z
   4:	ifeq	37
   7:	aload_0
   8:	new	#55; //class scala/collection/mutable/StringBuilder
   11:	dup
   12:	invokespecial	#56; //Method scala/collection/mutable/StringBuilder."<init>":()V
   15:	ldc	#111; //String [makeNode for 
   17:	invokevirtual	#62; //Method scala/collection/mutable/StringBuilder.append:(Ljava/lang/Object;)Lscala/collection/mutable/StringBuilder;
   20:	aload_2
   21:	invokevirtual	#62; //Method scala/collection/mutable/StringBuilder.append:(Ljava/lang/Object;)Lscala/collection/mutable/StringBuilder;
   24:	ldc	#113; //String ]
   26:	invokevirtual	#62; //Method scala/collection/mutable/StringBuilder.append:(Ljava/lang/Object;)Lscala/collection/mutable/StringBuilder;
   29:	invokevirtual	#70; //Method scala/collection/mutable/StringBuilder.toString:()Ljava/lang/String;
   32:	invokeinterface	#76,  2; //InterfaceMethod scala/util/logging/Logged.log:(Ljava/lang/String;)V
   37:	getstatic	#119; //Field scala/xml/Utility$.MODULE$:Lscala/xml/Utility$;
   40:	aload_1
   41:	aload_2
   42:	aload_3
   43:	invokevirtual	#125; //Method scala/xml/MetaData.hashCode:()I
   46:	aload	4
   48:	invokevirtual	#128; //Method scala/xml/NamespaceBinding.hashCode:()I
   51:	aload	5
   53:	invokevirtual	#131; //Method scala/xml/Utility$.hashCode:(Ljava/lang/String;Ljava/lang/String;IILscala/collection/Seq;)I
   56:	istore	6
   58:	aload_0
   59:	invokeinterface	#136,  1; //InterfaceMethod scala/xml/factory/NodeFactory.cache:()Lscala/collection/mutable/HashMap;
   64:	iload	6
   66:	invokestatic	#142; //Method scala/runtime/BoxesRunTime.boxToInteger:(I)Ljava/lang/Integer;
   69:	invokevirtual	#148; //Method scala/collection/mutable/HashMap.get:(Ljava/lang/Object;)Lscala/Option;
   72:	invokevirtual	#153; //Method scala/Option.isEmpty:()Z
   75:	ifne	94
   78:	aload_0
   79:	invokevirtual	#155; //Method logCompressLevel:()I
   82:	iconst_1
   83:	if_icmplt	94
   86:	aload_0
   87:	ldc	#157; //String [cache hit !]
   89:	invokeinterface	#76,  2; //InterfaceMethod scala/util/logging/Logged.log:(Ljava/lang/String;)V
   94:	aload_0
   95:	aload_1
   96:	aload_2
   97:	aload_3
   98:	aload	4
   100:	aload	5
   102:	invokestatic	#160; //Method scala/xml/factory/NodeFactory$class.makeNode:(Lscala/xml/factory/NodeFactory;Ljava/lang/String;Ljava/lang/String;Lscala/xml/MetaData;Lscala/xml/NamespaceBinding;Lscala/collection/Seq;)Lscala/xml/Node;
   105:	areturn
  LineNumberTable: 
   line 59: 0
   line 60: 7
   line 62: 37
   line 72: 58
   line 73: 86
   line 75: 94

  LocalVariableTable: 
   Start  Length  Slot  Name   Signature
   0      106      0    this       Lscala/xml/factory/LoggedNodeFactory;
   0      106      1    pre       Ljava/lang/String;
   0      106      2    label       Ljava/lang/String;
   0      106      3    attrSeq       Lscala/xml/MetaData;
   0      106      4    scope       Lscala/xml/NamespaceBinding;
   0      106      5    children       Lscala/collection/Seq;
   58      47      6    hash       I

  Signature: length = 0x2
   00 FFFFFFAA 

public int logCompressLevel();
  Code:
   Stack=1, Locals=1, Args_size=1
   0:	aload_0
   1:	getfield	#47; //Field logCompressLevel:I
   4:	ireturn
  LineNumberTable: 
   line 52: 0


public final int FULL();
  Code:
   Stack=1, Locals=1, Args_size=1
   0:	iconst_2
   1:	ireturn
  LineNumberTable: 
   line 50: 0


public final int CACHE();
  Code:
   Stack=1, Locals=1, Args_size=1
   0:	iconst_1
   1:	ireturn
  LineNumberTable: 
   line 49: 0


public final int NONE();
  Code:
   Stack=1, Locals=1, Args_size=1
   0:	iconst_0
   1:	ireturn
  LineNumberTable: 
   line 48: 0


public boolean logProcInstr();
  Code:
   Stack=1, Locals=1, Args_size=1
   0:	aload_0
   1:	getfield	#45; //Field logProcInstr:Z
   4:	ireturn
  LineNumberTable: 
   line 46: 0


public boolean logComment();
  Code:
   Stack=1, Locals=1, Args_size=1
   0:	aload_0
   1:	getfield	#43; //Field logComment:Z
   4:	ireturn
  LineNumberTable: 
   line 45: 0


public boolean logText();
  Code:
   Stack=1, Locals=1, Args_size=1
   0:	aload_0
   1:	getfield	#41; //Field logText:Z
   4:	ireturn
  LineNumberTable: 
   line 44: 0


public boolean logNode();
  Code:
   Stack=1, Locals=1, Args_size=1
   0:	aload_0
   1:	getfield	#39; //Field logNode:Z
   4:	ireturn
  LineNumberTable: 
   line 43: 0


public boolean nodeEquals(scala.xml.Node, java.lang.String, java.lang.String, scala.xml.MetaData, scala.xml.NamespaceBinding, scala.collection.Seq);
  Code:
   Stack=7, Locals=7, Args_size=7
   0:	aload_0
   1:	aload_1
   2:	aload_2
   3:	aload_3
   4:	aload	4
   6:	aload	5
   8:	aload	6
   10:	invokestatic	#175; //Method scala/xml/factory/NodeFactory$class.nodeEquals:(Lscala/xml/factory/NodeFactory;Lscala/xml/Node;Ljava/lang/String;Ljava/lang/String;Lscala/xml/MetaData;Lscala/xml/NamespaceBinding;Lscala/collection/Seq;)Z
   13:	ireturn
  LineNumberTable: 
   line 38: 0

  LocalVariableTable: 
   Start  Length  Slot  Name   Signature
   0      14      0    this       Lscala/xml/factory/LoggedNodeFactory;
   0      14      1    n       Lscala/xml/Node;
   0      14      2    pre       Ljava/lang/String;
   0      14      3    name       Ljava/lang/String;
   0      14      4    attrSeq       Lscala/xml/MetaData;
   0      14      5    scope       Lscala/xml/NamespaceBinding;
   0      14      6    children       Lscala/collection/Seq;


public boolean eqElements(scala.collection.Seq, scala.collection.Seq);
  Code:
   Stack=3, Locals=3, Args_size=3
   0:	aload_0
   1:	aload_1
   2:	aload_2
   3:	invokestatic	#183; //Method scala/xml/factory/NodeFactory$class.eqElements:(Lscala/xml/factory/NodeFactory;Lscala/collection/Seq;Lscala/collection/Seq;)Z
   6:	ireturn
  LineNumberTable: 
   line 38: 0

  LocalVariableTable: 
   Start  Length  Slot  Name   Signature
   0      7      0    this       Lscala/xml/factory/LoggedNodeFactory;
   0      7      1    ch1       Lscala/collection/Seq;
   0      7      2    ch2       Lscala/collection/Seq;


public scala.xml.Node construct(int, scala.collection.immutable.List, java.lang.String, java.lang.String, scala.xml.MetaData, scala.xml.NamespaceBinding, scala.collection.Seq);
  Code:
   Stack=8, Locals=8, Args_size=8
   0:	aload_0
   1:	iload_1
   2:	aload_2
   3:	aload_3
   4:	aload	4
   6:	aload	5
   8:	aload	6
   10:	aload	7
   12:	invokestatic	#190; //Method scala/xml/factory/NodeFactory$class.construct:(Lscala/xml/factory/NodeFactory;ILscala/collection/immutable/List;Ljava/lang/String;Ljava/lang/String;Lscala/xml/MetaData;Lscala/xml/NamespaceBinding;Lscala/collection/Seq;)Lscala/xml/Node;
   15:	areturn
  LineNumberTable: 
   line 38: 0

  LocalVariableTable: 
   Start  Length  Slot  Name   Signature
   0      16      0    this       Lscala/xml/factory/LoggedNodeFactory;
   0      16      1    hash       I
   0      16      2    old       Lscala/collection/immutable/List;
   0      16      3    pre       Ljava/lang/String;
   0      16      4    name       Ljava/lang/String;
   0      16      5    attrSeq       Lscala/xml/MetaData;
   0      16      6    scope       Lscala/xml/NamespaceBinding;
   0      16      7    children       Lscala/collection/Seq;


public void scala$xml$factory$NodeFactory$_setter_$cache_$eq(scala.collection.mutable.HashMap);
  Code:
   Stack=2, Locals=2, Args_size=2
   0:	aload_0
   1:	aload_1
   2:	putfield	#196; //Field cache:Lscala/collection/mutable/HashMap;
   5:	return
  LineNumberTable: 
   line 38: 0


public void scala$xml$factory$NodeFactory$_setter_$ignoreProcInstr_$eq(boolean);
  Code:
   Stack=2, Locals=2, Args_size=2
   0:	aload_0
   1:	iload_1
   2:	putfield	#200; //Field ignoreProcInstr:Z
   5:	return
  LineNumberTable: 
   line 38: 0


public void scala$xml$factory$NodeFactory$_setter_$ignoreComments_$eq(boolean);
  Code:
   Stack=2, Locals=2, Args_size=2
   0:	aload_0
   1:	iload_1
   2:	putfield	#203; //Field ignoreComments:Z
   5:	return
  LineNumberTable: 
   line 38: 0


public scala.collection.mutable.HashMap cache();
  Code:
   Stack=1, Locals=1, Args_size=1
   0:	aload_0
   1:	getfield	#196; //Field cache:Lscala/collection/mutable/HashMap;
   4:	areturn
  LineNumberTable: 
   line 38: 0


public boolean ignoreProcInstr();
  Code:
   Stack=1, Locals=1, Args_size=1
   0:	aload_0
   1:	getfield	#200; //Field ignoreProcInstr:Z
   4:	ireturn
  LineNumberTable: 
   line 38: 0


public boolean ignoreComments();
  Code:
   Stack=1, Locals=1, Args_size=1
   0:	aload_0
   1:	getfield	#203; //Field ignoreComments:Z
   4:	ireturn
  LineNumberTable: 
   line 38: 0


public void log(java.lang.String);
  Code:
   Stack=2, Locals=2, Args_size=2
   0:	aload_0
   1:	aload_1
   2:	invokestatic	#206; //Method scala/util/logging/Logged$class.log:(Lscala/util/logging/Logged;Ljava/lang/String;)V
   5:	return
  LineNumberTable: 
   line 38: 0

  LocalVariableTable: 
   Start  Length  Slot  Name   Signature
   0      6      0    this       Lscala/xml/factory/LoggedNodeFactory;
   0      6      1    msg       Ljava/lang/String;


}

