Compiled from "NodeFactory.scala"
public abstract class scala.xml.factory.NodeFactory$class extends java.lang.Object
  SourceFile: "NodeFactory.scala"
  Scala: length = 0x
   
  InnerClass: 
   public final $anonfun$makeNode$1=class scala/xml/factory/NodeFactory$$anonfun$makeNode$1 of class scala/xml/factory/NodeFactory
   public final $anonfun$eqElements$1=class scala/xml/factory/NodeFactory$$anonfun$eqElements$1 of class scala/xml/factory/NodeFactory
  minor version: 0
  major version: 49
  Constant pool:
Asciz	SourceFile;
Asciz	NodeFactory.scala;
Asciz	$init$;
Asciz	(Lscala/xml/factory/NodeFactory;)V;
Asciz	Code;
Asciz	LineNumberTable;
Asciz	scala/xml/factory/NodeFactory;
class	scala/xml/factory/NodeFactory
Asciz	scala$xml$factory$NodeFactory$_setter_$ignoreComments_$eq;
Asciz	(Z)V;
NameAndType	scala$xml$factory$NodeFactory$_setter_$ignoreComments_$eq:(Z)V
InterfaceMethod	scala/xml/factory/NodeFactory.scala$xml$factory$NodeFactory$_setter_$ignoreComments_$eq:(Z)V
Asciz	scala$xml$factory$NodeFactory$_setter_$ignoreProcInstr_$eq;
NameAndType	scala$xml$factory$NodeFactory$_setter_$ignoreProcInstr_$eq:(Z)V
InterfaceMethod	scala/xml/factory/NodeFactory.scala$xml$factory$NodeFactory$_setter_$ignoreProcInstr_$eq:(Z)V
Asciz	scala/collection/mutable/HashMap;
class	scala/collection/mutable/HashMap
Asciz	<init>;
Asciz	()V;
NameAndType	"<init>":()V
Method	scala/collection/mutable/HashMap."<init>":()V
Asciz	scala$xml$factory$NodeFactory$_setter_$cache_$eq;
Asciz	(Lscala/collection/mutable/HashMap;)V;
NameAndType	scala$xml$factory$NodeFactory$_setter_$cache_$eq:(Lscala/collection/mutable/HashMap;)V
InterfaceMethod	scala/xml/factory/NodeFactory.scala$xml$factory$NodeFactory$_setter_$cache_$eq:(Lscala/collection/mutable/HashMap;)V
Asciz	$this;
Asciz	Lscala/xml/factory/NodeFactory;;
Asciz	LocalVariableTable;
Asciz	cons$1;
Asciz	(Lscala/xml/factory/NodeFactory;Lscala/collection/immutable/List;Ljava/lang/String;Ljava/lang/String;Lscala/xml/MetaData;Lscala/xml/NamespaceBinding;Lscala/collection/Seq;I)Lscala/xml/Node;;
Asciz	construct;
Asciz	(ILscala/collection/immutable/List;Ljava/lang/String;Ljava/lang/String;Lscala/xml/MetaData;Lscala/xml/NamespaceBinding;Lscala/collection/Seq;)Lscala/xml/Node;;
NameAndType	construct:(ILscala/collection/immutable/List;Ljava/lang/String;Ljava/lang/String;Lscala/xml/MetaData;Lscala/xml/NamespaceBinding;Lscala/collection/Seq;)Lscala/xml/Node;
InterfaceMethod	scala/xml/factory/NodeFactory.construct:(ILscala/collection/immutable/List;Ljava/lang/String;Ljava/lang/String;Lscala/xml/MetaData;Lscala/xml/NamespaceBinding;Lscala/collection/Seq;)Lscala/xml/Node;
Asciz	old;
Asciz	Lscala/collection/immutable/List;;
Asciz	makeProcInstr;
Asciz	(Lscala/xml/factory/NodeFactory;Ljava/lang/String;Ljava/lang/String;)Lscala/collection/Seq;;
Asciz	ignoreProcInstr;
Asciz	()Z;
NameAndType	ignoreProcInstr:()Z
InterfaceMethod	scala/xml/factory/NodeFactory.ignoreProcInstr:()Z
Asciz	scala/collection/immutable/Nil$;
class	scala/collection/immutable/Nil$
Asciz	MODULE$;
Asciz	Lscala/collection/immutable/Nil$;;
NameAndType	MODULE$:Lscala/collection/immutable/Nil$;
Field	scala/collection/immutable/Nil$.MODULE$:Lscala/collection/immutable/Nil$;
Asciz	scala/Predef$;
class	scala/Predef$
Asciz	Lscala/Predef$;;
NameAndType	MODULE$:Lscala/Predef$;
Field	scala/Predef$.MODULE$:Lscala/Predef$;
Asciz	scala/xml/ProcInstr;
class	scala/xml/ProcInstr
Asciz	(Ljava/lang/String;Ljava/lang/String;)V;
NameAndType	"<init>":(Ljava/lang/String;Ljava/lang/String;)V
Method	scala/xml/ProcInstr."<init>":(Ljava/lang/String;Ljava/lang/String;)V
Asciz	[Ljava/lang/Object;;
class	"[Ljava/lang/Object;"
Asciz	wrapRefArray;
Asciz	([Ljava/lang/Object;)Lscala/collection/mutable/WrappedArray;;
NameAndType	wrapRefArray:([Ljava/lang/Object;)Lscala/collection/mutable/WrappedArray;
Method	scala/Predef$.wrapRefArray:([Ljava/lang/Object;)Lscala/collection/mutable/WrappedArray;
Asciz	scala/collection/TraversableLike;
class	scala/collection/TraversableLike
Asciz	toList;
Asciz	()Lscala/collection/immutable/List;;
NameAndType	toList:()Lscala/collection/immutable/List;
InterfaceMethod	scala/collection/TraversableLike.toList:()Lscala/collection/immutable/List;
Asciz	t;
Asciz	Ljava/lang/String;;
Asciz	s;
Asciz	makeComment;
Asciz	(Lscala/xml/factory/NodeFactory;Ljava/lang/String;)Lscala/collection/Seq;;
Asciz	ignoreComments;
NameAndType	ignoreComments:()Z
InterfaceMethod	scala/xml/factory/NodeFactory.ignoreComments:()Z
Asciz	scala/xml/Comment;
class	scala/xml/Comment
Asciz	(Ljava/lang/String;)V;
NameAndType	"<init>":(Ljava/lang/String;)V
Method	scala/xml/Comment."<init>":(Ljava/lang/String;)V
Asciz	makeText;
Asciz	(Lscala/xml/factory/NodeFactory;Ljava/lang/String;)Lscala/xml/Text;;
Asciz	scala/xml/Text$;
class	scala/xml/Text$
Asciz	Lscala/xml/Text$;;
NameAndType	MODULE$:Lscala/xml/Text$;
Field	scala/xml/Text$.MODULE$:Lscala/xml/Text$;
Asciz	apply;
Asciz	(Ljava/lang/String;)Lscala/xml/Text;;
NameAndType	apply:(Ljava/lang/String;)Lscala/xml/Text;
Method	scala/xml/Text$.apply:(Ljava/lang/String;)Lscala/xml/Text;
Asciz	makeNode;
Asciz	(Lscala/xml/factory/NodeFactory;Ljava/lang/String;Ljava/lang/String;Lscala/xml/MetaData;Lscala/xml/NamespaceBinding;Lscala/collection/Seq;)Lscala/xml/Node;;
Asciz	scala/xml/Utility$;
class	scala/xml/Utility$
Asciz	Lscala/xml/Utility$;;
NameAndType	MODULE$:Lscala/xml/Utility$;
Field	scala/xml/Utility$.MODULE$:Lscala/xml/Utility$;
Asciz	scala/xml/MetaData;
class	scala/xml/MetaData
Asciz	hashCode;
Asciz	()I;
NameAndType	hashCode:()I
Method	scala/xml/MetaData.hashCode:()I
Asciz	scala/xml/NamespaceBinding;
class	scala/xml/NamespaceBinding
Method	scala/xml/NamespaceBinding.hashCode:()I
Asciz	(Ljava/lang/String;Ljava/lang/String;IILscala/collection/Seq;)I;
NameAndType	hashCode:(Ljava/lang/String;Ljava/lang/String;IILscala/collection/Seq;)I
Method	scala/xml/Utility$.hashCode:(Ljava/lang/String;Ljava/lang/String;IILscala/collection/Seq;)I
Asciz	cache;
Asciz	()Lscala/collection/mutable/HashMap;;
NameAndType	cache:()Lscala/collection/mutable/HashMap;
InterfaceMethod	scala/xml/factory/NodeFactory.cache:()Lscala/collection/mutable/HashMap;
Asciz	scala/runtime/BoxesRunTime;
class	scala/runtime/BoxesRunTime
Asciz	boxToInteger;
Asciz	(I)Ljava/lang/Integer;;
NameAndType	boxToInteger:(I)Ljava/lang/Integer;
Method	scala/runtime/BoxesRunTime.boxToInteger:(I)Ljava/lang/Integer;
Asciz	get;
Asciz	(Ljava/lang/Object;)Lscala/Option;;
NameAndType	get:(Ljava/lang/Object;)Lscala/Option;
Method	scala/collection/mutable/HashMap.get:(Ljava/lang/Object;)Lscala/Option;
Asciz	scala/Some;
class	scala/Some
Asciz	x;
Asciz	Ljava/lang/Object;;
NameAndType	x:Ljava/lang/Object;
Field	scala/Some.x:Ljava/lang/Object;
Asciz	scala/collection/immutable/List;
class	scala/collection/immutable/List
Asciz	scala/xml/factory/NodeFactory$$anonfun$makeNode$1;
class	scala/xml/factory/NodeFactory$$anonfun$makeNode$1
Asciz	(Lscala/xml/factory/NodeFactory;Ljava/lang/String;Ljava/lang/String;Lscala/xml/MetaData;Lscala/xml/NamespaceBinding;Lscala/collection/Seq;)V;
NameAndType	"<init>":(Lscala/xml/factory/NodeFactory;Ljava/lang/String;Ljava/lang/String;Lscala/xml/MetaData;Lscala/xml/NamespaceBinding;Lscala/collection/Seq;)V
Method	scala/xml/factory/NodeFactory$$anonfun$makeNode$1."<init>":(Lscala/xml/factory/NodeFactory;Ljava/lang/String;Ljava/lang/String;Lscala/xml/MetaData;Lscala/xml/NamespaceBinding;Lscala/collection/Seq;)V
Asciz	scala/collection/LinearSeqLike;
class	scala/collection/LinearSeqLike
Asciz	find;
Asciz	(Lscala/Function1;)Lscala/Option;;
NameAndType	find:(Lscala/Function1;)Lscala/Option;
InterfaceMethod	scala/collection/LinearSeqLike.find:(Lscala/Function1;)Lscala/Option;
Asciz	scala/xml/Node;
class	scala/xml/Node
Asciz	scala/MatchError;
class	scala/MatchError
Asciz	scala/Option;
class	scala/Option
Asciz	toString;
Asciz	()Ljava/lang/String;;
NameAndType	toString:()Ljava/lang/String;
Method	scala/Option.toString:()Ljava/lang/String;
Method	scala/MatchError."<init>":(Ljava/lang/String;)V
Asciz	scala/xml/factory/NodeFactory$class;
class	scala/xml/factory/NodeFactory$class
NameAndType	cons$1:(Lscala/xml/factory/NodeFactory;Lscala/collection/immutable/List;Ljava/lang/String;Ljava/lang/String;Lscala/xml/MetaData;Lscala/xml/NamespaceBinding;Lscala/collection/Seq;I)Lscala/xml/Node;
Method	scala/xml/factory/NodeFactory$class.cons$1:(Lscala/xml/factory/NodeFactory;Lscala/collection/immutable/List;Ljava/lang/String;Ljava/lang/String;Lscala/xml/MetaData;Lscala/xml/NamespaceBinding;Lscala/collection/Seq;I)Lscala/xml/Node;
Asciz	scala/None$;
class	scala/None$
Asciz	Lscala/None$;;
NameAndType	MODULE$:Lscala/None$;
Field	scala/None$.MODULE$:Lscala/None$;
Asciz	java/lang/Object;
class	java/lang/Object
Asciz	equals;
Asciz	(Ljava/lang/Object;)Z;
NameAndType	equals:(Ljava/lang/Object;)Z
Method	java/lang/Object.equals:(Ljava/lang/Object;)Z
Asciz	pre$1;
Asciz	name$1;
Asciz	attrSeq$1;
Asciz	Lscala/xml/MetaData;;
Asciz	scope$1;
Asciz	Lscala/xml/NamespaceBinding;;
Asciz	children$1;
Asciz	Lscala/collection/Seq;;
Asciz	temp8;
Asciz	Lscala/Some;;
Asciz	temp5;
Asciz	temp6;
Asciz	Lscala/xml/Node;;
Asciz	temp9;
Asciz	temp4;
Asciz	Lscala/Option;;
Asciz	hash$1;
Asciz	I;
Asciz	temp7;
Asciz	nodeEquals;
Asciz	(Lscala/xml/factory/NodeFactory;Lscala/xml/Node;Ljava/lang/String;Ljava/lang/String;Lscala/xml/MetaData;Lscala/xml/NamespaceBinding;Lscala/collection/Seq;)Z;
Asciz	prefix;
NameAndType	prefix:()Ljava/lang/String;
Method	scala/xml/Node.prefix:()Ljava/lang/String;
Asciz	label;
NameAndType	label:()Ljava/lang/String;
Method	scala/xml/Node.label:()Ljava/lang/String;
Asciz	attributes;
Asciz	()Lscala/xml/MetaData;;
NameAndType	attributes:()Lscala/xml/MetaData;
Method	scala/xml/Node.attributes:()Lscala/xml/MetaData;
Asciz	child;
Asciz	()Lscala/collection/Seq;;
NameAndType	child:()Lscala/collection/Seq;
Method	scala/xml/Node.child:()Lscala/collection/Seq;
Asciz	eqElements;
Asciz	(Lscala/collection/Seq;Lscala/collection/Seq;)Z;
NameAndType	eqElements:(Lscala/collection/Seq;Lscala/collection/Seq;)Z
InterfaceMethod	scala/xml/factory/NodeFactory.eqElements:(Lscala/collection/Seq;Lscala/collection/Seq;)Z
Asciz	n;
Asciz	pre;
Asciz	name;
Asciz	attrSeq;
Asciz	scope;
Asciz	children;
Asciz	(Lscala/xml/factory/NodeFactory;Lscala/collection/Seq;Lscala/collection/Seq;)Z;
Asciz	scala/collection/SeqLike;
class	scala/collection/SeqLike
Asciz	view;
Asciz	()Ljava/lang/Object;;
NameAndType	view:()Ljava/lang/Object;
InterfaceMethod	scala/collection/SeqLike.view:()Ljava/lang/Object;
Asciz	scala/collection/IterableViewLike;
class	scala/collection/IterableViewLike
Asciz	scala/collection/Iterable;
class	scala/collection/Iterable
Asciz	scala/collection/SeqView$;
class	scala/collection/SeqView$
Asciz	Lscala/collection/SeqView$;;
NameAndType	MODULE$:Lscala/collection/SeqView$;
Field	scala/collection/SeqView$.MODULE$:Lscala/collection/SeqView$;
Asciz	canBuildFrom;
Asciz	()Lscala/collection/generic/CanBuildFrom;;
NameAndType	canBuildFrom:()Lscala/collection/generic/CanBuildFrom;
Method	scala/collection/SeqView$.canBuildFrom:()Lscala/collection/generic/CanBuildFrom;
Asciz	zipAll;
Asciz	(Lscala/collection/Iterable;Ljava/lang/Object;Ljava/lang/Object;Lscala/collection/generic/CanBuildFrom;)Ljava/lang/Object;;
NameAndType	zipAll:(Lscala/collection/Iterable;Ljava/lang/Object;Ljava/lang/Object;Lscala/collection/generic/CanBuildFrom;)Ljava/lang/Object;
InterfaceMethod	scala/collection/IterableViewLike.zipAll:(Lscala/collection/Iterable;Ljava/lang/Object;Ljava/lang/Object;Lscala/collection/generic/CanBuildFrom;)Ljava/lang/Object;
Asciz	scala/collection/IterableLike;
class	scala/collection/IterableLike
Asciz	scala/xml/factory/NodeFactory$$anonfun$eqElements$1;
class	scala/xml/factory/NodeFactory$$anonfun$eqElements$1
NameAndType	"<init>":(Lscala/xml/factory/NodeFactory;)V
Method	scala/xml/factory/NodeFactory$$anonfun$eqElements$1."<init>":(Lscala/xml/factory/NodeFactory;)V
Asciz	forall;
Asciz	(Lscala/Function1;)Z;
NameAndType	forall:(Lscala/Function1;)Z
InterfaceMethod	scala/collection/IterableLike.forall:(Lscala/Function1;)Z
Asciz	ch1;
Asciz	ch2;
Asciz	(Lscala/xml/factory/NodeFactory;ILscala/collection/immutable/List;Ljava/lang/String;Ljava/lang/String;Lscala/xml/MetaData;Lscala/xml/NamespaceBinding;Lscala/collection/Seq;)Lscala/xml/Node;;
Asciz	create;
Asciz	(Ljava/lang/String;Ljava/lang/String;Lscala/xml/MetaData;Lscala/xml/NamespaceBinding;Lscala/collection/Seq;)Lscala/xml/Node;;
NameAndType	create:(Ljava/lang/String;Ljava/lang/String;Lscala/xml/MetaData;Lscala/xml/NamespaceBinding;Lscala/collection/Seq;)Lscala/xml/Node;
InterfaceMethod	scala/xml/factory/NodeFactory.create:(Ljava/lang/String;Ljava/lang/String;Lscala/xml/MetaData;Lscala/xml/NamespaceBinding;Lscala/collection/Seq;)Lscala/xml/Node;
Asciz	$colon$colon;
Asciz	(Ljava/lang/Object;)Lscala/collection/immutable/List;;
NameAndType	$colon$colon:(Ljava/lang/Object;)Lscala/collection/immutable/List;
Method	scala/collection/immutable/List.$colon$colon:(Ljava/lang/Object;)Lscala/collection/immutable/List;
Asciz	update;
Asciz	(Ljava/lang/Object;Ljava/lang/Object;)V;
NameAndType	update:(Ljava/lang/Object;Ljava/lang/Object;)V
Method	scala/collection/mutable/HashMap.update:(Ljava/lang/Object;Ljava/lang/Object;)V
Asciz	hash;
Asciz	el;
Asciz	Scala;
Asciz	InnerClasses;
Asciz	$anonfun$makeNode$1;
Asciz	$anonfun$eqElements$1;

{
public static void $init$(scala.xml.factory.NodeFactory);
  Signature: (Lscala/xml/factory/NodeFactory;)V
  Code:
   Stack=3, Locals=1, Args_size=1
	aload_0
	iconst_0
	invokeinterface	InterfaceMethod scala/xml/factory/NodeFactory.scala$xml$factory$NodeFactory$_setter_$ignoreComments_$eq:(Z)V
	aload_0
	iconst_0
	invokeinterface	InterfaceMethod scala/xml/factory/NodeFactory.scala$xml$factory$NodeFactory$_setter_$ignoreProcInstr_$eq:(Z)V
	aload_0
	new	class scala/collection/mutable/HashMap
	dup
	invokespecial	Method scala/collection/mutable/HashMap."<init>":()V
	invokeinterface	InterfaceMethod scala/xml/factory/NodeFactory.scala$xml$factory$NodeFactory$_setter_$cache_$eq:(Lscala/collection/mutable/HashMap;)V
	return
  Labels:
  LocalVariableTable: 
   Start  Length  Slot  Name   Signature
   0      28      0    $this       Lscala/xml/factory/NodeFactory;


private static final scala.xml.Node cons$1(scala.xml.factory.NodeFactory, scala.collection.immutable.List, java.lang.String, java.lang.String, scala.xml.MetaData, scala.xml.NamespaceBinding, scala.collection.Seq, int);
  Signature: (Lscala/xml/factory/NodeFactory;Lscala/collection/immutable/List;Ljava/lang/String;Ljava/lang/String;Lscala/xml/MetaData;Lscala/xml/NamespaceBinding;Lscala/collection/Seq;I)Lscala/xml/Node;
  Code:
   Stack=8, Locals=8, Args_size=8
	aload_0
	iload	7
	aload_1
	aload_2
	aload_3
	aload	4
	aload	5
	aload	6
	invokeinterface	InterfaceMethod scala/xml/factory/NodeFactory.construct:(ILscala/collection/immutable/List;Ljava/lang/String;Ljava/lang/String;Lscala/xml/MetaData;Lscala/xml/NamespaceBinding;Lscala/collection/Seq;)Lscala/xml/Node;
	areturn
  Labels:
  LocalVariableTable: 
   Start  Length  Slot  Name   Signature
   0      18      0    $this       Lscala/xml/factory/NodeFactory;
   0      18      1    old       Lscala/collection/immutable/List;


public static scala.collection.Seq makeProcInstr(scala.xml.factory.NodeFactory, java.lang.String, java.lang.String);
  Signature: (Lscala/xml/factory/NodeFactory;Ljava/lang/String;Ljava/lang/String;)Lscala/collection/Seq;
  Code:
   Stack=8, Locals=4, Args_size=3
	aload_0
	invokeinterface	InterfaceMethod scala/xml/factory/NodeFactory.ignoreProcInstr:()Z
	ifeq	l1 // getstatic
	getstatic	Field scala/collection/immutable/Nil$.MODULE$:Lscala/collection/immutable/Nil$;
	goto	l2 // areturn
l1	getstatic	Field scala/Predef$.MODULE$:Lscala/Predef$;
	iconst_1
	anewarray	class scala/xml/ProcInstr
	dup
	iconst_0
	new	class scala/xml/ProcInstr
	dup
	aload_1
	aload_2
	invokespecial	Method scala/xml/ProcInstr."<init>":(Ljava/lang/String;Ljava/lang/String;)V
	aastore
	checkcast	class "[Ljava/lang/Object;"
	invokevirtual	Method scala/Predef$.wrapRefArray:([Ljava/lang/Object;)Lscala/collection/mutable/WrappedArray;
	astore_3
	aload_3
	invokeinterface	InterfaceMethod scala/collection/TraversableLike.toList:()Lscala/collection/immutable/List;
l2	areturn
  Labels:
   	l1 = 15 // getstatic
   	l2 = 47 // areturn
  LocalVariableTable: 
   Start  Length  Slot  Name   Signature
   0      48      0    $this       Lscala/xml/factory/NodeFactory;
   0      48      1    t       Ljava/lang/String;
   0      48      2    s       Ljava/lang/String;


public static scala.collection.Seq makeComment(scala.xml.factory.NodeFactory, java.lang.String);
  Signature: (Lscala/xml/factory/NodeFactory;Ljava/lang/String;)Lscala/collection/Seq;
  Code:
   Stack=7, Locals=3, Args_size=2
	aload_0
	invokeinterface	InterfaceMethod scala/xml/factory/NodeFactory.ignoreComments:()Z
	ifeq	l1 // getstatic
	getstatic	Field scala/collection/immutable/Nil$.MODULE$:Lscala/collection/immutable/Nil$;
	goto	l2 // areturn
l1	getstatic	Field scala/Predef$.MODULE$:Lscala/Predef$;
	iconst_1
	anewarray	class scala/xml/Comment
	dup
	iconst_0
	new	class scala/xml/Comment
	dup
	aload_1
	invokespecial	Method scala/xml/Comment."<init>":(Ljava/lang/String;)V
	aastore
	checkcast	class "[Ljava/lang/Object;"
	invokevirtual	Method scala/Predef$.wrapRefArray:([Ljava/lang/Object;)Lscala/collection/mutable/WrappedArray;
	astore_2
	aload_2
	invokeinterface	InterfaceMethod scala/collection/TraversableLike.toList:()Lscala/collection/immutable/List;
l2	areturn
  Labels:
   	l1 = 15 // getstatic
   	l2 = 46 // areturn
  LocalVariableTable: 
   Start  Length  Slot  Name   Signature
   0      47      0    $this       Lscala/xml/factory/NodeFactory;
   0      47      1    s       Ljava/lang/String;


public static scala.xml.Text makeText(scala.xml.factory.NodeFactory, java.lang.String);
  Signature: (Lscala/xml/factory/NodeFactory;Ljava/lang/String;)Lscala/xml/Text;
  Code:
   Stack=2, Locals=2, Args_size=2
	getstatic	Field scala/xml/Text$.MODULE$:Lscala/xml/Text$;
	aload_1
	invokevirtual	Method scala/xml/Text$.apply:(Ljava/lang/String;)Lscala/xml/Text;
	areturn
  Labels:
  LocalVariableTable: 
   Start  Length  Slot  Name   Signature
   0      8      0    $this       Lscala/xml/factory/NodeFactory;
   0      8      1    s       Ljava/lang/String;


public static scala.xml.Node makeNode(scala.xml.factory.NodeFactory, java.lang.String, java.lang.String, scala.xml.MetaData, scala.xml.NamespaceBinding, scala.collection.Seq);
  Signature: (Lscala/xml/factory/NodeFactory;Ljava/lang/String;Ljava/lang/String;Lscala/xml/MetaData;Lscala/xml/NamespaceBinding;Lscala/collection/Seq;)Lscala/xml/Node;
  Code:
   Stack=9, Locals=13, Args_size=6
	getstatic	Field scala/xml/Utility$.MODULE$:Lscala/xml/Utility$;
	aload_1
	aload_2
	aload_3
	invokevirtual	Method scala/xml/MetaData.hashCode:()I
	aload	4
	invokevirtual	Method scala/xml/NamespaceBinding.hashCode:()I
	aload	5
	invokevirtual	Method scala/xml/Utility$.hashCode:(Ljava/lang/String;Ljava/lang/String;IILscala/collection/Seq;)I
	istore	11
	aload_0
	invokeinterface	InterfaceMethod scala/xml/factory/NodeFactory.cache:()Lscala/collection/mutable/HashMap;
	iload	11
	invokestatic	Method scala/runtime/BoxesRunTime.boxToInteger:(I)Ljava/lang/Integer;
	invokevirtual	Method scala/collection/mutable/HashMap.get:(Ljava/lang/Object;)Lscala/Option;
	astore	12
	aload	12
	instanceof	class scala/Some
	ifeq	l1 // getstatic
	aload	12
	checkcast	class scala/Some
	astore	6
	aload	6
	getfield	Field scala/Some.x:Ljava/lang/Object;
	checkcast	class scala/collection/immutable/List
	astore	9
	iconst_1
	ifeq	l2 // new
	aload	9
	new	class scala/xml/factory/NodeFactory$$anonfun$makeNode$1
	dup
	aload_0
	aload_1
	aload_2
	aload_3
	aload	4
	aload	5
	invokespecial	Method scala/xml/factory/NodeFactory$$anonfun$makeNode$1."<init>":(Lscala/xml/factory/NodeFactory;Ljava/lang/String;Ljava/lang/String;Lscala/xml/MetaData;Lscala/xml/NamespaceBinding;Lscala/collection/Seq;)V
	invokeinterface	InterfaceMethod scala/collection/LinearSeqLike.find:(Lscala/Function1;)Lscala/Option;
	astore	10
	aload	10
	instanceof	class scala/Some
	ifeq	l3 // iconst_1
	aload	10
	checkcast	class scala/Some
	astore	7
	aload	7
	getfield	Field scala/Some.x:Ljava/lang/Object;
	checkcast	class scala/xml/Node
	astore	8
	iconst_1
	ifeq	l4 // new
	aload	8
	goto	l5 // areturn
l4	new	class scala/MatchError
	dup
	aload	10
	invokevirtual	Method scala/Option.toString:()Ljava/lang/String;
	invokespecial	Method scala/MatchError."<init>":(Ljava/lang/String;)V
	athrow
l3	iconst_1
	ifeq	l6 // new
	aload_0
	aload	9
	aload_1
	aload_2
	aload_3
	aload	4
	aload	5
	iload	11
	invokestatic	Method cons$1:(Lscala/xml/factory/NodeFactory;Lscala/collection/immutable/List;Ljava/lang/String;Ljava/lang/String;Lscala/xml/MetaData;Lscala/xml/NamespaceBinding;Lscala/collection/Seq;I)Lscala/xml/Node;
	goto	l5 // areturn
l6	new	class scala/MatchError
	dup
	aload	10
	invokevirtual	Method scala/Option.toString:()Ljava/lang/String;
	invokespecial	Method scala/MatchError."<init>":(Ljava/lang/String;)V
	athrow
l2	new	class scala/MatchError
	dup
	aload	12
	invokevirtual	Method scala/Option.toString:()Ljava/lang/String;
	invokespecial	Method scala/MatchError."<init>":(Ljava/lang/String;)V
	athrow
l1	getstatic	Field scala/None$.MODULE$:Lscala/None$;
	dup
	ifnonnull	l7 // aload
	pop
	aload	12
	ifnull	l8 // iconst_1
	goto	l9 // new
l7	aload	12
	invokevirtual	Method java/lang/Object.equals:(Ljava/lang/Object;)Z
	ifeq	l9 // new
l8	iconst_1
	ifeq	l10 // new
	aload_0
	getstatic	Field scala/collection/immutable/Nil$.MODULE$:Lscala/collection/immutable/Nil$;
	aload_1
	aload_2
	aload_3
	aload	4
	aload	5
	iload	11
	invokestatic	Method cons$1:(Lscala/xml/factory/NodeFactory;Lscala/collection/immutable/List;Ljava/lang/String;Ljava/lang/String;Lscala/xml/MetaData;Lscala/xml/NamespaceBinding;Lscala/collection/Seq;I)Lscala/xml/Node;
l5	areturn
l10	new	class scala/MatchError
	dup
	aload	12
	invokevirtual	Method scala/Option.toString:()Ljava/lang/String;
	invokespecial	Method scala/MatchError."<init>":(Ljava/lang/String;)V
	athrow
l9	new	class scala/MatchError
	dup
	aload	12
	invokevirtual	Method scala/Option.toString:()Ljava/lang/String;
	invokespecial	Method scala/MatchError."<init>":(Ljava/lang/String;)V
	athrow
  Labels:
   	l4 = 124 // new
   	l3 = 137 // iconst_1
   	l6 = 159 // new
   	l2 = 172 // new
   	l1 = 185 // getstatic
   	l7 = 201 // aload
   	l8 = 209 // iconst_1
   	l5 = 229 // areturn
   	l10 = 230 // new
   	l9 = 243 // new
  LocalVariableTable: 
   Start  Length  Slot  Name   Signature
   0      256      0    $this       Lscala/xml/factory/NodeFactory;
   0      256      1    pre$1       Ljava/lang/String;
   0      256      2    name$1       Ljava/lang/String;
   0      256      3    attrSeq$1       Lscala/xml/MetaData;
   0      256      4    scope$1       Lscala/xml/NamespaceBinding;
   0      256      5    children$1       Lscala/collection/Seq;
   52      133      6    temp8       Lscala/Some;
   105      32      7    temp5       Lscala/Some;
   115      22      8    temp6       Lscala/xml/Node;
   62      123      9    temp9       Lscala/collection/immutable/List;
   90      82      10    temp4       Lscala/Option;
   21      235      11    hash$1       I
   37      219      12    temp7       Lscala/Option;


public static boolean nodeEquals(scala.xml.factory.NodeFactory, scala.xml.Node, java.lang.String, java.lang.String, scala.xml.MetaData, scala.xml.NamespaceBinding, scala.collection.Seq);
  Signature: (Lscala/xml/factory/NodeFactory;Lscala/xml/Node;Ljava/lang/String;Ljava/lang/String;Lscala/xml/MetaData;Lscala/xml/NamespaceBinding;Lscala/collection/Seq;)Z
  Code:
   Stack=3, Locals=7, Args_size=7
	aload_1
	invokevirtual	Method scala/xml/Node.prefix:()Ljava/lang/String;
	dup
	ifnonnull	l1 // aload_2
	pop
	aload_2
	ifnull	l2 // aload_1
	goto	l3 // iconst_0
l1	aload_2
	invokevirtual	Method java/lang/Object.equals:(Ljava/lang/Object;)Z
	ifeq	l3 // iconst_0
l2	aload_1
	invokevirtual	Method scala/xml/Node.label:()Ljava/lang/String;
	dup
	ifnonnull	l4 // aload_3
	pop
	aload_3
	ifnull	l5 // aload_1
	goto	l3 // iconst_0
l4	aload_3
	invokevirtual	Method java/lang/Object.equals:(Ljava/lang/Object;)Z
	ifeq	l3 // iconst_0
l5	aload_1
	invokevirtual	Method scala/xml/Node.attributes:()Lscala/xml/MetaData;
	dup
	ifnonnull	l6 // aload
	pop
	aload	4
	ifnull	l7 // aload_0
	goto	l3 // iconst_0
l6	aload	4
	invokevirtual	Method java/lang/Object.equals:(Ljava/lang/Object;)Z
	ifeq	l3 // iconst_0
l7	aload_0
	aload_1
	invokevirtual	Method scala/xml/Node.child:()Lscala/collection/Seq;
	aload	6
	invokeinterface	InterfaceMethod scala/xml/factory/NodeFactory.eqElements:(Lscala/collection/Seq;Lscala/collection/Seq;)Z
	ifeq	l3 // iconst_0
	iconst_1
	goto	l8 // ireturn
l3	iconst_0
l8	ireturn
  Labels:
   	l1 = 16 // aload_2
   	l2 = 23 // aload_1
   	l4 = 39 // aload_3
   	l5 = 46 // aload_1
   	l6 = 63 // aload
   	l7 = 71 // aload_0
   	l3 = 90 // iconst_0
   	l8 = 91 // ireturn
  LocalVariableTable: 
   Start  Length  Slot  Name   Signature
   0      92      0    $this       Lscala/xml/factory/NodeFactory;
   0      92      1    n       Lscala/xml/Node;
   0      92      2    pre       Ljava/lang/String;
   0      92      3    name       Ljava/lang/String;
   0      92      4    attrSeq       Lscala/xml/MetaData;
   0      92      5    scope       Lscala/xml/NamespaceBinding;
   0      92      6    children       Lscala/collection/Seq;


public static boolean eqElements(scala.xml.factory.NodeFactory, scala.collection.Seq, scala.collection.Seq);
  Signature: (Lscala/xml/factory/NodeFactory;Lscala/collection/Seq;Lscala/collection/Seq;)Z
  Code:
   Stack=5, Locals=3, Args_size=3
	aload_1
	invokeinterface	InterfaceMethod scala/collection/SeqLike.view:()Ljava/lang/Object;
	checkcast	class scala/collection/IterableViewLike
	aload_2
	invokeinterface	InterfaceMethod scala/collection/SeqLike.view:()Ljava/lang/Object;
	checkcast	class scala/collection/Iterable
	aconst_null
	aconst_null
	getstatic	Field scala/collection/SeqView$.MODULE$:Lscala/collection/SeqView$;
	invokevirtual	Method scala/collection/SeqView$.canBuildFrom:()Lscala/collection/generic/CanBuildFrom;
	invokeinterface	InterfaceMethod scala/collection/IterableViewLike.zipAll:(Lscala/collection/Iterable;Ljava/lang/Object;Ljava/lang/Object;Lscala/collection/generic/CanBuildFrom;)Ljava/lang/Object;
	checkcast	class scala/collection/IterableLike
	new	class scala/xml/factory/NodeFactory$$anonfun$eqElements$1
	dup
	aload_0
	invokespecial	Method scala/xml/factory/NodeFactory$$anonfun$eqElements$1."<init>":(Lscala/xml/factory/NodeFactory;)V
	invokeinterface	InterfaceMethod scala/collection/IterableLike.forall:(Lscala/Function1;)Z
	ireturn
  Labels:
  LocalVariableTable: 
   Start  Length  Slot  Name   Signature
   0      48      0    $this       Lscala/xml/factory/NodeFactory;
   0      48      1    ch1       Lscala/collection/Seq;
   0      48      2    ch2       Lscala/collection/Seq;


public static scala.xml.Node construct(scala.xml.factory.NodeFactory, int, scala.collection.immutable.List, java.lang.String, java.lang.String, scala.xml.MetaData, scala.xml.NamespaceBinding, scala.collection.Seq);
  Signature: (Lscala/xml/factory/NodeFactory;ILscala/collection/immutable/List;Ljava/lang/String;Ljava/lang/String;Lscala/xml/MetaData;Lscala/xml/NamespaceBinding;Lscala/collection/Seq;)Lscala/xml/Node;
  Code:
   Stack=6, Locals=9, Args_size=8
	aload_0
	aload_3
	aload	4
	aload	5
	aload	6
	aload	7
	invokeinterface	InterfaceMethod scala/xml/factory/NodeFactory.create:(Ljava/lang/String;Ljava/lang/String;Lscala/xml/MetaData;Lscala/xml/NamespaceBinding;Lscala/collection/Seq;)Lscala/xml/Node;
	astore	8
	aload_0
	invokeinterface	InterfaceMethod scala/xml/factory/NodeFactory.cache:()Lscala/collection/mutable/HashMap;
	iload_1
	invokestatic	Method scala/runtime/BoxesRunTime.boxToInteger:(I)Ljava/lang/Integer;
	aload_2
	aload	8
	invokevirtual	Method scala/collection/immutable/List.$colon$colon:(Ljava/lang/Object;)Lscala/collection/immutable/List;
	invokevirtual	Method scala/collection/mutable/HashMap.update:(Ljava/lang/Object;Ljava/lang/Object;)V
	aload	8
	areturn
  Labels:
  LocalVariableTable: 
   Start  Length  Slot  Name   Signature
   0      39      0    $this       Lscala/xml/factory/NodeFactory;
   0      39      1    hash       I
   0      39      2    old       Lscala/collection/immutable/List;
   0      39      3    pre       Ljava/lang/String;
   0      39      4    name       Ljava/lang/String;
   0      39      5    attrSeq       Lscala/xml/MetaData;
   0      39      6    scope       Lscala/xml/NamespaceBinding;
   0      39      7    children       Lscala/collection/Seq;
   17      21      8    el       Lscala/xml/Node;


}

