Compiled from "NodeFactory.scala"
public final class scala.xml.factory.NodeFactory$$anonfun$makeNode$1 extends java.lang.Object implements scala.Function1,scala.ScalaObject,java.io.Serializable
  SourceFile: "NodeFactory.scala"
  Scala: length = 0x
   
  InnerClass: 
   public final #95= #9 of #72; //$anonfun$makeNode$1=class scala/xml/factory/NodeFactory$$anonfun$makeNode$1 of class scala/xml/factory/NodeFactory
  minor version: 0
  major version: 49
  Constant pool:
const #1 = Asciz	SourceFile;
const #2 = Asciz	NodeFactory.scala;
const #3 = Asciz	<clinit>;
const #4 = Asciz	()V;
const #5 = Asciz	Code;
const #6 = Asciz	serialVersionUID;
const #7 = Asciz	J;
const #8 = Asciz	scala/xml/factory/NodeFactory$$anonfun$makeNode$1;
const #9 = class	#8;	//  scala/xml/factory/NodeFactory$$anonfun$makeNode$1
const #10 = NameAndType	#6:#7;//  serialVersionUID:J
const #11 = Field	#9.#10;	//  scala/xml/factory/NodeFactory$$anonfun$makeNode$1.serialVersionUID:J
const #12 = Asciz	children$1;
const #13 = Asciz	Lscala/collection/Seq;;
const #14 = Asciz	scope$1;
const #15 = Asciz	Lscala/xml/NamespaceBinding;;
const #16 = Asciz	attrSeq$1;
const #17 = Asciz	Lscala/xml/MetaData;;
const #18 = Asciz	name$1;
const #19 = Asciz	Ljava/lang/String;;
const #20 = Asciz	pre$1;
const #21 = Asciz	$outer;
const #22 = Asciz	Lscala/xml/factory/NodeFactory;;
const #23 = Asciz	<init>;
const #24 = Asciz	(Lscala/xml/factory/NodeFactory;Ljava/lang/String;Ljava/lang/String;Lscala/xml/MetaData;Lscala/xml/NamespaceBinding;Lscala/collection/Seq;)V;
const #25 = Asciz	LineNumberTable;
const #26 = Asciz	java/lang/NullPointerException;
const #27 = class	#26;	//  java/lang/NullPointerException
const #28 = NameAndType	#23:#4;//  "<init>":()V
const #29 = Method	#27.#28;	//  java/lang/NullPointerException."<init>":()V
const #30 = NameAndType	#21:#22;//  $outer:Lscala/xml/factory/NodeFactory;
const #31 = Field	#9.#30;	//  scala/xml/factory/NodeFactory$$anonfun$makeNode$1.$outer:Lscala/xml/factory/NodeFactory;
const #32 = NameAndType	#20:#19;//  pre$1:Ljava/lang/String;
const #33 = Field	#9.#32;	//  scala/xml/factory/NodeFactory$$anonfun$makeNode$1.pre$1:Ljava/lang/String;
const #34 = NameAndType	#18:#19;//  name$1:Ljava/lang/String;
const #35 = Field	#9.#34;	//  scala/xml/factory/NodeFactory$$anonfun$makeNode$1.name$1:Ljava/lang/String;
const #36 = NameAndType	#16:#17;//  attrSeq$1:Lscala/xml/MetaData;
const #37 = Field	#9.#36;	//  scala/xml/factory/NodeFactory$$anonfun$makeNode$1.attrSeq$1:Lscala/xml/MetaData;
const #38 = NameAndType	#14:#15;//  scope$1:Lscala/xml/NamespaceBinding;
const #39 = Field	#9.#38;	//  scala/xml/factory/NodeFactory$$anonfun$makeNode$1.scope$1:Lscala/xml/NamespaceBinding;
const #40 = NameAndType	#12:#13;//  children$1:Lscala/collection/Seq;
const #41 = Field	#9.#40;	//  scala/xml/factory/NodeFactory$$anonfun$makeNode$1.children$1:Lscala/collection/Seq;
const #42 = Asciz	java/lang/Object;
const #43 = class	#42;	//  java/lang/Object
const #44 = Method	#43.#28;	//  java/lang/Object."<init>":()V
const #45 = Asciz	scala/Function1$class;
const #46 = class	#45;	//  scala/Function1$class
const #47 = Asciz	$init$;
const #48 = Asciz	(Lscala/Function1;)V;
const #49 = NameAndType	#47:#48;//  $init$:(Lscala/Function1;)V
const #50 = Method	#46.#49;	//  scala/Function1$class.$init$:(Lscala/Function1;)V
const #51 = Asciz	this;
const #52 = Asciz	Lscala/xml/factory/NodeFactory$$anonfun$makeNode$1;;
const #53 = Asciz	LocalVariableTable;
const #54 = Asciz	(Lscala/xml/factory/NodeFactory<TA;>;)V;
const #55 = Asciz	Signature;
const #56 = Asciz	apply;
const #57 = Asciz	(Ljava/lang/Object;)Ljava/lang/Object;;
const #58 = Asciz	scala/xml/Node;
const #59 = class	#58;	//  scala/xml/Node
const #60 = Asciz	(Lscala/xml/Node;)Z;
const #61 = NameAndType	#56:#60;//  apply:(Lscala/xml/Node;)Z
const #62 = Method	#9.#61;	//  scala/xml/factory/NodeFactory$$anonfun$makeNode$1.apply:(Lscala/xml/Node;)Z
const #63 = Asciz	scala/runtime/BoxesRunTime;
const #64 = class	#63;	//  scala/runtime/BoxesRunTime
const #65 = Asciz	boxToBoolean;
const #66 = Asciz	(Z)Ljava/lang/Boolean;;
const #67 = NameAndType	#65:#66;//  boxToBoolean:(Z)Ljava/lang/Boolean;
const #68 = Method	#64.#67;	//  scala/runtime/BoxesRunTime.boxToBoolean:(Z)Ljava/lang/Boolean;
const #69 = Asciz	v1;
const #70 = Asciz	Ljava/lang/Object;;
const #71 = Asciz	scala/xml/factory/NodeFactory;
const #72 = class	#71;	//  scala/xml/factory/NodeFactory
const #73 = Asciz	nodeEquals;
const #74 = Asciz	(Lscala/xml/Node;Ljava/lang/String;Ljava/lang/String;Lscala/xml/MetaData;Lscala/xml/NamespaceBinding;Lscala/collection/Seq;)Z;
const #75 = NameAndType	#73:#74;//  nodeEquals:(Lscala/xml/Node;Ljava/lang/String;Ljava/lang/String;Lscala/xml/MetaData;Lscala/xml/NamespaceBinding;Lscala/collection/Seq;)Z
const #76 = InterfaceMethod	#72.#75;	//  scala/xml/factory/NodeFactory.nodeEquals:(Lscala/xml/Node;Ljava/lang/String;Ljava/lang/String;Lscala/xml/MetaData;Lscala/xml/NamespaceBinding;Lscala/collection/Seq;)Z
const #77 = Asciz	(TA;)Z;
const #78 = Asciz	andThen;
const #79 = Asciz	(Lscala/Function1;)Lscala/Function1;;
const #80 = Asciz	(Lscala/Function1;Lscala/Function1;)Lscala/Function1;;
const #81 = NameAndType	#78:#80;//  andThen:(Lscala/Function1;Lscala/Function1;)Lscala/Function1;
const #82 = Method	#46.#81;	//  scala/Function1$class.andThen:(Lscala/Function1;Lscala/Function1;)Lscala/Function1;
const #83 = Asciz	g;
const #84 = Asciz	Lscala/Function1;;
const #85 = Asciz	compose;
const #86 = NameAndType	#85:#80;//  compose:(Lscala/Function1;Lscala/Function1;)Lscala/Function1;
const #87 = Method	#46.#86;	//  scala/Function1$class.compose:(Lscala/Function1;Lscala/Function1;)Lscala/Function1;
const #88 = Asciz	toString;
const #89 = Asciz	()Ljava/lang/String;;
const #90 = Asciz	(Lscala/Function1;)Ljava/lang/String;;
const #91 = NameAndType	#88:#90;//  toString:(Lscala/Function1;)Ljava/lang/String;
const #92 = Method	#46.#91;	//  scala/Function1$class.toString:(Lscala/Function1;)Ljava/lang/String;
const #93 = Asciz	Scala;
const #94 = Asciz	InnerClasses;
const #95 = Asciz	$anonfun$makeNode$1;
const #96 = Asciz	scala/Function1;
const #97 = class	#96;	//  scala/Function1
const #98 = Asciz	scala/ScalaObject;
const #99 = class	#98;	//  scala/ScalaObject
const #100 = Asciz	java/io/Serializable;
const #101 = class	#100;	//  java/io/Serializable

{
public static final long serialVersionUID;

public static {};
  Code:
   Stack=2, Locals=0, Args_size=0
   0:	lconst_0
   1:	putstatic	#11; //Field serialVersionUID:J
   4:	return

public scala.xml.factory.NodeFactory$$anonfun$makeNode$1(scala.xml.factory.NodeFactory, java.lang.String, java.lang.String, scala.xml.MetaData, scala.xml.NamespaceBinding, scala.collection.Seq);
  Code:
   Stack=2, Locals=7, Args_size=7
   0:	aload_1
   1:	ifnonnull	12
   4:	new	#27; //class java/lang/NullPointerException
   7:	dup
   8:	invokespecial	#29; //Method java/lang/NullPointerException."<init>":()V
   11:	athrow
   12:	aload_0
   13:	aload_1
   14:	putfield	#31; //Field $outer:Lscala/xml/factory/NodeFactory;
   17:	aload_0
   18:	aload_2
   19:	putfield	#33; //Field pre$1:Ljava/lang/String;
   22:	aload_0
   23:	aload_3
   24:	putfield	#35; //Field name$1:Ljava/lang/String;
   27:	aload_0
   28:	aload	4
   30:	putfield	#37; //Field attrSeq$1:Lscala/xml/MetaData;
   33:	aload_0
   34:	aload	5
   36:	putfield	#39; //Field scope$1:Lscala/xml/NamespaceBinding;
   39:	aload_0
   40:	aload	6
   42:	putfield	#41; //Field children$1:Lscala/collection/Seq;
   45:	aload_0
   46:	invokespecial	#44; //Method java/lang/Object."<init>":()V
   49:	aload_0
   50:	invokestatic	#50; //Method scala/Function1$class.$init$:(Lscala/Function1;)V
   53:	return
  LineNumberTable: 
   line 53: 0

  LocalVariableTable: 
   Start  Length  Slot  Name   Signature
   0      54      0    this       Lscala/xml/factory/NodeFactory$$anonfun$makeNode$1;
   0      54      1    $outer       Lscala/xml/factory/NodeFactory;

  Signature: length = 0x2
   00 36 

public final java.lang.Object apply(java.lang.Object);
  Code:
   Stack=2, Locals=4, Args_size=2
   0:	aload_0
   1:	getfield	#31; //Field $outer:Lscala/xml/factory/NodeFactory;
   4:	astore_3
   5:	aload_0
   6:	aload_1
   7:	checkcast	#59; //class scala/xml/Node
   10:	invokevirtual	#62; //Method apply:(Lscala/xml/Node;)Z
   13:	istore_2
   14:	iload_2
   15:	invokestatic	#68; //Method scala/runtime/BoxesRunTime.boxToBoolean:(Z)Ljava/lang/Boolean;
   18:	areturn
  LineNumberTable: 
   line 53: 0

  LocalVariableTable: 
   Start  Length  Slot  Name   Signature
   0      19      0    this       Lscala/xml/factory/NodeFactory$$anonfun$makeNode$1;
   5      14      1    v1       Ljava/lang/Object;


public final boolean apply(scala.xml.Node);
  Code:
   Stack=7, Locals=3, Args_size=2
   0:	aload_0
   1:	getfield	#31; //Field $outer:Lscala/xml/factory/NodeFactory;
   4:	astore_2
   5:	aload_0
   6:	getfield	#31; //Field $outer:Lscala/xml/factory/NodeFactory;
   9:	aload_1
   10:	aload_0
   11:	getfield	#33; //Field pre$1:Ljava/lang/String;
   14:	aload_0
   15:	getfield	#35; //Field name$1:Ljava/lang/String;
   18:	aload_0
   19:	getfield	#37; //Field attrSeq$1:Lscala/xml/MetaData;
   22:	aload_0
   23:	getfield	#39; //Field scope$1:Lscala/xml/NamespaceBinding;
   26:	aload_0
   27:	getfield	#41; //Field children$1:Lscala/collection/Seq;
   30:	invokeinterface	#76,  7; //InterfaceMethod scala/xml/factory/NodeFactory.nodeEquals:(Lscala/xml/Node;Ljava/lang/String;Ljava/lang/String;Lscala/xml/MetaData;Lscala/xml/NamespaceBinding;Lscala/collection/Seq;)Z
   35:	ireturn
  LineNumberTable: 
   line 53: 0

  LocalVariableTable: 
   Start  Length  Slot  Name   Signature
   0      36      0    this       Lscala/xml/factory/NodeFactory$$anonfun$makeNode$1;

  Signature: length = 0x2
   00 4D 

public scala.Function1 andThen(scala.Function1);
  Code:
   Stack=2, Locals=2, Args_size=2
   0:	aload_0
   1:	aload_1
   2:	invokestatic	#82; //Method scala/Function1$class.andThen:(Lscala/Function1;Lscala/Function1;)Lscala/Function1;
   5:	areturn
  LineNumberTable: 
   line 53: 0

  LocalVariableTable: 
   Start  Length  Slot  Name   Signature
   0      6      0    this       Lscala/xml/factory/NodeFactory$$anonfun$makeNode$1;
   0      6      1    g       Lscala/Function1;


public scala.Function1 compose(scala.Function1);
  Code:
   Stack=2, Locals=2, Args_size=2
   0:	aload_0
   1:	aload_1
   2:	invokestatic	#87; //Method scala/Function1$class.compose:(Lscala/Function1;Lscala/Function1;)Lscala/Function1;
   5:	areturn
  LineNumberTable: 
   line 53: 0

  LocalVariableTable: 
   Start  Length  Slot  Name   Signature
   0      6      0    this       Lscala/xml/factory/NodeFactory$$anonfun$makeNode$1;
   0      6      1    g       Lscala/Function1;


public java.lang.String toString();
  Code:
   Stack=1, Locals=1, Args_size=1
   0:	aload_0
   1:	invokestatic	#92; //Method scala/Function1$class.toString:(Lscala/Function1;)Ljava/lang/String;
   4:	areturn
  LineNumberTable: 
   line 53: 0


}

