Compiled from "XMLLoader.scala"
public abstract class scala.xml.factory.XMLLoader$class extends java.lang.Object
  SourceFile: "XMLLoader.scala"
  Scala: length = 0x
   
  minor version: 0
  major version: 49
  Constant pool:
const #1 = Asciz	SourceFile;
const #2 = Asciz	XMLLoader.scala;
const #3 = Asciz	$init$;
const #4 = Asciz	(Lscala/xml/factory/XMLLoader;)V;
const #5 = Asciz	Code;
const #6 = Asciz	LineNumberTable;
const #7 = Asciz	javax/xml/parsers/SAXParserFactory;
const #8 = class	#7;	//  javax/xml/parsers/SAXParserFactory
const #9 = Asciz	newInstance;
const #10 = Asciz	()Ljavax/xml/parsers/SAXParserFactory;;
const #11 = NameAndType	#9:#10;//  newInstance:()Ljavax/xml/parsers/SAXParserFactory;
const #12 = Method	#8.#11;	//  javax/xml/parsers/SAXParserFactory.newInstance:()Ljavax/xml/parsers/SAXParserFactory;
const #13 = Asciz	setNamespaceAware;
const #14 = Asciz	(Z)V;
const #15 = NameAndType	#13:#14;//  setNamespaceAware:(Z)V
const #16 = Method	#8.#15;	//  javax/xml/parsers/SAXParserFactory.setNamespaceAware:(Z)V
const #17 = Asciz	http://apache.org/xml/features/nonvalidating/load-external-dtd;
const #18 = String	#17;	//  http://apache.org/xml/features/nonvalidating/load-external-dtd
const #19 = Asciz	setFeature;
const #20 = Asciz	(Ljava/lang/String;Z)V;
const #21 = NameAndType	#19:#20;//  setFeature:(Ljava/lang/String;Z)V
const #22 = Method	#8.#21;	//  javax/xml/parsers/SAXParserFactory.setFeature:(Ljava/lang/String;Z)V
const #23 = Asciz	scala/xml/factory/XMLLoader;
const #24 = class	#23;	//  scala/xml/factory/XMLLoader
const #25 = Asciz	scala$xml$factory$XMLLoader$_setter_$scala$xml$factory$XMLLoader$$saxFactory_$eq;
const #26 = Asciz	(Ljavax/xml/parsers/SAXParserFactory;)V;
const #27 = NameAndType	#25:#26;//  scala$xml$factory$XMLLoader$_setter_$scala$xml$factory$XMLLoader$$saxFactory_$eq:(Ljavax/xml/parsers/SAXParserFactory;)V
const #28 = InterfaceMethod	#24.#27;	//  scala/xml/factory/XMLLoader.scala$xml$factory$XMLLoader$_setter_$scala$xml$factory$XMLLoader$$saxFactory_$eq:(Ljavax/xml/parsers/SAXParserFactory;)V
const #29 = Asciz	$this;
const #30 = Asciz	Lscala/xml/factory/XMLLoader;;
const #31 = Asciz	f;
const #32 = Asciz	Ljavax/xml/parsers/SAXParserFactory;;
const #33 = Asciz	LocalVariableTable;
const #34 = Asciz	loadString;
const #35 = Asciz	(Lscala/xml/factory/XMLLoader;Ljava/lang/String;)Lscala/xml/Node;;
const #36 = Asciz	scala/xml/Source$;
const #37 = class	#36;	//  scala/xml/Source$
const #38 = Asciz	MODULE$;
const #39 = Asciz	Lscala/xml/Source$;;
const #40 = NameAndType	#38:#39;//  MODULE$:Lscala/xml/Source$;
const #41 = Field	#37.#40;	//  scala/xml/Source$.MODULE$:Lscala/xml/Source$;
const #42 = Asciz	fromString;
const #43 = Asciz	(Ljava/lang/String;)Lorg/xml/sax/InputSource;;
const #44 = NameAndType	#42:#43;//  fromString:(Ljava/lang/String;)Lorg/xml/sax/InputSource;
const #45 = Method	#37.#44;	//  scala/xml/Source$.fromString:(Ljava/lang/String;)Lorg/xml/sax/InputSource;
const #46 = Asciz	parser;
const #47 = Asciz	()Ljavax/xml/parsers/SAXParser;;
const #48 = NameAndType	#46:#47;//  parser:()Ljavax/xml/parsers/SAXParser;
const #49 = InterfaceMethod	#24.#48;	//  scala/xml/factory/XMLLoader.parser:()Ljavax/xml/parsers/SAXParser;
const #50 = Asciz	loadXML;
const #51 = Asciz	(Lorg/xml/sax/InputSource;Ljavax/xml/parsers/SAXParser;)Lscala/xml/Node;;
const #52 = NameAndType	#50:#51;//  loadXML:(Lorg/xml/sax/InputSource;Ljavax/xml/parsers/SAXParser;)Lscala/xml/Node;
const #53 = InterfaceMethod	#24.#52;	//  scala/xml/factory/XMLLoader.loadXML:(Lorg/xml/sax/InputSource;Ljavax/xml/parsers/SAXParser;)Lscala/xml/Node;
const #54 = Asciz	string;
const #55 = Asciz	Ljava/lang/String;;
const #56 = Asciz	load;
const #57 = Asciz	(Lscala/xml/factory/XMLLoader;Lorg/xml/sax/InputSource;)Lscala/xml/Node;;
const #58 = Asciz	source;
const #59 = Asciz	Lorg/xml/sax/InputSource;;
const #60 = Asciz	fromSysId;
const #61 = NameAndType	#60:#43;//  fromSysId:(Ljava/lang/String;)Lorg/xml/sax/InputSource;
const #62 = Method	#37.#61;	//  scala/xml/Source$.fromSysId:(Ljava/lang/String;)Lorg/xml/sax/InputSource;
const #63 = Asciz	sysID;
const #64 = Asciz	(Lscala/xml/factory/XMLLoader;Ljava/io/Reader;)Lscala/xml/Node;;
const #65 = Asciz	fromReader;
const #66 = Asciz	(Ljava/io/Reader;)Lorg/xml/sax/InputSource;;
const #67 = NameAndType	#65:#66;//  fromReader:(Ljava/io/Reader;)Lorg/xml/sax/InputSource;
const #68 = Method	#37.#67;	//  scala/xml/Source$.fromReader:(Ljava/io/Reader;)Lorg/xml/sax/InputSource;
const #69 = Asciz	reader;
const #70 = Asciz	Ljava/io/Reader;;
const #71 = Asciz	(Lscala/xml/factory/XMLLoader;Ljava/io/InputStream;)Lscala/xml/Node;;
const #72 = Asciz	fromInputStream;
const #73 = Asciz	(Ljava/io/InputStream;)Lorg/xml/sax/InputSource;;
const #74 = NameAndType	#72:#73;//  fromInputStream:(Ljava/io/InputStream;)Lorg/xml/sax/InputSource;
const #75 = Method	#37.#74;	//  scala/xml/Source$.fromInputStream:(Ljava/io/InputStream;)Lorg/xml/sax/InputSource;
const #76 = Asciz	is;
const #77 = Asciz	Ljava/io/InputStream;;
const #78 = Asciz	loadFile;
const #79 = Asciz	fromFile;
const #80 = NameAndType	#79:#43;//  fromFile:(Ljava/lang/String;)Lorg/xml/sax/InputSource;
const #81 = Method	#37.#80;	//  scala/xml/Source$.fromFile:(Ljava/lang/String;)Lorg/xml/sax/InputSource;
const #82 = Asciz	name;
const #83 = Asciz	(Lscala/xml/factory/XMLLoader;Ljava/io/FileDescriptor;)Lscala/xml/Node;;
const #84 = Asciz	(Ljava/io/FileDescriptor;)Lorg/xml/sax/InputSource;;
const #85 = NameAndType	#79:#84;//  fromFile:(Ljava/io/FileDescriptor;)Lorg/xml/sax/InputSource;
const #86 = Method	#37.#85;	//  scala/xml/Source$.fromFile:(Ljava/io/FileDescriptor;)Lorg/xml/sax/InputSource;
const #87 = Asciz	fd;
const #88 = Asciz	Ljava/io/FileDescriptor;;
const #89 = Asciz	(Lscala/xml/factory/XMLLoader;Ljava/io/File;)Lscala/xml/Node;;
const #90 = Asciz	(Ljava/io/File;)Lorg/xml/sax/InputSource;;
const #91 = NameAndType	#79:#90;//  fromFile:(Ljava/io/File;)Lorg/xml/sax/InputSource;
const #92 = Method	#37.#91;	//  scala/xml/Source$.fromFile:(Ljava/io/File;)Lorg/xml/sax/InputSource;
const #93 = Asciz	file;
const #94 = Asciz	Ljava/io/File;;
const #95 = Asciz	(Lscala/xml/factory/XMLLoader;Lorg/xml/sax/InputSource;Ljavax/xml/parsers/SAXParser;)Lscala/xml/Node;;
const #96 = Asciz	adapter;
const #97 = Asciz	()Lscala/xml/parsing/FactoryAdapter;;
const #98 = NameAndType	#96:#97;//  adapter:()Lscala/xml/parsing/FactoryAdapter;
const #99 = InterfaceMethod	#24.#98;	//  scala/xml/factory/XMLLoader.adapter:()Lscala/xml/parsing/FactoryAdapter;
const #100 = Asciz	scala/xml/parsing/FactoryAdapter;
const #101 = class	#100;	//  scala/xml/parsing/FactoryAdapter
const #102 = Asciz	scopeStack;
const #103 = Asciz	()Lscala/collection/mutable/Stack;;
const #104 = NameAndType	#102:#103;//  scopeStack:()Lscala/collection/mutable/Stack;
const #105 = Method	#101.#104;	//  scala/xml/parsing/FactoryAdapter.scopeStack:()Lscala/collection/mutable/Stack;
const #106 = Asciz	scala/xml/TopScope$;
const #107 = class	#106;	//  scala/xml/TopScope$
const #108 = Asciz	Lscala/xml/TopScope$;;
const #109 = NameAndType	#38:#108;//  MODULE$:Lscala/xml/TopScope$;
const #110 = Field	#107.#109;	//  scala/xml/TopScope$.MODULE$:Lscala/xml/TopScope$;
const #111 = Asciz	scala/collection/mutable/Stack;
const #112 = class	#111;	//  scala/collection/mutable/Stack
const #113 = Asciz	push;
const #114 = Asciz	(Ljava/lang/Object;)Lscala/collection/mutable/Stack;;
const #115 = NameAndType	#113:#114;//  push:(Ljava/lang/Object;)Lscala/collection/mutable/Stack;
const #116 = Method	#112.#115;	//  scala/collection/mutable/Stack.push:(Ljava/lang/Object;)Lscala/collection/mutable/Stack;
const #117 = Asciz	javax/xml/parsers/SAXParser;
const #118 = class	#117;	//  javax/xml/parsers/SAXParser
const #119 = Asciz	parse;
const #120 = Asciz	(Lorg/xml/sax/InputSource;Lorg/xml/sax/helpers/DefaultHandler;)V;
const #121 = NameAndType	#119:#120;//  parse:(Lorg/xml/sax/InputSource;Lorg/xml/sax/helpers/DefaultHandler;)V
const #122 = Method	#118.#121;	//  javax/xml/parsers/SAXParser.parse:(Lorg/xml/sax/InputSource;Lorg/xml/sax/helpers/DefaultHandler;)V
const #123 = Asciz	pop;
const #124 = Asciz	()Ljava/lang/Object;;
const #125 = NameAndType	#123:#124;//  pop:()Ljava/lang/Object;
const #126 = Method	#112.#125;	//  scala/collection/mutable/Stack.pop:()Ljava/lang/Object;
const #127 = Asciz	rootElem;
const #128 = Asciz	()Lscala/xml/Node;;
const #129 = NameAndType	#127:#128;//  rootElem:()Lscala/xml/Node;
const #130 = Method	#101.#129;	//  scala/xml/parsing/FactoryAdapter.rootElem:()Lscala/xml/Node;
const #131 = Asciz	Ljavax/xml/parsers/SAXParser;;
const #132 = Asciz	newAdapter;
const #133 = Asciz	Lscala/xml/parsing/FactoryAdapter;;
const #134 = Asciz	(Lscala/xml/factory/XMLLoader;)Ljavax/xml/parsers/SAXParser;;
const #135 = Asciz	scala$xml$factory$XMLLoader$$saxFactory;
const #136 = NameAndType	#135:#10;//  scala$xml$factory$XMLLoader$$saxFactory:()Ljavax/xml/parsers/SAXParserFactory;
const #137 = InterfaceMethod	#24.#136;	//  scala/xml/factory/XMLLoader.scala$xml$factory$XMLLoader$$saxFactory:()Ljavax/xml/parsers/SAXParserFactory;
const #138 = Asciz	newSAXParser;
const #139 = NameAndType	#138:#47;//  newSAXParser:()Ljavax/xml/parsers/SAXParser;
const #140 = Method	#8.#139;	//  javax/xml/parsers/SAXParserFactory.newSAXParser:()Ljavax/xml/parsers/SAXParser;
const #141 = Asciz	(Lscala/xml/factory/XMLLoader;)Lscala/xml/parsing/FactoryAdapter;;
const #142 = Asciz	scala/xml/parsing/NoBindingFactoryAdapter;
const #143 = class	#142;	//  scala/xml/parsing/NoBindingFactoryAdapter
const #144 = Asciz	<init>;
const #145 = Asciz	()V;
const #146 = NameAndType	#144:#145;//  "<init>":()V
const #147 = Method	#143.#146;	//  scala/xml/parsing/NoBindingFactoryAdapter."<init>":()V
const #148 = Asciz	Scala;
const #149 = Asciz	scala/xml/factory/XMLLoader$class;
const #150 = class	#149;	//  scala/xml/factory/XMLLoader$class
const #151 = Asciz	java/lang/Object;
const #152 = class	#151;	//  java/lang/Object

{
public static void $init$(scala.xml.factory.XMLLoader);
  Code:
   Stack=4, Locals=2, Args_size=1
   0:	aload_0
   1:	invokestatic	#12; //Method javax/xml/parsers/SAXParserFactory.newInstance:()Ljavax/xml/parsers/SAXParserFactory;
   4:	astore_1
   5:	aload_1
   6:	iconst_0
   7:	invokevirtual	#16; //Method javax/xml/parsers/SAXParserFactory.setNamespaceAware:(Z)V
   10:	aload_1
   11:	ldc	#18; //String http://apache.org/xml/features/nonvalidating/load-external-dtd
   13:	iconst_0
   14:	invokevirtual	#22; //Method javax/xml/parsers/SAXParserFactory.setFeature:(Ljava/lang/String;Z)V
   17:	aload_1
   18:	invokeinterface	#28,  2; //InterfaceMethod scala/xml/factory/XMLLoader.scala$xml$factory$XMLLoader$_setter_$scala$xml$factory$XMLLoader$$saxFactory_$eq:(Ljavax/xml/parsers/SAXParserFactory;)V
   23:	return
  LineNumberTable: 
   line 27: 0
   line 28: 1
   line 29: 5
   line 31: 10
   line 32: 17
   line 27: 18

  LocalVariableTable: 
   Start  Length  Slot  Name   Signature
   0      24      0    $this       Lscala/xml/factory/XMLLoader;
   5      13      1    f       Ljavax/xml/parsers/SAXParserFactory;


public static scala.xml.Node loadString(scala.xml.factory.XMLLoader, java.lang.String);
  Code:
   Stack=3, Locals=2, Args_size=2
   0:	aload_0
   1:	getstatic	#41; //Field scala/xml/Source$.MODULE$:Lscala/xml/Source$;
   4:	aload_1
   5:	invokevirtual	#45; //Method scala/xml/Source$.fromString:(Ljava/lang/String;)Lorg/xml/sax/InputSource;
   8:	aload_0
   9:	invokeinterface	#49,  1; //InterfaceMethod scala/xml/factory/XMLLoader.parser:()Ljavax/xml/parsers/SAXParser;
   14:	invokeinterface	#53,  3; //InterfaceMethod scala/xml/factory/XMLLoader.loadXML:(Lorg/xml/sax/InputSource;Ljavax/xml/parsers/SAXParser;)Lscala/xml/Node;
   19:	areturn
  LineNumberTable: 
   line 63: 0

  LocalVariableTable: 
   Start  Length  Slot  Name   Signature
   0      20      0    $this       Lscala/xml/factory/XMLLoader;
   0      20      1    string       Ljava/lang/String;


public static scala.xml.Node load(scala.xml.factory.XMLLoader, org.xml.sax.InputSource);
  Code:
   Stack=3, Locals=2, Args_size=2
   0:	aload_0
   1:	aload_1
   2:	aload_0
   3:	invokeinterface	#49,  1; //InterfaceMethod scala/xml/factory/XMLLoader.parser:()Ljavax/xml/parsers/SAXParser;
   8:	invokeinterface	#53,  3; //InterfaceMethod scala/xml/factory/XMLLoader.loadXML:(Lorg/xml/sax/InputSource;Ljavax/xml/parsers/SAXParser;)Lscala/xml/Node;
   13:	areturn
  LineNumberTable: 
   line 60: 0

  LocalVariableTable: 
   Start  Length  Slot  Name   Signature
   0      14      0    $this       Lscala/xml/factory/XMLLoader;
   0      14      1    source       Lorg/xml/sax/InputSource;


public static scala.xml.Node load(scala.xml.factory.XMLLoader, java.lang.String);
  Code:
   Stack=3, Locals=2, Args_size=2
   0:	aload_0
   1:	getstatic	#41; //Field scala/xml/Source$.MODULE$:Lscala/xml/Source$;
   4:	aload_1
   5:	invokevirtual	#62; //Method scala/xml/Source$.fromSysId:(Ljava/lang/String;)Lorg/xml/sax/InputSource;
   8:	aload_0
   9:	invokeinterface	#49,  1; //InterfaceMethod scala/xml/factory/XMLLoader.parser:()Ljavax/xml/parsers/SAXParser;
   14:	invokeinterface	#53,  3; //InterfaceMethod scala/xml/factory/XMLLoader.loadXML:(Lorg/xml/sax/InputSource;Ljavax/xml/parsers/SAXParser;)Lscala/xml/Node;
   19:	areturn
  LineNumberTable: 
   line 59: 0

  LocalVariableTable: 
   Start  Length  Slot  Name   Signature
   0      20      0    $this       Lscala/xml/factory/XMLLoader;
   0      20      1    sysID       Ljava/lang/String;


public static scala.xml.Node load(scala.xml.factory.XMLLoader, java.io.Reader);
  Code:
   Stack=3, Locals=2, Args_size=2
   0:	aload_0
   1:	getstatic	#41; //Field scala/xml/Source$.MODULE$:Lscala/xml/Source$;
   4:	aload_1
   5:	invokevirtual	#68; //Method scala/xml/Source$.fromReader:(Ljava/io/Reader;)Lorg/xml/sax/InputSource;
   8:	aload_0
   9:	invokeinterface	#49,  1; //InterfaceMethod scala/xml/factory/XMLLoader.parser:()Ljavax/xml/parsers/SAXParser;
   14:	invokeinterface	#53,  3; //InterfaceMethod scala/xml/factory/XMLLoader.loadXML:(Lorg/xml/sax/InputSource;Ljavax/xml/parsers/SAXParser;)Lscala/xml/Node;
   19:	areturn
  LineNumberTable: 
   line 58: 0

  LocalVariableTable: 
   Start  Length  Slot  Name   Signature
   0      20      0    $this       Lscala/xml/factory/XMLLoader;
   0      20      1    reader       Ljava/io/Reader;


public static scala.xml.Node load(scala.xml.factory.XMLLoader, java.io.InputStream);
  Code:
   Stack=3, Locals=2, Args_size=2
   0:	aload_0
   1:	getstatic	#41; //Field scala/xml/Source$.MODULE$:Lscala/xml/Source$;
   4:	aload_1
   5:	invokevirtual	#75; //Method scala/xml/Source$.fromInputStream:(Ljava/io/InputStream;)Lorg/xml/sax/InputSource;
   8:	aload_0
   9:	invokeinterface	#49,  1; //InterfaceMethod scala/xml/factory/XMLLoader.parser:()Ljavax/xml/parsers/SAXParser;
   14:	invokeinterface	#53,  3; //InterfaceMethod scala/xml/factory/XMLLoader.loadXML:(Lorg/xml/sax/InputSource;Ljavax/xml/parsers/SAXParser;)Lscala/xml/Node;
   19:	areturn
  LineNumberTable: 
   line 57: 0

  LocalVariableTable: 
   Start  Length  Slot  Name   Signature
   0      20      0    $this       Lscala/xml/factory/XMLLoader;
   0      20      1    is       Ljava/io/InputStream;


public static scala.xml.Node loadFile(scala.xml.factory.XMLLoader, java.lang.String);
  Code:
   Stack=3, Locals=2, Args_size=2
   0:	aload_0
   1:	getstatic	#41; //Field scala/xml/Source$.MODULE$:Lscala/xml/Source$;
   4:	aload_1
   5:	invokevirtual	#81; //Method scala/xml/Source$.fromFile:(Ljava/lang/String;)Lorg/xml/sax/InputSource;
   8:	aload_0
   9:	invokeinterface	#49,  1; //InterfaceMethod scala/xml/factory/XMLLoader.parser:()Ljavax/xml/parsers/SAXParser;
   14:	invokeinterface	#53,  3; //InterfaceMethod scala/xml/factory/XMLLoader.loadXML:(Lorg/xml/sax/InputSource;Ljavax/xml/parsers/SAXParser;)Lscala/xml/Node;
   19:	areturn
  LineNumberTable: 
   line 54: 0

  LocalVariableTable: 
   Start  Length  Slot  Name   Signature
   0      20      0    $this       Lscala/xml/factory/XMLLoader;
   0      20      1    name       Ljava/lang/String;


public static scala.xml.Node loadFile(scala.xml.factory.XMLLoader, java.io.FileDescriptor);
  Code:
   Stack=3, Locals=2, Args_size=2
   0:	aload_0
   1:	getstatic	#41; //Field scala/xml/Source$.MODULE$:Lscala/xml/Source$;
   4:	aload_1
   5:	invokevirtual	#86; //Method scala/xml/Source$.fromFile:(Ljava/io/FileDescriptor;)Lorg/xml/sax/InputSource;
   8:	aload_0
   9:	invokeinterface	#49,  1; //InterfaceMethod scala/xml/factory/XMLLoader.parser:()Ljavax/xml/parsers/SAXParser;
   14:	invokeinterface	#53,  3; //InterfaceMethod scala/xml/factory/XMLLoader.loadXML:(Lorg/xml/sax/InputSource;Ljavax/xml/parsers/SAXParser;)Lscala/xml/Node;
   19:	areturn
  LineNumberTable: 
   line 53: 0

  LocalVariableTable: 
   Start  Length  Slot  Name   Signature
   0      20      0    $this       Lscala/xml/factory/XMLLoader;
   0      20      1    fd       Ljava/io/FileDescriptor;


public static scala.xml.Node loadFile(scala.xml.factory.XMLLoader, java.io.File);
  Code:
   Stack=3, Locals=2, Args_size=2
   0:	aload_0
   1:	getstatic	#41; //Field scala/xml/Source$.MODULE$:Lscala/xml/Source$;
   4:	aload_1
   5:	invokevirtual	#92; //Method scala/xml/Source$.fromFile:(Ljava/io/File;)Lorg/xml/sax/InputSource;
   8:	aload_0
   9:	invokeinterface	#49,  1; //InterfaceMethod scala/xml/factory/XMLLoader.parser:()Ljavax/xml/parsers/SAXParser;
   14:	invokeinterface	#53,  3; //InterfaceMethod scala/xml/factory/XMLLoader.loadXML:(Lorg/xml/sax/InputSource;Ljavax/xml/parsers/SAXParser;)Lscala/xml/Node;
   19:	areturn
  LineNumberTable: 
   line 52: 0

  LocalVariableTable: 
   Start  Length  Slot  Name   Signature
   0      20      0    $this       Lscala/xml/factory/XMLLoader;
   0      20      1    file       Ljava/io/File;


public static scala.xml.Node loadXML(scala.xml.factory.XMLLoader, org.xml.sax.InputSource, javax.xml.parsers.SAXParser);
  Code:
   Stack=3, Locals=4, Args_size=3
   0:	aload_0
   1:	invokeinterface	#99,  1; //InterfaceMethod scala/xml/factory/XMLLoader.adapter:()Lscala/xml/parsing/FactoryAdapter;
   6:	astore_3
   7:	aload_3
   8:	invokevirtual	#105; //Method scala/xml/parsing/FactoryAdapter.scopeStack:()Lscala/collection/mutable/Stack;
   11:	getstatic	#110; //Field scala/xml/TopScope$.MODULE$:Lscala/xml/TopScope$;
   14:	invokevirtual	#116; //Method scala/collection/mutable/Stack.push:(Ljava/lang/Object;)Lscala/collection/mutable/Stack;
   17:	pop
   18:	aload_2
   19:	aload_1
   20:	aload_3
   21:	invokevirtual	#122; //Method javax/xml/parsers/SAXParser.parse:(Lorg/xml/sax/InputSource;Lorg/xml/sax/helpers/DefaultHandler;)V
   24:	aload_3
   25:	invokevirtual	#105; //Method scala/xml/parsing/FactoryAdapter.scopeStack:()Lscala/collection/mutable/Stack;
   28:	invokevirtual	#126; //Method scala/collection/mutable/Stack.pop:()Ljava/lang/Object;
   31:	pop
   32:	aload_3
   33:	invokevirtual	#130; //Method scala/xml/parsing/FactoryAdapter.rootElem:()Lscala/xml/Node;
   36:	areturn
  LineNumberTable: 
   line 42: 0
   line 44: 7
   line 45: 18
   line 46: 24
   line 48: 32

  LocalVariableTable: 
   Start  Length  Slot  Name   Signature
   0      37      0    $this       Lscala/xml/factory/XMLLoader;
   0      37      1    source       Lorg/xml/sax/InputSource;
   0      37      2    parser       Ljavax/xml/parsers/SAXParser;
   7      29      3    newAdapter       Lscala/xml/parsing/FactoryAdapter;


public static javax.xml.parsers.SAXParser parser(scala.xml.factory.XMLLoader);
  Code:
   Stack=1, Locals=1, Args_size=1
   0:	aload_0
   1:	invokeinterface	#137,  1; //InterfaceMethod scala/xml/factory/XMLLoader.scala$xml$factory$XMLLoader$$saxFactory:()Ljavax/xml/parsers/SAXParserFactory;
   6:	invokevirtual	#140; //Method javax/xml/parsers/SAXParserFactory.newSAXParser:()Ljavax/xml/parsers/SAXParser;
   9:	areturn
  LineNumberTable: 
   line 36: 0

  LocalVariableTable: 
   Start  Length  Slot  Name   Signature
   0      10      0    $this       Lscala/xml/factory/XMLLoader;


public static scala.xml.parsing.FactoryAdapter adapter(scala.xml.factory.XMLLoader);
  Code:
   Stack=2, Locals=1, Args_size=1
   0:	new	#143; //class scala/xml/parsing/NoBindingFactoryAdapter
   3:	dup
   4:	invokespecial	#147; //Method scala/xml/parsing/NoBindingFactoryAdapter."<init>":()V
   7:	areturn
  LineNumberTable: 
   line 25: 0

  LocalVariableTable: 
   Start  Length  Slot  Name   Signature
   0      8      0    $this       Lscala/xml/factory/XMLLoader;


}

