Compiled from "XMLLoader.scala"
public abstract class scala.xml.factory.XMLLoader$class extends java.lang.Object
  SourceFile: "XMLLoader.scala"
  Scala: length = 0x
   
  minor version: 0
  major version: 49
  Constant pool:
Asciz	SourceFile;
Asciz	XMLLoader.scala;
Asciz	$init$;
Asciz	(Lscala/xml/factory/XMLLoader;)V;
Asciz	Code;
Asciz	LineNumberTable;
Asciz	javax/xml/parsers/SAXParserFactory;
class	javax/xml/parsers/SAXParserFactory
Asciz	newInstance;
Asciz	()Ljavax/xml/parsers/SAXParserFactory;;
NameAndType	newInstance:()Ljavax/xml/parsers/SAXParserFactory;
Method	javax/xml/parsers/SAXParserFactory.newInstance:()Ljavax/xml/parsers/SAXParserFactory;
Asciz	setNamespaceAware;
Asciz	(Z)V;
NameAndType	setNamespaceAware:(Z)V
Method	javax/xml/parsers/SAXParserFactory.setNamespaceAware:(Z)V
Asciz	http://apache.org/xml/features/nonvalidating/load-external-dtd;
String	http://apache.org/xml/features/nonvalidating/load-external-dtd
Asciz	setFeature;
Asciz	(Ljava/lang/String;Z)V;
NameAndType	setFeature:(Ljava/lang/String;Z)V
Method	javax/xml/parsers/SAXParserFactory.setFeature:(Ljava/lang/String;Z)V
Asciz	scala/xml/factory/XMLLoader;
class	scala/xml/factory/XMLLoader
Asciz	scala$xml$factory$XMLLoader$_setter_$scala$xml$factory$XMLLoader$$saxFactory_$eq;
Asciz	(Ljavax/xml/parsers/SAXParserFactory;)V;
NameAndType	scala$xml$factory$XMLLoader$_setter_$scala$xml$factory$XMLLoader$$saxFactory_$eq:(Ljavax/xml/parsers/SAXParserFactory;)V
InterfaceMethod	scala/xml/factory/XMLLoader.scala$xml$factory$XMLLoader$_setter_$scala$xml$factory$XMLLoader$$saxFactory_$eq:(Ljavax/xml/parsers/SAXParserFactory;)V
Asciz	$this;
Asciz	Lscala/xml/factory/XMLLoader;;
Asciz	f;
Asciz	Ljavax/xml/parsers/SAXParserFactory;;
Asciz	LocalVariableTable;
Asciz	loadString;
Asciz	(Lscala/xml/factory/XMLLoader;Ljava/lang/String;)Lscala/xml/Node;;
Asciz	scala/xml/Source$;
class	scala/xml/Source$
Asciz	MODULE$;
Asciz	Lscala/xml/Source$;;
NameAndType	MODULE$:Lscala/xml/Source$;
Field	scala/xml/Source$.MODULE$:Lscala/xml/Source$;
Asciz	fromString;
Asciz	(Ljava/lang/String;)Lorg/xml/sax/InputSource;;
NameAndType	fromString:(Ljava/lang/String;)Lorg/xml/sax/InputSource;
Method	scala/xml/Source$.fromString:(Ljava/lang/String;)Lorg/xml/sax/InputSource;
Asciz	parser;
Asciz	()Ljavax/xml/parsers/SAXParser;;
NameAndType	parser:()Ljavax/xml/parsers/SAXParser;
InterfaceMethod	scala/xml/factory/XMLLoader.parser:()Ljavax/xml/parsers/SAXParser;
Asciz	loadXML;
Asciz	(Lorg/xml/sax/InputSource;Ljavax/xml/parsers/SAXParser;)Lscala/xml/Node;;
NameAndType	loadXML:(Lorg/xml/sax/InputSource;Ljavax/xml/parsers/SAXParser;)Lscala/xml/Node;
InterfaceMethod	scala/xml/factory/XMLLoader.loadXML:(Lorg/xml/sax/InputSource;Ljavax/xml/parsers/SAXParser;)Lscala/xml/Node;
Asciz	string;
Asciz	Ljava/lang/String;;
Asciz	load;
Asciz	(Lscala/xml/factory/XMLLoader;Lorg/xml/sax/InputSource;)Lscala/xml/Node;;
Asciz	source;
Asciz	Lorg/xml/sax/InputSource;;
Asciz	fromSysId;
NameAndType	fromSysId:(Ljava/lang/String;)Lorg/xml/sax/InputSource;
Method	scala/xml/Source$.fromSysId:(Ljava/lang/String;)Lorg/xml/sax/InputSource;
Asciz	sysID;
Asciz	(Lscala/xml/factory/XMLLoader;Ljava/io/Reader;)Lscala/xml/Node;;
Asciz	fromReader;
Asciz	(Ljava/io/Reader;)Lorg/xml/sax/InputSource;;
NameAndType	fromReader:(Ljava/io/Reader;)Lorg/xml/sax/InputSource;
Method	scala/xml/Source$.fromReader:(Ljava/io/Reader;)Lorg/xml/sax/InputSource;
Asciz	reader;
Asciz	Ljava/io/Reader;;
Asciz	(Lscala/xml/factory/XMLLoader;Ljava/io/InputStream;)Lscala/xml/Node;;
Asciz	fromInputStream;
Asciz	(Ljava/io/InputStream;)Lorg/xml/sax/InputSource;;
NameAndType	fromInputStream:(Ljava/io/InputStream;)Lorg/xml/sax/InputSource;
Method	scala/xml/Source$.fromInputStream:(Ljava/io/InputStream;)Lorg/xml/sax/InputSource;
Asciz	is;
Asciz	Ljava/io/InputStream;;
Asciz	loadFile;
Asciz	fromFile;
NameAndType	fromFile:(Ljava/lang/String;)Lorg/xml/sax/InputSource;
Method	scala/xml/Source$.fromFile:(Ljava/lang/String;)Lorg/xml/sax/InputSource;
Asciz	name;
Asciz	(Lscala/xml/factory/XMLLoader;Ljava/io/FileDescriptor;)Lscala/xml/Node;;
Asciz	(Ljava/io/FileDescriptor;)Lorg/xml/sax/InputSource;;
NameAndType	fromFile:(Ljava/io/FileDescriptor;)Lorg/xml/sax/InputSource;
Method	scala/xml/Source$.fromFile:(Ljava/io/FileDescriptor;)Lorg/xml/sax/InputSource;
Asciz	fd;
Asciz	Ljava/io/FileDescriptor;;
Asciz	(Lscala/xml/factory/XMLLoader;Ljava/io/File;)Lscala/xml/Node;;
Asciz	(Ljava/io/File;)Lorg/xml/sax/InputSource;;
NameAndType	fromFile:(Ljava/io/File;)Lorg/xml/sax/InputSource;
Method	scala/xml/Source$.fromFile:(Ljava/io/File;)Lorg/xml/sax/InputSource;
Asciz	file;
Asciz	Ljava/io/File;;
Asciz	(Lscala/xml/factory/XMLLoader;Lorg/xml/sax/InputSource;Ljavax/xml/parsers/SAXParser;)Lscala/xml/Node;;
Asciz	adapter;
Asciz	()Lscala/xml/parsing/FactoryAdapter;;
NameAndType	adapter:()Lscala/xml/parsing/FactoryAdapter;
InterfaceMethod	scala/xml/factory/XMLLoader.adapter:()Lscala/xml/parsing/FactoryAdapter;
Asciz	scala/xml/parsing/FactoryAdapter;
class	scala/xml/parsing/FactoryAdapter
Asciz	scopeStack;
Asciz	()Lscala/collection/mutable/Stack;;
NameAndType	scopeStack:()Lscala/collection/mutable/Stack;
Method	scala/xml/parsing/FactoryAdapter.scopeStack:()Lscala/collection/mutable/Stack;
Asciz	scala/xml/TopScope$;
class	scala/xml/TopScope$
Asciz	Lscala/xml/TopScope$;;
NameAndType	MODULE$:Lscala/xml/TopScope$;
Field	scala/xml/TopScope$.MODULE$:Lscala/xml/TopScope$;
Asciz	scala/collection/mutable/Stack;
class	scala/collection/mutable/Stack
Asciz	push;
Asciz	(Ljava/lang/Object;)Lscala/collection/mutable/Stack;;
NameAndType	push:(Ljava/lang/Object;)Lscala/collection/mutable/Stack;
Method	scala/collection/mutable/Stack.push:(Ljava/lang/Object;)Lscala/collection/mutable/Stack;
Asciz	javax/xml/parsers/SAXParser;
class	javax/xml/parsers/SAXParser
Asciz	parse;
Asciz	(Lorg/xml/sax/InputSource;Lorg/xml/sax/helpers/DefaultHandler;)V;
NameAndType	parse:(Lorg/xml/sax/InputSource;Lorg/xml/sax/helpers/DefaultHandler;)V
Method	javax/xml/parsers/SAXParser.parse:(Lorg/xml/sax/InputSource;Lorg/xml/sax/helpers/DefaultHandler;)V
Asciz	pop;
Asciz	()Ljava/lang/Object;;
NameAndType	pop:()Ljava/lang/Object;
Method	scala/collection/mutable/Stack.pop:()Ljava/lang/Object;
Asciz	rootElem;
Asciz	()Lscala/xml/Node;;
NameAndType	rootElem:()Lscala/xml/Node;
Method	scala/xml/parsing/FactoryAdapter.rootElem:()Lscala/xml/Node;
Asciz	Ljavax/xml/parsers/SAXParser;;
Asciz	newAdapter;
Asciz	Lscala/xml/parsing/FactoryAdapter;;
Asciz	(Lscala/xml/factory/XMLLoader;)Ljavax/xml/parsers/SAXParser;;
Asciz	scala$xml$factory$XMLLoader$$saxFactory;
NameAndType	scala$xml$factory$XMLLoader$$saxFactory:()Ljavax/xml/parsers/SAXParserFactory;
InterfaceMethod	scala/xml/factory/XMLLoader.scala$xml$factory$XMLLoader$$saxFactory:()Ljavax/xml/parsers/SAXParserFactory;
Asciz	newSAXParser;
NameAndType	newSAXParser:()Ljavax/xml/parsers/SAXParser;
Method	javax/xml/parsers/SAXParserFactory.newSAXParser:()Ljavax/xml/parsers/SAXParser;
Asciz	(Lscala/xml/factory/XMLLoader;)Lscala/xml/parsing/FactoryAdapter;;
Asciz	scala/xml/parsing/NoBindingFactoryAdapter;
class	scala/xml/parsing/NoBindingFactoryAdapter
Asciz	<init>;
Asciz	()V;
NameAndType	"<init>":()V
Method	scala/xml/parsing/NoBindingFactoryAdapter."<init>":()V
Asciz	Scala;
Asciz	scala/xml/factory/XMLLoader$class;
class	scala/xml/factory/XMLLoader$class
Asciz	java/lang/Object;
class	java/lang/Object

{
public static void $init$(scala.xml.factory.XMLLoader);
  Signature: (Lscala/xml/factory/XMLLoader;)V
  Code:
   Stack=4, Locals=2, Args_size=1
	aload_0
	invokestatic	Method javax/xml/parsers/SAXParserFactory.newInstance:()Ljavax/xml/parsers/SAXParserFactory;
	astore_1
	aload_1
	iconst_0
	invokevirtual	Method javax/xml/parsers/SAXParserFactory.setNamespaceAware:(Z)V
	aload_1
	ldc	String http://apache.org/xml/features/nonvalidating/load-external-dtd
	iconst_0
	invokevirtual	Method javax/xml/parsers/SAXParserFactory.setFeature:(Ljava/lang/String;Z)V
	aload_1
	invokeinterface	InterfaceMethod scala/xml/factory/XMLLoader.scala$xml$factory$XMLLoader$_setter_$scala$xml$factory$XMLLoader$$saxFactory_$eq:(Ljavax/xml/parsers/SAXParserFactory;)V
	return
  Labels:
  LocalVariableTable: 
   Start  Length  Slot  Name   Signature
   0      24      0    $this       Lscala/xml/factory/XMLLoader;
   5      13      1    f       Ljavax/xml/parsers/SAXParserFactory;


public static scala.xml.Node loadString(scala.xml.factory.XMLLoader, java.lang.String);
  Signature: (Lscala/xml/factory/XMLLoader;Ljava/lang/String;)Lscala/xml/Node;
  Code:
   Stack=3, Locals=2, Args_size=2
	aload_0
	getstatic	Field scala/xml/Source$.MODULE$:Lscala/xml/Source$;
	aload_1
	invokevirtual	Method scala/xml/Source$.fromString:(Ljava/lang/String;)Lorg/xml/sax/InputSource;
	aload_0
	invokeinterface	InterfaceMethod scala/xml/factory/XMLLoader.parser:()Ljavax/xml/parsers/SAXParser;
	invokeinterface	InterfaceMethod scala/xml/factory/XMLLoader.loadXML:(Lorg/xml/sax/InputSource;Ljavax/xml/parsers/SAXParser;)Lscala/xml/Node;
	areturn
  Labels:
  LocalVariableTable: 
   Start  Length  Slot  Name   Signature
   0      20      0    $this       Lscala/xml/factory/XMLLoader;
   0      20      1    string       Ljava/lang/String;


public static scala.xml.Node load(scala.xml.factory.XMLLoader, org.xml.sax.InputSource);
  Signature: (Lscala/xml/factory/XMLLoader;Lorg/xml/sax/InputSource;)Lscala/xml/Node;
  Code:
   Stack=3, Locals=2, Args_size=2
	aload_0
	aload_1
	aload_0
	invokeinterface	InterfaceMethod scala/xml/factory/XMLLoader.parser:()Ljavax/xml/parsers/SAXParser;
	invokeinterface	InterfaceMethod scala/xml/factory/XMLLoader.loadXML:(Lorg/xml/sax/InputSource;Ljavax/xml/parsers/SAXParser;)Lscala/xml/Node;
	areturn
  Labels:
  LocalVariableTable: 
   Start  Length  Slot  Name   Signature
   0      14      0    $this       Lscala/xml/factory/XMLLoader;
   0      14      1    source       Lorg/xml/sax/InputSource;


public static scala.xml.Node load(scala.xml.factory.XMLLoader, java.lang.String);
  Signature: (Lscala/xml/factory/XMLLoader;Ljava/lang/String;)Lscala/xml/Node;
  Code:
   Stack=3, Locals=2, Args_size=2
	aload_0
	getstatic	Field scala/xml/Source$.MODULE$:Lscala/xml/Source$;
	aload_1
	invokevirtual	Method scala/xml/Source$.fromSysId:(Ljava/lang/String;)Lorg/xml/sax/InputSource;
	aload_0
	invokeinterface	InterfaceMethod scala/xml/factory/XMLLoader.parser:()Ljavax/xml/parsers/SAXParser;
	invokeinterface	InterfaceMethod scala/xml/factory/XMLLoader.loadXML:(Lorg/xml/sax/InputSource;Ljavax/xml/parsers/SAXParser;)Lscala/xml/Node;
	areturn
  Labels:
  LocalVariableTable: 
   Start  Length  Slot  Name   Signature
   0      20      0    $this       Lscala/xml/factory/XMLLoader;
   0      20      1    sysID       Ljava/lang/String;


public static scala.xml.Node load(scala.xml.factory.XMLLoader, java.io.Reader);
  Signature: (Lscala/xml/factory/XMLLoader;Ljava/io/Reader;)Lscala/xml/Node;
  Code:
   Stack=3, Locals=2, Args_size=2
	aload_0
	getstatic	Field scala/xml/Source$.MODULE$:Lscala/xml/Source$;
	aload_1
	invokevirtual	Method scala/xml/Source$.fromReader:(Ljava/io/Reader;)Lorg/xml/sax/InputSource;
	aload_0
	invokeinterface	InterfaceMethod scala/xml/factory/XMLLoader.parser:()Ljavax/xml/parsers/SAXParser;
	invokeinterface	InterfaceMethod scala/xml/factory/XMLLoader.loadXML:(Lorg/xml/sax/InputSource;Ljavax/xml/parsers/SAXParser;)Lscala/xml/Node;
	areturn
  Labels:
  LocalVariableTable: 
   Start  Length  Slot  Name   Signature
   0      20      0    $this       Lscala/xml/factory/XMLLoader;
   0      20      1    reader       Ljava/io/Reader;


public static scala.xml.Node load(scala.xml.factory.XMLLoader, java.io.InputStream);
  Signature: (Lscala/xml/factory/XMLLoader;Ljava/io/InputStream;)Lscala/xml/Node;
  Code:
   Stack=3, Locals=2, Args_size=2
	aload_0
	getstatic	Field scala/xml/Source$.MODULE$:Lscala/xml/Source$;
	aload_1
	invokevirtual	Method scala/xml/Source$.fromInputStream:(Ljava/io/InputStream;)Lorg/xml/sax/InputSource;
	aload_0
	invokeinterface	InterfaceMethod scala/xml/factory/XMLLoader.parser:()Ljavax/xml/parsers/SAXParser;
	invokeinterface	InterfaceMethod scala/xml/factory/XMLLoader.loadXML:(Lorg/xml/sax/InputSource;Ljavax/xml/parsers/SAXParser;)Lscala/xml/Node;
	areturn
  Labels:
  LocalVariableTable: 
   Start  Length  Slot  Name   Signature
   0      20      0    $this       Lscala/xml/factory/XMLLoader;
   0      20      1    is       Ljava/io/InputStream;


public static scala.xml.Node loadFile(scala.xml.factory.XMLLoader, java.lang.String);
  Signature: (Lscala/xml/factory/XMLLoader;Ljava/lang/String;)Lscala/xml/Node;
  Code:
   Stack=3, Locals=2, Args_size=2
	aload_0
	getstatic	Field scala/xml/Source$.MODULE$:Lscala/xml/Source$;
	aload_1
	invokevirtual	Method scala/xml/Source$.fromFile:(Ljava/lang/String;)Lorg/xml/sax/InputSource;
	aload_0
	invokeinterface	InterfaceMethod scala/xml/factory/XMLLoader.parser:()Ljavax/xml/parsers/SAXParser;
	invokeinterface	InterfaceMethod scala/xml/factory/XMLLoader.loadXML:(Lorg/xml/sax/InputSource;Ljavax/xml/parsers/SAXParser;)Lscala/xml/Node;
	areturn
  Labels:
  LocalVariableTable: 
   Start  Length  Slot  Name   Signature
   0      20      0    $this       Lscala/xml/factory/XMLLoader;
   0      20      1    name       Ljava/lang/String;


public static scala.xml.Node loadFile(scala.xml.factory.XMLLoader, java.io.FileDescriptor);
  Signature: (Lscala/xml/factory/XMLLoader;Ljava/io/FileDescriptor;)Lscala/xml/Node;
  Code:
   Stack=3, Locals=2, Args_size=2
	aload_0
	getstatic	Field scala/xml/Source$.MODULE$:Lscala/xml/Source$;
	aload_1
	invokevirtual	Method scala/xml/Source$.fromFile:(Ljava/io/FileDescriptor;)Lorg/xml/sax/InputSource;
	aload_0
	invokeinterface	InterfaceMethod scala/xml/factory/XMLLoader.parser:()Ljavax/xml/parsers/SAXParser;
	invokeinterface	InterfaceMethod scala/xml/factory/XMLLoader.loadXML:(Lorg/xml/sax/InputSource;Ljavax/xml/parsers/SAXParser;)Lscala/xml/Node;
	areturn
  Labels:
  LocalVariableTable: 
   Start  Length  Slot  Name   Signature
   0      20      0    $this       Lscala/xml/factory/XMLLoader;
   0      20      1    fd       Ljava/io/FileDescriptor;


public static scala.xml.Node loadFile(scala.xml.factory.XMLLoader, java.io.File);
  Signature: (Lscala/xml/factory/XMLLoader;Ljava/io/File;)Lscala/xml/Node;
  Code:
   Stack=3, Locals=2, Args_size=2
	aload_0
	getstatic	Field scala/xml/Source$.MODULE$:Lscala/xml/Source$;
	aload_1
	invokevirtual	Method scala/xml/Source$.fromFile:(Ljava/io/File;)Lorg/xml/sax/InputSource;
	aload_0
	invokeinterface	InterfaceMethod scala/xml/factory/XMLLoader.parser:()Ljavax/xml/parsers/SAXParser;
	invokeinterface	InterfaceMethod scala/xml/factory/XMLLoader.loadXML:(Lorg/xml/sax/InputSource;Ljavax/xml/parsers/SAXParser;)Lscala/xml/Node;
	areturn
  Labels:
  LocalVariableTable: 
   Start  Length  Slot  Name   Signature
   0      20      0    $this       Lscala/xml/factory/XMLLoader;
   0      20      1    file       Ljava/io/File;


public static scala.xml.Node loadXML(scala.xml.factory.XMLLoader, org.xml.sax.InputSource, javax.xml.parsers.SAXParser);
  Signature: (Lscala/xml/factory/XMLLoader;Lorg/xml/sax/InputSource;Ljavax/xml/parsers/SAXParser;)Lscala/xml/Node;
  Code:
   Stack=3, Locals=4, Args_size=3
	aload_0
	invokeinterface	InterfaceMethod scala/xml/factory/XMLLoader.adapter:()Lscala/xml/parsing/FactoryAdapter;
	astore_3
	aload_3
	invokevirtual	Method scala/xml/parsing/FactoryAdapter.scopeStack:()Lscala/collection/mutable/Stack;
	getstatic	Field scala/xml/TopScope$.MODULE$:Lscala/xml/TopScope$;
	invokevirtual	Method scala/collection/mutable/Stack.push:(Ljava/lang/Object;)Lscala/collection/mutable/Stack;
	pop
	aload_2
	aload_1
	aload_3
	invokevirtual	Method javax/xml/parsers/SAXParser.parse:(Lorg/xml/sax/InputSource;Lorg/xml/sax/helpers/DefaultHandler;)V
	aload_3
	invokevirtual	Method scala/xml/parsing/FactoryAdapter.scopeStack:()Lscala/collection/mutable/Stack;
	invokevirtual	Method scala/collection/mutable/Stack.pop:()Ljava/lang/Object;
	pop
	aload_3
	invokevirtual	Method scala/xml/parsing/FactoryAdapter.rootElem:()Lscala/xml/Node;
	areturn
  Labels:
  LocalVariableTable: 
   Start  Length  Slot  Name   Signature
   0      37      0    $this       Lscala/xml/factory/XMLLoader;
   0      37      1    source       Lorg/xml/sax/InputSource;
   0      37      2    parser       Ljavax/xml/parsers/SAXParser;
   7      29      3    newAdapter       Lscala/xml/parsing/FactoryAdapter;


public static javax.xml.parsers.SAXParser parser(scala.xml.factory.XMLLoader);
  Signature: (Lscala/xml/factory/XMLLoader;)Ljavax/xml/parsers/SAXParser;
  Code:
   Stack=1, Locals=1, Args_size=1
	aload_0
	invokeinterface	InterfaceMethod scala/xml/factory/XMLLoader.scala$xml$factory$XMLLoader$$saxFactory:()Ljavax/xml/parsers/SAXParserFactory;
	invokevirtual	Method javax/xml/parsers/SAXParserFactory.newSAXParser:()Ljavax/xml/parsers/SAXParser;
	areturn
  Labels:
  LocalVariableTable: 
   Start  Length  Slot  Name   Signature
   0      10      0    $this       Lscala/xml/factory/XMLLoader;


public static scala.xml.parsing.FactoryAdapter adapter(scala.xml.factory.XMLLoader);
  Signature: (Lscala/xml/factory/XMLLoader;)Lscala/xml/parsing/FactoryAdapter;
  Code:
   Stack=2, Locals=1, Args_size=1
	new	class scala/xml/parsing/NoBindingFactoryAdapter
	dup
	invokespecial	Method scala/xml/parsing/NoBindingFactoryAdapter."<init>":()V
	areturn
  Labels:
  LocalVariableTable: 
   Start  Length  Slot  Name   Signature
   0      8      0    $this       Lscala/xml/factory/XMLLoader;


}

