Compiled from "DelayedLazyVal.scala"
public final class scala.concurrent.DelayedLazyVal$$anonfun$1 extends scala.runtime.AbstractFunction0 implements java.io.Serializable
  SourceFile: "DelayedLazyVal.scala"
  Scala: length = 0x
   
  InnerClass: 
   public final $anonfun$1=class scala/concurrent/DelayedLazyVal$$anonfun$1 of class scala/concurrent/DelayedLazyVal
  minor version: 0
  major version: 49
  Constant pool:
Asciz	SourceFile;
Asciz	DelayedLazyVal.scala;
Asciz	<clinit>;
Asciz	()V;
Asciz	Code;
Asciz	serialVersionUID;
Asciz	J;
Asciz	scala/concurrent/DelayedLazyVal$$anonfun$1;
class	scala/concurrent/DelayedLazyVal$$anonfun$1
NameAndType	serialVersionUID:J
Field	scala/concurrent/DelayedLazyVal$$anonfun$1.serialVersionUID:J
Asciz	$outer;
Asciz	Lscala/concurrent/DelayedLazyVal;;
Asciz	apply;
Asciz	LineNumberTable;
NameAndType	$outer:Lscala/concurrent/DelayedLazyVal;
Field	scala/concurrent/DelayedLazyVal$$anonfun$1.$outer:Lscala/concurrent/DelayedLazyVal;
Asciz	scala/concurrent/DelayedLazyVal;
class	scala/concurrent/DelayedLazyVal
Asciz	scala$concurrent$DelayedLazyVal$$body;
Asciz	Lscala/Function0;;
NameAndType	scala$concurrent$DelayedLazyVal$$body:Lscala/Function0;
Field	scala/concurrent/DelayedLazyVal.scala$concurrent$DelayedLazyVal$$body:Lscala/Function0;
Asciz	scala/Function0;
class	scala/Function0
Asciz	()Ljava/lang/Object;;
NameAndType	apply:()Ljava/lang/Object;
InterfaceMethod	scala/Function0.apply:()Ljava/lang/Object;
Asciz	scala$concurrent$DelayedLazyVal$$_isDone;
Asciz	Z;
NameAndType	scala$concurrent$DelayedLazyVal$$_isDone:Z
Field	scala/concurrent/DelayedLazyVal.scala$concurrent$DelayedLazyVal$$_isDone:Z
NameAndType	apply:()V
Method	scala/concurrent/DelayedLazyVal$$anonfun$1.apply:()V
Asciz	scala/runtime/BoxedUnit;
class	scala/runtime/BoxedUnit
Asciz	UNIT;
Asciz	Lscala/runtime/BoxedUnit;;
NameAndType	UNIT:Lscala/runtime/BoxedUnit;
Field	scala/runtime/BoxedUnit.UNIT:Lscala/runtime/BoxedUnit;
Asciz	<init>;
Asciz	(Lscala/concurrent/DelayedLazyVal;)V;
Asciz	java/lang/NullPointerException;
class	java/lang/NullPointerException
NameAndType	"<init>":()V
Method	java/lang/NullPointerException."<init>":()V
Asciz	scala/runtime/AbstractFunction0;
class	scala/runtime/AbstractFunction0
Method	scala/runtime/AbstractFunction0."<init>":()V
Asciz	this;
Asciz	Lscala/concurrent/DelayedLazyVal$$anonfun$1;;
Asciz	LocalVariableTable;
Asciz	(Lscala/concurrent/DelayedLazyVal<TT;>;)V;
Asciz	Signature;
Asciz	Scala;
Asciz	InnerClasses;
Asciz	$anonfun$1;
Asciz	java/io/Serializable;
class	java/io/Serializable

{
public static final long serialVersionUID;
  Signature: J

private final scala.concurrent.DelayedLazyVal $outer;
  Signature: Lscala/concurrent/DelayedLazyVal;

public static {};
  Signature: ()V
  Code:
   Stack=2, Locals=0, Args_size=0
	lconst_0
	putstatic	Field serialVersionUID:J
	return
  Labels:

public final void apply();
  Signature: ()V
  Code:
   Stack=2, Locals=1, Args_size=1
	aload_0
	getfield	Field $outer:Lscala/concurrent/DelayedLazyVal;
	getfield	Field scala/concurrent/DelayedLazyVal.scala$concurrent$DelayedLazyVal$$body:Lscala/Function0;
	invokeinterface	InterfaceMethod scala/Function0.apply:()Ljava/lang/Object;
	pop
	aload_0
	getfield	Field $outer:Lscala/concurrent/DelayedLazyVal;
	iconst_1
	putfield	Field scala/concurrent/DelayedLazyVal.scala$concurrent$DelayedLazyVal$$_isDone:Z
	return
  Labels:

public final java.lang.Object apply();
  Signature: ()Ljava/lang/Object;
  Code:
   Stack=1, Locals=1, Args_size=1
	aload_0
	invokevirtual	Method apply:()V
	getstatic	Field scala/runtime/BoxedUnit.UNIT:Lscala/runtime/BoxedUnit;
	areturn
  Labels:

public scala.concurrent.DelayedLazyVal$$anonfun$1(scala.concurrent.DelayedLazyVal);
  Signature: (Lscala/concurrent/DelayedLazyVal;)V
  Code:
   Stack=2, Locals=2, Args_size=2
	aload_1
	ifnonnull	l1 // aload_0
	new	class java/lang/NullPointerException
	dup
	invokespecial	Method java/lang/NullPointerException."<init>":()V
	athrow
l1	aload_0
	aload_1
	putfield	Field $outer:Lscala/concurrent/DelayedLazyVal;
	aload_0
	invokespecial	Method scala/runtime/AbstractFunction0."<init>":()V
	return
  Labels:
   	l1 = 12 // aload_0
  LocalVariableTable: 
   Start  Length  Slot  Name   Signature
   0      22      0    this       Lscala/concurrent/DelayedLazyVal$$anonfun$1;
   0      22      1    $outer       Lscala/concurrent/DelayedLazyVal;

  Signature: length = 0x2
   00 35 

}

