Compiled from "DelayedLazyVal.scala"
public final class scala.concurrent.DelayedLazyVal$$anonfun$3 extends java.lang.Object implements scala.Function0,scala.ScalaObject,java.io.Serializable
  SourceFile: "DelayedLazyVal.scala"
  Scala: length = 0x
   
  InnerClass: 
   public final $anonfun$3=class scala/concurrent/DelayedLazyVal$$anonfun$3 of class scala/concurrent/DelayedLazyVal
  minor version: 0
  major version: 49
  Constant pool:
Asciz	SourceFile;
Asciz	DelayedLazyVal.scala;
Asciz	<clinit>;
Asciz	()V;
Asciz	Code;
Asciz	serialVersionUID;
Asciz	J;
Asciz	scala/concurrent/DelayedLazyVal$$anonfun$3;
class	scala/concurrent/DelayedLazyVal$$anonfun$3
NameAndType	serialVersionUID:J
Field	scala/concurrent/DelayedLazyVal$$anonfun$3.serialVersionUID:J
Asciz	x$1$1;
Asciz	Lscala/Function0;;
Asciz	<init>;
Asciz	(Lscala/concurrent/DelayedLazyVal;Lscala/Function0;)V;
Asciz	LineNumberTable;
NameAndType	x$1$1:Lscala/Function0;
Field	scala/concurrent/DelayedLazyVal$$anonfun$3.x$1$1:Lscala/Function0;
Asciz	java/lang/Object;
class	java/lang/Object
NameAndType	"<init>":()V
Method	java/lang/Object."<init>":()V
Asciz	scala/Function0$class;
class	scala/Function0$class
Asciz	$init$;
Asciz	(Lscala/Function0;)V;
NameAndType	$init$:(Lscala/Function0;)V
Method	scala/Function0$class.$init$:(Lscala/Function0;)V
Asciz	this;
Asciz	Lscala/concurrent/DelayedLazyVal$$anonfun$3;;
Asciz	$outer;
Asciz	Lscala/concurrent/DelayedLazyVal;;
Asciz	LocalVariableTable;
Asciz	(Lscala/concurrent/DelayedLazyVal<TT;>;)V;
Asciz	Signature;
Asciz	apply;
Asciz	()Ljava/lang/Object;;
NameAndType	apply:()V
Method	scala/concurrent/DelayedLazyVal$$anonfun$3.apply:()V
Asciz	scala/runtime/BoxedUnit;
class	scala/runtime/BoxedUnit
Asciz	UNIT;
Asciz	Lscala/runtime/BoxedUnit;;
NameAndType	UNIT:Lscala/runtime/BoxedUnit;
Field	scala/runtime/BoxedUnit.UNIT:Lscala/runtime/BoxedUnit;
Asciz	scala/Function0;
class	scala/Function0
NameAndType	apply:()Ljava/lang/Object;
InterfaceMethod	scala/Function0.apply:()Ljava/lang/Object;
Asciz	toString;
Asciz	()Ljava/lang/String;;
Asciz	(Lscala/Function0;)Ljava/lang/String;;
NameAndType	toString:(Lscala/Function0;)Ljava/lang/String;
Method	scala/Function0$class.toString:(Lscala/Function0;)Ljava/lang/String;
Asciz	Scala;
Asciz	InnerClasses;
Asciz	scala/concurrent/DelayedLazyVal;
class	scala/concurrent/DelayedLazyVal
Asciz	$anonfun$3;
Asciz	scala/ScalaObject;
class	scala/ScalaObject
Asciz	java/io/Serializable;
class	java/io/Serializable

{
public static final long serialVersionUID;
  Signature: J

private final scala.Function0 x$1$1;
  Signature: Lscala/Function0;

public static {};
  Signature: ()V
  Code:
   Stack=2, Locals=0, Args_size=0
	lconst_0
	putstatic	Field serialVersionUID:J
	return
  Labels:

public scala.concurrent.DelayedLazyVal$$anonfun$3(scala.concurrent.DelayedLazyVal, scala.Function0);
  Signature: (Lscala/concurrent/DelayedLazyVal;Lscala/Function0;)V
  Code:
   Stack=2, Locals=3, Args_size=3
	aload_0
	aload_2
	putfield	Field x$1$1:Lscala/Function0;
	aload_0
	invokespecial	Method java/lang/Object."<init>":()V
	aload_0
	invokestatic	Method scala/Function0$class.$init$:(Lscala/Function0;)V
	return
  Labels:
  LocalVariableTable: 
   Start  Length  Slot  Name   Signature
   0      14      0    this       Lscala/concurrent/DelayedLazyVal$$anonfun$3;
   0      14      1    $outer       Lscala/concurrent/DelayedLazyVal;

  Signature: length = 0x2
   00 22 

public final java.lang.Object apply();
  Signature: ()Ljava/lang/Object;
  Code:
   Stack=1, Locals=1, Args_size=1
	aload_0
	invokevirtual	Method apply:()V
	getstatic	Field scala/runtime/BoxedUnit.UNIT:Lscala/runtime/BoxedUnit;
	areturn
  Labels:

public final void apply();
  Signature: ()V
  Code:
   Stack=1, Locals=1, Args_size=1
	aload_0
	getfield	Field x$1$1:Lscala/Function0;
	invokeinterface	InterfaceMethod scala/Function0.apply:()Ljava/lang/Object;
	pop
	return
  Labels:

public java.lang.String toString();
  Signature: ()Ljava/lang/String;
  Code:
   Stack=1, Locals=1, Args_size=1
	aload_0
	invokestatic	Method scala/Function0$class.toString:(Lscala/Function0;)Ljava/lang/String;
	areturn
  Labels:

}

