Compiled from "JavaConversions.scala"
public final class scala.concurrent.JavaConversions$$anon$1 extends java.lang.Object implements scala.concurrent.ThreadPoolRunner
  SourceFile: "JavaConversions.scala"
  Scala: length = 0x
   
  InnerClass: 
   public final $anon$1=class scala/concurrent/JavaConversions$$anon$1 of class scala/concurrent/JavaConversions
  minor version: 0
  major version: 49
  Constant pool:
Asciz	SourceFile;
Asciz	JavaConversions.scala;
Asciz	exec$1;
Asciz	Ljava/util/concurrent/ExecutorService;;
Asciz	<init>;
Asciz	(Ljava/util/concurrent/ExecutorService;)V;
Asciz	Code;
Asciz	LineNumberTable;
Asciz	scala/concurrent/JavaConversions$$anon$1;
class	scala/concurrent/JavaConversions$$anon$1
NameAndType	exec$1:Ljava/util/concurrent/ExecutorService;
Field	scala/concurrent/JavaConversions$$anon$1.exec$1:Ljava/util/concurrent/ExecutorService;
Asciz	java/lang/Object;
class	java/lang/Object
Asciz	()V;
NameAndType	"<init>":()V
Method	java/lang/Object."<init>":()V
Asciz	scala/concurrent/TaskRunner$class;
class	scala/concurrent/TaskRunner$class
Asciz	$init$;
Asciz	(Lscala/concurrent/TaskRunner;)V;
NameAndType	$init$:(Lscala/concurrent/TaskRunner;)V
Method	scala/concurrent/TaskRunner$class.$init$:(Lscala/concurrent/TaskRunner;)V
Asciz	scala/concurrent/ThreadPoolRunner$class;
class	scala/concurrent/ThreadPoolRunner$class
Asciz	(Lscala/concurrent/ThreadPoolRunner;)V;
NameAndType	$init$:(Lscala/concurrent/ThreadPoolRunner;)V
Method	scala/concurrent/ThreadPoolRunner$class.$init$:(Lscala/concurrent/ThreadPoolRunner;)V
Asciz	functionAsTask;
Asciz	(Lscala/Function0;)Ljava/lang/Object;;
Asciz	scala/concurrent/ThreadPoolRunner;
class	scala/concurrent/ThreadPoolRunner
Asciz	(Lscala/Function0;)Ljava/util/concurrent/Callable;;
NameAndType	functionAsTask:(Lscala/Function0;)Ljava/util/concurrent/Callable;
InterfaceMethod	scala/concurrent/ThreadPoolRunner.functionAsTask:(Lscala/Function0;)Ljava/util/concurrent/Callable;
Asciz	this;
Asciz	Lscala/concurrent/JavaConversions$$anon$1;;
Asciz	fun;
Asciz	Lscala/Function0;;
Asciz	LocalVariableTable;
Asciz	futureAsFunction;
Asciz	(Ljava/lang/Object;)Lscala/Function0;;
Asciz	java/util/concurrent/Future;
class	java/util/concurrent/Future
Asciz	(Ljava/util/concurrent/Future;)Lscala/Function0;;
NameAndType	futureAsFunction:(Ljava/util/concurrent/Future;)Lscala/Function0;
InterfaceMethod	scala/concurrent/ThreadPoolRunner.futureAsFunction:(Ljava/util/concurrent/Future;)Lscala/Function0;
Asciz	x;
Asciz	Ljava/lang/Object;;
Asciz	submit;
Asciz	(Ljava/lang/Object;)Ljava/lang/Object;;
Asciz	java/util/concurrent/Callable;
class	java/util/concurrent/Callable
Asciz	(Ljava/util/concurrent/Callable;)Ljava/util/concurrent/Future;;
NameAndType	submit:(Ljava/util/concurrent/Callable;)Ljava/util/concurrent/Future;
InterfaceMethod	scala/concurrent/ThreadPoolRunner.submit:(Ljava/util/concurrent/Callable;)Ljava/util/concurrent/Future;
Asciz	task;
Asciz	execute;
Asciz	(Ljava/lang/Object;)V;
Asciz	(Ljava/util/concurrent/Callable;)V;
NameAndType	execute:(Ljava/util/concurrent/Callable;)V
InterfaceMethod	scala/concurrent/ThreadPoolRunner.execute:(Ljava/util/concurrent/Callable;)V
Asciz	shutdown;
Asciz	java/util/concurrent/ExecutorService;
class	java/util/concurrent/ExecutorService
NameAndType	shutdown:()V
InterfaceMethod	java/util/concurrent/ExecutorService.shutdown:()V
Asciz	executor;
Asciz	()Ljava/util/concurrent/ExecutorService;;
Asciz	tryCatch;
Asciz	(Lscala/Function0;)Lscala/Either;;
Asciz	(Lscala/concurrent/TaskRunner;Lscala/Function0;)Lscala/Either;;
NameAndType	tryCatch:(Lscala/concurrent/TaskRunner;Lscala/Function0;)Lscala/Either;
Method	scala/concurrent/TaskRunner$class.tryCatch:(Lscala/concurrent/TaskRunner;Lscala/Function0;)Lscala/Either;
Asciz	body;
Asciz	managedBlock;
Asciz	(Lscala/concurrent/ManagedBlocker;)V;
Asciz	(Lscala/concurrent/ThreadPoolRunner;Lscala/concurrent/ManagedBlocker;)V;
NameAndType	managedBlock:(Lscala/concurrent/ThreadPoolRunner;Lscala/concurrent/ManagedBlocker;)V
Method	scala/concurrent/ThreadPoolRunner$class.managedBlock:(Lscala/concurrent/ThreadPoolRunner;Lscala/concurrent/ManagedBlocker;)V
Asciz	blocker;
Asciz	Lscala/concurrent/ManagedBlocker;;
Asciz	(Lscala/concurrent/ThreadPoolRunner;Ljava/util/concurrent/Callable;)V;
NameAndType	execute:(Lscala/concurrent/ThreadPoolRunner;Ljava/util/concurrent/Callable;)V
Method	scala/concurrent/ThreadPoolRunner$class.execute:(Lscala/concurrent/ThreadPoolRunner;Ljava/util/concurrent/Callable;)V
Asciz	Ljava/util/concurrent/Callable;;
Asciz	(Lscala/concurrent/ThreadPoolRunner;Ljava/util/concurrent/Callable;)Ljava/util/concurrent/Future;;
NameAndType	submit:(Lscala/concurrent/ThreadPoolRunner;Ljava/util/concurrent/Callable;)Ljava/util/concurrent/Future;
Method	scala/concurrent/ThreadPoolRunner$class.submit:(Lscala/concurrent/ThreadPoolRunner;Ljava/util/concurrent/Callable;)Ljava/util/concurrent/Future;
Asciz	(Lscala/concurrent/ThreadPoolRunner;Ljava/util/concurrent/Future;)Lscala/Function0;;
NameAndType	futureAsFunction:(Lscala/concurrent/ThreadPoolRunner;Ljava/util/concurrent/Future;)Lscala/Function0;
Method	scala/concurrent/ThreadPoolRunner$class.futureAsFunction:(Lscala/concurrent/ThreadPoolRunner;Ljava/util/concurrent/Future;)Lscala/Function0;
Asciz	Ljava/util/concurrent/Future;;
Asciz	(Lscala/concurrent/ThreadPoolRunner;Lscala/Function0;)Ljava/util/concurrent/Callable;;
NameAndType	functionAsTask:(Lscala/concurrent/ThreadPoolRunner;Lscala/Function0;)Ljava/util/concurrent/Callable;
Method	scala/concurrent/ThreadPoolRunner$class.functionAsTask:(Lscala/concurrent/ThreadPoolRunner;Lscala/Function0;)Ljava/util/concurrent/Callable;
Asciz	Scala;
Asciz	InnerClasses;
Asciz	scala/concurrent/JavaConversions;
class	scala/concurrent/JavaConversions
Asciz	$anon$1;

{
private final java.util.concurrent.ExecutorService exec$1;
  Signature: Ljava/util/concurrent/ExecutorService;

public scala.concurrent.JavaConversions$$anon$1(java.util.concurrent.ExecutorService);
  Signature: (Ljava/util/concurrent/ExecutorService;)V
  Code:
   Stack=2, Locals=2, Args_size=2
	aload_0
	aload_1
	putfield	Field exec$1:Ljava/util/concurrent/ExecutorService;
	aload_0
	invokespecial	Method java/lang/Object."<init>":()V
	aload_0
	invokestatic	Method scala/concurrent/TaskRunner$class.$init$:(Lscala/concurrent/TaskRunner;)V
	aload_0
	invokestatic	Method scala/concurrent/ThreadPoolRunner$class.$init$:(Lscala/concurrent/ThreadPoolRunner;)V
	return
  Labels:

public java.lang.Object functionAsTask(scala.Function0);
  Signature: (Lscala/Function0;)Ljava/lang/Object;
  Code:
   Stack=2, Locals=2, Args_size=2
	aload_0
	aload_1
	invokeinterface	InterfaceMethod scala/concurrent/ThreadPoolRunner.functionAsTask:(Lscala/Function0;)Ljava/util/concurrent/Callable;
	areturn
  Labels:
  LocalVariableTable: 
   Start  Length  Slot  Name   Signature
   0      8      0    this       Lscala/concurrent/JavaConversions$$anon$1;
   0      8      1    fun       Lscala/Function0;


public scala.Function0 futureAsFunction(java.lang.Object);
  Signature: (Ljava/lang/Object;)Lscala/Function0;
  Code:
   Stack=2, Locals=2, Args_size=2
	aload_0
	aload_1
	checkcast	class java/util/concurrent/Future
	invokeinterface	InterfaceMethod scala/concurrent/ThreadPoolRunner.futureAsFunction:(Ljava/util/concurrent/Future;)Lscala/Function0;
	areturn
  Labels:
  LocalVariableTable: 
   Start  Length  Slot  Name   Signature
   0      11      0    this       Lscala/concurrent/JavaConversions$$anon$1;
   0      11      1    x       Ljava/lang/Object;


public java.lang.Object submit(java.lang.Object);
  Signature: (Ljava/lang/Object;)Ljava/lang/Object;
  Code:
   Stack=2, Locals=2, Args_size=2
	aload_0
	aload_1
	checkcast	class java/util/concurrent/Callable
	invokeinterface	InterfaceMethod scala/concurrent/ThreadPoolRunner.submit:(Ljava/util/concurrent/Callable;)Ljava/util/concurrent/Future;
	areturn
  Labels:
  LocalVariableTable: 
   Start  Length  Slot  Name   Signature
   0      11      0    this       Lscala/concurrent/JavaConversions$$anon$1;
   0      11      1    task       Ljava/lang/Object;


public void execute(java.lang.Object);
  Signature: (Ljava/lang/Object;)V
  Code:
   Stack=2, Locals=2, Args_size=2
	aload_0
	aload_1
	checkcast	class java/util/concurrent/Callable
	invokeinterface	InterfaceMethod scala/concurrent/ThreadPoolRunner.execute:(Ljava/util/concurrent/Callable;)V
	return
  Labels:
  LocalVariableTable: 
   Start  Length  Slot  Name   Signature
   0      11      0    this       Lscala/concurrent/JavaConversions$$anon$1;
   0      11      1    task       Ljava/lang/Object;


public void shutdown();
  Signature: ()V
  Code:
   Stack=1, Locals=1, Args_size=1
	aload_0
	getfield	Field exec$1:Ljava/util/concurrent/ExecutorService;
	invokeinterface	InterfaceMethod java/util/concurrent/ExecutorService.shutdown:()V
	return
  Labels:

public java.util.concurrent.ExecutorService executor();
  Signature: ()Ljava/util/concurrent/ExecutorService;
  Code:
   Stack=1, Locals=1, Args_size=1
	aload_0
	getfield	Field exec$1:Ljava/util/concurrent/ExecutorService;
	areturn
  Labels:

public scala.Either tryCatch(scala.Function0);
  Signature: (Lscala/Function0;)Lscala/Either;
  Code:
   Stack=2, Locals=2, Args_size=2
	aload_0
	aload_1
	invokestatic	Method scala/concurrent/TaskRunner$class.tryCatch:(Lscala/concurrent/TaskRunner;Lscala/Function0;)Lscala/Either;
	areturn
  Labels:
  LocalVariableTable: 
   Start  Length  Slot  Name   Signature
   0      6      0    this       Lscala/concurrent/JavaConversions$$anon$1;
   0      6      1    body       Lscala/Function0;


public void managedBlock(scala.concurrent.ManagedBlocker);
  Signature: (Lscala/concurrent/ManagedBlocker;)V
  Code:
   Stack=2, Locals=2, Args_size=2
	aload_0
	aload_1
	invokestatic	Method scala/concurrent/ThreadPoolRunner$class.managedBlock:(Lscala/concurrent/ThreadPoolRunner;Lscala/concurrent/ManagedBlocker;)V
	return
  Labels:
  LocalVariableTable: 
   Start  Length  Slot  Name   Signature
   0      6      0    this       Lscala/concurrent/JavaConversions$$anon$1;
   0      6      1    blocker       Lscala/concurrent/ManagedBlocker;


public void execute(java.util.concurrent.Callable);
  Signature: (Ljava/util/concurrent/Callable;)V
  Code:
   Stack=2, Locals=2, Args_size=2
	aload_0
	aload_1
	invokestatic	Method scala/concurrent/ThreadPoolRunner$class.execute:(Lscala/concurrent/ThreadPoolRunner;Ljava/util/concurrent/Callable;)V
	return
  Labels:
  LocalVariableTable: 
   Start  Length  Slot  Name   Signature
   0      6      0    this       Lscala/concurrent/JavaConversions$$anon$1;
   0      6      1    task       Ljava/util/concurrent/Callable;


public java.util.concurrent.Future submit(java.util.concurrent.Callable);
  Signature: (Ljava/util/concurrent/Callable;)Ljava/util/concurrent/Future;
  Code:
   Stack=2, Locals=2, Args_size=2
	aload_0
	aload_1
	invokestatic	Method scala/concurrent/ThreadPoolRunner$class.submit:(Lscala/concurrent/ThreadPoolRunner;Ljava/util/concurrent/Callable;)Ljava/util/concurrent/Future;
	areturn
  Labels:
  LocalVariableTable: 
   Start  Length  Slot  Name   Signature
   0      6      0    this       Lscala/concurrent/JavaConversions$$anon$1;
   0      6      1    task       Ljava/util/concurrent/Callable;


public scala.Function0 futureAsFunction(java.util.concurrent.Future);
  Signature: (Ljava/util/concurrent/Future;)Lscala/Function0;
  Code:
   Stack=2, Locals=2, Args_size=2
	aload_0
	aload_1
	invokestatic	Method scala/concurrent/ThreadPoolRunner$class.futureAsFunction:(Lscala/concurrent/ThreadPoolRunner;Ljava/util/concurrent/Future;)Lscala/Function0;
	areturn
  Labels:
  LocalVariableTable: 
   Start  Length  Slot  Name   Signature
   0      6      0    this       Lscala/concurrent/JavaConversions$$anon$1;
   0      6      1    x       Ljava/util/concurrent/Future;


public java.util.concurrent.Callable functionAsTask(scala.Function0);
  Signature: (Lscala/Function0;)Ljava/util/concurrent/Callable;
  Code:
   Stack=2, Locals=2, Args_size=2
	aload_0
	aload_1
	invokestatic	Method scala/concurrent/ThreadPoolRunner$class.functionAsTask:(Lscala/concurrent/ThreadPoolRunner;Lscala/Function0;)Ljava/util/concurrent/Callable;
	areturn
  Labels:
  LocalVariableTable: 
   Start  Length  Slot  Name   Signature
   0      6      0    this       Lscala/concurrent/JavaConversions$$anon$1;
   0      6      1    fun       Lscala/Function0;


}

