Compiled from "JavaConversions.scala"
public final class scala.concurrent.JavaConversions$$anon$2 extends java.lang.Object implements scala.concurrent.TaskRunner
  SourceFile: "JavaConversions.scala"
  Scala: length = 0x
   
  InnerClass: 
   public final $anon$2=class scala/concurrent/JavaConversions$$anon$2 of class scala/concurrent/JavaConversions
   public final $anon$3=class scala/concurrent/JavaConversions$$anon$2$$anon$3 of class scala/concurrent/JavaConversions$$anon$2
  minor version: 0
  major version: 49
  Constant pool:
Asciz	SourceFile;
Asciz	JavaConversions.scala;
Asciz	exec$2;
Asciz	Ljava/util/concurrent/Executor;;
Asciz	<init>;
Asciz	(Ljava/util/concurrent/Executor;)V;
Asciz	Code;
Asciz	LineNumberTable;
Asciz	scala/concurrent/JavaConversions$$anon$2;
class	scala/concurrent/JavaConversions$$anon$2
NameAndType	exec$2:Ljava/util/concurrent/Executor;
Field	scala/concurrent/JavaConversions$$anon$2.exec$2:Ljava/util/concurrent/Executor;
Asciz	java/lang/Object;
class	java/lang/Object
Asciz	()V;
NameAndType	"<init>":()V
Method	java/lang/Object."<init>":()V
Asciz	scala/concurrent/TaskRunner$class;
class	scala/concurrent/TaskRunner$class
Asciz	$init$;
Asciz	(Lscala/concurrent/TaskRunner;)V;
NameAndType	$init$:(Lscala/concurrent/TaskRunner;)V
Method	scala/concurrent/TaskRunner$class.$init$:(Lscala/concurrent/TaskRunner;)V
Asciz	functionAsTask;
Asciz	(Lscala/Function0;)Ljava/lang/Object;;
Asciz	(Lscala/Function0;)Ljava/lang/Runnable;;
NameAndType	functionAsTask:(Lscala/Function0;)Ljava/lang/Runnable;
Method	scala/concurrent/JavaConversions$$anon$2.functionAsTask:(Lscala/Function0;)Ljava/lang/Runnable;
Asciz	this;
Asciz	Lscala/concurrent/JavaConversions$$anon$2;;
Asciz	fun;
Asciz	Lscala/Function0;;
Asciz	LocalVariableTable;
Asciz	execute;
Asciz	(Ljava/lang/Object;)V;
Asciz	java/lang/Runnable;
class	java/lang/Runnable
Asciz	(Ljava/lang/Runnable;)V;
NameAndType	execute:(Ljava/lang/Runnable;)V
Method	scala/concurrent/JavaConversions$$anon$2.execute:(Ljava/lang/Runnable;)V
Asciz	task;
Asciz	Ljava/lang/Object;;
Asciz	shutdown;
Asciz	managedBlock;
Asciz	(Lscala/concurrent/ManagedBlocker;)V;
Asciz	scala/concurrent/ManagedBlocker;
class	scala/concurrent/ManagedBlocker
Asciz	block;
Asciz	()Z;
NameAndType	block:()Z
InterfaceMethod	scala/concurrent/ManagedBlocker.block:()Z
Asciz	blocker;
Asciz	Lscala/concurrent/ManagedBlocker;;
Asciz	java/util/concurrent/Executor;
class	java/util/concurrent/Executor
InterfaceMethod	java/util/concurrent/Executor.execute:(Ljava/lang/Runnable;)V
Asciz	Ljava/lang/Runnable;;
Asciz	<S:Ljava/lang/Object;>(Ljava/lang/Runnable;)V;
Asciz	Signature;
Asciz	scala/concurrent/JavaConversions$$anon$2$$anon$3;
class	scala/concurrent/JavaConversions$$anon$2$$anon$3
Asciz	(Lscala/concurrent/JavaConversions$$anon$2;Lscala/Function0;)V;
NameAndType	"<init>":(Lscala/concurrent/JavaConversions$$anon$2;Lscala/Function0;)V
Method	scala/concurrent/JavaConversions$$anon$2$$anon$3."<init>":(Lscala/concurrent/JavaConversions$$anon$2;Lscala/Function0;)V
Asciz	fun$1;
Asciz	<T:Ljava/lang/Object;>(Lscala/Function0<TT;>;)Ljava/lang/Runnable;;
Asciz	tryCatch;
Asciz	(Lscala/Function0;)Lscala/Either;;
Asciz	(Lscala/concurrent/TaskRunner;Lscala/Function0;)Lscala/Either;;
NameAndType	tryCatch:(Lscala/concurrent/TaskRunner;Lscala/Function0;)Lscala/Either;
Method	scala/concurrent/TaskRunner$class.tryCatch:(Lscala/concurrent/TaskRunner;Lscala/Function0;)Lscala/Either;
Asciz	body;
Asciz	Scala;
Asciz	InnerClasses;
Asciz	scala/concurrent/JavaConversions;
class	scala/concurrent/JavaConversions
Asciz	$anon$2;
Asciz	$anon$3;
Asciz	scala/concurrent/TaskRunner;
class	scala/concurrent/TaskRunner

{
public final java.util.concurrent.Executor exec$2;
  Signature: Ljava/util/concurrent/Executor;

public scala.concurrent.JavaConversions$$anon$2(java.util.concurrent.Executor);
  Signature: (Ljava/util/concurrent/Executor;)V
  Code:
   Stack=2, Locals=2, Args_size=2
	aload_0
	aload_1
	putfield	Field exec$2:Ljava/util/concurrent/Executor;
	aload_0
	invokespecial	Method java/lang/Object."<init>":()V
	aload_0
	invokestatic	Method scala/concurrent/TaskRunner$class.$init$:(Lscala/concurrent/TaskRunner;)V
	return
  Labels:

public java.lang.Object functionAsTask(scala.Function0);
  Signature: (Lscala/Function0;)Ljava/lang/Object;
  Code:
   Stack=2, Locals=2, Args_size=2
	aload_0
	aload_1
	invokevirtual	Method functionAsTask:(Lscala/Function0;)Ljava/lang/Runnable;
	areturn
  Labels:
  LocalVariableTable: 
   Start  Length  Slot  Name   Signature
   0      6      0    this       Lscala/concurrent/JavaConversions$$anon$2;
   0      6      1    fun       Lscala/Function0;


public void execute(java.lang.Object);
  Signature: (Ljava/lang/Object;)V
  Code:
   Stack=2, Locals=2, Args_size=2
	aload_0
	aload_1
	checkcast	class java/lang/Runnable
	invokevirtual	Method execute:(Ljava/lang/Runnable;)V
	return
  Labels:
  LocalVariableTable: 
   Start  Length  Slot  Name   Signature
   0      9      0    this       Lscala/concurrent/JavaConversions$$anon$2;
   0      9      1    task       Ljava/lang/Object;


public void shutdown();
  Signature: ()V
  Code:
   Stack=0, Locals=1, Args_size=1
	return
  Labels:

private void managedBlock(scala.concurrent.ManagedBlocker);
  Signature: (Lscala/concurrent/ManagedBlocker;)V
  Code:
   Stack=1, Locals=2, Args_size=2
	aload_1
	invokeinterface	InterfaceMethod scala/concurrent/ManagedBlocker.block:()Z
	pop
	return
  Labels:
  LocalVariableTable: 
   Start  Length  Slot  Name   Signature
   0      8      0    this       Lscala/concurrent/JavaConversions$$anon$2;
   0      8      1    blocker       Lscala/concurrent/ManagedBlocker;


public void execute(java.lang.Runnable);
  Signature: (Ljava/lang/Runnable;)V
  Code:
   Stack=2, Locals=2, Args_size=2
	aload_0
	getfield	Field exec$2:Ljava/util/concurrent/Executor;
	aload_1
	invokeinterface	InterfaceMethod java/util/concurrent/Executor.execute:(Ljava/lang/Runnable;)V
	return
  Labels:
  LocalVariableTable: 
   Start  Length  Slot  Name   Signature
   0      11      0    this       Lscala/concurrent/JavaConversions$$anon$2;
   0      11      1    task       Ljava/lang/Runnable;

  Signature: length = 0x2
   00 3A 

public java.lang.Runnable functionAsTask(scala.Function0);
  Signature: (Lscala/Function0;)Ljava/lang/Runnable;
  Code:
   Stack=4, Locals=2, Args_size=2
	new	class scala/concurrent/JavaConversions$$anon$2$$anon$3
	dup
	aload_0
	aload_1
	invokespecial	Method scala/concurrent/JavaConversions$$anon$2$$anon$3."<init>":(Lscala/concurrent/JavaConversions$$anon$2;Lscala/Function0;)V
	areturn
  Labels:
  LocalVariableTable: 
   Start  Length  Slot  Name   Signature
   0      10      0    this       Lscala/concurrent/JavaConversions$$anon$2;
   0      10      1    fun$1       Lscala/Function0;

  Signature: length = 0x2
   00 42 

public scala.Either tryCatch(scala.Function0);
  Signature: (Lscala/Function0;)Lscala/Either;
  Code:
   Stack=2, Locals=2, Args_size=2
	aload_0
	aload_1
	invokestatic	Method scala/concurrent/TaskRunner$class.tryCatch:(Lscala/concurrent/TaskRunner;Lscala/Function0;)Lscala/Either;
	areturn
  Labels:
  LocalVariableTable: 
   Start  Length  Slot  Name   Signature
   0      6      0    this       Lscala/concurrent/JavaConversions$$anon$2;
   0      6      1    body       Lscala/Function0;


}

