Compiled from "JavaConversions.scala"
public final class scala.concurrent.JavaConversions$$anon$2 extends java.lang.Object implements scala.concurrent.TaskRunner
  SourceFile: "JavaConversions.scala"
  Scala: length = 0x
   
  InnerClass: 
   public final #77= #10 of #76; //$anon$2=class scala/concurrent/JavaConversions$$anon$2 of class scala/concurrent/JavaConversions
   public final #78= #61 of #10; //$anon$3=class scala/concurrent/JavaConversions$$anon$2$$anon$3 of class scala/concurrent/JavaConversions$$anon$2
  minor version: 0
  major version: 49
  Constant pool:
const #1 = Asciz	SourceFile;
const #2 = Asciz	JavaConversions.scala;
const #3 = Asciz	exec$2;
const #4 = Asciz	Ljava/util/concurrent/Executor;;
const #5 = Asciz	<init>;
const #6 = Asciz	(Ljava/util/concurrent/Executor;)V;
const #7 = Asciz	Code;
const #8 = Asciz	LineNumberTable;
const #9 = Asciz	scala/concurrent/JavaConversions$$anon$2;
const #10 = class	#9;	//  scala/concurrent/JavaConversions$$anon$2
const #11 = NameAndType	#3:#4;//  exec$2:Ljava/util/concurrent/Executor;
const #12 = Field	#10.#11;	//  scala/concurrent/JavaConversions$$anon$2.exec$2:Ljava/util/concurrent/Executor;
const #13 = Asciz	java/lang/Object;
const #14 = class	#13;	//  java/lang/Object
const #15 = Asciz	()V;
const #16 = NameAndType	#5:#15;//  "<init>":()V
const #17 = Method	#14.#16;	//  java/lang/Object."<init>":()V
const #18 = Asciz	scala/concurrent/TaskRunner$class;
const #19 = class	#18;	//  scala/concurrent/TaskRunner$class
const #20 = Asciz	$init$;
const #21 = Asciz	(Lscala/concurrent/TaskRunner;)V;
const #22 = NameAndType	#20:#21;//  $init$:(Lscala/concurrent/TaskRunner;)V
const #23 = Method	#19.#22;	//  scala/concurrent/TaskRunner$class.$init$:(Lscala/concurrent/TaskRunner;)V
const #24 = Asciz	functionAsTask;
const #25 = Asciz	(Lscala/Function0;)Ljava/lang/Object;;
const #26 = Asciz	(Lscala/Function0;)Ljava/lang/Runnable;;
const #27 = NameAndType	#24:#26;//  functionAsTask:(Lscala/Function0;)Ljava/lang/Runnable;
const #28 = Method	#10.#27;	//  scala/concurrent/JavaConversions$$anon$2.functionAsTask:(Lscala/Function0;)Ljava/lang/Runnable;
const #29 = Asciz	this;
const #30 = Asciz	Lscala/concurrent/JavaConversions$$anon$2;;
const #31 = Asciz	fun;
const #32 = Asciz	Lscala/Function0;;
const #33 = Asciz	LocalVariableTable;
const #34 = Asciz	execute;
const #35 = Asciz	(Ljava/lang/Object;)V;
const #36 = Asciz	java/lang/Runnable;
const #37 = class	#36;	//  java/lang/Runnable
const #38 = Asciz	(Ljava/lang/Runnable;)V;
const #39 = NameAndType	#34:#38;//  execute:(Ljava/lang/Runnable;)V
const #40 = Method	#10.#39;	//  scala/concurrent/JavaConversions$$anon$2.execute:(Ljava/lang/Runnable;)V
const #41 = Asciz	task;
const #42 = Asciz	Ljava/lang/Object;;
const #43 = Asciz	shutdown;
const #44 = Asciz	managedBlock;
const #45 = Asciz	(Lscala/concurrent/ManagedBlocker;)V;
const #46 = Asciz	scala/concurrent/ManagedBlocker;
const #47 = class	#46;	//  scala/concurrent/ManagedBlocker
const #48 = Asciz	block;
const #49 = Asciz	()Z;
const #50 = NameAndType	#48:#49;//  block:()Z
const #51 = InterfaceMethod	#47.#50;	//  scala/concurrent/ManagedBlocker.block:()Z
const #52 = Asciz	blocker;
const #53 = Asciz	Lscala/concurrent/ManagedBlocker;;
const #54 = Asciz	java/util/concurrent/Executor;
const #55 = class	#54;	//  java/util/concurrent/Executor
const #56 = InterfaceMethod	#55.#39;	//  java/util/concurrent/Executor.execute:(Ljava/lang/Runnable;)V
const #57 = Asciz	Ljava/lang/Runnable;;
const #58 = Asciz	<S:Ljava/lang/Object;>(Ljava/lang/Runnable;)V;
const #59 = Asciz	Signature;
const #60 = Asciz	scala/concurrent/JavaConversions$$anon$2$$anon$3;
const #61 = class	#60;	//  scala/concurrent/JavaConversions$$anon$2$$anon$3
const #62 = Asciz	(Lscala/concurrent/JavaConversions$$anon$2;Lscala/Function0;)V;
const #63 = NameAndType	#5:#62;//  "<init>":(Lscala/concurrent/JavaConversions$$anon$2;Lscala/Function0;)V
const #64 = Method	#61.#63;	//  scala/concurrent/JavaConversions$$anon$2$$anon$3."<init>":(Lscala/concurrent/JavaConversions$$anon$2;Lscala/Function0;)V
const #65 = Asciz	fun$1;
const #66 = Asciz	<T:Ljava/lang/Object;>(Lscala/Function0<TT;>;)Ljava/lang/Runnable;;
const #67 = Asciz	tryCatch;
const #68 = Asciz	(Lscala/Function0;)Lscala/Either;;
const #69 = Asciz	(Lscala/concurrent/TaskRunner;Lscala/Function0;)Lscala/Either;;
const #70 = NameAndType	#67:#69;//  tryCatch:(Lscala/concurrent/TaskRunner;Lscala/Function0;)Lscala/Either;
const #71 = Method	#19.#70;	//  scala/concurrent/TaskRunner$class.tryCatch:(Lscala/concurrent/TaskRunner;Lscala/Function0;)Lscala/Either;
const #72 = Asciz	body;
const #73 = Asciz	Scala;
const #74 = Asciz	InnerClasses;
const #75 = Asciz	scala/concurrent/JavaConversions;
const #76 = class	#75;	//  scala/concurrent/JavaConversions
const #77 = Asciz	$anon$2;
const #78 = Asciz	$anon$3;
const #79 = Asciz	scala/concurrent/TaskRunner;
const #80 = class	#79;	//  scala/concurrent/TaskRunner

{
public scala.concurrent.JavaConversions$$anon$2(java.util.concurrent.Executor);
  Code:
   Stack=2, Locals=2, Args_size=2
   0:	aload_0
   1:	aload_1
   2:	putfield	#12; //Field exec$2:Ljava/util/concurrent/Executor;
   5:	aload_0
   6:	invokespecial	#17; //Method java/lang/Object."<init>":()V
   9:	aload_0
   10:	invokestatic	#23; //Method scala/concurrent/TaskRunner$class.$init$:(Lscala/concurrent/TaskRunner;)V
   13:	return
  LineNumberTable: 
   line 32: 0


public java.lang.Object functionAsTask(scala.Function0);
  Code:
   Stack=2, Locals=2, Args_size=2
   0:	aload_0
   1:	aload_1
   2:	invokevirtual	#28; //Method functionAsTask:(Lscala/Function0;)Ljava/lang/Runnable;
   5:	areturn
  LineNumberTable: 
   line 32: 0

  LocalVariableTable: 
   Start  Length  Slot  Name   Signature
   0      6      0    this       Lscala/concurrent/JavaConversions$$anon$2;
   0      6      1    fun       Lscala/Function0;


public void execute(java.lang.Object);
  Code:
   Stack=2, Locals=2, Args_size=2
   0:	aload_0
   1:	aload_1
   2:	checkcast	#37; //class java/lang/Runnable
   5:	invokevirtual	#40; //Method execute:(Ljava/lang/Runnable;)V
   8:	return
  LineNumberTable: 
   line 32: 0

  LocalVariableTable: 
   Start  Length  Slot  Name   Signature
   0      9      0    this       Lscala/concurrent/JavaConversions$$anon$2;
   0      9      1    task       Ljava/lang/Object;


public void shutdown();
  Code:
   Stack=0, Locals=1, Args_size=1
   0:	return
  LineNumberTable: 
   line 47: 0


public void execute(java.lang.Runnable);
  Code:
   Stack=2, Locals=2, Args_size=2
   0:	aload_0
   1:	getfield	#12; //Field exec$2:Ljava/util/concurrent/Executor;
   4:	aload_1
   5:	invokeinterface	#56,  2; //InterfaceMethod java/util/concurrent/Executor.execute:(Ljava/lang/Runnable;)V
   10:	return
  LineNumberTable: 
   line 40: 0

  LocalVariableTable: 
   Start  Length  Slot  Name   Signature
   0      11      0    this       Lscala/concurrent/JavaConversions$$anon$2;
   0      11      1    task       Ljava/lang/Runnable;

  Signature: length = 0x2
   00 3A 

public java.lang.Runnable functionAsTask(scala.Function0);
  Code:
   Stack=4, Locals=2, Args_size=2
   0:	new	#61; //class scala/concurrent/JavaConversions$$anon$2$$anon$3
   3:	dup
   4:	aload_0
   5:	aload_1
   6:	invokespecial	#64; //Method scala/concurrent/JavaConversions$$anon$2$$anon$3."<init>":(Lscala/concurrent/JavaConversions$$anon$2;Lscala/Function0;)V
   9:	areturn
  LineNumberTable: 
   line 35: 0

  LocalVariableTable: 
   Start  Length  Slot  Name   Signature
   0      10      0    this       Lscala/concurrent/JavaConversions$$anon$2;
   0      10      1    fun$1       Lscala/Function0;

  Signature: length = 0x2
   00 42 

public scala.Either tryCatch(scala.Function0);
  Code:
   Stack=2, Locals=2, Args_size=2
   0:	aload_0
   1:	aload_1
   2:	invokestatic	#71; //Method scala/concurrent/TaskRunner$class.tryCatch:(Lscala/concurrent/TaskRunner;Lscala/Function0;)Lscala/Either;
   5:	areturn
  LineNumberTable: 
   line 32: 0

  LocalVariableTable: 
   Start  Length  Slot  Name   Signature
   0      6      0    this       Lscala/concurrent/JavaConversions$$anon$2;
   0      6      1    body       Lscala/Function0;


}

