Compiled from "jolib.scala"
public abstract class scala.concurrent.jolib$Asynchr extends scala.concurrent.jolib$Signal implements scala.ScalaObject
  SourceFile: "jolib.scala"
  Scala: length = 0x
   
  InnerClass: 
   public #31= #28 of #30; //Join=class scala/concurrent/jolib$Join of class scala/concurrent/jolib
   public abstract #32= #8 of #30; //Signal=class scala/concurrent/jolib$Signal of class scala/concurrent/jolib
   public abstract #33= #19 of #30; //Asynchr=class scala/concurrent/jolib$Asynchr of class scala/concurrent/jolib
  minor version: 0
  major version: 49
  Constant pool:
const #1 = Asciz	SourceFile;
const #2 = Asciz	jolib.scala;
const #3 = Asciz	<init>;
const #4 = Asciz	(Lscala/concurrent/jolib$Join;)V;
const #5 = Asciz	Code;
const #6 = Asciz	LineNumberTable;
const #7 = Asciz	scala/concurrent/jolib$Signal;
const #8 = class	#7;	//  scala/concurrent/jolib$Signal
const #9 = NameAndType	#3:#4;//  "<init>":(Lscala/concurrent/jolib$Join;)V
const #10 = Method	#8.#9;	//  scala/concurrent/jolib$Signal."<init>":(Lscala/concurrent/jolib$Join;)V
const #11 = Asciz	this;
const #12 = Asciz	Lscala/concurrent/jolib$Asynchr;;
const #13 = Asciz	join;
const #14 = Asciz	Lscala/concurrent/jolib$Join;;
const #15 = Asciz	LocalVariableTable;
const #16 = Asciz	apply;
const #17 = Asciz	(Ljava/lang/Object;)V;
const #18 = Asciz	scala/concurrent/jolib$Asynchr;
const #19 = class	#18;	//  scala/concurrent/jolib$Asynchr
const #20 = Asciz	tryReduction;
const #21 = NameAndType	#20:#17;//  tryReduction:(Ljava/lang/Object;)V
const #22 = Method	#19.#21;	//  scala/concurrent/jolib$Asynchr.tryReduction:(Ljava/lang/Object;)V
const #23 = Asciz	x;
const #24 = Asciz	Ljava/lang/Object;;
const #25 = Asciz	Scala;
const #26 = Asciz	InnerClasses;
const #27 = Asciz	scala/concurrent/jolib$Join;
const #28 = class	#27;	//  scala/concurrent/jolib$Join
const #29 = Asciz	scala/concurrent/jolib;
const #30 = class	#29;	//  scala/concurrent/jolib
const #31 = Asciz	Join;
const #32 = Asciz	Signal;
const #33 = Asciz	Asynchr;
const #34 = Asciz	scala/ScalaObject;
const #35 = class	#34;	//  scala/ScalaObject

{
public scala.concurrent.jolib$Asynchr(scala.concurrent.jolib$Join);
  Code:
   Stack=2, Locals=2, Args_size=2
   0:	aload_0
   1:	aload_1
   2:	invokespecial	#10; //Method scala/concurrent/jolib$Signal."<init>":(Lscala/concurrent/jolib$Join;)V
   5:	return
  LineNumberTable: 
   line 67: 0

  LocalVariableTable: 
   Start  Length  Slot  Name   Signature
   0      6      0    this       Lscala/concurrent/jolib$Asynchr;
   0      6      1    join       Lscala/concurrent/jolib$Join;


public void apply(java.lang.Object);
  Code:
   Stack=2, Locals=2, Args_size=2
   0:	aload_0
   1:	aload_1
   2:	invokevirtual	#22; //Method tryReduction:(Ljava/lang/Object;)V
   5:	return
  LineNumberTable: 
   line 68: 0

  LocalVariableTable: 
   Start  Length  Slot  Name   Signature
   0      6      0    this       Lscala/concurrent/jolib$Asynchr;
   0      6      1    x       Ljava/lang/Object;


}

