Compiled from "jolib.scala"
public class scala.concurrent.jolib$Join extends java.lang.Object implements scala.ScalaObject
  SourceFile: "jolib.scala"
  Scala: length = 0x
   
  InnerClass: 
   public #155= #16 of #154; //Join=class scala/concurrent/jolib$Join of class scala/concurrent/jolib
   public final #156= #121 of #16; //$anonfun$values$1=class scala/concurrent/jolib$Join$$anonfun$values$1 of class scala/concurrent/jolib$Join
   public final #157= #46 of #16; //$anonfun$tryMatch$2=class scala/concurrent/jolib$Join$$anonfun$tryMatch$2 of class scala/concurrent/jolib$Join
   public final #158= #80 of #16; //$anonfun$tryMatch$3=class scala/concurrent/jolib$Join$$anonfun$tryMatch$3 of class scala/concurrent/jolib$Join
   public final #159= #25 of #16; //$anonfun$tryMatch$1=class scala/concurrent/jolib$Join$$anonfun$tryMatch$1 of class scala/concurrent/jolib$Join
   public final #160= #142 of #16; //$anonfun$canMatch$1=class scala/concurrent/jolib$Join$$anonfun$canMatch$1 of class scala/concurrent/jolib$Join
  minor version: 0
  major version: 49
  Constant pool:
const #1 = Asciz	SourceFile;
const #2 = Asciz	jolib.scala;
const #3 = Asciz	ruls;
const #4 = Asciz	Lscala/collection/immutable/List;;
const #5 = Asciz	Lscala/collection/immutable/List<Lscala/Tuple2<Lscala/collection/immutable/List<Lscala/concurrent/jolib$Signal;>;Lscala/PartialFunction<Lscala/collection/immutable/List<Ljava/lang/Object;>;Ljava/lang/Object;>;>;>;;
const #6 = Asciz	Signature;
const #7 = Asciz	<init>;
const #8 = Asciz	()V;
const #9 = Asciz	Code;
const #10 = Asciz	LineNumberTable;
const #11 = Asciz	java/lang/Object;
const #12 = class	#11;	//  java/lang/Object
const #13 = NameAndType	#7:#8;//  "<init>":()V
const #14 = Method	#12.#13;	//  java/lang/Object."<init>":()V
const #15 = Asciz	scala/concurrent/jolib$Join;
const #16 = class	#15;	//  scala/concurrent/jolib$Join
const #17 = NameAndType	#3:#4;//  ruls:Lscala/collection/immutable/List;
const #18 = Field	#16.#17;	//  scala/concurrent/jolib$Join.ruls:Lscala/collection/immutable/List;
const #19 = Asciz	tryMatch;
const #20 = Asciz	()Lscala/Function0;;
const #21 = Asciz	()Lscala/collection/immutable/List;;
const #22 = NameAndType	#3:#21;//  ruls:()Lscala/collection/immutable/List;
const #23 = Method	#16.#22;	//  scala/concurrent/jolib$Join.ruls:()Lscala/collection/immutable/List;
const #24 = Asciz	scala/concurrent/jolib$Join$$anonfun$tryMatch$1;
const #25 = class	#24;	//  scala/concurrent/jolib$Join$$anonfun$tryMatch$1
const #26 = Asciz	(Lscala/concurrent/jolib$Join;)V;
const #27 = NameAndType	#7:#26;//  "<init>":(Lscala/concurrent/jolib$Join;)V
const #28 = Method	#25.#27;	//  scala/concurrent/jolib$Join$$anonfun$tryMatch$1."<init>":(Lscala/concurrent/jolib$Join;)V
const #29 = Asciz	scala/collection/generic/LinearSequenceTemplate;
const #30 = class	#29;	//  scala/collection/generic/LinearSequenceTemplate
const #31 = Asciz	find;
const #32 = Asciz	(Lscala/Function1;)Lscala/Option;;
const #33 = NameAndType	#31:#32;//  find:(Lscala/Function1;)Lscala/Option;
const #34 = InterfaceMethod	#30.#33;	//  scala/collection/generic/LinearSequenceTemplate.find:(Lscala/Function1;)Lscala/Option;
const #35 = Asciz	scala/None$;
const #36 = class	#35;	//  scala/None$
const #37 = Asciz	MODULE$;
const #38 = Asciz	Lscala/None$;;
const #39 = NameAndType	#37:#38;//  MODULE$:Lscala/None$;
const #40 = Field	#36.#39;	//  scala/None$.MODULE$:Lscala/None$;
const #41 = Asciz	equals;
const #42 = Asciz	(Ljava/lang/Object;)Z;
const #43 = NameAndType	#41:#42;//  equals:(Ljava/lang/Object;)Z
const #44 = Method	#12.#43;	//  java/lang/Object.equals:(Ljava/lang/Object;)Z
const #45 = Asciz	scala/concurrent/jolib$Join$$anonfun$tryMatch$2;
const #46 = class	#45;	//  scala/concurrent/jolib$Join$$anonfun$tryMatch$2
const #47 = Method	#46.#27;	//  scala/concurrent/jolib$Join$$anonfun$tryMatch$2."<init>":(Lscala/concurrent/jolib$Join;)V
const #48 = Asciz	scala/Some;
const #49 = class	#48;	//  scala/Some
const #50 = Asciz	x;
const #51 = Asciz	()Ljava/lang/Object;;
const #52 = NameAndType	#50:#51;//  x:()Ljava/lang/Object;
const #53 = Method	#49.#52;	//  scala/Some.x:()Ljava/lang/Object;
const #54 = Asciz	scala/Tuple2;
const #55 = class	#54;	//  scala/Tuple2
const #56 = Asciz	_1;
const #57 = NameAndType	#56:#51;//  _1:()Ljava/lang/Object;
const #58 = Method	#55.#57;	//  scala/Tuple2._1:()Ljava/lang/Object;
const #59 = Asciz	scala/collection/immutable/List;
const #60 = class	#59;	//  scala/collection/immutable/List
const #61 = Asciz	_2;
const #62 = NameAndType	#61:#51;//  _2:()Ljava/lang/Object;
const #63 = Method	#55.#62;	//  scala/Tuple2._2:()Ljava/lang/Object;
const #64 = Asciz	scala/PartialFunction;
const #65 = class	#64;	//  scala/PartialFunction
const #66 = Asciz	scala/runtime/ScalaRunTime$;
const #67 = class	#66;	//  scala/runtime/ScalaRunTime$
const #68 = Asciz	Lscala/runtime/ScalaRunTime$;;
const #69 = NameAndType	#37:#68;//  MODULE$:Lscala/runtime/ScalaRunTime$;
const #70 = Field	#67.#69;	//  scala/runtime/ScalaRunTime$.MODULE$:Lscala/runtime/ScalaRunTime$;
const #71 = Asciz	boxArray;
const #72 = Asciz	(Ljava/lang/Object;)Lscala/runtime/BoxedArray;;
const #73 = NameAndType	#71:#72;//  boxArray:(Ljava/lang/Object;)Lscala/runtime/BoxedArray;
const #74 = Method	#67.#73;	//  scala/runtime/ScalaRunTime$.boxArray:(Ljava/lang/Object;)Lscala/runtime/BoxedArray;
const #75 = Asciz	values;
const #76 = Asciz	(Lscala/collection/immutable/List;)Lscala/collection/immutable/List;;
const #77 = NameAndType	#75:#76;//  values:(Lscala/collection/immutable/List;)Lscala/collection/immutable/List;
const #78 = Method	#16.#77;	//  scala/concurrent/jolib$Join.values:(Lscala/collection/immutable/List;)Lscala/collection/immutable/List;
const #79 = Asciz	scala/concurrent/jolib$Join$$anonfun$tryMatch$3;
const #80 = class	#79;	//  scala/concurrent/jolib$Join$$anonfun$tryMatch$3
const #81 = Asciz	(Lscala/concurrent/jolib$Join;Lscala/PartialFunction;Lscala/collection/immutable/List;)V;
const #82 = NameAndType	#7:#81;//  "<init>":(Lscala/concurrent/jolib$Join;Lscala/PartialFunction;Lscala/collection/immutable/List;)V
const #83 = Method	#80.#82;	//  scala/concurrent/jolib$Join$$anonfun$tryMatch$3."<init>":(Lscala/concurrent/jolib$Join;Lscala/PartialFunction;Lscala/collection/immutable/List;)V
const #84 = Asciz	scala/MatchError;
const #85 = class	#84;	//  scala/MatchError
const #86 = Asciz	scala/Option;
const #87 = class	#86;	//  scala/Option
const #88 = Asciz	toString;
const #89 = Asciz	()Ljava/lang/String;;
const #90 = NameAndType	#88:#89;//  toString:()Ljava/lang/String;
const #91 = Method	#87.#90;	//  scala/Option.toString:()Ljava/lang/String;
const #92 = Asciz	(Ljava/lang/String;)V;
const #93 = NameAndType	#7:#92;//  "<init>":(Ljava/lang/String;)V
const #94 = Method	#85.#93;	//  scala/MatchError."<init>":(Ljava/lang/String;)V
const #95 = Asciz	this;
const #96 = Asciz	Lscala/concurrent/jolib$Join;;
const #97 = Asciz	temp4;
const #98 = Asciz	Lscala/Option;;
const #99 = Asciz	temp6;
const #100 = Asciz	Lscala/Some;;
const #101 = Asciz	temp7;
const #102 = Asciz	Lscala/Tuple2;;
const #103 = Asciz	temp8;
const #104 = Asciz	temp9;
const #105 = Asciz	Lscala/PartialFunction;;
const #106 = Asciz	r$1;
const #107 = Asciz	p;
const #108 = Asciz	args$1;
const #109 = Asciz	LocalVariableTable;
const #110 = Asciz	()Lscala/Function0<Ljava/lang/Object;>;;
const #111 = Asciz	rules;
const #112 = Asciz	(Lscala/collection/Sequence;)V;
const #113 = Asciz	ruls_$eq;
const #114 = Asciz	(Lscala/collection/immutable/List;)V;
const #115 = NameAndType	#113:#114;//  ruls_$eq:(Lscala/collection/immutable/List;)V
const #116 = Method	#16.#115;	//  scala/concurrent/jolib$Join.ruls_$eq:(Lscala/collection/immutable/List;)V
const #117 = Asciz	rs;
const #118 = Asciz	Lscala/collection/Sequence;;
const #119 = Asciz	(Lscala/collection/Sequence<Lscala/Tuple2<Lscala/collection/immutable/List<Lscala/concurrent/jolib$Signal;>;Lscala/PartialFunction<Lscala/collection/immutable/List<Ljava/lang/Object;>;Ljava/lang/Object;>;>;>;)V;
const #120 = Asciz	scala/concurrent/jolib$Join$$anonfun$values$1;
const #121 = class	#120;	//  scala/concurrent/jolib$Join$$anonfun$values$1
const #122 = Method	#121.#27;	//  scala/concurrent/jolib$Join$$anonfun$values$1."<init>":(Lscala/concurrent/jolib$Join;)V
const #123 = Asciz	scala/collection/immutable/List$;
const #124 = class	#123;	//  scala/collection/immutable/List$
const #125 = Asciz	Lscala/collection/immutable/List$;;
const #126 = NameAndType	#37:#125;//  MODULE$:Lscala/collection/immutable/List$;
const #127 = Field	#124.#126;	//  scala/collection/immutable/List$.MODULE$:Lscala/collection/immutable/List$;
const #128 = Asciz	builderFactory;
const #129 = Asciz	()Lscala/collection/generic/BuilderFactory;;
const #130 = NameAndType	#128:#129;//  builderFactory:()Lscala/collection/generic/BuilderFactory;
const #131 = Method	#124.#130;	//  scala/collection/immutable/List$.builderFactory:()Lscala/collection/generic/BuilderFactory;
const #132 = Asciz	scala/collection/generic/TraversableTemplate;
const #133 = class	#132;	//  scala/collection/generic/TraversableTemplate
const #134 = Asciz	map;
const #135 = Asciz	(Lscala/Function1;Lscala/collection/generic/BuilderFactory;)Ljava/lang/Object;;
const #136 = NameAndType	#134:#135;//  map:(Lscala/Function1;Lscala/collection/generic/BuilderFactory;)Ljava/lang/Object;
const #137 = InterfaceMethod	#133.#136;	//  scala/collection/generic/TraversableTemplate.map:(Lscala/Function1;Lscala/collection/generic/BuilderFactory;)Ljava/lang/Object;
const #138 = Asciz	(Lscala/collection/immutable/List<Lscala/concurrent/jolib$Signal;>;)Lscala/collection/immutable/List<Ljava/lang/Object;>;;
const #139 = Asciz	canMatch;
const #140 = Asciz	(Lscala/collection/immutable/List;)Z;
const #141 = Asciz	scala/concurrent/jolib$Join$$anonfun$canMatch$1;
const #142 = class	#141;	//  scala/concurrent/jolib$Join$$anonfun$canMatch$1
const #143 = Method	#142.#27;	//  scala/concurrent/jolib$Join$$anonfun$canMatch$1."<init>":(Lscala/concurrent/jolib$Join;)V
const #144 = Asciz	forall;
const #145 = Asciz	(Lscala/Function1;)Z;
const #146 = NameAndType	#144:#145;//  forall:(Lscala/Function1;)Z
const #147 = InterfaceMethod	#30.#146;	//  scala/collection/generic/LinearSequenceTemplate.forall:(Lscala/Function1;)Z
const #148 = Asciz	(Lscala/collection/immutable/List<Lscala/concurrent/jolib$Signal;>;)Z;
const #149 = Asciz	(Lscala/collection/immutable/List<Lscala/Tuple2<Lscala/collection/immutable/List<Lscala/concurrent/jolib$Signal;>;Lscala/PartialFunction<Lscala/collection/immutable/List<Ljava/lang/Object;>;Ljava/lang/Object;>;>;>;)V;
const #150 = Asciz	()Lscala/collection/immutable/List<Lscala/Tuple2<Lscala/collection/immutable/List<Lscala/concurrent/jolib$Signal;>;Lscala/PartialFunction<Lscala/collection/immutable/List<Ljava/lang/Object;>;Ljava/lang/Object;>;>;>;;
const #151 = Asciz	Scala;
const #152 = Asciz	InnerClasses;
const #153 = Asciz	scala/concurrent/jolib;
const #154 = class	#153;	//  scala/concurrent/jolib
const #155 = Asciz	Join;
const #156 = Asciz	$anonfun$values$1;
const #157 = Asciz	$anonfun$tryMatch$2;
const #158 = Asciz	$anonfun$tryMatch$3;
const #159 = Asciz	$anonfun$tryMatch$1;
const #160 = Asciz	$anonfun$canMatch$1;
const #161 = Asciz	scala/ScalaObject;
const #162 = class	#161;	//  scala/ScalaObject

{
public scala.concurrent.jolib$Join();
  Code:
   Stack=2, Locals=1, Args_size=1
   0:	aload_0
   1:	invokespecial	#14; //Method java/lang/Object."<init>":()V
   4:	aload_0
   5:	aconst_null
   6:	pop
   7:	aconst_null
   8:	putfield	#18; //Field ruls:Lscala/collection/immutable/List;
   11:	return
  LineNumberTable: 
   line 29: 0
   line 31: 4


public scala.Function0 tryMatch();
  Code:
   Stack=5, Locals=11, Args_size=1
   0:	aload_0
   1:	invokespecial	#23; //Method ruls:()Lscala/collection/immutable/List;
   4:	new	#25; //class scala/concurrent/jolib$Join$$anonfun$tryMatch$1
   7:	dup
   8:	aload_0
   9:	invokespecial	#28; //Method scala/concurrent/jolib$Join$$anonfun$tryMatch$1."<init>":(Lscala/concurrent/jolib$Join;)V
   12:	invokeinterface	#34,  2; //InterfaceMethod scala/collection/generic/LinearSequenceTemplate.find:(Lscala/Function1;)Lscala/Option;
   17:	astore_1
   18:	getstatic	#40; //Field scala/None$.MODULE$:Lscala/None$;
   21:	aload_1
   22:	astore_2
   23:	dup
   24:	ifnonnull	35
   27:	pop
   28:	aload_2
   29:	ifnull	42
   32:	goto	60
   35:	aload_2
   36:	invokevirtual	#44; //Method java/lang/Object.equals:(Ljava/lang/Object;)Z
   39:	ifeq	60
   42:	aload_1
   43:	instanceof	#36; //class scala/None$
   46:	ifeq	60
   49:	new	#46; //class scala/concurrent/jolib$Join$$anonfun$tryMatch$2
   52:	dup
   53:	aload_0
   54:	invokespecial	#47; //Method scala/concurrent/jolib$Join$$anonfun$tryMatch$2."<init>":(Lscala/concurrent/jolib$Join;)V
   57:	goto	157
   60:	aload_1
   61:	instanceof	#49; //class scala/Some
   64:	ifeq	170
   67:	aload_1
   68:	checkcast	#49; //class scala/Some
   71:	astore_3
   72:	aload_3
   73:	invokevirtual	#53; //Method scala/Some.x:()Ljava/lang/Object;
   76:	checkcast	#55; //class scala/Tuple2
   79:	astore	4
   81:	aload	4
   83:	ifnull	158
   86:	aload	4
   88:	invokevirtual	#58; //Method scala/Tuple2._1:()Ljava/lang/Object;
   91:	checkcast	#60; //class scala/collection/immutable/List
   94:	astore	5
   96:	aload	4
   98:	invokevirtual	#63; //Method scala/Tuple2._2:()Ljava/lang/Object;
   101:	astore	7
   103:	aload	7
   105:	instanceof	#65; //class scala/PartialFunction
   108:	ifeq	116
   111:	aload	7
   113:	goto	124
   116:	getstatic	#70; //Field scala/runtime/ScalaRunTime$.MODULE$:Lscala/runtime/ScalaRunTime$;
   119:	aload	7
   121:	invokevirtual	#74; //Method scala/runtime/ScalaRunTime$.boxArray:(Ljava/lang/Object;)Lscala/runtime/BoxedArray;
   124:	checkcast	#65; //class scala/PartialFunction
   127:	astore	6
   129:	aload	6
   131:	astore	8
   133:	aload	5
   135:	astore	9
   137:	aload_0
   138:	aload	9
   140:	invokevirtual	#78; //Method values:(Lscala/collection/immutable/List;)Lscala/collection/immutable/List;
   143:	astore	10
   145:	new	#80; //class scala/concurrent/jolib$Join$$anonfun$tryMatch$3
   148:	dup
   149:	aload_0
   150:	aload	8
   152:	aload	10
   154:	invokespecial	#83; //Method scala/concurrent/jolib$Join$$anonfun$tryMatch$3."<init>":(Lscala/concurrent/jolib$Join;Lscala/PartialFunction;Lscala/collection/immutable/List;)V
   157:	areturn
   158:	new	#85; //class scala/MatchError
   161:	dup
   162:	aload_1
   163:	invokevirtual	#91; //Method scala/Option.toString:()Ljava/lang/String;
   166:	invokespecial	#94; //Method scala/MatchError."<init>":(Ljava/lang/String;)V
   169:	athrow
   170:	new	#85; //class scala/MatchError
   173:	dup
   174:	aload_1
   175:	invokevirtual	#91; //Method scala/Option.toString:()Ljava/lang/String;
   178:	invokespecial	#94; //Method scala/MatchError."<init>":(Ljava/lang/String;)V
   181:	athrow
  LineNumberTable: 
   line 43: 0
   line 44: 49
   line 43: 60
   line 45: 129
   line 46: 137
   line 47: 145
   line 43: 157

  LocalVariableTable: 
   Start  Length  Slot  Name   Signature
   0      182      0    this       Lscala/concurrent/jolib$Join;
   18      164      1    temp4       Lscala/Option;
   72      85      3    temp6       Lscala/Some;
   158      12      3    temp6       Lscala/Some;
   81      76      4    temp7       Lscala/Tuple2;
   158      12      4    temp7       Lscala/Tuple2;
   96      61      5    temp8       Lscala/collection/immutable/List;
   129      28      6    temp9       Lscala/PartialFunction;
   133      24      8    r$1       Lscala/PartialFunction;
   137      20      9    p       Lscala/collection/immutable/List;
   145      12      10    args$1       Lscala/collection/immutable/List;

  Signature: length = 0x2
   00 6E 

public void rules(scala.collection.Sequence);
  Code:
   Stack=2, Locals=2, Args_size=2
   0:	aload_0
   1:	aload_1
   2:	checkcast	#60; //class scala/collection/immutable/List
   5:	invokespecial	#116; //Method ruls_$eq:(Lscala/collection/immutable/List;)V
   8:	return
  LineNumberTable: 
   line 40: 0

  LocalVariableTable: 
   Start  Length  Slot  Name   Signature
   0      9      0    this       Lscala/concurrent/jolib$Join;
   0      9      1    rs       Lscala/collection/Sequence;

  Signature: length = 0x2
   00 77 

public scala.collection.immutable.List values(scala.collection.immutable.List);
  Code:
   Stack=4, Locals=2, Args_size=2
   0:	aload_1
   1:	new	#121; //class scala/concurrent/jolib$Join$$anonfun$values$1
   4:	dup
   5:	aload_0
   6:	invokespecial	#122; //Method scala/concurrent/jolib$Join$$anonfun$values$1."<init>":(Lscala/concurrent/jolib$Join;)V
   9:	getstatic	#127; //Field scala/collection/immutable/List$.MODULE$:Lscala/collection/immutable/List$;
   12:	invokevirtual	#131; //Method scala/collection/immutable/List$.builderFactory:()Lscala/collection/generic/BuilderFactory;
   15:	invokeinterface	#137,  3; //InterfaceMethod scala/collection/generic/TraversableTemplate.map:(Lscala/Function1;Lscala/collection/generic/BuilderFactory;)Ljava/lang/Object;
   20:	checkcast	#60; //class scala/collection/immutable/List
   23:	areturn
  LineNumberTable: 
   line 37: 0

  LocalVariableTable: 
   Start  Length  Slot  Name   Signature
   0      24      0    this       Lscala/concurrent/jolib$Join;
   0      24      1    p       Lscala/collection/immutable/List;

  Signature: length = 0x2
   00 FFFFFF8A 

public boolean canMatch(scala.collection.immutable.List);
  Code:
   Stack=4, Locals=2, Args_size=2
   0:	aload_1
   1:	new	#142; //class scala/concurrent/jolib$Join$$anonfun$canMatch$1
   4:	dup
   5:	aload_0
   6:	invokespecial	#143; //Method scala/concurrent/jolib$Join$$anonfun$canMatch$1."<init>":(Lscala/concurrent/jolib$Join;)V
   9:	invokeinterface	#147,  2; //InterfaceMethod scala/collection/generic/LinearSequenceTemplate.forall:(Lscala/Function1;)Z
   14:	ireturn
  LineNumberTable: 
   line 34: 0

  LocalVariableTable: 
   Start  Length  Slot  Name   Signature
   0      15      0    this       Lscala/concurrent/jolib$Join;
   0      15      1    p       Lscala/collection/immutable/List;

  Signature: length = 0x2
   00 FFFFFF94 

}

