Compiled from "jolib.scala"
public final class scala.concurrent.jolib$Join$$anonfun$tryMatch$3 extends java.lang.Object implements scala.Function0,scala.ScalaObject,java.io.Serializable
  SourceFile: "jolib.scala"
  Scala: length = 0x
   
  InnerClass: 
   public #68= #65 of #67; //Join=class scala/concurrent/jolib$Join of class scala/concurrent/jolib
   public final #69= #12 of #65; //$anonfun$tryMatch$3=class scala/concurrent/jolib$Join$$anonfun$tryMatch$3 of class scala/concurrent/jolib$Join
   public final #70= #50 of #12; //$anonfun$apply$1=class scala/concurrent/jolib$Join$$anonfun$tryMatch$3$$anonfun$apply$1 of class scala/concurrent/jolib$Join$$anonfun$tryMatch$3
  minor version: 0
  major version: 49
  Constant pool:
const #1 = Asciz	SourceFile;
const #2 = Asciz	jolib.scala;
const #3 = Asciz	args$1;
const #4 = Asciz	Lscala/collection/immutable/List;;
const #5 = Asciz	r$1;
const #6 = Asciz	Lscala/PartialFunction;;
const #7 = Asciz	<init>;
const #8 = Asciz	(Lscala/concurrent/jolib$Join;Lscala/PartialFunction;Lscala/collection/immutable/List;)V;
const #9 = Asciz	Code;
const #10 = Asciz	LineNumberTable;
const #11 = Asciz	scala/concurrent/jolib$Join$$anonfun$tryMatch$3;
const #12 = class	#11;	//  scala/concurrent/jolib$Join$$anonfun$tryMatch$3
const #13 = NameAndType	#5:#6;//  r$1:Lscala/PartialFunction;
const #14 = Field	#12.#13;	//  scala/concurrent/jolib$Join$$anonfun$tryMatch$3.r$1:Lscala/PartialFunction;
const #15 = NameAndType	#3:#4;//  args$1:Lscala/collection/immutable/List;
const #16 = Field	#12.#15;	//  scala/concurrent/jolib$Join$$anonfun$tryMatch$3.args$1:Lscala/collection/immutable/List;
const #17 = Asciz	java/lang/Object;
const #18 = class	#17;	//  java/lang/Object
const #19 = Asciz	()V;
const #20 = NameAndType	#7:#19;//  "<init>":()V
const #21 = Method	#18.#20;	//  java/lang/Object."<init>":()V
const #22 = Asciz	scala/Function0$class;
const #23 = class	#22;	//  scala/Function0$class
const #24 = Asciz	$init$;
const #25 = Asciz	(Lscala/Function0;)V;
const #26 = NameAndType	#24:#25;//  $init$:(Lscala/Function0;)V
const #27 = Method	#23.#26;	//  scala/Function0$class.$init$:(Lscala/Function0;)V
const #28 = Asciz	this;
const #29 = Asciz	Lscala/concurrent/jolib$Join$$anonfun$tryMatch$3;;
const #30 = Asciz	$outer;
const #31 = Asciz	Lscala/concurrent/jolib$Join;;
const #32 = Asciz	LocalVariableTable;
const #33 = Asciz	apply;
const #34 = Asciz	()Ljava/lang/Object;;
const #35 = NameAndType	#33:#19;//  apply:()V
const #36 = Method	#12.#35;	//  scala/concurrent/jolib$Join$$anonfun$tryMatch$3.apply:()V
const #37 = Asciz	scala/runtime/BoxedUnit;
const #38 = class	#37;	//  scala/runtime/BoxedUnit
const #39 = Asciz	UNIT;
const #40 = Asciz	Lscala/runtime/BoxedUnit;;
const #41 = NameAndType	#39:#40;//  UNIT:Lscala/runtime/BoxedUnit;
const #42 = Field	#38.#41;	//  scala/runtime/BoxedUnit.UNIT:Lscala/runtime/BoxedUnit;
const #43 = Asciz	scala/concurrent/ops$;
const #44 = class	#43;	//  scala/concurrent/ops$
const #45 = Asciz	MODULE$;
const #46 = Asciz	Lscala/concurrent/ops$;;
const #47 = NameAndType	#45:#46;//  MODULE$:Lscala/concurrent/ops$;
const #48 = Field	#44.#47;	//  scala/concurrent/ops$.MODULE$:Lscala/concurrent/ops$;
const #49 = Asciz	scala/concurrent/jolib$Join$$anonfun$tryMatch$3$$anonfun$apply$1;
const #50 = class	#49;	//  scala/concurrent/jolib$Join$$anonfun$tryMatch$3$$anonfun$apply$1
const #51 = Asciz	(Lscala/concurrent/jolib$Join$$anonfun$tryMatch$3;)V;
const #52 = NameAndType	#7:#51;//  "<init>":(Lscala/concurrent/jolib$Join$$anonfun$tryMatch$3;)V
const #53 = Method	#50.#52;	//  scala/concurrent/jolib$Join$$anonfun$tryMatch$3$$anonfun$apply$1."<init>":(Lscala/concurrent/jolib$Join$$anonfun$tryMatch$3;)V
const #54 = Asciz	spawn;
const #55 = NameAndType	#54:#25;//  spawn:(Lscala/Function0;)V
const #56 = Method	#44.#55;	//  scala/concurrent/ops$.spawn:(Lscala/Function0;)V
const #57 = Asciz	toString;
const #58 = Asciz	()Ljava/lang/String;;
const #59 = Asciz	(Lscala/Function0;)Ljava/lang/String;;
const #60 = NameAndType	#57:#59;//  toString:(Lscala/Function0;)Ljava/lang/String;
const #61 = Method	#23.#60;	//  scala/Function0$class.toString:(Lscala/Function0;)Ljava/lang/String;
const #62 = Asciz	Scala;
const #63 = Asciz	InnerClasses;
const #64 = Asciz	scala/concurrent/jolib$Join;
const #65 = class	#64;	//  scala/concurrent/jolib$Join
const #66 = Asciz	scala/concurrent/jolib;
const #67 = class	#66;	//  scala/concurrent/jolib
const #68 = Asciz	Join;
const #69 = Asciz	$anonfun$tryMatch$3;
const #70 = Asciz	$anonfun$apply$1;
const #71 = Asciz	scala/Function0;
const #72 = class	#71;	//  scala/Function0
const #73 = Asciz	scala/ScalaObject;
const #74 = class	#73;	//  scala/ScalaObject
const #75 = Asciz	java/io/Serializable;
const #76 = class	#75;	//  java/io/Serializable

{
public final scala.collection.immutable.List args$1;

public final scala.PartialFunction r$1;

public scala.concurrent.jolib$Join$$anonfun$tryMatch$3(scala.concurrent.jolib$Join, scala.PartialFunction, scala.collection.immutable.List);
  Code:
   Stack=2, Locals=4, Args_size=4
   0:	aload_0
   1:	aload_2
   2:	putfield	#14; //Field r$1:Lscala/PartialFunction;
   5:	aload_0
   6:	aload_3
   7:	putfield	#16; //Field args$1:Lscala/collection/immutable/List;
   10:	aload_0
   11:	invokespecial	#21; //Method java/lang/Object."<init>":()V
   14:	aload_0
   15:	invokestatic	#27; //Method scala/Function0$class.$init$:(Lscala/Function0;)V
   18:	return
  LineNumberTable: 
   line 47: 0

  LocalVariableTable: 
   Start  Length  Slot  Name   Signature
   0      19      0    this       Lscala/concurrent/jolib$Join$$anonfun$tryMatch$3;
   0      19      1    $outer       Lscala/concurrent/jolib$Join;


public final java.lang.Object apply();
  Code:
   Stack=1, Locals=1, Args_size=1
   0:	aload_0
   1:	invokevirtual	#36; //Method apply:()V
   4:	getstatic	#42; //Field scala/runtime/BoxedUnit.UNIT:Lscala/runtime/BoxedUnit;
   7:	areturn
  LineNumberTable: 
   line 47: 0


public final void apply();
  Code:
   Stack=4, Locals=1, Args_size=1
   0:	getstatic	#48; //Field scala/concurrent/ops$.MODULE$:Lscala/concurrent/ops$;
   3:	new	#50; //class scala/concurrent/jolib$Join$$anonfun$tryMatch$3$$anonfun$apply$1
   6:	dup
   7:	aload_0
   8:	invokespecial	#53; //Method scala/concurrent/jolib$Join$$anonfun$tryMatch$3$$anonfun$apply$1."<init>":(Lscala/concurrent/jolib$Join$$anonfun$tryMatch$3;)V
   11:	invokevirtual	#56; //Method scala/concurrent/ops$.spawn:(Lscala/Function0;)V
   14:	return
  LineNumberTable: 
   line 47: 0


public java.lang.String toString();
  Code:
   Stack=1, Locals=1, Args_size=1
   0:	aload_0
   1:	invokestatic	#61; //Method scala/Function0$class.toString:(Lscala/Function0;)Ljava/lang/String;
   4:	areturn
  LineNumberTable: 
   line 47: 0


}

