Compiled from "jolib.scala"
public final class scala.concurrent.jolib$ extends java.lang.Object implements scala.ScalaObject
  SourceFile: "jolib.scala"
  Scala: length = 0x
   
  InnerClass: 
   public #25= #22 of #24; //Join=class scala/concurrent/jolib$Join of class scala/concurrent/jolib
   public abstract #28= #27 of #24; //Signal=class scala/concurrent/jolib$Signal of class scala/concurrent/jolib
   public abstract #31= #30 of #24; //Synchr=class scala/concurrent/jolib$Synchr of class scala/concurrent/jolib
   public abstract #34= #33 of #24; //Asynchr=class scala/concurrent/jolib$Asynchr of class scala/concurrent/jolib
  minor version: 0
  major version: 49
  Constant pool:
const #1 = Asciz	SourceFile;
const #2 = Asciz	jolib.scala;
const #3 = Asciz	Scala;
const #4 = Asciz	MODULE$;
const #5 = Asciz	Lscala/concurrent/jolib$;;
const #6 = Asciz	<clinit>;
const #7 = Asciz	()V;
const #8 = Asciz	Code;
const #9 = Asciz	scala/concurrent/jolib$;
const #10 = class	#9;	//  scala/concurrent/jolib$
const #11 = Asciz	<init>;
const #12 = NameAndType	#11:#7;//  "<init>":()V
const #13 = Method	#10.#12;	//  scala/concurrent/jolib$."<init>":()V
const #14 = Asciz	LineNumberTable;
const #15 = Asciz	java/lang/Object;
const #16 = class	#15;	//  java/lang/Object
const #17 = Method	#16.#12;	//  java/lang/Object."<init>":()V
const #18 = NameAndType	#4:#5;//  MODULE$:Lscala/concurrent/jolib$;
const #19 = Field	#10.#18;	//  scala/concurrent/jolib$.MODULE$:Lscala/concurrent/jolib$;
const #20 = Asciz	InnerClasses;
const #21 = Asciz	scala/concurrent/jolib$Join;
const #22 = class	#21;	//  scala/concurrent/jolib$Join
const #23 = Asciz	scala/concurrent/jolib;
const #24 = class	#23;	//  scala/concurrent/jolib
const #25 = Asciz	Join;
const #26 = Asciz	scala/concurrent/jolib$Signal;
const #27 = class	#26;	//  scala/concurrent/jolib$Signal
const #28 = Asciz	Signal;
const #29 = Asciz	scala/concurrent/jolib$Synchr;
const #30 = class	#29;	//  scala/concurrent/jolib$Synchr
const #31 = Asciz	Synchr;
const #32 = Asciz	scala/concurrent/jolib$Asynchr;
const #33 = class	#32;	//  scala/concurrent/jolib$Asynchr
const #34 = Asciz	Asynchr;
const #35 = Asciz	scala/ScalaObject;
const #36 = class	#35;	//  scala/ScalaObject

{
public static final scala.concurrent.jolib$ MODULE$;

public static {};
  Code:
   Stack=1, Locals=0, Args_size=0
   0:	new	#10; //class scala/concurrent/jolib$
   3:	invokespecial	#13; //Method "<init>":()V
   6:	return

}

