Compiled from "jolib.scala"
public abstract class scala.concurrent.jolib$Synchr extends scala.concurrent.jolib$Signal implements scala.ScalaObject
  SourceFile: "jolib.scala"
  Signature: length = 0x2
   00 22 
  Scala: length = 0x
   
  InnerClass: 
   public #41= #38 of #40; //Join=class scala/concurrent/jolib$Join of class scala/concurrent/jolib
   public abstract #42= #8 of #40; //Signal=class scala/concurrent/jolib$Signal of class scala/concurrent/jolib
   public abstract #43= #20 of #40; //Synchr=class scala/concurrent/jolib$Synchr of class scala/concurrent/jolib
  minor version: 0
  major version: 49
  Constant pool:
const #1 = Asciz	SourceFile;
const #2 = Asciz	jolib.scala;
const #3 = Asciz	<init>;
const #4 = Asciz	(Lscala/concurrent/jolib$Join;)V;
const #5 = Asciz	Code;
const #6 = Asciz	LineNumberTable;
const #7 = Asciz	scala/concurrent/jolib$Signal;
const #8 = class	#7;	//  scala/concurrent/jolib$Signal
const #9 = NameAndType	#3:#4;//  "<init>":(Lscala/concurrent/jolib$Join;)V
const #10 = Method	#8.#9;	//  scala/concurrent/jolib$Signal."<init>":(Lscala/concurrent/jolib$Join;)V
const #11 = Asciz	this;
const #12 = Asciz	Lscala/concurrent/jolib$Synchr;;
const #13 = Asciz	join;
const #14 = Asciz	Lscala/concurrent/jolib$Join;;
const #15 = Asciz	LocalVariableTable;
const #16 = Asciz	Signature;
const #17 = Asciz	apply;
const #18 = Asciz	(Lscala/concurrent/SyncVar;)Ljava/lang/Object;;
const #19 = Asciz	scala/concurrent/jolib$Synchr;
const #20 = class	#19;	//  scala/concurrent/jolib$Synchr
const #21 = Asciz	tryReduction;
const #22 = Asciz	(Ljava/lang/Object;)V;
const #23 = NameAndType	#21:#22;//  tryReduction:(Ljava/lang/Object;)V
const #24 = Method	#20.#23;	//  scala/concurrent/jolib$Synchr.tryReduction:(Ljava/lang/Object;)V
const #25 = Asciz	scala/concurrent/SyncVar;
const #26 = class	#25;	//  scala/concurrent/SyncVar
const #27 = Asciz	get;
const #28 = Asciz	()Ljava/lang/Object;;
const #29 = NameAndType	#27:#28;//  get:()Ljava/lang/Object;
const #30 = Method	#26.#29;	//  scala/concurrent/SyncVar.get:()Ljava/lang/Object;
const #31 = Asciz	x;
const #32 = Asciz	Lscala/concurrent/SyncVar;;
const #33 = Asciz	(Lscala/concurrent/SyncVar<TA;>;)TA;;
const #34 = Asciz	<A:Ljava/lang/Object;>Lscala/concurrent/jolib$Signal;Lscala/ScalaObject;;
const #35 = Asciz	Scala;
const #36 = Asciz	InnerClasses;
const #37 = Asciz	scala/concurrent/jolib$Join;
const #38 = class	#37;	//  scala/concurrent/jolib$Join
const #39 = Asciz	scala/concurrent/jolib;
const #40 = class	#39;	//  scala/concurrent/jolib
const #41 = Asciz	Join;
const #42 = Asciz	Signal;
const #43 = Asciz	Synchr;
const #44 = Asciz	scala/ScalaObject;
const #45 = class	#44;	//  scala/ScalaObject

{
public scala.concurrent.jolib$Synchr(scala.concurrent.jolib$Join);
  Code:
   Stack=2, Locals=2, Args_size=2
   0:	aload_0
   1:	aload_1
   2:	invokespecial	#10; //Method scala/concurrent/jolib$Signal."<init>":(Lscala/concurrent/jolib$Join;)V
   5:	return
  LineNumberTable: 
   line 71: 0

  LocalVariableTable: 
   Start  Length  Slot  Name   Signature
   0      6      0    this       Lscala/concurrent/jolib$Synchr;
   0      6      1    join       Lscala/concurrent/jolib$Join;

  Signature: length = 0x2
   00 04 

public java.lang.Object apply(scala.concurrent.SyncVar);
  Code:
   Stack=2, Locals=2, Args_size=2
   0:	aload_0
   1:	aload_1
   2:	invokevirtual	#24; //Method tryReduction:(Ljava/lang/Object;)V
   5:	aload_1
   6:	invokevirtual	#30; //Method scala/concurrent/SyncVar.get:()Ljava/lang/Object;
   9:	areturn
  LineNumberTable: 
   line 74: 0
   line 75: 5

  LocalVariableTable: 
   Start  Length  Slot  Name   Signature
   0      10      0    this       Lscala/concurrent/jolib$Synchr;
   0      10      1    x       Lscala/concurrent/SyncVar;

  Signature: length = 0x2
   00 21 

}

