Compiled from "MailBox.scala"
public final class scala.concurrent.LinkedListQueueCreator$$anon$2 extends java.lang.Object implements scala.concurrent.QueueModule
  SourceFile: "MailBox.scala"
  Signature: length = 0x2
   00 67 
  Scala: length = 0x
   
  InnerClass: 
   public final $anon$2=class scala/concurrent/LinkedListQueueCreator$$anon$2 of class scala/concurrent/LinkedListQueueCreator
  minor version: 0
  major version: 49
  Constant pool:
Asciz	SourceFile;
Asciz	MailBox.scala;
Asciz	make;
Asciz	()Lscala/Tuple2;;
Asciz	Code;
Asciz	scala/collection/mutable/LinkedList;
class	scala/collection/mutable/LinkedList
Asciz	LineNumberTable;
Asciz	<init>;
Asciz	(Ljava/lang/Object;Lscala/collection/mutable/LinkedList;)V;
NameAndType	"<init>":(Ljava/lang/Object;Lscala/collection/mutable/LinkedList;)V
Method	scala/collection/mutable/LinkedList."<init>":(Ljava/lang/Object;Lscala/collection/mutable/LinkedList;)V
Asciz	scala/Tuple2;
class	scala/Tuple2
Asciz	(Ljava/lang/Object;Ljava/lang/Object;)V;
NameAndType	"<init>":(Ljava/lang/Object;Ljava/lang/Object;)V
Method	scala/Tuple2."<init>":(Ljava/lang/Object;Ljava/lang/Object;)V
Asciz	this;
Asciz	Lscala/concurrent/LinkedListQueueCreator$$anon$2;;
Asciz	l;
Asciz	Lscala/collection/mutable/LinkedList;;
Asciz	LocalVariableTable;
Asciz	()Lscala/Tuple2<Lscala/collection/mutable/LinkedList<TA;>;Lscala/collection/mutable/LinkedList<TA;>;>;;
Asciz	Signature;
Asciz	append;
Asciz	(Lscala/Tuple2;Ljava/lang/Object;)Lscala/Tuple2;;
Asciz	_2;
Asciz	()Ljava/lang/Object;;
NameAndType	_2:()Ljava/lang/Object;
Method	scala/Tuple2._2:()Ljava/lang/Object;
Asciz	scala/collection/mutable/LinkedListLike;
class	scala/collection/mutable/LinkedListLike
Asciz	(Lscala/collection/mutable/Seq;)Lscala/collection/mutable/Seq;;
NameAndType	append:(Lscala/collection/mutable/Seq;)Lscala/collection/mutable/Seq;
InterfaceMethod	scala/collection/mutable/LinkedListLike.append:(Lscala/collection/mutable/Seq;)Lscala/collection/mutable/Seq;
Asciz	_1;
NameAndType	_1:()Ljava/lang/Object;
Method	scala/Tuple2._1:()Ljava/lang/Object;
Asciz	Lscala/Tuple2;;
Asciz	x;
Asciz	Ljava/lang/Object;;
Asciz	atTail;
Asciz	(Lscala/Tuple2<Lscala/collection/mutable/LinkedList<TA;>;Lscala/collection/mutable/LinkedList<TA;>;>;TA;)Lscala/Tuple2<Lscala/collection/mutable/LinkedList<TA;>;Lscala/collection/mutable/LinkedList<TA;>;>;;
Asciz	extractFirst;
Asciz	(Lscala/Tuple2;Lscala/Function1;)Lscala/Option;;
Asciz	next;
Asciz	()Lscala/collection/mutable/Seq;;
NameAndType	next:()Lscala/collection/mutable/Seq;
InterfaceMethod	scala/collection/mutable/LinkedListLike.next:()Lscala/collection/mutable/Seq;
Asciz	elem;
NameAndType	elem:()Ljava/lang/Object;
InterfaceMethod	scala/collection/mutable/LinkedListLike.elem:()Ljava/lang/Object;
Asciz	scala/Function1;
class	scala/Function1
Asciz	apply;
Asciz	(Ljava/lang/Object;)Ljava/lang/Object;;
NameAndType	apply:(Ljava/lang/Object;)Ljava/lang/Object;
InterfaceMethod	scala/Function1.apply:(Ljava/lang/Object;)Ljava/lang/Object;
Asciz	scala/runtime/BoxesRunTime;
class	scala/runtime/BoxesRunTime
Asciz	unboxToBoolean;
Asciz	(Ljava/lang/Object;)Z;
NameAndType	unboxToBoolean:(Ljava/lang/Object;)Z
Method	scala/runtime/BoxesRunTime.unboxToBoolean:(Ljava/lang/Object;)Z
Asciz	next_$eq;
Asciz	(Lscala/collection/mutable/Seq;)V;
NameAndType	next_$eq:(Lscala/collection/mutable/Seq;)V
InterfaceMethod	scala/collection/mutable/LinkedListLike.next_$eq:(Lscala/collection/mutable/Seq;)V
Asciz	scala/Some;
class	scala/Some
Asciz	(Ljava/lang/Object;)V;
NameAndType	"<init>":(Ljava/lang/Object;)V
Method	scala/Some."<init>":(Ljava/lang/Object;)V
Asciz	scala/None$;
class	scala/None$
Asciz	MODULE$;
Asciz	Lscala/None$;;
NameAndType	MODULE$:Lscala/None$;
Field	scala/None$.MODULE$:Lscala/None$;
Asciz	p;
Asciz	Lscala/Function1;;
Asciz	xs;
Asciz	xs1;
Asciz	(Lscala/Tuple2<Lscala/collection/mutable/LinkedList<TA;>;Lscala/collection/mutable/LinkedList<TA;>;>;Lscala/Function1<TA;Ljava/lang/Boolean;>;)Lscala/Option<Lscala/Tuple2<TA;Lscala/Tuple2<Lscala/collection/mutable/LinkedList<TA;>;Lscala/collection/mutable/LinkedList<TA;>;>;>;>;;
Asciz	(Ljava/lang/Object;Lscala/Function1;)Lscala/Option;;
Asciz	scala/concurrent/LinkedListQueueCreator$$anon$2;
class	scala/concurrent/LinkedListQueueCreator$$anon$2
NameAndType	extractFirst:(Lscala/Tuple2;Lscala/Function1;)Lscala/Option;
Method	scala/concurrent/LinkedListQueueCreator$$anon$2.extractFirst:(Lscala/Tuple2;Lscala/Function1;)Lscala/Option;
Asciz	(Ljava/lang/Object;Ljava/lang/Object;)Ljava/lang/Object;;
NameAndType	append:(Lscala/Tuple2;Ljava/lang/Object;)Lscala/Tuple2;
Method	scala/concurrent/LinkedListQueueCreator$$anon$2.append:(Lscala/Tuple2;Ljava/lang/Object;)Lscala/Tuple2;
NameAndType	make:()Lscala/Tuple2;
Method	scala/concurrent/LinkedListQueueCreator$$anon$2.make:()Lscala/Tuple2;
Asciz	(Lscala/concurrent/LinkedListQueueCreator;)V;
Asciz	java/lang/Object;
class	java/lang/Object
Asciz	()V;
NameAndType	"<init>":()V
Method	java/lang/Object."<init>":()V
Asciz	$outer;
Asciz	Lscala/concurrent/LinkedListQueueCreator;;
Asciz	Ljava/lang/Object;Lscala/concurrent/QueueModule<TA;>;;
Asciz	Scala;
Asciz	InnerClasses;
Asciz	scala/concurrent/LinkedListQueueCreator;
class	scala/concurrent/LinkedListQueueCreator
Asciz	$anon$2;
Asciz	scala/concurrent/QueueModule;
class	scala/concurrent/QueueModule

{
public scala.Tuple2 make();
  Signature: ()Lscala/Tuple2;
  Code:
   Stack=4, Locals=2, Args_size=1
	new	class scala/collection/mutable/LinkedList
	dup
	aconst_null
	pop
	aconst_null
	aconst_null
	pop
	aconst_null
	invokespecial	Method scala/collection/mutable/LinkedList."<init>":(Ljava/lang/Object;Lscala/collection/mutable/LinkedList;)V
	astore_1
	new	class scala/Tuple2
	dup
	aload_1
	aload_1
	invokespecial	Method scala/Tuple2."<init>":(Ljava/lang/Object;Ljava/lang/Object;)V
	areturn
  Labels:
  LocalVariableTable: 
   Start  Length  Slot  Name   Signature
   0      24      0    this       Lscala/concurrent/LinkedListQueueCreator$$anon$2;
   14      9      1    l       Lscala/collection/mutable/LinkedList;

  Signature: length = 0x2
   00 17 

public scala.Tuple2 append(scala.Tuple2, java.lang.Object);
  Signature: (Lscala/Tuple2;Ljava/lang/Object;)Lscala/Tuple2;
  Code:
   Stack=4, Locals=4, Args_size=3
	new	class scala/collection/mutable/LinkedList
	dup
	aload_2
	aconst_null
	pop
	aconst_null
	invokespecial	Method scala/collection/mutable/LinkedList."<init>":(Ljava/lang/Object;Lscala/collection/mutable/LinkedList;)V
	astore_3
	aload_1
	invokevirtual	Method scala/Tuple2._2:()Ljava/lang/Object;
	checkcast	class scala/collection/mutable/LinkedListLike
	aload_3
	invokeinterface	InterfaceMethod scala/collection/mutable/LinkedListLike.append:(Lscala/collection/mutable/Seq;)Lscala/collection/mutable/Seq;
	pop
	new	class scala/Tuple2
	dup
	aload_1
	invokevirtual	Method scala/Tuple2._1:()Ljava/lang/Object;
	aload_3
	invokespecial	Method scala/Tuple2."<init>":(Ljava/lang/Object;Ljava/lang/Object;)V
	areturn
  Labels:
  LocalVariableTable: 
   Start  Length  Slot  Name   Signature
   0      39      0    this       Lscala/concurrent/LinkedListQueueCreator$$anon$2;
   0      39      1    l       Lscala/Tuple2;
   0      39      2    x       Ljava/lang/Object;
   12      26      3    atTail       Lscala/collection/mutable/LinkedList;

  Signature: length = 0x2
   00 2B 

public scala.Option extractFirst(scala.Tuple2, scala.Function1);
  Signature: (Lscala/Tuple2;Lscala/Function1;)Lscala/Option;
  Code:
   Stack=9, Locals=5, Args_size=3
	aload_1
	invokevirtual	Method scala/Tuple2._1:()Ljava/lang/Object;
	checkcast	class scala/collection/mutable/LinkedList
	astore_3
	aload_3
	invokeinterface	InterfaceMethod scala/collection/mutable/LinkedListLike.next:()Lscala/collection/mutable/Seq;
	checkcast	class scala/collection/mutable/LinkedList
	astore	4
l2	aload	4
	ifnull	l1 // aload
	aload_2
	aload	4
	invokeinterface	InterfaceMethod scala/collection/mutable/LinkedListLike.elem:()Ljava/lang/Object;
	invokeinterface	InterfaceMethod scala/Function1.apply:(Ljava/lang/Object;)Ljava/lang/Object;
	invokestatic	Method scala/runtime/BoxesRunTime.unboxToBoolean:(Ljava/lang/Object;)Z
	ifne	l1 // aload
	aload	4
	astore_3
	aload	4
	invokeinterface	InterfaceMethod scala/collection/mutable/LinkedListLike.next:()Lscala/collection/mutable/Seq;
	checkcast	class scala/collection/mutable/LinkedList
	astore	4
	goto	l2 // aload
l1	aload	4
	ifnull	l3 // getstatic
	aload_3
	aload	4
	invokeinterface	InterfaceMethod scala/collection/mutable/LinkedListLike.next:()Lscala/collection/mutable/Seq;
	invokeinterface	InterfaceMethod scala/collection/mutable/LinkedListLike.next_$eq:(Lscala/collection/mutable/Seq;)V
	aload_3
	invokeinterface	InterfaceMethod scala/collection/mutable/LinkedListLike.next:()Lscala/collection/mutable/Seq;
	ifnonnull	l4 // new
	new	class scala/Some
	dup
	new	class scala/Tuple2
	dup
	aload	4
	invokeinterface	InterfaceMethod scala/collection/mutable/LinkedListLike.elem:()Ljava/lang/Object;
	new	class scala/Tuple2
	dup
	aload_1
	invokevirtual	Method scala/Tuple2._1:()Ljava/lang/Object;
	aload_3
	invokespecial	Method scala/Tuple2."<init>":(Ljava/lang/Object;Ljava/lang/Object;)V
	invokespecial	Method scala/Tuple2."<init>":(Ljava/lang/Object;Ljava/lang/Object;)V
	invokespecial	Method scala/Some."<init>":(Ljava/lang/Object;)V
	goto	l5 // areturn
l4	new	class scala/Some
	dup
	new	class scala/Tuple2
	dup
	aload	4
	invokeinterface	InterfaceMethod scala/collection/mutable/LinkedListLike.elem:()Ljava/lang/Object;
	aload_1
	invokespecial	Method scala/Tuple2."<init>":(Ljava/lang/Object;Ljava/lang/Object;)V
	invokespecial	Method scala/Some."<init>":(Ljava/lang/Object;)V
	goto	l5 // areturn
l3	getstatic	Field scala/None$.MODULE$:Lscala/None$;
l5	areturn
  Labels:
   	l2 = 19 // aload
   	l1 = 61 // aload
   	l4 = 124 // new
   	l3 = 149 // getstatic
   	l5 = 152 // areturn
  LocalVariableTable: 
   Start  Length  Slot  Name   Signature
   0      153      0    this       Lscala/concurrent/LinkedListQueueCreator$$anon$2;
   0      153      1    l       Lscala/Tuple2;
   0      153      2    p       Lscala/Function1;
   8      145      3    xs       Lscala/collection/mutable/LinkedList;
   19      134      4    xs1       Lscala/collection/mutable/LinkedList;

  Signature: length = 0x2
   00 54 

public scala.Option extractFirst(java.lang.Object, scala.Function1);
  Signature: (Ljava/lang/Object;Lscala/Function1;)Lscala/Option;
  Code:
   Stack=3, Locals=3, Args_size=3
	aload_0
	aload_1
	checkcast	class scala/Tuple2
	aload_2
	invokevirtual	Method extractFirst:(Lscala/Tuple2;Lscala/Function1;)Lscala/Option;
	areturn
  Labels:
  LocalVariableTable: 
   Start  Length  Slot  Name   Signature
   0      10      0    this       Lscala/concurrent/LinkedListQueueCreator$$anon$2;
   0      10      1    l       Ljava/lang/Object;
   0      10      2    p       Lscala/Function1;


public java.lang.Object append(java.lang.Object, java.lang.Object);
  Signature: (Ljava/lang/Object;Ljava/lang/Object;)Ljava/lang/Object;
  Code:
   Stack=3, Locals=3, Args_size=3
	aload_0
	aload_1
	checkcast	class scala/Tuple2
	aload_2
	invokevirtual	Method append:(Lscala/Tuple2;Ljava/lang/Object;)Lscala/Tuple2;
	areturn
  Labels:
  LocalVariableTable: 
   Start  Length  Slot  Name   Signature
   0      10      0    this       Lscala/concurrent/LinkedListQueueCreator$$anon$2;
   0      10      1    l       Ljava/lang/Object;
   0      10      2    x       Ljava/lang/Object;


public java.lang.Object make();
  Signature: ()Ljava/lang/Object;
  Code:
   Stack=1, Locals=1, Args_size=1
	aload_0
	invokevirtual	Method make:()Lscala/Tuple2;
	areturn
  Labels:

public scala.concurrent.LinkedListQueueCreator$$anon$2(scala.concurrent.LinkedListQueueCreator);
  Signature: (Lscala/concurrent/LinkedListQueueCreator;)V
  Code:
   Stack=1, Locals=2, Args_size=2
	aload_0
	invokespecial	Method java/lang/Object."<init>":()V
	return
  Labels:
  LocalVariableTable: 
   Start  Length  Slot  Name   Signature
   0      5      0    this       Lscala/concurrent/LinkedListQueueCreator$$anon$2;
   0      5      1    $outer       Lscala/concurrent/LinkedListQueueCreator;


}

