Compiled from "MailBox.scala"
public final class scala.concurrent.LinkedListQueueCreator$$anon$2 extends java.lang.Object implements scala.concurrent.QueueModule
  SourceFile: "MailBox.scala"
  Signature: length = 0x2
   00 67 
  Scala: length = 0x
   
  InnerClass: 
   public final #108= #20 of #107; //$anon$2=class scala/concurrent/LinkedListQueueCreator$$anon$2 of class scala/concurrent/LinkedListQueueCreator
  minor version: 0
  major version: 49
  Constant pool:
const #1 = Asciz	SourceFile;
const #2 = Asciz	MailBox.scala;
const #3 = Asciz	<init>;
const #4 = Asciz	(Lscala/concurrent/LinkedListQueueCreator;)V;
const #5 = Asciz	Code;
const #6 = Asciz	LineNumberTable;
const #7 = Asciz	java/lang/Object;
const #8 = class	#7;	//  java/lang/Object
const #9 = Asciz	()V;
const #10 = NameAndType	#3:#9;//  "<init>":()V
const #11 = Method	#8.#10;	//  java/lang/Object."<init>":()V
const #12 = Asciz	this;
const #13 = Asciz	Lscala/concurrent/LinkedListQueueCreator$$anon$2;;
const #14 = Asciz	$outer;
const #15 = Asciz	Lscala/concurrent/LinkedListQueueCreator;;
const #16 = Asciz	LocalVariableTable;
const #17 = Asciz	make;
const #18 = Asciz	()Ljava/lang/Object;;
const #19 = Asciz	scala/concurrent/LinkedListQueueCreator$$anon$2;
const #20 = class	#19;	//  scala/concurrent/LinkedListQueueCreator$$anon$2
const #21 = Asciz	()Lscala/Tuple2;;
const #22 = NameAndType	#17:#21;//  make:()Lscala/Tuple2;
const #23 = Method	#20.#22;	//  scala/concurrent/LinkedListQueueCreator$$anon$2.make:()Lscala/Tuple2;
const #24 = Asciz	append;
const #25 = Asciz	(Ljava/lang/Object;Ljava/lang/Object;)Ljava/lang/Object;;
const #26 = Asciz	scala/Tuple2;
const #27 = class	#26;	//  scala/Tuple2
const #28 = Asciz	(Lscala/Tuple2;Ljava/lang/Object;)Lscala/Tuple2;;
const #29 = NameAndType	#24:#28;//  append:(Lscala/Tuple2;Ljava/lang/Object;)Lscala/Tuple2;
const #30 = Method	#20.#29;	//  scala/concurrent/LinkedListQueueCreator$$anon$2.append:(Lscala/Tuple2;Ljava/lang/Object;)Lscala/Tuple2;
const #31 = Asciz	l;
const #32 = Asciz	Ljava/lang/Object;;
const #33 = Asciz	x;
const #34 = Asciz	extractFirst;
const #35 = Asciz	(Ljava/lang/Object;Lscala/Function1;)Lscala/Option;;
const #36 = Asciz	(Lscala/Tuple2;Lscala/Function1;)Lscala/Option;;
const #37 = NameAndType	#34:#36;//  extractFirst:(Lscala/Tuple2;Lscala/Function1;)Lscala/Option;
const #38 = Method	#20.#37;	//  scala/concurrent/LinkedListQueueCreator$$anon$2.extractFirst:(Lscala/Tuple2;Lscala/Function1;)Lscala/Option;
const #39 = Asciz	p;
const #40 = Asciz	Lscala/Function1;;
const #41 = Asciz	_1;
const #42 = NameAndType	#41:#18;//  _1:()Ljava/lang/Object;
const #43 = Method	#27.#42;	//  scala/Tuple2._1:()Ljava/lang/Object;
const #44 = Asciz	scala/collection/mutable/LinkedList;
const #45 = class	#44;	//  scala/collection/mutable/LinkedList
const #46 = Asciz	scala/collection/mutable/LinkedListLike;
const #47 = class	#46;	//  scala/collection/mutable/LinkedListLike
const #48 = Asciz	next;
const #49 = Asciz	()Lscala/collection/mutable/Seq;;
const #50 = NameAndType	#48:#49;//  next:()Lscala/collection/mutable/Seq;
const #51 = InterfaceMethod	#47.#50;	//  scala/collection/mutable/LinkedListLike.next:()Lscala/collection/mutable/Seq;
const #52 = Asciz	elem;
const #53 = NameAndType	#52:#18;//  elem:()Ljava/lang/Object;
const #54 = InterfaceMethod	#47.#53;	//  scala/collection/mutable/LinkedListLike.elem:()Ljava/lang/Object;
const #55 = Asciz	scala/Function1;
const #56 = class	#55;	//  scala/Function1
const #57 = Asciz	apply;
const #58 = Asciz	(Ljava/lang/Object;)Ljava/lang/Object;;
const #59 = NameAndType	#57:#58;//  apply:(Ljava/lang/Object;)Ljava/lang/Object;
const #60 = InterfaceMethod	#56.#59;	//  scala/Function1.apply:(Ljava/lang/Object;)Ljava/lang/Object;
const #61 = Asciz	scala/runtime/BoxesRunTime;
const #62 = class	#61;	//  scala/runtime/BoxesRunTime
const #63 = Asciz	unboxToBoolean;
const #64 = Asciz	(Ljava/lang/Object;)Z;
const #65 = NameAndType	#63:#64;//  unboxToBoolean:(Ljava/lang/Object;)Z
const #66 = Method	#62.#65;	//  scala/runtime/BoxesRunTime.unboxToBoolean:(Ljava/lang/Object;)Z
const #67 = Asciz	next_$eq;
const #68 = Asciz	(Lscala/collection/mutable/Seq;)V;
const #69 = NameAndType	#67:#68;//  next_$eq:(Lscala/collection/mutable/Seq;)V
const #70 = InterfaceMethod	#47.#69;	//  scala/collection/mutable/LinkedListLike.next_$eq:(Lscala/collection/mutable/Seq;)V
const #71 = Asciz	scala/Some;
const #72 = class	#71;	//  scala/Some
const #73 = Asciz	(Ljava/lang/Object;Ljava/lang/Object;)V;
const #74 = NameAndType	#3:#73;//  "<init>":(Ljava/lang/Object;Ljava/lang/Object;)V
const #75 = Method	#27.#74;	//  scala/Tuple2."<init>":(Ljava/lang/Object;Ljava/lang/Object;)V
const #76 = Asciz	(Ljava/lang/Object;)V;
const #77 = NameAndType	#3:#76;//  "<init>":(Ljava/lang/Object;)V
const #78 = Method	#72.#77;	//  scala/Some."<init>":(Ljava/lang/Object;)V
const #79 = Asciz	scala/None$;
const #80 = class	#79;	//  scala/None$
const #81 = Asciz	MODULE$;
const #82 = Asciz	Lscala/None$;;
const #83 = NameAndType	#81:#82;//  MODULE$:Lscala/None$;
const #84 = Field	#80.#83;	//  scala/None$.MODULE$:Lscala/None$;
const #85 = Asciz	Lscala/Tuple2;;
const #86 = Asciz	xs;
const #87 = Asciz	Lscala/collection/mutable/LinkedList;;
const #88 = Asciz	xs1;
const #89 = Asciz	(Lscala/Tuple2<Lscala/collection/mutable/LinkedList<TA;>;Lscala/collection/mutable/LinkedList<TA;>;>;Lscala/Function1<TA;Ljava/lang/Boolean;>;)Lscala/Option<Lscala/Tuple2<TA;Lscala/Tuple2<Lscala/collection/mutable/LinkedList<TA;>;Lscala/collection/mutable/LinkedList<TA;>;>;>;>;;
const #90 = Asciz	Signature;
const #91 = Asciz	(Ljava/lang/Object;Lscala/collection/mutable/LinkedList;)V;
const #92 = NameAndType	#3:#91;//  "<init>":(Ljava/lang/Object;Lscala/collection/mutable/LinkedList;)V
const #93 = Method	#45.#92;	//  scala/collection/mutable/LinkedList."<init>":(Ljava/lang/Object;Lscala/collection/mutable/LinkedList;)V
const #94 = Asciz	_2;
const #95 = NameAndType	#94:#18;//  _2:()Ljava/lang/Object;
const #96 = Method	#27.#95;	//  scala/Tuple2._2:()Ljava/lang/Object;
const #97 = Asciz	(Lscala/collection/mutable/Seq;)Lscala/collection/mutable/Seq;;
const #98 = NameAndType	#24:#97;//  append:(Lscala/collection/mutable/Seq;)Lscala/collection/mutable/Seq;
const #99 = InterfaceMethod	#47.#98;	//  scala/collection/mutable/LinkedListLike.append:(Lscala/collection/mutable/Seq;)Lscala/collection/mutable/Seq;
const #100 = Asciz	atTail;
const #101 = Asciz	(Lscala/Tuple2<Lscala/collection/mutable/LinkedList<TA;>;Lscala/collection/mutable/LinkedList<TA;>;>;TA;)Lscala/Tuple2<Lscala/collection/mutable/LinkedList<TA;>;Lscala/collection/mutable/LinkedList<TA;>;>;;
const #102 = Asciz	()Lscala/Tuple2<Lscala/collection/mutable/LinkedList<TA;>;Lscala/collection/mutable/LinkedList<TA;>;>;;
const #103 = Asciz	Ljava/lang/Object;Lscala/concurrent/QueueModule<TA;>;;
const #104 = Asciz	Scala;
const #105 = Asciz	InnerClasses;
const #106 = Asciz	scala/concurrent/LinkedListQueueCreator;
const #107 = class	#106;	//  scala/concurrent/LinkedListQueueCreator
const #108 = Asciz	$anon$2;
const #109 = Asciz	scala/concurrent/QueueModule;
const #110 = class	#109;	//  scala/concurrent/QueueModule

{
public scala.concurrent.LinkedListQueueCreator$$anon$2(scala.concurrent.LinkedListQueueCreator);
  Code:
   Stack=1, Locals=2, Args_size=2
   0:	aload_0
   1:	invokespecial	#11; //Method java/lang/Object."<init>":()V
   4:	return
  LineNumberTable: 
   line 146: 0

  LocalVariableTable: 
   Start  Length  Slot  Name   Signature
   0      5      0    this       Lscala/concurrent/LinkedListQueueCreator$$anon$2;
   0      5      1    $outer       Lscala/concurrent/LinkedListQueueCreator;


public java.lang.Object make();
  Code:
   Stack=1, Locals=1, Args_size=1
   0:	aload_0
   1:	invokevirtual	#23; //Method make:()Lscala/Tuple2;
   4:	areturn
  LineNumberTable: 
   line 146: 0


public java.lang.Object append(java.lang.Object, java.lang.Object);
  Code:
   Stack=3, Locals=3, Args_size=3
   0:	aload_0
   1:	aload_1
   2:	checkcast	#27; //class scala/Tuple2
   5:	aload_2
   6:	invokevirtual	#30; //Method append:(Lscala/Tuple2;Ljava/lang/Object;)Lscala/Tuple2;
   9:	areturn
  LineNumberTable: 
   line 146: 0

  LocalVariableTable: 
   Start  Length  Slot  Name   Signature
   0      10      0    this       Lscala/concurrent/LinkedListQueueCreator$$anon$2;
   0      10      1    l       Ljava/lang/Object;
   0      10      2    x       Ljava/lang/Object;


public scala.Option extractFirst(java.lang.Object, scala.Function1);
  Code:
   Stack=3, Locals=3, Args_size=3
   0:	aload_0
   1:	aload_1
   2:	checkcast	#27; //class scala/Tuple2
   5:	aload_2
   6:	invokevirtual	#38; //Method extractFirst:(Lscala/Tuple2;Lscala/Function1;)Lscala/Option;
   9:	areturn
  LineNumberTable: 
   line 146: 0

  LocalVariableTable: 
   Start  Length  Slot  Name   Signature
   0      10      0    this       Lscala/concurrent/LinkedListQueueCreator$$anon$2;
   0      10      1    l       Ljava/lang/Object;
   0      10      2    p       Lscala/Function1;


public scala.Option extractFirst(scala.Tuple2, scala.Function1);
  Code:
   Stack=9, Locals=5, Args_size=3
   0:	aload_1
   1:	invokevirtual	#43; //Method scala/Tuple2._1:()Ljava/lang/Object;
   4:	checkcast	#45; //class scala/collection/mutable/LinkedList
   7:	astore_3
   8:	aload_3
   9:	invokeinterface	#51,  1; //InterfaceMethod scala/collection/mutable/LinkedListLike.next:()Lscala/collection/mutable/Seq;
   14:	checkcast	#45; //class scala/collection/mutable/LinkedList
   17:	astore	4
   19:	aload	4
   21:	ifnull	61
   24:	aload_2
   25:	aload	4
   27:	invokeinterface	#54,  1; //InterfaceMethod scala/collection/mutable/LinkedListLike.elem:()Ljava/lang/Object;
   32:	invokeinterface	#60,  2; //InterfaceMethod scala/Function1.apply:(Ljava/lang/Object;)Ljava/lang/Object;
   37:	invokestatic	#66; //Method scala/runtime/BoxesRunTime.unboxToBoolean:(Ljava/lang/Object;)Z
   40:	ifne	61
   43:	aload	4
   45:	astore_3
   46:	aload	4
   48:	invokeinterface	#51,  1; //InterfaceMethod scala/collection/mutable/LinkedListLike.next:()Lscala/collection/mutable/Seq;
   53:	checkcast	#45; //class scala/collection/mutable/LinkedList
   56:	astore	4
   58:	goto	19
   61:	aload	4
   63:	ifnull	149
   66:	aload_3
   67:	aload	4
   69:	invokeinterface	#51,  1; //InterfaceMethod scala/collection/mutable/LinkedListLike.next:()Lscala/collection/mutable/Seq;
   74:	invokeinterface	#70,  2; //InterfaceMethod scala/collection/mutable/LinkedListLike.next_$eq:(Lscala/collection/mutable/Seq;)V
   79:	aload_3
   80:	invokeinterface	#51,  1; //InterfaceMethod scala/collection/mutable/LinkedListLike.next:()Lscala/collection/mutable/Seq;
   85:	ifnonnull	124
   88:	new	#72; //class scala/Some
   91:	dup
   92:	new	#27; //class scala/Tuple2
   95:	dup
   96:	aload	4
   98:	invokeinterface	#54,  1; //InterfaceMethod scala/collection/mutable/LinkedListLike.elem:()Ljava/lang/Object;
   103:	new	#27; //class scala/Tuple2
   106:	dup
   107:	aload_1
   108:	invokevirtual	#43; //Method scala/Tuple2._1:()Ljava/lang/Object;
   111:	aload_3
   112:	invokespecial	#75; //Method scala/Tuple2."<init>":(Ljava/lang/Object;Ljava/lang/Object;)V
   115:	invokespecial	#75; //Method scala/Tuple2."<init>":(Ljava/lang/Object;Ljava/lang/Object;)V
   118:	invokespecial	#78; //Method scala/Some."<init>":(Ljava/lang/Object;)V
   121:	goto	152
   124:	new	#72; //class scala/Some
   127:	dup
   128:	new	#27; //class scala/Tuple2
   131:	dup
   132:	aload	4
   134:	invokeinterface	#54,  1; //InterfaceMethod scala/collection/mutable/LinkedListLike.elem:()Ljava/lang/Object;
   139:	aload_1
   140:	invokespecial	#75; //Method scala/Tuple2."<init>":(Ljava/lang/Object;Ljava/lang/Object;)V
   143:	invokespecial	#78; //Method scala/Some."<init>":(Ljava/lang/Object;)V
   146:	goto	152
   149:	getstatic	#84; //Field scala/None$.MODULE$:Lscala/None$;
   152:	areturn
  LineNumberTable: 
   line 158: 0
   line 159: 8
   line 160: 19
   line 161: 43
   line 162: 46
   line 164: 61
   line 165: 66
   line 166: 79
   line 167: 88
   line 169: 124
   line 166: 146
   line 172: 149
   line 157: 152

  LocalVariableTable: 
   Start  Length  Slot  Name   Signature
   0      153      0    this       Lscala/concurrent/LinkedListQueueCreator$$anon$2;
   0      153      1    l       Lscala/Tuple2;
   0      153      2    p       Lscala/Function1;
   8      145      3    xs       Lscala/collection/mutable/LinkedList;
   19      134      4    xs1       Lscala/collection/mutable/LinkedList;

  Signature: length = 0x2
   00 59 

public scala.Tuple2 append(scala.Tuple2, java.lang.Object);
  Code:
   Stack=4, Locals=4, Args_size=3
   0:	new	#45; //class scala/collection/mutable/LinkedList
   3:	dup
   4:	aload_2
   5:	aconst_null
   6:	invokespecial	#93; //Method scala/collection/mutable/LinkedList."<init>":(Ljava/lang/Object;Lscala/collection/mutable/LinkedList;)V
   9:	astore_3
   10:	aload_1
   11:	invokevirtual	#96; //Method scala/Tuple2._2:()Ljava/lang/Object;
   14:	checkcast	#47; //class scala/collection/mutable/LinkedListLike
   17:	aload_3
   18:	invokeinterface	#99,  2; //InterfaceMethod scala/collection/mutable/LinkedListLike.append:(Lscala/collection/mutable/Seq;)Lscala/collection/mutable/Seq;
   23:	pop
   24:	new	#27; //class scala/Tuple2
   27:	dup
   28:	aload_1
   29:	invokevirtual	#43; //Method scala/Tuple2._1:()Ljava/lang/Object;
   32:	aload_3
   33:	invokespecial	#75; //Method scala/Tuple2."<init>":(Ljava/lang/Object;Ljava/lang/Object;)V
   36:	areturn
  LineNumberTable: 
   line 153: 0
   line 154: 10
   line 155: 17
   line 154: 18
   line 155: 24

  LocalVariableTable: 
   Start  Length  Slot  Name   Signature
   0      37      0    this       Lscala/concurrent/LinkedListQueueCreator$$anon$2;
   0      37      1    l       Lscala/Tuple2;
   0      37      2    x       Ljava/lang/Object;
   10      26      3    atTail       Lscala/collection/mutable/LinkedList;

  Signature: length = 0x2
   00 65 

public scala.Tuple2 make();
  Code:
   Stack=4, Locals=2, Args_size=1
   0:	new	#45; //class scala/collection/mutable/LinkedList
   3:	dup
   4:	aconst_null
   5:	aconst_null
   6:	invokespecial	#93; //Method scala/collection/mutable/LinkedList."<init>":(Ljava/lang/Object;Lscala/collection/mutable/LinkedList;)V
   9:	astore_1
   10:	new	#27; //class scala/Tuple2
   13:	dup
   14:	aload_1
   15:	aload_1
   16:	invokespecial	#75; //Method scala/Tuple2."<init>":(Ljava/lang/Object;Ljava/lang/Object;)V
   19:	areturn
  LineNumberTable: 
   line 149: 0
   line 150: 10

  LocalVariableTable: 
   Start  Length  Slot  Name   Signature
   0      20      0    this       Lscala/concurrent/LinkedListQueueCreator$$anon$2;
   10      9      1    l       Lscala/collection/mutable/LinkedList;

  Signature: length = 0x2
   00 66 

}

