Compiled from "MailBox.scala"
public abstract class scala.concurrent.LinkedListQueueCreator$class extends java.lang.Object
  SourceFile: "MailBox.scala"
  Scala: length = 0x
   
  InnerClass: 
   public final #21= #13 of #20; //$anon$2=class scala/concurrent/LinkedListQueueCreator$$anon$2 of class scala/concurrent/LinkedListQueueCreator
  minor version: 0
  major version: 49
  Constant pool:
const #1 = Asciz	SourceFile;
const #2 = Asciz	MailBox.scala;
const #3 = Asciz	$init$;
const #4 = Asciz	(Lscala/concurrent/LinkedListQueueCreator;)V;
const #5 = Asciz	Code;
const #6 = Asciz	LineNumberTable;
const #7 = Asciz	$this;
const #8 = Asciz	Lscala/concurrent/LinkedListQueueCreator;;
const #9 = Asciz	LocalVariableTable;
const #10 = Asciz	queueCreate;
const #11 = Asciz	(Lscala/concurrent/LinkedListQueueCreator;)Lscala/concurrent/QueueModule;;
const #12 = Asciz	scala/concurrent/LinkedListQueueCreator$$anon$2;
const #13 = class	#12;	//  scala/concurrent/LinkedListQueueCreator$$anon$2
const #14 = Asciz	<init>;
const #15 = NameAndType	#14:#4;//  "<init>":(Lscala/concurrent/LinkedListQueueCreator;)V
const #16 = Method	#13.#15;	//  scala/concurrent/LinkedListQueueCreator$$anon$2."<init>":(Lscala/concurrent/LinkedListQueueCreator;)V
const #17 = Asciz	Scala;
const #18 = Asciz	InnerClasses;
const #19 = Asciz	scala/concurrent/LinkedListQueueCreator;
const #20 = class	#19;	//  scala/concurrent/LinkedListQueueCreator
const #21 = Asciz	$anon$2;
const #22 = Asciz	scala/concurrent/LinkedListQueueCreator$class;
const #23 = class	#22;	//  scala/concurrent/LinkedListQueueCreator$class
const #24 = Asciz	java/lang/Object;
const #25 = class	#24;	//  java/lang/Object

{
public static void $init$(scala.concurrent.LinkedListQueueCreator);
  Code:
   Stack=0, Locals=1, Args_size=1
   0:	return
  LineNumberTable: 
   line 144: 0

  LocalVariableTable: 
   Start  Length  Slot  Name   Signature
   0      1      0    $this       Lscala/concurrent/LinkedListQueueCreator;


public static scala.concurrent.QueueModule queueCreate(scala.concurrent.LinkedListQueueCreator);
  Code:
   Stack=3, Locals=1, Args_size=1
   0:	new	#13; //class scala/concurrent/LinkedListQueueCreator$$anon$2
   3:	dup
   4:	aload_0
   5:	invokespecial	#16; //Method scala/concurrent/LinkedListQueueCreator$$anon$2."<init>":(Lscala/concurrent/LinkedListQueueCreator;)V
   8:	areturn
  LineNumberTable: 
   line 146: 0

  LocalVariableTable: 
   Start  Length  Slot  Name   Signature
   0      9      0    $this       Lscala/concurrent/LinkedListQueueCreator;


}

