Compiled from "MailBox.scala"
public final class scala.concurrent.ListQueueCreator$$anon$1 extends java.lang.Object implements scala.concurrent.QueueModule
  SourceFile: "MailBox.scala"
  Signature: length = 0x2
   00 FFFFFF85 
  Scala: length = 0x
   
  InnerClass: 
   public final #138= #20 of #137; //$anon$1=class scala/concurrent/ListQueueCreator$$anon$1 of class scala/concurrent/ListQueueCreator
  minor version: 0
  major version: 49
  Constant pool:
const #1 = Asciz	SourceFile;
const #2 = Asciz	MailBox.scala;
const #3 = Asciz	<init>;
const #4 = Asciz	(Lscala/concurrent/ListQueueCreator;)V;
const #5 = Asciz	Code;
const #6 = Asciz	LineNumberTable;
const #7 = Asciz	java/lang/Object;
const #8 = class	#7;	//  java/lang/Object
const #9 = Asciz	()V;
const #10 = NameAndType	#3:#9;//  "<init>":()V
const #11 = Method	#8.#10;	//  java/lang/Object."<init>":()V
const #12 = Asciz	this;
const #13 = Asciz	Lscala/concurrent/ListQueueCreator$$anon$1;;
const #14 = Asciz	$outer;
const #15 = Asciz	Lscala/concurrent/ListQueueCreator;;
const #16 = Asciz	LocalVariableTable;
const #17 = Asciz	make;
const #18 = Asciz	()Ljava/lang/Object;;
const #19 = Asciz	scala/concurrent/ListQueueCreator$$anon$1;
const #20 = class	#19;	//  scala/concurrent/ListQueueCreator$$anon$1
const #21 = Asciz	()Lscala/collection/immutable/List;;
const #22 = NameAndType	#17:#21;//  make:()Lscala/collection/immutable/List;
const #23 = Method	#20.#22;	//  scala/concurrent/ListQueueCreator$$anon$1.make:()Lscala/collection/immutable/List;
const #24 = Asciz	append;
const #25 = Asciz	(Ljava/lang/Object;Ljava/lang/Object;)Ljava/lang/Object;;
const #26 = Asciz	scala/collection/immutable/List;
const #27 = class	#26;	//  scala/collection/immutable/List
const #28 = Asciz	(Lscala/collection/immutable/List;Ljava/lang/Object;)Lscala/collection/immutable/List;;
const #29 = NameAndType	#24:#28;//  append:(Lscala/collection/immutable/List;Ljava/lang/Object;)Lscala/collection/immutable/List;
const #30 = Method	#20.#29;	//  scala/concurrent/ListQueueCreator$$anon$1.append:(Lscala/collection/immutable/List;Ljava/lang/Object;)Lscala/collection/immutable/List;
const #31 = Asciz	l;
const #32 = Asciz	Ljava/lang/Object;;
const #33 = Asciz	x;
const #34 = Asciz	extractFirst;
const #35 = Asciz	(Ljava/lang/Object;Lscala/Function1;)Lscala/Option;;
const #36 = Asciz	(Lscala/collection/immutable/List;Lscala/Function1;)Lscala/Option;;
const #37 = NameAndType	#34:#36;//  extractFirst:(Lscala/collection/immutable/List;Lscala/Function1;)Lscala/Option;
const #38 = Method	#20.#37;	//  scala/concurrent/ListQueueCreator$$anon$1.extractFirst:(Lscala/collection/immutable/List;Lscala/Function1;)Lscala/Option;
const #39 = Asciz	p;
const #40 = Asciz	Lscala/Function1;;
const #41 = Asciz	scala/collection/immutable/Nil$;
const #42 = class	#41;	//  scala/collection/immutable/Nil$
const #43 = Asciz	MODULE$;
const #44 = Asciz	Lscala/collection/immutable/Nil$;;
const #45 = NameAndType	#43:#44;//  MODULE$:Lscala/collection/immutable/Nil$;
const #46 = Field	#42.#45;	//  scala/collection/immutable/Nil$.MODULE$:Lscala/collection/immutable/Nil$;
const #47 = Asciz	equals;
const #48 = Asciz	(Ljava/lang/Object;)Z;
const #49 = NameAndType	#47:#48;//  equals:(Ljava/lang/Object;)Z
const #50 = Method	#8.#49;	//  java/lang/Object.equals:(Ljava/lang/Object;)Z
const #51 = Asciz	scala/None$;
const #52 = class	#51;	//  scala/None$
const #53 = Asciz	Lscala/None$;;
const #54 = NameAndType	#43:#53;//  MODULE$:Lscala/None$;
const #55 = Field	#52.#54;	//  scala/None$.MODULE$:Lscala/None$;
const #56 = Asciz	scala/MatchError;
const #57 = class	#56;	//  scala/MatchError
const #58 = Asciz	scala/collection/SeqLike;
const #59 = class	#58;	//  scala/collection/SeqLike
const #60 = Asciz	toString;
const #61 = Asciz	()Ljava/lang/String;;
const #62 = NameAndType	#60:#61;//  toString:()Ljava/lang/String;
const #63 = InterfaceMethod	#59.#62;	//  scala/collection/SeqLike.toString:()Ljava/lang/String;
const #64 = Asciz	(Ljava/lang/String;)V;
const #65 = NameAndType	#3:#64;//  "<init>":(Ljava/lang/String;)V
const #66 = Method	#57.#65;	//  scala/MatchError."<init>":(Ljava/lang/String;)V
const #67 = Asciz	scala/collection/immutable/$colon$colon;
const #68 = class	#67;	//  scala/collection/immutable/$colon$colon
const #69 = Asciz	scala$collection$immutable$$colon$colon$$hd;
const #70 = NameAndType	#69:#32;//  scala$collection$immutable$$colon$colon$$hd:Ljava/lang/Object;
const #71 = Field	#68.#70;	//  scala/collection/immutable/$colon$colon.scala$collection$immutable$$colon$colon$$hd:Ljava/lang/Object;
const #72 = Asciz	tl;
const #73 = Asciz	Lscala/collection/immutable/List;;
const #74 = NameAndType	#72:#73;//  tl:Lscala/collection/immutable/List;
const #75 = Field	#68.#74;	//  scala/collection/immutable/$colon$colon.tl:Lscala/collection/immutable/List;
const #76 = Asciz	scala/Function1;
const #77 = class	#76;	//  scala/Function1
const #78 = Asciz	apply;
const #79 = Asciz	(Ljava/lang/Object;)Ljava/lang/Object;;
const #80 = NameAndType	#78:#79;//  apply:(Ljava/lang/Object;)Ljava/lang/Object;
const #81 = InterfaceMethod	#77.#80;	//  scala/Function1.apply:(Ljava/lang/Object;)Ljava/lang/Object;
const #82 = Asciz	scala/runtime/BoxesRunTime;
const #83 = class	#82;	//  scala/runtime/BoxesRunTime
const #84 = Asciz	unboxToBoolean;
const #85 = NameAndType	#84:#48;//  unboxToBoolean:(Ljava/lang/Object;)Z
const #86 = Method	#83.#85;	//  scala/runtime/BoxesRunTime.unboxToBoolean:(Ljava/lang/Object;)Z
const #87 = Asciz	scala/Some;
const #88 = class	#87;	//  scala/Some
const #89 = Asciz	scala/Tuple2;
const #90 = class	#89;	//  scala/Tuple2
const #91 = Asciz	(Ljava/lang/Object;Ljava/lang/Object;)V;
const #92 = NameAndType	#3:#91;//  "<init>":(Ljava/lang/Object;Ljava/lang/Object;)V
const #93 = Method	#90.#92;	//  scala/Tuple2."<init>":(Ljava/lang/Object;Ljava/lang/Object;)V
const #94 = Asciz	(Ljava/lang/Object;)V;
const #95 = NameAndType	#3:#94;//  "<init>":(Ljava/lang/Object;)V
const #96 = Method	#88.#95;	//  scala/Some."<init>":(Ljava/lang/Object;)V
const #97 = Asciz	scala/Option;
const #98 = class	#97;	//  scala/Option
const #99 = Method	#98.#62;	//  scala/Option.toString:()Ljava/lang/String;
const #100 = NameAndType	#33:#32;//  x:Ljava/lang/Object;
const #101 = Field	#88.#100;	//  scala/Some.x:Ljava/lang/Object;
const #102 = Asciz	_1;
const #103 = NameAndType	#102:#18;//  _1:()Ljava/lang/Object;
const #104 = Method	#90.#103;	//  scala/Tuple2._1:()Ljava/lang/Object;
const #105 = Asciz	_2;
const #106 = NameAndType	#105:#18;//  _2:()Ljava/lang/Object;
const #107 = Method	#90.#106;	//  scala/Tuple2._2:()Ljava/lang/Object;
const #108 = Asciz	$colon$colon;
const #109 = Asciz	(Ljava/lang/Object;)Lscala/collection/immutable/List;;
const #110 = NameAndType	#108:#109;//  $colon$colon:(Ljava/lang/Object;)Lscala/collection/immutable/List;
const #111 = Method	#27.#110;	//  scala/collection/immutable/List.$colon$colon:(Ljava/lang/Object;)Lscala/collection/immutable/List;
const #112 = Asciz	temp21;
const #113 = Asciz	Lscala/collection/immutable/$colon$colon;;
const #114 = Asciz	temp23;
const #115 = Asciz	temp15;
const #116 = Asciz	Lscala/Some;;
const #117 = Asciz	temp16;
const #118 = Asciz	Lscala/Tuple2;;
const #119 = Asciz	temp17;
const #120 = Asciz	temp18;
const #121 = Asciz	temp22;
const #122 = Asciz	temp13;
const #123 = Asciz	Lscala/Option;;
const #124 = Asciz	(Lscala/collection/immutable/List<TA;>;Lscala/Function1<TA;Ljava/lang/Boolean;>;)Lscala/Option<Lscala/Tuple2<TA;Lscala/collection/immutable/List<TA;>;>;>;;
const #125 = Asciz	Signature;
const #126 = Method	#42.#110;	//  scala/collection/immutable/Nil$.$colon$colon:(Ljava/lang/Object;)Lscala/collection/immutable/List;
const #127 = Asciz	$colon$colon$colon;
const #128 = Asciz	(Lscala/collection/immutable/List;)Lscala/collection/immutable/List;;
const #129 = NameAndType	#127:#128;//  $colon$colon$colon:(Lscala/collection/immutable/List;)Lscala/collection/immutable/List;
const #130 = Method	#27.#129;	//  scala/collection/immutable/List.$colon$colon$colon:(Lscala/collection/immutable/List;)Lscala/collection/immutable/List;
const #131 = Asciz	(Lscala/collection/immutable/List<TA;>;TA;)Lscala/collection/immutable/List<TA;>;;
const #132 = Asciz	()Lscala/collection/immutable/List<TA;>;;
const #133 = Asciz	Ljava/lang/Object;Lscala/concurrent/QueueModule<TA;>;;
const #134 = Asciz	Scala;
const #135 = Asciz	InnerClasses;
const #136 = Asciz	scala/concurrent/ListQueueCreator;
const #137 = class	#136;	//  scala/concurrent/ListQueueCreator
const #138 = Asciz	$anon$1;
const #139 = Asciz	scala/concurrent/QueueModule;
const #140 = class	#139;	//  scala/concurrent/QueueModule

{
public scala.concurrent.ListQueueCreator$$anon$1(scala.concurrent.ListQueueCreator);
  Code:
   Stack=1, Locals=2, Args_size=2
   0:	aload_0
   1:	invokespecial	#11; //Method java/lang/Object."<init>":()V
   4:	return
  LineNumberTable: 
   line 124: 0

  LocalVariableTable: 
   Start  Length  Slot  Name   Signature
   0      5      0    this       Lscala/concurrent/ListQueueCreator$$anon$1;
   0      5      1    $outer       Lscala/concurrent/ListQueueCreator;


public java.lang.Object make();
  Code:
   Stack=1, Locals=1, Args_size=1
   0:	aload_0
   1:	invokevirtual	#23; //Method make:()Lscala/collection/immutable/List;
   4:	areturn
  LineNumberTable: 
   line 124: 0


public java.lang.Object append(java.lang.Object, java.lang.Object);
  Code:
   Stack=3, Locals=3, Args_size=3
   0:	aload_0
   1:	aload_1
   2:	checkcast	#27; //class scala/collection/immutable/List
   5:	aload_2
   6:	invokevirtual	#30; //Method append:(Lscala/collection/immutable/List;Ljava/lang/Object;)Lscala/collection/immutable/List;
   9:	areturn
  LineNumberTable: 
   line 124: 0

  LocalVariableTable: 
   Start  Length  Slot  Name   Signature
   0      10      0    this       Lscala/concurrent/ListQueueCreator$$anon$1;
   0      10      1    l       Ljava/lang/Object;
   0      10      2    x       Ljava/lang/Object;


public scala.Option extractFirst(java.lang.Object, scala.Function1);
  Code:
   Stack=3, Locals=3, Args_size=3
   0:	aload_0
   1:	aload_1
   2:	checkcast	#27; //class scala/collection/immutable/List
   5:	aload_2
   6:	invokevirtual	#38; //Method extractFirst:(Lscala/collection/immutable/List;Lscala/Function1;)Lscala/Option;
   9:	areturn
  LineNumberTable: 
   line 124: 0

  LocalVariableTable: 
   Start  Length  Slot  Name   Signature
   0      10      0    this       Lscala/concurrent/ListQueueCreator$$anon$1;
   0      10      1    l       Ljava/lang/Object;
   0      10      2    p       Lscala/Function1;


public scala.Option extractFirst(scala.collection.immutable.List, scala.Function1);
  Code:
   Stack=7, Locals=11, Args_size=3
   0:	getstatic	#46; //Field scala/collection/immutable/Nil$.MODULE$:Lscala/collection/immutable/Nil$;
   3:	dup
   4:	ifnonnull	15
   7:	pop
   8:	aload_1
   9:	ifnull	22
   12:	goto	46
   15:	aload_1
   16:	invokevirtual	#50; //Method java/lang/Object.equals:(Ljava/lang/Object;)Z
   19:	ifeq	46
   22:	iconst_1
   23:	ifeq	32
   26:	getstatic	#55; //Field scala/None$.MODULE$:Lscala/None$;
   29:	goto	239
   32:	new	#57; //class scala/MatchError
   35:	dup
   36:	aload_1
   37:	invokeinterface	#63,  1; //InterfaceMethod scala/collection/SeqLike.toString:()Ljava/lang/String;
   42:	invokespecial	#66; //Method scala/MatchError."<init>":(Ljava/lang/String;)V
   45:	athrow
   46:	aload_1
   47:	instanceof	#68; //class scala/collection/immutable/$colon$colon
   50:	ifeq	293
   53:	aload_1
   54:	checkcast	#68; //class scala/collection/immutable/$colon$colon
   57:	astore_3
   58:	aload_3
   59:	getfield	#71; //Field scala/collection/immutable/$colon$colon.scala$collection$immutable$$colon$colon$$hd:Ljava/lang/Object;
   62:	astore	9
   64:	aload_3
   65:	getfield	#75; //Field scala/collection/immutable/$colon$colon.tl:Lscala/collection/immutable/List;
   68:	astore	4
   70:	iconst_1
   71:	ifeq	279
   74:	aload_2
   75:	aload	9
   77:	invokeinterface	#81,  2; //InterfaceMethod scala/Function1.apply:(Ljava/lang/Object;)Ljava/lang/Object;
   82:	invokestatic	#86; //Method scala/runtime/BoxesRunTime.unboxToBoolean:(Ljava/lang/Object;)Z
   85:	ifeq	109
   88:	new	#88; //class scala/Some
   91:	dup
   92:	new	#90; //class scala/Tuple2
   95:	dup
   96:	aload	9
   98:	aload	4
   100:	invokespecial	#93; //Method scala/Tuple2."<init>":(Ljava/lang/Object;Ljava/lang/Object;)V
   103:	invokespecial	#96; //Method scala/Some."<init>":(Ljava/lang/Object;)V
   106:	goto	239
   109:	aload_0
   110:	aload	4
   112:	aload_2
   113:	invokevirtual	#38; //Method extractFirst:(Lscala/collection/immutable/List;Lscala/Function1;)Lscala/Option;
   116:	astore	10
   118:	getstatic	#55; //Field scala/None$.MODULE$:Lscala/None$;
   121:	dup
   122:	ifnonnull	134
   125:	pop
   126:	aload	10
   128:	ifnull	142
   131:	goto	165
   134:	aload	10
   136:	invokevirtual	#50; //Method java/lang/Object.equals:(Ljava/lang/Object;)Z
   139:	ifeq	165
   142:	iconst_1
   143:	ifeq	152
   146:	getstatic	#55; //Field scala/None$.MODULE$:Lscala/None$;
   149:	goto	239
   152:	new	#57; //class scala/MatchError
   155:	dup
   156:	aload	10
   158:	invokevirtual	#99; //Method scala/Option.toString:()Ljava/lang/String;
   161:	invokespecial	#66; //Method scala/MatchError."<init>":(Ljava/lang/String;)V
   164:	athrow
   165:	aload	10
   167:	instanceof	#88; //class scala/Some
   170:	ifeq	266
   173:	aload	10
   175:	checkcast	#88; //class scala/Some
   178:	astore	5
   180:	aload	5
   182:	getfield	#101; //Field scala/Some.x:Ljava/lang/Object;
   185:	checkcast	#90; //class scala/Tuple2
   188:	astore	6
   190:	aload	6
   192:	ifnull	253
   195:	aload	6
   197:	invokevirtual	#104; //Method scala/Tuple2._1:()Ljava/lang/Object;
   200:	astore	7
   202:	aload	6
   204:	invokevirtual	#107; //Method scala/Tuple2._2:()Ljava/lang/Object;
   207:	checkcast	#27; //class scala/collection/immutable/List
   210:	astore	8
   212:	iconst_1
   213:	ifeq	240
   216:	new	#88; //class scala/Some
   219:	dup
   220:	new	#90; //class scala/Tuple2
   223:	dup
   224:	aload	7
   226:	aload	8
   228:	aload	9
   230:	invokevirtual	#111; //Method scala/collection/immutable/List.$colon$colon:(Ljava/lang/Object;)Lscala/collection/immutable/List;
   233:	invokespecial	#93; //Method scala/Tuple2."<init>":(Ljava/lang/Object;Ljava/lang/Object;)V
   236:	invokespecial	#96; //Method scala/Some."<init>":(Ljava/lang/Object;)V
   239:	areturn
   240:	new	#57; //class scala/MatchError
   243:	dup
   244:	aload	10
   246:	invokevirtual	#99; //Method scala/Option.toString:()Ljava/lang/String;
   249:	invokespecial	#66; //Method scala/MatchError."<init>":(Ljava/lang/String;)V
   252:	athrow
   253:	new	#57; //class scala/MatchError
   256:	dup
   257:	aload	10
   259:	invokevirtual	#99; //Method scala/Option.toString:()Ljava/lang/String;
   262:	invokespecial	#66; //Method scala/MatchError."<init>":(Ljava/lang/String;)V
   265:	athrow
   266:	new	#57; //class scala/MatchError
   269:	dup
   270:	aload	10
   272:	invokevirtual	#99; //Method scala/Option.toString:()Ljava/lang/String;
   275:	invokespecial	#66; //Method scala/MatchError."<init>":(Ljava/lang/String;)V
   278:	athrow
   279:	new	#57; //class scala/MatchError
   282:	dup
   283:	aload_1
   284:	invokeinterface	#63,  1; //InterfaceMethod scala/collection/SeqLike.toString:()Ljava/lang/String;
   289:	invokespecial	#66; //Method scala/MatchError."<init>":(Ljava/lang/String;)V
   292:	athrow
   293:	new	#57; //class scala/MatchError
   296:	dup
   297:	aload_1
   298:	invokeinterface	#63,  1; //InterfaceMethod scala/collection/SeqLike.toString:()Ljava/lang/String;
   303:	invokespecial	#66; //Method scala/MatchError."<init>":(Ljava/lang/String;)V
   306:	athrow
  LineNumberTable: 
   line 129: 0
   line 21: 22
   line 130: 26
   line 129: 32
   line 128: 53
   line 21: 70
   line 132: 74
   line 133: 88
   line 135: 109
   line 21: 142
   line 136: 146
   line 135: 152
   line 128: 173
   line 135: 190
   line 128: 195
   line 21: 212
   line 137: 216
   line 129: 239
   line 135: 240
   line 129: 279

  LocalVariableTable: 
   Start  Length  Slot  Name   Signature
   0      307      0    this       Lscala/concurrent/ListQueueCreator$$anon$1;
   0      307      1    l       Lscala/collection/immutable/List;
   0      307      2    p       Lscala/Function1;
   58      181      3    temp21       Lscala/collection/immutable/$colon$colon;
   240      53      3    temp21       Lscala/collection/immutable/$colon$colon;
   70      169      4    temp23       Lscala/collection/immutable/List;
   240      53      4    temp23       Lscala/collection/immutable/List;
   180      59      5    temp15       Lscala/Some;
   240      26      5    temp15       Lscala/Some;
   190      49      6    temp16       Lscala/Tuple2;
   240      26      6    temp16       Lscala/Tuple2;
   202      37      7    temp17       Ljava/lang/Object;
   240      13      7    temp17       Ljava/lang/Object;
   212      27      8    temp18       Lscala/collection/immutable/List;
   240      13      8    temp18       Lscala/collection/immutable/List;
   64      175      9    temp22       Ljava/lang/Object;
   240      53      9    temp22       Ljava/lang/Object;
   118      121      10    temp13       Lscala/Option;
   240      39      10    temp13       Lscala/Option;

  Signature: length = 0x2
   00 7C 

public scala.collection.immutable.List append(scala.collection.immutable.List, java.lang.Object);
  Code:
   Stack=2, Locals=3, Args_size=3
   0:	getstatic	#46; //Field scala/collection/immutable/Nil$.MODULE$:Lscala/collection/immutable/Nil$;
   3:	aload_2
   4:	invokevirtual	#126; //Method scala/collection/immutable/Nil$.$colon$colon:(Ljava/lang/Object;)Lscala/collection/immutable/List;
   7:	aload_1
   8:	invokevirtual	#130; //Method scala/collection/immutable/List.$colon$colon$colon:(Lscala/collection/immutable/List;)Lscala/collection/immutable/List;
   11:	areturn
  LineNumberTable: 
   line 127: 0

  LocalVariableTable: 
   Start  Length  Slot  Name   Signature
   0      12      0    this       Lscala/concurrent/ListQueueCreator$$anon$1;
   0      12      1    l       Lscala/collection/immutable/List;
   0      12      2    x       Ljava/lang/Object;

  Signature: length = 0x2
   00 FFFFFF83 

public scala.collection.immutable.List make();
  Code:
   Stack=1, Locals=1, Args_size=1
   0:	getstatic	#46; //Field scala/collection/immutable/Nil$.MODULE$:Lscala/collection/immutable/Nil$;
   3:	areturn
  LineNumberTable: 
   line 126: 0

  Signature: length = 0x2
   00 FFFFFF84 

}

