Compiled from "MailBox.scala"
public final class scala.concurrent.ListQueueCreator$$anon$1 extends java.lang.Object implements scala.concurrent.QueueModule
  SourceFile: "MailBox.scala"
  Signature: length = 0x2
   00 FFFFFF85 
  Scala: length = 0x
   
  InnerClass: 
   public final $anon$1=class scala/concurrent/ListQueueCreator$$anon$1 of class scala/concurrent/ListQueueCreator
  minor version: 0
  major version: 49
  Constant pool:
Asciz	SourceFile;
Asciz	MailBox.scala;
Asciz	<init>;
Asciz	(Lscala/concurrent/ListQueueCreator;)V;
Asciz	Code;
Asciz	LineNumberTable;
Asciz	java/lang/Object;
class	java/lang/Object
Asciz	()V;
NameAndType	"<init>":()V
Method	java/lang/Object."<init>":()V
Asciz	this;
Asciz	Lscala/concurrent/ListQueueCreator$$anon$1;;
Asciz	$outer;
Asciz	Lscala/concurrent/ListQueueCreator;;
Asciz	LocalVariableTable;
Asciz	make;
Asciz	()Ljava/lang/Object;;
Asciz	scala/concurrent/ListQueueCreator$$anon$1;
class	scala/concurrent/ListQueueCreator$$anon$1
Asciz	()Lscala/collection/immutable/List;;
NameAndType	make:()Lscala/collection/immutable/List;
Method	scala/concurrent/ListQueueCreator$$anon$1.make:()Lscala/collection/immutable/List;
Asciz	append;
Asciz	(Ljava/lang/Object;Ljava/lang/Object;)Ljava/lang/Object;;
Asciz	scala/collection/immutable/List;
class	scala/collection/immutable/List
Asciz	(Lscala/collection/immutable/List;Ljava/lang/Object;)Lscala/collection/immutable/List;;
NameAndType	append:(Lscala/collection/immutable/List;Ljava/lang/Object;)Lscala/collection/immutable/List;
Method	scala/concurrent/ListQueueCreator$$anon$1.append:(Lscala/collection/immutable/List;Ljava/lang/Object;)Lscala/collection/immutable/List;
Asciz	l;
Asciz	Ljava/lang/Object;;
Asciz	x;
Asciz	extractFirst;
Asciz	(Ljava/lang/Object;Lscala/Function1;)Lscala/Option;;
Asciz	(Lscala/collection/immutable/List;Lscala/Function1;)Lscala/Option;;
NameAndType	extractFirst:(Lscala/collection/immutable/List;Lscala/Function1;)Lscala/Option;
Method	scala/concurrent/ListQueueCreator$$anon$1.extractFirst:(Lscala/collection/immutable/List;Lscala/Function1;)Lscala/Option;
Asciz	p;
Asciz	Lscala/Function1;;
Asciz	scala/collection/immutable/Nil$;
class	scala/collection/immutable/Nil$
Asciz	MODULE$;
Asciz	Lscala/collection/immutable/Nil$;;
NameAndType	MODULE$:Lscala/collection/immutable/Nil$;
Field	scala/collection/immutable/Nil$.MODULE$:Lscala/collection/immutable/Nil$;
Asciz	equals;
Asciz	(Ljava/lang/Object;)Z;
NameAndType	equals:(Ljava/lang/Object;)Z
Method	java/lang/Object.equals:(Ljava/lang/Object;)Z
Asciz	scala/None$;
class	scala/None$
Asciz	Lscala/None$;;
NameAndType	MODULE$:Lscala/None$;
Field	scala/None$.MODULE$:Lscala/None$;
Asciz	scala/MatchError;
class	scala/MatchError
Asciz	scala/collection/SeqLike;
class	scala/collection/SeqLike
Asciz	toString;
Asciz	()Ljava/lang/String;;
NameAndType	toString:()Ljava/lang/String;
InterfaceMethod	scala/collection/SeqLike.toString:()Ljava/lang/String;
Asciz	(Ljava/lang/String;)V;
NameAndType	"<init>":(Ljava/lang/String;)V
Method	scala/MatchError."<init>":(Ljava/lang/String;)V
Asciz	scala/collection/immutable/$colon$colon;
class	scala/collection/immutable/$colon$colon
Asciz	scala$collection$immutable$$colon$colon$$hd;
NameAndType	scala$collection$immutable$$colon$colon$$hd:Ljava/lang/Object;
Field	scala/collection/immutable/$colon$colon.scala$collection$immutable$$colon$colon$$hd:Ljava/lang/Object;
Asciz	tl;
Asciz	Lscala/collection/immutable/List;;
NameAndType	tl:Lscala/collection/immutable/List;
Field	scala/collection/immutable/$colon$colon.tl:Lscala/collection/immutable/List;
Asciz	scala/Function1;
class	scala/Function1
Asciz	apply;
Asciz	(Ljava/lang/Object;)Ljava/lang/Object;;
NameAndType	apply:(Ljava/lang/Object;)Ljava/lang/Object;
InterfaceMethod	scala/Function1.apply:(Ljava/lang/Object;)Ljava/lang/Object;
Asciz	scala/runtime/BoxesRunTime;
class	scala/runtime/BoxesRunTime
Asciz	unboxToBoolean;
NameAndType	unboxToBoolean:(Ljava/lang/Object;)Z
Method	scala/runtime/BoxesRunTime.unboxToBoolean:(Ljava/lang/Object;)Z
Asciz	scala/Some;
class	scala/Some
Asciz	scala/Tuple2;
class	scala/Tuple2
Asciz	(Ljava/lang/Object;Ljava/lang/Object;)V;
NameAndType	"<init>":(Ljava/lang/Object;Ljava/lang/Object;)V
Method	scala/Tuple2."<init>":(Ljava/lang/Object;Ljava/lang/Object;)V
Asciz	(Ljava/lang/Object;)V;
NameAndType	"<init>":(Ljava/lang/Object;)V
Method	scala/Some."<init>":(Ljava/lang/Object;)V
Asciz	scala/Option;
class	scala/Option
Method	scala/Option.toString:()Ljava/lang/String;
NameAndType	x:Ljava/lang/Object;
Field	scala/Some.x:Ljava/lang/Object;
Asciz	_1;
NameAndType	_1:()Ljava/lang/Object;
Method	scala/Tuple2._1:()Ljava/lang/Object;
Asciz	_2;
NameAndType	_2:()Ljava/lang/Object;
Method	scala/Tuple2._2:()Ljava/lang/Object;
Asciz	$colon$colon;
Asciz	(Ljava/lang/Object;)Lscala/collection/immutable/List;;
NameAndType	$colon$colon:(Ljava/lang/Object;)Lscala/collection/immutable/List;
Method	scala/collection/immutable/List.$colon$colon:(Ljava/lang/Object;)Lscala/collection/immutable/List;
Asciz	temp21;
Asciz	Lscala/collection/immutable/$colon$colon;;
Asciz	temp23;
Asciz	temp15;
Asciz	Lscala/Some;;
Asciz	temp16;
Asciz	Lscala/Tuple2;;
Asciz	temp17;
Asciz	temp18;
Asciz	temp22;
Asciz	temp13;
Asciz	Lscala/Option;;
Asciz	(Lscala/collection/immutable/List<TA;>;Lscala/Function1<TA;Ljava/lang/Boolean;>;)Lscala/Option<Lscala/Tuple2<TA;Lscala/collection/immutable/List<TA;>;>;>;;
Asciz	Signature;
Method	scala/collection/immutable/Nil$.$colon$colon:(Ljava/lang/Object;)Lscala/collection/immutable/List;
Asciz	$colon$colon$colon;
Asciz	(Lscala/collection/immutable/List;)Lscala/collection/immutable/List;;
NameAndType	$colon$colon$colon:(Lscala/collection/immutable/List;)Lscala/collection/immutable/List;
Method	scala/collection/immutable/List.$colon$colon$colon:(Lscala/collection/immutable/List;)Lscala/collection/immutable/List;
Asciz	(Lscala/collection/immutable/List<TA;>;TA;)Lscala/collection/immutable/List<TA;>;;
Asciz	()Lscala/collection/immutable/List<TA;>;;
Asciz	Ljava/lang/Object;Lscala/concurrent/QueueModule<TA;>;;
Asciz	Scala;
Asciz	InnerClasses;
Asciz	scala/concurrent/ListQueueCreator;
class	scala/concurrent/ListQueueCreator
Asciz	$anon$1;
Asciz	scala/concurrent/QueueModule;
class	scala/concurrent/QueueModule

{
public scala.concurrent.ListQueueCreator$$anon$1(scala.concurrent.ListQueueCreator);
  Signature: (Lscala/concurrent/ListQueueCreator;)V
  Code:
   Stack=1, Locals=2, Args_size=2
	aload_0
	invokespecial	Method java/lang/Object."<init>":()V
	return
  Labels:
  LocalVariableTable: 
   Start  Length  Slot  Name   Signature
   0      5      0    this       Lscala/concurrent/ListQueueCreator$$anon$1;
   0      5      1    $outer       Lscala/concurrent/ListQueueCreator;


public java.lang.Object make();
  Signature: ()Ljava/lang/Object;
  Code:
   Stack=1, Locals=1, Args_size=1
	aload_0
	invokevirtual	Method make:()Lscala/collection/immutable/List;
	areturn
  Labels:

public java.lang.Object append(java.lang.Object, java.lang.Object);
  Signature: (Ljava/lang/Object;Ljava/lang/Object;)Ljava/lang/Object;
  Code:
   Stack=3, Locals=3, Args_size=3
	aload_0
	aload_1
	checkcast	class scala/collection/immutable/List
	aload_2
	invokevirtual	Method append:(Lscala/collection/immutable/List;Ljava/lang/Object;)Lscala/collection/immutable/List;
	areturn
  Labels:
  LocalVariableTable: 
   Start  Length  Slot  Name   Signature
   0      10      0    this       Lscala/concurrent/ListQueueCreator$$anon$1;
   0      10      1    l       Ljava/lang/Object;
   0      10      2    x       Ljava/lang/Object;


public scala.Option extractFirst(java.lang.Object, scala.Function1);
  Signature: (Ljava/lang/Object;Lscala/Function1;)Lscala/Option;
  Code:
   Stack=3, Locals=3, Args_size=3
	aload_0
	aload_1
	checkcast	class scala/collection/immutable/List
	aload_2
	invokevirtual	Method extractFirst:(Lscala/collection/immutable/List;Lscala/Function1;)Lscala/Option;
	areturn
  Labels:
  LocalVariableTable: 
   Start  Length  Slot  Name   Signature
   0      10      0    this       Lscala/concurrent/ListQueueCreator$$anon$1;
   0      10      1    l       Ljava/lang/Object;
   0      10      2    p       Lscala/Function1;


public scala.Option extractFirst(scala.collection.immutable.List, scala.Function1);
  Signature: (Lscala/collection/immutable/List;Lscala/Function1;)Lscala/Option;
  Code:
   Stack=7, Locals=11, Args_size=3
	getstatic	Field scala/collection/immutable/Nil$.MODULE$:Lscala/collection/immutable/Nil$;
	dup
	ifnonnull	l1 // aload_1
	pop
	aload_1
	ifnull	l2 // iconst_1
	goto	l3 // aload_1
l1	aload_1
	invokevirtual	Method java/lang/Object.equals:(Ljava/lang/Object;)Z
	ifeq	l3 // aload_1
l2	iconst_1
	ifeq	l4 // new
	getstatic	Field scala/None$.MODULE$:Lscala/None$;
	goto	l5 // areturn
l4	new	class scala/MatchError
	dup
	aload_1
	invokeinterface	InterfaceMethod scala/collection/SeqLike.toString:()Ljava/lang/String;
	invokespecial	Method scala/MatchError."<init>":(Ljava/lang/String;)V
	athrow
l3	aload_1
	instanceof	class scala/collection/immutable/$colon$colon
	ifeq	l6 // new
	aload_1
	checkcast	class scala/collection/immutable/$colon$colon
	astore_3
	aload_3
	getfield	Field scala/collection/immutable/$colon$colon.scala$collection$immutable$$colon$colon$$hd:Ljava/lang/Object;
	astore	9
	aload_3
	getfield	Field scala/collection/immutable/$colon$colon.tl:Lscala/collection/immutable/List;
	astore	4
	iconst_1
	ifeq	l7 // new
	aload_2
	aload	9
	invokeinterface	InterfaceMethod scala/Function1.apply:(Ljava/lang/Object;)Ljava/lang/Object;
	invokestatic	Method scala/runtime/BoxesRunTime.unboxToBoolean:(Ljava/lang/Object;)Z
	ifeq	l8 // aload_0
	new	class scala/Some
	dup
	new	class scala/Tuple2
	dup
	aload	9
	aload	4
	invokespecial	Method scala/Tuple2."<init>":(Ljava/lang/Object;Ljava/lang/Object;)V
	invokespecial	Method scala/Some."<init>":(Ljava/lang/Object;)V
	goto	l5 // areturn
l8	aload_0
	aload	4
	aload_2
	invokevirtual	Method extractFirst:(Lscala/collection/immutable/List;Lscala/Function1;)Lscala/Option;
	astore	10
	getstatic	Field scala/None$.MODULE$:Lscala/None$;
	dup
	ifnonnull	l9 // aload
	pop
	aload	10
	ifnull	l10 // iconst_1
	goto	l11 // aload
l9	aload	10
	invokevirtual	Method java/lang/Object.equals:(Ljava/lang/Object;)Z
	ifeq	l11 // aload
l10	iconst_1
	ifeq	l12 // new
	getstatic	Field scala/None$.MODULE$:Lscala/None$;
	goto	l5 // areturn
l12	new	class scala/MatchError
	dup
	aload	10
	invokevirtual	Method scala/Option.toString:()Ljava/lang/String;
	invokespecial	Method scala/MatchError."<init>":(Ljava/lang/String;)V
	athrow
l11	aload	10
	instanceof	class scala/Some
	ifeq	l13 // new
	aload	10
	checkcast	class scala/Some
	astore	5
	aload	5
	getfield	Field scala/Some.x:Ljava/lang/Object;
	checkcast	class scala/Tuple2
	astore	6
	aload	6
	ifnull	l14 // new
	aload	6
	invokevirtual	Method scala/Tuple2._1:()Ljava/lang/Object;
	astore	7
	aload	6
	invokevirtual	Method scala/Tuple2._2:()Ljava/lang/Object;
	checkcast	class scala/collection/immutable/List
	astore	8
	iconst_1
	ifeq	l15 // new
	new	class scala/Some
	dup
	new	class scala/Tuple2
	dup
	aload	7
	aload	8
	aload	9
	invokevirtual	Method scala/collection/immutable/List.$colon$colon:(Ljava/lang/Object;)Lscala/collection/immutable/List;
	invokespecial	Method scala/Tuple2."<init>":(Ljava/lang/Object;Ljava/lang/Object;)V
	invokespecial	Method scala/Some."<init>":(Ljava/lang/Object;)V
l5	areturn
l15	new	class scala/MatchError
	dup
	aload	10
	invokevirtual	Method scala/Option.toString:()Ljava/lang/String;
	invokespecial	Method scala/MatchError."<init>":(Ljava/lang/String;)V
	athrow
l14	new	class scala/MatchError
	dup
	aload	10
	invokevirtual	Method scala/Option.toString:()Ljava/lang/String;
	invokespecial	Method scala/MatchError."<init>":(Ljava/lang/String;)V
	athrow
l13	new	class scala/MatchError
	dup
	aload	10
	invokevirtual	Method scala/Option.toString:()Ljava/lang/String;
	invokespecial	Method scala/MatchError."<init>":(Ljava/lang/String;)V
	athrow
l7	new	class scala/MatchError
	dup
	aload_1
	invokeinterface	InterfaceMethod scala/collection/SeqLike.toString:()Ljava/lang/String;
	invokespecial	Method scala/MatchError."<init>":(Ljava/lang/String;)V
	athrow
l6	new	class scala/MatchError
	dup
	aload_1
	invokeinterface	InterfaceMethod scala/collection/SeqLike.toString:()Ljava/lang/String;
	invokespecial	Method scala/MatchError."<init>":(Ljava/lang/String;)V
	athrow
  Labels:
   	l1 = 15 // aload_1
   	l2 = 22 // iconst_1
   	l4 = 32 // new
   	l3 = 46 // aload_1
   	l8 = 109 // aload_0
   	l9 = 134 // aload
   	l10 = 142 // iconst_1
   	l12 = 152 // new
   	l11 = 165 // aload
   	l5 = 239 // areturn
   	l15 = 240 // new
   	l14 = 253 // new
   	l13 = 266 // new
   	l7 = 279 // new
   	l6 = 293 // new
  LocalVariableTable: 
   Start  Length  Slot  Name   Signature
   0      307      0    this       Lscala/concurrent/ListQueueCreator$$anon$1;
   0      307      1    l       Lscala/collection/immutable/List;
   0      307      2    p       Lscala/Function1;
   58      181      3    temp21       Lscala/collection/immutable/$colon$colon;
   240      53      3    temp21       Lscala/collection/immutable/$colon$colon;
   70      169      4    temp23       Lscala/collection/immutable/List;
   240      53      4    temp23       Lscala/collection/immutable/List;
   180      59      5    temp15       Lscala/Some;
   240      26      5    temp15       Lscala/Some;
   190      49      6    temp16       Lscala/Tuple2;
   240      26      6    temp16       Lscala/Tuple2;
   202      37      7    temp17       Ljava/lang/Object;
   240      13      7    temp17       Ljava/lang/Object;
   212      27      8    temp18       Lscala/collection/immutable/List;
   240      13      8    temp18       Lscala/collection/immutable/List;
   64      175      9    temp22       Ljava/lang/Object;
   240      53      9    temp22       Ljava/lang/Object;
   118      121      10    temp13       Lscala/Option;
   240      39      10    temp13       Lscala/Option;

  Signature: length = 0x2
   00 7C 

public scala.collection.immutable.List append(scala.collection.immutable.List, java.lang.Object);
  Signature: (Lscala/collection/immutable/List;Ljava/lang/Object;)Lscala/collection/immutable/List;
  Code:
   Stack=2, Locals=3, Args_size=3
	getstatic	Field scala/collection/immutable/Nil$.MODULE$:Lscala/collection/immutable/Nil$;
	aload_2
	invokevirtual	Method scala/collection/immutable/Nil$.$colon$colon:(Ljava/lang/Object;)Lscala/collection/immutable/List;
	aload_1
	invokevirtual	Method scala/collection/immutable/List.$colon$colon$colon:(Lscala/collection/immutable/List;)Lscala/collection/immutable/List;
	areturn
  Labels:
  LocalVariableTable: 
   Start  Length  Slot  Name   Signature
   0      12      0    this       Lscala/concurrent/ListQueueCreator$$anon$1;
   0      12      1    l       Lscala/collection/immutable/List;
   0      12      2    x       Ljava/lang/Object;

  Signature: length = 0x2
   00 FFFFFF83 

public scala.collection.immutable.List make();
  Signature: ()Lscala/collection/immutable/List;
  Code:
   Stack=1, Locals=1, Args_size=1
	getstatic	Field scala/collection/immutable/Nil$.MODULE$:Lscala/collection/immutable/Nil$;
	areturn
  Labels:
  Signature: length = 0x2
   00 FFFFFF84 

}

