Compiled from "Lock.scala"
public class scala.concurrent.Lock extends java.lang.Object implements scala.ScalaObject
  SourceFile: "Lock.scala"
  ScalaSig: length = 0x122
   05 00 2E 06 08 01 02 FFFFFF84 FFFFFF80 FFFFFF80 FFFFFF80 00 07 02 04 4C
   6F 63 6B 0A 02 03 04 01 0A 63 6F 6E 63 75 72 72
   65 6E 74 0A 01 05 01 05 73 63 61 6C 61 03 00 13
   03 00 08 10 10 02 09 0E 0D 01 0A 0A 02 0B 0C 01
   04 6C 61 6E 67 0A 01 0D 01 04 6A 61 76 61 09 02
   0F 0A 02 06 4F 62 6A 65 63 74 10 02 11 12 0D 01
   04 09 02 13 04 02 0B 53 63 61 6C 61 4F 62 6A 65
   63 74 08 05 15 00 FFFFFF84 00 16 01 06 3C 69 6E 69 74
   3E 14 01 17 10 02 18 00 0D 01 02 08 07 1A 00 FFFFFFC0
   FFFFFF80 FFFFFF84 00 1B 01 09 61 76 61 69 6C 61 62 6C 65 15
   01 1C 10 02 11 1D 09 02 1E 04 02 07 42 6F 6F 6C
   65 61 6E 08 07 20 00 FFFFFFC0 FFFFFF80 FFFFFF84 00 21 01 0D 61 76
   61 69 6C 61 62 6C 65 5F 24 65 71 14 02 22 25 10
   02 11 23 09 02 24 04 02 04 55 6E 69 74 08 07 26
   1F FFFFFF81 FFFFFF80 FFFFFFC0 00 1C 01 03 78 24 31 08 06 28 00 FFFFFFA0
   FFFFFFA0 04 1C 01 0A 61 76 61 69 6C 61 62 6C 65 20 08
   05 2A 00 FFFFFF84 00 2B 01 07 61 63 71 75 69 72 65 15
   01 22 08 05 2D 00 FFFFFF84 00 2B 01 07 72 65 6C 65 61
   73 65 
  minor version: 0
  major version: 49
  Constant pool:
Asciz	SourceFile;
Asciz	Lock.scala;
Asciz	available;
Asciz	Z;
Asciz	()Z;
Asciz	Code;
Asciz	LineNumberTable;
Asciz	scala/concurrent/Lock;
class	scala/concurrent/Lock
NameAndType	available:Z
Field	scala/concurrent/Lock.available:Z
Asciz	available_$eq;
Asciz	(Z)V;
Asciz	acquire;
Asciz	()V;
NameAndType	available:()Z
Method	scala/concurrent/Lock.available:()Z
NameAndType	available_$eq:(Z)V
Method	scala/concurrent/Lock.available_$eq:(Z)V
Asciz	scala/runtime/BoxedUnit;
class	scala/runtime/BoxedUnit
Asciz	UNIT;
Asciz	Lscala/runtime/BoxedUnit;;
NameAndType	UNIT:Lscala/runtime/BoxedUnit;
Field	scala/runtime/BoxedUnit.UNIT:Lscala/runtime/BoxedUnit;
Asciz	wait;
NameAndType	wait:()V
Method	scala/concurrent/Lock.wait:()V
Asciz	release;
Asciz	notify;
NameAndType	notify:()V
Method	scala/concurrent/Lock.notify:()V
Asciz	<init>;
Asciz	java/lang/Object;
class	java/lang/Object
NameAndType	"<init>":()V
Method	java/lang/Object."<init>":()V
Asciz	ScalaSig;
Asciz	scala/ScalaObject;
class	scala/ScalaObject

{
private boolean available;
  Signature: Z

public boolean available();
  Signature: ()Z
  Code:
   Stack=1, Locals=1, Args_size=1
	aload_0
	getfield	Field available:Z
	ireturn
  Labels:

public void available_$eq(boolean);
  Signature: (Z)V
  Code:
   Stack=2, Locals=2, Args_size=2
	aload_0
	iload_1
	putfield	Field available:Z
	return
  Labels:

public void acquire();
  Signature: ()V
  Code:
   Stack=2, Locals=2, Args_size=1
	aload_0
	dup
	astore_1
	monitorenter
l2	aload_0
	invokevirtual	Method available:()Z
	ifeq	l1 // aload_0
	aload_0
	iconst_0
	invokevirtual	Method available_$eq:(Z)V
	getstatic	Field scala/runtime/BoxedUnit.UNIT:Lscala/runtime/BoxedUnit;
	pop
	aload_1
	monitorexit
	return
l1	aload_0
	invokevirtual	Method wait:()V
	goto	l2 // aload_0
	aload_1
	monitorexit
	athrow
  Labels:
   	l2 = 4 // aload_0
   	l1 = 23 // aload_0
  Exception table:
   from   to  target type
     4    22    30   any
    23    30    30   any

public void release();
  Signature: ()V
  Code:
   Stack=2, Locals=2, Args_size=1
	aload_0
	dup
	astore_1
	monitorenter
	aload_0
	iconst_1
	invokevirtual	Method available_$eq:(Z)V
	aload_0
	invokevirtual	Method notify:()V
	getstatic	Field scala/runtime/BoxedUnit.UNIT:Lscala/runtime/BoxedUnit;
	pop
	aload_1
	monitorexit
	return
	aload_1
	monitorexit
	athrow
  Labels:
  Exception table:
   from   to  target type
     4    19    20   any

public scala.concurrent.Lock();
  Signature: ()V
  Code:
   Stack=2, Locals=1, Args_size=1
	aload_0
	invokespecial	Method java/lang/Object."<init>":()V
	aload_0
	iconst_1
	putfield	Field available:Z
	return
  Labels:

}

