Compiled from "MailBox.scala"
public final class scala.concurrent.MailBox$$anonfun$send$1 extends java.lang.Object implements scala.Function1,scala.ScalaObject,java.io.Serializable
  SourceFile: "MailBox.scala"
  Scala: length = 0x
   
  InnerClass: 
   public abstract #73= #37 of #72; //PreReceiver=class scala/concurrent/MailBox$PreReceiver of class scala/concurrent/MailBox
   public final #74= #9 of #72; //$anonfun$send$1=class scala/concurrent/MailBox$$anonfun$send$1 of class scala/concurrent/MailBox
  minor version: 0
  major version: 49
  Constant pool:
const #1 = Asciz	SourceFile;
const #2 = Asciz	MailBox.scala;
const #3 = Asciz	<clinit>;
const #4 = Asciz	()V;
const #5 = Asciz	Code;
const #6 = Asciz	serialVersionUID;
const #7 = Asciz	J;
const #8 = Asciz	scala/concurrent/MailBox$$anonfun$send$1;
const #9 = class	#8;	//  scala/concurrent/MailBox$$anonfun$send$1
const #10 = NameAndType	#6:#7;//  serialVersionUID:J
const #11 = Field	#9.#10;	//  scala/concurrent/MailBox$$anonfun$send$1.serialVersionUID:J
const #12 = Asciz	msg$1;
const #13 = Asciz	Ljava/lang/Object;;
const #14 = Asciz	<init>;
const #15 = Asciz	(Lscala/concurrent/MailBox;Ljava/lang/Object;)V;
const #16 = Asciz	LineNumberTable;
const #17 = NameAndType	#12:#13;//  msg$1:Ljava/lang/Object;
const #18 = Field	#9.#17;	//  scala/concurrent/MailBox$$anonfun$send$1.msg$1:Ljava/lang/Object;
const #19 = Asciz	java/lang/Object;
const #20 = class	#19;	//  java/lang/Object
const #21 = NameAndType	#14:#4;//  "<init>":()V
const #22 = Method	#20.#21;	//  java/lang/Object."<init>":()V
const #23 = Asciz	scala/Function1$class;
const #24 = class	#23;	//  scala/Function1$class
const #25 = Asciz	$init$;
const #26 = Asciz	(Lscala/Function1;)V;
const #27 = NameAndType	#25:#26;//  $init$:(Lscala/Function1;)V
const #28 = Method	#24.#27;	//  scala/Function1$class.$init$:(Lscala/Function1;)V
const #29 = Asciz	this;
const #30 = Asciz	Lscala/concurrent/MailBox$$anonfun$send$1;;
const #31 = Asciz	$outer;
const #32 = Asciz	Lscala/concurrent/MailBox;;
const #33 = Asciz	LocalVariableTable;
const #34 = Asciz	apply;
const #35 = Asciz	(Ljava/lang/Object;)Ljava/lang/Object;;
const #36 = Asciz	scala/concurrent/MailBox$PreReceiver;
const #37 = class	#36;	//  scala/concurrent/MailBox$PreReceiver
const #38 = Asciz	(Lscala/concurrent/MailBox$PreReceiver;)Z;
const #39 = NameAndType	#34:#38;//  apply:(Lscala/concurrent/MailBox$PreReceiver;)Z
const #40 = Method	#9.#39;	//  scala/concurrent/MailBox$$anonfun$send$1.apply:(Lscala/concurrent/MailBox$PreReceiver;)Z
const #41 = Asciz	scala/runtime/BoxesRunTime;
const #42 = class	#41;	//  scala/runtime/BoxesRunTime
const #43 = Asciz	boxToBoolean;
const #44 = Asciz	(Z)Ljava/lang/Boolean;;
const #45 = NameAndType	#43:#44;//  boxToBoolean:(Z)Ljava/lang/Boolean;
const #46 = Method	#42.#45;	//  scala/runtime/BoxesRunTime.boxToBoolean:(Z)Ljava/lang/Boolean;
const #47 = Asciz	v1;
const #48 = Asciz	isDefinedAt;
const #49 = Asciz	(Ljava/lang/Object;)Z;
const #50 = NameAndType	#48:#49;//  isDefinedAt:(Ljava/lang/Object;)Z
const #51 = Method	#37.#50;	//  scala/concurrent/MailBox$PreReceiver.isDefinedAt:(Ljava/lang/Object;)Z
const #52 = Asciz	r;
const #53 = Asciz	Lscala/concurrent/MailBox$PreReceiver;;
const #54 = Asciz	andThen;
const #55 = Asciz	(Lscala/Function1;)Lscala/Function1;;
const #56 = Asciz	(Lscala/Function1;Lscala/Function1;)Lscala/Function1;;
const #57 = NameAndType	#54:#56;//  andThen:(Lscala/Function1;Lscala/Function1;)Lscala/Function1;
const #58 = Method	#24.#57;	//  scala/Function1$class.andThen:(Lscala/Function1;Lscala/Function1;)Lscala/Function1;
const #59 = Asciz	g;
const #60 = Asciz	Lscala/Function1;;
const #61 = Asciz	compose;
const #62 = NameAndType	#61:#56;//  compose:(Lscala/Function1;Lscala/Function1;)Lscala/Function1;
const #63 = Method	#24.#62;	//  scala/Function1$class.compose:(Lscala/Function1;Lscala/Function1;)Lscala/Function1;
const #64 = Asciz	toString;
const #65 = Asciz	()Ljava/lang/String;;
const #66 = Asciz	(Lscala/Function1;)Ljava/lang/String;;
const #67 = NameAndType	#64:#66;//  toString:(Lscala/Function1;)Ljava/lang/String;
const #68 = Method	#24.#67;	//  scala/Function1$class.toString:(Lscala/Function1;)Ljava/lang/String;
const #69 = Asciz	Scala;
const #70 = Asciz	InnerClasses;
const #71 = Asciz	scala/concurrent/MailBox;
const #72 = class	#71;	//  scala/concurrent/MailBox
const #73 = Asciz	PreReceiver;
const #74 = Asciz	$anonfun$send$1;
const #75 = Asciz	scala/Function1;
const #76 = class	#75;	//  scala/Function1
const #77 = Asciz	scala/ScalaObject;
const #78 = class	#77;	//  scala/ScalaObject
const #79 = Asciz	java/io/Serializable;
const #80 = class	#79;	//  java/io/Serializable

{
public static final long serialVersionUID;

public static {};
  Code:
   Stack=2, Locals=0, Args_size=0
   0:	lconst_0
   1:	putstatic	#11; //Field serialVersionUID:J
   4:	return

public scala.concurrent.MailBox$$anonfun$send$1(scala.concurrent.MailBox, java.lang.Object);
  Code:
   Stack=2, Locals=3, Args_size=3
   0:	aload_0
   1:	aload_2
   2:	putfield	#18; //Field msg$1:Ljava/lang/Object;
   5:	aload_0
   6:	invokespecial	#22; //Method java/lang/Object."<init>":()V
   9:	aload_0
   10:	invokestatic	#28; //Method scala/Function1$class.$init$:(Lscala/Function1;)V
   13:	return
  LineNumberTable: 
   line 74: 0

  LocalVariableTable: 
   Start  Length  Slot  Name   Signature
   0      14      0    this       Lscala/concurrent/MailBox$$anonfun$send$1;
   0      14      1    $outer       Lscala/concurrent/MailBox;


public final java.lang.Object apply(java.lang.Object);
  Code:
   Stack=2, Locals=3, Args_size=2
   0:	aload_0
   1:	aload_1
   2:	checkcast	#37; //class scala/concurrent/MailBox$PreReceiver
   5:	invokevirtual	#40; //Method apply:(Lscala/concurrent/MailBox$PreReceiver;)Z
   8:	istore_2
   9:	iload_2
   10:	invokestatic	#46; //Method scala/runtime/BoxesRunTime.boxToBoolean:(Z)Ljava/lang/Boolean;
   13:	areturn
  LineNumberTable: 
   line 74: 0

  LocalVariableTable: 
   Start  Length  Slot  Name   Signature
   0      14      0    this       Lscala/concurrent/MailBox$$anonfun$send$1;
   0      14      1    v1       Ljava/lang/Object;


public final boolean apply(scala.concurrent.MailBox$PreReceiver);
  Code:
   Stack=2, Locals=2, Args_size=2
   0:	aload_1
   1:	aload_0
   2:	getfield	#18; //Field msg$1:Ljava/lang/Object;
   5:	invokevirtual	#51; //Method scala/concurrent/MailBox$PreReceiver.isDefinedAt:(Ljava/lang/Object;)Z
   8:	ireturn
  LineNumberTable: 
   line 74: 0

  LocalVariableTable: 
   Start  Length  Slot  Name   Signature
   0      9      0    this       Lscala/concurrent/MailBox$$anonfun$send$1;
   0      9      1    r       Lscala/concurrent/MailBox$PreReceiver;


public scala.Function1 andThen(scala.Function1);
  Code:
   Stack=2, Locals=2, Args_size=2
   0:	aload_0
   1:	aload_1
   2:	invokestatic	#58; //Method scala/Function1$class.andThen:(Lscala/Function1;Lscala/Function1;)Lscala/Function1;
   5:	areturn
  LineNumberTable: 
   line 74: 0

  LocalVariableTable: 
   Start  Length  Slot  Name   Signature
   0      6      0    this       Lscala/concurrent/MailBox$$anonfun$send$1;
   0      6      1    g       Lscala/Function1;


public scala.Function1 compose(scala.Function1);
  Code:
   Stack=2, Locals=2, Args_size=2
   0:	aload_0
   1:	aload_1
   2:	invokestatic	#63; //Method scala/Function1$class.compose:(Lscala/Function1;Lscala/Function1;)Lscala/Function1;
   5:	areturn
  LineNumberTable: 
   line 74: 0

  LocalVariableTable: 
   Start  Length  Slot  Name   Signature
   0      6      0    this       Lscala/concurrent/MailBox$$anonfun$send$1;
   0      6      1    g       Lscala/Function1;


public java.lang.String toString();
  Code:
   Stack=1, Locals=1, Args_size=1
   0:	aload_0
   1:	invokestatic	#68; //Method scala/Function1$class.toString:(Lscala/Function1;)Ljava/lang/String;
   4:	areturn
  LineNumberTable: 
   line 74: 0


}

