Compiled from "MailBox.scala"
public abstract class scala.concurrent.MailBox$PreReceiver extends java.lang.Object implements scala.ScalaObject
  SourceFile: "MailBox.scala"
  Scala: length = 0x
   
  InnerClass: 
   public abstract PreReceiver=class scala/concurrent/MailBox$PreReceiver of class scala/concurrent/MailBox
  minor version: 0
  major version: 49
  Constant pool:
Asciz	SourceFile;
Asciz	MailBox.scala;
Asciz	msg;
Asciz	Ljava/lang/Object;;
Asciz	$outer;
Asciz	Lscala/concurrent/MailBox;;
Asciz	()Ljava/lang/Object;;
Asciz	Code;
Asciz	LineNumberTable;
Asciz	scala/concurrent/MailBox$PreReceiver;
class	scala/concurrent/MailBox$PreReceiver
NameAndType	msg:Ljava/lang/Object;
Field	scala/concurrent/MailBox$PreReceiver.msg:Ljava/lang/Object;
Asciz	msg_$eq;
Asciz	(Ljava/lang/Object;)V;
Asciz	isDefinedAt;
Asciz	(Ljava/lang/Object;)Z;
Asciz	scala$concurrent$MailBox$PreReceiver$$$outer;
Asciz	()Lscala/concurrent/MailBox;;
NameAndType	$outer:Lscala/concurrent/MailBox;
Field	scala/concurrent/MailBox$PreReceiver.$outer:Lscala/concurrent/MailBox;
Asciz	<init>;
Asciz	(Lscala/concurrent/MailBox;)V;
Asciz	java/lang/NullPointerException;
class	java/lang/NullPointerException
Asciz	()V;
NameAndType	"<init>":()V
Method	java/lang/NullPointerException."<init>":()V
Asciz	java/lang/Object;
class	java/lang/Object
Method	java/lang/Object."<init>":()V
Asciz	this;
Asciz	Lscala/concurrent/MailBox$PreReceiver;;
Asciz	LocalVariableTable;
Asciz	Scala;
Asciz	InnerClasses;
Asciz	scala/concurrent/MailBox;
class	scala/concurrent/MailBox
Asciz	PreReceiver;
Asciz	scala/ScalaObject;
class	scala/ScalaObject

{
private java.lang.Object msg;
  Signature: Ljava/lang/Object;

public final scala.concurrent.MailBox $outer;
  Signature: Lscala/concurrent/MailBox;

public java.lang.Object msg();
  Signature: ()Ljava/lang/Object;
  Code:
   Stack=1, Locals=1, Args_size=1
	aload_0
	getfield	Field msg:Ljava/lang/Object;
	areturn
  Labels:

public void msg_$eq(java.lang.Object);
  Signature: (Ljava/lang/Object;)V
  Code:
   Stack=2, Locals=2, Args_size=2
	aload_0
	aload_1
	putfield	Field msg:Ljava/lang/Object;
	return
  Labels:

public abstract boolean isDefinedAt(java.lang.Object);
  Signature: (Ljava/lang/Object;)Z

public scala.concurrent.MailBox scala$concurrent$MailBox$PreReceiver$$$outer();
  Signature: ()Lscala/concurrent/MailBox;
  Code:
   Stack=1, Locals=1, Args_size=1
	aload_0
	getfield	Field $outer:Lscala/concurrent/MailBox;
	areturn
  Labels:

public scala.concurrent.MailBox$PreReceiver(scala.concurrent.MailBox);
  Signature: (Lscala/concurrent/MailBox;)V
  Code:
   Stack=2, Locals=2, Args_size=2
	aload_1
	ifnonnull	l1 // aload_0
	new	class java/lang/NullPointerException
	dup
	invokespecial	Method java/lang/NullPointerException."<init>":()V
	athrow
l1	aload_0
	aload_1
	putfield	Field $outer:Lscala/concurrent/MailBox;
	aload_0
	invokespecial	Method java/lang/Object."<init>":()V
	aload_0
	aconst_null
	putfield	Field msg:Ljava/lang/Object;
	return
  Labels:
   	l1 = 12 // aload_0
  LocalVariableTable: 
   Start  Length  Slot  Name   Signature
   0      27      0    this       Lscala/concurrent/MailBox$PreReceiver;
   0      27      1    $outer       Lscala/concurrent/MailBox;


}

