Compiled from "MailBox.scala"
public abstract class scala.concurrent.MailBox$PreReceiver extends java.lang.Object implements scala.ScalaObject
  SourceFile: "MailBox.scala"
  Scala: length = 0x
   
  InnerClass: 
   public abstract #39= #17 of #38; //PreReceiver=class scala/concurrent/MailBox$PreReceiver of class scala/concurrent/MailBox
  minor version: 0
  major version: 49
  Constant pool:
const #1 = Asciz	SourceFile;
const #2 = Asciz	MailBox.scala;
const #3 = Asciz	$outer;
const #4 = Asciz	Lscala/concurrent/MailBox;;
const #5 = Asciz	msg;
const #6 = Asciz	Ljava/lang/Object;;
const #7 = Asciz	<init>;
const #8 = Asciz	(Lscala/concurrent/MailBox;)V;
const #9 = Asciz	Code;
const #10 = Asciz	LineNumberTable;
const #11 = Asciz	java/lang/NullPointerException;
const #12 = class	#11;	//  java/lang/NullPointerException
const #13 = Asciz	()V;
const #14 = NameAndType	#7:#13;//  "<init>":()V
const #15 = Method	#12.#14;	//  java/lang/NullPointerException."<init>":()V
const #16 = Asciz	scala/concurrent/MailBox$PreReceiver;
const #17 = class	#16;	//  scala/concurrent/MailBox$PreReceiver
const #18 = NameAndType	#3:#4;//  $outer:Lscala/concurrent/MailBox;
const #19 = Field	#17.#18;	//  scala/concurrent/MailBox$PreReceiver.$outer:Lscala/concurrent/MailBox;
const #20 = Asciz	java/lang/Object;
const #21 = class	#20;	//  java/lang/Object
const #22 = Method	#21.#14;	//  java/lang/Object."<init>":()V
const #23 = NameAndType	#5:#6;//  msg:Ljava/lang/Object;
const #24 = Field	#17.#23;	//  scala/concurrent/MailBox$PreReceiver.msg:Ljava/lang/Object;
const #25 = Asciz	this;
const #26 = Asciz	Lscala/concurrent/MailBox$PreReceiver;;
const #27 = Asciz	LocalVariableTable;
const #28 = Asciz	scala$concurrent$MailBox$PreReceiver$$$outer;
const #29 = Asciz	()Lscala/concurrent/MailBox;;
const #30 = Asciz	isDefinedAt;
const #31 = Asciz	(Ljava/lang/Object;)Z;
const #32 = Asciz	msg_$eq;
const #33 = Asciz	(Ljava/lang/Object;)V;
const #34 = Asciz	()Ljava/lang/Object;;
const #35 = Asciz	Scala;
const #36 = Asciz	InnerClasses;
const #37 = Asciz	scala/concurrent/MailBox;
const #38 = class	#37;	//  scala/concurrent/MailBox
const #39 = Asciz	PreReceiver;
const #40 = Asciz	scala/ScalaObject;
const #41 = class	#40;	//  scala/ScalaObject

{
public final scala.concurrent.MailBox $outer;

public scala.concurrent.MailBox$PreReceiver(scala.concurrent.MailBox);
  Code:
   Stack=2, Locals=2, Args_size=2
   0:	aload_1
   1:	ifnonnull	12
   4:	new	#12; //class java/lang/NullPointerException
   7:	dup
   8:	invokespecial	#15; //Method java/lang/NullPointerException."<init>":()V
   11:	athrow
   12:	aload_0
   13:	aload_1
   14:	putfield	#19; //Field $outer:Lscala/concurrent/MailBox;
   17:	aload_0
   18:	invokespecial	#22; //Method java/lang/Object."<init>":()V
   21:	aload_0
   22:	aconst_null
   23:	pop
   24:	aconst_null
   25:	putfield	#24; //Field msg:Ljava/lang/Object;
   28:	return
  LineNumberTable: 
   line 24: 0
   line 25: 21

  LocalVariableTable: 
   Start  Length  Slot  Name   Signature
   0      29      0    this       Lscala/concurrent/MailBox$PreReceiver;
   0      29      1    $outer       Lscala/concurrent/MailBox;


public scala.concurrent.MailBox scala$concurrent$MailBox$PreReceiver$$$outer();
  Code:
   Stack=1, Locals=1, Args_size=1
   0:	aload_0
   1:	getfield	#19; //Field $outer:Lscala/concurrent/MailBox;
   4:	areturn
  LineNumberTable: 
   line 24: 0


public abstract boolean isDefinedAt(java.lang.Object);

public void msg_$eq(java.lang.Object);
  Code:
   Stack=2, Locals=2, Args_size=2
   0:	aload_0
   1:	aload_1
   2:	putfield	#24; //Field msg:Ljava/lang/Object;
   5:	return
  LineNumberTable: 
   line 25: 0


public java.lang.Object msg();
  Code:
   Stack=1, Locals=1, Args_size=1
   0:	aload_0
   1:	getfield	#24; //Field msg:Ljava/lang/Object;
   4:	areturn
  LineNumberTable: 
   line 25: 0


}

