Compiled from "MailBox.scala"
public class scala.concurrent.MailBox extends java.lang.Object implements scala.concurrent.ListQueueCreator,scala.ScalaObject
  SourceFile: "MailBox.scala"
  ScalaSig: length = 0x476
   05 00 FFFFFF81 26 06 08 01 02 FFFFFF84 FFFFFF80 FFFFFF80 FFFFFF80 00 07 02 07
   4D 61 69 6C 42 6F 78 0A 02 03 04 01 0A 63 6F 6E
   63 75 72 72 65 6E 74 0A 01 05 01 05 73 63 61 6C
   61 03 00 13 04 00 08 10 14 10 02 09 0E 0D 01 0A
   0A 02 0B 0C 01 04 6C 61 6E 67 0A 01 0D 01 04 6A
   61 76 61 09 02 0F 0A 02 06 4F 62 6A 65 63 74 10
   02 11 12 0D 01 02 09 02 13 02 02 10 4C 69 73 74
   51 75 65 75 65 43 72 65 61 74 6F 72 10 02 15 16
   0D 01 04 09 02 17 04 02 0B 53 63 61 6C 61 4F 62
   6A 65 63 74 08 05 19 00 FFFFFF84 00 1A 01 06 3C 69 6E
   69 74 3E 14 01 1B 10 02 11 00 05 08 1D 00 FFFFFF84 FFFFFF80
   FFFFFF80 FFFFFF80 00 1E 02 07 4D 65 73 73 61 67 65 10 02 15
   1F 09 02 20 04 02 06 41 6E 79 52 65 66 06 08 22
   00 FFFFFF84 FFFFFF80 FFFFFF80 FFFFFF81 04 23 02 0B 50 72 65 52 65 63 65
   69 76 65 72 13 03 21 08 14 08 05 19 21 FFFFFF84 00 25
   14 01 26 10 02 27 21 0D 01 00 08 07 29 21 FFFFFFC0 FFFFFF80
   FFFFFF84 00 2A 01 03 6D 73 67 15 01 2B 10 02 27 1C 08
   07 2D 21 FFFFFFC0 FFFFFF80 FFFFFF84 00 2E 01 07 6D 73 67 5F 24 65
   71 14 02 2F 32 10 02 15 30 09 02 31 04 02 04 55
   6E 69 74 08 07 33 2C FFFFFF81 FFFFFF80 FFFFFFC0 00 2B 01 03 78 24
   31 08 06 35 21 FFFFFFA0 FFFFFFA0 04 2B 01 04 6D 73 67 20 08
   05 37 21 FFFFFF86 00 38 01 0B 69 73 44 65 66 69 6E 65
   64 41 74 14 02 39 3C 10 02 15 3A 09 02 3B 04 02
   07 42 6F 6F 6C 65 61 6E 08 05 29 36 FFFFFFC0 00 2B 06
   04 3E 00 04 3F 02 08 52 65 63 65 69 76 65 72 15
   02 40 48 13 03 3D 26 14 08 08 42 3D FFFFFF82 FFFFFF80 FFFFFFA0 FFFFFF80
   04 43 01 08 72 65 63 65 69 76 65 72 10 04 15 44
   2B 46 09 02 45 04 02 0F 50 61 72 74 69 61 6C 46
   75 6E 63 74 69 6F 6E 10 02 47 48 0C 00 04 08 49
   3D FFFFFF84 FFFFFF80 FFFFFF80 FFFFFFC2 00 4A 02 01 41 11 02 4B 4E 10 02
   15 4C 09 02 4D 04 02 07 4E 6F 74 68 69 6E 67 10
   02 15 4F 09 02 50 04 02 03 41 6E 79 08 05 19 3D
   FFFFFF84 00 52 14 02 53 54 10 03 27 3D 46 08 05 42 51
   FFFFFFC0 00 43 08 05 37 3D FFFFFF84 00 56 14 02 39 57 08 05
   29 55 FFFFFFC0 00 2B 08 05 59 3D FFFFFF84 00 5A 01 07 72 65
   63 65 69 76 65 14 01 46 08 05 5C 3D FFFFFF84 00 5D 01
   0D 72 65 63 65 69 76 65 57 69 74 68 69 6E 14 02
   46 5E 08 05 5F 5B FFFFFFC0 00 60 01 04 6D 73 65 63 10
   02 15 61 09 02 62 04 02 04 4C 6F 6E 67 08 07 64
   00 FFFFFFC2 FFFFFF80 FFFFFF84 04 65 01 0C 6D 65 73 73 61 67 65 51
   75 65 75 65 15 01 66 10 03 11 67 2B 09 02 68 02
   02 0B 51 75 65 75 65 4D 6F 64 75 6C 65 08 06 6A
   00 FFFFFFA0 FFFFFF80 04 66 01 0D 6D 65 73 73 61 67 65 51 75
   65 75 65 20 08 07 6C 00 FFFFFFC2 FFFFFF80 FFFFFF84 04 6D 01 0D 72
   65 63 65 69 76 65 72 51 75 65 75 65 15 01 6E 10
   03 11 67 26 08 06 70 00 FFFFFFA0 FFFFFF80 04 6E 01 0E 72 65
   63 65 69 76 65 72 51 75 65 75 65 20 08 07 72 00
   FFFFFFC0 FFFFFF80 FFFFFF84 04 73 01 04 73 65 6E 74 15 01 74 10 02
   75 76 0E 02 27 63 09 02 77 67 02 01 54 08 07 79
   00 FFFFFFC0 FFFFFF80 FFFFFF84 04 7A 01 08 73 65 6E 74 5F 24 65 71
   14 02 2F 7B 08 07 33 78 FFFFFF81 FFFFFF80 FFFFFFC0 00 74 08 06 7D
   00 FFFFFFA0 FFFFFFA0 04 74 01 05 73 65 6E 74 20 08 08 7F 00
   FFFFFFC0 FFFFFF80 FFFFFF84 04 FFFFFF81 00 01 09 72 65 63 65 69 76 65 72
   73 15 02 FFFFFF81 01 10 03 FFFFFF81 02 76 0E 02 27 6B 08 09
   FFFFFF81 04 00 FFFFFFC0 FFFFFF80 FFFFFF84 04 FFFFFF81 05 01 0D 72 65 63 65 69
   76 65 72 73 5F 24 65 71 14 03 2F FFFFFF81 06 08 09 33
   FFFFFF81 03 FFFFFF81 FFFFFF80 FFFFFFC0 00 FFFFFF81 01 08 08 FFFFFF81 08 00 FFFFFFA0 FFFFFFA0 04
   FFFFFF81 01 01 0A 72 65 63 65 69 76 65 72 73 20 08 07
   FFFFFF81 0A 00 FFFFFF84 04 FFFFFF81 0B 01 0C 73 63 61 6E 53 65 6E
   74 4D 73 67 73 15 04 FFFFFF81 0C FFFFFF81 10 14 03 2F FFFFFF81 0D
   08 07 42 FFFFFF81 09 FFFFFFC0 00 FFFFFF81 0E 10 04 27 3D FFFFFF81 0F 10
   03 47 FFFFFF81 10 04 09 49 FFFFFF81 09 FFFFFF84 FFFFFF80 FFFFFF80 FFFFFFC2 00 4A 08
   07 FFFFFF81 12 00 FFFFFF84 00 FFFFFF81 13 01 04 73 65 6E 64 14 03
   2F FFFFFF81 14 08 06 29 FFFFFF81 11 FFFFFFC0 00 2B 08 06 59 00 FFFFFF84
   00 FFFFFF81 16 15 04 FFFFFF81 17 FFFFFF81 19 14 04 FFFFFF81 18 FFFFFF81 1A 10
   03 47 FFFFFF81 19 04 09 49 FFFFFF81 15 FFFFFF84 FFFFFF80 FFFFFF80 FFFFFFC2 00 4A 08
   08 FFFFFF81 1B FFFFFF81 15 FFFFFFC0 00 FFFFFF81 1C 01 01 66 10 05 15 44
   2B FFFFFF81 18 08 06 5C 00 FFFFFF84 00 FFFFFF81 1E 15 04 FFFFFF81 1F FFFFFF81
   22 14 04 FFFFFF81 20 FFFFFF81 25 14 04 FFFFFF81 21 FFFFFF81 23 10 03 47
   FFFFFF81 22 04 09 49 FFFFFF81 1D FFFFFF84 FFFFFF80 FFFFFF80 FFFFFFC2 00 4A 08 08 FFFFFF81
   1B FFFFFF81 1D FFFFFFC0 00 FFFFFF81 24 10 05 15 44 2B FFFFFF81 21 08 06
   5F FFFFFF81 1D FFFFFFC0 00 60 
  InnerClass: 
   public #187= #55 of #33; //Receiver=class scala/concurrent/MailBox$Receiver of class scala/concurrent/MailBox
   public abstract #188= #130 of #33; //PreReceiver=class scala/concurrent/MailBox$PreReceiver of class scala/concurrent/MailBox
   public final #189= #86 of #33; //$anonfun$send$1=class scala/concurrent/MailBox$$anonfun$send$1 of class scala/concurrent/MailBox
   public final #190= #167 of #33; //$anonfun$scanSentMsgs$1=class scala/concurrent/MailBox$$anonfun$scanSentMsgs$1 of class scala/concurrent/MailBox
  minor version: 0
  major version: 49
  Constant pool:
const #1 = Asciz	SourceFile;
const #2 = Asciz	MailBox.scala;
const #3 = Asciz	receivers;
const #4 = Asciz	Ljava/lang/Object;;
const #5 = Asciz	Signature;
const #6 = Asciz	sent;
const #7 = Asciz	receiverQueue;
const #8 = Asciz	Lscala/concurrent/QueueModule;;
const #9 = Asciz	Lscala/concurrent/QueueModule<Lscala/concurrent/MailBox$PreReceiver;>;;
const #10 = Asciz	messageQueue;
const #11 = Asciz	Lscala/concurrent/QueueModule<Ljava/lang/Object;>;;
const #12 = Asciz	<init>;
const #13 = Asciz	()V;
const #14 = Asciz	Code;
const #15 = Asciz	LineNumberTable;
const #16 = Asciz	java/lang/Object;
const #17 = class	#16;	//  java/lang/Object
const #18 = NameAndType	#12:#13;//  "<init>":()V
const #19 = Method	#17.#18;	//  java/lang/Object."<init>":()V
const #20 = Asciz	scala/concurrent/ListQueueCreator$class;
const #21 = class	#20;	//  scala/concurrent/ListQueueCreator$class
const #22 = Asciz	$init$;
const #23 = Asciz	(Lscala/concurrent/ListQueueCreator;)V;
const #24 = NameAndType	#22:#23;//  $init$:(Lscala/concurrent/ListQueueCreator;)V
const #25 = Method	#21.#24;	//  scala/concurrent/ListQueueCreator$class.$init$:(Lscala/concurrent/ListQueueCreator;)V
const #26 = Asciz	scala/concurrent/ListQueueCreator;
const #27 = class	#26;	//  scala/concurrent/ListQueueCreator
const #28 = Asciz	queueCreate;
const #29 = Asciz	()Lscala/concurrent/QueueModule;;
const #30 = NameAndType	#28:#29;//  queueCreate:()Lscala/concurrent/QueueModule;
const #31 = InterfaceMethod	#27.#30;	//  scala/concurrent/ListQueueCreator.queueCreate:()Lscala/concurrent/QueueModule;
const #32 = Asciz	scala/concurrent/MailBox;
const #33 = class	#32;	//  scala/concurrent/MailBox
const #34 = NameAndType	#10:#8;//  messageQueue:Lscala/concurrent/QueueModule;
const #35 = Field	#33.#34;	//  scala/concurrent/MailBox.messageQueue:Lscala/concurrent/QueueModule;
const #36 = NameAndType	#7:#8;//  receiverQueue:Lscala/concurrent/QueueModule;
const #37 = Field	#33.#36;	//  scala/concurrent/MailBox.receiverQueue:Lscala/concurrent/QueueModule;
const #38 = NameAndType	#10:#29;//  messageQueue:()Lscala/concurrent/QueueModule;
const #39 = Method	#33.#38;	//  scala/concurrent/MailBox.messageQueue:()Lscala/concurrent/QueueModule;
const #40 = Asciz	scala/concurrent/QueueModule;
const #41 = class	#40;	//  scala/concurrent/QueueModule
const #42 = Asciz	make;
const #43 = Asciz	()Ljava/lang/Object;;
const #44 = NameAndType	#42:#43;//  make:()Ljava/lang/Object;
const #45 = InterfaceMethod	#41.#44;	//  scala/concurrent/QueueModule.make:()Ljava/lang/Object;
const #46 = NameAndType	#6:#4;//  sent:Ljava/lang/Object;
const #47 = Field	#33.#46;	//  scala/concurrent/MailBox.sent:Ljava/lang/Object;
const #48 = NameAndType	#7:#29;//  receiverQueue:()Lscala/concurrent/QueueModule;
const #49 = Method	#33.#48;	//  scala/concurrent/MailBox.receiverQueue:()Lscala/concurrent/QueueModule;
const #50 = NameAndType	#3:#4;//  receivers:Ljava/lang/Object;
const #51 = Field	#33.#50;	//  scala/concurrent/MailBox.receivers:Ljava/lang/Object;
const #52 = Asciz	receiveWithin;
const #53 = Asciz	(JLscala/PartialFunction;)Ljava/lang/Object;;
const #54 = Asciz	scala/concurrent/MailBox$Receiver;
const #55 = class	#54;	//  scala/concurrent/MailBox$Receiver
const #56 = Asciz	(Lscala/concurrent/MailBox;Lscala/PartialFunction;)V;
const #57 = NameAndType	#12:#56;//  "<init>":(Lscala/concurrent/MailBox;Lscala/PartialFunction;)V
const #58 = Method	#55.#57;	//  scala/concurrent/MailBox$Receiver."<init>":(Lscala/concurrent/MailBox;Lscala/PartialFunction;)V
const #59 = Asciz	scanSentMsgs;
const #60 = Asciz	(Lscala/concurrent/MailBox$Receiver;)V;
const #61 = NameAndType	#59:#60;//  scanSentMsgs:(Lscala/concurrent/MailBox$Receiver;)V
const #62 = Method	#33.#61;	//  scala/concurrent/MailBox.scanSentMsgs:(Lscala/concurrent/MailBox$Receiver;)V
const #63 = Asciz	(J)Ljava/lang/Object;;
const #64 = NameAndType	#52:#63;//  receiveWithin:(J)Ljava/lang/Object;
const #65 = Method	#55.#64;	//  scala/concurrent/MailBox$Receiver.receiveWithin:(J)Ljava/lang/Object;
const #66 = Asciz	this;
const #67 = Asciz	Lscala/concurrent/MailBox;;
const #68 = Asciz	msec;
const #69 = Asciz	J;
const #70 = Asciz	f;
const #71 = Asciz	Lscala/PartialFunction;;
const #72 = Asciz	r;
const #73 = Asciz	Lscala/concurrent/MailBox$Receiver;;
const #74 = Asciz	LocalVariableTable;
const #75 = Asciz	<A:Ljava/lang/Object;>(JLscala/PartialFunction<Ljava/lang/Object;TA;>;)TA;;
const #76 = Asciz	receive;
const #77 = Asciz	(Lscala/PartialFunction;)Ljava/lang/Object;;
const #78 = NameAndType	#76:#43;//  receive:()Ljava/lang/Object;
const #79 = Method	#55.#78;	//  scala/concurrent/MailBox$Receiver.receive:()Ljava/lang/Object;
const #80 = Asciz	<A:Ljava/lang/Object;>(Lscala/PartialFunction<Ljava/lang/Object;TA;>;)TA;;
const #81 = Asciz	send;
const #82 = Asciz	(Ljava/lang/Object;)V;
const #83 = NameAndType	#3:#43;//  receivers:()Ljava/lang/Object;
const #84 = Method	#33.#83;	//  scala/concurrent/MailBox.receivers:()Ljava/lang/Object;
const #85 = Asciz	scala/concurrent/MailBox$$anonfun$send$1;
const #86 = class	#85;	//  scala/concurrent/MailBox$$anonfun$send$1
const #87 = Asciz	(Lscala/concurrent/MailBox;Ljava/lang/Object;)V;
const #88 = NameAndType	#12:#87;//  "<init>":(Lscala/concurrent/MailBox;Ljava/lang/Object;)V
const #89 = Method	#86.#88;	//  scala/concurrent/MailBox$$anonfun$send$1."<init>":(Lscala/concurrent/MailBox;Ljava/lang/Object;)V
const #90 = Asciz	extractFirst;
const #91 = Asciz	(Ljava/lang/Object;Lscala/Function1;)Lscala/Option;;
const #92 = NameAndType	#90:#91;//  extractFirst:(Ljava/lang/Object;Lscala/Function1;)Lscala/Option;
const #93 = InterfaceMethod	#41.#92;	//  scala/concurrent/QueueModule.extractFirst:(Ljava/lang/Object;Lscala/Function1;)Lscala/Option;
const #94 = Asciz	scala/None$;
const #95 = class	#94;	//  scala/None$
const #96 = Asciz	MODULE$;
const #97 = Asciz	Lscala/None$;;
const #98 = NameAndType	#96:#97;//  MODULE$:Lscala/None$;
const #99 = Field	#95.#98;	//  scala/None$.MODULE$:Lscala/None$;
const #100 = Asciz	equals;
const #101 = Asciz	(Ljava/lang/Object;)Z;
const #102 = NameAndType	#100:#101;//  equals:(Ljava/lang/Object;)Z
const #103 = Method	#17.#102;	//  java/lang/Object.equals:(Ljava/lang/Object;)Z
const #104 = NameAndType	#6:#43;//  sent:()Ljava/lang/Object;
const #105 = Method	#33.#104;	//  scala/concurrent/MailBox.sent:()Ljava/lang/Object;
const #106 = Asciz	append;
const #107 = Asciz	(Ljava/lang/Object;Ljava/lang/Object;)Ljava/lang/Object;;
const #108 = NameAndType	#106:#107;//  append:(Ljava/lang/Object;Ljava/lang/Object;)Ljava/lang/Object;
const #109 = InterfaceMethod	#41.#108;	//  scala/concurrent/QueueModule.append:(Ljava/lang/Object;Ljava/lang/Object;)Ljava/lang/Object;
const #110 = Asciz	sent_$eq;
const #111 = NameAndType	#110:#82;//  sent_$eq:(Ljava/lang/Object;)V
const #112 = Method	#33.#111;	//  scala/concurrent/MailBox.sent_$eq:(Ljava/lang/Object;)V
const #113 = Asciz	scala/runtime/BoxedUnit;
const #114 = class	#113;	//  scala/runtime/BoxedUnit
const #115 = Asciz	UNIT;
const #116 = Asciz	Lscala/runtime/BoxedUnit;;
const #117 = NameAndType	#115:#116;//  UNIT:Lscala/runtime/BoxedUnit;
const #118 = Field	#114.#117;	//  scala/runtime/BoxedUnit.UNIT:Lscala/runtime/BoxedUnit;
const #119 = Asciz	scala/Some;
const #120 = class	#119;	//  scala/Some
const #121 = Asciz	x;
const #122 = NameAndType	#121:#43;//  x:()Ljava/lang/Object;
const #123 = Method	#120.#122;	//  scala/Some.x:()Ljava/lang/Object;
const #124 = Asciz	scala/Tuple2;
const #125 = class	#124;	//  scala/Tuple2
const #126 = Asciz	_1;
const #127 = NameAndType	#126:#43;//  _1:()Ljava/lang/Object;
const #128 = Method	#125.#127;	//  scala/Tuple2._1:()Ljava/lang/Object;
const #129 = Asciz	scala/concurrent/MailBox$PreReceiver;
const #130 = class	#129;	//  scala/concurrent/MailBox$PreReceiver
const #131 = Asciz	_2;
const #132 = NameAndType	#131:#43;//  _2:()Ljava/lang/Object;
const #133 = Method	#125.#132;	//  scala/Tuple2._2:()Ljava/lang/Object;
const #134 = Asciz	receivers_$eq;
const #135 = NameAndType	#134:#82;//  receivers_$eq:(Ljava/lang/Object;)V
const #136 = Method	#33.#135;	//  scala/concurrent/MailBox.receivers_$eq:(Ljava/lang/Object;)V
const #137 = Asciz	msg_$eq;
const #138 = NameAndType	#137:#82;//  msg_$eq:(Ljava/lang/Object;)V
const #139 = Method	#130.#138;	//  scala/concurrent/MailBox$PreReceiver.msg_$eq:(Ljava/lang/Object;)V
const #140 = Asciz	notify;
const #141 = NameAndType	#140:#13;//  notify:()V
const #142 = Method	#130.#141;	//  scala/concurrent/MailBox$PreReceiver.notify:()V
const #143 = Asciz	scala/MatchError;
const #144 = class	#143;	//  scala/MatchError
const #145 = Asciz	scala/Option;
const #146 = class	#145;	//  scala/Option
const #147 = Asciz	toString;
const #148 = Asciz	()Ljava/lang/String;;
const #149 = NameAndType	#147:#148;//  toString:()Ljava/lang/String;
const #150 = Method	#146.#149;	//  scala/Option.toString:()Ljava/lang/String;
const #151 = Asciz	(Ljava/lang/String;)V;
const #152 = NameAndType	#12:#151;//  "<init>":(Ljava/lang/String;)V
const #153 = Method	#144.#152;	//  scala/MatchError."<init>":(Ljava/lang/String;)V
const #154 = Asciz	msg$1;
const #155 = Asciz	temp7;
const #156 = Asciz	Lscala/Option;;
const #157 = Asciz	temp9;
const #158 = Asciz	Lscala/Some;;
const #159 = Asciz	temp10;
const #160 = Asciz	Lscala/Tuple2;;
const #161 = Asciz	temp11;
const #162 = Asciz	Lscala/concurrent/MailBox$PreReceiver;;
const #163 = Asciz	temp12;
const #164 = Asciz	withoutReceiver;
const #165 = Asciz	receiver;
const #166 = Asciz	scala/concurrent/MailBox$$anonfun$scanSentMsgs$1;
const #167 = class	#166;	//  scala/concurrent/MailBox$$anonfun$scanSentMsgs$1
const #168 = Asciz	(Lscala/concurrent/MailBox;Lscala/concurrent/MailBox$Receiver;)V;
const #169 = NameAndType	#12:#168;//  "<init>":(Lscala/concurrent/MailBox;Lscala/concurrent/MailBox$Receiver;)V
const #170 = Method	#167.#169;	//  scala/concurrent/MailBox$$anonfun$scanSentMsgs$1."<init>":(Lscala/concurrent/MailBox;Lscala/concurrent/MailBox$Receiver;)V
const #171 = Method	#55.#138;	//  scala/concurrent/MailBox$Receiver.msg_$eq:(Ljava/lang/Object;)V
const #172 = Asciz	receiver$1;
const #173 = Asciz	temp1;
const #174 = Asciz	temp3;
const #175 = Asciz	temp4;
const #176 = Asciz	temp5;
const #177 = Asciz	temp6;
const #178 = Asciz	withoutMsg;
const #179 = Asciz	<A:Ljava/lang/Object;>(Lscala/concurrent/MailBox$Receiver<TA;>;)V;
const #180 = Asciz	()Lscala/concurrent/QueueModule<Lscala/concurrent/MailBox$PreReceiver;>;;
const #181 = Asciz	()Lscala/concurrent/QueueModule<Ljava/lang/Object;>;;
const #182 = Asciz	(Lscala/concurrent/ListQueueCreator;)Lscala/concurrent/QueueModule;;
const #183 = NameAndType	#28:#182;//  queueCreate:(Lscala/concurrent/ListQueueCreator;)Lscala/concurrent/QueueModule;
const #184 = Method	#21.#183;	//  scala/concurrent/ListQueueCreator$class.queueCreate:(Lscala/concurrent/ListQueueCreator;)Lscala/concurrent/QueueModule;
const #185 = Asciz	ScalaSig;
const #186 = Asciz	InnerClasses;
const #187 = Asciz	Receiver;
const #188 = Asciz	PreReceiver;
const #189 = Asciz	$anonfun$send$1;
const #190 = Asciz	$anonfun$scanSentMsgs$1;
const #191 = Asciz	scala/ScalaObject;
const #192 = class	#191;	//  scala/ScalaObject

{
public scala.concurrent.MailBox();
  Code:
   Stack=2, Locals=1, Args_size=1
   0:	aload_0
   1:	invokespecial	#19; //Method java/lang/Object."<init>":()V
   4:	aload_0
   5:	invokestatic	#25; //Method scala/concurrent/ListQueueCreator$class.$init$:(Lscala/concurrent/ListQueueCreator;)V
   8:	aload_0
   9:	aload_0
   10:	invokeinterface	#31,  1; //InterfaceMethod scala/concurrent/ListQueueCreator.queueCreate:()Lscala/concurrent/QueueModule;
   15:	putfield	#35; //Field messageQueue:Lscala/concurrent/QueueModule;
   18:	aload_0
   19:	aload_0
   20:	invokeinterface	#31,  1; //InterfaceMethod scala/concurrent/ListQueueCreator.queueCreate:()Lscala/concurrent/QueueModule;
   25:	putfield	#37; //Field receiverQueue:Lscala/concurrent/QueueModule;
   28:	aload_0
   29:	aload_0
   30:	invokespecial	#39; //Method messageQueue:()Lscala/concurrent/QueueModule;
   33:	invokeinterface	#45,  1; //InterfaceMethod scala/concurrent/QueueModule.make:()Ljava/lang/Object;
   38:	putfield	#47; //Field sent:Ljava/lang/Object;
   41:	aload_0
   42:	aload_0
   43:	invokespecial	#49; //Method receiverQueue:()Lscala/concurrent/QueueModule;
   46:	invokeinterface	#45,  1; //InterfaceMethod scala/concurrent/QueueModule.make:()Ljava/lang/Object;
   51:	putfield	#51; //Field receivers:Ljava/lang/Object;
   54:	return
  LineNumberTable: 
   line 20: 0
   line 44: 8
   line 45: 18
   line 48: 28
   line 51: 41


public java.lang.Object receiveWithin(long, scala.PartialFunction);
  Code:
   Stack=4, Locals=5, Args_size=3
   0:	new	#55; //class scala/concurrent/MailBox$Receiver
   3:	dup
   4:	aload_0
   5:	aload_3
   6:	invokespecial	#58; //Method scala/concurrent/MailBox$Receiver."<init>":(Lscala/concurrent/MailBox;Lscala/PartialFunction;)V
   9:	astore	4
   11:	aload_0
   12:	aload	4
   14:	invokespecial	#62; //Method scanSentMsgs:(Lscala/concurrent/MailBox$Receiver;)V
   17:	aload	4
   19:	lload_1
   20:	invokevirtual	#65; //Method scala/concurrent/MailBox$Receiver.receiveWithin:(J)Ljava/lang/Object;
   23:	areturn
  LineNumberTable: 
   line 99: 0
   line 100: 11
   line 101: 17

  LocalVariableTable: 
   Start  Length  Slot  Name   Signature
   0      24      0    this       Lscala/concurrent/MailBox;
   0      24      1    msec       J
   0      24      3    f       Lscala/PartialFunction;
   11      12      4    r       Lscala/concurrent/MailBox$Receiver;

  Signature: length = 0x2
   00 4B 

public java.lang.Object receive(scala.PartialFunction);
  Code:
   Stack=4, Locals=3, Args_size=2
   0:	new	#55; //class scala/concurrent/MailBox$Receiver
   3:	dup
   4:	aload_0
   5:	aload_1
   6:	invokespecial	#58; //Method scala/concurrent/MailBox$Receiver."<init>":(Lscala/concurrent/MailBox;Lscala/PartialFunction;)V
   9:	astore_2
   10:	aload_0
   11:	aload_2
   12:	invokespecial	#62; //Method scanSentMsgs:(Lscala/concurrent/MailBox$Receiver;)V
   15:	aload_2
   16:	invokevirtual	#79; //Method scala/concurrent/MailBox$Receiver.receive:()Ljava/lang/Object;
   19:	areturn
  LineNumberTable: 
   line 89: 0
   line 90: 10
   line 91: 15

  LocalVariableTable: 
   Start  Length  Slot  Name   Signature
   0      20      0    this       Lscala/concurrent/MailBox;
   0      20      1    f       Lscala/PartialFunction;
   10      9      2    r       Lscala/concurrent/MailBox$Receiver;

  Signature: length = 0x2
   00 50 

public void send(java.lang.Object);
  Code:
   Stack=6, Locals=12, Args_size=2
   0:	aload_0
   1:	dup
   2:	astore_2
   3:	monitorenter
   4:	aload_0
   5:	invokespecial	#49; //Method receiverQueue:()Lscala/concurrent/QueueModule;
   8:	aload_0
   9:	invokespecial	#84; //Method receivers:()Ljava/lang/Object;
   12:	new	#86; //class scala/concurrent/MailBox$$anonfun$send$1
   15:	dup
   16:	aload_0
   17:	aload_1
   18:	invokespecial	#89; //Method scala/concurrent/MailBox$$anonfun$send$1."<init>":(Lscala/concurrent/MailBox;Ljava/lang/Object;)V
   21:	invokeinterface	#93,  3; //InterfaceMethod scala/concurrent/QueueModule.extractFirst:(Ljava/lang/Object;Lscala/Function1;)Lscala/Option;
   26:	astore_3
   27:	getstatic	#99; //Field scala/None$.MODULE$:Lscala/None$;
   30:	aload_3
   31:	astore	4
   33:	dup
   34:	ifnonnull	46
   37:	pop
   38:	aload	4
   40:	ifnull	54
   43:	goto	85
   46:	aload	4
   48:	invokevirtual	#103; //Method java/lang/Object.equals:(Ljava/lang/Object;)Z
   51:	ifeq	85
   54:	aload_3
   55:	instanceof	#95; //class scala/None$
   58:	ifeq	85
   61:	aload_0
   62:	aload_0
   63:	invokespecial	#39; //Method messageQueue:()Lscala/concurrent/QueueModule;
   66:	aload_0
   67:	invokespecial	#105; //Method sent:()Ljava/lang/Object;
   70:	aload_1
   71:	invokeinterface	#109,  3; //InterfaceMethod scala/concurrent/QueueModule.append:(Ljava/lang/Object;Ljava/lang/Object;)Ljava/lang/Object;
   76:	invokespecial	#112; //Method sent_$eq:(Ljava/lang/Object;)V
   79:	getstatic	#118; //Field scala/runtime/BoxedUnit.UNIT:Lscala/runtime/BoxedUnit;
   82:	goto	167
   85:	aload_3
   86:	instanceof	#120; //class scala/Some
   89:	ifeq	183
   92:	aload_3
   93:	checkcast	#120; //class scala/Some
   96:	astore	5
   98:	aload	5
   100:	invokevirtual	#123; //Method scala/Some.x:()Ljava/lang/Object;
   103:	checkcast	#125; //class scala/Tuple2
   106:	astore	6
   108:	aload	6
   110:	ifnull	171
   113:	aload	6
   115:	invokevirtual	#128; //Method scala/Tuple2._1:()Ljava/lang/Object;
   118:	checkcast	#130; //class scala/concurrent/MailBox$PreReceiver
   121:	astore	7
   123:	aload	6
   125:	invokevirtual	#133; //Method scala/Tuple2._2:()Ljava/lang/Object;
   128:	astore	8
   130:	aload	8
   132:	astore	9
   134:	aload	7
   136:	astore	10
   138:	aload_0
   139:	aload	9
   141:	invokespecial	#136; //Method receivers_$eq:(Ljava/lang/Object;)V
   144:	aload	10
   146:	aload_1
   147:	invokevirtual	#139; //Method scala/concurrent/MailBox$PreReceiver.msg_$eq:(Ljava/lang/Object;)V
   150:	aload	10
   152:	dup
   153:	astore	11
   155:	monitorenter
   156:	aload	10
   158:	invokevirtual	#142; //Method scala/concurrent/MailBox$PreReceiver.notify:()V
   161:	getstatic	#118; //Field scala/runtime/BoxedUnit.UNIT:Lscala/runtime/BoxedUnit;
   164:	aload	11
   166:	monitorexit
   167:	pop
   168:	aload_2
   169:	monitorexit
   170:	return
   171:	new	#144; //class scala/MatchError
   174:	dup
   175:	aload_3
   176:	invokevirtual	#150; //Method scala/Option.toString:()Ljava/lang/String;
   179:	invokespecial	#153; //Method scala/MatchError."<init>":(Ljava/lang/String;)V
   182:	athrow
   183:	new	#144; //class scala/MatchError
   186:	dup
   187:	aload_3
   188:	invokevirtual	#150; //Method scala/Option.toString:()Ljava/lang/String;
   191:	invokespecial	#153; //Method scala/MatchError."<init>":(Ljava/lang/String;)V
   194:	athrow
   195:	aload	11
   197:	monitorexit
   198:	athrow
   199:	aload_2
   200:	monitorexit
   201:	athrow
  Exception table:
   from   to  target type
   156   167   195   any
     4   170   199   any
   171   199   199   any
  LineNumberTable: 
   line 73: 0
   line 74: 4
   line 76: 61
   line 74: 85
   line 77: 130
   line 78: 138
   line 79: 144
   line 80: 150
   line 74: 167
   line 73: 169
   line 74: 171
   line 80: 197
   line 73: 200

  LocalVariableTable: 
   Start  Length  Slot  Name   Signature
   0      202      0    this       Lscala/concurrent/MailBox;
   0      202      1    msg$1       Ljava/lang/Object;
   27      141      3    temp7       Lscala/Option;
   171      28      3    temp7       Lscala/Option;
   98      69      5    temp9       Lscala/Some;
   171      12      5    temp9       Lscala/Some;
   195      4      5    temp9       Lscala/Some;
   108      59      6    temp10       Lscala/Tuple2;
   171      12      6    temp10       Lscala/Tuple2;
   195      4      6    temp10       Lscala/Tuple2;
   123      44      7    temp11       Lscala/concurrent/MailBox$PreReceiver;
   195      4      7    temp11       Lscala/concurrent/MailBox$PreReceiver;
   130      37      8    temp12       Ljava/lang/Object;
   195      4      8    temp12       Ljava/lang/Object;
   134      33      9    withoutReceiver       Ljava/lang/Object;
   195      4      9    withoutReceiver       Ljava/lang/Object;
   138      29      10    receiver       Lscala/concurrent/MailBox$PreReceiver;
   195      4      10    receiver       Lscala/concurrent/MailBox$PreReceiver;


public scala.concurrent.QueueModule queueCreate();
  Code:
   Stack=1, Locals=1, Args_size=1
   0:	aload_0
   1:	invokestatic	#184; //Method scala/concurrent/ListQueueCreator$class.queueCreate:(Lscala/concurrent/ListQueueCreator;)Lscala/concurrent/QueueModule;
   4:	areturn
  LineNumberTable: 
   line 20: 0


}

