Compiled from "MailBox.scala"
public final class scala.concurrent.MailBox$$anonfun$scanSentMsgs$1 extends java.lang.Object implements scala.Function1,scala.ScalaObject,java.io.Serializable
  SourceFile: "MailBox.scala"
  Scala: length = 0x
   
  InnerClass: 
   public Receiver=class scala/concurrent/MailBox$Receiver of class scala/concurrent/MailBox
   public final $anonfun$scanSentMsgs$1=class scala/concurrent/MailBox$$anonfun$scanSentMsgs$1 of class scala/concurrent/MailBox
  minor version: 0
  major version: 49
  Constant pool:
Asciz	SourceFile;
Asciz	MailBox.scala;
Asciz	<clinit>;
Asciz	()V;
Asciz	Code;
Asciz	serialVersionUID;
Asciz	J;
Asciz	scala/concurrent/MailBox$$anonfun$scanSentMsgs$1;
class	scala/concurrent/MailBox$$anonfun$scanSentMsgs$1
NameAndType	serialVersionUID:J
Field	scala/concurrent/MailBox$$anonfun$scanSentMsgs$1.serialVersionUID:J
Asciz	receiver$1;
Asciz	Lscala/concurrent/MailBox$Receiver;;
Asciz	<init>;
Asciz	(Lscala/concurrent/MailBox;Lscala/concurrent/MailBox$Receiver;)V;
Asciz	LineNumberTable;
NameAndType	receiver$1:Lscala/concurrent/MailBox$Receiver;
Field	scala/concurrent/MailBox$$anonfun$scanSentMsgs$1.receiver$1:Lscala/concurrent/MailBox$Receiver;
Asciz	java/lang/Object;
class	java/lang/Object
NameAndType	"<init>":()V
Method	java/lang/Object."<init>":()V
Asciz	scala/Function1$class;
class	scala/Function1$class
Asciz	$init$;
Asciz	(Lscala/Function1;)V;
NameAndType	$init$:(Lscala/Function1;)V
Method	scala/Function1$class.$init$:(Lscala/Function1;)V
Asciz	this;
Asciz	Lscala/concurrent/MailBox$$anonfun$scanSentMsgs$1;;
Asciz	$outer;
Asciz	Lscala/concurrent/MailBox;;
Asciz	LocalVariableTable;
Asciz	apply;
Asciz	(Ljava/lang/Object;)Ljava/lang/Object;;
Asciz	(Ljava/lang/Object;)Z;
NameAndType	apply:(Ljava/lang/Object;)Z
Method	scala/concurrent/MailBox$$anonfun$scanSentMsgs$1.apply:(Ljava/lang/Object;)Z
Asciz	scala/runtime/BoxesRunTime;
class	scala/runtime/BoxesRunTime
Asciz	boxToBoolean;
Asciz	(Z)Ljava/lang/Boolean;;
NameAndType	boxToBoolean:(Z)Ljava/lang/Boolean;
Method	scala/runtime/BoxesRunTime.boxToBoolean:(Z)Ljava/lang/Boolean;
Asciz	v1;
Asciz	Ljava/lang/Object;;
Asciz	scala/concurrent/MailBox$Receiver;
class	scala/concurrent/MailBox$Receiver
Asciz	isDefinedAt;
NameAndType	isDefinedAt:(Ljava/lang/Object;)Z
Method	scala/concurrent/MailBox$Receiver.isDefinedAt:(Ljava/lang/Object;)Z
Asciz	msg;
Asciz	andThen;
Asciz	(Lscala/Function1;)Lscala/Function1;;
Asciz	(Lscala/Function1;Lscala/Function1;)Lscala/Function1;;
NameAndType	andThen:(Lscala/Function1;Lscala/Function1;)Lscala/Function1;
Method	scala/Function1$class.andThen:(Lscala/Function1;Lscala/Function1;)Lscala/Function1;
Asciz	g;
Asciz	Lscala/Function1;;
Asciz	compose;
NameAndType	compose:(Lscala/Function1;Lscala/Function1;)Lscala/Function1;
Method	scala/Function1$class.compose:(Lscala/Function1;Lscala/Function1;)Lscala/Function1;
Asciz	toString;
Asciz	()Ljava/lang/String;;
Asciz	(Lscala/Function1;)Ljava/lang/String;;
NameAndType	toString:(Lscala/Function1;)Ljava/lang/String;
Method	scala/Function1$class.toString:(Lscala/Function1;)Ljava/lang/String;
Asciz	Scala;
Asciz	InnerClasses;
Asciz	scala/concurrent/MailBox;
class	scala/concurrent/MailBox
Asciz	Receiver;
Asciz	$anonfun$scanSentMsgs$1;
Asciz	scala/Function1;
class	scala/Function1
Asciz	scala/ScalaObject;
class	scala/ScalaObject
Asciz	java/io/Serializable;
class	java/io/Serializable

{
public static final long serialVersionUID;
  Signature: J

private final scala.concurrent.MailBox$Receiver receiver$1;
  Signature: Lscala/concurrent/MailBox$Receiver;

public static {};
  Signature: ()V
  Code:
   Stack=2, Locals=0, Args_size=0
	lconst_0
	putstatic	Field serialVersionUID:J
	return
  Labels:

public scala.concurrent.MailBox$$anonfun$scanSentMsgs$1(scala.concurrent.MailBox, scala.concurrent.MailBox$Receiver);
  Signature: (Lscala/concurrent/MailBox;Lscala/concurrent/MailBox$Receiver;)V
  Code:
   Stack=2, Locals=3, Args_size=3
	aload_0
	aload_2
	putfield	Field receiver$1:Lscala/concurrent/MailBox$Receiver;
	aload_0
	invokespecial	Method java/lang/Object."<init>":()V
	aload_0
	invokestatic	Method scala/Function1$class.$init$:(Lscala/Function1;)V
	return
  Labels:
  LocalVariableTable: 
   Start  Length  Slot  Name   Signature
   0      14      0    this       Lscala/concurrent/MailBox$$anonfun$scanSentMsgs$1;
   0      14      1    $outer       Lscala/concurrent/MailBox;


public final java.lang.Object apply(java.lang.Object);
  Signature: (Ljava/lang/Object;)Ljava/lang/Object;
  Code:
   Stack=2, Locals=3, Args_size=2
	aload_0
	aload_1
	invokevirtual	Method apply:(Ljava/lang/Object;)Z
	istore_2
	iload_2
	invokestatic	Method scala/runtime/BoxesRunTime.boxToBoolean:(Z)Ljava/lang/Boolean;
	areturn
  Labels:
  LocalVariableTable: 
   Start  Length  Slot  Name   Signature
   0      11      0    this       Lscala/concurrent/MailBox$$anonfun$scanSentMsgs$1;
   0      11      1    v1       Ljava/lang/Object;


public final boolean apply(java.lang.Object);
  Signature: (Ljava/lang/Object;)Z
  Code:
   Stack=2, Locals=2, Args_size=2
	aload_0
	getfield	Field receiver$1:Lscala/concurrent/MailBox$Receiver;
	aload_1
	invokevirtual	Method scala/concurrent/MailBox$Receiver.isDefinedAt:(Ljava/lang/Object;)Z
	ireturn
  Labels:
  LocalVariableTable: 
   Start  Length  Slot  Name   Signature
   0      9      0    this       Lscala/concurrent/MailBox$$anonfun$scanSentMsgs$1;
   0      9      1    msg       Ljava/lang/Object;


public scala.Function1 andThen(scala.Function1);
  Signature: (Lscala/Function1;)Lscala/Function1;
  Code:
   Stack=2, Locals=2, Args_size=2
	aload_0
	aload_1
	invokestatic	Method scala/Function1$class.andThen:(Lscala/Function1;Lscala/Function1;)Lscala/Function1;
	areturn
  Labels:
  LocalVariableTable: 
   Start  Length  Slot  Name   Signature
   0      6      0    this       Lscala/concurrent/MailBox$$anonfun$scanSentMsgs$1;
   0      6      1    g       Lscala/Function1;


public scala.Function1 compose(scala.Function1);
  Signature: (Lscala/Function1;)Lscala/Function1;
  Code:
   Stack=2, Locals=2, Args_size=2
	aload_0
	aload_1
	invokestatic	Method scala/Function1$class.compose:(Lscala/Function1;Lscala/Function1;)Lscala/Function1;
	areturn
  Labels:
  LocalVariableTable: 
   Start  Length  Slot  Name   Signature
   0      6      0    this       Lscala/concurrent/MailBox$$anonfun$scanSentMsgs$1;
   0      6      1    g       Lscala/Function1;


public java.lang.String toString();
  Signature: ()Ljava/lang/String;
  Code:
   Stack=1, Locals=1, Args_size=1
	aload_0
	invokestatic	Method scala/Function1$class.toString:(Lscala/Function1;)Ljava/lang/String;
	areturn
  Labels:

}

