Compiled from "MailBox.scala"
public class scala.concurrent.MailBox extends java.lang.Object implements scala.concurrent.ListQueueCreator,scala.ScalaObject
  SourceFile: "MailBox.scala"
  ScalaSig: length = 0x4AA
   05 00 FFFFFF81 2F 06 08 01 02 FFFFFF84 FFFFFF80 FFFFFF80 FFFFFF80 00 07 02 07
   4D 61 69 6C 42 6F 78 0A 02 03 04 01 0A 63 6F 6E
   63 75 72 72 65 6E 74 0A 01 05 01 05 73 63 61 6C
   61 03 00 13 04 00 08 10 14 10 02 09 0E 0D 01 0A
   0A 02 0B 0C 01 04 6C 61 6E 67 0A 01 0D 01 04 6A
   61 76 61 09 02 0F 0A 02 06 4F 62 6A 65 63 74 10
   02 11 12 0D 01 02 09 02 13 02 02 10 4C 69 73 74
   51 75 65 75 65 43 72 65 61 74 6F 72 10 02 15 16
   0D 01 04 09 02 17 04 02 0B 53 63 61 6C 61 4F 62
   6A 65 63 74 08 05 19 00 FFFFFF84 00 1A 01 06 3C 69 6E
   69 74 3E 14 01 1B 10 02 11 00 05 08 1D 00 FFFFFF84 FFFFFF80
   FFFFFF80 FFFFFF80 00 1E 02 07 4D 65 73 73 61 67 65 10 02 15
   1F 09 02 20 04 02 06 41 6E 79 52 65 66 06 08 22
   00 FFFFFF84 FFFFFF80 FFFFFF80 FFFFFF81 04 23 02 0B 50 72 65 52 65 63 65
   69 76 65 72 13 03 21 08 14 08 05 19 21 FFFFFF84 00 25
   14 01 26 10 02 27 21 0D 01 00 08 07 29 21 FFFFFFC0 FFFFFF80
   FFFFFF84 00 2A 01 03 6D 73 67 15 01 2B 10 02 27 1C 08
   07 2D 21 FFFFFFC0 FFFFFF80 FFFFFF84 00 2E 01 07 6D 73 67 5F 24 65
   71 14 02 2F 32 10 02 15 30 09 02 31 04 02 04 55
   6E 69 74 08 07 33 2C FFFFFF81 FFFFFF80 FFFFFFC0 00 2B 01 03 78 24
   31 08 06 35 21 FFFFFFA0 FFFFFFA0 04 2B 01 04 6D 73 67 20 08
   05 37 21 FFFFFF86 00 38 01 0B 69 73 44 65 66 69 6E 65
   64 41 74 14 02 39 3C 10 02 15 3A 09 02 3B 04 02
   07 42 6F 6F 6C 65 61 6E 08 05 29 36 FFFFFFC0 00 2B 06
   04 3E 00 04 3F 02 08 52 65 63 65 69 76 65 72 15
   02 40 51 13 03 3D 26 14 08 08 42 3D FFFFFF82 FFFFFF80 FFFFFFA0 FFFFFF80
   04 43 01 08 72 65 63 65 69 76 65 72 10 04 44 4C
   2B 4F 0E 02 45 4A 0E 02 46 49 0D 01 47 0A 02 48
   06 01 06 3C 72 6F 6F 74 3E 09 01 05 09 02 4B 04
   01 07 70 61 63 6B 61 67 65 09 02 4D 4E 02 11 24
   65 71 24 67 72 65 61 74 65 72 24 71 6D 61 72 6B
   0A 02 4B 04 10 02 50 51 0C 00 04 08 52 3D FFFFFF84 FFFFFF80
   FFFFFF80 FFFFFFC2 00 53 02 01 41 11 02 54 57 10 02 15 55 09
   02 56 04 02 07 4E 6F 74 68 69 6E 67 10 02 15 58
   09 02 59 04 02 03 41 6E 79 08 05 19 3D FFFFFF84 00 5B
   14 02 5C 5D 10 03 27 3D 4F 08 05 42 5A FFFFFFC0 00 43
   08 05 37 3D FFFFFF84 00 5F 14 02 39 60 08 05 29 5E FFFFFFC0
   00 2B 08 05 62 3D FFFFFF84 00 63 01 07 72 65 63 65 69
   76 65 14 01 4F 08 05 65 3D FFFFFF84 00 66 01 0D 72 65
   63 65 69 76 65 57 69 74 68 69 6E 14 02 4F 67 08
   05 68 64 FFFFFFC0 00 69 01 04 6D 73 65 63 10 02 15 6A
   09 02 6B 04 02 04 4C 6F 6E 67 08 07 6D 00 FFFFFFC2 FFFFFF80
   FFFFFF84 04 6E 01 0C 6D 65 73 73 61 67 65 51 75 65 75
   65 15 01 6F 10 03 11 70 2B 09 02 71 02 02 0B 51
   75 65 75 65 4D 6F 64 75 6C 65 08 06 73 00 FFFFFFA0 FFFFFF80
   04 6F 01 0D 6D 65 73 73 61 67 65 51 75 65 75 65
   20 08 07 75 00 FFFFFFC2 FFFFFF80 FFFFFF84 04 76 01 0D 72 65 63 65
   69 76 65 72 51 75 65 75 65 15 01 77 10 03 11 70
   26 08 06 79 00 FFFFFFA0 FFFFFF80 04 77 01 0E 72 65 63 65 69
   76 65 72 51 75 65 75 65 20 08 07 7B 00 FFFFFFC0 FFFFFF80 FFFFFF84
   04 7C 01 04 73 65 6E 74 15 01 7D 10 02 7E 7F 0E
   02 27 6C 09 03 FFFFFF81 00 70 02 01 54 08 09 FFFFFF81 02 00
   FFFFFFC0 FFFFFF80 FFFFFF84 04 FFFFFF81 03 01 08 73 65 6E 74 5F 24 65 71
   14 03 2F FFFFFF81 04 08 08 33 FFFFFF81 01 FFFFFF81 FFFFFF80 FFFFFFC0 00 7D 08
   07 FFFFFF81 06 00 FFFFFFA0 FFFFFFA0 04 7D 01 05 73 65 6E 74 20 08
   09 FFFFFF81 08 00 FFFFFFC0 FFFFFF80 FFFFFF84 04 FFFFFF81 09 01 09 72 65 63 65
   69 76 65 72 73 15 02 FFFFFF81 0A 10 03 FFFFFF81 0B 7F 0E 02
   27 74 08 09 FFFFFF81 0D 00 FFFFFFC0 FFFFFF80 FFFFFF84 04 FFFFFF81 0E 01 0D 72
   65 63 65 69 76 65 72 73 5F 24 65 71 14 03 2F FFFFFF81
   0F 08 09 33 FFFFFF81 0C FFFFFF81 FFFFFF80 FFFFFFC0 00 FFFFFF81 0A 08 08 FFFFFF81 11
   00 FFFFFFA0 FFFFFFA0 04 FFFFFF81 0A 01 0A 72 65 63 65 69 76 65 72
   73 20 08 07 FFFFFF81 13 00 FFFFFF84 04 FFFFFF81 14 01 0C 73 63 61
   6E 53 65 6E 74 4D 73 67 73 15 04 FFFFFF81 15 FFFFFF81 19 14
   03 2F FFFFFF81 16 08 07 42 FFFFFF81 12 FFFFFFC0 00 FFFFFF81 17 10 04 27
   3D FFFFFF81 18 10 03 50 FFFFFF81 19 04 09 52 FFFFFF81 12 FFFFFF84 FFFFFF80 FFFFFF80
   FFFFFFC2 00 53 08 07 FFFFFF81 1B 00 FFFFFF84 00 FFFFFF81 1C 01 04 73 65
   6E 64 14 03 2F FFFFFF81 1D 08 06 29 FFFFFF81 1A FFFFFFC0 00 2B 08
   06 62 00 FFFFFF84 00 FFFFFF81 1F 15 04 FFFFFF81 20 FFFFFF81 22 14 04 FFFFFF81
   21 FFFFFF81 23 10 03 50 FFFFFF81 22 04 09 52 FFFFFF81 1E FFFFFF84 FFFFFF80 FFFFFF80
   FFFFFFC2 00 53 08 08 FFFFFF81 24 FFFFFF81 1E FFFFFFC0 00 FFFFFF81 25 01 01 66
   10 05 44 4C 2B FFFFFF81 21 08 06 65 00 FFFFFF84 00 FFFFFF81 27 15
   04 FFFFFF81 28 FFFFFF81 2B 14 04 FFFFFF81 29 FFFFFF81 2E 14 04 FFFFFF81 2A FFFFFF81
   2C 10 03 50 FFFFFF81 2B 04 09 52 FFFFFF81 26 FFFFFF84 FFFFFF80 FFFFFF80 FFFFFFC2 00
   53 08 08 FFFFFF81 24 FFFFFF81 26 FFFFFFC0 00 FFFFFF81 2D 10 05 44 4C 2B
   FFFFFF81 2A 08 06 68 FFFFFF81 26 FFFFFFC0 00 69 
  InnerClass: 
   public Receiver=class scala/concurrent/MailBox$Receiver of class scala/concurrent/MailBox
   public abstract PreReceiver=class scala/concurrent/MailBox$PreReceiver of class scala/concurrent/MailBox
   public final $anonfun$send$1=class scala/concurrent/MailBox$$anonfun$send$1 of class scala/concurrent/MailBox
   public final $anonfun$scanSentMsgs$1=class scala/concurrent/MailBox$$anonfun$scanSentMsgs$1 of class scala/concurrent/MailBox
  minor version: 0
  major version: 49
  Constant pool:
Asciz	SourceFile;
Asciz	MailBox.scala;
Asciz	receivers;
Asciz	Ljava/lang/Object;;
Asciz	Signature;
Asciz	sent;
Asciz	receiverQueue;
Asciz	Lscala/concurrent/QueueModule;;
Asciz	Lscala/concurrent/QueueModule<Lscala/concurrent/MailBox$PreReceiver;>;;
Asciz	messageQueue;
Asciz	Lscala/concurrent/QueueModule<Ljava/lang/Object;>;;
Asciz	<init>;
Asciz	()V;
Asciz	Code;
Asciz	LineNumberTable;
Asciz	java/lang/Object;
class	java/lang/Object
NameAndType	"<init>":()V
Method	java/lang/Object."<init>":()V
Asciz	scala/concurrent/ListQueueCreator$class;
class	scala/concurrent/ListQueueCreator$class
Asciz	$init$;
Asciz	(Lscala/concurrent/ListQueueCreator;)V;
NameAndType	$init$:(Lscala/concurrent/ListQueueCreator;)V
Method	scala/concurrent/ListQueueCreator$class.$init$:(Lscala/concurrent/ListQueueCreator;)V
Asciz	scala/concurrent/ListQueueCreator;
class	scala/concurrent/ListQueueCreator
Asciz	queueCreate;
Asciz	()Lscala/concurrent/QueueModule;;
NameAndType	queueCreate:()Lscala/concurrent/QueueModule;
InterfaceMethod	scala/concurrent/ListQueueCreator.queueCreate:()Lscala/concurrent/QueueModule;
Asciz	scala/concurrent/MailBox;
class	scala/concurrent/MailBox
NameAndType	messageQueue:Lscala/concurrent/QueueModule;
Field	scala/concurrent/MailBox.messageQueue:Lscala/concurrent/QueueModule;
NameAndType	receiverQueue:Lscala/concurrent/QueueModule;
Field	scala/concurrent/MailBox.receiverQueue:Lscala/concurrent/QueueModule;
NameAndType	messageQueue:()Lscala/concurrent/QueueModule;
Method	scala/concurrent/MailBox.messageQueue:()Lscala/concurrent/QueueModule;
Asciz	scala/concurrent/QueueModule;
class	scala/concurrent/QueueModule
Asciz	make;
Asciz	()Ljava/lang/Object;;
NameAndType	make:()Ljava/lang/Object;
InterfaceMethod	scala/concurrent/QueueModule.make:()Ljava/lang/Object;
NameAndType	sent:Ljava/lang/Object;
Field	scala/concurrent/MailBox.sent:Ljava/lang/Object;
NameAndType	receiverQueue:()Lscala/concurrent/QueueModule;
Method	scala/concurrent/MailBox.receiverQueue:()Lscala/concurrent/QueueModule;
NameAndType	receivers:Ljava/lang/Object;
Field	scala/concurrent/MailBox.receivers:Ljava/lang/Object;
Asciz	receiveWithin;
Asciz	(JLscala/PartialFunction;)Ljava/lang/Object;;
Asciz	scala/concurrent/MailBox$Receiver;
class	scala/concurrent/MailBox$Receiver
Asciz	(Lscala/concurrent/MailBox;Lscala/PartialFunction;)V;
NameAndType	"<init>":(Lscala/concurrent/MailBox;Lscala/PartialFunction;)V
Method	scala/concurrent/MailBox$Receiver."<init>":(Lscala/concurrent/MailBox;Lscala/PartialFunction;)V
Asciz	scanSentMsgs;
Asciz	(Lscala/concurrent/MailBox$Receiver;)V;
NameAndType	scanSentMsgs:(Lscala/concurrent/MailBox$Receiver;)V
Method	scala/concurrent/MailBox.scanSentMsgs:(Lscala/concurrent/MailBox$Receiver;)V
Asciz	(J)Ljava/lang/Object;;
NameAndType	receiveWithin:(J)Ljava/lang/Object;
Method	scala/concurrent/MailBox$Receiver.receiveWithin:(J)Ljava/lang/Object;
Asciz	this;
Asciz	Lscala/concurrent/MailBox;;
Asciz	msec;
Asciz	J;
Asciz	f;
Asciz	Lscala/PartialFunction;;
Asciz	r;
Asciz	Lscala/concurrent/MailBox$Receiver;;
Asciz	LocalVariableTable;
Asciz	<A:Ljava/lang/Object;>(JLscala/PartialFunction<Ljava/lang/Object;TA;>;)TA;;
Asciz	receive;
Asciz	(Lscala/PartialFunction;)Ljava/lang/Object;;
NameAndType	receive:()Ljava/lang/Object;
Method	scala/concurrent/MailBox$Receiver.receive:()Ljava/lang/Object;
Asciz	<A:Ljava/lang/Object;>(Lscala/PartialFunction<Ljava/lang/Object;TA;>;)TA;;
Asciz	send;
Asciz	(Ljava/lang/Object;)V;
NameAndType	receivers:()Ljava/lang/Object;
Method	scala/concurrent/MailBox.receivers:()Ljava/lang/Object;
Asciz	scala/concurrent/MailBox$$anonfun$send$1;
class	scala/concurrent/MailBox$$anonfun$send$1
Asciz	(Lscala/concurrent/MailBox;Ljava/lang/Object;)V;
NameAndType	"<init>":(Lscala/concurrent/MailBox;Ljava/lang/Object;)V
Method	scala/concurrent/MailBox$$anonfun$send$1."<init>":(Lscala/concurrent/MailBox;Ljava/lang/Object;)V
Asciz	extractFirst;
Asciz	(Ljava/lang/Object;Lscala/Function1;)Lscala/Option;;
NameAndType	extractFirst:(Ljava/lang/Object;Lscala/Function1;)Lscala/Option;
InterfaceMethod	scala/concurrent/QueueModule.extractFirst:(Ljava/lang/Object;Lscala/Function1;)Lscala/Option;
Asciz	scala/None$;
class	scala/None$
Asciz	MODULE$;
Asciz	Lscala/None$;;
NameAndType	MODULE$:Lscala/None$;
Field	scala/None$.MODULE$:Lscala/None$;
Asciz	equals;
Asciz	(Ljava/lang/Object;)Z;
NameAndType	equals:(Ljava/lang/Object;)Z
Method	java/lang/Object.equals:(Ljava/lang/Object;)Z
NameAndType	sent:()Ljava/lang/Object;
Method	scala/concurrent/MailBox.sent:()Ljava/lang/Object;
Asciz	append;
Asciz	(Ljava/lang/Object;Ljava/lang/Object;)Ljava/lang/Object;;
NameAndType	append:(Ljava/lang/Object;Ljava/lang/Object;)Ljava/lang/Object;
InterfaceMethod	scala/concurrent/QueueModule.append:(Ljava/lang/Object;Ljava/lang/Object;)Ljava/lang/Object;
Asciz	sent_$eq;
NameAndType	sent_$eq:(Ljava/lang/Object;)V
Method	scala/concurrent/MailBox.sent_$eq:(Ljava/lang/Object;)V
Asciz	scala/MatchError;
class	scala/MatchError
Asciz	scala/Option;
class	scala/Option
Asciz	toString;
Asciz	()Ljava/lang/String;;
NameAndType	toString:()Ljava/lang/String;
Method	scala/Option.toString:()Ljava/lang/String;
Asciz	(Ljava/lang/String;)V;
NameAndType	"<init>":(Ljava/lang/String;)V
Method	scala/MatchError."<init>":(Ljava/lang/String;)V
Asciz	scala/Some;
class	scala/Some
Asciz	x;
NameAndType	x:Ljava/lang/Object;
Field	scala/Some.x:Ljava/lang/Object;
Asciz	scala/Tuple2;
class	scala/Tuple2
Asciz	_1;
NameAndType	_1:()Ljava/lang/Object;
Method	scala/Tuple2._1:()Ljava/lang/Object;
Asciz	scala/concurrent/MailBox$PreReceiver;
class	scala/concurrent/MailBox$PreReceiver
Asciz	_2;
NameAndType	_2:()Ljava/lang/Object;
Method	scala/Tuple2._2:()Ljava/lang/Object;
Asciz	receivers_$eq;
NameAndType	receivers_$eq:(Ljava/lang/Object;)V
Method	scala/concurrent/MailBox.receivers_$eq:(Ljava/lang/Object;)V
Asciz	msg_$eq;
NameAndType	msg_$eq:(Ljava/lang/Object;)V
Method	scala/concurrent/MailBox$PreReceiver.msg_$eq:(Ljava/lang/Object;)V
Asciz	notify;
NameAndType	notify:()V
Method	scala/concurrent/MailBox$PreReceiver.notify:()V
Asciz	msg$1;
Asciz	temp9;
Asciz	Lscala/Some;;
Asciz	temp10;
Asciz	Lscala/Tuple2;;
Asciz	temp12;
Asciz	temp7;
Asciz	Lscala/Option;;
Asciz	temp11;
Asciz	Lscala/concurrent/MailBox$PreReceiver;;
Asciz	scala/concurrent/MailBox$$anonfun$scanSentMsgs$1;
class	scala/concurrent/MailBox$$anonfun$scanSentMsgs$1
Asciz	(Lscala/concurrent/MailBox;Lscala/concurrent/MailBox$Receiver;)V;
NameAndType	"<init>":(Lscala/concurrent/MailBox;Lscala/concurrent/MailBox$Receiver;)V
Method	scala/concurrent/MailBox$$anonfun$scanSentMsgs$1."<init>":(Lscala/concurrent/MailBox;Lscala/concurrent/MailBox$Receiver;)V
Method	scala/concurrent/MailBox$Receiver.msg_$eq:(Ljava/lang/Object;)V
Asciz	receiver$1;
Asciz	temp3;
Asciz	temp4;
Asciz	temp6;
Asciz	temp5;
Asciz	temp1;
Asciz	<A:Ljava/lang/Object;>(Lscala/concurrent/MailBox$Receiver<TA;>;)V;
Asciz	()Lscala/concurrent/QueueModule<Lscala/concurrent/MailBox$PreReceiver;>;;
Asciz	()Lscala/concurrent/QueueModule<Ljava/lang/Object;>;;
Asciz	(Lscala/concurrent/ListQueueCreator;)Lscala/concurrent/QueueModule;;
NameAndType	queueCreate:(Lscala/concurrent/ListQueueCreator;)Lscala/concurrent/QueueModule;
Method	scala/concurrent/ListQueueCreator$class.queueCreate:(Lscala/concurrent/ListQueueCreator;)Lscala/concurrent/QueueModule;
Asciz	ScalaSig;
Asciz	InnerClasses;
Asciz	Receiver;
Asciz	PreReceiver;
Asciz	$anonfun$send$1;
Asciz	$anonfun$scanSentMsgs$1;
Asciz	scala/ScalaObject;
class	scala/ScalaObject

{
private java.lang.Object receivers;
  Signature: Ljava/lang/Object;
  Signature: length = 0x2
   00 04 

private java.lang.Object sent;
  Signature: Ljava/lang/Object;
  Signature: length = 0x2
   00 04 

private final scala.concurrent.QueueModule receiverQueue;
  Signature: Lscala/concurrent/QueueModule;
  Signature: length = 0x2
   00 09 

private final scala.concurrent.QueueModule messageQueue;
  Signature: Lscala/concurrent/QueueModule;
  Signature: length = 0x2
   00 0B 

public scala.concurrent.MailBox();
  Signature: ()V
  Code:
   Stack=2, Locals=1, Args_size=1
	aload_0
	invokespecial	Method java/lang/Object."<init>":()V
	aload_0
	invokestatic	Method scala/concurrent/ListQueueCreator$class.$init$:(Lscala/concurrent/ListQueueCreator;)V
	aload_0
	aload_0
	invokeinterface	InterfaceMethod scala/concurrent/ListQueueCreator.queueCreate:()Lscala/concurrent/QueueModule;
	putfield	Field messageQueue:Lscala/concurrent/QueueModule;
	aload_0
	aload_0
	invokeinterface	InterfaceMethod scala/concurrent/ListQueueCreator.queueCreate:()Lscala/concurrent/QueueModule;
	putfield	Field receiverQueue:Lscala/concurrent/QueueModule;
	aload_0
	aload_0
	invokespecial	Method messageQueue:()Lscala/concurrent/QueueModule;
	invokeinterface	InterfaceMethod scala/concurrent/QueueModule.make:()Ljava/lang/Object;
	putfield	Field sent:Ljava/lang/Object;
	aload_0
	aload_0
	invokespecial	Method receiverQueue:()Lscala/concurrent/QueueModule;
	invokeinterface	InterfaceMethod scala/concurrent/QueueModule.make:()Ljava/lang/Object;
	putfield	Field receivers:Ljava/lang/Object;
	return
  Labels:

public java.lang.Object receiveWithin(long, scala.PartialFunction);
  Signature: (JLscala/PartialFunction;)Ljava/lang/Object;
  Code:
   Stack=4, Locals=5, Args_size=3
	new	class scala/concurrent/MailBox$Receiver
	dup
	aload_0
	aload_3
	invokespecial	Method scala/concurrent/MailBox$Receiver."<init>":(Lscala/concurrent/MailBox;Lscala/PartialFunction;)V
	astore	4
	aload_0
	aload	4
	invokespecial	Method scanSentMsgs:(Lscala/concurrent/MailBox$Receiver;)V
	aload	4
	lload_1
	invokevirtual	Method scala/concurrent/MailBox$Receiver.receiveWithin:(J)Ljava/lang/Object;
	areturn
  Labels:
  LocalVariableTable: 
   Start  Length  Slot  Name   Signature
   0      24      0    this       Lscala/concurrent/MailBox;
   0      24      1    msec       J
   0      24      3    f       Lscala/PartialFunction;
   11      12      4    r       Lscala/concurrent/MailBox$Receiver;

  Signature: length = 0x2
   00 4B 

public java.lang.Object receive(scala.PartialFunction);
  Signature: (Lscala/PartialFunction;)Ljava/lang/Object;
  Code:
   Stack=4, Locals=3, Args_size=2
	new	class scala/concurrent/MailBox$Receiver
	dup
	aload_0
	aload_1
	invokespecial	Method scala/concurrent/MailBox$Receiver."<init>":(Lscala/concurrent/MailBox;Lscala/PartialFunction;)V
	astore_2
	aload_0
	aload_2
	invokespecial	Method scanSentMsgs:(Lscala/concurrent/MailBox$Receiver;)V
	aload_2
	invokevirtual	Method scala/concurrent/MailBox$Receiver.receive:()Ljava/lang/Object;
	areturn
  Labels:
  LocalVariableTable: 
   Start  Length  Slot  Name   Signature
   0      20      0    this       Lscala/concurrent/MailBox;
   0      20      1    f       Lscala/PartialFunction;
   10      9      2    r       Lscala/concurrent/MailBox$Receiver;

  Signature: length = 0x2
   00 50 

public void send(java.lang.Object);
  Signature: (Ljava/lang/Object;)V
  Code:
   Stack=6, Locals=7, Args_size=2
	aload_0
	dup
	pop
	monitorenter
	aload_0
	invokespecial	Method receiverQueue:()Lscala/concurrent/QueueModule;
	aload_0
	invokespecial	Method receivers:()Ljava/lang/Object;
	new	class scala/concurrent/MailBox$$anonfun$send$1
	dup
	aload_0
	aload_1
	invokespecial	Method scala/concurrent/MailBox$$anonfun$send$1."<init>":(Lscala/concurrent/MailBox;Ljava/lang/Object;)V
	invokeinterface	InterfaceMethod scala/concurrent/QueueModule.extractFirst:(Ljava/lang/Object;Lscala/Function1;)Lscala/Option;
	astore	5
	getstatic	Field scala/None$.MODULE$:Lscala/None$;
	dup
	ifnonnull	l1 // aload
	pop
	aload	5
	ifnull	l2 // iconst_1
	goto	l3 // aload
l1	aload	5
	invokevirtual	Method java/lang/Object.equals:(Ljava/lang/Object;)Z
	ifeq	l3 // aload
l2	iconst_1
	ifeq	l4 // new
	aload_0
	aload_0
	invokespecial	Method messageQueue:()Lscala/concurrent/QueueModule;
	aload_0
	invokespecial	Method sent:()Ljava/lang/Object;
	aload_1
	invokeinterface	InterfaceMethod scala/concurrent/QueueModule.append:(Ljava/lang/Object;Ljava/lang/Object;)Ljava/lang/Object;
	invokespecial	Method sent_$eq:(Ljava/lang/Object;)V
	goto	l5 // aload_0
l4	new	class scala/MatchError
	dup
	aload	5
	invokevirtual	Method scala/Option.toString:()Ljava/lang/String;
	invokespecial	Method scala/MatchError."<init>":(Ljava/lang/String;)V
	athrow
l3	aload	5
	instanceof	class scala/Some
	ifeq	l6 // new
	aload	5
	checkcast	class scala/Some
	astore_2
	aload_2
	getfield	Field scala/Some.x:Ljava/lang/Object;
	checkcast	class scala/Tuple2
	astore_3
	aload_3
	ifnull	l7 // new
	aload_3
	invokevirtual	Method scala/Tuple2._1:()Ljava/lang/Object;
	checkcast	class scala/concurrent/MailBox$PreReceiver
	astore	6
	aload_3
	invokevirtual	Method scala/Tuple2._2:()Ljava/lang/Object;
	astore	4
	iconst_1
	ifeq	l8 // new
	aload_0
	aload	4
	invokespecial	Method receivers_$eq:(Ljava/lang/Object;)V
	aload	6
	aload_1
	invokevirtual	Method scala/concurrent/MailBox$PreReceiver.msg_$eq:(Ljava/lang/Object;)V
	aload	6
	dup
	pop
	monitorenter
	aload	6
	invokevirtual	Method scala/concurrent/MailBox$PreReceiver.notify:()V
	aload	6
	monitorexit
l5	aload_0
	monitorexit
	return
l8	new	class scala/MatchError
	dup
	aload	5
	invokevirtual	Method scala/Option.toString:()Ljava/lang/String;
	invokespecial	Method scala/MatchError."<init>":(Ljava/lang/String;)V
	athrow
l7	new	class scala/MatchError
	dup
	aload	5
	invokevirtual	Method scala/Option.toString:()Ljava/lang/String;
	invokespecial	Method scala/MatchError."<init>":(Ljava/lang/String;)V
	athrow
l6	new	class scala/MatchError
	dup
	aload	5
	invokevirtual	Method scala/Option.toString:()Ljava/lang/String;
	invokespecial	Method scala/MatchError."<init>":(Ljava/lang/String;)V
	athrow
	aload	6
	monitorexit
	athrow
	aload_0
	monitorexit
	athrow
  Labels:
   	l1 = 44 // aload
   	l2 = 52 // iconst_1
   	l4 = 77 // new
   	l3 = 90 // aload
   	l5 = 160 // aload_0
   	l8 = 163 // new
   	l7 = 176 // new
   	l6 = 189 // new
  Exception table:
   from   to  target type
   152   160   202   any
     4   162   206   any
   163   206   206   any
  LocalVariableTable: 
   Start  Length  Slot  Name   Signature
   0      209      0    this       Lscala/concurrent/MailBox;
   0      209      1    msg$1       Ljava/lang/Object;
   104      56      2    temp9       Lscala/Some;
   163      26      2    temp9       Lscala/Some;
   202      4      2    temp9       Lscala/Some;
   112      48      3    temp10       Lscala/Tuple2;
   163      26      3    temp10       Lscala/Tuple2;
   202      4      3    temp10       Lscala/Tuple2;
   131      29      4    temp12       Ljava/lang/Object;
   163      13      4    temp12       Ljava/lang/Object;
   202      4      4    temp12       Ljava/lang/Object;
   28      132      5    temp7       Lscala/Option;
   163      43      5    temp7       Lscala/Option;
   125      35      6    temp11       Lscala/concurrent/MailBox$PreReceiver;
   163      13      6    temp11       Lscala/concurrent/MailBox$PreReceiver;
   202      4      6    temp11       Lscala/concurrent/MailBox$PreReceiver;


private void scanSentMsgs(scala.concurrent.MailBox$Receiver);
  Signature: (Lscala/concurrent/MailBox$Receiver;)V
  Code:
   Stack=6, Locals=7, Args_size=2
	aload_0
	dup
	pop
	monitorenter
	aload_0
	invokespecial	Method messageQueue:()Lscala/concurrent/QueueModule;
	aload_0
	invokespecial	Method sent:()Ljava/lang/Object;
	new	class scala/concurrent/MailBox$$anonfun$scanSentMsgs$1
	dup
	aload_0
	aload_1
	invokespecial	Method scala/concurrent/MailBox$$anonfun$scanSentMsgs$1."<init>":(Lscala/concurrent/MailBox;Lscala/concurrent/MailBox$Receiver;)V
	invokeinterface	InterfaceMethod scala/concurrent/QueueModule.extractFirst:(Ljava/lang/Object;Lscala/Function1;)Lscala/Option;
	astore	6
	getstatic	Field scala/None$.MODULE$:Lscala/None$;
	dup
	ifnonnull	l1 // aload
	pop
	aload	6
	ifnull	l2 // iconst_1
	goto	l3 // aload
l1	aload	6
	invokevirtual	Method java/lang/Object.equals:(Ljava/lang/Object;)Z
	ifeq	l3 // aload
l2	iconst_1
	ifeq	l4 // new
	aload_0
	aload_0
	invokespecial	Method receiverQueue:()Lscala/concurrent/QueueModule;
	aload_0
	invokespecial	Method receivers:()Ljava/lang/Object;
	aload_1
	invokeinterface	InterfaceMethod scala/concurrent/QueueModule.append:(Ljava/lang/Object;Ljava/lang/Object;)Ljava/lang/Object;
	invokespecial	Method receivers_$eq:(Ljava/lang/Object;)V
	goto	l5 // aload_0
l4	new	class scala/MatchError
	dup
	aload	6
	invokevirtual	Method scala/Option.toString:()Ljava/lang/String;
	invokespecial	Method scala/MatchError."<init>":(Ljava/lang/String;)V
	athrow
l3	aload	6
	instanceof	class scala/Some
	ifeq	l6 // new
	aload	6
	checkcast	class scala/Some
	astore_2
	aload_2
	getfield	Field scala/Some.x:Ljava/lang/Object;
	checkcast	class scala/Tuple2
	astore_3
	aload_3
	ifnull	l7 // new
	aload_3
	invokevirtual	Method scala/Tuple2._1:()Ljava/lang/Object;
	astore	5
	aload_3
	invokevirtual	Method scala/Tuple2._2:()Ljava/lang/Object;
	astore	4
	iconst_1
	ifeq	l8 // new
	aload_0
	aload	4
	invokespecial	Method sent_$eq:(Ljava/lang/Object;)V
	aload_1
	aload	5
	invokevirtual	Method scala/concurrent/MailBox$Receiver.msg_$eq:(Ljava/lang/Object;)V
l5	aload_0
	monitorexit
	return
l8	new	class scala/MatchError
	dup
	aload	6
	invokevirtual	Method scala/Option.toString:()Ljava/lang/String;
	invokespecial	Method scala/MatchError."<init>":(Ljava/lang/String;)V
	athrow
l7	new	class scala/MatchError
	dup
	aload	6
	invokevirtual	Method scala/Option.toString:()Ljava/lang/String;
	invokespecial	Method scala/MatchError."<init>":(Ljava/lang/String;)V
	athrow
l6	new	class scala/MatchError
	dup
	aload	6
	invokevirtual	Method scala/Option.toString:()Ljava/lang/String;
	invokespecial	Method scala/MatchError."<init>":(Ljava/lang/String;)V
	athrow
	aload_0
	monitorexit
	athrow
  Labels:
   	l1 = 44 // aload
   	l2 = 52 // iconst_1
   	l4 = 77 // new
   	l3 = 90 // aload
   	l5 = 144 // aload_0
   	l8 = 147 // new
   	l7 = 160 // new
   	l6 = 173 // new
  Exception table:
   from   to  target type
     4   146   186   any
   147   186   186   any
  LocalVariableTable: 
   Start  Length  Slot  Name   Signature
   0      189      0    this       Lscala/concurrent/MailBox;
   0      189      1    receiver$1       Lscala/concurrent/MailBox$Receiver;
   104      40      2    temp3       Lscala/Some;
   147      26      2    temp3       Lscala/Some;
   112      32      3    temp4       Lscala/Tuple2;
   147      26      3    temp4       Lscala/Tuple2;
   128      16      4    temp6       Ljava/lang/Object;
   147      13      4    temp6       Ljava/lang/Object;
   122      22      5    temp5       Ljava/lang/Object;
   147      13      5    temp5       Ljava/lang/Object;
   28      116      6    temp1       Lscala/Option;
   147      39      6    temp1       Lscala/Option;

  Signature: length = 0x2
   00 FFFFFFAA 

private void receivers_$eq(java.lang.Object);
  Signature: (Ljava/lang/Object;)V
  Code:
   Stack=2, Locals=2, Args_size=2
	aload_0
	aload_1
	putfield	Field receivers:Ljava/lang/Object;
	return
  Labels:
  Signature: length = 0x2
   00 52 

private java.lang.Object receivers();
  Signature: ()Ljava/lang/Object;
  Code:
   Stack=1, Locals=1, Args_size=1
	aload_0
	getfield	Field receivers:Ljava/lang/Object;
	areturn
  Labels:
  Signature: length = 0x2
   00 2B 

private void sent_$eq(java.lang.Object);
  Signature: (Ljava/lang/Object;)V
  Code:
   Stack=2, Locals=2, Args_size=2
	aload_0
	aload_1
	putfield	Field sent:Ljava/lang/Object;
	return
  Labels:
  Signature: length = 0x2
   00 52 

private java.lang.Object sent();
  Signature: ()Ljava/lang/Object;
  Code:
   Stack=1, Locals=1, Args_size=1
	aload_0
	getfield	Field sent:Ljava/lang/Object;
	areturn
  Labels:
  Signature: length = 0x2
   00 2B 

private scala.concurrent.QueueModule receiverQueue();
  Signature: ()Lscala/concurrent/QueueModule;
  Code:
   Stack=1, Locals=1, Args_size=1
	aload_0
	getfield	Field receiverQueue:Lscala/concurrent/QueueModule;
	areturn
  Labels:
  Signature: length = 0x2
   00 FFFFFFAB 

private scala.concurrent.QueueModule messageQueue();
  Signature: ()Lscala/concurrent/QueueModule;
  Code:
   Stack=1, Locals=1, Args_size=1
	aload_0
	getfield	Field messageQueue:Lscala/concurrent/QueueModule;
	areturn
  Labels:
  Signature: length = 0x2
   00 FFFFFFAC 

public scala.concurrent.QueueModule queueCreate();
  Signature: ()Lscala/concurrent/QueueModule;
  Code:
   Stack=1, Locals=1, Args_size=1
	aload_0
	invokestatic	Method scala/concurrent/ListQueueCreator$class.queueCreate:(Lscala/concurrent/ListQueueCreator;)Lscala/concurrent/QueueModule;
	areturn
  Labels:

}

