Compiled from "MailBox.scala"
public final class scala.concurrent.MailBox$$anonfun$send$1 extends scala.runtime.AbstractFunction1 implements java.io.Serializable
  SourceFile: "MailBox.scala"
  Scala: length = 0x
   
  InnerClass: 
   public abstract PreReceiver=class scala/concurrent/MailBox$PreReceiver of class scala/concurrent/MailBox
   public final $anonfun$send$1=class scala/concurrent/MailBox$$anonfun$send$1 of class scala/concurrent/MailBox
  minor version: 0
  major version: 49
  Constant pool:
Asciz	SourceFile;
Asciz	MailBox.scala;
Asciz	<clinit>;
Asciz	()V;
Asciz	Code;
Asciz	serialVersionUID;
Asciz	J;
Asciz	scala/concurrent/MailBox$$anonfun$send$1;
class	scala/concurrent/MailBox$$anonfun$send$1
NameAndType	serialVersionUID:J
Field	scala/concurrent/MailBox$$anonfun$send$1.serialVersionUID:J
Asciz	msg$1;
Asciz	Ljava/lang/Object;;
Asciz	apply;
Asciz	(Lscala/concurrent/MailBox$PreReceiver;)Z;
Asciz	LineNumberTable;
NameAndType	msg$1:Ljava/lang/Object;
Field	scala/concurrent/MailBox$$anonfun$send$1.msg$1:Ljava/lang/Object;
Asciz	scala/concurrent/MailBox$PreReceiver;
class	scala/concurrent/MailBox$PreReceiver
Asciz	isDefinedAt;
Asciz	(Ljava/lang/Object;)Z;
NameAndType	isDefinedAt:(Ljava/lang/Object;)Z
Method	scala/concurrent/MailBox$PreReceiver.isDefinedAt:(Ljava/lang/Object;)Z
Asciz	this;
Asciz	Lscala/concurrent/MailBox$$anonfun$send$1;;
Asciz	r;
Asciz	Lscala/concurrent/MailBox$PreReceiver;;
Asciz	LocalVariableTable;
Asciz	(Ljava/lang/Object;)Ljava/lang/Object;;
NameAndType	apply:(Lscala/concurrent/MailBox$PreReceiver;)Z
Method	scala/concurrent/MailBox$$anonfun$send$1.apply:(Lscala/concurrent/MailBox$PreReceiver;)Z
Asciz	scala/runtime/BoxesRunTime;
class	scala/runtime/BoxesRunTime
Asciz	boxToBoolean;
Asciz	(Z)Ljava/lang/Boolean;;
NameAndType	boxToBoolean:(Z)Ljava/lang/Boolean;
Method	scala/runtime/BoxesRunTime.boxToBoolean:(Z)Ljava/lang/Boolean;
Asciz	v1;
Asciz	<init>;
Asciz	(Lscala/concurrent/MailBox;Ljava/lang/Object;)V;
Asciz	scala/runtime/AbstractFunction1;
class	scala/runtime/AbstractFunction1
NameAndType	"<init>":()V
Method	scala/runtime/AbstractFunction1."<init>":()V
Asciz	$outer;
Asciz	Lscala/concurrent/MailBox;;
Asciz	Scala;
Asciz	InnerClasses;
Asciz	scala/concurrent/MailBox;
class	scala/concurrent/MailBox
Asciz	PreReceiver;
Asciz	$anonfun$send$1;
Asciz	java/io/Serializable;
class	java/io/Serializable

{
public static final long serialVersionUID;
  Signature: J

public final java.lang.Object msg$1;
  Signature: Ljava/lang/Object;

public static {};
  Signature: ()V
  Code:
   Stack=2, Locals=0, Args_size=0
	lconst_0
	putstatic	Field serialVersionUID:J
	return
  Labels:

public final boolean apply(scala.concurrent.MailBox$PreReceiver);
  Signature: (Lscala/concurrent/MailBox$PreReceiver;)Z
  Code:
   Stack=2, Locals=2, Args_size=2
	aload_1
	aload_0
	getfield	Field msg$1:Ljava/lang/Object;
	invokevirtual	Method scala/concurrent/MailBox$PreReceiver.isDefinedAt:(Ljava/lang/Object;)Z
	ireturn
  Labels:
  LocalVariableTable: 
   Start  Length  Slot  Name   Signature
   0      9      0    this       Lscala/concurrent/MailBox$$anonfun$send$1;
   0      9      1    r       Lscala/concurrent/MailBox$PreReceiver;


public final java.lang.Object apply(java.lang.Object);
  Signature: (Ljava/lang/Object;)Ljava/lang/Object;
  Code:
   Stack=2, Locals=3, Args_size=2
	aload_0
	aload_1
	checkcast	class scala/concurrent/MailBox$PreReceiver
	invokevirtual	Method apply:(Lscala/concurrent/MailBox$PreReceiver;)Z
	istore_2
	iload_2
	invokestatic	Method scala/runtime/BoxesRunTime.boxToBoolean:(Z)Ljava/lang/Boolean;
	areturn
  Labels:
  LocalVariableTable: 
   Start  Length  Slot  Name   Signature
   0      14      0    this       Lscala/concurrent/MailBox$$anonfun$send$1;
   0      14      1    v1       Ljava/lang/Object;


public scala.concurrent.MailBox$$anonfun$send$1(scala.concurrent.MailBox, java.lang.Object);
  Signature: (Lscala/concurrent/MailBox;Ljava/lang/Object;)V
  Code:
   Stack=2, Locals=3, Args_size=3
	aload_0
	aload_2
	putfield	Field msg$1:Ljava/lang/Object;
	aload_0
	invokespecial	Method scala/runtime/AbstractFunction1."<init>":()V
	return
  Labels:
  LocalVariableTable: 
   Start  Length  Slot  Name   Signature
   0      10      0    this       Lscala/concurrent/MailBox$$anonfun$send$1;
   0      10      1    $outer       Lscala/concurrent/MailBox;


}

