Compiled from "ops.scala"
public final class scala.concurrent.ops$$anonfun$par$1 extends scala.runtime.AbstractFunction0 implements java.io.Serializable
  SourceFile: "ops.scala"
  Scala: length = 0x
   
  InnerClass: 
   public Catch=class scala/util/control/Exception$Catch of class scala/util/control/Exception
   public final $anonfun$par$1=class scala/concurrent/ops$$anonfun$par$1 of class scala/concurrent/ops
   public abstract Described=class scala/util/control/Exception$Described of class scala/util/control/Exception
   public final $anonfun$allCatch$1=class scala/util/control/Exception$$anonfun$allCatch$1 of class scala/util/control/Exception
  minor version: 0
  major version: 49
  Constant pool:
Asciz	SourceFile;
Asciz	ops.scala;
Asciz	<clinit>;
Asciz	()V;
Asciz	Code;
Asciz	serialVersionUID;
Asciz	J;
Asciz	scala/concurrent/ops$$anonfun$par$1;
class	scala/concurrent/ops$$anonfun$par$1
NameAndType	serialVersionUID:J
Field	scala/concurrent/ops$$anonfun$par$1.serialVersionUID:J
Asciz	y$1;
Asciz	Lscala/concurrent/SyncVar;;
Asciz	yp$1;
Asciz	Lscala/Function0;;
Asciz	<init>;
Asciz	(Lscala/Function0;Lscala/concurrent/SyncVar;)V;
Asciz	LineNumberTable;
NameAndType	yp$1:Lscala/Function0;
Field	scala/concurrent/ops$$anonfun$par$1.yp$1:Lscala/Function0;
NameAndType	y$1:Lscala/concurrent/SyncVar;
Field	scala/concurrent/ops$$anonfun$par$1.y$1:Lscala/concurrent/SyncVar;
Asciz	scala/runtime/AbstractFunction0;
class	scala/runtime/AbstractFunction0
NameAndType	"<init>":()V
Method	scala/runtime/AbstractFunction0."<init>":()V
Asciz	apply;
Asciz	()Ljava/lang/Object;;
NameAndType	apply:()V
Method	scala/concurrent/ops$$anonfun$par$1.apply:()V
Asciz	scala/runtime/BoxedUnit;
class	scala/runtime/BoxedUnit
Asciz	UNIT;
Asciz	Lscala/runtime/BoxedUnit;;
NameAndType	UNIT:Lscala/runtime/BoxedUnit;
Field	scala/runtime/BoxedUnit.UNIT:Lscala/runtime/BoxedUnit;
Asciz	scala/util/control/Exception$Catch;
class	scala/util/control/Exception$Catch
Asciz	scala/util/control/Exception$$anonfun$allCatch$1;
class	scala/util/control/Exception$$anonfun$allCatch$1
Method	scala/util/control/Exception$$anonfun$allCatch$1."<init>":()V
Asciz	(Lscala/PartialFunction;)V;
NameAndType	"<init>":(Lscala/PartialFunction;)V
Method	scala/util/control/Exception$Catch."<init>":(Lscala/PartialFunction;)V
Asciz	<everything>;
String	<everything>
Asciz	scala/util/control/Exception$Described;
class	scala/util/control/Exception$Described
Asciz	withDesc;
Asciz	(Ljava/lang/String;)Lscala/util/control/Exception$Described;;
NameAndType	withDesc:(Ljava/lang/String;)Lscala/util/control/Exception$Described;
InterfaceMethod	scala/util/control/Exception$Described.withDesc:(Ljava/lang/String;)Lscala/util/control/Exception$Described;
Asciz	either;
Asciz	(Lscala/Function0;)Lscala/Either;;
NameAndType	either:(Lscala/Function0;)Lscala/Either;
Method	scala/util/control/Exception$Catch.either:(Lscala/Function0;)Lscala/Either;
Asciz	scala/concurrent/SyncVar;
class	scala/concurrent/SyncVar
Asciz	set;
Asciz	(Ljava/lang/Object;)V;
NameAndType	set:(Ljava/lang/Object;)V
Method	scala/concurrent/SyncVar.set:(Ljava/lang/Object;)V
Asciz	this;
Asciz	Lscala/concurrent/ops$$anonfun$par$1;;
Asciz	LocalVariableTable;
Asciz	Scala;
Asciz	InnerClasses;
Asciz	scala/util/control/Exception;
class	scala/util/control/Exception
Asciz	Catch;
Asciz	scala/concurrent/ops;
class	scala/concurrent/ops
Asciz	$anonfun$par$1;
Asciz	Described;
Asciz	$anonfun$allCatch$1;
Asciz	java/io/Serializable;
class	java/io/Serializable

{
public static final long serialVersionUID;
  Signature: J

public final scala.concurrent.SyncVar y$1;
  Signature: Lscala/concurrent/SyncVar;

public final scala.Function0 yp$1;
  Signature: Lscala/Function0;

public static {};
  Signature: ()V
  Code:
   Stack=2, Locals=0, Args_size=0
	lconst_0
	putstatic	Field serialVersionUID:J
	return
  Labels:

public scala.concurrent.ops$$anonfun$par$1(scala.Function0, scala.concurrent.SyncVar);
  Signature: (Lscala/Function0;Lscala/concurrent/SyncVar;)V
  Code:
   Stack=2, Locals=3, Args_size=3
	aload_0
	aload_1
	putfield	Field yp$1:Lscala/Function0;
	aload_0
	aload_2
	putfield	Field y$1:Lscala/concurrent/SyncVar;
	aload_0
	invokespecial	Method scala/runtime/AbstractFunction0."<init>":()V
	return
  Labels:

public final java.lang.Object apply();
  Signature: ()Ljava/lang/Object;
  Code:
   Stack=1, Locals=1, Args_size=1
	aload_0
	invokevirtual	Method apply:()V
	getstatic	Field scala/runtime/BoxedUnit.UNIT:Lscala/runtime/BoxedUnit;
	areturn
  Labels:

public final void apply();
  Signature: ()V
  Code:
   Stack=5, Locals=2, Args_size=1
	aload_0
	getfield	Field y$1:Lscala/concurrent/SyncVar;
	aload_0
	getfield	Field yp$1:Lscala/Function0;
	astore_1
	new	class scala/util/control/Exception$Catch
	dup
	new	class scala/util/control/Exception$$anonfun$allCatch$1
	dup
	invokespecial	Method scala/util/control/Exception$$anonfun$allCatch$1."<init>":()V
	invokespecial	Method scala/util/control/Exception$Catch."<init>":(Lscala/PartialFunction;)V
	ldc	String <everything>
	invokeinterface	InterfaceMethod scala/util/control/Exception$Described.withDesc:(Ljava/lang/String;)Lscala/util/control/Exception$Described;
	checkcast	class scala/util/control/Exception$Catch
	aload_1
	invokevirtual	Method scala/util/control/Exception$Catch.either:(Lscala/Function0;)Lscala/Either;
	invokevirtual	Method scala/concurrent/SyncVar.set:(Ljava/lang/Object;)V
	return
  Labels:
  LocalVariableTable: 
   Start  Length  Slot  Name   Signature
   0      41      0    this       Lscala/concurrent/ops$$anonfun$par$1;


}

