Compiled from "ops.scala"
public final class scala.concurrent.ops$$anon$1 extends java.lang.Thread
  SourceFile: "ops.scala"
  Scala: length = 0x
   
  InnerClass: 
   public final #29= #10 of #28; //$anon$1=class scala/concurrent/ops$$anon$1 of class scala/concurrent/ops
  minor version: 0
  major version: 49
  Constant pool:
const #1 = Asciz	SourceFile;
const #2 = Asciz	ops.scala;
const #3 = Asciz	p$2;
const #4 = Asciz	Lscala/Function0;;
const #5 = Asciz	<init>;
const #6 = Asciz	(Lscala/Function0;)V;
const #7 = Asciz	Code;
const #8 = Asciz	LineNumberTable;
const #9 = Asciz	scala/concurrent/ops$$anon$1;
const #10 = class	#9;	//  scala/concurrent/ops$$anon$1
const #11 = NameAndType	#3:#4;//  p$2:Lscala/Function0;
const #12 = Field	#10.#11;	//  scala/concurrent/ops$$anon$1.p$2:Lscala/Function0;
const #13 = Asciz	java/lang/Thread;
const #14 = class	#13;	//  java/lang/Thread
const #15 = Asciz	()V;
const #16 = NameAndType	#5:#15;//  "<init>":()V
const #17 = Method	#14.#16;	//  java/lang/Thread."<init>":()V
const #18 = Asciz	run;
const #19 = Asciz	scala/Function0;
const #20 = class	#19;	//  scala/Function0
const #21 = Asciz	apply;
const #22 = Asciz	()Ljava/lang/Object;;
const #23 = NameAndType	#21:#22;//  apply:()Ljava/lang/Object;
const #24 = InterfaceMethod	#20.#23;	//  scala/Function0.apply:()Ljava/lang/Object;
const #25 = Asciz	Scala;
const #26 = Asciz	InnerClasses;
const #27 = Asciz	scala/concurrent/ops;
const #28 = class	#27;	//  scala/concurrent/ops
const #29 = Asciz	$anon$1;

{
public scala.concurrent.ops$$anon$1(scala.Function0);
  Code:
   Stack=2, Locals=2, Args_size=2
   0:	aload_0
   1:	aload_1
   2:	putfield	#12; //Field p$2:Lscala/Function0;
   5:	aload_0
   6:	invokespecial	#17; //Method java/lang/Thread."<init>":()V
   9:	return
  LineNumberTable: 
   line 40: 0


public void run();
  Code:
   Stack=1, Locals=1, Args_size=1
   0:	aload_0
   1:	getfield	#12; //Field p$2:Lscala/Function0;
   4:	invokeinterface	#24,  1; //InterfaceMethod scala/Function0.apply:()Ljava/lang/Object;
   9:	pop
   10:	return
  LineNumberTable: 
   line 40: 0


}

