Compiled from "ops.scala"
public final class scala.concurrent.ops$ extends java.lang.Object implements scala.ScalaObject
  SourceFile: "ops.scala"
  Scala: length = 0x
   
  InnerClass: 
   public final #193= #53 of #192; //$anonfun$2=class scala/concurrent/ops$$anonfun$2 of class scala/concurrent/ops
   public final #194= #95 of #192; //$anonfun$1=class scala/concurrent/ops$$anonfun$1 of class scala/concurrent/ops
   public #197= #179 of #196; //Catch=class scala/util/control/Exception$Catch of class scala/util/control/Exception
   public final #198= #98 of #192; //$anonfun$par$2=class scala/concurrent/ops$$anonfun$par$2 of class scala/concurrent/ops
   public final #199= #90 of #192; //$anonfun$par$1=class scala/concurrent/ops$$anonfun$par$1 of class scala/concurrent/ops
   public final #200= #58 of #192; //$anonfun$replicate$2=class scala/concurrent/ops$$anonfun$replicate$2 of class scala/concurrent/ops
   public final #201= #48 of #192; //$anonfun$replicate$1=class scala/concurrent/ops$$anonfun$replicate$1 of class scala/concurrent/ops
   public final #202= #116 of #192; //$anonfun$getOrThrow$2=class scala/concurrent/ops$$anonfun$getOrThrow$2 of class scala/concurrent/ops
   public final #203= #113 of #192; //$anonfun$getOrThrow$1=class scala/concurrent/ops$$anonfun$getOrThrow$1 of class scala/concurrent/ops
  minor version: 0
  major version: 49
  Constant pool:
const #1 = Asciz	SourceFile;
const #2 = Asciz	ops.scala;
const #3 = Asciz	Scala;
const #4 = Asciz	MODULE$;
const #5 = Asciz	Lscala/concurrent/ops$;;
const #6 = Asciz	<clinit>;
const #7 = Asciz	()V;
const #8 = Asciz	Code;
const #9 = Asciz	scala/concurrent/ops$;
const #10 = class	#9;	//  scala/concurrent/ops$
const #11 = Asciz	<init>;
const #12 = NameAndType	#11:#7;//  "<init>":()V
const #13 = Method	#10.#12;	//  scala/concurrent/ops$."<init>":()V
const #14 = Asciz	defaultRunner;
const #15 = Asciz	Lscala/concurrent/FutureTaskRunner;;
const #16 = Asciz	LineNumberTable;
const #17 = Asciz	java/lang/Object;
const #18 = class	#17;	//  java/lang/Object
const #19 = Method	#18.#12;	//  java/lang/Object."<init>":()V
const #20 = NameAndType	#4:#5;//  MODULE$:Lscala/concurrent/ops$;
const #21 = Field	#10.#20;	//  scala/concurrent/ops$.MODULE$:Lscala/concurrent/ops$;
const #22 = Asciz	scala/concurrent/TaskRunners$;
const #23 = class	#22;	//  scala/concurrent/TaskRunners$
const #24 = Asciz	Lscala/concurrent/TaskRunners$;;
const #25 = NameAndType	#4:#24;//  MODULE$:Lscala/concurrent/TaskRunners$;
const #26 = Field	#23.#25;	//  scala/concurrent/TaskRunners$.MODULE$:Lscala/concurrent/TaskRunners$;
const #27 = Asciz	threadRunner;
const #28 = Asciz	()Lscala/concurrent/FutureTaskRunner;;
const #29 = NameAndType	#27:#28;//  threadRunner:()Lscala/concurrent/FutureTaskRunner;
const #30 = Method	#23.#29;	//  scala/concurrent/TaskRunners$.threadRunner:()Lscala/concurrent/FutureTaskRunner;
const #31 = NameAndType	#14:#15;//  defaultRunner:Lscala/concurrent/FutureTaskRunner;
const #32 = Field	#10.#31;	//  scala/concurrent/ops$.defaultRunner:Lscala/concurrent/FutureTaskRunner;
const #33 = Asciz	replicate;
const #34 = Asciz	(IILscala/Function1;)V;
const #35 = Asciz	scala/runtime/BoxesRunTime;
const #36 = class	#35;	//  scala/runtime/BoxesRunTime
const #37 = Asciz	boxToInteger;
const #38 = Asciz	(I)Ljava/lang/Integer;;
const #39 = NameAndType	#37:#38;//  boxToInteger:(I)Ljava/lang/Integer;
const #40 = Method	#36.#39;	//  scala/runtime/BoxesRunTime.boxToInteger:(I)Ljava/lang/Integer;
const #41 = Asciz	scala/Function1;
const #42 = class	#41;	//  scala/Function1
const #43 = Asciz	apply;
const #44 = Asciz	(Ljava/lang/Object;)Ljava/lang/Object;;
const #45 = NameAndType	#43:#44;//  apply:(Ljava/lang/Object;)Ljava/lang/Object;
const #46 = InterfaceMethod	#42.#45;	//  scala/Function1.apply:(Ljava/lang/Object;)Ljava/lang/Object;
const #47 = Asciz	scala/concurrent/ops$$anonfun$replicate$1;
const #48 = class	#47;	//  scala/concurrent/ops$$anonfun$replicate$1
const #49 = Asciz	(ILscala/Function1;I)V;
const #50 = NameAndType	#11:#49;//  "<init>":(ILscala/Function1;I)V
const #51 = Method	#48.#50;	//  scala/concurrent/ops$$anonfun$replicate$1."<init>":(ILscala/Function1;I)V
const #52 = Asciz	scala/concurrent/ops$$anonfun$2;
const #53 = class	#52;	//  scala/concurrent/ops$$anonfun$2
const #54 = Asciz	(Lscala/Function0;)V;
const #55 = NameAndType	#11:#54;//  "<init>":(Lscala/Function0;)V
const #56 = Method	#53.#55;	//  scala/concurrent/ops$$anonfun$2."<init>":(Lscala/Function0;)V
const #57 = Asciz	scala/concurrent/ops$$anonfun$replicate$2;
const #58 = class	#57;	//  scala/concurrent/ops$$anonfun$replicate$2
const #59 = Method	#58.#55;	//  scala/concurrent/ops$$anonfun$replicate$2."<init>":(Lscala/Function0;)V
const #60 = Asciz	scala/concurrent/TaskRunner;
const #61 = class	#60;	//  scala/concurrent/TaskRunner
const #62 = Asciz	functionAsTask;
const #63 = Asciz	(Lscala/Function0;)Ljava/lang/Object;;
const #64 = NameAndType	#62:#63;//  functionAsTask:(Lscala/Function0;)Ljava/lang/Object;
const #65 = InterfaceMethod	#61.#64;	//  scala/concurrent/TaskRunner.functionAsTask:(Lscala/Function0;)Ljava/lang/Object;
const #66 = Asciz	execute;
const #67 = Asciz	(Ljava/lang/Object;)V;
const #68 = NameAndType	#66:#67;//  execute:(Ljava/lang/Object;)V
const #69 = InterfaceMethod	#61.#68;	//  scala/concurrent/TaskRunner.execute:(Ljava/lang/Object;)V
const #70 = Asciz	this;
const #71 = Asciz	start$1;
const #72 = Asciz	I;
const #73 = Asciz	end;
const #74 = Asciz	p$1;
const #75 = Asciz	Lscala/Function1;;
const #76 = Asciz	x$4$1;
const #77 = Asciz	Lscala/Function0;;
const #78 = Asciz	x$5;
const #79 = Asciz	Lscala/concurrent/TaskRunner;;
const #80 = Asciz	mid$1;
const #81 = Asciz	LocalVariableTable;
const #82 = Asciz	(IILscala/Function1<Ljava/lang/Integer;Ljava/lang/Object;>;)V;
const #83 = Asciz	Signature;
const #84 = Asciz	par;
const #85 = Asciz	(Lscala/Function0;Lscala/Function0;)Lscala/Tuple2;;
const #86 = Asciz	scala/concurrent/SyncVar;
const #87 = class	#86;	//  scala/concurrent/SyncVar
const #88 = Method	#87.#12;	//  scala/concurrent/SyncVar."<init>":()V
const #89 = Asciz	scala/concurrent/ops$$anonfun$par$1;
const #90 = class	#89;	//  scala/concurrent/ops$$anonfun$par$1
const #91 = Asciz	(Lscala/Function0;Lscala/concurrent/SyncVar;)V;
const #92 = NameAndType	#11:#91;//  "<init>":(Lscala/Function0;Lscala/concurrent/SyncVar;)V
const #93 = Method	#90.#92;	//  scala/concurrent/ops$$anonfun$par$1."<init>":(Lscala/Function0;Lscala/concurrent/SyncVar;)V
const #94 = Asciz	scala/concurrent/ops$$anonfun$1;
const #95 = class	#94;	//  scala/concurrent/ops$$anonfun$1
const #96 = Method	#95.#55;	//  scala/concurrent/ops$$anonfun$1."<init>":(Lscala/Function0;)V
const #97 = Asciz	scala/concurrent/ops$$anonfun$par$2;
const #98 = class	#97;	//  scala/concurrent/ops$$anonfun$par$2
const #99 = Method	#98.#55;	//  scala/concurrent/ops$$anonfun$par$2."<init>":(Lscala/Function0;)V
const #100 = Asciz	scala/Tuple2;
const #101 = class	#100;	//  scala/Tuple2
const #102 = Asciz	scala/Function0;
const #103 = class	#102;	//  scala/Function0
const #104 = Asciz	()Ljava/lang/Object;;
const #105 = NameAndType	#43:#104;//  apply:()Ljava/lang/Object;
const #106 = InterfaceMethod	#103.#105;	//  scala/Function0.apply:()Ljava/lang/Object;
const #107 = Asciz	get;
const #108 = NameAndType	#107:#104;//  get:()Ljava/lang/Object;
const #109 = Method	#87.#108;	//  scala/concurrent/SyncVar.get:()Ljava/lang/Object;
const #110 = Asciz	scala/Either;
const #111 = class	#110;	//  scala/Either
const #112 = Asciz	scala/concurrent/ops$$anonfun$getOrThrow$1;
const #113 = class	#112;	//  scala/concurrent/ops$$anonfun$getOrThrow$1
const #114 = Method	#113.#12;	//  scala/concurrent/ops$$anonfun$getOrThrow$1."<init>":()V
const #115 = Asciz	scala/concurrent/ops$$anonfun$getOrThrow$2;
const #116 = class	#115;	//  scala/concurrent/ops$$anonfun$getOrThrow$2
const #117 = Method	#116.#12;	//  scala/concurrent/ops$$anonfun$getOrThrow$2."<init>":()V
const #118 = Asciz	fold;
const #119 = Asciz	(Lscala/Function1;Lscala/Function1;)Ljava/lang/Object;;
const #120 = NameAndType	#118:#119;//  fold:(Lscala/Function1;Lscala/Function1;)Ljava/lang/Object;
const #121 = Method	#111.#120;	//  scala/Either.fold:(Lscala/Function1;Lscala/Function1;)Ljava/lang/Object;
const #122 = Asciz	(Ljava/lang/Object;Ljava/lang/Object;)V;
const #123 = NameAndType	#11:#122;//  "<init>":(Ljava/lang/Object;Ljava/lang/Object;)V
const #124 = Method	#101.#123;	//  scala/Tuple2."<init>":(Ljava/lang/Object;Ljava/lang/Object;)V
const #125 = Asciz	xp;
const #126 = Asciz	yp$1;
const #127 = Asciz	x$2$1;
const #128 = Asciz	x$3;
const #129 = Asciz	y$1;
const #130 = Asciz	Lscala/concurrent/SyncVar;;
const #131 = Asciz	<A:Ljava/lang/Object;B:Ljava/lang/Object;>(Lscala/Function0<TA;>;Lscala/Function0<TB;>;)Lscala/Tuple2<TA;TB;>;;
const #132 = Asciz	future;
const #133 = Asciz	(Lscala/Function0;Lscala/concurrent/FutureTaskRunner;)Lscala/Function0;;
const #134 = Asciz	scala/concurrent/FutureTaskRunner;
const #135 = class	#134;	//  scala/concurrent/FutureTaskRunner
const #136 = Asciz	submit;
const #137 = NameAndType	#136:#44;//  submit:(Ljava/lang/Object;)Ljava/lang/Object;
const #138 = InterfaceMethod	#135.#137;	//  scala/concurrent/FutureTaskRunner.submit:(Ljava/lang/Object;)Ljava/lang/Object;
const #139 = Asciz	futureAsFunction;
const #140 = Asciz	(Ljava/lang/Object;)Lscala/Function0;;
const #141 = NameAndType	#139:#140;//  futureAsFunction:(Ljava/lang/Object;)Lscala/Function0;
const #142 = InterfaceMethod	#135.#141;	//  scala/concurrent/FutureTaskRunner.futureAsFunction:(Ljava/lang/Object;)Lscala/Function0;
const #143 = Asciz	p;
const #144 = Asciz	runner;
const #145 = Asciz	<A:Ljava/lang/Object;>(Lscala/Function0<TA;>;Lscala/concurrent/FutureTaskRunner;)Lscala/Function0<TA;>;;
const #146 = Asciz	spawn;
const #147 = Asciz	(Lscala/Function0;Lscala/concurrent/TaskRunner;)V;
const #148 = Asciz	(Lscala/Function0<Ljava/lang/Object;>;Lscala/concurrent/TaskRunner;)V;
const #149 = Asciz	getOrThrow;
const #150 = Asciz	(Lscala/Either;)Ljava/lang/Object;;
const #151 = Asciz	x;
const #152 = Asciz	Lscala/Either;;
const #153 = Asciz	<T:Ljava/lang/Throwable;A:Ljava/lang/Object;>(Lscala/Either<TT;TA;>;)TA;;
const #154 = Asciz	tryCatchEx;
const #155 = Asciz	(Lscala/Function0;)Lscala/Either;;
const #156 = Asciz	scala/Right;
const #157 = class	#156;	//  scala/Right
const #158 = NameAndType	#11:#67;//  "<init>":(Ljava/lang/Object;)V
const #159 = Method	#157.#158;	//  scala/Right."<init>":(Ljava/lang/Object;)V
const #160 = Asciz	scala/Left;
const #161 = class	#160;	//  scala/Left
const #162 = Method	#161.#158;	//  scala/Left."<init>":(Ljava/lang/Object;)V
const #163 = Asciz	java/lang/Exception;
const #164 = class	#163;	//  java/lang/Exception
const #165 = Asciz	body;
const #166 = Asciz	exceptionResult1;
const #167 = Asciz	<A:Ljava/lang/Object;>(Lscala/Function0<TA;>;)Lscala/Either<Ljava/lang/Exception;TA;>;;
const #168 = Asciz	tryCatch;
const #169 = Asciz	scala/util/control/Exception$;
const #170 = class	#169;	//  scala/util/control/Exception$
const #171 = Asciz	Lscala/util/control/Exception$;;
const #172 = NameAndType	#4:#171;//  MODULE$:Lscala/util/control/Exception$;
const #173 = Field	#170.#172;	//  scala/util/control/Exception$.MODULE$:Lscala/util/control/Exception$;
const #174 = Asciz	allCatch;
const #175 = Asciz	()Lscala/util/control/Exception$Catch;;
const #176 = NameAndType	#174:#175;//  allCatch:()Lscala/util/control/Exception$Catch;
const #177 = Method	#170.#176;	//  scala/util/control/Exception$.allCatch:()Lscala/util/control/Exception$Catch;
const #178 = Asciz	scala/util/control/Exception$Catch;
const #179 = class	#178;	//  scala/util/control/Exception$Catch
const #180 = Asciz	either;
const #181 = NameAndType	#180:#155;//  either:(Lscala/Function0;)Lscala/Either;
const #182 = Method	#179.#181;	//  scala/util/control/Exception$Catch.either:(Lscala/Function0;)Lscala/Either;
const #183 = Asciz	<A:Ljava/lang/Object;>(Lscala/Function0<TA;>;)Lscala/Either<Ljava/lang/Throwable;TA;>;;
const #184 = Asciz	future$default$2;
const #185 = Asciz	(Lscala/Function0;)Lscala/concurrent/FutureTaskRunner;;
const #186 = NameAndType	#14:#28;//  defaultRunner:()Lscala/concurrent/FutureTaskRunner;
const #187 = Method	#10.#186;	//  scala/concurrent/ops$.defaultRunner:()Lscala/concurrent/FutureTaskRunner;
const #188 = Asciz	spawn$default$2;
const #189 = Asciz	(Lscala/Function0;)Lscala/concurrent/TaskRunner;;
const #190 = Asciz	InnerClasses;
const #191 = Asciz	scala/concurrent/ops;
const #192 = class	#191;	//  scala/concurrent/ops
const #193 = Asciz	$anonfun$2;
const #194 = Asciz	$anonfun$1;
const #195 = Asciz	scala/util/control/Exception;
const #196 = class	#195;	//  scala/util/control/Exception
const #197 = Asciz	Catch;
const #198 = Asciz	$anonfun$par$2;
const #199 = Asciz	$anonfun$par$1;
const #200 = Asciz	$anonfun$replicate$2;
const #201 = Asciz	$anonfun$replicate$1;
const #202 = Asciz	$anonfun$getOrThrow$2;
const #203 = Asciz	$anonfun$getOrThrow$1;
const #204 = Asciz	scala/ScalaObject;
const #205 = class	#204;	//  scala/ScalaObject

{
public static final scala.concurrent.ops$ MODULE$;

public static {};
  Code:
   Stack=1, Locals=0, Args_size=0
   0:	new	#10; //class scala/concurrent/ops$
   3:	invokespecial	#13; //Method "<init>":()V
   6:	return

public void replicate(int, int, scala.Function1);
  Code:
   Stack=5, Locals=8, Args_size=4
   0:	iload_1
   1:	iload_2
   2:	if_icmpeq	23
   5:	iload_1
   6:	iconst_1
   7:	iadd
   8:	iload_2
   9:	if_icmpne	24
   12:	aload_3
   13:	iload_1
   14:	invokestatic	#40; //Method scala/runtime/BoxesRunTime.boxToInteger:(I)Ljava/lang/Integer;
   17:	invokeinterface	#46,  2; //InterfaceMethod scala/Function1.apply:(Ljava/lang/Object;)Ljava/lang/Object;
   22:	pop
   23:	return
   24:	iload_1
   25:	iload_2
   26:	iadd
   27:	iconst_2
   28:	idiv
   29:	istore	7
   31:	new	#48; //class scala/concurrent/ops$$anonfun$replicate$1
   34:	dup
   35:	iload_1
   36:	aload_3
   37:	iload	7
   39:	invokespecial	#51; //Method scala/concurrent/ops$$anonfun$replicate$1."<init>":(ILscala/Function1;I)V
   42:	astore	4
   44:	new	#53; //class scala/concurrent/ops$$anonfun$2
   47:	dup
   48:	pop
   49:	aload	4
   51:	invokespecial	#56; //Method scala/concurrent/ops$$anonfun$2."<init>":(Lscala/Function0;)V
   54:	aload_0
   55:	getfield	#32; //Field defaultRunner:Lscala/concurrent/FutureTaskRunner;
   58:	astore	5
   60:	new	#58; //class scala/concurrent/ops$$anonfun$replicate$2
   63:	dup
   64:	aload	4
   66:	invokespecial	#59; //Method scala/concurrent/ops$$anonfun$replicate$2."<init>":(Lscala/Function0;)V
   69:	astore	6
   71:	aload	5
   73:	aload	5
   75:	aload	6
   77:	invokeinterface	#65,  2; //InterfaceMethod scala/concurrent/TaskRunner.functionAsTask:(Lscala/Function0;)Ljava/lang/Object;
   82:	invokeinterface	#69,  2; //InterfaceMethod scala/concurrent/TaskRunner.execute:(Ljava/lang/Object;)V
   87:	iload	7
   89:	istore_1
   90:	goto	0
  LineNumberTable: 
   line 76: 0
   line 78: 5
   line 79: 12
   line 75: 23
   line 81: 24
   line 82: 31
   line 83: 87

  LocalVariableTable: 
   Start  Length  Slot  Name   Signature
   0      93      0    this       Lscala/concurrent/ops$;
   0      93      1    start$1       I
   0      93      2    end       I
   0      93      3    p$1       Lscala/Function1;
   44      43      4    x$4$1       Lscala/Function0;
   60      27      5    x$5       Lscala/concurrent/TaskRunner;
   31      62      7    mid$1       I

  Signature: length = 0x2
   00 52 

public scala.Tuple2 par(scala.Function0, scala.Function0);
  Code:
   Stack=7, Locals=8, Args_size=3
   0:	new	#87; //class scala/concurrent/SyncVar
   3:	dup
   4:	invokespecial	#88; //Method scala/concurrent/SyncVar."<init>":()V
   7:	astore	6
   9:	new	#90; //class scala/concurrent/ops$$anonfun$par$1
   12:	dup
   13:	aload_2
   14:	aload	6
   16:	invokespecial	#93; //Method scala/concurrent/ops$$anonfun$par$1."<init>":(Lscala/Function0;Lscala/concurrent/SyncVar;)V
   19:	astore_3
   20:	new	#95; //class scala/concurrent/ops$$anonfun$1
   23:	dup
   24:	pop
   25:	aload_3
   26:	invokespecial	#96; //Method scala/concurrent/ops$$anonfun$1."<init>":(Lscala/Function0;)V
   29:	aload_0
   30:	getfield	#32; //Field defaultRunner:Lscala/concurrent/FutureTaskRunner;
   33:	astore	4
   35:	new	#98; //class scala/concurrent/ops$$anonfun$par$2
   38:	dup
   39:	aload_3
   40:	invokespecial	#99; //Method scala/concurrent/ops$$anonfun$par$2."<init>":(Lscala/Function0;)V
   43:	astore	5
   45:	aload	4
   47:	aload	4
   49:	aload	5
   51:	invokeinterface	#65,  2; //InterfaceMethod scala/concurrent/TaskRunner.functionAsTask:(Lscala/Function0;)Ljava/lang/Object;
   56:	invokeinterface	#69,  2; //InterfaceMethod scala/concurrent/TaskRunner.execute:(Ljava/lang/Object;)V
   61:	new	#101; //class scala/Tuple2
   64:	dup
   65:	aload_1
   66:	invokeinterface	#106,  1; //InterfaceMethod scala/Function0.apply:()Ljava/lang/Object;
   71:	aload	6
   73:	invokevirtual	#109; //Method scala/concurrent/SyncVar.get:()Ljava/lang/Object;
   76:	checkcast	#111; //class scala/Either
   79:	astore	7
   81:	aload	7
   83:	new	#113; //class scala/concurrent/ops$$anonfun$getOrThrow$1
   86:	dup
   87:	invokespecial	#114; //Method scala/concurrent/ops$$anonfun$getOrThrow$1."<init>":()V
   90:	new	#116; //class scala/concurrent/ops$$anonfun$getOrThrow$2
   93:	dup
   94:	invokespecial	#117; //Method scala/concurrent/ops$$anonfun$getOrThrow$2."<init>":()V
   97:	invokevirtual	#121; //Method scala/Either.fold:(Lscala/Function1;Lscala/Function1;)Ljava/lang/Object;
   100:	invokespecial	#124; //Method scala/Tuple2."<init>":(Ljava/lang/Object;Ljava/lang/Object;)V
   103:	areturn
  LineNumberTable: 
   line 65: 0
   line 66: 9
   line 67: 14
   line 66: 16
   line 67: 61

  LocalVariableTable: 
   Start  Length  Slot  Name   Signature
   0      104      0    this       Lscala/concurrent/ops$;
   0      104      1    xp       Lscala/Function0;
   0      104      2    yp$1       Lscala/Function0;
   20      41      3    x$2$1       Lscala/Function0;
   35      26      4    x$3       Lscala/concurrent/TaskRunner;
   9      94      6    y$1       Lscala/concurrent/SyncVar;

  Signature: length = 0x2
   00 FFFFFF83 

public scala.Function0 future(scala.Function0, scala.concurrent.FutureTaskRunner);
  Code:
   Stack=4, Locals=3, Args_size=3
   0:	aload_2
   1:	aload_2
   2:	aload_2
   3:	aload_1
   4:	invokeinterface	#65,  2; //InterfaceMethod scala/concurrent/TaskRunner.functionAsTask:(Lscala/Function0;)Ljava/lang/Object;
   9:	invokeinterface	#138,  2; //InterfaceMethod scala/concurrent/FutureTaskRunner.submit:(Ljava/lang/Object;)Ljava/lang/Object;
   14:	invokeinterface	#142,  2; //InterfaceMethod scala/concurrent/FutureTaskRunner.futureAsFunction:(Ljava/lang/Object;)Lscala/Function0;
   19:	areturn
  LineNumberTable: 
   line 56: 0

  LocalVariableTable: 
   Start  Length  Slot  Name   Signature
   0      20      0    this       Lscala/concurrent/ops$;
   0      20      1    p       Lscala/Function0;
   0      20      2    runner       Lscala/concurrent/FutureTaskRunner;

  Signature: length = 0x2
   00 FFFFFF91 

public void spawn(scala.Function0, scala.concurrent.TaskRunner);
  Code:
   Stack=3, Locals=3, Args_size=3
   0:	aload_2
   1:	aload_2
   2:	aload_1
   3:	invokeinterface	#65,  2; //InterfaceMethod scala/concurrent/TaskRunner.functionAsTask:(Lscala/Function0;)Ljava/lang/Object;
   8:	invokeinterface	#69,  2; //InterfaceMethod scala/concurrent/TaskRunner.execute:(Ljava/lang/Object;)V
   13:	return
  LineNumberTable: 
   line 48: 0

  LocalVariableTable: 
   Start  Length  Slot  Name   Signature
   0      14      0    this       Lscala/concurrent/ops$;
   0      14      1    p       Lscala/Function0;
   0      14      2    runner       Lscala/concurrent/TaskRunner;

  Signature: length = 0x2
   00 FFFFFF94 

public java.lang.Object getOrThrow(scala.Either);
  Code:
   Stack=4, Locals=2, Args_size=2
   0:	aload_1
   1:	new	#113; //class scala/concurrent/ops$$anonfun$getOrThrow$1
   4:	dup
   5:	invokespecial	#114; //Method scala/concurrent/ops$$anonfun$getOrThrow$1."<init>":()V
   8:	new	#116; //class scala/concurrent/ops$$anonfun$getOrThrow$2
   11:	dup
   12:	invokespecial	#117; //Method scala/concurrent/ops$$anonfun$getOrThrow$2."<init>":()V
   15:	invokevirtual	#121; //Method scala/Either.fold:(Lscala/Function1;Lscala/Function1;)Ljava/lang/Object;
   18:	areturn
  LineNumberTable: 
   line 41: 0

  LocalVariableTable: 
   Start  Length  Slot  Name   Signature
   0      19      0    this       Lscala/concurrent/ops$;
   0      19      1    x       Lscala/Either;

  Signature: length = 0x2
   00 FFFFFF99 

public scala.Either tryCatchEx(scala.Function0);
  Code:
   Stack=3, Locals=4, Args_size=2
   0:	new	#157; //class scala/Right
   3:	dup
   4:	aload_1
   5:	invokeinterface	#106,  1; //InterfaceMethod scala/Function0.apply:()Ljava/lang/Object;
   10:	invokespecial	#159; //Method scala/Right."<init>":(Ljava/lang/Object;)V
   13:	astore_2
   14:	goto	27
   17:	astore_3
   18:	new	#161; //class scala/Left
   21:	dup
   22:	aload_3
   23:	invokespecial	#162; //Method scala/Left."<init>":(Ljava/lang/Object;)V
   26:	astore_2
   27:	aload_2
   28:	areturn
  Exception table:
   from   to  target type
     0    17    17   Class java/lang/Exception

  LineNumberTable: 
   line 35: 0
   line 36: 17

  LocalVariableTable: 
   Start  Length  Slot  Name   Signature
   0      29      0    this       Lscala/concurrent/ops$;
   0      29      1    body       Lscala/Function0;
   0      28      2    exceptionResult1       Lscala/Either;

  Signature: length = 0x2
   00 FFFFFFA7 

public scala.Either tryCatch(scala.Function0);
  Code:
   Stack=2, Locals=2, Args_size=2
   0:	getstatic	#173; //Field scala/util/control/Exception$.MODULE$:Lscala/util/control/Exception$;
   3:	invokevirtual	#177; //Method scala/util/control/Exception$.allCatch:()Lscala/util/control/Exception$Catch;
   6:	aload_1
   7:	invokevirtual	#182; //Method scala/util/control/Exception$Catch.either:(Lscala/Function0;)Lscala/Either;
   10:	areturn
  LineNumberTable: 
   line 31: 0

  LocalVariableTable: 
   Start  Length  Slot  Name   Signature
   0      11      0    this       Lscala/concurrent/ops$;
   0      11      1    body       Lscala/Function0;

  Signature: length = 0x2
   00 FFFFFFB7 

public scala.concurrent.FutureTaskRunner defaultRunner();
  Code:
   Stack=1, Locals=1, Args_size=1
   0:	aload_0
   1:	getfield	#32; //Field defaultRunner:Lscala/concurrent/FutureTaskRunner;
   4:	areturn
  LineNumberTable: 
   line 23: 0


public scala.concurrent.FutureTaskRunner future$default$2(scala.Function0);
  Code:
   Stack=1, Locals=2, Args_size=2
   0:	aload_0
   1:	invokevirtual	#187; //Method defaultRunner:()Lscala/concurrent/FutureTaskRunner;
   4:	areturn
  LineNumberTable: 
   line 55: 0

  LocalVariableTable: 
   Start  Length  Slot  Name   Signature
   0      5      0    this       Lscala/concurrent/ops$;
   0      5      1    p       Lscala/Function0;


public scala.concurrent.TaskRunner spawn$default$2(scala.Function0);
  Code:
   Stack=1, Locals=2, Args_size=2
   0:	aload_0
   1:	invokevirtual	#187; //Method defaultRunner:()Lscala/concurrent/FutureTaskRunner;
   4:	areturn
  LineNumberTable: 
   line 47: 0

  LocalVariableTable: 
   Start  Length  Slot  Name   Signature
   0      5      0    this       Lscala/concurrent/ops$;
   0      5      1    p       Lscala/Function0;


}

