Compiled from "ops.scala"
public final class scala.concurrent.ops$$anonfun$replicate$1 extends java.lang.Object implements scala.Function0,scala.ScalaObject,java.io.Serializable
  SourceFile: "ops.scala"
  Scala: length = 0x
   
  InnerClass: 
   public final $anonfun$replicate$1=class scala/concurrent/ops$$anonfun$replicate$1 of class scala/concurrent/ops
  minor version: 0
  major version: 49
  Constant pool:
Asciz	SourceFile;
Asciz	ops.scala;
Asciz	<clinit>;
Asciz	()V;
Asciz	Code;
Asciz	serialVersionUID;
Asciz	J;
Asciz	scala/concurrent/ops$$anonfun$replicate$1;
class	scala/concurrent/ops$$anonfun$replicate$1
NameAndType	serialVersionUID:J
Field	scala/concurrent/ops$$anonfun$replicate$1.serialVersionUID:J
Asciz	mid$1;
Asciz	I;
Asciz	p$1;
Asciz	Lscala/Function1;;
Asciz	start$1;
Asciz	<init>;
Asciz	(ILscala/Function1;I)V;
Asciz	LineNumberTable;
NameAndType	start$1:I
Field	scala/concurrent/ops$$anonfun$replicate$1.start$1:I
NameAndType	p$1:Lscala/Function1;
Field	scala/concurrent/ops$$anonfun$replicate$1.p$1:Lscala/Function1;
NameAndType	mid$1:I
Field	scala/concurrent/ops$$anonfun$replicate$1.mid$1:I
Asciz	java/lang/Object;
class	java/lang/Object
NameAndType	"<init>":()V
Method	java/lang/Object."<init>":()V
Asciz	scala/Function0$class;
class	scala/Function0$class
Asciz	$init$;
Asciz	(Lscala/Function0;)V;
NameAndType	$init$:(Lscala/Function0;)V
Method	scala/Function0$class.$init$:(Lscala/Function0;)V
Asciz	apply;
Asciz	()Ljava/lang/Object;;
NameAndType	apply:()V
Method	scala/concurrent/ops$$anonfun$replicate$1.apply:()V
Asciz	scala/runtime/BoxedUnit;
class	scala/runtime/BoxedUnit
Asciz	UNIT;
Asciz	Lscala/runtime/BoxedUnit;;
NameAndType	UNIT:Lscala/runtime/BoxedUnit;
Field	scala/runtime/BoxedUnit.UNIT:Lscala/runtime/BoxedUnit;
Asciz	scala/concurrent/ops$;
class	scala/concurrent/ops$
Asciz	MODULE$;
Asciz	Lscala/concurrent/ops$;;
NameAndType	MODULE$:Lscala/concurrent/ops$;
Field	scala/concurrent/ops$.MODULE$:Lscala/concurrent/ops$;
Asciz	replicate;
Asciz	(IILscala/Function1;)V;
NameAndType	replicate:(IILscala/Function1;)V
Method	scala/concurrent/ops$.replicate:(IILscala/Function1;)V
Asciz	toString;
Asciz	()Ljava/lang/String;;
Asciz	(Lscala/Function0;)Ljava/lang/String;;
NameAndType	toString:(Lscala/Function0;)Ljava/lang/String;
Method	scala/Function0$class.toString:(Lscala/Function0;)Ljava/lang/String;
Asciz	Scala;
Asciz	InnerClasses;
Asciz	scala/concurrent/ops;
class	scala/concurrent/ops
Asciz	$anonfun$replicate$1;
Asciz	scala/Function0;
class	scala/Function0
Asciz	scala/ScalaObject;
class	scala/ScalaObject
Asciz	java/io/Serializable;
class	java/io/Serializable

{
public static final long serialVersionUID;
  Signature: J

private final int mid$1;
  Signature: I

private final scala.Function1 p$1;
  Signature: Lscala/Function1;

private final int start$1;
  Signature: I

public static {};
  Signature: ()V
  Code:
   Stack=2, Locals=0, Args_size=0
	lconst_0
	putstatic	Field serialVersionUID:J
	return
  Labels:

public scala.concurrent.ops$$anonfun$replicate$1(int, scala.Function1, int);
  Signature: (ILscala/Function1;I)V
  Code:
   Stack=2, Locals=4, Args_size=4
	aload_0
	iload_1
	putfield	Field start$1:I
	aload_0
	aload_2
	putfield	Field p$1:Lscala/Function1;
	aload_0
	iload_3
	putfield	Field mid$1:I
	aload_0
	invokespecial	Method java/lang/Object."<init>":()V
	aload_0
	invokestatic	Method scala/Function0$class.$init$:(Lscala/Function0;)V
	return
  Labels:

public final java.lang.Object apply();
  Signature: ()Ljava/lang/Object;
  Code:
   Stack=1, Locals=1, Args_size=1
	aload_0
	invokevirtual	Method apply:()V
	getstatic	Field scala/runtime/BoxedUnit.UNIT:Lscala/runtime/BoxedUnit;
	areturn
  Labels:

public final void apply();
  Signature: ()V
  Code:
   Stack=4, Locals=1, Args_size=1
	getstatic	Field scala/concurrent/ops$.MODULE$:Lscala/concurrent/ops$;
	aload_0
	getfield	Field start$1:I
	aload_0
	getfield	Field mid$1:I
	aload_0
	getfield	Field p$1:Lscala/Function1;
	invokevirtual	Method scala/concurrent/ops$.replicate:(IILscala/Function1;)V
	return
  Labels:

public java.lang.String toString();
  Signature: ()Ljava/lang/String;
  Code:
   Stack=1, Locals=1, Args_size=1
	aload_0
	invokestatic	Method scala/Function0$class.toString:(Lscala/Function0;)Ljava/lang/String;
	areturn
  Labels:

}

