Compiled from "ops.scala"
public final class scala.concurrent.ops$$anonfun$par$2 extends scala.runtime.AbstractFunction0$mcV$sp implements java.io.Serializable
  SourceFile: "ops.scala"
  Scala: length = 0x
   
  InnerClass: 
   public final $anonfun$par$2=class scala/concurrent/ops$$anonfun$par$2 of class scala/concurrent/ops
  minor version: 0
  major version: 49
  Constant pool:
Asciz	SourceFile;
Asciz	ops.scala;
Asciz	<clinit>;
Asciz	()V;
Asciz	Code;
Asciz	serialVersionUID;
Asciz	J;
Asciz	scala/concurrent/ops$$anonfun$par$2;
class	scala/concurrent/ops$$anonfun$par$2
NameAndType	serialVersionUID:J
Field	scala/concurrent/ops$$anonfun$par$2.serialVersionUID:J
Asciz	x$2$1;
Asciz	Lscala/Function0;;
Asciz	apply;
Asciz	LineNumberTable;
NameAndType	x$2$1:Lscala/Function0;
Field	scala/concurrent/ops$$anonfun$par$2.x$2$1:Lscala/Function0;
Asciz	scala/Function0;
class	scala/Function0
Asciz	apply$mcV$sp;
NameAndType	apply$mcV$sp:()V
InterfaceMethod	scala/Function0.apply$mcV$sp:()V
Asciz	()Ljava/lang/Object;;
NameAndType	apply:()V
Method	scala/concurrent/ops$$anonfun$par$2.apply:()V
Asciz	scala/runtime/BoxedUnit;
class	scala/runtime/BoxedUnit
Asciz	UNIT;
Asciz	Lscala/runtime/BoxedUnit;;
NameAndType	UNIT:Lscala/runtime/BoxedUnit;
Field	scala/runtime/BoxedUnit.UNIT:Lscala/runtime/BoxedUnit;
Asciz	<init>;
Asciz	(Lscala/Function0;)V;
Asciz	scala/runtime/AbstractFunction0$mcV$sp;
class	scala/runtime/AbstractFunction0$mcV$sp
NameAndType	"<init>":()V
Method	scala/runtime/AbstractFunction0$mcV$sp."<init>":()V
Asciz	Scala;
Asciz	InnerClasses;
Asciz	scala/concurrent/ops;
class	scala/concurrent/ops
Asciz	$anonfun$par$2;
Asciz	java/io/Serializable;
class	java/io/Serializable

{
public static final long serialVersionUID;
  Signature: J

public final scala.Function0 x$2$1;
  Signature: Lscala/Function0;

public static {};
  Signature: ()V
  Code:
   Stack=2, Locals=0, Args_size=0
	lconst_0
	putstatic	Field serialVersionUID:J
	return
  Labels:

public final void apply();
  Signature: ()V
  Code:
   Stack=1, Locals=1, Args_size=1
	aload_0
	getfield	Field x$2$1:Lscala/Function0;
	invokeinterface	InterfaceMethod scala/Function0.apply$mcV$sp:()V
	return
  Labels:

public void apply$mcV$sp();
  Signature: ()V
  Code:
   Stack=1, Locals=1, Args_size=1
	aload_0
	getfield	Field x$2$1:Lscala/Function0;
	invokeinterface	InterfaceMethod scala/Function0.apply$mcV$sp:()V
	return
  Labels:

public final java.lang.Object apply();
  Signature: ()Ljava/lang/Object;
  Code:
   Stack=1, Locals=1, Args_size=1
	aload_0
	invokevirtual	Method apply:()V
	getstatic	Field scala/runtime/BoxedUnit.UNIT:Lscala/runtime/BoxedUnit;
	areturn
  Labels:

public scala.concurrent.ops$$anonfun$par$2(scala.Function0);
  Signature: (Lscala/Function0;)V
  Code:
   Stack=2, Locals=2, Args_size=2
	aload_0
	aload_1
	putfield	Field x$2$1:Lscala/Function0;
	aload_0
	invokespecial	Method scala/runtime/AbstractFunction0$mcV$sp."<init>":()V
	return
  Labels:

}

