Compiled from "ops.scala"
public final class scala.concurrent.ops$$anonfun$1 extends scala.runtime.AbstractFunction0 implements java.io.Serializable
  SourceFile: "ops.scala"
  Scala: length = 0x
   
  InnerClass: 
   public final #41= #9 of #40; //$anonfun$1=class scala/concurrent/ops$$anonfun$1 of class scala/concurrent/ops
  minor version: 0
  major version: 49
  Constant pool:
const #1 = Asciz	SourceFile;
const #2 = Asciz	ops.scala;
const #3 = Asciz	<clinit>;
const #4 = Asciz	()V;
const #5 = Asciz	Code;
const #6 = Asciz	serialVersionUID;
const #7 = Asciz	J;
const #8 = Asciz	scala/concurrent/ops$$anonfun$1;
const #9 = class	#8;	//  scala/concurrent/ops$$anonfun$1
const #10 = NameAndType	#6:#7;//  serialVersionUID:J
const #11 = Field	#9.#10;	//  scala/concurrent/ops$$anonfun$1.serialVersionUID:J
const #12 = Asciz	x$2$1;
const #13 = Asciz	Lscala/Function0;;
const #14 = Asciz	<init>;
const #15 = Asciz	(Lscala/Function0;)V;
const #16 = Asciz	LineNumberTable;
const #17 = NameAndType	#12:#13;//  x$2$1:Lscala/Function0;
const #18 = Field	#9.#17;	//  scala/concurrent/ops$$anonfun$1.x$2$1:Lscala/Function0;
const #19 = Asciz	scala/runtime/AbstractFunction0;
const #20 = class	#19;	//  scala/runtime/AbstractFunction0
const #21 = NameAndType	#14:#4;//  "<init>":()V
const #22 = Method	#20.#21;	//  scala/runtime/AbstractFunction0."<init>":()V
const #23 = Asciz	apply;
const #24 = Asciz	()Ljava/lang/Object;;
const #25 = NameAndType	#23:#4;//  apply:()V
const #26 = Method	#9.#25;	//  scala/concurrent/ops$$anonfun$1.apply:()V
const #27 = Asciz	scala/runtime/BoxedUnit;
const #28 = class	#27;	//  scala/runtime/BoxedUnit
const #29 = Asciz	UNIT;
const #30 = Asciz	Lscala/runtime/BoxedUnit;;
const #31 = NameAndType	#29:#30;//  UNIT:Lscala/runtime/BoxedUnit;
const #32 = Field	#28.#31;	//  scala/runtime/BoxedUnit.UNIT:Lscala/runtime/BoxedUnit;
const #33 = Asciz	scala/Function0;
const #34 = class	#33;	//  scala/Function0
const #35 = NameAndType	#23:#24;//  apply:()Ljava/lang/Object;
const #36 = InterfaceMethod	#34.#35;	//  scala/Function0.apply:()Ljava/lang/Object;
const #37 = Asciz	Scala;
const #38 = Asciz	InnerClasses;
const #39 = Asciz	scala/concurrent/ops;
const #40 = class	#39;	//  scala/concurrent/ops
const #41 = Asciz	$anonfun$1;
const #42 = Asciz	java/io/Serializable;
const #43 = class	#42;	//  java/io/Serializable

{
public static final long serialVersionUID;

public static {};
  Code:
   Stack=2, Locals=0, Args_size=0
   0:	lconst_0
   1:	putstatic	#11; //Field serialVersionUID:J
   4:	return

public scala.concurrent.ops$$anonfun$1(scala.Function0);
  Code:
   Stack=2, Locals=2, Args_size=2
   0:	aload_0
   1:	aload_1
   2:	putfield	#18; //Field x$2$1:Lscala/Function0;
   5:	aload_0
   6:	invokespecial	#22; //Method scala/runtime/AbstractFunction0."<init>":()V
   9:	return
  LineNumberTable: 
   line 66: 0


public final java.lang.Object apply();
  Code:
   Stack=1, Locals=1, Args_size=1
   0:	aload_0
   1:	invokevirtual	#26; //Method apply:()V
   4:	getstatic	#32; //Field scala/runtime/BoxedUnit.UNIT:Lscala/runtime/BoxedUnit;
   7:	areturn
  LineNumberTable: 
   line 66: 0


public final void apply();
  Code:
   Stack=1, Locals=1, Args_size=1
   0:	aload_0
   1:	getfield	#18; //Field x$2$1:Lscala/Function0;
   4:	invokeinterface	#36,  1; //InterfaceMethod scala/Function0.apply:()Ljava/lang/Object;
   9:	pop
   10:	return
  LineNumberTable: 
   line 66: 0


}

