Compiled from "ops.scala"
public final class scala.concurrent.ops extends java.lang.Object
  SourceFile: "ops.scala"
  ScalaSig: length = 0x4A5
   05 00 FFFFFF81 33 07 05 01 02 FFFFFF88 02 07 01 03 6F 70 73
   0A 02 03 04 01 0A 63 6F 6E 63 75 72 72 65 6E 74
   0A 01 05 01 05 73 63 61 6C 61 03 00 10 02 08 09
   0D 01 02 06 08 0A 02 FFFFFF84 FFFFFF80 FFFFFF80 FFFFFF88 02 0B 02 03 6F
   70 73 13 03 09 0C 14 10 02 0D 12 0D 01 0E 0A 02
   0F 10 01 04 6C 61 6E 67 0A 01 11 01 04 6A 61 76
   61 09 02 13 0E 02 06 4F 62 6A 65 63 74 10 02 15
   16 0D 01 04 09 02 17 04 02 0B 53 63 61 6C 61 4F
   62 6A 65 63 74 08 05 19 09 FFFFFF84 00 1A 01 06 3C 69
   6E 69 74 3E 14 01 07 08 07 1C 09 FFFFFFC2 FFFFFF80 FFFFFF84 00 1D
   01 0D 64 65 66 61 75 6C 74 52 75 6E 6E 65 72 15
   01 1E 10 02 08 1F 09 02 20 02 02 10 46 75 74 75
   72 65 54 61 73 6B 52 75 6E 6E 65 72 08 06 22 09
   FFFFFFA0 FFFFFF80 04 1E 01 0E 64 65 66 61 75 6C 74 52 75 6E
   6E 65 72 20 08 05 24 09 FFFFFF84 00 25 01 08 74 72 79
   43 61 74 63 68 15 02 26 38 14 02 27 41 10 04 15
   28 2A 36 09 02 29 04 02 06 45 69 74 68 65 72 10
   02 2B 33 0E 02 2C 31 0E 02 2D 30 0D 01 2E 0A 02
   2F 06 01 06 3C 72 6F 6F 74 3E 09 01 05 09 02 32
   04 01 07 70 61 63 6B 61 67 65 09 02 34 35 02 09
   54 68 72 6F 77 61 62 6C 65 0A 02 32 04 10 02 37
   38 0C 00 04 08 39 23 FFFFFF84 FFFFFF80 FFFFFF80 FFFFFFC2 00 3A 02 01 41
   11 02 3B 3E 10 02 15 3C 09 02 3D 04 02 07 4E 6F
   74 68 69 6E 67 10 02 15 3F 09 02 40 04 02 03 41
   6E 79 08 06 42 23 FFFFFF84 FFFFFFC0 00 43 01 04 62 6F 64 79
   10 03 15 44 36 09 02 45 04 02 08 3C 62 79 6E 61
   6D 65 3E 08 05 47 09 FFFFFF84 00 48 01 0A 74 72 79 43
   61 74 63 68 45 78 15 02 49 4F 14 02 4A 50 10 04
   15 28 4B 4E 10 02 2B 4C 09 02 4D 35 02 09 45 78
   63 65 70 74 69 6F 6E 10 02 37 4F 04 08 39 46 FFFFFF84
   FFFFFF80 FFFFFF80 FFFFFFC2 00 3A 08 06 42 46 FFFFFF84 FFFFFFC0 00 51 10 03 15
   44 4E 08 05 53 09 FFFFFF84 00 54 01 0A 67 65 74 4F 72
   54 68 72 6F 77 15 03 55 5C 57 14 02 56 58 10 02
   37 57 04 08 39 52 FFFFFF84 FFFFFF80 FFFFFF80 FFFFFFC2 00 3A 08 05 59 52
   FFFFFFC0 00 5A 01 01 78 10 04 15 28 5B 56 10 02 37 5C
   04 08 5D 52 FFFFFF84 FFFFFF80 FFFFFF80 FFFFFFC2 00 5E 02 01 54 11 02 3B
   2A 08 05 60 09 FFFFFF84 00 61 01 05 73 70 61 77 6E 14
   02 62 7B 16 02 63 66 10 02 15 64 09 02 65 04 02
   04 55 6E 69 74 08 08 6B 67 5F FFFFFF90 FFFFFF80 FFFFFFC0 01 68 01
   06 72 75 6E 6E 65 72 10 02 08 69 09 02 6A 02 02
   0A 54 61 73 6B 52 75 6E 6E 65 72 08 07 6C 09 FFFFFF91
   FFFFFF80 FFFFFF84 00 6D 01 0F 73 70 61 77 6E 24 64 65 66 61
   75 6C 74 24 32 14 02 6E 78 2A 02 68 6F 2B 01 70
   10 02 71 76 0D 01 72 0A 02 73 74 01 09 75 6E 63
   68 65 63 6B 65 64 0A 02 75 04 01 0A 61 6E 6E 6F
   74 61 74 69 6F 6E 09 02 77 72 02 11 75 6E 63 68
   65 63 6B 65 64 56 61 72 69 61 6E 63 65 08 06 79
   6B FFFFFF84 FFFFFFC0 00 7A 01 01 70 10 03 15 44 63 08 06 79
   5F FFFFFF84 FFFFFFC0 00 7A 08 05 7D 09 FFFFFF84 00 7E 01 06 66 75
   74 75 72 65 15 03 7F FFFFFF81 05 14 04 FFFFFF81 00 FFFFFF81 10 16
   04 FFFFFF81 01 FFFFFF81 06 10 05 15 FFFFFF81 02 FFFFFF81 04 09 03 FFFFFF81 03
   04 02 09 46 75 6E 63 74 69 6F 6E 30 10 03 37 FFFFFF81
   05 04 08 39 7C FFFFFF84 FFFFFF80 FFFFFF80 FFFFFFC2 00 3A 08 09 FFFFFF81 07 67
   7C FFFFFF90 FFFFFF80 FFFFFFC0 01 1E 08 09 FFFFFF81 08 09 FFFFFF91 FFFFFF80 FFFFFF84 00 FFFFFF81
   09 01 10 66 75 74 75 72 65 24 64 65 66 61 75 6C
   74 24 32 15 04 FFFFFF81 0A FFFFFF81 0F 14 04 FFFFFF81 0B FFFFFF81 0C 2A
   02 1E 6F 08 08 79 FFFFFF81 07 FFFFFF84 FFFFFFC0 00 FFFFFF81 0D 10 04 15
   44 FFFFFF81 0E 10 03 37 FFFFFF81 0F 04 09 39 FFFFFF81 07 FFFFFF84 FFFFFF80 FFFFFF80
   FFFFFFC2 00 3A 08 07 79 7C FFFFFF84 FFFFFFC0 00 FFFFFF81 11 10 04 15 44
   FFFFFF81 04 08 07 FFFFFF81 13 09 FFFFFF84 00 FFFFFF81 14 01 03 70 61 72
   15 06 FFFFFF81 15 FFFFFF81 1A FFFFFF81 1C 14 06 FFFFFF81 16 FFFFFF81 1E FFFFFF81 21
   10 07 15 FFFFFF81 17 FFFFFF81 19 FFFFFF81 1B 09 03 FFFFFF81 18 04 02 06
   54 75 70 6C 65 32 10 03 37 FFFFFF81 1A 04 09 39 FFFFFF81 12
   FFFFFF84 FFFFFF80 FFFFFF80 FFFFFFC2 00 3A 10 03 37 FFFFFF81 1C 04 0A FFFFFF81 1D FFFFFF81
   12 FFFFFF84 FFFFFF80 FFFFFF80 FFFFFFC2 00 3A 02 01 42 08 09 FFFFFF81 1F FFFFFF81 12
   FFFFFF84 FFFFFFC0 00 FFFFFF81 20 01 02 78 70 10 04 15 44 FFFFFF81 19 08
   09 FFFFFF81 22 FFFFFF81 12 FFFFFF84 FFFFFFC0 00 FFFFFF81 23 01 02 79 70 10 04
   15 44 FFFFFF81 1B 08 07 FFFFFF81 25 09 FFFFFF84 00 FFFFFF81 26 01 09 72
   65 70 6C 69 63 61 74 65 14 06 FFFFFF81 27 FFFFFF81 2F FFFFFF81 31
   14 03 63 FFFFFF81 28 08 07 79 FFFFFF81 24 FFFFFFC0 00 FFFFFF81 29 10 06
   15 FFFFFF81 2A FFFFFF81 2C 63 09 03 FFFFFF81 2B 04 02 09 46 75 6E
   63 74 69 6F 6E 31 10 03 15 FFFFFF81 2D 09 03 FFFFFF81 2E 04
   02 03 49 6E 74 08 08 FFFFFF81 30 FFFFFF81 24 FFFFFFC0 00 FFFFFF81 2C 01
   05 73 74 61 72 74 08 08 FFFFFF81 32 FFFFFF81 24 FFFFFFC0 00 FFFFFF81 2C
   01 03 65 6E 64 
  InnerClass: 
   public final #63= #60 of #62; //$anonfun$2=class scala/concurrent/ops$$anonfun$2 of class scala/concurrent/ops
   public final #66= #65 of #62; //$anonfun$1=class scala/concurrent/ops$$anonfun$1 of class scala/concurrent/ops
   public final #69= #68 of #62; //$anonfun$par$2=class scala/concurrent/ops$$anonfun$par$2 of class scala/concurrent/ops
   public final #72= #71 of #62; //$anonfun$par$1=class scala/concurrent/ops$$anonfun$par$1 of class scala/concurrent/ops
   public final #75= #74 of #62; //$anonfun$replicate$2=class scala/concurrent/ops$$anonfun$replicate$2 of class scala/concurrent/ops
   public final #78= #77 of #62; //$anonfun$replicate$1=class scala/concurrent/ops$$anonfun$replicate$1 of class scala/concurrent/ops
   public final #81= #80 of #62; //$anonfun$getOrThrow$2=class scala/concurrent/ops$$anonfun$getOrThrow$2 of class scala/concurrent/ops
   public final #84= #83 of #62; //$anonfun$getOrThrow$1=class scala/concurrent/ops$$anonfun$getOrThrow$1 of class scala/concurrent/ops
  minor version: 0
  major version: 49
  Constant pool:
const #1 = Asciz	SourceFile;
const #2 = Asciz	ops.scala;
const #3 = Asciz	spawn$default$2;
const #4 = Asciz	(Lscala/Function0;)Lscala/concurrent/TaskRunner;;
const #5 = Asciz	Code;
const #6 = Asciz	scala/concurrent/ops$;
const #7 = class	#6;	//  scala/concurrent/ops$
const #8 = Asciz	MODULE$;
const #9 = Asciz	Lscala/concurrent/ops$;;
const #10 = NameAndType	#8:#9;//  MODULE$:Lscala/concurrent/ops$;
const #11 = Field	#7.#10;	//  scala/concurrent/ops$.MODULE$:Lscala/concurrent/ops$;
const #12 = NameAndType	#3:#4;//  spawn$default$2:(Lscala/Function0;)Lscala/concurrent/TaskRunner;
const #13 = Method	#7.#12;	//  scala/concurrent/ops$.spawn$default$2:(Lscala/Function0;)Lscala/concurrent/TaskRunner;
const #14 = Asciz	future$default$2;
const #15 = Asciz	(Lscala/Function0;)Lscala/concurrent/FutureTaskRunner;;
const #16 = NameAndType	#14:#15;//  future$default$2:(Lscala/Function0;)Lscala/concurrent/FutureTaskRunner;
const #17 = Method	#7.#16;	//  scala/concurrent/ops$.future$default$2:(Lscala/Function0;)Lscala/concurrent/FutureTaskRunner;
const #18 = Asciz	replicate;
const #19 = Asciz	(IILscala/Function1;)V;
const #20 = NameAndType	#18:#19;//  replicate:(IILscala/Function1;)V
const #21 = Method	#7.#20;	//  scala/concurrent/ops$.replicate:(IILscala/Function1;)V
const #22 = Asciz	(IILscala/Function1<Ljava/lang/Integer;Ljava/lang/Object;>;)V;
const #23 = Asciz	Signature;
const #24 = Asciz	par;
const #25 = Asciz	(Lscala/Function0;Lscala/Function0;)Lscala/Tuple2;;
const #26 = NameAndType	#24:#25;//  par:(Lscala/Function0;Lscala/Function0;)Lscala/Tuple2;
const #27 = Method	#7.#26;	//  scala/concurrent/ops$.par:(Lscala/Function0;Lscala/Function0;)Lscala/Tuple2;
const #28 = Asciz	<A:Ljava/lang/Object;B:Ljava/lang/Object;>(Lscala/Function0<TA;>;Lscala/Function0<TB;>;)Lscala/Tuple2<TA;TB;>;;
const #29 = Asciz	future;
const #30 = Asciz	(Lscala/Function0;Lscala/concurrent/FutureTaskRunner;)Lscala/Function0;;
const #31 = NameAndType	#29:#30;//  future:(Lscala/Function0;Lscala/concurrent/FutureTaskRunner;)Lscala/Function0;
const #32 = Method	#7.#31;	//  scala/concurrent/ops$.future:(Lscala/Function0;Lscala/concurrent/FutureTaskRunner;)Lscala/Function0;
const #33 = Asciz	<A:Ljava/lang/Object;>(Lscala/Function0<TA;>;Lscala/concurrent/FutureTaskRunner;)Lscala/Function0<TA;>;;
const #34 = Asciz	spawn;
const #35 = Asciz	(Lscala/Function0;Lscala/concurrent/TaskRunner;)V;
const #36 = NameAndType	#34:#35;//  spawn:(Lscala/Function0;Lscala/concurrent/TaskRunner;)V
const #37 = Method	#7.#36;	//  scala/concurrent/ops$.spawn:(Lscala/Function0;Lscala/concurrent/TaskRunner;)V
const #38 = Asciz	(Lscala/Function0<Ljava/lang/Object;>;Lscala/concurrent/TaskRunner;)V;
const #39 = Asciz	getOrThrow;
const #40 = Asciz	(Lscala/Either;)Ljava/lang/Object;;
const #41 = NameAndType	#39:#40;//  getOrThrow:(Lscala/Either;)Ljava/lang/Object;
const #42 = Method	#7.#41;	//  scala/concurrent/ops$.getOrThrow:(Lscala/Either;)Ljava/lang/Object;
const #43 = Asciz	<T:Ljava/lang/Throwable;A:Ljava/lang/Object;>(Lscala/Either<TT;TA;>;)TA;;
const #44 = Asciz	tryCatchEx;
const #45 = Asciz	(Lscala/Function0;)Lscala/Either;;
const #46 = NameAndType	#44:#45;//  tryCatchEx:(Lscala/Function0;)Lscala/Either;
const #47 = Method	#7.#46;	//  scala/concurrent/ops$.tryCatchEx:(Lscala/Function0;)Lscala/Either;
const #48 = Asciz	<A:Ljava/lang/Object;>(Lscala/Function0<TA;>;)Lscala/Either<Ljava/lang/Exception;TA;>;;
const #49 = Asciz	tryCatch;
const #50 = NameAndType	#49:#45;//  tryCatch:(Lscala/Function0;)Lscala/Either;
const #51 = Method	#7.#50;	//  scala/concurrent/ops$.tryCatch:(Lscala/Function0;)Lscala/Either;
const #52 = Asciz	<A:Ljava/lang/Object;>(Lscala/Function0<TA;>;)Lscala/Either<Ljava/lang/Throwable;TA;>;;
const #53 = Asciz	defaultRunner;
const #54 = Asciz	()Lscala/concurrent/FutureTaskRunner;;
const #55 = NameAndType	#53:#54;//  defaultRunner:()Lscala/concurrent/FutureTaskRunner;
const #56 = Method	#7.#55;	//  scala/concurrent/ops$.defaultRunner:()Lscala/concurrent/FutureTaskRunner;
const #57 = Asciz	ScalaSig;
const #58 = Asciz	InnerClasses;
const #59 = Asciz	scala/concurrent/ops$$anonfun$2;
const #60 = class	#59;	//  scala/concurrent/ops$$anonfun$2
const #61 = Asciz	scala/concurrent/ops;
const #62 = class	#61;	//  scala/concurrent/ops
const #63 = Asciz	$anonfun$2;
const #64 = Asciz	scala/concurrent/ops$$anonfun$1;
const #65 = class	#64;	//  scala/concurrent/ops$$anonfun$1
const #66 = Asciz	$anonfun$1;
const #67 = Asciz	scala/concurrent/ops$$anonfun$par$2;
const #68 = class	#67;	//  scala/concurrent/ops$$anonfun$par$2
const #69 = Asciz	$anonfun$par$2;
const #70 = Asciz	scala/concurrent/ops$$anonfun$par$1;
const #71 = class	#70;	//  scala/concurrent/ops$$anonfun$par$1
const #72 = Asciz	$anonfun$par$1;
const #73 = Asciz	scala/concurrent/ops$$anonfun$replicate$2;
const #74 = class	#73;	//  scala/concurrent/ops$$anonfun$replicate$2
const #75 = Asciz	$anonfun$replicate$2;
const #76 = Asciz	scala/concurrent/ops$$anonfun$replicate$1;
const #77 = class	#76;	//  scala/concurrent/ops$$anonfun$replicate$1
const #78 = Asciz	$anonfun$replicate$1;
const #79 = Asciz	scala/concurrent/ops$$anonfun$getOrThrow$2;
const #80 = class	#79;	//  scala/concurrent/ops$$anonfun$getOrThrow$2
const #81 = Asciz	$anonfun$getOrThrow$2;
const #82 = Asciz	scala/concurrent/ops$$anonfun$getOrThrow$1;
const #83 = class	#82;	//  scala/concurrent/ops$$anonfun$getOrThrow$1
const #84 = Asciz	$anonfun$getOrThrow$1;
const #85 = Asciz	java/lang/Object;
const #86 = class	#85;	//  java/lang/Object

{
public static final scala.concurrent.TaskRunner spawn$default$2(scala.Function0);
  Code:
   Stack=2, Locals=1, Args_size=1
   0:	getstatic	#11; //Field scala/concurrent/ops$.MODULE$:Lscala/concurrent/ops$;
   3:	aload_0
   4:	invokevirtual	#13; //Method scala/concurrent/ops$.spawn$default$2:(Lscala/Function0;)Lscala/concurrent/TaskRunner;
   7:	areturn

public static final scala.concurrent.FutureTaskRunner future$default$2(scala.Function0);
  Code:
   Stack=2, Locals=1, Args_size=1
   0:	getstatic	#11; //Field scala/concurrent/ops$.MODULE$:Lscala/concurrent/ops$;
   3:	aload_0
   4:	invokevirtual	#17; //Method scala/concurrent/ops$.future$default$2:(Lscala/Function0;)Lscala/concurrent/FutureTaskRunner;
   7:	areturn

public static final void replicate(int, int, scala.Function1);
  Code:
   Stack=4, Locals=3, Args_size=3
   0:	getstatic	#11; //Field scala/concurrent/ops$.MODULE$:Lscala/concurrent/ops$;
   3:	iload_0
   4:	iload_1
   5:	aload_2
   6:	invokevirtual	#21; //Method scala/concurrent/ops$.replicate:(IILscala/Function1;)V
   9:	return
  Signature: length = 0x2
   00 16 

public static final scala.Tuple2 par(scala.Function0, scala.Function0);
  Code:
   Stack=3, Locals=2, Args_size=2
   0:	getstatic	#11; //Field scala/concurrent/ops$.MODULE$:Lscala/concurrent/ops$;
   3:	aload_0
   4:	aload_1
   5:	invokevirtual	#27; //Method scala/concurrent/ops$.par:(Lscala/Function0;Lscala/Function0;)Lscala/Tuple2;
   8:	areturn
  Signature: length = 0x2
   00 1C 

public static final scala.Function0 future(scala.Function0, scala.concurrent.FutureTaskRunner);
  Code:
   Stack=3, Locals=2, Args_size=2
   0:	getstatic	#11; //Field scala/concurrent/ops$.MODULE$:Lscala/concurrent/ops$;
   3:	aload_0
   4:	aload_1
   5:	invokevirtual	#32; //Method scala/concurrent/ops$.future:(Lscala/Function0;Lscala/concurrent/FutureTaskRunner;)Lscala/Function0;
   8:	areturn
  Signature: length = 0x2
   00 21 

public static final void spawn(scala.Function0, scala.concurrent.TaskRunner);
  Code:
   Stack=3, Locals=2, Args_size=2
   0:	getstatic	#11; //Field scala/concurrent/ops$.MODULE$:Lscala/concurrent/ops$;
   3:	aload_0
   4:	aload_1
   5:	invokevirtual	#37; //Method scala/concurrent/ops$.spawn:(Lscala/Function0;Lscala/concurrent/TaskRunner;)V
   8:	return
  Signature: length = 0x2
   00 26 

public static final java.lang.Object getOrThrow(scala.Either);
  Code:
   Stack=2, Locals=1, Args_size=1
   0:	getstatic	#11; //Field scala/concurrent/ops$.MODULE$:Lscala/concurrent/ops$;
   3:	aload_0
   4:	invokevirtual	#42; //Method scala/concurrent/ops$.getOrThrow:(Lscala/Either;)Ljava/lang/Object;
   7:	areturn
  Signature: length = 0x2
   00 2B 

public static final scala.Either tryCatchEx(scala.Function0);
  Code:
   Stack=2, Locals=1, Args_size=1
   0:	getstatic	#11; //Field scala/concurrent/ops$.MODULE$:Lscala/concurrent/ops$;
   3:	aload_0
   4:	invokevirtual	#47; //Method scala/concurrent/ops$.tryCatchEx:(Lscala/Function0;)Lscala/Either;
   7:	areturn
  Signature: length = 0x2
   00 30 

public static final scala.Either tryCatch(scala.Function0);
  Code:
   Stack=2, Locals=1, Args_size=1
   0:	getstatic	#11; //Field scala/concurrent/ops$.MODULE$:Lscala/concurrent/ops$;
   3:	aload_0
   4:	invokevirtual	#51; //Method scala/concurrent/ops$.tryCatch:(Lscala/Function0;)Lscala/Either;
   7:	areturn
  Signature: length = 0x2
   00 34 

public static final scala.concurrent.FutureTaskRunner defaultRunner();
  Code:
   Stack=1, Locals=0, Args_size=0
   0:	getstatic	#11; //Field scala/concurrent/ops$.MODULE$:Lscala/concurrent/ops$;
   3:	invokevirtual	#56; //Method scala/concurrent/ops$.defaultRunner:()Lscala/concurrent/FutureTaskRunner;
   6:	areturn

}

