Compiled from "ops.scala"
public final class scala.concurrent.ops extends java.lang.Object
  SourceFile: "ops.scala"
  ScalaSig: length = 0x49F
   05 00 FFFFFF81 33 07 05 01 02 FFFFFF88 02 07 01 03 6F 70 73
   0A 02 03 04 01 0A 63 6F 6E 63 75 72 72 65 6E 74
   0A 01 05 01 05 73 63 61 6C 61 03 00 10 02 08 09
   0D 01 02 06 08 0A 02 FFFFFF84 FFFFFF80 FFFFFF80 FFFFFF88 02 0B 02 03 6F
   70 73 13 03 09 0C 14 10 02 0D 12 0D 01 0E 0A 02
   0F 10 01 04 6C 61 6E 67 0A 01 11 01 04 6A 61 76
   61 09 02 13 0E 02 06 4F 62 6A 65 63 74 10 02 15
   16 0D 01 04 09 02 17 04 02 0B 53 63 61 6C 61 4F
   62 6A 65 63 74 08 05 19 09 FFFFFF84 00 1A 01 06 3C 69
   6E 69 74 3E 14 01 07 08 07 1C 09 FFFFFFC2 FFFFFF80 FFFFFF84 00 1D
   01 0D 64 65 66 61 75 6C 74 52 75 6E 6E 65 72 15
   01 1E 10 02 08 1F 09 02 20 02 02 10 46 75 74 75
   72 65 54 61 73 6B 52 75 6E 6E 65 72 08 06 22 09
   FFFFFFA0 FFFFFF80 04 1E 01 0E 64 65 66 61 75 6C 74 52 75 6E
   6E 65 72 20 08 05 24 09 FFFFFF84 00 25 01 08 74 72 79
   43 61 74 63 68 15 02 26 38 14 02 27 41 10 04 15
   28 2A 36 09 02 29 04 02 06 45 69 74 68 65 72 10
   02 2B 33 0E 02 2C 31 0E 02 2D 30 0D 01 2E 0A 02
   2F 06 01 06 3C 72 6F 6F 74 3E 09 01 05 09 02 32
   04 01 07 70 61 63 6B 61 67 65 09 02 34 35 02 09
   54 68 72 6F 77 61 62 6C 65 0A 02 32 04 10 02 37
   38 0C 00 04 08 39 23 FFFFFF84 FFFFFF80 FFFFFF80 FFFFFFC2 00 3A 02 01 41
   11 02 3B 3E 10 02 15 3C 09 02 3D 04 02 07 4E 6F
   74 68 69 6E 67 10 02 15 3F 09 02 40 04 02 03 41
   6E 79 08 06 42 23 FFFFFF84 FFFFFFC0 00 43 01 04 62 6F 64 79
   10 03 15 44 36 09 02 45 04 02 08 3C 62 79 6E 61
   6D 65 3E 08 05 47 09 FFFFFF84 00 48 01 0A 74 72 79 43
   61 74 63 68 45 78 15 02 49 4F 14 02 4A 50 10 04
   15 28 4B 4E 10 02 2B 4C 09 02 4D 35 02 09 45 78
   63 65 70 74 69 6F 6E 10 02 37 4F 04 08 39 46 FFFFFF84
   FFFFFF80 FFFFFF80 FFFFFFC2 00 3A 08 06 42 46 FFFFFF84 FFFFFFC0 00 51 10 03 15
   44 4E 08 05 53 09 FFFFFF84 00 54 01 0A 67 65 74 4F 72
   54 68 72 6F 77 15 03 55 5C 57 14 02 56 58 10 02
   37 57 04 08 39 52 FFFFFF84 FFFFFF80 FFFFFF80 FFFFFFC2 00 3A 08 05 59 52
   FFFFFFC0 00 5A 01 01 78 10 04 15 28 5B 56 10 02 37 5C
   04 08 5D 52 FFFFFF84 FFFFFF80 FFFFFF80 FFFFFFC2 00 5E 02 01 54 11 02 3B
   2A 08 05 60 09 FFFFFF84 00 61 01 05 73 70 61 77 6E 14
   02 62 6B 16 02 63 66 10 02 15 64 09 02 65 04 02
   04 55 6E 69 74 08 07 67 5F FFFFFF90 FFFFFF80 FFFFFFC0 01 68 01 06
   72 75 6E 6E 65 72 10 02 08 69 09 02 6A 02 02 0A
   54 61 73 6B 52 75 6E 6E 65 72 08 06 6C 5F FFFFFF84 FFFFFFC0
   00 6D 01 01 70 10 03 15 44 63 08 05 6F 09 FFFFFF84 00
   70 01 06 66 75 74 75 72 65 15 02 71 77 14 02 72
   79 16 02 73 78 10 03 15 74 76 09 02 75 04 02 09
   46 75 6E 63 74 69 6F 6E 30 10 02 37 77 04 08 39
   6E FFFFFF84 FFFFFF80 FFFFFF80 FFFFFFC2 00 3A 08 07 67 6E FFFFFF90 FFFFFF80 FFFFFFC0 01 1E
   08 06 6C 6E FFFFFF84 FFFFFFC0 00 7A 10 03 15 44 76 08 05 7C
   09 FFFFFF84 00 7D 01 03 70 61 72 15 05 7E FFFFFF81 03 FFFFFF81 05
   14 05 7F FFFFFF81 07 FFFFFF81 0A 10 07 15 FFFFFF81 00 FFFFFF81 02 FFFFFF81 04
   09 03 FFFFFF81 01 04 02 06 54 75 70 6C 65 32 10 03 37
   FFFFFF81 03 04 08 39 7B FFFFFF84 FFFFFF80 FFFFFF80 FFFFFFC2 00 3A 10 03 37 FFFFFF81
   05 04 09 FFFFFF81 06 7B FFFFFF84 FFFFFF80 FFFFFF80 FFFFFFC2 00 3A 02 01 42 08
   08 FFFFFF81 08 7B FFFFFF84 FFFFFFC0 00 FFFFFF81 09 01 02 78 70 10 04 15
   44 FFFFFF81 02 08 08 FFFFFF81 0B 7B FFFFFF84 FFFFFFC0 00 FFFFFF81 0C 01 02 79
   70 10 04 15 44 FFFFFF81 04 08 07 FFFFFF81 0E 09 FFFFFF84 00 FFFFFF81 0F
   01 09 72 65 70 6C 69 63 61 74 65 14 06 FFFFFF81 10 FFFFFF81
   18 FFFFFF81 1A 14 03 63 FFFFFF81 11 08 07 6C FFFFFF81 0D FFFFFFC0 00 FFFFFF81
   12 10 06 15 FFFFFF81 13 FFFFFF81 15 63 09 03 FFFFFF81 14 04 02 09
   46 75 6E 63 74 69 6F 6E 31 10 03 15 FFFFFF81 16 09 03
   FFFFFF81 17 04 02 03 49 6E 74 08 08 FFFFFF81 19 FFFFFF81 0D FFFFFFC0 00
   FFFFFF81 15 01 05 73 74 61 72 74 08 08 FFFFFF81 1B FFFFFF81 0D FFFFFFC0
   00 FFFFFF81 15 01 03 65 6E 64 08 09 FFFFFF81 1D 09 FFFFFF91 FFFFFF80 FFFFFF84
   00 FFFFFF81 1E 01 10 66 75 74 75 72 65 24 64 65 66 61
   75 6C 74 24 32 15 04 FFFFFF81 1F FFFFFF81 2D 14 04 FFFFFF81 20 FFFFFF81
   2A 2A 03 1E FFFFFF81 21 2B 02 FFFFFF81 22 10 04 FFFFFF81 23 FFFFFF81 28
   0D 02 FFFFFF81 24 0A 04 FFFFFF81 25 FFFFFF81 26 01 09 75 6E 63 68
   65 63 6B 65 64 0A 03 FFFFFF81 27 04 01 0A 61 6E 6E 6F
   74 61 74 69 6F 6E 09 04 FFFFFF81 29 FFFFFF81 24 02 11 75 6E
   63 68 65 63 6B 65 64 56 61 72 69 61 6E 63 65 08
   08 6C FFFFFF81 1C FFFFFF84 FFFFFFC0 00 FFFFFF81 2B 10 04 15 44 FFFFFF81 2C 10
   03 37 FFFFFF81 2D 04 09 39 FFFFFF81 1C FFFFFF84 FFFFFF80 FFFFFF80 FFFFFFC2 00 3A 08
   09 FFFFFF81 2F 09 FFFFFF91 FFFFFF80 FFFFFF84 00 FFFFFF81 30 01 0F 73 70 61 77
   6E 24 64 65 66 61 75 6C 74 24 32 14 04 FFFFFF81 31 FFFFFF81
   32 2A 03 68 FFFFFF81 21 08 07 6C FFFFFF81 2E FFFFFF84 FFFFFFC0 00 6D 
  InnerClass: 
   public final $anonfun$2=class scala/concurrent/ops$$anonfun$2 of class scala/concurrent/ops
   public final $anonfun$1=class scala/concurrent/ops$$anonfun$1 of class scala/concurrent/ops
   public final $anonfun$par$2=class scala/concurrent/ops$$anonfun$par$2 of class scala/concurrent/ops
   public final $anonfun$par$1=class scala/concurrent/ops$$anonfun$par$1 of class scala/concurrent/ops
   public final $anonfun$replicate$2=class scala/concurrent/ops$$anonfun$replicate$2 of class scala/concurrent/ops
   public final $anonfun$replicate$1=class scala/concurrent/ops$$anonfun$replicate$1 of class scala/concurrent/ops
   public final $anonfun$getOrThrow$2=class scala/concurrent/ops$$anonfun$getOrThrow$2 of class scala/concurrent/ops
   public final $anonfun$getOrThrow$1=class scala/concurrent/ops$$anonfun$getOrThrow$1 of class scala/concurrent/ops
  minor version: 0
  major version: 49
  Constant pool:
Asciz	SourceFile;
Asciz	ops.scala;
Asciz	spawn$default$2;
Asciz	(Lscala/Function0;)Lscala/concurrent/TaskRunner;;
Asciz	Code;
Asciz	scala/concurrent/ops$;
class	scala/concurrent/ops$
Asciz	MODULE$;
Asciz	Lscala/concurrent/ops$;;
NameAndType	MODULE$:Lscala/concurrent/ops$;
Field	scala/concurrent/ops$.MODULE$:Lscala/concurrent/ops$;
NameAndType	spawn$default$2:(Lscala/Function0;)Lscala/concurrent/TaskRunner;
Method	scala/concurrent/ops$.spawn$default$2:(Lscala/Function0;)Lscala/concurrent/TaskRunner;
Asciz	future$default$2;
Asciz	(Lscala/Function0;)Lscala/concurrent/FutureTaskRunner;;
NameAndType	future$default$2:(Lscala/Function0;)Lscala/concurrent/FutureTaskRunner;
Method	scala/concurrent/ops$.future$default$2:(Lscala/Function0;)Lscala/concurrent/FutureTaskRunner;
Asciz	replicate;
Asciz	(IILscala/Function1;)V;
NameAndType	replicate:(IILscala/Function1;)V
Method	scala/concurrent/ops$.replicate:(IILscala/Function1;)V
Asciz	(IILscala/Function1<Ljava/lang/Integer;Ljava/lang/Object;>;)V;
Asciz	Signature;
Asciz	par;
Asciz	(Lscala/Function0;Lscala/Function0;)Lscala/Tuple2;;
NameAndType	par:(Lscala/Function0;Lscala/Function0;)Lscala/Tuple2;
Method	scala/concurrent/ops$.par:(Lscala/Function0;Lscala/Function0;)Lscala/Tuple2;
Asciz	<A:Ljava/lang/Object;B:Ljava/lang/Object;>(Lscala/Function0<TA;>;Lscala/Function0<TB;>;)Lscala/Tuple2<TA;TB;>;;
Asciz	future;
Asciz	(Lscala/Function0;Lscala/concurrent/FutureTaskRunner;)Lscala/Function0;;
NameAndType	future:(Lscala/Function0;Lscala/concurrent/FutureTaskRunner;)Lscala/Function0;
Method	scala/concurrent/ops$.future:(Lscala/Function0;Lscala/concurrent/FutureTaskRunner;)Lscala/Function0;
Asciz	<A:Ljava/lang/Object;>(Lscala/Function0<TA;>;Lscala/concurrent/FutureTaskRunner;)Lscala/Function0<TA;>;;
Asciz	spawn;
Asciz	(Lscala/Function0;Lscala/concurrent/TaskRunner;)V;
NameAndType	spawn:(Lscala/Function0;Lscala/concurrent/TaskRunner;)V
Method	scala/concurrent/ops$.spawn:(Lscala/Function0;Lscala/concurrent/TaskRunner;)V
Asciz	(Lscala/Function0<Ljava/lang/Object;>;Lscala/concurrent/TaskRunner;)V;
Asciz	getOrThrow;
Asciz	(Lscala/Either;)Ljava/lang/Object;;
NameAndType	getOrThrow:(Lscala/Either;)Ljava/lang/Object;
Method	scala/concurrent/ops$.getOrThrow:(Lscala/Either;)Ljava/lang/Object;
Asciz	<T:Ljava/lang/Throwable;A:Ljava/lang/Object;>(Lscala/Either<TT;TA;>;)TA;;
Asciz	tryCatchEx;
Asciz	(Lscala/Function0;)Lscala/Either;;
NameAndType	tryCatchEx:(Lscala/Function0;)Lscala/Either;
Method	scala/concurrent/ops$.tryCatchEx:(Lscala/Function0;)Lscala/Either;
Asciz	<A:Ljava/lang/Object;>(Lscala/Function0<TA;>;)Lscala/Either<Ljava/lang/Exception;TA;>;;
Asciz	tryCatch;
NameAndType	tryCatch:(Lscala/Function0;)Lscala/Either;
Method	scala/concurrent/ops$.tryCatch:(Lscala/Function0;)Lscala/Either;
Asciz	<A:Ljava/lang/Object;>(Lscala/Function0<TA;>;)Lscala/Either<Ljava/lang/Throwable;TA;>;;
Asciz	defaultRunner;
Asciz	()Lscala/concurrent/FutureTaskRunner;;
NameAndType	defaultRunner:()Lscala/concurrent/FutureTaskRunner;
Method	scala/concurrent/ops$.defaultRunner:()Lscala/concurrent/FutureTaskRunner;
Asciz	ScalaSig;
Asciz	InnerClasses;
Asciz	scala/concurrent/ops$$anonfun$2;
class	scala/concurrent/ops$$anonfun$2
Asciz	scala/concurrent/ops;
class	scala/concurrent/ops
Asciz	$anonfun$2;
Asciz	scala/concurrent/ops$$anonfun$1;
class	scala/concurrent/ops$$anonfun$1
Asciz	$anonfun$1;
Asciz	scala/concurrent/ops$$anonfun$par$2;
class	scala/concurrent/ops$$anonfun$par$2
Asciz	$anonfun$par$2;
Asciz	scala/concurrent/ops$$anonfun$par$1;
class	scala/concurrent/ops$$anonfun$par$1
Asciz	$anonfun$par$1;
Asciz	scala/concurrent/ops$$anonfun$replicate$2;
class	scala/concurrent/ops$$anonfun$replicate$2
Asciz	$anonfun$replicate$2;
Asciz	scala/concurrent/ops$$anonfun$replicate$1;
class	scala/concurrent/ops$$anonfun$replicate$1
Asciz	$anonfun$replicate$1;
Asciz	scala/concurrent/ops$$anonfun$getOrThrow$2;
class	scala/concurrent/ops$$anonfun$getOrThrow$2
Asciz	$anonfun$getOrThrow$2;
Asciz	scala/concurrent/ops$$anonfun$getOrThrow$1;
class	scala/concurrent/ops$$anonfun$getOrThrow$1
Asciz	$anonfun$getOrThrow$1;
Asciz	java/lang/Object;
class	java/lang/Object

{
public static final scala.concurrent.TaskRunner spawn$default$2(scala.Function0);
  Signature: (Lscala/Function0;)Lscala/concurrent/TaskRunner;
  Code:
   Stack=2, Locals=1, Args_size=1
	getstatic	Field scala/concurrent/ops$.MODULE$:Lscala/concurrent/ops$;
	aload_0
	invokevirtual	Method scala/concurrent/ops$.spawn$default$2:(Lscala/Function0;)Lscala/concurrent/TaskRunner;
	areturn
  Labels:

public static final scala.concurrent.FutureTaskRunner future$default$2(scala.Function0);
  Signature: (Lscala/Function0;)Lscala/concurrent/FutureTaskRunner;
  Code:
   Stack=2, Locals=1, Args_size=1
	getstatic	Field scala/concurrent/ops$.MODULE$:Lscala/concurrent/ops$;
	aload_0
	invokevirtual	Method scala/concurrent/ops$.future$default$2:(Lscala/Function0;)Lscala/concurrent/FutureTaskRunner;
	areturn
  Labels:

public static final void replicate(int, int, scala.Function1);
  Signature: (IILscala/Function1;)V
  Code:
   Stack=4, Locals=3, Args_size=3
	getstatic	Field scala/concurrent/ops$.MODULE$:Lscala/concurrent/ops$;
	iload_0
	iload_1
	aload_2
	invokevirtual	Method scala/concurrent/ops$.replicate:(IILscala/Function1;)V
	return
  Labels:
  Signature: length = 0x2
   00 16 

public static final scala.Tuple2 par(scala.Function0, scala.Function0);
  Signature: (Lscala/Function0;Lscala/Function0;)Lscala/Tuple2;
  Code:
   Stack=3, Locals=2, Args_size=2
	getstatic	Field scala/concurrent/ops$.MODULE$:Lscala/concurrent/ops$;
	aload_0
	aload_1
	invokevirtual	Method scala/concurrent/ops$.par:(Lscala/Function0;Lscala/Function0;)Lscala/Tuple2;
	areturn
  Labels:
  Signature: length = 0x2
   00 1C 

public static final scala.Function0 future(scala.Function0, scala.concurrent.FutureTaskRunner);
  Signature: (Lscala/Function0;Lscala/concurrent/FutureTaskRunner;)Lscala/Function0;
  Code:
   Stack=3, Locals=2, Args_size=2
	getstatic	Field scala/concurrent/ops$.MODULE$:Lscala/concurrent/ops$;
	aload_0
	aload_1
	invokevirtual	Method scala/concurrent/ops$.future:(Lscala/Function0;Lscala/concurrent/FutureTaskRunner;)Lscala/Function0;
	areturn
  Labels:
  Signature: length = 0x2
   00 21 

public static final void spawn(scala.Function0, scala.concurrent.TaskRunner);
  Signature: (Lscala/Function0;Lscala/concurrent/TaskRunner;)V
  Code:
   Stack=3, Locals=2, Args_size=2
	getstatic	Field scala/concurrent/ops$.MODULE$:Lscala/concurrent/ops$;
	aload_0
	aload_1
	invokevirtual	Method scala/concurrent/ops$.spawn:(Lscala/Function0;Lscala/concurrent/TaskRunner;)V
	return
  Labels:
  Signature: length = 0x2
   00 26 

public static final java.lang.Object getOrThrow(scala.Either);
  Signature: (Lscala/Either;)Ljava/lang/Object;
  Code:
   Stack=2, Locals=1, Args_size=1
	getstatic	Field scala/concurrent/ops$.MODULE$:Lscala/concurrent/ops$;
	aload_0
	invokevirtual	Method scala/concurrent/ops$.getOrThrow:(Lscala/Either;)Ljava/lang/Object;
	areturn
  Labels:
  Signature: length = 0x2
   00 2B 

public static final scala.Either tryCatchEx(scala.Function0);
  Signature: (Lscala/Function0;)Lscala/Either;
  Code:
   Stack=2, Locals=1, Args_size=1
	getstatic	Field scala/concurrent/ops$.MODULE$:Lscala/concurrent/ops$;
	aload_0
	invokevirtual	Method scala/concurrent/ops$.tryCatchEx:(Lscala/Function0;)Lscala/Either;
	areturn
  Labels:
  Signature: length = 0x2
   00 30 

public static final scala.Either tryCatch(scala.Function0);
  Signature: (Lscala/Function0;)Lscala/Either;
  Code:
   Stack=2, Locals=1, Args_size=1
	getstatic	Field scala/concurrent/ops$.MODULE$:Lscala/concurrent/ops$;
	aload_0
	invokevirtual	Method scala/concurrent/ops$.tryCatch:(Lscala/Function0;)Lscala/Either;
	areturn
  Labels:
  Signature: length = 0x2
   00 34 

public static final scala.concurrent.FutureTaskRunner defaultRunner();
  Signature: ()Lscala/concurrent/FutureTaskRunner;
  Code:
   Stack=1, Locals=0, Args_size=0
	getstatic	Field scala/concurrent/ops$.MODULE$:Lscala/concurrent/ops$;
	invokevirtual	Method scala/concurrent/ops$.defaultRunner:()Lscala/concurrent/FutureTaskRunner;
	areturn
  Labels:

}

