Compiled from "pilib.scala"
public class scala.concurrent.pilib$Product extends java.lang.Object implements scala.ScalaObject
  SourceFile: "pilib.scala"
  Signature: length = 0x2
   00 28 
  Scala: length = 0x
   
  InnerClass: 
   public #47= #44 of #46; //GP=class scala/concurrent/pilib$GP of class scala/concurrent/pilib
   public #48= #32 of #46; //Chan=class scala/concurrent/pilib$Chan of class scala/concurrent/pilib
   public #49= #15 of #46; //Product=class scala/concurrent/pilib$Product of class scala/concurrent/pilib
  minor version: 0
  major version: 49
  Constant pool:
const #1 = Asciz	SourceFile;
const #2 = Asciz	pilib.scala;
const #3 = Asciz	v;
const #4 = Asciz	Ljava/lang/Object;;
const #5 = Asciz	TA;;
const #6 = Asciz	Signature;
const #7 = Asciz	c;
const #8 = Asciz	Lscala/concurrent/pilib$Chan;;
const #9 = Asciz	Lscala/concurrent/pilib$Chan<TA;>;;
const #10 = Asciz	<init>;
const #11 = Asciz	(Lscala/concurrent/pilib$Chan;Ljava/lang/Object;)V;
const #12 = Asciz	Code;
const #13 = Asciz	LineNumberTable;
const #14 = Asciz	scala/concurrent/pilib$Product;
const #15 = class	#14;	//  scala/concurrent/pilib$Product
const #16 = NameAndType	#7:#8;//  c:Lscala/concurrent/pilib$Chan;
const #17 = Field	#15.#16;	//  scala/concurrent/pilib$Product.c:Lscala/concurrent/pilib$Chan;
const #18 = NameAndType	#3:#4;//  v:Ljava/lang/Object;
const #19 = Field	#15.#18;	//  scala/concurrent/pilib$Product.v:Ljava/lang/Object;
const #20 = Asciz	java/lang/Object;
const #21 = class	#20;	//  java/lang/Object
const #22 = Asciz	()V;
const #23 = NameAndType	#10:#22;//  "<init>":()V
const #24 = Method	#21.#23;	//  java/lang/Object."<init>":()V
const #25 = Asciz	this;
const #26 = Asciz	Lscala/concurrent/pilib$Product;;
const #27 = Asciz	LocalVariableTable;
const #28 = Asciz	(Lscala/concurrent/pilib$Chan<TA;>;TA;)V;
const #29 = Asciz	$times;
const #30 = Asciz	(Lscala/Function0;)Lscala/concurrent/pilib$GP;;
const #31 = Asciz	scala/concurrent/pilib$Chan;
const #32 = class	#31;	//  scala/concurrent/pilib$Chan
const #33 = Asciz	output;
const #34 = Asciz	(Ljava/lang/Object;Lscala/Function0;)Lscala/concurrent/pilib$GP;;
const #35 = NameAndType	#33:#34;//  output:(Ljava/lang/Object;Lscala/Function0;)Lscala/concurrent/pilib$GP;
const #36 = Method	#32.#35;	//  scala/concurrent/pilib$Chan.output:(Ljava/lang/Object;Lscala/Function0;)Lscala/concurrent/pilib$GP;
const #37 = Asciz	f;
const #38 = Asciz	Lscala/Function0;;
const #39 = Asciz	<B:Ljava/lang/Object;>(Lscala/Function0<TB;>;)Lscala/concurrent/pilib$GP<TB;>;;
const #40 = Asciz	<A:Ljava/lang/Object;>Ljava/lang/Object;Lscala/ScalaObject;;
const #41 = Asciz	Scala;
const #42 = Asciz	InnerClasses;
const #43 = Asciz	scala/concurrent/pilib$GP;
const #44 = class	#43;	//  scala/concurrent/pilib$GP
const #45 = Asciz	scala/concurrent/pilib;
const #46 = class	#45;	//  scala/concurrent/pilib
const #47 = Asciz	GP;
const #48 = Asciz	Chan;
const #49 = Asciz	Product;
const #50 = Asciz	scala/ScalaObject;
const #51 = class	#50;	//  scala/ScalaObject

{
public scala.concurrent.pilib$Product(scala.concurrent.pilib$Chan, java.lang.Object);
  Code:
   Stack=2, Locals=3, Args_size=3
   0:	aload_0
   1:	aload_1
   2:	putfield	#17; //Field c:Lscala/concurrent/pilib$Chan;
   5:	aload_0
   6:	aload_2
   7:	putfield	#19; //Field v:Ljava/lang/Object;
   10:	aload_0
   11:	invokespecial	#24; //Method java/lang/Object."<init>":()V
   14:	return
  LineNumberTable: 
   line 120: 0

  LocalVariableTable: 
   Start  Length  Slot  Name   Signature
   0      15      0    this       Lscala/concurrent/pilib$Product;
   0      15      1    c       Lscala/concurrent/pilib$Chan;
   0      15      2    v       Ljava/lang/Object;

  Signature: length = 0x2
   00 1C 

public scala.concurrent.pilib$GP $times(scala.Function0);
  Code:
   Stack=3, Locals=2, Args_size=2
   0:	aload_0
   1:	getfield	#17; //Field c:Lscala/concurrent/pilib$Chan;
   4:	aload_0
   5:	getfield	#19; //Field v:Ljava/lang/Object;
   8:	aload_1
   9:	invokevirtual	#36; //Method scala/concurrent/pilib$Chan.output:(Ljava/lang/Object;Lscala/Function0;)Lscala/concurrent/pilib$GP;
   12:	areturn
  LineNumberTable: 
   line 121: 0

  LocalVariableTable: 
   Start  Length  Slot  Name   Signature
   0      13      0    this       Lscala/concurrent/pilib$Product;
   0      13      1    f       Lscala/Function0;

  Signature: length = 0x2
   00 27 

}

