Compiled from "pilib.scala"
public final class scala.concurrent.pilib$$anon$1 extends scala.concurrent.pilib$Spawn
  SourceFile: "pilib.scala"
  Scala: length = 0x
   
  InnerClass: 
   public abstract Spawn=class scala/concurrent/pilib$Spawn of class scala/concurrent/pilib
   public final $anon$1=class scala/concurrent/pilib$$anon$1 of class scala/concurrent/pilib
  minor version: 0
  major version: 49
  Constant pool:
Asciz	SourceFile;
Asciz	pilib.scala;
Asciz	<init>;
Asciz	()V;
Asciz	Code;
Asciz	LineNumberTable;
Asciz	scala/concurrent/pilib$Spawn;
class	scala/concurrent/pilib$Spawn
NameAndType	"<init>":()V
Method	scala/concurrent/pilib$Spawn."<init>":()V
Asciz	$greater;
Asciz	$bar;
Asciz	(Lscala/Function0;)Lscala/concurrent/pilib$Spawn;;
Asciz	scala/concurrent/TaskRunners$;
class	scala/concurrent/TaskRunners$
Asciz	MODULE$;
Asciz	Lscala/concurrent/TaskRunners$;;
NameAndType	MODULE$:Lscala/concurrent/TaskRunners$;
Field	scala/concurrent/TaskRunners$.MODULE$:Lscala/concurrent/TaskRunners$;
Asciz	threadRunner;
Asciz	()Lscala/concurrent/FutureTaskRunner;;
NameAndType	threadRunner:()Lscala/concurrent/FutureTaskRunner;
Method	scala/concurrent/TaskRunners$.threadRunner:()Lscala/concurrent/FutureTaskRunner;
Asciz	scala/concurrent/TaskRunner;
class	scala/concurrent/TaskRunner
Asciz	functionAsTask;
Asciz	(Lscala/Function0;)Ljava/lang/Object;;
NameAndType	functionAsTask:(Lscala/Function0;)Ljava/lang/Object;
InterfaceMethod	scala/concurrent/TaskRunner.functionAsTask:(Lscala/Function0;)Ljava/lang/Object;
Asciz	execute;
Asciz	(Ljava/lang/Object;)V;
NameAndType	execute:(Ljava/lang/Object;)V
InterfaceMethod	scala/concurrent/TaskRunner.execute:(Ljava/lang/Object;)V
Asciz	this;
Asciz	Lscala/concurrent/pilib$$anon$1;;
Asciz	p;
Asciz	Lscala/Function0;;
Asciz	LocalVariableTable;
Asciz	(Lscala/Function0<Ljava/lang/Object;>;)Lscala/concurrent/pilib$Spawn;;
Asciz	Signature;
Asciz	$less;
Asciz	Scala;
Asciz	InnerClasses;
Asciz	scala/concurrent/pilib;
class	scala/concurrent/pilib
Asciz	Spawn;
Asciz	scala/concurrent/pilib$$anon$1;
class	scala/concurrent/pilib$$anon$1
Asciz	$anon$1;

{
public scala.concurrent.pilib$$anon$1();
  Signature: ()V
  Code:
   Stack=1, Locals=1, Args_size=1
	aload_0
	invokespecial	Method scala/concurrent/pilib$Spawn."<init>":()V
	return
  Labels:

public void $greater();
  Signature: ()V
  Code:
   Stack=0, Locals=1, Args_size=1
	return
  Labels:

public scala.concurrent.pilib$Spawn $bar(scala.Function0);
  Signature: (Lscala/Function0;)Lscala/concurrent/pilib$Spawn;
  Code:
   Stack=3, Locals=3, Args_size=2
	getstatic	Field scala/concurrent/TaskRunners$.MODULE$:Lscala/concurrent/TaskRunners$;
	invokevirtual	Method scala/concurrent/TaskRunners$.threadRunner:()Lscala/concurrent/FutureTaskRunner;
	astore_2
	aload_2
	aload_2
	aload_1
	invokeinterface	InterfaceMethod scala/concurrent/TaskRunner.functionAsTask:(Lscala/Function0;)Ljava/lang/Object;
	invokeinterface	InterfaceMethod scala/concurrent/TaskRunner.execute:(Ljava/lang/Object;)V
	aload_0
	areturn
  Labels:
  LocalVariableTable: 
   Start  Length  Slot  Name   Signature
   0      22      0    this       Lscala/concurrent/pilib$$anon$1;
   0      22      1    p       Lscala/Function0;

  Signature: length = 0x2
   00 27 

public scala.concurrent.pilib$Spawn $less(scala.Function0);
  Signature: (Lscala/Function0;)Lscala/concurrent/pilib$Spawn;
  Code:
   Stack=3, Locals=3, Args_size=2
	getstatic	Field scala/concurrent/TaskRunners$.MODULE$:Lscala/concurrent/TaskRunners$;
	invokevirtual	Method scala/concurrent/TaskRunners$.threadRunner:()Lscala/concurrent/FutureTaskRunner;
	astore_2
	aload_2
	aload_2
	aload_1
	invokeinterface	InterfaceMethod scala/concurrent/TaskRunner.functionAsTask:(Lscala/Function0;)Ljava/lang/Object;
	invokeinterface	InterfaceMethod scala/concurrent/TaskRunner.execute:(Ljava/lang/Object;)V
	aload_0
	areturn
  Labels:
  LocalVariableTable: 
   Start  Length  Slot  Name   Signature
   0      22      0    this       Lscala/concurrent/pilib$$anon$1;
   0      22      1    p       Lscala/Function0;

  Signature: length = 0x2
   00 27 

}

