Compiled from "pilib.scala"
public final class scala.concurrent.pilib$Sum$ extends java.lang.Object implements scala.Function1,scala.ScalaObject
  SourceFile: "pilib.scala"
  Scala: length = 0x
   
  InnerClass: 
   public Sum=class scala/concurrent/pilib$Sum of class scala/concurrent/pilib
  minor version: 0
  major version: 49
  Constant pool:
Asciz	SourceFile;
Asciz	pilib.scala;
Asciz	Scala;
Asciz	MODULE$;
Asciz	Lscala/concurrent/pilib$Sum$;;
Asciz	<clinit>;
Asciz	()V;
Asciz	Code;
Asciz	scala/concurrent/pilib$Sum$;
class	scala/concurrent/pilib$Sum$
Asciz	<init>;
NameAndType	"<init>":()V
Method	scala/concurrent/pilib$Sum$."<init>":()V
Asciz	toString;
Asciz	()Ljava/lang/String;;
Asciz	LineNumberTable;
Asciz	scala/Function1$class;
class	scala/Function1$class
Asciz	(Lscala/Function1;)Ljava/lang/String;;
NameAndType	toString:(Lscala/Function1;)Ljava/lang/String;
Method	scala/Function1$class.toString:(Lscala/Function1;)Ljava/lang/String;
Asciz	compose;
Asciz	(Lscala/Function1;)Lscala/Function1;;
Asciz	(Lscala/Function1;Lscala/Function1;)Lscala/Function1;;
NameAndType	compose:(Lscala/Function1;Lscala/Function1;)Lscala/Function1;
Method	scala/Function1$class.compose:(Lscala/Function1;Lscala/Function1;)Lscala/Function1;
Asciz	this;
Asciz	g;
Asciz	Lscala/Function1;;
Asciz	LocalVariableTable;
Asciz	andThen;
NameAndType	andThen:(Lscala/Function1;Lscala/Function1;)Lscala/Function1;
Method	scala/Function1$class.andThen:(Lscala/Function1;Lscala/Function1;)Lscala/Function1;
Asciz	unapply;
Asciz	(Lscala/concurrent/pilib$Sum;)Lscala/Option;;
Asciz	java/lang/Object;
class	java/lang/Object
Asciz	equals;
Asciz	(Ljava/lang/Object;)Z;
NameAndType	equals:(Ljava/lang/Object;)Z
Method	java/lang/Object.equals:(Ljava/lang/Object;)Z
Asciz	scala/None$;
class	scala/None$
Asciz	Lscala/None$;;
NameAndType	MODULE$:Lscala/None$;
Field	scala/None$.MODULE$:Lscala/None$;
Asciz	scala/Some;
class	scala/Some
Asciz	scala/concurrent/pilib$Sum;
class	scala/concurrent/pilib$Sum
Asciz	gs;
Asciz	()Lscala/collection/immutable/List;;
NameAndType	gs:()Lscala/collection/immutable/List;
Method	scala/concurrent/pilib$Sum.gs:()Lscala/collection/immutable/List;
Asciz	(Ljava/lang/Object;)V;
NameAndType	"<init>":(Ljava/lang/Object;)V
Method	scala/Some."<init>":(Ljava/lang/Object;)V
Asciz	x$0;
Asciz	Lscala/concurrent/pilib$Sum;;
Asciz	apply;
Asciz	(Lscala/collection/immutable/List;)Lscala/concurrent/pilib$Sum;;
Asciz	(Lscala/collection/immutable/List;)V;
NameAndType	"<init>":(Lscala/collection/immutable/List;)V
Method	scala/concurrent/pilib$Sum."<init>":(Lscala/collection/immutable/List;)V
Asciz	Lscala/collection/immutable/List;;
Asciz	(Ljava/lang/Object;)Ljava/lang/Object;;
Asciz	scala/collection/immutable/List;
class	scala/collection/immutable/List
NameAndType	apply:(Lscala/collection/immutable/List;)Lscala/concurrent/pilib$Sum;
Method	scala/concurrent/pilib$Sum$.apply:(Lscala/collection/immutable/List;)Lscala/concurrent/pilib$Sum;
Asciz	v1;
Asciz	Ljava/lang/Object;;
Method	java/lang/Object."<init>":()V
NameAndType	MODULE$:Lscala/concurrent/pilib$Sum$;
Field	scala/concurrent/pilib$Sum$.MODULE$:Lscala/concurrent/pilib$Sum$;
Asciz	$init$;
Asciz	(Lscala/Function1;)V;
NameAndType	$init$:(Lscala/Function1;)V
Method	scala/Function1$class.$init$:(Lscala/Function1;)V
Asciz	InnerClasses;
Asciz	scala/concurrent/pilib;
class	scala/concurrent/pilib
Asciz	Sum;
Asciz	scala/Function1;
class	scala/Function1
Asciz	scala/ScalaObject;
class	scala/ScalaObject

{
public static final scala.concurrent.pilib$Sum$ MODULE$;
  Signature: Lscala/concurrent/pilib$Sum$;

public static {};
  Signature: ()V
  Code:
   Stack=1, Locals=0, Args_size=0
	new	class scala/concurrent/pilib$Sum$
	invokespecial	Method "<init>":()V
	return
  Labels:

public java.lang.String toString();
  Signature: ()Ljava/lang/String;
  Code:
   Stack=1, Locals=1, Args_size=1
	aload_0
	invokestatic	Method scala/Function1$class.toString:(Lscala/Function1;)Ljava/lang/String;
	areturn
  Labels:

public scala.Function1 compose(scala.Function1);
  Signature: (Lscala/Function1;)Lscala/Function1;
  Code:
   Stack=2, Locals=2, Args_size=2
	aload_0
	aload_1
	invokestatic	Method scala/Function1$class.compose:(Lscala/Function1;Lscala/Function1;)Lscala/Function1;
	areturn
  Labels:
  LocalVariableTable: 
   Start  Length  Slot  Name   Signature
   0      6      0    this       Lscala/concurrent/pilib$Sum$;
   0      6      1    g       Lscala/Function1;


public scala.Function1 andThen(scala.Function1);
  Signature: (Lscala/Function1;)Lscala/Function1;
  Code:
   Stack=2, Locals=2, Args_size=2
	aload_0
	aload_1
	invokestatic	Method scala/Function1$class.andThen:(Lscala/Function1;Lscala/Function1;)Lscala/Function1;
	areturn
  Labels:
  LocalVariableTable: 
   Start  Length  Slot  Name   Signature
   0      6      0    this       Lscala/concurrent/pilib$Sum$;
   0      6      1    g       Lscala/Function1;


public scala.Option unapply(scala.concurrent.pilib$Sum);
  Signature: (Lscala/concurrent/pilib$Sum;)Lscala/Option;
  Code:
   Stack=3, Locals=2, Args_size=2
	aload_1
	dup
	pop
	ifnull	l1 // getstatic
	aload_1
	aconst_null
	invokevirtual	Method java/lang/Object.equals:(Ljava/lang/Object;)Z
	ifeq	l2 // new
l1	getstatic	Field scala/None$.MODULE$:Lscala/None$;
	goto	l3 // areturn
l2	new	class scala/Some
	dup
	aload_1
	invokevirtual	Method scala/concurrent/pilib$Sum.gs:()Lscala/collection/immutable/List;
	invokespecial	Method scala/Some."<init>":(Ljava/lang/Object;)V
l3	areturn
  Labels:
   	l1 = 14 // getstatic
   	l2 = 20 // new
   	l3 = 31 // areturn
  LocalVariableTable: 
   Start  Length  Slot  Name   Signature
   0      32      0    this       Lscala/concurrent/pilib$Sum$;
   0      32      1    x$0       Lscala/concurrent/pilib$Sum;


public scala.concurrent.pilib$Sum apply(scala.collection.immutable.List);
  Signature: (Lscala/collection/immutable/List;)Lscala/concurrent/pilib$Sum;
  Code:
   Stack=3, Locals=2, Args_size=2
	new	class scala/concurrent/pilib$Sum
	dup
	aload_1
	invokespecial	Method scala/concurrent/pilib$Sum."<init>":(Lscala/collection/immutable/List;)V
	areturn
  Labels:
  LocalVariableTable: 
   Start  Length  Slot  Name   Signature
   0      9      0    this       Lscala/concurrent/pilib$Sum$;
   0      9      1    gs       Lscala/collection/immutable/List;


public java.lang.Object apply(java.lang.Object);
  Signature: (Ljava/lang/Object;)Ljava/lang/Object;
  Code:
   Stack=2, Locals=2, Args_size=2
	aload_0
	aload_1
	checkcast	class scala/collection/immutable/List
	invokevirtual	Method apply:(Lscala/collection/immutable/List;)Lscala/concurrent/pilib$Sum;
	areturn
  Labels:
  LocalVariableTable: 
   Start  Length  Slot  Name   Signature
   0      9      0    this       Lscala/concurrent/pilib$Sum$;
   0      9      1    v1       Ljava/lang/Object;


public scala.concurrent.pilib$Sum$();
  Signature: ()V
  Code:
   Stack=1, Locals=1, Args_size=1
	aload_0
	invokespecial	Method java/lang/Object."<init>":()V
	aload_0
	putstatic	Field MODULE$:Lscala/concurrent/pilib$Sum$;
	aload_0
	invokestatic	Method scala/Function1$class.$init$:(Lscala/Function1;)V
	return
  Labels:

}

