Compiled from "pilib.scala"
public class scala.concurrent.pilib$GP extends java.lang.Object implements scala.ScalaObject
  SourceFile: "pilib.scala"
  Signature: length = 0x2
   00 24 
  Scala: length = 0x
   
  InnerClass: 
   public #41= #19 of #40; //GP=class scala/concurrent/pilib$GP of class scala/concurrent/pilib
   public #42= #15 of #40; //UGP=class scala/concurrent/pilib$UGP of class scala/concurrent/pilib
   public #45= #44 of #40; //UChan=class scala/concurrent/pilib$UChan of class scala/concurrent/pilib
  minor version: 0
  major version: 49
  Constant pool:
const #1 = Asciz	SourceFile;
const #2 = Asciz	pilib.scala;
const #3 = Asciz	untyped;
const #4 = Asciz	Lscala/concurrent/pilib$UGP;;
const #5 = Asciz	<init>;
const #6 = Asciz	(Lscala/concurrent/pilib$UChan;ZLjava/lang/Object;Lscala/Function1;)V;
const #7 = Asciz	Code;
const #8 = Asciz	LineNumberTable;
const #9 = Asciz	java/lang/Object;
const #10 = class	#9;	//  java/lang/Object
const #11 = Asciz	()V;
const #12 = NameAndType	#5:#11;//  "<init>":()V
const #13 = Method	#10.#12;	//  java/lang/Object."<init>":()V
const #14 = Asciz	scala/concurrent/pilib$UGP;
const #15 = class	#14;	//  scala/concurrent/pilib$UGP
const #16 = NameAndType	#5:#6;//  "<init>":(Lscala/concurrent/pilib$UChan;ZLjava/lang/Object;Lscala/Function1;)V
const #17 = Method	#15.#16;	//  scala/concurrent/pilib$UGP."<init>":(Lscala/concurrent/pilib$UChan;ZLjava/lang/Object;Lscala/Function1;)V
const #18 = Asciz	scala/concurrent/pilib$GP;
const #19 = class	#18;	//  scala/concurrent/pilib$GP
const #20 = NameAndType	#3:#4;//  untyped:Lscala/concurrent/pilib$UGP;
const #21 = Field	#19.#20;	//  scala/concurrent/pilib$GP.untyped:Lscala/concurrent/pilib$UGP;
const #22 = Asciz	this;
const #23 = Asciz	Lscala/concurrent/pilib$GP;;
const #24 = Asciz	n;
const #25 = Asciz	Lscala/concurrent/pilib$UChan;;
const #26 = Asciz	polarity;
const #27 = Asciz	Z;
const #28 = Asciz	v;
const #29 = Asciz	Ljava/lang/Object;;
const #30 = Asciz	c;
const #31 = Asciz	Lscala/Function1;;
const #32 = Asciz	LocalVariableTable;
const #33 = Asciz	(Lscala/concurrent/pilib$UChan;ZLjava/lang/Object;Lscala/Function1<Ljava/lang/Object;Ta;>;)V;
const #34 = Asciz	Signature;
const #35 = Asciz	()Lscala/concurrent/pilib$UGP;;
const #36 = Asciz	<a:Ljava/lang/Object;>Ljava/lang/Object;Lscala/ScalaObject;;
const #37 = Asciz	Scala;
const #38 = Asciz	InnerClasses;
const #39 = Asciz	scala/concurrent/pilib;
const #40 = class	#39;	//  scala/concurrent/pilib
const #41 = Asciz	GP;
const #42 = Asciz	UGP;
const #43 = Asciz	scala/concurrent/pilib$UChan;
const #44 = class	#43;	//  scala/concurrent/pilib$UChan
const #45 = Asciz	UChan;
const #46 = Asciz	scala/ScalaObject;
const #47 = class	#46;	//  scala/ScalaObject

{
public scala.concurrent.pilib$GP(scala.concurrent.pilib$UChan, boolean, java.lang.Object, scala.Function1);
  Code:
   Stack=7, Locals=5, Args_size=5
   0:	aload_0
   1:	invokespecial	#13; //Method java/lang/Object."<init>":()V
   4:	aload_0
   5:	new	#15; //class scala/concurrent/pilib$UGP
   8:	dup
   9:	aload_1
   10:	iload_2
   11:	aload_3
   12:	aload	4
   14:	invokespecial	#17; //Method scala/concurrent/pilib$UGP."<init>":(Lscala/concurrent/pilib$UChan;ZLjava/lang/Object;Lscala/Function1;)V
   17:	putfield	#21; //Field untyped:Lscala/concurrent/pilib$UGP;
   20:	return
  LineNumberTable: 
   line 72: 0
   line 73: 4

  LocalVariableTable: 
   Start  Length  Slot  Name   Signature
   0      21      0    this       Lscala/concurrent/pilib$GP;
   0      21      1    n       Lscala/concurrent/pilib$UChan;
   0      21      2    polarity       Z
   0      21      3    v       Ljava/lang/Object;
   0      21      4    c       Lscala/Function1;

  Signature: length = 0x2
   00 21 

public scala.concurrent.pilib$UGP untyped();
  Code:
   Stack=1, Locals=1, Args_size=1
   0:	aload_0
   1:	getfield	#21; //Field untyped:Lscala/concurrent/pilib$UGP;
   4:	areturn
  LineNumberTable: 
   line 73: 0


}

