Compiled from "pilib.scala"
public class scala.concurrent.pilib$Product extends java.lang.Object implements scala.ScalaObject
  SourceFile: "pilib.scala"
  Scala: length = 0x
   
  Signature: length = 0x2
   00 29 
  InnerClass: 
   public GP=class scala/concurrent/pilib$GP of class scala/concurrent/pilib
   public Chan=class scala/concurrent/pilib$Chan of class scala/concurrent/pilib
   public Product=class scala/concurrent/pilib$Product of class scala/concurrent/pilib
  minor version: 0
  major version: 49
  Constant pool:
Asciz	SourceFile;
Asciz	pilib.scala;
Asciz	c;
Asciz	Lscala/concurrent/pilib$Chan;;
Asciz	Lscala/concurrent/pilib$Chan<TA;>;;
Asciz	Signature;
Asciz	v;
Asciz	Ljava/lang/Object;;
Asciz	TA;;
Asciz	$times;
Asciz	(Lscala/Function0;)Lscala/concurrent/pilib$GP;;
Asciz	Code;
Asciz	LineNumberTable;
Asciz	scala/concurrent/pilib$Product;
class	scala/concurrent/pilib$Product
NameAndType	c:Lscala/concurrent/pilib$Chan;
Field	scala/concurrent/pilib$Product.c:Lscala/concurrent/pilib$Chan;
NameAndType	v:Ljava/lang/Object;
Field	scala/concurrent/pilib$Product.v:Ljava/lang/Object;
Asciz	scala/concurrent/pilib$Chan;
class	scala/concurrent/pilib$Chan
Asciz	output;
Asciz	(Ljava/lang/Object;Lscala/Function0;)Lscala/concurrent/pilib$GP;;
NameAndType	output:(Ljava/lang/Object;Lscala/Function0;)Lscala/concurrent/pilib$GP;
Method	scala/concurrent/pilib$Chan.output:(Ljava/lang/Object;Lscala/Function0;)Lscala/concurrent/pilib$GP;
Asciz	this;
Asciz	Lscala/concurrent/pilib$Product;;
Asciz	f;
Asciz	Lscala/Function0;;
Asciz	LocalVariableTable;
Asciz	<B:Ljava/lang/Object;>(Lscala/Function0<TB;>;)Lscala/concurrent/pilib$GP<TB;>;;
Asciz	<init>;
Asciz	(Lscala/concurrent/pilib$Chan;Ljava/lang/Object;)V;
Asciz	java/lang/Object;
class	java/lang/Object
Asciz	()V;
NameAndType	"<init>":()V
Method	java/lang/Object."<init>":()V
Asciz	(Lscala/concurrent/pilib$Chan<TA;>;TA;)V;
Asciz	Scala;
Asciz	<A:Ljava/lang/Object;>Ljava/lang/Object;Lscala/ScalaObject;;
Asciz	InnerClasses;
Asciz	scala/concurrent/pilib$GP;
class	scala/concurrent/pilib$GP
Asciz	scala/concurrent/pilib;
class	scala/concurrent/pilib
Asciz	GP;
Asciz	Chan;
Asciz	Product;
Asciz	scala/ScalaObject;
class	scala/ScalaObject

{
private final scala.concurrent.pilib$Chan c;
  Signature: Lscala/concurrent/pilib$Chan;
  Signature: length = 0x2
   00 05 

private final java.lang.Object v;
  Signature: Ljava/lang/Object;
  Signature: length = 0x2
   00 09 

public scala.concurrent.pilib$GP $times(scala.Function0);
  Signature: (Lscala/Function0;)Lscala/concurrent/pilib$GP;
  Code:
   Stack=3, Locals=2, Args_size=2
	aload_0
	getfield	Field c:Lscala/concurrent/pilib$Chan;
	aload_0
	getfield	Field v:Ljava/lang/Object;
	aload_1
	invokevirtual	Method scala/concurrent/pilib$Chan.output:(Ljava/lang/Object;Lscala/Function0;)Lscala/concurrent/pilib$GP;
	areturn
  Labels:
  LocalVariableTable: 
   Start  Length  Slot  Name   Signature
   0      13      0    this       Lscala/concurrent/pilib$Product;
   0      13      1    f       Lscala/Function0;

  Signature: length = 0x2
   00 1F 

public scala.concurrent.pilib$Product(scala.concurrent.pilib$Chan, java.lang.Object);
  Signature: (Lscala/concurrent/pilib$Chan;Ljava/lang/Object;)V
  Code:
   Stack=2, Locals=3, Args_size=3
	aload_0
	aload_1
	putfield	Field c:Lscala/concurrent/pilib$Chan;
	aload_0
	aload_2
	putfield	Field v:Ljava/lang/Object;
	aload_0
	invokespecial	Method java/lang/Object."<init>":()V
	return
  Labels:
  LocalVariableTable: 
   Start  Length  Slot  Name   Signature
   0      15      0    this       Lscala/concurrent/pilib$Product;
   0      15      1    c       Lscala/concurrent/pilib$Chan;
   0      15      2    v       Ljava/lang/Object;

  Signature: length = 0x2
   00 27 

}

