Compiled from "pilib.scala"
public final class scala.concurrent.pilib$UGP$ extends java.lang.Object implements scala.Function4,scala.ScalaObject
  SourceFile: "pilib.scala"
  Scala: length = 0x
   
  InnerClass: 
   public UGP=class scala/concurrent/pilib$UGP of class scala/concurrent/pilib
   public UChan=class scala/concurrent/pilib$UChan of class scala/concurrent/pilib
  minor version: 0
  major version: 49
  Constant pool:
Asciz	SourceFile;
Asciz	pilib.scala;
Asciz	MODULE$;
Asciz	Lscala/concurrent/pilib$UGP$;;
Asciz	<clinit>;
Asciz	()V;
Asciz	Code;
Asciz	scala/concurrent/pilib$UGP$;
class	scala/concurrent/pilib$UGP$
Asciz	<init>;
NameAndType	"<init>":()V
Method	scala/concurrent/pilib$UGP$."<init>":()V
Asciz	toString;
Asciz	()Ljava/lang/String;;
Asciz	LineNumberTable;
Asciz	scala/Function4$class;
class	scala/Function4$class
Asciz	(Lscala/Function4;)Ljava/lang/String;;
NameAndType	toString:(Lscala/Function4;)Ljava/lang/String;
Method	scala/Function4$class.toString:(Lscala/Function4;)Ljava/lang/String;
Asciz	curried;
Asciz	()Lscala/Function1;;
Asciz	(Lscala/Function4;)Lscala/Function1;;
NameAndType	curried:(Lscala/Function4;)Lscala/Function1;
Method	scala/Function4$class.curried:(Lscala/Function4;)Lscala/Function1;
Asciz	curry;
NameAndType	curry:(Lscala/Function4;)Lscala/Function1;
Method	scala/Function4$class.curry:(Lscala/Function4;)Lscala/Function1;
Asciz	Deprecated;
Asciz	tupled;
NameAndType	tupled:(Lscala/Function4;)Lscala/Function1;
Method	scala/Function4$class.tupled:(Lscala/Function4;)Lscala/Function1;
Asciz	unapply;
Asciz	(Lscala/concurrent/pilib$UGP;)Lscala/Option;;
Asciz	scala/None$;
class	scala/None$
Asciz	Lscala/None$;;
NameAndType	MODULE$:Lscala/None$;
Field	scala/None$.MODULE$:Lscala/None$;
Asciz	scala/Some;
class	scala/Some
Asciz	scala/Tuple4;
class	scala/Tuple4
Asciz	scala/concurrent/pilib$UGP;
class	scala/concurrent/pilib$UGP
Asciz	n;
Asciz	()Lscala/concurrent/pilib$UChan;;
NameAndType	n:()Lscala/concurrent/pilib$UChan;
Method	scala/concurrent/pilib$UGP.n:()Lscala/concurrent/pilib$UChan;
Asciz	polarity;
Asciz	()Z;
NameAndType	polarity:()Z
Method	scala/concurrent/pilib$UGP.polarity:()Z
Asciz	scala/runtime/BoxesRunTime;
class	scala/runtime/BoxesRunTime
Asciz	boxToBoolean;
Asciz	(Z)Ljava/lang/Boolean;;
NameAndType	boxToBoolean:(Z)Ljava/lang/Boolean;
Method	scala/runtime/BoxesRunTime.boxToBoolean:(Z)Ljava/lang/Boolean;
Asciz	v;
Asciz	()Ljava/lang/Object;;
NameAndType	v:()Ljava/lang/Object;
Method	scala/concurrent/pilib$UGP.v:()Ljava/lang/Object;
Asciz	c;
NameAndType	c:()Lscala/Function1;
Method	scala/concurrent/pilib$UGP.c:()Lscala/Function1;
Asciz	(Ljava/lang/Object;Ljava/lang/Object;Ljava/lang/Object;Ljava/lang/Object;)V;
NameAndType	"<init>":(Ljava/lang/Object;Ljava/lang/Object;Ljava/lang/Object;Ljava/lang/Object;)V
Method	scala/Tuple4."<init>":(Ljava/lang/Object;Ljava/lang/Object;Ljava/lang/Object;Ljava/lang/Object;)V
Asciz	(Ljava/lang/Object;)V;
NameAndType	"<init>":(Ljava/lang/Object;)V
Method	scala/Some."<init>":(Ljava/lang/Object;)V
Asciz	this;
Asciz	x$0;
Asciz	Lscala/concurrent/pilib$UGP;;
Asciz	LocalVariableTable;
Asciz	apply;
Asciz	(Lscala/concurrent/pilib$UChan;ZLjava/lang/Object;Lscala/Function1;)Lscala/concurrent/pilib$UGP;;
Asciz	(Lscala/concurrent/pilib$UChan;ZLjava/lang/Object;Lscala/Function1;)V;
NameAndType	"<init>":(Lscala/concurrent/pilib$UChan;ZLjava/lang/Object;Lscala/Function1;)V
Method	scala/concurrent/pilib$UGP."<init>":(Lscala/concurrent/pilib$UChan;ZLjava/lang/Object;Lscala/Function1;)V
Asciz	Lscala/concurrent/pilib$UChan;;
Asciz	Z;
Asciz	Ljava/lang/Object;;
Asciz	Lscala/Function1;;
Asciz	(Ljava/lang/Object;Ljava/lang/Object;Ljava/lang/Object;Ljava/lang/Object;)Ljava/lang/Object;;
Asciz	scala/concurrent/pilib$UChan;
class	scala/concurrent/pilib$UChan
Asciz	unboxToBoolean;
Asciz	(Ljava/lang/Object;)Z;
NameAndType	unboxToBoolean:(Ljava/lang/Object;)Z
Method	scala/runtime/BoxesRunTime.unboxToBoolean:(Ljava/lang/Object;)Z
Asciz	scala/Function1;
class	scala/Function1
NameAndType	apply:(Lscala/concurrent/pilib$UChan;ZLjava/lang/Object;Lscala/Function1;)Lscala/concurrent/pilib$UGP;
Method	scala/concurrent/pilib$UGP$.apply:(Lscala/concurrent/pilib$UChan;ZLjava/lang/Object;Lscala/Function1;)Lscala/concurrent/pilib$UGP;
Asciz	v1;
Asciz	v2;
Asciz	v3;
Asciz	v4;
Asciz	java/lang/Object;
class	java/lang/Object
Method	java/lang/Object."<init>":()V
NameAndType	MODULE$:Lscala/concurrent/pilib$UGP$;
Field	scala/concurrent/pilib$UGP$.MODULE$:Lscala/concurrent/pilib$UGP$;
Asciz	$init$;
Asciz	(Lscala/Function4;)V;
NameAndType	$init$:(Lscala/Function4;)V
Method	scala/Function4$class.$init$:(Lscala/Function4;)V
Asciz	Scala;
Asciz	InnerClasses;
Asciz	scala/concurrent/pilib;
class	scala/concurrent/pilib
Asciz	UGP;
Asciz	UChan;
Asciz	scala/Function4;
class	scala/Function4
Asciz	scala/ScalaObject;
class	scala/ScalaObject

{
public static final scala.concurrent.pilib$UGP$ MODULE$;
  Signature: Lscala/concurrent/pilib$UGP$;

public static {};
  Signature: ()V
  Code:
   Stack=1, Locals=0, Args_size=0
	new	class scala/concurrent/pilib$UGP$
	invokespecial	Method "<init>":()V
	return
  Labels:

public java.lang.String toString();
  Signature: ()Ljava/lang/String;
  Code:
   Stack=1, Locals=1, Args_size=1
	aload_0
	invokestatic	Method scala/Function4$class.toString:(Lscala/Function4;)Ljava/lang/String;
	areturn
  Labels:

public scala.Function1 curried();
  Signature: ()Lscala/Function1;
  Code:
   Stack=1, Locals=1, Args_size=1
	aload_0
	invokestatic	Method scala/Function4$class.curried:(Lscala/Function4;)Lscala/Function1;
	areturn
  Labels:

public scala.Function1 curry();
  Signature: ()Lscala/Function1;
  Code:
   Stack=1, Locals=1, Args_size=1
	aload_0
	invokestatic	Method scala/Function4$class.curry:(Lscala/Function4;)Lscala/Function1;
	areturn
  Labels:
  Deprecated: true

public scala.Function1 tupled();
  Signature: ()Lscala/Function1;
  Code:
   Stack=1, Locals=1, Args_size=1
	aload_0
	invokestatic	Method scala/Function4$class.tupled:(Lscala/Function4;)Lscala/Function1;
	areturn
  Labels:

public scala.Option unapply(scala.concurrent.pilib$UGP);
  Signature: (Lscala/concurrent/pilib$UGP;)Lscala/Option;
  Code:
   Stack=8, Locals=3, Args_size=2
	aload_1
	ifnonnull	l1 // new
	getstatic	Field scala/None$.MODULE$:Lscala/None$;
	goto	l2 // areturn
l1	new	class scala/Some
	dup
	new	class scala/Tuple4
	dup
	aload_1
	invokevirtual	Method scala/concurrent/pilib$UGP.n:()Lscala/concurrent/pilib$UChan;
	aload_1
	invokevirtual	Method scala/concurrent/pilib$UGP.polarity:()Z
	istore_2
	iload_2
	invokestatic	Method scala/runtime/BoxesRunTime.boxToBoolean:(Z)Ljava/lang/Boolean;
	aload_1
	invokevirtual	Method scala/concurrent/pilib$UGP.v:()Ljava/lang/Object;
	aload_1
	invokevirtual	Method scala/concurrent/pilib$UGP.c:()Lscala/Function1;
	invokespecial	Method scala/Tuple4."<init>":(Ljava/lang/Object;Ljava/lang/Object;Ljava/lang/Object;Ljava/lang/Object;)V
	invokespecial	Method scala/Some."<init>":(Ljava/lang/Object;)V
l2	areturn
  Labels:
   	l1 = 10 // new
   	l2 = 45 // areturn
  LocalVariableTable: 
   Start  Length  Slot  Name   Signature
   0      46      0    this       Lscala/concurrent/pilib$UGP$;
   0      46      1    x$0       Lscala/concurrent/pilib$UGP;


public scala.concurrent.pilib$UGP apply(scala.concurrent.pilib$UChan, boolean, java.lang.Object, scala.Function1);
  Signature: (Lscala/concurrent/pilib$UChan;ZLjava/lang/Object;Lscala/Function1;)Lscala/concurrent/pilib$UGP;
  Code:
   Stack=6, Locals=5, Args_size=5
	new	class scala/concurrent/pilib$UGP
	dup
	aload_1
	iload_2
	aload_3
	aload	4
	invokespecial	Method scala/concurrent/pilib$UGP."<init>":(Lscala/concurrent/pilib$UChan;ZLjava/lang/Object;Lscala/Function1;)V
	areturn
  Labels:
  LocalVariableTable: 
   Start  Length  Slot  Name   Signature
   0      13      0    this       Lscala/concurrent/pilib$UGP$;
   0      13      1    n       Lscala/concurrent/pilib$UChan;
   0      13      2    polarity       Z
   0      13      3    v       Ljava/lang/Object;
   0      13      4    c       Lscala/Function1;


public java.lang.Object apply(java.lang.Object, java.lang.Object, java.lang.Object, java.lang.Object);
  Signature: (Ljava/lang/Object;Ljava/lang/Object;Ljava/lang/Object;Ljava/lang/Object;)Ljava/lang/Object;
  Code:
   Stack=5, Locals=5, Args_size=5
	aload_0
	aload_1
	checkcast	class scala/concurrent/pilib$UChan
	aload_2
	invokestatic	Method scala/runtime/BoxesRunTime.unboxToBoolean:(Ljava/lang/Object;)Z
	aload_3
	aload	4
	checkcast	class scala/Function1
	invokevirtual	Method apply:(Lscala/concurrent/pilib$UChan;ZLjava/lang/Object;Lscala/Function1;)Lscala/concurrent/pilib$UGP;
	areturn
  Labels:
  LocalVariableTable: 
   Start  Length  Slot  Name   Signature
   0      19      0    this       Lscala/concurrent/pilib$UGP$;
   0      19      1    v1       Ljava/lang/Object;
   0      19      2    v2       Ljava/lang/Object;
   0      19      3    v3       Ljava/lang/Object;
   0      19      4    v4       Ljava/lang/Object;


public scala.concurrent.pilib$UGP$();
  Signature: ()V
  Code:
   Stack=1, Locals=1, Args_size=1
	aload_0
	invokespecial	Method java/lang/Object."<init>":()V
	aload_0
	putstatic	Field MODULE$:Lscala/concurrent/pilib$UGP$;
	aload_0
	invokestatic	Method scala/Function4$class.$init$:(Lscala/Function4;)V
	return
  Labels:

}

