Compiled from "pilib.scala"
public final class scala.concurrent.pilib$$anonfun$matches$1 extends java.lang.Object implements scala.Function0,scala.ScalaObject,java.io.Serializable
  SourceFile: "pilib.scala"
  Scala: length = 0x
   
  InnerClass: 
   public #65= #46 of #64; //UChan=class scala/concurrent/pilib$UChan of class scala/concurrent/pilib
   public final #66= #15 of #64; //$anonfun$matches$1=class scala/concurrent/pilib$$anonfun$matches$1 of class scala/concurrent/pilib
  minor version: 0
  major version: 49
  Constant pool:
const #1 = Asciz	SourceFile;
const #2 = Asciz	pilib.scala;
const #3 = Asciz	v2$1;
const #4 = Asciz	Ljava/lang/Object;;
const #5 = Asciz	v1$1;
const #6 = Asciz	d1$1;
const #7 = Asciz	Z;
const #8 = Asciz	a1$1;
const #9 = Asciz	Lscala/concurrent/pilib$UChan;;
const #10 = Asciz	<init>;
const #11 = Asciz	(Lscala/concurrent/pilib$UChan;ZLjava/lang/Object;Ljava/lang/Object;)V;
const #12 = Asciz	Code;
const #13 = Asciz	LineNumberTable;
const #14 = Asciz	scala/concurrent/pilib$$anonfun$matches$1;
const #15 = class	#14;	//  scala/concurrent/pilib$$anonfun$matches$1
const #16 = NameAndType	#8:#9;//  a1$1:Lscala/concurrent/pilib$UChan;
const #17 = Field	#15.#16;	//  scala/concurrent/pilib$$anonfun$matches$1.a1$1:Lscala/concurrent/pilib$UChan;
const #18 = NameAndType	#6:#7;//  d1$1:Z
const #19 = Field	#15.#18;	//  scala/concurrent/pilib$$anonfun$matches$1.d1$1:Z
const #20 = NameAndType	#5:#4;//  v1$1:Ljava/lang/Object;
const #21 = Field	#15.#20;	//  scala/concurrent/pilib$$anonfun$matches$1.v1$1:Ljava/lang/Object;
const #22 = NameAndType	#3:#4;//  v2$1:Ljava/lang/Object;
const #23 = Field	#15.#22;	//  scala/concurrent/pilib$$anonfun$matches$1.v2$1:Ljava/lang/Object;
const #24 = Asciz	java/lang/Object;
const #25 = class	#24;	//  java/lang/Object
const #26 = Asciz	()V;
const #27 = NameAndType	#10:#26;//  "<init>":()V
const #28 = Method	#25.#27;	//  java/lang/Object."<init>":()V
const #29 = Asciz	scala/Function0$class;
const #30 = class	#29;	//  scala/Function0$class
const #31 = Asciz	$init$;
const #32 = Asciz	(Lscala/Function0;)V;
const #33 = NameAndType	#31:#32;//  $init$:(Lscala/Function0;)V
const #34 = Method	#30.#33;	//  scala/Function0$class.$init$:(Lscala/Function0;)V
const #35 = Asciz	apply;
const #36 = Asciz	()Ljava/lang/Object;;
const #37 = NameAndType	#35:#26;//  apply:()V
const #38 = Method	#15.#37;	//  scala/concurrent/pilib$$anonfun$matches$1.apply:()V
const #39 = Asciz	scala/runtime/BoxedUnit;
const #40 = class	#39;	//  scala/runtime/BoxedUnit
const #41 = Asciz	UNIT;
const #42 = Asciz	Lscala/runtime/BoxedUnit;;
const #43 = NameAndType	#41:#42;//  UNIT:Lscala/runtime/BoxedUnit;
const #44 = Field	#40.#43;	//  scala/runtime/BoxedUnit.UNIT:Lscala/runtime/BoxedUnit;
const #45 = Asciz	scala/concurrent/pilib$UChan;
const #46 = class	#45;	//  scala/concurrent/pilib$UChan
const #47 = Asciz	log;
const #48 = Asciz	()Lscala/Function1;;
const #49 = NameAndType	#47:#48;//  log:()Lscala/Function1;
const #50 = Method	#46.#49;	//  scala/concurrent/pilib$UChan.log:()Lscala/Function1;
const #51 = Asciz	scala/Function1;
const #52 = class	#51;	//  scala/Function1
const #53 = Asciz	(Ljava/lang/Object;)Ljava/lang/Object;;
const #54 = NameAndType	#35:#53;//  apply:(Ljava/lang/Object;)Ljava/lang/Object;
const #55 = InterfaceMethod	#52.#54;	//  scala/Function1.apply:(Ljava/lang/Object;)Ljava/lang/Object;
const #56 = Asciz	toString;
const #57 = Asciz	()Ljava/lang/String;;
const #58 = Asciz	(Lscala/Function0;)Ljava/lang/String;;
const #59 = NameAndType	#56:#58;//  toString:(Lscala/Function0;)Ljava/lang/String;
const #60 = Method	#30.#59;	//  scala/Function0$class.toString:(Lscala/Function0;)Ljava/lang/String;
const #61 = Asciz	Scala;
const #62 = Asciz	InnerClasses;
const #63 = Asciz	scala/concurrent/pilib;
const #64 = class	#63;	//  scala/concurrent/pilib
const #65 = Asciz	UChan;
const #66 = Asciz	$anonfun$matches$1;
const #67 = Asciz	scala/Function0;
const #68 = class	#67;	//  scala/Function0
const #69 = Asciz	scala/ScalaObject;
const #70 = class	#69;	//  scala/ScalaObject
const #71 = Asciz	java/io/Serializable;
const #72 = class	#71;	//  java/io/Serializable

{
public scala.concurrent.pilib$$anonfun$matches$1(scala.concurrent.pilib$UChan, boolean, java.lang.Object, java.lang.Object);
  Code:
   Stack=2, Locals=5, Args_size=5
   0:	aload_0
   1:	aload_1
   2:	putfield	#17; //Field a1$1:Lscala/concurrent/pilib$UChan;
   5:	aload_0
   6:	iload_2
   7:	putfield	#19; //Field d1$1:Z
   10:	aload_0
   11:	aload_3
   12:	putfield	#21; //Field v1$1:Ljava/lang/Object;
   15:	aload_0
   16:	aload	4
   18:	putfield	#23; //Field v2$1:Ljava/lang/Object;
   21:	aload_0
   22:	invokespecial	#28; //Method java/lang/Object."<init>":()V
   25:	aload_0
   26:	invokestatic	#34; //Method scala/Function0$class.$init$:(Lscala/Function0;)V
   29:	return
  LineNumberTable: 
   line 168: 0


public final java.lang.Object apply();
  Code:
   Stack=1, Locals=1, Args_size=1
   0:	aload_0
   1:	invokevirtual	#38; //Method apply:()V
   4:	getstatic	#44; //Field scala/runtime/BoxedUnit.UNIT:Lscala/runtime/BoxedUnit;
   7:	areturn
  LineNumberTable: 
   line 168: 0


public final void apply();
  Code:
   Stack=2, Locals=1, Args_size=1
   0:	aload_0
   1:	getfield	#19; //Field d1$1:Z
   4:	ifeq	27
   7:	aload_0
   8:	getfield	#17; //Field a1$1:Lscala/concurrent/pilib$UChan;
   11:	invokevirtual	#50; //Method scala/concurrent/pilib$UChan.log:()Lscala/Function1;
   14:	aload_0
   15:	getfield	#23; //Field v2$1:Ljava/lang/Object;
   18:	invokeinterface	#55,  2; //InterfaceMethod scala/Function1.apply:(Ljava/lang/Object;)Ljava/lang/Object;
   23:	pop
   24:	goto	44
   27:	aload_0
   28:	getfield	#17; //Field a1$1:Lscala/concurrent/pilib$UChan;
   31:	invokevirtual	#50; //Method scala/concurrent/pilib$UChan.log:()Lscala/Function1;
   34:	aload_0
   35:	getfield	#21; //Field v1$1:Ljava/lang/Object;
   38:	invokeinterface	#55,  2; //InterfaceMethod scala/Function1.apply:(Ljava/lang/Object;)Ljava/lang/Object;
   43:	pop
   44:	return
  LineNumberTable: 
   line 168: 0


public java.lang.String toString();
  Code:
   Stack=1, Locals=1, Args_size=1
   0:	aload_0
   1:	invokestatic	#60; //Method scala/Function0$class.toString:(Lscala/Function0;)Ljava/lang/String;
   4:	areturn
  LineNumberTable: 
   line 168: 0


}

