Compiled from "pilib.scala"
public class scala.concurrent.pilib$UGP extends java.lang.Object implements scala.ScalaObject,scala.Product,java.io.Serializable
  SourceFile: "pilib.scala"
  Scala: length = 0x
   
  InnerClass: 
   public UGP=class scala/concurrent/pilib$UGP of class scala/concurrent/pilib
   public UChan=class scala/concurrent/pilib$UChan of class scala/concurrent/pilib
  minor version: 0
  major version: 49
  Constant pool:
Asciz	SourceFile;
Asciz	pilib.scala;
Asciz	c;
Asciz	Lscala/Function1;;
Asciz	Lscala/Function1<Ljava/lang/Object;Ljava/lang/Object;>;;
Asciz	Signature;
Asciz	v;
Asciz	Ljava/lang/Object;;
Asciz	polarity;
Asciz	Z;
Asciz	n;
Asciz	Lscala/concurrent/pilib$UChan;;
Asciz	<init>;
Asciz	(Lscala/concurrent/pilib$UChan;ZLjava/lang/Object;Lscala/Function1;)V;
Asciz	Code;
Asciz	LineNumberTable;
Asciz	scala/concurrent/pilib$UGP;
class	scala/concurrent/pilib$UGP
NameAndType	n:Lscala/concurrent/pilib$UChan;
Field	scala/concurrent/pilib$UGP.n:Lscala/concurrent/pilib$UChan;
NameAndType	polarity:Z
Field	scala/concurrent/pilib$UGP.polarity:Z
NameAndType	v:Ljava/lang/Object;
Field	scala/concurrent/pilib$UGP.v:Ljava/lang/Object;
NameAndType	c:Lscala/Function1;
Field	scala/concurrent/pilib$UGP.c:Lscala/Function1;
Asciz	java/lang/Object;
class	java/lang/Object
Asciz	()V;
NameAndType	"<init>":()V
Method	java/lang/Object."<init>":()V
Asciz	scala/Product$class;
class	scala/Product$class
Asciz	$init$;
Asciz	(Lscala/Product;)V;
NameAndType	$init$:(Lscala/Product;)V
Method	scala/Product$class.$init$:(Lscala/Product;)V
Asciz	this;
Asciz	Lscala/concurrent/pilib$UGP;;
Asciz	LocalVariableTable;
Asciz	(Lscala/concurrent/pilib$UChan;ZLjava/lang/Object;Lscala/Function1<Ljava/lang/Object;Ljava/lang/Object;>;)V;
Asciz	gd1$1;
Asciz	(Lscala/concurrent/pilib$UChan;ZLjava/lang/Object;Lscala/Function1;)Z;
Asciz	()Lscala/concurrent/pilib$UChan;;
NameAndType	n:()Lscala/concurrent/pilib$UChan;
Method	scala/concurrent/pilib$UGP.n:()Lscala/concurrent/pilib$UChan;
Asciz	equals;
Asciz	(Ljava/lang/Object;)Z;
NameAndType	equals:(Ljava/lang/Object;)Z
Method	java/lang/Object.equals:(Ljava/lang/Object;)Z
Asciz	()Z;
NameAndType	polarity:()Z
Method	scala/concurrent/pilib$UGP.polarity:()Z
Asciz	()Ljava/lang/Object;;
NameAndType	v:()Ljava/lang/Object;
Method	scala/concurrent/pilib$UGP.v:()Ljava/lang/Object;
Asciz	java/lang/Number;
class	java/lang/Number
Asciz	java/lang/Character;
class	java/lang/Character
Asciz	scala/runtime/BoxesRunTime;
class	scala/runtime/BoxesRunTime
Asciz	equals2;
Asciz	(Ljava/lang/Object;Ljava/lang/Object;)Z;
NameAndType	equals2:(Ljava/lang/Object;Ljava/lang/Object;)Z
Method	scala/runtime/BoxesRunTime.equals2:(Ljava/lang/Object;Ljava/lang/Object;)Z
Asciz	()Lscala/Function1;;
NameAndType	c:()Lscala/Function1;
Method	scala/concurrent/pilib$UGP.c:()Lscala/Function1;
Asciz	y0;
Asciz	canEqual;
Asciz	productElement;
Asciz	(I)Ljava/lang/Object;;
Asciz	java/lang/IndexOutOfBoundsException;
class	java/lang/IndexOutOfBoundsException
Asciz	boxToInteger;
Asciz	(I)Ljava/lang/Integer;;
NameAndType	boxToInteger:(I)Ljava/lang/Integer;
Method	scala/runtime/BoxesRunTime.boxToInteger:(I)Ljava/lang/Integer;
Asciz	toString;
Asciz	()Ljava/lang/String;;
NameAndType	toString:()Ljava/lang/String;
Method	java/lang/Object.toString:()Ljava/lang/String;
Asciz	(Ljava/lang/String;)V;
NameAndType	"<init>":(Ljava/lang/String;)V
Method	java/lang/IndexOutOfBoundsException."<init>":(Ljava/lang/String;)V
Asciz	scala/MatchError;
class	scala/MatchError
Method	scala/MatchError."<init>":(Ljava/lang/String;)V
Asciz	boxToBoolean;
Asciz	(Z)Ljava/lang/Boolean;;
NameAndType	boxToBoolean:(Z)Ljava/lang/Boolean;
Method	scala/runtime/BoxesRunTime.boxToBoolean:(Z)Ljava/lang/Boolean;
Asciz	productArity;
Asciz	()I;
Asciz	productPrefix;
Asciz	UGP;
String	UGP
NameAndType	gd1$1:(Lscala/concurrent/pilib$UChan;ZLjava/lang/Object;Lscala/Function1;)Z
Method	scala/concurrent/pilib$UGP.gd1$1:(Lscala/concurrent/pilib$UChan;ZLjava/lang/Object;Lscala/Function1;)Z
Asciz	scala/Equals;
class	scala/Equals
NameAndType	canEqual:(Ljava/lang/Object;)Z
InterfaceMethod	scala/Equals.canEqual:(Ljava/lang/Object;)Z
Asciz	temp2;
Asciz	temp3;
Asciz	temp4;
Asciz	temp5;
Asciz	temp6;
Asciz	scala/runtime/ScalaRunTime$;
class	scala/runtime/ScalaRunTime$
Asciz	MODULE$;
Asciz	Lscala/runtime/ScalaRunTime$;;
NameAndType	MODULE$:Lscala/runtime/ScalaRunTime$;
Field	scala/runtime/ScalaRunTime$.MODULE$:Lscala/runtime/ScalaRunTime$;
Asciz	_toString;
Asciz	(Lscala/Product;)Ljava/lang/String;;
NameAndType	_toString:(Lscala/Product;)Ljava/lang/String;
Method	scala/runtime/ScalaRunTime$._toString:(Lscala/Product;)Ljava/lang/String;
Asciz	hashCode;
Asciz	_hashCode;
Asciz	(Lscala/Product;)I;
NameAndType	_hashCode:(Lscala/Product;)I
Method	scala/runtime/ScalaRunTime$._hashCode:(Lscala/Product;)I
Asciz	copy;
Asciz	(Lscala/concurrent/pilib$UChan;ZLjava/lang/Object;Lscala/Function1;)Lscala/concurrent/pilib$UGP;;
NameAndType	"<init>":(Lscala/concurrent/pilib$UChan;ZLjava/lang/Object;Lscala/Function1;)V
Method	scala/concurrent/pilib$UGP."<init>":(Lscala/concurrent/pilib$UChan;ZLjava/lang/Object;Lscala/Function1;)V
Asciz	()Lscala/Function1<Ljava/lang/Object;Ljava/lang/Object;>;;
Asciz	copy$default$1;
Asciz	copy$default$2;
Asciz	copy$default$3;
Asciz	copy$default$4;
Asciz	productElements;
Asciz	()Lscala/collection/Iterator;;
Asciz	(Lscala/Product;)Lscala/collection/Iterator;;
NameAndType	productElements:(Lscala/Product;)Lscala/collection/Iterator;
Method	scala/Product$class.productElements:(Lscala/Product;)Lscala/collection/Iterator;
Asciz	Deprecated;
Asciz	productIterator;
NameAndType	productIterator:(Lscala/Product;)Lscala/collection/Iterator;
Method	scala/Product$class.productIterator:(Lscala/Product;)Lscala/collection/Iterator;
Asciz	Scala;
Asciz	InnerClasses;
Asciz	scala/concurrent/pilib;
class	scala/concurrent/pilib
Asciz	scala/concurrent/pilib$UChan;
class	scala/concurrent/pilib$UChan
Asciz	UChan;
Asciz	scala/ScalaObject;
class	scala/ScalaObject
Asciz	scala/Product;
class	scala/Product
Asciz	java/io/Serializable;
class	java/io/Serializable

{
private final scala.Function1 c;
  Signature: Lscala/Function1;
  Signature: length = 0x2
   00 05 

private final java.lang.Object v;
  Signature: Ljava/lang/Object;

private final boolean polarity;
  Signature: Z

private final scala.concurrent.pilib$UChan n;
  Signature: Lscala/concurrent/pilib$UChan;

public scala.concurrent.pilib$UGP(scala.concurrent.pilib$UChan, boolean, java.lang.Object, scala.Function1);
  Signature: (Lscala/concurrent/pilib$UChan;ZLjava/lang/Object;Lscala/Function1;)V
  Code:
   Stack=2, Locals=5, Args_size=5
	aload_0
	aload_1
	putfield	Field n:Lscala/concurrent/pilib$UChan;
	aload_0
	iload_2
	putfield	Field polarity:Z
	aload_0
	aload_3
	putfield	Field v:Ljava/lang/Object;
	aload_0
	aload	4
	putfield	Field c:Lscala/Function1;
	aload_0
	invokespecial	Method java/lang/Object."<init>":()V
	aload_0
	invokestatic	Method scala/Product$class.$init$:(Lscala/Product;)V
	return
  Labels:
  LocalVariableTable: 
   Start  Length  Slot  Name   Signature
   0      30      0    this       Lscala/concurrent/pilib$UGP;
   0      30      1    n       Lscala/concurrent/pilib$UChan;
   0      30      2    polarity       Z
   0      30      3    v       Ljava/lang/Object;
   0      30      4    c       Lscala/Function1;

  Signature: length = 0x2
   00 29 

private final boolean gd1$1(scala.concurrent.pilib$UChan, boolean, java.lang.Object, scala.Function1);
  Signature: (Lscala/concurrent/pilib$UChan;ZLjava/lang/Object;Lscala/Function1;)Z
  Code:
   Stack=2, Locals=8, Args_size=5
	aload_1
	aload_0
	invokevirtual	Method n:()Lscala/concurrent/pilib$UChan;
	astore	5
	dup
	ifnonnull	l1 // aload
	pop
	aload	5
	ifnull	l2 // iload_2
	goto	l3 // iconst_0
l1	aload	5
	invokevirtual	Method java/lang/Object.equals:(Ljava/lang/Object;)Z
	ifeq	l3 // iconst_0
l2	iload_2
	aload_0
	invokevirtual	Method polarity:()Z
	if_icmpne	l3 // iconst_0
	aload_0
	invokevirtual	Method v:()Ljava/lang/Object;
	astore	6
	aload_3
	aload	6
	if_acmpne	l4 // aload_3
	iconst_1
	goto	l5 // ifeq
l4	aload_3
	ifnonnull	l6 // aload_3
	iconst_0
	goto	l5 // ifeq
l6	aload_3
	instanceof	class java/lang/Number
	ifne	l7 // aload_3
	aload_3
	instanceof	class java/lang/Character
	ifeq	l8 // aload_3
l7	aload_3
	aload	6
	invokestatic	Method scala/runtime/BoxesRunTime.equals2:(Ljava/lang/Object;Ljava/lang/Object;)Z
	goto	l5 // ifeq
l8	aload_3
	aload	6
	invokevirtual	Method java/lang/Object.equals:(Ljava/lang/Object;)Z
l5	ifeq	l3 // iconst_0
	aload	4
	aload_0
	invokevirtual	Method c:()Lscala/Function1;
	astore	7
	dup
	ifnonnull	l9 // aload
	pop
	aload	7
	ifnull	l10 // iconst_1
	goto	l3 // iconst_0
l9	aload	7
	invokevirtual	Method java/lang/Object.equals:(Ljava/lang/Object;)Z
	ifeq	l3 // iconst_0
l10	iconst_1
	goto	l11 // ireturn
l3	iconst_0
l11	ireturn
  Labels:
   	l1 = 20 // aload
   	l2 = 28 // iload_2
   	l4 = 52 // aload_3
   	l6 = 60 // aload_3
   	l7 = 74 // aload_3
   	l8 = 83 // aload_3
   	l5 = 89 // ifeq
   	l9 = 113 // aload
   	l10 = 121 // iconst_1
   	l3 = 125 // iconst_0
   	l11 = 126 // ireturn
  LocalVariableTable: 
   Start  Length  Slot  Name   Signature
   0      127      0    this       Lscala/concurrent/pilib$UGP;
   48      44      6    y0       Ljava/lang/Object;


public boolean canEqual(java.lang.Object);
  Signature: (Ljava/lang/Object;)Z
  Code:
   Stack=1, Locals=2, Args_size=2
	aload_1
	instanceof	class scala/concurrent/pilib$UGP
	ireturn
  Labels:

public java.lang.Object productElement(int);
  Signature: (I)Ljava/lang/Object;
  Code:
   Stack=3, Locals=3, Args_size=2
	iload_1
	tableswitch{ //0 to 3
		0: 149;
		1: 118;
		2: 92;
		3: 66;
		default: 32 }
	iconst_1
	ifeq	l1 // new
	new	class java/lang/IndexOutOfBoundsException
	dup
	iload_1
	invokestatic	Method scala/runtime/BoxesRunTime.boxToInteger:(I)Ljava/lang/Integer;
	invokevirtual	Method java/lang/Object.toString:()Ljava/lang/String;
	invokespecial	Method java/lang/IndexOutOfBoundsException."<init>":(Ljava/lang/String;)V
	athrow
l1	new	class scala/MatchError
	dup
	iload_1
	invokestatic	Method scala/runtime/BoxesRunTime.boxToInteger:(I)Ljava/lang/Integer;
	invokevirtual	Method java/lang/Object.toString:()Ljava/lang/String;
	invokespecial	Method scala/MatchError."<init>":(Ljava/lang/String;)V
	athrow
	iconst_1
	ifeq	l2 // new
	aload_0
	invokevirtual	Method c:()Lscala/Function1;
	goto	l3 // areturn
l2	new	class scala/MatchError
	dup
	iload_1
	invokestatic	Method scala/runtime/BoxesRunTime.boxToInteger:(I)Ljava/lang/Integer;
	invokevirtual	Method java/lang/Object.toString:()Ljava/lang/String;
	invokespecial	Method scala/MatchError."<init>":(Ljava/lang/String;)V
	athrow
	iconst_1
	ifeq	l4 // new
	aload_0
	invokevirtual	Method v:()Ljava/lang/Object;
	goto	l3 // areturn
l4	new	class scala/MatchError
	dup
	iload_1
	invokestatic	Method scala/runtime/BoxesRunTime.boxToInteger:(I)Ljava/lang/Integer;
	invokevirtual	Method java/lang/Object.toString:()Ljava/lang/String;
	invokespecial	Method scala/MatchError."<init>":(Ljava/lang/String;)V
	athrow
	iconst_1
	ifeq	l5 // new
	aload_0
	invokevirtual	Method polarity:()Z
	istore_2
	iload_2
	invokestatic	Method scala/runtime/BoxesRunTime.boxToBoolean:(Z)Ljava/lang/Boolean;
	goto	l3 // areturn
l5	new	class scala/MatchError
	dup
	iload_1
	invokestatic	Method scala/runtime/BoxesRunTime.boxToInteger:(I)Ljava/lang/Integer;
	invokevirtual	Method java/lang/Object.toString:()Ljava/lang/String;
	invokespecial	Method scala/MatchError."<init>":(Ljava/lang/String;)V
	athrow
	iconst_1
	ifeq	l6 // new
	aload_0
	invokevirtual	Method n:()Lscala/concurrent/pilib$UChan;
l3	areturn
l6	new	class scala/MatchError
	dup
	iload_1
	invokestatic	Method scala/runtime/BoxesRunTime.boxToInteger:(I)Ljava/lang/Integer;
	invokevirtual	Method java/lang/Object.toString:()Ljava/lang/String;
	invokespecial	Method scala/MatchError."<init>":(Ljava/lang/String;)V
	athrow
  Labels:
   	l1 = 51 // new
   	l2 = 77 // new
   	l4 = 103 // new
   	l5 = 134 // new
   	l3 = 157 // areturn
   	l6 = 158 // new

public int productArity();
  Signature: ()I
  Code:
   Stack=1, Locals=1, Args_size=1
	iconst_4
	ireturn
  Labels:

public java.lang.String productPrefix();
  Signature: ()Ljava/lang/String;
  Code:
   Stack=1, Locals=1, Args_size=1
	ldc	String UGP
	areturn
  Labels:

public boolean equals(java.lang.Object);
  Signature: (Ljava/lang/Object;)Z
  Code:
   Stack=5, Locals=7, Args_size=2
	aload_0
	aload_1
	if_acmpeq	l1 // iconst_1
	aload_1
	instanceof	class scala/concurrent/pilib$UGP
	ifeq	l2 // iconst_1
	aload_1
	checkcast	class scala/concurrent/pilib$UGP
	astore_2
	aload_2
	invokevirtual	Method n:()Lscala/concurrent/pilib$UChan;
	astore_3
	aload_2
	invokevirtual	Method polarity:()Z
	istore	4
	aload_2
	invokevirtual	Method v:()Ljava/lang/Object;
	astore	5
	aload_2
	invokevirtual	Method c:()Lscala/Function1;
	astore	6
	aload_0
	aload_3
	iload	4
	aload	5
	aload	6
	invokespecial	Method gd1$1:(Lscala/concurrent/pilib$UChan;ZLjava/lang/Object;Lscala/Function1;)Z
	ifeq	l3 // iconst_1
	aload_1
	checkcast	class scala/concurrent/pilib$UGP
	aload_0
	invokeinterface	InterfaceMethod scala/Equals.canEqual:(Ljava/lang/Object;)Z
	goto	l4 // ifeq
l3	iconst_1
	ifeq	l5 // new
	iconst_0
	goto	l4 // ifeq
l5	new	class scala/MatchError
	dup
	aload_1
	invokevirtual	Method java/lang/Object.toString:()Ljava/lang/String;
	invokespecial	Method scala/MatchError."<init>":(Ljava/lang/String;)V
	athrow
l2	iconst_1
	ifeq	l6 // new
	iconst_0
l4	ifeq	l7 // iconst_0
l1	iconst_1
	goto	l8 // ireturn
l7	iconst_0
l8	ireturn
l6	new	class scala/MatchError
	dup
	aload_1
	invokevirtual	Method java/lang/Object.toString:()Ljava/lang/String;
	invokespecial	Method scala/MatchError."<init>":(Ljava/lang/String;)V
	athrow
  Labels:
   	l3 = 67 // iconst_1
   	l5 = 75 // new
   	l2 = 87 // iconst_1
   	l4 = 92 // ifeq
   	l1 = 95 // iconst_1
   	l7 = 99 // iconst_0
   	l8 = 100 // ireturn
   	l6 = 101 // new
  LocalVariableTable: 
   Start  Length  Slot  Name   Signature
   0      113      0    this       Lscala/concurrent/pilib$UGP;
   17      70      2    temp2       Lscala/concurrent/pilib$UGP;
   22      65      3    temp3       Lscala/concurrent/pilib$UChan;
   28      59      4    temp4       Z
   34      53      5    temp5       Ljava/lang/Object;
   40      47      6    temp6       Lscala/Function1;


public java.lang.String toString();
  Signature: ()Ljava/lang/String;
  Code:
   Stack=2, Locals=1, Args_size=1
	getstatic	Field scala/runtime/ScalaRunTime$.MODULE$:Lscala/runtime/ScalaRunTime$;
	aload_0
	invokevirtual	Method scala/runtime/ScalaRunTime$._toString:(Lscala/Product;)Ljava/lang/String;
	areturn
  Labels:

public int hashCode();
  Signature: ()I
  Code:
   Stack=2, Locals=1, Args_size=1
	getstatic	Field scala/runtime/ScalaRunTime$.MODULE$:Lscala/runtime/ScalaRunTime$;
	aload_0
	invokevirtual	Method scala/runtime/ScalaRunTime$._hashCode:(Lscala/Product;)I
	ireturn
  Labels:

public scala.concurrent.pilib$UGP copy(scala.concurrent.pilib$UChan, boolean, java.lang.Object, scala.Function1);
  Signature: (Lscala/concurrent/pilib$UChan;ZLjava/lang/Object;Lscala/Function1;)Lscala/concurrent/pilib$UGP;
  Code:
   Stack=6, Locals=5, Args_size=5
	new	class scala/concurrent/pilib$UGP
	dup
	aload_1
	iload_2
	aload_3
	aload	4
	invokespecial	Method "<init>":(Lscala/concurrent/pilib$UChan;ZLjava/lang/Object;Lscala/Function1;)V
	areturn
  Labels:
  LocalVariableTable: 
   Start  Length  Slot  Name   Signature
   0      13      0    this       Lscala/concurrent/pilib$UGP;
   0      13      1    n       Lscala/concurrent/pilib$UChan;
   0      13      2    polarity       Z
   0      13      3    v       Ljava/lang/Object;
   0      13      4    c       Lscala/Function1;


public scala.Function1 c();
  Signature: ()Lscala/Function1;
  Code:
   Stack=1, Locals=1, Args_size=1
	aload_0
	getfield	Field c:Lscala/Function1;
	areturn
  Labels:
  Signature: length = 0x2
   00 FFFFFF81 

public java.lang.Object v();
  Signature: ()Ljava/lang/Object;
  Code:
   Stack=1, Locals=1, Args_size=1
	aload_0
	getfield	Field v:Ljava/lang/Object;
	areturn
  Labels:

public boolean polarity();
  Signature: ()Z
  Code:
   Stack=1, Locals=1, Args_size=1
	aload_0
	getfield	Field polarity:Z
	ireturn
  Labels:

public scala.concurrent.pilib$UChan n();
  Signature: ()Lscala/concurrent/pilib$UChan;
  Code:
   Stack=1, Locals=1, Args_size=1
	aload_0
	getfield	Field n:Lscala/concurrent/pilib$UChan;
	areturn
  Labels:

public scala.concurrent.pilib$UChan copy$default$1();
  Signature: ()Lscala/concurrent/pilib$UChan;
  Code:
   Stack=1, Locals=1, Args_size=1
	aload_0
	invokevirtual	Method n:()Lscala/concurrent/pilib$UChan;
	areturn
  Labels:

public boolean copy$default$2();
  Signature: ()Z
  Code:
   Stack=1, Locals=1, Args_size=1
	aload_0
	invokevirtual	Method polarity:()Z
	ireturn
  Labels:

public java.lang.Object copy$default$3();
  Signature: ()Ljava/lang/Object;
  Code:
   Stack=1, Locals=1, Args_size=1
	aload_0
	invokevirtual	Method v:()Ljava/lang/Object;
	areturn
  Labels:

public scala.Function1 copy$default$4();
  Signature: ()Lscala/Function1;
  Code:
   Stack=1, Locals=1, Args_size=1
	aload_0
	invokevirtual	Method c:()Lscala/Function1;
	areturn
  Labels:

public scala.collection.Iterator productElements();
  Signature: ()Lscala/collection/Iterator;
  Code:
   Stack=1, Locals=1, Args_size=1
	aload_0
	invokestatic	Method scala/Product$class.productElements:(Lscala/Product;)Lscala/collection/Iterator;
	areturn
  Labels:
  Deprecated: true

public scala.collection.Iterator productIterator();
  Signature: ()Lscala/collection/Iterator;
  Code:
   Stack=1, Locals=1, Args_size=1
	aload_0
	invokestatic	Method scala/Product$class.productIterator:(Lscala/Product;)Lscala/collection/Iterator;
	areturn
  Labels:

}

