Compiled from "pilib.scala"
public final class scala.concurrent.pilib extends java.lang.Object
  SourceFile: "pilib.scala"
  ScalaSig: length = 0xDD1
   05 00 FFFFFF83 4C 07 05 01 02 FFFFFF88 02 07 01 05 70 69 6C
   69 62 0A 02 03 04 01 0A 63 6F 6E 63 75 72 72 65
   6E 74 0A 01 05 01 05 73 63 61 6C 61 03 00 10 02
   08 09 0D 01 02 06 08 0A 02 FFFFFF84 FFFFFF80 FFFFFF80 FFFFFF88 02 0B 02
   05 70 69 6C 69 62 13 03 09 0C 14 10 02 0D 12 0D
   01 0E 0A 02 0F 10 01 04 6C 61 6E 67 0A 01 11 01
   04 6A 61 76 61 09 02 13 0E 02 06 4F 62 6A 65 63
   74 10 02 15 16 0D 01 04 09 02 17 04 02 0B 53 63
   61 6C 61 4F 62 6A 65 63 74 08 05 19 09 FFFFFF84 00 1A
   01 06 3C 69 6E 69 74 3E 14 01 07 06 08 1C 09 FFFFFF84
   FFFFFF80 FFFFFF80 FFFFFF81 00 1D 02 05 53 70 61 77 6E 13 03 1B 0C
   14 08 05 19 1B FFFFFF84 00 1F 14 01 20 10 02 21 1B 0D
   01 09 08 05 23 1B FFFFFF86 00 24 01 05 24 6C 65 73 73
   14 02 20 25 08 06 26 22 FFFFFF84 FFFFFFC0 00 27 01 01 70 10
   03 15 28 2A 09 02 29 04 02 08 3C 62 79 6E 61 6D
   65 3E 10 02 15 2B 09 02 2C 04 02 04 55 6E 69 74
   08 05 2E 1B FFFFFF86 00 2F 01 04 24 62 61 72 14 02 20
   30 08 06 26 2D FFFFFF84 FFFFFFC0 00 27 08 05 32 1B FFFFFF86 00 33
   01 08 24 67 72 65 61 74 65 72 15 01 2A 08 07 35
   09 FFFFFFC2 FFFFFF80 FFFFFF84 00 36 01 05 73 70 61 77 6E 15 01 20
   08 06 38 09 FFFFFFA0 FFFFFF80 04 20 01 06 73 70 61 77 6E 20
   06 08 3A 09 FFFFFF84 FFFFFF80 FFFFFF80 FFFFFF80 00 3B 02 05 55 43 68 61
   6E 13 03 39 0C 14 08 05 19 39 FFFFFF84 00 3D 14 01 3E
   10 02 21 39 08 07 40 39 FFFFFFC0 FFFFFF80 FFFFFF84 00 41 01 03 6C
   6F 67 15 01 42 10 04 15 43 45 2A 09 02 44 04 02
   09 46 75 6E 63 74 69 6F 6E 31 10 02 15 46 09 02
   47 04 02 03 41 6E 79 08 07 49 39 FFFFFFC0 FFFFFF80 FFFFFF84 00 4A
   01 07 6C 6F 67 5F 24 65 71 14 02 2A 4B 08 07 4C
   48 FFFFFF81 FFFFFF80 FFFFFFC0 00 42 01 03 78 24 31 08 06 4E 39 FFFFFFA0
   FFFFFFA0 04 42 01 04 6C 6F 67 20 06 08 50 09 FFFFFF84 FFFFFF80 FFFFFF80
   FFFFFF80 40 51 02 03 55 47 50 13 04 4F 0C 14 52 10 02
   15 53 09 02 54 04 02 07 50 72 6F 64 75 63 74 08
   08 56 4F FFFFFF82 FFFFFFCA FFFFFF80 FFFFFF84 00 57 01 01 6E 15 01 3E 08
   08 59 4F FFFFFF82 FFFFFF88 FFFFFFA0 FFFFFF80 04 3E 01 02 6E 20 08 08 5B
   4F FFFFFF82 FFFFFFCA FFFFFF80 FFFFFF84 00 5C 01 08 70 6F 6C 61 72 69 74
   79 15 01 5D 10 02 15 5E 09 02 5F 04 02 07 42 6F
   6F 6C 65 61 6E 08 08 61 4F FFFFFF82 FFFFFF88 FFFFFFA0 FFFFFF80 04 5D 01
   09 70 6F 6C 61 72 69 74 79 20 08 08 63 4F FFFFFF82 FFFFFFCA
   FFFFFF80 FFFFFF84 00 64 01 01 76 15 01 45 08 08 66 4F FFFFFF82 FFFFFF88
   FFFFFFA0 FFFFFF80 04 45 01 02 76 20 08 08 68 4F FFFFFF82 FFFFFFCA FFFFFF80 FFFFFF84
   00 69 01 01 63 15 01 6A 10 04 15 43 45 45 08 08
   6C 4F FFFFFF82 FFFFFF88 FFFFFFA0 FFFFFF80 04 6A 01 02 63 20 08 05 19 4F
   FFFFFF84 00 6E 14 05 6F 70 71 72 73 10 02 21 4F 08 05
   56 6D FFFFFFC0 00 3E 08 05 5B 6D FFFFFFC0 00 5D 08 05 63 6D
   FFFFFFC0 00 45 08 05 68 6D FFFFFFC0 00 6A 08 07 75 4F FFFFFF81 FFFFFF80
   FFFFFF84 00 76 01 04 63 6F 70 79 14 08 6F 77 FFFFFF81 05 FFFFFF81
   0A FFFFFF81 0F 08 08 78 56 74 FFFFFF90 FFFFFF80 FFFFFFC0 00 3E 08 07 79
   4F FFFFFF91 FFFFFF80 FFFFFF84 00 7A 01 0E 63 6F 70 79 24 64 65 66
   61 75 6C 74 24 31 15 01 7B 2A 02 3E 7C 2B 01 7D
   10 03 7E FFFFFF81 03 0D 01 7F 0A 04 FFFFFF81 00 FFFFFF81 01 01 09
   75 6E 63 68 65 63 6B 65 64 0A 03 FFFFFF81 02 04 01 0A
   61 6E 6E 6F 74 61 74 69 6F 6E 09 03 FFFFFF81 04 7F 02
   11 75 6E 63 68 65 63 6B 65 64 56 61 72 69 61 6E
   63 65 08 09 FFFFFF81 06 5B 74 FFFFFF90 FFFFFF80 FFFFFFC0 00 5D 08 09 FFFFFF81
   07 4F FFFFFF91 FFFFFF80 FFFFFF84 00 FFFFFF81 08 01 0E 63 6F 70 79 24 64
   65 66 61 75 6C 74 24 32 15 02 FFFFFF81 09 2A 02 5D 7C
   08 09 FFFFFF81 0B 63 74 FFFFFF90 FFFFFF80 FFFFFFC0 00 45 08 09 FFFFFF81 0C 4F
   FFFFFF91 FFFFFF80 FFFFFF84 00 FFFFFF81 0D 01 0E 63 6F 70 79 24 64 65 66
   61 75 6C 74 24 33 15 02 FFFFFF81 0E 2A 02 45 7C 08 09
   FFFFFF81 10 68 74 FFFFFF90 FFFFFF80 FFFFFFC0 00 6A 08 09 FFFFFF81 11 4F FFFFFF91 FFFFFF80
   FFFFFF84 00 FFFFFF81 12 01 0E 63 6F 70 79 24 64 65 66 61 75
   6C 74 24 34 15 02 FFFFFF81 13 2A 02 6A 7C 08 0A FFFFFF81 15
   4F FFFFFF84 FFFFFF80 FFFFFF80 FFFFFF84 20 FFFFFF81 16 01 08 68 61 73 68 43 6F
   64 65 14 02 FFFFFF81 17 10 03 15 FFFFFF81 18 09 03 FFFFFF81 19 04
   02 03 49 6E 74 08 0A FFFFFF81 1B 4F FFFFFF84 FFFFFF80 FFFFFF80 FFFFFF84 20 FFFFFF81
   1C 01 08 74 6F 53 74 72 69 6E 67 14 02 FFFFFF81 1D 10
   04 FFFFFF81 1E FFFFFF81 21 0E 03 15 FFFFFF81 1F 09 03 FFFFFF81 20 04 01
   06 50 72 65 64 65 66 09 04 FFFFFF81 22 FFFFFF81 23 02 06 53
   74 72 69 6E 67 0A 03 FFFFFF81 20 04 08 0A FFFFFF81 25 4F FFFFFF84
   FFFFFF80 FFFFFF80 FFFFFF84 20 FFFFFF81 26 01 06 65 71 75 61 6C 73 14 03
   5D FFFFFF81 27 08 08 4C FFFFFF81 24 FFFFFF81 FFFFFF80 FFFFFFC0 00 45 08 0A FFFFFF81
   29 4F FFFFFF84 FFFFFF80 FFFFFF80 FFFFFF84 20 FFFFFF81 2A 01 0D 70 72 6F 64 75
   63 74 50 72 65 66 69 78 15 02 FFFFFF81 2B 10 03 0D FFFFFF81
   2C 09 03 FFFFFF81 22 0E 08 0A FFFFFF81 2E 4F FFFFFF84 FFFFFF80 FFFFFF80 FFFFFF84 20
   FFFFFF81 2F 01 0C 70 72 6F 64 75 63 74 41 72 69 74 79
   15 02 FFFFFF81 17 08 0A FFFFFF81 31 4F FFFFFF84 FFFFFF80 FFFFFF80 FFFFFF84 20 FFFFFF81 32
   01 0E 70 72 6F 64 75 63 74 45 6C 65 6D 65 6E 74
   14 03 45 FFFFFF81 33 08 09 4C FFFFFF81 30 FFFFFF81 FFFFFF80 FFFFFFC0 00 FFFFFF81 17
   08 0A FFFFFF81 35 4F FFFFFF84 FFFFFF80 FFFFFF80 FFFFFF84 20 FFFFFF81 36 01 08 63 61
   6E 45 71 75 61 6C 14 03 5D FFFFFF81 37 08 08 4C FFFFFF81 34
   FFFFFF81 FFFFFF80 FFFFFFC0 00 45 28 03 4F FFFFFF81 39 10 03 15 FFFFFF81 3A 09
   03 FFFFFF81 3B 04 02 0C 73 65 72 69 61 6C 69 7A 61 62
   6C 65 07 09 FFFFFF81 3D 09 FFFFFF81 FFFFFF80 FFFFFF88 02 FFFFFF81 3E 01 03 55
   47 50 10 03 21 FFFFFF81 3F 06 09 50 09 FFFFFF84 FFFFFF81 FFFFFF80 FFFFFF88 02
   FFFFFF81 40 13 06 FFFFFF81 3F 0C FFFFFF81 41 14 10 08 15 FFFFFF81 42 3E
   5D 45 6A 6F 09 03 FFFFFF81 43 04 02 09 46 75 6E 63 74
   69 6F 6E 34 08 07 19 FFFFFF81 3F FFFFFF84 00 FFFFFF81 45 14 02 FFFFFF81
   3E 08 0A FFFFFF81 47 FFFFFF81 3F FFFFFF81 FFFFFF80 FFFFFF84 40 FFFFFF81 48 01 05 61
   70 70 6C 79 14 09 6F FFFFFF81 49 FFFFFF81 4A FFFFFF81 4B FFFFFF81 4C 08
   06 56 FFFFFF81 46 FFFFFFC0 00 3E 08 06 5B FFFFFF81 46 FFFFFFC0 00 5D 08
   06 63 FFFFFF81 46 FFFFFFC0 00 45 08 06 68 FFFFFF81 46 FFFFFFC0 00 6A 08
   0A FFFFFF81 4E FFFFFF81 3F FFFFFF81 FFFFFF80 FFFFFF84 40 FFFFFF81 4F 01 07 75 6E 61
   70 70 6C 79 14 04 FFFFFF81 50 FFFFFF81 56 10 05 15 FFFFFF81 51 FFFFFF81
   53 09 03 FFFFFF81 52 04 02 04 53 6F 6D 65 10 07 15 FFFFFF81
   54 3E 5D 45 6A 09 03 FFFFFF81 55 04 02 06 54 75 70 6C
   65 34 08 07 FFFFFF81 57 FFFFFF81 4D FFFFFFC0 00 6F 01 03 78 24 30
   06 06 FFFFFF81 59 09 00 FFFFFF81 5A 02 02 47 50 15 04 FFFFFF81 5B
   FFFFFF81 63 13 04 FFFFFF81 58 0C 14 08 09 56 FFFFFF81 58 FFFFFF82 FFFFFF80 FFFFFFA0
   FFFFFF80 04 3E 08 09 5B FFFFFF81 58 FFFFFF82 FFFFFF80 FFFFFFA0 FFFFFF80 04 5D 08 09
   63 FFFFFF81 58 FFFFFF82 FFFFFF80 FFFFFFA0 FFFFFF80 04 45 08 0A 68 FFFFFF81 58 FFFFFF82 FFFFFF80
   FFFFFFA0 FFFFFF80 04 FFFFFF81 60 10 05 15 43 45 FFFFFF81 61 10 04 FFFFFF81 62
   FFFFFF81 63 0C 00 04 0B FFFFFF81 64 FFFFFF81 58 FFFFFF84 FFFFFF80 FFFFFF80 FFFFFFC2 00 FFFFFF81
   65 02 01 61 11 03 FFFFFF81 66 45 10 03 15 FFFFFF81 67 09 03
   FFFFFF81 68 04 02 07 4E 6F 74 68 69 6E 67 08 07 19 FFFFFF81
   58 FFFFFF84 00 FFFFFF81 6A 14 0A FFFFFF81 6B FFFFFF81 6C FFFFFF81 6D FFFFFF81 6E FFFFFF81
   6F 10 05 21 FFFFFF81 58 FFFFFF81 61 08 06 56 FFFFFF81 69 FFFFFFC0 00 3E
   08 06 5B FFFFFF81 69 FFFFFFC0 00 5D 08 06 63 FFFFFF81 69 FFFFFFC0 00 45
   08 07 68 FFFFFF81 69 FFFFFFC0 00 FFFFFF81 60 08 0A FFFFFF81 71 FFFFFF81 58 FFFFFFC2
   FFFFFF80 FFFFFF84 00 FFFFFF81 72 01 07 75 6E 74 79 70 65 64 15 01
   6F 08 08 FFFFFF81 74 FFFFFF81 58 FFFFFFA0 FFFFFF80 04 6F 01 08 75 6E 74
   79 70 65 64 20 06 06 FFFFFF81 76 09 00 FFFFFF81 77 02 04 43
   68 61 6E 15 04 FFFFFF81 78 FFFFFF81 7B 13 06 FFFFFF81 75 3E FFFFFF81 79
   14 10 06 15 43 FFFFFF81 7A FFFFFF81 7D 10 04 FFFFFF81 62 FFFFFF81 7B 04
   0B FFFFFF81 7C FFFFFF81 75 FFFFFF84 FFFFFF80 FFFFFF80 FFFFFFC2 00 FFFFFF81 65 02 01 41 10
   05 21 FFFFFF81 7E FFFFFF81 7A 06 05 54 09 00 FFFFFF81 7F 15 04 FFFFFF82
   00 FFFFFF82 04 13 04 FFFFFF81 7E 0C 14 08 0A 68 FFFFFF81 7E FFFFFF82 FFFFFF80
   FFFFFFA0 FFFFFF80 04 FFFFFF82 02 10 05 21 FFFFFF81 75 FFFFFF82 03 10 04 FFFFFF81 62
   FFFFFF82 04 04 0B FFFFFF81 7C FFFFFF81 7E FFFFFF84 FFFFFF80 FFFFFF80 FFFFFFC2 00 FFFFFF81 65 08
   0A 63 FFFFFF81 7E FFFFFF82 FFFFFF80 FFFFFFA0 FFFFFF80 04 FFFFFF82 03 08 07 19 FFFFFF81 7E
   FFFFFF84 00 FFFFFF82 07 14 06 FFFFFF82 08 FFFFFF82 09 FFFFFF82 0A 10 05 21 FFFFFF81
   7E FFFFFF82 03 08 07 68 FFFFFF82 06 FFFFFFC0 00 FFFFFF82 02 08 07 63 FFFFFF82
   06 FFFFFFC0 00 FFFFFF82 03 08 08 FFFFFF82 0C FFFFFF81 7E FFFFFF84 00 FFFFFF82 0D 01
   06 24 74 69 6D 65 73 15 04 FFFFFF82 0E FFFFFF82 11 14 04 FFFFFF82
   0F FFFFFF82 13 10 05 21 FFFFFF81 58 FFFFFF82 10 10 04 FFFFFF81 62 FFFFFF82 11
   04 0B FFFFFF82 12 FFFFFF82 0B FFFFFF84 FFFFFF80 FFFFFF80 FFFFFFC2 00 FFFFFF81 65 02 01 42
   08 09 FFFFFF82 14 FFFFFF82 0B FFFFFF84 FFFFFFC0 00 FFFFFF82 15 01 01 66 10 04
   15 28 FFFFFF82 10 08 07 19 FFFFFF81 75 FFFFFF84 00 FFFFFF82 17 14 02 FFFFFF82
   18 10 05 21 FFFFFF81 75 FFFFFF81 7A 08 0A FFFFFF82 1A FFFFFF81 75 FFFFFFC0 FFFFFF80
   FFFFFF84 00 FFFFFF82 1B 01 0C 64 65 66 61 75 6C 74 56 61 6C
   75 65 15 02 FFFFFF81 7A 08 0A FFFFFF82 1D FFFFFF81 75 FFFFFFC0 FFFFFF80 FFFFFF84 00
   FFFFFF82 1E 01 10 64 65 66 61 75 6C 74 56 61 6C 75 65
   5F 24 65 71 14 03 2A FFFFFF82 1F 08 09 4C FFFFFF82 1C FFFFFF81 FFFFFF80
   FFFFFFC0 00 FFFFFF81 7A 08 09 FFFFFF82 21 FFFFFF81 75 FFFFFFA0 FFFFFFA0 04 FFFFFF81 7A 01
   0D 64 65 66 61 75 6C 74 56 61 6C 75 65 20 08 08
   FFFFFF82 23 FFFFFF81 75 FFFFFF84 00 FFFFFF82 24 01 05 69 6E 70 75 74 15
   04 FFFFFF82 25 FFFFFF82 28 14 04 FFFFFF82 26 FFFFFF82 29 10 05 21 FFFFFF81 58
   FFFFFF82 27 10 04 FFFFFF81 62 FFFFFF82 28 04 0B FFFFFF82 12 FFFFFF82 22 FFFFFF84 FFFFFF80
   FFFFFF80 FFFFFFC2 00 FFFFFF81 65 08 07 68 FFFFFF82 22 FFFFFFC0 00 FFFFFF82 2A 10 06
   15 43 FFFFFF81 7A FFFFFF82 27 08 08 FFFFFF82 2C FFFFFF81 75 FFFFFF84 00 FFFFFF82 2D
   01 06 6F 75 74 70 75 74 15 04 FFFFFF82 2E FFFFFF82 31 14 06
   FFFFFF82 2F FFFFFF82 32 FFFFFF82 33 10 05 21 FFFFFF81 58 FFFFFF82 30 10 04 FFFFFF81
   62 FFFFFF82 31 04 0B FFFFFF82 12 FFFFFF82 2B FFFFFF84 FFFFFF80 FFFFFF80 FFFFFFC2 00 FFFFFF81 65
   08 07 63 FFFFFF82 2B FFFFFFC0 00 FFFFFF81 7A 08 07 68 FFFFFF82 2B FFFFFFC0 00
   FFFFFF82 34 10 05 15 FFFFFF82 35 FFFFFF82 30 09 03 FFFFFF82 36 04 02 09
   46 75 6E 63 74 69 6F 6E 30 08 08 FFFFFF82 38 FFFFFF81 75 FFFFFF84
   00 FFFFFF82 1B 01 04 72 65 61 64 08 08 FFFFFF82 3A FFFFFF81 75 FFFFFF84
   00 FFFFFF82 3B 01 05 77 72 69 74 65 14 03 2A FFFFFF82 3C 08
   08 FFFFFF82 3D FFFFFF82 39 FFFFFFC0 00 FFFFFF81 7A 01 01 78 08 08 FFFFFF82 0C
   FFFFFF81 75 FFFFFF84 00 FFFFFF82 3F 15 04 FFFFFF82 40 FFFFFF82 43 14 04 FFFFFF82 41
   FFFFFF82 44 10 05 21 FFFFFF81 58 FFFFFF82 42 10 04 FFFFFF81 62 FFFFFF82 43 04
   0B FFFFFF82 12 FFFFFF82 3E FFFFFF84 FFFFFF80 FFFFFF80 FFFFFFC2 00 FFFFFF81 65 08 08 FFFFFF82 14
   FFFFFF82 3E FFFFFFC0 00 FFFFFF82 45 10 06 15 43 FFFFFF81 7A FFFFFF82 42 08 08
   FFFFFF81 47 FFFFFF81 75 FFFFFF84 00 FFFFFF82 47 14 04 FFFFFF81 7D FFFFFF82 48 08 07
   63 FFFFFF82 46 FFFFFFC0 00 FFFFFF81 7A 08 08 FFFFFF82 4A FFFFFF81 75 FFFFFF84 00 FFFFFF82
   4B 01 06 61 74 74 61 63 68 14 03 2A FFFFFF82 4C 08 08
   FFFFFF82 14 FFFFFF82 49 FFFFFFC0 00 FFFFFF82 4D 10 05 15 43 FFFFFF81 7A 2A 06
   0A FFFFFF82 4F 09 FFFFFF84 FFFFFF80 FFFFFF80 FFFFFF80 40 FFFFFF82 50 02 03 53 75 6D
   13 05 FFFFFF82 4E 0C 14 52 08 0B FFFFFF82 52 FFFFFF82 4E FFFFFF82 FFFFFFCA FFFFFF80
   FFFFFF84 00 FFFFFF82 53 01 02 67 73 15 02 FFFFFF82 54 10 05 FFFFFF82 55
   FFFFFF82 5D 6F 0E 04 FFFFFF82 56 FFFFFF82 5B 0E 04 FFFFFF82 57 FFFFFF82 5A 0D
   02 FFFFFF82 58 0A 03 FFFFFF82 59 06 01 06 3C 72 6F 6F 74 3E
   09 01 05 09 03 FFFFFF82 5C 04 01 07 70 61 63 6B 61 67
   65 09 04 FFFFFF82 5E FFFFFF82 5F 02 04 4C 69 73 74 0A 03 FFFFFF82
   5C 04 08 0B FFFFFF82 61 FFFFFF82 4E FFFFFF82 FFFFFF88 FFFFFFA0 FFFFFF80 04 FFFFFF82 54 01
   03 67 73 20 08 07 19 FFFFFF82 4E FFFFFF84 00 FFFFFF82 63 14 04 FFFFFF82
   64 FFFFFF82 65 10 03 21 FFFFFF82 4E 08 08 FFFFFF82 52 FFFFFF82 62 FFFFFFC0 00
   FFFFFF82 54 08 0A FFFFFF82 67 FFFFFF82 4E FFFFFFC0 FFFFFF80 FFFFFF84 00 FFFFFF82 68 01 04
   63 6F 6E 74 15 02 FFFFFF82 69 10 04 15 FFFFFF82 35 45 08 0A
   FFFFFF82 6B FFFFFF82 4E FFFFFFC0 FFFFFF80 FFFFFF84 00 FFFFFF82 6C 01 08 63 6F 6E 74
   5F 24 65 71 14 03 2A FFFFFF82 6D 08 09 4C FFFFFF82 6A FFFFFF81 FFFFFF80
   FFFFFFC0 00 FFFFFF82 69 08 09 FFFFFF82 6F FFFFFF82 4E FFFFFFA0 FFFFFFA0 04 FFFFFF82 69 01
   05 63 6F 6E 74 20 08 09 FFFFFF82 71 FFFFFF82 4E FFFFFFC0 FFFFFF80 FFFFFF84 00
   5C 01 0B 69 6E 69 74 69 61 6C 69 7A 65 64 08 0A
   FFFFFF82 73 FFFFFF82 4E FFFFFFC0 FFFFFF80 FFFFFF84 00 FFFFFF82 74 01 0F 69 6E 69 74
   69 61 6C 69 7A 65 64 5F 24 65 71 14 03 2A FFFFFF82 75
   08 08 4C FFFFFF82 72 FFFFFF81 FFFFFF80 FFFFFFC0 00 5D 08 08 FFFFFF82 77 FFFFFF82 4E
   FFFFFFA0 FFFFFFA0 04 5D 01 0C 69 6E 69 74 69 61 6C 69 7A 65
   64 20 08 07 FFFFFF82 79 FFFFFF82 4E FFFFFF84 00 64 01 08 63 6F 6E
   74 69 6E 75 65 08 08 FFFFFF82 7B FFFFFF82 4E FFFFFF84 00 FFFFFF82 7C 01
   03 73 65 74 14 03 2A FFFFFF82 7D 08 08 FFFFFF82 14 FFFFFF82 7A FFFFFFC0
   00 FFFFFF82 69 08 09 75 FFFFFF82 4E FFFFFF81 FFFFFF80 FFFFFF84 00 FFFFFF82 7F 14 04
   FFFFFF82 64 FFFFFF83 00 08 0C FFFFFF83 01 FFFFFF82 52 FFFFFF82 7E FFFFFF90 FFFFFF80 FFFFFFC0 00
   FFFFFF82 54 08 09 79 FFFFFF82 4E FFFFFF91 FFFFFF80 FFFFFF84 00 FFFFFF83 02 15 02 FFFFFF83
   03 2A 03 FFFFFF82 54 7C 08 0B FFFFFF81 15 FFFFFF82 4E FFFFFF84 FFFFFF80 FFFFFF80 FFFFFF84
   20 FFFFFF81 16 08 0B FFFFFF81 1B FFFFFF82 4E FFFFFF84 FFFFFF80 FFFFFF80 FFFFFF84 20 FFFFFF81 1C
   08 0B FFFFFF81 25 FFFFFF82 4E FFFFFF84 FFFFFF80 FFFFFF80 FFFFFF84 20 FFFFFF83 07 14 03 5D
   FFFFFF83 08 08 08 4C FFFFFF83 06 FFFFFF81 FFFFFF80 FFFFFFC0 00 45 08 0B FFFFFF81 29
   FFFFFF82 4E FFFFFF84 FFFFFF80 FFFFFF80 FFFFFF84 20 FFFFFF81 2A 08 0B FFFFFF81 2E FFFFFF82 4E FFFFFF84
   FFFFFF80 FFFFFF80 FFFFFF84 20 FFFFFF81 2F 08 0B FFFFFF81 31 FFFFFF82 4E FFFFFF84 FFFFFF80 FFFFFF80 FFFFFF84
   20 FFFFFF83 0C 14 03 45 FFFFFF83 0D 08 09 4C FFFFFF83 0B FFFFFF81 FFFFFF80 FFFFFFC0
   00 FFFFFF81 17 08 0B FFFFFF81 35 FFFFFF82 4E FFFFFF84 FFFFFF80 FFFFFF80 FFFFFF84 20 FFFFFF83 0F
   14 03 5D FFFFFF83 10 08 08 4C FFFFFF83 0E FFFFFF81 FFFFFF80 FFFFFFC0 00 45 28
   04 FFFFFF82 4E FFFFFF81 39 07 09 FFFFFF83 13 09 FFFFFF81 FFFFFF80 FFFFFF88 02 FFFFFF83 14
   01 03 53 75 6D 10 03 21 FFFFFF83 15 06 0A FFFFFF82 4F 09 FFFFFF84
   FFFFFF81 FFFFFF80 FFFFFF88 02 FFFFFF83 16 13 06 FFFFFF83 15 0C FFFFFF83 17 14 10 06
   15 43 FFFFFF82 54 FFFFFF82 64 08 07 19 FFFFFF83 15 FFFFFF84 00 FFFFFF83 19 14
   02 FFFFFF83 14 08 0A FFFFFF81 47 FFFFFF83 15 FFFFFF81 FFFFFF80 FFFFFF84 40 FFFFFF83 1B 14
   04 FFFFFF82 64 FFFFFF83 1C 08 08 FFFFFF82 52 FFFFFF83 1A FFFFFFC0 00 FFFFFF82 54 08
   0A FFFFFF81 4E FFFFFF83 15 FFFFFF81 FFFFFF80 FFFFFF84 40 FFFFFF83 1E 14 04 FFFFFF83 1F FFFFFF83
   20 10 05 15 FFFFFF81 51 FFFFFF82 54 08 08 FFFFFF81 57 FFFFFF83 1D FFFFFFC0 00
   FFFFFF82 64 08 09 FFFFFF83 22 09 FFFFFFC0 FFFFFF80 FFFFFF84 04 FFFFFF83 23 01 04 73
   75 6D 73 15 02 FFFFFF83 24 10 06 FFFFFF82 55 FFFFFF82 5D FFFFFF82 64 08
   09 FFFFFF83 26 09 FFFFFFC0 FFFFFF80 FFFFFF84 04 FFFFFF83 27 01 08 73 75 6D 73
   5F 24 65 71 14 03 2A FFFFFF83 28 08 09 4C FFFFFF83 25 FFFFFF81 FFFFFF80
   FFFFFFC0 00 FFFFFF83 24 08 08 FFFFFF83 2A 09 FFFFFFA0 FFFFFFA0 04 FFFFFF83 24 01 05
   73 75 6D 73 20 08 07 FFFFFF83 2C 09 FFFFFF84 04 FFFFFF83 2D 01 07
   6D 61 74 63 68 65 73 14 06 FFFFFF83 2E FFFFFF83 35 FFFFFF83 37 10
   05 15 FFFFFF83 2F FFFFFF83 31 09 03 FFFFFF83 30 04 02 06 4F 70 74
   69 6F 6E 10 09 15 FFFFFF83 32 FFFFFF83 34 FFFFFF82 69 FFFFFF82 69 09 03
   FFFFFF83 33 04 02 06 54 75 70 6C 65 33 10 04 15 FFFFFF82 35
   2A 08 08 FFFFFF83 36 FFFFFF83 2B FFFFFFC0 00 FFFFFF82 54 01 03 67 73 31
   08 08 FFFFFF83 38 FFFFFF83 2B FFFFFFC0 00 FFFFFF82 54 01 03 67 73 32 08
   07 FFFFFF83 3A 09 FFFFFF84 04 FFFFFF83 3B 01 07 63 6F 6D 70 61 72
   65 14 06 FFFFFF83 24 FFFFFF83 3C FFFFFF83 3E 08 08 FFFFFF83 3D FFFFFF83 39 FFFFFFC0
   00 FFFFFF82 64 01 02 73 31 08 08 FFFFFF83 3F FFFFFF83 39 FFFFFFC0 00 FFFFFF83
   24 01 02 73 73 08 07 FFFFFF83 41 09 FFFFFF84 00 FFFFFF83 42 01 06
   63 68 6F 69 63 65 15 04 FFFFFF83 43 FFFFFF83 45 14 04 FFFFFF83 44
   FFFFFF83 46 10 04 FFFFFF81 62 FFFFFF83 45 04 0B FFFFFF81 7C FFFFFF83 40 FFFFFF84 FFFFFF80
   FFFFFF80 FFFFFFC2 00 FFFFFF81 65 08 08 FFFFFF83 47 FFFFFF83 40 FFFFFFC0 00 FFFFFF83 48 01
   01 73 10 05 15 FFFFFF83 49 FFFFFF83 4B 09 03 FFFFFF83 4A 04 02 0A
   3C 72 65 70 65 61 74 65 64 3E 10 05 21 FFFFFF81 58 FFFFFF83
   44 
  InnerClass: 
   public #26= #23 of #25; //GP=class scala/concurrent/pilib$GP of class scala/concurrent/pilib
   public #29= #28 of #25; //Sum=class scala/concurrent/pilib$Sum of class scala/concurrent/pilib
   public #32= #31 of #25; //UGP=class scala/concurrent/pilib$UGP of class scala/concurrent/pilib
   public #35= #34 of #25; //Chan=class scala/concurrent/pilib$Chan of class scala/concurrent/pilib
   public #38= #37 of #25; //UChan=class scala/concurrent/pilib$UChan of class scala/concurrent/pilib
   public abstract #41= #40 of #25; //Spawn=class scala/concurrent/pilib$Spawn of class scala/concurrent/pilib
   public final #44= #43 of #25; //$anon$1=class scala/concurrent/pilib$$anon$1 of class scala/concurrent/pilib
   public #47= #46 of #25; //Product=class scala/concurrent/pilib$Product of class scala/concurrent/pilib
   public final #50= #49 of #25; //$anonfun$2=class scala/concurrent/pilib$$anonfun$2 of class scala/concurrent/pilib
   public final #53= #52 of #25; //$anonfun$matches$3=class scala/concurrent/pilib$$anonfun$matches$3 of class scala/concurrent/pilib
   public final #56= #55 of #25; //$anonfun$matches$2=class scala/concurrent/pilib$$anonfun$matches$2 of class scala/concurrent/pilib
   public final #59= #58 of #25; //$anonfun$matches$1=class scala/concurrent/pilib$$anonfun$matches$1 of class scala/concurrent/pilib
  minor version: 0
  major version: 49
  Constant pool:
const #1 = Asciz	SourceFile;
const #2 = Asciz	pilib.scala;
const #3 = Asciz	choice;
const #4 = Asciz	(Lscala/collection/Seq;)Ljava/lang/Object;;
const #5 = Asciz	Code;
const #6 = Asciz	scala/concurrent/pilib$;
const #7 = class	#6;	//  scala/concurrent/pilib$
const #8 = Asciz	MODULE$;
const #9 = Asciz	Lscala/concurrent/pilib$;;
const #10 = NameAndType	#8:#9;//  MODULE$:Lscala/concurrent/pilib$;
const #11 = Field	#7.#10;	//  scala/concurrent/pilib$.MODULE$:Lscala/concurrent/pilib$;
const #12 = NameAndType	#3:#4;//  choice:(Lscala/collection/Seq;)Ljava/lang/Object;
const #13 = Method	#7.#12;	//  scala/concurrent/pilib$.choice:(Lscala/collection/Seq;)Ljava/lang/Object;
const #14 = Asciz	<A:Ljava/lang/Object;>(Lscala/collection/Seq<Lscala/concurrent/pilib$GP<TA;>;>;)TA;;
const #15 = Asciz	Signature;
const #16 = Asciz	spawn;
const #17 = Asciz	()Lscala/concurrent/pilib$Spawn;;
const #18 = NameAndType	#16:#17;//  spawn:()Lscala/concurrent/pilib$Spawn;
const #19 = Method	#7.#18;	//  scala/concurrent/pilib$.spawn:()Lscala/concurrent/pilib$Spawn;
const #20 = Asciz	ScalaSig;
const #21 = Asciz	InnerClasses;
const #22 = Asciz	scala/concurrent/pilib$GP;
const #23 = class	#22;	//  scala/concurrent/pilib$GP
const #24 = Asciz	scala/concurrent/pilib;
const #25 = class	#24;	//  scala/concurrent/pilib
const #26 = Asciz	GP;
const #27 = Asciz	scala/concurrent/pilib$Sum;
const #28 = class	#27;	//  scala/concurrent/pilib$Sum
const #29 = Asciz	Sum;
const #30 = Asciz	scala/concurrent/pilib$UGP;
const #31 = class	#30;	//  scala/concurrent/pilib$UGP
const #32 = Asciz	UGP;
const #33 = Asciz	scala/concurrent/pilib$Chan;
const #34 = class	#33;	//  scala/concurrent/pilib$Chan
const #35 = Asciz	Chan;
const #36 = Asciz	scala/concurrent/pilib$UChan;
const #37 = class	#36;	//  scala/concurrent/pilib$UChan
const #38 = Asciz	UChan;
const #39 = Asciz	scala/concurrent/pilib$Spawn;
const #40 = class	#39;	//  scala/concurrent/pilib$Spawn
const #41 = Asciz	Spawn;
const #42 = Asciz	scala/concurrent/pilib$$anon$1;
const #43 = class	#42;	//  scala/concurrent/pilib$$anon$1
const #44 = Asciz	$anon$1;
const #45 = Asciz	scala/concurrent/pilib$Product;
const #46 = class	#45;	//  scala/concurrent/pilib$Product
const #47 = Asciz	Product;
const #48 = Asciz	scala/concurrent/pilib$$anonfun$2;
const #49 = class	#48;	//  scala/concurrent/pilib$$anonfun$2
const #50 = Asciz	$anonfun$2;
const #51 = Asciz	scala/concurrent/pilib$$anonfun$matches$3;
const #52 = class	#51;	//  scala/concurrent/pilib$$anonfun$matches$3
const #53 = Asciz	$anonfun$matches$3;
const #54 = Asciz	scala/concurrent/pilib$$anonfun$matches$2;
const #55 = class	#54;	//  scala/concurrent/pilib$$anonfun$matches$2
const #56 = Asciz	$anonfun$matches$2;
const #57 = Asciz	scala/concurrent/pilib$$anonfun$matches$1;
const #58 = class	#57;	//  scala/concurrent/pilib$$anonfun$matches$1
const #59 = Asciz	$anonfun$matches$1;
const #60 = Asciz	java/lang/Object;
const #61 = class	#60;	//  java/lang/Object

{
public static final java.lang.Object choice(scala.collection.Seq);
  Code:
   Stack=2, Locals=1, Args_size=1
   0:	getstatic	#11; //Field scala/concurrent/pilib$.MODULE$:Lscala/concurrent/pilib$;
   3:	aload_0
   4:	invokevirtual	#13; //Method scala/concurrent/pilib$.choice:(Lscala/collection/Seq;)Ljava/lang/Object;
   7:	areturn
  Signature: length = 0x2
   00 0E 

public static final scala.concurrent.pilib$Spawn spawn();
  Code:
   Stack=1, Locals=0, Args_size=0
   0:	getstatic	#11; //Field scala/concurrent/pilib$.MODULE$:Lscala/concurrent/pilib$;
   3:	invokevirtual	#19; //Method scala/concurrent/pilib$.spawn:()Lscala/concurrent/pilib$Spawn;
   6:	areturn

}

