Compiled from "pilib.scala"
public final class scala.concurrent.pilib$$anonfun$matches$1 extends scala.runtime.AbstractFunction0 implements java.io.Serializable
  SourceFile: "pilib.scala"
  Scala: length = 0x
   
  InnerClass: 
   public UChan=class scala/concurrent/pilib$UChan of class scala/concurrent/pilib
   public final $anonfun$matches$1=class scala/concurrent/pilib$$anonfun$matches$1 of class scala/concurrent/pilib
  minor version: 0
  major version: 49
  Constant pool:
Asciz	SourceFile;
Asciz	pilib.scala;
Asciz	<clinit>;
Asciz	()V;
Asciz	Code;
Asciz	serialVersionUID;
Asciz	J;
Asciz	scala/concurrent/pilib$$anonfun$matches$1;
class	scala/concurrent/pilib$$anonfun$matches$1
NameAndType	serialVersionUID:J
Field	scala/concurrent/pilib$$anonfun$matches$1.serialVersionUID:J
Asciz	v2$1;
Asciz	Ljava/lang/Object;;
Asciz	v1$1;
Asciz	d1$1;
Asciz	Z;
Asciz	a1$1;
Asciz	Lscala/concurrent/pilib$UChan;;
Asciz	<init>;
Asciz	(Lscala/concurrent/pilib$UChan;ZLjava/lang/Object;Ljava/lang/Object;)V;
Asciz	LineNumberTable;
NameAndType	a1$1:Lscala/concurrent/pilib$UChan;
Field	scala/concurrent/pilib$$anonfun$matches$1.a1$1:Lscala/concurrent/pilib$UChan;
NameAndType	d1$1:Z
Field	scala/concurrent/pilib$$anonfun$matches$1.d1$1:Z
NameAndType	v1$1:Ljava/lang/Object;
Field	scala/concurrent/pilib$$anonfun$matches$1.v1$1:Ljava/lang/Object;
NameAndType	v2$1:Ljava/lang/Object;
Field	scala/concurrent/pilib$$anonfun$matches$1.v2$1:Ljava/lang/Object;
Asciz	scala/runtime/AbstractFunction0;
class	scala/runtime/AbstractFunction0
NameAndType	"<init>":()V
Method	scala/runtime/AbstractFunction0."<init>":()V
Asciz	apply;
Asciz	()Ljava/lang/Object;;
NameAndType	apply:()V
Method	scala/concurrent/pilib$$anonfun$matches$1.apply:()V
Asciz	scala/runtime/BoxedUnit;
class	scala/runtime/BoxedUnit
Asciz	UNIT;
Asciz	Lscala/runtime/BoxedUnit;;
NameAndType	UNIT:Lscala/runtime/BoxedUnit;
Field	scala/runtime/BoxedUnit.UNIT:Lscala/runtime/BoxedUnit;
Asciz	scala/concurrent/pilib$UChan;
class	scala/concurrent/pilib$UChan
Asciz	log;
Asciz	()Lscala/Function1;;
NameAndType	log:()Lscala/Function1;
Method	scala/concurrent/pilib$UChan.log:()Lscala/Function1;
Asciz	scala/Function1;
class	scala/Function1
Asciz	(Ljava/lang/Object;)Ljava/lang/Object;;
NameAndType	apply:(Ljava/lang/Object;)Ljava/lang/Object;
InterfaceMethod	scala/Function1.apply:(Ljava/lang/Object;)Ljava/lang/Object;
Asciz	Scala;
Asciz	InnerClasses;
Asciz	scala/concurrent/pilib;
class	scala/concurrent/pilib
Asciz	UChan;
Asciz	$anonfun$matches$1;
Asciz	java/io/Serializable;
class	java/io/Serializable

{
public static final long serialVersionUID;
  Signature: J

private final java.lang.Object v2$1;
  Signature: Ljava/lang/Object;

private final java.lang.Object v1$1;
  Signature: Ljava/lang/Object;

private final boolean d1$1;
  Signature: Z

private final scala.concurrent.pilib$UChan a1$1;
  Signature: Lscala/concurrent/pilib$UChan;

public static {};
  Signature: ()V
  Code:
   Stack=2, Locals=0, Args_size=0
	lconst_0
	putstatic	Field serialVersionUID:J
	return
  Labels:

public scala.concurrent.pilib$$anonfun$matches$1(scala.concurrent.pilib$UChan, boolean, java.lang.Object, java.lang.Object);
  Signature: (Lscala/concurrent/pilib$UChan;ZLjava/lang/Object;Ljava/lang/Object;)V
  Code:
   Stack=2, Locals=5, Args_size=5
	aload_0
	aload_1
	putfield	Field a1$1:Lscala/concurrent/pilib$UChan;
	aload_0
	iload_2
	putfield	Field d1$1:Z
	aload_0
	aload_3
	putfield	Field v1$1:Ljava/lang/Object;
	aload_0
	aload	4
	putfield	Field v2$1:Ljava/lang/Object;
	aload_0
	invokespecial	Method scala/runtime/AbstractFunction0."<init>":()V
	return
  Labels:

public final java.lang.Object apply();
  Signature: ()Ljava/lang/Object;
  Code:
   Stack=1, Locals=1, Args_size=1
	aload_0
	invokevirtual	Method apply:()V
	getstatic	Field scala/runtime/BoxedUnit.UNIT:Lscala/runtime/BoxedUnit;
	areturn
  Labels:

public final void apply();
  Signature: ()V
  Code:
   Stack=2, Locals=1, Args_size=1
	aload_0
	getfield	Field d1$1:Z
	ifeq	l1 // aload_0
	aload_0
	getfield	Field a1$1:Lscala/concurrent/pilib$UChan;
	invokevirtual	Method scala/concurrent/pilib$UChan.log:()Lscala/Function1;
	aload_0
	getfield	Field v2$1:Ljava/lang/Object;
	invokeinterface	InterfaceMethod scala/Function1.apply:(Ljava/lang/Object;)Ljava/lang/Object;
	pop
	goto	l2 // return
l1	aload_0
	getfield	Field a1$1:Lscala/concurrent/pilib$UChan;
	invokevirtual	Method scala/concurrent/pilib$UChan.log:()Lscala/Function1;
	aload_0
	getfield	Field v1$1:Ljava/lang/Object;
	invokeinterface	InterfaceMethod scala/Function1.apply:(Ljava/lang/Object;)Ljava/lang/Object;
	pop
l2	return
  Labels:
   	l1 = 27 // aload_0
   	l2 = 44 // return

}

