Compiled from "pilib.scala"
public final class scala.concurrent.pilib$ extends java.lang.Object implements scala.ScalaObject
  SourceFile: "pilib.scala"
  Scala: length = 0x
   
  InnerClass: 
   public #289= #286 of #288; //GP=class scala/concurrent/pilib$GP of class scala/concurrent/pilib
   public #290= #41 of #288; //Sum=class scala/concurrent/pilib$Sum of class scala/concurrent/pilib
   public #291= #201 of #288; //UGP=class scala/concurrent/pilib$UGP of class scala/concurrent/pilib
   public #294= #293 of #288; //Chan=class scala/concurrent/pilib$Chan of class scala/concurrent/pilib
   public abstract #297= #296 of #288; //Spawn=class scala/concurrent/pilib$Spawn of class scala/concurrent/pilib
   public #300= #299 of #288; //UChan=class scala/concurrent/pilib$UChan of class scala/concurrent/pilib
   public #303= #302 of #288; //Product=class scala/concurrent/pilib$Product of class scala/concurrent/pilib
   public final #304= #27 of #288; //$anon$1=class scala/concurrent/pilib$$anon$1 of class scala/concurrent/pilib
   public final #305= #49 of #288; //$anonfun$2=class scala/concurrent/pilib$$anonfun$2 of class scala/concurrent/pilib
   public final #306= #218 of #288; //$anonfun$matches$1=class scala/concurrent/pilib$$anonfun$matches$1 of class scala/concurrent/pilib
   public final #307= #228 of #288; //$anonfun$matches$3=class scala/concurrent/pilib$$anonfun$matches$3 of class scala/concurrent/pilib
   public final #308= #223 of #288; //$anonfun$matches$2=class scala/concurrent/pilib$$anonfun$matches$2 of class scala/concurrent/pilib
  minor version: 0
  major version: 49
  Constant pool:
const #1 = Asciz	SourceFile;
const #2 = Asciz	pilib.scala;
const #3 = Asciz	Scala;
const #4 = Asciz	MODULE$;
const #5 = Asciz	Lscala/concurrent/pilib$;;
const #6 = Asciz	<clinit>;
const #7 = Asciz	()V;
const #8 = Asciz	Code;
const #9 = Asciz	scala/concurrent/pilib$;
const #10 = class	#9;	//  scala/concurrent/pilib$
const #11 = Asciz	<init>;
const #12 = NameAndType	#11:#7;//  "<init>":()V
const #13 = Method	#10.#12;	//  scala/concurrent/pilib$."<init>":()V
const #14 = Asciz	sums;
const #15 = Asciz	Lscala/collection/immutable/List;;
const #16 = Asciz	Lscala/collection/immutable/List<Lscala/concurrent/pilib$Sum;>;;
const #17 = Asciz	Signature;
const #18 = Asciz	spawn;
const #19 = Asciz	Lscala/concurrent/pilib$Spawn;;
const #20 = Asciz	LineNumberTable;
const #21 = Asciz	java/lang/Object;
const #22 = class	#21;	//  java/lang/Object
const #23 = Method	#22.#12;	//  java/lang/Object."<init>":()V
const #24 = NameAndType	#4:#5;//  MODULE$:Lscala/concurrent/pilib$;
const #25 = Field	#10.#24;	//  scala/concurrent/pilib$.MODULE$:Lscala/concurrent/pilib$;
const #26 = Asciz	scala/concurrent/pilib$$anon$1;
const #27 = class	#26;	//  scala/concurrent/pilib$$anon$1
const #28 = Method	#27.#12;	//  scala/concurrent/pilib$$anon$1."<init>":()V
const #29 = NameAndType	#18:#19;//  spawn:Lscala/concurrent/pilib$Spawn;
const #30 = Field	#10.#29;	//  scala/concurrent/pilib$.spawn:Lscala/concurrent/pilib$Spawn;
const #31 = Asciz	scala/collection/immutable/Nil$;
const #32 = class	#31;	//  scala/collection/immutable/Nil$
const #33 = Asciz	Lscala/collection/immutable/Nil$;;
const #34 = NameAndType	#4:#33;//  MODULE$:Lscala/collection/immutable/Nil$;
const #35 = Field	#32.#34;	//  scala/collection/immutable/Nil$.MODULE$:Lscala/collection/immutable/Nil$;
const #36 = NameAndType	#14:#15;//  sums:Lscala/collection/immutable/List;
const #37 = Field	#10.#36;	//  scala/concurrent/pilib$.sums:Lscala/collection/immutable/List;
const #38 = Asciz	choice;
const #39 = Asciz	(Lscala/collection/Sequence;)Ljava/lang/Object;;
const #40 = Asciz	scala/concurrent/pilib$Sum;
const #41 = class	#40;	//  scala/concurrent/pilib$Sum
const #42 = Asciz	scala/collection/generic/TraversableTemplate;
const #43 = class	#42;	//  scala/collection/generic/TraversableTemplate
const #44 = Asciz	toList;
const #45 = Asciz	()Lscala/collection/immutable/List;;
const #46 = NameAndType	#44:#45;//  toList:()Lscala/collection/immutable/List;
const #47 = InterfaceMethod	#43.#46;	//  scala/collection/generic/TraversableTemplate.toList:()Lscala/collection/immutable/List;
const #48 = Asciz	scala/concurrent/pilib$$anonfun$2;
const #49 = class	#48;	//  scala/concurrent/pilib$$anonfun$2
const #50 = Method	#49.#12;	//  scala/concurrent/pilib$$anonfun$2."<init>":()V
const #51 = Asciz	scala/collection/immutable/List$;
const #52 = class	#51;	//  scala/collection/immutable/List$
const #53 = Asciz	Lscala/collection/immutable/List$;;
const #54 = NameAndType	#4:#53;//  MODULE$:Lscala/collection/immutable/List$;
const #55 = Field	#52.#54;	//  scala/collection/immutable/List$.MODULE$:Lscala/collection/immutable/List$;
const #56 = Asciz	builderFactory;
const #57 = Asciz	()Lscala/collection/generic/BuilderFactory;;
const #58 = NameAndType	#56:#57;//  builderFactory:()Lscala/collection/generic/BuilderFactory;
const #59 = Method	#52.#58;	//  scala/collection/immutable/List$.builderFactory:()Lscala/collection/generic/BuilderFactory;
const #60 = Asciz	map;
const #61 = Asciz	(Lscala/Function1;Lscala/collection/generic/BuilderFactory;)Ljava/lang/Object;;
const #62 = NameAndType	#60:#61;//  map:(Lscala/Function1;Lscala/collection/generic/BuilderFactory;)Ljava/lang/Object;
const #63 = InterfaceMethod	#43.#62;	//  scala/collection/generic/TraversableTemplate.map:(Lscala/Function1;Lscala/collection/generic/BuilderFactory;)Ljava/lang/Object;
const #64 = Asciz	scala/collection/immutable/List;
const #65 = class	#64;	//  scala/collection/immutable/List
const #66 = Asciz	(Lscala/collection/immutable/List;)V;
const #67 = NameAndType	#11:#66;//  "<init>":(Lscala/collection/immutable/List;)V
const #68 = Method	#41.#67;	//  scala/concurrent/pilib$Sum."<init>":(Lscala/collection/immutable/List;)V
const #69 = NameAndType	#14:#45;//  sums:()Lscala/collection/immutable/List;
const #70 = Method	#10.#69;	//  scala/concurrent/pilib$.sums:()Lscala/collection/immutable/List;
const #71 = Asciz	compare;
const #72 = Asciz	(Lscala/concurrent/pilib$Sum;Lscala/collection/immutable/List;)Lscala/collection/immutable/List;;
const #73 = NameAndType	#71:#72;//  compare:(Lscala/concurrent/pilib$Sum;Lscala/collection/immutable/List;)Lscala/collection/immutable/List;
const #74 = Method	#10.#73;	//  scala/concurrent/pilib$.compare:(Lscala/concurrent/pilib$Sum;Lscala/collection/immutable/List;)Lscala/collection/immutable/List;
const #75 = Asciz	sums_$eq;
const #76 = NameAndType	#75:#66;//  sums_$eq:(Lscala/collection/immutable/List;)V
const #77 = Method	#10.#76;	//  scala/concurrent/pilib$.sums_$eq:(Lscala/collection/immutable/List;)V
const #78 = Asciz	scala/runtime/BoxedUnit;
const #79 = class	#78;	//  scala/runtime/BoxedUnit
const #80 = Asciz	UNIT;
const #81 = Asciz	Lscala/runtime/BoxedUnit;;
const #82 = NameAndType	#80:#81;//  UNIT:Lscala/runtime/BoxedUnit;
const #83 = Field	#79.#82;	//  scala/runtime/BoxedUnit.UNIT:Lscala/runtime/BoxedUnit;
const #84 = Asciz	continue;
const #85 = Asciz	()Ljava/lang/Object;;
const #86 = NameAndType	#84:#85;//  continue:()Ljava/lang/Object;
const #87 = Method	#41.#86;	//  scala/concurrent/pilib$Sum.continue:()Ljava/lang/Object;
const #88 = Asciz	this;
const #89 = Asciz	s;
const #90 = Asciz	Lscala/collection/Sequence;;
const #91 = Asciz	sum;
const #92 = Asciz	Lscala/concurrent/pilib$Sum;;
const #93 = Asciz	LocalVariableTable;
const #94 = Asciz	<A:Ljava/lang/Object;>(Lscala/collection/Sequence<Lscala/concurrent/pilib$GP<TA;>;>;)TA;;
const #95 = Asciz	equals;
const #96 = Asciz	(Ljava/lang/Object;)Z;
const #97 = NameAndType	#95:#96;//  equals:(Ljava/lang/Object;)Z
const #98 = Method	#22.#97;	//  java/lang/Object.equals:(Ljava/lang/Object;)Z
const #99 = Asciz	scala/runtime/ScalaRunTime$;
const #100 = class	#99;	//  scala/runtime/ScalaRunTime$
const #101 = Asciz	Lscala/runtime/ScalaRunTime$;;
const #102 = NameAndType	#4:#101;//  MODULE$:Lscala/runtime/ScalaRunTime$;
const #103 = Field	#100.#102;	//  scala/runtime/ScalaRunTime$.MODULE$:Lscala/runtime/ScalaRunTime$;
const #104 = Asciz	boxArray;
const #105 = Asciz	(Ljava/lang/Object;)Lscala/runtime/BoxedArray;;
const #106 = NameAndType	#104:#105;//  boxArray:(Ljava/lang/Object;)Lscala/runtime/BoxedArray;
const #107 = Method	#100.#106;	//  scala/runtime/ScalaRunTime$.boxArray:(Ljava/lang/Object;)Lscala/runtime/BoxedArray;
const #108 = Asciz	apply;
const #109 = Asciz	(Lscala/collection/Sequence;)Lscala/collection/immutable/List;;
const #110 = NameAndType	#108:#109;//  apply:(Lscala/collection/Sequence;)Lscala/collection/immutable/List;
const #111 = Method	#52.#110;	//  scala/collection/immutable/List$.apply:(Lscala/collection/Sequence;)Lscala/collection/immutable/List;
const #112 = Asciz	$colon$colon$colon;
const #113 = Asciz	(Lscala/collection/immutable/List;)Lscala/collection/immutable/List;;
const #114 = NameAndType	#112:#113;//  $colon$colon$colon:(Lscala/collection/immutable/List;)Lscala/collection/immutable/List;
const #115 = Method	#65.#114;	//  scala/collection/immutable/List.$colon$colon$colon:(Lscala/collection/immutable/List;)Lscala/collection/immutable/List;
const #116 = Asciz	scala/collection/immutable/$colon$colon;
const #117 = class	#116;	//  scala/collection/immutable/$colon$colon
const #118 = Asciz	hd$1;
const #119 = NameAndType	#118:#85;//  hd$1:()Ljava/lang/Object;
const #120 = Method	#117.#119;	//  scala/collection/immutable/$colon$colon.hd$1:()Ljava/lang/Object;
const #121 = Asciz	tl$1;
const #122 = NameAndType	#121:#45;//  tl$1:()Lscala/collection/immutable/List;
const #123 = Method	#117.#122;	//  scala/collection/immutable/$colon$colon.tl$1:()Lscala/collection/immutable/List;
const #124 = Asciz	gs;
const #125 = NameAndType	#124:#45;//  gs:()Lscala/collection/immutable/List;
const #126 = Method	#41.#125;	//  scala/concurrent/pilib$Sum.gs:()Lscala/collection/immutable/List;
const #127 = Asciz	matches;
const #128 = Asciz	(Lscala/collection/immutable/List;Lscala/collection/immutable/List;)Lscala/Option;;
const #129 = NameAndType	#127:#128;//  matches:(Lscala/collection/immutable/List;Lscala/collection/immutable/List;)Lscala/Option;
const #130 = Method	#10.#129;	//  scala/concurrent/pilib$.matches:(Lscala/collection/immutable/List;Lscala/collection/immutable/List;)Lscala/Option;
const #131 = Asciz	scala/None$;
const #132 = class	#131;	//  scala/None$
const #133 = Asciz	Lscala/None$;;
const #134 = NameAndType	#4:#133;//  MODULE$:Lscala/None$;
const #135 = Field	#132.#134;	//  scala/None$.MODULE$:Lscala/None$;
const #136 = Asciz	$colon$colon;
const #137 = Asciz	(Ljava/lang/Object;)Lscala/collection/immutable/List;;
const #138 = NameAndType	#136:#137;//  $colon$colon:(Ljava/lang/Object;)Lscala/collection/immutable/List;
const #139 = Method	#65.#138;	//  scala/collection/immutable/List.$colon$colon:(Ljava/lang/Object;)Lscala/collection/immutable/List;
const #140 = Asciz	scala/Some;
const #141 = class	#140;	//  scala/Some
const #142 = Asciz	x;
const #143 = NameAndType	#142:#85;//  x:()Ljava/lang/Object;
const #144 = Method	#141.#143;	//  scala/Some.x:()Ljava/lang/Object;
const #145 = Asciz	scala/Tuple3;
const #146 = class	#145;	//  scala/Tuple3
const #147 = Asciz	_1;
const #148 = NameAndType	#147:#85;//  _1:()Ljava/lang/Object;
const #149 = Method	#146.#148;	//  scala/Tuple3._1:()Ljava/lang/Object;
const #150 = Asciz	scala/Function0;
const #151 = class	#150;	//  scala/Function0
const #152 = Asciz	_2;
const #153 = NameAndType	#152:#85;//  _2:()Ljava/lang/Object;
const #154 = Method	#146.#153;	//  scala/Tuple3._2:()Ljava/lang/Object;
const #155 = Asciz	_3;
const #156 = NameAndType	#155:#85;//  _3:()Ljava/lang/Object;
const #157 = Method	#146.#156;	//  scala/Tuple3._3:()Ljava/lang/Object;
const #158 = NameAndType	#108:#85;//  apply:()Ljava/lang/Object;
const #159 = InterfaceMethod	#151.#158;	//  scala/Function0.apply:()Ljava/lang/Object;
const #160 = Asciz	set;
const #161 = Asciz	(Lscala/Function0;)V;
const #162 = NameAndType	#160:#161;//  set:(Lscala/Function0;)V
const #163 = Method	#41.#162;	//  scala/concurrent/pilib$Sum.set:(Lscala/Function0;)V
const #164 = Asciz	scala/MatchError;
const #165 = class	#164;	//  scala/MatchError
const #166 = Asciz	scala/Option;
const #167 = class	#166;	//  scala/Option
const #168 = Asciz	toString;
const #169 = Asciz	()Ljava/lang/String;;
const #170 = NameAndType	#168:#169;//  toString:()Ljava/lang/String;
const #171 = Method	#167.#170;	//  scala/Option.toString:()Ljava/lang/String;
const #172 = Asciz	(Ljava/lang/String;)V;
const #173 = NameAndType	#11:#172;//  "<init>":(Ljava/lang/String;)V
const #174 = Method	#165.#173;	//  scala/MatchError."<init>":(Ljava/lang/String;)V
const #175 = Asciz	scala/collection/generic/SequenceTemplate;
const #176 = class	#175;	//  scala/collection/generic/SequenceTemplate
const #177 = InterfaceMethod	#176.#170;	//  scala/collection/generic/SequenceTemplate.toString:()Ljava/lang/String;
const #178 = Asciz	s1;
const #179 = Asciz	ss;
const #180 = Asciz	temp39;
const #181 = Asciz	temp41;
const #182 = Asciz	Lscala/collection/immutable/$colon$colon;;
const #183 = Asciz	temp42;
const #184 = Asciz	temp43;
const #185 = Asciz	rest;
const #186 = Asciz	s2;
const #187 = Asciz	temp32;
const #188 = Asciz	Lscala/Option;;
const #189 = Asciz	temp34;
const #190 = Asciz	Lscala/Some;;
const #191 = Asciz	temp35;
const #192 = Asciz	Lscala/Tuple3;;
const #193 = Asciz	temp36;
const #194 = Asciz	Lscala/Function0;;
const #195 = Asciz	temp37;
const #196 = Asciz	temp38;
const #197 = Asciz	c2;
const #198 = Asciz	c1;
const #199 = Asciz	(Lscala/concurrent/pilib$Sum;Lscala/collection/immutable/List<Lscala/concurrent/pilib$Sum;>;)Lscala/collection/immutable/List<Lscala/concurrent/pilib$Sum;>;;
const #200 = Asciz	scala/concurrent/pilib$UGP;
const #201 = class	#200;	//  scala/concurrent/pilib$UGP
const #202 = Asciz	n;
const #203 = Asciz	()Lscala/concurrent/pilib$UChan;;
const #204 = NameAndType	#202:#203;//  n:()Lscala/concurrent/pilib$UChan;
const #205 = Method	#201.#204;	//  scala/concurrent/pilib$UGP.n:()Lscala/concurrent/pilib$UChan;
const #206 = Asciz	polarity;
const #207 = Asciz	()Z;
const #208 = NameAndType	#206:#207;//  polarity:()Z
const #209 = Method	#201.#208;	//  scala/concurrent/pilib$UGP.polarity:()Z
const #210 = Asciz	v;
const #211 = NameAndType	#210:#85;//  v:()Ljava/lang/Object;
const #212 = Method	#201.#211;	//  scala/concurrent/pilib$UGP.v:()Ljava/lang/Object;
const #213 = Asciz	c;
const #214 = Asciz	()Lscala/Function1;;
const #215 = NameAndType	#213:#214;//  c:()Lscala/Function1;
const #216 = Method	#201.#215;	//  scala/concurrent/pilib$UGP.c:()Lscala/Function1;
const #217 = Asciz	scala/concurrent/pilib$$anonfun$matches$1;
const #218 = class	#217;	//  scala/concurrent/pilib$$anonfun$matches$1
const #219 = Asciz	(Lscala/concurrent/pilib$UChan;ZLjava/lang/Object;Ljava/lang/Object;)V;
const #220 = NameAndType	#11:#219;//  "<init>":(Lscala/concurrent/pilib$UChan;ZLjava/lang/Object;Ljava/lang/Object;)V
const #221 = Method	#218.#220;	//  scala/concurrent/pilib$$anonfun$matches$1."<init>":(Lscala/concurrent/pilib$UChan;ZLjava/lang/Object;Ljava/lang/Object;)V
const #222 = Asciz	scala/concurrent/pilib$$anonfun$matches$2;
const #223 = class	#222;	//  scala/concurrent/pilib$$anonfun$matches$2
const #224 = Asciz	(Lscala/Function1;Ljava/lang/Object;)V;
const #225 = NameAndType	#11:#224;//  "<init>":(Lscala/Function1;Ljava/lang/Object;)V
const #226 = Method	#223.#225;	//  scala/concurrent/pilib$$anonfun$matches$2."<init>":(Lscala/Function1;Ljava/lang/Object;)V
const #227 = Asciz	scala/concurrent/pilib$$anonfun$matches$3;
const #228 = class	#227;	//  scala/concurrent/pilib$$anonfun$matches$3
const #229 = Asciz	(Ljava/lang/Object;Lscala/Function1;)V;
const #230 = NameAndType	#11:#229;//  "<init>":(Ljava/lang/Object;Lscala/Function1;)V
const #231 = Method	#228.#230;	//  scala/concurrent/pilib$$anonfun$matches$3."<init>":(Ljava/lang/Object;Lscala/Function1;)V
const #232 = Asciz	(Ljava/lang/Object;Ljava/lang/Object;Ljava/lang/Object;)V;
const #233 = NameAndType	#11:#232;//  "<init>":(Ljava/lang/Object;Ljava/lang/Object;Ljava/lang/Object;)V
const #234 = Method	#146.#233;	//  scala/Tuple3."<init>":(Ljava/lang/Object;Ljava/lang/Object;Ljava/lang/Object;)V
const #235 = Asciz	(Ljava/lang/Object;)V;
const #236 = NameAndType	#11:#235;//  "<init>":(Ljava/lang/Object;)V
const #237 = Method	#141.#236;	//  scala/Some."<init>":(Ljava/lang/Object;)V
const #238 = Asciz	scala/Tuple2;
const #239 = class	#238;	//  scala/Tuple2
const #240 = Asciz	(Ljava/lang/Object;Ljava/lang/Object;)V;
const #241 = NameAndType	#11:#240;//  "<init>":(Ljava/lang/Object;Ljava/lang/Object;)V
const #242 = Method	#239.#241;	//  scala/Tuple2."<init>":(Ljava/lang/Object;Ljava/lang/Object;)V
const #243 = Method	#239.#170;	//  scala/Tuple2.toString:()Ljava/lang/String;
const #244 = Asciz	gs1;
const #245 = Asciz	gs2;
const #246 = Asciz	tp1;
const #247 = Asciz	tp2;
const #248 = Asciz	temp18;
const #249 = Asciz	temp19;
const #250 = Asciz	Lscala/concurrent/pilib$UGP;;
const #251 = Asciz	temp20;
const #252 = Asciz	temp21;
const #253 = Asciz	Lscala/concurrent/pilib$UChan;;
const #254 = Asciz	temp22;
const #255 = Asciz	Z;
const #256 = Asciz	temp23;
const #257 = Asciz	Ljava/lang/Object;;
const #258 = Asciz	temp24;
const #259 = Asciz	Lscala/Function1;;
const #260 = Asciz	temp25;
const #261 = Asciz	temp26;
const #262 = Asciz	temp27;
const #263 = Asciz	temp28;
const #264 = Asciz	temp29;
const #265 = Asciz	temp30;
const #266 = Asciz	temp31;
const #267 = Asciz	rest2;
const #268 = Asciz	c2$1;
const #269 = Asciz	v2$1;
const #270 = Asciz	d2;
const #271 = Asciz	a2;
const #272 = Asciz	rest1;
const #273 = Asciz	c1$1;
const #274 = Asciz	v1$1;
const #275 = Asciz	d1$1;
const #276 = Asciz	a1$1;
const #277 = Asciz	temp12;
const #278 = Asciz	temp14;
const #279 = Asciz	temp15;
const #280 = Asciz	(Lscala/collection/immutable/List<Lscala/concurrent/pilib$UGP;>;Lscala/collection/immutable/List<Lscala/concurrent/pilib$UGP;>;)Lscala/Option<Lscala/Tuple3<Lscala/Function0<Ljava/lang/Object;>;Lscala/Function0<Ljava/lang/Object;>;Lscala/Function0<Ljava/lang/Object;>;>;>;;
const #281 = Asciz	(Lscala/collection/immutable/List<Lscala/concurrent/pilib$Sum;>;)V;
const #282 = Asciz	()Lscala/collection/immutable/List<Lscala/concurrent/pilib$Sum;>;;
const #283 = Asciz	()Lscala/concurrent/pilib$Spawn;;
const #284 = Asciz	InnerClasses;
const #285 = Asciz	scala/concurrent/pilib$GP;
const #286 = class	#285;	//  scala/concurrent/pilib$GP
const #287 = Asciz	scala/concurrent/pilib;
const #288 = class	#287;	//  scala/concurrent/pilib
const #289 = Asciz	GP;
const #290 = Asciz	Sum;
const #291 = Asciz	UGP;
const #292 = Asciz	scala/concurrent/pilib$Chan;
const #293 = class	#292;	//  scala/concurrent/pilib$Chan
const #294 = Asciz	Chan;
const #295 = Asciz	scala/concurrent/pilib$Spawn;
const #296 = class	#295;	//  scala/concurrent/pilib$Spawn
const #297 = Asciz	Spawn;
const #298 = Asciz	scala/concurrent/pilib$UChan;
const #299 = class	#298;	//  scala/concurrent/pilib$UChan
const #300 = Asciz	UChan;
const #301 = Asciz	scala/concurrent/pilib$Product;
const #302 = class	#301;	//  scala/concurrent/pilib$Product
const #303 = Asciz	Product;
const #304 = Asciz	$anon$1;
const #305 = Asciz	$anonfun$2;
const #306 = Asciz	$anonfun$matches$1;
const #307 = Asciz	$anonfun$matches$3;
const #308 = Asciz	$anonfun$matches$2;
const #309 = Asciz	scala/ScalaObject;
const #310 = class	#309;	//  scala/ScalaObject

{
public static final scala.concurrent.pilib$ MODULE$;

public static {};
  Code:
   Stack=1, Locals=0, Args_size=0
   0:	new	#10; //class scala/concurrent/pilib$
   3:	invokespecial	#13; //Method "<init>":()V
   6:	return

public java.lang.Object choice(scala.collection.Sequence);
  Code:
   Stack=5, Locals=4, Args_size=2
   0:	new	#41; //class scala/concurrent/pilib$Sum
   3:	dup
   4:	aload_1
   5:	invokeinterface	#47,  1; //InterfaceMethod scala/collection/generic/TraversableTemplate.toList:()Lscala/collection/immutable/List;
   10:	new	#49; //class scala/concurrent/pilib$$anonfun$2
   13:	dup
   14:	invokespecial	#50; //Method scala/concurrent/pilib$$anonfun$2."<init>":()V
   17:	getstatic	#55; //Field scala/collection/immutable/List$.MODULE$:Lscala/collection/immutable/List$;
   20:	invokevirtual	#59; //Method scala/collection/immutable/List$.builderFactory:()Lscala/collection/generic/BuilderFactory;
   23:	invokeinterface	#63,  3; //InterfaceMethod scala/collection/generic/TraversableTemplate.map:(Lscala/Function1;Lscala/collection/generic/BuilderFactory;)Ljava/lang/Object;
   28:	checkcast	#65; //class scala/collection/immutable/List
   31:	invokespecial	#68; //Method scala/concurrent/pilib$Sum."<init>":(Lscala/collection/immutable/List;)V
   34:	astore_2
   35:	aload_0
   36:	dup
   37:	astore_3
   38:	monitorenter
   39:	aload_0
   40:	aload_0
   41:	aload_2
   42:	aload_0
   43:	invokespecial	#70; //Method sums:()Lscala/collection/immutable/List;
   46:	invokespecial	#74; //Method compare:(Lscala/concurrent/pilib$Sum;Lscala/collection/immutable/List;)Lscala/collection/immutable/List;
   49:	invokespecial	#77; //Method sums_$eq:(Lscala/collection/immutable/List;)V
   52:	getstatic	#83; //Field scala/runtime/BoxedUnit.UNIT:Lscala/runtime/BoxedUnit;
   55:	pop
   56:	aload_3
   57:	monitorexit
   58:	aload_2
   59:	invokevirtual	#87; //Method scala/concurrent/pilib$Sum.continue:()Ljava/lang/Object;
   62:	areturn
   63:	aload_3
   64:	monitorexit
   65:	athrow
  Exception table:
   from   to  target type
    39    58    63   any
  LineNumberTable: 
   line 202: 0
   line 203: 35
   line 204: 58
   line 203: 64

  LocalVariableTable: 
   Start  Length  Slot  Name   Signature
   0      66      0    this       Lscala/concurrent/pilib$;
   0      66      1    s       Lscala/collection/Sequence;
   35      27      2    sum       Lscala/concurrent/pilib$Sum;
   63      3      2    sum       Lscala/concurrent/pilib$Sum;

  Signature: length = 0x2
   00 5E 

public scala.concurrent.pilib$Spawn spawn();
  Code:
   Stack=1, Locals=1, Args_size=1
   0:	aload_0
   1:	getfield	#30; //Field spawn:Lscala/concurrent/pilib$Spawn;
   4:	areturn
  LineNumberTable: 
   line 47: 0


}

