Compiled from "pilib.scala"
public final class scala.concurrent.pilib$Chan$$anonfun$read$1 extends java.lang.Object implements scala.Function1,scala.ScalaObject,java.io.Serializable
  SourceFile: "pilib.scala"
  Scala: length = 0x
   
  InnerClass: 
   public Chan=class scala/concurrent/pilib$Chan of class scala/concurrent/pilib
   public final $anonfun$read$1=class scala/concurrent/pilib$Chan$$anonfun$read$1 of class scala/concurrent/pilib$Chan
  minor version: 0
  major version: 49
  Constant pool:
Asciz	SourceFile;
Asciz	pilib.scala;
Asciz	<clinit>;
Asciz	()V;
Asciz	Code;
Asciz	serialVersionUID;
Asciz	J;
Asciz	scala/concurrent/pilib$Chan$$anonfun$read$1;
class	scala/concurrent/pilib$Chan$$anonfun$read$1
NameAndType	serialVersionUID:J
Field	scala/concurrent/pilib$Chan$$anonfun$read$1.serialVersionUID:J
Asciz	res$1;
Asciz	Lscala/runtime/ObjectRef;;
Asciz	<init>;
Asciz	(Lscala/concurrent/pilib$Chan;Lscala/runtime/ObjectRef;)V;
Asciz	LineNumberTable;
NameAndType	res$1:Lscala/runtime/ObjectRef;
Field	scala/concurrent/pilib$Chan$$anonfun$read$1.res$1:Lscala/runtime/ObjectRef;
Asciz	java/lang/Object;
class	java/lang/Object
NameAndType	"<init>":()V
Method	java/lang/Object."<init>":()V
Asciz	scala/Function1$class;
class	scala/Function1$class
Asciz	$init$;
Asciz	(Lscala/Function1;)V;
NameAndType	$init$:(Lscala/Function1;)V
Method	scala/Function1$class.$init$:(Lscala/Function1;)V
Asciz	this;
Asciz	Lscala/concurrent/pilib$Chan$$anonfun$read$1;;
Asciz	$outer;
Asciz	Lscala/concurrent/pilib$Chan;;
Asciz	LocalVariableTable;
Asciz	(Lscala/concurrent/pilib$Chan<TA;>;)V;
Asciz	Signature;
Asciz	apply;
Asciz	(Ljava/lang/Object;)Ljava/lang/Object;;
Asciz	(Ljava/lang/Object;)V;
NameAndType	apply:(Ljava/lang/Object;)V
Method	scala/concurrent/pilib$Chan$$anonfun$read$1.apply:(Ljava/lang/Object;)V
Asciz	scala/runtime/BoxedUnit;
class	scala/runtime/BoxedUnit
Asciz	UNIT;
Asciz	Lscala/runtime/BoxedUnit;;
NameAndType	UNIT:Lscala/runtime/BoxedUnit;
Field	scala/runtime/BoxedUnit.UNIT:Lscala/runtime/BoxedUnit;
Asciz	v1;
Asciz	Ljava/lang/Object;;
Asciz	scala/runtime/ObjectRef;
class	scala/runtime/ObjectRef
Asciz	elem;
NameAndType	elem:Ljava/lang/Object;
Field	scala/runtime/ObjectRef.elem:Ljava/lang/Object;
Asciz	x;
Asciz	(TA;)V;
Asciz	andThen;
Asciz	(Lscala/Function1;)Lscala/Function1;;
Asciz	(Lscala/Function1;Lscala/Function1;)Lscala/Function1;;
NameAndType	andThen:(Lscala/Function1;Lscala/Function1;)Lscala/Function1;
Method	scala/Function1$class.andThen:(Lscala/Function1;Lscala/Function1;)Lscala/Function1;
Asciz	g;
Asciz	Lscala/Function1;;
Asciz	compose;
NameAndType	compose:(Lscala/Function1;Lscala/Function1;)Lscala/Function1;
Method	scala/Function1$class.compose:(Lscala/Function1;Lscala/Function1;)Lscala/Function1;
Asciz	toString;
Asciz	()Ljava/lang/String;;
Asciz	(Lscala/Function1;)Ljava/lang/String;;
NameAndType	toString:(Lscala/Function1;)Ljava/lang/String;
Method	scala/Function1$class.toString:(Lscala/Function1;)Ljava/lang/String;
Asciz	Scala;
Asciz	InnerClasses;
Asciz	scala/concurrent/pilib$Chan;
class	scala/concurrent/pilib$Chan
Asciz	scala/concurrent/pilib;
class	scala/concurrent/pilib
Asciz	Chan;
Asciz	$anonfun$read$1;
Asciz	scala/Function1;
class	scala/Function1
Asciz	scala/ScalaObject;
class	scala/ScalaObject
Asciz	java/io/Serializable;
class	java/io/Serializable

{
public static final long serialVersionUID;
  Signature: J

private final scala.runtime.ObjectRef res$1;
  Signature: Lscala/runtime/ObjectRef;

public static {};
  Signature: ()V
  Code:
   Stack=2, Locals=0, Args_size=0
	lconst_0
	putstatic	Field serialVersionUID:J
	return
  Labels:

public scala.concurrent.pilib$Chan$$anonfun$read$1(scala.concurrent.pilib$Chan, scala.runtime.ObjectRef);
  Signature: (Lscala/concurrent/pilib$Chan;Lscala/runtime/ObjectRef;)V
  Code:
   Stack=2, Locals=3, Args_size=3
	aload_0
	aload_2
	putfield	Field res$1:Lscala/runtime/ObjectRef;
	aload_0
	invokespecial	Method java/lang/Object."<init>":()V
	aload_0
	invokestatic	Method scala/Function1$class.$init$:(Lscala/Function1;)V
	return
  Labels:
  LocalVariableTable: 
   Start  Length  Slot  Name   Signature
   0      14      0    this       Lscala/concurrent/pilib$Chan$$anonfun$read$1;
   0      14      1    $outer       Lscala/concurrent/pilib$Chan;

  Signature: length = 0x2
   00 22 

public final java.lang.Object apply(java.lang.Object);
  Signature: (Ljava/lang/Object;)Ljava/lang/Object;
  Code:
   Stack=2, Locals=2, Args_size=2
	aload_0
	aload_1
	invokevirtual	Method apply:(Ljava/lang/Object;)V
	getstatic	Field scala/runtime/BoxedUnit.UNIT:Lscala/runtime/BoxedUnit;
	areturn
  Labels:
  LocalVariableTable: 
   Start  Length  Slot  Name   Signature
   0      9      0    this       Lscala/concurrent/pilib$Chan$$anonfun$read$1;
   0      9      1    v1       Ljava/lang/Object;


public final void apply(java.lang.Object);
  Signature: (Ljava/lang/Object;)V
  Code:
   Stack=2, Locals=2, Args_size=2
	aload_0
	getfield	Field res$1:Lscala/runtime/ObjectRef;
	aload_1
	putfield	Field scala/runtime/ObjectRef.elem:Ljava/lang/Object;
	return
  Labels:
  LocalVariableTable: 
   Start  Length  Slot  Name   Signature
   0      9      0    this       Lscala/concurrent/pilib$Chan$$anonfun$read$1;
   0      9      1    x       Ljava/lang/Object;

  Signature: length = 0x2
   00 37 

public scala.Function1 andThen(scala.Function1);
  Signature: (Lscala/Function1;)Lscala/Function1;
  Code:
   Stack=2, Locals=2, Args_size=2
	aload_0
	aload_1
	invokestatic	Method scala/Function1$class.andThen:(Lscala/Function1;Lscala/Function1;)Lscala/Function1;
	areturn
  Labels:
  LocalVariableTable: 
   Start  Length  Slot  Name   Signature
   0      6      0    this       Lscala/concurrent/pilib$Chan$$anonfun$read$1;
   0      6      1    g       Lscala/Function1;


public scala.Function1 compose(scala.Function1);
  Signature: (Lscala/Function1;)Lscala/Function1;
  Code:
   Stack=2, Locals=2, Args_size=2
	aload_0
	aload_1
	invokestatic	Method scala/Function1$class.compose:(Lscala/Function1;Lscala/Function1;)Lscala/Function1;
	areturn
  Labels:
  LocalVariableTable: 
   Start  Length  Slot  Name   Signature
   0      6      0    this       Lscala/concurrent/pilib$Chan$$anonfun$read$1;
   0      6      1    g       Lscala/Function1;


public java.lang.String toString();
  Signature: ()Ljava/lang/String;
  Code:
   Stack=1, Locals=1, Args_size=1
	aload_0
	invokestatic	Method scala/Function1$class.toString:(Lscala/Function1;)Ljava/lang/String;
	areturn
  Labels:

}

