Compiled from "pilib.scala"
public final class scala.concurrent.pilib$UGP$ extends java.lang.Object implements scala.Function4,scala.ScalaObject
  SourceFile: "pilib.scala"
  Scala: length = 0x
   
  InnerClass: 
   public #111= #58 of #110; //UGP=class scala/concurrent/pilib$UGP of class scala/concurrent/pilib
   public #112= #29 of #110; //UChan=class scala/concurrent/pilib$UChan of class scala/concurrent/pilib
  minor version: 0
  major version: 49
  Constant pool:
const #1 = Asciz	SourceFile;
const #2 = Asciz	pilib.scala;
const #3 = Asciz	Scala;
const #4 = Asciz	MODULE$;
const #5 = Asciz	Lscala/concurrent/pilib$UGP$;;
const #6 = Asciz	<clinit>;
const #7 = Asciz	()V;
const #8 = Asciz	Code;
const #9 = Asciz	scala/concurrent/pilib$UGP$;
const #10 = class	#9;	//  scala/concurrent/pilib$UGP$
const #11 = Asciz	<init>;
const #12 = NameAndType	#11:#7;//  "<init>":()V
const #13 = Method	#10.#12;	//  scala/concurrent/pilib$UGP$."<init>":()V
const #14 = Asciz	LineNumberTable;
const #15 = Asciz	java/lang/Object;
const #16 = class	#15;	//  java/lang/Object
const #17 = Method	#16.#12;	//  java/lang/Object."<init>":()V
const #18 = NameAndType	#4:#5;//  MODULE$:Lscala/concurrent/pilib$UGP$;
const #19 = Field	#10.#18;	//  scala/concurrent/pilib$UGP$.MODULE$:Lscala/concurrent/pilib$UGP$;
const #20 = Asciz	scala/Function4$class;
const #21 = class	#20;	//  scala/Function4$class
const #22 = Asciz	$init$;
const #23 = Asciz	(Lscala/Function4;)V;
const #24 = NameAndType	#22:#23;//  $init$:(Lscala/Function4;)V
const #25 = Method	#21.#24;	//  scala/Function4$class.$init$:(Lscala/Function4;)V
const #26 = Asciz	apply;
const #27 = Asciz	(Ljava/lang/Object;Ljava/lang/Object;Ljava/lang/Object;Ljava/lang/Object;)Ljava/lang/Object;;
const #28 = Asciz	scala/concurrent/pilib$UChan;
const #29 = class	#28;	//  scala/concurrent/pilib$UChan
const #30 = Asciz	scala/runtime/BoxesRunTime;
const #31 = class	#30;	//  scala/runtime/BoxesRunTime
const #32 = Asciz	unboxToBoolean;
const #33 = Asciz	(Ljava/lang/Object;)Z;
const #34 = NameAndType	#32:#33;//  unboxToBoolean:(Ljava/lang/Object;)Z
const #35 = Method	#31.#34;	//  scala/runtime/BoxesRunTime.unboxToBoolean:(Ljava/lang/Object;)Z
const #36 = Asciz	scala/Function1;
const #37 = class	#36;	//  scala/Function1
const #38 = Asciz	scala/runtime/ScalaRunTime$;
const #39 = class	#38;	//  scala/runtime/ScalaRunTime$
const #40 = Asciz	Lscala/runtime/ScalaRunTime$;;
const #41 = NameAndType	#4:#40;//  MODULE$:Lscala/runtime/ScalaRunTime$;
const #42 = Field	#39.#41;	//  scala/runtime/ScalaRunTime$.MODULE$:Lscala/runtime/ScalaRunTime$;
const #43 = Asciz	boxArray;
const #44 = Asciz	(Ljava/lang/Object;)Lscala/runtime/BoxedArray;;
const #45 = NameAndType	#43:#44;//  boxArray:(Ljava/lang/Object;)Lscala/runtime/BoxedArray;
const #46 = Method	#39.#45;	//  scala/runtime/ScalaRunTime$.boxArray:(Ljava/lang/Object;)Lscala/runtime/BoxedArray;
const #47 = Asciz	(Lscala/concurrent/pilib$UChan;ZLjava/lang/Object;Lscala/Function1;)Lscala/concurrent/pilib$UGP;;
const #48 = NameAndType	#26:#47;//  apply:(Lscala/concurrent/pilib$UChan;ZLjava/lang/Object;Lscala/Function1;)Lscala/concurrent/pilib$UGP;
const #49 = Method	#10.#48;	//  scala/concurrent/pilib$UGP$.apply:(Lscala/concurrent/pilib$UChan;ZLjava/lang/Object;Lscala/Function1;)Lscala/concurrent/pilib$UGP;
const #50 = Asciz	this;
const #51 = Asciz	v1;
const #52 = Asciz	Ljava/lang/Object;;
const #53 = Asciz	v2;
const #54 = Asciz	v3;
const #55 = Asciz	v4;
const #56 = Asciz	LocalVariableTable;
const #57 = Asciz	scala/concurrent/pilib$UGP;
const #58 = class	#57;	//  scala/concurrent/pilib$UGP
const #59 = Asciz	(Lscala/concurrent/pilib$UChan;ZLjava/lang/Object;Lscala/Function1;)V;
const #60 = NameAndType	#11:#59;//  "<init>":(Lscala/concurrent/pilib$UChan;ZLjava/lang/Object;Lscala/Function1;)V
const #61 = Method	#58.#60;	//  scala/concurrent/pilib$UGP."<init>":(Lscala/concurrent/pilib$UChan;ZLjava/lang/Object;Lscala/Function1;)V
const #62 = Asciz	n;
const #63 = Asciz	Lscala/concurrent/pilib$UChan;;
const #64 = Asciz	polarity;
const #65 = Asciz	Z;
const #66 = Asciz	v;
const #67 = Asciz	c;
const #68 = Asciz	Lscala/Function1;;
const #69 = Asciz	unapply;
const #70 = Asciz	(Lscala/concurrent/pilib$UGP;)Lscala/Some;;
const #71 = Asciz	scala/Some;
const #72 = class	#71;	//  scala/Some
const #73 = Asciz	scala/Tuple4;
const #74 = class	#73;	//  scala/Tuple4
const #75 = Asciz	()Lscala/concurrent/pilib$UChan;;
const #76 = NameAndType	#62:#75;//  n:()Lscala/concurrent/pilib$UChan;
const #77 = Method	#58.#76;	//  scala/concurrent/pilib$UGP.n:()Lscala/concurrent/pilib$UChan;
const #78 = Asciz	()Z;
const #79 = NameAndType	#64:#78;//  polarity:()Z
const #80 = Method	#58.#79;	//  scala/concurrent/pilib$UGP.polarity:()Z
const #81 = Asciz	boxToBoolean;
const #82 = Asciz	(Z)Ljava/lang/Boolean;;
const #83 = NameAndType	#81:#82;//  boxToBoolean:(Z)Ljava/lang/Boolean;
const #84 = Method	#31.#83;	//  scala/runtime/BoxesRunTime.boxToBoolean:(Z)Ljava/lang/Boolean;
const #85 = Asciz	()Ljava/lang/Object;;
const #86 = NameAndType	#66:#85;//  v:()Ljava/lang/Object;
const #87 = Method	#58.#86;	//  scala/concurrent/pilib$UGP.v:()Ljava/lang/Object;
const #88 = Asciz	()Lscala/Function1;;
const #89 = NameAndType	#67:#88;//  c:()Lscala/Function1;
const #90 = Method	#58.#89;	//  scala/concurrent/pilib$UGP.c:()Lscala/Function1;
const #91 = Asciz	(Ljava/lang/Object;Ljava/lang/Object;Ljava/lang/Object;Ljava/lang/Object;)V;
const #92 = NameAndType	#11:#91;//  "<init>":(Ljava/lang/Object;Ljava/lang/Object;Ljava/lang/Object;Ljava/lang/Object;)V
const #93 = Method	#74.#92;	//  scala/Tuple4."<init>":(Ljava/lang/Object;Ljava/lang/Object;Ljava/lang/Object;Ljava/lang/Object;)V
const #94 = Asciz	(Ljava/lang/Object;)V;
const #95 = NameAndType	#11:#94;//  "<init>":(Ljava/lang/Object;)V
const #96 = Method	#72.#95;	//  scala/Some."<init>":(Ljava/lang/Object;)V
const #97 = Asciz	x$0;
const #98 = Asciz	Lscala/concurrent/pilib$UGP;;
const #99 = Asciz	curry;
const #100 = Asciz	(Lscala/Function4;)Lscala/Function1;;
const #101 = NameAndType	#99:#100;//  curry:(Lscala/Function4;)Lscala/Function1;
const #102 = Method	#21.#101;	//  scala/Function4$class.curry:(Lscala/Function4;)Lscala/Function1;
const #103 = Asciz	toString;
const #104 = Asciz	()Ljava/lang/String;;
const #105 = Asciz	(Lscala/Function4;)Ljava/lang/String;;
const #106 = NameAndType	#103:#105;//  toString:(Lscala/Function4;)Ljava/lang/String;
const #107 = Method	#21.#106;	//  scala/Function4$class.toString:(Lscala/Function4;)Ljava/lang/String;
const #108 = Asciz	InnerClasses;
const #109 = Asciz	scala/concurrent/pilib;
const #110 = class	#109;	//  scala/concurrent/pilib
const #111 = Asciz	UGP;
const #112 = Asciz	UChan;
const #113 = Asciz	scala/Function4;
const #114 = class	#113;	//  scala/Function4
const #115 = Asciz	scala/ScalaObject;
const #116 = class	#115;	//  scala/ScalaObject

{
public static final scala.concurrent.pilib$UGP$ MODULE$;

public static {};
  Code:
   Stack=1, Locals=0, Args_size=0
   0:	new	#10; //class scala/concurrent/pilib$UGP$
   3:	invokespecial	#13; //Method "<init>":()V
   6:	return

public scala.concurrent.pilib$UGP$();
  Code:
   Stack=1, Locals=1, Args_size=1
   0:	aload_0
   1:	invokespecial	#17; //Method java/lang/Object."<init>":()V
   4:	aload_0
   5:	putstatic	#19; //Field MODULE$:Lscala/concurrent/pilib$UGP$;
   8:	aload_0
   9:	invokestatic	#25; //Method scala/Function4$class.$init$:(Lscala/Function4;)V
   12:	return
  LineNumberTable: 
   line 69: 0


public java.lang.Object apply(java.lang.Object, java.lang.Object, java.lang.Object, java.lang.Object);
  Code:
   Stack=6, Locals=5, Args_size=5
   0:	aload_0
   1:	aload_1
   2:	checkcast	#29; //class scala/concurrent/pilib$UChan
   5:	aload_2
   6:	invokestatic	#35; //Method scala/runtime/BoxesRunTime.unboxToBoolean:(Ljava/lang/Object;)Z
   9:	aload_3
   10:	aload	4
   12:	instanceof	#37; //class scala/Function1
   15:	ifeq	23
   18:	aload	4
   20:	goto	31
   23:	getstatic	#42; //Field scala/runtime/ScalaRunTime$.MODULE$:Lscala/runtime/ScalaRunTime$;
   26:	aload	4
   28:	invokevirtual	#46; //Method scala/runtime/ScalaRunTime$.boxArray:(Ljava/lang/Object;)Lscala/runtime/BoxedArray;
   31:	checkcast	#37; //class scala/Function1
   34:	invokevirtual	#49; //Method apply:(Lscala/concurrent/pilib$UChan;ZLjava/lang/Object;Lscala/Function1;)Lscala/concurrent/pilib$UGP;
   37:	areturn
  LineNumberTable: 
   line 69: 0

  LocalVariableTable: 
   Start  Length  Slot  Name   Signature
   0      38      0    this       Lscala/concurrent/pilib$UGP$;
   0      38      1    v1       Ljava/lang/Object;
   0      38      2    v2       Ljava/lang/Object;
   0      38      3    v3       Ljava/lang/Object;
   0      38      4    v4       Ljava/lang/Object;


public scala.concurrent.pilib$UGP apply(scala.concurrent.pilib$UChan, boolean, java.lang.Object, scala.Function1);
  Code:
   Stack=6, Locals=5, Args_size=5
   0:	new	#58; //class scala/concurrent/pilib$UGP
   3:	dup
   4:	aload_1
   5:	iload_2
   6:	aload_3
   7:	aload	4
   9:	invokespecial	#61; //Method scala/concurrent/pilib$UGP."<init>":(Lscala/concurrent/pilib$UChan;ZLjava/lang/Object;Lscala/Function1;)V
   12:	areturn
  LineNumberTable: 
   line 69: 0

  LocalVariableTable: 
   Start  Length  Slot  Name   Signature
   0      13      0    this       Lscala/concurrent/pilib$UGP$;
   0      13      1    n       Lscala/concurrent/pilib$UChan;
   0      13      2    polarity       Z
   0      13      3    v       Ljava/lang/Object;
   0      13      4    c       Lscala/Function1;


public scala.Some unapply(scala.concurrent.pilib$UGP);
  Code:
   Stack=8, Locals=2, Args_size=2
   0:	new	#72; //class scala/Some
   3:	dup
   4:	new	#74; //class scala/Tuple4
   7:	dup
   8:	aload_1
   9:	invokevirtual	#77; //Method scala/concurrent/pilib$UGP.n:()Lscala/concurrent/pilib$UChan;
   12:	aload_1
   13:	invokevirtual	#80; //Method scala/concurrent/pilib$UGP.polarity:()Z
   16:	invokestatic	#84; //Method scala/runtime/BoxesRunTime.boxToBoolean:(Z)Ljava/lang/Boolean;
   19:	aload_1
   20:	invokevirtual	#87; //Method scala/concurrent/pilib$UGP.v:()Ljava/lang/Object;
   23:	aload_1
   24:	invokevirtual	#90; //Method scala/concurrent/pilib$UGP.c:()Lscala/Function1;
   27:	invokespecial	#93; //Method scala/Tuple4."<init>":(Ljava/lang/Object;Ljava/lang/Object;Ljava/lang/Object;Ljava/lang/Object;)V
   30:	invokespecial	#96; //Method scala/Some."<init>":(Ljava/lang/Object;)V
   33:	areturn
  LineNumberTable: 
   line 69: 0

  LocalVariableTable: 
   Start  Length  Slot  Name   Signature
   0      34      0    this       Lscala/concurrent/pilib$UGP$;
   0      34      1    x$0       Lscala/concurrent/pilib$UGP;


public scala.Function1 curry();
  Code:
   Stack=1, Locals=1, Args_size=1
   0:	aload_0
   1:	invokestatic	#102; //Method scala/Function4$class.curry:(Lscala/Function4;)Lscala/Function1;
   4:	areturn
  LineNumberTable: 
   line 69: 0


public java.lang.String toString();
  Code:
   Stack=1, Locals=1, Args_size=1
   0:	aload_0
   1:	invokestatic	#107; //Method scala/Function4$class.toString:(Lscala/Function4;)Ljava/lang/String;
   4:	areturn
  LineNumberTable: 
   line 69: 0


}

