Compiled from "pilib.scala"
public class scala.concurrent.pilib$Chan extends scala.concurrent.pilib$UChan implements scala.Function1,scala.ScalaObject
  SourceFile: "pilib.scala"
  Signature: length = 0x2
   00 FFFFFF97 
  Scala: length = 0x
   
  InnerClass: 
   public GP=class scala/concurrent/pilib$GP of class scala/concurrent/pilib
   public Chan=class scala/concurrent/pilib$Chan of class scala/concurrent/pilib
   public UChan=class scala/concurrent/pilib$UChan of class scala/concurrent/pilib
   public Product=class scala/concurrent/pilib$Product of class scala/concurrent/pilib
   public final $anonfun$read$1=class scala/concurrent/pilib$Chan$$anonfun$read$1 of class scala/concurrent/pilib$Chan
   public final $anonfun$input$1=class scala/concurrent/pilib$Chan$$anonfun$input$1 of class scala/concurrent/pilib$Chan
   public final $anonfun$write$1=class scala/concurrent/pilib$Chan$$anonfun$write$1 of class scala/concurrent/pilib$Chan
   public final $anonfun$output$1=class scala/concurrent/pilib$Chan$$anonfun$output$1 of class scala/concurrent/pilib$Chan
   public final $anonfun$attach$1=class scala/concurrent/pilib$Chan$$anonfun$attach$1 of class scala/concurrent/pilib$Chan
  minor version: 0
  major version: 49
  Constant pool:
Asciz	SourceFile;
Asciz	pilib.scala;
Asciz	defaultValue;
Asciz	Ljava/lang/Object;;
Asciz	TA;;
Asciz	Signature;
Asciz	<init>;
Asciz	()V;
Asciz	Code;
Asciz	LineNumberTable;
Asciz	scala/concurrent/pilib$UChan;
class	scala/concurrent/pilib$UChan
NameAndType	"<init>":()V
Method	scala/concurrent/pilib$UChan."<init>":()V
Asciz	scala/Function1$class;
class	scala/Function1$class
Asciz	$init$;
Asciz	(Lscala/Function1;)V;
NameAndType	$init$:(Lscala/Function1;)V
Method	scala/Function1$class.$init$:(Lscala/Function1;)V
Asciz	apply;
Asciz	(Ljava/lang/Object;)Ljava/lang/Object;;
Asciz	scala/concurrent/pilib$Chan;
class	scala/concurrent/pilib$Chan
Asciz	(Ljava/lang/Object;)Lscala/concurrent/pilib$Product;;
NameAndType	apply:(Ljava/lang/Object;)Lscala/concurrent/pilib$Product;
Method	scala/concurrent/pilib$Chan.apply:(Ljava/lang/Object;)Lscala/concurrent/pilib$Product;
Asciz	this;
Asciz	Lscala/concurrent/pilib$Chan;;
Asciz	v1;
Asciz	LocalVariableTable;
Asciz	attach;
Asciz	scala/concurrent/pilib$Chan$$anonfun$attach$1;
class	scala/concurrent/pilib$Chan$$anonfun$attach$1
Asciz	(Lscala/concurrent/pilib$Chan;Lscala/Function1;)V;
NameAndType	"<init>":(Lscala/concurrent/pilib$Chan;Lscala/Function1;)V
Method	scala/concurrent/pilib$Chan$$anonfun$attach$1."<init>":(Lscala/concurrent/pilib$Chan;Lscala/Function1;)V
Asciz	log_$eq;
NameAndType	log_$eq:(Lscala/Function1;)V
Method	scala/concurrent/pilib$Chan.log_$eq:(Lscala/Function1;)V
Asciz	f$1;
Asciz	Lscala/Function1;;
Asciz	(Lscala/Function1<TA;Ljava/lang/Object;>;)V;
Asciz	scala/concurrent/pilib$Product;
class	scala/concurrent/pilib$Product
Asciz	(Lscala/concurrent/pilib$Chan;Ljava/lang/Object;)V;
NameAndType	"<init>":(Lscala/concurrent/pilib$Chan;Ljava/lang/Object;)V
Method	scala/concurrent/pilib$Product."<init>":(Lscala/concurrent/pilib$Chan;Ljava/lang/Object;)V
Asciz	v;
Asciz	(TA;)Lscala/concurrent/pilib$Product<TA;>;;
Asciz	$times;
Asciz	(Lscala/Function1;)Lscala/concurrent/pilib$GP;;
Asciz	input;
NameAndType	input:(Lscala/Function1;)Lscala/concurrent/pilib$GP;
Method	scala/concurrent/pilib$Chan.input:(Lscala/Function1;)Lscala/concurrent/pilib$GP;
Asciz	f;
Asciz	<B:Ljava/lang/Object;>(Lscala/Function1<TA;TB;>;)Lscala/concurrent/pilib$GP<TB;>;;
Asciz	write;
Asciz	(Ljava/lang/Object;)V;
Asciz	scala/concurrent/pilib$;
class	scala/concurrent/pilib$
Asciz	MODULE$;
Asciz	Lscala/concurrent/pilib$;;
NameAndType	MODULE$:Lscala/concurrent/pilib$;
Field	scala/concurrent/pilib$.MODULE$:Lscala/concurrent/pilib$;
Asciz	scala/Predef$;
class	scala/Predef$
Asciz	Lscala/Predef$;;
NameAndType	MODULE$:Lscala/Predef$;
Field	scala/Predef$.MODULE$:Lscala/Predef$;
Asciz	scala/concurrent/pilib$GP;
class	scala/concurrent/pilib$GP
Asciz	scala/concurrent/pilib$Chan$$anonfun$write$1;
class	scala/concurrent/pilib$Chan$$anonfun$write$1
Asciz	(Lscala/concurrent/pilib$Chan;)V;
NameAndType	"<init>":(Lscala/concurrent/pilib$Chan;)V
Method	scala/concurrent/pilib$Chan$$anonfun$write$1."<init>":(Lscala/concurrent/pilib$Chan;)V
Asciz	output;
Asciz	(Ljava/lang/Object;Lscala/Function0;)Lscala/concurrent/pilib$GP;;
NameAndType	output:(Ljava/lang/Object;Lscala/Function0;)Lscala/concurrent/pilib$GP;
Method	scala/concurrent/pilib$Chan.output:(Ljava/lang/Object;Lscala/Function0;)Lscala/concurrent/pilib$GP;
Asciz	[Ljava/lang/Object;;
class	"[Ljava/lang/Object;"
Asciz	wrapRefArray;
Asciz	([Ljava/lang/Object;)Lscala/collection/mutable/WrappedArray;;
NameAndType	wrapRefArray:([Ljava/lang/Object;)Lscala/collection/mutable/WrappedArray;
Method	scala/Predef$.wrapRefArray:([Ljava/lang/Object;)Lscala/collection/mutable/WrappedArray;
Asciz	choice;
Asciz	(Lscala/collection/Seq;)Ljava/lang/Object;;
NameAndType	choice:(Lscala/collection/Seq;)Ljava/lang/Object;
Method	scala/concurrent/pilib$.choice:(Lscala/collection/Seq;)Ljava/lang/Object;
Asciz	x;
Asciz	(TA;)V;
Asciz	read;
Asciz	()Ljava/lang/Object;;
Asciz	scala/runtime/ObjectRef;
class	scala/runtime/ObjectRef
NameAndType	defaultValue:()Ljava/lang/Object;
Method	scala/concurrent/pilib$Chan.defaultValue:()Ljava/lang/Object;
NameAndType	"<init>":(Ljava/lang/Object;)V
Method	scala/runtime/ObjectRef."<init>":(Ljava/lang/Object;)V
Asciz	scala/concurrent/pilib$Chan$$anonfun$read$1;
class	scala/concurrent/pilib$Chan$$anonfun$read$1
Asciz	(Lscala/concurrent/pilib$Chan;Lscala/runtime/ObjectRef;)V;
NameAndType	"<init>":(Lscala/concurrent/pilib$Chan;Lscala/runtime/ObjectRef;)V
Method	scala/concurrent/pilib$Chan$$anonfun$read$1."<init>":(Lscala/concurrent/pilib$Chan;Lscala/runtime/ObjectRef;)V
Asciz	elem;
NameAndType	elem:Ljava/lang/Object;
Field	scala/runtime/ObjectRef.elem:Ljava/lang/Object;
Asciz	res$1;
Asciz	Lscala/runtime/ObjectRef;;
Asciz	()TA;;
Asciz	scala/concurrent/pilib$Chan$$anonfun$output$1;
class	scala/concurrent/pilib$Chan$$anonfun$output$1
Asciz	(Lscala/concurrent/pilib$Chan;Lscala/Function0;)V;
NameAndType	"<init>":(Lscala/concurrent/pilib$Chan;Lscala/Function0;)V
Method	scala/concurrent/pilib$Chan$$anonfun$output$1."<init>":(Lscala/concurrent/pilib$Chan;Lscala/Function0;)V
Asciz	(Lscala/concurrent/pilib$UChan;ZLjava/lang/Object;Lscala/Function1;)V;
NameAndType	"<init>":(Lscala/concurrent/pilib$UChan;ZLjava/lang/Object;Lscala/Function1;)V
Method	scala/concurrent/pilib$GP."<init>":(Lscala/concurrent/pilib$UChan;ZLjava/lang/Object;Lscala/Function1;)V
Asciz	c$3;
Asciz	Lscala/Function0;;
Asciz	<B:Ljava/lang/Object;>(TA;Lscala/Function0<TB;>;)Lscala/concurrent/pilib$GP<TB;>;;
Asciz	scala/runtime/BoxedUnit;
class	scala/runtime/BoxedUnit
Asciz	UNIT;
Asciz	Lscala/runtime/BoxedUnit;;
NameAndType	UNIT:Lscala/runtime/BoxedUnit;
Field	scala/runtime/BoxedUnit.UNIT:Lscala/runtime/BoxedUnit;
Asciz	scala/concurrent/pilib$Chan$$anonfun$input$1;
class	scala/concurrent/pilib$Chan$$anonfun$input$1
Method	scala/concurrent/pilib$Chan$$anonfun$input$1."<init>":(Lscala/concurrent/pilib$Chan;Lscala/Function1;)V
Asciz	c$2;
Asciz	defaultValue_$eq;
NameAndType	defaultValue:Ljava/lang/Object;
Field	scala/concurrent/pilib$Chan.defaultValue:Ljava/lang/Object;
Asciz	andThen;
Asciz	(Lscala/Function1;)Lscala/Function1;;
Asciz	(Lscala/Function1;Lscala/Function1;)Lscala/Function1;;
NameAndType	andThen:(Lscala/Function1;Lscala/Function1;)Lscala/Function1;
Method	scala/Function1$class.andThen:(Lscala/Function1;Lscala/Function1;)Lscala/Function1;
Asciz	g;
Asciz	compose;
NameAndType	compose:(Lscala/Function1;Lscala/Function1;)Lscala/Function1;
Method	scala/Function1$class.compose:(Lscala/Function1;Lscala/Function1;)Lscala/Function1;
Asciz	toString;
Asciz	()Ljava/lang/String;;
Asciz	(Lscala/Function1;)Ljava/lang/String;;
NameAndType	toString:(Lscala/Function1;)Ljava/lang/String;
Method	scala/Function1$class.toString:(Lscala/Function1;)Ljava/lang/String;
Asciz	<A:Ljava/lang/Object;>Lscala/concurrent/pilib$UChan;Lscala/Function1<TA;Lscala/concurrent/pilib$Product<TA;>;>;Lscala/ScalaObject;;
Asciz	Scala;
Asciz	InnerClasses;
Asciz	scala/concurrent/pilib;
class	scala/concurrent/pilib
Asciz	GP;
Asciz	Chan;
Asciz	UChan;
Asciz	Product;
Asciz	$anonfun$read$1;
Asciz	$anonfun$input$1;
Asciz	$anonfun$write$1;
Asciz	$anonfun$output$1;
Asciz	$anonfun$attach$1;
Asciz	scala/Function1;
class	scala/Function1
Asciz	scala/ScalaObject;
class	scala/ScalaObject

{
private java.lang.Object defaultValue;
  Signature: Ljava/lang/Object;
  Signature: length = 0x2
   00 05 

public scala.concurrent.pilib$Chan();
  Signature: ()V
  Code:
   Stack=1, Locals=1, Args_size=1
	aload_0
	invokespecial	Method scala/concurrent/pilib$UChan."<init>":()V
	aload_0
	invokestatic	Method scala/Function1$class.$init$:(Lscala/Function1;)V
	return
  Labels:
  Signature: length = 0x2
   00 08 

public java.lang.Object apply(java.lang.Object);
  Signature: (Ljava/lang/Object;)Ljava/lang/Object;
  Code:
   Stack=2, Locals=2, Args_size=2
	aload_0
	aload_1
	invokevirtual	Method apply:(Ljava/lang/Object;)Lscala/concurrent/pilib$Product;
	areturn
  Labels:
  LocalVariableTable: 
   Start  Length  Slot  Name   Signature
   0      6      0    this       Lscala/concurrent/pilib$Chan;
   0      6      1    v1       Ljava/lang/Object;


public void attach(scala.Function1);
  Signature: (Lscala/Function1;)V
  Code:
   Stack=5, Locals=2, Args_size=2
	aload_0
	new	class scala/concurrent/pilib$Chan$$anonfun$attach$1
	dup
	aload_0
	aload_1
	invokespecial	Method scala/concurrent/pilib$Chan$$anonfun$attach$1."<init>":(Lscala/concurrent/pilib$Chan;Lscala/Function1;)V
	invokevirtual	Method log_$eq:(Lscala/Function1;)V
	return
  Labels:
  LocalVariableTable: 
   Start  Length  Slot  Name   Signature
   0      14      0    this       Lscala/concurrent/pilib$Chan;
   0      14      1    f$1       Lscala/Function1;

  Signature: length = 0x2
   00 2B 

public scala.concurrent.pilib$Product apply(java.lang.Object);
  Signature: (Ljava/lang/Object;)Lscala/concurrent/pilib$Product;
  Code:
   Stack=4, Locals=2, Args_size=2
	new	class scala/concurrent/pilib$Product
	dup
	aload_0
	aload_1
	invokespecial	Method scala/concurrent/pilib$Product."<init>":(Lscala/concurrent/pilib$Chan;Ljava/lang/Object;)V
	areturn
  Labels:
  LocalVariableTable: 
   Start  Length  Slot  Name   Signature
   0      10      0    this       Lscala/concurrent/pilib$Chan;
   0      10      1    v       Ljava/lang/Object;

  Signature: length = 0x2
   00 32 

public scala.concurrent.pilib$GP $times(scala.Function1);
  Signature: (Lscala/Function1;)Lscala/concurrent/pilib$GP;
  Code:
   Stack=2, Locals=2, Args_size=2
	aload_0
	aload_1
	invokevirtual	Method input:(Lscala/Function1;)Lscala/concurrent/pilib$GP;
	areturn
  Labels:
  LocalVariableTable: 
   Start  Length  Slot  Name   Signature
   0      6      0    this       Lscala/concurrent/pilib$Chan;
   0      6      1    f       Lscala/Function1;

  Signature: length = 0x2
   00 39 

public void write(java.lang.Object);
  Signature: (Ljava/lang/Object;)V
  Code:
   Stack=10, Locals=2, Args_size=2
	getstatic	Field scala/concurrent/pilib$.MODULE$:Lscala/concurrent/pilib$;
	getstatic	Field scala/Predef$.MODULE$:Lscala/Predef$;
	iconst_1
	anewarray	class scala/concurrent/pilib$GP
	dup
	iconst_0
	aload_0
	aload_1
	new	class scala/concurrent/pilib$Chan$$anonfun$write$1
	dup
	aload_0
	invokespecial	Method scala/concurrent/pilib$Chan$$anonfun$write$1."<init>":(Lscala/concurrent/pilib$Chan;)V
	invokevirtual	Method output:(Ljava/lang/Object;Lscala/Function0;)Lscala/concurrent/pilib$GP;
	aastore
	checkcast	class "[Ljava/lang/Object;"
	invokevirtual	Method scala/Predef$.wrapRefArray:([Ljava/lang/Object;)Lscala/collection/mutable/WrappedArray;
	invokevirtual	Method scala/concurrent/pilib$.choice:(Lscala/collection/Seq;)Ljava/lang/Object;
	pop
	return
  Labels:
  LocalVariableTable: 
   Start  Length  Slot  Name   Signature
   0      37      0    this       Lscala/concurrent/pilib$Chan;
   0      37      1    x       Ljava/lang/Object;

  Signature: length = 0x2
   00 5D 

public java.lang.Object read();
  Signature: ()Ljava/lang/Object;
  Code:
   Stack=10, Locals=2, Args_size=1
	new	class scala/runtime/ObjectRef
	dup
	aload_0
	invokevirtual	Method defaultValue:()Ljava/lang/Object;
	invokespecial	Method scala/runtime/ObjectRef."<init>":(Ljava/lang/Object;)V
	astore_1
	getstatic	Field scala/concurrent/pilib$.MODULE$:Lscala/concurrent/pilib$;
	getstatic	Field scala/Predef$.MODULE$:Lscala/Predef$;
	iconst_1
	anewarray	class scala/concurrent/pilib$GP
	dup
	iconst_0
	aload_0
	new	class scala/concurrent/pilib$Chan$$anonfun$read$1
	dup
	aload_0
	aload_1
	invokespecial	Method scala/concurrent/pilib$Chan$$anonfun$read$1."<init>":(Lscala/concurrent/pilib$Chan;Lscala/runtime/ObjectRef;)V
	invokevirtual	Method input:(Lscala/Function1;)Lscala/concurrent/pilib$GP;
	aastore
	checkcast	class "[Ljava/lang/Object;"
	invokevirtual	Method scala/Predef$.wrapRefArray:([Ljava/lang/Object;)Lscala/collection/mutable/WrappedArray;
	invokevirtual	Method scala/concurrent/pilib$.choice:(Lscala/collection/Seq;)Ljava/lang/Object;
	pop
	aload_1
	getfield	Field scala/runtime/ObjectRef.elem:Ljava/lang/Object;
	areturn
  Labels:
  LocalVariableTable: 
   Start  Length  Slot  Name   Signature
   0      53      0    this       Lscala/concurrent/pilib$Chan;
   12      40      1    res$1       Lscala/runtime/ObjectRef;

  Signature: length = 0x2
   00 70 

public scala.concurrent.pilib$GP output(java.lang.Object, scala.Function0);
  Signature: (Ljava/lang/Object;Lscala/Function0;)Lscala/concurrent/pilib$GP;
  Code:
   Stack=9, Locals=3, Args_size=3
	new	class scala/concurrent/pilib$GP
	dup
	aload_0
	iconst_0
	aload_1
	new	class scala/concurrent/pilib$Chan$$anonfun$output$1
	dup
	aload_0
	aload_2
	invokespecial	Method scala/concurrent/pilib$Chan$$anonfun$output$1."<init>":(Lscala/concurrent/pilib$Chan;Lscala/Function0;)V
	invokespecial	Method scala/concurrent/pilib$GP."<init>":(Lscala/concurrent/pilib$UChan;ZLjava/lang/Object;Lscala/Function1;)V
	areturn
  Labels:
  LocalVariableTable: 
   Start  Length  Slot  Name   Signature
   0      20      0    this       Lscala/concurrent/pilib$Chan;
   0      20      1    v       Ljava/lang/Object;
   0      20      2    c$3       Lscala/Function0;

  Signature: length = 0x2
   00 7B 

public scala.concurrent.pilib$GP input(scala.Function1);
  Signature: (Lscala/Function1;)Lscala/concurrent/pilib$GP;
  Code:
   Stack=9, Locals=2, Args_size=2
	new	class scala/concurrent/pilib$GP
	dup
	aload_0
	iconst_1
	getstatic	Field scala/runtime/BoxedUnit.UNIT:Lscala/runtime/BoxedUnit;
	new	class scala/concurrent/pilib$Chan$$anonfun$input$1
	dup
	aload_0
	aload_1
	invokespecial	Method scala/concurrent/pilib$Chan$$anonfun$input$1."<init>":(Lscala/concurrent/pilib$Chan;Lscala/Function1;)V
	invokespecial	Method scala/concurrent/pilib$GP."<init>":(Lscala/concurrent/pilib$UChan;ZLjava/lang/Object;Lscala/Function1;)V
	areturn
  Labels:
  LocalVariableTable: 
   Start  Length  Slot  Name   Signature
   0      22      0    this       Lscala/concurrent/pilib$Chan;
   0      22      1    c$2       Lscala/Function1;

  Signature: length = 0x2
   00 39 

public void defaultValue_$eq(java.lang.Object);
  Signature: (Ljava/lang/Object;)V
  Code:
   Stack=2, Locals=2, Args_size=2
	aload_0
	aload_1
	putfield	Field defaultValue:Ljava/lang/Object;
	return
  Labels:
  Signature: length = 0x2
   00 5D 

public java.lang.Object defaultValue();
  Signature: ()Ljava/lang/Object;
  Code:
   Stack=1, Locals=1, Args_size=1
	aload_0
	getfield	Field defaultValue:Ljava/lang/Object;
	areturn
  Labels:
  Signature: length = 0x2
   00 70 

public scala.Function1 andThen(scala.Function1);
  Signature: (Lscala/Function1;)Lscala/Function1;
  Code:
   Stack=2, Locals=2, Args_size=2
	aload_0
	aload_1
	invokestatic	Method scala/Function1$class.andThen:(Lscala/Function1;Lscala/Function1;)Lscala/Function1;
	areturn
  Labels:
  LocalVariableTable: 
   Start  Length  Slot  Name   Signature
   0      6      0    this       Lscala/concurrent/pilib$Chan;
   0      6      1    g       Lscala/Function1;


public scala.Function1 compose(scala.Function1);
  Signature: (Lscala/Function1;)Lscala/Function1;
  Code:
   Stack=2, Locals=2, Args_size=2
	aload_0
	aload_1
	invokestatic	Method scala/Function1$class.compose:(Lscala/Function1;Lscala/Function1;)Lscala/Function1;
	areturn
  Labels:
  LocalVariableTable: 
   Start  Length  Slot  Name   Signature
   0      6      0    this       Lscala/concurrent/pilib$Chan;
   0      6      1    g       Lscala/Function1;


public java.lang.String toString();
  Signature: ()Ljava/lang/String;
  Code:
   Stack=1, Locals=1, Args_size=1
	aload_0
	invokestatic	Method scala/Function1$class.toString:(Lscala/Function1;)Ljava/lang/String;
	areturn
  Labels:

}

