Compiled from "pilib.scala"
public final class scala.concurrent.pilib$$anonfun$matches$2 extends java.lang.Object implements scala.Function0,scala.ScalaObject,java.io.Serializable
  SourceFile: "pilib.scala"
  Scala: length = 0x
   
  InnerClass: 
   public final $anonfun$matches$2=class scala/concurrent/pilib$$anonfun$matches$2 of class scala/concurrent/pilib
  minor version: 0
  major version: 49
  Constant pool:
Asciz	SourceFile;
Asciz	pilib.scala;
Asciz	<clinit>;
Asciz	()V;
Asciz	Code;
Asciz	serialVersionUID;
Asciz	J;
Asciz	scala/concurrent/pilib$$anonfun$matches$2;
class	scala/concurrent/pilib$$anonfun$matches$2
NameAndType	serialVersionUID:J
Field	scala/concurrent/pilib$$anonfun$matches$2.serialVersionUID:J
Asciz	v2$1;
Asciz	Ljava/lang/Object;;
Asciz	c1$1;
Asciz	Lscala/Function1;;
Asciz	<init>;
Asciz	(Lscala/Function1;Ljava/lang/Object;)V;
Asciz	LineNumberTable;
NameAndType	c1$1:Lscala/Function1;
Field	scala/concurrent/pilib$$anonfun$matches$2.c1$1:Lscala/Function1;
NameAndType	v2$1:Ljava/lang/Object;
Field	scala/concurrent/pilib$$anonfun$matches$2.v2$1:Ljava/lang/Object;
Asciz	java/lang/Object;
class	java/lang/Object
NameAndType	"<init>":()V
Method	java/lang/Object."<init>":()V
Asciz	scala/Function0$class;
class	scala/Function0$class
Asciz	$init$;
Asciz	(Lscala/Function0;)V;
NameAndType	$init$:(Lscala/Function0;)V
Method	scala/Function0$class.$init$:(Lscala/Function0;)V
Asciz	apply;
Asciz	()Ljava/lang/Object;;
Asciz	scala/Function1;
class	scala/Function1
Asciz	(Ljava/lang/Object;)Ljava/lang/Object;;
NameAndType	apply:(Ljava/lang/Object;)Ljava/lang/Object;
InterfaceMethod	scala/Function1.apply:(Ljava/lang/Object;)Ljava/lang/Object;
Asciz	toString;
Asciz	()Ljava/lang/String;;
Asciz	(Lscala/Function0;)Ljava/lang/String;;
NameAndType	toString:(Lscala/Function0;)Ljava/lang/String;
Method	scala/Function0$class.toString:(Lscala/Function0;)Ljava/lang/String;
Asciz	Scala;
Asciz	InnerClasses;
Asciz	scala/concurrent/pilib;
class	scala/concurrent/pilib
Asciz	$anonfun$matches$2;
Asciz	scala/Function0;
class	scala/Function0
Asciz	scala/ScalaObject;
class	scala/ScalaObject
Asciz	java/io/Serializable;
class	java/io/Serializable

{
public static final long serialVersionUID;
  Signature: J

private final java.lang.Object v2$1;
  Signature: Ljava/lang/Object;

private final scala.Function1 c1$1;
  Signature: Lscala/Function1;

public static {};
  Signature: ()V
  Code:
   Stack=2, Locals=0, Args_size=0
	lconst_0
	putstatic	Field serialVersionUID:J
	return
  Labels:

public scala.concurrent.pilib$$anonfun$matches$2(scala.Function1, java.lang.Object);
  Signature: (Lscala/Function1;Ljava/lang/Object;)V
  Code:
   Stack=2, Locals=3, Args_size=3
	aload_0
	aload_1
	putfield	Field c1$1:Lscala/Function1;
	aload_0
	aload_2
	putfield	Field v2$1:Ljava/lang/Object;
	aload_0
	invokespecial	Method java/lang/Object."<init>":()V
	aload_0
	invokestatic	Method scala/Function0$class.$init$:(Lscala/Function0;)V
	return
  Labels:

public final java.lang.Object apply();
  Signature: ()Ljava/lang/Object;
  Code:
   Stack=2, Locals=1, Args_size=1
	aload_0
	getfield	Field c1$1:Lscala/Function1;
	aload_0
	getfield	Field v2$1:Ljava/lang/Object;
	invokeinterface	InterfaceMethod scala/Function1.apply:(Ljava/lang/Object;)Ljava/lang/Object;
	areturn
  Labels:

public java.lang.String toString();
  Signature: ()Ljava/lang/String;
  Code:
   Stack=1, Locals=1, Args_size=1
	aload_0
	invokestatic	Method scala/Function0$class.toString:(Lscala/Function0;)Ljava/lang/String;
	areturn
  Labels:

}

