Compiled from "pilib.scala"
public final class scala.concurrent.pilib$ extends java.lang.Object implements scala.ScalaObject
  SourceFile: "pilib.scala"
  Scala: length = 0x
   
  InnerClass: 
   public GP=class scala/concurrent/pilib$GP of class scala/concurrent/pilib
   public Sum=class scala/concurrent/pilib$Sum of class scala/concurrent/pilib
   public UGP=class scala/concurrent/pilib$UGP of class scala/concurrent/pilib
   public Chan=class scala/concurrent/pilib$Chan of class scala/concurrent/pilib
   public UChan=class scala/concurrent/pilib$UChan of class scala/concurrent/pilib
   public abstract Spawn=class scala/concurrent/pilib$Spawn of class scala/concurrent/pilib
   public final $anon$1=class scala/concurrent/pilib$$anon$1 of class scala/concurrent/pilib
   public Product=class scala/concurrent/pilib$Product of class scala/concurrent/pilib
   public final $anonfun$2=class scala/concurrent/pilib$$anonfun$2 of class scala/concurrent/pilib
   public final $anonfun$matches$3=class scala/concurrent/pilib$$anonfun$matches$3 of class scala/concurrent/pilib
   public final $anonfun$matches$2=class scala/concurrent/pilib$$anonfun$matches$2 of class scala/concurrent/pilib
   public final $anonfun$matches$1=class scala/concurrent/pilib$$anonfun$matches$1 of class scala/concurrent/pilib
   public GenericCanBuildFrom=class scala/collection/generic/TraversableFactory$GenericCanBuildFrom of class scala/collection/generic/TraversableFactory
  minor version: 0
  major version: 49
  Constant pool:
Asciz	SourceFile;
Asciz	pilib.scala;
Asciz	Scala;
Asciz	MODULE$;
Asciz	Lscala/concurrent/pilib$;;
Asciz	<clinit>;
Asciz	()V;
Asciz	Code;
Asciz	scala/concurrent/pilib$;
class	scala/concurrent/pilib$
Asciz	<init>;
NameAndType	"<init>":()V
Method	scala/concurrent/pilib$."<init>":()V
Asciz	sums;
Asciz	Lscala/collection/immutable/List;;
Asciz	Lscala/collection/immutable/List<Lscala/concurrent/pilib$Sum;>;;
Asciz	Signature;
Asciz	spawn;
Asciz	Lscala/concurrent/pilib$Spawn;;
Asciz	LineNumberTable;
Asciz	java/lang/Object;
class	java/lang/Object
Method	java/lang/Object."<init>":()V
NameAndType	MODULE$:Lscala/concurrent/pilib$;
Field	scala/concurrent/pilib$.MODULE$:Lscala/concurrent/pilib$;
Asciz	scala/concurrent/pilib$$anon$1;
class	scala/concurrent/pilib$$anon$1
Method	scala/concurrent/pilib$$anon$1."<init>":()V
NameAndType	spawn:Lscala/concurrent/pilib$Spawn;
Field	scala/concurrent/pilib$.spawn:Lscala/concurrent/pilib$Spawn;
Asciz	scala/collection/immutable/Nil$;
class	scala/collection/immutable/Nil$
Asciz	Lscala/collection/immutable/Nil$;;
NameAndType	MODULE$:Lscala/collection/immutable/Nil$;
Field	scala/collection/immutable/Nil$.MODULE$:Lscala/collection/immutable/Nil$;
NameAndType	sums:Lscala/collection/immutable/List;
Field	scala/concurrent/pilib$.sums:Lscala/collection/immutable/List;
Asciz	choice;
Asciz	(Lscala/collection/Seq;)Ljava/lang/Object;;
Asciz	scala/concurrent/pilib$Sum;
class	scala/concurrent/pilib$Sum
Asciz	scala/collection/TraversableLike;
class	scala/collection/TraversableLike
Asciz	toList;
Asciz	()Lscala/collection/immutable/List;;
NameAndType	toList:()Lscala/collection/immutable/List;
InterfaceMethod	scala/collection/TraversableLike.toList:()Lscala/collection/immutable/List;
Asciz	scala/concurrent/pilib$$anonfun$2;
class	scala/concurrent/pilib$$anonfun$2
Method	scala/concurrent/pilib$$anonfun$2."<init>":()V
Asciz	scala/collection/immutable/List$;
class	scala/collection/immutable/List$
Asciz	Lscala/collection/immutable/List$;;
NameAndType	MODULE$:Lscala/collection/immutable/List$;
Field	scala/collection/immutable/List$.MODULE$:Lscala/collection/immutable/List$;
Asciz	scala/collection/generic/TraversableFactory$GenericCanBuildFrom;
class	scala/collection/generic/TraversableFactory$GenericCanBuildFrom
Asciz	(Lscala/collection/generic/TraversableFactory;)V;
NameAndType	"<init>":(Lscala/collection/generic/TraversableFactory;)V
Method	scala/collection/generic/TraversableFactory$GenericCanBuildFrom."<init>":(Lscala/collection/generic/TraversableFactory;)V
Asciz	map;
Asciz	(Lscala/Function1;Lscala/collection/generic/CanBuildFrom;)Ljava/lang/Object;;
NameAndType	map:(Lscala/Function1;Lscala/collection/generic/CanBuildFrom;)Ljava/lang/Object;
InterfaceMethod	scala/collection/TraversableLike.map:(Lscala/Function1;Lscala/collection/generic/CanBuildFrom;)Ljava/lang/Object;
Asciz	scala/collection/immutable/List;
class	scala/collection/immutable/List
Asciz	(Lscala/collection/immutable/List;)V;
NameAndType	"<init>":(Lscala/collection/immutable/List;)V
Method	scala/concurrent/pilib$Sum."<init>":(Lscala/collection/immutable/List;)V
NameAndType	sums:()Lscala/collection/immutable/List;
Method	scala/concurrent/pilib$.sums:()Lscala/collection/immutable/List;
Asciz	compare;
Asciz	(Lscala/concurrent/pilib$Sum;Lscala/collection/immutable/List;)Lscala/collection/immutable/List;;
NameAndType	compare:(Lscala/concurrent/pilib$Sum;Lscala/collection/immutable/List;)Lscala/collection/immutable/List;
Method	scala/concurrent/pilib$.compare:(Lscala/concurrent/pilib$Sum;Lscala/collection/immutable/List;)Lscala/collection/immutable/List;
Asciz	sums_$eq;
NameAndType	sums_$eq:(Lscala/collection/immutable/List;)V
Method	scala/concurrent/pilib$.sums_$eq:(Lscala/collection/immutable/List;)V
Asciz	continue;
Asciz	()Ljava/lang/Object;;
NameAndType	continue:()Ljava/lang/Object;
Method	scala/concurrent/pilib$Sum.continue:()Ljava/lang/Object;
Asciz	this;
Asciz	s;
Asciz	Lscala/collection/Seq;;
Asciz	sum;
Asciz	Lscala/concurrent/pilib$Sum;;
Asciz	LocalVariableTable;
Asciz	<A:Ljava/lang/Object;>(Lscala/collection/Seq<Lscala/concurrent/pilib$GP<TA;>;>;)TA;;
Asciz	equals;
Asciz	(Ljava/lang/Object;)Z;
NameAndType	equals:(Ljava/lang/Object;)Z
Method	java/lang/Object.equals:(Ljava/lang/Object;)Z
Asciz	scala/Predef$;
class	scala/Predef$
Asciz	Lscala/Predef$;;
NameAndType	MODULE$:Lscala/Predef$;
Field	scala/Predef$.MODULE$:Lscala/Predef$;
Asciz	[Ljava/lang/Object;;
class	"[Ljava/lang/Object;"
Asciz	wrapRefArray;
Asciz	([Ljava/lang/Object;)Lscala/collection/mutable/WrappedArray;;
NameAndType	wrapRefArray:([Ljava/lang/Object;)Lscala/collection/mutable/WrappedArray;
Method	scala/Predef$.wrapRefArray:([Ljava/lang/Object;)Lscala/collection/mutable/WrappedArray;
Asciz	$colon$colon$colon;
Asciz	(Lscala/collection/immutable/List;)Lscala/collection/immutable/List;;
NameAndType	$colon$colon$colon:(Lscala/collection/immutable/List;)Lscala/collection/immutable/List;
Method	scala/collection/immutable/List.$colon$colon$colon:(Lscala/collection/immutable/List;)Lscala/collection/immutable/List;
Asciz	scala/MatchError;
class	scala/MatchError
Asciz	scala/collection/SeqLike;
class	scala/collection/SeqLike
Asciz	toString;
Asciz	()Ljava/lang/String;;
NameAndType	toString:()Ljava/lang/String;
InterfaceMethod	scala/collection/SeqLike.toString:()Ljava/lang/String;
Asciz	(Ljava/lang/String;)V;
NameAndType	"<init>":(Ljava/lang/String;)V
Method	scala/MatchError."<init>":(Ljava/lang/String;)V
Asciz	scala/collection/immutable/$colon$colon;
class	scala/collection/immutable/$colon$colon
Asciz	scala$collection$immutable$$colon$colon$$hd;
Asciz	Ljava/lang/Object;;
NameAndType	scala$collection$immutable$$colon$colon$$hd:Ljava/lang/Object;
Field	scala/collection/immutable/$colon$colon.scala$collection$immutable$$colon$colon$$hd:Ljava/lang/Object;
Asciz	tl;
NameAndType	tl:Lscala/collection/immutable/List;
Field	scala/collection/immutable/$colon$colon.tl:Lscala/collection/immutable/List;
Asciz	gs;
NameAndType	gs:()Lscala/collection/immutable/List;
Method	scala/concurrent/pilib$Sum.gs:()Lscala/collection/immutable/List;
Asciz	matches;
Asciz	(Lscala/collection/immutable/List;Lscala/collection/immutable/List;)Lscala/Option;;
NameAndType	matches:(Lscala/collection/immutable/List;Lscala/collection/immutable/List;)Lscala/Option;
Method	scala/concurrent/pilib$.matches:(Lscala/collection/immutable/List;Lscala/collection/immutable/List;)Lscala/Option;
Asciz	scala/None$;
class	scala/None$
Asciz	Lscala/None$;;
NameAndType	MODULE$:Lscala/None$;
Field	scala/None$.MODULE$:Lscala/None$;
Asciz	$colon$colon;
Asciz	(Ljava/lang/Object;)Lscala/collection/immutable/List;;
NameAndType	$colon$colon:(Ljava/lang/Object;)Lscala/collection/immutable/List;
Method	scala/collection/immutable/List.$colon$colon:(Ljava/lang/Object;)Lscala/collection/immutable/List;
Asciz	scala/Option;
class	scala/Option
Method	scala/Option.toString:()Ljava/lang/String;
Asciz	scala/Some;
class	scala/Some
Asciz	x;
NameAndType	x:Ljava/lang/Object;
Field	scala/Some.x:Ljava/lang/Object;
Asciz	scala/Tuple3;
class	scala/Tuple3
Asciz	_1;
NameAndType	_1:()Ljava/lang/Object;
Method	scala/Tuple3._1:()Ljava/lang/Object;
Asciz	scala/Function0;
class	scala/Function0
Asciz	_2;
NameAndType	_2:()Ljava/lang/Object;
Method	scala/Tuple3._2:()Ljava/lang/Object;
Asciz	_3;
NameAndType	_3:()Ljava/lang/Object;
Method	scala/Tuple3._3:()Ljava/lang/Object;
Asciz	apply;
NameAndType	apply:()Ljava/lang/Object;
InterfaceMethod	scala/Function0.apply:()Ljava/lang/Object;
Asciz	set;
Asciz	(Lscala/Function0;)V;
NameAndType	set:(Lscala/Function0;)V
Method	scala/concurrent/pilib$Sum.set:(Lscala/Function0;)V
Asciz	s1;
Asciz	ss;
Asciz	temp41;
Asciz	Lscala/collection/immutable/$colon$colon;;
Asciz	temp34;
Asciz	Lscala/Some;;
Asciz	temp35;
Asciz	Lscala/Tuple3;;
Asciz	temp36;
Asciz	Lscala/Function0;;
Asciz	temp37;
Asciz	temp42;
Asciz	temp38;
Asciz	temp43;
Asciz	temp32;
Asciz	Lscala/Option;;
Asciz	(Lscala/concurrent/pilib$Sum;Lscala/collection/immutable/List<Lscala/concurrent/pilib$Sum;>;)Lscala/collection/immutable/List<Lscala/concurrent/pilib$Sum;>;;
Asciz	scala/Tuple2;
class	scala/Tuple2
Asciz	(Ljava/lang/Object;Ljava/lang/Object;)V;
NameAndType	"<init>":(Ljava/lang/Object;Ljava/lang/Object;)V
Method	scala/Tuple2."<init>":(Ljava/lang/Object;Ljava/lang/Object;)V
Method	scala/Tuple2.toString:()Ljava/lang/String;
Asciz	scala/concurrent/pilib$UGP;
class	scala/concurrent/pilib$UGP
Asciz	n;
Asciz	()Lscala/concurrent/pilib$UChan;;
NameAndType	n:()Lscala/concurrent/pilib$UChan;
Method	scala/concurrent/pilib$UGP.n:()Lscala/concurrent/pilib$UChan;
Asciz	polarity;
Asciz	()Z;
NameAndType	polarity:()Z
Method	scala/concurrent/pilib$UGP.polarity:()Z
Asciz	v;
NameAndType	v:()Ljava/lang/Object;
Method	scala/concurrent/pilib$UGP.v:()Ljava/lang/Object;
Asciz	c;
Asciz	()Lscala/Function1;;
NameAndType	c:()Lscala/Function1;
Method	scala/concurrent/pilib$UGP.c:()Lscala/Function1;
Asciz	scala/concurrent/pilib$$anonfun$matches$1;
class	scala/concurrent/pilib$$anonfun$matches$1
Asciz	(Lscala/concurrent/pilib$UChan;ZLjava/lang/Object;Ljava/lang/Object;)V;
NameAndType	"<init>":(Lscala/concurrent/pilib$UChan;ZLjava/lang/Object;Ljava/lang/Object;)V
Method	scala/concurrent/pilib$$anonfun$matches$1."<init>":(Lscala/concurrent/pilib$UChan;ZLjava/lang/Object;Ljava/lang/Object;)V
Asciz	scala/concurrent/pilib$$anonfun$matches$2;
class	scala/concurrent/pilib$$anonfun$matches$2
Asciz	(Lscala/Function1;Ljava/lang/Object;)V;
NameAndType	"<init>":(Lscala/Function1;Ljava/lang/Object;)V
Method	scala/concurrent/pilib$$anonfun$matches$2."<init>":(Lscala/Function1;Ljava/lang/Object;)V
Asciz	scala/concurrent/pilib$$anonfun$matches$3;
class	scala/concurrent/pilib$$anonfun$matches$3
Asciz	(Ljava/lang/Object;Lscala/Function1;)V;
NameAndType	"<init>":(Ljava/lang/Object;Lscala/Function1;)V
Method	scala/concurrent/pilib$$anonfun$matches$3."<init>":(Ljava/lang/Object;Lscala/Function1;)V
Asciz	(Ljava/lang/Object;Ljava/lang/Object;Ljava/lang/Object;)V;
NameAndType	"<init>":(Ljava/lang/Object;Ljava/lang/Object;Ljava/lang/Object;)V
Method	scala/Tuple3."<init>":(Ljava/lang/Object;Ljava/lang/Object;Ljava/lang/Object;)V
Asciz	(Ljava/lang/Object;)V;
NameAndType	"<init>":(Ljava/lang/Object;)V
Method	scala/Some."<init>":(Ljava/lang/Object;)V
Asciz	gs1;
Asciz	gs2;
Asciz	temp18;
Asciz	temp19;
Asciz	Lscala/concurrent/pilib$UGP;;
Asciz	temp25;
Asciz	temp26;
Asciz	temp21;
Asciz	Lscala/concurrent/pilib$UChan;;
Asciz	temp22;
Asciz	Z;
Asciz	temp28;
Asciz	temp29;
Asciz	temp31;
Asciz	Lscala/Function1;;
Asciz	temp23;
Asciz	temp30;
Asciz	temp24;
Asciz	temp20;
Asciz	temp27;
Asciz	temp14;
Asciz	temp15;
Asciz	temp12;
Asciz	(Lscala/collection/immutable/List<Lscala/concurrent/pilib$UGP;>;Lscala/collection/immutable/List<Lscala/concurrent/pilib$UGP;>;)Lscala/Option<Lscala/Tuple3<Lscala/Function0<Ljava/lang/Object;>;Lscala/Function0<Ljava/lang/Object;>;Lscala/Function0<Ljava/lang/Object;>;>;>;;
Asciz	(Lscala/collection/immutable/List<Lscala/concurrent/pilib$Sum;>;)V;
Asciz	()Lscala/collection/immutable/List<Lscala/concurrent/pilib$Sum;>;;
Asciz	()Lscala/concurrent/pilib$Spawn;;
Asciz	InnerClasses;
Asciz	scala/concurrent/pilib$GP;
class	scala/concurrent/pilib$GP
Asciz	scala/concurrent/pilib;
class	scala/concurrent/pilib
Asciz	GP;
Asciz	Sum;
Asciz	UGP;
Asciz	scala/concurrent/pilib$Chan;
class	scala/concurrent/pilib$Chan
Asciz	Chan;
Asciz	scala/concurrent/pilib$UChan;
class	scala/concurrent/pilib$UChan
Asciz	UChan;
Asciz	scala/concurrent/pilib$Spawn;
class	scala/concurrent/pilib$Spawn
Asciz	Spawn;
Asciz	$anon$1;
Asciz	scala/concurrent/pilib$Product;
class	scala/concurrent/pilib$Product
Asciz	Product;
Asciz	$anonfun$2;
Asciz	$anonfun$matches$3;
Asciz	$anonfun$matches$2;
Asciz	$anonfun$matches$1;
Asciz	scala/collection/generic/TraversableFactory;
class	scala/collection/generic/TraversableFactory
Asciz	GenericCanBuildFrom;
Asciz	scala/ScalaObject;
class	scala/ScalaObject

{
public static final scala.concurrent.pilib$ MODULE$;
  Signature: Lscala/concurrent/pilib$;

private scala.collection.immutable.List sums;
  Signature: Lscala/collection/immutable/List;
  Signature: length = 0x2
   00 10 

private final scala.concurrent.pilib$Spawn spawn;
  Signature: Lscala/concurrent/pilib$Spawn;

public static {};
  Signature: ()V
  Code:
   Stack=1, Locals=0, Args_size=0
	new	class scala/concurrent/pilib$
	invokespecial	Method "<init>":()V
	return
  Labels:

private scala.concurrent.pilib$();
  Signature: ()V
  Code:
   Stack=3, Locals=1, Args_size=1
	aload_0
	invokespecial	Method java/lang/Object."<init>":()V
	aload_0
	putstatic	Field MODULE$:Lscala/concurrent/pilib$;
	aload_0
	new	class scala/concurrent/pilib$$anon$1
	dup
	invokespecial	Method scala/concurrent/pilib$$anon$1."<init>":()V
	putfield	Field spawn:Lscala/concurrent/pilib$Spawn;
	aload_0
	getstatic	Field scala/collection/immutable/Nil$.MODULE$:Lscala/collection/immutable/Nil$;
	putfield	Field sums:Lscala/collection/immutable/List;
	return
  Labels:

public java.lang.Object choice(scala.collection.Seq);
  Signature: (Lscala/collection/Seq;)Ljava/lang/Object;
  Code:
   Stack=7, Locals=4, Args_size=2
	new	class scala/concurrent/pilib$Sum
	dup
	aload_1
	invokeinterface	InterfaceMethod scala/collection/TraversableLike.toList:()Lscala/collection/immutable/List;
	new	class scala/concurrent/pilib$$anonfun$2
	dup
	invokespecial	Method scala/concurrent/pilib$$anonfun$2."<init>":()V
	getstatic	Field scala/collection/immutable/List$.MODULE$:Lscala/collection/immutable/List$;
	astore_2
	new	class scala/collection/generic/TraversableFactory$GenericCanBuildFrom
	dup
	aload_2
	invokespecial	Method scala/collection/generic/TraversableFactory$GenericCanBuildFrom."<init>":(Lscala/collection/generic/TraversableFactory;)V
	invokeinterface	InterfaceMethod scala/collection/TraversableLike.map:(Lscala/Function1;Lscala/collection/generic/CanBuildFrom;)Ljava/lang/Object;
	checkcast	class scala/collection/immutable/List
	invokespecial	Method scala/concurrent/pilib$Sum."<init>":(Lscala/collection/immutable/List;)V
	astore_3
	aload_0
	dup
	pop
	monitorenter
	aload_0
	aload_0
	aload_3
	aload_0
	invokespecial	Method sums:()Lscala/collection/immutable/List;
	invokespecial	Method compare:(Lscala/concurrent/pilib$Sum;Lscala/collection/immutable/List;)Lscala/collection/immutable/List;
	invokespecial	Method sums_$eq:(Lscala/collection/immutable/List;)V
	aload_0
	monitorexit
	aload_3
	invokevirtual	Method scala/concurrent/pilib$Sum.continue:()Ljava/lang/Object;
	areturn
	aload_0
	monitorexit
	athrow
  Labels:
  Exception table:
   from   to  target type
    45    60    65   any
  LocalVariableTable: 
   Start  Length  Slot  Name   Signature
   0      68      0    this       Lscala/concurrent/pilib$;
   0      68      1    s       Lscala/collection/Seq;
   41      23      3    sum       Lscala/concurrent/pilib$Sum;
   65      3      3    sum       Lscala/concurrent/pilib$Sum;

  Signature: length = 0x2
   00 59 

private scala.collection.immutable.List compare(scala.concurrent.pilib$Sum, scala.collection.immutable.List);
  Signature: (Lscala/concurrent/pilib$Sum;Lscala/collection/immutable/List;)Lscala/collection/immutable/List;
  Code:
   Stack=5, Locals=13, Args_size=3
	getstatic	Field scala/collection/immutable/Nil$.MODULE$:Lscala/collection/immutable/Nil$;
	dup
	ifnonnull	l1 // aload_2
	pop
	aload_2
	ifnull	l2 // iconst_1
	goto	l3 // aload_2
l1	aload_2
	invokevirtual	Method java/lang/Object.equals:(Ljava/lang/Object;)Z
	ifeq	l3 // aload_2
l2	iconst_1
	ifeq	l4 // new
	getstatic	Field scala/Predef$.MODULE$:Lscala/Predef$;
	iconst_1
	anewarray	class scala/concurrent/pilib$Sum
	dup
	iconst_0
	aload_1
	aastore
	checkcast	class "[Ljava/lang/Object;"
	invokevirtual	Method scala/Predef$.wrapRefArray:([Ljava/lang/Object;)Lscala/collection/mutable/WrappedArray;
	astore_3
	aload_3
	invokeinterface	InterfaceMethod scala/collection/TraversableLike.toList:()Lscala/collection/immutable/List;
	aload_2
	invokevirtual	Method scala/collection/immutable/List.$colon$colon$colon:(Lscala/collection/immutable/List;)Lscala/collection/immutable/List;
	goto	l5 // areturn
l4	new	class scala/MatchError
	dup
	aload_2
	invokeinterface	InterfaceMethod scala/collection/SeqLike.toString:()Ljava/lang/String;
	invokespecial	Method scala/MatchError."<init>":(Ljava/lang/String;)V
	athrow
l3	aload_2
	instanceof	class scala/collection/immutable/$colon$colon
	ifeq	l6 // new
	aload_2
	checkcast	class scala/collection/immutable/$colon$colon
	astore	4
	aload	4
	getfield	Field scala/collection/immutable/$colon$colon.scala$collection$immutable$$colon$colon$$hd:Ljava/lang/Object;
	checkcast	class scala/concurrent/pilib$Sum
	astore	9
	aload	4
	getfield	Field scala/collection/immutable/$colon$colon.tl:Lscala/collection/immutable/List;
	astore	11
	iconst_1
	ifeq	l7 // new
	aload_0
	aload_1
	invokevirtual	Method scala/concurrent/pilib$Sum.gs:()Lscala/collection/immutable/List;
	aload	9
	invokevirtual	Method scala/concurrent/pilib$Sum.gs:()Lscala/collection/immutable/List;
	invokespecial	Method matches:(Lscala/collection/immutable/List;Lscala/collection/immutable/List;)Lscala/Option;
	astore	12
	getstatic	Field scala/None$.MODULE$:Lscala/None$;
	dup
	ifnonnull	l8 // aload
	pop
	aload	12
	ifnull	l9 // iconst_1
	goto	l10 // aload
l8	aload	12
	invokevirtual	Method java/lang/Object.equals:(Ljava/lang/Object;)Z
	ifeq	l10 // aload
l9	iconst_1
	ifeq	l11 // new
	aload_0
	aload_1
	aload	11
	invokespecial	Method compare:(Lscala/concurrent/pilib$Sum;Lscala/collection/immutable/List;)Lscala/collection/immutable/List;
	aload	9
	invokevirtual	Method scala/collection/immutable/List.$colon$colon:(Ljava/lang/Object;)Lscala/collection/immutable/List;
	goto	l5 // areturn
l11	new	class scala/MatchError
	dup
	aload	12
	invokevirtual	Method scala/Option.toString:()Ljava/lang/String;
	invokespecial	Method scala/MatchError."<init>":(Ljava/lang/String;)V
	athrow
l10	aload	12
	instanceof	class scala/Some
	ifeq	l12 // new
	aload	12
	checkcast	class scala/Some
	astore	5
	aload	5
	getfield	Field scala/Some.x:Ljava/lang/Object;
	checkcast	class scala/Tuple3
	astore	6
	aload	6
	ifnull	l13 // new
	aload	6
	invokevirtual	Method scala/Tuple3._1:()Ljava/lang/Object;
	checkcast	class scala/Function0
	astore	7
	aload	6
	invokevirtual	Method scala/Tuple3._2:()Ljava/lang/Object;
	checkcast	class scala/Function0
	astore	8
	aload	6
	invokevirtual	Method scala/Tuple3._3:()Ljava/lang/Object;
	checkcast	class scala/Function0
	astore	10
	iconst_1
	ifeq	l14 // new
	aload	7
	invokeinterface	InterfaceMethod scala/Function0.apply:()Ljava/lang/Object;
	pop
	aload_1
	aload	8
	invokevirtual	Method scala/concurrent/pilib$Sum.set:(Lscala/Function0;)V
	aload	9
	aload	10
	invokevirtual	Method scala/concurrent/pilib$Sum.set:(Lscala/Function0;)V
	aload	11
l5	areturn
l14	new	class scala/MatchError
	dup
	aload	12
	invokevirtual	Method scala/Option.toString:()Ljava/lang/String;
	invokespecial	Method scala/MatchError."<init>":(Ljava/lang/String;)V
	athrow
l13	new	class scala/MatchError
	dup
	aload	12
	invokevirtual	Method scala/Option.toString:()Ljava/lang/String;
	invokespecial	Method scala/MatchError."<init>":(Ljava/lang/String;)V
	athrow
l12	new	class scala/MatchError
	dup
	aload	12
	invokevirtual	Method scala/Option.toString:()Ljava/lang/String;
	invokespecial	Method scala/MatchError."<init>":(Ljava/lang/String;)V
	athrow
l7	new	class scala/MatchError
	dup
	aload_2
	invokeinterface	InterfaceMethod scala/collection/SeqLike.toString:()Ljava/lang/String;
	invokespecial	Method scala/MatchError."<init>":(Ljava/lang/String;)V
	athrow
l6	new	class scala/MatchError
	dup
	aload_2
	invokeinterface	InterfaceMethod scala/collection/SeqLike.toString:()Ljava/lang/String;
	invokespecial	Method scala/MatchError."<init>":(Ljava/lang/String;)V
	athrow
  Labels:
   	l1 = 15 // aload_2
   	l2 = 22 // iconst_1
   	l4 = 57 // new
   	l3 = 71 // aload_2
   	l8 = 136 // aload
   	l9 = 144 // iconst_1
   	l11 = 163 // new
   	l10 = 176 // aload
   	l5 = 263 // areturn
   	l14 = 264 // new
   	l13 = 277 // new
   	l12 = 290 // new
   	l7 = 303 // new
   	l6 = 317 // new
  LocalVariableTable: 
   Start  Length  Slot  Name   Signature
   0      331      0    this       Lscala/concurrent/pilib$;
   0      331      1    s1       Lscala/concurrent/pilib$Sum;
   0      331      2    ss       Lscala/collection/immutable/List;
   84      179      4    temp41       Lscala/collection/immutable/$colon$colon;
   264      53      4    temp41       Lscala/collection/immutable/$colon$colon;
   191      72      5    temp34       Lscala/Some;
   264      26      5    temp34       Lscala/Some;
   201      62      6    temp35       Lscala/Tuple3;
   264      26      6    temp35       Lscala/Tuple3;
   216      47      7    temp36       Lscala/Function0;
   264      13      7    temp36       Lscala/Function0;
   226      37      8    temp37       Lscala/Function0;
   264      13      8    temp37       Lscala/Function0;
   94      169      9    temp42       Lscala/concurrent/pilib$Sum;
   264      53      9    temp42       Lscala/concurrent/pilib$Sum;
   236      27      10    temp38       Lscala/Function0;
   264      13      10    temp38       Lscala/Function0;
   101      162      11    temp43       Lscala/collection/immutable/List;
   264      53      11    temp43       Lscala/collection/immutable/List;
   120      143      12    temp32       Lscala/Option;
   264      39      12    temp32       Lscala/Option;

  Signature: length = 0x2
   00 FFFFFFBD 

private scala.Option matches(scala.collection.immutable.List, scala.collection.immutable.List);
  Signature: (Lscala/collection/immutable/List;Lscala/collection/immutable/List;)Lscala/Option;
  Code:
   Stack=10, Locals=20, Args_size=3
l24	getstatic	Field scala/collection/immutable/Nil$.MODULE$:Lscala/collection/immutable/Nil$;
	dup
	ifnonnull	l1 // aload_1
	pop
	aload_1
	ifnull	l2 // iconst_1
	goto	l3 // getstatic
l1	aload_1
	invokevirtual	Method java/lang/Object.equals:(Ljava/lang/Object;)Z
	ifeq	l3 // getstatic
l2	iconst_1
	ifeq	l4 // new
	getstatic	Field scala/None$.MODULE$:Lscala/None$;
	goto	l5 // areturn
l4	new	class scala/MatchError
	dup
	new	class scala/Tuple2
	dup
	aload_1
	aload_2
	invokespecial	Method scala/Tuple2."<init>":(Ljava/lang/Object;Ljava/lang/Object;)V
	invokevirtual	Method scala/Tuple2.toString:()Ljava/lang/String;
	invokespecial	Method scala/MatchError."<init>":(Ljava/lang/String;)V
	athrow
l3	getstatic	Field scala/collection/immutable/Nil$.MODULE$:Lscala/collection/immutable/Nil$;
	dup
	ifnonnull	l6 // aload_2
	pop
	aload_2
	ifnull	l7 // iconst_1
	goto	l8 // aload_2
l6	aload_2
	invokevirtual	Method java/lang/Object.equals:(Ljava/lang/Object;)Z
	ifeq	l8 // aload_2
l7	iconst_1
	ifeq	l9 // new
	getstatic	Field scala/None$.MODULE$:Lscala/None$;
	goto	l5 // areturn
l9	new	class scala/MatchError
	dup
	new	class scala/Tuple2
	dup
	aload_1
	aload_2
	invokespecial	Method scala/Tuple2."<init>":(Ljava/lang/Object;Ljava/lang/Object;)V
	invokevirtual	Method scala/Tuple2.toString:()Ljava/lang/String;
	invokespecial	Method scala/MatchError."<init>":(Ljava/lang/String;)V
	athrow
l8	aload_2
	instanceof	class scala/collection/immutable/$colon$colon
	ifeq	l10 // new
	aload_2
	checkcast	class scala/collection/immutable/$colon$colon
	astore_3
	aload_3
	getfield	Field scala/collection/immutable/$colon$colon.scala$collection$immutable$$colon$colon$$hd:Ljava/lang/Object;
	checkcast	class scala/concurrent/pilib$UGP
	astore	4
	aload_3
	getfield	Field scala/collection/immutable/$colon$colon.tl:Lscala/collection/immutable/List;
	astore	15
	aload	4
	ifnull	l11 // new
	aload	4
	invokevirtual	Method scala/concurrent/pilib$UGP.n:()Lscala/concurrent/pilib$UChan;
	astore	7
	aload	4
	invokevirtual	Method scala/concurrent/pilib$UGP.polarity:()Z
	istore	8
	aload	4
	invokevirtual	Method scala/concurrent/pilib$UGP.v:()Ljava/lang/Object;
	astore	12
	aload	4
	invokevirtual	Method scala/concurrent/pilib$UGP.c:()Lscala/Function1;
	astore	14
	aload_1
	instanceof	class scala/collection/immutable/$colon$colon
	ifeq	l12 // new
	aload_1
	checkcast	class scala/collection/immutable/$colon$colon
	astore	5
	aload	5
	getfield	Field scala/collection/immutable/$colon$colon.scala$collection$immutable$$colon$colon$$hd:Ljava/lang/Object;
	checkcast	class scala/concurrent/pilib$UGP
	astore	6
	aload	5
	getfield	Field scala/collection/immutable/$colon$colon.tl:Lscala/collection/immutable/List;
	astore	16
	aload	6
	ifnull	l13 // new
	aload	6
	invokevirtual	Method scala/concurrent/pilib$UGP.n:()Lscala/concurrent/pilib$UChan;
	astore	9
	aload	6
	invokevirtual	Method scala/concurrent/pilib$UGP.polarity:()Z
	istore	10
	aload	6
	invokevirtual	Method scala/concurrent/pilib$UGP.v:()Ljava/lang/Object;
	astore	13
	aload	6
	invokevirtual	Method scala/concurrent/pilib$UGP.c:()Lscala/Function1;
	astore	11
	iconst_1
	ifeq	l14 // new
	aload	9
	dup
	ifnonnull	l15 // aload
	pop
	aload	7
	ifnull	l16 // iload
	goto	l17 // aload_0
l15	aload	7
	invokevirtual	Method java/lang/Object.equals:(Ljava/lang/Object;)Z
	ifeq	l17 // aload_0
l16	iload	10
	iload	8
	ifeq	l18 // iconst_1
	iconst_0
	goto	l19 // if_icmpne
l18	iconst_1
l19	if_icmpne	l17 // aload_0
	new	class scala/Some
	dup
	new	class scala/Tuple3
	dup
	new	class scala/concurrent/pilib$$anonfun$matches$1
	dup
	aload	9
	iload	10
	aload	13
	aload	12
	invokespecial	Method scala/concurrent/pilib$$anonfun$matches$1."<init>":(Lscala/concurrent/pilib$UChan;ZLjava/lang/Object;Ljava/lang/Object;)V
	new	class scala/concurrent/pilib$$anonfun$matches$2
	dup
	aload	11
	aload	12
	invokespecial	Method scala/concurrent/pilib$$anonfun$matches$2."<init>":(Lscala/Function1;Ljava/lang/Object;)V
	new	class scala/concurrent/pilib$$anonfun$matches$3
	dup
	aload	13
	aload	14
	invokespecial	Method scala/concurrent/pilib$$anonfun$matches$3."<init>":(Ljava/lang/Object;Lscala/Function1;)V
	invokespecial	Method scala/Tuple3."<init>":(Ljava/lang/Object;Ljava/lang/Object;Ljava/lang/Object;)V
	invokespecial	Method scala/Some."<init>":(Ljava/lang/Object;)V
	goto	l5 // areturn
l17	aload_0
	aload_1
	aload	15
	invokespecial	Method matches:(Lscala/collection/immutable/List;Lscala/collection/immutable/List;)Lscala/Option;
	astore	19
	getstatic	Field scala/None$.MODULE$:Lscala/None$;
	dup
	ifnonnull	l20 // aload
	pop
	aload	19
	ifnull	l21 // iconst_1
	goto	l22 // aload
l20	aload	19
	invokevirtual	Method java/lang/Object.equals:(Ljava/lang/Object;)Z
	ifeq	l22 // aload
l21	iconst_1
	ifeq	l23 // new
	aload	16
	astore_1
	goto	l24 // getstatic
l23	new	class scala/MatchError
	dup
	aload	19
	invokevirtual	Method scala/Option.toString:()Ljava/lang/String;
	invokespecial	Method scala/MatchError."<init>":(Ljava/lang/String;)V
	athrow
l22	aload	19
	instanceof	class scala/Some
	ifeq	l25 // new
	aload	19
	checkcast	class scala/Some
	astore	17
	aload	17
	getfield	Field scala/Some.x:Ljava/lang/Object;
	checkcast	class scala/Tuple3
	astore	18
	iconst_1
	ifeq	l26 // new
	new	class scala/Some
	dup
	aload	18
	invokespecial	Method scala/Some."<init>":(Ljava/lang/Object;)V
l5	areturn
l26	new	class scala/MatchError
	dup
	aload	19
	invokevirtual	Method scala/Option.toString:()Ljava/lang/String;
	invokespecial	Method scala/MatchError."<init>":(Ljava/lang/String;)V
	athrow
l25	new	class scala/MatchError
	dup
	aload	19
	invokevirtual	Method scala/Option.toString:()Ljava/lang/String;
	invokespecial	Method scala/MatchError."<init>":(Ljava/lang/String;)V
	athrow
l14	new	class scala/MatchError
	dup
	new	class scala/Tuple2
	dup
	aload_1
	aload_2
	invokespecial	Method scala/Tuple2."<init>":(Ljava/lang/Object;Ljava/lang/Object;)V
	invokevirtual	Method scala/Tuple2.toString:()Ljava/lang/String;
	invokespecial	Method scala/MatchError."<init>":(Ljava/lang/String;)V
	athrow
l13	new	class scala/MatchError
	dup
	new	class scala/Tuple2
	dup
	aload_1
	aload_2
	invokespecial	Method scala/Tuple2."<init>":(Ljava/lang/Object;Ljava/lang/Object;)V
	invokevirtual	Method scala/Tuple2.toString:()Ljava/lang/String;
	invokespecial	Method scala/MatchError."<init>":(Ljava/lang/String;)V
	athrow
l12	new	class scala/MatchError
	dup
	new	class scala/Tuple2
	dup
	aload_1
	aload_2
	invokespecial	Method scala/Tuple2."<init>":(Ljava/lang/Object;Ljava/lang/Object;)V
	invokevirtual	Method scala/Tuple2.toString:()Ljava/lang/String;
	invokespecial	Method scala/MatchError."<init>":(Ljava/lang/String;)V
	athrow
l11	new	class scala/MatchError
	dup
	new	class scala/Tuple2
	dup
	aload_1
	aload_2
	invokespecial	Method scala/Tuple2."<init>":(Ljava/lang/Object;Ljava/lang/Object;)V
	invokevirtual	Method scala/Tuple2.toString:()Ljava/lang/String;
	invokespecial	Method scala/MatchError."<init>":(Ljava/lang/String;)V
	athrow
l10	new	class scala/MatchError
	dup
	new	class scala/Tuple2
	dup
	aload_1
	aload_2
	invokespecial	Method scala/Tuple2."<init>":(Ljava/lang/Object;Ljava/lang/Object;)V
	invokevirtual	Method scala/Tuple2.toString:()Ljava/lang/String;
	invokespecial	Method scala/MatchError."<init>":(Ljava/lang/String;)V
	athrow
  Labels:
   	l24 = 0 // getstatic
   	l1 = 15 // aload_1
   	l2 = 22 // iconst_1
   	l4 = 32 // new
   	l3 = 52 // getstatic
   	l6 = 67 // aload_2
   	l7 = 74 // iconst_1
   	l9 = 84 // new
   	l8 = 104 // aload_2
   	l15 = 246 // aload
   	l16 = 254 // iload
   	l18 = 265 // iconst_1
   	l19 = 266 // if_icmpne
   	l17 = 323 // aload_0
   	l20 = 348 // aload
   	l21 = 356 // iconst_1
   	l23 = 366 // new
   	l22 = 379 // aload
   	l5 = 417 // areturn
   	l26 = 418 // new
   	l25 = 431 // new
   	l14 = 444 // new
   	l13 = 464 // new
   	l12 = 484 // new
   	l11 = 504 // new
   	l10 = 524 // new
  LocalVariableTable: 
   Start  Length  Slot  Name   Signature
   0      544      0    this       Lscala/concurrent/pilib$;
   0      544      1    gs1       Lscala/collection/immutable/List;
   0      544      2    gs2       Lscala/collection/immutable/List;
   116      301      3    temp18       Lscala/collection/immutable/$colon$colon;
   418      106      3    temp18       Lscala/collection/immutable/$colon$colon;
   125      292      4    temp19       Lscala/concurrent/pilib$UGP;
   418      106      4    temp19       Lscala/concurrent/pilib$UGP;
   177      240      5    temp25       Lscala/collection/immutable/$colon$colon;
   418      66      5    temp25       Lscala/collection/immutable/$colon$colon;
   187      230      6    temp26       Lscala/concurrent/pilib$UGP;
   418      66      6    temp26       Lscala/concurrent/pilib$UGP;
   143      274      7    temp21       Lscala/concurrent/pilib$UChan;
   418      86      7    temp21       Lscala/concurrent/pilib$UChan;
   150      267      8    temp22       Z
   418      86      8    temp22       Z
   206      211      9    temp28       Lscala/concurrent/pilib$UChan;
   418      46      9    temp28       Lscala/concurrent/pilib$UChan;
   213      204      10    temp29       Z
   418      46      10    temp29       Z
   227      190      11    temp31       Lscala/Function1;
   418      46      11    temp31       Lscala/Function1;
   157      260      12    temp23       Ljava/lang/Object;
   418      86      12    temp23       Ljava/lang/Object;
   220      197      13    temp30       Ljava/lang/Object;
   418      46      13    temp30       Ljava/lang/Object;
   164      253      14    temp24       Lscala/Function1;
   418      86      14    temp24       Lscala/Function1;
   131      286      15    temp20       Lscala/collection/immutable/List;
   418      106      15    temp20       Lscala/collection/immutable/List;
   194      223      16    temp27       Lscala/collection/immutable/List;
   418      66      16    temp27       Lscala/collection/immutable/List;
   394      23      17    temp14       Lscala/Some;
   418      13      17    temp14       Lscala/Some;
   404      13      18    temp15       Lscala/Tuple3;
   418      13      18    temp15       Lscala/Tuple3;
   332      85      19    temp12       Lscala/Option;
   418      26      19    temp12       Lscala/Option;

  Signature: length = 0x2
   01 01 

private void sums_$eq(scala.collection.immutable.List);
  Signature: (Lscala/collection/immutable/List;)V
  Code:
   Stack=2, Locals=2, Args_size=2
	aload_0
	aload_1
	putfield	Field sums:Lscala/collection/immutable/List;
	return
  Labels:
  Signature: length = 0x2
   01 02 

private scala.collection.immutable.List sums();
  Signature: ()Lscala/collection/immutable/List;
  Code:
   Stack=1, Locals=1, Args_size=1
	aload_0
	getfield	Field sums:Lscala/collection/immutable/List;
	areturn
  Labels:
  Signature: length = 0x2
   01 03 

public scala.concurrent.pilib$Spawn spawn();
  Signature: ()Lscala/concurrent/pilib$Spawn;
  Code:
   Stack=1, Locals=1, Args_size=1
	aload_0
	getfield	Field spawn:Lscala/concurrent/pilib$Spawn;
	areturn
  Labels:

}

