Compiled from "pilib.scala"
public class scala.concurrent.pilib$UChan extends java.lang.Object implements scala.ScalaObject
  SourceFile: "pilib.scala"
  Scala: length = 0x
   
  InnerClass: 
   public #33= #21 of #32; //UChan=class scala/concurrent/pilib$UChan of class scala/concurrent/pilib
   public final #34= #16 of #21; //$anonfun$1=class scala/concurrent/pilib$UChan$$anonfun$1 of class scala/concurrent/pilib$UChan
  minor version: 0
  major version: 49
  Constant pool:
const #1 = Asciz	SourceFile;
const #2 = Asciz	pilib.scala;
const #3 = Asciz	log;
const #4 = Asciz	Lscala/Function1;;
const #5 = Asciz	Lscala/Function1<Ljava/lang/Object;Ljava/lang/Object;>;;
const #6 = Asciz	Signature;
const #7 = Asciz	<init>;
const #8 = Asciz	()V;
const #9 = Asciz	Code;
const #10 = Asciz	LineNumberTable;
const #11 = Asciz	java/lang/Object;
const #12 = class	#11;	//  java/lang/Object
const #13 = NameAndType	#7:#8;//  "<init>":()V
const #14 = Method	#12.#13;	//  java/lang/Object."<init>":()V
const #15 = Asciz	scala/concurrent/pilib$UChan$$anonfun$1;
const #16 = class	#15;	//  scala/concurrent/pilib$UChan$$anonfun$1
const #17 = Asciz	(Lscala/concurrent/pilib$UChan;)V;
const #18 = NameAndType	#7:#17;//  "<init>":(Lscala/concurrent/pilib$UChan;)V
const #19 = Method	#16.#18;	//  scala/concurrent/pilib$UChan$$anonfun$1."<init>":(Lscala/concurrent/pilib$UChan;)V
const #20 = Asciz	scala/concurrent/pilib$UChan;
const #21 = class	#20;	//  scala/concurrent/pilib$UChan
const #22 = NameAndType	#3:#4;//  log:Lscala/Function1;
const #23 = Field	#21.#22;	//  scala/concurrent/pilib$UChan.log:Lscala/Function1;
const #24 = Asciz	log_$eq;
const #25 = Asciz	(Lscala/Function1;)V;
const #26 = Asciz	(Lscala/Function1<Ljava/lang/Object;Ljava/lang/Object;>;)V;
const #27 = Asciz	()Lscala/Function1;;
const #28 = Asciz	()Lscala/Function1<Ljava/lang/Object;Ljava/lang/Object;>;;
const #29 = Asciz	Scala;
const #30 = Asciz	InnerClasses;
const #31 = Asciz	scala/concurrent/pilib;
const #32 = class	#31;	//  scala/concurrent/pilib
const #33 = Asciz	UChan;
const #34 = Asciz	$anonfun$1;
const #35 = Asciz	scala/ScalaObject;
const #36 = class	#35;	//  scala/ScalaObject

{
public scala.concurrent.pilib$UChan();
  Code:
   Stack=4, Locals=1, Args_size=1
   0:	aload_0
   1:	invokespecial	#14; //Method java/lang/Object."<init>":()V
   4:	aload_0
   5:	new	#16; //class scala/concurrent/pilib$UChan$$anonfun$1
   8:	dup
   9:	aload_0
   10:	invokespecial	#19; //Method scala/concurrent/pilib$UChan$$anonfun$1."<init>":(Lscala/concurrent/pilib$UChan;)V
   13:	putfield	#23; //Field log:Lscala/Function1;
   16:	return
  LineNumberTable: 
   line 57: 0
   line 59: 4


public void log_$eq(scala.Function1);
  Code:
   Stack=2, Locals=2, Args_size=2
   0:	aload_0
   1:	aload_1
   2:	putfield	#23; //Field log:Lscala/Function1;
   5:	return
  LineNumberTable: 
   line 59: 0

  Signature: length = 0x2
   00 1A 

public scala.Function1 log();
  Code:
   Stack=1, Locals=1, Args_size=1
   0:	aload_0
   1:	getfield	#23; //Field log:Lscala/Function1;
   4:	areturn
  LineNumberTable: 
   line 59: 0

  Signature: length = 0x2
   00 1C 

}

