Compiled from "pilib.scala"
public abstract class scala.concurrent.pilib$Spawn extends java.lang.Object implements scala.ScalaObject
  SourceFile: "pilib.scala"
  Scala: length = 0x
   
  InnerClass: 
   public abstract #23= #20 of #22; //Spawn=class scala/concurrent/pilib$Spawn of class scala/concurrent/pilib
  minor version: 0
  major version: 49
  Constant pool:
const #1 = Asciz	SourceFile;
const #2 = Asciz	pilib.scala;
const #3 = Asciz	<init>;
const #4 = Asciz	()V;
const #5 = Asciz	Code;
const #6 = Asciz	LineNumberTable;
const #7 = Asciz	java/lang/Object;
const #8 = class	#7;	//  java/lang/Object
const #9 = NameAndType	#3:#4;//  "<init>":()V
const #10 = Method	#8.#9;	//  java/lang/Object."<init>":()V
const #11 = Asciz	$greater;
const #12 = Asciz	$bar;
const #13 = Asciz	(Lscala/Function0;)Lscala/concurrent/pilib$Spawn;;
const #14 = Asciz	(Lscala/Function0<Ljava/lang/Object;>;)Lscala/concurrent/pilib$Spawn;;
const #15 = Asciz	Signature;
const #16 = Asciz	$less;
const #17 = Asciz	Scala;
const #18 = Asciz	InnerClasses;
const #19 = Asciz	scala/concurrent/pilib$Spawn;
const #20 = class	#19;	//  scala/concurrent/pilib$Spawn
const #21 = Asciz	scala/concurrent/pilib;
const #22 = class	#21;	//  scala/concurrent/pilib
const #23 = Asciz	Spawn;
const #24 = Asciz	scala/ScalaObject;
const #25 = class	#24;	//  scala/ScalaObject

{
public scala.concurrent.pilib$Spawn();
  Code:
   Stack=1, Locals=1, Args_size=1
   0:	aload_0
   1:	invokespecial	#10; //Method java/lang/Object."<init>":()V
   4:	return
  LineNumberTable: 
   line 42: 0


public abstract void $greater();

public abstract scala.concurrent.pilib$Spawn $bar(scala.Function0);
  Signature: length = 0x2
   00 0E 

public abstract scala.concurrent.pilib$Spawn $less(scala.Function0);
  Signature: length = 0x2
   00 0E 

}

