Compiled from "pilib.scala"
public class scala.concurrent.pilib$Chan extends scala.concurrent.pilib$UChan implements scala.Function1,scala.ScalaObject
  SourceFile: "pilib.scala"
  Signature: length = 0x2
   00 FFFFFF97 
  Scala: length = 0x
   
  InnerClass: 
   public #156= #72 of #155; //GP=class scala/concurrent/pilib$GP of class scala/concurrent/pilib
   public #157= #24 of #155; //Chan=class scala/concurrent/pilib$Chan of class scala/concurrent/pilib
   public #158= #12 of #155; //UChan=class scala/concurrent/pilib$UChan of class scala/concurrent/pilib
   public #159= #45 of #155; //Product=class scala/concurrent/pilib$Product of class scala/concurrent/pilib
   public final #160= #103 of #24; //$anonfun$read$1=class scala/concurrent/pilib$Chan$$anonfun$read$1 of class scala/concurrent/pilib$Chan
   public final #161= #131 of #24; //$anonfun$input$1=class scala/concurrent/pilib$Chan$$anonfun$input$1 of class scala/concurrent/pilib$Chan
   public final #162= #74 of #24; //$anonfun$write$1=class scala/concurrent/pilib$Chan$$anonfun$write$1 of class scala/concurrent/pilib$Chan
   public final #163= #114 of #24; //$anonfun$output$1=class scala/concurrent/pilib$Chan$$anonfun$output$1 of class scala/concurrent/pilib$Chan
   public final #164= #34 of #24; //$anonfun$attach$1=class scala/concurrent/pilib$Chan$$anonfun$attach$1 of class scala/concurrent/pilib$Chan
  minor version: 0
  major version: 49
  Constant pool:
const #1 = Asciz	SourceFile;
const #2 = Asciz	pilib.scala;
const #3 = Asciz	defaultValue;
const #4 = Asciz	Ljava/lang/Object;;
const #5 = Asciz	TA;;
const #6 = Asciz	Signature;
const #7 = Asciz	<init>;
const #8 = Asciz	()V;
const #9 = Asciz	Code;
const #10 = Asciz	LineNumberTable;
const #11 = Asciz	scala/concurrent/pilib$UChan;
const #12 = class	#11;	//  scala/concurrent/pilib$UChan
const #13 = NameAndType	#7:#8;//  "<init>":()V
const #14 = Method	#12.#13;	//  scala/concurrent/pilib$UChan."<init>":()V
const #15 = Asciz	scala/Function1$class;
const #16 = class	#15;	//  scala/Function1$class
const #17 = Asciz	$init$;
const #18 = Asciz	(Lscala/Function1;)V;
const #19 = NameAndType	#17:#18;//  $init$:(Lscala/Function1;)V
const #20 = Method	#16.#19;	//  scala/Function1$class.$init$:(Lscala/Function1;)V
const #21 = Asciz	apply;
const #22 = Asciz	(Ljava/lang/Object;)Ljava/lang/Object;;
const #23 = Asciz	scala/concurrent/pilib$Chan;
const #24 = class	#23;	//  scala/concurrent/pilib$Chan
const #25 = Asciz	(Ljava/lang/Object;)Lscala/concurrent/pilib$Product;;
const #26 = NameAndType	#21:#25;//  apply:(Ljava/lang/Object;)Lscala/concurrent/pilib$Product;
const #27 = Method	#24.#26;	//  scala/concurrent/pilib$Chan.apply:(Ljava/lang/Object;)Lscala/concurrent/pilib$Product;
const #28 = Asciz	this;
const #29 = Asciz	Lscala/concurrent/pilib$Chan;;
const #30 = Asciz	v1;
const #31 = Asciz	LocalVariableTable;
const #32 = Asciz	attach;
const #33 = Asciz	scala/concurrent/pilib$Chan$$anonfun$attach$1;
const #34 = class	#33;	//  scala/concurrent/pilib$Chan$$anonfun$attach$1
const #35 = Asciz	(Lscala/concurrent/pilib$Chan;Lscala/Function1;)V;
const #36 = NameAndType	#7:#35;//  "<init>":(Lscala/concurrent/pilib$Chan;Lscala/Function1;)V
const #37 = Method	#34.#36;	//  scala/concurrent/pilib$Chan$$anonfun$attach$1."<init>":(Lscala/concurrent/pilib$Chan;Lscala/Function1;)V
const #38 = Asciz	log_$eq;
const #39 = NameAndType	#38:#18;//  log_$eq:(Lscala/Function1;)V
const #40 = Method	#24.#39;	//  scala/concurrent/pilib$Chan.log_$eq:(Lscala/Function1;)V
const #41 = Asciz	f$1;
const #42 = Asciz	Lscala/Function1;;
const #43 = Asciz	(Lscala/Function1<TA;Ljava/lang/Object;>;)V;
const #44 = Asciz	scala/concurrent/pilib$Product;
const #45 = class	#44;	//  scala/concurrent/pilib$Product
const #46 = Asciz	(Lscala/concurrent/pilib$Chan;Ljava/lang/Object;)V;
const #47 = NameAndType	#7:#46;//  "<init>":(Lscala/concurrent/pilib$Chan;Ljava/lang/Object;)V
const #48 = Method	#45.#47;	//  scala/concurrent/pilib$Product."<init>":(Lscala/concurrent/pilib$Chan;Ljava/lang/Object;)V
const #49 = Asciz	v;
const #50 = Asciz	(TA;)Lscala/concurrent/pilib$Product<TA;>;;
const #51 = Asciz	$times;
const #52 = Asciz	(Lscala/Function1;)Lscala/concurrent/pilib$GP;;
const #53 = Asciz	input;
const #54 = NameAndType	#53:#52;//  input:(Lscala/Function1;)Lscala/concurrent/pilib$GP;
const #55 = Method	#24.#54;	//  scala/concurrent/pilib$Chan.input:(Lscala/Function1;)Lscala/concurrent/pilib$GP;
const #56 = Asciz	f;
const #57 = Asciz	<B:Ljava/lang/Object;>(Lscala/Function1<TA;TB;>;)Lscala/concurrent/pilib$GP<TB;>;;
const #58 = Asciz	write;
const #59 = Asciz	(Ljava/lang/Object;)V;
const #60 = Asciz	scala/concurrent/pilib$;
const #61 = class	#60;	//  scala/concurrent/pilib$
const #62 = Asciz	MODULE$;
const #63 = Asciz	Lscala/concurrent/pilib$;;
const #64 = NameAndType	#62:#63;//  MODULE$:Lscala/concurrent/pilib$;
const #65 = Field	#61.#64;	//  scala/concurrent/pilib$.MODULE$:Lscala/concurrent/pilib$;
const #66 = Asciz	scala/Predef$;
const #67 = class	#66;	//  scala/Predef$
const #68 = Asciz	Lscala/Predef$;;
const #69 = NameAndType	#62:#68;//  MODULE$:Lscala/Predef$;
const #70 = Field	#67.#69;	//  scala/Predef$.MODULE$:Lscala/Predef$;
const #71 = Asciz	scala/concurrent/pilib$GP;
const #72 = class	#71;	//  scala/concurrent/pilib$GP
const #73 = Asciz	scala/concurrent/pilib$Chan$$anonfun$write$1;
const #74 = class	#73;	//  scala/concurrent/pilib$Chan$$anonfun$write$1
const #75 = Asciz	(Lscala/concurrent/pilib$Chan;)V;
const #76 = NameAndType	#7:#75;//  "<init>":(Lscala/concurrent/pilib$Chan;)V
const #77 = Method	#74.#76;	//  scala/concurrent/pilib$Chan$$anonfun$write$1."<init>":(Lscala/concurrent/pilib$Chan;)V
const #78 = Asciz	output;
const #79 = Asciz	(Ljava/lang/Object;Lscala/Function0;)Lscala/concurrent/pilib$GP;;
const #80 = NameAndType	#78:#79;//  output:(Ljava/lang/Object;Lscala/Function0;)Lscala/concurrent/pilib$GP;
const #81 = Method	#24.#80;	//  scala/concurrent/pilib$Chan.output:(Ljava/lang/Object;Lscala/Function0;)Lscala/concurrent/pilib$GP;
const #82 = Asciz	[Ljava/lang/Object;;
const #83 = class	#82;	//  "[Ljava/lang/Object;"
const #84 = Asciz	wrapRefArray;
const #85 = Asciz	([Ljava/lang/Object;)Lscala/collection/mutable/WrappedArray;;
const #86 = NameAndType	#84:#85;//  wrapRefArray:([Ljava/lang/Object;)Lscala/collection/mutable/WrappedArray;
const #87 = Method	#67.#86;	//  scala/Predef$.wrapRefArray:([Ljava/lang/Object;)Lscala/collection/mutable/WrappedArray;
const #88 = Asciz	choice;
const #89 = Asciz	(Lscala/collection/Seq;)Ljava/lang/Object;;
const #90 = NameAndType	#88:#89;//  choice:(Lscala/collection/Seq;)Ljava/lang/Object;
const #91 = Method	#61.#90;	//  scala/concurrent/pilib$.choice:(Lscala/collection/Seq;)Ljava/lang/Object;
const #92 = Asciz	x;
const #93 = Asciz	(TA;)V;
const #94 = Asciz	read;
const #95 = Asciz	()Ljava/lang/Object;;
const #96 = Asciz	scala/runtime/ObjectRef;
const #97 = class	#96;	//  scala/runtime/ObjectRef
const #98 = NameAndType	#3:#95;//  defaultValue:()Ljava/lang/Object;
const #99 = Method	#24.#98;	//  scala/concurrent/pilib$Chan.defaultValue:()Ljava/lang/Object;
const #100 = NameAndType	#7:#59;//  "<init>":(Ljava/lang/Object;)V
const #101 = Method	#97.#100;	//  scala/runtime/ObjectRef."<init>":(Ljava/lang/Object;)V
const #102 = Asciz	scala/concurrent/pilib$Chan$$anonfun$read$1;
const #103 = class	#102;	//  scala/concurrent/pilib$Chan$$anonfun$read$1
const #104 = Asciz	(Lscala/concurrent/pilib$Chan;Lscala/runtime/ObjectRef;)V;
const #105 = NameAndType	#7:#104;//  "<init>":(Lscala/concurrent/pilib$Chan;Lscala/runtime/ObjectRef;)V
const #106 = Method	#103.#105;	//  scala/concurrent/pilib$Chan$$anonfun$read$1."<init>":(Lscala/concurrent/pilib$Chan;Lscala/runtime/ObjectRef;)V
const #107 = Asciz	elem;
const #108 = NameAndType	#107:#4;//  elem:Ljava/lang/Object;
const #109 = Field	#97.#108;	//  scala/runtime/ObjectRef.elem:Ljava/lang/Object;
const #110 = Asciz	res$1;
const #111 = Asciz	Lscala/runtime/ObjectRef;;
const #112 = Asciz	()TA;;
const #113 = Asciz	scala/concurrent/pilib$Chan$$anonfun$output$1;
const #114 = class	#113;	//  scala/concurrent/pilib$Chan$$anonfun$output$1
const #115 = Asciz	(Lscala/concurrent/pilib$Chan;Lscala/Function0;)V;
const #116 = NameAndType	#7:#115;//  "<init>":(Lscala/concurrent/pilib$Chan;Lscala/Function0;)V
const #117 = Method	#114.#116;	//  scala/concurrent/pilib$Chan$$anonfun$output$1."<init>":(Lscala/concurrent/pilib$Chan;Lscala/Function0;)V
const #118 = Asciz	(Lscala/concurrent/pilib$UChan;ZLjava/lang/Object;Lscala/Function1;)V;
const #119 = NameAndType	#7:#118;//  "<init>":(Lscala/concurrent/pilib$UChan;ZLjava/lang/Object;Lscala/Function1;)V
const #120 = Method	#72.#119;	//  scala/concurrent/pilib$GP."<init>":(Lscala/concurrent/pilib$UChan;ZLjava/lang/Object;Lscala/Function1;)V
const #121 = Asciz	c$3;
const #122 = Asciz	Lscala/Function0;;
const #123 = Asciz	<B:Ljava/lang/Object;>(TA;Lscala/Function0<TB;>;)Lscala/concurrent/pilib$GP<TB;>;;
const #124 = Asciz	scala/runtime/BoxedUnit;
const #125 = class	#124;	//  scala/runtime/BoxedUnit
const #126 = Asciz	UNIT;
const #127 = Asciz	Lscala/runtime/BoxedUnit;;
const #128 = NameAndType	#126:#127;//  UNIT:Lscala/runtime/BoxedUnit;
const #129 = Field	#125.#128;	//  scala/runtime/BoxedUnit.UNIT:Lscala/runtime/BoxedUnit;
const #130 = Asciz	scala/concurrent/pilib$Chan$$anonfun$input$1;
const #131 = class	#130;	//  scala/concurrent/pilib$Chan$$anonfun$input$1
const #132 = Method	#131.#36;	//  scala/concurrent/pilib$Chan$$anonfun$input$1."<init>":(Lscala/concurrent/pilib$Chan;Lscala/Function1;)V
const #133 = Asciz	c$2;
const #134 = Asciz	defaultValue_$eq;
const #135 = NameAndType	#3:#4;//  defaultValue:Ljava/lang/Object;
const #136 = Field	#24.#135;	//  scala/concurrent/pilib$Chan.defaultValue:Ljava/lang/Object;
const #137 = Asciz	andThen;
const #138 = Asciz	(Lscala/Function1;)Lscala/Function1;;
const #139 = Asciz	(Lscala/Function1;Lscala/Function1;)Lscala/Function1;;
const #140 = NameAndType	#137:#139;//  andThen:(Lscala/Function1;Lscala/Function1;)Lscala/Function1;
const #141 = Method	#16.#140;	//  scala/Function1$class.andThen:(Lscala/Function1;Lscala/Function1;)Lscala/Function1;
const #142 = Asciz	g;
const #143 = Asciz	compose;
const #144 = NameAndType	#143:#139;//  compose:(Lscala/Function1;Lscala/Function1;)Lscala/Function1;
const #145 = Method	#16.#144;	//  scala/Function1$class.compose:(Lscala/Function1;Lscala/Function1;)Lscala/Function1;
const #146 = Asciz	toString;
const #147 = Asciz	()Ljava/lang/String;;
const #148 = Asciz	(Lscala/Function1;)Ljava/lang/String;;
const #149 = NameAndType	#146:#148;//  toString:(Lscala/Function1;)Ljava/lang/String;
const #150 = Method	#16.#149;	//  scala/Function1$class.toString:(Lscala/Function1;)Ljava/lang/String;
const #151 = Asciz	<A:Ljava/lang/Object;>Lscala/concurrent/pilib$UChan;Lscala/Function1<TA;Lscala/concurrent/pilib$Product<TA;>;>;Lscala/ScalaObject;;
const #152 = Asciz	Scala;
const #153 = Asciz	InnerClasses;
const #154 = Asciz	scala/concurrent/pilib;
const #155 = class	#154;	//  scala/concurrent/pilib
const #156 = Asciz	GP;
const #157 = Asciz	Chan;
const #158 = Asciz	UChan;
const #159 = Asciz	Product;
const #160 = Asciz	$anonfun$read$1;
const #161 = Asciz	$anonfun$input$1;
const #162 = Asciz	$anonfun$write$1;
const #163 = Asciz	$anonfun$output$1;
const #164 = Asciz	$anonfun$attach$1;
const #165 = Asciz	scala/Function1;
const #166 = class	#165;	//  scala/Function1
const #167 = Asciz	scala/ScalaObject;
const #168 = class	#167;	//  scala/ScalaObject

{
public scala.concurrent.pilib$Chan();
  Code:
   Stack=1, Locals=1, Args_size=1
   0:	aload_0
   1:	invokespecial	#14; //Method scala/concurrent/pilib$UChan."<init>":()V
   4:	aload_0
   5:	invokestatic	#20; //Method scala/Function1$class.$init$:(Lscala/Function1;)V
   8:	return
  LineNumberTable: 
   line 83: 0

  Signature: length = 0x2
   00 08 

public java.lang.Object apply(java.lang.Object);
  Code:
   Stack=2, Locals=2, Args_size=2
   0:	aload_0
   1:	aload_1
   2:	invokevirtual	#27; //Method apply:(Ljava/lang/Object;)Lscala/concurrent/pilib$Product;
   5:	areturn
  LineNumberTable: 
   line 83: 0

  LocalVariableTable: 
   Start  Length  Slot  Name   Signature
   0      6      0    this       Lscala/concurrent/pilib$Chan;
   0      6      1    v1       Ljava/lang/Object;


public void attach(scala.Function1);
  Code:
   Stack=5, Locals=2, Args_size=2
   0:	aload_0
   1:	new	#34; //class scala/concurrent/pilib$Chan$$anonfun$attach$1
   4:	dup
   5:	aload_0
   6:	aload_1
   7:	invokespecial	#37; //Method scala/concurrent/pilib$Chan$$anonfun$attach$1."<init>":(Lscala/concurrent/pilib$Chan;Lscala/Function1;)V
   10:	invokevirtual	#40; //Method log_$eq:(Lscala/Function1;)V
   13:	return
  LineNumberTable: 
   line 118: 0

  LocalVariableTable: 
   Start  Length  Slot  Name   Signature
   0      14      0    this       Lscala/concurrent/pilib$Chan;
   0      14      1    f$1       Lscala/Function1;

  Signature: length = 0x2
   00 2B 

public scala.concurrent.pilib$Product apply(java.lang.Object);
  Code:
   Stack=4, Locals=2, Args_size=2
   0:	new	#45; //class scala/concurrent/pilib$Product
   3:	dup
   4:	aload_0
   5:	aload_1
   6:	invokespecial	#48; //Method scala/concurrent/pilib$Product."<init>":(Lscala/concurrent/pilib$Chan;Ljava/lang/Object;)V
   9:	areturn
  LineNumberTable: 
   line 112: 0

  LocalVariableTable: 
   Start  Length  Slot  Name   Signature
   0      10      0    this       Lscala/concurrent/pilib$Chan;
   0      10      1    v       Ljava/lang/Object;

  Signature: length = 0x2
   00 32 

public scala.concurrent.pilib$GP $times(scala.Function1);
  Code:
   Stack=2, Locals=2, Args_size=2
   0:	aload_0
   1:	aload_1
   2:	invokevirtual	#55; //Method input:(Lscala/Function1;)Lscala/concurrent/pilib$GP;
   5:	areturn
  LineNumberTable: 
   line 108: 0

  LocalVariableTable: 
   Start  Length  Slot  Name   Signature
   0      6      0    this       Lscala/concurrent/pilib$Chan;
   0      6      1    f       Lscala/Function1;

  Signature: length = 0x2
   00 39 

public void write(java.lang.Object);
  Code:
   Stack=10, Locals=2, Args_size=2
   0:	getstatic	#65; //Field scala/concurrent/pilib$.MODULE$:Lscala/concurrent/pilib$;
   3:	getstatic	#70; //Field scala/Predef$.MODULE$:Lscala/Predef$;
   6:	iconst_1
   7:	anewarray	#72; //class scala/concurrent/pilib$GP
   10:	dup
   11:	iconst_0
   12:	aload_0
   13:	aload_1
   14:	new	#74; //class scala/concurrent/pilib$Chan$$anonfun$write$1
   17:	dup
   18:	aload_0
   19:	invokespecial	#77; //Method scala/concurrent/pilib$Chan$$anonfun$write$1."<init>":(Lscala/concurrent/pilib$Chan;)V
   22:	invokevirtual	#81; //Method output:(Ljava/lang/Object;Lscala/Function0;)Lscala/concurrent/pilib$GP;
   25:	aastore
   26:	checkcast	#83; //class "[Ljava/lang/Object;"
   29:	invokevirtual	#87; //Method scala/Predef$.wrapRefArray:([Ljava/lang/Object;)Lscala/collection/mutable/WrappedArray;
   32:	invokevirtual	#91; //Method scala/concurrent/pilib$.choice:(Lscala/collection/Seq;)Ljava/lang/Object;
   35:	pop
   36:	return
  LineNumberTable: 
   line 104: 0

  LocalVariableTable: 
   Start  Length  Slot  Name   Signature
   0      37      0    this       Lscala/concurrent/pilib$Chan;
   0      37      1    x       Ljava/lang/Object;

  Signature: length = 0x2
   00 5D 

public java.lang.Object read();
  Code:
   Stack=10, Locals=2, Args_size=1
   0:	new	#97; //class scala/runtime/ObjectRef
   3:	dup
   4:	aload_0
   5:	invokevirtual	#99; //Method defaultValue:()Ljava/lang/Object;
   8:	invokespecial	#101; //Method scala/runtime/ObjectRef."<init>":(Ljava/lang/Object;)V
   11:	astore_1
   12:	getstatic	#65; //Field scala/concurrent/pilib$.MODULE$:Lscala/concurrent/pilib$;
   15:	getstatic	#70; //Field scala/Predef$.MODULE$:Lscala/Predef$;
   18:	iconst_1
   19:	anewarray	#72; //class scala/concurrent/pilib$GP
   22:	dup
   23:	iconst_0
   24:	aload_0
   25:	new	#103; //class scala/concurrent/pilib$Chan$$anonfun$read$1
   28:	dup
   29:	aload_0
   30:	aload_1
   31:	invokespecial	#106; //Method scala/concurrent/pilib$Chan$$anonfun$read$1."<init>":(Lscala/concurrent/pilib$Chan;Lscala/runtime/ObjectRef;)V
   34:	invokevirtual	#55; //Method input:(Lscala/Function1;)Lscala/concurrent/pilib$GP;
   37:	aastore
   38:	checkcast	#83; //class "[Ljava/lang/Object;"
   41:	invokevirtual	#87; //Method scala/Predef$.wrapRefArray:([Ljava/lang/Object;)Lscala/collection/mutable/WrappedArray;
   44:	invokevirtual	#91; //Method scala/concurrent/pilib$.choice:(Lscala/collection/Seq;)Ljava/lang/Object;
   47:	pop
   48:	aload_1
   49:	getfield	#109; //Field scala/runtime/ObjectRef.elem:Ljava/lang/Object;
   52:	areturn
  LineNumberTable: 
   line 97: 0
   line 98: 12
   line 99: 30
   line 98: 31
   line 99: 48

  LocalVariableTable: 
   Start  Length  Slot  Name   Signature
   0      53      0    this       Lscala/concurrent/pilib$Chan;
   12      40      1    res$1       Lscala/runtime/ObjectRef;

  Signature: length = 0x2
   00 70 

public scala.concurrent.pilib$GP output(java.lang.Object, scala.Function0);
  Code:
   Stack=9, Locals=3, Args_size=3
   0:	new	#72; //class scala/concurrent/pilib$GP
   3:	dup
   4:	aload_0
   5:	iconst_0
   6:	aload_1
   7:	new	#114; //class scala/concurrent/pilib$Chan$$anonfun$output$1
   10:	dup
   11:	aload_0
   12:	aload_2
   13:	invokespecial	#117; //Method scala/concurrent/pilib$Chan$$anonfun$output$1."<init>":(Lscala/concurrent/pilib$Chan;Lscala/Function0;)V
   16:	invokespecial	#120; //Method scala/concurrent/pilib$GP."<init>":(Lscala/concurrent/pilib$UChan;ZLjava/lang/Object;Lscala/Function1;)V
   19:	areturn
  LineNumberTable: 
   line 93: 0

  LocalVariableTable: 
   Start  Length  Slot  Name   Signature
   0      20      0    this       Lscala/concurrent/pilib$Chan;
   0      20      1    v       Ljava/lang/Object;
   0      20      2    c$3       Lscala/Function0;

  Signature: length = 0x2
   00 7B 

public scala.concurrent.pilib$GP input(scala.Function1);
  Code:
   Stack=9, Locals=2, Args_size=2
   0:	new	#72; //class scala/concurrent/pilib$GP
   3:	dup
   4:	aload_0
   5:	iconst_1
   6:	getstatic	#129; //Field scala/runtime/BoxedUnit.UNIT:Lscala/runtime/BoxedUnit;
   9:	new	#131; //class scala/concurrent/pilib$Chan$$anonfun$input$1
   12:	dup
   13:	aload_0
   14:	aload_1
   15:	invokespecial	#132; //Method scala/concurrent/pilib$Chan$$anonfun$input$1."<init>":(Lscala/concurrent/pilib$Chan;Lscala/Function1;)V
   18:	invokespecial	#120; //Method scala/concurrent/pilib$GP."<init>":(Lscala/concurrent/pilib$UChan;ZLjava/lang/Object;Lscala/Function1;)V
   21:	areturn
  LineNumberTable: 
   line 89: 0

  LocalVariableTable: 
   Start  Length  Slot  Name   Signature
   0      22      0    this       Lscala/concurrent/pilib$Chan;
   0      22      1    c$2       Lscala/Function1;

  Signature: length = 0x2
   00 39 

public void defaultValue_$eq(java.lang.Object);
  Code:
   Stack=2, Locals=2, Args_size=2
   0:	aload_0
   1:	aload_1
   2:	putfield	#136; //Field defaultValue:Ljava/lang/Object;
   5:	return
  LineNumberTable: 
   line 85: 0

  Signature: length = 0x2
   00 5D 

public java.lang.Object defaultValue();
  Code:
   Stack=1, Locals=1, Args_size=1
   0:	aload_0
   1:	getfield	#136; //Field defaultValue:Ljava/lang/Object;
   4:	areturn
  LineNumberTable: 
   line 85: 0

  Signature: length = 0x2
   00 70 

public scala.Function1 andThen(scala.Function1);
  Code:
   Stack=2, Locals=2, Args_size=2
   0:	aload_0
   1:	aload_1
   2:	invokestatic	#141; //Method scala/Function1$class.andThen:(Lscala/Function1;Lscala/Function1;)Lscala/Function1;
   5:	areturn
  LineNumberTable: 
   line 83: 0

  LocalVariableTable: 
   Start  Length  Slot  Name   Signature
   0      6      0    this       Lscala/concurrent/pilib$Chan;
   0      6      1    g       Lscala/Function1;


public scala.Function1 compose(scala.Function1);
  Code:
   Stack=2, Locals=2, Args_size=2
   0:	aload_0
   1:	aload_1
   2:	invokestatic	#145; //Method scala/Function1$class.compose:(Lscala/Function1;Lscala/Function1;)Lscala/Function1;
   5:	areturn
  LineNumberTable: 
   line 83: 0

  LocalVariableTable: 
   Start  Length  Slot  Name   Signature
   0      6      0    this       Lscala/concurrent/pilib$Chan;
   0      6      1    g       Lscala/Function1;


public java.lang.String toString();
  Code:
   Stack=1, Locals=1, Args_size=1
   0:	aload_0
   1:	invokestatic	#150; //Method scala/Function1$class.toString:(Lscala/Function1;)Ljava/lang/String;
   4:	areturn
  LineNumberTable: 
   line 83: 0


}

