Compiled from "TaskRunners.scala"
public final class scala.concurrent.TaskRunners$ extends java.lang.Object implements scala.ScalaObject
  SourceFile: "TaskRunners.scala"
  Scala: length = 0x
   
  InnerClass: 
   public #80= #52 of #44; //CallerRunsPolicy=class java/util/concurrent/ThreadPoolExecutor$CallerRunsPolicy of class java/util/concurrent/ThreadPoolExecutor
  minor version: 0
  major version: 49
  Constant pool:
const #1 = Asciz	SourceFile;
const #2 = Asciz	TaskRunners.scala;
const #3 = Asciz	Scala;
const #4 = Asciz	MODULE$;
const #5 = Asciz	Lscala/concurrent/TaskRunners$;;
const #6 = Asciz	<clinit>;
const #7 = Asciz	()V;
const #8 = Asciz	Code;
const #9 = Asciz	scala/concurrent/TaskRunners$;
const #10 = class	#9;	//  scala/concurrent/TaskRunners$
const #11 = Asciz	<init>;
const #12 = NameAndType	#11:#7;//  "<init>":()V
const #13 = Method	#10.#12;	//  scala/concurrent/TaskRunners$."<init>":()V
const #14 = Asciz	threadPoolRunner;
const #15 = Asciz	Lscala/concurrent/FutureTaskRunner;;
const #16 = Asciz	threadRunner;
const #17 = Asciz	LineNumberTable;
const #18 = Asciz	java/lang/Object;
const #19 = class	#18;	//  java/lang/Object
const #20 = Method	#19.#12;	//  java/lang/Object."<init>":()V
const #21 = NameAndType	#4:#5;//  MODULE$:Lscala/concurrent/TaskRunners$;
const #22 = Field	#10.#21;	//  scala/concurrent/TaskRunners$.MODULE$:Lscala/concurrent/TaskRunners$;
const #23 = Asciz	scala/concurrent/ThreadRunner;
const #24 = class	#23;	//  scala/concurrent/ThreadRunner
const #25 = Method	#24.#12;	//  scala/concurrent/ThreadRunner."<init>":()V
const #26 = NameAndType	#16:#15;//  threadRunner:Lscala/concurrent/FutureTaskRunner;
const #27 = Field	#10.#26;	//  scala/concurrent/TaskRunners$.threadRunner:Lscala/concurrent/FutureTaskRunner;
const #28 = Asciz	java/lang/Runtime;
const #29 = class	#28;	//  java/lang/Runtime
const #30 = Asciz	getRuntime;
const #31 = Asciz	()Ljava/lang/Runtime;;
const #32 = NameAndType	#30:#31;//  getRuntime:()Ljava/lang/Runtime;
const #33 = Method	#29.#32;	//  java/lang/Runtime.getRuntime:()Ljava/lang/Runtime;
const #34 = Asciz	availableProcessors;
const #35 = Asciz	()I;
const #36 = NameAndType	#34:#35;//  availableProcessors:()I
const #37 = Method	#29.#36;	//  java/lang/Runtime.availableProcessors:()I
const #38 = long	60000l;
const #40 = Asciz	java/util/concurrent/LinkedBlockingQueue;
const #41 = class	#40;	//  java/util/concurrent/LinkedBlockingQueue
const #42 = Method	#41.#12;	//  java/util/concurrent/LinkedBlockingQueue."<init>":()V
const #43 = Asciz	java/util/concurrent/ThreadPoolExecutor;
const #44 = class	#43;	//  java/util/concurrent/ThreadPoolExecutor
const #45 = Asciz	java/util/concurrent/TimeUnit;
const #46 = class	#45;	//  java/util/concurrent/TimeUnit
const #47 = Asciz	MILLISECONDS;
const #48 = Asciz	Ljava/util/concurrent/TimeUnit;;
const #49 = NameAndType	#47:#48;//  MILLISECONDS:Ljava/util/concurrent/TimeUnit;
const #50 = Field	#46.#49;	//  java/util/concurrent/TimeUnit.MILLISECONDS:Ljava/util/concurrent/TimeUnit;
const #51 = Asciz	java/util/concurrent/ThreadPoolExecutor$CallerRunsPolicy;
const #52 = class	#51;	//  java/util/concurrent/ThreadPoolExecutor$CallerRunsPolicy
const #53 = Method	#52.#12;	//  java/util/concurrent/ThreadPoolExecutor$CallerRunsPolicy."<init>":()V
const #54 = Asciz	(IIJLjava/util/concurrent/TimeUnit;Ljava/util/concurrent/BlockingQueue;Ljava/util/concurrent/RejectedExecutionHandler;)V;
const #55 = NameAndType	#11:#54;//  "<init>":(IIJLjava/util/concurrent/TimeUnit;Ljava/util/concurrent/BlockingQueue;Ljava/util/concurrent/RejectedExecutionHandler;)V
const #56 = Method	#44.#55;	//  java/util/concurrent/ThreadPoolExecutor."<init>":(IIJLjava/util/concurrent/TimeUnit;Ljava/util/concurrent/BlockingQueue;Ljava/util/concurrent/RejectedExecutionHandler;)V
const #57 = Asciz	scala/concurrent/JavaConversions$;
const #58 = class	#57;	//  scala/concurrent/JavaConversions$
const #59 = Asciz	Lscala/concurrent/JavaConversions$;;
const #60 = NameAndType	#4:#59;//  MODULE$:Lscala/concurrent/JavaConversions$;
const #61 = Field	#58.#60;	//  scala/concurrent/JavaConversions$.MODULE$:Lscala/concurrent/JavaConversions$;
const #62 = Asciz	asTaskRunner;
const #63 = Asciz	(Ljava/util/concurrent/ExecutorService;)Lscala/concurrent/FutureTaskRunner;;
const #64 = NameAndType	#62:#63;//  asTaskRunner:(Ljava/util/concurrent/ExecutorService;)Lscala/concurrent/FutureTaskRunner;
const #65 = Method	#58.#64;	//  scala/concurrent/JavaConversions$.asTaskRunner:(Ljava/util/concurrent/ExecutorService;)Lscala/concurrent/FutureTaskRunner;
const #66 = NameAndType	#14:#15;//  threadPoolRunner:Lscala/concurrent/FutureTaskRunner;
const #67 = Field	#10.#66;	//  scala/concurrent/TaskRunners$.threadPoolRunner:Lscala/concurrent/FutureTaskRunner;
const #68 = Asciz	this;
const #69 = Asciz	numCores;
const #70 = Asciz	I;
const #71 = Asciz	keepAliveTime;
const #72 = Asciz	J;
const #73 = Asciz	workQueue;
const #74 = Asciz	Ljava/util/concurrent/LinkedBlockingQueue;;
const #75 = Asciz	exec;
const #76 = Asciz	Ljava/util/concurrent/ThreadPoolExecutor;;
const #77 = Asciz	LocalVariableTable;
const #78 = Asciz	()Lscala/concurrent/FutureTaskRunner;;
const #79 = Asciz	InnerClasses;
const #80 = Asciz	CallerRunsPolicy;
const #81 = Asciz	scala/ScalaObject;
const #82 = class	#81;	//  scala/ScalaObject

{
public static final scala.concurrent.TaskRunners$ MODULE$;

public static {};
  Code:
   Stack=1, Locals=0, Args_size=0
   0:	new	#10; //class scala/concurrent/TaskRunners$
   3:	invokespecial	#13; //Method "<init>":()V
   6:	return

public scala.concurrent.FutureTaskRunner threadPoolRunner();
  Code:
   Stack=1, Locals=1, Args_size=1
   0:	aload_0
   1:	getfield	#67; //Field threadPoolRunner:Lscala/concurrent/FutureTaskRunner;
   4:	areturn
  LineNumberTable: 
   line 25: 0


public scala.concurrent.FutureTaskRunner threadRunner();
  Code:
   Stack=1, Locals=1, Args_size=1
   0:	aload_0
   1:	getfield	#27; //Field threadRunner:Lscala/concurrent/FutureTaskRunner;
   4:	areturn
  LineNumberTable: 
   line 22: 0


}

