Compiled from "TaskRunners.scala"
public final class scala.concurrent.TaskRunners$ extends java.lang.Object implements scala.ScalaObject
  SourceFile: "TaskRunners.scala"
  Scala: length = 0x
   
  InnerClass: 
   public CallerRunsPolicy=class java/util/concurrent/ThreadPoolExecutor$CallerRunsPolicy of class java/util/concurrent/ThreadPoolExecutor
  minor version: 0
  major version: 49
  Constant pool:
Asciz	SourceFile;
Asciz	TaskRunners.scala;
Asciz	Scala;
Asciz	MODULE$;
Asciz	Lscala/concurrent/TaskRunners$;;
Asciz	<clinit>;
Asciz	()V;
Asciz	Code;
Asciz	scala/concurrent/TaskRunners$;
class	scala/concurrent/TaskRunners$
Asciz	<init>;
NameAndType	"<init>":()V
Method	scala/concurrent/TaskRunners$."<init>":()V
Asciz	threadPoolRunner;
Asciz	Lscala/concurrent/FutureTaskRunner;;
Asciz	threadRunner;
Asciz	LineNumberTable;
Asciz	java/lang/Object;
class	java/lang/Object
Method	java/lang/Object."<init>":()V
NameAndType	MODULE$:Lscala/concurrent/TaskRunners$;
Field	scala/concurrent/TaskRunners$.MODULE$:Lscala/concurrent/TaskRunners$;
Asciz	scala/concurrent/ThreadRunner;
class	scala/concurrent/ThreadRunner
Method	scala/concurrent/ThreadRunner."<init>":()V
NameAndType	threadRunner:Lscala/concurrent/FutureTaskRunner;
Field	scala/concurrent/TaskRunners$.threadRunner:Lscala/concurrent/FutureTaskRunner;
Asciz	java/lang/Runtime;
class	java/lang/Runtime
Asciz	getRuntime;
Asciz	()Ljava/lang/Runtime;;
NameAndType	getRuntime:()Ljava/lang/Runtime;
Method	java/lang/Runtime.getRuntime:()Ljava/lang/Runtime;
Asciz	availableProcessors;
Asciz	()I;
NameAndType	availableProcessors:()I
Method	java/lang/Runtime.availableProcessors:()I
long	60000l;
Asciz	java/util/concurrent/LinkedBlockingQueue;
class	java/util/concurrent/LinkedBlockingQueue
Method	java/util/concurrent/LinkedBlockingQueue."<init>":()V
Asciz	java/util/concurrent/ThreadPoolExecutor;
class	java/util/concurrent/ThreadPoolExecutor
Asciz	java/util/concurrent/TimeUnit;
class	java/util/concurrent/TimeUnit
Asciz	MILLISECONDS;
Asciz	Ljava/util/concurrent/TimeUnit;;
NameAndType	MILLISECONDS:Ljava/util/concurrent/TimeUnit;
Field	java/util/concurrent/TimeUnit.MILLISECONDS:Ljava/util/concurrent/TimeUnit;
Asciz	java/util/concurrent/ThreadPoolExecutor$CallerRunsPolicy;
class	java/util/concurrent/ThreadPoolExecutor$CallerRunsPolicy
Method	java/util/concurrent/ThreadPoolExecutor$CallerRunsPolicy."<init>":()V
Asciz	(IIJLjava/util/concurrent/TimeUnit;Ljava/util/concurrent/BlockingQueue;Ljava/util/concurrent/RejectedExecutionHandler;)V;
NameAndType	"<init>":(IIJLjava/util/concurrent/TimeUnit;Ljava/util/concurrent/BlockingQueue;Ljava/util/concurrent/RejectedExecutionHandler;)V
Method	java/util/concurrent/ThreadPoolExecutor."<init>":(IIJLjava/util/concurrent/TimeUnit;Ljava/util/concurrent/BlockingQueue;Ljava/util/concurrent/RejectedExecutionHandler;)V
Asciz	scala/concurrent/JavaConversions$;
class	scala/concurrent/JavaConversions$
Asciz	Lscala/concurrent/JavaConversions$;;
NameAndType	MODULE$:Lscala/concurrent/JavaConversions$;
Field	scala/concurrent/JavaConversions$.MODULE$:Lscala/concurrent/JavaConversions$;
Asciz	asTaskRunner;
Asciz	(Ljava/util/concurrent/ExecutorService;)Lscala/concurrent/FutureTaskRunner;;
NameAndType	asTaskRunner:(Ljava/util/concurrent/ExecutorService;)Lscala/concurrent/FutureTaskRunner;
Method	scala/concurrent/JavaConversions$.asTaskRunner:(Ljava/util/concurrent/ExecutorService;)Lscala/concurrent/FutureTaskRunner;
NameAndType	threadPoolRunner:Lscala/concurrent/FutureTaskRunner;
Field	scala/concurrent/TaskRunners$.threadPoolRunner:Lscala/concurrent/FutureTaskRunner;
Asciz	this;
Asciz	numCores;
Asciz	I;
Asciz	keepAliveTime;
Asciz	J;
Asciz	workQueue;
Asciz	Ljava/util/concurrent/LinkedBlockingQueue;;
Asciz	exec;
Asciz	Ljava/util/concurrent/ThreadPoolExecutor;;
Asciz	LocalVariableTable;
Asciz	()Lscala/concurrent/FutureTaskRunner;;
Asciz	InnerClasses;
Asciz	CallerRunsPolicy;
Asciz	scala/ScalaObject;
class	scala/ScalaObject

{
public static final scala.concurrent.TaskRunners$ MODULE$;
  Signature: Lscala/concurrent/TaskRunners$;

private final scala.concurrent.FutureTaskRunner threadPoolRunner;
  Signature: Lscala/concurrent/FutureTaskRunner;

private final scala.concurrent.FutureTaskRunner threadRunner;
  Signature: Lscala/concurrent/FutureTaskRunner;

public static {};
  Signature: ()V
  Code:
   Stack=1, Locals=0, Args_size=0
	new	class scala/concurrent/TaskRunners$
	invokespecial	Method "<init>":()V
	return
  Labels:

private scala.concurrent.TaskRunners$();
  Signature: ()V
  Code:
   Stack=11, Locals=6, Args_size=1
	aload_0
	invokespecial	Method java/lang/Object."<init>":()V
	aload_0
	putstatic	Field MODULE$:Lscala/concurrent/TaskRunners$;
	aload_0
	new	class scala/concurrent/ThreadRunner
	dup
	invokespecial	Method scala/concurrent/ThreadRunner."<init>":()V
	putfield	Field threadRunner:Lscala/concurrent/FutureTaskRunner;
	aload_0
	invokestatic	Method java/lang/Runtime.getRuntime:()Ljava/lang/Runtime;
	invokevirtual	Method java/lang/Runtime.availableProcessors:()I
	istore_1
	ldc2_w	long 60000l
	lstore_2
	new	class java/util/concurrent/LinkedBlockingQueue
	dup
	invokespecial	Method java/util/concurrent/LinkedBlockingQueue."<init>":()V
	astore	4
	new	class java/util/concurrent/ThreadPoolExecutor
	dup
	iload_1
	iload_1
	lload_2
	getstatic	Field java/util/concurrent/TimeUnit.MILLISECONDS:Ljava/util/concurrent/TimeUnit;
	aload	4
	new	class java/util/concurrent/ThreadPoolExecutor$CallerRunsPolicy
	dup
	invokespecial	Method java/util/concurrent/ThreadPoolExecutor$CallerRunsPolicy."<init>":()V
	invokespecial	Method java/util/concurrent/ThreadPoolExecutor."<init>":(IIJLjava/util/concurrent/TimeUnit;Ljava/util/concurrent/BlockingQueue;Ljava/util/concurrent/RejectedExecutionHandler;)V
	astore	5
	getstatic	Field scala/concurrent/JavaConversions$.MODULE$:Lscala/concurrent/JavaConversions$;
	aload	5
	invokevirtual	Method scala/concurrent/JavaConversions$.asTaskRunner:(Ljava/util/concurrent/ExecutorService;)Lscala/concurrent/FutureTaskRunner;
	putfield	Field threadPoolRunner:Lscala/concurrent/FutureTaskRunner;
	return
  Labels:
  LocalVariableTable: 
   Start  Length  Slot  Name   Signature
   0      76      0    this       Lscala/concurrent/TaskRunners$;
   27      45      1    numCores       I
   31      41      2    keepAliveTime       J
   40      32      4    workQueue       Ljava/util/concurrent/LinkedBlockingQueue;
   64      8      5    exec       Ljava/util/concurrent/ThreadPoolExecutor;


public scala.concurrent.FutureTaskRunner threadPoolRunner();
  Signature: ()Lscala/concurrent/FutureTaskRunner;
  Code:
   Stack=1, Locals=1, Args_size=1
	aload_0
	getfield	Field threadPoolRunner:Lscala/concurrent/FutureTaskRunner;
	areturn
  Labels:

public scala.concurrent.FutureTaskRunner threadRunner();
  Signature: ()Lscala/concurrent/FutureTaskRunner;
  Code:
   Stack=1, Locals=1, Args_size=1
	aload_0
	getfield	Field threadRunner:Lscala/concurrent/FutureTaskRunner;
	areturn
  Labels:

}

