Compiled from "ThreadPoolRunner.scala"
public final class scala.concurrent.ThreadPoolRunner$$anonfun$futureAsFunction$1 extends java.lang.Object implements scala.Function0,scala.ScalaObject,java.io.Serializable
  SourceFile: "ThreadPoolRunner.scala"
  Scala: length = 0x
   
  InnerClass: 
   public final $anonfun$futureAsFunction$1=class scala/concurrent/ThreadPoolRunner$$anonfun$futureAsFunction$1 of class scala/concurrent/ThreadPoolRunner
  minor version: 0
  major version: 49
  Constant pool:
Asciz	SourceFile;
Asciz	ThreadPoolRunner.scala;
Asciz	<clinit>;
Asciz	()V;
Asciz	Code;
Asciz	serialVersionUID;
Asciz	J;
Asciz	scala/concurrent/ThreadPoolRunner$$anonfun$futureAsFunction$1;
class	scala/concurrent/ThreadPoolRunner$$anonfun$futureAsFunction$1
NameAndType	serialVersionUID:J
Field	scala/concurrent/ThreadPoolRunner$$anonfun$futureAsFunction$1.serialVersionUID:J
Asciz	x$1;
Asciz	Ljava/util/concurrent/Future;;
Asciz	<init>;
Asciz	(Lscala/concurrent/ThreadPoolRunner;Ljava/util/concurrent/Future;)V;
Asciz	LineNumberTable;
NameAndType	x$1:Ljava/util/concurrent/Future;
Field	scala/concurrent/ThreadPoolRunner$$anonfun$futureAsFunction$1.x$1:Ljava/util/concurrent/Future;
Asciz	java/lang/Object;
class	java/lang/Object
NameAndType	"<init>":()V
Method	java/lang/Object."<init>":()V
Asciz	scala/Function0$class;
class	scala/Function0$class
Asciz	$init$;
Asciz	(Lscala/Function0;)V;
NameAndType	$init$:(Lscala/Function0;)V
Method	scala/Function0$class.$init$:(Lscala/Function0;)V
Asciz	this;
Asciz	Lscala/concurrent/ThreadPoolRunner$$anonfun$futureAsFunction$1;;
Asciz	$outer;
Asciz	Lscala/concurrent/ThreadPoolRunner;;
Asciz	LocalVariableTable;
Asciz	apply;
Asciz	()Ljava/lang/Object;;
Asciz	java/util/concurrent/Future;
class	java/util/concurrent/Future
Asciz	get;
NameAndType	get:()Ljava/lang/Object;
InterfaceMethod	java/util/concurrent/Future.get:()Ljava/lang/Object;
Asciz	()TS;;
Asciz	Signature;
Asciz	toString;
Asciz	()Ljava/lang/String;;
Asciz	(Lscala/Function0;)Ljava/lang/String;;
NameAndType	toString:(Lscala/Function0;)Ljava/lang/String;
Method	scala/Function0$class.toString:(Lscala/Function0;)Ljava/lang/String;
Asciz	Scala;
Asciz	InnerClasses;
Asciz	scala/concurrent/ThreadPoolRunner;
class	scala/concurrent/ThreadPoolRunner
Asciz	$anonfun$futureAsFunction$1;
Asciz	scala/Function0;
class	scala/Function0
Asciz	scala/ScalaObject;
class	scala/ScalaObject
Asciz	java/io/Serializable;
class	java/io/Serializable

{
public static final long serialVersionUID;
  Signature: J

private final java.util.concurrent.Future x$1;
  Signature: Ljava/util/concurrent/Future;

public static {};
  Signature: ()V
  Code:
   Stack=2, Locals=0, Args_size=0
	lconst_0
	putstatic	Field serialVersionUID:J
	return
  Labels:

public scala.concurrent.ThreadPoolRunner$$anonfun$futureAsFunction$1(scala.concurrent.ThreadPoolRunner, java.util.concurrent.Future);
  Signature: (Lscala/concurrent/ThreadPoolRunner;Ljava/util/concurrent/Future;)V
  Code:
   Stack=2, Locals=3, Args_size=3
	aload_0
	aload_2
	putfield	Field x$1:Ljava/util/concurrent/Future;
	aload_0
	invokespecial	Method java/lang/Object."<init>":()V
	aload_0
	invokestatic	Method scala/Function0$class.$init$:(Lscala/Function0;)V
	return
  Labels:
  LocalVariableTable: 
   Start  Length  Slot  Name   Signature
   0      14      0    this       Lscala/concurrent/ThreadPoolRunner$$anonfun$futureAsFunction$1;
   0      14      1    $outer       Lscala/concurrent/ThreadPoolRunner;


public final java.lang.Object apply();
  Signature: ()Ljava/lang/Object;
  Code:
   Stack=1, Locals=1, Args_size=1
	aload_0
	getfield	Field x$1:Ljava/util/concurrent/Future;
	invokeinterface	InterfaceMethod java/util/concurrent/Future.get:()Ljava/lang/Object;
	areturn
  Labels:
  Signature: length = 0x2
   00 29 

public java.lang.String toString();
  Signature: ()Ljava/lang/String;
  Code:
   Stack=1, Locals=1, Args_size=1
	aload_0
	invokestatic	Method scala/Function0$class.toString:(Lscala/Function0;)Ljava/lang/String;
	areturn
  Labels:

}

