Compiled from "ThreadPoolRunner.scala"
public class scala.concurrent.ThreadPoolRunner$RunCallable extends java.lang.Object implements java.lang.Runnable,java.util.concurrent.Callable,scala.ScalaObject
  SourceFile: "ThreadPoolRunner.scala"
  Signature: length = 0x2
   00 2A 
  Scala: length = 0x
   
  InnerClass: 
   public #47= #14 of #46; //RunCallable=class scala/concurrent/ThreadPoolRunner$RunCallable of class scala/concurrent/ThreadPoolRunner
  minor version: 0
  major version: 49
  Constant pool:
const #1 = Asciz	SourceFile;
const #2 = Asciz	ThreadPoolRunner.scala;
const #3 = Asciz	$outer;
const #4 = Asciz	Lscala/concurrent/ThreadPoolRunner;;
const #5 = Asciz	fun;
const #6 = Asciz	Lscala/Function0;;
const #7 = Asciz	Lscala/Function0<TS;>;;
const #8 = Asciz	Signature;
const #9 = Asciz	<init>;
const #10 = Asciz	(Lscala/concurrent/ThreadPoolRunner;Lscala/Function0;)V;
const #11 = Asciz	Code;
const #12 = Asciz	LineNumberTable;
const #13 = Asciz	scala/concurrent/ThreadPoolRunner$RunCallable;
const #14 = class	#13;	//  scala/concurrent/ThreadPoolRunner$RunCallable
const #15 = NameAndType	#5:#6;//  fun:Lscala/Function0;
const #16 = Field	#14.#15;	//  scala/concurrent/ThreadPoolRunner$RunCallable.fun:Lscala/Function0;
const #17 = Asciz	java/lang/NullPointerException;
const #18 = class	#17;	//  java/lang/NullPointerException
const #19 = Asciz	()V;
const #20 = NameAndType	#9:#19;//  "<init>":()V
const #21 = Method	#18.#20;	//  java/lang/NullPointerException."<init>":()V
const #22 = NameAndType	#3:#4;//  $outer:Lscala/concurrent/ThreadPoolRunner;
const #23 = Field	#14.#22;	//  scala/concurrent/ThreadPoolRunner$RunCallable.$outer:Lscala/concurrent/ThreadPoolRunner;
const #24 = Asciz	java/lang/Object;
const #25 = class	#24;	//  java/lang/Object
const #26 = Method	#25.#20;	//  java/lang/Object."<init>":()V
const #27 = Asciz	this;
const #28 = Asciz	Lscala/concurrent/ThreadPoolRunner$RunCallable;;
const #29 = Asciz	LocalVariableTable;
const #30 = Asciz	(Lscala/concurrent/ThreadPoolRunner;Lscala/Function0<TS;>;)V;
const #31 = Asciz	scala$concurrent$ThreadPoolRunner$RunCallable$$$outer;
const #32 = Asciz	()Lscala/concurrent/ThreadPoolRunner;;
const #33 = Asciz	call;
const #34 = Asciz	()Ljava/lang/Object;;
const #35 = Asciz	scala/Function0;
const #36 = class	#35;	//  scala/Function0
const #37 = Asciz	apply;
const #38 = NameAndType	#37:#34;//  apply:()Ljava/lang/Object;
const #39 = InterfaceMethod	#36.#38;	//  scala/Function0.apply:()Ljava/lang/Object;
const #40 = Asciz	()TS;;
const #41 = Asciz	run;
const #42 = Asciz	<S:Ljava/lang/Object;>Ljava/lang/Object;Ljava/lang/Runnable;Ljava/util/concurrent/Callable<TS;>;Lscala/ScalaObject;;
const #43 = Asciz	Scala;
const #44 = Asciz	InnerClasses;
const #45 = Asciz	scala/concurrent/ThreadPoolRunner;
const #46 = class	#45;	//  scala/concurrent/ThreadPoolRunner
const #47 = Asciz	RunCallable;
const #48 = Asciz	java/lang/Runnable;
const #49 = class	#48;	//  java/lang/Runnable
const #50 = Asciz	java/util/concurrent/Callable;
const #51 = class	#50;	//  java/util/concurrent/Callable
const #52 = Asciz	scala/ScalaObject;
const #53 = class	#52;	//  scala/ScalaObject

{
public final scala.concurrent.ThreadPoolRunner $outer;

public scala.concurrent.ThreadPoolRunner$RunCallable(scala.concurrent.ThreadPoolRunner, scala.Function0);
  Code:
   Stack=2, Locals=3, Args_size=3
   0:	aload_0
   1:	aload_2
   2:	putfield	#16; //Field fun:Lscala/Function0;
   5:	aload_1
   6:	ifnonnull	17
   9:	new	#18; //class java/lang/NullPointerException
   12:	dup
   13:	invokespecial	#21; //Method java/lang/NullPointerException."<init>":()V
   16:	athrow
   17:	aload_0
   18:	aload_1
   19:	putfield	#23; //Field $outer:Lscala/concurrent/ThreadPoolRunner;
   22:	aload_0
   23:	invokespecial	#26; //Method java/lang/Object."<init>":()V
   26:	return
  LineNumberTable: 
   line 27: 0

  LocalVariableTable: 
   Start  Length  Slot  Name   Signature
   0      27      0    this       Lscala/concurrent/ThreadPoolRunner$RunCallable;
   0      27      1    $outer       Lscala/concurrent/ThreadPoolRunner;
   0      27      2    fun       Lscala/Function0;

  Signature: length = 0x2
   00 1E 

public scala.concurrent.ThreadPoolRunner scala$concurrent$ThreadPoolRunner$RunCallable$$$outer();
  Code:
   Stack=1, Locals=1, Args_size=1
   0:	aload_0
   1:	getfield	#23; //Field $outer:Lscala/concurrent/ThreadPoolRunner;
   4:	areturn
  LineNumberTable: 
   line 27: 0


public java.lang.Object call();
  Code:
   Stack=1, Locals=1, Args_size=1
   0:	aload_0
   1:	getfield	#16; //Field fun:Lscala/Function0;
   4:	invokeinterface	#39,  1; //InterfaceMethod scala/Function0.apply:()Ljava/lang/Object;
   9:	areturn
  LineNumberTable: 
   line 29: 0

  Signature: length = 0x2
   00 28 

public void run();
  Code:
   Stack=1, Locals=1, Args_size=1
   0:	aload_0
   1:	getfield	#16; //Field fun:Lscala/Function0;
   4:	invokeinterface	#39,  1; //InterfaceMethod scala/Function0.apply:()Ljava/lang/Object;
   9:	pop
   10:	return
  LineNumberTable: 
   line 28: 0


}

