Compiled from "ThreadRunner.scala"
public final class scala.concurrent.ThreadRunner$$anon$2$$anonfun$run$2 extends java.lang.Object implements scala.Function0,scala.ScalaObject,java.io.Serializable
  SourceFile: "ThreadRunner.scala"
  Scala: length = 0x
   
  InnerClass: 
   public final $anon$2=class scala/concurrent/ThreadRunner$$anon$2 of class scala/concurrent/ThreadRunner
   public final $anonfun$run$2=class scala/concurrent/ThreadRunner$$anon$2$$anonfun$run$2 of class scala/concurrent/ThreadRunner$$anon$2
  minor version: 0
  major version: 49
  Constant pool:
Asciz	SourceFile;
Asciz	ThreadRunner.scala;
Asciz	<clinit>;
Asciz	()V;
Asciz	Code;
Asciz	serialVersionUID;
Asciz	J;
Asciz	scala/concurrent/ThreadRunner$$anon$2$$anonfun$run$2;
class	scala/concurrent/ThreadRunner$$anon$2$$anonfun$run$2
NameAndType	serialVersionUID:J
Field	scala/concurrent/ThreadRunner$$anon$2$$anonfun$run$2.serialVersionUID:J
Asciz	$outer;
Asciz	Lscala/concurrent/ThreadRunner$$anon$2;;
Asciz	<init>;
Asciz	(Lscala/concurrent/ThreadRunner$$anon$2;)V;
Asciz	LineNumberTable;
Asciz	java/lang/NullPointerException;
class	java/lang/NullPointerException
NameAndType	"<init>":()V
Method	java/lang/NullPointerException."<init>":()V
NameAndType	$outer:Lscala/concurrent/ThreadRunner$$anon$2;
Field	scala/concurrent/ThreadRunner$$anon$2$$anonfun$run$2.$outer:Lscala/concurrent/ThreadRunner$$anon$2;
Asciz	java/lang/Object;
class	java/lang/Object
Method	java/lang/Object."<init>":()V
Asciz	scala/Function0$class;
class	scala/Function0$class
Asciz	$init$;
Asciz	(Lscala/Function0;)V;
NameAndType	$init$:(Lscala/Function0;)V
Method	scala/Function0$class.$init$:(Lscala/Function0;)V
Asciz	this;
Asciz	Lscala/concurrent/ThreadRunner$$anon$2$$anonfun$run$2;;
Asciz	LocalVariableTable;
Asciz	apply;
Asciz	()Ljava/lang/Object;;
Asciz	scala/concurrent/ThreadRunner$$anon$2;
class	scala/concurrent/ThreadRunner$$anon$2
Asciz	task$2;
Asciz	Lscala/Function0;;
NameAndType	task$2:Lscala/Function0;
Field	scala/concurrent/ThreadRunner$$anon$2.task$2:Lscala/Function0;
Asciz	scala/Function0;
class	scala/Function0
NameAndType	apply:()Ljava/lang/Object;
InterfaceMethod	scala/Function0.apply:()Ljava/lang/Object;
Asciz	()TS;;
Asciz	Signature;
Asciz	toString;
Asciz	()Ljava/lang/String;;
Asciz	(Lscala/Function0;)Ljava/lang/String;;
NameAndType	toString:(Lscala/Function0;)Ljava/lang/String;
Method	scala/Function0$class.toString:(Lscala/Function0;)Ljava/lang/String;
Asciz	Scala;
Asciz	InnerClasses;
Asciz	scala/concurrent/ThreadRunner;
class	scala/concurrent/ThreadRunner
Asciz	$anon$2;
Asciz	$anonfun$run$2;
Asciz	scala/ScalaObject;
class	scala/ScalaObject
Asciz	java/io/Serializable;
class	java/io/Serializable

{
public static final long serialVersionUID;
  Signature: J

private final scala.concurrent.ThreadRunner$$anon$2 $outer;
  Signature: Lscala/concurrent/ThreadRunner$$anon$2;

public static {};
  Signature: ()V
  Code:
   Stack=2, Locals=0, Args_size=0
	lconst_0
	putstatic	Field serialVersionUID:J
	return
  Labels:

public scala.concurrent.ThreadRunner$$anon$2$$anonfun$run$2(scala.concurrent.ThreadRunner$$anon$2);
  Signature: (Lscala/concurrent/ThreadRunner$$anon$2;)V
  Code:
   Stack=2, Locals=2, Args_size=2
	aload_1
	ifnonnull	l1 // aload_0
	new	class java/lang/NullPointerException
	dup
	invokespecial	Method java/lang/NullPointerException."<init>":()V
	athrow
l1	aload_0
	aload_1
	putfield	Field $outer:Lscala/concurrent/ThreadRunner$$anon$2;
	aload_0
	invokespecial	Method java/lang/Object."<init>":()V
	aload_0
	invokestatic	Method scala/Function0$class.$init$:(Lscala/Function0;)V
	return
  Labels:
   	l1 = 12 // aload_0
  LocalVariableTable: 
   Start  Length  Slot  Name   Signature
   0      26      0    this       Lscala/concurrent/ThreadRunner$$anon$2$$anonfun$run$2;
   0      26      1    $outer       Lscala/concurrent/ThreadRunner$$anon$2;


public final java.lang.Object apply();
  Signature: ()Ljava/lang/Object;
  Code:
   Stack=1, Locals=2, Args_size=1
	aload_0
	getfield	Field $outer:Lscala/concurrent/ThreadRunner$$anon$2;
	astore_1
	aload_0
	getfield	Field $outer:Lscala/concurrent/ThreadRunner$$anon$2;
	getfield	Field scala/concurrent/ThreadRunner$$anon$2.task$2:Lscala/Function0;
	invokeinterface	InterfaceMethod scala/Function0.apply:()Ljava/lang/Object;
	areturn
  Labels:
  LocalVariableTable: 
   Start  Length  Slot  Name   Signature
   0      18      0    this       Lscala/concurrent/ThreadRunner$$anon$2$$anonfun$run$2;

  Signature: length = 0x2
   00 2F 

public java.lang.String toString();
  Signature: ()Ljava/lang/String;
  Code:
   Stack=1, Locals=1, Args_size=1
	aload_0
	invokestatic	Method scala/Function0$class.toString:(Lscala/Function0;)Ljava/lang/String;
	areturn
  Labels:

}

