Compiled from "ThreadRunner.scala"
public final class scala.concurrent.ThreadRunner$$anonfun$submit$1 extends java.lang.Object implements scala.Function0,scala.ScalaObject,java.io.Serializable
  SourceFile: "ThreadRunner.scala"
  Scala: length = 0x
   
  InnerClass: 
   public final $anonfun$submit$1=class scala/concurrent/ThreadRunner$$anonfun$submit$1 of class scala/concurrent/ThreadRunner
  minor version: 0
  major version: 49
  Constant pool:
Asciz	SourceFile;
Asciz	ThreadRunner.scala;
Asciz	<clinit>;
Asciz	()V;
Asciz	Code;
Asciz	serialVersionUID;
Asciz	J;
Asciz	scala/concurrent/ThreadRunner$$anonfun$submit$1;
class	scala/concurrent/ThreadRunner$$anonfun$submit$1
NameAndType	serialVersionUID:J
Field	scala/concurrent/ThreadRunner$$anonfun$submit$1.serialVersionUID:J
Asciz	result$1;
Asciz	Lscala/concurrent/SyncVar;;
Asciz	<init>;
Asciz	(Lscala/concurrent/ThreadRunner;Lscala/concurrent/SyncVar;)V;
Asciz	LineNumberTable;
NameAndType	result$1:Lscala/concurrent/SyncVar;
Field	scala/concurrent/ThreadRunner$$anonfun$submit$1.result$1:Lscala/concurrent/SyncVar;
Asciz	java/lang/Object;
class	java/lang/Object
NameAndType	"<init>":()V
Method	java/lang/Object."<init>":()V
Asciz	scala/Function0$class;
class	scala/Function0$class
Asciz	$init$;
Asciz	(Lscala/Function0;)V;
NameAndType	$init$:(Lscala/Function0;)V
Method	scala/Function0$class.$init$:(Lscala/Function0;)V
Asciz	this;
Asciz	Lscala/concurrent/ThreadRunner$$anonfun$submit$1;;
Asciz	$outer;
Asciz	Lscala/concurrent/ThreadRunner;;
Asciz	LocalVariableTable;
Asciz	apply;
Asciz	()Ljava/lang/Object;;
Asciz	scala/concurrent/ops$;
class	scala/concurrent/ops$
Asciz	MODULE$;
Asciz	Lscala/concurrent/ops$;;
NameAndType	MODULE$:Lscala/concurrent/ops$;
Field	scala/concurrent/ops$.MODULE$:Lscala/concurrent/ops$;
Asciz	scala/concurrent/SyncVar;
class	scala/concurrent/SyncVar
Asciz	get;
NameAndType	get:()Ljava/lang/Object;
Method	scala/concurrent/SyncVar.get:()Ljava/lang/Object;
Asciz	scala/Either;
class	scala/Either
Asciz	getOrThrow;
Asciz	(Lscala/Either;)Ljava/lang/Object;;
NameAndType	getOrThrow:(Lscala/Either;)Ljava/lang/Object;
Method	scala/concurrent/ops$.getOrThrow:(Lscala/Either;)Ljava/lang/Object;
Asciz	()TS;;
Asciz	Signature;
Asciz	toString;
Asciz	()Ljava/lang/String;;
Asciz	(Lscala/Function0;)Ljava/lang/String;;
NameAndType	toString:(Lscala/Function0;)Ljava/lang/String;
Method	scala/Function0$class.toString:(Lscala/Function0;)Ljava/lang/String;
Asciz	Scala;
Asciz	InnerClasses;
Asciz	scala/concurrent/ThreadRunner;
class	scala/concurrent/ThreadRunner
Asciz	$anonfun$submit$1;
Asciz	scala/Function0;
class	scala/Function0
Asciz	scala/ScalaObject;
class	scala/ScalaObject
Asciz	java/io/Serializable;
class	java/io/Serializable

{
public static final long serialVersionUID;
  Signature: J

private final scala.concurrent.SyncVar result$1;
  Signature: Lscala/concurrent/SyncVar;

public static {};
  Signature: ()V
  Code:
   Stack=2, Locals=0, Args_size=0
	lconst_0
	putstatic	Field serialVersionUID:J
	return
  Labels:

public scala.concurrent.ThreadRunner$$anonfun$submit$1(scala.concurrent.ThreadRunner, scala.concurrent.SyncVar);
  Signature: (Lscala/concurrent/ThreadRunner;Lscala/concurrent/SyncVar;)V
  Code:
   Stack=2, Locals=3, Args_size=3
	aload_0
	aload_2
	putfield	Field result$1:Lscala/concurrent/SyncVar;
	aload_0
	invokespecial	Method java/lang/Object."<init>":()V
	aload_0
	invokestatic	Method scala/Function0$class.$init$:(Lscala/Function0;)V
	return
  Labels:
  LocalVariableTable: 
   Start  Length  Slot  Name   Signature
   0      14      0    this       Lscala/concurrent/ThreadRunner$$anonfun$submit$1;
   0      14      1    $outer       Lscala/concurrent/ThreadRunner;


public final java.lang.Object apply();
  Signature: ()Ljava/lang/Object;
  Code:
   Stack=2, Locals=1, Args_size=1
	getstatic	Field scala/concurrent/ops$.MODULE$:Lscala/concurrent/ops$;
	aload_0
	getfield	Field result$1:Lscala/concurrent/SyncVar;
	invokevirtual	Method scala/concurrent/SyncVar.get:()Ljava/lang/Object;
	checkcast	class scala/Either
	invokevirtual	Method scala/concurrent/ops$.getOrThrow:(Lscala/Either;)Ljava/lang/Object;
	areturn
  Labels:
  Signature: length = 0x2
   00 35 

public java.lang.String toString();
  Signature: ()Ljava/lang/String;
  Code:
   Stack=1, Locals=1, Args_size=1
	aload_0
	invokestatic	Method scala/Function0$class.toString:(Lscala/Function0;)Ljava/lang/String;
	areturn
  Labels:

}

