Compiled from "ThreadRunner.scala"
public final class scala.concurrent.ThreadRunner$$anon$2 extends java.lang.Object implements java.lang.Runnable
  SourceFile: "ThreadRunner.scala"
  Scala: length = 0x
   
  InnerClass: 
   public final #54= #19 of #53; //$anon$2=class scala/concurrent/ThreadRunner$$anon$2 of class scala/concurrent/ThreadRunner
   public final #55= #34 of #19; //$anonfun$run$2=class scala/concurrent/ThreadRunner$$anon$2$$anonfun$run$2 of class scala/concurrent/ThreadRunner$$anon$2
  minor version: 0
  major version: 49
  Constant pool:
const #1 = Asciz	SourceFile;
const #2 = Asciz	ThreadRunner.scala;
const #3 = Asciz	result$1;
const #4 = Asciz	Lscala/concurrent/SyncVar;;
const #5 = Asciz	task$2;
const #6 = Asciz	Lscala/Function0;;
const #7 = Asciz	$outer;
const #8 = Asciz	Lscala/concurrent/ThreadRunner;;
const #9 = Asciz	<init>;
const #10 = Asciz	(Lscala/concurrent/ThreadRunner;Lscala/Function0;Lscala/concurrent/SyncVar;)V;
const #11 = Asciz	Code;
const #12 = Asciz	LineNumberTable;
const #13 = Asciz	java/lang/NullPointerException;
const #14 = class	#13;	//  java/lang/NullPointerException
const #15 = Asciz	()V;
const #16 = NameAndType	#9:#15;//  "<init>":()V
const #17 = Method	#14.#16;	//  java/lang/NullPointerException."<init>":()V
const #18 = Asciz	scala/concurrent/ThreadRunner$$anon$2;
const #19 = class	#18;	//  scala/concurrent/ThreadRunner$$anon$2
const #20 = NameAndType	#7:#8;//  $outer:Lscala/concurrent/ThreadRunner;
const #21 = Field	#19.#20;	//  scala/concurrent/ThreadRunner$$anon$2.$outer:Lscala/concurrent/ThreadRunner;
const #22 = NameAndType	#5:#6;//  task$2:Lscala/Function0;
const #23 = Field	#19.#22;	//  scala/concurrent/ThreadRunner$$anon$2.task$2:Lscala/Function0;
const #24 = NameAndType	#3:#4;//  result$1:Lscala/concurrent/SyncVar;
const #25 = Field	#19.#24;	//  scala/concurrent/ThreadRunner$$anon$2.result$1:Lscala/concurrent/SyncVar;
const #26 = Asciz	java/lang/Object;
const #27 = class	#26;	//  java/lang/Object
const #28 = Method	#27.#16;	//  java/lang/Object."<init>":()V
const #29 = Asciz	this;
const #30 = Asciz	Lscala/concurrent/ThreadRunner$$anon$2;;
const #31 = Asciz	LocalVariableTable;
const #32 = Asciz	run;
const #33 = Asciz	scala/concurrent/ThreadRunner$$anon$2$$anonfun$run$2;
const #34 = class	#33;	//  scala/concurrent/ThreadRunner$$anon$2$$anonfun$run$2
const #35 = Asciz	(Lscala/concurrent/ThreadRunner$$anon$2;)V;
const #36 = NameAndType	#9:#35;//  "<init>":(Lscala/concurrent/ThreadRunner$$anon$2;)V
const #37 = Method	#34.#36;	//  scala/concurrent/ThreadRunner$$anon$2$$anonfun$run$2."<init>":(Lscala/concurrent/ThreadRunner$$anon$2;)V
const #38 = Asciz	scala/concurrent/TaskRunner;
const #39 = class	#38;	//  scala/concurrent/TaskRunner
const #40 = Asciz	tryCatch;
const #41 = Asciz	(Lscala/Function0;)Lscala/Either;;
const #42 = NameAndType	#40:#41;//  tryCatch:(Lscala/Function0;)Lscala/Either;
const #43 = InterfaceMethod	#39.#42;	//  scala/concurrent/TaskRunner.tryCatch:(Lscala/Function0;)Lscala/Either;
const #44 = Asciz	scala/concurrent/SyncVar;
const #45 = class	#44;	//  scala/concurrent/SyncVar
const #46 = Asciz	set;
const #47 = Asciz	(Ljava/lang/Object;)V;
const #48 = NameAndType	#46:#47;//  set:(Ljava/lang/Object;)V
const #49 = Method	#45.#48;	//  scala/concurrent/SyncVar.set:(Ljava/lang/Object;)V
const #50 = Asciz	Scala;
const #51 = Asciz	InnerClasses;
const #52 = Asciz	scala/concurrent/ThreadRunner;
const #53 = class	#52;	//  scala/concurrent/ThreadRunner
const #54 = Asciz	$anon$2;
const #55 = Asciz	$anonfun$run$2;
const #56 = Asciz	java/lang/Runnable;
const #57 = class	#56;	//  java/lang/Runnable

{
public final scala.Function0 task$2;

public scala.concurrent.ThreadRunner$$anon$2(scala.concurrent.ThreadRunner, scala.Function0, scala.concurrent.SyncVar);
  Code:
   Stack=2, Locals=4, Args_size=4
   0:	aload_1
   1:	ifnonnull	12
   4:	new	#14; //class java/lang/NullPointerException
   7:	dup
   8:	invokespecial	#17; //Method java/lang/NullPointerException."<init>":()V
   11:	athrow
   12:	aload_0
   13:	aload_1
   14:	putfield	#21; //Field $outer:Lscala/concurrent/ThreadRunner;
   17:	aload_0
   18:	aload_2
   19:	putfield	#23; //Field task$2:Lscala/Function0;
   22:	aload_0
   23:	aload_3
   24:	putfield	#25; //Field result$1:Lscala/concurrent/SyncVar;
   27:	aload_0
   28:	invokespecial	#28; //Method java/lang/Object."<init>":()V
   31:	return
  LineNumberTable: 
   line 37: 0

  LocalVariableTable: 
   Start  Length  Slot  Name   Signature
   0      32      0    this       Lscala/concurrent/ThreadRunner$$anon$2;
   0      32      1    $outer       Lscala/concurrent/ThreadRunner;


public void run();
  Code:
   Stack=5, Locals=1, Args_size=1
   0:	aload_0
   1:	getfield	#25; //Field result$1:Lscala/concurrent/SyncVar;
   4:	aload_0
   5:	getfield	#21; //Field $outer:Lscala/concurrent/ThreadRunner;
   8:	new	#34; //class scala/concurrent/ThreadRunner$$anon$2$$anonfun$run$2
   11:	dup
   12:	aload_0
   13:	invokespecial	#37; //Method scala/concurrent/ThreadRunner$$anon$2$$anonfun$run$2."<init>":(Lscala/concurrent/ThreadRunner$$anon$2;)V
   16:	invokeinterface	#43,  2; //InterfaceMethod scala/concurrent/TaskRunner.tryCatch:(Lscala/Function0;)Lscala/Either;
   21:	invokevirtual	#49; //Method scala/concurrent/SyncVar.set:(Ljava/lang/Object;)V
   24:	return
  LineNumberTable: 
   line 38: 0


}

