Compiled from "ThreadPoolRunner.scala"
public final class scala.concurrent.ThreadPoolRunner$$anonfun$futureAsFunction$1 extends java.lang.Object implements scala.Function0,scala.ScalaObject,java.io.Serializable
  SourceFile: "ThreadPoolRunner.scala"
  Scala: length = 0x
   
  InnerClass: 
   public final #52= #9 of #51; //$anonfun$futureAsFunction$1=class scala/concurrent/ThreadPoolRunner$$anonfun$futureAsFunction$1 of class scala/concurrent/ThreadPoolRunner
  minor version: 0
  major version: 49
  Constant pool:
const #1 = Asciz	SourceFile;
const #2 = Asciz	ThreadPoolRunner.scala;
const #3 = Asciz	<clinit>;
const #4 = Asciz	()V;
const #5 = Asciz	Code;
const #6 = Asciz	serialVersionUID;
const #7 = Asciz	J;
const #8 = Asciz	scala/concurrent/ThreadPoolRunner$$anonfun$futureAsFunction$1;
const #9 = class	#8;	//  scala/concurrent/ThreadPoolRunner$$anonfun$futureAsFunction$1
const #10 = NameAndType	#6:#7;//  serialVersionUID:J
const #11 = Field	#9.#10;	//  scala/concurrent/ThreadPoolRunner$$anonfun$futureAsFunction$1.serialVersionUID:J
const #12 = Asciz	x$1;
const #13 = Asciz	Ljava/util/concurrent/Future;;
const #14 = Asciz	<init>;
const #15 = Asciz	(Lscala/concurrent/ThreadPoolRunner;Ljava/util/concurrent/Future;)V;
const #16 = Asciz	LineNumberTable;
const #17 = NameAndType	#12:#13;//  x$1:Ljava/util/concurrent/Future;
const #18 = Field	#9.#17;	//  scala/concurrent/ThreadPoolRunner$$anonfun$futureAsFunction$1.x$1:Ljava/util/concurrent/Future;
const #19 = Asciz	java/lang/Object;
const #20 = class	#19;	//  java/lang/Object
const #21 = NameAndType	#14:#4;//  "<init>":()V
const #22 = Method	#20.#21;	//  java/lang/Object."<init>":()V
const #23 = Asciz	scala/Function0$class;
const #24 = class	#23;	//  scala/Function0$class
const #25 = Asciz	$init$;
const #26 = Asciz	(Lscala/Function0;)V;
const #27 = NameAndType	#25:#26;//  $init$:(Lscala/Function0;)V
const #28 = Method	#24.#27;	//  scala/Function0$class.$init$:(Lscala/Function0;)V
const #29 = Asciz	this;
const #30 = Asciz	Lscala/concurrent/ThreadPoolRunner$$anonfun$futureAsFunction$1;;
const #31 = Asciz	$outer;
const #32 = Asciz	Lscala/concurrent/ThreadPoolRunner;;
const #33 = Asciz	LocalVariableTable;
const #34 = Asciz	apply;
const #35 = Asciz	()Ljava/lang/Object;;
const #36 = Asciz	java/util/concurrent/Future;
const #37 = class	#36;	//  java/util/concurrent/Future
const #38 = Asciz	get;
const #39 = NameAndType	#38:#35;//  get:()Ljava/lang/Object;
const #40 = InterfaceMethod	#37.#39;	//  java/util/concurrent/Future.get:()Ljava/lang/Object;
const #41 = Asciz	()TS;;
const #42 = Asciz	Signature;
const #43 = Asciz	toString;
const #44 = Asciz	()Ljava/lang/String;;
const #45 = Asciz	(Lscala/Function0;)Ljava/lang/String;;
const #46 = NameAndType	#43:#45;//  toString:(Lscala/Function0;)Ljava/lang/String;
const #47 = Method	#24.#46;	//  scala/Function0$class.toString:(Lscala/Function0;)Ljava/lang/String;
const #48 = Asciz	Scala;
const #49 = Asciz	InnerClasses;
const #50 = Asciz	scala/concurrent/ThreadPoolRunner;
const #51 = class	#50;	//  scala/concurrent/ThreadPoolRunner
const #52 = Asciz	$anonfun$futureAsFunction$1;
const #53 = Asciz	scala/Function0;
const #54 = class	#53;	//  scala/Function0
const #55 = Asciz	scala/ScalaObject;
const #56 = class	#55;	//  scala/ScalaObject
const #57 = Asciz	java/io/Serializable;
const #58 = class	#57;	//  java/io/Serializable

{
public static final long serialVersionUID;

public static {};
  Code:
   Stack=2, Locals=0, Args_size=0
   0:	lconst_0
   1:	putstatic	#11; //Field serialVersionUID:J
   4:	return

public scala.concurrent.ThreadPoolRunner$$anonfun$futureAsFunction$1(scala.concurrent.ThreadPoolRunner, java.util.concurrent.Future);
  Code:
   Stack=2, Locals=3, Args_size=3
   0:	aload_0
   1:	aload_2
   2:	putfield	#18; //Field x$1:Ljava/util/concurrent/Future;
   5:	aload_0
   6:	invokespecial	#22; //Method java/lang/Object."<init>":()V
   9:	aload_0
   10:	invokestatic	#28; //Method scala/Function0$class.$init$:(Lscala/Function0;)V
   13:	return
  LineNumberTable: 
   line 36: 0

  LocalVariableTable: 
   Start  Length  Slot  Name   Signature
   0      14      0    this       Lscala/concurrent/ThreadPoolRunner$$anonfun$futureAsFunction$1;
   0      14      1    $outer       Lscala/concurrent/ThreadPoolRunner;


public final java.lang.Object apply();
  Code:
   Stack=1, Locals=1, Args_size=1
   0:	aload_0
   1:	getfield	#18; //Field x$1:Ljava/util/concurrent/Future;
   4:	invokeinterface	#40,  1; //InterfaceMethod java/util/concurrent/Future.get:()Ljava/lang/Object;
   9:	areturn
  LineNumberTable: 
   line 36: 0

  Signature: length = 0x2
   00 29 

public java.lang.String toString();
  Code:
   Stack=1, Locals=1, Args_size=1
   0:	aload_0
   1:	invokestatic	#47; //Method scala/Function0$class.toString:(Lscala/Function0;)Ljava/lang/String;
   4:	areturn
  LineNumberTable: 
   line 36: 0


}

