Compiled from "ThreadPoolRunner.scala"
public abstract class scala.concurrent.ThreadPoolRunner$class extends java.lang.Object
  SourceFile: "ThreadPoolRunner.scala"
  Scala: length = 0x
   
  InnerClass: 
   public RunCallable=class scala/concurrent/ThreadPoolRunner$RunCallable of class scala/concurrent/ThreadPoolRunner
   public final $anonfun$futureAsFunction$1=class scala/concurrent/ThreadPoolRunner$$anonfun$futureAsFunction$1 of class scala/concurrent/ThreadPoolRunner
  minor version: 0
  major version: 49
  Constant pool:
Asciz	SourceFile;
Asciz	ThreadPoolRunner.scala;
Asciz	functionAsTask;
Asciz	(Lscala/concurrent/ThreadPoolRunner;Lscala/Function0;)Ljava/util/concurrent/Callable;;
Asciz	Code;
Asciz	scala/concurrent/ThreadPoolRunner$RunCallable;
class	scala/concurrent/ThreadPoolRunner$RunCallable
Asciz	LineNumberTable;
Asciz	<init>;
Asciz	(Lscala/concurrent/ThreadPoolRunner;Lscala/Function0;)V;
NameAndType	"<init>":(Lscala/concurrent/ThreadPoolRunner;Lscala/Function0;)V
Method	scala/concurrent/ThreadPoolRunner$RunCallable."<init>":(Lscala/concurrent/ThreadPoolRunner;Lscala/Function0;)V
Asciz	$this;
Asciz	Lscala/concurrent/ThreadPoolRunner;;
Asciz	fun;
Asciz	Lscala/Function0;;
Asciz	LocalVariableTable;
Asciz	futureAsFunction;
Asciz	(Lscala/concurrent/ThreadPoolRunner;Ljava/util/concurrent/Future;)Lscala/Function0;;
Asciz	scala/concurrent/ThreadPoolRunner$$anonfun$futureAsFunction$1;
class	scala/concurrent/ThreadPoolRunner$$anonfun$futureAsFunction$1
Asciz	(Lscala/concurrent/ThreadPoolRunner;Ljava/util/concurrent/Future;)V;
NameAndType	"<init>":(Lscala/concurrent/ThreadPoolRunner;Ljava/util/concurrent/Future;)V
Method	scala/concurrent/ThreadPoolRunner$$anonfun$futureAsFunction$1."<init>":(Lscala/concurrent/ThreadPoolRunner;Ljava/util/concurrent/Future;)V
Asciz	x$1;
Asciz	Ljava/util/concurrent/Future;;
Asciz	submit;
Asciz	(Lscala/concurrent/ThreadPoolRunner;Ljava/util/concurrent/Callable;)Ljava/util/concurrent/Future;;
Asciz	scala/concurrent/ThreadPoolRunner;
class	scala/concurrent/ThreadPoolRunner
Asciz	executor;
Asciz	()Ljava/util/concurrent/ExecutorService;;
NameAndType	executor:()Ljava/util/concurrent/ExecutorService;
InterfaceMethod	scala/concurrent/ThreadPoolRunner.executor:()Ljava/util/concurrent/ExecutorService;
Asciz	java/util/concurrent/ExecutorService;
class	java/util/concurrent/ExecutorService
Asciz	(Ljava/util/concurrent/Callable;)Ljava/util/concurrent/Future;;
NameAndType	submit:(Ljava/util/concurrent/Callable;)Ljava/util/concurrent/Future;
InterfaceMethod	java/util/concurrent/ExecutorService.submit:(Ljava/util/concurrent/Callable;)Ljava/util/concurrent/Future;
Asciz	task;
Asciz	Ljava/util/concurrent/Callable;;
Asciz	execute;
Asciz	(Lscala/concurrent/ThreadPoolRunner;Ljava/util/concurrent/Callable;)V;
Asciz	java/lang/Runnable;
class	java/lang/Runnable
Asciz	java/util/concurrent/Executor;
class	java/util/concurrent/Executor
Asciz	(Ljava/lang/Runnable;)V;
NameAndType	execute:(Ljava/lang/Runnable;)V
InterfaceMethod	java/util/concurrent/Executor.execute:(Ljava/lang/Runnable;)V
Asciz	managedBlock;
Asciz	(Lscala/concurrent/ThreadPoolRunner;Lscala/concurrent/ManagedBlocker;)V;
Asciz	scala/concurrent/ManagedBlocker;
class	scala/concurrent/ManagedBlocker
Asciz	block;
Asciz	()Z;
NameAndType	block:()Z
InterfaceMethod	scala/concurrent/ManagedBlocker.block:()Z
Asciz	blocker;
Asciz	Lscala/concurrent/ManagedBlocker;;
Asciz	$init$;
Asciz	(Lscala/concurrent/ThreadPoolRunner;)V;
Asciz	Scala;
Asciz	InnerClasses;
Asciz	RunCallable;
Asciz	$anonfun$futureAsFunction$1;
Asciz	scala/concurrent/ThreadPoolRunner$class;
class	scala/concurrent/ThreadPoolRunner$class
Asciz	java/lang/Object;
class	java/lang/Object

{
public static java.util.concurrent.Callable functionAsTask(scala.concurrent.ThreadPoolRunner, scala.Function0);
  Signature: (Lscala/concurrent/ThreadPoolRunner;Lscala/Function0;)Ljava/util/concurrent/Callable;
  Code:
   Stack=4, Locals=2, Args_size=2
	new	class scala/concurrent/ThreadPoolRunner$RunCallable
	dup
	aload_0
	aload_1
	invokespecial	Method scala/concurrent/ThreadPoolRunner$RunCallable."<init>":(Lscala/concurrent/ThreadPoolRunner;Lscala/Function0;)V
	areturn
  Labels:
  LocalVariableTable: 
   Start  Length  Slot  Name   Signature
   0      10      0    $this       Lscala/concurrent/ThreadPoolRunner;
   0      10      1    fun       Lscala/Function0;


public static scala.Function0 futureAsFunction(scala.concurrent.ThreadPoolRunner, java.util.concurrent.Future);
  Signature: (Lscala/concurrent/ThreadPoolRunner;Ljava/util/concurrent/Future;)Lscala/Function0;
  Code:
   Stack=4, Locals=2, Args_size=2
	new	class scala/concurrent/ThreadPoolRunner$$anonfun$futureAsFunction$1
	dup
	aload_0
	aload_1
	invokespecial	Method scala/concurrent/ThreadPoolRunner$$anonfun$futureAsFunction$1."<init>":(Lscala/concurrent/ThreadPoolRunner;Ljava/util/concurrent/Future;)V
	areturn
  Labels:
  LocalVariableTable: 
   Start  Length  Slot  Name   Signature
   0      10      0    $this       Lscala/concurrent/ThreadPoolRunner;
   0      10      1    x$1       Ljava/util/concurrent/Future;


public static java.util.concurrent.Future submit(scala.concurrent.ThreadPoolRunner, java.util.concurrent.Callable);
  Signature: (Lscala/concurrent/ThreadPoolRunner;Ljava/util/concurrent/Callable;)Ljava/util/concurrent/Future;
  Code:
   Stack=2, Locals=2, Args_size=2
	aload_0
	invokeinterface	InterfaceMethod scala/concurrent/ThreadPoolRunner.executor:()Ljava/util/concurrent/ExecutorService;
	aload_1
	invokeinterface	InterfaceMethod java/util/concurrent/ExecutorService.submit:(Ljava/util/concurrent/Callable;)Ljava/util/concurrent/Future;
	areturn
  Labels:
  LocalVariableTable: 
   Start  Length  Slot  Name   Signature
   0      13      0    $this       Lscala/concurrent/ThreadPoolRunner;
   0      13      1    task       Ljava/util/concurrent/Callable;


public static void execute(scala.concurrent.ThreadPoolRunner, java.util.concurrent.Callable);
  Signature: (Lscala/concurrent/ThreadPoolRunner;Ljava/util/concurrent/Callable;)V
  Code:
   Stack=2, Locals=2, Args_size=2
	aload_0
	invokeinterface	InterfaceMethod scala/concurrent/ThreadPoolRunner.executor:()Ljava/util/concurrent/ExecutorService;
	aload_1
	checkcast	class java/lang/Runnable
	invokeinterface	InterfaceMethod java/util/concurrent/Executor.execute:(Ljava/lang/Runnable;)V
	return
  Labels:
  LocalVariableTable: 
   Start  Length  Slot  Name   Signature
   0      16      0    $this       Lscala/concurrent/ThreadPoolRunner;
   0      16      1    task       Ljava/util/concurrent/Callable;


public static void managedBlock(scala.concurrent.ThreadPoolRunner, scala.concurrent.ManagedBlocker);
  Signature: (Lscala/concurrent/ThreadPoolRunner;Lscala/concurrent/ManagedBlocker;)V
  Code:
   Stack=1, Locals=2, Args_size=2
	aload_1
	invokeinterface	InterfaceMethod scala/concurrent/ManagedBlocker.block:()Z
	pop
	return
  Labels:
  LocalVariableTable: 
   Start  Length  Slot  Name   Signature
   0      8      0    $this       Lscala/concurrent/ThreadPoolRunner;
   0      8      1    blocker       Lscala/concurrent/ManagedBlocker;


public static void $init$(scala.concurrent.ThreadPoolRunner);
  Signature: (Lscala/concurrent/ThreadPoolRunner;)V
  Code:
   Stack=0, Locals=1, Args_size=1
	return
  Labels:
  LocalVariableTable: 
   Start  Length  Slot  Name   Signature
   0      1      0    $this       Lscala/concurrent/ThreadPoolRunner;


}

