Compiled from "ThreadRunner.scala"
public class scala.concurrent.ThreadRunner extends java.lang.Object implements scala.concurrent.FutureTaskRunner,scala.ScalaObject
  SourceFile: "ThreadRunner.scala"
  ScalaSig: length = 0x289
   05 00 69 06 08 01 02 FFFFFF84 FFFFFF80 FFFFFF80 FFFFFF80 00 07 02 0C 54
   68 72 65 61 64 52 75 6E 6E 65 72 0A 02 03 04 01
   0A 63 6F 6E 63 75 72 72 65 6E 74 0A 01 05 01 05
   73 63 61 6C 61 03 00 13 04 00 08 10 14 10 02 09
   0E 0D 01 0A 0A 02 0B 0C 01 04 6C 61 6E 67 0A 01
   0D 01 04 6A 61 76 61 09 02 0F 0A 02 06 4F 62 6A
   65 63 74 10 02 11 12 0D 01 02 09 02 13 02 02 10
   46 75 74 75 72 65 54 61 73 6B 52 75 6E 6E 65 72
   10 02 15 16 0D 01 04 09 02 17 04 02 0B 53 63 61
   6C 61 4F 62 6A 65 63 74 08 05 19 00 FFFFFF84 00 1A 01
   06 3C 69 6E 69 74 3E 14 01 1B 10 02 11 00 05 04
   1D 00 00 1E 02 04 54 61 73 6B 15 02 1F 24 10 03
   15 20 22 09 02 21 04 02 09 46 75 6E 63 74 69 6F
   6E 30 10 02 23 24 0C 00 04 08 25 1C FFFFFF84 FFFFFF80 FFFFFF80 FFFFFFC2
   00 26 02 01 54 11 02 27 2A 10 02 15 28 09 02 29
   04 02 07 4E 6F 74 68 69 6E 67 10 02 15 2B 09 02
   2C 04 02 03 41 6E 79 05 04 2E 00 00 2F 02 06 46
   75 74 75 72 65 15 02 30 32 10 03 15 20 31 10 02
   23 32 04 08 25 2D FFFFFF84 FFFFFF80 FFFFFF80 FFFFFFC2 00 26 08 05 34 00
   FFFFFF84 01 35 01 0E 66 75 6E 63 74 69 6F 6E 41 73 54
   61 73 6B 15 02 36 3A 14 02 37 3C 10 03 38 1C 39
   0D 01 00 10 02 23 3A 04 08 3B 33 FFFFFF84 FFFFFF80 FFFFFF80 FFFFFFC2 00
   26 02 01 53 08 05 3D 33 FFFFFFC0 00 3E 01 03 66 75 6E
   10 03 15 20 39 08 05 40 00 FFFFFF84 01 41 01 10 66 75
   74 75 72 65 41 73 46 75 6E 63 74 69 6F 6E 15 02
   42 45 14 02 43 46 10 03 15 20 44 10 02 23 45 04
   08 3B 3F FFFFFF84 FFFFFF80 FFFFFF80 FFFFFFC2 00 26 08 05 47 3F FFFFFFC0 00 48
   01 01 78 10 03 38 2D 44 08 05 4A 00 FFFFFF84 00 4B 01
   07 65 78 65 63 75 74 65 15 02 4C 54 14 02 4D 50
   10 02 15 4E 09 02 4F 04 02 04 55 6E 69 74 08 05
   51 49 FFFFFFC0 00 52 01 04 74 61 73 6B 10 03 38 1C 53
   10 02 23 54 04 08 3B 49 FFFFFF84 FFFFFF80 FFFFFF80 FFFFFFC2 00 26 08 05
   56 00 FFFFFF84 00 57 01 06 73 75 62 6D 69 74 15 02 58
   5B 14 02 59 5C 10 03 38 2D 5A 10 02 23 5B 04 08
   3B 55 FFFFFF84 FFFFFF80 FFFFFF80 FFFFFFC2 00 26 08 05 51 55 FFFFFFC0 00 5D 10
   03 38 1C 5A 08 05 5F 00 FFFFFF84 00 60 01 0C 6D 61 6E
   61 67 65 64 42 6C 6F 63 6B 14 02 4D 61 08 05 62
   5E FFFFFFC0 00 63 01 07 62 6C 6F 63 6B 65 72 10 02 11
   64 09 02 65 02 02 0E 4D 61 6E 61 67 65 64 42 6C
   6F 63 6B 65 72 08 05 67 00 FFFFFF84 00 68 01 08 73 68
   75 74 64 6F 77 6E 14 01 4D 
  InnerClass: 
   public final $anon$1=class scala/concurrent/ThreadRunner$$anon$1 of class scala/concurrent/ThreadRunner
   public final $anon$2=class scala/concurrent/ThreadRunner$$anon$2 of class scala/concurrent/ThreadRunner
   public final $anonfun$submit$1=class scala/concurrent/ThreadRunner$$anonfun$submit$1 of class scala/concurrent/ThreadRunner
  minor version: 0
  major version: 49
  Constant pool:
Asciz	SourceFile;
Asciz	ThreadRunner.scala;
Asciz	<init>;
Asciz	()V;
Asciz	Code;
Asciz	LineNumberTable;
Asciz	java/lang/Object;
class	java/lang/Object
NameAndType	"<init>":()V
Method	java/lang/Object."<init>":()V
Asciz	scala/concurrent/TaskRunner$class;
class	scala/concurrent/TaskRunner$class
Asciz	$init$;
Asciz	(Lscala/concurrent/TaskRunner;)V;
NameAndType	$init$:(Lscala/concurrent/TaskRunner;)V
Method	scala/concurrent/TaskRunner$class.$init$:(Lscala/concurrent/TaskRunner;)V
Asciz	functionAsTask;
Asciz	(Lscala/Function0;)Ljava/lang/Object;;
Asciz	scala/concurrent/ThreadRunner;
class	scala/concurrent/ThreadRunner
Asciz	(Lscala/Function0;)Lscala/Function0;;
NameAndType	functionAsTask:(Lscala/Function0;)Lscala/Function0;
Method	scala/concurrent/ThreadRunner.functionAsTask:(Lscala/Function0;)Lscala/Function0;
Asciz	this;
Asciz	Lscala/concurrent/ThreadRunner;;
Asciz	fun;
Asciz	Lscala/Function0;;
Asciz	LocalVariableTable;
Asciz	futureAsFunction;
Asciz	(Ljava/lang/Object;)Lscala/Function0;;
Asciz	scala/Function0;
class	scala/Function0
NameAndType	futureAsFunction:(Lscala/Function0;)Lscala/Function0;
Method	scala/concurrent/ThreadRunner.futureAsFunction:(Lscala/Function0;)Lscala/Function0;
Asciz	x;
Asciz	Ljava/lang/Object;;
Asciz	execute;
Asciz	(Ljava/lang/Object;)V;
Asciz	(Lscala/Function0;)V;
NameAndType	execute:(Lscala/Function0;)V
Method	scala/concurrent/ThreadRunner.execute:(Lscala/Function0;)V
Asciz	task;
Asciz	submit;
Asciz	(Ljava/lang/Object;)Ljava/lang/Object;;
NameAndType	submit:(Lscala/Function0;)Lscala/Function0;
Method	scala/concurrent/ThreadRunner.submit:(Lscala/Function0;)Lscala/Function0;
Asciz	shutdown;
Asciz	managedBlock;
Asciz	(Lscala/concurrent/ManagedBlocker;)V;
Asciz	scala/concurrent/ManagedBlocker;
class	scala/concurrent/ManagedBlocker
Asciz	block;
Asciz	()Z;
NameAndType	block:()Z
InterfaceMethod	scala/concurrent/ManagedBlocker.block:()Z
Asciz	blocker;
Asciz	Lscala/concurrent/ManagedBlocker;;
Asciz	scala/concurrent/SyncVar;
class	scala/concurrent/SyncVar
Method	scala/concurrent/SyncVar."<init>":()V
Asciz	scala/concurrent/ThreadRunner$$anon$2;
class	scala/concurrent/ThreadRunner$$anon$2
Asciz	(Lscala/concurrent/ThreadRunner;Lscala/Function0;Lscala/concurrent/SyncVar;)V;
NameAndType	"<init>":(Lscala/concurrent/ThreadRunner;Lscala/Function0;Lscala/concurrent/SyncVar;)V
Method	scala/concurrent/ThreadRunner$$anon$2."<init>":(Lscala/concurrent/ThreadRunner;Lscala/Function0;Lscala/concurrent/SyncVar;)V
Asciz	java/lang/Thread;
class	java/lang/Thread
Asciz	java/lang/Runnable;
class	java/lang/Runnable
Asciz	(Ljava/lang/Runnable;)V;
NameAndType	"<init>":(Ljava/lang/Runnable;)V
Method	java/lang/Thread."<init>":(Ljava/lang/Runnable;)V
Asciz	start;
NameAndType	start:()V
Method	java/lang/Thread.start:()V
Asciz	scala/concurrent/ThreadRunner$$anonfun$submit$1;
class	scala/concurrent/ThreadRunner$$anonfun$submit$1
Asciz	(Lscala/concurrent/ThreadRunner;Lscala/concurrent/SyncVar;)V;
NameAndType	"<init>":(Lscala/concurrent/ThreadRunner;Lscala/concurrent/SyncVar;)V
Method	scala/concurrent/ThreadRunner$$anonfun$submit$1."<init>":(Lscala/concurrent/ThreadRunner;Lscala/concurrent/SyncVar;)V
Asciz	task$2;
Asciz	result$1;
Asciz	Lscala/concurrent/SyncVar;;
Asciz	runnable;
Asciz	<S:Ljava/lang/Object;>(Lscala/Function0<TS;>;)Lscala/Function0<TS;>;;
Asciz	Signature;
Asciz	scala/concurrent/ThreadRunner$$anon$1;
class	scala/concurrent/ThreadRunner$$anon$1
Asciz	(Lscala/concurrent/ThreadRunner;Lscala/Function0;)V;
NameAndType	"<init>":(Lscala/concurrent/ThreadRunner;Lscala/Function0;)V
Method	scala/concurrent/ThreadRunner$$anon$1."<init>":(Lscala/concurrent/ThreadRunner;Lscala/Function0;)V
Asciz	task$1;
Asciz	<S:Ljava/lang/Object;>(Lscala/Function0<TS;>;)V;
Asciz	tryCatch;
Asciz	(Lscala/Function0;)Lscala/Either;;
Asciz	(Lscala/concurrent/TaskRunner;Lscala/Function0;)Lscala/Either;;
NameAndType	tryCatch:(Lscala/concurrent/TaskRunner;Lscala/Function0;)Lscala/Either;
Method	scala/concurrent/TaskRunner$class.tryCatch:(Lscala/concurrent/TaskRunner;Lscala/Function0;)Lscala/Either;
Asciz	body;
Asciz	ScalaSig;
Asciz	InnerClasses;
Asciz	$anon$1;
Asciz	$anon$2;
Asciz	$anonfun$submit$1;
Asciz	scala/concurrent/FutureTaskRunner;
class	scala/concurrent/FutureTaskRunner
Asciz	scala/ScalaObject;
class	scala/ScalaObject

{
public scala.concurrent.ThreadRunner();
  Signature: ()V
  Code:
   Stack=1, Locals=1, Args_size=1
	aload_0
	invokespecial	Method java/lang/Object."<init>":()V
	aload_0
	invokestatic	Method scala/concurrent/TaskRunner$class.$init$:(Lscala/concurrent/TaskRunner;)V
	return
  Labels:

public java.lang.Object functionAsTask(scala.Function0);
  Signature: (Lscala/Function0;)Ljava/lang/Object;
  Code:
   Stack=2, Locals=2, Args_size=2
	aload_0
	aload_1
	invokevirtual	Method functionAsTask:(Lscala/Function0;)Lscala/Function0;
	areturn
  Labels:
  LocalVariableTable: 
   Start  Length  Slot  Name   Signature
   0      6      0    this       Lscala/concurrent/ThreadRunner;
   0      6      1    fun       Lscala/Function0;


public scala.Function0 futureAsFunction(java.lang.Object);
  Signature: (Ljava/lang/Object;)Lscala/Function0;
  Code:
   Stack=2, Locals=2, Args_size=2
	aload_0
	aload_1
	checkcast	class scala/Function0
	invokevirtual	Method futureAsFunction:(Lscala/Function0;)Lscala/Function0;
	areturn
  Labels:
  LocalVariableTable: 
   Start  Length  Slot  Name   Signature
   0      9      0    this       Lscala/concurrent/ThreadRunner;
   0      9      1    x       Ljava/lang/Object;


public void execute(java.lang.Object);
  Signature: (Ljava/lang/Object;)V
  Code:
   Stack=2, Locals=2, Args_size=2
	aload_0
	aload_1
	checkcast	class scala/Function0
	invokevirtual	Method execute:(Lscala/Function0;)V
	return
  Labels:
  LocalVariableTable: 
   Start  Length  Slot  Name   Signature
   0      9      0    this       Lscala/concurrent/ThreadRunner;
   0      9      1    task       Ljava/lang/Object;


public java.lang.Object submit(java.lang.Object);
  Signature: (Ljava/lang/Object;)Ljava/lang/Object;
  Code:
   Stack=2, Locals=2, Args_size=2
	aload_0
	aload_1
	checkcast	class scala/Function0
	invokevirtual	Method submit:(Lscala/Function0;)Lscala/Function0;
	areturn
  Labels:
  LocalVariableTable: 
   Start  Length  Slot  Name   Signature
   0      9      0    this       Lscala/concurrent/ThreadRunner;
   0      9      1    task       Ljava/lang/Object;


public void shutdown();
  Signature: ()V
  Code:
   Stack=0, Locals=1, Args_size=1
	return
  Labels:

public void managedBlock(scala.concurrent.ManagedBlocker);
  Signature: (Lscala/concurrent/ManagedBlocker;)V
  Code:
   Stack=1, Locals=2, Args_size=2
	aload_1
	invokeinterface	InterfaceMethod scala/concurrent/ManagedBlocker.block:()Z
	pop
	return
  Labels:
  LocalVariableTable: 
   Start  Length  Slot  Name   Signature
   0      8      0    this       Lscala/concurrent/ThreadRunner;
   0      8      1    blocker       Lscala/concurrent/ManagedBlocker;


public scala.Function0 submit(scala.Function0);
  Signature: (Lscala/Function0;)Lscala/Function0;
  Code:
   Stack=5, Locals=4, Args_size=2
	new	class scala/concurrent/SyncVar
	dup
	invokespecial	Method scala/concurrent/SyncVar."<init>":()V
	astore_2
	new	class scala/concurrent/ThreadRunner$$anon$2
	dup
	aload_0
	aload_1
	aload_2
	invokespecial	Method scala/concurrent/ThreadRunner$$anon$2."<init>":(Lscala/concurrent/ThreadRunner;Lscala/Function0;Lscala/concurrent/SyncVar;)V
	astore_3
	new	class java/lang/Thread
	dup
	aload_3
	checkcast	class java/lang/Runnable
	invokespecial	Method java/lang/Thread."<init>":(Ljava/lang/Runnable;)V
	invokevirtual	Method java/lang/Thread.start:()V
	new	class scala/concurrent/ThreadRunner$$anonfun$submit$1
	dup
	aload_0
	aload_2
	invokespecial	Method scala/concurrent/ThreadRunner$$anonfun$submit$1."<init>":(Lscala/concurrent/ThreadRunner;Lscala/concurrent/SyncVar;)V
	areturn
  Labels:
  LocalVariableTable: 
   Start  Length  Slot  Name   Signature
   0      43      0    this       Lscala/concurrent/ThreadRunner;
   0      43      1    task$2       Lscala/Function0;
   8      34      2    result$1       Lscala/concurrent/SyncVar;
   19      23      3    runnable       Ljava/lang/Object;

  Signature: length = 0x2
   00 55 

public void execute(scala.Function0);
  Signature: (Lscala/Function0;)V
  Code:
   Stack=4, Locals=3, Args_size=2
	new	class scala/concurrent/ThreadRunner$$anon$1
	dup
	aload_0
	aload_1
	invokespecial	Method scala/concurrent/ThreadRunner$$anon$1."<init>":(Lscala/concurrent/ThreadRunner;Lscala/Function0;)V
	astore_2
	new	class java/lang/Thread
	dup
	aload_2
	checkcast	class java/lang/Runnable
	invokespecial	Method java/lang/Thread."<init>":(Ljava/lang/Runnable;)V
	invokevirtual	Method java/lang/Thread.start:()V
	return
  Labels:
  LocalVariableTable: 
   Start  Length  Slot  Name   Signature
   0      25      0    this       Lscala/concurrent/ThreadRunner;
   0      25      1    task$1       Lscala/Function0;
   10      14      2    runnable       Ljava/lang/Object;

  Signature: length = 0x2
   00 5D 

public scala.Function0 futureAsFunction(scala.Function0);
  Signature: (Lscala/Function0;)Lscala/Function0;
  Code:
   Stack=1, Locals=2, Args_size=2
	aload_1
	areturn
  Labels:
  LocalVariableTable: 
   Start  Length  Slot  Name   Signature
   0      2      0    this       Lscala/concurrent/ThreadRunner;
   0      2      1    x       Lscala/Function0;

  Signature: length = 0x2
   00 55 

public scala.Function0 functionAsTask(scala.Function0);
  Signature: (Lscala/Function0;)Lscala/Function0;
  Code:
   Stack=1, Locals=2, Args_size=2
	aload_1
	areturn
  Labels:
  LocalVariableTable: 
   Start  Length  Slot  Name   Signature
   0      2      0    this       Lscala/concurrent/ThreadRunner;
   0      2      1    fun       Lscala/Function0;

  Signature: length = 0x2
   00 55 

public scala.Either tryCatch(scala.Function0);
  Signature: (Lscala/Function0;)Lscala/Either;
  Code:
   Stack=2, Locals=2, Args_size=2
	aload_0
	aload_1
	invokestatic	Method scala/concurrent/TaskRunner$class.tryCatch:(Lscala/concurrent/TaskRunner;Lscala/Function0;)Lscala/Either;
	areturn
  Labels:
  LocalVariableTable: 
   Start  Length  Slot  Name   Signature
   0      6      0    this       Lscala/concurrent/ThreadRunner;
   0      6      1    body       Lscala/Function0;


}

