Compiled from "TIMEOUT.scala"
public final class scala.concurrent.TIMEOUT extends java.lang.Object
  SourceFile: "TIMEOUT.scala"
  ScalaSig: length = 0x3
   05 00 00 
  RuntimeVisibleAnnotations: length = 0xB
   00 01 00 27 00 01 00 28 73 00 29 
  minor version: 0
  major version: 49
  Constant pool:
Asciz	SourceFile;
Asciz	TIMEOUT.scala;
Asciz	productElements;
Asciz	()Lscala/collection/Iterator;;
Asciz	Code;
Asciz	scala/concurrent/TIMEOUT$;
class	scala/concurrent/TIMEOUT$
Asciz	MODULE$;
Asciz	Lscala/concurrent/TIMEOUT$;;
NameAndType	MODULE$:Lscala/concurrent/TIMEOUT$;
Field	scala/concurrent/TIMEOUT$.MODULE$:Lscala/concurrent/TIMEOUT$;
NameAndType	productElements:()Lscala/collection/Iterator;
Method	scala/concurrent/TIMEOUT$.productElements:()Lscala/collection/Iterator;
Asciz	Deprecated;
Asciz	productIterator;
NameAndType	productIterator:()Lscala/collection/Iterator;
Method	scala/concurrent/TIMEOUT$.productIterator:()Lscala/collection/Iterator;
Asciz	productElementName;
Asciz	(I)Ljava/lang/String;;
NameAndType	productElementName:(I)Ljava/lang/String;
Method	scala/concurrent/TIMEOUT$.productElementName:(I)Ljava/lang/String;
Asciz	canEqual;
Asciz	(Ljava/lang/Object;)Z;
NameAndType	canEqual:(Ljava/lang/Object;)Z
Method	scala/concurrent/TIMEOUT$.canEqual:(Ljava/lang/Object;)Z
Asciz	productElement;
Asciz	(I)Ljava/lang/Object;;
NameAndType	productElement:(I)Ljava/lang/Object;
Method	scala/concurrent/TIMEOUT$.productElement:(I)Ljava/lang/Object;
Asciz	productArity;
Asciz	()I;
NameAndType	productArity:()I
Method	scala/concurrent/TIMEOUT$.productArity:()I
Asciz	productPrefix;
Asciz	()Ljava/lang/String;;
NameAndType	productPrefix:()Ljava/lang/String;
Method	scala/concurrent/TIMEOUT$.productPrefix:()Ljava/lang/String;
Asciz	ScalaSig;
Asciz	Lscala/reflect/ScalaSignature;;
Asciz	bytes;
Asciz	\r;Q!\t\tqV%N>+FK\tQ1m8dkJXM;\tQa]2bY\t5\t!A\t#\"!*T#P+RB!1AQBE)qEYtwMCQM^1\nMq!AB(cUG-5\tA!\t\tY1kY1mC>'.Z2u!\t)$\t\t9K]8ek$\"\n\tiAj]&$hF!y\"A\n;p'RN\4\"!\n\rr!AB*ue&tw\r&\t\"'5(o3vGR&/4jqV\t)\t\"*1(o3vGR%/;z+QCA,\taCAAJ]RDBL%\teLaJ|G-^2u2,W.8u)\t4c%!:Lb.\rAKq\n\n\tII\rg.R9vC2$\"OUIBun7fC:DqN>\t\"?-X-3SKN|GN^31A#!!U\tB\"1XM]5bY&TM7f;
Asciz	RuntimeVisibleAnnotations;
Asciz	scala/concurrent/TIMEOUT;
class	scala/concurrent/TIMEOUT
Asciz	java/lang/Object;
class	java/lang/Object

{
public static final scala.collection.Iterator productElements();
  Signature: ()Lscala/collection/Iterator;
  Code:
   Stack=1, Locals=0, Args_size=0
	getstatic	Field scala/concurrent/TIMEOUT$.MODULE$:Lscala/concurrent/TIMEOUT$;
	invokevirtual	Method scala/concurrent/TIMEOUT$.productElements:()Lscala/collection/Iterator;
	areturn
  Labels:
  Deprecated: true

public static final scala.collection.Iterator productIterator();
  Signature: ()Lscala/collection/Iterator;
  Code:
   Stack=1, Locals=0, Args_size=0
	getstatic	Field scala/concurrent/TIMEOUT$.MODULE$:Lscala/concurrent/TIMEOUT$;
	invokevirtual	Method scala/concurrent/TIMEOUT$.productIterator:()Lscala/collection/Iterator;
	areturn
  Labels:

public static final java.lang.String productElementName(int);
  Signature: (I)Ljava/lang/String;
  Code:
   Stack=2, Locals=1, Args_size=1
	getstatic	Field scala/concurrent/TIMEOUT$.MODULE$:Lscala/concurrent/TIMEOUT$;
	iload_0
	invokevirtual	Method scala/concurrent/TIMEOUT$.productElementName:(I)Ljava/lang/String;
	areturn
  Labels:

public static final boolean canEqual(java.lang.Object);
  Signature: (Ljava/lang/Object;)Z
  Code:
   Stack=2, Locals=1, Args_size=1
	getstatic	Field scala/concurrent/TIMEOUT$.MODULE$:Lscala/concurrent/TIMEOUT$;
	aload_0
	invokevirtual	Method scala/concurrent/TIMEOUT$.canEqual:(Ljava/lang/Object;)Z
	ireturn
  Labels:

public static final java.lang.Object productElement(int);
  Signature: (I)Ljava/lang/Object;
  Code:
   Stack=2, Locals=1, Args_size=1
	getstatic	Field scala/concurrent/TIMEOUT$.MODULE$:Lscala/concurrent/TIMEOUT$;
	iload_0
	invokevirtual	Method scala/concurrent/TIMEOUT$.productElement:(I)Ljava/lang/Object;
	areturn
  Labels:

public static final int productArity();
  Signature: ()I
  Code:
   Stack=1, Locals=0, Args_size=0
	getstatic	Field scala/concurrent/TIMEOUT$.MODULE$:Lscala/concurrent/TIMEOUT$;
	invokevirtual	Method scala/concurrent/TIMEOUT$.productArity:()I
	ireturn
  Labels:

public static final java.lang.String productPrefix();
  Signature: ()Ljava/lang/String;
  Code:
   Stack=1, Locals=0, Args_size=0
	getstatic	Field scala/concurrent/TIMEOUT$.MODULE$:Lscala/concurrent/TIMEOUT$;
	invokevirtual	Method scala/concurrent/TIMEOUT$.productPrefix:()Ljava/lang/String;
	areturn
  Labels:

}

