Compiled from "AbstractSyntax.scala"
public abstract class scala.util.parsing.ast.AbstractSyntax$NameElement$class extends java.lang.Object
  SourceFile: "AbstractSyntax.scala"
  Scala: length = 0x
   
  InnerClass: 
   public abstract #43= #13 of #42; //NameElement=class scala/util/parsing/ast/AbstractSyntax$NameElement of class scala/util/parsing/ast/AbstractSyntax
  minor version: 0
  major version: 49
  Constant pool:
const #1 = Asciz	SourceFile;
const #2 = Asciz	AbstractSyntax.scala;
const #3 = Asciz	$init$;
const #4 = Asciz	(Lscala/util/parsing/ast/AbstractSyntax$NameElement;)V;
const #5 = Asciz	Code;
const #6 = Asciz	LineNumberTable;
const #7 = Asciz	$this;
const #8 = Asciz	Lscala/util/parsing/ast/AbstractSyntax$NameElement;;
const #9 = Asciz	LocalVariableTable;
const #10 = Asciz	equals;
const #11 = Asciz	(Lscala/util/parsing/ast/AbstractSyntax$NameElement;Ljava/lang/Object;)Z;
const #12 = Asciz	scala/util/parsing/ast/AbstractSyntax$NameElement;
const #13 = class	#12;	//  scala/util/parsing/ast/AbstractSyntax$NameElement
const #14 = Asciz	scala$util$parsing$ast$AbstractSyntax$NameElement$$$outer;
const #15 = Asciz	()Lscala/util/parsing/ast/AbstractSyntax;;
const #16 = NameAndType	#14:#15;//  scala$util$parsing$ast$AbstractSyntax$NameElement$$$outer:()Lscala/util/parsing/ast/AbstractSyntax;
const #17 = InterfaceMethod	#13.#16;	//  scala/util/parsing/ast/AbstractSyntax$NameElement.scala$util$parsing$ast$AbstractSyntax$NameElement$$$outer:()Lscala/util/parsing/ast/AbstractSyntax;
const #18 = Asciz	name;
const #19 = Asciz	()Ljava/lang/String;;
const #20 = NameAndType	#18:#19;//  name:()Ljava/lang/String;
const #21 = InterfaceMethod	#13.#20;	//  scala/util/parsing/ast/AbstractSyntax$NameElement.name:()Ljava/lang/String;
const #22 = Asciz	java/lang/Object;
const #23 = class	#22;	//  java/lang/Object
const #24 = Asciz	(Ljava/lang/Object;)Z;
const #25 = NameAndType	#10:#24;//  equals:(Ljava/lang/Object;)Z
const #26 = Method	#23.#25;	//  java/lang/Object.equals:(Ljava/lang/Object;)Z
const #27 = Asciz	scala/MatchError;
const #28 = class	#27;	//  scala/MatchError
const #29 = Asciz	toString;
const #30 = NameAndType	#29:#19;//  toString:()Ljava/lang/String;
const #31 = Method	#23.#30;	//  java/lang/Object.toString:()Ljava/lang/String;
const #32 = Asciz	<init>;
const #33 = Asciz	(Ljava/lang/String;)V;
const #34 = NameAndType	#32:#33;//  "<init>":(Ljava/lang/String;)V
const #35 = Method	#28.#34;	//  scala/MatchError."<init>":(Ljava/lang/String;)V
const #36 = Asciz	that;
const #37 = Asciz	Ljava/lang/Object;;
const #38 = Asciz	temp2;
const #39 = Asciz	Scala;
const #40 = Asciz	InnerClasses;
const #41 = Asciz	scala/util/parsing/ast/AbstractSyntax;
const #42 = class	#41;	//  scala/util/parsing/ast/AbstractSyntax
const #43 = Asciz	NameElement;
const #44 = Asciz	scala/util/parsing/ast/AbstractSyntax$NameElement$class;
const #45 = class	#44;	//  scala/util/parsing/ast/AbstractSyntax$NameElement$class

{
public static void $init$(scala.util.parsing.ast.AbstractSyntax$NameElement);
  Code:
   Stack=0, Locals=1, Args_size=1
   0:	return
  LineNumberTable: 
   line 24: 0

  LocalVariableTable: 
   Start  Length  Slot  Name   Signature
   0      1      0    $this       Lscala/util/parsing/ast/AbstractSyntax$NameElement;


public static boolean equals(scala.util.parsing.ast.AbstractSyntax$NameElement, java.lang.Object);
  Code:
   Stack=3, Locals=4, Args_size=2
   0:	aload_1
   1:	instanceof	#13; //class scala/util/parsing/ast/AbstractSyntax$NameElement
   4:	ifeq	86
   7:	aload_1
   8:	checkcast	#13; //class scala/util/parsing/ast/AbstractSyntax$NameElement
   11:	invokeinterface	#17,  1; //InterfaceMethod scala/util/parsing/ast/AbstractSyntax$NameElement.scala$util$parsing$ast$AbstractSyntax$NameElement$$$outer:()Lscala/util/parsing/ast/AbstractSyntax;
   16:	aload_0
   17:	invokeinterface	#17,  1; //InterfaceMethod scala/util/parsing/ast/AbstractSyntax$NameElement.scala$util$parsing$ast$AbstractSyntax$NameElement$$$outer:()Lscala/util/parsing/ast/AbstractSyntax;
   22:	if_acmpne	86
   25:	aload_1
   26:	checkcast	#13; //class scala/util/parsing/ast/AbstractSyntax$NameElement
   29:	astore_2
   30:	iconst_1
   31:	ifeq	74
   34:	aload_2
   35:	invokeinterface	#21,  1; //InterfaceMethod scala/util/parsing/ast/AbstractSyntax$NameElement.name:()Ljava/lang/String;
   40:	aload_0
   41:	invokeinterface	#21,  1; //InterfaceMethod scala/util/parsing/ast/AbstractSyntax$NameElement.name:()Ljava/lang/String;
   46:	astore_3
   47:	dup
   48:	ifnonnull	59
   51:	pop
   52:	aload_3
   53:	ifnull	66
   56:	goto	70
   59:	aload_3
   60:	invokevirtual	#26; //Method java/lang/Object.equals:(Ljava/lang/Object;)Z
   63:	ifeq	70
   66:	iconst_1
   67:	goto	91
   70:	iconst_0
   71:	goto	91
   74:	new	#28; //class scala/MatchError
   77:	dup
   78:	aload_1
   79:	invokevirtual	#31; //Method java/lang/Object.toString:()Ljava/lang/String;
   82:	invokespecial	#35; //Method scala/MatchError."<init>":(Ljava/lang/String;)V
   85:	athrow
   86:	iconst_1
   87:	ifeq	92
   90:	iconst_0
   91:	ireturn
   92:	new	#28; //class scala/MatchError
   95:	dup
   96:	aload_1
   97:	invokevirtual	#31; //Method java/lang/Object.toString:()Ljava/lang/String;
   100:	invokespecial	#35; //Method scala/MatchError."<init>":(Ljava/lang/String;)V
   103:	athrow
  LineNumberTable: 
   line 26: 0
   line 21: 30
   line 27: 34
   line 26: 74
   line 21: 86
   line 28: 90
   line 26: 91

  LocalVariableTable: 
   Start  Length  Slot  Name   Signature
   0      104      0    $this       Lscala/util/parsing/ast/AbstractSyntax$NameElement;
   0      104      1    that       Ljava/lang/Object;
   30      56      2    temp2       Lscala/util/parsing/ast/AbstractSyntax$NameElement;


}

