Compiled from "Binders.scala"
public final class scala.util.parsing.ast.Binders$$anon$5$$anonfun$gmap$5 extends java.lang.Object implements scala.Function1,scala.ScalaObject,java.io.Serializable
  SourceFile: "Binders.scala"
  Scala: length = 0x
   
  InnerClass: 
   public Scope=class scala/util/parsing/ast/Binders$Scope of class scala/util/parsing/ast/Binders
   public final $anon$5=class scala/util/parsing/ast/Binders$$anon$5 of class scala/util/parsing/ast/Binders
   public abstract Mapper=class scala/util/parsing/ast/Mappable$Mapper of class scala/util/parsing/ast/Mappable
   public abstract NameElement=class scala/util/parsing/ast/AbstractSyntax$NameElement of class scala/util/parsing/ast/AbstractSyntax
   public final $anonfun$gmap$5=class scala/util/parsing/ast/Binders$$anon$5$$anonfun$gmap$5 of class scala/util/parsing/ast/Binders$$anon$5
  minor version: 0
  major version: 49
  Constant pool:
Asciz	SourceFile;
Asciz	Binders.scala;
Asciz	<clinit>;
Asciz	()V;
Asciz	Code;
Asciz	serialVersionUID;
Asciz	J;
Asciz	scala/util/parsing/ast/Binders$$anon$5$$anonfun$gmap$5;
class	scala/util/parsing/ast/Binders$$anon$5$$anonfun$gmap$5
NameAndType	serialVersionUID:J
Field	scala/util/parsing/ast/Binders$$anon$5$$anonfun$gmap$5.serialVersionUID:J
Asciz	newScope$1;
Asciz	Lscala/util/parsing/ast/Binders$Scope;;
Asciz	f$4;
Asciz	Lscala/util/parsing/ast/Mappable$Mapper;;
Asciz	$outer;
Asciz	Lscala/util/parsing/ast/Binders$$anon$5;;
Asciz	<init>;
Asciz	(Lscala/util/parsing/ast/Binders$$anon$5;Lscala/util/parsing/ast/Mappable$Mapper;Lscala/util/parsing/ast/Binders$Scope;)V;
Asciz	LineNumberTable;
Asciz	java/lang/NullPointerException;
class	java/lang/NullPointerException
NameAndType	"<init>":()V
Method	java/lang/NullPointerException."<init>":()V
NameAndType	$outer:Lscala/util/parsing/ast/Binders$$anon$5;
Field	scala/util/parsing/ast/Binders$$anon$5$$anonfun$gmap$5.$outer:Lscala/util/parsing/ast/Binders$$anon$5;
NameAndType	f$4:Lscala/util/parsing/ast/Mappable$Mapper;
Field	scala/util/parsing/ast/Binders$$anon$5$$anonfun$gmap$5.f$4:Lscala/util/parsing/ast/Mappable$Mapper;
NameAndType	newScope$1:Lscala/util/parsing/ast/Binders$Scope;
Field	scala/util/parsing/ast/Binders$$anon$5$$anonfun$gmap$5.newScope$1:Lscala/util/parsing/ast/Binders$Scope;
Asciz	java/lang/Object;
class	java/lang/Object
Method	java/lang/Object."<init>":()V
Asciz	scala/Function1$class;
class	scala/Function1$class
Asciz	$init$;
Asciz	(Lscala/Function1;)V;
NameAndType	$init$:(Lscala/Function1;)V
Method	scala/Function1$class.$init$:(Lscala/Function1;)V
Asciz	this;
Asciz	Lscala/util/parsing/ast/Binders$$anon$5$$anonfun$gmap$5;;
Asciz	LocalVariableTable;
Asciz	apply;
Asciz	(Ljava/lang/Object;)Ljava/lang/Object;;
Asciz	scala/util/parsing/ast/AbstractSyntax$NameElement;
class	scala/util/parsing/ast/AbstractSyntax$NameElement
Asciz	(Lscala/util/parsing/ast/AbstractSyntax$NameElement;)V;
NameAndType	apply:(Lscala/util/parsing/ast/AbstractSyntax$NameElement;)V
Method	scala/util/parsing/ast/Binders$$anon$5$$anonfun$gmap$5.apply:(Lscala/util/parsing/ast/AbstractSyntax$NameElement;)V
Asciz	scala/runtime/BoxedUnit;
class	scala/runtime/BoxedUnit
Asciz	UNIT;
Asciz	Lscala/runtime/BoxedUnit;;
NameAndType	UNIT:Lscala/runtime/BoxedUnit;
Field	scala/runtime/BoxedUnit.UNIT:Lscala/runtime/BoxedUnit;
Asciz	v1;
Asciz	Ljava/lang/Object;;
Asciz	scala/util/parsing/ast/Binders$$anon$5;
class	scala/util/parsing/ast/Binders$$anon$5
Asciz	evidence$10$1;
Asciz	Lscala/Function1;;
NameAndType	evidence$10$1:Lscala/Function1;
Field	scala/util/parsing/ast/Binders$$anon$5.evidence$10$1:Lscala/Function1;
Asciz	scala/util/parsing/ast/Mappable$Mapper;
class	scala/util/parsing/ast/Mappable$Mapper
Asciz	(Ljava/lang/Object;Lscala/Function1;)Ljava/lang/Object;;
NameAndType	apply:(Ljava/lang/Object;Lscala/Function1;)Ljava/lang/Object;
InterfaceMethod	scala/util/parsing/ast/Mappable$Mapper.apply:(Ljava/lang/Object;Lscala/Function1;)Ljava/lang/Object;
Asciz	scala/util/parsing/ast/Binders$Scope;
class	scala/util/parsing/ast/Binders$Scope
Asciz	addBinder;
NameAndType	addBinder:(Lscala/util/parsing/ast/AbstractSyntax$NameElement;)V
Method	scala/util/parsing/ast/Binders$Scope.addBinder:(Lscala/util/parsing/ast/AbstractSyntax$NameElement;)V
Asciz	b;
Asciz	Lscala/util/parsing/ast/AbstractSyntax$NameElement;;
Asciz	(Tbt;)V;
Asciz	Signature;
Asciz	andThen;
Asciz	(Lscala/Function1;)Lscala/Function1;;
Asciz	(Lscala/Function1;Lscala/Function1;)Lscala/Function1;;
NameAndType	andThen:(Lscala/Function1;Lscala/Function1;)Lscala/Function1;
Method	scala/Function1$class.andThen:(Lscala/Function1;Lscala/Function1;)Lscala/Function1;
Asciz	g;
Asciz	compose;
NameAndType	compose:(Lscala/Function1;Lscala/Function1;)Lscala/Function1;
Method	scala/Function1$class.compose:(Lscala/Function1;Lscala/Function1;)Lscala/Function1;
Asciz	toString;
Asciz	()Ljava/lang/String;;
Asciz	(Lscala/Function1;)Ljava/lang/String;;
NameAndType	toString:(Lscala/Function1;)Ljava/lang/String;
Method	scala/Function1$class.toString:(Lscala/Function1;)Ljava/lang/String;
Asciz	Scala;
Asciz	InnerClasses;
Asciz	scala/util/parsing/ast/Binders;
class	scala/util/parsing/ast/Binders
Asciz	Scope;
Asciz	$anon$5;
Asciz	scala/util/parsing/ast/Mappable;
class	scala/util/parsing/ast/Mappable
Asciz	Mapper;
Asciz	scala/util/parsing/ast/AbstractSyntax;
class	scala/util/parsing/ast/AbstractSyntax
Asciz	NameElement;
Asciz	$anonfun$gmap$5;
Asciz	scala/Function1;
class	scala/Function1
Asciz	scala/ScalaObject;
class	scala/ScalaObject
Asciz	java/io/Serializable;
class	java/io/Serializable

{
public static final long serialVersionUID;
  Signature: J

private final scala.util.parsing.ast.Binders$Scope newScope$1;
  Signature: Lscala/util/parsing/ast/Binders$Scope;

private final scala.util.parsing.ast.Mappable$Mapper f$4;
  Signature: Lscala/util/parsing/ast/Mappable$Mapper;

private final scala.util.parsing.ast.Binders$$anon$5 $outer;
  Signature: Lscala/util/parsing/ast/Binders$$anon$5;

public static {};
  Signature: ()V
  Code:
   Stack=2, Locals=0, Args_size=0
	lconst_0
	putstatic	Field serialVersionUID:J
	return
  Labels:

public scala.util.parsing.ast.Binders$$anon$5$$anonfun$gmap$5(scala.util.parsing.ast.Binders$$anon$5, scala.util.parsing.ast.Mappable$Mapper, scala.util.parsing.ast.Binders$Scope);
  Signature: (Lscala/util/parsing/ast/Binders$$anon$5;Lscala/util/parsing/ast/Mappable$Mapper;Lscala/util/parsing/ast/Binders$Scope;)V
  Code:
   Stack=2, Locals=4, Args_size=4
	aload_1
	ifnonnull	l1 // aload_0
	new	class java/lang/NullPointerException
	dup
	invokespecial	Method java/lang/NullPointerException."<init>":()V
	athrow
l1	aload_0
	aload_1
	putfield	Field $outer:Lscala/util/parsing/ast/Binders$$anon$5;
	aload_0
	aload_2
	putfield	Field f$4:Lscala/util/parsing/ast/Mappable$Mapper;
	aload_0
	aload_3
	putfield	Field newScope$1:Lscala/util/parsing/ast/Binders$Scope;
	aload_0
	invokespecial	Method java/lang/Object."<init>":()V
	aload_0
	invokestatic	Method scala/Function1$class.$init$:(Lscala/Function1;)V
	return
  Labels:
   	l1 = 12 // aload_0
  LocalVariableTable: 
   Start  Length  Slot  Name   Signature
   0      36      0    this       Lscala/util/parsing/ast/Binders$$anon$5$$anonfun$gmap$5;
   0      36      1    $outer       Lscala/util/parsing/ast/Binders$$anon$5;


public final java.lang.Object apply(java.lang.Object);
  Signature: (Ljava/lang/Object;)Ljava/lang/Object;
  Code:
   Stack=2, Locals=3, Args_size=2
	aload_0
	getfield	Field $outer:Lscala/util/parsing/ast/Binders$$anon$5;
	astore_2
	aload_0
	aload_1
	checkcast	class scala/util/parsing/ast/AbstractSyntax$NameElement
	invokevirtual	Method apply:(Lscala/util/parsing/ast/AbstractSyntax$NameElement;)V
	getstatic	Field scala/runtime/BoxedUnit.UNIT:Lscala/runtime/BoxedUnit;
	areturn
  Labels:
  LocalVariableTable: 
   Start  Length  Slot  Name   Signature
   0      17      0    this       Lscala/util/parsing/ast/Binders$$anon$5$$anonfun$gmap$5;
   5      12      1    v1       Ljava/lang/Object;


public final void apply(scala.util.parsing.ast.AbstractSyntax$NameElement);
  Signature: (Lscala/util/parsing/ast/AbstractSyntax$NameElement;)V
  Code:
   Stack=4, Locals=3, Args_size=2
	aload_0
	getfield	Field $outer:Lscala/util/parsing/ast/Binders$$anon$5;
	astore_2
	aload_0
	getfield	Field newScope$1:Lscala/util/parsing/ast/Binders$Scope;
	aload_0
	getfield	Field f$4:Lscala/util/parsing/ast/Mappable$Mapper;
	aload_1
	aload_0
	getfield	Field $outer:Lscala/util/parsing/ast/Binders$$anon$5;
	getfield	Field scala/util/parsing/ast/Binders$$anon$5.evidence$10$1:Lscala/Function1;
	invokeinterface	InterfaceMethod scala/util/parsing/ast/Mappable$Mapper.apply:(Ljava/lang/Object;Lscala/Function1;)Ljava/lang/Object;
	checkcast	class scala/util/parsing/ast/AbstractSyntax$NameElement
	invokevirtual	Method scala/util/parsing/ast/Binders$Scope.addBinder:(Lscala/util/parsing/ast/AbstractSyntax$NameElement;)V
	return
  Labels:
  LocalVariableTable: 
   Start  Length  Slot  Name   Signature
   0      33      0    this       Lscala/util/parsing/ast/Binders$$anon$5$$anonfun$gmap$5;
   5      28      1    b       Lscala/util/parsing/ast/AbstractSyntax$NameElement;

  Signature: length = 0x2
   00 4C 

public scala.Function1 andThen(scala.Function1);
  Signature: (Lscala/Function1;)Lscala/Function1;
  Code:
   Stack=2, Locals=2, Args_size=2
	aload_0
	aload_1
	invokestatic	Method scala/Function1$class.andThen:(Lscala/Function1;Lscala/Function1;)Lscala/Function1;
	areturn
  Labels:
  LocalVariableTable: 
   Start  Length  Slot  Name   Signature
   0      6      0    this       Lscala/util/parsing/ast/Binders$$anon$5$$anonfun$gmap$5;
   0      6      1    g       Lscala/Function1;


public scala.Function1 compose(scala.Function1);
  Signature: (Lscala/Function1;)Lscala/Function1;
  Code:
   Stack=2, Locals=2, Args_size=2
	aload_0
	aload_1
	invokestatic	Method scala/Function1$class.compose:(Lscala/Function1;Lscala/Function1;)Lscala/Function1;
	areturn
  Labels:
  LocalVariableTable: 
   Start  Length  Slot  Name   Signature
   0      6      0    this       Lscala/util/parsing/ast/Binders$$anon$5$$anonfun$gmap$5;
   0      6      1    g       Lscala/Function1;


public java.lang.String toString();
  Signature: ()Ljava/lang/String;
  Code:
   Stack=1, Locals=1, Args_size=1
	aload_0
	invokestatic	Method scala/Function1$class.toString:(Lscala/Function1;)Ljava/lang/String;
	areturn
  Labels:

}

