Compiled from "Binders.scala"
public class scala.util.parsing.ast.Binders$UnboundElement extends java.lang.Object implements scala.util.parsing.ast.AbstractSyntax$NameElement,scala.ScalaObject
  SourceFile: "Binders.scala"
  Signature: length = 0x2
   00 5A 
  Scala: length = 0x
   
  InnerClass: 
   public #95= #16 of #94; //UnboundElement=class scala/util/parsing/ast/Binders$UnboundElement of class scala/util/parsing/ast/Binders
   public abstract #98= #59 of #97; //NameElement=class scala/util/parsing/ast/AbstractSyntax$NameElement of class scala/util/parsing/ast/AbstractSyntax
  minor version: 0
  major version: 49
  Constant pool:
const #1 = Asciz	SourceFile;
const #2 = Asciz	Binders.scala;
const #3 = Asciz	pos;
const #4 = Asciz	Lscala/util/parsing/input/Position;;
const #5 = Asciz	$outer;
const #6 = Asciz	Lscala/util/parsing/ast/Binders;;
const #7 = Asciz	el;
const #8 = Asciz	Lscala/util/parsing/ast/AbstractSyntax$NameElement;;
const #9 = Asciz	TN;;
const #10 = Asciz	Signature;
const #11 = Asciz	<init>;
const #12 = Asciz	(Lscala/util/parsing/ast/Binders;Lscala/util/parsing/ast/AbstractSyntax$NameElement;)V;
const #13 = Asciz	Code;
const #14 = Asciz	LineNumberTable;
const #15 = Asciz	scala/util/parsing/ast/Binders$UnboundElement;
const #16 = class	#15;	//  scala/util/parsing/ast/Binders$UnboundElement
const #17 = NameAndType	#7:#8;//  el:Lscala/util/parsing/ast/AbstractSyntax$NameElement;
const #18 = Field	#16.#17;	//  scala/util/parsing/ast/Binders$UnboundElement.el:Lscala/util/parsing/ast/AbstractSyntax$NameElement;
const #19 = Asciz	java/lang/NullPointerException;
const #20 = class	#19;	//  java/lang/NullPointerException
const #21 = Asciz	()V;
const #22 = NameAndType	#11:#21;//  "<init>":()V
const #23 = Method	#20.#22;	//  java/lang/NullPointerException."<init>":()V
const #24 = NameAndType	#5:#6;//  $outer:Lscala/util/parsing/ast/Binders;
const #25 = Field	#16.#24;	//  scala/util/parsing/ast/Binders$UnboundElement.$outer:Lscala/util/parsing/ast/Binders;
const #26 = Asciz	java/lang/Object;
const #27 = class	#26;	//  java/lang/Object
const #28 = Method	#27.#22;	//  java/lang/Object."<init>":()V
const #29 = Asciz	scala/util/parsing/input/Positional$class;
const #30 = class	#29;	//  scala/util/parsing/input/Positional$class
const #31 = Asciz	$init$;
const #32 = Asciz	(Lscala/util/parsing/input/Positional;)V;
const #33 = NameAndType	#31:#32;//  $init$:(Lscala/util/parsing/input/Positional;)V
const #34 = Method	#30.#33;	//  scala/util/parsing/input/Positional$class.$init$:(Lscala/util/parsing/input/Positional;)V
const #35 = Asciz	scala/util/parsing/ast/AbstractSyntax$NameElement$class;
const #36 = class	#35;	//  scala/util/parsing/ast/AbstractSyntax$NameElement$class
const #37 = Asciz	(Lscala/util/parsing/ast/AbstractSyntax$NameElement;)V;
const #38 = NameAndType	#31:#37;//  $init$:(Lscala/util/parsing/ast/AbstractSyntax$NameElement;)V
const #39 = Method	#36.#38;	//  scala/util/parsing/ast/AbstractSyntax$NameElement$class.$init$:(Lscala/util/parsing/ast/AbstractSyntax$NameElement;)V
const #40 = Asciz	this;
const #41 = Asciz	Lscala/util/parsing/ast/Binders$UnboundElement;;
const #42 = Asciz	LocalVariableTable;
const #43 = Asciz	(Lscala/util/parsing/ast/Binders;TN;)V;
const #44 = Asciz	scala$util$parsing$ast$AbstractSyntax$NameElement$$$outer;
const #45 = Asciz	()Lscala/util/parsing/ast/AbstractSyntax;;
const #46 = Asciz	scala$util$parsing$ast$Binders$UnboundElement$$$outer;
const #47 = Asciz	()Lscala/util/parsing/ast/Binders;;
const #48 = NameAndType	#46:#47;//  scala$util$parsing$ast$Binders$UnboundElement$$$outer:()Lscala/util/parsing/ast/Binders;
const #49 = Method	#16.#48;	//  scala/util/parsing/ast/Binders$UnboundElement.scala$util$parsing$ast$Binders$UnboundElement$$$outer:()Lscala/util/parsing/ast/Binders;
const #50 = Asciz	name;
const #51 = Asciz	()Ljava/lang/String;;
const #52 = Asciz	scala/collection/mutable/StringBuilder;
const #53 = class	#52;	//  scala/collection/mutable/StringBuilder
const #54 = Method	#53.#22;	//  scala/collection/mutable/StringBuilder."<init>":()V
const #55 = Asciz	()Lscala/util/parsing/ast/AbstractSyntax$NameElement;;
const #56 = NameAndType	#7:#55;//  el:()Lscala/util/parsing/ast/AbstractSyntax$NameElement;
const #57 = Method	#16.#56;	//  scala/util/parsing/ast/Binders$UnboundElement.el:()Lscala/util/parsing/ast/AbstractSyntax$NameElement;
const #58 = Asciz	scala/util/parsing/ast/AbstractSyntax$NameElement;
const #59 = class	#58;	//  scala/util/parsing/ast/AbstractSyntax$NameElement
const #60 = NameAndType	#50:#51;//  name:()Ljava/lang/String;
const #61 = InterfaceMethod	#59.#60;	//  scala/util/parsing/ast/AbstractSyntax$NameElement.name:()Ljava/lang/String;
const #62 = Asciz	append;
const #63 = Asciz	(Ljava/lang/Object;)Lscala/collection/mutable/StringBuilder;;
const #64 = NameAndType	#62:#63;//  append:(Ljava/lang/Object;)Lscala/collection/mutable/StringBuilder;
const #65 = Method	#53.#64;	//  scala/collection/mutable/StringBuilder.append:(Ljava/lang/Object;)Lscala/collection/mutable/StringBuilder;
const #66 = Asciz	@??;
const #67 = String	#66;	//  @??
const #68 = Asciz	toString;
const #69 = NameAndType	#68:#51;//  toString:()Ljava/lang/String;
const #70 = Method	#53.#69;	//  scala/collection/mutable/StringBuilder.toString:()Ljava/lang/String;
const #71 = Asciz	()TN;;
const #72 = Asciz	setPos;
const #73 = Asciz	(Lscala/util/parsing/input/Position;)Lscala/util/parsing/input/Positional;;
const #74 = Asciz	(Lscala/util/parsing/input/Positional;Lscala/util/parsing/input/Position;)Lscala/util/parsing/input/Positional;;
const #75 = NameAndType	#72:#74;//  setPos:(Lscala/util/parsing/input/Positional;Lscala/util/parsing/input/Position;)Lscala/util/parsing/input/Positional;
const #76 = Method	#30.#75;	//  scala/util/parsing/input/Positional$class.setPos:(Lscala/util/parsing/input/Positional;Lscala/util/parsing/input/Position;)Lscala/util/parsing/input/Positional;
const #77 = Asciz	newpos;
const #78 = Asciz	pos_$eq;
const #79 = Asciz	(Lscala/util/parsing/input/Position;)V;
const #80 = NameAndType	#3:#4;//  pos:Lscala/util/parsing/input/Position;
const #81 = Field	#16.#80;	//  scala/util/parsing/ast/Binders$UnboundElement.pos:Lscala/util/parsing/input/Position;
const #82 = Asciz	()Lscala/util/parsing/input/Position;;
const #83 = Asciz	equals;
const #84 = Asciz	(Ljava/lang/Object;)Z;
const #85 = Asciz	(Lscala/util/parsing/ast/AbstractSyntax$NameElement;Ljava/lang/Object;)Z;
const #86 = NameAndType	#83:#85;//  equals:(Lscala/util/parsing/ast/AbstractSyntax$NameElement;Ljava/lang/Object;)Z
const #87 = Method	#36.#86;	//  scala/util/parsing/ast/AbstractSyntax$NameElement$class.equals:(Lscala/util/parsing/ast/AbstractSyntax$NameElement;Ljava/lang/Object;)Z
const #88 = Asciz	that;
const #89 = Asciz	Ljava/lang/Object;;
const #90 = Asciz	<N::Lscala/util/parsing/ast/AbstractSyntax$NameElement;>Ljava/lang/Object;Lscala/util/parsing/ast/AbstractSyntax$NameElement;Lscala/ScalaObject;;
const #91 = Asciz	Scala;
const #92 = Asciz	InnerClasses;
const #93 = Asciz	scala/util/parsing/ast/Binders;
const #94 = class	#93;	//  scala/util/parsing/ast/Binders
const #95 = Asciz	UnboundElement;
const #96 = Asciz	scala/util/parsing/ast/AbstractSyntax;
const #97 = class	#96;	//  scala/util/parsing/ast/AbstractSyntax
const #98 = Asciz	NameElement;
const #99 = Asciz	scala/ScalaObject;
const #100 = class	#99;	//  scala/ScalaObject

{
public final scala.util.parsing.ast.Binders $outer;

public scala.util.parsing.ast.Binders$UnboundElement(scala.util.parsing.ast.Binders, scala.util.parsing.ast.AbstractSyntax$NameElement);
  Code:
   Stack=2, Locals=3, Args_size=3
   0:	aload_0
   1:	aload_2
   2:	putfield	#18; //Field el:Lscala/util/parsing/ast/AbstractSyntax$NameElement;
   5:	aload_1
   6:	ifnonnull	17
   9:	new	#20; //class java/lang/NullPointerException
   12:	dup
   13:	invokespecial	#23; //Method java/lang/NullPointerException."<init>":()V
   16:	athrow
   17:	aload_0
   18:	aload_1
   19:	putfield	#25; //Field $outer:Lscala/util/parsing/ast/Binders;
   22:	aload_0
   23:	invokespecial	#28; //Method java/lang/Object."<init>":()V
   26:	aload_0
   27:	invokestatic	#34; //Method scala/util/parsing/input/Positional$class.$init$:(Lscala/util/parsing/input/Positional;)V
   30:	aload_0
   31:	invokestatic	#39; //Method scala/util/parsing/ast/AbstractSyntax$NameElement$class.$init$:(Lscala/util/parsing/ast/AbstractSyntax$NameElement;)V
   34:	return
  LineNumberTable: 
   line 215: 0

  LocalVariableTable: 
   Start  Length  Slot  Name   Signature
   0      35      0    this       Lscala/util/parsing/ast/Binders$UnboundElement;
   0      35      1    $outer       Lscala/util/parsing/ast/Binders;
   0      35      2    el       Lscala/util/parsing/ast/AbstractSyntax$NameElement;

  Signature: length = 0x2
   00 2B 

public scala.util.parsing.ast.AbstractSyntax scala$util$parsing$ast$AbstractSyntax$NameElement$$$outer();
  Code:
   Stack=1, Locals=1, Args_size=1
   0:	aload_0
   1:	invokevirtual	#49; //Method scala$util$parsing$ast$Binders$UnboundElement$$$outer:()Lscala/util/parsing/ast/Binders;
   4:	areturn
  LineNumberTable: 
   line 215: 1


public scala.util.parsing.ast.Binders scala$util$parsing$ast$Binders$UnboundElement$$$outer();
  Code:
   Stack=1, Locals=1, Args_size=1
   0:	aload_0
   1:	getfield	#25; //Field $outer:Lscala/util/parsing/ast/Binders;
   4:	areturn
  LineNumberTable: 
   line 215: 0


public java.lang.String name();
  Code:
   Stack=2, Locals=1, Args_size=1
   0:	new	#53; //class scala/collection/mutable/StringBuilder
   3:	dup
   4:	invokespecial	#54; //Method scala/collection/mutable/StringBuilder."<init>":()V
   7:	aload_0
   8:	invokespecial	#57; //Method el:()Lscala/util/parsing/ast/AbstractSyntax$NameElement;
   11:	invokeinterface	#61,  1; //InterfaceMethod scala/util/parsing/ast/AbstractSyntax$NameElement.name:()Ljava/lang/String;
   16:	invokevirtual	#65; //Method scala/collection/mutable/StringBuilder.append:(Ljava/lang/Object;)Lscala/collection/mutable/StringBuilder;
   19:	ldc	#67; //String @??
   21:	invokevirtual	#65; //Method scala/collection/mutable/StringBuilder.append:(Ljava/lang/Object;)Lscala/collection/mutable/StringBuilder;
   24:	invokevirtual	#70; //Method scala/collection/mutable/StringBuilder.toString:()Ljava/lang/String;
   27:	areturn
  LineNumberTable: 
   line 216: 0


public scala.util.parsing.input.Positional setPos(scala.util.parsing.input.Position);
  Code:
   Stack=2, Locals=2, Args_size=2
   0:	aload_0
   1:	aload_1
   2:	invokestatic	#76; //Method scala/util/parsing/input/Positional$class.setPos:(Lscala/util/parsing/input/Positional;Lscala/util/parsing/input/Position;)Lscala/util/parsing/input/Positional;
   5:	areturn
  LineNumberTable: 
   line 215: 0

  LocalVariableTable: 
   Start  Length  Slot  Name   Signature
   0      6      0    this       Lscala/util/parsing/ast/Binders$UnboundElement;
   0      6      1    newpos       Lscala/util/parsing/input/Position;


public void pos_$eq(scala.util.parsing.input.Position);
  Code:
   Stack=2, Locals=2, Args_size=2
   0:	aload_0
   1:	aload_1
   2:	putfield	#81; //Field pos:Lscala/util/parsing/input/Position;
   5:	return
  LineNumberTable: 
   line 215: 0


public scala.util.parsing.input.Position pos();
  Code:
   Stack=1, Locals=1, Args_size=1
   0:	aload_0
   1:	getfield	#81; //Field pos:Lscala/util/parsing/input/Position;
   4:	areturn
  LineNumberTable: 
   line 215: 0


public boolean equals(java.lang.Object);
  Code:
   Stack=2, Locals=2, Args_size=2
   0:	aload_0
   1:	aload_1
   2:	invokestatic	#87; //Method scala/util/parsing/ast/AbstractSyntax$NameElement$class.equals:(Lscala/util/parsing/ast/AbstractSyntax$NameElement;Ljava/lang/Object;)Z
   5:	ireturn
  LineNumberTable: 
   line 215: 0

  LocalVariableTable: 
   Start  Length  Slot  Name   Signature
   0      6      0    this       Lscala/util/parsing/ast/Binders$UnboundElement;
   0      6      1    that       Ljava/lang/Object;


}

