Compiled from "Binders.scala"
public final class scala.util.parsing.ast.Binders$_Binder$ extends java.lang.Object implements scala.ScalaObject
  SourceFile: "Binders.scala"
  Scala: length = 0x
   
  InnerClass: 
   public abstract #63= #51 of #40; //ReturnAndDo=class scala/util/parsing/ast/Binders$ReturnAndDo of class scala/util/parsing/ast/Binders
   public final #66= #46 of #65; //$anonfun$genId$1=class scala/util/parsing/ast/Binders$_Binder$$anonfun$genId$1 of class scala/util/parsing/ast/Binders$_Binder
  minor version: 0
  major version: 49
  Constant pool:
const #1 = Asciz	SourceFile;
const #2 = Asciz	Binders.scala;
const #3 = Asciz	Scala;
const #4 = Asciz	$outer;
const #5 = Asciz	Lscala/util/parsing/ast/Binders;;
const #6 = Asciz	scala$util$parsing$ast$Binders$_Binder$$currentId;
const #7 = Asciz	I;
const #8 = Asciz	<init>;
const #9 = Asciz	(Lscala/util/parsing/ast/Binders;)V;
const #10 = Asciz	Code;
const #11 = Asciz	LineNumberTable;
const #12 = Asciz	java/lang/NullPointerException;
const #13 = class	#12;	//  java/lang/NullPointerException
const #14 = Asciz	()V;
const #15 = NameAndType	#8:#14;//  "<init>":()V
const #16 = Method	#13.#15;	//  java/lang/NullPointerException."<init>":()V
const #17 = Asciz	scala/util/parsing/ast/Binders$_Binder$;
const #18 = class	#17;	//  scala/util/parsing/ast/Binders$_Binder$
const #19 = NameAndType	#4:#5;//  $outer:Lscala/util/parsing/ast/Binders;
const #20 = Field	#18.#19;	//  scala/util/parsing/ast/Binders$_Binder$.$outer:Lscala/util/parsing/ast/Binders;
const #21 = Asciz	java/lang/Object;
const #22 = class	#21;	//  java/lang/Object
const #23 = Method	#22.#15;	//  java/lang/Object."<init>":()V
const #24 = NameAndType	#6:#7;//  scala$util$parsing$ast$Binders$_Binder$$currentId:I
const #25 = Field	#18.#24;	//  scala/util/parsing/ast/Binders$_Binder$.scala$util$parsing$ast$Binders$_Binder$$currentId:I
const #26 = Asciz	this;
const #27 = Asciz	Lscala/util/parsing/ast/Binders$_Binder$;;
const #28 = Asciz	LocalVariableTable;
const #29 = Asciz	genId;
const #30 = Asciz	()I;
const #31 = NameAndType	#6:#30;//  scala$util$parsing$ast$Binders$_Binder$$currentId:()I
const #32 = Method	#18.#31;	//  scala/util/parsing/ast/Binders$_Binder$.scala$util$parsing$ast$Binders$_Binder$$currentId:()I
const #33 = Asciz	scala/runtime/BoxesRunTime;
const #34 = class	#33;	//  scala/runtime/BoxesRunTime
const #35 = Asciz	boxToInteger;
const #36 = Asciz	(I)Ljava/lang/Integer;;
const #37 = NameAndType	#35:#36;//  boxToInteger:(I)Ljava/lang/Integer;
const #38 = Method	#34.#37;	//  scala/runtime/BoxesRunTime.boxToInteger:(I)Ljava/lang/Integer;
const #39 = Asciz	scala/util/parsing/ast/Binders;
const #40 = class	#39;	//  scala/util/parsing/ast/Binders
const #41 = Asciz	return_;
const #42 = Asciz	(Ljava/lang/Object;)Lscala/util/parsing/ast/Binders$ReturnAndDo;;
const #43 = NameAndType	#41:#42;//  return_:(Ljava/lang/Object;)Lscala/util/parsing/ast/Binders$ReturnAndDo;
const #44 = InterfaceMethod	#40.#43;	//  scala/util/parsing/ast/Binders.return_:(Ljava/lang/Object;)Lscala/util/parsing/ast/Binders$ReturnAndDo;
const #45 = Asciz	scala/util/parsing/ast/Binders$_Binder$$anonfun$genId$1;
const #46 = class	#45;	//  scala/util/parsing/ast/Binders$_Binder$$anonfun$genId$1
const #47 = Asciz	(Lscala/util/parsing/ast/Binders$_Binder$;)V;
const #48 = NameAndType	#8:#47;//  "<init>":(Lscala/util/parsing/ast/Binders$_Binder$;)V
const #49 = Method	#46.#48;	//  scala/util/parsing/ast/Binders$_Binder$$anonfun$genId$1."<init>":(Lscala/util/parsing/ast/Binders$_Binder$;)V
const #50 = Asciz	scala/util/parsing/ast/Binders$ReturnAndDo;
const #51 = class	#50;	//  scala/util/parsing/ast/Binders$ReturnAndDo
const #52 = Asciz	andDo;
const #53 = Asciz	(Lscala/Function0;)Ljava/lang/Object;;
const #54 = NameAndType	#52:#53;//  andDo:(Lscala/Function0;)Ljava/lang/Object;
const #55 = InterfaceMethod	#51.#54;	//  scala/util/parsing/ast/Binders$ReturnAndDo.andDo:(Lscala/Function0;)Ljava/lang/Object;
const #56 = Asciz	unboxToInt;
const #57 = Asciz	(Ljava/lang/Object;)I;
const #58 = NameAndType	#56:#57;//  unboxToInt:(Ljava/lang/Object;)I
const #59 = Method	#34.#58;	//  scala/runtime/BoxesRunTime.unboxToInt:(Ljava/lang/Object;)I
const #60 = Asciz	scala$util$parsing$ast$Binders$_Binder$$currentId_$eq;
const #61 = Asciz	(I)V;
const #62 = Asciz	InnerClasses;
const #63 = Asciz	ReturnAndDo;
const #64 = Asciz	scala/util/parsing/ast/Binders$_Binder;
const #65 = class	#64;	//  scala/util/parsing/ast/Binders$_Binder
const #66 = Asciz	$anonfun$genId$1;
const #67 = Asciz	scala/ScalaObject;
const #68 = class	#67;	//  scala/ScalaObject

{
public scala.util.parsing.ast.Binders$_Binder$(scala.util.parsing.ast.Binders);
  Code:
   Stack=2, Locals=2, Args_size=2
   0:	aload_1
   1:	ifnonnull	12
   4:	new	#13; //class java/lang/NullPointerException
   7:	dup
   8:	invokespecial	#16; //Method java/lang/NullPointerException."<init>":()V
   11:	athrow
   12:	aload_0
   13:	aload_1
   14:	putfield	#20; //Field $outer:Lscala/util/parsing/ast/Binders;
   17:	aload_0
   18:	invokespecial	#23; //Method java/lang/Object."<init>":()V
   21:	aload_0
   22:	iconst_0
   23:	putfield	#25; //Field scala$util$parsing$ast$Binders$_Binder$$currentId:I
   26:	return
  LineNumberTable: 
   line 353: 0
   line 354: 21

  LocalVariableTable: 
   Start  Length  Slot  Name   Signature
   0      27      0    this       Lscala/util/parsing/ast/Binders$_Binder$;
   0      27      1    $outer       Lscala/util/parsing/ast/Binders;


public int genId();
  Code:
   Stack=4, Locals=1, Args_size=1
   0:	aload_0
   1:	getfield	#20; //Field $outer:Lscala/util/parsing/ast/Binders;
   4:	aload_0
   5:	invokevirtual	#32; //Method scala$util$parsing$ast$Binders$_Binder$$currentId:()I
   8:	invokestatic	#38; //Method scala/runtime/BoxesRunTime.boxToInteger:(I)Ljava/lang/Integer;
   11:	invokeinterface	#44,  2; //InterfaceMethod scala/util/parsing/ast/Binders.return_:(Ljava/lang/Object;)Lscala/util/parsing/ast/Binders$ReturnAndDo;
   16:	new	#46; //class scala/util/parsing/ast/Binders$_Binder$$anonfun$genId$1
   19:	dup
   20:	aload_0
   21:	invokespecial	#49; //Method scala/util/parsing/ast/Binders$_Binder$$anonfun$genId$1."<init>":(Lscala/util/parsing/ast/Binders$_Binder$;)V
   24:	invokeinterface	#55,  2; //InterfaceMethod scala/util/parsing/ast/Binders$ReturnAndDo.andDo:(Lscala/Function0;)Ljava/lang/Object;
   29:	invokestatic	#59; //Method scala/runtime/BoxesRunTime.unboxToInt:(Ljava/lang/Object;)I
   32:	ireturn
  LineNumberTable: 
   line 355: 0


public final void scala$util$parsing$ast$Binders$_Binder$$currentId_$eq(int);
  Code:
   Stack=2, Locals=2, Args_size=2
   0:	aload_0
   1:	iload_1
   2:	putfield	#25; //Field scala$util$parsing$ast$Binders$_Binder$$currentId:I
   5:	return
  LineNumberTable: 
   line 354: 0


public final int scala$util$parsing$ast$Binders$_Binder$$currentId();
  Code:
   Stack=1, Locals=1, Args_size=1
   0:	aload_0
   1:	getfield	#25; //Field scala$util$parsing$ast$Binders$_Binder$$currentId:I
   4:	ireturn
  LineNumberTable: 
   line 354: 0


}

