Compiled from "Binders.scala"
public class scala.util.parsing.ast.Binders$UnboundElement extends java.lang.Object implements scala.util.parsing.ast.AbstractSyntax$NameElement,scala.ScalaObject
  SourceFile: "Binders.scala"
  Signature: length = 0x2
   00 5A 
  Scala: length = 0x
   
  InnerClass: 
   public UnboundElement=class scala/util/parsing/ast/Binders$UnboundElement of class scala/util/parsing/ast/Binders
   public abstract NameElement=class scala/util/parsing/ast/AbstractSyntax$NameElement of class scala/util/parsing/ast/AbstractSyntax
  minor version: 0
  major version: 49
  Constant pool:
Asciz	SourceFile;
Asciz	Binders.scala;
Asciz	pos;
Asciz	Lscala/util/parsing/input/Position;;
Asciz	$outer;
Asciz	Lscala/util/parsing/ast/Binders;;
Asciz	el;
Asciz	Lscala/util/parsing/ast/AbstractSyntax$NameElement;;
Asciz	TN;;
Asciz	Signature;
Asciz	<init>;
Asciz	(Lscala/util/parsing/ast/Binders;Lscala/util/parsing/ast/AbstractSyntax$NameElement;)V;
Asciz	Code;
Asciz	LineNumberTable;
Asciz	scala/util/parsing/ast/Binders$UnboundElement;
class	scala/util/parsing/ast/Binders$UnboundElement
NameAndType	el:Lscala/util/parsing/ast/AbstractSyntax$NameElement;
Field	scala/util/parsing/ast/Binders$UnboundElement.el:Lscala/util/parsing/ast/AbstractSyntax$NameElement;
Asciz	java/lang/NullPointerException;
class	java/lang/NullPointerException
Asciz	()V;
NameAndType	"<init>":()V
Method	java/lang/NullPointerException."<init>":()V
NameAndType	$outer:Lscala/util/parsing/ast/Binders;
Field	scala/util/parsing/ast/Binders$UnboundElement.$outer:Lscala/util/parsing/ast/Binders;
Asciz	java/lang/Object;
class	java/lang/Object
Method	java/lang/Object."<init>":()V
Asciz	scala/util/parsing/input/Positional$class;
class	scala/util/parsing/input/Positional$class
Asciz	$init$;
Asciz	(Lscala/util/parsing/input/Positional;)V;
NameAndType	$init$:(Lscala/util/parsing/input/Positional;)V
Method	scala/util/parsing/input/Positional$class.$init$:(Lscala/util/parsing/input/Positional;)V
Asciz	scala/util/parsing/ast/AbstractSyntax$NameElement$class;
class	scala/util/parsing/ast/AbstractSyntax$NameElement$class
Asciz	(Lscala/util/parsing/ast/AbstractSyntax$NameElement;)V;
NameAndType	$init$:(Lscala/util/parsing/ast/AbstractSyntax$NameElement;)V
Method	scala/util/parsing/ast/AbstractSyntax$NameElement$class.$init$:(Lscala/util/parsing/ast/AbstractSyntax$NameElement;)V
Asciz	this;
Asciz	Lscala/util/parsing/ast/Binders$UnboundElement;;
Asciz	LocalVariableTable;
Asciz	(Lscala/util/parsing/ast/Binders;TN;)V;
Asciz	scala$util$parsing$ast$AbstractSyntax$NameElement$$$outer;
Asciz	()Lscala/util/parsing/ast/AbstractSyntax;;
Asciz	scala$util$parsing$ast$Binders$UnboundElement$$$outer;
Asciz	()Lscala/util/parsing/ast/Binders;;
NameAndType	scala$util$parsing$ast$Binders$UnboundElement$$$outer:()Lscala/util/parsing/ast/Binders;
Method	scala/util/parsing/ast/Binders$UnboundElement.scala$util$parsing$ast$Binders$UnboundElement$$$outer:()Lscala/util/parsing/ast/Binders;
Asciz	name;
Asciz	()Ljava/lang/String;;
Asciz	scala/collection/mutable/StringBuilder;
class	scala/collection/mutable/StringBuilder
Method	scala/collection/mutable/StringBuilder."<init>":()V
Asciz	()Lscala/util/parsing/ast/AbstractSyntax$NameElement;;
NameAndType	el:()Lscala/util/parsing/ast/AbstractSyntax$NameElement;
Method	scala/util/parsing/ast/Binders$UnboundElement.el:()Lscala/util/parsing/ast/AbstractSyntax$NameElement;
Asciz	scala/util/parsing/ast/AbstractSyntax$NameElement;
class	scala/util/parsing/ast/AbstractSyntax$NameElement
NameAndType	name:()Ljava/lang/String;
InterfaceMethod	scala/util/parsing/ast/AbstractSyntax$NameElement.name:()Ljava/lang/String;
Asciz	append;
Asciz	(Ljava/lang/Object;)Lscala/collection/mutable/StringBuilder;;
NameAndType	append:(Ljava/lang/Object;)Lscala/collection/mutable/StringBuilder;
Method	scala/collection/mutable/StringBuilder.append:(Ljava/lang/Object;)Lscala/collection/mutable/StringBuilder;
Asciz	@??;
String	@??
Asciz	toString;
NameAndType	toString:()Ljava/lang/String;
Method	scala/collection/mutable/StringBuilder.toString:()Ljava/lang/String;
Asciz	()TN;;
Asciz	setPos;
Asciz	(Lscala/util/parsing/input/Position;)Lscala/util/parsing/input/Positional;;
Asciz	(Lscala/util/parsing/input/Positional;Lscala/util/parsing/input/Position;)Lscala/util/parsing/input/Positional;;
NameAndType	setPos:(Lscala/util/parsing/input/Positional;Lscala/util/parsing/input/Position;)Lscala/util/parsing/input/Positional;
Method	scala/util/parsing/input/Positional$class.setPos:(Lscala/util/parsing/input/Positional;Lscala/util/parsing/input/Position;)Lscala/util/parsing/input/Positional;
Asciz	newpos;
Asciz	pos_$eq;
Asciz	(Lscala/util/parsing/input/Position;)V;
NameAndType	pos:Lscala/util/parsing/input/Position;
Field	scala/util/parsing/ast/Binders$UnboundElement.pos:Lscala/util/parsing/input/Position;
Asciz	()Lscala/util/parsing/input/Position;;
Asciz	equals;
Asciz	(Ljava/lang/Object;)Z;
Asciz	(Lscala/util/parsing/ast/AbstractSyntax$NameElement;Ljava/lang/Object;)Z;
NameAndType	equals:(Lscala/util/parsing/ast/AbstractSyntax$NameElement;Ljava/lang/Object;)Z
Method	scala/util/parsing/ast/AbstractSyntax$NameElement$class.equals:(Lscala/util/parsing/ast/AbstractSyntax$NameElement;Ljava/lang/Object;)Z
Asciz	that;
Asciz	Ljava/lang/Object;;
Asciz	<N::Lscala/util/parsing/ast/AbstractSyntax$NameElement;>Ljava/lang/Object;Lscala/util/parsing/ast/AbstractSyntax$NameElement;Lscala/ScalaObject;;
Asciz	Scala;
Asciz	InnerClasses;
Asciz	scala/util/parsing/ast/Binders;
class	scala/util/parsing/ast/Binders
Asciz	UnboundElement;
Asciz	scala/util/parsing/ast/AbstractSyntax;
class	scala/util/parsing/ast/AbstractSyntax
Asciz	NameElement;
Asciz	scala/ScalaObject;
class	scala/ScalaObject

{
private scala.util.parsing.input.Position pos;
  Signature: Lscala/util/parsing/input/Position;

public final scala.util.parsing.ast.Binders $outer;
  Signature: Lscala/util/parsing/ast/Binders;

private final scala.util.parsing.ast.AbstractSyntax$NameElement el;
  Signature: Lscala/util/parsing/ast/AbstractSyntax$NameElement;
  Signature: length = 0x2
   00 09 

public scala.util.parsing.ast.Binders$UnboundElement(scala.util.parsing.ast.Binders, scala.util.parsing.ast.AbstractSyntax$NameElement);
  Signature: (Lscala/util/parsing/ast/Binders;Lscala/util/parsing/ast/AbstractSyntax$NameElement;)V
  Code:
   Stack=2, Locals=3, Args_size=3
	aload_0
	aload_2
	putfield	Field el:Lscala/util/parsing/ast/AbstractSyntax$NameElement;
	aload_1
	ifnonnull	l1 // aload_0
	new	class java/lang/NullPointerException
	dup
	invokespecial	Method java/lang/NullPointerException."<init>":()V
	athrow
l1	aload_0
	aload_1
	putfield	Field $outer:Lscala/util/parsing/ast/Binders;
	aload_0
	invokespecial	Method java/lang/Object."<init>":()V
	aload_0
	invokestatic	Method scala/util/parsing/input/Positional$class.$init$:(Lscala/util/parsing/input/Positional;)V
	aload_0
	invokestatic	Method scala/util/parsing/ast/AbstractSyntax$NameElement$class.$init$:(Lscala/util/parsing/ast/AbstractSyntax$NameElement;)V
	return
  Labels:
   	l1 = 17 // aload_0
  LocalVariableTable: 
   Start  Length  Slot  Name   Signature
   0      35      0    this       Lscala/util/parsing/ast/Binders$UnboundElement;
   0      35      1    $outer       Lscala/util/parsing/ast/Binders;
   0      35      2    el       Lscala/util/parsing/ast/AbstractSyntax$NameElement;

  Signature: length = 0x2
   00 2B 

public scala.util.parsing.ast.AbstractSyntax scala$util$parsing$ast$AbstractSyntax$NameElement$$$outer();
  Signature: ()Lscala/util/parsing/ast/AbstractSyntax;
  Code:
   Stack=1, Locals=1, Args_size=1
	aload_0
	invokevirtual	Method scala$util$parsing$ast$Binders$UnboundElement$$$outer:()Lscala/util/parsing/ast/Binders;
	areturn
  Labels:

public scala.util.parsing.ast.Binders scala$util$parsing$ast$Binders$UnboundElement$$$outer();
  Signature: ()Lscala/util/parsing/ast/Binders;
  Code:
   Stack=1, Locals=1, Args_size=1
	aload_0
	getfield	Field $outer:Lscala/util/parsing/ast/Binders;
	areturn
  Labels:

public java.lang.String name();
  Signature: ()Ljava/lang/String;
  Code:
   Stack=2, Locals=1, Args_size=1
	new	class scala/collection/mutable/StringBuilder
	dup
	invokespecial	Method scala/collection/mutable/StringBuilder."<init>":()V
	aload_0
	invokespecial	Method el:()Lscala/util/parsing/ast/AbstractSyntax$NameElement;
	invokeinterface	InterfaceMethod scala/util/parsing/ast/AbstractSyntax$NameElement.name:()Ljava/lang/String;
	invokevirtual	Method scala/collection/mutable/StringBuilder.append:(Ljava/lang/Object;)Lscala/collection/mutable/StringBuilder;
	ldc	String @??
	invokevirtual	Method scala/collection/mutable/StringBuilder.append:(Ljava/lang/Object;)Lscala/collection/mutable/StringBuilder;
	invokevirtual	Method scala/collection/mutable/StringBuilder.toString:()Ljava/lang/String;
	areturn
  Labels:

private scala.util.parsing.ast.AbstractSyntax$NameElement el();
  Signature: ()Lscala/util/parsing/ast/AbstractSyntax$NameElement;
  Code:
   Stack=1, Locals=1, Args_size=1
	aload_0
	getfield	Field el:Lscala/util/parsing/ast/AbstractSyntax$NameElement;
	areturn
  Labels:
  Signature: length = 0x2
   00 47 

public scala.util.parsing.input.Positional setPos(scala.util.parsing.input.Position);
  Signature: (Lscala/util/parsing/input/Position;)Lscala/util/parsing/input/Positional;
  Code:
   Stack=2, Locals=2, Args_size=2
	aload_0
	aload_1
	invokestatic	Method scala/util/parsing/input/Positional$class.setPos:(Lscala/util/parsing/input/Positional;Lscala/util/parsing/input/Position;)Lscala/util/parsing/input/Positional;
	areturn
  Labels:
  LocalVariableTable: 
   Start  Length  Slot  Name   Signature
   0      6      0    this       Lscala/util/parsing/ast/Binders$UnboundElement;
   0      6      1    newpos       Lscala/util/parsing/input/Position;


public void pos_$eq(scala.util.parsing.input.Position);
  Signature: (Lscala/util/parsing/input/Position;)V
  Code:
   Stack=2, Locals=2, Args_size=2
	aload_0
	aload_1
	putfield	Field pos:Lscala/util/parsing/input/Position;
	return
  Labels:

public scala.util.parsing.input.Position pos();
  Signature: ()Lscala/util/parsing/input/Position;
  Code:
   Stack=1, Locals=1, Args_size=1
	aload_0
	getfield	Field pos:Lscala/util/parsing/input/Position;
	areturn
  Labels:

public boolean equals(java.lang.Object);
  Signature: (Ljava/lang/Object;)Z
  Code:
   Stack=2, Locals=2, Args_size=2
	aload_0
	aload_1
	invokestatic	Method scala/util/parsing/ast/AbstractSyntax$NameElement$class.equals:(Lscala/util/parsing/ast/AbstractSyntax$NameElement;Ljava/lang/Object;)Z
	ireturn
  Labels:
  LocalVariableTable: 
   Start  Length  Slot  Name   Signature
   0      6      0    this       Lscala/util/parsing/ast/Binders$UnboundElement;
   0      6      1    that       Ljava/lang/Object;


}

