Compiled from "Binders.scala"
public final class scala.util.parsing.ast.Binders$BinderEnv$$anon$7 extends scala.util.parsing.ast.Binders$BinderEnv
  SourceFile: "Binders.scala"
  Scala: length = 0x
   
  InnerClass: 
   public #62= #59 of #61; //Scope=class scala/util/parsing/ast/Binders$Scope of class scala/util/parsing/ast/Binders
   public abstract #63= #27 of #61; //BinderEnv=class scala/util/parsing/ast/Binders$BinderEnv of class scala/util/parsing/ast/Binders
   public final #64= #19 of #27; //$anon$7=class scala/util/parsing/ast/Binders$BinderEnv$$anon$7 of class scala/util/parsing/ast/Binders$BinderEnv
   public abstract #69= #66 of #68; //NameElement=class scala/util/parsing/ast/AbstractSyntax$NameElement of class scala/util/parsing/ast/AbstractSyntax
  minor version: 0
  major version: 49
  Constant pool:
const #1 = Asciz	SourceFile;
const #2 = Asciz	Binders.scala;
const #3 = Asciz	x$3;
const #4 = Asciz	Lscala/util/parsing/ast/Binders$Scope;;
const #5 = Asciz	v$1;
const #6 = Asciz	Lscala/util/parsing/ast/AbstractSyntax$NameElement;;
const #7 = Asciz	$outer;
const #8 = Asciz	Lscala/util/parsing/ast/Binders$BinderEnv;;
const #9 = Asciz	<init>;
const #10 = Asciz	(Lscala/util/parsing/ast/Binders$BinderEnv;Lscala/util/parsing/ast/AbstractSyntax$NameElement;Lscala/util/parsing/ast/Binders$Scope;)V;
const #11 = Asciz	Code;
const #12 = Asciz	LineNumberTable;
const #13 = Asciz	java/lang/NullPointerException;
const #14 = class	#13;	//  java/lang/NullPointerException
const #15 = Asciz	()V;
const #16 = NameAndType	#9:#15;//  "<init>":()V
const #17 = Method	#14.#16;	//  java/lang/NullPointerException."<init>":()V
const #18 = Asciz	scala/util/parsing/ast/Binders$BinderEnv$$anon$7;
const #19 = class	#18;	//  scala/util/parsing/ast/Binders$BinderEnv$$anon$7
const #20 = NameAndType	#7:#8;//  $outer:Lscala/util/parsing/ast/Binders$BinderEnv;
const #21 = Field	#19.#20;	//  scala/util/parsing/ast/Binders$BinderEnv$$anon$7.$outer:Lscala/util/parsing/ast/Binders$BinderEnv;
const #22 = NameAndType	#5:#6;//  v$1:Lscala/util/parsing/ast/AbstractSyntax$NameElement;
const #23 = Field	#19.#22;	//  scala/util/parsing/ast/Binders$BinderEnv$$anon$7.v$1:Lscala/util/parsing/ast/AbstractSyntax$NameElement;
const #24 = NameAndType	#3:#4;//  x$3:Lscala/util/parsing/ast/Binders$Scope;
const #25 = Field	#19.#24;	//  scala/util/parsing/ast/Binders$BinderEnv$$anon$7.x$3:Lscala/util/parsing/ast/Binders$Scope;
const #26 = Asciz	scala/util/parsing/ast/Binders$BinderEnv;
const #27 = class	#26;	//  scala/util/parsing/ast/Binders$BinderEnv
const #28 = Asciz	scala$util$parsing$ast$Binders$BinderEnv$$$outer;
const #29 = Asciz	()Lscala/util/parsing/ast/Binders;;
const #30 = NameAndType	#28:#29;//  scala$util$parsing$ast$Binders$BinderEnv$$$outer:()Lscala/util/parsing/ast/Binders;
const #31 = Method	#27.#30;	//  scala/util/parsing/ast/Binders$BinderEnv.scala$util$parsing$ast$Binders$BinderEnv$$$outer:()Lscala/util/parsing/ast/Binders;
const #32 = Asciz	(Lscala/util/parsing/ast/Binders;)V;
const #33 = NameAndType	#9:#32;//  "<init>":(Lscala/util/parsing/ast/Binders;)V
const #34 = Method	#27.#33;	//  scala/util/parsing/ast/Binders$BinderEnv."<init>":(Lscala/util/parsing/ast/Binders;)V
const #35 = Asciz	this;
const #36 = Asciz	Lscala/util/parsing/ast/Binders$BinderEnv$$anon$7;;
const #37 = Asciz	LocalVariableTable;
const #38 = Asciz	apply;
const #39 = Asciz	(Lscala/util/parsing/ast/AbstractSyntax$NameElement;)Lscala/Option;;
const #40 = Asciz	java/lang/Object;
const #41 = class	#40;	//  java/lang/Object
const #42 = Asciz	equals;
const #43 = Asciz	(Ljava/lang/Object;)Z;
const #44 = NameAndType	#42:#43;//  equals:(Ljava/lang/Object;)Z
const #45 = Method	#41.#44;	//  java/lang/Object.equals:(Ljava/lang/Object;)Z
const #46 = Asciz	scala/Some;
const #47 = class	#46;	//  scala/Some
const #48 = Asciz	(Ljava/lang/Object;)V;
const #49 = NameAndType	#9:#48;//  "<init>":(Ljava/lang/Object;)V
const #50 = Method	#47.#49;	//  scala/Some."<init>":(Ljava/lang/Object;)V
const #51 = NameAndType	#38:#39;//  apply:(Lscala/util/parsing/ast/AbstractSyntax$NameElement;)Lscala/Option;
const #52 = Method	#27.#51;	//  scala/util/parsing/ast/Binders$BinderEnv.apply:(Lscala/util/parsing/ast/AbstractSyntax$NameElement;)Lscala/Option;
const #53 = Asciz	w;
const #54 = Asciz	<b::Lscala/util/parsing/ast/AbstractSyntax$NameElement;>(Tb;)Lscala/Option<Lscala/util/parsing/ast/Binders$Scope<Tb;>;>;;
const #55 = Asciz	Signature;
const #56 = Asciz	Scala;
const #57 = Asciz	InnerClasses;
const #58 = Asciz	scala/util/parsing/ast/Binders$Scope;
const #59 = class	#58;	//  scala/util/parsing/ast/Binders$Scope
const #60 = Asciz	scala/util/parsing/ast/Binders;
const #61 = class	#60;	//  scala/util/parsing/ast/Binders
const #62 = Asciz	Scope;
const #63 = Asciz	BinderEnv;
const #64 = Asciz	$anon$7;
const #65 = Asciz	scala/util/parsing/ast/AbstractSyntax$NameElement;
const #66 = class	#65;	//  scala/util/parsing/ast/AbstractSyntax$NameElement
const #67 = Asciz	scala/util/parsing/ast/AbstractSyntax;
const #68 = class	#67;	//  scala/util/parsing/ast/AbstractSyntax
const #69 = Asciz	NameElement;

{
public scala.util.parsing.ast.Binders$BinderEnv$$anon$7(scala.util.parsing.ast.Binders$BinderEnv, scala.util.parsing.ast.AbstractSyntax$NameElement, scala.util.parsing.ast.Binders$Scope);
  Code:
   Stack=2, Locals=4, Args_size=4
   0:	aload_1
   1:	ifnonnull	12
   4:	new	#14; //class java/lang/NullPointerException
   7:	dup
   8:	invokespecial	#17; //Method java/lang/NullPointerException."<init>":()V
   11:	athrow
   12:	aload_0
   13:	aload_1
   14:	putfield	#21; //Field $outer:Lscala/util/parsing/ast/Binders$BinderEnv;
   17:	aload_0
   18:	aload_2
   19:	putfield	#23; //Field v$1:Lscala/util/parsing/ast/AbstractSyntax$NameElement;
   22:	aload_0
   23:	aload_3
   24:	putfield	#25; //Field x$3:Lscala/util/parsing/ast/Binders$Scope;
   27:	aload_0
   28:	aload_1
   29:	invokevirtual	#31; //Method scala/util/parsing/ast/Binders$BinderEnv.scala$util$parsing$ast$Binders$BinderEnv$$$outer:()Lscala/util/parsing/ast/Binders;
   32:	invokespecial	#34; //Method scala/util/parsing/ast/Binders$BinderEnv."<init>":(Lscala/util/parsing/ast/Binders;)V
   35:	return
  LineNumberTable: 
   line 324: 0

  LocalVariableTable: 
   Start  Length  Slot  Name   Signature
   0      36      0    this       Lscala/util/parsing/ast/Binders$BinderEnv$$anon$7;
   0      36      1    $outer       Lscala/util/parsing/ast/Binders$BinderEnv;


public scala.Option apply(scala.util.parsing.ast.AbstractSyntax$NameElement);
  Code:
   Stack=3, Locals=3, Args_size=2
   0:	aload_1
   1:	aload_0
   2:	getfield	#23; //Field v$1:Lscala/util/parsing/ast/AbstractSyntax$NameElement;
   5:	astore_2
   6:	dup
   7:	ifnonnull	18
   10:	pop
   11:	aload_2
   12:	ifnull	25
   15:	goto	39
   18:	aload_2
   19:	invokevirtual	#45; //Method java/lang/Object.equals:(Ljava/lang/Object;)Z
   22:	ifeq	39
   25:	new	#47; //class scala/Some
   28:	dup
   29:	aload_0
   30:	getfield	#25; //Field x$3:Lscala/util/parsing/ast/Binders$Scope;
   33:	invokespecial	#50; //Method scala/Some."<init>":(Ljava/lang/Object;)V
   36:	goto	47
   39:	aload_0
   40:	getfield	#21; //Field $outer:Lscala/util/parsing/ast/Binders$BinderEnv;
   43:	aload_1
   44:	invokevirtual	#52; //Method scala/util/parsing/ast/Binders$BinderEnv.apply:(Lscala/util/parsing/ast/AbstractSyntax$NameElement;)Lscala/Option;
   47:	areturn
  LineNumberTable: 
   line 326: 0
   line 327: 39
   line 326: 47

  LocalVariableTable: 
   Start  Length  Slot  Name   Signature
   0      48      0    this       Lscala/util/parsing/ast/Binders$BinderEnv$$anon$7;
   0      48      1    w       Lscala/util/parsing/ast/AbstractSyntax$NameElement;

  Signature: length = 0x2
   00 36 

}

