Compiled from "Binders.scala"
public final class scala.util.parsing.ast.Binders$$anon$5 extends java.lang.Object implements scala.util.parsing.ast.Mappable$Mappable
  SourceFile: "Binders.scala"
  Scala: length = 0x
   
  Signature: length = 0x2
   00 4A 
  InnerClass: 
   public Scope=class scala/util/parsing/ast/Binders$Scope of class scala/util/parsing/ast/Binders
   public abstract Mapper=class scala/util/parsing/ast/Mappable$Mapper of class scala/util/parsing/ast/Mappable
   public final $anon$5=class scala/util/parsing/ast/Binders$$anon$5 of class scala/util/parsing/ast/Binders
   public abstract Mappable=class scala/util/parsing/ast/Mappable$Mappable of class scala/util/parsing/ast/Mappable
   public final $anonfun$gmap$5=class scala/util/parsing/ast/Binders$$anon$5$$anonfun$gmap$5 of class scala/util/parsing/ast/Binders$$anon$5
  minor version: 0
  major version: 49
  Constant pool:
Asciz	SourceFile;
Asciz	Binders.scala;
Asciz	$outer;
Asciz	Lscala/util/parsing/ast/Binders;;
Asciz	scope$1;
Asciz	Lscala/util/parsing/ast/Binders$Scope;;
Asciz	evidence$10$1;
Asciz	Lscala/Function1;;
Asciz	everywhere;
Asciz	(Lscala/util/parsing/ast/Mappable$Mapper;Lscala/Function1;)Ljava/lang/Object;;
Asciz	Code;
Asciz	LineNumberTable;
Asciz	scala/util/parsing/ast/Mappable$Mappable$class;
class	scala/util/parsing/ast/Mappable$Mappable$class
Asciz	(Lscala/util/parsing/ast/Mappable$Mappable;Lscala/util/parsing/ast/Mappable$Mapper;Lscala/Function1;)Ljava/lang/Object;;
NameAndType	everywhere:(Lscala/util/parsing/ast/Mappable$Mappable;Lscala/util/parsing/ast/Mappable$Mapper;Lscala/Function1;)Ljava/lang/Object;
Method	scala/util/parsing/ast/Mappable$Mappable$class.everywhere:(Lscala/util/parsing/ast/Mappable$Mappable;Lscala/util/parsing/ast/Mappable$Mapper;Lscala/Function1;)Ljava/lang/Object;
Asciz	this;
Asciz	Lscala/util/parsing/ast/Binders$$anon$5;;
Asciz	f;
Asciz	Lscala/util/parsing/ast/Mappable$Mapper;;
Asciz	c;
Asciz	LocalVariableTable;
Asciz	gmap;
Asciz	(Lscala/util/parsing/ast/Mappable$Mapper;)Lscala/util/parsing/ast/Binders$Scope;;
Asciz	scala/util/parsing/ast/Binders$Scope;
class	scala/util/parsing/ast/Binders$Scope
Asciz	scala/util/parsing/ast/Binders$$anon$5;
class	scala/util/parsing/ast/Binders$$anon$5
NameAndType	$outer:Lscala/util/parsing/ast/Binders;
Field	scala/util/parsing/ast/Binders$$anon$5.$outer:Lscala/util/parsing/ast/Binders;
Asciz	<init>;
Asciz	(Lscala/util/parsing/ast/Binders;)V;
NameAndType	"<init>":(Lscala/util/parsing/ast/Binders;)V
Method	scala/util/parsing/ast/Binders$Scope."<init>":(Lscala/util/parsing/ast/Binders;)V
NameAndType	scope$1:Lscala/util/parsing/ast/Binders$Scope;
Field	scala/util/parsing/ast/Binders$$anon$5.scope$1:Lscala/util/parsing/ast/Binders$Scope;
Asciz	scala/util/parsing/ast/Binders$$anon$5$$anonfun$gmap$5;
class	scala/util/parsing/ast/Binders$$anon$5$$anonfun$gmap$5
Asciz	(Lscala/util/parsing/ast/Binders$$anon$5;Lscala/util/parsing/ast/Mappable$Mapper;Lscala/util/parsing/ast/Binders$Scope;)V;
NameAndType	"<init>":(Lscala/util/parsing/ast/Binders$$anon$5;Lscala/util/parsing/ast/Mappable$Mapper;Lscala/util/parsing/ast/Binders$Scope;)V
Method	scala/util/parsing/ast/Binders$$anon$5$$anonfun$gmap$5."<init>":(Lscala/util/parsing/ast/Binders$$anon$5;Lscala/util/parsing/ast/Mappable$Mapper;Lscala/util/parsing/ast/Binders$Scope;)V
Asciz	scala/collection/IterableLike;
class	scala/collection/IterableLike
Asciz	foreach;
Asciz	(Lscala/Function1;)V;
NameAndType	foreach:(Lscala/Function1;)V
InterfaceMethod	scala/collection/IterableLike.foreach:(Lscala/Function1;)V
Asciz	f$4;
Asciz	newScope$1;
Asciz	(Lscala/util/parsing/ast/Mappable$Mapper;)Lscala/util/parsing/ast/Binders$Scope<Tbt;>;;
Asciz	Signature;
Asciz	scala$util$parsing$ast$Mappable$Mappable$$$outer;
Asciz	()Lscala/util/parsing/ast/Mappable;;
Asciz	(Lscala/util/parsing/ast/Mappable$Mapper;)Ljava/lang/Object;;
NameAndType	gmap:(Lscala/util/parsing/ast/Mappable$Mapper;)Lscala/util/parsing/ast/Binders$Scope;
Method	scala/util/parsing/ast/Binders$$anon$5.gmap:(Lscala/util/parsing/ast/Mappable$Mapper;)Lscala/util/parsing/ast/Binders$Scope;
Asciz	(Lscala/util/parsing/ast/Binders;Lscala/util/parsing/ast/Binders$Scope;Lscala/Function1;)V;
Asciz	java/lang/NullPointerException;
class	java/lang/NullPointerException
Asciz	()V;
NameAndType	"<init>":()V
Method	java/lang/NullPointerException."<init>":()V
NameAndType	evidence$10$1:Lscala/Function1;
Field	scala/util/parsing/ast/Binders$$anon$5.evidence$10$1:Lscala/Function1;
Asciz	java/lang/Object;
class	java/lang/Object
Method	java/lang/Object."<init>":()V
Asciz	$init$;
Asciz	(Lscala/util/parsing/ast/Mappable$Mappable;)V;
NameAndType	$init$:(Lscala/util/parsing/ast/Mappable$Mappable;)V
Method	scala/util/parsing/ast/Mappable$Mappable$class.$init$:(Lscala/util/parsing/ast/Mappable$Mappable;)V
Asciz	Scala;
Asciz	Ljava/lang/Object;Lscala/util/parsing/ast/Mappable$Mappable<Lscala/util/parsing/ast/Binders$Scope<Tbt;>;>;;
Asciz	InnerClasses;
Asciz	scala/util/parsing/ast/Binders;
class	scala/util/parsing/ast/Binders
Asciz	Scope;
Asciz	scala/util/parsing/ast/Mappable$Mapper;
class	scala/util/parsing/ast/Mappable$Mapper
Asciz	scala/util/parsing/ast/Mappable;
class	scala/util/parsing/ast/Mappable
Asciz	Mapper;
Asciz	$anon$5;
Asciz	scala/util/parsing/ast/Mappable$Mappable;
class	scala/util/parsing/ast/Mappable$Mappable
Asciz	Mappable;
Asciz	$anonfun$gmap$5;

{
public final scala.util.parsing.ast.Binders $outer;
  Signature: Lscala/util/parsing/ast/Binders;

public final scala.util.parsing.ast.Binders$Scope scope$1;
  Signature: Lscala/util/parsing/ast/Binders$Scope;

public final scala.Function1 evidence$10$1;
  Signature: Lscala/Function1;

public java.lang.Object everywhere(scala.util.parsing.ast.Mappable$Mapper, scala.Function1);
  Signature: (Lscala/util/parsing/ast/Mappable$Mapper;Lscala/Function1;)Ljava/lang/Object;
  Code:
   Stack=3, Locals=3, Args_size=3
	aload_0
	aload_1
	aload_2
	invokestatic	Method scala/util/parsing/ast/Mappable$Mappable$class.everywhere:(Lscala/util/parsing/ast/Mappable$Mappable;Lscala/util/parsing/ast/Mappable$Mapper;Lscala/Function1;)Ljava/lang/Object;
	areturn
  Labels:
  LocalVariableTable: 
   Start  Length  Slot  Name   Signature
   0      7      0    this       Lscala/util/parsing/ast/Binders$$anon$5;
   0      7      1    f       Lscala/util/parsing/ast/Mappable$Mapper;
   0      7      2    c       Lscala/Function1;


public scala.util.parsing.ast.Binders$Scope gmap(scala.util.parsing.ast.Mappable$Mapper);
  Signature: (Lscala/util/parsing/ast/Mappable$Mapper;)Lscala/util/parsing/ast/Binders$Scope;
  Code:
   Stack=6, Locals=3, Args_size=2
	new	class scala/util/parsing/ast/Binders$Scope
	dup
	aload_0
	getfield	Field $outer:Lscala/util/parsing/ast/Binders;
	invokespecial	Method scala/util/parsing/ast/Binders$Scope."<init>":(Lscala/util/parsing/ast/Binders;)V
	astore_2
	aload_0
	getfield	Field scope$1:Lscala/util/parsing/ast/Binders$Scope;
	new	class scala/util/parsing/ast/Binders$$anon$5$$anonfun$gmap$5
	dup
	aload_0
	aload_1
	aload_2
	invokespecial	Method scala/util/parsing/ast/Binders$$anon$5$$anonfun$gmap$5."<init>":(Lscala/util/parsing/ast/Binders$$anon$5;Lscala/util/parsing/ast/Mappable$Mapper;Lscala/util/parsing/ast/Binders$Scope;)V
	invokeinterface	InterfaceMethod scala/collection/IterableLike.foreach:(Lscala/Function1;)V
	aload_2
	areturn
  Labels:
  LocalVariableTable: 
   Start  Length  Slot  Name   Signature
   0      33      0    this       Lscala/util/parsing/ast/Binders$$anon$5;
   0      33      1    f$4       Lscala/util/parsing/ast/Mappable$Mapper;
   12      20      2    newScope$1       Lscala/util/parsing/ast/Binders$Scope;

  Signature: length = 0x2
   00 33 

public scala.util.parsing.ast.Mappable scala$util$parsing$ast$Mappable$Mappable$$$outer();
  Signature: ()Lscala/util/parsing/ast/Mappable;
  Code:
   Stack=1, Locals=1, Args_size=1
	aload_0
	getfield	Field $outer:Lscala/util/parsing/ast/Binders;
	areturn
  Labels:

public java.lang.Object gmap(scala.util.parsing.ast.Mappable$Mapper);
  Signature: (Lscala/util/parsing/ast/Mappable$Mapper;)Ljava/lang/Object;
  Code:
   Stack=2, Locals=2, Args_size=2
	aload_0
	aload_1
	invokevirtual	Method gmap:(Lscala/util/parsing/ast/Mappable$Mapper;)Lscala/util/parsing/ast/Binders$Scope;
	areturn
  Labels:
  LocalVariableTable: 
   Start  Length  Slot  Name   Signature
   0      6      0    this       Lscala/util/parsing/ast/Binders$$anon$5;
   0      6      1    f       Lscala/util/parsing/ast/Mappable$Mapper;


public scala.util.parsing.ast.Binders$$anon$5(scala.util.parsing.ast.Binders, scala.util.parsing.ast.Binders$Scope, scala.Function1);
  Signature: (Lscala/util/parsing/ast/Binders;Lscala/util/parsing/ast/Binders$Scope;Lscala/Function1;)V
  Code:
   Stack=2, Locals=4, Args_size=4
	aload_1
	ifnonnull	l1 // aload_0
	new	class java/lang/NullPointerException
	dup
	invokespecial	Method java/lang/NullPointerException."<init>":()V
	athrow
l1	aload_0
	aload_1
	putfield	Field $outer:Lscala/util/parsing/ast/Binders;
	aload_0
	aload_2
	putfield	Field scope$1:Lscala/util/parsing/ast/Binders$Scope;
	aload_0
	aload_3
	putfield	Field evidence$10$1:Lscala/Function1;
	aload_0
	invokespecial	Method java/lang/Object."<init>":()V
	aload_0
	invokestatic	Method scala/util/parsing/ast/Mappable$Mappable$class.$init$:(Lscala/util/parsing/ast/Mappable$Mappable;)V
	return
  Labels:
   	l1 = 12 // aload_0
  LocalVariableTable: 
   Start  Length  Slot  Name   Signature
   0      36      0    this       Lscala/util/parsing/ast/Binders$$anon$5;
   0      36      1    $outer       Lscala/util/parsing/ast/Binders;


}

