Compiled from "Binders.scala"
public final class scala.util.parsing.ast.Binders$UnderBinder$ extends java.lang.Object implements scala.ScalaObject
  SourceFile: "Binders.scala"
  Scala: length = 0x
   
  InnerClass: 
   public #58= #34 of #28; //Scope=class scala/util/parsing/ast/Binders$Scope of class scala/util/parsing/ast/Binders
   public #29= #48 of #28; //UnderBinder=class scala/util/parsing/ast/Binders$UnderBinder of class scala/util/parsing/ast/Binders
   public final #61= #60 of #48; //$anon$9=class scala/util/parsing/ast/Binders$UnderBinder$$anon$9 of class scala/util/parsing/ast/Binders$UnderBinder
   public final #64= #63 of #48; //$anon$10=class scala/util/parsing/ast/Binders$UnderBinder$$anon$10 of class scala/util/parsing/ast/Binders$UnderBinder
  minor version: 0
  major version: 49
  Constant pool:
const #1 = Asciz	SourceFile;
const #2 = Asciz	Binders.scala;
const #3 = Asciz	Scala;
const #4 = Asciz	$outer;
const #5 = Asciz	Lscala/util/parsing/ast/Binders;;
const #6 = Asciz	<init>;
const #7 = Asciz	(Lscala/util/parsing/ast/Binders;)V;
const #8 = Asciz	Code;
const #9 = Asciz	LineNumberTable;
const #10 = Asciz	java/lang/NullPointerException;
const #11 = class	#10;	//  java/lang/NullPointerException
const #12 = Asciz	()V;
const #13 = NameAndType	#6:#12;//  "<init>":()V
const #14 = Method	#11.#13;	//  java/lang/NullPointerException."<init>":()V
const #15 = Asciz	scala/util/parsing/ast/Binders$UnderBinder$;
const #16 = class	#15;	//  scala/util/parsing/ast/Binders$UnderBinder$
const #17 = NameAndType	#4:#5;//  $outer:Lscala/util/parsing/ast/Binders;
const #18 = Field	#16.#17;	//  scala/util/parsing/ast/Binders$UnderBinder$.$outer:Lscala/util/parsing/ast/Binders;
const #19 = Asciz	java/lang/Object;
const #20 = class	#19;	//  java/lang/Object
const #21 = Method	#20.#13;	//  java/lang/Object."<init>":()V
const #22 = Asciz	this;
const #23 = Asciz	Lscala/util/parsing/ast/Binders$UnderBinder$;;
const #24 = Asciz	LocalVariableTable;
const #25 = Asciz	unit;
const #26 = Asciz	(Ljava/lang/Object;Lscala/Function1;)Lscala/util/parsing/ast/Binders$UnderBinder;;
const #27 = Asciz	scala/util/parsing/ast/Binders;
const #28 = class	#27;	//  scala/util/parsing/ast/Binders
const #29 = Asciz	UnderBinder;
const #30 = Asciz	()Lscala/util/parsing/ast/Binders$UnderBinder$;;
const #31 = NameAndType	#29:#30;//  UnderBinder:()Lscala/util/parsing/ast/Binders$UnderBinder$;
const #32 = InterfaceMethod	#28.#31;	//  scala/util/parsing/ast/Binders.UnderBinder:()Lscala/util/parsing/ast/Binders$UnderBinder$;
const #33 = Asciz	scala/util/parsing/ast/Binders$Scope;
const #34 = class	#33;	//  scala/util/parsing/ast/Binders$Scope
const #35 = NameAndType	#6:#7;//  "<init>":(Lscala/util/parsing/ast/Binders;)V
const #36 = Method	#34.#35;	//  scala/util/parsing/ast/Binders$Scope."<init>":(Lscala/util/parsing/ast/Binders;)V
const #37 = Asciz	apply;
const #38 = Asciz	(Lscala/util/parsing/ast/Binders$Scope;Ljava/lang/Object;Lscala/Function1;)Lscala/util/parsing/ast/Binders$UnderBinder;;
const #39 = NameAndType	#37:#38;//  apply:(Lscala/util/parsing/ast/Binders$Scope;Ljava/lang/Object;Lscala/Function1;)Lscala/util/parsing/ast/Binders$UnderBinder;
const #40 = Method	#16.#39;	//  scala/util/parsing/ast/Binders$UnderBinder$.apply:(Lscala/util/parsing/ast/Binders$Scope;Ljava/lang/Object;Lscala/Function1;)Lscala/util/parsing/ast/Binders$UnderBinder;
const #41 = Asciz	x;
const #42 = Asciz	Ljava/lang/Object;;
const #43 = Asciz	view$12;
const #44 = Asciz	Lscala/Function1;;
const #45 = Asciz	<bt::Lscala/util/parsing/ast/AbstractSyntax$NameElement;elementT:Ljava/lang/Object;>(TelementT;Lscala/Function1<TelementT;Lscala/util/parsing/ast/Mappable$Mappable<TelementT;>;>;)Lscala/util/parsing/ast/Binders$UnderBinder<Tbt;TelementT;>;;
const #46 = Asciz	Signature;
const #47 = Asciz	scala/util/parsing/ast/Binders$UnderBinder;
const #48 = class	#47;	//  scala/util/parsing/ast/Binders$UnderBinder
const #49 = Asciz	(Lscala/util/parsing/ast/Binders;Lscala/util/parsing/ast/Binders$Scope;Ljava/lang/Object;Lscala/Function1;)V;
const #50 = NameAndType	#6:#49;//  "<init>":(Lscala/util/parsing/ast/Binders;Lscala/util/parsing/ast/Binders$Scope;Ljava/lang/Object;Lscala/Function1;)V
const #51 = Method	#48.#50;	//  scala/util/parsing/ast/Binders$UnderBinder."<init>":(Lscala/util/parsing/ast/Binders;Lscala/util/parsing/ast/Binders$Scope;Ljava/lang/Object;Lscala/Function1;)V
const #52 = Asciz	scope;
const #53 = Asciz	Lscala/util/parsing/ast/Binders$Scope;;
const #54 = Asciz	element;
const #55 = Asciz	view$11;
const #56 = Asciz	<binderType::Lscala/util/parsing/ast/AbstractSyntax$NameElement;elementT:Ljava/lang/Object;>(Lscala/util/parsing/ast/Binders$Scope<TbinderType;>;TelementT;Lscala/Function1<TelementT;Lscala/util/parsing/ast/Mappable$Mappable<TelementT;>;>;)Lscala/util/parsing/ast/Binders$UnderBinder<TbinderType;TelementT;>;;
const #57 = Asciz	InnerClasses;
const #58 = Asciz	Scope;
const #59 = Asciz	scala/util/parsing/ast/Binders$UnderBinder$$anon$9;
const #60 = class	#59;	//  scala/util/parsing/ast/Binders$UnderBinder$$anon$9
const #61 = Asciz	$anon$9;
const #62 = Asciz	scala/util/parsing/ast/Binders$UnderBinder$$anon$10;
const #63 = class	#62;	//  scala/util/parsing/ast/Binders$UnderBinder$$anon$10
const #64 = Asciz	$anon$10;
const #65 = Asciz	scala/ScalaObject;
const #66 = class	#65;	//  scala/ScalaObject

{
public scala.util.parsing.ast.Binders$UnderBinder$(scala.util.parsing.ast.Binders);
  Code:
   Stack=2, Locals=2, Args_size=2
   0:	aload_1
   1:	ifnonnull	12
   4:	new	#11; //class java/lang/NullPointerException
   7:	dup
   8:	invokespecial	#14; //Method java/lang/NullPointerException."<init>":()V
   11:	athrow
   12:	aload_0
   13:	aload_1
   14:	putfield	#18; //Field $outer:Lscala/util/parsing/ast/Binders;
   17:	aload_0
   18:	invokespecial	#21; //Method java/lang/Object."<init>":()V
   21:	return
  LineNumberTable: 
   line 293: 0

  LocalVariableTable: 
   Start  Length  Slot  Name   Signature
   0      22      0    this       Lscala/util/parsing/ast/Binders$UnderBinder$;
   0      22      1    $outer       Lscala/util/parsing/ast/Binders;


public scala.util.parsing.ast.Binders$UnderBinder unit(java.lang.Object, scala.Function1);
  Code:
   Stack=4, Locals=3, Args_size=3
   0:	aload_0
   1:	getfield	#18; //Field $outer:Lscala/util/parsing/ast/Binders;
   4:	invokeinterface	#32,  1; //InterfaceMethod scala/util/parsing/ast/Binders.UnderBinder:()Lscala/util/parsing/ast/Binders$UnderBinder$;
   9:	new	#34; //class scala/util/parsing/ast/Binders$Scope
   12:	dup
   13:	aload_0
   14:	getfield	#18; //Field $outer:Lscala/util/parsing/ast/Binders;
   17:	invokespecial	#36; //Method scala/util/parsing/ast/Binders$Scope."<init>":(Lscala/util/parsing/ast/Binders;)V
   20:	aload_1
   21:	aload_2
   22:	invokevirtual	#40; //Method apply:(Lscala/util/parsing/ast/Binders$Scope;Ljava/lang/Object;Lscala/Function1;)Lscala/util/parsing/ast/Binders$UnderBinder;
   25:	areturn
  LineNumberTable: 
   line 295: 0

  LocalVariableTable: 
   Start  Length  Slot  Name   Signature
   0      26      0    this       Lscala/util/parsing/ast/Binders$UnderBinder$;
   0      26      1    x       Ljava/lang/Object;
   0      26      2    view$12       Lscala/Function1;

  Signature: length = 0x2
   00 2D 

public scala.util.parsing.ast.Binders$UnderBinder apply(scala.util.parsing.ast.Binders$Scope, java.lang.Object, scala.Function1);
  Code:
   Stack=6, Locals=4, Args_size=4
   0:	new	#48; //class scala/util/parsing/ast/Binders$UnderBinder
   3:	dup
   4:	aload_0
   5:	getfield	#18; //Field $outer:Lscala/util/parsing/ast/Binders;
   8:	aload_1
   9:	aload_2
   10:	aload_3
   11:	invokespecial	#51; //Method scala/util/parsing/ast/Binders$UnderBinder."<init>":(Lscala/util/parsing/ast/Binders;Lscala/util/parsing/ast/Binders$Scope;Ljava/lang/Object;Lscala/Function1;)V
   14:	areturn
  LineNumberTable: 
   line 294: 0

  LocalVariableTable: 
   Start  Length  Slot  Name   Signature
   0      15      0    this       Lscala/util/parsing/ast/Binders$UnderBinder$;
   0      15      1    scope       Lscala/util/parsing/ast/Binders$Scope;
   0      15      2    element       Ljava/lang/Object;
   0      15      3    view$11       Lscala/Function1;

  Signature: length = 0x2
   00 38 

}

