Compiled from "Binders.scala"
public final class scala.util.parsing.ast.Binders$UnderBinder$ extends java.lang.Object implements scala.ScalaObject
  SourceFile: "Binders.scala"
  Scala: length = 0x
   
  InnerClass: 
   public Scope=class scala/util/parsing/ast/Binders$Scope of class scala/util/parsing/ast/Binders
   public UnderBinder=class scala/util/parsing/ast/Binders$UnderBinder of class scala/util/parsing/ast/Binders
   public final $anon$9=class scala/util/parsing/ast/Binders$UnderBinder$$anon$9 of class scala/util/parsing/ast/Binders$UnderBinder
   public final $anon$10=class scala/util/parsing/ast/Binders$UnderBinder$$anon$10 of class scala/util/parsing/ast/Binders$UnderBinder
  minor version: 0
  major version: 49
  Constant pool:
Asciz	SourceFile;
Asciz	Binders.scala;
Asciz	Scala;
Asciz	$outer;
Asciz	Lscala/util/parsing/ast/Binders;;
Asciz	<init>;
Asciz	(Lscala/util/parsing/ast/Binders;)V;
Asciz	Code;
Asciz	LineNumberTable;
Asciz	java/lang/NullPointerException;
class	java/lang/NullPointerException
Asciz	()V;
NameAndType	"<init>":()V
Method	java/lang/NullPointerException."<init>":()V
Asciz	scala/util/parsing/ast/Binders$UnderBinder$;
class	scala/util/parsing/ast/Binders$UnderBinder$
NameAndType	$outer:Lscala/util/parsing/ast/Binders;
Field	scala/util/parsing/ast/Binders$UnderBinder$.$outer:Lscala/util/parsing/ast/Binders;
Asciz	java/lang/Object;
class	java/lang/Object
Method	java/lang/Object."<init>":()V
Asciz	this;
Asciz	Lscala/util/parsing/ast/Binders$UnderBinder$;;
Asciz	LocalVariableTable;
Asciz	unit;
Asciz	(Ljava/lang/Object;Lscala/Function1;)Lscala/util/parsing/ast/Binders$UnderBinder;;
Asciz	scala/util/parsing/ast/Binders;
class	scala/util/parsing/ast/Binders
Asciz	UnderBinder;
Asciz	()Lscala/util/parsing/ast/Binders$UnderBinder$;;
NameAndType	UnderBinder:()Lscala/util/parsing/ast/Binders$UnderBinder$;
InterfaceMethod	scala/util/parsing/ast/Binders.UnderBinder:()Lscala/util/parsing/ast/Binders$UnderBinder$;
Asciz	scala/util/parsing/ast/Binders$Scope;
class	scala/util/parsing/ast/Binders$Scope
NameAndType	"<init>":(Lscala/util/parsing/ast/Binders;)V
Method	scala/util/parsing/ast/Binders$Scope."<init>":(Lscala/util/parsing/ast/Binders;)V
Asciz	scala/util/parsing/ast/Binders$UnderBinder;
class	scala/util/parsing/ast/Binders$UnderBinder
Asciz	(Lscala/util/parsing/ast/Binders;Lscala/util/parsing/ast/Binders$Scope;Ljava/lang/Object;Lscala/Function1;)V;
NameAndType	"<init>":(Lscala/util/parsing/ast/Binders;Lscala/util/parsing/ast/Binders$Scope;Ljava/lang/Object;Lscala/Function1;)V
Method	scala/util/parsing/ast/Binders$UnderBinder."<init>":(Lscala/util/parsing/ast/Binders;Lscala/util/parsing/ast/Binders$Scope;Ljava/lang/Object;Lscala/Function1;)V
Asciz	x;
Asciz	Ljava/lang/Object;;
Asciz	evidence$12;
Asciz	Lscala/Function1;;
Asciz	<bt::Lscala/util/parsing/ast/AbstractSyntax$NameElement;elementT:Ljava/lang/Object;>(TelementT;Lscala/Function1<TelementT;Lscala/util/parsing/ast/Mappable$Mappable<TelementT;>;>;)Lscala/util/parsing/ast/Binders$UnderBinder<Tbt;TelementT;>;;
Asciz	Signature;
Asciz	apply;
Asciz	(Lscala/util/parsing/ast/Binders$Scope;Ljava/lang/Object;Lscala/Function1;)Lscala/util/parsing/ast/Binders$UnderBinder;;
Asciz	scope;
Asciz	Lscala/util/parsing/ast/Binders$Scope;;
Asciz	element;
Asciz	evidence$11;
Asciz	<binderType::Lscala/util/parsing/ast/AbstractSyntax$NameElement;elementT:Ljava/lang/Object;>(Lscala/util/parsing/ast/Binders$Scope<TbinderType;>;TelementT;Lscala/Function1<TelementT;Lscala/util/parsing/ast/Mappable$Mappable<TelementT;>;>;)Lscala/util/parsing/ast/Binders$UnderBinder<TbinderType;TelementT;>;;
Asciz	InnerClasses;
Asciz	Scope;
Asciz	scala/util/parsing/ast/Binders$UnderBinder$$anon$9;
class	scala/util/parsing/ast/Binders$UnderBinder$$anon$9
Asciz	$anon$9;
Asciz	scala/util/parsing/ast/Binders$UnderBinder$$anon$10;
class	scala/util/parsing/ast/Binders$UnderBinder$$anon$10
Asciz	$anon$10;
Asciz	scala/ScalaObject;
class	scala/ScalaObject

{
public final scala.util.parsing.ast.Binders $outer;
  Signature: Lscala/util/parsing/ast/Binders;

public scala.util.parsing.ast.Binders$UnderBinder$(scala.util.parsing.ast.Binders);
  Signature: (Lscala/util/parsing/ast/Binders;)V
  Code:
   Stack=2, Locals=2, Args_size=2
	aload_1
	ifnonnull	l1 // aload_0
	new	class java/lang/NullPointerException
	dup
	invokespecial	Method java/lang/NullPointerException."<init>":()V
	athrow
l1	aload_0
	aload_1
	putfield	Field $outer:Lscala/util/parsing/ast/Binders;
	aload_0
	invokespecial	Method java/lang/Object."<init>":()V
	return
  Labels:
   	l1 = 12 // aload_0
  LocalVariableTable: 
   Start  Length  Slot  Name   Signature
   0      22      0    this       Lscala/util/parsing/ast/Binders$UnderBinder$;
   0      22      1    $outer       Lscala/util/parsing/ast/Binders;


public scala.util.parsing.ast.Binders$UnderBinder unit(java.lang.Object, scala.Function1);
  Signature: (Ljava/lang/Object;Lscala/Function1;)Lscala/util/parsing/ast/Binders$UnderBinder;
  Code:
   Stack=6, Locals=5, Args_size=3
	aload_0
	getfield	Field $outer:Lscala/util/parsing/ast/Binders;
	invokeinterface	InterfaceMethod scala/util/parsing/ast/Binders.UnderBinder:()Lscala/util/parsing/ast/Binders$UnderBinder$;
	new	class scala/util/parsing/ast/Binders$Scope
	dup
	aload_0
	getfield	Field $outer:Lscala/util/parsing/ast/Binders;
	invokespecial	Method scala/util/parsing/ast/Binders$Scope."<init>":(Lscala/util/parsing/ast/Binders;)V
	astore	4
	astore_3
	new	class scala/util/parsing/ast/Binders$UnderBinder
	dup
	aload_3
	getfield	Field $outer:Lscala/util/parsing/ast/Binders;
	aload	4
	aload_1
	aload_2
	invokespecial	Method scala/util/parsing/ast/Binders$UnderBinder."<init>":(Lscala/util/parsing/ast/Binders;Lscala/util/parsing/ast/Binders$Scope;Ljava/lang/Object;Lscala/Function1;)V
	areturn
  Labels:
  LocalVariableTable: 
   Start  Length  Slot  Name   Signature
   0      39      0    this       Lscala/util/parsing/ast/Binders$UnderBinder$;
   0      39      1    x       Ljava/lang/Object;
   0      39      2    evidence$12       Lscala/Function1;

  Signature: length = 0x2
   00 2E 

public scala.util.parsing.ast.Binders$UnderBinder apply(scala.util.parsing.ast.Binders$Scope, java.lang.Object, scala.Function1);
  Signature: (Lscala/util/parsing/ast/Binders$Scope;Ljava/lang/Object;Lscala/Function1;)Lscala/util/parsing/ast/Binders$UnderBinder;
  Code:
   Stack=6, Locals=4, Args_size=4
	new	class scala/util/parsing/ast/Binders$UnderBinder
	dup
	aload_0
	getfield	Field $outer:Lscala/util/parsing/ast/Binders;
	aload_1
	aload_2
	aload_3
	invokespecial	Method scala/util/parsing/ast/Binders$UnderBinder."<init>":(Lscala/util/parsing/ast/Binders;Lscala/util/parsing/ast/Binders$Scope;Ljava/lang/Object;Lscala/Function1;)V
	areturn
  Labels:
  LocalVariableTable: 
   Start  Length  Slot  Name   Signature
   0      15      0    this       Lscala/util/parsing/ast/Binders$UnderBinder$;
   0      15      1    scope       Lscala/util/parsing/ast/Binders$Scope;
   0      15      2    element       Ljava/lang/Object;
   0      15      3    evidence$11       Lscala/Function1;

  Signature: length = 0x2
   00 36 

}

