Compiled from "Binders.scala"
public final class scala.util.parsing.ast.Binders$$anon$11 extends java.lang.Object implements scala.util.parsing.ast.Binders$ReturnAndDo
  SourceFile: "Binders.scala"
  Signature: length = 0x2
   00 27 
  Scala: length = 0x
   
  InnerClass: 
   public final #44= #17 of #43; //$anon$11=class scala/util/parsing/ast/Binders$$anon$11 of class scala/util/parsing/ast/Binders
   public abstract #47= #46 of #43; //ReturnAndDo=class scala/util/parsing/ast/Binders$ReturnAndDo of class scala/util/parsing/ast/Binders
  minor version: 0
  major version: 49
  Constant pool:
const #1 = Asciz	SourceFile;
const #2 = Asciz	Binders.scala;
const #3 = Asciz	r;
const #4 = Asciz	Ljava/lang/Object;;
const #5 = Asciz	TT;;
const #6 = Asciz	Signature;
const #7 = Asciz	<init>;
const #8 = Asciz	(Lscala/util/parsing/ast/Binders;Ljava/lang/Object;)V;
const #9 = Asciz	Code;
const #10 = Asciz	LineNumberTable;
const #11 = Asciz	java/lang/Object;
const #12 = class	#11;	//  java/lang/Object
const #13 = Asciz	()V;
const #14 = NameAndType	#7:#13;//  "<init>":()V
const #15 = Method	#12.#14;	//  java/lang/Object."<init>":()V
const #16 = Asciz	scala/util/parsing/ast/Binders$$anon$11;
const #17 = class	#16;	//  scala/util/parsing/ast/Binders$$anon$11
const #18 = NameAndType	#3:#4;//  r:Ljava/lang/Object;
const #19 = Field	#17.#18;	//  scala/util/parsing/ast/Binders$$anon$11.r:Ljava/lang/Object;
const #20 = Asciz	this;
const #21 = Asciz	Lscala/util/parsing/ast/Binders$$anon$11;;
const #22 = Asciz	$outer;
const #23 = Asciz	Lscala/util/parsing/ast/Binders;;
const #24 = Asciz	LocalVariableTable;
const #25 = Asciz	andDo;
const #26 = Asciz	(Lscala/Function0;)Ljava/lang/Object;;
const #27 = Asciz	scala/Function0;
const #28 = class	#27;	//  scala/Function0
const #29 = Asciz	apply;
const #30 = Asciz	()Ljava/lang/Object;;
const #31 = NameAndType	#29:#30;//  apply:()Ljava/lang/Object;
const #32 = InterfaceMethod	#28.#31;	//  scala/Function0.apply:()Ljava/lang/Object;
const #33 = NameAndType	#3:#30;//  r:()Ljava/lang/Object;
const #34 = Method	#17.#33;	//  scala/util/parsing/ast/Binders$$anon$11.r:()Ljava/lang/Object;
const #35 = Asciz	block;
const #36 = Asciz	Lscala/Function0;;
const #37 = Asciz	(Lscala/Function0<Ljava/lang/Object;>;)TT;;
const #38 = Asciz	()TT;;
const #39 = Asciz	Ljava/lang/Object;Lscala/util/parsing/ast/Binders$ReturnAndDo<TT;>;;
const #40 = Asciz	Scala;
const #41 = Asciz	InnerClasses;
const #42 = Asciz	scala/util/parsing/ast/Binders;
const #43 = class	#42;	//  scala/util/parsing/ast/Binders
const #44 = Asciz	$anon$11;
const #45 = Asciz	scala/util/parsing/ast/Binders$ReturnAndDo;
const #46 = class	#45;	//  scala/util/parsing/ast/Binders$ReturnAndDo
const #47 = Asciz	ReturnAndDo;

{
public scala.util.parsing.ast.Binders$$anon$11(scala.util.parsing.ast.Binders, java.lang.Object);
  Code:
   Stack=2, Locals=3, Args_size=3
   0:	aload_0
   1:	invokespecial	#15; //Method java/lang/Object."<init>":()V
   4:	aload_0
   5:	aload_2
   6:	putfield	#19; //Field r:Ljava/lang/Object;
   9:	return
  LineNumberTable: 
   line 348: 0
   line 349: 4

  LocalVariableTable: 
   Start  Length  Slot  Name   Signature
   0      10      0    this       Lscala/util/parsing/ast/Binders$$anon$11;
   0      10      1    $outer       Lscala/util/parsing/ast/Binders;


public java.lang.Object andDo(scala.Function0);
  Code:
   Stack=1, Locals=2, Args_size=2
   0:	aload_1
   1:	invokeinterface	#32,  1; //InterfaceMethod scala/Function0.apply:()Ljava/lang/Object;
   6:	pop
   7:	aload_0
   8:	invokespecial	#34; //Method r:()Ljava/lang/Object;
   11:	areturn
  LineNumberTable: 
   line 350: 0

  LocalVariableTable: 
   Start  Length  Slot  Name   Signature
   0      12      0    this       Lscala/util/parsing/ast/Binders$$anon$11;
   0      12      1    block       Lscala/Function0;

  Signature: length = 0x2
   00 25 

}

