Compiled from "Binders.scala"
public final class scala.util.parsing.ast.Binders$EmptyBinderEnv$ extends scala.util.parsing.ast.Binders$BinderEnv implements scala.ScalaObject
  SourceFile: "Binders.scala"
  Scala: length = 0x
   
  InnerClass: 
   public abstract #32= #9 of #31; //BinderEnv=class scala/util/parsing/ast/Binders$BinderEnv of class scala/util/parsing/ast/Binders
   public abstract #37= #34 of #36; //NameElement=class scala/util/parsing/ast/AbstractSyntax$NameElement of class scala/util/parsing/ast/AbstractSyntax
  minor version: 0
  major version: 49
  Constant pool:
const #1 = Asciz	SourceFile;
const #2 = Asciz	Binders.scala;
const #3 = Asciz	Scala;
const #4 = Asciz	<init>;
const #5 = Asciz	(Lscala/util/parsing/ast/Binders;)V;
const #6 = Asciz	Code;
const #7 = Asciz	LineNumberTable;
const #8 = Asciz	scala/util/parsing/ast/Binders$BinderEnv;
const #9 = class	#8;	//  scala/util/parsing/ast/Binders$BinderEnv
const #10 = NameAndType	#4:#5;//  "<init>":(Lscala/util/parsing/ast/Binders;)V
const #11 = Method	#9.#10;	//  scala/util/parsing/ast/Binders$BinderEnv."<init>":(Lscala/util/parsing/ast/Binders;)V
const #12 = Asciz	this;
const #13 = Asciz	Lscala/util/parsing/ast/Binders$EmptyBinderEnv$;;
const #14 = Asciz	$outer;
const #15 = Asciz	Lscala/util/parsing/ast/Binders;;
const #16 = Asciz	LocalVariableTable;
const #17 = Asciz	apply;
const #18 = Asciz	(Lscala/util/parsing/ast/AbstractSyntax$NameElement;)Lscala/Option;;
const #19 = Asciz	scala/None$;
const #20 = class	#19;	//  scala/None$
const #21 = Asciz	MODULE$;
const #22 = Asciz	Lscala/None$;;
const #23 = NameAndType	#21:#22;//  MODULE$:Lscala/None$;
const #24 = Field	#20.#23;	//  scala/None$.MODULE$:Lscala/None$;
const #25 = Asciz	v;
const #26 = Asciz	Lscala/util/parsing/ast/AbstractSyntax$NameElement;;
const #27 = Asciz	<A::Lscala/util/parsing/ast/AbstractSyntax$NameElement;>(TA;)Lscala/Option<Lscala/util/parsing/ast/Binders$Scope<TA;>;>;;
const #28 = Asciz	Signature;
const #29 = Asciz	InnerClasses;
const #30 = Asciz	scala/util/parsing/ast/Binders;
const #31 = class	#30;	//  scala/util/parsing/ast/Binders
const #32 = Asciz	BinderEnv;
const #33 = Asciz	scala/util/parsing/ast/AbstractSyntax$NameElement;
const #34 = class	#33;	//  scala/util/parsing/ast/AbstractSyntax$NameElement
const #35 = Asciz	scala/util/parsing/ast/AbstractSyntax;
const #36 = class	#35;	//  scala/util/parsing/ast/AbstractSyntax
const #37 = Asciz	NameElement;
const #38 = Asciz	scala/util/parsing/ast/Binders$EmptyBinderEnv$;
const #39 = class	#38;	//  scala/util/parsing/ast/Binders$EmptyBinderEnv$
const #40 = Asciz	scala/ScalaObject;
const #41 = class	#40;	//  scala/ScalaObject

{
public scala.util.parsing.ast.Binders$EmptyBinderEnv$(scala.util.parsing.ast.Binders);
  Code:
   Stack=2, Locals=2, Args_size=2
   0:	aload_0
   1:	aload_1
   2:	invokespecial	#11; //Method scala/util/parsing/ast/Binders$BinderEnv."<init>":(Lscala/util/parsing/ast/Binders;)V
   5:	return
  LineNumberTable: 
   line 331: 0

  LocalVariableTable: 
   Start  Length  Slot  Name   Signature
   0      6      0    this       Lscala/util/parsing/ast/Binders$EmptyBinderEnv$;
   0      6      1    $outer       Lscala/util/parsing/ast/Binders;


public scala.Option apply(scala.util.parsing.ast.AbstractSyntax$NameElement);
  Code:
   Stack=1, Locals=2, Args_size=2
   0:	getstatic	#24; //Field scala/None$.MODULE$:Lscala/None$;
   3:	areturn
  LineNumberTable: 
   line 332: 0

  LocalVariableTable: 
   Start  Length  Slot  Name   Signature
   0      4      0    this       Lscala/util/parsing/ast/Binders$EmptyBinderEnv$;
   0      4      1    v       Lscala/util/parsing/ast/AbstractSyntax$NameElement;

  Signature: length = 0x2
   00 1B 

}

