Compiled from "Binders.scala"
public final class scala.util.parsing.ast.Binders$$anon$6 extends java.lang.Object implements scala.util.parsing.ast.Mappable$Mappable
  SourceFile: "Binders.scala"
  Signature: length = 0x2
   00 6C 
  Scala: length = 0x
   
  InnerClass: 
   public #112= #72 of #86; //Scope=class scala/util/parsing/ast/Binders$Scope of class scala/util/parsing/ast/Binders
   public abstract #115= #61 of #114; //Mapper=class scala/util/parsing/ast/Mappable$Mapper of class scala/util/parsing/ast/Mappable
   public final #116= #17 of #86; //$anon$6=class scala/util/parsing/ast/Binders$$anon$6 of class scala/util/parsing/ast/Binders
   public abstract #117= #92 of #114; //Mappable=class scala/util/parsing/ast/Mappable$Mappable of class scala/util/parsing/ast/Mappable
   public #118= #46 of #86; //BoundElement=class scala/util/parsing/ast/Binders$BoundElement of class scala/util/parsing/ast/Binders
   public abstract #121= #67 of #120; //NameElement=class scala/util/parsing/ast/AbstractSyntax$NameElement of class scala/util/parsing/ast/AbstractSyntax
   public final #122= #69 of #17; //$anonfun$gmap$7=class scala/util/parsing/ast/Binders$$anon$6$$anonfun$gmap$7 of class scala/util/parsing/ast/Binders$$anon$6
   public final #123= #56 of #17; //$anonfun$gmap$6=class scala/util/parsing/ast/Binders$$anon$6$$anonfun$gmap$6 of class scala/util/parsing/ast/Binders$$anon$6
  minor version: 0
  major version: 49
  Constant pool:
const #1 = Asciz	SourceFile;
const #2 = Asciz	Binders.scala;
const #3 = Asciz	self$1;
const #4 = Asciz	Lscala/util/parsing/ast/AbstractSyntax$NameElement;;
const #5 = Asciz	$outer;
const #6 = Asciz	Lscala/util/parsing/ast/Binders;;
const #7 = Asciz	<init>;
const #8 = Asciz	(Lscala/util/parsing/ast/Binders;Lscala/util/parsing/ast/AbstractSyntax$NameElement;)V;
const #9 = Asciz	Code;
const #10 = Asciz	LineNumberTable;
const #11 = Asciz	java/lang/NullPointerException;
const #12 = class	#11;	//  java/lang/NullPointerException
const #13 = Asciz	()V;
const #14 = NameAndType	#7:#13;//  "<init>":()V
const #15 = Method	#12.#14;	//  java/lang/NullPointerException."<init>":()V
const #16 = Asciz	scala/util/parsing/ast/Binders$$anon$6;
const #17 = class	#16;	//  scala/util/parsing/ast/Binders$$anon$6
const #18 = NameAndType	#5:#6;//  $outer:Lscala/util/parsing/ast/Binders;
const #19 = Field	#17.#18;	//  scala/util/parsing/ast/Binders$$anon$6.$outer:Lscala/util/parsing/ast/Binders;
const #20 = NameAndType	#3:#4;//  self$1:Lscala/util/parsing/ast/AbstractSyntax$NameElement;
const #21 = Field	#17.#20;	//  scala/util/parsing/ast/Binders$$anon$6.self$1:Lscala/util/parsing/ast/AbstractSyntax$NameElement;
const #22 = Asciz	java/lang/Object;
const #23 = class	#22;	//  java/lang/Object
const #24 = Method	#23.#14;	//  java/lang/Object."<init>":()V
const #25 = Asciz	scala/util/parsing/ast/Mappable$Mappable$class;
const #26 = class	#25;	//  scala/util/parsing/ast/Mappable$Mappable$class
const #27 = Asciz	$init$;
const #28 = Asciz	(Lscala/util/parsing/ast/Mappable$Mappable;)V;
const #29 = NameAndType	#27:#28;//  $init$:(Lscala/util/parsing/ast/Mappable$Mappable;)V
const #30 = Method	#26.#29;	//  scala/util/parsing/ast/Mappable$Mappable$class.$init$:(Lscala/util/parsing/ast/Mappable$Mappable;)V
const #31 = Asciz	this;
const #32 = Asciz	Lscala/util/parsing/ast/Binders$$anon$6;;
const #33 = Asciz	LocalVariableTable;
const #34 = Asciz	gmap;
const #35 = Asciz	(Lscala/util/parsing/ast/Mappable$Mapper;)Ljava/lang/Object;;
const #36 = Asciz	(Lscala/util/parsing/ast/Mappable$Mapper;)Lscala/util/parsing/ast/AbstractSyntax$NameElement;;
const #37 = NameAndType	#34:#36;//  gmap:(Lscala/util/parsing/ast/Mappable$Mapper;)Lscala/util/parsing/ast/AbstractSyntax$NameElement;
const #38 = Method	#17.#37;	//  scala/util/parsing/ast/Binders$$anon$6.gmap:(Lscala/util/parsing/ast/Mappable$Mapper;)Lscala/util/parsing/ast/AbstractSyntax$NameElement;
const #39 = Asciz	f;
const #40 = Asciz	Lscala/util/parsing/ast/Mappable$Mapper;;
const #41 = Asciz	scala$util$parsing$ast$Mappable$Mappable$$$outer;
const #42 = Asciz	()Lscala/util/parsing/ast/Mappable;;
const #43 = Asciz	scala$util$parsing$ast$Binders$$anon$$$outer;
const #44 = Asciz	()Lscala/util/parsing/ast/Binders;;
const #45 = Asciz	scala/util/parsing/ast/Binders$BoundElement;
const #46 = class	#45;	//  scala/util/parsing/ast/Binders$BoundElement
const #47 = Asciz	el;
const #48 = Asciz	()Lscala/util/parsing/ast/AbstractSyntax$NameElement;;
const #49 = NameAndType	#47:#48;//  el:()Lscala/util/parsing/ast/AbstractSyntax$NameElement;
const #50 = Method	#46.#49;	//  scala/util/parsing/ast/Binders$BoundElement.el:()Lscala/util/parsing/ast/AbstractSyntax$NameElement;
const #51 = Asciz	scope;
const #52 = Asciz	()Lscala/util/parsing/ast/Binders$Scope;;
const #53 = NameAndType	#51:#52;//  scope:()Lscala/util/parsing/ast/Binders$Scope;
const #54 = Method	#46.#53;	//  scala/util/parsing/ast/Binders$BoundElement.scope:()Lscala/util/parsing/ast/Binders$Scope;
const #55 = Asciz	scala/util/parsing/ast/Binders$$anon$6$$anonfun$gmap$6;
const #56 = class	#55;	//  scala/util/parsing/ast/Binders$$anon$6$$anonfun$gmap$6
const #57 = Asciz	(Lscala/util/parsing/ast/Binders$$anon$6;)V;
const #58 = NameAndType	#7:#57;//  "<init>":(Lscala/util/parsing/ast/Binders$$anon$6;)V
const #59 = Method	#56.#58;	//  scala/util/parsing/ast/Binders$$anon$6$$anonfun$gmap$6."<init>":(Lscala/util/parsing/ast/Binders$$anon$6;)V
const #60 = Asciz	scala/util/parsing/ast/Mappable$Mapper;
const #61 = class	#60;	//  scala/util/parsing/ast/Mappable$Mapper
const #62 = Asciz	apply;
const #63 = Asciz	(Ljava/lang/Object;Lscala/Function1;)Ljava/lang/Object;;
const #64 = NameAndType	#62:#63;//  apply:(Ljava/lang/Object;Lscala/Function1;)Ljava/lang/Object;
const #65 = InterfaceMethod	#61.#64;	//  scala/util/parsing/ast/Mappable$Mapper.apply:(Ljava/lang/Object;Lscala/Function1;)Ljava/lang/Object;
const #66 = Asciz	scala/util/parsing/ast/AbstractSyntax$NameElement;
const #67 = class	#66;	//  scala/util/parsing/ast/AbstractSyntax$NameElement
const #68 = Asciz	scala/util/parsing/ast/Binders$$anon$6$$anonfun$gmap$7;
const #69 = class	#68;	//  scala/util/parsing/ast/Binders$$anon$6$$anonfun$gmap$7
const #70 = Method	#69.#58;	//  scala/util/parsing/ast/Binders$$anon$6$$anonfun$gmap$7."<init>":(Lscala/util/parsing/ast/Binders$$anon$6;)V
const #71 = Asciz	scala/util/parsing/ast/Binders$Scope;
const #72 = class	#71;	//  scala/util/parsing/ast/Binders$Scope
const #73 = Asciz	(Lscala/util/parsing/ast/Binders;Lscala/util/parsing/ast/AbstractSyntax$NameElement;Lscala/util/parsing/ast/Binders$Scope;)V;
const #74 = NameAndType	#7:#73;//  "<init>":(Lscala/util/parsing/ast/Binders;Lscala/util/parsing/ast/AbstractSyntax$NameElement;Lscala/util/parsing/ast/Binders$Scope;)V
const #75 = Method	#46.#74;	//  scala/util/parsing/ast/Binders$BoundElement."<init>":(Lscala/util/parsing/ast/Binders;Lscala/util/parsing/ast/AbstractSyntax$NameElement;Lscala/util/parsing/ast/Binders$Scope;)V
const #76 = Asciz	scala/MatchError;
const #77 = class	#76;	//  scala/MatchError
const #78 = Asciz	toString;
const #79 = Asciz	()Ljava/lang/String;;
const #80 = NameAndType	#78:#79;//  toString:()Ljava/lang/String;
const #81 = Method	#23.#80;	//  java/lang/Object.toString:()Ljava/lang/String;
const #82 = Asciz	(Ljava/lang/String;)V;
const #83 = NameAndType	#7:#82;//  "<init>":(Ljava/lang/String;)V
const #84 = Method	#77.#83;	//  scala/MatchError."<init>":(Ljava/lang/String;)V
const #85 = Asciz	scala/util/parsing/ast/Binders;
const #86 = class	#85;	//  scala/util/parsing/ast/Binders
const #87 = Asciz	UserNameElementIsMappable;
const #88 = Asciz	(Lscala/util/parsing/ast/AbstractSyntax$NameElement;)Lscala/util/parsing/ast/Mappable$Mappable;;
const #89 = NameAndType	#87:#88;//  UserNameElementIsMappable:(Lscala/util/parsing/ast/AbstractSyntax$NameElement;)Lscala/util/parsing/ast/Mappable$Mappable;
const #90 = InterfaceMethod	#86.#89;	//  scala/util/parsing/ast/Binders.UserNameElementIsMappable:(Lscala/util/parsing/ast/AbstractSyntax$NameElement;)Lscala/util/parsing/ast/Mappable$Mappable;
const #91 = Asciz	scala/util/parsing/ast/Mappable$Mappable;
const #92 = class	#91;	//  scala/util/parsing/ast/Mappable$Mappable
const #93 = NameAndType	#34:#35;//  gmap:(Lscala/util/parsing/ast/Mappable$Mapper;)Ljava/lang/Object;
const #94 = InterfaceMethod	#92.#93;	//  scala/util/parsing/ast/Mappable$Mappable.gmap:(Lscala/util/parsing/ast/Mappable$Mapper;)Ljava/lang/Object;
const #95 = Asciz	temp12;
const #96 = Asciz	Lscala/util/parsing/ast/Binders$BoundElement;;
const #97 = Asciz	temp13;
const #98 = Asciz	temp14;
const #99 = Asciz	Lscala/util/parsing/ast/Binders$Scope;;
const #100 = Asciz	temp11;
const #101 = Asciz	everywhere;
const #102 = Asciz	(Lscala/util/parsing/ast/Mappable$Mapper;Lscala/Function1;)Ljava/lang/Object;;
const #103 = Asciz	(Lscala/util/parsing/ast/Mappable$Mappable;Lscala/util/parsing/ast/Mappable$Mapper;Lscala/Function1;)Ljava/lang/Object;;
const #104 = NameAndType	#101:#103;//  everywhere:(Lscala/util/parsing/ast/Mappable$Mappable;Lscala/util/parsing/ast/Mappable$Mapper;Lscala/Function1;)Ljava/lang/Object;
const #105 = Method	#26.#104;	//  scala/util/parsing/ast/Mappable$Mappable$class.everywhere:(Lscala/util/parsing/ast/Mappable$Mappable;Lscala/util/parsing/ast/Mappable$Mapper;Lscala/Function1;)Ljava/lang/Object;
const #106 = Asciz	c;
const #107 = Asciz	Lscala/Function1;;
const #108 = Asciz	Ljava/lang/Object;Lscala/util/parsing/ast/Mappable$Mappable<Lscala/util/parsing/ast/AbstractSyntax$NameElement;>;;
const #109 = Asciz	Signature;
const #110 = Asciz	Scala;
const #111 = Asciz	InnerClasses;
const #112 = Asciz	Scope;
const #113 = Asciz	scala/util/parsing/ast/Mappable;
const #114 = class	#113;	//  scala/util/parsing/ast/Mappable
const #115 = Asciz	Mapper;
const #116 = Asciz	$anon$6;
const #117 = Asciz	Mappable;
const #118 = Asciz	BoundElement;
const #119 = Asciz	scala/util/parsing/ast/AbstractSyntax;
const #120 = class	#119;	//  scala/util/parsing/ast/AbstractSyntax
const #121 = Asciz	NameElement;
const #122 = Asciz	$anonfun$gmap$7;
const #123 = Asciz	$anonfun$gmap$6;

{
public final scala.util.parsing.ast.Binders $outer;

public scala.util.parsing.ast.Binders$$anon$6(scala.util.parsing.ast.Binders, scala.util.parsing.ast.AbstractSyntax$NameElement);
  Code:
   Stack=2, Locals=3, Args_size=3
   0:	aload_1
   1:	ifnonnull	12
   4:	new	#12; //class java/lang/NullPointerException
   7:	dup
   8:	invokespecial	#15; //Method java/lang/NullPointerException."<init>":()V
   11:	athrow
   12:	aload_0
   13:	aload_1
   14:	putfield	#19; //Field $outer:Lscala/util/parsing/ast/Binders;
   17:	aload_0
   18:	aload_2
   19:	putfield	#21; //Field self$1:Lscala/util/parsing/ast/AbstractSyntax$NameElement;
   22:	aload_0
   23:	invokespecial	#24; //Method java/lang/Object."<init>":()V
   26:	aload_0
   27:	invokestatic	#30; //Method scala/util/parsing/ast/Mappable$Mappable$class.$init$:(Lscala/util/parsing/ast/Mappable$Mappable;)V
   30:	return
  LineNumberTable: 
   line 284: 0

  LocalVariableTable: 
   Start  Length  Slot  Name   Signature
   0      31      0    this       Lscala/util/parsing/ast/Binders$$anon$6;
   0      31      1    $outer       Lscala/util/parsing/ast/Binders;


public java.lang.Object gmap(scala.util.parsing.ast.Mappable$Mapper);
  Code:
   Stack=2, Locals=2, Args_size=2
   0:	aload_0
   1:	aload_1
   2:	invokevirtual	#38; //Method gmap:(Lscala/util/parsing/ast/Mappable$Mapper;)Lscala/util/parsing/ast/AbstractSyntax$NameElement;
   5:	areturn
  LineNumberTable: 
   line 284: 0

  LocalVariableTable: 
   Start  Length  Slot  Name   Signature
   0      6      0    this       Lscala/util/parsing/ast/Binders$$anon$6;
   0      6      1    f       Lscala/util/parsing/ast/Mappable$Mapper;


public scala.util.parsing.ast.Mappable scala$util$parsing$ast$Mappable$Mappable$$$outer();
  Code:
   Stack=1, Locals=1, Args_size=1
   0:	aload_0
   1:	getfield	#19; //Field $outer:Lscala/util/parsing/ast/Binders;
   4:	areturn
  LineNumberTable: 
   line 284: 1


public scala.util.parsing.ast.Binders scala$util$parsing$ast$Binders$$anon$$$outer();
  Code:
   Stack=1, Locals=1, Args_size=1
   0:	aload_0
   1:	getfield	#19; //Field $outer:Lscala/util/parsing/ast/Binders;
   4:	areturn
  LineNumberTable: 
   line 284: 0


public scala.util.parsing.ast.AbstractSyntax$NameElement gmap(scala.util.parsing.ast.Mappable$Mapper);
  Code:
   Stack=9, Locals=6, Args_size=2
   0:	aload_0
   1:	getfield	#21; //Field self$1:Lscala/util/parsing/ast/AbstractSyntax$NameElement;
   4:	astore	5
   6:	aload	5
   8:	instanceof	#46; //class scala/util/parsing/ast/Binders$BoundElement
   11:	ifeq	99
   14:	aload	5
   16:	checkcast	#46; //class scala/util/parsing/ast/Binders$BoundElement
   19:	astore_2
   20:	aload_2
   21:	invokevirtual	#50; //Method scala/util/parsing/ast/Binders$BoundElement.el:()Lscala/util/parsing/ast/AbstractSyntax$NameElement;
   24:	astore_3
   25:	aload_2
   26:	invokevirtual	#54; //Method scala/util/parsing/ast/Binders$BoundElement.scope:()Lscala/util/parsing/ast/Binders$Scope;
   29:	astore	4
   31:	iconst_1
   32:	ifeq	86
   35:	new	#46; //class scala/util/parsing/ast/Binders$BoundElement
   38:	dup
   39:	aload_0
   40:	getfield	#19; //Field $outer:Lscala/util/parsing/ast/Binders;
   43:	aload_1
   44:	aload_3
   45:	new	#56; //class scala/util/parsing/ast/Binders$$anon$6$$anonfun$gmap$6
   48:	dup
   49:	aload_0
   50:	invokespecial	#59; //Method scala/util/parsing/ast/Binders$$anon$6$$anonfun$gmap$6."<init>":(Lscala/util/parsing/ast/Binders$$anon$6;)V
   53:	invokeinterface	#65,  3; //InterfaceMethod scala/util/parsing/ast/Mappable$Mapper.apply:(Ljava/lang/Object;Lscala/Function1;)Ljava/lang/Object;
   58:	checkcast	#67; //class scala/util/parsing/ast/AbstractSyntax$NameElement
   61:	aload_1
   62:	aload	4
   64:	new	#69; //class scala/util/parsing/ast/Binders$$anon$6$$anonfun$gmap$7
   67:	dup
   68:	aload_0
   69:	invokespecial	#70; //Method scala/util/parsing/ast/Binders$$anon$6$$anonfun$gmap$7."<init>":(Lscala/util/parsing/ast/Binders$$anon$6;)V
   72:	invokeinterface	#65,  3; //InterfaceMethod scala/util/parsing/ast/Mappable$Mapper.apply:(Ljava/lang/Object;Lscala/Function1;)Ljava/lang/Object;
   77:	checkcast	#72; //class scala/util/parsing/ast/Binders$Scope
   80:	invokespecial	#75; //Method scala/util/parsing/ast/Binders$BoundElement."<init>":(Lscala/util/parsing/ast/Binders;Lscala/util/parsing/ast/AbstractSyntax$NameElement;Lscala/util/parsing/ast/Binders$Scope;)V
   83:	goto	125
   86:	new	#77; //class scala/MatchError
   89:	dup
   90:	aload	5
   92:	invokevirtual	#81; //Method java/lang/Object.toString:()Ljava/lang/String;
   95:	invokespecial	#84; //Method scala/MatchError."<init>":(Ljava/lang/String;)V
   98:	athrow
   99:	iconst_1
   100:	ifeq	126
   103:	aload_0
   104:	getfield	#19; //Field $outer:Lscala/util/parsing/ast/Binders;
   107:	aload_0
   108:	getfield	#21; //Field self$1:Lscala/util/parsing/ast/AbstractSyntax$NameElement;
   111:	invokeinterface	#90,  2; //InterfaceMethod scala/util/parsing/ast/Binders.UserNameElementIsMappable:(Lscala/util/parsing/ast/AbstractSyntax$NameElement;)Lscala/util/parsing/ast/Mappable$Mappable;
   116:	aload_1
   117:	invokeinterface	#94,  2; //InterfaceMethod scala/util/parsing/ast/Mappable$Mappable.gmap:(Lscala/util/parsing/ast/Mappable$Mapper;)Ljava/lang/Object;
   122:	checkcast	#67; //class scala/util/parsing/ast/AbstractSyntax$NameElement
   125:	areturn
   126:	new	#77; //class scala/MatchError
   129:	dup
   130:	aload	5
   132:	invokevirtual	#81; //Method java/lang/Object.toString:()Ljava/lang/String;
   135:	invokespecial	#84; //Method scala/MatchError."<init>":(Ljava/lang/String;)V
   138:	athrow
  LineNumberTable: 
   line 285: 0
   line 21: 31
   line 286: 35
   line 285: 86
   line 21: 99
   line 287: 103
   line 285: 125

  LocalVariableTable: 
   Start  Length  Slot  Name   Signature
   0      139      0    this       Lscala/util/parsing/ast/Binders$$anon$6;
   0      139      1    f       Lscala/util/parsing/ast/Mappable$Mapper;
   20      79      2    temp12       Lscala/util/parsing/ast/Binders$BoundElement;
   25      74      3    temp13       Lscala/util/parsing/ast/AbstractSyntax$NameElement;
   31      68      4    temp14       Lscala/util/parsing/ast/Binders$Scope;
   6      133      5    temp11       Lscala/util/parsing/ast/AbstractSyntax$NameElement;


public java.lang.Object everywhere(scala.util.parsing.ast.Mappable$Mapper, scala.Function1);
  Code:
   Stack=3, Locals=3, Args_size=3
   0:	aload_0
   1:	aload_1
   2:	aload_2
   3:	invokestatic	#105; //Method scala/util/parsing/ast/Mappable$Mappable$class.everywhere:(Lscala/util/parsing/ast/Mappable$Mappable;Lscala/util/parsing/ast/Mappable$Mapper;Lscala/Function1;)Ljava/lang/Object;
   6:	areturn
  LineNumberTable: 
   line 284: 0

  LocalVariableTable: 
   Start  Length  Slot  Name   Signature
   0      7      0    this       Lscala/util/parsing/ast/Binders$$anon$6;
   0      7      1    f       Lscala/util/parsing/ast/Mappable$Mapper;
   0      7      2    c       Lscala/Function1;


}

