Compiled from "Binders.scala"
public final class scala.util.parsing.ast.Binders$UnderBinder$$anon$9 extends java.lang.Object implements scala.util.parsing.ast.Mappable$Mapper
  SourceFile: "Binders.scala"
  Scala: length = 0x
   
  InnerClass: 
   public abstract Mapper=class scala/util/parsing/ast/Mappable$Mapper of class scala/util/parsing/ast/Mappable
   public UnderBinder=class scala/util/parsing/ast/Binders$UnderBinder of class scala/util/parsing/ast/Binders
   public abstract NameElement=class scala/util/parsing/ast/AbstractSyntax$NameElement of class scala/util/parsing/ast/AbstractSyntax
   public final $anon$9=class scala/util/parsing/ast/Binders$UnderBinder$$anon$9 of class scala/util/parsing/ast/Binders$UnderBinder
  minor version: 0
  major version: 49
  Constant pool:
Asciz	SourceFile;
Asciz	Binders.scala;
Asciz	subst$1;
Asciz	Lscala/collection/immutable/Map;;
Asciz	$outer;
Asciz	Lscala/util/parsing/ast/Binders$UnderBinder;;
Asciz	<init>;
Asciz	(Lscala/util/parsing/ast/Binders$UnderBinder;Lscala/collection/immutable/Map;)V;
Asciz	Code;
Asciz	LineNumberTable;
Asciz	java/lang/NullPointerException;
class	java/lang/NullPointerException
Asciz	()V;
NameAndType	"<init>":()V
Method	java/lang/NullPointerException."<init>":()V
Asciz	scala/util/parsing/ast/Binders$UnderBinder$$anon$9;
class	scala/util/parsing/ast/Binders$UnderBinder$$anon$9
NameAndType	$outer:Lscala/util/parsing/ast/Binders$UnderBinder;
Field	scala/util/parsing/ast/Binders$UnderBinder$$anon$9.$outer:Lscala/util/parsing/ast/Binders$UnderBinder;
NameAndType	subst$1:Lscala/collection/immutable/Map;
Field	scala/util/parsing/ast/Binders$UnderBinder$$anon$9.subst$1:Lscala/collection/immutable/Map;
Asciz	java/lang/Object;
class	java/lang/Object
Method	java/lang/Object."<init>":()V
Asciz	this;
Asciz	Lscala/util/parsing/ast/Binders$UnderBinder$$anon$9;;
Asciz	LocalVariableTable;
Asciz	(Lscala/util/parsing/ast/Binders$UnderBinder<TbinderType;TelementT;>;)V;
Asciz	Signature;
Asciz	gd1$1;
Asciz	(Lscala/util/parsing/ast/AbstractSyntax$NameElement;)Z;
Asciz	scala/collection/MapLike;
class	scala/collection/MapLike
Asciz	contains;
Asciz	(Ljava/lang/Object;)Z;
NameAndType	contains:(Ljava/lang/Object;)Z
InterfaceMethod	scala/collection/MapLike.contains:(Ljava/lang/Object;)Z
Asciz	apply;
Asciz	(Ljava/lang/Object;Lscala/Function1;)Ljava/lang/Object;;
Asciz	scala/util/parsing/ast/AbstractSyntax$NameElement;
class	scala/util/parsing/ast/AbstractSyntax$NameElement
Asciz	scala$util$parsing$ast$AbstractSyntax$NameElement$$$outer;
Asciz	()Lscala/util/parsing/ast/AbstractSyntax;;
NameAndType	scala$util$parsing$ast$AbstractSyntax$NameElement$$$outer:()Lscala/util/parsing/ast/AbstractSyntax;
InterfaceMethod	scala/util/parsing/ast/AbstractSyntax$NameElement.scala$util$parsing$ast$AbstractSyntax$NameElement$$$outer:()Lscala/util/parsing/ast/AbstractSyntax;
Asciz	scala/util/parsing/ast/Binders$UnderBinder;
class	scala/util/parsing/ast/Binders$UnderBinder
Asciz	scala$util$parsing$ast$Binders$UnderBinder$$$outer;
Asciz	()Lscala/util/parsing/ast/Binders;;
NameAndType	scala$util$parsing$ast$Binders$UnderBinder$$$outer:()Lscala/util/parsing/ast/Binders;
Method	scala/util/parsing/ast/Binders$UnderBinder.scala$util$parsing$ast$Binders$UnderBinder$$$outer:()Lscala/util/parsing/ast/Binders;
NameAndType	gd1$1:(Lscala/util/parsing/ast/AbstractSyntax$NameElement;)Z
Method	scala/util/parsing/ast/Binders$UnderBinder$$anon$9.gd1$1:(Lscala/util/parsing/ast/AbstractSyntax$NameElement;)Z
Asciz	get;
Asciz	(Ljava/lang/Object;)Lscala/Option;;
NameAndType	get:(Ljava/lang/Object;)Lscala/Option;
InterfaceMethod	scala/collection/MapLike.get:(Ljava/lang/Object;)Lscala/Option;
Asciz	scala/MatchError;
class	scala/MatchError
Asciz	toString;
Asciz	()Ljava/lang/String;;
NameAndType	toString:()Ljava/lang/String;
Method	java/lang/Object.toString:()Ljava/lang/String;
Asciz	(Ljava/lang/String;)V;
NameAndType	"<init>":(Ljava/lang/String;)V
Method	scala/MatchError."<init>":(Ljava/lang/String;)V
Asciz	x;
Asciz	Ljava/lang/Object;;
Asciz	evidence$6;
Asciz	Lscala/Function1;;
Asciz	temp6;
Asciz	Lscala/util/parsing/ast/AbstractSyntax$NameElement;;
Asciz	<t:Ljava/lang/Object;>(Tt;Lscala/Function1<Tt;Lscala/util/parsing/ast/Mappable$Mappable<Tt;>;>;)Tt;;
Asciz	Scala;
Asciz	InnerClasses;
Asciz	scala/util/parsing/ast/Mappable$Mapper;
class	scala/util/parsing/ast/Mappable$Mapper
Asciz	scala/util/parsing/ast/Mappable;
class	scala/util/parsing/ast/Mappable
Asciz	Mapper;
Asciz	scala/util/parsing/ast/Binders;
class	scala/util/parsing/ast/Binders
Asciz	UnderBinder;
Asciz	scala/util/parsing/ast/AbstractSyntax;
class	scala/util/parsing/ast/AbstractSyntax
Asciz	NameElement;
Asciz	$anon$9;

{
private final scala.collection.immutable.Map subst$1;
  Signature: Lscala/collection/immutable/Map;

private final scala.util.parsing.ast.Binders$UnderBinder $outer;
  Signature: Lscala/util/parsing/ast/Binders$UnderBinder;

public scala.util.parsing.ast.Binders$UnderBinder$$anon$9(scala.util.parsing.ast.Binders$UnderBinder, scala.collection.immutable.Map);
  Signature: (Lscala/util/parsing/ast/Binders$UnderBinder;Lscala/collection/immutable/Map;)V
  Code:
   Stack=2, Locals=3, Args_size=3
	aload_1
	ifnonnull	l1 // aload_0
	new	class java/lang/NullPointerException
	dup
	invokespecial	Method java/lang/NullPointerException."<init>":()V
	athrow
l1	aload_0
	aload_1
	putfield	Field $outer:Lscala/util/parsing/ast/Binders$UnderBinder;
	aload_0
	aload_2
	putfield	Field subst$1:Lscala/collection/immutable/Map;
	aload_0
	invokespecial	Method java/lang/Object."<init>":()V
	return
  Labels:
   	l1 = 12 // aload_0
  LocalVariableTable: 
   Start  Length  Slot  Name   Signature
   0      27      0    this       Lscala/util/parsing/ast/Binders$UnderBinder$$anon$9;
   0      27      1    $outer       Lscala/util/parsing/ast/Binders$UnderBinder;

  Signature: length = 0x2
   00 1C 

private final boolean gd1$1(scala.util.parsing.ast.AbstractSyntax$NameElement);
  Signature: (Lscala/util/parsing/ast/AbstractSyntax$NameElement;)Z
  Code:
   Stack=2, Locals=2, Args_size=2
	aload_0
	getfield	Field subst$1:Lscala/collection/immutable/Map;
	aload_1
	invokeinterface	InterfaceMethod scala/collection/MapLike.contains:(Ljava/lang/Object;)Z
	ireturn
  Labels:

public java.lang.Object apply(java.lang.Object, scala.Function1);
  Signature: (Ljava/lang/Object;Lscala/Function1;)Ljava/lang/Object;
  Code:
   Stack=3, Locals=5, Args_size=3
	aload_1
	instanceof	class scala/util/parsing/ast/AbstractSyntax$NameElement
	ifeq	l1 // iconst_1
	aload_1
	checkcast	class scala/util/parsing/ast/AbstractSyntax$NameElement
	invokeinterface	InterfaceMethod scala/util/parsing/ast/AbstractSyntax$NameElement.scala$util$parsing$ast$AbstractSyntax$NameElement$$$outer:()Lscala/util/parsing/ast/AbstractSyntax;
	aload_0
	getfield	Field $outer:Lscala/util/parsing/ast/Binders$UnderBinder;
	invokevirtual	Method scala/util/parsing/ast/Binders$UnderBinder.scala$util$parsing$ast$Binders$UnderBinder$$$outer:()Lscala/util/parsing/ast/Binders;
	if_acmpne	l1 // iconst_1
	aload_1
	checkcast	class scala/util/parsing/ast/AbstractSyntax$NameElement
	astore_3
	aload_0
	aload_3
	invokespecial	Method gd1$1:(Lscala/util/parsing/ast/AbstractSyntax$NameElement;)Z
	ifeq	l2 // iconst_1
	aload_0
	getfield	Field subst$1:Lscala/collection/immutable/Map;
	aload_3
	invokeinterface	InterfaceMethod scala/collection/MapLike.get:(Ljava/lang/Object;)Lscala/Option;
	goto	l3 // areturn
l2	iconst_1
	ifeq	l4 // new
	aload_3
	astore	4
	goto	l5 // aload
l4	new	class scala/MatchError
	dup
	aload_1
	invokevirtual	Method java/lang/Object.toString:()Ljava/lang/String;
	invokespecial	Method scala/MatchError."<init>":(Ljava/lang/String;)V
	athrow
l1	iconst_1
	ifeq	l6 // new
	aload_1
	astore	4
l5	aload	4
l3	areturn
l6	new	class scala/MatchError
	dup
	aload_1
	invokevirtual	Method java/lang/Object.toString:()Ljava/lang/String;
	invokespecial	Method scala/MatchError."<init>":(Ljava/lang/String;)V
	athrow
  Labels:
   	l2 = 52 // iconst_1
   	l4 = 62 // new
   	l1 = 74 // iconst_1
   	l5 = 81 // aload
   	l3 = 83 // areturn
   	l6 = 84 // new
  LocalVariableTable: 
   Start  Length  Slot  Name   Signature
   0      96      0    this       Lscala/util/parsing/ast/Binders$UnderBinder$$anon$9;
   0      96      1    x       Ljava/lang/Object;
   0      96      2    evidence$6       Lscala/Function1;
   31      43      3    temp6       Lscala/util/parsing/ast/AbstractSyntax$NameElement;
   81      2      3    temp6       Lscala/util/parsing/ast/AbstractSyntax$NameElement;
   52      4      4    x       Ljava/lang/Object;
   59      3      4    x       Ljava/lang/Object;
   56      18      4    x       Ljava/lang/Object;
   81      2      4    x       Ljava/lang/Object;

  Signature: length = 0x2
   00 49 

}

