Compiled from "Binders.scala"
public final class scala.util.parsing.ast.Binders$$anon$6$$anonfun$gmap$7 extends java.lang.Object implements scala.Function1,scala.ScalaObject,java.io.Serializable
  SourceFile: "Binders.scala"
  Scala: length = 0x
   
  InnerClass: 
   public Scope=class scala/util/parsing/ast/Binders$Scope of class scala/util/parsing/ast/Binders
   public final $anon$6=class scala/util/parsing/ast/Binders$$anon$6 of class scala/util/parsing/ast/Binders
   public abstract Mappable=class scala/util/parsing/ast/Mappable$Mappable of class scala/util/parsing/ast/Mappable
   public final $anonfun$gmap$7=class scala/util/parsing/ast/Binders$$anon$6$$anonfun$gmap$7 of class scala/util/parsing/ast/Binders$$anon$6
   public final $anonfun$apply$1=class scala/util/parsing/ast/Binders$$anon$6$$anonfun$gmap$7$$anonfun$apply$1 of class scala/util/parsing/ast/Binders$$anon$6$$anonfun$gmap$7
  minor version: 0
  major version: 49
  Constant pool:
Asciz	SourceFile;
Asciz	Binders.scala;
Asciz	<clinit>;
Asciz	()V;
Asciz	Code;
Asciz	serialVersionUID;
Asciz	J;
Asciz	scala/util/parsing/ast/Binders$$anon$6$$anonfun$gmap$7;
class	scala/util/parsing/ast/Binders$$anon$6$$anonfun$gmap$7
NameAndType	serialVersionUID:J
Field	scala/util/parsing/ast/Binders$$anon$6$$anonfun$gmap$7.serialVersionUID:J
Asciz	$outer;
Asciz	Lscala/util/parsing/ast/Binders$$anon$6;;
Asciz	<init>;
Asciz	(Lscala/util/parsing/ast/Binders$$anon$6;)V;
Asciz	LineNumberTable;
Asciz	java/lang/NullPointerException;
class	java/lang/NullPointerException
NameAndType	"<init>":()V
Method	java/lang/NullPointerException."<init>":()V
NameAndType	$outer:Lscala/util/parsing/ast/Binders$$anon$6;
Field	scala/util/parsing/ast/Binders$$anon$6$$anonfun$gmap$7.$outer:Lscala/util/parsing/ast/Binders$$anon$6;
Asciz	java/lang/Object;
class	java/lang/Object
Method	java/lang/Object."<init>":()V
Asciz	scala/Function1$class;
class	scala/Function1$class
Asciz	$init$;
Asciz	(Lscala/Function1;)V;
NameAndType	$init$:(Lscala/Function1;)V
Method	scala/Function1$class.$init$:(Lscala/Function1;)V
Asciz	this;
Asciz	Lscala/util/parsing/ast/Binders$$anon$6$$anonfun$gmap$7;;
Asciz	LocalVariableTable;
Asciz	apply;
Asciz	(Ljava/lang/Object;)Ljava/lang/Object;;
Asciz	scala/util/parsing/ast/Binders$Scope;
class	scala/util/parsing/ast/Binders$Scope
Asciz	(Lscala/util/parsing/ast/Binders$Scope;)Lscala/util/parsing/ast/Mappable$Mappable;;
NameAndType	apply:(Lscala/util/parsing/ast/Binders$Scope;)Lscala/util/parsing/ast/Mappable$Mappable;
Method	scala/util/parsing/ast/Binders$$anon$6$$anonfun$gmap$7.apply:(Lscala/util/parsing/ast/Binders$Scope;)Lscala/util/parsing/ast/Mappable$Mappable;
Asciz	v1;
Asciz	Ljava/lang/Object;;
Asciz	scala$util$parsing$ast$Binders$$anon$$anonfun$$$outer;
Asciz	()Lscala/util/parsing/ast/Binders$$anon$6;;
Asciz	scala/util/parsing/ast/Binders$$anon$6;
class	scala/util/parsing/ast/Binders$$anon$6
Asciz	scala$util$parsing$ast$Binders$$anon$$$outer;
Asciz	()Lscala/util/parsing/ast/Binders;;
NameAndType	scala$util$parsing$ast$Binders$$anon$$$outer:()Lscala/util/parsing/ast/Binders;
Method	scala/util/parsing/ast/Binders$$anon$6.scala$util$parsing$ast$Binders$$anon$$$outer:()Lscala/util/parsing/ast/Binders;
Asciz	scala/util/parsing/ast/Binders$$anon$6$$anonfun$gmap$7$$anonfun$apply$1;
class	scala/util/parsing/ast/Binders$$anon$6$$anonfun$gmap$7$$anonfun$apply$1
Asciz	(Lscala/util/parsing/ast/Binders$$anon$6$$anonfun$gmap$7;)V;
NameAndType	"<init>":(Lscala/util/parsing/ast/Binders$$anon$6$$anonfun$gmap$7;)V
Method	scala/util/parsing/ast/Binders$$anon$6$$anonfun$gmap$7$$anonfun$apply$1."<init>":(Lscala/util/parsing/ast/Binders$$anon$6$$anonfun$gmap$7;)V
Asciz	scala/util/parsing/ast/Binders;
class	scala/util/parsing/ast/Binders
Asciz	ScopeIsMappable;
Asciz	(Lscala/util/parsing/ast/Binders$Scope;Lscala/Function1;)Lscala/util/parsing/ast/Mappable$Mappable;;
NameAndType	ScopeIsMappable:(Lscala/util/parsing/ast/Binders$Scope;Lscala/Function1;)Lscala/util/parsing/ast/Mappable$Mappable;
InterfaceMethod	scala/util/parsing/ast/Binders.ScopeIsMappable:(Lscala/util/parsing/ast/Binders$Scope;Lscala/Function1;)Lscala/util/parsing/ast/Mappable$Mappable;
Asciz	(Lscala/util/parsing/ast/Binders$Scope<Lscala/util/parsing/ast/AbstractSyntax$NameElement;>;)Lscala/util/parsing/ast/Mappable$Mappable<Lscala/util/parsing/ast/Binders$Scope<Lscala/util/parsing/ast/AbstractSyntax$NameElement;>;>;;
Asciz	Signature;
Asciz	andThen;
Asciz	(Lscala/Function1;)Lscala/Function1;;
Asciz	(Lscala/Function1;Lscala/Function1;)Lscala/Function1;;
NameAndType	andThen:(Lscala/Function1;Lscala/Function1;)Lscala/Function1;
Method	scala/Function1$class.andThen:(Lscala/Function1;Lscala/Function1;)Lscala/Function1;
Asciz	g;
Asciz	Lscala/Function1;;
Asciz	compose;
NameAndType	compose:(Lscala/Function1;Lscala/Function1;)Lscala/Function1;
Method	scala/Function1$class.compose:(Lscala/Function1;Lscala/Function1;)Lscala/Function1;
Asciz	toString;
Asciz	()Ljava/lang/String;;
Asciz	(Lscala/Function1;)Ljava/lang/String;;
NameAndType	toString:(Lscala/Function1;)Ljava/lang/String;
Method	scala/Function1$class.toString:(Lscala/Function1;)Ljava/lang/String;
Asciz	Scala;
Asciz	InnerClasses;
Asciz	Scope;
Asciz	$anon$6;
Asciz	scala/util/parsing/ast/Mappable$Mappable;
class	scala/util/parsing/ast/Mappable$Mappable
Asciz	scala/util/parsing/ast/Mappable;
class	scala/util/parsing/ast/Mappable
Asciz	Mappable;
Asciz	$anonfun$gmap$7;
Asciz	$anonfun$apply$1;
Asciz	scala/Function1;
class	scala/Function1
Asciz	scala/ScalaObject;
class	scala/ScalaObject
Asciz	java/io/Serializable;
class	java/io/Serializable

{
public static final long serialVersionUID;
  Signature: J

public final scala.util.parsing.ast.Binders$$anon$6 $outer;
  Signature: Lscala/util/parsing/ast/Binders$$anon$6;

public static {};
  Signature: ()V
  Code:
   Stack=2, Locals=0, Args_size=0
	lconst_0
	putstatic	Field serialVersionUID:J
	return
  Labels:

public scala.util.parsing.ast.Binders$$anon$6$$anonfun$gmap$7(scala.util.parsing.ast.Binders$$anon$6);
  Signature: (Lscala/util/parsing/ast/Binders$$anon$6;)V
  Code:
   Stack=2, Locals=2, Args_size=2
	aload_1
	ifnonnull	l1 // aload_0
	new	class java/lang/NullPointerException
	dup
	invokespecial	Method java/lang/NullPointerException."<init>":()V
	athrow
l1	aload_0
	aload_1
	putfield	Field $outer:Lscala/util/parsing/ast/Binders$$anon$6;
	aload_0
	invokespecial	Method java/lang/Object."<init>":()V
	aload_0
	invokestatic	Method scala/Function1$class.$init$:(Lscala/Function1;)V
	return
  Labels:
   	l1 = 12 // aload_0
  LocalVariableTable: 
   Start  Length  Slot  Name   Signature
   0      26      0    this       Lscala/util/parsing/ast/Binders$$anon$6$$anonfun$gmap$7;
   0      26      1    $outer       Lscala/util/parsing/ast/Binders$$anon$6;


public final java.lang.Object apply(java.lang.Object);
  Signature: (Ljava/lang/Object;)Ljava/lang/Object;
  Code:
   Stack=2, Locals=3, Args_size=2
	aload_0
	getfield	Field $outer:Lscala/util/parsing/ast/Binders$$anon$6;
	astore_2
	aload_0
	aload_1
	checkcast	class scala/util/parsing/ast/Binders$Scope
	invokevirtual	Method apply:(Lscala/util/parsing/ast/Binders$Scope;)Lscala/util/parsing/ast/Mappable$Mappable;
	areturn
  Labels:
  LocalVariableTable: 
   Start  Length  Slot  Name   Signature
   0      14      0    this       Lscala/util/parsing/ast/Binders$$anon$6$$anonfun$gmap$7;
   5      9      1    v1       Ljava/lang/Object;


public scala.util.parsing.ast.Binders$$anon$6 scala$util$parsing$ast$Binders$$anon$$anonfun$$$outer();
  Signature: ()Lscala/util/parsing/ast/Binders$$anon$6;
  Code:
   Stack=1, Locals=1, Args_size=1
	aload_0
	getfield	Field $outer:Lscala/util/parsing/ast/Binders$$anon$6;
	areturn
  Labels:

public final scala.util.parsing.ast.Mappable$Mappable apply(scala.util.parsing.ast.Binders$Scope);
  Signature: (Lscala/util/parsing/ast/Binders$Scope;)Lscala/util/parsing/ast/Mappable$Mappable;
  Code:
   Stack=5, Locals=3, Args_size=2
	aload_0
	getfield	Field $outer:Lscala/util/parsing/ast/Binders$$anon$6;
	astore_2
	aload_0
	getfield	Field $outer:Lscala/util/parsing/ast/Binders$$anon$6;
	invokevirtual	Method scala/util/parsing/ast/Binders$$anon$6.scala$util$parsing$ast$Binders$$anon$$$outer:()Lscala/util/parsing/ast/Binders;
	aload_1
	new	class scala/util/parsing/ast/Binders$$anon$6$$anonfun$gmap$7$$anonfun$apply$1
	dup
	aload_0
	invokespecial	Method scala/util/parsing/ast/Binders$$anon$6$$anonfun$gmap$7$$anonfun$apply$1."<init>":(Lscala/util/parsing/ast/Binders$$anon$6$$anonfun$gmap$7;)V
	invokeinterface	InterfaceMethod scala/util/parsing/ast/Binders.ScopeIsMappable:(Lscala/util/parsing/ast/Binders$Scope;Lscala/Function1;)Lscala/util/parsing/ast/Mappable$Mappable;
	areturn
  Labels:
  LocalVariableTable: 
   Start  Length  Slot  Name   Signature
   0      27      0    this       Lscala/util/parsing/ast/Binders$$anon$6$$anonfun$gmap$7;

  Signature: length = 0x2
   00 3F 

public scala.Function1 andThen(scala.Function1);
  Signature: (Lscala/Function1;)Lscala/Function1;
  Code:
   Stack=2, Locals=2, Args_size=2
	aload_0
	aload_1
	invokestatic	Method scala/Function1$class.andThen:(Lscala/Function1;Lscala/Function1;)Lscala/Function1;
	areturn
  Labels:
  LocalVariableTable: 
   Start  Length  Slot  Name   Signature
   0      6      0    this       Lscala/util/parsing/ast/Binders$$anon$6$$anonfun$gmap$7;
   0      6      1    g       Lscala/Function1;


public scala.Function1 compose(scala.Function1);
  Signature: (Lscala/Function1;)Lscala/Function1;
  Code:
   Stack=2, Locals=2, Args_size=2
	aload_0
	aload_1
	invokestatic	Method scala/Function1$class.compose:(Lscala/Function1;Lscala/Function1;)Lscala/Function1;
	areturn
  Labels:
  LocalVariableTable: 
   Start  Length  Slot  Name   Signature
   0      6      0    this       Lscala/util/parsing/ast/Binders$$anon$6$$anonfun$gmap$7;
   0      6      1    g       Lscala/Function1;


public java.lang.String toString();
  Signature: ()Ljava/lang/String;
  Code:
   Stack=1, Locals=1, Args_size=1
	aload_0
	invokestatic	Method scala/Function1$class.toString:(Lscala/Function1;)Ljava/lang/String;
	areturn
  Labels:

}

