Compiled from "Binders.scala"
public final class scala.util.parsing.ast.Binders$UnderBinder$$anon$9 extends java.lang.Object implements scala.util.parsing.ast.Mappable$Mapper
  SourceFile: "Binders.scala"
  Scala: length = 0x
   
  InnerClass: 
   public abstract #80= #77 of #79; //Mapper=class scala/util/parsing/ast/Mappable$Mapper of class scala/util/parsing/ast/Mappable
   public #83= #47 of #82; //UnderBinder=class scala/util/parsing/ast/Binders$UnderBinder of class scala/util/parsing/ast/Binders
   public abstract #86= #41 of #85; //NameElement=class scala/util/parsing/ast/AbstractSyntax$NameElement of class scala/util/parsing/ast/AbstractSyntax
   public final #87= #17 of #47; //$anon$9=class scala/util/parsing/ast/Binders$UnderBinder$$anon$9 of class scala/util/parsing/ast/Binders$UnderBinder
  minor version: 0
  major version: 49
  Constant pool:
const #1 = Asciz	SourceFile;
const #2 = Asciz	Binders.scala;
const #3 = Asciz	subst$1;
const #4 = Asciz	Lscala/collection/immutable/Map;;
const #5 = Asciz	$outer;
const #6 = Asciz	Lscala/util/parsing/ast/Binders$UnderBinder;;
const #7 = Asciz	<init>;
const #8 = Asciz	(Lscala/util/parsing/ast/Binders$UnderBinder;Lscala/collection/immutable/Map;)V;
const #9 = Asciz	Code;
const #10 = Asciz	LineNumberTable;
const #11 = Asciz	java/lang/NullPointerException;
const #12 = class	#11;	//  java/lang/NullPointerException
const #13 = Asciz	()V;
const #14 = NameAndType	#7:#13;//  "<init>":()V
const #15 = Method	#12.#14;	//  java/lang/NullPointerException."<init>":()V
const #16 = Asciz	scala/util/parsing/ast/Binders$UnderBinder$$anon$9;
const #17 = class	#16;	//  scala/util/parsing/ast/Binders$UnderBinder$$anon$9
const #18 = NameAndType	#5:#6;//  $outer:Lscala/util/parsing/ast/Binders$UnderBinder;
const #19 = Field	#17.#18;	//  scala/util/parsing/ast/Binders$UnderBinder$$anon$9.$outer:Lscala/util/parsing/ast/Binders$UnderBinder;
const #20 = NameAndType	#3:#4;//  subst$1:Lscala/collection/immutable/Map;
const #21 = Field	#17.#20;	//  scala/util/parsing/ast/Binders$UnderBinder$$anon$9.subst$1:Lscala/collection/immutable/Map;
const #22 = Asciz	java/lang/Object;
const #23 = class	#22;	//  java/lang/Object
const #24 = Method	#23.#14;	//  java/lang/Object."<init>":()V
const #25 = Asciz	this;
const #26 = Asciz	Lscala/util/parsing/ast/Binders$UnderBinder$$anon$9;;
const #27 = Asciz	LocalVariableTable;
const #28 = Asciz	(Lscala/util/parsing/ast/Binders$UnderBinder<TbinderType;TelementT;>;)V;
const #29 = Asciz	Signature;
const #30 = Asciz	gd1$1;
const #31 = Asciz	(Lscala/util/parsing/ast/AbstractSyntax$NameElement;)Z;
const #32 = Asciz	scala/collection/MapLike;
const #33 = class	#32;	//  scala/collection/MapLike
const #34 = Asciz	contains;
const #35 = Asciz	(Ljava/lang/Object;)Z;
const #36 = NameAndType	#34:#35;//  contains:(Ljava/lang/Object;)Z
const #37 = InterfaceMethod	#33.#36;	//  scala/collection/MapLike.contains:(Ljava/lang/Object;)Z
const #38 = Asciz	apply;
const #39 = Asciz	(Ljava/lang/Object;Lscala/Function1;)Ljava/lang/Object;;
const #40 = Asciz	scala/util/parsing/ast/AbstractSyntax$NameElement;
const #41 = class	#40;	//  scala/util/parsing/ast/AbstractSyntax$NameElement
const #42 = Asciz	scala$util$parsing$ast$AbstractSyntax$NameElement$$$outer;
const #43 = Asciz	()Lscala/util/parsing/ast/AbstractSyntax;;
const #44 = NameAndType	#42:#43;//  scala$util$parsing$ast$AbstractSyntax$NameElement$$$outer:()Lscala/util/parsing/ast/AbstractSyntax;
const #45 = InterfaceMethod	#41.#44;	//  scala/util/parsing/ast/AbstractSyntax$NameElement.scala$util$parsing$ast$AbstractSyntax$NameElement$$$outer:()Lscala/util/parsing/ast/AbstractSyntax;
const #46 = Asciz	scala/util/parsing/ast/Binders$UnderBinder;
const #47 = class	#46;	//  scala/util/parsing/ast/Binders$UnderBinder
const #48 = Asciz	scala$util$parsing$ast$Binders$UnderBinder$$$outer;
const #49 = Asciz	()Lscala/util/parsing/ast/Binders;;
const #50 = NameAndType	#48:#49;//  scala$util$parsing$ast$Binders$UnderBinder$$$outer:()Lscala/util/parsing/ast/Binders;
const #51 = Method	#47.#50;	//  scala/util/parsing/ast/Binders$UnderBinder.scala$util$parsing$ast$Binders$UnderBinder$$$outer:()Lscala/util/parsing/ast/Binders;
const #52 = NameAndType	#30:#31;//  gd1$1:(Lscala/util/parsing/ast/AbstractSyntax$NameElement;)Z
const #53 = Method	#17.#52;	//  scala/util/parsing/ast/Binders$UnderBinder$$anon$9.gd1$1:(Lscala/util/parsing/ast/AbstractSyntax$NameElement;)Z
const #54 = Asciz	get;
const #55 = Asciz	(Ljava/lang/Object;)Lscala/Option;;
const #56 = NameAndType	#54:#55;//  get:(Ljava/lang/Object;)Lscala/Option;
const #57 = InterfaceMethod	#33.#56;	//  scala/collection/MapLike.get:(Ljava/lang/Object;)Lscala/Option;
const #58 = Asciz	scala/MatchError;
const #59 = class	#58;	//  scala/MatchError
const #60 = Asciz	toString;
const #61 = Asciz	()Ljava/lang/String;;
const #62 = NameAndType	#60:#61;//  toString:()Ljava/lang/String;
const #63 = Method	#23.#62;	//  java/lang/Object.toString:()Ljava/lang/String;
const #64 = Asciz	(Ljava/lang/String;)V;
const #65 = NameAndType	#7:#64;//  "<init>":(Ljava/lang/String;)V
const #66 = Method	#59.#65;	//  scala/MatchError."<init>":(Ljava/lang/String;)V
const #67 = Asciz	x;
const #68 = Asciz	Ljava/lang/Object;;
const #69 = Asciz	evidence$6;
const #70 = Asciz	Lscala/Function1;;
const #71 = Asciz	temp6;
const #72 = Asciz	Lscala/util/parsing/ast/AbstractSyntax$NameElement;;
const #73 = Asciz	<t:Ljava/lang/Object;>(Tt;Lscala/Function1<Tt;Lscala/util/parsing/ast/Mappable$Mappable<Tt;>;>;)Tt;;
const #74 = Asciz	Scala;
const #75 = Asciz	InnerClasses;
const #76 = Asciz	scala/util/parsing/ast/Mappable$Mapper;
const #77 = class	#76;	//  scala/util/parsing/ast/Mappable$Mapper
const #78 = Asciz	scala/util/parsing/ast/Mappable;
const #79 = class	#78;	//  scala/util/parsing/ast/Mappable
const #80 = Asciz	Mapper;
const #81 = Asciz	scala/util/parsing/ast/Binders;
const #82 = class	#81;	//  scala/util/parsing/ast/Binders
const #83 = Asciz	UnderBinder;
const #84 = Asciz	scala/util/parsing/ast/AbstractSyntax;
const #85 = class	#84;	//  scala/util/parsing/ast/AbstractSyntax
const #86 = Asciz	NameElement;
const #87 = Asciz	$anon$9;

{
public scala.util.parsing.ast.Binders$UnderBinder$$anon$9(scala.util.parsing.ast.Binders$UnderBinder, scala.collection.immutable.Map);
  Code:
   Stack=2, Locals=3, Args_size=3
   0:	aload_1
   1:	ifnonnull	12
   4:	new	#12; //class java/lang/NullPointerException
   7:	dup
   8:	invokespecial	#15; //Method java/lang/NullPointerException."<init>":()V
   11:	athrow
   12:	aload_0
   13:	aload_1
   14:	putfield	#19; //Field $outer:Lscala/util/parsing/ast/Binders$UnderBinder;
   17:	aload_0
   18:	aload_2
   19:	putfield	#21; //Field subst$1:Lscala/collection/immutable/Map;
   22:	aload_0
   23:	invokespecial	#24; //Method java/lang/Object."<init>":()V
   26:	return
  LineNumberTable: 
   line 251: 0

  LocalVariableTable: 
   Start  Length  Slot  Name   Signature
   0      27      0    this       Lscala/util/parsing/ast/Binders$UnderBinder$$anon$9;
   0      27      1    $outer       Lscala/util/parsing/ast/Binders$UnderBinder;

  Signature: length = 0x2
   00 1C 

public java.lang.Object apply(java.lang.Object, scala.Function1);
  Code:
   Stack=3, Locals=5, Args_size=3
   0:	aload_1
   1:	instanceof	#41; //class scala/util/parsing/ast/AbstractSyntax$NameElement
   4:	ifeq	74
   7:	aload_1
   8:	checkcast	#41; //class scala/util/parsing/ast/AbstractSyntax$NameElement
   11:	invokeinterface	#45,  1; //InterfaceMethod scala/util/parsing/ast/AbstractSyntax$NameElement.scala$util$parsing$ast$AbstractSyntax$NameElement$$$outer:()Lscala/util/parsing/ast/AbstractSyntax;
   16:	aload_0
   17:	getfield	#19; //Field $outer:Lscala/util/parsing/ast/Binders$UnderBinder;
   20:	invokevirtual	#51; //Method scala/util/parsing/ast/Binders$UnderBinder.scala$util$parsing$ast$Binders$UnderBinder$$$outer:()Lscala/util/parsing/ast/Binders;
   23:	if_acmpne	74
   26:	aload_1
   27:	checkcast	#41; //class scala/util/parsing/ast/AbstractSyntax$NameElement
   30:	astore_3
   31:	aload_0
   32:	aload_3
   33:	invokespecial	#53; //Method gd1$1:(Lscala/util/parsing/ast/AbstractSyntax$NameElement;)Z
   36:	ifeq	52
   39:	aload_0
   40:	getfield	#21; //Field subst$1:Lscala/collection/immutable/Map;
   43:	aload_3
   44:	invokeinterface	#57,  2; //InterfaceMethod scala/collection/MapLike.get:(Ljava/lang/Object;)Lscala/Option;
   49:	goto	83
   52:	iconst_1
   53:	ifeq	62
   56:	aload_3
   57:	astore	4
   59:	goto	81
   62:	new	#59; //class scala/MatchError
   65:	dup
   66:	aload_1
   67:	invokevirtual	#63; //Method java/lang/Object.toString:()Ljava/lang/String;
   70:	invokespecial	#66; //Method scala/MatchError."<init>":(Ljava/lang/String;)V
   73:	athrow
   74:	iconst_1
   75:	ifeq	84
   78:	aload_1
   79:	astore	4
   81:	aload	4
   83:	areturn
   84:	new	#59; //class scala/MatchError
   87:	dup
   88:	aload_1
   89:	invokevirtual	#63; //Method java/lang/Object.toString:()Ljava/lang/String;
   92:	invokespecial	#66; //Method scala/MatchError."<init>":(Ljava/lang/String;)V
   95:	athrow
  LineNumberTable: 
   line 251: 0
   line 252: 39
   line 21: 52
   line 254: 56
   line 251: 62
   line 21: 74
   line 254: 78
   line 251: 83

  LocalVariableTable: 
   Start  Length  Slot  Name   Signature
   0      96      0    this       Lscala/util/parsing/ast/Binders$UnderBinder$$anon$9;
   0      96      1    x       Ljava/lang/Object;
   0      96      2    evidence$6       Lscala/Function1;
   31      43      3    temp6       Lscala/util/parsing/ast/AbstractSyntax$NameElement;
   81      2      3    temp6       Lscala/util/parsing/ast/AbstractSyntax$NameElement;
   52      4      4    x       Ljava/lang/Object;
   59      3      4    x       Ljava/lang/Object;
   56      18      4    x       Ljava/lang/Object;
   81      2      4    x       Ljava/lang/Object;

  Signature: length = 0x2
   00 49 

}

