Compiled from "Binders.scala"
public final class scala.util.parsing.ast.Binders$$anonfun$sequence$2 extends java.lang.Object implements scala.Function1,scala.ScalaObject,java.io.Serializable
  SourceFile: "Binders.scala"
  Scala: length = 0x
   
  InnerClass: 
   public UnderBinder=class scala/util/parsing/ast/Binders$UnderBinder of class scala/util/parsing/ast/Binders
   public final $anonfun$sequence$2=class scala/util/parsing/ast/Binders$$anonfun$sequence$2 of class scala/util/parsing/ast/Binders
  minor version: 0
  major version: 49
  Constant pool:
Asciz	SourceFile;
Asciz	Binders.scala;
Asciz	<clinit>;
Asciz	()V;
Asciz	Code;
Asciz	serialVersionUID;
Asciz	J;
Asciz	scala/util/parsing/ast/Binders$$anonfun$sequence$2;
class	scala/util/parsing/ast/Binders$$anonfun$sequence$2
NameAndType	serialVersionUID:J
Field	scala/util/parsing/ast/Binders$$anonfun$sequence$2.serialVersionUID:J
Asciz	<init>;
Asciz	(Lscala/util/parsing/ast/Binders;)V;
Asciz	LineNumberTable;
Asciz	java/lang/Object;
class	java/lang/Object
NameAndType	"<init>":()V
Method	java/lang/Object."<init>":()V
Asciz	scala/Function1$class;
class	scala/Function1$class
Asciz	$init$;
Asciz	(Lscala/Function1;)V;
NameAndType	$init$:(Lscala/Function1;)V
Method	scala/Function1$class.$init$:(Lscala/Function1;)V
Asciz	this;
Asciz	Lscala/util/parsing/ast/Binders$$anonfun$sequence$2;;
Asciz	$outer;
Asciz	Lscala/util/parsing/ast/Binders;;
Asciz	LocalVariableTable;
Asciz	apply;
Asciz	(Ljava/lang/Object;)Ljava/lang/Object;;
Asciz	scala/util/parsing/ast/Binders$UnderBinder;
class	scala/util/parsing/ast/Binders$UnderBinder
Asciz	(Lscala/util/parsing/ast/Binders$UnderBinder;)Ljava/lang/Object;;
NameAndType	apply:(Lscala/util/parsing/ast/Binders$UnderBinder;)Ljava/lang/Object;
Method	scala/util/parsing/ast/Binders$$anonfun$sequence$2.apply:(Lscala/util/parsing/ast/Binders$UnderBinder;)Ljava/lang/Object;
Asciz	v1;
Asciz	Ljava/lang/Object;;
Asciz	scala$util$parsing$ast$Binders$$element;
Asciz	()Ljava/lang/Object;;
NameAndType	scala$util$parsing$ast$Binders$$element:()Ljava/lang/Object;
Method	scala/util/parsing/ast/Binders$UnderBinder.scala$util$parsing$ast$Binders$$element:()Ljava/lang/Object;
Asciz	(Lscala/util/parsing/ast/Binders$UnderBinder<Tbt;Tst;>;)Tst;;
Asciz	Signature;
Asciz	andThen;
Asciz	(Lscala/Function1;)Lscala/Function1;;
Asciz	(Lscala/Function1;Lscala/Function1;)Lscala/Function1;;
NameAndType	andThen:(Lscala/Function1;Lscala/Function1;)Lscala/Function1;
Method	scala/Function1$class.andThen:(Lscala/Function1;Lscala/Function1;)Lscala/Function1;
Asciz	g;
Asciz	Lscala/Function1;;
Asciz	compose;
NameAndType	compose:(Lscala/Function1;Lscala/Function1;)Lscala/Function1;
Method	scala/Function1$class.compose:(Lscala/Function1;Lscala/Function1;)Lscala/Function1;
Asciz	toString;
Asciz	()Ljava/lang/String;;
Asciz	(Lscala/Function1;)Ljava/lang/String;;
NameAndType	toString:(Lscala/Function1;)Ljava/lang/String;
Method	scala/Function1$class.toString:(Lscala/Function1;)Ljava/lang/String;
Asciz	Scala;
Asciz	InnerClasses;
Asciz	scala/util/parsing/ast/Binders;
class	scala/util/parsing/ast/Binders
Asciz	UnderBinder;
Asciz	$anonfun$sequence$2;
Asciz	scala/Function1;
class	scala/Function1
Asciz	scala/ScalaObject;
class	scala/ScalaObject
Asciz	java/io/Serializable;
class	java/io/Serializable

{
public static final long serialVersionUID;
  Signature: J

public static {};
  Signature: ()V
  Code:
   Stack=2, Locals=0, Args_size=0
	lconst_0
	putstatic	Field serialVersionUID:J
	return
  Labels:

public scala.util.parsing.ast.Binders$$anonfun$sequence$2(scala.util.parsing.ast.Binders);
  Signature: (Lscala/util/parsing/ast/Binders;)V
  Code:
   Stack=1, Locals=2, Args_size=2
	aload_0
	invokespecial	Method java/lang/Object."<init>":()V
	aload_0
	invokestatic	Method scala/Function1$class.$init$:(Lscala/Function1;)V
	return
  Labels:
  LocalVariableTable: 
   Start  Length  Slot  Name   Signature
   0      9      0    this       Lscala/util/parsing/ast/Binders$$anonfun$sequence$2;
   0      9      1    $outer       Lscala/util/parsing/ast/Binders;


public final java.lang.Object apply(java.lang.Object);
  Signature: (Ljava/lang/Object;)Ljava/lang/Object;
  Code:
   Stack=2, Locals=2, Args_size=2
	aload_0
	aload_1
	checkcast	class scala/util/parsing/ast/Binders$UnderBinder
	invokevirtual	Method apply:(Lscala/util/parsing/ast/Binders$UnderBinder;)Ljava/lang/Object;
	areturn
  Labels:
  LocalVariableTable: 
   Start  Length  Slot  Name   Signature
   0      9      0    this       Lscala/util/parsing/ast/Binders$$anonfun$sequence$2;
   0      9      1    v1       Ljava/lang/Object;


public final java.lang.Object apply(scala.util.parsing.ast.Binders$UnderBinder);
  Signature: (Lscala/util/parsing/ast/Binders$UnderBinder;)Ljava/lang/Object;
  Code:
   Stack=1, Locals=2, Args_size=2
	aload_1
	invokevirtual	Method scala/util/parsing/ast/Binders$UnderBinder.scala$util$parsing$ast$Binders$$element:()Ljava/lang/Object;
	areturn
  Labels:
  Signature: length = 0x2
   00 2B 

public scala.Function1 andThen(scala.Function1);
  Signature: (Lscala/Function1;)Lscala/Function1;
  Code:
   Stack=2, Locals=2, Args_size=2
	aload_0
	aload_1
	invokestatic	Method scala/Function1$class.andThen:(Lscala/Function1;Lscala/Function1;)Lscala/Function1;
	areturn
  Labels:
  LocalVariableTable: 
   Start  Length  Slot  Name   Signature
   0      6      0    this       Lscala/util/parsing/ast/Binders$$anonfun$sequence$2;
   0      6      1    g       Lscala/Function1;


public scala.Function1 compose(scala.Function1);
  Signature: (Lscala/Function1;)Lscala/Function1;
  Code:
   Stack=2, Locals=2, Args_size=2
	aload_0
	aload_1
	invokestatic	Method scala/Function1$class.compose:(Lscala/Function1;Lscala/Function1;)Lscala/Function1;
	areturn
  Labels:
  LocalVariableTable: 
   Start  Length  Slot  Name   Signature
   0      6      0    this       Lscala/util/parsing/ast/Binders$$anonfun$sequence$2;
   0      6      1    g       Lscala/Function1;


public java.lang.String toString();
  Signature: ()Ljava/lang/String;
  Code:
   Stack=1, Locals=1, Args_size=1
	aload_0
	invokestatic	Method scala/Function1$class.toString:(Lscala/Function1;)Ljava/lang/String;
	areturn
  Labels:

}

