Compiled from "Binders.scala"
public final class scala.util.parsing.ast.Binders$$anonfun$unsequence$1 extends java.lang.Object implements scala.Function1,scala.ScalaObject,java.io.Serializable
  SourceFile: "Binders.scala"
  Scala: length = 0x
   
  InnerClass: 
   public Scope=class scala/util/parsing/ast/Binders$Scope of class scala/util/parsing/ast/Binders
   public UnderBinder=class scala/util/parsing/ast/Binders$UnderBinder of class scala/util/parsing/ast/Binders
   public final $anonfun$unsequence$1=class scala/util/parsing/ast/Binders$$anonfun$unsequence$1 of class scala/util/parsing/ast/Binders
  minor version: 0
  major version: 49
  Constant pool:
Asciz	SourceFile;
Asciz	Binders.scala;
Asciz	<clinit>;
Asciz	()V;
Asciz	Code;
Asciz	serialVersionUID;
Asciz	J;
Asciz	scala/util/parsing/ast/Binders$$anonfun$unsequence$1;
class	scala/util/parsing/ast/Binders$$anonfun$unsequence$1
NameAndType	serialVersionUID:J
Field	scala/util/parsing/ast/Binders$$anonfun$unsequence$1.serialVersionUID:J
Asciz	evidence$14$1;
Asciz	Lscala/Function1;;
Asciz	orig$1;
Asciz	Lscala/util/parsing/ast/Binders$UnderBinder;;
Asciz	$outer;
Asciz	Lscala/util/parsing/ast/Binders;;
Asciz	<init>;
Asciz	(Lscala/util/parsing/ast/Binders;Lscala/util/parsing/ast/Binders$UnderBinder;Lscala/Function1;)V;
Asciz	LineNumberTable;
Asciz	java/lang/NullPointerException;
class	java/lang/NullPointerException
NameAndType	"<init>":()V
Method	java/lang/NullPointerException."<init>":()V
NameAndType	$outer:Lscala/util/parsing/ast/Binders;
Field	scala/util/parsing/ast/Binders$$anonfun$unsequence$1.$outer:Lscala/util/parsing/ast/Binders;
NameAndType	orig$1:Lscala/util/parsing/ast/Binders$UnderBinder;
Field	scala/util/parsing/ast/Binders$$anonfun$unsequence$1.orig$1:Lscala/util/parsing/ast/Binders$UnderBinder;
NameAndType	evidence$14$1:Lscala/Function1;
Field	scala/util/parsing/ast/Binders$$anonfun$unsequence$1.evidence$14$1:Lscala/Function1;
Asciz	java/lang/Object;
class	java/lang/Object
Method	java/lang/Object."<init>":()V
Asciz	scala/Function1$class;
class	scala/Function1$class
Asciz	$init$;
Asciz	(Lscala/Function1;)V;
NameAndType	$init$:(Lscala/Function1;)V
Method	scala/Function1$class.$init$:(Lscala/Function1;)V
Asciz	this;
Asciz	Lscala/util/parsing/ast/Binders$$anonfun$unsequence$1;;
Asciz	LocalVariableTable;
Asciz	apply;
Asciz	(Ljava/lang/Object;)Ljava/lang/Object;;
Asciz	(Ljava/lang/Object;)Lscala/util/parsing/ast/Binders$UnderBinder;;
NameAndType	apply:(Ljava/lang/Object;)Lscala/util/parsing/ast/Binders$UnderBinder;
Method	scala/util/parsing/ast/Binders$$anonfun$unsequence$1.apply:(Ljava/lang/Object;)Lscala/util/parsing/ast/Binders$UnderBinder;
Asciz	v1;
Asciz	Ljava/lang/Object;;
Asciz	scala/util/parsing/ast/Binders;
class	scala/util/parsing/ast/Binders
Asciz	UnderBinder;
Asciz	()Lscala/util/parsing/ast/Binders$UnderBinder$;;
NameAndType	UnderBinder:()Lscala/util/parsing/ast/Binders$UnderBinder$;
InterfaceMethod	scala/util/parsing/ast/Binders.UnderBinder:()Lscala/util/parsing/ast/Binders$UnderBinder$;
Asciz	scala/util/parsing/ast/Binders$UnderBinder;
class	scala/util/parsing/ast/Binders$UnderBinder
Asciz	scope;
Asciz	()Lscala/util/parsing/ast/Binders$Scope;;
NameAndType	scope:()Lscala/util/parsing/ast/Binders$Scope;
Method	scala/util/parsing/ast/Binders$UnderBinder.scope:()Lscala/util/parsing/ast/Binders$Scope;
Asciz	scala/util/parsing/ast/Binders$UnderBinder$;
class	scala/util/parsing/ast/Binders$UnderBinder$
Field	scala/util/parsing/ast/Binders$UnderBinder$.$outer:Lscala/util/parsing/ast/Binders;
Asciz	(Lscala/util/parsing/ast/Binders;Lscala/util/parsing/ast/Binders$Scope;Ljava/lang/Object;Lscala/Function1;)V;
NameAndType	"<init>":(Lscala/util/parsing/ast/Binders;Lscala/util/parsing/ast/Binders$Scope;Ljava/lang/Object;Lscala/Function1;)V
Method	scala/util/parsing/ast/Binders$UnderBinder."<init>":(Lscala/util/parsing/ast/Binders;Lscala/util/parsing/ast/Binders$Scope;Ljava/lang/Object;Lscala/Function1;)V
Asciz	sc;
Asciz	(Tst;)Lscala/util/parsing/ast/Binders$UnderBinder<Tbt;Tst;>;;
Asciz	Signature;
Asciz	andThen;
Asciz	(Lscala/Function1;)Lscala/Function1;;
Asciz	(Lscala/Function1;Lscala/Function1;)Lscala/Function1;;
NameAndType	andThen:(Lscala/Function1;Lscala/Function1;)Lscala/Function1;
Method	scala/Function1$class.andThen:(Lscala/Function1;Lscala/Function1;)Lscala/Function1;
Asciz	g;
Asciz	compose;
NameAndType	compose:(Lscala/Function1;Lscala/Function1;)Lscala/Function1;
Method	scala/Function1$class.compose:(Lscala/Function1;Lscala/Function1;)Lscala/Function1;
Asciz	toString;
Asciz	()Ljava/lang/String;;
Asciz	(Lscala/Function1;)Ljava/lang/String;;
NameAndType	toString:(Lscala/Function1;)Ljava/lang/String;
Method	scala/Function1$class.toString:(Lscala/Function1;)Ljava/lang/String;
Asciz	Scala;
Asciz	InnerClasses;
Asciz	scala/util/parsing/ast/Binders$Scope;
class	scala/util/parsing/ast/Binders$Scope
Asciz	Scope;
Asciz	$anonfun$unsequence$1;
Asciz	scala/Function1;
class	scala/Function1
Asciz	scala/ScalaObject;
class	scala/ScalaObject
Asciz	java/io/Serializable;
class	java/io/Serializable

{
public static final long serialVersionUID;
  Signature: J

private final scala.Function1 evidence$14$1;
  Signature: Lscala/Function1;

private final scala.util.parsing.ast.Binders$UnderBinder orig$1;
  Signature: Lscala/util/parsing/ast/Binders$UnderBinder;

private final scala.util.parsing.ast.Binders $outer;
  Signature: Lscala/util/parsing/ast/Binders;

public static {};
  Signature: ()V
  Code:
   Stack=2, Locals=0, Args_size=0
	lconst_0
	putstatic	Field serialVersionUID:J
	return
  Labels:

public scala.util.parsing.ast.Binders$$anonfun$unsequence$1(scala.util.parsing.ast.Binders, scala.util.parsing.ast.Binders$UnderBinder, scala.Function1);
  Signature: (Lscala/util/parsing/ast/Binders;Lscala/util/parsing/ast/Binders$UnderBinder;Lscala/Function1;)V
  Code:
   Stack=2, Locals=4, Args_size=4
	aload_1
	ifnonnull	l1 // aload_0
	new	class java/lang/NullPointerException
	dup
	invokespecial	Method java/lang/NullPointerException."<init>":()V
	athrow
l1	aload_0
	aload_1
	putfield	Field $outer:Lscala/util/parsing/ast/Binders;
	aload_0
	aload_2
	putfield	Field orig$1:Lscala/util/parsing/ast/Binders$UnderBinder;
	aload_0
	aload_3
	putfield	Field evidence$14$1:Lscala/Function1;
	aload_0
	invokespecial	Method java/lang/Object."<init>":()V
	aload_0
	invokestatic	Method scala/Function1$class.$init$:(Lscala/Function1;)V
	return
  Labels:
   	l1 = 12 // aload_0
  LocalVariableTable: 
   Start  Length  Slot  Name   Signature
   0      36      0    this       Lscala/util/parsing/ast/Binders$$anonfun$unsequence$1;
   0      36      1    $outer       Lscala/util/parsing/ast/Binders;


public final java.lang.Object apply(java.lang.Object);
  Signature: (Ljava/lang/Object;)Ljava/lang/Object;
  Code:
   Stack=2, Locals=3, Args_size=2
	aload_0
	getfield	Field $outer:Lscala/util/parsing/ast/Binders;
	astore_2
	aload_0
	aload_1
	invokevirtual	Method apply:(Ljava/lang/Object;)Lscala/util/parsing/ast/Binders$UnderBinder;
	areturn
  Labels:
  LocalVariableTable: 
   Start  Length  Slot  Name   Signature
   0      11      0    this       Lscala/util/parsing/ast/Binders$$anonfun$unsequence$1;
   5      6      1    v1       Ljava/lang/Object;


public final scala.util.parsing.ast.Binders$UnderBinder apply(java.lang.Object);
  Signature: (Ljava/lang/Object;)Lscala/util/parsing/ast/Binders$UnderBinder;
  Code:
   Stack=6, Locals=6, Args_size=2
	aload_0
	getfield	Field $outer:Lscala/util/parsing/ast/Binders;
	astore	5
	aload_0
	getfield	Field $outer:Lscala/util/parsing/ast/Binders;
	invokeinterface	InterfaceMethod scala/util/parsing/ast/Binders.UnderBinder:()Lscala/util/parsing/ast/Binders$UnderBinder$;
	aload_0
	getfield	Field orig$1:Lscala/util/parsing/ast/Binders$UnderBinder;
	invokevirtual	Method scala/util/parsing/ast/Binders$UnderBinder.scope:()Lscala/util/parsing/ast/Binders$Scope;
	aload_0
	getfield	Field evidence$14$1:Lscala/Function1;
	astore	4
	astore_3
	astore_2
	new	class scala/util/parsing/ast/Binders$UnderBinder
	dup
	aload_2
	getfield	Field scala/util/parsing/ast/Binders$UnderBinder$.$outer:Lscala/util/parsing/ast/Binders;
	aload_3
	aload_1
	aload	4
	invokespecial	Method scala/util/parsing/ast/Binders$UnderBinder."<init>":(Lscala/util/parsing/ast/Binders;Lscala/util/parsing/ast/Binders$Scope;Ljava/lang/Object;Lscala/Function1;)V
	areturn
  Labels:
  LocalVariableTable: 
   Start  Length  Slot  Name   Signature
   0      46      0    this       Lscala/util/parsing/ast/Binders$$anonfun$unsequence$1;
   6      40      1    sc       Ljava/lang/Object;

  Signature: length = 0x2
   00 45 

public scala.Function1 andThen(scala.Function1);
  Signature: (Lscala/Function1;)Lscala/Function1;
  Code:
   Stack=2, Locals=2, Args_size=2
	aload_0
	aload_1
	invokestatic	Method scala/Function1$class.andThen:(Lscala/Function1;Lscala/Function1;)Lscala/Function1;
	areturn
  Labels:
  LocalVariableTable: 
   Start  Length  Slot  Name   Signature
   0      6      0    this       Lscala/util/parsing/ast/Binders$$anonfun$unsequence$1;
   0      6      1    g       Lscala/Function1;


public scala.Function1 compose(scala.Function1);
  Signature: (Lscala/Function1;)Lscala/Function1;
  Code:
   Stack=2, Locals=2, Args_size=2
	aload_0
	aload_1
	invokestatic	Method scala/Function1$class.compose:(Lscala/Function1;Lscala/Function1;)Lscala/Function1;
	areturn
  Labels:
  LocalVariableTable: 
   Start  Length  Slot  Name   Signature
   0      6      0    this       Lscala/util/parsing/ast/Binders$$anonfun$unsequence$1;
   0      6      1    g       Lscala/Function1;


public java.lang.String toString();
  Signature: ()Ljava/lang/String;
  Code:
   Stack=1, Locals=1, Args_size=1
	aload_0
	invokestatic	Method scala/Function1$class.toString:(Lscala/Function1;)Ljava/lang/String;
	areturn
  Labels:

}

