Compiled from "Binders.scala"
public final class scala.util.parsing.ast.Binders$Scope$$anonfun$indexFor$1 extends java.lang.Object implements scala.Function1,scala.ScalaObject,java.io.Serializable
  SourceFile: "Binders.scala"
  Scala: length = 0x
   
  InnerClass: 
   public #153= #150 of #152; //Scope=class scala/util/parsing/ast/Binders$Scope of class scala/util/parsing/ast/Binders
   public abstract #156= #59 of #155; //NameElement=class scala/util/parsing/ast/AbstractSyntax$NameElement of class scala/util/parsing/ast/AbstractSyntax
   public final #157= #9 of #150; //$anonfun$indexFor$1=class scala/util/parsing/ast/Binders$Scope$$anonfun$indexFor$1 of class scala/util/parsing/ast/Binders$Scope
  minor version: 0
  major version: 49
  Constant pool:
const #1 = Asciz	SourceFile;
const #2 = Asciz	Binders.scala;
const #3 = Asciz	<clinit>;
const #4 = Asciz	()V;
const #5 = Asciz	Code;
const #6 = Asciz	serialVersionUID;
const #7 = Asciz	J;
const #8 = Asciz	scala/util/parsing/ast/Binders$Scope$$anonfun$indexFor$1;
const #9 = class	#8;	//  scala/util/parsing/ast/Binders$Scope$$anonfun$indexFor$1
const #10 = NameAndType	#6:#7;//  serialVersionUID:J
const #11 = Field	#9.#10;	//  scala/util/parsing/ast/Binders$Scope$$anonfun$indexFor$1.serialVersionUID:J
const #12 = Asciz	nonLocalReturnKey1$1;
const #13 = Asciz	Ljava/lang/Object;;
const #14 = Asciz	b$1;
const #15 = Asciz	Lscala/util/parsing/ast/AbstractSyntax$NameElement;;
const #16 = Asciz	<init>;
const #17 = Asciz	(Lscala/util/parsing/ast/Binders$Scope;Lscala/util/parsing/ast/AbstractSyntax$NameElement;Ljava/lang/Object;)V;
const #18 = Asciz	LineNumberTable;
const #19 = NameAndType	#14:#15;//  b$1:Lscala/util/parsing/ast/AbstractSyntax$NameElement;
const #20 = Field	#9.#19;	//  scala/util/parsing/ast/Binders$Scope$$anonfun$indexFor$1.b$1:Lscala/util/parsing/ast/AbstractSyntax$NameElement;
const #21 = NameAndType	#12:#13;//  nonLocalReturnKey1$1:Ljava/lang/Object;
const #22 = Field	#9.#21;	//  scala/util/parsing/ast/Binders$Scope$$anonfun$indexFor$1.nonLocalReturnKey1$1:Ljava/lang/Object;
const #23 = Asciz	java/lang/Object;
const #24 = class	#23;	//  java/lang/Object
const #25 = NameAndType	#16:#4;//  "<init>":()V
const #26 = Method	#24.#25;	//  java/lang/Object."<init>":()V
const #27 = Asciz	scala/Function1$class;
const #28 = class	#27;	//  scala/Function1$class
const #29 = Asciz	$init$;
const #30 = Asciz	(Lscala/Function1;)V;
const #31 = NameAndType	#29:#30;//  $init$:(Lscala/Function1;)V
const #32 = Method	#28.#31;	//  scala/Function1$class.$init$:(Lscala/Function1;)V
const #33 = Asciz	this;
const #34 = Asciz	Lscala/util/parsing/ast/Binders$Scope$$anonfun$indexFor$1;;
const #35 = Asciz	$outer;
const #36 = Asciz	Lscala/util/parsing/ast/Binders$Scope;;
const #37 = Asciz	LocalVariableTable;
const #38 = Asciz	(Lscala/util/parsing/ast/Binders$Scope<TbinderType;>;)V;
const #39 = Asciz	Signature;
const #40 = Asciz	apply;
const #41 = Asciz	(Ljava/lang/Object;)Ljava/lang/Object;;
const #42 = Asciz	scala/Tuple2;
const #43 = class	#42;	//  scala/Tuple2
const #44 = Asciz	(Lscala/Tuple2;)V;
const #45 = NameAndType	#40:#44;//  apply:(Lscala/Tuple2;)V
const #46 = Method	#9.#45;	//  scala/util/parsing/ast/Binders$Scope$$anonfun$indexFor$1.apply:(Lscala/Tuple2;)V
const #47 = Asciz	scala/runtime/BoxedUnit;
const #48 = class	#47;	//  scala/runtime/BoxedUnit
const #49 = Asciz	UNIT;
const #50 = Asciz	Lscala/runtime/BoxedUnit;;
const #51 = NameAndType	#49:#50;//  UNIT:Lscala/runtime/BoxedUnit;
const #52 = Field	#48.#51;	//  scala/runtime/BoxedUnit.UNIT:Lscala/runtime/BoxedUnit;
const #53 = Asciz	v1;
const #54 = Asciz	_1;
const #55 = Asciz	()Ljava/lang/Object;;
const #56 = NameAndType	#54:#55;//  _1:()Ljava/lang/Object;
const #57 = Method	#43.#56;	//  scala/Tuple2._1:()Ljava/lang/Object;
const #58 = Asciz	scala/util/parsing/ast/AbstractSyntax$NameElement;
const #59 = class	#58;	//  scala/util/parsing/ast/AbstractSyntax$NameElement
const #60 = Asciz	_2;
const #61 = NameAndType	#60:#55;//  _2:()Ljava/lang/Object;
const #62 = Method	#43.#61;	//  scala/Tuple2._2:()Ljava/lang/Object;
const #63 = Asciz	scala/runtime/BoxesRunTime;
const #64 = class	#63;	//  scala/runtime/BoxesRunTime
const #65 = Asciz	unboxToInt;
const #66 = Asciz	(Ljava/lang/Object;)I;
const #67 = NameAndType	#65:#66;//  unboxToInt:(Ljava/lang/Object;)I
const #68 = Method	#64.#67;	//  scala/runtime/BoxesRunTime.unboxToInt:(Ljava/lang/Object;)I
const #69 = Asciz	name;
const #70 = Asciz	()Ljava/lang/String;;
const #71 = NameAndType	#69:#70;//  name:()Ljava/lang/String;
const #72 = InterfaceMethod	#59.#71;	//  scala/util/parsing/ast/AbstractSyntax$NameElement.name:()Ljava/lang/String;
const #73 = Asciz	equals;
const #74 = Asciz	(Ljava/lang/Object;)Z;
const #75 = NameAndType	#73:#74;//  equals:(Ljava/lang/Object;)Z
const #76 = Method	#24.#75;	//  java/lang/Object.equals:(Ljava/lang/Object;)Z
const #77 = Asciz	scala/runtime/NonLocalReturnException;
const #78 = class	#77;	//  scala/runtime/NonLocalReturnException
const #79 = Asciz	scala/Some;
const #80 = class	#79;	//  scala/Some
const #81 = Asciz	boxToInteger;
const #82 = Asciz	(I)Ljava/lang/Integer;;
const #83 = NameAndType	#81:#82;//  boxToInteger:(I)Ljava/lang/Integer;
const #84 = Method	#64.#83;	//  scala/runtime/BoxesRunTime.boxToInteger:(I)Ljava/lang/Integer;
const #85 = Asciz	(Ljava/lang/Object;)V;
const #86 = NameAndType	#16:#85;//  "<init>":(Ljava/lang/Object;)V
const #87 = Method	#80.#86;	//  scala/Some."<init>":(Ljava/lang/Object;)V
const #88 = Asciz	(Ljava/lang/Object;Ljava/lang/Object;)V;
const #89 = NameAndType	#16:#88;//  "<init>":(Ljava/lang/Object;Ljava/lang/Object;)V
const #90 = Method	#78.#89;	//  scala/runtime/NonLocalReturnException."<init>":(Ljava/lang/Object;Ljava/lang/Object;)V
const #91 = Asciz	scala/Console$;
const #92 = class	#91;	//  scala/Console$
const #93 = Asciz	MODULE$;
const #94 = Asciz	Lscala/Console$;;
const #95 = NameAndType	#93:#94;//  MODULE$:Lscala/Console$;
const #96 = Field	#92.#95;	//  scala/Console$.MODULE$:Lscala/Console$;
const #97 = Asciz	scala/collection/mutable/StringBuilder;
const #98 = class	#97;	//  scala/collection/mutable/StringBuilder
const #99 = Method	#98.#25;	//  scala/collection/mutable/StringBuilder."<init>":()V
const #100 = Asciz	!=;
const #101 = String	#100;	//  !=
const #102 = Asciz	java/lang/String;
const #103 = class	#102;	//  java/lang/String
const #104 = Asciz	valueOf;
const #105 = Asciz	(Ljava/lang/Object;)Ljava/lang/String;;
const #106 = NameAndType	#104:#105;//  valueOf:(Ljava/lang/Object;)Ljava/lang/String;
const #107 = Method	#103.#106;	//  java/lang/String.valueOf:(Ljava/lang/Object;)Ljava/lang/String;
const #108 = Asciz	append;
const #109 = Asciz	(Ljava/lang/Object;)Lscala/collection/mutable/StringBuilder;;
const #110 = NameAndType	#108:#109;//  append:(Ljava/lang/Object;)Lscala/collection/mutable/StringBuilder;
const #111 = Method	#98.#110;	//  scala/collection/mutable/StringBuilder.append:(Ljava/lang/Object;)Lscala/collection/mutable/StringBuilder;
const #112 = Asciz	toString;
const #113 = NameAndType	#112:#70;//  toString:()Ljava/lang/String;
const #114 = Method	#98.#113;	//  scala/collection/mutable/StringBuilder.toString:()Ljava/lang/String;
const #115 = Asciz	out;
const #116 = Asciz	()Ljava/io/PrintStream;;
const #117 = NameAndType	#115:#116;//  out:()Ljava/io/PrintStream;
const #118 = Method	#92.#117;	//  scala/Console$.out:()Ljava/io/PrintStream;
const #119 = Asciz	java/io/PrintStream;
const #120 = class	#119;	//  java/io/PrintStream
const #121 = Asciz	println;
const #122 = NameAndType	#121:#85;//  println:(Ljava/lang/Object;)V
const #123 = Method	#120.#122;	//  java/io/PrintStream.println:(Ljava/lang/Object;)V
const #124 = Asciz	scala/MatchError;
const #125 = class	#124;	//  scala/MatchError
const #126 = Method	#43.#113;	//  scala/Tuple2.toString:()Ljava/lang/String;
const #127 = Asciz	(Ljava/lang/String;)V;
const #128 = NameAndType	#16:#127;//  "<init>":(Ljava/lang/String;)V
const #129 = Method	#125.#128;	//  scala/MatchError."<init>":(Ljava/lang/String;)V
const #130 = Asciz	temp3;
const #131 = Asciz	I;
const #132 = Asciz	temp2;
const #133 = Asciz	(Lscala/Tuple2<TbinderType;Ljava/lang/Integer;>;)V;
const #134 = Asciz	andThen;
const #135 = Asciz	(Lscala/Function1;)Lscala/Function1;;
const #136 = Asciz	(Lscala/Function1;Lscala/Function1;)Lscala/Function1;;
const #137 = NameAndType	#134:#136;//  andThen:(Lscala/Function1;Lscala/Function1;)Lscala/Function1;
const #138 = Method	#28.#137;	//  scala/Function1$class.andThen:(Lscala/Function1;Lscala/Function1;)Lscala/Function1;
const #139 = Asciz	g;
const #140 = Asciz	Lscala/Function1;;
const #141 = Asciz	compose;
const #142 = NameAndType	#141:#136;//  compose:(Lscala/Function1;Lscala/Function1;)Lscala/Function1;
const #143 = Method	#28.#142;	//  scala/Function1$class.compose:(Lscala/Function1;Lscala/Function1;)Lscala/Function1;
const #144 = Asciz	(Lscala/Function1;)Ljava/lang/String;;
const #145 = NameAndType	#112:#144;//  toString:(Lscala/Function1;)Ljava/lang/String;
const #146 = Method	#28.#145;	//  scala/Function1$class.toString:(Lscala/Function1;)Ljava/lang/String;
const #147 = Asciz	Scala;
const #148 = Asciz	InnerClasses;
const #149 = Asciz	scala/util/parsing/ast/Binders$Scope;
const #150 = class	#149;	//  scala/util/parsing/ast/Binders$Scope
const #151 = Asciz	scala/util/parsing/ast/Binders;
const #152 = class	#151;	//  scala/util/parsing/ast/Binders
const #153 = Asciz	Scope;
const #154 = Asciz	scala/util/parsing/ast/AbstractSyntax;
const #155 = class	#154;	//  scala/util/parsing/ast/AbstractSyntax
const #156 = Asciz	NameElement;
const #157 = Asciz	$anonfun$indexFor$1;
const #158 = Asciz	scala/Function1;
const #159 = class	#158;	//  scala/Function1
const #160 = Asciz	scala/ScalaObject;
const #161 = class	#160;	//  scala/ScalaObject
const #162 = Asciz	java/io/Serializable;
const #163 = class	#162;	//  java/io/Serializable

{
public static final long serialVersionUID;

public static {};
  Code:
   Stack=2, Locals=0, Args_size=0
   0:	lconst_0
   1:	putstatic	#11; //Field serialVersionUID:J
   4:	return

public scala.util.parsing.ast.Binders$Scope$$anonfun$indexFor$1(scala.util.parsing.ast.Binders$Scope, scala.util.parsing.ast.AbstractSyntax$NameElement, java.lang.Object);
  Code:
   Stack=2, Locals=4, Args_size=4
   0:	aload_0
   1:	aload_2
   2:	putfield	#20; //Field b$1:Lscala/util/parsing/ast/AbstractSyntax$NameElement;
   5:	aload_0
   6:	aload_3
   7:	putfield	#22; //Field nonLocalReturnKey1$1:Ljava/lang/Object;
   10:	aload_0
   11:	invokespecial	#26; //Method java/lang/Object."<init>":()V
   14:	aload_0
   15:	invokestatic	#32; //Method scala/Function1$class.$init$:(Lscala/Function1;)V
   18:	return
  LineNumberTable: 
   line 116: 0

  LocalVariableTable: 
   Start  Length  Slot  Name   Signature
   0      19      0    this       Lscala/util/parsing/ast/Binders$Scope$$anonfun$indexFor$1;
   0      19      1    $outer       Lscala/util/parsing/ast/Binders$Scope;

  Signature: length = 0x2
   00 26 

public final java.lang.Object apply(java.lang.Object);
  Code:
   Stack=2, Locals=2, Args_size=2
   0:	aload_0
   1:	aload_1
   2:	checkcast	#43; //class scala/Tuple2
   5:	invokevirtual	#46; //Method apply:(Lscala/Tuple2;)V
   8:	getstatic	#52; //Field scala/runtime/BoxedUnit.UNIT:Lscala/runtime/BoxedUnit;
   11:	areturn
  LineNumberTable: 
   line 116: 0

  LocalVariableTable: 
   Start  Length  Slot  Name   Signature
   0      12      0    this       Lscala/util/parsing/ast/Binders$Scope$$anonfun$indexFor$1;
   0      12      1    v1       Ljava/lang/Object;


public final void apply(scala.Tuple2);
  Code:
   Stack=7, Locals=9, Args_size=2
   0:	aload_1
   1:	ifnull	167
   4:	aload_1
   5:	invokevirtual	#57; //Method scala/Tuple2._1:()Ljava/lang/Object;
   8:	checkcast	#59; //class scala/util/parsing/ast/AbstractSyntax$NameElement
   11:	astore	5
   13:	aload_1
   14:	invokevirtual	#62; //Method scala/Tuple2._2:()Ljava/lang/Object;
   17:	invokestatic	#68; //Method scala/runtime/BoxesRunTime.unboxToInt:(Ljava/lang/Object;)I
   20:	istore_3
   21:	iconst_1
   22:	ifeq	155
   25:	aload	5
   27:	invokeinterface	#72,  1; //InterfaceMethod scala/util/parsing/ast/AbstractSyntax$NameElement.name:()Ljava/lang/String;
   32:	aload_0
   33:	getfield	#20; //Field b$1:Lscala/util/parsing/ast/AbstractSyntax$NameElement;
   36:	invokeinterface	#72,  1; //InterfaceMethod scala/util/parsing/ast/AbstractSyntax$NameElement.name:()Ljava/lang/String;
   41:	astore_2
   42:	dup
   43:	ifnonnull	54
   46:	pop
   47:	aload_2
   48:	ifnull	61
   51:	goto	90
   54:	aload_2
   55:	invokevirtual	#76; //Method java/lang/Object.equals:(Ljava/lang/Object;)Z
   58:	ifeq	90
   61:	new	#78; //class scala/runtime/NonLocalReturnException
   64:	dup
   65:	aload_0
   66:	getfield	#22; //Field nonLocalReturnKey1$1:Ljava/lang/Object;
   69:	new	#80; //class scala/Some
   72:	dup
   73:	iload_3
   74:	iconst_1
   75:	iadd
   76:	istore	4
   78:	iload	4
   80:	invokestatic	#84; //Method scala/runtime/BoxesRunTime.boxToInteger:(I)Ljava/lang/Integer;
   83:	invokespecial	#87; //Method scala/Some."<init>":(Ljava/lang/Object;)V
   86:	invokespecial	#90; //Method scala/runtime/NonLocalReturnException."<init>":(Ljava/lang/Object;Ljava/lang/Object;)V
   89:	athrow
   90:	getstatic	#96; //Field scala/Console$.MODULE$:Lscala/Console$;
   93:	new	#98; //class scala/collection/mutable/StringBuilder
   96:	dup
   97:	invokespecial	#99; //Method scala/collection/mutable/StringBuilder."<init>":()V
   100:	ldc	#101; //String !=
   102:	astore	6
   104:	new	#98; //class scala/collection/mutable/StringBuilder
   107:	dup
   108:	invokespecial	#99; //Method scala/collection/mutable/StringBuilder."<init>":()V
   111:	aload	5
   113:	invokestatic	#107; //Method java/lang/String.valueOf:(Ljava/lang/Object;)Ljava/lang/String;
   116:	invokevirtual	#111; //Method scala/collection/mutable/StringBuilder.append:(Ljava/lang/Object;)Lscala/collection/mutable/StringBuilder;
   119:	aload	6
   121:	invokevirtual	#111; //Method scala/collection/mutable/StringBuilder.append:(Ljava/lang/Object;)Lscala/collection/mutable/StringBuilder;
   124:	invokevirtual	#114; //Method scala/collection/mutable/StringBuilder.toString:()Ljava/lang/String;
   127:	invokevirtual	#111; //Method scala/collection/mutable/StringBuilder.append:(Ljava/lang/Object;)Lscala/collection/mutable/StringBuilder;
   130:	aload_0
   131:	getfield	#20; //Field b$1:Lscala/util/parsing/ast/AbstractSyntax$NameElement;
   134:	invokevirtual	#111; //Method scala/collection/mutable/StringBuilder.append:(Ljava/lang/Object;)Lscala/collection/mutable/StringBuilder;
   137:	invokevirtual	#114; //Method scala/collection/mutable/StringBuilder.toString:()Ljava/lang/String;
   140:	astore	8
   142:	astore	7
   144:	aload	7
   146:	invokevirtual	#118; //Method scala/Console$.out:()Ljava/io/PrintStream;
   149:	aload	8
   151:	invokevirtual	#123; //Method java/io/PrintStream.println:(Ljava/lang/Object;)V
   154:	return
   155:	new	#125; //class scala/MatchError
   158:	dup
   159:	aload_1
   160:	invokevirtual	#126; //Method scala/Tuple2.toString:()Ljava/lang/String;
   163:	invokespecial	#129; //Method scala/MatchError."<init>":(Ljava/lang/String;)V
   166:	athrow
   167:	new	#125; //class scala/MatchError
   170:	dup
   171:	aload_1
   172:	invokevirtual	#126; //Method scala/Tuple2.toString:()Ljava/lang/String;
   175:	invokespecial	#129; //Method scala/MatchError."<init>":(Ljava/lang/String;)V
   178:	athrow
  LineNumberTable: 
   line 116: 0
   line 21: 21
   line 117: 25
   line 118: 61
   line 120: 90
   line 116: 154

  LocalVariableTable: 
   Start  Length  Slot  Name   Signature
   0      179      0    this       Lscala/util/parsing/ast/Binders$Scope$$anonfun$indexFor$1;
   21      146      3    temp3       I
   13      154      5    temp2       Lscala/util/parsing/ast/AbstractSyntax$NameElement;

  Signature: length = 0x2
   00 FFFFFF85 

public scala.Function1 andThen(scala.Function1);
  Code:
   Stack=2, Locals=2, Args_size=2
   0:	aload_0
   1:	aload_1
   2:	invokestatic	#138; //Method scala/Function1$class.andThen:(Lscala/Function1;Lscala/Function1;)Lscala/Function1;
   5:	areturn
  LineNumberTable: 
   line 116: 0

  LocalVariableTable: 
   Start  Length  Slot  Name   Signature
   0      6      0    this       Lscala/util/parsing/ast/Binders$Scope$$anonfun$indexFor$1;
   0      6      1    g       Lscala/Function1;


public scala.Function1 compose(scala.Function1);
  Code:
   Stack=2, Locals=2, Args_size=2
   0:	aload_0
   1:	aload_1
   2:	invokestatic	#143; //Method scala/Function1$class.compose:(Lscala/Function1;Lscala/Function1;)Lscala/Function1;
   5:	areturn
  LineNumberTable: 
   line 116: 0

  LocalVariableTable: 
   Start  Length  Slot  Name   Signature
   0      6      0    this       Lscala/util/parsing/ast/Binders$Scope$$anonfun$indexFor$1;
   0      6      1    g       Lscala/Function1;


public java.lang.String toString();
  Code:
   Stack=1, Locals=1, Args_size=1
   0:	aload_0
   1:	invokestatic	#146; //Method scala/Function1$class.toString:(Lscala/Function1;)Ljava/lang/String;
   4:	areturn
  LineNumberTable: 
   line 116: 0


}

