Compiled from "Binders.scala"
public abstract class scala.util.parsing.ast.Binders$BinderEnv extends java.lang.Object implements scala.ScalaObject
  SourceFile: "Binders.scala"
  Scala: length = 0x
   
  InnerClass: 
   public Scope=class scala/util/parsing/ast/Binders$Scope of class scala/util/parsing/ast/Binders
   public abstract BinderEnv=class scala/util/parsing/ast/Binders$BinderEnv of class scala/util/parsing/ast/Binders
   public final $anon$7=class scala/util/parsing/ast/Binders$BinderEnv$$anon$7 of class scala/util/parsing/ast/Binders$BinderEnv
   public abstract NameElement=class scala/util/parsing/ast/AbstractSyntax$NameElement of class scala/util/parsing/ast/AbstractSyntax
  minor version: 0
  major version: 49
  Constant pool:
Asciz	SourceFile;
Asciz	Binders.scala;
Asciz	$outer;
Asciz	Lscala/util/parsing/ast/Binders;;
Asciz	apply;
Asciz	(Lscala/util/parsing/ast/AbstractSyntax$NameElement;)Lscala/Option;;
Asciz	<A::Lscala/util/parsing/ast/AbstractSyntax$NameElement;>(TA;)Lscala/Option<Lscala/util/parsing/ast/Binders$Scope<TA;>;>;;
Asciz	Signature;
Asciz	extend;
Asciz	(Lscala/util/parsing/ast/AbstractSyntax$NameElement;Lscala/util/parsing/ast/Binders$Scope;)Lscala/util/parsing/ast/Binders$BinderEnv;;
Asciz	Code;
Asciz	scala/util/parsing/ast/Binders$BinderEnv$$anon$7;
class	scala/util/parsing/ast/Binders$BinderEnv$$anon$7
Asciz	LineNumberTable;
Asciz	<init>;
Asciz	(Lscala/util/parsing/ast/Binders$BinderEnv;Lscala/util/parsing/ast/AbstractSyntax$NameElement;Lscala/util/parsing/ast/Binders$Scope;)V;
NameAndType	"<init>":(Lscala/util/parsing/ast/Binders$BinderEnv;Lscala/util/parsing/ast/AbstractSyntax$NameElement;Lscala/util/parsing/ast/Binders$Scope;)V
Method	scala/util/parsing/ast/Binders$BinderEnv$$anon$7."<init>":(Lscala/util/parsing/ast/Binders$BinderEnv;Lscala/util/parsing/ast/AbstractSyntax$NameElement;Lscala/util/parsing/ast/Binders$Scope;)V
Asciz	this;
Asciz	Lscala/util/parsing/ast/Binders$BinderEnv;;
Asciz	v$1;
Asciz	Lscala/util/parsing/ast/AbstractSyntax$NameElement;;
Asciz	x$3;
Asciz	Lscala/util/parsing/ast/Binders$Scope;;
Asciz	LocalVariableTable;
Asciz	<a::Lscala/util/parsing/ast/AbstractSyntax$NameElement;>(Ta;Lscala/util/parsing/ast/Binders$Scope<Ta;>;)Lscala/util/parsing/ast/Binders$BinderEnv;;
Asciz	scala$util$parsing$ast$Binders$BinderEnv$$$outer;
Asciz	()Lscala/util/parsing/ast/Binders;;
Asciz	scala/util/parsing/ast/Binders$BinderEnv;
class	scala/util/parsing/ast/Binders$BinderEnv
NameAndType	$outer:Lscala/util/parsing/ast/Binders;
Field	scala/util/parsing/ast/Binders$BinderEnv.$outer:Lscala/util/parsing/ast/Binders;
Asciz	(Lscala/util/parsing/ast/Binders;)V;
Asciz	java/lang/NullPointerException;
class	java/lang/NullPointerException
Asciz	()V;
NameAndType	"<init>":()V
Method	java/lang/NullPointerException."<init>":()V
Asciz	java/lang/Object;
class	java/lang/Object
Method	java/lang/Object."<init>":()V
Asciz	Scala;
Asciz	InnerClasses;
Asciz	scala/util/parsing/ast/Binders$Scope;
class	scala/util/parsing/ast/Binders$Scope
Asciz	scala/util/parsing/ast/Binders;
class	scala/util/parsing/ast/Binders
Asciz	Scope;
Asciz	BinderEnv;
Asciz	$anon$7;
Asciz	scala/util/parsing/ast/AbstractSyntax$NameElement;
class	scala/util/parsing/ast/AbstractSyntax$NameElement
Asciz	scala/util/parsing/ast/AbstractSyntax;
class	scala/util/parsing/ast/AbstractSyntax
Asciz	NameElement;
Asciz	scala/ScalaObject;
class	scala/ScalaObject

{
public final scala.util.parsing.ast.Binders $outer;
  Signature: Lscala/util/parsing/ast/Binders;

public abstract scala.Option apply(scala.util.parsing.ast.AbstractSyntax$NameElement);
  Signature: (Lscala/util/parsing/ast/AbstractSyntax$NameElement;)Lscala/Option;
  Signature: length = 0x2
   00 07 

public scala.util.parsing.ast.Binders$BinderEnv extend(scala.util.parsing.ast.AbstractSyntax$NameElement, scala.util.parsing.ast.Binders$Scope);
  Signature: (Lscala/util/parsing/ast/AbstractSyntax$NameElement;Lscala/util/parsing/ast/Binders$Scope;)Lscala/util/parsing/ast/Binders$BinderEnv;
  Code:
   Stack=5, Locals=3, Args_size=3
	new	class scala/util/parsing/ast/Binders$BinderEnv$$anon$7
	dup
	aload_0
	aload_1
	aload_2
	invokespecial	Method scala/util/parsing/ast/Binders$BinderEnv$$anon$7."<init>":(Lscala/util/parsing/ast/Binders$BinderEnv;Lscala/util/parsing/ast/AbstractSyntax$NameElement;Lscala/util/parsing/ast/Binders$Scope;)V
	areturn
  Labels:
  LocalVariableTable: 
   Start  Length  Slot  Name   Signature
   0      11      0    this       Lscala/util/parsing/ast/Binders$BinderEnv;
   0      11      1    v$1       Lscala/util/parsing/ast/AbstractSyntax$NameElement;
   0      11      2    x$3       Lscala/util/parsing/ast/Binders$Scope;

  Signature: length = 0x2
   00 1A 

public scala.util.parsing.ast.Binders scala$util$parsing$ast$Binders$BinderEnv$$$outer();
  Signature: ()Lscala/util/parsing/ast/Binders;
  Code:
   Stack=1, Locals=1, Args_size=1
	aload_0
	getfield	Field $outer:Lscala/util/parsing/ast/Binders;
	areturn
  Labels:

public scala.util.parsing.ast.Binders$BinderEnv(scala.util.parsing.ast.Binders);
  Signature: (Lscala/util/parsing/ast/Binders;)V
  Code:
   Stack=2, Locals=2, Args_size=2
	aload_1
	ifnonnull	l1 // aload_0
	new	class java/lang/NullPointerException
	dup
	invokespecial	Method java/lang/NullPointerException."<init>":()V
	athrow
l1	aload_0
	aload_1
	putfield	Field $outer:Lscala/util/parsing/ast/Binders;
	aload_0
	invokespecial	Method java/lang/Object."<init>":()V
	return
  Labels:
   	l1 = 12 // aload_0
  LocalVariableTable: 
   Start  Length  Slot  Name   Signature
   0      22      0    this       Lscala/util/parsing/ast/Binders$BinderEnv;
   0      22      1    $outer       Lscala/util/parsing/ast/Binders;


}

