Compiled from "Binders.scala"
public final class scala.util.parsing.ast.Binders$UnderBinder$$anon$10 extends java.lang.Object implements scala.util.parsing.ast.Mappable$Mapper
  SourceFile: "Binders.scala"
  Scala: length = 0x
   
  InnerClass: 
   public abstract Mapper=class scala/util/parsing/ast/Mappable$Mapper of class scala/util/parsing/ast/Mappable
   public UnderBinder=class scala/util/parsing/ast/Binders$UnderBinder of class scala/util/parsing/ast/Binders
   public BoundElement=class scala/util/parsing/ast/Binders$BoundElement of class scala/util/parsing/ast/Binders
   public UnboundElement=class scala/util/parsing/ast/Binders$UnboundElement of class scala/util/parsing/ast/Binders
   public abstract NameElement=class scala/util/parsing/ast/AbstractSyntax$NameElement of class scala/util/parsing/ast/AbstractSyntax
   public final $anon$10=class scala/util/parsing/ast/Binders$UnderBinder$$anon$10 of class scala/util/parsing/ast/Binders$UnderBinder
  minor version: 0
  major version: 49
  Constant pool:
Asciz	SourceFile;
Asciz	Binders.scala;
Asciz	$outer;
Asciz	Lscala/util/parsing/ast/Binders$UnderBinder;;
Asciz	apply;
Asciz	(Ljava/lang/Object;Lscala/Function1;)Ljava/lang/Object;;
Asciz	Code;
Asciz	LineNumberTable;
Asciz	scala/util/parsing/ast/Binders$BoundElement;
class	scala/util/parsing/ast/Binders$BoundElement
Asciz	scala$util$parsing$ast$Binders$BoundElement$$$outer;
Asciz	()Lscala/util/parsing/ast/Binders;;
NameAndType	scala$util$parsing$ast$Binders$BoundElement$$$outer:()Lscala/util/parsing/ast/Binders;
Method	scala/util/parsing/ast/Binders$BoundElement.scala$util$parsing$ast$Binders$BoundElement$$$outer:()Lscala/util/parsing/ast/Binders;
Asciz	scala/util/parsing/ast/Binders$UnderBinder$$anon$10;
class	scala/util/parsing/ast/Binders$UnderBinder$$anon$10
NameAndType	$outer:Lscala/util/parsing/ast/Binders$UnderBinder;
Field	scala/util/parsing/ast/Binders$UnderBinder$$anon$10.$outer:Lscala/util/parsing/ast/Binders$UnderBinder;
Asciz	scala/util/parsing/ast/Binders$UnderBinder;
class	scala/util/parsing/ast/Binders$UnderBinder
Asciz	scala$util$parsing$ast$Binders$UnderBinder$$$outer;
NameAndType	scala$util$parsing$ast$Binders$UnderBinder$$$outer:()Lscala/util/parsing/ast/Binders;
Method	scala/util/parsing/ast/Binders$UnderBinder.scala$util$parsing$ast$Binders$UnderBinder$$$outer:()Lscala/util/parsing/ast/Binders;
Asciz	el;
Asciz	()Lscala/util/parsing/ast/AbstractSyntax$NameElement;;
NameAndType	el:()Lscala/util/parsing/ast/AbstractSyntax$NameElement;
Method	scala/util/parsing/ast/Binders$BoundElement.el:()Lscala/util/parsing/ast/AbstractSyntax$NameElement;
Asciz	scala/util/parsing/ast/Binders$UnboundElement;
class	scala/util/parsing/ast/Binders$UnboundElement
Asciz	<init>;
Asciz	(Lscala/util/parsing/ast/Binders;Lscala/util/parsing/ast/AbstractSyntax$NameElement;)V;
NameAndType	"<init>":(Lscala/util/parsing/ast/Binders;Lscala/util/parsing/ast/AbstractSyntax$NameElement;)V
Method	scala/util/parsing/ast/Binders$UnboundElement."<init>":(Lscala/util/parsing/ast/Binders;Lscala/util/parsing/ast/AbstractSyntax$NameElement;)V
Asciz	this;
Asciz	Lscala/util/parsing/ast/Binders$UnderBinder$$anon$10;;
Asciz	x;
Asciz	Ljava/lang/Object;;
Asciz	evidence$7;
Asciz	Lscala/Function1;;
Asciz	temp9;
Asciz	Lscala/util/parsing/ast/Binders$BoundElement;;
Asciz	temp10;
Asciz	Lscala/util/parsing/ast/AbstractSyntax$NameElement;;
Asciz	LocalVariableTable;
Asciz	<t:Ljava/lang/Object;>(Tt;Lscala/Function1<Tt;Lscala/util/parsing/ast/Mappable$Mappable<Tt;>;>;)Tt;;
Asciz	Signature;
Asciz	(Lscala/util/parsing/ast/Binders$UnderBinder;)V;
Asciz	java/lang/NullPointerException;
class	java/lang/NullPointerException
Asciz	()V;
NameAndType	"<init>":()V
Method	java/lang/NullPointerException."<init>":()V
Asciz	java/lang/Object;
class	java/lang/Object
Method	java/lang/Object."<init>":()V
Asciz	(Lscala/util/parsing/ast/Binders$UnderBinder<TbinderType;TelementT;>;)V;
Asciz	Scala;
Asciz	InnerClasses;
Asciz	scala/util/parsing/ast/Mappable$Mapper;
class	scala/util/parsing/ast/Mappable$Mapper
Asciz	scala/util/parsing/ast/Mappable;
class	scala/util/parsing/ast/Mappable
Asciz	Mapper;
Asciz	scala/util/parsing/ast/Binders;
class	scala/util/parsing/ast/Binders
Asciz	UnderBinder;
Asciz	BoundElement;
Asciz	UnboundElement;
Asciz	scala/util/parsing/ast/AbstractSyntax$NameElement;
class	scala/util/parsing/ast/AbstractSyntax$NameElement
Asciz	scala/util/parsing/ast/AbstractSyntax;
class	scala/util/parsing/ast/AbstractSyntax
Asciz	NameElement;
Asciz	$anon$10;

{
private final scala.util.parsing.ast.Binders$UnderBinder $outer;
  Signature: Lscala/util/parsing/ast/Binders$UnderBinder;

public java.lang.Object apply(java.lang.Object, scala.Function1);
  Signature: (Ljava/lang/Object;Lscala/Function1;)Ljava/lang/Object;
  Code:
   Stack=4, Locals=5, Args_size=3
	aload_1
	instanceof	class scala/util/parsing/ast/Binders$BoundElement
	ifeq	l1 // aload_1
	aload_1
	checkcast	class scala/util/parsing/ast/Binders$BoundElement
	invokevirtual	Method scala/util/parsing/ast/Binders$BoundElement.scala$util$parsing$ast$Binders$BoundElement$$$outer:()Lscala/util/parsing/ast/Binders;
	aload_0
	getfield	Field $outer:Lscala/util/parsing/ast/Binders$UnderBinder;
	invokevirtual	Method scala/util/parsing/ast/Binders$UnderBinder.scala$util$parsing$ast$Binders$UnderBinder$$$outer:()Lscala/util/parsing/ast/Binders;
	if_acmpne	l1 // aload_1
	aload_1
	checkcast	class scala/util/parsing/ast/Binders$BoundElement
	astore_3
	aload_3
	invokevirtual	Method scala/util/parsing/ast/Binders$BoundElement.el:()Lscala/util/parsing/ast/AbstractSyntax$NameElement;
	astore	4
	new	class scala/util/parsing/ast/Binders$UnboundElement
	dup
	aload_0
	getfield	Field $outer:Lscala/util/parsing/ast/Binders$UnderBinder;
	invokevirtual	Method scala/util/parsing/ast/Binders$UnderBinder.scala$util$parsing$ast$Binders$UnderBinder$$$outer:()Lscala/util/parsing/ast/Binders;
	aload	4
	invokespecial	Method scala/util/parsing/ast/Binders$UnboundElement."<init>":(Lscala/util/parsing/ast/Binders;Lscala/util/parsing/ast/AbstractSyntax$NameElement;)V
	goto	l2 // areturn
l1	aload_1
l2	areturn
  Labels:
   	l1 = 54 // aload_1
   	l2 = 55 // areturn
  LocalVariableTable: 
   Start  Length  Slot  Name   Signature
   0      56      0    this       Lscala/util/parsing/ast/Binders$UnderBinder$$anon$10;
   0      56      1    x       Ljava/lang/Object;
   0      56      2    evidence$7       Lscala/Function1;
   29      22      3    temp9       Lscala/util/parsing/ast/Binders$BoundElement;
   35      16      4    temp10       Lscala/util/parsing/ast/AbstractSyntax$NameElement;

  Signature: length = 0x2
   00 2D 

public scala.util.parsing.ast.Binders$UnderBinder$$anon$10(scala.util.parsing.ast.Binders$UnderBinder);
  Signature: (Lscala/util/parsing/ast/Binders$UnderBinder;)V
  Code:
   Stack=2, Locals=2, Args_size=2
	aload_1
	ifnonnull	l1 // aload_0
	new	class java/lang/NullPointerException
	dup
	invokespecial	Method java/lang/NullPointerException."<init>":()V
	athrow
l1	aload_0
	aload_1
	putfield	Field $outer:Lscala/util/parsing/ast/Binders$UnderBinder;
	aload_0
	invokespecial	Method java/lang/Object."<init>":()V
	return
  Labels:
   	l1 = 12 // aload_0
  LocalVariableTable: 
   Start  Length  Slot  Name   Signature
   0      22      0    this       Lscala/util/parsing/ast/Binders$UnderBinder$$anon$10;
   0      22      1    $outer       Lscala/util/parsing/ast/Binders$UnderBinder;

  Signature: length = 0x2
   00 38 

}

