Compiled from "Binders.scala"
public class scala.util.parsing.ast.Binders$BoundElement extends java.lang.Object implements scala.util.parsing.ast.AbstractSyntax$NameElement,scala.Proxy,scala.util.parsing.ast.Binders$BindingSensitive,scala.ScalaObject,scala.Product,java.io.Serializable
  SourceFile: "Binders.scala"
  Signature: length = 0x2
   00 FFFFFFB6 
  Scala: length = 0x
   
  InnerClass: 
   public Scope=class scala/util/parsing/ast/Binders$Scope of class scala/util/parsing/ast/Binders
   public BoundElement=class scala/util/parsing/ast/Binders$BoundElement of class scala/util/parsing/ast/Binders
   public abstract Element=class scala/util/parsing/ast/AbstractSyntax$Element of class scala/util/parsing/ast/AbstractSyntax
   public abstract BindingSensitive=class scala/util/parsing/ast/Binders$BindingSensitive of class scala/util/parsing/ast/Binders
   public abstract NameElement=class scala/util/parsing/ast/AbstractSyntax$NameElement of class scala/util/parsing/ast/AbstractSyntax
  minor version: 0
  major version: 49
  Constant pool:
Asciz	SourceFile;
Asciz	Binders.scala;
Asciz	pos;
Asciz	Lscala/util/parsing/input/Position;;
Asciz	$outer;
Asciz	Lscala/util/parsing/ast/Binders;;
Asciz	scope;
Asciz	Lscala/util/parsing/ast/Binders$Scope;;
Asciz	Lscala/util/parsing/ast/Binders$Scope<TboundElement;>;;
Asciz	Signature;
Asciz	el;
Asciz	Lscala/util/parsing/ast/AbstractSyntax$NameElement;;
Asciz	TboundElement;;
Asciz	productIterator;
Asciz	()Lscala/collection/Iterator;;
Asciz	Code;
Asciz	LineNumberTable;
Asciz	scala/Product$class;
class	scala/Product$class
Asciz	(Lscala/Product;)Lscala/collection/Iterator;;
NameAndType	productIterator:(Lscala/Product;)Lscala/collection/Iterator;
Method	scala/Product$class.productIterator:(Lscala/Product;)Lscala/collection/Iterator;
Asciz	productElements;
NameAndType	productElements:(Lscala/Product;)Lscala/collection/Iterator;
Method	scala/Product$class.productElements:(Lscala/Product;)Lscala/collection/Iterator;
Asciz	Deprecated;
Asciz	hashCode;
Asciz	()I;
Asciz	scala/Proxy$class;
class	scala/Proxy$class
Asciz	(Lscala/Proxy;)I;
NameAndType	hashCode:(Lscala/Proxy;)I
Method	scala/Proxy$class.hashCode:(Lscala/Proxy;)I
Asciz	equals;
Asciz	(Ljava/lang/Object;)Z;
Asciz	(Lscala/Proxy;Ljava/lang/Object;)Z;
NameAndType	equals:(Lscala/Proxy;Ljava/lang/Object;)Z
Method	scala/Proxy$class.equals:(Lscala/Proxy;Ljava/lang/Object;)Z
Asciz	this;
Asciz	Lscala/util/parsing/ast/Binders$BoundElement;;
Asciz	that;
Asciz	Ljava/lang/Object;;
Asciz	LocalVariableTable;
Asciz	()Lscala/util/parsing/input/Position;;
Asciz	scala/util/parsing/ast/Binders$BoundElement;
class	scala/util/parsing/ast/Binders$BoundElement
NameAndType	pos:Lscala/util/parsing/input/Position;
Field	scala/util/parsing/ast/Binders$BoundElement.pos:Lscala/util/parsing/input/Position;
Asciz	pos_$eq;
Asciz	(Lscala/util/parsing/input/Position;)V;
Asciz	setPos;
Asciz	(Lscala/util/parsing/input/Position;)Lscala/util/parsing/input/Positional;;
Asciz	scala/util/parsing/input/Positional$class;
class	scala/util/parsing/input/Positional$class
Asciz	(Lscala/util/parsing/input/Positional;Lscala/util/parsing/input/Position;)Lscala/util/parsing/input/Positional;;
NameAndType	setPos:(Lscala/util/parsing/input/Positional;Lscala/util/parsing/input/Position;)Lscala/util/parsing/input/Positional;
Method	scala/util/parsing/input/Positional$class.setPos:(Lscala/util/parsing/input/Positional;Lscala/util/parsing/input/Position;)Lscala/util/parsing/input/Positional;
Asciz	newpos;
Asciz	copy$default$2;
Asciz	()Lscala/util/parsing/ast/Binders$Scope;;
NameAndType	scope:()Lscala/util/parsing/ast/Binders$Scope;
Method	scala/util/parsing/ast/Binders$BoundElement.scope:()Lscala/util/parsing/ast/Binders$Scope;
Asciz	copy$default$1;
Asciz	()Lscala/util/parsing/ast/AbstractSyntax$NameElement;;
NameAndType	el:()Lscala/util/parsing/ast/AbstractSyntax$NameElement;
Method	scala/util/parsing/ast/Binders$BoundElement.el:()Lscala/util/parsing/ast/AbstractSyntax$NameElement;
NameAndType	el:Lscala/util/parsing/ast/AbstractSyntax$NameElement;
Field	scala/util/parsing/ast/Binders$BoundElement.el:Lscala/util/parsing/ast/AbstractSyntax$NameElement;
Asciz	()TboundElement;;
NameAndType	scope:Lscala/util/parsing/ast/Binders$Scope;
Field	scala/util/parsing/ast/Binders$BoundElement.scope:Lscala/util/parsing/ast/Binders$Scope;
Asciz	()Lscala/util/parsing/ast/Binders$Scope<TboundElement;>;;
Asciz	self;
Asciz	()Lscala/util/parsing/ast/AbstractSyntax$Element;;
Asciz	scala/util/parsing/ast/Binders$Scope;
class	scala/util/parsing/ast/Binders$Scope
Asciz	getElementFor;
Asciz	(Lscala/util/parsing/ast/AbstractSyntax$NameElement;)Lscala/util/parsing/ast/AbstractSyntax$Element;;
NameAndType	getElementFor:(Lscala/util/parsing/ast/AbstractSyntax$NameElement;)Lscala/util/parsing/ast/AbstractSyntax$Element;
Method	scala/util/parsing/ast/Binders$Scope.getElementFor:(Lscala/util/parsing/ast/AbstractSyntax$NameElement;)Lscala/util/parsing/ast/AbstractSyntax$Element;
Asciz	name;
Asciz	()Ljava/lang/String;;
NameAndType	self:()Lscala/util/parsing/ast/AbstractSyntax$Element;
Method	scala/util/parsing/ast/Binders$BoundElement.self:()Lscala/util/parsing/ast/AbstractSyntax$Element;
Asciz	scala/util/parsing/ast/AbstractSyntax$NameElement;
class	scala/util/parsing/ast/AbstractSyntax$NameElement
NameAndType	name:()Ljava/lang/String;
InterfaceMethod	scala/util/parsing/ast/AbstractSyntax$NameElement.name:()Ljava/lang/String;
Asciz	toString;
Asciz	scala/collection/mutable/StringBuilder;
class	scala/collection/mutable/StringBuilder
Asciz	<init>;
Asciz	()V;
NameAndType	"<init>":()V
Method	scala/collection/mutable/StringBuilder."<init>":()V
Asciz	(Lscala/Proxy;)Ljava/lang/String;;
NameAndType	toString:(Lscala/Proxy;)Ljava/lang/String;
Method	scala/Proxy$class.toString:(Lscala/Proxy;)Ljava/lang/String;
Asciz	append;
Asciz	(Ljava/lang/Object;)Lscala/collection/mutable/StringBuilder;;
NameAndType	append:(Ljava/lang/Object;)Lscala/collection/mutable/StringBuilder;
Method	scala/collection/mutable/StringBuilder.append:(Ljava/lang/Object;)Lscala/collection/mutable/StringBuilder;
Asciz	@;
String	@
Asciz	id;
NameAndType	id:()I
Method	scala/util/parsing/ast/Binders$Scope.id:()I
Asciz	scala/runtime/BoxesRunTime;
class	scala/runtime/BoxesRunTime
Asciz	boxToInteger;
Asciz	(I)Ljava/lang/Integer;;
NameAndType	boxToInteger:(I)Ljava/lang/Integer;
Method	scala/runtime/BoxesRunTime.boxToInteger:(I)Ljava/lang/Integer;
NameAndType	toString:()Ljava/lang/String;
Method	scala/collection/mutable/StringBuilder.toString:()Ljava/lang/String;
Asciz	alpha_$eq$eq;
Asciz	(Lscala/util/parsing/ast/Binders$BoundElement;)Z;
Asciz	indexFor;
Asciz	(Lscala/util/parsing/ast/AbstractSyntax$NameElement;)Lscala/Option;;
NameAndType	indexFor:(Lscala/util/parsing/ast/AbstractSyntax$NameElement;)Lscala/Option;
Method	scala/util/parsing/ast/Binders$Scope.indexFor:(Lscala/util/parsing/ast/AbstractSyntax$NameElement;)Lscala/Option;
Asciz	java/lang/Object;
class	java/lang/Object
NameAndType	equals:(Ljava/lang/Object;)Z
Method	java/lang/Object.equals:(Ljava/lang/Object;)Z
Asciz	other;
Asciz	<t::Lscala/util/parsing/ast/AbstractSyntax$NameElement;>(Lscala/util/parsing/ast/Binders$BoundElement<Tt;>;)Z;
Asciz	copy;
Asciz	(Lscala/util/parsing/ast/AbstractSyntax$NameElement;Lscala/util/parsing/ast/Binders$Scope;)Lscala/util/parsing/ast/Binders$BoundElement;;
Asciz	scala$util$parsing$ast$Binders$BoundElement$$$outer;
Asciz	()Lscala/util/parsing/ast/Binders;;
NameAndType	scala$util$parsing$ast$Binders$BoundElement$$$outer:()Lscala/util/parsing/ast/Binders;
Method	scala/util/parsing/ast/Binders$BoundElement.scala$util$parsing$ast$Binders$BoundElement$$$outer:()Lscala/util/parsing/ast/Binders;
Asciz	(Lscala/util/parsing/ast/Binders;Lscala/util/parsing/ast/AbstractSyntax$NameElement;Lscala/util/parsing/ast/Binders$Scope;)V;
NameAndType	"<init>":(Lscala/util/parsing/ast/Binders;Lscala/util/parsing/ast/AbstractSyntax$NameElement;Lscala/util/parsing/ast/Binders$Scope;)V
Method	scala/util/parsing/ast/Binders$BoundElement."<init>":(Lscala/util/parsing/ast/Binders;Lscala/util/parsing/ast/AbstractSyntax$NameElement;Lscala/util/parsing/ast/Binders$Scope;)V
Asciz	productPrefix;
Asciz	BoundElement;
String	BoundElement
Asciz	productArity;
Asciz	productElement;
Asciz	(I)Ljava/lang/Object;;
Asciz	java/lang/IndexOutOfBoundsException;
class	java/lang/IndexOutOfBoundsException
Method	java/lang/Object.toString:()Ljava/lang/String;
Asciz	(Ljava/lang/String;)V;
NameAndType	"<init>":(Ljava/lang/String;)V
Method	java/lang/IndexOutOfBoundsException."<init>":(Ljava/lang/String;)V
Asciz	temp4;
Asciz	I;
Asciz	productElementName;
Asciz	(I)Ljava/lang/String;;
String	scope
String	el
Asciz	temp5;
Asciz	canEqual;
NameAndType	$outer:Lscala/util/parsing/ast/Binders;
Field	scala/util/parsing/ast/Binders$BoundElement.$outer:Lscala/util/parsing/ast/Binders;
Asciz	scala$util$parsing$ast$AbstractSyntax$NameElement$$$outer;
Asciz	()Lscala/util/parsing/ast/AbstractSyntax;;
Asciz	()Ljava/lang/Object;;
Asciz	java/lang/NullPointerException;
class	java/lang/NullPointerException
Method	java/lang/NullPointerException."<init>":()V
Method	java/lang/Object."<init>":()V
Asciz	$init$;
Asciz	(Lscala/util/parsing/input/Positional;)V;
NameAndType	$init$:(Lscala/util/parsing/input/Positional;)V
Method	scala/util/parsing/input/Positional$class.$init$:(Lscala/util/parsing/input/Positional;)V
Asciz	scala/util/parsing/ast/AbstractSyntax$NameElement$class;
class	scala/util/parsing/ast/AbstractSyntax$NameElement$class
Asciz	(Lscala/util/parsing/ast/AbstractSyntax$NameElement;)V;
NameAndType	$init$:(Lscala/util/parsing/ast/AbstractSyntax$NameElement;)V
Method	scala/util/parsing/ast/AbstractSyntax$NameElement$class.$init$:(Lscala/util/parsing/ast/AbstractSyntax$NameElement;)V
Asciz	(Lscala/Proxy;)V;
NameAndType	$init$:(Lscala/Proxy;)V
Method	scala/Proxy$class.$init$:(Lscala/Proxy;)V
Asciz	(Lscala/Product;)V;
NameAndType	$init$:(Lscala/Product;)V
Method	scala/Product$class.$init$:(Lscala/Product;)V
Asciz	(Lscala/util/parsing/ast/Binders;TboundElement;Lscala/util/parsing/ast/Binders$Scope<TboundElement;>;)V;
Asciz	<boundElement::Lscala/util/parsing/ast/AbstractSyntax$NameElement;>Ljava/lang/Object;Lscala/util/parsing/ast/AbstractSyntax$NameElement;Lscala/Proxy;Lscala/util/parsing/ast/Binders$BindingSensitive;Lscala/ScalaObject;Lscala/Product;;
Asciz	Scala;
Asciz	InnerClasses;
Asciz	scala/util/parsing/ast/Binders;
class	scala/util/parsing/ast/Binders
Asciz	Scope;
Asciz	scala/util/parsing/ast/AbstractSyntax$Element;
class	scala/util/parsing/ast/AbstractSyntax$Element
Asciz	scala/util/parsing/ast/AbstractSyntax;
class	scala/util/parsing/ast/AbstractSyntax
Asciz	Element;
Asciz	scala/util/parsing/ast/Binders$BindingSensitive;
class	scala/util/parsing/ast/Binders$BindingSensitive
Asciz	BindingSensitive;
Asciz	NameElement;
Asciz	scala/Proxy;
class	scala/Proxy
Asciz	scala/ScalaObject;
class	scala/ScalaObject
Asciz	scala/Product;
class	scala/Product
Asciz	java/io/Serializable;
class	java/io/Serializable

{
private scala.util.parsing.input.Position pos;
  Signature: Lscala/util/parsing/input/Position;

public final scala.util.parsing.ast.Binders $outer;
  Signature: Lscala/util/parsing/ast/Binders;

private final scala.util.parsing.ast.Binders$Scope scope;
  Signature: Lscala/util/parsing/ast/Binders$Scope;
  Signature: length = 0x2
   00 09 

private final scala.util.parsing.ast.AbstractSyntax$NameElement el;
  Signature: Lscala/util/parsing/ast/AbstractSyntax$NameElement;
  Signature: length = 0x2
   00 0D 

public scala.collection.Iterator productIterator();
  Signature: ()Lscala/collection/Iterator;
  Code:
   Stack=1, Locals=1, Args_size=1
	aload_0
	invokestatic	Method scala/Product$class.productIterator:(Lscala/Product;)Lscala/collection/Iterator;
	areturn
  Labels:

public scala.collection.Iterator productElements();
  Signature: ()Lscala/collection/Iterator;
  Code:
   Stack=1, Locals=1, Args_size=1
	aload_0
	invokestatic	Method scala/Product$class.productElements:(Lscala/Product;)Lscala/collection/Iterator;
	areturn
  Labels:
  Deprecated: true

public int hashCode();
  Signature: ()I
  Code:
   Stack=1, Locals=1, Args_size=1
	aload_0
	invokestatic	Method scala/Proxy$class.hashCode:(Lscala/Proxy;)I
	ireturn
  Labels:

public boolean equals(java.lang.Object);
  Signature: (Ljava/lang/Object;)Z
  Code:
   Stack=2, Locals=2, Args_size=2
	aload_0
	aload_1
	invokestatic	Method scala/Proxy$class.equals:(Lscala/Proxy;Ljava/lang/Object;)Z
	ireturn
  Labels:
  LocalVariableTable: 
   Start  Length  Slot  Name   Signature
   0      6      0    this       Lscala/util/parsing/ast/Binders$BoundElement;
   0      6      1    that       Ljava/lang/Object;


public scala.util.parsing.input.Position pos();
  Signature: ()Lscala/util/parsing/input/Position;
  Code:
   Stack=1, Locals=1, Args_size=1
	aload_0
	getfield	Field pos:Lscala/util/parsing/input/Position;
	areturn
  Labels:

public void pos_$eq(scala.util.parsing.input.Position);
  Signature: (Lscala/util/parsing/input/Position;)V
  Code:
   Stack=2, Locals=2, Args_size=2
	aload_0
	aload_1
	putfield	Field pos:Lscala/util/parsing/input/Position;
	return
  Labels:

public scala.util.parsing.input.Positional setPos(scala.util.parsing.input.Position);
  Signature: (Lscala/util/parsing/input/Position;)Lscala/util/parsing/input/Positional;
  Code:
   Stack=2, Locals=2, Args_size=2
	aload_0
	aload_1
	invokestatic	Method scala/util/parsing/input/Positional$class.setPos:(Lscala/util/parsing/input/Positional;Lscala/util/parsing/input/Position;)Lscala/util/parsing/input/Positional;
	areturn
  Labels:
  LocalVariableTable: 
   Start  Length  Slot  Name   Signature
   0      6      0    this       Lscala/util/parsing/ast/Binders$BoundElement;
   0      6      1    newpos       Lscala/util/parsing/input/Position;


public scala.util.parsing.ast.Binders$Scope copy$default$2();
  Signature: ()Lscala/util/parsing/ast/Binders$Scope;
  Code:
   Stack=1, Locals=1, Args_size=1
	aload_0
	invokevirtual	Method scope:()Lscala/util/parsing/ast/Binders$Scope;
	areturn
  Labels:

public scala.util.parsing.ast.AbstractSyntax$NameElement copy$default$1();
  Signature: ()Lscala/util/parsing/ast/AbstractSyntax$NameElement;
  Code:
   Stack=1, Locals=1, Args_size=1
	aload_0
	invokevirtual	Method el:()Lscala/util/parsing/ast/AbstractSyntax$NameElement;
	areturn
  Labels:

public scala.util.parsing.ast.AbstractSyntax$NameElement el();
  Signature: ()Lscala/util/parsing/ast/AbstractSyntax$NameElement;
  Code:
   Stack=1, Locals=1, Args_size=1
	aload_0
	getfield	Field el:Lscala/util/parsing/ast/AbstractSyntax$NameElement;
	areturn
  Labels:
  Signature: length = 0x2
   00 45 

public scala.util.parsing.ast.Binders$Scope scope();
  Signature: ()Lscala/util/parsing/ast/Binders$Scope;
  Code:
   Stack=1, Locals=1, Args_size=1
	aload_0
	getfield	Field scope:Lscala/util/parsing/ast/Binders$Scope;
	areturn
  Labels:
  Signature: length = 0x2
   00 48 

public scala.util.parsing.ast.AbstractSyntax$Element self();
  Signature: ()Lscala/util/parsing/ast/AbstractSyntax$Element;
  Code:
   Stack=2, Locals=1, Args_size=1
	aload_0
	invokevirtual	Method scope:()Lscala/util/parsing/ast/Binders$Scope;
	aload_0
	invokevirtual	Method el:()Lscala/util/parsing/ast/AbstractSyntax$NameElement;
	invokevirtual	Method scala/util/parsing/ast/Binders$Scope.getElementFor:(Lscala/util/parsing/ast/AbstractSyntax$NameElement;)Lscala/util/parsing/ast/AbstractSyntax$Element;
	areturn
  Labels:

public java.lang.String name();
  Signature: ()Ljava/lang/String;
  Code:
   Stack=1, Locals=1, Args_size=1
	aload_0
	invokevirtual	Method self:()Lscala/util/parsing/ast/AbstractSyntax$Element;
	checkcast	class scala/util/parsing/ast/AbstractSyntax$NameElement
	invokeinterface	InterfaceMethod scala/util/parsing/ast/AbstractSyntax$NameElement.name:()Ljava/lang/String;
	areturn
  Labels:

public java.lang.String toString();
  Signature: ()Ljava/lang/String;
  Code:
   Stack=2, Locals=1, Args_size=1
	new	class scala/collection/mutable/StringBuilder
	dup
	invokespecial	Method scala/collection/mutable/StringBuilder."<init>":()V
	aload_0
	invokestatic	Method scala/Proxy$class.toString:(Lscala/Proxy;)Ljava/lang/String;
	invokevirtual	Method scala/collection/mutable/StringBuilder.append:(Ljava/lang/Object;)Lscala/collection/mutable/StringBuilder;
	ldc	String @
	invokevirtual	Method scala/collection/mutable/StringBuilder.append:(Ljava/lang/Object;)Lscala/collection/mutable/StringBuilder;
	aload_0
	invokevirtual	Method scope:()Lscala/util/parsing/ast/Binders$Scope;
	invokevirtual	Method scala/util/parsing/ast/Binders$Scope.id:()I
	invokestatic	Method scala/runtime/BoxesRunTime.boxToInteger:(I)Ljava/lang/Integer;
	invokevirtual	Method scala/collection/mutable/StringBuilder.append:(Ljava/lang/Object;)Lscala/collection/mutable/StringBuilder;
	invokevirtual	Method scala/collection/mutable/StringBuilder.toString:()Ljava/lang/String;
	areturn
  Labels:

public boolean alpha_$eq$eq(scala.util.parsing.ast.Binders$BoundElement);
  Signature: (Lscala/util/parsing/ast/Binders$BoundElement;)Z
  Code:
   Stack=3, Locals=3, Args_size=2
	aload_0
	invokevirtual	Method scope:()Lscala/util/parsing/ast/Binders$Scope;
	aload_0
	invokevirtual	Method el:()Lscala/util/parsing/ast/AbstractSyntax$NameElement;
	invokevirtual	Method scala/util/parsing/ast/Binders$Scope.indexFor:(Lscala/util/parsing/ast/AbstractSyntax$NameElement;)Lscala/Option;
	aload_1
	invokevirtual	Method scope:()Lscala/util/parsing/ast/Binders$Scope;
	aload_1
	invokevirtual	Method el:()Lscala/util/parsing/ast/AbstractSyntax$NameElement;
	invokevirtual	Method scala/util/parsing/ast/Binders$Scope.indexFor:(Lscala/util/parsing/ast/AbstractSyntax$NameElement;)Lscala/Option;
	astore_2
	dup
	ifnonnull	l1 // aload_2
	pop
	aload_2
	ifnull	l2 // iconst_1
	goto	l3 // iconst_0
l1	aload_2
	invokevirtual	Method java/lang/Object.equals:(Ljava/lang/Object;)Z
	ifeq	l3 // iconst_0
l2	iconst_1
	goto	l4 // ireturn
l3	iconst_0
l4	ireturn
  Labels:
   	l1 = 35 // aload_2
   	l2 = 42 // iconst_1
   	l3 = 46 // iconst_0
   	l4 = 47 // ireturn
  LocalVariableTable: 
   Start  Length  Slot  Name   Signature
   0      48      0    this       Lscala/util/parsing/ast/Binders$BoundElement;
   0      48      1    other       Lscala/util/parsing/ast/Binders$BoundElement;

  Signature: length = 0x2
   00 7F 

public scala.util.parsing.ast.Binders$BoundElement copy(scala.util.parsing.ast.AbstractSyntax$NameElement, scala.util.parsing.ast.Binders$Scope);
  Signature: (Lscala/util/parsing/ast/AbstractSyntax$NameElement;Lscala/util/parsing/ast/Binders$Scope;)Lscala/util/parsing/ast/Binders$BoundElement;
  Code:
   Stack=5, Locals=3, Args_size=3
	new	class scala/util/parsing/ast/Binders$BoundElement
	dup
	aload_0
	invokevirtual	Method scala$util$parsing$ast$Binders$BoundElement$$$outer:()Lscala/util/parsing/ast/Binders;
	aload_1
	aload_2
	invokespecial	Method "<init>":(Lscala/util/parsing/ast/Binders;Lscala/util/parsing/ast/AbstractSyntax$NameElement;Lscala/util/parsing/ast/Binders$Scope;)V
	areturn
  Labels:
  LocalVariableTable: 
   Start  Length  Slot  Name   Signature
   0      14      0    this       Lscala/util/parsing/ast/Binders$BoundElement;
   0      14      1    el       Lscala/util/parsing/ast/AbstractSyntax$NameElement;
   0      14      2    scope       Lscala/util/parsing/ast/Binders$Scope;


public java.lang.String productPrefix();
  Signature: ()Ljava/lang/String;
  Code:
   Stack=1, Locals=1, Args_size=1
	ldc	String BoundElement
	areturn
  Labels:

public int productArity();
  Signature: ()I
  Code:
   Stack=1, Locals=1, Args_size=1
	iconst_2
	ireturn
  Labels:

public java.lang.Object productElement(int);
  Signature: (I)Ljava/lang/Object;
  Code:
   Stack=3, Locals=3, Args_size=2
	iload_1
	istore_2
	iload_2
	tableswitch{ //0 to 1
		0: 46;
		1: 39;
		default: 24 }
	new	class java/lang/IndexOutOfBoundsException
	dup
	iload_1
	invokestatic	Method scala/runtime/BoxesRunTime.boxToInteger:(I)Ljava/lang/Integer;
	invokevirtual	Method java/lang/Object.toString:()Ljava/lang/String;
	invokespecial	Method java/lang/IndexOutOfBoundsException."<init>":(Ljava/lang/String;)V
	athrow
	aload_0
	invokevirtual	Method scope:()Lscala/util/parsing/ast/Binders$Scope;
	goto	l1 // areturn
	aload_0
	invokevirtual	Method el:()Lscala/util/parsing/ast/AbstractSyntax$NameElement;
l1	areturn
  Labels:
   	l1 = 50 // areturn
  LocalVariableTable: 
   Start  Length  Slot  Name   Signature
   0      51      0    this       Lscala/util/parsing/ast/Binders$BoundElement;
   2      49      2    temp4       I


public java.lang.String productElementName(int);
  Signature: (I)Ljava/lang/String;
  Code:
   Stack=3, Locals=3, Args_size=2
	iload_1
	istore_2
	iload_2
	tableswitch{ //0 to 1
		0: 44;
		1: 39;
		default: 24 }
	new	class java/lang/IndexOutOfBoundsException
	dup
	iload_1
	invokestatic	Method scala/runtime/BoxesRunTime.boxToInteger:(I)Ljava/lang/Integer;
	invokevirtual	Method java/lang/Object.toString:()Ljava/lang/String;
	invokespecial	Method java/lang/IndexOutOfBoundsException."<init>":(Ljava/lang/String;)V
	athrow
	ldc	String scope
	goto	l1 // areturn
	ldc	String el
l1	areturn
  Labels:
   	l1 = 46 // areturn
  LocalVariableTable: 
   Start  Length  Slot  Name   Signature
   0      47      0    this       Lscala/util/parsing/ast/Binders$BoundElement;
   2      45      2    temp5       I


public boolean canEqual(java.lang.Object);
  Signature: (Ljava/lang/Object;)Z
  Code:
   Stack=1, Locals=2, Args_size=2
	aload_1
	instanceof	class scala/util/parsing/ast/Binders$BoundElement
	ireturn
  Labels:

public scala.util.parsing.ast.Binders scala$util$parsing$ast$Binders$BoundElement$$$outer();
  Signature: ()Lscala/util/parsing/ast/Binders;
  Code:
   Stack=1, Locals=1, Args_size=1
	aload_0
	getfield	Field $outer:Lscala/util/parsing/ast/Binders;
	areturn
  Labels:

public scala.util.parsing.ast.AbstractSyntax scala$util$parsing$ast$AbstractSyntax$NameElement$$$outer();
  Signature: ()Lscala/util/parsing/ast/AbstractSyntax;
  Code:
   Stack=1, Locals=1, Args_size=1
	aload_0
	invokevirtual	Method scala$util$parsing$ast$Binders$BoundElement$$$outer:()Lscala/util/parsing/ast/Binders;
	areturn
  Labels:

public java.lang.Object self();
  Signature: ()Ljava/lang/Object;
  Code:
   Stack=1, Locals=1, Args_size=1
	aload_0
	invokevirtual	Method self:()Lscala/util/parsing/ast/AbstractSyntax$Element;
	areturn
  Labels:

public scala.util.parsing.ast.Binders$BoundElement(scala.util.parsing.ast.Binders, scala.util.parsing.ast.AbstractSyntax$NameElement, scala.util.parsing.ast.Binders$Scope);
  Signature: (Lscala/util/parsing/ast/Binders;Lscala/util/parsing/ast/AbstractSyntax$NameElement;Lscala/util/parsing/ast/Binders$Scope;)V
  Code:
   Stack=2, Locals=4, Args_size=4
	aload_0
	aload_2
	putfield	Field el:Lscala/util/parsing/ast/AbstractSyntax$NameElement;
	aload_0
	aload_3
	putfield	Field scope:Lscala/util/parsing/ast/Binders$Scope;
	aload_1
	ifnonnull	l1 // aload_0
	new	class java/lang/NullPointerException
	dup
	invokespecial	Method java/lang/NullPointerException."<init>":()V
	athrow
l1	aload_0
	aload_1
	putfield	Field $outer:Lscala/util/parsing/ast/Binders;
	aload_0
	invokespecial	Method java/lang/Object."<init>":()V
	aload_0
	invokestatic	Method scala/util/parsing/input/Positional$class.$init$:(Lscala/util/parsing/input/Positional;)V
	aload_0
	invokestatic	Method scala/util/parsing/ast/AbstractSyntax$NameElement$class.$init$:(Lscala/util/parsing/ast/AbstractSyntax$NameElement;)V
	aload_0
	invokestatic	Method scala/Proxy$class.$init$:(Lscala/Proxy;)V
	aload_0
	invokestatic	Method scala/Product$class.$init$:(Lscala/Product;)V
	return
  Labels:
   	l1 = 22 // aload_0
  LocalVariableTable: 
   Start  Length  Slot  Name   Signature
   0      48      0    this       Lscala/util/parsing/ast/Binders$BoundElement;
   0      48      1    $outer       Lscala/util/parsing/ast/Binders;
   0      48      2    el       Lscala/util/parsing/ast/AbstractSyntax$NameElement;
   0      48      3    scope       Lscala/util/parsing/ast/Binders$Scope;

  Signature: length = 0x2
   00 FFFFFFB5 

}

