Compiled from "Binders.scala"
public class scala.util.parsing.ast.Binders$UnderBinder extends java.lang.Object implements scala.util.parsing.ast.AbstractSyntax$Element,scala.util.parsing.ast.Binders$BindingSensitive,scala.ScalaObject
  SourceFile: "Binders.scala"
  Signature: length = 0x2
   00 7E 
  Scala: length = 0x
   
  InnerClass: 
   public #131= #107 of #130; //Scope=class scala/util/parsing/ast/Binders$Scope of class scala/util/parsing/ast/Binders
   public abstract #136= #133 of #135; //Mapper=class scala/util/parsing/ast/Mappable$Mapper of class scala/util/parsing/ast/Mappable
   public abstract #137= #78 of #135; //Mappable=class scala/util/parsing/ast/Mappable$Mappable of class scala/util/parsing/ast/Mappable
   public #138= #21 of #130; //UnderBinder=class scala/util/parsing/ast/Binders$UnderBinder of class scala/util/parsing/ast/Binders
   public abstract #143= #140 of #142; //Element=class scala/util/parsing/ast/AbstractSyntax$Element of class scala/util/parsing/ast/AbstractSyntax
   public abstract #146= #145 of #130; //BindingSensitive=class scala/util/parsing/ast/Binders$BindingSensitive of class scala/util/parsing/ast/Binders
   public final #147= #89 of #21; //$anon$9=class scala/util/parsing/ast/Binders$UnderBinder$$anon$9 of class scala/util/parsing/ast/Binders$UnderBinder
   public final #148= #80 of #21; //$anon$10=class scala/util/parsing/ast/Binders$UnderBinder$$anon$10 of class scala/util/parsing/ast/Binders$UnderBinder
  minor version: 0
  major version: 49
  Constant pool:
const #1 = Asciz	SourceFile;
const #2 = Asciz	Binders.scala;
const #3 = Asciz	pos;
const #4 = Asciz	Lscala/util/parsing/input/Position;;
const #5 = Asciz	$outer;
const #6 = Asciz	Lscala/util/parsing/ast/Binders;;
const #7 = Asciz	evidence$5;
const #8 = Asciz	Lscala/Function1;;
const #9 = Asciz	Lscala/Function1<TelementT;Lscala/util/parsing/ast/Mappable$Mappable<TelementT;>;>;;
const #10 = Asciz	Signature;
const #11 = Asciz	scala$util$parsing$ast$Binders$$element;
const #12 = Asciz	Ljava/lang/Object;;
const #13 = Asciz	scope;
const #14 = Asciz	Lscala/util/parsing/ast/Binders$Scope;;
const #15 = Asciz	Lscala/util/parsing/ast/Binders$Scope<TbinderType;>;;
const #16 = Asciz	<init>;
const #17 = Asciz	(Lscala/util/parsing/ast/Binders;Lscala/util/parsing/ast/Binders$Scope;Ljava/lang/Object;Lscala/Function1;)V;
const #18 = Asciz	Code;
const #19 = Asciz	LineNumberTable;
const #20 = Asciz	scala/util/parsing/ast/Binders$UnderBinder;
const #21 = class	#20;	//  scala/util/parsing/ast/Binders$UnderBinder
const #22 = NameAndType	#13:#14;//  scope:Lscala/util/parsing/ast/Binders$Scope;
const #23 = Field	#21.#22;	//  scala/util/parsing/ast/Binders$UnderBinder.scope:Lscala/util/parsing/ast/Binders$Scope;
const #24 = NameAndType	#11:#12;//  scala$util$parsing$ast$Binders$$element:Ljava/lang/Object;
const #25 = Field	#21.#24;	//  scala/util/parsing/ast/Binders$UnderBinder.scala$util$parsing$ast$Binders$$element:Ljava/lang/Object;
const #26 = NameAndType	#7:#8;//  evidence$5:Lscala/Function1;
const #27 = Field	#21.#26;	//  scala/util/parsing/ast/Binders$UnderBinder.evidence$5:Lscala/Function1;
const #28 = Asciz	java/lang/NullPointerException;
const #29 = class	#28;	//  java/lang/NullPointerException
const #30 = Asciz	()V;
const #31 = NameAndType	#16:#30;//  "<init>":()V
const #32 = Method	#29.#31;	//  java/lang/NullPointerException."<init>":()V
const #33 = NameAndType	#5:#6;//  $outer:Lscala/util/parsing/ast/Binders;
const #34 = Field	#21.#33;	//  scala/util/parsing/ast/Binders$UnderBinder.$outer:Lscala/util/parsing/ast/Binders;
const #35 = Asciz	java/lang/Object;
const #36 = class	#35;	//  java/lang/Object
const #37 = Method	#36.#31;	//  java/lang/Object."<init>":()V
const #38 = Asciz	scala/util/parsing/input/Positional$class;
const #39 = class	#38;	//  scala/util/parsing/input/Positional$class
const #40 = Asciz	$init$;
const #41 = Asciz	(Lscala/util/parsing/input/Positional;)V;
const #42 = NameAndType	#40:#41;//  $init$:(Lscala/util/parsing/input/Positional;)V
const #43 = Method	#39.#42;	//  scala/util/parsing/input/Positional$class.$init$:(Lscala/util/parsing/input/Positional;)V
const #44 = Asciz	this;
const #45 = Asciz	Lscala/util/parsing/ast/Binders$UnderBinder;;
const #46 = Asciz	element;
const #47 = Asciz	LocalVariableTable;
const #48 = Asciz	(Lscala/util/parsing/ast/Binders;Lscala/util/parsing/ast/Binders$Scope<TbinderType;>;TelementT;Lscala/Function1<TelementT;Lscala/util/parsing/ast/Mappable$Mappable<TelementT;>;>;)V;
const #49 = Asciz	scala$util$parsing$ast$Binders$UnderBinder$$$outer;
const #50 = Asciz	()Lscala/util/parsing/ast/Binders;;
const #51 = Asciz	elementToString;
const #52 = Asciz	()Ljava/lang/String;;
const #53 = Asciz	()Ljava/lang/Object;;
const #54 = NameAndType	#11:#53;//  scala$util$parsing$ast$Binders$$element:()Ljava/lang/Object;
const #55 = Method	#21.#54;	//  scala/util/parsing/ast/Binders$UnderBinder.scala$util$parsing$ast$Binders$$element:()Ljava/lang/Object;
const #56 = Asciz	toString;
const #57 = NameAndType	#56:#52;//  toString:()Ljava/lang/String;
const #58 = Method	#36.#57;	//  java/lang/Object.toString:()Ljava/lang/String;
const #59 = Asciz	extract;
const #60 = Asciz	(Lscala/collection/immutable/Map;)Ljava/lang/Object;;
const #61 = Asciz	cloneElementWithSubst;
const #62 = NameAndType	#61:#60;//  cloneElementWithSubst:(Lscala/collection/immutable/Map;)Ljava/lang/Object;
const #63 = Method	#21.#62;	//  scala/util/parsing/ast/Binders$UnderBinder.cloneElementWithSubst:(Lscala/collection/immutable/Map;)Ljava/lang/Object;
const #64 = Asciz	subst;
const #65 = Asciz	Lscala/collection/immutable/Map;;
const #66 = Asciz	(Lscala/collection/immutable/Map<Lscala/util/parsing/ast/AbstractSyntax$NameElement;Lscala/util/parsing/ast/AbstractSyntax$NameElement;>;)TelementT;;
const #67 = Asciz	cloneElementNoBoundElements;
const #68 = NameAndType	#67:#53;//  cloneElementNoBoundElements:()Ljava/lang/Object;
const #69 = Method	#21.#68;	//  scala/util/parsing/ast/Binders$UnderBinder.cloneElementNoBoundElements:()Ljava/lang/Object;
const #70 = Asciz	()TelementT;;
const #71 = Asciz	scala/Function1;
const #72 = class	#71;	//  scala/Function1
const #73 = Asciz	apply;
const #74 = Asciz	(Ljava/lang/Object;)Ljava/lang/Object;;
const #75 = NameAndType	#73:#74;//  apply:(Ljava/lang/Object;)Ljava/lang/Object;
const #76 = InterfaceMethod	#72.#75;	//  scala/Function1.apply:(Ljava/lang/Object;)Ljava/lang/Object;
const #77 = Asciz	scala/util/parsing/ast/Mappable$Mappable;
const #78 = class	#77;	//  scala/util/parsing/ast/Mappable$Mappable
const #79 = Asciz	scala/util/parsing/ast/Binders$UnderBinder$$anon$10;
const #80 = class	#79;	//  scala/util/parsing/ast/Binders$UnderBinder$$anon$10
const #81 = Asciz	(Lscala/util/parsing/ast/Binders$UnderBinder;)V;
const #82 = NameAndType	#16:#81;//  "<init>":(Lscala/util/parsing/ast/Binders$UnderBinder;)V
const #83 = Method	#80.#82;	//  scala/util/parsing/ast/Binders$UnderBinder$$anon$10."<init>":(Lscala/util/parsing/ast/Binders$UnderBinder;)V
const #84 = Asciz	gmap;
const #85 = Asciz	(Lscala/util/parsing/ast/Mappable$Mapper;)Ljava/lang/Object;;
const #86 = NameAndType	#84:#85;//  gmap:(Lscala/util/parsing/ast/Mappable$Mapper;)Ljava/lang/Object;
const #87 = InterfaceMethod	#78.#86;	//  scala/util/parsing/ast/Mappable$Mappable.gmap:(Lscala/util/parsing/ast/Mappable$Mapper;)Ljava/lang/Object;
const #88 = Asciz	scala/util/parsing/ast/Binders$UnderBinder$$anon$9;
const #89 = class	#88;	//  scala/util/parsing/ast/Binders$UnderBinder$$anon$9
const #90 = Asciz	(Lscala/util/parsing/ast/Binders$UnderBinder;Lscala/collection/immutable/Map;)V;
const #91 = NameAndType	#16:#90;//  "<init>":(Lscala/util/parsing/ast/Binders$UnderBinder;Lscala/collection/immutable/Map;)V
const #92 = Method	#89.#91;	//  scala/util/parsing/ast/Binders$UnderBinder$$anon$9."<init>":(Lscala/util/parsing/ast/Binders$UnderBinder;Lscala/collection/immutable/Map;)V
const #93 = Asciz	subst$1;
const #94 = Asciz	scala/collection/mutable/StringBuilder;
const #95 = class	#94;	//  scala/collection/mutable/StringBuilder
const #96 = Method	#95.#31;	//  scala/collection/mutable/StringBuilder."<init>":()V
const #97 = Asciz	(;
const #98 = String	#97;	//  (
const #99 = Asciz	append;
const #100 = Asciz	(Ljava/lang/Object;)Lscala/collection/mutable/StringBuilder;;
const #101 = NameAndType	#99:#100;//  append:(Ljava/lang/Object;)Lscala/collection/mutable/StringBuilder;
const #102 = Method	#95.#101;	//  scala/collection/mutable/StringBuilder.append:(Ljava/lang/Object;)Lscala/collection/mutable/StringBuilder;
const #103 = Asciz	()Lscala/util/parsing/ast/Binders$Scope;;
const #104 = NameAndType	#13:#103;//  scope:()Lscala/util/parsing/ast/Binders$Scope;
const #105 = Method	#21.#104;	//  scala/util/parsing/ast/Binders$UnderBinder.scope:()Lscala/util/parsing/ast/Binders$Scope;
const #106 = Asciz	scala/util/parsing/ast/Binders$Scope;
const #107 = class	#106;	//  scala/util/parsing/ast/Binders$Scope
const #108 = Method	#107.#57;	//  scala/util/parsing/ast/Binders$Scope.toString:()Ljava/lang/String;
const #109 = Asciz	) in { ;
const #110 = String	#109;	//  ) in { 
const #111 = Asciz	 };
const #112 = String	#111;	//   }
const #113 = Method	#95.#57;	//  scala/collection/mutable/StringBuilder.toString:()Ljava/lang/String;
const #114 = Asciz	()Lscala/util/parsing/ast/Binders$Scope<TbinderType;>;;
const #115 = Asciz	setPos;
const #116 = Asciz	(Lscala/util/parsing/input/Position;)Lscala/util/parsing/input/Positional;;
const #117 = Asciz	(Lscala/util/parsing/input/Positional;Lscala/util/parsing/input/Position;)Lscala/util/parsing/input/Positional;;
const #118 = NameAndType	#115:#117;//  setPos:(Lscala/util/parsing/input/Positional;Lscala/util/parsing/input/Position;)Lscala/util/parsing/input/Positional;
const #119 = Method	#39.#118;	//  scala/util/parsing/input/Positional$class.setPos:(Lscala/util/parsing/input/Positional;Lscala/util/parsing/input/Position;)Lscala/util/parsing/input/Positional;
const #120 = Asciz	newpos;
const #121 = Asciz	pos_$eq;
const #122 = Asciz	(Lscala/util/parsing/input/Position;)V;
const #123 = NameAndType	#3:#4;//  pos:Lscala/util/parsing/input/Position;
const #124 = Field	#21.#123;	//  scala/util/parsing/ast/Binders$UnderBinder.pos:Lscala/util/parsing/input/Position;
const #125 = Asciz	()Lscala/util/parsing/input/Position;;
const #126 = Asciz	<binderType::Lscala/util/parsing/ast/AbstractSyntax$NameElement;elementT:Ljava/lang/Object;>Ljava/lang/Object;Lscala/util/parsing/ast/AbstractSyntax$Element;Lscala/util/parsing/ast/Binders$BindingSensitive;Lscala/ScalaObject;;
const #127 = Asciz	Scala;
const #128 = Asciz	InnerClasses;
const #129 = Asciz	scala/util/parsing/ast/Binders;
const #130 = class	#129;	//  scala/util/parsing/ast/Binders
const #131 = Asciz	Scope;
const #132 = Asciz	scala/util/parsing/ast/Mappable$Mapper;
const #133 = class	#132;	//  scala/util/parsing/ast/Mappable$Mapper
const #134 = Asciz	scala/util/parsing/ast/Mappable;
const #135 = class	#134;	//  scala/util/parsing/ast/Mappable
const #136 = Asciz	Mapper;
const #137 = Asciz	Mappable;
const #138 = Asciz	UnderBinder;
const #139 = Asciz	scala/util/parsing/ast/AbstractSyntax$Element;
const #140 = class	#139;	//  scala/util/parsing/ast/AbstractSyntax$Element
const #141 = Asciz	scala/util/parsing/ast/AbstractSyntax;
const #142 = class	#141;	//  scala/util/parsing/ast/AbstractSyntax
const #143 = Asciz	Element;
const #144 = Asciz	scala/util/parsing/ast/Binders$BindingSensitive;
const #145 = class	#144;	//  scala/util/parsing/ast/Binders$BindingSensitive
const #146 = Asciz	BindingSensitive;
const #147 = Asciz	$anon$9;
const #148 = Asciz	$anon$10;
const #149 = Asciz	scala/ScalaObject;
const #150 = class	#149;	//  scala/ScalaObject

{
public final scala.util.parsing.ast.Binders $outer;

public scala.util.parsing.ast.Binders$UnderBinder(scala.util.parsing.ast.Binders, scala.util.parsing.ast.Binders$Scope, java.lang.Object, scala.Function1);
  Code:
   Stack=2, Locals=5, Args_size=5
   0:	aload_0
   1:	aload_2
   2:	putfield	#23; //Field scope:Lscala/util/parsing/ast/Binders$Scope;
   5:	aload_0
   6:	aload_3
   7:	putfield	#25; //Field scala$util$parsing$ast$Binders$$element:Ljava/lang/Object;
   10:	aload_0
   11:	aload	4
   13:	putfield	#27; //Field evidence$5:Lscala/Function1;
   16:	aload_1
   17:	ifnonnull	28
   20:	new	#29; //class java/lang/NullPointerException
   23:	dup
   24:	invokespecial	#32; //Method java/lang/NullPointerException."<init>":()V
   27:	athrow
   28:	aload_0
   29:	aload_1
   30:	putfield	#34; //Field $outer:Lscala/util/parsing/ast/Binders;
   33:	aload_0
   34:	invokespecial	#37; //Method java/lang/Object."<init>":()V
   37:	aload_0
   38:	invokestatic	#43; //Method scala/util/parsing/input/Positional$class.$init$:(Lscala/util/parsing/input/Positional;)V
   41:	return
  LineNumberTable: 
   line 225: 0

  LocalVariableTable: 
   Start  Length  Slot  Name   Signature
   0      42      0    this       Lscala/util/parsing/ast/Binders$UnderBinder;
   0      42      1    $outer       Lscala/util/parsing/ast/Binders;
   0      42      2    scope       Lscala/util/parsing/ast/Binders$Scope;
   0      42      3    element       Ljava/lang/Object;
   0      42      4    evidence$5       Lscala/Function1;

  Signature: length = 0x2
   00 30 

public scala.util.parsing.ast.Binders scala$util$parsing$ast$Binders$UnderBinder$$$outer();
  Code:
   Stack=1, Locals=1, Args_size=1
   0:	aload_0
   1:	getfield	#34; //Field $outer:Lscala/util/parsing/ast/Binders;
   4:	areturn
  LineNumberTable: 
   line 225: 0


public java.lang.String elementToString();
  Code:
   Stack=1, Locals=1, Args_size=1
   0:	aload_0
   1:	invokevirtual	#55; //Method scala$util$parsing$ast$Binders$$element:()Ljava/lang/Object;
   4:	invokevirtual	#58; //Method java/lang/Object.toString:()Ljava/lang/String;
   7:	areturn
  LineNumberTable: 
   line 267: 0


public java.lang.Object extract(scala.collection.immutable.Map);
  Code:
   Stack=2, Locals=2, Args_size=2
   0:	aload_0
   1:	aload_1
   2:	invokevirtual	#63; //Method cloneElementWithSubst:(Lscala/collection/immutable/Map;)Ljava/lang/Object;
   5:	areturn
  LineNumberTable: 
   line 264: 0

  LocalVariableTable: 
   Start  Length  Slot  Name   Signature
   0      6      0    this       Lscala/util/parsing/ast/Binders$UnderBinder;
   0      6      1    subst       Lscala/collection/immutable/Map;

  Signature: length = 0x2
   00 42 

public java.lang.Object extract();
  Code:
   Stack=1, Locals=1, Args_size=1
   0:	aload_0
   1:	invokevirtual	#69; //Method cloneElementNoBoundElements:()Ljava/lang/Object;
   4:	areturn
  LineNumberTable: 
   line 263: 0

  Signature: length = 0x2
   00 46 

public java.lang.Object cloneElementNoBoundElements();
  Code:
   Stack=4, Locals=1, Args_size=1
   0:	aload_0
   1:	getfield	#27; //Field evidence$5:Lscala/Function1;
   4:	aload_0
   5:	invokevirtual	#55; //Method scala$util$parsing$ast$Binders$$element:()Ljava/lang/Object;
   8:	invokeinterface	#76,  2; //InterfaceMethod scala/Function1.apply:(Ljava/lang/Object;)Ljava/lang/Object;
   13:	checkcast	#78; //class scala/util/parsing/ast/Mappable$Mappable
   16:	new	#80; //class scala/util/parsing/ast/Binders$UnderBinder$$anon$10
   19:	dup
   20:	aload_0
   21:	invokespecial	#83; //Method scala/util/parsing/ast/Binders$UnderBinder$$anon$10."<init>":(Lscala/util/parsing/ast/Binders$UnderBinder;)V
   24:	invokeinterface	#87,  2; //InterfaceMethod scala/util/parsing/ast/Mappable$Mappable.gmap:(Lscala/util/parsing/ast/Mappable$Mapper;)Ljava/lang/Object;
   29:	areturn
  LineNumberTable: 
   line 258: 0

  Signature: length = 0x2
   00 46 

public java.lang.Object cloneElementWithSubst(scala.collection.immutable.Map);
  Code:
   Stack=5, Locals=2, Args_size=2
   0:	aload_0
   1:	getfield	#27; //Field evidence$5:Lscala/Function1;
   4:	aload_0
   5:	invokevirtual	#55; //Method scala$util$parsing$ast$Binders$$element:()Ljava/lang/Object;
   8:	invokeinterface	#76,  2; //InterfaceMethod scala/Function1.apply:(Ljava/lang/Object;)Ljava/lang/Object;
   13:	checkcast	#78; //class scala/util/parsing/ast/Mappable$Mappable
   16:	new	#89; //class scala/util/parsing/ast/Binders$UnderBinder$$anon$9
   19:	dup
   20:	aload_0
   21:	aload_1
   22:	invokespecial	#92; //Method scala/util/parsing/ast/Binders$UnderBinder$$anon$9."<init>":(Lscala/util/parsing/ast/Binders$UnderBinder;Lscala/collection/immutable/Map;)V
   25:	invokeinterface	#87,  2; //InterfaceMethod scala/util/parsing/ast/Mappable$Mappable.gmap:(Lscala/util/parsing/ast/Mappable$Mapper;)Ljava/lang/Object;
   30:	areturn
  LineNumberTable: 
   line 251: 0

  LocalVariableTable: 
   Start  Length  Slot  Name   Signature
   0      31      0    this       Lscala/util/parsing/ast/Binders$UnderBinder;
   0      31      1    subst$1       Lscala/collection/immutable/Map;

  Signature: length = 0x2
   00 42 

public java.lang.String toString();
  Code:
   Stack=2, Locals=1, Args_size=1
   0:	new	#95; //class scala/collection/mutable/StringBuilder
   3:	dup
   4:	invokespecial	#96; //Method scala/collection/mutable/StringBuilder."<init>":()V
   7:	ldc	#98; //String (
   9:	invokevirtual	#102; //Method scala/collection/mutable/StringBuilder.append:(Ljava/lang/Object;)Lscala/collection/mutable/StringBuilder;
   12:	aload_0
   13:	invokevirtual	#105; //Method scope:()Lscala/util/parsing/ast/Binders$Scope;
   16:	invokevirtual	#108; //Method scala/util/parsing/ast/Binders$Scope.toString:()Ljava/lang/String;
   19:	invokevirtual	#102; //Method scala/collection/mutable/StringBuilder.append:(Ljava/lang/Object;)Lscala/collection/mutable/StringBuilder;
   22:	ldc	#110; //String ) in { 
   24:	invokevirtual	#102; //Method scala/collection/mutable/StringBuilder.append:(Ljava/lang/Object;)Lscala/collection/mutable/StringBuilder;
   27:	aload_0
   28:	invokevirtual	#55; //Method scala$util$parsing$ast$Binders$$element:()Ljava/lang/Object;
   31:	invokevirtual	#58; //Method java/lang/Object.toString:()Ljava/lang/String;
   34:	invokevirtual	#102; //Method scala/collection/mutable/StringBuilder.append:(Ljava/lang/Object;)Lscala/collection/mutable/StringBuilder;
   37:	ldc	#112; //String  }
   39:	invokevirtual	#102; //Method scala/collection/mutable/StringBuilder.append:(Ljava/lang/Object;)Lscala/collection/mutable/StringBuilder;
   42:	invokevirtual	#113; //Method scala/collection/mutable/StringBuilder.toString:()Ljava/lang/String;
   45:	areturn
  LineNumberTable: 
   line 226: 0


public java.lang.Object scala$util$parsing$ast$Binders$$element();
  Code:
   Stack=1, Locals=1, Args_size=1
   0:	aload_0
   1:	getfield	#25; //Field scala$util$parsing$ast$Binders$$element:Ljava/lang/Object;
   4:	areturn
  LineNumberTable: 
   line 225: 0


public scala.util.parsing.ast.Binders$Scope scope();
  Code:
   Stack=1, Locals=1, Args_size=1
   0:	aload_0
   1:	getfield	#23; //Field scope:Lscala/util/parsing/ast/Binders$Scope;
   4:	areturn
  LineNumberTable: 
   line 225: 0

  Signature: length = 0x2
   00 72 

public scala.util.parsing.input.Positional setPos(scala.util.parsing.input.Position);
  Code:
   Stack=2, Locals=2, Args_size=2
   0:	aload_0
   1:	aload_1
   2:	invokestatic	#119; //Method scala/util/parsing/input/Positional$class.setPos:(Lscala/util/parsing/input/Positional;Lscala/util/parsing/input/Position;)Lscala/util/parsing/input/Positional;
   5:	areturn
  LineNumberTable: 
   line 225: 0

  LocalVariableTable: 
   Start  Length  Slot  Name   Signature
   0      6      0    this       Lscala/util/parsing/ast/Binders$UnderBinder;
   0      6      1    newpos       Lscala/util/parsing/input/Position;


public void pos_$eq(scala.util.parsing.input.Position);
  Code:
   Stack=2, Locals=2, Args_size=2
   0:	aload_0
   1:	aload_1
   2:	putfield	#124; //Field pos:Lscala/util/parsing/input/Position;
   5:	return
  LineNumberTable: 
   line 225: 0


public scala.util.parsing.input.Position pos();
  Code:
   Stack=1, Locals=1, Args_size=1
   0:	aload_0
   1:	getfield	#124; //Field pos:Lscala/util/parsing/input/Position;
   4:	areturn
  LineNumberTable: 
   line 225: 0


}

