Compiled from "Binders.scala"
public final class scala.util.parsing.ast.Binders$_Binder$$anonfun$genId$1 extends java.lang.Object implements scala.Function0,scala.ScalaObject,java.io.Serializable
  SourceFile: "Binders.scala"
  Scala: length = 0x
   
  InnerClass: 
   public final $anonfun$genId$1=class scala/util/parsing/ast/Binders$_Binder$$anonfun$genId$1 of class scala/util/parsing/ast/Binders$_Binder$
  minor version: 0
  major version: 49
  Constant pool:
Asciz	SourceFile;
Asciz	Binders.scala;
Asciz	<clinit>;
Asciz	()V;
Asciz	Code;
Asciz	serialVersionUID;
Asciz	J;
Asciz	scala/util/parsing/ast/Binders$_Binder$$anonfun$genId$1;
class	scala/util/parsing/ast/Binders$_Binder$$anonfun$genId$1
NameAndType	serialVersionUID:J
Field	scala/util/parsing/ast/Binders$_Binder$$anonfun$genId$1.serialVersionUID:J
Asciz	$outer;
Asciz	Lscala/util/parsing/ast/Binders$_Binder$;;
Asciz	<init>;
Asciz	(Lscala/util/parsing/ast/Binders$_Binder$;)V;
Asciz	LineNumberTable;
Asciz	java/lang/NullPointerException;
class	java/lang/NullPointerException
NameAndType	"<init>":()V
Method	java/lang/NullPointerException."<init>":()V
NameAndType	$outer:Lscala/util/parsing/ast/Binders$_Binder$;
Field	scala/util/parsing/ast/Binders$_Binder$$anonfun$genId$1.$outer:Lscala/util/parsing/ast/Binders$_Binder$;
Asciz	java/lang/Object;
class	java/lang/Object
Method	java/lang/Object."<init>":()V
Asciz	scala/Function0$class;
class	scala/Function0$class
Asciz	$init$;
Asciz	(Lscala/Function0;)V;
NameAndType	$init$:(Lscala/Function0;)V
Method	scala/Function0$class.$init$:(Lscala/Function0;)V
Asciz	this;
Asciz	Lscala/util/parsing/ast/Binders$_Binder$$anonfun$genId$1;;
Asciz	LocalVariableTable;
Asciz	apply;
Asciz	()Ljava/lang/Object;;
NameAndType	apply:()V
Method	scala/util/parsing/ast/Binders$_Binder$$anonfun$genId$1.apply:()V
Asciz	scala/runtime/BoxedUnit;
class	scala/runtime/BoxedUnit
Asciz	UNIT;
Asciz	Lscala/runtime/BoxedUnit;;
NameAndType	UNIT:Lscala/runtime/BoxedUnit;
Field	scala/runtime/BoxedUnit.UNIT:Lscala/runtime/BoxedUnit;
Asciz	scala/util/parsing/ast/Binders$_Binder$;
class	scala/util/parsing/ast/Binders$_Binder$
Asciz	scala$util$parsing$ast$Binders$_Binder$$currentId;
Asciz	()I;
NameAndType	scala$util$parsing$ast$Binders$_Binder$$currentId:()I
Method	scala/util/parsing/ast/Binders$_Binder$.scala$util$parsing$ast$Binders$_Binder$$currentId:()I
Asciz	scala$util$parsing$ast$Binders$_Binder$$currentId_$eq;
Asciz	(I)V;
NameAndType	scala$util$parsing$ast$Binders$_Binder$$currentId_$eq:(I)V
Method	scala/util/parsing/ast/Binders$_Binder$.scala$util$parsing$ast$Binders$_Binder$$currentId_$eq:(I)V
Asciz	toString;
Asciz	()Ljava/lang/String;;
Asciz	(Lscala/Function0;)Ljava/lang/String;;
NameAndType	toString:(Lscala/Function0;)Ljava/lang/String;
Method	scala/Function0$class.toString:(Lscala/Function0;)Ljava/lang/String;
Asciz	Scala;
Asciz	InnerClasses;
Asciz	$anonfun$genId$1;
Asciz	scala/Function0;
class	scala/Function0
Asciz	scala/ScalaObject;
class	scala/ScalaObject
Asciz	java/io/Serializable;
class	java/io/Serializable

{
public static final long serialVersionUID;
  Signature: J

private final scala.util.parsing.ast.Binders$_Binder$ $outer;
  Signature: Lscala/util/parsing/ast/Binders$_Binder$;

public static {};
  Signature: ()V
  Code:
   Stack=2, Locals=0, Args_size=0
	lconst_0
	putstatic	Field serialVersionUID:J
	return
  Labels:

public scala.util.parsing.ast.Binders$_Binder$$anonfun$genId$1(scala.util.parsing.ast.Binders$_Binder$);
  Signature: (Lscala/util/parsing/ast/Binders$_Binder$;)V
  Code:
   Stack=2, Locals=2, Args_size=2
	aload_1
	ifnonnull	l1 // aload_0
	new	class java/lang/NullPointerException
	dup
	invokespecial	Method java/lang/NullPointerException."<init>":()V
	athrow
l1	aload_0
	aload_1
	putfield	Field $outer:Lscala/util/parsing/ast/Binders$_Binder$;
	aload_0
	invokespecial	Method java/lang/Object."<init>":()V
	aload_0
	invokestatic	Method scala/Function0$class.$init$:(Lscala/Function0;)V
	return
  Labels:
   	l1 = 12 // aload_0
  LocalVariableTable: 
   Start  Length  Slot  Name   Signature
   0      26      0    this       Lscala/util/parsing/ast/Binders$_Binder$$anonfun$genId$1;
   0      26      1    $outer       Lscala/util/parsing/ast/Binders$_Binder$;


public final java.lang.Object apply();
  Signature: ()Ljava/lang/Object;
  Code:
   Stack=1, Locals=2, Args_size=1
	aload_0
	getfield	Field $outer:Lscala/util/parsing/ast/Binders$_Binder$;
	astore_1
	aload_0
	invokevirtual	Method apply:()V
	getstatic	Field scala/runtime/BoxedUnit.UNIT:Lscala/runtime/BoxedUnit;
	areturn
  Labels:
  LocalVariableTable: 
   Start  Length  Slot  Name   Signature
   0      13      0    this       Lscala/util/parsing/ast/Binders$_Binder$$anonfun$genId$1;


public final void apply();
  Signature: ()V
  Code:
   Stack=3, Locals=2, Args_size=1
	aload_0
	getfield	Field $outer:Lscala/util/parsing/ast/Binders$_Binder$;
	astore_1
	aload_0
	getfield	Field $outer:Lscala/util/parsing/ast/Binders$_Binder$;
	aload_0
	getfield	Field $outer:Lscala/util/parsing/ast/Binders$_Binder$;
	invokevirtual	Method scala/util/parsing/ast/Binders$_Binder$.scala$util$parsing$ast$Binders$_Binder$$currentId:()I
	iconst_1
	iadd
	invokevirtual	Method scala/util/parsing/ast/Binders$_Binder$.scala$util$parsing$ast$Binders$_Binder$$currentId_$eq:(I)V
	return
  Labels:
  LocalVariableTable: 
   Start  Length  Slot  Name   Signature
   0      22      0    this       Lscala/util/parsing/ast/Binders$_Binder$$anonfun$genId$1;


public java.lang.String toString();
  Signature: ()Ljava/lang/String;
  Code:
   Stack=1, Locals=1, Args_size=1
	aload_0
	invokestatic	Method scala/Function0$class.toString:(Lscala/Function0;)Ljava/lang/String;
	areturn
  Labels:

}

