Compiled from "Binders.scala"
public final class scala.util.parsing.ast.Binders$BoundElement$ extends java.lang.Object implements scala.ScalaObject
  SourceFile: "Binders.scala"
  Scala: length = 0x
   
  InnerClass: 
   public #61= #58 of #60; //Scope=class scala/util/parsing/ast/Binders$Scope of class scala/util/parsing/ast/Binders
   public #62= #28 of #60; //BoundElement=class scala/util/parsing/ast/Binders$BoundElement of class scala/util/parsing/ast/Binders
   public abstract #67= #64 of #66; //NameElement=class scala/util/parsing/ast/AbstractSyntax$NameElement of class scala/util/parsing/ast/AbstractSyntax
  minor version: 0
  major version: 49
  Constant pool:
const #1 = Asciz	SourceFile;
const #2 = Asciz	Binders.scala;
const #3 = Asciz	Scala;
const #4 = Asciz	$outer;
const #5 = Asciz	Lscala/util/parsing/ast/Binders;;
const #6 = Asciz	<init>;
const #7 = Asciz	(Lscala/util/parsing/ast/Binders;)V;
const #8 = Asciz	Code;
const #9 = Asciz	LineNumberTable;
const #10 = Asciz	java/lang/NullPointerException;
const #11 = class	#10;	//  java/lang/NullPointerException
const #12 = Asciz	()V;
const #13 = NameAndType	#6:#12;//  "<init>":()V
const #14 = Method	#11.#13;	//  java/lang/NullPointerException."<init>":()V
const #15 = Asciz	scala/util/parsing/ast/Binders$BoundElement$;
const #16 = class	#15;	//  scala/util/parsing/ast/Binders$BoundElement$
const #17 = NameAndType	#4:#5;//  $outer:Lscala/util/parsing/ast/Binders;
const #18 = Field	#16.#17;	//  scala/util/parsing/ast/Binders$BoundElement$.$outer:Lscala/util/parsing/ast/Binders;
const #19 = Asciz	java/lang/Object;
const #20 = class	#19;	//  java/lang/Object
const #21 = Method	#20.#13;	//  java/lang/Object."<init>":()V
const #22 = Asciz	this;
const #23 = Asciz	Lscala/util/parsing/ast/Binders$BoundElement$;;
const #24 = Asciz	LocalVariableTable;
const #25 = Asciz	apply;
const #26 = Asciz	(Lscala/util/parsing/ast/AbstractSyntax$NameElement;Lscala/util/parsing/ast/Binders$Scope;)Lscala/util/parsing/ast/Binders$BoundElement;;
const #27 = Asciz	scala/util/parsing/ast/Binders$BoundElement;
const #28 = class	#27;	//  scala/util/parsing/ast/Binders$BoundElement
const #29 = Asciz	(Lscala/util/parsing/ast/Binders;Lscala/util/parsing/ast/AbstractSyntax$NameElement;Lscala/util/parsing/ast/Binders$Scope;)V;
const #30 = NameAndType	#6:#29;//  "<init>":(Lscala/util/parsing/ast/Binders;Lscala/util/parsing/ast/AbstractSyntax$NameElement;Lscala/util/parsing/ast/Binders$Scope;)V
const #31 = Method	#28.#30;	//  scala/util/parsing/ast/Binders$BoundElement."<init>":(Lscala/util/parsing/ast/Binders;Lscala/util/parsing/ast/AbstractSyntax$NameElement;Lscala/util/parsing/ast/Binders$Scope;)V
const #32 = Asciz	el;
const #33 = Asciz	Lscala/util/parsing/ast/AbstractSyntax$NameElement;;
const #34 = Asciz	scope;
const #35 = Asciz	Lscala/util/parsing/ast/Binders$Scope;;
const #36 = Asciz	unapply;
const #37 = Asciz	(Lscala/util/parsing/ast/Binders$BoundElement;)Lscala/Some;;
const #38 = Asciz	scala/Some;
const #39 = class	#38;	//  scala/Some
const #40 = Asciz	scala/Tuple2;
const #41 = class	#40;	//  scala/Tuple2
const #42 = Asciz	()Lscala/util/parsing/ast/AbstractSyntax$NameElement;;
const #43 = NameAndType	#32:#42;//  el:()Lscala/util/parsing/ast/AbstractSyntax$NameElement;
const #44 = Method	#28.#43;	//  scala/util/parsing/ast/Binders$BoundElement.el:()Lscala/util/parsing/ast/AbstractSyntax$NameElement;
const #45 = Asciz	()Lscala/util/parsing/ast/Binders$Scope;;
const #46 = NameAndType	#34:#45;//  scope:()Lscala/util/parsing/ast/Binders$Scope;
const #47 = Method	#28.#46;	//  scala/util/parsing/ast/Binders$BoundElement.scope:()Lscala/util/parsing/ast/Binders$Scope;
const #48 = Asciz	(Ljava/lang/Object;Ljava/lang/Object;)V;
const #49 = NameAndType	#6:#48;//  "<init>":(Ljava/lang/Object;Ljava/lang/Object;)V
const #50 = Method	#41.#49;	//  scala/Tuple2."<init>":(Ljava/lang/Object;Ljava/lang/Object;)V
const #51 = Asciz	(Ljava/lang/Object;)V;
const #52 = NameAndType	#6:#51;//  "<init>":(Ljava/lang/Object;)V
const #53 = Method	#39.#52;	//  scala/Some."<init>":(Ljava/lang/Object;)V
const #54 = Asciz	x$0;
const #55 = Asciz	Lscala/util/parsing/ast/Binders$BoundElement;;
const #56 = Asciz	InnerClasses;
const #57 = Asciz	scala/util/parsing/ast/Binders$Scope;
const #58 = class	#57;	//  scala/util/parsing/ast/Binders$Scope
const #59 = Asciz	scala/util/parsing/ast/Binders;
const #60 = class	#59;	//  scala/util/parsing/ast/Binders
const #61 = Asciz	Scope;
const #62 = Asciz	BoundElement;
const #63 = Asciz	scala/util/parsing/ast/AbstractSyntax$NameElement;
const #64 = class	#63;	//  scala/util/parsing/ast/AbstractSyntax$NameElement
const #65 = Asciz	scala/util/parsing/ast/AbstractSyntax;
const #66 = class	#65;	//  scala/util/parsing/ast/AbstractSyntax
const #67 = Asciz	NameElement;
const #68 = Asciz	scala/ScalaObject;
const #69 = class	#68;	//  scala/ScalaObject

{
public scala.util.parsing.ast.Binders$BoundElement$(scala.util.parsing.ast.Binders);
  Code:
   Stack=2, Locals=2, Args_size=2
   0:	aload_1
   1:	ifnonnull	12
   4:	new	#11; //class java/lang/NullPointerException
   7:	dup
   8:	invokespecial	#14; //Method java/lang/NullPointerException."<init>":()V
   11:	athrow
   12:	aload_0
   13:	aload_1
   14:	putfield	#18; //Field $outer:Lscala/util/parsing/ast/Binders;
   17:	aload_0
   18:	invokespecial	#21; //Method java/lang/Object."<init>":()V
   21:	return
  LineNumberTable: 
   line 198: 0

  LocalVariableTable: 
   Start  Length  Slot  Name   Signature
   0      22      0    this       Lscala/util/parsing/ast/Binders$BoundElement$;
   0      22      1    $outer       Lscala/util/parsing/ast/Binders;


public scala.util.parsing.ast.Binders$BoundElement apply(scala.util.parsing.ast.AbstractSyntax$NameElement, scala.util.parsing.ast.Binders$Scope);
  Code:
   Stack=5, Locals=3, Args_size=3
   0:	new	#28; //class scala/util/parsing/ast/Binders$BoundElement
   3:	dup
   4:	aload_0
   5:	getfield	#18; //Field $outer:Lscala/util/parsing/ast/Binders;
   8:	aload_1
   9:	aload_2
   10:	invokespecial	#31; //Method scala/util/parsing/ast/Binders$BoundElement."<init>":(Lscala/util/parsing/ast/Binders;Lscala/util/parsing/ast/AbstractSyntax$NameElement;Lscala/util/parsing/ast/Binders$Scope;)V
   13:	areturn
  LineNumberTable: 
   line 198: 0

  LocalVariableTable: 
   Start  Length  Slot  Name   Signature
   0      14      0    this       Lscala/util/parsing/ast/Binders$BoundElement$;
   0      14      1    el       Lscala/util/parsing/ast/AbstractSyntax$NameElement;
   0      14      2    scope       Lscala/util/parsing/ast/Binders$Scope;


public scala.Some unapply(scala.util.parsing.ast.Binders$BoundElement);
  Code:
   Stack=6, Locals=2, Args_size=2
   0:	new	#39; //class scala/Some
   3:	dup
   4:	new	#41; //class scala/Tuple2
   7:	dup
   8:	aload_1
   9:	invokevirtual	#44; //Method scala/util/parsing/ast/Binders$BoundElement.el:()Lscala/util/parsing/ast/AbstractSyntax$NameElement;
   12:	aload_1
   13:	invokevirtual	#47; //Method scala/util/parsing/ast/Binders$BoundElement.scope:()Lscala/util/parsing/ast/Binders$Scope;
   16:	invokespecial	#50; //Method scala/Tuple2."<init>":(Ljava/lang/Object;Ljava/lang/Object;)V
   19:	invokespecial	#53; //Method scala/Some."<init>":(Ljava/lang/Object;)V
   22:	areturn
  LineNumberTable: 
   line 198: 0

  LocalVariableTable: 
   Start  Length  Slot  Name   Signature
   0      23      0    this       Lscala/util/parsing/ast/Binders$BoundElement$;
   0      23      1    x$0       Lscala/util/parsing/ast/Binders$BoundElement;


}

