Compiled from "Binders.scala"
public final class scala.util.parsing.ast.Binders$_Binder$ extends java.lang.Object implements scala.ScalaObject
  SourceFile: "Binders.scala"
  Scala: length = 0x
   
  InnerClass: 
   public abstract ReturnAndDo=class scala/util/parsing/ast/Binders$ReturnAndDo of class scala/util/parsing/ast/Binders
   public final $anonfun$genId$1=class scala/util/parsing/ast/Binders$_Binder$$anonfun$genId$1 of class scala/util/parsing/ast/Binders$_Binder$
  minor version: 0
  major version: 49
  Constant pool:
Asciz	SourceFile;
Asciz	Binders.scala;
Asciz	Scala;
Asciz	$outer;
Asciz	Lscala/util/parsing/ast/Binders;;
Asciz	scala$util$parsing$ast$Binders$_Binder$$currentId;
Asciz	I;
Asciz	()I;
Asciz	Code;
Asciz	LineNumberTable;
Asciz	scala/util/parsing/ast/Binders$_Binder$;
class	scala/util/parsing/ast/Binders$_Binder$
NameAndType	scala$util$parsing$ast$Binders$_Binder$$currentId:I
Field	scala/util/parsing/ast/Binders$_Binder$.scala$util$parsing$ast$Binders$_Binder$$currentId:I
Asciz	scala$util$parsing$ast$Binders$_Binder$$currentId_$eq;
Asciz	(I)V;
Asciz	genId;
NameAndType	$outer:Lscala/util/parsing/ast/Binders;
Field	scala/util/parsing/ast/Binders$_Binder$.$outer:Lscala/util/parsing/ast/Binders;
NameAndType	scala$util$parsing$ast$Binders$_Binder$$currentId:()I
Method	scala/util/parsing/ast/Binders$_Binder$.scala$util$parsing$ast$Binders$_Binder$$currentId:()I
Asciz	scala/runtime/BoxesRunTime;
class	scala/runtime/BoxesRunTime
Asciz	boxToInteger;
Asciz	(I)Ljava/lang/Integer;;
NameAndType	boxToInteger:(I)Ljava/lang/Integer;
Method	scala/runtime/BoxesRunTime.boxToInteger:(I)Ljava/lang/Integer;
Asciz	scala/util/parsing/ast/Binders;
class	scala/util/parsing/ast/Binders
Asciz	return_;
Asciz	(Ljava/lang/Object;)Lscala/util/parsing/ast/Binders$ReturnAndDo;;
NameAndType	return_:(Ljava/lang/Object;)Lscala/util/parsing/ast/Binders$ReturnAndDo;
InterfaceMethod	scala/util/parsing/ast/Binders.return_:(Ljava/lang/Object;)Lscala/util/parsing/ast/Binders$ReturnAndDo;
Asciz	scala/util/parsing/ast/Binders$_Binder$$anonfun$genId$1;
class	scala/util/parsing/ast/Binders$_Binder$$anonfun$genId$1
Asciz	<init>;
Asciz	(Lscala/util/parsing/ast/Binders$_Binder$;)V;
NameAndType	"<init>":(Lscala/util/parsing/ast/Binders$_Binder$;)V
Method	scala/util/parsing/ast/Binders$_Binder$$anonfun$genId$1."<init>":(Lscala/util/parsing/ast/Binders$_Binder$;)V
Asciz	scala/util/parsing/ast/Binders$ReturnAndDo;
class	scala/util/parsing/ast/Binders$ReturnAndDo
Asciz	andDo;
Asciz	(Lscala/Function0;)Ljava/lang/Object;;
NameAndType	andDo:(Lscala/Function0;)Ljava/lang/Object;
InterfaceMethod	scala/util/parsing/ast/Binders$ReturnAndDo.andDo:(Lscala/Function0;)Ljava/lang/Object;
Asciz	unboxToInt;
Asciz	(Ljava/lang/Object;)I;
NameAndType	unboxToInt:(Ljava/lang/Object;)I
Method	scala/runtime/BoxesRunTime.unboxToInt:(Ljava/lang/Object;)I
Asciz	(Lscala/util/parsing/ast/Binders;)V;
Asciz	java/lang/NullPointerException;
class	java/lang/NullPointerException
Asciz	()V;
NameAndType	"<init>":()V
Method	java/lang/NullPointerException."<init>":()V
Asciz	java/lang/Object;
class	java/lang/Object
Method	java/lang/Object."<init>":()V
Asciz	this;
Asciz	Lscala/util/parsing/ast/Binders$_Binder$;;
Asciz	LocalVariableTable;
Asciz	InnerClasses;
Asciz	ReturnAndDo;
Asciz	$anonfun$genId$1;
Asciz	scala/ScalaObject;
class	scala/ScalaObject

{
private final scala.util.parsing.ast.Binders $outer;
  Signature: Lscala/util/parsing/ast/Binders;

private int scala$util$parsing$ast$Binders$_Binder$$currentId;
  Signature: I

public final int scala$util$parsing$ast$Binders$_Binder$$currentId();
  Signature: ()I
  Code:
   Stack=1, Locals=1, Args_size=1
	aload_0
	getfield	Field scala$util$parsing$ast$Binders$_Binder$$currentId:I
	ireturn
  Labels:

public final void scala$util$parsing$ast$Binders$_Binder$$currentId_$eq(int);
  Signature: (I)V
  Code:
   Stack=2, Locals=2, Args_size=2
	aload_0
	iload_1
	putfield	Field scala$util$parsing$ast$Binders$_Binder$$currentId:I
	return
  Labels:

public int genId();
  Signature: ()I
  Code:
   Stack=4, Locals=2, Args_size=1
	aload_0
	getfield	Field $outer:Lscala/util/parsing/ast/Binders;
	aload_0
	invokevirtual	Method scala$util$parsing$ast$Binders$_Binder$$currentId:()I
	istore_1
	iload_1
	invokestatic	Method scala/runtime/BoxesRunTime.boxToInteger:(I)Ljava/lang/Integer;
	invokeinterface	InterfaceMethod scala/util/parsing/ast/Binders.return_:(Ljava/lang/Object;)Lscala/util/parsing/ast/Binders$ReturnAndDo;
	new	class scala/util/parsing/ast/Binders$_Binder$$anonfun$genId$1
	dup
	aload_0
	invokespecial	Method scala/util/parsing/ast/Binders$_Binder$$anonfun$genId$1."<init>":(Lscala/util/parsing/ast/Binders$_Binder$;)V
	invokeinterface	InterfaceMethod scala/util/parsing/ast/Binders$ReturnAndDo.andDo:(Lscala/Function0;)Ljava/lang/Object;
	invokestatic	Method scala/runtime/BoxesRunTime.unboxToInt:(Ljava/lang/Object;)I
	ireturn
  Labels:

public scala.util.parsing.ast.Binders$_Binder$(scala.util.parsing.ast.Binders);
  Signature: (Lscala/util/parsing/ast/Binders;)V
  Code:
   Stack=2, Locals=2, Args_size=2
	aload_1
	ifnonnull	l1 // aload_0
	new	class java/lang/NullPointerException
	dup
	invokespecial	Method java/lang/NullPointerException."<init>":()V
	athrow
l1	aload_0
	aload_1
	putfield	Field $outer:Lscala/util/parsing/ast/Binders;
	aload_0
	invokespecial	Method java/lang/Object."<init>":()V
	aload_0
	iconst_0
	putfield	Field scala$util$parsing$ast$Binders$_Binder$$currentId:I
	return
  Labels:
   	l1 = 12 // aload_0
  LocalVariableTable: 
   Start  Length  Slot  Name   Signature
   0      27      0    this       Lscala/util/parsing/ast/Binders$_Binder$;
   0      27      1    $outer       Lscala/util/parsing/ast/Binders;


}

