Compiled from "Binders.scala"
public final class scala.util.parsing.ast.Binders$BinderEnv$$anon$7 extends scala.util.parsing.ast.Binders$BinderEnv
  SourceFile: "Binders.scala"
  Scala: length = 0x
   
  InnerClass: 
   public Scope=class scala/util/parsing/ast/Binders$Scope of class scala/util/parsing/ast/Binders
   public abstract BinderEnv=class scala/util/parsing/ast/Binders$BinderEnv of class scala/util/parsing/ast/Binders
   public final $anon$7=class scala/util/parsing/ast/Binders$BinderEnv$$anon$7 of class scala/util/parsing/ast/Binders$BinderEnv
   public abstract NameElement=class scala/util/parsing/ast/AbstractSyntax$NameElement of class scala/util/parsing/ast/AbstractSyntax
  minor version: 0
  major version: 49
  Constant pool:
Asciz	SourceFile;
Asciz	Binders.scala;
Asciz	x$3;
Asciz	Lscala/util/parsing/ast/Binders$Scope;;
Asciz	v$1;
Asciz	Lscala/util/parsing/ast/AbstractSyntax$NameElement;;
Asciz	$outer;
Asciz	Lscala/util/parsing/ast/Binders$BinderEnv;;
Asciz	apply;
Asciz	(Lscala/util/parsing/ast/AbstractSyntax$NameElement;)Lscala/Option;;
Asciz	Code;
Asciz	LineNumberTable;
Asciz	scala/util/parsing/ast/Binders$BinderEnv$$anon$7;
class	scala/util/parsing/ast/Binders$BinderEnv$$anon$7
NameAndType	v$1:Lscala/util/parsing/ast/AbstractSyntax$NameElement;
Field	scala/util/parsing/ast/Binders$BinderEnv$$anon$7.v$1:Lscala/util/parsing/ast/AbstractSyntax$NameElement;
Asciz	java/lang/Object;
class	java/lang/Object
Asciz	equals;
Asciz	(Ljava/lang/Object;)Z;
NameAndType	equals:(Ljava/lang/Object;)Z
Method	java/lang/Object.equals:(Ljava/lang/Object;)Z
Asciz	scala/Some;
class	scala/Some
NameAndType	x$3:Lscala/util/parsing/ast/Binders$Scope;
Field	scala/util/parsing/ast/Binders$BinderEnv$$anon$7.x$3:Lscala/util/parsing/ast/Binders$Scope;
Asciz	<init>;
Asciz	(Ljava/lang/Object;)V;
NameAndType	"<init>":(Ljava/lang/Object;)V
Method	scala/Some."<init>":(Ljava/lang/Object;)V
NameAndType	$outer:Lscala/util/parsing/ast/Binders$BinderEnv;
Field	scala/util/parsing/ast/Binders$BinderEnv$$anon$7.$outer:Lscala/util/parsing/ast/Binders$BinderEnv;
Asciz	scala/util/parsing/ast/Binders$BinderEnv;
class	scala/util/parsing/ast/Binders$BinderEnv
NameAndType	apply:(Lscala/util/parsing/ast/AbstractSyntax$NameElement;)Lscala/Option;
Method	scala/util/parsing/ast/Binders$BinderEnv.apply:(Lscala/util/parsing/ast/AbstractSyntax$NameElement;)Lscala/Option;
Asciz	this;
Asciz	Lscala/util/parsing/ast/Binders$BinderEnv$$anon$7;;
Asciz	w;
Asciz	LocalVariableTable;
Asciz	<b::Lscala/util/parsing/ast/AbstractSyntax$NameElement;>(Tb;)Lscala/Option<Lscala/util/parsing/ast/Binders$Scope<Tb;>;>;;
Asciz	Signature;
Asciz	(Lscala/util/parsing/ast/Binders$BinderEnv;Lscala/util/parsing/ast/AbstractSyntax$NameElement;Lscala/util/parsing/ast/Binders$Scope;)V;
Asciz	java/lang/NullPointerException;
class	java/lang/NullPointerException
Asciz	()V;
NameAndType	"<init>":()V
Method	java/lang/NullPointerException."<init>":()V
Asciz	scala$util$parsing$ast$Binders$BinderEnv$$$outer;
Asciz	()Lscala/util/parsing/ast/Binders;;
NameAndType	scala$util$parsing$ast$Binders$BinderEnv$$$outer:()Lscala/util/parsing/ast/Binders;
Method	scala/util/parsing/ast/Binders$BinderEnv.scala$util$parsing$ast$Binders$BinderEnv$$$outer:()Lscala/util/parsing/ast/Binders;
Asciz	(Lscala/util/parsing/ast/Binders;)V;
NameAndType	"<init>":(Lscala/util/parsing/ast/Binders;)V
Method	scala/util/parsing/ast/Binders$BinderEnv."<init>":(Lscala/util/parsing/ast/Binders;)V
Asciz	Scala;
Asciz	InnerClasses;
Asciz	scala/util/parsing/ast/Binders$Scope;
class	scala/util/parsing/ast/Binders$Scope
Asciz	scala/util/parsing/ast/Binders;
class	scala/util/parsing/ast/Binders
Asciz	Scope;
Asciz	BinderEnv;
Asciz	$anon$7;
Asciz	scala/util/parsing/ast/AbstractSyntax$NameElement;
class	scala/util/parsing/ast/AbstractSyntax$NameElement
Asciz	scala/util/parsing/ast/AbstractSyntax;
class	scala/util/parsing/ast/AbstractSyntax
Asciz	NameElement;

{
private final scala.util.parsing.ast.Binders$Scope x$3;
  Signature: Lscala/util/parsing/ast/Binders$Scope;

private final scala.util.parsing.ast.AbstractSyntax$NameElement v$1;
  Signature: Lscala/util/parsing/ast/AbstractSyntax$NameElement;

private final scala.util.parsing.ast.Binders$BinderEnv $outer;
  Signature: Lscala/util/parsing/ast/Binders$BinderEnv;

public scala.Option apply(scala.util.parsing.ast.AbstractSyntax$NameElement);
  Signature: (Lscala/util/parsing/ast/AbstractSyntax$NameElement;)Lscala/Option;
  Code:
   Stack=3, Locals=3, Args_size=2
	aload_1
	aload_0
	getfield	Field v$1:Lscala/util/parsing/ast/AbstractSyntax$NameElement;
	astore_2
	dup
	ifnonnull	l1 // aload_2
	pop
	aload_2
	ifnull	l2 // new
	goto	l3 // aload_0
l1	aload_2
	invokevirtual	Method java/lang/Object.equals:(Ljava/lang/Object;)Z
	ifeq	l3 // aload_0
l2	new	class scala/Some
	dup
	aload_0
	getfield	Field x$3:Lscala/util/parsing/ast/Binders$Scope;
	invokespecial	Method scala/Some."<init>":(Ljava/lang/Object;)V
	goto	l4 // areturn
l3	aload_0
	getfield	Field $outer:Lscala/util/parsing/ast/Binders$BinderEnv;
	aload_1
	invokevirtual	Method scala/util/parsing/ast/Binders$BinderEnv.apply:(Lscala/util/parsing/ast/AbstractSyntax$NameElement;)Lscala/Option;
l4	areturn
  Labels:
   	l1 = 18 // aload_2
   	l2 = 25 // new
   	l3 = 39 // aload_0
   	l4 = 47 // areturn
  LocalVariableTable: 
   Start  Length  Slot  Name   Signature
   0      48      0    this       Lscala/util/parsing/ast/Binders$BinderEnv$$anon$7;
   0      48      1    w       Lscala/util/parsing/ast/AbstractSyntax$NameElement;

  Signature: length = 0x2
   00 29 

public scala.util.parsing.ast.Binders$BinderEnv$$anon$7(scala.util.parsing.ast.Binders$BinderEnv, scala.util.parsing.ast.AbstractSyntax$NameElement, scala.util.parsing.ast.Binders$Scope);
  Signature: (Lscala/util/parsing/ast/Binders$BinderEnv;Lscala/util/parsing/ast/AbstractSyntax$NameElement;Lscala/util/parsing/ast/Binders$Scope;)V
  Code:
   Stack=2, Locals=4, Args_size=4
	aload_1
	ifnonnull	l1 // aload_0
	new	class java/lang/NullPointerException
	dup
	invokespecial	Method java/lang/NullPointerException."<init>":()V
	athrow
l1	aload_0
	aload_1
	putfield	Field $outer:Lscala/util/parsing/ast/Binders$BinderEnv;
	aload_0
	aload_2
	putfield	Field v$1:Lscala/util/parsing/ast/AbstractSyntax$NameElement;
	aload_0
	aload_3
	putfield	Field x$3:Lscala/util/parsing/ast/Binders$Scope;
	aload_0
	aload_1
	invokevirtual	Method scala/util/parsing/ast/Binders$BinderEnv.scala$util$parsing$ast$Binders$BinderEnv$$$outer:()Lscala/util/parsing/ast/Binders;
	invokespecial	Method scala/util/parsing/ast/Binders$BinderEnv."<init>":(Lscala/util/parsing/ast/Binders;)V
	return
  Labels:
   	l1 = 12 // aload_0
  LocalVariableTable: 
   Start  Length  Slot  Name   Signature
   0      36      0    this       Lscala/util/parsing/ast/Binders$BinderEnv$$anon$7;
   0      36      1    $outer       Lscala/util/parsing/ast/Binders$BinderEnv;


}

