Compiled from "Binders.scala"
public final class scala.util.parsing.ast.Binders$$anon$6 extends java.lang.Object implements scala.util.parsing.ast.Mappable$Mappable
  SourceFile: "Binders.scala"
  Signature: length = 0x2
   00 63 
  Scala: length = 0x
   
  InnerClass: 
   public Scope=class scala/util/parsing/ast/Binders$Scope of class scala/util/parsing/ast/Binders
   public abstract Mapper=class scala/util/parsing/ast/Mappable$Mapper of class scala/util/parsing/ast/Mappable
   public final $anon$6=class scala/util/parsing/ast/Binders$$anon$6 of class scala/util/parsing/ast/Binders
   public abstract Mappable=class scala/util/parsing/ast/Mappable$Mappable of class scala/util/parsing/ast/Mappable
   public BoundElement=class scala/util/parsing/ast/Binders$BoundElement of class scala/util/parsing/ast/Binders
   public abstract NameElement=class scala/util/parsing/ast/AbstractSyntax$NameElement of class scala/util/parsing/ast/AbstractSyntax
   public final $anonfun$gmap$7=class scala/util/parsing/ast/Binders$$anon$6$$anonfun$gmap$7 of class scala/util/parsing/ast/Binders$$anon$6
   public final $anonfun$gmap$6=class scala/util/parsing/ast/Binders$$anon$6$$anonfun$gmap$6 of class scala/util/parsing/ast/Binders$$anon$6
  minor version: 0
  major version: 49
  Constant pool:
Asciz	SourceFile;
Asciz	Binders.scala;
Asciz	self$1;
Asciz	Lscala/util/parsing/ast/AbstractSyntax$NameElement;;
Asciz	$outer;
Asciz	Lscala/util/parsing/ast/Binders;;
Asciz	everywhere;
Asciz	(Lscala/util/parsing/ast/Mappable$Mapper;Lscala/Function1;)Ljava/lang/Object;;
Asciz	Code;
Asciz	LineNumberTable;
Asciz	scala/util/parsing/ast/Mappable$Mappable$class;
class	scala/util/parsing/ast/Mappable$Mappable$class
Asciz	(Lscala/util/parsing/ast/Mappable$Mappable;Lscala/util/parsing/ast/Mappable$Mapper;Lscala/Function1;)Ljava/lang/Object;;
NameAndType	everywhere:(Lscala/util/parsing/ast/Mappable$Mappable;Lscala/util/parsing/ast/Mappable$Mapper;Lscala/Function1;)Ljava/lang/Object;
Method	scala/util/parsing/ast/Mappable$Mappable$class.everywhere:(Lscala/util/parsing/ast/Mappable$Mappable;Lscala/util/parsing/ast/Mappable$Mapper;Lscala/Function1;)Ljava/lang/Object;
Asciz	this;
Asciz	Lscala/util/parsing/ast/Binders$$anon$6;;
Asciz	f;
Asciz	Lscala/util/parsing/ast/Mappable$Mapper;;
Asciz	c;
Asciz	Lscala/Function1;;
Asciz	LocalVariableTable;
Asciz	gmap;
Asciz	(Lscala/util/parsing/ast/Mappable$Mapper;)Lscala/util/parsing/ast/AbstractSyntax$NameElement;;
Asciz	scala/util/parsing/ast/Binders$$anon$6;
class	scala/util/parsing/ast/Binders$$anon$6
NameAndType	self$1:Lscala/util/parsing/ast/AbstractSyntax$NameElement;
Field	scala/util/parsing/ast/Binders$$anon$6.self$1:Lscala/util/parsing/ast/AbstractSyntax$NameElement;
Asciz	scala/util/parsing/ast/Binders$BoundElement;
class	scala/util/parsing/ast/Binders$BoundElement
Asciz	el;
Asciz	()Lscala/util/parsing/ast/AbstractSyntax$NameElement;;
NameAndType	el:()Lscala/util/parsing/ast/AbstractSyntax$NameElement;
Method	scala/util/parsing/ast/Binders$BoundElement.el:()Lscala/util/parsing/ast/AbstractSyntax$NameElement;
Asciz	scope;
Asciz	()Lscala/util/parsing/ast/Binders$Scope;;
NameAndType	scope:()Lscala/util/parsing/ast/Binders$Scope;
Method	scala/util/parsing/ast/Binders$BoundElement.scope:()Lscala/util/parsing/ast/Binders$Scope;
NameAndType	$outer:Lscala/util/parsing/ast/Binders;
Field	scala/util/parsing/ast/Binders$$anon$6.$outer:Lscala/util/parsing/ast/Binders;
Asciz	scala/util/parsing/ast/Binders$$anon$6$$anonfun$gmap$6;
class	scala/util/parsing/ast/Binders$$anon$6$$anonfun$gmap$6
Asciz	<init>;
Asciz	(Lscala/util/parsing/ast/Binders$$anon$6;)V;
NameAndType	"<init>":(Lscala/util/parsing/ast/Binders$$anon$6;)V
Method	scala/util/parsing/ast/Binders$$anon$6$$anonfun$gmap$6."<init>":(Lscala/util/parsing/ast/Binders$$anon$6;)V
Asciz	scala/util/parsing/ast/Mappable$Mapper;
class	scala/util/parsing/ast/Mappable$Mapper
Asciz	apply;
Asciz	(Ljava/lang/Object;Lscala/Function1;)Ljava/lang/Object;;
NameAndType	apply:(Ljava/lang/Object;Lscala/Function1;)Ljava/lang/Object;
InterfaceMethod	scala/util/parsing/ast/Mappable$Mapper.apply:(Ljava/lang/Object;Lscala/Function1;)Ljava/lang/Object;
Asciz	scala/util/parsing/ast/AbstractSyntax$NameElement;
class	scala/util/parsing/ast/AbstractSyntax$NameElement
Asciz	scala/util/parsing/ast/Binders$$anon$6$$anonfun$gmap$7;
class	scala/util/parsing/ast/Binders$$anon$6$$anonfun$gmap$7
Method	scala/util/parsing/ast/Binders$$anon$6$$anonfun$gmap$7."<init>":(Lscala/util/parsing/ast/Binders$$anon$6;)V
Asciz	scala/util/parsing/ast/Binders$Scope;
class	scala/util/parsing/ast/Binders$Scope
Asciz	(Lscala/util/parsing/ast/Binders;Lscala/util/parsing/ast/AbstractSyntax$NameElement;Lscala/util/parsing/ast/Binders$Scope;)V;
NameAndType	"<init>":(Lscala/util/parsing/ast/Binders;Lscala/util/parsing/ast/AbstractSyntax$NameElement;Lscala/util/parsing/ast/Binders$Scope;)V
Method	scala/util/parsing/ast/Binders$BoundElement."<init>":(Lscala/util/parsing/ast/Binders;Lscala/util/parsing/ast/AbstractSyntax$NameElement;Lscala/util/parsing/ast/Binders$Scope;)V
Asciz	scala/util/parsing/ast/Binders;
class	scala/util/parsing/ast/Binders
Asciz	UserNameElementIsMappable;
Asciz	(Lscala/util/parsing/ast/AbstractSyntax$NameElement;)Lscala/util/parsing/ast/Mappable$Mappable;;
NameAndType	UserNameElementIsMappable:(Lscala/util/parsing/ast/AbstractSyntax$NameElement;)Lscala/util/parsing/ast/Mappable$Mappable;
InterfaceMethod	scala/util/parsing/ast/Binders.UserNameElementIsMappable:(Lscala/util/parsing/ast/AbstractSyntax$NameElement;)Lscala/util/parsing/ast/Mappable$Mappable;
Asciz	scala/util/parsing/ast/Mappable$Mappable;
class	scala/util/parsing/ast/Mappable$Mappable
Asciz	(Lscala/util/parsing/ast/Mappable$Mapper;)Ljava/lang/Object;;
NameAndType	gmap:(Lscala/util/parsing/ast/Mappable$Mapper;)Ljava/lang/Object;
InterfaceMethod	scala/util/parsing/ast/Mappable$Mappable.gmap:(Lscala/util/parsing/ast/Mappable$Mapper;)Ljava/lang/Object;
Asciz	temp11;
Asciz	temp12;
Asciz	Lscala/util/parsing/ast/Binders$BoundElement;;
Asciz	temp13;
Asciz	temp14;
Asciz	Lscala/util/parsing/ast/Binders$Scope;;
Asciz	scala$util$parsing$ast$Binders$$anon$$$outer;
Asciz	()Lscala/util/parsing/ast/Binders;;
Asciz	scala$util$parsing$ast$Mappable$Mappable$$$outer;
Asciz	()Lscala/util/parsing/ast/Mappable;;
NameAndType	gmap:(Lscala/util/parsing/ast/Mappable$Mapper;)Lscala/util/parsing/ast/AbstractSyntax$NameElement;
Method	scala/util/parsing/ast/Binders$$anon$6.gmap:(Lscala/util/parsing/ast/Mappable$Mapper;)Lscala/util/parsing/ast/AbstractSyntax$NameElement;
Asciz	(Lscala/util/parsing/ast/Binders;Lscala/util/parsing/ast/AbstractSyntax$NameElement;)V;
Asciz	java/lang/NullPointerException;
class	java/lang/NullPointerException
Asciz	()V;
NameAndType	"<init>":()V
Method	java/lang/NullPointerException."<init>":()V
Asciz	java/lang/Object;
class	java/lang/Object
Method	java/lang/Object."<init>":()V
Asciz	$init$;
Asciz	(Lscala/util/parsing/ast/Mappable$Mappable;)V;
NameAndType	$init$:(Lscala/util/parsing/ast/Mappable$Mappable;)V
Method	scala/util/parsing/ast/Mappable$Mappable$class.$init$:(Lscala/util/parsing/ast/Mappable$Mappable;)V
Asciz	Ljava/lang/Object;Lscala/util/parsing/ast/Mappable$Mappable<Lscala/util/parsing/ast/AbstractSyntax$NameElement;>;;
Asciz	Signature;
Asciz	Scala;
Asciz	InnerClasses;
Asciz	Scope;
Asciz	scala/util/parsing/ast/Mappable;
class	scala/util/parsing/ast/Mappable
Asciz	Mapper;
Asciz	$anon$6;
Asciz	Mappable;
Asciz	BoundElement;
Asciz	scala/util/parsing/ast/AbstractSyntax;
class	scala/util/parsing/ast/AbstractSyntax
Asciz	NameElement;
Asciz	$anonfun$gmap$7;
Asciz	$anonfun$gmap$6;

{
public final scala.util.parsing.ast.AbstractSyntax$NameElement self$1;
  Signature: Lscala/util/parsing/ast/AbstractSyntax$NameElement;

public final scala.util.parsing.ast.Binders $outer;
  Signature: Lscala/util/parsing/ast/Binders;

public java.lang.Object everywhere(scala.util.parsing.ast.Mappable$Mapper, scala.Function1);
  Signature: (Lscala/util/parsing/ast/Mappable$Mapper;Lscala/Function1;)Ljava/lang/Object;
  Code:
   Stack=3, Locals=3, Args_size=3
	aload_0
	aload_1
	aload_2
	invokestatic	Method scala/util/parsing/ast/Mappable$Mappable$class.everywhere:(Lscala/util/parsing/ast/Mappable$Mappable;Lscala/util/parsing/ast/Mappable$Mapper;Lscala/Function1;)Ljava/lang/Object;
	areturn
  Labels:
  LocalVariableTable: 
   Start  Length  Slot  Name   Signature
   0      7      0    this       Lscala/util/parsing/ast/Binders$$anon$6;
   0      7      1    f       Lscala/util/parsing/ast/Mappable$Mapper;
   0      7      2    c       Lscala/Function1;


public scala.util.parsing.ast.AbstractSyntax$NameElement gmap(scala.util.parsing.ast.Mappable$Mapper);
  Signature: (Lscala/util/parsing/ast/Mappable$Mapper;)Lscala/util/parsing/ast/AbstractSyntax$NameElement;
  Code:
   Stack=9, Locals=6, Args_size=2
	aload_0
	getfield	Field self$1:Lscala/util/parsing/ast/AbstractSyntax$NameElement;
	astore_2
	aload_2
	instanceof	class scala/util/parsing/ast/Binders$BoundElement
	ifeq	l1 // aload_0
	aload_2
	checkcast	class scala/util/parsing/ast/Binders$BoundElement
	astore_3
	aload_3
	invokevirtual	Method scala/util/parsing/ast/Binders$BoundElement.el:()Lscala/util/parsing/ast/AbstractSyntax$NameElement;
	astore	4
	aload_3
	invokevirtual	Method scala/util/parsing/ast/Binders$BoundElement.scope:()Lscala/util/parsing/ast/Binders$Scope;
	astore	5
	new	class scala/util/parsing/ast/Binders$BoundElement
	dup
	aload_0
	getfield	Field $outer:Lscala/util/parsing/ast/Binders;
	aload_1
	aload	4
	new	class scala/util/parsing/ast/Binders$$anon$6$$anonfun$gmap$6
	dup
	aload_0
	invokespecial	Method scala/util/parsing/ast/Binders$$anon$6$$anonfun$gmap$6."<init>":(Lscala/util/parsing/ast/Binders$$anon$6;)V
	invokeinterface	InterfaceMethod scala/util/parsing/ast/Mappable$Mapper.apply:(Ljava/lang/Object;Lscala/Function1;)Ljava/lang/Object;
	checkcast	class scala/util/parsing/ast/AbstractSyntax$NameElement
	aload_1
	aload	5
	new	class scala/util/parsing/ast/Binders$$anon$6$$anonfun$gmap$7
	dup
	aload_0
	invokespecial	Method scala/util/parsing/ast/Binders$$anon$6$$anonfun$gmap$7."<init>":(Lscala/util/parsing/ast/Binders$$anon$6;)V
	invokeinterface	InterfaceMethod scala/util/parsing/ast/Mappable$Mapper.apply:(Ljava/lang/Object;Lscala/Function1;)Ljava/lang/Object;
	checkcast	class scala/util/parsing/ast/Binders$Scope
	invokespecial	Method scala/util/parsing/ast/Binders$BoundElement."<init>":(Lscala/util/parsing/ast/Binders;Lscala/util/parsing/ast/AbstractSyntax$NameElement;Lscala/util/parsing/ast/Binders$Scope;)V
	goto	l2 // areturn
l1	aload_0
	getfield	Field $outer:Lscala/util/parsing/ast/Binders;
	aload_0
	getfield	Field self$1:Lscala/util/parsing/ast/AbstractSyntax$NameElement;
	invokeinterface	InterfaceMethod scala/util/parsing/ast/Binders.UserNameElementIsMappable:(Lscala/util/parsing/ast/AbstractSyntax$NameElement;)Lscala/util/parsing/ast/Mappable$Mappable;
	aload_1
	invokeinterface	InterfaceMethod scala/util/parsing/ast/Mappable$Mappable.gmap:(Lscala/util/parsing/ast/Mappable$Mapper;)Ljava/lang/Object;
	checkcast	class scala/util/parsing/ast/AbstractSyntax$NameElement
l2	areturn
  Labels:
   	l1 = 81 // aload_0
   	l2 = 103 // areturn
  LocalVariableTable: 
   Start  Length  Slot  Name   Signature
   0      104      0    this       Lscala/util/parsing/ast/Binders$$anon$6;
   0      104      1    f       Lscala/util/parsing/ast/Mappable$Mapper;
   5      99      2    temp11       Lscala/util/parsing/ast/AbstractSyntax$NameElement;
   17      61      3    temp12       Lscala/util/parsing/ast/Binders$BoundElement;
   23      55      4    temp13       Lscala/util/parsing/ast/AbstractSyntax$NameElement;
   29      49      5    temp14       Lscala/util/parsing/ast/Binders$Scope;


public scala.util.parsing.ast.Binders scala$util$parsing$ast$Binders$$anon$$$outer();
  Signature: ()Lscala/util/parsing/ast/Binders;
  Code:
   Stack=1, Locals=1, Args_size=1
	aload_0
	getfield	Field $outer:Lscala/util/parsing/ast/Binders;
	areturn
  Labels:

public scala.util.parsing.ast.Mappable scala$util$parsing$ast$Mappable$Mappable$$$outer();
  Signature: ()Lscala/util/parsing/ast/Mappable;
  Code:
   Stack=1, Locals=1, Args_size=1
	aload_0
	getfield	Field $outer:Lscala/util/parsing/ast/Binders;
	areturn
  Labels:

public java.lang.Object gmap(scala.util.parsing.ast.Mappable$Mapper);
  Signature: (Lscala/util/parsing/ast/Mappable$Mapper;)Ljava/lang/Object;
  Code:
   Stack=2, Locals=2, Args_size=2
	aload_0
	aload_1
	invokevirtual	Method gmap:(Lscala/util/parsing/ast/Mappable$Mapper;)Lscala/util/parsing/ast/AbstractSyntax$NameElement;
	areturn
  Labels:
  LocalVariableTable: 
   Start  Length  Slot  Name   Signature
   0      6      0    this       Lscala/util/parsing/ast/Binders$$anon$6;
   0      6      1    f       Lscala/util/parsing/ast/Mappable$Mapper;


public scala.util.parsing.ast.Binders$$anon$6(scala.util.parsing.ast.Binders, scala.util.parsing.ast.AbstractSyntax$NameElement);
  Signature: (Lscala/util/parsing/ast/Binders;Lscala/util/parsing/ast/AbstractSyntax$NameElement;)V
  Code:
   Stack=2, Locals=3, Args_size=3
	aload_1
	ifnonnull	l1 // aload_0
	new	class java/lang/NullPointerException
	dup
	invokespecial	Method java/lang/NullPointerException."<init>":()V
	athrow
l1	aload_0
	aload_1
	putfield	Field $outer:Lscala/util/parsing/ast/Binders;
	aload_0
	aload_2
	putfield	Field self$1:Lscala/util/parsing/ast/AbstractSyntax$NameElement;
	aload_0
	invokespecial	Method java/lang/Object."<init>":()V
	aload_0
	invokestatic	Method scala/util/parsing/ast/Mappable$Mappable$class.$init$:(Lscala/util/parsing/ast/Mappable$Mappable;)V
	return
  Labels:
   	l1 = 12 // aload_0
  LocalVariableTable: 
   Start  Length  Slot  Name   Signature
   0      31      0    this       Lscala/util/parsing/ast/Binders$$anon$6;
   0      31      1    $outer       Lscala/util/parsing/ast/Binders;


}

