Compiled from "Binders.scala"
public class scala.util.parsing.ast.Binders$UnderBinder extends java.lang.Object implements scala.util.parsing.ast.AbstractSyntax$Element,scala.util.parsing.ast.Binders$BindingSensitive,scala.ScalaObject
  SourceFile: "Binders.scala"
  Signature: length = 0x2
   00 7E 
  Scala: length = 0x
   
  InnerClass: 
   public Scope=class scala/util/parsing/ast/Binders$Scope of class scala/util/parsing/ast/Binders
   public abstract Mapper=class scala/util/parsing/ast/Mappable$Mapper of class scala/util/parsing/ast/Mappable
   public abstract Mappable=class scala/util/parsing/ast/Mappable$Mappable of class scala/util/parsing/ast/Mappable
   public UnderBinder=class scala/util/parsing/ast/Binders$UnderBinder of class scala/util/parsing/ast/Binders
   public abstract Element=class scala/util/parsing/ast/AbstractSyntax$Element of class scala/util/parsing/ast/AbstractSyntax
   public abstract BindingSensitive=class scala/util/parsing/ast/Binders$BindingSensitive of class scala/util/parsing/ast/Binders
   public final $anon$9=class scala/util/parsing/ast/Binders$UnderBinder$$anon$9 of class scala/util/parsing/ast/Binders$UnderBinder
   public final $anon$10=class scala/util/parsing/ast/Binders$UnderBinder$$anon$10 of class scala/util/parsing/ast/Binders$UnderBinder
  minor version: 0
  major version: 49
  Constant pool:
Asciz	SourceFile;
Asciz	Binders.scala;
Asciz	pos;
Asciz	Lscala/util/parsing/input/Position;;
Asciz	$outer;
Asciz	Lscala/util/parsing/ast/Binders;;
Asciz	evidence$5;
Asciz	Lscala/Function1;;
Asciz	Lscala/Function1<TelementT;Lscala/util/parsing/ast/Mappable$Mappable<TelementT;>;>;;
Asciz	Signature;
Asciz	scala$util$parsing$ast$Binders$$element;
Asciz	Ljava/lang/Object;;
Asciz	scope;
Asciz	Lscala/util/parsing/ast/Binders$Scope;;
Asciz	Lscala/util/parsing/ast/Binders$Scope<TbinderType;>;;
Asciz	()Lscala/util/parsing/input/Position;;
Asciz	Code;
Asciz	LineNumberTable;
Asciz	scala/util/parsing/ast/Binders$UnderBinder;
class	scala/util/parsing/ast/Binders$UnderBinder
NameAndType	pos:Lscala/util/parsing/input/Position;
Field	scala/util/parsing/ast/Binders$UnderBinder.pos:Lscala/util/parsing/input/Position;
Asciz	pos_$eq;
Asciz	(Lscala/util/parsing/input/Position;)V;
Asciz	setPos;
Asciz	(Lscala/util/parsing/input/Position;)Lscala/util/parsing/input/Positional;;
Asciz	scala/util/parsing/input/Positional$class;
class	scala/util/parsing/input/Positional$class
Asciz	(Lscala/util/parsing/input/Positional;Lscala/util/parsing/input/Position;)Lscala/util/parsing/input/Positional;;
NameAndType	setPos:(Lscala/util/parsing/input/Positional;Lscala/util/parsing/input/Position;)Lscala/util/parsing/input/Positional;
Method	scala/util/parsing/input/Positional$class.setPos:(Lscala/util/parsing/input/Positional;Lscala/util/parsing/input/Position;)Lscala/util/parsing/input/Positional;
Asciz	this;
Asciz	Lscala/util/parsing/ast/Binders$UnderBinder;;
Asciz	newpos;
Asciz	LocalVariableTable;
Asciz	()Lscala/util/parsing/ast/Binders$Scope;;
NameAndType	scope:Lscala/util/parsing/ast/Binders$Scope;
Field	scala/util/parsing/ast/Binders$UnderBinder.scope:Lscala/util/parsing/ast/Binders$Scope;
Asciz	()Lscala/util/parsing/ast/Binders$Scope<TbinderType;>;;
Asciz	()Ljava/lang/Object;;
NameAndType	scala$util$parsing$ast$Binders$$element:Ljava/lang/Object;
Field	scala/util/parsing/ast/Binders$UnderBinder.scala$util$parsing$ast$Binders$$element:Ljava/lang/Object;
Asciz	toString;
Asciz	()Ljava/lang/String;;
Asciz	scala/collection/mutable/StringBuilder;
class	scala/collection/mutable/StringBuilder
Asciz	<init>;
Asciz	()V;
NameAndType	"<init>":()V
Method	scala/collection/mutable/StringBuilder."<init>":()V
Asciz	(;
String	(
Asciz	append;
Asciz	(Ljava/lang/Object;)Lscala/collection/mutable/StringBuilder;;
NameAndType	append:(Ljava/lang/Object;)Lscala/collection/mutable/StringBuilder;
Method	scala/collection/mutable/StringBuilder.append:(Ljava/lang/Object;)Lscala/collection/mutable/StringBuilder;
NameAndType	scope:()Lscala/util/parsing/ast/Binders$Scope;
Method	scala/util/parsing/ast/Binders$UnderBinder.scope:()Lscala/util/parsing/ast/Binders$Scope;
Asciz	scala/util/parsing/ast/Binders$Scope;
class	scala/util/parsing/ast/Binders$Scope
NameAndType	toString:()Ljava/lang/String;
Method	scala/util/parsing/ast/Binders$Scope.toString:()Ljava/lang/String;
Asciz	) in { ;
String	) in { 
NameAndType	scala$util$parsing$ast$Binders$$element:()Ljava/lang/Object;
Method	scala/util/parsing/ast/Binders$UnderBinder.scala$util$parsing$ast$Binders$$element:()Ljava/lang/Object;
Asciz	java/lang/Object;
class	java/lang/Object
Method	java/lang/Object.toString:()Ljava/lang/String;
Asciz	 };
String	 }
Method	scala/collection/mutable/StringBuilder.toString:()Ljava/lang/String;
Asciz	cloneElementWithSubst;
Asciz	(Lscala/collection/immutable/Map;)Ljava/lang/Object;;
NameAndType	evidence$5:Lscala/Function1;
Field	scala/util/parsing/ast/Binders$UnderBinder.evidence$5:Lscala/Function1;
Asciz	scala/Function1;
class	scala/Function1
Asciz	apply;
Asciz	(Ljava/lang/Object;)Ljava/lang/Object;;
NameAndType	apply:(Ljava/lang/Object;)Ljava/lang/Object;
InterfaceMethod	scala/Function1.apply:(Ljava/lang/Object;)Ljava/lang/Object;
Asciz	scala/util/parsing/ast/Mappable$Mappable;
class	scala/util/parsing/ast/Mappable$Mappable
Asciz	scala/util/parsing/ast/Binders$UnderBinder$$anon$9;
class	scala/util/parsing/ast/Binders$UnderBinder$$anon$9
Asciz	(Lscala/util/parsing/ast/Binders$UnderBinder;Lscala/collection/immutable/Map;)V;
NameAndType	"<init>":(Lscala/util/parsing/ast/Binders$UnderBinder;Lscala/collection/immutable/Map;)V
Method	scala/util/parsing/ast/Binders$UnderBinder$$anon$9."<init>":(Lscala/util/parsing/ast/Binders$UnderBinder;Lscala/collection/immutable/Map;)V
Asciz	gmap;
Asciz	(Lscala/util/parsing/ast/Mappable$Mapper;)Ljava/lang/Object;;
NameAndType	gmap:(Lscala/util/parsing/ast/Mappable$Mapper;)Ljava/lang/Object;
InterfaceMethod	scala/util/parsing/ast/Mappable$Mappable.gmap:(Lscala/util/parsing/ast/Mappable$Mapper;)Ljava/lang/Object;
Asciz	subst$1;
Asciz	Lscala/collection/immutable/Map;;
Asciz	(Lscala/collection/immutable/Map<Lscala/util/parsing/ast/AbstractSyntax$NameElement;Lscala/util/parsing/ast/AbstractSyntax$NameElement;>;)TelementT;;
Asciz	cloneElementNoBoundElements;
Asciz	scala/util/parsing/ast/Binders$UnderBinder$$anon$10;
class	scala/util/parsing/ast/Binders$UnderBinder$$anon$10
Asciz	(Lscala/util/parsing/ast/Binders$UnderBinder;)V;
NameAndType	"<init>":(Lscala/util/parsing/ast/Binders$UnderBinder;)V
Method	scala/util/parsing/ast/Binders$UnderBinder$$anon$10."<init>":(Lscala/util/parsing/ast/Binders$UnderBinder;)V
Asciz	()TelementT;;
Asciz	extract;
NameAndType	cloneElementNoBoundElements:()Ljava/lang/Object;
Method	scala/util/parsing/ast/Binders$UnderBinder.cloneElementNoBoundElements:()Ljava/lang/Object;
NameAndType	cloneElementWithSubst:(Lscala/collection/immutable/Map;)Ljava/lang/Object;
Method	scala/util/parsing/ast/Binders$UnderBinder.cloneElementWithSubst:(Lscala/collection/immutable/Map;)Ljava/lang/Object;
Asciz	subst;
Asciz	elementToString;
Asciz	scala$util$parsing$ast$Binders$UnderBinder$$$outer;
Asciz	()Lscala/util/parsing/ast/Binders;;
NameAndType	$outer:Lscala/util/parsing/ast/Binders;
Field	scala/util/parsing/ast/Binders$UnderBinder.$outer:Lscala/util/parsing/ast/Binders;
Asciz	(Lscala/util/parsing/ast/Binders;Lscala/util/parsing/ast/Binders$Scope;Ljava/lang/Object;Lscala/Function1;)V;
Asciz	java/lang/NullPointerException;
class	java/lang/NullPointerException
Method	java/lang/NullPointerException."<init>":()V
Method	java/lang/Object."<init>":()V
Asciz	$init$;
Asciz	(Lscala/util/parsing/input/Positional;)V;
NameAndType	$init$:(Lscala/util/parsing/input/Positional;)V
Method	scala/util/parsing/input/Positional$class.$init$:(Lscala/util/parsing/input/Positional;)V
Asciz	element;
Asciz	(Lscala/util/parsing/ast/Binders;Lscala/util/parsing/ast/Binders$Scope<TbinderType;>;TelementT;Lscala/Function1<TelementT;Lscala/util/parsing/ast/Mappable$Mappable<TelementT;>;>;)V;
Asciz	<binderType::Lscala/util/parsing/ast/AbstractSyntax$NameElement;elementT:Ljava/lang/Object;>Ljava/lang/Object;Lscala/util/parsing/ast/AbstractSyntax$Element;Lscala/util/parsing/ast/Binders$BindingSensitive;Lscala/ScalaObject;;
Asciz	Scala;
Asciz	InnerClasses;
Asciz	scala/util/parsing/ast/Binders;
class	scala/util/parsing/ast/Binders
Asciz	Scope;
Asciz	scala/util/parsing/ast/Mappable$Mapper;
class	scala/util/parsing/ast/Mappable$Mapper
Asciz	scala/util/parsing/ast/Mappable;
class	scala/util/parsing/ast/Mappable
Asciz	Mapper;
Asciz	Mappable;
Asciz	UnderBinder;
Asciz	scala/util/parsing/ast/AbstractSyntax$Element;
class	scala/util/parsing/ast/AbstractSyntax$Element
Asciz	scala/util/parsing/ast/AbstractSyntax;
class	scala/util/parsing/ast/AbstractSyntax
Asciz	Element;
Asciz	scala/util/parsing/ast/Binders$BindingSensitive;
class	scala/util/parsing/ast/Binders$BindingSensitive
Asciz	BindingSensitive;
Asciz	$anon$9;
Asciz	$anon$10;
Asciz	scala/ScalaObject;
class	scala/ScalaObject

{
private scala.util.parsing.input.Position pos;
  Signature: Lscala/util/parsing/input/Position;

public final scala.util.parsing.ast.Binders $outer;
  Signature: Lscala/util/parsing/ast/Binders;

private final scala.Function1 evidence$5;
  Signature: Lscala/Function1;
  Signature: length = 0x2
   00 09 

private final java.lang.Object scala$util$parsing$ast$Binders$$element;
  Signature: Ljava/lang/Object;

private final scala.util.parsing.ast.Binders$Scope scope;
  Signature: Lscala/util/parsing/ast/Binders$Scope;
  Signature: length = 0x2
   00 0F 

public scala.util.parsing.input.Position pos();
  Signature: ()Lscala/util/parsing/input/Position;
  Code:
   Stack=1, Locals=1, Args_size=1
	aload_0
	getfield	Field pos:Lscala/util/parsing/input/Position;
	areturn
  Labels:

public void pos_$eq(scala.util.parsing.input.Position);
  Signature: (Lscala/util/parsing/input/Position;)V
  Code:
   Stack=2, Locals=2, Args_size=2
	aload_0
	aload_1
	putfield	Field pos:Lscala/util/parsing/input/Position;
	return
  Labels:

public scala.util.parsing.input.Positional setPos(scala.util.parsing.input.Position);
  Signature: (Lscala/util/parsing/input/Position;)Lscala/util/parsing/input/Positional;
  Code:
   Stack=2, Locals=2, Args_size=2
	aload_0
	aload_1
	invokestatic	Method scala/util/parsing/input/Positional$class.setPos:(Lscala/util/parsing/input/Positional;Lscala/util/parsing/input/Position;)Lscala/util/parsing/input/Positional;
	areturn
  Labels:
  LocalVariableTable: 
   Start  Length  Slot  Name   Signature
   0      6      0    this       Lscala/util/parsing/ast/Binders$UnderBinder;
   0      6      1    newpos       Lscala/util/parsing/input/Position;


public scala.util.parsing.ast.Binders$Scope scope();
  Signature: ()Lscala/util/parsing/ast/Binders$Scope;
  Code:
   Stack=1, Locals=1, Args_size=1
	aload_0
	getfield	Field scope:Lscala/util/parsing/ast/Binders$Scope;
	areturn
  Labels:
  Signature: length = 0x2
   00 27 

public java.lang.Object scala$util$parsing$ast$Binders$$element();
  Signature: ()Ljava/lang/Object;
  Code:
   Stack=1, Locals=1, Args_size=1
	aload_0
	getfield	Field scala$util$parsing$ast$Binders$$element:Ljava/lang/Object;
	areturn
  Labels:

public java.lang.String toString();
  Signature: ()Ljava/lang/String;
  Code:
   Stack=2, Locals=1, Args_size=1
	new	class scala/collection/mutable/StringBuilder
	dup
	invokespecial	Method scala/collection/mutable/StringBuilder."<init>":()V
	ldc	String (
	invokevirtual	Method scala/collection/mutable/StringBuilder.append:(Ljava/lang/Object;)Lscala/collection/mutable/StringBuilder;
	aload_0
	invokevirtual	Method scope:()Lscala/util/parsing/ast/Binders$Scope;
	invokevirtual	Method scala/util/parsing/ast/Binders$Scope.toString:()Ljava/lang/String;
	invokevirtual	Method scala/collection/mutable/StringBuilder.append:(Ljava/lang/Object;)Lscala/collection/mutable/StringBuilder;
	ldc	String ) in { 
	invokevirtual	Method scala/collection/mutable/StringBuilder.append:(Ljava/lang/Object;)Lscala/collection/mutable/StringBuilder;
	aload_0
	invokevirtual	Method scala$util$parsing$ast$Binders$$element:()Ljava/lang/Object;
	invokevirtual	Method java/lang/Object.toString:()Ljava/lang/String;
	invokevirtual	Method scala/collection/mutable/StringBuilder.append:(Ljava/lang/Object;)Lscala/collection/mutable/StringBuilder;
	ldc	String  }
	invokevirtual	Method scala/collection/mutable/StringBuilder.append:(Ljava/lang/Object;)Lscala/collection/mutable/StringBuilder;
	invokevirtual	Method scala/collection/mutable/StringBuilder.toString:()Ljava/lang/String;
	areturn
  Labels:

public java.lang.Object cloneElementWithSubst(scala.collection.immutable.Map);
  Signature: (Lscala/collection/immutable/Map;)Ljava/lang/Object;
  Code:
   Stack=5, Locals=2, Args_size=2
	aload_0
	getfield	Field evidence$5:Lscala/Function1;
	aload_0
	invokevirtual	Method scala$util$parsing$ast$Binders$$element:()Ljava/lang/Object;
	invokeinterface	InterfaceMethod scala/Function1.apply:(Ljava/lang/Object;)Ljava/lang/Object;
	checkcast	class scala/util/parsing/ast/Mappable$Mappable
	new	class scala/util/parsing/ast/Binders$UnderBinder$$anon$9
	dup
	aload_0
	aload_1
	invokespecial	Method scala/util/parsing/ast/Binders$UnderBinder$$anon$9."<init>":(Lscala/util/parsing/ast/Binders$UnderBinder;Lscala/collection/immutable/Map;)V
	invokeinterface	InterfaceMethod scala/util/parsing/ast/Mappable$Mappable.gmap:(Lscala/util/parsing/ast/Mappable$Mapper;)Ljava/lang/Object;
	areturn
  Labels:
  LocalVariableTable: 
   Start  Length  Slot  Name   Signature
   0      31      0    this       Lscala/util/parsing/ast/Binders$UnderBinder;
   0      31      1    subst$1       Lscala/collection/immutable/Map;

  Signature: length = 0x2
   00 60 

public java.lang.Object cloneElementNoBoundElements();
  Signature: ()Ljava/lang/Object;
  Code:
   Stack=4, Locals=1, Args_size=1
	aload_0
	getfield	Field evidence$5:Lscala/Function1;
	aload_0
	invokevirtual	Method scala$util$parsing$ast$Binders$$element:()Ljava/lang/Object;
	invokeinterface	InterfaceMethod scala/Function1.apply:(Ljava/lang/Object;)Ljava/lang/Object;
	checkcast	class scala/util/parsing/ast/Mappable$Mappable
	new	class scala/util/parsing/ast/Binders$UnderBinder$$anon$10
	dup
	aload_0
	invokespecial	Method scala/util/parsing/ast/Binders$UnderBinder$$anon$10."<init>":(Lscala/util/parsing/ast/Binders$UnderBinder;)V
	invokeinterface	InterfaceMethod scala/util/parsing/ast/Mappable$Mappable.gmap:(Lscala/util/parsing/ast/Mappable$Mapper;)Ljava/lang/Object;
	areturn
  Labels:
  Signature: length = 0x2
   00 67 

public java.lang.Object extract();
  Signature: ()Ljava/lang/Object;
  Code:
   Stack=1, Locals=1, Args_size=1
	aload_0
	invokevirtual	Method cloneElementNoBoundElements:()Ljava/lang/Object;
	areturn
  Labels:
  Signature: length = 0x2
   00 67 

public java.lang.Object extract(scala.collection.immutable.Map);
  Signature: (Lscala/collection/immutable/Map;)Ljava/lang/Object;
  Code:
   Stack=2, Locals=2, Args_size=2
	aload_0
	aload_1
	invokevirtual	Method cloneElementWithSubst:(Lscala/collection/immutable/Map;)Ljava/lang/Object;
	areturn
  Labels:
  LocalVariableTable: 
   Start  Length  Slot  Name   Signature
   0      6      0    this       Lscala/util/parsing/ast/Binders$UnderBinder;
   0      6      1    subst       Lscala/collection/immutable/Map;

  Signature: length = 0x2
   00 60 

public java.lang.String elementToString();
  Signature: ()Ljava/lang/String;
  Code:
   Stack=1, Locals=1, Args_size=1
	aload_0
	invokevirtual	Method scala$util$parsing$ast$Binders$$element:()Ljava/lang/Object;
	invokevirtual	Method java/lang/Object.toString:()Ljava/lang/String;
	areturn
  Labels:

public scala.util.parsing.ast.Binders scala$util$parsing$ast$Binders$UnderBinder$$$outer();
  Signature: ()Lscala/util/parsing/ast/Binders;
  Code:
   Stack=1, Locals=1, Args_size=1
	aload_0
	getfield	Field $outer:Lscala/util/parsing/ast/Binders;
	areturn
  Labels:

public scala.util.parsing.ast.Binders$UnderBinder(scala.util.parsing.ast.Binders, scala.util.parsing.ast.Binders$Scope, java.lang.Object, scala.Function1);
  Signature: (Lscala/util/parsing/ast/Binders;Lscala/util/parsing/ast/Binders$Scope;Ljava/lang/Object;Lscala/Function1;)V
  Code:
   Stack=2, Locals=5, Args_size=5
	aload_0
	aload_2
	putfield	Field scope:Lscala/util/parsing/ast/Binders$Scope;
	aload_0
	aload_3
	putfield	Field scala$util$parsing$ast$Binders$$element:Ljava/lang/Object;
	aload_0
	aload	4
	putfield	Field evidence$5:Lscala/Function1;
	aload_1
	ifnonnull	l1 // aload_0
	new	class java/lang/NullPointerException
	dup
	invokespecial	Method java/lang/NullPointerException."<init>":()V
	athrow
l1	aload_0
	aload_1
	putfield	Field $outer:Lscala/util/parsing/ast/Binders;
	aload_0
	invokespecial	Method java/lang/Object."<init>":()V
	aload_0
	invokestatic	Method scala/util/parsing/input/Positional$class.$init$:(Lscala/util/parsing/input/Positional;)V
	return
  Labels:
   	l1 = 28 // aload_0
  LocalVariableTable: 
   Start  Length  Slot  Name   Signature
   0      42      0    this       Lscala/util/parsing/ast/Binders$UnderBinder;
   0      42      1    $outer       Lscala/util/parsing/ast/Binders;
   0      42      2    scope       Lscala/util/parsing/ast/Binders$Scope;
   0      42      3    element       Ljava/lang/Object;
   0      42      4    evidence$5       Lscala/Function1;

  Signature: length = 0x2
   00 7D 

}

