Compiled from "Binders.scala"
public class scala.util.parsing.ast.Binders$BoundElement extends java.lang.Object implements scala.util.parsing.ast.AbstractSyntax$NameElement,scala.Proxy,scala.util.parsing.ast.Binders$BindingSensitive,scala.ScalaObject,scala.Product,java.io.Serializable
  SourceFile: "Binders.scala"
  Signature: length = 0x2
   00 FFFFFFB2 
  Scala: length = 0x
   
  InnerClass: 
   public #183= #110 of #182; //Scope=class scala/util/parsing/ast/Binders$Scope of class scala/util/parsing/ast/Binders
   public #101= #19 of #182; //BoundElement=class scala/util/parsing/ast/Binders$BoundElement of class scala/util/parsing/ast/Binders
   public abstract #188= #185 of #187; //Element=class scala/util/parsing/ast/AbstractSyntax$Element of class scala/util/parsing/ast/AbstractSyntax
   public abstract #191= #190 of #182; //BindingSensitive=class scala/util/parsing/ast/Binders$BindingSensitive of class scala/util/parsing/ast/Binders
   public abstract #192= #138 of #187; //NameElement=class scala/util/parsing/ast/AbstractSyntax$NameElement of class scala/util/parsing/ast/AbstractSyntax
  minor version: 0
  major version: 49
  Constant pool:
const #1 = Asciz	SourceFile;
const #2 = Asciz	Binders.scala;
const #3 = Asciz	pos;
const #4 = Asciz	Lscala/util/parsing/input/Position;;
const #5 = Asciz	$outer;
const #6 = Asciz	Lscala/util/parsing/ast/Binders;;
const #7 = Asciz	scope;
const #8 = Asciz	Lscala/util/parsing/ast/Binders$Scope;;
const #9 = Asciz	Lscala/util/parsing/ast/Binders$Scope<TboundElement;>;;
const #10 = Asciz	Signature;
const #11 = Asciz	el;
const #12 = Asciz	Lscala/util/parsing/ast/AbstractSyntax$NameElement;;
const #13 = Asciz	TboundElement;;
const #14 = Asciz	<init>;
const #15 = Asciz	(Lscala/util/parsing/ast/Binders;Lscala/util/parsing/ast/AbstractSyntax$NameElement;Lscala/util/parsing/ast/Binders$Scope;)V;
const #16 = Asciz	Code;
const #17 = Asciz	LineNumberTable;
const #18 = Asciz	scala/util/parsing/ast/Binders$BoundElement;
const #19 = class	#18;	//  scala/util/parsing/ast/Binders$BoundElement
const #20 = NameAndType	#11:#12;//  el:Lscala/util/parsing/ast/AbstractSyntax$NameElement;
const #21 = Field	#19.#20;	//  scala/util/parsing/ast/Binders$BoundElement.el:Lscala/util/parsing/ast/AbstractSyntax$NameElement;
const #22 = NameAndType	#7:#8;//  scope:Lscala/util/parsing/ast/Binders$Scope;
const #23 = Field	#19.#22;	//  scala/util/parsing/ast/Binders$BoundElement.scope:Lscala/util/parsing/ast/Binders$Scope;
const #24 = Asciz	java/lang/NullPointerException;
const #25 = class	#24;	//  java/lang/NullPointerException
const #26 = Asciz	()V;
const #27 = NameAndType	#14:#26;//  "<init>":()V
const #28 = Method	#25.#27;	//  java/lang/NullPointerException."<init>":()V
const #29 = NameAndType	#5:#6;//  $outer:Lscala/util/parsing/ast/Binders;
const #30 = Field	#19.#29;	//  scala/util/parsing/ast/Binders$BoundElement.$outer:Lscala/util/parsing/ast/Binders;
const #31 = Asciz	java/lang/Object;
const #32 = class	#31;	//  java/lang/Object
const #33 = Method	#32.#27;	//  java/lang/Object."<init>":()V
const #34 = Asciz	scala/util/parsing/input/Positional$class;
const #35 = class	#34;	//  scala/util/parsing/input/Positional$class
const #36 = Asciz	$init$;
const #37 = Asciz	(Lscala/util/parsing/input/Positional;)V;
const #38 = NameAndType	#36:#37;//  $init$:(Lscala/util/parsing/input/Positional;)V
const #39 = Method	#35.#38;	//  scala/util/parsing/input/Positional$class.$init$:(Lscala/util/parsing/input/Positional;)V
const #40 = Asciz	scala/util/parsing/ast/AbstractSyntax$NameElement$class;
const #41 = class	#40;	//  scala/util/parsing/ast/AbstractSyntax$NameElement$class
const #42 = Asciz	(Lscala/util/parsing/ast/AbstractSyntax$NameElement;)V;
const #43 = NameAndType	#36:#42;//  $init$:(Lscala/util/parsing/ast/AbstractSyntax$NameElement;)V
const #44 = Method	#41.#43;	//  scala/util/parsing/ast/AbstractSyntax$NameElement$class.$init$:(Lscala/util/parsing/ast/AbstractSyntax$NameElement;)V
const #45 = Asciz	scala/Proxy$class;
const #46 = class	#45;	//  scala/Proxy$class
const #47 = Asciz	(Lscala/Proxy;)V;
const #48 = NameAndType	#36:#47;//  $init$:(Lscala/Proxy;)V
const #49 = Method	#46.#48;	//  scala/Proxy$class.$init$:(Lscala/Proxy;)V
const #50 = Asciz	scala/Product$class;
const #51 = class	#50;	//  scala/Product$class
const #52 = Asciz	(Lscala/Product;)V;
const #53 = NameAndType	#36:#52;//  $init$:(Lscala/Product;)V
const #54 = Method	#51.#53;	//  scala/Product$class.$init$:(Lscala/Product;)V
const #55 = Asciz	this;
const #56 = Asciz	Lscala/util/parsing/ast/Binders$BoundElement;;
const #57 = Asciz	LocalVariableTable;
const #58 = Asciz	(Lscala/util/parsing/ast/Binders;TboundElement;Lscala/util/parsing/ast/Binders$Scope<TboundElement;>;)V;
const #59 = Asciz	self;
const #60 = Asciz	()Ljava/lang/Object;;
const #61 = Asciz	()Lscala/util/parsing/ast/AbstractSyntax$Element;;
const #62 = NameAndType	#59:#61;//  self:()Lscala/util/parsing/ast/AbstractSyntax$Element;
const #63 = Method	#19.#62;	//  scala/util/parsing/ast/Binders$BoundElement.self:()Lscala/util/parsing/ast/AbstractSyntax$Element;
const #64 = Asciz	scala$util$parsing$ast$AbstractSyntax$NameElement$$$outer;
const #65 = Asciz	()Lscala/util/parsing/ast/AbstractSyntax;;
const #66 = Asciz	scala$util$parsing$ast$Binders$BoundElement$$$outer;
const #67 = Asciz	()Lscala/util/parsing/ast/Binders;;
const #68 = NameAndType	#66:#67;//  scala$util$parsing$ast$Binders$BoundElement$$$outer:()Lscala/util/parsing/ast/Binders;
const #69 = Method	#19.#68;	//  scala/util/parsing/ast/Binders$BoundElement.scala$util$parsing$ast$Binders$BoundElement$$$outer:()Lscala/util/parsing/ast/Binders;
const #70 = Asciz	canEqual;
const #71 = Asciz	(Ljava/lang/Object;)Z;
const #72 = Asciz	productElement;
const #73 = Asciz	(I)Ljava/lang/Object;;
const #74 = Asciz	java/lang/IndexOutOfBoundsException;
const #75 = class	#74;	//  java/lang/IndexOutOfBoundsException
const #76 = Asciz	scala/runtime/BoxesRunTime;
const #77 = class	#76;	//  scala/runtime/BoxesRunTime
const #78 = Asciz	boxToInteger;
const #79 = Asciz	(I)Ljava/lang/Integer;;
const #80 = NameAndType	#78:#79;//  boxToInteger:(I)Ljava/lang/Integer;
const #81 = Method	#77.#80;	//  scala/runtime/BoxesRunTime.boxToInteger:(I)Ljava/lang/Integer;
const #82 = Asciz	toString;
const #83 = Asciz	()Ljava/lang/String;;
const #84 = NameAndType	#82:#83;//  toString:()Ljava/lang/String;
const #85 = Method	#32.#84;	//  java/lang/Object.toString:()Ljava/lang/String;
const #86 = Asciz	(Ljava/lang/String;)V;
const #87 = NameAndType	#14:#86;//  "<init>":(Ljava/lang/String;)V
const #88 = Method	#75.#87;	//  java/lang/IndexOutOfBoundsException."<init>":(Ljava/lang/String;)V
const #89 = Asciz	scala/MatchError;
const #90 = class	#89;	//  scala/MatchError
const #91 = Method	#90.#87;	//  scala/MatchError."<init>":(Ljava/lang/String;)V
const #92 = Asciz	()Lscala/util/parsing/ast/Binders$Scope;;
const #93 = NameAndType	#7:#92;//  scope:()Lscala/util/parsing/ast/Binders$Scope;
const #94 = Method	#19.#93;	//  scala/util/parsing/ast/Binders$BoundElement.scope:()Lscala/util/parsing/ast/Binders$Scope;
const #95 = Asciz	()Lscala/util/parsing/ast/AbstractSyntax$NameElement;;
const #96 = NameAndType	#11:#95;//  el:()Lscala/util/parsing/ast/AbstractSyntax$NameElement;
const #97 = Method	#19.#96;	//  scala/util/parsing/ast/Binders$BoundElement.el:()Lscala/util/parsing/ast/AbstractSyntax$NameElement;
const #98 = Asciz	productArity;
const #99 = Asciz	()I;
const #100 = Asciz	productPrefix;
const #101 = Asciz	BoundElement;
const #102 = String	#101;	//  BoundElement
const #103 = Asciz	copy;
const #104 = Asciz	(Lscala/util/parsing/ast/AbstractSyntax$NameElement;Lscala/util/parsing/ast/Binders$Scope;)Lscala/util/parsing/ast/Binders$BoundElement;;
const #105 = NameAndType	#14:#15;//  "<init>":(Lscala/util/parsing/ast/Binders;Lscala/util/parsing/ast/AbstractSyntax$NameElement;Lscala/util/parsing/ast/Binders$Scope;)V
const #106 = Method	#19.#105;	//  scala/util/parsing/ast/Binders$BoundElement."<init>":(Lscala/util/parsing/ast/Binders;Lscala/util/parsing/ast/AbstractSyntax$NameElement;Lscala/util/parsing/ast/Binders$Scope;)V
const #107 = Asciz	alpha_$eq$eq;
const #108 = Asciz	(Lscala/util/parsing/ast/Binders$BoundElement;)Z;
const #109 = Asciz	scala/util/parsing/ast/Binders$Scope;
const #110 = class	#109;	//  scala/util/parsing/ast/Binders$Scope
const #111 = Asciz	indexFor;
const #112 = Asciz	(Lscala/util/parsing/ast/AbstractSyntax$NameElement;)Lscala/Option;;
const #113 = NameAndType	#111:#112;//  indexFor:(Lscala/util/parsing/ast/AbstractSyntax$NameElement;)Lscala/Option;
const #114 = Method	#110.#113;	//  scala/util/parsing/ast/Binders$Scope.indexFor:(Lscala/util/parsing/ast/AbstractSyntax$NameElement;)Lscala/Option;
const #115 = Asciz	equals;
const #116 = NameAndType	#115:#71;//  equals:(Ljava/lang/Object;)Z
const #117 = Method	#32.#116;	//  java/lang/Object.equals:(Ljava/lang/Object;)Z
const #118 = Asciz	other;
const #119 = Asciz	<t::Lscala/util/parsing/ast/AbstractSyntax$NameElement;>(Lscala/util/parsing/ast/Binders$BoundElement<Tt;>;)Z;
const #120 = Asciz	scala/collection/mutable/StringBuilder;
const #121 = class	#120;	//  scala/collection/mutable/StringBuilder
const #122 = Method	#121.#27;	//  scala/collection/mutable/StringBuilder."<init>":()V
const #123 = Asciz	(Lscala/Proxy;)Ljava/lang/String;;
const #124 = NameAndType	#82:#123;//  toString:(Lscala/Proxy;)Ljava/lang/String;
const #125 = Method	#46.#124;	//  scala/Proxy$class.toString:(Lscala/Proxy;)Ljava/lang/String;
const #126 = Asciz	append;
const #127 = Asciz	(Ljava/lang/Object;)Lscala/collection/mutable/StringBuilder;;
const #128 = NameAndType	#126:#127;//  append:(Ljava/lang/Object;)Lscala/collection/mutable/StringBuilder;
const #129 = Method	#121.#128;	//  scala/collection/mutable/StringBuilder.append:(Ljava/lang/Object;)Lscala/collection/mutable/StringBuilder;
const #130 = Asciz	@;
const #131 = String	#130;	//  @
const #132 = Asciz	id;
const #133 = NameAndType	#132:#99;//  id:()I
const #134 = Method	#110.#133;	//  scala/util/parsing/ast/Binders$Scope.id:()I
const #135 = Method	#121.#84;	//  scala/collection/mutable/StringBuilder.toString:()Ljava/lang/String;
const #136 = Asciz	name;
const #137 = Asciz	scala/util/parsing/ast/AbstractSyntax$NameElement;
const #138 = class	#137;	//  scala/util/parsing/ast/AbstractSyntax$NameElement
const #139 = NameAndType	#136:#83;//  name:()Ljava/lang/String;
const #140 = InterfaceMethod	#138.#139;	//  scala/util/parsing/ast/AbstractSyntax$NameElement.name:()Ljava/lang/String;
const #141 = Asciz	getElementFor;
const #142 = Asciz	(Lscala/util/parsing/ast/AbstractSyntax$NameElement;)Lscala/util/parsing/ast/AbstractSyntax$Element;;
const #143 = NameAndType	#141:#142;//  getElementFor:(Lscala/util/parsing/ast/AbstractSyntax$NameElement;)Lscala/util/parsing/ast/AbstractSyntax$Element;
const #144 = Method	#110.#143;	//  scala/util/parsing/ast/Binders$Scope.getElementFor:(Lscala/util/parsing/ast/AbstractSyntax$NameElement;)Lscala/util/parsing/ast/AbstractSyntax$Element;
const #145 = Asciz	()Lscala/util/parsing/ast/Binders$Scope<TboundElement;>;;
const #146 = Asciz	()TboundElement;;
const #147 = Asciz	copy$default$1;
const #148 = Asciz	copy$default$2;
const #149 = Asciz	setPos;
const #150 = Asciz	(Lscala/util/parsing/input/Position;)Lscala/util/parsing/input/Positional;;
const #151 = Asciz	(Lscala/util/parsing/input/Positional;Lscala/util/parsing/input/Position;)Lscala/util/parsing/input/Positional;;
const #152 = NameAndType	#149:#151;//  setPos:(Lscala/util/parsing/input/Positional;Lscala/util/parsing/input/Position;)Lscala/util/parsing/input/Positional;
const #153 = Method	#35.#152;	//  scala/util/parsing/input/Positional$class.setPos:(Lscala/util/parsing/input/Positional;Lscala/util/parsing/input/Position;)Lscala/util/parsing/input/Positional;
const #154 = Asciz	newpos;
const #155 = Asciz	pos_$eq;
const #156 = Asciz	(Lscala/util/parsing/input/Position;)V;
const #157 = NameAndType	#3:#4;//  pos:Lscala/util/parsing/input/Position;
const #158 = Field	#19.#157;	//  scala/util/parsing/ast/Binders$BoundElement.pos:Lscala/util/parsing/input/Position;
const #159 = Asciz	()Lscala/util/parsing/input/Position;;
const #160 = Asciz	(Lscala/Proxy;Ljava/lang/Object;)Z;
const #161 = NameAndType	#115:#160;//  equals:(Lscala/Proxy;Ljava/lang/Object;)Z
const #162 = Method	#46.#161;	//  scala/Proxy$class.equals:(Lscala/Proxy;Ljava/lang/Object;)Z
const #163 = Asciz	that;
const #164 = Asciz	Ljava/lang/Object;;
const #165 = Asciz	hashCode;
const #166 = Asciz	(Lscala/Proxy;)I;
const #167 = NameAndType	#165:#166;//  hashCode:(Lscala/Proxy;)I
const #168 = Method	#46.#167;	//  scala/Proxy$class.hashCode:(Lscala/Proxy;)I
const #169 = Asciz	productElements;
const #170 = Asciz	()Lscala/collection/Iterator;;
const #171 = Asciz	(Lscala/Product;)Lscala/collection/Iterator;;
const #172 = NameAndType	#169:#171;//  productElements:(Lscala/Product;)Lscala/collection/Iterator;
const #173 = Method	#51.#172;	//  scala/Product$class.productElements:(Lscala/Product;)Lscala/collection/Iterator;
const #174 = Asciz	Deprecated;
const #175 = Asciz	productIterator;
const #176 = NameAndType	#175:#171;//  productIterator:(Lscala/Product;)Lscala/collection/Iterator;
const #177 = Method	#51.#176;	//  scala/Product$class.productIterator:(Lscala/Product;)Lscala/collection/Iterator;
const #178 = Asciz	<boundElement::Lscala/util/parsing/ast/AbstractSyntax$NameElement;>Ljava/lang/Object;Lscala/util/parsing/ast/AbstractSyntax$NameElement;Lscala/Proxy;Lscala/util/parsing/ast/Binders$BindingSensitive;Lscala/ScalaObject;Lscala/Product;;
const #179 = Asciz	Scala;
const #180 = Asciz	InnerClasses;
const #181 = Asciz	scala/util/parsing/ast/Binders;
const #182 = class	#181;	//  scala/util/parsing/ast/Binders
const #183 = Asciz	Scope;
const #184 = Asciz	scala/util/parsing/ast/AbstractSyntax$Element;
const #185 = class	#184;	//  scala/util/parsing/ast/AbstractSyntax$Element
const #186 = Asciz	scala/util/parsing/ast/AbstractSyntax;
const #187 = class	#186;	//  scala/util/parsing/ast/AbstractSyntax
const #188 = Asciz	Element;
const #189 = Asciz	scala/util/parsing/ast/Binders$BindingSensitive;
const #190 = class	#189;	//  scala/util/parsing/ast/Binders$BindingSensitive
const #191 = Asciz	BindingSensitive;
const #192 = Asciz	NameElement;
const #193 = Asciz	scala/Proxy;
const #194 = class	#193;	//  scala/Proxy
const #195 = Asciz	scala/ScalaObject;
const #196 = class	#195;	//  scala/ScalaObject
const #197 = Asciz	scala/Product;
const #198 = class	#197;	//  scala/Product
const #199 = Asciz	java/io/Serializable;
const #200 = class	#199;	//  java/io/Serializable

{
public final scala.util.parsing.ast.Binders $outer;

public scala.util.parsing.ast.Binders$BoundElement(scala.util.parsing.ast.Binders, scala.util.parsing.ast.AbstractSyntax$NameElement, scala.util.parsing.ast.Binders$Scope);
  Code:
   Stack=2, Locals=4, Args_size=4
   0:	aload_0
   1:	aload_2
   2:	putfield	#21; //Field el:Lscala/util/parsing/ast/AbstractSyntax$NameElement;
   5:	aload_0
   6:	aload_3
   7:	putfield	#23; //Field scope:Lscala/util/parsing/ast/Binders$Scope;
   10:	aload_1
   11:	ifnonnull	22
   14:	new	#25; //class java/lang/NullPointerException
   17:	dup
   18:	invokespecial	#28; //Method java/lang/NullPointerException."<init>":()V
   21:	athrow
   22:	aload_0
   23:	aload_1
   24:	putfield	#30; //Field $outer:Lscala/util/parsing/ast/Binders;
   27:	aload_0
   28:	invokespecial	#33; //Method java/lang/Object."<init>":()V
   31:	aload_0
   32:	invokestatic	#39; //Method scala/util/parsing/input/Positional$class.$init$:(Lscala/util/parsing/input/Positional;)V
   35:	aload_0
   36:	invokestatic	#44; //Method scala/util/parsing/ast/AbstractSyntax$NameElement$class.$init$:(Lscala/util/parsing/ast/AbstractSyntax$NameElement;)V
   39:	aload_0
   40:	invokestatic	#49; //Method scala/Proxy$class.$init$:(Lscala/Proxy;)V
   43:	aload_0
   44:	invokestatic	#54; //Method scala/Product$class.$init$:(Lscala/Product;)V
   47:	return
  LineNumberTable: 
   line 198: 0

  LocalVariableTable: 
   Start  Length  Slot  Name   Signature
   0      48      0    this       Lscala/util/parsing/ast/Binders$BoundElement;
   0      48      1    $outer       Lscala/util/parsing/ast/Binders;
   0      48      2    el       Lscala/util/parsing/ast/AbstractSyntax$NameElement;
   0      48      3    scope       Lscala/util/parsing/ast/Binders$Scope;

  Signature: length = 0x2
   00 3A 

public java.lang.Object self();
  Code:
   Stack=1, Locals=1, Args_size=1
   0:	aload_0
   1:	invokevirtual	#63; //Method self:()Lscala/util/parsing/ast/AbstractSyntax$Element;
   4:	areturn
  LineNumberTable: 
   line 198: 0


public scala.util.parsing.ast.AbstractSyntax scala$util$parsing$ast$AbstractSyntax$NameElement$$$outer();
  Code:
   Stack=1, Locals=1, Args_size=1
   0:	aload_0
   1:	invokevirtual	#69; //Method scala$util$parsing$ast$Binders$BoundElement$$$outer:()Lscala/util/parsing/ast/Binders;
   4:	areturn
  LineNumberTable: 
   line 198: 1


public scala.util.parsing.ast.Binders scala$util$parsing$ast$Binders$BoundElement$$$outer();
  Code:
   Stack=1, Locals=1, Args_size=1
   0:	aload_0
   1:	getfield	#30; //Field $outer:Lscala/util/parsing/ast/Binders;
   4:	areturn
  LineNumberTable: 
   line 198: 0


public boolean canEqual(java.lang.Object);
  Code:
   Stack=1, Locals=2, Args_size=2
   0:	aload_1
   1:	instanceof	#19; //class scala/util/parsing/ast/Binders$BoundElement
   4:	ireturn
  LineNumberTable: 
   line 198: 0


public java.lang.Object productElement(int);
  Code:
   Stack=3, Locals=2, Args_size=2
   0:	iload_1
   1:	tableswitch{ //0 to 1
		0: 84;
		1: 58;
		default: 24 }
   24:	iconst_1
   25:	ifeq	43
   28:	new	#75; //class java/lang/IndexOutOfBoundsException
   31:	dup
   32:	iload_1
   33:	invokestatic	#81; //Method scala/runtime/BoxesRunTime.boxToInteger:(I)Ljava/lang/Integer;
   36:	invokevirtual	#85; //Method java/lang/Object.toString:()Ljava/lang/String;
   39:	invokespecial	#88; //Method java/lang/IndexOutOfBoundsException."<init>":(Ljava/lang/String;)V
   42:	athrow
   43:	new	#90; //class scala/MatchError
   46:	dup
   47:	iload_1
   48:	invokestatic	#81; //Method scala/runtime/BoxesRunTime.boxToInteger:(I)Ljava/lang/Integer;
   51:	invokevirtual	#85; //Method java/lang/Object.toString:()Ljava/lang/String;
   54:	invokespecial	#91; //Method scala/MatchError."<init>":(Ljava/lang/String;)V
   57:	athrow
   58:	iconst_1
   59:	ifeq	69
   62:	aload_0
   63:	invokevirtual	#94; //Method scope:()Lscala/util/parsing/ast/Binders$Scope;
   66:	goto	92
   69:	new	#90; //class scala/MatchError
   72:	dup
   73:	iload_1
   74:	invokestatic	#81; //Method scala/runtime/BoxesRunTime.boxToInteger:(I)Ljava/lang/Integer;
   77:	invokevirtual	#85; //Method java/lang/Object.toString:()Ljava/lang/String;
   80:	invokespecial	#91; //Method scala/MatchError."<init>":(Ljava/lang/String;)V
   83:	athrow
   84:	iconst_1
   85:	ifeq	93
   88:	aload_0
   89:	invokevirtual	#97; //Method el:()Lscala/util/parsing/ast/AbstractSyntax$NameElement;
   92:	areturn
   93:	new	#90; //class scala/MatchError
   96:	dup
   97:	iload_1
   98:	invokestatic	#81; //Method scala/runtime/BoxesRunTime.boxToInteger:(I)Ljava/lang/Integer;
   101:	invokevirtual	#85; //Method java/lang/Object.toString:()Ljava/lang/String;
   104:	invokespecial	#91; //Method scala/MatchError."<init>":(Ljava/lang/String;)V
   107:	athrow
  LineNumberTable: 
   line 198: 0
   line 21: 24
   line 198: 28
   line 21: 58
   line 198: 62
   line 21: 84
   line 198: 88


public int productArity();
  Code:
   Stack=1, Locals=1, Args_size=1
   0:	iconst_2
   1:	ireturn
  LineNumberTable: 
   line 198: 0


public java.lang.String productPrefix();
  Code:
   Stack=1, Locals=1, Args_size=1
   0:	ldc	#102; //String BoundElement
   2:	areturn
  LineNumberTable: 
   line 198: 0


public scala.util.parsing.ast.Binders$BoundElement copy(scala.util.parsing.ast.AbstractSyntax$NameElement, scala.util.parsing.ast.Binders$Scope);
  Code:
   Stack=5, Locals=3, Args_size=3
   0:	new	#19; //class scala/util/parsing/ast/Binders$BoundElement
   3:	dup
   4:	aload_0
   5:	invokevirtual	#69; //Method scala$util$parsing$ast$Binders$BoundElement$$$outer:()Lscala/util/parsing/ast/Binders;
   8:	aload_1
   9:	aload_2
   10:	invokespecial	#106; //Method "<init>":(Lscala/util/parsing/ast/Binders;Lscala/util/parsing/ast/AbstractSyntax$NameElement;Lscala/util/parsing/ast/Binders$Scope;)V
   13:	areturn
  LineNumberTable: 
   line 198: 0

  LocalVariableTable: 
   Start  Length  Slot  Name   Signature
   0      14      0    this       Lscala/util/parsing/ast/Binders$BoundElement;
   0      14      1    el       Lscala/util/parsing/ast/AbstractSyntax$NameElement;
   0      14      2    scope       Lscala/util/parsing/ast/Binders$Scope;


public boolean alpha_$eq$eq(scala.util.parsing.ast.Binders$BoundElement);
  Code:
   Stack=3, Locals=3, Args_size=2
   0:	aload_0
   1:	invokevirtual	#94; //Method scope:()Lscala/util/parsing/ast/Binders$Scope;
   4:	aload_0
   5:	invokevirtual	#97; //Method el:()Lscala/util/parsing/ast/AbstractSyntax$NameElement;
   8:	invokevirtual	#114; //Method scala/util/parsing/ast/Binders$Scope.indexFor:(Lscala/util/parsing/ast/AbstractSyntax$NameElement;)Lscala/Option;
   11:	aload_1
   12:	invokevirtual	#94; //Method scope:()Lscala/util/parsing/ast/Binders$Scope;
   15:	aload_1
   16:	invokevirtual	#97; //Method el:()Lscala/util/parsing/ast/AbstractSyntax$NameElement;
   19:	invokevirtual	#114; //Method scala/util/parsing/ast/Binders$Scope.indexFor:(Lscala/util/parsing/ast/AbstractSyntax$NameElement;)Lscala/Option;
   22:	astore_2
   23:	dup
   24:	ifnonnull	35
   27:	pop
   28:	aload_2
   29:	ifnull	42
   32:	goto	46
   35:	aload_2
   36:	invokevirtual	#117; //Method java/lang/Object.equals:(Ljava/lang/Object;)Z
   39:	ifeq	46
   42:	iconst_1
   43:	goto	47
   46:	iconst_0
   47:	ireturn
  LineNumberTable: 
   line 210: 0

  LocalVariableTable: 
   Start  Length  Slot  Name   Signature
   0      48      0    this       Lscala/util/parsing/ast/Binders$BoundElement;
   0      48      1    other       Lscala/util/parsing/ast/Binders$BoundElement;

  Signature: length = 0x2
   00 77 

public java.lang.String toString();
  Code:
   Stack=2, Locals=2, Args_size=1
   0:	new	#121; //class scala/collection/mutable/StringBuilder
   3:	dup
   4:	invokespecial	#122; //Method scala/collection/mutable/StringBuilder."<init>":()V
   7:	aload_0
   8:	invokestatic	#125; //Method scala/Proxy$class.toString:(Lscala/Proxy;)Ljava/lang/String;
   11:	invokevirtual	#129; //Method scala/collection/mutable/StringBuilder.append:(Ljava/lang/Object;)Lscala/collection/mutable/StringBuilder;
   14:	ldc	#131; //String @
   16:	invokevirtual	#129; //Method scala/collection/mutable/StringBuilder.append:(Ljava/lang/Object;)Lscala/collection/mutable/StringBuilder;
   19:	aload_0
   20:	invokevirtual	#94; //Method scope:()Lscala/util/parsing/ast/Binders$Scope;
   23:	invokevirtual	#134; //Method scala/util/parsing/ast/Binders$Scope.id:()I
   26:	istore_1
   27:	iload_1
   28:	invokestatic	#81; //Method scala/runtime/BoxesRunTime.boxToInteger:(I)Ljava/lang/Integer;
   31:	invokevirtual	#129; //Method scala/collection/mutable/StringBuilder.append:(Ljava/lang/Object;)Lscala/collection/mutable/StringBuilder;
   34:	invokevirtual	#135; //Method scala/collection/mutable/StringBuilder.toString:()Ljava/lang/String;
   37:	areturn
  LineNumberTable: 
   line 208: 0


public java.lang.String name();
  Code:
   Stack=1, Locals=1, Args_size=1
   0:	aload_0
   1:	invokevirtual	#63; //Method self:()Lscala/util/parsing/ast/AbstractSyntax$Element;
   4:	checkcast	#138; //class scala/util/parsing/ast/AbstractSyntax$NameElement
   7:	invokeinterface	#140,  1; //InterfaceMethod scala/util/parsing/ast/AbstractSyntax$NameElement.name:()Ljava/lang/String;
   12:	areturn
  LineNumberTable: 
   line 205: 0


public scala.util.parsing.ast.AbstractSyntax$Element self();
  Code:
   Stack=2, Locals=1, Args_size=1
   0:	aload_0
   1:	invokevirtual	#94; //Method scope:()Lscala/util/parsing/ast/Binders$Scope;
   4:	aload_0
   5:	invokevirtual	#97; //Method el:()Lscala/util/parsing/ast/AbstractSyntax$NameElement;
   8:	invokevirtual	#144; //Method scala/util/parsing/ast/Binders$Scope.getElementFor:(Lscala/util/parsing/ast/AbstractSyntax$NameElement;)Lscala/util/parsing/ast/AbstractSyntax$Element;
   11:	areturn
  LineNumberTable: 
   line 203: 0


public scala.util.parsing.ast.Binders$Scope scope();
  Code:
   Stack=1, Locals=1, Args_size=1
   0:	aload_0
   1:	getfield	#23; //Field scope:Lscala/util/parsing/ast/Binders$Scope;
   4:	areturn
  LineNumberTable: 
   line 198: 0

  Signature: length = 0x2
   00 FFFFFF91 

public scala.util.parsing.ast.AbstractSyntax$NameElement el();
  Code:
   Stack=1, Locals=1, Args_size=1
   0:	aload_0
   1:	getfield	#21; //Field el:Lscala/util/parsing/ast/AbstractSyntax$NameElement;
   4:	areturn
  LineNumberTable: 
   line 198: 0

  Signature: length = 0x2
   00 FFFFFF92 

public scala.util.parsing.ast.AbstractSyntax$NameElement copy$default$1();
  Code:
   Stack=1, Locals=1, Args_size=1
   0:	aload_0
   1:	invokevirtual	#97; //Method el:()Lscala/util/parsing/ast/AbstractSyntax$NameElement;
   4:	areturn
  LineNumberTable: 
   line 198: 0


public scala.util.parsing.ast.Binders$Scope copy$default$2();
  Code:
   Stack=1, Locals=1, Args_size=1
   0:	aload_0
   1:	invokevirtual	#94; //Method scope:()Lscala/util/parsing/ast/Binders$Scope;
   4:	areturn
  LineNumberTable: 
   line 198: 0


public scala.util.parsing.input.Positional setPos(scala.util.parsing.input.Position);
  Code:
   Stack=2, Locals=2, Args_size=2
   0:	aload_0
   1:	aload_1
   2:	invokestatic	#153; //Method scala/util/parsing/input/Positional$class.setPos:(Lscala/util/parsing/input/Positional;Lscala/util/parsing/input/Position;)Lscala/util/parsing/input/Positional;
   5:	areturn
  LineNumberTable: 
   line 198: 0

  LocalVariableTable: 
   Start  Length  Slot  Name   Signature
   0      6      0    this       Lscala/util/parsing/ast/Binders$BoundElement;
   0      6      1    newpos       Lscala/util/parsing/input/Position;


public void pos_$eq(scala.util.parsing.input.Position);
  Code:
   Stack=2, Locals=2, Args_size=2
   0:	aload_0
   1:	aload_1
   2:	putfield	#158; //Field pos:Lscala/util/parsing/input/Position;
   5:	return
  LineNumberTable: 
   line 198: 0


public scala.util.parsing.input.Position pos();
  Code:
   Stack=1, Locals=1, Args_size=1
   0:	aload_0
   1:	getfield	#158; //Field pos:Lscala/util/parsing/input/Position;
   4:	areturn
  LineNumberTable: 
   line 198: 0


public boolean equals(java.lang.Object);
  Code:
   Stack=2, Locals=2, Args_size=2
   0:	aload_0
   1:	aload_1
   2:	invokestatic	#162; //Method scala/Proxy$class.equals:(Lscala/Proxy;Ljava/lang/Object;)Z
   5:	ireturn
  LineNumberTable: 
   line 198: 0

  LocalVariableTable: 
   Start  Length  Slot  Name   Signature
   0      6      0    this       Lscala/util/parsing/ast/Binders$BoundElement;
   0      6      1    that       Ljava/lang/Object;


public int hashCode();
  Code:
   Stack=1, Locals=1, Args_size=1
   0:	aload_0
   1:	invokestatic	#168; //Method scala/Proxy$class.hashCode:(Lscala/Proxy;)I
   4:	ireturn
  LineNumberTable: 
   line 198: 0


public scala.collection.Iterator productElements();
  Code:
   Stack=1, Locals=1, Args_size=1
   0:	aload_0
   1:	invokestatic	#173; //Method scala/Product$class.productElements:(Lscala/Product;)Lscala/collection/Iterator;
   4:	areturn
  LineNumberTable: 
   line 198: 0

  Deprecated: true

public scala.collection.Iterator productIterator();
  Code:
   Stack=1, Locals=1, Args_size=1
   0:	aload_0
   1:	invokestatic	#177; //Method scala/Product$class.productIterator:(Lscala/Product;)Lscala/collection/Iterator;
   4:	areturn
  LineNumberTable: 
   line 198: 0


}

