Compiled from "Binders.scala"
public final class scala.util.parsing.ast.Mappable$$anon$2$$anonfun$gmap$2 extends scala.runtime.AbstractFunction1 implements java.io.Serializable
  SourceFile: "Binders.scala"
  Scala: length = 0x
   
  InnerClass: 
   public abstract Mapper=class scala/util/parsing/ast/Mappable$Mapper of class scala/util/parsing/ast/Mappable
   public final $anon$2=class scala/util/parsing/ast/Mappable$$anon$2 of class scala/util/parsing/ast/Mappable
   public final $anonfun$gmap$2=class scala/util/parsing/ast/Mappable$$anon$2$$anonfun$gmap$2 of class scala/util/parsing/ast/Mappable$$anon$2
  minor version: 0
  major version: 49
  Constant pool:
Asciz	SourceFile;
Asciz	Binders.scala;
Asciz	<clinit>;
Asciz	()V;
Asciz	Code;
Asciz	serialVersionUID;
Asciz	J;
Asciz	scala/util/parsing/ast/Mappable$$anon$2$$anonfun$gmap$2;
class	scala/util/parsing/ast/Mappable$$anon$2$$anonfun$gmap$2
NameAndType	serialVersionUID:J
Field	scala/util/parsing/ast/Mappable$$anon$2$$anonfun$gmap$2.serialVersionUID:J
Asciz	f$2;
Asciz	Lscala/util/parsing/ast/Mappable$Mapper;;
Asciz	$outer;
Asciz	Lscala/util/parsing/ast/Mappable$$anon$2;;
Asciz	<init>;
Asciz	(Lscala/util/parsing/ast/Mappable$$anon$2;Lscala/util/parsing/ast/Mappable$Mapper;)V;
Asciz	LineNumberTable;
Asciz	java/lang/NullPointerException;
class	java/lang/NullPointerException
NameAndType	"<init>":()V
Method	java/lang/NullPointerException."<init>":()V
NameAndType	$outer:Lscala/util/parsing/ast/Mappable$$anon$2;
Field	scala/util/parsing/ast/Mappable$$anon$2$$anonfun$gmap$2.$outer:Lscala/util/parsing/ast/Mappable$$anon$2;
NameAndType	f$2:Lscala/util/parsing/ast/Mappable$Mapper;
Field	scala/util/parsing/ast/Mappable$$anon$2$$anonfun$gmap$2.f$2:Lscala/util/parsing/ast/Mappable$Mapper;
Asciz	scala/runtime/AbstractFunction1;
class	scala/runtime/AbstractFunction1
Method	scala/runtime/AbstractFunction1."<init>":()V
Asciz	this;
Asciz	Lscala/util/parsing/ast/Mappable$$anon$2$$anonfun$gmap$2;;
Asciz	LocalVariableTable;
Asciz	apply;
Asciz	(Ljava/lang/Object;)Ljava/lang/Object;;
Asciz	scala/util/parsing/ast/Mappable$$anon$2;
class	scala/util/parsing/ast/Mappable$$anon$2
Asciz	evidence$3$1;
Asciz	Lscala/Function1;;
NameAndType	evidence$3$1:Lscala/Function1;
Field	scala/util/parsing/ast/Mappable$$anon$2.evidence$3$1:Lscala/Function1;
Asciz	scala/util/parsing/ast/Mappable$Mapper;
class	scala/util/parsing/ast/Mappable$Mapper
Asciz	(Ljava/lang/Object;Lscala/Function1;)Ljava/lang/Object;;
NameAndType	apply:(Ljava/lang/Object;Lscala/Function1;)Ljava/lang/Object;
InterfaceMethod	scala/util/parsing/ast/Mappable$Mapper.apply:(Ljava/lang/Object;Lscala/Function1;)Ljava/lang/Object;
Asciz	x;
Asciz	Ljava/lang/Object;;
Asciz	(Tt;)Tt;;
Asciz	Signature;
Asciz	Scala;
Asciz	InnerClasses;
Asciz	scala/util/parsing/ast/Mappable;
class	scala/util/parsing/ast/Mappable
Asciz	Mapper;
Asciz	$anon$2;
Asciz	$anonfun$gmap$2;
Asciz	java/io/Serializable;
class	java/io/Serializable

{
public static final long serialVersionUID;
  Signature: J

private final scala.util.parsing.ast.Mappable$Mapper f$2;
  Signature: Lscala/util/parsing/ast/Mappable$Mapper;

private final scala.util.parsing.ast.Mappable$$anon$2 $outer;
  Signature: Lscala/util/parsing/ast/Mappable$$anon$2;

public static {};
  Signature: ()V
  Code:
   Stack=2, Locals=0, Args_size=0
	lconst_0
	putstatic	Field serialVersionUID:J
	return
  Labels:

public scala.util.parsing.ast.Mappable$$anon$2$$anonfun$gmap$2(scala.util.parsing.ast.Mappable$$anon$2, scala.util.parsing.ast.Mappable$Mapper);
  Signature: (Lscala/util/parsing/ast/Mappable$$anon$2;Lscala/util/parsing/ast/Mappable$Mapper;)V
  Code:
   Stack=2, Locals=3, Args_size=3
	aload_1
	ifnonnull	l1 // aload_0
	new	class java/lang/NullPointerException
	dup
	invokespecial	Method java/lang/NullPointerException."<init>":()V
	athrow
l1	aload_0
	aload_1
	putfield	Field $outer:Lscala/util/parsing/ast/Mappable$$anon$2;
	aload_0
	aload_2
	putfield	Field f$2:Lscala/util/parsing/ast/Mappable$Mapper;
	aload_0
	invokespecial	Method scala/runtime/AbstractFunction1."<init>":()V
	return
  Labels:
   	l1 = 12 // aload_0
  LocalVariableTable: 
   Start  Length  Slot  Name   Signature
   0      27      0    this       Lscala/util/parsing/ast/Mappable$$anon$2$$anonfun$gmap$2;
   0      27      1    $outer       Lscala/util/parsing/ast/Mappable$$anon$2;


public final java.lang.Object apply(java.lang.Object);
  Signature: (Ljava/lang/Object;)Ljava/lang/Object;
  Code:
   Stack=3, Locals=2, Args_size=2
	aload_0
	getfield	Field f$2:Lscala/util/parsing/ast/Mappable$Mapper;
	aload_1
	aload_0
	getfield	Field $outer:Lscala/util/parsing/ast/Mappable$$anon$2;
	getfield	Field scala/util/parsing/ast/Mappable$$anon$2.evidence$3$1:Lscala/Function1;
	invokeinterface	InterfaceMethod scala/util/parsing/ast/Mappable$Mapper.apply:(Ljava/lang/Object;Lscala/Function1;)Ljava/lang/Object;
	areturn
  Labels:
  LocalVariableTable: 
   Start  Length  Slot  Name   Signature
   0      18      0    this       Lscala/util/parsing/ast/Mappable$$anon$2$$anonfun$gmap$2;
   0      18      1    x       Ljava/lang/Object;

  Signature: length = 0x2
   00 30 

}

