Compiled from "Binders.scala"
public final class scala.util.parsing.ast.Mappable$$anon$3 extends java.lang.Object implements scala.util.parsing.ast.Mappable$Mappable
  SourceFile: "Binders.scala"
  Signature: length = 0x2
   00 43 
  Scala: length = 0x
   
  InnerClass: 
   public abstract Mapper=class scala/util/parsing/ast/Mappable$Mapper of class scala/util/parsing/ast/Mappable
   public final $anon$3=class scala/util/parsing/ast/Mappable$$anon$3 of class scala/util/parsing/ast/Mappable
   public abstract Mappable=class scala/util/parsing/ast/Mappable$Mappable of class scala/util/parsing/ast/Mappable
   public final $anonfun$gmap$3=class scala/util/parsing/ast/Mappable$$anon$3$$anonfun$gmap$3 of class scala/util/parsing/ast/Mappable$$anon$3
  minor version: 0
  major version: 49
  Constant pool:
Asciz	SourceFile;
Asciz	Binders.scala;
Asciz	evidence$4$1;
Asciz	Lscala/Function1;;
Asciz	xs$1;
Asciz	Lscala/Option;;
Asciz	$outer;
Asciz	Lscala/util/parsing/ast/Mappable;;
Asciz	<init>;
Asciz	(Lscala/util/parsing/ast/Mappable;Lscala/Option;Lscala/Function1;)V;
Asciz	Code;
Asciz	LineNumberTable;
Asciz	java/lang/NullPointerException;
class	java/lang/NullPointerException
Asciz	()V;
NameAndType	"<init>":()V
Method	java/lang/NullPointerException."<init>":()V
Asciz	scala/util/parsing/ast/Mappable$$anon$3;
class	scala/util/parsing/ast/Mappable$$anon$3
NameAndType	$outer:Lscala/util/parsing/ast/Mappable;
Field	scala/util/parsing/ast/Mappable$$anon$3.$outer:Lscala/util/parsing/ast/Mappable;
NameAndType	xs$1:Lscala/Option;
Field	scala/util/parsing/ast/Mappable$$anon$3.xs$1:Lscala/Option;
NameAndType	evidence$4$1:Lscala/Function1;
Field	scala/util/parsing/ast/Mappable$$anon$3.evidence$4$1:Lscala/Function1;
Asciz	java/lang/Object;
class	java/lang/Object
Method	java/lang/Object."<init>":()V
Asciz	scala/util/parsing/ast/Mappable$Mappable$class;
class	scala/util/parsing/ast/Mappable$Mappable$class
Asciz	$init$;
Asciz	(Lscala/util/parsing/ast/Mappable$Mappable;)V;
NameAndType	$init$:(Lscala/util/parsing/ast/Mappable$Mappable;)V
Method	scala/util/parsing/ast/Mappable$Mappable$class.$init$:(Lscala/util/parsing/ast/Mappable$Mappable;)V
Asciz	this;
Asciz	Lscala/util/parsing/ast/Mappable$$anon$3;;
Asciz	LocalVariableTable;
Asciz	gmap;
Asciz	(Lscala/util/parsing/ast/Mappable$Mapper;)Ljava/lang/Object;;
Asciz	(Lscala/util/parsing/ast/Mappable$Mapper;)Lscala/Option;;
NameAndType	gmap:(Lscala/util/parsing/ast/Mappable$Mapper;)Lscala/Option;
Method	scala/util/parsing/ast/Mappable$$anon$3.gmap:(Lscala/util/parsing/ast/Mappable$Mapper;)Lscala/Option;
Asciz	f;
Asciz	Lscala/util/parsing/ast/Mappable$Mapper;;
Asciz	scala$util$parsing$ast$Mappable$Mappable$$$outer;
Asciz	()Lscala/util/parsing/ast/Mappable;;
Asciz	scala/util/parsing/ast/Mappable$$anon$3$$anonfun$gmap$3;
class	scala/util/parsing/ast/Mappable$$anon$3$$anonfun$gmap$3
Asciz	(Lscala/util/parsing/ast/Mappable$$anon$3;Lscala/util/parsing/ast/Mappable$Mapper;)V;
NameAndType	"<init>":(Lscala/util/parsing/ast/Mappable$$anon$3;Lscala/util/parsing/ast/Mappable$Mapper;)V
Method	scala/util/parsing/ast/Mappable$$anon$3$$anonfun$gmap$3."<init>":(Lscala/util/parsing/ast/Mappable$$anon$3;Lscala/util/parsing/ast/Mappable$Mapper;)V
Asciz	scala/Option;
class	scala/Option
Asciz	map;
Asciz	(Lscala/Function1;)Lscala/Option;;
NameAndType	map:(Lscala/Function1;)Lscala/Option;
Method	scala/Option.map:(Lscala/Function1;)Lscala/Option;
Asciz	f$3;
Asciz	(Lscala/util/parsing/ast/Mappable$Mapper;)Lscala/Option<Tt;>;;
Asciz	Signature;
Asciz	everywhere;
Asciz	(Lscala/util/parsing/ast/Mappable$Mapper;Lscala/Function1;)Ljava/lang/Object;;
Asciz	(Lscala/util/parsing/ast/Mappable$Mappable;Lscala/util/parsing/ast/Mappable$Mapper;Lscala/Function1;)Ljava/lang/Object;;
NameAndType	everywhere:(Lscala/util/parsing/ast/Mappable$Mappable;Lscala/util/parsing/ast/Mappable$Mapper;Lscala/Function1;)Ljava/lang/Object;
Method	scala/util/parsing/ast/Mappable$Mappable$class.everywhere:(Lscala/util/parsing/ast/Mappable$Mappable;Lscala/util/parsing/ast/Mappable$Mapper;Lscala/Function1;)Ljava/lang/Object;
Asciz	c;
Asciz	Ljava/lang/Object;Lscala/util/parsing/ast/Mappable$Mappable<Lscala/Option<Tt;>;>;;
Asciz	Scala;
Asciz	InnerClasses;
Asciz	scala/util/parsing/ast/Mappable$Mapper;
class	scala/util/parsing/ast/Mappable$Mapper
Asciz	scala/util/parsing/ast/Mappable;
class	scala/util/parsing/ast/Mappable
Asciz	Mapper;
Asciz	$anon$3;
Asciz	scala/util/parsing/ast/Mappable$Mappable;
class	scala/util/parsing/ast/Mappable$Mappable
Asciz	Mappable;
Asciz	$anonfun$gmap$3;

{
public final scala.Function1 evidence$4$1;
  Signature: Lscala/Function1;

private final scala.Option xs$1;
  Signature: Lscala/Option;

private final scala.util.parsing.ast.Mappable $outer;
  Signature: Lscala/util/parsing/ast/Mappable;

public scala.util.parsing.ast.Mappable$$anon$3(scala.util.parsing.ast.Mappable, scala.Option, scala.Function1);
  Signature: (Lscala/util/parsing/ast/Mappable;Lscala/Option;Lscala/Function1;)V
  Code:
   Stack=2, Locals=4, Args_size=4
	aload_1
	ifnonnull	l1 // aload_0
	new	class java/lang/NullPointerException
	dup
	invokespecial	Method java/lang/NullPointerException."<init>":()V
	athrow
l1	aload_0
	aload_1
	putfield	Field $outer:Lscala/util/parsing/ast/Mappable;
	aload_0
	aload_2
	putfield	Field xs$1:Lscala/Option;
	aload_0
	aload_3
	putfield	Field evidence$4$1:Lscala/Function1;
	aload_0
	invokespecial	Method java/lang/Object."<init>":()V
	aload_0
	invokestatic	Method scala/util/parsing/ast/Mappable$Mappable$class.$init$:(Lscala/util/parsing/ast/Mappable$Mappable;)V
	return
  Labels:
   	l1 = 12 // aload_0
  LocalVariableTable: 
   Start  Length  Slot  Name   Signature
   0      36      0    this       Lscala/util/parsing/ast/Mappable$$anon$3;
   0      36      1    $outer       Lscala/util/parsing/ast/Mappable;


public java.lang.Object gmap(scala.util.parsing.ast.Mappable$Mapper);
  Signature: (Lscala/util/parsing/ast/Mappable$Mapper;)Ljava/lang/Object;
  Code:
   Stack=2, Locals=2, Args_size=2
	aload_0
	aload_1
	invokevirtual	Method gmap:(Lscala/util/parsing/ast/Mappable$Mapper;)Lscala/Option;
	areturn
  Labels:
  LocalVariableTable: 
   Start  Length  Slot  Name   Signature
   0      6      0    this       Lscala/util/parsing/ast/Mappable$$anon$3;
   0      6      1    f       Lscala/util/parsing/ast/Mappable$Mapper;


public scala.util.parsing.ast.Mappable scala$util$parsing$ast$Mappable$Mappable$$$outer();
  Signature: ()Lscala/util/parsing/ast/Mappable;
  Code:
   Stack=1, Locals=1, Args_size=1
	aload_0
	getfield	Field $outer:Lscala/util/parsing/ast/Mappable;
	areturn
  Labels:

public scala.Option gmap(scala.util.parsing.ast.Mappable$Mapper);
  Signature: (Lscala/util/parsing/ast/Mappable$Mapper;)Lscala/Option;
  Code:
   Stack=5, Locals=2, Args_size=2
	aload_0
	getfield	Field xs$1:Lscala/Option;
	new	class scala/util/parsing/ast/Mappable$$anon$3$$anonfun$gmap$3
	dup
	aload_0
	aload_1
	invokespecial	Method scala/util/parsing/ast/Mappable$$anon$3$$anonfun$gmap$3."<init>":(Lscala/util/parsing/ast/Mappable$$anon$3;Lscala/util/parsing/ast/Mappable$Mapper;)V
	invokevirtual	Method scala/Option.map:(Lscala/Function1;)Lscala/Option;
	areturn
  Labels:
  LocalVariableTable: 
   Start  Length  Slot  Name   Signature
   0      17      0    this       Lscala/util/parsing/ast/Mappable$$anon$3;
   0      17      1    f$3       Lscala/util/parsing/ast/Mappable$Mapper;

  Signature: length = 0x2
   00 3B 

public java.lang.Object everywhere(scala.util.parsing.ast.Mappable$Mapper, scala.Function1);
  Signature: (Lscala/util/parsing/ast/Mappable$Mapper;Lscala/Function1;)Ljava/lang/Object;
  Code:
   Stack=3, Locals=3, Args_size=3
	aload_0
	aload_1
	aload_2
	invokestatic	Method scala/util/parsing/ast/Mappable$Mappable$class.everywhere:(Lscala/util/parsing/ast/Mappable$Mappable;Lscala/util/parsing/ast/Mappable$Mapper;Lscala/Function1;)Ljava/lang/Object;
	areturn
  Labels:
  LocalVariableTable: 
   Start  Length  Slot  Name   Signature
   0      7      0    this       Lscala/util/parsing/ast/Mappable$$anon$3;
   0      7      1    f       Lscala/util/parsing/ast/Mappable$Mapper;
   0      7      2    c       Lscala/Function1;


}

