Compiled from "Binders.scala"
public abstract class scala.util.parsing.ast.Mappable$class extends java.lang.Object
  SourceFile: "Binders.scala"
  Scala: length = 0x
   
  InnerClass: 
   public final #45= #25 of #44; //$anon$2=class scala/util/parsing/ast/Mappable$$anon$2 of class scala/util/parsing/ast/Mappable
   public final #46= #13 of #44; //$anon$3=class scala/util/parsing/ast/Mappable$$anon$3 of class scala/util/parsing/ast/Mappable
   public final #47= #35 of #44; //$anon$1=class scala/util/parsing/ast/Mappable$$anon$1 of class scala/util/parsing/ast/Mappable
   public abstract #50= #49 of #44; //Mappable=class scala/util/parsing/ast/Mappable$Mappable of class scala/util/parsing/ast/Mappable
  minor version: 0
  major version: 49
  Constant pool:
const #1 = Asciz	SourceFile;
const #2 = Asciz	Binders.scala;
const #3 = Asciz	$init$;
const #4 = Asciz	(Lscala/util/parsing/ast/Mappable;)V;
const #5 = Asciz	Code;
const #6 = Asciz	LineNumberTable;
const #7 = Asciz	$this;
const #8 = Asciz	Lscala/util/parsing/ast/Mappable;;
const #9 = Asciz	LocalVariableTable;
const #10 = Asciz	OptionIsMappable;
const #11 = Asciz	(Lscala/util/parsing/ast/Mappable;Lscala/Option;Lscala/Function1;)Lscala/util/parsing/ast/Mappable$Mappable;;
const #12 = Asciz	scala/util/parsing/ast/Mappable$$anon$3;
const #13 = class	#12;	//  scala/util/parsing/ast/Mappable$$anon$3
const #14 = Asciz	<init>;
const #15 = Asciz	(Lscala/util/parsing/ast/Mappable;Lscala/Option;Lscala/Function1;)V;
const #16 = NameAndType	#14:#15;//  "<init>":(Lscala/util/parsing/ast/Mappable;Lscala/Option;Lscala/Function1;)V
const #17 = Method	#13.#16;	//  scala/util/parsing/ast/Mappable$$anon$3."<init>":(Lscala/util/parsing/ast/Mappable;Lscala/Option;Lscala/Function1;)V
const #18 = Asciz	xs$1;
const #19 = Asciz	Lscala/Option;;
const #20 = Asciz	view$4$1;
const #21 = Asciz	Lscala/Function1;;
const #22 = Asciz	ListIsMappable;
const #23 = Asciz	(Lscala/util/parsing/ast/Mappable;Lscala/collection/immutable/List;Lscala/Function1;)Lscala/util/parsing/ast/Mappable$Mappable;;
const #24 = Asciz	scala/util/parsing/ast/Mappable$$anon$2;
const #25 = class	#24;	//  scala/util/parsing/ast/Mappable$$anon$2
const #26 = Asciz	(Lscala/util/parsing/ast/Mappable;Lscala/collection/immutable/List;Lscala/Function1;)V;
const #27 = NameAndType	#14:#26;//  "<init>":(Lscala/util/parsing/ast/Mappable;Lscala/collection/immutable/List;Lscala/Function1;)V
const #28 = Method	#25.#27;	//  scala/util/parsing/ast/Mappable$$anon$2."<init>":(Lscala/util/parsing/ast/Mappable;Lscala/collection/immutable/List;Lscala/Function1;)V
const #29 = Asciz	xs$2;
const #30 = Asciz	Lscala/collection/immutable/List;;
const #31 = Asciz	view$3$1;
const #32 = Asciz	StringIsMappable;
const #33 = Asciz	(Lscala/util/parsing/ast/Mappable;Ljava/lang/String;)Lscala/util/parsing/ast/Mappable$Mappable;;
const #34 = Asciz	scala/util/parsing/ast/Mappable$$anon$1;
const #35 = class	#34;	//  scala/util/parsing/ast/Mappable$$anon$1
const #36 = Asciz	(Lscala/util/parsing/ast/Mappable;Ljava/lang/String;)V;
const #37 = NameAndType	#14:#36;//  "<init>":(Lscala/util/parsing/ast/Mappable;Ljava/lang/String;)V
const #38 = Method	#35.#37;	//  scala/util/parsing/ast/Mappable$$anon$1."<init>":(Lscala/util/parsing/ast/Mappable;Ljava/lang/String;)V
const #39 = Asciz	s$1;
const #40 = Asciz	Ljava/lang/String;;
const #41 = Asciz	Scala;
const #42 = Asciz	InnerClasses;
const #43 = Asciz	scala/util/parsing/ast/Mappable;
const #44 = class	#43;	//  scala/util/parsing/ast/Mappable
const #45 = Asciz	$anon$2;
const #46 = Asciz	$anon$3;
const #47 = Asciz	$anon$1;
const #48 = Asciz	scala/util/parsing/ast/Mappable$Mappable;
const #49 = class	#48;	//  scala/util/parsing/ast/Mappable$Mappable
const #50 = Asciz	Mappable;
const #51 = Asciz	scala/util/parsing/ast/Mappable$class;
const #52 = class	#51;	//  scala/util/parsing/ast/Mappable$class
const #53 = Asciz	java/lang/Object;
const #54 = class	#53;	//  java/lang/Object

{
public static void $init$(scala.util.parsing.ast.Mappable);
  Code:
   Stack=0, Locals=1, Args_size=1
   0:	return
  LineNumberTable: 
   line 29: 0

  LocalVariableTable: 
   Start  Length  Slot  Name   Signature
   0      1      0    $this       Lscala/util/parsing/ast/Mappable;


public static scala.util.parsing.ast.Mappable$Mappable OptionIsMappable(scala.util.parsing.ast.Mappable, scala.Option, scala.Function1);
  Code:
   Stack=5, Locals=3, Args_size=3
   0:	new	#13; //class scala/util/parsing/ast/Mappable$$anon$3
   3:	dup
   4:	aload_0
   5:	aload_1
   6:	aload_2
   7:	invokespecial	#17; //Method scala/util/parsing/ast/Mappable$$anon$3."<init>":(Lscala/util/parsing/ast/Mappable;Lscala/Option;Lscala/Function1;)V
   10:	areturn
  LineNumberTable: 
   line 56: 0

  LocalVariableTable: 
   Start  Length  Slot  Name   Signature
   0      11      0    $this       Lscala/util/parsing/ast/Mappable;
   0      11      1    xs$1       Lscala/Option;
   0      11      2    view$4$1       Lscala/Function1;


public static scala.util.parsing.ast.Mappable$Mappable ListIsMappable(scala.util.parsing.ast.Mappable, scala.collection.immutable.List, scala.Function1);
  Code:
   Stack=5, Locals=3, Args_size=3
   0:	new	#25; //class scala/util/parsing/ast/Mappable$$anon$2
   3:	dup
   4:	aload_0
   5:	aload_1
   6:	aload_2
   7:	invokespecial	#28; //Method scala/util/parsing/ast/Mappable$$anon$2."<init>":(Lscala/util/parsing/ast/Mappable;Lscala/collection/immutable/List;Lscala/Function1;)V
   10:	areturn
  LineNumberTable: 
   line 51: 0

  LocalVariableTable: 
   Start  Length  Slot  Name   Signature
   0      11      0    $this       Lscala/util/parsing/ast/Mappable;
   0      11      1    xs$2       Lscala/collection/immutable/List;
   0      11      2    view$3$1       Lscala/Function1;


public static scala.util.parsing.ast.Mappable$Mappable StringIsMappable(scala.util.parsing.ast.Mappable, java.lang.String);
  Code:
   Stack=4, Locals=2, Args_size=2
   0:	new	#35; //class scala/util/parsing/ast/Mappable$$anon$1
   3:	dup
   4:	aload_0
   5:	aload_1
   6:	invokespecial	#38; //Method scala/util/parsing/ast/Mappable$$anon$1."<init>":(Lscala/util/parsing/ast/Mappable;Ljava/lang/String;)V
   9:	areturn
  LineNumberTable: 
   line 46: 0

  LocalVariableTable: 
   Start  Length  Slot  Name   Signature
   0      10      0    $this       Lscala/util/parsing/ast/Mappable;
   0      10      1    s$1       Ljava/lang/String;


}

