Compiled from "Binders.scala"
public abstract class scala.util.parsing.ast.Mappable$class extends java.lang.Object
  SourceFile: "Binders.scala"
  Scala: length = 0x
   
  InnerClass: 
   public final $anon$1=class scala/util/parsing/ast/Mappable$$anon$1 of class scala/util/parsing/ast/Mappable
   public final $anon$2=class scala/util/parsing/ast/Mappable$$anon$2 of class scala/util/parsing/ast/Mappable
   public final $anon$3=class scala/util/parsing/ast/Mappable$$anon$3 of class scala/util/parsing/ast/Mappable
   public abstract Mappable=class scala/util/parsing/ast/Mappable$Mappable of class scala/util/parsing/ast/Mappable
  minor version: 0
  major version: 49
  Constant pool:
Asciz	SourceFile;
Asciz	Binders.scala;
Asciz	$init$;
Asciz	(Lscala/util/parsing/ast/Mappable;)V;
Asciz	Code;
Asciz	LineNumberTable;
Asciz	$this;
Asciz	Lscala/util/parsing/ast/Mappable;;
Asciz	LocalVariableTable;
Asciz	OptionIsMappable;
Asciz	(Lscala/util/parsing/ast/Mappable;Lscala/Option;Lscala/Function1;)Lscala/util/parsing/ast/Mappable$Mappable;;
Asciz	scala/util/parsing/ast/Mappable$$anon$3;
class	scala/util/parsing/ast/Mappable$$anon$3
Asciz	<init>;
Asciz	(Lscala/util/parsing/ast/Mappable;Lscala/Option;Lscala/Function1;)V;
NameAndType	"<init>":(Lscala/util/parsing/ast/Mappable;Lscala/Option;Lscala/Function1;)V
Method	scala/util/parsing/ast/Mappable$$anon$3."<init>":(Lscala/util/parsing/ast/Mappable;Lscala/Option;Lscala/Function1;)V
Asciz	xs$1;
Asciz	Lscala/Option;;
Asciz	evidence$4$1;
Asciz	Lscala/Function1;;
Asciz	ListIsMappable;
Asciz	(Lscala/util/parsing/ast/Mappable;Lscala/collection/immutable/List;Lscala/Function1;)Lscala/util/parsing/ast/Mappable$Mappable;;
Asciz	scala/util/parsing/ast/Mappable$$anon$2;
class	scala/util/parsing/ast/Mappable$$anon$2
Asciz	(Lscala/util/parsing/ast/Mappable;Lscala/collection/immutable/List;Lscala/Function1;)V;
NameAndType	"<init>":(Lscala/util/parsing/ast/Mappable;Lscala/collection/immutable/List;Lscala/Function1;)V
Method	scala/util/parsing/ast/Mappable$$anon$2."<init>":(Lscala/util/parsing/ast/Mappable;Lscala/collection/immutable/List;Lscala/Function1;)V
Asciz	xs$2;
Asciz	Lscala/collection/immutable/List;;
Asciz	evidence$3$1;
Asciz	StringIsMappable;
Asciz	(Lscala/util/parsing/ast/Mappable;Ljava/lang/String;)Lscala/util/parsing/ast/Mappable$Mappable;;
Asciz	scala/util/parsing/ast/Mappable$$anon$1;
class	scala/util/parsing/ast/Mappable$$anon$1
Asciz	(Lscala/util/parsing/ast/Mappable;Ljava/lang/String;)V;
NameAndType	"<init>":(Lscala/util/parsing/ast/Mappable;Ljava/lang/String;)V
Method	scala/util/parsing/ast/Mappable$$anon$1."<init>":(Lscala/util/parsing/ast/Mappable;Ljava/lang/String;)V
Asciz	s$1;
Asciz	Ljava/lang/String;;
Asciz	Scala;
Asciz	InnerClasses;
Asciz	scala/util/parsing/ast/Mappable;
class	scala/util/parsing/ast/Mappable
Asciz	$anon$1;
Asciz	$anon$2;
Asciz	$anon$3;
Asciz	scala/util/parsing/ast/Mappable$Mappable;
class	scala/util/parsing/ast/Mappable$Mappable
Asciz	Mappable;
Asciz	scala/util/parsing/ast/Mappable$class;
class	scala/util/parsing/ast/Mappable$class
Asciz	java/lang/Object;
class	java/lang/Object

{
public static void $init$(scala.util.parsing.ast.Mappable);
  Signature: (Lscala/util/parsing/ast/Mappable;)V
  Code:
   Stack=0, Locals=1, Args_size=1
	return
  Labels:
  LocalVariableTable: 
   Start  Length  Slot  Name   Signature
   0      1      0    $this       Lscala/util/parsing/ast/Mappable;


public static scala.util.parsing.ast.Mappable$Mappable OptionIsMappable(scala.util.parsing.ast.Mappable, scala.Option, scala.Function1);
  Signature: (Lscala/util/parsing/ast/Mappable;Lscala/Option;Lscala/Function1;)Lscala/util/parsing/ast/Mappable$Mappable;
  Code:
   Stack=5, Locals=3, Args_size=3
	new	class scala/util/parsing/ast/Mappable$$anon$3
	dup
	aload_0
	aload_1
	aload_2
	invokespecial	Method scala/util/parsing/ast/Mappable$$anon$3."<init>":(Lscala/util/parsing/ast/Mappable;Lscala/Option;Lscala/Function1;)V
	areturn
  Labels:
  LocalVariableTable: 
   Start  Length  Slot  Name   Signature
   0      11      0    $this       Lscala/util/parsing/ast/Mappable;
   0      11      1    xs$1       Lscala/Option;
   0      11      2    evidence$4$1       Lscala/Function1;


public static scala.util.parsing.ast.Mappable$Mappable ListIsMappable(scala.util.parsing.ast.Mappable, scala.collection.immutable.List, scala.Function1);
  Signature: (Lscala/util/parsing/ast/Mappable;Lscala/collection/immutable/List;Lscala/Function1;)Lscala/util/parsing/ast/Mappable$Mappable;
  Code:
   Stack=5, Locals=3, Args_size=3
	new	class scala/util/parsing/ast/Mappable$$anon$2
	dup
	aload_0
	aload_1
	aload_2
	invokespecial	Method scala/util/parsing/ast/Mappable$$anon$2."<init>":(Lscala/util/parsing/ast/Mappable;Lscala/collection/immutable/List;Lscala/Function1;)V
	areturn
  Labels:
  LocalVariableTable: 
   Start  Length  Slot  Name   Signature
   0      11      0    $this       Lscala/util/parsing/ast/Mappable;
   0      11      1    xs$2       Lscala/collection/immutable/List;
   0      11      2    evidence$3$1       Lscala/Function1;


public static scala.util.parsing.ast.Mappable$Mappable StringIsMappable(scala.util.parsing.ast.Mappable, java.lang.String);
  Signature: (Lscala/util/parsing/ast/Mappable;Ljava/lang/String;)Lscala/util/parsing/ast/Mappable$Mappable;
  Code:
   Stack=4, Locals=2, Args_size=2
	new	class scala/util/parsing/ast/Mappable$$anon$1
	dup
	aload_0
	aload_1
	invokespecial	Method scala/util/parsing/ast/Mappable$$anon$1."<init>":(Lscala/util/parsing/ast/Mappable;Ljava/lang/String;)V
	areturn
  Labels:
  LocalVariableTable: 
   Start  Length  Slot  Name   Signature
   0      10      0    $this       Lscala/util/parsing/ast/Mappable;
   0      10      1    s$1       Ljava/lang/String;


}

