Compiled from "Binders.scala"
public abstract class scala.util.parsing.ast.Mappable$Mappable$class extends java.lang.Object
  SourceFile: "Binders.scala"
  Scala: length = 0x
   
  InnerClass: 
   public abstract #38= #25 of #37; //Mapper=class scala/util/parsing/ast/Mappable$Mapper of class scala/util/parsing/ast/Mappable
   public abstract #39= #19 of #37; //Mappable=class scala/util/parsing/ast/Mappable$Mappable of class scala/util/parsing/ast/Mappable
   public final #40= #13 of #19; //$anon$8=class scala/util/parsing/ast/Mappable$Mappable$$anon$8 of class scala/util/parsing/ast/Mappable$Mappable
  minor version: 0
  major version: 49
  Constant pool:
const #1 = Asciz	SourceFile;
const #2 = Asciz	Binders.scala;
const #3 = Asciz	$init$;
const #4 = Asciz	(Lscala/util/parsing/ast/Mappable$Mappable;)V;
const #5 = Asciz	Code;
const #6 = Asciz	LineNumberTable;
const #7 = Asciz	$this;
const #8 = Asciz	Lscala/util/parsing/ast/Mappable$Mappable;;
const #9 = Asciz	LocalVariableTable;
const #10 = Asciz	everywhere;
const #11 = Asciz	(Lscala/util/parsing/ast/Mappable$Mappable;Lscala/util/parsing/ast/Mappable$Mapper;Lscala/Function1;)Ljava/lang/Object;;
const #12 = Asciz	scala/util/parsing/ast/Mappable$Mappable$$anon$8;
const #13 = class	#12;	//  scala/util/parsing/ast/Mappable$Mappable$$anon$8
const #14 = Asciz	<init>;
const #15 = Asciz	(Lscala/util/parsing/ast/Mappable$Mappable;Lscala/util/parsing/ast/Mappable$Mapper;)V;
const #16 = NameAndType	#14:#15;//  "<init>":(Lscala/util/parsing/ast/Mappable$Mappable;Lscala/util/parsing/ast/Mappable$Mapper;)V
const #17 = Method	#13.#16;	//  scala/util/parsing/ast/Mappable$Mappable$$anon$8."<init>":(Lscala/util/parsing/ast/Mappable$Mappable;Lscala/util/parsing/ast/Mappable$Mapper;)V
const #18 = Asciz	scala/util/parsing/ast/Mappable$Mappable;
const #19 = class	#18;	//  scala/util/parsing/ast/Mappable$Mappable
const #20 = Asciz	gmap;
const #21 = Asciz	(Lscala/util/parsing/ast/Mappable$Mapper;)Ljava/lang/Object;;
const #22 = NameAndType	#20:#21;//  gmap:(Lscala/util/parsing/ast/Mappable$Mapper;)Ljava/lang/Object;
const #23 = InterfaceMethod	#19.#22;	//  scala/util/parsing/ast/Mappable$Mappable.gmap:(Lscala/util/parsing/ast/Mappable$Mapper;)Ljava/lang/Object;
const #24 = Asciz	scala/util/parsing/ast/Mappable$Mapper;
const #25 = class	#24;	//  scala/util/parsing/ast/Mappable$Mapper
const #26 = Asciz	apply;
const #27 = Asciz	(Ljava/lang/Object;Lscala/Function1;)Ljava/lang/Object;;
const #28 = NameAndType	#26:#27;//  apply:(Ljava/lang/Object;Lscala/Function1;)Ljava/lang/Object;
const #29 = InterfaceMethod	#25.#28;	//  scala/util/parsing/ast/Mappable$Mapper.apply:(Ljava/lang/Object;Lscala/Function1;)Ljava/lang/Object;
const #30 = Asciz	f$1;
const #31 = Asciz	Lscala/util/parsing/ast/Mappable$Mapper;;
const #32 = Asciz	c;
const #33 = Asciz	Lscala/Function1;;
const #34 = Asciz	Scala;
const #35 = Asciz	InnerClasses;
const #36 = Asciz	scala/util/parsing/ast/Mappable;
const #37 = class	#36;	//  scala/util/parsing/ast/Mappable
const #38 = Asciz	Mapper;
const #39 = Asciz	Mappable;
const #40 = Asciz	$anon$8;
const #41 = Asciz	scala/util/parsing/ast/Mappable$Mappable$class;
const #42 = class	#41;	//  scala/util/parsing/ast/Mappable$Mappable$class
const #43 = Asciz	java/lang/Object;
const #44 = class	#43;	//  java/lang/Object

{
public static void $init$(scala.util.parsing.ast.Mappable$Mappable);
  Code:
   Stack=0, Locals=1, Args_size=1
   0:	return
  LineNumberTable: 
   line 37: 0

  LocalVariableTable: 
   Start  Length  Slot  Name   Signature
   0      1      0    $this       Lscala/util/parsing/ast/Mappable$Mappable;


public static java.lang.Object everywhere(scala.util.parsing.ast.Mappable$Mappable, scala.util.parsing.ast.Mappable$Mapper, scala.Function1);
  Code:
   Stack=6, Locals=3, Args_size=3
   0:	aload_1
   1:	aload_0
   2:	new	#13; //class scala/util/parsing/ast/Mappable$Mappable$$anon$8
   5:	dup
   6:	aload_0
   7:	aload_1
   8:	invokespecial	#17; //Method scala/util/parsing/ast/Mappable$Mappable$$anon$8."<init>":(Lscala/util/parsing/ast/Mappable$Mappable;Lscala/util/parsing/ast/Mappable$Mapper;)V
   11:	invokeinterface	#23,  2; //InterfaceMethod scala/util/parsing/ast/Mappable$Mappable.gmap:(Lscala/util/parsing/ast/Mappable$Mapper;)Ljava/lang/Object;
   16:	aload_2
   17:	invokeinterface	#29,  3; //InterfaceMethod scala/util/parsing/ast/Mappable$Mapper.apply:(Ljava/lang/Object;Lscala/Function1;)Ljava/lang/Object;
   22:	areturn
  LineNumberTable: 
   line 42: 0

  LocalVariableTable: 
   Start  Length  Slot  Name   Signature
   0      23      0    $this       Lscala/util/parsing/ast/Mappable$Mappable;
   0      23      1    f$1       Lscala/util/parsing/ast/Mappable$Mapper;
   0      23      2    c       Lscala/Function1;


}

