Compiled from "Binders.scala"
public final class scala.util.parsing.ast.Mappable$$anon$1 extends java.lang.Object implements scala.util.parsing.ast.Mappable$Mappable
  SourceFile: "Binders.scala"
  Scala: length = 0x
   
  Signature: length = 0x2
   00 41 
  InnerClass: 
   public abstract Mapper=class scala/util/parsing/ast/Mappable$Mapper of class scala/util/parsing/ast/Mappable
   public final $anon$1=class scala/util/parsing/ast/Mappable$$anon$1 of class scala/util/parsing/ast/Mappable
   public abstract Mappable=class scala/util/parsing/ast/Mappable$Mappable of class scala/util/parsing/ast/Mappable
   public final $anonfun$gmap$1=class scala/util/parsing/ast/Mappable$$anon$1$$anonfun$gmap$1 of class scala/util/parsing/ast/Mappable$$anon$1
  minor version: 0
  major version: 49
  Constant pool:
Asciz	SourceFile;
Asciz	Binders.scala;
Asciz	$outer;
Asciz	Lscala/util/parsing/ast/Mappable;;
Asciz	s$1;
Asciz	Ljava/lang/String;;
Asciz	everywhere;
Asciz	(Lscala/util/parsing/ast/Mappable$Mapper;Lscala/Function1;)Ljava/lang/Object;;
Asciz	Code;
Asciz	LineNumberTable;
Asciz	scala/util/parsing/ast/Mappable$Mappable$class;
class	scala/util/parsing/ast/Mappable$Mappable$class
Asciz	(Lscala/util/parsing/ast/Mappable$Mappable;Lscala/util/parsing/ast/Mappable$Mapper;Lscala/Function1;)Ljava/lang/Object;;
NameAndType	everywhere:(Lscala/util/parsing/ast/Mappable$Mappable;Lscala/util/parsing/ast/Mappable$Mapper;Lscala/Function1;)Ljava/lang/Object;
Method	scala/util/parsing/ast/Mappable$Mappable$class.everywhere:(Lscala/util/parsing/ast/Mappable$Mappable;Lscala/util/parsing/ast/Mappable$Mapper;Lscala/Function1;)Ljava/lang/Object;
Asciz	this;
Asciz	Lscala/util/parsing/ast/Mappable$$anon$1;;
Asciz	f;
Asciz	Lscala/util/parsing/ast/Mappable$Mapper;;
Asciz	c;
Asciz	Lscala/Function1;;
Asciz	LocalVariableTable;
Asciz	gmap;
Asciz	(Lscala/util/parsing/ast/Mappable$Mapper;)Ljava/lang/String;;
Asciz	scala/util/parsing/ast/Mappable$$anon$1;
class	scala/util/parsing/ast/Mappable$$anon$1
NameAndType	s$1:Ljava/lang/String;
Field	scala/util/parsing/ast/Mappable$$anon$1.s$1:Ljava/lang/String;
Asciz	scala/util/parsing/ast/Mappable$$anon$1$$anonfun$gmap$1;
class	scala/util/parsing/ast/Mappable$$anon$1$$anonfun$gmap$1
Asciz	<init>;
Asciz	(Lscala/util/parsing/ast/Mappable$$anon$1;)V;
NameAndType	"<init>":(Lscala/util/parsing/ast/Mappable$$anon$1;)V
Method	scala/util/parsing/ast/Mappable$$anon$1$$anonfun$gmap$1."<init>":(Lscala/util/parsing/ast/Mappable$$anon$1;)V
Asciz	scala/util/parsing/ast/Mappable$Mapper;
class	scala/util/parsing/ast/Mappable$Mapper
Asciz	apply;
Asciz	(Ljava/lang/Object;Lscala/Function1;)Ljava/lang/Object;;
NameAndType	apply:(Ljava/lang/Object;Lscala/Function1;)Ljava/lang/Object;
InterfaceMethod	scala/util/parsing/ast/Mappable$Mapper.apply:(Ljava/lang/Object;Lscala/Function1;)Ljava/lang/Object;
Asciz	java/lang/String;
class	java/lang/String
Asciz	scala$util$parsing$ast$Mappable$$anon$$$outer;
Asciz	()Lscala/util/parsing/ast/Mappable;;
NameAndType	$outer:Lscala/util/parsing/ast/Mappable;
Field	scala/util/parsing/ast/Mappable$$anon$1.$outer:Lscala/util/parsing/ast/Mappable;
Asciz	scala$util$parsing$ast$Mappable$Mappable$$$outer;
Asciz	(Lscala/util/parsing/ast/Mappable$Mapper;)Ljava/lang/Object;;
NameAndType	gmap:(Lscala/util/parsing/ast/Mappable$Mapper;)Ljava/lang/String;
Method	scala/util/parsing/ast/Mappable$$anon$1.gmap:(Lscala/util/parsing/ast/Mappable$Mapper;)Ljava/lang/String;
Asciz	(Lscala/util/parsing/ast/Mappable;Ljava/lang/String;)V;
Asciz	java/lang/NullPointerException;
class	java/lang/NullPointerException
Asciz	()V;
NameAndType	"<init>":()V
Method	java/lang/NullPointerException."<init>":()V
Asciz	java/lang/Object;
class	java/lang/Object
Method	java/lang/Object."<init>":()V
Asciz	$init$;
Asciz	(Lscala/util/parsing/ast/Mappable$Mappable;)V;
NameAndType	$init$:(Lscala/util/parsing/ast/Mappable$Mappable;)V
Method	scala/util/parsing/ast/Mappable$Mappable$class.$init$:(Lscala/util/parsing/ast/Mappable$Mappable;)V
Asciz	Scala;
Asciz	Ljava/lang/Object;Lscala/util/parsing/ast/Mappable$Mappable<Ljava/lang/String;>;;
Asciz	Signature;
Asciz	InnerClasses;
Asciz	scala/util/parsing/ast/Mappable;
class	scala/util/parsing/ast/Mappable
Asciz	Mapper;
Asciz	$anon$1;
Asciz	scala/util/parsing/ast/Mappable$Mappable;
class	scala/util/parsing/ast/Mappable$Mappable
Asciz	Mappable;
Asciz	$anonfun$gmap$1;

{
public final scala.util.parsing.ast.Mappable $outer;
  Signature: Lscala/util/parsing/ast/Mappable;

public final java.lang.String s$1;
  Signature: Ljava/lang/String;

public java.lang.Object everywhere(scala.util.parsing.ast.Mappable$Mapper, scala.Function1);
  Signature: (Lscala/util/parsing/ast/Mappable$Mapper;Lscala/Function1;)Ljava/lang/Object;
  Code:
   Stack=3, Locals=3, Args_size=3
	aload_0
	aload_1
	aload_2
	invokestatic	Method scala/util/parsing/ast/Mappable$Mappable$class.everywhere:(Lscala/util/parsing/ast/Mappable$Mappable;Lscala/util/parsing/ast/Mappable$Mapper;Lscala/Function1;)Ljava/lang/Object;
	areturn
  Labels:
  LocalVariableTable: 
   Start  Length  Slot  Name   Signature
   0      7      0    this       Lscala/util/parsing/ast/Mappable$$anon$1;
   0      7      1    f       Lscala/util/parsing/ast/Mappable$Mapper;
   0      7      2    c       Lscala/Function1;


public java.lang.String gmap(scala.util.parsing.ast.Mappable$Mapper);
  Signature: (Lscala/util/parsing/ast/Mappable$Mapper;)Ljava/lang/String;
  Code:
   Stack=5, Locals=2, Args_size=2
	aload_1
	aload_0
	getfield	Field s$1:Ljava/lang/String;
	new	class scala/util/parsing/ast/Mappable$$anon$1$$anonfun$gmap$1
	dup
	aload_0
	invokespecial	Method scala/util/parsing/ast/Mappable$$anon$1$$anonfun$gmap$1."<init>":(Lscala/util/parsing/ast/Mappable$$anon$1;)V
	invokeinterface	InterfaceMethod scala/util/parsing/ast/Mappable$Mapper.apply:(Ljava/lang/Object;Lscala/Function1;)Ljava/lang/Object;
	checkcast	class java/lang/String
	areturn
  Labels:
  LocalVariableTable: 
   Start  Length  Slot  Name   Signature
   0      22      0    this       Lscala/util/parsing/ast/Mappable$$anon$1;
   0      22      1    f       Lscala/util/parsing/ast/Mappable$Mapper;


public scala.util.parsing.ast.Mappable scala$util$parsing$ast$Mappable$$anon$$$outer();
  Signature: ()Lscala/util/parsing/ast/Mappable;
  Code:
   Stack=1, Locals=1, Args_size=1
	aload_0
	getfield	Field $outer:Lscala/util/parsing/ast/Mappable;
	areturn
  Labels:

public scala.util.parsing.ast.Mappable scala$util$parsing$ast$Mappable$Mappable$$$outer();
  Signature: ()Lscala/util/parsing/ast/Mappable;
  Code:
   Stack=1, Locals=1, Args_size=1
	aload_0
	getfield	Field $outer:Lscala/util/parsing/ast/Mappable;
	areturn
  Labels:

public java.lang.Object gmap(scala.util.parsing.ast.Mappable$Mapper);
  Signature: (Lscala/util/parsing/ast/Mappable$Mapper;)Ljava/lang/Object;
  Code:
   Stack=2, Locals=2, Args_size=2
	aload_0
	aload_1
	invokevirtual	Method gmap:(Lscala/util/parsing/ast/Mappable$Mapper;)Ljava/lang/String;
	areturn
  Labels:
  LocalVariableTable: 
   Start  Length  Slot  Name   Signature
   0      6      0    this       Lscala/util/parsing/ast/Mappable$$anon$1;
   0      6      1    f       Lscala/util/parsing/ast/Mappable$Mapper;


public scala.util.parsing.ast.Mappable$$anon$1(scala.util.parsing.ast.Mappable, java.lang.String);
  Signature: (Lscala/util/parsing/ast/Mappable;Ljava/lang/String;)V
  Code:
   Stack=2, Locals=3, Args_size=3
	aload_1
	ifnonnull	l1 // aload_0
	new	class java/lang/NullPointerException
	dup
	invokespecial	Method java/lang/NullPointerException."<init>":()V
	athrow
l1	aload_0
	aload_1
	putfield	Field $outer:Lscala/util/parsing/ast/Mappable;
	aload_0
	aload_2
	putfield	Field s$1:Ljava/lang/String;
	aload_0
	invokespecial	Method java/lang/Object."<init>":()V
	aload_0
	invokestatic	Method scala/util/parsing/ast/Mappable$Mappable$class.$init$:(Lscala/util/parsing/ast/Mappable$Mappable;)V
	return
  Labels:
   	l1 = 12 // aload_0
  LocalVariableTable: 
   Start  Length  Slot  Name   Signature
   0      31      0    this       Lscala/util/parsing/ast/Mappable$$anon$1;
   0      31      1    $outer       Lscala/util/parsing/ast/Mappable;


}

