Compiled from "Binders.scala"
public final class scala.util.parsing.ast.Mappable$$anon$2 extends java.lang.Object implements scala.util.parsing.ast.Mappable$Mappable
  SourceFile: "Binders.scala"
  Signature: length = 0x2
   00 53 
  Scala: length = 0x
   
  InnerClass: 
   public abstract Mapper=class scala/util/parsing/ast/Mappable$Mapper of class scala/util/parsing/ast/Mappable
   public final $anon$2=class scala/util/parsing/ast/Mappable$$anon$2 of class scala/util/parsing/ast/Mappable
   public abstract Mappable=class scala/util/parsing/ast/Mappable$Mappable of class scala/util/parsing/ast/Mappable
   public final $anonfun$gmap$2=class scala/util/parsing/ast/Mappable$$anon$2$$anonfun$gmap$2 of class scala/util/parsing/ast/Mappable$$anon$2
  minor version: 0
  major version: 49
  Constant pool:
Asciz	SourceFile;
Asciz	Binders.scala;
Asciz	evidence$3$1;
Asciz	Lscala/Function1;;
Asciz	xs$2;
Asciz	Lscala/collection/immutable/List;;
Asciz	$outer;
Asciz	Lscala/util/parsing/ast/Mappable;;
Asciz	everywhere;
Asciz	(Lscala/util/parsing/ast/Mappable$Mapper;Lscala/Function1;)Ljava/lang/Object;;
Asciz	Code;
Asciz	LineNumberTable;
Asciz	scala/util/parsing/ast/Mappable$Mappable$class;
class	scala/util/parsing/ast/Mappable$Mappable$class
Asciz	(Lscala/util/parsing/ast/Mappable$Mappable;Lscala/util/parsing/ast/Mappable$Mapper;Lscala/Function1;)Ljava/lang/Object;;
NameAndType	everywhere:(Lscala/util/parsing/ast/Mappable$Mappable;Lscala/util/parsing/ast/Mappable$Mapper;Lscala/Function1;)Ljava/lang/Object;
Method	scala/util/parsing/ast/Mappable$Mappable$class.everywhere:(Lscala/util/parsing/ast/Mappable$Mappable;Lscala/util/parsing/ast/Mappable$Mapper;Lscala/Function1;)Ljava/lang/Object;
Asciz	this;
Asciz	Lscala/util/parsing/ast/Mappable$$anon$2;;
Asciz	f;
Asciz	Lscala/util/parsing/ast/Mappable$Mapper;;
Asciz	c;
Asciz	LocalVariableTable;
Asciz	gmap;
Asciz	(Lscala/util/parsing/ast/Mappable$Mapper;)Lscala/collection/immutable/List;;
Asciz	scala/util/parsing/ast/Mappable$$anon$2;
class	scala/util/parsing/ast/Mappable$$anon$2
NameAndType	xs$2:Lscala/collection/immutable/List;
Field	scala/util/parsing/ast/Mappable$$anon$2.xs$2:Lscala/collection/immutable/List;
Asciz	scala/util/parsing/ast/Mappable$$anon$2$$anonfun$gmap$2;
class	scala/util/parsing/ast/Mappable$$anon$2$$anonfun$gmap$2
Asciz	<init>;
Asciz	(Lscala/util/parsing/ast/Mappable$$anon$2;Lscala/util/parsing/ast/Mappable$Mapper;)V;
NameAndType	"<init>":(Lscala/util/parsing/ast/Mappable$$anon$2;Lscala/util/parsing/ast/Mappable$Mapper;)V
Method	scala/util/parsing/ast/Mappable$$anon$2$$anonfun$gmap$2."<init>":(Lscala/util/parsing/ast/Mappable$$anon$2;Lscala/util/parsing/ast/Mappable$Mapper;)V
Asciz	scala/collection/immutable/List$;
class	scala/collection/immutable/List$
Asciz	MODULE$;
Asciz	Lscala/collection/immutable/List$;;
NameAndType	MODULE$:Lscala/collection/immutable/List$;
Field	scala/collection/immutable/List$.MODULE$:Lscala/collection/immutable/List$;
Asciz	canBuildFrom;
Asciz	()Lscala/collection/generic/CanBuildFrom;;
NameAndType	canBuildFrom:()Lscala/collection/generic/CanBuildFrom;
Method	scala/collection/immutable/List$.canBuildFrom:()Lscala/collection/generic/CanBuildFrom;
Asciz	scala/collection/TraversableLike;
class	scala/collection/TraversableLike
Asciz	map;
Asciz	(Lscala/Function1;Lscala/collection/generic/CanBuildFrom;)Ljava/lang/Object;;
NameAndType	map:(Lscala/Function1;Lscala/collection/generic/CanBuildFrom;)Ljava/lang/Object;
InterfaceMethod	scala/collection/TraversableLike.map:(Lscala/Function1;Lscala/collection/generic/CanBuildFrom;)Ljava/lang/Object;
Asciz	scala/collection/immutable/List;
class	scala/collection/immutable/List
Asciz	toList;
Asciz	()Lscala/collection/immutable/List;;
NameAndType	toList:()Lscala/collection/immutable/List;
Method	scala/collection/immutable/List.toList:()Lscala/collection/immutable/List;
Asciz	f$2;
Asciz	(Lscala/util/parsing/ast/Mappable$Mapper;)Lscala/collection/immutable/List<Tt;>;;
Asciz	Signature;
Asciz	scala$util$parsing$ast$Mappable$Mappable$$$outer;
Asciz	()Lscala/util/parsing/ast/Mappable;;
NameAndType	$outer:Lscala/util/parsing/ast/Mappable;
Field	scala/util/parsing/ast/Mappable$$anon$2.$outer:Lscala/util/parsing/ast/Mappable;
Asciz	(Lscala/util/parsing/ast/Mappable$Mapper;)Ljava/lang/Object;;
NameAndType	gmap:(Lscala/util/parsing/ast/Mappable$Mapper;)Lscala/collection/immutable/List;
Method	scala/util/parsing/ast/Mappable$$anon$2.gmap:(Lscala/util/parsing/ast/Mappable$Mapper;)Lscala/collection/immutable/List;
Asciz	(Lscala/util/parsing/ast/Mappable;Lscala/collection/immutable/List;Lscala/Function1;)V;
Asciz	java/lang/NullPointerException;
class	java/lang/NullPointerException
Asciz	()V;
NameAndType	"<init>":()V
Method	java/lang/NullPointerException."<init>":()V
NameAndType	evidence$3$1:Lscala/Function1;
Field	scala/util/parsing/ast/Mappable$$anon$2.evidence$3$1:Lscala/Function1;
Asciz	java/lang/Object;
class	java/lang/Object
Method	java/lang/Object."<init>":()V
Asciz	$init$;
Asciz	(Lscala/util/parsing/ast/Mappable$Mappable;)V;
NameAndType	$init$:(Lscala/util/parsing/ast/Mappable$Mappable;)V
Method	scala/util/parsing/ast/Mappable$Mappable$class.$init$:(Lscala/util/parsing/ast/Mappable$Mappable;)V
Asciz	Ljava/lang/Object;Lscala/util/parsing/ast/Mappable$Mappable<Lscala/collection/immutable/List<Tt;>;>;;
Asciz	Scala;
Asciz	InnerClasses;
Asciz	scala/util/parsing/ast/Mappable$Mapper;
class	scala/util/parsing/ast/Mappable$Mapper
Asciz	scala/util/parsing/ast/Mappable;
class	scala/util/parsing/ast/Mappable
Asciz	Mapper;
Asciz	$anon$2;
Asciz	scala/util/parsing/ast/Mappable$Mappable;
class	scala/util/parsing/ast/Mappable$Mappable
Asciz	Mappable;
Asciz	$anonfun$gmap$2;

{
public final scala.Function1 evidence$3$1;
  Signature: Lscala/Function1;

public final scala.collection.immutable.List xs$2;
  Signature: Lscala/collection/immutable/List;

private final scala.util.parsing.ast.Mappable $outer;
  Signature: Lscala/util/parsing/ast/Mappable;

public java.lang.Object everywhere(scala.util.parsing.ast.Mappable$Mapper, scala.Function1);
  Signature: (Lscala/util/parsing/ast/Mappable$Mapper;Lscala/Function1;)Ljava/lang/Object;
  Code:
   Stack=3, Locals=3, Args_size=3
	aload_0
	aload_1
	aload_2
	invokestatic	Method scala/util/parsing/ast/Mappable$Mappable$class.everywhere:(Lscala/util/parsing/ast/Mappable$Mappable;Lscala/util/parsing/ast/Mappable$Mapper;Lscala/Function1;)Ljava/lang/Object;
	areturn
  Labels:
  LocalVariableTable: 
   Start  Length  Slot  Name   Signature
   0      7      0    this       Lscala/util/parsing/ast/Mappable$$anon$2;
   0      7      1    f       Lscala/util/parsing/ast/Mappable$Mapper;
   0      7      2    c       Lscala/Function1;


public scala.collection.immutable.List gmap(scala.util.parsing.ast.Mappable$Mapper);
  Signature: (Lscala/util/parsing/ast/Mappable$Mapper;)Lscala/collection/immutable/List;
  Code:
   Stack=5, Locals=2, Args_size=2
	aload_0
	getfield	Field xs$2:Lscala/collection/immutable/List;
	new	class scala/util/parsing/ast/Mappable$$anon$2$$anonfun$gmap$2
	dup
	aload_0
	aload_1
	invokespecial	Method scala/util/parsing/ast/Mappable$$anon$2$$anonfun$gmap$2."<init>":(Lscala/util/parsing/ast/Mappable$$anon$2;Lscala/util/parsing/ast/Mappable$Mapper;)V
	getstatic	Field scala/collection/immutable/List$.MODULE$:Lscala/collection/immutable/List$;
	invokevirtual	Method scala/collection/immutable/List$.canBuildFrom:()Lscala/collection/generic/CanBuildFrom;
	invokeinterface	InterfaceMethod scala/collection/TraversableLike.map:(Lscala/Function1;Lscala/collection/generic/CanBuildFrom;)Ljava/lang/Object;
	checkcast	class scala/collection/immutable/List
	invokevirtual	Method scala/collection/immutable/List.toList:()Lscala/collection/immutable/List;
	areturn
  Labels:
  LocalVariableTable: 
   Start  Length  Slot  Name   Signature
   0      31      0    this       Lscala/util/parsing/ast/Mappable$$anon$2;
   0      31      1    f$2       Lscala/util/parsing/ast/Mappable$Mapper;

  Signature: length = 0x2
   00 3B 

public scala.util.parsing.ast.Mappable scala$util$parsing$ast$Mappable$Mappable$$$outer();
  Signature: ()Lscala/util/parsing/ast/Mappable;
  Code:
   Stack=1, Locals=1, Args_size=1
	aload_0
	getfield	Field $outer:Lscala/util/parsing/ast/Mappable;
	areturn
  Labels:

public java.lang.Object gmap(scala.util.parsing.ast.Mappable$Mapper);
  Signature: (Lscala/util/parsing/ast/Mappable$Mapper;)Ljava/lang/Object;
  Code:
   Stack=2, Locals=2, Args_size=2
	aload_0
	aload_1
	invokevirtual	Method gmap:(Lscala/util/parsing/ast/Mappable$Mapper;)Lscala/collection/immutable/List;
	areturn
  Labels:
  LocalVariableTable: 
   Start  Length  Slot  Name   Signature
   0      6      0    this       Lscala/util/parsing/ast/Mappable$$anon$2;
   0      6      1    f       Lscala/util/parsing/ast/Mappable$Mapper;


public scala.util.parsing.ast.Mappable$$anon$2(scala.util.parsing.ast.Mappable, scala.collection.immutable.List, scala.Function1);
  Signature: (Lscala/util/parsing/ast/Mappable;Lscala/collection/immutable/List;Lscala/Function1;)V
  Code:
   Stack=2, Locals=4, Args_size=4
	aload_1
	ifnonnull	l1 // aload_0
	new	class java/lang/NullPointerException
	dup
	invokespecial	Method java/lang/NullPointerException."<init>":()V
	athrow
l1	aload_0
	aload_1
	putfield	Field $outer:Lscala/util/parsing/ast/Mappable;
	aload_0
	aload_2
	putfield	Field xs$2:Lscala/collection/immutable/List;
	aload_0
	aload_3
	putfield	Field evidence$3$1:Lscala/Function1;
	aload_0
	invokespecial	Method java/lang/Object."<init>":()V
	aload_0
	invokestatic	Method scala/util/parsing/ast/Mappable$Mappable$class.$init$:(Lscala/util/parsing/ast/Mappable$Mappable;)V
	return
  Labels:
   	l1 = 12 // aload_0
  LocalVariableTable: 
   Start  Length  Slot  Name   Signature
   0      36      0    this       Lscala/util/parsing/ast/Mappable$$anon$2;
   0      36      1    $outer       Lscala/util/parsing/ast/Mappable;


}

