Compiled from "Binders.scala"
public final class scala.util.parsing.ast.Mappable$Mappable$$anon$8 extends java.lang.Object implements scala.util.parsing.ast.Mappable$Mapper
  SourceFile: "Binders.scala"
  Scala: length = 0x
   
  InnerClass: 
   public abstract Mapper=class scala/util/parsing/ast/Mappable$Mapper of class scala/util/parsing/ast/Mappable
   public abstract Mappable=class scala/util/parsing/ast/Mappable$Mappable of class scala/util/parsing/ast/Mappable
   public final $anon$8=class scala/util/parsing/ast/Mappable$Mappable$$anon$8 of class scala/util/parsing/ast/Mappable$Mappable
  minor version: 0
  major version: 49
  Constant pool:
Asciz	SourceFile;
Asciz	Binders.scala;
Asciz	f$1;
Asciz	Lscala/util/parsing/ast/Mappable$Mapper;;
Asciz	apply;
Asciz	(Ljava/lang/Object;Lscala/Function1;)Ljava/lang/Object;;
Asciz	Code;
Asciz	LineNumberTable;
Asciz	scala/Function1;
class	scala/Function1
Asciz	(Ljava/lang/Object;)Ljava/lang/Object;;
NameAndType	apply:(Ljava/lang/Object;)Ljava/lang/Object;
InterfaceMethod	scala/Function1.apply:(Ljava/lang/Object;)Ljava/lang/Object;
Asciz	scala/util/parsing/ast/Mappable$Mappable;
class	scala/util/parsing/ast/Mappable$Mappable
Asciz	scala/util/parsing/ast/Mappable$Mappable$$anon$8;
class	scala/util/parsing/ast/Mappable$Mappable$$anon$8
NameAndType	f$1:Lscala/util/parsing/ast/Mappable$Mapper;
Field	scala/util/parsing/ast/Mappable$Mappable$$anon$8.f$1:Lscala/util/parsing/ast/Mappable$Mapper;
Asciz	everywhere;
Asciz	(Lscala/util/parsing/ast/Mappable$Mapper;Lscala/Function1;)Ljava/lang/Object;;
NameAndType	everywhere:(Lscala/util/parsing/ast/Mappable$Mapper;Lscala/Function1;)Ljava/lang/Object;
InterfaceMethod	scala/util/parsing/ast/Mappable$Mappable.everywhere:(Lscala/util/parsing/ast/Mappable$Mapper;Lscala/Function1;)Ljava/lang/Object;
Asciz	this;
Asciz	Lscala/util/parsing/ast/Mappable$Mappable$$anon$8;;
Asciz	x;
Asciz	Ljava/lang/Object;;
Asciz	evidence$2;
Asciz	Lscala/Function1;;
Asciz	LocalVariableTable;
Asciz	<T:Ljava/lang/Object;>(TT;Lscala/Function1<TT;Lscala/util/parsing/ast/Mappable$Mappable<TT;>;>;)TT;;
Asciz	Signature;
Asciz	<init>;
Asciz	(Lscala/util/parsing/ast/Mappable$Mappable;Lscala/util/parsing/ast/Mappable$Mapper;)V;
Asciz	java/lang/Object;
class	java/lang/Object
Asciz	()V;
NameAndType	"<init>":()V
Method	java/lang/Object."<init>":()V
Asciz	$outer;
Asciz	Lscala/util/parsing/ast/Mappable$Mappable;;
Asciz	(Lscala/util/parsing/ast/Mappable$Mappable<TT;>;)V;
Asciz	Scala;
Asciz	InnerClasses;
Asciz	scala/util/parsing/ast/Mappable$Mapper;
class	scala/util/parsing/ast/Mappable$Mapper
Asciz	scala/util/parsing/ast/Mappable;
class	scala/util/parsing/ast/Mappable
Asciz	Mapper;
Asciz	Mappable;
Asciz	$anon$8;

{
private final scala.util.parsing.ast.Mappable$Mapper f$1;
  Signature: Lscala/util/parsing/ast/Mappable$Mapper;

public java.lang.Object apply(java.lang.Object, scala.Function1);
  Signature: (Ljava/lang/Object;Lscala/Function1;)Ljava/lang/Object;
  Code:
   Stack=3, Locals=3, Args_size=3
	aload_2
	aload_1
	invokeinterface	InterfaceMethod scala/Function1.apply:(Ljava/lang/Object;)Ljava/lang/Object;
	checkcast	class scala/util/parsing/ast/Mappable$Mappable
	aload_0
	getfield	Field f$1:Lscala/util/parsing/ast/Mappable$Mapper;
	aload_2
	invokeinterface	InterfaceMethod scala/util/parsing/ast/Mappable$Mappable.everywhere:(Lscala/util/parsing/ast/Mappable$Mapper;Lscala/Function1;)Ljava/lang/Object;
	areturn
  Labels:
  LocalVariableTable: 
   Start  Length  Slot  Name   Signature
   0      21      0    this       Lscala/util/parsing/ast/Mappable$Mappable$$anon$8;
   0      21      1    x       Ljava/lang/Object;
   0      21      2    evidence$2       Lscala/Function1;

  Signature: length = 0x2
   00 1F 

public scala.util.parsing.ast.Mappable$Mappable$$anon$8(scala.util.parsing.ast.Mappable$Mappable, scala.util.parsing.ast.Mappable$Mapper);
  Signature: (Lscala/util/parsing/ast/Mappable$Mappable;Lscala/util/parsing/ast/Mappable$Mapper;)V
  Code:
   Stack=2, Locals=3, Args_size=3
	aload_0
	aload_2
	putfield	Field f$1:Lscala/util/parsing/ast/Mappable$Mapper;
	aload_0
	invokespecial	Method java/lang/Object."<init>":()V
	return
  Labels:
  LocalVariableTable: 
   Start  Length  Slot  Name   Signature
   0      10      0    this       Lscala/util/parsing/ast/Mappable$Mappable$$anon$8;
   0      10      1    $outer       Lscala/util/parsing/ast/Mappable$Mappable;

  Signature: length = 0x2
   00 2A 

}

