Compiled from "Lexical.scala"
public final class scala.util.parsing.combinator.lexical.Lexical$$anonfun$chrExcept$1 extends java.lang.Object implements scala.Function1,scala.ScalaObject,java.io.Serializable
  SourceFile: "Lexical.scala"
  Scala: length = 0x
   
  InnerClass: 
   public final #83= #9 of #82; //$anonfun$chrExcept$1=class scala/util/parsing/combinator/lexical/Lexical$$anonfun$chrExcept$1 of class scala/util/parsing/combinator/lexical/Lexical
   public final #84= #52 of #9; //$anonfun$apply$1=class scala/util/parsing/combinator/lexical/Lexical$$anonfun$chrExcept$1$$anonfun$apply$1 of class scala/util/parsing/combinator/lexical/Lexical$$anonfun$chrExcept$1
  minor version: 0
  major version: 49
  Constant pool:
const #1 = Asciz	SourceFile;
const #2 = Asciz	Lexical.scala;
const #3 = Asciz	<clinit>;
const #4 = Asciz	()V;
const #5 = Asciz	Code;
const #6 = Asciz	serialVersionUID;
const #7 = Asciz	J;
const #8 = Asciz	scala/util/parsing/combinator/lexical/Lexical$$anonfun$chrExcept$1;
const #9 = class	#8;	//  scala/util/parsing/combinator/lexical/Lexical$$anonfun$chrExcept$1
const #10 = NameAndType	#6:#7;//  serialVersionUID:J
const #11 = Field	#9.#10;	//  scala/util/parsing/combinator/lexical/Lexical$$anonfun$chrExcept$1.serialVersionUID:J
const #12 = Asciz	cs$1;
const #13 = Asciz	Lscala/collection/Seq;;
const #14 = Asciz	<init>;
const #15 = Asciz	(Lscala/util/parsing/combinator/lexical/Lexical;Lscala/collection/Seq;)V;
const #16 = Asciz	LineNumberTable;
const #17 = NameAndType	#12:#13;//  cs$1:Lscala/collection/Seq;
const #18 = Field	#9.#17;	//  scala/util/parsing/combinator/lexical/Lexical$$anonfun$chrExcept$1.cs$1:Lscala/collection/Seq;
const #19 = Asciz	java/lang/Object;
const #20 = class	#19;	//  java/lang/Object
const #21 = NameAndType	#14:#4;//  "<init>":()V
const #22 = Method	#20.#21;	//  java/lang/Object."<init>":()V
const #23 = Asciz	scala/Function1$class;
const #24 = class	#23;	//  scala/Function1$class
const #25 = Asciz	$init$;
const #26 = Asciz	(Lscala/Function1;)V;
const #27 = NameAndType	#25:#26;//  $init$:(Lscala/Function1;)V
const #28 = Method	#24.#27;	//  scala/Function1$class.$init$:(Lscala/Function1;)V
const #29 = Asciz	this;
const #30 = Asciz	Lscala/util/parsing/combinator/lexical/Lexical$$anonfun$chrExcept$1;;
const #31 = Asciz	$outer;
const #32 = Asciz	Lscala/util/parsing/combinator/lexical/Lexical;;
const #33 = Asciz	LocalVariableTable;
const #34 = Asciz	apply;
const #35 = Asciz	(Ljava/lang/Object;)Ljava/lang/Object;;
const #36 = Asciz	scala/runtime/BoxesRunTime;
const #37 = class	#36;	//  scala/runtime/BoxesRunTime
const #38 = Asciz	unboxToChar;
const #39 = Asciz	(Ljava/lang/Object;)C;
const #40 = NameAndType	#38:#39;//  unboxToChar:(Ljava/lang/Object;)C
const #41 = Method	#37.#40;	//  scala/runtime/BoxesRunTime.unboxToChar:(Ljava/lang/Object;)C
const #42 = Asciz	(C)Z;
const #43 = NameAndType	#34:#42;//  apply:(C)Z
const #44 = Method	#9.#43;	//  scala/util/parsing/combinator/lexical/Lexical$$anonfun$chrExcept$1.apply:(C)Z
const #45 = Asciz	boxToBoolean;
const #46 = Asciz	(Z)Ljava/lang/Boolean;;
const #47 = NameAndType	#45:#46;//  boxToBoolean:(Z)Ljava/lang/Boolean;
const #48 = Method	#37.#47;	//  scala/runtime/BoxesRunTime.boxToBoolean:(Z)Ljava/lang/Boolean;
const #49 = Asciz	v1;
const #50 = Asciz	Ljava/lang/Object;;
const #51 = Asciz	scala/util/parsing/combinator/lexical/Lexical$$anonfun$chrExcept$1$$anonfun$apply$1;
const #52 = class	#51;	//  scala/util/parsing/combinator/lexical/Lexical$$anonfun$chrExcept$1$$anonfun$apply$1
const #53 = Asciz	(Lscala/util/parsing/combinator/lexical/Lexical$$anonfun$chrExcept$1;C)V;
const #54 = NameAndType	#14:#53;//  "<init>":(Lscala/util/parsing/combinator/lexical/Lexical$$anonfun$chrExcept$1;C)V
const #55 = Method	#52.#54;	//  scala/util/parsing/combinator/lexical/Lexical$$anonfun$chrExcept$1$$anonfun$apply$1."<init>":(Lscala/util/parsing/combinator/lexical/Lexical$$anonfun$chrExcept$1;C)V
const #56 = Asciz	scala/collection/IterableLike;
const #57 = class	#56;	//  scala/collection/IterableLike
const #58 = Asciz	forall;
const #59 = Asciz	(Lscala/Function1;)Z;
const #60 = NameAndType	#58:#59;//  forall:(Lscala/Function1;)Z
const #61 = InterfaceMethod	#57.#60;	//  scala/collection/IterableLike.forall:(Lscala/Function1;)Z
const #62 = Asciz	ch$1;
const #63 = Asciz	C;
const #64 = Asciz	andThen;
const #65 = Asciz	(Lscala/Function1;)Lscala/Function1;;
const #66 = Asciz	(Lscala/Function1;Lscala/Function1;)Lscala/Function1;;
const #67 = NameAndType	#64:#66;//  andThen:(Lscala/Function1;Lscala/Function1;)Lscala/Function1;
const #68 = Method	#24.#67;	//  scala/Function1$class.andThen:(Lscala/Function1;Lscala/Function1;)Lscala/Function1;
const #69 = Asciz	g;
const #70 = Asciz	Lscala/Function1;;
const #71 = Asciz	compose;
const #72 = NameAndType	#71:#66;//  compose:(Lscala/Function1;Lscala/Function1;)Lscala/Function1;
const #73 = Method	#24.#72;	//  scala/Function1$class.compose:(Lscala/Function1;Lscala/Function1;)Lscala/Function1;
const #74 = Asciz	toString;
const #75 = Asciz	()Ljava/lang/String;;
const #76 = Asciz	(Lscala/Function1;)Ljava/lang/String;;
const #77 = NameAndType	#74:#76;//  toString:(Lscala/Function1;)Ljava/lang/String;
const #78 = Method	#24.#77;	//  scala/Function1$class.toString:(Lscala/Function1;)Ljava/lang/String;
const #79 = Asciz	Scala;
const #80 = Asciz	InnerClasses;
const #81 = Asciz	scala/util/parsing/combinator/lexical/Lexical;
const #82 = class	#81;	//  scala/util/parsing/combinator/lexical/Lexical
const #83 = Asciz	$anonfun$chrExcept$1;
const #84 = Asciz	$anonfun$apply$1;
const #85 = Asciz	scala/Function1;
const #86 = class	#85;	//  scala/Function1
const #87 = Asciz	scala/ScalaObject;
const #88 = class	#87;	//  scala/ScalaObject
const #89 = Asciz	java/io/Serializable;
const #90 = class	#89;	//  java/io/Serializable

{
public static final long serialVersionUID;

public static {};
  Code:
   Stack=2, Locals=0, Args_size=0
   0:	lconst_0
   1:	putstatic	#11; //Field serialVersionUID:J
   4:	return

public scala.util.parsing.combinator.lexical.Lexical$$anonfun$chrExcept$1(scala.util.parsing.combinator.lexical.Lexical, scala.collection.Seq);
  Code:
   Stack=2, Locals=3, Args_size=3
   0:	aload_0
   1:	aload_2
   2:	putfield	#18; //Field cs$1:Lscala/collection/Seq;
   5:	aload_0
   6:	invokespecial	#22; //Method java/lang/Object."<init>":()V
   9:	aload_0
   10:	invokestatic	#28; //Method scala/Function1$class.$init$:(Lscala/Function1;)V
   13:	return
  LineNumberTable: 
   line 38: 0

  LocalVariableTable: 
   Start  Length  Slot  Name   Signature
   0      14      0    this       Lscala/util/parsing/combinator/lexical/Lexical$$anonfun$chrExcept$1;
   0      14      1    $outer       Lscala/util/parsing/combinator/lexical/Lexical;


public final java.lang.Object apply(java.lang.Object);
  Code:
   Stack=2, Locals=3, Args_size=2
   0:	aload_0
   1:	aload_1
   2:	invokestatic	#41; //Method scala/runtime/BoxesRunTime.unboxToChar:(Ljava/lang/Object;)C
   5:	invokevirtual	#44; //Method apply:(C)Z
   8:	istore_2
   9:	iload_2
   10:	invokestatic	#48; //Method scala/runtime/BoxesRunTime.boxToBoolean:(Z)Ljava/lang/Boolean;
   13:	areturn
  LineNumberTable: 
   line 38: 0

  LocalVariableTable: 
   Start  Length  Slot  Name   Signature
   0      14      0    this       Lscala/util/parsing/combinator/lexical/Lexical$$anonfun$chrExcept$1;
   0      14      1    v1       Ljava/lang/Object;


public final boolean apply(char);
  Code:
   Stack=5, Locals=2, Args_size=2
   0:	aload_0
   1:	getfield	#18; //Field cs$1:Lscala/collection/Seq;
   4:	new	#52; //class scala/util/parsing/combinator/lexical/Lexical$$anonfun$chrExcept$1$$anonfun$apply$1
   7:	dup
   8:	aload_0
   9:	iload_1
   10:	invokespecial	#55; //Method scala/util/parsing/combinator/lexical/Lexical$$anonfun$chrExcept$1$$anonfun$apply$1."<init>":(Lscala/util/parsing/combinator/lexical/Lexical$$anonfun$chrExcept$1;C)V
   13:	invokeinterface	#61,  2; //InterfaceMethod scala/collection/IterableLike.forall:(Lscala/Function1;)Z
   18:	ireturn
  LineNumberTable: 
   line 38: 0

  LocalVariableTable: 
   Start  Length  Slot  Name   Signature
   0      19      0    this       Lscala/util/parsing/combinator/lexical/Lexical$$anonfun$chrExcept$1;
   0      19      1    ch$1       C


public scala.Function1 andThen(scala.Function1);
  Code:
   Stack=2, Locals=2, Args_size=2
   0:	aload_0
   1:	aload_1
   2:	invokestatic	#68; //Method scala/Function1$class.andThen:(Lscala/Function1;Lscala/Function1;)Lscala/Function1;
   5:	areturn
  LineNumberTable: 
   line 38: 0

  LocalVariableTable: 
   Start  Length  Slot  Name   Signature
   0      6      0    this       Lscala/util/parsing/combinator/lexical/Lexical$$anonfun$chrExcept$1;
   0      6      1    g       Lscala/Function1;


public scala.Function1 compose(scala.Function1);
  Code:
   Stack=2, Locals=2, Args_size=2
   0:	aload_0
   1:	aload_1
   2:	invokestatic	#73; //Method scala/Function1$class.compose:(Lscala/Function1;Lscala/Function1;)Lscala/Function1;
   5:	areturn
  LineNumberTable: 
   line 38: 0

  LocalVariableTable: 
   Start  Length  Slot  Name   Signature
   0      6      0    this       Lscala/util/parsing/combinator/lexical/Lexical$$anonfun$chrExcept$1;
   0      6      1    g       Lscala/Function1;


public java.lang.String toString();
  Code:
   Stack=1, Locals=1, Args_size=1
   0:	aload_0
   1:	invokestatic	#78; //Method scala/Function1$class.toString:(Lscala/Function1;)Ljava/lang/String;
   4:	areturn
  LineNumberTable: 
   line 38: 0


}

