Compiled from "Lexical.scala"
public abstract class scala.util.parsing.combinator.lexical.Lexical extends java.lang.Object implements scala.util.parsing.combinator.lexical.Scanners,scala.util.parsing.combinator.token.Tokens,scala.ScalaObject
  SourceFile: "Lexical.scala"
  ScalaSig: length = 0x3
   05 00 00 
  RuntimeVisibleAnnotations: length = 0xB
   00 01 01 24 00 01 01 25 73 01 26 
  InnerClass: 
   public abstract Token=class scala/util/parsing/combinator/token/Tokens$Token of class scala/util/parsing/combinator/token/Tokens
   public abstract Parser=class scala/util/parsing/combinator/Parsers$Parser of class scala/util/parsing/combinator/Parsers
   public abstract NoSuccess=class scala/util/parsing/combinator/Parsers$NoSuccess of class scala/util/parsing/combinator/Parsers
   public abstract OnceParser=class scala/util/parsing/combinator/Parsers$OnceParser of class scala/util/parsing/combinator/Parsers
   public final $anonfun$digit$1=class scala/util/parsing/combinator/lexical/Lexical$$anonfun$digit$1 of class scala/util/parsing/combinator/lexical/Lexical
   public final $anonfun$letter$1=class scala/util/parsing/combinator/lexical/Lexical$$anonfun$letter$1 of class scala/util/parsing/combinator/lexical/Lexical
   public final $anonfun$chrExcept$1=class scala/util/parsing/combinator/lexical/Lexical$$anonfun$chrExcept$1 of class scala/util/parsing/combinator/lexical/Lexical
   public final $anonfun$whitespaceChar$1=class scala/util/parsing/combinator/lexical/Lexical$$anonfun$whitespaceChar$1 of class scala/util/parsing/combinator/lexical/Lexical
  minor version: 0
  major version: 49
  Constant pool:
Asciz	SourceFile;
Asciz	Lexical.scala;
Asciz	lastNoSuccess;
Asciz	Lscala/util/parsing/combinator/Parsers$NoSuccess;;
Asciz	ErrorToken$module;
Asciz	Lscala/util/parsing/combinator/token/Tokens$ErrorToken$;;
Asciz	EOF$module;
Asciz	Lscala/util/parsing/combinator/token/Tokens$EOF$;;
Asciz	Success$module;
Asciz	Lscala/util/parsing/combinator/Parsers$Success$;;
Asciz	NoSuccess$module;
Asciz	Lscala/util/parsing/combinator/Parsers$NoSuccess$;;
Asciz	Failure$module;
Asciz	Lscala/util/parsing/combinator/Parsers$Failure$;;
Asciz	Error$module;
Asciz	Lscala/util/parsing/combinator/Parsers$Error$;;
Asciz	$tilde$module;
Asciz	Lscala/util/parsing/combinator/Parsers$$tilde$;;
Asciz	ErrorToken;
Asciz	()Lscala/util/parsing/combinator/token/Tokens$ErrorToken$;;
Asciz	Code;
Asciz	LineNumberTable;
Asciz	scala/util/parsing/combinator/lexical/Lexical;
class	scala/util/parsing/combinator/lexical/Lexical
NameAndType	ErrorToken$module:Lscala/util/parsing/combinator/token/Tokens$ErrorToken$;
Field	scala/util/parsing/combinator/lexical/Lexical.ErrorToken$module:Lscala/util/parsing/combinator/token/Tokens$ErrorToken$;
Asciz	scala/util/parsing/combinator/token/Tokens$ErrorToken$;
class	scala/util/parsing/combinator/token/Tokens$ErrorToken$
Asciz	<init>;
Asciz	(Lscala/util/parsing/combinator/token/Tokens;)V;
NameAndType	"<init>":(Lscala/util/parsing/combinator/token/Tokens;)V
Method	scala/util/parsing/combinator/token/Tokens$ErrorToken$."<init>":(Lscala/util/parsing/combinator/token/Tokens;)V
Asciz	EOF;
Asciz	()Lscala/util/parsing/combinator/token/Tokens$EOF$;;
NameAndType	EOF$module:Lscala/util/parsing/combinator/token/Tokens$EOF$;
Field	scala/util/parsing/combinator/lexical/Lexical.EOF$module:Lscala/util/parsing/combinator/token/Tokens$EOF$;
Asciz	scala/util/parsing/combinator/token/Tokens$EOF$;
class	scala/util/parsing/combinator/token/Tokens$EOF$
Method	scala/util/parsing/combinator/token/Tokens$EOF$."<init>":(Lscala/util/parsing/combinator/token/Tokens;)V
Asciz	errorToken;
Asciz	(Ljava/lang/String;)Lscala/util/parsing/combinator/token/Tokens$Token;;
Asciz	scala/util/parsing/combinator/token/Tokens$class;
class	scala/util/parsing/combinator/token/Tokens$class
Asciz	(Lscala/util/parsing/combinator/token/Tokens;Ljava/lang/String;)Lscala/util/parsing/combinator/token/Tokens$Token;;
NameAndType	errorToken:(Lscala/util/parsing/combinator/token/Tokens;Ljava/lang/String;)Lscala/util/parsing/combinator/token/Tokens$Token;
Method	scala/util/parsing/combinator/token/Tokens$class.errorToken:(Lscala/util/parsing/combinator/token/Tokens;Ljava/lang/String;)Lscala/util/parsing/combinator/token/Tokens$Token;
Asciz	this;
Asciz	Lscala/util/parsing/combinator/lexical/Lexical;;
Asciz	msg;
Asciz	Ljava/lang/String;;
Asciz	LocalVariableTable;
Asciz	Success;
Asciz	()Lscala/util/parsing/combinator/Parsers$Success$;;
NameAndType	Success$module:Lscala/util/parsing/combinator/Parsers$Success$;
Field	scala/util/parsing/combinator/lexical/Lexical.Success$module:Lscala/util/parsing/combinator/Parsers$Success$;
Asciz	scala/util/parsing/combinator/Parsers$Success$;
class	scala/util/parsing/combinator/Parsers$Success$
Asciz	(Lscala/util/parsing/combinator/Parsers;)V;
NameAndType	"<init>":(Lscala/util/parsing/combinator/Parsers;)V
Method	scala/util/parsing/combinator/Parsers$Success$."<init>":(Lscala/util/parsing/combinator/Parsers;)V
Asciz	()Lscala/util/parsing/combinator/Parsers$NoSuccess;;
NameAndType	lastNoSuccess:Lscala/util/parsing/combinator/Parsers$NoSuccess;
Field	scala/util/parsing/combinator/lexical/Lexical.lastNoSuccess:Lscala/util/parsing/combinator/Parsers$NoSuccess;
Asciz	lastNoSuccess_$eq;
Asciz	(Lscala/util/parsing/combinator/Parsers$NoSuccess;)V;
Asciz	NoSuccess;
Asciz	()Lscala/util/parsing/combinator/Parsers$NoSuccess$;;
NameAndType	NoSuccess$module:Lscala/util/parsing/combinator/Parsers$NoSuccess$;
Field	scala/util/parsing/combinator/lexical/Lexical.NoSuccess$module:Lscala/util/parsing/combinator/Parsers$NoSuccess$;
Asciz	scala/util/parsing/combinator/Parsers$NoSuccess$;
class	scala/util/parsing/combinator/Parsers$NoSuccess$
Method	scala/util/parsing/combinator/Parsers$NoSuccess$."<init>":(Lscala/util/parsing/combinator/Parsers;)V
Asciz	Failure;
Asciz	()Lscala/util/parsing/combinator/Parsers$Failure$;;
NameAndType	Failure$module:Lscala/util/parsing/combinator/Parsers$Failure$;
Field	scala/util/parsing/combinator/lexical/Lexical.Failure$module:Lscala/util/parsing/combinator/Parsers$Failure$;
Asciz	scala/util/parsing/combinator/Parsers$Failure$;
class	scala/util/parsing/combinator/Parsers$Failure$
Method	scala/util/parsing/combinator/Parsers$Failure$."<init>":(Lscala/util/parsing/combinator/Parsers;)V
Asciz	Error;
Asciz	()Lscala/util/parsing/combinator/Parsers$Error$;;
NameAndType	Error$module:Lscala/util/parsing/combinator/Parsers$Error$;
Field	scala/util/parsing/combinator/lexical/Lexical.Error$module:Lscala/util/parsing/combinator/Parsers$Error$;
Asciz	scala/util/parsing/combinator/Parsers$Error$;
class	scala/util/parsing/combinator/Parsers$Error$
Method	scala/util/parsing/combinator/Parsers$Error$."<init>":(Lscala/util/parsing/combinator/Parsers;)V
Asciz	$tilde;
Asciz	()Lscala/util/parsing/combinator/Parsers$$tilde$;;
NameAndType	$tilde$module:Lscala/util/parsing/combinator/Parsers$$tilde$;
Field	scala/util/parsing/combinator/lexical/Lexical.$tilde$module:Lscala/util/parsing/combinator/Parsers$$tilde$;
Asciz	scala/util/parsing/combinator/Parsers$$tilde$;
class	scala/util/parsing/combinator/Parsers$$tilde$
Method	scala/util/parsing/combinator/Parsers$$tilde$."<init>":(Lscala/util/parsing/combinator/Parsers;)V
Asciz	Parser;
Asciz	(Lscala/Function1;)Lscala/util/parsing/combinator/Parsers$Parser;;
Asciz	scala/util/parsing/combinator/Parsers$class;
class	scala/util/parsing/combinator/Parsers$class
Asciz	(Lscala/util/parsing/combinator/Parsers;Lscala/Function1;)Lscala/util/parsing/combinator/Parsers$Parser;;
NameAndType	Parser:(Lscala/util/parsing/combinator/Parsers;Lscala/Function1;)Lscala/util/parsing/combinator/Parsers$Parser;
Method	scala/util/parsing/combinator/Parsers$class.Parser:(Lscala/util/parsing/combinator/Parsers;Lscala/Function1;)Lscala/util/parsing/combinator/Parsers$Parser;
Asciz	f;
Asciz	Lscala/Function1;;
Asciz	OnceParser;
Asciz	(Lscala/Function1;)Lscala/util/parsing/combinator/Parsers$OnceParser;;
Asciz	(Lscala/util/parsing/combinator/Parsers;Lscala/Function1;)Lscala/util/parsing/combinator/Parsers$OnceParser;;
NameAndType	OnceParser:(Lscala/util/parsing/combinator/Parsers;Lscala/Function1;)Lscala/util/parsing/combinator/Parsers$OnceParser;
Method	scala/util/parsing/combinator/Parsers$class.OnceParser:(Lscala/util/parsing/combinator/Parsers;Lscala/Function1;)Lscala/util/parsing/combinator/Parsers$OnceParser;
Asciz	commit;
Asciz	(Lscala/Function0;)Lscala/util/parsing/combinator/Parsers$Parser;;
Asciz	(Lscala/util/parsing/combinator/Parsers;Lscala/Function0;)Lscala/util/parsing/combinator/Parsers$Parser;;
NameAndType	commit:(Lscala/util/parsing/combinator/Parsers;Lscala/Function0;)Lscala/util/parsing/combinator/Parsers$Parser;
Method	scala/util/parsing/combinator/Parsers$class.commit:(Lscala/util/parsing/combinator/Parsers;Lscala/Function0;)Lscala/util/parsing/combinator/Parsers$Parser;
Asciz	p;
Asciz	Lscala/Function0;;
Asciz	elem;
Asciz	(Ljava/lang/String;Lscala/Function1;)Lscala/util/parsing/combinator/Parsers$Parser;;
Asciz	(Lscala/util/parsing/combinator/Parsers;Ljava/lang/String;Lscala/Function1;)Lscala/util/parsing/combinator/Parsers$Parser;;
NameAndType	elem:(Lscala/util/parsing/combinator/Parsers;Ljava/lang/String;Lscala/Function1;)Lscala/util/parsing/combinator/Parsers$Parser;
Method	scala/util/parsing/combinator/Parsers$class.elem:(Lscala/util/parsing/combinator/Parsers;Ljava/lang/String;Lscala/Function1;)Lscala/util/parsing/combinator/Parsers$Parser;
Asciz	kind;
Asciz	(Ljava/lang/Object;)Lscala/util/parsing/combinator/Parsers$Parser;;
Asciz	(Lscala/util/parsing/combinator/Parsers;Ljava/lang/Object;)Lscala/util/parsing/combinator/Parsers$Parser;;
NameAndType	elem:(Lscala/util/parsing/combinator/Parsers;Ljava/lang/Object;)Lscala/util/parsing/combinator/Parsers$Parser;
Method	scala/util/parsing/combinator/Parsers$class.elem:(Lscala/util/parsing/combinator/Parsers;Ljava/lang/Object;)Lscala/util/parsing/combinator/Parsers$Parser;
Asciz	e;
Asciz	Ljava/lang/Object;;
Asciz	accept;
NameAndType	accept:(Lscala/util/parsing/combinator/Parsers;Ljava/lang/Object;)Lscala/util/parsing/combinator/Parsers$Parser;
Method	scala/util/parsing/combinator/Parsers$class.accept:(Lscala/util/parsing/combinator/Parsers;Ljava/lang/Object;)Lscala/util/parsing/combinator/Parsers$Parser;
Asciz	(Ljava/lang/Object;Lscala/Function1;)Lscala/util/parsing/combinator/Parsers$Parser;;
Asciz	(Lscala/util/parsing/combinator/Parsers;Ljava/lang/Object;Lscala/Function1;)Lscala/util/parsing/combinator/Parsers$Parser;;
NameAndType	accept:(Lscala/util/parsing/combinator/Parsers;Ljava/lang/Object;Lscala/Function1;)Lscala/util/parsing/combinator/Parsers$Parser;
Method	scala/util/parsing/combinator/Parsers$class.accept:(Lscala/util/parsing/combinator/Parsers;Ljava/lang/Object;Lscala/Function1;)Lscala/util/parsing/combinator/Parsers$Parser;
Asciz	es;
Asciz	evidence$1;
Asciz	(Ljava/lang/String;Lscala/PartialFunction;)Lscala/util/parsing/combinator/Parsers$Parser;;
Asciz	(Lscala/util/parsing/combinator/Parsers;Ljava/lang/String;Lscala/PartialFunction;)Lscala/util/parsing/combinator/Parsers$Parser;;
NameAndType	accept:(Lscala/util/parsing/combinator/Parsers;Ljava/lang/String;Lscala/PartialFunction;)Lscala/util/parsing/combinator/Parsers$Parser;
Method	scala/util/parsing/combinator/Parsers$class.accept:(Lscala/util/parsing/combinator/Parsers;Ljava/lang/String;Lscala/PartialFunction;)Lscala/util/parsing/combinator/Parsers$Parser;
Asciz	expected;
Asciz	Lscala/PartialFunction;;
Asciz	acceptIf;
Asciz	(Lscala/Function1;Lscala/Function1;)Lscala/util/parsing/combinator/Parsers$Parser;;
Asciz	(Lscala/util/parsing/combinator/Parsers;Lscala/Function1;Lscala/Function1;)Lscala/util/parsing/combinator/Parsers$Parser;;
NameAndType	acceptIf:(Lscala/util/parsing/combinator/Parsers;Lscala/Function1;Lscala/Function1;)Lscala/util/parsing/combinator/Parsers$Parser;
Method	scala/util/parsing/combinator/Parsers$class.acceptIf:(Lscala/util/parsing/combinator/Parsers;Lscala/Function1;Lscala/Function1;)Lscala/util/parsing/combinator/Parsers$Parser;
Asciz	err;
Asciz	acceptMatch;
NameAndType	acceptMatch:(Lscala/util/parsing/combinator/Parsers;Ljava/lang/String;Lscala/PartialFunction;)Lscala/util/parsing/combinator/Parsers$Parser;
Method	scala/util/parsing/combinator/Parsers$class.acceptMatch:(Lscala/util/parsing/combinator/Parsers;Ljava/lang/String;Lscala/PartialFunction;)Lscala/util/parsing/combinator/Parsers$Parser;
Asciz	acceptSeq;
NameAndType	acceptSeq:(Lscala/util/parsing/combinator/Parsers;Ljava/lang/Object;Lscala/Function1;)Lscala/util/parsing/combinator/Parsers$Parser;
Method	scala/util/parsing/combinator/Parsers$class.acceptSeq:(Lscala/util/parsing/combinator/Parsers;Ljava/lang/Object;Lscala/Function1;)Lscala/util/parsing/combinator/Parsers$Parser;
Asciz	evidence$2;
Asciz	failure;
Asciz	(Ljava/lang/String;)Lscala/util/parsing/combinator/Parsers$Parser;;
Asciz	(Lscala/util/parsing/combinator/Parsers;Ljava/lang/String;)Lscala/util/parsing/combinator/Parsers$Parser;;
NameAndType	failure:(Lscala/util/parsing/combinator/Parsers;Ljava/lang/String;)Lscala/util/parsing/combinator/Parsers$Parser;
Method	scala/util/parsing/combinator/Parsers$class.failure:(Lscala/util/parsing/combinator/Parsers;Ljava/lang/String;)Lscala/util/parsing/combinator/Parsers$Parser;
NameAndType	err:(Lscala/util/parsing/combinator/Parsers;Ljava/lang/String;)Lscala/util/parsing/combinator/Parsers$Parser;
Method	scala/util/parsing/combinator/Parsers$class.err:(Lscala/util/parsing/combinator/Parsers;Ljava/lang/String;)Lscala/util/parsing/combinator/Parsers$Parser;
Asciz	success;
NameAndType	success:(Lscala/util/parsing/combinator/Parsers;Ljava/lang/Object;)Lscala/util/parsing/combinator/Parsers$Parser;
Method	scala/util/parsing/combinator/Parsers$class.success:(Lscala/util/parsing/combinator/Parsers;Ljava/lang/Object;)Lscala/util/parsing/combinator/Parsers$Parser;
Asciz	v;
Asciz	log;
Asciz	(Lscala/Function0;Ljava/lang/String;)Lscala/util/parsing/combinator/Parsers$Parser;;
Asciz	(Lscala/util/parsing/combinator/Parsers;Lscala/Function0;Ljava/lang/String;)Lscala/util/parsing/combinator/Parsers$Parser;;
NameAndType	log:(Lscala/util/parsing/combinator/Parsers;Lscala/Function0;Ljava/lang/String;)Lscala/util/parsing/combinator/Parsers$Parser;
Method	scala/util/parsing/combinator/Parsers$class.log:(Lscala/util/parsing/combinator/Parsers;Lscala/Function0;Ljava/lang/String;)Lscala/util/parsing/combinator/Parsers$Parser;
Asciz	name;
Asciz	rep;
NameAndType	rep:(Lscala/util/parsing/combinator/Parsers;Lscala/Function0;)Lscala/util/parsing/combinator/Parsers$Parser;
Method	scala/util/parsing/combinator/Parsers$class.rep:(Lscala/util/parsing/combinator/Parsers;Lscala/Function0;)Lscala/util/parsing/combinator/Parsers$Parser;
Asciz	repsep;
Asciz	(Lscala/Function0;Lscala/Function0;)Lscala/util/parsing/combinator/Parsers$Parser;;
Asciz	(Lscala/util/parsing/combinator/Parsers;Lscala/Function0;Lscala/Function0;)Lscala/util/parsing/combinator/Parsers$Parser;;
NameAndType	repsep:(Lscala/util/parsing/combinator/Parsers;Lscala/Function0;Lscala/Function0;)Lscala/util/parsing/combinator/Parsers$Parser;
Method	scala/util/parsing/combinator/Parsers$class.repsep:(Lscala/util/parsing/combinator/Parsers;Lscala/Function0;Lscala/Function0;)Lscala/util/parsing/combinator/Parsers$Parser;
Asciz	q;
Asciz	rep1;
NameAndType	rep1:(Lscala/util/parsing/combinator/Parsers;Lscala/Function0;)Lscala/util/parsing/combinator/Parsers$Parser;
Method	scala/util/parsing/combinator/Parsers$class.rep1:(Lscala/util/parsing/combinator/Parsers;Lscala/Function0;)Lscala/util/parsing/combinator/Parsers$Parser;
NameAndType	rep1:(Lscala/util/parsing/combinator/Parsers;Lscala/Function0;Lscala/Function0;)Lscala/util/parsing/combinator/Parsers$Parser;
Method	scala/util/parsing/combinator/Parsers$class.rep1:(Lscala/util/parsing/combinator/Parsers;Lscala/Function0;Lscala/Function0;)Lscala/util/parsing/combinator/Parsers$Parser;
Asciz	first;
Asciz	repN;
Asciz	(ILscala/Function0;)Lscala/util/parsing/combinator/Parsers$Parser;;
Asciz	(Lscala/util/parsing/combinator/Parsers;ILscala/Function0;)Lscala/util/parsing/combinator/Parsers$Parser;;
NameAndType	repN:(Lscala/util/parsing/combinator/Parsers;ILscala/Function0;)Lscala/util/parsing/combinator/Parsers$Parser;
Method	scala/util/parsing/combinator/Parsers$class.repN:(Lscala/util/parsing/combinator/Parsers;ILscala/Function0;)Lscala/util/parsing/combinator/Parsers$Parser;
Asciz	num;
Asciz	I;
Asciz	rep1sep;
NameAndType	rep1sep:(Lscala/util/parsing/combinator/Parsers;Lscala/Function0;Lscala/Function0;)Lscala/util/parsing/combinator/Parsers$Parser;
Method	scala/util/parsing/combinator/Parsers$class.rep1sep:(Lscala/util/parsing/combinator/Parsers;Lscala/Function0;Lscala/Function0;)Lscala/util/parsing/combinator/Parsers$Parser;
Asciz	chainl1;
NameAndType	chainl1:(Lscala/util/parsing/combinator/Parsers;Lscala/Function0;Lscala/Function0;)Lscala/util/parsing/combinator/Parsers$Parser;
Method	scala/util/parsing/combinator/Parsers$class.chainl1:(Lscala/util/parsing/combinator/Parsers;Lscala/Function0;Lscala/Function0;)Lscala/util/parsing/combinator/Parsers$Parser;
Asciz	(Lscala/Function0;Lscala/Function0;Lscala/Function0;)Lscala/util/parsing/combinator/Parsers$Parser;;
Asciz	(Lscala/util/parsing/combinator/Parsers;Lscala/Function0;Lscala/Function0;Lscala/Function0;)Lscala/util/parsing/combinator/Parsers$Parser;;
NameAndType	chainl1:(Lscala/util/parsing/combinator/Parsers;Lscala/Function0;Lscala/Function0;Lscala/Function0;)Lscala/util/parsing/combinator/Parsers$Parser;
Method	scala/util/parsing/combinator/Parsers$class.chainl1:(Lscala/util/parsing/combinator/Parsers;Lscala/Function0;Lscala/Function0;Lscala/Function0;)Lscala/util/parsing/combinator/Parsers$Parser;
Asciz	chainr1;
Asciz	(Lscala/Function0;Lscala/Function0;Lscala/Function2;Ljava/lang/Object;)Lscala/util/parsing/combinator/Parsers$Parser;;
Asciz	(Lscala/util/parsing/combinator/Parsers;Lscala/Function0;Lscala/Function0;Lscala/Function2;Ljava/lang/Object;)Lscala/util/parsing/combinator/Parsers$Parser;;
NameAndType	chainr1:(Lscala/util/parsing/combinator/Parsers;Lscala/Function0;Lscala/Function0;Lscala/Function2;Ljava/lang/Object;)Lscala/util/parsing/combinator/Parsers$Parser;
Method	scala/util/parsing/combinator/Parsers$class.chainr1:(Lscala/util/parsing/combinator/Parsers;Lscala/Function0;Lscala/Function0;Lscala/Function2;Ljava/lang/Object;)Lscala/util/parsing/combinator/Parsers$Parser;
Asciz	combine;
Asciz	Lscala/Function2;;
Asciz	opt;
NameAndType	opt:(Lscala/util/parsing/combinator/Parsers;Lscala/Function0;)Lscala/util/parsing/combinator/Parsers$Parser;
Method	scala/util/parsing/combinator/Parsers$class.opt:(Lscala/util/parsing/combinator/Parsers;Lscala/Function0;)Lscala/util/parsing/combinator/Parsers$Parser;
Asciz	not;
NameAndType	not:(Lscala/util/parsing/combinator/Parsers;Lscala/Function0;)Lscala/util/parsing/combinator/Parsers$Parser;
Method	scala/util/parsing/combinator/Parsers$class.not:(Lscala/util/parsing/combinator/Parsers;Lscala/Function0;)Lscala/util/parsing/combinator/Parsers$Parser;
Asciz	guard;
NameAndType	guard:(Lscala/util/parsing/combinator/Parsers;Lscala/Function0;)Lscala/util/parsing/combinator/Parsers$Parser;
Method	scala/util/parsing/combinator/Parsers$class.guard:(Lscala/util/parsing/combinator/Parsers;Lscala/Function0;)Lscala/util/parsing/combinator/Parsers$Parser;
Asciz	positioned;
NameAndType	positioned:(Lscala/util/parsing/combinator/Parsers;Lscala/Function0;)Lscala/util/parsing/combinator/Parsers$Parser;
Method	scala/util/parsing/combinator/Parsers$class.positioned:(Lscala/util/parsing/combinator/Parsers;Lscala/Function0;)Lscala/util/parsing/combinator/Parsers$Parser;
Asciz	phrase;
Asciz	(Lscala/util/parsing/combinator/Parsers$Parser;)Lscala/util/parsing/combinator/Parsers$Parser;;
Asciz	(Lscala/util/parsing/combinator/Parsers;Lscala/util/parsing/combinator/Parsers$Parser;)Lscala/util/parsing/combinator/Parsers$Parser;;
NameAndType	phrase:(Lscala/util/parsing/combinator/Parsers;Lscala/util/parsing/combinator/Parsers$Parser;)Lscala/util/parsing/combinator/Parsers$Parser;
Method	scala/util/parsing/combinator/Parsers$class.phrase:(Lscala/util/parsing/combinator/Parsers;Lscala/util/parsing/combinator/Parsers$Parser;)Lscala/util/parsing/combinator/Parsers$Parser;
Asciz	Lscala/util/parsing/combinator/Parsers$Parser;;
Asciz	mkList;
Asciz	()Lscala/Function1;;
Asciz	(Lscala/util/parsing/combinator/Parsers;)Lscala/Function1;;
NameAndType	mkList:(Lscala/util/parsing/combinator/Parsers;)Lscala/Function1;
Method	scala/util/parsing/combinator/Parsers$class.mkList:(Lscala/util/parsing/combinator/Parsers;)Lscala/Function1;
Asciz	letter;
Asciz	()Lscala/util/parsing/combinator/Parsers$Parser;;
String	letter
Asciz	scala/util/parsing/combinator/lexical/Lexical$$anonfun$letter$1;
class	scala/util/parsing/combinator/lexical/Lexical$$anonfun$letter$1
Asciz	(Lscala/util/parsing/combinator/lexical/Lexical;)V;
NameAndType	"<init>":(Lscala/util/parsing/combinator/lexical/Lexical;)V
Method	scala/util/parsing/combinator/lexical/Lexical$$anonfun$letter$1."<init>":(Lscala/util/parsing/combinator/lexical/Lexical;)V
Asciz	scala/util/parsing/combinator/Parsers;
class	scala/util/parsing/combinator/Parsers
NameAndType	elem:(Ljava/lang/String;Lscala/Function1;)Lscala/util/parsing/combinator/Parsers$Parser;
InterfaceMethod	scala/util/parsing/combinator/Parsers.elem:(Ljava/lang/String;Lscala/Function1;)Lscala/util/parsing/combinator/Parsers$Parser;
Asciz	()Lscala/util/parsing/combinator/Parsers$Parser<Ljava/lang/Character;>;;
Asciz	Signature;
Asciz	digit;
String	digit
Asciz	scala/util/parsing/combinator/lexical/Lexical$$anonfun$digit$1;
class	scala/util/parsing/combinator/lexical/Lexical$$anonfun$digit$1
Method	scala/util/parsing/combinator/lexical/Lexical$$anonfun$digit$1."<init>":(Lscala/util/parsing/combinator/lexical/Lexical;)V
Asciz	chrExcept;
Asciz	(Lscala/collection/Seq;)Lscala/util/parsing/combinator/Parsers$Parser;;
Asciz	;
String	
Asciz	scala/util/parsing/combinator/lexical/Lexical$$anonfun$chrExcept$1;
class	scala/util/parsing/combinator/lexical/Lexical$$anonfun$chrExcept$1
Asciz	(Lscala/util/parsing/combinator/lexical/Lexical;Lscala/collection/Seq;)V;
NameAndType	"<init>":(Lscala/util/parsing/combinator/lexical/Lexical;Lscala/collection/Seq;)V
Method	scala/util/parsing/combinator/lexical/Lexical$$anonfun$chrExcept$1."<init>":(Lscala/util/parsing/combinator/lexical/Lexical;Lscala/collection/Seq;)V
Asciz	cs$1;
Asciz	Lscala/collection/Seq;;
Asciz	(Lscala/collection/Seq<Ljava/lang/Character;>;)Lscala/util/parsing/combinator/Parsers$Parser<Ljava/lang/Character;>;;
Asciz	whitespaceChar;
Asciz	space char;
String	space char
Asciz	scala/util/parsing/combinator/lexical/Lexical$$anonfun$whitespaceChar$1;
class	scala/util/parsing/combinator/lexical/Lexical$$anonfun$whitespaceChar$1
Method	scala/util/parsing/combinator/lexical/Lexical$$anonfun$whitespaceChar$1."<init>":(Lscala/util/parsing/combinator/lexical/Lexical;)V
Asciz	(Ljava/lang/String;)Ljava/lang/Object;;
Asciz	scala/util/parsing/combinator/token/Tokens;
class	scala/util/parsing/combinator/token/Tokens
NameAndType	errorToken:(Ljava/lang/String;)Lscala/util/parsing/combinator/token/Tokens$Token;
InterfaceMethod	scala/util/parsing/combinator/token/Tokens.errorToken:(Ljava/lang/String;)Lscala/util/parsing/combinator/token/Tokens$Token;
Asciz	()V;
Asciz	java/lang/Object;
class	java/lang/Object
NameAndType	"<init>":()V
Method	java/lang/Object."<init>":()V
Asciz	$init$;
NameAndType	$init$:(Lscala/util/parsing/combinator/Parsers;)V
Method	scala/util/parsing/combinator/Parsers$class.$init$:(Lscala/util/parsing/combinator/Parsers;)V
Asciz	scala/util/parsing/combinator/lexical/Scanners$class;
class	scala/util/parsing/combinator/lexical/Scanners$class
Asciz	(Lscala/util/parsing/combinator/lexical/Scanners;)V;
NameAndType	$init$:(Lscala/util/parsing/combinator/lexical/Scanners;)V
Method	scala/util/parsing/combinator/lexical/Scanners$class.$init$:(Lscala/util/parsing/combinator/lexical/Scanners;)V
NameAndType	$init$:(Lscala/util/parsing/combinator/token/Tokens;)V
Method	scala/util/parsing/combinator/token/Tokens$class.$init$:(Lscala/util/parsing/combinator/token/Tokens;)V
Asciz	ScalaSig;
Asciz	Lscala/reflect/ScalaSignature;;
Asciz	bytes;
Asciz	\r3\"\r\t!DnY1m\tA!AmKbL7-71AC2p[\nLg.;pe*qCa8/8h\tI!\"vi&d'\"AM\r\1M)AAAqF!)CEYtwMCQM^1\nU\"AB(cUG15\t!!\tA1kY1o]8=5\tAD\t)Ao\6f]&q)>\WM\:S\"\n\rR!aC*dC2wJ6fGRDQ!\n\naP5oSRtD#A]\"B\tQA7fiR,'/F,!\raS&M%af!8/:\nA\"!a)beN,'o\tYIJ!a\r\r\tcW-k!\tAKI&<o!\tO\nG\"X\t_2faR$\"aK\ti2A\rcA=}%QHyI,/Z1uKtCA@\t%BDQ\"\"\tQAD<iSR,7]1dKCM;
Asciz	RuntimeVisibleAnnotations;
Asciz	InnerClasses;
Asciz	scala/util/parsing/combinator/token/Tokens$Token;
class	scala/util/parsing/combinator/token/Tokens$Token
Asciz	Token;
Asciz	scala/util/parsing/combinator/Parsers$Parser;
class	scala/util/parsing/combinator/Parsers$Parser
Asciz	scala/util/parsing/combinator/Parsers$NoSuccess;
class	scala/util/parsing/combinator/Parsers$NoSuccess
Asciz	scala/util/parsing/combinator/Parsers$OnceParser;
class	scala/util/parsing/combinator/Parsers$OnceParser
Asciz	$anonfun$digit$1;
Asciz	$anonfun$letter$1;
Asciz	$anonfun$chrExcept$1;
Asciz	$anonfun$whitespaceChar$1;
Asciz	scala/util/parsing/combinator/lexical/Scanners;
class	scala/util/parsing/combinator/lexical/Scanners
Asciz	scala/ScalaObject;
class	scala/ScalaObject

{
private scala.util.parsing.combinator.Parsers$NoSuccess lastNoSuccess;
  Signature: Lscala/util/parsing/combinator/Parsers$NoSuccess;

private scala.util.parsing.combinator.token.Tokens$ErrorToken$ ErrorToken$module;
  Signature: Lscala/util/parsing/combinator/token/Tokens$ErrorToken$;

private scala.util.parsing.combinator.token.Tokens$EOF$ EOF$module;
  Signature: Lscala/util/parsing/combinator/token/Tokens$EOF$;

private scala.util.parsing.combinator.Parsers$Success$ Success$module;
  Signature: Lscala/util/parsing/combinator/Parsers$Success$;

private scala.util.parsing.combinator.Parsers$NoSuccess$ NoSuccess$module;
  Signature: Lscala/util/parsing/combinator/Parsers$NoSuccess$;

private scala.util.parsing.combinator.Parsers$Failure$ Failure$module;
  Signature: Lscala/util/parsing/combinator/Parsers$Failure$;

private scala.util.parsing.combinator.Parsers$Error$ Error$module;
  Signature: Lscala/util/parsing/combinator/Parsers$Error$;

private scala.util.parsing.combinator.Parsers$$tilde$ $tilde$module;
  Signature: Lscala/util/parsing/combinator/Parsers$$tilde$;

public final scala.util.parsing.combinator.token.Tokens$ErrorToken$ ErrorToken();
  Signature: ()Lscala/util/parsing/combinator/token/Tokens$ErrorToken$;
  Code:
   Stack=4, Locals=1, Args_size=1
	aload_0
	getfield	Field ErrorToken$module:Lscala/util/parsing/combinator/token/Tokens$ErrorToken$;
	ifnonnull	l1 // aload_0
	aload_0
	new	class scala/util/parsing/combinator/token/Tokens$ErrorToken$
	dup
	aload_0
	invokespecial	Method scala/util/parsing/combinator/token/Tokens$ErrorToken$."<init>":(Lscala/util/parsing/combinator/token/Tokens;)V
	putfield	Field ErrorToken$module:Lscala/util/parsing/combinator/token/Tokens$ErrorToken$;
l1	aload_0
	getfield	Field ErrorToken$module:Lscala/util/parsing/combinator/token/Tokens$ErrorToken$;
	areturn
  Labels:
   	l1 = 19 // aload_0

public final scala.util.parsing.combinator.token.Tokens$EOF$ EOF();
  Signature: ()Lscala/util/parsing/combinator/token/Tokens$EOF$;
  Code:
   Stack=4, Locals=1, Args_size=1
	aload_0
	getfield	Field EOF$module:Lscala/util/parsing/combinator/token/Tokens$EOF$;
	ifnonnull	l1 // aload_0
	aload_0
	new	class scala/util/parsing/combinator/token/Tokens$EOF$
	dup
	aload_0
	invokespecial	Method scala/util/parsing/combinator/token/Tokens$EOF$."<init>":(Lscala/util/parsing/combinator/token/Tokens;)V
	putfield	Field EOF$module:Lscala/util/parsing/combinator/token/Tokens$EOF$;
l1	aload_0
	getfield	Field EOF$module:Lscala/util/parsing/combinator/token/Tokens$EOF$;
	areturn
  Labels:
   	l1 = 19 // aload_0

public scala.util.parsing.combinator.token.Tokens$Token errorToken(java.lang.String);
  Signature: (Ljava/lang/String;)Lscala/util/parsing/combinator/token/Tokens$Token;
  Code:
   Stack=2, Locals=2, Args_size=2
	aload_0
	aload_1
	invokestatic	Method scala/util/parsing/combinator/token/Tokens$class.errorToken:(Lscala/util/parsing/combinator/token/Tokens;Ljava/lang/String;)Lscala/util/parsing/combinator/token/Tokens$Token;
	areturn
  Labels:
  LocalVariableTable: 
   Start  Length  Slot  Name   Signature
   0      6      0    this       Lscala/util/parsing/combinator/lexical/Lexical;
   0      6      1    msg       Ljava/lang/String;


public final scala.util.parsing.combinator.Parsers$Success$ Success();
  Signature: ()Lscala/util/parsing/combinator/Parsers$Success$;
  Code:
   Stack=4, Locals=1, Args_size=1
	aload_0
	getfield	Field Success$module:Lscala/util/parsing/combinator/Parsers$Success$;
	ifnonnull	l1 // aload_0
	aload_0
	new	class scala/util/parsing/combinator/Parsers$Success$
	dup
	aload_0
	invokespecial	Method scala/util/parsing/combinator/Parsers$Success$."<init>":(Lscala/util/parsing/combinator/Parsers;)V
	putfield	Field Success$module:Lscala/util/parsing/combinator/Parsers$Success$;
l1	aload_0
	getfield	Field Success$module:Lscala/util/parsing/combinator/Parsers$Success$;
	areturn
  Labels:
   	l1 = 19 // aload_0

public scala.util.parsing.combinator.Parsers$NoSuccess lastNoSuccess();
  Signature: ()Lscala/util/parsing/combinator/Parsers$NoSuccess;
  Code:
   Stack=1, Locals=1, Args_size=1
	aload_0
	getfield	Field lastNoSuccess:Lscala/util/parsing/combinator/Parsers$NoSuccess;
	areturn
  Labels:

public void lastNoSuccess_$eq(scala.util.parsing.combinator.Parsers$NoSuccess);
  Signature: (Lscala/util/parsing/combinator/Parsers$NoSuccess;)V
  Code:
   Stack=2, Locals=2, Args_size=2
	aload_0
	aload_1
	putfield	Field lastNoSuccess:Lscala/util/parsing/combinator/Parsers$NoSuccess;
	return
  Labels:

public final scala.util.parsing.combinator.Parsers$NoSuccess$ NoSuccess();
  Signature: ()Lscala/util/parsing/combinator/Parsers$NoSuccess$;
  Code:
   Stack=4, Locals=1, Args_size=1
	aload_0
	getfield	Field NoSuccess$module:Lscala/util/parsing/combinator/Parsers$NoSuccess$;
	ifnonnull	l1 // aload_0
	aload_0
	new	class scala/util/parsing/combinator/Parsers$NoSuccess$
	dup
	aload_0
	invokespecial	Method scala/util/parsing/combinator/Parsers$NoSuccess$."<init>":(Lscala/util/parsing/combinator/Parsers;)V
	putfield	Field NoSuccess$module:Lscala/util/parsing/combinator/Parsers$NoSuccess$;
l1	aload_0
	getfield	Field NoSuccess$module:Lscala/util/parsing/combinator/Parsers$NoSuccess$;
	areturn
  Labels:
   	l1 = 19 // aload_0

public final scala.util.parsing.combinator.Parsers$Failure$ Failure();
  Signature: ()Lscala/util/parsing/combinator/Parsers$Failure$;
  Code:
   Stack=4, Locals=1, Args_size=1
	aload_0
	getfield	Field Failure$module:Lscala/util/parsing/combinator/Parsers$Failure$;
	ifnonnull	l1 // aload_0
	aload_0
	new	class scala/util/parsing/combinator/Parsers$Failure$
	dup
	aload_0
	invokespecial	Method scala/util/parsing/combinator/Parsers$Failure$."<init>":(Lscala/util/parsing/combinator/Parsers;)V
	putfield	Field Failure$module:Lscala/util/parsing/combinator/Parsers$Failure$;
l1	aload_0
	getfield	Field Failure$module:Lscala/util/parsing/combinator/Parsers$Failure$;
	areturn
  Labels:
   	l1 = 19 // aload_0

public final scala.util.parsing.combinator.Parsers$Error$ Error();
  Signature: ()Lscala/util/parsing/combinator/Parsers$Error$;
  Code:
   Stack=4, Locals=1, Args_size=1
	aload_0
	getfield	Field Error$module:Lscala/util/parsing/combinator/Parsers$Error$;
	ifnonnull	l1 // aload_0
	aload_0
	new	class scala/util/parsing/combinator/Parsers$Error$
	dup
	aload_0
	invokespecial	Method scala/util/parsing/combinator/Parsers$Error$."<init>":(Lscala/util/parsing/combinator/Parsers;)V
	putfield	Field Error$module:Lscala/util/parsing/combinator/Parsers$Error$;
l1	aload_0
	getfield	Field Error$module:Lscala/util/parsing/combinator/Parsers$Error$;
	areturn
  Labels:
   	l1 = 19 // aload_0

public final scala.util.parsing.combinator.Parsers$$tilde$ $tilde();
  Signature: ()Lscala/util/parsing/combinator/Parsers$$tilde$;
  Code:
   Stack=4, Locals=1, Args_size=1
	aload_0
	getfield	Field $tilde$module:Lscala/util/parsing/combinator/Parsers$$tilde$;
	ifnonnull	l1 // aload_0
	aload_0
	new	class scala/util/parsing/combinator/Parsers$$tilde$
	dup
	aload_0
	invokespecial	Method scala/util/parsing/combinator/Parsers$$tilde$."<init>":(Lscala/util/parsing/combinator/Parsers;)V
	putfield	Field $tilde$module:Lscala/util/parsing/combinator/Parsers$$tilde$;
l1	aload_0
	getfield	Field $tilde$module:Lscala/util/parsing/combinator/Parsers$$tilde$;
	areturn
  Labels:
   	l1 = 19 // aload_0

public scala.util.parsing.combinator.Parsers$Parser Parser(scala.Function1);
  Signature: (Lscala/Function1;)Lscala/util/parsing/combinator/Parsers$Parser;
  Code:
   Stack=2, Locals=2, Args_size=2
	aload_0
	aload_1
	invokestatic	Method scala/util/parsing/combinator/Parsers$class.Parser:(Lscala/util/parsing/combinator/Parsers;Lscala/Function1;)Lscala/util/parsing/combinator/Parsers$Parser;
	areturn
  Labels:
  LocalVariableTable: 
   Start  Length  Slot  Name   Signature
   0      6      0    this       Lscala/util/parsing/combinator/lexical/Lexical;
   0      6      1    f       Lscala/Function1;


public scala.util.parsing.combinator.Parsers$OnceParser OnceParser(scala.Function1);
  Signature: (Lscala/Function1;)Lscala/util/parsing/combinator/Parsers$OnceParser;
  Code:
   Stack=2, Locals=2, Args_size=2
	aload_0
	aload_1
	invokestatic	Method scala/util/parsing/combinator/Parsers$class.OnceParser:(Lscala/util/parsing/combinator/Parsers;Lscala/Function1;)Lscala/util/parsing/combinator/Parsers$OnceParser;
	areturn
  Labels:
  LocalVariableTable: 
   Start  Length  Slot  Name   Signature
   0      6      0    this       Lscala/util/parsing/combinator/lexical/Lexical;
   0      6      1    f       Lscala/Function1;


public scala.util.parsing.combinator.Parsers$Parser commit(scala.Function0);
  Signature: (Lscala/Function0;)Lscala/util/parsing/combinator/Parsers$Parser;
  Code:
   Stack=2, Locals=2, Args_size=2
	aload_0
	aload_1
	invokestatic	Method scala/util/parsing/combinator/Parsers$class.commit:(Lscala/util/parsing/combinator/Parsers;Lscala/Function0;)Lscala/util/parsing/combinator/Parsers$Parser;
	areturn
  Labels:
  LocalVariableTable: 
   Start  Length  Slot  Name   Signature
   0      6      0    this       Lscala/util/parsing/combinator/lexical/Lexical;
   0      6      1    p       Lscala/Function0;


public scala.util.parsing.combinator.Parsers$Parser elem(java.lang.String, scala.Function1);
  Signature: (Ljava/lang/String;Lscala/Function1;)Lscala/util/parsing/combinator/Parsers$Parser;
  Code:
   Stack=3, Locals=3, Args_size=3
	aload_0
	aload_1
	aload_2
	invokestatic	Method scala/util/parsing/combinator/Parsers$class.elem:(Lscala/util/parsing/combinator/Parsers;Ljava/lang/String;Lscala/Function1;)Lscala/util/parsing/combinator/Parsers$Parser;
	areturn
  Labels:
  LocalVariableTable: 
   Start  Length  Slot  Name   Signature
   0      7      0    this       Lscala/util/parsing/combinator/lexical/Lexical;
   0      7      1    kind       Ljava/lang/String;
   0      7      2    p       Lscala/Function1;


public scala.util.parsing.combinator.Parsers$Parser elem(java.lang.Object);
  Signature: (Ljava/lang/Object;)Lscala/util/parsing/combinator/Parsers$Parser;
  Code:
   Stack=2, Locals=2, Args_size=2
	aload_0
	aload_1
	invokestatic	Method scala/util/parsing/combinator/Parsers$class.elem:(Lscala/util/parsing/combinator/Parsers;Ljava/lang/Object;)Lscala/util/parsing/combinator/Parsers$Parser;
	areturn
  Labels:
  LocalVariableTable: 
   Start  Length  Slot  Name   Signature
   0      6      0    this       Lscala/util/parsing/combinator/lexical/Lexical;
   0      6      1    e       Ljava/lang/Object;


public scala.util.parsing.combinator.Parsers$Parser accept(java.lang.Object);
  Signature: (Ljava/lang/Object;)Lscala/util/parsing/combinator/Parsers$Parser;
  Code:
   Stack=2, Locals=2, Args_size=2
	aload_0
	aload_1
	invokestatic	Method scala/util/parsing/combinator/Parsers$class.accept:(Lscala/util/parsing/combinator/Parsers;Ljava/lang/Object;)Lscala/util/parsing/combinator/Parsers$Parser;
	areturn
  Labels:
  LocalVariableTable: 
   Start  Length  Slot  Name   Signature
   0      6      0    this       Lscala/util/parsing/combinator/lexical/Lexical;
   0      6      1    e       Ljava/lang/Object;


public scala.util.parsing.combinator.Parsers$Parser accept(java.lang.Object, scala.Function1);
  Signature: (Ljava/lang/Object;Lscala/Function1;)Lscala/util/parsing/combinator/Parsers$Parser;
  Code:
   Stack=3, Locals=3, Args_size=3
	aload_0
	aload_1
	aload_2
	invokestatic	Method scala/util/parsing/combinator/Parsers$class.accept:(Lscala/util/parsing/combinator/Parsers;Ljava/lang/Object;Lscala/Function1;)Lscala/util/parsing/combinator/Parsers$Parser;
	areturn
  Labels:
  LocalVariableTable: 
   Start  Length  Slot  Name   Signature
   0      7      0    this       Lscala/util/parsing/combinator/lexical/Lexical;
   0      7      1    es       Ljava/lang/Object;
   0      7      2    evidence$1       Lscala/Function1;


public scala.util.parsing.combinator.Parsers$Parser accept(java.lang.String, scala.PartialFunction);
  Signature: (Ljava/lang/String;Lscala/PartialFunction;)Lscala/util/parsing/combinator/Parsers$Parser;
  Code:
   Stack=3, Locals=3, Args_size=3
	aload_0
	aload_1
	aload_2
	invokestatic	Method scala/util/parsing/combinator/Parsers$class.accept:(Lscala/util/parsing/combinator/Parsers;Ljava/lang/String;Lscala/PartialFunction;)Lscala/util/parsing/combinator/Parsers$Parser;
	areturn
  Labels:
  LocalVariableTable: 
   Start  Length  Slot  Name   Signature
   0      7      0    this       Lscala/util/parsing/combinator/lexical/Lexical;
   0      7      1    expected       Ljava/lang/String;
   0      7      2    f       Lscala/PartialFunction;


public scala.util.parsing.combinator.Parsers$Parser acceptIf(scala.Function1, scala.Function1);
  Signature: (Lscala/Function1;Lscala/Function1;)Lscala/util/parsing/combinator/Parsers$Parser;
  Code:
   Stack=3, Locals=3, Args_size=3
	aload_0
	aload_1
	aload_2
	invokestatic	Method scala/util/parsing/combinator/Parsers$class.acceptIf:(Lscala/util/parsing/combinator/Parsers;Lscala/Function1;Lscala/Function1;)Lscala/util/parsing/combinator/Parsers$Parser;
	areturn
  Labels:
  LocalVariableTable: 
   Start  Length  Slot  Name   Signature
   0      7      0    this       Lscala/util/parsing/combinator/lexical/Lexical;
   0      7      1    p       Lscala/Function1;
   0      7      2    err       Lscala/Function1;


public scala.util.parsing.combinator.Parsers$Parser acceptMatch(java.lang.String, scala.PartialFunction);
  Signature: (Ljava/lang/String;Lscala/PartialFunction;)Lscala/util/parsing/combinator/Parsers$Parser;
  Code:
   Stack=3, Locals=3, Args_size=3
	aload_0
	aload_1
	aload_2
	invokestatic	Method scala/util/parsing/combinator/Parsers$class.acceptMatch:(Lscala/util/parsing/combinator/Parsers;Ljava/lang/String;Lscala/PartialFunction;)Lscala/util/parsing/combinator/Parsers$Parser;
	areturn
  Labels:
  LocalVariableTable: 
   Start  Length  Slot  Name   Signature
   0      7      0    this       Lscala/util/parsing/combinator/lexical/Lexical;
   0      7      1    expected       Ljava/lang/String;
   0      7      2    f       Lscala/PartialFunction;


public scala.util.parsing.combinator.Parsers$Parser acceptSeq(java.lang.Object, scala.Function1);
  Signature: (Ljava/lang/Object;Lscala/Function1;)Lscala/util/parsing/combinator/Parsers$Parser;
  Code:
   Stack=3, Locals=3, Args_size=3
	aload_0
	aload_1
	aload_2
	invokestatic	Method scala/util/parsing/combinator/Parsers$class.acceptSeq:(Lscala/util/parsing/combinator/Parsers;Ljava/lang/Object;Lscala/Function1;)Lscala/util/parsing/combinator/Parsers$Parser;
	areturn
  Labels:
  LocalVariableTable: 
   Start  Length  Slot  Name   Signature
   0      7      0    this       Lscala/util/parsing/combinator/lexical/Lexical;
   0      7      1    es       Ljava/lang/Object;
   0      7      2    evidence$2       Lscala/Function1;


public scala.util.parsing.combinator.Parsers$Parser failure(java.lang.String);
  Signature: (Ljava/lang/String;)Lscala/util/parsing/combinator/Parsers$Parser;
  Code:
   Stack=2, Locals=2, Args_size=2
	aload_0
	aload_1
	invokestatic	Method scala/util/parsing/combinator/Parsers$class.failure:(Lscala/util/parsing/combinator/Parsers;Ljava/lang/String;)Lscala/util/parsing/combinator/Parsers$Parser;
	areturn
  Labels:
  LocalVariableTable: 
   Start  Length  Slot  Name   Signature
   0      6      0    this       Lscala/util/parsing/combinator/lexical/Lexical;
   0      6      1    msg       Ljava/lang/String;


public scala.util.parsing.combinator.Parsers$Parser err(java.lang.String);
  Signature: (Ljava/lang/String;)Lscala/util/parsing/combinator/Parsers$Parser;
  Code:
   Stack=2, Locals=2, Args_size=2
	aload_0
	aload_1
	invokestatic	Method scala/util/parsing/combinator/Parsers$class.err:(Lscala/util/parsing/combinator/Parsers;Ljava/lang/String;)Lscala/util/parsing/combinator/Parsers$Parser;
	areturn
  Labels:
  LocalVariableTable: 
   Start  Length  Slot  Name   Signature
   0      6      0    this       Lscala/util/parsing/combinator/lexical/Lexical;
   0      6      1    msg       Ljava/lang/String;


public scala.util.parsing.combinator.Parsers$Parser success(java.lang.Object);
  Signature: (Ljava/lang/Object;)Lscala/util/parsing/combinator/Parsers$Parser;
  Code:
   Stack=2, Locals=2, Args_size=2
	aload_0
	aload_1
	invokestatic	Method scala/util/parsing/combinator/Parsers$class.success:(Lscala/util/parsing/combinator/Parsers;Ljava/lang/Object;)Lscala/util/parsing/combinator/Parsers$Parser;
	areturn
  Labels:
  LocalVariableTable: 
   Start  Length  Slot  Name   Signature
   0      6      0    this       Lscala/util/parsing/combinator/lexical/Lexical;
   0      6      1    v       Ljava/lang/Object;


public scala.util.parsing.combinator.Parsers$Parser log(scala.Function0, java.lang.String);
  Signature: (Lscala/Function0;Ljava/lang/String;)Lscala/util/parsing/combinator/Parsers$Parser;
  Code:
   Stack=3, Locals=3, Args_size=3
	aload_0
	aload_1
	aload_2
	invokestatic	Method scala/util/parsing/combinator/Parsers$class.log:(Lscala/util/parsing/combinator/Parsers;Lscala/Function0;Ljava/lang/String;)Lscala/util/parsing/combinator/Parsers$Parser;
	areturn
  Labels:
  LocalVariableTable: 
   Start  Length  Slot  Name   Signature
   0      7      0    this       Lscala/util/parsing/combinator/lexical/Lexical;
   0      7      1    p       Lscala/Function0;
   0      7      2    name       Ljava/lang/String;


public scala.util.parsing.combinator.Parsers$Parser rep(scala.Function0);
  Signature: (Lscala/Function0;)Lscala/util/parsing/combinator/Parsers$Parser;
  Code:
   Stack=2, Locals=2, Args_size=2
	aload_0
	aload_1
	invokestatic	Method scala/util/parsing/combinator/Parsers$class.rep:(Lscala/util/parsing/combinator/Parsers;Lscala/Function0;)Lscala/util/parsing/combinator/Parsers$Parser;
	areturn
  Labels:
  LocalVariableTable: 
   Start  Length  Slot  Name   Signature
   0      6      0    this       Lscala/util/parsing/combinator/lexical/Lexical;
   0      6      1    p       Lscala/Function0;


public scala.util.parsing.combinator.Parsers$Parser repsep(scala.Function0, scala.Function0);
  Signature: (Lscala/Function0;Lscala/Function0;)Lscala/util/parsing/combinator/Parsers$Parser;
  Code:
   Stack=3, Locals=3, Args_size=3
	aload_0
	aload_1
	aload_2
	invokestatic	Method scala/util/parsing/combinator/Parsers$class.repsep:(Lscala/util/parsing/combinator/Parsers;Lscala/Function0;Lscala/Function0;)Lscala/util/parsing/combinator/Parsers$Parser;
	areturn
  Labels:
  LocalVariableTable: 
   Start  Length  Slot  Name   Signature
   0      7      0    this       Lscala/util/parsing/combinator/lexical/Lexical;
   0      7      1    p       Lscala/Function0;
   0      7      2    q       Lscala/Function0;


public scala.util.parsing.combinator.Parsers$Parser rep1(scala.Function0);
  Signature: (Lscala/Function0;)Lscala/util/parsing/combinator/Parsers$Parser;
  Code:
   Stack=2, Locals=2, Args_size=2
	aload_0
	aload_1
	invokestatic	Method scala/util/parsing/combinator/Parsers$class.rep1:(Lscala/util/parsing/combinator/Parsers;Lscala/Function0;)Lscala/util/parsing/combinator/Parsers$Parser;
	areturn
  Labels:
  LocalVariableTable: 
   Start  Length  Slot  Name   Signature
   0      6      0    this       Lscala/util/parsing/combinator/lexical/Lexical;
   0      6      1    p       Lscala/Function0;


public scala.util.parsing.combinator.Parsers$Parser rep1(scala.Function0, scala.Function0);
  Signature: (Lscala/Function0;Lscala/Function0;)Lscala/util/parsing/combinator/Parsers$Parser;
  Code:
   Stack=3, Locals=3, Args_size=3
	aload_0
	aload_1
	aload_2
	invokestatic	Method scala/util/parsing/combinator/Parsers$class.rep1:(Lscala/util/parsing/combinator/Parsers;Lscala/Function0;Lscala/Function0;)Lscala/util/parsing/combinator/Parsers$Parser;
	areturn
  Labels:
  LocalVariableTable: 
   Start  Length  Slot  Name   Signature
   0      7      0    this       Lscala/util/parsing/combinator/lexical/Lexical;
   0      7      1    first       Lscala/Function0;
   0      7      2    p       Lscala/Function0;


public scala.util.parsing.combinator.Parsers$Parser repN(int, scala.Function0);
  Signature: (ILscala/Function0;)Lscala/util/parsing/combinator/Parsers$Parser;
  Code:
   Stack=3, Locals=3, Args_size=3
	aload_0
	iload_1
	aload_2
	invokestatic	Method scala/util/parsing/combinator/Parsers$class.repN:(Lscala/util/parsing/combinator/Parsers;ILscala/Function0;)Lscala/util/parsing/combinator/Parsers$Parser;
	areturn
  Labels:
  LocalVariableTable: 
   Start  Length  Slot  Name   Signature
   0      7      0    this       Lscala/util/parsing/combinator/lexical/Lexical;
   0      7      1    num       I
   0      7      2    p       Lscala/Function0;


public scala.util.parsing.combinator.Parsers$Parser rep1sep(scala.Function0, scala.Function0);
  Signature: (Lscala/Function0;Lscala/Function0;)Lscala/util/parsing/combinator/Parsers$Parser;
  Code:
   Stack=3, Locals=3, Args_size=3
	aload_0
	aload_1
	aload_2
	invokestatic	Method scala/util/parsing/combinator/Parsers$class.rep1sep:(Lscala/util/parsing/combinator/Parsers;Lscala/Function0;Lscala/Function0;)Lscala/util/parsing/combinator/Parsers$Parser;
	areturn
  Labels:
  LocalVariableTable: 
   Start  Length  Slot  Name   Signature
   0      7      0    this       Lscala/util/parsing/combinator/lexical/Lexical;
   0      7      1    p       Lscala/Function0;
   0      7      2    q       Lscala/Function0;


public scala.util.parsing.combinator.Parsers$Parser chainl1(scala.Function0, scala.Function0);
  Signature: (Lscala/Function0;Lscala/Function0;)Lscala/util/parsing/combinator/Parsers$Parser;
  Code:
   Stack=3, Locals=3, Args_size=3
	aload_0
	aload_1
	aload_2
	invokestatic	Method scala/util/parsing/combinator/Parsers$class.chainl1:(Lscala/util/parsing/combinator/Parsers;Lscala/Function0;Lscala/Function0;)Lscala/util/parsing/combinator/Parsers$Parser;
	areturn
  Labels:
  LocalVariableTable: 
   Start  Length  Slot  Name   Signature
   0      7      0    this       Lscala/util/parsing/combinator/lexical/Lexical;
   0      7      1    p       Lscala/Function0;
   0      7      2    q       Lscala/Function0;


public scala.util.parsing.combinator.Parsers$Parser chainl1(scala.Function0, scala.Function0, scala.Function0);
  Signature: (Lscala/Function0;Lscala/Function0;Lscala/Function0;)Lscala/util/parsing/combinator/Parsers$Parser;
  Code:
   Stack=4, Locals=4, Args_size=4
	aload_0
	aload_1
	aload_2
	aload_3
	invokestatic	Method scala/util/parsing/combinator/Parsers$class.chainl1:(Lscala/util/parsing/combinator/Parsers;Lscala/Function0;Lscala/Function0;Lscala/Function0;)Lscala/util/parsing/combinator/Parsers$Parser;
	areturn
  Labels:
  LocalVariableTable: 
   Start  Length  Slot  Name   Signature
   0      8      0    this       Lscala/util/parsing/combinator/lexical/Lexical;
   0      8      1    first       Lscala/Function0;
   0      8      2    p       Lscala/Function0;
   0      8      3    q       Lscala/Function0;


public scala.util.parsing.combinator.Parsers$Parser chainr1(scala.Function0, scala.Function0, scala.Function2, java.lang.Object);
  Signature: (Lscala/Function0;Lscala/Function0;Lscala/Function2;Ljava/lang/Object;)Lscala/util/parsing/combinator/Parsers$Parser;
  Code:
   Stack=5, Locals=5, Args_size=5
	aload_0
	aload_1
	aload_2
	aload_3
	aload	4
	invokestatic	Method scala/util/parsing/combinator/Parsers$class.chainr1:(Lscala/util/parsing/combinator/Parsers;Lscala/Function0;Lscala/Function0;Lscala/Function2;Ljava/lang/Object;)Lscala/util/parsing/combinator/Parsers$Parser;
	areturn
  Labels:
  LocalVariableTable: 
   Start  Length  Slot  Name   Signature
   0      10      0    this       Lscala/util/parsing/combinator/lexical/Lexical;
   0      10      1    p       Lscala/Function0;
   0      10      2    q       Lscala/Function0;
   0      10      3    combine       Lscala/Function2;
   0      10      4    first       Ljava/lang/Object;


public scala.util.parsing.combinator.Parsers$Parser opt(scala.Function0);
  Signature: (Lscala/Function0;)Lscala/util/parsing/combinator/Parsers$Parser;
  Code:
   Stack=2, Locals=2, Args_size=2
	aload_0
	aload_1
	invokestatic	Method scala/util/parsing/combinator/Parsers$class.opt:(Lscala/util/parsing/combinator/Parsers;Lscala/Function0;)Lscala/util/parsing/combinator/Parsers$Parser;
	areturn
  Labels:
  LocalVariableTable: 
   Start  Length  Slot  Name   Signature
   0      6      0    this       Lscala/util/parsing/combinator/lexical/Lexical;
   0      6      1    p       Lscala/Function0;


public scala.util.parsing.combinator.Parsers$Parser not(scala.Function0);
  Signature: (Lscala/Function0;)Lscala/util/parsing/combinator/Parsers$Parser;
  Code:
   Stack=2, Locals=2, Args_size=2
	aload_0
	aload_1
	invokestatic	Method scala/util/parsing/combinator/Parsers$class.not:(Lscala/util/parsing/combinator/Parsers;Lscala/Function0;)Lscala/util/parsing/combinator/Parsers$Parser;
	areturn
  Labels:
  LocalVariableTable: 
   Start  Length  Slot  Name   Signature
   0      6      0    this       Lscala/util/parsing/combinator/lexical/Lexical;
   0      6      1    p       Lscala/Function0;


public scala.util.parsing.combinator.Parsers$Parser guard(scala.Function0);
  Signature: (Lscala/Function0;)Lscala/util/parsing/combinator/Parsers$Parser;
  Code:
   Stack=2, Locals=2, Args_size=2
	aload_0
	aload_1
	invokestatic	Method scala/util/parsing/combinator/Parsers$class.guard:(Lscala/util/parsing/combinator/Parsers;Lscala/Function0;)Lscala/util/parsing/combinator/Parsers$Parser;
	areturn
  Labels:
  LocalVariableTable: 
   Start  Length  Slot  Name   Signature
   0      6      0    this       Lscala/util/parsing/combinator/lexical/Lexical;
   0      6      1    p       Lscala/Function0;


public scala.util.parsing.combinator.Parsers$Parser positioned(scala.Function0);
  Signature: (Lscala/Function0;)Lscala/util/parsing/combinator/Parsers$Parser;
  Code:
   Stack=2, Locals=2, Args_size=2
	aload_0
	aload_1
	invokestatic	Method scala/util/parsing/combinator/Parsers$class.positioned:(Lscala/util/parsing/combinator/Parsers;Lscala/Function0;)Lscala/util/parsing/combinator/Parsers$Parser;
	areturn
  Labels:
  LocalVariableTable: 
   Start  Length  Slot  Name   Signature
   0      6      0    this       Lscala/util/parsing/combinator/lexical/Lexical;
   0      6      1    p       Lscala/Function0;


public scala.util.parsing.combinator.Parsers$Parser phrase(scala.util.parsing.combinator.Parsers$Parser);
  Signature: (Lscala/util/parsing/combinator/Parsers$Parser;)Lscala/util/parsing/combinator/Parsers$Parser;
  Code:
   Stack=2, Locals=2, Args_size=2
	aload_0
	aload_1
	invokestatic	Method scala/util/parsing/combinator/Parsers$class.phrase:(Lscala/util/parsing/combinator/Parsers;Lscala/util/parsing/combinator/Parsers$Parser;)Lscala/util/parsing/combinator/Parsers$Parser;
	areturn
  Labels:
  LocalVariableTable: 
   Start  Length  Slot  Name   Signature
   0      6      0    this       Lscala/util/parsing/combinator/lexical/Lexical;
   0      6      1    p       Lscala/util/parsing/combinator/Parsers$Parser;


public scala.Function1 mkList();
  Signature: ()Lscala/Function1;
  Code:
   Stack=1, Locals=1, Args_size=1
	aload_0
	invokestatic	Method scala/util/parsing/combinator/Parsers$class.mkList:(Lscala/util/parsing/combinator/Parsers;)Lscala/Function1;
	areturn
  Labels:

public scala.util.parsing.combinator.Parsers$Parser letter();
  Signature: ()Lscala/util/parsing/combinator/Parsers$Parser;
  Code:
   Stack=5, Locals=1, Args_size=1
	aload_0
	ldc	String letter
	new	class scala/util/parsing/combinator/lexical/Lexical$$anonfun$letter$1
	dup
	aload_0
	invokespecial	Method scala/util/parsing/combinator/lexical/Lexical$$anonfun$letter$1."<init>":(Lscala/util/parsing/combinator/lexical/Lexical;)V
	invokeinterface	InterfaceMethod scala/util/parsing/combinator/Parsers.elem:(Ljava/lang/String;Lscala/Function1;)Lscala/util/parsing/combinator/Parsers$Parser;
	areturn
  Labels:
  Signature: length = 0x2
   00 FFFFFFF6 

public scala.util.parsing.combinator.Parsers$Parser digit();
  Signature: ()Lscala/util/parsing/combinator/Parsers$Parser;
  Code:
   Stack=5, Locals=1, Args_size=1
	aload_0
	ldc	String digit
	new	class scala/util/parsing/combinator/lexical/Lexical$$anonfun$digit$1
	dup
	aload_0
	invokespecial	Method scala/util/parsing/combinator/lexical/Lexical$$anonfun$digit$1."<init>":(Lscala/util/parsing/combinator/lexical/Lexical;)V
	invokeinterface	InterfaceMethod scala/util/parsing/combinator/Parsers.elem:(Ljava/lang/String;Lscala/Function1;)Lscala/util/parsing/combinator/Parsers$Parser;
	areturn
  Labels:
  Signature: length = 0x2
   00 FFFFFFF6 

public scala.util.parsing.combinator.Parsers$Parser chrExcept(scala.collection.Seq);
  Signature: (Lscala/collection/Seq;)Lscala/util/parsing/combinator/Parsers$Parser;
  Code:
   Stack=6, Locals=2, Args_size=2
	aload_0
	ldc_w	String 
	new	class scala/util/parsing/combinator/lexical/Lexical$$anonfun$chrExcept$1
	dup
	aload_0
	aload_1
	invokespecial	Method scala/util/parsing/combinator/lexical/Lexical$$anonfun$chrExcept$1."<init>":(Lscala/util/parsing/combinator/lexical/Lexical;Lscala/collection/Seq;)V
	invokeinterface	InterfaceMethod scala/util/parsing/combinator/Parsers.elem:(Ljava/lang/String;Lscala/Function1;)Lscala/util/parsing/combinator/Parsers$Parser;
	areturn
  Labels:
  LocalVariableTable: 
   Start  Length  Slot  Name   Signature
   0      19      0    this       Lscala/util/parsing/combinator/lexical/Lexical;
   0      19      1    cs$1       Lscala/collection/Seq;

  Signature: length = 0x2
   01 08 

public scala.util.parsing.combinator.Parsers$Parser whitespaceChar();
  Signature: ()Lscala/util/parsing/combinator/Parsers$Parser;
  Code:
   Stack=5, Locals=1, Args_size=1
	aload_0
	ldc_w	String space char
	new	class scala/util/parsing/combinator/lexical/Lexical$$anonfun$whitespaceChar$1
	dup
	aload_0
	invokespecial	Method scala/util/parsing/combinator/lexical/Lexical$$anonfun$whitespaceChar$1."<init>":(Lscala/util/parsing/combinator/lexical/Lexical;)V
	invokeinterface	InterfaceMethod scala/util/parsing/combinator/Parsers.elem:(Ljava/lang/String;Lscala/Function1;)Lscala/util/parsing/combinator/Parsers$Parser;
	areturn
  Labels:
  Signature: length = 0x2
   00 FFFFFFF6 

public java.lang.Object errorToken(java.lang.String);
  Signature: (Ljava/lang/String;)Ljava/lang/Object;
  Code:
   Stack=2, Locals=2, Args_size=2
	aload_0
	aload_1
	invokeinterface	InterfaceMethod scala/util/parsing/combinator/token/Tokens.errorToken:(Ljava/lang/String;)Lscala/util/parsing/combinator/token/Tokens$Token;
	areturn
  Labels:
  LocalVariableTable: 
   Start  Length  Slot  Name   Signature
   0      8      0    this       Lscala/util/parsing/combinator/lexical/Lexical;
   0      8      1    msg       Ljava/lang/String;


public scala.util.parsing.combinator.lexical.Lexical();
  Signature: ()V
  Code:
   Stack=1, Locals=1, Args_size=1
	aload_0
	invokespecial	Method java/lang/Object."<init>":()V
	aload_0
	invokestatic	Method scala/util/parsing/combinator/Parsers$class.$init$:(Lscala/util/parsing/combinator/Parsers;)V
	aload_0
	invokestatic	Method scala/util/parsing/combinator/lexical/Scanners$class.$init$:(Lscala/util/parsing/combinator/lexical/Scanners;)V
	aload_0
	invokestatic	Method scala/util/parsing/combinator/token/Tokens$class.$init$:(Lscala/util/parsing/combinator/token/Tokens;)V
	return
  Labels:

}

