Compiled from "Lexical.scala"
public abstract class scala.util.parsing.combinator.lexical.Lexical extends java.lang.Object implements scala.util.parsing.combinator.lexical.Scanners,scala.util.parsing.syntax.Tokens,scala.ScalaObject
  SourceFile: "Lexical.scala"
  ScalaSig: length = 0x18F
   05 00 43 06 08 01 02 FFFFFF84 FFFFFF80 FFFFFF80 FFFFFF81 00 0D 02 07 4C
   65 78 69 63 61 6C 0A 02 03 04 01 07 6C 65 78 69
   63 61 6C 0A 02 05 06 01 0A 63 6F 6D 62 69 6E 61
   74 6F 72 0A 02 07 08 01 07 70 61 72 73 69 6E 67
   0A 02 09 0A 01 04 75 74 69 6C 0A 01 0B 01 05 73
   63 61 6C 61 03 00 13 05 00 0E 16 1A 20 10 02 0F
   14 0D 01 10 0A 02 11 12 01 04 6C 61 6E 67 0A 01
   13 01 04 6A 61 76 61 09 02 15 10 02 06 4F 62 6A
   65 63 74 10 02 17 18 0D 01 02 09 02 19 02 02 08
   53 63 61 6E 6E 65 72 73 10 02 1B 1E 0D 01 1C 0A
   02 1D 06 01 06 73 79 6E 74 61 78 09 02 1F 1C 02
   06 54 6F 6B 65 6E 73 10 02 21 22 0D 01 0A 09 02
   23 0A 02 0B 53 63 61 6C 61 4F 62 6A 65 63 74 08
   05 25 00 FFFFFF84 00 26 01 06 3C 69 6E 69 74 3E 14 01
   27 10 02 17 00 08 05 29 00 FFFFFF84 00 2A 01 06 6C 65
   74 74 65 72 15 01 2B 10 03 2C 2D 31 0D 01 00 09
   02 2E 2F 02 06 50 61 72 73 65 72 09 02 30 04 02
   07 50 61 72 73 65 72 73 10 02 2C 32 09 02 33 18
   02 04 45 6C 65 6D 08 05 35 00 FFFFFF84 00 2A 01 05 64
   69 67 69 74 08 05 37 00 FFFFFF84 00 38 01 09 63 68 72
   45 78 63 65 70 74 14 02 2B 39 08 05 3A 36 FFFFFFC0 00
   3B 01 02 63 73 10 03 21 3C 3E 09 02 3D 0A 02 0A
   3C 72 65 70 65 61 74 65 64 3E 10 02 21 3F 09 02
   40 0A 02 04 43 68 61 72 08 05 42 00 FFFFFF84 00 2A 01
   0E 77 68 69 74 65 73 70 61 63 65 43 68 61 72 
  InnerClass: 
   public abstract #293= #292 of #46; //Token=class scala/util/parsing/syntax/Tokens$Token of class scala/util/parsing/syntax/Tokens
   public abstract #225= #295 of #65; //Parser=class scala/util/parsing/combinator/Parsers$Parser of class scala/util/parsing/combinator/Parsers
   public abstract #252= #297 of #65; //NoSuccess=class scala/util/parsing/combinator/Parsers$NoSuccess of class scala/util/parsing/combinator/Parsers
   public final #298= #87 of #231; //$anonfun$digit$1=class scala/util/parsing/combinator/lexical/Lexical$$anonfun$digit$1 of class scala/util/parsing/combinator/lexical/Lexical
   public final #299= #92 of #231; //$anonfun$letter$1=class scala/util/parsing/combinator/lexical/Lexical$$anonfun$letter$1 of class scala/util/parsing/combinator/lexical/Lexical
   public final #300= #77 of #231; //$anonfun$chrExcept$1=class scala/util/parsing/combinator/lexical/Lexical$$anonfun$chrExcept$1 of class scala/util/parsing/combinator/lexical/Lexical
   public final #301= #60 of #231; //$anonfun$whitespaceChar$1=class scala/util/parsing/combinator/lexical/Lexical$$anonfun$whitespaceChar$1 of class scala/util/parsing/combinator/lexical/Lexical
  minor version: 0
  major version: 49
  Constant pool:
const #1 = Asciz	SourceFile;
const #2 = Asciz	Lexical.scala;
const #3 = Asciz	$tilde$module;
const #4 = Asciz	Lscala/util/parsing/combinator/Parsers$$tilde$;;
const #5 = Asciz	Error$module;
const #6 = Asciz	Lscala/util/parsing/combinator/Parsers$Error$;;
const #7 = Asciz	Failure$module;
const #8 = Asciz	Lscala/util/parsing/combinator/Parsers$Failure$;;
const #9 = Asciz	NoSuccess$module;
const #10 = Asciz	Lscala/util/parsing/combinator/Parsers$NoSuccess$;;
const #11 = Asciz	Success$module;
const #12 = Asciz	Lscala/util/parsing/combinator/Parsers$Success$;;
const #13 = Asciz	EOF$module;
const #14 = Asciz	Lscala/util/parsing/syntax/Tokens$EOF$;;
const #15 = Asciz	ErrorToken$module;
const #16 = Asciz	Lscala/util/parsing/syntax/Tokens$ErrorToken$;;
const #17 = Asciz	lastNoSuccess;
const #18 = Asciz	Lscala/util/parsing/combinator/Parsers$NoSuccess;;
const #19 = Asciz	<init>;
const #20 = Asciz	()V;
const #21 = Asciz	Code;
const #22 = Asciz	LineNumberTable;
const #23 = Asciz	java/lang/Object;
const #24 = class	#23;	//  java/lang/Object
const #25 = NameAndType	#19:#20;//  "<init>":()V
const #26 = Method	#24.#25;	//  java/lang/Object."<init>":()V
const #27 = Asciz	scala/util/parsing/combinator/Parsers$class;
const #28 = class	#27;	//  scala/util/parsing/combinator/Parsers$class
const #29 = Asciz	$init$;
const #30 = Asciz	(Lscala/util/parsing/combinator/Parsers;)V;
const #31 = NameAndType	#29:#30;//  $init$:(Lscala/util/parsing/combinator/Parsers;)V
const #32 = Method	#28.#31;	//  scala/util/parsing/combinator/Parsers$class.$init$:(Lscala/util/parsing/combinator/Parsers;)V
const #33 = Asciz	scala/util/parsing/combinator/lexical/Scanners$class;
const #34 = class	#33;	//  scala/util/parsing/combinator/lexical/Scanners$class
const #35 = Asciz	(Lscala/util/parsing/combinator/lexical/Scanners;)V;
const #36 = NameAndType	#29:#35;//  $init$:(Lscala/util/parsing/combinator/lexical/Scanners;)V
const #37 = Method	#34.#36;	//  scala/util/parsing/combinator/lexical/Scanners$class.$init$:(Lscala/util/parsing/combinator/lexical/Scanners;)V
const #38 = Asciz	scala/util/parsing/syntax/Tokens$class;
const #39 = class	#38;	//  scala/util/parsing/syntax/Tokens$class
const #40 = Asciz	(Lscala/util/parsing/syntax/Tokens;)V;
const #41 = NameAndType	#29:#40;//  $init$:(Lscala/util/parsing/syntax/Tokens;)V
const #42 = Method	#39.#41;	//  scala/util/parsing/syntax/Tokens$class.$init$:(Lscala/util/parsing/syntax/Tokens;)V
const #43 = Asciz	errorToken;
const #44 = Asciz	(Ljava/lang/String;)Ljava/lang/Object;;
const #45 = Asciz	scala/util/parsing/syntax/Tokens;
const #46 = class	#45;	//  scala/util/parsing/syntax/Tokens
const #47 = Asciz	(Ljava/lang/String;)Lscala/util/parsing/syntax/Tokens$Token;;
const #48 = NameAndType	#43:#47;//  errorToken:(Ljava/lang/String;)Lscala/util/parsing/syntax/Tokens$Token;
const #49 = InterfaceMethod	#46.#48;	//  scala/util/parsing/syntax/Tokens.errorToken:(Ljava/lang/String;)Lscala/util/parsing/syntax/Tokens$Token;
const #50 = Asciz	this;
const #51 = Asciz	Lscala/util/parsing/combinator/lexical/Lexical;;
const #52 = Asciz	msg;
const #53 = Asciz	Ljava/lang/String;;
const #54 = Asciz	LocalVariableTable;
const #55 = Asciz	whitespaceChar;
const #56 = Asciz	()Lscala/util/parsing/combinator/Parsers$Parser;;
const #57 = Asciz	space char;
const #58 = String	#57;	//  space char
const #59 = Asciz	scala/util/parsing/combinator/lexical/Lexical$$anonfun$whitespaceChar$1;
const #60 = class	#59;	//  scala/util/parsing/combinator/lexical/Lexical$$anonfun$whitespaceChar$1
const #61 = Asciz	(Lscala/util/parsing/combinator/lexical/Lexical;)V;
const #62 = NameAndType	#19:#61;//  "<init>":(Lscala/util/parsing/combinator/lexical/Lexical;)V
const #63 = Method	#60.#62;	//  scala/util/parsing/combinator/lexical/Lexical$$anonfun$whitespaceChar$1."<init>":(Lscala/util/parsing/combinator/lexical/Lexical;)V
const #64 = Asciz	scala/util/parsing/combinator/Parsers;
const #65 = class	#64;	//  scala/util/parsing/combinator/Parsers
const #66 = Asciz	elem;
const #67 = Asciz	(Ljava/lang/String;Lscala/Function1;)Lscala/util/parsing/combinator/Parsers$Parser;;
const #68 = NameAndType	#66:#67;//  elem:(Ljava/lang/String;Lscala/Function1;)Lscala/util/parsing/combinator/Parsers$Parser;
const #69 = InterfaceMethod	#65.#68;	//  scala/util/parsing/combinator/Parsers.elem:(Ljava/lang/String;Lscala/Function1;)Lscala/util/parsing/combinator/Parsers$Parser;
const #70 = Asciz	()Lscala/util/parsing/combinator/Parsers$Parser<Ljava/lang/Character;>;;
const #71 = Asciz	Signature;
const #72 = Asciz	chrExcept;
const #73 = Asciz	(Lscala/collection/Seq;)Lscala/util/parsing/combinator/Parsers$Parser;;
const #74 = Asciz	;
const #75 = String	#74;	//  
const #76 = Asciz	scala/util/parsing/combinator/lexical/Lexical$$anonfun$chrExcept$1;
const #77 = class	#76;	//  scala/util/parsing/combinator/lexical/Lexical$$anonfun$chrExcept$1
const #78 = Asciz	(Lscala/util/parsing/combinator/lexical/Lexical;Lscala/collection/Seq;)V;
const #79 = NameAndType	#19:#78;//  "<init>":(Lscala/util/parsing/combinator/lexical/Lexical;Lscala/collection/Seq;)V
const #80 = Method	#77.#79;	//  scala/util/parsing/combinator/lexical/Lexical$$anonfun$chrExcept$1."<init>":(Lscala/util/parsing/combinator/lexical/Lexical;Lscala/collection/Seq;)V
const #81 = Asciz	cs$1;
const #82 = Asciz	Lscala/collection/Seq;;
const #83 = Asciz	(Lscala/collection/Seq<Ljava/lang/Character;>;)Lscala/util/parsing/combinator/Parsers$Parser<Ljava/lang/Character;>;;
const #84 = Asciz	digit;
const #85 = String	#84;	//  digit
const #86 = Asciz	scala/util/parsing/combinator/lexical/Lexical$$anonfun$digit$1;
const #87 = class	#86;	//  scala/util/parsing/combinator/lexical/Lexical$$anonfun$digit$1
const #88 = Method	#87.#62;	//  scala/util/parsing/combinator/lexical/Lexical$$anonfun$digit$1."<init>":(Lscala/util/parsing/combinator/lexical/Lexical;)V
const #89 = Asciz	letter;
const #90 = String	#89;	//  letter
const #91 = Asciz	scala/util/parsing/combinator/lexical/Lexical$$anonfun$letter$1;
const #92 = class	#91;	//  scala/util/parsing/combinator/lexical/Lexical$$anonfun$letter$1
const #93 = Method	#92.#62;	//  scala/util/parsing/combinator/lexical/Lexical$$anonfun$letter$1."<init>":(Lscala/util/parsing/combinator/lexical/Lexical;)V
const #94 = Asciz	mkList;
const #95 = Asciz	()Lscala/Function1;;
const #96 = Asciz	(Lscala/util/parsing/combinator/Parsers;)Lscala/Function1;;
const #97 = NameAndType	#94:#96;//  mkList:(Lscala/util/parsing/combinator/Parsers;)Lscala/Function1;
const #98 = Method	#28.#97;	//  scala/util/parsing/combinator/Parsers$class.mkList:(Lscala/util/parsing/combinator/Parsers;)Lscala/Function1;
const #99 = Asciz	phrase;
const #100 = Asciz	(Lscala/util/parsing/combinator/Parsers$Parser;)Lscala/util/parsing/combinator/Parsers$Parser;;
const #101 = Asciz	(Lscala/util/parsing/combinator/Parsers;Lscala/util/parsing/combinator/Parsers$Parser;)Lscala/util/parsing/combinator/Parsers$Parser;;
const #102 = NameAndType	#99:#101;//  phrase:(Lscala/util/parsing/combinator/Parsers;Lscala/util/parsing/combinator/Parsers$Parser;)Lscala/util/parsing/combinator/Parsers$Parser;
const #103 = Method	#28.#102;	//  scala/util/parsing/combinator/Parsers$class.phrase:(Lscala/util/parsing/combinator/Parsers;Lscala/util/parsing/combinator/Parsers$Parser;)Lscala/util/parsing/combinator/Parsers$Parser;
const #104 = Asciz	p;
const #105 = Asciz	Lscala/util/parsing/combinator/Parsers$Parser;;
const #106 = Asciz	positioned;
const #107 = Asciz	(Lscala/Function0;)Lscala/util/parsing/combinator/Parsers$Parser;;
const #108 = Asciz	(Lscala/util/parsing/combinator/Parsers;Lscala/Function0;)Lscala/util/parsing/combinator/Parsers$Parser;;
const #109 = NameAndType	#106:#108;//  positioned:(Lscala/util/parsing/combinator/Parsers;Lscala/Function0;)Lscala/util/parsing/combinator/Parsers$Parser;
const #110 = Method	#28.#109;	//  scala/util/parsing/combinator/Parsers$class.positioned:(Lscala/util/parsing/combinator/Parsers;Lscala/Function0;)Lscala/util/parsing/combinator/Parsers$Parser;
const #111 = Asciz	Lscala/Function0;;
const #112 = Asciz	guard;
const #113 = NameAndType	#112:#108;//  guard:(Lscala/util/parsing/combinator/Parsers;Lscala/Function0;)Lscala/util/parsing/combinator/Parsers$Parser;
const #114 = Method	#28.#113;	//  scala/util/parsing/combinator/Parsers$class.guard:(Lscala/util/parsing/combinator/Parsers;Lscala/Function0;)Lscala/util/parsing/combinator/Parsers$Parser;
const #115 = Asciz	not;
const #116 = NameAndType	#115:#108;//  not:(Lscala/util/parsing/combinator/Parsers;Lscala/Function0;)Lscala/util/parsing/combinator/Parsers$Parser;
const #117 = Method	#28.#116;	//  scala/util/parsing/combinator/Parsers$class.not:(Lscala/util/parsing/combinator/Parsers;Lscala/Function0;)Lscala/util/parsing/combinator/Parsers$Parser;
const #118 = Asciz	opt;
const #119 = NameAndType	#118:#108;//  opt:(Lscala/util/parsing/combinator/Parsers;Lscala/Function0;)Lscala/util/parsing/combinator/Parsers$Parser;
const #120 = Method	#28.#119;	//  scala/util/parsing/combinator/Parsers$class.opt:(Lscala/util/parsing/combinator/Parsers;Lscala/Function0;)Lscala/util/parsing/combinator/Parsers$Parser;
const #121 = Asciz	chainr1;
const #122 = Asciz	(Lscala/Function0;Lscala/Function0;Lscala/Function2;Ljava/lang/Object;)Lscala/util/parsing/combinator/Parsers$Parser;;
const #123 = Asciz	(Lscala/util/parsing/combinator/Parsers;Lscala/Function0;Lscala/Function0;Lscala/Function2;Ljava/lang/Object;)Lscala/util/parsing/combinator/Parsers$Parser;;
const #124 = NameAndType	#121:#123;//  chainr1:(Lscala/util/parsing/combinator/Parsers;Lscala/Function0;Lscala/Function0;Lscala/Function2;Ljava/lang/Object;)Lscala/util/parsing/combinator/Parsers$Parser;
const #125 = Method	#28.#124;	//  scala/util/parsing/combinator/Parsers$class.chainr1:(Lscala/util/parsing/combinator/Parsers;Lscala/Function0;Lscala/Function0;Lscala/Function2;Ljava/lang/Object;)Lscala/util/parsing/combinator/Parsers$Parser;
const #126 = Asciz	q;
const #127 = Asciz	combine;
const #128 = Asciz	Lscala/Function2;;
const #129 = Asciz	first;
const #130 = Asciz	Ljava/lang/Object;;
const #131 = Asciz	chainl1;
const #132 = Asciz	(Lscala/Function0;Lscala/Function0;Lscala/Function0;)Lscala/util/parsing/combinator/Parsers$Parser;;
const #133 = Asciz	(Lscala/util/parsing/combinator/Parsers;Lscala/Function0;Lscala/Function0;Lscala/Function0;)Lscala/util/parsing/combinator/Parsers$Parser;;
const #134 = NameAndType	#131:#133;//  chainl1:(Lscala/util/parsing/combinator/Parsers;Lscala/Function0;Lscala/Function0;Lscala/Function0;)Lscala/util/parsing/combinator/Parsers$Parser;
const #135 = Method	#28.#134;	//  scala/util/parsing/combinator/Parsers$class.chainl1:(Lscala/util/parsing/combinator/Parsers;Lscala/Function0;Lscala/Function0;Lscala/Function0;)Lscala/util/parsing/combinator/Parsers$Parser;
const #136 = Asciz	(Lscala/Function0;Lscala/Function0;)Lscala/util/parsing/combinator/Parsers$Parser;;
const #137 = Asciz	(Lscala/util/parsing/combinator/Parsers;Lscala/Function0;Lscala/Function0;)Lscala/util/parsing/combinator/Parsers$Parser;;
const #138 = NameAndType	#131:#137;//  chainl1:(Lscala/util/parsing/combinator/Parsers;Lscala/Function0;Lscala/Function0;)Lscala/util/parsing/combinator/Parsers$Parser;
const #139 = Method	#28.#138;	//  scala/util/parsing/combinator/Parsers$class.chainl1:(Lscala/util/parsing/combinator/Parsers;Lscala/Function0;Lscala/Function0;)Lscala/util/parsing/combinator/Parsers$Parser;
const #140 = Asciz	rep1sep;
const #141 = NameAndType	#140:#137;//  rep1sep:(Lscala/util/parsing/combinator/Parsers;Lscala/Function0;Lscala/Function0;)Lscala/util/parsing/combinator/Parsers$Parser;
const #142 = Method	#28.#141;	//  scala/util/parsing/combinator/Parsers$class.rep1sep:(Lscala/util/parsing/combinator/Parsers;Lscala/Function0;Lscala/Function0;)Lscala/util/parsing/combinator/Parsers$Parser;
const #143 = Asciz	repN;
const #144 = Asciz	(ILscala/Function0;)Lscala/util/parsing/combinator/Parsers$Parser;;
const #145 = Asciz	(Lscala/util/parsing/combinator/Parsers;ILscala/Function0;)Lscala/util/parsing/combinator/Parsers$Parser;;
const #146 = NameAndType	#143:#145;//  repN:(Lscala/util/parsing/combinator/Parsers;ILscala/Function0;)Lscala/util/parsing/combinator/Parsers$Parser;
const #147 = Method	#28.#146;	//  scala/util/parsing/combinator/Parsers$class.repN:(Lscala/util/parsing/combinator/Parsers;ILscala/Function0;)Lscala/util/parsing/combinator/Parsers$Parser;
const #148 = Asciz	n;
const #149 = Asciz	I;
const #150 = Asciz	rep1;
const #151 = NameAndType	#150:#137;//  rep1:(Lscala/util/parsing/combinator/Parsers;Lscala/Function0;Lscala/Function0;)Lscala/util/parsing/combinator/Parsers$Parser;
const #152 = Method	#28.#151;	//  scala/util/parsing/combinator/Parsers$class.rep1:(Lscala/util/parsing/combinator/Parsers;Lscala/Function0;Lscala/Function0;)Lscala/util/parsing/combinator/Parsers$Parser;
const #153 = NameAndType	#150:#108;//  rep1:(Lscala/util/parsing/combinator/Parsers;Lscala/Function0;)Lscala/util/parsing/combinator/Parsers$Parser;
const #154 = Method	#28.#153;	//  scala/util/parsing/combinator/Parsers$class.rep1:(Lscala/util/parsing/combinator/Parsers;Lscala/Function0;)Lscala/util/parsing/combinator/Parsers$Parser;
const #155 = Asciz	repsep;
const #156 = NameAndType	#155:#137;//  repsep:(Lscala/util/parsing/combinator/Parsers;Lscala/Function0;Lscala/Function0;)Lscala/util/parsing/combinator/Parsers$Parser;
const #157 = Method	#28.#156;	//  scala/util/parsing/combinator/Parsers$class.repsep:(Lscala/util/parsing/combinator/Parsers;Lscala/Function0;Lscala/Function0;)Lscala/util/parsing/combinator/Parsers$Parser;
const #158 = Asciz	rep;
const #159 = NameAndType	#158:#108;//  rep:(Lscala/util/parsing/combinator/Parsers;Lscala/Function0;)Lscala/util/parsing/combinator/Parsers$Parser;
const #160 = Method	#28.#159;	//  scala/util/parsing/combinator/Parsers$class.rep:(Lscala/util/parsing/combinator/Parsers;Lscala/Function0;)Lscala/util/parsing/combinator/Parsers$Parser;
const #161 = Asciz	log;
const #162 = Asciz	(Lscala/Function0;Ljava/lang/String;)Lscala/util/parsing/combinator/Parsers$Parser;;
const #163 = Asciz	(Lscala/util/parsing/combinator/Parsers;Lscala/Function0;Ljava/lang/String;)Lscala/util/parsing/combinator/Parsers$Parser;;
const #164 = NameAndType	#161:#163;//  log:(Lscala/util/parsing/combinator/Parsers;Lscala/Function0;Ljava/lang/String;)Lscala/util/parsing/combinator/Parsers$Parser;
const #165 = Method	#28.#164;	//  scala/util/parsing/combinator/Parsers$class.log:(Lscala/util/parsing/combinator/Parsers;Lscala/Function0;Ljava/lang/String;)Lscala/util/parsing/combinator/Parsers$Parser;
const #166 = Asciz	name;
const #167 = Asciz	success;
const #168 = Asciz	(Ljava/lang/Object;)Lscala/util/parsing/combinator/Parsers$Parser;;
const #169 = Asciz	(Lscala/util/parsing/combinator/Parsers;Ljava/lang/Object;)Lscala/util/parsing/combinator/Parsers$Parser;;
const #170 = NameAndType	#167:#169;//  success:(Lscala/util/parsing/combinator/Parsers;Ljava/lang/Object;)Lscala/util/parsing/combinator/Parsers$Parser;
const #171 = Method	#28.#170;	//  scala/util/parsing/combinator/Parsers$class.success:(Lscala/util/parsing/combinator/Parsers;Ljava/lang/Object;)Lscala/util/parsing/combinator/Parsers$Parser;
const #172 = Asciz	v;
const #173 = Asciz	err;
const #174 = Asciz	(Ljava/lang/String;)Lscala/util/parsing/combinator/Parsers$Parser;;
const #175 = Asciz	(Lscala/util/parsing/combinator/Parsers;Ljava/lang/String;)Lscala/util/parsing/combinator/Parsers$Parser;;
const #176 = NameAndType	#173:#175;//  err:(Lscala/util/parsing/combinator/Parsers;Ljava/lang/String;)Lscala/util/parsing/combinator/Parsers$Parser;
const #177 = Method	#28.#176;	//  scala/util/parsing/combinator/Parsers$class.err:(Lscala/util/parsing/combinator/Parsers;Ljava/lang/String;)Lscala/util/parsing/combinator/Parsers$Parser;
const #178 = Asciz	failure;
const #179 = NameAndType	#178:#175;//  failure:(Lscala/util/parsing/combinator/Parsers;Ljava/lang/String;)Lscala/util/parsing/combinator/Parsers$Parser;
const #180 = Method	#28.#179;	//  scala/util/parsing/combinator/Parsers$class.failure:(Lscala/util/parsing/combinator/Parsers;Ljava/lang/String;)Lscala/util/parsing/combinator/Parsers$Parser;
const #181 = Asciz	acceptSeq;
const #182 = Asciz	(Ljava/lang/Object;Lscala/Function1;)Lscala/util/parsing/combinator/Parsers$Parser;;
const #183 = Asciz	(Lscala/util/parsing/combinator/Parsers;Ljava/lang/Object;Lscala/Function1;)Lscala/util/parsing/combinator/Parsers$Parser;;
const #184 = NameAndType	#181:#183;//  acceptSeq:(Lscala/util/parsing/combinator/Parsers;Ljava/lang/Object;Lscala/Function1;)Lscala/util/parsing/combinator/Parsers$Parser;
const #185 = Method	#28.#184;	//  scala/util/parsing/combinator/Parsers$class.acceptSeq:(Lscala/util/parsing/combinator/Parsers;Ljava/lang/Object;Lscala/Function1;)Lscala/util/parsing/combinator/Parsers$Parser;
const #186 = Asciz	es;
const #187 = Asciz	evidence$2;
const #188 = Asciz	Lscala/Function1;;
const #189 = Asciz	acceptMatch;
const #190 = Asciz	(Ljava/lang/String;Lscala/PartialFunction;)Lscala/util/parsing/combinator/Parsers$Parser;;
const #191 = Asciz	(Lscala/util/parsing/combinator/Parsers;Ljava/lang/String;Lscala/PartialFunction;)Lscala/util/parsing/combinator/Parsers$Parser;;
const #192 = NameAndType	#189:#191;//  acceptMatch:(Lscala/util/parsing/combinator/Parsers;Ljava/lang/String;Lscala/PartialFunction;)Lscala/util/parsing/combinator/Parsers$Parser;
const #193 = Method	#28.#192;	//  scala/util/parsing/combinator/Parsers$class.acceptMatch:(Lscala/util/parsing/combinator/Parsers;Ljava/lang/String;Lscala/PartialFunction;)Lscala/util/parsing/combinator/Parsers$Parser;
const #194 = Asciz	expected;
const #195 = Asciz	f;
const #196 = Asciz	Lscala/PartialFunction;;
const #197 = Asciz	acceptIf;
const #198 = Asciz	(Lscala/Function1;Lscala/Function1;)Lscala/util/parsing/combinator/Parsers$Parser;;
const #199 = Asciz	(Lscala/util/parsing/combinator/Parsers;Lscala/Function1;Lscala/Function1;)Lscala/util/parsing/combinator/Parsers$Parser;;
const #200 = NameAndType	#197:#199;//  acceptIf:(Lscala/util/parsing/combinator/Parsers;Lscala/Function1;Lscala/Function1;)Lscala/util/parsing/combinator/Parsers$Parser;
const #201 = Method	#28.#200;	//  scala/util/parsing/combinator/Parsers$class.acceptIf:(Lscala/util/parsing/combinator/Parsers;Lscala/Function1;Lscala/Function1;)Lscala/util/parsing/combinator/Parsers$Parser;
const #202 = Asciz	accept;
const #203 = NameAndType	#202:#191;//  accept:(Lscala/util/parsing/combinator/Parsers;Ljava/lang/String;Lscala/PartialFunction;)Lscala/util/parsing/combinator/Parsers$Parser;
const #204 = Method	#28.#203;	//  scala/util/parsing/combinator/Parsers$class.accept:(Lscala/util/parsing/combinator/Parsers;Ljava/lang/String;Lscala/PartialFunction;)Lscala/util/parsing/combinator/Parsers$Parser;
const #205 = NameAndType	#202:#183;//  accept:(Lscala/util/parsing/combinator/Parsers;Ljava/lang/Object;Lscala/Function1;)Lscala/util/parsing/combinator/Parsers$Parser;
const #206 = Method	#28.#205;	//  scala/util/parsing/combinator/Parsers$class.accept:(Lscala/util/parsing/combinator/Parsers;Ljava/lang/Object;Lscala/Function1;)Lscala/util/parsing/combinator/Parsers$Parser;
const #207 = Asciz	evidence$1;
const #208 = NameAndType	#202:#169;//  accept:(Lscala/util/parsing/combinator/Parsers;Ljava/lang/Object;)Lscala/util/parsing/combinator/Parsers$Parser;
const #209 = Method	#28.#208;	//  scala/util/parsing/combinator/Parsers$class.accept:(Lscala/util/parsing/combinator/Parsers;Ljava/lang/Object;)Lscala/util/parsing/combinator/Parsers$Parser;
const #210 = Asciz	e;
const #211 = NameAndType	#66:#169;//  elem:(Lscala/util/parsing/combinator/Parsers;Ljava/lang/Object;)Lscala/util/parsing/combinator/Parsers$Parser;
const #212 = Method	#28.#211;	//  scala/util/parsing/combinator/Parsers$class.elem:(Lscala/util/parsing/combinator/Parsers;Ljava/lang/Object;)Lscala/util/parsing/combinator/Parsers$Parser;
const #213 = Asciz	(Lscala/util/parsing/combinator/Parsers;Ljava/lang/String;Lscala/Function1;)Lscala/util/parsing/combinator/Parsers$Parser;;
const #214 = NameAndType	#66:#213;//  elem:(Lscala/util/parsing/combinator/Parsers;Ljava/lang/String;Lscala/Function1;)Lscala/util/parsing/combinator/Parsers$Parser;
const #215 = Method	#28.#214;	//  scala/util/parsing/combinator/Parsers$class.elem:(Lscala/util/parsing/combinator/Parsers;Ljava/lang/String;Lscala/Function1;)Lscala/util/parsing/combinator/Parsers$Parser;
const #216 = Asciz	kind;
const #217 = Asciz	commit;
const #218 = NameAndType	#217:#108;//  commit:(Lscala/util/parsing/combinator/Parsers;Lscala/Function0;)Lscala/util/parsing/combinator/Parsers$Parser;
const #219 = Method	#28.#218;	//  scala/util/parsing/combinator/Parsers$class.commit:(Lscala/util/parsing/combinator/Parsers;Lscala/Function0;)Lscala/util/parsing/combinator/Parsers$Parser;
const #220 = Asciz	OnceParser;
const #221 = Asciz	(Lscala/Function1;)Lscala/util/parsing/combinator/Parsers$Parser;;
const #222 = Asciz	(Lscala/util/parsing/combinator/Parsers;Lscala/Function1;)Lscala/util/parsing/combinator/Parsers$Parser;;
const #223 = NameAndType	#220:#222;//  OnceParser:(Lscala/util/parsing/combinator/Parsers;Lscala/Function1;)Lscala/util/parsing/combinator/Parsers$Parser;
const #224 = Method	#28.#223;	//  scala/util/parsing/combinator/Parsers$class.OnceParser:(Lscala/util/parsing/combinator/Parsers;Lscala/Function1;)Lscala/util/parsing/combinator/Parsers$Parser;
const #225 = Asciz	Parser;
const #226 = NameAndType	#225:#222;//  Parser:(Lscala/util/parsing/combinator/Parsers;Lscala/Function1;)Lscala/util/parsing/combinator/Parsers$Parser;
const #227 = Method	#28.#226;	//  scala/util/parsing/combinator/Parsers$class.Parser:(Lscala/util/parsing/combinator/Parsers;Lscala/Function1;)Lscala/util/parsing/combinator/Parsers$Parser;
const #228 = Asciz	$tilde;
const #229 = Asciz	()Lscala/util/parsing/combinator/Parsers$$tilde$;;
const #230 = Asciz	scala/util/parsing/combinator/lexical/Lexical;
const #231 = class	#230;	//  scala/util/parsing/combinator/lexical/Lexical
const #232 = NameAndType	#3:#4;//  $tilde$module:Lscala/util/parsing/combinator/Parsers$$tilde$;
const #233 = Field	#231.#232;	//  scala/util/parsing/combinator/lexical/Lexical.$tilde$module:Lscala/util/parsing/combinator/Parsers$$tilde$;
const #234 = Asciz	scala/util/parsing/combinator/Parsers$$tilde$;
const #235 = class	#234;	//  scala/util/parsing/combinator/Parsers$$tilde$
const #236 = NameAndType	#19:#30;//  "<init>":(Lscala/util/parsing/combinator/Parsers;)V
const #237 = Method	#235.#236;	//  scala/util/parsing/combinator/Parsers$$tilde$."<init>":(Lscala/util/parsing/combinator/Parsers;)V
const #238 = Asciz	Error;
const #239 = Asciz	()Lscala/util/parsing/combinator/Parsers$Error$;;
const #240 = NameAndType	#5:#6;//  Error$module:Lscala/util/parsing/combinator/Parsers$Error$;
const #241 = Field	#231.#240;	//  scala/util/parsing/combinator/lexical/Lexical.Error$module:Lscala/util/parsing/combinator/Parsers$Error$;
const #242 = Asciz	scala/util/parsing/combinator/Parsers$Error$;
const #243 = class	#242;	//  scala/util/parsing/combinator/Parsers$Error$
const #244 = Method	#243.#236;	//  scala/util/parsing/combinator/Parsers$Error$."<init>":(Lscala/util/parsing/combinator/Parsers;)V
const #245 = Asciz	Failure;
const #246 = Asciz	()Lscala/util/parsing/combinator/Parsers$Failure$;;
const #247 = NameAndType	#7:#8;//  Failure$module:Lscala/util/parsing/combinator/Parsers$Failure$;
const #248 = Field	#231.#247;	//  scala/util/parsing/combinator/lexical/Lexical.Failure$module:Lscala/util/parsing/combinator/Parsers$Failure$;
const #249 = Asciz	scala/util/parsing/combinator/Parsers$Failure$;
const #250 = class	#249;	//  scala/util/parsing/combinator/Parsers$Failure$
const #251 = Method	#250.#236;	//  scala/util/parsing/combinator/Parsers$Failure$."<init>":(Lscala/util/parsing/combinator/Parsers;)V
const #252 = Asciz	NoSuccess;
const #253 = Asciz	()Lscala/util/parsing/combinator/Parsers$NoSuccess$;;
const #254 = NameAndType	#9:#10;//  NoSuccess$module:Lscala/util/parsing/combinator/Parsers$NoSuccess$;
const #255 = Field	#231.#254;	//  scala/util/parsing/combinator/lexical/Lexical.NoSuccess$module:Lscala/util/parsing/combinator/Parsers$NoSuccess$;
const #256 = Asciz	scala/util/parsing/combinator/Parsers$NoSuccess$;
const #257 = class	#256;	//  scala/util/parsing/combinator/Parsers$NoSuccess$
const #258 = Method	#257.#236;	//  scala/util/parsing/combinator/Parsers$NoSuccess$."<init>":(Lscala/util/parsing/combinator/Parsers;)V
const #259 = Asciz	lastNoSuccess_$eq;
const #260 = Asciz	(Lscala/util/parsing/combinator/Parsers$NoSuccess;)V;
const #261 = NameAndType	#17:#18;//  lastNoSuccess:Lscala/util/parsing/combinator/Parsers$NoSuccess;
const #262 = Field	#231.#261;	//  scala/util/parsing/combinator/lexical/Lexical.lastNoSuccess:Lscala/util/parsing/combinator/Parsers$NoSuccess;
const #263 = Asciz	()Lscala/util/parsing/combinator/Parsers$NoSuccess;;
const #264 = Asciz	Success;
const #265 = Asciz	()Lscala/util/parsing/combinator/Parsers$Success$;;
const #266 = NameAndType	#11:#12;//  Success$module:Lscala/util/parsing/combinator/Parsers$Success$;
const #267 = Field	#231.#266;	//  scala/util/parsing/combinator/lexical/Lexical.Success$module:Lscala/util/parsing/combinator/Parsers$Success$;
const #268 = Asciz	scala/util/parsing/combinator/Parsers$Success$;
const #269 = class	#268;	//  scala/util/parsing/combinator/Parsers$Success$
const #270 = Method	#269.#236;	//  scala/util/parsing/combinator/Parsers$Success$."<init>":(Lscala/util/parsing/combinator/Parsers;)V
const #271 = Asciz	(Lscala/util/parsing/syntax/Tokens;Ljava/lang/String;)Lscala/util/parsing/syntax/Tokens$Token;;
const #272 = NameAndType	#43:#271;//  errorToken:(Lscala/util/parsing/syntax/Tokens;Ljava/lang/String;)Lscala/util/parsing/syntax/Tokens$Token;
const #273 = Method	#39.#272;	//  scala/util/parsing/syntax/Tokens$class.errorToken:(Lscala/util/parsing/syntax/Tokens;Ljava/lang/String;)Lscala/util/parsing/syntax/Tokens$Token;
const #274 = Asciz	EOF;
const #275 = Asciz	()Lscala/util/parsing/syntax/Tokens$EOF$;;
const #276 = NameAndType	#13:#14;//  EOF$module:Lscala/util/parsing/syntax/Tokens$EOF$;
const #277 = Field	#231.#276;	//  scala/util/parsing/combinator/lexical/Lexical.EOF$module:Lscala/util/parsing/syntax/Tokens$EOF$;
const #278 = Asciz	scala/util/parsing/syntax/Tokens$EOF$;
const #279 = class	#278;	//  scala/util/parsing/syntax/Tokens$EOF$
const #280 = NameAndType	#19:#40;//  "<init>":(Lscala/util/parsing/syntax/Tokens;)V
const #281 = Method	#279.#280;	//  scala/util/parsing/syntax/Tokens$EOF$."<init>":(Lscala/util/parsing/syntax/Tokens;)V
const #282 = Asciz	ErrorToken;
const #283 = Asciz	()Lscala/util/parsing/syntax/Tokens$ErrorToken$;;
const #284 = NameAndType	#15:#16;//  ErrorToken$module:Lscala/util/parsing/syntax/Tokens$ErrorToken$;
const #285 = Field	#231.#284;	//  scala/util/parsing/combinator/lexical/Lexical.ErrorToken$module:Lscala/util/parsing/syntax/Tokens$ErrorToken$;
const #286 = Asciz	scala/util/parsing/syntax/Tokens$ErrorToken$;
const #287 = class	#286;	//  scala/util/parsing/syntax/Tokens$ErrorToken$
const #288 = Method	#287.#280;	//  scala/util/parsing/syntax/Tokens$ErrorToken$."<init>":(Lscala/util/parsing/syntax/Tokens;)V
const #289 = Asciz	ScalaSig;
const #290 = Asciz	InnerClasses;
const #291 = Asciz	scala/util/parsing/syntax/Tokens$Token;
const #292 = class	#291;	//  scala/util/parsing/syntax/Tokens$Token
const #293 = Asciz	Token;
const #294 = Asciz	scala/util/parsing/combinator/Parsers$Parser;
const #295 = class	#294;	//  scala/util/parsing/combinator/Parsers$Parser
const #296 = Asciz	scala/util/parsing/combinator/Parsers$NoSuccess;
const #297 = class	#296;	//  scala/util/parsing/combinator/Parsers$NoSuccess
const #298 = Asciz	$anonfun$digit$1;
const #299 = Asciz	$anonfun$letter$1;
const #300 = Asciz	$anonfun$chrExcept$1;
const #301 = Asciz	$anonfun$whitespaceChar$1;
const #302 = Asciz	scala/util/parsing/combinator/lexical/Scanners;
const #303 = class	#302;	//  scala/util/parsing/combinator/lexical/Scanners
const #304 = Asciz	scala/ScalaObject;
const #305 = class	#304;	//  scala/ScalaObject

{
public scala.util.parsing.combinator.lexical.Lexical();
  Code:
   Stack=1, Locals=1, Args_size=1
   0:	aload_0
   1:	invokespecial	#26; //Method java/lang/Object."<init>":()V
   4:	aload_0
   5:	invokestatic	#32; //Method scala/util/parsing/combinator/Parsers$class.$init$:(Lscala/util/parsing/combinator/Parsers;)V
   8:	aload_0
   9:	invokestatic	#37; //Method scala/util/parsing/combinator/lexical/Scanners$class.$init$:(Lscala/util/parsing/combinator/lexical/Scanners;)V
   12:	aload_0
   13:	invokestatic	#42; //Method scala/util/parsing/syntax/Tokens$class.$init$:(Lscala/util/parsing/syntax/Tokens;)V
   16:	return
  LineNumberTable: 
   line 29: 0


public java.lang.Object errorToken(java.lang.String);
  Code:
   Stack=2, Locals=2, Args_size=2
   0:	aload_0
   1:	aload_1
   2:	invokeinterface	#49,  2; //InterfaceMethod scala/util/parsing/syntax/Tokens.errorToken:(Ljava/lang/String;)Lscala/util/parsing/syntax/Tokens$Token;
   7:	areturn
  LineNumberTable: 
   line 29: 0

  LocalVariableTable: 
   Start  Length  Slot  Name   Signature
   0      8      0    this       Lscala/util/parsing/combinator/lexical/Lexical;
   0      8      1    msg       Ljava/lang/String;


public scala.util.parsing.combinator.Parsers$Parser whitespaceChar();
  Code:
   Stack=5, Locals=1, Args_size=1
   0:	aload_0
   1:	ldc	#58; //String space char
   3:	new	#60; //class scala/util/parsing/combinator/lexical/Lexical$$anonfun$whitespaceChar$1
   6:	dup
   7:	aload_0
   8:	invokespecial	#63; //Method scala/util/parsing/combinator/lexical/Lexical$$anonfun$whitespaceChar$1."<init>":(Lscala/util/parsing/combinator/lexical/Lexical;)V
   11:	invokeinterface	#69,  3; //InterfaceMethod scala/util/parsing/combinator/Parsers.elem:(Ljava/lang/String;Lscala/Function1;)Lscala/util/parsing/combinator/Parsers$Parser;
   16:	areturn
  LineNumberTable: 
   line 41: 0

  Signature: length = 0x2
   00 46 

public scala.util.parsing.combinator.Parsers$Parser chrExcept(scala.collection.Seq);
  Code:
   Stack=6, Locals=2, Args_size=2
   0:	aload_0
   1:	ldc	#75; //String 
   3:	new	#77; //class scala/util/parsing/combinator/lexical/Lexical$$anonfun$chrExcept$1
   6:	dup
   7:	aload_0
   8:	aload_1
   9:	invokespecial	#80; //Method scala/util/parsing/combinator/lexical/Lexical$$anonfun$chrExcept$1."<init>":(Lscala/util/parsing/combinator/lexical/Lexical;Lscala/collection/Seq;)V
   12:	invokeinterface	#69,  3; //InterfaceMethod scala/util/parsing/combinator/Parsers.elem:(Ljava/lang/String;Lscala/Function1;)Lscala/util/parsing/combinator/Parsers$Parser;
   17:	areturn
  LineNumberTable: 
   line 38: 0

  LocalVariableTable: 
   Start  Length  Slot  Name   Signature
   0      18      0    this       Lscala/util/parsing/combinator/lexical/Lexical;
   0      18      1    cs$1       Lscala/collection/Seq;

  Signature: length = 0x2
   00 53 

public scala.util.parsing.combinator.Parsers$Parser digit();
  Code:
   Stack=5, Locals=1, Args_size=1
   0:	aload_0
   1:	ldc	#85; //String digit
   3:	new	#87; //class scala/util/parsing/combinator/lexical/Lexical$$anonfun$digit$1
   6:	dup
   7:	aload_0
   8:	invokespecial	#88; //Method scala/util/parsing/combinator/lexical/Lexical$$anonfun$digit$1."<init>":(Lscala/util/parsing/combinator/lexical/Lexical;)V
   11:	invokeinterface	#69,  3; //InterfaceMethod scala/util/parsing/combinator/Parsers.elem:(Ljava/lang/String;Lscala/Function1;)Lscala/util/parsing/combinator/Parsers$Parser;
   16:	areturn
  LineNumberTable: 
   line 35: 0

  Signature: length = 0x2
   00 46 

public scala.util.parsing.combinator.Parsers$Parser letter();
  Code:
   Stack=5, Locals=1, Args_size=1
   0:	aload_0
   1:	ldc	#90; //String letter
   3:	new	#92; //class scala/util/parsing/combinator/lexical/Lexical$$anonfun$letter$1
   6:	dup
   7:	aload_0
   8:	invokespecial	#93; //Method scala/util/parsing/combinator/lexical/Lexical$$anonfun$letter$1."<init>":(Lscala/util/parsing/combinator/lexical/Lexical;)V
   11:	invokeinterface	#69,  3; //InterfaceMethod scala/util/parsing/combinator/Parsers.elem:(Ljava/lang/String;Lscala/Function1;)Lscala/util/parsing/combinator/Parsers$Parser;
   16:	areturn
  LineNumberTable: 
   line 32: 0

  Signature: length = 0x2
   00 46 

public scala.Function1 mkList();
  Code:
   Stack=1, Locals=1, Args_size=1
   0:	aload_0
   1:	invokestatic	#98; //Method scala/util/parsing/combinator/Parsers$class.mkList:(Lscala/util/parsing/combinator/Parsers;)Lscala/Function1;
   4:	areturn
  LineNumberTable: 
   line 29: 0


public scala.util.parsing.combinator.Parsers$Parser phrase(scala.util.parsing.combinator.Parsers$Parser);
  Code:
   Stack=2, Locals=2, Args_size=2
   0:	aload_0
   1:	aload_1
   2:	invokestatic	#103; //Method scala/util/parsing/combinator/Parsers$class.phrase:(Lscala/util/parsing/combinator/Parsers;Lscala/util/parsing/combinator/Parsers$Parser;)Lscala/util/parsing/combinator/Parsers$Parser;
   5:	areturn
  LineNumberTable: 
   line 29: 0

  LocalVariableTable: 
   Start  Length  Slot  Name   Signature
   0      6      0    this       Lscala/util/parsing/combinator/lexical/Lexical;
   0      6      1    p       Lscala/util/parsing/combinator/Parsers$Parser;


public scala.util.parsing.combinator.Parsers$Parser positioned(scala.Function0);
  Code:
   Stack=2, Locals=2, Args_size=2
   0:	aload_0
   1:	aload_1
   2:	invokestatic	#110; //Method scala/util/parsing/combinator/Parsers$class.positioned:(Lscala/util/parsing/combinator/Parsers;Lscala/Function0;)Lscala/util/parsing/combinator/Parsers$Parser;
   5:	areturn
  LineNumberTable: 
   line 29: 0

  LocalVariableTable: 
   Start  Length  Slot  Name   Signature
   0      6      0    this       Lscala/util/parsing/combinator/lexical/Lexical;
   0      6      1    p       Lscala/Function0;


public scala.util.parsing.combinator.Parsers$Parser guard(scala.Function0);
  Code:
   Stack=2, Locals=2, Args_size=2
   0:	aload_0
   1:	aload_1
   2:	invokestatic	#114; //Method scala/util/parsing/combinator/Parsers$class.guard:(Lscala/util/parsing/combinator/Parsers;Lscala/Function0;)Lscala/util/parsing/combinator/Parsers$Parser;
   5:	areturn
  LineNumberTable: 
   line 29: 0

  LocalVariableTable: 
   Start  Length  Slot  Name   Signature
   0      6      0    this       Lscala/util/parsing/combinator/lexical/Lexical;
   0      6      1    p       Lscala/Function0;


public scala.util.parsing.combinator.Parsers$Parser not(scala.Function0);
  Code:
   Stack=2, Locals=2, Args_size=2
   0:	aload_0
   1:	aload_1
   2:	invokestatic	#117; //Method scala/util/parsing/combinator/Parsers$class.not:(Lscala/util/parsing/combinator/Parsers;Lscala/Function0;)Lscala/util/parsing/combinator/Parsers$Parser;
   5:	areturn
  LineNumberTable: 
   line 29: 0

  LocalVariableTable: 
   Start  Length  Slot  Name   Signature
   0      6      0    this       Lscala/util/parsing/combinator/lexical/Lexical;
   0      6      1    p       Lscala/Function0;


public scala.util.parsing.combinator.Parsers$Parser opt(scala.Function0);
  Code:
   Stack=2, Locals=2, Args_size=2
   0:	aload_0
   1:	aload_1
   2:	invokestatic	#120; //Method scala/util/parsing/combinator/Parsers$class.opt:(Lscala/util/parsing/combinator/Parsers;Lscala/Function0;)Lscala/util/parsing/combinator/Parsers$Parser;
   5:	areturn
  LineNumberTable: 
   line 29: 0

  LocalVariableTable: 
   Start  Length  Slot  Name   Signature
   0      6      0    this       Lscala/util/parsing/combinator/lexical/Lexical;
   0      6      1    p       Lscala/Function0;


public scala.util.parsing.combinator.Parsers$Parser chainr1(scala.Function0, scala.Function0, scala.Function2, java.lang.Object);
  Code:
   Stack=5, Locals=5, Args_size=5
   0:	aload_0
   1:	aload_1
   2:	aload_2
   3:	aload_3
   4:	aload	4
   6:	invokestatic	#125; //Method scala/util/parsing/combinator/Parsers$class.chainr1:(Lscala/util/parsing/combinator/Parsers;Lscala/Function0;Lscala/Function0;Lscala/Function2;Ljava/lang/Object;)Lscala/util/parsing/combinator/Parsers$Parser;
   9:	areturn
  LineNumberTable: 
   line 29: 0

  LocalVariableTable: 
   Start  Length  Slot  Name   Signature
   0      10      0    this       Lscala/util/parsing/combinator/lexical/Lexical;
   0      10      1    p       Lscala/Function0;
   0      10      2    q       Lscala/Function0;
   0      10      3    combine       Lscala/Function2;
   0      10      4    first       Ljava/lang/Object;


public scala.util.parsing.combinator.Parsers$Parser chainl1(scala.Function0, scala.Function0, scala.Function0);
  Code:
   Stack=4, Locals=4, Args_size=4
   0:	aload_0
   1:	aload_1
   2:	aload_2
   3:	aload_3
   4:	invokestatic	#135; //Method scala/util/parsing/combinator/Parsers$class.chainl1:(Lscala/util/parsing/combinator/Parsers;Lscala/Function0;Lscala/Function0;Lscala/Function0;)Lscala/util/parsing/combinator/Parsers$Parser;
   7:	areturn
  LineNumberTable: 
   line 29: 0

  LocalVariableTable: 
   Start  Length  Slot  Name   Signature
   0      8      0    this       Lscala/util/parsing/combinator/lexical/Lexical;
   0      8      1    first       Lscala/Function0;
   0      8      2    p       Lscala/Function0;
   0      8      3    q       Lscala/Function0;


public scala.util.parsing.combinator.Parsers$Parser chainl1(scala.Function0, scala.Function0);
  Code:
   Stack=3, Locals=3, Args_size=3
   0:	aload_0
   1:	aload_1
   2:	aload_2
   3:	invokestatic	#139; //Method scala/util/parsing/combinator/Parsers$class.chainl1:(Lscala/util/parsing/combinator/Parsers;Lscala/Function0;Lscala/Function0;)Lscala/util/parsing/combinator/Parsers$Parser;
   6:	areturn
  LineNumberTable: 
   line 29: 0

  LocalVariableTable: 
   Start  Length  Slot  Name   Signature
   0      7      0    this       Lscala/util/parsing/combinator/lexical/Lexical;
   0      7      1    p       Lscala/Function0;
   0      7      2    q       Lscala/Function0;


public scala.util.parsing.combinator.Parsers$Parser rep1sep(scala.Function0, scala.Function0);
  Code:
   Stack=3, Locals=3, Args_size=3
   0:	aload_0
   1:	aload_1
   2:	aload_2
   3:	invokestatic	#142; //Method scala/util/parsing/combinator/Parsers$class.rep1sep:(Lscala/util/parsing/combinator/Parsers;Lscala/Function0;Lscala/Function0;)Lscala/util/parsing/combinator/Parsers$Parser;
   6:	areturn
  LineNumberTable: 
   line 29: 0

  LocalVariableTable: 
   Start  Length  Slot  Name   Signature
   0      7      0    this       Lscala/util/parsing/combinator/lexical/Lexical;
   0      7      1    p       Lscala/Function0;
   0      7      2    q       Lscala/Function0;


public scala.util.parsing.combinator.Parsers$Parser repN(int, scala.Function0);
  Code:
   Stack=3, Locals=3, Args_size=3
   0:	aload_0
   1:	iload_1
   2:	aload_2
   3:	invokestatic	#147; //Method scala/util/parsing/combinator/Parsers$class.repN:(Lscala/util/parsing/combinator/Parsers;ILscala/Function0;)Lscala/util/parsing/combinator/Parsers$Parser;
   6:	areturn
  LineNumberTable: 
   line 29: 0

  LocalVariableTable: 
   Start  Length  Slot  Name   Signature
   0      7      0    this       Lscala/util/parsing/combinator/lexical/Lexical;
   0      7      1    n       I
   0      7      2    p       Lscala/Function0;


public scala.util.parsing.combinator.Parsers$Parser rep1(scala.Function0, scala.Function0);
  Code:
   Stack=3, Locals=3, Args_size=3
   0:	aload_0
   1:	aload_1
   2:	aload_2
   3:	invokestatic	#152; //Method scala/util/parsing/combinator/Parsers$class.rep1:(Lscala/util/parsing/combinator/Parsers;Lscala/Function0;Lscala/Function0;)Lscala/util/parsing/combinator/Parsers$Parser;
   6:	areturn
  LineNumberTable: 
   line 29: 0

  LocalVariableTable: 
   Start  Length  Slot  Name   Signature
   0      7      0    this       Lscala/util/parsing/combinator/lexical/Lexical;
   0      7      1    first       Lscala/Function0;
   0      7      2    p       Lscala/Function0;


public scala.util.parsing.combinator.Parsers$Parser rep1(scala.Function0);
  Code:
   Stack=2, Locals=2, Args_size=2
   0:	aload_0
   1:	aload_1
   2:	invokestatic	#154; //Method scala/util/parsing/combinator/Parsers$class.rep1:(Lscala/util/parsing/combinator/Parsers;Lscala/Function0;)Lscala/util/parsing/combinator/Parsers$Parser;
   5:	areturn
  LineNumberTable: 
   line 29: 0

  LocalVariableTable: 
   Start  Length  Slot  Name   Signature
   0      6      0    this       Lscala/util/parsing/combinator/lexical/Lexical;
   0      6      1    p       Lscala/Function0;


public scala.util.parsing.combinator.Parsers$Parser repsep(scala.Function0, scala.Function0);
  Code:
   Stack=3, Locals=3, Args_size=3
   0:	aload_0
   1:	aload_1
   2:	aload_2
   3:	invokestatic	#157; //Method scala/util/parsing/combinator/Parsers$class.repsep:(Lscala/util/parsing/combinator/Parsers;Lscala/Function0;Lscala/Function0;)Lscala/util/parsing/combinator/Parsers$Parser;
   6:	areturn
  LineNumberTable: 
   line 29: 0

  LocalVariableTable: 
   Start  Length  Slot  Name   Signature
   0      7      0    this       Lscala/util/parsing/combinator/lexical/Lexical;
   0      7      1    p       Lscala/Function0;
   0      7      2    q       Lscala/Function0;


public scala.util.parsing.combinator.Parsers$Parser rep(scala.Function0);
  Code:
   Stack=2, Locals=2, Args_size=2
   0:	aload_0
   1:	aload_1
   2:	invokestatic	#160; //Method scala/util/parsing/combinator/Parsers$class.rep:(Lscala/util/parsing/combinator/Parsers;Lscala/Function0;)Lscala/util/parsing/combinator/Parsers$Parser;
   5:	areturn
  LineNumberTable: 
   line 29: 0

  LocalVariableTable: 
   Start  Length  Slot  Name   Signature
   0      6      0    this       Lscala/util/parsing/combinator/lexical/Lexical;
   0      6      1    p       Lscala/Function0;


public scala.util.parsing.combinator.Parsers$Parser log(scala.Function0, java.lang.String);
  Code:
   Stack=3, Locals=3, Args_size=3
   0:	aload_0
   1:	aload_1
   2:	aload_2
   3:	invokestatic	#165; //Method scala/util/parsing/combinator/Parsers$class.log:(Lscala/util/parsing/combinator/Parsers;Lscala/Function0;Ljava/lang/String;)Lscala/util/parsing/combinator/Parsers$Parser;
   6:	areturn
  LineNumberTable: 
   line 29: 0

  LocalVariableTable: 
   Start  Length  Slot  Name   Signature
   0      7      0    this       Lscala/util/parsing/combinator/lexical/Lexical;
   0      7      1    p       Lscala/Function0;
   0      7      2    name       Ljava/lang/String;


public scala.util.parsing.combinator.Parsers$Parser success(java.lang.Object);
  Code:
   Stack=2, Locals=2, Args_size=2
   0:	aload_0
   1:	aload_1
   2:	invokestatic	#171; //Method scala/util/parsing/combinator/Parsers$class.success:(Lscala/util/parsing/combinator/Parsers;Ljava/lang/Object;)Lscala/util/parsing/combinator/Parsers$Parser;
   5:	areturn
  LineNumberTable: 
   line 29: 0

  LocalVariableTable: 
   Start  Length  Slot  Name   Signature
   0      6      0    this       Lscala/util/parsing/combinator/lexical/Lexical;
   0      6      1    v       Ljava/lang/Object;


public scala.util.parsing.combinator.Parsers$Parser err(java.lang.String);
  Code:
   Stack=2, Locals=2, Args_size=2
   0:	aload_0
   1:	aload_1
   2:	invokestatic	#177; //Method scala/util/parsing/combinator/Parsers$class.err:(Lscala/util/parsing/combinator/Parsers;Ljava/lang/String;)Lscala/util/parsing/combinator/Parsers$Parser;
   5:	areturn
  LineNumberTable: 
   line 29: 0

  LocalVariableTable: 
   Start  Length  Slot  Name   Signature
   0      6      0    this       Lscala/util/parsing/combinator/lexical/Lexical;
   0      6      1    msg       Ljava/lang/String;


public scala.util.parsing.combinator.Parsers$Parser failure(java.lang.String);
  Code:
   Stack=2, Locals=2, Args_size=2
   0:	aload_0
   1:	aload_1
   2:	invokestatic	#180; //Method scala/util/parsing/combinator/Parsers$class.failure:(Lscala/util/parsing/combinator/Parsers;Ljava/lang/String;)Lscala/util/parsing/combinator/Parsers$Parser;
   5:	areturn
  LineNumberTable: 
   line 29: 0

  LocalVariableTable: 
   Start  Length  Slot  Name   Signature
   0      6      0    this       Lscala/util/parsing/combinator/lexical/Lexical;
   0      6      1    msg       Ljava/lang/String;


public scala.util.parsing.combinator.Parsers$Parser acceptSeq(java.lang.Object, scala.Function1);
  Code:
   Stack=3, Locals=3, Args_size=3
   0:	aload_0
   1:	aload_1
   2:	aload_2
   3:	invokestatic	#185; //Method scala/util/parsing/combinator/Parsers$class.acceptSeq:(Lscala/util/parsing/combinator/Parsers;Ljava/lang/Object;Lscala/Function1;)Lscala/util/parsing/combinator/Parsers$Parser;
   6:	areturn
  LineNumberTable: 
   line 29: 0

  LocalVariableTable: 
   Start  Length  Slot  Name   Signature
   0      7      0    this       Lscala/util/parsing/combinator/lexical/Lexical;
   0      7      1    es       Ljava/lang/Object;
   0      7      2    evidence$2       Lscala/Function1;


public scala.util.parsing.combinator.Parsers$Parser acceptMatch(java.lang.String, scala.PartialFunction);
  Code:
   Stack=3, Locals=3, Args_size=3
   0:	aload_0
   1:	aload_1
   2:	aload_2
   3:	invokestatic	#193; //Method scala/util/parsing/combinator/Parsers$class.acceptMatch:(Lscala/util/parsing/combinator/Parsers;Ljava/lang/String;Lscala/PartialFunction;)Lscala/util/parsing/combinator/Parsers$Parser;
   6:	areturn
  LineNumberTable: 
   line 29: 0

  LocalVariableTable: 
   Start  Length  Slot  Name   Signature
   0      7      0    this       Lscala/util/parsing/combinator/lexical/Lexical;
   0      7      1    expected       Ljava/lang/String;
   0      7      2    f       Lscala/PartialFunction;


public scala.util.parsing.combinator.Parsers$Parser acceptIf(scala.Function1, scala.Function1);
  Code:
   Stack=3, Locals=3, Args_size=3
   0:	aload_0
   1:	aload_1
   2:	aload_2
   3:	invokestatic	#201; //Method scala/util/parsing/combinator/Parsers$class.acceptIf:(Lscala/util/parsing/combinator/Parsers;Lscala/Function1;Lscala/Function1;)Lscala/util/parsing/combinator/Parsers$Parser;
   6:	areturn
  LineNumberTable: 
   line 29: 0

  LocalVariableTable: 
   Start  Length  Slot  Name   Signature
   0      7      0    this       Lscala/util/parsing/combinator/lexical/Lexical;
   0      7      1    p       Lscala/Function1;
   0      7      2    err       Lscala/Function1;


public scala.util.parsing.combinator.Parsers$Parser accept(java.lang.String, scala.PartialFunction);
  Code:
   Stack=3, Locals=3, Args_size=3
   0:	aload_0
   1:	aload_1
   2:	aload_2
   3:	invokestatic	#204; //Method scala/util/parsing/combinator/Parsers$class.accept:(Lscala/util/parsing/combinator/Parsers;Ljava/lang/String;Lscala/PartialFunction;)Lscala/util/parsing/combinator/Parsers$Parser;
   6:	areturn
  LineNumberTable: 
   line 29: 0

  LocalVariableTable: 
   Start  Length  Slot  Name   Signature
   0      7      0    this       Lscala/util/parsing/combinator/lexical/Lexical;
   0      7      1    expected       Ljava/lang/String;
   0      7      2    f       Lscala/PartialFunction;


public scala.util.parsing.combinator.Parsers$Parser accept(java.lang.Object, scala.Function1);
  Code:
   Stack=3, Locals=3, Args_size=3
   0:	aload_0
   1:	aload_1
   2:	aload_2
   3:	invokestatic	#206; //Method scala/util/parsing/combinator/Parsers$class.accept:(Lscala/util/parsing/combinator/Parsers;Ljava/lang/Object;Lscala/Function1;)Lscala/util/parsing/combinator/Parsers$Parser;
   6:	areturn
  LineNumberTable: 
   line 29: 0

  LocalVariableTable: 
   Start  Length  Slot  Name   Signature
   0      7      0    this       Lscala/util/parsing/combinator/lexical/Lexical;
   0      7      1    es       Ljava/lang/Object;
   0      7      2    evidence$1       Lscala/Function1;


public scala.util.parsing.combinator.Parsers$Parser accept(java.lang.Object);
  Code:
   Stack=2, Locals=2, Args_size=2
   0:	aload_0
   1:	aload_1
   2:	invokestatic	#209; //Method scala/util/parsing/combinator/Parsers$class.accept:(Lscala/util/parsing/combinator/Parsers;Ljava/lang/Object;)Lscala/util/parsing/combinator/Parsers$Parser;
   5:	areturn
  LineNumberTable: 
   line 29: 0

  LocalVariableTable: 
   Start  Length  Slot  Name   Signature
   0      6      0    this       Lscala/util/parsing/combinator/lexical/Lexical;
   0      6      1    e       Ljava/lang/Object;


public scala.util.parsing.combinator.Parsers$Parser elem(java.lang.Object);
  Code:
   Stack=2, Locals=2, Args_size=2
   0:	aload_0
   1:	aload_1
   2:	invokestatic	#212; //Method scala/util/parsing/combinator/Parsers$class.elem:(Lscala/util/parsing/combinator/Parsers;Ljava/lang/Object;)Lscala/util/parsing/combinator/Parsers$Parser;
   5:	areturn
  LineNumberTable: 
   line 29: 0

  LocalVariableTable: 
   Start  Length  Slot  Name   Signature
   0      6      0    this       Lscala/util/parsing/combinator/lexical/Lexical;
   0      6      1    e       Ljava/lang/Object;


public scala.util.parsing.combinator.Parsers$Parser elem(java.lang.String, scala.Function1);
  Code:
   Stack=3, Locals=3, Args_size=3
   0:	aload_0
   1:	aload_1
   2:	aload_2
   3:	invokestatic	#215; //Method scala/util/parsing/combinator/Parsers$class.elem:(Lscala/util/parsing/combinator/Parsers;Ljava/lang/String;Lscala/Function1;)Lscala/util/parsing/combinator/Parsers$Parser;
   6:	areturn
  LineNumberTable: 
   line 29: 0

  LocalVariableTable: 
   Start  Length  Slot  Name   Signature
   0      7      0    this       Lscala/util/parsing/combinator/lexical/Lexical;
   0      7      1    kind       Ljava/lang/String;
   0      7      2    p       Lscala/Function1;


public scala.util.parsing.combinator.Parsers$Parser commit(scala.Function0);
  Code:
   Stack=2, Locals=2, Args_size=2
   0:	aload_0
   1:	aload_1
   2:	invokestatic	#219; //Method scala/util/parsing/combinator/Parsers$class.commit:(Lscala/util/parsing/combinator/Parsers;Lscala/Function0;)Lscala/util/parsing/combinator/Parsers$Parser;
   5:	areturn
  LineNumberTable: 
   line 29: 0

  LocalVariableTable: 
   Start  Length  Slot  Name   Signature
   0      6      0    this       Lscala/util/parsing/combinator/lexical/Lexical;
   0      6      1    p       Lscala/Function0;


public scala.util.parsing.combinator.Parsers$Parser OnceParser(scala.Function1);
  Code:
   Stack=2, Locals=2, Args_size=2
   0:	aload_0
   1:	aload_1
   2:	invokestatic	#224; //Method scala/util/parsing/combinator/Parsers$class.OnceParser:(Lscala/util/parsing/combinator/Parsers;Lscala/Function1;)Lscala/util/parsing/combinator/Parsers$Parser;
   5:	areturn
  LineNumberTable: 
   line 29: 0

  LocalVariableTable: 
   Start  Length  Slot  Name   Signature
   0      6      0    this       Lscala/util/parsing/combinator/lexical/Lexical;
   0      6      1    f       Lscala/Function1;


public scala.util.parsing.combinator.Parsers$Parser Parser(scala.Function1);
  Code:
   Stack=2, Locals=2, Args_size=2
   0:	aload_0
   1:	aload_1
   2:	invokestatic	#227; //Method scala/util/parsing/combinator/Parsers$class.Parser:(Lscala/util/parsing/combinator/Parsers;Lscala/Function1;)Lscala/util/parsing/combinator/Parsers$Parser;
   5:	areturn
  LineNumberTable: 
   line 29: 0

  LocalVariableTable: 
   Start  Length  Slot  Name   Signature
   0      6      0    this       Lscala/util/parsing/combinator/lexical/Lexical;
   0      6      1    f       Lscala/Function1;


public final scala.util.parsing.combinator.Parsers$$tilde$ $tilde();
  Code:
   Stack=4, Locals=1, Args_size=1
   0:	aload_0
   1:	getfield	#233; //Field $tilde$module:Lscala/util/parsing/combinator/Parsers$$tilde$;
   4:	ifnonnull	19
   7:	aload_0
   8:	new	#235; //class scala/util/parsing/combinator/Parsers$$tilde$
   11:	dup
   12:	aload_0
   13:	invokespecial	#237; //Method scala/util/parsing/combinator/Parsers$$tilde$."<init>":(Lscala/util/parsing/combinator/Parsers;)V
   16:	putfield	#233; //Field $tilde$module:Lscala/util/parsing/combinator/Parsers$$tilde$;
   19:	aload_0
   20:	getfield	#233; //Field $tilde$module:Lscala/util/parsing/combinator/Parsers$$tilde$;
   23:	areturn
  LineNumberTable: 
   line 29: 0


public final scala.util.parsing.combinator.Parsers$Error$ Error();
  Code:
   Stack=4, Locals=1, Args_size=1
   0:	aload_0
   1:	getfield	#241; //Field Error$module:Lscala/util/parsing/combinator/Parsers$Error$;
   4:	ifnonnull	19
   7:	aload_0
   8:	new	#243; //class scala/util/parsing/combinator/Parsers$Error$
   11:	dup
   12:	aload_0
   13:	invokespecial	#244; //Method scala/util/parsing/combinator/Parsers$Error$."<init>":(Lscala/util/parsing/combinator/Parsers;)V
   16:	putfield	#241; //Field Error$module:Lscala/util/parsing/combinator/Parsers$Error$;
   19:	aload_0
   20:	getfield	#241; //Field Error$module:Lscala/util/parsing/combinator/Parsers$Error$;
   23:	areturn
  LineNumberTable: 
   line 29: 0


public final scala.util.parsing.combinator.Parsers$Failure$ Failure();
  Code:
   Stack=4, Locals=1, Args_size=1
   0:	aload_0
   1:	getfield	#248; //Field Failure$module:Lscala/util/parsing/combinator/Parsers$Failure$;
   4:	ifnonnull	19
   7:	aload_0
   8:	new	#250; //class scala/util/parsing/combinator/Parsers$Failure$
   11:	dup
   12:	aload_0
   13:	invokespecial	#251; //Method scala/util/parsing/combinator/Parsers$Failure$."<init>":(Lscala/util/parsing/combinator/Parsers;)V
   16:	putfield	#248; //Field Failure$module:Lscala/util/parsing/combinator/Parsers$Failure$;
   19:	aload_0
   20:	getfield	#248; //Field Failure$module:Lscala/util/parsing/combinator/Parsers$Failure$;
   23:	areturn
  LineNumberTable: 
   line 29: 0


public final scala.util.parsing.combinator.Parsers$NoSuccess$ NoSuccess();
  Code:
   Stack=4, Locals=1, Args_size=1
   0:	aload_0
   1:	getfield	#255; //Field NoSuccess$module:Lscala/util/parsing/combinator/Parsers$NoSuccess$;
   4:	ifnonnull	19
   7:	aload_0
   8:	new	#257; //class scala/util/parsing/combinator/Parsers$NoSuccess$
   11:	dup
   12:	aload_0
   13:	invokespecial	#258; //Method scala/util/parsing/combinator/Parsers$NoSuccess$."<init>":(Lscala/util/parsing/combinator/Parsers;)V
   16:	putfield	#255; //Field NoSuccess$module:Lscala/util/parsing/combinator/Parsers$NoSuccess$;
   19:	aload_0
   20:	getfield	#255; //Field NoSuccess$module:Lscala/util/parsing/combinator/Parsers$NoSuccess$;
   23:	areturn
  LineNumberTable: 
   line 29: 0


public void lastNoSuccess_$eq(scala.util.parsing.combinator.Parsers$NoSuccess);
  Code:
   Stack=2, Locals=2, Args_size=2
   0:	aload_0
   1:	aload_1
   2:	putfield	#262; //Field lastNoSuccess:Lscala/util/parsing/combinator/Parsers$NoSuccess;
   5:	return
  LineNumberTable: 
   line 29: 0


public scala.util.parsing.combinator.Parsers$NoSuccess lastNoSuccess();
  Code:
   Stack=1, Locals=1, Args_size=1
   0:	aload_0
   1:	getfield	#262; //Field lastNoSuccess:Lscala/util/parsing/combinator/Parsers$NoSuccess;
   4:	areturn
  LineNumberTable: 
   line 29: 0


public final scala.util.parsing.combinator.Parsers$Success$ Success();
  Code:
   Stack=4, Locals=1, Args_size=1
   0:	aload_0
   1:	getfield	#267; //Field Success$module:Lscala/util/parsing/combinator/Parsers$Success$;
   4:	ifnonnull	19
   7:	aload_0
   8:	new	#269; //class scala/util/parsing/combinator/Parsers$Success$
   11:	dup
   12:	aload_0
   13:	invokespecial	#270; //Method scala/util/parsing/combinator/Parsers$Success$."<init>":(Lscala/util/parsing/combinator/Parsers;)V
   16:	putfield	#267; //Field Success$module:Lscala/util/parsing/combinator/Parsers$Success$;
   19:	aload_0
   20:	getfield	#267; //Field Success$module:Lscala/util/parsing/combinator/Parsers$Success$;
   23:	areturn
  LineNumberTable: 
   line 29: 0


public scala.util.parsing.syntax.Tokens$Token errorToken(java.lang.String);
  Code:
   Stack=2, Locals=2, Args_size=2
   0:	aload_0
   1:	aload_1
   2:	invokestatic	#273; //Method scala/util/parsing/syntax/Tokens$class.errorToken:(Lscala/util/parsing/syntax/Tokens;Ljava/lang/String;)Lscala/util/parsing/syntax/Tokens$Token;
   5:	areturn
  LineNumberTable: 
   line 29: 0

  LocalVariableTable: 
   Start  Length  Slot  Name   Signature
   0      6      0    this       Lscala/util/parsing/combinator/lexical/Lexical;
   0      6      1    msg       Ljava/lang/String;


public final scala.util.parsing.syntax.Tokens$EOF$ EOF();
  Code:
   Stack=4, Locals=1, Args_size=1
   0:	aload_0
   1:	getfield	#277; //Field EOF$module:Lscala/util/parsing/syntax/Tokens$EOF$;
   4:	ifnonnull	19
   7:	aload_0
   8:	new	#279; //class scala/util/parsing/syntax/Tokens$EOF$
   11:	dup
   12:	aload_0
   13:	invokespecial	#281; //Method scala/util/parsing/syntax/Tokens$EOF$."<init>":(Lscala/util/parsing/syntax/Tokens;)V
   16:	putfield	#277; //Field EOF$module:Lscala/util/parsing/syntax/Tokens$EOF$;
   19:	aload_0
   20:	getfield	#277; //Field EOF$module:Lscala/util/parsing/syntax/Tokens$EOF$;
   23:	areturn
  LineNumberTable: 
   line 29: 0


public final scala.util.parsing.syntax.Tokens$ErrorToken$ ErrorToken();
  Code:
   Stack=4, Locals=1, Args_size=1
   0:	aload_0
   1:	getfield	#285; //Field ErrorToken$module:Lscala/util/parsing/syntax/Tokens$ErrorToken$;
   4:	ifnonnull	19
   7:	aload_0
   8:	new	#287; //class scala/util/parsing/syntax/Tokens$ErrorToken$
   11:	dup
   12:	aload_0
   13:	invokespecial	#288; //Method scala/util/parsing/syntax/Tokens$ErrorToken$."<init>":(Lscala/util/parsing/syntax/Tokens;)V
   16:	putfield	#285; //Field ErrorToken$module:Lscala/util/parsing/syntax/Tokens$ErrorToken$;
   19:	aload_0
   20:	getfield	#285; //Field ErrorToken$module:Lscala/util/parsing/syntax/Tokens$ErrorToken$;
   23:	areturn
  LineNumberTable: 
   line 29: 0


}

