Compiled from "Lexical.scala"
public final class scala.util.parsing.combinator.lexical.Lexical$$anonfun$chrExcept$1 extends scala.runtime.AbstractFunction1 implements java.io.Serializable
  SourceFile: "Lexical.scala"
  Scala: length = 0x
   
  InnerClass: 
   public final $anonfun$chrExcept$1=class scala/util/parsing/combinator/lexical/Lexical$$anonfun$chrExcept$1 of class scala/util/parsing/combinator/lexical/Lexical
   public final $anonfun$apply$1=class scala/util/parsing/combinator/lexical/Lexical$$anonfun$chrExcept$1$$anonfun$apply$1 of class scala/util/parsing/combinator/lexical/Lexical$$anonfun$chrExcept$1
  minor version: 0
  major version: 49
  Constant pool:
Asciz	SourceFile;
Asciz	Lexical.scala;
Asciz	<clinit>;
Asciz	()V;
Asciz	Code;
Asciz	serialVersionUID;
Asciz	J;
Asciz	scala/util/parsing/combinator/lexical/Lexical$$anonfun$chrExcept$1;
class	scala/util/parsing/combinator/lexical/Lexical$$anonfun$chrExcept$1
NameAndType	serialVersionUID:J
Field	scala/util/parsing/combinator/lexical/Lexical$$anonfun$chrExcept$1.serialVersionUID:J
Asciz	cs$1;
Asciz	Lscala/collection/Seq;;
Asciz	apply;
Asciz	(C)Z;
Asciz	LineNumberTable;
NameAndType	cs$1:Lscala/collection/Seq;
Field	scala/util/parsing/combinator/lexical/Lexical$$anonfun$chrExcept$1.cs$1:Lscala/collection/Seq;
Asciz	scala/util/parsing/combinator/lexical/Lexical$$anonfun$chrExcept$1$$anonfun$apply$1;
class	scala/util/parsing/combinator/lexical/Lexical$$anonfun$chrExcept$1$$anonfun$apply$1
Asciz	<init>;
Asciz	(Lscala/util/parsing/combinator/lexical/Lexical$$anonfun$chrExcept$1;C)V;
NameAndType	"<init>":(Lscala/util/parsing/combinator/lexical/Lexical$$anonfun$chrExcept$1;C)V
Method	scala/util/parsing/combinator/lexical/Lexical$$anonfun$chrExcept$1$$anonfun$apply$1."<init>":(Lscala/util/parsing/combinator/lexical/Lexical$$anonfun$chrExcept$1;C)V
Asciz	scala/collection/IterableLike;
class	scala/collection/IterableLike
Asciz	forall;
Asciz	(Lscala/Function1;)Z;
NameAndType	forall:(Lscala/Function1;)Z
InterfaceMethod	scala/collection/IterableLike.forall:(Lscala/Function1;)Z
Asciz	this;
Asciz	Lscala/util/parsing/combinator/lexical/Lexical$$anonfun$chrExcept$1;;
Asciz	ch$1;
Asciz	C;
Asciz	LocalVariableTable;
Asciz	(Ljava/lang/Object;)Ljava/lang/Object;;
Asciz	scala/runtime/BoxesRunTime;
class	scala/runtime/BoxesRunTime
Asciz	unboxToChar;
Asciz	(Ljava/lang/Object;)C;
NameAndType	unboxToChar:(Ljava/lang/Object;)C
Method	scala/runtime/BoxesRunTime.unboxToChar:(Ljava/lang/Object;)C
NameAndType	apply:(C)Z
Method	scala/util/parsing/combinator/lexical/Lexical$$anonfun$chrExcept$1.apply:(C)Z
Asciz	boxToBoolean;
Asciz	(Z)Ljava/lang/Boolean;;
NameAndType	boxToBoolean:(Z)Ljava/lang/Boolean;
Method	scala/runtime/BoxesRunTime.boxToBoolean:(Z)Ljava/lang/Boolean;
Asciz	v1;
Asciz	Ljava/lang/Object;;
Asciz	(Lscala/util/parsing/combinator/lexical/Lexical;Lscala/collection/Seq;)V;
Asciz	scala/runtime/AbstractFunction1;
class	scala/runtime/AbstractFunction1
NameAndType	"<init>":()V
Method	scala/runtime/AbstractFunction1."<init>":()V
Asciz	$outer;
Asciz	Lscala/util/parsing/combinator/lexical/Lexical;;
Asciz	Scala;
Asciz	InnerClasses;
Asciz	scala/util/parsing/combinator/lexical/Lexical;
class	scala/util/parsing/combinator/lexical/Lexical
Asciz	$anonfun$chrExcept$1;
Asciz	$anonfun$apply$1;
Asciz	java/io/Serializable;
class	java/io/Serializable

{
public static final long serialVersionUID;
  Signature: J

private final scala.collection.Seq cs$1;
  Signature: Lscala/collection/Seq;

public static {};
  Signature: ()V
  Code:
   Stack=2, Locals=0, Args_size=0
	lconst_0
	putstatic	Field serialVersionUID:J
	return
  Labels:

public final boolean apply(char);
  Signature: (C)Z
  Code:
   Stack=5, Locals=2, Args_size=2
	aload_0
	getfield	Field cs$1:Lscala/collection/Seq;
	new	class scala/util/parsing/combinator/lexical/Lexical$$anonfun$chrExcept$1$$anonfun$apply$1
	dup
	aload_0
	iload_1
	invokespecial	Method scala/util/parsing/combinator/lexical/Lexical$$anonfun$chrExcept$1$$anonfun$apply$1."<init>":(Lscala/util/parsing/combinator/lexical/Lexical$$anonfun$chrExcept$1;C)V
	invokeinterface	InterfaceMethod scala/collection/IterableLike.forall:(Lscala/Function1;)Z
	ireturn
  Labels:
  LocalVariableTable: 
   Start  Length  Slot  Name   Signature
   0      19      0    this       Lscala/util/parsing/combinator/lexical/Lexical$$anonfun$chrExcept$1;
   0      19      1    ch$1       C


public final java.lang.Object apply(java.lang.Object);
  Signature: (Ljava/lang/Object;)Ljava/lang/Object;
  Code:
   Stack=2, Locals=2, Args_size=2
	aload_0
	aload_1
	invokestatic	Method scala/runtime/BoxesRunTime.unboxToChar:(Ljava/lang/Object;)C
	invokevirtual	Method apply:(C)Z
	invokestatic	Method scala/runtime/BoxesRunTime.boxToBoolean:(Z)Ljava/lang/Boolean;
	areturn
  Labels:
  LocalVariableTable: 
   Start  Length  Slot  Name   Signature
   0      12      0    this       Lscala/util/parsing/combinator/lexical/Lexical$$anonfun$chrExcept$1;
   0      12      1    v1       Ljava/lang/Object;


public scala.util.parsing.combinator.lexical.Lexical$$anonfun$chrExcept$1(scala.util.parsing.combinator.lexical.Lexical, scala.collection.Seq);
  Signature: (Lscala/util/parsing/combinator/lexical/Lexical;Lscala/collection/Seq;)V
  Code:
   Stack=2, Locals=3, Args_size=3
	aload_0
	aload_2
	putfield	Field cs$1:Lscala/collection/Seq;
	aload_0
	invokespecial	Method scala/runtime/AbstractFunction1."<init>":()V
	return
  Labels:
  LocalVariableTable: 
   Start  Length  Slot  Name   Signature
   0      10      0    this       Lscala/util/parsing/combinator/lexical/Lexical$$anonfun$chrExcept$1;
   0      10      1    $outer       Lscala/util/parsing/combinator/lexical/Lexical;


}

