Compiled from "Scanners.scala"
public class scala.util.parsing.combinator.lexical.Scanners$Scanner extends scala.util.parsing.input.Reader implements scala.ScalaObject
  SourceFile: "Scanners.scala"
  Signature: length = 0x2
   00 FFFFFFB3 
  Scala: length = 0x
   
  InnerClass: 
   public abstract #184= #40 of #183; //Parser=class scala/util/parsing/combinator/Parsers$Parser of class scala/util/parsing/combinator/Parsers
   public #185= #46 of #183; //Success=class scala/util/parsing/combinator/Parsers$Success of class scala/util/parsing/combinator/Parsers
   public #186= #20 of #34; //Scanner=class scala/util/parsing/combinator/lexical/Scanners$Scanner of class scala/util/parsing/combinator/lexical/Scanners
   public abstract #187= #75 of #183; //NoSuccess=class scala/util/parsing/combinator/Parsers$NoSuccess of class scala/util/parsing/combinator/Parsers
   public abstract #188= #66 of #183; //ParseResult=class scala/util/parsing/combinator/Parsers$ParseResult of class scala/util/parsing/combinator/Parsers
  minor version: 0
  major version: 49
  Constant pool:
const #1 = Asciz	SourceFile;
const #2 = Asciz	Scanners.scala;
const #3 = Asciz	$outer;
const #4 = Asciz	Lscala/util/parsing/combinator/lexical/Scanners;;
const #5 = Asciz	rest2;
const #6 = Asciz	Lscala/util/parsing/input/Reader;;
const #7 = Asciz	Lscala/util/parsing/input/Reader<Ljava/lang/Character;>;;
const #8 = Asciz	Signature;
const #9 = Asciz	rest1;
const #10 = Asciz	tok;
const #11 = Asciz	Ljava/lang/Object;;
const #12 = Asciz	x$1;
const #13 = Asciz	Lscala/Tuple3;;
const #14 = Asciz	in;
const #15 = Asciz	<init>;
const #16 = Asciz	(Lscala/util/parsing/combinator/lexical/Scanners;Lscala/util/parsing/input/Reader;)V;
const #17 = Asciz	Code;
const #18 = Asciz	LineNumberTable;
const #19 = Asciz	scala/util/parsing/combinator/lexical/Scanners$Scanner;
const #20 = class	#19;	//  scala/util/parsing/combinator/lexical/Scanners$Scanner
const #21 = NameAndType	#14:#6;//  in:Lscala/util/parsing/input/Reader;
const #22 = Field	#20.#21;	//  scala/util/parsing/combinator/lexical/Scanners$Scanner.in:Lscala/util/parsing/input/Reader;
const #23 = Asciz	java/lang/NullPointerException;
const #24 = class	#23;	//  java/lang/NullPointerException
const #25 = Asciz	()V;
const #26 = NameAndType	#15:#25;//  "<init>":()V
const #27 = Method	#24.#26;	//  java/lang/NullPointerException."<init>":()V
const #28 = NameAndType	#3:#4;//  $outer:Lscala/util/parsing/combinator/lexical/Scanners;
const #29 = Field	#20.#28;	//  scala/util/parsing/combinator/lexical/Scanners$Scanner.$outer:Lscala/util/parsing/combinator/lexical/Scanners;
const #30 = Asciz	scala/util/parsing/input/Reader;
const #31 = class	#30;	//  scala/util/parsing/input/Reader
const #32 = Method	#31.#26;	//  scala/util/parsing/input/Reader."<init>":()V
const #33 = Asciz	scala/util/parsing/combinator/lexical/Scanners;
const #34 = class	#33;	//  scala/util/parsing/combinator/lexical/Scanners
const #35 = Asciz	whitespace;
const #36 = Asciz	()Lscala/util/parsing/combinator/Parsers$Parser;;
const #37 = NameAndType	#35:#36;//  whitespace:()Lscala/util/parsing/combinator/Parsers$Parser;
const #38 = InterfaceMethod	#34.#37;	//  scala/util/parsing/combinator/lexical/Scanners.whitespace:()Lscala/util/parsing/combinator/Parsers$Parser;
const #39 = Asciz	scala/util/parsing/combinator/Parsers$Parser;
const #40 = class	#39;	//  scala/util/parsing/combinator/Parsers$Parser
const #41 = Asciz	apply;
const #42 = Asciz	(Lscala/util/parsing/input/Reader;)Lscala/util/parsing/combinator/Parsers$ParseResult;;
const #43 = NameAndType	#41:#42;//  apply:(Lscala/util/parsing/input/Reader;)Lscala/util/parsing/combinator/Parsers$ParseResult;
const #44 = Method	#40.#43;	//  scala/util/parsing/combinator/Parsers$Parser.apply:(Lscala/util/parsing/input/Reader;)Lscala/util/parsing/combinator/Parsers$ParseResult;
const #45 = Asciz	scala/util/parsing/combinator/Parsers$Success;
const #46 = class	#45;	//  scala/util/parsing/combinator/Parsers$Success
const #47 = Asciz	next;
const #48 = Asciz	()Lscala/util/parsing/input/Reader;;
const #49 = NameAndType	#47:#48;//  next:()Lscala/util/parsing/input/Reader;
const #50 = Method	#46.#49;	//  scala/util/parsing/combinator/Parsers$Success.next:()Lscala/util/parsing/input/Reader;
const #51 = Asciz	token;
const #52 = NameAndType	#51:#36;//  token:()Lscala/util/parsing/combinator/Parsers$Parser;
const #53 = InterfaceMethod	#34.#52;	//  scala/util/parsing/combinator/lexical/Scanners.token:()Lscala/util/parsing/combinator/Parsers$Parser;
const #54 = Asciz	result;
const #55 = Asciz	()Ljava/lang/Object;;
const #56 = NameAndType	#54:#55;//  result:()Ljava/lang/Object;
const #57 = Method	#46.#56;	//  scala/util/parsing/combinator/Parsers$Success.result:()Ljava/lang/Object;
const #58 = Asciz	scala/Tuple3;
const #59 = class	#58;	//  scala/Tuple3
const #60 = Asciz	(Ljava/lang/Object;Ljava/lang/Object;Ljava/lang/Object;)V;
const #61 = NameAndType	#15:#60;//  "<init>":(Ljava/lang/Object;Ljava/lang/Object;Ljava/lang/Object;)V
const #62 = Method	#59.#61;	//  scala/Tuple3."<init>":(Ljava/lang/Object;Ljava/lang/Object;Ljava/lang/Object;)V
const #63 = Asciz	scala/MatchError;
const #64 = class	#63;	//  scala/MatchError
const #65 = Asciz	scala/util/parsing/combinator/Parsers$ParseResult;
const #66 = class	#65;	//  scala/util/parsing/combinator/Parsers$ParseResult
const #67 = Asciz	toString;
const #68 = Asciz	()Ljava/lang/String;;
const #69 = NameAndType	#67:#68;//  toString:()Ljava/lang/String;
const #70 = Method	#66.#69;	//  scala/util/parsing/combinator/Parsers$ParseResult.toString:()Ljava/lang/String;
const #71 = Asciz	(Ljava/lang/String;)V;
const #72 = NameAndType	#15:#71;//  "<init>":(Ljava/lang/String;)V
const #73 = Method	#64.#72;	//  scala/MatchError."<init>":(Ljava/lang/String;)V
const #74 = Asciz	scala/util/parsing/combinator/Parsers$NoSuccess;
const #75 = class	#74;	//  scala/util/parsing/combinator/Parsers$NoSuccess
const #76 = Asciz	msg;
const #77 = NameAndType	#76:#68;//  msg:()Ljava/lang/String;
const #78 = Method	#75.#77;	//  scala/util/parsing/combinator/Parsers$NoSuccess.msg:()Ljava/lang/String;
const #79 = Asciz	errorToken;
const #80 = Asciz	(Ljava/lang/String;)Ljava/lang/Object;;
const #81 = NameAndType	#79:#80;//  errorToken:(Ljava/lang/String;)Ljava/lang/Object;
const #82 = InterfaceMethod	#34.#81;	//  scala/util/parsing/combinator/lexical/Scanners.errorToken:(Ljava/lang/String;)Ljava/lang/Object;
const #83 = Method	#75.#49;	//  scala/util/parsing/combinator/Parsers$NoSuccess.next:()Lscala/util/parsing/input/Reader;
const #84 = Asciz	skip;
const #85 = Asciz	(Lscala/util/parsing/input/Reader;)Lscala/util/parsing/input/Reader;;
const #86 = NameAndType	#84:#85;//  skip:(Lscala/util/parsing/input/Reader;)Lscala/util/parsing/input/Reader;
const #87 = Method	#20.#86;	//  scala/util/parsing/combinator/lexical/Scanners$Scanner.skip:(Lscala/util/parsing/input/Reader;)Lscala/util/parsing/input/Reader;
const #88 = Asciz	_1;
const #89 = NameAndType	#88:#55;//  _1:()Ljava/lang/Object;
const #90 = Method	#59.#89;	//  scala/Tuple3._1:()Ljava/lang/Object;
const #91 = Asciz	_2;
const #92 = NameAndType	#91:#55;//  _2:()Ljava/lang/Object;
const #93 = Method	#59.#92;	//  scala/Tuple3._2:()Ljava/lang/Object;
const #94 = Asciz	_3;
const #95 = NameAndType	#94:#55;//  _3:()Ljava/lang/Object;
const #96 = Method	#59.#95;	//  scala/Tuple3._3:()Ljava/lang/Object;
const #97 = NameAndType	#12:#13;//  x$1:Lscala/Tuple3;
const #98 = Field	#20.#97;	//  scala/util/parsing/combinator/lexical/Scanners$Scanner.x$1:Lscala/Tuple3;
const #99 = NameAndType	#10:#11;//  tok:Ljava/lang/Object;
const #100 = Field	#20.#99;	//  scala/util/parsing/combinator/lexical/Scanners$Scanner.tok:Ljava/lang/Object;
const #101 = NameAndType	#9:#6;//  rest1:Lscala/util/parsing/input/Reader;
const #102 = Field	#20.#101;	//  scala/util/parsing/combinator/lexical/Scanners$Scanner.rest1:Lscala/util/parsing/input/Reader;
const #103 = NameAndType	#5:#6;//  rest2:Lscala/util/parsing/input/Reader;
const #104 = Field	#20.#103;	//  scala/util/parsing/combinator/lexical/Scanners$Scanner.rest2:Lscala/util/parsing/input/Reader;
const #105 = Method	#59.#69;	//  scala/Tuple3.toString:()Ljava/lang/String;
const #106 = Asciz	this;
const #107 = Asciz	Lscala/util/parsing/combinator/lexical/Scanners$Scanner;;
const #108 = Asciz	temp7;
const #109 = Asciz	Lscala/util/parsing/combinator/Parsers$Success;;
const #110 = Asciz	temp2;
const #111 = Asciz	temp3;
const #112 = Asciz	temp9;
const #113 = Asciz	temp4;
const #114 = Asciz	temp5;
const #115 = Asciz	Lscala/util/parsing/combinator/Parsers$NoSuccess;;
const #116 = Asciz	temp1;
const #117 = Asciz	Lscala/util/parsing/combinator/Parsers$ParseResult;;
const #118 = Asciz	temp10;
const #119 = Asciz	temp12;
const #120 = Asciz	temp13;
const #121 = Asciz	temp14;
const #122 = Asciz	temp11;
const #123 = Asciz	temp6;
const #124 = Asciz	LocalVariableTable;
const #125 = Asciz	(Lscala/util/parsing/combinator/lexical/Scanners;Lscala/util/parsing/input/Reader<Ljava/lang/Character;>;)V;
const #126 = Asciz	rest;
const #127 = Asciz	()Lscala/util/parsing/combinator/lexical/Scanners$Scanner;;
const #128 = NameAndType	#126:#127;//  rest:()Lscala/util/parsing/combinator/lexical/Scanners$Scanner;
const #129 = Method	#20.#128;	//  scala/util/parsing/combinator/lexical/Scanners$Scanner.rest:()Lscala/util/parsing/combinator/lexical/Scanners$Scanner;
const #130 = Asciz	scala$util$parsing$combinator$lexical$Scanners$Scanner$$$outer;
const #131 = Asciz	()Lscala/util/parsing/combinator/lexical/Scanners;;
const #132 = Asciz	atEnd;
const #133 = Asciz	()Z;
const #134 = NameAndType	#132:#133;//  atEnd:()Z
const #135 = Method	#31.#134;	//  scala/util/parsing/input/Reader.atEnd:()Z
const #136 = NameAndType	#130:#131;//  scala$util$parsing$combinator$lexical$Scanners$Scanner$$$outer:()Lscala/util/parsing/combinator/lexical/Scanners;
const #137 = Method	#20.#136;	//  scala/util/parsing/combinator/lexical/Scanners$Scanner.scala$util$parsing$combinator$lexical$Scanners$Scanner$$$outer:()Lscala/util/parsing/combinator/lexical/Scanners;
const #138 = Asciz	temp16;
const #139 = Asciz	temp18;
const #140 = Asciz	temp15;
const #141 = Asciz	pos;
const #142 = Asciz	()Lscala/util/parsing/input/Position;;
const #143 = NameAndType	#9:#48;//  rest1:()Lscala/util/parsing/input/Reader;
const #144 = Method	#20.#143;	//  scala/util/parsing/combinator/lexical/Scanners$Scanner.rest1:()Lscala/util/parsing/input/Reader;
const #145 = NameAndType	#141:#142;//  pos:()Lscala/util/parsing/input/Position;
const #146 = Method	#31.#145;	//  scala/util/parsing/input/Reader.pos:()Lscala/util/parsing/input/Position;
const #147 = NameAndType	#5:#48;//  rest2:()Lscala/util/parsing/input/Reader;
const #148 = Method	#20.#147;	//  scala/util/parsing/combinator/lexical/Scanners$Scanner.rest2:()Lscala/util/parsing/input/Reader;
const #149 = NameAndType	#15:#16;//  "<init>":(Lscala/util/parsing/combinator/lexical/Scanners;Lscala/util/parsing/input/Reader;)V
const #150 = Method	#20.#149;	//  scala/util/parsing/combinator/lexical/Scanners$Scanner."<init>":(Lscala/util/parsing/combinator/lexical/Scanners;Lscala/util/parsing/input/Reader;)V
const #151 = Asciz	first;
const #152 = NameAndType	#10:#55;//  tok:()Ljava/lang/Object;
const #153 = Method	#20.#152;	//  scala/util/parsing/combinator/lexical/Scanners$Scanner.tok:()Ljava/lang/Object;
const #154 = Asciz	offset;
const #155 = Asciz	()I;
const #156 = NameAndType	#154:#155;//  offset:()I
const #157 = Method	#31.#156;	//  scala/util/parsing/input/Reader.offset:()I
const #158 = Asciz	source;
const #159 = Asciz	()Ljava/lang/CharSequence;;
const #160 = NameAndType	#158:#159;//  source:()Ljava/lang/CharSequence;
const #161 = Method	#31.#160;	//  scala/util/parsing/input/Reader.source:()Ljava/lang/CharSequence;
const #162 = NameAndType	#126:#48;//  rest:()Lscala/util/parsing/input/Reader;
const #163 = Method	#31.#162;	//  scala/util/parsing/input/Reader.rest:()Lscala/util/parsing/input/Reader;
const #164 = Asciz	(Lscala/util/parsing/input/Reader<Ljava/lang/Character;>;)Lscala/util/parsing/input/Reader<Ljava/lang/Character;>;;
const #165 = Asciz	()Lscala/util/parsing/input/Reader<Ljava/lang/Character;>;;
const #166 = Asciz	(Lscala/util/parsing/combinator/lexical/Scanners;Ljava/lang/String;)V;
const #167 = Asciz	scala/util/parsing/input/CharArrayReader;
const #168 = class	#167;	//  scala/util/parsing/input/CharArrayReader
const #169 = Asciz	java/lang/String;
const #170 = class	#169;	//  java/lang/String
const #171 = Asciz	toCharArray;
const #172 = Asciz	()[C;
const #173 = NameAndType	#171:#172;//  toCharArray:()[C
const #174 = Method	#170.#173;	//  java/lang/String.toCharArray:()[C
const #175 = Asciz	([C)V;
const #176 = NameAndType	#15:#175;//  "<init>":([C)V
const #177 = Method	#168.#176;	//  scala/util/parsing/input/CharArrayReader."<init>":([C)V
const #178 = Asciz	Ljava/lang/String;;
const #179 = Asciz	Lscala/util/parsing/input/Reader<Ljava/lang/Object;>;Lscala/ScalaObject;;
const #180 = Asciz	Scala;
const #181 = Asciz	InnerClasses;
const #182 = Asciz	scala/util/parsing/combinator/Parsers;
const #183 = class	#182;	//  scala/util/parsing/combinator/Parsers
const #184 = Asciz	Parser;
const #185 = Asciz	Success;
const #186 = Asciz	Scanner;
const #187 = Asciz	NoSuccess;
const #188 = Asciz	ParseResult;
const #189 = Asciz	scala/ScalaObject;
const #190 = class	#189;	//  scala/ScalaObject

{
public final scala.util.parsing.combinator.lexical.Scanners $outer;

public scala.util.parsing.combinator.lexical.Scanners$Scanner(scala.util.parsing.combinator.lexical.Scanners, scala.util.parsing.input.Reader);
  Code:
   Stack=7, Locals=16, Args_size=3
   0:	aload_0
   1:	aload_2
   2:	putfield	#22; //Field in:Lscala/util/parsing/input/Reader;
   5:	aload_1
   6:	ifnonnull	17
   9:	new	#24; //class java/lang/NullPointerException
   12:	dup
   13:	invokespecial	#27; //Method java/lang/NullPointerException."<init>":()V
   16:	athrow
   17:	aload_0
   18:	aload_1
   19:	putfield	#29; //Field $outer:Lscala/util/parsing/combinator/lexical/Scanners;
   22:	aload_0
   23:	invokespecial	#32; //Method scala/util/parsing/input/Reader."<init>":()V
   26:	aload_0
   27:	aload_1
   28:	invokeinterface	#38,  1; //InterfaceMethod scala/util/parsing/combinator/lexical/Scanners.whitespace:()Lscala/util/parsing/combinator/Parsers$Parser;
   33:	aload_2
   34:	invokevirtual	#44; //Method scala/util/parsing/combinator/Parsers$Parser.apply:(Lscala/util/parsing/input/Reader;)Lscala/util/parsing/combinator/Parsers$ParseResult;
   37:	astore	15
   39:	aload	15
   41:	instanceof	#46; //class scala/util/parsing/combinator/Parsers$Success
   44:	ifeq	231
   47:	aload	15
   49:	checkcast	#46; //class scala/util/parsing/combinator/Parsers$Success
   52:	astore_3
   53:	aload_3
   54:	invokevirtual	#50; //Method scala/util/parsing/combinator/Parsers$Success.next:()Lscala/util/parsing/input/Reader;
   57:	astore	6
   59:	iconst_1
   60:	ifeq	218
   63:	aload_1
   64:	invokeinterface	#53,  1; //InterfaceMethod scala/util/parsing/combinator/lexical/Scanners.token:()Lscala/util/parsing/combinator/Parsers$Parser;
   69:	aload	6
   71:	invokevirtual	#44; //Method scala/util/parsing/combinator/Parsers$Parser.apply:(Lscala/util/parsing/input/Reader;)Lscala/util/parsing/combinator/Parsers$ParseResult;
   74:	astore	9
   76:	aload	9
   78:	instanceof	#46; //class scala/util/parsing/combinator/Parsers$Success
   81:	ifeq	138
   84:	aload	9
   86:	checkcast	#46; //class scala/util/parsing/combinator/Parsers$Success
   89:	astore	4
   91:	aload	4
   93:	invokevirtual	#57; //Method scala/util/parsing/combinator/Parsers$Success.result:()Ljava/lang/Object;
   96:	astore	5
   98:	aload	4
   100:	invokevirtual	#50; //Method scala/util/parsing/combinator/Parsers$Success.next:()Lscala/util/parsing/input/Reader;
   103:	astore	7
   105:	iconst_1
   106:	ifeq	125
   109:	new	#59; //class scala/Tuple3
   112:	dup
   113:	aload	5
   115:	aload	6
   117:	aload	7
   119:	invokespecial	#62; //Method scala/Tuple3."<init>":(Ljava/lang/Object;Ljava/lang/Object;Ljava/lang/Object;)V
   122:	goto	282
   125:	new	#64; //class scala/MatchError
   128:	dup
   129:	aload	9
   131:	invokevirtual	#70; //Method scala/util/parsing/combinator/Parsers$ParseResult.toString:()Ljava/lang/String;
   134:	invokespecial	#73; //Method scala/MatchError."<init>":(Ljava/lang/String;)V
   137:	athrow
   138:	aload	9
   140:	instanceof	#75; //class scala/util/parsing/combinator/Parsers$NoSuccess
   143:	ifeq	205
   146:	aload	9
   148:	checkcast	#75; //class scala/util/parsing/combinator/Parsers$NoSuccess
   151:	astore	8
   153:	iconst_1
   154:	ifeq	192
   157:	new	#59; //class scala/Tuple3
   160:	dup
   161:	aload_1
   162:	aload	8
   164:	invokevirtual	#78; //Method scala/util/parsing/combinator/Parsers$NoSuccess.msg:()Ljava/lang/String;
   167:	invokeinterface	#82,  2; //InterfaceMethod scala/util/parsing/combinator/lexical/Scanners.errorToken:(Ljava/lang/String;)Ljava/lang/Object;
   172:	aload	8
   174:	invokevirtual	#83; //Method scala/util/parsing/combinator/Parsers$NoSuccess.next:()Lscala/util/parsing/input/Reader;
   177:	aload_0
   178:	aload	8
   180:	invokevirtual	#83; //Method scala/util/parsing/combinator/Parsers$NoSuccess.next:()Lscala/util/parsing/input/Reader;
   183:	invokespecial	#87; //Method skip:(Lscala/util/parsing/input/Reader;)Lscala/util/parsing/input/Reader;
   186:	invokespecial	#62; //Method scala/Tuple3."<init>":(Ljava/lang/Object;Ljava/lang/Object;Ljava/lang/Object;)V
   189:	goto	282
   192:	new	#64; //class scala/MatchError
   195:	dup
   196:	aload	9
   198:	invokevirtual	#70; //Method scala/util/parsing/combinator/Parsers$ParseResult.toString:()Ljava/lang/String;
   201:	invokespecial	#73; //Method scala/MatchError."<init>":(Ljava/lang/String;)V
   204:	athrow
   205:	new	#64; //class scala/MatchError
   208:	dup
   209:	aload	9
   211:	invokevirtual	#70; //Method scala/util/parsing/combinator/Parsers$ParseResult.toString:()Ljava/lang/String;
   214:	invokespecial	#73; //Method scala/MatchError."<init>":(Ljava/lang/String;)V
   217:	athrow
   218:	new	#64; //class scala/MatchError
   221:	dup
   222:	aload	15
   224:	invokevirtual	#70; //Method scala/util/parsing/combinator/Parsers$ParseResult.toString:()Ljava/lang/String;
   227:	invokespecial	#73; //Method scala/MatchError."<init>":(Ljava/lang/String;)V
   230:	athrow
   231:	aload	15
   233:	instanceof	#75; //class scala/util/parsing/combinator/Parsers$NoSuccess
   236:	ifeq	415
   239:	aload	15
   241:	checkcast	#75; //class scala/util/parsing/combinator/Parsers$NoSuccess
   244:	astore	10
   246:	iconst_1
   247:	ifeq	402
   250:	new	#59; //class scala/Tuple3
   253:	dup
   254:	aload_1
   255:	aload	10
   257:	invokevirtual	#78; //Method scala/util/parsing/combinator/Parsers$NoSuccess.msg:()Ljava/lang/String;
   260:	invokeinterface	#82,  2; //InterfaceMethod scala/util/parsing/combinator/lexical/Scanners.errorToken:(Ljava/lang/String;)Ljava/lang/Object;
   265:	aload	10
   267:	invokevirtual	#83; //Method scala/util/parsing/combinator/Parsers$NoSuccess.next:()Lscala/util/parsing/input/Reader;
   270:	aload_0
   271:	aload	10
   273:	invokevirtual	#83; //Method scala/util/parsing/combinator/Parsers$NoSuccess.next:()Lscala/util/parsing/input/Reader;
   276:	invokespecial	#87; //Method skip:(Lscala/util/parsing/input/Reader;)Lscala/util/parsing/input/Reader;
   279:	invokespecial	#62; //Method scala/Tuple3."<init>":(Ljava/lang/Object;Ljava/lang/Object;Ljava/lang/Object;)V
   282:	astore	14
   284:	aload	14
   286:	ifnull	389
   289:	aload	14
   291:	invokevirtual	#90; //Method scala/Tuple3._1:()Ljava/lang/Object;
   294:	astore	11
   296:	aload	14
   298:	invokevirtual	#93; //Method scala/Tuple3._2:()Ljava/lang/Object;
   301:	checkcast	#31; //class scala/util/parsing/input/Reader
   304:	astore	12
   306:	aload	14
   308:	invokevirtual	#96; //Method scala/Tuple3._3:()Ljava/lang/Object;
   311:	checkcast	#31; //class scala/util/parsing/input/Reader
   314:	astore	13
   316:	iconst_1
   317:	ifeq	376
   320:	new	#59; //class scala/Tuple3
   323:	dup
   324:	aload	11
   326:	aload	12
   328:	aload	13
   330:	invokespecial	#62; //Method scala/Tuple3."<init>":(Ljava/lang/Object;Ljava/lang/Object;Ljava/lang/Object;)V
   333:	putfield	#98; //Field x$1:Lscala/Tuple3;
   336:	aload_0
   337:	aload_0
   338:	getfield	#98; //Field x$1:Lscala/Tuple3;
   341:	invokevirtual	#90; //Method scala/Tuple3._1:()Ljava/lang/Object;
   344:	putfield	#100; //Field tok:Ljava/lang/Object;
   347:	aload_0
   348:	aload_0
   349:	getfield	#98; //Field x$1:Lscala/Tuple3;
   352:	invokevirtual	#93; //Method scala/Tuple3._2:()Ljava/lang/Object;
   355:	checkcast	#31; //class scala/util/parsing/input/Reader
   358:	putfield	#102; //Field rest1:Lscala/util/parsing/input/Reader;
   361:	aload_0
   362:	aload_0
   363:	getfield	#98; //Field x$1:Lscala/Tuple3;
   366:	invokevirtual	#96; //Method scala/Tuple3._3:()Ljava/lang/Object;
   369:	checkcast	#31; //class scala/util/parsing/input/Reader
   372:	putfield	#104; //Field rest2:Lscala/util/parsing/input/Reader;
   375:	return
   376:	new	#64; //class scala/MatchError
   379:	dup
   380:	aload	14
   382:	invokevirtual	#105; //Method scala/Tuple3.toString:()Ljava/lang/String;
   385:	invokespecial	#73; //Method scala/MatchError."<init>":(Ljava/lang/String;)V
   388:	athrow
   389:	new	#64; //class scala/MatchError
   392:	dup
   393:	aload	14
   395:	invokevirtual	#105; //Method scala/Tuple3.toString:()Ljava/lang/String;
   398:	invokespecial	#73; //Method scala/MatchError."<init>":(Ljava/lang/String;)V
   401:	athrow
   402:	new	#64; //class scala/MatchError
   405:	dup
   406:	aload	15
   408:	invokevirtual	#70; //Method scala/util/parsing/combinator/Parsers$ParseResult.toString:()Ljava/lang/String;
   411:	invokespecial	#73; //Method scala/MatchError."<init>":(Ljava/lang/String;)V
   414:	athrow
   415:	new	#64; //class scala/MatchError
   418:	dup
   419:	aload	15
   421:	invokevirtual	#70; //Method scala/util/parsing/combinator/Parsers$ParseResult.toString:()Ljava/lang/String;
   424:	invokespecial	#73; //Method scala/MatchError."<init>":(Ljava/lang/String;)V
   427:	athrow
  LineNumberTable: 
   line 57: 0
   line 60: 26
   line 21: 59
   line 62: 63
   line 60: 84
   line 21: 105
   line 63: 109
   line 62: 125
   line 60: 146
   line 21: 153
   line 64: 157
   line 62: 192
   line 60: 218
   line 21: 246
   line 66: 250
   line 60: 282
   line 21: 316
   line 60: 320

  LocalVariableTable: 
   Start  Length  Slot  Name   Signature
   0      428      0    this       Lscala/util/parsing/combinator/lexical/Scanners$Scanner;
   0      428      1    $outer       Lscala/util/parsing/combinator/lexical/Scanners;
   0      428      2    in       Lscala/util/parsing/input/Reader;
   53      178      3    temp7       Lscala/util/parsing/combinator/Parsers$Success;
   91      47      4    temp2       Lscala/util/parsing/combinator/Parsers$Success;
   98      40      5    temp3       Ljava/lang/Object;
   59      172      6    temp9       Lscala/util/parsing/input/Reader;
   105      33      7    temp4       Lscala/util/parsing/input/Reader;
   153      52      8    temp5       Lscala/util/parsing/combinator/Parsers$NoSuccess;
   76      142      9    temp1       Lscala/util/parsing/combinator/Parsers$ParseResult;
   246      36      10    temp10       Lscala/util/parsing/combinator/Parsers$NoSuccess;
   402      13      10    temp10       Lscala/util/parsing/combinator/Parsers$NoSuccess;
   296      37      11    temp12       Ljava/lang/Object;
   376      13      11    temp12       Ljava/lang/Object;
   306      27      12    temp13       Lscala/util/parsing/input/Reader;
   376      13      12    temp13       Lscala/util/parsing/input/Reader;
   316      17      13    temp14       Lscala/util/parsing/input/Reader;
   376      13      13    temp14       Lscala/util/parsing/input/Reader;
   284      118      14    temp11       Lscala/Tuple3;
   39      250      15    temp6       Lscala/util/parsing/combinator/Parsers$ParseResult;
   402      26      15    temp6       Lscala/util/parsing/combinator/Parsers$ParseResult;

  Signature: length = 0x2
   00 7D 

public scala.util.parsing.input.Reader rest();
  Code:
   Stack=1, Locals=1, Args_size=1
   0:	aload_0
   1:	invokevirtual	#129; //Method rest:()Lscala/util/parsing/combinator/lexical/Scanners$Scanner;
   4:	areturn
  LineNumberTable: 
   line 57: 0


public scala.util.parsing.combinator.lexical.Scanners scala$util$parsing$combinator$lexical$Scanners$Scanner$$$outer();
  Code:
   Stack=1, Locals=1, Args_size=1
   0:	aload_0
   1:	getfield	#29; //Field $outer:Lscala/util/parsing/combinator/lexical/Scanners;
   4:	areturn
  LineNumberTable: 
   line 57: 0


public boolean atEnd();
  Code:
   Stack=3, Locals=4, Args_size=1
   0:	aload_0
   1:	getfield	#22; //Field in:Lscala/util/parsing/input/Reader;
   4:	invokevirtual	#135; //Method scala/util/parsing/input/Reader.atEnd:()Z
   7:	ifne	75
   10:	aload_0
   11:	invokevirtual	#137; //Method scala$util$parsing$combinator$lexical$Scanners$Scanner$$$outer:()Lscala/util/parsing/combinator/lexical/Scanners;
   14:	invokeinterface	#38,  1; //InterfaceMethod scala/util/parsing/combinator/lexical/Scanners.whitespace:()Lscala/util/parsing/combinator/Parsers$Parser;
   19:	aload_0
   20:	getfield	#22; //Field in:Lscala/util/parsing/input/Reader;
   23:	invokevirtual	#44; //Method scala/util/parsing/combinator/Parsers$Parser.apply:(Lscala/util/parsing/input/Reader;)Lscala/util/parsing/combinator/Parsers$ParseResult;
   26:	astore_3
   27:	aload_3
   28:	instanceof	#46; //class scala/util/parsing/combinator/Parsers$Success
   31:	ifeq	67
   34:	aload_3
   35:	checkcast	#46; //class scala/util/parsing/combinator/Parsers$Success
   38:	astore_1
   39:	aload_1
   40:	invokevirtual	#50; //Method scala/util/parsing/combinator/Parsers$Success.next:()Lscala/util/parsing/input/Reader;
   43:	astore_2
   44:	iconst_1
   45:	ifeq	55
   48:	aload_2
   49:	invokevirtual	#135; //Method scala/util/parsing/input/Reader.atEnd:()Z
   52:	goto	72
   55:	new	#64; //class scala/MatchError
   58:	dup
   59:	aload_3
   60:	invokevirtual	#70; //Method scala/util/parsing/combinator/Parsers$ParseResult.toString:()Ljava/lang/String;
   63:	invokespecial	#73; //Method scala/MatchError."<init>":(Ljava/lang/String;)V
   66:	athrow
   67:	iconst_1
   68:	ifeq	81
   71:	iconst_0
   72:	ifeq	79
   75:	iconst_1
   76:	goto	80
   79:	iconst_0
   80:	ireturn
   81:	new	#64; //class scala/MatchError
   84:	dup
   85:	aload_3
   86:	invokevirtual	#70; //Method scala/util/parsing/combinator/Parsers$ParseResult.toString:()Ljava/lang/String;
   89:	invokespecial	#73; //Method scala/MatchError."<init>":(Ljava/lang/String;)V
   92:	athrow
  LineNumberTable: 
   line 75: 0
   line 21: 44
   line 75: 48
   line 21: 67
   line 75: 71

  LocalVariableTable: 
   Start  Length  Slot  Name   Signature
   0      93      0    this       Lscala/util/parsing/combinator/lexical/Scanners$Scanner;
   39      28      1    temp16       Lscala/util/parsing/combinator/Parsers$Success;
   44      23      2    temp18       Lscala/util/parsing/input/Reader;
   27      48      3    temp15       Lscala/util/parsing/combinator/Parsers$ParseResult;
   81      12      3    temp15       Lscala/util/parsing/combinator/Parsers$ParseResult;


public scala.util.parsing.input.Position pos();
  Code:
   Stack=1, Locals=1, Args_size=1
   0:	aload_0
   1:	invokespecial	#144; //Method rest1:()Lscala/util/parsing/input/Reader;
   4:	invokevirtual	#146; //Method scala/util/parsing/input/Reader.pos:()Lscala/util/parsing/input/Position;
   7:	areturn
  LineNumberTable: 
   line 74: 0


public scala.util.parsing.combinator.lexical.Scanners$Scanner rest();
  Code:
   Stack=4, Locals=1, Args_size=1
   0:	new	#20; //class scala/util/parsing/combinator/lexical/Scanners$Scanner
   3:	dup
   4:	aload_0
   5:	invokevirtual	#137; //Method scala$util$parsing$combinator$lexical$Scanners$Scanner$$$outer:()Lscala/util/parsing/combinator/lexical/Scanners;
   8:	aload_0
   9:	invokespecial	#148; //Method rest2:()Lscala/util/parsing/input/Reader;
   12:	invokespecial	#150; //Method "<init>":(Lscala/util/parsing/combinator/lexical/Scanners;Lscala/util/parsing/input/Reader;)V
   15:	areturn
  LineNumberTable: 
   line 73: 0


public java.lang.Object first();
  Code:
   Stack=1, Locals=1, Args_size=1
   0:	aload_0
   1:	invokespecial	#153; //Method tok:()Ljava/lang/Object;
   4:	areturn
  LineNumberTable: 
   line 72: 0


public int offset();
  Code:
   Stack=1, Locals=1, Args_size=1
   0:	aload_0
   1:	getfield	#22; //Field in:Lscala/util/parsing/input/Reader;
   4:	invokevirtual	#157; //Method scala/util/parsing/input/Reader.offset:()I
   7:	ireturn
  LineNumberTable: 
   line 71: 0


public java.lang.CharSequence source();
  Code:
   Stack=1, Locals=1, Args_size=1
   0:	aload_0
   1:	getfield	#22; //Field in:Lscala/util/parsing/input/Reader;
   4:	invokevirtual	#161; //Method scala/util/parsing/input/Reader.source:()Ljava/lang/CharSequence;
   7:	areturn
  LineNumberTable: 
   line 70: 0


public scala.util.parsing.combinator.lexical.Scanners$Scanner(scala.util.parsing.combinator.lexical.Scanners, java.lang.String);
  Code:
   Stack=5, Locals=3, Args_size=3
   0:	aload_0
   1:	aload_1
   2:	new	#168; //class scala/util/parsing/input/CharArrayReader
   5:	dup
   6:	aload_2
   7:	invokevirtual	#174; //Method java/lang/String.toCharArray:()[C
   10:	invokespecial	#177; //Method scala/util/parsing/input/CharArrayReader."<init>":([C)V
   13:	invokespecial	#150; //Method "<init>":(Lscala/util/parsing/combinator/lexical/Scanners;Lscala/util/parsing/input/Reader;)V
   16:	return
  LineNumberTable: 
   line 59: 0

  LocalVariableTable: 
   Start  Length  Slot  Name   Signature
   0      17      0    this       Lscala/util/parsing/combinator/lexical/Scanners$Scanner;
   0      17      1    $outer       Lscala/util/parsing/combinator/lexical/Scanners;
   0      17      2    in       Ljava/lang/String;


}

