Compiled from "Scanners.scala"
public class scala.util.parsing.combinator.lexical.Scanners$Scanner extends scala.util.parsing.input.Reader implements scala.ScalaObject
  SourceFile: "Scanners.scala"
  Signature: length = 0x2
   00 FFFFFFB3 
  Scala: length = 0x
   
  InnerClass: 
   public abstract Parser=class scala/util/parsing/combinator/Parsers$Parser of class scala/util/parsing/combinator/Parsers
   public Success=class scala/util/parsing/combinator/Parsers$Success of class scala/util/parsing/combinator/Parsers
   public Scanner=class scala/util/parsing/combinator/lexical/Scanners$Scanner of class scala/util/parsing/combinator/lexical/Scanners
   public abstract NoSuccess=class scala/util/parsing/combinator/Parsers$NoSuccess of class scala/util/parsing/combinator/Parsers
   public abstract ParseResult=class scala/util/parsing/combinator/Parsers$ParseResult of class scala/util/parsing/combinator/Parsers
  minor version: 0
  major version: 49
  Constant pool:
Asciz	SourceFile;
Asciz	Scanners.scala;
Asciz	$outer;
Asciz	Lscala/util/parsing/combinator/lexical/Scanners;;
Asciz	rest2;
Asciz	Lscala/util/parsing/input/Reader;;
Asciz	Lscala/util/parsing/input/Reader<Ljava/lang/Character;>;;
Asciz	Signature;
Asciz	rest1;
Asciz	tok;
Asciz	Ljava/lang/Object;;
Asciz	x$1;
Asciz	Lscala/Tuple3;;
Asciz	in;
Asciz	<init>;
Asciz	(Lscala/util/parsing/combinator/lexical/Scanners;Lscala/util/parsing/input/Reader;)V;
Asciz	Code;
Asciz	LineNumberTable;
Asciz	scala/util/parsing/combinator/lexical/Scanners$Scanner;
class	scala/util/parsing/combinator/lexical/Scanners$Scanner
NameAndType	in:Lscala/util/parsing/input/Reader;
Field	scala/util/parsing/combinator/lexical/Scanners$Scanner.in:Lscala/util/parsing/input/Reader;
Asciz	java/lang/NullPointerException;
class	java/lang/NullPointerException
Asciz	()V;
NameAndType	"<init>":()V
Method	java/lang/NullPointerException."<init>":()V
NameAndType	$outer:Lscala/util/parsing/combinator/lexical/Scanners;
Field	scala/util/parsing/combinator/lexical/Scanners$Scanner.$outer:Lscala/util/parsing/combinator/lexical/Scanners;
Asciz	scala/util/parsing/input/Reader;
class	scala/util/parsing/input/Reader
Method	scala/util/parsing/input/Reader."<init>":()V
Asciz	scala/util/parsing/combinator/lexical/Scanners;
class	scala/util/parsing/combinator/lexical/Scanners
Asciz	whitespace;
Asciz	()Lscala/util/parsing/combinator/Parsers$Parser;;
NameAndType	whitespace:()Lscala/util/parsing/combinator/Parsers$Parser;
InterfaceMethod	scala/util/parsing/combinator/lexical/Scanners.whitespace:()Lscala/util/parsing/combinator/Parsers$Parser;
Asciz	scala/util/parsing/combinator/Parsers$Parser;
class	scala/util/parsing/combinator/Parsers$Parser
Asciz	apply;
Asciz	(Lscala/util/parsing/input/Reader;)Lscala/util/parsing/combinator/Parsers$ParseResult;;
NameAndType	apply:(Lscala/util/parsing/input/Reader;)Lscala/util/parsing/combinator/Parsers$ParseResult;
Method	scala/util/parsing/combinator/Parsers$Parser.apply:(Lscala/util/parsing/input/Reader;)Lscala/util/parsing/combinator/Parsers$ParseResult;
Asciz	scala/util/parsing/combinator/Parsers$Success;
class	scala/util/parsing/combinator/Parsers$Success
Asciz	next;
Asciz	()Lscala/util/parsing/input/Reader;;
NameAndType	next:()Lscala/util/parsing/input/Reader;
Method	scala/util/parsing/combinator/Parsers$Success.next:()Lscala/util/parsing/input/Reader;
Asciz	token;
NameAndType	token:()Lscala/util/parsing/combinator/Parsers$Parser;
InterfaceMethod	scala/util/parsing/combinator/lexical/Scanners.token:()Lscala/util/parsing/combinator/Parsers$Parser;
Asciz	result;
Asciz	()Ljava/lang/Object;;
NameAndType	result:()Ljava/lang/Object;
Method	scala/util/parsing/combinator/Parsers$Success.result:()Ljava/lang/Object;
Asciz	scala/Tuple3;
class	scala/Tuple3
Asciz	(Ljava/lang/Object;Ljava/lang/Object;Ljava/lang/Object;)V;
NameAndType	"<init>":(Ljava/lang/Object;Ljava/lang/Object;Ljava/lang/Object;)V
Method	scala/Tuple3."<init>":(Ljava/lang/Object;Ljava/lang/Object;Ljava/lang/Object;)V
Asciz	scala/MatchError;
class	scala/MatchError
Asciz	scala/util/parsing/combinator/Parsers$ParseResult;
class	scala/util/parsing/combinator/Parsers$ParseResult
Asciz	toString;
Asciz	()Ljava/lang/String;;
NameAndType	toString:()Ljava/lang/String;
Method	scala/util/parsing/combinator/Parsers$ParseResult.toString:()Ljava/lang/String;
Asciz	(Ljava/lang/String;)V;
NameAndType	"<init>":(Ljava/lang/String;)V
Method	scala/MatchError."<init>":(Ljava/lang/String;)V
Asciz	scala/util/parsing/combinator/Parsers$NoSuccess;
class	scala/util/parsing/combinator/Parsers$NoSuccess
Asciz	msg;
NameAndType	msg:()Ljava/lang/String;
Method	scala/util/parsing/combinator/Parsers$NoSuccess.msg:()Ljava/lang/String;
Asciz	errorToken;
Asciz	(Ljava/lang/String;)Ljava/lang/Object;;
NameAndType	errorToken:(Ljava/lang/String;)Ljava/lang/Object;
InterfaceMethod	scala/util/parsing/combinator/lexical/Scanners.errorToken:(Ljava/lang/String;)Ljava/lang/Object;
Method	scala/util/parsing/combinator/Parsers$NoSuccess.next:()Lscala/util/parsing/input/Reader;
Asciz	skip;
Asciz	(Lscala/util/parsing/input/Reader;)Lscala/util/parsing/input/Reader;;
NameAndType	skip:(Lscala/util/parsing/input/Reader;)Lscala/util/parsing/input/Reader;
Method	scala/util/parsing/combinator/lexical/Scanners$Scanner.skip:(Lscala/util/parsing/input/Reader;)Lscala/util/parsing/input/Reader;
Asciz	_1;
NameAndType	_1:()Ljava/lang/Object;
Method	scala/Tuple3._1:()Ljava/lang/Object;
Asciz	_2;
NameAndType	_2:()Ljava/lang/Object;
Method	scala/Tuple3._2:()Ljava/lang/Object;
Asciz	_3;
NameAndType	_3:()Ljava/lang/Object;
Method	scala/Tuple3._3:()Ljava/lang/Object;
NameAndType	x$1:Lscala/Tuple3;
Field	scala/util/parsing/combinator/lexical/Scanners$Scanner.x$1:Lscala/Tuple3;
NameAndType	tok:Ljava/lang/Object;
Field	scala/util/parsing/combinator/lexical/Scanners$Scanner.tok:Ljava/lang/Object;
NameAndType	rest1:Lscala/util/parsing/input/Reader;
Field	scala/util/parsing/combinator/lexical/Scanners$Scanner.rest1:Lscala/util/parsing/input/Reader;
NameAndType	rest2:Lscala/util/parsing/input/Reader;
Field	scala/util/parsing/combinator/lexical/Scanners$Scanner.rest2:Lscala/util/parsing/input/Reader;
Method	scala/Tuple3.toString:()Ljava/lang/String;
Asciz	this;
Asciz	Lscala/util/parsing/combinator/lexical/Scanners$Scanner;;
Asciz	temp7;
Asciz	Lscala/util/parsing/combinator/Parsers$Success;;
Asciz	temp2;
Asciz	temp3;
Asciz	temp9;
Asciz	temp4;
Asciz	temp5;
Asciz	Lscala/util/parsing/combinator/Parsers$NoSuccess;;
Asciz	temp1;
Asciz	Lscala/util/parsing/combinator/Parsers$ParseResult;;
Asciz	temp10;
Asciz	temp12;
Asciz	temp13;
Asciz	temp14;
Asciz	temp11;
Asciz	temp6;
Asciz	LocalVariableTable;
Asciz	(Lscala/util/parsing/combinator/lexical/Scanners;Lscala/util/parsing/input/Reader<Ljava/lang/Character;>;)V;
Asciz	rest;
Asciz	()Lscala/util/parsing/combinator/lexical/Scanners$Scanner;;
NameAndType	rest:()Lscala/util/parsing/combinator/lexical/Scanners$Scanner;
Method	scala/util/parsing/combinator/lexical/Scanners$Scanner.rest:()Lscala/util/parsing/combinator/lexical/Scanners$Scanner;
Asciz	scala$util$parsing$combinator$lexical$Scanners$Scanner$$$outer;
Asciz	()Lscala/util/parsing/combinator/lexical/Scanners;;
Asciz	atEnd;
Asciz	()Z;
NameAndType	atEnd:()Z
Method	scala/util/parsing/input/Reader.atEnd:()Z
NameAndType	scala$util$parsing$combinator$lexical$Scanners$Scanner$$$outer:()Lscala/util/parsing/combinator/lexical/Scanners;
Method	scala/util/parsing/combinator/lexical/Scanners$Scanner.scala$util$parsing$combinator$lexical$Scanners$Scanner$$$outer:()Lscala/util/parsing/combinator/lexical/Scanners;
Asciz	temp16;
Asciz	temp18;
Asciz	temp15;
Asciz	pos;
Asciz	()Lscala/util/parsing/input/Position;;
NameAndType	rest1:()Lscala/util/parsing/input/Reader;
Method	scala/util/parsing/combinator/lexical/Scanners$Scanner.rest1:()Lscala/util/parsing/input/Reader;
NameAndType	pos:()Lscala/util/parsing/input/Position;
Method	scala/util/parsing/input/Reader.pos:()Lscala/util/parsing/input/Position;
NameAndType	rest2:()Lscala/util/parsing/input/Reader;
Method	scala/util/parsing/combinator/lexical/Scanners$Scanner.rest2:()Lscala/util/parsing/input/Reader;
NameAndType	"<init>":(Lscala/util/parsing/combinator/lexical/Scanners;Lscala/util/parsing/input/Reader;)V
Method	scala/util/parsing/combinator/lexical/Scanners$Scanner."<init>":(Lscala/util/parsing/combinator/lexical/Scanners;Lscala/util/parsing/input/Reader;)V
Asciz	first;
NameAndType	tok:()Ljava/lang/Object;
Method	scala/util/parsing/combinator/lexical/Scanners$Scanner.tok:()Ljava/lang/Object;
Asciz	offset;
Asciz	()I;
NameAndType	offset:()I
Method	scala/util/parsing/input/Reader.offset:()I
Asciz	source;
Asciz	()Ljava/lang/CharSequence;;
NameAndType	source:()Ljava/lang/CharSequence;
Method	scala/util/parsing/input/Reader.source:()Ljava/lang/CharSequence;
NameAndType	rest:()Lscala/util/parsing/input/Reader;
Method	scala/util/parsing/input/Reader.rest:()Lscala/util/parsing/input/Reader;
Asciz	(Lscala/util/parsing/input/Reader<Ljava/lang/Character;>;)Lscala/util/parsing/input/Reader<Ljava/lang/Character;>;;
Asciz	()Lscala/util/parsing/input/Reader<Ljava/lang/Character;>;;
Asciz	(Lscala/util/parsing/combinator/lexical/Scanners;Ljava/lang/String;)V;
Asciz	scala/util/parsing/input/CharArrayReader;
class	scala/util/parsing/input/CharArrayReader
Asciz	java/lang/String;
class	java/lang/String
Asciz	toCharArray;
Asciz	()[C;
NameAndType	toCharArray:()[C
Method	java/lang/String.toCharArray:()[C
Asciz	([C)V;
NameAndType	"<init>":([C)V
Method	scala/util/parsing/input/CharArrayReader."<init>":([C)V
Asciz	Ljava/lang/String;;
Asciz	Lscala/util/parsing/input/Reader<Ljava/lang/Object;>;Lscala/ScalaObject;;
Asciz	Scala;
Asciz	InnerClasses;
Asciz	scala/util/parsing/combinator/Parsers;
class	scala/util/parsing/combinator/Parsers
Asciz	Parser;
Asciz	Success;
Asciz	Scanner;
Asciz	NoSuccess;
Asciz	ParseResult;
Asciz	scala/ScalaObject;
class	scala/ScalaObject

{
public final scala.util.parsing.combinator.lexical.Scanners $outer;
  Signature: Lscala/util/parsing/combinator/lexical/Scanners;

private final scala.util.parsing.input.Reader rest2;
  Signature: Lscala/util/parsing/input/Reader;
  Signature: length = 0x2
   00 07 

private final scala.util.parsing.input.Reader rest1;
  Signature: Lscala/util/parsing/input/Reader;
  Signature: length = 0x2
   00 07 

private final java.lang.Object tok;
  Signature: Ljava/lang/Object;

private final scala.Tuple3 x$1;
  Signature: Lscala/Tuple3;

private final scala.util.parsing.input.Reader in;
  Signature: Lscala/util/parsing/input/Reader;
  Signature: length = 0x2
   00 07 

public scala.util.parsing.combinator.lexical.Scanners$Scanner(scala.util.parsing.combinator.lexical.Scanners, scala.util.parsing.input.Reader);
  Signature: (Lscala/util/parsing/combinator/lexical/Scanners;Lscala/util/parsing/input/Reader;)V
  Code:
   Stack=7, Locals=16, Args_size=3
	aload_0
	aload_2
	putfield	Field in:Lscala/util/parsing/input/Reader;
	aload_1
	ifnonnull	l1 // aload_0
	new	class java/lang/NullPointerException
	dup
	invokespecial	Method java/lang/NullPointerException."<init>":()V
	athrow
l1	aload_0
	aload_1
	putfield	Field $outer:Lscala/util/parsing/combinator/lexical/Scanners;
	aload_0
	invokespecial	Method scala/util/parsing/input/Reader."<init>":()V
	aload_0
	aload_1
	invokeinterface	InterfaceMethod scala/util/parsing/combinator/lexical/Scanners.whitespace:()Lscala/util/parsing/combinator/Parsers$Parser;
	aload_2
	invokevirtual	Method scala/util/parsing/combinator/Parsers$Parser.apply:(Lscala/util/parsing/input/Reader;)Lscala/util/parsing/combinator/Parsers$ParseResult;
	astore	15
	aload	15
	instanceof	class scala/util/parsing/combinator/Parsers$Success
	ifeq	l2 // aload
	aload	15
	checkcast	class scala/util/parsing/combinator/Parsers$Success
	astore_3
	aload_3
	invokevirtual	Method scala/util/parsing/combinator/Parsers$Success.next:()Lscala/util/parsing/input/Reader;
	astore	6
	iconst_1
	ifeq	l3 // new
	aload_1
	invokeinterface	InterfaceMethod scala/util/parsing/combinator/lexical/Scanners.token:()Lscala/util/parsing/combinator/Parsers$Parser;
	aload	6
	invokevirtual	Method scala/util/parsing/combinator/Parsers$Parser.apply:(Lscala/util/parsing/input/Reader;)Lscala/util/parsing/combinator/Parsers$ParseResult;
	astore	9
	aload	9
	instanceof	class scala/util/parsing/combinator/Parsers$Success
	ifeq	l4 // aload
	aload	9
	checkcast	class scala/util/parsing/combinator/Parsers$Success
	astore	4
	aload	4
	invokevirtual	Method scala/util/parsing/combinator/Parsers$Success.result:()Ljava/lang/Object;
	astore	5
	aload	4
	invokevirtual	Method scala/util/parsing/combinator/Parsers$Success.next:()Lscala/util/parsing/input/Reader;
	astore	7
	iconst_1
	ifeq	l5 // new
	new	class scala/Tuple3
	dup
	aload	5
	aload	6
	aload	7
	invokespecial	Method scala/Tuple3."<init>":(Ljava/lang/Object;Ljava/lang/Object;Ljava/lang/Object;)V
	goto	l6 // astore
l5	new	class scala/MatchError
	dup
	aload	9
	invokevirtual	Method scala/util/parsing/combinator/Parsers$ParseResult.toString:()Ljava/lang/String;
	invokespecial	Method scala/MatchError."<init>":(Ljava/lang/String;)V
	athrow
l4	aload	9
	instanceof	class scala/util/parsing/combinator/Parsers$NoSuccess
	ifeq	l7 // new
	aload	9
	checkcast	class scala/util/parsing/combinator/Parsers$NoSuccess
	astore	8
	iconst_1
	ifeq	l8 // new
	new	class scala/Tuple3
	dup
	aload_1
	aload	8
	invokevirtual	Method scala/util/parsing/combinator/Parsers$NoSuccess.msg:()Ljava/lang/String;
	invokeinterface	InterfaceMethod scala/util/parsing/combinator/lexical/Scanners.errorToken:(Ljava/lang/String;)Ljava/lang/Object;
	aload	8
	invokevirtual	Method scala/util/parsing/combinator/Parsers$NoSuccess.next:()Lscala/util/parsing/input/Reader;
	aload_0
	aload	8
	invokevirtual	Method scala/util/parsing/combinator/Parsers$NoSuccess.next:()Lscala/util/parsing/input/Reader;
	invokespecial	Method skip:(Lscala/util/parsing/input/Reader;)Lscala/util/parsing/input/Reader;
	invokespecial	Method scala/Tuple3."<init>":(Ljava/lang/Object;Ljava/lang/Object;Ljava/lang/Object;)V
	goto	l6 // astore
l8	new	class scala/MatchError
	dup
	aload	9
	invokevirtual	Method scala/util/parsing/combinator/Parsers$ParseResult.toString:()Ljava/lang/String;
	invokespecial	Method scala/MatchError."<init>":(Ljava/lang/String;)V
	athrow
l7	new	class scala/MatchError
	dup
	aload	9
	invokevirtual	Method scala/util/parsing/combinator/Parsers$ParseResult.toString:()Ljava/lang/String;
	invokespecial	Method scala/MatchError."<init>":(Ljava/lang/String;)V
	athrow
l3	new	class scala/MatchError
	dup
	aload	15
	invokevirtual	Method scala/util/parsing/combinator/Parsers$ParseResult.toString:()Ljava/lang/String;
	invokespecial	Method scala/MatchError."<init>":(Ljava/lang/String;)V
	athrow
l2	aload	15
	instanceof	class scala/util/parsing/combinator/Parsers$NoSuccess
	ifeq	l9 // new
	aload	15
	checkcast	class scala/util/parsing/combinator/Parsers$NoSuccess
	astore	10
	iconst_1
	ifeq	l10 // new
	new	class scala/Tuple3
	dup
	aload_1
	aload	10
	invokevirtual	Method scala/util/parsing/combinator/Parsers$NoSuccess.msg:()Ljava/lang/String;
	invokeinterface	InterfaceMethod scala/util/parsing/combinator/lexical/Scanners.errorToken:(Ljava/lang/String;)Ljava/lang/Object;
	aload	10
	invokevirtual	Method scala/util/parsing/combinator/Parsers$NoSuccess.next:()Lscala/util/parsing/input/Reader;
	aload_0
	aload	10
	invokevirtual	Method scala/util/parsing/combinator/Parsers$NoSuccess.next:()Lscala/util/parsing/input/Reader;
	invokespecial	Method skip:(Lscala/util/parsing/input/Reader;)Lscala/util/parsing/input/Reader;
	invokespecial	Method scala/Tuple3."<init>":(Ljava/lang/Object;Ljava/lang/Object;Ljava/lang/Object;)V
l6	astore	14
	aload	14
	ifnull	l11 // new
	aload	14
	invokevirtual	Method scala/Tuple3._1:()Ljava/lang/Object;
	astore	11
	aload	14
	invokevirtual	Method scala/Tuple3._2:()Ljava/lang/Object;
	checkcast	class scala/util/parsing/input/Reader
	astore	12
	aload	14
	invokevirtual	Method scala/Tuple3._3:()Ljava/lang/Object;
	checkcast	class scala/util/parsing/input/Reader
	astore	13
	iconst_1
	ifeq	l12 // new
	new	class scala/Tuple3
	dup
	aload	11
	aload	12
	aload	13
	invokespecial	Method scala/Tuple3."<init>":(Ljava/lang/Object;Ljava/lang/Object;Ljava/lang/Object;)V
	putfield	Field x$1:Lscala/Tuple3;
	aload_0
	aload_0
	getfield	Field x$1:Lscala/Tuple3;
	invokevirtual	Method scala/Tuple3._1:()Ljava/lang/Object;
	putfield	Field tok:Ljava/lang/Object;
	aload_0
	aload_0
	getfield	Field x$1:Lscala/Tuple3;
	invokevirtual	Method scala/Tuple3._2:()Ljava/lang/Object;
	checkcast	class scala/util/parsing/input/Reader
	putfield	Field rest1:Lscala/util/parsing/input/Reader;
	aload_0
	aload_0
	getfield	Field x$1:Lscala/Tuple3;
	invokevirtual	Method scala/Tuple3._3:()Ljava/lang/Object;
	checkcast	class scala/util/parsing/input/Reader
	putfield	Field rest2:Lscala/util/parsing/input/Reader;
	return
l12	new	class scala/MatchError
	dup
	aload	14
	invokevirtual	Method scala/Tuple3.toString:()Ljava/lang/String;
	invokespecial	Method scala/MatchError."<init>":(Ljava/lang/String;)V
	athrow
l11	new	class scala/MatchError
	dup
	aload	14
	invokevirtual	Method scala/Tuple3.toString:()Ljava/lang/String;
	invokespecial	Method scala/MatchError."<init>":(Ljava/lang/String;)V
	athrow
l10	new	class scala/MatchError
	dup
	aload	15
	invokevirtual	Method scala/util/parsing/combinator/Parsers$ParseResult.toString:()Ljava/lang/String;
	invokespecial	Method scala/MatchError."<init>":(Ljava/lang/String;)V
	athrow
l9	new	class scala/MatchError
	dup
	aload	15
	invokevirtual	Method scala/util/parsing/combinator/Parsers$ParseResult.toString:()Ljava/lang/String;
	invokespecial	Method scala/MatchError."<init>":(Ljava/lang/String;)V
	athrow
  Labels:
   	l1 = 17 // aload_0
   	l5 = 125 // new
   	l4 = 138 // aload
   	l8 = 192 // new
   	l7 = 205 // new
   	l3 = 218 // new
   	l2 = 231 // aload
   	l6 = 282 // astore
   	l12 = 376 // new
   	l11 = 389 // new
   	l10 = 402 // new
   	l9 = 415 // new
  LocalVariableTable: 
   Start  Length  Slot  Name   Signature
   0      428      0    this       Lscala/util/parsing/combinator/lexical/Scanners$Scanner;
   0      428      1    $outer       Lscala/util/parsing/combinator/lexical/Scanners;
   0      428      2    in       Lscala/util/parsing/input/Reader;
   53      178      3    temp7       Lscala/util/parsing/combinator/Parsers$Success;
   91      47      4    temp2       Lscala/util/parsing/combinator/Parsers$Success;
   98      40      5    temp3       Ljava/lang/Object;
   59      172      6    temp9       Lscala/util/parsing/input/Reader;
   105      33      7    temp4       Lscala/util/parsing/input/Reader;
   153      52      8    temp5       Lscala/util/parsing/combinator/Parsers$NoSuccess;
   76      142      9    temp1       Lscala/util/parsing/combinator/Parsers$ParseResult;
   246      36      10    temp10       Lscala/util/parsing/combinator/Parsers$NoSuccess;
   402      13      10    temp10       Lscala/util/parsing/combinator/Parsers$NoSuccess;
   296      37      11    temp12       Ljava/lang/Object;
   376      13      11    temp12       Ljava/lang/Object;
   306      27      12    temp13       Lscala/util/parsing/input/Reader;
   376      13      12    temp13       Lscala/util/parsing/input/Reader;
   316      17      13    temp14       Lscala/util/parsing/input/Reader;
   376      13      13    temp14       Lscala/util/parsing/input/Reader;
   284      118      14    temp11       Lscala/Tuple3;
   39      250      15    temp6       Lscala/util/parsing/combinator/Parsers$ParseResult;
   402      26      15    temp6       Lscala/util/parsing/combinator/Parsers$ParseResult;

  Signature: length = 0x2
   00 7D 

public scala.util.parsing.input.Reader rest();
  Signature: ()Lscala/util/parsing/input/Reader;
  Code:
   Stack=1, Locals=1, Args_size=1
	aload_0
	invokevirtual	Method rest:()Lscala/util/parsing/combinator/lexical/Scanners$Scanner;
	areturn
  Labels:

public scala.util.parsing.combinator.lexical.Scanners scala$util$parsing$combinator$lexical$Scanners$Scanner$$$outer();
  Signature: ()Lscala/util/parsing/combinator/lexical/Scanners;
  Code:
   Stack=1, Locals=1, Args_size=1
	aload_0
	getfield	Field $outer:Lscala/util/parsing/combinator/lexical/Scanners;
	areturn
  Labels:

public boolean atEnd();
  Signature: ()Z
  Code:
   Stack=3, Locals=4, Args_size=1
	aload_0
	getfield	Field in:Lscala/util/parsing/input/Reader;
	invokevirtual	Method scala/util/parsing/input/Reader.atEnd:()Z
	ifne	l1 // iconst_1
	aload_0
	invokevirtual	Method scala$util$parsing$combinator$lexical$Scanners$Scanner$$$outer:()Lscala/util/parsing/combinator/lexical/Scanners;
	invokeinterface	InterfaceMethod scala/util/parsing/combinator/lexical/Scanners.whitespace:()Lscala/util/parsing/combinator/Parsers$Parser;
	aload_0
	getfield	Field in:Lscala/util/parsing/input/Reader;
	invokevirtual	Method scala/util/parsing/combinator/Parsers$Parser.apply:(Lscala/util/parsing/input/Reader;)Lscala/util/parsing/combinator/Parsers$ParseResult;
	astore_3
	aload_3
	instanceof	class scala/util/parsing/combinator/Parsers$Success
	ifeq	l2 // iconst_1
	aload_3
	checkcast	class scala/util/parsing/combinator/Parsers$Success
	astore_1
	aload_1
	invokevirtual	Method scala/util/parsing/combinator/Parsers$Success.next:()Lscala/util/parsing/input/Reader;
	astore_2
	iconst_1
	ifeq	l3 // new
	aload_2
	invokevirtual	Method scala/util/parsing/input/Reader.atEnd:()Z
	goto	l4 // ifeq
l3	new	class scala/MatchError
	dup
	aload_3
	invokevirtual	Method scala/util/parsing/combinator/Parsers$ParseResult.toString:()Ljava/lang/String;
	invokespecial	Method scala/MatchError."<init>":(Ljava/lang/String;)V
	athrow
l2	iconst_1
	ifeq	l5 // new
	iconst_0
l4	ifeq	l6 // iconst_0
l1	iconst_1
	goto	l7 // ireturn
l6	iconst_0
l7	ireturn
l5	new	class scala/MatchError
	dup
	aload_3
	invokevirtual	Method scala/util/parsing/combinator/Parsers$ParseResult.toString:()Ljava/lang/String;
	invokespecial	Method scala/MatchError."<init>":(Ljava/lang/String;)V
	athrow
  Labels:
   	l3 = 55 // new
   	l2 = 67 // iconst_1
   	l4 = 72 // ifeq
   	l1 = 75 // iconst_1
   	l6 = 79 // iconst_0
   	l7 = 80 // ireturn
   	l5 = 81 // new
  LocalVariableTable: 
   Start  Length  Slot  Name   Signature
   0      93      0    this       Lscala/util/parsing/combinator/lexical/Scanners$Scanner;
   39      28      1    temp16       Lscala/util/parsing/combinator/Parsers$Success;
   44      23      2    temp18       Lscala/util/parsing/input/Reader;
   27      48      3    temp15       Lscala/util/parsing/combinator/Parsers$ParseResult;
   81      12      3    temp15       Lscala/util/parsing/combinator/Parsers$ParseResult;


public scala.util.parsing.input.Position pos();
  Signature: ()Lscala/util/parsing/input/Position;
  Code:
   Stack=1, Locals=1, Args_size=1
	aload_0
	invokespecial	Method rest1:()Lscala/util/parsing/input/Reader;
	invokevirtual	Method scala/util/parsing/input/Reader.pos:()Lscala/util/parsing/input/Position;
	areturn
  Labels:

public scala.util.parsing.combinator.lexical.Scanners$Scanner rest();
  Signature: ()Lscala/util/parsing/combinator/lexical/Scanners$Scanner;
  Code:
   Stack=4, Locals=1, Args_size=1
	new	class scala/util/parsing/combinator/lexical/Scanners$Scanner
	dup
	aload_0
	invokevirtual	Method scala$util$parsing$combinator$lexical$Scanners$Scanner$$$outer:()Lscala/util/parsing/combinator/lexical/Scanners;
	aload_0
	invokespecial	Method rest2:()Lscala/util/parsing/input/Reader;
	invokespecial	Method "<init>":(Lscala/util/parsing/combinator/lexical/Scanners;Lscala/util/parsing/input/Reader;)V
	areturn
  Labels:

public java.lang.Object first();
  Signature: ()Ljava/lang/Object;
  Code:
   Stack=1, Locals=1, Args_size=1
	aload_0
	invokespecial	Method tok:()Ljava/lang/Object;
	areturn
  Labels:

public int offset();
  Signature: ()I
  Code:
   Stack=1, Locals=1, Args_size=1
	aload_0
	getfield	Field in:Lscala/util/parsing/input/Reader;
	invokevirtual	Method scala/util/parsing/input/Reader.offset:()I
	ireturn
  Labels:

public java.lang.CharSequence source();
  Signature: ()Ljava/lang/CharSequence;
  Code:
   Stack=1, Locals=1, Args_size=1
	aload_0
	getfield	Field in:Lscala/util/parsing/input/Reader;
	invokevirtual	Method scala/util/parsing/input/Reader.source:()Ljava/lang/CharSequence;
	areturn
  Labels:

private scala.util.parsing.input.Reader skip(scala.util.parsing.input.Reader);
  Signature: (Lscala/util/parsing/input/Reader;)Lscala/util/parsing/input/Reader;
  Code:
   Stack=1, Locals=2, Args_size=2
	aload_1
	invokevirtual	Method scala/util/parsing/input/Reader.atEnd:()Z
	ifeq	l1 // aload_1
	aload_1
	goto	l2 // areturn
l1	aload_1
	invokevirtual	Method scala/util/parsing/input/Reader.rest:()Lscala/util/parsing/input/Reader;
l2	areturn
  Labels:
   	l1 = 11 // aload_1
   	l2 = 15 // areturn
  LocalVariableTable: 
   Start  Length  Slot  Name   Signature
   0      16      0    this       Lscala/util/parsing/combinator/lexical/Scanners$Scanner;
   0      16      1    in       Lscala/util/parsing/input/Reader;

  Signature: length = 0x2
   00 FFFFFFA4 

private scala.util.parsing.input.Reader rest2();
  Signature: ()Lscala/util/parsing/input/Reader;
  Code:
   Stack=1, Locals=1, Args_size=1
	aload_0
	getfield	Field rest2:Lscala/util/parsing/input/Reader;
	areturn
  Labels:
  Signature: length = 0x2
   00 FFFFFFA5 

private scala.util.parsing.input.Reader rest1();
  Signature: ()Lscala/util/parsing/input/Reader;
  Code:
   Stack=1, Locals=1, Args_size=1
	aload_0
	getfield	Field rest1:Lscala/util/parsing/input/Reader;
	areturn
  Labels:
  Signature: length = 0x2
   00 FFFFFFA5 

private java.lang.Object tok();
  Signature: ()Ljava/lang/Object;
  Code:
   Stack=1, Locals=1, Args_size=1
	aload_0
	getfield	Field tok:Ljava/lang/Object;
	areturn
  Labels:

public scala.util.parsing.combinator.lexical.Scanners$Scanner(scala.util.parsing.combinator.lexical.Scanners, java.lang.String);
  Signature: (Lscala/util/parsing/combinator/lexical/Scanners;Ljava/lang/String;)V
  Code:
   Stack=5, Locals=3, Args_size=3
	aload_0
	aload_1
	new	class scala/util/parsing/input/CharArrayReader
	dup
	aload_2
	invokevirtual	Method java/lang/String.toCharArray:()[C
	invokespecial	Method scala/util/parsing/input/CharArrayReader."<init>":([C)V
	invokespecial	Method "<init>":(Lscala/util/parsing/combinator/lexical/Scanners;Lscala/util/parsing/input/Reader;)V
	return
  Labels:
  LocalVariableTable: 
   Start  Length  Slot  Name   Signature
   0      17      0    this       Lscala/util/parsing/combinator/lexical/Scanners$Scanner;
   0      17      1    $outer       Lscala/util/parsing/combinator/lexical/Scanners;
   0      17      2    in       Ljava/lang/String;


}

