Compiled from "StdLexical.scala"
public final class scala.util.parsing.combinator.lexical.StdLexical$$anonfun$comment$3 extends java.lang.Object implements scala.Function0,scala.ScalaObject,java.io.Serializable
  SourceFile: "StdLexical.scala"
  Scala: length = 0x
   
  InnerClass: 
   public abstract #81= #65 of #80; //Parser=class scala/util/parsing/combinator/Parsers$Parser of class scala/util/parsing/combinator/Parsers
   public final #82= #9 of #54; //$anonfun$comment$3=class scala/util/parsing/combinator/lexical/StdLexical$$anonfun$comment$3 of class scala/util/parsing/combinator/lexical/StdLexical
   public final #83= #60 of #9; //$anonfun$apply$26=class scala/util/parsing/combinator/lexical/StdLexical$$anonfun$comment$3$$anonfun$apply$26 of class scala/util/parsing/combinator/lexical/StdLexical$$anonfun$comment$3
  minor version: 0
  major version: 49
  Constant pool:
const #1 = Asciz	SourceFile;
const #2 = Asciz	StdLexical.scala;
const #3 = Asciz	<clinit>;
const #4 = Asciz	()V;
const #5 = Asciz	Code;
const #6 = Asciz	serialVersionUID;
const #7 = Asciz	J;
const #8 = Asciz	scala/util/parsing/combinator/lexical/StdLexical$$anonfun$comment$3;
const #9 = class	#8;	//  scala/util/parsing/combinator/lexical/StdLexical$$anonfun$comment$3
const #10 = NameAndType	#6:#7;//  serialVersionUID:J
const #11 = Field	#9.#10;	//  scala/util/parsing/combinator/lexical/StdLexical$$anonfun$comment$3.serialVersionUID:J
const #12 = Asciz	$outer;
const #13 = Asciz	Lscala/util/parsing/combinator/lexical/StdLexical;;
const #14 = Asciz	<init>;
const #15 = Asciz	(Lscala/util/parsing/combinator/lexical/StdLexical;)V;
const #16 = Asciz	LineNumberTable;
const #17 = Asciz	java/lang/NullPointerException;
const #18 = class	#17;	//  java/lang/NullPointerException
const #19 = NameAndType	#14:#4;//  "<init>":()V
const #20 = Method	#18.#19;	//  java/lang/NullPointerException."<init>":()V
const #21 = NameAndType	#12:#13;//  $outer:Lscala/util/parsing/combinator/lexical/StdLexical;
const #22 = Field	#9.#21;	//  scala/util/parsing/combinator/lexical/StdLexical$$anonfun$comment$3.$outer:Lscala/util/parsing/combinator/lexical/StdLexical;
const #23 = Asciz	java/lang/Object;
const #24 = class	#23;	//  java/lang/Object
const #25 = Method	#24.#19;	//  java/lang/Object."<init>":()V
const #26 = Asciz	scala/Function0$class;
const #27 = class	#26;	//  scala/Function0$class
const #28 = Asciz	$init$;
const #29 = Asciz	(Lscala/Function0;)V;
const #30 = NameAndType	#28:#29;//  $init$:(Lscala/Function0;)V
const #31 = Method	#27.#30;	//  scala/Function0$class.$init$:(Lscala/Function0;)V
const #32 = Asciz	this;
const #33 = Asciz	Lscala/util/parsing/combinator/lexical/StdLexical$$anonfun$comment$3;;
const #34 = Asciz	LocalVariableTable;
const #35 = Asciz	apply;
const #36 = Asciz	()Ljava/lang/Object;;
const #37 = Asciz	()Lscala/util/parsing/combinator/Parsers$Parser;;
const #38 = NameAndType	#35:#37;//  apply:()Lscala/util/parsing/combinator/Parsers$Parser;
const #39 = Method	#9.#38;	//  scala/util/parsing/combinator/lexical/StdLexical$$anonfun$comment$3.apply:()Lscala/util/parsing/combinator/Parsers$Parser;
const #40 = Asciz	scala$util$parsing$combinator$lexical$StdLexical$$anonfun$$$outer;
const #41 = Asciz	()Lscala/util/parsing/combinator/lexical/StdLexical;;
const #42 = Asciz	scala/Predef$;
const #43 = class	#42;	//  scala/Predef$
const #44 = Asciz	MODULE$;
const #45 = Asciz	Lscala/Predef$;;
const #46 = NameAndType	#44:#45;//  MODULE$:Lscala/Predef$;
const #47 = Field	#43.#46;	//  scala/Predef$.MODULE$:Lscala/Predef$;
const #48 = int	26;
const #49 = Asciz	wrapCharArray;
const #50 = Asciz	([C)Lscala/collection/mutable/WrappedArray;;
const #51 = NameAndType	#49:#50;//  wrapCharArray:([C)Lscala/collection/mutable/WrappedArray;
const #52 = Method	#43.#51;	//  scala/Predef$.wrapCharArray:([C)Lscala/collection/mutable/WrappedArray;
const #53 = Asciz	scala/util/parsing/combinator/lexical/StdLexical;
const #54 = class	#53;	//  scala/util/parsing/combinator/lexical/StdLexical
const #55 = Asciz	chrExcept;
const #56 = Asciz	(Lscala/collection/Seq;)Lscala/util/parsing/combinator/Parsers$Parser;;
const #57 = NameAndType	#55:#56;//  chrExcept:(Lscala/collection/Seq;)Lscala/util/parsing/combinator/Parsers$Parser;
const #58 = Method	#54.#57;	//  scala/util/parsing/combinator/lexical/StdLexical.chrExcept:(Lscala/collection/Seq;)Lscala/util/parsing/combinator/Parsers$Parser;
const #59 = Asciz	scala/util/parsing/combinator/lexical/StdLexical$$anonfun$comment$3$$anonfun$apply$26;
const #60 = class	#59;	//  scala/util/parsing/combinator/lexical/StdLexical$$anonfun$comment$3$$anonfun$apply$26
const #61 = Asciz	(Lscala/util/parsing/combinator/lexical/StdLexical$$anonfun$comment$3;)V;
const #62 = NameAndType	#14:#61;//  "<init>":(Lscala/util/parsing/combinator/lexical/StdLexical$$anonfun$comment$3;)V
const #63 = Method	#60.#62;	//  scala/util/parsing/combinator/lexical/StdLexical$$anonfun$comment$3$$anonfun$apply$26."<init>":(Lscala/util/parsing/combinator/lexical/StdLexical$$anonfun$comment$3;)V
const #64 = Asciz	scala/util/parsing/combinator/Parsers$Parser;
const #65 = class	#64;	//  scala/util/parsing/combinator/Parsers$Parser
const #66 = Asciz	$tilde;
const #67 = Asciz	(Lscala/Function0;)Lscala/util/parsing/combinator/Parsers$Parser;;
const #68 = NameAndType	#66:#67;//  $tilde:(Lscala/Function0;)Lscala/util/parsing/combinator/Parsers$Parser;
const #69 = Method	#65.#68;	//  scala/util/parsing/combinator/Parsers$Parser.$tilde:(Lscala/Function0;)Lscala/util/parsing/combinator/Parsers$Parser;
const #70 = Asciz	()Lscala/util/parsing/combinator/Parsers$Parser<Lscala/util/parsing/combinator/Parsers$$tilde<Ljava/lang/Character;Ljava/lang/Object;>;>;;
const #71 = Asciz	Signature;
const #72 = Asciz	toString;
const #73 = Asciz	()Ljava/lang/String;;
const #74 = Asciz	(Lscala/Function0;)Ljava/lang/String;;
const #75 = NameAndType	#72:#74;//  toString:(Lscala/Function0;)Ljava/lang/String;
const #76 = Method	#27.#75;	//  scala/Function0$class.toString:(Lscala/Function0;)Ljava/lang/String;
const #77 = Asciz	Scala;
const #78 = Asciz	InnerClasses;
const #79 = Asciz	scala/util/parsing/combinator/Parsers;
const #80 = class	#79;	//  scala/util/parsing/combinator/Parsers
const #81 = Asciz	Parser;
const #82 = Asciz	$anonfun$comment$3;
const #83 = Asciz	$anonfun$apply$26;
const #84 = Asciz	scala/Function0;
const #85 = class	#84;	//  scala/Function0
const #86 = Asciz	scala/ScalaObject;
const #87 = class	#86;	//  scala/ScalaObject
const #88 = Asciz	java/io/Serializable;
const #89 = class	#88;	//  java/io/Serializable

{
public static final long serialVersionUID;

public final scala.util.parsing.combinator.lexical.StdLexical $outer;

public static {};
  Code:
   Stack=2, Locals=0, Args_size=0
   0:	lconst_0
   1:	putstatic	#11; //Field serialVersionUID:J
   4:	return

public scala.util.parsing.combinator.lexical.StdLexical$$anonfun$comment$3(scala.util.parsing.combinator.lexical.StdLexical);
  Code:
   Stack=2, Locals=2, Args_size=2
   0:	aload_1
   1:	ifnonnull	12
   4:	new	#18; //class java/lang/NullPointerException
   7:	dup
   8:	invokespecial	#20; //Method java/lang/NullPointerException."<init>":()V
   11:	athrow
   12:	aload_0
   13:	aload_1
   14:	putfield	#22; //Field $outer:Lscala/util/parsing/combinator/lexical/StdLexical;
   17:	aload_0
   18:	invokespecial	#25; //Method java/lang/Object."<init>":()V
   21:	aload_0
   22:	invokestatic	#31; //Method scala/Function0$class.$init$:(Lscala/Function0;)V
   25:	return
  LineNumberTable: 
   line 63: 0

  LocalVariableTable: 
   Start  Length  Slot  Name   Signature
   0      26      0    this       Lscala/util/parsing/combinator/lexical/StdLexical$$anonfun$comment$3;
   0      26      1    $outer       Lscala/util/parsing/combinator/lexical/StdLexical;


public final java.lang.Object apply();
  Code:
   Stack=1, Locals=2, Args_size=1
   0:	aload_0
   1:	getfield	#22; //Field $outer:Lscala/util/parsing/combinator/lexical/StdLexical;
   4:	astore_1
   5:	aload_0
   6:	invokevirtual	#39; //Method apply:()Lscala/util/parsing/combinator/Parsers$Parser;
   9:	areturn
  LineNumberTable: 
   line 63: 0

  LocalVariableTable: 
   Start  Length  Slot  Name   Signature
   0      10      0    this       Lscala/util/parsing/combinator/lexical/StdLexical$$anonfun$comment$3;


public scala.util.parsing.combinator.lexical.StdLexical scala$util$parsing$combinator$lexical$StdLexical$$anonfun$$$outer();
  Code:
   Stack=1, Locals=1, Args_size=1
   0:	aload_0
   1:	getfield	#22; //Field $outer:Lscala/util/parsing/combinator/lexical/StdLexical;
   4:	areturn
  LineNumberTable: 
   line 63: 0


public final scala.util.parsing.combinator.Parsers$Parser apply();
  Code:
   Stack=6, Locals=2, Args_size=1
   0:	aload_0
   1:	getfield	#22; //Field $outer:Lscala/util/parsing/combinator/lexical/StdLexical;
   4:	astore_1
   5:	aload_0
   6:	getfield	#22; //Field $outer:Lscala/util/parsing/combinator/lexical/StdLexical;
   9:	getstatic	#47; //Field scala/Predef$.MODULE$:Lscala/Predef$;
   12:	iconst_1
   13:	newarray char
   15:	dup
   16:	iconst_0
   17:	ldc	#48; //int 26
   19:	castore
   20:	invokevirtual	#52; //Method scala/Predef$.wrapCharArray:([C)Lscala/collection/mutable/WrappedArray;
   23:	invokevirtual	#58; //Method scala/util/parsing/combinator/lexical/StdLexical.chrExcept:(Lscala/collection/Seq;)Lscala/util/parsing/combinator/Parsers$Parser;
   26:	new	#60; //class scala/util/parsing/combinator/lexical/StdLexical$$anonfun$comment$3$$anonfun$apply$26
   29:	dup
   30:	aload_0
   31:	invokespecial	#63; //Method scala/util/parsing/combinator/lexical/StdLexical$$anonfun$comment$3$$anonfun$apply$26."<init>":(Lscala/util/parsing/combinator/lexical/StdLexical$$anonfun$comment$3;)V
   34:	invokevirtual	#69; //Method scala/util/parsing/combinator/Parsers$Parser.$tilde:(Lscala/Function0;)Lscala/util/parsing/combinator/Parsers$Parser;
   37:	areturn
  LineNumberTable: 
   line 63: 0

  LocalVariableTable: 
   Start  Length  Slot  Name   Signature
   0      38      0    this       Lscala/util/parsing/combinator/lexical/StdLexical$$anonfun$comment$3;

  Signature: length = 0x2
   00 46 

public java.lang.String toString();
  Code:
   Stack=1, Locals=1, Args_size=1
   0:	aload_0
   1:	invokestatic	#76; //Method scala/Function0$class.toString:(Lscala/Function0;)Ljava/lang/String;
   4:	areturn
  LineNumberTable: 
   line 63: 0


}

