Compiled from "StdLexical.scala"
public final class scala.util.parsing.combinator.lexical.StdLexical$$anonfun$whitespace$1$$anonfun$apply$23$$anonfun$apply$25 extends scala.runtime.AbstractFunction0 implements java.io.Serializable
  SourceFile: "StdLexical.scala"
  Scala: length = 0x
   
  InnerClass: 
   public abstract Parser=class scala/util/parsing/combinator/Parsers$Parser of class scala/util/parsing/combinator/Parsers
   public final $anonfun$whitespace$1=class scala/util/parsing/combinator/lexical/StdLexical$$anonfun$whitespace$1 of class scala/util/parsing/combinator/lexical/StdLexical
   public final $anonfun$apply$23=class scala/util/parsing/combinator/lexical/StdLexical$$anonfun$whitespace$1$$anonfun$apply$23 of class scala/util/parsing/combinator/lexical/StdLexical$$anonfun$whitespace$1
   public final $anonfun$apply$25=class scala/util/parsing/combinator/lexical/StdLexical$$anonfun$whitespace$1$$anonfun$apply$23$$anonfun$apply$25 of class scala/util/parsing/combinator/lexical/StdLexical$$anonfun$whitespace$1$$anonfun$apply$23
  minor version: 0
  major version: 49
  Constant pool:
Asciz	SourceFile;
Asciz	StdLexical.scala;
Asciz	<clinit>;
Asciz	()V;
Asciz	Code;
Asciz	serialVersionUID;
Asciz	J;
Asciz	scala/util/parsing/combinator/lexical/StdLexical$$anonfun$whitespace$1$$anonfun$apply$23$$anonfun$apply$25;
class	scala/util/parsing/combinator/lexical/StdLexical$$anonfun$whitespace$1$$anonfun$apply$23$$anonfun$apply$25
NameAndType	serialVersionUID:J
Field	scala/util/parsing/combinator/lexical/StdLexical$$anonfun$whitespace$1$$anonfun$apply$23$$anonfun$apply$25.serialVersionUID:J
Asciz	$outer;
Asciz	Lscala/util/parsing/combinator/lexical/StdLexical$$anonfun$whitespace$1$$anonfun$apply$23;;
Asciz	apply;
Asciz	()Lscala/util/parsing/combinator/Parsers$Parser;;
Asciz	LineNumberTable;
NameAndType	$outer:Lscala/util/parsing/combinator/lexical/StdLexical$$anonfun$whitespace$1$$anonfun$apply$23;
Field	scala/util/parsing/combinator/lexical/StdLexical$$anonfun$whitespace$1$$anonfun$apply$23$$anonfun$apply$25.$outer:Lscala/util/parsing/combinator/lexical/StdLexical$$anonfun$whitespace$1$$anonfun$apply$23;
Asciz	scala/util/parsing/combinator/lexical/StdLexical$$anonfun$whitespace$1$$anonfun$apply$23;
class	scala/util/parsing/combinator/lexical/StdLexical$$anonfun$whitespace$1$$anonfun$apply$23
Asciz	scala$util$parsing$combinator$lexical$StdLexical$$anonfun$$anonfun$$$outer;
Asciz	()Lscala/util/parsing/combinator/lexical/StdLexical$$anonfun$whitespace$1;;
NameAndType	scala$util$parsing$combinator$lexical$StdLexical$$anonfun$$anonfun$$$outer:()Lscala/util/parsing/combinator/lexical/StdLexical$$anonfun$whitespace$1;
Method	scala/util/parsing/combinator/lexical/StdLexical$$anonfun$whitespace$1$$anonfun$apply$23.scala$util$parsing$combinator$lexical$StdLexical$$anonfun$$anonfun$$$outer:()Lscala/util/parsing/combinator/lexical/StdLexical$$anonfun$whitespace$1;
Asciz	scala/util/parsing/combinator/lexical/StdLexical$$anonfun$whitespace$1;
class	scala/util/parsing/combinator/lexical/StdLexical$$anonfun$whitespace$1
Asciz	scala$util$parsing$combinator$lexical$StdLexical$$anonfun$$$outer;
Asciz	()Lscala/util/parsing/combinator/lexical/StdLexical;;
NameAndType	scala$util$parsing$combinator$lexical$StdLexical$$anonfun$$$outer:()Lscala/util/parsing/combinator/lexical/StdLexical;
Method	scala/util/parsing/combinator/lexical/StdLexical$$anonfun$whitespace$1.scala$util$parsing$combinator$lexical$StdLexical$$anonfun$$$outer:()Lscala/util/parsing/combinator/lexical/StdLexical;
Asciz	unclosed comment;
String	unclosed comment
Asciz	scala/util/parsing/combinator/Parsers;
class	scala/util/parsing/combinator/Parsers
Asciz	failure;
Asciz	(Ljava/lang/String;)Lscala/util/parsing/combinator/Parsers$Parser;;
NameAndType	failure:(Ljava/lang/String;)Lscala/util/parsing/combinator/Parsers$Parser;
InterfaceMethod	scala/util/parsing/combinator/Parsers.failure:(Ljava/lang/String;)Lscala/util/parsing/combinator/Parsers$Parser;
Asciz	()Lscala/util/parsing/combinator/Parsers$Parser<Lscala/runtime/Nothing$;>;;
Asciz	Signature;
Asciz	()Ljava/lang/Object;;
NameAndType	apply:()Lscala/util/parsing/combinator/Parsers$Parser;
Method	scala/util/parsing/combinator/lexical/StdLexical$$anonfun$whitespace$1$$anonfun$apply$23$$anonfun$apply$25.apply:()Lscala/util/parsing/combinator/Parsers$Parser;
Asciz	<init>;
Asciz	(Lscala/util/parsing/combinator/lexical/StdLexical$$anonfun$whitespace$1$$anonfun$apply$23;)V;
Asciz	java/lang/NullPointerException;
class	java/lang/NullPointerException
NameAndType	"<init>":()V
Method	java/lang/NullPointerException."<init>":()V
Asciz	scala/runtime/AbstractFunction0;
class	scala/runtime/AbstractFunction0
Method	scala/runtime/AbstractFunction0."<init>":()V
Asciz	this;
Asciz	Lscala/util/parsing/combinator/lexical/StdLexical$$anonfun$whitespace$1$$anonfun$apply$23$$anonfun$apply$25;;
Asciz	LocalVariableTable;
Asciz	Scala;
Asciz	InnerClasses;
Asciz	scala/util/parsing/combinator/Parsers$Parser;
class	scala/util/parsing/combinator/Parsers$Parser
Asciz	Parser;
Asciz	scala/util/parsing/combinator/lexical/StdLexical;
class	scala/util/parsing/combinator/lexical/StdLexical
Asciz	$anonfun$whitespace$1;
Asciz	$anonfun$apply$23;
Asciz	$anonfun$apply$25;
Asciz	java/io/Serializable;
class	java/io/Serializable

{
public static final long serialVersionUID;
  Signature: J

private final scala.util.parsing.combinator.lexical.StdLexical$$anonfun$whitespace$1$$anonfun$apply$23 $outer;
  Signature: Lscala/util/parsing/combinator/lexical/StdLexical$$anonfun$whitespace$1$$anonfun$apply$23;

public static {};
  Signature: ()V
  Code:
   Stack=2, Locals=0, Args_size=0
	lconst_0
	putstatic	Field serialVersionUID:J
	return
  Labels:

public final scala.util.parsing.combinator.Parsers$Parser apply();
  Signature: ()Lscala/util/parsing/combinator/Parsers$Parser;
  Code:
   Stack=2, Locals=1, Args_size=1
	aload_0
	getfield	Field $outer:Lscala/util/parsing/combinator/lexical/StdLexical$$anonfun$whitespace$1$$anonfun$apply$23;
	invokevirtual	Method scala/util/parsing/combinator/lexical/StdLexical$$anonfun$whitespace$1$$anonfun$apply$23.scala$util$parsing$combinator$lexical$StdLexical$$anonfun$$anonfun$$$outer:()Lscala/util/parsing/combinator/lexical/StdLexical$$anonfun$whitespace$1;
	invokevirtual	Method scala/util/parsing/combinator/lexical/StdLexical$$anonfun$whitespace$1.scala$util$parsing$combinator$lexical$StdLexical$$anonfun$$$outer:()Lscala/util/parsing/combinator/lexical/StdLexical;
	ldc	String unclosed comment
	invokeinterface	InterfaceMethod scala/util/parsing/combinator/Parsers.failure:(Ljava/lang/String;)Lscala/util/parsing/combinator/Parsers$Parser;
	areturn
  Labels:
  Signature: length = 0x2
   00 27 

public final java.lang.Object apply();
  Signature: ()Ljava/lang/Object;
  Code:
   Stack=1, Locals=1, Args_size=1
	aload_0
	invokevirtual	Method apply:()Lscala/util/parsing/combinator/Parsers$Parser;
	areturn
  Labels:

public scala.util.parsing.combinator.lexical.StdLexical$$anonfun$whitespace$1$$anonfun$apply$23$$anonfun$apply$25(scala.util.parsing.combinator.lexical.StdLexical$$anonfun$whitespace$1$$anonfun$apply$23);
  Signature: (Lscala/util/parsing/combinator/lexical/StdLexical$$anonfun$whitespace$1$$anonfun$apply$23;)V
  Code:
   Stack=2, Locals=2, Args_size=2
	aload_1
	ifnonnull	l1 // aload_0
	new	class java/lang/NullPointerException
	dup
	invokespecial	Method java/lang/NullPointerException."<init>":()V
	athrow
l1	aload_0
	aload_1
	putfield	Field $outer:Lscala/util/parsing/combinator/lexical/StdLexical$$anonfun$whitespace$1$$anonfun$apply$23;
	aload_0
	invokespecial	Method scala/runtime/AbstractFunction0."<init>":()V
	return
  Labels:
   	l1 = 12 // aload_0
  LocalVariableTable: 
   Start  Length  Slot  Name   Signature
   0      22      0    this       Lscala/util/parsing/combinator/lexical/StdLexical$$anonfun$whitespace$1$$anonfun$apply$23$$anonfun$apply$25;
   0      22      1    $outer       Lscala/util/parsing/combinator/lexical/StdLexical$$anonfun$whitespace$1$$anonfun$apply$23;


}

