Compiled from "StdLexical.scala"
public final class scala.util.parsing.combinator.lexical.StdLexical$$anonfun$whitespace$1$$anonfun$apply$23 extends java.lang.Object implements scala.Function0,scala.ScalaObject,java.io.Serializable
  SourceFile: "StdLexical.scala"
  Scala: length = 0x
   
  InnerClass: 
   public abstract Parser=class scala/util/parsing/combinator/Parsers$Parser of class scala/util/parsing/combinator/Parsers
   public final $anonfun$whitespace$1=class scala/util/parsing/combinator/lexical/StdLexical$$anonfun$whitespace$1 of class scala/util/parsing/combinator/lexical/StdLexical
   public final $anonfun$apply$23=class scala/util/parsing/combinator/lexical/StdLexical$$anonfun$whitespace$1$$anonfun$apply$23 of class scala/util/parsing/combinator/lexical/StdLexical$$anonfun$whitespace$1
   public final $anonfun$apply$25=class scala/util/parsing/combinator/lexical/StdLexical$$anonfun$whitespace$1$$anonfun$apply$23$$anonfun$apply$25 of class scala/util/parsing/combinator/lexical/StdLexical$$anonfun$whitespace$1$$anonfun$apply$23
   public final $anonfun$apply$24=class scala/util/parsing/combinator/lexical/StdLexical$$anonfun$whitespace$1$$anonfun$apply$23$$anonfun$apply$24 of class scala/util/parsing/combinator/lexical/StdLexical$$anonfun$whitespace$1$$anonfun$apply$23
  minor version: 0
  major version: 49
  Constant pool:
Asciz	SourceFile;
Asciz	StdLexical.scala;
Asciz	<clinit>;
Asciz	()V;
Asciz	Code;
Asciz	serialVersionUID;
Asciz	J;
Asciz	scala/util/parsing/combinator/lexical/StdLexical$$anonfun$whitespace$1$$anonfun$apply$23;
class	scala/util/parsing/combinator/lexical/StdLexical$$anonfun$whitespace$1$$anonfun$apply$23
NameAndType	serialVersionUID:J
Field	scala/util/parsing/combinator/lexical/StdLexical$$anonfun$whitespace$1$$anonfun$apply$23.serialVersionUID:J
Asciz	$outer;
Asciz	Lscala/util/parsing/combinator/lexical/StdLexical$$anonfun$whitespace$1;;
Asciz	<init>;
Asciz	(Lscala/util/parsing/combinator/lexical/StdLexical$$anonfun$whitespace$1;)V;
Asciz	LineNumberTable;
Asciz	java/lang/NullPointerException;
class	java/lang/NullPointerException
NameAndType	"<init>":()V
Method	java/lang/NullPointerException."<init>":()V
NameAndType	$outer:Lscala/util/parsing/combinator/lexical/StdLexical$$anonfun$whitespace$1;
Field	scala/util/parsing/combinator/lexical/StdLexical$$anonfun$whitespace$1$$anonfun$apply$23.$outer:Lscala/util/parsing/combinator/lexical/StdLexical$$anonfun$whitespace$1;
Asciz	java/lang/Object;
class	java/lang/Object
Method	java/lang/Object."<init>":()V
Asciz	scala/Function0$class;
class	scala/Function0$class
Asciz	$init$;
Asciz	(Lscala/Function0;)V;
NameAndType	$init$:(Lscala/Function0;)V
Method	scala/Function0$class.$init$:(Lscala/Function0;)V
Asciz	this;
Asciz	Lscala/util/parsing/combinator/lexical/StdLexical$$anonfun$whitespace$1$$anonfun$apply$23;;
Asciz	LocalVariableTable;
Asciz	apply;
Asciz	()Ljava/lang/Object;;
Asciz	()Lscala/util/parsing/combinator/Parsers$Parser;;
NameAndType	apply:()Lscala/util/parsing/combinator/Parsers$Parser;
Method	scala/util/parsing/combinator/lexical/StdLexical$$anonfun$whitespace$1$$anonfun$apply$23.apply:()Lscala/util/parsing/combinator/Parsers$Parser;
Asciz	scala$util$parsing$combinator$lexical$StdLexical$$anonfun$$anonfun$$$outer;
Asciz	()Lscala/util/parsing/combinator/lexical/StdLexical$$anonfun$whitespace$1;;
Asciz	scala/util/parsing/combinator/lexical/StdLexical$$anonfun$whitespace$1;
class	scala/util/parsing/combinator/lexical/StdLexical$$anonfun$whitespace$1
Asciz	Lscala/util/parsing/combinator/lexical/StdLexical;;
NameAndType	$outer:Lscala/util/parsing/combinator/lexical/StdLexical;
Field	scala/util/parsing/combinator/lexical/StdLexical$$anonfun$whitespace$1.$outer:Lscala/util/parsing/combinator/lexical/StdLexical;
int	47;
Asciz	scala/runtime/BoxesRunTime;
class	scala/runtime/BoxesRunTime
Asciz	boxToCharacter;
Asciz	(C)Ljava/lang/Character;;
NameAndType	boxToCharacter:(C)Ljava/lang/Character;
Method	scala/runtime/BoxesRunTime.boxToCharacter:(C)Ljava/lang/Character;
Asciz	scala/util/parsing/combinator/Parsers;
class	scala/util/parsing/combinator/Parsers
Asciz	accept;
Asciz	(Ljava/lang/Object;)Lscala/util/parsing/combinator/Parsers$Parser;;
NameAndType	accept:(Ljava/lang/Object;)Lscala/util/parsing/combinator/Parsers$Parser;
InterfaceMethod	scala/util/parsing/combinator/Parsers.accept:(Ljava/lang/Object;)Lscala/util/parsing/combinator/Parsers$Parser;
Asciz	scala/util/parsing/combinator/lexical/StdLexical$$anonfun$whitespace$1$$anonfun$apply$23$$anonfun$apply$24;
class	scala/util/parsing/combinator/lexical/StdLexical$$anonfun$whitespace$1$$anonfun$apply$23$$anonfun$apply$24
Asciz	(Lscala/util/parsing/combinator/lexical/StdLexical$$anonfun$whitespace$1$$anonfun$apply$23;)V;
NameAndType	"<init>":(Lscala/util/parsing/combinator/lexical/StdLexical$$anonfun$whitespace$1$$anonfun$apply$23;)V
Method	scala/util/parsing/combinator/lexical/StdLexical$$anonfun$whitespace$1$$anonfun$apply$23$$anonfun$apply$24."<init>":(Lscala/util/parsing/combinator/lexical/StdLexical$$anonfun$whitespace$1$$anonfun$apply$23;)V
Asciz	scala/util/parsing/combinator/Parsers$Parser;
class	scala/util/parsing/combinator/Parsers$Parser
Asciz	$tilde;
Asciz	(Lscala/Function0;)Lscala/util/parsing/combinator/Parsers$Parser;;
NameAndType	$tilde:(Lscala/Function0;)Lscala/util/parsing/combinator/Parsers$Parser;
Method	scala/util/parsing/combinator/Parsers$Parser.$tilde:(Lscala/Function0;)Lscala/util/parsing/combinator/Parsers$Parser;
Asciz	scala/util/parsing/combinator/lexical/StdLexical$$anonfun$whitespace$1$$anonfun$apply$23$$anonfun$apply$25;
class	scala/util/parsing/combinator/lexical/StdLexical$$anonfun$whitespace$1$$anonfun$apply$23$$anonfun$apply$25
Method	scala/util/parsing/combinator/lexical/StdLexical$$anonfun$whitespace$1$$anonfun$apply$23$$anonfun$apply$25."<init>":(Lscala/util/parsing/combinator/lexical/StdLexical$$anonfun$whitespace$1$$anonfun$apply$23;)V
Asciz	()Lscala/util/parsing/combinator/Parsers$Parser<Lscala/util/parsing/combinator/Parsers$$tilde<Lscala/util/parsing/combinator/Parsers$$tilde<Ljava/lang/Character;Ljava/lang/Character;>;Lscala/runtime/Nothing$;>;>;;
Asciz	Signature;
Asciz	toString;
Asciz	()Ljava/lang/String;;
Asciz	(Lscala/Function0;)Ljava/lang/String;;
NameAndType	toString:(Lscala/Function0;)Ljava/lang/String;
Method	scala/Function0$class.toString:(Lscala/Function0;)Ljava/lang/String;
Asciz	Scala;
Asciz	InnerClasses;
Asciz	Parser;
Asciz	scala/util/parsing/combinator/lexical/StdLexical;
class	scala/util/parsing/combinator/lexical/StdLexical
Asciz	$anonfun$whitespace$1;
Asciz	$anonfun$apply$23;
Asciz	$anonfun$apply$25;
Asciz	$anonfun$apply$24;
Asciz	scala/Function0;
class	scala/Function0
Asciz	scala/ScalaObject;
class	scala/ScalaObject
Asciz	java/io/Serializable;
class	java/io/Serializable

{
public static final long serialVersionUID;
  Signature: J

public final scala.util.parsing.combinator.lexical.StdLexical$$anonfun$whitespace$1 $outer;
  Signature: Lscala/util/parsing/combinator/lexical/StdLexical$$anonfun$whitespace$1;

public static {};
  Signature: ()V
  Code:
   Stack=2, Locals=0, Args_size=0
	lconst_0
	putstatic	Field serialVersionUID:J
	return
  Labels:

public scala.util.parsing.combinator.lexical.StdLexical$$anonfun$whitespace$1$$anonfun$apply$23(scala.util.parsing.combinator.lexical.StdLexical$$anonfun$whitespace$1);
  Signature: (Lscala/util/parsing/combinator/lexical/StdLexical$$anonfun$whitespace$1;)V
  Code:
   Stack=2, Locals=2, Args_size=2
	aload_1
	ifnonnull	l1 // aload_0
	new	class java/lang/NullPointerException
	dup
	invokespecial	Method java/lang/NullPointerException."<init>":()V
	athrow
l1	aload_0
	aload_1
	putfield	Field $outer:Lscala/util/parsing/combinator/lexical/StdLexical$$anonfun$whitespace$1;
	aload_0
	invokespecial	Method java/lang/Object."<init>":()V
	aload_0
	invokestatic	Method scala/Function0$class.$init$:(Lscala/Function0;)V
	return
  Labels:
   	l1 = 12 // aload_0
  LocalVariableTable: 
   Start  Length  Slot  Name   Signature
   0      26      0    this       Lscala/util/parsing/combinator/lexical/StdLexical$$anonfun$whitespace$1$$anonfun$apply$23;
   0      26      1    $outer       Lscala/util/parsing/combinator/lexical/StdLexical$$anonfun$whitespace$1;


public final java.lang.Object apply();
  Signature: ()Ljava/lang/Object;
  Code:
   Stack=1, Locals=2, Args_size=1
	aload_0
	getfield	Field $outer:Lscala/util/parsing/combinator/lexical/StdLexical$$anonfun$whitespace$1;
	astore_1
	aload_0
	invokevirtual	Method apply:()Lscala/util/parsing/combinator/Parsers$Parser;
	areturn
  Labels:
  LocalVariableTable: 
   Start  Length  Slot  Name   Signature
   0      10      0    this       Lscala/util/parsing/combinator/lexical/StdLexical$$anonfun$whitespace$1$$anonfun$apply$23;


public scala.util.parsing.combinator.lexical.StdLexical$$anonfun$whitespace$1 scala$util$parsing$combinator$lexical$StdLexical$$anonfun$$anonfun$$$outer();
  Signature: ()Lscala/util/parsing/combinator/lexical/StdLexical$$anonfun$whitespace$1;
  Code:
   Stack=1, Locals=1, Args_size=1
	aload_0
	getfield	Field $outer:Lscala/util/parsing/combinator/lexical/StdLexical$$anonfun$whitespace$1;
	areturn
  Labels:

public final scala.util.parsing.combinator.Parsers$Parser apply();
  Signature: ()Lscala/util/parsing/combinator/Parsers$Parser;
  Code:
   Stack=4, Locals=4, Args_size=1
	aload_0
	getfield	Field $outer:Lscala/util/parsing/combinator/lexical/StdLexical$$anonfun$whitespace$1;
	astore_3
	aload_0
	getfield	Field $outer:Lscala/util/parsing/combinator/lexical/StdLexical$$anonfun$whitespace$1;
	astore_1
	aload_1
	getfield	Field scala/util/parsing/combinator/lexical/StdLexical$$anonfun$whitespace$1.$outer:Lscala/util/parsing/combinator/lexical/StdLexical;
	ldc	int 47
	istore_2
	iload_2
	invokestatic	Method scala/runtime/BoxesRunTime.boxToCharacter:(C)Ljava/lang/Character;
	invokeinterface	InterfaceMethod scala/util/parsing/combinator/Parsers.accept:(Ljava/lang/Object;)Lscala/util/parsing/combinator/Parsers$Parser;
	new	class scala/util/parsing/combinator/lexical/StdLexical$$anonfun$whitespace$1$$anonfun$apply$23$$anonfun$apply$24
	dup
	aload_0
	invokespecial	Method scala/util/parsing/combinator/lexical/StdLexical$$anonfun$whitespace$1$$anonfun$apply$23$$anonfun$apply$24."<init>":(Lscala/util/parsing/combinator/lexical/StdLexical$$anonfun$whitespace$1$$anonfun$apply$23;)V
	invokevirtual	Method scala/util/parsing/combinator/Parsers$Parser.$tilde:(Lscala/Function0;)Lscala/util/parsing/combinator/Parsers$Parser;
	new	class scala/util/parsing/combinator/lexical/StdLexical$$anonfun$whitespace$1$$anonfun$apply$23$$anonfun$apply$25
	dup
	aload_0
	invokespecial	Method scala/util/parsing/combinator/lexical/StdLexical$$anonfun$whitespace$1$$anonfun$apply$23$$anonfun$apply$25."<init>":(Lscala/util/parsing/combinator/lexical/StdLexical$$anonfun$whitespace$1$$anonfun$apply$23;)V
	invokevirtual	Method scala/util/parsing/combinator/Parsers$Parser.$tilde:(Lscala/Function0;)Lscala/util/parsing/combinator/Parsers$Parser;
	areturn
  Labels:
  LocalVariableTable: 
   Start  Length  Slot  Name   Signature
   0      49      0    this       Lscala/util/parsing/combinator/lexical/StdLexical$$anonfun$whitespace$1$$anonfun$apply$23;

  Signature: length = 0x2
   00 4A 

public java.lang.String toString();
  Signature: ()Ljava/lang/String;
  Code:
   Stack=1, Locals=1, Args_size=1
	aload_0
	invokestatic	Method scala/Function0$class.toString:(Lscala/Function0;)Ljava/lang/String;
	areturn
  Labels:

}

