Compiled from "StdLexical.scala"
public class scala.util.parsing.combinator.lexical.StdLexical extends scala.util.parsing.combinator.lexical.Lexical implements scala.util.parsing.syntax.StdTokens,scala.ScalaObject
  SourceFile: "StdLexical.scala"
  ScalaSig: length = 0x3D5
   05 00 FFFFFF81 1A 06 08 01 02 FFFFFF84 FFFFFF80 FFFFFF80 FFFFFF80 00 0D 02 0A
   53 74 64 4C 65 78 69 63 61 6C 0A 02 03 04 01 07
   6C 65 78 69 63 61 6C 0A 02 05 06 01 0A 63 6F 6D
   62 69 6E 61 74 6F 72 0A 02 07 08 01 07 70 61 72
   73 69 6E 67 0A 02 09 0A 01 04 75 74 69 6C 0A 01
   0B 01 05 73 63 61 6C 61 03 00 13 04 00 0E 12 18
   10 02 0F 10 0D 01 02 09 02 11 02 02 07 4C 65 78
   69 63 61 6C 10 02 13 16 0D 01 14 0A 02 15 06 01
   06 73 79 6E 74 61 78 09 02 17 14 02 09 53 74 64
   54 6F 6B 65 6E 73 10 02 19 1A 0D 01 0A 09 02 1B
   0A 02 0B 53 63 61 6C 61 4F 62 6A 65 63 74 08 05
   1D 00 FFFFFF84 00 1E 01 06 3C 69 6E 69 74 3E 14 01 1F
   10 02 0F 00 08 05 21 00 FFFFFF84 00 22 01 05 74 6F 6B
   65 6E 15 01 23 10 03 24 25 29 0D 01 00 09 02 26
   27 02 06 50 61 72 73 65 72 09 02 28 04 02 07 50
   61 72 73 65 72 73 10 02 24 2A 09 02 2B 2C 02 05
   54 6F 6B 65 6E 09 02 2D 14 02 06 54 6F 6B 65 6E
   73 08 05 2F 00 FFFFFF84 00 30 01 09 69 64 65 6E 74 43
   68 61 72 15 01 31 10 03 24 25 32 10 02 24 33 09
   02 34 35 02 04 45 6C 65 6D 09 02 36 02 02 08 53
   63 61 6E 6E 65 72 73 08 05 38 00 FFFFFF84 00 39 01 0A
   77 68 69 74 65 73 70 61 63 65 15 01 3A 10 03 24
   25 3B 10 02 19 3C 09 02 3D 0A 02 03 41 6E 79 08
   05 3F 00 FFFFFF84 08 39 01 07 63 6F 6D 6D 65 6E 74 08
   07 41 00 FFFFFFC2 FFFFFF80 FFFFFF84 00 42 01 08 72 65 73 65 72 76
   65 64 15 01 43 10 03 44 49 4B 0D 01 45 0A 02 46
   47 01 07 6D 75 74 61 62 6C 65 0A 02 48 0A 01 0A
   63 6F 6C 6C 65 63 74 69 6F 6E 09 02 4A 45 02 07
   48 61 73 68 53 65 74 10 02 4C 4F 0E 02 19 4D 09
   02 4E 0A 01 06 50 72 65 64 65 66 09 02 50 51 02
   06 53 74 72 69 6E 67 0A 02 4E 0A 08 06 53 00 FFFFFFA0
   FFFFFF80 04 43 01 09 72 65 73 65 72 76 65 64 20 08 07
   55 00 FFFFFFC2 FFFFFF80 FFFFFF84 00 42 01 0A 64 65 6C 69 6D 69 74
   65 72 73 08 06 57 00 FFFFFFA0 FFFFFF80 04 43 01 0B 64 65 6C
   69 6D 69 74 65 72 73 20 08 05 59 00 FFFFFF84 08 5A 01
   0C 70 72 6F 63 65 73 73 49 64 65 6E 74 14 02 5B
   61 12 03 5C 5E 29 06 08 5D 00 FFFFFF84 FFFFFF80 FFFFFF80 FFFFFF80 00 5B
   02 0C 3C 72 65 66 69 6E 65 6D 65 6E 74 3E 10 02
   19 5F 09 02 60 0A 02 07 50 72 6F 64 75 63 74 08
   05 62 58 FFFFFFC0 00 4B 01 04 6E 61 6D 65 08 08 64 00
   FFFFFF88 FFFFFFC2 FFFFFF80 FFFFFF84 04 22 01 06 5F 64 65 6C 69 6D 08 08
   66 00 FFFFFF88 FFFFFF80 FFFFFFA0 FFFFFFA0 04 23 01 07 5F 64 65 6C 69 6D
   20 08 05 68 00 FFFFFF84 08 22 01 05 64 65 6C 69 6D 08
   05 6A 00 FFFFFF84 04 6B 01 04 6C 69 66 74 15 02 6C 70
   14 03 6D FFFFFF81 07 14 02 6E 76 10 02 6F 70 0C 00 04
   08 71 69 FFFFFF84 FFFFFF80 FFFFFF80 FFFFFFC2 00 72 02 01 54 11 02 73 3B
   10 02 19 74 09 02 75 0A 02 07 4E 6F 74 68 69 6E
   67 08 05 77 69 FFFFFFC0 00 78 01 02 78 73 10 05 79 FFFFFF81
   01 FFFFFF81 04 0E 02 7A 7F 0E 02 7B 7E 0D 01 7C 0A 02
   7D 0C 01 06 3C 72 6F 6F 74 3E 09 01 0B 09 03 FFFFFF81
   00 0A 01 07 70 61 63 6B 61 67 65 09 04 FFFFFF81 02 FFFFFF81
   03 02 04 4C 69 73 74 0A 03 FFFFFF81 00 0A 10 03 19 FFFFFF81
   05 09 03 FFFFFF81 06 0A 02 04 43 68 61 72 08 07 FFFFFF81 08
   69 FFFFFFC0 00 FFFFFF81 09 01 01 66 10 05 19 FFFFFF81 0A 4B 6E 09
   03 FFFFFF81 0B 0A 02 09 46 75 6E 63 74 69 6F 6E 31 08
   07 FFFFFF81 0D 00 FFFFFF84 04 FFFFFF81 0E 01 05 6C 69 66 74 32 15
   04 FFFFFF81 0F FFFFFF81 12 14 04 FFFFFF81 10 FFFFFF81 18 14 04 FFFFFF81 11 FFFFFF81
   13 10 03 6F FFFFFF81 12 04 09 71 FFFFFF81 0C FFFFFF84 FFFFFF80 FFFFFF80 FFFFFFC2 00
   72 08 08 FFFFFF81 14 FFFFFF81 0C FFFFFFC0 00 FFFFFF81 15 01 01 70 10 06
   24 FFFFFF81 16 FFFFFF81 04 78 09 03 FFFFFF81 17 27 02 06 24 74 69
   6C 64 65 08 08 FFFFFF81 08 FFFFFF81 0C FFFFFFC0 00 FFFFFF81 19 10 06 19
   FFFFFF81 0A 4B FFFFFF81 11 
  InnerClass: 
   public #341= #176 of #340; //ofRef=class scala/collection/mutable/ArrayOps$ofRef of class scala/collection/mutable/ArrayOps
   public #246= #91 of #67; //$tilde=class scala/util/parsing/combinator/Parsers$$tilde of class scala/util/parsing/combinator/Parsers
   public abstract #342= #78 of #67; //Parser=class scala/util/parsing/combinator/Parsers$Parser of class scala/util/parsing/combinator/Parsers
   public #330= #229 of #344; //Keyword=class scala/util/parsing/syntax/StdTokens$Keyword of class scala/util/parsing/syntax/StdTokens
   public #308= #234 of #344; //Identifier=class scala/util/parsing/syntax/StdTokens$Identifier of class scala/util/parsing/syntax/StdTokens
   public abstract #349= #346 of #348; //$less$colon$less=class scala/Predef$$less$colon$less of class scala/Predef
   public final #350= #303 of #39; //$anonfun$token$9=class scala/util/parsing/combinator/lexical/StdLexical$$anonfun$token$9 of class scala/util/parsing/combinator/lexical/StdLexical
   public final #351= #300 of #39; //$anonfun$token$8=class scala/util/parsing/combinator/lexical/StdLexical$$anonfun$token$8 of class scala/util/parsing/combinator/lexical/StdLexical
   public final #352= #297 of #39; //$anonfun$token$7=class scala/util/parsing/combinator/lexical/StdLexical$$anonfun$token$7 of class scala/util/parsing/combinator/lexical/StdLexical
   public final #353= #294 of #39; //$anonfun$token$6=class scala/util/parsing/combinator/lexical/StdLexical$$anonfun$token$6 of class scala/util/parsing/combinator/lexical/StdLexical
   public final #354= #291 of #39; //$anonfun$token$5=class scala/util/parsing/combinator/lexical/StdLexical$$anonfun$token$5 of class scala/util/parsing/combinator/lexical/StdLexical
   public final #355= #288 of #39; //$anonfun$token$4=class scala/util/parsing/combinator/lexical/StdLexical$$anonfun$token$4 of class scala/util/parsing/combinator/lexical/StdLexical
   public final #356= #285 of #39; //$anonfun$token$3=class scala/util/parsing/combinator/lexical/StdLexical$$anonfun$token$3 of class scala/util/parsing/combinator/lexical/StdLexical
   public final #357= #282 of #39; //$anonfun$token$2=class scala/util/parsing/combinator/lexical/StdLexical$$anonfun$token$2 of class scala/util/parsing/combinator/lexical/StdLexical
   public final #358= #279 of #39; //$anonfun$token$1=class scala/util/parsing/combinator/lexical/StdLexical$$anonfun$token$1 of class scala/util/parsing/combinator/lexical/StdLexical
   public final #359= #306 of #39; //$anonfun$token$10=class scala/util/parsing/combinator/lexical/StdLexical$$anonfun$token$10 of class scala/util/parsing/combinator/lexical/StdLexical
   public final #360= #205 of #39; //$anonfun$_delim$3=class scala/util/parsing/combinator/lexical/StdLexical$$anonfun$_delim$3 of class scala/util/parsing/combinator/lexical/StdLexical
   public final #361= #181 of #39; //$anonfun$_delim$2=class scala/util/parsing/combinator/lexical/StdLexical$$anonfun$_delim$2 of class scala/util/parsing/combinator/lexical/StdLexical
   public final #362= #165 of #39; //$anonfun$_delim$1=class scala/util/parsing/combinator/lexical/StdLexical$$anonfun$_delim$1 of class scala/util/parsing/combinator/lexical/StdLexical
   public final #363= #254 of #39; //$anonfun$comment$3=class scala/util/parsing/combinator/lexical/StdLexical$$anonfun$comment$3 of class scala/util/parsing/combinator/lexical/StdLexical
   public final #364= #251 of #39; //$anonfun$comment$2=class scala/util/parsing/combinator/lexical/StdLexical$$anonfun$comment$2 of class scala/util/parsing/combinator/lexical/StdLexical
   public final #365= #244 of #39; //$anonfun$comment$1=class scala/util/parsing/combinator/lexical/StdLexical$$anonfun$comment$1 of class scala/util/parsing/combinator/lexical/StdLexical
   public final #366= #272 of #39; //$anonfun$identChar$1=class scala/util/parsing/combinator/lexical/StdLexical$$anonfun$identChar$1 of class scala/util/parsing/combinator/lexical/StdLexical
   public final #367= #262 of #39; //$anonfun$whitespace$1=class scala/util/parsing/combinator/lexical/StdLexical$$anonfun$whitespace$1 of class scala/util/parsing/combinator/lexical/StdLexical
   public final #368= #73 of #39; //$anonfun$parseDelim$1$1=class scala/util/parsing/combinator/lexical/StdLexical$$anonfun$parseDelim$1$1 of class scala/util/parsing/combinator/lexical/StdLexical
   public #371= #189 of #370; //GenericCanBuildFrom=class scala/collection/generic/TraversableFactory$GenericCanBuildFrom of class scala/collection/generic/TraversableFactory
  minor version: 0
  major version: 49
  Constant pool:
const #1 = Asciz	SourceFile;
const #2 = Asciz	StdLexical.scala;
const #3 = Asciz	Identifier$module;
const #4 = Asciz	Lscala/util/parsing/syntax/StdTokens$Identifier$;;
const #5 = Asciz	StringLit$module;
const #6 = Asciz	Lscala/util/parsing/syntax/StdTokens$StringLit$;;
const #7 = Asciz	NumericLit$module;
const #8 = Asciz	Lscala/util/parsing/syntax/StdTokens$NumericLit$;;
const #9 = Asciz	Keyword$module;
const #10 = Asciz	Lscala/util/parsing/syntax/StdTokens$Keyword$;;
const #11 = Asciz	bitmap$0;
const #12 = Asciz	I;
const #13 = Asciz	_delim;
const #14 = Asciz	Lscala/util/parsing/combinator/Parsers$Parser;;
const #15 = Asciz	Lscala/util/parsing/combinator/Parsers$Parser<Lscala/util/parsing/syntax/Tokens$Token;>;;
const #16 = Asciz	Signature;
const #17 = Asciz	delimiters;
const #18 = Asciz	Lscala/collection/mutable/HashSet;;
const #19 = Asciz	Lscala/collection/mutable/HashSet<Ljava/lang/String;>;;
const #20 = Asciz	reserved;
const #21 = Asciz	<init>;
const #22 = Asciz	()V;
const #23 = Asciz	Code;
const #24 = Asciz	LineNumberTable;
const #25 = Asciz	scala/util/parsing/combinator/lexical/Lexical;
const #26 = class	#25;	//  scala/util/parsing/combinator/lexical/Lexical
const #27 = NameAndType	#21:#22;//  "<init>":()V
const #28 = Method	#26.#27;	//  scala/util/parsing/combinator/lexical/Lexical."<init>":()V
const #29 = Asciz	scala/util/parsing/syntax/StdTokens$class;
const #30 = class	#29;	//  scala/util/parsing/syntax/StdTokens$class
const #31 = Asciz	$init$;
const #32 = Asciz	(Lscala/util/parsing/syntax/StdTokens;)V;
const #33 = NameAndType	#31:#32;//  $init$:(Lscala/util/parsing/syntax/StdTokens;)V
const #34 = Method	#30.#33;	//  scala/util/parsing/syntax/StdTokens$class.$init$:(Lscala/util/parsing/syntax/StdTokens;)V
const #35 = Asciz	scala/collection/mutable/HashSet;
const #36 = class	#35;	//  scala/collection/mutable/HashSet
const #37 = Method	#36.#27;	//  scala/collection/mutable/HashSet."<init>":()V
const #38 = Asciz	scala/util/parsing/combinator/lexical/StdLexical;
const #39 = class	#38;	//  scala/util/parsing/combinator/lexical/StdLexical
const #40 = NameAndType	#20:#18;//  reserved:Lscala/collection/mutable/HashSet;
const #41 = Field	#39.#40;	//  scala/util/parsing/combinator/lexical/StdLexical.reserved:Lscala/collection/mutable/HashSet;
const #42 = NameAndType	#17:#18;//  delimiters:Lscala/collection/mutable/HashSet;
const #43 = Field	#39.#42;	//  scala/util/parsing/combinator/lexical/StdLexical.delimiters:Lscala/collection/mutable/HashSet;
const #44 = Asciz	parseDelim$1;
const #45 = Asciz	(Ljava/lang/String;)Lscala/util/parsing/combinator/Parsers$Parser;;
const #46 = Asciz	scala/Predef$;
const #47 = class	#46;	//  scala/Predef$
const #48 = Asciz	MODULE$;
const #49 = Asciz	Lscala/Predef$;;
const #50 = NameAndType	#48:#49;//  MODULE$:Lscala/Predef$;
const #51 = Field	#47.#50;	//  scala/Predef$.MODULE$:Lscala/Predef$;
const #52 = Asciz	augmentString;
const #53 = Asciz	(Ljava/lang/String;)Lscala/collection/immutable/StringOps;;
const #54 = NameAndType	#52:#53;//  augmentString:(Ljava/lang/String;)Lscala/collection/immutable/StringOps;
const #55 = Method	#47.#54;	//  scala/Predef$.augmentString:(Ljava/lang/String;)Lscala/collection/immutable/StringOps;
const #56 = Asciz	scala/collection/TraversableLike;
const #57 = class	#56;	//  scala/collection/TraversableLike
const #58 = Asciz	toList;
const #59 = Asciz	()Lscala/collection/immutable/List;;
const #60 = NameAndType	#58:#59;//  toList:()Lscala/collection/immutable/List;
const #61 = InterfaceMethod	#57.#60;	//  scala/collection/TraversableLike.toList:()Lscala/collection/immutable/List;
const #62 = Asciz	conforms;
const #63 = Asciz	()Lscala/Predef$$less$colon$less;;
const #64 = NameAndType	#62:#63;//  conforms:()Lscala/Predef$$less$colon$less;
const #65 = Method	#47.#64;	//  scala/Predef$.conforms:()Lscala/Predef$$less$colon$less;
const #66 = Asciz	scala/util/parsing/combinator/Parsers;
const #67 = class	#66;	//  scala/util/parsing/combinator/Parsers
const #68 = Asciz	accept;
const #69 = Asciz	(Ljava/lang/Object;Lscala/Function1;)Lscala/util/parsing/combinator/Parsers$Parser;;
const #70 = NameAndType	#68:#69;//  accept:(Ljava/lang/Object;Lscala/Function1;)Lscala/util/parsing/combinator/Parsers$Parser;
const #71 = InterfaceMethod	#67.#70;	//  scala/util/parsing/combinator/Parsers.accept:(Ljava/lang/Object;Lscala/Function1;)Lscala/util/parsing/combinator/Parsers$Parser;
const #72 = Asciz	scala/util/parsing/combinator/lexical/StdLexical$$anonfun$parseDelim$1$1;
const #73 = class	#72;	//  scala/util/parsing/combinator/lexical/StdLexical$$anonfun$parseDelim$1$1
const #74 = Asciz	(Lscala/util/parsing/combinator/lexical/StdLexical;Ljava/lang/String;)V;
const #75 = NameAndType	#21:#74;//  "<init>":(Lscala/util/parsing/combinator/lexical/StdLexical;Ljava/lang/String;)V
const #76 = Method	#73.#75;	//  scala/util/parsing/combinator/lexical/StdLexical$$anonfun$parseDelim$1$1."<init>":(Lscala/util/parsing/combinator/lexical/StdLexical;Ljava/lang/String;)V
const #77 = Asciz	scala/util/parsing/combinator/Parsers$Parser;
const #78 = class	#77;	//  scala/util/parsing/combinator/Parsers$Parser
const #79 = Asciz	$up$up;
const #80 = Asciz	(Lscala/Function1;)Lscala/util/parsing/combinator/Parsers$Parser;;
const #81 = NameAndType	#79:#80;//  $up$up:(Lscala/Function1;)Lscala/util/parsing/combinator/Parsers$Parser;
const #82 = Method	#78.#81;	//  scala/util/parsing/combinator/Parsers$Parser.$up$up:(Lscala/Function1;)Lscala/util/parsing/combinator/Parsers$Parser;
const #83 = Asciz	this;
const #84 = Asciz	Lscala/util/parsing/combinator/lexical/StdLexical;;
const #85 = Asciz	s$1;
const #86 = Asciz	Ljava/lang/String;;
const #87 = Asciz	LocalVariableTable;
const #88 = Asciz	lift2;
const #89 = Asciz	(Lscala/Function1;Lscala/util/parsing/combinator/Parsers$$tilde;)Ljava/lang/Object;;
const #90 = Asciz	scala/util/parsing/combinator/Parsers$$tilde;
const #91 = class	#90;	//  scala/util/parsing/combinator/Parsers$$tilde
const #92 = Asciz	_1;
const #93 = Asciz	()Ljava/lang/Object;;
const #94 = NameAndType	#92:#93;//  _1:()Ljava/lang/Object;
const #95 = Method	#91.#94;	//  scala/util/parsing/combinator/Parsers$$tilde._1:()Ljava/lang/Object;
const #96 = Asciz	scala/runtime/BoxesRunTime;
const #97 = class	#96;	//  scala/runtime/BoxesRunTime
const #98 = Asciz	unboxToChar;
const #99 = Asciz	(Ljava/lang/Object;)C;
const #100 = NameAndType	#98:#99;//  unboxToChar:(Ljava/lang/Object;)C
const #101 = Method	#97.#100;	//  scala/runtime/BoxesRunTime.unboxToChar:(Ljava/lang/Object;)C
const #102 = Asciz	_2;
const #103 = NameAndType	#102:#93;//  _2:()Ljava/lang/Object;
const #104 = Method	#91.#103;	//  scala/util/parsing/combinator/Parsers$$tilde._2:()Ljava/lang/Object;
const #105 = Asciz	scala/collection/immutable/List;
const #106 = class	#105;	//  scala/collection/immutable/List
const #107 = Asciz	boxToCharacter;
const #108 = Asciz	(C)Ljava/lang/Character;;
const #109 = NameAndType	#107:#108;//  boxToCharacter:(C)Ljava/lang/Character;
const #110 = Method	#97.#109;	//  scala/runtime/BoxesRunTime.boxToCharacter:(C)Ljava/lang/Character;
const #111 = Asciz	$colon$colon;
const #112 = Asciz	(Ljava/lang/Object;)Lscala/collection/immutable/List;;
const #113 = NameAndType	#111:#112;//  $colon$colon:(Ljava/lang/Object;)Lscala/collection/immutable/List;
const #114 = Method	#106.#113;	//  scala/collection/immutable/List.$colon$colon:(Ljava/lang/Object;)Lscala/collection/immutable/List;
const #115 = Asciz	lift;
const #116 = Asciz	(Lscala/Function1;Lscala/collection/immutable/List;)Ljava/lang/Object;;
const #117 = NameAndType	#115:#116;//  lift:(Lscala/Function1;Lscala/collection/immutable/List;)Ljava/lang/Object;
const #118 = Method	#39.#117;	//  scala/util/parsing/combinator/lexical/StdLexical.lift:(Lscala/Function1;Lscala/collection/immutable/List;)Ljava/lang/Object;
const #119 = Asciz	f;
const #120 = Asciz	Lscala/Function1;;
const #121 = Asciz	p;
const #122 = Asciz	Lscala/util/parsing/combinator/Parsers$$tilde;;
const #123 = Asciz	<T:Ljava/lang/Object;>(Lscala/Function1<Ljava/lang/String;TT;>;Lscala/util/parsing/combinator/Parsers$$tilde<Ljava/lang/Character;Lscala/collection/immutable/List<Ljava/lang/Character;>;>;)TT;;
const #124 = Asciz	;
const #125 = String	#124;	//  
const #126 = Asciz	mkString;
const #127 = Asciz	(Ljava/lang/String;Ljava/lang/String;Ljava/lang/String;)Ljava/lang/String;;
const #128 = NameAndType	#126:#127;//  mkString:(Ljava/lang/String;Ljava/lang/String;Ljava/lang/String;)Ljava/lang/String;
const #129 = InterfaceMethod	#57.#128;	//  scala/collection/TraversableLike.mkString:(Ljava/lang/String;Ljava/lang/String;Ljava/lang/String;)Ljava/lang/String;
const #130 = Asciz	scala/Function1;
const #131 = class	#130;	//  scala/Function1
const #132 = Asciz	apply;
const #133 = Asciz	(Ljava/lang/Object;)Ljava/lang/Object;;
const #134 = NameAndType	#132:#133;//  apply:(Ljava/lang/Object;)Ljava/lang/Object;
const #135 = InterfaceMethod	#131.#134;	//  scala/Function1.apply:(Ljava/lang/Object;)Ljava/lang/Object;
const #136 = Asciz	xs;
const #137 = Asciz	Lscala/collection/immutable/List;;
const #138 = Asciz	<T:Ljava/lang/Object;>(Lscala/Function1<Ljava/lang/String;TT;>;Lscala/collection/immutable/List<Ljava/lang/Character;>;)TT;;
const #139 = Asciz	delim;
const #140 = Asciz	()Lscala/util/parsing/combinator/Parsers$Parser;;
const #141 = NameAndType	#13:#140;//  _delim:()Lscala/util/parsing/combinator/Parsers$Parser;
const #142 = Method	#39.#141;	//  scala/util/parsing/combinator/lexical/StdLexical._delim:()Lscala/util/parsing/combinator/Parsers$Parser;
const #143 = Asciz	()Lscala/util/parsing/combinator/Parsers$Parser<Lscala/util/parsing/syntax/Tokens$Token;>;;
const #144 = NameAndType	#11:#12;//  bitmap$0:I
const #145 = Field	#39.#144;	//  scala/util/parsing/combinator/lexical/StdLexical.bitmap$0:I
const #146 = Asciz	()Lscala/collection/mutable/HashSet;;
const #147 = NameAndType	#17:#146;//  delimiters:()Lscala/collection/mutable/HashSet;
const #148 = Method	#39.#147;	//  scala/util/parsing/combinator/lexical/StdLexical.delimiters:()Lscala/collection/mutable/HashSet;
const #149 = Asciz	size;
const #150 = Asciz	()I;
const #151 = NameAndType	#149:#150;//  size:()I
const #152 = Method	#36.#151;	//  scala/collection/mutable/HashSet.size:()I
const #153 = Asciz	java/lang/String;
const #154 = class	#153;	//  java/lang/String
const #155 = Asciz	copyToArray;
const #156 = Asciz	(Ljava/lang/Object;I)V;
const #157 = NameAndType	#155:#156;//  copyToArray:(Ljava/lang/Object;I)V
const #158 = InterfaceMethod	#57.#157;	//  scala/collection/TraversableLike.copyToArray:(Ljava/lang/Object;I)V
const #159 = Asciz	scala/util/Sorting$;
const #160 = class	#159;	//  scala/util/Sorting$
const #161 = Asciz	Lscala/util/Sorting$;;
const #162 = NameAndType	#48:#161;//  MODULE$:Lscala/util/Sorting$;
const #163 = Field	#160.#162;	//  scala/util/Sorting$.MODULE$:Lscala/util/Sorting$;
const #164 = Asciz	scala/util/parsing/combinator/lexical/StdLexical$$anonfun$_delim$1;
const #165 = class	#164;	//  scala/util/parsing/combinator/lexical/StdLexical$$anonfun$_delim$1
const #166 = Asciz	(Lscala/util/parsing/combinator/lexical/StdLexical;)V;
const #167 = NameAndType	#21:#166;//  "<init>":(Lscala/util/parsing/combinator/lexical/StdLexical;)V
const #168 = Method	#165.#167;	//  scala/util/parsing/combinator/lexical/StdLexical$$anonfun$_delim$1."<init>":(Lscala/util/parsing/combinator/lexical/StdLexical;)V
const #169 = Asciz	quickSort;
const #170 = Asciz	(Ljava/lang/Object;Lscala/Function1;)V;
const #171 = NameAndType	#169:#170;//  quickSort:(Ljava/lang/Object;Lscala/Function1;)V
const #172 = Method	#160.#171;	//  scala/util/Sorting$.quickSort:(Ljava/lang/Object;Lscala/Function1;)V
const #173 = Asciz	[Ljava/lang/Object;;
const #174 = class	#173;	//  "[Ljava/lang/Object;"
const #175 = Asciz	scala/collection/mutable/ArrayOps$ofRef;
const #176 = class	#175;	//  scala/collection/mutable/ArrayOps$ofRef
const #177 = Asciz	([Ljava/lang/Object;)V;
const #178 = NameAndType	#21:#177;//  "<init>":([Ljava/lang/Object;)V
const #179 = Method	#176.#178;	//  scala/collection/mutable/ArrayOps$ofRef."<init>":([Ljava/lang/Object;)V
const #180 = Asciz	scala/util/parsing/combinator/lexical/StdLexical$$anonfun$_delim$2;
const #181 = class	#180;	//  scala/util/parsing/combinator/lexical/StdLexical$$anonfun$_delim$2
const #182 = Method	#181.#167;	//  scala/util/parsing/combinator/lexical/StdLexical$$anonfun$_delim$2."<init>":(Lscala/util/parsing/combinator/lexical/StdLexical;)V
const #183 = Asciz	scala/collection/immutable/List$;
const #184 = class	#183;	//  scala/collection/immutable/List$
const #185 = Asciz	Lscala/collection/immutable/List$;;
const #186 = NameAndType	#48:#185;//  MODULE$:Lscala/collection/immutable/List$;
const #187 = Field	#184.#186;	//  scala/collection/immutable/List$.MODULE$:Lscala/collection/immutable/List$;
const #188 = Asciz	scala/collection/generic/TraversableFactory$GenericCanBuildFrom;
const #189 = class	#188;	//  scala/collection/generic/TraversableFactory$GenericCanBuildFrom
const #190 = Asciz	(Lscala/collection/generic/TraversableFactory;)V;
const #191 = NameAndType	#21:#190;//  "<init>":(Lscala/collection/generic/TraversableFactory;)V
const #192 = Method	#189.#191;	//  scala/collection/generic/TraversableFactory$GenericCanBuildFrom."<init>":(Lscala/collection/generic/TraversableFactory;)V
const #193 = Asciz	map;
const #194 = Asciz	(Lscala/Function1;Lscala/collection/generic/CanBuildFrom;)Ljava/lang/Object;;
const #195 = NameAndType	#193:#194;//  map:(Lscala/Function1;Lscala/collection/generic/CanBuildFrom;)Ljava/lang/Object;
const #196 = InterfaceMethod	#57.#195;	//  scala/collection/TraversableLike.map:(Lscala/Function1;Lscala/collection/generic/CanBuildFrom;)Ljava/lang/Object;
const #197 = Asciz	scala/collection/LinearSeqLike;
const #198 = class	#197;	//  scala/collection/LinearSeqLike
const #199 = Asciz	no matching delimiter;
const #200 = String	#199;	//  no matching delimiter
const #201 = Asciz	failure;
const #202 = NameAndType	#201:#45;//  failure:(Ljava/lang/String;)Lscala/util/parsing/combinator/Parsers$Parser;
const #203 = InterfaceMethod	#67.#202;	//  scala/util/parsing/combinator/Parsers.failure:(Ljava/lang/String;)Lscala/util/parsing/combinator/Parsers$Parser;
const #204 = Asciz	scala/util/parsing/combinator/lexical/StdLexical$$anonfun$_delim$3;
const #205 = class	#204;	//  scala/util/parsing/combinator/lexical/StdLexical$$anonfun$_delim$3
const #206 = Method	#205.#167;	//  scala/util/parsing/combinator/lexical/StdLexical$$anonfun$_delim$3."<init>":(Lscala/util/parsing/combinator/lexical/StdLexical;)V
const #207 = Asciz	foldRight;
const #208 = Asciz	(Ljava/lang/Object;Lscala/Function2;)Ljava/lang/Object;;
const #209 = NameAndType	#207:#208;//  foldRight:(Ljava/lang/Object;Lscala/Function2;)Ljava/lang/Object;
const #210 = InterfaceMethod	#198.#209;	//  scala/collection/LinearSeqLike.foldRight:(Ljava/lang/Object;Lscala/Function2;)Ljava/lang/Object;
const #211 = NameAndType	#13:#14;//  _delim:Lscala/util/parsing/combinator/Parsers$Parser;
const #212 = Field	#39.#211;	//  scala/util/parsing/combinator/lexical/StdLexical._delim:Lscala/util/parsing/combinator/Parsers$Parser;
const #213 = Asciz	java/lang/Throwable;
const #214 = class	#213;	//  java/lang/Throwable
const #215 = Asciz	d;
const #216 = Asciz	[Ljava/lang/String;;
const #217 = Asciz	xs0;
const #218 = Asciz	$inlThis1;
const #219 = Asciz	Ljava/lang/Object;;
const #220 = Asciz	processIdent;
const #221 = Asciz	(Ljava/lang/String;)Lscala/Product;;
const #222 = NameAndType	#20:#146;//  reserved:()Lscala/collection/mutable/HashSet;
const #223 = Method	#39.#222;	//  scala/util/parsing/combinator/lexical/StdLexical.reserved:()Lscala/collection/mutable/HashSet;
const #224 = Asciz	contains;
const #225 = Asciz	(Ljava/lang/Object;)Z;
const #226 = NameAndType	#224:#225;//  contains:(Ljava/lang/Object;)Z
const #227 = Method	#36.#226;	//  scala/collection/mutable/HashSet.contains:(Ljava/lang/Object;)Z
const #228 = Asciz	scala/util/parsing/syntax/StdTokens$Keyword;
const #229 = class	#228;	//  scala/util/parsing/syntax/StdTokens$Keyword
const #230 = Asciz	(Lscala/util/parsing/syntax/StdTokens;Ljava/lang/String;)V;
const #231 = NameAndType	#21:#230;//  "<init>":(Lscala/util/parsing/syntax/StdTokens;Ljava/lang/String;)V
const #232 = Method	#229.#231;	//  scala/util/parsing/syntax/StdTokens$Keyword."<init>":(Lscala/util/parsing/syntax/StdTokens;Ljava/lang/String;)V
const #233 = Asciz	scala/util/parsing/syntax/StdTokens$Identifier;
const #234 = class	#233;	//  scala/util/parsing/syntax/StdTokens$Identifier
const #235 = Method	#234.#231;	//  scala/util/parsing/syntax/StdTokens$Identifier."<init>":(Lscala/util/parsing/syntax/StdTokens;Ljava/lang/String;)V
const #236 = Asciz	name;
const #237 = Asciz	()Lscala/collection/mutable/HashSet<Ljava/lang/String;>;;
const #238 = Asciz	comment;
const #239 = int	42;
const #240 = Asciz	(Ljava/lang/Object;)Lscala/util/parsing/combinator/Parsers$Parser;;
const #241 = NameAndType	#68:#240;//  accept:(Ljava/lang/Object;)Lscala/util/parsing/combinator/Parsers$Parser;
const #242 = InterfaceMethod	#67.#241;	//  scala/util/parsing/combinator/Parsers.accept:(Ljava/lang/Object;)Lscala/util/parsing/combinator/Parsers$Parser;
const #243 = Asciz	scala/util/parsing/combinator/lexical/StdLexical$$anonfun$comment$1;
const #244 = class	#243;	//  scala/util/parsing/combinator/lexical/StdLexical$$anonfun$comment$1
const #245 = Method	#244.#167;	//  scala/util/parsing/combinator/lexical/StdLexical$$anonfun$comment$1."<init>":(Lscala/util/parsing/combinator/lexical/StdLexical;)V
const #246 = Asciz	$tilde;
const #247 = Asciz	(Lscala/Function0;)Lscala/util/parsing/combinator/Parsers$Parser;;
const #248 = NameAndType	#246:#247;//  $tilde:(Lscala/Function0;)Lscala/util/parsing/combinator/Parsers$Parser;
const #249 = Method	#78.#248;	//  scala/util/parsing/combinator/Parsers$Parser.$tilde:(Lscala/Function0;)Lscala/util/parsing/combinator/Parsers$Parser;
const #250 = Asciz	scala/util/parsing/combinator/lexical/StdLexical$$anonfun$comment$2;
const #251 = class	#250;	//  scala/util/parsing/combinator/lexical/StdLexical$$anonfun$comment$2
const #252 = Method	#251.#167;	//  scala/util/parsing/combinator/lexical/StdLexical$$anonfun$comment$2."<init>":(Lscala/util/parsing/combinator/lexical/StdLexical;)V
const #253 = Asciz	scala/util/parsing/combinator/lexical/StdLexical$$anonfun$comment$3;
const #254 = class	#253;	//  scala/util/parsing/combinator/lexical/StdLexical$$anonfun$comment$3
const #255 = Method	#254.#167;	//  scala/util/parsing/combinator/lexical/StdLexical$$anonfun$comment$3."<init>":(Lscala/util/parsing/combinator/lexical/StdLexical;)V
const #256 = Asciz	$bar;
const #257 = NameAndType	#256:#247;//  $bar:(Lscala/Function0;)Lscala/util/parsing/combinator/Parsers$Parser;
const #258 = Method	#78.#257;	//  scala/util/parsing/combinator/Parsers$Parser.$bar:(Lscala/Function0;)Lscala/util/parsing/combinator/Parsers$Parser;
const #259 = Asciz	()Lscala/util/parsing/combinator/Parsers$Parser<Ljava/lang/Object;>;;
const #260 = Asciz	whitespace;
const #261 = Asciz	scala/util/parsing/combinator/lexical/StdLexical$$anonfun$whitespace$1;
const #262 = class	#261;	//  scala/util/parsing/combinator/lexical/StdLexical$$anonfun$whitespace$1
const #263 = Method	#262.#167;	//  scala/util/parsing/combinator/lexical/StdLexical$$anonfun$whitespace$1."<init>":(Lscala/util/parsing/combinator/lexical/StdLexical;)V
const #264 = Asciz	rep;
const #265 = NameAndType	#264:#247;//  rep:(Lscala/Function0;)Lscala/util/parsing/combinator/Parsers$Parser;
const #266 = InterfaceMethod	#67.#265;	//  scala/util/parsing/combinator/Parsers.rep:(Lscala/Function0;)Lscala/util/parsing/combinator/Parsers$Parser;
const #267 = Asciz	identChar;
const #268 = Asciz	letter;
const #269 = NameAndType	#268:#140;//  letter:()Lscala/util/parsing/combinator/Parsers$Parser;
const #270 = Method	#39.#269;	//  scala/util/parsing/combinator/lexical/StdLexical.letter:()Lscala/util/parsing/combinator/Parsers$Parser;
const #271 = Asciz	scala/util/parsing/combinator/lexical/StdLexical$$anonfun$identChar$1;
const #272 = class	#271;	//  scala/util/parsing/combinator/lexical/StdLexical$$anonfun$identChar$1
const #273 = Method	#272.#167;	//  scala/util/parsing/combinator/lexical/StdLexical$$anonfun$identChar$1."<init>":(Lscala/util/parsing/combinator/lexical/StdLexical;)V
const #274 = Asciz	()Lscala/util/parsing/combinator/Parsers$Parser<Ljava/lang/Character;>;;
const #275 = Asciz	token;
const #276 = NameAndType	#267:#140;//  identChar:()Lscala/util/parsing/combinator/Parsers$Parser;
const #277 = Method	#39.#276;	//  scala/util/parsing/combinator/lexical/StdLexical.identChar:()Lscala/util/parsing/combinator/Parsers$Parser;
const #278 = Asciz	scala/util/parsing/combinator/lexical/StdLexical$$anonfun$token$1;
const #279 = class	#278;	//  scala/util/parsing/combinator/lexical/StdLexical$$anonfun$token$1
const #280 = Method	#279.#167;	//  scala/util/parsing/combinator/lexical/StdLexical$$anonfun$token$1."<init>":(Lscala/util/parsing/combinator/lexical/StdLexical;)V
const #281 = Asciz	scala/util/parsing/combinator/lexical/StdLexical$$anonfun$token$2;
const #282 = class	#281;	//  scala/util/parsing/combinator/lexical/StdLexical$$anonfun$token$2
const #283 = Method	#282.#167;	//  scala/util/parsing/combinator/lexical/StdLexical$$anonfun$token$2."<init>":(Lscala/util/parsing/combinator/lexical/StdLexical;)V
const #284 = Asciz	scala/util/parsing/combinator/lexical/StdLexical$$anonfun$token$3;
const #285 = class	#284;	//  scala/util/parsing/combinator/lexical/StdLexical$$anonfun$token$3
const #286 = Method	#285.#167;	//  scala/util/parsing/combinator/lexical/StdLexical$$anonfun$token$3."<init>":(Lscala/util/parsing/combinator/lexical/StdLexical;)V
const #287 = Asciz	scala/util/parsing/combinator/lexical/StdLexical$$anonfun$token$4;
const #288 = class	#287;	//  scala/util/parsing/combinator/lexical/StdLexical$$anonfun$token$4
const #289 = Method	#288.#167;	//  scala/util/parsing/combinator/lexical/StdLexical$$anonfun$token$4."<init>":(Lscala/util/parsing/combinator/lexical/StdLexical;)V
const #290 = Asciz	scala/util/parsing/combinator/lexical/StdLexical$$anonfun$token$5;
const #291 = class	#290;	//  scala/util/parsing/combinator/lexical/StdLexical$$anonfun$token$5
const #292 = Method	#291.#167;	//  scala/util/parsing/combinator/lexical/StdLexical$$anonfun$token$5."<init>":(Lscala/util/parsing/combinator/lexical/StdLexical;)V
const #293 = Asciz	scala/util/parsing/combinator/lexical/StdLexical$$anonfun$token$6;
const #294 = class	#293;	//  scala/util/parsing/combinator/lexical/StdLexical$$anonfun$token$6
const #295 = Method	#294.#167;	//  scala/util/parsing/combinator/lexical/StdLexical$$anonfun$token$6."<init>":(Lscala/util/parsing/combinator/lexical/StdLexical;)V
const #296 = Asciz	scala/util/parsing/combinator/lexical/StdLexical$$anonfun$token$7;
const #297 = class	#296;	//  scala/util/parsing/combinator/lexical/StdLexical$$anonfun$token$7
const #298 = Method	#297.#167;	//  scala/util/parsing/combinator/lexical/StdLexical$$anonfun$token$7."<init>":(Lscala/util/parsing/combinator/lexical/StdLexical;)V
const #299 = Asciz	scala/util/parsing/combinator/lexical/StdLexical$$anonfun$token$8;
const #300 = class	#299;	//  scala/util/parsing/combinator/lexical/StdLexical$$anonfun$token$8
const #301 = Method	#300.#167;	//  scala/util/parsing/combinator/lexical/StdLexical$$anonfun$token$8."<init>":(Lscala/util/parsing/combinator/lexical/StdLexical;)V
const #302 = Asciz	scala/util/parsing/combinator/lexical/StdLexical$$anonfun$token$9;
const #303 = class	#302;	//  scala/util/parsing/combinator/lexical/StdLexical$$anonfun$token$9
const #304 = Method	#303.#167;	//  scala/util/parsing/combinator/lexical/StdLexical$$anonfun$token$9."<init>":(Lscala/util/parsing/combinator/lexical/StdLexical;)V
const #305 = Asciz	scala/util/parsing/combinator/lexical/StdLexical$$anonfun$token$10;
const #306 = class	#305;	//  scala/util/parsing/combinator/lexical/StdLexical$$anonfun$token$10
const #307 = Method	#306.#167;	//  scala/util/parsing/combinator/lexical/StdLexical$$anonfun$token$10."<init>":(Lscala/util/parsing/combinator/lexical/StdLexical;)V
const #308 = Asciz	Identifier;
const #309 = Asciz	()Lscala/util/parsing/syntax/StdTokens$Identifier$;;
const #310 = NameAndType	#3:#4;//  Identifier$module:Lscala/util/parsing/syntax/StdTokens$Identifier$;
const #311 = Field	#39.#310;	//  scala/util/parsing/combinator/lexical/StdLexical.Identifier$module:Lscala/util/parsing/syntax/StdTokens$Identifier$;
const #312 = Asciz	scala/util/parsing/syntax/StdTokens$Identifier$;
const #313 = class	#312;	//  scala/util/parsing/syntax/StdTokens$Identifier$
const #314 = NameAndType	#21:#32;//  "<init>":(Lscala/util/parsing/syntax/StdTokens;)V
const #315 = Method	#313.#314;	//  scala/util/parsing/syntax/StdTokens$Identifier$."<init>":(Lscala/util/parsing/syntax/StdTokens;)V
const #316 = Asciz	StringLit;
const #317 = Asciz	()Lscala/util/parsing/syntax/StdTokens$StringLit$;;
const #318 = NameAndType	#5:#6;//  StringLit$module:Lscala/util/parsing/syntax/StdTokens$StringLit$;
const #319 = Field	#39.#318;	//  scala/util/parsing/combinator/lexical/StdLexical.StringLit$module:Lscala/util/parsing/syntax/StdTokens$StringLit$;
const #320 = Asciz	scala/util/parsing/syntax/StdTokens$StringLit$;
const #321 = class	#320;	//  scala/util/parsing/syntax/StdTokens$StringLit$
const #322 = Method	#321.#314;	//  scala/util/parsing/syntax/StdTokens$StringLit$."<init>":(Lscala/util/parsing/syntax/StdTokens;)V
const #323 = Asciz	NumericLit;
const #324 = Asciz	()Lscala/util/parsing/syntax/StdTokens$NumericLit$;;
const #325 = NameAndType	#7:#8;//  NumericLit$module:Lscala/util/parsing/syntax/StdTokens$NumericLit$;
const #326 = Field	#39.#325;	//  scala/util/parsing/combinator/lexical/StdLexical.NumericLit$module:Lscala/util/parsing/syntax/StdTokens$NumericLit$;
const #327 = Asciz	scala/util/parsing/syntax/StdTokens$NumericLit$;
const #328 = class	#327;	//  scala/util/parsing/syntax/StdTokens$NumericLit$
const #329 = Method	#328.#314;	//  scala/util/parsing/syntax/StdTokens$NumericLit$."<init>":(Lscala/util/parsing/syntax/StdTokens;)V
const #330 = Asciz	Keyword;
const #331 = Asciz	()Lscala/util/parsing/syntax/StdTokens$Keyword$;;
const #332 = NameAndType	#9:#10;//  Keyword$module:Lscala/util/parsing/syntax/StdTokens$Keyword$;
const #333 = Field	#39.#332;	//  scala/util/parsing/combinator/lexical/StdLexical.Keyword$module:Lscala/util/parsing/syntax/StdTokens$Keyword$;
const #334 = Asciz	scala/util/parsing/syntax/StdTokens$Keyword$;
const #335 = class	#334;	//  scala/util/parsing/syntax/StdTokens$Keyword$
const #336 = Method	#335.#314;	//  scala/util/parsing/syntax/StdTokens$Keyword$."<init>":(Lscala/util/parsing/syntax/StdTokens;)V
const #337 = Asciz	ScalaSig;
const #338 = Asciz	InnerClasses;
const #339 = Asciz	scala/collection/mutable/ArrayOps;
const #340 = class	#339;	//  scala/collection/mutable/ArrayOps
const #341 = Asciz	ofRef;
const #342 = Asciz	Parser;
const #343 = Asciz	scala/util/parsing/syntax/StdTokens;
const #344 = class	#343;	//  scala/util/parsing/syntax/StdTokens
const #345 = Asciz	scala/Predef$$less$colon$less;
const #346 = class	#345;	//  scala/Predef$$less$colon$less
const #347 = Asciz	scala/Predef;
const #348 = class	#347;	//  scala/Predef
const #349 = Asciz	$less$colon$less;
const #350 = Asciz	$anonfun$token$9;
const #351 = Asciz	$anonfun$token$8;
const #352 = Asciz	$anonfun$token$7;
const #353 = Asciz	$anonfun$token$6;
const #354 = Asciz	$anonfun$token$5;
const #355 = Asciz	$anonfun$token$4;
const #356 = Asciz	$anonfun$token$3;
const #357 = Asciz	$anonfun$token$2;
const #358 = Asciz	$anonfun$token$1;
const #359 = Asciz	$anonfun$token$10;
const #360 = Asciz	$anonfun$_delim$3;
const #361 = Asciz	$anonfun$_delim$2;
const #362 = Asciz	$anonfun$_delim$1;
const #363 = Asciz	$anonfun$comment$3;
const #364 = Asciz	$anonfun$comment$2;
const #365 = Asciz	$anonfun$comment$1;
const #366 = Asciz	$anonfun$identChar$1;
const #367 = Asciz	$anonfun$whitespace$1;
const #368 = Asciz	$anonfun$parseDelim$1$1;
const #369 = Asciz	scala/collection/generic/TraversableFactory;
const #370 = class	#369;	//  scala/collection/generic/TraversableFactory
const #371 = Asciz	GenericCanBuildFrom;
const #372 = Asciz	scala/ScalaObject;
const #373 = class	#372;	//  scala/ScalaObject

{
public volatile int bitmap$0;

public scala.util.parsing.combinator.lexical.StdLexical();
  Code:
   Stack=3, Locals=1, Args_size=1
   0:	aload_0
   1:	invokespecial	#28; //Method scala/util/parsing/combinator/lexical/Lexical."<init>":()V
   4:	aload_0
   5:	invokestatic	#34; //Method scala/util/parsing/syntax/StdTokens$class.$init$:(Lscala/util/parsing/syntax/StdTokens;)V
   8:	aload_0
   9:	new	#36; //class scala/collection/mutable/HashSet
   12:	dup
   13:	invokespecial	#37; //Method scala/collection/mutable/HashSet."<init>":()V
   16:	putfield	#41; //Field reserved:Lscala/collection/mutable/HashSet;
   19:	aload_0
   20:	new	#36; //class scala/collection/mutable/HashSet
   23:	dup
   24:	invokespecial	#37; //Method scala/collection/mutable/HashSet."<init>":()V
   27:	putfield	#43; //Field delimiters:Lscala/collection/mutable/HashSet;
   30:	return
  LineNumberTable: 
   line 36: 0
   line 67: 8
   line 70: 19


public final scala.util.parsing.combinator.Parsers$Parser parseDelim$1(java.lang.String);
  Code:
   Stack=5, Locals=2, Args_size=2
   0:	aload_0
   1:	getstatic	#51; //Field scala/Predef$.MODULE$:Lscala/Predef$;
   4:	aload_1
   5:	invokevirtual	#55; //Method scala/Predef$.augmentString:(Ljava/lang/String;)Lscala/collection/immutable/StringOps;
   8:	invokeinterface	#61,  1; //InterfaceMethod scala/collection/TraversableLike.toList:()Lscala/collection/immutable/List;
   13:	getstatic	#51; //Field scala/Predef$.MODULE$:Lscala/Predef$;
   16:	invokevirtual	#65; //Method scala/Predef$.conforms:()Lscala/Predef$$less$colon$less;
   19:	invokeinterface	#71,  3; //InterfaceMethod scala/util/parsing/combinator/Parsers.accept:(Ljava/lang/Object;Lscala/Function1;)Lscala/util/parsing/combinator/Parsers$Parser;
   24:	new	#73; //class scala/util/parsing/combinator/lexical/StdLexical$$anonfun$parseDelim$1$1
   27:	dup
   28:	aload_0
   29:	aload_1
   30:	invokespecial	#76; //Method scala/util/parsing/combinator/lexical/StdLexical$$anonfun$parseDelim$1$1."<init>":(Lscala/util/parsing/combinator/lexical/StdLexical;Ljava/lang/String;)V
   33:	invokevirtual	#82; //Method scala/util/parsing/combinator/Parsers$Parser.$up$up:(Lscala/Function1;)Lscala/util/parsing/combinator/Parsers$Parser;
   36:	areturn
  LineNumberTable: 
   line 79: 0

  LocalVariableTable: 
   Start  Length  Slot  Name   Signature
   0      37      0    this       Lscala/util/parsing/combinator/lexical/StdLexical;
   0      37      1    s$1       Ljava/lang/String;


public scala.util.parsing.combinator.Parsers$Parser delim();
  Code:
   Stack=1, Locals=1, Args_size=1
   0:	aload_0
   1:	invokespecial	#142; //Method _delim:()Lscala/util/parsing/combinator/Parsers$Parser;
   4:	areturn
  LineNumberTable: 
   line 86: 0

  Signature: length = 0x2
   00 FFFFFF8F 

public scala.Product processIdent(java.lang.String);
  Code:
   Stack=4, Locals=2, Args_size=2
   0:	aload_0
   1:	invokevirtual	#223; //Method reserved:()Lscala/collection/mutable/HashSet;
   4:	aload_1
   5:	invokevirtual	#227; //Method scala/collection/mutable/HashSet.contains:(Ljava/lang/Object;)Z
   8:	ifeq	23
   11:	new	#229; //class scala/util/parsing/syntax/StdTokens$Keyword
   14:	dup
   15:	aload_0
   16:	aload_1
   17:	invokespecial	#232; //Method scala/util/parsing/syntax/StdTokens$Keyword."<init>":(Lscala/util/parsing/syntax/StdTokens;Ljava/lang/String;)V
   20:	goto	32
   23:	new	#234; //class scala/util/parsing/syntax/StdTokens$Identifier
   26:	dup
   27:	aload_0
   28:	aload_1
   29:	invokespecial	#235; //Method scala/util/parsing/syntax/StdTokens$Identifier."<init>":(Lscala/util/parsing/syntax/StdTokens;Ljava/lang/String;)V
   32:	areturn
  LineNumberTable: 
   line 73: 0

  LocalVariableTable: 
   Start  Length  Slot  Name   Signature
   0      33      0    this       Lscala/util/parsing/combinator/lexical/StdLexical;
   0      33      1    name       Ljava/lang/String;


public scala.collection.mutable.HashSet delimiters();
  Code:
   Stack=1, Locals=1, Args_size=1
   0:	aload_0
   1:	getfield	#43; //Field delimiters:Lscala/collection/mutable/HashSet;
   4:	areturn
  LineNumberTable: 
   line 70: 0

  Signature: length = 0x2
   00 FFFFFFED 

public scala.collection.mutable.HashSet reserved();
  Code:
   Stack=1, Locals=1, Args_size=1
   0:	aload_0
   1:	getfield	#41; //Field reserved:Lscala/collection/mutable/HashSet;
   4:	areturn
  LineNumberTable: 
   line 67: 0

  Signature: length = 0x2
   00 FFFFFFED 

public scala.util.parsing.combinator.Parsers$Parser comment();
  Code:
   Stack=4, Locals=2, Args_size=1
   0:	aload_0
   1:	ldc	#239; //int 42
   3:	istore_1
   4:	iload_1
   5:	invokestatic	#110; //Method scala/runtime/BoxesRunTime.boxToCharacter:(C)Ljava/lang/Character;
   8:	invokeinterface	#242,  2; //InterfaceMethod scala/util/parsing/combinator/Parsers.accept:(Ljava/lang/Object;)Lscala/util/parsing/combinator/Parsers$Parser;
   13:	new	#244; //class scala/util/parsing/combinator/lexical/StdLexical$$anonfun$comment$1
   16:	dup
   17:	aload_0
   18:	invokespecial	#245; //Method scala/util/parsing/combinator/lexical/StdLexical$$anonfun$comment$1."<init>":(Lscala/util/parsing/combinator/lexical/StdLexical;)V
   21:	invokevirtual	#249; //Method scala/util/parsing/combinator/Parsers$Parser.$tilde:(Lscala/Function0;)Lscala/util/parsing/combinator/Parsers$Parser;
   24:	new	#251; //class scala/util/parsing/combinator/lexical/StdLexical$$anonfun$comment$2
   27:	dup
   28:	aload_0
   29:	invokespecial	#252; //Method scala/util/parsing/combinator/lexical/StdLexical$$anonfun$comment$2."<init>":(Lscala/util/parsing/combinator/lexical/StdLexical;)V
   32:	invokevirtual	#82; //Method scala/util/parsing/combinator/Parsers$Parser.$up$up:(Lscala/Function1;)Lscala/util/parsing/combinator/Parsers$Parser;
   35:	new	#254; //class scala/util/parsing/combinator/lexical/StdLexical$$anonfun$comment$3
   38:	dup
   39:	aload_0
   40:	invokespecial	#255; //Method scala/util/parsing/combinator/lexical/StdLexical$$anonfun$comment$3."<init>":(Lscala/util/parsing/combinator/lexical/StdLexical;)V
   43:	invokevirtual	#258; //Method scala/util/parsing/combinator/Parsers$Parser.$bar:(Lscala/Function0;)Lscala/util/parsing/combinator/Parsers$Parser;
   46:	areturn
  LineNumberTable: 
   line 62: 0
   line 63: 35

  Signature: length = 0x2
   01 03 

public scala.util.parsing.combinator.Parsers$Parser whitespace();
  Code:
   Stack=4, Locals=1, Args_size=1
   0:	aload_0
   1:	new	#262; //class scala/util/parsing/combinator/lexical/StdLexical$$anonfun$whitespace$1
   4:	dup
   5:	aload_0
   6:	invokespecial	#263; //Method scala/util/parsing/combinator/lexical/StdLexical$$anonfun$whitespace$1."<init>":(Lscala/util/parsing/combinator/lexical/StdLexical;)V
   9:	invokeinterface	#266,  2; //InterfaceMethod scala/util/parsing/combinator/Parsers.rep:(Lscala/Function0;)Lscala/util/parsing/combinator/Parsers$Parser;
   14:	areturn
  LineNumberTable: 
   line 54: 0
   line 58: 1
   line 54: 9

  Signature: length = 0x2
   01 03 

public scala.util.parsing.combinator.Parsers$Parser identChar();
  Code:
   Stack=4, Locals=1, Args_size=1
   0:	aload_0
   1:	invokevirtual	#270; //Method letter:()Lscala/util/parsing/combinator/Parsers$Parser;
   4:	new	#272; //class scala/util/parsing/combinator/lexical/StdLexical$$anonfun$identChar$1
   7:	dup
   8:	aload_0
   9:	invokespecial	#273; //Method scala/util/parsing/combinator/lexical/StdLexical$$anonfun$identChar$1."<init>":(Lscala/util/parsing/combinator/lexical/StdLexical;)V
   12:	invokevirtual	#258; //Method scala/util/parsing/combinator/Parsers$Parser.$bar:(Lscala/Function0;)Lscala/util/parsing/combinator/Parsers$Parser;
   15:	areturn
  LineNumberTable: 
   line 51: 0

  Signature: length = 0x2
   01 12 

public scala.util.parsing.combinator.Parsers$Parser token();
  Code:
   Stack=4, Locals=1, Args_size=1
   0:	aload_0
   1:	invokevirtual	#277; //Method identChar:()Lscala/util/parsing/combinator/Parsers$Parser;
   4:	new	#279; //class scala/util/parsing/combinator/lexical/StdLexical$$anonfun$token$1
   7:	dup
   8:	aload_0
   9:	invokespecial	#280; //Method scala/util/parsing/combinator/lexical/StdLexical$$anonfun$token$1."<init>":(Lscala/util/parsing/combinator/lexical/StdLexical;)V
   12:	invokevirtual	#249; //Method scala/util/parsing/combinator/Parsers$Parser.$tilde:(Lscala/Function0;)Lscala/util/parsing/combinator/Parsers$Parser;
   15:	new	#282; //class scala/util/parsing/combinator/lexical/StdLexical$$anonfun$token$2
   18:	dup
   19:	aload_0
   20:	invokespecial	#283; //Method scala/util/parsing/combinator/lexical/StdLexical$$anonfun$token$2."<init>":(Lscala/util/parsing/combinator/lexical/StdLexical;)V
   23:	invokevirtual	#82; //Method scala/util/parsing/combinator/Parsers$Parser.$up$up:(Lscala/Function1;)Lscala/util/parsing/combinator/Parsers$Parser;
   26:	new	#285; //class scala/util/parsing/combinator/lexical/StdLexical$$anonfun$token$3
   29:	dup
   30:	aload_0
   31:	invokespecial	#286; //Method scala/util/parsing/combinator/lexical/StdLexical$$anonfun$token$3."<init>":(Lscala/util/parsing/combinator/lexical/StdLexical;)V
   34:	invokevirtual	#258; //Method scala/util/parsing/combinator/Parsers$Parser.$bar:(Lscala/Function0;)Lscala/util/parsing/combinator/Parsers$Parser;
   37:	new	#288; //class scala/util/parsing/combinator/lexical/StdLexical$$anonfun$token$4
   40:	dup
   41:	aload_0
   42:	invokespecial	#289; //Method scala/util/parsing/combinator/lexical/StdLexical$$anonfun$token$4."<init>":(Lscala/util/parsing/combinator/lexical/StdLexical;)V
   45:	invokevirtual	#258; //Method scala/util/parsing/combinator/Parsers$Parser.$bar:(Lscala/Function0;)Lscala/util/parsing/combinator/Parsers$Parser;
   48:	new	#291; //class scala/util/parsing/combinator/lexical/StdLexical$$anonfun$token$5
   51:	dup
   52:	aload_0
   53:	invokespecial	#292; //Method scala/util/parsing/combinator/lexical/StdLexical$$anonfun$token$5."<init>":(Lscala/util/parsing/combinator/lexical/StdLexical;)V
   56:	invokevirtual	#258; //Method scala/util/parsing/combinator/Parsers$Parser.$bar:(Lscala/Function0;)Lscala/util/parsing/combinator/Parsers$Parser;
   59:	new	#294; //class scala/util/parsing/combinator/lexical/StdLexical$$anonfun$token$6
   62:	dup
   63:	aload_0
   64:	invokespecial	#295; //Method scala/util/parsing/combinator/lexical/StdLexical$$anonfun$token$6."<init>":(Lscala/util/parsing/combinator/lexical/StdLexical;)V
   67:	invokevirtual	#258; //Method scala/util/parsing/combinator/Parsers$Parser.$bar:(Lscala/Function0;)Lscala/util/parsing/combinator/Parsers$Parser;
   70:	new	#297; //class scala/util/parsing/combinator/lexical/StdLexical$$anonfun$token$7
   73:	dup
   74:	aload_0
   75:	invokespecial	#298; //Method scala/util/parsing/combinator/lexical/StdLexical$$anonfun$token$7."<init>":(Lscala/util/parsing/combinator/lexical/StdLexical;)V
   78:	invokevirtual	#258; //Method scala/util/parsing/combinator/Parsers$Parser.$bar:(Lscala/Function0;)Lscala/util/parsing/combinator/Parsers$Parser;
   81:	new	#300; //class scala/util/parsing/combinator/lexical/StdLexical$$anonfun$token$8
   84:	dup
   85:	aload_0
   86:	invokespecial	#301; //Method scala/util/parsing/combinator/lexical/StdLexical$$anonfun$token$8."<init>":(Lscala/util/parsing/combinator/lexical/StdLexical;)V
   89:	invokevirtual	#258; //Method scala/util/parsing/combinator/Parsers$Parser.$bar:(Lscala/Function0;)Lscala/util/parsing/combinator/Parsers$Parser;
   92:	new	#303; //class scala/util/parsing/combinator/lexical/StdLexical$$anonfun$token$9
   95:	dup
   96:	aload_0
   97:	invokespecial	#304; //Method scala/util/parsing/combinator/lexical/StdLexical$$anonfun$token$9."<init>":(Lscala/util/parsing/combinator/lexical/StdLexical;)V
   100:	invokevirtual	#258; //Method scala/util/parsing/combinator/Parsers$Parser.$bar:(Lscala/Function0;)Lscala/util/parsing/combinator/Parsers$Parser;
   103:	new	#306; //class scala/util/parsing/combinator/lexical/StdLexical$$anonfun$token$10
   106:	dup
   107:	aload_0
   108:	invokespecial	#307; //Method scala/util/parsing/combinator/lexical/StdLexical$$anonfun$token$10."<init>":(Lscala/util/parsing/combinator/lexical/StdLexical;)V
   111:	invokevirtual	#258; //Method scala/util/parsing/combinator/Parsers$Parser.$bar:(Lscala/Function0;)Lscala/util/parsing/combinator/Parsers$Parser;
   114:	areturn
  LineNumberTable: 
   line 39: 0
   line 40: 26
   line 41: 37
   line 42: 48
   line 43: 59
   line 44: 70
   line 45: 81
   line 46: 92
   line 47: 103

  Signature: length = 0x2
   00 FFFFFF8F 

public final scala.util.parsing.syntax.StdTokens$Identifier$ Identifier();
  Code:
   Stack=4, Locals=1, Args_size=1
   0:	aload_0
   1:	getfield	#311; //Field Identifier$module:Lscala/util/parsing/syntax/StdTokens$Identifier$;
   4:	ifnonnull	19
   7:	aload_0
   8:	new	#313; //class scala/util/parsing/syntax/StdTokens$Identifier$
   11:	dup
   12:	aload_0
   13:	invokespecial	#315; //Method scala/util/parsing/syntax/StdTokens$Identifier$."<init>":(Lscala/util/parsing/syntax/StdTokens;)V
   16:	putfield	#311; //Field Identifier$module:Lscala/util/parsing/syntax/StdTokens$Identifier$;
   19:	aload_0
   20:	getfield	#311; //Field Identifier$module:Lscala/util/parsing/syntax/StdTokens$Identifier$;
   23:	areturn
  LineNumberTable: 
   line 36: 0


public final scala.util.parsing.syntax.StdTokens$StringLit$ StringLit();
  Code:
   Stack=4, Locals=1, Args_size=1
   0:	aload_0
   1:	getfield	#319; //Field StringLit$module:Lscala/util/parsing/syntax/StdTokens$StringLit$;
   4:	ifnonnull	19
   7:	aload_0
   8:	new	#321; //class scala/util/parsing/syntax/StdTokens$StringLit$
   11:	dup
   12:	aload_0
   13:	invokespecial	#322; //Method scala/util/parsing/syntax/StdTokens$StringLit$."<init>":(Lscala/util/parsing/syntax/StdTokens;)V
   16:	putfield	#319; //Field StringLit$module:Lscala/util/parsing/syntax/StdTokens$StringLit$;
   19:	aload_0
   20:	getfield	#319; //Field StringLit$module:Lscala/util/parsing/syntax/StdTokens$StringLit$;
   23:	areturn
  LineNumberTable: 
   line 36: 0


public final scala.util.parsing.syntax.StdTokens$NumericLit$ NumericLit();
  Code:
   Stack=4, Locals=1, Args_size=1
   0:	aload_0
   1:	getfield	#326; //Field NumericLit$module:Lscala/util/parsing/syntax/StdTokens$NumericLit$;
   4:	ifnonnull	19
   7:	aload_0
   8:	new	#328; //class scala/util/parsing/syntax/StdTokens$NumericLit$
   11:	dup
   12:	aload_0
   13:	invokespecial	#329; //Method scala/util/parsing/syntax/StdTokens$NumericLit$."<init>":(Lscala/util/parsing/syntax/StdTokens;)V
   16:	putfield	#326; //Field NumericLit$module:Lscala/util/parsing/syntax/StdTokens$NumericLit$;
   19:	aload_0
   20:	getfield	#326; //Field NumericLit$module:Lscala/util/parsing/syntax/StdTokens$NumericLit$;
   23:	areturn
  LineNumberTable: 
   line 36: 0


public final scala.util.parsing.syntax.StdTokens$Keyword$ Keyword();
  Code:
   Stack=4, Locals=1, Args_size=1
   0:	aload_0
   1:	getfield	#333; //Field Keyword$module:Lscala/util/parsing/syntax/StdTokens$Keyword$;
   4:	ifnonnull	19
   7:	aload_0
   8:	new	#335; //class scala/util/parsing/syntax/StdTokens$Keyword$
   11:	dup
   12:	aload_0
   13:	invokespecial	#336; //Method scala/util/parsing/syntax/StdTokens$Keyword$."<init>":(Lscala/util/parsing/syntax/StdTokens;)V
   16:	putfield	#333; //Field Keyword$module:Lscala/util/parsing/syntax/StdTokens$Keyword$;
   19:	aload_0
   20:	getfield	#333; //Field Keyword$module:Lscala/util/parsing/syntax/StdTokens$Keyword$;
   23:	areturn
  LineNumberTable: 
   line 36: 0


}

