Compiled from "StdLexical.scala"
public final class scala.util.parsing.combinator.lexical.StdLexical$$anonfun$parseDelim$1$1 extends java.lang.Object implements scala.Function1,scala.ScalaObject,java.io.Serializable
  SourceFile: "StdLexical.scala"
  Scala: length = 0x
   
  InnerClass: 
   public final #64= #28 of #63; //$anonfun$parseDelim$1$1=class scala/util/parsing/combinator/lexical/StdLexical$$anonfun$parseDelim$1$1 of class scala/util/parsing/combinator/lexical/StdLexical
  minor version: 0
  major version: 49
  Constant pool:
const #1 = Asciz	SourceFile;
const #2 = Asciz	StdLexical.scala;
const #3 = Asciz	<init>;
const #4 = Asciz	(Lscala/util/parsing/combinator/lexical/StdLexical;)V;
const #5 = Asciz	Code;
const #6 = Asciz	LineNumberTable;
const #7 = Asciz	java/lang/Object;
const #8 = class	#7;	//  java/lang/Object
const #9 = Asciz	()V;
const #10 = NameAndType	#3:#9;//  "<init>":()V
const #11 = Method	#8.#10;	//  java/lang/Object."<init>":()V
const #12 = Asciz	scala/Function1$class;
const #13 = class	#12;	//  scala/Function1$class
const #14 = Asciz	$init$;
const #15 = Asciz	(Lscala/Function1;)V;
const #16 = NameAndType	#14:#15;//  $init$:(Lscala/Function1;)V
const #17 = Method	#13.#16;	//  scala/Function1$class.$init$:(Lscala/Function1;)V
const #18 = Asciz	this;
const #19 = Asciz	Lscala/util/parsing/combinator/lexical/StdLexical$$anonfun$parseDelim$1$1;;
const #20 = Asciz	$outer;
const #21 = Asciz	Lscala/util/parsing/combinator/lexical/StdLexical;;
const #22 = Asciz	LocalVariableTable;
const #23 = Asciz	apply;
const #24 = Asciz	(Ljava/lang/Object;)Ljava/lang/Object;;
const #25 = Asciz	scala/collection/immutable/List;
const #26 = class	#25;	//  scala/collection/immutable/List
const #27 = Asciz	scala/util/parsing/combinator/lexical/StdLexical$$anonfun$parseDelim$1$1;
const #28 = class	#27;	//  scala/util/parsing/combinator/lexical/StdLexical$$anonfun$parseDelim$1$1
const #29 = Asciz	(Lscala/collection/immutable/List;)Lscala/collection/immutable/List;;
const #30 = NameAndType	#23:#29;//  apply:(Lscala/collection/immutable/List;)Lscala/collection/immutable/List;
const #31 = Method	#28.#30;	//  scala/util/parsing/combinator/lexical/StdLexical$$anonfun$parseDelim$1$1.apply:(Lscala/collection/immutable/List;)Lscala/collection/immutable/List;
const #32 = Asciz	v1;
const #33 = Asciz	Ljava/lang/Object;;
const #34 = Asciz	scala/Predef$;
const #35 = class	#34;	//  scala/Predef$
const #36 = Asciz	MODULE$;
const #37 = Asciz	Lscala/Predef$;;
const #38 = NameAndType	#36:#37;//  MODULE$:Lscala/Predef$;
const #39 = Field	#35.#38;	//  scala/Predef$.MODULE$:Lscala/Predef$;
const #40 = Asciz	identity;
const #41 = NameAndType	#40:#24;//  identity:(Ljava/lang/Object;)Ljava/lang/Object;
const #42 = Method	#35.#41;	//  scala/Predef$.identity:(Ljava/lang/Object;)Ljava/lang/Object;
const #43 = Asciz	(Lscala/collection/immutable/List<Ljava/lang/Character;>;)Lscala/collection/immutable/List<Ljava/lang/Character;>;;
const #44 = Asciz	Signature;
const #45 = Asciz	andThen;
const #46 = Asciz	(Lscala/Function1;)Lscala/Function1;;
const #47 = Asciz	(Lscala/Function1;Lscala/Function1;)Lscala/Function1;;
const #48 = NameAndType	#45:#47;//  andThen:(Lscala/Function1;Lscala/Function1;)Lscala/Function1;
const #49 = Method	#13.#48;	//  scala/Function1$class.andThen:(Lscala/Function1;Lscala/Function1;)Lscala/Function1;
const #50 = Asciz	g;
const #51 = Asciz	Lscala/Function1;;
const #52 = Asciz	compose;
const #53 = NameAndType	#52:#47;//  compose:(Lscala/Function1;Lscala/Function1;)Lscala/Function1;
const #54 = Method	#13.#53;	//  scala/Function1$class.compose:(Lscala/Function1;Lscala/Function1;)Lscala/Function1;
const #55 = Asciz	toString;
const #56 = Asciz	()Ljava/lang/String;;
const #57 = Asciz	(Lscala/Function1;)Ljava/lang/String;;
const #58 = NameAndType	#55:#57;//  toString:(Lscala/Function1;)Ljava/lang/String;
const #59 = Method	#13.#58;	//  scala/Function1$class.toString:(Lscala/Function1;)Ljava/lang/String;
const #60 = Asciz	Scala;
const #61 = Asciz	InnerClasses;
const #62 = Asciz	scala/util/parsing/combinator/lexical/StdLexical;
const #63 = class	#62;	//  scala/util/parsing/combinator/lexical/StdLexical
const #64 = Asciz	$anonfun$parseDelim$1$1;
const #65 = Asciz	scala/Function1;
const #66 = class	#65;	//  scala/Function1
const #67 = Asciz	scala/ScalaObject;
const #68 = class	#67;	//  scala/ScalaObject
const #69 = Asciz	java/io/Serializable;
const #70 = class	#69;	//  java/io/Serializable

{
public scala.util.parsing.combinator.lexical.StdLexical$$anonfun$parseDelim$1$1(scala.util.parsing.combinator.lexical.StdLexical);
  Code:
   Stack=1, Locals=2, Args_size=2
   0:	aload_0
   1:	invokespecial	#11; //Method java/lang/Object."<init>":()V
   4:	aload_0
   5:	invokestatic	#17; //Method scala/Function1$class.$init$:(Lscala/Function1;)V
   8:	return
  LineNumberTable: 
   line 79: 0

  LocalVariableTable: 
   Start  Length  Slot  Name   Signature
   0      9      0    this       Lscala/util/parsing/combinator/lexical/StdLexical$$anonfun$parseDelim$1$1;
   0      9      1    $outer       Lscala/util/parsing/combinator/lexical/StdLexical;


public final java.lang.Object apply(java.lang.Object);
  Code:
   Stack=2, Locals=2, Args_size=2
   0:	aload_0
   1:	aload_1
   2:	checkcast	#26; //class scala/collection/immutable/List
   5:	invokevirtual	#31; //Method apply:(Lscala/collection/immutable/List;)Lscala/collection/immutable/List;
   8:	areturn
  LineNumberTable: 
   line 79: 0

  LocalVariableTable: 
   Start  Length  Slot  Name   Signature
   0      9      0    this       Lscala/util/parsing/combinator/lexical/StdLexical$$anonfun$parseDelim$1$1;
   0      9      1    v1       Ljava/lang/Object;


public final scala.collection.immutable.List apply(scala.collection.immutable.List);
  Code:
   Stack=2, Locals=2, Args_size=2
   0:	getstatic	#39; //Field scala/Predef$.MODULE$:Lscala/Predef$;
   3:	aload_1
   4:	invokevirtual	#42; //Method scala/Predef$.identity:(Ljava/lang/Object;)Ljava/lang/Object;
   7:	checkcast	#26; //class scala/collection/immutable/List
   10:	areturn
  LineNumberTable: 
   line 79: 0

  Signature: length = 0x2
   00 2B 

public scala.Function1 andThen(scala.Function1);
  Code:
   Stack=2, Locals=2, Args_size=2
   0:	aload_0
   1:	aload_1
   2:	invokestatic	#49; //Method scala/Function1$class.andThen:(Lscala/Function1;Lscala/Function1;)Lscala/Function1;
   5:	areturn
  LineNumberTable: 
   line 79: 0

  LocalVariableTable: 
   Start  Length  Slot  Name   Signature
   0      6      0    this       Lscala/util/parsing/combinator/lexical/StdLexical$$anonfun$parseDelim$1$1;
   0      6      1    g       Lscala/Function1;


public scala.Function1 compose(scala.Function1);
  Code:
   Stack=2, Locals=2, Args_size=2
   0:	aload_0
   1:	aload_1
   2:	invokestatic	#54; //Method scala/Function1$class.compose:(Lscala/Function1;Lscala/Function1;)Lscala/Function1;
   5:	areturn
  LineNumberTable: 
   line 79: 0

  LocalVariableTable: 
   Start  Length  Slot  Name   Signature
   0      6      0    this       Lscala/util/parsing/combinator/lexical/StdLexical$$anonfun$parseDelim$1$1;
   0      6      1    g       Lscala/Function1;


public java.lang.String toString();
  Code:
   Stack=1, Locals=1, Args_size=1
   0:	aload_0
   1:	invokestatic	#59; //Method scala/Function1$class.toString:(Lscala/Function1;)Ljava/lang/String;
   4:	areturn
  LineNumberTable: 
   line 79: 0


}

