Compiled from "StdLexical.scala"
public final class scala.util.parsing.combinator.lexical.StdLexical$$anonfun$comment$3 extends scala.runtime.AbstractFunction0 implements java.io.Serializable
  SourceFile: "StdLexical.scala"
  Scala: length = 0x
   
  InnerClass: 
   public abstract Parser=class scala/util/parsing/combinator/Parsers$Parser of class scala/util/parsing/combinator/Parsers
   public final $anonfun$comment$3=class scala/util/parsing/combinator/lexical/StdLexical$$anonfun$comment$3 of class scala/util/parsing/combinator/lexical/StdLexical
   public final $anonfun$apply$26=class scala/util/parsing/combinator/lexical/StdLexical$$anonfun$comment$3$$anonfun$apply$26 of class scala/util/parsing/combinator/lexical/StdLexical$$anonfun$comment$3
  minor version: 0
  major version: 49
  Constant pool:
Asciz	SourceFile;
Asciz	StdLexical.scala;
Asciz	<clinit>;
Asciz	()V;
Asciz	Code;
Asciz	serialVersionUID;
Asciz	J;
Asciz	scala/util/parsing/combinator/lexical/StdLexical$$anonfun$comment$3;
class	scala/util/parsing/combinator/lexical/StdLexical$$anonfun$comment$3
NameAndType	serialVersionUID:J
Field	scala/util/parsing/combinator/lexical/StdLexical$$anonfun$comment$3.serialVersionUID:J
Asciz	$outer;
Asciz	Lscala/util/parsing/combinator/lexical/StdLexical;;
Asciz	<init>;
Asciz	(Lscala/util/parsing/combinator/lexical/StdLexical;)V;
Asciz	LineNumberTable;
Asciz	java/lang/NullPointerException;
class	java/lang/NullPointerException
NameAndType	"<init>":()V
Method	java/lang/NullPointerException."<init>":()V
NameAndType	$outer:Lscala/util/parsing/combinator/lexical/StdLexical;
Field	scala/util/parsing/combinator/lexical/StdLexical$$anonfun$comment$3.$outer:Lscala/util/parsing/combinator/lexical/StdLexical;
Asciz	scala/runtime/AbstractFunction0;
class	scala/runtime/AbstractFunction0
Method	scala/runtime/AbstractFunction0."<init>":()V
Asciz	this;
Asciz	Lscala/util/parsing/combinator/lexical/StdLexical$$anonfun$comment$3;;
Asciz	LocalVariableTable;
Asciz	apply;
Asciz	()Ljava/lang/Object;;
Asciz	()Lscala/util/parsing/combinator/Parsers$Parser;;
NameAndType	apply:()Lscala/util/parsing/combinator/Parsers$Parser;
Method	scala/util/parsing/combinator/lexical/StdLexical$$anonfun$comment$3.apply:()Lscala/util/parsing/combinator/Parsers$Parser;
Asciz	scala$util$parsing$combinator$lexical$StdLexical$$anonfun$$$outer;
Asciz	()Lscala/util/parsing/combinator/lexical/StdLexical;;
Asciz	scala/Predef$;
class	scala/Predef$
Asciz	MODULE$;
Asciz	Lscala/Predef$;;
NameAndType	MODULE$:Lscala/Predef$;
Field	scala/Predef$.MODULE$:Lscala/Predef$;
int	26;
Asciz	wrapCharArray;
Asciz	([C)Lscala/collection/mutable/WrappedArray;;
NameAndType	wrapCharArray:([C)Lscala/collection/mutable/WrappedArray;
Method	scala/Predef$.wrapCharArray:([C)Lscala/collection/mutable/WrappedArray;
Asciz	scala/util/parsing/combinator/lexical/StdLexical;
class	scala/util/parsing/combinator/lexical/StdLexical
Asciz	chrExcept;
Asciz	(Lscala/collection/Seq;)Lscala/util/parsing/combinator/Parsers$Parser;;
NameAndType	chrExcept:(Lscala/collection/Seq;)Lscala/util/parsing/combinator/Parsers$Parser;
Method	scala/util/parsing/combinator/lexical/StdLexical.chrExcept:(Lscala/collection/Seq;)Lscala/util/parsing/combinator/Parsers$Parser;
Asciz	scala/util/parsing/combinator/lexical/StdLexical$$anonfun$comment$3$$anonfun$apply$26;
class	scala/util/parsing/combinator/lexical/StdLexical$$anonfun$comment$3$$anonfun$apply$26
Asciz	(Lscala/util/parsing/combinator/lexical/StdLexical$$anonfun$comment$3;)V;
NameAndType	"<init>":(Lscala/util/parsing/combinator/lexical/StdLexical$$anonfun$comment$3;)V
Method	scala/util/parsing/combinator/lexical/StdLexical$$anonfun$comment$3$$anonfun$apply$26."<init>":(Lscala/util/parsing/combinator/lexical/StdLexical$$anonfun$comment$3;)V
Asciz	scala/util/parsing/combinator/Parsers$Parser;
class	scala/util/parsing/combinator/Parsers$Parser
Asciz	$tilde;
Asciz	(Lscala/Function0;)Lscala/util/parsing/combinator/Parsers$Parser;;
NameAndType	$tilde:(Lscala/Function0;)Lscala/util/parsing/combinator/Parsers$Parser;
Method	scala/util/parsing/combinator/Parsers$Parser.$tilde:(Lscala/Function0;)Lscala/util/parsing/combinator/Parsers$Parser;
Asciz	()Lscala/util/parsing/combinator/Parsers$Parser<Lscala/util/parsing/combinator/Parsers$$tilde<Ljava/lang/Character;Ljava/lang/Object;>;>;;
Asciz	Signature;
Asciz	Scala;
Asciz	InnerClasses;
Asciz	scala/util/parsing/combinator/Parsers;
class	scala/util/parsing/combinator/Parsers
Asciz	Parser;
Asciz	$anonfun$comment$3;
Asciz	$anonfun$apply$26;
Asciz	java/io/Serializable;
class	java/io/Serializable

{
public static final long serialVersionUID;
  Signature: J

private final scala.util.parsing.combinator.lexical.StdLexical $outer;
  Signature: Lscala/util/parsing/combinator/lexical/StdLexical;

public static {};
  Signature: ()V
  Code:
   Stack=2, Locals=0, Args_size=0
	lconst_0
	putstatic	Field serialVersionUID:J
	return
  Labels:

public scala.util.parsing.combinator.lexical.StdLexical$$anonfun$comment$3(scala.util.parsing.combinator.lexical.StdLexical);
  Signature: (Lscala/util/parsing/combinator/lexical/StdLexical;)V
  Code:
   Stack=2, Locals=2, Args_size=2
	aload_1
	ifnonnull	l1 // aload_0
	new	class java/lang/NullPointerException
	dup
	invokespecial	Method java/lang/NullPointerException."<init>":()V
	athrow
l1	aload_0
	aload_1
	putfield	Field $outer:Lscala/util/parsing/combinator/lexical/StdLexical;
	aload_0
	invokespecial	Method scala/runtime/AbstractFunction0."<init>":()V
	return
  Labels:
   	l1 = 12 // aload_0
  LocalVariableTable: 
   Start  Length  Slot  Name   Signature
   0      22      0    this       Lscala/util/parsing/combinator/lexical/StdLexical$$anonfun$comment$3;
   0      22      1    $outer       Lscala/util/parsing/combinator/lexical/StdLexical;


public final java.lang.Object apply();
  Signature: ()Ljava/lang/Object;
  Code:
   Stack=1, Locals=1, Args_size=1
	aload_0
	invokevirtual	Method apply:()Lscala/util/parsing/combinator/Parsers$Parser;
	areturn
  Labels:

public scala.util.parsing.combinator.lexical.StdLexical scala$util$parsing$combinator$lexical$StdLexical$$anonfun$$$outer();
  Signature: ()Lscala/util/parsing/combinator/lexical/StdLexical;
  Code:
   Stack=1, Locals=1, Args_size=1
	aload_0
	getfield	Field $outer:Lscala/util/parsing/combinator/lexical/StdLexical;
	areturn
  Labels:

public final scala.util.parsing.combinator.Parsers$Parser apply();
  Signature: ()Lscala/util/parsing/combinator/Parsers$Parser;
  Code:
   Stack=6, Locals=1, Args_size=1
	aload_0
	getfield	Field $outer:Lscala/util/parsing/combinator/lexical/StdLexical;
	getstatic	Field scala/Predef$.MODULE$:Lscala/Predef$;
	iconst_1
	newarray char
	dup
	iconst_0
	ldc	int 26
	castore
	invokevirtual	Method scala/Predef$.wrapCharArray:([C)Lscala/collection/mutable/WrappedArray;
	invokevirtual	Method scala/util/parsing/combinator/lexical/StdLexical.chrExcept:(Lscala/collection/Seq;)Lscala/util/parsing/combinator/Parsers$Parser;
	new	class scala/util/parsing/combinator/lexical/StdLexical$$anonfun$comment$3$$anonfun$apply$26
	dup
	aload_0
	invokespecial	Method scala/util/parsing/combinator/lexical/StdLexical$$anonfun$comment$3$$anonfun$apply$26."<init>":(Lscala/util/parsing/combinator/lexical/StdLexical$$anonfun$comment$3;)V
	invokevirtual	Method scala/util/parsing/combinator/Parsers$Parser.$tilde:(Lscala/Function0;)Lscala/util/parsing/combinator/Parsers$Parser;
	areturn
  Labels:
  Signature: length = 0x2
   00 40 

}

