Compiled from "StdLexical.scala"
public final class scala.util.parsing.combinator.lexical.StdLexical$$anonfun$token$4$$anonfun$apply$9 extends scala.runtime.AbstractFunction1 implements java.io.Serializable
  SourceFile: "StdLexical.scala"
  Scala: length = 0x
   
  InnerClass: 
   public #91= #32 of #90; //$tilde=class scala/util/parsing/combinator/Parsers$$tilde of class scala/util/parsing/combinator/Parsers
   public #94= #55 of #93; //StringLit=class scala/util/parsing/syntax/StdTokens$StringLit of class scala/util/parsing/syntax/StdTokens
   public final #97= #57 of #96; //$anonfun$token$4=class scala/util/parsing/combinator/lexical/StdLexical$$anonfun$token$4 of class scala/util/parsing/combinator/lexical/StdLexical
   public final #98= #9 of #57; //$anonfun$apply$9=class scala/util/parsing/combinator/lexical/StdLexical$$anonfun$token$4$$anonfun$apply$9 of class scala/util/parsing/combinator/lexical/StdLexical$$anonfun$token$4
  minor version: 0
  major version: 49
  Constant pool:
const #1 = Asciz	SourceFile;
const #2 = Asciz	StdLexical.scala;
const #3 = Asciz	<clinit>;
const #4 = Asciz	()V;
const #5 = Asciz	Code;
const #6 = Asciz	serialVersionUID;
const #7 = Asciz	J;
const #8 = Asciz	scala/util/parsing/combinator/lexical/StdLexical$$anonfun$token$4$$anonfun$apply$9;
const #9 = class	#8;	//  scala/util/parsing/combinator/lexical/StdLexical$$anonfun$token$4$$anonfun$apply$9
const #10 = NameAndType	#6:#7;//  serialVersionUID:J
const #11 = Field	#9.#10;	//  scala/util/parsing/combinator/lexical/StdLexical$$anonfun$token$4$$anonfun$apply$9.serialVersionUID:J
const #12 = Asciz	$outer;
const #13 = Asciz	Lscala/util/parsing/combinator/lexical/StdLexical$$anonfun$token$4;;
const #14 = Asciz	<init>;
const #15 = Asciz	(Lscala/util/parsing/combinator/lexical/StdLexical$$anonfun$token$4;)V;
const #16 = Asciz	LineNumberTable;
const #17 = Asciz	java/lang/NullPointerException;
const #18 = class	#17;	//  java/lang/NullPointerException
const #19 = NameAndType	#14:#4;//  "<init>":()V
const #20 = Method	#18.#19;	//  java/lang/NullPointerException."<init>":()V
const #21 = NameAndType	#12:#13;//  $outer:Lscala/util/parsing/combinator/lexical/StdLexical$$anonfun$token$4;
const #22 = Field	#9.#21;	//  scala/util/parsing/combinator/lexical/StdLexical$$anonfun$token$4$$anonfun$apply$9.$outer:Lscala/util/parsing/combinator/lexical/StdLexical$$anonfun$token$4;
const #23 = Asciz	scala/runtime/AbstractFunction1;
const #24 = class	#23;	//  scala/runtime/AbstractFunction1
const #25 = Method	#24.#19;	//  scala/runtime/AbstractFunction1."<init>":()V
const #26 = Asciz	this;
const #27 = Asciz	Lscala/util/parsing/combinator/lexical/StdLexical$$anonfun$token$4$$anonfun$apply$9;;
const #28 = Asciz	LocalVariableTable;
const #29 = Asciz	apply;
const #30 = Asciz	(Ljava/lang/Object;)Ljava/lang/Object;;
const #31 = Asciz	scala/util/parsing/combinator/Parsers$$tilde;
const #32 = class	#31;	//  scala/util/parsing/combinator/Parsers$$tilde
const #33 = Asciz	(Lscala/util/parsing/combinator/Parsers$$tilde;)Lscala/util/parsing/syntax/StdTokens$StringLit;;
const #34 = NameAndType	#29:#33;//  apply:(Lscala/util/parsing/combinator/Parsers$$tilde;)Lscala/util/parsing/syntax/StdTokens$StringLit;
const #35 = Method	#9.#34;	//  scala/util/parsing/combinator/lexical/StdLexical$$anonfun$token$4$$anonfun$apply$9.apply:(Lscala/util/parsing/combinator/Parsers$$tilde;)Lscala/util/parsing/syntax/StdTokens$StringLit;
const #36 = Asciz	v1;
const #37 = Asciz	Ljava/lang/Object;;
const #38 = Asciz	_1;
const #39 = Asciz	()Ljava/lang/Object;;
const #40 = NameAndType	#38:#39;//  _1:()Ljava/lang/Object;
const #41 = Method	#32.#40;	//  scala/util/parsing/combinator/Parsers$$tilde._1:()Ljava/lang/Object;
const #42 = Asciz	_2;
const #43 = NameAndType	#42:#39;//  _2:()Ljava/lang/Object;
const #44 = Method	#32.#43;	//  scala/util/parsing/combinator/Parsers$$tilde._2:()Ljava/lang/Object;
const #45 = Asciz	scala/collection/immutable/List;
const #46 = class	#45;	//  scala/collection/immutable/List
const #47 = Asciz	scala/runtime/BoxesRunTime;
const #48 = class	#47;	//  scala/runtime/BoxesRunTime
const #49 = Asciz	unboxToChar;
const #50 = Asciz	(Ljava/lang/Object;)C;
const #51 = NameAndType	#49:#50;//  unboxToChar:(Ljava/lang/Object;)C
const #52 = Method	#48.#51;	//  scala/runtime/BoxesRunTime.unboxToChar:(Ljava/lang/Object;)C
const #53 = int	39;
const #54 = Asciz	scala/util/parsing/syntax/StdTokens$StringLit;
const #55 = class	#54;	//  scala/util/parsing/syntax/StdTokens$StringLit
const #56 = Asciz	scala/util/parsing/combinator/lexical/StdLexical$$anonfun$token$4;
const #57 = class	#56;	//  scala/util/parsing/combinator/lexical/StdLexical$$anonfun$token$4
const #58 = Asciz	Lscala/util/parsing/combinator/lexical/StdLexical;;
const #59 = NameAndType	#12:#58;//  $outer:Lscala/util/parsing/combinator/lexical/StdLexical;
const #60 = Field	#57.#59;	//  scala/util/parsing/combinator/lexical/StdLexical$$anonfun$token$4.$outer:Lscala/util/parsing/combinator/lexical/StdLexical;
const #61 = Asciz	;
const #62 = String	#61;	//  
const #63 = Asciz	scala/collection/TraversableLike;
const #64 = class	#63;	//  scala/collection/TraversableLike
const #65 = Asciz	mkString;
const #66 = Asciz	(Ljava/lang/String;)Ljava/lang/String;;
const #67 = NameAndType	#65:#66;//  mkString:(Ljava/lang/String;)Ljava/lang/String;
const #68 = InterfaceMethod	#64.#67;	//  scala/collection/TraversableLike.mkString:(Ljava/lang/String;)Ljava/lang/String;
const #69 = Asciz	(Lscala/util/parsing/syntax/StdTokens;Ljava/lang/String;)V;
const #70 = NameAndType	#14:#69;//  "<init>":(Lscala/util/parsing/syntax/StdTokens;Ljava/lang/String;)V
const #71 = Method	#55.#70;	//  scala/util/parsing/syntax/StdTokens$StringLit."<init>":(Lscala/util/parsing/syntax/StdTokens;Ljava/lang/String;)V
const #72 = Asciz	scala/MatchError;
const #73 = class	#72;	//  scala/MatchError
const #74 = Asciz	toString;
const #75 = Asciz	()Ljava/lang/String;;
const #76 = NameAndType	#74:#75;//  toString:()Ljava/lang/String;
const #77 = Method	#32.#76;	//  scala/util/parsing/combinator/Parsers$$tilde.toString:()Ljava/lang/String;
const #78 = Asciz	(Ljava/lang/String;)V;
const #79 = NameAndType	#14:#78;//  "<init>":(Ljava/lang/String;)V
const #80 = Method	#73.#79;	//  scala/MatchError."<init>":(Ljava/lang/String;)V
const #81 = Asciz	temp8;
const #82 = Asciz	Lscala/util/parsing/combinator/Parsers$$tilde;;
const #83 = Asciz	temp11;
const #84 = Asciz	Lscala/collection/immutable/List;;
const #85 = Asciz	(Lscala/util/parsing/combinator/Parsers$$tilde<Lscala/util/parsing/combinator/Parsers$$tilde<Ljava/lang/Character;Lscala/collection/immutable/List<Ljava/lang/Character;>;>;Ljava/lang/Character;>;)Lscala/util/parsing/syntax/StdTokens$StringLit;;
const #86 = Asciz	Signature;
const #87 = Asciz	Scala;
const #88 = Asciz	InnerClasses;
const #89 = Asciz	scala/util/parsing/combinator/Parsers;
const #90 = class	#89;	//  scala/util/parsing/combinator/Parsers
const #91 = Asciz	$tilde;
const #92 = Asciz	scala/util/parsing/syntax/StdTokens;
const #93 = class	#92;	//  scala/util/parsing/syntax/StdTokens
const #94 = Asciz	StringLit;
const #95 = Asciz	scala/util/parsing/combinator/lexical/StdLexical;
const #96 = class	#95;	//  scala/util/parsing/combinator/lexical/StdLexical
const #97 = Asciz	$anonfun$token$4;
const #98 = Asciz	$anonfun$apply$9;
const #99 = Asciz	java/io/Serializable;
const #100 = class	#99;	//  java/io/Serializable

{
public static final long serialVersionUID;

public static {};
  Code:
   Stack=2, Locals=0, Args_size=0
   0:	lconst_0
   1:	putstatic	#11; //Field serialVersionUID:J
   4:	return

public scala.util.parsing.combinator.lexical.StdLexical$$anonfun$token$4$$anonfun$apply$9(scala.util.parsing.combinator.lexical.StdLexical$$anonfun$token$4);
  Code:
   Stack=2, Locals=2, Args_size=2
   0:	aload_1
   1:	ifnonnull	12
   4:	new	#18; //class java/lang/NullPointerException
   7:	dup
   8:	invokespecial	#20; //Method java/lang/NullPointerException."<init>":()V
   11:	athrow
   12:	aload_0
   13:	aload_1
   14:	putfield	#22; //Field $outer:Lscala/util/parsing/combinator/lexical/StdLexical$$anonfun$token$4;
   17:	aload_0
   18:	invokespecial	#25; //Method scala/runtime/AbstractFunction1."<init>":()V
   21:	return
  LineNumberTable: 
   line 41: 0

  LocalVariableTable: 
   Start  Length  Slot  Name   Signature
   0      22      0    this       Lscala/util/parsing/combinator/lexical/StdLexical$$anonfun$token$4$$anonfun$apply$9;
   0      22      1    $outer       Lscala/util/parsing/combinator/lexical/StdLexical$$anonfun$token$4;


public final java.lang.Object apply(java.lang.Object);
  Code:
   Stack=2, Locals=2, Args_size=2
   0:	aload_0
   1:	aload_1
   2:	checkcast	#32; //class scala/util/parsing/combinator/Parsers$$tilde
   5:	invokevirtual	#35; //Method apply:(Lscala/util/parsing/combinator/Parsers$$tilde;)Lscala/util/parsing/syntax/StdTokens$StringLit;
   8:	areturn
  LineNumberTable: 
   line 41: 0

  LocalVariableTable: 
   Start  Length  Slot  Name   Signature
   0      9      0    this       Lscala/util/parsing/combinator/lexical/StdLexical$$anonfun$token$4$$anonfun$apply$9;
   0      9      1    v1       Ljava/lang/Object;


public final scala.util.parsing.syntax.StdTokens$StringLit apply(scala.util.parsing.combinator.Parsers$$tilde);
  Code:
   Stack=5, Locals=5, Args_size=2
   0:	aload_1
   1:	ifnull	115
   4:	aload_1
   5:	invokevirtual	#41; //Method scala/util/parsing/combinator/Parsers$$tilde._1:()Ljava/lang/Object;
   8:	checkcast	#32; //class scala/util/parsing/combinator/Parsers$$tilde
   11:	astore_2
   12:	aload_2
   13:	ifnull	103
   16:	aload_2
   17:	invokevirtual	#44; //Method scala/util/parsing/combinator/Parsers$$tilde._2:()Ljava/lang/Object;
   20:	checkcast	#46; //class scala/collection/immutable/List
   23:	astore	4
   25:	aload_2
   26:	invokevirtual	#41; //Method scala/util/parsing/combinator/Parsers$$tilde._1:()Ljava/lang/Object;
   29:	invokestatic	#52; //Method scala/runtime/BoxesRunTime.unboxToChar:(Ljava/lang/Object;)C
   32:	ldc	#53; //int 39
   34:	if_icmpne	91
   37:	aload_1
   38:	invokevirtual	#44; //Method scala/util/parsing/combinator/Parsers$$tilde._2:()Ljava/lang/Object;
   41:	invokestatic	#52; //Method scala/runtime/BoxesRunTime.unboxToChar:(Ljava/lang/Object;)C
   44:	ldc	#53; //int 39
   46:	if_icmpne	91
   49:	iconst_1
   50:	ifeq	79
   53:	new	#55; //class scala/util/parsing/syntax/StdTokens$StringLit
   56:	dup
   57:	aload_0
   58:	getfield	#22; //Field $outer:Lscala/util/parsing/combinator/lexical/StdLexical$$anonfun$token$4;
   61:	astore_3
   62:	aload_3
   63:	getfield	#60; //Field scala/util/parsing/combinator/lexical/StdLexical$$anonfun$token$4.$outer:Lscala/util/parsing/combinator/lexical/StdLexical;
   66:	aload	4
   68:	ldc	#62; //String 
   70:	invokeinterface	#68,  2; //InterfaceMethod scala/collection/TraversableLike.mkString:(Ljava/lang/String;)Ljava/lang/String;
   75:	invokespecial	#71; //Method scala/util/parsing/syntax/StdTokens$StringLit."<init>":(Lscala/util/parsing/syntax/StdTokens;Ljava/lang/String;)V
   78:	areturn
   79:	new	#73; //class scala/MatchError
   82:	dup
   83:	aload_1
   84:	invokevirtual	#77; //Method scala/util/parsing/combinator/Parsers$$tilde.toString:()Ljava/lang/String;
   87:	invokespecial	#80; //Method scala/MatchError."<init>":(Ljava/lang/String;)V
   90:	athrow
   91:	new	#73; //class scala/MatchError
   94:	dup
   95:	aload_1
   96:	invokevirtual	#77; //Method scala/util/parsing/combinator/Parsers$$tilde.toString:()Ljava/lang/String;
   99:	invokespecial	#80; //Method scala/MatchError."<init>":(Ljava/lang/String;)V
   102:	athrow
   103:	new	#73; //class scala/MatchError
   106:	dup
   107:	aload_1
   108:	invokevirtual	#77; //Method scala/util/parsing/combinator/Parsers$$tilde.toString:()Ljava/lang/String;
   111:	invokespecial	#80; //Method scala/MatchError."<init>":(Ljava/lang/String;)V
   114:	athrow
   115:	new	#73; //class scala/MatchError
   118:	dup
   119:	aload_1
   120:	invokevirtual	#77; //Method scala/util/parsing/combinator/Parsers$$tilde.toString:()Ljava/lang/String;
   123:	invokespecial	#80; //Method scala/MatchError."<init>":(Ljava/lang/String;)V
   126:	athrow
  LineNumberTable: 
   line 41: 0
   line 21: 49
   line 41: 53

  LocalVariableTable: 
   Start  Length  Slot  Name   Signature
   0      127      0    this       Lscala/util/parsing/combinator/lexical/StdLexical$$anonfun$token$4$$anonfun$apply$9;
   12      103      2    temp8       Lscala/util/parsing/combinator/Parsers$$tilde;
   25      78      4    temp11       Lscala/collection/immutable/List;

  Signature: length = 0x2
   00 55 

}

