Compiled from "StdLexical.scala"
public final class scala.util.parsing.combinator.lexical.StdLexical$$anonfun$_delim$3 extends java.lang.Object implements scala.Function2,scala.ScalaObject,java.io.Serializable
  SourceFile: "StdLexical.scala"
  Scala: length = 0x
   
  InnerClass: 
   public abstract Parser=class scala/util/parsing/combinator/Parsers$Parser of class scala/util/parsing/combinator/Parsers
   public final $anonfun$_delim$3=class scala/util/parsing/combinator/lexical/StdLexical$$anonfun$_delim$3 of class scala/util/parsing/combinator/lexical/StdLexical
   public final $anonfun$apply$27=class scala/util/parsing/combinator/lexical/StdLexical$$anonfun$_delim$3$$anonfun$apply$27 of class scala/util/parsing/combinator/lexical/StdLexical$$anonfun$_delim$3
  minor version: 0
  major version: 49
  Constant pool:
Asciz	SourceFile;
Asciz	StdLexical.scala;
Asciz	<clinit>;
Asciz	()V;
Asciz	Code;
Asciz	serialVersionUID;
Asciz	J;
Asciz	scala/util/parsing/combinator/lexical/StdLexical$$anonfun$_delim$3;
class	scala/util/parsing/combinator/lexical/StdLexical$$anonfun$_delim$3
NameAndType	serialVersionUID:J
Field	scala/util/parsing/combinator/lexical/StdLexical$$anonfun$_delim$3.serialVersionUID:J
Asciz	<init>;
Asciz	(Lscala/util/parsing/combinator/lexical/StdLexical;)V;
Asciz	LineNumberTable;
Asciz	java/lang/Object;
class	java/lang/Object
NameAndType	"<init>":()V
Method	java/lang/Object."<init>":()V
Asciz	scala/Function2$class;
class	scala/Function2$class
Asciz	$init$;
Asciz	(Lscala/Function2;)V;
NameAndType	$init$:(Lscala/Function2;)V
Method	scala/Function2$class.$init$:(Lscala/Function2;)V
Asciz	this;
Asciz	Lscala/util/parsing/combinator/lexical/StdLexical$$anonfun$_delim$3;;
Asciz	$outer;
Asciz	Lscala/util/parsing/combinator/lexical/StdLexical;;
Asciz	LocalVariableTable;
Asciz	apply;
Asciz	(Ljava/lang/Object;Ljava/lang/Object;)Ljava/lang/Object;;
Asciz	scala/util/parsing/combinator/Parsers$Parser;
class	scala/util/parsing/combinator/Parsers$Parser
Asciz	(Lscala/util/parsing/combinator/Parsers$Parser;Lscala/util/parsing/combinator/Parsers$Parser;)Lscala/util/parsing/combinator/Parsers$Parser;;
NameAndType	apply:(Lscala/util/parsing/combinator/Parsers$Parser;Lscala/util/parsing/combinator/Parsers$Parser;)Lscala/util/parsing/combinator/Parsers$Parser;
Method	scala/util/parsing/combinator/lexical/StdLexical$$anonfun$_delim$3.apply:(Lscala/util/parsing/combinator/Parsers$Parser;Lscala/util/parsing/combinator/Parsers$Parser;)Lscala/util/parsing/combinator/Parsers$Parser;
Asciz	v1;
Asciz	Ljava/lang/Object;;
Asciz	v2;
Asciz	scala/util/parsing/combinator/lexical/StdLexical$$anonfun$_delim$3$$anonfun$apply$27;
class	scala/util/parsing/combinator/lexical/StdLexical$$anonfun$_delim$3$$anonfun$apply$27
Asciz	(Lscala/util/parsing/combinator/lexical/StdLexical$$anonfun$_delim$3;Lscala/util/parsing/combinator/Parsers$Parser;)V;
NameAndType	"<init>":(Lscala/util/parsing/combinator/lexical/StdLexical$$anonfun$_delim$3;Lscala/util/parsing/combinator/Parsers$Parser;)V
Method	scala/util/parsing/combinator/lexical/StdLexical$$anonfun$_delim$3$$anonfun$apply$27."<init>":(Lscala/util/parsing/combinator/lexical/StdLexical$$anonfun$_delim$3;Lscala/util/parsing/combinator/Parsers$Parser;)V
Asciz	$bar;
Asciz	(Lscala/Function0;)Lscala/util/parsing/combinator/Parsers$Parser;;
NameAndType	$bar:(Lscala/Function0;)Lscala/util/parsing/combinator/Parsers$Parser;
Method	scala/util/parsing/combinator/Parsers$Parser.$bar:(Lscala/Function0;)Lscala/util/parsing/combinator/Parsers$Parser;
Asciz	x$4;
Asciz	Lscala/util/parsing/combinator/Parsers$Parser;;
Asciz	y;
Asciz	(Lscala/util/parsing/combinator/Parsers$Parser<Lscala/util/parsing/syntax/Tokens$Token;>;Lscala/util/parsing/combinator/Parsers$Parser<Lscala/util/parsing/syntax/Tokens$Token;>;)Lscala/util/parsing/combinator/Parsers$Parser<Lscala/util/parsing/syntax/Tokens$Token;>;;
Asciz	Signature;
Asciz	curry;
Asciz	()Lscala/Function1;;
Asciz	(Lscala/Function2;)Lscala/Function1;;
NameAndType	curry:(Lscala/Function2;)Lscala/Function1;
Method	scala/Function2$class.curry:(Lscala/Function2;)Lscala/Function1;
Asciz	toString;
Asciz	()Ljava/lang/String;;
Asciz	(Lscala/Function2;)Ljava/lang/String;;
NameAndType	toString:(Lscala/Function2;)Ljava/lang/String;
Method	scala/Function2$class.toString:(Lscala/Function2;)Ljava/lang/String;
Asciz	Scala;
Asciz	InnerClasses;
Asciz	scala/util/parsing/combinator/Parsers;
class	scala/util/parsing/combinator/Parsers
Asciz	Parser;
Asciz	scala/util/parsing/combinator/lexical/StdLexical;
class	scala/util/parsing/combinator/lexical/StdLexical
Asciz	$anonfun$_delim$3;
Asciz	$anonfun$apply$27;
Asciz	scala/Function2;
class	scala/Function2
Asciz	scala/ScalaObject;
class	scala/ScalaObject
Asciz	java/io/Serializable;
class	java/io/Serializable

{
public static final long serialVersionUID;
  Signature: J

public static {};
  Signature: ()V
  Code:
   Stack=2, Locals=0, Args_size=0
	lconst_0
	putstatic	Field serialVersionUID:J
	return
  Labels:

public scala.util.parsing.combinator.lexical.StdLexical$$anonfun$_delim$3(scala.util.parsing.combinator.lexical.StdLexical);
  Signature: (Lscala/util/parsing/combinator/lexical/StdLexical;)V
  Code:
   Stack=1, Locals=2, Args_size=2
	aload_0
	invokespecial	Method java/lang/Object."<init>":()V
	aload_0
	invokestatic	Method scala/Function2$class.$init$:(Lscala/Function2;)V
	return
  Labels:
  LocalVariableTable: 
   Start  Length  Slot  Name   Signature
   0      9      0    this       Lscala/util/parsing/combinator/lexical/StdLexical$$anonfun$_delim$3;
   0      9      1    $outer       Lscala/util/parsing/combinator/lexical/StdLexical;


public final java.lang.Object apply(java.lang.Object, java.lang.Object);
  Signature: (Ljava/lang/Object;Ljava/lang/Object;)Ljava/lang/Object;
  Code:
   Stack=3, Locals=3, Args_size=3
	aload_0
	aload_1
	checkcast	class scala/util/parsing/combinator/Parsers$Parser
	aload_2
	checkcast	class scala/util/parsing/combinator/Parsers$Parser
	invokevirtual	Method apply:(Lscala/util/parsing/combinator/Parsers$Parser;Lscala/util/parsing/combinator/Parsers$Parser;)Lscala/util/parsing/combinator/Parsers$Parser;
	areturn
  Labels:
  LocalVariableTable: 
   Start  Length  Slot  Name   Signature
   0      13      0    this       Lscala/util/parsing/combinator/lexical/StdLexical$$anonfun$_delim$3;
   0      13      1    v1       Ljava/lang/Object;
   0      13      2    v2       Ljava/lang/Object;


public final scala.util.parsing.combinator.Parsers$Parser apply(scala.util.parsing.combinator.Parsers$Parser, scala.util.parsing.combinator.Parsers$Parser);
  Signature: (Lscala/util/parsing/combinator/Parsers$Parser;Lscala/util/parsing/combinator/Parsers$Parser;)Lscala/util/parsing/combinator/Parsers$Parser;
  Code:
   Stack=5, Locals=3, Args_size=3
	aload_2
	new	class scala/util/parsing/combinator/lexical/StdLexical$$anonfun$_delim$3$$anonfun$apply$27
	dup
	aload_0
	aload_1
	invokespecial	Method scala/util/parsing/combinator/lexical/StdLexical$$anonfun$_delim$3$$anonfun$apply$27."<init>":(Lscala/util/parsing/combinator/lexical/StdLexical$$anonfun$_delim$3;Lscala/util/parsing/combinator/Parsers$Parser;)V
	invokevirtual	Method scala/util/parsing/combinator/Parsers$Parser.$bar:(Lscala/Function0;)Lscala/util/parsing/combinator/Parsers$Parser;
	areturn
  Labels:
  LocalVariableTable: 
   Start  Length  Slot  Name   Signature
   0      14      0    this       Lscala/util/parsing/combinator/lexical/StdLexical$$anonfun$_delim$3;
   0      14      1    x$4       Lscala/util/parsing/combinator/Parsers$Parser;
   0      14      2    y       Lscala/util/parsing/combinator/Parsers$Parser;

  Signature: length = 0x2
   00 34 

public scala.Function1 curry();
  Signature: ()Lscala/Function1;
  Code:
   Stack=1, Locals=1, Args_size=1
	aload_0
	invokestatic	Method scala/Function2$class.curry:(Lscala/Function2;)Lscala/Function1;
	areturn
  Labels:

public java.lang.String toString();
  Signature: ()Ljava/lang/String;
  Code:
   Stack=1, Locals=1, Args_size=1
	aload_0
	invokestatic	Method scala/Function2$class.toString:(Lscala/Function2;)Ljava/lang/String;
	areturn
  Labels:

}

