Compiled from "StdLexical.scala"
public final class scala.util.parsing.combinator.lexical.StdLexical$$anonfun$token$4$$anonfun$apply$9 extends scala.runtime.AbstractFunction1 implements java.io.Serializable
  SourceFile: "StdLexical.scala"
  Scala: length = 0x
   
  InnerClass: 
   public $tilde=class scala/util/parsing/combinator/Parsers$$tilde of class scala/util/parsing/combinator/Parsers
   public StringLit=class scala/util/parsing/syntax/StdTokens$StringLit of class scala/util/parsing/syntax/StdTokens
   public final $anonfun$token$4=class scala/util/parsing/combinator/lexical/StdLexical$$anonfun$token$4 of class scala/util/parsing/combinator/lexical/StdLexical
   public final $anonfun$apply$9=class scala/util/parsing/combinator/lexical/StdLexical$$anonfun$token$4$$anonfun$apply$9 of class scala/util/parsing/combinator/lexical/StdLexical$$anonfun$token$4
  minor version: 0
  major version: 49
  Constant pool:
Asciz	SourceFile;
Asciz	StdLexical.scala;
Asciz	<clinit>;
Asciz	()V;
Asciz	Code;
Asciz	serialVersionUID;
Asciz	J;
Asciz	scala/util/parsing/combinator/lexical/StdLexical$$anonfun$token$4$$anonfun$apply$9;
class	scala/util/parsing/combinator/lexical/StdLexical$$anonfun$token$4$$anonfun$apply$9
NameAndType	serialVersionUID:J
Field	scala/util/parsing/combinator/lexical/StdLexical$$anonfun$token$4$$anonfun$apply$9.serialVersionUID:J
Asciz	$outer;
Asciz	Lscala/util/parsing/combinator/lexical/StdLexical$$anonfun$token$4;;
Asciz	apply;
Asciz	(Lscala/util/parsing/combinator/Parsers$$tilde;)Lscala/util/parsing/syntax/StdTokens$StringLit;;
Asciz	LineNumberTable;
Asciz	scala/util/parsing/combinator/Parsers$$tilde;
class	scala/util/parsing/combinator/Parsers$$tilde
Asciz	_1;
Asciz	()Ljava/lang/Object;;
NameAndType	_1:()Ljava/lang/Object;
Method	scala/util/parsing/combinator/Parsers$$tilde._1:()Ljava/lang/Object;
Asciz	_2;
NameAndType	_2:()Ljava/lang/Object;
Method	scala/util/parsing/combinator/Parsers$$tilde._2:()Ljava/lang/Object;
Asciz	scala/collection/immutable/List;
class	scala/collection/immutable/List
Asciz	scala/runtime/BoxesRunTime;
class	scala/runtime/BoxesRunTime
Asciz	unboxToChar;
Asciz	(Ljava/lang/Object;)C;
NameAndType	unboxToChar:(Ljava/lang/Object;)C
Method	scala/runtime/BoxesRunTime.unboxToChar:(Ljava/lang/Object;)C
int	39;
Asciz	scala/util/parsing/syntax/StdTokens$StringLit;
class	scala/util/parsing/syntax/StdTokens$StringLit
NameAndType	$outer:Lscala/util/parsing/combinator/lexical/StdLexical$$anonfun$token$4;
Field	scala/util/parsing/combinator/lexical/StdLexical$$anonfun$token$4$$anonfun$apply$9.$outer:Lscala/util/parsing/combinator/lexical/StdLexical$$anonfun$token$4;
Asciz	scala/util/parsing/combinator/lexical/StdLexical$$anonfun$token$4;
class	scala/util/parsing/combinator/lexical/StdLexical$$anonfun$token$4
Asciz	Lscala/util/parsing/combinator/lexical/StdLexical;;
NameAndType	$outer:Lscala/util/parsing/combinator/lexical/StdLexical;
Field	scala/util/parsing/combinator/lexical/StdLexical$$anonfun$token$4.$outer:Lscala/util/parsing/combinator/lexical/StdLexical;
Asciz	;
String	
Asciz	scala/collection/TraversableLike;
class	scala/collection/TraversableLike
Asciz	mkString;
Asciz	(Ljava/lang/String;)Ljava/lang/String;;
NameAndType	mkString:(Ljava/lang/String;)Ljava/lang/String;
InterfaceMethod	scala/collection/TraversableLike.mkString:(Ljava/lang/String;)Ljava/lang/String;
Asciz	<init>;
Asciz	(Lscala/util/parsing/syntax/StdTokens;Ljava/lang/String;)V;
NameAndType	"<init>":(Lscala/util/parsing/syntax/StdTokens;Ljava/lang/String;)V
Method	scala/util/parsing/syntax/StdTokens$StringLit."<init>":(Lscala/util/parsing/syntax/StdTokens;Ljava/lang/String;)V
Asciz	scala/MatchError;
class	scala/MatchError
Asciz	toString;
Asciz	()Ljava/lang/String;;
NameAndType	toString:()Ljava/lang/String;
Method	scala/util/parsing/combinator/Parsers$$tilde.toString:()Ljava/lang/String;
Asciz	(Ljava/lang/String;)V;
NameAndType	"<init>":(Ljava/lang/String;)V
Method	scala/MatchError."<init>":(Ljava/lang/String;)V
Asciz	this;
Asciz	Lscala/util/parsing/combinator/lexical/StdLexical$$anonfun$token$4$$anonfun$apply$9;;
Asciz	temp8;
Asciz	Lscala/util/parsing/combinator/Parsers$$tilde;;
Asciz	temp11;
Asciz	Lscala/collection/immutable/List;;
Asciz	LocalVariableTable;
Asciz	(Lscala/util/parsing/combinator/Parsers$$tilde<Lscala/util/parsing/combinator/Parsers$$tilde<Ljava/lang/Character;Lscala/collection/immutable/List<Ljava/lang/Character;>;>;Ljava/lang/Character;>;)Lscala/util/parsing/syntax/StdTokens$StringLit;;
Asciz	Signature;
Asciz	(Ljava/lang/Object;)Ljava/lang/Object;;
NameAndType	apply:(Lscala/util/parsing/combinator/Parsers$$tilde;)Lscala/util/parsing/syntax/StdTokens$StringLit;
Method	scala/util/parsing/combinator/lexical/StdLexical$$anonfun$token$4$$anonfun$apply$9.apply:(Lscala/util/parsing/combinator/Parsers$$tilde;)Lscala/util/parsing/syntax/StdTokens$StringLit;
Asciz	v1;
Asciz	Ljava/lang/Object;;
Asciz	(Lscala/util/parsing/combinator/lexical/StdLexical$$anonfun$token$4;)V;
Asciz	java/lang/NullPointerException;
class	java/lang/NullPointerException
NameAndType	"<init>":()V
Method	java/lang/NullPointerException."<init>":()V
Asciz	scala/runtime/AbstractFunction1;
class	scala/runtime/AbstractFunction1
Method	scala/runtime/AbstractFunction1."<init>":()V
Asciz	Scala;
Asciz	InnerClasses;
Asciz	scala/util/parsing/combinator/Parsers;
class	scala/util/parsing/combinator/Parsers
Asciz	$tilde;
Asciz	scala/util/parsing/syntax/StdTokens;
class	scala/util/parsing/syntax/StdTokens
Asciz	StringLit;
Asciz	scala/util/parsing/combinator/lexical/StdLexical;
class	scala/util/parsing/combinator/lexical/StdLexical
Asciz	$anonfun$token$4;
Asciz	$anonfun$apply$9;
Asciz	java/io/Serializable;
class	java/io/Serializable

{
public static final long serialVersionUID;
  Signature: J

public final scala.util.parsing.combinator.lexical.StdLexical$$anonfun$token$4 $outer;
  Signature: Lscala/util/parsing/combinator/lexical/StdLexical$$anonfun$token$4;

public static {};
  Signature: ()V
  Code:
   Stack=2, Locals=0, Args_size=0
	lconst_0
	putstatic	Field serialVersionUID:J
	return
  Labels:

public final scala.util.parsing.syntax.StdTokens$StringLit apply(scala.util.parsing.combinator.Parsers$$tilde);
  Signature: (Lscala/util/parsing/combinator/Parsers$$tilde;)Lscala/util/parsing/syntax/StdTokens$StringLit;
  Code:
   Stack=5, Locals=5, Args_size=2
	aload_1
	ifnull	l1 // new
	aload_1
	invokevirtual	Method scala/util/parsing/combinator/Parsers$$tilde._1:()Ljava/lang/Object;
	checkcast	class scala/util/parsing/combinator/Parsers$$tilde
	astore_2
	aload_2
	ifnull	l2 // new
	aload_2
	invokevirtual	Method scala/util/parsing/combinator/Parsers$$tilde._2:()Ljava/lang/Object;
	checkcast	class scala/collection/immutable/List
	astore	4
	aload_2
	invokevirtual	Method scala/util/parsing/combinator/Parsers$$tilde._1:()Ljava/lang/Object;
	invokestatic	Method scala/runtime/BoxesRunTime.unboxToChar:(Ljava/lang/Object;)C
	ldc	int 39
	if_icmpne	l3 // new
	aload_1
	invokevirtual	Method scala/util/parsing/combinator/Parsers$$tilde._2:()Ljava/lang/Object;
	invokestatic	Method scala/runtime/BoxesRunTime.unboxToChar:(Ljava/lang/Object;)C
	ldc	int 39
	if_icmpne	l3 // new
	new	class scala/util/parsing/syntax/StdTokens$StringLit
	dup
	aload_0
	getfield	Field $outer:Lscala/util/parsing/combinator/lexical/StdLexical$$anonfun$token$4;
	astore_3
	aload_3
	getfield	Field scala/util/parsing/combinator/lexical/StdLexical$$anonfun$token$4.$outer:Lscala/util/parsing/combinator/lexical/StdLexical;
	aload	4
	ldc	String 
	invokeinterface	InterfaceMethod scala/collection/TraversableLike.mkString:(Ljava/lang/String;)Ljava/lang/String;
	invokespecial	Method scala/util/parsing/syntax/StdTokens$StringLit."<init>":(Lscala/util/parsing/syntax/StdTokens;Ljava/lang/String;)V
	areturn
l3	new	class scala/MatchError
	dup
	aload_1
	invokevirtual	Method scala/util/parsing/combinator/Parsers$$tilde.toString:()Ljava/lang/String;
	invokespecial	Method scala/MatchError."<init>":(Ljava/lang/String;)V
	athrow
l2	new	class scala/MatchError
	dup
	aload_1
	invokevirtual	Method scala/util/parsing/combinator/Parsers$$tilde.toString:()Ljava/lang/String;
	invokespecial	Method scala/MatchError."<init>":(Ljava/lang/String;)V
	athrow
l1	new	class scala/MatchError
	dup
	aload_1
	invokevirtual	Method scala/util/parsing/combinator/Parsers$$tilde.toString:()Ljava/lang/String;
	invokespecial	Method scala/MatchError."<init>":(Ljava/lang/String;)V
	athrow
  Labels:
   	l3 = 75 // new
   	l2 = 87 // new
   	l1 = 99 // new
  LocalVariableTable: 
   Start  Length  Slot  Name   Signature
   0      111      0    this       Lscala/util/parsing/combinator/lexical/StdLexical$$anonfun$token$4$$anonfun$apply$9;
   12      87      2    temp8       Lscala/util/parsing/combinator/Parsers$$tilde;
   25      62      4    temp11       Lscala/collection/immutable/List;

  Signature: length = 0x2
   00 48 

public final java.lang.Object apply(java.lang.Object);
  Signature: (Ljava/lang/Object;)Ljava/lang/Object;
  Code:
   Stack=2, Locals=2, Args_size=2
	aload_0
	aload_1
	checkcast	class scala/util/parsing/combinator/Parsers$$tilde
	invokevirtual	Method apply:(Lscala/util/parsing/combinator/Parsers$$tilde;)Lscala/util/parsing/syntax/StdTokens$StringLit;
	areturn
  Labels:
  LocalVariableTable: 
   Start  Length  Slot  Name   Signature
   0      9      0    this       Lscala/util/parsing/combinator/lexical/StdLexical$$anonfun$token$4$$anonfun$apply$9;
   0      9      1    v1       Ljava/lang/Object;


public scala.util.parsing.combinator.lexical.StdLexical$$anonfun$token$4$$anonfun$apply$9(scala.util.parsing.combinator.lexical.StdLexical$$anonfun$token$4);
  Signature: (Lscala/util/parsing/combinator/lexical/StdLexical$$anonfun$token$4;)V
  Code:
   Stack=2, Locals=2, Args_size=2
	aload_1
	ifnonnull	l1 // aload_0
	new	class java/lang/NullPointerException
	dup
	invokespecial	Method java/lang/NullPointerException."<init>":()V
	athrow
l1	aload_0
	aload_1
	putfield	Field $outer:Lscala/util/parsing/combinator/lexical/StdLexical$$anonfun$token$4;
	aload_0
	invokespecial	Method scala/runtime/AbstractFunction1."<init>":()V
	return
  Labels:
   	l1 = 12 // aload_0
  LocalVariableTable: 
   Start  Length  Slot  Name   Signature
   0      22      0    this       Lscala/util/parsing/combinator/lexical/StdLexical$$anonfun$token$4$$anonfun$apply$9;
   0      22      1    $outer       Lscala/util/parsing/combinator/lexical/StdLexical$$anonfun$token$4;


}

