Compiled from "StdLexical.scala"
public final class scala.util.parsing.combinator.lexical.StdLexical$$anonfun$parseDelim$1$1 extends java.lang.Object implements scala.Function1,scala.ScalaObject,java.io.Serializable
  SourceFile: "StdLexical.scala"
  Scala: length = 0x
   
  InnerClass: 
   public Keyword=class scala/util/parsing/syntax/StdTokens$Keyword of class scala/util/parsing/syntax/StdTokens
   public final $anonfun$parseDelim$1$1=class scala/util/parsing/combinator/lexical/StdLexical$$anonfun$parseDelim$1$1 of class scala/util/parsing/combinator/lexical/StdLexical
  minor version: 0
  major version: 49
  Constant pool:
Asciz	SourceFile;
Asciz	StdLexical.scala;
Asciz	<clinit>;
Asciz	()V;
Asciz	Code;
Asciz	serialVersionUID;
Asciz	J;
Asciz	scala/util/parsing/combinator/lexical/StdLexical$$anonfun$parseDelim$1$1;
class	scala/util/parsing/combinator/lexical/StdLexical$$anonfun$parseDelim$1$1
NameAndType	serialVersionUID:J
Field	scala/util/parsing/combinator/lexical/StdLexical$$anonfun$parseDelim$1$1.serialVersionUID:J
Asciz	s$1;
Asciz	Ljava/lang/String;;
Asciz	$outer;
Asciz	Lscala/util/parsing/combinator/lexical/StdLexical;;
Asciz	<init>;
Asciz	(Lscala/util/parsing/combinator/lexical/StdLexical;Ljava/lang/String;)V;
Asciz	LineNumberTable;
Asciz	java/lang/NullPointerException;
class	java/lang/NullPointerException
NameAndType	"<init>":()V
Method	java/lang/NullPointerException."<init>":()V
NameAndType	$outer:Lscala/util/parsing/combinator/lexical/StdLexical;
Field	scala/util/parsing/combinator/lexical/StdLexical$$anonfun$parseDelim$1$1.$outer:Lscala/util/parsing/combinator/lexical/StdLexical;
NameAndType	s$1:Ljava/lang/String;
Field	scala/util/parsing/combinator/lexical/StdLexical$$anonfun$parseDelim$1$1.s$1:Ljava/lang/String;
Asciz	java/lang/Object;
class	java/lang/Object
Method	java/lang/Object."<init>":()V
Asciz	scala/Function1$class;
class	scala/Function1$class
Asciz	$init$;
Asciz	(Lscala/Function1;)V;
NameAndType	$init$:(Lscala/Function1;)V
Method	scala/Function1$class.$init$:(Lscala/Function1;)V
Asciz	this;
Asciz	Lscala/util/parsing/combinator/lexical/StdLexical$$anonfun$parseDelim$1$1;;
Asciz	LocalVariableTable;
Asciz	apply;
Asciz	(Ljava/lang/Object;)Ljava/lang/Object;;
Asciz	scala/collection/immutable/List;
class	scala/collection/immutable/List
Asciz	(Lscala/collection/immutable/List;)Lscala/util/parsing/syntax/StdTokens$Keyword;;
NameAndType	apply:(Lscala/collection/immutable/List;)Lscala/util/parsing/syntax/StdTokens$Keyword;
Method	scala/util/parsing/combinator/lexical/StdLexical$$anonfun$parseDelim$1$1.apply:(Lscala/collection/immutable/List;)Lscala/util/parsing/syntax/StdTokens$Keyword;
Asciz	v1;
Asciz	Ljava/lang/Object;;
Asciz	scala/util/parsing/syntax/StdTokens$Keyword;
class	scala/util/parsing/syntax/StdTokens$Keyword
Asciz	(Lscala/util/parsing/syntax/StdTokens;Ljava/lang/String;)V;
NameAndType	"<init>":(Lscala/util/parsing/syntax/StdTokens;Ljava/lang/String;)V
Method	scala/util/parsing/syntax/StdTokens$Keyword."<init>":(Lscala/util/parsing/syntax/StdTokens;Ljava/lang/String;)V
Asciz	x;
Asciz	Lscala/collection/immutable/List;;
Asciz	(Lscala/collection/immutable/List<Ljava/lang/Character;>;)Lscala/util/parsing/syntax/StdTokens$Keyword;;
Asciz	Signature;
Asciz	andThen;
Asciz	(Lscala/Function1;)Lscala/Function1;;
Asciz	(Lscala/Function1;Lscala/Function1;)Lscala/Function1;;
NameAndType	andThen:(Lscala/Function1;Lscala/Function1;)Lscala/Function1;
Method	scala/Function1$class.andThen:(Lscala/Function1;Lscala/Function1;)Lscala/Function1;
Asciz	g;
Asciz	Lscala/Function1;;
Asciz	compose;
NameAndType	compose:(Lscala/Function1;Lscala/Function1;)Lscala/Function1;
Method	scala/Function1$class.compose:(Lscala/Function1;Lscala/Function1;)Lscala/Function1;
Asciz	toString;
Asciz	()Ljava/lang/String;;
Asciz	(Lscala/Function1;)Ljava/lang/String;;
NameAndType	toString:(Lscala/Function1;)Ljava/lang/String;
Method	scala/Function1$class.toString:(Lscala/Function1;)Ljava/lang/String;
Asciz	Scala;
Asciz	InnerClasses;
Asciz	scala/util/parsing/syntax/StdTokens;
class	scala/util/parsing/syntax/StdTokens
Asciz	Keyword;
Asciz	scala/util/parsing/combinator/lexical/StdLexical;
class	scala/util/parsing/combinator/lexical/StdLexical
Asciz	$anonfun$parseDelim$1$1;
Asciz	scala/Function1;
class	scala/Function1
Asciz	scala/ScalaObject;
class	scala/ScalaObject
Asciz	java/io/Serializable;
class	java/io/Serializable

{
public static final long serialVersionUID;
  Signature: J

private final java.lang.String s$1;
  Signature: Ljava/lang/String;

private final scala.util.parsing.combinator.lexical.StdLexical $outer;
  Signature: Lscala/util/parsing/combinator/lexical/StdLexical;

public static {};
  Signature: ()V
  Code:
   Stack=2, Locals=0, Args_size=0
	lconst_0
	putstatic	Field serialVersionUID:J
	return
  Labels:

public scala.util.parsing.combinator.lexical.StdLexical$$anonfun$parseDelim$1$1(scala.util.parsing.combinator.lexical.StdLexical, java.lang.String);
  Signature: (Lscala/util/parsing/combinator/lexical/StdLexical;Ljava/lang/String;)V
  Code:
   Stack=2, Locals=3, Args_size=3
	aload_1
	ifnonnull	l1 // aload_0
	new	class java/lang/NullPointerException
	dup
	invokespecial	Method java/lang/NullPointerException."<init>":()V
	athrow
l1	aload_0
	aload_1
	putfield	Field $outer:Lscala/util/parsing/combinator/lexical/StdLexical;
	aload_0
	aload_2
	putfield	Field s$1:Ljava/lang/String;
	aload_0
	invokespecial	Method java/lang/Object."<init>":()V
	aload_0
	invokestatic	Method scala/Function1$class.$init$:(Lscala/Function1;)V
	return
  Labels:
   	l1 = 12 // aload_0
  LocalVariableTable: 
   Start  Length  Slot  Name   Signature
   0      31      0    this       Lscala/util/parsing/combinator/lexical/StdLexical$$anonfun$parseDelim$1$1;
   0      31      1    $outer       Lscala/util/parsing/combinator/lexical/StdLexical;


public final java.lang.Object apply(java.lang.Object);
  Signature: (Ljava/lang/Object;)Ljava/lang/Object;
  Code:
   Stack=2, Locals=3, Args_size=2
	aload_0
	getfield	Field $outer:Lscala/util/parsing/combinator/lexical/StdLexical;
	astore_2
	aload_0
	aload_1
	checkcast	class scala/collection/immutable/List
	invokevirtual	Method apply:(Lscala/collection/immutable/List;)Lscala/util/parsing/syntax/StdTokens$Keyword;
	areturn
  Labels:
  LocalVariableTable: 
   Start  Length  Slot  Name   Signature
   0      14      0    this       Lscala/util/parsing/combinator/lexical/StdLexical$$anonfun$parseDelim$1$1;
   5      9      1    v1       Ljava/lang/Object;


public final scala.util.parsing.syntax.StdTokens$Keyword apply(scala.collection.immutable.List);
  Signature: (Lscala/collection/immutable/List;)Lscala/util/parsing/syntax/StdTokens$Keyword;
  Code:
   Stack=4, Locals=3, Args_size=2
	aload_0
	getfield	Field $outer:Lscala/util/parsing/combinator/lexical/StdLexical;
	astore_2
	new	class scala/util/parsing/syntax/StdTokens$Keyword
	dup
	aload_0
	getfield	Field $outer:Lscala/util/parsing/combinator/lexical/StdLexical;
	aload_0
	getfield	Field s$1:Ljava/lang/String;
	invokespecial	Method scala/util/parsing/syntax/StdTokens$Keyword."<init>":(Lscala/util/parsing/syntax/StdTokens;Ljava/lang/String;)V
	areturn
  Labels:
  LocalVariableTable: 
   Start  Length  Slot  Name   Signature
   0      21      0    this       Lscala/util/parsing/combinator/lexical/StdLexical$$anonfun$parseDelim$1$1;
   5      16      1    x       Lscala/collection/immutable/List;

  Signature: length = 0x2
   00 37 

public scala.Function1 andThen(scala.Function1);
  Signature: (Lscala/Function1;)Lscala/Function1;
  Code:
   Stack=2, Locals=2, Args_size=2
	aload_0
	aload_1
	invokestatic	Method scala/Function1$class.andThen:(Lscala/Function1;Lscala/Function1;)Lscala/Function1;
	areturn
  Labels:
  LocalVariableTable: 
   Start  Length  Slot  Name   Signature
   0      6      0    this       Lscala/util/parsing/combinator/lexical/StdLexical$$anonfun$parseDelim$1$1;
   0      6      1    g       Lscala/Function1;


public scala.Function1 compose(scala.Function1);
  Signature: (Lscala/Function1;)Lscala/Function1;
  Code:
   Stack=2, Locals=2, Args_size=2
	aload_0
	aload_1
	invokestatic	Method scala/Function1$class.compose:(Lscala/Function1;Lscala/Function1;)Lscala/Function1;
	areturn
  Labels:
  LocalVariableTable: 
   Start  Length  Slot  Name   Signature
   0      6      0    this       Lscala/util/parsing/combinator/lexical/StdLexical$$anonfun$parseDelim$1$1;
   0      6      1    g       Lscala/Function1;


public java.lang.String toString();
  Signature: ()Ljava/lang/String;
  Code:
   Stack=1, Locals=1, Args_size=1
	aload_0
	invokestatic	Method scala/Function1$class.toString:(Lscala/Function1;)Ljava/lang/String;
	areturn
  Labels:

}

