Compiled from "StdLexical.scala"
public final class scala.util.parsing.combinator.lexical.StdLexical$$anonfun$comment$2 extends scala.runtime.AbstractFunction1 implements java.io.Serializable
  SourceFile: "StdLexical.scala"
  Scala: length = 0x
   
  InnerClass: 
   public $tilde=class scala/util/parsing/combinator/Parsers$$tilde of class scala/util/parsing/combinator/Parsers
   public final $anonfun$comment$2=class scala/util/parsing/combinator/lexical/StdLexical$$anonfun$comment$2 of class scala/util/parsing/combinator/lexical/StdLexical
  minor version: 0
  major version: 49
  Constant pool:
Asciz	SourceFile;
Asciz	StdLexical.scala;
Asciz	<clinit>;
Asciz	()V;
Asciz	Code;
Asciz	serialVersionUID;
Asciz	J;
Asciz	scala/util/parsing/combinator/lexical/StdLexical$$anonfun$comment$2;
class	scala/util/parsing/combinator/lexical/StdLexical$$anonfun$comment$2
NameAndType	serialVersionUID:J
Field	scala/util/parsing/combinator/lexical/StdLexical$$anonfun$comment$2.serialVersionUID:J
Asciz	<init>;
Asciz	(Lscala/util/parsing/combinator/lexical/StdLexical;)V;
Asciz	LineNumberTable;
Asciz	scala/runtime/AbstractFunction1;
class	scala/runtime/AbstractFunction1
NameAndType	"<init>":()V
Method	scala/runtime/AbstractFunction1."<init>":()V
Asciz	this;
Asciz	Lscala/util/parsing/combinator/lexical/StdLexical$$anonfun$comment$2;;
Asciz	$outer;
Asciz	Lscala/util/parsing/combinator/lexical/StdLexical;;
Asciz	LocalVariableTable;
Asciz	apply;
Asciz	(Ljava/lang/Object;)Ljava/lang/Object;;
Asciz	scala/util/parsing/combinator/Parsers$$tilde;
class	scala/util/parsing/combinator/Parsers$$tilde
Asciz	(Lscala/util/parsing/combinator/Parsers$$tilde;)C;
NameAndType	apply:(Lscala/util/parsing/combinator/Parsers$$tilde;)C
Method	scala/util/parsing/combinator/lexical/StdLexical$$anonfun$comment$2.apply:(Lscala/util/parsing/combinator/Parsers$$tilde;)C
Asciz	scala/runtime/BoxesRunTime;
class	scala/runtime/BoxesRunTime
Asciz	boxToCharacter;
Asciz	(C)Ljava/lang/Character;;
NameAndType	boxToCharacter:(C)Ljava/lang/Character;
Method	scala/runtime/BoxesRunTime.boxToCharacter:(C)Ljava/lang/Character;
Asciz	v1;
Asciz	Ljava/lang/Object;;
int	32;
Asciz	scala/MatchError;
class	scala/MatchError
Asciz	toString;
Asciz	()Ljava/lang/String;;
NameAndType	toString:()Ljava/lang/String;
Method	scala/util/parsing/combinator/Parsers$$tilde.toString:()Ljava/lang/String;
Asciz	(Ljava/lang/String;)V;
NameAndType	"<init>":(Ljava/lang/String;)V
Method	scala/MatchError."<init>":(Ljava/lang/String;)V
Asciz	(Lscala/util/parsing/combinator/Parsers$$tilde<Ljava/lang/Character;Ljava/lang/Character;>;)C;
Asciz	Signature;
Asciz	Scala;
Asciz	InnerClasses;
Asciz	scala/util/parsing/combinator/Parsers;
class	scala/util/parsing/combinator/Parsers
Asciz	$tilde;
Asciz	scala/util/parsing/combinator/lexical/StdLexical;
class	scala/util/parsing/combinator/lexical/StdLexical
Asciz	$anonfun$comment$2;
Asciz	java/io/Serializable;
class	java/io/Serializable

{
public static final long serialVersionUID;
  Signature: J

public static {};
  Signature: ()V
  Code:
   Stack=2, Locals=0, Args_size=0
	lconst_0
	putstatic	Field serialVersionUID:J
	return
  Labels:

public scala.util.parsing.combinator.lexical.StdLexical$$anonfun$comment$2(scala.util.parsing.combinator.lexical.StdLexical);
  Signature: (Lscala/util/parsing/combinator/lexical/StdLexical;)V
  Code:
   Stack=1, Locals=2, Args_size=2
	aload_0
	invokespecial	Method scala/runtime/AbstractFunction1."<init>":()V
	return
  Labels:
  LocalVariableTable: 
   Start  Length  Slot  Name   Signature
   0      5      0    this       Lscala/util/parsing/combinator/lexical/StdLexical$$anonfun$comment$2;
   0      5      1    $outer       Lscala/util/parsing/combinator/lexical/StdLexical;


public final java.lang.Object apply(java.lang.Object);
  Signature: (Ljava/lang/Object;)Ljava/lang/Object;
  Code:
   Stack=2, Locals=3, Args_size=2
	aload_0
	aload_1
	checkcast	class scala/util/parsing/combinator/Parsers$$tilde
	invokevirtual	Method apply:(Lscala/util/parsing/combinator/Parsers$$tilde;)C
	istore_2
	iload_2
	invokestatic	Method scala/runtime/BoxesRunTime.boxToCharacter:(C)Ljava/lang/Character;
	areturn
  Labels:
  LocalVariableTable: 
   Start  Length  Slot  Name   Signature
   0      14      0    this       Lscala/util/parsing/combinator/lexical/StdLexical$$anonfun$comment$2;
   0      14      1    v1       Ljava/lang/Object;


public final char apply(scala.util.parsing.combinator.Parsers$$tilde);
  Signature: (Lscala/util/parsing/combinator/Parsers$$tilde;)C
  Code:
   Stack=3, Locals=2, Args_size=2
	iconst_1
	ifeq	l1 // new
	ldc	int 32
	ireturn
l1	new	class scala/MatchError
	dup
	aload_1
	invokevirtual	Method scala/util/parsing/combinator/Parsers$$tilde.toString:()Ljava/lang/String;
	invokespecial	Method scala/MatchError."<init>":(Ljava/lang/String;)V
	athrow
  Labels:
   	l1 = 7 // new
  Signature: length = 0x2
   00 31 

}

