Compiled from "StdLexical.scala"
public class scala.util.parsing.combinator.lexical.StdLexical extends scala.util.parsing.combinator.lexical.Lexical implements scala.util.parsing.combinator.token.StdTokens,scala.ScalaObject
  SourceFile: "StdLexical.scala"
  ScalaSig: length = 0x3CB
   05 00 FFFFFF81 19 06 08 01 02 FFFFFF84 FFFFFF80 FFFFFF80 FFFFFF80 00 0D 02 0A
   53 74 64 4C 65 78 69 63 61 6C 0A 02 03 04 01 07
   6C 65 78 69 63 61 6C 0A 02 05 06 01 0A 63 6F 6D
   62 69 6E 61 74 6F 72 0A 02 07 08 01 07 70 61 72
   73 69 6E 67 0A 02 09 0A 01 04 75 74 69 6C 0A 01
   0B 01 05 73 63 61 6C 61 03 00 13 04 00 0E 12 18
   10 02 0F 10 0D 01 02 09 02 11 02 02 07 4C 65 78
   69 63 61 6C 10 02 13 16 0D 01 14 0A 02 15 04 01
   05 74 6F 6B 65 6E 09 02 17 14 02 09 53 74 64 54
   6F 6B 65 6E 73 10 02 19 1A 0D 01 0A 09 02 1B 0A
   02 0B 53 63 61 6C 61 4F 62 6A 65 63 74 08 05 1D
   00 FFFFFF84 00 1E 01 06 3C 69 6E 69 74 3E 14 01 1F 10
   02 0F 00 08 05 15 00 FFFFFF84 00 21 15 01 22 10 03 23
   24 28 0D 01 00 09 02 25 26 02 06 50 61 72 73 65
   72 09 02 27 04 02 07 50 61 72 73 65 72 73 10 02
   23 29 09 02 2A 2B 02 05 54 6F 6B 65 6E 09 02 2C
   14 02 06 54 6F 6B 65 6E 73 08 05 2E 00 FFFFFF84 00 2F
   01 09 69 64 65 6E 74 43 68 61 72 15 01 30 10 03
   23 24 31 10 02 23 32 09 02 33 34 02 04 45 6C 65
   6D 09 02 35 02 02 08 53 63 61 6E 6E 65 72 73 08
   05 37 00 FFFFFF84 00 38 01 0A 77 68 69 74 65 73 70 61
   63 65 15 01 39 10 03 23 24 3A 10 02 19 3B 09 02
   3C 0A 02 03 41 6E 79 08 05 3E 00 FFFFFF84 08 38 01 07
   63 6F 6D 6D 65 6E 74 08 07 40 00 FFFFFFC2 FFFFFF80 FFFFFF84 00 41
   01 08 72 65 73 65 72 76 65 64 15 01 42 10 03 43
   48 4A 0D 01 44 0A 02 45 46 01 07 6D 75 74 61 62
   6C 65 0A 02 47 0A 01 0A 63 6F 6C 6C 65 63 74 69
   6F 6E 09 02 49 44 02 07 48 61 73 68 53 65 74 10
   02 4B 4E 0E 02 19 4C 09 02 4D 0A 01 06 50 72 65
   64 65 66 09 02 4F 50 02 06 53 74 72 69 6E 67 0A
   02 4D 0A 08 06 52 00 FFFFFFA0 FFFFFF80 04 42 01 09 72 65 73
   65 72 76 65 64 20 08 07 54 00 FFFFFFC2 FFFFFF80 FFFFFF84 00 41 01
   0A 64 65 6C 69 6D 69 74 65 72 73 08 06 56 00 FFFFFFA0
   FFFFFF80 04 42 01 0B 64 65 6C 69 6D 69 74 65 72 73 20
   08 05 58 00 FFFFFF84 08 59 01 0C 70 72 6F 63 65 73 73
   49 64 65 6E 74 14 02 5A 60 12 03 5B 5D 28 06 08
   5C 00 FFFFFF84 FFFFFF80 FFFFFF80 FFFFFF80 00 5A 02 0C 3C 72 65 66 69 6E
   65 6D 65 6E 74 3E 10 02 19 5E 09 02 5F 0A 02 07
   50 72 6F 64 75 63 74 08 05 61 57 FFFFFFC0 00 4A 01 04
   6E 61 6D 65 08 08 63 00 FFFFFF88 FFFFFFC2 FFFFFF80 FFFFFF84 04 21 01 06
   5F 64 65 6C 69 6D 08 08 65 00 FFFFFF88 FFFFFF80 FFFFFFA0 FFFFFFA0 04 22
   01 07 5F 64 65 6C 69 6D 20 08 05 67 00 FFFFFF84 08 21
   01 05 64 65 6C 69 6D 08 05 69 00 FFFFFF84 04 6A 01 04
   6C 69 66 74 15 02 6B 6F 14 03 6C FFFFFF81 06 14 02 6D
   75 10 02 6E 6F 0C 00 04 08 70 68 FFFFFF84 FFFFFF80 FFFFFF80 FFFFFFC2 00
   71 02 01 54 11 02 72 3A 10 02 19 73 09 02 74 0A
   02 07 4E 6F 74 68 69 6E 67 08 05 76 68 FFFFFFC0 00 77
   01 02 78 73 10 05 78 FFFFFF81 00 FFFFFF81 03 0E 02 79 7E 0E
   02 7A 7D 0D 01 7B 0A 02 7C 0C 01 06 3C 72 6F 6F
   74 3E 09 01 0B 09 02 7F 0A 01 07 70 61 63 6B 61
   67 65 09 04 FFFFFF81 01 FFFFFF81 02 02 04 4C 69 73 74 0A 02
   7F 0A 10 03 19 FFFFFF81 04 09 03 FFFFFF81 05 0A 02 04 43 68
   61 72 08 07 FFFFFF81 07 68 FFFFFFC0 00 FFFFFF81 08 01 01 66 10 05
   19 FFFFFF81 09 4A 6D 09 03 FFFFFF81 0A 0A 02 09 46 75 6E 63
   74 69 6F 6E 31 08 07 FFFFFF81 0C 00 FFFFFF84 04 FFFFFF81 0D 01 05
   6C 69 66 74 32 15 04 FFFFFF81 0E FFFFFF81 11 14 04 FFFFFF81 0F FFFFFF81
   17 14 04 FFFFFF81 10 FFFFFF81 12 10 03 6E FFFFFF81 11 04 09 70 FFFFFF81
   0B FFFFFF84 FFFFFF80 FFFFFF80 FFFFFFC2 00 71 08 08 FFFFFF81 13 FFFFFF81 0B FFFFFFC0 00 FFFFFF81
   14 01 01 70 10 06 23 FFFFFF81 15 FFFFFF81 03 77 09 03 FFFFFF81 16
   26 02 06 24 74 69 6C 64 65 08 08 FFFFFF81 07 FFFFFF81 0B FFFFFFC0
   00 FFFFFF81 18 10 06 19 FFFFFF81 09 4A FFFFFF81 10 
  InnerClass: 
   public abstract Token=class scala/util/parsing/combinator/token/Tokens$Token of class scala/util/parsing/combinator/token/Tokens
   public $tilde=class scala/util/parsing/combinator/Parsers$$tilde of class scala/util/parsing/combinator/Parsers
   public abstract Parser=class scala/util/parsing/combinator/Parsers$Parser of class scala/util/parsing/combinator/Parsers
   public Keyword=class scala/util/parsing/combinator/token/StdTokens$Keyword of class scala/util/parsing/combinator/token/StdTokens
   public Identifier=class scala/util/parsing/combinator/token/StdTokens$Identifier of class scala/util/parsing/combinator/token/StdTokens
   public abstract $less$colon$less=class scala/Predef$$less$colon$less of class scala/Predef
   public final $anonfun$token$9=class scala/util/parsing/combinator/lexical/StdLexical$$anonfun$token$9 of class scala/util/parsing/combinator/lexical/StdLexical
   public final $anonfun$token$8=class scala/util/parsing/combinator/lexical/StdLexical$$anonfun$token$8 of class scala/util/parsing/combinator/lexical/StdLexical
   public final $anonfun$token$7=class scala/util/parsing/combinator/lexical/StdLexical$$anonfun$token$7 of class scala/util/parsing/combinator/lexical/StdLexical
   public final $anonfun$token$6=class scala/util/parsing/combinator/lexical/StdLexical$$anonfun$token$6 of class scala/util/parsing/combinator/lexical/StdLexical
   public final $anonfun$token$5=class scala/util/parsing/combinator/lexical/StdLexical$$anonfun$token$5 of class scala/util/parsing/combinator/lexical/StdLexical
   public final $anonfun$token$4=class scala/util/parsing/combinator/lexical/StdLexical$$anonfun$token$4 of class scala/util/parsing/combinator/lexical/StdLexical
   public final $anonfun$token$3=class scala/util/parsing/combinator/lexical/StdLexical$$anonfun$token$3 of class scala/util/parsing/combinator/lexical/StdLexical
   public final $anonfun$token$2=class scala/util/parsing/combinator/lexical/StdLexical$$anonfun$token$2 of class scala/util/parsing/combinator/lexical/StdLexical
   public final $anonfun$token$1=class scala/util/parsing/combinator/lexical/StdLexical$$anonfun$token$1 of class scala/util/parsing/combinator/lexical/StdLexical
   public final $anonfun$_delim$2=class scala/util/parsing/combinator/lexical/StdLexical$$anonfun$_delim$2 of class scala/util/parsing/combinator/lexical/StdLexical
   public final $anonfun$_delim$1=class scala/util/parsing/combinator/lexical/StdLexical$$anonfun$_delim$1 of class scala/util/parsing/combinator/lexical/StdLexical
   public final $anonfun$token$10=class scala/util/parsing/combinator/lexical/StdLexical$$anonfun$token$10 of class scala/util/parsing/combinator/lexical/StdLexical
   public final $anonfun$comment$3=class scala/util/parsing/combinator/lexical/StdLexical$$anonfun$comment$3 of class scala/util/parsing/combinator/lexical/StdLexical
   public final $anonfun$comment$2=class scala/util/parsing/combinator/lexical/StdLexical$$anonfun$comment$2 of class scala/util/parsing/combinator/lexical/StdLexical
   public final $anonfun$comment$1=class scala/util/parsing/combinator/lexical/StdLexical$$anonfun$comment$1 of class scala/util/parsing/combinator/lexical/StdLexical
   public final $anonfun$identChar$1=class scala/util/parsing/combinator/lexical/StdLexical$$anonfun$identChar$1 of class scala/util/parsing/combinator/lexical/StdLexical
   public final $anonfun$whitespace$1=class scala/util/parsing/combinator/lexical/StdLexical$$anonfun$whitespace$1 of class scala/util/parsing/combinator/lexical/StdLexical
   public final $anonfun$parseDelim$1$1=class scala/util/parsing/combinator/lexical/StdLexical$$anonfun$parseDelim$1$1 of class scala/util/parsing/combinator/lexical/StdLexical
  minor version: 0
  major version: 49
  Constant pool:
Asciz	SourceFile;
Asciz	StdLexical.scala;
Asciz	Identifier$module;
Asciz	Lscala/util/parsing/combinator/token/StdTokens$Identifier$;;
Asciz	StringLit$module;
Asciz	Lscala/util/parsing/combinator/token/StdTokens$StringLit$;;
Asciz	NumericLit$module;
Asciz	Lscala/util/parsing/combinator/token/StdTokens$NumericLit$;;
Asciz	Keyword$module;
Asciz	Lscala/util/parsing/combinator/token/StdTokens$Keyword$;;
Asciz	bitmap$0;
Asciz	I;
Asciz	_delim;
Asciz	Lscala/util/parsing/combinator/Parsers$Parser;;
Asciz	Lscala/util/parsing/combinator/Parsers$Parser<Lscala/util/parsing/combinator/token/Tokens$Token;>;;
Asciz	Signature;
Asciz	delimiters;
Asciz	Lscala/collection/mutable/HashSet;;
Asciz	Lscala/collection/mutable/HashSet<Ljava/lang/String;>;;
Asciz	reserved;
Asciz	Keyword;
Asciz	()Lscala/util/parsing/combinator/token/StdTokens$Keyword$;;
Asciz	Code;
Asciz	LineNumberTable;
Asciz	scala/util/parsing/combinator/lexical/StdLexical;
class	scala/util/parsing/combinator/lexical/StdLexical
NameAndType	Keyword$module:Lscala/util/parsing/combinator/token/StdTokens$Keyword$;
Field	scala/util/parsing/combinator/lexical/StdLexical.Keyword$module:Lscala/util/parsing/combinator/token/StdTokens$Keyword$;
Asciz	scala/util/parsing/combinator/token/StdTokens$Keyword$;
class	scala/util/parsing/combinator/token/StdTokens$Keyword$
Asciz	<init>;
Asciz	(Lscala/util/parsing/combinator/token/StdTokens;)V;
NameAndType	"<init>":(Lscala/util/parsing/combinator/token/StdTokens;)V
Method	scala/util/parsing/combinator/token/StdTokens$Keyword$."<init>":(Lscala/util/parsing/combinator/token/StdTokens;)V
Asciz	NumericLit;
Asciz	()Lscala/util/parsing/combinator/token/StdTokens$NumericLit$;;
NameAndType	NumericLit$module:Lscala/util/parsing/combinator/token/StdTokens$NumericLit$;
Field	scala/util/parsing/combinator/lexical/StdLexical.NumericLit$module:Lscala/util/parsing/combinator/token/StdTokens$NumericLit$;
Asciz	scala/util/parsing/combinator/token/StdTokens$NumericLit$;
class	scala/util/parsing/combinator/token/StdTokens$NumericLit$
Method	scala/util/parsing/combinator/token/StdTokens$NumericLit$."<init>":(Lscala/util/parsing/combinator/token/StdTokens;)V
Asciz	StringLit;
Asciz	()Lscala/util/parsing/combinator/token/StdTokens$StringLit$;;
NameAndType	StringLit$module:Lscala/util/parsing/combinator/token/StdTokens$StringLit$;
Field	scala/util/parsing/combinator/lexical/StdLexical.StringLit$module:Lscala/util/parsing/combinator/token/StdTokens$StringLit$;
Asciz	scala/util/parsing/combinator/token/StdTokens$StringLit$;
class	scala/util/parsing/combinator/token/StdTokens$StringLit$
Method	scala/util/parsing/combinator/token/StdTokens$StringLit$."<init>":(Lscala/util/parsing/combinator/token/StdTokens;)V
Asciz	Identifier;
Asciz	()Lscala/util/parsing/combinator/token/StdTokens$Identifier$;;
NameAndType	Identifier$module:Lscala/util/parsing/combinator/token/StdTokens$Identifier$;
Field	scala/util/parsing/combinator/lexical/StdLexical.Identifier$module:Lscala/util/parsing/combinator/token/StdTokens$Identifier$;
Asciz	scala/util/parsing/combinator/token/StdTokens$Identifier$;
class	scala/util/parsing/combinator/token/StdTokens$Identifier$
Method	scala/util/parsing/combinator/token/StdTokens$Identifier$."<init>":(Lscala/util/parsing/combinator/token/StdTokens;)V
Asciz	token;
Asciz	()Lscala/util/parsing/combinator/Parsers$Parser;;
Asciz	identChar;
NameAndType	identChar:()Lscala/util/parsing/combinator/Parsers$Parser;
Method	scala/util/parsing/combinator/lexical/StdLexical.identChar:()Lscala/util/parsing/combinator/Parsers$Parser;
Asciz	scala/util/parsing/combinator/lexical/StdLexical$$anonfun$token$1;
class	scala/util/parsing/combinator/lexical/StdLexical$$anonfun$token$1
Asciz	(Lscala/util/parsing/combinator/lexical/StdLexical;)V;
NameAndType	"<init>":(Lscala/util/parsing/combinator/lexical/StdLexical;)V
Method	scala/util/parsing/combinator/lexical/StdLexical$$anonfun$token$1."<init>":(Lscala/util/parsing/combinator/lexical/StdLexical;)V
Asciz	scala/util/parsing/combinator/Parsers$Parser;
class	scala/util/parsing/combinator/Parsers$Parser
Asciz	$tilde;
Asciz	(Lscala/Function0;)Lscala/util/parsing/combinator/Parsers$Parser;;
NameAndType	$tilde:(Lscala/Function0;)Lscala/util/parsing/combinator/Parsers$Parser;
Method	scala/util/parsing/combinator/Parsers$Parser.$tilde:(Lscala/Function0;)Lscala/util/parsing/combinator/Parsers$Parser;
Asciz	scala/util/parsing/combinator/lexical/StdLexical$$anonfun$token$2;
class	scala/util/parsing/combinator/lexical/StdLexical$$anonfun$token$2
Method	scala/util/parsing/combinator/lexical/StdLexical$$anonfun$token$2."<init>":(Lscala/util/parsing/combinator/lexical/StdLexical;)V
Asciz	$up$up;
Asciz	(Lscala/Function1;)Lscala/util/parsing/combinator/Parsers$Parser;;
NameAndType	$up$up:(Lscala/Function1;)Lscala/util/parsing/combinator/Parsers$Parser;
Method	scala/util/parsing/combinator/Parsers$Parser.$up$up:(Lscala/Function1;)Lscala/util/parsing/combinator/Parsers$Parser;
Asciz	scala/util/parsing/combinator/lexical/StdLexical$$anonfun$token$3;
class	scala/util/parsing/combinator/lexical/StdLexical$$anonfun$token$3
Method	scala/util/parsing/combinator/lexical/StdLexical$$anonfun$token$3."<init>":(Lscala/util/parsing/combinator/lexical/StdLexical;)V
Asciz	$bar;
NameAndType	$bar:(Lscala/Function0;)Lscala/util/parsing/combinator/Parsers$Parser;
Method	scala/util/parsing/combinator/Parsers$Parser.$bar:(Lscala/Function0;)Lscala/util/parsing/combinator/Parsers$Parser;
Asciz	scala/util/parsing/combinator/lexical/StdLexical$$anonfun$token$4;
class	scala/util/parsing/combinator/lexical/StdLexical$$anonfun$token$4
Method	scala/util/parsing/combinator/lexical/StdLexical$$anonfun$token$4."<init>":(Lscala/util/parsing/combinator/lexical/StdLexical;)V
Asciz	scala/util/parsing/combinator/lexical/StdLexical$$anonfun$token$5;
class	scala/util/parsing/combinator/lexical/StdLexical$$anonfun$token$5
Method	scala/util/parsing/combinator/lexical/StdLexical$$anonfun$token$5."<init>":(Lscala/util/parsing/combinator/lexical/StdLexical;)V
Asciz	scala/util/parsing/combinator/lexical/StdLexical$$anonfun$token$6;
class	scala/util/parsing/combinator/lexical/StdLexical$$anonfun$token$6
Method	scala/util/parsing/combinator/lexical/StdLexical$$anonfun$token$6."<init>":(Lscala/util/parsing/combinator/lexical/StdLexical;)V
Asciz	scala/util/parsing/combinator/lexical/StdLexical$$anonfun$token$7;
class	scala/util/parsing/combinator/lexical/StdLexical$$anonfun$token$7
Method	scala/util/parsing/combinator/lexical/StdLexical$$anonfun$token$7."<init>":(Lscala/util/parsing/combinator/lexical/StdLexical;)V
Asciz	scala/util/parsing/combinator/lexical/StdLexical$$anonfun$token$8;
class	scala/util/parsing/combinator/lexical/StdLexical$$anonfun$token$8
Method	scala/util/parsing/combinator/lexical/StdLexical$$anonfun$token$8."<init>":(Lscala/util/parsing/combinator/lexical/StdLexical;)V
Asciz	scala/util/parsing/combinator/lexical/StdLexical$$anonfun$token$9;
class	scala/util/parsing/combinator/lexical/StdLexical$$anonfun$token$9
Method	scala/util/parsing/combinator/lexical/StdLexical$$anonfun$token$9."<init>":(Lscala/util/parsing/combinator/lexical/StdLexical;)V
Asciz	scala/util/parsing/combinator/lexical/StdLexical$$anonfun$token$10;
class	scala/util/parsing/combinator/lexical/StdLexical$$anonfun$token$10
Method	scala/util/parsing/combinator/lexical/StdLexical$$anonfun$token$10."<init>":(Lscala/util/parsing/combinator/lexical/StdLexical;)V
Asciz	()Lscala/util/parsing/combinator/Parsers$Parser<Lscala/util/parsing/combinator/token/Tokens$Token;>;;
Asciz	letter;
NameAndType	letter:()Lscala/util/parsing/combinator/Parsers$Parser;
Method	scala/util/parsing/combinator/lexical/StdLexical.letter:()Lscala/util/parsing/combinator/Parsers$Parser;
Asciz	scala/util/parsing/combinator/lexical/StdLexical$$anonfun$identChar$1;
class	scala/util/parsing/combinator/lexical/StdLexical$$anonfun$identChar$1
Method	scala/util/parsing/combinator/lexical/StdLexical$$anonfun$identChar$1."<init>":(Lscala/util/parsing/combinator/lexical/StdLexical;)V
Asciz	()Lscala/util/parsing/combinator/Parsers$Parser<Ljava/lang/Character;>;;
Asciz	whitespace;
Asciz	scala/util/parsing/combinator/lexical/StdLexical$$anonfun$whitespace$1;
class	scala/util/parsing/combinator/lexical/StdLexical$$anonfun$whitespace$1
Method	scala/util/parsing/combinator/lexical/StdLexical$$anonfun$whitespace$1."<init>":(Lscala/util/parsing/combinator/lexical/StdLexical;)V
Asciz	scala/util/parsing/combinator/Parsers;
class	scala/util/parsing/combinator/Parsers
Asciz	rep;
NameAndType	rep:(Lscala/Function0;)Lscala/util/parsing/combinator/Parsers$Parser;
InterfaceMethod	scala/util/parsing/combinator/Parsers.rep:(Lscala/Function0;)Lscala/util/parsing/combinator/Parsers$Parser;
Asciz	()Lscala/util/parsing/combinator/Parsers$Parser<Ljava/lang/Object;>;;
Asciz	comment;
int	42;
Asciz	scala/runtime/BoxesRunTime;
class	scala/runtime/BoxesRunTime
Asciz	boxToCharacter;
Asciz	(C)Ljava/lang/Character;;
NameAndType	boxToCharacter:(C)Ljava/lang/Character;
Method	scala/runtime/BoxesRunTime.boxToCharacter:(C)Ljava/lang/Character;
Asciz	accept;
Asciz	(Ljava/lang/Object;)Lscala/util/parsing/combinator/Parsers$Parser;;
NameAndType	accept:(Ljava/lang/Object;)Lscala/util/parsing/combinator/Parsers$Parser;
InterfaceMethod	scala/util/parsing/combinator/Parsers.accept:(Ljava/lang/Object;)Lscala/util/parsing/combinator/Parsers$Parser;
Asciz	scala/util/parsing/combinator/lexical/StdLexical$$anonfun$comment$1;
class	scala/util/parsing/combinator/lexical/StdLexical$$anonfun$comment$1
Method	scala/util/parsing/combinator/lexical/StdLexical$$anonfun$comment$1."<init>":(Lscala/util/parsing/combinator/lexical/StdLexical;)V
Asciz	scala/util/parsing/combinator/lexical/StdLexical$$anonfun$comment$2;
class	scala/util/parsing/combinator/lexical/StdLexical$$anonfun$comment$2
Method	scala/util/parsing/combinator/lexical/StdLexical$$anonfun$comment$2."<init>":(Lscala/util/parsing/combinator/lexical/StdLexical;)V
Asciz	scala/util/parsing/combinator/lexical/StdLexical$$anonfun$comment$3;
class	scala/util/parsing/combinator/lexical/StdLexical$$anonfun$comment$3
Method	scala/util/parsing/combinator/lexical/StdLexical$$anonfun$comment$3."<init>":(Lscala/util/parsing/combinator/lexical/StdLexical;)V
Asciz	()Lscala/collection/mutable/HashSet;;
NameAndType	reserved:Lscala/collection/mutable/HashSet;
Field	scala/util/parsing/combinator/lexical/StdLexical.reserved:Lscala/collection/mutable/HashSet;
Asciz	()Lscala/collection/mutable/HashSet<Ljava/lang/String;>;;
NameAndType	delimiters:Lscala/collection/mutable/HashSet;
Field	scala/util/parsing/combinator/lexical/StdLexical.delimiters:Lscala/collection/mutable/HashSet;
Asciz	processIdent;
Asciz	(Ljava/lang/String;)Lscala/util/parsing/combinator/token/Tokens$Token;;
NameAndType	reserved:()Lscala/collection/mutable/HashSet;
Method	scala/util/parsing/combinator/lexical/StdLexical.reserved:()Lscala/collection/mutable/HashSet;
Asciz	scala/collection/mutable/HashSet;
class	scala/collection/mutable/HashSet
Asciz	contains;
Asciz	(Ljava/lang/Object;)Z;
NameAndType	contains:(Ljava/lang/Object;)Z
Method	scala/collection/mutable/HashSet.contains:(Ljava/lang/Object;)Z
Asciz	scala/util/parsing/combinator/token/StdTokens$Keyword;
class	scala/util/parsing/combinator/token/StdTokens$Keyword
Asciz	(Lscala/util/parsing/combinator/token/StdTokens;Ljava/lang/String;)V;
NameAndType	"<init>":(Lscala/util/parsing/combinator/token/StdTokens;Ljava/lang/String;)V
Method	scala/util/parsing/combinator/token/StdTokens$Keyword."<init>":(Lscala/util/parsing/combinator/token/StdTokens;Ljava/lang/String;)V
Asciz	scala/util/parsing/combinator/token/StdTokens$Identifier;
class	scala/util/parsing/combinator/token/StdTokens$Identifier
Method	scala/util/parsing/combinator/token/StdTokens$Identifier."<init>":(Lscala/util/parsing/combinator/token/StdTokens;Ljava/lang/String;)V
Asciz	this;
Asciz	Lscala/util/parsing/combinator/lexical/StdLexical;;
Asciz	name;
Asciz	Ljava/lang/String;;
Asciz	LocalVariableTable;
NameAndType	bitmap$0:I
Field	scala/util/parsing/combinator/lexical/StdLexical.bitmap$0:I
NameAndType	delimiters:()Lscala/collection/mutable/HashSet;
Method	scala/util/parsing/combinator/lexical/StdLexical.delimiters:()Lscala/collection/mutable/HashSet;
Asciz	size;
Asciz	()I;
NameAndType	size:()I
Method	scala/collection/mutable/HashSet.size:()I
Asciz	java/lang/String;
class	java/lang/String
Asciz	scala/collection/TraversableLike;
class	scala/collection/TraversableLike
Asciz	copyToArray;
Asciz	(Ljava/lang/Object;I)V;
NameAndType	copyToArray:(Ljava/lang/Object;I)V
InterfaceMethod	scala/collection/TraversableLike.copyToArray:(Ljava/lang/Object;I)V
Asciz	scala/util/Sorting$;
class	scala/util/Sorting$
Asciz	MODULE$;
Asciz	Lscala/util/Sorting$;;
NameAndType	MODULE$:Lscala/util/Sorting$;
Field	scala/util/Sorting$.MODULE$:Lscala/util/Sorting$;
Asciz	scala/math/Ordering$String$;
class	scala/math/Ordering$String$
Asciz	Lscala/math/Ordering$String$;;
NameAndType	MODULE$:Lscala/math/Ordering$String$;
Field	scala/math/Ordering$String$.MODULE$:Lscala/math/Ordering$String$;
Asciz	quickSort;
Asciz	(Ljava/lang/Object;Lscala/math/Ordering;)V;
NameAndType	quickSort:(Ljava/lang/Object;Lscala/math/Ordering;)V
Method	scala/util/Sorting$.quickSort:(Ljava/lang/Object;Lscala/math/Ordering;)V
Asciz	scala/Predef$;
class	scala/Predef$
Asciz	Lscala/Predef$;;
NameAndType	MODULE$:Lscala/Predef$;
Field	scala/Predef$.MODULE$:Lscala/Predef$;
Asciz	[Ljava/lang/Object;;
class	"[Ljava/lang/Object;"
Asciz	refArrayOps;
Asciz	([Ljava/lang/Object;)Lscala/collection/mutable/ArrayOps;;
NameAndType	refArrayOps:([Ljava/lang/Object;)Lscala/collection/mutable/ArrayOps;
Method	scala/Predef$.refArrayOps:([Ljava/lang/Object;)Lscala/collection/mutable/ArrayOps;
Asciz	toList;
Asciz	()Lscala/collection/immutable/List;;
NameAndType	toList:()Lscala/collection/immutable/List;
InterfaceMethod	scala/collection/TraversableLike.toList:()Lscala/collection/immutable/List;
Asciz	scala/util/parsing/combinator/lexical/StdLexical$$anonfun$_delim$1;
class	scala/util/parsing/combinator/lexical/StdLexical$$anonfun$_delim$1
Method	scala/util/parsing/combinator/lexical/StdLexical$$anonfun$_delim$1."<init>":(Lscala/util/parsing/combinator/lexical/StdLexical;)V
Asciz	scala/collection/immutable/List$;
class	scala/collection/immutable/List$
Asciz	Lscala/collection/immutable/List$;;
NameAndType	MODULE$:Lscala/collection/immutable/List$;
Field	scala/collection/immutable/List$.MODULE$:Lscala/collection/immutable/List$;
Asciz	canBuildFrom;
Asciz	()Lscala/collection/generic/CanBuildFrom;;
NameAndType	canBuildFrom:()Lscala/collection/generic/CanBuildFrom;
Method	scala/collection/immutable/List$.canBuildFrom:()Lscala/collection/generic/CanBuildFrom;
Asciz	map;
Asciz	(Lscala/Function1;Lscala/collection/generic/CanBuildFrom;)Ljava/lang/Object;;
NameAndType	map:(Lscala/Function1;Lscala/collection/generic/CanBuildFrom;)Ljava/lang/Object;
InterfaceMethod	scala/collection/TraversableLike.map:(Lscala/Function1;Lscala/collection/generic/CanBuildFrom;)Ljava/lang/Object;
Asciz	scala/collection/LinearSeqLike;
class	scala/collection/LinearSeqLike
Asciz	no matching delimiter;
String	no matching delimiter
Asciz	failure;
Asciz	(Ljava/lang/String;)Lscala/util/parsing/combinator/Parsers$Parser;;
NameAndType	failure:(Ljava/lang/String;)Lscala/util/parsing/combinator/Parsers$Parser;
InterfaceMethod	scala/util/parsing/combinator/Parsers.failure:(Ljava/lang/String;)Lscala/util/parsing/combinator/Parsers$Parser;
Asciz	scala/util/parsing/combinator/lexical/StdLexical$$anonfun$_delim$2;
class	scala/util/parsing/combinator/lexical/StdLexical$$anonfun$_delim$2
Method	scala/util/parsing/combinator/lexical/StdLexical$$anonfun$_delim$2."<init>":(Lscala/util/parsing/combinator/lexical/StdLexical;)V
Asciz	foldRight;
Asciz	(Ljava/lang/Object;Lscala/Function2;)Ljava/lang/Object;;
NameAndType	foldRight:(Ljava/lang/Object;Lscala/Function2;)Ljava/lang/Object;
InterfaceMethod	scala/collection/LinearSeqLike.foldRight:(Ljava/lang/Object;Lscala/Function2;)Ljava/lang/Object;
NameAndType	_delim:Lscala/util/parsing/combinator/Parsers$Parser;
Field	scala/util/parsing/combinator/lexical/StdLexical._delim:Lscala/util/parsing/combinator/Parsers$Parser;
Asciz	scala/runtime/BoxedUnit;
class	scala/runtime/BoxedUnit
Asciz	UNIT;
Asciz	Lscala/runtime/BoxedUnit;;
NameAndType	UNIT:Lscala/runtime/BoxedUnit;
Field	scala/runtime/BoxedUnit.UNIT:Lscala/runtime/BoxedUnit;
Asciz	d;
Asciz	[Ljava/lang/String;;
Asciz	delim;
NameAndType	_delim:()Lscala/util/parsing/combinator/Parsers$Parser;
Method	scala/util/parsing/combinator/lexical/StdLexical._delim:()Lscala/util/parsing/combinator/Parsers$Parser;
Asciz	lift;
Asciz	(Lscala/Function1;Lscala/collection/immutable/List;)Ljava/lang/Object;;
Asciz	;
String	
Asciz	mkString;
Asciz	(Ljava/lang/String;Ljava/lang/String;Ljava/lang/String;)Ljava/lang/String;;
NameAndType	mkString:(Ljava/lang/String;Ljava/lang/String;Ljava/lang/String;)Ljava/lang/String;
InterfaceMethod	scala/collection/TraversableLike.mkString:(Ljava/lang/String;Ljava/lang/String;Ljava/lang/String;)Ljava/lang/String;
Asciz	scala/Function1;
class	scala/Function1
Asciz	apply;
Asciz	(Ljava/lang/Object;)Ljava/lang/Object;;
NameAndType	apply:(Ljava/lang/Object;)Ljava/lang/Object;
InterfaceMethod	scala/Function1.apply:(Ljava/lang/Object;)Ljava/lang/Object;
Asciz	f;
Asciz	Lscala/Function1;;
Asciz	xs;
Asciz	Lscala/collection/immutable/List;;
Asciz	<T:Ljava/lang/Object;>(Lscala/Function1<Ljava/lang/String;TT;>;Lscala/collection/immutable/List<Ljava/lang/Character;>;)TT;;
Asciz	lift2;
Asciz	(Lscala/Function1;Lscala/util/parsing/combinator/Parsers$$tilde;)Ljava/lang/Object;;
Asciz	scala/util/parsing/combinator/Parsers$$tilde;
class	scala/util/parsing/combinator/Parsers$$tilde
Asciz	_1;
Asciz	()Ljava/lang/Object;;
NameAndType	_1:()Ljava/lang/Object;
Method	scala/util/parsing/combinator/Parsers$$tilde._1:()Ljava/lang/Object;
Asciz	unboxToChar;
Asciz	(Ljava/lang/Object;)C;
NameAndType	unboxToChar:(Ljava/lang/Object;)C
Method	scala/runtime/BoxesRunTime.unboxToChar:(Ljava/lang/Object;)C
Asciz	_2;
NameAndType	_2:()Ljava/lang/Object;
Method	scala/util/parsing/combinator/Parsers$$tilde._2:()Ljava/lang/Object;
Asciz	scala/collection/immutable/List;
class	scala/collection/immutable/List
Asciz	$colon$colon;
Asciz	(Ljava/lang/Object;)Lscala/collection/immutable/List;;
NameAndType	$colon$colon:(Ljava/lang/Object;)Lscala/collection/immutable/List;
Method	scala/collection/immutable/List.$colon$colon:(Ljava/lang/Object;)Lscala/collection/immutable/List;
NameAndType	lift:(Lscala/Function1;Lscala/collection/immutable/List;)Ljava/lang/Object;
Method	scala/util/parsing/combinator/lexical/StdLexical.lift:(Lscala/Function1;Lscala/collection/immutable/List;)Ljava/lang/Object;
Asciz	p;
Asciz	Lscala/util/parsing/combinator/Parsers$$tilde;;
Asciz	<T:Ljava/lang/Object;>(Lscala/Function1<Ljava/lang/String;TT;>;Lscala/util/parsing/combinator/Parsers$$tilde<Ljava/lang/Character;Lscala/collection/immutable/List<Ljava/lang/Character;>;>;)TT;;
Asciz	parseDelim$1;
Asciz	augmentString;
Asciz	(Ljava/lang/String;)Lscala/collection/immutable/StringOps;;
NameAndType	augmentString:(Ljava/lang/String;)Lscala/collection/immutable/StringOps;
Method	scala/Predef$.augmentString:(Ljava/lang/String;)Lscala/collection/immutable/StringOps;
Asciz	conforms;
Asciz	()Lscala/Predef$$less$colon$less;;
NameAndType	conforms:()Lscala/Predef$$less$colon$less;
Method	scala/Predef$.conforms:()Lscala/Predef$$less$colon$less;
Asciz	(Ljava/lang/Object;Lscala/Function1;)Lscala/util/parsing/combinator/Parsers$Parser;;
NameAndType	accept:(Ljava/lang/Object;Lscala/Function1;)Lscala/util/parsing/combinator/Parsers$Parser;
InterfaceMethod	scala/util/parsing/combinator/Parsers.accept:(Ljava/lang/Object;Lscala/Function1;)Lscala/util/parsing/combinator/Parsers$Parser;
Asciz	scala/util/parsing/combinator/lexical/StdLexical$$anonfun$parseDelim$1$1;
class	scala/util/parsing/combinator/lexical/StdLexical$$anonfun$parseDelim$1$1
Asciz	(Lscala/util/parsing/combinator/lexical/StdLexical;Ljava/lang/String;)V;
NameAndType	"<init>":(Lscala/util/parsing/combinator/lexical/StdLexical;Ljava/lang/String;)V
Method	scala/util/parsing/combinator/lexical/StdLexical$$anonfun$parseDelim$1$1."<init>":(Lscala/util/parsing/combinator/lexical/StdLexical;Ljava/lang/String;)V
Asciz	s$1;
Asciz	()V;
Asciz	scala/util/parsing/combinator/lexical/Lexical;
class	scala/util/parsing/combinator/lexical/Lexical
NameAndType	"<init>":()V
Method	scala/util/parsing/combinator/lexical/Lexical."<init>":()V
Asciz	scala/util/parsing/combinator/token/StdTokens$class;
class	scala/util/parsing/combinator/token/StdTokens$class
Asciz	$init$;
NameAndType	$init$:(Lscala/util/parsing/combinator/token/StdTokens;)V
Method	scala/util/parsing/combinator/token/StdTokens$class.$init$:(Lscala/util/parsing/combinator/token/StdTokens;)V
Method	scala/collection/mutable/HashSet."<init>":()V
Asciz	ScalaSig;
Asciz	InnerClasses;
Asciz	scala/util/parsing/combinator/token/Tokens$Token;
class	scala/util/parsing/combinator/token/Tokens$Token
Asciz	scala/util/parsing/combinator/token/Tokens;
class	scala/util/parsing/combinator/token/Tokens
Asciz	Token;
Asciz	Parser;
Asciz	scala/util/parsing/combinator/token/StdTokens;
class	scala/util/parsing/combinator/token/StdTokens
Asciz	scala/Predef$$less$colon$less;
class	scala/Predef$$less$colon$less
Asciz	scala/Predef;
class	scala/Predef
Asciz	$less$colon$less;
Asciz	$anonfun$token$9;
Asciz	$anonfun$token$8;
Asciz	$anonfun$token$7;
Asciz	$anonfun$token$6;
Asciz	$anonfun$token$5;
Asciz	$anonfun$token$4;
Asciz	$anonfun$token$3;
Asciz	$anonfun$token$2;
Asciz	$anonfun$token$1;
Asciz	$anonfun$_delim$2;
Asciz	$anonfun$_delim$1;
Asciz	$anonfun$token$10;
Asciz	$anonfun$comment$3;
Asciz	$anonfun$comment$2;
Asciz	$anonfun$comment$1;
Asciz	$anonfun$identChar$1;
Asciz	$anonfun$whitespace$1;
Asciz	$anonfun$parseDelim$1$1;
Asciz	scala/ScalaObject;
class	scala/ScalaObject

{
private scala.util.parsing.combinator.token.StdTokens$Identifier$ Identifier$module;
  Signature: Lscala/util/parsing/combinator/token/StdTokens$Identifier$;

private scala.util.parsing.combinator.token.StdTokens$StringLit$ StringLit$module;
  Signature: Lscala/util/parsing/combinator/token/StdTokens$StringLit$;

private scala.util.parsing.combinator.token.StdTokens$NumericLit$ NumericLit$module;
  Signature: Lscala/util/parsing/combinator/token/StdTokens$NumericLit$;

private scala.util.parsing.combinator.token.StdTokens$Keyword$ Keyword$module;
  Signature: Lscala/util/parsing/combinator/token/StdTokens$Keyword$;

public volatile int bitmap$0;
  Signature: I

private scala.util.parsing.combinator.Parsers$Parser _delim;
  Signature: Lscala/util/parsing/combinator/Parsers$Parser;
  Signature: length = 0x2
   00 0F 

private final scala.collection.mutable.HashSet delimiters;
  Signature: Lscala/collection/mutable/HashSet;
  Signature: length = 0x2
   00 13 

private final scala.collection.mutable.HashSet reserved;
  Signature: Lscala/collection/mutable/HashSet;
  Signature: length = 0x2
   00 13 

public final scala.util.parsing.combinator.token.StdTokens$Keyword$ Keyword();
  Signature: ()Lscala/util/parsing/combinator/token/StdTokens$Keyword$;
  Code:
   Stack=4, Locals=1, Args_size=1
	aload_0
	getfield	Field Keyword$module:Lscala/util/parsing/combinator/token/StdTokens$Keyword$;
	ifnonnull	l1 // aload_0
	aload_0
	new	class scala/util/parsing/combinator/token/StdTokens$Keyword$
	dup
	aload_0
	invokespecial	Method scala/util/parsing/combinator/token/StdTokens$Keyword$."<init>":(Lscala/util/parsing/combinator/token/StdTokens;)V
	putfield	Field Keyword$module:Lscala/util/parsing/combinator/token/StdTokens$Keyword$;
l1	aload_0
	getfield	Field Keyword$module:Lscala/util/parsing/combinator/token/StdTokens$Keyword$;
	areturn
  Labels:
   	l1 = 19 // aload_0

public final scala.util.parsing.combinator.token.StdTokens$NumericLit$ NumericLit();
  Signature: ()Lscala/util/parsing/combinator/token/StdTokens$NumericLit$;
  Code:
   Stack=4, Locals=1, Args_size=1
	aload_0
	getfield	Field NumericLit$module:Lscala/util/parsing/combinator/token/StdTokens$NumericLit$;
	ifnonnull	l1 // aload_0
	aload_0
	new	class scala/util/parsing/combinator/token/StdTokens$NumericLit$
	dup
	aload_0
	invokespecial	Method scala/util/parsing/combinator/token/StdTokens$NumericLit$."<init>":(Lscala/util/parsing/combinator/token/StdTokens;)V
	putfield	Field NumericLit$module:Lscala/util/parsing/combinator/token/StdTokens$NumericLit$;
l1	aload_0
	getfield	Field NumericLit$module:Lscala/util/parsing/combinator/token/StdTokens$NumericLit$;
	areturn
  Labels:
   	l1 = 19 // aload_0

public final scala.util.parsing.combinator.token.StdTokens$StringLit$ StringLit();
  Signature: ()Lscala/util/parsing/combinator/token/StdTokens$StringLit$;
  Code:
   Stack=4, Locals=1, Args_size=1
	aload_0
	getfield	Field StringLit$module:Lscala/util/parsing/combinator/token/StdTokens$StringLit$;
	ifnonnull	l1 // aload_0
	aload_0
	new	class scala/util/parsing/combinator/token/StdTokens$StringLit$
	dup
	aload_0
	invokespecial	Method scala/util/parsing/combinator/token/StdTokens$StringLit$."<init>":(Lscala/util/parsing/combinator/token/StdTokens;)V
	putfield	Field StringLit$module:Lscala/util/parsing/combinator/token/StdTokens$StringLit$;
l1	aload_0
	getfield	Field StringLit$module:Lscala/util/parsing/combinator/token/StdTokens$StringLit$;
	areturn
  Labels:
   	l1 = 19 // aload_0

public final scala.util.parsing.combinator.token.StdTokens$Identifier$ Identifier();
  Signature: ()Lscala/util/parsing/combinator/token/StdTokens$Identifier$;
  Code:
   Stack=4, Locals=1, Args_size=1
	aload_0
	getfield	Field Identifier$module:Lscala/util/parsing/combinator/token/StdTokens$Identifier$;
	ifnonnull	l1 // aload_0
	aload_0
	new	class scala/util/parsing/combinator/token/StdTokens$Identifier$
	dup
	aload_0
	invokespecial	Method scala/util/parsing/combinator/token/StdTokens$Identifier$."<init>":(Lscala/util/parsing/combinator/token/StdTokens;)V
	putfield	Field Identifier$module:Lscala/util/parsing/combinator/token/StdTokens$Identifier$;
l1	aload_0
	getfield	Field Identifier$module:Lscala/util/parsing/combinator/token/StdTokens$Identifier$;
	areturn
  Labels:
   	l1 = 19 // aload_0

public scala.util.parsing.combinator.Parsers$Parser token();
  Signature: ()Lscala/util/parsing/combinator/Parsers$Parser;
  Code:
   Stack=4, Locals=1, Args_size=1
	aload_0
	invokevirtual	Method identChar:()Lscala/util/parsing/combinator/Parsers$Parser;
	new	class scala/util/parsing/combinator/lexical/StdLexical$$anonfun$token$1
	dup
	aload_0
	invokespecial	Method scala/util/parsing/combinator/lexical/StdLexical$$anonfun$token$1."<init>":(Lscala/util/parsing/combinator/lexical/StdLexical;)V
	invokevirtual	Method scala/util/parsing/combinator/Parsers$Parser.$tilde:(Lscala/Function0;)Lscala/util/parsing/combinator/Parsers$Parser;
	new	class scala/util/parsing/combinator/lexical/StdLexical$$anonfun$token$2
	dup
	aload_0
	invokespecial	Method scala/util/parsing/combinator/lexical/StdLexical$$anonfun$token$2."<init>":(Lscala/util/parsing/combinator/lexical/StdLexical;)V
	invokevirtual	Method scala/util/parsing/combinator/Parsers$Parser.$up$up:(Lscala/Function1;)Lscala/util/parsing/combinator/Parsers$Parser;
	new	class scala/util/parsing/combinator/lexical/StdLexical$$anonfun$token$3
	dup
	aload_0
	invokespecial	Method scala/util/parsing/combinator/lexical/StdLexical$$anonfun$token$3."<init>":(Lscala/util/parsing/combinator/lexical/StdLexical;)V
	invokevirtual	Method scala/util/parsing/combinator/Parsers$Parser.$bar:(Lscala/Function0;)Lscala/util/parsing/combinator/Parsers$Parser;
	new	class scala/util/parsing/combinator/lexical/StdLexical$$anonfun$token$4
	dup
	aload_0
	invokespecial	Method scala/util/parsing/combinator/lexical/StdLexical$$anonfun$token$4."<init>":(Lscala/util/parsing/combinator/lexical/StdLexical;)V
	invokevirtual	Method scala/util/parsing/combinator/Parsers$Parser.$bar:(Lscala/Function0;)Lscala/util/parsing/combinator/Parsers$Parser;
	new	class scala/util/parsing/combinator/lexical/StdLexical$$anonfun$token$5
	dup
	aload_0
	invokespecial	Method scala/util/parsing/combinator/lexical/StdLexical$$anonfun$token$5."<init>":(Lscala/util/parsing/combinator/lexical/StdLexical;)V
	invokevirtual	Method scala/util/parsing/combinator/Parsers$Parser.$bar:(Lscala/Function0;)Lscala/util/parsing/combinator/Parsers$Parser;
	new	class scala/util/parsing/combinator/lexical/StdLexical$$anonfun$token$6
	dup
	aload_0
	invokespecial	Method scala/util/parsing/combinator/lexical/StdLexical$$anonfun$token$6."<init>":(Lscala/util/parsing/combinator/lexical/StdLexical;)V
	invokevirtual	Method scala/util/parsing/combinator/Parsers$Parser.$bar:(Lscala/Function0;)Lscala/util/parsing/combinator/Parsers$Parser;
	new	class scala/util/parsing/combinator/lexical/StdLexical$$anonfun$token$7
	dup
	aload_0
	invokespecial	Method scala/util/parsing/combinator/lexical/StdLexical$$anonfun$token$7."<init>":(Lscala/util/parsing/combinator/lexical/StdLexical;)V
	invokevirtual	Method scala/util/parsing/combinator/Parsers$Parser.$bar:(Lscala/Function0;)Lscala/util/parsing/combinator/Parsers$Parser;
	new	class scala/util/parsing/combinator/lexical/StdLexical$$anonfun$token$8
	dup
	aload_0
	invokespecial	Method scala/util/parsing/combinator/lexical/StdLexical$$anonfun$token$8."<init>":(Lscala/util/parsing/combinator/lexical/StdLexical;)V
	invokevirtual	Method scala/util/parsing/combinator/Parsers$Parser.$bar:(Lscala/Function0;)Lscala/util/parsing/combinator/Parsers$Parser;
	new	class scala/util/parsing/combinator/lexical/StdLexical$$anonfun$token$9
	dup
	aload_0
	invokespecial	Method scala/util/parsing/combinator/lexical/StdLexical$$anonfun$token$9."<init>":(Lscala/util/parsing/combinator/lexical/StdLexical;)V
	invokevirtual	Method scala/util/parsing/combinator/Parsers$Parser.$bar:(Lscala/Function0;)Lscala/util/parsing/combinator/Parsers$Parser;
	new	class scala/util/parsing/combinator/lexical/StdLexical$$anonfun$token$10
	dup
	aload_0
	invokespecial	Method scala/util/parsing/combinator/lexical/StdLexical$$anonfun$token$10."<init>":(Lscala/util/parsing/combinator/lexical/StdLexical;)V
	invokevirtual	Method scala/util/parsing/combinator/Parsers$Parser.$bar:(Lscala/Function0;)Lscala/util/parsing/combinator/Parsers$Parser;
	areturn
  Labels:
  Signature: length = 0x2
   00 6A 

public scala.util.parsing.combinator.Parsers$Parser identChar();
  Signature: ()Lscala/util/parsing/combinator/Parsers$Parser;
  Code:
   Stack=4, Locals=1, Args_size=1
	aload_0
	invokevirtual	Method letter:()Lscala/util/parsing/combinator/Parsers$Parser;
	new	class scala/util/parsing/combinator/lexical/StdLexical$$anonfun$identChar$1
	dup
	aload_0
	invokespecial	Method scala/util/parsing/combinator/lexical/StdLexical$$anonfun$identChar$1."<init>":(Lscala/util/parsing/combinator/lexical/StdLexical;)V
	invokevirtual	Method scala/util/parsing/combinator/Parsers$Parser.$bar:(Lscala/Function0;)Lscala/util/parsing/combinator/Parsers$Parser;
	areturn
  Labels:
  Signature: length = 0x2
   00 71 

public scala.util.parsing.combinator.Parsers$Parser whitespace();
  Signature: ()Lscala/util/parsing/combinator/Parsers$Parser;
  Code:
   Stack=4, Locals=1, Args_size=1
	aload_0
	new	class scala/util/parsing/combinator/lexical/StdLexical$$anonfun$whitespace$1
	dup
	aload_0
	invokespecial	Method scala/util/parsing/combinator/lexical/StdLexical$$anonfun$whitespace$1."<init>":(Lscala/util/parsing/combinator/lexical/StdLexical;)V
	invokeinterface	InterfaceMethod scala/util/parsing/combinator/Parsers.rep:(Lscala/Function0;)Lscala/util/parsing/combinator/Parsers$Parser;
	areturn
  Labels:
  Signature: length = 0x2
   00 7B 

public scala.util.parsing.combinator.Parsers$Parser comment();
  Signature: ()Lscala/util/parsing/combinator/Parsers$Parser;
  Code:
   Stack=4, Locals=1, Args_size=1
	aload_0
	ldc	int 42
	invokestatic	Method scala/runtime/BoxesRunTime.boxToCharacter:(C)Ljava/lang/Character;
	invokeinterface	InterfaceMethod scala/util/parsing/combinator/Parsers.accept:(Ljava/lang/Object;)Lscala/util/parsing/combinator/Parsers$Parser;
	new	class scala/util/parsing/combinator/lexical/StdLexical$$anonfun$comment$1
	dup
	aload_0
	invokespecial	Method scala/util/parsing/combinator/lexical/StdLexical$$anonfun$comment$1."<init>":(Lscala/util/parsing/combinator/lexical/StdLexical;)V
	invokevirtual	Method scala/util/parsing/combinator/Parsers$Parser.$tilde:(Lscala/Function0;)Lscala/util/parsing/combinator/Parsers$Parser;
	new	class scala/util/parsing/combinator/lexical/StdLexical$$anonfun$comment$2
	dup
	aload_0
	invokespecial	Method scala/util/parsing/combinator/lexical/StdLexical$$anonfun$comment$2."<init>":(Lscala/util/parsing/combinator/lexical/StdLexical;)V
	invokevirtual	Method scala/util/parsing/combinator/Parsers$Parser.$up$up:(Lscala/Function1;)Lscala/util/parsing/combinator/Parsers$Parser;
	new	class scala/util/parsing/combinator/lexical/StdLexical$$anonfun$comment$3
	dup
	aload_0
	invokespecial	Method scala/util/parsing/combinator/lexical/StdLexical$$anonfun$comment$3."<init>":(Lscala/util/parsing/combinator/lexical/StdLexical;)V
	invokevirtual	Method scala/util/parsing/combinator/Parsers$Parser.$bar:(Lscala/Function0;)Lscala/util/parsing/combinator/Parsers$Parser;
	areturn
  Labels:
  Signature: length = 0x2
   00 7B 

public scala.collection.mutable.HashSet reserved();
  Signature: ()Lscala/collection/mutable/HashSet;
  Code:
   Stack=1, Locals=1, Args_size=1
	aload_0
	getfield	Field reserved:Lscala/collection/mutable/HashSet;
	areturn
  Labels:
  Signature: length = 0x2
   00 FFFFFF94 

public scala.collection.mutable.HashSet delimiters();
  Signature: ()Lscala/collection/mutable/HashSet;
  Code:
   Stack=1, Locals=1, Args_size=1
	aload_0
	getfield	Field delimiters:Lscala/collection/mutable/HashSet;
	areturn
  Labels:
  Signature: length = 0x2
   00 FFFFFF94 

public scala.util.parsing.combinator.token.Tokens$Token processIdent(java.lang.String);
  Signature: (Ljava/lang/String;)Lscala/util/parsing/combinator/token/Tokens$Token;
  Code:
   Stack=4, Locals=2, Args_size=2
	aload_0
	invokevirtual	Method reserved:()Lscala/collection/mutable/HashSet;
	aload_1
	invokevirtual	Method scala/collection/mutable/HashSet.contains:(Ljava/lang/Object;)Z
	ifeq	l1 // new
	new	class scala/util/parsing/combinator/token/StdTokens$Keyword
	dup
	aload_0
	aload_1
	invokespecial	Method scala/util/parsing/combinator/token/StdTokens$Keyword."<init>":(Lscala/util/parsing/combinator/token/StdTokens;Ljava/lang/String;)V
	goto	l2 // areturn
l1	new	class scala/util/parsing/combinator/token/StdTokens$Identifier
	dup
	aload_0
	aload_1
	invokespecial	Method scala/util/parsing/combinator/token/StdTokens$Identifier."<init>":(Lscala/util/parsing/combinator/token/StdTokens;Ljava/lang/String;)V
l2	areturn
  Labels:
   	l1 = 23 // new
   	l2 = 32 // areturn
  LocalVariableTable: 
   Start  Length  Slot  Name   Signature
   0      33      0    this       Lscala/util/parsing/combinator/lexical/StdLexical;
   0      33      1    name       Ljava/lang/String;


private scala.util.parsing.combinator.Parsers$Parser _delim();
  Signature: ()Lscala/util/parsing/combinator/Parsers$Parser;
  Code:
   Stack=6, Locals=3, Args_size=1
	aload_0
	getfield	Field bitmap$0:I
	iconst_1
	iand
	iconst_0
	if_icmpne	l1 // aload_0
	aload_0
	dup
	astore_1
	monitorenter
	aload_0
	getfield	Field bitmap$0:I
	iconst_1
	iand
	iconst_0
	if_icmpne	l2 // getstatic
	aload_0
	aload_0
	invokevirtual	Method delimiters:()Lscala/collection/mutable/HashSet;
	invokevirtual	Method scala/collection/mutable/HashSet.size:()I
	anewarray	class java/lang/String
	astore_2
	aload_0
	invokevirtual	Method delimiters:()Lscala/collection/mutable/HashSet;
	aload_2
	iconst_0
	invokeinterface	InterfaceMethod scala/collection/TraversableLike.copyToArray:(Ljava/lang/Object;I)V
	getstatic	Field scala/util/Sorting$.MODULE$:Lscala/util/Sorting$;
	aload_2
	getstatic	Field scala/math/Ordering$String$.MODULE$:Lscala/math/Ordering$String$;
	invokevirtual	Method scala/util/Sorting$.quickSort:(Ljava/lang/Object;Lscala/math/Ordering;)V
	getstatic	Field scala/Predef$.MODULE$:Lscala/Predef$;
	aload_2
	checkcast	class "[Ljava/lang/Object;"
	invokevirtual	Method scala/Predef$.refArrayOps:([Ljava/lang/Object;)Lscala/collection/mutable/ArrayOps;
	invokeinterface	InterfaceMethod scala/collection/TraversableLike.toList:()Lscala/collection/immutable/List;
	new	class scala/util/parsing/combinator/lexical/StdLexical$$anonfun$_delim$1
	dup
	aload_0
	invokespecial	Method scala/util/parsing/combinator/lexical/StdLexical$$anonfun$_delim$1."<init>":(Lscala/util/parsing/combinator/lexical/StdLexical;)V
	getstatic	Field scala/collection/immutable/List$.MODULE$:Lscala/collection/immutable/List$;
	invokevirtual	Method scala/collection/immutable/List$.canBuildFrom:()Lscala/collection/generic/CanBuildFrom;
	invokeinterface	InterfaceMethod scala/collection/TraversableLike.map:(Lscala/Function1;Lscala/collection/generic/CanBuildFrom;)Ljava/lang/Object;
	checkcast	class scala/collection/LinearSeqLike
	aload_0
	ldc	String no matching delimiter
	invokeinterface	InterfaceMethod scala/util/parsing/combinator/Parsers.failure:(Ljava/lang/String;)Lscala/util/parsing/combinator/Parsers$Parser;
	new	class scala/util/parsing/combinator/lexical/StdLexical$$anonfun$_delim$2
	dup
	aload_0
	invokespecial	Method scala/util/parsing/combinator/lexical/StdLexical$$anonfun$_delim$2."<init>":(Lscala/util/parsing/combinator/lexical/StdLexical;)V
	invokeinterface	InterfaceMethod scala/collection/LinearSeqLike.foldRight:(Ljava/lang/Object;Lscala/Function2;)Ljava/lang/Object;
	checkcast	class scala/util/parsing/combinator/Parsers$Parser
	putfield	Field _delim:Lscala/util/parsing/combinator/Parsers$Parser;
	aload_0
	aload_0
	getfield	Field bitmap$0:I
	iconst_1
	ior
	putfield	Field bitmap$0:I
l2	getstatic	Field scala/runtime/BoxedUnit.UNIT:Lscala/runtime/BoxedUnit;
	pop
	aload_1
	monitorexit
l1	aload_0
	getfield	Field _delim:Lscala/util/parsing/combinator/Parsers$Parser;
	areturn
	aload_1
	monitorexit
	athrow
  Labels:
   	l2 = 131 // getstatic
   	l1 = 137 // aload_0
  Exception table:
   from   to  target type
    14   137   142   any
  LocalVariableTable: 
   Start  Length  Slot  Name   Signature
   0      145      0    this       Lscala/util/parsing/combinator/lexical/StdLexical;
   36      82      2    d       [Ljava/lang/String;

  Signature: length = 0x2
   00 6A 

public scala.util.parsing.combinator.Parsers$Parser delim();
  Signature: ()Lscala/util/parsing/combinator/Parsers$Parser;
  Code:
   Stack=1, Locals=1, Args_size=1
	aload_0
	invokespecial	Method _delim:()Lscala/util/parsing/combinator/Parsers$Parser;
	areturn
  Labels:
  Signature: length = 0x2
   00 6A 

private java.lang.Object lift(scala.Function1, scala.collection.immutable.List);
  Signature: (Lscala/Function1;Lscala/collection/immutable/List;)Ljava/lang/Object;
  Code:
   Stack=5, Locals=3, Args_size=3
	aload_1
	aload_2
	ldc_w	String 
	ldc_w	String 
	ldc_w	String 
	invokeinterface	InterfaceMethod scala/collection/TraversableLike.mkString:(Ljava/lang/String;Ljava/lang/String;Ljava/lang/String;)Ljava/lang/String;
	invokeinterface	InterfaceMethod scala/Function1.apply:(Ljava/lang/Object;)Ljava/lang/Object;
	areturn
  Labels:
  LocalVariableTable: 
   Start  Length  Slot  Name   Signature
   0      22      0    this       Lscala/util/parsing/combinator/lexical/StdLexical;
   0      22      1    f       Lscala/Function1;
   0      22      2    xs       Lscala/collection/immutable/List;

  Signature: length = 0x2
   01 1A 

private java.lang.Object lift2(scala.Function1, scala.util.parsing.combinator.Parsers$$tilde);
  Signature: (Lscala/Function1;Lscala/util/parsing/combinator/Parsers$$tilde;)Ljava/lang/Object;
  Code:
   Stack=4, Locals=4, Args_size=3
	aload_0
	aload_1
	aload_2
	invokevirtual	Method scala/util/parsing/combinator/Parsers$$tilde._1:()Ljava/lang/Object;
	invokestatic	Method scala/runtime/BoxesRunTime.unboxToChar:(Ljava/lang/Object;)C
	istore_3
	aload_2
	invokevirtual	Method scala/util/parsing/combinator/Parsers$$tilde._2:()Ljava/lang/Object;
	checkcast	class scala/collection/immutable/List
	iload_3
	invokestatic	Method scala/runtime/BoxesRunTime.boxToCharacter:(C)Ljava/lang/Character;
	invokevirtual	Method scala/collection/immutable/List.$colon$colon:(Ljava/lang/Object;)Lscala/collection/immutable/List;
	invokespecial	Method lift:(Lscala/Function1;Lscala/collection/immutable/List;)Ljava/lang/Object;
	areturn
  Labels:
  LocalVariableTable: 
   Start  Length  Slot  Name   Signature
   0      28      0    this       Lscala/util/parsing/combinator/lexical/StdLexical;
   0      28      1    f       Lscala/Function1;
   0      28      2    p       Lscala/util/parsing/combinator/Parsers$$tilde;

  Signature: length = 0x2
   01 34 

public final scala.util.parsing.combinator.Parsers$Parser parseDelim$1(java.lang.String);
  Signature: (Ljava/lang/String;)Lscala/util/parsing/combinator/Parsers$Parser;
  Code:
   Stack=5, Locals=2, Args_size=2
	aload_0
	getstatic	Field scala/Predef$.MODULE$:Lscala/Predef$;
	aload_1
	invokevirtual	Method scala/Predef$.augmentString:(Ljava/lang/String;)Lscala/collection/immutable/StringOps;
	invokeinterface	InterfaceMethod scala/collection/TraversableLike.toList:()Lscala/collection/immutable/List;
	getstatic	Field scala/Predef$.MODULE$:Lscala/Predef$;
	invokevirtual	Method scala/Predef$.conforms:()Lscala/Predef$$less$colon$less;
	invokeinterface	InterfaceMethod scala/util/parsing/combinator/Parsers.accept:(Ljava/lang/Object;Lscala/Function1;)Lscala/util/parsing/combinator/Parsers$Parser;
	new	class scala/util/parsing/combinator/lexical/StdLexical$$anonfun$parseDelim$1$1
	dup
	aload_0
	aload_1
	invokespecial	Method scala/util/parsing/combinator/lexical/StdLexical$$anonfun$parseDelim$1$1."<init>":(Lscala/util/parsing/combinator/lexical/StdLexical;Ljava/lang/String;)V
	invokevirtual	Method scala/util/parsing/combinator/Parsers$Parser.$up$up:(Lscala/Function1;)Lscala/util/parsing/combinator/Parsers$Parser;
	areturn
  Labels:
  LocalVariableTable: 
   Start  Length  Slot  Name   Signature
   0      37      0    this       Lscala/util/parsing/combinator/lexical/StdLexical;
   0      37      1    s$1       Ljava/lang/String;


public scala.util.parsing.combinator.lexical.StdLexical();
  Signature: ()V
  Code:
   Stack=3, Locals=1, Args_size=1
	aload_0
	invokespecial	Method scala/util/parsing/combinator/lexical/Lexical."<init>":()V
	aload_0
	invokestatic	Method scala/util/parsing/combinator/token/StdTokens$class.$init$:(Lscala/util/parsing/combinator/token/StdTokens;)V
	aload_0
	new	class scala/collection/mutable/HashSet
	dup
	invokespecial	Method scala/collection/mutable/HashSet."<init>":()V
	putfield	Field reserved:Lscala/collection/mutable/HashSet;
	aload_0
	new	class scala/collection/mutable/HashSet
	dup
	invokespecial	Method scala/collection/mutable/HashSet."<init>":()V
	putfield	Field delimiters:Lscala/collection/mutable/HashSet;
	return
  Labels:

}

