Compiled from "Expression.scala"
public class scala.xml.path.Expression$Exists extends scala.xml.path.Expression$Cond implements scala.ScalaObject,scala.Product,java.io.Serializable
  SourceFile: "Expression.scala"
  Scala: length = 0x
   
  InnerClass: 
   public abstract #109= #14 of #108; //Cond=class scala/xml/path/Expression$Cond of class scala/xml/path/Expression
   public #64= #10 of #108; //Exists=class scala/xml/path/Expression$Exists of class scala/xml/path/Expression
   public abstract #112= #111 of #108; //GenExp=class scala/xml/path/Expression$GenExp of class scala/xml/path/Expression
  minor version: 0
  major version: 49
  Constant pool:
const #1 = Asciz	SourceFile;
const #2 = Asciz	Expression.scala;
const #3 = Asciz	p;
const #4 = Asciz	Lscala/xml/path/Expression$GenExp;;
const #5 = Asciz	<init>;
const #6 = Asciz	(Lscala/xml/path/Expression$GenExp;)V;
const #7 = Asciz	Code;
const #8 = Asciz	LineNumberTable;
const #9 = Asciz	scala/xml/path/Expression$Exists;
const #10 = class	#9;	//  scala/xml/path/Expression$Exists
const #11 = NameAndType	#3:#4;//  p:Lscala/xml/path/Expression$GenExp;
const #12 = Field	#10.#11;	//  scala/xml/path/Expression$Exists.p:Lscala/xml/path/Expression$GenExp;
const #13 = Asciz	scala/xml/path/Expression$Cond;
const #14 = class	#13;	//  scala/xml/path/Expression$Cond
const #15 = Asciz	()V;
const #16 = NameAndType	#5:#15;//  "<init>":()V
const #17 = Method	#14.#16;	//  scala/xml/path/Expression$Cond."<init>":()V
const #18 = Asciz	scala/Product$class;
const #19 = class	#18;	//  scala/Product$class
const #20 = Asciz	$init$;
const #21 = Asciz	(Lscala/Product;)V;
const #22 = NameAndType	#20:#21;//  $init$:(Lscala/Product;)V
const #23 = Method	#19.#22;	//  scala/Product$class.$init$:(Lscala/Product;)V
const #24 = Asciz	this;
const #25 = Asciz	Lscala/xml/path/Expression$Exists;;
const #26 = Asciz	LocalVariableTable;
const #27 = Asciz	gd7$1;
const #28 = Asciz	(Lscala/xml/path/Expression$GenExp;)Z;
const #29 = Asciz	()Lscala/xml/path/Expression$GenExp;;
const #30 = NameAndType	#3:#29;//  p:()Lscala/xml/path/Expression$GenExp;
const #31 = Method	#10.#30;	//  scala/xml/path/Expression$Exists.p:()Lscala/xml/path/Expression$GenExp;
const #32 = Asciz	java/lang/Object;
const #33 = class	#32;	//  java/lang/Object
const #34 = Asciz	equals;
const #35 = Asciz	(Ljava/lang/Object;)Z;
const #36 = NameAndType	#34:#35;//  equals:(Ljava/lang/Object;)Z
const #37 = Method	#33.#36;	//  java/lang/Object.equals:(Ljava/lang/Object;)Z
const #38 = Asciz	canEqual;
const #39 = Asciz	productElement;
const #40 = Asciz	(I)Ljava/lang/Object;;
const #41 = Asciz	scala/runtime/BoxesRunTime;
const #42 = class	#41;	//  scala/runtime/BoxesRunTime
const #43 = Asciz	boxToInteger;
const #44 = Asciz	(I)Ljava/lang/Integer;;
const #45 = NameAndType	#43:#44;//  boxToInteger:(I)Ljava/lang/Integer;
const #46 = Method	#42.#45;	//  scala/runtime/BoxesRunTime.boxToInteger:(I)Ljava/lang/Integer;
const #47 = Asciz	(Ljava/lang/Object;Ljava/lang/Object;)Z;
const #48 = NameAndType	#34:#47;//  equals:(Ljava/lang/Object;Ljava/lang/Object;)Z
const #49 = Method	#42.#48;	//  scala/runtime/BoxesRunTime.equals:(Ljava/lang/Object;Ljava/lang/Object;)Z
const #50 = Asciz	java/lang/IndexOutOfBoundsException;
const #51 = class	#50;	//  java/lang/IndexOutOfBoundsException
const #52 = Asciz	toString;
const #53 = Asciz	()Ljava/lang/String;;
const #54 = NameAndType	#52:#53;//  toString:()Ljava/lang/String;
const #55 = Method	#33.#54;	//  java/lang/Object.toString:()Ljava/lang/String;
const #56 = Asciz	(Ljava/lang/String;)V;
const #57 = NameAndType	#5:#56;//  "<init>":(Ljava/lang/String;)V
const #58 = Method	#51.#57;	//  java/lang/IndexOutOfBoundsException."<init>":(Ljava/lang/String;)V
const #59 = Asciz	temp31;
const #60 = Asciz	I;
const #61 = Asciz	productArity;
const #62 = Asciz	()I;
const #63 = Asciz	productPrefix;
const #64 = Asciz	Exists;
const #65 = String	#64;	//  Exists
const #66 = NameAndType	#27:#28;//  gd7$1:(Lscala/xml/path/Expression$GenExp;)Z
const #67 = Method	#10.#66;	//  scala/xml/path/Expression$Exists.gd7$1:(Lscala/xml/path/Expression$GenExp;)Z
const #68 = Asciz	scala/Product;
const #69 = class	#68;	//  scala/Product
const #70 = NameAndType	#38:#35;//  canEqual:(Ljava/lang/Object;)Z
const #71 = InterfaceMethod	#69.#70;	//  scala/Product.canEqual:(Ljava/lang/Object;)Z
const #72 = Asciz	temp28;
const #73 = Asciz	Ljava/lang/Object;;
const #74 = Asciz	temp29;
const #75 = Asciz	temp30;
const #76 = Asciz	p$1;
const #77 = Asciz	scala/runtime/ScalaRunTime$;
const #78 = class	#77;	//  scala/runtime/ScalaRunTime$
const #79 = Asciz	MODULE$;
const #80 = Asciz	Lscala/runtime/ScalaRunTime$;;
const #81 = NameAndType	#79:#80;//  MODULE$:Lscala/runtime/ScalaRunTime$;
const #82 = Field	#78.#81;	//  scala/runtime/ScalaRunTime$.MODULE$:Lscala/runtime/ScalaRunTime$;
const #83 = Asciz	_toString;
const #84 = Asciz	(Lscala/Product;)Ljava/lang/String;;
const #85 = NameAndType	#83:#84;//  _toString:(Lscala/Product;)Ljava/lang/String;
const #86 = Method	#78.#85;	//  scala/runtime/ScalaRunTime$._toString:(Lscala/Product;)Ljava/lang/String;
const #87 = Asciz	hashCode;
const #88 = Asciz	_hashCode;
const #89 = Asciz	(Lscala/Product;)I;
const #90 = NameAndType	#88:#89;//  _hashCode:(Lscala/Product;)I
const #91 = Method	#78.#90;	//  scala/runtime/ScalaRunTime$._hashCode:(Lscala/Product;)I
const #92 = Asciz	copy$default$1;
const #93 = Asciz	copy;
const #94 = Asciz	(Lscala/xml/path/Expression$GenExp;)Lscala/xml/path/Expression$Exists;;
const #95 = NameAndType	#5:#6;//  "<init>":(Lscala/xml/path/Expression$GenExp;)V
const #96 = Method	#10.#95;	//  scala/xml/path/Expression$Exists."<init>":(Lscala/xml/path/Expression$GenExp;)V
const #97 = Asciz	productElements;
const #98 = Asciz	()Lscala/collection/Iterator;;
const #99 = Asciz	(Lscala/Product;)Lscala/collection/Iterator;;
const #100 = NameAndType	#97:#99;//  productElements:(Lscala/Product;)Lscala/collection/Iterator;
const #101 = Method	#19.#100;	//  scala/Product$class.productElements:(Lscala/Product;)Lscala/collection/Iterator;
const #102 = Asciz	productIterator;
const #103 = NameAndType	#102:#99;//  productIterator:(Lscala/Product;)Lscala/collection/Iterator;
const #104 = Method	#19.#103;	//  scala/Product$class.productIterator:(Lscala/Product;)Lscala/collection/Iterator;
const #105 = Asciz	Scala;
const #106 = Asciz	InnerClasses;
const #107 = Asciz	scala/xml/path/Expression;
const #108 = class	#107;	//  scala/xml/path/Expression
const #109 = Asciz	Cond;
const #110 = Asciz	scala/xml/path/Expression$GenExp;
const #111 = class	#110;	//  scala/xml/path/Expression$GenExp
const #112 = Asciz	GenExp;
const #113 = Asciz	scala/ScalaObject;
const #114 = class	#113;	//  scala/ScalaObject
const #115 = Asciz	java/io/Serializable;
const #116 = class	#115;	//  java/io/Serializable

{
public scala.xml.path.Expression$Exists(scala.xml.path.Expression$GenExp);
  Code:
   Stack=2, Locals=2, Args_size=2
   0:	aload_0
   1:	aload_1
   2:	putfield	#12; //Field p:Lscala/xml/path/Expression$GenExp;
   5:	aload_0
   6:	invokespecial	#17; //Method scala/xml/path/Expression$Cond."<init>":()V
   9:	aload_0
   10:	invokestatic	#23; //Method scala/Product$class.$init$:(Lscala/Product;)V
   13:	return
  LineNumberTable: 
   line 63: 0

  LocalVariableTable: 
   Start  Length  Slot  Name   Signature
   0      14      0    this       Lscala/xml/path/Expression$Exists;
   0      14      1    p       Lscala/xml/path/Expression$GenExp;


public boolean canEqual(java.lang.Object);
  Code:
   Stack=1, Locals=2, Args_size=2
   0:	aload_1
   1:	instanceof	#10; //class scala/xml/path/Expression$Exists
   4:	ireturn
  LineNumberTable: 
   line 63: 0


public java.lang.Object productElement(int);
  Code:
   Stack=3, Locals=3, Args_size=2
   0:	iload_1
   1:	istore_2
   2:	iload_2
   3:	invokestatic	#46; //Method scala/runtime/BoxesRunTime.boxToInteger:(I)Ljava/lang/Integer;
   6:	iconst_0
   7:	invokestatic	#46; //Method scala/runtime/BoxesRunTime.boxToInteger:(I)Ljava/lang/Integer;
   10:	invokestatic	#49; //Method scala/runtime/BoxesRunTime.equals:(Ljava/lang/Object;Ljava/lang/Object;)Z
   13:	ifeq	21
   16:	aload_0
   17:	invokevirtual	#31; //Method p:()Lscala/xml/path/Expression$GenExp;
   20:	areturn
   21:	new	#51; //class java/lang/IndexOutOfBoundsException
   24:	dup
   25:	iload_1
   26:	invokestatic	#46; //Method scala/runtime/BoxesRunTime.boxToInteger:(I)Ljava/lang/Integer;
   29:	invokevirtual	#55; //Method java/lang/Object.toString:()Ljava/lang/String;
   32:	invokespecial	#58; //Method java/lang/IndexOutOfBoundsException."<init>":(Ljava/lang/String;)V
   35:	athrow
  LineNumberTable: 
   line 63: 0

  LocalVariableTable: 
   Start  Length  Slot  Name   Signature
   0      36      0    this       Lscala/xml/path/Expression$Exists;
   2      34      2    temp31       I


public int productArity();
  Code:
   Stack=1, Locals=1, Args_size=1
   0:	iconst_1
   1:	ireturn
  LineNumberTable: 
   line 63: 0


public java.lang.String productPrefix();
  Code:
   Stack=1, Locals=1, Args_size=1
   0:	ldc	#65; //String Exists
   2:	areturn
  LineNumberTable: 
   line 63: 0


public boolean equals(java.lang.Object);
  Code:
   Stack=2, Locals=6, Args_size=2
   0:	aload_0
   1:	aload_1
   2:	if_acmpeq	59
   5:	aload_1
   6:	astore_2
   7:	aload_2
   8:	instanceof	#10; //class scala/xml/path/Expression$Exists
   11:	ifeq	55
   14:	aload_2
   15:	checkcast	#10; //class scala/xml/path/Expression$Exists
   18:	astore_3
   19:	aload_3
   20:	invokevirtual	#31; //Method p:()Lscala/xml/path/Expression$GenExp;
   23:	astore	4
   25:	aload	4
   27:	astore	5
   29:	aload_0
   30:	aload	5
   32:	invokespecial	#67; //Method gd7$1:(Lscala/xml/path/Expression$GenExp;)Z
   35:	ifeq	51
   38:	aload_1
   39:	checkcast	#10; //class scala/xml/path/Expression$Exists
   42:	aload_0
   43:	invokeinterface	#71,  2; //InterfaceMethod scala/Product.canEqual:(Ljava/lang/Object;)Z
   48:	goto	56
   51:	iconst_0
   52:	goto	56
   55:	iconst_0
   56:	ifeq	63
   59:	iconst_1
   60:	goto	64
   63:	iconst_0
   64:	ireturn
  LineNumberTable: 
   line 63: 0
   line 21: 51
   line 63: 56

  LocalVariableTable: 
   Start  Length  Slot  Name   Signature
   0      65      0    this       Lscala/xml/path/Expression$Exists;
   7      52      2    temp28       Ljava/lang/Object;
   19      36      3    temp29       Lscala/xml/path/Expression$Exists;
   25      30      4    temp30       Lscala/xml/path/Expression$GenExp;
   29      26      5    p$1       Lscala/xml/path/Expression$GenExp;


public java.lang.String toString();
  Code:
   Stack=2, Locals=1, Args_size=1
   0:	getstatic	#82; //Field scala/runtime/ScalaRunTime$.MODULE$:Lscala/runtime/ScalaRunTime$;
   3:	aload_0
   4:	invokevirtual	#86; //Method scala/runtime/ScalaRunTime$._toString:(Lscala/Product;)Ljava/lang/String;
   7:	areturn
  LineNumberTable: 
   line 63: 0


public int hashCode();
  Code:
   Stack=2, Locals=1, Args_size=1
   0:	getstatic	#82; //Field scala/runtime/ScalaRunTime$.MODULE$:Lscala/runtime/ScalaRunTime$;
   3:	aload_0
   4:	invokevirtual	#91; //Method scala/runtime/ScalaRunTime$._hashCode:(Lscala/Product;)I
   7:	ireturn
  LineNumberTable: 
   line 63: 0


public scala.xml.path.Expression$GenExp copy$default$1();
  Code:
   Stack=1, Locals=1, Args_size=1
   0:	aload_0
   1:	invokevirtual	#31; //Method p:()Lscala/xml/path/Expression$GenExp;
   4:	areturn
  LineNumberTable: 
   line 63: 0


public scala.xml.path.Expression$Exists copy(scala.xml.path.Expression$GenExp);
  Code:
   Stack=3, Locals=2, Args_size=2
   0:	new	#10; //class scala/xml/path/Expression$Exists
   3:	dup
   4:	aload_1
   5:	invokespecial	#96; //Method "<init>":(Lscala/xml/path/Expression$GenExp;)V
   8:	areturn
  LineNumberTable: 
   line 63: 0

  LocalVariableTable: 
   Start  Length  Slot  Name   Signature
   0      9      0    this       Lscala/xml/path/Expression$Exists;
   0      9      1    p       Lscala/xml/path/Expression$GenExp;


public scala.xml.path.Expression$GenExp p();
  Code:
   Stack=1, Locals=1, Args_size=1
   0:	aload_0
   1:	getfield	#12; //Field p:Lscala/xml/path/Expression$GenExp;
   4:	areturn
  LineNumberTable: 
   line 63: 0


public scala.collection.Iterator productElements();
  Code:
   Stack=1, Locals=1, Args_size=1
   0:	aload_0
   1:	invokestatic	#101; //Method scala/Product$class.productElements:(Lscala/Product;)Lscala/collection/Iterator;
   4:	areturn
  LineNumberTable: 
   line 63: 0


public scala.collection.Iterator productIterator();
  Code:
   Stack=1, Locals=1, Args_size=1
   0:	aload_0
   1:	invokestatic	#104; //Method scala/Product$class.productIterator:(Lscala/Product;)Lscala/collection/Iterator;
   4:	areturn
  LineNumberTable: 
   line 63: 0


}

