Compiled from "Expression.scala"
public final class scala.xml.path.Expression extends java.lang.Object
  SourceFile: "Expression.scala"
  ScalaSig: length = 0x10C2
   05 00 FFFFFF84 07 07 05 01 02 FFFFFF88 02 09 01 0A 45 78 70
   72 65 73 73 69 6F 6E 0A 02 03 04 01 04 70 61 74
   68 0A 02 05 06 01 03 78 6D 6C 0A 01 07 01 05 73
   63 61 6C 61 03 00 10 02 0A 0B 0D 01 02 06 08 0C
   02 FFFFFF84 FFFFFF80 FFFFFF80 FFFFFF88 02 0D 02 0A 45 78 70 72 65 73 73
   69 6F 6E 13 03 0B 0E 16 10 02 0F 14 0D 01 10 0A
   02 11 12 01 04 6C 61 6E 67 0A 01 13 01 04 6A 61
   76 61 09 02 15 10 02 06 4F 62 6A 65 63 74 10 02
   17 18 0D 01 06 09 02 19 06 02 0B 53 63 61 6C 61
   4F 62 6A 65 63 74 08 05 1B 0B FFFFFF84 00 1C 01 06 3C
   69 6E 69 74 3E 14 01 09 08 05 1E 0B FFFFFF84 02 1F 01
   0E 74 65 73 74 46 72 6F 6D 53 74 72 69 6E 67 14
   02 20 27 10 02 21 22 0D 01 0B 06 08 23 0B FFFFFF84 FFFFFF80
   FFFFFF80 FFFFFF81 00 24 02 04 54 65 73 74 13 03 22 0E 16 08
   05 1B 22 FFFFFF84 00 26 14 01 20 08 05 28 1D FFFFFFC0 00 29
   01 01 78 10 02 2A 2D 0E 02 17 2B 09 02 2C 06 01
   06 50 72 65 64 65 66 09 02 2E 2F 02 06 53 74 72
   69 6E 67 0A 02 2C 06 06 08 31 0B FFFFFF84 FFFFFF80 FFFFFF80 FFFFFF80 40
   32 02 04 46 45 78 70 13 04 30 0E 16 33 10 02 17
   34 09 02 35 06 02 07 50 72 6F 64 75 63 74 08 08
   37 30 FFFFFF82 FFFFFFCA FFFFFF80 FFFFFF84 00 38 01 01 65 15 01 39 10 02
   21 3A 06 08 3B 0B FFFFFF84 FFFFFF80 FFFFFF80 FFFFFF81 00 3C 02 04 45 78
   70 72 13 03 3A 3D 16 10 02 21 3E 06 08 3F 0B FFFFFF84
   FFFFFF80 FFFFFF80 FFFFFF81 00 40 02 06 47 65 6E 45 78 70 13 03 3E
   0E 16 08 05 1B 3E FFFFFF84 00 42 14 01 3D 08 05 1B 3A
   FFFFFF84 00 44 14 01 39 08 05 46 3A FFFFFF84 00 47 01 07 24
   62 73 6C 61 73 68 14 03 48 FFFFFF81 09 10 02 21 49 06
   08 4A 0B FFFFFF84 FFFFFF80 FFFFFF80 FFFFFF80 40 4B 02 05 43 68 69 6C 64
   13 04 49 39 16 33 08 08 4D 49 FFFFFF82 FFFFFFCA FFFFFF80 FFFFFF84 00 4E
   01 04 74 65 73 74 15 01 20 08 08 50 49 FFFFFF82 FFFFFF88 FFFFFFA0
   FFFFFF80 04 20 01 05 74 65 73 74 20 08 08 37 49 FFFFFF82 FFFFFFCA
   FFFFFF80 FFFFFF84 00 38 08 08 53 49 FFFFFF82 FFFFFF88 FFFFFFA0 FFFFFF80 04 39 01 02
   65 20 08 05 1B 49 FFFFFF84 00 55 14 03 48 56 57 08 05
   4D 54 FFFFFFC0 00 20 08 05 37 54 FFFFFFC0 00 39 08 07 59 49
   FFFFFF81 FFFFFF80 FFFFFF84 00 5A 01 04 63 6F 70 79 14 03 48 5B 5E
   08 08 5C 4D 58 FFFFFF90 FFFFFF80 FFFFFFC0 00 20 08 07 5D 49 FFFFFF91 FFFFFF80
   FFFFFF84 00 4E 01 0E 63 6F 70 79 24 64 65 66 61 75 6C
   74 24 31 08 08 5F 37 58 FFFFFF90 FFFFFF80 FFFFFFC0 00 39 08 07 60
   49 FFFFFF91 FFFFFF80 FFFFFF84 00 38 01 0E 63 6F 70 79 24 64 65 66
   61 75 6C 74 24 32 08 08 62 49 FFFFFF84 FFFFFF80 FFFFFF80 FFFFFF84 20 63
   01 08 68 61 73 68 43 6F 64 65 14 01 64 10 02 17
   65 09 02 66 06 02 03 49 6E 74 08 08 68 49 FFFFFF84 FFFFFF80
   FFFFFF80 FFFFFF84 20 69 01 08 74 6F 53 74 72 69 6E 67 14 01
   29 08 08 6B 49 FFFFFF84 FFFFFF80 FFFFFF80 FFFFFF84 20 6C 01 06 65 71 75
   61 6C 73 14 02 6D 70 10 02 17 6E 09 02 6F 06 02
   07 42 6F 6F 6C 65 61 6E 08 07 71 6A FFFFFF81 FFFFFF80 FFFFFFC0 00
   72 01 03 78 24 31 10 02 17 73 09 02 74 06 02 03
   41 6E 79 08 08 76 49 FFFFFF84 FFFFFF80 FFFFFF80 FFFFFF84 20 77 01 0D 70
   72 6F 64 75 63 74 50 72 65 66 69 78 15 01 78 10
   02 0F 79 09 02 2E 10 08 08 7B 49 FFFFFF84 FFFFFF80 FFFFFF80 FFFFFF84 20
   7C 01 0C 70 72 6F 64 75 63 74 41 72 69 74 79 15
   01 64 08 08 7E 49 FFFFFF84 FFFFFF80 FFFFFF80 FFFFFF84 20 7F 01 0E 70 72
   6F 64 75 63 74 45 6C 65 6D 65 6E 74 14 03 72 FFFFFF81
   00 08 07 71 7D FFFFFF81 FFFFFF80 FFFFFFC0 00 64 08 0A FFFFFF81 02 49 FFFFFF84
   FFFFFF80 FFFFFF80 FFFFFF84 20 FFFFFF81 03 01 08 63 61 6E 45 71 75 61 6C
   14 03 6D FFFFFF81 04 08 08 71 FFFFFF81 01 FFFFFF81 FFFFFF80 FFFFFFC0 00 72 28
   03 49 FFFFFF81 06 10 03 17 FFFFFF81 07 09 03 FFFFFF81 08 06 02 0C
   73 65 72 69 61 6C 69 7A 61 62 6C 65 08 05 28 45
   FFFFFFC0 00 29 08 07 FFFFFF81 0B 3A FFFFFF84 00 FFFFFF81 0C 01 0E 24 62
   73 6C 61 73 68 24 62 73 6C 61 73 68 14 04 FFFFFF81 0D
   FFFFFF81 2D 10 03 21 FFFFFF81 0E 06 0A FFFFFF81 0F 0B FFFFFF84 FFFFFF80 FFFFFF80 FFFFFF80
   40 FFFFFF81 10 02 0A 44 65 73 63 4F 72 53 65 6C 66 13
   05 FFFFFF81 0E 39 16 33 08 09 4D FFFFFF81 0E FFFFFF82 FFFFFFCA FFFFFF80 FFFFFF84 00
   4E 08 09 50 FFFFFF81 0E FFFFFF82 FFFFFF88 FFFFFFA0 FFFFFF80 04 20 08 09 37 FFFFFF81
   0E FFFFFF82 FFFFFFCA FFFFFF80 FFFFFF84 00 38 08 09 53 FFFFFF81 0E FFFFFF82 FFFFFF88 FFFFFFA0 FFFFFF80
   04 39 08 07 1B FFFFFF81 0E FFFFFF84 00 FFFFFF81 16 14 06 FFFFFF81 0D FFFFFF81
   17 FFFFFF81 18 08 06 4D FFFFFF81 15 FFFFFFC0 00 20 08 06 37 FFFFFF81 15
   FFFFFFC0 00 39 08 09 59 FFFFFF81 0E FFFFFF81 FFFFFF80 FFFFFF84 00 FFFFFF81 1A 14 06
   FFFFFF81 0D FFFFFF81 1B FFFFFF81 1D 08 0A FFFFFF81 1C 4D FFFFFF81 19 FFFFFF90 FFFFFF80 FFFFFFC0
   00 20 08 08 5D FFFFFF81 0E FFFFFF91 FFFFFF80 FFFFFF84 00 4E 08 0A FFFFFF81 1E
   37 FFFFFF81 19 FFFFFF90 FFFFFF80 FFFFFFC0 00 39 08 08 60 FFFFFF81 0E FFFFFF91 FFFFFF80 FFFFFF84
   00 38 08 09 62 FFFFFF81 0E FFFFFF84 FFFFFF80 FFFFFF80 FFFFFF84 20 63 08 09 68
   FFFFFF81 0E FFFFFF84 FFFFFF80 FFFFFF80 FFFFFF84 20 69 08 0A 6B FFFFFF81 0E FFFFFF84 FFFFFF80 FFFFFF80
   FFFFFF84 20 FFFFFF81 22 14 03 6D FFFFFF81 23 08 08 71 FFFFFF81 21 FFFFFF81 FFFFFF80
   FFFFFFC0 00 72 08 09 76 FFFFFF81 0E FFFFFF84 FFFFFF80 FFFFFF80 FFFFFF84 20 77 08 09
   7B FFFFFF81 0E FFFFFF84 FFFFFF80 FFFFFF80 FFFFFF84 20 7C 08 0A 7E FFFFFF81 0E FFFFFF84 FFFFFF80
   FFFFFF80 FFFFFF84 20 FFFFFF81 27 14 03 72 FFFFFF81 28 08 08 71 FFFFFF81 26 FFFFFF81
   FFFFFF80 FFFFFFC0 00 64 08 0B FFFFFF81 02 FFFFFF81 0E FFFFFF84 FFFFFF80 FFFFFF80 FFFFFF84 20 FFFFFF81
   2A 14 03 6D FFFFFF81 2B 08 08 71 FFFFFF81 29 FFFFFF81 FFFFFF80 FFFFFFC0 00 72
   28 04 FFFFFF81 0E FFFFFF81 06 08 06 28 FFFFFF81 0A FFFFFFC0 00 29 08 07
   FFFFFF81 2F 3A FFFFFF84 00 FFFFFF81 30 01 05 61 70 70 6C 79 14 04
   FFFFFF81 31 FFFFFF81 32 10 02 21 30 08 08 FFFFFF81 33 FFFFFF81 2E FFFFFFC0 00
   FFFFFF81 34 01 01 63 10 03 21 FFFFFF81 35 06 0A FFFFFF81 36 0B FFFFFF84
   FFFFFF80 FFFFFF80 FFFFFF81 00 FFFFFF81 37 02 04 43 6F 6E 64 13 04 FFFFFF81 35
   0E 16 08 07 1B FFFFFF81 35 FFFFFF84 00 FFFFFF81 39 14 02 FFFFFF81 34 08
   07 FFFFFF81 3B 3A FFFFFF84 00 FFFFFF81 3C 01 04 65 76 61 6C 14 04
   FFFFFF81 3D FFFFFF81 41 10 04 FFFFFF81 3E FFFFFF81 3F 0D 01 04 09 03 FFFFFF81
   40 04 02 07 4E 6F 64 65 53 65 71 08 08 FFFFFF81 42 FFFFFF81
   3A FFFFFFC0 00 FFFFFF81 43 01 01 6E 10 04 FFFFFF81 3E FFFFFF81 44 09 03
   FFFFFF81 45 04 02 04 4E 6F 64 65 08 08 53 30 FFFFFF82 FFFFFF88 FFFFFFA0
   FFFFFF80 04 39 08 0A FFFFFF81 33 30 FFFFFF82 FFFFFFCA FFFFFF80 FFFFFF84 00 FFFFFF81 48 15
   02 FFFFFF81 34 08 0A FFFFFF81 4A 30 FFFFFF82 FFFFFF88 FFFFFFA0 FFFFFF80 04 FFFFFF81 34 01
   02 63 20 08 06 1B 30 FFFFFF84 00 FFFFFF81 4C 14 06 FFFFFF81 31 FFFFFF81
   4D FFFFFF81 4E 08 06 37 FFFFFF81 4B FFFFFFC0 00 39 08 08 FFFFFF81 33 FFFFFF81
   4B FFFFFFC0 00 FFFFFF81 34 08 07 FFFFFF81 3B 30 FFFFFF84 00 FFFFFF81 50 14 04
   FFFFFF81 3D FFFFFF81 51 08 08 FFFFFF81 42 FFFFFF81 4F FFFFFFC0 00 FFFFFF81 43 08 08
   59 30 FFFFFF81 FFFFFF80 FFFFFF84 00 FFFFFF81 53 14 06 FFFFFF81 31 FFFFFF81 54 FFFFFF81 56
   08 0A FFFFFF81 55 37 FFFFFF81 52 FFFFFF90 FFFFFF80 FFFFFFC0 00 39 08 07 5D 30
   FFFFFF91 FFFFFF80 FFFFFF84 00 38 08 0C FFFFFF81 57 FFFFFF81 33 FFFFFF81 52 FFFFFF90 FFFFFF80 FFFFFFC0
   00 FFFFFF81 34 08 08 60 30 FFFFFF91 FFFFFF80 FFFFFF84 00 FFFFFF81 48 08 08 62
   30 FFFFFF84 FFFFFF80 FFFFFF80 FFFFFF84 20 63 08 08 68 30 FFFFFF84 FFFFFF80 FFFFFF80 FFFFFF84 20
   69 08 09 6B 30 FFFFFF84 FFFFFF80 FFFFFF80 FFFFFF84 20 FFFFFF81 5B 14 03 6D FFFFFF81
   5C 08 08 71 FFFFFF81 5A FFFFFF81 FFFFFF80 FFFFFFC0 00 72 08 08 76 30 FFFFFF84
   FFFFFF80 FFFFFF80 FFFFFF84 20 77 08 08 7B 30 FFFFFF84 FFFFFF80 FFFFFF80 FFFFFF84 20 7C 08
   09 7E 30 FFFFFF84 FFFFFF80 FFFFFF80 FFFFFF84 20 FFFFFF81 60 14 03 72 FFFFFF81 61 08
   08 71 FFFFFF81 5F FFFFFF81 FFFFFF80 FFFFFFC0 00 64 08 0A FFFFFF81 02 30 FFFFFF84 FFFFFF80
   FFFFFF80 FFFFFF84 20 FFFFFF81 63 14 03 6D FFFFFF81 64 08 08 71 FFFFFF81 62 FFFFFF81
   FFFFFF80 FFFFFFC0 00 72 28 03 30 FFFFFF81 06 07 09 FFFFFF81 67 0B FFFFFF81 FFFFFF80
   FFFFFF88 02 FFFFFF81 68 01 04 46 45 78 70 10 03 21 FFFFFF81 69 06
   09 31 0B FFFFFF84 FFFFFF81 FFFFFF80 FFFFFF88 02 FFFFFF81 6A 13 06 FFFFFF81 69 0E FFFFFF81
   6B 16 10 08 17 FFFFFF81 6C 39 FFFFFF81 34 FFFFFF81 31 09 03 FFFFFF81 6D
   06 02 09 46 75 6E 63 74 69 6F 6E 32 08 07 1B FFFFFF81
   69 FFFFFF84 00 FFFFFF81 6F 14 02 FFFFFF81 68 08 0A FFFFFF81 2F FFFFFF81 69 FFFFFF81
   FFFFFF80 FFFFFF84 40 FFFFFF81 71 14 06 FFFFFF81 31 FFFFFF81 72 FFFFFF81 73 08 06 37
   FFFFFF81 70 FFFFFFC0 00 39 08 08 FFFFFF81 33 FFFFFF81 70 FFFFFFC0 00 FFFFFF81 34 08
   0A FFFFFF81 75 FFFFFF81 69 FFFFFF81 FFFFFF80 FFFFFF84 40 FFFFFF81 76 01 07 75 6E 61
   70 70 6C 79 14 04 FFFFFF81 77 FFFFFF81 7D 10 05 17 FFFFFF81 78 FFFFFF81
   7A 09 03 FFFFFF81 79 06 02 04 53 6F 6D 65 10 06 17 FFFFFF81
   7B 39 FFFFFF81 34 09 03 FFFFFF81 7C 06 02 06 54 75 70 6C 65
   32 08 08 FFFFFF81 7E FFFFFF81 74 FFFFFFC0 00 FFFFFF81 31 01 03 78 24 30
   06 0A FFFFFF82 00 0B FFFFFF84 FFFFFF80 FFFFFF80 FFFFFF80 40 FFFFFF82 01 02 06 41 74
   74 72 69 62 13 05 FFFFFF81 7F 3D 16 33 08 0A 4D FFFFFF81 7F
   FFFFFF82 FFFFFFCA FFFFFF80 FFFFFF84 00 FFFFFF82 03 15 02 FFFFFF82 04 10 03 21 FFFFFF82 05
   06 0A FFFFFF82 06 0B FFFFFF84 FFFFFF80 FFFFFF80 FFFFFF80 40 FFFFFF82 07 02 08 4E 61
   6D 65 54 65 73 74 13 05 FFFFFF82 05 20 16 33 08 0B FFFFFF82
   09 FFFFFF82 05 FFFFFF82 FFFFFFCA FFFFFF80 FFFFFF84 00 FFFFFF82 0A 01 05 6C 61 62 65
   6C 15 01 29 08 0A FFFFFF82 0C FFFFFF82 05 FFFFFF82 FFFFFF88 FFFFFFA0 FFFFFF80 04 29
   01 06 6C 61 62 65 6C 20 08 07 1B FFFFFF82 05 FFFFFF84 00 FFFFFF82
   0E 14 04 FFFFFF82 04 FFFFFF82 0F 08 07 FFFFFF82 09 FFFFFF82 0D FFFFFFC0 00 29
   08 09 59 FFFFFF82 05 FFFFFF81 FFFFFF80 FFFFFF84 00 FFFFFF82 11 14 04 FFFFFF82 04 FFFFFF82
   12 08 0B FFFFFF82 13 FFFFFF82 09 FFFFFF82 10 FFFFFF90 FFFFFF80 FFFFFFC0 00 29 08 09
   5D FFFFFF82 05 FFFFFF91 FFFFFF80 FFFFFF84 00 FFFFFF82 0A 08 09 62 FFFFFF82 05 FFFFFF84 FFFFFF80
   FFFFFF80 FFFFFF84 20 63 08 09 68 FFFFFF82 05 FFFFFF84 FFFFFF80 FFFFFF80 FFFFFF84 20 69 08
   0A 6B FFFFFF82 05 FFFFFF84 FFFFFF80 FFFFFF80 FFFFFF84 20 FFFFFF82 17 14 03 6D FFFFFF82 18
   08 08 71 FFFFFF82 16 FFFFFF81 FFFFFF80 FFFFFFC0 00 72 08 09 76 FFFFFF82 05 FFFFFF84
   FFFFFF80 FFFFFF80 FFFFFF84 20 77 08 09 7B FFFFFF82 05 FFFFFF84 FFFFFF80 FFFFFF80 FFFFFF84 20 7C
   08 0A 7E FFFFFF82 05 FFFFFF84 FFFFFF80 FFFFFF80 FFFFFF84 20 FFFFFF82 1C 14 03 72 FFFFFF82
   1D 08 08 71 FFFFFF82 1B FFFFFF81 FFFFFF80 FFFFFFC0 00 64 08 0B FFFFFF81 02 FFFFFF82
   05 FFFFFF84 FFFFFF80 FFFFFF80 FFFFFF84 20 FFFFFF82 1F 14 03 6D FFFFFF82 20 08 08 71
   FFFFFF82 1E FFFFFF81 FFFFFF80 FFFFFFC0 00 72 28 04 FFFFFF82 05 FFFFFF81 06 08 0A 50
   FFFFFF81 7F FFFFFF82 FFFFFF88 FFFFFFA0 FFFFFF80 04 FFFFFF82 04 08 09 37 FFFFFF81 7F FFFFFF82 FFFFFFCA
   FFFFFF80 FFFFFF84 00 38 08 09 53 FFFFFF81 7F FFFFFF82 FFFFFF88 FFFFFFA0 FFFFFF80 04 39 08
   07 1B FFFFFF81 7F FFFFFF84 00 FFFFFF82 26 14 06 FFFFFF82 27 FFFFFF82 28 FFFFFF82 29
   10 03 21 FFFFFF81 7F 08 07 4D FFFFFF82 25 FFFFFFC0 00 FFFFFF82 04 08 06
   37 FFFFFF82 25 FFFFFFC0 00 39 08 09 59 FFFFFF81 7F FFFFFF81 FFFFFF80 FFFFFF84 00 FFFFFF82
   2B 14 06 FFFFFF82 27 FFFFFF82 2C FFFFFF82 2E 08 0B FFFFFF82 2D 4D FFFFFF82 2A
   FFFFFF90 FFFFFF80 FFFFFFC0 00 FFFFFF82 04 08 09 5D FFFFFF81 7F FFFFFF91 FFFFFF80 FFFFFF84 00 FFFFFF82
   03 08 0A FFFFFF82 2F 37 FFFFFF82 2A FFFFFF90 FFFFFF80 FFFFFFC0 00 39 08 08 60
   FFFFFF81 7F FFFFFF91 FFFFFF80 FFFFFF84 00 38 08 09 62 FFFFFF81 7F FFFFFF84 FFFFFF80 FFFFFF80 FFFFFF84
   20 63 08 09 68 FFFFFF81 7F FFFFFF84 FFFFFF80 FFFFFF80 FFFFFF84 20 69 08 0A 6B
   FFFFFF81 7F FFFFFF84 FFFFFF80 FFFFFF80 FFFFFF84 20 FFFFFF82 33 14 03 6D FFFFFF82 34 08 08
   71 FFFFFF82 32 FFFFFF81 FFFFFF80 FFFFFFC0 00 72 08 09 76 FFFFFF81 7F FFFFFF84 FFFFFF80 FFFFFF80
   FFFFFF84 20 77 08 09 7B FFFFFF81 7F FFFFFF84 FFFFFF80 FFFFFF80 FFFFFF84 20 7C 08 0A
   7E FFFFFF81 7F FFFFFF84 FFFFFF80 FFFFFF80 FFFFFF84 20 FFFFFF82 38 14 03 72 FFFFFF82 39 08
   08 71 FFFFFF82 37 FFFFFF81 FFFFFF80 FFFFFFC0 00 64 08 0B FFFFFF81 02 FFFFFF81 7F FFFFFF84
   FFFFFF80 FFFFFF80 FFFFFF84 20 FFFFFF82 3B 14 03 6D FFFFFF82 3C 08 08 71 FFFFFF82 3A
   FFFFFF81 FFFFFF80 FFFFFFC0 00 72 28 04 FFFFFF81 7F FFFFFF81 06 07 09 FFFFFF82 3F 0B
   FFFFFF81 FFFFFF80 FFFFFF88 02 FFFFFF82 40 01 06 41 74 74 72 69 62 10 03
   21 FFFFFF82 41 06 0A FFFFFF82 00 0B FFFFFF84 FFFFFF81 FFFFFF80 FFFFFF88 02 FFFFFF82 42 13
   06 FFFFFF82 41 0E FFFFFF82 43 16 10 08 17 FFFFFF81 6C FFFFFF82 04 39 FFFFFF82
   27 08 07 1B FFFFFF82 41 FFFFFF84 00 FFFFFF82 45 14 02 FFFFFF82 40 08 0A
   FFFFFF81 2F FFFFFF82 41 FFFFFF81 FFFFFF80 FFFFFF84 40 FFFFFF82 47 14 06 FFFFFF82 27 FFFFFF82 48
   FFFFFF82 49 08 07 4D FFFFFF82 46 FFFFFFC0 00 FFFFFF82 04 08 06 37 FFFFFF82 46
   FFFFFFC0 00 39 08 0A FFFFFF81 75 FFFFFF82 41 FFFFFF81 FFFFFF80 FFFFFF84 40 FFFFFF82 4B 14
   04 FFFFFF82 4C FFFFFF82 4E 10 05 17 FFFFFF81 78 FFFFFF82 4D 10 06 17 FFFFFF81
   7B FFFFFF82 04 39 08 08 FFFFFF81 7E FFFFFF82 4A FFFFFFC0 00 FFFFFF82 27 07 07
   FFFFFF82 50 0B FFFFFF88 42 FFFFFF82 51 01 04 52 6F 6F 74 10 03 21
   FFFFFF82 52 06 0A FFFFFF82 53 0B FFFFFF84 FFFFFF80 FFFFFF80 FFFFFF88 42 FFFFFF82 54 02 04
   52 6F 6F 74 13 05 FFFFFF82 52 39 16 33 08 07 1B FFFFFF82 52
   FFFFFF84 00 FFFFFF82 56 14 02 FFFFFF82 51 08 0A 68 FFFFFF82 52 FFFFFF84 FFFFFF80 FFFFFF80
   FFFFFF84 22 FFFFFF82 58 14 01 78 08 09 76 FFFFFF82 52 FFFFFF84 FFFFFF80 FFFFFF80 FFFFFF84
   20 77 08 09 7B FFFFFF82 52 FFFFFF84 FFFFFF80 FFFFFF80 FFFFFF84 20 7C 08 0A 7E
   FFFFFF82 52 FFFFFF84 FFFFFF80 FFFFFF80 FFFFFF84 20 FFFFFF82 5C 14 03 72 FFFFFF82 5D 08 08
   71 FFFFFF82 5B FFFFFF81 FFFFFF80 FFFFFFC0 00 64 08 0B FFFFFF81 02 FFFFFF82 52 FFFFFF84 FFFFFF80
   FFFFFF80 FFFFFF84 20 FFFFFF82 5F 14 03 6D FFFFFF82 60 08 08 71 FFFFFF82 5E FFFFFF81
   FFFFFF80 FFFFFFC0 00 72 08 0B FFFFFF82 62 FFFFFF82 52 FFFFFF84 FFFFFF80 FFFFFF80 FFFFFF84 08 FFFFFF82
   63 01 0B 72 65 61 64 52 65 73 6F 6C 76 65 14 01
   0E 28 04 FFFFFF82 52 FFFFFF81 06 07 09 FFFFFF82 66 0B FFFFFF81 FFFFFF80 FFFFFF88 02
   FFFFFF82 67 01 05 43 68 69 6C 64 10 03 21 FFFFFF82 68 06 09
   4A 0B FFFFFF84 FFFFFF81 FFFFFF80 FFFFFF88 02 FFFFFF82 69 13 06 FFFFFF82 68 0E FFFFFF82 6A
   16 10 06 17 FFFFFF81 6C 20 39 48 08 07 1B FFFFFF82 68 FFFFFF84 00
   FFFFFF82 6C 14 02 FFFFFF82 67 08 0A FFFFFF81 2F FFFFFF82 68 FFFFFF81 FFFFFF80 FFFFFF84 40
   FFFFFF82 6E 14 05 48 FFFFFF82 6F FFFFFF82 70 08 06 4D FFFFFF82 6D FFFFFFC0 00
   20 08 06 37 FFFFFF82 6D FFFFFFC0 00 39 08 0A FFFFFF81 75 FFFFFF82 68 FFFFFF81
   FFFFFF80 FFFFFF84 40 FFFFFF82 72 14 04 FFFFFF82 73 FFFFFF82 75 10 05 17 FFFFFF81 78
   FFFFFF82 74 10 05 17 FFFFFF81 7B 20 39 08 07 FFFFFF81 7E FFFFFF82 71 FFFFFFC0
   00 48 07 09 FFFFFF82 77 0B FFFFFF81 FFFFFF80 FFFFFF88 02 FFFFFF82 78 01 0A 44
   65 73 63 4F 72 53 65 6C 66 10 03 21 FFFFFF82 79 06 0A
   FFFFFF81 0F 0B FFFFFF84 FFFFFF81 FFFFFF80 FFFFFF88 02 FFFFFF82 7A 13 06 FFFFFF82 79 0E FFFFFF82
   7B 16 10 07 17 FFFFFF81 6C 20 39 FFFFFF81 0D 08 07 1B FFFFFF82 79
   FFFFFF84 00 FFFFFF82 7D 14 02 FFFFFF82 78 08 0A FFFFFF81 2F FFFFFF82 79 FFFFFF81 FFFFFF80
   FFFFFF84 40 FFFFFF82 7F 14 06 FFFFFF81 0D FFFFFF83 00 FFFFFF83 01 08 06 4D FFFFFF82
   7E FFFFFFC0 00 20 08 06 37 FFFFFF82 7E FFFFFFC0 00 39 08 0A FFFFFF81 75
   FFFFFF82 79 FFFFFF81 FFFFFF80 FFFFFF84 40 FFFFFF83 03 14 04 FFFFFF82 73 FFFFFF83 04 08 08
   FFFFFF81 7E FFFFFF83 02 FFFFFFC0 00 FFFFFF81 0D 07 07 FFFFFF83 06 0B FFFFFF88 42 FFFFFF83
   07 01 0C 57 69 6C 64 63 61 72 64 54 65 73 74 10
   03 21 FFFFFF83 08 06 0A FFFFFF83 09 0B FFFFFF84 FFFFFF80 FFFFFF80 FFFFFF88 42 FFFFFF83 0A
   02 0C 57 69 6C 64 63 61 72 64 54 65 73 74 13 05
   FFFFFF83 08 20 16 33 08 07 1B FFFFFF83 08 FFFFFF84 00 FFFFFF83 0C 14 02
   FFFFFF83 07 08 0A 68 FFFFFF83 08 FFFFFF84 FFFFFF80 FFFFFF80 FFFFFF84 22 FFFFFF82 58 08 09
   76 FFFFFF83 08 FFFFFF84 FFFFFF80 FFFFFF80 FFFFFF84 20 77 08 09 7B FFFFFF83 08 FFFFFF84 FFFFFF80
   FFFFFF80 FFFFFF84 20 7C 08 0A 7E FFFFFF83 08 FFFFFF84 FFFFFF80 FFFFFF80 FFFFFF84 20 FFFFFF83 11
   14 03 72 FFFFFF83 12 08 08 71 FFFFFF83 10 FFFFFF81 FFFFFF80 FFFFFFC0 00 64 08
   0B FFFFFF81 02 FFFFFF83 08 FFFFFF84 FFFFFF80 FFFFFF80 FFFFFF84 20 FFFFFF83 14 14 03 6D FFFFFF83
   15 08 08 71 FFFFFF83 13 FFFFFF81 FFFFFF80 FFFFFFC0 00 72 08 0B FFFFFF82 62 FFFFFF83
   08 FFFFFF84 FFFFFF80 FFFFFF80 FFFFFF84 08 FFFFFF82 63 28 04 FFFFFF83 08 FFFFFF81 06 07 09
   FFFFFF83 19 0B FFFFFF81 FFFFFF80 FFFFFF88 02 FFFFFF83 1A 01 08 4E 61 6D 65 54
   65 73 74 10 03 21 FFFFFF83 1B 06 0A FFFFFF82 06 0B FFFFFF84 FFFFFF81 FFFFFF80
   FFFFFF88 02 FFFFFF83 1C 13 06 FFFFFF83 1B 0E FFFFFF83 1D 16 10 06 17 FFFFFF83
   1E 29 FFFFFF82 04 09 03 FFFFFF83 1F 06 02 09 46 75 6E 63 74
   69 6F 6E 31 08 07 1B FFFFFF83 1B FFFFFF84 00 FFFFFF83 21 14 02 FFFFFF83
   1A 08 0A FFFFFF81 2F FFFFFF83 1B FFFFFF81 FFFFFF80 FFFFFF84 40 FFFFFF83 23 14 04 FFFFFF82
   04 FFFFFF83 24 08 07 FFFFFF82 09 FFFFFF83 22 FFFFFFC0 00 29 08 0A FFFFFF81 75
   FFFFFF83 1B FFFFFF81 FFFFFF80 FFFFFF84 40 FFFFFF83 26 14 04 FFFFFF83 27 FFFFFF83 28 10 04
   17 FFFFFF81 78 29 08 08 FFFFFF81 7E FFFFFF83 25 FFFFFFC0 00 FFFFFF82 04 06 0A
   FFFFFF83 2A 0B FFFFFF84 FFFFFF80 FFFFFF80 FFFFFF80 40 FFFFFF83 2B 02 06 45 78 69 73
   74 73 13 06 FFFFFF83 29 FFFFFF81 34 16 33 08 0B FFFFFF83 2D FFFFFF83 29
   FFFFFF82 FFFFFFCA FFFFFF80 FFFFFF84 00 FFFFFF83 2E 01 01 70 15 01 3D 08 0A FFFFFF83
   30 FFFFFF83 29 FFFFFF82 FFFFFF88 FFFFFFA0 FFFFFF80 04 3D 01 02 70 20 08 07 1B
   FFFFFF83 29 FFFFFF84 00 FFFFFF83 32 14 04 FFFFFF83 33 FFFFFF83 34 10 03 21 FFFFFF83
   29 08 07 FFFFFF83 2D FFFFFF83 31 FFFFFFC0 00 3D 08 09 59 FFFFFF83 29 FFFFFF81
   FFFFFF80 FFFFFF84 00 FFFFFF83 36 14 04 FFFFFF83 33 FFFFFF83 37 08 0B FFFFFF83 38 FFFFFF83
   2D FFFFFF83 35 FFFFFF90 FFFFFF80 FFFFFFC0 00 3D 08 09 5D FFFFFF83 29 FFFFFF91 FFFFFF80 FFFFFF84
   00 FFFFFF83 2E 08 09 62 FFFFFF83 29 FFFFFF84 FFFFFF80 FFFFFF80 FFFFFF84 20 63 08 09
   68 FFFFFF83 29 FFFFFF84 FFFFFF80 FFFFFF80 FFFFFF84 20 69 08 0A 6B FFFFFF83 29 FFFFFF84 FFFFFF80
   FFFFFF80 FFFFFF84 20 FFFFFF83 3C 14 03 6D FFFFFF83 3D 08 08 71 FFFFFF83 3B FFFFFF81
   FFFFFF80 FFFFFFC0 00 72 08 09 76 FFFFFF83 29 FFFFFF84 FFFFFF80 FFFFFF80 FFFFFF84 20 77 08
   09 7B FFFFFF83 29 FFFFFF84 FFFFFF80 FFFFFF80 FFFFFF84 20 7C 08 0A 7E FFFFFF83 29 FFFFFF84
   FFFFFF80 FFFFFF80 FFFFFF84 20 FFFFFF83 41 14 03 72 FFFFFF83 42 08 08 71 FFFFFF83 40
   FFFFFF81 FFFFFF80 FFFFFFC0 00 64 08 0B FFFFFF81 02 FFFFFF83 29 FFFFFF84 FFFFFF80 FFFFFF80 FFFFFF84 20
   FFFFFF83 44 14 03 6D FFFFFF83 45 08 08 71 FFFFFF83 43 FFFFFF81 FFFFFF80 FFFFFFC0 00
   72 28 04 FFFFFF83 29 FFFFFF81 06 07 09 FFFFFF83 48 0B FFFFFF81 FFFFFF80 FFFFFF88 02
   FFFFFF83 49 01 06 45 78 69 73 74 73 10 03 21 FFFFFF83 4A 06
   0A FFFFFF83 2A 0B FFFFFF84 FFFFFF81 FFFFFF80 FFFFFF88 02 FFFFFF83 4B 13 06 FFFFFF83 4A 0E
   FFFFFF83 4C 16 10 06 17 FFFFFF83 1E 3D FFFFFF83 33 08 07 1B FFFFFF83 4A
   FFFFFF84 00 FFFFFF83 4E 14 02 FFFFFF83 49 08 0A FFFFFF81 2F FFFFFF83 4A FFFFFF81 FFFFFF80
   FFFFFF84 40 FFFFFF83 50 14 04 FFFFFF83 33 FFFFFF83 51 08 07 FFFFFF83 2D FFFFFF83 4F
   FFFFFFC0 00 3D 08 0A FFFFFF81 75 FFFFFF83 4A FFFFFF81 FFFFFF80 FFFFFF84 40 FFFFFF83 53 14
   04 FFFFFF83 54 FFFFFF83 55 10 04 17 FFFFFF81 78 3D 08 08 FFFFFF81 7E FFFFFF83
   52 FFFFFFC0 00 FFFFFF83 33 06 0A FFFFFF83 57 0B FFFFFF84 FFFFFF80 FFFFFF80 FFFFFF80 40 FFFFFF83
   58 02 06 45 71 75 61 6C 73 13 06 FFFFFF83 56 FFFFFF81 34 16
   33 08 0A FFFFFF83 2D FFFFFF83 56 FFFFFF82 FFFFFFCA FFFFFF80 FFFFFF84 00 38 08 0A FFFFFF83
   30 FFFFFF83 56 FFFFFF82 FFFFFF88 FFFFFFA0 FFFFFF80 04 39 08 0B FFFFFF81 33 FFFFFF83 56 FFFFFF82
   FFFFFFCA FFFFFF80 FFFFFF84 00 FFFFFF82 0A 08 0A FFFFFF81 4A FFFFFF83 56 FFFFFF82 FFFFFF88 FFFFFFA0 FFFFFF80
   04 29 08 07 1B FFFFFF83 56 FFFFFF84 00 FFFFFF83 5E 14 06 FFFFFF83 5F FFFFFF83
   60 FFFFFF83 61 10 03 21 FFFFFF83 56 08 07 FFFFFF83 2D FFFFFF83 5D FFFFFFC0 00
   39 08 07 FFFFFF81 33 FFFFFF83 5D FFFFFFC0 00 29 08 09 59 FFFFFF83 56 FFFFFF81
   FFFFFF80 FFFFFF84 00 FFFFFF83 63 14 06 FFFFFF83 5F FFFFFF83 64 FFFFFF83 66 08 0B FFFFFF83
   65 FFFFFF83 2D FFFFFF83 62 FFFFFF90 FFFFFF80 FFFFFFC0 00 39 08 08 5D FFFFFF83 56 FFFFFF91
   FFFFFF80 FFFFFF84 00 38 08 0B FFFFFF83 67 FFFFFF81 33 FFFFFF83 62 FFFFFF90 FFFFFF80 FFFFFFC0 00
   29 08 09 60 FFFFFF83 56 FFFFFF91 FFFFFF80 FFFFFF84 00 FFFFFF82 0A 08 09 62 FFFFFF83
   56 FFFFFF84 FFFFFF80 FFFFFF80 FFFFFF84 20 63 08 09 68 FFFFFF83 56 FFFFFF84 FFFFFF80 FFFFFF80 FFFFFF84
   20 69 08 0A 6B FFFFFF83 56 FFFFFF84 FFFFFF80 FFFFFF80 FFFFFF84 20 FFFFFF83 6B 14 03
   6D FFFFFF83 6C 08 08 71 FFFFFF83 6A FFFFFF81 FFFFFF80 FFFFFFC0 00 72 08 09 76
   FFFFFF83 56 FFFFFF84 FFFFFF80 FFFFFF80 FFFFFF84 20 77 08 09 7B FFFFFF83 56 FFFFFF84 FFFFFF80 FFFFFF80
   FFFFFF84 20 7C 08 0A 7E FFFFFF83 56 FFFFFF84 FFFFFF80 FFFFFF80 FFFFFF84 20 FFFFFF83 70 14
   03 72 FFFFFF83 71 08 08 71 FFFFFF83 6F FFFFFF81 FFFFFF80 FFFFFFC0 00 64 08 0B
   FFFFFF81 02 FFFFFF83 56 FFFFFF84 FFFFFF80 FFFFFF80 FFFFFF84 20 FFFFFF83 73 14 03 6D FFFFFF83 74
   08 08 71 FFFFFF83 72 FFFFFF81 FFFFFF80 FFFFFFC0 00 72 28 04 FFFFFF83 56 FFFFFF81 06
   07 09 FFFFFF83 77 0B FFFFFF81 FFFFFF80 FFFFFF88 02 FFFFFF83 78 01 06 45 71 75
   61 6C 73 10 03 21 FFFFFF83 79 06 0A FFFFFF83 57 0B FFFFFF84 FFFFFF81 FFFFFF80
   FFFFFF88 02 FFFFFF83 7A 13 06 FFFFFF83 79 0E FFFFFF83 7B 16 10 07 17 FFFFFF81
   6C 39 29 FFFFFF83 5F 08 07 1B FFFFFF83 79 FFFFFF84 00 FFFFFF83 7D 14 02
   FFFFFF83 78 08 0A FFFFFF81 2F FFFFFF83 79 FFFFFF81 FFFFFF80 FFFFFF84 40 FFFFFF83 7F 14 06
   FFFFFF83 5F FFFFFF84 00 FFFFFF84 01 08 07 FFFFFF83 2D FFFFFF83 7E FFFFFFC0 00 39 08
   07 FFFFFF81 33 FFFFFF83 7E FFFFFFC0 00 29 08 0A FFFFFF81 75 FFFFFF83 79 FFFFFF81 FFFFFF80
   FFFFFF84 40 FFFFFF84 03 14 04 FFFFFF84 04 FFFFFF84 06 10 05 17 FFFFFF81 78 FFFFFF84
   05 10 05 17 FFFFFF81 7B 39 29 08 08 FFFFFF81 7E FFFFFF84 02 FFFFFFC0 00
   FFFFFF83 5F 
  InnerClass: 
   public #20= #17 of #19; //FExp=class scala/xml/path/Expression$FExp of class scala/xml/path/Expression
   public abstract #23= #22 of #19; //Expr=class scala/xml/path/Expression$Expr of class scala/xml/path/Expression
   public abstract #26= #25 of #19; //Test=class scala/xml/path/Expression$Test of class scala/xml/path/Expression
   public abstract #29= #28 of #19; //Cond=class scala/xml/path/Expression$Cond of class scala/xml/path/Expression
   public #32= #31 of #19; //Child=class scala/xml/path/Expression$Child of class scala/xml/path/Expression
   public #35= #34 of #19; //Attrib=class scala/xml/path/Expression$Attrib of class scala/xml/path/Expression
   public #38= #37 of #19; //Exists=class scala/xml/path/Expression$Exists of class scala/xml/path/Expression
   public abstract #41= #40 of #19; //GenExp=class scala/xml/path/Expression$GenExp of class scala/xml/path/Expression
   public #44= #43 of #19; //Equals=class scala/xml/path/Expression$Equals of class scala/xml/path/Expression
   public #47= #46 of #19; //NameTest=class scala/xml/path/Expression$NameTest of class scala/xml/path/Expression
   public #50= #49 of #19; //DescOrSelf=class scala/xml/path/Expression$DescOrSelf of class scala/xml/path/Expression
  minor version: 0
  major version: 49
  Constant pool:
const #1 = Asciz	SourceFile;
const #2 = Asciz	Expression.scala;
const #3 = Asciz	testFromString;
const #4 = Asciz	(Ljava/lang/String;)Lscala/xml/path/Expression$Test;;
const #5 = Asciz	Code;
const #6 = Asciz	scala/xml/path/Expression$;
const #7 = class	#6;	//  scala/xml/path/Expression$
const #8 = Asciz	MODULE$;
const #9 = Asciz	Lscala/xml/path/Expression$;;
const #10 = NameAndType	#8:#9;//  MODULE$:Lscala/xml/path/Expression$;
const #11 = Field	#7.#10;	//  scala/xml/path/Expression$.MODULE$:Lscala/xml/path/Expression$;
const #12 = NameAndType	#3:#4;//  testFromString:(Ljava/lang/String;)Lscala/xml/path/Expression$Test;
const #13 = Method	#7.#12;	//  scala/xml/path/Expression$.testFromString:(Ljava/lang/String;)Lscala/xml/path/Expression$Test;
const #14 = Asciz	ScalaSig;
const #15 = Asciz	InnerClasses;
const #16 = Asciz	scala/xml/path/Expression$FExp;
const #17 = class	#16;	//  scala/xml/path/Expression$FExp
const #18 = Asciz	scala/xml/path/Expression;
const #19 = class	#18;	//  scala/xml/path/Expression
const #20 = Asciz	FExp;
const #21 = Asciz	scala/xml/path/Expression$Expr;
const #22 = class	#21;	//  scala/xml/path/Expression$Expr
const #23 = Asciz	Expr;
const #24 = Asciz	scala/xml/path/Expression$Test;
const #25 = class	#24;	//  scala/xml/path/Expression$Test
const #26 = Asciz	Test;
const #27 = Asciz	scala/xml/path/Expression$Cond;
const #28 = class	#27;	//  scala/xml/path/Expression$Cond
const #29 = Asciz	Cond;
const #30 = Asciz	scala/xml/path/Expression$Child;
const #31 = class	#30;	//  scala/xml/path/Expression$Child
const #32 = Asciz	Child;
const #33 = Asciz	scala/xml/path/Expression$Attrib;
const #34 = class	#33;	//  scala/xml/path/Expression$Attrib
const #35 = Asciz	Attrib;
const #36 = Asciz	scala/xml/path/Expression$Exists;
const #37 = class	#36;	//  scala/xml/path/Expression$Exists
const #38 = Asciz	Exists;
const #39 = Asciz	scala/xml/path/Expression$GenExp;
const #40 = class	#39;	//  scala/xml/path/Expression$GenExp
const #41 = Asciz	GenExp;
const #42 = Asciz	scala/xml/path/Expression$Equals;
const #43 = class	#42;	//  scala/xml/path/Expression$Equals
const #44 = Asciz	Equals;
const #45 = Asciz	scala/xml/path/Expression$NameTest;
const #46 = class	#45;	//  scala/xml/path/Expression$NameTest
const #47 = Asciz	NameTest;
const #48 = Asciz	scala/xml/path/Expression$DescOrSelf;
const #49 = class	#48;	//  scala/xml/path/Expression$DescOrSelf
const #50 = Asciz	DescOrSelf;
const #51 = Asciz	java/lang/Object;
const #52 = class	#51;	//  java/lang/Object

{
public static final scala.xml.path.Expression$Test testFromString(java.lang.String);
  Code:
   Stack=2, Locals=1, Args_size=1
   0:	getstatic	#11; //Field scala/xml/path/Expression$.MODULE$:Lscala/xml/path/Expression$;
   3:	aload_0
   4:	invokevirtual	#13; //Method scala/xml/path/Expression$.testFromString:(Ljava/lang/String;)Lscala/xml/path/Expression$Test;
   7:	areturn

}

