Compiled from "Expression.scala"
public final class scala.xml.path.Expression$FExp$$anon$1 extends scala.xml.NodeSeq
  SourceFile: "Expression.scala"
  Scala: length = 0x
   
  InnerClass: 
   public #38= #35 of #37; //FExp=class scala/xml/path/Expression$FExp of class scala/xml/path/Expression
   public final #39= #20 of #35; //$anon$1=class scala/xml/path/Expression$FExp$$anon$1 of class scala/xml/path/Expression$FExp
  minor version: 0
  major version: 49
  Constant pool:
const #1 = Asciz	SourceFile;
const #2 = Asciz	Expression.scala;
const #3 = Asciz	theSeq;
const #4 = Asciz	Lscala/collection/immutable/Nil$;;
const #5 = Asciz	<init>;
const #6 = Asciz	(Lscala/xml/path/Expression$FExp;)V;
const #7 = Asciz	Code;
const #8 = Asciz	LineNumberTable;
const #9 = Asciz	scala/xml/NodeSeq;
const #10 = class	#9;	//  scala/xml/NodeSeq
const #11 = Asciz	()V;
const #12 = NameAndType	#5:#11;//  "<init>":()V
const #13 = Method	#10.#12;	//  scala/xml/NodeSeq."<init>":()V
const #14 = Asciz	scala/collection/immutable/Nil$;
const #15 = class	#14;	//  scala/collection/immutable/Nil$
const #16 = Asciz	MODULE$;
const #17 = NameAndType	#16:#4;//  MODULE$:Lscala/collection/immutable/Nil$;
const #18 = Field	#15.#17;	//  scala/collection/immutable/Nil$.MODULE$:Lscala/collection/immutable/Nil$;
const #19 = Asciz	scala/xml/path/Expression$FExp$$anon$1;
const #20 = class	#19;	//  scala/xml/path/Expression$FExp$$anon$1
const #21 = NameAndType	#3:#4;//  theSeq:Lscala/collection/immutable/Nil$;
const #22 = Field	#20.#21;	//  scala/xml/path/Expression$FExp$$anon$1.theSeq:Lscala/collection/immutable/Nil$;
const #23 = Asciz	this;
const #24 = Asciz	Lscala/xml/path/Expression$FExp$$anon$1;;
const #25 = Asciz	$outer;
const #26 = Asciz	Lscala/xml/path/Expression$FExp;;
const #27 = Asciz	LocalVariableTable;
const #28 = Asciz	()Lscala/collection/Sequence;;
const #29 = Asciz	()Lscala/collection/immutable/Nil$;;
const #30 = NameAndType	#3:#29;//  theSeq:()Lscala/collection/immutable/Nil$;
const #31 = Method	#20.#30;	//  scala/xml/path/Expression$FExp$$anon$1.theSeq:()Lscala/collection/immutable/Nil$;
const #32 = Asciz	Scala;
const #33 = Asciz	InnerClasses;
const #34 = Asciz	scala/xml/path/Expression$FExp;
const #35 = class	#34;	//  scala/xml/path/Expression$FExp
const #36 = Asciz	scala/xml/path/Expression;
const #37 = class	#36;	//  scala/xml/path/Expression
const #38 = Asciz	FExp;
const #39 = Asciz	$anon$1;

{
public scala.xml.path.Expression$FExp$$anon$1(scala.xml.path.Expression$FExp);
  Code:
   Stack=2, Locals=2, Args_size=2
   0:	aload_0
   1:	invokespecial	#13; //Method scala/xml/NodeSeq."<init>":()V
   4:	aload_0
   5:	getstatic	#18; //Field scala/collection/immutable/Nil$.MODULE$:Lscala/collection/immutable/Nil$;
   8:	putfield	#22; //Field theSeq:Lscala/collection/immutable/Nil$;
   11:	return
  LineNumberTable: 
   line 25: 0

  LocalVariableTable: 
   Start  Length  Slot  Name   Signature
   0      12      0    this       Lscala/xml/path/Expression$FExp$$anon$1;
   0      12      1    $outer       Lscala/xml/path/Expression$FExp;


public scala.collection.Sequence theSeq();
  Code:
   Stack=1, Locals=1, Args_size=1
   0:	aload_0
   1:	invokevirtual	#31; //Method theSeq:()Lscala/collection/immutable/Nil$;
   4:	areturn
  LineNumberTable: 
   line 25: 0


public scala.collection.immutable.Nil$ theSeq();
  Code:
   Stack=1, Locals=1, Args_size=1
   0:	aload_0
   1:	getfield	#22; //Field theSeq:Lscala/collection/immutable/Nil$;
   4:	areturn
  LineNumberTable: 
   line 25: 0


}

