Compiled from "Expression.scala"
public final class scala.xml.path.Expression$FExp$ extends java.lang.Object implements scala.Function2,scala.ScalaObject
  SourceFile: "Expression.scala"
  Scala: length = 0x
   
  InnerClass: 
   public abstract #82= #29 of #81; //Expr=class scala/xml/path/Expression$Expr of class scala/xml/path/Expression
   public #83= #41 of #81; //FExp=class scala/xml/path/Expression$FExp of class scala/xml/path/Expression
   public abstract #84= #31 of #81; //Cond=class scala/xml/path/Expression$Cond of class scala/xml/path/Expression
   public final #87= #86 of #41; //$anon$1=class scala/xml/path/Expression$FExp$$anon$1 of class scala/xml/path/Expression$FExp
  minor version: 0
  major version: 49
  Constant pool:
const #1 = Asciz	SourceFile;
const #2 = Asciz	Expression.scala;
const #3 = Asciz	Scala;
const #4 = Asciz	MODULE$;
const #5 = Asciz	Lscala/xml/path/Expression$FExp$;;
const #6 = Asciz	<clinit>;
const #7 = Asciz	()V;
const #8 = Asciz	Code;
const #9 = Asciz	scala/xml/path/Expression$FExp$;
const #10 = class	#9;	//  scala/xml/path/Expression$FExp$
const #11 = Asciz	<init>;
const #12 = NameAndType	#11:#7;//  "<init>":()V
const #13 = Method	#10.#12;	//  scala/xml/path/Expression$FExp$."<init>":()V
const #14 = Asciz	LineNumberTable;
const #15 = Asciz	java/lang/Object;
const #16 = class	#15;	//  java/lang/Object
const #17 = Method	#16.#12;	//  java/lang/Object."<init>":()V
const #18 = NameAndType	#4:#5;//  MODULE$:Lscala/xml/path/Expression$FExp$;
const #19 = Field	#10.#18;	//  scala/xml/path/Expression$FExp$.MODULE$:Lscala/xml/path/Expression$FExp$;
const #20 = Asciz	scala/Function2$class;
const #21 = class	#20;	//  scala/Function2$class
const #22 = Asciz	$init$;
const #23 = Asciz	(Lscala/Function2;)V;
const #24 = NameAndType	#22:#23;//  $init$:(Lscala/Function2;)V
const #25 = Method	#21.#24;	//  scala/Function2$class.$init$:(Lscala/Function2;)V
const #26 = Asciz	apply;
const #27 = Asciz	(Ljava/lang/Object;Ljava/lang/Object;)Ljava/lang/Object;;
const #28 = Asciz	scala/xml/path/Expression$Expr;
const #29 = class	#28;	//  scala/xml/path/Expression$Expr
const #30 = Asciz	scala/xml/path/Expression$Cond;
const #31 = class	#30;	//  scala/xml/path/Expression$Cond
const #32 = Asciz	(Lscala/xml/path/Expression$Expr;Lscala/xml/path/Expression$Cond;)Lscala/xml/path/Expression$FExp;;
const #33 = NameAndType	#26:#32;//  apply:(Lscala/xml/path/Expression$Expr;Lscala/xml/path/Expression$Cond;)Lscala/xml/path/Expression$FExp;
const #34 = Method	#10.#33;	//  scala/xml/path/Expression$FExp$.apply:(Lscala/xml/path/Expression$Expr;Lscala/xml/path/Expression$Cond;)Lscala/xml/path/Expression$FExp;
const #35 = Asciz	this;
const #36 = Asciz	v1;
const #37 = Asciz	Ljava/lang/Object;;
const #38 = Asciz	v2;
const #39 = Asciz	LocalVariableTable;
const #40 = Asciz	scala/xml/path/Expression$FExp;
const #41 = class	#40;	//  scala/xml/path/Expression$FExp
const #42 = Asciz	(Lscala/xml/path/Expression$Expr;Lscala/xml/path/Expression$Cond;)V;
const #43 = NameAndType	#11:#42;//  "<init>":(Lscala/xml/path/Expression$Expr;Lscala/xml/path/Expression$Cond;)V
const #44 = Method	#41.#43;	//  scala/xml/path/Expression$FExp."<init>":(Lscala/xml/path/Expression$Expr;Lscala/xml/path/Expression$Cond;)V
const #45 = Asciz	e;
const #46 = Asciz	Lscala/xml/path/Expression$Expr;;
const #47 = Asciz	c;
const #48 = Asciz	Lscala/xml/path/Expression$Cond;;
const #49 = Asciz	unapply;
const #50 = Asciz	(Lscala/xml/path/Expression$FExp;)Lscala/Some;;
const #51 = Asciz	scala/Some;
const #52 = class	#51;	//  scala/Some
const #53 = Asciz	scala/Tuple2;
const #54 = class	#53;	//  scala/Tuple2
const #55 = Asciz	()Lscala/xml/path/Expression$Expr;;
const #56 = NameAndType	#45:#55;//  e:()Lscala/xml/path/Expression$Expr;
const #57 = Method	#41.#56;	//  scala/xml/path/Expression$FExp.e:()Lscala/xml/path/Expression$Expr;
const #58 = Asciz	()Lscala/xml/path/Expression$Cond;;
const #59 = NameAndType	#47:#58;//  c:()Lscala/xml/path/Expression$Cond;
const #60 = Method	#41.#59;	//  scala/xml/path/Expression$FExp.c:()Lscala/xml/path/Expression$Cond;
const #61 = Asciz	(Ljava/lang/Object;Ljava/lang/Object;)V;
const #62 = NameAndType	#11:#61;//  "<init>":(Ljava/lang/Object;Ljava/lang/Object;)V
const #63 = Method	#54.#62;	//  scala/Tuple2."<init>":(Ljava/lang/Object;Ljava/lang/Object;)V
const #64 = Asciz	(Ljava/lang/Object;)V;
const #65 = NameAndType	#11:#64;//  "<init>":(Ljava/lang/Object;)V
const #66 = Method	#52.#65;	//  scala/Some."<init>":(Ljava/lang/Object;)V
const #67 = Asciz	x$0;
const #68 = Asciz	Lscala/xml/path/Expression$FExp;;
const #69 = Asciz	curry;
const #70 = Asciz	()Lscala/Function1;;
const #71 = Asciz	(Lscala/Function2;)Lscala/Function1;;
const #72 = NameAndType	#69:#71;//  curry:(Lscala/Function2;)Lscala/Function1;
const #73 = Method	#21.#72;	//  scala/Function2$class.curry:(Lscala/Function2;)Lscala/Function1;
const #74 = Asciz	toString;
const #75 = Asciz	()Ljava/lang/String;;
const #76 = Asciz	(Lscala/Function2;)Ljava/lang/String;;
const #77 = NameAndType	#74:#76;//  toString:(Lscala/Function2;)Ljava/lang/String;
const #78 = Method	#21.#77;	//  scala/Function2$class.toString:(Lscala/Function2;)Ljava/lang/String;
const #79 = Asciz	InnerClasses;
const #80 = Asciz	scala/xml/path/Expression;
const #81 = class	#80;	//  scala/xml/path/Expression
const #82 = Asciz	Expr;
const #83 = Asciz	FExp;
const #84 = Asciz	Cond;
const #85 = Asciz	scala/xml/path/Expression$FExp$$anon$1;
const #86 = class	#85;	//  scala/xml/path/Expression$FExp$$anon$1
const #87 = Asciz	$anon$1;
const #88 = Asciz	scala/Function2;
const #89 = class	#88;	//  scala/Function2
const #90 = Asciz	scala/ScalaObject;
const #91 = class	#90;	//  scala/ScalaObject

{
public static final scala.xml.path.Expression$FExp$ MODULE$;

public static {};
  Code:
   Stack=1, Locals=0, Args_size=0
   0:	new	#10; //class scala/xml/path/Expression$FExp$
   3:	invokespecial	#13; //Method "<init>":()V
   6:	return

public scala.xml.path.Expression$FExp$();
  Code:
   Stack=1, Locals=1, Args_size=1
   0:	aload_0
   1:	invokespecial	#17; //Method java/lang/Object."<init>":()V
   4:	aload_0
   5:	putstatic	#19; //Field MODULE$:Lscala/xml/path/Expression$FExp$;
   8:	aload_0
   9:	invokestatic	#25; //Method scala/Function2$class.$init$:(Lscala/Function2;)V
   12:	return
  LineNumberTable: 
   line 24: 0


public java.lang.Object apply(java.lang.Object, java.lang.Object);
  Code:
   Stack=3, Locals=3, Args_size=3
   0:	aload_0
   1:	aload_1
   2:	checkcast	#29; //class scala/xml/path/Expression$Expr
   5:	aload_2
   6:	checkcast	#31; //class scala/xml/path/Expression$Cond
   9:	invokevirtual	#34; //Method apply:(Lscala/xml/path/Expression$Expr;Lscala/xml/path/Expression$Cond;)Lscala/xml/path/Expression$FExp;
   12:	areturn
  LineNumberTable: 
   line 24: 0

  LocalVariableTable: 
   Start  Length  Slot  Name   Signature
   0      13      0    this       Lscala/xml/path/Expression$FExp$;
   0      13      1    v1       Ljava/lang/Object;
   0      13      2    v2       Ljava/lang/Object;


public scala.xml.path.Expression$FExp apply(scala.xml.path.Expression$Expr, scala.xml.path.Expression$Cond);
  Code:
   Stack=4, Locals=3, Args_size=3
   0:	new	#41; //class scala/xml/path/Expression$FExp
   3:	dup
   4:	aload_1
   5:	aload_2
   6:	invokespecial	#44; //Method scala/xml/path/Expression$FExp."<init>":(Lscala/xml/path/Expression$Expr;Lscala/xml/path/Expression$Cond;)V
   9:	areturn
  LineNumberTable: 
   line 24: 0

  LocalVariableTable: 
   Start  Length  Slot  Name   Signature
   0      10      0    this       Lscala/xml/path/Expression$FExp$;
   0      10      1    e       Lscala/xml/path/Expression$Expr;
   0      10      2    c       Lscala/xml/path/Expression$Cond;


public scala.Some unapply(scala.xml.path.Expression$FExp);
  Code:
   Stack=6, Locals=2, Args_size=2
   0:	new	#52; //class scala/Some
   3:	dup
   4:	new	#54; //class scala/Tuple2
   7:	dup
   8:	aload_1
   9:	invokevirtual	#57; //Method scala/xml/path/Expression$FExp.e:()Lscala/xml/path/Expression$Expr;
   12:	aload_1
   13:	invokevirtual	#60; //Method scala/xml/path/Expression$FExp.c:()Lscala/xml/path/Expression$Cond;
   16:	invokespecial	#63; //Method scala/Tuple2."<init>":(Ljava/lang/Object;Ljava/lang/Object;)V
   19:	invokespecial	#66; //Method scala/Some."<init>":(Ljava/lang/Object;)V
   22:	areturn
  LineNumberTable: 
   line 24: 0

  LocalVariableTable: 
   Start  Length  Slot  Name   Signature
   0      23      0    this       Lscala/xml/path/Expression$FExp$;
   0      23      1    x$0       Lscala/xml/path/Expression$FExp;


public scala.Function1 curry();
  Code:
   Stack=1, Locals=1, Args_size=1
   0:	aload_0
   1:	invokestatic	#73; //Method scala/Function2$class.curry:(Lscala/Function2;)Lscala/Function1;
   4:	areturn
  LineNumberTable: 
   line 24: 0


public java.lang.String toString();
  Code:
   Stack=1, Locals=1, Args_size=1
   0:	aload_0
   1:	invokestatic	#78; //Method scala/Function2$class.toString:(Lscala/Function2;)Ljava/lang/String;
   4:	areturn
  LineNumberTable: 
   line 24: 0


}

