Compiled from "Expression.scala"
public abstract class scala.xml.path.Expression$GenExp extends java.lang.Object implements scala.ScalaObject
  SourceFile: "Expression.scala"
  Scala: length = 0x
   
  InnerClass: 
   public abstract #17= #14 of #16; //GenExp=class scala/xml/path/Expression$GenExp of class scala/xml/path/Expression
  minor version: 0
  major version: 49
  Constant pool:
const #1 = Asciz	SourceFile;
const #2 = Asciz	Expression.scala;
const #3 = Asciz	<init>;
const #4 = Asciz	()V;
const #5 = Asciz	Code;
const #6 = Asciz	LineNumberTable;
const #7 = Asciz	java/lang/Object;
const #8 = class	#7;	//  java/lang/Object
const #9 = NameAndType	#3:#4;//  "<init>":()V
const #10 = Method	#8.#9;	//  java/lang/Object."<init>":()V
const #11 = Asciz	Scala;
const #12 = Asciz	InnerClasses;
const #13 = Asciz	scala/xml/path/Expression$GenExp;
const #14 = class	#13;	//  scala/xml/path/Expression$GenExp
const #15 = Asciz	scala/xml/path/Expression;
const #16 = class	#15;	//  scala/xml/path/Expression
const #17 = Asciz	GenExp;
const #18 = Asciz	scala/ScalaObject;
const #19 = class	#18;	//  scala/ScalaObject

{
public scala.xml.path.Expression$GenExp();
  Code:
   Stack=1, Locals=1, Args_size=1
   0:	aload_0
   1:	invokespecial	#10; //Method java/lang/Object."<init>":()V
   4:	return
  LineNumberTable: 
   line 28: 0


}

