Compiled from "StandardTokenParsers.scala"
public class scala.util.parsing.combinator.syntactical.StandardTokenParsers extends java.lang.Object implements scala.util.parsing.combinator.syntactical.StdTokenParsers,scala.ScalaObject
  SourceFile: "StandardTokenParsers.scala"
  ScalaSig: length = 0x1BA
   05 00 46 06 08 01 02 FFFFFF84 FFFFFF80 FFFFFF80 FFFFFF80 00 0D 02 14 53
   74 61 6E 64 61 72 64 54 6F 6B 65 6E 50 61 72 73
   65 72 73 0A 02 03 04 01 0B 73 79 6E 74 61 63 74
   69 63 61 6C 0A 02 05 06 01 0A 63 6F 6D 62 69 6E
   61 74 6F 72 0A 02 07 08 01 07 70 61 72 73 69 6E
   67 0A 02 09 0A 01 04 75 74 69 6C 0A 01 0B 01 05
   73 63 61 6C 61 03 00 13 04 00 0E 16 1A 10 02 0F
   14 0D 01 10 0A 02 11 12 01 04 6C 61 6E 67 0A 01
   13 01 04 6A 61 76 61 09 02 15 10 02 06 4F 62 6A
   65 63 74 10 02 17 18 0D 01 02 09 02 19 02 02 0F
   53 74 64 54 6F 6B 65 6E 50 61 72 73 65 72 73 10
   02 1B 1C 0D 01 0A 09 02 1D 0A 02 0B 53 63 61 6C
   61 4F 62 6A 65 63 74 08 05 1F 00 FFFFFF84 00 20 01 06
   3C 69 6E 69 74 3E 14 01 21 10 02 17 00 05 08 23
   00 FFFFFF84 FFFFFF80 FFFFFF80 FFFFFF80 00 24 02 06 54 6F 6B 65 6E 73 10
   02 25 28 0D 01 26 0A 02 27 06 01 06 73 79 6E 74
   61 78 09 02 29 26 02 09 53 74 64 54 6F 6B 65 6E
   73 08 07 2B 00 FFFFFFC2 FFFFFF80 FFFFFF84 00 2C 01 07 6C 65 78 69
   63 61 6C 15 01 2D 10 02 2E 30 0D 01 2F 0A 02 2B
   04 09 02 31 2F 02 0A 53 74 64 4C 65 78 69 63 61
   6C 08 06 33 00 FFFFFFA0 FFFFFF80 04 2D 01 08 6C 65 78 69 63
   61 6C 20 08 05 35 00 FFFFFF84 21 36 01 07 6B 65 79 77
   6F 72 64 14 02 37 44 10 03 38 39 3D 0D 01 00 09
   02 3A 3B 02 06 50 61 72 73 65 72 09 02 3C 04 02
   07 50 61 72 73 65 72 73 10 02 3E 41 0E 02 1B 3F
   09 02 40 0A 01 06 50 72 65 64 65 66 09 02 42 43
   02 06 53 74 72 69 6E 67 0A 02 40 0A 08 05 45 34
   FFFFFFC0 00 3D 01 05 63 68 61 72 73 
  InnerClass: 
   public abstract Parser=class scala/util/parsing/combinator/Parsers$Parser of class scala/util/parsing/combinator/Parsers
   public abstract NoSuccess=class scala/util/parsing/combinator/Parsers$NoSuccess of class scala/util/parsing/combinator/Parsers
   public abstract OnceParser=class scala/util/parsing/combinator/Parsers$OnceParser of class scala/util/parsing/combinator/Parsers
  minor version: 0
  major version: 49
  Constant pool:
Asciz	SourceFile;
Asciz	StandardTokenParsers.scala;
Asciz	$tilde$module;
Asciz	Lscala/util/parsing/combinator/Parsers$$tilde$;;
Asciz	Error$module;
Asciz	Lscala/util/parsing/combinator/Parsers$Error$;;
Asciz	Failure$module;
Asciz	Lscala/util/parsing/combinator/Parsers$Failure$;;
Asciz	NoSuccess$module;
Asciz	Lscala/util/parsing/combinator/Parsers$NoSuccess$;;
Asciz	Success$module;
Asciz	Lscala/util/parsing/combinator/Parsers$Success$;;
Asciz	lastNoSuccess;
Asciz	Lscala/util/parsing/combinator/Parsers$NoSuccess;;
Asciz	keywordCache;
Asciz	Lscala/collection/mutable/HashMap;;
Asciz	lexical;
Asciz	Lscala/util/parsing/combinator/lexical/StdLexical;;
Asciz	()Lscala/collection/mutable/HashMap;;
Asciz	Code;
Asciz	LineNumberTable;
Asciz	scala/util/parsing/combinator/syntactical/StandardTokenParsers;
class	scala/util/parsing/combinator/syntactical/StandardTokenParsers
NameAndType	keywordCache:Lscala/collection/mutable/HashMap;
Field	scala/util/parsing/combinator/syntactical/StandardTokenParsers.keywordCache:Lscala/collection/mutable/HashMap;
Asciz	scala$util$parsing$combinator$syntactical$StdTokenParsers$_setter_$keywordCache_$eq;
Asciz	(Lscala/collection/mutable/HashMap;)V;
Asciz	numericLit;
Asciz	()Lscala/util/parsing/combinator/Parsers$Parser;;
Asciz	scala/util/parsing/combinator/syntactical/StdTokenParsers$class;
class	scala/util/parsing/combinator/syntactical/StdTokenParsers$class
Asciz	(Lscala/util/parsing/combinator/syntactical/StdTokenParsers;)Lscala/util/parsing/combinator/Parsers$Parser;;
NameAndType	numericLit:(Lscala/util/parsing/combinator/syntactical/StdTokenParsers;)Lscala/util/parsing/combinator/Parsers$Parser;
Method	scala/util/parsing/combinator/syntactical/StdTokenParsers$class.numericLit:(Lscala/util/parsing/combinator/syntactical/StdTokenParsers;)Lscala/util/parsing/combinator/Parsers$Parser;
Asciz	stringLit;
NameAndType	stringLit:(Lscala/util/parsing/combinator/syntactical/StdTokenParsers;)Lscala/util/parsing/combinator/Parsers$Parser;
Method	scala/util/parsing/combinator/syntactical/StdTokenParsers$class.stringLit:(Lscala/util/parsing/combinator/syntactical/StdTokenParsers;)Lscala/util/parsing/combinator/Parsers$Parser;
Asciz	ident;
NameAndType	ident:(Lscala/util/parsing/combinator/syntactical/StdTokenParsers;)Lscala/util/parsing/combinator/Parsers$Parser;
Method	scala/util/parsing/combinator/syntactical/StdTokenParsers$class.ident:(Lscala/util/parsing/combinator/syntactical/StdTokenParsers;)Lscala/util/parsing/combinator/Parsers$Parser;
Asciz	Success;
Asciz	()Lscala/util/parsing/combinator/Parsers$Success$;;
NameAndType	Success$module:Lscala/util/parsing/combinator/Parsers$Success$;
Field	scala/util/parsing/combinator/syntactical/StandardTokenParsers.Success$module:Lscala/util/parsing/combinator/Parsers$Success$;
Asciz	scala/util/parsing/combinator/Parsers$Success$;
class	scala/util/parsing/combinator/Parsers$Success$
Asciz	<init>;
Asciz	(Lscala/util/parsing/combinator/Parsers;)V;
NameAndType	"<init>":(Lscala/util/parsing/combinator/Parsers;)V
Method	scala/util/parsing/combinator/Parsers$Success$."<init>":(Lscala/util/parsing/combinator/Parsers;)V
Asciz	()Lscala/util/parsing/combinator/Parsers$NoSuccess;;
NameAndType	lastNoSuccess:Lscala/util/parsing/combinator/Parsers$NoSuccess;
Field	scala/util/parsing/combinator/syntactical/StandardTokenParsers.lastNoSuccess:Lscala/util/parsing/combinator/Parsers$NoSuccess;
Asciz	lastNoSuccess_$eq;
Asciz	(Lscala/util/parsing/combinator/Parsers$NoSuccess;)V;
Asciz	NoSuccess;
Asciz	()Lscala/util/parsing/combinator/Parsers$NoSuccess$;;
NameAndType	NoSuccess$module:Lscala/util/parsing/combinator/Parsers$NoSuccess$;
Field	scala/util/parsing/combinator/syntactical/StandardTokenParsers.NoSuccess$module:Lscala/util/parsing/combinator/Parsers$NoSuccess$;
Asciz	scala/util/parsing/combinator/Parsers$NoSuccess$;
class	scala/util/parsing/combinator/Parsers$NoSuccess$
Method	scala/util/parsing/combinator/Parsers$NoSuccess$."<init>":(Lscala/util/parsing/combinator/Parsers;)V
Asciz	Failure;
Asciz	()Lscala/util/parsing/combinator/Parsers$Failure$;;
NameAndType	Failure$module:Lscala/util/parsing/combinator/Parsers$Failure$;
Field	scala/util/parsing/combinator/syntactical/StandardTokenParsers.Failure$module:Lscala/util/parsing/combinator/Parsers$Failure$;
Asciz	scala/util/parsing/combinator/Parsers$Failure$;
class	scala/util/parsing/combinator/Parsers$Failure$
Method	scala/util/parsing/combinator/Parsers$Failure$."<init>":(Lscala/util/parsing/combinator/Parsers;)V
Asciz	Error;
Asciz	()Lscala/util/parsing/combinator/Parsers$Error$;;
NameAndType	Error$module:Lscala/util/parsing/combinator/Parsers$Error$;
Field	scala/util/parsing/combinator/syntactical/StandardTokenParsers.Error$module:Lscala/util/parsing/combinator/Parsers$Error$;
Asciz	scala/util/parsing/combinator/Parsers$Error$;
class	scala/util/parsing/combinator/Parsers$Error$
Method	scala/util/parsing/combinator/Parsers$Error$."<init>":(Lscala/util/parsing/combinator/Parsers;)V
Asciz	$tilde;
Asciz	()Lscala/util/parsing/combinator/Parsers$$tilde$;;
NameAndType	$tilde$module:Lscala/util/parsing/combinator/Parsers$$tilde$;
Field	scala/util/parsing/combinator/syntactical/StandardTokenParsers.$tilde$module:Lscala/util/parsing/combinator/Parsers$$tilde$;
Asciz	scala/util/parsing/combinator/Parsers$$tilde$;
class	scala/util/parsing/combinator/Parsers$$tilde$
Method	scala/util/parsing/combinator/Parsers$$tilde$."<init>":(Lscala/util/parsing/combinator/Parsers;)V
Asciz	Parser;
Asciz	(Lscala/Function1;)Lscala/util/parsing/combinator/Parsers$Parser;;
Asciz	scala/util/parsing/combinator/Parsers$class;
class	scala/util/parsing/combinator/Parsers$class
Asciz	(Lscala/util/parsing/combinator/Parsers;Lscala/Function1;)Lscala/util/parsing/combinator/Parsers$Parser;;
NameAndType	Parser:(Lscala/util/parsing/combinator/Parsers;Lscala/Function1;)Lscala/util/parsing/combinator/Parsers$Parser;
Method	scala/util/parsing/combinator/Parsers$class.Parser:(Lscala/util/parsing/combinator/Parsers;Lscala/Function1;)Lscala/util/parsing/combinator/Parsers$Parser;
Asciz	this;
Asciz	Lscala/util/parsing/combinator/syntactical/StandardTokenParsers;;
Asciz	f;
Asciz	Lscala/Function1;;
Asciz	LocalVariableTable;
Asciz	OnceParser;
Asciz	(Lscala/Function1;)Lscala/util/parsing/combinator/Parsers$OnceParser;;
Asciz	(Lscala/util/parsing/combinator/Parsers;Lscala/Function1;)Lscala/util/parsing/combinator/Parsers$OnceParser;;
NameAndType	OnceParser:(Lscala/util/parsing/combinator/Parsers;Lscala/Function1;)Lscala/util/parsing/combinator/Parsers$OnceParser;
Method	scala/util/parsing/combinator/Parsers$class.OnceParser:(Lscala/util/parsing/combinator/Parsers;Lscala/Function1;)Lscala/util/parsing/combinator/Parsers$OnceParser;
Asciz	commit;
Asciz	(Lscala/Function0;)Lscala/util/parsing/combinator/Parsers$Parser;;
Asciz	(Lscala/util/parsing/combinator/Parsers;Lscala/Function0;)Lscala/util/parsing/combinator/Parsers$Parser;;
NameAndType	commit:(Lscala/util/parsing/combinator/Parsers;Lscala/Function0;)Lscala/util/parsing/combinator/Parsers$Parser;
Method	scala/util/parsing/combinator/Parsers$class.commit:(Lscala/util/parsing/combinator/Parsers;Lscala/Function0;)Lscala/util/parsing/combinator/Parsers$Parser;
Asciz	p;
Asciz	Lscala/Function0;;
Asciz	elem;
Asciz	(Ljava/lang/String;Lscala/Function1;)Lscala/util/parsing/combinator/Parsers$Parser;;
Asciz	(Lscala/util/parsing/combinator/Parsers;Ljava/lang/String;Lscala/Function1;)Lscala/util/parsing/combinator/Parsers$Parser;;
NameAndType	elem:(Lscala/util/parsing/combinator/Parsers;Ljava/lang/String;Lscala/Function1;)Lscala/util/parsing/combinator/Parsers$Parser;
Method	scala/util/parsing/combinator/Parsers$class.elem:(Lscala/util/parsing/combinator/Parsers;Ljava/lang/String;Lscala/Function1;)Lscala/util/parsing/combinator/Parsers$Parser;
Asciz	kind;
Asciz	Ljava/lang/String;;
Asciz	(Ljava/lang/Object;)Lscala/util/parsing/combinator/Parsers$Parser;;
Asciz	(Lscala/util/parsing/combinator/Parsers;Ljava/lang/Object;)Lscala/util/parsing/combinator/Parsers$Parser;;
NameAndType	elem:(Lscala/util/parsing/combinator/Parsers;Ljava/lang/Object;)Lscala/util/parsing/combinator/Parsers$Parser;
Method	scala/util/parsing/combinator/Parsers$class.elem:(Lscala/util/parsing/combinator/Parsers;Ljava/lang/Object;)Lscala/util/parsing/combinator/Parsers$Parser;
Asciz	e;
Asciz	Ljava/lang/Object;;
Asciz	accept;
NameAndType	accept:(Lscala/util/parsing/combinator/Parsers;Ljava/lang/Object;)Lscala/util/parsing/combinator/Parsers$Parser;
Method	scala/util/parsing/combinator/Parsers$class.accept:(Lscala/util/parsing/combinator/Parsers;Ljava/lang/Object;)Lscala/util/parsing/combinator/Parsers$Parser;
Asciz	(Ljava/lang/Object;Lscala/Function1;)Lscala/util/parsing/combinator/Parsers$Parser;;
Asciz	(Lscala/util/parsing/combinator/Parsers;Ljava/lang/Object;Lscala/Function1;)Lscala/util/parsing/combinator/Parsers$Parser;;
NameAndType	accept:(Lscala/util/parsing/combinator/Parsers;Ljava/lang/Object;Lscala/Function1;)Lscala/util/parsing/combinator/Parsers$Parser;
Method	scala/util/parsing/combinator/Parsers$class.accept:(Lscala/util/parsing/combinator/Parsers;Ljava/lang/Object;Lscala/Function1;)Lscala/util/parsing/combinator/Parsers$Parser;
Asciz	es;
Asciz	evidence$1;
Asciz	(Ljava/lang/String;Lscala/PartialFunction;)Lscala/util/parsing/combinator/Parsers$Parser;;
Asciz	(Lscala/util/parsing/combinator/Parsers;Ljava/lang/String;Lscala/PartialFunction;)Lscala/util/parsing/combinator/Parsers$Parser;;
NameAndType	accept:(Lscala/util/parsing/combinator/Parsers;Ljava/lang/String;Lscala/PartialFunction;)Lscala/util/parsing/combinator/Parsers$Parser;
Method	scala/util/parsing/combinator/Parsers$class.accept:(Lscala/util/parsing/combinator/Parsers;Ljava/lang/String;Lscala/PartialFunction;)Lscala/util/parsing/combinator/Parsers$Parser;
Asciz	expected;
Asciz	Lscala/PartialFunction;;
Asciz	acceptIf;
Asciz	(Lscala/Function1;Lscala/Function1;)Lscala/util/parsing/combinator/Parsers$Parser;;
Asciz	(Lscala/util/parsing/combinator/Parsers;Lscala/Function1;Lscala/Function1;)Lscala/util/parsing/combinator/Parsers$Parser;;
NameAndType	acceptIf:(Lscala/util/parsing/combinator/Parsers;Lscala/Function1;Lscala/Function1;)Lscala/util/parsing/combinator/Parsers$Parser;
Method	scala/util/parsing/combinator/Parsers$class.acceptIf:(Lscala/util/parsing/combinator/Parsers;Lscala/Function1;Lscala/Function1;)Lscala/util/parsing/combinator/Parsers$Parser;
Asciz	err;
Asciz	acceptMatch;
NameAndType	acceptMatch:(Lscala/util/parsing/combinator/Parsers;Ljava/lang/String;Lscala/PartialFunction;)Lscala/util/parsing/combinator/Parsers$Parser;
Method	scala/util/parsing/combinator/Parsers$class.acceptMatch:(Lscala/util/parsing/combinator/Parsers;Ljava/lang/String;Lscala/PartialFunction;)Lscala/util/parsing/combinator/Parsers$Parser;
Asciz	acceptSeq;
NameAndType	acceptSeq:(Lscala/util/parsing/combinator/Parsers;Ljava/lang/Object;Lscala/Function1;)Lscala/util/parsing/combinator/Parsers$Parser;
Method	scala/util/parsing/combinator/Parsers$class.acceptSeq:(Lscala/util/parsing/combinator/Parsers;Ljava/lang/Object;Lscala/Function1;)Lscala/util/parsing/combinator/Parsers$Parser;
Asciz	evidence$2;
Asciz	failure;
Asciz	(Ljava/lang/String;)Lscala/util/parsing/combinator/Parsers$Parser;;
Asciz	(Lscala/util/parsing/combinator/Parsers;Ljava/lang/String;)Lscala/util/parsing/combinator/Parsers$Parser;;
NameAndType	failure:(Lscala/util/parsing/combinator/Parsers;Ljava/lang/String;)Lscala/util/parsing/combinator/Parsers$Parser;
Method	scala/util/parsing/combinator/Parsers$class.failure:(Lscala/util/parsing/combinator/Parsers;Ljava/lang/String;)Lscala/util/parsing/combinator/Parsers$Parser;
Asciz	msg;
NameAndType	err:(Lscala/util/parsing/combinator/Parsers;Ljava/lang/String;)Lscala/util/parsing/combinator/Parsers$Parser;
Method	scala/util/parsing/combinator/Parsers$class.err:(Lscala/util/parsing/combinator/Parsers;Ljava/lang/String;)Lscala/util/parsing/combinator/Parsers$Parser;
Asciz	success;
NameAndType	success:(Lscala/util/parsing/combinator/Parsers;Ljava/lang/Object;)Lscala/util/parsing/combinator/Parsers$Parser;
Method	scala/util/parsing/combinator/Parsers$class.success:(Lscala/util/parsing/combinator/Parsers;Ljava/lang/Object;)Lscala/util/parsing/combinator/Parsers$Parser;
Asciz	v;
Asciz	log;
Asciz	(Lscala/Function0;Ljava/lang/String;)Lscala/util/parsing/combinator/Parsers$Parser;;
Asciz	(Lscala/util/parsing/combinator/Parsers;Lscala/Function0;Ljava/lang/String;)Lscala/util/parsing/combinator/Parsers$Parser;;
NameAndType	log:(Lscala/util/parsing/combinator/Parsers;Lscala/Function0;Ljava/lang/String;)Lscala/util/parsing/combinator/Parsers$Parser;
Method	scala/util/parsing/combinator/Parsers$class.log:(Lscala/util/parsing/combinator/Parsers;Lscala/Function0;Ljava/lang/String;)Lscala/util/parsing/combinator/Parsers$Parser;
Asciz	name;
Asciz	rep;
NameAndType	rep:(Lscala/util/parsing/combinator/Parsers;Lscala/Function0;)Lscala/util/parsing/combinator/Parsers$Parser;
Method	scala/util/parsing/combinator/Parsers$class.rep:(Lscala/util/parsing/combinator/Parsers;Lscala/Function0;)Lscala/util/parsing/combinator/Parsers$Parser;
Asciz	repsep;
Asciz	(Lscala/Function0;Lscala/Function0;)Lscala/util/parsing/combinator/Parsers$Parser;;
Asciz	(Lscala/util/parsing/combinator/Parsers;Lscala/Function0;Lscala/Function0;)Lscala/util/parsing/combinator/Parsers$Parser;;
NameAndType	repsep:(Lscala/util/parsing/combinator/Parsers;Lscala/Function0;Lscala/Function0;)Lscala/util/parsing/combinator/Parsers$Parser;
Method	scala/util/parsing/combinator/Parsers$class.repsep:(Lscala/util/parsing/combinator/Parsers;Lscala/Function0;Lscala/Function0;)Lscala/util/parsing/combinator/Parsers$Parser;
Asciz	q;
Asciz	rep1;
NameAndType	rep1:(Lscala/util/parsing/combinator/Parsers;Lscala/Function0;)Lscala/util/parsing/combinator/Parsers$Parser;
Method	scala/util/parsing/combinator/Parsers$class.rep1:(Lscala/util/parsing/combinator/Parsers;Lscala/Function0;)Lscala/util/parsing/combinator/Parsers$Parser;
NameAndType	rep1:(Lscala/util/parsing/combinator/Parsers;Lscala/Function0;Lscala/Function0;)Lscala/util/parsing/combinator/Parsers$Parser;
Method	scala/util/parsing/combinator/Parsers$class.rep1:(Lscala/util/parsing/combinator/Parsers;Lscala/Function0;Lscala/Function0;)Lscala/util/parsing/combinator/Parsers$Parser;
Asciz	first;
Asciz	repN;
Asciz	(ILscala/Function0;)Lscala/util/parsing/combinator/Parsers$Parser;;
Asciz	(Lscala/util/parsing/combinator/Parsers;ILscala/Function0;)Lscala/util/parsing/combinator/Parsers$Parser;;
NameAndType	repN:(Lscala/util/parsing/combinator/Parsers;ILscala/Function0;)Lscala/util/parsing/combinator/Parsers$Parser;
Method	scala/util/parsing/combinator/Parsers$class.repN:(Lscala/util/parsing/combinator/Parsers;ILscala/Function0;)Lscala/util/parsing/combinator/Parsers$Parser;
Asciz	num;
Asciz	I;
Asciz	rep1sep;
NameAndType	rep1sep:(Lscala/util/parsing/combinator/Parsers;Lscala/Function0;Lscala/Function0;)Lscala/util/parsing/combinator/Parsers$Parser;
Method	scala/util/parsing/combinator/Parsers$class.rep1sep:(Lscala/util/parsing/combinator/Parsers;Lscala/Function0;Lscala/Function0;)Lscala/util/parsing/combinator/Parsers$Parser;
Asciz	chainl1;
NameAndType	chainl1:(Lscala/util/parsing/combinator/Parsers;Lscala/Function0;Lscala/Function0;)Lscala/util/parsing/combinator/Parsers$Parser;
Method	scala/util/parsing/combinator/Parsers$class.chainl1:(Lscala/util/parsing/combinator/Parsers;Lscala/Function0;Lscala/Function0;)Lscala/util/parsing/combinator/Parsers$Parser;
Asciz	(Lscala/Function0;Lscala/Function0;Lscala/Function0;)Lscala/util/parsing/combinator/Parsers$Parser;;
Asciz	(Lscala/util/parsing/combinator/Parsers;Lscala/Function0;Lscala/Function0;Lscala/Function0;)Lscala/util/parsing/combinator/Parsers$Parser;;
NameAndType	chainl1:(Lscala/util/parsing/combinator/Parsers;Lscala/Function0;Lscala/Function0;Lscala/Function0;)Lscala/util/parsing/combinator/Parsers$Parser;
Method	scala/util/parsing/combinator/Parsers$class.chainl1:(Lscala/util/parsing/combinator/Parsers;Lscala/Function0;Lscala/Function0;Lscala/Function0;)Lscala/util/parsing/combinator/Parsers$Parser;
Asciz	chainr1;
Asciz	(Lscala/Function0;Lscala/Function0;Lscala/Function2;Ljava/lang/Object;)Lscala/util/parsing/combinator/Parsers$Parser;;
Asciz	(Lscala/util/parsing/combinator/Parsers;Lscala/Function0;Lscala/Function0;Lscala/Function2;Ljava/lang/Object;)Lscala/util/parsing/combinator/Parsers$Parser;;
NameAndType	chainr1:(Lscala/util/parsing/combinator/Parsers;Lscala/Function0;Lscala/Function0;Lscala/Function2;Ljava/lang/Object;)Lscala/util/parsing/combinator/Parsers$Parser;
Method	scala/util/parsing/combinator/Parsers$class.chainr1:(Lscala/util/parsing/combinator/Parsers;Lscala/Function0;Lscala/Function0;Lscala/Function2;Ljava/lang/Object;)Lscala/util/parsing/combinator/Parsers$Parser;
Asciz	combine;
Asciz	Lscala/Function2;;
Asciz	opt;
NameAndType	opt:(Lscala/util/parsing/combinator/Parsers;Lscala/Function0;)Lscala/util/parsing/combinator/Parsers$Parser;
Method	scala/util/parsing/combinator/Parsers$class.opt:(Lscala/util/parsing/combinator/Parsers;Lscala/Function0;)Lscala/util/parsing/combinator/Parsers$Parser;
Asciz	not;
NameAndType	not:(Lscala/util/parsing/combinator/Parsers;Lscala/Function0;)Lscala/util/parsing/combinator/Parsers$Parser;
Method	scala/util/parsing/combinator/Parsers$class.not:(Lscala/util/parsing/combinator/Parsers;Lscala/Function0;)Lscala/util/parsing/combinator/Parsers$Parser;
Asciz	guard;
NameAndType	guard:(Lscala/util/parsing/combinator/Parsers;Lscala/Function0;)Lscala/util/parsing/combinator/Parsers$Parser;
Method	scala/util/parsing/combinator/Parsers$class.guard:(Lscala/util/parsing/combinator/Parsers;Lscala/Function0;)Lscala/util/parsing/combinator/Parsers$Parser;
Asciz	positioned;
NameAndType	positioned:(Lscala/util/parsing/combinator/Parsers;Lscala/Function0;)Lscala/util/parsing/combinator/Parsers$Parser;
Method	scala/util/parsing/combinator/Parsers$class.positioned:(Lscala/util/parsing/combinator/Parsers;Lscala/Function0;)Lscala/util/parsing/combinator/Parsers$Parser;
Asciz	phrase;
Asciz	(Lscala/util/parsing/combinator/Parsers$Parser;)Lscala/util/parsing/combinator/Parsers$Parser;;
Asciz	(Lscala/util/parsing/combinator/Parsers;Lscala/util/parsing/combinator/Parsers$Parser;)Lscala/util/parsing/combinator/Parsers$Parser;;
NameAndType	phrase:(Lscala/util/parsing/combinator/Parsers;Lscala/util/parsing/combinator/Parsers$Parser;)Lscala/util/parsing/combinator/Parsers$Parser;
Method	scala/util/parsing/combinator/Parsers$class.phrase:(Lscala/util/parsing/combinator/Parsers;Lscala/util/parsing/combinator/Parsers$Parser;)Lscala/util/parsing/combinator/Parsers$Parser;
Asciz	Lscala/util/parsing/combinator/Parsers$Parser;;
Asciz	mkList;
Asciz	()Lscala/Function1;;
Asciz	(Lscala/util/parsing/combinator/Parsers;)Lscala/Function1;;
NameAndType	mkList:(Lscala/util/parsing/combinator/Parsers;)Lscala/Function1;
Method	scala/util/parsing/combinator/Parsers$class.mkList:(Lscala/util/parsing/combinator/Parsers;)Lscala/Function1;
Asciz	()Lscala/util/parsing/combinator/lexical/StdLexical;;
NameAndType	lexical:Lscala/util/parsing/combinator/lexical/StdLexical;
Field	scala/util/parsing/combinator/syntactical/StandardTokenParsers.lexical:Lscala/util/parsing/combinator/lexical/StdLexical;
Asciz	keyword;
NameAndType	lexical:()Lscala/util/parsing/combinator/lexical/StdLexical;
Method	scala/util/parsing/combinator/syntactical/StandardTokenParsers.lexical:()Lscala/util/parsing/combinator/lexical/StdLexical;
Asciz	scala/util/parsing/combinator/lexical/StdLexical;
class	scala/util/parsing/combinator/lexical/StdLexical
Asciz	reserved;
Asciz	()Lscala/collection/mutable/HashSet;;
NameAndType	reserved:()Lscala/collection/mutable/HashSet;
Method	scala/util/parsing/combinator/lexical/StdLexical.reserved:()Lscala/collection/mutable/HashSet;
Asciz	scala/collection/mutable/HashSet;
class	scala/collection/mutable/HashSet
Asciz	contains;
Asciz	(Ljava/lang/Object;)Z;
NameAndType	contains:(Ljava/lang/Object;)Z
Method	scala/collection/mutable/HashSet.contains:(Ljava/lang/Object;)Z
Asciz	delimiters;
NameAndType	delimiters:()Lscala/collection/mutable/HashSet;
Method	scala/util/parsing/combinator/lexical/StdLexical.delimiters:()Lscala/collection/mutable/HashSet;
Asciz	(Lscala/util/parsing/combinator/syntactical/StdTokenParsers;Ljava/lang/String;)Lscala/util/parsing/combinator/Parsers$Parser;;
NameAndType	keyword:(Lscala/util/parsing/combinator/syntactical/StdTokenParsers;Ljava/lang/String;)Lscala/util/parsing/combinator/Parsers$Parser;
Method	scala/util/parsing/combinator/syntactical/StdTokenParsers$class.keyword:(Lscala/util/parsing/combinator/syntactical/StdTokenParsers;Ljava/lang/String;)Lscala/util/parsing/combinator/Parsers$Parser;
Asciz	scala/collection/mutable/StringBuilder;
class	scala/collection/mutable/StringBuilder
Asciz	()V;
NameAndType	"<init>":()V
Method	scala/collection/mutable/StringBuilder."<init>":()V
Asciz	You are trying to parse \";
String	You are trying to parse \"
Asciz	append;
Asciz	(Ljava/lang/Object;)Lscala/collection/mutable/StringBuilder;;
NameAndType	append:(Ljava/lang/Object;)Lscala/collection/mutable/StringBuilder;
Method	scala/collection/mutable/StringBuilder.append:(Ljava/lang/Object;)Lscala/collection/mutable/StringBuilder;
Asciz	\", but it is neither contained in the delimiters list, nor in the reserved keyword list of your lexical object;
String	\", but it is neither contained in the delimiters list, nor in the reserved keyword list of your lexical object
Asciz	toString;
Asciz	()Ljava/lang/String;;
NameAndType	toString:()Ljava/lang/String;
Method	scala/collection/mutable/StringBuilder.toString:()Ljava/lang/String;
Asciz	scala/util/parsing/combinator/Parsers;
class	scala/util/parsing/combinator/Parsers
NameAndType	failure:(Ljava/lang/String;)Lscala/util/parsing/combinator/Parsers$Parser;
InterfaceMethod	scala/util/parsing/combinator/Parsers.failure:(Ljava/lang/String;)Lscala/util/parsing/combinator/Parsers$Parser;
Asciz	chars;
Asciz	(Ljava/lang/String;)Lscala/util/parsing/combinator/Parsers$Parser<Ljava/lang/String;>;;
Asciz	Signature;
Asciz	()Lscala/util/parsing/syntax/Tokens;;
Asciz	java/lang/Object;
class	java/lang/Object
Method	java/lang/Object."<init>":()V
Asciz	$init$;
NameAndType	$init$:(Lscala/util/parsing/combinator/Parsers;)V
Method	scala/util/parsing/combinator/Parsers$class.$init$:(Lscala/util/parsing/combinator/Parsers;)V
Asciz	(Lscala/util/parsing/combinator/syntactical/StdTokenParsers;)V;
NameAndType	$init$:(Lscala/util/parsing/combinator/syntactical/StdTokenParsers;)V
Method	scala/util/parsing/combinator/syntactical/StdTokenParsers$class.$init$:(Lscala/util/parsing/combinator/syntactical/StdTokenParsers;)V
Method	scala/util/parsing/combinator/lexical/StdLexical."<init>":()V
Asciz	ScalaSig;
Asciz	InnerClasses;
Asciz	scala/util/parsing/combinator/Parsers$Parser;
class	scala/util/parsing/combinator/Parsers$Parser
Asciz	scala/util/parsing/combinator/Parsers$NoSuccess;
class	scala/util/parsing/combinator/Parsers$NoSuccess
Asciz	scala/util/parsing/combinator/Parsers$OnceParser;
class	scala/util/parsing/combinator/Parsers$OnceParser
Asciz	scala/util/parsing/combinator/syntactical/StdTokenParsers;
class	scala/util/parsing/combinator/syntactical/StdTokenParsers
Asciz	scala/ScalaObject;
class	scala/ScalaObject

{
private scala.util.parsing.combinator.Parsers$$tilde$ $tilde$module;
  Signature: Lscala/util/parsing/combinator/Parsers$$tilde$;

private scala.util.parsing.combinator.Parsers$Error$ Error$module;
  Signature: Lscala/util/parsing/combinator/Parsers$Error$;

private scala.util.parsing.combinator.Parsers$Failure$ Failure$module;
  Signature: Lscala/util/parsing/combinator/Parsers$Failure$;

private scala.util.parsing.combinator.Parsers$NoSuccess$ NoSuccess$module;
  Signature: Lscala/util/parsing/combinator/Parsers$NoSuccess$;

private scala.util.parsing.combinator.Parsers$Success$ Success$module;
  Signature: Lscala/util/parsing/combinator/Parsers$Success$;

private scala.util.parsing.combinator.Parsers$NoSuccess lastNoSuccess;
  Signature: Lscala/util/parsing/combinator/Parsers$NoSuccess;

private final scala.collection.mutable.HashMap keywordCache;
  Signature: Lscala/collection/mutable/HashMap;

private final scala.util.parsing.combinator.lexical.StdLexical lexical;
  Signature: Lscala/util/parsing/combinator/lexical/StdLexical;

public scala.collection.mutable.HashMap keywordCache();
  Signature: ()Lscala/collection/mutable/HashMap;
  Code:
   Stack=1, Locals=1, Args_size=1
	aload_0
	getfield	Field keywordCache:Lscala/collection/mutable/HashMap;
	areturn
  Labels:

public void scala$util$parsing$combinator$syntactical$StdTokenParsers$_setter_$keywordCache_$eq(scala.collection.mutable.HashMap);
  Signature: (Lscala/collection/mutable/HashMap;)V
  Code:
   Stack=2, Locals=2, Args_size=2
	aload_0
	aload_1
	putfield	Field keywordCache:Lscala/collection/mutable/HashMap;
	return
  Labels:

public scala.util.parsing.combinator.Parsers$Parser numericLit();
  Signature: ()Lscala/util/parsing/combinator/Parsers$Parser;
  Code:
   Stack=1, Locals=1, Args_size=1
	aload_0
	invokestatic	Method scala/util/parsing/combinator/syntactical/StdTokenParsers$class.numericLit:(Lscala/util/parsing/combinator/syntactical/StdTokenParsers;)Lscala/util/parsing/combinator/Parsers$Parser;
	areturn
  Labels:

public scala.util.parsing.combinator.Parsers$Parser stringLit();
  Signature: ()Lscala/util/parsing/combinator/Parsers$Parser;
  Code:
   Stack=1, Locals=1, Args_size=1
	aload_0
	invokestatic	Method scala/util/parsing/combinator/syntactical/StdTokenParsers$class.stringLit:(Lscala/util/parsing/combinator/syntactical/StdTokenParsers;)Lscala/util/parsing/combinator/Parsers$Parser;
	areturn
  Labels:

public scala.util.parsing.combinator.Parsers$Parser ident();
  Signature: ()Lscala/util/parsing/combinator/Parsers$Parser;
  Code:
   Stack=1, Locals=1, Args_size=1
	aload_0
	invokestatic	Method scala/util/parsing/combinator/syntactical/StdTokenParsers$class.ident:(Lscala/util/parsing/combinator/syntactical/StdTokenParsers;)Lscala/util/parsing/combinator/Parsers$Parser;
	areturn
  Labels:

public final scala.util.parsing.combinator.Parsers$Success$ Success();
  Signature: ()Lscala/util/parsing/combinator/Parsers$Success$;
  Code:
   Stack=4, Locals=1, Args_size=1
	aload_0
	getfield	Field Success$module:Lscala/util/parsing/combinator/Parsers$Success$;
	ifnonnull	l1 // aload_0
	aload_0
	new	class scala/util/parsing/combinator/Parsers$Success$
	dup
	aload_0
	invokespecial	Method scala/util/parsing/combinator/Parsers$Success$."<init>":(Lscala/util/parsing/combinator/Parsers;)V
	putfield	Field Success$module:Lscala/util/parsing/combinator/Parsers$Success$;
l1	aload_0
	getfield	Field Success$module:Lscala/util/parsing/combinator/Parsers$Success$;
	areturn
  Labels:
   	l1 = 19 // aload_0

public scala.util.parsing.combinator.Parsers$NoSuccess lastNoSuccess();
  Signature: ()Lscala/util/parsing/combinator/Parsers$NoSuccess;
  Code:
   Stack=1, Locals=1, Args_size=1
	aload_0
	getfield	Field lastNoSuccess:Lscala/util/parsing/combinator/Parsers$NoSuccess;
	areturn
  Labels:

public void lastNoSuccess_$eq(scala.util.parsing.combinator.Parsers$NoSuccess);
  Signature: (Lscala/util/parsing/combinator/Parsers$NoSuccess;)V
  Code:
   Stack=2, Locals=2, Args_size=2
	aload_0
	aload_1
	putfield	Field lastNoSuccess:Lscala/util/parsing/combinator/Parsers$NoSuccess;
	return
  Labels:

public final scala.util.parsing.combinator.Parsers$NoSuccess$ NoSuccess();
  Signature: ()Lscala/util/parsing/combinator/Parsers$NoSuccess$;
  Code:
   Stack=4, Locals=1, Args_size=1
	aload_0
	getfield	Field NoSuccess$module:Lscala/util/parsing/combinator/Parsers$NoSuccess$;
	ifnonnull	l1 // aload_0
	aload_0
	new	class scala/util/parsing/combinator/Parsers$NoSuccess$
	dup
	aload_0
	invokespecial	Method scala/util/parsing/combinator/Parsers$NoSuccess$."<init>":(Lscala/util/parsing/combinator/Parsers;)V
	putfield	Field NoSuccess$module:Lscala/util/parsing/combinator/Parsers$NoSuccess$;
l1	aload_0
	getfield	Field NoSuccess$module:Lscala/util/parsing/combinator/Parsers$NoSuccess$;
	areturn
  Labels:
   	l1 = 19 // aload_0

public final scala.util.parsing.combinator.Parsers$Failure$ Failure();
  Signature: ()Lscala/util/parsing/combinator/Parsers$Failure$;
  Code:
   Stack=4, Locals=1, Args_size=1
	aload_0
	getfield	Field Failure$module:Lscala/util/parsing/combinator/Parsers$Failure$;
	ifnonnull	l1 // aload_0
	aload_0
	new	class scala/util/parsing/combinator/Parsers$Failure$
	dup
	aload_0
	invokespecial	Method scala/util/parsing/combinator/Parsers$Failure$."<init>":(Lscala/util/parsing/combinator/Parsers;)V
	putfield	Field Failure$module:Lscala/util/parsing/combinator/Parsers$Failure$;
l1	aload_0
	getfield	Field Failure$module:Lscala/util/parsing/combinator/Parsers$Failure$;
	areturn
  Labels:
   	l1 = 19 // aload_0

public final scala.util.parsing.combinator.Parsers$Error$ Error();
  Signature: ()Lscala/util/parsing/combinator/Parsers$Error$;
  Code:
   Stack=4, Locals=1, Args_size=1
	aload_0
	getfield	Field Error$module:Lscala/util/parsing/combinator/Parsers$Error$;
	ifnonnull	l1 // aload_0
	aload_0
	new	class scala/util/parsing/combinator/Parsers$Error$
	dup
	aload_0
	invokespecial	Method scala/util/parsing/combinator/Parsers$Error$."<init>":(Lscala/util/parsing/combinator/Parsers;)V
	putfield	Field Error$module:Lscala/util/parsing/combinator/Parsers$Error$;
l1	aload_0
	getfield	Field Error$module:Lscala/util/parsing/combinator/Parsers$Error$;
	areturn
  Labels:
   	l1 = 19 // aload_0

public final scala.util.parsing.combinator.Parsers$$tilde$ $tilde();
  Signature: ()Lscala/util/parsing/combinator/Parsers$$tilde$;
  Code:
   Stack=4, Locals=1, Args_size=1
	aload_0
	getfield	Field $tilde$module:Lscala/util/parsing/combinator/Parsers$$tilde$;
	ifnonnull	l1 // aload_0
	aload_0
	new	class scala/util/parsing/combinator/Parsers$$tilde$
	dup
	aload_0
	invokespecial	Method scala/util/parsing/combinator/Parsers$$tilde$."<init>":(Lscala/util/parsing/combinator/Parsers;)V
	putfield	Field $tilde$module:Lscala/util/parsing/combinator/Parsers$$tilde$;
l1	aload_0
	getfield	Field $tilde$module:Lscala/util/parsing/combinator/Parsers$$tilde$;
	areturn
  Labels:
   	l1 = 19 // aload_0

public scala.util.parsing.combinator.Parsers$Parser Parser(scala.Function1);
  Signature: (Lscala/Function1;)Lscala/util/parsing/combinator/Parsers$Parser;
  Code:
   Stack=2, Locals=2, Args_size=2
	aload_0
	aload_1
	invokestatic	Method scala/util/parsing/combinator/Parsers$class.Parser:(Lscala/util/parsing/combinator/Parsers;Lscala/Function1;)Lscala/util/parsing/combinator/Parsers$Parser;
	areturn
  Labels:
  LocalVariableTable: 
   Start  Length  Slot  Name   Signature
   0      6      0    this       Lscala/util/parsing/combinator/syntactical/StandardTokenParsers;
   0      6      1    f       Lscala/Function1;


public scala.util.parsing.combinator.Parsers$OnceParser OnceParser(scala.Function1);
  Signature: (Lscala/Function1;)Lscala/util/parsing/combinator/Parsers$OnceParser;
  Code:
   Stack=2, Locals=2, Args_size=2
	aload_0
	aload_1
	invokestatic	Method scala/util/parsing/combinator/Parsers$class.OnceParser:(Lscala/util/parsing/combinator/Parsers;Lscala/Function1;)Lscala/util/parsing/combinator/Parsers$OnceParser;
	areturn
  Labels:
  LocalVariableTable: 
   Start  Length  Slot  Name   Signature
   0      6      0    this       Lscala/util/parsing/combinator/syntactical/StandardTokenParsers;
   0      6      1    f       Lscala/Function1;


public scala.util.parsing.combinator.Parsers$Parser commit(scala.Function0);
  Signature: (Lscala/Function0;)Lscala/util/parsing/combinator/Parsers$Parser;
  Code:
   Stack=2, Locals=2, Args_size=2
	aload_0
	aload_1
	invokestatic	Method scala/util/parsing/combinator/Parsers$class.commit:(Lscala/util/parsing/combinator/Parsers;Lscala/Function0;)Lscala/util/parsing/combinator/Parsers$Parser;
	areturn
  Labels:
  LocalVariableTable: 
   Start  Length  Slot  Name   Signature
   0      6      0    this       Lscala/util/parsing/combinator/syntactical/StandardTokenParsers;
   0      6      1    p       Lscala/Function0;


public scala.util.parsing.combinator.Parsers$Parser elem(java.lang.String, scala.Function1);
  Signature: (Ljava/lang/String;Lscala/Function1;)Lscala/util/parsing/combinator/Parsers$Parser;
  Code:
   Stack=3, Locals=3, Args_size=3
	aload_0
	aload_1
	aload_2
	invokestatic	Method scala/util/parsing/combinator/Parsers$class.elem:(Lscala/util/parsing/combinator/Parsers;Ljava/lang/String;Lscala/Function1;)Lscala/util/parsing/combinator/Parsers$Parser;
	areturn
  Labels:
  LocalVariableTable: 
   Start  Length  Slot  Name   Signature
   0      7      0    this       Lscala/util/parsing/combinator/syntactical/StandardTokenParsers;
   0      7      1    kind       Ljava/lang/String;
   0      7      2    p       Lscala/Function1;


public scala.util.parsing.combinator.Parsers$Parser elem(java.lang.Object);
  Signature: (Ljava/lang/Object;)Lscala/util/parsing/combinator/Parsers$Parser;
  Code:
   Stack=2, Locals=2, Args_size=2
	aload_0
	aload_1
	invokestatic	Method scala/util/parsing/combinator/Parsers$class.elem:(Lscala/util/parsing/combinator/Parsers;Ljava/lang/Object;)Lscala/util/parsing/combinator/Parsers$Parser;
	areturn
  Labels:
  LocalVariableTable: 
   Start  Length  Slot  Name   Signature
   0      6      0    this       Lscala/util/parsing/combinator/syntactical/StandardTokenParsers;
   0      6      1    e       Ljava/lang/Object;


public scala.util.parsing.combinator.Parsers$Parser accept(java.lang.Object);
  Signature: (Ljava/lang/Object;)Lscala/util/parsing/combinator/Parsers$Parser;
  Code:
   Stack=2, Locals=2, Args_size=2
	aload_0
	aload_1
	invokestatic	Method scala/util/parsing/combinator/Parsers$class.accept:(Lscala/util/parsing/combinator/Parsers;Ljava/lang/Object;)Lscala/util/parsing/combinator/Parsers$Parser;
	areturn
  Labels:
  LocalVariableTable: 
   Start  Length  Slot  Name   Signature
   0      6      0    this       Lscala/util/parsing/combinator/syntactical/StandardTokenParsers;
   0      6      1    e       Ljava/lang/Object;


public scala.util.parsing.combinator.Parsers$Parser accept(java.lang.Object, scala.Function1);
  Signature: (Ljava/lang/Object;Lscala/Function1;)Lscala/util/parsing/combinator/Parsers$Parser;
  Code:
   Stack=3, Locals=3, Args_size=3
	aload_0
	aload_1
	aload_2
	invokestatic	Method scala/util/parsing/combinator/Parsers$class.accept:(Lscala/util/parsing/combinator/Parsers;Ljava/lang/Object;Lscala/Function1;)Lscala/util/parsing/combinator/Parsers$Parser;
	areturn
  Labels:
  LocalVariableTable: 
   Start  Length  Slot  Name   Signature
   0      7      0    this       Lscala/util/parsing/combinator/syntactical/StandardTokenParsers;
   0      7      1    es       Ljava/lang/Object;
   0      7      2    evidence$1       Lscala/Function1;


public scala.util.parsing.combinator.Parsers$Parser accept(java.lang.String, scala.PartialFunction);
  Signature: (Ljava/lang/String;Lscala/PartialFunction;)Lscala/util/parsing/combinator/Parsers$Parser;
  Code:
   Stack=3, Locals=3, Args_size=3
	aload_0
	aload_1
	aload_2
	invokestatic	Method scala/util/parsing/combinator/Parsers$class.accept:(Lscala/util/parsing/combinator/Parsers;Ljava/lang/String;Lscala/PartialFunction;)Lscala/util/parsing/combinator/Parsers$Parser;
	areturn
  Labels:
  LocalVariableTable: 
   Start  Length  Slot  Name   Signature
   0      7      0    this       Lscala/util/parsing/combinator/syntactical/StandardTokenParsers;
   0      7      1    expected       Ljava/lang/String;
   0      7      2    f       Lscala/PartialFunction;


public scala.util.parsing.combinator.Parsers$Parser acceptIf(scala.Function1, scala.Function1);
  Signature: (Lscala/Function1;Lscala/Function1;)Lscala/util/parsing/combinator/Parsers$Parser;
  Code:
   Stack=3, Locals=3, Args_size=3
	aload_0
	aload_1
	aload_2
	invokestatic	Method scala/util/parsing/combinator/Parsers$class.acceptIf:(Lscala/util/parsing/combinator/Parsers;Lscala/Function1;Lscala/Function1;)Lscala/util/parsing/combinator/Parsers$Parser;
	areturn
  Labels:
  LocalVariableTable: 
   Start  Length  Slot  Name   Signature
   0      7      0    this       Lscala/util/parsing/combinator/syntactical/StandardTokenParsers;
   0      7      1    p       Lscala/Function1;
   0      7      2    err       Lscala/Function1;


public scala.util.parsing.combinator.Parsers$Parser acceptMatch(java.lang.String, scala.PartialFunction);
  Signature: (Ljava/lang/String;Lscala/PartialFunction;)Lscala/util/parsing/combinator/Parsers$Parser;
  Code:
   Stack=3, Locals=3, Args_size=3
	aload_0
	aload_1
	aload_2
	invokestatic	Method scala/util/parsing/combinator/Parsers$class.acceptMatch:(Lscala/util/parsing/combinator/Parsers;Ljava/lang/String;Lscala/PartialFunction;)Lscala/util/parsing/combinator/Parsers$Parser;
	areturn
  Labels:
  LocalVariableTable: 
   Start  Length  Slot  Name   Signature
   0      7      0    this       Lscala/util/parsing/combinator/syntactical/StandardTokenParsers;
   0      7      1    expected       Ljava/lang/String;
   0      7      2    f       Lscala/PartialFunction;


public scala.util.parsing.combinator.Parsers$Parser acceptSeq(java.lang.Object, scala.Function1);
  Signature: (Ljava/lang/Object;Lscala/Function1;)Lscala/util/parsing/combinator/Parsers$Parser;
  Code:
   Stack=3, Locals=3, Args_size=3
	aload_0
	aload_1
	aload_2
	invokestatic	Method scala/util/parsing/combinator/Parsers$class.acceptSeq:(Lscala/util/parsing/combinator/Parsers;Ljava/lang/Object;Lscala/Function1;)Lscala/util/parsing/combinator/Parsers$Parser;
	areturn
  Labels:
  LocalVariableTable: 
   Start  Length  Slot  Name   Signature
   0      7      0    this       Lscala/util/parsing/combinator/syntactical/StandardTokenParsers;
   0      7      1    es       Ljava/lang/Object;
   0      7      2    evidence$2       Lscala/Function1;


public scala.util.parsing.combinator.Parsers$Parser failure(java.lang.String);
  Signature: (Ljava/lang/String;)Lscala/util/parsing/combinator/Parsers$Parser;
  Code:
   Stack=2, Locals=2, Args_size=2
	aload_0
	aload_1
	invokestatic	Method scala/util/parsing/combinator/Parsers$class.failure:(Lscala/util/parsing/combinator/Parsers;Ljava/lang/String;)Lscala/util/parsing/combinator/Parsers$Parser;
	areturn
  Labels:
  LocalVariableTable: 
   Start  Length  Slot  Name   Signature
   0      6      0    this       Lscala/util/parsing/combinator/syntactical/StandardTokenParsers;
   0      6      1    msg       Ljava/lang/String;


public scala.util.parsing.combinator.Parsers$Parser err(java.lang.String);
  Signature: (Ljava/lang/String;)Lscala/util/parsing/combinator/Parsers$Parser;
  Code:
   Stack=2, Locals=2, Args_size=2
	aload_0
	aload_1
	invokestatic	Method scala/util/parsing/combinator/Parsers$class.err:(Lscala/util/parsing/combinator/Parsers;Ljava/lang/String;)Lscala/util/parsing/combinator/Parsers$Parser;
	areturn
  Labels:
  LocalVariableTable: 
   Start  Length  Slot  Name   Signature
   0      6      0    this       Lscala/util/parsing/combinator/syntactical/StandardTokenParsers;
   0      6      1    msg       Ljava/lang/String;


public scala.util.parsing.combinator.Parsers$Parser success(java.lang.Object);
  Signature: (Ljava/lang/Object;)Lscala/util/parsing/combinator/Parsers$Parser;
  Code:
   Stack=2, Locals=2, Args_size=2
	aload_0
	aload_1
	invokestatic	Method scala/util/parsing/combinator/Parsers$class.success:(Lscala/util/parsing/combinator/Parsers;Ljava/lang/Object;)Lscala/util/parsing/combinator/Parsers$Parser;
	areturn
  Labels:
  LocalVariableTable: 
   Start  Length  Slot  Name   Signature
   0      6      0    this       Lscala/util/parsing/combinator/syntactical/StandardTokenParsers;
   0      6      1    v       Ljava/lang/Object;


public scala.util.parsing.combinator.Parsers$Parser log(scala.Function0, java.lang.String);
  Signature: (Lscala/Function0;Ljava/lang/String;)Lscala/util/parsing/combinator/Parsers$Parser;
  Code:
   Stack=3, Locals=3, Args_size=3
	aload_0
	aload_1
	aload_2
	invokestatic	Method scala/util/parsing/combinator/Parsers$class.log:(Lscala/util/parsing/combinator/Parsers;Lscala/Function0;Ljava/lang/String;)Lscala/util/parsing/combinator/Parsers$Parser;
	areturn
  Labels:
  LocalVariableTable: 
   Start  Length  Slot  Name   Signature
   0      7      0    this       Lscala/util/parsing/combinator/syntactical/StandardTokenParsers;
   0      7      1    p       Lscala/Function0;
   0      7      2    name       Ljava/lang/String;


public scala.util.parsing.combinator.Parsers$Parser rep(scala.Function0);
  Signature: (Lscala/Function0;)Lscala/util/parsing/combinator/Parsers$Parser;
  Code:
   Stack=2, Locals=2, Args_size=2
	aload_0
	aload_1
	invokestatic	Method scala/util/parsing/combinator/Parsers$class.rep:(Lscala/util/parsing/combinator/Parsers;Lscala/Function0;)Lscala/util/parsing/combinator/Parsers$Parser;
	areturn
  Labels:
  LocalVariableTable: 
   Start  Length  Slot  Name   Signature
   0      6      0    this       Lscala/util/parsing/combinator/syntactical/StandardTokenParsers;
   0      6      1    p       Lscala/Function0;


public scala.util.parsing.combinator.Parsers$Parser repsep(scala.Function0, scala.Function0);
  Signature: (Lscala/Function0;Lscala/Function0;)Lscala/util/parsing/combinator/Parsers$Parser;
  Code:
   Stack=3, Locals=3, Args_size=3
	aload_0
	aload_1
	aload_2
	invokestatic	Method scala/util/parsing/combinator/Parsers$class.repsep:(Lscala/util/parsing/combinator/Parsers;Lscala/Function0;Lscala/Function0;)Lscala/util/parsing/combinator/Parsers$Parser;
	areturn
  Labels:
  LocalVariableTable: 
   Start  Length  Slot  Name   Signature
   0      7      0    this       Lscala/util/parsing/combinator/syntactical/StandardTokenParsers;
   0      7      1    p       Lscala/Function0;
   0      7      2    q       Lscala/Function0;


public scala.util.parsing.combinator.Parsers$Parser rep1(scala.Function0);
  Signature: (Lscala/Function0;)Lscala/util/parsing/combinator/Parsers$Parser;
  Code:
   Stack=2, Locals=2, Args_size=2
	aload_0
	aload_1
	invokestatic	Method scala/util/parsing/combinator/Parsers$class.rep1:(Lscala/util/parsing/combinator/Parsers;Lscala/Function0;)Lscala/util/parsing/combinator/Parsers$Parser;
	areturn
  Labels:
  LocalVariableTable: 
   Start  Length  Slot  Name   Signature
   0      6      0    this       Lscala/util/parsing/combinator/syntactical/StandardTokenParsers;
   0      6      1    p       Lscala/Function0;


public scala.util.parsing.combinator.Parsers$Parser rep1(scala.Function0, scala.Function0);
  Signature: (Lscala/Function0;Lscala/Function0;)Lscala/util/parsing/combinator/Parsers$Parser;
  Code:
   Stack=3, Locals=3, Args_size=3
	aload_0
	aload_1
	aload_2
	invokestatic	Method scala/util/parsing/combinator/Parsers$class.rep1:(Lscala/util/parsing/combinator/Parsers;Lscala/Function0;Lscala/Function0;)Lscala/util/parsing/combinator/Parsers$Parser;
	areturn
  Labels:
  LocalVariableTable: 
   Start  Length  Slot  Name   Signature
   0      7      0    this       Lscala/util/parsing/combinator/syntactical/StandardTokenParsers;
   0      7      1    first       Lscala/Function0;
   0      7      2    p       Lscala/Function0;


public scala.util.parsing.combinator.Parsers$Parser repN(int, scala.Function0);
  Signature: (ILscala/Function0;)Lscala/util/parsing/combinator/Parsers$Parser;
  Code:
   Stack=3, Locals=3, Args_size=3
	aload_0
	iload_1
	aload_2
	invokestatic	Method scala/util/parsing/combinator/Parsers$class.repN:(Lscala/util/parsing/combinator/Parsers;ILscala/Function0;)Lscala/util/parsing/combinator/Parsers$Parser;
	areturn
  Labels:
  LocalVariableTable: 
   Start  Length  Slot  Name   Signature
   0      7      0    this       Lscala/util/parsing/combinator/syntactical/StandardTokenParsers;
   0      7      1    num       I
   0      7      2    p       Lscala/Function0;


public scala.util.parsing.combinator.Parsers$Parser rep1sep(scala.Function0, scala.Function0);
  Signature: (Lscala/Function0;Lscala/Function0;)Lscala/util/parsing/combinator/Parsers$Parser;
  Code:
   Stack=3, Locals=3, Args_size=3
	aload_0
	aload_1
	aload_2
	invokestatic	Method scala/util/parsing/combinator/Parsers$class.rep1sep:(Lscala/util/parsing/combinator/Parsers;Lscala/Function0;Lscala/Function0;)Lscala/util/parsing/combinator/Parsers$Parser;
	areturn
  Labels:
  LocalVariableTable: 
   Start  Length  Slot  Name   Signature
   0      7      0    this       Lscala/util/parsing/combinator/syntactical/StandardTokenParsers;
   0      7      1    p       Lscala/Function0;
   0      7      2    q       Lscala/Function0;


public scala.util.parsing.combinator.Parsers$Parser chainl1(scala.Function0, scala.Function0);
  Signature: (Lscala/Function0;Lscala/Function0;)Lscala/util/parsing/combinator/Parsers$Parser;
  Code:
   Stack=3, Locals=3, Args_size=3
	aload_0
	aload_1
	aload_2
	invokestatic	Method scala/util/parsing/combinator/Parsers$class.chainl1:(Lscala/util/parsing/combinator/Parsers;Lscala/Function0;Lscala/Function0;)Lscala/util/parsing/combinator/Parsers$Parser;
	areturn
  Labels:
  LocalVariableTable: 
   Start  Length  Slot  Name   Signature
   0      7      0    this       Lscala/util/parsing/combinator/syntactical/StandardTokenParsers;
   0      7      1    p       Lscala/Function0;
   0      7      2    q       Lscala/Function0;


public scala.util.parsing.combinator.Parsers$Parser chainl1(scala.Function0, scala.Function0, scala.Function0);
  Signature: (Lscala/Function0;Lscala/Function0;Lscala/Function0;)Lscala/util/parsing/combinator/Parsers$Parser;
  Code:
   Stack=4, Locals=4, Args_size=4
	aload_0
	aload_1
	aload_2
	aload_3
	invokestatic	Method scala/util/parsing/combinator/Parsers$class.chainl1:(Lscala/util/parsing/combinator/Parsers;Lscala/Function0;Lscala/Function0;Lscala/Function0;)Lscala/util/parsing/combinator/Parsers$Parser;
	areturn
  Labels:
  LocalVariableTable: 
   Start  Length  Slot  Name   Signature
   0      8      0    this       Lscala/util/parsing/combinator/syntactical/StandardTokenParsers;
   0      8      1    first       Lscala/Function0;
   0      8      2    p       Lscala/Function0;
   0      8      3    q       Lscala/Function0;


public scala.util.parsing.combinator.Parsers$Parser chainr1(scala.Function0, scala.Function0, scala.Function2, java.lang.Object);
  Signature: (Lscala/Function0;Lscala/Function0;Lscala/Function2;Ljava/lang/Object;)Lscala/util/parsing/combinator/Parsers$Parser;
  Code:
   Stack=5, Locals=5, Args_size=5
	aload_0
	aload_1
	aload_2
	aload_3
	aload	4
	invokestatic	Method scala/util/parsing/combinator/Parsers$class.chainr1:(Lscala/util/parsing/combinator/Parsers;Lscala/Function0;Lscala/Function0;Lscala/Function2;Ljava/lang/Object;)Lscala/util/parsing/combinator/Parsers$Parser;
	areturn
  Labels:
  LocalVariableTable: 
   Start  Length  Slot  Name   Signature
   0      10      0    this       Lscala/util/parsing/combinator/syntactical/StandardTokenParsers;
   0      10      1    p       Lscala/Function0;
   0      10      2    q       Lscala/Function0;
   0      10      3    combine       Lscala/Function2;
   0      10      4    first       Ljava/lang/Object;


public scala.util.parsing.combinator.Parsers$Parser opt(scala.Function0);
  Signature: (Lscala/Function0;)Lscala/util/parsing/combinator/Parsers$Parser;
  Code:
   Stack=2, Locals=2, Args_size=2
	aload_0
	aload_1
	invokestatic	Method scala/util/parsing/combinator/Parsers$class.opt:(Lscala/util/parsing/combinator/Parsers;Lscala/Function0;)Lscala/util/parsing/combinator/Parsers$Parser;
	areturn
  Labels:
  LocalVariableTable: 
   Start  Length  Slot  Name   Signature
   0      6      0    this       Lscala/util/parsing/combinator/syntactical/StandardTokenParsers;
   0      6      1    p       Lscala/Function0;


public scala.util.parsing.combinator.Parsers$Parser not(scala.Function0);
  Signature: (Lscala/Function0;)Lscala/util/parsing/combinator/Parsers$Parser;
  Code:
   Stack=2, Locals=2, Args_size=2
	aload_0
	aload_1
	invokestatic	Method scala/util/parsing/combinator/Parsers$class.not:(Lscala/util/parsing/combinator/Parsers;Lscala/Function0;)Lscala/util/parsing/combinator/Parsers$Parser;
	areturn
  Labels:
  LocalVariableTable: 
   Start  Length  Slot  Name   Signature
   0      6      0    this       Lscala/util/parsing/combinator/syntactical/StandardTokenParsers;
   0      6      1    p       Lscala/Function0;


public scala.util.parsing.combinator.Parsers$Parser guard(scala.Function0);
  Signature: (Lscala/Function0;)Lscala/util/parsing/combinator/Parsers$Parser;
  Code:
   Stack=2, Locals=2, Args_size=2
	aload_0
	aload_1
	invokestatic	Method scala/util/parsing/combinator/Parsers$class.guard:(Lscala/util/parsing/combinator/Parsers;Lscala/Function0;)Lscala/util/parsing/combinator/Parsers$Parser;
	areturn
  Labels:
  LocalVariableTable: 
   Start  Length  Slot  Name   Signature
   0      6      0    this       Lscala/util/parsing/combinator/syntactical/StandardTokenParsers;
   0      6      1    p       Lscala/Function0;


public scala.util.parsing.combinator.Parsers$Parser positioned(scala.Function0);
  Signature: (Lscala/Function0;)Lscala/util/parsing/combinator/Parsers$Parser;
  Code:
   Stack=2, Locals=2, Args_size=2
	aload_0
	aload_1
	invokestatic	Method scala/util/parsing/combinator/Parsers$class.positioned:(Lscala/util/parsing/combinator/Parsers;Lscala/Function0;)Lscala/util/parsing/combinator/Parsers$Parser;
	areturn
  Labels:
  LocalVariableTable: 
   Start  Length  Slot  Name   Signature
   0      6      0    this       Lscala/util/parsing/combinator/syntactical/StandardTokenParsers;
   0      6      1    p       Lscala/Function0;


public scala.util.parsing.combinator.Parsers$Parser phrase(scala.util.parsing.combinator.Parsers$Parser);
  Signature: (Lscala/util/parsing/combinator/Parsers$Parser;)Lscala/util/parsing/combinator/Parsers$Parser;
  Code:
   Stack=2, Locals=2, Args_size=2
	aload_0
	aload_1
	invokestatic	Method scala/util/parsing/combinator/Parsers$class.phrase:(Lscala/util/parsing/combinator/Parsers;Lscala/util/parsing/combinator/Parsers$Parser;)Lscala/util/parsing/combinator/Parsers$Parser;
	areturn
  Labels:
  LocalVariableTable: 
   Start  Length  Slot  Name   Signature
   0      6      0    this       Lscala/util/parsing/combinator/syntactical/StandardTokenParsers;
   0      6      1    p       Lscala/util/parsing/combinator/Parsers$Parser;


public scala.Function1 mkList();
  Signature: ()Lscala/Function1;
  Code:
   Stack=1, Locals=1, Args_size=1
	aload_0
	invokestatic	Method scala/util/parsing/combinator/Parsers$class.mkList:(Lscala/util/parsing/combinator/Parsers;)Lscala/Function1;
	areturn
  Labels:

public scala.util.parsing.combinator.lexical.StdLexical lexical();
  Signature: ()Lscala/util/parsing/combinator/lexical/StdLexical;
  Code:
   Stack=1, Locals=1, Args_size=1
	aload_0
	getfield	Field lexical:Lscala/util/parsing/combinator/lexical/StdLexical;
	areturn
  Labels:

public scala.util.parsing.combinator.Parsers$Parser keyword(java.lang.String);
  Signature: (Ljava/lang/String;)Lscala/util/parsing/combinator/Parsers$Parser;
  Code:
   Stack=3, Locals=2, Args_size=2
	aload_0
	invokevirtual	Method lexical:()Lscala/util/parsing/combinator/lexical/StdLexical;
	invokevirtual	Method scala/util/parsing/combinator/lexical/StdLexical.reserved:()Lscala/collection/mutable/HashSet;
	aload_1
	invokevirtual	Method scala/collection/mutable/HashSet.contains:(Ljava/lang/Object;)Z
	ifne	l1 // aload_0
	aload_0
	invokevirtual	Method lexical:()Lscala/util/parsing/combinator/lexical/StdLexical;
	invokevirtual	Method scala/util/parsing/combinator/lexical/StdLexical.delimiters:()Lscala/collection/mutable/HashSet;
	aload_1
	invokevirtual	Method scala/collection/mutable/HashSet.contains:(Ljava/lang/Object;)Z
	ifeq	l2 // aload_0
l1	aload_0
	aload_1
	invokestatic	Method scala/util/parsing/combinator/syntactical/StdTokenParsers$class.keyword:(Lscala/util/parsing/combinator/syntactical/StdTokenParsers;Ljava/lang/String;)Lscala/util/parsing/combinator/Parsers$Parser;
	goto	l3 // areturn
l2	aload_0
	new	class scala/collection/mutable/StringBuilder
	dup
	invokespecial	Method scala/collection/mutable/StringBuilder."<init>":()V
	ldc_w	String You are trying to parse \"
	invokevirtual	Method scala/collection/mutable/StringBuilder.append:(Ljava/lang/Object;)Lscala/collection/mutable/StringBuilder;
	aload_1
	invokevirtual	Method scala/collection/mutable/StringBuilder.append:(Ljava/lang/Object;)Lscala/collection/mutable/StringBuilder;
	ldc_w	String \", but it is neither contained in the delimiters list, nor in the reserved keyword list of your lexical object
	invokevirtual	Method scala/collection/mutable/StringBuilder.append:(Ljava/lang/Object;)Lscala/collection/mutable/StringBuilder;
	invokevirtual	Method scala/collection/mutable/StringBuilder.toString:()Ljava/lang/String;
	invokeinterface	InterfaceMethod scala/util/parsing/combinator/Parsers.failure:(Ljava/lang/String;)Lscala/util/parsing/combinator/Parsers$Parser;
l3	areturn
  Labels:
   	l1 = 28 // aload_0
   	l2 = 36 // aload_0
   	l3 = 68 // areturn
  LocalVariableTable: 
   Start  Length  Slot  Name   Signature
   0      69      0    this       Lscala/util/parsing/combinator/syntactical/StandardTokenParsers;
   0      69      1    chars       Ljava/lang/String;

  Signature: length = 0x2
   01 13 

public scala.util.parsing.syntax.Tokens lexical();
  Signature: ()Lscala/util/parsing/syntax/Tokens;
  Code:
   Stack=1, Locals=1, Args_size=1
	aload_0
	invokevirtual	Method lexical:()Lscala/util/parsing/combinator/lexical/StdLexical;
	areturn
  Labels:

public scala.util.parsing.combinator.syntactical.StandardTokenParsers();
  Signature: ()V
  Code:
   Stack=3, Locals=1, Args_size=1
	aload_0
	invokespecial	Method java/lang/Object."<init>":()V
	aload_0
	invokestatic	Method scala/util/parsing/combinator/Parsers$class.$init$:(Lscala/util/parsing/combinator/Parsers;)V
	aload_0
	invokestatic	Method scala/util/parsing/combinator/syntactical/StdTokenParsers$class.$init$:(Lscala/util/parsing/combinator/syntactical/StdTokenParsers;)V
	aload_0
	new	class scala/util/parsing/combinator/lexical/StdLexical
	dup
	invokespecial	Method scala/util/parsing/combinator/lexical/StdLexical."<init>":()V
	putfield	Field lexical:Lscala/util/parsing/combinator/lexical/StdLexical;
	return
  Labels:

}

