Compiled from "StdTokenParsers.scala"
public abstract class scala.util.parsing.combinator.syntactical.StdTokenParsers$class extends java.lang.Object
  SourceFile: "StdTokenParsers.scala"
  Scala: length = 0x
   
  InnerClass: 
   public abstract Parser=class scala/util/parsing/combinator/Parsers$Parser of class scala/util/parsing/combinator/Parsers
   public final $anonfun$ident$2=class scala/util/parsing/combinator/syntactical/StdTokenParsers$$anonfun$ident$2 of class scala/util/parsing/combinator/syntactical/StdTokenParsers
   public final $anonfun$ident$1=class scala/util/parsing/combinator/syntactical/StdTokenParsers$$anonfun$ident$1 of class scala/util/parsing/combinator/syntactical/StdTokenParsers
   public final $anonfun$keyword$1=class scala/util/parsing/combinator/syntactical/StdTokenParsers$$anonfun$keyword$1 of class scala/util/parsing/combinator/syntactical/StdTokenParsers
   public final $anonfun$stringLit$2=class scala/util/parsing/combinator/syntactical/StdTokenParsers$$anonfun$stringLit$2 of class scala/util/parsing/combinator/syntactical/StdTokenParsers
   public final $anonfun$stringLit$1=class scala/util/parsing/combinator/syntactical/StdTokenParsers$$anonfun$stringLit$1 of class scala/util/parsing/combinator/syntactical/StdTokenParsers
   public final $anonfun$numericLit$2=class scala/util/parsing/combinator/syntactical/StdTokenParsers$$anonfun$numericLit$2 of class scala/util/parsing/combinator/syntactical/StdTokenParsers
   public final $anonfun$numericLit$1=class scala/util/parsing/combinator/syntactical/StdTokenParsers$$anonfun$numericLit$1 of class scala/util/parsing/combinator/syntactical/StdTokenParsers
  minor version: 0
  major version: 49
  Constant pool:
Asciz	SourceFile;
Asciz	StdTokenParsers.scala;
Asciz	keyword;
Asciz	(Lscala/util/parsing/combinator/syntactical/StdTokenParsers;Ljava/lang/String;)Lscala/util/parsing/combinator/Parsers$Parser;;
Asciz	Code;
Asciz	LineNumberTable;
Asciz	scala/util/parsing/combinator/syntactical/StdTokenParsers;
class	scala/util/parsing/combinator/syntactical/StdTokenParsers
Asciz	keywordCache;
Asciz	()Lscala/collection/mutable/HashMap;;
NameAndType	keywordCache:()Lscala/collection/mutable/HashMap;
InterfaceMethod	scala/util/parsing/combinator/syntactical/StdTokenParsers.keywordCache:()Lscala/collection/mutable/HashMap;
Asciz	scala/util/parsing/combinator/syntactical/StdTokenParsers$$anonfun$keyword$1;
class	scala/util/parsing/combinator/syntactical/StdTokenParsers$$anonfun$keyword$1
Asciz	<init>;
Asciz	(Lscala/util/parsing/combinator/syntactical/StdTokenParsers;Ljava/lang/String;)V;
NameAndType	"<init>":(Lscala/util/parsing/combinator/syntactical/StdTokenParsers;Ljava/lang/String;)V
Method	scala/util/parsing/combinator/syntactical/StdTokenParsers$$anonfun$keyword$1."<init>":(Lscala/util/parsing/combinator/syntactical/StdTokenParsers;Ljava/lang/String;)V
Asciz	scala/collection/mutable/MapLike;
class	scala/collection/mutable/MapLike
Asciz	getOrElseUpdate;
Asciz	(Ljava/lang/Object;Lscala/Function0;)Ljava/lang/Object;;
NameAndType	getOrElseUpdate:(Ljava/lang/Object;Lscala/Function0;)Ljava/lang/Object;
InterfaceMethod	scala/collection/mutable/MapLike.getOrElseUpdate:(Ljava/lang/Object;Lscala/Function0;)Ljava/lang/Object;
Asciz	scala/util/parsing/combinator/Parsers$Parser;
class	scala/util/parsing/combinator/Parsers$Parser
Asciz	$this;
Asciz	Lscala/util/parsing/combinator/syntactical/StdTokenParsers;;
Asciz	chars$1;
Asciz	Ljava/lang/String;;
Asciz	LocalVariableTable;
Asciz	numericLit;
Asciz	(Lscala/util/parsing/combinator/syntactical/StdTokenParsers;)Lscala/util/parsing/combinator/Parsers$Parser;;
Asciz	number;
String	number
Asciz	scala/util/parsing/combinator/syntactical/StdTokenParsers$$anonfun$numericLit$1;
class	scala/util/parsing/combinator/syntactical/StdTokenParsers$$anonfun$numericLit$1
Asciz	(Lscala/util/parsing/combinator/syntactical/StdTokenParsers;)V;
NameAndType	"<init>":(Lscala/util/parsing/combinator/syntactical/StdTokenParsers;)V
Method	scala/util/parsing/combinator/syntactical/StdTokenParsers$$anonfun$numericLit$1."<init>":(Lscala/util/parsing/combinator/syntactical/StdTokenParsers;)V
Asciz	scala/util/parsing/combinator/Parsers;
class	scala/util/parsing/combinator/Parsers
Asciz	elem;
Asciz	(Ljava/lang/String;Lscala/Function1;)Lscala/util/parsing/combinator/Parsers$Parser;;
NameAndType	elem:(Ljava/lang/String;Lscala/Function1;)Lscala/util/parsing/combinator/Parsers$Parser;
InterfaceMethod	scala/util/parsing/combinator/Parsers.elem:(Ljava/lang/String;Lscala/Function1;)Lscala/util/parsing/combinator/Parsers$Parser;
Asciz	scala/util/parsing/combinator/syntactical/StdTokenParsers$$anonfun$numericLit$2;
class	scala/util/parsing/combinator/syntactical/StdTokenParsers$$anonfun$numericLit$2
Method	scala/util/parsing/combinator/syntactical/StdTokenParsers$$anonfun$numericLit$2."<init>":(Lscala/util/parsing/combinator/syntactical/StdTokenParsers;)V
Asciz	$up$up;
Asciz	(Lscala/Function1;)Lscala/util/parsing/combinator/Parsers$Parser;;
NameAndType	$up$up:(Lscala/Function1;)Lscala/util/parsing/combinator/Parsers$Parser;
Method	scala/util/parsing/combinator/Parsers$Parser.$up$up:(Lscala/Function1;)Lscala/util/parsing/combinator/Parsers$Parser;
Asciz	stringLit;
Asciz	string literal;
String	string literal
Asciz	scala/util/parsing/combinator/syntactical/StdTokenParsers$$anonfun$stringLit$1;
class	scala/util/parsing/combinator/syntactical/StdTokenParsers$$anonfun$stringLit$1
Method	scala/util/parsing/combinator/syntactical/StdTokenParsers$$anonfun$stringLit$1."<init>":(Lscala/util/parsing/combinator/syntactical/StdTokenParsers;)V
Asciz	scala/util/parsing/combinator/syntactical/StdTokenParsers$$anonfun$stringLit$2;
class	scala/util/parsing/combinator/syntactical/StdTokenParsers$$anonfun$stringLit$2
Method	scala/util/parsing/combinator/syntactical/StdTokenParsers$$anonfun$stringLit$2."<init>":(Lscala/util/parsing/combinator/syntactical/StdTokenParsers;)V
Asciz	ident;
Asciz	identifier;
String	identifier
Asciz	scala/util/parsing/combinator/syntactical/StdTokenParsers$$anonfun$ident$1;
class	scala/util/parsing/combinator/syntactical/StdTokenParsers$$anonfun$ident$1
Method	scala/util/parsing/combinator/syntactical/StdTokenParsers$$anonfun$ident$1."<init>":(Lscala/util/parsing/combinator/syntactical/StdTokenParsers;)V
Asciz	scala/util/parsing/combinator/syntactical/StdTokenParsers$$anonfun$ident$2;
class	scala/util/parsing/combinator/syntactical/StdTokenParsers$$anonfun$ident$2
Method	scala/util/parsing/combinator/syntactical/StdTokenParsers$$anonfun$ident$2."<init>":(Lscala/util/parsing/combinator/syntactical/StdTokenParsers;)V
Asciz	$init$;
Asciz	scala/collection/mutable/HashMap$;
class	scala/collection/mutable/HashMap$
Asciz	MODULE$;
Asciz	Lscala/collection/mutable/HashMap$;;
NameAndType	MODULE$:Lscala/collection/mutable/HashMap$;
Field	scala/collection/mutable/HashMap$.MODULE$:Lscala/collection/mutable/HashMap$;
Asciz	empty;
NameAndType	empty:()Lscala/collection/mutable/HashMap;
Method	scala/collection/mutable/HashMap$.empty:()Lscala/collection/mutable/HashMap;
Asciz	scala$util$parsing$combinator$syntactical$StdTokenParsers$_setter_$keywordCache_$eq;
Asciz	(Lscala/collection/mutable/HashMap;)V;
NameAndType	scala$util$parsing$combinator$syntactical$StdTokenParsers$_setter_$keywordCache_$eq:(Lscala/collection/mutable/HashMap;)V
InterfaceMethod	scala/util/parsing/combinator/syntactical/StdTokenParsers.scala$util$parsing$combinator$syntactical$StdTokenParsers$_setter_$keywordCache_$eq:(Lscala/collection/mutable/HashMap;)V
Asciz	Scala;
Asciz	InnerClasses;
Asciz	Parser;
Asciz	$anonfun$ident$2;
Asciz	$anonfun$ident$1;
Asciz	$anonfun$keyword$1;
Asciz	$anonfun$stringLit$2;
Asciz	$anonfun$stringLit$1;
Asciz	$anonfun$numericLit$2;
Asciz	$anonfun$numericLit$1;
Asciz	scala/util/parsing/combinator/syntactical/StdTokenParsers$class;
class	scala/util/parsing/combinator/syntactical/StdTokenParsers$class
Asciz	java/lang/Object;
class	java/lang/Object

{
public static scala.util.parsing.combinator.Parsers$Parser keyword(scala.util.parsing.combinator.syntactical.StdTokenParsers, java.lang.String);
  Signature: (Lscala/util/parsing/combinator/syntactical/StdTokenParsers;Ljava/lang/String;)Lscala/util/parsing/combinator/Parsers$Parser;
  Code:
   Stack=6, Locals=2, Args_size=2
	aload_0
	invokeinterface	InterfaceMethod scala/util/parsing/combinator/syntactical/StdTokenParsers.keywordCache:()Lscala/collection/mutable/HashMap;
	aload_1
	new	class scala/util/parsing/combinator/syntactical/StdTokenParsers$$anonfun$keyword$1
	dup
	aload_0
	aload_1
	invokespecial	Method scala/util/parsing/combinator/syntactical/StdTokenParsers$$anonfun$keyword$1."<init>":(Lscala/util/parsing/combinator/syntactical/StdTokenParsers;Ljava/lang/String;)V
	invokeinterface	InterfaceMethod scala/collection/mutable/MapLike.getOrElseUpdate:(Ljava/lang/Object;Lscala/Function0;)Ljava/lang/Object;
	checkcast	class scala/util/parsing/combinator/Parsers$Parser
	areturn
  Labels:
  LocalVariableTable: 
   Start  Length  Slot  Name   Signature
   0      25      0    $this       Lscala/util/parsing/combinator/syntactical/StdTokenParsers;
   0      25      1    chars$1       Ljava/lang/String;


public static scala.util.parsing.combinator.Parsers$Parser numericLit(scala.util.parsing.combinator.syntactical.StdTokenParsers);
  Signature: (Lscala/util/parsing/combinator/syntactical/StdTokenParsers;)Lscala/util/parsing/combinator/Parsers$Parser;
  Code:
   Stack=5, Locals=1, Args_size=1
	aload_0
	ldc	String number
	new	class scala/util/parsing/combinator/syntactical/StdTokenParsers$$anonfun$numericLit$1
	dup
	aload_0
	invokespecial	Method scala/util/parsing/combinator/syntactical/StdTokenParsers$$anonfun$numericLit$1."<init>":(Lscala/util/parsing/combinator/syntactical/StdTokenParsers;)V
	invokeinterface	InterfaceMethod scala/util/parsing/combinator/Parsers.elem:(Ljava/lang/String;Lscala/Function1;)Lscala/util/parsing/combinator/Parsers$Parser;
	new	class scala/util/parsing/combinator/syntactical/StdTokenParsers$$anonfun$numericLit$2
	dup
	aload_0
	invokespecial	Method scala/util/parsing/combinator/syntactical/StdTokenParsers$$anonfun$numericLit$2."<init>":(Lscala/util/parsing/combinator/syntactical/StdTokenParsers;)V
	invokevirtual	Method scala/util/parsing/combinator/Parsers$Parser.$up$up:(Lscala/Function1;)Lscala/util/parsing/combinator/Parsers$Parser;
	areturn
  Labels:
  LocalVariableTable: 
   Start  Length  Slot  Name   Signature
   0      28      0    $this       Lscala/util/parsing/combinator/syntactical/StdTokenParsers;


public static scala.util.parsing.combinator.Parsers$Parser stringLit(scala.util.parsing.combinator.syntactical.StdTokenParsers);
  Signature: (Lscala/util/parsing/combinator/syntactical/StdTokenParsers;)Lscala/util/parsing/combinator/Parsers$Parser;
  Code:
   Stack=5, Locals=1, Args_size=1
	aload_0
	ldc	String string literal
	new	class scala/util/parsing/combinator/syntactical/StdTokenParsers$$anonfun$stringLit$1
	dup
	aload_0
	invokespecial	Method scala/util/parsing/combinator/syntactical/StdTokenParsers$$anonfun$stringLit$1."<init>":(Lscala/util/parsing/combinator/syntactical/StdTokenParsers;)V
	invokeinterface	InterfaceMethod scala/util/parsing/combinator/Parsers.elem:(Ljava/lang/String;Lscala/Function1;)Lscala/util/parsing/combinator/Parsers$Parser;
	new	class scala/util/parsing/combinator/syntactical/StdTokenParsers$$anonfun$stringLit$2
	dup
	aload_0
	invokespecial	Method scala/util/parsing/combinator/syntactical/StdTokenParsers$$anonfun$stringLit$2."<init>":(Lscala/util/parsing/combinator/syntactical/StdTokenParsers;)V
	invokevirtual	Method scala/util/parsing/combinator/Parsers$Parser.$up$up:(Lscala/Function1;)Lscala/util/parsing/combinator/Parsers$Parser;
	areturn
  Labels:
  LocalVariableTable: 
   Start  Length  Slot  Name   Signature
   0      28      0    $this       Lscala/util/parsing/combinator/syntactical/StdTokenParsers;


public static scala.util.parsing.combinator.Parsers$Parser ident(scala.util.parsing.combinator.syntactical.StdTokenParsers);
  Signature: (Lscala/util/parsing/combinator/syntactical/StdTokenParsers;)Lscala/util/parsing/combinator/Parsers$Parser;
  Code:
   Stack=5, Locals=1, Args_size=1
	aload_0
	ldc	String identifier
	new	class scala/util/parsing/combinator/syntactical/StdTokenParsers$$anonfun$ident$1
	dup
	aload_0
	invokespecial	Method scala/util/parsing/combinator/syntactical/StdTokenParsers$$anonfun$ident$1."<init>":(Lscala/util/parsing/combinator/syntactical/StdTokenParsers;)V
	invokeinterface	InterfaceMethod scala/util/parsing/combinator/Parsers.elem:(Ljava/lang/String;Lscala/Function1;)Lscala/util/parsing/combinator/Parsers$Parser;
	new	class scala/util/parsing/combinator/syntactical/StdTokenParsers$$anonfun$ident$2
	dup
	aload_0
	invokespecial	Method scala/util/parsing/combinator/syntactical/StdTokenParsers$$anonfun$ident$2."<init>":(Lscala/util/parsing/combinator/syntactical/StdTokenParsers;)V
	invokevirtual	Method scala/util/parsing/combinator/Parsers$Parser.$up$up:(Lscala/Function1;)Lscala/util/parsing/combinator/Parsers$Parser;
	areturn
  Labels:
  LocalVariableTable: 
   Start  Length  Slot  Name   Signature
   0      28      0    $this       Lscala/util/parsing/combinator/syntactical/StdTokenParsers;


public static void $init$(scala.util.parsing.combinator.syntactical.StdTokenParsers);
  Signature: (Lscala/util/parsing/combinator/syntactical/StdTokenParsers;)V
  Code:
   Stack=2, Locals=1, Args_size=1
	aload_0
	getstatic	Field scala/collection/mutable/HashMap$.MODULE$:Lscala/collection/mutable/HashMap$;
	invokevirtual	Method scala/collection/mutable/HashMap$.empty:()Lscala/collection/mutable/HashMap;
	invokeinterface	InterfaceMethod scala/util/parsing/combinator/syntactical/StdTokenParsers.scala$util$parsing$combinator$syntactical$StdTokenParsers$_setter_$keywordCache_$eq:(Lscala/collection/mutable/HashMap;)V
	return
  Labels:
  LocalVariableTable: 
   Start  Length  Slot  Name   Signature
   0      13      0    $this       Lscala/util/parsing/combinator/syntactical/StdTokenParsers;


}

