Compiled from "StdTokenParsers.scala"
public final class scala.util.parsing.combinator.syntactical.StdTokenParsers$$anonfun$keyword$1 extends scala.runtime.AbstractFunction0 implements java.io.Serializable
  SourceFile: "StdTokenParsers.scala"
  Scala: length = 0x
   
  InnerClass: 
   public abstract Parser=class scala/util/parsing/combinator/Parsers$Parser of class scala/util/parsing/combinator/Parsers
   public Keyword=class scala/util/parsing/syntax/StdTokens$Keyword of class scala/util/parsing/syntax/StdTokens
   public final $anonfun$keyword$1=class scala/util/parsing/combinator/syntactical/StdTokenParsers$$anonfun$keyword$1 of class scala/util/parsing/combinator/syntactical/StdTokenParsers
   public final $anonfun$apply$1=class scala/util/parsing/combinator/syntactical/StdTokenParsers$$anonfun$keyword$1$$anonfun$apply$1 of class scala/util/parsing/combinator/syntactical/StdTokenParsers$$anonfun$keyword$1
  minor version: 0
  major version: 49
  Constant pool:
Asciz	SourceFile;
Asciz	StdTokenParsers.scala;
Asciz	<clinit>;
Asciz	()V;
Asciz	Code;
Asciz	serialVersionUID;
Asciz	J;
Asciz	scala/util/parsing/combinator/syntactical/StdTokenParsers$$anonfun$keyword$1;
class	scala/util/parsing/combinator/syntactical/StdTokenParsers$$anonfun$keyword$1
NameAndType	serialVersionUID:J
Field	scala/util/parsing/combinator/syntactical/StdTokenParsers$$anonfun$keyword$1.serialVersionUID:J
Asciz	chars$1;
Asciz	Ljava/lang/String;;
Asciz	$outer;
Asciz	Lscala/util/parsing/combinator/syntactical/StdTokenParsers;;
Asciz	<init>;
Asciz	(Lscala/util/parsing/combinator/syntactical/StdTokenParsers;Ljava/lang/String;)V;
Asciz	LineNumberTable;
Asciz	java/lang/NullPointerException;
class	java/lang/NullPointerException
NameAndType	"<init>":()V
Method	java/lang/NullPointerException."<init>":()V
NameAndType	$outer:Lscala/util/parsing/combinator/syntactical/StdTokenParsers;
Field	scala/util/parsing/combinator/syntactical/StdTokenParsers$$anonfun$keyword$1.$outer:Lscala/util/parsing/combinator/syntactical/StdTokenParsers;
NameAndType	chars$1:Ljava/lang/String;
Field	scala/util/parsing/combinator/syntactical/StdTokenParsers$$anonfun$keyword$1.chars$1:Ljava/lang/String;
Asciz	scala/runtime/AbstractFunction0;
class	scala/runtime/AbstractFunction0
Method	scala/runtime/AbstractFunction0."<init>":()V
Asciz	this;
Asciz	Lscala/util/parsing/combinator/syntactical/StdTokenParsers$$anonfun$keyword$1;;
Asciz	LocalVariableTable;
Asciz	apply;
Asciz	()Ljava/lang/Object;;
Asciz	()Lscala/util/parsing/combinator/Parsers$Parser;;
NameAndType	apply:()Lscala/util/parsing/combinator/Parsers$Parser;
Method	scala/util/parsing/combinator/syntactical/StdTokenParsers$$anonfun$keyword$1.apply:()Lscala/util/parsing/combinator/Parsers$Parser;
Asciz	scala/util/parsing/syntax/StdTokens$Keyword;
class	scala/util/parsing/syntax/StdTokens$Keyword
Asciz	scala/util/parsing/combinator/syntactical/TokenParsers;
class	scala/util/parsing/combinator/syntactical/TokenParsers
Asciz	lexical;
Asciz	()Lscala/util/parsing/syntax/Tokens;;
NameAndType	lexical:()Lscala/util/parsing/syntax/Tokens;
InterfaceMethod	scala/util/parsing/combinator/syntactical/TokenParsers.lexical:()Lscala/util/parsing/syntax/Tokens;
Asciz	scala/util/parsing/syntax/StdTokens;
class	scala/util/parsing/syntax/StdTokens
Asciz	(Lscala/util/parsing/syntax/StdTokens;Ljava/lang/String;)V;
NameAndType	"<init>":(Lscala/util/parsing/syntax/StdTokens;Ljava/lang/String;)V
Method	scala/util/parsing/syntax/StdTokens$Keyword."<init>":(Lscala/util/parsing/syntax/StdTokens;Ljava/lang/String;)V
Asciz	scala/util/parsing/combinator/Parsers;
class	scala/util/parsing/combinator/Parsers
Asciz	accept;
Asciz	(Ljava/lang/Object;)Lscala/util/parsing/combinator/Parsers$Parser;;
NameAndType	accept:(Ljava/lang/Object;)Lscala/util/parsing/combinator/Parsers$Parser;
InterfaceMethod	scala/util/parsing/combinator/Parsers.accept:(Ljava/lang/Object;)Lscala/util/parsing/combinator/Parsers$Parser;
Asciz	scala/util/parsing/combinator/syntactical/StdTokenParsers$$anonfun$keyword$1$$anonfun$apply$1;
class	scala/util/parsing/combinator/syntactical/StdTokenParsers$$anonfun$keyword$1$$anonfun$apply$1
Asciz	(Lscala/util/parsing/combinator/syntactical/StdTokenParsers$$anonfun$keyword$1;)V;
NameAndType	"<init>":(Lscala/util/parsing/combinator/syntactical/StdTokenParsers$$anonfun$keyword$1;)V
Method	scala/util/parsing/combinator/syntactical/StdTokenParsers$$anonfun$keyword$1$$anonfun$apply$1."<init>":(Lscala/util/parsing/combinator/syntactical/StdTokenParsers$$anonfun$keyword$1;)V
Asciz	scala/util/parsing/combinator/Parsers$Parser;
class	scala/util/parsing/combinator/Parsers$Parser
Asciz	$up$up;
Asciz	(Lscala/Function1;)Lscala/util/parsing/combinator/Parsers$Parser;;
NameAndType	$up$up:(Lscala/Function1;)Lscala/util/parsing/combinator/Parsers$Parser;
Method	scala/util/parsing/combinator/Parsers$Parser.$up$up:(Lscala/Function1;)Lscala/util/parsing/combinator/Parsers$Parser;
Asciz	()Lscala/util/parsing/combinator/Parsers$Parser<Ljava/lang/String;>;;
Asciz	Signature;
Asciz	Scala;
Asciz	InnerClasses;
Asciz	Parser;
Asciz	Keyword;
Asciz	scala/util/parsing/combinator/syntactical/StdTokenParsers;
class	scala/util/parsing/combinator/syntactical/StdTokenParsers
Asciz	$anonfun$keyword$1;
Asciz	$anonfun$apply$1;
Asciz	java/io/Serializable;
class	java/io/Serializable

{
public static final long serialVersionUID;
  Signature: J

private final java.lang.String chars$1;
  Signature: Ljava/lang/String;

private final scala.util.parsing.combinator.syntactical.StdTokenParsers $outer;
  Signature: Lscala/util/parsing/combinator/syntactical/StdTokenParsers;

public static {};
  Signature: ()V
  Code:
   Stack=2, Locals=0, Args_size=0
	lconst_0
	putstatic	Field serialVersionUID:J
	return
  Labels:

public scala.util.parsing.combinator.syntactical.StdTokenParsers$$anonfun$keyword$1(scala.util.parsing.combinator.syntactical.StdTokenParsers, java.lang.String);
  Signature: (Lscala/util/parsing/combinator/syntactical/StdTokenParsers;Ljava/lang/String;)V
  Code:
   Stack=2, Locals=3, Args_size=3
	aload_1
	ifnonnull	l1 // aload_0
	new	class java/lang/NullPointerException
	dup
	invokespecial	Method java/lang/NullPointerException."<init>":()V
	athrow
l1	aload_0
	aload_1
	putfield	Field $outer:Lscala/util/parsing/combinator/syntactical/StdTokenParsers;
	aload_0
	aload_2
	putfield	Field chars$1:Ljava/lang/String;
	aload_0
	invokespecial	Method scala/runtime/AbstractFunction0."<init>":()V
	return
  Labels:
   	l1 = 12 // aload_0
  LocalVariableTable: 
   Start  Length  Slot  Name   Signature
   0      27      0    this       Lscala/util/parsing/combinator/syntactical/StdTokenParsers$$anonfun$keyword$1;
   0      27      1    $outer       Lscala/util/parsing/combinator/syntactical/StdTokenParsers;


public final java.lang.Object apply();
  Signature: ()Ljava/lang/Object;
  Code:
   Stack=1, Locals=1, Args_size=1
	aload_0
	invokevirtual	Method apply:()Lscala/util/parsing/combinator/Parsers$Parser;
	areturn
  Labels:

public final scala.util.parsing.combinator.Parsers$Parser apply();
  Signature: ()Lscala/util/parsing/combinator/Parsers$Parser;
  Code:
   Stack=5, Locals=1, Args_size=1
	aload_0
	getfield	Field $outer:Lscala/util/parsing/combinator/syntactical/StdTokenParsers;
	new	class scala/util/parsing/syntax/StdTokens$Keyword
	dup
	aload_0
	getfield	Field $outer:Lscala/util/parsing/combinator/syntactical/StdTokenParsers;
	invokeinterface	InterfaceMethod scala/util/parsing/combinator/syntactical/TokenParsers.lexical:()Lscala/util/parsing/syntax/Tokens;
	checkcast	class scala/util/parsing/syntax/StdTokens
	aload_0
	getfield	Field chars$1:Ljava/lang/String;
	invokespecial	Method scala/util/parsing/syntax/StdTokens$Keyword."<init>":(Lscala/util/parsing/syntax/StdTokens;Ljava/lang/String;)V
	invokeinterface	InterfaceMethod scala/util/parsing/combinator/Parsers.accept:(Ljava/lang/Object;)Lscala/util/parsing/combinator/Parsers$Parser;
	new	class scala/util/parsing/combinator/syntactical/StdTokenParsers$$anonfun$keyword$1$$anonfun$apply$1
	dup
	aload_0
	invokespecial	Method scala/util/parsing/combinator/syntactical/StdTokenParsers$$anonfun$keyword$1$$anonfun$apply$1."<init>":(Lscala/util/parsing/combinator/syntactical/StdTokenParsers$$anonfun$keyword$1;)V
	invokevirtual	Method scala/util/parsing/combinator/Parsers$Parser.$up$up:(Lscala/Function1;)Lscala/util/parsing/combinator/Parsers$Parser;
	areturn
  Labels:
  Signature: length = 0x2
   00 44 

}

