Compiled from "StdTokenParsers.scala"
public final class scala.util.parsing.combinator.syntactical.StdTokenParsers$$anonfun$numericLit$1 extends java.lang.Object implements scala.Function1,scala.ScalaObject,java.io.Serializable
  SourceFile: "StdTokenParsers.scala"
  Scala: length = 0x
   
  InnerClass: 
   public abstract Token=class scala/util/parsing/syntax/Tokens$Token of class scala/util/parsing/syntax/Tokens
   public NumericLit=class scala/util/parsing/syntax/StdTokens$NumericLit of class scala/util/parsing/syntax/StdTokens
   public final $anonfun$numericLit$1=class scala/util/parsing/combinator/syntactical/StdTokenParsers$$anonfun$numericLit$1 of class scala/util/parsing/combinator/syntactical/StdTokenParsers
  minor version: 0
  major version: 49
  Constant pool:
Asciz	SourceFile;
Asciz	StdTokenParsers.scala;
Asciz	<clinit>;
Asciz	()V;
Asciz	Code;
Asciz	serialVersionUID;
Asciz	J;
Asciz	scala/util/parsing/combinator/syntactical/StdTokenParsers$$anonfun$numericLit$1;
class	scala/util/parsing/combinator/syntactical/StdTokenParsers$$anonfun$numericLit$1
NameAndType	serialVersionUID:J
Field	scala/util/parsing/combinator/syntactical/StdTokenParsers$$anonfun$numericLit$1.serialVersionUID:J
Asciz	<init>;
Asciz	(Lscala/util/parsing/combinator/syntactical/StdTokenParsers;)V;
Asciz	LineNumberTable;
Asciz	java/lang/Object;
class	java/lang/Object
NameAndType	"<init>":()V
Method	java/lang/Object."<init>":()V
Asciz	scala/Function1$class;
class	scala/Function1$class
Asciz	$init$;
Asciz	(Lscala/Function1;)V;
NameAndType	$init$:(Lscala/Function1;)V
Method	scala/Function1$class.$init$:(Lscala/Function1;)V
Asciz	this;
Asciz	Lscala/util/parsing/combinator/syntactical/StdTokenParsers$$anonfun$numericLit$1;;
Asciz	$outer;
Asciz	Lscala/util/parsing/combinator/syntactical/StdTokenParsers;;
Asciz	LocalVariableTable;
Asciz	apply;
Asciz	(Ljava/lang/Object;)Ljava/lang/Object;;
Asciz	scala/util/parsing/syntax/Tokens$Token;
class	scala/util/parsing/syntax/Tokens$Token
Asciz	(Lscala/util/parsing/syntax/Tokens$Token;)Z;
NameAndType	apply:(Lscala/util/parsing/syntax/Tokens$Token;)Z
Method	scala/util/parsing/combinator/syntactical/StdTokenParsers$$anonfun$numericLit$1.apply:(Lscala/util/parsing/syntax/Tokens$Token;)Z
Asciz	scala/runtime/BoxesRunTime;
class	scala/runtime/BoxesRunTime
Asciz	boxToBoolean;
Asciz	(Z)Ljava/lang/Boolean;;
NameAndType	boxToBoolean:(Z)Ljava/lang/Boolean;
Method	scala/runtime/BoxesRunTime.boxToBoolean:(Z)Ljava/lang/Boolean;
Asciz	v1;
Asciz	Ljava/lang/Object;;
Asciz	scala/util/parsing/syntax/StdTokens$NumericLit;
class	scala/util/parsing/syntax/StdTokens$NumericLit
Asciz	andThen;
Asciz	(Lscala/Function1;)Lscala/Function1;;
Asciz	(Lscala/Function1;Lscala/Function1;)Lscala/Function1;;
NameAndType	andThen:(Lscala/Function1;Lscala/Function1;)Lscala/Function1;
Method	scala/Function1$class.andThen:(Lscala/Function1;Lscala/Function1;)Lscala/Function1;
Asciz	g;
Asciz	Lscala/Function1;;
Asciz	compose;
NameAndType	compose:(Lscala/Function1;Lscala/Function1;)Lscala/Function1;
Method	scala/Function1$class.compose:(Lscala/Function1;Lscala/Function1;)Lscala/Function1;
Asciz	toString;
Asciz	()Ljava/lang/String;;
Asciz	(Lscala/Function1;)Ljava/lang/String;;
NameAndType	toString:(Lscala/Function1;)Ljava/lang/String;
Method	scala/Function1$class.toString:(Lscala/Function1;)Ljava/lang/String;
Asciz	Scala;
Asciz	InnerClasses;
Asciz	scala/util/parsing/syntax/Tokens;
class	scala/util/parsing/syntax/Tokens
Asciz	Token;
Asciz	scala/util/parsing/syntax/StdTokens;
class	scala/util/parsing/syntax/StdTokens
Asciz	NumericLit;
Asciz	scala/util/parsing/combinator/syntactical/StdTokenParsers;
class	scala/util/parsing/combinator/syntactical/StdTokenParsers
Asciz	$anonfun$numericLit$1;
Asciz	scala/Function1;
class	scala/Function1
Asciz	scala/ScalaObject;
class	scala/ScalaObject
Asciz	java/io/Serializable;
class	java/io/Serializable

{
public static final long serialVersionUID;
  Signature: J

public static {};
  Signature: ()V
  Code:
   Stack=2, Locals=0, Args_size=0
	lconst_0
	putstatic	Field serialVersionUID:J
	return
  Labels:

public scala.util.parsing.combinator.syntactical.StdTokenParsers$$anonfun$numericLit$1(scala.util.parsing.combinator.syntactical.StdTokenParsers);
  Signature: (Lscala/util/parsing/combinator/syntactical/StdTokenParsers;)V
  Code:
   Stack=1, Locals=2, Args_size=2
	aload_0
	invokespecial	Method java/lang/Object."<init>":()V
	aload_0
	invokestatic	Method scala/Function1$class.$init$:(Lscala/Function1;)V
	return
  Labels:
  LocalVariableTable: 
   Start  Length  Slot  Name   Signature
   0      9      0    this       Lscala/util/parsing/combinator/syntactical/StdTokenParsers$$anonfun$numericLit$1;
   0      9      1    $outer       Lscala/util/parsing/combinator/syntactical/StdTokenParsers;


public final java.lang.Object apply(java.lang.Object);
  Signature: (Ljava/lang/Object;)Ljava/lang/Object;
  Code:
   Stack=2, Locals=3, Args_size=2
	aload_0
	aload_1
	checkcast	class scala/util/parsing/syntax/Tokens$Token
	invokevirtual	Method apply:(Lscala/util/parsing/syntax/Tokens$Token;)Z
	istore_2
	iload_2
	invokestatic	Method scala/runtime/BoxesRunTime.boxToBoolean:(Z)Ljava/lang/Boolean;
	areturn
  Labels:
  LocalVariableTable: 
   Start  Length  Slot  Name   Signature
   0      14      0    this       Lscala/util/parsing/combinator/syntactical/StdTokenParsers$$anonfun$numericLit$1;
   0      14      1    v1       Ljava/lang/Object;


public final boolean apply(scala.util.parsing.syntax.Tokens$Token);
  Signature: (Lscala/util/parsing/syntax/Tokens$Token;)Z
  Code:
   Stack=1, Locals=2, Args_size=2
	aload_1
	instanceof	class scala/util/parsing/syntax/StdTokens$NumericLit
	ireturn
  Labels:

public scala.Function1 andThen(scala.Function1);
  Signature: (Lscala/Function1;)Lscala/Function1;
  Code:
   Stack=2, Locals=2, Args_size=2
	aload_0
	aload_1
	invokestatic	Method scala/Function1$class.andThen:(Lscala/Function1;Lscala/Function1;)Lscala/Function1;
	areturn
  Labels:
  LocalVariableTable: 
   Start  Length  Slot  Name   Signature
   0      6      0    this       Lscala/util/parsing/combinator/syntactical/StdTokenParsers$$anonfun$numericLit$1;
   0      6      1    g       Lscala/Function1;


public scala.Function1 compose(scala.Function1);
  Signature: (Lscala/Function1;)Lscala/Function1;
  Code:
   Stack=2, Locals=2, Args_size=2
	aload_0
	aload_1
	invokestatic	Method scala/Function1$class.compose:(Lscala/Function1;Lscala/Function1;)Lscala/Function1;
	areturn
  Labels:
  LocalVariableTable: 
   Start  Length  Slot  Name   Signature
   0      6      0    this       Lscala/util/parsing/combinator/syntactical/StdTokenParsers$$anonfun$numericLit$1;
   0      6      1    g       Lscala/Function1;


public java.lang.String toString();
  Signature: ()Ljava/lang/String;
  Code:
   Stack=1, Locals=1, Args_size=1
	aload_0
	invokestatic	Method scala/Function1$class.toString:(Lscala/Function1;)Ljava/lang/String;
	areturn
  Labels:

}

