Compiled from "Attribute.scala"
public final class scala.xml.Attribute$ extends java.lang.Object implements scala.ScalaObject
  SourceFile: "Attribute.scala"
  Scala: length = 0x
   
  minor version: 0
  major version: 49
  Constant pool:
Asciz	SourceFile;
Asciz	Attribute.scala;
Asciz	Scala;
Asciz	MODULE$;
Asciz	Lscala/xml/Attribute$;;
Asciz	<clinit>;
Asciz	()V;
Asciz	Code;
Asciz	scala/xml/Attribute$;
class	scala/xml/Attribute$
Asciz	<init>;
NameAndType	"<init>":()V
Method	scala/xml/Attribute$."<init>":()V
Asciz	LineNumberTable;
Asciz	java/lang/Object;
class	java/lang/Object
Method	java/lang/Object."<init>":()V
NameAndType	MODULE$:Lscala/xml/Attribute$;
Field	scala/xml/Attribute$.MODULE$:Lscala/xml/Attribute$;
Asciz	apply;
Asciz	(Lscala/Option;Ljava/lang/String;Lscala/collection/Seq;Lscala/xml/MetaData;)Lscala/xml/Attribute;;
Asciz	scala/None$;
class	scala/None$
Asciz	Lscala/None$;;
NameAndType	MODULE$:Lscala/None$;
Field	scala/None$.MODULE$:Lscala/None$;
Asciz	equals;
Asciz	(Ljava/lang/Object;)Z;
NameAndType	equals:(Ljava/lang/Object;)Z
Method	java/lang/Object.equals:(Ljava/lang/Object;)Z
Asciz	scala/xml/UnprefixedAttribute;
class	scala/xml/UnprefixedAttribute
Asciz	(Ljava/lang/String;Lscala/collection/Seq;Lscala/xml/MetaData;)V;
NameAndType	"<init>":(Ljava/lang/String;Lscala/collection/Seq;Lscala/xml/MetaData;)V
Method	scala/xml/UnprefixedAttribute."<init>":(Ljava/lang/String;Lscala/collection/Seq;Lscala/xml/MetaData;)V
Asciz	scala/MatchError;
class	scala/MatchError
Asciz	scala/Option;
class	scala/Option
Asciz	toString;
Asciz	()Ljava/lang/String;;
NameAndType	toString:()Ljava/lang/String;
Method	scala/Option.toString:()Ljava/lang/String;
Asciz	(Ljava/lang/String;)V;
NameAndType	"<init>":(Ljava/lang/String;)V
Method	scala/MatchError."<init>":(Ljava/lang/String;)V
Asciz	scala/Some;
class	scala/Some
Asciz	x;
Asciz	Ljava/lang/Object;;
NameAndType	x:Ljava/lang/Object;
Field	scala/Some.x:Ljava/lang/Object;
Asciz	java/lang/String;
class	java/lang/String
Asciz	scala/xml/PrefixedAttribute;
class	scala/xml/PrefixedAttribute
Asciz	(Ljava/lang/String;Ljava/lang/String;Lscala/collection/Seq;Lscala/xml/MetaData;)V;
NameAndType	"<init>":(Ljava/lang/String;Ljava/lang/String;Lscala/collection/Seq;Lscala/xml/MetaData;)V
Method	scala/xml/PrefixedAttribute."<init>":(Ljava/lang/String;Ljava/lang/String;Lscala/collection/Seq;Lscala/xml/MetaData;)V
Asciz	this;
Asciz	pre;
Asciz	Lscala/Option;;
Asciz	key;
Asciz	Ljava/lang/String;;
Asciz	value;
Asciz	Lscala/collection/Seq;;
Asciz	next;
Asciz	Lscala/xml/MetaData;;
Asciz	temp17;
Asciz	Lscala/Some;;
Asciz	temp18;
Asciz	LocalVariableTable;
Asciz	(Lscala/Option<Ljava/lang/String;>;Ljava/lang/String;Lscala/collection/Seq<Lscala/xml/Node;>;Lscala/xml/MetaData;)Lscala/xml/Attribute;;
Asciz	Signature;
Asciz	(Ljava/lang/String;Ljava/lang/String;Lscala/collection/Seq;Lscala/xml/MetaData;)Lscala/xml/Attribute;;
Asciz	;
String	
Asciz	(Ljava/lang/String;Ljava/lang/String;Lscala/collection/Seq<Lscala/xml/Node;>;Lscala/xml/MetaData;)Lscala/xml/Attribute;;
Asciz	(Ljava/lang/String;Ljava/lang/String;Ljava/lang/String;Lscala/xml/MetaData;)Lscala/xml/Attribute;;
Asciz	(Ljava/lang/String;Ljava/lang/String;Lscala/xml/MetaData;)V;
NameAndType	"<init>":(Ljava/lang/String;Ljava/lang/String;Lscala/xml/MetaData;)V
Method	scala/xml/UnprefixedAttribute."<init>":(Ljava/lang/String;Ljava/lang/String;Lscala/xml/MetaData;)V
Asciz	(Ljava/lang/String;Ljava/lang/String;Ljava/lang/String;Lscala/xml/MetaData;)V;
NameAndType	"<init>":(Ljava/lang/String;Ljava/lang/String;Ljava/lang/String;Lscala/xml/MetaData;)V
Method	scala/xml/PrefixedAttribute."<init>":(Ljava/lang/String;Ljava/lang/String;Ljava/lang/String;Lscala/xml/MetaData;)V
Asciz	(Ljava/lang/String;Lscala/collection/Seq;Lscala/xml/MetaData;)Lscala/xml/Attribute;;
Asciz	(Ljava/lang/String;Lscala/collection/Seq<Lscala/xml/Node;>;Lscala/xml/MetaData;)Lscala/xml/Attribute;;
Asciz	unapply;
Asciz	(Lscala/xml/Attribute;)Lscala/Option;;
Asciz	scala/Tuple4;
class	scala/Tuple4
NameAndType	pre:()Ljava/lang/String;
Method	scala/xml/PrefixedAttribute.pre:()Ljava/lang/String;
NameAndType	key:()Ljava/lang/String;
Method	scala/xml/PrefixedAttribute.key:()Ljava/lang/String;
Asciz	()Lscala/collection/Seq;;
NameAndType	value:()Lscala/collection/Seq;
Method	scala/xml/PrefixedAttribute.value:()Lscala/collection/Seq;
Asciz	()Lscala/xml/MetaData;;
NameAndType	next:()Lscala/xml/MetaData;
Method	scala/xml/PrefixedAttribute.next:()Lscala/xml/MetaData;
Asciz	(Ljava/lang/Object;Ljava/lang/Object;Ljava/lang/Object;Ljava/lang/Object;)V;
NameAndType	"<init>":(Ljava/lang/Object;Ljava/lang/Object;Ljava/lang/Object;Ljava/lang/Object;)V
Method	scala/Tuple4."<init>":(Ljava/lang/Object;Ljava/lang/Object;Ljava/lang/Object;Ljava/lang/Object;)V
Asciz	(Ljava/lang/Object;)V;
NameAndType	"<init>":(Ljava/lang/Object;)V
Method	scala/Some."<init>":(Ljava/lang/Object;)V
Asciz	_2;
Asciz	()Ljava/lang/Object;;
NameAndType	_2:()Ljava/lang/Object;
Method	scala/Tuple4._2:()Ljava/lang/Object;
Asciz	_3;
NameAndType	_3:()Ljava/lang/Object;
Method	scala/Tuple4._3:()Ljava/lang/Object;
Asciz	scala/collection/Seq;
class	scala/collection/Seq
Asciz	_4;
NameAndType	_4:()Ljava/lang/Object;
Method	scala/Tuple4._4:()Ljava/lang/Object;
Asciz	scala/xml/MetaData;
class	scala/xml/MetaData
Asciz	scala/Tuple3;
class	scala/Tuple3
Asciz	(Ljava/lang/Object;Ljava/lang/Object;Ljava/lang/Object;)V;
NameAndType	"<init>":(Ljava/lang/Object;Ljava/lang/Object;Ljava/lang/Object;)V
Method	scala/Tuple3."<init>":(Ljava/lang/Object;Ljava/lang/Object;Ljava/lang/Object;)V
Method	scala/xml/MetaData.toString:()Ljava/lang/String;
Method	scala/xml/UnprefixedAttribute.key:()Ljava/lang/String;
Method	scala/xml/UnprefixedAttribute.value:()Lscala/collection/Seq;
Method	scala/xml/UnprefixedAttribute.next:()Lscala/xml/MetaData;
Asciz	_1;
NameAndType	_1:()Ljava/lang/Object;
Method	scala/Tuple3._1:()Ljava/lang/Object;
Method	scala/Tuple3._2:()Ljava/lang/Object;
Method	scala/Tuple3._3:()Ljava/lang/Object;
Asciz	Lscala/xml/Attribute;;
Asciz	temp2;
Asciz	Lscala/xml/PrefixedAttribute;;
Asciz	temp3;
Asciz	temp4;
Asciz	Lscala/Tuple4;;
Asciz	temp6;
Asciz	temp7;
Asciz	temp8;
Asciz	temp9;
Asciz	Lscala/xml/UnprefixedAttribute;;
Asciz	temp10;
Asciz	temp11;
Asciz	Lscala/Tuple3;;
Asciz	temp12;
Asciz	temp13;
Asciz	temp14;
Asciz	(Lscala/xml/Attribute;)Lscala/Option<Lscala/Tuple3<Ljava/lang/String;Lscala/collection/Seq<Lscala/xml/Node;>;Lscala/xml/MetaData;>;>;;
Asciz	scala/ScalaObject;
class	scala/ScalaObject

{
public static final scala.xml.Attribute$ MODULE$;
  Signature: Lscala/xml/Attribute$;

public static {};
  Signature: ()V
  Code:
   Stack=1, Locals=0, Args_size=0
	new	class scala/xml/Attribute$
	invokespecial	Method "<init>":()V
	return
  Labels:

private scala.xml.Attribute$();
  Signature: ()V
  Code:
   Stack=1, Locals=1, Args_size=1
	aload_0
	invokespecial	Method java/lang/Object."<init>":()V
	aload_0
	putstatic	Field MODULE$:Lscala/xml/Attribute$;
	return
  Labels:

public scala.xml.Attribute apply(scala.Option, java.lang.String, scala.collection.Seq, scala.xml.MetaData);
  Signature: (Lscala/Option;Ljava/lang/String;Lscala/collection/Seq;Lscala/xml/MetaData;)Lscala/xml/Attribute;
  Code:
   Stack=6, Locals=7, Args_size=5
	getstatic	Field scala/None$.MODULE$:Lscala/None$;
	dup
	ifnonnull	l1 // aload_1
	pop
	aload_1
	ifnull	l2 // iconst_1
	goto	l3 // aload_1
l1	aload_1
	invokevirtual	Method java/lang/Object.equals:(Ljava/lang/Object;)Z
	ifeq	l3 // aload_1
l2	iconst_1
	ifeq	l4 // new
	new	class scala/xml/UnprefixedAttribute
	dup
	aload_2
	aload_3
	aload	4
	invokespecial	Method scala/xml/UnprefixedAttribute."<init>":(Ljava/lang/String;Lscala/collection/Seq;Lscala/xml/MetaData;)V
	goto	l5 // areturn
l4	new	class scala/MatchError
	dup
	aload_1
	invokevirtual	Method scala/Option.toString:()Ljava/lang/String;
	invokespecial	Method scala/MatchError."<init>":(Ljava/lang/String;)V
	athrow
l3	aload_1
	instanceof	class scala/Some
	ifeq	l6 // new
	aload_1
	checkcast	class scala/Some
	astore	5
	aload	5
	getfield	Field scala/Some.x:Ljava/lang/Object;
	checkcast	class java/lang/String
	astore	6
	iconst_1
	ifeq	l7 // new
	new	class scala/xml/PrefixedAttribute
	dup
	aload	6
	aload_2
	aload_3
	aload	4
	invokespecial	Method scala/xml/PrefixedAttribute."<init>":(Ljava/lang/String;Ljava/lang/String;Lscala/collection/Seq;Lscala/xml/MetaData;)V
l5	areturn
l7	new	class scala/MatchError
	dup
	aload_1
	invokevirtual	Method scala/Option.toString:()Ljava/lang/String;
	invokespecial	Method scala/MatchError."<init>":(Ljava/lang/String;)V
	athrow
l6	new	class scala/MatchError
	dup
	aload_1
	invokevirtual	Method scala/Option.toString:()Ljava/lang/String;
	invokespecial	Method scala/MatchError."<init>":(Ljava/lang/String;)V
	athrow
  Labels:
   	l1 = 15 // aload_1
   	l2 = 22 // iconst_1
   	l4 = 40 // new
   	l3 = 52 // aload_1
   	l5 = 92 // areturn
   	l7 = 93 // new
   	l6 = 105 // new
  LocalVariableTable: 
   Start  Length  Slot  Name   Signature
   0      117      0    this       Lscala/xml/Attribute$;
   0      117      1    pre       Lscala/Option;
   0      117      2    key       Ljava/lang/String;
   0      117      3    value       Lscala/collection/Seq;
   0      117      4    next       Lscala/xml/MetaData;
   65      27      5    temp17       Lscala/Some;
   93      12      5    temp17       Lscala/Some;
   75      17      6    temp18       Ljava/lang/String;
   93      12      6    temp18       Ljava/lang/String;

  Signature: length = 0x2
   00 49 

public scala.xml.Attribute apply(java.lang.String, java.lang.String, scala.collection.Seq, scala.xml.MetaData);
  Signature: (Ljava/lang/String;Ljava/lang/String;Lscala/collection/Seq;Lscala/xml/MetaData;)Lscala/xml/Attribute;
  Code:
   Stack=6, Locals=6, Args_size=5
	aload_1
	dup
	pop
	ifnull	l1 // new
	aload_1
	aconst_null
	invokevirtual	Method java/lang/Object.equals:(Ljava/lang/Object;)Z
	ifne	l1 // new
	aload_1
	ldc	String 
	astore	5
	dup
	ifnonnull	l2 // aload
	pop
	aload	5
	ifnull	l1 // new
	goto	l3 // new
l2	aload	5
	invokevirtual	Method java/lang/Object.equals:(Ljava/lang/Object;)Z
	ifeq	l3 // new
l1	new	class scala/xml/UnprefixedAttribute
	dup
	aload_2
	aload_3
	aload	4
	invokespecial	Method scala/xml/UnprefixedAttribute."<init>":(Ljava/lang/String;Lscala/collection/Seq;Lscala/xml/MetaData;)V
	goto	l4 // areturn
l3	new	class scala/xml/PrefixedAttribute
	dup
	aload_1
	aload_2
	aload_3
	aload	4
	invokespecial	Method scala/xml/PrefixedAttribute."<init>":(Ljava/lang/String;Ljava/lang/String;Lscala/collection/Seq;Lscala/xml/MetaData;)V
l4	areturn
  Labels:
   	l2 = 32 // aload
   	l1 = 40 // new
   	l3 = 54 // new
   	l4 = 66 // areturn
  LocalVariableTable: 
   Start  Length  Slot  Name   Signature
   0      67      0    this       Lscala/xml/Attribute$;
   0      67      1    pre       Ljava/lang/String;
   0      67      2    key       Ljava/lang/String;
   0      67      3    value       Lscala/collection/Seq;
   0      67      4    next       Lscala/xml/MetaData;

  Signature: length = 0x2
   00 4E 

public scala.xml.Attribute apply(java.lang.String, java.lang.String, java.lang.String, scala.xml.MetaData);
  Signature: (Ljava/lang/String;Ljava/lang/String;Ljava/lang/String;Lscala/xml/MetaData;)Lscala/xml/Attribute;
  Code:
   Stack=6, Locals=6, Args_size=5
	aload_1
	dup
	pop
	ifnull	l1 // new
	aload_1
	aconst_null
	invokevirtual	Method java/lang/Object.equals:(Ljava/lang/Object;)Z
	ifne	l1 // new
	aload_1
	ldc	String 
	astore	5
	dup
	ifnonnull	l2 // aload
	pop
	aload	5
	ifnull	l1 // new
	goto	l3 // new
l2	aload	5
	invokevirtual	Method java/lang/Object.equals:(Ljava/lang/Object;)Z
	ifeq	l3 // new
l1	new	class scala/xml/UnprefixedAttribute
	dup
	aload_2
	aload_3
	aload	4
	invokespecial	Method scala/xml/UnprefixedAttribute."<init>":(Ljava/lang/String;Ljava/lang/String;Lscala/xml/MetaData;)V
	goto	l4 // areturn
l3	new	class scala/xml/PrefixedAttribute
	dup
	aload_1
	aload_2
	aload_3
	aload	4
	invokespecial	Method scala/xml/PrefixedAttribute."<init>":(Ljava/lang/String;Ljava/lang/String;Ljava/lang/String;Lscala/xml/MetaData;)V
l4	areturn
  Labels:
   	l2 = 32 // aload
   	l1 = 40 // new
   	l3 = 54 // new
   	l4 = 66 // areturn
  LocalVariableTable: 
   Start  Length  Slot  Name   Signature
   0      67      0    this       Lscala/xml/Attribute$;
   0      67      1    pre       Ljava/lang/String;
   0      67      2    key       Ljava/lang/String;
   0      67      3    value       Ljava/lang/String;
   0      67      4    next       Lscala/xml/MetaData;


public scala.xml.Attribute apply(java.lang.String, scala.collection.Seq, scala.xml.MetaData);
  Signature: (Ljava/lang/String;Lscala/collection/Seq;Lscala/xml/MetaData;)Lscala/xml/Attribute;
  Code:
   Stack=5, Locals=4, Args_size=4
	new	class scala/xml/UnprefixedAttribute
	dup
	aload_1
	aload_2
	aload_3
	invokespecial	Method scala/xml/UnprefixedAttribute."<init>":(Ljava/lang/String;Lscala/collection/Seq;Lscala/xml/MetaData;)V
	areturn
  Labels:
  LocalVariableTable: 
   Start  Length  Slot  Name   Signature
   0      11      0    this       Lscala/xml/Attribute$;
   0      11      1    key       Ljava/lang/String;
   0      11      2    value       Lscala/collection/Seq;
   0      11      3    next       Lscala/xml/MetaData;

  Signature: length = 0x2
   00 57 

public scala.Option unapply(scala.xml.Attribute);
  Signature: (Lscala/xml/Attribute;)Lscala/Option;
  Code:
   Stack=8, Locals=14, Args_size=2
	aload_1
	instanceof	class scala/xml/PrefixedAttribute
	ifeq	l1 // aload_1
	aload_1
	checkcast	class scala/xml/PrefixedAttribute
	astore_2
	new	class scala/Some
	dup
	new	class scala/Tuple4
	dup
	aload_2
	invokevirtual	Method scala/xml/PrefixedAttribute.pre:()Ljava/lang/String;
	aload_2
	invokevirtual	Method scala/xml/PrefixedAttribute.key:()Ljava/lang/String;
	aload_2
	invokevirtual	Method scala/xml/PrefixedAttribute.value:()Lscala/collection/Seq;
	aload_2
	invokevirtual	Method scala/xml/PrefixedAttribute.next:()Lscala/xml/MetaData;
	invokespecial	Method scala/Tuple4."<init>":(Ljava/lang/Object;Ljava/lang/Object;Ljava/lang/Object;Ljava/lang/Object;)V
	invokespecial	Method scala/Some."<init>":(Ljava/lang/Object;)V
	astore_3
	iconst_1
	ifeq	l2 // iconst_1
	aload_3
	getfield	Field scala/Some.x:Ljava/lang/Object;
	checkcast	class scala/Tuple4
	astore	4
	aload	4
	invokevirtual	Method scala/Tuple4._2:()Ljava/lang/Object;
	checkcast	class java/lang/String
	astore	5
	aload	4
	invokevirtual	Method scala/Tuple4._3:()Ljava/lang/Object;
	checkcast	class scala/collection/Seq
	astore	6
	aload	4
	invokevirtual	Method scala/Tuple4._4:()Ljava/lang/Object;
	checkcast	class scala/xml/MetaData
	astore	7
	iconst_1
	ifeq	l3 // new
	new	class scala/Some
	dup
	new	class scala/Tuple3
	dup
	aload	5
	aload	6
	aload	7
	invokespecial	Method scala/Tuple3."<init>":(Ljava/lang/Object;Ljava/lang/Object;Ljava/lang/Object;)V
	invokespecial	Method scala/Some."<init>":(Ljava/lang/Object;)V
	goto	l4 // areturn
l3	new	class scala/MatchError
	dup
	aload_1
	checkcast	class scala/xml/MetaData
	invokevirtual	Method scala/xml/MetaData.toString:()Ljava/lang/String;
	invokespecial	Method scala/MatchError."<init>":(Ljava/lang/String;)V
	athrow
l2	iconst_1
	ifne	l5 // getstatic
	new	class scala/MatchError
	dup
	aload_1
	checkcast	class scala/xml/MetaData
	invokevirtual	Method scala/xml/MetaData.toString:()Ljava/lang/String;
	invokespecial	Method scala/MatchError."<init>":(Ljava/lang/String;)V
	athrow
l1	aload_1
	instanceof	class scala/xml/UnprefixedAttribute
	ifeq	l6 // iconst_1
	aload_1
	checkcast	class scala/xml/UnprefixedAttribute
	astore	8
	new	class scala/Some
	dup
	new	class scala/Tuple3
	dup
	aload	8
	invokevirtual	Method scala/xml/UnprefixedAttribute.key:()Ljava/lang/String;
	aload	8
	invokevirtual	Method scala/xml/UnprefixedAttribute.value:()Lscala/collection/Seq;
	aload	8
	invokevirtual	Method scala/xml/UnprefixedAttribute.next:()Lscala/xml/MetaData;
	invokespecial	Method scala/Tuple3."<init>":(Ljava/lang/Object;Ljava/lang/Object;Ljava/lang/Object;)V
	invokespecial	Method scala/Some."<init>":(Ljava/lang/Object;)V
	astore	9
	iconst_1
	ifeq	l7 // iconst_1
	aload	9
	getfield	Field scala/Some.x:Ljava/lang/Object;
	checkcast	class scala/Tuple3
	astore	10
	aload	10
	invokevirtual	Method scala/Tuple3._1:()Ljava/lang/Object;
	checkcast	class java/lang/String
	astore	11
	aload	10
	invokevirtual	Method scala/Tuple3._2:()Ljava/lang/Object;
	checkcast	class scala/collection/Seq
	astore	12
	aload	10
	invokevirtual	Method scala/Tuple3._3:()Ljava/lang/Object;
	checkcast	class scala/xml/MetaData
	astore	13
	iconst_1
	ifeq	l8 // new
	new	class scala/Some
	dup
	new	class scala/Tuple3
	dup
	aload	11
	aload	12
	aload	13
	invokespecial	Method scala/Tuple3."<init>":(Ljava/lang/Object;Ljava/lang/Object;Ljava/lang/Object;)V
	invokespecial	Method scala/Some."<init>":(Ljava/lang/Object;)V
	goto	l4 // areturn
l8	new	class scala/MatchError
	dup
	aload_1
	checkcast	class scala/xml/MetaData
	invokevirtual	Method scala/xml/MetaData.toString:()Ljava/lang/String;
	invokespecial	Method scala/MatchError."<init>":(Ljava/lang/String;)V
	athrow
l7	iconst_1
	ifne	l5 // getstatic
	new	class scala/MatchError
	dup
	aload_1
	checkcast	class scala/xml/MetaData
	invokevirtual	Method scala/xml/MetaData.toString:()Ljava/lang/String;
	invokespecial	Method scala/MatchError."<init>":(Ljava/lang/String;)V
	athrow
l6	iconst_1
	ifeq	l9 // new
l5	getstatic	Field scala/None$.MODULE$:Lscala/None$;
l4	areturn
l9	new	class scala/MatchError
	dup
	aload_1
	checkcast	class scala/xml/MetaData
	invokevirtual	Method scala/xml/MetaData.toString:()Ljava/lang/String;
	invokespecial	Method scala/MatchError."<init>":(Ljava/lang/String;)V
	athrow
  Labels:
   	l3 = 113 // new
   	l2 = 128 // iconst_1
   	l1 = 147 // aload_1
   	l8 = 262 // new
   	l7 = 277 // iconst_1
   	l6 = 296 // iconst_1
   	l5 = 300 // getstatic
   	l4 = 303 // areturn
   	l9 = 304 // new
  LocalVariableTable: 
   Start  Length  Slot  Name   Signature
   0      319      0    this       Lscala/xml/Attribute$;
   0      319      1    x       Lscala/xml/Attribute;
   12      135      2    temp2       Lscala/xml/PrefixedAttribute;
   300      3      2    temp2       Lscala/xml/PrefixedAttribute;
   43      104      3    temp3       Lscala/Some;
   300      3      3    temp3       Lscala/Some;
   56      72      4    temp4       Lscala/Tuple4;
   66      62      5    temp6       Ljava/lang/String;
   76      52      6    temp7       Lscala/collection/Seq;
   86      42      7    temp8       Lscala/xml/MetaData;
   160      136      8    temp9       Lscala/xml/UnprefixedAttribute;
   191      105      9    temp10       Lscala/Some;
   205      72      10    temp11       Lscala/Tuple3;
   215      62      11    temp12       Ljava/lang/String;
   225      52      12    temp13       Lscala/collection/Seq;
   235      42      13    temp14       Lscala/xml/MetaData;

  Signature: length = 0x2
   00 FFFFFF99 

}

