Compiled from "Document.scala"
public class scala.xml.Document extends scala.xml.NodeSeq implements scala.xml.pull.XMLEvent,scala.ScalaObject,java.io.Serializable
  SourceFile: "Document.scala"
  ScalaSig: length = 0x49F
   05 00 FFFFFF81 20 06 08 01 02 FFFFFF84 FFFFFF80 FFFFFF80 FFFFFF80 00 07 02 08
   44 6F 63 75 6D 65 6E 74 0A 02 03 04 01 03 78 6D
   6C 0A 01 05 01 05 73 63 61 6C 61 03 00 13 04 00
   08 0C 12 10 02 09 0A 0D 01 02 09 02 0B 02 02 07
   4E 6F 64 65 53 65 71 10 02 0D 10 0D 01 0E 0A 02
   0F 02 01 04 70 75 6C 6C 09 02 11 0E 02 08 58 4D
   4C 45 76 65 6E 74 10 02 13 14 0D 01 04 09 02 15
   04 02 0B 53 63 61 6C 61 4F 62 6A 65 63 74 08 05
   17 00 FFFFFF84 00 18 01 06 3C 69 6E 69 74 3E 14 01 19
   10 02 09 00 08 07 1B 00 FFFFFFC0 FFFFFF80 FFFFFF84 00 1C 01 08 63
   68 69 6C 64 72 65 6E 15 01 1D 10 03 1E 26 29 0E
   02 1F 24 0E 02 20 23 0D 01 21 0A 02 22 06 01 06
   3C 72 6F 6F 74 3E 09 01 05 09 02 25 04 01 07 70
   61 63 6B 61 67 65 09 02 27 28 02 03 53 65 71 0A
   02 25 04 10 02 09 2A 09 02 2B 02 02 04 4E 6F 64
   65 08 07 2D 00 FFFFFFC0 FFFFFF80 FFFFFF84 00 2E 01 0C 63 68 69 6C
   64 72 65 6E 5F 24 65 71 14 02 2F 32 10 02 13 30
   09 02 31 04 02 04 55 6E 69 74 08 07 33 2C FFFFFF81 FFFFFF80
   FFFFFFC0 00 1D 01 03 78 24 31 08 06 35 00 FFFFFFA0 FFFFFFA0 04 1D
   01 09 63 68 69 6C 64 72 65 6E 20 08 07 37 00 FFFFFFC0
   FFFFFF80 FFFFFF84 00 38 01 07 64 6F 63 45 6C 65 6D 15 01 29
   08 07 3A 00 FFFFFFC0 FFFFFF80 FFFFFF84 00 3B 01 0B 64 6F 63 45 6C
   65 6D 5F 24 65 71 14 02 2F 3C 08 07 33 39 FFFFFF81 FFFFFF80
   FFFFFFC0 00 29 08 06 3E 00 FFFFFFA0 FFFFFFA0 04 29 01 08 64 6F 63
   45 6C 65 6D 20 08 07 40 00 FFFFFFC0 FFFFFF80 FFFFFF84 00 41 01 03
   64 74 64 15 01 42 10 02 43 45 0D 01 44 0A 02 40
   02 09 02 46 44 02 03 44 54 44 08 07 48 00 FFFFFFC0 FFFFFF80
   FFFFFF84 00 49 01 07 64 74 64 5F 24 65 71 14 02 2F 4A
   08 07 33 47 FFFFFF81 FFFFFF80 FFFFFFC0 00 42 08 06 4C 00 FFFFFFA0 FFFFFFA0 04
   42 01 04 64 74 64 20 08 05 4E 00 FFFFFF84 00 4F 01 09
   6E 6F 74 61 74 69 6F 6E 73 15 01 50 10 03 1E 26
   51 10 02 43 52 09 02 53 44 02 0C 4E 6F 74 61 74
   69 6F 6E 44 65 63 6C 08 05 55 00 FFFFFF84 00 56 01 10
   75 6E 70 61 72 73 65 64 45 6E 74 69 74 69 65 73
   15 01 57 10 03 1E 26 58 10 02 43 59 09 02 5A 44
   02 0A 45 6E 74 69 74 79 44 65 63 6C 08 07 5C 00
   FFFFFFC0 FFFFFF80 FFFFFF84 00 5D 01 07 62 61 73 65 55 52 49 15 01
   5E 10 02 5F 62 0E 02 13 60 09 02 61 04 01 06 50
   72 65 64 65 66 09 02 63 64 02 06 53 74 72 69 6E
   67 0A 02 61 04 08 07 66 00 FFFFFFC0 FFFFFF80 FFFFFF84 00 67 01 0B
   62 61 73 65 55 52 49 5F 24 65 71 14 02 2F 68 08
   07 33 65 FFFFFF81 FFFFFF80 FFFFFFC0 00 5E 08 06 6A 00 FFFFFFA0 FFFFFFA0 04 5E
   01 08 62 61 73 65 55 52 49 20 08 07 6C 00 FFFFFFC0 FFFFFF80
   FFFFFF84 00 6D 01 08 65 6E 63 6F 64 69 6E 67 15 01 6E
   10 03 13 6F 5E 09 02 70 04 02 06 4F 70 74 69 6F
   6E 08 07 72 00 FFFFFFC0 FFFFFF80 FFFFFF84 00 73 01 0C 65 6E 63 6F
   64 69 6E 67 5F 24 65 71 14 02 2F 74 08 07 33 71
   FFFFFF81 FFFFFF80 FFFFFFC0 00 6E 08 06 76 00 FFFFFFA0 FFFFFFA0 04 6E 01 09 65
   6E 63 6F 64 69 6E 67 20 08 07 78 00 FFFFFFC0 FFFFFF80 FFFFFF84 00
   79 01 0A 73 74 61 6E 64 41 6C 6F 6E 65 15 01 7A
   10 03 13 6F 7B 10 02 13 7C 09 02 7D 04 02 07 42
   6F 6F 6C 65 61 6E 08 08 7F 00 FFFFFFC0 FFFFFF80 FFFFFF84 00 FFFFFF81 00
   01 0E 73 74 61 6E 64 41 6C 6F 6E 65 5F 24 65 71
   14 03 2F FFFFFF81 01 08 07 33 7E FFFFFF81 FFFFFF80 FFFFFFC0 00 7A 08 07
   FFFFFF81 03 00 FFFFFFA0 FFFFFFA0 04 7A 01 0B 73 74 61 6E 64 41 6C
   6F 6E 65 20 08 08 FFFFFF81 05 00 FFFFFFC0 FFFFFF80 FFFFFF84 00 6D 01 07
   76 65 72 73 69 6F 6E 08 09 FFFFFF81 07 00 FFFFFFC0 FFFFFF80 FFFFFF84 00
   FFFFFF81 08 01 0B 76 65 72 73 69 6F 6E 5F 24 65 71 14
   03 2F FFFFFF81 09 08 08 33 FFFFFF81 06 FFFFFF81 FFFFFF80 FFFFFFC0 00 6E 08 07
   FFFFFF81 0B 00 FFFFFFA0 FFFFFFA0 04 6E 01 08 76 65 72 73 69 6F 6E
   20 08 09 FFFFFF81 0D 00 FFFFFFC0 FFFFFF80 FFFFFF84 00 FFFFFF81 0E 01 18 61 6C
   6C 44 65 63 6C 61 72 61 74 69 6F 6E 73 50 72 6F
   63 65 73 73 65 64 15 01 7B 08 09 FFFFFF81 10 00 FFFFFFC0 FFFFFF80
   FFFFFF84 00 FFFFFF81 11 01 1C 61 6C 6C 44 65 63 6C 61 72 61
   74 69 6F 6E 73 50 72 6F 63 65 73 73 65 64 5F 24
   65 71 14 03 2F FFFFFF81 12 08 08 33 FFFFFF81 0F FFFFFF81 FFFFFF80 FFFFFFC0 00
   7B 08 07 FFFFFF81 14 00 FFFFFFA0 FFFFFFA0 04 7B 01 19 61 6C 6C 44
   65 63 6C 61 72 61 74 69 6F 6E 73 50 72 6F 63 65
   73 73 65 64 20 08 06 FFFFFF81 16 00 FFFFFF84 00 1C 01 06 74
   68 65 53 65 71 28 05 00 FFFFFF81 18 FFFFFF81 1B 10 03 13 FFFFFF81
   19 09 03 FFFFFF81 1A 04 02 10 53 65 72 69 61 6C 56 65
   72 73 69 6F 6E 55 49 44 1E 08 FFFFFFE0 3A FFFFFFB3 13 FFFFFFB6 35
   0D FFFFFFDB 28 03 00 FFFFFF81 1D 10 03 13 FFFFFF81 1E 09 03 FFFFFF81 1F
   04 02 0C 73 65 72 69 61 6C 69 7A 61 62 6C 65 
  minor version: 0
  major version: 49
  Constant pool:
Asciz	SourceFile;
Asciz	Document.scala;
Asciz	<clinit>;
Asciz	()V;
Asciz	Code;
Asciz	serialVersionUID;
Asciz	J;
long	-2289320563321795109l;
Asciz	scala/xml/Document;
class	scala/xml/Document
NameAndType	serialVersionUID:J
Field	scala/xml/Document.serialVersionUID:J
Asciz	allDeclarationsProcessed;
Asciz	Z;
Asciz	version;
Asciz	Lscala/Option;;
Asciz	Lscala/Option<Ljava/lang/String;>;;
Asciz	Signature;
Asciz	standAlone;
Asciz	Lscala/Option<Ljava/lang/Boolean;>;;
Asciz	encoding;
Asciz	baseURI;
Asciz	Ljava/lang/String;;
Asciz	dtd;
Asciz	Lscala/xml/dtd/DTD;;
Asciz	docElem;
Asciz	Lscala/xml/Node;;
Asciz	children;
Asciz	Lscala/collection/Seq;;
Asciz	Lscala/collection/Seq<Lscala/xml/Node;>;;
Asciz	()Lscala/collection/Seq;;
Asciz	LineNumberTable;
NameAndType	children:Lscala/collection/Seq;
Field	scala/xml/Document.children:Lscala/collection/Seq;
Asciz	()Lscala/collection/Seq<Lscala/xml/Node;>;;
Asciz	children_$eq;
Asciz	(Lscala/collection/Seq;)V;
Asciz	(Lscala/collection/Seq<Lscala/xml/Node;>;)V;
Asciz	()Lscala/xml/Node;;
NameAndType	docElem:Lscala/xml/Node;
Field	scala/xml/Document.docElem:Lscala/xml/Node;
Asciz	docElem_$eq;
Asciz	(Lscala/xml/Node;)V;
Asciz	()Lscala/xml/dtd/DTD;;
NameAndType	dtd:Lscala/xml/dtd/DTD;
Field	scala/xml/Document.dtd:Lscala/xml/dtd/DTD;
Asciz	dtd_$eq;
Asciz	(Lscala/xml/dtd/DTD;)V;
Asciz	notations;
NameAndType	dtd:()Lscala/xml/dtd/DTD;
Method	scala/xml/Document.dtd:()Lscala/xml/dtd/DTD;
Asciz	scala/xml/dtd/DTD;
class	scala/xml/dtd/DTD
NameAndType	notations:()Lscala/collection/Seq;
Method	scala/xml/dtd/DTD.notations:()Lscala/collection/Seq;
Asciz	()Lscala/collection/Seq<Lscala/xml/dtd/NotationDecl;>;;
Asciz	unparsedEntities;
NameAndType	unparsedEntities:()Lscala/collection/Seq;
Method	scala/xml/dtd/DTD.unparsedEntities:()Lscala/collection/Seq;
Asciz	()Lscala/collection/Seq<Lscala/xml/dtd/EntityDecl;>;;
Asciz	()Ljava/lang/String;;
NameAndType	baseURI:Ljava/lang/String;
Field	scala/xml/Document.baseURI:Ljava/lang/String;
Asciz	baseURI_$eq;
Asciz	(Ljava/lang/String;)V;
Asciz	()Lscala/Option;;
NameAndType	encoding:Lscala/Option;
Field	scala/xml/Document.encoding:Lscala/Option;
Asciz	()Lscala/Option<Ljava/lang/String;>;;
Asciz	encoding_$eq;
Asciz	(Lscala/Option;)V;
Asciz	(Lscala/Option<Ljava/lang/String;>;)V;
NameAndType	standAlone:Lscala/Option;
Field	scala/xml/Document.standAlone:Lscala/Option;
Asciz	()Lscala/Option<Ljava/lang/Boolean;>;;
Asciz	standAlone_$eq;
Asciz	(Lscala/Option<Ljava/lang/Boolean;>;)V;
NameAndType	version:Lscala/Option;
Field	scala/xml/Document.version:Lscala/Option;
Asciz	version_$eq;
Asciz	()Z;
NameAndType	allDeclarationsProcessed:Z
Field	scala/xml/Document.allDeclarationsProcessed:Z
Asciz	allDeclarationsProcessed_$eq;
Asciz	(Z)V;
Asciz	theSeq;
NameAndType	docElem:()Lscala/xml/Node;
Method	scala/xml/Document.docElem:()Lscala/xml/Node;
Asciz	<init>;
Asciz	scala/xml/NodeSeq;
class	scala/xml/NodeSeq
NameAndType	"<init>":()V
Method	scala/xml/NodeSeq."<init>":()V
Asciz	ScalaSig;
Asciz	scala/xml/pull/XMLEvent;
class	scala/xml/pull/XMLEvent
Asciz	scala/ScalaObject;
class	scala/ScalaObject
Asciz	java/io/Serializable;
class	java/io/Serializable

{
public static final long serialVersionUID;
  Signature: J

private boolean allDeclarationsProcessed;
  Signature: Z

private scala.Option version;
  Signature: Lscala/Option;
  Signature: length = 0x2
   00 12 

private scala.Option standAlone;
  Signature: Lscala/Option;
  Signature: length = 0x2
   00 15 

private scala.Option encoding;
  Signature: Lscala/Option;
  Signature: length = 0x2
   00 12 

private java.lang.String baseURI;
  Signature: Ljava/lang/String;

private scala.xml.dtd.DTD dtd;
  Signature: Lscala/xml/dtd/DTD;

private scala.xml.Node docElem;
  Signature: Lscala/xml/Node;

private scala.collection.Seq children;
  Signature: Lscala/collection/Seq;
  Signature: length = 0x2
   00 1F 

public static {};
  Signature: ()V
  Code:
   Stack=2, Locals=0, Args_size=0
	ldc2_w	long -2289320563321795109l
	putstatic	Field serialVersionUID:J
	return
  Labels:

public scala.collection.Seq children();
  Signature: ()Lscala/collection/Seq;
  Code:
   Stack=1, Locals=1, Args_size=1
	aload_0
	getfield	Field children:Lscala/collection/Seq;
	areturn
  Labels:
  Signature: length = 0x2
   00 24 

public void children_$eq(scala.collection.Seq);
  Signature: (Lscala/collection/Seq;)V
  Code:
   Stack=2, Locals=2, Args_size=2
	aload_0
	aload_1
	putfield	Field children:Lscala/collection/Seq;
	return
  Labels:
  Signature: length = 0x2
   00 27 

public scala.xml.Node docElem();
  Signature: ()Lscala/xml/Node;
  Code:
   Stack=1, Locals=1, Args_size=1
	aload_0
	getfield	Field docElem:Lscala/xml/Node;
	areturn
  Labels:

public void docElem_$eq(scala.xml.Node);
  Signature: (Lscala/xml/Node;)V
  Code:
   Stack=2, Locals=2, Args_size=2
	aload_0
	aload_1
	putfield	Field docElem:Lscala/xml/Node;
	return
  Labels:

public scala.xml.dtd.DTD dtd();
  Signature: ()Lscala/xml/dtd/DTD;
  Code:
   Stack=1, Locals=1, Args_size=1
	aload_0
	getfield	Field dtd:Lscala/xml/dtd/DTD;
	areturn
  Labels:

public void dtd_$eq(scala.xml.dtd.DTD);
  Signature: (Lscala/xml/dtd/DTD;)V
  Code:
   Stack=2, Locals=2, Args_size=2
	aload_0
	aload_1
	putfield	Field dtd:Lscala/xml/dtd/DTD;
	return
  Labels:

public scala.collection.Seq notations();
  Signature: ()Lscala/collection/Seq;
  Code:
   Stack=1, Locals=1, Args_size=1
	aload_0
	invokevirtual	Method dtd:()Lscala/xml/dtd/DTD;
	invokevirtual	Method scala/xml/dtd/DTD.notations:()Lscala/collection/Seq;
	areturn
  Labels:
  Signature: length = 0x2
   00 39 

public scala.collection.Seq unparsedEntities();
  Signature: ()Lscala/collection/Seq;
  Code:
   Stack=1, Locals=1, Args_size=1
	aload_0
	invokevirtual	Method dtd:()Lscala/xml/dtd/DTD;
	invokevirtual	Method scala/xml/dtd/DTD.unparsedEntities:()Lscala/collection/Seq;
	areturn
  Labels:
  Signature: length = 0x2
   00 3D 

public java.lang.String baseURI();
  Signature: ()Ljava/lang/String;
  Code:
   Stack=1, Locals=1, Args_size=1
	aload_0
	getfield	Field baseURI:Ljava/lang/String;
	areturn
  Labels:

public void baseURI_$eq(java.lang.String);
  Signature: (Ljava/lang/String;)V
  Code:
   Stack=2, Locals=2, Args_size=2
	aload_0
	aload_1
	putfield	Field baseURI:Ljava/lang/String;
	return
  Labels:

public scala.Option encoding();
  Signature: ()Lscala/Option;
  Code:
   Stack=1, Locals=1, Args_size=1
	aload_0
	getfield	Field encoding:Lscala/Option;
	areturn
  Labels:
  Signature: length = 0x2
   00 46 

public void encoding_$eq(scala.Option);
  Signature: (Lscala/Option;)V
  Code:
   Stack=2, Locals=2, Args_size=2
	aload_0
	aload_1
	putfield	Field encoding:Lscala/Option;
	return
  Labels:
  Signature: length = 0x2
   00 49 

public scala.Option standAlone();
  Signature: ()Lscala/Option;
  Code:
   Stack=1, Locals=1, Args_size=1
	aload_0
	getfield	Field standAlone:Lscala/Option;
	areturn
  Labels:
  Signature: length = 0x2
   00 4C 

public void standAlone_$eq(scala.Option);
  Signature: (Lscala/Option;)V
  Code:
   Stack=2, Locals=2, Args_size=2
	aload_0
	aload_1
	putfield	Field standAlone:Lscala/Option;
	return
  Labels:
  Signature: length = 0x2
   00 4E 

public scala.Option version();
  Signature: ()Lscala/Option;
  Code:
   Stack=1, Locals=1, Args_size=1
	aload_0
	getfield	Field version:Lscala/Option;
	areturn
  Labels:
  Signature: length = 0x2
   00 46 

public void version_$eq(scala.Option);
  Signature: (Lscala/Option;)V
  Code:
   Stack=2, Locals=2, Args_size=2
	aload_0
	aload_1
	putfield	Field version:Lscala/Option;
	return
  Labels:
  Signature: length = 0x2
   00 49 

public boolean allDeclarationsProcessed();
  Signature: ()Z
  Code:
   Stack=1, Locals=1, Args_size=1
	aload_0
	getfield	Field allDeclarationsProcessed:Z
	ireturn
  Labels:

public void allDeclarationsProcessed_$eq(boolean);
  Signature: (Z)V
  Code:
   Stack=2, Locals=2, Args_size=2
	aload_0
	iload_1
	putfield	Field allDeclarationsProcessed:Z
	return
  Labels:

public scala.collection.Seq theSeq();
  Signature: ()Lscala/collection/Seq;
  Code:
   Stack=1, Locals=1, Args_size=1
	aload_0
	invokevirtual	Method docElem:()Lscala/xml/Node;
	areturn
  Labels:
  Signature: length = 0x2
   00 24 

public scala.xml.Document();
  Signature: ()V
  Code:
   Stack=2, Locals=1, Args_size=1
	aload_0
	invokespecial	Method scala/xml/NodeSeq."<init>":()V
	aload_0
	iconst_0
	putfield	Field allDeclarationsProcessed:Z
	return
  Labels:

}

