Compiled from "Elem.scala"
public final class scala.xml.Elem$ extends java.lang.Object implements scala.ScalaObject
  SourceFile: "Elem.scala"
  Scala: length = 0x
   
  InnerClass: 
   public final $anonfun$text$1=class scala/xml/Elem$$anonfun$text$1 of class scala/xml/Elem
  minor version: 0
  major version: 49
  Constant pool:
Asciz	SourceFile;
Asciz	Elem.scala;
Asciz	Scala;
Asciz	MODULE$;
Asciz	Lscala/xml/Elem$;;
Asciz	<clinit>;
Asciz	()V;
Asciz	Code;
Asciz	scala/xml/Elem$;
class	scala/xml/Elem$
Asciz	<init>;
NameAndType	"<init>":()V
Method	scala/xml/Elem$."<init>":()V
Asciz	LineNumberTable;
Asciz	java/lang/Object;
class	java/lang/Object
Method	java/lang/Object."<init>":()V
NameAndType	MODULE$:Lscala/xml/Elem$;
Field	scala/xml/Elem$.MODULE$:Lscala/xml/Elem$;
Asciz	unapplySeq;
Asciz	(Lscala/xml/Node;)Lscala/Option;;
Asciz	scala/xml/SpecialNode;
class	scala/xml/SpecialNode
Asciz	scala/xml/Group;
class	scala/xml/Group
Asciz	scala/None$;
class	scala/None$
Asciz	Lscala/None$;;
NameAndType	MODULE$:Lscala/None$;
Field	scala/None$.MODULE$:Lscala/None$;
Asciz	scala/Some;
class	scala/Some
Asciz	scala/Tuple5;
class	scala/Tuple5
Asciz	scala/xml/Node;
class	scala/xml/Node
Asciz	prefix;
Asciz	()Ljava/lang/String;;
NameAndType	prefix:()Ljava/lang/String;
Method	scala/xml/Node.prefix:()Ljava/lang/String;
Asciz	label;
NameAndType	label:()Ljava/lang/String;
Method	scala/xml/Node.label:()Ljava/lang/String;
Asciz	attributes;
Asciz	()Lscala/xml/MetaData;;
NameAndType	attributes:()Lscala/xml/MetaData;
Method	scala/xml/Node.attributes:()Lscala/xml/MetaData;
Asciz	scope;
Asciz	()Lscala/xml/NamespaceBinding;;
NameAndType	scope:()Lscala/xml/NamespaceBinding;
Method	scala/xml/Node.scope:()Lscala/xml/NamespaceBinding;
Asciz	child;
Asciz	()Lscala/collection/Seq;;
NameAndType	child:()Lscala/collection/Seq;
Method	scala/xml/Node.child:()Lscala/collection/Seq;
Asciz	(Ljava/lang/Object;Ljava/lang/Object;Ljava/lang/Object;Ljava/lang/Object;Ljava/lang/Object;)V;
NameAndType	"<init>":(Ljava/lang/Object;Ljava/lang/Object;Ljava/lang/Object;Ljava/lang/Object;Ljava/lang/Object;)V
Method	scala/Tuple5."<init>":(Ljava/lang/Object;Ljava/lang/Object;Ljava/lang/Object;Ljava/lang/Object;Ljava/lang/Object;)V
Asciz	(Ljava/lang/Object;)V;
NameAndType	"<init>":(Ljava/lang/Object;)V
Method	scala/Some."<init>":(Ljava/lang/Object;)V
Asciz	this;
Asciz	n;
Asciz	Lscala/xml/Node;;
Asciz	LocalVariableTable;
Asciz	(Lscala/xml/Node;)Lscala/Option<Lscala/Tuple5<Ljava/lang/String;Ljava/lang/String;Lscala/xml/MetaData;Lscala/xml/NamespaceBinding;Lscala/collection/Seq<Lscala/xml/Node;>;>;>;;
Asciz	Signature;
Asciz	apply;
Asciz	(Ljava/lang/String;Ljava/lang/String;Lscala/xml/MetaData;Lscala/xml/NamespaceBinding;Lscala/collection/Seq;)Lscala/xml/Elem;;
Asciz	scala/xml/Elem;
class	scala/xml/Elem
Asciz	(Ljava/lang/String;Ljava/lang/String;Lscala/xml/MetaData;Lscala/xml/NamespaceBinding;Lscala/collection/Seq;)V;
NameAndType	"<init>":(Ljava/lang/String;Ljava/lang/String;Lscala/xml/MetaData;Lscala/xml/NamespaceBinding;Lscala/collection/Seq;)V
Method	scala/xml/Elem."<init>":(Ljava/lang/String;Ljava/lang/String;Lscala/xml/MetaData;Lscala/xml/NamespaceBinding;Lscala/collection/Seq;)V
Asciz	Ljava/lang/String;;
Asciz	Lscala/xml/MetaData;;
Asciz	Lscala/xml/NamespaceBinding;;
Asciz	Lscala/collection/Seq;;
Asciz	(Ljava/lang/String;Ljava/lang/String;Lscala/xml/MetaData;Lscala/xml/NamespaceBinding;Lscala/collection/Seq<Lscala/xml/Node;>;)Lscala/xml/Elem;;
Asciz	InnerClasses;
Asciz	scala/xml/Elem$$anonfun$text$1;
class	scala/xml/Elem$$anonfun$text$1
Asciz	$anonfun$text$1;
Asciz	scala/ScalaObject;
class	scala/ScalaObject

{
public static final scala.xml.Elem$ MODULE$;
  Signature: Lscala/xml/Elem$;

public static {};
  Signature: ()V
  Code:
   Stack=1, Locals=0, Args_size=0
	new	class scala/xml/Elem$
	invokespecial	Method "<init>":()V
	return
  Labels:

private scala.xml.Elem$();
  Signature: ()V
  Code:
   Stack=1, Locals=1, Args_size=1
	aload_0
	invokespecial	Method java/lang/Object."<init>":()V
	aload_0
	putstatic	Field MODULE$:Lscala/xml/Elem$;
	return
  Labels:

public scala.Option unapplySeq(scala.xml.Node);
  Signature: (Lscala/xml/Node;)Lscala/Option;
  Code:
   Stack=9, Locals=2, Args_size=2
	aload_1
	instanceof	class scala/xml/SpecialNode
	ifne	l1 // getstatic
	aload_1
	instanceof	class scala/xml/Group
	ifeq	l2 // new
l1	getstatic	Field scala/None$.MODULE$:Lscala/None$;
	goto	l3 // areturn
l2	new	class scala/Some
	dup
	new	class scala/Tuple5
	dup
	aload_1
	invokevirtual	Method scala/xml/Node.prefix:()Ljava/lang/String;
	aload_1
	invokevirtual	Method scala/xml/Node.label:()Ljava/lang/String;
	aload_1
	invokevirtual	Method scala/xml/Node.attributes:()Lscala/xml/MetaData;
	aload_1
	invokevirtual	Method scala/xml/Node.scope:()Lscala/xml/NamespaceBinding;
	aload_1
	invokevirtual	Method scala/xml/Node.child:()Lscala/collection/Seq;
	invokespecial	Method scala/Tuple5."<init>":(Ljava/lang/Object;Ljava/lang/Object;Ljava/lang/Object;Ljava/lang/Object;Ljava/lang/Object;)V
	invokespecial	Method scala/Some."<init>":(Ljava/lang/Object;)V
l3	areturn
  Labels:
   	l1 = 14 // getstatic
   	l2 = 20 // new
   	l3 = 54 // areturn
  LocalVariableTable: 
   Start  Length  Slot  Name   Signature
   0      55      0    this       Lscala/xml/Elem$;
   0      55      1    n       Lscala/xml/Node;

  Signature: length = 0x2
   00 42 

public scala.xml.Elem apply(java.lang.String, java.lang.String, scala.xml.MetaData, scala.xml.NamespaceBinding, scala.collection.Seq);
  Signature: (Ljava/lang/String;Ljava/lang/String;Lscala/xml/MetaData;Lscala/xml/NamespaceBinding;Lscala/collection/Seq;)Lscala/xml/Elem;
  Code:
   Stack=7, Locals=6, Args_size=6
	new	class scala/xml/Elem
	dup
	aload_1
	aload_2
	aload_3
	aload	4
	aload	5
	invokespecial	Method scala/xml/Elem."<init>":(Ljava/lang/String;Ljava/lang/String;Lscala/xml/MetaData;Lscala/xml/NamespaceBinding;Lscala/collection/Seq;)V
	areturn
  Labels:
  LocalVariableTable: 
   Start  Length  Slot  Name   Signature
   0      15      0    this       Lscala/xml/Elem$;
   0      15      1    prefix       Ljava/lang/String;
   0      15      2    label       Ljava/lang/String;
   0      15      3    attributes       Lscala/xml/MetaData;
   0      15      4    scope       Lscala/xml/NamespaceBinding;
   0      15      5    child       Lscala/collection/Seq;

  Signature: length = 0x2
   00 4F 

}

