Compiled from "Elem.scala"
public class scala.xml.Elem extends scala.xml.Node implements scala.ScalaObject,java.io.Serializable
  SourceFile: "Elem.scala"
  ScalaSig: length = 0x4CE
   05 00 FFFFFF81 2C 07 05 01 02 FFFFFF88 02 07 01 04 45 6C 65
   6D 0A 02 03 04 01 03 78 6D 6C 0A 01 05 01 05 73
   63 61 6C 61 03 00 10 02 08 09 0D 01 02 06 08 0A
   02 FFFFFF84 FFFFFF80 FFFFFF80 FFFFFF88 02 0B 02 04 45 6C 65 6D 13 03 09
   0C 14 10 02 0D 12 0D 01 0E 0A 02 0F 10 01 04 6C
   61 6E 67 0A 01 11 01 04 6A 61 76 61 09 02 13 0E
   02 06 4F 62 6A 65 63 74 10 02 15 16 0D 01 04 09
   02 17 04 02 0B 53 63 61 6C 61 4F 62 6A 65 63 74
   08 05 19 09 FFFFFF84 00 1A 01 06 3C 69 6E 69 74 3E 14
   01 07 08 05 1C 09 FFFFFF84 00 1D 01 05 61 70 70 6C 79
   14 0B 1E FFFFFF81 1C FFFFFF81 1D FFFFFF81 1E FFFFFF81 1F FFFFFF81 20 10 02 08
   1F 06 08 0A 02 FFFFFF84 FFFFFF80 FFFFFF80 FFFFFF80 00 20 13 03 1F 21 14
   10 02 08 22 09 02 23 02 02 04 4E 6F 64 65 08 08
   25 1F FFFFFF82 FFFFFFC2 FFFFFF80 FFFFFF84 20 26 01 06 70 72 65 66 69 78
   15 01 27 10 02 28 2B 0E 02 15 29 09 02 2A 04 01
   06 50 72 65 64 65 66 09 02 2C 2D 02 06 53 74 72
   69 6E 67 0A 02 2A 04 08 08 2F 1F FFFFFF82 FFFFFF80 FFFFFFA0 FFFFFF80 04
   27 01 07 70 72 65 66 69 78 20 08 08 31 1F FFFFFF82 FFFFFFC2
   FFFFFF80 FFFFFF84 00 26 01 05 6C 61 62 65 6C 08 08 33 1F FFFFFF82
   FFFFFF80 FFFFFFA0 FFFFFF80 04 27 01 06 6C 61 62 65 6C 20 08 08 35
   1F FFFFFF82 FFFFFFC2 FFFFFF80 FFFFFF84 20 36 01 0A 61 74 74 72 69 62 75
   74 65 73 15 01 37 10 02 08 38 09 02 39 02 02 08
   4D 65 74 61 44 61 74 61 08 08 3B 1F FFFFFF82 FFFFFF80 FFFFFFA0 FFFFFF80
   04 37 01 0B 61 74 74 72 69 62 75 74 65 73 20 08
   08 3D 1F FFFFFF82 FFFFFFC2 FFFFFF80 FFFFFF84 20 3E 01 05 73 63 6F 70 65
   15 01 3F 10 02 08 40 09 02 41 02 02 10 4E 61 6D
   65 73 70 61 63 65 42 69 6E 64 69 6E 67 08 08 43
   1F FFFFFF82 FFFFFF80 FFFFFFA0 FFFFFF80 04 3F 01 06 73 63 6F 70 65 20 08
   08 45 1F FFFFFF82 FFFFFFC2 FFFFFF80 FFFFFF84 00 46 01 05 63 68 69 6C 64
   15 01 47 10 03 15 48 21 09 02 49 04 02 0A 3C 72
   65 70 65 61 74 65 64 3E 08 08 4B 1F FFFFFF82 FFFFFF80 FFFFFFA0 FFFFFF80
   04 47 01 06 63 68 69 6C 64 20 08 05 19 1F FFFFFF84 00
   4D 14 06 1E 4E 4F 50 51 52 08 05 25 4C FFFFFFC0 00 27
   08 05 31 4C FFFFFFC0 00 27 08 05 35 4C FFFFFFC0 00 37 08 05
   3D 4C FFFFFFC0 00 3F 08 05 45 4C FFFFFFC0 00 47 08 05 54 1F
   FFFFFF84 22 55 01 13 64 6F 43 6F 6C 6C 65 63 74 4E 61
   6D 65 73 70 61 63 65 73 15 01 56 10 02 15 57 09
   02 58 04 02 07 42 6F 6F 6C 65 61 6E 08 05 5A 1F
   FFFFFF84 22 55 01 0B 64 6F 54 72 61 6E 73 66 6F 72 6D
   08 05 5C 1F FFFFFF84 20 5D 01 10 62 61 73 69 73 46 6F
   72 48 61 73 68 43 6F 64 65 15 01 5E 10 03 5F 67
   6A 0E 02 60 65 0E 02 61 64 0D 01 62 0A 02 63 06
   01 06 3C 72 6F 6F 74 3E 09 01 05 09 02 66 04 01
   07 70 61 63 6B 61 67 65 09 02 68 69 02 03 53 65
   71 0A 02 66 04 10 02 15 6B 09 02 6C 04 02 03 41
   6E 79 08 05 6E 1F FFFFFF84 02 6F 01 08 24 70 65 72 63
   65 6E 74 14 02 1E 70 08 05 71 6D FFFFFFC0 00 37 01 07
   75 70 64 61 74 65 73 08 05 73 1F FFFFFF84 00 74 01 04
   63 6F 70 79 14 06 1E 75 76 77 78 79 08 07 25 72
   FFFFFF90 FFFFFF80 FFFFFFC0 00 27 08 07 31 72 FFFFFF90 FFFFFF80 FFFFFFC0 00 27 08 07
   35 72 FFFFFF90 FFFFFF80 FFFFFFC0 00 37 08 07 3D 72 FFFFFF90 FFFFFF80 FFFFFFC0 00 3F
   08 07 45 72 FFFFFF90 FFFFFF80 FFFFFFC0 00 7A 10 03 5F 67 21 08 05
   7C 1F FFFFFF84 20 26 01 04 74 65 78 74 08 07 7E 1F FFFFFF91
   FFFFFF80 FFFFFF84 00 7F 01 0E 63 6F 70 79 24 64 65 66 61 75
   6C 74 24 31 15 02 FFFFFF81 00 2A 03 27 FFFFFF81 01 2B 02 FFFFFF81
   02 10 04 FFFFFF81 03 FFFFFF81 08 0D 02 FFFFFF81 04 0A 04 FFFFFF81 05 FFFFFF81
   06 01 09 75 6E 63 68 65 63 6B 65 64 0A 03 FFFFFF81 07
   04 01 0A 61 6E 6E 6F 74 61 74 69 6F 6E 09 04 FFFFFF81
   09 FFFFFF81 04 02 11 75 6E 63 68 65 63 6B 65 64 56 61
   72 69 61 6E 63 65 08 08 FFFFFF81 0B 1F FFFFFF91 FFFFFF80 FFFFFF84 00 7F
   01 0E 63 6F 70 79 24 64 65 66 61 75 6C 74 24 32
   08 09 FFFFFF81 0D 1F FFFFFF91 FFFFFF80 FFFFFF84 00 FFFFFF81 0E 01 0E 63 6F 70
   79 24 64 65 66 61 75 6C 74 24 33 15 02 FFFFFF81 0F 2A
   03 37 FFFFFF81 01 08 09 FFFFFF81 11 1F FFFFFF91 FFFFFF80 FFFFFF84 00 FFFFFF81 12 01
   0E 63 6F 70 79 24 64 65 66 61 75 6C 74 24 34 15
   02 FFFFFF81 13 2A 03 3F FFFFFF81 01 08 09 FFFFFF81 15 1F FFFFFF91 FFFFFF80 FFFFFF84
   00 FFFFFF81 16 01 0E 63 6F 70 79 24 64 65 66 61 75 6C
   74 24 35 15 02 FFFFFF81 17 2A 03 7A FFFFFF81 01 28 03 1F FFFFFF81
   19 10 03 15 FFFFFF81 1A 09 03 FFFFFF81 1B 04 02 0C 73 65 72
   69 61 6C 69 7A 61 62 6C 65 08 05 25 1B FFFFFFC0 00 27
   08 05 31 1B FFFFFFC0 00 27 08 05 35 1B FFFFFFC0 00 37 08 05
   3D 1B FFFFFFC0 00 3F 08 05 45 1B FFFFFFC0 00 47 08 07 FFFFFF81 22
   09 FFFFFF84 00 FFFFFF81 23 01 0A 75 6E 61 70 70 6C 79 53 65
   71 14 04 FFFFFF81 24 FFFFFF81 2A 10 05 15 FFFFFF81 25 FFFFFF81 27 09 03
   FFFFFF81 26 04 02 06 4F 70 74 69 6F 6E 10 08 15 FFFFFF81 28
   27 27 37 3F 7A 09 03 FFFFFF81 29 04 02 06 54 75 70 6C
   65 35 08 07 FFFFFF81 2B FFFFFF81 21 FFFFFFC0 00 21 01 01 6E 
  InnerClass: 
   public final $anonfun$text$1=class scala/xml/Elem$$anonfun$text$1 of class scala/xml/Elem
  minor version: 0
  major version: 49
  Constant pool:
Asciz	SourceFile;
Asciz	Elem.scala;
Asciz	unapplySeq;
Asciz	(Lscala/xml/Node;)Lscala/Option;;
Asciz	Code;
Asciz	scala/xml/Elem$;
class	scala/xml/Elem$
Asciz	MODULE$;
Asciz	Lscala/xml/Elem$;;
NameAndType	MODULE$:Lscala/xml/Elem$;
Field	scala/xml/Elem$.MODULE$:Lscala/xml/Elem$;
NameAndType	unapplySeq:(Lscala/xml/Node;)Lscala/Option;
Method	scala/xml/Elem$.unapplySeq:(Lscala/xml/Node;)Lscala/Option;
Asciz	(Lscala/xml/Node;)Lscala/Option<Lscala/Tuple5<Ljava/lang/String;Ljava/lang/String;Lscala/xml/MetaData;Lscala/xml/NamespaceBinding;Lscala/collection/Seq<Lscala/xml/Node;>;>;>;;
Asciz	Signature;
Asciz	child;
Asciz	Lscala/collection/Seq;;
Asciz	Lscala/collection/Seq<Lscala/xml/Node;>;;
Asciz	scope;
Asciz	Lscala/xml/NamespaceBinding;;
Asciz	attributes;
Asciz	Lscala/xml/MetaData;;
Asciz	label;
Asciz	Ljava/lang/String;;
Asciz	prefix;
Asciz	copy$default$5;
Asciz	()Lscala/collection/Seq;;
Asciz	LineNumberTable;
Asciz	scala/xml/Elem;
class	scala/xml/Elem
NameAndType	child:()Lscala/collection/Seq;
Method	scala/xml/Elem.child:()Lscala/collection/Seq;
Asciz	scala/collection/SeqLike;
class	scala/collection/SeqLike
Asciz	toSeq;
NameAndType	toSeq:()Lscala/collection/Seq;
InterfaceMethod	scala/collection/SeqLike.toSeq:()Lscala/collection/Seq;
Asciz	copy$default$4;
Asciz	()Lscala/xml/NamespaceBinding;;
NameAndType	scope:()Lscala/xml/NamespaceBinding;
Method	scala/xml/Elem.scope:()Lscala/xml/NamespaceBinding;
Asciz	copy$default$3;
Asciz	()Lscala/xml/MetaData;;
NameAndType	attributes:()Lscala/xml/MetaData;
Method	scala/xml/Elem.attributes:()Lscala/xml/MetaData;
Asciz	copy$default$2;
Asciz	()Ljava/lang/String;;
NameAndType	label:()Ljava/lang/String;
Method	scala/xml/Elem.label:()Ljava/lang/String;
Asciz	copy$default$1;
NameAndType	prefix:()Ljava/lang/String;
Method	scala/xml/Elem.prefix:()Ljava/lang/String;
NameAndType	prefix:Ljava/lang/String;
Field	scala/xml/Elem.prefix:Ljava/lang/String;
NameAndType	label:Ljava/lang/String;
Field	scala/xml/Elem.label:Ljava/lang/String;
NameAndType	attributes:Lscala/xml/MetaData;
Field	scala/xml/Elem.attributes:Lscala/xml/MetaData;
NameAndType	scope:Lscala/xml/NamespaceBinding;
Field	scala/xml/Elem.scope:Lscala/xml/NamespaceBinding;
NameAndType	child:Lscala/collection/Seq;
Field	scala/xml/Elem.child:Lscala/collection/Seq;
Asciz	()Lscala/collection/Seq<Lscala/xml/Node;>;;
Asciz	doCollectNamespaces;
Asciz	()Z;
Asciz	doTransform;
Asciz	basisForHashCode;
Asciz	scala/collection/TraversableLike;
class	scala/collection/TraversableLike
Asciz	toList;
Asciz	()Lscala/collection/immutable/List;;
NameAndType	toList:()Lscala/collection/immutable/List;
InterfaceMethod	scala/collection/TraversableLike.toList:()Lscala/collection/immutable/List;
Asciz	scala/collection/immutable/List;
class	scala/collection/immutable/List
Asciz	$colon$colon;
Asciz	(Ljava/lang/Object;)Lscala/collection/immutable/List;;
NameAndType	$colon$colon:(Ljava/lang/Object;)Lscala/collection/immutable/List;
Method	scala/collection/immutable/List.$colon$colon:(Ljava/lang/Object;)Lscala/collection/immutable/List;
Asciz	()Lscala/collection/Seq<Ljava/lang/Object;>;;
Asciz	$percent;
Asciz	(Lscala/xml/MetaData;)Lscala/xml/Elem;;
Asciz	scala/xml/MetaData$;
class	scala/xml/MetaData$
Asciz	Lscala/xml/MetaData$;;
NameAndType	MODULE$:Lscala/xml/MetaData$;
Field	scala/xml/MetaData$.MODULE$:Lscala/xml/MetaData$;
Asciz	update;
Asciz	(Lscala/xml/MetaData;Lscala/xml/NamespaceBinding;Lscala/xml/MetaData;)Lscala/xml/MetaData;;
NameAndType	update:(Lscala/xml/MetaData;Lscala/xml/NamespaceBinding;Lscala/xml/MetaData;)Lscala/xml/MetaData;
Method	scala/xml/MetaData$.update:(Lscala/xml/MetaData;Lscala/xml/NamespaceBinding;Lscala/xml/MetaData;)Lscala/xml/MetaData;
NameAndType	copy$default$1:()Ljava/lang/String;
Method	scala/xml/Elem.copy$default$1:()Ljava/lang/String;
NameAndType	copy$default$2:()Ljava/lang/String;
Method	scala/xml/Elem.copy$default$2:()Ljava/lang/String;
NameAndType	copy$default$4:()Lscala/xml/NamespaceBinding;
Method	scala/xml/Elem.copy$default$4:()Lscala/xml/NamespaceBinding;
NameAndType	copy$default$5:()Lscala/collection/Seq;
Method	scala/xml/Elem.copy$default$5:()Lscala/collection/Seq;
Asciz	copy;
Asciz	(Ljava/lang/String;Ljava/lang/String;Lscala/xml/MetaData;Lscala/xml/NamespaceBinding;Lscala/collection/Seq;)Lscala/xml/Elem;;
NameAndType	copy:(Ljava/lang/String;Ljava/lang/String;Lscala/xml/MetaData;Lscala/xml/NamespaceBinding;Lscala/collection/Seq;)Lscala/xml/Elem;
Method	scala/xml/Elem.copy:(Ljava/lang/String;Ljava/lang/String;Lscala/xml/MetaData;Lscala/xml/NamespaceBinding;Lscala/collection/Seq;)Lscala/xml/Elem;
Asciz	this;
Asciz	Lscala/xml/Elem;;
Asciz	updates;
Asciz	x$5;
Asciz	x$6;
Asciz	x$7;
Asciz	x$8;
Asciz	x$9;
Asciz	LocalVariableTable;
Asciz	apply;
NameAndType	apply:(Ljava/lang/String;Ljava/lang/String;Lscala/xml/MetaData;Lscala/xml/NamespaceBinding;Lscala/collection/Seq;)Lscala/xml/Elem;
Method	scala/xml/Elem$.apply:(Ljava/lang/String;Ljava/lang/String;Lscala/xml/MetaData;Lscala/xml/NamespaceBinding;Lscala/collection/Seq;)Lscala/xml/Elem;
Asciz	(Ljava/lang/String;Ljava/lang/String;Lscala/xml/MetaData;Lscala/xml/NamespaceBinding;Lscala/collection/Seq<Lscala/xml/Node;>;)Lscala/xml/Elem;;
Asciz	text;
Asciz	scala/xml/Elem$$anonfun$text$1;
class	scala/xml/Elem$$anonfun$text$1
Asciz	<init>;
Asciz	(Lscala/xml/Elem;)V;
NameAndType	"<init>":(Lscala/xml/Elem;)V
Method	scala/xml/Elem$$anonfun$text$1."<init>":(Lscala/xml/Elem;)V
Asciz	scala/collection/Seq$;
class	scala/collection/Seq$
Asciz	Lscala/collection/Seq$;;
NameAndType	MODULE$:Lscala/collection/Seq$;
Field	scala/collection/Seq$.MODULE$:Lscala/collection/Seq$;
Asciz	canBuildFrom;
Asciz	()Lscala/collection/generic/CanBuildFrom;;
NameAndType	canBuildFrom:()Lscala/collection/generic/CanBuildFrom;
Method	scala/collection/Seq$.canBuildFrom:()Lscala/collection/generic/CanBuildFrom;
Asciz	map;
Asciz	(Lscala/Function1;Lscala/collection/generic/CanBuildFrom;)Ljava/lang/Object;;
NameAndType	map:(Lscala/Function1;Lscala/collection/generic/CanBuildFrom;)Ljava/lang/Object;
InterfaceMethod	scala/collection/TraversableLike.map:(Lscala/Function1;Lscala/collection/generic/CanBuildFrom;)Ljava/lang/Object;
Asciz	mkString;
NameAndType	mkString:()Ljava/lang/String;
InterfaceMethod	scala/collection/TraversableLike.mkString:()Ljava/lang/String;
Asciz	(Ljava/lang/String;Ljava/lang/String;Lscala/xml/MetaData;Lscala/xml/NamespaceBinding;Lscala/collection/Seq;)V;
Asciz	scala/xml/Node;
class	scala/xml/Node
Asciz	()V;
NameAndType	"<init>":()V
Method	scala/xml/Node."<init>":()V
Asciz	;
String	
Asciz	java/lang/Object;
class	java/lang/Object
Asciz	equals;
Asciz	(Ljava/lang/Object;)Z;
NameAndType	equals:(Ljava/lang/Object;)Z
Method	java/lang/Object.equals:(Ljava/lang/Object;)Z
Asciz	java/lang/IllegalArgumentException;
class	java/lang/IllegalArgumentException
Asciz	prefix of zero length, use null instead;
String	prefix of zero length, use null instead
Asciz	(Ljava/lang/String;)V;
NameAndType	"<init>":(Ljava/lang/String;)V
Method	java/lang/IllegalArgumentException."<init>":(Ljava/lang/String;)V
Asciz	scope is null, use xml.TopScope for empty scope;
String	scope is null, use xml.TopScope for empty scope
Asciz	(Ljava/lang/String;Ljava/lang/String;Lscala/xml/MetaData;Lscala/xml/NamespaceBinding;Lscala/collection/Seq<Lscala/xml/Node;>;)V;
Asciz	ScalaSig;
Asciz	InnerClasses;
Asciz	$anonfun$text$1;
Asciz	scala/ScalaObject;
class	scala/ScalaObject
Asciz	java/io/Serializable;
class	java/io/Serializable

{
private final scala.collection.Seq child;
  Signature: Lscala/collection/Seq;
  Signature: length = 0x2
   00 12 

private final scala.xml.NamespaceBinding scope;
  Signature: Lscala/xml/NamespaceBinding;

private final scala.xml.MetaData attributes;
  Signature: Lscala/xml/MetaData;

private final java.lang.String label;
  Signature: Ljava/lang/String;

private final java.lang.String prefix;
  Signature: Ljava/lang/String;

public static final scala.Option unapplySeq(scala.xml.Node);
  Signature: (Lscala/xml/Node;)Lscala/Option;
  Code:
   Stack=2, Locals=1, Args_size=1
	getstatic	Field scala/xml/Elem$.MODULE$:Lscala/xml/Elem$;
	aload_0
	invokevirtual	Method scala/xml/Elem$.unapplySeq:(Lscala/xml/Node;)Lscala/Option;
	areturn
  Labels:
  Signature: length = 0x2
   00 0E 

public scala.collection.Seq copy$default$5();
  Signature: ()Lscala/collection/Seq;
  Code:
   Stack=1, Locals=1, Args_size=1
	aload_0
	invokevirtual	Method child:()Lscala/collection/Seq;
	invokeinterface	InterfaceMethod scala/collection/SeqLike.toSeq:()Lscala/collection/Seq;
	areturn
  Labels:

public scala.xml.NamespaceBinding copy$default$4();
  Signature: ()Lscala/xml/NamespaceBinding;
  Code:
   Stack=1, Locals=1, Args_size=1
	aload_0
	invokevirtual	Method scope:()Lscala/xml/NamespaceBinding;
	areturn
  Labels:

public scala.xml.MetaData copy$default$3();
  Signature: ()Lscala/xml/MetaData;
  Code:
   Stack=1, Locals=1, Args_size=1
	aload_0
	invokevirtual	Method attributes:()Lscala/xml/MetaData;
	areturn
  Labels:

public java.lang.String copy$default$2();
  Signature: ()Ljava/lang/String;
  Code:
   Stack=1, Locals=1, Args_size=1
	aload_0
	invokevirtual	Method label:()Ljava/lang/String;
	areturn
  Labels:

public java.lang.String copy$default$1();
  Signature: ()Ljava/lang/String;
  Code:
   Stack=1, Locals=1, Args_size=1
	aload_0
	invokevirtual	Method prefix:()Ljava/lang/String;
	areturn
  Labels:

public java.lang.String prefix();
  Signature: ()Ljava/lang/String;
  Code:
   Stack=1, Locals=1, Args_size=1
	aload_0
	getfield	Field prefix:Ljava/lang/String;
	areturn
  Labels:

public java.lang.String label();
  Signature: ()Ljava/lang/String;
  Code:
   Stack=1, Locals=1, Args_size=1
	aload_0
	getfield	Field label:Ljava/lang/String;
	areturn
  Labels:

public scala.xml.MetaData attributes();
  Signature: ()Lscala/xml/MetaData;
  Code:
   Stack=1, Locals=1, Args_size=1
	aload_0
	getfield	Field attributes:Lscala/xml/MetaData;
	areturn
  Labels:

public scala.xml.NamespaceBinding scope();
  Signature: ()Lscala/xml/NamespaceBinding;
  Code:
   Stack=1, Locals=1, Args_size=1
	aload_0
	getfield	Field scope:Lscala/xml/NamespaceBinding;
	areturn
  Labels:

public scala.collection.Seq child();
  Signature: ()Lscala/collection/Seq;
  Code:
   Stack=1, Locals=1, Args_size=1
	aload_0
	getfield	Field child:Lscala/collection/Seq;
	areturn
  Labels:
  Signature: length = 0x2
   00 3F 

public final boolean doCollectNamespaces();
  Signature: ()Z
  Code:
   Stack=1, Locals=1, Args_size=1
	iconst_1
	ireturn
  Labels:

public final boolean doTransform();
  Signature: ()Z
  Code:
   Stack=1, Locals=1, Args_size=1
	iconst_1
	ireturn
  Labels:

public scala.collection.Seq basisForHashCode();
  Signature: ()Lscala/collection/Seq;
  Code:
   Stack=2, Locals=4, Args_size=1
	aload_0
	invokevirtual	Method prefix:()Ljava/lang/String;
	astore_1
	aload_0
	invokevirtual	Method label:()Ljava/lang/String;
	astore_2
	aload_0
	invokevirtual	Method attributes:()Lscala/xml/MetaData;
	astore_3
	aload_0
	invokevirtual	Method child:()Lscala/collection/Seq;
	invokeinterface	InterfaceMethod scala/collection/TraversableLike.toList:()Lscala/collection/immutable/List;
	aload_3
	invokevirtual	Method scala/collection/immutable/List.$colon$colon:(Ljava/lang/Object;)Lscala/collection/immutable/List;
	aload_2
	invokevirtual	Method scala/collection/immutable/List.$colon$colon:(Ljava/lang/Object;)Lscala/collection/immutable/List;
	aload_1
	invokevirtual	Method scala/collection/immutable/List.$colon$colon:(Ljava/lang/Object;)Lscala/collection/immutable/List;
	areturn
  Labels:
  Signature: length = 0x2
   00 50 

public final scala.xml.Elem $percent(scala.xml.MetaData);
  Signature: (Lscala/xml/MetaData;)Lscala/xml/Elem;
  Code:
   Stack=6, Locals=7, Args_size=2
	getstatic	Field scala/xml/MetaData$.MODULE$:Lscala/xml/MetaData$;
	aload_0
	invokevirtual	Method attributes:()Lscala/xml/MetaData;
	aload_0
	invokevirtual	Method scope:()Lscala/xml/NamespaceBinding;
	aload_1
	invokevirtual	Method scala/xml/MetaData$.update:(Lscala/xml/MetaData;Lscala/xml/NamespaceBinding;Lscala/xml/MetaData;)Lscala/xml/MetaData;
	astore_2
	aload_0
	invokevirtual	Method copy$default$1:()Ljava/lang/String;
	astore_3
	aload_0
	invokevirtual	Method copy$default$2:()Ljava/lang/String;
	astore	4
	aload_0
	invokevirtual	Method copy$default$4:()Lscala/xml/NamespaceBinding;
	astore	5
	aload_0
	invokevirtual	Method copy$default$5:()Lscala/collection/Seq;
	astore	6
	aload_0
	aload_3
	aload	4
	aload_2
	aload	5
	aload	6
	invokevirtual	Method copy:(Ljava/lang/String;Ljava/lang/String;Lscala/xml/MetaData;Lscala/xml/NamespaceBinding;Lscala/collection/Seq;)Lscala/xml/Elem;
	areturn
  Labels:
  LocalVariableTable: 
   Start  Length  Slot  Name   Signature
   0      52      0    this       Lscala/xml/Elem;
   0      52      1    updates       Lscala/xml/MetaData;
   16      35      2    x$5       Lscala/xml/MetaData;
   21      30      3    x$6       Ljava/lang/String;
   27      24      4    x$7       Ljava/lang/String;
   33      18      5    x$8       Lscala/xml/NamespaceBinding;
   39      12      6    x$9       Lscala/collection/Seq;


public scala.xml.Elem copy(java.lang.String, java.lang.String, scala.xml.MetaData, scala.xml.NamespaceBinding, scala.collection.Seq);
  Signature: (Ljava/lang/String;Ljava/lang/String;Lscala/xml/MetaData;Lscala/xml/NamespaceBinding;Lscala/collection/Seq;)Lscala/xml/Elem;
  Code:
   Stack=6, Locals=6, Args_size=6
	getstatic	Field scala/xml/Elem$.MODULE$:Lscala/xml/Elem$;
	aload_1
	aload_2
	aload_3
	aload	4
	aload	5
	invokevirtual	Method scala/xml/Elem$.apply:(Ljava/lang/String;Ljava/lang/String;Lscala/xml/MetaData;Lscala/xml/NamespaceBinding;Lscala/collection/Seq;)Lscala/xml/Elem;
	areturn
  Labels:
  LocalVariableTable: 
   Start  Length  Slot  Name   Signature
   0      14      0    this       Lscala/xml/Elem;
   0      14      1    prefix       Ljava/lang/String;
   0      14      2    label       Ljava/lang/String;
   0      14      3    attributes       Lscala/xml/MetaData;
   0      14      4    scope       Lscala/xml/NamespaceBinding;
   0      14      5    child       Lscala/collection/Seq;

  Signature: length = 0x2
   00 74 

public java.lang.String text();
  Signature: ()Ljava/lang/String;
  Code:
   Stack=4, Locals=1, Args_size=1
	aload_0
	invokevirtual	Method child:()Lscala/collection/Seq;
	new	class scala/xml/Elem$$anonfun$text$1
	dup
	aload_0
	invokespecial	Method scala/xml/Elem$$anonfun$text$1."<init>":(Lscala/xml/Elem;)V
	getstatic	Field scala/collection/Seq$.MODULE$:Lscala/collection/Seq$;
	invokevirtual	Method scala/collection/Seq$.canBuildFrom:()Lscala/collection/generic/CanBuildFrom;
	invokeinterface	InterfaceMethod scala/collection/TraversableLike.map:(Lscala/Function1;Lscala/collection/generic/CanBuildFrom;)Ljava/lang/Object;
	checkcast	class scala/collection/TraversableLike
	invokeinterface	InterfaceMethod scala/collection/TraversableLike.mkString:()Ljava/lang/String;
	areturn
  Labels:

public scala.xml.Elem(java.lang.String, java.lang.String, scala.xml.MetaData, scala.xml.NamespaceBinding, scala.collection.Seq);
  Signature: (Ljava/lang/String;Ljava/lang/String;Lscala/xml/MetaData;Lscala/xml/NamespaceBinding;Lscala/collection/Seq;)V
  Code:
   Stack=3, Locals=7, Args_size=6
	aload_0
	aload_1
	putfield	Field prefix:Ljava/lang/String;
	aload_0
	aload_2
	putfield	Field label:Ljava/lang/String;
	aload_0
	aload_3
	putfield	Field attributes:Lscala/xml/MetaData;
	aload_0
	aload	4
	putfield	Field scope:Lscala/xml/NamespaceBinding;
	aload_0
	aload	5
	putfield	Field child:Lscala/collection/Seq;
	aload_0
	invokespecial	Method scala/xml/Node."<init>":()V
	aload_1
	ldc	String 
	astore	6
	dup
	ifnonnull	l1 // aload
	pop
	aload	6
	ifnull	l2 // new
	goto	l3 // aload
l1	aload	6
	invokevirtual	Method java/lang/Object.equals:(Ljava/lang/Object;)Z
	ifeq	l3 // aload
l2	new	class java/lang/IllegalArgumentException
	dup
	ldc	String prefix of zero length, use null instead
	invokespecial	Method java/lang/IllegalArgumentException."<init>":(Ljava/lang/String;)V
	athrow
l3	aload	4
	dup
	pop
	ifnull	l4 // new
	aload	4
	aconst_null
	invokevirtual	Method java/lang/Object.equals:(Ljava/lang/Object;)Z
	ifeq	l5 // return
l4	new	class java/lang/IllegalArgumentException
	dup
	ldc	String scope is null, use xml.TopScope for empty scope
	invokespecial	Method java/lang/IllegalArgumentException."<init>":(Ljava/lang/String;)V
	athrow
l5	return
  Labels:
   	l1 = 49 // aload
   	l2 = 57 // new
   	l3 = 67 // aload
   	l4 = 83 // new
   	l5 = 93 // return
  LocalVariableTable: 
   Start  Length  Slot  Name   Signature
   0      94      0    this       Lscala/xml/Elem;
   0      94      1    prefix       Ljava/lang/String;
   0      94      2    label       Ljava/lang/String;
   0      94      3    attributes       Lscala/xml/MetaData;
   0      94      4    scope       Lscala/xml/NamespaceBinding;
   0      94      5    child       Lscala/collection/Seq;

  Signature: length = 0x2
   00 FFFFFFA3 

}

