Compiled from "EntityRef.scala"
public class scala.xml.EntityRef extends scala.xml.SpecialNode implements scala.ScalaObject,scala.Product,java.io.Serializable
  SourceFile: "EntityRef.scala"
  ScalaSig: length = 0x378
   05 00 FFFFFF81 03 06 08 01 02 FFFFFF84 FFFFFF80 FFFFFF80 FFFFFF80 40 07 02 09
   45 6E 74 69 74 79 52 65 66 0A 02 03 04 01 03 78
   6D 6C 0A 01 05 01 05 73 63 61 6C 61 03 00 13 04
   00 08 0C 10 10 02 09 0A 0D 01 02 09 02 0B 02 02
   0B 53 70 65 63 69 61 6C 4E 6F 64 65 10 02 0D 0E
   0D 01 04 09 02 0F 04 02 0B 53 63 61 6C 61 4F 62
   6A 65 63 74 10 02 0D 11 09 02 12 04 02 07 50 72
   6F 64 75 63 74 08 08 14 00 FFFFFF82 FFFFFFCA FFFFFF80 FFFFFF84 00 15 01
   0A 65 6E 74 69 74 79 4E 61 6D 65 15 01 16 10 02
   17 1A 0E 02 0D 18 09 02 19 04 01 06 50 72 65 64
   65 66 09 02 1B 1C 02 06 53 74 72 69 6E 67 0A 02
   19 04 08 08 1E 00 FFFFFF82 FFFFFF88 FFFFFFA0 FFFFFF80 04 16 01 0B 65 6E
   74 69 74 79 4E 61 6D 65 20 08 05 20 00 FFFFFF84 00 21
   01 06 3C 69 6E 69 74 3E 14 02 22 23 10 02 09 00
   08 05 14 1F FFFFFFC0 00 16 08 05 25 00 FFFFFF84 22 26 01 13
   64 6F 43 6F 6C 6C 65 63 74 4E 61 6D 65 73 70 61
   63 65 73 15 01 27 10 02 0D 28 09 02 29 04 02 07
   42 6F 6F 6C 65 61 6E 08 05 2B 00 FFFFFF84 22 26 01 0B
   64 6F 54 72 61 6E 73 66 6F 72 6D 08 05 2D 00 FFFFFF84
   00 2E 01 05 6C 61 62 65 6C 15 01 2F 10 02 30 35
   0D 01 31 0A 02 32 33 01 04 6C 61 6E 67 0A 01 34
   01 04 6A 61 76 61 09 02 1B 31 08 05 37 00 FFFFFF84 20
   15 01 04 74 65 78 74 08 05 39 00 FFFFFF84 20 3A 01 0B
   62 75 69 6C 64 53 74 72 69 6E 67 14 02 3B 43 10
   02 3C 41 0D 01 3D 0A 02 3E 3F 01 07 6D 75 74 61
   62 6C 65 0A 02 40 04 01 0A 63 6F 6C 6C 65 63 74
   69 6F 6E 09 02 42 3D 02 0D 53 74 72 69 6E 67 42
   75 69 6C 64 65 72 08 05 44 38 FFFFFFC0 00 3B 01 02 73
   62 08 07 46 00 FFFFFF81 FFFFFF80 FFFFFF84 00 47 01 04 63 6F 70 79
   14 02 22 48 08 08 49 14 45 FFFFFF90 FFFFFF80 FFFFFFC0 00 16 08 07
   4A 00 FFFFFF91 FFFFFF80 FFFFFF84 00 4B 01 0E 63 6F 70 79 24 64 65
   66 61 75 6C 74 24 31 15 01 4C 2A 02 16 4D 2B 01
   4E 10 02 4F 54 0D 01 50 0A 02 51 52 01 09 75 6E
   63 68 65 63 6B 65 64 0A 02 53 04 01 0A 61 6E 6E
   6F 74 61 74 69 6F 6E 09 02 55 50 02 11 75 6E 63
   68 65 63 6B 65 64 56 61 72 69 61 6E 63 65 08 08
   57 00 FFFFFF84 FFFFFF80 FFFFFF80 FFFFFF84 20 2E 01 0D 70 72 6F 64 75 63
   74 50 72 65 66 69 78 08 08 59 00 FFFFFF84 FFFFFF80 FFFFFF80 FFFFFF84 20
   5A 01 0C 70 72 6F 64 75 63 74 41 72 69 74 79 15
   01 5B 10 02 0D 5C 09 02 5D 04 02 03 49 6E 74 08
   08 5F 00 FFFFFF84 FFFFFF80 FFFFFF80 FFFFFF84 20 60 01 0E 70 72 6F 64 75
   63 74 45 6C 65 6D 65 6E 74 14 02 61 64 10 02 0D
   62 09 02 63 04 02 03 41 6E 79 08 07 65 5E FFFFFF81 FFFFFF80
   FFFFFFC0 00 5B 01 03 78 24 31 28 02 00 67 10 02 0D 68
   09 02 69 04 02 0C 73 65 72 69 61 6C 69 7A 61 62
   6C 65 07 07 6B 02 FFFFFF81 FFFFFF80 FFFFFF88 02 6C 01 09 45 6E 74
   69 74 79 52 65 66 10 02 09 6D 06 08 01 02 FFFFFF84 FFFFFF81
   FFFFFF80 FFFFFF88 02 6E 13 04 6D 6F 72 0C 10 02 30 70 09 02
   71 31 02 06 4F 62 6A 65 63 74 10 04 0D 73 16 22
   09 02 74 04 02 09 46 75 6E 63 74 69 6F 6E 31 08
   05 20 6D FFFFFF84 00 76 14 01 6C 08 07 78 6D FFFFFF81 FFFFFF80 FFFFFF84
   40 79 01 05 61 70 70 6C 79 14 02 22 7A 08 05 14
   77 FFFFFFC0 00 16 08 07 7C 6D FFFFFF81 FFFFFF80 FFFFFF84 40 7D 01 07 75
   6E 61 70 70 6C 79 14 03 7E FFFFFF81 01 10 03 0D 7F 16
   09 03 FFFFFF81 00 04 02 04 53 6F 6D 65 08 06 FFFFFF81 02 7B
   FFFFFFC0 00 22 01 03 78 24 30 
  InnerClass: 
   public final $anonfun$text$1=class scala/xml/EntityRef$$anonfun$text$1 of class scala/xml/EntityRef
  minor version: 0
  major version: 49
  Constant pool:
Asciz	SourceFile;
Asciz	EntityRef.scala;
Asciz	entityName;
Asciz	Ljava/lang/String;;
Asciz	<init>;
Asciz	(Ljava/lang/String;)V;
Asciz	Code;
Asciz	LineNumberTable;
Asciz	scala/xml/EntityRef;
class	scala/xml/EntityRef
NameAndType	entityName:Ljava/lang/String;
Field	scala/xml/EntityRef.entityName:Ljava/lang/String;
Asciz	scala/xml/SpecialNode;
class	scala/xml/SpecialNode
Asciz	()V;
NameAndType	"<init>":()V
Method	scala/xml/SpecialNode."<init>":()V
Asciz	scala/Product$class;
class	scala/Product$class
Asciz	$init$;
Asciz	(Lscala/Product;)V;
NameAndType	$init$:(Lscala/Product;)V
Method	scala/Product$class.$init$:(Lscala/Product;)V
Asciz	this;
Asciz	Lscala/xml/EntityRef;;
Asciz	LocalVariableTable;
Asciz	productElement;
Asciz	(I)Ljava/lang/Object;;
Asciz	()Ljava/lang/String;;
NameAndType	entityName:()Ljava/lang/String;
Method	scala/xml/EntityRef.entityName:()Ljava/lang/String;
Asciz	scala/MatchError;
class	scala/MatchError
Asciz	scala/runtime/BoxesRunTime;
class	scala/runtime/BoxesRunTime
Asciz	boxToInteger;
Asciz	(I)Ljava/lang/Integer;;
NameAndType	boxToInteger:(I)Ljava/lang/Integer;
Method	scala/runtime/BoxesRunTime.boxToInteger:(I)Ljava/lang/Integer;
Asciz	java/lang/Object;
class	java/lang/Object
Asciz	toString;
NameAndType	toString:()Ljava/lang/String;
Method	java/lang/Object.toString:()Ljava/lang/String;
NameAndType	"<init>":(Ljava/lang/String;)V
Method	scala/MatchError."<init>":(Ljava/lang/String;)V
Asciz	java/lang/IndexOutOfBoundsException;
class	java/lang/IndexOutOfBoundsException
Method	java/lang/IndexOutOfBoundsException."<init>":(Ljava/lang/String;)V
Asciz	productArity;
Asciz	()I;
Asciz	productPrefix;
Asciz	EntityRef;
String	EntityRef
Asciz	copy;
Asciz	(Ljava/lang/String;)Lscala/xml/EntityRef;;
Method	scala/xml/EntityRef."<init>":(Ljava/lang/String;)V
Asciz	buildString;
Asciz	(Lscala/collection/mutable/StringBuilder;)Lscala/collection/mutable/StringBuilder;;
Asciz	&;
String	&
Asciz	scala/collection/mutable/StringBuilder;
class	scala/collection/mutable/StringBuilder
Asciz	append;
Asciz	(Ljava/lang/String;)Lscala/collection/mutable/StringBuilder;;
NameAndType	append:(Ljava/lang/String;)Lscala/collection/mutable/StringBuilder;
Method	scala/collection/mutable/StringBuilder.append:(Ljava/lang/String;)Lscala/collection/mutable/StringBuilder;
Asciz	;;
String	;
Asciz	sb;
Asciz	Lscala/collection/mutable/StringBuilder;;
Asciz	text;
Asciz	lt;
String	lt
Asciz	equals;
Asciz	(Ljava/lang/Object;)Z;
NameAndType	equals:(Ljava/lang/Object;)Z
Method	java/lang/Object.equals:(Ljava/lang/Object;)Z
Asciz	<;
String	<
Asciz	java/lang/String;
class	java/lang/String
Method	java/lang/String.toString:()Ljava/lang/String;
Asciz	gt;
String	gt
Asciz	>;
String	>
Asciz	amp;
String	amp
Asciz	apos;
String	apos
Asciz	';
String	'
Asciz	quot;
String	quot
Asciz	\";
String	\"
Method	scala/collection/mutable/StringBuilder."<init>":()V
NameAndType	buildString:(Lscala/collection/mutable/StringBuilder;)Lscala/collection/mutable/StringBuilder;
Method	scala/xml/EntityRef.buildString:(Lscala/collection/mutable/StringBuilder;)Lscala/collection/mutable/StringBuilder;
Method	scala/collection/mutable/StringBuilder.toString:()Ljava/lang/String;
Asciz	sb0;
Asciz	temp1;
Asciz	label;
Asciz	#ENTITY;
String	#ENTITY
Asciz	doTransform;
Asciz	()Z;
Asciz	doCollectNamespaces;
Asciz	copy$default$1;
Asciz	productElements;
Asciz	()Lscala/collection/Iterator;;
Asciz	(Lscala/Product;)Lscala/collection/Iterator;;
NameAndType	productElements:(Lscala/Product;)Lscala/collection/Iterator;
Method	scala/Product$class.productElements:(Lscala/Product;)Lscala/collection/Iterator;
Asciz	productIterator;
NameAndType	productIterator:(Lscala/Product;)Lscala/collection/Iterator;
Method	scala/Product$class.productIterator:(Lscala/Product;)Lscala/collection/Iterator;
Asciz	ScalaSig;
Asciz	InnerClasses;
Asciz	scala/xml/EntityRef$$anonfun$text$1;
class	scala/xml/EntityRef$$anonfun$text$1
Asciz	$anonfun$text$1;
Asciz	scala/ScalaObject;
class	scala/ScalaObject
Asciz	scala/Product;
class	scala/Product
Asciz	java/io/Serializable;
class	java/io/Serializable

{
private final java.lang.String entityName;
  Signature: Ljava/lang/String;

public scala.xml.EntityRef(java.lang.String);
  Signature: (Ljava/lang/String;)V
  Code:
   Stack=2, Locals=2, Args_size=2
	aload_0
	aload_1
	putfield	Field entityName:Ljava/lang/String;
	aload_0
	invokespecial	Method scala/xml/SpecialNode."<init>":()V
	aload_0
	invokestatic	Method scala/Product$class.$init$:(Lscala/Product;)V
	return
  Labels:
  LocalVariableTable: 
   Start  Length  Slot  Name   Signature
   0      14      0    this       Lscala/xml/EntityRef;
   0      14      1    entityName       Ljava/lang/String;


public java.lang.Object productElement(int);
  Signature: (I)Ljava/lang/Object;
  Code:
   Stack=3, Locals=2, Args_size=2
	iload_1
	iconst_0
	if_icmpne	l1 // iconst_1
	iconst_1
	ifeq	l2 // new
	aload_0
	invokevirtual	Method entityName:()Ljava/lang/String;
	areturn
l2	new	class scala/MatchError
	dup
	iload_1
	invokestatic	Method scala/runtime/BoxesRunTime.boxToInteger:(I)Ljava/lang/Integer;
	invokevirtual	Method java/lang/Object.toString:()Ljava/lang/String;
	invokespecial	Method scala/MatchError."<init>":(Ljava/lang/String;)V
	athrow
l1	iconst_1
	ifeq	l3 // new
	new	class java/lang/IndexOutOfBoundsException
	dup
	iload_1
	invokestatic	Method scala/runtime/BoxesRunTime.boxToInteger:(I)Ljava/lang/Integer;
	invokevirtual	Method java/lang/Object.toString:()Ljava/lang/String;
	invokespecial	Method java/lang/IndexOutOfBoundsException."<init>":(Ljava/lang/String;)V
	athrow
l3	new	class scala/MatchError
	dup
	iload_1
	invokestatic	Method scala/runtime/BoxesRunTime.boxToInteger:(I)Ljava/lang/Integer;
	invokevirtual	Method java/lang/Object.toString:()Ljava/lang/String;
	invokespecial	Method scala/MatchError."<init>":(Ljava/lang/String;)V
	athrow
  Labels:
   	l2 = 14 // new
   	l1 = 29 // iconst_1
   	l3 = 48 // new

public int productArity();
  Signature: ()I
  Code:
   Stack=1, Locals=1, Args_size=1
	iconst_1
	ireturn
  Labels:

public java.lang.String productPrefix();
  Signature: ()Ljava/lang/String;
  Code:
   Stack=1, Locals=1, Args_size=1
	ldc	String EntityRef
	areturn
  Labels:

public scala.xml.EntityRef copy(java.lang.String);
  Signature: (Ljava/lang/String;)Lscala/xml/EntityRef;
  Code:
   Stack=3, Locals=2, Args_size=2
	new	class scala/xml/EntityRef
	dup
	aload_1
	invokespecial	Method "<init>":(Ljava/lang/String;)V
	areturn
  Labels:
  LocalVariableTable: 
   Start  Length  Slot  Name   Signature
   0      9      0    this       Lscala/xml/EntityRef;
   0      9      1    entityName       Ljava/lang/String;


public scala.collection.mutable.StringBuilder buildString(scala.collection.mutable.StringBuilder);
  Signature: (Lscala/collection/mutable/StringBuilder;)Lscala/collection/mutable/StringBuilder;
  Code:
   Stack=2, Locals=2, Args_size=2
	aload_1
	ldc	String &
	invokevirtual	Method scala/collection/mutable/StringBuilder.append:(Ljava/lang/String;)Lscala/collection/mutable/StringBuilder;
	aload_0
	invokevirtual	Method entityName:()Ljava/lang/String;
	invokevirtual	Method scala/collection/mutable/StringBuilder.append:(Ljava/lang/String;)Lscala/collection/mutable/StringBuilder;
	ldc	String ;
	invokevirtual	Method scala/collection/mutable/StringBuilder.append:(Ljava/lang/String;)Lscala/collection/mutable/StringBuilder;
	areturn
  Labels:
  LocalVariableTable: 
   Start  Length  Slot  Name   Signature
   0      19      0    this       Lscala/xml/EntityRef;
   0      19      1    sb       Lscala/collection/mutable/StringBuilder;


public java.lang.String text();
  Signature: ()Ljava/lang/String;
  Code:
   Stack=3, Locals=9, Args_size=1
	aload_0
	invokevirtual	Method entityName:()Ljava/lang/String;
	astore	8
	aload	8
	ldc	String lt
	astore_1
	dup
	ifnonnull	l1 // aload_1
	pop
	aload_1
	ifnull	l2 // iconst_1
	goto	l3 // aload
l1	aload_1
	invokevirtual	Method java/lang/Object.equals:(Ljava/lang/Object;)Z
	ifeq	l3 // aload
l2	iconst_1
	ifeq	l4 // new
	ldc	String <
	goto	l5 // areturn
l4	new	class scala/MatchError
	dup
	aload	8
	invokevirtual	Method java/lang/String.toString:()Ljava/lang/String;
	invokespecial	Method scala/MatchError."<init>":(Ljava/lang/String;)V
	athrow
l3	aload	8
	ldc	String gt
	astore_2
	dup
	ifnonnull	l6 // aload_2
	pop
	aload_2
	ifnull	l7 // iconst_1
	goto	l8 // aload
l6	aload_2
	invokevirtual	Method java/lang/Object.equals:(Ljava/lang/Object;)Z
	ifeq	l8 // aload
l7	iconst_1
	ifeq	l9 // new
	ldc	String >
	goto	l5 // areturn
l9	new	class scala/MatchError
	dup
	aload	8
	invokevirtual	Method java/lang/String.toString:()Ljava/lang/String;
	invokespecial	Method scala/MatchError."<init>":(Ljava/lang/String;)V
	athrow
l8	aload	8
	ldc	String amp
	astore_3
	dup
	ifnonnull	l10 // aload_3
	pop
	aload_3
	ifnull	l11 // iconst_1
	goto	l12 // aload
l10	aload_3
	invokevirtual	Method java/lang/Object.equals:(Ljava/lang/Object;)Z
	ifeq	l12 // aload
l11	iconst_1
	ifeq	l13 // new
	ldc	String &
	goto	l5 // areturn
l13	new	class scala/MatchError
	dup
	aload	8
	invokevirtual	Method java/lang/String.toString:()Ljava/lang/String;
	invokespecial	Method scala/MatchError."<init>":(Ljava/lang/String;)V
	athrow
l12	aload	8
	ldc	String apos
	astore	4
	dup
	ifnonnull	l14 // aload
	pop
	aload	4
	ifnull	l15 // iconst_1
	goto	l16 // aload
l14	aload	4
	invokevirtual	Method java/lang/Object.equals:(Ljava/lang/Object;)Z
	ifeq	l16 // aload
l15	iconst_1
	ifeq	l17 // new
	ldc	String '
	goto	l5 // areturn
l17	new	class scala/MatchError
	dup
	aload	8
	invokevirtual	Method java/lang/String.toString:()Ljava/lang/String;
	invokespecial	Method scala/MatchError."<init>":(Ljava/lang/String;)V
	athrow
l16	aload	8
	ldc	String quot
	astore	5
	dup
	ifnonnull	l18 // aload
	pop
	aload	5
	ifnull	l19 // iconst_1
	goto	l20 // iconst_1
l18	aload	5
	invokevirtual	Method java/lang/Object.equals:(Ljava/lang/Object;)Z
	ifeq	l20 // iconst_1
l19	iconst_1
	ifeq	l21 // new
	ldc	String \"
	goto	l5 // areturn
l21	new	class scala/MatchError
	dup
	aload	8
	invokevirtual	Method java/lang/String.toString:()Ljava/lang/String;
	invokespecial	Method scala/MatchError."<init>":(Ljava/lang/String;)V
	athrow
l20	iconst_1
	ifeq	l22 // new
	new	class scala/collection/mutable/StringBuilder
	dup
	invokespecial	Method scala/collection/mutable/StringBuilder."<init>":()V
	astore	7
	aload	7
	checkcast	class scala/collection/mutable/StringBuilder
	astore	6
	aload_0
	aload	6
	invokevirtual	Method buildString:(Lscala/collection/mutable/StringBuilder;)Lscala/collection/mutable/StringBuilder;
	pop
	aload	7
	invokevirtual	Method scala/collection/mutable/StringBuilder.toString:()Ljava/lang/String;
l5	areturn
l22	new	class scala/MatchError
	dup
	aload	8
	invokevirtual	Method java/lang/String.toString:()Ljava/lang/String;
	invokespecial	Method scala/MatchError."<init>":(Ljava/lang/String;)V
	athrow
  Labels:
   	l1 = 23 // aload_1
   	l2 = 30 // iconst_1
   	l4 = 39 // new
   	l3 = 52 // aload
   	l6 = 69 // aload_2
   	l7 = 76 // iconst_1
   	l9 = 85 // new
   	l8 = 98 // aload
   	l10 = 115 // aload_3
   	l11 = 122 // iconst_1
   	l13 = 131 // new
   	l12 = 144 // aload
   	l14 = 163 // aload
   	l15 = 171 // iconst_1
   	l17 = 180 // new
   	l16 = 193 // aload
   	l18 = 212 // aload
   	l19 = 220 // iconst_1
   	l21 = 229 // new
   	l20 = 242 // iconst_1
   	l5 = 274 // areturn
   	l22 = 275 // new
  LocalVariableTable: 
   Start  Length  Slot  Name   Signature
   0      288      0    this       Lscala/xml/EntityRef;
   255      19      7    sb0       Lscala/collection/mutable/StringBuilder;
   6      282      8    temp1       Ljava/lang/String;


public java.lang.String label();
  Signature: ()Ljava/lang/String;
  Code:
   Stack=1, Locals=1, Args_size=1
	ldc	String #ENTITY
	areturn
  Labels:

public final boolean doTransform();
  Signature: ()Z
  Code:
   Stack=1, Locals=1, Args_size=1
	iconst_0
	ireturn
  Labels:

public final boolean doCollectNamespaces();
  Signature: ()Z
  Code:
   Stack=1, Locals=1, Args_size=1
	iconst_0
	ireturn
  Labels:

public java.lang.String entityName();
  Signature: ()Ljava/lang/String;
  Code:
   Stack=1, Locals=1, Args_size=1
	aload_0
	getfield	Field entityName:Ljava/lang/String;
	areturn
  Labels:

public java.lang.String copy$default$1();
  Signature: ()Ljava/lang/String;
  Code:
   Stack=1, Locals=1, Args_size=1
	aload_0
	invokevirtual	Method entityName:()Ljava/lang/String;
	areturn
  Labels:

public scala.collection.Iterator productElements();
  Signature: ()Lscala/collection/Iterator;
  Code:
   Stack=1, Locals=1, Args_size=1
	aload_0
	invokestatic	Method scala/Product$class.productElements:(Lscala/Product;)Lscala/collection/Iterator;
	areturn
  Labels:

public scala.collection.Iterator productIterator();
  Signature: ()Lscala/collection/Iterator;
  Code:
   Stack=1, Locals=1, Args_size=1
	aload_0
	invokestatic	Method scala/Product$class.productIterator:(Lscala/Product;)Lscala/collection/Iterator;
	areturn
  Labels:

}

