Compiled from "EntityRef.scala"
public final class scala.xml.EntityRef$ extends java.lang.Object implements scala.Function1,scala.ScalaObject
  SourceFile: "EntityRef.scala"
  Scala: length = 0x
   
  InnerClass: 
   public final $anonfun$text$1=class scala/xml/EntityRef$$anonfun$text$1 of class scala/xml/EntityRef
  minor version: 0
  major version: 49
  Constant pool:
Asciz	SourceFile;
Asciz	EntityRef.scala;
Asciz	Scala;
Asciz	MODULE$;
Asciz	Lscala/xml/EntityRef$;;
Asciz	<clinit>;
Asciz	()V;
Asciz	Code;
Asciz	scala/xml/EntityRef$;
class	scala/xml/EntityRef$
Asciz	<init>;
NameAndType	"<init>":()V
Method	scala/xml/EntityRef$."<init>":()V
Asciz	toString;
Asciz	()Ljava/lang/String;;
Asciz	LineNumberTable;
Asciz	scala/Function1$class;
class	scala/Function1$class
Asciz	(Lscala/Function1;)Ljava/lang/String;;
NameAndType	toString:(Lscala/Function1;)Ljava/lang/String;
Method	scala/Function1$class.toString:(Lscala/Function1;)Ljava/lang/String;
Asciz	compose;
Asciz	(Lscala/Function1;)Lscala/Function1;;
Asciz	(Lscala/Function1;Lscala/Function1;)Lscala/Function1;;
NameAndType	compose:(Lscala/Function1;Lscala/Function1;)Lscala/Function1;
Method	scala/Function1$class.compose:(Lscala/Function1;Lscala/Function1;)Lscala/Function1;
Asciz	this;
Asciz	g;
Asciz	Lscala/Function1;;
Asciz	LocalVariableTable;
Asciz	andThen;
NameAndType	andThen:(Lscala/Function1;Lscala/Function1;)Lscala/Function1;
Method	scala/Function1$class.andThen:(Lscala/Function1;Lscala/Function1;)Lscala/Function1;
Asciz	unapply;
Asciz	(Lscala/xml/EntityRef;)Lscala/Some;;
Asciz	scala/Some;
class	scala/Some
Asciz	scala/xml/EntityRef;
class	scala/xml/EntityRef
Asciz	entityName;
NameAndType	entityName:()Ljava/lang/String;
Method	scala/xml/EntityRef.entityName:()Ljava/lang/String;
Asciz	(Ljava/lang/Object;)V;
NameAndType	"<init>":(Ljava/lang/Object;)V
Method	scala/Some."<init>":(Ljava/lang/Object;)V
Asciz	x$0;
Asciz	Lscala/xml/EntityRef;;
Asciz	apply;
Asciz	(Ljava/lang/String;)Lscala/xml/EntityRef;;
Asciz	(Ljava/lang/String;)V;
NameAndType	"<init>":(Ljava/lang/String;)V
Method	scala/xml/EntityRef."<init>":(Ljava/lang/String;)V
Asciz	Ljava/lang/String;;
Asciz	(Ljava/lang/Object;)Ljava/lang/Object;;
Asciz	java/lang/String;
class	java/lang/String
NameAndType	apply:(Ljava/lang/String;)Lscala/xml/EntityRef;
Method	scala/xml/EntityRef$.apply:(Ljava/lang/String;)Lscala/xml/EntityRef;
Asciz	v1;
Asciz	Ljava/lang/Object;;
Asciz	java/lang/Object;
class	java/lang/Object
Method	java/lang/Object."<init>":()V
NameAndType	MODULE$:Lscala/xml/EntityRef$;
Field	scala/xml/EntityRef$.MODULE$:Lscala/xml/EntityRef$;
Asciz	$init$;
Asciz	(Lscala/Function1;)V;
NameAndType	$init$:(Lscala/Function1;)V
Method	scala/Function1$class.$init$:(Lscala/Function1;)V
Asciz	InnerClasses;
Asciz	scala/xml/EntityRef$$anonfun$text$1;
class	scala/xml/EntityRef$$anonfun$text$1
Asciz	$anonfun$text$1;
Asciz	scala/Function1;
class	scala/Function1
Asciz	scala/ScalaObject;
class	scala/ScalaObject

{
public static final scala.xml.EntityRef$ MODULE$;
  Signature: Lscala/xml/EntityRef$;

public static {};
  Signature: ()V
  Code:
   Stack=1, Locals=0, Args_size=0
	new	class scala/xml/EntityRef$
	invokespecial	Method "<init>":()V
	return
  Labels:

public java.lang.String toString();
  Signature: ()Ljava/lang/String;
  Code:
   Stack=1, Locals=1, Args_size=1
	aload_0
	invokestatic	Method scala/Function1$class.toString:(Lscala/Function1;)Ljava/lang/String;
	areturn
  Labels:

public scala.Function1 compose(scala.Function1);
  Signature: (Lscala/Function1;)Lscala/Function1;
  Code:
   Stack=2, Locals=2, Args_size=2
	aload_0
	aload_1
	invokestatic	Method scala/Function1$class.compose:(Lscala/Function1;Lscala/Function1;)Lscala/Function1;
	areturn
  Labels:
  LocalVariableTable: 
   Start  Length  Slot  Name   Signature
   0      6      0    this       Lscala/xml/EntityRef$;
   0      6      1    g       Lscala/Function1;


public scala.Function1 andThen(scala.Function1);
  Signature: (Lscala/Function1;)Lscala/Function1;
  Code:
   Stack=2, Locals=2, Args_size=2
	aload_0
	aload_1
	invokestatic	Method scala/Function1$class.andThen:(Lscala/Function1;Lscala/Function1;)Lscala/Function1;
	areturn
  Labels:
  LocalVariableTable: 
   Start  Length  Slot  Name   Signature
   0      6      0    this       Lscala/xml/EntityRef$;
   0      6      1    g       Lscala/Function1;


public scala.Some unapply(scala.xml.EntityRef);
  Signature: (Lscala/xml/EntityRef;)Lscala/Some;
  Code:
   Stack=3, Locals=2, Args_size=2
	new	class scala/Some
	dup
	aload_1
	invokevirtual	Method scala/xml/EntityRef.entityName:()Ljava/lang/String;
	invokespecial	Method scala/Some."<init>":(Ljava/lang/Object;)V
	areturn
  Labels:
  LocalVariableTable: 
   Start  Length  Slot  Name   Signature
   0      12      0    this       Lscala/xml/EntityRef$;
   0      12      1    x$0       Lscala/xml/EntityRef;


public scala.xml.EntityRef apply(java.lang.String);
  Signature: (Ljava/lang/String;)Lscala/xml/EntityRef;
  Code:
   Stack=3, Locals=2, Args_size=2
	new	class scala/xml/EntityRef
	dup
	aload_1
	invokespecial	Method scala/xml/EntityRef."<init>":(Ljava/lang/String;)V
	areturn
  Labels:
  LocalVariableTable: 
   Start  Length  Slot  Name   Signature
   0      9      0    this       Lscala/xml/EntityRef$;
   0      9      1    entityName       Ljava/lang/String;


public java.lang.Object apply(java.lang.Object);
  Signature: (Ljava/lang/Object;)Ljava/lang/Object;
  Code:
   Stack=2, Locals=2, Args_size=2
	aload_0
	aload_1
	checkcast	class java/lang/String
	invokevirtual	Method apply:(Ljava/lang/String;)Lscala/xml/EntityRef;
	areturn
  Labels:
  LocalVariableTable: 
   Start  Length  Slot  Name   Signature
   0      9      0    this       Lscala/xml/EntityRef$;
   0      9      1    v1       Ljava/lang/Object;


private scala.xml.EntityRef$();
  Signature: ()V
  Code:
   Stack=1, Locals=1, Args_size=1
	aload_0
	invokespecial	Method java/lang/Object."<init>":()V
	aload_0
	putstatic	Field MODULE$:Lscala/xml/EntityRef$;
	aload_0
	invokestatic	Method scala/Function1$class.$init$:(Lscala/Function1;)V
	return
  Labels:

}

