Compiled from "Equality.scala"
public final class scala.xml.Equality$$anonfun$hashCode$1 extends scala.runtime.AbstractFunction1 implements java.io.Serializable
  InnerClass: 
   public final $anonfun$hashCode$1=class scala/xml/Equality$$anonfun$hashCode$1 of class scala/xml/Equality
  Scala: length = 0x
   
  SourceFile: "Equality.scala"
  minor version: 0
  major version: 49
  Constant pool:
class	java/io/Serializable
class	java/lang/NullPointerException
class	scala/runtime/AbstractFunction1
class	scala/runtime/BoxesRunTime
class	scala/xml/Equality
class	scala/xml/Equality$$anonfun$hashCode$1
class	scala/xml/Equality$class
Field	scala/xml/Equality$$anonfun$hashCode$1.$outer:Lscala/xml/Equality;
Field	scala/xml/Equality$$anonfun$hashCode$1.serialVersionUID:J
Method	java/lang/NullPointerException."<init>":()V
Method	scala/runtime/AbstractFunction1."<init>":()V
Method	scala/runtime/BoxesRunTime.boxToInteger:(I)Ljava/lang/Integer;
Method	scala/xml/Equality$$anonfun$hashCode$1.apply:(Ljava/lang/Object;)I
Method	scala/xml/Equality$class.scala$xml$Equality$$hashOf:(Lscala/xml/Equality;Ljava/lang/Object;)I
NameAndType	$outer:Lscala/xml/Equality;
NameAndType	"<init>":()V
NameAndType	apply:(Ljava/lang/Object;)I
NameAndType	boxToInteger:(I)Ljava/lang/Integer;
NameAndType	scala$xml$Equality$$hashOf:(Lscala/xml/Equality;Ljava/lang/Object;)I
NameAndType	serialVersionUID:J
Asciz	$anonfun$hashCode$1;
Asciz	$outer;
Asciz	()V;
Asciz	(I)Ljava/lang/Integer;;
Asciz	(Ljava/lang/Object;)I;
Asciz	(Ljava/lang/Object;)Ljava/lang/Object;;
Asciz	(Lscala/xml/Equality;)V;
Asciz	(Lscala/xml/Equality;Ljava/lang/Object;)I;
Asciz	<clinit>;
Asciz	<init>;
Asciz	Code;
Asciz	Equality.scala;
Asciz	InnerClasses;
Asciz	J;
Asciz	LineNumberTable;
Asciz	Ljava/lang/Object;;
Asciz	LocalVariableTable;
Asciz	Lscala/xml/Equality$$anonfun$hashCode$1;;
Asciz	Lscala/xml/Equality;;
Asciz	Scala;
Asciz	SourceFile;
Asciz	apply;
Asciz	boxToInteger;
Asciz	java/io/Serializable;
Asciz	java/lang/NullPointerException;
Asciz	scala$xml$Equality$$hashOf;
Asciz	scala/runtime/AbstractFunction1;
Asciz	scala/runtime/BoxesRunTime;
Asciz	scala/xml/Equality;
Asciz	scala/xml/Equality$$anonfun$hashCode$1;
Asciz	scala/xml/Equality$class;
Asciz	serialVersionUID;
Asciz	this;
Asciz	v1;

{
public static final long serialVersionUID;
  Signature: J

public final scala.xml.Equality $outer;
  Signature: Lscala/xml/Equality;

public static {};
  Signature: ()V
  Code:
   Stack=2, Locals=0, Args_size=0
	lconst_0
	putstatic	Field serialVersionUID:J
	return
  Labels:

public final int apply(java.lang.Object);
  Signature: (Ljava/lang/Object;)I
  Code:
   Stack=2, Locals=2, Args_size=2
	aload_0
	getfield	Field $outer:Lscala/xml/Equality;
	aload_1
	invokestatic	Method scala/xml/Equality$class.scala$xml$Equality$$hashOf:(Lscala/xml/Equality;Ljava/lang/Object;)I
	ireturn
  Labels:

public final java.lang.Object apply(java.lang.Object);
  Signature: (Ljava/lang/Object;)Ljava/lang/Object;
  Code:
   Stack=2, Locals=3, Args_size=2
	aload_0
	aload_1
	invokevirtual	Method apply:(Ljava/lang/Object;)I
	istore_2
	iload_2
	invokestatic	Method scala/runtime/BoxesRunTime.boxToInteger:(I)Ljava/lang/Integer;
	areturn
  Labels:
  LocalVariableTable: 
   Start  Length  Slot  Name   Signature
   0      11      0    this       Lscala/xml/Equality$$anonfun$hashCode$1;
   0      11      1    v1       Ljava/lang/Object;


public scala.xml.Equality$$anonfun$hashCode$1(scala.xml.Equality);
  Signature: (Lscala/xml/Equality;)V
  Code:
   Stack=2, Locals=2, Args_size=2
	aload_1
	ifnonnull	l1 // aload_0
	new	class java/lang/NullPointerException
	dup
	invokespecial	Method java/lang/NullPointerException."<init>":()V
	athrow
l1	aload_0
	aload_1
	putfield	Field $outer:Lscala/xml/Equality;
	aload_0
	invokespecial	Method scala/runtime/AbstractFunction1."<init>":()V
	return
  Labels:
   	l1 = 12 // aload_0
  LocalVariableTable: 
   Start  Length  Slot  Name   Signature
   0      22      0    this       Lscala/xml/Equality$$anonfun$hashCode$1;
   0      22      1    $outer       Lscala/xml/Equality;


}

