Compiled from "Equality.scala"
public final class scala.xml.Equality$$anonfun$hashCode$2 extends scala.runtime.AbstractFunction2 implements java.io.Serializable
  InnerClass: 
   public final $anonfun$hashCode$2=class scala/xml/Equality$$anonfun$hashCode$2 of class scala/xml/Equality
  Scala: length = 0x
   
  SourceFile: "Equality.scala"
  minor version: 0
  major version: 49
  Constant pool:
int	7;
class	java/io/Serializable
class	scala/runtime/AbstractFunction2
class	scala/runtime/BoxesRunTime
class	scala/xml/Equality
class	scala/xml/Equality$$anonfun$hashCode$2
Field	scala/xml/Equality$$anonfun$hashCode$2.serialVersionUID:J
Method	scala/runtime/AbstractFunction2."<init>":()V
Method	scala/runtime/BoxesRunTime.boxToInteger:(I)Ljava/lang/Integer;
Method	scala/runtime/BoxesRunTime.unboxToInt:(Ljava/lang/Object;)I
Method	scala/xml/Equality$$anonfun$hashCode$2.apply:(II)I
NameAndType	"<init>":()V
NameAndType	apply:(II)I
NameAndType	boxToInteger:(I)Ljava/lang/Integer;
NameAndType	serialVersionUID:J
NameAndType	unboxToInt:(Ljava/lang/Object;)I
Asciz	$anonfun$hashCode$2;
Asciz	$outer;
Asciz	()V;
Asciz	(I)Ljava/lang/Integer;;
Asciz	(II)I;
Asciz	(Ljava/lang/Object;)I;
Asciz	(Ljava/lang/Object;Ljava/lang/Object;)Ljava/lang/Object;;
Asciz	(Lscala/xml/Equality;)V;
Asciz	<clinit>;
Asciz	<init>;
Asciz	Code;
Asciz	Equality.scala;
Asciz	InnerClasses;
Asciz	J;
Asciz	LineNumberTable;
Asciz	Ljava/lang/Object;;
Asciz	LocalVariableTable;
Asciz	Lscala/xml/Equality$$anonfun$hashCode$2;;
Asciz	Lscala/xml/Equality;;
Asciz	Scala;
Asciz	SourceFile;
Asciz	apply;
Asciz	boxToInteger;
Asciz	java/io/Serializable;
Asciz	scala/runtime/AbstractFunction2;
Asciz	scala/runtime/BoxesRunTime;
Asciz	scala/xml/Equality;
Asciz	scala/xml/Equality$$anonfun$hashCode$2;
Asciz	serialVersionUID;
Asciz	this;
Asciz	unboxToInt;
Asciz	v1;
Asciz	v2;

{
public static final long serialVersionUID;
  Signature: J

public static {};
  Signature: ()V
  Code:
   Stack=2, Locals=0, Args_size=0
	lconst_0
	putstatic	Field serialVersionUID:J
	return
  Labels:

public final int apply(int, int);
  Signature: (II)I
  Code:
   Stack=2, Locals=3, Args_size=3
	iload_1
	ldc	int 7
	imul
	iload_2
	iadd
	ireturn
  Labels:

public final java.lang.Object apply(java.lang.Object, java.lang.Object);
  Signature: (Ljava/lang/Object;Ljava/lang/Object;)Ljava/lang/Object;
  Code:
   Stack=3, Locals=4, Args_size=3
	aload_0
	aload_1
	invokestatic	Method scala/runtime/BoxesRunTime.unboxToInt:(Ljava/lang/Object;)I
	aload_2
	invokestatic	Method scala/runtime/BoxesRunTime.unboxToInt:(Ljava/lang/Object;)I
	invokevirtual	Method apply:(II)I
	istore_3
	iload_3
	invokestatic	Method scala/runtime/BoxesRunTime.boxToInteger:(I)Ljava/lang/Integer;
	areturn
  Labels:
  LocalVariableTable: 
   Start  Length  Slot  Name   Signature
   0      18      0    this       Lscala/xml/Equality$$anonfun$hashCode$2;
   0      18      1    v1       Ljava/lang/Object;
   0      18      2    v2       Ljava/lang/Object;


public scala.xml.Equality$$anonfun$hashCode$2(scala.xml.Equality);
  Signature: (Lscala/xml/Equality;)V
  Code:
   Stack=1, Locals=2, Args_size=2
	aload_0
	invokespecial	Method scala/runtime/AbstractFunction2."<init>":()V
	return
  Labels:
  LocalVariableTable: 
   Start  Length  Slot  Name   Signature
   0      5      0    this       Lscala/xml/Equality$$anonfun$hashCode$2;
   0      5      1    $outer       Lscala/xml/Equality;


}

