Compiled from "Equality.scala"
public abstract class scala.xml.Equality$class extends java.lang.Object
  SourceFile: "Equality.scala"
  Scala: length = 0x
   
  InnerClass: 
   public final $anonfun$hashCode$2=class scala/xml/Equality$$anonfun$hashCode$2 of class scala/xml/Equality
   public final $anonfun$hashCode$1=class scala/xml/Equality$$anonfun$hashCode$1 of class scala/xml/Equality
  minor version: 0
  major version: 49
  Constant pool:
Asciz	SourceFile;
Asciz	Equality.scala;
Asciz	strict_$bang$eq;
Asciz	(Lscala/xml/Equality;Lscala/xml/Equality;)Z;
Asciz	Code;
Asciz	LineNumberTable;
Asciz	scala/xml/Equality;
class	scala/xml/Equality
Asciz	strict_$eq$eq;
Asciz	(Lscala/xml/Equality;)Z;
NameAndType	strict_$eq$eq:(Lscala/xml/Equality;)Z
InterfaceMethod	scala/xml/Equality.strict_$eq$eq:(Lscala/xml/Equality;)Z
Asciz	$this;
Asciz	Lscala/xml/Equality;;
Asciz	other;
Asciz	LocalVariableTable;
Asciz	scala$xml$Equality$$hashOf;
Asciz	(Lscala/xml/Equality;Ljava/lang/Object;)I;
Asciz	java/lang/Object;
class	java/lang/Object
Asciz	equals;
Asciz	(Ljava/lang/Object;)Z;
NameAndType	equals:(Ljava/lang/Object;)Z
Method	java/lang/Object.equals:(Ljava/lang/Object;)Z
Asciz	hashCode;
Asciz	()I;
NameAndType	hashCode:()I
Method	java/lang/Object.hashCode:()I
Asciz	x;
Asciz	Ljava/lang/Object;;
Asciz	canEqual;
Asciz	(Lscala/xml/Equality;Ljava/lang/Object;)Z;
Asciz	temp9;
Asciz	(Lscala/xml/Equality;)I;
Asciz	basisForHashCode;
Asciz	()Lscala/collection/Seq;;
NameAndType	basisForHashCode:()Lscala/collection/Seq;
InterfaceMethod	scala/xml/Equality.basisForHashCode:()Lscala/collection/Seq;
Asciz	scala/collection/immutable/Nil$;
class	scala/collection/immutable/Nil$
Asciz	MODULE$;
Asciz	Lscala/collection/immutable/Nil$;;
NameAndType	MODULE$:Lscala/collection/immutable/Nil$;
Field	scala/collection/immutable/Nil$.MODULE$:Lscala/collection/immutable/Nil$;
Asciz	scala/collection/immutable/$colon$colon;
class	scala/collection/immutable/$colon$colon
Asciz	hd$1;
Asciz	()Ljava/lang/Object;;
NameAndType	hd$1:()Ljava/lang/Object;
Method	scala/collection/immutable/$colon$colon.hd$1:()Ljava/lang/Object;
Asciz	scala/xml/Equality$class;
class	scala/xml/Equality$class
NameAndType	scala$xml$Equality$$hashOf:(Lscala/xml/Equality;Ljava/lang/Object;)I
Method	scala/xml/Equality$class.scala$xml$Equality$$hashOf:(Lscala/xml/Equality;Ljava/lang/Object;)I
int	41;
Asciz	tl$1;
Asciz	()Lscala/collection/immutable/List;;
NameAndType	tl$1:()Lscala/collection/immutable/List;
Method	scala/collection/immutable/$colon$colon.tl$1:()Lscala/collection/immutable/List;
Asciz	scala/xml/Equality$$anonfun$hashCode$1;
class	scala/xml/Equality$$anonfun$hashCode$1
Asciz	<init>;
Asciz	(Lscala/xml/Equality;)V;
NameAndType	"<init>":(Lscala/xml/Equality;)V
Method	scala/xml/Equality$$anonfun$hashCode$1."<init>":(Lscala/xml/Equality;)V
Asciz	scala/collection/immutable/List$;
class	scala/collection/immutable/List$
Asciz	Lscala/collection/immutable/List$;;
NameAndType	MODULE$:Lscala/collection/immutable/List$;
Field	scala/collection/immutable/List$.MODULE$:Lscala/collection/immutable/List$;
Asciz	canBuildFrom;
Asciz	()Lscala/collection/generic/CanBuildFrom;;
NameAndType	canBuildFrom:()Lscala/collection/generic/CanBuildFrom;
Method	scala/collection/immutable/List$.canBuildFrom:()Lscala/collection/generic/CanBuildFrom;
Asciz	scala/collection/TraversableLike;
class	scala/collection/TraversableLike
Asciz	map;
Asciz	(Lscala/Function1;Lscala/collection/generic/CanBuildFrom;)Ljava/lang/Object;;
NameAndType	map:(Lscala/Function1;Lscala/collection/generic/CanBuildFrom;)Ljava/lang/Object;
InterfaceMethod	scala/collection/TraversableLike.map:(Lscala/Function1;Lscala/collection/generic/CanBuildFrom;)Ljava/lang/Object;
Asciz	scala/collection/LinearSeqLike;
class	scala/collection/LinearSeqLike
Asciz	scala/runtime/BoxesRunTime;
class	scala/runtime/BoxesRunTime
Asciz	boxToInteger;
Asciz	(I)Ljava/lang/Integer;;
NameAndType	boxToInteger:(I)Ljava/lang/Integer;
Method	scala/runtime/BoxesRunTime.boxToInteger:(I)Ljava/lang/Integer;
Asciz	scala/xml/Equality$$anonfun$hashCode$2;
class	scala/xml/Equality$$anonfun$hashCode$2
Method	scala/xml/Equality$$anonfun$hashCode$2."<init>":(Lscala/xml/Equality;)V
Asciz	foldLeft;
Asciz	(Ljava/lang/Object;Lscala/Function2;)Ljava/lang/Object;;
NameAndType	foldLeft:(Ljava/lang/Object;Lscala/Function2;)Ljava/lang/Object;
InterfaceMethod	scala/collection/LinearSeqLike.foldLeft:(Ljava/lang/Object;Lscala/Function2;)Ljava/lang/Object;
Asciz	unboxToInt;
Asciz	(Ljava/lang/Object;)I;
NameAndType	unboxToInt:(Ljava/lang/Object;)I
Method	scala/runtime/BoxesRunTime.unboxToInt:(Ljava/lang/Object;)I
Asciz	scala/MatchError;
class	scala/MatchError
Asciz	(Ljava/lang/Object;)V;
NameAndType	"<init>":(Ljava/lang/Object;)V
Method	scala/MatchError."<init>":(Ljava/lang/Object;)V
Asciz	temp11;
Asciz	Lscala/collection/Seq;;
Asciz	temp13;
Asciz	Lscala/collection/immutable/$colon$colon;;
Asciz	doComparison;
Asciz	(Lscala/xml/Equality;Ljava/lang/Object;Z)Z;
NameAndType	doComparison:(Lscala/xml/Equality;Ljava/lang/Object;Z)Z
Method	scala/xml/Equality$class.doComparison:(Lscala/xml/Equality;Ljava/lang/Object;Z)Z
Asciz	xml_$eq$eq;
Asciz	xml_$bang$eq;
NameAndType	xml_$eq$eq:(Ljava/lang/Object;)Z
InterfaceMethod	scala/xml/Equality.xml_$eq$eq:(Ljava/lang/Object;)Z
Asciz	gd2$1;
NameAndType	gd2$1:(Lscala/xml/Equality;Ljava/lang/Object;)Z
Method	scala/xml/Equality$class.gd2$1:(Lscala/xml/Equality;Ljava/lang/Object;)Z
NameAndType	canEqual:(Ljava/lang/Object;)Z
InterfaceMethod	scala/xml/Equality.canEqual:(Ljava/lang/Object;)Z
Asciz	scala/xml/Equality$;
class	scala/xml/Equality$
Asciz	Lscala/xml/Equality$;;
NameAndType	MODULE$:Lscala/xml/Equality$;
Field	scala/xml/Equality$.MODULE$:Lscala/xml/Equality$;
Asciz	asRef;
Asciz	(Ljava/lang/Object;)Ljava/lang/Object;;
NameAndType	asRef:(Ljava/lang/Object;)Ljava/lang/Object;
Method	scala/xml/Equality$.asRef:(Ljava/lang/Object;)Ljava/lang/Object;
Asciz	compareBlithely;
Asciz	(Ljava/lang/Object;Ljava/lang/Object;)Z;
NameAndType	compareBlithely:(Ljava/lang/Object;Ljava/lang/Object;)Z
Method	scala/xml/Equality$.compareBlithely:(Ljava/lang/Object;Ljava/lang/Object;)Z
Asciz	blithe;
Asciz	Z;
Asciz	strictlyEqual;
Asciz	temp16;
Asciz	temp17;
Asciz	temp18;
Asciz	$init$;
Asciz	Scala;
Asciz	InnerClasses;
Asciz	$anonfun$hashCode$2;
Asciz	$anonfun$hashCode$1;

{
public static boolean strict_$bang$eq(scala.xml.Equality, scala.xml.Equality);
  Signature: (Lscala/xml/Equality;Lscala/xml/Equality;)Z
  Code:
   Stack=2, Locals=2, Args_size=2
	aload_0
	aload_1
	invokeinterface	InterfaceMethod scala/xml/Equality.strict_$eq$eq:(Lscala/xml/Equality;)Z
	ifeq	l1 // iconst_1
	iconst_0
	goto	l2 // ireturn
l1	iconst_1
l2	ireturn
  Labels:
   	l1 = 14 // iconst_1
   	l2 = 15 // ireturn
  LocalVariableTable: 
   Start  Length  Slot  Name   Signature
   0      16      0    $this       Lscala/xml/Equality;
   0      16      1    other       Lscala/xml/Equality;


public static final int scala$xml$Equality$$hashOf(scala.xml.Equality, java.lang.Object);
  Signature: (Lscala/xml/Equality;Ljava/lang/Object;)I
  Code:
   Stack=2, Locals=3, Args_size=2
	aload_1
	dup
	astore_2
	ifnull	l1 // iconst_1
	aload_2
	aconst_null
	invokevirtual	Method java/lang/Object.equals:(Ljava/lang/Object;)Z
	ifeq	l2 // aload_1
l1	iconst_1
	goto	l3 // ireturn
l2	aload_1
	invokevirtual	Method java/lang/Object.hashCode:()I
l3	ireturn
  Labels:
   	l1 = 14 // iconst_1
   	l2 = 18 // aload_1
   	l3 = 22 // ireturn
  LocalVariableTable: 
   Start  Length  Slot  Name   Signature
   0      23      0    $this       Lscala/xml/Equality;
   0      23      1    x       Ljava/lang/Object;


public static boolean canEqual(scala.xml.Equality, java.lang.Object);
  Signature: (Lscala/xml/Equality;Ljava/lang/Object;)Z
  Code:
   Stack=1, Locals=3, Args_size=2
	aload_1
	astore_2
	aload_2
	instanceof	class scala/xml/Equality
	ireturn
  Labels:
  LocalVariableTable: 
   Start  Length  Slot  Name   Signature
   0      7      0    $this       Lscala/xml/Equality;
   0      7      1    other       Ljava/lang/Object;
   2      4      2    temp9       Ljava/lang/Object;


public static int hashCode(scala.xml.Equality);
  Signature: (Lscala/xml/Equality;)I
  Code:
   Stack=6, Locals=4, Args_size=1
	aload_0
	invokeinterface	InterfaceMethod scala/xml/Equality.basisForHashCode:()Lscala/collection/Seq;
	astore_1
	getstatic	Field scala/collection/immutable/Nil$.MODULE$:Lscala/collection/immutable/Nil$;
	aload_1
	astore_2
	dup
	ifnonnull	l1 // aload_2
	pop
	aload_2
	ifnull	l2 // iconst_0
	goto	l3 // aload_1
l1	aload_2
	invokevirtual	Method java/lang/Object.equals:(Ljava/lang/Object;)Z
	ifeq	l3 // aload_1
l2	iconst_0
	goto	l4 // ireturn
l3	aload_1
	instanceof	class scala/collection/immutable/$colon$colon
	ifeq	l5 // new
	aload_1
	checkcast	class scala/collection/immutable/$colon$colon
	astore_3
	aload_0
	aload_3
	invokevirtual	Method scala/collection/immutable/$colon$colon.hd$1:()Ljava/lang/Object;
	invokestatic	Method scala$xml$Equality$$hashOf:(Lscala/xml/Equality;Ljava/lang/Object;)I
	ldc	int 41
	imul
	aload_3
	invokevirtual	Method scala/collection/immutable/$colon$colon.tl$1:()Lscala/collection/immutable/List;
	new	class scala/xml/Equality$$anonfun$hashCode$1
	dup
	aload_0
	invokespecial	Method scala/xml/Equality$$anonfun$hashCode$1."<init>":(Lscala/xml/Equality;)V
	getstatic	Field scala/collection/immutable/List$.MODULE$:Lscala/collection/immutable/List$;
	invokevirtual	Method scala/collection/immutable/List$.canBuildFrom:()Lscala/collection/generic/CanBuildFrom;
	invokeinterface	InterfaceMethod scala/collection/TraversableLike.map:(Lscala/Function1;Lscala/collection/generic/CanBuildFrom;)Ljava/lang/Object;
	checkcast	class scala/collection/LinearSeqLike
	iconst_0
	invokestatic	Method scala/runtime/BoxesRunTime.boxToInteger:(I)Ljava/lang/Integer;
	new	class scala/xml/Equality$$anonfun$hashCode$2
	dup
	aload_0
	invokespecial	Method scala/xml/Equality$$anonfun$hashCode$2."<init>":(Lscala/xml/Equality;)V
	invokeinterface	InterfaceMethod scala/collection/LinearSeqLike.foldLeft:(Ljava/lang/Object;Lscala/Function2;)Ljava/lang/Object;
	invokestatic	Method scala/runtime/BoxesRunTime.unboxToInt:(Ljava/lang/Object;)I
	iadd
l4	ireturn
l5	new	class scala/MatchError
	dup
	aload_1
	invokespecial	Method scala/MatchError."<init>":(Ljava/lang/Object;)V
	athrow
  Labels:
   	l1 = 24 // aload_2
   	l2 = 31 // iconst_0
   	l3 = 35 // aload_1
   	l4 = 105 // ireturn
   	l5 = 106 // new
  LocalVariableTable: 
   Start  Length  Slot  Name   Signature
   0      115      0    $this       Lscala/xml/Equality;
   7      108      1    temp11       Lscala/collection/Seq;
   47      58      3    temp13       Lscala/collection/immutable/$colon$colon;


public static boolean equals(scala.xml.Equality, java.lang.Object);
  Signature: (Lscala/xml/Equality;Ljava/lang/Object;)Z
  Code:
   Stack=3, Locals=2, Args_size=2
	aload_0
	aload_1
	iconst_0
	invokestatic	Method doComparison:(Lscala/xml/Equality;Ljava/lang/Object;Z)Z
	ireturn
  Labels:
  LocalVariableTable: 
   Start  Length  Slot  Name   Signature
   0      7      0    $this       Lscala/xml/Equality;
   0      7      1    other       Ljava/lang/Object;


public static final boolean xml_$eq$eq(scala.xml.Equality, java.lang.Object);
  Signature: (Lscala/xml/Equality;Ljava/lang/Object;)Z
  Code:
   Stack=3, Locals=2, Args_size=2
	aload_0
	aload_1
	iconst_1
	invokestatic	Method doComparison:(Lscala/xml/Equality;Ljava/lang/Object;Z)Z
	ireturn
  Labels:
  LocalVariableTable: 
   Start  Length  Slot  Name   Signature
   0      7      0    $this       Lscala/xml/Equality;
   0      7      1    other       Ljava/lang/Object;


public static final boolean xml_$bang$eq(scala.xml.Equality, java.lang.Object);
  Signature: (Lscala/xml/Equality;Ljava/lang/Object;)Z
  Code:
   Stack=2, Locals=2, Args_size=2
	aload_0
	aload_1
	invokeinterface	InterfaceMethod scala/xml/Equality.xml_$eq$eq:(Ljava/lang/Object;)Z
	ifeq	l1 // iconst_1
	iconst_0
	goto	l2 // ireturn
l1	iconst_1
l2	ireturn
  Labels:
   	l1 = 14 // iconst_1
   	l2 = 15 // ireturn
  LocalVariableTable: 
   Start  Length  Slot  Name   Signature
   0      16      0    $this       Lscala/xml/Equality;
   0      16      1    other       Ljava/lang/Object;


private static boolean doComparison(scala.xml.Equality, java.lang.Object, boolean);
  Signature: (Lscala/xml/Equality;Ljava/lang/Object;Z)Z
  Code:
   Stack=4, Locals=8, Args_size=3
	aload_1
	astore	4
	aload	4
	instanceof	class java/lang/Object
	ifeq	l1 // iconst_0
	aload	4
	astore	5
	aload_0
	aload	5
	invokestatic	Method gd2$1:(Lscala/xml/Equality;Ljava/lang/Object;)Z
	ifeq	l2 // aload
	iconst_1
	goto	l3 // istore_3
l2	aload	5
	instanceof	class scala/xml/Equality
	ifeq	l4 // iconst_0
	aload	5
	checkcast	class scala/xml/Equality
	astore	6
	aload	6
	astore	7
	aload	7
	aload_0
	invokeinterface	InterfaceMethod scala/xml/Equality.canEqual:(Ljava/lang/Object;)Z
	ifeq	l5 // iconst_0
	aload_0
	aload	7
	invokeinterface	InterfaceMethod scala/xml/Equality.strict_$eq$eq:(Lscala/xml/Equality;)Z
	ifeq	l5 // iconst_0
	iconst_1
	goto	l3 // istore_3
l5	iconst_0
	goto	l3 // istore_3
l4	iconst_0
	goto	l3 // istore_3
l1	iconst_0
l3	istore_3
	iload_3
	ifne	l6 // iconst_1
	iload_2
	ifeq	l7 // iconst_0
	getstatic	Field scala/xml/Equality$.MODULE$:Lscala/xml/Equality$;
	aload_0
	getstatic	Field scala/xml/Equality$.MODULE$:Lscala/xml/Equality$;
	aload_1
	invokevirtual	Method scala/xml/Equality$.asRef:(Ljava/lang/Object;)Ljava/lang/Object;
	invokevirtual	Method scala/xml/Equality$.compareBlithely:(Ljava/lang/Object;Ljava/lang/Object;)Z
	ifeq	l7 // iconst_0
l6	iconst_1
	goto	l8 // ireturn
l7	iconst_0
l8	ireturn
  Labels:
   	l2 = 28 // aload
   	l5 = 73 // iconst_0
   	l4 = 77 // iconst_0
   	l1 = 81 // iconst_0
   	l3 = 82 // istore_3
   	l6 = 108 // iconst_1
   	l7 = 112 // iconst_0
   	l8 = 113 // ireturn
  LocalVariableTable: 
   Start  Length  Slot  Name   Signature
   0      114      0    $this       Lscala/xml/Equality;
   0      114      1    other       Ljava/lang/Object;
   0      114      2    blithe       Z
   83      31      3    strictlyEqual       Z
   3      84      4    temp16       Ljava/lang/Object;
   15      66      5    temp17       Ljava/lang/Object;
   43      34      6    temp18       Lscala/xml/Equality;
   47      30      7    x       Lscala/xml/Equality;


private static final boolean gd2$1(scala.xml.Equality, java.lang.Object);
  Signature: (Lscala/xml/Equality;Ljava/lang/Object;)Z
  Code:
   Stack=2, Locals=2, Args_size=2
	aload_0
	aload_1
	if_acmpne	l1 // iconst_0
	iconst_1
	goto	l2 // ireturn
l1	iconst_0
l2	ireturn
  Labels:
   	l1 = 9 // iconst_0
   	l2 = 10 // ireturn
  LocalVariableTable: 
   Start  Length  Slot  Name   Signature
   0      11      0    $this       Lscala/xml/Equality;


public static void $init$(scala.xml.Equality);
  Signature: (Lscala/xml/Equality;)V
  Code:
   Stack=0, Locals=1, Args_size=1
	return
  Labels:
  LocalVariableTable: 
   Start  Length  Slot  Name   Signature
   0      1      0    $this       Lscala/xml/Equality;


}

