Compiled from "Group.scala"
public class scala.xml.Group extends scala.xml.Node implements scala.ScalaObject,scala.Product,java.io.Serializable
  SourceFile: "Group.scala"
  ScalaSig: length = 0x3C6
   05 00 FFFFFF81 14 06 08 01 02 FFFFFF84 FFFFFF80 FFFFFF80 FFFFFF80 40 07 02 05
   47 72 6F 75 70 0A 02 03 04 01 03 78 6D 6C 0A 01
   05 01 05 73 63 61 6C 61 03 00 13 04 00 08 0C 10
   10 02 09 0A 0D 01 02 09 02 0B 02 02 04 4E 6F 64
   65 10 02 0D 0E 0D 01 04 09 02 0F 04 02 0B 53 63
   61 6C 61 4F 62 6A 65 63 74 10 02 0D 11 09 02 12
   04 02 07 50 72 6F 64 75 63 74 08 08 14 00 FFFFFF82 FFFFFFCA
   FFFFFF80 FFFFFF84 00 15 01 05 6E 6F 64 65 73 15 01 16 10 03
   17 1A 08 0D 01 18 0A 02 19 04 01 0A 63 6F 6C 6C
   65 63 74 69 6F 6E 09 02 1B 18 02 03 53 65 71 08
   08 1D 00 FFFFFF82 FFFFFF88 FFFFFFA0 FFFFFF80 04 16 01 06 6E 6F 64 65 73
   20 08 05 1F 00 FFFFFF84 00 20 01 06 3C 69 6E 69 74 3E
   14 02 21 22 10 02 09 00 08 05 14 1E FFFFFFC0 00 16 08
   05 24 00 FFFFFF84 20 15 01 06 74 68 65 53 65 71 08 05
   26 00 FFFFFF84 20 27 01 06 65 71 75 61 6C 73 14 02 28
   2B 10 02 0D 29 09 02 2A 04 02 07 42 6F 6F 6C 65
   61 6E 08 05 2C 25 FFFFFFC0 00 2D 01 01 78 10 02 0D 2E
   09 02 2F 04 02 03 41 6E 79 08 05 31 00 FFFFFF84 20 32
   01 08 68 61 73 68 43 6F 64 65 14 01 33 10 02 0D
   34 09 02 35 04 02 03 49 6E 74 08 05 37 00 FFFFFF84 02
   38 01 05 6C 61 62 65 6C 15 01 39 10 02 0D 3A 09
   02 3B 04 02 07 4E 6F 74 68 69 6E 67 08 05 3D 00
   FFFFFF84 22 38 01 0A 61 74 74 72 69 62 75 74 65 73 08
   05 3F 00 FFFFFF84 22 38 01 09 6E 61 6D 65 73 70 61 63
   65 08 05 41 00 FFFFFF84 22 38 01 05 63 68 69 6C 64 08
   05 43 00 FFFFFF84 00 44 01 0B 62 75 69 6C 64 53 74 72
   69 6E 67 14 02 39 45 08 05 46 42 FFFFFFC0 00 47 01 02
   73 62 10 02 48 50 0E 02 49 4E 0E 02 4A 4D 0D 01
   4B 0A 02 4C 06 01 06 3C 72 6F 6F 74 3E 09 01 05
   09 02 4F 04 01 07 70 61 63 6B 61 67 65 09 02 51
   52 02 0D 53 74 72 69 6E 67 42 75 69 6C 64 65 72
   0A 02 4F 04 08 07 54 00 FFFFFF81 FFFFFF80 FFFFFF84 00 55 01 04 63
   6F 70 79 14 02 21 56 08 08 57 14 53 FFFFFF90 FFFFFF80 FFFFFFC0 00
   16 08 07 58 00 FFFFFF91 FFFFFF80 FFFFFF84 00 59 01 0E 63 6F 70 79
   24 64 65 66 61 75 6C 74 24 31 15 01 5A 2A 02 16
   5B 2B 01 5C 10 02 5D 62 0D 01 5E 0A 02 5F 60 01
   09 75 6E 63 68 65 63 6B 65 64 0A 02 61 04 01 0A
   61 6E 6E 6F 74 61 74 69 6F 6E 09 02 63 5E 02 11
   75 6E 63 68 65 63 6B 65 64 56 61 72 69 61 6E 63
   65 08 08 65 00 FFFFFF84 FFFFFF80 FFFFFF80 FFFFFF84 20 66 01 0D 70 72 6F
   64 75 63 74 50 72 65 66 69 78 15 01 67 10 02 68
   6D 0D 01 69 0A 02 6A 6B 01 04 6C 61 6E 67 0A 01
   6C 01 04 6A 61 76 61 09 02 6E 69 02 06 53 74 72
   69 6E 67 08 08 70 00 FFFFFF84 FFFFFF80 FFFFFF80 FFFFFF84 20 71 01 0C 70
   72 6F 64 75 63 74 41 72 69 74 79 15 01 33 08 08
   73 00 FFFFFF84 FFFFFF80 FFFFFF80 FFFFFF84 20 74 01 0E 70 72 6F 64 75 63
   74 45 6C 65 6D 65 6E 74 14 02 2D 75 08 07 76 72
   FFFFFF81 FFFFFF80 FFFFFFC0 00 33 01 03 78 24 31 28 02 00 78 10 02
   0D 79 09 02 7A 04 02 0C 73 65 72 69 61 6C 69 7A
   61 62 6C 65 07 07 7C 02 FFFFFF81 FFFFFF80 FFFFFF88 02 7D 01 05 47
   72 6F 75 70 10 02 09 7E 06 08 01 02 FFFFFF84 FFFFFF81 FFFFFF80 FFFFFF88
   02 7F 13 06 7E FFFFFF81 00 FFFFFF81 03 0C 10 03 68 FFFFFF81 01 09
   03 FFFFFF81 02 69 02 06 4F 62 6A 65 63 74 10 05 0D FFFFFF81
   04 16 21 09 03 FFFFFF81 05 04 02 09 46 75 6E 63 74 69
   6F 6E 31 08 06 1F 7E FFFFFF84 00 FFFFFF81 07 14 01 7D 08 09
   FFFFFF81 09 7E FFFFFF81 FFFFFF80 FFFFFF84 40 FFFFFF81 0A 01 05 61 70 70 6C 79
   14 03 21 FFFFFF81 0B 08 06 14 FFFFFF81 08 FFFFFFC0 00 16 08 09 FFFFFF81
   0D 7E FFFFFF81 FFFFFF80 FFFFFF84 40 FFFFFF81 0E 01 07 75 6E 61 70 70 6C
   79 14 04 FFFFFF81 0F FFFFFF81 12 10 04 0D FFFFFF81 10 16 09 03 FFFFFF81
   11 04 02 04 53 6F 6D 65 08 07 FFFFFF81 13 FFFFFF81 0C FFFFFFC0 00
   21 01 03 78 24 30 
  minor version: 0
  major version: 49
  Constant pool:
Asciz	SourceFile;
Asciz	Group.scala;
Asciz	nodes;
Asciz	Lscala/collection/Seq;;
Asciz	Lscala/collection/Seq<Lscala/xml/Node;>;;
Asciz	Signature;
Asciz	<init>;
Asciz	(Lscala/collection/Seq;)V;
Asciz	Code;
Asciz	LineNumberTable;
Asciz	scala/xml/Group;
class	scala/xml/Group
NameAndType	nodes:Lscala/collection/Seq;
Field	scala/xml/Group.nodes:Lscala/collection/Seq;
Asciz	scala/xml/Node;
class	scala/xml/Node
Asciz	()V;
NameAndType	"<init>":()V
Method	scala/xml/Node."<init>":()V
Asciz	scala/Product$class;
class	scala/Product$class
Asciz	$init$;
Asciz	(Lscala/Product;)V;
NameAndType	$init$:(Lscala/Product;)V
Method	scala/Product$class.$init$:(Lscala/Product;)V
Asciz	this;
Asciz	Lscala/xml/Group;;
Asciz	LocalVariableTable;
Asciz	(Lscala/collection/Seq<Lscala/xml/Node;>;)V;
Asciz	label;
Asciz	()Ljava/lang/String;;
Asciz	()Lscala/runtime/Nothing$;;
NameAndType	label:()Lscala/runtime/Nothing$;
Method	scala/xml/Group.label:()Lscala/runtime/Nothing$;
Asciz	attributes;
Asciz	()Lscala/xml/MetaData;;
NameAndType	attributes:()Lscala/runtime/Nothing$;
Method	scala/xml/Group.attributes:()Lscala/runtime/Nothing$;
Asciz	namespace;
NameAndType	namespace:()Lscala/runtime/Nothing$;
Method	scala/xml/Group.namespace:()Lscala/runtime/Nothing$;
Asciz	child;
Asciz	()Lscala/collection/Seq;;
NameAndType	child:()Lscala/runtime/Nothing$;
Method	scala/xml/Group.child:()Lscala/runtime/Nothing$;
Asciz	productElement;
Asciz	(I)Ljava/lang/Object;;
NameAndType	nodes:()Lscala/collection/Seq;
Method	scala/xml/Group.nodes:()Lscala/collection/Seq;
Asciz	scala/MatchError;
class	scala/MatchError
Asciz	scala/runtime/BoxesRunTime;
class	scala/runtime/BoxesRunTime
Asciz	boxToInteger;
Asciz	(I)Ljava/lang/Integer;;
NameAndType	boxToInteger:(I)Ljava/lang/Integer;
Method	scala/runtime/BoxesRunTime.boxToInteger:(I)Ljava/lang/Integer;
Asciz	java/lang/Object;
class	java/lang/Object
Asciz	toString;
NameAndType	toString:()Ljava/lang/String;
Method	java/lang/Object.toString:()Ljava/lang/String;
Asciz	(Ljava/lang/String;)V;
NameAndType	"<init>":(Ljava/lang/String;)V
Method	scala/MatchError."<init>":(Ljava/lang/String;)V
Asciz	java/lang/IndexOutOfBoundsException;
class	java/lang/IndexOutOfBoundsException
Method	java/lang/IndexOutOfBoundsException."<init>":(Ljava/lang/String;)V
Asciz	productArity;
Asciz	()I;
Asciz	productPrefix;
Asciz	Group;
String	Group
Asciz	copy;
Asciz	(Lscala/collection/Seq;)Lscala/xml/Group;;
NameAndType	"<init>":(Lscala/collection/Seq;)V
Method	scala/xml/Group."<init>":(Lscala/collection/Seq;)V
Asciz	buildString;
Asciz	(Lscala/collection/mutable/StringBuilder;)Lscala/runtime/Nothing$;;
Asciz	java/lang/UnsupportedOperationException;
class	java/lang/UnsupportedOperationException
Asciz	class Group does not support method toString(StringBuilder);
String	class Group does not support method toString(StringBuilder)
Method	java/lang/UnsupportedOperationException."<init>":(Ljava/lang/String;)V
Asciz	sb;
Asciz	Lscala/collection/mutable/StringBuilder;;
Asciz	class Group does not support method 'child';
String	class Group does not support method 'child'
Asciz	class Group does not support method 'namespace';
String	class Group does not support method 'namespace'
Asciz	class Group does not support method 'attributes';
String	class Group does not support method 'attributes'
Asciz	class Group does not support method 'label';
String	class Group does not support method 'label'
Asciz	hashCode;
Asciz	scala/collection/SeqLike;
class	scala/collection/SeqLike
NameAndType	hashCode:()I
InterfaceMethod	scala/collection/SeqLike.hashCode:()I
Asciz	equals;
Asciz	(Ljava/lang/Object;)Z;
Asciz	length;
NameAndType	length:()I
Method	scala/xml/Group.length:()I
Asciz	scala/collection/IterableLike;
class	scala/collection/IterableLike
Asciz	sameElements;
Asciz	(Lscala/collection/Iterable;)Z;
NameAndType	sameElements:(Lscala/collection/Iterable;)Z
InterfaceMethod	scala/collection/IterableLike.sameElements:(Lscala/collection/Iterable;)Z
Asciz	apply;
Asciz	(I)Lscala/xml/Node;;
NameAndType	apply:(I)Lscala/xml/Node;
Method	scala/xml/Group.apply:(I)Lscala/xml/Node;
NameAndType	equals:(Ljava/lang/Object;)Z
Method	java/lang/Object.equals:(Ljava/lang/Object;)Z
Asciz	scala/collection/Seq;
class	scala/collection/Seq
Asciz	java/lang/String;
class	java/lang/String
Asciz	text;
NameAndType	text:()Ljava/lang/String;
Method	scala/xml/Group.text:()Ljava/lang/String;
Asciz	x;
Asciz	Ljava/lang/Object;;
Asciz	temp2;
Asciz	temp4;
Asciz	Lscala/xml/Node;;
Asciz	temp5;
Asciz	temp6;
Asciz	Ljava/lang/String;;
Asciz	theSeq;
Asciz	()Lscala/collection/Seq<Lscala/xml/Node;>;;
Asciz	copy$default$1;
Asciz	productElements;
Asciz	()Lscala/collection/Iterator;;
Asciz	(Lscala/Product;)Lscala/collection/Iterator;;
NameAndType	productElements:(Lscala/Product;)Lscala/collection/Iterator;
Method	scala/Product$class.productElements:(Lscala/Product;)Lscala/collection/Iterator;
Asciz	productIterator;
NameAndType	productIterator:(Lscala/Product;)Lscala/collection/Iterator;
Method	scala/Product$class.productIterator:(Lscala/Product;)Lscala/collection/Iterator;
Asciz	ScalaSig;
Asciz	scala/ScalaObject;
class	scala/ScalaObject
Asciz	scala/Product;
class	scala/Product
Asciz	java/io/Serializable;
class	java/io/Serializable

{
private final scala.collection.Seq nodes;
  Signature: Lscala/collection/Seq;
  Signature: length = 0x2
   00 05 

public scala.xml.Group(scala.collection.Seq);
  Signature: (Lscala/collection/Seq;)V
  Code:
   Stack=2, Locals=2, Args_size=2
	aload_0
	aload_1
	putfield	Field nodes:Lscala/collection/Seq;
	aload_0
	invokespecial	Method scala/xml/Node."<init>":()V
	aload_0
	invokestatic	Method scala/Product$class.$init$:(Lscala/Product;)V
	return
  Labels:
  LocalVariableTable: 
   Start  Length  Slot  Name   Signature
   0      14      0    this       Lscala/xml/Group;
   0      14      1    nodes       Lscala/collection/Seq;

  Signature: length = 0x2
   00 1D 

public final java.lang.String label();
  Signature: ()Ljava/lang/String;
  Code:
   Stack=1, Locals=1, Args_size=1
	aload_0
	invokevirtual	Method label:()Lscala/runtime/Nothing$;
	athrow
  Labels:

public final scala.xml.MetaData attributes();
  Signature: ()Lscala/xml/MetaData;
  Code:
   Stack=1, Locals=1, Args_size=1
	aload_0
	invokevirtual	Method attributes:()Lscala/runtime/Nothing$;
	athrow
  Labels:

public final java.lang.String namespace();
  Signature: ()Ljava/lang/String;
  Code:
   Stack=1, Locals=1, Args_size=1
	aload_0
	invokevirtual	Method namespace:()Lscala/runtime/Nothing$;
	athrow
  Labels:

public final scala.collection.Seq child();
  Signature: ()Lscala/collection/Seq;
  Code:
   Stack=1, Locals=1, Args_size=1
	aload_0
	invokevirtual	Method child:()Lscala/runtime/Nothing$;
	athrow
  Labels:

public java.lang.Object productElement(int);
  Signature: (I)Ljava/lang/Object;
  Code:
   Stack=3, Locals=2, Args_size=2
	iload_1
	iconst_0
	if_icmpne	l1 // iconst_1
	iconst_1
	ifeq	l2 // new
	aload_0
	invokevirtual	Method nodes:()Lscala/collection/Seq;
	areturn
l2	new	class scala/MatchError
	dup
	iload_1
	invokestatic	Method scala/runtime/BoxesRunTime.boxToInteger:(I)Ljava/lang/Integer;
	invokevirtual	Method java/lang/Object.toString:()Ljava/lang/String;
	invokespecial	Method scala/MatchError."<init>":(Ljava/lang/String;)V
	athrow
l1	iconst_1
	ifeq	l3 // new
	new	class java/lang/IndexOutOfBoundsException
	dup
	iload_1
	invokestatic	Method scala/runtime/BoxesRunTime.boxToInteger:(I)Ljava/lang/Integer;
	invokevirtual	Method java/lang/Object.toString:()Ljava/lang/String;
	invokespecial	Method java/lang/IndexOutOfBoundsException."<init>":(Ljava/lang/String;)V
	athrow
l3	new	class scala/MatchError
	dup
	iload_1
	invokestatic	Method scala/runtime/BoxesRunTime.boxToInteger:(I)Ljava/lang/Integer;
	invokevirtual	Method java/lang/Object.toString:()Ljava/lang/String;
	invokespecial	Method scala/MatchError."<init>":(Ljava/lang/String;)V
	athrow
  Labels:
   	l2 = 14 // new
   	l1 = 29 // iconst_1
   	l3 = 48 // new

public int productArity();
  Signature: ()I
  Code:
   Stack=1, Locals=1, Args_size=1
	iconst_1
	ireturn
  Labels:

public java.lang.String productPrefix();
  Signature: ()Ljava/lang/String;
  Code:
   Stack=1, Locals=1, Args_size=1
	ldc	String Group
	areturn
  Labels:

public scala.xml.Group copy(scala.collection.Seq);
  Signature: (Lscala/collection/Seq;)Lscala/xml/Group;
  Code:
   Stack=3, Locals=2, Args_size=2
	new	class scala/xml/Group
	dup
	aload_1
	invokespecial	Method "<init>":(Lscala/collection/Seq;)V
	areturn
  Labels:
  LocalVariableTable: 
   Start  Length  Slot  Name   Signature
   0      9      0    this       Lscala/xml/Group;
   0      9      1    nodes       Lscala/collection/Seq;


public scala.runtime.Nothing$ buildString(scala.collection.mutable.StringBuilder);
  Signature: (Lscala/collection/mutable/StringBuilder;)Lscala/runtime/Nothing$;
  Code:
   Stack=3, Locals=2, Args_size=2
	new	class java/lang/UnsupportedOperationException
	dup
	ldc	String class Group does not support method toString(StringBuilder)
	invokespecial	Method java/lang/UnsupportedOperationException."<init>":(Ljava/lang/String;)V
	athrow
  Labels:
  LocalVariableTable: 
   Start  Length  Slot  Name   Signature
   0      10      0    this       Lscala/xml/Group;
   0      10      1    sb       Lscala/collection/mutable/StringBuilder;


public final scala.runtime.Nothing$ child();
  Signature: ()Lscala/runtime/Nothing$;
  Code:
   Stack=3, Locals=1, Args_size=1
	new	class java/lang/UnsupportedOperationException
	dup
	ldc	String class Group does not support method 'child'
	invokespecial	Method java/lang/UnsupportedOperationException."<init>":(Ljava/lang/String;)V
	athrow
  Labels:

public final scala.runtime.Nothing$ namespace();
  Signature: ()Lscala/runtime/Nothing$;
  Code:
   Stack=3, Locals=1, Args_size=1
	new	class java/lang/UnsupportedOperationException
	dup
	ldc	String class Group does not support method 'namespace'
	invokespecial	Method java/lang/UnsupportedOperationException."<init>":(Ljava/lang/String;)V
	athrow
  Labels:

public final scala.runtime.Nothing$ attributes();
  Signature: ()Lscala/runtime/Nothing$;
  Code:
   Stack=3, Locals=1, Args_size=1
	new	class java/lang/UnsupportedOperationException
	dup
	ldc	String class Group does not support method 'attributes'
	invokespecial	Method java/lang/UnsupportedOperationException."<init>":(Ljava/lang/String;)V
	athrow
  Labels:

public final scala.runtime.Nothing$ label();
  Signature: ()Lscala/runtime/Nothing$;
  Code:
   Stack=3, Locals=1, Args_size=1
	new	class java/lang/UnsupportedOperationException
	dup
	ldc	String class Group does not support method 'label'
	invokespecial	Method java/lang/UnsupportedOperationException."<init>":(Ljava/lang/String;)V
	athrow
  Labels:

public int hashCode();
  Signature: ()I
  Code:
   Stack=1, Locals=1, Args_size=1
	aload_0
	invokevirtual	Method nodes:()Lscala/collection/Seq;
	invokeinterface	InterfaceMethod scala/collection/SeqLike.hashCode:()I
	ireturn
  Labels:

public boolean equals(java.lang.Object);
  Signature: (Ljava/lang/Object;)Z
  Code:
   Stack=3, Locals=7, Args_size=2
	aload_1
	instanceof	class scala/xml/Group
	ifeq	l1 // aload_1
	aload_1
	checkcast	class scala/xml/Group
	astore_2
	iconst_1
	ifeq	l2 // new
	aload_0
	invokevirtual	Method length:()I
	aload_2
	invokevirtual	Method length:()I
	if_icmpne	l3 // iconst_0
	aload_0
	aload_2
	invokeinterface	InterfaceMethod scala/collection/IterableLike.sameElements:(Lscala/collection/Iterable;)Z
	ifeq	l3 // iconst_0
	iconst_1
	goto	l4 // ireturn
l3	iconst_0
	goto	l4 // ireturn
l2	new	class scala/MatchError
	dup
	aload_1
	invokevirtual	Method java/lang/Object.toString:()Ljava/lang/String;
	invokespecial	Method scala/MatchError."<init>":(Ljava/lang/String;)V
	athrow
l1	aload_1
	instanceof	class scala/xml/Node
	ifeq	l5 // aload_1
	aload_1
	checkcast	class scala/xml/Node
	astore_3
	iconst_1
	ifeq	l6 // new
	aload_0
	invokevirtual	Method length:()I
	iconst_1
	if_icmpne	l7 // iconst_0
	aload_3
	aload_0
	iconst_0
	invokevirtual	Method apply:(I)Lscala/xml/Node;
	astore	4
	dup
	ifnonnull	l8 // aload
	pop
	aload	4
	ifnull	l9 // iconst_1
	goto	l7 // iconst_0
l8	aload	4
	invokevirtual	Method java/lang/Object.equals:(Ljava/lang/Object;)Z
	ifeq	l7 // iconst_0
l9	iconst_1
	goto	l4 // ireturn
l7	iconst_0
	goto	l4 // ireturn
l6	new	class scala/MatchError
	dup
	aload_1
	invokevirtual	Method java/lang/Object.toString:()Ljava/lang/String;
	invokespecial	Method scala/MatchError."<init>":(Ljava/lang/String;)V
	athrow
l5	aload_1
	instanceof	class scala/collection/Seq
	ifeq	l10 // aload_1
	aload_1
	checkcast	class scala/collection/Seq
	astore	5
	iconst_1
	ifeq	l11 // new
	aload_0
	aload	5
	invokeinterface	InterfaceMethod scala/collection/IterableLike.sameElements:(Lscala/collection/Iterable;)Z
	goto	l4 // ireturn
l11	new	class scala/MatchError
	dup
	aload_1
	invokevirtual	Method java/lang/Object.toString:()Ljava/lang/String;
	invokespecial	Method scala/MatchError."<init>":(Ljava/lang/String;)V
	athrow
l10	aload_1
	instanceof	class java/lang/String
	ifeq	l12 // iconst_1
	aload_1
	checkcast	class java/lang/String
	astore	6
	iconst_1
	ifeq	l13 // new
	aload_0
	invokevirtual	Method text:()Ljava/lang/String;
	dup
	ifnonnull	l14 // aload
	pop
	aload	6
	ifnull	l15 // iconst_1
	goto	l16 // iconst_0
l14	aload	6
	invokevirtual	Method java/lang/Object.equals:(Ljava/lang/Object;)Z
	ifeq	l16 // iconst_0
l15	iconst_1
	goto	l4 // ireturn
l16	iconst_0
	goto	l4 // ireturn
l13	new	class scala/MatchError
	dup
	aload_1
	invokevirtual	Method java/lang/Object.toString:()Ljava/lang/String;
	invokespecial	Method scala/MatchError."<init>":(Ljava/lang/String;)V
	athrow
l12	iconst_1
	ifeq	l17 // new
	iconst_0
l4	ireturn
l17	new	class scala/MatchError
	dup
	aload_1
	invokevirtual	Method java/lang/Object.toString:()Ljava/lang/String;
	invokespecial	Method scala/MatchError."<init>":(Ljava/lang/String;)V
	athrow
  Labels:
   	l3 = 41 // iconst_0
   	l2 = 45 // new
   	l1 = 57 // aload_1
   	l8 = 102 // aload
   	l9 = 110 // iconst_1
   	l7 = 114 // iconst_0
   	l6 = 118 // new
   	l5 = 130 // aload_1
   	l11 = 158 // new
   	l10 = 170 // aload_1
   	l14 = 204 // aload
   	l15 = 212 // iconst_1
   	l16 = 216 // iconst_0
   	l13 = 220 // new
   	l12 = 232 // iconst_1
   	l4 = 237 // ireturn
   	l17 = 238 // new
  LocalVariableTable: 
   Start  Length  Slot  Name   Signature
   0      250      0    this       Lscala/xml/Group;
   0      250      1    x       Ljava/lang/Object;
   12      45      2    temp2       Lscala/xml/Group;
   69      61      3    temp4       Lscala/xml/Node;
   143      27      5    temp5       Lscala/collection/Seq;
   183      49      6    temp6       Ljava/lang/String;


public scala.collection.Seq theSeq();
  Signature: ()Lscala/collection/Seq;
  Code:
   Stack=1, Locals=1, Args_size=1
	aload_0
	invokevirtual	Method nodes:()Lscala/collection/Seq;
	areturn
  Labels:
  Signature: length = 0x2
   00 FFFFFF85 

public scala.collection.Seq nodes();
  Signature: ()Lscala/collection/Seq;
  Code:
   Stack=1, Locals=1, Args_size=1
	aload_0
	getfield	Field nodes:Lscala/collection/Seq;
	areturn
  Labels:
  Signature: length = 0x2
   00 FFFFFF85 

public scala.collection.Seq copy$default$1();
  Signature: ()Lscala/collection/Seq;
  Code:
   Stack=1, Locals=1, Args_size=1
	aload_0
	invokevirtual	Method nodes:()Lscala/collection/Seq;
	areturn
  Labels:

public scala.collection.Iterator productElements();
  Signature: ()Lscala/collection/Iterator;
  Code:
   Stack=1, Locals=1, Args_size=1
	aload_0
	invokestatic	Method scala/Product$class.productElements:(Lscala/Product;)Lscala/collection/Iterator;
	areturn
  Labels:

public scala.collection.Iterator productIterator();
  Signature: ()Lscala/collection/Iterator;
  Code:
   Stack=1, Locals=1, Args_size=1
	aload_0
	invokestatic	Method scala/Product$class.productIterator:(Lscala/Product;)Lscala/collection/Iterator;
	areturn
  Labels:

}

