Compiled from "HasKeyValue.scala"
public class scala.xml.HasKeyValue extends java.lang.Object implements scala.ScalaObject
  SourceFile: "HasKeyValue.scala"
  ScalaSig: length = 0x151
   05 00 3D 06 08 01 02 FFFFFF84 FFFFFF80 FFFFFF80 FFFFFF80 00 07 02 0B 48
   61 73 4B 65 79 56 61 6C 75 65 0A 02 03 04 01 03
   78 6D 6C 0A 01 05 01 05 73 63 61 6C 61 03 00 13
   03 00 08 10 10 02 09 0E 0D 01 0A 0A 02 0B 0C 01
   04 6C 61 6E 67 0A 01 0D 01 04 6A 61 76 61 09 02
   0F 0A 02 06 4F 62 6A 65 63 74 10 02 11 12 0D 01
   04 09 02 13 04 02 0B 53 63 61 6C 61 4F 62 6A 65
   63 74 08 08 15 00 FFFFFF82 FFFFFF80 FFFFFFA0 FFFFFF80 04 16 01 03 6B 65
   79 10 02 17 1A 0E 02 11 18 09 02 19 04 01 06 50
   72 65 64 65 66 09 02 1B 1C 02 06 53 74 72 69 6E
   67 0A 02 19 04 08 05 1E 00 FFFFFF84 00 1F 01 06 3C 69
   6E 69 74 3E 14 02 20 22 10 02 21 00 0D 01 02 08
   05 15 1D FFFFFFC0 00 16 08 05 24 00 FFFFFF84 00 25 01 0A 75
   6E 61 70 70 6C 79 53 65 71 14 02 26 38 10 03 11
   27 29 09 02 28 04 02 06 4F 70 74 69 6F 6E 10 03
   2A 32 35 0E 02 2B 30 0E 02 2C 2F 0D 01 2D 0A 02
   2E 06 01 06 3C 72 6F 6F 74 3E 09 01 05 09 02 31
   04 01 07 70 61 63 6B 61 67 65 09 02 33 34 02 03
   53 65 71 0A 02 31 04 10 02 21 36 09 02 37 02 02
   04 4E 6F 64 65 08 05 39 23 FFFFFFC0 00 3A 01 01 78 10
   02 21 3B 09 02 3C 02 02 08 4D 65 74 61 44 61 74
   61 
  minor version: 0
  major version: 49
  Constant pool:
const #1 = Asciz	SourceFile;
const #2 = Asciz	HasKeyValue.scala;
const #3 = Asciz	key;
const #4 = Asciz	Ljava/lang/String;;
const #5 = Asciz	<init>;
const #6 = Asciz	(Ljava/lang/String;)V;
const #7 = Asciz	Code;
const #8 = Asciz	LineNumberTable;
const #9 = Asciz	scala/xml/HasKeyValue;
const #10 = class	#9;	//  scala/xml/HasKeyValue
const #11 = NameAndType	#3:#4;//  key:Ljava/lang/String;
const #12 = Field	#10.#11;	//  scala/xml/HasKeyValue.key:Ljava/lang/String;
const #13 = Asciz	java/lang/Object;
const #14 = class	#13;	//  java/lang/Object
const #15 = Asciz	()V;
const #16 = NameAndType	#5:#15;//  "<init>":()V
const #17 = Method	#14.#16;	//  java/lang/Object."<init>":()V
const #18 = Asciz	this;
const #19 = Asciz	Lscala/xml/HasKeyValue;;
const #20 = Asciz	LocalVariableTable;
const #21 = Asciz	unapplySeq;
const #22 = Asciz	(Lscala/xml/MetaData;)Lscala/Option;;
const #23 = Asciz	scala/xml/MetaData;
const #24 = class	#23;	//  scala/xml/MetaData
const #25 = Asciz	get;
const #26 = Asciz	(Ljava/lang/String;)Lscala/Option;;
const #27 = NameAndType	#25:#26;//  get:(Ljava/lang/String;)Lscala/Option;
const #28 = Method	#24.#27;	//  scala/xml/MetaData.get:(Ljava/lang/String;)Lscala/Option;
const #29 = Asciz	x;
const #30 = Asciz	Lscala/xml/MetaData;;
const #31 = Asciz	(Lscala/xml/MetaData;)Lscala/Option<Lscala/collection/Sequence<Lscala/xml/Node;>;>;;
const #32 = Asciz	Signature;
const #33 = Asciz	ScalaSig;
const #34 = Asciz	scala/ScalaObject;
const #35 = class	#34;	//  scala/ScalaObject

{
public scala.xml.HasKeyValue(java.lang.String);
  Code:
   Stack=2, Locals=2, Args_size=2
   0:	aload_0
   1:	aload_1
   2:	putfield	#12; //Field key:Ljava/lang/String;
   5:	aload_0
   6:	invokespecial	#17; //Method java/lang/Object."<init>":()V
   9:	return
  LineNumberTable: 
   line 23: 0

  LocalVariableTable: 
   Start  Length  Slot  Name   Signature
   0      10      0    this       Lscala/xml/HasKeyValue;
   0      10      1    key       Ljava/lang/String;


public scala.Option unapplySeq(scala.xml.MetaData);
  Code:
   Stack=2, Locals=2, Args_size=2
   0:	aload_1
   1:	aload_0
   2:	getfield	#12; //Field key:Ljava/lang/String;
   5:	invokevirtual	#28; //Method scala/xml/MetaData.get:(Ljava/lang/String;)Lscala/Option;
   8:	areturn
  LineNumberTable: 
   line 24: 0

  LocalVariableTable: 
   Start  Length  Slot  Name   Signature
   0      9      0    this       Lscala/xml/HasKeyValue;
   0      9      1    x       Lscala/xml/MetaData;

  Signature: length = 0x2
   00 1F 

}

