Compiled from "MalformedAttributeException.scala"
public class scala.xml.MalformedAttributeException extends java.lang.RuntimeException implements scala.ScalaObject,scala.Product,java.io.Serializable
  SourceFile: "MalformedAttributeException.scala"
  ScalaSig: length = 0x36A
   05 00 7C 06 08 01 02 FFFFFF84 FFFFFF80 FFFFFF80 FFFFFF80 40 07 02 1B 4D
   61 6C 66 6F 72 6D 65 64 41 74 74 72 69 62 75 74
   65 45 78 63 65 70 74 69 6F 6E 0A 02 03 04 01 03
   78 6D 6C 0A 01 05 01 05 73 63 61 6C 61 03 00 13
   04 00 08 10 14 10 02 09 0E 0D 01 0A 0A 02 0B 0C
   01 04 6C 61 6E 67 0A 01 0D 01 04 6A 61 76 61 09
   02 0F 0A 02 10 52 75 6E 74 69 6D 65 45 78 63 65
   70 74 69 6F 6E 10 02 11 12 0D 01 04 09 02 13 04
   02 0B 53 63 61 6C 61 4F 62 6A 65 63 74 10 02 11
   15 09 02 16 04 02 07 50 72 6F 64 75 63 74 08 08
   18 00 FFFFFF82 FFFFFFCA FFFFFF80 FFFFFF84 00 19 01 03 6D 73 67 15 01 1A
   10 02 1B 1E 0E 02 11 1C 09 02 1D 04 01 06 50 72
   65 64 65 66 09 02 1F 20 02 06 53 74 72 69 6E 67
   0A 02 1D 04 08 08 22 00 FFFFFF82 FFFFFF88 FFFFFFA0 FFFFFF80 04 1A 01 04
   6D 73 67 20 08 05 24 00 FFFFFF84 00 25 01 06 3C 69 6E
   69 74 3E 14 02 26 28 10 02 27 00 0D 01 02 08 05
   18 23 FFFFFFC0 00 1A 08 07 2A 00 FFFFFF81 FFFFFF80 FFFFFF84 00 2B 01 04
   63 6F 70 79 14 02 26 2C 08 07 18 29 FFFFFF90 FFFFFF80 FFFFFFC0 00
   1A 08 07 2E 00 FFFFFF91 FFFFFF80 FFFFFF84 00 2F 01 0E 63 6F 70 79
   24 64 65 66 61 75 6C 74 24 31 15 01 30 2A 02 1A
   31 2B 01 32 10 02 33 38 0D 01 34 0A 02 35 36 01
   09 75 6E 63 68 65 63 6B 65 64 0A 02 37 04 01 0A
   61 6E 6E 6F 74 61 74 69 6F 6E 09 02 39 34 02 11
   75 6E 63 68 65 63 6B 65 64 56 61 72 69 61 6E 63
   65 08 08 3B 00 FFFFFF84 FFFFFF80 FFFFFF80 FFFFFF84 20 3C 01 08 68 61 73
   68 43 6F 64 65 14 01 3D 10 02 11 3E 09 02 3F 04
   02 03 49 6E 74 08 08 41 00 FFFFFF84 FFFFFF80 FFFFFF80 FFFFFF84 20 42 01
   06 65 71 75 61 6C 73 14 02 43 46 10 02 11 44 09
   02 45 04 02 07 42 6F 6F 6C 65 61 6E 08 07 47 40
   FFFFFF81 FFFFFF80 FFFFFFC0 00 48 01 03 78 24 31 10 02 11 49 09 02
   4A 04 02 03 41 6E 79 08 08 4C 00 FFFFFF84 FFFFFF80 FFFFFF80 FFFFFF84 20
   4D 01 0D 70 72 6F 64 75 63 74 50 72 65 66 69 78
   15 01 4E 10 02 09 4F 09 02 1F 0A 08 08 51 00 FFFFFF84
   FFFFFF80 FFFFFF80 FFFFFF84 20 52 01 0C 70 72 6F 64 75 63 74 41 72
   69 74 79 15 01 3D 08 08 54 00 FFFFFF84 FFFFFF80 FFFFFF80 FFFFFF84 20 55
   01 0E 70 72 6F 64 75 63 74 45 6C 65 6D 65 6E 74
   14 02 48 56 08 07 47 53 FFFFFF81 FFFFFF80 FFFFFFC0 00 3D 08 08 58
   00 FFFFFF84 FFFFFF80 FFFFFF80 FFFFFF84 20 59 01 12 70 72 6F 64 75 63 74
   45 6C 65 6D 65 6E 74 4E 61 6D 65 14 02 4E 5A 08
   07 47 57 FFFFFF81 FFFFFF80 FFFFFFC0 00 3D 08 08 5C 00 FFFFFF84 FFFFFF80 FFFFFF80 FFFFFF84
   20 5D 01 08 63 61 6E 45 71 75 61 6C 14 02 43 5E
   08 07 47 5B FFFFFF81 FFFFFF80 FFFFFFC0 00 48 28 02 00 60 10 02 11
   61 09 02 62 04 02 0C 73 65 72 69 61 6C 69 7A 61
   62 6C 65 07 07 64 02 FFFFFF81 FFFFFF80 FFFFFF88 02 65 01 1B 4D 61
   6C 66 6F 72 6D 65 64 41 74 74 72 69 62 75 74 65
   45 78 63 65 70 74 69 6F 6E 10 02 27 66 06 08 01
   02 FFFFFF84 FFFFFF81 FFFFFF80 FFFFFF88 02 67 13 04 66 68 6B 10 10 02 09
   69 09 02 6A 0A 02 06 4F 62 6A 65 63 74 10 04 11
   6C 1A 26 09 02 6D 04 02 09 46 75 6E 63 74 69 6F
   6E 31 08 05 24 66 FFFFFF84 00 6F 14 01 65 08 07 71 66
   FFFFFF81 FFFFFF80 FFFFFF84 40 72 01 05 61 70 70 6C 79 14 02 26 73
   08 05 18 70 FFFFFFC0 00 1A 08 07 75 66 FFFFFF81 FFFFFF80 FFFFFF84 40 76
   01 07 75 6E 61 70 70 6C 79 14 02 77 7A 10 03 11
   78 1A 09 02 79 04 02 06 4F 70 74 69 6F 6E 08 05
   7B 74 FFFFFFC0 00 26 01 03 78 24 30 
  minor version: 0
  major version: 49
  Constant pool:
Asciz	SourceFile;
Asciz	MalformedAttributeException.scala;
Asciz	andThen;
Asciz	(Lscala/Function1;)Lscala/Function1;;
Asciz	Code;
Asciz	scala/xml/MalformedAttributeException$;
class	scala/xml/MalformedAttributeException$
Asciz	MODULE$;
Asciz	Lscala/xml/MalformedAttributeException$;;
NameAndType	MODULE$:Lscala/xml/MalformedAttributeException$;
Field	scala/xml/MalformedAttributeException$.MODULE$:Lscala/xml/MalformedAttributeException$;
NameAndType	andThen:(Lscala/Function1;)Lscala/Function1;
Method	scala/xml/MalformedAttributeException$.andThen:(Lscala/Function1;)Lscala/Function1;
Asciz	compose;
NameAndType	compose:(Lscala/Function1;)Lscala/Function1;
Method	scala/xml/MalformedAttributeException$.compose:(Lscala/Function1;)Lscala/Function1;
Asciz	msg;
Asciz	Ljava/lang/String;;
Asciz	productIterator;
Asciz	()Lscala/collection/Iterator;;
Asciz	LineNumberTable;
Asciz	scala/Product$class;
class	scala/Product$class
Asciz	(Lscala/Product;)Lscala/collection/Iterator;;
NameAndType	productIterator:(Lscala/Product;)Lscala/collection/Iterator;
Method	scala/Product$class.productIterator:(Lscala/Product;)Lscala/collection/Iterator;
Asciz	productElements;
NameAndType	productElements:(Lscala/Product;)Lscala/collection/Iterator;
Method	scala/Product$class.productElements:(Lscala/Product;)Lscala/collection/Iterator;
Asciz	Deprecated;
Asciz	copy$default$1;
Asciz	()Ljava/lang/String;;
Asciz	scala/xml/MalformedAttributeException;
class	scala/xml/MalformedAttributeException
NameAndType	msg:()Ljava/lang/String;
Method	scala/xml/MalformedAttributeException.msg:()Ljava/lang/String;
NameAndType	msg:Ljava/lang/String;
Field	scala/xml/MalformedAttributeException.msg:Ljava/lang/String;
Asciz	copy;
Asciz	(Ljava/lang/String;)Lscala/xml/MalformedAttributeException;;
Asciz	<init>;
Asciz	(Ljava/lang/String;)V;
NameAndType	"<init>":(Ljava/lang/String;)V
Method	scala/xml/MalformedAttributeException."<init>":(Ljava/lang/String;)V
Asciz	this;
Asciz	Lscala/xml/MalformedAttributeException;;
Asciz	LocalVariableTable;
Asciz	hashCode;
Asciz	()I;
Asciz	scala/runtime/ScalaRunTime$;
class	scala/runtime/ScalaRunTime$
Asciz	Lscala/runtime/ScalaRunTime$;;
NameAndType	MODULE$:Lscala/runtime/ScalaRunTime$;
Field	scala/runtime/ScalaRunTime$.MODULE$:Lscala/runtime/ScalaRunTime$;
Asciz	_hashCode;
Asciz	(Lscala/Product;)I;
NameAndType	_hashCode:(Lscala/Product;)I
Method	scala/runtime/ScalaRunTime$._hashCode:(Lscala/Product;)I
Asciz	equals;
Asciz	(Ljava/lang/Object;)Z;
Asciz	gd1$1;
Asciz	(Ljava/lang/String;)Z;
NameAndType	gd1$1:(Ljava/lang/String;)Z
Method	scala/xml/MalformedAttributeException.gd1$1:(Ljava/lang/String;)Z
Asciz	scala/Equals;
class	scala/Equals
Asciz	canEqual;
NameAndType	canEqual:(Ljava/lang/Object;)Z
InterfaceMethod	scala/Equals.canEqual:(Ljava/lang/Object;)Z
Asciz	temp1;
Asciz	Ljava/lang/Object;;
Asciz	temp2;
Asciz	temp3;
Asciz	msg$1;
Asciz	productPrefix;
Asciz	MalformedAttributeException;
String	MalformedAttributeException
Asciz	productArity;
Asciz	productElement;
Asciz	(I)Ljava/lang/Object;;
Asciz	java/lang/IndexOutOfBoundsException;
class	java/lang/IndexOutOfBoundsException
Asciz	scala/runtime/BoxesRunTime;
class	scala/runtime/BoxesRunTime
Asciz	boxToInteger;
Asciz	(I)Ljava/lang/Integer;;
NameAndType	boxToInteger:(I)Ljava/lang/Integer;
Method	scala/runtime/BoxesRunTime.boxToInteger:(I)Ljava/lang/Integer;
Asciz	java/lang/Object;
class	java/lang/Object
Asciz	toString;
NameAndType	toString:()Ljava/lang/String;
Method	java/lang/Object.toString:()Ljava/lang/String;
Method	java/lang/IndexOutOfBoundsException."<init>":(Ljava/lang/String;)V
Asciz	temp4;
Asciz	I;
Asciz	productElementName;
Asciz	(I)Ljava/lang/String;;
String	msg
Asciz	temp5;
NameAndType	equals:(Ljava/lang/Object;)Z
Method	java/lang/Object.equals:(Ljava/lang/Object;)Z
Asciz	java/lang/RuntimeException;
class	java/lang/RuntimeException
Method	java/lang/RuntimeException."<init>":(Ljava/lang/String;)V
Asciz	$init$;
Asciz	(Lscala/Product;)V;
NameAndType	$init$:(Lscala/Product;)V
Method	scala/Product$class.$init$:(Lscala/Product;)V
Asciz	ScalaSig;
Asciz	scala/ScalaObject;
class	scala/ScalaObject
Asciz	scala/Product;
class	scala/Product
Asciz	java/io/Serializable;
class	java/io/Serializable

{
private final java.lang.String msg;
  Signature: Ljava/lang/String;

public static final scala.Function1 andThen(scala.Function1);
  Signature: (Lscala/Function1;)Lscala/Function1;
  Code:
   Stack=2, Locals=1, Args_size=1
	getstatic	Field scala/xml/MalformedAttributeException$.MODULE$:Lscala/xml/MalformedAttributeException$;
	aload_0
	invokevirtual	Method scala/xml/MalformedAttributeException$.andThen:(Lscala/Function1;)Lscala/Function1;
	areturn
  Labels:

public static final scala.Function1 compose(scala.Function1);
  Signature: (Lscala/Function1;)Lscala/Function1;
  Code:
   Stack=2, Locals=1, Args_size=1
	getstatic	Field scala/xml/MalformedAttributeException$.MODULE$:Lscala/xml/MalformedAttributeException$;
	aload_0
	invokevirtual	Method scala/xml/MalformedAttributeException$.compose:(Lscala/Function1;)Lscala/Function1;
	areturn
  Labels:

public scala.collection.Iterator productIterator();
  Signature: ()Lscala/collection/Iterator;
  Code:
   Stack=1, Locals=1, Args_size=1
	aload_0
	invokestatic	Method scala/Product$class.productIterator:(Lscala/Product;)Lscala/collection/Iterator;
	areturn
  Labels:

public scala.collection.Iterator productElements();
  Signature: ()Lscala/collection/Iterator;
  Code:
   Stack=1, Locals=1, Args_size=1
	aload_0
	invokestatic	Method scala/Product$class.productElements:(Lscala/Product;)Lscala/collection/Iterator;
	areturn
  Labels:
  Deprecated: true

public java.lang.String copy$default$1();
  Signature: ()Ljava/lang/String;
  Code:
   Stack=1, Locals=1, Args_size=1
	aload_0
	invokevirtual	Method msg:()Ljava/lang/String;
	areturn
  Labels:

public java.lang.String msg();
  Signature: ()Ljava/lang/String;
  Code:
   Stack=1, Locals=1, Args_size=1
	aload_0
	getfield	Field msg:Ljava/lang/String;
	areturn
  Labels:

public scala.xml.MalformedAttributeException copy(java.lang.String);
  Signature: (Ljava/lang/String;)Lscala/xml/MalformedAttributeException;
  Code:
   Stack=3, Locals=2, Args_size=2
	new	class scala/xml/MalformedAttributeException
	dup
	aload_1
	invokespecial	Method "<init>":(Ljava/lang/String;)V
	areturn
  Labels:
  LocalVariableTable: 
   Start  Length  Slot  Name   Signature
   0      9      0    this       Lscala/xml/MalformedAttributeException;
   0      9      1    msg       Ljava/lang/String;


public int hashCode();
  Signature: ()I
  Code:
   Stack=2, Locals=1, Args_size=1
	getstatic	Field scala/runtime/ScalaRunTime$.MODULE$:Lscala/runtime/ScalaRunTime$;
	aload_0
	invokevirtual	Method scala/runtime/ScalaRunTime$._hashCode:(Lscala/Product;)I
	ireturn
  Labels:

public boolean equals(java.lang.Object);
  Signature: (Ljava/lang/Object;)Z
  Code:
   Stack=2, Locals=6, Args_size=2
	aload_0
	aload_1
	if_acmpeq	l1 // iconst_1
	aload_1
	astore_2
	aload_2
	instanceof	class scala/xml/MalformedAttributeException
	ifeq	l2 // iconst_0
	aload_2
	checkcast	class scala/xml/MalformedAttributeException
	astore_3
	aload_3
	invokevirtual	Method msg:()Ljava/lang/String;
	astore	4
	aload	4
	astore	5
	aload_0
	aload	5
	invokespecial	Method gd1$1:(Ljava/lang/String;)Z
	ifeq	l3 // iconst_0
	aload_1
	checkcast	class scala/xml/MalformedAttributeException
	aload_0
	invokeinterface	InterfaceMethod scala/Equals.canEqual:(Ljava/lang/Object;)Z
	goto	l4 // ifeq
l3	iconst_0
	goto	l4 // ifeq
l2	iconst_0
l4	ifeq	l5 // iconst_0
l1	iconst_1
	goto	l6 // ireturn
l5	iconst_0
l6	ireturn
  Labels:
   	l3 = 51 // iconst_0
   	l2 = 55 // iconst_0
   	l4 = 56 // ifeq
   	l1 = 59 // iconst_1
   	l5 = 63 // iconst_0
   	l6 = 64 // ireturn
  LocalVariableTable: 
   Start  Length  Slot  Name   Signature
   0      65      0    this       Lscala/xml/MalformedAttributeException;
   7      52      2    temp1       Ljava/lang/Object;
   19      36      3    temp2       Lscala/xml/MalformedAttributeException;
   25      30      4    temp3       Ljava/lang/String;
   29      26      5    msg$1       Ljava/lang/String;


public java.lang.String productPrefix();
  Signature: ()Ljava/lang/String;
  Code:
   Stack=1, Locals=1, Args_size=1
	ldc	String MalformedAttributeException
	areturn
  Labels:

public int productArity();
  Signature: ()I
  Code:
   Stack=1, Locals=1, Args_size=1
	iconst_1
	ireturn
  Labels:

public java.lang.Object productElement(int);
  Signature: (I)Ljava/lang/Object;
  Code:
   Stack=3, Locals=3, Args_size=2
	iload_1
	istore_2
	iload_2
	iconst_0
	if_icmpne	l1 // new
	aload_0
	invokevirtual	Method msg:()Ljava/lang/String;
	areturn
l1	new	class java/lang/IndexOutOfBoundsException
	dup
	iload_1
	invokestatic	Method scala/runtime/BoxesRunTime.boxToInteger:(I)Ljava/lang/Integer;
	invokevirtual	Method java/lang/Object.toString:()Ljava/lang/String;
	invokespecial	Method java/lang/IndexOutOfBoundsException."<init>":(Ljava/lang/String;)V
	athrow
  Labels:
   	l1 = 12 // new
  LocalVariableTable: 
   Start  Length  Slot  Name   Signature
   0      27      0    this       Lscala/xml/MalformedAttributeException;
   2      25      2    temp4       I


public java.lang.String productElementName(int);
  Signature: (I)Ljava/lang/String;
  Code:
   Stack=3, Locals=3, Args_size=2
	iload_1
	istore_2
	iload_2
	iconst_0
	if_icmpne	l1 // new
	ldc	String msg
	areturn
l1	new	class java/lang/IndexOutOfBoundsException
	dup
	iload_1
	invokestatic	Method scala/runtime/BoxesRunTime.boxToInteger:(I)Ljava/lang/Integer;
	invokevirtual	Method java/lang/Object.toString:()Ljava/lang/String;
	invokespecial	Method java/lang/IndexOutOfBoundsException."<init>":(Ljava/lang/String;)V
	athrow
  Labels:
   	l1 = 10 // new
  LocalVariableTable: 
   Start  Length  Slot  Name   Signature
   0      25      0    this       Lscala/xml/MalformedAttributeException;
   2      23      2    temp5       I


public boolean canEqual(java.lang.Object);
  Signature: (Ljava/lang/Object;)Z
  Code:
   Stack=1, Locals=2, Args_size=2
	aload_1
	instanceof	class scala/xml/MalformedAttributeException
	ireturn
  Labels:

private final boolean gd1$1(java.lang.String);
  Signature: (Ljava/lang/String;)Z
  Code:
   Stack=2, Locals=3, Args_size=2
	aload_1
	aload_0
	invokevirtual	Method msg:()Ljava/lang/String;
	astore_2
	dup
	ifnonnull	l1 // aload_2
	pop
	aload_2
	ifnull	l2 // iconst_1
	goto	l3 // iconst_0
l1	aload_2
	invokevirtual	Method java/lang/Object.equals:(Ljava/lang/Object;)Z
	ifeq	l3 // iconst_0
l2	iconst_1
	goto	l4 // ireturn
l3	iconst_0
l4	ireturn
  Labels:
   	l1 = 18 // aload_2
   	l2 = 25 // iconst_1
   	l3 = 29 // iconst_0
   	l4 = 30 // ireturn

public scala.xml.MalformedAttributeException(java.lang.String);
  Signature: (Ljava/lang/String;)V
  Code:
   Stack=2, Locals=2, Args_size=2
	aload_0
	aload_1
	putfield	Field msg:Ljava/lang/String;
	aload_0
	aload_1
	invokespecial	Method java/lang/RuntimeException."<init>":(Ljava/lang/String;)V
	aload_0
	invokestatic	Method scala/Product$class.$init$:(Lscala/Product;)V
	return
  Labels:
  LocalVariableTable: 
   Start  Length  Slot  Name   Signature
   0      15      0    this       Lscala/xml/MalformedAttributeException;
   0      15      1    msg       Ljava/lang/String;


}

