Compiled from "MetaData.scala"
public final class scala.xml.MetaData$$anonfun$equals$1 extends scala.runtime.AbstractFunction1 implements java.io.Serializable
  SourceFile: "MetaData.scala"
  Scala: length = 0x
   
  InnerClass: 
   public final $anonfun$equals$1=class scala/xml/MetaData$$anonfun$equals$1 of class scala/xml/MetaData
  minor version: 0
  major version: 49
  Constant pool:
Asciz	SourceFile;
Asciz	MetaData.scala;
Asciz	<clinit>;
Asciz	()V;
Asciz	Code;
Asciz	serialVersionUID;
Asciz	J;
Asciz	scala/xml/MetaData$$anonfun$equals$1;
class	scala/xml/MetaData$$anonfun$equals$1
NameAndType	serialVersionUID:J
Field	scala/xml/MetaData$$anonfun$equals$1.serialVersionUID:J
Asciz	m$1;
Asciz	Lscala/xml/MetaData;;
Asciz	<init>;
Asciz	(Lscala/xml/MetaData;Lscala/xml/MetaData;)V;
Asciz	LineNumberTable;
NameAndType	m$1:Lscala/xml/MetaData;
Field	scala/xml/MetaData$$anonfun$equals$1.m$1:Lscala/xml/MetaData;
Asciz	scala/runtime/AbstractFunction1;
class	scala/runtime/AbstractFunction1
NameAndType	"<init>":()V
Method	scala/runtime/AbstractFunction1."<init>":()V
Asciz	this;
Asciz	Lscala/xml/MetaData$$anonfun$equals$1;;
Asciz	$outer;
Asciz	LocalVariableTable;
Asciz	apply;
Asciz	(Ljava/lang/Object;)Ljava/lang/Object;;
Asciz	scala/xml/MetaData;
class	scala/xml/MetaData
Asciz	(Lscala/xml/MetaData;)Z;
NameAndType	apply:(Lscala/xml/MetaData;)Z
Method	scala/xml/MetaData$$anonfun$equals$1.apply:(Lscala/xml/MetaData;)Z
Asciz	scala/runtime/BoxesRunTime;
class	scala/runtime/BoxesRunTime
Asciz	boxToBoolean;
Asciz	(Z)Ljava/lang/Boolean;;
NameAndType	boxToBoolean:(Z)Ljava/lang/Boolean;
Method	scala/runtime/BoxesRunTime.boxToBoolean:(Z)Ljava/lang/Boolean;
Asciz	v1;
Asciz	Ljava/lang/Object;;
Asciz	containedIn1;
NameAndType	containedIn1:(Lscala/xml/MetaData;)Z
Method	scala/xml/MetaData.containedIn1:(Lscala/xml/MetaData;)Z
Asciz	Scala;
Asciz	InnerClasses;
Asciz	$anonfun$equals$1;
Asciz	java/io/Serializable;
class	java/io/Serializable

{
public static final long serialVersionUID;
  Signature: J

private final scala.xml.MetaData m$1;
  Signature: Lscala/xml/MetaData;

public static {};
  Signature: ()V
  Code:
   Stack=2, Locals=0, Args_size=0
	lconst_0
	putstatic	Field serialVersionUID:J
	return
  Labels:

public scala.xml.MetaData$$anonfun$equals$1(scala.xml.MetaData, scala.xml.MetaData);
  Signature: (Lscala/xml/MetaData;Lscala/xml/MetaData;)V
  Code:
   Stack=2, Locals=3, Args_size=3
	aload_0
	aload_2
	putfield	Field m$1:Lscala/xml/MetaData;
	aload_0
	invokespecial	Method scala/runtime/AbstractFunction1."<init>":()V
	return
  Labels:
  LocalVariableTable: 
   Start  Length  Slot  Name   Signature
   0      10      0    this       Lscala/xml/MetaData$$anonfun$equals$1;
   0      10      1    $outer       Lscala/xml/MetaData;


public final java.lang.Object apply(java.lang.Object);
  Signature: (Ljava/lang/Object;)Ljava/lang/Object;
  Code:
   Stack=2, Locals=3, Args_size=2
	aload_0
	aload_1
	checkcast	class scala/xml/MetaData
	invokevirtual	Method apply:(Lscala/xml/MetaData;)Z
	istore_2
	iload_2
	invokestatic	Method scala/runtime/BoxesRunTime.boxToBoolean:(Z)Ljava/lang/Boolean;
	areturn
  Labels:
  LocalVariableTable: 
   Start  Length  Slot  Name   Signature
   0      14      0    this       Lscala/xml/MetaData$$anonfun$equals$1;
   0      14      1    v1       Ljava/lang/Object;


public final boolean apply(scala.xml.MetaData);
  Signature: (Lscala/xml/MetaData;)Z
  Code:
   Stack=2, Locals=2, Args_size=2
	aload_1
	aload_0
	getfield	Field m$1:Lscala/xml/MetaData;
	invokevirtual	Method scala/xml/MetaData.containedIn1:(Lscala/xml/MetaData;)Z
	ireturn
  Labels:

}

