Compiled from "MetaData.scala"
public abstract class scala.xml.MetaData extends java.lang.Object implements scala.collection.Iterable,scala.ScalaObject,java.io.Serializable
  SourceFile: "MetaData.scala"
  Signature: length = 0x2
   02 FFFFFF89 
  ScalaSig: length = 0x772
   05 00 FFFFFF82 0F 07 05 01 02 FFFFFF88 02 07 01 08 4D 65 74
   61 44 61 74 61 0A 02 03 04 01 03 78 6D 6C 0A 01
   05 01 05 73 63 61 6C 61 03 00 10 02 08 09 0D 01
   02 06 08 0A 02 FFFFFF84 FFFFFF80 FFFFFF80 FFFFFF88 02 0B 02 08 4D 65 74
   61 44 61 74 61 13 03 09 0C 14 10 02 0D 12 0D 01
   0E 0A 02 0F 10 01 04 6C 61 6E 67 0A 01 11 01 04
   6A 61 76 61 09 02 13 0E 02 06 4F 62 6A 65 63 74
   10 02 15 16 0D 01 04 09 02 17 04 02 0B 53 63 61
   6C 61 4F 62 6A 65 63 74 08 05 19 09 FFFFFF84 00 1A 01
   06 3C 69 6E 69 74 3E 14 01 07 08 05 1C 09 FFFFFF84 00
   1D 01 0B 63 6F 6E 63 61 74 65 6E 61 74 65 14 05
   1E FFFFFF81 73 FFFFFF81 75 10 02 08 1F 06 08 0A 02 FFFFFF84 FFFFFF80 FFFFFF80
   FFFFFF81 00 20 13 04 1F 0C 21 14 10 03 22 25 1E 0D 01
   23 0A 02 24 04 01 0A 63 6F 6C 6C 65 63 74 69 6F
   6E 09 02 26 23 02 08 49 74 65 72 61 62 6C 65 08
   05 19 1F FFFFFF84 00 28 14 01 1E 08 05 2A 1F FFFFFF84 00 2B
   01 06 61 70 70 65 6E 64 14 03 1E 2C 2E 08 05 2D
   29 FFFFFFC0 00 1E 01 07 75 70 64 61 74 65 73 08 08 33
   2F 29 FFFFFF90 FFFFFF80 FFFFFFC0 00 30 01 05 73 63 6F 70 65 10 02
   08 31 09 02 32 02 02 10 4E 61 6D 65 73 70 61 63
   65 42 69 6E 64 69 6E 67 08 07 34 1F FFFFFF91 FFFFFF80 FFFFFF84 00
   35 01 10 61 70 70 65 6E 64 24 64 65 66 61 75 6C
   74 24 32 15 01 36 2A 02 30 37 2B 01 38 10 02 39
   3E 0D 01 3A 0A 02 3B 3C 01 09 75 6E 63 68 65 63
   6B 65 64 0A 02 3D 04 01 0A 61 6E 6E 6F 74 61 74
   69 6F 6E 09 02 3F 3A 02 11 75 6E 63 68 65 63 6B
   65 64 56 61 72 69 61 6E 63 65 08 05 41 1F FFFFFF86 00
   42 01 05 61 70 70 6C 79 14 02 43 49 10 03 22 44
   46 09 02 45 23 02 03 53 65 71 10 02 08 47 09 02
   48 02 02 04 4E 6F 64 65 08 05 4A 40 FFFFFFC0 00 4B 01
   03 6B 65 79 10 02 4C 4F 0E 02 15 4D 09 02 4E 04
   01 06 50 72 65 64 65 66 09 02 50 51 02 06 53 74
   72 69 6E 67 0A 02 4E 04 08 05 41 1F FFFFFF84 02 53 14
   04 43 54 56 58 08 05 55 52 FFFFFFC0 00 4B 01 0D 6E 61
   6D 65 73 70 61 63 65 5F 75 72 69 08 05 57 52 FFFFFFC0
   00 46 01 05 6F 77 6E 65 72 08 05 4A 52 FFFFFFC0 00 4B
   08 05 41 1F FFFFFF86 00 5A 14 04 43 5B 5C 5E 08 05 55
   59 FFFFFFC0 00 4B 08 05 5D 59 FFFFFFC0 00 30 01 03 73 63 70
   08 05 5F 59 FFFFFFC0 00 4B 01 01 6B 08 05 61 1F FFFFFF84 00
   62 01 0C 63 6F 6E 74 61 69 6E 65 64 49 6E 31 14
   02 63 66 10 02 15 64 09 02 65 04 02 07 42 6F 6F
   6C 65 61 6E 08 05 67 60 FFFFFFC0 00 1E 01 01 6D 08 05
   69 1F FFFFFF86 00 6A 01 04 63 6F 70 79 14 02 1E 6B 08
   05 6C 68 FFFFFFC0 00 1E 01 04 6E 65 78 74 08 05 6E 1F
   FFFFFF86 00 6F 01 0C 67 65 74 4E 61 6D 65 73 70 61 63
   65 14 02 4B 70 08 05 57 6D FFFFFFC0 00 46 08 05 72 1F
   FFFFFF84 00 73 01 07 68 61 73 4E 65 78 74 15 01 63 08
   05 75 1F FFFFFF84 00 76 01 06 6C 65 6E 67 74 68 15 01
   77 10 02 15 78 09 02 79 04 02 03 49 6E 74 08 05
   75 1F FFFFFF84 00 7B 14 02 77 7C 08 05 7D 7A FFFFFFC0 00 77
   01 01 69 08 05 7F 1F FFFFFF86 00 73 01 0A 69 73 50 72
   65 66 69 78 65 64 08 07 FFFFFF81 01 1F FFFFFF84 20 FFFFFF81 02 01
   06 65 71 75 61 6C 73 14 03 63 FFFFFF81 03 08 08 FFFFFF81 04
   FFFFFF81 00 FFFFFFC0 00 FFFFFF81 05 01 04 74 68 61 74 10 03 15 FFFFFF81
   06 09 03 FFFFFF81 07 04 02 03 41 6E 79 08 07 FFFFFF81 09 1F
   FFFFFF84 00 FFFFFF81 0A 01 08 69 74 65 72 61 74 6F 72 15 02
   FFFFFF81 0B 10 04 22 FFFFFF81 0C 1E 09 03 FFFFFF81 0D 23 02 08 49
   74 65 72 61 74 6F 72 08 06 FFFFFF81 0F 1F FFFFFF84 20 76 01
   04 73 69 7A 65 08 07 FFFFFF81 11 1F FFFFFF86 00 FFFFFF81 12 01 07
   65 71 75 61 6C 73 31 14 03 63 FFFFFF81 13 08 07 FFFFFF81 04
   FFFFFF81 10 FFFFFFC0 00 1E 08 07 FFFFFF81 15 1F FFFFFF84 20 FFFFFF81 16 01 06
   66 69 6C 74 65 72 14 03 1E FFFFFF81 17 08 08 FFFFFF81 18 FFFFFF81
   14 FFFFFFC0 00 FFFFFF81 19 01 01 66 10 05 15 FFFFFF81 1A 1E 63 09
   03 FFFFFF81 1B 04 02 09 46 75 6E 63 74 69 6F 6E 31 08
   06 4A 1F FFFFFF86 00 FFFFFF81 1D 15 01 4B 08 07 FFFFFF81 1F 1F FFFFFF86
   00 FFFFFF81 20 01 05 76 61 6C 75 65 15 01 43 08 07 FFFFFF81
   22 1F FFFFFF84 00 FFFFFF81 23 01 03 6D 61 70 14 04 FFFFFF81 24 FFFFFF81
   2D 10 06 FFFFFF81 25 FFFFFF81 28 FFFFFF81 2A 0D 02 FFFFFF81 26 0A 03 FFFFFF81
   27 23 01 09 69 6D 6D 75 74 61 62 6C 65 09 04 FFFFFF81
   29 FFFFFF81 26 02 04 4C 69 73 74 10 03 08 FFFFFF81 2B 09 03
   FFFFFF81 2C 02 02 04 54 65 78 74 08 08 FFFFFF81 18 FFFFFF81 21 FFFFFFC0
   00 FFFFFF81 2E 10 06 15 FFFFFF81 1A 1E FFFFFF81 2A 08 06 6C 1F FFFFFF86
   00 FFFFFF81 30 15 01 1E 08 07 FFFFFF81 32 1F FFFFFF84 02 FFFFFF81 33 01
   03 67 65 74 14 04 FFFFFF81 34 FFFFFF81 37 10 04 15 FFFFFF81 35 43
   09 03 FFFFFF81 36 04 02 06 4F 70 74 69 6F 6E 08 06 4A
   FFFFFF81 31 FFFFFFC0 00 4B 08 07 FFFFFF81 32 1F FFFFFF84 02 FFFFFF81 39 14 08
   FFFFFF81 34 FFFFFF81 3A FFFFFF81 3C FFFFFF81 3D 08 07 FFFFFF81 3B FFFFFF81 38 FFFFFFC0 00
   4B 01 03 75 72 69 08 06 57 FFFFFF81 38 FFFFFFC0 00 46 08 06
   4A FFFFFF81 38 FFFFFFC0 00 4B 08 07 FFFFFF81 32 1F FFFFFF84 02 FFFFFF81 3F 14
   08 FFFFFF81 34 FFFFFF81 40 FFFFFF81 41 FFFFFF81 42 08 07 FFFFFF81 3B FFFFFF81 3E FFFFFFC0
   00 4B 08 06 2F FFFFFF81 3E FFFFFFC0 00 30 08 06 4A FFFFFF81 3E FFFFFFC0
   00 4B 08 07 FFFFFF81 44 1F FFFFFF86 20 FFFFFF81 45 01 08 68 61 73
   68 43 6F 64 65 14 01 77 08 07 FFFFFF81 47 1F FFFFFF84 00 FFFFFF81
   48 01 09 74 6F 53 74 72 69 6E 67 31 14 01 4B 08
   07 FFFFFF81 47 1F FFFFFF86 00 FFFFFF81 4A 14 04 FFFFFF81 4B FFFFFF81 4E 10 03
   15 FFFFFF81 4C 09 03 FFFFFF81 4D 04 02 04 55 6E 69 74 08 08
   FFFFFF81 4F FFFFFF81 49 FFFFFFC0 00 FFFFFF81 50 01 02 73 62 10 04 FFFFFF81 51
   FFFFFF81 54 0D 02 FFFFFF81 52 0A 03 FFFFFF81 53 23 01 07 6D 75 74
   61 62 6C 65 09 04 FFFFFF81 55 FFFFFF81 52 02 0D 53 74 72 69
   6E 67 42 75 69 6C 64 65 72 08 07 FFFFFF81 57 1F FFFFFF84 20
   FFFFFF81 48 01 08 74 6F 53 74 72 69 6E 67 08 07 FFFFFF81 59
   1F FFFFFF84 00 FFFFFF81 5A 01 0B 62 75 69 6C 64 53 74 72 69
   6E 67 14 04 FFFFFF81 50 FFFFFF81 5B 08 08 FFFFFF81 4F FFFFFF81 58 FFFFFFC0 00
   FFFFFF81 50 08 07 FFFFFF81 5D 1F FFFFFF86 00 FFFFFF81 5E 01 0A 77 65 6C
   6C 66 6F 72 6D 65 64 14 03 63 FFFFFF81 5F 08 06 2F FFFFFF81
   5C FFFFFFC0 00 30 08 07 FFFFFF81 61 1F FFFFFF86 00 FFFFFF81 62 01 06 72
   65 6D 6F 76 65 14 03 1E FFFFFF81 63 08 06 4A FFFFFF81 60 FFFFFFC0
   00 4B 08 07 FFFFFF81 61 1F FFFFFF86 00 FFFFFF81 65 14 07 1E FFFFFF81 66
   FFFFFF81 68 FFFFFF81 69 08 07 FFFFFF81 67 FFFFFF81 64 FFFFFFC0 00 4B 01 09 6E
   61 6D 65 73 70 61 63 65 08 06 2F FFFFFF81 64 FFFFFFC0 00 30
   08 06 4A FFFFFF81 64 FFFFFFC0 00 4B 08 07 FFFFFF81 61 1F FFFFFF84 02 FFFFFF81
   6B 14 07 1E FFFFFF81 6C FFFFFF81 6D FFFFFF81 6E 08 07 FFFFFF81 67 FFFFFF81 6A
   FFFFFFC0 00 4B 08 06 57 FFFFFF81 6A FFFFFFC0 00 46 08 06 4A FFFFFF81 6A
   FFFFFFC0 00 4B 28 03 1F FFFFFF81 70 10 03 15 FFFFFF81 71 09 03 FFFFFF81
   72 04 02 0C 73 65 72 69 61 6C 69 7A 61 62 6C 65
   08 06 FFFFFF81 74 1B FFFFFFC0 00 1E 01 07 61 74 74 72 69 62
   73 08 06 FFFFFF81 76 1B FFFFFFC0 00 1E 01 08 6E 65 77 5F 74
   61 69 6C 28 03 1B FFFFFF81 78 10 04 FFFFFF81 79 FFFFFF81 7A 0D 01
   3C 09 03 FFFFFF81 7B 3C 02 07 74 61 69 6C 72 65 63 08
   07 FFFFFF81 7D 09 FFFFFF84 00 FFFFFF81 7E 01 09 6E 6F 72 6D 61 6C
   69 7A 65 14 05 1E FFFFFF81 7F FFFFFF82 00 08 07 FFFFFF81 74 FFFFFF81 7C
   FFFFFFC0 00 1E 08 06 2F FFFFFF81 7C FFFFFFC0 00 30 08 07 FFFFFF82 02 09
   FFFFFF84 00 FFFFFF82 03 01 0F 67 65 74 55 6E 69 76 65 72 73
   61 6C 4B 65 79 14 06 FFFFFF82 04 FFFFFF82 06 FFFFFF82 08 10 03 0D
   FFFFFF82 05 09 02 50 0E 08 07 FFFFFF82 07 FFFFFF82 01 FFFFFFC0 00 1E 01
   06 61 74 74 72 69 62 08 06 2F FFFFFF82 01 FFFFFFC0 00 30 08
   07 FFFFFF82 0A 09 FFFFFF84 00 FFFFFF82 0B 01 06 75 70 64 61 74 65
   14 07 1E FFFFFF82 0C FFFFFF82 0D FFFFFF82 0E 08 07 FFFFFF81 74 FFFFFF82 09 FFFFFFC0
   00 1E 08 06 2F FFFFFF82 09 FFFFFFC0 00 30 08 06 2D FFFFFF82 09 FFFFFFC0
   00 1E 
  InnerClass: 
   public final #652= #222 of #183; //$anon$11=class scala/collection/Iterator$$anon$11 of class scala/collection/Iterator
   public #657= #654 of #656; //WithFilter=class scala/collection/TraversableLike$WithFilter of class scala/collection/TraversableLike
   public final #658= #241 of #62; //$anonfun$equals$1=class scala/xml/MetaData$$anonfun$equals$1 of class scala/xml/MetaData
   public final #659= #227 of #62; //$anonfun$iterator$2=class scala/xml/MetaData$$anonfun$iterator$2 of class scala/xml/MetaData
   public final #660= #219 of #62; //$anonfun$iterator$1=class scala/xml/MetaData$$anonfun$iterator$1 of class scala/xml/MetaData
   public final #661= #136 of #62; //$anonfun$toString$1=class scala/xml/MetaData$$anonfun$toString$1 of class scala/xml/MetaData
   public final #662= #145 of #62; //$anonfun$toString1$1=class scala/xml/MetaData$$anonfun$toString1$1 of class scala/xml/MetaData
  minor version: 0
  major version: 49
  Constant pool:
const #1 = Asciz	SourceFile;
const #2 = Asciz	MetaData.scala;
const #3 = Asciz	update;
const #4 = Asciz	(Lscala/xml/MetaData;Lscala/xml/NamespaceBinding;Lscala/xml/MetaData;)Lscala/xml/MetaData;;
const #5 = Asciz	Code;
const #6 = Asciz	scala/xml/MetaData$;
const #7 = class	#6;	//  scala/xml/MetaData$
const #8 = Asciz	MODULE$;
const #9 = Asciz	Lscala/xml/MetaData$;;
const #10 = NameAndType	#8:#9;//  MODULE$:Lscala/xml/MetaData$;
const #11 = Field	#7.#10;	//  scala/xml/MetaData$.MODULE$:Lscala/xml/MetaData$;
const #12 = NameAndType	#3:#4;//  update:(Lscala/xml/MetaData;Lscala/xml/NamespaceBinding;Lscala/xml/MetaData;)Lscala/xml/MetaData;
const #13 = Method	#7.#12;	//  scala/xml/MetaData$.update:(Lscala/xml/MetaData;Lscala/xml/NamespaceBinding;Lscala/xml/MetaData;)Lscala/xml/MetaData;
const #14 = Asciz	getUniversalKey;
const #15 = Asciz	(Lscala/xml/MetaData;Lscala/xml/NamespaceBinding;)Ljava/lang/String;;
const #16 = NameAndType	#14:#15;//  getUniversalKey:(Lscala/xml/MetaData;Lscala/xml/NamespaceBinding;)Ljava/lang/String;
const #17 = Method	#7.#16;	//  scala/xml/MetaData$.getUniversalKey:(Lscala/xml/MetaData;Lscala/xml/NamespaceBinding;)Ljava/lang/String;
const #18 = Asciz	normalize;
const #19 = Asciz	(Lscala/xml/MetaData;Lscala/xml/NamespaceBinding;)Lscala/xml/MetaData;;
const #20 = NameAndType	#18:#19;//  normalize:(Lscala/xml/MetaData;Lscala/xml/NamespaceBinding;)Lscala/xml/MetaData;
const #21 = Method	#7.#20;	//  scala/xml/MetaData$.normalize:(Lscala/xml/MetaData;Lscala/xml/NamespaceBinding;)Lscala/xml/MetaData;
const #22 = Asciz	concatenate;
const #23 = Asciz	(Lscala/xml/MetaData;Lscala/xml/MetaData;)Lscala/xml/MetaData;;
const #24 = NameAndType	#22:#23;//  concatenate:(Lscala/xml/MetaData;Lscala/xml/MetaData;)Lscala/xml/MetaData;
const #25 = Method	#7.#24;	//  scala/xml/MetaData$.concatenate:(Lscala/xml/MetaData;Lscala/xml/MetaData;)Lscala/xml/MetaData;
const #26 = Asciz	<init>;
const #27 = Asciz	()V;
const #28 = Asciz	LineNumberTable;
const #29 = Asciz	java/lang/Object;
const #30 = class	#29;	//  java/lang/Object
const #31 = NameAndType	#26:#27;//  "<init>":()V
const #32 = Method	#30.#31;	//  java/lang/Object."<init>":()V
const #33 = Asciz	scala/collection/TraversableLike$class;
const #34 = class	#33;	//  scala/collection/TraversableLike$class
const #35 = Asciz	$init$;
const #36 = Asciz	(Lscala/collection/TraversableLike;)V;
const #37 = NameAndType	#35:#36;//  $init$:(Lscala/collection/TraversableLike;)V
const #38 = Method	#34.#37;	//  scala/collection/TraversableLike$class.$init$:(Lscala/collection/TraversableLike;)V
const #39 = Asciz	scala/collection/generic/GenericTraversableTemplate$class;
const #40 = class	#39;	//  scala/collection/generic/GenericTraversableTemplate$class
const #41 = Asciz	(Lscala/collection/generic/GenericTraversableTemplate;)V;
const #42 = NameAndType	#35:#41;//  $init$:(Lscala/collection/generic/GenericTraversableTemplate;)V
const #43 = Method	#40.#42;	//  scala/collection/generic/GenericTraversableTemplate$class.$init$:(Lscala/collection/generic/GenericTraversableTemplate;)V
const #44 = Asciz	scala/collection/Traversable$class;
const #45 = class	#44;	//  scala/collection/Traversable$class
const #46 = Asciz	(Lscala/collection/Traversable;)V;
const #47 = NameAndType	#35:#46;//  $init$:(Lscala/collection/Traversable;)V
const #48 = Method	#45.#47;	//  scala/collection/Traversable$class.$init$:(Lscala/collection/Traversable;)V
const #49 = Asciz	scala/collection/IterableLike$class;
const #50 = class	#49;	//  scala/collection/IterableLike$class
const #51 = Asciz	(Lscala/collection/IterableLike;)V;
const #52 = NameAndType	#35:#51;//  $init$:(Lscala/collection/IterableLike;)V
const #53 = Method	#50.#52;	//  scala/collection/IterableLike$class.$init$:(Lscala/collection/IterableLike;)V
const #54 = Asciz	scala/collection/Iterable$class;
const #55 = class	#54;	//  scala/collection/Iterable$class
const #56 = Asciz	(Lscala/collection/Iterable;)V;
const #57 = NameAndType	#35:#56;//  $init$:(Lscala/collection/Iterable;)V
const #58 = Method	#55.#57;	//  scala/collection/Iterable$class.$init$:(Lscala/collection/Iterable;)V
const #59 = Asciz	filter;
const #60 = Asciz	(Lscala/Function1;)Ljava/lang/Object;;
const #61 = Asciz	scala/xml/MetaData;
const #62 = class	#61;	//  scala/xml/MetaData
const #63 = Asciz	(Lscala/Function1;)Lscala/xml/MetaData;;
const #64 = NameAndType	#59:#63;//  filter:(Lscala/Function1;)Lscala/xml/MetaData;
const #65 = Method	#62.#64;	//  scala/xml/MetaData.filter:(Lscala/Function1;)Lscala/xml/MetaData;
const #66 = Asciz	this;
const #67 = Asciz	Lscala/xml/MetaData;;
const #68 = Asciz	p;
const #69 = Asciz	Lscala/Function1;;
const #70 = Asciz	LocalVariableTable;
const #71 = Asciz	thisCollection;
const #72 = Asciz	()Lscala/collection/Traversable;;
const #73 = Asciz	scala/collection/IterableLike;
const #74 = class	#73;	//  scala/collection/IterableLike
const #75 = Asciz	()Lscala/collection/Iterable;;
const #76 = NameAndType	#71:#75;//  thisCollection:()Lscala/collection/Iterable;
const #77 = InterfaceMethod	#74.#76;	//  scala/collection/IterableLike.thisCollection:()Lscala/collection/Iterable;
const #78 = Asciz	toCollection;
const #79 = Asciz	(Ljava/lang/Object;)Lscala/collection/Traversable;;
const #80 = Asciz	(Ljava/lang/Object;)Lscala/collection/Iterable;;
const #81 = NameAndType	#78:#80;//  toCollection:(Ljava/lang/Object;)Lscala/collection/Iterable;
const #82 = InterfaceMethod	#74.#81;	//  scala/collection/IterableLike.toCollection:(Ljava/lang/Object;)Lscala/collection/Iterable;
const #83 = Asciz	repr;
const #84 = Asciz	Ljava/lang/Object;;
const #85 = Asciz	view;
const #86 = Asciz	(II)Lscala/collection/TraversableView;;
const #87 = Asciz	(II)Lscala/collection/IterableView;;
const #88 = NameAndType	#85:#87;//  view:(II)Lscala/collection/IterableView;
const #89 = InterfaceMethod	#74.#88;	//  scala/collection/IterableLike.view:(II)Lscala/collection/IterableView;
const #90 = Asciz	from;
const #91 = Asciz	I;
const #92 = Asciz	until;
const #93 = Asciz	remove;
const #94 = Asciz	(Ljava/lang/String;Lscala/xml/Node;Ljava/lang/String;)Lscala/xml/MetaData;;
const #95 = Asciz	scala/xml/Node;
const #96 = class	#95;	//  scala/xml/Node
const #97 = Asciz	scope;
const #98 = Asciz	()Lscala/xml/NamespaceBinding;;
const #99 = NameAndType	#97:#98;//  scope:()Lscala/xml/NamespaceBinding;
const #100 = Method	#96.#99;	//  scala/xml/Node.scope:()Lscala/xml/NamespaceBinding;
const #101 = Asciz	(Ljava/lang/String;Lscala/xml/NamespaceBinding;Ljava/lang/String;)Lscala/xml/MetaData;;
const #102 = NameAndType	#93:#101;//  remove:(Ljava/lang/String;Lscala/xml/NamespaceBinding;Ljava/lang/String;)Lscala/xml/MetaData;
const #103 = Method	#62.#102;	//  scala/xml/MetaData.remove:(Ljava/lang/String;Lscala/xml/NamespaceBinding;Ljava/lang/String;)Lscala/xml/MetaData;
const #104 = Asciz	namespace;
const #105 = Asciz	Ljava/lang/String;;
const #106 = Asciz	owner;
const #107 = Asciz	Lscala/xml/Node;;
const #108 = Asciz	key;
const #109 = Asciz	(Ljava/lang/String;)Lscala/xml/MetaData;;
const #110 = Asciz	wellformed;
const #111 = Asciz	(Lscala/xml/NamespaceBinding;)Z;
const #112 = Asciz	buildString;
const #113 = Asciz	(Lscala/collection/mutable/StringBuilder;)Lscala/collection/mutable/StringBuilder;;
const #114 = int	32;
const #115 = Asciz	scala/collection/mutable/StringBuilder;
const #116 = class	#115;	//  scala/collection/mutable/StringBuilder
const #117 = Asciz	append;
const #118 = Asciz	(C)Lscala/collection/mutable/StringBuilder;;
const #119 = NameAndType	#117:#118;//  append:(C)Lscala/collection/mutable/StringBuilder;
const #120 = Method	#116.#119;	//  scala/collection/mutable/StringBuilder.append:(C)Lscala/collection/mutable/StringBuilder;
const #121 = Asciz	toString1;
const #122 = Asciz	(Lscala/collection/mutable/StringBuilder;)V;
const #123 = NameAndType	#121:#122;//  toString1:(Lscala/collection/mutable/StringBuilder;)V
const #124 = Method	#62.#123;	//  scala/xml/MetaData.toString1:(Lscala/collection/mutable/StringBuilder;)V
const #125 = Asciz	next;
const #126 = Asciz	()Lscala/xml/MetaData;;
const #127 = NameAndType	#125:#126;//  next:()Lscala/xml/MetaData;
const #128 = Method	#62.#127;	//  scala/xml/MetaData.next:()Lscala/xml/MetaData;
const #129 = NameAndType	#112:#113;//  buildString:(Lscala/collection/mutable/StringBuilder;)Lscala/collection/mutable/StringBuilder;
const #130 = Method	#62.#129;	//  scala/xml/MetaData.buildString:(Lscala/collection/mutable/StringBuilder;)Lscala/collection/mutable/StringBuilder;
const #131 = Asciz	sb;
const #132 = Asciz	Lscala/collection/mutable/StringBuilder;;
const #133 = Asciz	toString;
const #134 = Asciz	()Ljava/lang/String;;
const #135 = Asciz	scala/xml/MetaData$$anonfun$toString$1;
const #136 = class	#135;	//  scala/xml/MetaData$$anonfun$toString$1
const #137 = Asciz	(Lscala/xml/MetaData;)V;
const #138 = NameAndType	#26:#137;//  "<init>":(Lscala/xml/MetaData;)V
const #139 = Method	#136.#138;	//  scala/xml/MetaData$$anonfun$toString$1."<init>":(Lscala/xml/MetaData;)V
const #140 = Method	#116.#31;	//  scala/collection/mutable/StringBuilder."<init>":()V
const #141 = NameAndType	#133:#134;//  toString:()Ljava/lang/String;
const #142 = Method	#116.#141;	//  scala/collection/mutable/StringBuilder.toString:()Ljava/lang/String;
const #143 = Asciz	sb0;
const #144 = Asciz	scala/xml/MetaData$$anonfun$toString1$1;
const #145 = class	#144;	//  scala/xml/MetaData$$anonfun$toString1$1
const #146 = Method	#145.#138;	//  scala/xml/MetaData$$anonfun$toString1$1."<init>":(Lscala/xml/MetaData;)V
const #147 = Asciz	hashCode;
const #148 = Asciz	()I;
const #149 = Asciz	get;
const #150 = Asciz	(Ljava/lang/String;Lscala/xml/NamespaceBinding;Ljava/lang/String;)Lscala/Option;;
const #151 = Asciz	scala/Option$;
const #152 = class	#151;	//  scala/Option$
const #153 = Asciz	Lscala/Option$;;
const #154 = NameAndType	#8:#153;//  MODULE$:Lscala/Option$;
const #155 = Field	#152.#154;	//  scala/Option$.MODULE$:Lscala/Option$;
const #156 = Asciz	apply;
const #157 = Asciz	(Ljava/lang/String;Lscala/xml/NamespaceBinding;Ljava/lang/String;)Lscala/collection/Seq;;
const #158 = NameAndType	#156:#157;//  apply:(Ljava/lang/String;Lscala/xml/NamespaceBinding;Ljava/lang/String;)Lscala/collection/Seq;
const #159 = Method	#62.#158;	//  scala/xml/MetaData.apply:(Ljava/lang/String;Lscala/xml/NamespaceBinding;Ljava/lang/String;)Lscala/collection/Seq;
const #160 = Asciz	(Ljava/lang/Object;)Lscala/Option;;
const #161 = NameAndType	#156:#160;//  apply:(Ljava/lang/Object;)Lscala/Option;
const #162 = Method	#152.#161;	//  scala/Option$.apply:(Ljava/lang/Object;)Lscala/Option;
const #163 = Asciz	uri;
const #164 = Asciz	Lscala/xml/NamespaceBinding;;
const #165 = Asciz	(Ljava/lang/String;Lscala/xml/NamespaceBinding;Ljava/lang/String;)Lscala/Option<Lscala/collection/Seq<Lscala/xml/Node;>;>;;
const #166 = Asciz	Signature;
const #167 = Asciz	(Ljava/lang/String;Lscala/xml/Node;Ljava/lang/String;)Lscala/Option;;
const #168 = NameAndType	#149:#150;//  get:(Ljava/lang/String;Lscala/xml/NamespaceBinding;Ljava/lang/String;)Lscala/Option;
const #169 = Method	#62.#168;	//  scala/xml/MetaData.get:(Ljava/lang/String;Lscala/xml/NamespaceBinding;Ljava/lang/String;)Lscala/Option;
const #170 = Asciz	(Ljava/lang/String;Lscala/xml/Node;Ljava/lang/String;)Lscala/Option<Lscala/collection/Seq<Lscala/xml/Node;>;>;;
const #171 = Asciz	(Ljava/lang/String;)Lscala/Option;;
const #172 = Asciz	(Ljava/lang/String;)Lscala/collection/Seq;;
const #173 = NameAndType	#156:#172;//  apply:(Ljava/lang/String;)Lscala/collection/Seq;
const #174 = Method	#62.#173;	//  scala/xml/MetaData.apply:(Ljava/lang/String;)Lscala/collection/Seq;
const #175 = Asciz	(Ljava/lang/String;)Lscala/Option<Lscala/collection/Seq<Lscala/xml/Node;>;>;;
const #176 = Asciz	map;
const #177 = Asciz	(Lscala/Function1;)Lscala/collection/immutable/List;;
const #178 = Asciz	iterator;
const #179 = Asciz	()Lscala/collection/Iterator;;
const #180 = NameAndType	#178:#179;//  iterator:()Lscala/collection/Iterator;
const #181 = Method	#62.#180;	//  scala/xml/MetaData.iterator:()Lscala/collection/Iterator;
const #182 = Asciz	scala/collection/Iterator;
const #183 = class	#182;	//  scala/collection/Iterator
const #184 = Asciz	(Lscala/Function1;)Lscala/collection/Iterator;;
const #185 = NameAndType	#176:#184;//  map:(Lscala/Function1;)Lscala/collection/Iterator;
const #186 = InterfaceMethod	#183.#185;	//  scala/collection/Iterator.map:(Lscala/Function1;)Lscala/collection/Iterator;
const #187 = Asciz	toList;
const #188 = Asciz	()Lscala/collection/immutable/List;;
const #189 = NameAndType	#187:#188;//  toList:()Lscala/collection/immutable/List;
const #190 = InterfaceMethod	#183.#189;	//  scala/collection/Iterator.toList:()Lscala/collection/immutable/List;
const #191 = Asciz	f;
const #192 = Asciz	(Lscala/Function1<Lscala/xml/MetaData;Lscala/xml/Text;>;)Lscala/collection/immutable/List<Lscala/xml/Text;>;;
const #193 = Asciz	value;
const #194 = Asciz	()Lscala/collection/Seq;;
const #195 = Asciz	()Lscala/collection/Seq<Lscala/xml/Node;>;;
const #196 = Asciz	scala/Function1;
const #197 = class	#196;	//  scala/Function1
const #198 = Asciz	(Ljava/lang/Object;)Ljava/lang/Object;;
const #199 = NameAndType	#156:#198;//  apply:(Ljava/lang/Object;)Ljava/lang/Object;
const #200 = InterfaceMethod	#197.#199;	//  scala/Function1.apply:(Ljava/lang/Object;)Ljava/lang/Object;
const #201 = Asciz	scala/runtime/BoxesRunTime;
const #202 = class	#201;	//  scala/runtime/BoxesRunTime
const #203 = Asciz	unboxToBoolean;
const #204 = Asciz	(Ljava/lang/Object;)Z;
const #205 = NameAndType	#203:#204;//  unboxToBoolean:(Ljava/lang/Object;)Z
const #206 = Method	#202.#205;	//  scala/runtime/BoxesRunTime.unboxToBoolean:(Ljava/lang/Object;)Z
const #207 = Asciz	copy;
const #208 = Asciz	(Lscala/xml/MetaData;)Lscala/xml/MetaData;;
const #209 = NameAndType	#207:#208;//  copy:(Lscala/xml/MetaData;)Lscala/xml/MetaData;
const #210 = Method	#62.#209;	//  scala/xml/MetaData.copy:(Lscala/xml/MetaData;)Lscala/xml/MetaData;
const #211 = Asciz	(Lscala/Function1<Lscala/xml/MetaData;Ljava/lang/Boolean;>;)Lscala/xml/MetaData;;
const #212 = Asciz	equals1;
const #213 = Asciz	(Lscala/xml/MetaData;)Z;
const #214 = Asciz	size;
const #215 = Asciz	length;
const #216 = NameAndType	#215:#148;//  length:()I
const #217 = InterfaceMethod	#183.#216;	//  scala/collection/Iterator.length:()I
const #218 = Asciz	scala/xml/MetaData$$anonfun$iterator$1;
const #219 = class	#218;	//  scala/xml/MetaData$$anonfun$iterator$1
const #220 = Method	#219.#138;	//  scala/xml/MetaData$$anonfun$iterator$1."<init>":(Lscala/xml/MetaData;)V
const #221 = Asciz	scala/collection/Iterator$$anon$11;
const #222 = class	#221;	//  scala/collection/Iterator$$anon$11
const #223 = Asciz	(Ljava/lang/Object;Lscala/Function1;)V;
const #224 = NameAndType	#26:#223;//  "<init>":(Ljava/lang/Object;Lscala/Function1;)V
const #225 = Method	#222.#224;	//  scala/collection/Iterator$$anon$11."<init>":(Ljava/lang/Object;Lscala/Function1;)V
const #226 = Asciz	scala/xml/MetaData$$anonfun$iterator$2;
const #227 = class	#226;	//  scala/xml/MetaData$$anonfun$iterator$2
const #228 = Method	#227.#138;	//  scala/xml/MetaData$$anonfun$iterator$2."<init>":(Lscala/xml/MetaData;)V
const #229 = Asciz	scala/collection/Iterator$class;
const #230 = class	#229;	//  scala/collection/Iterator$class
const #231 = Asciz	takeWhile;
const #232 = Asciz	(Lscala/collection/Iterator;Lscala/Function1;)Lscala/collection/Iterator;;
const #233 = NameAndType	#231:#232;//  takeWhile:(Lscala/collection/Iterator;Lscala/Function1;)Lscala/collection/Iterator;
const #234 = Method	#230.#233;	//  scala/collection/Iterator$class.takeWhile:(Lscala/collection/Iterator;Lscala/Function1;)Lscala/collection/Iterator;
const #235 = Asciz	()Lscala/collection/Iterator<Lscala/xml/MetaData;>;;
const #236 = Asciz	equals;
const #237 = Method	#62.#216;	//  scala/xml/MetaData.length:()I
const #238 = NameAndType	#147:#148;//  hashCode:()I
const #239 = Method	#62.#238;	//  scala/xml/MetaData.hashCode:()I
const #240 = Asciz	scala/xml/MetaData$$anonfun$equals$1;
const #241 = class	#240;	//  scala/xml/MetaData$$anonfun$equals$1
const #242 = Asciz	(Lscala/xml/MetaData;Lscala/xml/MetaData;)V;
const #243 = NameAndType	#26:#242;//  "<init>":(Lscala/xml/MetaData;Lscala/xml/MetaData;)V
const #244 = Method	#241.#243;	//  scala/xml/MetaData$$anonfun$equals$1."<init>":(Lscala/xml/MetaData;Lscala/xml/MetaData;)V
const #245 = Asciz	forall;
const #246 = Asciz	(Lscala/Function1;)Z;
const #247 = NameAndType	#245:#246;//  forall:(Lscala/Function1;)Z
const #248 = InterfaceMethod	#74.#247;	//  scala/collection/IterableLike.forall:(Lscala/Function1;)Z
const #249 = Asciz	scala/MatchError;
const #250 = class	#249;	//  scala/MatchError
const #251 = Method	#30.#141;	//  java/lang/Object.toString:()Ljava/lang/String;
const #252 = Asciz	(Ljava/lang/String;)V;
const #253 = NameAndType	#26:#252;//  "<init>":(Ljava/lang/String;)V
const #254 = Method	#250.#253;	//  scala/MatchError."<init>":(Ljava/lang/String;)V
const #255 = Asciz	that;
const #256 = Asciz	temp5;
const #257 = Asciz	isPrefixed;
const #258 = Asciz	()Z;
const #259 = Asciz	(I)I;
const #260 = NameAndType	#215:#259;//  length:(I)I
const #261 = Method	#62.#260;	//  scala/xml/MetaData.length:(I)I
const #262 = Asciz	i;
const #263 = Asciz	hasNext;
const #264 = Asciz	scala/xml/Null$;
const #265 = class	#264;	//  scala/xml/Null$
const #266 = Asciz	Lscala/xml/Null$;;
const #267 = NameAndType	#8:#266;//  MODULE$:Lscala/xml/Null$;
const #268 = Field	#265.#267;	//  scala/xml/Null$.MODULE$:Lscala/xml/Null$;
const #269 = NameAndType	#236:#204;//  equals:(Ljava/lang/Object;)Z
const #270 = Method	#30.#269;	//  java/lang/Object.equals:(Ljava/lang/Object;)Z
const #271 = Asciz	getNamespace;
const #272 = Asciz	(Lscala/xml/Node;)Ljava/lang/String;;
const #273 = Asciz	containedIn1;
const #274 = NameAndType	#212:#213;//  equals1:(Lscala/xml/MetaData;)Z
const #275 = Method	#62.#274;	//  scala/xml/MetaData.equals1:(Lscala/xml/MetaData;)Z
const #276 = NameAndType	#273:#213;//  containedIn1:(Lscala/xml/MetaData;)Z
const #277 = Method	#62.#276;	//  scala/xml/MetaData.containedIn1:(Lscala/xml/MetaData;)Z
const #278 = Asciz	m;
const #279 = Asciz	(Ljava/lang/String;Lscala/xml/NamespaceBinding;Ljava/lang/String;)Lscala/collection/Seq<Lscala/xml/Node;>;;
const #280 = Asciz	(Ljava/lang/String;Lscala/xml/Node;Ljava/lang/String;)Lscala/collection/Seq;;
const #281 = Asciz	namespace_uri;
const #282 = Asciz	(Ljava/lang/String;Lscala/xml/Node;Ljava/lang/String;)Lscala/collection/Seq<Lscala/xml/Node;>;;
const #283 = Asciz	(Ljava/lang/String;)Lscala/collection/Seq<Lscala/xml/Node;>;;
const #284 = Asciz	updates;
const #285 = Asciz	append$default$2;
const #286 = Asciz	scala/xml/TopScope$;
const #287 = class	#286;	//  scala/xml/TopScope$
const #288 = Asciz	Lscala/xml/TopScope$;;
const #289 = NameAndType	#8:#288;//  MODULE$:Lscala/xml/TopScope$;
const #290 = Field	#287.#289;	//  scala/xml/TopScope$.MODULE$:Lscala/xml/TopScope$;
const #291 = Asciz	withFilter;
const #292 = Asciz	(Lscala/Function1;)Lscala/collection/TraversableLike$WithFilter;;
const #293 = Asciz	(Lscala/collection/TraversableLike;Lscala/Function1;)Lscala/collection/TraversableLike$WithFilter;;
const #294 = NameAndType	#291:#293;//  withFilter:(Lscala/collection/TraversableLike;Lscala/Function1;)Lscala/collection/TraversableLike$WithFilter;
const #295 = Method	#34.#294;	//  scala/collection/TraversableLike$class.withFilter:(Lscala/collection/TraversableLike;Lscala/Function1;)Lscala/collection/TraversableLike$WithFilter;
const #296 = Asciz	stringPrefix;
const #297 = Asciz	(Lscala/collection/TraversableLike;)Ljava/lang/String;;
const #298 = NameAndType	#296:#297;//  stringPrefix:(Lscala/collection/TraversableLike;)Ljava/lang/String;
const #299 = Method	#34.#298;	//  scala/collection/TraversableLike$class.stringPrefix:(Lscala/collection/TraversableLike;)Ljava/lang/String;
const #300 = Asciz	addString;
const #301 = Asciz	(Lscala/collection/TraversableLike;Lscala/collection/mutable/StringBuilder;)Lscala/collection/mutable/StringBuilder;;
const #302 = NameAndType	#300:#301;//  addString:(Lscala/collection/TraversableLike;Lscala/collection/mutable/StringBuilder;)Lscala/collection/mutable/StringBuilder;
const #303 = Method	#34.#302;	//  scala/collection/TraversableLike$class.addString:(Lscala/collection/TraversableLike;Lscala/collection/mutable/StringBuilder;)Lscala/collection/mutable/StringBuilder;
const #304 = Asciz	b;
const #305 = Asciz	(Lscala/collection/mutable/StringBuilder;Ljava/lang/String;)Lscala/collection/mutable/StringBuilder;;
const #306 = Asciz	(Lscala/collection/TraversableLike;Lscala/collection/mutable/StringBuilder;Ljava/lang/String;)Lscala/collection/mutable/StringBuilder;;
const #307 = NameAndType	#300:#306;//  addString:(Lscala/collection/TraversableLike;Lscala/collection/mutable/StringBuilder;Ljava/lang/String;)Lscala/collection/mutable/StringBuilder;
const #308 = Method	#34.#307;	//  scala/collection/TraversableLike$class.addString:(Lscala/collection/TraversableLike;Lscala/collection/mutable/StringBuilder;Ljava/lang/String;)Lscala/collection/mutable/StringBuilder;
const #309 = Asciz	sep;
const #310 = Asciz	(Lscala/collection/mutable/StringBuilder;Ljava/lang/String;Ljava/lang/String;Ljava/lang/String;)Lscala/collection/mutable/StringBuilder;;
const #311 = Asciz	(Lscala/collection/TraversableLike;Lscala/collection/mutable/StringBuilder;Ljava/lang/String;Ljava/lang/String;Ljava/lang/String;)Lscala/collection/mutable/StringBuilder;;
const #312 = NameAndType	#300:#311;//  addString:(Lscala/collection/TraversableLike;Lscala/collection/mutable/StringBuilder;Ljava/lang/String;Ljava/lang/String;Ljava/lang/String;)Lscala/collection/mutable/StringBuilder;
const #313 = Method	#34.#312;	//  scala/collection/TraversableLike$class.addString:(Lscala/collection/TraversableLike;Lscala/collection/mutable/StringBuilder;Ljava/lang/String;Ljava/lang/String;Ljava/lang/String;)Lscala/collection/mutable/StringBuilder;
const #314 = Asciz	start;
const #315 = Asciz	end;
const #316 = Asciz	mkString;
const #317 = NameAndType	#316:#297;//  mkString:(Lscala/collection/TraversableLike;)Ljava/lang/String;
const #318 = Method	#34.#317;	//  scala/collection/TraversableLike$class.mkString:(Lscala/collection/TraversableLike;)Ljava/lang/String;
const #319 = Asciz	(Ljava/lang/String;)Ljava/lang/String;;
const #320 = Asciz	(Lscala/collection/TraversableLike;Ljava/lang/String;)Ljava/lang/String;;
const #321 = NameAndType	#316:#320;//  mkString:(Lscala/collection/TraversableLike;Ljava/lang/String;)Ljava/lang/String;
const #322 = Method	#34.#321;	//  scala/collection/TraversableLike$class.mkString:(Lscala/collection/TraversableLike;Ljava/lang/String;)Ljava/lang/String;
const #323 = Asciz	(Ljava/lang/String;Ljava/lang/String;Ljava/lang/String;)Ljava/lang/String;;
const #324 = Asciz	(Lscala/collection/TraversableLike;Ljava/lang/String;Ljava/lang/String;Ljava/lang/String;)Ljava/lang/String;;
const #325 = NameAndType	#316:#324;//  mkString:(Lscala/collection/TraversableLike;Ljava/lang/String;Ljava/lang/String;Ljava/lang/String;)Ljava/lang/String;
const #326 = Method	#34.#325;	//  scala/collection/TraversableLike$class.mkString:(Lscala/collection/TraversableLike;Ljava/lang/String;Ljava/lang/String;Ljava/lang/String;)Ljava/lang/String;
const #327 = Asciz	toSet;
const #328 = Asciz	()Lscala/collection/immutable/Set;;
const #329 = Asciz	(Lscala/collection/TraversableLike;)Lscala/collection/immutable/Set;;
const #330 = NameAndType	#327:#329;//  toSet:(Lscala/collection/TraversableLike;)Lscala/collection/immutable/Set;
const #331 = Method	#34.#330;	//  scala/collection/TraversableLike$class.toSet:(Lscala/collection/TraversableLike;)Lscala/collection/immutable/Set;
const #332 = Asciz	toIndexedSeq;
const #333 = Asciz	()Lscala/collection/mutable/IndexedSeq;;
const #334 = Asciz	(Lscala/collection/TraversableLike;)Lscala/collection/mutable/IndexedSeq;;
const #335 = NameAndType	#332:#334;//  toIndexedSeq:(Lscala/collection/TraversableLike;)Lscala/collection/mutable/IndexedSeq;
const #336 = Method	#34.#335;	//  scala/collection/TraversableLike$class.toIndexedSeq:(Lscala/collection/TraversableLike;)Lscala/collection/mutable/IndexedSeq;
const #337 = Asciz	toSeq;
const #338 = Asciz	(Lscala/collection/TraversableLike;)Lscala/collection/Seq;;
const #339 = NameAndType	#337:#338;//  toSeq:(Lscala/collection/TraversableLike;)Lscala/collection/Seq;
const #340 = Method	#34.#339;	//  scala/collection/TraversableLike$class.toSeq:(Lscala/collection/TraversableLike;)Lscala/collection/Seq;
const #341 = Asciz	(Lscala/collection/TraversableLike;)Lscala/collection/immutable/List;;
const #342 = NameAndType	#187:#341;//  toList:(Lscala/collection/TraversableLike;)Lscala/collection/immutable/List;
const #343 = Method	#34.#342;	//  scala/collection/TraversableLike$class.toList:(Lscala/collection/TraversableLike;)Lscala/collection/immutable/List;
const #344 = Asciz	toArray;
const #345 = Asciz	(Lscala/reflect/ClassManifest;)Ljava/lang/Object;;
const #346 = Asciz	(Lscala/collection/TraversableLike;Lscala/reflect/ClassManifest;)Ljava/lang/Object;;
const #347 = NameAndType	#344:#346;//  toArray:(Lscala/collection/TraversableLike;Lscala/reflect/ClassManifest;)Ljava/lang/Object;
const #348 = Method	#34.#347;	//  scala/collection/TraversableLike$class.toArray:(Lscala/collection/TraversableLike;Lscala/reflect/ClassManifest;)Ljava/lang/Object;
const #349 = Asciz	evidence$1;
const #350 = Asciz	Lscala/reflect/ClassManifest;;
const #351 = Asciz	copyToArray;
const #352 = Asciz	(Ljava/lang/Object;)V;
const #353 = Asciz	(Lscala/collection/TraversableLike;Ljava/lang/Object;)V;
const #354 = NameAndType	#351:#353;//  copyToArray:(Lscala/collection/TraversableLike;Ljava/lang/Object;)V
const #355 = Method	#34.#354;	//  scala/collection/TraversableLike$class.copyToArray:(Lscala/collection/TraversableLike;Ljava/lang/Object;)V
const #356 = Asciz	xs;
const #357 = Asciz	(Ljava/lang/Object;I)V;
const #358 = Asciz	(Lscala/collection/TraversableLike;Ljava/lang/Object;I)V;
const #359 = NameAndType	#351:#358;//  copyToArray:(Lscala/collection/TraversableLike;Ljava/lang/Object;I)V
const #360 = Method	#34.#359;	//  scala/collection/TraversableLike$class.copyToArray:(Lscala/collection/TraversableLike;Ljava/lang/Object;I)V
const #361 = Asciz	copyToBuffer;
const #362 = Asciz	(Lscala/collection/mutable/Buffer;)V;
const #363 = Asciz	(Lscala/collection/TraversableLike;Lscala/collection/mutable/Buffer;)V;
const #364 = NameAndType	#361:#363;//  copyToBuffer:(Lscala/collection/TraversableLike;Lscala/collection/mutable/Buffer;)V
const #365 = Method	#34.#364;	//  scala/collection/TraversableLike$class.copyToBuffer:(Lscala/collection/TraversableLike;Lscala/collection/mutable/Buffer;)V
const #366 = Asciz	dest;
const #367 = Asciz	Lscala/collection/mutable/Buffer;;
const #368 = Asciz	splitAt;
const #369 = Asciz	(I)Lscala/Tuple2;;
const #370 = Asciz	(Lscala/collection/TraversableLike;I)Lscala/Tuple2;;
const #371 = NameAndType	#368:#370;//  splitAt:(Lscala/collection/TraversableLike;I)Lscala/Tuple2;
const #372 = Method	#34.#371;	//  scala/collection/TraversableLike$class.splitAt:(Lscala/collection/TraversableLike;I)Lscala/Tuple2;
const #373 = Asciz	n;
const #374 = Asciz	span;
const #375 = Asciz	(Lscala/Function1;)Lscala/Tuple2;;
const #376 = Asciz	(Lscala/collection/TraversableLike;Lscala/Function1;)Lscala/Tuple2;;
const #377 = NameAndType	#374:#376;//  span:(Lscala/collection/TraversableLike;Lscala/Function1;)Lscala/Tuple2;
const #378 = Method	#34.#377;	//  scala/collection/TraversableLike$class.span:(Lscala/collection/TraversableLike;Lscala/Function1;)Lscala/Tuple2;
const #379 = Asciz	dropWhile;
const #380 = Asciz	(Lscala/collection/TraversableLike;Lscala/Function1;)Ljava/lang/Object;;
const #381 = NameAndType	#379:#380;//  dropWhile:(Lscala/collection/TraversableLike;Lscala/Function1;)Ljava/lang/Object;
const #382 = Method	#34.#381;	//  scala/collection/TraversableLike$class.dropWhile:(Lscala/collection/TraversableLike;Lscala/Function1;)Ljava/lang/Object;
const #383 = Asciz	drop;
const #384 = Asciz	(I)Ljava/lang/Object;;
const #385 = Asciz	(Lscala/collection/TraversableLike;I)Ljava/lang/Object;;
const #386 = NameAndType	#383:#385;//  drop:(Lscala/collection/TraversableLike;I)Ljava/lang/Object;
const #387 = Method	#34.#386;	//  scala/collection/TraversableLike$class.drop:(Lscala/collection/TraversableLike;I)Ljava/lang/Object;
const #388 = Asciz	init;
const #389 = Asciz	()Ljava/lang/Object;;
const #390 = Asciz	(Lscala/collection/TraversableLike;)Ljava/lang/Object;;
const #391 = NameAndType	#388:#390;//  init:(Lscala/collection/TraversableLike;)Ljava/lang/Object;
const #392 = Method	#34.#391;	//  scala/collection/TraversableLike$class.init:(Lscala/collection/TraversableLike;)Ljava/lang/Object;
const #393 = Asciz	lastOption;
const #394 = Asciz	()Lscala/Option;;
const #395 = Asciz	(Lscala/collection/TraversableLike;)Lscala/Option;;
const #396 = NameAndType	#393:#395;//  lastOption:(Lscala/collection/TraversableLike;)Lscala/Option;
const #397 = Method	#34.#396;	//  scala/collection/TraversableLike$class.lastOption:(Lscala/collection/TraversableLike;)Lscala/Option;
const #398 = Asciz	last;
const #399 = NameAndType	#398:#390;//  last:(Lscala/collection/TraversableLike;)Ljava/lang/Object;
const #400 = Method	#34.#399;	//  scala/collection/TraversableLike$class.last:(Lscala/collection/TraversableLike;)Ljava/lang/Object;
const #401 = Asciz	tail;
const #402 = NameAndType	#401:#390;//  tail:(Lscala/collection/TraversableLike;)Ljava/lang/Object;
const #403 = Method	#34.#402;	//  scala/collection/TraversableLike$class.tail:(Lscala/collection/TraversableLike;)Ljava/lang/Object;
const #404 = Asciz	headOption;
const #405 = NameAndType	#404:#395;//  headOption:(Lscala/collection/TraversableLike;)Lscala/Option;
const #406 = Method	#34.#405;	//  scala/collection/TraversableLike$class.headOption:(Lscala/collection/TraversableLike;)Lscala/Option;
const #407 = Asciz	max;
const #408 = Asciz	(Lscala/math/Ordering;)Ljava/lang/Object;;
const #409 = Asciz	(Lscala/collection/TraversableLike;Lscala/math/Ordering;)Ljava/lang/Object;;
const #410 = NameAndType	#407:#409;//  max:(Lscala/collection/TraversableLike;Lscala/math/Ordering;)Ljava/lang/Object;
const #411 = Method	#34.#410;	//  scala/collection/TraversableLike$class.max:(Lscala/collection/TraversableLike;Lscala/math/Ordering;)Ljava/lang/Object;
const #412 = Asciz	cmp;
const #413 = Asciz	Lscala/math/Ordering;;
const #414 = Asciz	min;
const #415 = NameAndType	#414:#409;//  min:(Lscala/collection/TraversableLike;Lscala/math/Ordering;)Ljava/lang/Object;
const #416 = Method	#34.#415;	//  scala/collection/TraversableLike$class.min:(Lscala/collection/TraversableLike;Lscala/math/Ordering;)Ljava/lang/Object;
const #417 = Asciz	product;
const #418 = Asciz	(Lscala/math/Numeric;)Ljava/lang/Object;;
const #419 = Asciz	(Lscala/collection/TraversableLike;Lscala/math/Numeric;)Ljava/lang/Object;;
const #420 = NameAndType	#417:#419;//  product:(Lscala/collection/TraversableLike;Lscala/math/Numeric;)Ljava/lang/Object;
const #421 = Method	#34.#420;	//  scala/collection/TraversableLike$class.product:(Lscala/collection/TraversableLike;Lscala/math/Numeric;)Ljava/lang/Object;
const #422 = Asciz	num;
const #423 = Asciz	Lscala/math/Numeric;;
const #424 = Asciz	sum;
const #425 = NameAndType	#424:#419;//  sum:(Lscala/collection/TraversableLike;Lscala/math/Numeric;)Ljava/lang/Object;
const #426 = Method	#34.#425;	//  scala/collection/TraversableLike$class.sum:(Lscala/collection/TraversableLike;Lscala/math/Numeric;)Ljava/lang/Object;
const #427 = Asciz	reduceRightOption;
const #428 = Asciz	(Lscala/Function2;)Lscala/Option;;
const #429 = Asciz	(Lscala/collection/TraversableLike;Lscala/Function2;)Lscala/Option;;
const #430 = NameAndType	#427:#429;//  reduceRightOption:(Lscala/collection/TraversableLike;Lscala/Function2;)Lscala/Option;
const #431 = Method	#34.#430;	//  scala/collection/TraversableLike$class.reduceRightOption:(Lscala/collection/TraversableLike;Lscala/Function2;)Lscala/Option;
const #432 = Asciz	op;
const #433 = Asciz	Lscala/Function2;;
const #434 = Asciz	reduceLeftOption;
const #435 = NameAndType	#434:#429;//  reduceLeftOption:(Lscala/collection/TraversableLike;Lscala/Function2;)Lscala/Option;
const #436 = Method	#34.#435;	//  scala/collection/TraversableLike$class.reduceLeftOption:(Lscala/collection/TraversableLike;Lscala/Function2;)Lscala/Option;
const #437 = Asciz	reduceLeft;
const #438 = Asciz	(Lscala/Function2;)Ljava/lang/Object;;
const #439 = Asciz	(Lscala/collection/TraversableLike;Lscala/Function2;)Ljava/lang/Object;;
const #440 = NameAndType	#437:#439;//  reduceLeft:(Lscala/collection/TraversableLike;Lscala/Function2;)Ljava/lang/Object;
const #441 = Method	#34.#440;	//  scala/collection/TraversableLike$class.reduceLeft:(Lscala/collection/TraversableLike;Lscala/Function2;)Ljava/lang/Object;
const #442 = Asciz	$colon$bslash;
const #443 = Asciz	(Ljava/lang/Object;Lscala/Function2;)Ljava/lang/Object;;
const #444 = Asciz	(Lscala/collection/TraversableLike;Ljava/lang/Object;Lscala/Function2;)Ljava/lang/Object;;
const #445 = NameAndType	#442:#444;//  $colon$bslash:(Lscala/collection/TraversableLike;Ljava/lang/Object;Lscala/Function2;)Ljava/lang/Object;
const #446 = Method	#34.#445;	//  scala/collection/TraversableLike$class.$colon$bslash:(Lscala/collection/TraversableLike;Ljava/lang/Object;Lscala/Function2;)Ljava/lang/Object;
const #447 = Asciz	z;
const #448 = Asciz	$div$colon;
const #449 = NameAndType	#448:#444;//  $div$colon:(Lscala/collection/TraversableLike;Ljava/lang/Object;Lscala/Function2;)Ljava/lang/Object;
const #450 = Method	#34.#449;	//  scala/collection/TraversableLike$class.$div$colon:(Lscala/collection/TraversableLike;Ljava/lang/Object;Lscala/Function2;)Ljava/lang/Object;
const #451 = Asciz	foldLeft;
const #452 = NameAndType	#451:#444;//  foldLeft:(Lscala/collection/TraversableLike;Ljava/lang/Object;Lscala/Function2;)Ljava/lang/Object;
const #453 = Method	#34.#452;	//  scala/collection/TraversableLike$class.foldLeft:(Lscala/collection/TraversableLike;Ljava/lang/Object;Lscala/Function2;)Ljava/lang/Object;
const #454 = Asciz	count;
const #455 = Asciz	(Lscala/Function1;)I;
const #456 = Asciz	(Lscala/collection/TraversableLike;Lscala/Function1;)I;
const #457 = NameAndType	#454:#456;//  count:(Lscala/collection/TraversableLike;Lscala/Function1;)I
const #458 = Method	#34.#457;	//  scala/collection/TraversableLike$class.count:(Lscala/collection/TraversableLike;Lscala/Function1;)I
const #459 = Asciz	groupBy;
const #460 = Asciz	(Lscala/Function1;)Lscala/collection/Map;;
const #461 = Asciz	(Lscala/collection/TraversableLike;Lscala/Function1;)Lscala/collection/Map;;
const #462 = NameAndType	#459:#461;//  groupBy:(Lscala/collection/TraversableLike;Lscala/Function1;)Lscala/collection/Map;
const #463 = Method	#34.#462;	//  scala/collection/TraversableLike$class.groupBy:(Lscala/collection/TraversableLike;Lscala/Function1;)Lscala/collection/Map;
const #464 = Asciz	partition;
const #465 = NameAndType	#464:#376;//  partition:(Lscala/collection/TraversableLike;Lscala/Function1;)Lscala/Tuple2;
const #466 = Method	#34.#465;	//  scala/collection/TraversableLike$class.partition:(Lscala/collection/TraversableLike;Lscala/Function1;)Lscala/Tuple2;
const #467 = Asciz	partialMap;
const #468 = Asciz	(Lscala/PartialFunction;Lscala/collection/generic/CanBuildFrom;)Ljava/lang/Object;;
const #469 = Asciz	(Lscala/collection/TraversableLike;Lscala/PartialFunction;Lscala/collection/generic/CanBuildFrom;)Ljava/lang/Object;;
const #470 = NameAndType	#467:#469;//  partialMap:(Lscala/collection/TraversableLike;Lscala/PartialFunction;Lscala/collection/generic/CanBuildFrom;)Ljava/lang/Object;
const #471 = Method	#34.#470;	//  scala/collection/TraversableLike$class.partialMap:(Lscala/collection/TraversableLike;Lscala/PartialFunction;Lscala/collection/generic/CanBuildFrom;)Ljava/lang/Object;
const #472 = Asciz	pf;
const #473 = Asciz	Lscala/PartialFunction;;
const #474 = Asciz	bf;
const #475 = Asciz	Lscala/collection/generic/CanBuildFrom;;
const #476 = Asciz	filterNot;
const #477 = NameAndType	#476:#380;//  filterNot:(Lscala/collection/TraversableLike;Lscala/Function1;)Ljava/lang/Object;
const #478 = Method	#34.#477;	//  scala/collection/TraversableLike$class.filterNot:(Lscala/collection/TraversableLike;Lscala/Function1;)Ljava/lang/Object;
const #479 = Asciz	flatMap;
const #480 = Asciz	(Lscala/Function1;Lscala/collection/generic/CanBuildFrom;)Ljava/lang/Object;;
const #481 = Asciz	(Lscala/collection/TraversableLike;Lscala/Function1;Lscala/collection/generic/CanBuildFrom;)Ljava/lang/Object;;
const #482 = NameAndType	#479:#481;//  flatMap:(Lscala/collection/TraversableLike;Lscala/Function1;Lscala/collection/generic/CanBuildFrom;)Ljava/lang/Object;
const #483 = Method	#34.#482;	//  scala/collection/TraversableLike$class.flatMap:(Lscala/collection/TraversableLike;Lscala/Function1;Lscala/collection/generic/CanBuildFrom;)Ljava/lang/Object;
const #484 = NameAndType	#176:#481;//  map:(Lscala/collection/TraversableLike;Lscala/Function1;Lscala/collection/generic/CanBuildFrom;)Ljava/lang/Object;
const #485 = Method	#34.#484;	//  scala/collection/TraversableLike$class.map:(Lscala/collection/TraversableLike;Lscala/Function1;Lscala/collection/generic/CanBuildFrom;)Ljava/lang/Object;
const #486 = Asciz	$plus$plus;
const #487 = Asciz	(Lscala/collection/Iterator;Lscala/collection/generic/CanBuildFrom;)Ljava/lang/Object;;
const #488 = Asciz	(Lscala/collection/TraversableLike;Lscala/collection/Iterator;Lscala/collection/generic/CanBuildFrom;)Ljava/lang/Object;;
const #489 = NameAndType	#486:#488;//  $plus$plus:(Lscala/collection/TraversableLike;Lscala/collection/Iterator;Lscala/collection/generic/CanBuildFrom;)Ljava/lang/Object;
const #490 = Method	#34.#489;	//  scala/collection/TraversableLike$class.$plus$plus:(Lscala/collection/TraversableLike;Lscala/collection/Iterator;Lscala/collection/generic/CanBuildFrom;)Ljava/lang/Object;
const #491 = Asciz	Lscala/collection/Iterator;;
const #492 = Asciz	(Lscala/collection/Traversable;Lscala/collection/generic/CanBuildFrom;)Ljava/lang/Object;;
const #493 = Asciz	(Lscala/collection/TraversableLike;Lscala/collection/Traversable;Lscala/collection/generic/CanBuildFrom;)Ljava/lang/Object;;
const #494 = NameAndType	#486:#493;//  $plus$plus:(Lscala/collection/TraversableLike;Lscala/collection/Traversable;Lscala/collection/generic/CanBuildFrom;)Ljava/lang/Object;
const #495 = Method	#34.#494;	//  scala/collection/TraversableLike$class.$plus$plus:(Lscala/collection/TraversableLike;Lscala/collection/Traversable;Lscala/collection/generic/CanBuildFrom;)Ljava/lang/Object;
const #496 = Asciz	Lscala/collection/Traversable;;
const #497 = Asciz	hasDefiniteSize;
const #498 = Asciz	(Lscala/collection/TraversableLike;)Z;
const #499 = NameAndType	#497:#498;//  hasDefiniteSize:(Lscala/collection/TraversableLike;)Z
const #500 = Method	#34.#499;	//  scala/collection/TraversableLike$class.hasDefiniteSize:(Lscala/collection/TraversableLike;)Z
const #501 = Asciz	nonEmpty;
const #502 = NameAndType	#501:#498;//  nonEmpty:(Lscala/collection/TraversableLike;)Z
const #503 = Method	#34.#502;	//  scala/collection/TraversableLike$class.nonEmpty:(Lscala/collection/TraversableLike;)Z
const #504 = NameAndType	#83:#390;//  repr:(Lscala/collection/TraversableLike;)Ljava/lang/Object;
const #505 = Method	#34.#504;	//  scala/collection/TraversableLike$class.repr:(Lscala/collection/TraversableLike;)Ljava/lang/Object;
const #506 = Asciz	transpose;
const #507 = Asciz	(Lscala/Function1;)Lscala/collection/Traversable;;
const #508 = Asciz	(Lscala/collection/generic/GenericTraversableTemplate;Lscala/Function1;)Lscala/collection/Traversable;;
const #509 = NameAndType	#506:#508;//  transpose:(Lscala/collection/generic/GenericTraversableTemplate;Lscala/Function1;)Lscala/collection/Traversable;
const #510 = Method	#40.#509;	//  scala/collection/generic/GenericTraversableTemplate$class.transpose:(Lscala/collection/generic/GenericTraversableTemplate;Lscala/Function1;)Lscala/collection/Traversable;
const #511 = Asciz	asTraversable;
const #512 = Asciz	flatten;
const #513 = NameAndType	#512:#508;//  flatten:(Lscala/collection/generic/GenericTraversableTemplate;Lscala/Function1;)Lscala/collection/Traversable;
const #514 = Method	#40.#513;	//  scala/collection/generic/GenericTraversableTemplate$class.flatten:(Lscala/collection/generic/GenericTraversableTemplate;Lscala/Function1;)Lscala/collection/Traversable;
const #515 = Asciz	unzip;
const #516 = Asciz	(Lscala/collection/generic/GenericTraversableTemplate;Lscala/Function1;)Lscala/Tuple2;;
const #517 = NameAndType	#515:#516;//  unzip:(Lscala/collection/generic/GenericTraversableTemplate;Lscala/Function1;)Lscala/Tuple2;
const #518 = Method	#40.#517;	//  scala/collection/generic/GenericTraversableTemplate$class.unzip:(Lscala/collection/generic/GenericTraversableTemplate;Lscala/Function1;)Lscala/Tuple2;
const #519 = Asciz	asPair;
const #520 = Asciz	genericBuilder;
const #521 = Asciz	()Lscala/collection/mutable/Builder;;
const #522 = Asciz	(Lscala/collection/generic/GenericTraversableTemplate;)Lscala/collection/mutable/Builder;;
const #523 = NameAndType	#520:#522;//  genericBuilder:(Lscala/collection/generic/GenericTraversableTemplate;)Lscala/collection/mutable/Builder;
const #524 = Method	#40.#523;	//  scala/collection/generic/GenericTraversableTemplate$class.genericBuilder:(Lscala/collection/generic/GenericTraversableTemplate;)Lscala/collection/mutable/Builder;
const #525 = Asciz	newBuilder;
const #526 = NameAndType	#525:#522;//  newBuilder:(Lscala/collection/generic/GenericTraversableTemplate;)Lscala/collection/mutable/Builder;
const #527 = Method	#40.#526;	//  scala/collection/generic/GenericTraversableTemplate$class.newBuilder:(Lscala/collection/generic/GenericTraversableTemplate;)Lscala/collection/mutable/Builder;
const #528 = Asciz	projection;
const #529 = Asciz	(Lscala/collection/IterableLike;)Ljava/lang/Object;;
const #530 = NameAndType	#528:#529;//  projection:(Lscala/collection/IterableLike;)Ljava/lang/Object;
const #531 = Method	#50.#530;	//  scala/collection/IterableLike$class.projection:(Lscala/collection/IterableLike;)Ljava/lang/Object;
const #532 = Asciz	Deprecated;
const #533 = Asciz	firstOption;
const #534 = Asciz	(Lscala/collection/IterableLike;)Lscala/Option;;
const #535 = NameAndType	#533:#534;//  firstOption:(Lscala/collection/IterableLike;)Lscala/Option;
const #536 = Method	#50.#535;	//  scala/collection/IterableLike$class.firstOption:(Lscala/collection/IterableLike;)Lscala/Option;
const #537 = Asciz	first;
const #538 = NameAndType	#537:#529;//  first:(Lscala/collection/IterableLike;)Ljava/lang/Object;
const #539 = Method	#50.#538;	//  scala/collection/IterableLike$class.first:(Lscala/collection/IterableLike;)Ljava/lang/Object;
const #540 = Asciz	(Lscala/collection/IterableLike;II)Lscala/collection/IterableView;;
const #541 = NameAndType	#85:#540;//  view:(Lscala/collection/IterableLike;II)Lscala/collection/IterableView;
const #542 = Method	#50.#541;	//  scala/collection/IterableLike$class.view:(Lscala/collection/IterableLike;II)Lscala/collection/IterableView;
const #543 = NameAndType	#85:#529;//  view:(Lscala/collection/IterableLike;)Ljava/lang/Object;
const #544 = Method	#50.#543;	//  scala/collection/IterableLike$class.view:(Lscala/collection/IterableLike;)Ljava/lang/Object;
const #545 = Asciz	canEqual;
const #546 = Asciz	(Lscala/collection/IterableLike;Ljava/lang/Object;)Z;
const #547 = NameAndType	#545:#546;//  canEqual:(Lscala/collection/IterableLike;Ljava/lang/Object;)Z
const #548 = Method	#50.#547;	//  scala/collection/IterableLike$class.canEqual:(Lscala/collection/IterableLike;Ljava/lang/Object;)Z
const #549 = Asciz	toStream;
const #550 = Asciz	()Lscala/collection/immutable/Stream;;
const #551 = Asciz	(Lscala/collection/IterableLike;)Lscala/collection/immutable/Stream;;
const #552 = NameAndType	#549:#551;//  toStream:(Lscala/collection/IterableLike;)Lscala/collection/immutable/Stream;
const #553 = Method	#50.#552;	//  scala/collection/IterableLike$class.toStream:(Lscala/collection/IterableLike;)Lscala/collection/immutable/Stream;
const #554 = Asciz	sameElements;
const #555 = Asciz	(Lscala/collection/Iterable;)Z;
const #556 = Asciz	(Lscala/collection/IterableLike;Lscala/collection/Iterable;)Z;
const #557 = NameAndType	#554:#556;//  sameElements:(Lscala/collection/IterableLike;Lscala/collection/Iterable;)Z
const #558 = Method	#50.#557;	//  scala/collection/IterableLike$class.sameElements:(Lscala/collection/IterableLike;Lscala/collection/Iterable;)Z
const #559 = Asciz	Lscala/collection/Iterable;;
const #560 = Asciz	zipWithIndex;
const #561 = Asciz	(Lscala/collection/generic/CanBuildFrom;)Ljava/lang/Object;;
const #562 = Asciz	(Lscala/collection/IterableLike;Lscala/collection/generic/CanBuildFrom;)Ljava/lang/Object;;
const #563 = NameAndType	#560:#562;//  zipWithIndex:(Lscala/collection/IterableLike;Lscala/collection/generic/CanBuildFrom;)Ljava/lang/Object;
const #564 = Method	#50.#563;	//  scala/collection/IterableLike$class.zipWithIndex:(Lscala/collection/IterableLike;Lscala/collection/generic/CanBuildFrom;)Ljava/lang/Object;
const #565 = Asciz	zipAll;
const #566 = Asciz	(Lscala/collection/Iterable;Ljava/lang/Object;Ljava/lang/Object;Lscala/collection/generic/CanBuildFrom;)Ljava/lang/Object;;
const #567 = Asciz	(Lscala/collection/IterableLike;Lscala/collection/Iterable;Ljava/lang/Object;Ljava/lang/Object;Lscala/collection/generic/CanBuildFrom;)Ljava/lang/Object;;
const #568 = NameAndType	#565:#567;//  zipAll:(Lscala/collection/IterableLike;Lscala/collection/Iterable;Ljava/lang/Object;Ljava/lang/Object;Lscala/collection/generic/CanBuildFrom;)Ljava/lang/Object;
const #569 = Method	#50.#568;	//  scala/collection/IterableLike$class.zipAll:(Lscala/collection/IterableLike;Lscala/collection/Iterable;Ljava/lang/Object;Ljava/lang/Object;Lscala/collection/generic/CanBuildFrom;)Ljava/lang/Object;
const #570 = Asciz	thisElem;
const #571 = Asciz	thatElem;
const #572 = Asciz	zip;
const #573 = Asciz	(Lscala/collection/Iterable;Lscala/collection/generic/CanBuildFrom;)Ljava/lang/Object;;
const #574 = Asciz	(Lscala/collection/IterableLike;Lscala/collection/Iterable;Lscala/collection/generic/CanBuildFrom;)Ljava/lang/Object;;
const #575 = NameAndType	#572:#574;//  zip:(Lscala/collection/IterableLike;Lscala/collection/Iterable;Lscala/collection/generic/CanBuildFrom;)Ljava/lang/Object;
const #576 = Method	#50.#575;	//  scala/collection/IterableLike$class.zip:(Lscala/collection/IterableLike;Lscala/collection/Iterable;Lscala/collection/generic/CanBuildFrom;)Ljava/lang/Object;
const #577 = Asciz	(Ljava/lang/Object;II)V;
const #578 = Asciz	(Lscala/collection/IterableLike;Ljava/lang/Object;II)V;
const #579 = NameAndType	#351:#578;//  copyToArray:(Lscala/collection/IterableLike;Ljava/lang/Object;II)V
const #580 = Method	#50.#579;	//  scala/collection/IterableLike$class.copyToArray:(Lscala/collection/IterableLike;Ljava/lang/Object;II)V
const #581 = Asciz	len;
const #582 = Asciz	dropRight;
const #583 = Asciz	(Lscala/collection/IterableLike;I)Ljava/lang/Object;;
const #584 = NameAndType	#582:#583;//  dropRight:(Lscala/collection/IterableLike;I)Ljava/lang/Object;
const #585 = Method	#50.#584;	//  scala/collection/IterableLike$class.dropRight:(Lscala/collection/IterableLike;I)Ljava/lang/Object;
const #586 = Asciz	takeRight;
const #587 = NameAndType	#586:#583;//  takeRight:(Lscala/collection/IterableLike;I)Ljava/lang/Object;
const #588 = Method	#50.#587;	//  scala/collection/IterableLike$class.takeRight:(Lscala/collection/IterableLike;I)Ljava/lang/Object;
const #589 = Asciz	(Lscala/collection/IterableLike;Lscala/Function1;)Ljava/lang/Object;;
const #590 = NameAndType	#231:#589;//  takeWhile:(Lscala/collection/IterableLike;Lscala/Function1;)Ljava/lang/Object;
const #591 = Method	#50.#590;	//  scala/collection/IterableLike$class.takeWhile:(Lscala/collection/IterableLike;Lscala/Function1;)Ljava/lang/Object;
const #592 = Asciz	slice;
const #593 = Asciz	(II)Ljava/lang/Object;;
const #594 = Asciz	(Lscala/collection/IterableLike;II)Ljava/lang/Object;;
const #595 = NameAndType	#592:#594;//  slice:(Lscala/collection/IterableLike;II)Ljava/lang/Object;
const #596 = Method	#50.#595;	//  scala/collection/IterableLike$class.slice:(Lscala/collection/IterableLike;II)Ljava/lang/Object;
const #597 = Asciz	take;
const #598 = NameAndType	#597:#583;//  take:(Lscala/collection/IterableLike;I)Ljava/lang/Object;
const #599 = Method	#50.#598;	//  scala/collection/IterableLike$class.take:(Lscala/collection/IterableLike;I)Ljava/lang/Object;
const #600 = Asciz	head;
const #601 = NameAndType	#600:#529;//  head:(Lscala/collection/IterableLike;)Ljava/lang/Object;
const #602 = Method	#50.#601;	//  scala/collection/IterableLike$class.head:(Lscala/collection/IterableLike;)Ljava/lang/Object;
const #603 = Asciz	toIterable;
const #604 = Asciz	(Lscala/collection/IterableLike;)Lscala/collection/Iterable;;
const #605 = NameAndType	#603:#604;//  toIterable:(Lscala/collection/IterableLike;)Lscala/collection/Iterable;
const #606 = Method	#50.#605;	//  scala/collection/IterableLike$class.toIterable:(Lscala/collection/IterableLike;)Lscala/collection/Iterable;
const #607 = Asciz	reduceRight;
const #608 = Asciz	(Lscala/collection/IterableLike;Lscala/Function2;)Ljava/lang/Object;;
const #609 = NameAndType	#607:#608;//  reduceRight:(Lscala/collection/IterableLike;Lscala/Function2;)Ljava/lang/Object;
const #610 = Method	#50.#609;	//  scala/collection/IterableLike$class.reduceRight:(Lscala/collection/IterableLike;Lscala/Function2;)Ljava/lang/Object;
const #611 = Asciz	foldRight;
const #612 = Asciz	(Lscala/collection/IterableLike;Ljava/lang/Object;Lscala/Function2;)Ljava/lang/Object;;
const #613 = NameAndType	#611:#612;//  foldRight:(Lscala/collection/IterableLike;Ljava/lang/Object;Lscala/Function2;)Ljava/lang/Object;
const #614 = Method	#50.#613;	//  scala/collection/IterableLike$class.foldRight:(Lscala/collection/IterableLike;Ljava/lang/Object;Lscala/Function2;)Ljava/lang/Object;
const #615 = Asciz	isEmpty;
const #616 = Asciz	(Lscala/collection/IterableLike;)Z;
const #617 = NameAndType	#615:#616;//  isEmpty:(Lscala/collection/IterableLike;)Z
const #618 = Method	#50.#617;	//  scala/collection/IterableLike$class.isEmpty:(Lscala/collection/IterableLike;)Z
const #619 = Asciz	find;
const #620 = Asciz	(Lscala/Function1;)Lscala/Option;;
const #621 = Asciz	(Lscala/collection/IterableLike;Lscala/Function1;)Lscala/Option;;
const #622 = NameAndType	#619:#621;//  find:(Lscala/collection/IterableLike;Lscala/Function1;)Lscala/Option;
const #623 = Method	#50.#622;	//  scala/collection/IterableLike$class.find:(Lscala/collection/IterableLike;Lscala/Function1;)Lscala/Option;
const #624 = Asciz	exists;
const #625 = Asciz	(Lscala/collection/IterableLike;Lscala/Function1;)Z;
const #626 = NameAndType	#624:#625;//  exists:(Lscala/collection/IterableLike;Lscala/Function1;)Z
const #627 = Method	#50.#626;	//  scala/collection/IterableLike$class.exists:(Lscala/collection/IterableLike;Lscala/Function1;)Z
const #628 = NameAndType	#245:#625;//  forall:(Lscala/collection/IterableLike;Lscala/Function1;)Z
const #629 = Method	#50.#628;	//  scala/collection/IterableLike$class.forall:(Lscala/collection/IterableLike;Lscala/Function1;)Z
const #630 = Asciz	foreach;
const #631 = Asciz	(Lscala/Function1;)V;
const #632 = Asciz	(Lscala/collection/IterableLike;Lscala/Function1;)V;
const #633 = NameAndType	#630:#632;//  foreach:(Lscala/collection/IterableLike;Lscala/Function1;)V
const #634 = Method	#50.#633;	//  scala/collection/IterableLike$class.foreach:(Lscala/collection/IterableLike;Lscala/Function1;)V
const #635 = Asciz	elements;
const #636 = Asciz	(Lscala/collection/IterableLike;)Lscala/collection/Iterator;;
const #637 = NameAndType	#635:#636;//  elements:(Lscala/collection/IterableLike;)Lscala/collection/Iterator;
const #638 = Method	#50.#637;	//  scala/collection/IterableLike$class.elements:(Lscala/collection/IterableLike;)Lscala/collection/Iterator;
const #639 = Asciz	(Lscala/collection/IterableLike;Ljava/lang/Object;)Lscala/collection/Iterable;;
const #640 = NameAndType	#78:#639;//  toCollection:(Lscala/collection/IterableLike;Ljava/lang/Object;)Lscala/collection/Iterable;
const #641 = Method	#50.#640;	//  scala/collection/IterableLike$class.toCollection:(Lscala/collection/IterableLike;Ljava/lang/Object;)Lscala/collection/Iterable;
const #642 = NameAndType	#71:#604;//  thisCollection:(Lscala/collection/IterableLike;)Lscala/collection/Iterable;
const #643 = Method	#50.#642;	//  scala/collection/IterableLike$class.thisCollection:(Lscala/collection/IterableLike;)Lscala/collection/Iterable;
const #644 = Asciz	companion;
const #645 = Asciz	()Lscala/collection/generic/GenericCompanion;;
const #646 = Asciz	(Lscala/collection/Iterable;)Lscala/collection/generic/GenericCompanion;;
const #647 = NameAndType	#644:#646;//  companion:(Lscala/collection/Iterable;)Lscala/collection/generic/GenericCompanion;
const #648 = Method	#55.#647;	//  scala/collection/Iterable$class.companion:(Lscala/collection/Iterable;)Lscala/collection/generic/GenericCompanion;
const #649 = Asciz	Ljava/lang/Object;Lscala/collection/Iterable<Lscala/xml/MetaData;>;Lscala/ScalaObject;;
const #650 = Asciz	ScalaSig;
const #651 = Asciz	InnerClasses;
const #652 = Asciz	$anon$11;
const #653 = Asciz	scala/collection/TraversableLike$WithFilter;
const #654 = class	#653;	//  scala/collection/TraversableLike$WithFilter
const #655 = Asciz	scala/collection/TraversableLike;
const #656 = class	#655;	//  scala/collection/TraversableLike
const #657 = Asciz	WithFilter;
const #658 = Asciz	$anonfun$equals$1;
const #659 = Asciz	$anonfun$iterator$2;
const #660 = Asciz	$anonfun$iterator$1;
const #661 = Asciz	$anonfun$toString$1;
const #662 = Asciz	$anonfun$toString1$1;
const #663 = Asciz	scala/collection/Iterable;
const #664 = class	#663;	//  scala/collection/Iterable
const #665 = Asciz	scala/ScalaObject;
const #666 = class	#665;	//  scala/ScalaObject
const #667 = Asciz	java/io/Serializable;
const #668 = class	#667;	//  java/io/Serializable

{
public static final scala.xml.MetaData update(scala.xml.MetaData, scala.xml.NamespaceBinding, scala.xml.MetaData);
  Code:
   Stack=4, Locals=3, Args_size=3
   0:	getstatic	#11; //Field scala/xml/MetaData$.MODULE$:Lscala/xml/MetaData$;
   3:	aload_0
   4:	aload_1
   5:	aload_2
   6:	invokevirtual	#13; //Method scala/xml/MetaData$.update:(Lscala/xml/MetaData;Lscala/xml/NamespaceBinding;Lscala/xml/MetaData;)Lscala/xml/MetaData;
   9:	areturn

public static final java.lang.String getUniversalKey(scala.xml.MetaData, scala.xml.NamespaceBinding);
  Code:
   Stack=3, Locals=2, Args_size=2
   0:	getstatic	#11; //Field scala/xml/MetaData$.MODULE$:Lscala/xml/MetaData$;
   3:	aload_0
   4:	aload_1
   5:	invokevirtual	#17; //Method scala/xml/MetaData$.getUniversalKey:(Lscala/xml/MetaData;Lscala/xml/NamespaceBinding;)Ljava/lang/String;
   8:	areturn

public static final scala.xml.MetaData normalize(scala.xml.MetaData, scala.xml.NamespaceBinding);
  Code:
   Stack=3, Locals=2, Args_size=2
   0:	getstatic	#11; //Field scala/xml/MetaData$.MODULE$:Lscala/xml/MetaData$;
   3:	aload_0
   4:	aload_1
   5:	invokevirtual	#21; //Method scala/xml/MetaData$.normalize:(Lscala/xml/MetaData;Lscala/xml/NamespaceBinding;)Lscala/xml/MetaData;
   8:	areturn

public static final scala.xml.MetaData concatenate(scala.xml.MetaData, scala.xml.MetaData);
  Code:
   Stack=3, Locals=2, Args_size=2
   0:	getstatic	#11; //Field scala/xml/MetaData$.MODULE$:Lscala/xml/MetaData$;
   3:	aload_0
   4:	aload_1
   5:	invokevirtual	#25; //Method scala/xml/MetaData$.concatenate:(Lscala/xml/MetaData;Lscala/xml/MetaData;)Lscala/xml/MetaData;
   8:	areturn

public scala.xml.MetaData();
  Code:
   Stack=1, Locals=1, Args_size=1
   0:	aload_0
   1:	invokespecial	#32; //Method java/lang/Object."<init>":()V
   4:	aload_0
   5:	invokestatic	#38; //Method scala/collection/TraversableLike$class.$init$:(Lscala/collection/TraversableLike;)V
   8:	aload_0
   9:	invokestatic	#43; //Method scala/collection/generic/GenericTraversableTemplate$class.$init$:(Lscala/collection/generic/GenericTraversableTemplate;)V
   12:	aload_0
   13:	invokestatic	#48; //Method scala/collection/Traversable$class.$init$:(Lscala/collection/Traversable;)V
   16:	aload_0
   17:	invokestatic	#53; //Method scala/collection/IterableLike$class.$init$:(Lscala/collection/IterableLike;)V
   20:	aload_0
   21:	invokestatic	#58; //Method scala/collection/Iterable$class.$init$:(Lscala/collection/Iterable;)V
   24:	return
  LineNumberTable: 
   line 80: 0


public java.lang.Object filter(scala.Function1);
  Code:
   Stack=2, Locals=2, Args_size=2
   0:	aload_0
   1:	aload_1
   2:	invokevirtual	#65; //Method filter:(Lscala/Function1;)Lscala/xml/MetaData;
   5:	areturn
  LineNumberTable: 
   line 80: 0

  LocalVariableTable: 
   Start  Length  Slot  Name   Signature
   0      6      0    this       Lscala/xml/MetaData;
   0      6      1    p       Lscala/Function1;


public scala.collection.Traversable thisCollection();
  Code:
   Stack=1, Locals=1, Args_size=1
   0:	aload_0
   1:	invokeinterface	#77,  1; //InterfaceMethod scala/collection/IterableLike.thisCollection:()Lscala/collection/Iterable;
   6:	areturn
  LineNumberTable: 
   line 80: 0


public scala.collection.Traversable toCollection(java.lang.Object);
  Code:
   Stack=2, Locals=2, Args_size=2
   0:	aload_0
   1:	aload_1
   2:	invokeinterface	#82,  2; //InterfaceMethod scala/collection/IterableLike.toCollection:(Ljava/lang/Object;)Lscala/collection/Iterable;
   7:	areturn
  LineNumberTable: 
   line 80: 0

  LocalVariableTable: 
   Start  Length  Slot  Name   Signature
   0      8      0    this       Lscala/xml/MetaData;
   0      8      1    repr       Ljava/lang/Object;


public scala.collection.TraversableView view(int, int);
  Code:
   Stack=3, Locals=3, Args_size=3
   0:	aload_0
   1:	iload_1
   2:	iload_2
   3:	invokeinterface	#89,  3; //InterfaceMethod scala/collection/IterableLike.view:(II)Lscala/collection/IterableView;
   8:	areturn
  LineNumberTable: 
   line 80: 0

  LocalVariableTable: 
   Start  Length  Slot  Name   Signature
   0      9      0    this       Lscala/xml/MetaData;
   0      9      1    from       I
   0      9      2    until       I


public final scala.xml.MetaData remove(java.lang.String, scala.xml.Node, java.lang.String);
  Code:
   Stack=4, Locals=4, Args_size=4
   0:	aload_0
   1:	aload_1
   2:	aload_2
   3:	invokevirtual	#100; //Method scala/xml/Node.scope:()Lscala/xml/NamespaceBinding;
   6:	aload_3
   7:	invokevirtual	#103; //Method remove:(Ljava/lang/String;Lscala/xml/NamespaceBinding;Ljava/lang/String;)Lscala/xml/MetaData;
   10:	areturn
  LineNumberTable: 
   line 243: 0

  LocalVariableTable: 
   Start  Length  Slot  Name   Signature
   0      11      0    this       Lscala/xml/MetaData;
   0      11      1    namespace       Ljava/lang/String;
   0      11      2    owner       Lscala/xml/Node;
   0      11      3    key       Ljava/lang/String;


public abstract scala.xml.MetaData remove(java.lang.String, scala.xml.NamespaceBinding, java.lang.String);

public abstract scala.xml.MetaData remove(java.lang.String);

public abstract boolean wellformed(scala.xml.NamespaceBinding);

public scala.collection.mutable.StringBuilder buildString(scala.collection.mutable.StringBuilder);
  Code:
   Stack=2, Locals=2, Args_size=2
   0:	aload_1
   1:	ldc	#114; //int 32
   3:	invokevirtual	#120; //Method scala/collection/mutable/StringBuilder.append:(C)Lscala/collection/mutable/StringBuilder;
   6:	pop
   7:	aload_0
   8:	aload_1
   9:	invokevirtual	#124; //Method toString1:(Lscala/collection/mutable/StringBuilder;)V
   12:	aload_0
   13:	invokevirtual	#128; //Method next:()Lscala/xml/MetaData;
   16:	aload_1
   17:	invokevirtual	#130; //Method buildString:(Lscala/collection/mutable/StringBuilder;)Lscala/collection/mutable/StringBuilder;
   20:	areturn
  LineNumberTable: 
   line 211: 0
   line 212: 7
   line 213: 12

  LocalVariableTable: 
   Start  Length  Slot  Name   Signature
   0      21      0    this       Lscala/xml/MetaData;
   0      21      1    sb       Lscala/collection/mutable/StringBuilder;


public java.lang.String toString();
  Code:
   Stack=2, Locals=3, Args_size=1
   0:	new	#136; //class scala/xml/MetaData$$anonfun$toString$1
   3:	dup
   4:	pop
   5:	aload_0
   6:	invokespecial	#139; //Method scala/xml/MetaData$$anonfun$toString$1."<init>":(Lscala/xml/MetaData;)V
   9:	new	#116; //class scala/collection/mutable/StringBuilder
   12:	dup
   13:	invokespecial	#140; //Method scala/collection/mutable/StringBuilder."<init>":()V
   16:	astore_2
   17:	aload_2
   18:	checkcast	#116; //class scala/collection/mutable/StringBuilder
   21:	astore_1
   22:	aload_0
   23:	aload_1
   24:	invokevirtual	#130; //Method buildString:(Lscala/collection/mutable/StringBuilder;)Lscala/collection/mutable/StringBuilder;
   27:	pop
   28:	aload_2
   29:	invokevirtual	#142; //Method scala/collection/mutable/StringBuilder.toString:()Ljava/lang/String;
   32:	areturn
  LineNumberTable: 
   line 208: 0

  LocalVariableTable: 
   Start  Length  Slot  Name   Signature
   0      33      0    this       Lscala/xml/MetaData;
   17      15      2    sb0       Lscala/collection/mutable/StringBuilder;


public abstract void toString1(scala.collection.mutable.StringBuilder);

public java.lang.String toString1();
  Code:
   Stack=2, Locals=3, Args_size=1
   0:	new	#145; //class scala/xml/MetaData$$anonfun$toString1$1
   3:	dup
   4:	pop
   5:	aload_0
   6:	invokespecial	#146; //Method scala/xml/MetaData$$anonfun$toString1$1."<init>":(Lscala/xml/MetaData;)V
   9:	new	#116; //class scala/collection/mutable/StringBuilder
   12:	dup
   13:	invokespecial	#140; //Method scala/collection/mutable/StringBuilder."<init>":()V
   16:	astore_2
   17:	aload_2
   18:	checkcast	#116; //class scala/collection/mutable/StringBuilder
   21:	astore_1
   22:	aload_0
   23:	aload_1
   24:	invokevirtual	#124; //Method toString1:(Lscala/collection/mutable/StringBuilder;)V
   27:	aload_2
   28:	invokevirtual	#142; //Method scala/collection/mutable/StringBuilder.toString:()Ljava/lang/String;
   31:	areturn
  LineNumberTable: 
   line 203: 0

  LocalVariableTable: 
   Start  Length  Slot  Name   Signature
   0      32      0    this       Lscala/xml/MetaData;
   17      14      2    sb0       Lscala/collection/mutable/StringBuilder;


public abstract int hashCode();

public final scala.Option get(java.lang.String, scala.xml.NamespaceBinding, java.lang.String);
  Code:
   Stack=5, Locals=4, Args_size=4
   0:	getstatic	#155; //Field scala/Option$.MODULE$:Lscala/Option$;
   3:	aload_0
   4:	aload_1
   5:	aload_2
   6:	aload_3
   7:	invokevirtual	#159; //Method apply:(Ljava/lang/String;Lscala/xml/NamespaceBinding;Ljava/lang/String;)Lscala/collection/Seq;
   10:	invokevirtual	#162; //Method scala/Option$.apply:(Ljava/lang/Object;)Lscala/Option;
   13:	areturn
  LineNumberTable: 
   line 199: 0

  LocalVariableTable: 
   Start  Length  Slot  Name   Signature
   0      14      0    this       Lscala/xml/MetaData;
   0      14      1    uri       Ljava/lang/String;
   0      14      2    scope       Lscala/xml/NamespaceBinding;
   0      14      3    key       Ljava/lang/String;

  Signature: length = 0x2
   00 FFFFFFA5 

public final scala.Option get(java.lang.String, scala.xml.Node, java.lang.String);
  Code:
   Stack=4, Locals=4, Args_size=4
   0:	aload_0
   1:	aload_1
   2:	aload_2
   3:	invokevirtual	#100; //Method scala/xml/Node.scope:()Lscala/xml/NamespaceBinding;
   6:	aload_3
   7:	invokevirtual	#169; //Method get:(Ljava/lang/String;Lscala/xml/NamespaceBinding;Ljava/lang/String;)Lscala/Option;
   10:	areturn
  LineNumberTable: 
   line 189: 0

  LocalVariableTable: 
   Start  Length  Slot  Name   Signature
   0      11      0    this       Lscala/xml/MetaData;
   0      11      1    uri       Ljava/lang/String;
   0      11      2    owner       Lscala/xml/Node;
   0      11      3    key       Ljava/lang/String;

  Signature: length = 0x2
   00 FFFFFFAA 

public final scala.Option get(java.lang.String);
  Code:
   Stack=3, Locals=2, Args_size=2
   0:	getstatic	#155; //Field scala/Option$.MODULE$:Lscala/Option$;
   3:	aload_0
   4:	aload_1
   5:	invokevirtual	#174; //Method apply:(Ljava/lang/String;)Lscala/collection/Seq;
   8:	invokevirtual	#162; //Method scala/Option$.apply:(Ljava/lang/Object;)Lscala/Option;
   11:	areturn
  LineNumberTable: 
   line 185: 0

  LocalVariableTable: 
   Start  Length  Slot  Name   Signature
   0      12      0    this       Lscala/xml/MetaData;
   0      12      1    key       Ljava/lang/String;

  Signature: length = 0x2
   00 FFFFFFAF 

public abstract scala.xml.MetaData next();

public scala.collection.immutable.List map(scala.Function1);
  Code:
   Stack=2, Locals=2, Args_size=2
   0:	aload_0
   1:	invokevirtual	#181; //Method iterator:()Lscala/collection/Iterator;
   4:	aload_1
   5:	invokeinterface	#186,  2; //InterfaceMethod scala/collection/Iterator.map:(Lscala/Function1;)Lscala/collection/Iterator;
   10:	invokeinterface	#190,  1; //InterfaceMethod scala/collection/Iterator.toList:()Lscala/collection/immutable/List;
   15:	areturn
  LineNumberTable: 
   line 174: 0

  LocalVariableTable: 
   Start  Length  Slot  Name   Signature
   0      16      0    this       Lscala/xml/MetaData;
   0      16      1    f       Lscala/Function1;

  Signature: length = 0x2
   00 FFFFFFC0 

public abstract scala.collection.Seq value();
  Signature: length = 0x2
   00 FFFFFFC3 

public abstract java.lang.String key();

public scala.xml.MetaData filter(scala.Function1);
  Code:
   Stack=3, Locals=2, Args_size=2
   0:	aload_1
   1:	aload_0
   2:	invokeinterface	#200,  2; //InterfaceMethod scala/Function1.apply:(Ljava/lang/Object;)Ljava/lang/Object;
   7:	invokestatic	#206; //Method scala/runtime/BoxesRunTime.unboxToBoolean:(Ljava/lang/Object;)Z
   10:	ifeq	28
   13:	aload_0
   14:	aload_0
   15:	invokevirtual	#128; //Method next:()Lscala/xml/MetaData;
   18:	aload_1
   19:	invokevirtual	#65; //Method filter:(Lscala/Function1;)Lscala/xml/MetaData;
   22:	invokevirtual	#210; //Method copy:(Lscala/xml/MetaData;)Lscala/xml/MetaData;
   25:	goto	36
   28:	aload_0
   29:	invokevirtual	#128; //Method next:()Lscala/xml/MetaData;
   32:	aload_1
   33:	invokevirtual	#65; //Method filter:(Lscala/Function1;)Lscala/xml/MetaData;
   36:	areturn
  LineNumberTable: 
   line 164: 0
   line 165: 28
   line 164: 36

  LocalVariableTable: 
   Start  Length  Slot  Name   Signature
   0      37      0    this       Lscala/xml/MetaData;
   0      37      1    f       Lscala/Function1;

  Signature: length = 0x2
   00 FFFFFFD3 

public abstract boolean equals1(scala.xml.MetaData);

public int size();
  Code:
   Stack=2, Locals=1, Args_size=1
   0:	iconst_1
   1:	aload_0
   2:	invokevirtual	#181; //Method iterator:()Lscala/collection/Iterator;
   5:	invokeinterface	#217,  1; //InterfaceMethod scala/collection/Iterator.length:()I
   10:	iadd
   11:	ireturn
  LineNumberTable: 
   line 157: 0


public scala.collection.Iterator iterator();
  Code:
   Stack=4, Locals=4, Args_size=1
   0:	new	#219; //class scala/xml/MetaData$$anonfun$iterator$1
   3:	dup
   4:	aload_0
   5:	invokespecial	#220; //Method scala/xml/MetaData$$anonfun$iterator$1."<init>":(Lscala/xml/MetaData;)V
   8:	astore_1
   9:	new	#222; //class scala/collection/Iterator$$anon$11
   12:	dup
   13:	aload_0
   14:	aload_1
   15:	invokespecial	#225; //Method scala/collection/Iterator$$anon$11."<init>":(Ljava/lang/Object;Lscala/Function1;)V
   18:	new	#227; //class scala/xml/MetaData$$anonfun$iterator$2
   21:	dup
   22:	aload_0
   23:	invokespecial	#228; //Method scala/xml/MetaData$$anonfun$iterator$2."<init>":(Lscala/xml/MetaData;)V
   26:	astore_3
   27:	astore_2
   28:	aload_2
   29:	aload_3
   30:	invokestatic	#234; //Method scala/collection/Iterator$class.takeWhile:(Lscala/collection/Iterator;Lscala/Function1;)Lscala/collection/Iterator;
   33:	areturn
  LineNumberTable: 
   line 156: 0

  LocalVariableTable: 
   Start  Length  Slot  Name   Signature
   0      34      0    this       Lscala/xml/MetaData;

  Signature: length = 0x2
   00 FFFFFFEB 

public boolean equals(java.lang.Object);
  Code:
   Stack=5, Locals=3, Args_size=2
   0:	aload_1
   1:	instanceof	#62; //class scala/xml/MetaData
   4:	ifeq	76
   7:	aload_1
   8:	checkcast	#62; //class scala/xml/MetaData
   11:	astore_2
   12:	iconst_1
   13:	ifeq	64
   16:	aload_0
   17:	invokevirtual	#237; //Method length:()I
   20:	aload_2
   21:	invokevirtual	#237; //Method length:()I
   24:	if_icmpne	60
   27:	aload_0
   28:	invokevirtual	#239; //Method hashCode:()I
   31:	aload_2
   32:	invokevirtual	#239; //Method hashCode:()I
   35:	if_icmpne	60
   38:	aload_0
   39:	new	#241; //class scala/xml/MetaData$$anonfun$equals$1
   42:	dup
   43:	aload_0
   44:	aload_2
   45:	invokespecial	#244; //Method scala/xml/MetaData$$anonfun$equals$1."<init>":(Lscala/xml/MetaData;Lscala/xml/MetaData;)V
   48:	invokeinterface	#248,  2; //InterfaceMethod scala/collection/IterableLike.forall:(Lscala/Function1;)Z
   53:	ifeq	60
   56:	iconst_1
   57:	goto	81
   60:	iconst_0
   61:	goto	81
   64:	new	#250; //class scala/MatchError
   67:	dup
   68:	aload_1
   69:	invokevirtual	#251; //Method java/lang/Object.toString:()Ljava/lang/String;
   72:	invokespecial	#254; //Method scala/MatchError."<init>":(Ljava/lang/String;)V
   75:	athrow
   76:	iconst_1
   77:	ifeq	82
   80:	iconst_0
   81:	ireturn
   82:	new	#250; //class scala/MatchError
   85:	dup
   86:	aload_1
   87:	invokevirtual	#251; //Method java/lang/Object.toString:()Ljava/lang/String;
   90:	invokespecial	#254; //Method scala/MatchError."<init>":(Ljava/lang/String;)V
   93:	athrow
  LineNumberTable: 
   line 147: 0
   line 21: 12
   line 149: 16
   line 150: 27
   line 151: 38
   line 150: 56
   line 147: 64
   line 21: 76
   line 152: 80
   line 147: 81

  LocalVariableTable: 
   Start  Length  Slot  Name   Signature
   0      94      0    this       Lscala/xml/MetaData;
   0      94      1    that       Ljava/lang/Object;
   12      64      2    temp5       Lscala/xml/MetaData;


public abstract boolean isPrefixed();

public int length(int);
  Code:
   Stack=3, Locals=2, Args_size=2
   0:	aload_0
   1:	invokevirtual	#128; //Method next:()Lscala/xml/MetaData;
   4:	iload_1
   5:	iconst_1
   6:	iadd
   7:	invokevirtual	#261; //Method length:(I)I
   10:	ireturn
  LineNumberTable: 
   line 142: 0

  LocalVariableTable: 
   Start  Length  Slot  Name   Signature
   0      11      0    this       Lscala/xml/MetaData;
   0      11      1    i       I


public int length();
  Code:
   Stack=2, Locals=1, Args_size=1
   0:	aload_0
   1:	iconst_0
   2:	invokevirtual	#261; //Method length:(I)I
   5:	ireturn
  LineNumberTable: 
   line 140: 0


public boolean hasNext();
  Code:
   Stack=2, Locals=2, Args_size=1
   0:	getstatic	#268; //Field scala/xml/Null$.MODULE$:Lscala/xml/Null$;
   3:	aload_0
   4:	invokevirtual	#128; //Method next:()Lscala/xml/MetaData;
   7:	astore_1
   8:	dup
   9:	ifnonnull	20
   12:	pop
   13:	aload_1
   14:	ifnull	27
   17:	goto	31
   20:	aload_1
   21:	invokevirtual	#270; //Method java/lang/Object.equals:(Ljava/lang/Object;)Z
   24:	ifeq	31
   27:	iconst_0
   28:	goto	32
   31:	iconst_1
   32:	ireturn
  LineNumberTable: 
   line 138: 0


public abstract java.lang.String getNamespace(scala.xml.Node);

public abstract scala.xml.MetaData copy(scala.xml.MetaData);

public boolean containedIn1(scala.xml.MetaData);
  Code:
   Stack=2, Locals=2, Args_size=2
   0:	aload_1
   1:	dup
   2:	pop
   3:	ifnull	37
   6:	aload_1
   7:	aconst_null
   8:	invokevirtual	#270; //Method java/lang/Object.equals:(Ljava/lang/Object;)Z
   11:	ifne	37
   14:	aload_1
   15:	aload_0
   16:	invokevirtual	#275; //Method equals1:(Lscala/xml/MetaData;)Z
   19:	ifne	33
   22:	aload_0
   23:	aload_1
   24:	invokevirtual	#128; //Method next:()Lscala/xml/MetaData;
   27:	invokevirtual	#277; //Method containedIn1:(Lscala/xml/MetaData;)Z
   30:	ifeq	37
   33:	iconst_1
   34:	goto	38
   37:	iconst_0
   38:	ireturn
  LineNumberTable: 
   line 126: 0

  LocalVariableTable: 
   Start  Length  Slot  Name   Signature
   0      39      0    this       Lscala/xml/MetaData;
   0      39      1    m       Lscala/xml/MetaData;


public abstract scala.collection.Seq apply(java.lang.String, scala.xml.NamespaceBinding, java.lang.String);
  Signature: length = 0x2
   01 17 

public final scala.collection.Seq apply(java.lang.String, scala.xml.Node, java.lang.String);
  Code:
   Stack=4, Locals=4, Args_size=4
   0:	aload_0
   1:	aload_1
   2:	aload_2
   3:	invokevirtual	#100; //Method scala/xml/Node.scope:()Lscala/xml/NamespaceBinding;
   6:	aload_3
   7:	invokevirtual	#159; //Method apply:(Ljava/lang/String;Lscala/xml/NamespaceBinding;Ljava/lang/String;)Lscala/collection/Seq;
   10:	areturn
  LineNumberTable: 
   line 109: 0

  LocalVariableTable: 
   Start  Length  Slot  Name   Signature
   0      11      0    this       Lscala/xml/MetaData;
   0      11      1    namespace_uri       Ljava/lang/String;
   0      11      2    owner       Lscala/xml/Node;
   0      11      3    key       Ljava/lang/String;

  Signature: length = 0x2
   01 1A 

public abstract scala.collection.Seq apply(java.lang.String);
  Signature: length = 0x2
   01 1B 

public scala.xml.MetaData append(scala.xml.MetaData, scala.xml.NamespaceBinding);
  Code:
   Stack=4, Locals=3, Args_size=3
   0:	getstatic	#11; //Field scala/xml/MetaData$.MODULE$:Lscala/xml/MetaData$;
   3:	aload_0
   4:	aload_2
   5:	aload_1
   6:	invokevirtual	#13; //Method scala/xml/MetaData$.update:(Lscala/xml/MetaData;Lscala/xml/NamespaceBinding;Lscala/xml/MetaData;)Lscala/xml/MetaData;
   9:	areturn
  LineNumberTable: 
   line 91: 0

  LocalVariableTable: 
   Start  Length  Slot  Name   Signature
   0      10      0    this       Lscala/xml/MetaData;
   0      10      1    updates       Lscala/xml/MetaData;
   0      10      2    scope       Lscala/xml/NamespaceBinding;


public scala.xml.NamespaceBinding append$default$2();
  Code:
   Stack=1, Locals=1, Args_size=1
   0:	getstatic	#290; //Field scala/xml/TopScope$.MODULE$:Lscala/xml/TopScope$;
   3:	areturn
  LineNumberTable: 
   line 90: 0


public scala.collection.TraversableLike$WithFilter withFilter(scala.Function1);
  Code:
   Stack=2, Locals=2, Args_size=2
   0:	aload_0
   1:	aload_1
   2:	invokestatic	#295; //Method scala/collection/TraversableLike$class.withFilter:(Lscala/collection/TraversableLike;Lscala/Function1;)Lscala/collection/TraversableLike$WithFilter;
   5:	areturn
  LineNumberTable: 
   line 80: 0

  LocalVariableTable: 
   Start  Length  Slot  Name   Signature
   0      6      0    this       Lscala/xml/MetaData;
   0      6      1    p       Lscala/Function1;

  Signature: length = 0x2
   01 24 

public java.lang.String stringPrefix();
  Code:
   Stack=1, Locals=1, Args_size=1
   0:	aload_0
   1:	invokestatic	#299; //Method scala/collection/TraversableLike$class.stringPrefix:(Lscala/collection/TraversableLike;)Ljava/lang/String;
   4:	areturn
  LineNumberTable: 
   line 80: 0


public scala.collection.mutable.StringBuilder addString(scala.collection.mutable.StringBuilder);
  Code:
   Stack=2, Locals=2, Args_size=2
   0:	aload_0
   1:	aload_1
   2:	invokestatic	#303; //Method scala/collection/TraversableLike$class.addString:(Lscala/collection/TraversableLike;Lscala/collection/mutable/StringBuilder;)Lscala/collection/mutable/StringBuilder;
   5:	areturn
  LineNumberTable: 
   line 80: 0

  LocalVariableTable: 
   Start  Length  Slot  Name   Signature
   0      6      0    this       Lscala/xml/MetaData;
   0      6      1    b       Lscala/collection/mutable/StringBuilder;


public scala.collection.mutable.StringBuilder addString(scala.collection.mutable.StringBuilder, java.lang.String);
  Code:
   Stack=3, Locals=3, Args_size=3
   0:	aload_0
   1:	aload_1
   2:	aload_2
   3:	invokestatic	#308; //Method scala/collection/TraversableLike$class.addString:(Lscala/collection/TraversableLike;Lscala/collection/mutable/StringBuilder;Ljava/lang/String;)Lscala/collection/mutable/StringBuilder;
   6:	areturn
  LineNumberTable: 
   line 80: 0

  LocalVariableTable: 
   Start  Length  Slot  Name   Signature
   0      7      0    this       Lscala/xml/MetaData;
   0      7      1    b       Lscala/collection/mutable/StringBuilder;
   0      7      2    sep       Ljava/lang/String;


public scala.collection.mutable.StringBuilder addString(scala.collection.mutable.StringBuilder, java.lang.String, java.lang.String, java.lang.String);
  Code:
   Stack=5, Locals=5, Args_size=5
   0:	aload_0
   1:	aload_1
   2:	aload_2
   3:	aload_3
   4:	aload	4
   6:	invokestatic	#313; //Method scala/collection/TraversableLike$class.addString:(Lscala/collection/TraversableLike;Lscala/collection/mutable/StringBuilder;Ljava/lang/String;Ljava/lang/String;Ljava/lang/String;)Lscala/collection/mutable/StringBuilder;
   9:	areturn
  LineNumberTable: 
   line 80: 0

  LocalVariableTable: 
   Start  Length  Slot  Name   Signature
   0      10      0    this       Lscala/xml/MetaData;
   0      10      1    b       Lscala/collection/mutable/StringBuilder;
   0      10      2    start       Ljava/lang/String;
   0      10      3    sep       Ljava/lang/String;
   0      10      4    end       Ljava/lang/String;


public java.lang.String mkString();
  Code:
   Stack=1, Locals=1, Args_size=1
   0:	aload_0
   1:	invokestatic	#318; //Method scala/collection/TraversableLike$class.mkString:(Lscala/collection/TraversableLike;)Ljava/lang/String;
   4:	areturn
  LineNumberTable: 
   line 80: 0


public java.lang.String mkString(java.lang.String);
  Code:
   Stack=2, Locals=2, Args_size=2
   0:	aload_0
   1:	aload_1
   2:	invokestatic	#322; //Method scala/collection/TraversableLike$class.mkString:(Lscala/collection/TraversableLike;Ljava/lang/String;)Ljava/lang/String;
   5:	areturn
  LineNumberTable: 
   line 80: 0

  LocalVariableTable: 
   Start  Length  Slot  Name   Signature
   0      6      0    this       Lscala/xml/MetaData;
   0      6      1    sep       Ljava/lang/String;


public java.lang.String mkString(java.lang.String, java.lang.String, java.lang.String);
  Code:
   Stack=4, Locals=4, Args_size=4
   0:	aload_0
   1:	aload_1
   2:	aload_2
   3:	aload_3
   4:	invokestatic	#326; //Method scala/collection/TraversableLike$class.mkString:(Lscala/collection/TraversableLike;Ljava/lang/String;Ljava/lang/String;Ljava/lang/String;)Ljava/lang/String;
   7:	areturn
  LineNumberTable: 
   line 80: 0

  LocalVariableTable: 
   Start  Length  Slot  Name   Signature
   0      8      0    this       Lscala/xml/MetaData;
   0      8      1    start       Ljava/lang/String;
   0      8      2    sep       Ljava/lang/String;
   0      8      3    end       Ljava/lang/String;


public scala.collection.immutable.Set toSet();
  Code:
   Stack=1, Locals=1, Args_size=1
   0:	aload_0
   1:	invokestatic	#331; //Method scala/collection/TraversableLike$class.toSet:(Lscala/collection/TraversableLike;)Lscala/collection/immutable/Set;
   4:	areturn
  LineNumberTable: 
   line 80: 0


public scala.collection.mutable.IndexedSeq toIndexedSeq();
  Code:
   Stack=1, Locals=1, Args_size=1
   0:	aload_0
   1:	invokestatic	#336; //Method scala/collection/TraversableLike$class.toIndexedSeq:(Lscala/collection/TraversableLike;)Lscala/collection/mutable/IndexedSeq;
   4:	areturn
  LineNumberTable: 
   line 80: 0


public scala.collection.Seq toSeq();
  Code:
   Stack=1, Locals=1, Args_size=1
   0:	aload_0
   1:	invokestatic	#340; //Method scala/collection/TraversableLike$class.toSeq:(Lscala/collection/TraversableLike;)Lscala/collection/Seq;
   4:	areturn
  LineNumberTable: 
   line 80: 0


public scala.collection.immutable.List toList();
  Code:
   Stack=1, Locals=1, Args_size=1
   0:	aload_0
   1:	invokestatic	#343; //Method scala/collection/TraversableLike$class.toList:(Lscala/collection/TraversableLike;)Lscala/collection/immutable/List;
   4:	areturn
  LineNumberTable: 
   line 80: 0


public java.lang.Object toArray(scala.reflect.ClassManifest);
  Code:
   Stack=2, Locals=2, Args_size=2
   0:	aload_0
   1:	aload_1
   2:	invokestatic	#348; //Method scala/collection/TraversableLike$class.toArray:(Lscala/collection/TraversableLike;Lscala/reflect/ClassManifest;)Ljava/lang/Object;
   5:	areturn
  LineNumberTable: 
   line 80: 0

  LocalVariableTable: 
   Start  Length  Slot  Name   Signature
   0      6      0    this       Lscala/xml/MetaData;
   0      6      1    evidence$1       Lscala/reflect/ClassManifest;


public void copyToArray(java.lang.Object);
  Code:
   Stack=2, Locals=2, Args_size=2
   0:	aload_0
   1:	aload_1
   2:	invokestatic	#355; //Method scala/collection/TraversableLike$class.copyToArray:(Lscala/collection/TraversableLike;Ljava/lang/Object;)V
   5:	return
  LineNumberTable: 
   line 80: 0

  LocalVariableTable: 
   Start  Length  Slot  Name   Signature
   0      6      0    this       Lscala/xml/MetaData;
   0      6      1    xs       Ljava/lang/Object;


public void copyToArray(java.lang.Object, int);
  Code:
   Stack=3, Locals=3, Args_size=3
   0:	aload_0
   1:	aload_1
   2:	iload_2
   3:	invokestatic	#360; //Method scala/collection/TraversableLike$class.copyToArray:(Lscala/collection/TraversableLike;Ljava/lang/Object;I)V
   6:	return
  LineNumberTable: 
   line 80: 0

  LocalVariableTable: 
   Start  Length  Slot  Name   Signature
   0      7      0    this       Lscala/xml/MetaData;
   0      7      1    xs       Ljava/lang/Object;
   0      7      2    start       I


public void copyToBuffer(scala.collection.mutable.Buffer);
  Code:
   Stack=2, Locals=2, Args_size=2
   0:	aload_0
   1:	aload_1
   2:	invokestatic	#365; //Method scala/collection/TraversableLike$class.copyToBuffer:(Lscala/collection/TraversableLike;Lscala/collection/mutable/Buffer;)V
   5:	return
  LineNumberTable: 
   line 80: 0

  LocalVariableTable: 
   Start  Length  Slot  Name   Signature
   0      6      0    this       Lscala/xml/MetaData;
   0      6      1    dest       Lscala/collection/mutable/Buffer;


public scala.Tuple2 splitAt(int);
  Code:
   Stack=2, Locals=2, Args_size=2
   0:	aload_0
   1:	iload_1
   2:	invokestatic	#372; //Method scala/collection/TraversableLike$class.splitAt:(Lscala/collection/TraversableLike;I)Lscala/Tuple2;
   5:	areturn
  LineNumberTable: 
   line 80: 0

  LocalVariableTable: 
   Start  Length  Slot  Name   Signature
   0      6      0    this       Lscala/xml/MetaData;
   0      6      1    n       I


public scala.Tuple2 span(scala.Function1);
  Code:
   Stack=2, Locals=2, Args_size=2
   0:	aload_0
   1:	aload_1
   2:	invokestatic	#378; //Method scala/collection/TraversableLike$class.span:(Lscala/collection/TraversableLike;Lscala/Function1;)Lscala/Tuple2;
   5:	areturn
  LineNumberTable: 
   line 80: 0

  LocalVariableTable: 
   Start  Length  Slot  Name   Signature
   0      6      0    this       Lscala/xml/MetaData;
   0      6      1    p       Lscala/Function1;


public java.lang.Object dropWhile(scala.Function1);
  Code:
   Stack=2, Locals=2, Args_size=2
   0:	aload_0
   1:	aload_1
   2:	invokestatic	#382; //Method scala/collection/TraversableLike$class.dropWhile:(Lscala/collection/TraversableLike;Lscala/Function1;)Ljava/lang/Object;
   5:	areturn
  LineNumberTable: 
   line 80: 0

  LocalVariableTable: 
   Start  Length  Slot  Name   Signature
   0      6      0    this       Lscala/xml/MetaData;
   0      6      1    p       Lscala/Function1;


public java.lang.Object drop(int);
  Code:
   Stack=2, Locals=2, Args_size=2
   0:	aload_0
   1:	iload_1
   2:	invokestatic	#387; //Method scala/collection/TraversableLike$class.drop:(Lscala/collection/TraversableLike;I)Ljava/lang/Object;
   5:	areturn
  LineNumberTable: 
   line 80: 0

  LocalVariableTable: 
   Start  Length  Slot  Name   Signature
   0      6      0    this       Lscala/xml/MetaData;
   0      6      1    n       I


public java.lang.Object init();
  Code:
   Stack=1, Locals=1, Args_size=1
   0:	aload_0
   1:	invokestatic	#392; //Method scala/collection/TraversableLike$class.init:(Lscala/collection/TraversableLike;)Ljava/lang/Object;
   4:	areturn
  LineNumberTable: 
   line 80: 0


public scala.Option lastOption();
  Code:
   Stack=1, Locals=1, Args_size=1
   0:	aload_0
   1:	invokestatic	#397; //Method scala/collection/TraversableLike$class.lastOption:(Lscala/collection/TraversableLike;)Lscala/Option;
   4:	areturn
  LineNumberTable: 
   line 80: 0


public java.lang.Object last();
  Code:
   Stack=1, Locals=1, Args_size=1
   0:	aload_0
   1:	invokestatic	#400; //Method scala/collection/TraversableLike$class.last:(Lscala/collection/TraversableLike;)Ljava/lang/Object;
   4:	areturn
  LineNumberTable: 
   line 80: 0


public java.lang.Object tail();
  Code:
   Stack=1, Locals=1, Args_size=1
   0:	aload_0
   1:	invokestatic	#403; //Method scala/collection/TraversableLike$class.tail:(Lscala/collection/TraversableLike;)Ljava/lang/Object;
   4:	areturn
  LineNumberTable: 
   line 80: 0


public scala.Option headOption();
  Code:
   Stack=1, Locals=1, Args_size=1
   0:	aload_0
   1:	invokestatic	#406; //Method scala/collection/TraversableLike$class.headOption:(Lscala/collection/TraversableLike;)Lscala/Option;
   4:	areturn
  LineNumberTable: 
   line 80: 0


public java.lang.Object max(scala.math.Ordering);
  Code:
   Stack=2, Locals=2, Args_size=2
   0:	aload_0
   1:	aload_1
   2:	invokestatic	#411; //Method scala/collection/TraversableLike$class.max:(Lscala/collection/TraversableLike;Lscala/math/Ordering;)Ljava/lang/Object;
   5:	areturn
  LineNumberTable: 
   line 80: 0

  LocalVariableTable: 
   Start  Length  Slot  Name   Signature
   0      6      0    this       Lscala/xml/MetaData;
   0      6      1    cmp       Lscala/math/Ordering;


public java.lang.Object min(scala.math.Ordering);
  Code:
   Stack=2, Locals=2, Args_size=2
   0:	aload_0
   1:	aload_1
   2:	invokestatic	#416; //Method scala/collection/TraversableLike$class.min:(Lscala/collection/TraversableLike;Lscala/math/Ordering;)Ljava/lang/Object;
   5:	areturn
  LineNumberTable: 
   line 80: 0

  LocalVariableTable: 
   Start  Length  Slot  Name   Signature
   0      6      0    this       Lscala/xml/MetaData;
   0      6      1    cmp       Lscala/math/Ordering;


public java.lang.Object product(scala.math.Numeric);
  Code:
   Stack=2, Locals=2, Args_size=2
   0:	aload_0
   1:	aload_1
   2:	invokestatic	#421; //Method scala/collection/TraversableLike$class.product:(Lscala/collection/TraversableLike;Lscala/math/Numeric;)Ljava/lang/Object;
   5:	areturn
  LineNumberTable: 
   line 80: 0

  LocalVariableTable: 
   Start  Length  Slot  Name   Signature
   0      6      0    this       Lscala/xml/MetaData;
   0      6      1    num       Lscala/math/Numeric;


public java.lang.Object sum(scala.math.Numeric);
  Code:
   Stack=2, Locals=2, Args_size=2
   0:	aload_0
   1:	aload_1
   2:	invokestatic	#426; //Method scala/collection/TraversableLike$class.sum:(Lscala/collection/TraversableLike;Lscala/math/Numeric;)Ljava/lang/Object;
   5:	areturn
  LineNumberTable: 
   line 80: 0

  LocalVariableTable: 
   Start  Length  Slot  Name   Signature
   0      6      0    this       Lscala/xml/MetaData;
   0      6      1    num       Lscala/math/Numeric;


public scala.Option reduceRightOption(scala.Function2);
  Code:
   Stack=2, Locals=2, Args_size=2
   0:	aload_0
   1:	aload_1
   2:	invokestatic	#431; //Method scala/collection/TraversableLike$class.reduceRightOption:(Lscala/collection/TraversableLike;Lscala/Function2;)Lscala/Option;
   5:	areturn
  LineNumberTable: 
   line 80: 0

  LocalVariableTable: 
   Start  Length  Slot  Name   Signature
   0      6      0    this       Lscala/xml/MetaData;
   0      6      1    op       Lscala/Function2;


public scala.Option reduceLeftOption(scala.Function2);
  Code:
   Stack=2, Locals=2, Args_size=2
   0:	aload_0
   1:	aload_1
   2:	invokestatic	#436; //Method scala/collection/TraversableLike$class.reduceLeftOption:(Lscala/collection/TraversableLike;Lscala/Function2;)Lscala/Option;
   5:	areturn
  LineNumberTable: 
   line 80: 0

  LocalVariableTable: 
   Start  Length  Slot  Name   Signature
   0      6      0    this       Lscala/xml/MetaData;
   0      6      1    op       Lscala/Function2;


public java.lang.Object reduceLeft(scala.Function2);
  Code:
   Stack=2, Locals=2, Args_size=2
   0:	aload_0
   1:	aload_1
   2:	invokestatic	#441; //Method scala/collection/TraversableLike$class.reduceLeft:(Lscala/collection/TraversableLike;Lscala/Function2;)Ljava/lang/Object;
   5:	areturn
  LineNumberTable: 
   line 80: 0

  LocalVariableTable: 
   Start  Length  Slot  Name   Signature
   0      6      0    this       Lscala/xml/MetaData;
   0      6      1    op       Lscala/Function2;


public java.lang.Object $colon$bslash(java.lang.Object, scala.Function2);
  Code:
   Stack=3, Locals=3, Args_size=3
   0:	aload_0
   1:	aload_1
   2:	aload_2
   3:	invokestatic	#446; //Method scala/collection/TraversableLike$class.$colon$bslash:(Lscala/collection/TraversableLike;Ljava/lang/Object;Lscala/Function2;)Ljava/lang/Object;
   6:	areturn
  LineNumberTable: 
   line 80: 0

  LocalVariableTable: 
   Start  Length  Slot  Name   Signature
   0      7      0    this       Lscala/xml/MetaData;
   0      7      1    z       Ljava/lang/Object;
   0      7      2    op       Lscala/Function2;


public java.lang.Object $div$colon(java.lang.Object, scala.Function2);
  Code:
   Stack=3, Locals=3, Args_size=3
   0:	aload_0
   1:	aload_1
   2:	aload_2
   3:	invokestatic	#450; //Method scala/collection/TraversableLike$class.$div$colon:(Lscala/collection/TraversableLike;Ljava/lang/Object;Lscala/Function2;)Ljava/lang/Object;
   6:	areturn
  LineNumberTable: 
   line 80: 0

  LocalVariableTable: 
   Start  Length  Slot  Name   Signature
   0      7      0    this       Lscala/xml/MetaData;
   0      7      1    z       Ljava/lang/Object;
   0      7      2    op       Lscala/Function2;


public java.lang.Object foldLeft(java.lang.Object, scala.Function2);
  Code:
   Stack=3, Locals=3, Args_size=3
   0:	aload_0
   1:	aload_1
   2:	aload_2
   3:	invokestatic	#453; //Method scala/collection/TraversableLike$class.foldLeft:(Lscala/collection/TraversableLike;Ljava/lang/Object;Lscala/Function2;)Ljava/lang/Object;
   6:	areturn
  LineNumberTable: 
   line 80: 0

  LocalVariableTable: 
   Start  Length  Slot  Name   Signature
   0      7      0    this       Lscala/xml/MetaData;
   0      7      1    z       Ljava/lang/Object;
   0      7      2    op       Lscala/Function2;


public int count(scala.Function1);
  Code:
   Stack=2, Locals=2, Args_size=2
   0:	aload_0
   1:	aload_1
   2:	invokestatic	#458; //Method scala/collection/TraversableLike$class.count:(Lscala/collection/TraversableLike;Lscala/Function1;)I
   5:	ireturn
  LineNumberTable: 
   line 80: 0

  LocalVariableTable: 
   Start  Length  Slot  Name   Signature
   0      6      0    this       Lscala/xml/MetaData;
   0      6      1    p       Lscala/Function1;


public scala.collection.Map groupBy(scala.Function1);
  Code:
   Stack=2, Locals=2, Args_size=2
   0:	aload_0
   1:	aload_1
   2:	invokestatic	#463; //Method scala/collection/TraversableLike$class.groupBy:(Lscala/collection/TraversableLike;Lscala/Function1;)Lscala/collection/Map;
   5:	areturn
  LineNumberTable: 
   line 80: 0

  LocalVariableTable: 
   Start  Length  Slot  Name   Signature
   0      6      0    this       Lscala/xml/MetaData;
   0      6      1    f       Lscala/Function1;


public scala.Tuple2 partition(scala.Function1);
  Code:
   Stack=2, Locals=2, Args_size=2
   0:	aload_0
   1:	aload_1
   2:	invokestatic	#466; //Method scala/collection/TraversableLike$class.partition:(Lscala/collection/TraversableLike;Lscala/Function1;)Lscala/Tuple2;
   5:	areturn
  LineNumberTable: 
   line 80: 0

  LocalVariableTable: 
   Start  Length  Slot  Name   Signature
   0      6      0    this       Lscala/xml/MetaData;
   0      6      1    p       Lscala/Function1;


public java.lang.Object partialMap(scala.PartialFunction, scala.collection.generic.CanBuildFrom);
  Code:
   Stack=3, Locals=3, Args_size=3
   0:	aload_0
   1:	aload_1
   2:	aload_2
   3:	invokestatic	#471; //Method scala/collection/TraversableLike$class.partialMap:(Lscala/collection/TraversableLike;Lscala/PartialFunction;Lscala/collection/generic/CanBuildFrom;)Ljava/lang/Object;
   6:	areturn
  LineNumberTable: 
   line 80: 0

  LocalVariableTable: 
   Start  Length  Slot  Name   Signature
   0      7      0    this       Lscala/xml/MetaData;
   0      7      1    pf       Lscala/PartialFunction;
   0      7      2    bf       Lscala/collection/generic/CanBuildFrom;


public java.lang.Object filterNot(scala.Function1);
  Code:
   Stack=2, Locals=2, Args_size=2
   0:	aload_0
   1:	aload_1
   2:	invokestatic	#478; //Method scala/collection/TraversableLike$class.filterNot:(Lscala/collection/TraversableLike;Lscala/Function1;)Ljava/lang/Object;
   5:	areturn
  LineNumberTable: 
   line 80: 0

  LocalVariableTable: 
   Start  Length  Slot  Name   Signature
   0      6      0    this       Lscala/xml/MetaData;
   0      6      1    p       Lscala/Function1;


public java.lang.Object flatMap(scala.Function1, scala.collection.generic.CanBuildFrom);
  Code:
   Stack=3, Locals=3, Args_size=3
   0:	aload_0
   1:	aload_1
   2:	aload_2
   3:	invokestatic	#483; //Method scala/collection/TraversableLike$class.flatMap:(Lscala/collection/TraversableLike;Lscala/Function1;Lscala/collection/generic/CanBuildFrom;)Ljava/lang/Object;
   6:	areturn
  LineNumberTable: 
   line 80: 0

  LocalVariableTable: 
   Start  Length  Slot  Name   Signature
   0      7      0    this       Lscala/xml/MetaData;
   0      7      1    f       Lscala/Function1;
   0      7      2    bf       Lscala/collection/generic/CanBuildFrom;


public java.lang.Object map(scala.Function1, scala.collection.generic.CanBuildFrom);
  Code:
   Stack=3, Locals=3, Args_size=3
   0:	aload_0
   1:	aload_1
   2:	aload_2
   3:	invokestatic	#485; //Method scala/collection/TraversableLike$class.map:(Lscala/collection/TraversableLike;Lscala/Function1;Lscala/collection/generic/CanBuildFrom;)Ljava/lang/Object;
   6:	areturn
  LineNumberTable: 
   line 80: 0

  LocalVariableTable: 
   Start  Length  Slot  Name   Signature
   0      7      0    this       Lscala/xml/MetaData;
   0      7      1    f       Lscala/Function1;
   0      7      2    bf       Lscala/collection/generic/CanBuildFrom;


public java.lang.Object $plus$plus(scala.collection.Iterator, scala.collection.generic.CanBuildFrom);
  Code:
   Stack=3, Locals=3, Args_size=3
   0:	aload_0
   1:	aload_1
   2:	aload_2
   3:	invokestatic	#490; //Method scala/collection/TraversableLike$class.$plus$plus:(Lscala/collection/TraversableLike;Lscala/collection/Iterator;Lscala/collection/generic/CanBuildFrom;)Ljava/lang/Object;
   6:	areturn
  LineNumberTable: 
   line 80: 0

  LocalVariableTable: 
   Start  Length  Slot  Name   Signature
   0      7      0    this       Lscala/xml/MetaData;
   0      7      1    that       Lscala/collection/Iterator;
   0      7      2    bf       Lscala/collection/generic/CanBuildFrom;


public java.lang.Object $plus$plus(scala.collection.Traversable, scala.collection.generic.CanBuildFrom);
  Code:
   Stack=3, Locals=3, Args_size=3
   0:	aload_0
   1:	aload_1
   2:	aload_2
   3:	invokestatic	#495; //Method scala/collection/TraversableLike$class.$plus$plus:(Lscala/collection/TraversableLike;Lscala/collection/Traversable;Lscala/collection/generic/CanBuildFrom;)Ljava/lang/Object;
   6:	areturn
  LineNumberTable: 
   line 80: 0

  LocalVariableTable: 
   Start  Length  Slot  Name   Signature
   0      7      0    this       Lscala/xml/MetaData;
   0      7      1    that       Lscala/collection/Traversable;
   0      7      2    bf       Lscala/collection/generic/CanBuildFrom;


public boolean hasDefiniteSize();
  Code:
   Stack=1, Locals=1, Args_size=1
   0:	aload_0
   1:	invokestatic	#500; //Method scala/collection/TraversableLike$class.hasDefiniteSize:(Lscala/collection/TraversableLike;)Z
   4:	ireturn
  LineNumberTable: 
   line 80: 0


public boolean nonEmpty();
  Code:
   Stack=1, Locals=1, Args_size=1
   0:	aload_0
   1:	invokestatic	#503; //Method scala/collection/TraversableLike$class.nonEmpty:(Lscala/collection/TraversableLike;)Z
   4:	ireturn
  LineNumberTable: 
   line 80: 0


public java.lang.Object repr();
  Code:
   Stack=1, Locals=1, Args_size=1
   0:	aload_0
   1:	invokestatic	#505; //Method scala/collection/TraversableLike$class.repr:(Lscala/collection/TraversableLike;)Ljava/lang/Object;
   4:	areturn
  LineNumberTable: 
   line 80: 0


public scala.collection.Traversable transpose(scala.Function1);
  Code:
   Stack=2, Locals=2, Args_size=2
   0:	aload_0
   1:	aload_1
   2:	invokestatic	#510; //Method scala/collection/generic/GenericTraversableTemplate$class.transpose:(Lscala/collection/generic/GenericTraversableTemplate;Lscala/Function1;)Lscala/collection/Traversable;
   5:	areturn
  LineNumberTable: 
   line 80: 0

  LocalVariableTable: 
   Start  Length  Slot  Name   Signature
   0      6      0    this       Lscala/xml/MetaData;
   0      6      1    asTraversable       Lscala/Function1;


public scala.collection.Traversable flatten(scala.Function1);
  Code:
   Stack=2, Locals=2, Args_size=2
   0:	aload_0
   1:	aload_1
   2:	invokestatic	#514; //Method scala/collection/generic/GenericTraversableTemplate$class.flatten:(Lscala/collection/generic/GenericTraversableTemplate;Lscala/Function1;)Lscala/collection/Traversable;
   5:	areturn
  LineNumberTable: 
   line 80: 0

  LocalVariableTable: 
   Start  Length  Slot  Name   Signature
   0      6      0    this       Lscala/xml/MetaData;
   0      6      1    asTraversable       Lscala/Function1;


public scala.Tuple2 unzip(scala.Function1);
  Code:
   Stack=2, Locals=2, Args_size=2
   0:	aload_0
   1:	aload_1
   2:	invokestatic	#518; //Method scala/collection/generic/GenericTraversableTemplate$class.unzip:(Lscala/collection/generic/GenericTraversableTemplate;Lscala/Function1;)Lscala/Tuple2;
   5:	areturn
  LineNumberTable: 
   line 80: 0

  LocalVariableTable: 
   Start  Length  Slot  Name   Signature
   0      6      0    this       Lscala/xml/MetaData;
   0      6      1    asPair       Lscala/Function1;


public scala.collection.mutable.Builder genericBuilder();
  Code:
   Stack=1, Locals=1, Args_size=1
   0:	aload_0
   1:	invokestatic	#524; //Method scala/collection/generic/GenericTraversableTemplate$class.genericBuilder:(Lscala/collection/generic/GenericTraversableTemplate;)Lscala/collection/mutable/Builder;
   4:	areturn
  LineNumberTable: 
   line 80: 0


public scala.collection.mutable.Builder newBuilder();
  Code:
   Stack=1, Locals=1, Args_size=1
   0:	aload_0
   1:	invokestatic	#527; //Method scala/collection/generic/GenericTraversableTemplate$class.newBuilder:(Lscala/collection/generic/GenericTraversableTemplate;)Lscala/collection/mutable/Builder;
   4:	areturn
  LineNumberTable: 
   line 80: 0


public java.lang.Object projection();
  Code:
   Stack=1, Locals=1, Args_size=1
   0:	aload_0
   1:	invokestatic	#531; //Method scala/collection/IterableLike$class.projection:(Lscala/collection/IterableLike;)Ljava/lang/Object;
   4:	areturn
  LineNumberTable: 
   line 80: 0

  Deprecated: true

public scala.Option firstOption();
  Code:
   Stack=1, Locals=1, Args_size=1
   0:	aload_0
   1:	invokestatic	#536; //Method scala/collection/IterableLike$class.firstOption:(Lscala/collection/IterableLike;)Lscala/Option;
   4:	areturn
  LineNumberTable: 
   line 80: 0

  Deprecated: true

public java.lang.Object first();
  Code:
   Stack=1, Locals=1, Args_size=1
   0:	aload_0
   1:	invokestatic	#539; //Method scala/collection/IterableLike$class.first:(Lscala/collection/IterableLike;)Ljava/lang/Object;
   4:	areturn
  LineNumberTable: 
   line 80: 0

  Deprecated: true

public scala.collection.IterableView view(int, int);
  Code:
   Stack=3, Locals=3, Args_size=3
   0:	aload_0
   1:	iload_1
   2:	iload_2
   3:	invokestatic	#542; //Method scala/collection/IterableLike$class.view:(Lscala/collection/IterableLike;II)Lscala/collection/IterableView;
   6:	areturn
  LineNumberTable: 
   line 80: 0

  LocalVariableTable: 
   Start  Length  Slot  Name   Signature
   0      7      0    this       Lscala/xml/MetaData;
   0      7      1    from       I
   0      7      2    until       I


public java.lang.Object view();
  Code:
   Stack=1, Locals=1, Args_size=1
   0:	aload_0
   1:	invokestatic	#544; //Method scala/collection/IterableLike$class.view:(Lscala/collection/IterableLike;)Ljava/lang/Object;
   4:	areturn
  LineNumberTable: 
   line 80: 0


public boolean canEqual(java.lang.Object);
  Code:
   Stack=2, Locals=2, Args_size=2
   0:	aload_0
   1:	aload_1
   2:	invokestatic	#548; //Method scala/collection/IterableLike$class.canEqual:(Lscala/collection/IterableLike;Ljava/lang/Object;)Z
   5:	ireturn
  LineNumberTable: 
   line 80: 0

  LocalVariableTable: 
   Start  Length  Slot  Name   Signature
   0      6      0    this       Lscala/xml/MetaData;
   0      6      1    that       Ljava/lang/Object;


public scala.collection.immutable.Stream toStream();
  Code:
   Stack=1, Locals=1, Args_size=1
   0:	aload_0
   1:	invokestatic	#553; //Method scala/collection/IterableLike$class.toStream:(Lscala/collection/IterableLike;)Lscala/collection/immutable/Stream;
   4:	areturn
  LineNumberTable: 
   line 80: 0


public boolean sameElements(scala.collection.Iterable);
  Code:
   Stack=2, Locals=2, Args_size=2
   0:	aload_0
   1:	aload_1
   2:	invokestatic	#558; //Method scala/collection/IterableLike$class.sameElements:(Lscala/collection/IterableLike;Lscala/collection/Iterable;)Z
   5:	ireturn
  LineNumberTable: 
   line 80: 0

  LocalVariableTable: 
   Start  Length  Slot  Name   Signature
   0      6      0    this       Lscala/xml/MetaData;
   0      6      1    that       Lscala/collection/Iterable;


public java.lang.Object zipWithIndex(scala.collection.generic.CanBuildFrom);
  Code:
   Stack=2, Locals=2, Args_size=2
   0:	aload_0
   1:	aload_1
   2:	invokestatic	#564; //Method scala/collection/IterableLike$class.zipWithIndex:(Lscala/collection/IterableLike;Lscala/collection/generic/CanBuildFrom;)Ljava/lang/Object;
   5:	areturn
  LineNumberTable: 
   line 80: 0

  LocalVariableTable: 
   Start  Length  Slot  Name   Signature
   0      6      0    this       Lscala/xml/MetaData;
   0      6      1    bf       Lscala/collection/generic/CanBuildFrom;


public java.lang.Object zipAll(scala.collection.Iterable, java.lang.Object, java.lang.Object, scala.collection.generic.CanBuildFrom);
  Code:
   Stack=5, Locals=5, Args_size=5
   0:	aload_0
   1:	aload_1
   2:	aload_2
   3:	aload_3
   4:	aload	4
   6:	invokestatic	#569; //Method scala/collection/IterableLike$class.zipAll:(Lscala/collection/IterableLike;Lscala/collection/Iterable;Ljava/lang/Object;Ljava/lang/Object;Lscala/collection/generic/CanBuildFrom;)Ljava/lang/Object;
   9:	areturn
  LineNumberTable: 
   line 80: 0

  LocalVariableTable: 
   Start  Length  Slot  Name   Signature
   0      10      0    this       Lscala/xml/MetaData;
   0      10      1    that       Lscala/collection/Iterable;
   0      10      2    thisElem       Ljava/lang/Object;
   0      10      3    thatElem       Ljava/lang/Object;
   0      10      4    bf       Lscala/collection/generic/CanBuildFrom;


public java.lang.Object zip(scala.collection.Iterable, scala.collection.generic.CanBuildFrom);
  Code:
   Stack=3, Locals=3, Args_size=3
   0:	aload_0
   1:	aload_1
   2:	aload_2
   3:	invokestatic	#576; //Method scala/collection/IterableLike$class.zip:(Lscala/collection/IterableLike;Lscala/collection/Iterable;Lscala/collection/generic/CanBuildFrom;)Ljava/lang/Object;
   6:	areturn
  LineNumberTable: 
   line 80: 0

  LocalVariableTable: 
   Start  Length  Slot  Name   Signature
   0      7      0    this       Lscala/xml/MetaData;
   0      7      1    that       Lscala/collection/Iterable;
   0      7      2    bf       Lscala/collection/generic/CanBuildFrom;


public void copyToArray(java.lang.Object, int, int);
  Code:
   Stack=4, Locals=4, Args_size=4
   0:	aload_0
   1:	aload_1
   2:	iload_2
   3:	iload_3
   4:	invokestatic	#580; //Method scala/collection/IterableLike$class.copyToArray:(Lscala/collection/IterableLike;Ljava/lang/Object;II)V
   7:	return
  LineNumberTable: 
   line 80: 0

  LocalVariableTable: 
   Start  Length  Slot  Name   Signature
   0      8      0    this       Lscala/xml/MetaData;
   0      8      1    xs       Ljava/lang/Object;
   0      8      2    start       I
   0      8      3    len       I


public java.lang.Object dropRight(int);
  Code:
   Stack=2, Locals=2, Args_size=2
   0:	aload_0
   1:	iload_1
   2:	invokestatic	#585; //Method scala/collection/IterableLike$class.dropRight:(Lscala/collection/IterableLike;I)Ljava/lang/Object;
   5:	areturn
  LineNumberTable: 
   line 80: 0

  LocalVariableTable: 
   Start  Length  Slot  Name   Signature
   0      6      0    this       Lscala/xml/MetaData;
   0      6      1    n       I


public java.lang.Object takeRight(int);
  Code:
   Stack=2, Locals=2, Args_size=2
   0:	aload_0
   1:	iload_1
   2:	invokestatic	#588; //Method scala/collection/IterableLike$class.takeRight:(Lscala/collection/IterableLike;I)Ljava/lang/Object;
   5:	areturn
  LineNumberTable: 
   line 80: 0

  LocalVariableTable: 
   Start  Length  Slot  Name   Signature
   0      6      0    this       Lscala/xml/MetaData;
   0      6      1    n       I


public java.lang.Object takeWhile(scala.Function1);
  Code:
   Stack=2, Locals=2, Args_size=2
   0:	aload_0
   1:	aload_1
   2:	invokestatic	#591; //Method scala/collection/IterableLike$class.takeWhile:(Lscala/collection/IterableLike;Lscala/Function1;)Ljava/lang/Object;
   5:	areturn
  LineNumberTable: 
   line 80: 0

  LocalVariableTable: 
   Start  Length  Slot  Name   Signature
   0      6      0    this       Lscala/xml/MetaData;
   0      6      1    p       Lscala/Function1;


public java.lang.Object slice(int, int);
  Code:
   Stack=3, Locals=3, Args_size=3
   0:	aload_0
   1:	iload_1
   2:	iload_2
   3:	invokestatic	#596; //Method scala/collection/IterableLike$class.slice:(Lscala/collection/IterableLike;II)Ljava/lang/Object;
   6:	areturn
  LineNumberTable: 
   line 80: 0

  LocalVariableTable: 
   Start  Length  Slot  Name   Signature
   0      7      0    this       Lscala/xml/MetaData;
   0      7      1    from       I
   0      7      2    until       I


public java.lang.Object take(int);
  Code:
   Stack=2, Locals=2, Args_size=2
   0:	aload_0
   1:	iload_1
   2:	invokestatic	#599; //Method scala/collection/IterableLike$class.take:(Lscala/collection/IterableLike;I)Ljava/lang/Object;
   5:	areturn
  LineNumberTable: 
   line 80: 0

  LocalVariableTable: 
   Start  Length  Slot  Name   Signature
   0      6      0    this       Lscala/xml/MetaData;
   0      6      1    n       I


public java.lang.Object head();
  Code:
   Stack=1, Locals=1, Args_size=1
   0:	aload_0
   1:	invokestatic	#602; //Method scala/collection/IterableLike$class.head:(Lscala/collection/IterableLike;)Ljava/lang/Object;
   4:	areturn
  LineNumberTable: 
   line 80: 0


public scala.collection.Iterable toIterable();
  Code:
   Stack=1, Locals=1, Args_size=1
   0:	aload_0
   1:	invokestatic	#606; //Method scala/collection/IterableLike$class.toIterable:(Lscala/collection/IterableLike;)Lscala/collection/Iterable;
   4:	areturn
  LineNumberTable: 
   line 80: 0


public java.lang.Object reduceRight(scala.Function2);
  Code:
   Stack=2, Locals=2, Args_size=2
   0:	aload_0
   1:	aload_1
   2:	invokestatic	#610; //Method scala/collection/IterableLike$class.reduceRight:(Lscala/collection/IterableLike;Lscala/Function2;)Ljava/lang/Object;
   5:	areturn
  LineNumberTable: 
   line 80: 0

  LocalVariableTable: 
   Start  Length  Slot  Name   Signature
   0      6      0    this       Lscala/xml/MetaData;
   0      6      1    op       Lscala/Function2;


public java.lang.Object foldRight(java.lang.Object, scala.Function2);
  Code:
   Stack=3, Locals=3, Args_size=3
   0:	aload_0
   1:	aload_1
   2:	aload_2
   3:	invokestatic	#614; //Method scala/collection/IterableLike$class.foldRight:(Lscala/collection/IterableLike;Ljava/lang/Object;Lscala/Function2;)Ljava/lang/Object;
   6:	areturn
  LineNumberTable: 
   line 80: 0

  LocalVariableTable: 
   Start  Length  Slot  Name   Signature
   0      7      0    this       Lscala/xml/MetaData;
   0      7      1    z       Ljava/lang/Object;
   0      7      2    op       Lscala/Function2;


public boolean isEmpty();
  Code:
   Stack=1, Locals=1, Args_size=1
   0:	aload_0
   1:	invokestatic	#618; //Method scala/collection/IterableLike$class.isEmpty:(Lscala/collection/IterableLike;)Z
   4:	ireturn
  LineNumberTable: 
   line 80: 0


public scala.Option find(scala.Function1);
  Code:
   Stack=2, Locals=2, Args_size=2
   0:	aload_0
   1:	aload_1
   2:	invokestatic	#623; //Method scala/collection/IterableLike$class.find:(Lscala/collection/IterableLike;Lscala/Function1;)Lscala/Option;
   5:	areturn
  LineNumberTable: 
   line 80: 0

  LocalVariableTable: 
   Start  Length  Slot  Name   Signature
   0      6      0    this       Lscala/xml/MetaData;
   0      6      1    p       Lscala/Function1;


public boolean exists(scala.Function1);
  Code:
   Stack=2, Locals=2, Args_size=2
   0:	aload_0
   1:	aload_1
   2:	invokestatic	#627; //Method scala/collection/IterableLike$class.exists:(Lscala/collection/IterableLike;Lscala/Function1;)Z
   5:	ireturn
  LineNumberTable: 
   line 80: 0

  LocalVariableTable: 
   Start  Length  Slot  Name   Signature
   0      6      0    this       Lscala/xml/MetaData;
   0      6      1    p       Lscala/Function1;


public boolean forall(scala.Function1);
  Code:
   Stack=2, Locals=2, Args_size=2
   0:	aload_0
   1:	aload_1
   2:	invokestatic	#629; //Method scala/collection/IterableLike$class.forall:(Lscala/collection/IterableLike;Lscala/Function1;)Z
   5:	ireturn
  LineNumberTable: 
   line 80: 0

  LocalVariableTable: 
   Start  Length  Slot  Name   Signature
   0      6      0    this       Lscala/xml/MetaData;
   0      6      1    p       Lscala/Function1;


public void foreach(scala.Function1);
  Code:
   Stack=2, Locals=2, Args_size=2
   0:	aload_0
   1:	aload_1
   2:	invokestatic	#634; //Method scala/collection/IterableLike$class.foreach:(Lscala/collection/IterableLike;Lscala/Function1;)V
   5:	return
  LineNumberTable: 
   line 80: 0

  LocalVariableTable: 
   Start  Length  Slot  Name   Signature
   0      6      0    this       Lscala/xml/MetaData;
   0      6      1    f       Lscala/Function1;


public scala.collection.Iterator elements();
  Code:
   Stack=1, Locals=1, Args_size=1
   0:	aload_0
   1:	invokestatic	#638; //Method scala/collection/IterableLike$class.elements:(Lscala/collection/IterableLike;)Lscala/collection/Iterator;
   4:	areturn
  LineNumberTable: 
   line 80: 0

  Deprecated: true

public scala.collection.Iterable toCollection(java.lang.Object);
  Code:
   Stack=2, Locals=2, Args_size=2
   0:	aload_0
   1:	aload_1
   2:	invokestatic	#641; //Method scala/collection/IterableLike$class.toCollection:(Lscala/collection/IterableLike;Ljava/lang/Object;)Lscala/collection/Iterable;
   5:	areturn
  LineNumberTable: 
   line 80: 0

  LocalVariableTable: 
   Start  Length  Slot  Name   Signature
   0      6      0    this       Lscala/xml/MetaData;
   0      6      1    repr       Ljava/lang/Object;


public scala.collection.Iterable thisCollection();
  Code:
   Stack=1, Locals=1, Args_size=1
   0:	aload_0
   1:	invokestatic	#643; //Method scala/collection/IterableLike$class.thisCollection:(Lscala/collection/IterableLike;)Lscala/collection/Iterable;
   4:	areturn
  LineNumberTable: 
   line 80: 0


public scala.collection.generic.GenericCompanion companion();
  Code:
   Stack=1, Locals=1, Args_size=1
   0:	aload_0
   1:	invokestatic	#648; //Method scala/collection/Iterable$class.companion:(Lscala/collection/Iterable;)Lscala/collection/generic/GenericCompanion;
   4:	areturn
  LineNumberTable: 
   line 80: 0


}

