Compiled from "MetaData.scala"
public final class scala.xml.MetaData$$anonfun$iterator$1 extends scala.runtime.AbstractFunction0 implements java.io.Serializable
  SourceFile: "MetaData.scala"
  Scala: length = 0x
   
  InnerClass: 
   public final $anonfun$iterator$1=class scala/xml/MetaData$$anonfun$iterator$1 of class scala/xml/MetaData
  minor version: 0
  major version: 49
  Constant pool:
Asciz	SourceFile;
Asciz	MetaData.scala;
Asciz	<clinit>;
Asciz	()V;
Asciz	Code;
Asciz	serialVersionUID;
Asciz	J;
Asciz	scala/xml/MetaData$$anonfun$iterator$1;
class	scala/xml/MetaData$$anonfun$iterator$1
NameAndType	serialVersionUID:J
Field	scala/xml/MetaData$$anonfun$iterator$1.serialVersionUID:J
Asciz	$outer;
Asciz	Lscala/xml/MetaData;;
Asciz	apply;
Asciz	()Lscala/collection/Iterator;;
Asciz	LineNumberTable;
NameAndType	$outer:Lscala/xml/MetaData;
Field	scala/xml/MetaData$$anonfun$iterator$1.$outer:Lscala/xml/MetaData;
Asciz	scala/xml/MetaData;
class	scala/xml/MetaData
Asciz	next;
Asciz	()Lscala/xml/MetaData;;
NameAndType	next:()Lscala/xml/MetaData;
Method	scala/xml/MetaData.next:()Lscala/xml/MetaData;
Asciz	iterator;
NameAndType	iterator:()Lscala/collection/Iterator;
Method	scala/xml/MetaData.iterator:()Lscala/collection/Iterator;
Asciz	()Lscala/collection/Iterator<Lscala/xml/MetaData;>;;
Asciz	Signature;
Asciz	()Ljava/lang/Object;;
NameAndType	apply:()Lscala/collection/Iterator;
Method	scala/xml/MetaData$$anonfun$iterator$1.apply:()Lscala/collection/Iterator;
Asciz	<init>;
Asciz	(Lscala/xml/MetaData;)V;
Asciz	java/lang/NullPointerException;
class	java/lang/NullPointerException
NameAndType	"<init>":()V
Method	java/lang/NullPointerException."<init>":()V
Asciz	scala/runtime/AbstractFunction0;
class	scala/runtime/AbstractFunction0
Method	scala/runtime/AbstractFunction0."<init>":()V
Asciz	this;
Asciz	Lscala/xml/MetaData$$anonfun$iterator$1;;
Asciz	LocalVariableTable;
Asciz	Scala;
Asciz	InnerClasses;
Asciz	$anonfun$iterator$1;
Asciz	java/io/Serializable;
class	java/io/Serializable

{
public static final long serialVersionUID;
  Signature: J

public final scala.xml.MetaData $outer;
  Signature: Lscala/xml/MetaData;

public static {};
  Signature: ()V
  Code:
   Stack=2, Locals=0, Args_size=0
	lconst_0
	putstatic	Field serialVersionUID:J
	return
  Labels:

public final scala.collection.Iterator apply();
  Signature: ()Lscala/collection/Iterator;
  Code:
   Stack=1, Locals=1, Args_size=1
	aload_0
	getfield	Field $outer:Lscala/xml/MetaData;
	invokevirtual	Method scala/xml/MetaData.next:()Lscala/xml/MetaData;
	invokevirtual	Method scala/xml/MetaData.iterator:()Lscala/collection/Iterator;
	areturn
  Labels:
  Signature: length = 0x2
   00 1C 

public final java.lang.Object apply();
  Signature: ()Ljava/lang/Object;
  Code:
   Stack=1, Locals=1, Args_size=1
	aload_0
	invokevirtual	Method apply:()Lscala/collection/Iterator;
	areturn
  Labels:

public scala.xml.MetaData$$anonfun$iterator$1(scala.xml.MetaData);
  Signature: (Lscala/xml/MetaData;)V
  Code:
   Stack=2, Locals=2, Args_size=2
	aload_1
	ifnonnull	l1 // aload_0
	new	class java/lang/NullPointerException
	dup
	invokespecial	Method java/lang/NullPointerException."<init>":()V
	athrow
l1	aload_0
	aload_1
	putfield	Field $outer:Lscala/xml/MetaData;
	aload_0
	invokespecial	Method scala/runtime/AbstractFunction0."<init>":()V
	return
  Labels:
   	l1 = 12 // aload_0
  LocalVariableTable: 
   Start  Length  Slot  Name   Signature
   0      22      0    this       Lscala/xml/MetaData$$anonfun$iterator$1;
   0      22      1    $outer       Lscala/xml/MetaData;


}

