Compiled from "MetaData.scala"
public final class scala.xml.MetaData$ extends java.lang.Object implements scala.ScalaObject
  SourceFile: "MetaData.scala"
  Scala: length = 0x
   
  InnerClass: 
   public final $anonfun$equals$1=class scala/xml/MetaData$$anonfun$equals$1 of class scala/xml/MetaData
   public final $anonfun$toString$1=class scala/xml/MetaData$$anonfun$toString$1 of class scala/xml/MetaData
   public final $anonfun$iterator$2=class scala/xml/MetaData$$anonfun$iterator$2 of class scala/xml/MetaData
   public final $anonfun$iterator$1=class scala/xml/MetaData$$anonfun$iterator$1 of class scala/xml/MetaData
   public final $anonfun$toString1$1=class scala/xml/MetaData$$anonfun$toString1$1 of class scala/xml/MetaData
  minor version: 0
  major version: 49
  Constant pool:
Asciz	SourceFile;
Asciz	MetaData.scala;
Asciz	Scala;
Asciz	MODULE$;
Asciz	Lscala/xml/MetaData$;;
Asciz	<clinit>;
Asciz	()V;
Asciz	Code;
Asciz	scala/xml/MetaData$;
class	scala/xml/MetaData$
Asciz	<init>;
NameAndType	"<init>":()V
Method	scala/xml/MetaData$."<init>":()V
Asciz	LineNumberTable;
Asciz	java/lang/Object;
class	java/lang/Object
Method	java/lang/Object."<init>":()V
NameAndType	MODULE$:Lscala/xml/MetaData$;
Field	scala/xml/MetaData$.MODULE$:Lscala/xml/MetaData$;
Asciz	iterate$1;
Asciz	(Lscala/xml/MetaData;Lscala/xml/MetaData;Lscala/collection/immutable/Set;Lscala/xml/NamespaceBinding;)Lscala/xml/MetaData;;
Asciz	scala/runtime/IntRef;
class	scala/runtime/IntRef
Asciz	(I)V;
NameAndType	"<init>":(I)V
Method	scala/runtime/IntRef."<init>":(I)V
Asciz	scala/runtime/ObjectRef;
class	scala/runtime/ObjectRef
Asciz	(Ljava/lang/Object;)V;
NameAndType	"<init>":(Ljava/lang/Object;)V
Method	scala/runtime/ObjectRef."<init>":(Ljava/lang/Object;)V
Asciz	scala/xml/Null$;
class	scala/xml/Null$
Asciz	Lscala/xml/Null$;;
NameAndType	MODULE$:Lscala/xml/Null$;
Field	scala/xml/Null$.MODULE$:Lscala/xml/Null$;
Asciz	key$1;
Asciz	(Lscala/xml/NamespaceBinding;Lscala/xml/MetaData;Lscala/runtime/ObjectRef;Lscala/runtime/IntRef;)Ljava/lang/String;;
NameAndType	key$1:(Lscala/xml/NamespaceBinding;Lscala/xml/MetaData;Lscala/runtime/ObjectRef;Lscala/runtime/IntRef;)Ljava/lang/String;
Method	scala/xml/MetaData$.key$1:(Lscala/xml/NamespaceBinding;Lscala/xml/MetaData;Lscala/runtime/ObjectRef;Lscala/runtime/IntRef;)Ljava/lang/String;
Asciz	scala/collection/SetLike;
class	scala/collection/SetLike
Asciz	apply;
Asciz	(Ljava/lang/Object;)Z;
NameAndType	apply:(Ljava/lang/Object;)Z
InterfaceMethod	scala/collection/SetLike.apply:(Ljava/lang/Object;)Z
Asciz	scala/xml/MetaData;
class	scala/xml/MetaData
Asciz	next;
Asciz	()Lscala/xml/MetaData;;
NameAndType	next:()Lscala/xml/MetaData;
Method	scala/xml/MetaData.next:()Lscala/xml/MetaData;
Asciz	copy;
Asciz	(Lscala/xml/MetaData;)Lscala/xml/MetaData;;
NameAndType	copy:(Lscala/xml/MetaData;)Lscala/xml/MetaData;
Method	scala/xml/MetaData.copy:(Lscala/xml/MetaData;)Lscala/xml/MetaData;
Asciz	$plus;
Asciz	(Ljava/lang/Object;)Lscala/collection/Set;;
NameAndType	$plus:(Ljava/lang/Object;)Lscala/collection/Set;
InterfaceMethod	scala/collection/SetLike.$plus:(Ljava/lang/Object;)Lscala/collection/Set;
Asciz	scala/collection/immutable/Set;
class	scala/collection/immutable/Set
Asciz	this;
Asciz	md$1;
Asciz	Lscala/xml/MetaData;;
Asciz	normalized_attribs;
Asciz	set;
Asciz	Lscala/collection/immutable/Set;;
Asciz	key$lzy$1;
Asciz	Lscala/runtime/ObjectRef;;
Asciz	bitmap$0$1;
Asciz	Lscala/runtime/IntRef;;
Asciz	LocalVariableTable;
Asciz	elem;
Asciz	I;
NameAndType	elem:I
Field	scala/runtime/IntRef.elem:I
Asciz	getUniversalKey;
Asciz	(Lscala/xml/MetaData;Lscala/xml/NamespaceBinding;)Ljava/lang/String;;
NameAndType	getUniversalKey:(Lscala/xml/MetaData;Lscala/xml/NamespaceBinding;)Ljava/lang/String;
Method	scala/xml/MetaData$.getUniversalKey:(Lscala/xml/MetaData;Lscala/xml/NamespaceBinding;)Ljava/lang/String;
Asciz	Ljava/lang/Object;;
NameAndType	elem:Ljava/lang/Object;
Field	scala/runtime/ObjectRef.elem:Ljava/lang/Object;
Asciz	java/lang/String;
class	java/lang/String
Asciz	update;
Asciz	(Lscala/xml/MetaData;Lscala/xml/NamespaceBinding;Lscala/xml/MetaData;)Lscala/xml/MetaData;;
Asciz	concatenate;
Asciz	(Lscala/xml/MetaData;Lscala/xml/MetaData;)Lscala/xml/MetaData;;
NameAndType	concatenate:(Lscala/xml/MetaData;Lscala/xml/MetaData;)Lscala/xml/MetaData;
Method	scala/xml/MetaData$.concatenate:(Lscala/xml/MetaData;Lscala/xml/MetaData;)Lscala/xml/MetaData;
Asciz	normalize;
Asciz	(Lscala/xml/MetaData;Lscala/xml/NamespaceBinding;)Lscala/xml/MetaData;;
NameAndType	normalize:(Lscala/xml/MetaData;Lscala/xml/NamespaceBinding;)Lscala/xml/MetaData;
Method	scala/xml/MetaData$.normalize:(Lscala/xml/MetaData;Lscala/xml/NamespaceBinding;)Lscala/xml/MetaData;
Asciz	attribs;
Asciz	scope;
Asciz	Lscala/xml/NamespaceBinding;;
Asciz	updates;
Asciz	scala/xml/PrefixedAttribute;
class	scala/xml/PrefixedAttribute
Asciz	scala/collection/mutable/StringBuilder;
class	scala/collection/mutable/StringBuilder
Method	scala/collection/mutable/StringBuilder."<init>":()V
Asciz	pre;
Asciz	()Ljava/lang/String;;
NameAndType	pre:()Ljava/lang/String;
Method	scala/xml/PrefixedAttribute.pre:()Ljava/lang/String;
Asciz	scala/xml/NamespaceBinding;
class	scala/xml/NamespaceBinding
Asciz	getURI;
Asciz	(Ljava/lang/String;)Ljava/lang/String;;
NameAndType	getURI:(Ljava/lang/String;)Ljava/lang/String;
Method	scala/xml/NamespaceBinding.getURI:(Ljava/lang/String;)Ljava/lang/String;
Asciz	append;
Asciz	(Ljava/lang/Object;)Lscala/collection/mutable/StringBuilder;;
NameAndType	append:(Ljava/lang/Object;)Lscala/collection/mutable/StringBuilder;
Method	scala/collection/mutable/StringBuilder.append:(Ljava/lang/Object;)Lscala/collection/mutable/StringBuilder;
Asciz	key;
NameAndType	key:()Ljava/lang/String;
Method	scala/xml/PrefixedAttribute.key:()Ljava/lang/String;
Asciz	toString;
NameAndType	toString:()Ljava/lang/String;
Method	scala/collection/mutable/StringBuilder.toString:()Ljava/lang/String;
Asciz	scala/xml/UnprefixedAttribute;
class	scala/xml/UnprefixedAttribute
Method	scala/xml/UnprefixedAttribute.key:()Ljava/lang/String;
Asciz	scala/MatchError;
class	scala/MatchError
Method	scala/xml/MetaData.toString:()Ljava/lang/String;
Asciz	(Ljava/lang/String;)V;
NameAndType	"<init>":(Ljava/lang/String;)V
Method	scala/MatchError."<init>":(Ljava/lang/String;)V
Asciz	attrib;
Asciz	temp2;
Asciz	Lscala/xml/PrefixedAttribute;;
Asciz	temp3;
Asciz	Lscala/xml/UnprefixedAttribute;;
Asciz	scala/Predef$;
class	scala/Predef$
Asciz	Lscala/Predef$;;
NameAndType	MODULE$:Lscala/Predef$;
Field	scala/Predef$.MODULE$:Lscala/Predef$;
Asciz	Set;
Asciz	()Lscala/collection/immutable/Set$;;
NameAndType	Set:()Lscala/collection/immutable/Set$;
Method	scala/Predef$.Set:()Lscala/collection/immutable/Set$;
Asciz	[Ljava/lang/Object;;
class	"[Ljava/lang/Object;"
Asciz	wrapRefArray;
Asciz	([Ljava/lang/Object;)Lscala/collection/mutable/WrappedArray;;
NameAndType	wrapRefArray:([Ljava/lang/Object;)Lscala/collection/mutable/WrappedArray;
Method	scala/Predef$.wrapRefArray:([Ljava/lang/Object;)Lscala/collection/mutable/WrappedArray;
Asciz	scala/collection/immutable/Set$;
class	scala/collection/immutable/Set$
Asciz	(Lscala/collection/Seq;)Lscala/collection/Traversable;;
NameAndType	apply:(Lscala/collection/Seq;)Lscala/collection/Traversable;
Method	scala/collection/immutable/Set$.apply:(Lscala/collection/Seq;)Lscala/collection/Traversable;
NameAndType	iterate$1:(Lscala/xml/MetaData;Lscala/xml/MetaData;Lscala/collection/immutable/Set;Lscala/xml/NamespaceBinding;)Lscala/xml/MetaData;
Method	scala/xml/MetaData$.iterate$1:(Lscala/xml/MetaData;Lscala/xml/MetaData;Lscala/collection/immutable/Set;Lscala/xml/NamespaceBinding;)Lscala/xml/MetaData;
Asciz	scope$1;
Asciz	new_tail;
Asciz	InnerClasses;
Asciz	scala/xml/MetaData$$anonfun$equals$1;
class	scala/xml/MetaData$$anonfun$equals$1
Asciz	$anonfun$equals$1;
Asciz	scala/xml/MetaData$$anonfun$toString$1;
class	scala/xml/MetaData$$anonfun$toString$1
Asciz	$anonfun$toString$1;
Asciz	scala/xml/MetaData$$anonfun$iterator$2;
class	scala/xml/MetaData$$anonfun$iterator$2
Asciz	$anonfun$iterator$2;
Asciz	scala/xml/MetaData$$anonfun$iterator$1;
class	scala/xml/MetaData$$anonfun$iterator$1
Asciz	$anonfun$iterator$1;
Asciz	scala/xml/MetaData$$anonfun$toString1$1;
class	scala/xml/MetaData$$anonfun$toString1$1
Asciz	$anonfun$toString1$1;
Asciz	scala/ScalaObject;
class	scala/ScalaObject

{
public static final scala.xml.MetaData$ MODULE$;
  Signature: Lscala/xml/MetaData$;

public static {};
  Signature: ()V
  Code:
   Stack=1, Locals=0, Args_size=0
	new	class scala/xml/MetaData$
	invokespecial	Method "<init>":()V
	return
  Labels:

private scala.xml.MetaData$();
  Signature: ()V
  Code:
   Stack=1, Locals=1, Args_size=1
	aload_0
	invokespecial	Method java/lang/Object."<init>":()V
	aload_0
	putstatic	Field MODULE$:Lscala/xml/MetaData$;
	return
  Labels:

private final scala.xml.MetaData iterate$1(scala.xml.MetaData, scala.xml.MetaData, scala.collection.immutable.Set, scala.xml.NamespaceBinding);
  Signature: (Lscala/xml/MetaData;Lscala/xml/MetaData;Lscala/collection/immutable/Set;Lscala/xml/NamespaceBinding;)Lscala/xml/MetaData;
  Code:
   Stack=8, Locals=7, Args_size=5
l3	new	class scala/runtime/IntRef
	dup
	iconst_0
	invokespecial	Method scala/runtime/IntRef."<init>":(I)V
	astore	6
	new	class scala/runtime/ObjectRef
	dup
	aconst_null
	invokespecial	Method scala/runtime/ObjectRef."<init>":(Ljava/lang/Object;)V
	astore	5
	aload_1
	getstatic	Field scala/xml/Null$.MODULE$:Lscala/xml/Null$;
	if_acmpne	l1 // aload_3
	aload_2
	areturn
l1	aload_3
	aload_0
	aload	4
	aload_1
	aload	5
	aload	6
	invokespecial	Method key$1:(Lscala/xml/NamespaceBinding;Lscala/xml/MetaData;Lscala/runtime/ObjectRef;Lscala/runtime/IntRef;)Ljava/lang/String;
	invokeinterface	InterfaceMethod scala/collection/SetLike.apply:(Ljava/lang/Object;)Z
	ifeq	l2 // aload_1
	aload_1
	invokevirtual	Method scala/xml/MetaData.next:()Lscala/xml/MetaData;
	astore_1
	goto	l3 // new
l2	aload_1
	invokevirtual	Method scala/xml/MetaData.next:()Lscala/xml/MetaData;
	aload_1
	aload_2
	invokevirtual	Method scala/xml/MetaData.copy:(Lscala/xml/MetaData;)Lscala/xml/MetaData;
	aload_3
	aload_0
	aload	4
	aload_1
	aload	5
	aload	6
	invokespecial	Method key$1:(Lscala/xml/NamespaceBinding;Lscala/xml/MetaData;Lscala/runtime/ObjectRef;Lscala/runtime/IntRef;)Ljava/lang/String;
	invokeinterface	InterfaceMethod scala/collection/SetLike.$plus:(Ljava/lang/Object;)Lscala/collection/Set;
	checkcast	class scala/collection/immutable/Set
	astore_3
	astore_2
	astore_1
	goto	l3 // new
  Labels:
   	l3 = 0 // new
   	l1 = 29 // aload_3
   	l2 = 57 // aload_1
  LocalVariableTable: 
   Start  Length  Slot  Name   Signature
   0      92      0    this       Lscala/xml/MetaData$;
   0      92      1    md$1       Lscala/xml/MetaData;
   0      92      2    normalized_attribs       Lscala/xml/MetaData;
   0      92      3    set       Lscala/collection/immutable/Set;
   20      72      5    key$lzy$1       Lscala/runtime/ObjectRef;
   10      82      6    bitmap$0$1       Lscala/runtime/IntRef;


private final java.lang.String key$1(scala.xml.NamespaceBinding, scala.xml.MetaData, scala.runtime.ObjectRef, scala.runtime.IntRef);
  Signature: (Lscala/xml/NamespaceBinding;Lscala/xml/MetaData;Lscala/runtime/ObjectRef;Lscala/runtime/IntRef;)Ljava/lang/String;
  Code:
   Stack=4, Locals=5, Args_size=5
	aload	4
	getfield	Field scala/runtime/IntRef.elem:I
	iconst_1
	iand
	iconst_0
	if_icmpne	l1 // aload_3
	aload_3
	aload_0
	aload_2
	aload_1
	invokevirtual	Method getUniversalKey:(Lscala/xml/MetaData;Lscala/xml/NamespaceBinding;)Ljava/lang/String;
	putfield	Field scala/runtime/ObjectRef.elem:Ljava/lang/Object;
	aload	4
	aload	4
	getfield	Field scala/runtime/IntRef.elem:I
	iconst_1
	ior
	putfield	Field scala/runtime/IntRef.elem:I
l1	aload_3
	getfield	Field scala/runtime/ObjectRef.elem:Ljava/lang/Object;
	checkcast	class java/lang/String
	areturn
  Labels:
   	l1 = 33 // aload_3

public scala.xml.MetaData update(scala.xml.MetaData, scala.xml.NamespaceBinding, scala.xml.MetaData);
  Signature: (Lscala/xml/MetaData;Lscala/xml/NamespaceBinding;Lscala/xml/MetaData;)Lscala/xml/MetaData;
  Code:
   Stack=4, Locals=4, Args_size=4
	aload_0
	aload_0
	aload_3
	aload_1
	invokevirtual	Method concatenate:(Lscala/xml/MetaData;Lscala/xml/MetaData;)Lscala/xml/MetaData;
	aload_2
	invokevirtual	Method normalize:(Lscala/xml/MetaData;Lscala/xml/NamespaceBinding;)Lscala/xml/MetaData;
	areturn
  Labels:
  LocalVariableTable: 
   Start  Length  Slot  Name   Signature
   0      12      0    this       Lscala/xml/MetaData$;
   0      12      1    attribs       Lscala/xml/MetaData;
   0      12      2    scope       Lscala/xml/NamespaceBinding;
   0      12      3    updates       Lscala/xml/MetaData;


public java.lang.String getUniversalKey(scala.xml.MetaData, scala.xml.NamespaceBinding);
  Signature: (Lscala/xml/MetaData;Lscala/xml/NamespaceBinding;)Ljava/lang/String;
  Code:
   Stack=3, Locals=5, Args_size=3
	aload_1
	instanceof	class scala/xml/PrefixedAttribute
	ifeq	l1 // aload_1
	aload_1
	checkcast	class scala/xml/PrefixedAttribute
	astore_3
	new	class scala/collection/mutable/StringBuilder
	dup
	invokespecial	Method scala/collection/mutable/StringBuilder."<init>":()V
	aload_2
	aload_3
	invokevirtual	Method scala/xml/PrefixedAttribute.pre:()Ljava/lang/String;
	invokevirtual	Method scala/xml/NamespaceBinding.getURI:(Ljava/lang/String;)Ljava/lang/String;
	invokevirtual	Method scala/collection/mutable/StringBuilder.append:(Ljava/lang/Object;)Lscala/collection/mutable/StringBuilder;
	aload_3
	invokevirtual	Method scala/xml/PrefixedAttribute.key:()Ljava/lang/String;
	invokevirtual	Method scala/collection/mutable/StringBuilder.append:(Ljava/lang/Object;)Lscala/collection/mutable/StringBuilder;
	invokevirtual	Method scala/collection/mutable/StringBuilder.toString:()Ljava/lang/String;
	goto	l2 // areturn
l1	aload_1
	instanceof	class scala/xml/UnprefixedAttribute
	ifeq	l3 // new
	aload_1
	checkcast	class scala/xml/UnprefixedAttribute
	astore	4
	aload	4
	invokevirtual	Method scala/xml/UnprefixedAttribute.key:()Ljava/lang/String;
l2	areturn
l3	new	class scala/MatchError
	dup
	aload_1
	invokevirtual	Method scala/xml/MetaData.toString:()Ljava/lang/String;
	invokespecial	Method scala/MatchError."<init>":(Ljava/lang/String;)V
	athrow
  Labels:
   	l1 = 43 // aload_1
   	l2 = 61 // areturn
   	l3 = 62 // new
  LocalVariableTable: 
   Start  Length  Slot  Name   Signature
   0      74      0    this       Lscala/xml/MetaData$;
   0      74      1    attrib       Lscala/xml/MetaData;
   0      74      2    scope       Lscala/xml/NamespaceBinding;
   12      28      3    temp2       Lscala/xml/PrefixedAttribute;
   56      5      4    temp3       Lscala/xml/UnprefixedAttribute;


public scala.xml.MetaData normalize(scala.xml.MetaData, scala.xml.NamespaceBinding);
  Signature: (Lscala/xml/MetaData;Lscala/xml/NamespaceBinding;)Lscala/xml/MetaData;
  Code:
   Stack=6, Locals=3, Args_size=3
	aload_0
	aload_1
	getstatic	Field scala/xml/Null$.MODULE$:Lscala/xml/Null$;
	getstatic	Field scala/Predef$.MODULE$:Lscala/Predef$;
	invokevirtual	Method scala/Predef$.Set:()Lscala/collection/immutable/Set$;
	getstatic	Field scala/Predef$.MODULE$:Lscala/Predef$;
	iconst_0
	anewarray	class java/lang/String
	checkcast	class "[Ljava/lang/Object;"
	invokevirtual	Method scala/Predef$.wrapRefArray:([Ljava/lang/Object;)Lscala/collection/mutable/WrappedArray;
	invokevirtual	Method scala/collection/immutable/Set$.apply:(Lscala/collection/Seq;)Lscala/collection/Traversable;
	checkcast	class scala/collection/immutable/Set
	aload_2
	invokespecial	Method iterate$1:(Lscala/xml/MetaData;Lscala/xml/MetaData;Lscala/collection/immutable/Set;Lscala/xml/NamespaceBinding;)Lscala/xml/MetaData;
	areturn
  Labels:
  LocalVariableTable: 
   Start  Length  Slot  Name   Signature
   0      35      0    this       Lscala/xml/MetaData$;
   0      35      1    attribs       Lscala/xml/MetaData;
   0      35      2    scope$1       Lscala/xml/NamespaceBinding;


public scala.xml.MetaData concatenate(scala.xml.MetaData, scala.xml.MetaData);
  Signature: (Lscala/xml/MetaData;Lscala/xml/MetaData;)Lscala/xml/MetaData;
  Code:
   Stack=3, Locals=3, Args_size=3
l2	aload_1
	getstatic	Field scala/xml/Null$.MODULE$:Lscala/xml/Null$;
	if_acmpne	l1 // aload_1
	aload_2
	areturn
l1	aload_1
	invokevirtual	Method scala/xml/MetaData.next:()Lscala/xml/MetaData;
	aload_1
	aload_2
	invokevirtual	Method scala/xml/MetaData.copy:(Lscala/xml/MetaData;)Lscala/xml/MetaData;
	astore_2
	astore_1
	goto	l2 // aload_1
  Labels:
   	l2 = 0 // aload_1
   	l1 = 9 // aload_1
  LocalVariableTable: 
   Start  Length  Slot  Name   Signature
   0      23      0    this       Lscala/xml/MetaData$;
   0      23      1    attribs       Lscala/xml/MetaData;
   0      23      2    new_tail       Lscala/xml/MetaData;


}

