Compiled from "MetaData.scala"
public abstract class scala.xml.MetaData extends java.lang.Object implements scala.collection.Iterable,scala.xml.Equality,scala.ScalaObject,java.io.Serializable
  SourceFile: "MetaData.scala"
  Signature: length = 0x2
   02 FFFFFFE8 
  ScalaSig: length = 0x766
   05 00 FFFFFF82 0C 07 05 01 02 FFFFFF88 02 07 01 08 4D 65 74
   61 44 61 74 61 0A 02 03 04 01 03 78 6D 6C 0A 01
   05 01 05 73 63 61 6C 61 03 00 10 02 08 09 0D 01
   02 06 08 0A 02 FFFFFF84 FFFFFF80 FFFFFF80 FFFFFF88 02 0B 02 08 4D 65 74
   61 44 61 74 61 13 03 09 0C 14 10 02 0D 12 0D 01
   0E 0A 02 0F 10 01 04 6C 61 6E 67 0A 01 11 01 04
   6A 61 76 61 09 02 13 0E 02 06 4F 62 6A 65 63 74
   10 02 15 16 0D 01 04 09 02 17 04 02 0B 53 63 61
   6C 61 4F 62 6A 65 63 74 08 05 19 09 FFFFFF84 00 1A 01
   06 3C 69 6E 69 74 3E 14 01 07 08 05 1C 09 FFFFFF84 00
   1D 01 0B 63 6F 6E 63 61 74 65 6E 61 74 65 14 05
   1E FFFFFF81 72 FFFFFF81 74 10 02 08 1F 06 08 0A 02 FFFFFF84 FFFFFF80 FFFFFF80
   FFFFFF81 00 20 13 05 1F 0C 21 2D 14 10 03 22 2A 1E 0E
   02 23 28 0E 02 24 27 0D 01 25 0A 02 26 06 01 06
   3C 72 6F 6F 74 3E 09 01 05 09 02 29 04 01 07 70
   61 63 6B 61 67 65 09 02 2B 2C 02 08 49 74 65 72
   61 62 6C 65 0A 02 29 04 10 02 08 2E 09 02 2F 02
   02 08 45 71 75 61 6C 69 74 79 08 05 19 1F FFFFFF84 00
   31 14 01 1E 08 05 33 1F FFFFFF84 00 34 01 06 61 70 70
   65 6E 64 14 03 1E 35 37 08 05 36 32 FFFFFFC0 00 1E 01
   07 75 70 64 61 74 65 73 08 07 38 32 FFFFFF90 FFFFFF80 FFFFFFC0 00
   39 01 05 73 63 6F 70 65 10 02 08 3A 09 02 3B 02
   02 10 4E 61 6D 65 73 70 61 63 65 42 69 6E 64 69
   6E 67 08 05 3D 1F FFFFFF86 00 3E 01 05 61 70 70 6C 79
   14 02 3F 45 10 03 22 40 42 09 02 41 2C 02 03 53
   65 71 10 02 08 43 09 02 44 02 02 04 4E 6F 64 65
   08 05 46 3C FFFFFFC0 00 47 01 03 6B 65 79 10 02 48 4B
   0E 02 15 49 09 02 4A 04 01 06 50 72 65 64 65 66
   09 02 4C 4D 02 06 53 74 72 69 6E 67 0A 02 4A 04
   08 05 3D 1F FFFFFF84 02 4F 14 04 3F 50 52 54 08 05 51
   4E FFFFFFC0 00 47 01 0D 6E 61 6D 65 73 70 61 63 65 5F
   75 72 69 08 05 53 4E FFFFFFC0 00 42 01 05 6F 77 6E 65
   72 08 05 46 4E FFFFFFC0 00 47 08 05 3D 1F FFFFFF86 00 56 14
   04 3F 57 58 5A 08 05 51 55 FFFFFFC0 00 47 08 05 59 55
   FFFFFFC0 00 39 01 03 73 63 70 08 05 5B 55 FFFFFFC0 00 47 01
   01 6B 08 05 5D 1F FFFFFF86 00 5E 01 04 63 6F 70 79 14
   02 1E 5F 08 05 60 5C FFFFFFC0 00 1E 01 04 6E 65 78 74
   08 05 62 1F FFFFFF86 00 63 01 0C 67 65 74 4E 61 6D 65
   73 70 61 63 65 14 02 47 64 08 05 53 61 FFFFFFC0 00 42
   08 05 66 1F FFFFFF84 00 67 01 07 68 61 73 4E 65 78 74
   15 01 68 10 02 15 69 09 02 6A 04 02 07 42 6F 6F
   6C 65 61 6E 08 05 6C 1F FFFFFF84 00 6D 01 06 6C 65 6E
   67 74 68 15 01 6E 10 02 15 6F 09 02 70 04 02 03
   49 6E 74 08 05 6C 1F FFFFFF84 00 72 14 02 6E 73 08 05
   74 71 FFFFFFC0 00 6E 01 01 69 08 05 76 1F FFFFFF86 00 67 01
   0A 69 73 50 72 65 66 69 78 65 64 08 05 78 1F FFFFFF84
   20 79 01 08 63 61 6E 45 71 75 61 6C 14 02 68 7A
   08 05 7B 77 FFFFFFC0 00 7C 01 05 6F 74 68 65 72 10 02
   15 7D 09 02 7E 04 02 03 41 6E 79 08 07 FFFFFF81 00 1F
   FFFFFF84 20 FFFFFF81 01 01 0D 73 74 72 69 63 74 5F 24 65 71
   24 65 71 14 03 68 FFFFFF81 02 08 05 7B 7F FFFFFFC0 00 2D 08
   07 FFFFFF81 04 1F FFFFFF84 00 FFFFFF81 05 01 10 62 61 73 69 73 46
   6F 72 48 61 73 68 43 6F 64 65 15 02 FFFFFF81 06 10 03
   22 40 7C 08 07 FFFFFF81 08 1F FFFFFF84 00 FFFFFF81 09 01 08 69 74
   65 72 61 74 6F 72 15 02 FFFFFF81 0A 10 04 22 FFFFFF81 0B 1E
   09 03 FFFFFF81 0C 2C 02 08 49 74 65 72 61 74 6F 72 08
   06 FFFFFF81 0E 1F FFFFFF84 20 6D 01 04 73 69 7A 65 08 07 FFFFFF81
   10 1F FFFFFF84 20 FFFFFF81 11 01 06 66 69 6C 74 65 72 14 03
   1E FFFFFF81 12 08 08 FFFFFF81 13 FFFFFF81 0F FFFFFFC0 00 FFFFFF81 14 01 01 66
   10 05 15 FFFFFF81 15 1E 68 09 03 FFFFFF81 16 04 02 09 46 75
   6E 63 74 69 6F 6E 31 08 06 46 1F FFFFFF86 00 FFFFFF81 18 15
   01 47 08 07 FFFFFF81 1A 1F FFFFFF86 00 FFFFFF81 1B 01 05 76 61 6C
   75 65 15 01 3F 08 07 FFFFFF81 1D 1F FFFFFF84 00 FFFFFF81 1E 01 0B
   70 72 65 66 69 78 65 64 4B 65 79 15 02 FFFFFF81 1F 10
   03 0D FFFFFF81 20 09 02 4C 0E 08 07 FFFFFF81 22 1F FFFFFF84 00 FFFFFF81
   23 01 09 61 73 41 74 74 72 4D 61 70 15 02 FFFFFF81 24
   10 05 48 FFFFFF81 25 47 47 09 03 FFFFFF81 26 4D 02 03 4D 61
   70 08 06 60 1F FFFFFF86 00 FFFFFF81 28 15 01 1E 08 07 FFFFFF81 2A
   1F FFFFFF84 02 FFFFFF81 2B 01 03 67 65 74 14 04 FFFFFF81 2C FFFFFF81 2F
   10 04 15 FFFFFF81 2D 3F 09 03 FFFFFF81 2E 04 02 06 4F 70 74
   69 6F 6E 08 06 46 FFFFFF81 29 FFFFFFC0 00 47 08 07 FFFFFF81 2A 1F
   FFFFFF84 02 FFFFFF81 31 14 08 FFFFFF81 2C FFFFFF81 32 FFFFFF81 34 FFFFFF81 35 08 07
   FFFFFF81 33 FFFFFF81 30 FFFFFFC0 00 47 01 03 75 72 69 08 06 53 FFFFFF81
   30 FFFFFFC0 00 42 08 06 46 FFFFFF81 30 FFFFFFC0 00 47 08 07 FFFFFF81 2A
   1F FFFFFF84 02 FFFFFF81 37 14 08 FFFFFF81 2C FFFFFF81 38 FFFFFF81 39 FFFFFF81 3A 08
   07 FFFFFF81 33 FFFFFF81 36 FFFFFFC0 00 47 08 06 38 FFFFFF81 36 FFFFFFC0 00 39
   08 06 46 FFFFFF81 36 FFFFFFC0 00 47 08 07 FFFFFF81 3C 1F FFFFFF84 00 FFFFFF81
   3D 01 09 74 6F 53 74 72 69 6E 67 31 14 01 47 08
   07 FFFFFF81 3C 1F FFFFFF86 00 FFFFFF81 3F 14 04 FFFFFF81 40 FFFFFF81 43 10 03
   15 FFFFFF81 41 09 03 FFFFFF81 42 04 02 04 55 6E 69 74 08 08
   FFFFFF81 44 FFFFFF81 3E FFFFFFC0 00 FFFFFF81 45 01 02 73 62 10 03 22 FFFFFF81
   46 09 03 FFFFFF81 47 2C 02 0D 53 74 72 69 6E 67 42 75
   69 6C 64 65 72 08 07 FFFFFF81 49 1F FFFFFF84 20 FFFFFF81 3D 01 08
   74 6F 53 74 72 69 6E 67 08 07 FFFFFF81 4B 1F FFFFFF84 00 FFFFFF81
   4C 01 0B 62 75 69 6C 64 53 74 72 69 6E 67 14 04
   FFFFFF81 45 FFFFFF81 4D 08 08 FFFFFF81 44 FFFFFF81 4A FFFFFFC0 00 FFFFFF81 45 08 07
   FFFFFF81 4F 1F FFFFFF86 00 FFFFFF81 50 01 0A 77 65 6C 6C 66 6F 72
   6D 65 64 14 03 68 FFFFFF81 51 08 06 38 FFFFFF81 4E FFFFFFC0 00 39
   08 07 FFFFFF81 53 1F FFFFFF86 00 FFFFFF81 54 01 06 72 65 6D 6F 76
   65 14 03 1E FFFFFF81 55 08 06 46 FFFFFF81 52 FFFFFFC0 00 47 08 07
   FFFFFF81 53 1F FFFFFF86 00 FFFFFF81 57 14 07 1E FFFFFF81 58 FFFFFF81 5A FFFFFF81 5B
   08 07 FFFFFF81 59 FFFFFF81 56 FFFFFFC0 00 47 01 09 6E 61 6D 65 73
   70 61 63 65 08 06 38 FFFFFF81 56 FFFFFFC0 00 39 08 06 46 FFFFFF81
   56 FFFFFFC0 00 47 08 07 FFFFFF81 53 1F FFFFFF84 02 FFFFFF81 5D 14 07 1E
   FFFFFF81 5E FFFFFF81 5F FFFFFF81 60 08 07 FFFFFF81 59 FFFFFF81 5C FFFFFFC0 00 47 08
   06 53 FFFFFF81 5C FFFFFFC0 00 42 08 06 46 FFFFFF81 5C FFFFFFC0 00 47 08
   09 FFFFFF81 62 1F FFFFFF91 FFFFFF80 FFFFFF84 00 FFFFFF81 63 01 10 61 70 70 65
   6E 64 24 64 65 66 61 75 6C 74 24 32 15 02 FFFFFF81 64
   2A 03 39 FFFFFF81 65 2B 02 FFFFFF81 66 10 04 FFFFFF81 67 FFFFFF81 6C 0D
   02 FFFFFF81 68 0A 04 FFFFFF81 69 FFFFFF81 6A 01 09 75 6E 63 68 65
   63 6B 65 64 0A 03 FFFFFF81 6B 04 01 0A 61 6E 6E 6F 74
   61 74 69 6F 6E 09 04 FFFFFF81 6D FFFFFF81 68 02 11 75 6E 63
   68 65 63 6B 65 64 56 61 72 69 61 6E 63 65 28 03
   1F FFFFFF81 6F 10 03 15 FFFFFF81 70 09 03 FFFFFF81 71 04 02 0C 73
   65 72 69 61 6C 69 7A 61 62 6C 65 08 06 FFFFFF81 73 1B
   FFFFFFC0 00 1E 01 07 61 74 74 72 69 62 73 08 06 FFFFFF81 75
   1B FFFFFFC0 00 1E 01 08 6E 65 77 5F 74 61 69 6C 28 03
   1B FFFFFF81 77 10 04 FFFFFF81 78 FFFFFF81 79 0D 02 FFFFFF81 6A 09 04 FFFFFF81
   7A FFFFFF81 6A 02 07 74 61 69 6C 72 65 63 08 07 FFFFFF81 7C
   09 FFFFFF84 00 FFFFFF81 7D 01 09 6E 6F 72 6D 61 6C 69 7A 65
   14 05 1E FFFFFF81 7E FFFFFF81 7F 08 07 FFFFFF81 73 FFFFFF81 7B FFFFFFC0 00 1E
   08 06 38 FFFFFF81 7B FFFFFFC0 00 39 08 07 FFFFFF82 01 09 FFFFFF84 00 FFFFFF82
   02 01 0F 67 65 74 55 6E 69 76 65 72 73 61 6C 4B
   65 79 14 06 FFFFFF81 1F FFFFFF82 03 FFFFFF82 05 08 07 FFFFFF82 04 FFFFFF82 00
   FFFFFFC0 00 1E 01 06 61 74 74 72 69 62 08 06 38 FFFFFF82 00
   FFFFFFC0 00 39 08 07 FFFFFF82 07 09 FFFFFF84 00 FFFFFF82 08 01 06 75 70
   64 61 74 65 14 07 1E FFFFFF82 09 FFFFFF82 0A FFFFFF82 0B 08 07 FFFFFF81
   73 FFFFFF82 06 FFFFFFC0 00 1E 08 06 38 FFFFFF82 06 FFFFFFC0 00 39 08 06
   36 FFFFFF82 06 FFFFFFC0 00 1E 
  InnerClass: 
   public abstract $less$colon$less=class scala/Predef$$less$colon$less of class scala/Predef
   public WithFilter=class scala/collection/TraversableLike$WithFilter of class scala/collection/TraversableLike
   public final $anonfun$toString$1=class scala/xml/MetaData$$anonfun$toString$1 of class scala/xml/MetaData
   public final $anonfun$iterator$1=class scala/xml/MetaData$$anonfun$iterator$1 of class scala/xml/MetaData
   public final $anonfun$toString1$1=class scala/xml/MetaData$$anonfun$toString1$1 of class scala/xml/MetaData
   public final $anonfun$asAttrMap$1=class scala/xml/MetaData$$anonfun$asAttrMap$1 of class scala/xml/MetaData
  minor version: 0
  major version: 49
  Constant pool:
Asciz	SourceFile;
Asciz	MetaData.scala;
Asciz	update;
Asciz	(Lscala/xml/MetaData;Lscala/xml/NamespaceBinding;Lscala/xml/MetaData;)Lscala/xml/MetaData;;
Asciz	Code;
Asciz	scala/xml/MetaData$;
class	scala/xml/MetaData$
Asciz	MODULE$;
Asciz	Lscala/xml/MetaData$;;
NameAndType	MODULE$:Lscala/xml/MetaData$;
Field	scala/xml/MetaData$.MODULE$:Lscala/xml/MetaData$;
NameAndType	update:(Lscala/xml/MetaData;Lscala/xml/NamespaceBinding;Lscala/xml/MetaData;)Lscala/xml/MetaData;
Method	scala/xml/MetaData$.update:(Lscala/xml/MetaData;Lscala/xml/NamespaceBinding;Lscala/xml/MetaData;)Lscala/xml/MetaData;
Asciz	getUniversalKey;
Asciz	(Lscala/xml/MetaData;Lscala/xml/NamespaceBinding;)Ljava/lang/String;;
NameAndType	getUniversalKey:(Lscala/xml/MetaData;Lscala/xml/NamespaceBinding;)Ljava/lang/String;
Method	scala/xml/MetaData$.getUniversalKey:(Lscala/xml/MetaData;Lscala/xml/NamespaceBinding;)Ljava/lang/String;
Asciz	normalize;
Asciz	(Lscala/xml/MetaData;Lscala/xml/NamespaceBinding;)Lscala/xml/MetaData;;
NameAndType	normalize:(Lscala/xml/MetaData;Lscala/xml/NamespaceBinding;)Lscala/xml/MetaData;
Method	scala/xml/MetaData$.normalize:(Lscala/xml/MetaData;Lscala/xml/NamespaceBinding;)Lscala/xml/MetaData;
Asciz	concatenate;
Asciz	(Lscala/xml/MetaData;Lscala/xml/MetaData;)Lscala/xml/MetaData;;
NameAndType	concatenate:(Lscala/xml/MetaData;Lscala/xml/MetaData;)Lscala/xml/MetaData;
Method	scala/xml/MetaData$.concatenate:(Lscala/xml/MetaData;Lscala/xml/MetaData;)Lscala/xml/MetaData;
Asciz	strict_$bang$eq;
Asciz	(Lscala/xml/Equality;)Z;
Asciz	LineNumberTable;
Asciz	scala/xml/Equality$class;
class	scala/xml/Equality$class
Asciz	(Lscala/xml/Equality;Lscala/xml/Equality;)Z;
NameAndType	strict_$bang$eq:(Lscala/xml/Equality;Lscala/xml/Equality;)Z
Method	scala/xml/Equality$class.strict_$bang$eq:(Lscala/xml/Equality;Lscala/xml/Equality;)Z
Asciz	this;
Asciz	Lscala/xml/MetaData;;
Asciz	other;
Asciz	Lscala/xml/Equality;;
Asciz	LocalVariableTable;
Asciz	hashCode;
Asciz	()I;
Asciz	(Lscala/xml/Equality;)I;
NameAndType	hashCode:(Lscala/xml/Equality;)I
Method	scala/xml/Equality$class.hashCode:(Lscala/xml/Equality;)I
Asciz	equals;
Asciz	(Ljava/lang/Object;)Z;
Asciz	(Lscala/xml/Equality;Ljava/lang/Object;)Z;
NameAndType	equals:(Lscala/xml/Equality;Ljava/lang/Object;)Z
Method	scala/xml/Equality$class.equals:(Lscala/xml/Equality;Ljava/lang/Object;)Z
Asciz	Ljava/lang/Object;;
Asciz	xml_$eq$eq;
NameAndType	xml_$eq$eq:(Lscala/xml/Equality;Ljava/lang/Object;)Z
Method	scala/xml/Equality$class.xml_$eq$eq:(Lscala/xml/Equality;Ljava/lang/Object;)Z
Asciz	xml_$bang$eq;
NameAndType	xml_$bang$eq:(Lscala/xml/Equality;Ljava/lang/Object;)Z
Method	scala/xml/Equality$class.xml_$bang$eq:(Lscala/xml/Equality;Ljava/lang/Object;)Z
Asciz	companion;
Asciz	()Lscala/collection/generic/GenericCompanion;;
Asciz	scala/collection/Iterable$class;
class	scala/collection/Iterable$class
Asciz	(Lscala/collection/Iterable;)Lscala/collection/generic/GenericCompanion;;
NameAndType	companion:(Lscala/collection/Iterable;)Lscala/collection/generic/GenericCompanion;
Method	scala/collection/Iterable$class.companion:(Lscala/collection/Iterable;)Lscala/collection/generic/GenericCompanion;
Asciz	thisCollection;
Asciz	()Lscala/collection/Iterable;;
Asciz	scala/collection/IterableLike$class;
class	scala/collection/IterableLike$class
Asciz	(Lscala/collection/IterableLike;)Lscala/collection/Iterable;;
NameAndType	thisCollection:(Lscala/collection/IterableLike;)Lscala/collection/Iterable;
Method	scala/collection/IterableLike$class.thisCollection:(Lscala/collection/IterableLike;)Lscala/collection/Iterable;
Asciz	toCollection;
Asciz	(Ljava/lang/Object;)Lscala/collection/Iterable;;
Asciz	(Lscala/collection/IterableLike;Ljava/lang/Object;)Lscala/collection/Iterable;;
NameAndType	toCollection:(Lscala/collection/IterableLike;Ljava/lang/Object;)Lscala/collection/Iterable;
Method	scala/collection/IterableLike$class.toCollection:(Lscala/collection/IterableLike;Ljava/lang/Object;)Lscala/collection/Iterable;
Asciz	repr;
Asciz	elements;
Asciz	()Lscala/collection/Iterator;;
Asciz	(Lscala/collection/IterableLike;)Lscala/collection/Iterator;;
NameAndType	elements:(Lscala/collection/IterableLike;)Lscala/collection/Iterator;
Method	scala/collection/IterableLike$class.elements:(Lscala/collection/IterableLike;)Lscala/collection/Iterator;
Asciz	Deprecated;
Asciz	foreach;
Asciz	(Lscala/Function1;)V;
Asciz	(Lscala/collection/IterableLike;Lscala/Function1;)V;
NameAndType	foreach:(Lscala/collection/IterableLike;Lscala/Function1;)V
Method	scala/collection/IterableLike$class.foreach:(Lscala/collection/IterableLike;Lscala/Function1;)V
Asciz	f;
Asciz	Lscala/Function1;;
Asciz	forall;
Asciz	(Lscala/Function1;)Z;
Asciz	(Lscala/collection/IterableLike;Lscala/Function1;)Z;
NameAndType	forall:(Lscala/collection/IterableLike;Lscala/Function1;)Z
Method	scala/collection/IterableLike$class.forall:(Lscala/collection/IterableLike;Lscala/Function1;)Z
Asciz	p;
Asciz	exists;
NameAndType	exists:(Lscala/collection/IterableLike;Lscala/Function1;)Z
Method	scala/collection/IterableLike$class.exists:(Lscala/collection/IterableLike;Lscala/Function1;)Z
Asciz	find;
Asciz	(Lscala/Function1;)Lscala/Option;;
Asciz	(Lscala/collection/IterableLike;Lscala/Function1;)Lscala/Option;;
NameAndType	find:(Lscala/collection/IterableLike;Lscala/Function1;)Lscala/Option;
Method	scala/collection/IterableLike$class.find:(Lscala/collection/IterableLike;Lscala/Function1;)Lscala/Option;
Asciz	isEmpty;
Asciz	()Z;
Asciz	(Lscala/collection/IterableLike;)Z;
NameAndType	isEmpty:(Lscala/collection/IterableLike;)Z
Method	scala/collection/IterableLike$class.isEmpty:(Lscala/collection/IterableLike;)Z
Asciz	foldRight;
Asciz	(Ljava/lang/Object;Lscala/Function2;)Ljava/lang/Object;;
Asciz	(Lscala/collection/IterableLike;Ljava/lang/Object;Lscala/Function2;)Ljava/lang/Object;;
NameAndType	foldRight:(Lscala/collection/IterableLike;Ljava/lang/Object;Lscala/Function2;)Ljava/lang/Object;
Method	scala/collection/IterableLike$class.foldRight:(Lscala/collection/IterableLike;Ljava/lang/Object;Lscala/Function2;)Ljava/lang/Object;
Asciz	z;
Asciz	op;
Asciz	Lscala/Function2;;
Asciz	reduceRight;
Asciz	(Lscala/Function2;)Ljava/lang/Object;;
Asciz	(Lscala/collection/IterableLike;Lscala/Function2;)Ljava/lang/Object;;
NameAndType	reduceRight:(Lscala/collection/IterableLike;Lscala/Function2;)Ljava/lang/Object;
Method	scala/collection/IterableLike$class.reduceRight:(Lscala/collection/IterableLike;Lscala/Function2;)Ljava/lang/Object;
Asciz	toIterable;
NameAndType	toIterable:(Lscala/collection/IterableLike;)Lscala/collection/Iterable;
Method	scala/collection/IterableLike$class.toIterable:(Lscala/collection/IterableLike;)Lscala/collection/Iterable;
Asciz	head;
Asciz	()Ljava/lang/Object;;
Asciz	(Lscala/collection/IterableLike;)Ljava/lang/Object;;
NameAndType	head:(Lscala/collection/IterableLike;)Ljava/lang/Object;
Method	scala/collection/IterableLike$class.head:(Lscala/collection/IterableLike;)Ljava/lang/Object;
Asciz	take;
Asciz	(I)Ljava/lang/Object;;
Asciz	(Lscala/collection/IterableLike;I)Ljava/lang/Object;;
NameAndType	take:(Lscala/collection/IterableLike;I)Ljava/lang/Object;
Method	scala/collection/IterableLike$class.take:(Lscala/collection/IterableLike;I)Ljava/lang/Object;
Asciz	n;
Asciz	I;
Asciz	slice;
Asciz	(II)Ljava/lang/Object;;
Asciz	(Lscala/collection/IterableLike;II)Ljava/lang/Object;;
NameAndType	slice:(Lscala/collection/IterableLike;II)Ljava/lang/Object;
Method	scala/collection/IterableLike$class.slice:(Lscala/collection/IterableLike;II)Ljava/lang/Object;
Asciz	from;
Asciz	until;
Asciz	takeWhile;
Asciz	(Lscala/Function1;)Ljava/lang/Object;;
Asciz	(Lscala/collection/IterableLike;Lscala/Function1;)Ljava/lang/Object;;
NameAndType	takeWhile:(Lscala/collection/IterableLike;Lscala/Function1;)Ljava/lang/Object;
Method	scala/collection/IterableLike$class.takeWhile:(Lscala/collection/IterableLike;Lscala/Function1;)Ljava/lang/Object;
Asciz	grouped;
Asciz	(I)Lscala/collection/Iterator;;
Asciz	(Lscala/collection/IterableLike;I)Lscala/collection/Iterator;;
NameAndType	grouped:(Lscala/collection/IterableLike;I)Lscala/collection/Iterator;
Method	scala/collection/IterableLike$class.grouped:(Lscala/collection/IterableLike;I)Lscala/collection/Iterator;
Asciz	size;
Asciz	sliding;
NameAndType	sliding:(Lscala/collection/IterableLike;I)Lscala/collection/Iterator;
Method	scala/collection/IterableLike$class.sliding:(Lscala/collection/IterableLike;I)Lscala/collection/Iterator;
Asciz	(II)Lscala/collection/Iterator;;
Asciz	(Lscala/collection/IterableLike;II)Lscala/collection/Iterator;;
NameAndType	sliding:(Lscala/collection/IterableLike;II)Lscala/collection/Iterator;
Method	scala/collection/IterableLike$class.sliding:(Lscala/collection/IterableLike;II)Lscala/collection/Iterator;
Asciz	step;
Asciz	takeRight;
NameAndType	takeRight:(Lscala/collection/IterableLike;I)Ljava/lang/Object;
Method	scala/collection/IterableLike$class.takeRight:(Lscala/collection/IterableLike;I)Ljava/lang/Object;
Asciz	dropRight;
NameAndType	dropRight:(Lscala/collection/IterableLike;I)Ljava/lang/Object;
Method	scala/collection/IterableLike$class.dropRight:(Lscala/collection/IterableLike;I)Ljava/lang/Object;
Asciz	copyToArray;
Asciz	(Ljava/lang/Object;II)V;
Asciz	(Lscala/collection/IterableLike;Ljava/lang/Object;II)V;
NameAndType	copyToArray:(Lscala/collection/IterableLike;Ljava/lang/Object;II)V
Method	scala/collection/IterableLike$class.copyToArray:(Lscala/collection/IterableLike;Ljava/lang/Object;II)V
Asciz	xs;
Asciz	start;
Asciz	len;
Asciz	zip;
Asciz	(Lscala/collection/Iterable;Lscala/collection/generic/CanBuildFrom;)Ljava/lang/Object;;
Asciz	(Lscala/collection/IterableLike;Lscala/collection/Iterable;Lscala/collection/generic/CanBuildFrom;)Ljava/lang/Object;;
NameAndType	zip:(Lscala/collection/IterableLike;Lscala/collection/Iterable;Lscala/collection/generic/CanBuildFrom;)Ljava/lang/Object;
Method	scala/collection/IterableLike$class.zip:(Lscala/collection/IterableLike;Lscala/collection/Iterable;Lscala/collection/generic/CanBuildFrom;)Ljava/lang/Object;
Asciz	that;
Asciz	Lscala/collection/Iterable;;
Asciz	bf;
Asciz	Lscala/collection/generic/CanBuildFrom;;
Asciz	zipAll;
Asciz	(Lscala/collection/Iterable;Ljava/lang/Object;Ljava/lang/Object;Lscala/collection/generic/CanBuildFrom;)Ljava/lang/Object;;
Asciz	(Lscala/collection/IterableLike;Lscala/collection/Iterable;Ljava/lang/Object;Ljava/lang/Object;Lscala/collection/generic/CanBuildFrom;)Ljava/lang/Object;;
NameAndType	zipAll:(Lscala/collection/IterableLike;Lscala/collection/Iterable;Ljava/lang/Object;Ljava/lang/Object;Lscala/collection/generic/CanBuildFrom;)Ljava/lang/Object;
Method	scala/collection/IterableLike$class.zipAll:(Lscala/collection/IterableLike;Lscala/collection/Iterable;Ljava/lang/Object;Ljava/lang/Object;Lscala/collection/generic/CanBuildFrom;)Ljava/lang/Object;
Asciz	thisElem;
Asciz	thatElem;
Asciz	zipWithIndex;
Asciz	(Lscala/collection/generic/CanBuildFrom;)Ljava/lang/Object;;
Asciz	(Lscala/collection/IterableLike;Lscala/collection/generic/CanBuildFrom;)Ljava/lang/Object;;
NameAndType	zipWithIndex:(Lscala/collection/IterableLike;Lscala/collection/generic/CanBuildFrom;)Ljava/lang/Object;
Method	scala/collection/IterableLike$class.zipWithIndex:(Lscala/collection/IterableLike;Lscala/collection/generic/CanBuildFrom;)Ljava/lang/Object;
Asciz	sameElements;
Asciz	(Lscala/collection/Iterable;)Z;
Asciz	(Lscala/collection/IterableLike;Lscala/collection/Iterable;)Z;
NameAndType	sameElements:(Lscala/collection/IterableLike;Lscala/collection/Iterable;)Z
Method	scala/collection/IterableLike$class.sameElements:(Lscala/collection/IterableLike;Lscala/collection/Iterable;)Z
Asciz	toStream;
Asciz	()Lscala/collection/immutable/Stream;;
Asciz	(Lscala/collection/IterableLike;)Lscala/collection/immutable/Stream;;
NameAndType	toStream:(Lscala/collection/IterableLike;)Lscala/collection/immutable/Stream;
Method	scala/collection/IterableLike$class.toStream:(Lscala/collection/IterableLike;)Lscala/collection/immutable/Stream;
Asciz	view;
Asciz	()Lscala/collection/IterableView;;
Asciz	(Lscala/collection/IterableLike;)Lscala/collection/IterableView;;
NameAndType	view:(Lscala/collection/IterableLike;)Lscala/collection/IterableView;
Method	scala/collection/IterableLike$class.view:(Lscala/collection/IterableLike;)Lscala/collection/IterableView;
Asciz	(II)Lscala/collection/IterableView;;
Asciz	(Lscala/collection/IterableLike;II)Lscala/collection/IterableView;;
NameAndType	view:(Lscala/collection/IterableLike;II)Lscala/collection/IterableView;
Method	scala/collection/IterableLike$class.view:(Lscala/collection/IterableLike;II)Lscala/collection/IterableView;
Asciz	first;
NameAndType	first:(Lscala/collection/IterableLike;)Ljava/lang/Object;
Method	scala/collection/IterableLike$class.first:(Lscala/collection/IterableLike;)Ljava/lang/Object;
Asciz	firstOption;
Asciz	()Lscala/Option;;
Asciz	(Lscala/collection/IterableLike;)Lscala/Option;;
NameAndType	firstOption:(Lscala/collection/IterableLike;)Lscala/Option;
Method	scala/collection/IterableLike$class.firstOption:(Lscala/collection/IterableLike;)Lscala/Option;
Asciz	projection;
NameAndType	projection:(Lscala/collection/IterableLike;)Lscala/collection/IterableView;
Method	scala/collection/IterableLike$class.projection:(Lscala/collection/IterableLike;)Lscala/collection/IterableView;
Asciz	newBuilder;
Asciz	()Lscala/collection/mutable/Builder;;
Asciz	scala/collection/generic/GenericTraversableTemplate$class;
class	scala/collection/generic/GenericTraversableTemplate$class
Asciz	(Lscala/collection/generic/GenericTraversableTemplate;)Lscala/collection/mutable/Builder;;
NameAndType	newBuilder:(Lscala/collection/generic/GenericTraversableTemplate;)Lscala/collection/mutable/Builder;
Method	scala/collection/generic/GenericTraversableTemplate$class.newBuilder:(Lscala/collection/generic/GenericTraversableTemplate;)Lscala/collection/mutable/Builder;
Asciz	genericBuilder;
NameAndType	genericBuilder:(Lscala/collection/generic/GenericTraversableTemplate;)Lscala/collection/mutable/Builder;
Method	scala/collection/generic/GenericTraversableTemplate$class.genericBuilder:(Lscala/collection/generic/GenericTraversableTemplate;)Lscala/collection/mutable/Builder;
Asciz	unzip;
Asciz	(Lscala/Function1;)Lscala/Tuple2;;
Asciz	(Lscala/collection/generic/GenericTraversableTemplate;Lscala/Function1;)Lscala/Tuple2;;
NameAndType	unzip:(Lscala/collection/generic/GenericTraversableTemplate;Lscala/Function1;)Lscala/Tuple2;
Method	scala/collection/generic/GenericTraversableTemplate$class.unzip:(Lscala/collection/generic/GenericTraversableTemplate;Lscala/Function1;)Lscala/Tuple2;
Asciz	asPair;
Asciz	flatten;
Asciz	(Lscala/Function1;)Lscala/collection/Traversable;;
Asciz	(Lscala/collection/generic/GenericTraversableTemplate;Lscala/Function1;)Lscala/collection/Traversable;;
NameAndType	flatten:(Lscala/collection/generic/GenericTraversableTemplate;Lscala/Function1;)Lscala/collection/Traversable;
Method	scala/collection/generic/GenericTraversableTemplate$class.flatten:(Lscala/collection/generic/GenericTraversableTemplate;Lscala/Function1;)Lscala/collection/Traversable;
Asciz	asTraversable;
Asciz	transpose;
NameAndType	transpose:(Lscala/collection/generic/GenericTraversableTemplate;Lscala/Function1;)Lscala/collection/Traversable;
Method	scala/collection/generic/GenericTraversableTemplate$class.transpose:(Lscala/collection/generic/GenericTraversableTemplate;Lscala/Function1;)Lscala/collection/Traversable;
Asciz	scala/collection/TraversableLike$class;
class	scala/collection/TraversableLike$class
Asciz	(Lscala/collection/TraversableLike;)Ljava/lang/Object;;
NameAndType	repr:(Lscala/collection/TraversableLike;)Ljava/lang/Object;
Method	scala/collection/TraversableLike$class.repr:(Lscala/collection/TraversableLike;)Ljava/lang/Object;
Asciz	nonEmpty;
Asciz	(Lscala/collection/TraversableLike;)Z;
NameAndType	nonEmpty:(Lscala/collection/TraversableLike;)Z
Method	scala/collection/TraversableLike$class.nonEmpty:(Lscala/collection/TraversableLike;)Z
Asciz	hasDefiniteSize;
NameAndType	hasDefiniteSize:(Lscala/collection/TraversableLike;)Z
Method	scala/collection/TraversableLike$class.hasDefiniteSize:(Lscala/collection/TraversableLike;)Z
Asciz	$plus$plus;
Asciz	(Lscala/collection/Traversable;Lscala/collection/generic/CanBuildFrom;)Ljava/lang/Object;;
Asciz	(Lscala/collection/TraversableLike;Lscala/collection/Traversable;Lscala/collection/generic/CanBuildFrom;)Ljava/lang/Object;;
NameAndType	$plus$plus:(Lscala/collection/TraversableLike;Lscala/collection/Traversable;Lscala/collection/generic/CanBuildFrom;)Ljava/lang/Object;
Method	scala/collection/TraversableLike$class.$plus$plus:(Lscala/collection/TraversableLike;Lscala/collection/Traversable;Lscala/collection/generic/CanBuildFrom;)Ljava/lang/Object;
Asciz	Lscala/collection/Traversable;;
Asciz	(Lscala/collection/Iterator;Lscala/collection/generic/CanBuildFrom;)Ljava/lang/Object;;
Asciz	(Lscala/collection/TraversableLike;Lscala/collection/Iterator;Lscala/collection/generic/CanBuildFrom;)Ljava/lang/Object;;
NameAndType	$plus$plus:(Lscala/collection/TraversableLike;Lscala/collection/Iterator;Lscala/collection/generic/CanBuildFrom;)Ljava/lang/Object;
Method	scala/collection/TraversableLike$class.$plus$plus:(Lscala/collection/TraversableLike;Lscala/collection/Iterator;Lscala/collection/generic/CanBuildFrom;)Ljava/lang/Object;
Asciz	Lscala/collection/Iterator;;
Asciz	map;
Asciz	(Lscala/Function1;Lscala/collection/generic/CanBuildFrom;)Ljava/lang/Object;;
Asciz	(Lscala/collection/TraversableLike;Lscala/Function1;Lscala/collection/generic/CanBuildFrom;)Ljava/lang/Object;;
NameAndType	map:(Lscala/collection/TraversableLike;Lscala/Function1;Lscala/collection/generic/CanBuildFrom;)Ljava/lang/Object;
Method	scala/collection/TraversableLike$class.map:(Lscala/collection/TraversableLike;Lscala/Function1;Lscala/collection/generic/CanBuildFrom;)Ljava/lang/Object;
Asciz	flatMap;
NameAndType	flatMap:(Lscala/collection/TraversableLike;Lscala/Function1;Lscala/collection/generic/CanBuildFrom;)Ljava/lang/Object;
Method	scala/collection/TraversableLike$class.flatMap:(Lscala/collection/TraversableLike;Lscala/Function1;Lscala/collection/generic/CanBuildFrom;)Ljava/lang/Object;
Asciz	filterNot;
Asciz	(Lscala/collection/TraversableLike;Lscala/Function1;)Ljava/lang/Object;;
NameAndType	filterNot:(Lscala/collection/TraversableLike;Lscala/Function1;)Ljava/lang/Object;
Method	scala/collection/TraversableLike$class.filterNot:(Lscala/collection/TraversableLike;Lscala/Function1;)Ljava/lang/Object;
Asciz	partialMap;
Asciz	(Lscala/PartialFunction;Lscala/collection/generic/CanBuildFrom;)Ljava/lang/Object;;
Asciz	(Lscala/collection/TraversableLike;Lscala/PartialFunction;Lscala/collection/generic/CanBuildFrom;)Ljava/lang/Object;;
NameAndType	partialMap:(Lscala/collection/TraversableLike;Lscala/PartialFunction;Lscala/collection/generic/CanBuildFrom;)Ljava/lang/Object;
Method	scala/collection/TraversableLike$class.partialMap:(Lscala/collection/TraversableLike;Lscala/PartialFunction;Lscala/collection/generic/CanBuildFrom;)Ljava/lang/Object;
Asciz	pf;
Asciz	Lscala/PartialFunction;;
Asciz	partition;
Asciz	(Lscala/collection/TraversableLike;Lscala/Function1;)Lscala/Tuple2;;
NameAndType	partition:(Lscala/collection/TraversableLike;Lscala/Function1;)Lscala/Tuple2;
Method	scala/collection/TraversableLike$class.partition:(Lscala/collection/TraversableLike;Lscala/Function1;)Lscala/Tuple2;
Asciz	groupBy;
Asciz	(Lscala/Function1;)Lscala/collection/Map;;
Asciz	(Lscala/collection/TraversableLike;Lscala/Function1;)Lscala/collection/Map;;
NameAndType	groupBy:(Lscala/collection/TraversableLike;Lscala/Function1;)Lscala/collection/Map;
Method	scala/collection/TraversableLike$class.groupBy:(Lscala/collection/TraversableLike;Lscala/Function1;)Lscala/collection/Map;
Asciz	count;
Asciz	(Lscala/Function1;)I;
Asciz	(Lscala/collection/TraversableLike;Lscala/Function1;)I;
NameAndType	count:(Lscala/collection/TraversableLike;Lscala/Function1;)I
Method	scala/collection/TraversableLike$class.count:(Lscala/collection/TraversableLike;Lscala/Function1;)I
Asciz	foldLeft;
Asciz	(Lscala/collection/TraversableLike;Ljava/lang/Object;Lscala/Function2;)Ljava/lang/Object;;
NameAndType	foldLeft:(Lscala/collection/TraversableLike;Ljava/lang/Object;Lscala/Function2;)Ljava/lang/Object;
Method	scala/collection/TraversableLike$class.foldLeft:(Lscala/collection/TraversableLike;Ljava/lang/Object;Lscala/Function2;)Ljava/lang/Object;
Asciz	$div$colon;
NameAndType	$div$colon:(Lscala/collection/TraversableLike;Ljava/lang/Object;Lscala/Function2;)Ljava/lang/Object;
Method	scala/collection/TraversableLike$class.$div$colon:(Lscala/collection/TraversableLike;Ljava/lang/Object;Lscala/Function2;)Ljava/lang/Object;
Asciz	$colon$bslash;
NameAndType	$colon$bslash:(Lscala/collection/TraversableLike;Ljava/lang/Object;Lscala/Function2;)Ljava/lang/Object;
Method	scala/collection/TraversableLike$class.$colon$bslash:(Lscala/collection/TraversableLike;Ljava/lang/Object;Lscala/Function2;)Ljava/lang/Object;
Asciz	reduceLeft;
Asciz	(Lscala/collection/TraversableLike;Lscala/Function2;)Ljava/lang/Object;;
NameAndType	reduceLeft:(Lscala/collection/TraversableLike;Lscala/Function2;)Ljava/lang/Object;
Method	scala/collection/TraversableLike$class.reduceLeft:(Lscala/collection/TraversableLike;Lscala/Function2;)Ljava/lang/Object;
Asciz	reduceLeftOption;
Asciz	(Lscala/Function2;)Lscala/Option;;
Asciz	(Lscala/collection/TraversableLike;Lscala/Function2;)Lscala/Option;;
NameAndType	reduceLeftOption:(Lscala/collection/TraversableLike;Lscala/Function2;)Lscala/Option;
Method	scala/collection/TraversableLike$class.reduceLeftOption:(Lscala/collection/TraversableLike;Lscala/Function2;)Lscala/Option;
Asciz	reduceRightOption;
NameAndType	reduceRightOption:(Lscala/collection/TraversableLike;Lscala/Function2;)Lscala/Option;
Method	scala/collection/TraversableLike$class.reduceRightOption:(Lscala/collection/TraversableLike;Lscala/Function2;)Lscala/Option;
Asciz	sum;
Asciz	(Lscala/math/Numeric;)Ljava/lang/Object;;
Asciz	(Lscala/collection/TraversableLike;Lscala/math/Numeric;)Ljava/lang/Object;;
NameAndType	sum:(Lscala/collection/TraversableLike;Lscala/math/Numeric;)Ljava/lang/Object;
Method	scala/collection/TraversableLike$class.sum:(Lscala/collection/TraversableLike;Lscala/math/Numeric;)Ljava/lang/Object;
Asciz	num;
Asciz	Lscala/math/Numeric;;
Asciz	product;
NameAndType	product:(Lscala/collection/TraversableLike;Lscala/math/Numeric;)Ljava/lang/Object;
Method	scala/collection/TraversableLike$class.product:(Lscala/collection/TraversableLike;Lscala/math/Numeric;)Ljava/lang/Object;
Asciz	min;
Asciz	(Lscala/math/Ordering;)Ljava/lang/Object;;
Asciz	(Lscala/collection/TraversableLike;Lscala/math/Ordering;)Ljava/lang/Object;;
NameAndType	min:(Lscala/collection/TraversableLike;Lscala/math/Ordering;)Ljava/lang/Object;
Method	scala/collection/TraversableLike$class.min:(Lscala/collection/TraversableLike;Lscala/math/Ordering;)Ljava/lang/Object;
Asciz	cmp;
Asciz	Lscala/math/Ordering;;
Asciz	max;
NameAndType	max:(Lscala/collection/TraversableLike;Lscala/math/Ordering;)Ljava/lang/Object;
Method	scala/collection/TraversableLike$class.max:(Lscala/collection/TraversableLike;Lscala/math/Ordering;)Ljava/lang/Object;
Asciz	headOption;
Asciz	(Lscala/collection/TraversableLike;)Lscala/Option;;
NameAndType	headOption:(Lscala/collection/TraversableLike;)Lscala/Option;
Method	scala/collection/TraversableLike$class.headOption:(Lscala/collection/TraversableLike;)Lscala/Option;
Asciz	tail;
NameAndType	tail:(Lscala/collection/TraversableLike;)Ljava/lang/Object;
Method	scala/collection/TraversableLike$class.tail:(Lscala/collection/TraversableLike;)Ljava/lang/Object;
Asciz	last;
NameAndType	last:(Lscala/collection/TraversableLike;)Ljava/lang/Object;
Method	scala/collection/TraversableLike$class.last:(Lscala/collection/TraversableLike;)Ljava/lang/Object;
Asciz	lastOption;
NameAndType	lastOption:(Lscala/collection/TraversableLike;)Lscala/Option;
Method	scala/collection/TraversableLike$class.lastOption:(Lscala/collection/TraversableLike;)Lscala/Option;
Asciz	init;
NameAndType	init:(Lscala/collection/TraversableLike;)Ljava/lang/Object;
Method	scala/collection/TraversableLike$class.init:(Lscala/collection/TraversableLike;)Ljava/lang/Object;
Asciz	drop;
Asciz	(Lscala/collection/TraversableLike;I)Ljava/lang/Object;;
NameAndType	drop:(Lscala/collection/TraversableLike;I)Ljava/lang/Object;
Method	scala/collection/TraversableLike$class.drop:(Lscala/collection/TraversableLike;I)Ljava/lang/Object;
Asciz	dropWhile;
NameAndType	dropWhile:(Lscala/collection/TraversableLike;Lscala/Function1;)Ljava/lang/Object;
Method	scala/collection/TraversableLike$class.dropWhile:(Lscala/collection/TraversableLike;Lscala/Function1;)Ljava/lang/Object;
Asciz	span;
NameAndType	span:(Lscala/collection/TraversableLike;Lscala/Function1;)Lscala/Tuple2;
Method	scala/collection/TraversableLike$class.span:(Lscala/collection/TraversableLike;Lscala/Function1;)Lscala/Tuple2;
Asciz	splitAt;
Asciz	(I)Lscala/Tuple2;;
Asciz	(Lscala/collection/TraversableLike;I)Lscala/Tuple2;;
NameAndType	splitAt:(Lscala/collection/TraversableLike;I)Lscala/Tuple2;
Method	scala/collection/TraversableLike$class.splitAt:(Lscala/collection/TraversableLike;I)Lscala/Tuple2;
Asciz	copyToBuffer;
Asciz	(Lscala/collection/mutable/Buffer;)V;
Asciz	(Lscala/collection/TraversableLike;Lscala/collection/mutable/Buffer;)V;
NameAndType	copyToBuffer:(Lscala/collection/TraversableLike;Lscala/collection/mutable/Buffer;)V
Method	scala/collection/TraversableLike$class.copyToBuffer:(Lscala/collection/TraversableLike;Lscala/collection/mutable/Buffer;)V
Asciz	dest;
Asciz	Lscala/collection/mutable/Buffer;;
Asciz	(Ljava/lang/Object;I)V;
Asciz	(Lscala/collection/TraversableLike;Ljava/lang/Object;I)V;
NameAndType	copyToArray:(Lscala/collection/TraversableLike;Ljava/lang/Object;I)V
Method	scala/collection/TraversableLike$class.copyToArray:(Lscala/collection/TraversableLike;Ljava/lang/Object;I)V
Asciz	(Ljava/lang/Object;)V;
Asciz	(Lscala/collection/TraversableLike;Ljava/lang/Object;)V;
NameAndType	copyToArray:(Lscala/collection/TraversableLike;Ljava/lang/Object;)V
Method	scala/collection/TraversableLike$class.copyToArray:(Lscala/collection/TraversableLike;Ljava/lang/Object;)V
Asciz	toArray;
Asciz	(Lscala/reflect/ClassManifest;)Ljava/lang/Object;;
Asciz	(Lscala/collection/TraversableLike;Lscala/reflect/ClassManifest;)Ljava/lang/Object;;
NameAndType	toArray:(Lscala/collection/TraversableLike;Lscala/reflect/ClassManifest;)Ljava/lang/Object;
Method	scala/collection/TraversableLike$class.toArray:(Lscala/collection/TraversableLike;Lscala/reflect/ClassManifest;)Ljava/lang/Object;
Asciz	evidence$1;
Asciz	Lscala/reflect/ClassManifest;;
Asciz	toList;
Asciz	()Lscala/collection/immutable/List;;
Asciz	(Lscala/collection/TraversableLike;)Lscala/collection/immutable/List;;
NameAndType	toList:(Lscala/collection/TraversableLike;)Lscala/collection/immutable/List;
Method	scala/collection/TraversableLike$class.toList:(Lscala/collection/TraversableLike;)Lscala/collection/immutable/List;
Asciz	toSeq;
Asciz	()Lscala/collection/Seq;;
Asciz	(Lscala/collection/TraversableLike;)Lscala/collection/Seq;;
NameAndType	toSeq:(Lscala/collection/TraversableLike;)Lscala/collection/Seq;
Method	scala/collection/TraversableLike$class.toSeq:(Lscala/collection/TraversableLike;)Lscala/collection/Seq;
Asciz	toIndexedSeq;
Asciz	()Lscala/collection/mutable/IndexedSeq;;
Asciz	(Lscala/collection/TraversableLike;)Lscala/collection/mutable/IndexedSeq;;
NameAndType	toIndexedSeq:(Lscala/collection/TraversableLike;)Lscala/collection/mutable/IndexedSeq;
Method	scala/collection/TraversableLike$class.toIndexedSeq:(Lscala/collection/TraversableLike;)Lscala/collection/mutable/IndexedSeq;
Asciz	toSet;
Asciz	()Lscala/collection/immutable/Set;;
Asciz	(Lscala/collection/TraversableLike;)Lscala/collection/immutable/Set;;
NameAndType	toSet:(Lscala/collection/TraversableLike;)Lscala/collection/immutable/Set;
Method	scala/collection/TraversableLike$class.toSet:(Lscala/collection/TraversableLike;)Lscala/collection/immutable/Set;
Asciz	toMap;
Asciz	(Lscala/Predef$$less$colon$less;)Lscala/collection/immutable/Map;;
Asciz	(Lscala/collection/TraversableLike;Lscala/Predef$$less$colon$less;)Lscala/collection/immutable/Map;;
NameAndType	toMap:(Lscala/collection/TraversableLike;Lscala/Predef$$less$colon$less;)Lscala/collection/immutable/Map;
Method	scala/collection/TraversableLike$class.toMap:(Lscala/collection/TraversableLike;Lscala/Predef$$less$colon$less;)Lscala/collection/immutable/Map;
Asciz	ev;
Asciz	Lscala/Predef$$less$colon$less;;
Asciz	mkString;
Asciz	(Ljava/lang/String;Ljava/lang/String;Ljava/lang/String;)Ljava/lang/String;;
Asciz	(Lscala/collection/TraversableLike;Ljava/lang/String;Ljava/lang/String;Ljava/lang/String;)Ljava/lang/String;;
NameAndType	mkString:(Lscala/collection/TraversableLike;Ljava/lang/String;Ljava/lang/String;Ljava/lang/String;)Ljava/lang/String;
Method	scala/collection/TraversableLike$class.mkString:(Lscala/collection/TraversableLike;Ljava/lang/String;Ljava/lang/String;Ljava/lang/String;)Ljava/lang/String;
Asciz	Ljava/lang/String;;
Asciz	sep;
Asciz	end;
Asciz	(Ljava/lang/String;)Ljava/lang/String;;
Asciz	(Lscala/collection/TraversableLike;Ljava/lang/String;)Ljava/lang/String;;
NameAndType	mkString:(Lscala/collection/TraversableLike;Ljava/lang/String;)Ljava/lang/String;
Method	scala/collection/TraversableLike$class.mkString:(Lscala/collection/TraversableLike;Ljava/lang/String;)Ljava/lang/String;
Asciz	()Ljava/lang/String;;
Asciz	(Lscala/collection/TraversableLike;)Ljava/lang/String;;
NameAndType	mkString:(Lscala/collection/TraversableLike;)Ljava/lang/String;
Method	scala/collection/TraversableLike$class.mkString:(Lscala/collection/TraversableLike;)Ljava/lang/String;
Asciz	addString;
Asciz	(Lscala/collection/mutable/StringBuilder;Ljava/lang/String;Ljava/lang/String;Ljava/lang/String;)Lscala/collection/mutable/StringBuilder;;
Asciz	(Lscala/collection/TraversableLike;Lscala/collection/mutable/StringBuilder;Ljava/lang/String;Ljava/lang/String;Ljava/lang/String;)Lscala/collection/mutable/StringBuilder;;
NameAndType	addString:(Lscala/collection/TraversableLike;Lscala/collection/mutable/StringBuilder;Ljava/lang/String;Ljava/lang/String;Ljava/lang/String;)Lscala/collection/mutable/StringBuilder;
Method	scala/collection/TraversableLike$class.addString:(Lscala/collection/TraversableLike;Lscala/collection/mutable/StringBuilder;Ljava/lang/String;Ljava/lang/String;Ljava/lang/String;)Lscala/collection/mutable/StringBuilder;
Asciz	b;
Asciz	Lscala/collection/mutable/StringBuilder;;
Asciz	(Lscala/collection/mutable/StringBuilder;Ljava/lang/String;)Lscala/collection/mutable/StringBuilder;;
Asciz	(Lscala/collection/TraversableLike;Lscala/collection/mutable/StringBuilder;Ljava/lang/String;)Lscala/collection/mutable/StringBuilder;;
NameAndType	addString:(Lscala/collection/TraversableLike;Lscala/collection/mutable/StringBuilder;Ljava/lang/String;)Lscala/collection/mutable/StringBuilder;
Method	scala/collection/TraversableLike$class.addString:(Lscala/collection/TraversableLike;Lscala/collection/mutable/StringBuilder;Ljava/lang/String;)Lscala/collection/mutable/StringBuilder;
Asciz	(Lscala/collection/mutable/StringBuilder;)Lscala/collection/mutable/StringBuilder;;
Asciz	(Lscala/collection/TraversableLike;Lscala/collection/mutable/StringBuilder;)Lscala/collection/mutable/StringBuilder;;
NameAndType	addString:(Lscala/collection/TraversableLike;Lscala/collection/mutable/StringBuilder;)Lscala/collection/mutable/StringBuilder;
Method	scala/collection/TraversableLike$class.addString:(Lscala/collection/TraversableLike;Lscala/collection/mutable/StringBuilder;)Lscala/collection/mutable/StringBuilder;
Asciz	stringPrefix;
NameAndType	stringPrefix:(Lscala/collection/TraversableLike;)Ljava/lang/String;
Method	scala/collection/TraversableLike$class.stringPrefix:(Lscala/collection/TraversableLike;)Ljava/lang/String;
Asciz	withFilter;
Asciz	(Lscala/Function1;)Lscala/collection/TraversableLike$WithFilter;;
Asciz	(Lscala/collection/TraversableLike;Lscala/Function1;)Lscala/collection/TraversableLike$WithFilter;;
NameAndType	withFilter:(Lscala/collection/TraversableLike;Lscala/Function1;)Lscala/collection/TraversableLike$WithFilter;
Method	scala/collection/TraversableLike$class.withFilter:(Lscala/collection/TraversableLike;Lscala/Function1;)Lscala/collection/TraversableLike$WithFilter;
Asciz	Signature;
Asciz	append$default$2;
Asciz	()Lscala/xml/NamespaceBinding;;
Asciz	scala/xml/TopScope$;
class	scala/xml/TopScope$
Asciz	Lscala/xml/TopScope$;;
NameAndType	MODULE$:Lscala/xml/TopScope$;
Field	scala/xml/TopScope$.MODULE$:Lscala/xml/TopScope$;
Asciz	append;
Asciz	updates;
Asciz	scope;
Asciz	Lscala/xml/NamespaceBinding;;
Asciz	apply;
Asciz	(Ljava/lang/String;)Lscala/collection/Seq;;
Asciz	(Ljava/lang/String;)Lscala/collection/Seq<Lscala/xml/Node;>;;
Asciz	(Ljava/lang/String;Lscala/xml/Node;Ljava/lang/String;)Lscala/collection/Seq;;
Asciz	scala/xml/Node;
class	scala/xml/Node
NameAndType	scope:()Lscala/xml/NamespaceBinding;
Method	scala/xml/Node.scope:()Lscala/xml/NamespaceBinding;
Asciz	scala/xml/MetaData;
class	scala/xml/MetaData
Asciz	(Ljava/lang/String;Lscala/xml/NamespaceBinding;Ljava/lang/String;)Lscala/collection/Seq;;
NameAndType	apply:(Ljava/lang/String;Lscala/xml/NamespaceBinding;Ljava/lang/String;)Lscala/collection/Seq;
Method	scala/xml/MetaData.apply:(Ljava/lang/String;Lscala/xml/NamespaceBinding;Ljava/lang/String;)Lscala/collection/Seq;
Asciz	namespace_uri;
Asciz	owner;
Asciz	Lscala/xml/Node;;
Asciz	key;
Asciz	(Ljava/lang/String;Lscala/xml/Node;Ljava/lang/String;)Lscala/collection/Seq<Lscala/xml/Node;>;;
Asciz	(Ljava/lang/String;Lscala/xml/NamespaceBinding;Ljava/lang/String;)Lscala/collection/Seq<Lscala/xml/Node;>;;
Asciz	copy;
Asciz	(Lscala/xml/MetaData;)Lscala/xml/MetaData;;
Asciz	getNamespace;
Asciz	(Lscala/xml/Node;)Ljava/lang/String;;
Asciz	hasNext;
Asciz	scala/xml/Null$;
class	scala/xml/Null$
Asciz	Lscala/xml/Null$;;
NameAndType	MODULE$:Lscala/xml/Null$;
Field	scala/xml/Null$.MODULE$:Lscala/xml/Null$;
Asciz	next;
Asciz	()Lscala/xml/MetaData;;
NameAndType	next:()Lscala/xml/MetaData;
Method	scala/xml/MetaData.next:()Lscala/xml/MetaData;
Asciz	java/lang/Object;
class	java/lang/Object
NameAndType	equals:(Ljava/lang/Object;)Z
Method	java/lang/Object.equals:(Ljava/lang/Object;)Z
Asciz	length;
Asciz	(I)I;
NameAndType	length:(I)I
Method	scala/xml/MetaData.length:(I)I
Asciz	i;
Asciz	isPrefixed;
Asciz	canEqual;
Asciz	temp4;
Asciz	strict_$eq$eq;
Asciz	scala/collection/TraversableLike;
class	scala/collection/TraversableLike
NameAndType	toSet:()Lscala/collection/immutable/Set;
InterfaceMethod	scala/collection/TraversableLike.toSet:()Lscala/collection/immutable/Set;
Asciz	temp6;
Asciz	basisForHashCode;
Asciz	scala/collection/immutable/List$;
class	scala/collection/immutable/List$
Asciz	Lscala/collection/immutable/List$;;
NameAndType	MODULE$:Lscala/collection/immutable/List$;
Field	scala/collection/immutable/List$.MODULE$:Lscala/collection/immutable/List$;
Asciz	scala/Predef$;
class	scala/Predef$
Asciz	Lscala/Predef$;;
NameAndType	MODULE$:Lscala/Predef$;
Field	scala/Predef$.MODULE$:Lscala/Predef$;
Asciz	scala/collection/immutable/Set;
class	scala/collection/immutable/Set
Asciz	[Ljava/lang/Object;;
class	"[Ljava/lang/Object;"
Asciz	wrapRefArray;
Asciz	([Ljava/lang/Object;)Lscala/collection/mutable/WrappedArray;;
NameAndType	wrapRefArray:([Ljava/lang/Object;)Lscala/collection/mutable/WrappedArray;
Method	scala/Predef$.wrapRefArray:([Ljava/lang/Object;)Lscala/collection/mutable/WrappedArray;
Asciz	(Lscala/collection/Seq;)Lscala/collection/immutable/List;;
NameAndType	apply:(Lscala/collection/Seq;)Lscala/collection/immutable/List;
Method	scala/collection/immutable/List$.apply:(Lscala/collection/Seq;)Lscala/collection/immutable/List;
Asciz	()Lscala/collection/Seq<Ljava/lang/Object;>;;
Asciz	iterator;
Asciz	scala/package$;
class	scala/package$
Asciz	Lscala/package$;;
NameAndType	MODULE$:Lscala/package$;
Field	scala/package$.MODULE$:Lscala/package$;
Asciz	Iterator;
Asciz	()Lscala/collection/Iterator$;;
NameAndType	Iterator:()Lscala/collection/Iterator$;
Method	scala/package$.Iterator:()Lscala/collection/Iterator$;
Asciz	scala/collection/Iterator$;
class	scala/collection/Iterator$
Asciz	single;
Asciz	(Ljava/lang/Object;)Lscala/collection/Iterator;;
NameAndType	single:(Ljava/lang/Object;)Lscala/collection/Iterator;
Method	scala/collection/Iterator$.single:(Ljava/lang/Object;)Lscala/collection/Iterator;
Asciz	scala/xml/MetaData$$anonfun$iterator$1;
class	scala/xml/MetaData$$anonfun$iterator$1
Asciz	<init>;
Asciz	(Lscala/xml/MetaData;)V;
NameAndType	"<init>":(Lscala/xml/MetaData;)V
Method	scala/xml/MetaData$$anonfun$iterator$1."<init>":(Lscala/xml/MetaData;)V
Asciz	scala/collection/Iterator;
class	scala/collection/Iterator
Asciz	(Lscala/Function0;)Lscala/collection/Iterator;;
NameAndType	$plus$plus:(Lscala/Function0;)Lscala/collection/Iterator;
InterfaceMethod	scala/collection/Iterator.$plus$plus:(Lscala/Function0;)Lscala/collection/Iterator;
Asciz	()Lscala/collection/Iterator<Lscala/xml/MetaData;>;;
NameAndType	iterator:()Lscala/collection/Iterator;
Method	scala/xml/MetaData.iterator:()Lscala/collection/Iterator;
NameAndType	length:()I
InterfaceMethod	scala/collection/Iterator.length:()I
Asciz	filter;
Asciz	(Lscala/Function1;)Lscala/xml/MetaData;;
Asciz	scala/Function1;
class	scala/Function1
Asciz	(Ljava/lang/Object;)Ljava/lang/Object;;
NameAndType	apply:(Ljava/lang/Object;)Ljava/lang/Object;
InterfaceMethod	scala/Function1.apply:(Ljava/lang/Object;)Ljava/lang/Object;
Asciz	scala/runtime/BoxesRunTime;
class	scala/runtime/BoxesRunTime
Asciz	unboxToBoolean;
NameAndType	unboxToBoolean:(Ljava/lang/Object;)Z
Method	scala/runtime/BoxesRunTime.unboxToBoolean:(Ljava/lang/Object;)Z
NameAndType	filter:(Lscala/Function1;)Lscala/xml/MetaData;
Method	scala/xml/MetaData.filter:(Lscala/Function1;)Lscala/xml/MetaData;
NameAndType	copy:(Lscala/xml/MetaData;)Lscala/xml/MetaData;
Method	scala/xml/MetaData.copy:(Lscala/xml/MetaData;)Lscala/xml/MetaData;
Asciz	(Lscala/Function1<Lscala/xml/MetaData;Ljava/lang/Boolean;>;)Lscala/xml/MetaData;;
Asciz	value;
Asciz	()Lscala/collection/Seq<Lscala/xml/Node;>;;
Asciz	prefixedKey;
Asciz	scala/xml/Attribute;
class	scala/xml/Attribute
Asciz	gd1$1;
Asciz	(Lscala/xml/Attribute;)Z;
NameAndType	gd1$1:(Lscala/xml/Attribute;)Z
Method	scala/xml/MetaData.gd1$1:(Lscala/xml/Attribute;)Z
Asciz	scala/collection/mutable/StringBuilder;
class	scala/collection/mutable/StringBuilder
Asciz	()V;
NameAndType	"<init>":()V
Method	scala/collection/mutable/StringBuilder."<init>":()V
Asciz	pre;
NameAndType	pre:()Ljava/lang/String;
InterfaceMethod	scala/xml/Attribute.pre:()Ljava/lang/String;
Asciz	(Ljava/lang/Object;)Lscala/collection/mutable/StringBuilder;;
NameAndType	append:(Ljava/lang/Object;)Lscala/collection/mutable/StringBuilder;
Method	scala/collection/mutable/StringBuilder.append:(Ljava/lang/Object;)Lscala/collection/mutable/StringBuilder;
Asciz	:;
String	:
NameAndType	key:()Ljava/lang/String;
Method	scala/xml/MetaData.key:()Ljava/lang/String;
Asciz	toString;
NameAndType	toString:()Ljava/lang/String;
Method	scala/collection/mutable/StringBuilder.toString:()Ljava/lang/String;
Asciz	temp8;
Asciz	temp9;
Asciz	Lscala/xml/Attribute;;
Asciz	x;
Asciz	asAttrMap;
Asciz	()Lscala/collection/immutable/Map;;
Asciz	scala/xml/MetaData$$anonfun$asAttrMap$1;
class	scala/xml/MetaData$$anonfun$asAttrMap$1
Method	scala/xml/MetaData$$anonfun$asAttrMap$1."<init>":(Lscala/xml/MetaData;)V
Asciz	(Lscala/Function1;)Lscala/collection/Iterator;;
NameAndType	map:(Lscala/Function1;)Lscala/collection/Iterator;
InterfaceMethod	scala/collection/Iterator.map:(Lscala/Function1;)Lscala/collection/Iterator;
Asciz	conforms;
Asciz	()Lscala/Predef$$less$colon$less;;
NameAndType	conforms:()Lscala/Predef$$less$colon$less;
Method	scala/Predef$.conforms:()Lscala/Predef$$less$colon$less;
NameAndType	toMap:(Lscala/Predef$$less$colon$less;)Lscala/collection/immutable/Map;
InterfaceMethod	scala/collection/Iterator.toMap:(Lscala/Predef$$less$colon$less;)Lscala/collection/immutable/Map;
Asciz	()Lscala/collection/immutable/Map<Ljava/lang/String;Ljava/lang/String;>;;
Asciz	get;
Asciz	(Ljava/lang/String;)Lscala/Option;;
Asciz	scala/Option$;
class	scala/Option$
Asciz	Lscala/Option$;;
NameAndType	MODULE$:Lscala/Option$;
Field	scala/Option$.MODULE$:Lscala/Option$;
NameAndType	apply:(Ljava/lang/String;)Lscala/collection/Seq;
Method	scala/xml/MetaData.apply:(Ljava/lang/String;)Lscala/collection/Seq;
Asciz	(Ljava/lang/Object;)Lscala/Option;;
NameAndType	apply:(Ljava/lang/Object;)Lscala/Option;
Method	scala/Option$.apply:(Ljava/lang/Object;)Lscala/Option;
Asciz	(Ljava/lang/String;)Lscala/Option<Lscala/collection/Seq<Lscala/xml/Node;>;>;;
Asciz	(Ljava/lang/String;Lscala/xml/Node;Ljava/lang/String;)Lscala/Option;;
Asciz	(Ljava/lang/String;Lscala/xml/NamespaceBinding;Ljava/lang/String;)Lscala/Option;;
NameAndType	get:(Ljava/lang/String;Lscala/xml/NamespaceBinding;Ljava/lang/String;)Lscala/Option;
Method	scala/xml/MetaData.get:(Ljava/lang/String;Lscala/xml/NamespaceBinding;Ljava/lang/String;)Lscala/Option;
Asciz	uri;
Asciz	(Ljava/lang/String;Lscala/xml/Node;Ljava/lang/String;)Lscala/Option<Lscala/collection/Seq<Lscala/xml/Node;>;>;;
Asciz	(Ljava/lang/String;Lscala/xml/NamespaceBinding;Ljava/lang/String;)Lscala/Option<Lscala/collection/Seq<Lscala/xml/Node;>;>;;
Asciz	toString1;
Asciz	scala/xml/Utility$;
class	scala/xml/Utility$
Asciz	Lscala/xml/Utility$;;
NameAndType	MODULE$:Lscala/xml/Utility$;
Field	scala/xml/Utility$.MODULE$:Lscala/xml/Utility$;
Asciz	scala/xml/MetaData$$anonfun$toString1$1;
class	scala/xml/MetaData$$anonfun$toString1$1
Method	scala/xml/MetaData$$anonfun$toString1$1."<init>":(Lscala/xml/MetaData;)V
Asciz	sbToString;
Asciz	(Lscala/Function1;)Ljava/lang/String;;
NameAndType	sbToString:(Lscala/Function1;)Ljava/lang/String;
Method	scala/xml/Utility$.sbToString:(Lscala/Function1;)Ljava/lang/String;
Asciz	(Lscala/collection/mutable/StringBuilder;)V;
Asciz	scala/xml/MetaData$$anonfun$toString$1;
class	scala/xml/MetaData$$anonfun$toString$1
Method	scala/xml/MetaData$$anonfun$toString$1."<init>":(Lscala/xml/MetaData;)V
Asciz	buildString;
int	32;
Asciz	(C)Lscala/collection/mutable/StringBuilder;;
NameAndType	append:(C)Lscala/collection/mutable/StringBuilder;
Method	scala/collection/mutable/StringBuilder.append:(C)Lscala/collection/mutable/StringBuilder;
NameAndType	toString1:(Lscala/collection/mutable/StringBuilder;)V
Method	scala/xml/MetaData.toString1:(Lscala/collection/mutable/StringBuilder;)V
NameAndType	buildString:(Lscala/collection/mutable/StringBuilder;)Lscala/collection/mutable/StringBuilder;
Method	scala/xml/MetaData.buildString:(Lscala/collection/mutable/StringBuilder;)Lscala/collection/mutable/StringBuilder;
Asciz	sb;
Asciz	wellformed;
Asciz	(Lscala/xml/NamespaceBinding;)Z;
Asciz	remove;
Asciz	(Ljava/lang/String;)Lscala/xml/MetaData;;
Asciz	(Ljava/lang/String;Lscala/xml/NamespaceBinding;Ljava/lang/String;)Lscala/xml/MetaData;;
Asciz	(Ljava/lang/String;Lscala/xml/Node;Ljava/lang/String;)Lscala/xml/MetaData;;
NameAndType	remove:(Ljava/lang/String;Lscala/xml/NamespaceBinding;Ljava/lang/String;)Lscala/xml/MetaData;
Method	scala/xml/MetaData.remove:(Ljava/lang/String;Lscala/xml/NamespaceBinding;Ljava/lang/String;)Lscala/xml/MetaData;
Asciz	namespace;
Asciz	(II)Lscala/collection/TraversableView;;
Asciz	scala/collection/IterableLike;
class	scala/collection/IterableLike
NameAndType	view:(II)Lscala/collection/IterableView;
InterfaceMethod	scala/collection/IterableLike.view:(II)Lscala/collection/IterableView;
Asciz	()Lscala/collection/TraversableView;;
NameAndType	view:()Lscala/collection/IterableView;
InterfaceMethod	scala/collection/IterableLike.view:()Lscala/collection/IterableView;
Asciz	(Ljava/lang/Object;)Lscala/collection/Traversable;;
NameAndType	toCollection:(Ljava/lang/Object;)Lscala/collection/Iterable;
InterfaceMethod	scala/collection/IterableLike.toCollection:(Ljava/lang/Object;)Lscala/collection/Iterable;
Asciz	()Lscala/collection/Traversable;;
NameAndType	thisCollection:()Lscala/collection/Iterable;
InterfaceMethod	scala/collection/IterableLike.thisCollection:()Lscala/collection/Iterable;
NameAndType	isPrefixed:()Z
InterfaceMethod	scala/xml/Attribute.isPrefixed:()Z
Method	java/lang/Object."<init>":()V
Asciz	$init$;
Asciz	(Lscala/collection/TraversableLike;)V;
NameAndType	$init$:(Lscala/collection/TraversableLike;)V
Method	scala/collection/TraversableLike$class.$init$:(Lscala/collection/TraversableLike;)V
Asciz	(Lscala/collection/generic/GenericTraversableTemplate;)V;
NameAndType	$init$:(Lscala/collection/generic/GenericTraversableTemplate;)V
Method	scala/collection/generic/GenericTraversableTemplate$class.$init$:(Lscala/collection/generic/GenericTraversableTemplate;)V
Asciz	scala/collection/Traversable$class;
class	scala/collection/Traversable$class
Asciz	(Lscala/collection/Traversable;)V;
NameAndType	$init$:(Lscala/collection/Traversable;)V
Method	scala/collection/Traversable$class.$init$:(Lscala/collection/Traversable;)V
Asciz	(Lscala/collection/IterableLike;)V;
NameAndType	$init$:(Lscala/collection/IterableLike;)V
Method	scala/collection/IterableLike$class.$init$:(Lscala/collection/IterableLike;)V
Asciz	(Lscala/collection/Iterable;)V;
NameAndType	$init$:(Lscala/collection/Iterable;)V
Method	scala/collection/Iterable$class.$init$:(Lscala/collection/Iterable;)V
Asciz	(Lscala/xml/Equality;)V;
NameAndType	$init$:(Lscala/xml/Equality;)V
Method	scala/xml/Equality$class.$init$:(Lscala/xml/Equality;)V
Asciz	Ljava/lang/Object;Lscala/collection/Iterable<Lscala/xml/MetaData;>;Lscala/xml/Equality;Lscala/ScalaObject;;
Asciz	ScalaSig;
Asciz	InnerClasses;
Asciz	scala/Predef$$less$colon$less;
class	scala/Predef$$less$colon$less
Asciz	scala/Predef;
class	scala/Predef
Asciz	$less$colon$less;
Asciz	scala/collection/TraversableLike$WithFilter;
class	scala/collection/TraversableLike$WithFilter
Asciz	WithFilter;
Asciz	$anonfun$toString$1;
Asciz	$anonfun$iterator$1;
Asciz	$anonfun$toString1$1;
Asciz	$anonfun$asAttrMap$1;
Asciz	scala/collection/Iterable;
class	scala/collection/Iterable
Asciz	scala/xml/Equality;
class	scala/xml/Equality
Asciz	scala/ScalaObject;
class	scala/ScalaObject
Asciz	java/io/Serializable;
class	java/io/Serializable

{
public static final scala.xml.MetaData update(scala.xml.MetaData, scala.xml.NamespaceBinding, scala.xml.MetaData);
  Signature: (Lscala/xml/MetaData;Lscala/xml/NamespaceBinding;Lscala/xml/MetaData;)Lscala/xml/MetaData;
  Code:
   Stack=4, Locals=3, Args_size=3
	getstatic	Field scala/xml/MetaData$.MODULE$:Lscala/xml/MetaData$;
	aload_0
	aload_1
	aload_2
	invokevirtual	Method scala/xml/MetaData$.update:(Lscala/xml/MetaData;Lscala/xml/NamespaceBinding;Lscala/xml/MetaData;)Lscala/xml/MetaData;
	areturn
  Labels:

public static final java.lang.String getUniversalKey(scala.xml.MetaData, scala.xml.NamespaceBinding);
  Signature: (Lscala/xml/MetaData;Lscala/xml/NamespaceBinding;)Ljava/lang/String;
  Code:
   Stack=3, Locals=2, Args_size=2
	getstatic	Field scala/xml/MetaData$.MODULE$:Lscala/xml/MetaData$;
	aload_0
	aload_1
	invokevirtual	Method scala/xml/MetaData$.getUniversalKey:(Lscala/xml/MetaData;Lscala/xml/NamespaceBinding;)Ljava/lang/String;
	areturn
  Labels:

public static final scala.xml.MetaData normalize(scala.xml.MetaData, scala.xml.NamespaceBinding);
  Signature: (Lscala/xml/MetaData;Lscala/xml/NamespaceBinding;)Lscala/xml/MetaData;
  Code:
   Stack=3, Locals=2, Args_size=2
	getstatic	Field scala/xml/MetaData$.MODULE$:Lscala/xml/MetaData$;
	aload_0
	aload_1
	invokevirtual	Method scala/xml/MetaData$.normalize:(Lscala/xml/MetaData;Lscala/xml/NamespaceBinding;)Lscala/xml/MetaData;
	areturn
  Labels:

public static final scala.xml.MetaData concatenate(scala.xml.MetaData, scala.xml.MetaData);
  Signature: (Lscala/xml/MetaData;Lscala/xml/MetaData;)Lscala/xml/MetaData;
  Code:
   Stack=3, Locals=2, Args_size=2
	getstatic	Field scala/xml/MetaData$.MODULE$:Lscala/xml/MetaData$;
	aload_0
	aload_1
	invokevirtual	Method scala/xml/MetaData$.concatenate:(Lscala/xml/MetaData;Lscala/xml/MetaData;)Lscala/xml/MetaData;
	areturn
  Labels:

public boolean strict_$bang$eq(scala.xml.Equality);
  Signature: (Lscala/xml/Equality;)Z
  Code:
   Stack=2, Locals=2, Args_size=2
	aload_0
	aload_1
	invokestatic	Method scala/xml/Equality$class.strict_$bang$eq:(Lscala/xml/Equality;Lscala/xml/Equality;)Z
	ireturn
  Labels:
  LocalVariableTable: 
   Start  Length  Slot  Name   Signature
   0      6      0    this       Lscala/xml/MetaData;
   0      6      1    other       Lscala/xml/Equality;


public int hashCode();
  Signature: ()I
  Code:
   Stack=1, Locals=1, Args_size=1
	aload_0
	invokestatic	Method scala/xml/Equality$class.hashCode:(Lscala/xml/Equality;)I
	ireturn
  Labels:

public boolean equals(java.lang.Object);
  Signature: (Ljava/lang/Object;)Z
  Code:
   Stack=2, Locals=2, Args_size=2
	aload_0
	aload_1
	invokestatic	Method scala/xml/Equality$class.equals:(Lscala/xml/Equality;Ljava/lang/Object;)Z
	ireturn
  Labels:
  LocalVariableTable: 
   Start  Length  Slot  Name   Signature
   0      6      0    this       Lscala/xml/MetaData;
   0      6      1    other       Ljava/lang/Object;


public final boolean xml_$eq$eq(java.lang.Object);
  Signature: (Ljava/lang/Object;)Z
  Code:
   Stack=2, Locals=2, Args_size=2
	aload_0
	aload_1
	invokestatic	Method scala/xml/Equality$class.xml_$eq$eq:(Lscala/xml/Equality;Ljava/lang/Object;)Z
	ireturn
  Labels:
  LocalVariableTable: 
   Start  Length  Slot  Name   Signature
   0      6      0    this       Lscala/xml/MetaData;
   0      6      1    other       Ljava/lang/Object;


public final boolean xml_$bang$eq(java.lang.Object);
  Signature: (Ljava/lang/Object;)Z
  Code:
   Stack=2, Locals=2, Args_size=2
	aload_0
	aload_1
	invokestatic	Method scala/xml/Equality$class.xml_$bang$eq:(Lscala/xml/Equality;Ljava/lang/Object;)Z
	ireturn
  Labels:
  LocalVariableTable: 
   Start  Length  Slot  Name   Signature
   0      6      0    this       Lscala/xml/MetaData;
   0      6      1    other       Ljava/lang/Object;


public scala.collection.generic.GenericCompanion companion();
  Signature: ()Lscala/collection/generic/GenericCompanion;
  Code:
   Stack=1, Locals=1, Args_size=1
	aload_0
	invokestatic	Method scala/collection/Iterable$class.companion:(Lscala/collection/Iterable;)Lscala/collection/generic/GenericCompanion;
	areturn
  Labels:

public scala.collection.Iterable thisCollection();
  Signature: ()Lscala/collection/Iterable;
  Code:
   Stack=1, Locals=1, Args_size=1
	aload_0
	invokestatic	Method scala/collection/IterableLike$class.thisCollection:(Lscala/collection/IterableLike;)Lscala/collection/Iterable;
	areturn
  Labels:

public scala.collection.Iterable toCollection(java.lang.Object);
  Signature: (Ljava/lang/Object;)Lscala/collection/Iterable;
  Code:
   Stack=2, Locals=2, Args_size=2
	aload_0
	aload_1
	invokestatic	Method scala/collection/IterableLike$class.toCollection:(Lscala/collection/IterableLike;Ljava/lang/Object;)Lscala/collection/Iterable;
	areturn
  Labels:
  LocalVariableTable: 
   Start  Length  Slot  Name   Signature
   0      6      0    this       Lscala/xml/MetaData;
   0      6      1    repr       Ljava/lang/Object;


public scala.collection.Iterator elements();
  Signature: ()Lscala/collection/Iterator;
  Code:
   Stack=1, Locals=1, Args_size=1
	aload_0
	invokestatic	Method scala/collection/IterableLike$class.elements:(Lscala/collection/IterableLike;)Lscala/collection/Iterator;
	areturn
  Labels:
  Deprecated: true

public void foreach(scala.Function1);
  Signature: (Lscala/Function1;)V
  Code:
   Stack=2, Locals=2, Args_size=2
	aload_0
	aload_1
	invokestatic	Method scala/collection/IterableLike$class.foreach:(Lscala/collection/IterableLike;Lscala/Function1;)V
	return
  Labels:
  LocalVariableTable: 
   Start  Length  Slot  Name   Signature
   0      6      0    this       Lscala/xml/MetaData;
   0      6      1    f       Lscala/Function1;


public boolean forall(scala.Function1);
  Signature: (Lscala/Function1;)Z
  Code:
   Stack=2, Locals=2, Args_size=2
	aload_0
	aload_1
	invokestatic	Method scala/collection/IterableLike$class.forall:(Lscala/collection/IterableLike;Lscala/Function1;)Z
	ireturn
  Labels:
  LocalVariableTable: 
   Start  Length  Slot  Name   Signature
   0      6      0    this       Lscala/xml/MetaData;
   0      6      1    p       Lscala/Function1;


public boolean exists(scala.Function1);
  Signature: (Lscala/Function1;)Z
  Code:
   Stack=2, Locals=2, Args_size=2
	aload_0
	aload_1
	invokestatic	Method scala/collection/IterableLike$class.exists:(Lscala/collection/IterableLike;Lscala/Function1;)Z
	ireturn
  Labels:
  LocalVariableTable: 
   Start  Length  Slot  Name   Signature
   0      6      0    this       Lscala/xml/MetaData;
   0      6      1    p       Lscala/Function1;


public scala.Option find(scala.Function1);
  Signature: (Lscala/Function1;)Lscala/Option;
  Code:
   Stack=2, Locals=2, Args_size=2
	aload_0
	aload_1
	invokestatic	Method scala/collection/IterableLike$class.find:(Lscala/collection/IterableLike;Lscala/Function1;)Lscala/Option;
	areturn
  Labels:
  LocalVariableTable: 
   Start  Length  Slot  Name   Signature
   0      6      0    this       Lscala/xml/MetaData;
   0      6      1    p       Lscala/Function1;


public boolean isEmpty();
  Signature: ()Z
  Code:
   Stack=1, Locals=1, Args_size=1
	aload_0
	invokestatic	Method scala/collection/IterableLike$class.isEmpty:(Lscala/collection/IterableLike;)Z
	ireturn
  Labels:

public java.lang.Object foldRight(java.lang.Object, scala.Function2);
  Signature: (Ljava/lang/Object;Lscala/Function2;)Ljava/lang/Object;
  Code:
   Stack=3, Locals=3, Args_size=3
	aload_0
	aload_1
	aload_2
	invokestatic	Method scala/collection/IterableLike$class.foldRight:(Lscala/collection/IterableLike;Ljava/lang/Object;Lscala/Function2;)Ljava/lang/Object;
	areturn
  Labels:
  LocalVariableTable: 
   Start  Length  Slot  Name   Signature
   0      7      0    this       Lscala/xml/MetaData;
   0      7      1    z       Ljava/lang/Object;
   0      7      2    op       Lscala/Function2;


public java.lang.Object reduceRight(scala.Function2);
  Signature: (Lscala/Function2;)Ljava/lang/Object;
  Code:
   Stack=2, Locals=2, Args_size=2
	aload_0
	aload_1
	invokestatic	Method scala/collection/IterableLike$class.reduceRight:(Lscala/collection/IterableLike;Lscala/Function2;)Ljava/lang/Object;
	areturn
  Labels:
  LocalVariableTable: 
   Start  Length  Slot  Name   Signature
   0      6      0    this       Lscala/xml/MetaData;
   0      6      1    op       Lscala/Function2;


public scala.collection.Iterable toIterable();
  Signature: ()Lscala/collection/Iterable;
  Code:
   Stack=1, Locals=1, Args_size=1
	aload_0
	invokestatic	Method scala/collection/IterableLike$class.toIterable:(Lscala/collection/IterableLike;)Lscala/collection/Iterable;
	areturn
  Labels:

public java.lang.Object head();
  Signature: ()Ljava/lang/Object;
  Code:
   Stack=1, Locals=1, Args_size=1
	aload_0
	invokestatic	Method scala/collection/IterableLike$class.head:(Lscala/collection/IterableLike;)Ljava/lang/Object;
	areturn
  Labels:

public java.lang.Object take(int);
  Signature: (I)Ljava/lang/Object;
  Code:
   Stack=2, Locals=2, Args_size=2
	aload_0
	iload_1
	invokestatic	Method scala/collection/IterableLike$class.take:(Lscala/collection/IterableLike;I)Ljava/lang/Object;
	areturn
  Labels:
  LocalVariableTable: 
   Start  Length  Slot  Name   Signature
   0      6      0    this       Lscala/xml/MetaData;
   0      6      1    n       I


public java.lang.Object slice(int, int);
  Signature: (II)Ljava/lang/Object;
  Code:
   Stack=3, Locals=3, Args_size=3
	aload_0
	iload_1
	iload_2
	invokestatic	Method scala/collection/IterableLike$class.slice:(Lscala/collection/IterableLike;II)Ljava/lang/Object;
	areturn
  Labels:
  LocalVariableTable: 
   Start  Length  Slot  Name   Signature
   0      7      0    this       Lscala/xml/MetaData;
   0      7      1    from       I
   0      7      2    until       I


public java.lang.Object takeWhile(scala.Function1);
  Signature: (Lscala/Function1;)Ljava/lang/Object;
  Code:
   Stack=2, Locals=2, Args_size=2
	aload_0
	aload_1
	invokestatic	Method scala/collection/IterableLike$class.takeWhile:(Lscala/collection/IterableLike;Lscala/Function1;)Ljava/lang/Object;
	areturn
  Labels:
  LocalVariableTable: 
   Start  Length  Slot  Name   Signature
   0      6      0    this       Lscala/xml/MetaData;
   0      6      1    p       Lscala/Function1;


public scala.collection.Iterator grouped(int);
  Signature: (I)Lscala/collection/Iterator;
  Code:
   Stack=2, Locals=2, Args_size=2
	aload_0
	iload_1
	invokestatic	Method scala/collection/IterableLike$class.grouped:(Lscala/collection/IterableLike;I)Lscala/collection/Iterator;
	areturn
  Labels:
  LocalVariableTable: 
   Start  Length  Slot  Name   Signature
   0      6      0    this       Lscala/xml/MetaData;
   0      6      1    size       I


public scala.collection.Iterator sliding(int);
  Signature: (I)Lscala/collection/Iterator;
  Code:
   Stack=2, Locals=2, Args_size=2
	aload_0
	iload_1
	invokestatic	Method scala/collection/IterableLike$class.sliding:(Lscala/collection/IterableLike;I)Lscala/collection/Iterator;
	areturn
  Labels:
  LocalVariableTable: 
   Start  Length  Slot  Name   Signature
   0      6      0    this       Lscala/xml/MetaData;
   0      6      1    size       I


public scala.collection.Iterator sliding(int, int);
  Signature: (II)Lscala/collection/Iterator;
  Code:
   Stack=3, Locals=3, Args_size=3
	aload_0
	iload_1
	iload_2
	invokestatic	Method scala/collection/IterableLike$class.sliding:(Lscala/collection/IterableLike;II)Lscala/collection/Iterator;
	areturn
  Labels:
  LocalVariableTable: 
   Start  Length  Slot  Name   Signature
   0      7      0    this       Lscala/xml/MetaData;
   0      7      1    size       I
   0      7      2    step       I


public java.lang.Object takeRight(int);
  Signature: (I)Ljava/lang/Object;
  Code:
   Stack=2, Locals=2, Args_size=2
	aload_0
	iload_1
	invokestatic	Method scala/collection/IterableLike$class.takeRight:(Lscala/collection/IterableLike;I)Ljava/lang/Object;
	areturn
  Labels:
  LocalVariableTable: 
   Start  Length  Slot  Name   Signature
   0      6      0    this       Lscala/xml/MetaData;
   0      6      1    n       I


public java.lang.Object dropRight(int);
  Signature: (I)Ljava/lang/Object;
  Code:
   Stack=2, Locals=2, Args_size=2
	aload_0
	iload_1
	invokestatic	Method scala/collection/IterableLike$class.dropRight:(Lscala/collection/IterableLike;I)Ljava/lang/Object;
	areturn
  Labels:
  LocalVariableTable: 
   Start  Length  Slot  Name   Signature
   0      6      0    this       Lscala/xml/MetaData;
   0      6      1    n       I


public void copyToArray(java.lang.Object, int, int);
  Signature: (Ljava/lang/Object;II)V
  Code:
   Stack=4, Locals=4, Args_size=4
	aload_0
	aload_1
	iload_2
	iload_3
	invokestatic	Method scala/collection/IterableLike$class.copyToArray:(Lscala/collection/IterableLike;Ljava/lang/Object;II)V
	return
  Labels:
  LocalVariableTable: 
   Start  Length  Slot  Name   Signature
   0      8      0    this       Lscala/xml/MetaData;
   0      8      1    xs       Ljava/lang/Object;
   0      8      2    start       I
   0      8      3    len       I


public java.lang.Object zip(scala.collection.Iterable, scala.collection.generic.CanBuildFrom);
  Signature: (Lscala/collection/Iterable;Lscala/collection/generic/CanBuildFrom;)Ljava/lang/Object;
  Code:
   Stack=3, Locals=3, Args_size=3
	aload_0
	aload_1
	aload_2
	invokestatic	Method scala/collection/IterableLike$class.zip:(Lscala/collection/IterableLike;Lscala/collection/Iterable;Lscala/collection/generic/CanBuildFrom;)Ljava/lang/Object;
	areturn
  Labels:
  LocalVariableTable: 
   Start  Length  Slot  Name   Signature
   0      7      0    this       Lscala/xml/MetaData;
   0      7      1    that       Lscala/collection/Iterable;
   0      7      2    bf       Lscala/collection/generic/CanBuildFrom;


public java.lang.Object zipAll(scala.collection.Iterable, java.lang.Object, java.lang.Object, scala.collection.generic.CanBuildFrom);
  Signature: (Lscala/collection/Iterable;Ljava/lang/Object;Ljava/lang/Object;Lscala/collection/generic/CanBuildFrom;)Ljava/lang/Object;
  Code:
   Stack=5, Locals=5, Args_size=5
	aload_0
	aload_1
	aload_2
	aload_3
	aload	4
	invokestatic	Method scala/collection/IterableLike$class.zipAll:(Lscala/collection/IterableLike;Lscala/collection/Iterable;Ljava/lang/Object;Ljava/lang/Object;Lscala/collection/generic/CanBuildFrom;)Ljava/lang/Object;
	areturn
  Labels:
  LocalVariableTable: 
   Start  Length  Slot  Name   Signature
   0      10      0    this       Lscala/xml/MetaData;
   0      10      1    that       Lscala/collection/Iterable;
   0      10      2    thisElem       Ljava/lang/Object;
   0      10      3    thatElem       Ljava/lang/Object;
   0      10      4    bf       Lscala/collection/generic/CanBuildFrom;


public java.lang.Object zipWithIndex(scala.collection.generic.CanBuildFrom);
  Signature: (Lscala/collection/generic/CanBuildFrom;)Ljava/lang/Object;
  Code:
   Stack=2, Locals=2, Args_size=2
	aload_0
	aload_1
	invokestatic	Method scala/collection/IterableLike$class.zipWithIndex:(Lscala/collection/IterableLike;Lscala/collection/generic/CanBuildFrom;)Ljava/lang/Object;
	areturn
  Labels:
  LocalVariableTable: 
   Start  Length  Slot  Name   Signature
   0      6      0    this       Lscala/xml/MetaData;
   0      6      1    bf       Lscala/collection/generic/CanBuildFrom;


public boolean sameElements(scala.collection.Iterable);
  Signature: (Lscala/collection/Iterable;)Z
  Code:
   Stack=2, Locals=2, Args_size=2
	aload_0
	aload_1
	invokestatic	Method scala/collection/IterableLike$class.sameElements:(Lscala/collection/IterableLike;Lscala/collection/Iterable;)Z
	ireturn
  Labels:
  LocalVariableTable: 
   Start  Length  Slot  Name   Signature
   0      6      0    this       Lscala/xml/MetaData;
   0      6      1    that       Lscala/collection/Iterable;


public scala.collection.immutable.Stream toStream();
  Signature: ()Lscala/collection/immutable/Stream;
  Code:
   Stack=1, Locals=1, Args_size=1
	aload_0
	invokestatic	Method scala/collection/IterableLike$class.toStream:(Lscala/collection/IterableLike;)Lscala/collection/immutable/Stream;
	areturn
  Labels:

public scala.collection.IterableView view();
  Signature: ()Lscala/collection/IterableView;
  Code:
   Stack=1, Locals=1, Args_size=1
	aload_0
	invokestatic	Method scala/collection/IterableLike$class.view:(Lscala/collection/IterableLike;)Lscala/collection/IterableView;
	areturn
  Labels:

public scala.collection.IterableView view(int, int);
  Signature: (II)Lscala/collection/IterableView;
  Code:
   Stack=3, Locals=3, Args_size=3
	aload_0
	iload_1
	iload_2
	invokestatic	Method scala/collection/IterableLike$class.view:(Lscala/collection/IterableLike;II)Lscala/collection/IterableView;
	areturn
  Labels:
  LocalVariableTable: 
   Start  Length  Slot  Name   Signature
   0      7      0    this       Lscala/xml/MetaData;
   0      7      1    from       I
   0      7      2    until       I


public java.lang.Object first();
  Signature: ()Ljava/lang/Object;
  Code:
   Stack=1, Locals=1, Args_size=1
	aload_0
	invokestatic	Method scala/collection/IterableLike$class.first:(Lscala/collection/IterableLike;)Ljava/lang/Object;
	areturn
  Labels:
  Deprecated: true

public scala.Option firstOption();
  Signature: ()Lscala/Option;
  Code:
   Stack=1, Locals=1, Args_size=1
	aload_0
	invokestatic	Method scala/collection/IterableLike$class.firstOption:(Lscala/collection/IterableLike;)Lscala/Option;
	areturn
  Labels:
  Deprecated: true

public scala.collection.IterableView projection();
  Signature: ()Lscala/collection/IterableView;
  Code:
   Stack=1, Locals=1, Args_size=1
	aload_0
	invokestatic	Method scala/collection/IterableLike$class.projection:(Lscala/collection/IterableLike;)Lscala/collection/IterableView;
	areturn
  Labels:
  Deprecated: true

public scala.collection.mutable.Builder newBuilder();
  Signature: ()Lscala/collection/mutable/Builder;
  Code:
   Stack=1, Locals=1, Args_size=1
	aload_0
	invokestatic	Method scala/collection/generic/GenericTraversableTemplate$class.newBuilder:(Lscala/collection/generic/GenericTraversableTemplate;)Lscala/collection/mutable/Builder;
	areturn
  Labels:

public scala.collection.mutable.Builder genericBuilder();
  Signature: ()Lscala/collection/mutable/Builder;
  Code:
   Stack=1, Locals=1, Args_size=1
	aload_0
	invokestatic	Method scala/collection/generic/GenericTraversableTemplate$class.genericBuilder:(Lscala/collection/generic/GenericTraversableTemplate;)Lscala/collection/mutable/Builder;
	areturn
  Labels:

public scala.Tuple2 unzip(scala.Function1);
  Signature: (Lscala/Function1;)Lscala/Tuple2;
  Code:
   Stack=2, Locals=2, Args_size=2
	aload_0
	aload_1
	invokestatic	Method scala/collection/generic/GenericTraversableTemplate$class.unzip:(Lscala/collection/generic/GenericTraversableTemplate;Lscala/Function1;)Lscala/Tuple2;
	areturn
  Labels:
  LocalVariableTable: 
   Start  Length  Slot  Name   Signature
   0      6      0    this       Lscala/xml/MetaData;
   0      6      1    asPair       Lscala/Function1;


public scala.collection.Traversable flatten(scala.Function1);
  Signature: (Lscala/Function1;)Lscala/collection/Traversable;
  Code:
   Stack=2, Locals=2, Args_size=2
	aload_0
	aload_1
	invokestatic	Method scala/collection/generic/GenericTraversableTemplate$class.flatten:(Lscala/collection/generic/GenericTraversableTemplate;Lscala/Function1;)Lscala/collection/Traversable;
	areturn
  Labels:
  LocalVariableTable: 
   Start  Length  Slot  Name   Signature
   0      6      0    this       Lscala/xml/MetaData;
   0      6      1    asTraversable       Lscala/Function1;


public scala.collection.Traversable transpose(scala.Function1);
  Signature: (Lscala/Function1;)Lscala/collection/Traversable;
  Code:
   Stack=2, Locals=2, Args_size=2
	aload_0
	aload_1
	invokestatic	Method scala/collection/generic/GenericTraversableTemplate$class.transpose:(Lscala/collection/generic/GenericTraversableTemplate;Lscala/Function1;)Lscala/collection/Traversable;
	areturn
  Labels:
  LocalVariableTable: 
   Start  Length  Slot  Name   Signature
   0      6      0    this       Lscala/xml/MetaData;
   0      6      1    asTraversable       Lscala/Function1;


public java.lang.Object repr();
  Signature: ()Ljava/lang/Object;
  Code:
   Stack=1, Locals=1, Args_size=1
	aload_0
	invokestatic	Method scala/collection/TraversableLike$class.repr:(Lscala/collection/TraversableLike;)Ljava/lang/Object;
	areturn
  Labels:

public boolean nonEmpty();
  Signature: ()Z
  Code:
   Stack=1, Locals=1, Args_size=1
	aload_0
	invokestatic	Method scala/collection/TraversableLike$class.nonEmpty:(Lscala/collection/TraversableLike;)Z
	ireturn
  Labels:

public boolean hasDefiniteSize();
  Signature: ()Z
  Code:
   Stack=1, Locals=1, Args_size=1
	aload_0
	invokestatic	Method scala/collection/TraversableLike$class.hasDefiniteSize:(Lscala/collection/TraversableLike;)Z
	ireturn
  Labels:

public java.lang.Object $plus$plus(scala.collection.Traversable, scala.collection.generic.CanBuildFrom);
  Signature: (Lscala/collection/Traversable;Lscala/collection/generic/CanBuildFrom;)Ljava/lang/Object;
  Code:
   Stack=3, Locals=3, Args_size=3
	aload_0
	aload_1
	aload_2
	invokestatic	Method scala/collection/TraversableLike$class.$plus$plus:(Lscala/collection/TraversableLike;Lscala/collection/Traversable;Lscala/collection/generic/CanBuildFrom;)Ljava/lang/Object;
	areturn
  Labels:
  LocalVariableTable: 
   Start  Length  Slot  Name   Signature
   0      7      0    this       Lscala/xml/MetaData;
   0      7      1    that       Lscala/collection/Traversable;
   0      7      2    bf       Lscala/collection/generic/CanBuildFrom;


public java.lang.Object $plus$plus(scala.collection.Iterator, scala.collection.generic.CanBuildFrom);
  Signature: (Lscala/collection/Iterator;Lscala/collection/generic/CanBuildFrom;)Ljava/lang/Object;
  Code:
   Stack=3, Locals=3, Args_size=3
	aload_0
	aload_1
	aload_2
	invokestatic	Method scala/collection/TraversableLike$class.$plus$plus:(Lscala/collection/TraversableLike;Lscala/collection/Iterator;Lscala/collection/generic/CanBuildFrom;)Ljava/lang/Object;
	areturn
  Labels:
  LocalVariableTable: 
   Start  Length  Slot  Name   Signature
   0      7      0    this       Lscala/xml/MetaData;
   0      7      1    that       Lscala/collection/Iterator;
   0      7      2    bf       Lscala/collection/generic/CanBuildFrom;


public java.lang.Object map(scala.Function1, scala.collection.generic.CanBuildFrom);
  Signature: (Lscala/Function1;Lscala/collection/generic/CanBuildFrom;)Ljava/lang/Object;
  Code:
   Stack=3, Locals=3, Args_size=3
	aload_0
	aload_1
	aload_2
	invokestatic	Method scala/collection/TraversableLike$class.map:(Lscala/collection/TraversableLike;Lscala/Function1;Lscala/collection/generic/CanBuildFrom;)Ljava/lang/Object;
	areturn
  Labels:
  LocalVariableTable: 
   Start  Length  Slot  Name   Signature
   0      7      0    this       Lscala/xml/MetaData;
   0      7      1    f       Lscala/Function1;
   0      7      2    bf       Lscala/collection/generic/CanBuildFrom;


public java.lang.Object flatMap(scala.Function1, scala.collection.generic.CanBuildFrom);
  Signature: (Lscala/Function1;Lscala/collection/generic/CanBuildFrom;)Ljava/lang/Object;
  Code:
   Stack=3, Locals=3, Args_size=3
	aload_0
	aload_1
	aload_2
	invokestatic	Method scala/collection/TraversableLike$class.flatMap:(Lscala/collection/TraversableLike;Lscala/Function1;Lscala/collection/generic/CanBuildFrom;)Ljava/lang/Object;
	areturn
  Labels:
  LocalVariableTable: 
   Start  Length  Slot  Name   Signature
   0      7      0    this       Lscala/xml/MetaData;
   0      7      1    f       Lscala/Function1;
   0      7      2    bf       Lscala/collection/generic/CanBuildFrom;


public java.lang.Object filterNot(scala.Function1);
  Signature: (Lscala/Function1;)Ljava/lang/Object;
  Code:
   Stack=2, Locals=2, Args_size=2
	aload_0
	aload_1
	invokestatic	Method scala/collection/TraversableLike$class.filterNot:(Lscala/collection/TraversableLike;Lscala/Function1;)Ljava/lang/Object;
	areturn
  Labels:
  LocalVariableTable: 
   Start  Length  Slot  Name   Signature
   0      6      0    this       Lscala/xml/MetaData;
   0      6      1    p       Lscala/Function1;


public java.lang.Object partialMap(scala.PartialFunction, scala.collection.generic.CanBuildFrom);
  Signature: (Lscala/PartialFunction;Lscala/collection/generic/CanBuildFrom;)Ljava/lang/Object;
  Code:
   Stack=3, Locals=3, Args_size=3
	aload_0
	aload_1
	aload_2
	invokestatic	Method scala/collection/TraversableLike$class.partialMap:(Lscala/collection/TraversableLike;Lscala/PartialFunction;Lscala/collection/generic/CanBuildFrom;)Ljava/lang/Object;
	areturn
  Labels:
  LocalVariableTable: 
   Start  Length  Slot  Name   Signature
   0      7      0    this       Lscala/xml/MetaData;
   0      7      1    pf       Lscala/PartialFunction;
   0      7      2    bf       Lscala/collection/generic/CanBuildFrom;


public scala.Tuple2 partition(scala.Function1);
  Signature: (Lscala/Function1;)Lscala/Tuple2;
  Code:
   Stack=2, Locals=2, Args_size=2
	aload_0
	aload_1
	invokestatic	Method scala/collection/TraversableLike$class.partition:(Lscala/collection/TraversableLike;Lscala/Function1;)Lscala/Tuple2;
	areturn
  Labels:
  LocalVariableTable: 
   Start  Length  Slot  Name   Signature
   0      6      0    this       Lscala/xml/MetaData;
   0      6      1    p       Lscala/Function1;


public scala.collection.Map groupBy(scala.Function1);
  Signature: (Lscala/Function1;)Lscala/collection/Map;
  Code:
   Stack=2, Locals=2, Args_size=2
	aload_0
	aload_1
	invokestatic	Method scala/collection/TraversableLike$class.groupBy:(Lscala/collection/TraversableLike;Lscala/Function1;)Lscala/collection/Map;
	areturn
  Labels:
  LocalVariableTable: 
   Start  Length  Slot  Name   Signature
   0      6      0    this       Lscala/xml/MetaData;
   0      6      1    f       Lscala/Function1;


public int count(scala.Function1);
  Signature: (Lscala/Function1;)I
  Code:
   Stack=2, Locals=2, Args_size=2
	aload_0
	aload_1
	invokestatic	Method scala/collection/TraversableLike$class.count:(Lscala/collection/TraversableLike;Lscala/Function1;)I
	ireturn
  Labels:
  LocalVariableTable: 
   Start  Length  Slot  Name   Signature
   0      6      0    this       Lscala/xml/MetaData;
   0      6      1    p       Lscala/Function1;


public java.lang.Object foldLeft(java.lang.Object, scala.Function2);
  Signature: (Ljava/lang/Object;Lscala/Function2;)Ljava/lang/Object;
  Code:
   Stack=3, Locals=3, Args_size=3
	aload_0
	aload_1
	aload_2
	invokestatic	Method scala/collection/TraversableLike$class.foldLeft:(Lscala/collection/TraversableLike;Ljava/lang/Object;Lscala/Function2;)Ljava/lang/Object;
	areturn
  Labels:
  LocalVariableTable: 
   Start  Length  Slot  Name   Signature
   0      7      0    this       Lscala/xml/MetaData;
   0      7      1    z       Ljava/lang/Object;
   0      7      2    op       Lscala/Function2;


public java.lang.Object $div$colon(java.lang.Object, scala.Function2);
  Signature: (Ljava/lang/Object;Lscala/Function2;)Ljava/lang/Object;
  Code:
   Stack=3, Locals=3, Args_size=3
	aload_0
	aload_1
	aload_2
	invokestatic	Method scala/collection/TraversableLike$class.$div$colon:(Lscala/collection/TraversableLike;Ljava/lang/Object;Lscala/Function2;)Ljava/lang/Object;
	areturn
  Labels:
  LocalVariableTable: 
   Start  Length  Slot  Name   Signature
   0      7      0    this       Lscala/xml/MetaData;
   0      7      1    z       Ljava/lang/Object;
   0      7      2    op       Lscala/Function2;


public java.lang.Object $colon$bslash(java.lang.Object, scala.Function2);
  Signature: (Ljava/lang/Object;Lscala/Function2;)Ljava/lang/Object;
  Code:
   Stack=3, Locals=3, Args_size=3
	aload_0
	aload_1
	aload_2
	invokestatic	Method scala/collection/TraversableLike$class.$colon$bslash:(Lscala/collection/TraversableLike;Ljava/lang/Object;Lscala/Function2;)Ljava/lang/Object;
	areturn
  Labels:
  LocalVariableTable: 
   Start  Length  Slot  Name   Signature
   0      7      0    this       Lscala/xml/MetaData;
   0      7      1    z       Ljava/lang/Object;
   0      7      2    op       Lscala/Function2;


public java.lang.Object reduceLeft(scala.Function2);
  Signature: (Lscala/Function2;)Ljava/lang/Object;
  Code:
   Stack=2, Locals=2, Args_size=2
	aload_0
	aload_1
	invokestatic	Method scala/collection/TraversableLike$class.reduceLeft:(Lscala/collection/TraversableLike;Lscala/Function2;)Ljava/lang/Object;
	areturn
  Labels:
  LocalVariableTable: 
   Start  Length  Slot  Name   Signature
   0      6      0    this       Lscala/xml/MetaData;
   0      6      1    op       Lscala/Function2;


public scala.Option reduceLeftOption(scala.Function2);
  Signature: (Lscala/Function2;)Lscala/Option;
  Code:
   Stack=2, Locals=2, Args_size=2
	aload_0
	aload_1
	invokestatic	Method scala/collection/TraversableLike$class.reduceLeftOption:(Lscala/collection/TraversableLike;Lscala/Function2;)Lscala/Option;
	areturn
  Labels:
  LocalVariableTable: 
   Start  Length  Slot  Name   Signature
   0      6      0    this       Lscala/xml/MetaData;
   0      6      1    op       Lscala/Function2;


public scala.Option reduceRightOption(scala.Function2);
  Signature: (Lscala/Function2;)Lscala/Option;
  Code:
   Stack=2, Locals=2, Args_size=2
	aload_0
	aload_1
	invokestatic	Method scala/collection/TraversableLike$class.reduceRightOption:(Lscala/collection/TraversableLike;Lscala/Function2;)Lscala/Option;
	areturn
  Labels:
  LocalVariableTable: 
   Start  Length  Slot  Name   Signature
   0      6      0    this       Lscala/xml/MetaData;
   0      6      1    op       Lscala/Function2;


public java.lang.Object sum(scala.math.Numeric);
  Signature: (Lscala/math/Numeric;)Ljava/lang/Object;
  Code:
   Stack=2, Locals=2, Args_size=2
	aload_0
	aload_1
	invokestatic	Method scala/collection/TraversableLike$class.sum:(Lscala/collection/TraversableLike;Lscala/math/Numeric;)Ljava/lang/Object;
	areturn
  Labels:
  LocalVariableTable: 
   Start  Length  Slot  Name   Signature
   0      6      0    this       Lscala/xml/MetaData;
   0      6      1    num       Lscala/math/Numeric;


public java.lang.Object product(scala.math.Numeric);
  Signature: (Lscala/math/Numeric;)Ljava/lang/Object;
  Code:
   Stack=2, Locals=2, Args_size=2
	aload_0
	aload_1
	invokestatic	Method scala/collection/TraversableLike$class.product:(Lscala/collection/TraversableLike;Lscala/math/Numeric;)Ljava/lang/Object;
	areturn
  Labels:
  LocalVariableTable: 
   Start  Length  Slot  Name   Signature
   0      6      0    this       Lscala/xml/MetaData;
   0      6      1    num       Lscala/math/Numeric;


public java.lang.Object min(scala.math.Ordering);
  Signature: (Lscala/math/Ordering;)Ljava/lang/Object;
  Code:
   Stack=2, Locals=2, Args_size=2
	aload_0
	aload_1
	invokestatic	Method scala/collection/TraversableLike$class.min:(Lscala/collection/TraversableLike;Lscala/math/Ordering;)Ljava/lang/Object;
	areturn
  Labels:
  LocalVariableTable: 
   Start  Length  Slot  Name   Signature
   0      6      0    this       Lscala/xml/MetaData;
   0      6      1    cmp       Lscala/math/Ordering;


public java.lang.Object max(scala.math.Ordering);
  Signature: (Lscala/math/Ordering;)Ljava/lang/Object;
  Code:
   Stack=2, Locals=2, Args_size=2
	aload_0
	aload_1
	invokestatic	Method scala/collection/TraversableLike$class.max:(Lscala/collection/TraversableLike;Lscala/math/Ordering;)Ljava/lang/Object;
	areturn
  Labels:
  LocalVariableTable: 
   Start  Length  Slot  Name   Signature
   0      6      0    this       Lscala/xml/MetaData;
   0      6      1    cmp       Lscala/math/Ordering;


public scala.Option headOption();
  Signature: ()Lscala/Option;
  Code:
   Stack=1, Locals=1, Args_size=1
	aload_0
	invokestatic	Method scala/collection/TraversableLike$class.headOption:(Lscala/collection/TraversableLike;)Lscala/Option;
	areturn
  Labels:

public java.lang.Object tail();
  Signature: ()Ljava/lang/Object;
  Code:
   Stack=1, Locals=1, Args_size=1
	aload_0
	invokestatic	Method scala/collection/TraversableLike$class.tail:(Lscala/collection/TraversableLike;)Ljava/lang/Object;
	areturn
  Labels:

public java.lang.Object last();
  Signature: ()Ljava/lang/Object;
  Code:
   Stack=1, Locals=1, Args_size=1
	aload_0
	invokestatic	Method scala/collection/TraversableLike$class.last:(Lscala/collection/TraversableLike;)Ljava/lang/Object;
	areturn
  Labels:

public scala.Option lastOption();
  Signature: ()Lscala/Option;
  Code:
   Stack=1, Locals=1, Args_size=1
	aload_0
	invokestatic	Method scala/collection/TraversableLike$class.lastOption:(Lscala/collection/TraversableLike;)Lscala/Option;
	areturn
  Labels:

public java.lang.Object init();
  Signature: ()Ljava/lang/Object;
  Code:
   Stack=1, Locals=1, Args_size=1
	aload_0
	invokestatic	Method scala/collection/TraversableLike$class.init:(Lscala/collection/TraversableLike;)Ljava/lang/Object;
	areturn
  Labels:

public java.lang.Object drop(int);
  Signature: (I)Ljava/lang/Object;
  Code:
   Stack=2, Locals=2, Args_size=2
	aload_0
	iload_1
	invokestatic	Method scala/collection/TraversableLike$class.drop:(Lscala/collection/TraversableLike;I)Ljava/lang/Object;
	areturn
  Labels:
  LocalVariableTable: 
   Start  Length  Slot  Name   Signature
   0      6      0    this       Lscala/xml/MetaData;
   0      6      1    n       I


public java.lang.Object dropWhile(scala.Function1);
  Signature: (Lscala/Function1;)Ljava/lang/Object;
  Code:
   Stack=2, Locals=2, Args_size=2
	aload_0
	aload_1
	invokestatic	Method scala/collection/TraversableLike$class.dropWhile:(Lscala/collection/TraversableLike;Lscala/Function1;)Ljava/lang/Object;
	areturn
  Labels:
  LocalVariableTable: 
   Start  Length  Slot  Name   Signature
   0      6      0    this       Lscala/xml/MetaData;
   0      6      1    p       Lscala/Function1;


public scala.Tuple2 span(scala.Function1);
  Signature: (Lscala/Function1;)Lscala/Tuple2;
  Code:
   Stack=2, Locals=2, Args_size=2
	aload_0
	aload_1
	invokestatic	Method scala/collection/TraversableLike$class.span:(Lscala/collection/TraversableLike;Lscala/Function1;)Lscala/Tuple2;
	areturn
  Labels:
  LocalVariableTable: 
   Start  Length  Slot  Name   Signature
   0      6      0    this       Lscala/xml/MetaData;
   0      6      1    p       Lscala/Function1;


public scala.Tuple2 splitAt(int);
  Signature: (I)Lscala/Tuple2;
  Code:
   Stack=2, Locals=2, Args_size=2
	aload_0
	iload_1
	invokestatic	Method scala/collection/TraversableLike$class.splitAt:(Lscala/collection/TraversableLike;I)Lscala/Tuple2;
	areturn
  Labels:
  LocalVariableTable: 
   Start  Length  Slot  Name   Signature
   0      6      0    this       Lscala/xml/MetaData;
   0      6      1    n       I


public void copyToBuffer(scala.collection.mutable.Buffer);
  Signature: (Lscala/collection/mutable/Buffer;)V
  Code:
   Stack=2, Locals=2, Args_size=2
	aload_0
	aload_1
	invokestatic	Method scala/collection/TraversableLike$class.copyToBuffer:(Lscala/collection/TraversableLike;Lscala/collection/mutable/Buffer;)V
	return
  Labels:
  LocalVariableTable: 
   Start  Length  Slot  Name   Signature
   0      6      0    this       Lscala/xml/MetaData;
   0      6      1    dest       Lscala/collection/mutable/Buffer;


public void copyToArray(java.lang.Object, int);
  Signature: (Ljava/lang/Object;I)V
  Code:
   Stack=3, Locals=3, Args_size=3
	aload_0
	aload_1
	iload_2
	invokestatic	Method scala/collection/TraversableLike$class.copyToArray:(Lscala/collection/TraversableLike;Ljava/lang/Object;I)V
	return
  Labels:
  LocalVariableTable: 
   Start  Length  Slot  Name   Signature
   0      7      0    this       Lscala/xml/MetaData;
   0      7      1    xs       Ljava/lang/Object;
   0      7      2    start       I


public void copyToArray(java.lang.Object);
  Signature: (Ljava/lang/Object;)V
  Code:
   Stack=2, Locals=2, Args_size=2
	aload_0
	aload_1
	invokestatic	Method scala/collection/TraversableLike$class.copyToArray:(Lscala/collection/TraversableLike;Ljava/lang/Object;)V
	return
  Labels:
  LocalVariableTable: 
   Start  Length  Slot  Name   Signature
   0      6      0    this       Lscala/xml/MetaData;
   0      6      1    xs       Ljava/lang/Object;


public java.lang.Object toArray(scala.reflect.ClassManifest);
  Signature: (Lscala/reflect/ClassManifest;)Ljava/lang/Object;
  Code:
   Stack=2, Locals=2, Args_size=2
	aload_0
	aload_1
	invokestatic	Method scala/collection/TraversableLike$class.toArray:(Lscala/collection/TraversableLike;Lscala/reflect/ClassManifest;)Ljava/lang/Object;
	areturn
  Labels:
  LocalVariableTable: 
   Start  Length  Slot  Name   Signature
   0      6      0    this       Lscala/xml/MetaData;
   0      6      1    evidence$1       Lscala/reflect/ClassManifest;


public scala.collection.immutable.List toList();
  Signature: ()Lscala/collection/immutable/List;
  Code:
   Stack=1, Locals=1, Args_size=1
	aload_0
	invokestatic	Method scala/collection/TraversableLike$class.toList:(Lscala/collection/TraversableLike;)Lscala/collection/immutable/List;
	areturn
  Labels:

public scala.collection.Seq toSeq();
  Signature: ()Lscala/collection/Seq;
  Code:
   Stack=1, Locals=1, Args_size=1
	aload_0
	invokestatic	Method scala/collection/TraversableLike$class.toSeq:(Lscala/collection/TraversableLike;)Lscala/collection/Seq;
	areturn
  Labels:

public scala.collection.mutable.IndexedSeq toIndexedSeq();
  Signature: ()Lscala/collection/mutable/IndexedSeq;
  Code:
   Stack=1, Locals=1, Args_size=1
	aload_0
	invokestatic	Method scala/collection/TraversableLike$class.toIndexedSeq:(Lscala/collection/TraversableLike;)Lscala/collection/mutable/IndexedSeq;
	areturn
  Labels:

public scala.collection.immutable.Set toSet();
  Signature: ()Lscala/collection/immutable/Set;
  Code:
   Stack=1, Locals=1, Args_size=1
	aload_0
	invokestatic	Method scala/collection/TraversableLike$class.toSet:(Lscala/collection/TraversableLike;)Lscala/collection/immutable/Set;
	areturn
  Labels:

public scala.collection.immutable.Map toMap(scala.Predef$$less$colon$less);
  Signature: (Lscala/Predef$$less$colon$less;)Lscala/collection/immutable/Map;
  Code:
   Stack=2, Locals=2, Args_size=2
	aload_0
	aload_1
	invokestatic	Method scala/collection/TraversableLike$class.toMap:(Lscala/collection/TraversableLike;Lscala/Predef$$less$colon$less;)Lscala/collection/immutable/Map;
	areturn
  Labels:
  LocalVariableTable: 
   Start  Length  Slot  Name   Signature
   0      6      0    this       Lscala/xml/MetaData;
   0      6      1    ev       Lscala/Predef$$less$colon$less;


public java.lang.String mkString(java.lang.String, java.lang.String, java.lang.String);
  Signature: (Ljava/lang/String;Ljava/lang/String;Ljava/lang/String;)Ljava/lang/String;
  Code:
   Stack=4, Locals=4, Args_size=4
	aload_0
	aload_1
	aload_2
	aload_3
	invokestatic	Method scala/collection/TraversableLike$class.mkString:(Lscala/collection/TraversableLike;Ljava/lang/String;Ljava/lang/String;Ljava/lang/String;)Ljava/lang/String;
	areturn
  Labels:
  LocalVariableTable: 
   Start  Length  Slot  Name   Signature
   0      8      0    this       Lscala/xml/MetaData;
   0      8      1    start       Ljava/lang/String;
   0      8      2    sep       Ljava/lang/String;
   0      8      3    end       Ljava/lang/String;


public java.lang.String mkString(java.lang.String);
  Signature: (Ljava/lang/String;)Ljava/lang/String;
  Code:
   Stack=2, Locals=2, Args_size=2
	aload_0
	aload_1
	invokestatic	Method scala/collection/TraversableLike$class.mkString:(Lscala/collection/TraversableLike;Ljava/lang/String;)Ljava/lang/String;
	areturn
  Labels:
  LocalVariableTable: 
   Start  Length  Slot  Name   Signature
   0      6      0    this       Lscala/xml/MetaData;
   0      6      1    sep       Ljava/lang/String;


public java.lang.String mkString();
  Signature: ()Ljava/lang/String;
  Code:
   Stack=1, Locals=1, Args_size=1
	aload_0
	invokestatic	Method scala/collection/TraversableLike$class.mkString:(Lscala/collection/TraversableLike;)Ljava/lang/String;
	areturn
  Labels:

public scala.collection.mutable.StringBuilder addString(scala.collection.mutable.StringBuilder, java.lang.String, java.lang.String, java.lang.String);
  Signature: (Lscala/collection/mutable/StringBuilder;Ljava/lang/String;Ljava/lang/String;Ljava/lang/String;)Lscala/collection/mutable/StringBuilder;
  Code:
   Stack=5, Locals=5, Args_size=5
	aload_0
	aload_1
	aload_2
	aload_3
	aload	4
	invokestatic	Method scala/collection/TraversableLike$class.addString:(Lscala/collection/TraversableLike;Lscala/collection/mutable/StringBuilder;Ljava/lang/String;Ljava/lang/String;Ljava/lang/String;)Lscala/collection/mutable/StringBuilder;
	areturn
  Labels:
  LocalVariableTable: 
   Start  Length  Slot  Name   Signature
   0      10      0    this       Lscala/xml/MetaData;
   0      10      1    b       Lscala/collection/mutable/StringBuilder;
   0      10      2    start       Ljava/lang/String;
   0      10      3    sep       Ljava/lang/String;
   0      10      4    end       Ljava/lang/String;


public scala.collection.mutable.StringBuilder addString(scala.collection.mutable.StringBuilder, java.lang.String);
  Signature: (Lscala/collection/mutable/StringBuilder;Ljava/lang/String;)Lscala/collection/mutable/StringBuilder;
  Code:
   Stack=3, Locals=3, Args_size=3
	aload_0
	aload_1
	aload_2
	invokestatic	Method scala/collection/TraversableLike$class.addString:(Lscala/collection/TraversableLike;Lscala/collection/mutable/StringBuilder;Ljava/lang/String;)Lscala/collection/mutable/StringBuilder;
	areturn
  Labels:
  LocalVariableTable: 
   Start  Length  Slot  Name   Signature
   0      7      0    this       Lscala/xml/MetaData;
   0      7      1    b       Lscala/collection/mutable/StringBuilder;
   0      7      2    sep       Ljava/lang/String;


public scala.collection.mutable.StringBuilder addString(scala.collection.mutable.StringBuilder);
  Signature: (Lscala/collection/mutable/StringBuilder;)Lscala/collection/mutable/StringBuilder;
  Code:
   Stack=2, Locals=2, Args_size=2
	aload_0
	aload_1
	invokestatic	Method scala/collection/TraversableLike$class.addString:(Lscala/collection/TraversableLike;Lscala/collection/mutable/StringBuilder;)Lscala/collection/mutable/StringBuilder;
	areturn
  Labels:
  LocalVariableTable: 
   Start  Length  Slot  Name   Signature
   0      6      0    this       Lscala/xml/MetaData;
   0      6      1    b       Lscala/collection/mutable/StringBuilder;


public java.lang.String stringPrefix();
  Signature: ()Ljava/lang/String;
  Code:
   Stack=1, Locals=1, Args_size=1
	aload_0
	invokestatic	Method scala/collection/TraversableLike$class.stringPrefix:(Lscala/collection/TraversableLike;)Ljava/lang/String;
	areturn
  Labels:

public scala.collection.TraversableLike$WithFilter withFilter(scala.Function1);
  Signature: (Lscala/Function1;)Lscala/collection/TraversableLike$WithFilter;
  Code:
   Stack=2, Locals=2, Args_size=2
	aload_0
	aload_1
	invokestatic	Method scala/collection/TraversableLike$class.withFilter:(Lscala/collection/TraversableLike;Lscala/Function1;)Lscala/collection/TraversableLike$WithFilter;
	areturn
  Labels:
  LocalVariableTable: 
   Start  Length  Slot  Name   Signature
   0      6      0    this       Lscala/xml/MetaData;
   0      6      1    p       Lscala/Function1;

  Signature: length = 0x2
   01 FFFFFFD1 

public scala.xml.NamespaceBinding append$default$2();
  Signature: ()Lscala/xml/NamespaceBinding;
  Code:
   Stack=1, Locals=1, Args_size=1
	getstatic	Field scala/xml/TopScope$.MODULE$:Lscala/xml/TopScope$;
	areturn
  Labels:

public scala.xml.MetaData append(scala.xml.MetaData, scala.xml.NamespaceBinding);
  Signature: (Lscala/xml/MetaData;Lscala/xml/NamespaceBinding;)Lscala/xml/MetaData;
  Code:
   Stack=4, Locals=3, Args_size=3
	getstatic	Field scala/xml/MetaData$.MODULE$:Lscala/xml/MetaData$;
	aload_0
	aload_2
	aload_1
	invokevirtual	Method scala/xml/MetaData$.update:(Lscala/xml/MetaData;Lscala/xml/NamespaceBinding;Lscala/xml/MetaData;)Lscala/xml/MetaData;
	areturn
  Labels:
  LocalVariableTable: 
   Start  Length  Slot  Name   Signature
   0      10      0    this       Lscala/xml/MetaData;
   0      10      1    updates       Lscala/xml/MetaData;
   0      10      2    scope       Lscala/xml/NamespaceBinding;


public abstract scala.collection.Seq apply(java.lang.String);
  Signature: (Ljava/lang/String;)Lscala/collection/Seq;
  Signature: length = 0x2
   01 FFFFFFE3 

public final scala.collection.Seq apply(java.lang.String, scala.xml.Node, java.lang.String);
  Signature: (Ljava/lang/String;Lscala/xml/Node;Ljava/lang/String;)Lscala/collection/Seq;
  Code:
   Stack=4, Locals=4, Args_size=4
	aload_0
	aload_1
	aload_2
	invokevirtual	Method scala/xml/Node.scope:()Lscala/xml/NamespaceBinding;
	aload_3
	invokevirtual	Method apply:(Ljava/lang/String;Lscala/xml/NamespaceBinding;Ljava/lang/String;)Lscala/collection/Seq;
	areturn
  Labels:
  LocalVariableTable: 
   Start  Length  Slot  Name   Signature
   0      11      0    this       Lscala/xml/MetaData;
   0      11      1    namespace_uri       Ljava/lang/String;
   0      11      2    owner       Lscala/xml/Node;
   0      11      3    key       Ljava/lang/String;

  Signature: length = 0x2
   01 FFFFFFF2 

public abstract scala.collection.Seq apply(java.lang.String, scala.xml.NamespaceBinding, java.lang.String);
  Signature: (Ljava/lang/String;Lscala/xml/NamespaceBinding;Ljava/lang/String;)Lscala/collection/Seq;
  Signature: length = 0x2
   01 FFFFFFF3 

public abstract scala.xml.MetaData copy(scala.xml.MetaData);
  Signature: (Lscala/xml/MetaData;)Lscala/xml/MetaData;

public abstract java.lang.String getNamespace(scala.xml.Node);
  Signature: (Lscala/xml/Node;)Ljava/lang/String;

public boolean hasNext();
  Signature: ()Z
  Code:
   Stack=2, Locals=2, Args_size=1
	getstatic	Field scala/xml/Null$.MODULE$:Lscala/xml/Null$;
	aload_0
	invokevirtual	Method next:()Lscala/xml/MetaData;
	astore_1
	dup
	ifnonnull	l1 // aload_1
	pop
	aload_1
	ifnull	l2 // iconst_0
	goto	l3 // iconst_1
l1	aload_1
	invokevirtual	Method java/lang/Object.equals:(Ljava/lang/Object;)Z
	ifeq	l3 // iconst_1
l2	iconst_0
	goto	l4 // ireturn
l3	iconst_1
l4	ireturn
  Labels:
   	l1 = 20 // aload_1
   	l2 = 27 // iconst_0
   	l3 = 31 // iconst_1
   	l4 = 32 // ireturn

public int length();
  Signature: ()I
  Code:
   Stack=2, Locals=1, Args_size=1
	aload_0
	iconst_0
	invokevirtual	Method length:(I)I
	ireturn
  Labels:

public int length(int);
  Signature: (I)I
  Code:
   Stack=3, Locals=2, Args_size=2
	aload_0
	invokevirtual	Method next:()Lscala/xml/MetaData;
	iload_1
	iconst_1
	iadd
	invokevirtual	Method length:(I)I
	ireturn
  Labels:
  LocalVariableTable: 
   Start  Length  Slot  Name   Signature
   0      11      0    this       Lscala/xml/MetaData;
   0      11      1    i       I


public abstract boolean isPrefixed();
  Signature: ()Z

public boolean canEqual(java.lang.Object);
  Signature: (Ljava/lang/Object;)Z
  Code:
   Stack=1, Locals=3, Args_size=2
	aload_1
	astore_2
	aload_2
	instanceof	class scala/xml/MetaData
	ireturn
  Labels:
  LocalVariableTable: 
   Start  Length  Slot  Name   Signature
   0      7      0    this       Lscala/xml/MetaData;
   0      7      1    other       Ljava/lang/Object;
   2      4      2    temp4       Ljava/lang/Object;


public boolean strict_$eq$eq(scala.xml.Equality);
  Signature: (Lscala/xml/Equality;)Z
  Code:
   Stack=2, Locals=4, Args_size=2
	aload_1
	astore_2
	aload_2
	instanceof	class scala/xml/MetaData
	ifeq	l1 // iconst_0
	aload_0
	invokeinterface	InterfaceMethod scala/collection/TraversableLike.toSet:()Lscala/collection/immutable/Set;
	aload_2
	checkcast	class scala/xml/MetaData
	invokeinterface	InterfaceMethod scala/collection/TraversableLike.toSet:()Lscala/collection/immutable/Set;
	astore_3
	dup
	ifnonnull	l2 // aload_3
	pop
	aload_3
	ifnull	l3 // iconst_1
	goto	l4 // iconst_0
l2	aload_3
	invokevirtual	Method java/lang/Object.equals:(Ljava/lang/Object;)Z
	ifeq	l4 // iconst_0
l3	iconst_1
	goto	l5 // ireturn
l4	iconst_0
	goto	l5 // ireturn
l1	iconst_0
l5	ireturn
  Labels:
   	l2 = 37 // aload_3
   	l3 = 44 // iconst_1
   	l4 = 48 // iconst_0
   	l1 = 52 // iconst_0
   	l5 = 53 // ireturn
  LocalVariableTable: 
   Start  Length  Slot  Name   Signature
   0      54      0    this       Lscala/xml/MetaData;
   0      54      1    other       Lscala/xml/Equality;
   2      52      2    temp6       Lscala/xml/Equality;


public scala.collection.Seq basisForHashCode();
  Signature: ()Lscala/collection/Seq;
  Code:
   Stack=6, Locals=1, Args_size=1
	getstatic	Field scala/collection/immutable/List$.MODULE$:Lscala/collection/immutable/List$;
	getstatic	Field scala/Predef$.MODULE$:Lscala/Predef$;
	iconst_1
	anewarray	class scala/collection/immutable/Set
	dup
	iconst_0
	aload_0
	invokeinterface	InterfaceMethod scala/collection/TraversableLike.toSet:()Lscala/collection/immutable/Set;
	aastore
	checkcast	class "[Ljava/lang/Object;"
	invokevirtual	Method scala/Predef$.wrapRefArray:([Ljava/lang/Object;)Lscala/collection/mutable/WrappedArray;
	invokevirtual	Method scala/collection/immutable/List$.apply:(Lscala/collection/Seq;)Lscala/collection/immutable/List;
	areturn
  Labels:
  Signature: length = 0x2
   02 2A 

public scala.collection.Iterator iterator();
  Signature: ()Lscala/collection/Iterator;
  Code:
   Stack=4, Locals=1, Args_size=1
	getstatic	Field scala/package$.MODULE$:Lscala/package$;
	invokevirtual	Method scala/package$.Iterator:()Lscala/collection/Iterator$;
	aload_0
	invokevirtual	Method scala/collection/Iterator$.single:(Ljava/lang/Object;)Lscala/collection/Iterator;
	new	class scala/xml/MetaData$$anonfun$iterator$1
	dup
	aload_0
	invokespecial	Method scala/xml/MetaData$$anonfun$iterator$1."<init>":(Lscala/xml/MetaData;)V
	invokeinterface	InterfaceMethod scala/collection/Iterator.$plus$plus:(Lscala/Function0;)Lscala/collection/Iterator;
	areturn
  Labels:
  Signature: length = 0x2
   02 46 

public int size();
  Signature: ()I
  Code:
   Stack=2, Locals=1, Args_size=1
	iconst_1
	aload_0
	invokevirtual	Method iterator:()Lscala/collection/Iterator;
	invokeinterface	InterfaceMethod scala/collection/Iterator.length:()I
	iadd
	ireturn
  Labels:

public scala.xml.MetaData filter(scala.Function1);
  Signature: (Lscala/Function1;)Lscala/xml/MetaData;
  Code:
   Stack=3, Locals=2, Args_size=2
	aload_1
	aload_0
	invokeinterface	InterfaceMethod scala/Function1.apply:(Ljava/lang/Object;)Ljava/lang/Object;
	invokestatic	Method scala/runtime/BoxesRunTime.unboxToBoolean:(Ljava/lang/Object;)Z
	ifeq	l1 // aload_0
	aload_0
	aload_0
	invokevirtual	Method next:()Lscala/xml/MetaData;
	aload_1
	invokevirtual	Method filter:(Lscala/Function1;)Lscala/xml/MetaData;
	invokevirtual	Method copy:(Lscala/xml/MetaData;)Lscala/xml/MetaData;
	goto	l2 // areturn
l1	aload_0
	invokevirtual	Method next:()Lscala/xml/MetaData;
	aload_1
	invokevirtual	Method filter:(Lscala/Function1;)Lscala/xml/MetaData;
l2	areturn
  Labels:
   	l1 = 28 // aload_0
   	l2 = 36 // areturn
  LocalVariableTable: 
   Start  Length  Slot  Name   Signature
   0      37      0    this       Lscala/xml/MetaData;
   0      37      1    f       Lscala/Function1;

  Signature: length = 0x2
   02 5B 

public abstract java.lang.String key();
  Signature: ()Ljava/lang/String;

public abstract scala.collection.Seq value();
  Signature: ()Lscala/collection/Seq;
  Signature: length = 0x2
   02 5D 

public java.lang.String prefixedKey();
  Signature: ()Ljava/lang/String;
  Code:
   Stack=2, Locals=4, Args_size=1
	aload_0
	astore_1
	aload_1
	instanceof	class scala/xml/Attribute
	ifeq	l1 // aload_0
	aload_1
	checkcast	class scala/xml/Attribute
	astore_2
	aload_2
	astore_3
	aload_0
	aload_3
	invokespecial	Method gd1$1:(Lscala/xml/Attribute;)Z
	ifeq	l1 // aload_0
	new	class scala/collection/mutable/StringBuilder
	dup
	invokespecial	Method scala/collection/mutable/StringBuilder."<init>":()V
	aload_2
	invokeinterface	InterfaceMethod scala/xml/Attribute.pre:()Ljava/lang/String;
	invokevirtual	Method scala/collection/mutable/StringBuilder.append:(Ljava/lang/Object;)Lscala/collection/mutable/StringBuilder;
	ldc_w	String :
	invokevirtual	Method scala/collection/mutable/StringBuilder.append:(Ljava/lang/Object;)Lscala/collection/mutable/StringBuilder;
	aload_0
	invokevirtual	Method key:()Ljava/lang/String;
	invokevirtual	Method scala/collection/mutable/StringBuilder.append:(Ljava/lang/Object;)Lscala/collection/mutable/StringBuilder;
	invokevirtual	Method scala/collection/mutable/StringBuilder.toString:()Ljava/lang/String;
	goto	l2 // areturn
l1	aload_0
	invokevirtual	Method key:()Ljava/lang/String;
l2	areturn
  Labels:
   	l1 = 59 // aload_0
   	l2 = 63 // areturn
  LocalVariableTable: 
   Start  Length  Slot  Name   Signature
   0      64      0    this       Lscala/xml/MetaData;
   2      62      1    temp8       Lscala/xml/MetaData;
   14      49      2    temp9       Lscala/xml/Attribute;
   16      47      3    x       Lscala/xml/Attribute;


public scala.collection.immutable.Map asAttrMap();
  Signature: ()Lscala/collection/immutable/Map;
  Code:
   Stack=4, Locals=1, Args_size=1
	aload_0
	invokevirtual	Method iterator:()Lscala/collection/Iterator;
	new	class scala/xml/MetaData$$anonfun$asAttrMap$1
	dup
	aload_0
	invokespecial	Method scala/xml/MetaData$$anonfun$asAttrMap$1."<init>":(Lscala/xml/MetaData;)V
	invokeinterface	InterfaceMethod scala/collection/Iterator.map:(Lscala/Function1;)Lscala/collection/Iterator;
	getstatic	Field scala/Predef$.MODULE$:Lscala/Predef$;
	invokevirtual	Method scala/Predef$.conforms:()Lscala/Predef$$less$colon$less;
	invokeinterface	InterfaceMethod scala/collection/Iterator.toMap:(Lscala/Predef$$less$colon$less;)Lscala/collection/immutable/Map;
	areturn
  Labels:
  Signature: length = 0x2
   02 FFFFFF89 

public abstract scala.xml.MetaData next();
  Signature: ()Lscala/xml/MetaData;

public final scala.Option get(java.lang.String);
  Signature: (Ljava/lang/String;)Lscala/Option;
  Code:
   Stack=3, Locals=2, Args_size=2
	getstatic	Field scala/Option$.MODULE$:Lscala/Option$;
	aload_0
	aload_1
	invokevirtual	Method apply:(Ljava/lang/String;)Lscala/collection/Seq;
	invokevirtual	Method scala/Option$.apply:(Ljava/lang/Object;)Lscala/Option;
	areturn
  Labels:
  LocalVariableTable: 
   Start  Length  Slot  Name   Signature
   0      12      0    this       Lscala/xml/MetaData;
   0      12      1    key       Ljava/lang/String;

  Signature: length = 0x2
   02 FFFFFF96 

public final scala.Option get(java.lang.String, scala.xml.Node, java.lang.String);
  Signature: (Ljava/lang/String;Lscala/xml/Node;Ljava/lang/String;)Lscala/Option;
  Code:
   Stack=4, Locals=4, Args_size=4
	aload_0
	aload_1
	aload_2
	invokevirtual	Method scala/xml/Node.scope:()Lscala/xml/NamespaceBinding;
	aload_3
	invokevirtual	Method get:(Ljava/lang/String;Lscala/xml/NamespaceBinding;Ljava/lang/String;)Lscala/Option;
	areturn
  Labels:
  LocalVariableTable: 
   Start  Length  Slot  Name   Signature
   0      11      0    this       Lscala/xml/MetaData;
   0      11      1    uri       Ljava/lang/String;
   0      11      2    owner       Lscala/xml/Node;
   0      11      3    key       Ljava/lang/String;

  Signature: length = 0x2
   02 FFFFFF9C 

public final scala.Option get(java.lang.String, scala.xml.NamespaceBinding, java.lang.String);
  Signature: (Ljava/lang/String;Lscala/xml/NamespaceBinding;Ljava/lang/String;)Lscala/Option;
  Code:
   Stack=5, Locals=4, Args_size=4
	getstatic	Field scala/Option$.MODULE$:Lscala/Option$;
	aload_0
	aload_1
	aload_2
	aload_3
	invokevirtual	Method apply:(Ljava/lang/String;Lscala/xml/NamespaceBinding;Ljava/lang/String;)Lscala/collection/Seq;
	invokevirtual	Method scala/Option$.apply:(Ljava/lang/Object;)Lscala/Option;
	areturn
  Labels:
  LocalVariableTable: 
   Start  Length  Slot  Name   Signature
   0      14      0    this       Lscala/xml/MetaData;
   0      14      1    uri       Ljava/lang/String;
   0      14      2    scope       Lscala/xml/NamespaceBinding;
   0      14      3    key       Ljava/lang/String;

  Signature: length = 0x2
   02 FFFFFF9D 

public java.lang.String toString1();
  Signature: ()Ljava/lang/String;
  Code:
   Stack=4, Locals=1, Args_size=1
	getstatic	Field scala/xml/Utility$.MODULE$:Lscala/xml/Utility$;
	new	class scala/xml/MetaData$$anonfun$toString1$1
	dup
	aload_0
	invokespecial	Method scala/xml/MetaData$$anonfun$toString1$1."<init>":(Lscala/xml/MetaData;)V
	invokevirtual	Method scala/xml/Utility$.sbToString:(Lscala/Function1;)Ljava/lang/String;
	areturn
  Labels:

public abstract void toString1(scala.collection.mutable.StringBuilder);
  Signature: (Lscala/collection/mutable/StringBuilder;)V

public java.lang.String toString();
  Signature: ()Ljava/lang/String;
  Code:
   Stack=4, Locals=1, Args_size=1
	getstatic	Field scala/xml/Utility$.MODULE$:Lscala/xml/Utility$;
	new	class scala/xml/MetaData$$anonfun$toString$1
	dup
	aload_0
	invokespecial	Method scala/xml/MetaData$$anonfun$toString$1."<init>":(Lscala/xml/MetaData;)V
	invokevirtual	Method scala/xml/Utility$.sbToString:(Lscala/Function1;)Ljava/lang/String;
	areturn
  Labels:

public scala.collection.mutable.StringBuilder buildString(scala.collection.mutable.StringBuilder);
  Signature: (Lscala/collection/mutable/StringBuilder;)Lscala/collection/mutable/StringBuilder;
  Code:
   Stack=2, Locals=2, Args_size=2
	aload_1
	ldc_w	int 32
	invokevirtual	Method scala/collection/mutable/StringBuilder.append:(C)Lscala/collection/mutable/StringBuilder;
	pop
	aload_0
	aload_1
	invokevirtual	Method toString1:(Lscala/collection/mutable/StringBuilder;)V
	aload_0
	invokevirtual	Method next:()Lscala/xml/MetaData;
	aload_1
	invokevirtual	Method buildString:(Lscala/collection/mutable/StringBuilder;)Lscala/collection/mutable/StringBuilder;
	areturn
  Labels:
  LocalVariableTable: 
   Start  Length  Slot  Name   Signature
   0      22      0    this       Lscala/xml/MetaData;
   0      22      1    sb       Lscala/collection/mutable/StringBuilder;


public abstract boolean wellformed(scala.xml.NamespaceBinding);
  Signature: (Lscala/xml/NamespaceBinding;)Z

public abstract scala.xml.MetaData remove(java.lang.String);
  Signature: (Ljava/lang/String;)Lscala/xml/MetaData;

public abstract scala.xml.MetaData remove(java.lang.String, scala.xml.NamespaceBinding, java.lang.String);
  Signature: (Ljava/lang/String;Lscala/xml/NamespaceBinding;Ljava/lang/String;)Lscala/xml/MetaData;

public final scala.xml.MetaData remove(java.lang.String, scala.xml.Node, java.lang.String);
  Signature: (Ljava/lang/String;Lscala/xml/Node;Ljava/lang/String;)Lscala/xml/MetaData;
  Code:
   Stack=4, Locals=4, Args_size=4
	aload_0
	aload_1
	aload_2
	invokevirtual	Method scala/xml/Node.scope:()Lscala/xml/NamespaceBinding;
	aload_3
	invokevirtual	Method remove:(Ljava/lang/String;Lscala/xml/NamespaceBinding;Ljava/lang/String;)Lscala/xml/MetaData;
	areturn
  Labels:
  LocalVariableTable: 
   Start  Length  Slot  Name   Signature
   0      11      0    this       Lscala/xml/MetaData;
   0      11      1    namespace       Ljava/lang/String;
   0      11      2    owner       Lscala/xml/Node;
   0      11      3    key       Ljava/lang/String;


public scala.collection.TraversableView view(int, int);
  Signature: (II)Lscala/collection/TraversableView;
  Code:
   Stack=3, Locals=3, Args_size=3
	aload_0
	iload_1
	iload_2
	invokeinterface	InterfaceMethod scala/collection/IterableLike.view:(II)Lscala/collection/IterableView;
	areturn
  Labels:
  LocalVariableTable: 
   Start  Length  Slot  Name   Signature
   0      9      0    this       Lscala/xml/MetaData;
   0      9      1    from       I
   0      9      2    until       I


public scala.collection.TraversableView view();
  Signature: ()Lscala/collection/TraversableView;
  Code:
   Stack=1, Locals=1, Args_size=1
	aload_0
	invokeinterface	InterfaceMethod scala/collection/IterableLike.view:()Lscala/collection/IterableView;
	areturn
  Labels:

public scala.collection.Traversable toCollection(java.lang.Object);
  Signature: (Ljava/lang/Object;)Lscala/collection/Traversable;
  Code:
   Stack=2, Locals=2, Args_size=2
	aload_0
	aload_1
	invokeinterface	InterfaceMethod scala/collection/IterableLike.toCollection:(Ljava/lang/Object;)Lscala/collection/Iterable;
	areturn
  Labels:
  LocalVariableTable: 
   Start  Length  Slot  Name   Signature
   0      8      0    this       Lscala/xml/MetaData;
   0      8      1    repr       Ljava/lang/Object;


public scala.collection.Traversable thisCollection();
  Signature: ()Lscala/collection/Traversable;
  Code:
   Stack=1, Locals=1, Args_size=1
	aload_0
	invokeinterface	InterfaceMethod scala/collection/IterableLike.thisCollection:()Lscala/collection/Iterable;
	areturn
  Labels:

public java.lang.Object filter(scala.Function1);
  Signature: (Lscala/Function1;)Ljava/lang/Object;
  Code:
   Stack=2, Locals=2, Args_size=2
	aload_0
	aload_1
	invokevirtual	Method filter:(Lscala/Function1;)Lscala/xml/MetaData;
	areturn
  Labels:
  LocalVariableTable: 
   Start  Length  Slot  Name   Signature
   0      6      0    this       Lscala/xml/MetaData;
   0      6      1    p       Lscala/Function1;


private final boolean gd1$1(scala.xml.Attribute);
  Signature: (Lscala/xml/Attribute;)Z
  Code:
   Stack=1, Locals=2, Args_size=2
	aload_1
	invokeinterface	InterfaceMethod scala/xml/Attribute.isPrefixed:()Z
	ireturn
  Labels:

public scala.xml.MetaData();
  Signature: ()V
  Code:
   Stack=1, Locals=1, Args_size=1
	aload_0
	invokespecial	Method java/lang/Object."<init>":()V
	aload_0
	invokestatic	Method scala/collection/TraversableLike$class.$init$:(Lscala/collection/TraversableLike;)V
	aload_0
	invokestatic	Method scala/collection/generic/GenericTraversableTemplate$class.$init$:(Lscala/collection/generic/GenericTraversableTemplate;)V
	aload_0
	invokestatic	Method scala/collection/Traversable$class.$init$:(Lscala/collection/Traversable;)V
	aload_0
	invokestatic	Method scala/collection/IterableLike$class.$init$:(Lscala/collection/IterableLike;)V
	aload_0
	invokestatic	Method scala/collection/Iterable$class.$init$:(Lscala/collection/Iterable;)V
	aload_0
	invokestatic	Method scala/xml/Equality$class.$init$:(Lscala/xml/Equality;)V
	return
  Labels:

}

