Compiled from "MetaData.scala"
public final class scala.xml.MetaData$$anonfun$asAttrMap$1 extends scala.runtime.AbstractFunction1 implements java.io.Serializable
  SourceFile: "MetaData.scala"
  Scala: length = 0x
   
  InnerClass: 
   public final $anonfun$asAttrMap$1=class scala/xml/MetaData$$anonfun$asAttrMap$1 of class scala/xml/MetaData
  minor version: 0
  major version: 49
  Constant pool:
Asciz	SourceFile;
Asciz	MetaData.scala;
Asciz	<clinit>;
Asciz	()V;
Asciz	Code;
Asciz	serialVersionUID;
Asciz	J;
Asciz	scala/xml/MetaData$$anonfun$asAttrMap$1;
class	scala/xml/MetaData$$anonfun$asAttrMap$1
NameAndType	serialVersionUID:J
Field	scala/xml/MetaData$$anonfun$asAttrMap$1.serialVersionUID:J
Asciz	apply;
Asciz	(Lscala/xml/MetaData;)Lscala/Tuple2;;
Asciz	scala/Tuple2;
class	scala/Tuple2
Asciz	LineNumberTable;
Asciz	scala/xml/MetaData;
class	scala/xml/MetaData
Asciz	prefixedKey;
Asciz	()Ljava/lang/String;;
NameAndType	prefixedKey:()Ljava/lang/String;
Method	scala/xml/MetaData.prefixedKey:()Ljava/lang/String;
Asciz	scala/xml/NodeSeq$;
class	scala/xml/NodeSeq$
Asciz	MODULE$;
Asciz	Lscala/xml/NodeSeq$;;
NameAndType	MODULE$:Lscala/xml/NodeSeq$;
Field	scala/xml/NodeSeq$.MODULE$:Lscala/xml/NodeSeq$;
Asciz	value;
Asciz	()Lscala/collection/Seq;;
NameAndType	value:()Lscala/collection/Seq;
Method	scala/xml/MetaData.value:()Lscala/collection/Seq;
Asciz	seqToNodeSeq;
Asciz	(Lscala/collection/Seq;)Lscala/xml/NodeSeq;;
NameAndType	seqToNodeSeq:(Lscala/collection/Seq;)Lscala/xml/NodeSeq;
Method	scala/xml/NodeSeq$.seqToNodeSeq:(Lscala/collection/Seq;)Lscala/xml/NodeSeq;
Asciz	scala/xml/NodeSeq;
class	scala/xml/NodeSeq
Asciz	text;
NameAndType	text:()Ljava/lang/String;
Method	scala/xml/NodeSeq.text:()Ljava/lang/String;
Asciz	<init>;
Asciz	(Ljava/lang/Object;Ljava/lang/Object;)V;
NameAndType	"<init>":(Ljava/lang/Object;Ljava/lang/Object;)V
Method	scala/Tuple2."<init>":(Ljava/lang/Object;Ljava/lang/Object;)V
Asciz	this;
Asciz	Lscala/xml/MetaData$$anonfun$asAttrMap$1;;
Asciz	x;
Asciz	Lscala/xml/MetaData;;
Asciz	LocalVariableTable;
Asciz	(Lscala/xml/MetaData;)Lscala/Tuple2<Ljava/lang/String;Ljava/lang/String;>;;
Asciz	Signature;
Asciz	(Ljava/lang/Object;)Ljava/lang/Object;;
NameAndType	apply:(Lscala/xml/MetaData;)Lscala/Tuple2;
Method	scala/xml/MetaData$$anonfun$asAttrMap$1.apply:(Lscala/xml/MetaData;)Lscala/Tuple2;
Asciz	v1;
Asciz	Ljava/lang/Object;;
Asciz	(Lscala/xml/MetaData;)V;
Asciz	scala/runtime/AbstractFunction1;
class	scala/runtime/AbstractFunction1
NameAndType	"<init>":()V
Method	scala/runtime/AbstractFunction1."<init>":()V
Asciz	$outer;
Asciz	Scala;
Asciz	InnerClasses;
Asciz	$anonfun$asAttrMap$1;
Asciz	java/io/Serializable;
class	java/io/Serializable

{
public static final long serialVersionUID;
  Signature: J

public static {};
  Signature: ()V
  Code:
   Stack=2, Locals=0, Args_size=0
	lconst_0
	putstatic	Field serialVersionUID:J
	return
  Labels:

public final scala.Tuple2 apply(scala.xml.MetaData);
  Signature: (Lscala/xml/MetaData;)Lscala/Tuple2;
  Code:
   Stack=5, Locals=2, Args_size=2
	new	class scala/Tuple2
	dup
	aload_1
	invokevirtual	Method scala/xml/MetaData.prefixedKey:()Ljava/lang/String;
	getstatic	Field scala/xml/NodeSeq$.MODULE$:Lscala/xml/NodeSeq$;
	aload_1
	invokevirtual	Method scala/xml/MetaData.value:()Lscala/collection/Seq;
	invokevirtual	Method scala/xml/NodeSeq$.seqToNodeSeq:(Lscala/collection/Seq;)Lscala/xml/NodeSeq;
	invokevirtual	Method scala/xml/NodeSeq.text:()Ljava/lang/String;
	invokespecial	Method scala/Tuple2."<init>":(Ljava/lang/Object;Ljava/lang/Object;)V
	areturn
  Labels:
  LocalVariableTable: 
   Start  Length  Slot  Name   Signature
   0      25      0    this       Lscala/xml/MetaData$$anonfun$asAttrMap$1;
   0      25      1    x       Lscala/xml/MetaData;

  Signature: length = 0x2
   00 33 

public final java.lang.Object apply(java.lang.Object);
  Signature: (Ljava/lang/Object;)Ljava/lang/Object;
  Code:
   Stack=2, Locals=2, Args_size=2
	aload_0
	aload_1
	checkcast	class scala/xml/MetaData
	invokevirtual	Method apply:(Lscala/xml/MetaData;)Lscala/Tuple2;
	areturn
  Labels:
  LocalVariableTable: 
   Start  Length  Slot  Name   Signature
   0      9      0    this       Lscala/xml/MetaData$$anonfun$asAttrMap$1;
   0      9      1    v1       Ljava/lang/Object;


public scala.xml.MetaData$$anonfun$asAttrMap$1(scala.xml.MetaData);
  Signature: (Lscala/xml/MetaData;)V
  Code:
   Stack=1, Locals=2, Args_size=2
	aload_0
	invokespecial	Method scala/runtime/AbstractFunction1."<init>":()V
	return
  Labels:
  LocalVariableTable: 
   Start  Length  Slot  Name   Signature
   0      5      0    this       Lscala/xml/MetaData$$anonfun$asAttrMap$1;
   0      5      1    $outer       Lscala/xml/MetaData;


}

