Compiled from "NamespaceBinding.scala"
public class scala.xml.NamespaceBinding extends java.lang.Object implements scala.xml.Equality,scala.ScalaObject,scala.Product,java.io.Serializable
  SourceFile: "NamespaceBinding.scala"
  ScalaSig: length = 0x590
   05 00 FFFFFF81 43 06 08 01 02 FFFFFF84 FFFFFF80 FFFFFF80 FFFFFF80 40 07 02 10
   4E 61 6D 65 73 70 61 63 65 42 69 6E 64 69 6E 67
   0A 02 03 04 01 03 78 6D 6C 0A 01 05 01 05 73 63
   61 6C 61 03 00 13 05 00 08 10 14 18 10 02 09 0E
   0D 01 0A 0A 02 0B 0C 01 04 6C 61 6E 67 0A 01 0D
   01 04 6A 61 76 61 09 02 0F 0A 02 06 4F 62 6A 65
   63 74 10 02 11 12 0D 01 02 09 02 13 02 02 08 45
   71 75 61 6C 69 74 79 10 02 15 16 0D 01 04 09 02
   17 04 02 0B 53 63 61 6C 61 4F 62 6A 65 63 74 10
   02 15 19 09 02 1A 04 02 07 50 72 6F 64 75 63 74
   08 08 1C 00 FFFFFF82 FFFFFFCA FFFFFF80 FFFFFF84 00 1D 01 06 70 72 65 66
   69 78 15 01 1E 10 02 1F 22 0E 02 15 20 09 02 21
   04 01 06 50 72 65 64 65 66 09 02 23 24 02 06 53
   74 72 69 6E 67 0A 02 21 04 08 08 26 00 FFFFFF82 FFFFFF88 FFFFFFA0
   FFFFFF80 04 1E 01 07 70 72 65 66 69 78 20 08 08 28 00
   FFFFFF82 FFFFFFCA FFFFFF80 FFFFFF84 00 1D 01 03 75 72 69 08 08 2A 00 FFFFFF82
   FFFFFF88 FFFFFFA0 FFFFFF80 04 1E 01 04 75 72 69 20 08 08 2C 00 FFFFFF82
   FFFFFFCA FFFFFF80 FFFFFF84 00 2D 01 06 70 61 72 65 6E 74 15 01 2E
   10 02 11 00 08 08 30 00 FFFFFF82 FFFFFF88 FFFFFFA0 FFFFFF80 04 2E 01 07
   70 61 72 65 6E 74 20 08 05 32 00 FFFFFF84 00 33 01 06
   3C 69 6E 69 74 3E 14 04 2E 34 35 36 08 05 1C 31
   FFFFFFC0 00 1E 08 05 28 31 FFFFFFC0 00 1E 08 05 2C 31 FFFFFFC0 00
   2E 08 05 38 00 FFFFFF84 00 39 01 06 67 65 74 55 52 49
   14 02 1E 3A 08 05 3B 37 FFFFFFC0 00 1E 01 07 5F 70 72
   65 66 69 78 08 05 3D 00 FFFFFF84 00 3E 01 09 67 65 74
   50 72 65 66 69 78 14 02 1E 3F 08 05 40 3C FFFFFFC0 00
   1E 01 04 5F 75 72 69 08 05 42 00 FFFFFF84 20 43 01 08
   74 6F 53 74 72 69 6E 67 14 01 1E 08 05 45 00 FFFFFF84
   20 46 01 08 63 61 6E 45 71 75 61 6C 14 02 47 4A
   10 02 15 48 09 02 49 04 02 07 42 6F 6F 6C 65 61
   6E 08 05 4B 44 FFFFFFC0 00 4C 01 05 6F 74 68 65 72 10
   02 15 4D 09 02 4E 04 02 03 41 6E 79 08 05 50 00
   FFFFFF84 20 51 01 0D 73 74 72 69 63 74 5F 24 65 71 24
   65 71 14 02 47 52 08 05 4B 4F FFFFFFC0 00 10 08 05 54
   00 FFFFFF84 00 55 01 10 62 61 73 69 73 46 6F 72 48 61
   73 68 43 6F 64 65 15 01 56 10 03 57 5F 4C 0E 02
   58 5D 0E 02 59 5C 0D 01 5A 0A 02 5B 06 01 06 3C
   72 6F 6F 74 3E 09 01 05 09 02 5E 04 01 07 70 61
   63 6B 61 67 65 09 02 60 61 02 03 53 65 71 0A 02
   5E 04 08 05 63 00 FFFFFF84 00 64 01 0B 62 75 69 6C 64
   53 74 72 69 6E 67 14 02 1E 65 08 05 66 62 FFFFFFC0 00
   2E 01 04 73 74 6F 70 08 05 63 00 FFFFFF84 00 68 14 03
   69 6C 71 10 02 15 6A 09 02 6B 04 02 04 55 6E 69
   74 08 05 6D 67 FFFFFFC0 00 6E 01 02 73 62 10 02 57 6F
   09 02 70 61 02 0D 53 74 72 69 6E 67 42 75 69 6C
   64 65 72 08 05 66 67 FFFFFFC0 00 2E 08 07 73 00 FFFFFF81 FFFFFF80
   FFFFFF84 00 74 01 04 63 6F 70 79 14 04 2E 75 76 77 08
   07 1C 72 FFFFFF90 FFFFFF80 FFFFFFC0 00 1E 08 07 28 72 FFFFFF90 FFFFFF80 FFFFFFC0 00
   1E 08 07 2C 72 FFFFFF90 FFFFFF80 FFFFFFC0 00 2E 08 07 79 00 FFFFFF91 FFFFFF80
   FFFFFF84 00 7A 01 0E 63 6F 70 79 24 64 65 66 61 75 6C
   74 24 31 15 01 7B 2A 02 1E 7C 2B 01 7D 10 03 7E
   FFFFFF81 03 0D 01 7F 0A 04 FFFFFF81 00 FFFFFF81 01 01 09 75 6E 63
   68 65 63 6B 65 64 0A 03 FFFFFF81 02 04 01 0A 61 6E 6E
   6F 74 61 74 69 6F 6E 09 03 FFFFFF81 04 7F 02 11 75 6E
   63 68 65 63 6B 65 64 56 61 72 69 61 6E 63 65 08
   08 FFFFFF81 06 00 FFFFFF91 FFFFFF80 FFFFFF84 00 7A 01 0E 63 6F 70 79 24
   64 65 66 61 75 6C 74 24 32 08 09 FFFFFF81 08 00 FFFFFF91 FFFFFF80
   FFFFFF84 00 FFFFFF81 09 01 0E 63 6F 70 79 24 64 65 66 61 75
   6C 74 24 33 15 02 FFFFFF81 0A 2A 02 2E 7C 08 0A FFFFFF81 0C
   00 FFFFFF84 FFFFFF80 FFFFFF80 FFFFFF84 20 FFFFFF81 0D 01 0D 70 72 6F 64 75 63
   74 50 72 65 66 69 78 15 02 FFFFFF81 0E 10 03 09 FFFFFF81 0F
   09 02 23 0A 08 0A FFFFFF81 11 00 FFFFFF84 FFFFFF80 FFFFFF80 FFFFFF84 20 FFFFFF81 12
   01 0C 70 72 6F 64 75 63 74 41 72 69 74 79 15 02
   FFFFFF81 13 10 03 15 FFFFFF81 14 09 03 FFFFFF81 15 04 02 03 49 6E
   74 08 0A FFFFFF81 17 00 FFFFFF84 FFFFFF80 FFFFFF80 FFFFFF84 20 FFFFFF81 18 01 0E 70
   72 6F 64 75 63 74 45 6C 65 6D 65 6E 74 14 03 4C
   FFFFFF81 19 08 0A FFFFFF81 1A FFFFFF81 16 FFFFFF81 FFFFFF80 FFFFFFC0 00 FFFFFF81 13 01 03
   78 24 31 08 0A FFFFFF81 1C 00 FFFFFF84 FFFFFF80 FFFFFF80 FFFFFF84 20 FFFFFF81 1D 01
   12 70 72 6F 64 75 63 74 45 6C 65 6D 65 6E 74 4E
   61 6D 65 14 04 FFFFFF81 0E FFFFFF81 1E 08 0A FFFFFF81 1A FFFFFF81 1B FFFFFF81
   FFFFFF80 FFFFFFC0 00 FFFFFF81 13 28 05 00 FFFFFF81 20 FFFFFF81 23 10 03 15 FFFFFF81
   21 09 03 FFFFFF81 22 04 02 10 53 65 72 69 61 6C 56 65
   72 73 69 6F 6E 55 49 44 1E 08 FFFFFFDD 0B FFFFFFFA 79 FFFFFFCB 62
   73 FFFFFFBB 28 03 00 FFFFFF81 25 10 03 15 FFFFFF81 26 09 03 FFFFFF81 27
   04 02 0C 73 65 72 69 61 6C 69 7A 61 62 6C 65 07
   09 FFFFFF81 29 02 FFFFFF81 FFFFFF80 FFFFFF88 02 FFFFFF81 2A 01 10 4E 61 6D 65
   73 70 61 63 65 42 69 6E 64 69 6E 67 10 03 11 FFFFFF81
   2B 06 09 01 02 FFFFFF84 FFFFFF81 FFFFFF80 FFFFFF88 02 FFFFFF81 2C 13 06 FFFFFF81 2B
   08 FFFFFF81 2D 14 10 07 15 FFFFFF81 2E 1E 1E 2E 2E 09 03 FFFFFF81
   2F 04 02 09 46 75 6E 63 74 69 6F 6E 33 08 07 32
   FFFFFF81 2B FFFFFF84 00 FFFFFF81 31 14 02 FFFFFF81 2A 08 0A FFFFFF81 33 FFFFFF81 2B
   FFFFFF81 FFFFFF80 FFFFFF84 40 FFFFFF81 34 01 05 61 70 70 6C 79 14 07 2E
   FFFFFF81 35 FFFFFF81 36 FFFFFF81 37 08 06 1C FFFFFF81 32 FFFFFFC0 00 1E 08 06
   28 FFFFFF81 32 FFFFFFC0 00 1E 08 06 2C FFFFFF81 32 FFFFFFC0 00 2E 08 0A
   FFFFFF81 39 FFFFFF81 2B FFFFFF81 FFFFFF80 FFFFFF84 40 FFFFFF81 3A 01 07 75 6E 61 70
   70 6C 79 14 04 FFFFFF81 3B FFFFFF81 41 10 05 15 FFFFFF81 3C FFFFFF81 3E
   09 03 FFFFFF81 3D 04 02 06 4F 70 74 69 6F 6E 10 06 15
   FFFFFF81 3F 1E 1E 2E 09 03 FFFFFF81 40 04 02 06 54 75 70 6C
   65 33 08 07 FFFFFF81 42 FFFFFF81 38 FFFFFFC0 00 2E 01 03 78 24 30
   
  InnerClass: 
   public final $anonfun$toString$1=class scala/xml/NamespaceBinding$$anonfun$toString$1 of class scala/xml/NamespaceBinding
   public final $anonfun$buildString$1=class scala/xml/NamespaceBinding$$anonfun$buildString$1 of class scala/xml/NamespaceBinding
  minor version: 0
  major version: 49
  Constant pool:
Asciz	SourceFile;
Asciz	NamespaceBinding.scala;
Asciz	<clinit>;
Asciz	()V;
Asciz	Code;
Asciz	serialVersionUID;
Asciz	J;
long	-2518644165573446725l;
Asciz	scala/xml/NamespaceBinding;
class	scala/xml/NamespaceBinding
NameAndType	serialVersionUID:J
Field	scala/xml/NamespaceBinding.serialVersionUID:J
Asciz	parent;
Asciz	Lscala/xml/NamespaceBinding;;
Asciz	uri;
Asciz	Ljava/lang/String;;
Asciz	prefix;
Asciz	productIterator;
Asciz	()Lscala/collection/Iterator;;
Asciz	LineNumberTable;
Asciz	scala/Product$class;
class	scala/Product$class
Asciz	(Lscala/Product;)Lscala/collection/Iterator;;
NameAndType	productIterator:(Lscala/Product;)Lscala/collection/Iterator;
Method	scala/Product$class.productIterator:(Lscala/Product;)Lscala/collection/Iterator;
Asciz	productElements;
NameAndType	productElements:(Lscala/Product;)Lscala/collection/Iterator;
Method	scala/Product$class.productElements:(Lscala/Product;)Lscala/collection/Iterator;
Asciz	Deprecated;
Asciz	strict_$bang$eq;
Asciz	(Lscala/xml/Equality;)Z;
Asciz	scala/xml/Equality$class;
class	scala/xml/Equality$class
Asciz	(Lscala/xml/Equality;Lscala/xml/Equality;)Z;
NameAndType	strict_$bang$eq:(Lscala/xml/Equality;Lscala/xml/Equality;)Z
Method	scala/xml/Equality$class.strict_$bang$eq:(Lscala/xml/Equality;Lscala/xml/Equality;)Z
Asciz	this;
Asciz	other;
Asciz	Lscala/xml/Equality;;
Asciz	LocalVariableTable;
Asciz	hashCode;
Asciz	()I;
Asciz	(Lscala/xml/Equality;)I;
NameAndType	hashCode:(Lscala/xml/Equality;)I
Method	scala/xml/Equality$class.hashCode:(Lscala/xml/Equality;)I
Asciz	equals;
Asciz	(Ljava/lang/Object;)Z;
Asciz	(Lscala/xml/Equality;Ljava/lang/Object;)Z;
NameAndType	equals:(Lscala/xml/Equality;Ljava/lang/Object;)Z
Method	scala/xml/Equality$class.equals:(Lscala/xml/Equality;Ljava/lang/Object;)Z
Asciz	Ljava/lang/Object;;
Asciz	xml_$eq$eq;
NameAndType	xml_$eq$eq:(Lscala/xml/Equality;Ljava/lang/Object;)Z
Method	scala/xml/Equality$class.xml_$eq$eq:(Lscala/xml/Equality;Ljava/lang/Object;)Z
Asciz	xml_$bang$eq;
NameAndType	xml_$bang$eq:(Lscala/xml/Equality;Ljava/lang/Object;)Z
Method	scala/xml/Equality$class.xml_$bang$eq:(Lscala/xml/Equality;Ljava/lang/Object;)Z
Asciz	copy$default$3;
Asciz	()Lscala/xml/NamespaceBinding;;
NameAndType	parent:()Lscala/xml/NamespaceBinding;
Method	scala/xml/NamespaceBinding.parent:()Lscala/xml/NamespaceBinding;
Asciz	copy$default$2;
Asciz	()Ljava/lang/String;;
NameAndType	uri:()Ljava/lang/String;
Method	scala/xml/NamespaceBinding.uri:()Ljava/lang/String;
Asciz	copy$default$1;
NameAndType	prefix:()Ljava/lang/String;
Method	scala/xml/NamespaceBinding.prefix:()Ljava/lang/String;
NameAndType	prefix:Ljava/lang/String;
Field	scala/xml/NamespaceBinding.prefix:Ljava/lang/String;
NameAndType	uri:Ljava/lang/String;
Field	scala/xml/NamespaceBinding.uri:Ljava/lang/String;
NameAndType	parent:Lscala/xml/NamespaceBinding;
Field	scala/xml/NamespaceBinding.parent:Lscala/xml/NamespaceBinding;
Asciz	getURI;
Asciz	(Ljava/lang/String;)Ljava/lang/String;;
Asciz	java/lang/Object;
class	java/lang/Object
NameAndType	equals:(Ljava/lang/Object;)Z
Method	java/lang/Object.equals:(Ljava/lang/Object;)Z
NameAndType	getURI:(Ljava/lang/String;)Ljava/lang/String;
Method	scala/xml/NamespaceBinding.getURI:(Ljava/lang/String;)Ljava/lang/String;
Asciz	_prefix;
Asciz	getPrefix;
NameAndType	getPrefix:(Ljava/lang/String;)Ljava/lang/String;
Method	scala/xml/NamespaceBinding.getPrefix:(Ljava/lang/String;)Ljava/lang/String;
Asciz	_uri;
Asciz	toString;
Asciz	scala/xml/Utility$;
class	scala/xml/Utility$
Asciz	MODULE$;
Asciz	Lscala/xml/Utility$;;
NameAndType	MODULE$:Lscala/xml/Utility$;
Field	scala/xml/Utility$.MODULE$:Lscala/xml/Utility$;
Asciz	scala/xml/NamespaceBinding$$anonfun$toString$1;
class	scala/xml/NamespaceBinding$$anonfun$toString$1
Asciz	<init>;
Asciz	(Lscala/xml/NamespaceBinding;)V;
NameAndType	"<init>":(Lscala/xml/NamespaceBinding;)V
Method	scala/xml/NamespaceBinding$$anonfun$toString$1."<init>":(Lscala/xml/NamespaceBinding;)V
Asciz	sbToString;
Asciz	(Lscala/Function1;)Ljava/lang/String;;
NameAndType	sbToString:(Lscala/Function1;)Ljava/lang/String;
Method	scala/xml/Utility$.sbToString:(Lscala/Function1;)Ljava/lang/String;
Asciz	canEqual;
Asciz	temp1;
Asciz	strict_$eq$eq;
Asciz	temp6;
Asciz	temp7;
Asciz	x;
Asciz	basisForHashCode;
Asciz	()Lscala/collection/Seq;;
Asciz	scala/collection/immutable/List$;
class	scala/collection/immutable/List$
Asciz	Lscala/collection/immutable/List$;;
NameAndType	MODULE$:Lscala/collection/immutable/List$;
Field	scala/collection/immutable/List$.MODULE$:Lscala/collection/immutable/List$;
Asciz	scala/Predef$;
class	scala/Predef$
Asciz	Lscala/Predef$;;
NameAndType	MODULE$:Lscala/Predef$;
Field	scala/Predef$.MODULE$:Lscala/Predef$;
Asciz	wrapRefArray;
Asciz	([Ljava/lang/Object;)Lscala/collection/mutable/WrappedArray;;
NameAndType	wrapRefArray:([Ljava/lang/Object;)Lscala/collection/mutable/WrappedArray;
Method	scala/Predef$.wrapRefArray:([Ljava/lang/Object;)Lscala/collection/mutable/WrappedArray;
Asciz	apply;
Asciz	(Lscala/collection/Seq;)Lscala/collection/immutable/List;;
NameAndType	apply:(Lscala/collection/Seq;)Lscala/collection/immutable/List;
Method	scala/collection/immutable/List$.apply:(Lscala/collection/Seq;)Lscala/collection/immutable/List;
Asciz	()Lscala/collection/Seq<Ljava/lang/Object;>;;
Asciz	Signature;
Asciz	buildString;
Asciz	(Lscala/xml/NamespaceBinding;)Ljava/lang/String;;
Asciz	scala/xml/NamespaceBinding$$anonfun$buildString$1;
class	scala/xml/NamespaceBinding$$anonfun$buildString$1
Asciz	(Lscala/xml/NamespaceBinding;Lscala/xml/NamespaceBinding;)V;
NameAndType	"<init>":(Lscala/xml/NamespaceBinding;Lscala/xml/NamespaceBinding;)V
Method	scala/xml/NamespaceBinding$$anonfun$buildString$1."<init>":(Lscala/xml/NamespaceBinding;Lscala/xml/NamespaceBinding;)V
Asciz	stop$1;
Asciz	(Lscala/collection/mutable/StringBuilder;Lscala/xml/NamespaceBinding;)V;
Asciz	 xmlns%s=\"%s\";
String	 xmlns%s=\"%s\"
Asciz	augmentString;
Asciz	(Ljava/lang/String;)Lscala/collection/immutable/StringOps;;
NameAndType	augmentString:(Ljava/lang/String;)Lscala/collection/immutable/StringOps;
Method	scala/Predef$.augmentString:(Ljava/lang/String;)Lscala/collection/immutable/StringOps;
Asciz	;
String	
Asciz	scala/collection/mutable/StringBuilder;
class	scala/collection/mutable/StringBuilder
NameAndType	"<init>":()V
Method	scala/collection/mutable/StringBuilder."<init>":()V
Asciz	:;
String	:
Asciz	append;
Asciz	(Ljava/lang/Object;)Lscala/collection/mutable/StringBuilder;;
NameAndType	append:(Ljava/lang/Object;)Lscala/collection/mutable/StringBuilder;
Method	scala/collection/mutable/StringBuilder.append:(Ljava/lang/Object;)Lscala/collection/mutable/StringBuilder;
NameAndType	toString:()Ljava/lang/String;
Method	scala/collection/mutable/StringBuilder.toString:()Ljava/lang/String;
Asciz	genericWrapArray;
Asciz	(Ljava/lang/Object;)Lscala/collection/mutable/WrappedArray;;
NameAndType	genericWrapArray:(Ljava/lang/Object;)Lscala/collection/mutable/WrappedArray;
Method	scala/Predef$.genericWrapArray:(Ljava/lang/Object;)Lscala/collection/mutable/WrappedArray;
Asciz	scala/collection/immutable/StringLike;
class	scala/collection/immutable/StringLike
Asciz	format;
Asciz	(Lscala/collection/Seq;)Ljava/lang/String;;
NameAndType	format:(Lscala/collection/Seq;)Ljava/lang/String;
InterfaceMethod	scala/collection/immutable/StringLike.format:(Lscala/collection/Seq;)Ljava/lang/String;
Asciz	(Ljava/lang/String;)Lscala/collection/mutable/StringBuilder;;
NameAndType	append:(Ljava/lang/String;)Lscala/collection/mutable/StringBuilder;
Method	scala/collection/mutable/StringBuilder.append:(Ljava/lang/String;)Lscala/collection/mutable/StringBuilder;
NameAndType	buildString:(Lscala/collection/mutable/StringBuilder;Lscala/xml/NamespaceBinding;)V
Method	scala/xml/NamespaceBinding.buildString:(Lscala/collection/mutable/StringBuilder;Lscala/xml/NamespaceBinding;)V
Asciz	sb;
Asciz	Lscala/collection/mutable/StringBuilder;;
Asciz	stop;
Asciz	s;
Asciz	copy;
Asciz	(Ljava/lang/String;Ljava/lang/String;Lscala/xml/NamespaceBinding;)Lscala/xml/NamespaceBinding;;
Asciz	(Ljava/lang/String;Ljava/lang/String;Lscala/xml/NamespaceBinding;)V;
NameAndType	"<init>":(Ljava/lang/String;Ljava/lang/String;Lscala/xml/NamespaceBinding;)V
Method	scala/xml/NamespaceBinding."<init>":(Ljava/lang/String;Ljava/lang/String;Lscala/xml/NamespaceBinding;)V
Asciz	productPrefix;
Asciz	NamespaceBinding;
String	NamespaceBinding
Asciz	productArity;
Asciz	productElement;
Asciz	(I)Ljava/lang/Object;;
Asciz	java/lang/IndexOutOfBoundsException;
class	java/lang/IndexOutOfBoundsException
Asciz	scala/runtime/BoxesRunTime;
class	scala/runtime/BoxesRunTime
Asciz	boxToInteger;
Asciz	(I)Ljava/lang/Integer;;
NameAndType	boxToInteger:(I)Ljava/lang/Integer;
Method	scala/runtime/BoxesRunTime.boxToInteger:(I)Ljava/lang/Integer;
Method	java/lang/Object.toString:()Ljava/lang/String;
Asciz	(Ljava/lang/String;)V;
NameAndType	"<init>":(Ljava/lang/String;)V
Method	java/lang/IndexOutOfBoundsException."<init>":(Ljava/lang/String;)V
Asciz	temp11;
Asciz	I;
Asciz	productElementName;
Asciz	(I)Ljava/lang/String;;
String	parent
String	uri
String	prefix
Asciz	temp12;
Method	java/lang/Object."<init>":()V
Asciz	$init$;
Asciz	(Lscala/xml/Equality;)V;
NameAndType	$init$:(Lscala/xml/Equality;)V
Method	scala/xml/Equality$class.$init$:(Lscala/xml/Equality;)V
Asciz	(Lscala/Product;)V;
NameAndType	$init$:(Lscala/Product;)V
Method	scala/Product$class.$init$:(Lscala/Product;)V
Asciz	java/lang/IllegalArgumentException;
class	java/lang/IllegalArgumentException
Asciz	zero length prefix not allowed;
String	zero length prefix not allowed
Method	java/lang/IllegalArgumentException."<init>":(Ljava/lang/String;)V
Asciz	ScalaSig;
Asciz	InnerClasses;
Asciz	$anonfun$toString$1;
Asciz	$anonfun$buildString$1;
Asciz	scala/xml/Equality;
class	scala/xml/Equality
Asciz	scala/ScalaObject;
class	scala/ScalaObject
Asciz	scala/Product;
class	scala/Product
Asciz	java/io/Serializable;
class	java/io/Serializable

{
public static final long serialVersionUID;
  Signature: J

private final scala.xml.NamespaceBinding parent;
  Signature: Lscala/xml/NamespaceBinding;

private final java.lang.String uri;
  Signature: Ljava/lang/String;

private final java.lang.String prefix;
  Signature: Ljava/lang/String;

public static {};
  Signature: ()V
  Code:
   Stack=2, Locals=0, Args_size=0
	ldc2_w	long -2518644165573446725l
	putstatic	Field serialVersionUID:J
	return
  Labels:

public scala.collection.Iterator productIterator();
  Signature: ()Lscala/collection/Iterator;
  Code:
   Stack=1, Locals=1, Args_size=1
	aload_0
	invokestatic	Method scala/Product$class.productIterator:(Lscala/Product;)Lscala/collection/Iterator;
	areturn
  Labels:

public scala.collection.Iterator productElements();
  Signature: ()Lscala/collection/Iterator;
  Code:
   Stack=1, Locals=1, Args_size=1
	aload_0
	invokestatic	Method scala/Product$class.productElements:(Lscala/Product;)Lscala/collection/Iterator;
	areturn
  Labels:
  Deprecated: true

public boolean strict_$bang$eq(scala.xml.Equality);
  Signature: (Lscala/xml/Equality;)Z
  Code:
   Stack=2, Locals=2, Args_size=2
	aload_0
	aload_1
	invokestatic	Method scala/xml/Equality$class.strict_$bang$eq:(Lscala/xml/Equality;Lscala/xml/Equality;)Z
	ireturn
  Labels:
  LocalVariableTable: 
   Start  Length  Slot  Name   Signature
   0      6      0    this       Lscala/xml/NamespaceBinding;
   0      6      1    other       Lscala/xml/Equality;


public int hashCode();
  Signature: ()I
  Code:
   Stack=1, Locals=1, Args_size=1
	aload_0
	invokestatic	Method scala/xml/Equality$class.hashCode:(Lscala/xml/Equality;)I
	ireturn
  Labels:

public boolean equals(java.lang.Object);
  Signature: (Ljava/lang/Object;)Z
  Code:
   Stack=2, Locals=2, Args_size=2
	aload_0
	aload_1
	invokestatic	Method scala/xml/Equality$class.equals:(Lscala/xml/Equality;Ljava/lang/Object;)Z
	ireturn
  Labels:
  LocalVariableTable: 
   Start  Length  Slot  Name   Signature
   0      6      0    this       Lscala/xml/NamespaceBinding;
   0      6      1    other       Ljava/lang/Object;


public final boolean xml_$eq$eq(java.lang.Object);
  Signature: (Ljava/lang/Object;)Z
  Code:
   Stack=2, Locals=2, Args_size=2
	aload_0
	aload_1
	invokestatic	Method scala/xml/Equality$class.xml_$eq$eq:(Lscala/xml/Equality;Ljava/lang/Object;)Z
	ireturn
  Labels:
  LocalVariableTable: 
   Start  Length  Slot  Name   Signature
   0      6      0    this       Lscala/xml/NamespaceBinding;
   0      6      1    other       Ljava/lang/Object;


public final boolean xml_$bang$eq(java.lang.Object);
  Signature: (Ljava/lang/Object;)Z
  Code:
   Stack=2, Locals=2, Args_size=2
	aload_0
	aload_1
	invokestatic	Method scala/xml/Equality$class.xml_$bang$eq:(Lscala/xml/Equality;Ljava/lang/Object;)Z
	ireturn
  Labels:
  LocalVariableTable: 
   Start  Length  Slot  Name   Signature
   0      6      0    this       Lscala/xml/NamespaceBinding;
   0      6      1    other       Ljava/lang/Object;


public scala.xml.NamespaceBinding copy$default$3();
  Signature: ()Lscala/xml/NamespaceBinding;
  Code:
   Stack=1, Locals=1, Args_size=1
	aload_0
	invokevirtual	Method parent:()Lscala/xml/NamespaceBinding;
	areturn
  Labels:

public java.lang.String copy$default$2();
  Signature: ()Ljava/lang/String;
  Code:
   Stack=1, Locals=1, Args_size=1
	aload_0
	invokevirtual	Method uri:()Ljava/lang/String;
	areturn
  Labels:

public java.lang.String copy$default$1();
  Signature: ()Ljava/lang/String;
  Code:
   Stack=1, Locals=1, Args_size=1
	aload_0
	invokevirtual	Method prefix:()Ljava/lang/String;
	areturn
  Labels:

public java.lang.String prefix();
  Signature: ()Ljava/lang/String;
  Code:
   Stack=1, Locals=1, Args_size=1
	aload_0
	getfield	Field prefix:Ljava/lang/String;
	areturn
  Labels:

public java.lang.String uri();
  Signature: ()Ljava/lang/String;
  Code:
   Stack=1, Locals=1, Args_size=1
	aload_0
	getfield	Field uri:Ljava/lang/String;
	areturn
  Labels:

public scala.xml.NamespaceBinding parent();
  Signature: ()Lscala/xml/NamespaceBinding;
  Code:
   Stack=1, Locals=1, Args_size=1
	aload_0
	getfield	Field parent:Lscala/xml/NamespaceBinding;
	areturn
  Labels:

public java.lang.String getURI(java.lang.String);
  Signature: (Ljava/lang/String;)Ljava/lang/String;
  Code:
   Stack=2, Locals=3, Args_size=2
	aload_0
	invokevirtual	Method prefix:()Ljava/lang/String;
	aload_1
	astore_2
	dup
	ifnonnull	l1 // aload_2
	pop
	aload_2
	ifnull	l2 // aload_0
	goto	l3 // aload_0
l1	aload_2
	invokevirtual	Method java/lang/Object.equals:(Ljava/lang/Object;)Z
	ifeq	l3 // aload_0
l2	aload_0
	invokevirtual	Method uri:()Ljava/lang/String;
	goto	l4 // areturn
l3	aload_0
	invokevirtual	Method parent:()Lscala/xml/NamespaceBinding;
	aload_1
	invokevirtual	Method getURI:(Ljava/lang/String;)Ljava/lang/String;
l4	areturn
  Labels:
   	l1 = 18 // aload_2
   	l2 = 25 // aload_0
   	l3 = 32 // aload_0
   	l4 = 40 // areturn
  LocalVariableTable: 
   Start  Length  Slot  Name   Signature
   0      41      0    this       Lscala/xml/NamespaceBinding;
   0      41      1    _prefix       Ljava/lang/String;


public java.lang.String getPrefix(java.lang.String);
  Signature: (Ljava/lang/String;)Ljava/lang/String;
  Code:
   Stack=2, Locals=3, Args_size=2
	aload_1
	aload_0
	invokevirtual	Method uri:()Ljava/lang/String;
	astore_2
	dup
	ifnonnull	l1 // aload_2
	pop
	aload_2
	ifnull	l2 // aload_0
	goto	l3 // aload_0
l1	aload_2
	invokevirtual	Method java/lang/Object.equals:(Ljava/lang/Object;)Z
	ifeq	l3 // aload_0
l2	aload_0
	invokevirtual	Method prefix:()Ljava/lang/String;
	goto	l4 // areturn
l3	aload_0
	invokevirtual	Method parent:()Lscala/xml/NamespaceBinding;
	aload_1
	invokevirtual	Method getPrefix:(Ljava/lang/String;)Ljava/lang/String;
l4	areturn
  Labels:
   	l1 = 18 // aload_2
   	l2 = 25 // aload_0
   	l3 = 32 // aload_0
   	l4 = 40 // areturn
  LocalVariableTable: 
   Start  Length  Slot  Name   Signature
   0      41      0    this       Lscala/xml/NamespaceBinding;
   0      41      1    _uri       Ljava/lang/String;


public java.lang.String toString();
  Signature: ()Ljava/lang/String;
  Code:
   Stack=4, Locals=1, Args_size=1
	getstatic	Field scala/xml/Utility$.MODULE$:Lscala/xml/Utility$;
	new	class scala/xml/NamespaceBinding$$anonfun$toString$1
	dup
	aload_0
	invokespecial	Method scala/xml/NamespaceBinding$$anonfun$toString$1."<init>":(Lscala/xml/NamespaceBinding;)V
	invokevirtual	Method scala/xml/Utility$.sbToString:(Lscala/Function1;)Ljava/lang/String;
	areturn
  Labels:

public boolean canEqual(java.lang.Object);
  Signature: (Ljava/lang/Object;)Z
  Code:
   Stack=1, Locals=3, Args_size=2
	aload_1
	astore_2
	aload_2
	instanceof	class scala/xml/NamespaceBinding
	ireturn
  Labels:
  LocalVariableTable: 
   Start  Length  Slot  Name   Signature
   0      7      0    this       Lscala/xml/NamespaceBinding;
   0      7      1    other       Ljava/lang/Object;
   2      4      2    temp1       Ljava/lang/Object;


public boolean strict_$eq$eq(scala.xml.Equality);
  Signature: (Lscala/xml/Equality;)Z
  Code:
   Stack=2, Locals=8, Args_size=2
	aload_1
	astore_2
	aload_2
	instanceof	class scala/xml/NamespaceBinding
	ifeq	l1 // iconst_0
	aload_2
	checkcast	class scala/xml/NamespaceBinding
	astore_3
	aload_3
	astore	4
	aload_0
	invokevirtual	Method prefix:()Ljava/lang/String;
	aload	4
	invokevirtual	Method prefix:()Ljava/lang/String;
	astore	5
	dup
	ifnonnull	l2 // aload
	pop
	aload	5
	ifnull	l3 // aload_0
	goto	l4 // iconst_0
l2	aload	5
	invokevirtual	Method java/lang/Object.equals:(Ljava/lang/Object;)Z
	ifeq	l4 // iconst_0
l3	aload_0
	invokevirtual	Method uri:()Ljava/lang/String;
	aload	4
	invokevirtual	Method uri:()Ljava/lang/String;
	astore	6
	dup
	ifnonnull	l5 // aload
	pop
	aload	6
	ifnull	l6 // aload_0
	goto	l4 // iconst_0
l5	aload	6
	invokevirtual	Method java/lang/Object.equals:(Ljava/lang/Object;)Z
	ifeq	l4 // iconst_0
l6	aload_0
	invokevirtual	Method parent:()Lscala/xml/NamespaceBinding;
	aload	4
	invokevirtual	Method parent:()Lscala/xml/NamespaceBinding;
	astore	7
	dup
	ifnonnull	l7 // aload
	pop
	aload	7
	ifnull	l8 // iconst_1
	goto	l4 // iconst_0
l7	aload	7
	invokevirtual	Method java/lang/Object.equals:(Ljava/lang/Object;)Z
	ifeq	l4 // iconst_0
l8	iconst_1
	goto	l9 // ireturn
l4	iconst_0
	goto	l9 // ireturn
l1	iconst_0
l9	ireturn
  Labels:
   	l2 = 41 // aload
   	l3 = 49 // aload_0
   	l5 = 73 // aload
   	l6 = 81 // aload_0
   	l7 = 105 // aload
   	l8 = 113 // iconst_1
   	l4 = 117 // iconst_0
   	l1 = 121 // iconst_0
   	l9 = 122 // ireturn
  LocalVariableTable: 
   Start  Length  Slot  Name   Signature
   0      123      0    this       Lscala/xml/NamespaceBinding;
   0      123      1    other       Lscala/xml/Equality;
   2      121      2    temp6       Lscala/xml/Equality;
   14      107      3    temp7       Lscala/xml/NamespaceBinding;
   17      104      4    x       Lscala/xml/NamespaceBinding;


public scala.collection.Seq basisForHashCode();
  Signature: ()Lscala/collection/Seq;
  Code:
   Stack=6, Locals=1, Args_size=1
	getstatic	Field scala/collection/immutable/List$.MODULE$:Lscala/collection/immutable/List$;
	getstatic	Field scala/Predef$.MODULE$:Lscala/Predef$;
	iconst_3
	anewarray	class java/lang/Object
	dup
	iconst_0
	aload_0
	invokevirtual	Method prefix:()Ljava/lang/String;
	aastore
	dup
	iconst_1
	aload_0
	invokevirtual	Method uri:()Ljava/lang/String;
	aastore
	dup
	iconst_2
	aload_0
	invokevirtual	Method parent:()Lscala/xml/NamespaceBinding;
	aastore
	invokevirtual	Method scala/Predef$.wrapRefArray:([Ljava/lang/Object;)Lscala/collection/mutable/WrappedArray;
	invokevirtual	Method scala/collection/immutable/List$.apply:(Lscala/collection/Seq;)Lscala/collection/immutable/List;
	areturn
  Labels:
  Signature: length = 0x2
   00 FFFFFF84 

public java.lang.String buildString(scala.xml.NamespaceBinding);
  Signature: (Lscala/xml/NamespaceBinding;)Ljava/lang/String;
  Code:
   Stack=5, Locals=2, Args_size=2
	getstatic	Field scala/xml/Utility$.MODULE$:Lscala/xml/Utility$;
	new	class scala/xml/NamespaceBinding$$anonfun$buildString$1
	dup
	aload_0
	aload_1
	invokespecial	Method scala/xml/NamespaceBinding$$anonfun$buildString$1."<init>":(Lscala/xml/NamespaceBinding;Lscala/xml/NamespaceBinding;)V
	invokevirtual	Method scala/xml/Utility$.sbToString:(Lscala/Function1;)Ljava/lang/String;
	areturn
  Labels:
  LocalVariableTable: 
   Start  Length  Slot  Name   Signature
   0      16      0    this       Lscala/xml/NamespaceBinding;
   0      16      1    stop$1       Lscala/xml/NamespaceBinding;


public void buildString(scala.collection.mutable.StringBuilder, scala.xml.NamespaceBinding);
  Signature: (Lscala/collection/mutable/StringBuilder;Lscala/xml/NamespaceBinding;)V
  Code:
   Stack=7, Locals=6, Args_size=3
	aload_0
	aload_2
	if_acmpne	l1 // getstatic
	return
l1	getstatic	Field scala/Predef$.MODULE$:Lscala/Predef$;
	ldc	String  xmlns%s=\"%s\"
	invokevirtual	Method scala/Predef$.augmentString:(Ljava/lang/String;)Lscala/collection/immutable/StringOps;
	getstatic	Field scala/Predef$.MODULE$:Lscala/Predef$;
	iconst_2
	anewarray	class java/lang/Object
	dup
	iconst_0
	aload_0
	invokevirtual	Method prefix:()Ljava/lang/String;
	dup
	astore	4
	ifnull	l2 // ldc
	aload	4
	aconst_null
	invokevirtual	Method java/lang/Object.equals:(Ljava/lang/Object;)Z
	ifeq	l3 // new
l2	ldc	String 
	goto	l4 // aastore
l3	new	class scala/collection/mutable/StringBuilder
	dup
	invokespecial	Method scala/collection/mutable/StringBuilder."<init>":()V
	ldc	String :
	invokevirtual	Method scala/collection/mutable/StringBuilder.append:(Ljava/lang/Object;)Lscala/collection/mutable/StringBuilder;
	aload_0
	invokevirtual	Method prefix:()Ljava/lang/String;
	invokevirtual	Method scala/collection/mutable/StringBuilder.append:(Ljava/lang/Object;)Lscala/collection/mutable/StringBuilder;
	invokevirtual	Method scala/collection/mutable/StringBuilder.toString:()Ljava/lang/String;
l4	aastore
	dup
	iconst_1
	aload_0
	invokevirtual	Method uri:()Ljava/lang/String;
	dup
	astore	5
	ifnull	l5 // ldc
	aload	5
	aconst_null
	invokevirtual	Method java/lang/Object.equals:(Ljava/lang/Object;)Z
	ifeq	l6 // aload_0
l5	ldc	String 
	goto	l7 // aastore
l6	aload_0
	invokevirtual	Method uri:()Ljava/lang/String;
l7	aastore
	invokevirtual	Method scala/Predef$.genericWrapArray:(Ljava/lang/Object;)Lscala/collection/mutable/WrappedArray;
	invokeinterface	InterfaceMethod scala/collection/immutable/StringLike.format:(Lscala/collection/Seq;)Ljava/lang/String;
	astore_3
	aload_0
	invokevirtual	Method parent:()Lscala/xml/NamespaceBinding;
	aload_1
	aload_3
	invokevirtual	Method scala/collection/mutable/StringBuilder.append:(Ljava/lang/String;)Lscala/collection/mutable/StringBuilder;
	aload_2
	invokevirtual	Method buildString:(Lscala/collection/mutable/StringBuilder;Lscala/xml/NamespaceBinding;)V
	return
  Labels:
   	l1 = 6 // getstatic
   	l2 = 42 // ldc
   	l3 = 47 // new
   	l4 = 69 // aastore
   	l5 = 91 // ldc
   	l6 = 96 // aload_0
   	l7 = 100 // aastore
  LocalVariableTable: 
   Start  Length  Slot  Name   Signature
   0      124      0    this       Lscala/xml/NamespaceBinding;
   0      124      1    sb       Lscala/collection/mutable/StringBuilder;
   0      124      2    stop       Lscala/xml/NamespaceBinding;
   110      13      3    s       Ljava/lang/String;


public scala.xml.NamespaceBinding copy(java.lang.String, java.lang.String, scala.xml.NamespaceBinding);
  Signature: (Ljava/lang/String;Ljava/lang/String;Lscala/xml/NamespaceBinding;)Lscala/xml/NamespaceBinding;
  Code:
   Stack=5, Locals=4, Args_size=4
	new	class scala/xml/NamespaceBinding
	dup
	aload_1
	aload_2
	aload_3
	invokespecial	Method "<init>":(Ljava/lang/String;Ljava/lang/String;Lscala/xml/NamespaceBinding;)V
	areturn
  Labels:
  LocalVariableTable: 
   Start  Length  Slot  Name   Signature
   0      11      0    this       Lscala/xml/NamespaceBinding;
   0      11      1    prefix       Ljava/lang/String;
   0      11      2    uri       Ljava/lang/String;
   0      11      3    parent       Lscala/xml/NamespaceBinding;


public java.lang.String productPrefix();
  Signature: ()Ljava/lang/String;
  Code:
   Stack=1, Locals=1, Args_size=1
	ldc	String NamespaceBinding
	areturn
  Labels:

public int productArity();
  Signature: ()I
  Code:
   Stack=1, Locals=1, Args_size=1
	iconst_3
	ireturn
  Labels:

public java.lang.Object productElement(int);
  Signature: (I)Ljava/lang/Object;
  Code:
   Stack=3, Locals=3, Args_size=2
	iload_1
	istore_2
	iload_2
	tableswitch{ //0 to 2
		0: 57;
		1: 50;
		2: 43;
		default: 28 }
	new	class java/lang/IndexOutOfBoundsException
	dup
	iload_1
	invokestatic	Method scala/runtime/BoxesRunTime.boxToInteger:(I)Ljava/lang/Integer;
	invokevirtual	Method java/lang/Object.toString:()Ljava/lang/String;
	invokespecial	Method java/lang/IndexOutOfBoundsException."<init>":(Ljava/lang/String;)V
	athrow
	aload_0
	invokevirtual	Method parent:()Lscala/xml/NamespaceBinding;
	goto	l1 // areturn
	aload_0
	invokevirtual	Method uri:()Ljava/lang/String;
	goto	l1 // areturn
	aload_0
	invokevirtual	Method prefix:()Ljava/lang/String;
l1	areturn
  Labels:
   	l1 = 61 // areturn
  LocalVariableTable: 
   Start  Length  Slot  Name   Signature
   0      62      0    this       Lscala/xml/NamespaceBinding;
   2      60      2    temp11       I


public java.lang.String productElementName(int);
  Signature: (I)Ljava/lang/String;
  Code:
   Stack=3, Locals=3, Args_size=2
	iload_1
	istore_2
	iload_2
	tableswitch{ //0 to 2
		0: 53;
		1: 48;
		2: 43;
		default: 28 }
	new	class java/lang/IndexOutOfBoundsException
	dup
	iload_1
	invokestatic	Method scala/runtime/BoxesRunTime.boxToInteger:(I)Ljava/lang/Integer;
	invokevirtual	Method java/lang/Object.toString:()Ljava/lang/String;
	invokespecial	Method java/lang/IndexOutOfBoundsException."<init>":(Ljava/lang/String;)V
	athrow
	ldc	String parent
	goto	l1 // areturn
	ldc	String uri
	goto	l1 // areturn
	ldc	String prefix
l1	areturn
  Labels:
   	l1 = 55 // areturn
  LocalVariableTable: 
   Start  Length  Slot  Name   Signature
   0      56      0    this       Lscala/xml/NamespaceBinding;
   2      54      2    temp12       I


public scala.xml.NamespaceBinding(java.lang.String, java.lang.String, scala.xml.NamespaceBinding);
  Signature: (Ljava/lang/String;Ljava/lang/String;Lscala/xml/NamespaceBinding;)V
  Code:
   Stack=3, Locals=5, Args_size=4
	aload_0
	aload_1
	putfield	Field prefix:Ljava/lang/String;
	aload_0
	aload_2
	putfield	Field uri:Ljava/lang/String;
	aload_0
	aload_3
	putfield	Field parent:Lscala/xml/NamespaceBinding;
	aload_0
	invokespecial	Method java/lang/Object."<init>":()V
	aload_0
	invokestatic	Method scala/xml/Equality$class.$init$:(Lscala/xml/Equality;)V
	aload_0
	invokestatic	Method scala/Product$class.$init$:(Lscala/Product;)V
	aload_1
	ldc	String 
	astore	4
	dup
	ifnonnull	l1 // aload
	pop
	aload	4
	ifnull	l2 // new
	goto	l3 // return
l1	aload	4
	invokevirtual	Method java/lang/Object.equals:(Ljava/lang/Object;)Z
	ifeq	l3 // return
l2	new	class java/lang/IllegalArgumentException
	dup
	ldc	String zero length prefix not allowed
	invokespecial	Method java/lang/IllegalArgumentException."<init>":(Ljava/lang/String;)V
	athrow
l3	return
  Labels:
   	l1 = 45 // aload
   	l2 = 53 // new
   	l3 = 63 // return
  LocalVariableTable: 
   Start  Length  Slot  Name   Signature
   0      64      0    this       Lscala/xml/NamespaceBinding;
   0      64      1    prefix       Ljava/lang/String;
   0      64      2    uri       Ljava/lang/String;
   0      64      3    parent       Lscala/xml/NamespaceBinding;


}

