Compiled from "NamespaceBinding.scala"
public final class scala.xml.NamespaceBinding$ extends java.lang.Object implements scala.Function3,scala.ScalaObject
  SourceFile: "NamespaceBinding.scala"
  Scala: length = 0x
   
  InnerClass: 
   public final $anonfun$toString$1=class scala/xml/NamespaceBinding$$anonfun$toString$1 of class scala/xml/NamespaceBinding
   public final $anonfun$buildString$1=class scala/xml/NamespaceBinding$$anonfun$buildString$1 of class scala/xml/NamespaceBinding
  minor version: 0
  major version: 49
  Constant pool:
Asciz	SourceFile;
Asciz	NamespaceBinding.scala;
Asciz	Scala;
Asciz	MODULE$;
Asciz	Lscala/xml/NamespaceBinding$;;
Asciz	<clinit>;
Asciz	()V;
Asciz	Code;
Asciz	scala/xml/NamespaceBinding$;
class	scala/xml/NamespaceBinding$
Asciz	<init>;
NameAndType	"<init>":()V
Method	scala/xml/NamespaceBinding$."<init>":()V
Asciz	toString;
Asciz	()Ljava/lang/String;;
Asciz	LineNumberTable;
Asciz	scala/Function3$class;
class	scala/Function3$class
Asciz	(Lscala/Function3;)Ljava/lang/String;;
NameAndType	toString:(Lscala/Function3;)Ljava/lang/String;
Method	scala/Function3$class.toString:(Lscala/Function3;)Ljava/lang/String;
Asciz	curried;
Asciz	()Lscala/Function1;;
Asciz	(Lscala/Function3;)Lscala/Function1;;
NameAndType	curried:(Lscala/Function3;)Lscala/Function1;
Method	scala/Function3$class.curried:(Lscala/Function3;)Lscala/Function1;
Asciz	curry;
NameAndType	curry:(Lscala/Function3;)Lscala/Function1;
Method	scala/Function3$class.curry:(Lscala/Function3;)Lscala/Function1;
Asciz	Deprecated;
Asciz	tupled;
NameAndType	tupled:(Lscala/Function3;)Lscala/Function1;
Method	scala/Function3$class.tupled:(Lscala/Function3;)Lscala/Function1;
Asciz	unapply;
Asciz	(Lscala/xml/NamespaceBinding;)Lscala/Option;;
Asciz	java/lang/Object;
class	java/lang/Object
Asciz	equals;
Asciz	(Ljava/lang/Object;)Z;
NameAndType	equals:(Ljava/lang/Object;)Z
Method	java/lang/Object.equals:(Ljava/lang/Object;)Z
Asciz	scala/None$;
class	scala/None$
Asciz	Lscala/None$;;
NameAndType	MODULE$:Lscala/None$;
Field	scala/None$.MODULE$:Lscala/None$;
Asciz	scala/Some;
class	scala/Some
Asciz	scala/Tuple3;
class	scala/Tuple3
Asciz	scala/xml/NamespaceBinding;
class	scala/xml/NamespaceBinding
Asciz	prefix;
NameAndType	prefix:()Ljava/lang/String;
Method	scala/xml/NamespaceBinding.prefix:()Ljava/lang/String;
Asciz	uri;
NameAndType	uri:()Ljava/lang/String;
Method	scala/xml/NamespaceBinding.uri:()Ljava/lang/String;
Asciz	parent;
Asciz	()Lscala/xml/NamespaceBinding;;
NameAndType	parent:()Lscala/xml/NamespaceBinding;
Method	scala/xml/NamespaceBinding.parent:()Lscala/xml/NamespaceBinding;
Asciz	(Ljava/lang/Object;Ljava/lang/Object;Ljava/lang/Object;)V;
NameAndType	"<init>":(Ljava/lang/Object;Ljava/lang/Object;Ljava/lang/Object;)V
Method	scala/Tuple3."<init>":(Ljava/lang/Object;Ljava/lang/Object;Ljava/lang/Object;)V
Asciz	(Ljava/lang/Object;)V;
NameAndType	"<init>":(Ljava/lang/Object;)V
Method	scala/Some."<init>":(Ljava/lang/Object;)V
Asciz	this;
Asciz	x$0;
Asciz	Lscala/xml/NamespaceBinding;;
Asciz	LocalVariableTable;
Asciz	apply;
Asciz	(Ljava/lang/String;Ljava/lang/String;Lscala/xml/NamespaceBinding;)Lscala/xml/NamespaceBinding;;
Asciz	(Ljava/lang/String;Ljava/lang/String;Lscala/xml/NamespaceBinding;)V;
NameAndType	"<init>":(Ljava/lang/String;Ljava/lang/String;Lscala/xml/NamespaceBinding;)V
Method	scala/xml/NamespaceBinding."<init>":(Ljava/lang/String;Ljava/lang/String;Lscala/xml/NamespaceBinding;)V
Asciz	Ljava/lang/String;;
Asciz	(Ljava/lang/Object;Ljava/lang/Object;Ljava/lang/Object;)Ljava/lang/Object;;
Asciz	java/lang/String;
class	java/lang/String
NameAndType	apply:(Ljava/lang/String;Ljava/lang/String;Lscala/xml/NamespaceBinding;)Lscala/xml/NamespaceBinding;
Method	scala/xml/NamespaceBinding$.apply:(Ljava/lang/String;Ljava/lang/String;Lscala/xml/NamespaceBinding;)Lscala/xml/NamespaceBinding;
Asciz	v1;
Asciz	Ljava/lang/Object;;
Asciz	v2;
Asciz	v3;
Method	java/lang/Object."<init>":()V
NameAndType	MODULE$:Lscala/xml/NamespaceBinding$;
Field	scala/xml/NamespaceBinding$.MODULE$:Lscala/xml/NamespaceBinding$;
Asciz	$init$;
Asciz	(Lscala/Function3;)V;
NameAndType	$init$:(Lscala/Function3;)V
Method	scala/Function3$class.$init$:(Lscala/Function3;)V
Asciz	InnerClasses;
Asciz	scala/xml/NamespaceBinding$$anonfun$toString$1;
class	scala/xml/NamespaceBinding$$anonfun$toString$1
Asciz	$anonfun$toString$1;
Asciz	scala/xml/NamespaceBinding$$anonfun$buildString$1;
class	scala/xml/NamespaceBinding$$anonfun$buildString$1
Asciz	$anonfun$buildString$1;
Asciz	scala/Function3;
class	scala/Function3
Asciz	scala/ScalaObject;
class	scala/ScalaObject

{
public static final scala.xml.NamespaceBinding$ MODULE$;
  Signature: Lscala/xml/NamespaceBinding$;

public static {};
  Signature: ()V
  Code:
   Stack=1, Locals=0, Args_size=0
	new	class scala/xml/NamespaceBinding$
	invokespecial	Method "<init>":()V
	return
  Labels:

public java.lang.String toString();
  Signature: ()Ljava/lang/String;
  Code:
   Stack=1, Locals=1, Args_size=1
	aload_0
	invokestatic	Method scala/Function3$class.toString:(Lscala/Function3;)Ljava/lang/String;
	areturn
  Labels:

public scala.Function1 curried();
  Signature: ()Lscala/Function1;
  Code:
   Stack=1, Locals=1, Args_size=1
	aload_0
	invokestatic	Method scala/Function3$class.curried:(Lscala/Function3;)Lscala/Function1;
	areturn
  Labels:

public scala.Function1 curry();
  Signature: ()Lscala/Function1;
  Code:
   Stack=1, Locals=1, Args_size=1
	aload_0
	invokestatic	Method scala/Function3$class.curry:(Lscala/Function3;)Lscala/Function1;
	areturn
  Labels:
  Deprecated: true

public scala.Function1 tupled();
  Signature: ()Lscala/Function1;
  Code:
   Stack=1, Locals=1, Args_size=1
	aload_0
	invokestatic	Method scala/Function3$class.tupled:(Lscala/Function3;)Lscala/Function1;
	areturn
  Labels:

public scala.Option unapply(scala.xml.NamespaceBinding);
  Signature: (Lscala/xml/NamespaceBinding;)Lscala/Option;
  Code:
   Stack=7, Locals=3, Args_size=2
	aload_1
	dup
	astore_2
	ifnull	l1 // getstatic
	aload_2
	aconst_null
	invokevirtual	Method java/lang/Object.equals:(Ljava/lang/Object;)Z
	ifeq	l2 // new
l1	getstatic	Field scala/None$.MODULE$:Lscala/None$;
	goto	l3 // areturn
l2	new	class scala/Some
	dup
	new	class scala/Tuple3
	dup
	aload_1
	invokevirtual	Method scala/xml/NamespaceBinding.prefix:()Ljava/lang/String;
	aload_1
	invokevirtual	Method scala/xml/NamespaceBinding.uri:()Ljava/lang/String;
	aload_1
	invokevirtual	Method scala/xml/NamespaceBinding.parent:()Lscala/xml/NamespaceBinding;
	invokespecial	Method scala/Tuple3."<init>":(Ljava/lang/Object;Ljava/lang/Object;Ljava/lang/Object;)V
	invokespecial	Method scala/Some."<init>":(Ljava/lang/Object;)V
l3	areturn
  Labels:
   	l1 = 14 // getstatic
   	l2 = 20 // new
   	l3 = 46 // areturn
  LocalVariableTable: 
   Start  Length  Slot  Name   Signature
   0      47      0    this       Lscala/xml/NamespaceBinding$;
   0      47      1    x$0       Lscala/xml/NamespaceBinding;


public scala.xml.NamespaceBinding apply(java.lang.String, java.lang.String, scala.xml.NamespaceBinding);
  Signature: (Ljava/lang/String;Ljava/lang/String;Lscala/xml/NamespaceBinding;)Lscala/xml/NamespaceBinding;
  Code:
   Stack=5, Locals=4, Args_size=4
	new	class scala/xml/NamespaceBinding
	dup
	aload_1
	aload_2
	aload_3
	invokespecial	Method scala/xml/NamespaceBinding."<init>":(Ljava/lang/String;Ljava/lang/String;Lscala/xml/NamespaceBinding;)V
	areturn
  Labels:
  LocalVariableTable: 
   Start  Length  Slot  Name   Signature
   0      11      0    this       Lscala/xml/NamespaceBinding$;
   0      11      1    prefix       Ljava/lang/String;
   0      11      2    uri       Ljava/lang/String;
   0      11      3    parent       Lscala/xml/NamespaceBinding;


public java.lang.Object apply(java.lang.Object, java.lang.Object, java.lang.Object);
  Signature: (Ljava/lang/Object;Ljava/lang/Object;Ljava/lang/Object;)Ljava/lang/Object;
  Code:
   Stack=4, Locals=4, Args_size=4
	aload_0
	aload_1
	checkcast	class java/lang/String
	aload_2
	checkcast	class java/lang/String
	aload_3
	checkcast	class scala/xml/NamespaceBinding
	invokevirtual	Method apply:(Ljava/lang/String;Ljava/lang/String;Lscala/xml/NamespaceBinding;)Lscala/xml/NamespaceBinding;
	areturn
  Labels:
  LocalVariableTable: 
   Start  Length  Slot  Name   Signature
   0      17      0    this       Lscala/xml/NamespaceBinding$;
   0      17      1    v1       Ljava/lang/Object;
   0      17      2    v2       Ljava/lang/Object;
   0      17      3    v3       Ljava/lang/Object;


private scala.xml.NamespaceBinding$();
  Signature: ()V
  Code:
   Stack=1, Locals=1, Args_size=1
	aload_0
	invokespecial	Method java/lang/Object."<init>":()V
	aload_0
	putstatic	Field MODULE$:Lscala/xml/NamespaceBinding$;
	aload_0
	invokestatic	Method scala/Function3$class.$init$:(Lscala/Function3;)V
	return
  Labels:

}

