Compiled from "Node.scala"
public final class scala.xml.Node$$anonfun$nonEmptyChildren$1 extends scala.runtime.AbstractFunction1 implements java.io.Serializable
  InnerClass: 
   public final $anonfun$nonEmptyChildren$1=class scala/xml/Node$$anonfun$nonEmptyChildren$1 of class scala/xml/Node
  Scala: length = 0x
   
  SourceFile: "Node.scala"
  minor version: 0
  major version: 49
  Constant pool:
String	
class	java/io/Serializable
class	java/lang/Object
class	scala/runtime/AbstractFunction1
class	scala/runtime/BoxesRunTime
class	scala/xml/Node
class	scala/xml/Node$$anonfun$nonEmptyChildren$1
Field	scala/xml/Node$$anonfun$nonEmptyChildren$1.serialVersionUID:J
Method	java/lang/Object.equals:(Ljava/lang/Object;)Z
Method	scala/runtime/AbstractFunction1."<init>":()V
Method	scala/runtime/BoxesRunTime.boxToBoolean:(Z)Ljava/lang/Boolean;
Method	scala/xml/Node.toString:()Ljava/lang/String;
Method	scala/xml/Node$$anonfun$nonEmptyChildren$1.apply:(Lscala/xml/Node;)Z
NameAndType	"<init>":()V
NameAndType	apply:(Lscala/xml/Node;)Z
NameAndType	boxToBoolean:(Z)Ljava/lang/Boolean;
NameAndType	equals:(Ljava/lang/Object;)Z
NameAndType	serialVersionUID:J
NameAndType	toString:()Ljava/lang/String;
Asciz	;
Asciz	$anonfun$nonEmptyChildren$1;
Asciz	$outer;
Asciz	()Ljava/lang/String;;
Asciz	()V;
Asciz	(Ljava/lang/Object;)Ljava/lang/Object;;
Asciz	(Ljava/lang/Object;)Z;
Asciz	(Lscala/xml/Node;)V;
Asciz	(Lscala/xml/Node;)Z;
Asciz	(Z)Ljava/lang/Boolean;;
Asciz	<clinit>;
Asciz	<init>;
Asciz	Code;
Asciz	InnerClasses;
Asciz	J;
Asciz	LineNumberTable;
Asciz	Ljava/lang/Object;;
Asciz	LocalVariableTable;
Asciz	Lscala/xml/Node$$anonfun$nonEmptyChildren$1;;
Asciz	Lscala/xml/Node;;
Asciz	Node.scala;
Asciz	Scala;
Asciz	SourceFile;
Asciz	apply;
Asciz	boxToBoolean;
Asciz	equals;
Asciz	java/io/Serializable;
Asciz	java/lang/Object;
Asciz	scala/runtime/AbstractFunction1;
Asciz	scala/runtime/BoxesRunTime;
Asciz	scala/xml/Node;
Asciz	scala/xml/Node$$anonfun$nonEmptyChildren$1;
Asciz	serialVersionUID;
Asciz	this;
Asciz	toString;
Asciz	v1;

{
public static final long serialVersionUID;
  Signature: J

public static {};
  Signature: ()V
  Code:
   Stack=2, Locals=0, Args_size=0
	lconst_0
	putstatic	Field serialVersionUID:J
	return
  Labels:

public final boolean apply(scala.xml.Node);
  Signature: (Lscala/xml/Node;)Z
  Code:
   Stack=2, Locals=3, Args_size=2
	aload_1
	invokevirtual	Method scala/xml/Node.toString:()Ljava/lang/String;
	ldc	String 
	astore_2
	dup
	ifnonnull	l1 // aload_2
	pop
	aload_2
	ifnull	l2 // iconst_1
	goto	l3 // iconst_0
l1	aload_2
	invokevirtual	Method java/lang/Object.equals:(Ljava/lang/Object;)Z
	ifeq	l3 // iconst_0
l2	iconst_1
	goto	l4 // ireturn
l3	iconst_0
l4	ireturn
  Labels:
   	l1 = 19 // aload_2
   	l2 = 26 // iconst_1
   	l3 = 30 // iconst_0
   	l4 = 31 // ireturn

public final java.lang.Object apply(java.lang.Object);
  Signature: (Ljava/lang/Object;)Ljava/lang/Object;
  Code:
   Stack=2, Locals=3, Args_size=2
	aload_0
	aload_1
	checkcast	class scala/xml/Node
	invokevirtual	Method apply:(Lscala/xml/Node;)Z
	istore_2
	iload_2
	invokestatic	Method scala/runtime/BoxesRunTime.boxToBoolean:(Z)Ljava/lang/Boolean;
	areturn
  Labels:
  LocalVariableTable: 
   Start  Length  Slot  Name   Signature
   0      14      0    this       Lscala/xml/Node$$anonfun$nonEmptyChildren$1;
   0      14      1    v1       Ljava/lang/Object;


public scala.xml.Node$$anonfun$nonEmptyChildren$1(scala.xml.Node);
  Signature: (Lscala/xml/Node;)V
  Code:
   Stack=1, Locals=2, Args_size=2
	aload_0
	invokespecial	Method scala/runtime/AbstractFunction1."<init>":()V
	return
  Labels:
  LocalVariableTable: 
   Start  Length  Slot  Name   Signature
   0      5      0    this       Lscala/xml/Node$$anonfun$nonEmptyChildren$1;
   0      5      1    $outer       Lscala/xml/Node;


}

