Compiled from "NodeSeq.scala"
public final class scala.xml.NodeSeq$ extends java.lang.Object implements scala.ScalaObject
  SourceFile: "NodeSeq.scala"
  Scala: length = 0x
   
  InnerClass: 
   public final $anon$1=class scala/xml/NodeSeq$$anon$1 of class scala/xml/NodeSeq
   public final $anon$2=class scala/xml/NodeSeq$$anon$2 of class scala/xml/NodeSeq
   public final $anonfun$text$1=class scala/xml/NodeSeq$$anonfun$text$1 of class scala/xml/NodeSeq
   public final $anonfun$filt$1$1=class scala/xml/NodeSeq$$anonfun$filt$1$1 of class scala/xml/NodeSeq
   public final $anonfun$$bslash$2=class scala/xml/NodeSeq$$anonfun$$bslash$2 of class scala/xml/NodeSeq
   public final $anonfun$$bslash$1=class scala/xml/NodeSeq$$anonfun$$bslash$1 of class scala/xml/NodeSeq
   public final $anonfun$makeSeq$1$1=class scala/xml/NodeSeq$$anonfun$makeSeq$1$1 of class scala/xml/NodeSeq
   public final $anonfun$newBuilder$1=class scala/xml/NodeSeq$$anonfun$newBuilder$1 of class scala/xml/NodeSeq
   public final $anonfun$$bslash$bslash$4=class scala/xml/NodeSeq$$anonfun$$bslash$bslash$4 of class scala/xml/NodeSeq
   public final $anonfun$$bslash$bslash$3=class scala/xml/NodeSeq$$anonfun$$bslash$bslash$3 of class scala/xml/NodeSeq
   public final $anonfun$$bslash$bslash$2=class scala/xml/NodeSeq$$anonfun$$bslash$bslash$2 of class scala/xml/NodeSeq
   public final $anonfun$$bslash$bslash$1=class scala/xml/NodeSeq$$anonfun$$bslash$bslash$1 of class scala/xml/NodeSeq
  minor version: 0
  major version: 49
  Constant pool:
Asciz	SourceFile;
Asciz	NodeSeq.scala;
Asciz	Scala;
Asciz	MODULE$;
Asciz	Lscala/xml/NodeSeq$;;
Asciz	<clinit>;
Asciz	()V;
Asciz	Code;
Asciz	scala/xml/NodeSeq$;
class	scala/xml/NodeSeq$
Asciz	<init>;
NameAndType	"<init>":()V
Method	scala/xml/NodeSeq$."<init>":()V
Asciz	Empty;
Asciz	Lscala/xml/NodeSeq;;
Asciz	LineNumberTable;
Asciz	java/lang/Object;
class	java/lang/Object
Method	java/lang/Object."<init>":()V
NameAndType	MODULE$:Lscala/xml/NodeSeq$;
Field	scala/xml/NodeSeq$.MODULE$:Lscala/xml/NodeSeq$;
Asciz	scala/collection/immutable/Nil$;
class	scala/collection/immutable/Nil$
Asciz	Lscala/collection/immutable/Nil$;;
NameAndType	MODULE$:Lscala/collection/immutable/Nil$;
Field	scala/collection/immutable/Nil$.MODULE$:Lscala/collection/immutable/Nil$;
Asciz	fromSeq;
Asciz	(Lscala/collection/Seq;)Lscala/xml/NodeSeq;;
NameAndType	fromSeq:(Lscala/collection/Seq;)Lscala/xml/NodeSeq;
Method	scala/xml/NodeSeq$.fromSeq:(Lscala/collection/Seq;)Lscala/xml/NodeSeq;
NameAndType	Empty:Lscala/xml/NodeSeq;
Field	scala/xml/NodeSeq$.Empty:Lscala/xml/NodeSeq;
Asciz	seqToNodeSeq;
Asciz	this;
Asciz	s;
Asciz	Lscala/collection/Seq;;
Asciz	LocalVariableTable;
Asciz	(Lscala/collection/Seq<Lscala/xml/Node;>;)Lscala/xml/NodeSeq;;
Asciz	Signature;
Asciz	newBuilder;
Asciz	()Lscala/collection/mutable/Builder;;
Asciz	scala/collection/mutable/ListBuffer;
class	scala/collection/mutable/ListBuffer
Method	scala/collection/mutable/ListBuffer."<init>":()V
Asciz	scala/xml/NodeSeq$$anonfun$newBuilder$1;
class	scala/xml/NodeSeq$$anonfun$newBuilder$1
Method	scala/xml/NodeSeq$$anonfun$newBuilder$1."<init>":()V
Asciz	scala/collection/mutable/Builder;
class	scala/collection/mutable/Builder
Asciz	mapResult;
Asciz	(Lscala/Function1;)Lscala/collection/mutable/Builder;;
NameAndType	mapResult:(Lscala/Function1;)Lscala/collection/mutable/Builder;
InterfaceMethod	scala/collection/mutable/Builder.mapResult:(Lscala/Function1;)Lscala/collection/mutable/Builder;
Asciz	()Lscala/collection/mutable/Builder<Lscala/xml/Node;Lscala/xml/NodeSeq;>;;
Asciz	canBuildFrom;
Asciz	()Lscala/collection/generic/CanBuildFrom;;
Asciz	scala/xml/NodeSeq$$anon$2;
class	scala/xml/NodeSeq$$anon$2
Method	scala/xml/NodeSeq$$anon$2."<init>":()V
Asciz	()Lscala/collection/generic/CanBuildFrom<Lscala/xml/NodeSeq;Lscala/xml/Node;Lscala/xml/NodeSeq;>;;
Asciz	scala/xml/NodeSeq$$anon$1;
class	scala/xml/NodeSeq$$anon$1
Asciz	(Lscala/collection/Seq;)V;
NameAndType	"<init>":(Lscala/collection/Seq;)V
Method	scala/xml/NodeSeq$$anon$1."<init>":(Lscala/collection/Seq;)V
Asciz	s$1;
Asciz	()Lscala/xml/NodeSeq;;
Asciz	InnerClasses;
Asciz	scala/xml/NodeSeq;
class	scala/xml/NodeSeq
Asciz	$anon$1;
Asciz	$anon$2;
Asciz	scala/xml/NodeSeq$$anonfun$text$1;
class	scala/xml/NodeSeq$$anonfun$text$1
Asciz	$anonfun$text$1;
Asciz	scala/xml/NodeSeq$$anonfun$filt$1$1;
class	scala/xml/NodeSeq$$anonfun$filt$1$1
Asciz	$anonfun$filt$1$1;
Asciz	scala/xml/NodeSeq$$anonfun$$bslash$2;
class	scala/xml/NodeSeq$$anonfun$$bslash$2
Asciz	$anonfun$$bslash$2;
Asciz	scala/xml/NodeSeq$$anonfun$$bslash$1;
class	scala/xml/NodeSeq$$anonfun$$bslash$1
Asciz	$anonfun$$bslash$1;
Asciz	scala/xml/NodeSeq$$anonfun$makeSeq$1$1;
class	scala/xml/NodeSeq$$anonfun$makeSeq$1$1
Asciz	$anonfun$makeSeq$1$1;
Asciz	$anonfun$newBuilder$1;
Asciz	scala/xml/NodeSeq$$anonfun$$bslash$bslash$4;
class	scala/xml/NodeSeq$$anonfun$$bslash$bslash$4
Asciz	$anonfun$$bslash$bslash$4;
Asciz	scala/xml/NodeSeq$$anonfun$$bslash$bslash$3;
class	scala/xml/NodeSeq$$anonfun$$bslash$bslash$3
Asciz	$anonfun$$bslash$bslash$3;
Asciz	scala/xml/NodeSeq$$anonfun$$bslash$bslash$2;
class	scala/xml/NodeSeq$$anonfun$$bslash$bslash$2
Asciz	$anonfun$$bslash$bslash$2;
Asciz	scala/xml/NodeSeq$$anonfun$$bslash$bslash$1;
class	scala/xml/NodeSeq$$anonfun$$bslash$bslash$1
Asciz	$anonfun$$bslash$bslash$1;
Asciz	scala/ScalaObject;
class	scala/ScalaObject

{
public static final scala.xml.NodeSeq$ MODULE$;
  Signature: Lscala/xml/NodeSeq$;

private final scala.xml.NodeSeq Empty;
  Signature: Lscala/xml/NodeSeq;

public static {};
  Signature: ()V
  Code:
   Stack=1, Locals=0, Args_size=0
	new	class scala/xml/NodeSeq$
	invokespecial	Method "<init>":()V
	return
  Labels:

private scala.xml.NodeSeq$();
  Signature: ()V
  Code:
   Stack=3, Locals=1, Args_size=1
	aload_0
	invokespecial	Method java/lang/Object."<init>":()V
	aload_0
	putstatic	Field MODULE$:Lscala/xml/NodeSeq$;
	aload_0
	aload_0
	getstatic	Field scala/collection/immutable/Nil$.MODULE$:Lscala/collection/immutable/Nil$;
	invokevirtual	Method fromSeq:(Lscala/collection/Seq;)Lscala/xml/NodeSeq;
	putfield	Field Empty:Lscala/xml/NodeSeq;
	return
  Labels:

public scala.xml.NodeSeq seqToNodeSeq(scala.collection.Seq);
  Signature: (Lscala/collection/Seq;)Lscala/xml/NodeSeq;
  Code:
   Stack=2, Locals=2, Args_size=2
	aload_0
	aload_1
	invokevirtual	Method fromSeq:(Lscala/collection/Seq;)Lscala/xml/NodeSeq;
	areturn
  Labels:
  LocalVariableTable: 
   Start  Length  Slot  Name   Signature
   0      6      0    this       Lscala/xml/NodeSeq$;
   0      6      1    s       Lscala/collection/Seq;

  Signature: length = 0x2
   00 26 

public scala.collection.mutable.Builder newBuilder();
  Signature: ()Lscala/collection/mutable/Builder;
  Code:
   Stack=3, Locals=1, Args_size=1
	new	class scala/collection/mutable/ListBuffer
	dup
	invokespecial	Method scala/collection/mutable/ListBuffer."<init>":()V
	new	class scala/xml/NodeSeq$$anonfun$newBuilder$1
	dup
	invokespecial	Method scala/xml/NodeSeq$$anonfun$newBuilder$1."<init>":()V
	invokeinterface	InterfaceMethod scala/collection/mutable/Builder.mapResult:(Lscala/Function1;)Lscala/collection/mutable/Builder;
	areturn
  Labels:
  Signature: length = 0x2
   00 36 

public scala.collection.generic.CanBuildFrom canBuildFrom();
  Signature: ()Lscala/collection/generic/CanBuildFrom;
  Code:
   Stack=2, Locals=1, Args_size=1
	new	class scala/xml/NodeSeq$$anon$2
	dup
	invokespecial	Method scala/xml/NodeSeq$$anon$2."<init>":()V
	areturn
  Labels:
  Signature: length = 0x2
   00 3C 

public scala.xml.NodeSeq fromSeq(scala.collection.Seq);
  Signature: (Lscala/collection/Seq;)Lscala/xml/NodeSeq;
  Code:
   Stack=3, Locals=2, Args_size=2
	new	class scala/xml/NodeSeq$$anon$1
	dup
	aload_1
	invokespecial	Method scala/xml/NodeSeq$$anon$1."<init>":(Lscala/collection/Seq;)V
	areturn
  Labels:
  LocalVariableTable: 
   Start  Length  Slot  Name   Signature
   0      9      0    this       Lscala/xml/NodeSeq$;
   0      9      1    s$1       Lscala/collection/Seq;

  Signature: length = 0x2
   00 26 

public final scala.xml.NodeSeq Empty();
  Signature: ()Lscala/xml/NodeSeq;
  Code:
   Stack=1, Locals=1, Args_size=1
	aload_0
	getfield	Field Empty:Lscala/xml/NodeSeq;
	areturn
  Labels:

}

