Compiled from "NodeBuffer.scala"
public class scala.xml.NodeBuffer extends scala.collection.mutable.ArrayBuffer implements scala.ScalaObject
  SourceFile: "NodeBuffer.scala"
  Signature: length = 0x2
   00 6A 
  ScalaSig: length = 0xD5
   05 00 24 06 08 01 02 FFFFFF84 FFFFFF80 FFFFFF80 FFFFFF80 00 07 02 0A 4E
   6F 64 65 42 75 66 66 65 72 0A 02 03 04 01 03 78
   6D 6C 0A 01 05 01 05 73 63 61 6C 61 03 00 13 03
   00 08 14 10 03 09 0E 10 0D 01 0A 0A 02 0B 0C 01
   07 6D 75 74 61 62 6C 65 0A 02 0D 04 01 0A 63 6F
   6C 6C 65 63 74 69 6F 6E 09 02 0F 0A 02 0B 41 72
   72 61 79 42 75 66 66 65 72 10 02 11 12 0D 01 02
   09 02 13 02 02 04 4E 6F 64 65 10 02 15 16 0D 01
   04 09 02 17 04 02 0B 53 63 61 6C 61 4F 62 6A 65
   63 74 08 05 19 00 FFFFFF84 00 1A 01 06 3C 69 6E 69 74
   3E 14 01 1B 10 02 11 00 08 05 1D 00 FFFFFF84 00 1E 01
   09 24 61 6D 70 24 70 6C 75 73 14 02 1B 1F 08 05
   20 1C FFFFFFC0 00 21 01 01 6F 10 02 15 22 09 02 23 04
   02 03 41 6E 79 
  InnerClass: 
   public final $anonfun$$amp$plus$1=class scala/xml/NodeBuffer$$anonfun$$amp$plus$1 of class scala/xml/NodeBuffer
  minor version: 0
  major version: 49
  Constant pool:
Asciz	SourceFile;
Asciz	NodeBuffer.scala;
Asciz	<init>;
Asciz	()V;
Asciz	Code;
Asciz	LineNumberTable;
Asciz	scala/collection/mutable/ArrayBuffer;
class	scala/collection/mutable/ArrayBuffer
NameAndType	"<init>":()V
Method	scala/collection/mutable/ArrayBuffer."<init>":()V
Asciz	$amp$plus;
Asciz	(Ljava/lang/Object;)Lscala/xml/NodeBuffer;;
Asciz	java/lang/Object;
class	java/lang/Object
Asciz	equals;
Asciz	(Ljava/lang/Object;)Z;
NameAndType	equals:(Ljava/lang/Object;)Z
Method	java/lang/Object.equals:(Ljava/lang/Object;)Z
Asciz	scala/runtime/BoxedUnit;
class	scala/runtime/BoxedUnit
Asciz	UNIT;
Asciz	Lscala/runtime/BoxedUnit;;
NameAndType	UNIT:Lscala/runtime/BoxedUnit;
Field	scala/runtime/BoxedUnit.UNIT:Lscala/runtime/BoxedUnit;
Asciz	scala/MatchError;
class	scala/MatchError
Asciz	toString;
Asciz	()Ljava/lang/String;;
NameAndType	toString:()Ljava/lang/String;
Method	java/lang/Object.toString:()Ljava/lang/String;
Asciz	(Ljava/lang/String;)V;
NameAndType	"<init>":(Ljava/lang/String;)V
Method	scala/MatchError."<init>":(Ljava/lang/String;)V
Asciz	scala/xml/Text$;
class	scala/xml/Text$
Asciz	MODULE$;
Asciz	Lscala/xml/Text$;;
NameAndType	MODULE$:Lscala/xml/Text$;
Field	scala/xml/Text$.MODULE$:Lscala/xml/Text$;
Asciz	unapply;
Asciz	(Ljava/lang/Object;)Lscala/Option;;
NameAndType	unapply:(Ljava/lang/Object;)Lscala/Option;
Method	scala/xml/Text$.unapply:(Ljava/lang/Object;)Lscala/Option;
Asciz	scala/Option;
class	scala/Option
Asciz	isEmpty;
Asciz	()Z;
NameAndType	isEmpty:()Z
Method	scala/Option.isEmpty:()Z
Asciz	scala/collection/Iterator;
class	scala/collection/Iterator
Asciz	scala/xml/Node;
class	scala/xml/Node
Asciz	scala/collection/Iterable;
class	scala/collection/Iterable
Asciz	get;
Asciz	()Ljava/lang/Object;;
NameAndType	get:()Ljava/lang/Object;
Method	scala/Option.get:()Ljava/lang/Object;
Asciz	;
String	
Asciz	scala/xml/NodeBuffer$$anonfun$$amp$plus$1;
class	scala/xml/NodeBuffer$$anonfun$$amp$plus$1
Asciz	(Lscala/xml/NodeBuffer;)V;
NameAndType	"<init>":(Lscala/xml/NodeBuffer;)V
Method	scala/xml/NodeBuffer$$anonfun$$amp$plus$1."<init>":(Lscala/xml/NodeBuffer;)V
Asciz	foreach;
Asciz	(Lscala/Function1;)V;
NameAndType	foreach:(Lscala/Function1;)V
InterfaceMethod	scala/collection/Iterator.foreach:(Lscala/Function1;)V
Asciz	$plus$eq;
Asciz	(Ljava/lang/Object;)Lscala/collection/mutable/ArrayBuffer;;
NameAndType	$plus$eq:(Ljava/lang/Object;)Lscala/collection/mutable/ArrayBuffer;
Method	scala/collection/mutable/ArrayBuffer.$plus$eq:(Ljava/lang/Object;)Lscala/collection/mutable/ArrayBuffer;
Asciz	scala/collection/IterableLike;
class	scala/collection/IterableLike
Asciz	iterator;
Asciz	()Lscala/collection/Iterator;;
NameAndType	iterator:()Lscala/collection/Iterator;
InterfaceMethod	scala/collection/IterableLike.iterator:()Lscala/collection/Iterator;
Asciz	scala/xml/NodeBuffer;
class	scala/xml/NodeBuffer
NameAndType	$amp$plus:(Ljava/lang/Object;)Lscala/xml/NodeBuffer;
Method	scala/xml/NodeBuffer.$amp$plus:(Ljava/lang/Object;)Lscala/xml/NodeBuffer;
Asciz	scala/xml/Atom;
class	scala/xml/Atom
Asciz	(Ljava/lang/Object;)V;
NameAndType	"<init>":(Ljava/lang/Object;)V
Method	scala/xml/Atom."<init>":(Ljava/lang/Object;)V
Asciz	this;
Asciz	Lscala/xml/NodeBuffer;;
Asciz	o;
Asciz	Ljava/lang/Object;;
Asciz	temp4;
Asciz	Lscala/Option;;
Asciz	temp7;
Asciz	Lscala/collection/Iterator;;
Asciz	it;
Asciz	temp8;
Asciz	Lscala/xml/Node;;
Asciz	n;
Asciz	temp9;
Asciz	Lscala/collection/Iterable;;
Asciz	ns;
Asciz	LocalVariableTable;
Asciz	Lscala/collection/mutable/ArrayBuffer<Lscala/xml/Node;>;Lscala/ScalaObject;;
Asciz	Signature;
Asciz	ScalaSig;
Asciz	InnerClasses;
Asciz	$anonfun$$amp$plus$1;
Asciz	scala/ScalaObject;
class	scala/ScalaObject

{
public scala.xml.NodeBuffer();
  Signature: ()V
  Code:
   Stack=1, Locals=1, Args_size=1
	aload_0
	invokespecial	Method scala/collection/mutable/ArrayBuffer."<init>":()V
	return
  Labels:

public scala.xml.NodeBuffer $amp$plus(java.lang.Object);
  Signature: (Ljava/lang/Object;)Lscala/xml/NodeBuffer;
  Code:
   Stack=4, Locals=10, Args_size=2
	aload_1
	dup
	pop
	ifnull	l1 // iconst_1
	aload_1
	aconst_null
	invokevirtual	Method java/lang/Object.equals:(Ljava/lang/Object;)Z
	ifeq	l2 // aload_1
l1	iconst_1
	ifeq	l3 // new
	getstatic	Field scala/runtime/BoxedUnit.UNIT:Lscala/runtime/BoxedUnit;
	goto	l4 // pop
l3	new	class scala/MatchError
	dup
	aload_1
	invokevirtual	Method java/lang/Object.toString:()Ljava/lang/String;
	invokespecial	Method scala/MatchError."<init>":(Ljava/lang/String;)V
	athrow
l2	aload_1
	instanceof	class scala/runtime/BoxedUnit
	ifeq	l5 // getstatic
	iconst_1
	ifeq	l6 // new
	getstatic	Field scala/runtime/BoxedUnit.UNIT:Lscala/runtime/BoxedUnit;
	goto	l4 // pop
l6	new	class scala/MatchError
	dup
	aload_1
	invokevirtual	Method java/lang/Object.toString:()Ljava/lang/String;
	invokespecial	Method scala/MatchError."<init>":(Ljava/lang/String;)V
	athrow
l5	getstatic	Field scala/xml/Text$.MODULE$:Lscala/xml/Text$;
	aload_1
	invokevirtual	Method scala/xml/Text$.unapply:(Ljava/lang/Object;)Lscala/Option;
	astore_2
	aload_2
	invokevirtual	Method scala/Option.isEmpty:()Z
	ifeq	l7 // aload_2
	aload_1
	instanceof	class scala/collection/Iterator
	ifeq	l8 // aload_1
	iconst_1
	ifeq	l9 // new
	aload_1
	checkcast	class scala/collection/Iterator
	astore	5
	goto	l10 // aload
l9	new	class scala/MatchError
	dup
	aload_1
	invokevirtual	Method java/lang/Object.toString:()Ljava/lang/String;
	invokespecial	Method scala/MatchError."<init>":(Ljava/lang/String;)V
	athrow
l8	aload_1
	instanceof	class scala/xml/Node
	ifeq	l11 // aload_1
	iconst_1
	ifeq	l12 // new
	aload_1
	checkcast	class scala/xml/Node
	astore	7
	goto	l13 // aload_0
l12	new	class scala/MatchError
	dup
	aload_1
	invokevirtual	Method java/lang/Object.toString:()Ljava/lang/String;
	invokespecial	Method scala/MatchError."<init>":(Ljava/lang/String;)V
	athrow
l11	aload_1
	instanceof	class scala/collection/Iterable
	ifeq	l14 // iconst_1
	iconst_1
	ifeq	l15 // new
	aload_1
	checkcast	class scala/collection/Iterable
	astore	9
	goto	l16 // aload_0
l15	new	class scala/MatchError
	dup
	aload_1
	invokevirtual	Method java/lang/Object.toString:()Ljava/lang/String;
	invokespecial	Method scala/MatchError."<init>":(Ljava/lang/String;)V
	athrow
l14	iconst_1
	ifeq	l17 // new
	goto	l18 // aload_0
l17	new	class scala/MatchError
	dup
	aload_1
	invokevirtual	Method java/lang/Object.toString:()Ljava/lang/String;
	invokespecial	Method scala/MatchError."<init>":(Ljava/lang/String;)V
	athrow
l7	aload_2
	invokevirtual	Method scala/Option.get:()Ljava/lang/Object;
	ldc	String 
	astore_3
	dup
	ifnonnull	l19 // aload_3
	pop
	aload_3
	ifnull	l20 // iconst_1
	goto	l21 // aload_1
l19	aload_3
	invokevirtual	Method java/lang/Object.equals:(Ljava/lang/Object;)Z
	ifeq	l21 // aload_1
l20	iconst_1
	ifeq	l22 // new
	getstatic	Field scala/runtime/BoxedUnit.UNIT:Lscala/runtime/BoxedUnit;
	goto	l4 // pop
l22	new	class scala/MatchError
	dup
	aload_1
	invokevirtual	Method java/lang/Object.toString:()Ljava/lang/String;
	invokespecial	Method scala/MatchError."<init>":(Ljava/lang/String;)V
	athrow
l21	aload_1
	instanceof	class scala/collection/Iterator
	ifeq	l23 // aload_1
	aload_1
	checkcast	class scala/collection/Iterator
	astore	4
	iconst_1
	ifeq	l24 // new
	aload	4
	astore	5
l10	aload	5
	new	class scala/xml/NodeBuffer$$anonfun$$amp$plus$1
	dup
	aload_0
	invokespecial	Method scala/xml/NodeBuffer$$anonfun$$amp$plus$1."<init>":(Lscala/xml/NodeBuffer;)V
	invokeinterface	InterfaceMethod scala/collection/Iterator.foreach:(Lscala/Function1;)V
	getstatic	Field scala/runtime/BoxedUnit.UNIT:Lscala/runtime/BoxedUnit;
	goto	l4 // pop
l24	new	class scala/MatchError
	dup
	aload_1
	invokevirtual	Method java/lang/Object.toString:()Ljava/lang/String;
	invokespecial	Method scala/MatchError."<init>":(Ljava/lang/String;)V
	athrow
l23	aload_1
	instanceof	class scala/xml/Node
	ifeq	l25 // aload_1
	aload_1
	checkcast	class scala/xml/Node
	astore	6
	iconst_1
	ifeq	l26 // new
	aload	6
	astore	7
l13	aload_0
	aload	7
	invokespecial	Method scala/collection/mutable/ArrayBuffer.$plus$eq:(Ljava/lang/Object;)Lscala/collection/mutable/ArrayBuffer;
	goto	l4 // pop
l26	new	class scala/MatchError
	dup
	aload_1
	invokevirtual	Method java/lang/Object.toString:()Ljava/lang/String;
	invokespecial	Method scala/MatchError."<init>":(Ljava/lang/String;)V
	athrow
l25	aload_1
	instanceof	class scala/collection/Iterable
	ifeq	l27 // iconst_1
	aload_1
	checkcast	class scala/collection/Iterable
	astore	8
	iconst_1
	ifeq	l28 // new
	aload	8
	astore	9
l16	aload_0
	aload	9
	invokeinterface	InterfaceMethod scala/collection/IterableLike.iterator:()Lscala/collection/Iterator;
	invokevirtual	Method $amp$plus:(Ljava/lang/Object;)Lscala/xml/NodeBuffer;
	goto	l4 // pop
l28	new	class scala/MatchError
	dup
	aload_1
	invokevirtual	Method java/lang/Object.toString:()Ljava/lang/String;
	invokespecial	Method scala/MatchError."<init>":(Ljava/lang/String;)V
	athrow
l27	iconst_1
	ifeq	l29 // new
l18	aload_0
	new	class scala/xml/Atom
	dup
	aload_1
	invokespecial	Method scala/xml/Atom."<init>":(Ljava/lang/Object;)V
	invokespecial	Method scala/collection/mutable/ArrayBuffer.$plus$eq:(Ljava/lang/Object;)Lscala/collection/mutable/ArrayBuffer;
l4	pop
	aload_0
	areturn
l29	new	class scala/MatchError
	dup
	aload_1
	invokevirtual	Method java/lang/Object.toString:()Ljava/lang/String;
	invokespecial	Method scala/MatchError."<init>":(Ljava/lang/String;)V
	athrow
  Labels:
   	l1 = 14 // iconst_1
   	l3 = 24 // new
   	l2 = 36 // aload_1
   	l6 = 53 // new
   	l5 = 65 // getstatic
   	l9 = 100 // new
   	l8 = 112 // aload_1
   	l12 = 132 // new
   	l11 = 144 // aload_1
   	l15 = 164 // new
   	l14 = 176 // iconst_1
   	l17 = 183 // new
   	l7 = 195 // aload_2
   	l19 = 214 // aload_3
   	l20 = 221 // iconst_1
   	l22 = 231 // new
   	l21 = 243 // aload_1
   	l10 = 264 // aload
   	l24 = 285 // new
   	l23 = 297 // aload_1
   	l13 = 318 // aload_0
   	l26 = 327 // new
   	l25 = 339 // aload_1
   	l16 = 360 // aload_0
   	l28 = 374 // new
   	l27 = 386 // iconst_1
   	l18 = 390 // aload_0
   	l4 = 402 // pop
   	l29 = 405 // new
  LocalVariableTable: 
   Start  Length  Slot  Name   Signature
   0      417      0    this       Lscala/xml/NodeBuffer;
   0      417      1    o       Ljava/lang/Object;
   73      329      2    temp4       Lscala/Option;
   405      12      2    temp4       Lscala/Option;
   256      41      4    temp7       Lscala/collection/Iterator;
   256      4      5    it       Lscala/collection/Iterator;
   264      0      5    it       Lscala/collection/Iterator;
   260      22      5    it       Lscala/collection/Iterator;
   285      12      5    it       Lscala/collection/Iterator;
   310      29      6    temp8       Lscala/xml/Node;
   310      4      7    n       Lscala/xml/Node;
   318      0      7    n       Lscala/xml/Node;
   314      10      7    n       Lscala/xml/Node;
   327      12      7    n       Lscala/xml/Node;
   352      34      8    temp9       Lscala/collection/Iterable;
   352      4      9    ns       Lscala/collection/Iterable;
   360      0      9    ns       Lscala/collection/Iterable;
   356      15      9    ns       Lscala/collection/Iterable;
   374      12      9    ns       Lscala/collection/Iterable;


}

