Compiled from "Node.scala"
public abstract class scala.xml.Node extends scala.xml.NodeSeq implements scala.ScalaObject
  SourceFile: "Node.scala"
  ScalaSig: length = 0x4BC
   05 00 FFFFFF81 31 07 05 01 02 FFFFFF88 02 07 01 04 4E 6F 64
   65 0A 02 03 04 01 03 78 6D 6C 0A 01 05 01 05 73
   63 61 6C 61 03 00 10 02 08 09 0D 01 02 06 08 0A
   02 FFFFFF84 FFFFFF80 FFFFFF80 FFFFFF88 02 0B 02 04 4E 6F 64 65 13 03 09
   0C 14 10 02 0D 12 0D 01 0E 0A 02 0F 10 01 04 6C
   61 6E 67 0A 01 11 01 04 6A 61 76 61 09 02 13 0E
   02 06 4F 62 6A 65 63 74 10 02 15 16 0D 01 04 09
   02 17 04 02 0B 53 63 61 6C 61 4F 62 6A 65 63 74
   08 05 19 09 FFFFFF84 00 1A 01 06 3C 69 6E 69 74 3E 14
   01 07 08 05 1C 09 FFFFFF84 02 1D 01 0C 4E 6F 41 74 74
   72 69 62 75 74 65 73 15 01 1E 10 02 08 1F 09 02
   20 02 02 08 4D 65 74 61 44 61 74 61 08 07 22 09
   FFFFFFC2 FFFFFF80 FFFFFF84 00 23 01 0E 45 6D 70 74 79 4E 61 6D 65
   73 70 61 63 65 15 01 24 10 02 0D 25 09 02 26 0E
   02 06 53 74 72 69 6E 67 08 06 28 09 FFFFFFA0 FFFFFF80 04 24
   01 0F 45 6D 70 74 79 4E 61 6D 65 73 70 61 63 65
   20 08 05 2A 09 FFFFFF84 00 2B 01 0A 75 6E 61 70 70 6C
   79 53 65 71 14 03 2C FFFFFF81 2F 10 03 15 2D 2F 09 02
   2E 04 02 04 53 6F 6D 65 10 05 15 30 32 1E 38 09
   02 31 04 02 06 54 75 70 6C 65 33 10 02 33 36 0E
   02 15 34 09 02 35 04 01 06 50 72 65 64 65 66 09
   02 26 37 0A 02 35 04 10 03 39 3C 3E 0D 01 3A 0A
   02 3B 04 01 0A 63 6F 6C 6C 65 63 74 69 6F 6E 09
   02 3D 3A 02 03 53 65 71 10 02 08 3F 06 08 0A 02
   FFFFFF84 FFFFFF80 FFFFFF80 FFFFFF81 00 40 13 03 3F 41 14 10 02 08 42 09
   02 43 02 02 07 4E 6F 64 65 53 65 71 08 05 19 3F
   FFFFFF84 00 45 14 01 3E 08 05 47 3F FFFFFF84 00 48 01 06 70
   72 65 66 69 78 15 01 32 08 05 4A 3F FFFFFF86 00 48 01
   05 6C 61 62 65 6C 08 05 4C 3F FFFFFF84 00 4D 01 06 69
   73 41 74 6F 6D 15 01 4E 10 02 15 4F 09 02 50 04
   02 07 42 6F 6F 6C 65 61 6E 08 05 52 3F FFFFFF84 00 4D
   01 13 64 6F 43 6F 6C 6C 65 63 74 4E 61 6D 65 73
   70 61 63 65 73 08 05 54 3F FFFFFF84 00 4D 01 0B 64 6F
   54 72 61 6E 73 66 6F 72 6D 08 05 56 3F FFFFFF84 00 57
   01 05 73 63 6F 70 65 15 01 58 10 02 08 59 09 02
   5A 02 02 10 4E 61 6D 65 73 70 61 63 65 42 69 6E
   64 69 6E 67 08 05 5C 3F FFFFFF84 00 48 01 09 6E 61 6D
   65 73 70 61 63 65 08 05 5E 3F FFFFFF84 00 5F 01 0C 67
   65 74 4E 61 6D 65 73 70 61 63 65 14 02 32 60 08
   05 61 5D FFFFFFC0 00 32 01 03 70 72 65 08 05 63 3F FFFFFF84
   02 64 01 09 61 74 74 72 69 62 75 74 65 14 02 65
   68 10 03 15 66 38 09 02 67 04 02 06 4F 70 74 69
   6F 6E 08 05 69 62 FFFFFFC0 00 32 01 03 6B 65 79 08 05
   63 3F FFFFFF84 02 6B 14 03 65 6C 6E 08 05 6D 6A FFFFFFC0 00
   32 01 03 75 72 69 08 05 69 6A FFFFFFC0 00 32 08 05 70
   3F FFFFFF84 00 1D 01 0A 61 74 74 72 69 62 75 74 65 73
   08 05 72 3F FFFFFF86 00 73 01 05 63 68 69 6C 64 15 01
   38 08 05 75 3F FFFFFF84 00 76 01 0A 64 65 73 63 65 6E
   64 61 6E 74 15 01 77 10 03 78 7B 3E 0D 01 79 0A
   02 7A 3A 01 09 69 6D 6D 75 74 61 62 6C 65 09 02
   7C 79 02 04 4C 69 73 74 08 05 7E 3F FFFFFF84 00 76 01
   12 64 65 73 63 65 6E 64 61 6E 74 5F 6F 72 5F 73
   65 6C 66 08 07 FFFFFF81 00 3F FFFFFF84 20 FFFFFF81 01 01 06 65 71
   75 61 6C 73 14 03 4E FFFFFF81 02 08 07 FFFFFF81 03 7F FFFFFFC0 00
   FFFFFF81 04 01 01 78 10 03 15 FFFFFF81 05 09 03 FFFFFF81 06 04 02
   03 41 6E 79 08 07 FFFFFF81 08 3F FFFFFF84 04 FFFFFF81 09 01 0D 65
   71 75 61 6C 43 68 69 6C 64 72 65 6E 14 03 4E FFFFFF81
   0A 08 07 FFFFFF81 0B FFFFFF81 07 FFFFFFC0 00 3E 01 04 74 68 61 74
   08 07 FFFFFF81 0D 3F FFFFFF84 20 FFFFFF81 0E 01 08 68 61 73 68 43
   6F 64 65 14 02 FFFFFF81 0F 10 03 15 FFFFFF81 10 09 03 FFFFFF81 11
   04 02 03 49 6E 74 08 06 FFFFFF81 13 3F FFFFFF84 00 73 01 06
   74 68 65 53 65 71 08 07 FFFFFF81 15 3F FFFFFF84 00 FFFFFF81 16 01
   0B 62 75 69 6C 64 53 74 72 69 6E 67 14 03 32 FFFFFF81
   17 08 07 FFFFFF81 18 FFFFFF81 14 FFFFFFC0 00 4E 01 0D 73 74 72 69
   70 43 6F 6D 6D 65 6E 74 73 08 07 FFFFFF81 1A 3F FFFFFF84 20
   FFFFFF81 1B 01 08 74 6F 53 74 72 69 6E 67 14 01 32 08
   07 FFFFFF81 1D 3F FFFFFF84 00 FFFFFF81 1E 01 0C 6E 61 6D 65 54 6F
   53 74 72 69 6E 67 14 04 FFFFFF81 1F FFFFFF81 25 10 04 FFFFFF81 20
   FFFFFF81 23 0D 02 FFFFFF81 21 0A 03 FFFFFF81 22 3A 01 07 6D 75 74
   61 62 6C 65 09 04 FFFFFF81 24 FFFFFF81 21 02 0D 53 74 72 69
   6E 67 42 75 69 6C 64 65 72 08 08 FFFFFF81 26 FFFFFF81 1C FFFFFFC0
   00 FFFFFF81 1F 01 02 73 62 08 07 FFFFFF81 28 3F FFFFFF84 00 FFFFFF81 29
   01 07 78 6D 6C 54 79 70 65 14 02 FFFFFF81 2A 10 03 08
   FFFFFF81 2B 09 03 FFFFFF81 2C 02 02 0A 54 79 70 65 53 79 6D
   62 6F 6C 08 06 FFFFFF81 2E 3F FFFFFF84 20 48 01 04 74 65 78
   74 08 06 FFFFFF81 30 29 FFFFFFC0 00 3E 01 01 6E 
  InnerClass: 
   public final $anonfun$descendant$1=class scala/xml/Node$$anonfun$descendant$1 of class scala/xml/Node
   public final $anonfun$noEmpties$1$1=class scala/xml/Node$$anonfun$noEmpties$1$1 of class scala/xml/Node
  minor version: 0
  major version: 49
  Constant pool:
Asciz	SourceFile;
Asciz	Node.scala;
Asciz	unapplySeq;
Asciz	(Lscala/xml/Node;)Lscala/Some;;
Asciz	Code;
Asciz	scala/xml/Node$;
class	scala/xml/Node$
Asciz	MODULE$;
Asciz	Lscala/xml/Node$;;
NameAndType	MODULE$:Lscala/xml/Node$;
Field	scala/xml/Node$.MODULE$:Lscala/xml/Node$;
NameAndType	unapplySeq:(Lscala/xml/Node;)Lscala/Some;
Method	scala/xml/Node$.unapplySeq:(Lscala/xml/Node;)Lscala/Some;
Asciz	(Lscala/xml/Node;)Lscala/Some<Lscala/Tuple3<Ljava/lang/String;Lscala/xml/MetaData;Lscala/collection/Seq<Lscala/xml/Node;>;>;>;;
Asciz	Signature;
Asciz	EmptyNamespace;
Asciz	()Ljava/lang/String;;
NameAndType	EmptyNamespace:()Ljava/lang/String;
Method	scala/xml/Node$.EmptyNamespace:()Ljava/lang/String;
Asciz	NoAttributes;
Asciz	()Lscala/xml/MetaData;;
NameAndType	NoAttributes:()Lscala/xml/MetaData;
Method	scala/xml/Node$.NoAttributes:()Lscala/xml/MetaData;
Asciz	prefix;
Asciz	LineNumberTable;
Asciz	label;
Asciz	isAtom;
Asciz	()Z;
Asciz	scala/xml/Atom;
class	scala/xml/Atom
Asciz	doCollectNamespaces;
Asciz	doTransform;
Asciz	scope;
Asciz	()Lscala/xml/NamespaceBinding;;
Asciz	scala/xml/TopScope$;
class	scala/xml/TopScope$
Asciz	Lscala/xml/TopScope$;;
NameAndType	MODULE$:Lscala/xml/TopScope$;
Field	scala/xml/TopScope$.MODULE$:Lscala/xml/TopScope$;
Asciz	namespace;
Asciz	scala/xml/Node;
class	scala/xml/Node
NameAndType	prefix:()Ljava/lang/String;
Method	scala/xml/Node.prefix:()Ljava/lang/String;
Asciz	getNamespace;
Asciz	(Ljava/lang/String;)Ljava/lang/String;;
NameAndType	getNamespace:(Ljava/lang/String;)Ljava/lang/String;
Method	scala/xml/Node.getNamespace:(Ljava/lang/String;)Ljava/lang/String;
NameAndType	scope:()Lscala/xml/NamespaceBinding;
Method	scala/xml/Node.scope:()Lscala/xml/NamespaceBinding;
Asciz	scala/xml/NamespaceBinding;
class	scala/xml/NamespaceBinding
Asciz	getURI;
NameAndType	getURI:(Ljava/lang/String;)Ljava/lang/String;
Method	scala/xml/NamespaceBinding.getURI:(Ljava/lang/String;)Ljava/lang/String;
Asciz	this;
Asciz	Lscala/xml/Node;;
Asciz	pre;
Asciz	Ljava/lang/String;;
Asciz	LocalVariableTable;
Asciz	attribute;
Asciz	(Ljava/lang/String;)Lscala/Option;;
Asciz	attributes;
NameAndType	attributes:()Lscala/xml/MetaData;
Method	scala/xml/Node.attributes:()Lscala/xml/MetaData;
Asciz	scala/xml/MetaData;
class	scala/xml/MetaData
Asciz	get;
NameAndType	get:(Ljava/lang/String;)Lscala/Option;
Method	scala/xml/MetaData.get:(Ljava/lang/String;)Lscala/Option;
Asciz	key;
Asciz	(Ljava/lang/String;)Lscala/Option<Lscala/collection/Seq<Lscala/xml/Node;>;>;;
Asciz	(Ljava/lang/String;Ljava/lang/String;)Lscala/Option;;
Asciz	(Ljava/lang/String;Lscala/xml/Node;Ljava/lang/String;)Lscala/Option;;
NameAndType	get:(Ljava/lang/String;Lscala/xml/Node;Ljava/lang/String;)Lscala/Option;
Method	scala/xml/MetaData.get:(Ljava/lang/String;Lscala/xml/Node;Ljava/lang/String;)Lscala/Option;
Asciz	uri;
Asciz	(Ljava/lang/String;Ljava/lang/String;)Lscala/Option<Lscala/collection/Seq<Lscala/xml/Node;>;>;;
Asciz	scala/xml/Null$;
class	scala/xml/Null$
Asciz	Lscala/xml/Null$;;
NameAndType	MODULE$:Lscala/xml/Null$;
Field	scala/xml/Null$.MODULE$:Lscala/xml/Null$;
Asciz	child;
Asciz	()Lscala/collection/Seq;;
Asciz	()Lscala/collection/Seq<Lscala/xml/Node;>;;
Asciz	descendant;
Asciz	()Lscala/collection/immutable/List;;
NameAndType	child:()Lscala/collection/Seq;
Method	scala/xml/Node.child:()Lscala/collection/Seq;
Asciz	scala/collection/TraversableLike;
class	scala/collection/TraversableLike
Asciz	toList;
NameAndType	toList:()Lscala/collection/immutable/List;
InterfaceMethod	scala/collection/TraversableLike.toList:()Lscala/collection/immutable/List;
Asciz	scala/xml/Node$$anonfun$descendant$1;
class	scala/xml/Node$$anonfun$descendant$1
Asciz	<init>;
Asciz	(Lscala/xml/Node;)V;
NameAndType	"<init>":(Lscala/xml/Node;)V
Method	scala/xml/Node$$anonfun$descendant$1."<init>":(Lscala/xml/Node;)V
Asciz	scala/collection/immutable/List$;
class	scala/collection/immutable/List$
Asciz	Lscala/collection/immutable/List$;;
NameAndType	MODULE$:Lscala/collection/immutable/List$;
Field	scala/collection/immutable/List$.MODULE$:Lscala/collection/immutable/List$;
Asciz	canBuildFrom;
Asciz	()Lscala/collection/generic/CanBuildFrom;;
NameAndType	canBuildFrom:()Lscala/collection/generic/CanBuildFrom;
Method	scala/collection/immutable/List$.canBuildFrom:()Lscala/collection/generic/CanBuildFrom;
Asciz	flatMap;
Asciz	(Lscala/Function1;Lscala/collection/generic/CanBuildFrom;)Ljava/lang/Object;;
NameAndType	flatMap:(Lscala/Function1;Lscala/collection/generic/CanBuildFrom;)Ljava/lang/Object;
InterfaceMethod	scala/collection/TraversableLike.flatMap:(Lscala/Function1;Lscala/collection/generic/CanBuildFrom;)Ljava/lang/Object;
Asciz	scala/collection/immutable/List;
class	scala/collection/immutable/List
Asciz	()Lscala/collection/immutable/List<Lscala/xml/Node;>;;
Asciz	descendant_or_self;
NameAndType	descendant:()Lscala/collection/immutable/List;
Method	scala/xml/Node.descendant:()Lscala/collection/immutable/List;
Asciz	$colon$colon;
Asciz	(Ljava/lang/Object;)Lscala/collection/immutable/List;;
NameAndType	$colon$colon:(Ljava/lang/Object;)Lscala/collection/immutable/List;
Method	scala/collection/immutable/List.$colon$colon:(Ljava/lang/Object;)Lscala/collection/immutable/List;
Asciz	equals;
Asciz	(Ljava/lang/Object;)Z;
Asciz	scala/xml/Group;
class	scala/xml/Group
Asciz	java/lang/Object;
class	java/lang/Object
NameAndType	equals:(Ljava/lang/Object;)Z
Method	java/lang/Object.equals:(Ljava/lang/Object;)Z
NameAndType	label:()Ljava/lang/String;
Method	scala/xml/Node.label:()Ljava/lang/String;
Asciz	equalChildren;
Asciz	(Lscala/xml/Node;)Z;
NameAndType	equalChildren:(Lscala/xml/Node;)Z
Method	scala/xml/Node.equalChildren:(Lscala/xml/Node;)Z
Asciz	x;
Asciz	Ljava/lang/Object;;
Asciz	temp4;
Asciz	noEmpties$1;
Asciz	(Lscala/collection/Seq;)Lscala/collection/Seq;;
NameAndType	noEmpties$1:(Lscala/collection/Seq;)Lscala/collection/Seq;
Method	scala/xml/Node.noEmpties$1:(Lscala/collection/Seq;)Lscala/collection/Seq;
Asciz	scala/collection/IterableLike;
class	scala/collection/IterableLike
Asciz	sameElements;
Asciz	(Lscala/collection/Iterable;)Z;
NameAndType	sameElements:(Lscala/collection/Iterable;)Z
InterfaceMethod	scala/collection/IterableLike.sameElements:(Lscala/collection/Iterable;)Z
Asciz	that;
Asciz	hashCode;
Asciz	()I;
Asciz	scala/xml/Utility$;
class	scala/xml/Utility$
Asciz	Lscala/xml/Utility$;;
NameAndType	MODULE$:Lscala/xml/Utility$;
Field	scala/xml/Utility$.MODULE$:Lscala/xml/Utility$;
NameAndType	hashCode:()I
Method	scala/xml/MetaData.hashCode:()I
Method	scala/xml/NamespaceBinding.hashCode:()I
Asciz	(Ljava/lang/String;Ljava/lang/String;IILscala/collection/Seq;)I;
NameAndType	hashCode:(Ljava/lang/String;Ljava/lang/String;IILscala/collection/Seq;)I
Method	scala/xml/Utility$.hashCode:(Ljava/lang/String;Ljava/lang/String;IILscala/collection/Seq;)I
Asciz	theSeq;
Asciz	scala/collection/immutable/Nil$;
class	scala/collection/immutable/Nil$
Asciz	Lscala/collection/immutable/Nil$;;
NameAndType	MODULE$:Lscala/collection/immutable/Nil$;
Field	scala/collection/immutable/Nil$.MODULE$:Lscala/collection/immutable/Nil$;
Method	scala/collection/immutable/Nil$.$colon$colon:(Ljava/lang/Object;)Lscala/collection/immutable/List;
Asciz	buildString;
Asciz	(Z)Ljava/lang/String;;
Asciz	toXML$default$2;
NameAndType	toXML$default$2:()Lscala/xml/NamespaceBinding;
Method	scala/xml/Utility$.toXML$default$2:()Lscala/xml/NamespaceBinding;
Asciz	toXML$default$3;
Asciz	()Lscala/collection/mutable/StringBuilder;;
NameAndType	toXML$default$3:()Lscala/collection/mutable/StringBuilder;
Method	scala/xml/Utility$.toXML$default$3:()Lscala/collection/mutable/StringBuilder;
Asciz	toXML$default$5;
NameAndType	toXML$default$5:()Z
Method	scala/xml/Utility$.toXML$default$5:()Z
Asciz	toXML$default$6;
NameAndType	toXML$default$6:()Z
Method	scala/xml/Utility$.toXML$default$6:()Z
Asciz	toXML$default$7;
NameAndType	toXML$default$7:()Z
Method	scala/xml/Utility$.toXML$default$7:()Z
Asciz	toXML;
Asciz	(Lscala/xml/Node;Lscala/xml/NamespaceBinding;Lscala/collection/mutable/StringBuilder;ZZZZ)Lscala/collection/mutable/StringBuilder;;
NameAndType	toXML:(Lscala/xml/Node;Lscala/xml/NamespaceBinding;Lscala/collection/mutable/StringBuilder;ZZZZ)Lscala/collection/mutable/StringBuilder;
Method	scala/xml/Utility$.toXML:(Lscala/xml/Node;Lscala/xml/NamespaceBinding;Lscala/collection/mutable/StringBuilder;ZZZZ)Lscala/collection/mutable/StringBuilder;
Asciz	scala/collection/mutable/StringBuilder;
class	scala/collection/mutable/StringBuilder
Asciz	toString;
NameAndType	toString:()Ljava/lang/String;
Method	scala/collection/mutable/StringBuilder.toString:()Ljava/lang/String;
Asciz	stripComments;
Asciz	Z;
Asciz	x$7;
Asciz	Lscala/xml/NamespaceBinding;;
Asciz	x$8;
Asciz	Lscala/collection/mutable/StringBuilder;;
Asciz	x$9;
Asciz	x$10;
Asciz	x$11;
NameAndType	buildString:(Z)Ljava/lang/String;
Method	scala/xml/Node.buildString:(Z)Ljava/lang/String;
Asciz	nameToString;
Asciz	(Lscala/collection/mutable/StringBuilder;)Lscala/collection/mutable/StringBuilder;;
Asciz	scala/runtime/BoxedUnit;
class	scala/runtime/BoxedUnit
Asciz	UNIT;
Asciz	Lscala/runtime/BoxedUnit;;
NameAndType	UNIT:Lscala/runtime/BoxedUnit;
Field	scala/runtime/BoxedUnit.UNIT:Lscala/runtime/BoxedUnit;
Asciz	append;
Asciz	(Ljava/lang/String;)Lscala/collection/mutable/StringBuilder;;
NameAndType	append:(Ljava/lang/String;)Lscala/collection/mutable/StringBuilder;
Method	scala/collection/mutable/StringBuilder.append:(Ljava/lang/String;)Lscala/collection/mutable/StringBuilder;
int	58;
Asciz	(C)Lscala/collection/mutable/StringBuilder;;
NameAndType	append:(C)Lscala/collection/mutable/StringBuilder;
Method	scala/collection/mutable/StringBuilder.append:(C)Lscala/collection/mutable/StringBuilder;
Asciz	sb;
Asciz	xmlType;
Asciz	()Lscala/xml/TypeSymbol;;
Asciz	text;
Asciz	scala/xml/NodeSeq;
class	scala/xml/NodeSeq
NameAndType	text:()Ljava/lang/String;
Method	scala/xml/NodeSeq.text:()Ljava/lang/String;
Asciz	scala/xml/Node$$anonfun$noEmpties$1$1;
class	scala/xml/Node$$anonfun$noEmpties$1$1
Method	scala/xml/Node$$anonfun$noEmpties$1$1."<init>":(Lscala/xml/Node;)V
Asciz	filter;
Asciz	(Lscala/Function1;)Ljava/lang/Object;;
NameAndType	filter:(Lscala/Function1;)Ljava/lang/Object;
InterfaceMethod	scala/collection/TraversableLike.filter:(Lscala/Function1;)Ljava/lang/Object;
Asciz	scala/collection/Seq;
class	scala/collection/Seq
Asciz	xs;
Asciz	Lscala/collection/Seq;;
Asciz	()V;
NameAndType	"<init>":()V
Method	scala/xml/NodeSeq."<init>":()V
Asciz	ScalaSig;
Asciz	InnerClasses;
Asciz	$anonfun$descendant$1;
Asciz	$anonfun$noEmpties$1$1;
Asciz	scala/ScalaObject;
class	scala/ScalaObject

{
public static final scala.Some unapplySeq(scala.xml.Node);
  Signature: (Lscala/xml/Node;)Lscala/Some;
  Code:
   Stack=2, Locals=1, Args_size=1
	getstatic	Field scala/xml/Node$.MODULE$:Lscala/xml/Node$;
	aload_0
	invokevirtual	Method scala/xml/Node$.unapplySeq:(Lscala/xml/Node;)Lscala/Some;
	areturn
  Labels:
  Signature: length = 0x2
   00 0E 

public static final java.lang.String EmptyNamespace();
  Signature: ()Ljava/lang/String;
  Code:
   Stack=1, Locals=0, Args_size=0
	getstatic	Field scala/xml/Node$.MODULE$:Lscala/xml/Node$;
	invokevirtual	Method scala/xml/Node$.EmptyNamespace:()Ljava/lang/String;
	areturn
  Labels:

public static final scala.xml.MetaData NoAttributes();
  Signature: ()Lscala/xml/MetaData;
  Code:
   Stack=1, Locals=0, Args_size=0
	getstatic	Field scala/xml/Node$.MODULE$:Lscala/xml/Node$;
	invokevirtual	Method scala/xml/Node$.NoAttributes:()Lscala/xml/MetaData;
	areturn
  Labels:

public java.lang.String prefix();
  Signature: ()Ljava/lang/String;
  Code:
   Stack=1, Locals=1, Args_size=1
	aconst_null
	areturn
  Labels:

public abstract java.lang.String label();
  Signature: ()Ljava/lang/String;

public boolean isAtom();
  Signature: ()Z
  Code:
   Stack=1, Locals=1, Args_size=1
	aload_0
	instanceof	class scala/xml/Atom
	ireturn
  Labels:

public boolean doCollectNamespaces();
  Signature: ()Z
  Code:
   Stack=1, Locals=1, Args_size=1
	iconst_1
	ireturn
  Labels:

public boolean doTransform();
  Signature: ()Z
  Code:
   Stack=1, Locals=1, Args_size=1
	iconst_1
	ireturn
  Labels:

public scala.xml.NamespaceBinding scope();
  Signature: ()Lscala/xml/NamespaceBinding;
  Code:
   Stack=1, Locals=1, Args_size=1
	getstatic	Field scala/xml/TopScope$.MODULE$:Lscala/xml/TopScope$;
	areturn
  Labels:

public java.lang.String namespace();
  Signature: ()Ljava/lang/String;
  Code:
   Stack=2, Locals=1, Args_size=1
	aload_0
	aload_0
	invokevirtual	Method prefix:()Ljava/lang/String;
	invokevirtual	Method getNamespace:(Ljava/lang/String;)Ljava/lang/String;
	areturn
  Labels:

public java.lang.String getNamespace(java.lang.String);
  Signature: (Ljava/lang/String;)Ljava/lang/String;
  Code:
   Stack=2, Locals=2, Args_size=2
	aload_0
	invokevirtual	Method scope:()Lscala/xml/NamespaceBinding;
	ifnonnull	l1 // aload_0
	aconst_null
	goto	l2 // areturn
l1	aload_0
	invokevirtual	Method scope:()Lscala/xml/NamespaceBinding;
	aload_1
	invokevirtual	Method scala/xml/NamespaceBinding.getURI:(Ljava/lang/String;)Ljava/lang/String;
l2	areturn
  Labels:
   	l1 = 11 // aload_0
   	l2 = 19 // areturn
  LocalVariableTable: 
   Start  Length  Slot  Name   Signature
   0      20      0    this       Lscala/xml/Node;
   0      20      1    pre       Ljava/lang/String;


public final scala.Option attribute(java.lang.String);
  Signature: (Ljava/lang/String;)Lscala/Option;
  Code:
   Stack=2, Locals=2, Args_size=2
	aload_0
	invokevirtual	Method attributes:()Lscala/xml/MetaData;
	aload_1
	invokevirtual	Method scala/xml/MetaData.get:(Ljava/lang/String;)Lscala/Option;
	areturn
  Labels:
  LocalVariableTable: 
   Start  Length  Slot  Name   Signature
   0      9      0    this       Lscala/xml/Node;
   0      9      1    key       Ljava/lang/String;

  Signature: length = 0x2
   00 48 

public final scala.Option attribute(java.lang.String, java.lang.String);
  Signature: (Ljava/lang/String;Ljava/lang/String;)Lscala/Option;
  Code:
   Stack=4, Locals=3, Args_size=3
	aload_0
	invokevirtual	Method attributes:()Lscala/xml/MetaData;
	aload_1
	aload_0
	aload_2
	invokevirtual	Method scala/xml/MetaData.get:(Ljava/lang/String;Lscala/xml/Node;Ljava/lang/String;)Lscala/Option;
	areturn
  Labels:
  LocalVariableTable: 
   Start  Length  Slot  Name   Signature
   0      11      0    this       Lscala/xml/Node;
   0      11      1    uri       Ljava/lang/String;
   0      11      2    key       Ljava/lang/String;

  Signature: length = 0x2
   00 4E 

public scala.xml.MetaData attributes();
  Signature: ()Lscala/xml/MetaData;
  Code:
   Stack=1, Locals=1, Args_size=1
	getstatic	Field scala/xml/Null$.MODULE$:Lscala/xml/Null$;
	areturn
  Labels:

public abstract scala.collection.Seq child();
  Signature: ()Lscala/collection/Seq;
  Signature: length = 0x2
   00 56 

public scala.collection.immutable.List descendant();
  Signature: ()Lscala/collection/immutable/List;
  Code:
   Stack=4, Locals=1, Args_size=1
	aload_0
	invokevirtual	Method child:()Lscala/collection/Seq;
	invokeinterface	InterfaceMethod scala/collection/TraversableLike.toList:()Lscala/collection/immutable/List;
	new	class scala/xml/Node$$anonfun$descendant$1
	dup
	aload_0
	invokespecial	Method scala/xml/Node$$anonfun$descendant$1."<init>":(Lscala/xml/Node;)V
	getstatic	Field scala/collection/immutable/List$.MODULE$:Lscala/collection/immutable/List$;
	invokevirtual	Method scala/collection/immutable/List$.canBuildFrom:()Lscala/collection/generic/CanBuildFrom;
	invokeinterface	InterfaceMethod scala/collection/TraversableLike.flatMap:(Lscala/Function1;Lscala/collection/generic/CanBuildFrom;)Ljava/lang/Object;
	checkcast	class scala/collection/immutable/List
	areturn
  Labels:
  Signature: length = 0x2
   00 75 

public scala.collection.immutable.List descendant_or_self();
  Signature: ()Lscala/collection/immutable/List;
  Code:
   Stack=2, Locals=1, Args_size=1
	aload_0
	invokevirtual	Method descendant:()Lscala/collection/immutable/List;
	aload_0
	invokevirtual	Method scala/collection/immutable/List.$colon$colon:(Ljava/lang/Object;)Lscala/collection/immutable/List;
	areturn
  Labels:
  Signature: length = 0x2
   00 75 

public boolean equals(java.lang.Object);
  Signature: (Ljava/lang/Object;)Z
  Code:
   Stack=2, Locals=7, Args_size=2
	aload_1
	instanceof	class scala/xml/Group
	ifeq	l1 // aload_1
	iconst_0
	goto	l2 // ireturn
l1	aload_1
	instanceof	class scala/xml/Node
	ifeq	l3 // iconst_0
	aload_1
	checkcast	class scala/xml/Node
	astore	6
	aload_0
	invokevirtual	Method prefix:()Ljava/lang/String;
	aload	6
	invokevirtual	Method prefix:()Ljava/lang/String;
	astore_2
	dup
	ifnonnull	l4 // aload_2
	pop
	aload_2
	ifnull	l5 // aload_0
	goto	l6 // iconst_0
l4	aload_2
	invokevirtual	Method java/lang/Object.equals:(Ljava/lang/Object;)Z
	ifeq	l6 // iconst_0
l5	aload_0
	invokevirtual	Method label:()Ljava/lang/String;
	aload	6
	invokevirtual	Method label:()Ljava/lang/String;
	astore_3
	dup
	ifnonnull	l7 // aload_3
	pop
	aload_3
	ifnull	l8 // aload_0
	goto	l6 // iconst_0
l7	aload_3
	invokevirtual	Method java/lang/Object.equals:(Ljava/lang/Object;)Z
	ifeq	l6 // iconst_0
l8	aload_0
	invokevirtual	Method attributes:()Lscala/xml/MetaData;
	aload	6
	invokevirtual	Method attributes:()Lscala/xml/MetaData;
	astore	4
	dup
	ifnonnull	l9 // aload
	pop
	aload	4
	ifnull	l10 // aload_0
	goto	l6 // iconst_0
l9	aload	4
	invokevirtual	Method java/lang/Object.equals:(Ljava/lang/Object;)Z
	ifeq	l6 // iconst_0
l10	aload_0
	invokevirtual	Method scope:()Lscala/xml/NamespaceBinding;
	aload	6
	invokevirtual	Method scope:()Lscala/xml/NamespaceBinding;
	astore	5
	dup
	ifnonnull	l11 // aload
	pop
	aload	5
	ifnull	l12 // aload_0
	goto	l6 // iconst_0
l11	aload	5
	invokevirtual	Method java/lang/Object.equals:(Ljava/lang/Object;)Z
	ifeq	l6 // iconst_0
l12	aload_0
	aload	6
	invokespecial	Method equalChildren:(Lscala/xml/Node;)Z
	ifeq	l6 // iconst_0
	iconst_1
	goto	l2 // ireturn
l6	iconst_0
	goto	l2 // ireturn
l3	iconst_0
l2	ireturn
  Labels:
   	l1 = 11 // aload_1
   	l4 = 46 // aload_2
   	l5 = 53 // aload_0
   	l7 = 75 // aload_3
   	l8 = 82 // aload_0
   	l9 = 106 // aload
   	l10 = 114 // aload_0
   	l11 = 138 // aload
   	l12 = 146 // aload_0
   	l6 = 159 // iconst_0
   	l3 = 163 // iconst_0
   	l2 = 164 // ireturn
  LocalVariableTable: 
   Start  Length  Slot  Name   Signature
   0      165      0    this       Lscala/xml/Node;
   0      165      1    x       Ljava/lang/Object;
   24      139      6    temp4       Lscala/xml/Node;


private boolean equalChildren(scala.xml.Node);
  Signature: (Lscala/xml/Node;)Z
  Code:
   Stack=3, Locals=2, Args_size=2
	aload_0
	aload_0
	invokevirtual	Method child:()Lscala/collection/Seq;
	invokespecial	Method noEmpties$1:(Lscala/collection/Seq;)Lscala/collection/Seq;
	aload_0
	aload_1
	invokevirtual	Method child:()Lscala/collection/Seq;
	invokespecial	Method noEmpties$1:(Lscala/collection/Seq;)Lscala/collection/Seq;
	invokeinterface	InterfaceMethod scala/collection/IterableLike.sameElements:(Lscala/collection/Iterable;)Z
	ireturn
  Labels:
  LocalVariableTable: 
   Start  Length  Slot  Name   Signature
   0      22      0    this       Lscala/xml/Node;
   0      22      1    that       Lscala/xml/Node;


public int hashCode();
  Signature: ()I
  Code:
   Stack=6, Locals=1, Args_size=1
	getstatic	Field scala/xml/Utility$.MODULE$:Lscala/xml/Utility$;
	aload_0
	invokevirtual	Method prefix:()Ljava/lang/String;
	aload_0
	invokevirtual	Method label:()Ljava/lang/String;
	aload_0
	invokevirtual	Method attributes:()Lscala/xml/MetaData;
	invokevirtual	Method scala/xml/MetaData.hashCode:()I
	aload_0
	invokevirtual	Method scope:()Lscala/xml/NamespaceBinding;
	invokevirtual	Method scala/xml/NamespaceBinding.hashCode:()I
	aload_0
	invokevirtual	Method child:()Lscala/collection/Seq;
	invokevirtual	Method scala/xml/Utility$.hashCode:(Ljava/lang/String;Ljava/lang/String;IILscala/collection/Seq;)I
	ireturn
  Labels:

public scala.collection.Seq theSeq();
  Signature: ()Lscala/collection/Seq;
  Code:
   Stack=2, Locals=1, Args_size=1
	getstatic	Field scala/collection/immutable/Nil$.MODULE$:Lscala/collection/immutable/Nil$;
	aload_0
	invokevirtual	Method scala/collection/immutable/Nil$.$colon$colon:(Ljava/lang/Object;)Lscala/collection/immutable/List;
	areturn
  Labels:
  Signature: length = 0x2
   00 56 

public java.lang.String buildString(boolean);
  Signature: (Z)Ljava/lang/String;
  Code:
   Stack=8, Locals=7, Args_size=2
	getstatic	Field scala/xml/Utility$.MODULE$:Lscala/xml/Utility$;
	invokevirtual	Method scala/xml/Utility$.toXML$default$2:()Lscala/xml/NamespaceBinding;
	astore_2
	getstatic	Field scala/xml/Utility$.MODULE$:Lscala/xml/Utility$;
	invokevirtual	Method scala/xml/Utility$.toXML$default$3:()Lscala/collection/mutable/StringBuilder;
	astore_3
	getstatic	Field scala/xml/Utility$.MODULE$:Lscala/xml/Utility$;
	invokevirtual	Method scala/xml/Utility$.toXML$default$5:()Z
	istore	4
	getstatic	Field scala/xml/Utility$.MODULE$:Lscala/xml/Utility$;
	invokevirtual	Method scala/xml/Utility$.toXML$default$6:()Z
	istore	5
	getstatic	Field scala/xml/Utility$.MODULE$:Lscala/xml/Utility$;
	invokevirtual	Method scala/xml/Utility$.toXML$default$7:()Z
	istore	6
	getstatic	Field scala/xml/Utility$.MODULE$:Lscala/xml/Utility$;
	aload_0
	aload_2
	aload_3
	iload_1
	iload	4
	iload	5
	iload	6
	invokevirtual	Method scala/xml/Utility$.toXML:(Lscala/xml/Node;Lscala/xml/NamespaceBinding;Lscala/collection/mutable/StringBuilder;ZZZZ)Lscala/collection/mutable/StringBuilder;
	invokevirtual	Method scala/collection/mutable/StringBuilder.toString:()Ljava/lang/String;
	areturn
  Labels:
  LocalVariableTable: 
   Start  Length  Slot  Name   Signature
   0      58      0    this       Lscala/xml/Node;
   0      58      1    stripComments       Z
   7      47      2    x$7       Lscala/xml/NamespaceBinding;
   14      40      3    x$8       Lscala/collection/mutable/StringBuilder;
   22      32      4    x$9       Z
   30      24      5    x$10       Z
   38      16      6    x$11       Z


public java.lang.String toString();
  Signature: ()Ljava/lang/String;
  Code:
   Stack=2, Locals=1, Args_size=1
	aload_0
	iconst_0
	invokevirtual	Method buildString:(Z)Ljava/lang/String;
	areturn
  Labels:

public scala.collection.mutable.StringBuilder nameToString(scala.collection.mutable.StringBuilder);
  Signature: (Lscala/collection/mutable/StringBuilder;)Lscala/collection/mutable/StringBuilder;
  Code:
   Stack=2, Locals=2, Args_size=2
	aload_0
	invokevirtual	Method prefix:()Ljava/lang/String;
	ifnonnull	l1 // aload_1
	getstatic	Field scala/runtime/BoxedUnit.UNIT:Lscala/runtime/BoxedUnit;
	goto	l2 // pop
l1	aload_1
	aload_0
	invokevirtual	Method prefix:()Ljava/lang/String;
	invokevirtual	Method scala/collection/mutable/StringBuilder.append:(Ljava/lang/String;)Lscala/collection/mutable/StringBuilder;
	pop
	aload_1
	ldc	int 58
	invokevirtual	Method scala/collection/mutable/StringBuilder.append:(C)Lscala/collection/mutable/StringBuilder;
l2	pop
	aload_1
	aload_0
	invokevirtual	Method label:()Ljava/lang/String;
	invokevirtual	Method scala/collection/mutable/StringBuilder.append:(Ljava/lang/String;)Lscala/collection/mutable/StringBuilder;
	areturn
  Labels:
   	l1 = 13 // aload_1
   	l2 = 28 // pop
  LocalVariableTable: 
   Start  Length  Slot  Name   Signature
   0      38      0    this       Lscala/xml/Node;
   0      38      1    sb       Lscala/collection/mutable/StringBuilder;


public scala.xml.TypeSymbol xmlType();
  Signature: ()Lscala/xml/TypeSymbol;
  Code:
   Stack=1, Locals=1, Args_size=1
	aconst_null
	areturn
  Labels:

public java.lang.String text();
  Signature: ()Ljava/lang/String;
  Code:
   Stack=1, Locals=1, Args_size=1
	aload_0
	invokespecial	Method scala/xml/NodeSeq.text:()Ljava/lang/String;
	areturn
  Labels:

private final scala.collection.Seq noEmpties$1(scala.collection.Seq);
  Signature: (Lscala/collection/Seq;)Lscala/collection/Seq;
  Code:
   Stack=4, Locals=2, Args_size=2
	aload_1
	new	class scala/xml/Node$$anonfun$noEmpties$1$1
	dup
	aload_0
	invokespecial	Method scala/xml/Node$$anonfun$noEmpties$1$1."<init>":(Lscala/xml/Node;)V
	invokeinterface	InterfaceMethod scala/collection/TraversableLike.filter:(Lscala/Function1;)Ljava/lang/Object;
	checkcast	class scala/collection/Seq
	areturn
  Labels:
  LocalVariableTable: 
   Start  Length  Slot  Name   Signature
   0      18      0    this       Lscala/xml/Node;
   0      18      1    xs       Lscala/collection/Seq;


public scala.xml.Node();
  Signature: ()V
  Code:
   Stack=1, Locals=1, Args_size=1
	aload_0
	invokespecial	Method scala/xml/NodeSeq."<init>":()V
	return
  Labels:

}

