Compiled from "NodeSeq.scala"
public final class scala.xml.NodeSeq$$anon$2 extends java.lang.Object implements scala.collection.generic.CanBuildFrom
  SourceFile: "NodeSeq.scala"
  Signature: length = 0x2
   00 27 
  Scala: length = 0x
   
  InnerClass: 
   public final #42= #16 of #14; //$anon$2=class scala/xml/NodeSeq$$anon$2 of class scala/xml/NodeSeq
  minor version: 0
  major version: 49
  Constant pool:
const #1 = Asciz	SourceFile;
const #2 = Asciz	NodeSeq.scala;
const #3 = Asciz	<init>;
const #4 = Asciz	()V;
const #5 = Asciz	Code;
const #6 = Asciz	LineNumberTable;
const #7 = Asciz	java/lang/Object;
const #8 = class	#7;	//  java/lang/Object
const #9 = NameAndType	#3:#4;//  "<init>":()V
const #10 = Method	#8.#9;	//  java/lang/Object."<init>":()V
const #11 = Asciz	apply;
const #12 = Asciz	(Ljava/lang/Object;)Lscala/collection/mutable/Builder;;
const #13 = Asciz	scala/xml/NodeSeq;
const #14 = class	#13;	//  scala/xml/NodeSeq
const #15 = Asciz	scala/xml/NodeSeq$$anon$2;
const #16 = class	#15;	//  scala/xml/NodeSeq$$anon$2
const #17 = Asciz	(Lscala/xml/NodeSeq;)Lscala/collection/mutable/Builder;;
const #18 = NameAndType	#11:#17;//  apply:(Lscala/xml/NodeSeq;)Lscala/collection/mutable/Builder;
const #19 = Method	#16.#18;	//  scala/xml/NodeSeq$$anon$2.apply:(Lscala/xml/NodeSeq;)Lscala/collection/mutable/Builder;
const #20 = Asciz	this;
const #21 = Asciz	Lscala/xml/NodeSeq$$anon$2;;
const #22 = Asciz	from;
const #23 = Asciz	Ljava/lang/Object;;
const #24 = Asciz	LocalVariableTable;
const #25 = Asciz	()Lscala/collection/mutable/Builder;;
const #26 = Asciz	scala/xml/NodeSeq$;
const #27 = class	#26;	//  scala/xml/NodeSeq$
const #28 = Asciz	MODULE$;
const #29 = Asciz	Lscala/xml/NodeSeq$;;
const #30 = NameAndType	#28:#29;//  MODULE$:Lscala/xml/NodeSeq$;
const #31 = Field	#27.#30;	//  scala/xml/NodeSeq$.MODULE$:Lscala/xml/NodeSeq$;
const #32 = Asciz	newBuilder;
const #33 = NameAndType	#32:#25;//  newBuilder:()Lscala/collection/mutable/Builder;
const #34 = Method	#27.#33;	//  scala/xml/NodeSeq$.newBuilder:()Lscala/collection/mutable/Builder;
const #35 = Asciz	()Lscala/collection/mutable/Builder<Lscala/xml/Node;Lscala/xml/NodeSeq;>;;
const #36 = Asciz	Signature;
const #37 = Asciz	Lscala/xml/NodeSeq;;
const #38 = Asciz	(Lscala/xml/NodeSeq;)Lscala/collection/mutable/Builder<Lscala/xml/Node;Lscala/xml/NodeSeq;>;;
const #39 = Asciz	Ljava/lang/Object;Lscala/collection/generic/CanBuildFrom<Lscala/xml/NodeSeq;Lscala/xml/Node;Lscala/xml/NodeSeq;>;;
const #40 = Asciz	Scala;
const #41 = Asciz	InnerClasses;
const #42 = Asciz	$anon$2;
const #43 = Asciz	scala/collection/generic/CanBuildFrom;
const #44 = class	#43;	//  scala/collection/generic/CanBuildFrom

{
public scala.xml.NodeSeq$$anon$2();
  Code:
   Stack=1, Locals=1, Args_size=1
   0:	aload_0
   1:	invokespecial	#10; //Method java/lang/Object."<init>":()V
   4:	return
  LineNumberTable: 
   line 32: 0


public scala.collection.mutable.Builder apply(java.lang.Object);
  Code:
   Stack=2, Locals=2, Args_size=2
   0:	aload_0
   1:	aload_1
   2:	checkcast	#14; //class scala/xml/NodeSeq
   5:	invokevirtual	#19; //Method apply:(Lscala/xml/NodeSeq;)Lscala/collection/mutable/Builder;
   8:	areturn
  LineNumberTable: 
   line 32: 0

  LocalVariableTable: 
   Start  Length  Slot  Name   Signature
   0      9      0    this       Lscala/xml/NodeSeq$$anon$2;
   0      9      1    from       Ljava/lang/Object;


public scala.collection.mutable.Builder apply();
  Code:
   Stack=1, Locals=1, Args_size=1
   0:	getstatic	#31; //Field scala/xml/NodeSeq$.MODULE$:Lscala/xml/NodeSeq$;
   3:	invokevirtual	#34; //Method scala/xml/NodeSeq$.newBuilder:()Lscala/collection/mutable/Builder;
   6:	areturn
  LineNumberTable: 
   line 34: 0

  Signature: length = 0x2
   00 23 

public scala.collection.mutable.Builder apply(scala.xml.NodeSeq);
  Code:
   Stack=1, Locals=2, Args_size=2
   0:	getstatic	#31; //Field scala/xml/NodeSeq$.MODULE$:Lscala/xml/NodeSeq$;
   3:	invokevirtual	#34; //Method scala/xml/NodeSeq$.newBuilder:()Lscala/collection/mutable/Builder;
   6:	areturn
  LineNumberTable: 
   line 33: 0

  LocalVariableTable: 
   Start  Length  Slot  Name   Signature
   0      7      0    this       Lscala/xml/NodeSeq$$anon$2;
   0      7      1    from       Lscala/xml/NodeSeq;

  Signature: length = 0x2
   00 26 

}

