Compiled from "NodeSeq.scala"
public final class scala.xml.NodeSeq$$anonfun$$bslash$2 extends scala.runtime.AbstractFunction1 implements java.io.Serializable
  SourceFile: "NodeSeq.scala"
  Scala: length = 0x
   
  InnerClass: 
   public final $anonfun$$bslash$2=class scala/xml/NodeSeq$$anonfun$$bslash$2 of class scala/xml/NodeSeq
  minor version: 0
  major version: 49
  Constant pool:
Asciz	SourceFile;
Asciz	NodeSeq.scala;
Asciz	<clinit>;
Asciz	()V;
Asciz	Code;
Asciz	serialVersionUID;
Asciz	J;
Asciz	scala/xml/NodeSeq$$anonfun$$bslash$2;
class	scala/xml/NodeSeq$$anonfun$$bslash$2
NameAndType	serialVersionUID:J
Field	scala/xml/NodeSeq$$anonfun$$bslash$2.serialVersionUID:J
Asciz	that$1;
Asciz	Ljava/lang/String;;
Asciz	<init>;
Asciz	(Lscala/xml/NodeSeq;Ljava/lang/String;)V;
Asciz	LineNumberTable;
NameAndType	that$1:Ljava/lang/String;
Field	scala/xml/NodeSeq$$anonfun$$bslash$2.that$1:Ljava/lang/String;
Asciz	scala/runtime/AbstractFunction1;
class	scala/runtime/AbstractFunction1
NameAndType	"<init>":()V
Method	scala/runtime/AbstractFunction1."<init>":()V
Asciz	this;
Asciz	Lscala/xml/NodeSeq$$anonfun$$bslash$2;;
Asciz	$outer;
Asciz	Lscala/xml/NodeSeq;;
Asciz	LocalVariableTable;
Asciz	apply;
Asciz	(Ljava/lang/Object;)Ljava/lang/Object;;
Asciz	scala/xml/Node;
class	scala/xml/Node
Asciz	(Lscala/xml/Node;)Z;
NameAndType	apply:(Lscala/xml/Node;)Z
Method	scala/xml/NodeSeq$$anonfun$$bslash$2.apply:(Lscala/xml/Node;)Z
Asciz	scala/runtime/BoxesRunTime;
class	scala/runtime/BoxesRunTime
Asciz	boxToBoolean;
Asciz	(Z)Ljava/lang/Boolean;;
NameAndType	boxToBoolean:(Z)Ljava/lang/Boolean;
Method	scala/runtime/BoxesRunTime.boxToBoolean:(Z)Ljava/lang/Boolean;
Asciz	v1;
Asciz	Ljava/lang/Object;;
Asciz	label;
Asciz	()Ljava/lang/String;;
NameAndType	label:()Ljava/lang/String;
Method	scala/xml/Node.label:()Ljava/lang/String;
Asciz	java/lang/Object;
class	java/lang/Object
Asciz	equals;
Asciz	(Ljava/lang/Object;)Z;
NameAndType	equals:(Ljava/lang/Object;)Z
Method	java/lang/Object.equals:(Ljava/lang/Object;)Z
Asciz	Scala;
Asciz	InnerClasses;
Asciz	scala/xml/NodeSeq;
class	scala/xml/NodeSeq
Asciz	$anonfun$$bslash$2;
Asciz	java/io/Serializable;
class	java/io/Serializable

{
public static final long serialVersionUID;
  Signature: J

public final java.lang.String that$1;
  Signature: Ljava/lang/String;

public static {};
  Signature: ()V
  Code:
   Stack=2, Locals=0, Args_size=0
	lconst_0
	putstatic	Field serialVersionUID:J
	return
  Labels:

public scala.xml.NodeSeq$$anonfun$$bslash$2(scala.xml.NodeSeq, java.lang.String);
  Signature: (Lscala/xml/NodeSeq;Ljava/lang/String;)V
  Code:
   Stack=2, Locals=3, Args_size=3
	aload_0
	aload_2
	putfield	Field that$1:Ljava/lang/String;
	aload_0
	invokespecial	Method scala/runtime/AbstractFunction1."<init>":()V
	return
  Labels:
  LocalVariableTable: 
   Start  Length  Slot  Name   Signature
   0      10      0    this       Lscala/xml/NodeSeq$$anonfun$$bslash$2;
   0      10      1    $outer       Lscala/xml/NodeSeq;


public final java.lang.Object apply(java.lang.Object);
  Signature: (Ljava/lang/Object;)Ljava/lang/Object;
  Code:
   Stack=2, Locals=3, Args_size=2
	aload_0
	aload_1
	checkcast	class scala/xml/Node
	invokevirtual	Method apply:(Lscala/xml/Node;)Z
	istore_2
	iload_2
	invokestatic	Method scala/runtime/BoxesRunTime.boxToBoolean:(Z)Ljava/lang/Boolean;
	areturn
  Labels:
  LocalVariableTable: 
   Start  Length  Slot  Name   Signature
   0      14      0    this       Lscala/xml/NodeSeq$$anonfun$$bslash$2;
   0      14      1    v1       Ljava/lang/Object;


public final boolean apply(scala.xml.Node);
  Signature: (Lscala/xml/Node;)Z
  Code:
   Stack=2, Locals=3, Args_size=2
	aload_1
	invokevirtual	Method scala/xml/Node.label:()Ljava/lang/String;
	aload_0
	getfield	Field that$1:Ljava/lang/String;
	astore_2
	dup
	ifnonnull	l1 // aload_2
	pop
	aload_2
	ifnull	l2 // iconst_1
	goto	l3 // iconst_0
l1	aload_2
	invokevirtual	Method java/lang/Object.equals:(Ljava/lang/Object;)Z
	ifeq	l3 // iconst_0
l2	iconst_1
	goto	l4 // ireturn
l3	iconst_0
l4	ireturn
  Labels:
   	l1 = 21 // aload_2
   	l2 = 28 // iconst_1
   	l3 = 32 // iconst_0
   	l4 = 33 // ireturn

}

