Compiled from "Null.scala"
public final class scala.xml.Null extends java.lang.Object
  SourceFile: "Null.scala"
  ScalaSig: length = 0x614
   05 00 FFFFFF81 5C 07 05 01 02 FFFFFF88 42 07 01 04 4E 75 6C
   6C 0A 02 03 04 01 03 78 6D 6C 0A 01 05 01 05 73
   63 61 6C 61 03 00 10 02 08 09 0D 01 02 06 08 0A
   02 FFFFFF84 FFFFFF80 FFFFFF80 FFFFFF88 42 0B 02 04 4E 75 6C 6C 13 04 09
   0C 0F 13 10 02 08 0D 09 02 0E 02 02 08 4D 65 74
   61 44 61 74 61 10 02 10 11 0D 01 04 09 02 12 04
   02 0B 53 63 61 6C 61 4F 62 6A 65 63 74 10 02 10
   14 09 02 15 04 02 07 50 72 6F 64 75 63 74 08 05
   17 09 FFFFFF84 00 18 01 06 3C 69 6E 69 74 3E 14 01 07
   08 05 1A 09 FFFFFF84 20 1B 01 08 69 74 65 72 61 74 6F
   72 15 01 1C 12 03 1D 25 2D 06 08 1E 00 FFFFFF84 FFFFFF80 FFFFFF80
   FFFFFF80 00 1C 02 0C 3C 72 65 66 69 6E 65 6D 65 6E 74
   3E 09 02 20 21 01 06 65 6D 70 74 79 20 0A 02 22
   23 01 08 49 74 65 72 61 74 6F 72 0A 02 24 04 01
   0A 63 6F 6C 6C 65 63 74 69 6F 6E 10 02 26 2B 0D
   01 27 0A 02 28 29 01 04 6C 61 6E 67 0A 01 2A 01
   04 6A 61 76 61 09 02 2C 27 02 06 4F 62 6A 65 63
   74 10 03 2E 2F 31 0D 01 23 09 02 30 23 02 08 49
   74 65 72 61 74 6F 72 10 02 10 32 09 02 33 04 02
   07 4E 6F 74 68 69 6E 67 08 05 35 09 FFFFFF84 20 36 01
   06 61 70 70 65 6E 64 14 03 0C 37 39 08 05 38 34
   FFFFFFC0 00 0C 01 01 6D 08 07 3A 34 FFFFFF90 FFFFFF80 FFFFFFC0 00 3B 01
   05 73 63 6F 70 65 10 02 08 3C 09 02 3D 02 02 10
   4E 61 6D 65 73 70 61 63 65 42 69 6E 64 69 6E 67
   08 05 3F 09 FFFFFF84 20 40 01 06 66 69 6C 74 65 72 14
   02 0C 41 08 05 42 3E FFFFFFC0 00 43 01 01 66 10 04 10
   44 0C 46 09 02 45 04 02 09 46 75 6E 63 74 69 6F
   6E 31 10 02 10 47 09 02 48 04 02 07 42 6F 6F 6C
   65 61 6E 08 05 4A 09 FFFFFF84 00 4B 01 04 63 6F 70 79
   14 02 0C 4C 08 05 4D 49 FFFFFFC0 00 0C 01 04 6E 65 78
   74 08 05 4F 09 FFFFFF84 00 50 01 0C 67 65 74 4E 61 6D
   65 73 70 61 63 65 14 02 51 53 10 02 10 52 09 02
   0A 04 08 05 54 4E FFFFFFC0 00 55 01 05 6F 77 6E 65 72
   10 02 08 56 09 02 57 02 02 04 4E 6F 64 65 08 05
   59 09 FFFFFF84 20 5A 01 07 68 61 73 4E 65 78 74 15 01
   46 08 05 4D 09 FFFFFF84 00 5C 15 01 51 08 05 5E 09 FFFFFF84
   00 5C 01 03 6B 65 79 08 05 60 09 FFFFFF84 00 5C 01 05
   76 61 6C 75 65 08 05 62 09 FFFFFF84 00 5A 01 0A 69 73
   50 72 65 66 69 78 65 64 08 05 64 09 FFFFFF84 20 65 01
   06 6C 65 6E 67 74 68 15 01 66 10 02 10 67 09 02
   68 04 02 03 49 6E 74 08 05 64 09 FFFFFF84 20 6A 14 02
   66 6B 08 05 6C 69 FFFFFFC0 00 66 01 01 69 08 05 6E 09
   FFFFFF84 20 6F 01 0D 73 74 72 69 63 74 5F 24 65 71 24
   65 71 14 02 46 70 08 05 71 6D FFFFFFC0 00 72 01 05 6F
   74 68 65 72 10 02 08 73 09 02 74 02 02 08 45 71
   75 61 6C 69 74 79 08 05 76 09 FFFFFF84 20 77 01 10 62
   61 73 69 73 46 6F 72 48 61 73 68 43 6F 64 65 15
   01 78 10 05 79 FFFFFF81 01 FFFFFF81 04 0E 02 7A 7F 0E 02 7B
   7E 0D 01 7C 0A 02 7D 06 01 06 3C 72 6F 6F 74 3E
   09 01 05 09 03 FFFFFF81 00 04 01 07 70 61 63 6B 61 67
   65 09 04 FFFFFF81 02 FFFFFF81 03 02 03 53 65 71 0A 03 FFFFFF81 00
   04 10 03 10 FFFFFF81 05 09 03 FFFFFF81 06 04 02 03 41 6E 79
   08 07 FFFFFF81 08 09 FFFFFF84 00 FFFFFF81 09 01 05 61 70 70 6C 79
   14 07 51 FFFFFF81 0A FFFFFF81 13 FFFFFF81 14 08 08 FFFFFF81 0B FFFFFF81 07 FFFFFFC0
   00 FFFFFF81 0C 01 09 6E 61 6D 65 73 70 61 63 65 10 04
   FFFFFF81 0D FFFFFF81 10 0E 03 10 FFFFFF81 0E 09 03 FFFFFF81 0F 04 01 06
   50 72 65 64 65 66 09 04 FFFFFF81 11 FFFFFF81 12 02 06 53 74
   72 69 6E 67 0A 03 FFFFFF81 0F 04 08 06 3A FFFFFF81 07 FFFFFFC0 00
   3B 08 07 5E FFFFFF81 07 FFFFFFC0 00 FFFFFF81 0C 08 07 FFFFFF81 08 09 FFFFFF84
   00 FFFFFF81 16 14 03 51 FFFFFF81 17 08 07 5E FFFFFF81 15 FFFFFFC0 00 FFFFFF81
   0C 08 07 FFFFFF81 19 09 FFFFFF84 00 FFFFFF81 1A 01 09 74 6F 53 74
   72 69 6E 67 31 14 04 FFFFFF81 1B FFFFFF81 1E 10 03 10 FFFFFF81 1C
   09 03 FFFFFF81 1D 04 02 04 55 6E 69 74 08 08 FFFFFF81 1F FFFFFF81
   18 FFFFFFC0 00 FFFFFF81 20 01 02 73 62 10 03 79 FFFFFF81 21 09 04
   FFFFFF81 22 FFFFFF81 03 02 0D 53 74 72 69 6E 67 42 75 69 6C
   64 65 72 08 07 FFFFFF81 19 09 FFFFFF84 20 FFFFFF81 24 14 02 FFFFFF81 0C
   08 07 FFFFFF81 26 09 FFFFFF84 20 FFFFFF81 24 01 08 74 6F 53 74 72
   69 6E 67 08 07 FFFFFF81 28 09 FFFFFF84 20 FFFFFF81 29 01 0B 62 75
   69 6C 64 53 74 72 69 6E 67 14 04 FFFFFF81 20 FFFFFF81 2A 08
   08 FFFFFF81 1F FFFFFF81 27 FFFFFFC0 00 FFFFFF81 20 08 07 FFFFFF81 2C 09 FFFFFF84 20
   FFFFFF81 2D 01 0A 77 65 6C 6C 66 6F 72 6D 65 64 14 03
   46 FFFFFF81 2E 08 06 3A FFFFFF81 2B FFFFFFC0 00 3B 08 07 FFFFFF81 30 09
   FFFFFF84 00 FFFFFF81 31 01 06 72 65 6D 6F 76 65 14 03 07 FFFFFF81
   32 08 07 5E FFFFFF81 2F FFFFFFC0 00 FFFFFF81 0C 08 07 FFFFFF81 30 09 FFFFFF84
   00 FFFFFF81 34 14 07 07 FFFFFF81 35 FFFFFF81 36 FFFFFF81 37 08 08 FFFFFF81 0B
   FFFFFF81 33 FFFFFFC0 00 FFFFFF81 0C 08 06 3A FFFFFF81 33 FFFFFFC0 00 3B 08 07
   5E FFFFFF81 33 FFFFFFC0 00 FFFFFF81 0C 08 09 FFFFFF81 39 09 FFFFFF91 FFFFFF80 FFFFFF84 20
   FFFFFF81 3A 01 10 61 70 70 65 6E 64 24 64 65 66 61 75
   6C 74 24 32 15 02 FFFFFF81 3B 2A 03 3B FFFFFF81 3C 2B 02 FFFFFF81
   3D 10 04 FFFFFF81 3E FFFFFF81 43 0D 02 FFFFFF81 3F 0A 04 FFFFFF81 40 FFFFFF81
   41 01 09 75 6E 63 68 65 63 6B 65 64 0A 03 FFFFFF81 42
   04 01 0A 61 6E 6E 6F 74 61 74 69 6F 6E 09 04 FFFFFF81
   44 FFFFFF81 3F 02 11 75 6E 63 68 65 63 6B 65 64 56 61
   72 69 61 6E 63 65 08 0A FFFFFF81 46 09 FFFFFF84 FFFFFF80 FFFFFF80 FFFFFF84 20
   FFFFFF81 47 01 0D 70 72 6F 64 75 63 74 50 72 65 66 69
   78 15 02 FFFFFF81 48 10 03 26 FFFFFF81 49 09 03 FFFFFF81 11 27 08
   09 FFFFFF81 4B 09 FFFFFF84 FFFFFF80 FFFFFF80 FFFFFF84 20 65 01 0C 70 72 6F 64
   75 63 74 41 72 69 74 79 08 0A FFFFFF81 4D 09 FFFFFF84 FFFFFF80 FFFFFF80
   FFFFFF84 20 FFFFFF81 4E 01 0E 70 72 6F 64 75 63 74 45 6C 65
   6D 65 6E 74 14 04 FFFFFF81 04 FFFFFF81 4F 08 09 FFFFFF81 50 FFFFFF81 4C
   FFFFFF81 FFFFFF80 FFFFFFC0 00 66 01 03 78 24 31 08 0A FFFFFF81 52 09 FFFFFF84
   FFFFFF80 FFFFFF80 FFFFFF84 20 FFFFFF81 53 01 12 70 72 6F 64 75 63 74 45
   6C 65 6D 65 6E 74 4E 61 6D 65 14 04 FFFFFF81 48 FFFFFF81 54
   08 09 FFFFFF81 50 FFFFFF81 51 FFFFFF81 FFFFFF80 FFFFFFC0 00 66 08 0A FFFFFF81 56 09
   FFFFFF84 FFFFFF80 FFFFFF80 FFFFFF84 08 FFFFFF81 57 01 0B 72 65 61 64 52 65 73
   6F 6C 76 65 14 01 25 28 03 09 FFFFFF81 59 10 03 10 FFFFFF81
   5A 09 03 FFFFFF81 5B 04 02 0C 73 65 72 69 61 6C 69 7A
   61 62 6C 65 
  InnerClass: 
   public abstract $less$colon$less=class scala/Predef$$less$colon$less of class scala/Predef
   public WithFilter=class scala/collection/TraversableLike$WithFilter of class scala/collection/TraversableLike
  minor version: 0
  major version: 49
  Constant pool:
Asciz	SourceFile;
Asciz	Null.scala;
Asciz	productElements;
Asciz	()Lscala/collection/Iterator;;
Asciz	Code;
Asciz	scala/xml/Null$;
class	scala/xml/Null$
Asciz	MODULE$;
Asciz	Lscala/xml/Null$;;
NameAndType	MODULE$:Lscala/xml/Null$;
Field	scala/xml/Null$.MODULE$:Lscala/xml/Null$;
NameAndType	productElements:()Lscala/collection/Iterator;
Method	scala/xml/Null$.productElements:()Lscala/collection/Iterator;
Asciz	Deprecated;
Asciz	productIterator;
NameAndType	productIterator:()Lscala/collection/Iterator;
Method	scala/xml/Null$.productIterator:()Lscala/collection/Iterator;
Asciz	productElementName;
Asciz	(I)Ljava/lang/String;;
NameAndType	productElementName:(I)Ljava/lang/String;
Method	scala/xml/Null$.productElementName:(I)Ljava/lang/String;
Asciz	productElement;
Asciz	(I)Ljava/lang/Object;;
NameAndType	productElement:(I)Ljava/lang/Object;
Method	scala/xml/Null$.productElement:(I)Ljava/lang/Object;
Asciz	productArity;
Asciz	()I;
NameAndType	productArity:()I
Method	scala/xml/Null$.productArity:()I
Asciz	productPrefix;
Asciz	()Ljava/lang/String;;
NameAndType	productPrefix:()Ljava/lang/String;
Method	scala/xml/Null$.productPrefix:()Ljava/lang/String;
Asciz	append$default$2;
Asciz	()Lscala/xml/NamespaceBinding;;
NameAndType	append$default$2:()Lscala/xml/NamespaceBinding;
Method	scala/xml/Null$.append$default$2:()Lscala/xml/NamespaceBinding;
Asciz	remove;
Asciz	(Ljava/lang/String;Lscala/xml/NamespaceBinding;Ljava/lang/String;)Lscala/xml/Null$;;
NameAndType	remove:(Ljava/lang/String;Lscala/xml/NamespaceBinding;Ljava/lang/String;)Lscala/xml/Null$;
Method	scala/xml/Null$.remove:(Ljava/lang/String;Lscala/xml/NamespaceBinding;Ljava/lang/String;)Lscala/xml/Null$;
Asciz	(Ljava/lang/String;)Lscala/xml/Null$;;
NameAndType	remove:(Ljava/lang/String;)Lscala/xml/Null$;
Method	scala/xml/Null$.remove:(Ljava/lang/String;)Lscala/xml/Null$;
Asciz	wellformed;
Asciz	(Lscala/xml/NamespaceBinding;)Z;
NameAndType	wellformed:(Lscala/xml/NamespaceBinding;)Z
Method	scala/xml/Null$.wellformed:(Lscala/xml/NamespaceBinding;)Z
Asciz	buildString;
Asciz	(Lscala/collection/mutable/StringBuilder;)Lscala/collection/mutable/StringBuilder;;
NameAndType	buildString:(Lscala/collection/mutable/StringBuilder;)Lscala/collection/mutable/StringBuilder;
Method	scala/xml/Null$.buildString:(Lscala/collection/mutable/StringBuilder;)Lscala/collection/mutable/StringBuilder;
Asciz	toString1;
NameAndType	toString1:()Ljava/lang/String;
Method	scala/xml/Null$.toString1:()Ljava/lang/String;
Asciz	(Lscala/collection/mutable/StringBuilder;)V;
NameAndType	toString1:(Lscala/collection/mutable/StringBuilder;)V
Method	scala/xml/Null$.toString1:(Lscala/collection/mutable/StringBuilder;)V
Asciz	apply;
Asciz	(Ljava/lang/String;)Lscala/runtime/Null$;;
NameAndType	apply:(Ljava/lang/String;)Lscala/runtime/Null$;
Method	scala/xml/Null$.apply:(Ljava/lang/String;)Lscala/runtime/Null$;
Asciz	(Ljava/lang/String;Lscala/xml/NamespaceBinding;Ljava/lang/String;)Lscala/runtime/Null$;;
NameAndType	apply:(Ljava/lang/String;Lscala/xml/NamespaceBinding;Ljava/lang/String;)Lscala/runtime/Null$;
Method	scala/xml/Null$.apply:(Ljava/lang/String;Lscala/xml/NamespaceBinding;Ljava/lang/String;)Lscala/runtime/Null$;
Asciz	basisForHashCode;
Asciz	()Lscala/collection/Seq;;
NameAndType	basisForHashCode:()Lscala/collection/Seq;
Method	scala/xml/Null$.basisForHashCode:()Lscala/collection/Seq;
Asciz	()Lscala/collection/Seq<Ljava/lang/Object;>;;
Asciz	Signature;
Asciz	strict_$eq$eq;
Asciz	(Lscala/xml/Equality;)Z;
NameAndType	strict_$eq$eq:(Lscala/xml/Equality;)Z
Method	scala/xml/Null$.strict_$eq$eq:(Lscala/xml/Equality;)Z
Asciz	length;
Asciz	(I)I;
NameAndType	length:(I)I
Method	scala/xml/Null$.length:(I)I
NameAndType	length:()I
Method	scala/xml/Null$.length:()I
Asciz	isPrefixed;
Asciz	()Z;
NameAndType	isPrefixed:()Z
Method	scala/xml/Null$.isPrefixed:()Z
Asciz	value;
Asciz	()Lscala/runtime/Null$;;
NameAndType	value:()Lscala/runtime/Null$;
Method	scala/xml/Null$.value:()Lscala/runtime/Null$;
Asciz	key;
NameAndType	key:()Lscala/runtime/Null$;
Method	scala/xml/Null$.key:()Lscala/runtime/Null$;
Asciz	next;
NameAndType	next:()Lscala/runtime/Null$;
Method	scala/xml/Null$.next:()Lscala/runtime/Null$;
Asciz	hasNext;
NameAndType	hasNext:()Z
Method	scala/xml/Null$.hasNext:()Z
Asciz	getNamespace;
Asciz	(Lscala/xml/Node;)Lscala/runtime/Null$;;
NameAndType	getNamespace:(Lscala/xml/Node;)Lscala/runtime/Null$;
Method	scala/xml/Null$.getNamespace:(Lscala/xml/Node;)Lscala/runtime/Null$;
Asciz	copy;
Asciz	(Lscala/xml/MetaData;)Lscala/xml/MetaData;;
NameAndType	copy:(Lscala/xml/MetaData;)Lscala/xml/MetaData;
Method	scala/xml/Null$.copy:(Lscala/xml/MetaData;)Lscala/xml/MetaData;
Asciz	filter;
Asciz	(Lscala/Function1;)Lscala/xml/MetaData;;
NameAndType	filter:(Lscala/Function1;)Lscala/xml/MetaData;
Method	scala/xml/Null$.filter:(Lscala/Function1;)Lscala/xml/MetaData;
Asciz	(Lscala/Function1<Lscala/xml/MetaData;Ljava/lang/Boolean;>;)Lscala/xml/MetaData;;
Asciz	append;
Asciz	(Lscala/xml/MetaData;Lscala/xml/NamespaceBinding;)Lscala/xml/MetaData;;
NameAndType	append:(Lscala/xml/MetaData;Lscala/xml/NamespaceBinding;)Lscala/xml/MetaData;
Method	scala/xml/Null$.append:(Lscala/xml/MetaData;Lscala/xml/NamespaceBinding;)Lscala/xml/MetaData;
Asciz	iterator;
NameAndType	iterator:()Lscala/collection/Iterator;
Method	scala/xml/Null$.iterator:()Lscala/collection/Iterator;
Asciz	withFilter;
Asciz	(Lscala/Function1;)Lscala/collection/TraversableLike$WithFilter;;
NameAndType	withFilter:(Lscala/Function1;)Lscala/collection/TraversableLike$WithFilter;
Method	scala/xml/Null$.withFilter:(Lscala/Function1;)Lscala/collection/TraversableLike$WithFilter;
Asciz	stringPrefix;
NameAndType	stringPrefix:()Ljava/lang/String;
Method	scala/xml/Null$.stringPrefix:()Ljava/lang/String;
Asciz	addString;
NameAndType	addString:(Lscala/collection/mutable/StringBuilder;)Lscala/collection/mutable/StringBuilder;
Method	scala/xml/Null$.addString:(Lscala/collection/mutable/StringBuilder;)Lscala/collection/mutable/StringBuilder;
Asciz	(Lscala/collection/mutable/StringBuilder;Ljava/lang/String;)Lscala/collection/mutable/StringBuilder;;
NameAndType	addString:(Lscala/collection/mutable/StringBuilder;Ljava/lang/String;)Lscala/collection/mutable/StringBuilder;
Method	scala/xml/Null$.addString:(Lscala/collection/mutable/StringBuilder;Ljava/lang/String;)Lscala/collection/mutable/StringBuilder;
Asciz	(Lscala/collection/mutable/StringBuilder;Ljava/lang/String;Ljava/lang/String;Ljava/lang/String;)Lscala/collection/mutable/StringBuilder;;
NameAndType	addString:(Lscala/collection/mutable/StringBuilder;Ljava/lang/String;Ljava/lang/String;Ljava/lang/String;)Lscala/collection/mutable/StringBuilder;
Method	scala/xml/Null$.addString:(Lscala/collection/mutable/StringBuilder;Ljava/lang/String;Ljava/lang/String;Ljava/lang/String;)Lscala/collection/mutable/StringBuilder;
Asciz	mkString;
NameAndType	mkString:()Ljava/lang/String;
Method	scala/xml/Null$.mkString:()Ljava/lang/String;
Asciz	(Ljava/lang/String;)Ljava/lang/String;;
NameAndType	mkString:(Ljava/lang/String;)Ljava/lang/String;
Method	scala/xml/Null$.mkString:(Ljava/lang/String;)Ljava/lang/String;
Asciz	(Ljava/lang/String;Ljava/lang/String;Ljava/lang/String;)Ljava/lang/String;;
NameAndType	mkString:(Ljava/lang/String;Ljava/lang/String;Ljava/lang/String;)Ljava/lang/String;
Method	scala/xml/Null$.mkString:(Ljava/lang/String;Ljava/lang/String;Ljava/lang/String;)Ljava/lang/String;
Asciz	toMap;
Asciz	(Lscala/Predef$$less$colon$less;)Lscala/collection/immutable/Map;;
NameAndType	toMap:(Lscala/Predef$$less$colon$less;)Lscala/collection/immutable/Map;
Method	scala/xml/Null$.toMap:(Lscala/Predef$$less$colon$less;)Lscala/collection/immutable/Map;
Asciz	toSet;
Asciz	()Lscala/collection/immutable/Set;;
NameAndType	toSet:()Lscala/collection/immutable/Set;
Method	scala/xml/Null$.toSet:()Lscala/collection/immutable/Set;
Asciz	toIndexedSeq;
Asciz	()Lscala/collection/mutable/IndexedSeq;;
NameAndType	toIndexedSeq:()Lscala/collection/mutable/IndexedSeq;
Method	scala/xml/Null$.toIndexedSeq:()Lscala/collection/mutable/IndexedSeq;
Asciz	toSeq;
NameAndType	toSeq:()Lscala/collection/Seq;
Method	scala/xml/Null$.toSeq:()Lscala/collection/Seq;
Asciz	toList;
Asciz	()Lscala/collection/immutable/List;;
NameAndType	toList:()Lscala/collection/immutable/List;
Method	scala/xml/Null$.toList:()Lscala/collection/immutable/List;
Asciz	toArray;
Asciz	(Lscala/reflect/ClassManifest;)Ljava/lang/Object;;
NameAndType	toArray:(Lscala/reflect/ClassManifest;)Ljava/lang/Object;
Method	scala/xml/Null$.toArray:(Lscala/reflect/ClassManifest;)Ljava/lang/Object;
Asciz	copyToArray;
Asciz	(Ljava/lang/Object;)V;
NameAndType	copyToArray:(Ljava/lang/Object;)V
Method	scala/xml/Null$.copyToArray:(Ljava/lang/Object;)V
Asciz	(Ljava/lang/Object;I)V;
NameAndType	copyToArray:(Ljava/lang/Object;I)V
Method	scala/xml/Null$.copyToArray:(Ljava/lang/Object;I)V
Asciz	copyToBuffer;
Asciz	(Lscala/collection/mutable/Buffer;)V;
NameAndType	copyToBuffer:(Lscala/collection/mutable/Buffer;)V
Method	scala/xml/Null$.copyToBuffer:(Lscala/collection/mutable/Buffer;)V
Asciz	splitAt;
Asciz	(I)Lscala/Tuple2;;
NameAndType	splitAt:(I)Lscala/Tuple2;
Method	scala/xml/Null$.splitAt:(I)Lscala/Tuple2;
Asciz	span;
Asciz	(Lscala/Function1;)Lscala/Tuple2;;
NameAndType	span:(Lscala/Function1;)Lscala/Tuple2;
Method	scala/xml/Null$.span:(Lscala/Function1;)Lscala/Tuple2;
Asciz	dropWhile;
Asciz	(Lscala/Function1;)Ljava/lang/Object;;
NameAndType	dropWhile:(Lscala/Function1;)Ljava/lang/Object;
Method	scala/xml/Null$.dropWhile:(Lscala/Function1;)Ljava/lang/Object;
Asciz	drop;
NameAndType	drop:(I)Ljava/lang/Object;
Method	scala/xml/Null$.drop:(I)Ljava/lang/Object;
Asciz	init;
Asciz	()Ljava/lang/Object;;
NameAndType	init:()Ljava/lang/Object;
Method	scala/xml/Null$.init:()Ljava/lang/Object;
Asciz	lastOption;
Asciz	()Lscala/Option;;
NameAndType	lastOption:()Lscala/Option;
Method	scala/xml/Null$.lastOption:()Lscala/Option;
Asciz	last;
NameAndType	last:()Ljava/lang/Object;
Method	scala/xml/Null$.last:()Ljava/lang/Object;
Asciz	tail;
NameAndType	tail:()Ljava/lang/Object;
Method	scala/xml/Null$.tail:()Ljava/lang/Object;
Asciz	headOption;
NameAndType	headOption:()Lscala/Option;
Method	scala/xml/Null$.headOption:()Lscala/Option;
Asciz	max;
Asciz	(Lscala/math/Ordering;)Ljava/lang/Object;;
NameAndType	max:(Lscala/math/Ordering;)Ljava/lang/Object;
Method	scala/xml/Null$.max:(Lscala/math/Ordering;)Ljava/lang/Object;
Asciz	min;
NameAndType	min:(Lscala/math/Ordering;)Ljava/lang/Object;
Method	scala/xml/Null$.min:(Lscala/math/Ordering;)Ljava/lang/Object;
Asciz	product;
Asciz	(Lscala/math/Numeric;)Ljava/lang/Object;;
NameAndType	product:(Lscala/math/Numeric;)Ljava/lang/Object;
Method	scala/xml/Null$.product:(Lscala/math/Numeric;)Ljava/lang/Object;
Asciz	sum;
NameAndType	sum:(Lscala/math/Numeric;)Ljava/lang/Object;
Method	scala/xml/Null$.sum:(Lscala/math/Numeric;)Ljava/lang/Object;
Asciz	reduceRightOption;
Asciz	(Lscala/Function2;)Lscala/Option;;
NameAndType	reduceRightOption:(Lscala/Function2;)Lscala/Option;
Method	scala/xml/Null$.reduceRightOption:(Lscala/Function2;)Lscala/Option;
Asciz	reduceLeftOption;
NameAndType	reduceLeftOption:(Lscala/Function2;)Lscala/Option;
Method	scala/xml/Null$.reduceLeftOption:(Lscala/Function2;)Lscala/Option;
Asciz	reduceLeft;
Asciz	(Lscala/Function2;)Ljava/lang/Object;;
NameAndType	reduceLeft:(Lscala/Function2;)Ljava/lang/Object;
Method	scala/xml/Null$.reduceLeft:(Lscala/Function2;)Ljava/lang/Object;
Asciz	$colon$bslash;
Asciz	(Ljava/lang/Object;Lscala/Function2;)Ljava/lang/Object;;
NameAndType	$colon$bslash:(Ljava/lang/Object;Lscala/Function2;)Ljava/lang/Object;
Method	scala/xml/Null$.$colon$bslash:(Ljava/lang/Object;Lscala/Function2;)Ljava/lang/Object;
Asciz	$div$colon;
NameAndType	$div$colon:(Ljava/lang/Object;Lscala/Function2;)Ljava/lang/Object;
Method	scala/xml/Null$.$div$colon:(Ljava/lang/Object;Lscala/Function2;)Ljava/lang/Object;
Asciz	foldLeft;
NameAndType	foldLeft:(Ljava/lang/Object;Lscala/Function2;)Ljava/lang/Object;
Method	scala/xml/Null$.foldLeft:(Ljava/lang/Object;Lscala/Function2;)Ljava/lang/Object;
Asciz	count;
Asciz	(Lscala/Function1;)I;
NameAndType	count:(Lscala/Function1;)I
Method	scala/xml/Null$.count:(Lscala/Function1;)I
Asciz	groupBy;
Asciz	(Lscala/Function1;)Lscala/collection/Map;;
NameAndType	groupBy:(Lscala/Function1;)Lscala/collection/Map;
Method	scala/xml/Null$.groupBy:(Lscala/Function1;)Lscala/collection/Map;
Asciz	partition;
NameAndType	partition:(Lscala/Function1;)Lscala/Tuple2;
Method	scala/xml/Null$.partition:(Lscala/Function1;)Lscala/Tuple2;
Asciz	partialMap;
Asciz	(Lscala/PartialFunction;Lscala/collection/generic/CanBuildFrom;)Ljava/lang/Object;;
NameAndType	partialMap:(Lscala/PartialFunction;Lscala/collection/generic/CanBuildFrom;)Ljava/lang/Object;
Method	scala/xml/Null$.partialMap:(Lscala/PartialFunction;Lscala/collection/generic/CanBuildFrom;)Ljava/lang/Object;
Asciz	filterNot;
NameAndType	filterNot:(Lscala/Function1;)Ljava/lang/Object;
Method	scala/xml/Null$.filterNot:(Lscala/Function1;)Ljava/lang/Object;
Asciz	flatMap;
Asciz	(Lscala/Function1;Lscala/collection/generic/CanBuildFrom;)Ljava/lang/Object;;
NameAndType	flatMap:(Lscala/Function1;Lscala/collection/generic/CanBuildFrom;)Ljava/lang/Object;
Method	scala/xml/Null$.flatMap:(Lscala/Function1;Lscala/collection/generic/CanBuildFrom;)Ljava/lang/Object;
Asciz	map;
NameAndType	map:(Lscala/Function1;Lscala/collection/generic/CanBuildFrom;)Ljava/lang/Object;
Method	scala/xml/Null$.map:(Lscala/Function1;Lscala/collection/generic/CanBuildFrom;)Ljava/lang/Object;
Asciz	$plus$plus;
Asciz	(Lscala/collection/Iterator;Lscala/collection/generic/CanBuildFrom;)Ljava/lang/Object;;
NameAndType	$plus$plus:(Lscala/collection/Iterator;Lscala/collection/generic/CanBuildFrom;)Ljava/lang/Object;
Method	scala/xml/Null$.$plus$plus:(Lscala/collection/Iterator;Lscala/collection/generic/CanBuildFrom;)Ljava/lang/Object;
Asciz	(Lscala/collection/Traversable;Lscala/collection/generic/CanBuildFrom;)Ljava/lang/Object;;
NameAndType	$plus$plus:(Lscala/collection/Traversable;Lscala/collection/generic/CanBuildFrom;)Ljava/lang/Object;
Method	scala/xml/Null$.$plus$plus:(Lscala/collection/Traversable;Lscala/collection/generic/CanBuildFrom;)Ljava/lang/Object;
Asciz	hasDefiniteSize;
NameAndType	hasDefiniteSize:()Z
Method	scala/xml/Null$.hasDefiniteSize:()Z
Asciz	nonEmpty;
NameAndType	nonEmpty:()Z
Method	scala/xml/Null$.nonEmpty:()Z
Asciz	repr;
NameAndType	repr:()Ljava/lang/Object;
Method	scala/xml/Null$.repr:()Ljava/lang/Object;
Asciz	transpose;
Asciz	(Lscala/Function1;)Lscala/collection/Traversable;;
NameAndType	transpose:(Lscala/Function1;)Lscala/collection/Traversable;
Method	scala/xml/Null$.transpose:(Lscala/Function1;)Lscala/collection/Traversable;
Asciz	flatten;
NameAndType	flatten:(Lscala/Function1;)Lscala/collection/Traversable;
Method	scala/xml/Null$.flatten:(Lscala/Function1;)Lscala/collection/Traversable;
Asciz	unzip;
NameAndType	unzip:(Lscala/Function1;)Lscala/Tuple2;
Method	scala/xml/Null$.unzip:(Lscala/Function1;)Lscala/Tuple2;
Asciz	genericBuilder;
Asciz	()Lscala/collection/mutable/Builder;;
NameAndType	genericBuilder:()Lscala/collection/mutable/Builder;
Method	scala/xml/Null$.genericBuilder:()Lscala/collection/mutable/Builder;
Asciz	projection;
Asciz	()Lscala/collection/IterableView;;
NameAndType	projection:()Lscala/collection/IterableView;
Method	scala/xml/Null$.projection:()Lscala/collection/IterableView;
Asciz	firstOption;
NameAndType	firstOption:()Lscala/Option;
Method	scala/xml/Null$.firstOption:()Lscala/Option;
Asciz	first;
NameAndType	first:()Ljava/lang/Object;
Method	scala/xml/Null$.first:()Ljava/lang/Object;
Asciz	view;
Asciz	(II)Lscala/collection/IterableView;;
NameAndType	view:(II)Lscala/collection/IterableView;
Method	scala/xml/Null$.view:(II)Lscala/collection/IterableView;
NameAndType	view:()Lscala/collection/IterableView;
Method	scala/xml/Null$.view:()Lscala/collection/IterableView;
Asciz	toStream;
Asciz	()Lscala/collection/immutable/Stream;;
NameAndType	toStream:()Lscala/collection/immutable/Stream;
Method	scala/xml/Null$.toStream:()Lscala/collection/immutable/Stream;
Asciz	sameElements;
Asciz	(Lscala/collection/Iterable;)Z;
NameAndType	sameElements:(Lscala/collection/Iterable;)Z
Method	scala/xml/Null$.sameElements:(Lscala/collection/Iterable;)Z
Asciz	zipWithIndex;
Asciz	(Lscala/collection/generic/CanBuildFrom;)Ljava/lang/Object;;
NameAndType	zipWithIndex:(Lscala/collection/generic/CanBuildFrom;)Ljava/lang/Object;
Method	scala/xml/Null$.zipWithIndex:(Lscala/collection/generic/CanBuildFrom;)Ljava/lang/Object;
Asciz	zipAll;
Asciz	(Lscala/collection/Iterable;Ljava/lang/Object;Ljava/lang/Object;Lscala/collection/generic/CanBuildFrom;)Ljava/lang/Object;;
NameAndType	zipAll:(Lscala/collection/Iterable;Ljava/lang/Object;Ljava/lang/Object;Lscala/collection/generic/CanBuildFrom;)Ljava/lang/Object;
Method	scala/xml/Null$.zipAll:(Lscala/collection/Iterable;Ljava/lang/Object;Ljava/lang/Object;Lscala/collection/generic/CanBuildFrom;)Ljava/lang/Object;
Asciz	zip;
Asciz	(Lscala/collection/Iterable;Lscala/collection/generic/CanBuildFrom;)Ljava/lang/Object;;
NameAndType	zip:(Lscala/collection/Iterable;Lscala/collection/generic/CanBuildFrom;)Ljava/lang/Object;
Method	scala/xml/Null$.zip:(Lscala/collection/Iterable;Lscala/collection/generic/CanBuildFrom;)Ljava/lang/Object;
Asciz	(Ljava/lang/Object;II)V;
NameAndType	copyToArray:(Ljava/lang/Object;II)V
Method	scala/xml/Null$.copyToArray:(Ljava/lang/Object;II)V
Asciz	dropRight;
NameAndType	dropRight:(I)Ljava/lang/Object;
Method	scala/xml/Null$.dropRight:(I)Ljava/lang/Object;
Asciz	takeRight;
NameAndType	takeRight:(I)Ljava/lang/Object;
Method	scala/xml/Null$.takeRight:(I)Ljava/lang/Object;
Asciz	sliding;
Asciz	(II)Lscala/collection/Iterator;;
NameAndType	sliding:(II)Lscala/collection/Iterator;
Method	scala/xml/Null$.sliding:(II)Lscala/collection/Iterator;
Asciz	(I)Lscala/collection/Iterator;;
NameAndType	sliding:(I)Lscala/collection/Iterator;
Method	scala/xml/Null$.sliding:(I)Lscala/collection/Iterator;
Asciz	grouped;
NameAndType	grouped:(I)Lscala/collection/Iterator;
Method	scala/xml/Null$.grouped:(I)Lscala/collection/Iterator;
Asciz	takeWhile;
NameAndType	takeWhile:(Lscala/Function1;)Ljava/lang/Object;
Method	scala/xml/Null$.takeWhile:(Lscala/Function1;)Ljava/lang/Object;
Asciz	slice;
Asciz	(II)Ljava/lang/Object;;
NameAndType	slice:(II)Ljava/lang/Object;
Method	scala/xml/Null$.slice:(II)Ljava/lang/Object;
Asciz	take;
NameAndType	take:(I)Ljava/lang/Object;
Method	scala/xml/Null$.take:(I)Ljava/lang/Object;
Asciz	head;
NameAndType	head:()Ljava/lang/Object;
Method	scala/xml/Null$.head:()Ljava/lang/Object;
Asciz	toIterable;
Asciz	()Lscala/collection/Iterable;;
NameAndType	toIterable:()Lscala/collection/Iterable;
Method	scala/xml/Null$.toIterable:()Lscala/collection/Iterable;
Asciz	reduceRight;
NameAndType	reduceRight:(Lscala/Function2;)Ljava/lang/Object;
Method	scala/xml/Null$.reduceRight:(Lscala/Function2;)Ljava/lang/Object;
Asciz	foldRight;
NameAndType	foldRight:(Ljava/lang/Object;Lscala/Function2;)Ljava/lang/Object;
Method	scala/xml/Null$.foldRight:(Ljava/lang/Object;Lscala/Function2;)Ljava/lang/Object;
Asciz	isEmpty;
NameAndType	isEmpty:()Z
Method	scala/xml/Null$.isEmpty:()Z
Asciz	find;
Asciz	(Lscala/Function1;)Lscala/Option;;
NameAndType	find:(Lscala/Function1;)Lscala/Option;
Method	scala/xml/Null$.find:(Lscala/Function1;)Lscala/Option;
Asciz	exists;
Asciz	(Lscala/Function1;)Z;
NameAndType	exists:(Lscala/Function1;)Z
Method	scala/xml/Null$.exists:(Lscala/Function1;)Z
Asciz	forall;
NameAndType	forall:(Lscala/Function1;)Z
Method	scala/xml/Null$.forall:(Lscala/Function1;)Z
Asciz	foreach;
Asciz	(Lscala/Function1;)V;
NameAndType	foreach:(Lscala/Function1;)V
Method	scala/xml/Null$.foreach:(Lscala/Function1;)V
Asciz	elements;
NameAndType	elements:()Lscala/collection/Iterator;
Method	scala/xml/Null$.elements:()Lscala/collection/Iterator;
Asciz	companion;
Asciz	()Lscala/collection/generic/GenericCompanion;;
NameAndType	companion:()Lscala/collection/generic/GenericCompanion;
Method	scala/xml/Null$.companion:()Lscala/collection/generic/GenericCompanion;
Asciz	xml_$bang$eq;
Asciz	(Ljava/lang/Object;)Z;
NameAndType	xml_$bang$eq:(Ljava/lang/Object;)Z
Method	scala/xml/Null$.xml_$bang$eq:(Ljava/lang/Object;)Z
Asciz	xml_$eq$eq;
NameAndType	xml_$eq$eq:(Ljava/lang/Object;)Z
Method	scala/xml/Null$.xml_$eq$eq:(Ljava/lang/Object;)Z
Asciz	strict_$bang$eq;
NameAndType	strict_$bang$eq:(Lscala/xml/Equality;)Z
Method	scala/xml/Null$.strict_$bang$eq:(Lscala/xml/Equality;)Z
Asciz	(Ljava/lang/String;Lscala/xml/Node;Ljava/lang/String;)Lscala/xml/MetaData;;
NameAndType	remove:(Ljava/lang/String;Lscala/xml/Node;Ljava/lang/String;)Lscala/xml/MetaData;
Method	scala/xml/Null$.remove:(Ljava/lang/String;Lscala/xml/Node;Ljava/lang/String;)Lscala/xml/MetaData;
Asciz	get;
Asciz	(Ljava/lang/String;Lscala/xml/NamespaceBinding;Ljava/lang/String;)Lscala/Option;;
NameAndType	get:(Ljava/lang/String;Lscala/xml/NamespaceBinding;Ljava/lang/String;)Lscala/Option;
Method	scala/xml/Null$.get:(Ljava/lang/String;Lscala/xml/NamespaceBinding;Ljava/lang/String;)Lscala/Option;
Asciz	(Ljava/lang/String;Lscala/xml/NamespaceBinding;Ljava/lang/String;)Lscala/Option<Lscala/collection/Seq<Lscala/xml/Node;>;>;;
Asciz	(Ljava/lang/String;Lscala/xml/Node;Ljava/lang/String;)Lscala/Option;;
NameAndType	get:(Ljava/lang/String;Lscala/xml/Node;Ljava/lang/String;)Lscala/Option;
Method	scala/xml/Null$.get:(Ljava/lang/String;Lscala/xml/Node;Ljava/lang/String;)Lscala/Option;
Asciz	(Ljava/lang/String;Lscala/xml/Node;Ljava/lang/String;)Lscala/Option<Lscala/collection/Seq<Lscala/xml/Node;>;>;;
Asciz	(Ljava/lang/String;)Lscala/Option;;
NameAndType	get:(Ljava/lang/String;)Lscala/Option;
Method	scala/xml/Null$.get:(Ljava/lang/String;)Lscala/Option;
Asciz	(Ljava/lang/String;)Lscala/Option<Lscala/collection/Seq<Lscala/xml/Node;>;>;;
Asciz	asAttrMap;
Asciz	()Lscala/collection/immutable/Map;;
NameAndType	asAttrMap:()Lscala/collection/immutable/Map;
Method	scala/xml/Null$.asAttrMap:()Lscala/collection/immutable/Map;
Asciz	()Lscala/collection/immutable/Map<Ljava/lang/String;Ljava/lang/String;>;;
Asciz	prefixedKey;
NameAndType	prefixedKey:()Ljava/lang/String;
Method	scala/xml/Null$.prefixedKey:()Ljava/lang/String;
Asciz	size;
NameAndType	size:()I
Method	scala/xml/Null$.size:()I
Asciz	canEqual;
NameAndType	canEqual:(Ljava/lang/Object;)Z
Method	scala/xml/Null$.canEqual:(Ljava/lang/Object;)Z
Asciz	(Ljava/lang/String;Lscala/xml/Node;Ljava/lang/String;)Lscala/collection/Seq;;
NameAndType	apply:(Ljava/lang/String;Lscala/xml/Node;Ljava/lang/String;)Lscala/collection/Seq;
Method	scala/xml/Null$.apply:(Ljava/lang/String;Lscala/xml/Node;Ljava/lang/String;)Lscala/collection/Seq;
Asciz	(Ljava/lang/String;Lscala/xml/Node;Ljava/lang/String;)Lscala/collection/Seq<Lscala/xml/Node;>;;
Asciz	(II)Lscala/collection/TraversableView;;
NameAndType	view:(II)Lscala/collection/TraversableView;
Method	scala/xml/Null$.view:(II)Lscala/collection/TraversableView;
Asciz	()Lscala/collection/TraversableView;;
NameAndType	view:()Lscala/collection/TraversableView;
Method	scala/xml/Null$.view:()Lscala/collection/TraversableView;
NameAndType	filter:(Lscala/Function1;)Ljava/lang/Object;
Method	scala/xml/Null$.filter:(Lscala/Function1;)Ljava/lang/Object;
Asciz	ScalaSig;
Asciz	InnerClasses;
Asciz	scala/Predef$$less$colon$less;
class	scala/Predef$$less$colon$less
Asciz	scala/Predef;
class	scala/Predef
Asciz	$less$colon$less;
Asciz	scala/collection/TraversableLike$WithFilter;
class	scala/collection/TraversableLike$WithFilter
Asciz	scala/collection/TraversableLike;
class	scala/collection/TraversableLike
Asciz	WithFilter;
Asciz	scala/xml/Null;
class	scala/xml/Null
Asciz	java/lang/Object;
class	java/lang/Object

{
public static final scala.collection.Iterator productElements();
  Signature: ()Lscala/collection/Iterator;
  Code:
   Stack=1, Locals=0, Args_size=0
	getstatic	Field scala/xml/Null$.MODULE$:Lscala/xml/Null$;
	invokevirtual	Method scala/xml/Null$.productElements:()Lscala/collection/Iterator;
	areturn
  Labels:
  Deprecated: true

public static final scala.collection.Iterator productIterator();
  Signature: ()Lscala/collection/Iterator;
  Code:
   Stack=1, Locals=0, Args_size=0
	getstatic	Field scala/xml/Null$.MODULE$:Lscala/xml/Null$;
	invokevirtual	Method scala/xml/Null$.productIterator:()Lscala/collection/Iterator;
	areturn
  Labels:

public static final java.lang.String productElementName(int);
  Signature: (I)Ljava/lang/String;
  Code:
   Stack=2, Locals=1, Args_size=1
	getstatic	Field scala/xml/Null$.MODULE$:Lscala/xml/Null$;
	iload_0
	invokevirtual	Method scala/xml/Null$.productElementName:(I)Ljava/lang/String;
	areturn
  Labels:

public static final java.lang.Object productElement(int);
  Signature: (I)Ljava/lang/Object;
  Code:
   Stack=2, Locals=1, Args_size=1
	getstatic	Field scala/xml/Null$.MODULE$:Lscala/xml/Null$;
	iload_0
	invokevirtual	Method scala/xml/Null$.productElement:(I)Ljava/lang/Object;
	areturn
  Labels:

public static final int productArity();
  Signature: ()I
  Code:
   Stack=1, Locals=0, Args_size=0
	getstatic	Field scala/xml/Null$.MODULE$:Lscala/xml/Null$;
	invokevirtual	Method scala/xml/Null$.productArity:()I
	ireturn
  Labels:

public static final java.lang.String productPrefix();
  Signature: ()Ljava/lang/String;
  Code:
   Stack=1, Locals=0, Args_size=0
	getstatic	Field scala/xml/Null$.MODULE$:Lscala/xml/Null$;
	invokevirtual	Method scala/xml/Null$.productPrefix:()Ljava/lang/String;
	areturn
  Labels:

public static final scala.xml.NamespaceBinding append$default$2();
  Signature: ()Lscala/xml/NamespaceBinding;
  Code:
   Stack=1, Locals=0, Args_size=0
	getstatic	Field scala/xml/Null$.MODULE$:Lscala/xml/Null$;
	invokevirtual	Method scala/xml/Null$.append$default$2:()Lscala/xml/NamespaceBinding;
	areturn
  Labels:

public static final scala.xml.Null$ remove(java.lang.String, scala.xml.NamespaceBinding, java.lang.String);
  Signature: (Ljava/lang/String;Lscala/xml/NamespaceBinding;Ljava/lang/String;)Lscala/xml/Null$;
  Code:
   Stack=4, Locals=3, Args_size=3
	getstatic	Field scala/xml/Null$.MODULE$:Lscala/xml/Null$;
	aload_0
	aload_1
	aload_2
	invokevirtual	Method scala/xml/Null$.remove:(Ljava/lang/String;Lscala/xml/NamespaceBinding;Ljava/lang/String;)Lscala/xml/Null$;
	areturn
  Labels:

public static final scala.xml.Null$ remove(java.lang.String);
  Signature: (Ljava/lang/String;)Lscala/xml/Null$;
  Code:
   Stack=2, Locals=1, Args_size=1
	getstatic	Field scala/xml/Null$.MODULE$:Lscala/xml/Null$;
	aload_0
	invokevirtual	Method scala/xml/Null$.remove:(Ljava/lang/String;)Lscala/xml/Null$;
	areturn
  Labels:

public static final boolean wellformed(scala.xml.NamespaceBinding);
  Signature: (Lscala/xml/NamespaceBinding;)Z
  Code:
   Stack=2, Locals=1, Args_size=1
	getstatic	Field scala/xml/Null$.MODULE$:Lscala/xml/Null$;
	aload_0
	invokevirtual	Method scala/xml/Null$.wellformed:(Lscala/xml/NamespaceBinding;)Z
	ireturn
  Labels:

public static final scala.collection.mutable.StringBuilder buildString(scala.collection.mutable.StringBuilder);
  Signature: (Lscala/collection/mutable/StringBuilder;)Lscala/collection/mutable/StringBuilder;
  Code:
   Stack=2, Locals=1, Args_size=1
	getstatic	Field scala/xml/Null$.MODULE$:Lscala/xml/Null$;
	aload_0
	invokevirtual	Method scala/xml/Null$.buildString:(Lscala/collection/mutable/StringBuilder;)Lscala/collection/mutable/StringBuilder;
	areturn
  Labels:

public static final java.lang.String toString1();
  Signature: ()Ljava/lang/String;
  Code:
   Stack=1, Locals=0, Args_size=0
	getstatic	Field scala/xml/Null$.MODULE$:Lscala/xml/Null$;
	invokevirtual	Method scala/xml/Null$.toString1:()Ljava/lang/String;
	areturn
  Labels:

public static final void toString1(scala.collection.mutable.StringBuilder);
  Signature: (Lscala/collection/mutable/StringBuilder;)V
  Code:
   Stack=2, Locals=1, Args_size=1
	getstatic	Field scala/xml/Null$.MODULE$:Lscala/xml/Null$;
	aload_0
	invokevirtual	Method scala/xml/Null$.toString1:(Lscala/collection/mutable/StringBuilder;)V
	return
  Labels:

public static final scala.runtime.Null$ apply(java.lang.String);
  Signature: (Ljava/lang/String;)Lscala/runtime/Null$;
  Code:
   Stack=2, Locals=1, Args_size=1
	getstatic	Field scala/xml/Null$.MODULE$:Lscala/xml/Null$;
	aload_0
	invokevirtual	Method scala/xml/Null$.apply:(Ljava/lang/String;)Lscala/runtime/Null$;
	areturn
  Labels:

public static final scala.runtime.Null$ apply(java.lang.String, scala.xml.NamespaceBinding, java.lang.String);
  Signature: (Ljava/lang/String;Lscala/xml/NamespaceBinding;Ljava/lang/String;)Lscala/runtime/Null$;
  Code:
   Stack=4, Locals=3, Args_size=3
	getstatic	Field scala/xml/Null$.MODULE$:Lscala/xml/Null$;
	aload_0
	aload_1
	aload_2
	invokevirtual	Method scala/xml/Null$.apply:(Ljava/lang/String;Lscala/xml/NamespaceBinding;Ljava/lang/String;)Lscala/runtime/Null$;
	areturn
  Labels:

public static final scala.collection.Seq basisForHashCode();
  Signature: ()Lscala/collection/Seq;
  Code:
   Stack=1, Locals=0, Args_size=0
	getstatic	Field scala/xml/Null$.MODULE$:Lscala/xml/Null$;
	invokevirtual	Method scala/xml/Null$.basisForHashCode:()Lscala/collection/Seq;
	areturn
  Labels:
  Signature: length = 0x2
   00 46 

public static final boolean strict_$eq$eq(scala.xml.Equality);
  Signature: (Lscala/xml/Equality;)Z
  Code:
   Stack=2, Locals=1, Args_size=1
	getstatic	Field scala/xml/Null$.MODULE$:Lscala/xml/Null$;
	aload_0
	invokevirtual	Method scala/xml/Null$.strict_$eq$eq:(Lscala/xml/Equality;)Z
	ireturn
  Labels:

public static final int length(int);
  Signature: (I)I
  Code:
   Stack=2, Locals=1, Args_size=1
	getstatic	Field scala/xml/Null$.MODULE$:Lscala/xml/Null$;
	iload_0
	invokevirtual	Method scala/xml/Null$.length:(I)I
	ireturn
  Labels:

public static final int length();
  Signature: ()I
  Code:
   Stack=1, Locals=0, Args_size=0
	getstatic	Field scala/xml/Null$.MODULE$:Lscala/xml/Null$;
	invokevirtual	Method scala/xml/Null$.length:()I
	ireturn
  Labels:

public static final boolean isPrefixed();
  Signature: ()Z
  Code:
   Stack=1, Locals=0, Args_size=0
	getstatic	Field scala/xml/Null$.MODULE$:Lscala/xml/Null$;
	invokevirtual	Method scala/xml/Null$.isPrefixed:()Z
	ireturn
  Labels:

public static final scala.runtime.Null$ value();
  Signature: ()Lscala/runtime/Null$;
  Code:
   Stack=1, Locals=0, Args_size=0
	getstatic	Field scala/xml/Null$.MODULE$:Lscala/xml/Null$;
	invokevirtual	Method scala/xml/Null$.value:()Lscala/runtime/Null$;
	areturn
  Labels:

public static final scala.runtime.Null$ key();
  Signature: ()Lscala/runtime/Null$;
  Code:
   Stack=1, Locals=0, Args_size=0
	getstatic	Field scala/xml/Null$.MODULE$:Lscala/xml/Null$;
	invokevirtual	Method scala/xml/Null$.key:()Lscala/runtime/Null$;
	areturn
  Labels:

public static final scala.runtime.Null$ next();
  Signature: ()Lscala/runtime/Null$;
  Code:
   Stack=1, Locals=0, Args_size=0
	getstatic	Field scala/xml/Null$.MODULE$:Lscala/xml/Null$;
	invokevirtual	Method scala/xml/Null$.next:()Lscala/runtime/Null$;
	areturn
  Labels:

public static final boolean hasNext();
  Signature: ()Z
  Code:
   Stack=1, Locals=0, Args_size=0
	getstatic	Field scala/xml/Null$.MODULE$:Lscala/xml/Null$;
	invokevirtual	Method scala/xml/Null$.hasNext:()Z
	ireturn
  Labels:

public static final scala.runtime.Null$ getNamespace(scala.xml.Node);
  Signature: (Lscala/xml/Node;)Lscala/runtime/Null$;
  Code:
   Stack=2, Locals=1, Args_size=1
	getstatic	Field scala/xml/Null$.MODULE$:Lscala/xml/Null$;
	aload_0
	invokevirtual	Method scala/xml/Null$.getNamespace:(Lscala/xml/Node;)Lscala/runtime/Null$;
	areturn
  Labels:

public static final scala.xml.MetaData copy(scala.xml.MetaData);
  Signature: (Lscala/xml/MetaData;)Lscala/xml/MetaData;
  Code:
   Stack=2, Locals=1, Args_size=1
	getstatic	Field scala/xml/Null$.MODULE$:Lscala/xml/Null$;
	aload_0
	invokevirtual	Method scala/xml/Null$.copy:(Lscala/xml/MetaData;)Lscala/xml/MetaData;
	areturn
  Labels:

public static final scala.xml.MetaData filter(scala.Function1);
  Signature: (Lscala/Function1;)Lscala/xml/MetaData;
  Code:
   Stack=2, Locals=1, Args_size=1
	getstatic	Field scala/xml/Null$.MODULE$:Lscala/xml/Null$;
	aload_0
	invokevirtual	Method scala/xml/Null$.filter:(Lscala/Function1;)Lscala/xml/MetaData;
	areturn
  Labels:
  Signature: length = 0x2
   00 6F 

public static final scala.xml.MetaData append(scala.xml.MetaData, scala.xml.NamespaceBinding);
  Signature: (Lscala/xml/MetaData;Lscala/xml/NamespaceBinding;)Lscala/xml/MetaData;
  Code:
   Stack=3, Locals=2, Args_size=2
	getstatic	Field scala/xml/Null$.MODULE$:Lscala/xml/Null$;
	aload_0
	aload_1
	invokevirtual	Method scala/xml/Null$.append:(Lscala/xml/MetaData;Lscala/xml/NamespaceBinding;)Lscala/xml/MetaData;
	areturn
  Labels:

public static final scala.collection.Iterator iterator();
  Signature: ()Lscala/collection/Iterator;
  Code:
   Stack=1, Locals=0, Args_size=0
	getstatic	Field scala/xml/Null$.MODULE$:Lscala/xml/Null$;
	invokevirtual	Method scala/xml/Null$.iterator:()Lscala/collection/Iterator;
	areturn
  Labels:

public static final scala.collection.TraversableLike$WithFilter withFilter(scala.Function1);
  Signature: (Lscala/Function1;)Lscala/collection/TraversableLike$WithFilter;
  Code:
   Stack=2, Locals=1, Args_size=1
	getstatic	Field scala/xml/Null$.MODULE$:Lscala/xml/Null$;
	aload_0
	invokevirtual	Method scala/xml/Null$.withFilter:(Lscala/Function1;)Lscala/collection/TraversableLike$WithFilter;
	areturn
  Labels:
  Signature: length = 0x2
   00 78 

public static final java.lang.String stringPrefix();
  Signature: ()Ljava/lang/String;
  Code:
   Stack=1, Locals=0, Args_size=0
	getstatic	Field scala/xml/Null$.MODULE$:Lscala/xml/Null$;
	invokevirtual	Method scala/xml/Null$.stringPrefix:()Ljava/lang/String;
	areturn
  Labels:

public static final scala.collection.mutable.StringBuilder addString(scala.collection.mutable.StringBuilder);
  Signature: (Lscala/collection/mutable/StringBuilder;)Lscala/collection/mutable/StringBuilder;
  Code:
   Stack=2, Locals=1, Args_size=1
	getstatic	Field scala/xml/Null$.MODULE$:Lscala/xml/Null$;
	aload_0
	invokevirtual	Method scala/xml/Null$.addString:(Lscala/collection/mutable/StringBuilder;)Lscala/collection/mutable/StringBuilder;
	areturn
  Labels:

public static final scala.collection.mutable.StringBuilder addString(scala.collection.mutable.StringBuilder, java.lang.String);
  Signature: (Lscala/collection/mutable/StringBuilder;Ljava/lang/String;)Lscala/collection/mutable/StringBuilder;
  Code:
   Stack=3, Locals=2, Args_size=2
	getstatic	Field scala/xml/Null$.MODULE$:Lscala/xml/Null$;
	aload_0
	aload_1
	invokevirtual	Method scala/xml/Null$.addString:(Lscala/collection/mutable/StringBuilder;Ljava/lang/String;)Lscala/collection/mutable/StringBuilder;
	areturn
  Labels:

public static final scala.collection.mutable.StringBuilder addString(scala.collection.mutable.StringBuilder, java.lang.String, java.lang.String, java.lang.String);
  Signature: (Lscala/collection/mutable/StringBuilder;Ljava/lang/String;Ljava/lang/String;Ljava/lang/String;)Lscala/collection/mutable/StringBuilder;
  Code:
   Stack=5, Locals=4, Args_size=4
	getstatic	Field scala/xml/Null$.MODULE$:Lscala/xml/Null$;
	aload_0
	aload_1
	aload_2
	aload_3
	invokevirtual	Method scala/xml/Null$.addString:(Lscala/collection/mutable/StringBuilder;Ljava/lang/String;Ljava/lang/String;Ljava/lang/String;)Lscala/collection/mutable/StringBuilder;
	areturn
  Labels:

public static final java.lang.String mkString();
  Signature: ()Ljava/lang/String;
  Code:
   Stack=1, Locals=0, Args_size=0
	getstatic	Field scala/xml/Null$.MODULE$:Lscala/xml/Null$;
	invokevirtual	Method scala/xml/Null$.mkString:()Ljava/lang/String;
	areturn
  Labels:

public static final java.lang.String mkString(java.lang.String);
  Signature: (Ljava/lang/String;)Ljava/lang/String;
  Code:
   Stack=2, Locals=1, Args_size=1
	getstatic	Field scala/xml/Null$.MODULE$:Lscala/xml/Null$;
	aload_0
	invokevirtual	Method scala/xml/Null$.mkString:(Ljava/lang/String;)Ljava/lang/String;
	areturn
  Labels:

public static final java.lang.String mkString(java.lang.String, java.lang.String, java.lang.String);
  Signature: (Ljava/lang/String;Ljava/lang/String;Ljava/lang/String;)Ljava/lang/String;
  Code:
   Stack=4, Locals=3, Args_size=3
	getstatic	Field scala/xml/Null$.MODULE$:Lscala/xml/Null$;
	aload_0
	aload_1
	aload_2
	invokevirtual	Method scala/xml/Null$.mkString:(Ljava/lang/String;Ljava/lang/String;Ljava/lang/String;)Ljava/lang/String;
	areturn
  Labels:

public static final scala.collection.immutable.Map toMap(scala.Predef$$less$colon$less);
  Signature: (Lscala/Predef$$less$colon$less;)Lscala/collection/immutable/Map;
  Code:
   Stack=2, Locals=1, Args_size=1
	getstatic	Field scala/xml/Null$.MODULE$:Lscala/xml/Null$;
	aload_0
	invokevirtual	Method scala/xml/Null$.toMap:(Lscala/Predef$$less$colon$less;)Lscala/collection/immutable/Map;
	areturn
  Labels:

public static final scala.collection.immutable.Set toSet();
  Signature: ()Lscala/collection/immutable/Set;
  Code:
   Stack=1, Locals=0, Args_size=0
	getstatic	Field scala/xml/Null$.MODULE$:Lscala/xml/Null$;
	invokevirtual	Method scala/xml/Null$.toSet:()Lscala/collection/immutable/Set;
	areturn
  Labels:

public static final scala.collection.mutable.IndexedSeq toIndexedSeq();
  Signature: ()Lscala/collection/mutable/IndexedSeq;
  Code:
   Stack=1, Locals=0, Args_size=0
	getstatic	Field scala/xml/Null$.MODULE$:Lscala/xml/Null$;
	invokevirtual	Method scala/xml/Null$.toIndexedSeq:()Lscala/collection/mutable/IndexedSeq;
	areturn
  Labels:

public static final scala.collection.Seq toSeq();
  Signature: ()Lscala/collection/Seq;
  Code:
   Stack=1, Locals=0, Args_size=0
	getstatic	Field scala/xml/Null$.MODULE$:Lscala/xml/Null$;
	invokevirtual	Method scala/xml/Null$.toSeq:()Lscala/collection/Seq;
	areturn
  Labels:

public static final scala.collection.immutable.List toList();
  Signature: ()Lscala/collection/immutable/List;
  Code:
   Stack=1, Locals=0, Args_size=0
	getstatic	Field scala/xml/Null$.MODULE$:Lscala/xml/Null$;
	invokevirtual	Method scala/xml/Null$.toList:()Lscala/collection/immutable/List;
	areturn
  Labels:

public static final java.lang.Object toArray(scala.reflect.ClassManifest);
  Signature: (Lscala/reflect/ClassManifest;)Ljava/lang/Object;
  Code:
   Stack=2, Locals=1, Args_size=1
	getstatic	Field scala/xml/Null$.MODULE$:Lscala/xml/Null$;
	aload_0
	invokevirtual	Method scala/xml/Null$.toArray:(Lscala/reflect/ClassManifest;)Ljava/lang/Object;
	areturn
  Labels:

public static final void copyToArray(java.lang.Object);
  Signature: (Ljava/lang/Object;)V
  Code:
   Stack=2, Locals=1, Args_size=1
	getstatic	Field scala/xml/Null$.MODULE$:Lscala/xml/Null$;
	aload_0
	invokevirtual	Method scala/xml/Null$.copyToArray:(Ljava/lang/Object;)V
	return
  Labels:

public static final void copyToArray(java.lang.Object, int);
  Signature: (Ljava/lang/Object;I)V
  Code:
   Stack=3, Locals=2, Args_size=2
	getstatic	Field scala/xml/Null$.MODULE$:Lscala/xml/Null$;
	aload_0
	iload_1
	invokevirtual	Method scala/xml/Null$.copyToArray:(Ljava/lang/Object;I)V
	return
  Labels:

public static final void copyToBuffer(scala.collection.mutable.Buffer);
  Signature: (Lscala/collection/mutable/Buffer;)V
  Code:
   Stack=2, Locals=1, Args_size=1
	getstatic	Field scala/xml/Null$.MODULE$:Lscala/xml/Null$;
	aload_0
	invokevirtual	Method scala/xml/Null$.copyToBuffer:(Lscala/collection/mutable/Buffer;)V
	return
  Labels:

public static final scala.Tuple2 splitAt(int);
  Signature: (I)Lscala/Tuple2;
  Code:
   Stack=2, Locals=1, Args_size=1
	getstatic	Field scala/xml/Null$.MODULE$:Lscala/xml/Null$;
	iload_0
	invokevirtual	Method scala/xml/Null$.splitAt:(I)Lscala/Tuple2;
	areturn
  Labels:

public static final scala.Tuple2 span(scala.Function1);
  Signature: (Lscala/Function1;)Lscala/Tuple2;
  Code:
   Stack=2, Locals=1, Args_size=1
	getstatic	Field scala/xml/Null$.MODULE$:Lscala/xml/Null$;
	aload_0
	invokevirtual	Method scala/xml/Null$.span:(Lscala/Function1;)Lscala/Tuple2;
	areturn
  Labels:

public static final java.lang.Object dropWhile(scala.Function1);
  Signature: (Lscala/Function1;)Ljava/lang/Object;
  Code:
   Stack=2, Locals=1, Args_size=1
	getstatic	Field scala/xml/Null$.MODULE$:Lscala/xml/Null$;
	aload_0
	invokevirtual	Method scala/xml/Null$.dropWhile:(Lscala/Function1;)Ljava/lang/Object;
	areturn
  Labels:

public static final java.lang.Object drop(int);
  Signature: (I)Ljava/lang/Object;
  Code:
   Stack=2, Locals=1, Args_size=1
	getstatic	Field scala/xml/Null$.MODULE$:Lscala/xml/Null$;
	iload_0
	invokevirtual	Method scala/xml/Null$.drop:(I)Ljava/lang/Object;
	areturn
  Labels:

public static final java.lang.Object init();
  Signature: ()Ljava/lang/Object;
  Code:
   Stack=1, Locals=0, Args_size=0
	getstatic	Field scala/xml/Null$.MODULE$:Lscala/xml/Null$;
	invokevirtual	Method scala/xml/Null$.init:()Ljava/lang/Object;
	areturn
  Labels:

public static final scala.Option lastOption();
  Signature: ()Lscala/Option;
  Code:
   Stack=1, Locals=0, Args_size=0
	getstatic	Field scala/xml/Null$.MODULE$:Lscala/xml/Null$;
	invokevirtual	Method scala/xml/Null$.lastOption:()Lscala/Option;
	areturn
  Labels:

public static final java.lang.Object last();
  Signature: ()Ljava/lang/Object;
  Code:
   Stack=1, Locals=0, Args_size=0
	getstatic	Field scala/xml/Null$.MODULE$:Lscala/xml/Null$;
	invokevirtual	Method scala/xml/Null$.last:()Ljava/lang/Object;
	areturn
  Labels:

public static final java.lang.Object tail();
  Signature: ()Ljava/lang/Object;
  Code:
   Stack=1, Locals=0, Args_size=0
	getstatic	Field scala/xml/Null$.MODULE$:Lscala/xml/Null$;
	invokevirtual	Method scala/xml/Null$.tail:()Ljava/lang/Object;
	areturn
  Labels:

public static final scala.Option headOption();
  Signature: ()Lscala/Option;
  Code:
   Stack=1, Locals=0, Args_size=0
	getstatic	Field scala/xml/Null$.MODULE$:Lscala/xml/Null$;
	invokevirtual	Method scala/xml/Null$.headOption:()Lscala/Option;
	areturn
  Labels:

public static final java.lang.Object max(scala.math.Ordering);
  Signature: (Lscala/math/Ordering;)Ljava/lang/Object;
  Code:
   Stack=2, Locals=1, Args_size=1
	getstatic	Field scala/xml/Null$.MODULE$:Lscala/xml/Null$;
	aload_0
	invokevirtual	Method scala/xml/Null$.max:(Lscala/math/Ordering;)Ljava/lang/Object;
	areturn
  Labels:

public static final java.lang.Object min(scala.math.Ordering);
  Signature: (Lscala/math/Ordering;)Ljava/lang/Object;
  Code:
   Stack=2, Locals=1, Args_size=1
	getstatic	Field scala/xml/Null$.MODULE$:Lscala/xml/Null$;
	aload_0
	invokevirtual	Method scala/xml/Null$.min:(Lscala/math/Ordering;)Ljava/lang/Object;
	areturn
  Labels:

public static final java.lang.Object product(scala.math.Numeric);
  Signature: (Lscala/math/Numeric;)Ljava/lang/Object;
  Code:
   Stack=2, Locals=1, Args_size=1
	getstatic	Field scala/xml/Null$.MODULE$:Lscala/xml/Null$;
	aload_0
	invokevirtual	Method scala/xml/Null$.product:(Lscala/math/Numeric;)Ljava/lang/Object;
	areturn
  Labels:

public static final java.lang.Object sum(scala.math.Numeric);
  Signature: (Lscala/math/Numeric;)Ljava/lang/Object;
  Code:
   Stack=2, Locals=1, Args_size=1
	getstatic	Field scala/xml/Null$.MODULE$:Lscala/xml/Null$;
	aload_0
	invokevirtual	Method scala/xml/Null$.sum:(Lscala/math/Numeric;)Ljava/lang/Object;
	areturn
  Labels:

public static final scala.Option reduceRightOption(scala.Function2);
  Signature: (Lscala/Function2;)Lscala/Option;
  Code:
   Stack=2, Locals=1, Args_size=1
	getstatic	Field scala/xml/Null$.MODULE$:Lscala/xml/Null$;
	aload_0
	invokevirtual	Method scala/xml/Null$.reduceRightOption:(Lscala/Function2;)Lscala/Option;
	areturn
  Labels:

public static final scala.Option reduceLeftOption(scala.Function2);
  Signature: (Lscala/Function2;)Lscala/Option;
  Code:
   Stack=2, Locals=1, Args_size=1
	getstatic	Field scala/xml/Null$.MODULE$:Lscala/xml/Null$;
	aload_0
	invokevirtual	Method scala/xml/Null$.reduceLeftOption:(Lscala/Function2;)Lscala/Option;
	areturn
  Labels:

public static final java.lang.Object reduceLeft(scala.Function2);
  Signature: (Lscala/Function2;)Ljava/lang/Object;
  Code:
   Stack=2, Locals=1, Args_size=1
	getstatic	Field scala/xml/Null$.MODULE$:Lscala/xml/Null$;
	aload_0
	invokevirtual	Method scala/xml/Null$.reduceLeft:(Lscala/Function2;)Ljava/lang/Object;
	areturn
  Labels:

public static final java.lang.Object $colon$bslash(java.lang.Object, scala.Function2);
  Signature: (Ljava/lang/Object;Lscala/Function2;)Ljava/lang/Object;
  Code:
   Stack=3, Locals=2, Args_size=2
	getstatic	Field scala/xml/Null$.MODULE$:Lscala/xml/Null$;
	aload_0
	aload_1
	invokevirtual	Method scala/xml/Null$.$colon$bslash:(Ljava/lang/Object;Lscala/Function2;)Ljava/lang/Object;
	areturn
  Labels:

public static final java.lang.Object $div$colon(java.lang.Object, scala.Function2);
  Signature: (Ljava/lang/Object;Lscala/Function2;)Ljava/lang/Object;
  Code:
   Stack=3, Locals=2, Args_size=2
	getstatic	Field scala/xml/Null$.MODULE$:Lscala/xml/Null$;
	aload_0
	aload_1
	invokevirtual	Method scala/xml/Null$.$div$colon:(Ljava/lang/Object;Lscala/Function2;)Ljava/lang/Object;
	areturn
  Labels:

public static final java.lang.Object foldLeft(java.lang.Object, scala.Function2);
  Signature: (Ljava/lang/Object;Lscala/Function2;)Ljava/lang/Object;
  Code:
   Stack=3, Locals=2, Args_size=2
	getstatic	Field scala/xml/Null$.MODULE$:Lscala/xml/Null$;
	aload_0
	aload_1
	invokevirtual	Method scala/xml/Null$.foldLeft:(Ljava/lang/Object;Lscala/Function2;)Ljava/lang/Object;
	areturn
  Labels:

public static final int count(scala.Function1);
  Signature: (Lscala/Function1;)I
  Code:
   Stack=2, Locals=1, Args_size=1
	getstatic	Field scala/xml/Null$.MODULE$:Lscala/xml/Null$;
	aload_0
	invokevirtual	Method scala/xml/Null$.count:(Lscala/Function1;)I
	ireturn
  Labels:

public static final scala.collection.Map groupBy(scala.Function1);
  Signature: (Lscala/Function1;)Lscala/collection/Map;
  Code:
   Stack=2, Locals=1, Args_size=1
	getstatic	Field scala/xml/Null$.MODULE$:Lscala/xml/Null$;
	aload_0
	invokevirtual	Method scala/xml/Null$.groupBy:(Lscala/Function1;)Lscala/collection/Map;
	areturn
  Labels:

public static final scala.Tuple2 partition(scala.Function1);
  Signature: (Lscala/Function1;)Lscala/Tuple2;
  Code:
   Stack=2, Locals=1, Args_size=1
	getstatic	Field scala/xml/Null$.MODULE$:Lscala/xml/Null$;
	aload_0
	invokevirtual	Method scala/xml/Null$.partition:(Lscala/Function1;)Lscala/Tuple2;
	areturn
  Labels:

public static final java.lang.Object partialMap(scala.PartialFunction, scala.collection.generic.CanBuildFrom);
  Signature: (Lscala/PartialFunction;Lscala/collection/generic/CanBuildFrom;)Ljava/lang/Object;
  Code:
   Stack=3, Locals=2, Args_size=2
	getstatic	Field scala/xml/Null$.MODULE$:Lscala/xml/Null$;
	aload_0
	aload_1
	invokevirtual	Method scala/xml/Null$.partialMap:(Lscala/PartialFunction;Lscala/collection/generic/CanBuildFrom;)Ljava/lang/Object;
	areturn
  Labels:

public static final java.lang.Object filterNot(scala.Function1);
  Signature: (Lscala/Function1;)Ljava/lang/Object;
  Code:
   Stack=2, Locals=1, Args_size=1
	getstatic	Field scala/xml/Null$.MODULE$:Lscala/xml/Null$;
	aload_0
	invokevirtual	Method scala/xml/Null$.filterNot:(Lscala/Function1;)Ljava/lang/Object;
	areturn
  Labels:

public static final java.lang.Object flatMap(scala.Function1, scala.collection.generic.CanBuildFrom);
  Signature: (Lscala/Function1;Lscala/collection/generic/CanBuildFrom;)Ljava/lang/Object;
  Code:
   Stack=3, Locals=2, Args_size=2
	getstatic	Field scala/xml/Null$.MODULE$:Lscala/xml/Null$;
	aload_0
	aload_1
	invokevirtual	Method scala/xml/Null$.flatMap:(Lscala/Function1;Lscala/collection/generic/CanBuildFrom;)Ljava/lang/Object;
	areturn
  Labels:

public static final java.lang.Object map(scala.Function1, scala.collection.generic.CanBuildFrom);
  Signature: (Lscala/Function1;Lscala/collection/generic/CanBuildFrom;)Ljava/lang/Object;
  Code:
   Stack=3, Locals=2, Args_size=2
	getstatic	Field scala/xml/Null$.MODULE$:Lscala/xml/Null$;
	aload_0
	aload_1
	invokevirtual	Method scala/xml/Null$.map:(Lscala/Function1;Lscala/collection/generic/CanBuildFrom;)Ljava/lang/Object;
	areturn
  Labels:

public static final java.lang.Object $plus$plus(scala.collection.Iterator, scala.collection.generic.CanBuildFrom);
  Signature: (Lscala/collection/Iterator;Lscala/collection/generic/CanBuildFrom;)Ljava/lang/Object;
  Code:
   Stack=3, Locals=2, Args_size=2
	getstatic	Field scala/xml/Null$.MODULE$:Lscala/xml/Null$;
	aload_0
	aload_1
	invokevirtual	Method scala/xml/Null$.$plus$plus:(Lscala/collection/Iterator;Lscala/collection/generic/CanBuildFrom;)Ljava/lang/Object;
	areturn
  Labels:

public static final java.lang.Object $plus$plus(scala.collection.Traversable, scala.collection.generic.CanBuildFrom);
  Signature: (Lscala/collection/Traversable;Lscala/collection/generic/CanBuildFrom;)Ljava/lang/Object;
  Code:
   Stack=3, Locals=2, Args_size=2
	getstatic	Field scala/xml/Null$.MODULE$:Lscala/xml/Null$;
	aload_0
	aload_1
	invokevirtual	Method scala/xml/Null$.$plus$plus:(Lscala/collection/Traversable;Lscala/collection/generic/CanBuildFrom;)Ljava/lang/Object;
	areturn
  Labels:

public static final boolean hasDefiniteSize();
  Signature: ()Z
  Code:
   Stack=1, Locals=0, Args_size=0
	getstatic	Field scala/xml/Null$.MODULE$:Lscala/xml/Null$;
	invokevirtual	Method scala/xml/Null$.hasDefiniteSize:()Z
	ireturn
  Labels:

public static final boolean nonEmpty();
  Signature: ()Z
  Code:
   Stack=1, Locals=0, Args_size=0
	getstatic	Field scala/xml/Null$.MODULE$:Lscala/xml/Null$;
	invokevirtual	Method scala/xml/Null$.nonEmpty:()Z
	ireturn
  Labels:

public static final java.lang.Object repr();
  Signature: ()Ljava/lang/Object;
  Code:
   Stack=1, Locals=0, Args_size=0
	getstatic	Field scala/xml/Null$.MODULE$:Lscala/xml/Null$;
	invokevirtual	Method scala/xml/Null$.repr:()Ljava/lang/Object;
	areturn
  Labels:

public static final scala.collection.Traversable transpose(scala.Function1);
  Signature: (Lscala/Function1;)Lscala/collection/Traversable;
  Code:
   Stack=2, Locals=1, Args_size=1
	getstatic	Field scala/xml/Null$.MODULE$:Lscala/xml/Null$;
	aload_0
	invokevirtual	Method scala/xml/Null$.transpose:(Lscala/Function1;)Lscala/collection/Traversable;
	areturn
  Labels:

public static final scala.collection.Traversable flatten(scala.Function1);
  Signature: (Lscala/Function1;)Lscala/collection/Traversable;
  Code:
   Stack=2, Locals=1, Args_size=1
	getstatic	Field scala/xml/Null$.MODULE$:Lscala/xml/Null$;
	aload_0
	invokevirtual	Method scala/xml/Null$.flatten:(Lscala/Function1;)Lscala/collection/Traversable;
	areturn
  Labels:

public static final scala.Tuple2 unzip(scala.Function1);
  Signature: (Lscala/Function1;)Lscala/Tuple2;
  Code:
   Stack=2, Locals=1, Args_size=1
	getstatic	Field scala/xml/Null$.MODULE$:Lscala/xml/Null$;
	aload_0
	invokevirtual	Method scala/xml/Null$.unzip:(Lscala/Function1;)Lscala/Tuple2;
	areturn
  Labels:

public static final scala.collection.mutable.Builder genericBuilder();
  Signature: ()Lscala/collection/mutable/Builder;
  Code:
   Stack=1, Locals=0, Args_size=0
	getstatic	Field scala/xml/Null$.MODULE$:Lscala/xml/Null$;
	invokevirtual	Method scala/xml/Null$.genericBuilder:()Lscala/collection/mutable/Builder;
	areturn
  Labels:

public static final scala.collection.IterableView projection();
  Signature: ()Lscala/collection/IterableView;
  Code:
   Stack=1, Locals=0, Args_size=0
	getstatic	Field scala/xml/Null$.MODULE$:Lscala/xml/Null$;
	invokevirtual	Method scala/xml/Null$.projection:()Lscala/collection/IterableView;
	areturn
  Labels:
  Deprecated: true

public static final scala.Option firstOption();
  Signature: ()Lscala/Option;
  Code:
   Stack=1, Locals=0, Args_size=0
	getstatic	Field scala/xml/Null$.MODULE$:Lscala/xml/Null$;
	invokevirtual	Method scala/xml/Null$.firstOption:()Lscala/Option;
	areturn
  Labels:
  Deprecated: true

public static final java.lang.Object first();
  Signature: ()Ljava/lang/Object;
  Code:
   Stack=1, Locals=0, Args_size=0
	getstatic	Field scala/xml/Null$.MODULE$:Lscala/xml/Null$;
	invokevirtual	Method scala/xml/Null$.first:()Ljava/lang/Object;
	areturn
  Labels:
  Deprecated: true

public static final scala.collection.IterableView view(int, int);
  Signature: (II)Lscala/collection/IterableView;
  Code:
   Stack=3, Locals=2, Args_size=2
	getstatic	Field scala/xml/Null$.MODULE$:Lscala/xml/Null$;
	iload_0
	iload_1
	invokevirtual	Method scala/xml/Null$.view:(II)Lscala/collection/IterableView;
	areturn
  Labels:

public static final scala.collection.IterableView view();
  Signature: ()Lscala/collection/IterableView;
  Code:
   Stack=1, Locals=0, Args_size=0
	getstatic	Field scala/xml/Null$.MODULE$:Lscala/xml/Null$;
	invokevirtual	Method scala/xml/Null$.view:()Lscala/collection/IterableView;
	areturn
  Labels:

public static final scala.collection.immutable.Stream toStream();
  Signature: ()Lscala/collection/immutable/Stream;
  Code:
   Stack=1, Locals=0, Args_size=0
	getstatic	Field scala/xml/Null$.MODULE$:Lscala/xml/Null$;
	invokevirtual	Method scala/xml/Null$.toStream:()Lscala/collection/immutable/Stream;
	areturn
  Labels:

public static final boolean sameElements(scala.collection.Iterable);
  Signature: (Lscala/collection/Iterable;)Z
  Code:
   Stack=2, Locals=1, Args_size=1
	getstatic	Field scala/xml/Null$.MODULE$:Lscala/xml/Null$;
	aload_0
	invokevirtual	Method scala/xml/Null$.sameElements:(Lscala/collection/Iterable;)Z
	ireturn
  Labels:

public static final java.lang.Object zipWithIndex(scala.collection.generic.CanBuildFrom);
  Signature: (Lscala/collection/generic/CanBuildFrom;)Ljava/lang/Object;
  Code:
   Stack=2, Locals=1, Args_size=1
	getstatic	Field scala/xml/Null$.MODULE$:Lscala/xml/Null$;
	aload_0
	invokevirtual	Method scala/xml/Null$.zipWithIndex:(Lscala/collection/generic/CanBuildFrom;)Ljava/lang/Object;
	areturn
  Labels:

public static final java.lang.Object zipAll(scala.collection.Iterable, java.lang.Object, java.lang.Object, scala.collection.generic.CanBuildFrom);
  Signature: (Lscala/collection/Iterable;Ljava/lang/Object;Ljava/lang/Object;Lscala/collection/generic/CanBuildFrom;)Ljava/lang/Object;
  Code:
   Stack=5, Locals=4, Args_size=4
	getstatic	Field scala/xml/Null$.MODULE$:Lscala/xml/Null$;
	aload_0
	aload_1
	aload_2
	aload_3
	invokevirtual	Method scala/xml/Null$.zipAll:(Lscala/collection/Iterable;Ljava/lang/Object;Ljava/lang/Object;Lscala/collection/generic/CanBuildFrom;)Ljava/lang/Object;
	areturn
  Labels:

public static final java.lang.Object zip(scala.collection.Iterable, scala.collection.generic.CanBuildFrom);
  Signature: (Lscala/collection/Iterable;Lscala/collection/generic/CanBuildFrom;)Ljava/lang/Object;
  Code:
   Stack=3, Locals=2, Args_size=2
	getstatic	Field scala/xml/Null$.MODULE$:Lscala/xml/Null$;
	aload_0
	aload_1
	invokevirtual	Method scala/xml/Null$.zip:(Lscala/collection/Iterable;Lscala/collection/generic/CanBuildFrom;)Ljava/lang/Object;
	areturn
  Labels:

public static final void copyToArray(java.lang.Object, int, int);
  Signature: (Ljava/lang/Object;II)V
  Code:
   Stack=4, Locals=3, Args_size=3
	getstatic	Field scala/xml/Null$.MODULE$:Lscala/xml/Null$;
	aload_0
	iload_1
	iload_2
	invokevirtual	Method scala/xml/Null$.copyToArray:(Ljava/lang/Object;II)V
	return
  Labels:

public static final java.lang.Object dropRight(int);
  Signature: (I)Ljava/lang/Object;
  Code:
   Stack=2, Locals=1, Args_size=1
	getstatic	Field scala/xml/Null$.MODULE$:Lscala/xml/Null$;
	iload_0
	invokevirtual	Method scala/xml/Null$.dropRight:(I)Ljava/lang/Object;
	areturn
  Labels:

public static final java.lang.Object takeRight(int);
  Signature: (I)Ljava/lang/Object;
  Code:
   Stack=2, Locals=1, Args_size=1
	getstatic	Field scala/xml/Null$.MODULE$:Lscala/xml/Null$;
	iload_0
	invokevirtual	Method scala/xml/Null$.takeRight:(I)Ljava/lang/Object;
	areturn
  Labels:

public static final scala.collection.Iterator sliding(int, int);
  Signature: (II)Lscala/collection/Iterator;
  Code:
   Stack=3, Locals=2, Args_size=2
	getstatic	Field scala/xml/Null$.MODULE$:Lscala/xml/Null$;
	iload_0
	iload_1
	invokevirtual	Method scala/xml/Null$.sliding:(II)Lscala/collection/Iterator;
	areturn
  Labels:

public static final scala.collection.Iterator sliding(int);
  Signature: (I)Lscala/collection/Iterator;
  Code:
   Stack=2, Locals=1, Args_size=1
	getstatic	Field scala/xml/Null$.MODULE$:Lscala/xml/Null$;
	iload_0
	invokevirtual	Method scala/xml/Null$.sliding:(I)Lscala/collection/Iterator;
	areturn
  Labels:

public static final scala.collection.Iterator grouped(int);
  Signature: (I)Lscala/collection/Iterator;
  Code:
   Stack=2, Locals=1, Args_size=1
	getstatic	Field scala/xml/Null$.MODULE$:Lscala/xml/Null$;
	iload_0
	invokevirtual	Method scala/xml/Null$.grouped:(I)Lscala/collection/Iterator;
	areturn
  Labels:

public static final java.lang.Object takeWhile(scala.Function1);
  Signature: (Lscala/Function1;)Ljava/lang/Object;
  Code:
   Stack=2, Locals=1, Args_size=1
	getstatic	Field scala/xml/Null$.MODULE$:Lscala/xml/Null$;
	aload_0
	invokevirtual	Method scala/xml/Null$.takeWhile:(Lscala/Function1;)Ljava/lang/Object;
	areturn
  Labels:

public static final java.lang.Object slice(int, int);
  Signature: (II)Ljava/lang/Object;
  Code:
   Stack=3, Locals=2, Args_size=2
	getstatic	Field scala/xml/Null$.MODULE$:Lscala/xml/Null$;
	iload_0
	iload_1
	invokevirtual	Method scala/xml/Null$.slice:(II)Ljava/lang/Object;
	areturn
  Labels:

public static final java.lang.Object take(int);
  Signature: (I)Ljava/lang/Object;
  Code:
   Stack=2, Locals=1, Args_size=1
	getstatic	Field scala/xml/Null$.MODULE$:Lscala/xml/Null$;
	iload_0
	invokevirtual	Method scala/xml/Null$.take:(I)Ljava/lang/Object;
	areturn
  Labels:

public static final java.lang.Object head();
  Signature: ()Ljava/lang/Object;
  Code:
   Stack=1, Locals=0, Args_size=0
	getstatic	Field scala/xml/Null$.MODULE$:Lscala/xml/Null$;
	invokevirtual	Method scala/xml/Null$.head:()Ljava/lang/Object;
	areturn
  Labels:

public static final scala.collection.Iterable toIterable();
  Signature: ()Lscala/collection/Iterable;
  Code:
   Stack=1, Locals=0, Args_size=0
	getstatic	Field scala/xml/Null$.MODULE$:Lscala/xml/Null$;
	invokevirtual	Method scala/xml/Null$.toIterable:()Lscala/collection/Iterable;
	areturn
  Labels:

public static final java.lang.Object reduceRight(scala.Function2);
  Signature: (Lscala/Function2;)Ljava/lang/Object;
  Code:
   Stack=2, Locals=1, Args_size=1
	getstatic	Field scala/xml/Null$.MODULE$:Lscala/xml/Null$;
	aload_0
	invokevirtual	Method scala/xml/Null$.reduceRight:(Lscala/Function2;)Ljava/lang/Object;
	areturn
  Labels:

public static final java.lang.Object foldRight(java.lang.Object, scala.Function2);
  Signature: (Ljava/lang/Object;Lscala/Function2;)Ljava/lang/Object;
  Code:
   Stack=3, Locals=2, Args_size=2
	getstatic	Field scala/xml/Null$.MODULE$:Lscala/xml/Null$;
	aload_0
	aload_1
	invokevirtual	Method scala/xml/Null$.foldRight:(Ljava/lang/Object;Lscala/Function2;)Ljava/lang/Object;
	areturn
  Labels:

public static final boolean isEmpty();
  Signature: ()Z
  Code:
   Stack=1, Locals=0, Args_size=0
	getstatic	Field scala/xml/Null$.MODULE$:Lscala/xml/Null$;
	invokevirtual	Method scala/xml/Null$.isEmpty:()Z
	ireturn
  Labels:

public static final scala.Option find(scala.Function1);
  Signature: (Lscala/Function1;)Lscala/Option;
  Code:
   Stack=2, Locals=1, Args_size=1
	getstatic	Field scala/xml/Null$.MODULE$:Lscala/xml/Null$;
	aload_0
	invokevirtual	Method scala/xml/Null$.find:(Lscala/Function1;)Lscala/Option;
	areturn
  Labels:

public static final boolean exists(scala.Function1);
  Signature: (Lscala/Function1;)Z
  Code:
   Stack=2, Locals=1, Args_size=1
	getstatic	Field scala/xml/Null$.MODULE$:Lscala/xml/Null$;
	aload_0
	invokevirtual	Method scala/xml/Null$.exists:(Lscala/Function1;)Z
	ireturn
  Labels:

public static final boolean forall(scala.Function1);
  Signature: (Lscala/Function1;)Z
  Code:
   Stack=2, Locals=1, Args_size=1
	getstatic	Field scala/xml/Null$.MODULE$:Lscala/xml/Null$;
	aload_0
	invokevirtual	Method scala/xml/Null$.forall:(Lscala/Function1;)Z
	ireturn
  Labels:

public static final void foreach(scala.Function1);
  Signature: (Lscala/Function1;)V
  Code:
   Stack=2, Locals=1, Args_size=1
	getstatic	Field scala/xml/Null$.MODULE$:Lscala/xml/Null$;
	aload_0
	invokevirtual	Method scala/xml/Null$.foreach:(Lscala/Function1;)V
	return
  Labels:

public static final scala.collection.Iterator elements();
  Signature: ()Lscala/collection/Iterator;
  Code:
   Stack=1, Locals=0, Args_size=0
	getstatic	Field scala/xml/Null$.MODULE$:Lscala/xml/Null$;
	invokevirtual	Method scala/xml/Null$.elements:()Lscala/collection/Iterator;
	areturn
  Labels:
  Deprecated: true

public static final scala.collection.generic.GenericCompanion companion();
  Signature: ()Lscala/collection/generic/GenericCompanion;
  Code:
   Stack=1, Locals=0, Args_size=0
	getstatic	Field scala/xml/Null$.MODULE$:Lscala/xml/Null$;
	invokevirtual	Method scala/xml/Null$.companion:()Lscala/collection/generic/GenericCompanion;
	areturn
  Labels:

public static final boolean xml_$bang$eq(java.lang.Object);
  Signature: (Ljava/lang/Object;)Z
  Code:
   Stack=2, Locals=1, Args_size=1
	getstatic	Field scala/xml/Null$.MODULE$:Lscala/xml/Null$;
	aload_0
	invokevirtual	Method scala/xml/Null$.xml_$bang$eq:(Ljava/lang/Object;)Z
	ireturn
  Labels:

public static final boolean xml_$eq$eq(java.lang.Object);
  Signature: (Ljava/lang/Object;)Z
  Code:
   Stack=2, Locals=1, Args_size=1
	getstatic	Field scala/xml/Null$.MODULE$:Lscala/xml/Null$;
	aload_0
	invokevirtual	Method scala/xml/Null$.xml_$eq$eq:(Ljava/lang/Object;)Z
	ireturn
  Labels:

public static final boolean strict_$bang$eq(scala.xml.Equality);
  Signature: (Lscala/xml/Equality;)Z
  Code:
   Stack=2, Locals=1, Args_size=1
	getstatic	Field scala/xml/Null$.MODULE$:Lscala/xml/Null$;
	aload_0
	invokevirtual	Method scala/xml/Null$.strict_$bang$eq:(Lscala/xml/Equality;)Z
	ireturn
  Labels:

public static final scala.xml.MetaData remove(java.lang.String, scala.xml.Node, java.lang.String);
  Signature: (Ljava/lang/String;Lscala/xml/Node;Ljava/lang/String;)Lscala/xml/MetaData;
  Code:
   Stack=4, Locals=3, Args_size=3
	getstatic	Field scala/xml/Null$.MODULE$:Lscala/xml/Null$;
	aload_0
	aload_1
	aload_2
	invokevirtual	Method scala/xml/Null$.remove:(Ljava/lang/String;Lscala/xml/Node;Ljava/lang/String;)Lscala/xml/MetaData;
	areturn
  Labels:

public static final scala.Option get(java.lang.String, scala.xml.NamespaceBinding, java.lang.String);
  Signature: (Ljava/lang/String;Lscala/xml/NamespaceBinding;Ljava/lang/String;)Lscala/Option;
  Code:
   Stack=4, Locals=3, Args_size=3
	getstatic	Field scala/xml/Null$.MODULE$:Lscala/xml/Null$;
	aload_0
	aload_1
	aload_2
	invokevirtual	Method scala/xml/Null$.get:(Ljava/lang/String;Lscala/xml/NamespaceBinding;Ljava/lang/String;)Lscala/Option;
	areturn
  Labels:
  Signature: length = 0x2
   01 FFFFFFA4 

public static final scala.Option get(java.lang.String, scala.xml.Node, java.lang.String);
  Signature: (Ljava/lang/String;Lscala/xml/Node;Ljava/lang/String;)Lscala/Option;
  Code:
   Stack=4, Locals=3, Args_size=3
	getstatic	Field scala/xml/Null$.MODULE$:Lscala/xml/Null$;
	aload_0
	aload_1
	aload_2
	invokevirtual	Method scala/xml/Null$.get:(Ljava/lang/String;Lscala/xml/Node;Ljava/lang/String;)Lscala/Option;
	areturn
  Labels:
  Signature: length = 0x2
   01 FFFFFFA8 

public static final scala.Option get(java.lang.String);
  Signature: (Ljava/lang/String;)Lscala/Option;
  Code:
   Stack=2, Locals=1, Args_size=1
	getstatic	Field scala/xml/Null$.MODULE$:Lscala/xml/Null$;
	aload_0
	invokevirtual	Method scala/xml/Null$.get:(Ljava/lang/String;)Lscala/Option;
	areturn
  Labels:
  Signature: length = 0x2
   01 FFFFFFAC 

public static final scala.collection.immutable.Map asAttrMap();
  Signature: ()Lscala/collection/immutable/Map;
  Code:
   Stack=1, Locals=0, Args_size=0
	getstatic	Field scala/xml/Null$.MODULE$:Lscala/xml/Null$;
	invokevirtual	Method scala/xml/Null$.asAttrMap:()Lscala/collection/immutable/Map;
	areturn
  Labels:
  Signature: length = 0x2
   01 FFFFFFB1 

public static final java.lang.String prefixedKey();
  Signature: ()Ljava/lang/String;
  Code:
   Stack=1, Locals=0, Args_size=0
	getstatic	Field scala/xml/Null$.MODULE$:Lscala/xml/Null$;
	invokevirtual	Method scala/xml/Null$.prefixedKey:()Ljava/lang/String;
	areturn
  Labels:

public static final int size();
  Signature: ()I
  Code:
   Stack=1, Locals=0, Args_size=0
	getstatic	Field scala/xml/Null$.MODULE$:Lscala/xml/Null$;
	invokevirtual	Method scala/xml/Null$.size:()I
	ireturn
  Labels:

public static final boolean canEqual(java.lang.Object);
  Signature: (Ljava/lang/Object;)Z
  Code:
   Stack=2, Locals=1, Args_size=1
	getstatic	Field scala/xml/Null$.MODULE$:Lscala/xml/Null$;
	aload_0
	invokevirtual	Method scala/xml/Null$.canEqual:(Ljava/lang/Object;)Z
	ireturn
  Labels:

public static final scala.collection.Seq apply(java.lang.String, scala.xml.Node, java.lang.String);
  Signature: (Ljava/lang/String;Lscala/xml/Node;Ljava/lang/String;)Lscala/collection/Seq;
  Code:
   Stack=4, Locals=3, Args_size=3
	getstatic	Field scala/xml/Null$.MODULE$:Lscala/xml/Null$;
	aload_0
	aload_1
	aload_2
	invokevirtual	Method scala/xml/Null$.apply:(Ljava/lang/String;Lscala/xml/Node;Ljava/lang/String;)Lscala/collection/Seq;
	areturn
  Labels:
  Signature: length = 0x2
   01 FFFFFFBE 

public static final scala.collection.TraversableView view(int, int);
  Signature: (II)Lscala/collection/TraversableView;
  Code:
   Stack=3, Locals=2, Args_size=2
	getstatic	Field scala/xml/Null$.MODULE$:Lscala/xml/Null$;
	iload_0
	iload_1
	invokevirtual	Method scala/xml/Null$.view:(II)Lscala/collection/TraversableView;
	areturn
  Labels:

public static final scala.collection.TraversableView view();
  Signature: ()Lscala/collection/TraversableView;
  Code:
   Stack=1, Locals=0, Args_size=0
	getstatic	Field scala/xml/Null$.MODULE$:Lscala/xml/Null$;
	invokevirtual	Method scala/xml/Null$.view:()Lscala/collection/TraversableView;
	areturn
  Labels:

public static final java.lang.Object filter(scala.Function1);
  Signature: (Lscala/Function1;)Ljava/lang/Object;
  Code:
   Stack=2, Locals=1, Args_size=1
	getstatic	Field scala/xml/Null$.MODULE$:Lscala/xml/Null$;
	aload_0
	invokevirtual	Method scala/xml/Null$.filter:(Lscala/Function1;)Ljava/lang/Object;
	areturn
  Labels:

}

