Compiled from "Null.scala"
public final class scala.xml.Null$ extends scala.xml.MetaData implements scala.ScalaObject,scala.Product,java.io.Serializable
  SourceFile: "Null.scala"
  Scala: length = 0x
   
  InnerClass: 
   public WithFilter=class scala/collection/TraversableLike$WithFilter of class scala/collection/TraversableLike
  minor version: 0
  major version: 49
  Constant pool:
Asciz	SourceFile;
Asciz	Null.scala;
Asciz	Scala;
Asciz	MODULE$;
Asciz	Lscala/xml/Null$;;
Asciz	<clinit>;
Asciz	()V;
Asciz	Code;
Asciz	scala/xml/Null$;
class	scala/xml/Null$
Asciz	<init>;
NameAndType	"<init>":()V
Method	scala/xml/Null$."<init>":()V
Asciz	LineNumberTable;
Asciz	scala/xml/MetaData;
class	scala/xml/MetaData
Method	scala/xml/MetaData."<init>":()V
NameAndType	MODULE$:Lscala/xml/Null$;
Field	scala/xml/Null$.MODULE$:Lscala/xml/Null$;
Asciz	scala/Product$class;
class	scala/Product$class
Asciz	$init$;
Asciz	(Lscala/Product;)V;
NameAndType	$init$:(Lscala/Product;)V
Method	scala/Product$class.$init$:(Lscala/Product;)V
Asciz	filter;
Asciz	(Lscala/Function1;)Ljava/lang/Object;;
Asciz	(Lscala/Function1;)Lscala/xml/MetaData;;
NameAndType	filter:(Lscala/Function1;)Lscala/xml/MetaData;
Method	scala/xml/Null$.filter:(Lscala/Function1;)Lscala/xml/MetaData;
Asciz	this;
Asciz	p;
Asciz	Lscala/Function1;;
Asciz	LocalVariableTable;
Asciz	getNamespace;
Asciz	(Lscala/xml/Node;)Ljava/lang/String;;
Asciz	(Lscala/xml/Node;)Lscala/runtime/Null$;;
NameAndType	getNamespace:(Lscala/xml/Node;)Lscala/runtime/Null$;
Method	scala/xml/Null$.getNamespace:(Lscala/xml/Node;)Lscala/runtime/Null$;
Asciz	owner;
Asciz	Lscala/xml/Node;;
Asciz	next;
Asciz	()Lscala/xml/MetaData;;
Asciz	()Lscala/runtime/Null$;;
NameAndType	next:()Lscala/runtime/Null$;
Method	scala/xml/Null$.next:()Lscala/runtime/Null$;
Asciz	key;
Asciz	()Ljava/lang/String;;
NameAndType	key:()Lscala/runtime/Null$;
Method	scala/xml/Null$.key:()Lscala/runtime/Null$;
Asciz	value;
Asciz	()Lscala/collection/Seq;;
NameAndType	value:()Lscala/runtime/Null$;
Method	scala/xml/Null$.value:()Lscala/runtime/Null$;
Asciz	apply;
Asciz	(Ljava/lang/String;)Lscala/collection/Seq;;
Asciz	(Ljava/lang/String;)Lscala/runtime/Null$;;
NameAndType	apply:(Ljava/lang/String;)Lscala/runtime/Null$;
Method	scala/xml/Null$.apply:(Ljava/lang/String;)Lscala/runtime/Null$;
Asciz	Ljava/lang/String;;
Asciz	(Ljava/lang/String;Lscala/xml/NamespaceBinding;Ljava/lang/String;)Lscala/collection/Seq;;
Asciz	(Ljava/lang/String;Lscala/xml/NamespaceBinding;Ljava/lang/String;)Lscala/runtime/Null$;;
NameAndType	apply:(Ljava/lang/String;Lscala/xml/NamespaceBinding;Ljava/lang/String;)Lscala/runtime/Null$;
Method	scala/xml/Null$.apply:(Ljava/lang/String;Lscala/xml/NamespaceBinding;Ljava/lang/String;)Lscala/runtime/Null$;
Asciz	namespace_uri;
Asciz	scp;
Asciz	Lscala/xml/NamespaceBinding;;
Asciz	k;
Asciz	remove;
Asciz	(Ljava/lang/String;)Lscala/xml/MetaData;;
Asciz	(Ljava/lang/String;)Lscala/xml/Null$;;
NameAndType	remove:(Ljava/lang/String;)Lscala/xml/Null$;
Method	scala/xml/Null$.remove:(Ljava/lang/String;)Lscala/xml/Null$;
Asciz	(Ljava/lang/String;Lscala/xml/NamespaceBinding;Ljava/lang/String;)Lscala/xml/MetaData;;
Asciz	(Ljava/lang/String;Lscala/xml/NamespaceBinding;Ljava/lang/String;)Lscala/xml/Null$;;
NameAndType	remove:(Ljava/lang/String;Lscala/xml/NamespaceBinding;Ljava/lang/String;)Lscala/xml/Null$;
Method	scala/xml/Null$.remove:(Ljava/lang/String;Lscala/xml/NamespaceBinding;Ljava/lang/String;)Lscala/xml/Null$;
Asciz	namespace;
Asciz	scope;
Asciz	readResolve;
Asciz	()Ljava/lang/Object;;
Asciz	productElement;
Asciz	(I)Ljava/lang/Object;;
Asciz	java/lang/IndexOutOfBoundsException;
class	java/lang/IndexOutOfBoundsException
Asciz	scala/runtime/BoxesRunTime;
class	scala/runtime/BoxesRunTime
Asciz	boxToInteger;
Asciz	(I)Ljava/lang/Integer;;
NameAndType	boxToInteger:(I)Ljava/lang/Integer;
Method	scala/runtime/BoxesRunTime.boxToInteger:(I)Ljava/lang/Integer;
Asciz	java/lang/Object;
class	java/lang/Object
Asciz	toString;
NameAndType	toString:()Ljava/lang/String;
Method	java/lang/Object.toString:()Ljava/lang/String;
Asciz	(Ljava/lang/String;)V;
NameAndType	"<init>":(Ljava/lang/String;)V
Method	java/lang/IndexOutOfBoundsException."<init>":(Ljava/lang/String;)V
Asciz	scala/MatchError;
class	scala/MatchError
Method	scala/MatchError."<init>":(Ljava/lang/String;)V
Asciz	productArity;
Asciz	()I;
Asciz	productPrefix;
Asciz	Null;
String	Null
Asciz	wellformed;
Asciz	(Lscala/xml/NamespaceBinding;)Z;
Asciz	buildString;
Asciz	(Lscala/collection/mutable/StringBuilder;)Lscala/collection/mutable/StringBuilder;;
Asciz	sb;
Asciz	Lscala/collection/mutable/StringBuilder;;
Asciz	;
String	
Asciz	toString1;
Asciz	(Lscala/collection/mutable/StringBuilder;)V;
Asciz	hashCode;
Asciz	scala/xml/Utility$;
class	scala/xml/Utility$
Asciz	Lscala/xml/Utility$;;
NameAndType	MODULE$:Lscala/xml/Utility$;
Field	scala/xml/Utility$.MODULE$:Lscala/xml/Utility$;
Asciz	java/lang/String;
class	java/lang/String
Asciz	charAt;
Asciz	(I)C;
NameAndType	charAt:(I)C
Method	java/lang/String.charAt:(I)C
Asciz	scala/xml/parsing/TokenTests$class;
class	scala/xml/parsing/TokenTests$class
Asciz	isNameStart;
Asciz	(Lscala/xml/parsing/TokenTests;C)Z;
NameAndType	isNameStart:(Lscala/xml/parsing/TokenTests;C)Z
Method	scala/xml/parsing/TokenTests$class.isNameStart:(Lscala/xml/parsing/TokenTests;C)Z
Asciz	java/lang/IllegalArgumentException;
class	java/lang/IllegalArgumentException
Asciz	scala/collection/mutable/StringBuilder;
class	scala/collection/mutable/StringBuilder
Method	scala/collection/mutable/StringBuilder."<init>":()V
Asciz	not a valid attribute name ';
String	not a valid attribute name '
Asciz	append;
Asciz	(Ljava/lang/Object;)Lscala/collection/mutable/StringBuilder;;
NameAndType	append:(Ljava/lang/Object;)Lscala/collection/mutable/StringBuilder;
Method	scala/collection/mutable/StringBuilder.append:(Ljava/lang/Object;)Lscala/collection/mutable/StringBuilder;
Asciz	', so can never match !;
String	', so can never match !
Method	scala/collection/mutable/StringBuilder.toString:()Ljava/lang/String;
Method	java/lang/IllegalArgumentException."<init>":(Ljava/lang/String;)V
Asciz	map;
Asciz	(Lscala/Function1;)Lscala/collection/immutable/List;;
Asciz	scala/collection/immutable/Nil$;
class	scala/collection/immutable/Nil$
Asciz	Lscala/collection/immutable/Nil$;;
NameAndType	MODULE$:Lscala/collection/immutable/Nil$;
Field	scala/collection/immutable/Nil$.MODULE$:Lscala/collection/immutable/Nil$;
Asciz	f;
Asciz	(Lscala/Function1<Lscala/xml/MetaData;Lscala/xml/Text;>;)Lscala/collection/immutable/List<Lscala/xml/Text;>;;
Asciz	Signature;
Asciz	equals1;
Asciz	(Lscala/xml/MetaData;)Z;
Asciz	length;
NameAndType	length:()I
Method	scala/xml/MetaData.length:()I
Asciz	that;
Asciz	Lscala/xml/MetaData;;
Asciz	equals;
Asciz	(Ljava/lang/Object;)Z;
Asciz	Ljava/lang/Object;;
Asciz	temp2;
Asciz	isPrefixed;
Asciz	()Z;
Asciz	(I)I;
Asciz	i;
Asciz	I;
Asciz	hasNext;
Asciz	(Lscala/Function1<Lscala/xml/MetaData;Ljava/lang/Boolean;>;)Lscala/xml/MetaData;;
Asciz	iterator;
Asciz	()Lscala/collection/Iterator;;
Asciz	scala/collection/Iterator$;
class	scala/collection/Iterator$
Asciz	Lscala/collection/Iterator$;;
NameAndType	MODULE$:Lscala/collection/Iterator$;
Field	scala/collection/Iterator$.MODULE$:Lscala/collection/Iterator$;
Asciz	empty;
NameAndType	empty:()Lscala/collection/Iterator;
Method	scala/collection/Iterator$.empty:()Lscala/collection/Iterator;
Asciz	copy;
Asciz	(Lscala/xml/MetaData;)Lscala/xml/MetaData;;
Asciz	containedIn1;
Asciz	m;
Asciz	(Lscala/xml/MetaData;Lscala/xml/NamespaceBinding;)Lscala/xml/MetaData;;
Asciz	append$default$2;
Asciz	()Lscala/xml/NamespaceBinding;;
Asciz	scala/xml/TopScope$;
class	scala/xml/TopScope$
Asciz	Lscala/xml/TopScope$;;
NameAndType	MODULE$:Lscala/xml/TopScope$;
Field	scala/xml/TopScope$.MODULE$:Lscala/xml/TopScope$;
Asciz	productElements;
Asciz	(Lscala/Product;)Lscala/collection/Iterator;;
NameAndType	productElements:(Lscala/Product;)Lscala/collection/Iterator;
Method	scala/Product$class.productElements:(Lscala/Product;)Lscala/collection/Iterator;
Asciz	Deprecated;
Asciz	productIterator;
NameAndType	productIterator:(Lscala/Product;)Lscala/collection/Iterator;
Method	scala/Product$class.productIterator:(Lscala/Product;)Lscala/collection/Iterator;
Asciz	InnerClasses;
Asciz	scala/collection/TraversableLike$WithFilter;
class	scala/collection/TraversableLike$WithFilter
Asciz	scala/collection/TraversableLike;
class	scala/collection/TraversableLike
Asciz	WithFilter;
Asciz	scala/ScalaObject;
class	scala/ScalaObject
Asciz	scala/Product;
class	scala/Product
Asciz	java/io/Serializable;
class	java/io/Serializable

{
public static final scala.xml.Null$ MODULE$;
  Signature: Lscala/xml/Null$;

public static {};
  Signature: ()V
  Code:
   Stack=1, Locals=0, Args_size=0
	new	class scala/xml/Null$
	invokespecial	Method "<init>":()V
	return
  Labels:

private scala.xml.Null$();
  Signature: ()V
  Code:
   Stack=1, Locals=1, Args_size=1
	aload_0
	invokespecial	Method scala/xml/MetaData."<init>":()V
	aload_0
	putstatic	Field MODULE$:Lscala/xml/Null$;
	aload_0
	invokestatic	Method scala/Product$class.$init$:(Lscala/Product;)V
	return
  Labels:

public java.lang.Object filter(scala.Function1);
  Signature: (Lscala/Function1;)Ljava/lang/Object;
  Code:
   Stack=2, Locals=2, Args_size=2
	aload_0
	aload_1
	invokevirtual	Method filter:(Lscala/Function1;)Lscala/xml/MetaData;
	areturn
  Labels:
  LocalVariableTable: 
   Start  Length  Slot  Name   Signature
   0      6      0    this       Lscala/xml/Null$;
   0      6      1    p       Lscala/Function1;


public java.lang.String getNamespace(scala.xml.Node);
  Signature: (Lscala/xml/Node;)Ljava/lang/String;
  Code:
   Stack=2, Locals=2, Args_size=2
	aload_0
	aload_1
	invokevirtual	Method getNamespace:(Lscala/xml/Node;)Lscala/runtime/Null$;
	pop
	aconst_null
	areturn
  Labels:
  LocalVariableTable: 
   Start  Length  Slot  Name   Signature
   0      8      0    this       Lscala/xml/Null$;
   0      8      1    owner       Lscala/xml/Node;


public scala.xml.MetaData next();
  Signature: ()Lscala/xml/MetaData;
  Code:
   Stack=1, Locals=1, Args_size=1
	aload_0
	invokevirtual	Method next:()Lscala/runtime/Null$;
	pop
	aconst_null
	areturn
  Labels:

public java.lang.String key();
  Signature: ()Ljava/lang/String;
  Code:
   Stack=1, Locals=1, Args_size=1
	aload_0
	invokevirtual	Method key:()Lscala/runtime/Null$;
	pop
	aconst_null
	areturn
  Labels:

public scala.collection.Seq value();
  Signature: ()Lscala/collection/Seq;
  Code:
   Stack=1, Locals=1, Args_size=1
	aload_0
	invokevirtual	Method value:()Lscala/runtime/Null$;
	pop
	aconst_null
	areturn
  Labels:

public scala.collection.Seq apply(java.lang.String);
  Signature: (Ljava/lang/String;)Lscala/collection/Seq;
  Code:
   Stack=2, Locals=2, Args_size=2
	aload_0
	aload_1
	invokevirtual	Method apply:(Ljava/lang/String;)Lscala/runtime/Null$;
	pop
	aconst_null
	areturn
  Labels:
  LocalVariableTable: 
   Start  Length  Slot  Name   Signature
   0      8      0    this       Lscala/xml/Null$;
   0      8      1    key       Ljava/lang/String;


public scala.collection.Seq apply(java.lang.String, scala.xml.NamespaceBinding, java.lang.String);
  Signature: (Ljava/lang/String;Lscala/xml/NamespaceBinding;Ljava/lang/String;)Lscala/collection/Seq;
  Code:
   Stack=4, Locals=4, Args_size=4
	aload_0
	aload_1
	aload_2
	aload_3
	invokevirtual	Method apply:(Ljava/lang/String;Lscala/xml/NamespaceBinding;Ljava/lang/String;)Lscala/runtime/Null$;
	pop
	aconst_null
	areturn
  Labels:
  LocalVariableTable: 
   Start  Length  Slot  Name   Signature
   0      10      0    this       Lscala/xml/Null$;
   0      10      1    namespace_uri       Ljava/lang/String;
   0      10      2    scp       Lscala/xml/NamespaceBinding;
   0      10      3    k       Ljava/lang/String;


public scala.xml.MetaData remove(java.lang.String);
  Signature: (Ljava/lang/String;)Lscala/xml/MetaData;
  Code:
   Stack=2, Locals=2, Args_size=2
	aload_0
	aload_1
	invokevirtual	Method remove:(Ljava/lang/String;)Lscala/xml/Null$;
	areturn
  Labels:
  LocalVariableTable: 
   Start  Length  Slot  Name   Signature
   0      6      0    this       Lscala/xml/Null$;
   0      6      1    key       Ljava/lang/String;


public scala.xml.MetaData remove(java.lang.String, scala.xml.NamespaceBinding, java.lang.String);
  Signature: (Ljava/lang/String;Lscala/xml/NamespaceBinding;Ljava/lang/String;)Lscala/xml/MetaData;
  Code:
   Stack=4, Locals=4, Args_size=4
	aload_0
	aload_1
	aload_2
	aload_3
	invokevirtual	Method remove:(Ljava/lang/String;Lscala/xml/NamespaceBinding;Ljava/lang/String;)Lscala/xml/Null$;
	areturn
  Labels:
  LocalVariableTable: 
   Start  Length  Slot  Name   Signature
   0      8      0    this       Lscala/xml/Null$;
   0      8      1    namespace       Ljava/lang/String;
   0      8      2    scope       Lscala/xml/NamespaceBinding;
   0      8      3    key       Ljava/lang/String;


public java.lang.Object readResolve();
  Signature: ()Ljava/lang/Object;
  Code:
   Stack=1, Locals=1, Args_size=1
	getstatic	Field MODULE$:Lscala/xml/Null$;
	areturn
  Labels:

public java.lang.Object productElement(int);
  Signature: (I)Ljava/lang/Object;
  Code:
   Stack=3, Locals=2, Args_size=2
	iconst_1
	ifeq	l1 // new
	new	class java/lang/IndexOutOfBoundsException
	dup
	iload_1
	invokestatic	Method scala/runtime/BoxesRunTime.boxToInteger:(I)Ljava/lang/Integer;
	invokevirtual	Method java/lang/Object.toString:()Ljava/lang/String;
	invokespecial	Method java/lang/IndexOutOfBoundsException."<init>":(Ljava/lang/String;)V
	athrow
l1	new	class scala/MatchError
	dup
	iload_1
	invokestatic	Method scala/runtime/BoxesRunTime.boxToInteger:(I)Ljava/lang/Integer;
	invokevirtual	Method java/lang/Object.toString:()Ljava/lang/String;
	invokespecial	Method scala/MatchError."<init>":(Ljava/lang/String;)V
	athrow
  Labels:
   	l1 = 19 // new

public int productArity();
  Signature: ()I
  Code:
   Stack=1, Locals=1, Args_size=1
	iconst_0
	ireturn
  Labels:

public java.lang.String productPrefix();
  Signature: ()Ljava/lang/String;
  Code:
   Stack=1, Locals=1, Args_size=1
	ldc	String Null
	areturn
  Labels:

public scala.xml.Null$ remove(java.lang.String, scala.xml.NamespaceBinding, java.lang.String);
  Signature: (Ljava/lang/String;Lscala/xml/NamespaceBinding;Ljava/lang/String;)Lscala/xml/Null$;
  Code:
   Stack=1, Locals=4, Args_size=4
	aload_0
	areturn
  Labels:
  LocalVariableTable: 
   Start  Length  Slot  Name   Signature
   0      2      0    this       Lscala/xml/Null$;
   0      2      1    namespace       Ljava/lang/String;
   0      2      2    scope       Lscala/xml/NamespaceBinding;
   0      2      3    key       Ljava/lang/String;


public scala.xml.Null$ remove(java.lang.String);
  Signature: (Ljava/lang/String;)Lscala/xml/Null$;
  Code:
   Stack=1, Locals=2, Args_size=2
	aload_0
	areturn
  Labels:
  LocalVariableTable: 
   Start  Length  Slot  Name   Signature
   0      2      0    this       Lscala/xml/Null$;
   0      2      1    key       Ljava/lang/String;


public boolean wellformed(scala.xml.NamespaceBinding);
  Signature: (Lscala/xml/NamespaceBinding;)Z
  Code:
   Stack=1, Locals=2, Args_size=2
	iconst_1
	ireturn
  Labels:
  LocalVariableTable: 
   Start  Length  Slot  Name   Signature
   0      2      0    this       Lscala/xml/Null$;
   0      2      1    scope       Lscala/xml/NamespaceBinding;


public scala.collection.mutable.StringBuilder buildString(scala.collection.mutable.StringBuilder);
  Signature: (Lscala/collection/mutable/StringBuilder;)Lscala/collection/mutable/StringBuilder;
  Code:
   Stack=1, Locals=2, Args_size=2
	aload_1
	areturn
  Labels:
  LocalVariableTable: 
   Start  Length  Slot  Name   Signature
   0      2      0    this       Lscala/xml/Null$;
   0      2      1    sb       Lscala/collection/mutable/StringBuilder;


public java.lang.String toString();
  Signature: ()Ljava/lang/String;
  Code:
   Stack=1, Locals=1, Args_size=1
	ldc	String 
	areturn
  Labels:

public void toString1(scala.collection.mutable.StringBuilder);
  Signature: (Lscala/collection/mutable/StringBuilder;)V
  Code:
   Stack=0, Locals=2, Args_size=2
	return
  Labels:
  LocalVariableTable: 
   Start  Length  Slot  Name   Signature
   0      1      0    this       Lscala/xml/Null$;
   0      1      1    sb       Lscala/collection/mutable/StringBuilder;


public java.lang.String toString1();
  Signature: ()Ljava/lang/String;
  Code:
   Stack=1, Locals=1, Args_size=1
	ldc	String 
	areturn
  Labels:

public int hashCode();
  Signature: ()I
  Code:
   Stack=1, Locals=1, Args_size=1
	iconst_0
	ireturn
  Labels:

public scala.runtime.Null$ apply(java.lang.String, scala.xml.NamespaceBinding, java.lang.String);
  Signature: (Ljava/lang/String;Lscala/xml/NamespaceBinding;Ljava/lang/String;)Lscala/runtime/Null$;
  Code:
   Stack=1, Locals=4, Args_size=4
	aconst_null
	areturn
  Labels:
  LocalVariableTable: 
   Start  Length  Slot  Name   Signature
   0      2      0    this       Lscala/xml/Null$;
   0      2      1    namespace       Ljava/lang/String;
   0      2      2    scope       Lscala/xml/NamespaceBinding;
   0      2      3    key       Ljava/lang/String;


public scala.runtime.Null$ apply(java.lang.String);
  Signature: (Ljava/lang/String;)Lscala/runtime/Null$;
  Code:
   Stack=4, Locals=4, Args_size=2
	getstatic	Field scala/xml/Utility$.MODULE$:Lscala/xml/Utility$;
	aload_1
	iconst_0
	invokevirtual	Method java/lang/String.charAt:(I)C
	istore_3
	astore_2
	aload_2
	iload_3
	invokestatic	Method scala/xml/parsing/TokenTests$class.isNameStart:(Lscala/xml/parsing/TokenTests;C)Z
	ifeq	l1 // new
	aconst_null
	areturn
l1	new	class java/lang/IllegalArgumentException
	dup
	new	class scala/collection/mutable/StringBuilder
	dup
	invokespecial	Method scala/collection/mutable/StringBuilder."<init>":()V
	ldc	String not a valid attribute name '
	invokevirtual	Method scala/collection/mutable/StringBuilder.append:(Ljava/lang/Object;)Lscala/collection/mutable/StringBuilder;
	aload_1
	invokevirtual	Method scala/collection/mutable/StringBuilder.append:(Ljava/lang/Object;)Lscala/collection/mutable/StringBuilder;
	ldc	String ', so can never match !
	invokevirtual	Method scala/collection/mutable/StringBuilder.append:(Ljava/lang/Object;)Lscala/collection/mutable/StringBuilder;
	invokevirtual	Method scala/collection/mutable/StringBuilder.toString:()Ljava/lang/String;
	invokespecial	Method java/lang/IllegalArgumentException."<init>":(Ljava/lang/String;)V
	athrow
  Labels:
   	l1 = 20 // new
  LocalVariableTable: 
   Start  Length  Slot  Name   Signature
   0      52      0    this       Lscala/xml/Null$;
   0      52      1    key       Ljava/lang/String;


public scala.collection.immutable.List map(scala.Function1);
  Signature: (Lscala/Function1;)Lscala/collection/immutable/List;
  Code:
   Stack=1, Locals=2, Args_size=2
	getstatic	Field scala/collection/immutable/Nil$.MODULE$:Lscala/collection/immutable/Nil$;
	areturn
  Labels:
  LocalVariableTable: 
   Start  Length  Slot  Name   Signature
   0      4      0    this       Lscala/xml/Null$;
   0      4      1    f       Lscala/Function1;

  Signature: length = 0x2
   00 FFFFFF9F 

public boolean equals1(scala.xml.MetaData);
  Signature: (Lscala/xml/MetaData;)Z
  Code:
   Stack=2, Locals=2, Args_size=2
	aload_1
	invokevirtual	Method scala/xml/MetaData.length:()I
	iconst_0
	if_icmpne	l1 // iconst_0
	iconst_1
	goto	l2 // ireturn
l1	iconst_0
l2	ireturn
  Labels:
   	l1 = 12 // iconst_0
   	l2 = 13 // ireturn
  LocalVariableTable: 
   Start  Length  Slot  Name   Signature
   0      14      0    this       Lscala/xml/Null$;
   0      14      1    that       Lscala/xml/MetaData;


public boolean equals(java.lang.Object);
  Signature: (Ljava/lang/Object;)Z
  Code:
   Stack=3, Locals=3, Args_size=2
	aload_1
	instanceof	class scala/xml/MetaData
	ifeq	l1 // iconst_1
	aload_1
	checkcast	class scala/xml/MetaData
	astore_2
	iconst_1
	ifeq	l2 // new
	aload_2
	invokevirtual	Method scala/xml/MetaData.length:()I
	iconst_0
	if_icmpne	l3 // iconst_0
	iconst_1
	goto	l4 // ireturn
l3	iconst_0
	goto	l4 // ireturn
l2	new	class scala/MatchError
	dup
	aload_1
	invokevirtual	Method java/lang/Object.toString:()Ljava/lang/String;
	invokespecial	Method scala/MatchError."<init>":(Ljava/lang/String;)V
	athrow
l1	iconst_1
	ifeq	l5 // new
	iconst_0
l4	ireturn
l5	new	class scala/MatchError
	dup
	aload_1
	invokevirtual	Method java/lang/Object.toString:()Ljava/lang/String;
	invokespecial	Method scala/MatchError."<init>":(Ljava/lang/String;)V
	athrow
  Labels:
   	l3 = 28 // iconst_0
   	l2 = 32 // new
   	l1 = 44 // iconst_1
   	l4 = 49 // ireturn
   	l5 = 50 // new
  LocalVariableTable: 
   Start  Length  Slot  Name   Signature
   0      62      0    this       Lscala/xml/Null$;
   0      62      1    that       Ljava/lang/Object;
   12      32      2    temp2       Lscala/xml/MetaData;


public boolean isPrefixed();
  Signature: ()Z
  Code:
   Stack=1, Locals=1, Args_size=1
	iconst_0
	ireturn
  Labels:

public final int length(int);
  Signature: (I)I
  Code:
   Stack=1, Locals=2, Args_size=2
	iload_1
	ireturn
  Labels:
  LocalVariableTable: 
   Start  Length  Slot  Name   Signature
   0      2      0    this       Lscala/xml/Null$;
   0      2      1    i       I


public final int length();
  Signature: ()I
  Code:
   Stack=1, Locals=1, Args_size=1
	iconst_0
	ireturn
  Labels:

public scala.runtime.Null$ value();
  Signature: ()Lscala/runtime/Null$;
  Code:
   Stack=1, Locals=1, Args_size=1
	aconst_null
	areturn
  Labels:

public scala.runtime.Null$ key();
  Signature: ()Lscala/runtime/Null$;
  Code:
   Stack=1, Locals=1, Args_size=1
	aconst_null
	areturn
  Labels:

public scala.runtime.Null$ next();
  Signature: ()Lscala/runtime/Null$;
  Code:
   Stack=1, Locals=1, Args_size=1
	aconst_null
	areturn
  Labels:

public final boolean hasNext();
  Signature: ()Z
  Code:
   Stack=1, Locals=1, Args_size=1
	iconst_0
	ireturn
  Labels:

public scala.runtime.Null$ getNamespace(scala.xml.Node);
  Signature: (Lscala/xml/Node;)Lscala/runtime/Null$;
  Code:
   Stack=1, Locals=2, Args_size=2
	aconst_null
	areturn
  Labels:
  LocalVariableTable: 
   Start  Length  Slot  Name   Signature
   0      2      0    this       Lscala/xml/Null$;
   0      2      1    owner       Lscala/xml/Node;


public scala.xml.MetaData filter(scala.Function1);
  Signature: (Lscala/Function1;)Lscala/xml/MetaData;
  Code:
   Stack=1, Locals=2, Args_size=2
	aload_0
	areturn
  Labels:
  LocalVariableTable: 
   Start  Length  Slot  Name   Signature
   0      2      0    this       Lscala/xml/Null$;
   0      2      1    f       Lscala/Function1;

  Signature: length = 0x2
   00 FFFFFFB2 

public scala.collection.Iterator iterator();
  Signature: ()Lscala/collection/Iterator;
  Code:
   Stack=1, Locals=1, Args_size=1
	getstatic	Field scala/collection/Iterator$.MODULE$:Lscala/collection/Iterator$;
	invokevirtual	Method scala/collection/Iterator$.empty:()Lscala/collection/Iterator;
	areturn
  Labels:

public scala.xml.MetaData copy(scala.xml.MetaData);
  Signature: (Lscala/xml/MetaData;)Lscala/xml/MetaData;
  Code:
   Stack=1, Locals=2, Args_size=2
	aload_1
	areturn
  Labels:
  LocalVariableTable: 
   Start  Length  Slot  Name   Signature
   0      2      0    this       Lscala/xml/Null$;
   0      2      1    next       Lscala/xml/MetaData;


public boolean containedIn1(scala.xml.MetaData);
  Signature: (Lscala/xml/MetaData;)Z
  Code:
   Stack=1, Locals=2, Args_size=2
	iconst_0
	ireturn
  Labels:
  LocalVariableTable: 
   Start  Length  Slot  Name   Signature
   0      2      0    this       Lscala/xml/Null$;
   0      2      1    m       Lscala/xml/MetaData;


public scala.xml.MetaData append(scala.xml.MetaData, scala.xml.NamespaceBinding);
  Signature: (Lscala/xml/MetaData;Lscala/xml/NamespaceBinding;)Lscala/xml/MetaData;
  Code:
   Stack=1, Locals=3, Args_size=3
	aload_1
	areturn
  Labels:
  LocalVariableTable: 
   Start  Length  Slot  Name   Signature
   0      2      0    this       Lscala/xml/Null$;
   0      2      1    m       Lscala/xml/MetaData;
   0      2      2    scope       Lscala/xml/NamespaceBinding;


public scala.xml.NamespaceBinding append$default$2();
  Signature: ()Lscala/xml/NamespaceBinding;
  Code:
   Stack=1, Locals=1, Args_size=1
	getstatic	Field scala/xml/TopScope$.MODULE$:Lscala/xml/TopScope$;
	areturn
  Labels:

public scala.collection.Iterator productElements();
  Signature: ()Lscala/collection/Iterator;
  Code:
   Stack=1, Locals=1, Args_size=1
	aload_0
	invokestatic	Method scala/Product$class.productElements:(Lscala/Product;)Lscala/collection/Iterator;
	areturn
  Labels:
  Deprecated: true

public scala.collection.Iterator productIterator();
  Signature: ()Lscala/collection/Iterator;
  Code:
   Stack=1, Locals=1, Args_size=1
	aload_0
	invokestatic	Method scala/Product$class.productIterator:(Lscala/Product;)Lscala/collection/Iterator;
	areturn
  Labels:

}

