Compiled from "Parsing.scala"
public final class scala.xml.Parsing extends java.lang.Object
  SourceFile: "Parsing.scala"
  ScalaSig: length = 0x278
   05 00 67 07 05 01 02 FFFFFF88 02 07 01 07 50 61 72 73
   69 6E 67 0A 02 03 04 01 03 78 6D 6C 0A 01 05 01
   05 73 63 61 6C 61 03 00 10 02 08 09 0D 01 02 06
   08 0A 02 FFFFFF84 FFFFFF80 FFFFFF80 FFFFFF88 02 0B 02 07 50 61 72 73 69
   6E 67 13 03 09 0C 14 10 02 0D 12 0D 01 0E 0A 02
   0F 10 01 04 6C 61 6E 67 0A 01 11 01 04 6A 61 76
   61 09 02 13 0E 02 06 4F 62 6A 65 63 74 10 02 15
   16 0D 01 04 09 02 17 04 02 0B 53 63 61 6C 61 4F
   62 6A 65 63 74 08 05 19 09 FFFFFF84 00 1A 01 06 3C 69
   6E 69 74 3E 14 01 07 08 05 1C 09 FFFFFF84 02 1D 01 07
   69 73 53 70 61 63 65 14 02 1E 21 10 02 15 1F 09
   02 20 04 02 07 42 6F 6F 6C 65 61 6E 08 05 22 1B
   FFFFFFC0 00 23 01 02 63 68 10 02 15 24 09 02 25 04 02
   04 43 68 61 72 08 05 1C 09 FFFFFF84 02 27 14 02 1E 28
   08 05 29 26 FFFFFFC0 00 2A 01 02 63 73 10 03 2B 33 23
   0E 02 2C 31 0E 02 2D 30 0D 01 2E 0A 02 2F 06 01
   06 3C 72 6F 6F 74 3E 09 01 05 09 02 32 04 01 07
   70 61 63 6B 61 67 65 09 02 34 35 02 03 53 65 71
   0A 02 32 04 08 07 37 09 FFFFFFC2 FFFFFF80 FFFFFF84 04 38 01 10 6E
   61 6D 65 43 68 61 72 54 79 70 65 4C 69 73 74 15
   01 39 10 03 3A 3F 41 0D 01 3B 0A 02 3C 3D 01 09
   69 6D 6D 75 74 61 62 6C 65 0A 02 3E 04 01 0A 63
   6F 6C 6C 65 63 74 69 6F 6E 09 02 40 3B 02 04 4C
   69 73 74 10 02 15 42 09 02 43 04 02 04 42 79 74
   65 08 06 45 09 FFFFFFA0 FFFFFF80 04 39 01 11 6E 61 6D 65 43
   68 61 72 54 79 70 65 4C 69 73 74 20 08 05 47 09
   FFFFFF84 00 48 01 0A 69 73 4E 61 6D 65 43 68 61 72 14
   02 1E 49 08 05 22 46 FFFFFFC0 00 23 08 05 4B 09 FFFFFF84 00
   4C 01 0B 69 73 4E 61 6D 65 53 74 61 72 74 14 02
   1E 4D 08 05 22 4A FFFFFFC0 00 23 08 05 4F 09 FFFFFF84 00 50
   01 06 69 73 4E 61 6D 65 14 02 1E 51 08 05 52 4E
   FFFFFFC0 00 53 01 01 73 10 02 54 57 0E 02 15 55 09 02
   56 04 01 06 50 72 65 64 65 66 09 02 58 59 02 06
   53 74 72 69 6E 67 0A 02 56 04 08 05 5B 09 FFFFFF84 00
   5C 01 0B 69 73 50 75 62 49 44 43 68 61 72 14 02
   1E 5D 08 05 5E 5A FFFFFFC0 00 23 01 01 63 08 05 60 09
   FFFFFF84 00 61 01 0A 63 68 65 63 6B 53 79 73 49 44 14
   02 1E 62 08 05 52 5F FFFFFFC0 00 53 08 05 64 09 FFFFFF84 00
   65 01 0A 63 68 65 63 6B 50 75 62 49 44 14 02 1E
   66 08 05 52 63 FFFFFFC0 00 53 
  InnerClass: 
   public final #44= #41 of #43; //$anonfun$isSpace$1=class scala/xml/Parsing$$anonfun$isSpace$1 of class scala/xml/Parsing
   public final #47= #46 of #43; //$anonfun$checkPubID$1=class scala/xml/Parsing$$anonfun$checkPubID$1 of class scala/xml/Parsing
  minor version: 0
  major version: 49
  Constant pool:
const #1 = Asciz	SourceFile;
const #2 = Asciz	Parsing.scala;
const #3 = Asciz	checkPubID;
const #4 = Asciz	(Ljava/lang/String;)Z;
const #5 = Asciz	Code;
const #6 = Asciz	scala/xml/Parsing$;
const #7 = class	#6;	//  scala/xml/Parsing$
const #8 = Asciz	MODULE$;
const #9 = Asciz	Lscala/xml/Parsing$;;
const #10 = NameAndType	#8:#9;//  MODULE$:Lscala/xml/Parsing$;
const #11 = Field	#7.#10;	//  scala/xml/Parsing$.MODULE$:Lscala/xml/Parsing$;
const #12 = NameAndType	#3:#4;//  checkPubID:(Ljava/lang/String;)Z
const #13 = Method	#7.#12;	//  scala/xml/Parsing$.checkPubID:(Ljava/lang/String;)Z
const #14 = Asciz	checkSysID;
const #15 = NameAndType	#14:#4;//  checkSysID:(Ljava/lang/String;)Z
const #16 = Method	#7.#15;	//  scala/xml/Parsing$.checkSysID:(Ljava/lang/String;)Z
const #17 = Asciz	isPubIDChar;
const #18 = Asciz	(C)Z;
const #19 = NameAndType	#17:#18;//  isPubIDChar:(C)Z
const #20 = Method	#7.#19;	//  scala/xml/Parsing$.isPubIDChar:(C)Z
const #21 = Asciz	isName;
const #22 = NameAndType	#21:#4;//  isName:(Ljava/lang/String;)Z
const #23 = Method	#7.#22;	//  scala/xml/Parsing$.isName:(Ljava/lang/String;)Z
const #24 = Asciz	isNameStart;
const #25 = NameAndType	#24:#18;//  isNameStart:(C)Z
const #26 = Method	#7.#25;	//  scala/xml/Parsing$.isNameStart:(C)Z
const #27 = Asciz	isNameChar;
const #28 = NameAndType	#27:#18;//  isNameChar:(C)Z
const #29 = Method	#7.#28;	//  scala/xml/Parsing$.isNameChar:(C)Z
const #30 = Asciz	isSpace;
const #31 = Asciz	(Lscala/collection/Sequence;)Z;
const #32 = NameAndType	#30:#31;//  isSpace:(Lscala/collection/Sequence;)Z
const #33 = Method	#7.#32;	//  scala/xml/Parsing$.isSpace:(Lscala/collection/Sequence;)Z
const #34 = Asciz	(Lscala/collection/Sequence<Ljava/lang/Character;>;)Z;
const #35 = Asciz	Signature;
const #36 = NameAndType	#30:#18;//  isSpace:(C)Z
const #37 = Method	#7.#36;	//  scala/xml/Parsing$.isSpace:(C)Z
const #38 = Asciz	ScalaSig;
const #39 = Asciz	InnerClasses;
const #40 = Asciz	scala/xml/Parsing$$anonfun$isSpace$1;
const #41 = class	#40;	//  scala/xml/Parsing$$anonfun$isSpace$1
const #42 = Asciz	scala/xml/Parsing;
const #43 = class	#42;	//  scala/xml/Parsing
const #44 = Asciz	$anonfun$isSpace$1;
const #45 = Asciz	scala/xml/Parsing$$anonfun$checkPubID$1;
const #46 = class	#45;	//  scala/xml/Parsing$$anonfun$checkPubID$1
const #47 = Asciz	$anonfun$checkPubID$1;
const #48 = Asciz	java/lang/Object;
const #49 = class	#48;	//  java/lang/Object

{
public static final boolean checkPubID(java.lang.String);
  Code:
   Stack=2, Locals=1, Args_size=1
   0:	getstatic	#11; //Field scala/xml/Parsing$.MODULE$:Lscala/xml/Parsing$;
   3:	aload_0
   4:	invokevirtual	#13; //Method scala/xml/Parsing$.checkPubID:(Ljava/lang/String;)Z
   7:	ireturn

public static final boolean checkSysID(java.lang.String);
  Code:
   Stack=2, Locals=1, Args_size=1
   0:	getstatic	#11; //Field scala/xml/Parsing$.MODULE$:Lscala/xml/Parsing$;
   3:	aload_0
   4:	invokevirtual	#16; //Method scala/xml/Parsing$.checkSysID:(Ljava/lang/String;)Z
   7:	ireturn

public static final boolean isPubIDChar(char);
  Code:
   Stack=2, Locals=1, Args_size=1
   0:	getstatic	#11; //Field scala/xml/Parsing$.MODULE$:Lscala/xml/Parsing$;
   3:	iload_0
   4:	invokevirtual	#20; //Method scala/xml/Parsing$.isPubIDChar:(C)Z
   7:	ireturn

public static final boolean isName(java.lang.String);
  Code:
   Stack=2, Locals=1, Args_size=1
   0:	getstatic	#11; //Field scala/xml/Parsing$.MODULE$:Lscala/xml/Parsing$;
   3:	aload_0
   4:	invokevirtual	#23; //Method scala/xml/Parsing$.isName:(Ljava/lang/String;)Z
   7:	ireturn

public static final boolean isNameStart(char);
  Code:
   Stack=2, Locals=1, Args_size=1
   0:	getstatic	#11; //Field scala/xml/Parsing$.MODULE$:Lscala/xml/Parsing$;
   3:	iload_0
   4:	invokevirtual	#26; //Method scala/xml/Parsing$.isNameStart:(C)Z
   7:	ireturn

public static final boolean isNameChar(char);
  Code:
   Stack=2, Locals=1, Args_size=1
   0:	getstatic	#11; //Field scala/xml/Parsing$.MODULE$:Lscala/xml/Parsing$;
   3:	iload_0
   4:	invokevirtual	#29; //Method scala/xml/Parsing$.isNameChar:(C)Z
   7:	ireturn

public static final boolean isSpace(scala.collection.Sequence);
  Code:
   Stack=2, Locals=1, Args_size=1
   0:	getstatic	#11; //Field scala/xml/Parsing$.MODULE$:Lscala/xml/Parsing$;
   3:	aload_0
   4:	invokevirtual	#33; //Method scala/xml/Parsing$.isSpace:(Lscala/collection/Sequence;)Z
   7:	ireturn
  Signature: length = 0x2
   00 22 

public static final boolean isSpace(char);
  Code:
   Stack=2, Locals=1, Args_size=1
   0:	getstatic	#11; //Field scala/xml/Parsing$.MODULE$:Lscala/xml/Parsing$;
   3:	iload_0
   4:	invokevirtual	#37; //Method scala/xml/Parsing$.isSpace:(C)Z
   7:	ireturn

}

