Compiled from "PCData.scala"
public class scala.xml.PCData extends scala.xml.Atom implements scala.ScalaObject,scala.Product,java.io.Serializable
  SourceFile: "PCData.scala"
  Signature: length = 0x2
   00 FFFFFF82 
  ScalaSig: length = 0x378
   05 00 FFFFFF81 0C 06 08 01 02 FFFFFF84 FFFFFF80 FFFFFF80 FFFFFF80 40 07 02 06
   50 43 44 61 74 61 0A 02 03 04 01 03 78 6D 6C 0A
   01 05 01 05 73 63 61 6C 61 03 00 13 04 00 08 14
   17 10 03 09 0A 0C 0D 01 02 09 02 0B 02 02 04 41
   74 6F 6D 10 02 0D 11 0E 02 0E 0F 0D 01 04 09 02
   10 04 01 06 50 72 65 64 65 66 09 02 12 13 02 06
   53 74 72 69 6E 67 0A 02 10 04 10 02 0E 15 09 02
   16 04 02 0B 53 63 61 6C 61 4F 62 6A 65 63 74 10
   02 0E 18 09 02 19 04 02 07 50 72 6F 64 75 63 74
   08 08 1B 00 FFFFFF82 FFFFFFCA FFFFFF80 FFFFFF84 00 1C 01 05 5F 64 61 74
   61 15 01 0C 08 09 1E 00 FFFFFF82 FFFFFF88 FFFFFFA0 FFFFFF80 04 0C 1F 01
   06 5F 64 61 74 61 20 09 02 20 0A 01 04 64 61 74
   61 08 05 22 00 FFFFFF84 00 23 01 06 3C 69 6E 69 74 3E
   14 02 24 25 10 02 09 00 08 05 1B 21 FFFFFFC0 00 0C 08
   05 27 00 FFFFFF84 22 28 01 06 65 71 75 61 6C 73 14 02
   29 2C 10 02 0E 2A 09 02 2B 04 02 07 42 6F 6F 6C
   65 61 6E 08 05 2D 26 FFFFFFC0 00 2E 01 01 78 10 02 0E
   2F 09 02 30 04 02 03 41 6E 79 08 05 32 00 FFFFFF84 20
   33 01 0B 62 75 69 6C 64 53 74 72 69 6E 67 14 02
   34 3C 10 02 35 3A 0D 01 36 0A 02 37 38 01 07 6D
   75 74 61 62 6C 65 0A 02 39 04 01 0A 63 6F 6C 6C
   65 63 74 69 6F 6E 09 02 3B 36 02 0D 53 74 72 69
   6E 67 42 75 69 6C 64 65 72 08 05 3D 31 FFFFFFC0 00 3E
   01 02 73 62 10 02 3F 47 0E 02 40 45 0E 02 41 44
   0D 01 42 0A 02 43 06 01 06 3C 72 6F 6F 74 3E 09
   01 05 09 02 46 04 01 07 70 61 63 6B 61 67 65 09
   02 3B 48 0A 02 46 04 08 07 4A 00 FFFFFF81 FFFFFF80 FFFFFF84 00 4B
   01 04 63 6F 70 79 14 02 24 4C 08 08 4D 1B 49 FFFFFF90
   FFFFFF80 FFFFFFC0 00 0C 08 07 4E 00 FFFFFF91 FFFFFF80 FFFFFF84 00 4F 01 0E 63
   6F 70 79 24 64 65 66 61 75 6C 74 24 31 15 01 50
   2A 02 0C 51 2B 01 52 10 02 53 58 0D 01 54 0A 02
   55 56 01 09 75 6E 63 68 65 63 6B 65 64 0A 02 57
   04 01 0A 61 6E 6E 6F 74 61 74 69 6F 6E 09 02 59
   54 02 11 75 6E 63 68 65 63 6B 65 64 56 61 72 69
   61 6E 63 65 08 08 5B 00 FFFFFF84 FFFFFF80 FFFFFF80 FFFFFF84 20 5C 01 0D
   70 72 6F 64 75 63 74 50 72 65 66 69 78 15 01 5D
   10 02 5E 63 0D 01 5F 0A 02 60 61 01 04 6C 61 6E
   67 0A 01 62 01 04 6A 61 76 61 09 02 12 5F 08 08
   65 00 FFFFFF84 FFFFFF80 FFFFFF80 FFFFFF84 20 66 01 0C 70 72 6F 64 75 63
   74 41 72 69 74 79 15 01 67 10 02 0E 68 09 02 69
   04 02 03 49 6E 74 08 08 6B 00 FFFFFF84 FFFFFF80 FFFFFF80 FFFFFF84 20 6C
   01 0E 70 72 6F 64 75 63 74 45 6C 65 6D 65 6E 74
   14 02 2E 6D 08 07 6E 6A FFFFFF81 FFFFFF80 FFFFFFC0 00 67 01 03 78
   24 31 28 02 00 70 10 02 0E 71 09 02 72 04 02 0C
   73 65 72 69 61 6C 69 7A 61 62 6C 65 07 07 74 02
   FFFFFF81 FFFFFF80 FFFFFF88 02 75 01 06 50 43 44 61 74 61 10 02 09
   76 06 08 01 02 FFFFFF84 FFFFFF81 FFFFFF80 FFFFFF88 02 77 13 04 76 78 7B
   14 10 02 5E 79 09 02 7A 5F 02 06 4F 62 6A 65 63
   74 10 04 0E 7C 0C 24 09 02 7D 04 02 09 46 75 6E
   63 74 69 6F 6E 31 08 05 22 76 FFFFFF84 00 7F 14 01 75
   08 09 FFFFFF81 01 76 FFFFFF81 FFFFFF80 FFFFFF84 40 FFFFFF81 02 01 05 61 70 70
   6C 79 14 03 24 FFFFFF81 03 08 06 1B FFFFFF81 00 FFFFFFC0 00 0C 08
   09 FFFFFF81 05 76 FFFFFF81 FFFFFF80 FFFFFF84 40 FFFFFF81 06 01 07 75 6E 61 70
   70 6C 79 14 04 FFFFFF81 07 FFFFFF81 0A 10 04 0E FFFFFF81 08 0C 09
   03 FFFFFF81 09 04 02 04 53 6F 6D 65 08 07 FFFFFF81 0B FFFFFF81 04
   FFFFFFC0 00 24 01 03 78 24 30 
  minor version: 0
  major version: 49
  Constant pool:
const #1 = Asciz	SourceFile;
const #2 = Asciz	PCData.scala;
const #3 = Asciz	<init>;
const #4 = Asciz	(Ljava/lang/String;)V;
const #5 = Asciz	Code;
const #6 = Asciz	LineNumberTable;
const #7 = Asciz	scala/xml/Atom;
const #8 = class	#7;	//  scala/xml/Atom
const #9 = Asciz	(Ljava/lang/Object;)V;
const #10 = NameAndType	#3:#9;//  "<init>":(Ljava/lang/Object;)V
const #11 = Method	#8.#10;	//  scala/xml/Atom."<init>":(Ljava/lang/Object;)V
const #12 = Asciz	scala/Product$class;
const #13 = class	#12;	//  scala/Product$class
const #14 = Asciz	$init$;
const #15 = Asciz	(Lscala/Product;)V;
const #16 = NameAndType	#14:#15;//  $init$:(Lscala/Product;)V
const #17 = Method	#13.#16;	//  scala/Product$class.$init$:(Lscala/Product;)V
const #18 = Asciz	scala/xml/PCData;
const #19 = class	#18;	//  scala/xml/PCData
const #20 = Asciz	data;
const #21 = Asciz	()Ljava/lang/Object;;
const #22 = NameAndType	#20:#21;//  data:()Ljava/lang/Object;
const #23 = Method	#19.#22;	//  scala/xml/PCData.data:()Ljava/lang/Object;
const #24 = Asciz	java/lang/IllegalArgumentException;
const #25 = class	#24;	//  java/lang/IllegalArgumentException
const #26 = Asciz	tried to construct PCData with null;
const #27 = String	#26;	//  tried to construct PCData with null
const #28 = NameAndType	#3:#4;//  "<init>":(Ljava/lang/String;)V
const #29 = Method	#25.#28;	//  java/lang/IllegalArgumentException."<init>":(Ljava/lang/String;)V
const #30 = Asciz	this;
const #31 = Asciz	Lscala/xml/PCData;;
const #32 = Asciz	_data;
const #33 = Asciz	Ljava/lang/String;;
const #34 = Asciz	LocalVariableTable;
const #35 = Asciz	productElement;
const #36 = Asciz	(I)Ljava/lang/Object;;
const #37 = Asciz	()Ljava/lang/String;;
const #38 = NameAndType	#32:#37;//  _data:()Ljava/lang/String;
const #39 = Method	#19.#38;	//  scala/xml/PCData._data:()Ljava/lang/String;
const #40 = Asciz	scala/MatchError;
const #41 = class	#40;	//  scala/MatchError
const #42 = Asciz	scala/runtime/BoxesRunTime;
const #43 = class	#42;	//  scala/runtime/BoxesRunTime
const #44 = Asciz	boxToInteger;
const #45 = Asciz	(I)Ljava/lang/Integer;;
const #46 = NameAndType	#44:#45;//  boxToInteger:(I)Ljava/lang/Integer;
const #47 = Method	#43.#46;	//  scala/runtime/BoxesRunTime.boxToInteger:(I)Ljava/lang/Integer;
const #48 = Asciz	java/lang/Object;
const #49 = class	#48;	//  java/lang/Object
const #50 = Asciz	toString;
const #51 = NameAndType	#50:#37;//  toString:()Ljava/lang/String;
const #52 = Method	#49.#51;	//  java/lang/Object.toString:()Ljava/lang/String;
const #53 = Method	#41.#28;	//  scala/MatchError."<init>":(Ljava/lang/String;)V
const #54 = Asciz	java/lang/IndexOutOfBoundsException;
const #55 = class	#54;	//  java/lang/IndexOutOfBoundsException
const #56 = Method	#55.#28;	//  java/lang/IndexOutOfBoundsException."<init>":(Ljava/lang/String;)V
const #57 = Asciz	productArity;
const #58 = Asciz	()I;
const #59 = Asciz	productPrefix;
const #60 = Asciz	PCData;
const #61 = String	#60;	//  PCData
const #62 = Asciz	copy;
const #63 = Asciz	(Ljava/lang/String;)Lscala/xml/PCData;;
const #64 = Method	#19.#28;	//  scala/xml/PCData."<init>":(Ljava/lang/String;)V
const #65 = Asciz	buildString;
const #66 = Asciz	(Lscala/collection/mutable/StringBuilder;)Lscala/collection/mutable/StringBuilder;;
const #67 = Asciz	scala/Predef$;
const #68 = class	#67;	//  scala/Predef$
const #69 = Asciz	MODULE$;
const #70 = Asciz	Lscala/Predef$;;
const #71 = NameAndType	#69:#70;//  MODULE$:Lscala/Predef$;
const #72 = Field	#68.#71;	//  scala/Predef$.MODULE$:Lscala/Predef$;
const #73 = Asciz	<![CDATA[%s]]>;
const #74 = String	#73;	//  <![CDATA[%s]]>
const #75 = Asciz	augmentString;
const #76 = Asciz	(Ljava/lang/String;)Lscala/collection/immutable/StringOps;;
const #77 = NameAndType	#75:#76;//  augmentString:(Ljava/lang/String;)Lscala/collection/immutable/StringOps;
const #78 = Method	#68.#77;	//  scala/Predef$.augmentString:(Ljava/lang/String;)Lscala/collection/immutable/StringOps;
const #79 = Asciz	genericWrapArray;
const #80 = Asciz	(Ljava/lang/Object;)Lscala/collection/mutable/WrappedArray;;
const #81 = NameAndType	#79:#80;//  genericWrapArray:(Ljava/lang/Object;)Lscala/collection/mutable/WrappedArray;
const #82 = Method	#68.#81;	//  scala/Predef$.genericWrapArray:(Ljava/lang/Object;)Lscala/collection/mutable/WrappedArray;
const #83 = Asciz	scala/collection/immutable/StringLike;
const #84 = class	#83;	//  scala/collection/immutable/StringLike
const #85 = Asciz	format;
const #86 = Asciz	(Lscala/collection/Seq;)Ljava/lang/String;;
const #87 = NameAndType	#85:#86;//  format:(Lscala/collection/Seq;)Ljava/lang/String;
const #88 = InterfaceMethod	#84.#87;	//  scala/collection/immutable/StringLike.format:(Lscala/collection/Seq;)Ljava/lang/String;
const #89 = Asciz	scala/collection/mutable/StringBuilder;
const #90 = class	#89;	//  scala/collection/mutable/StringBuilder
const #91 = Asciz	append;
const #92 = Asciz	(Ljava/lang/String;)Lscala/collection/mutable/StringBuilder;;
const #93 = NameAndType	#91:#92;//  append:(Ljava/lang/String;)Lscala/collection/mutable/StringBuilder;
const #94 = Method	#90.#93;	//  scala/collection/mutable/StringBuilder.append:(Ljava/lang/String;)Lscala/collection/mutable/StringBuilder;
const #95 = Asciz	sb;
const #96 = Asciz	Lscala/collection/mutable/StringBuilder;;
const #97 = Asciz	equals;
const #98 = Asciz	(Ljava/lang/Object;)Z;
const #99 = Asciz	java/lang/String;
const #100 = class	#99;	//  java/lang/String
const #101 = NameAndType	#97:#98;//  equals:(Ljava/lang/Object;)Z
const #102 = Method	#100.#101;	//  java/lang/String.equals:(Ljava/lang/Object;)Z
const #103 = Method	#8.#22;	//  scala/xml/Atom.data:()Ljava/lang/Object;
const #104 = Asciz	java/lang/Number;
const #105 = class	#104;	//  java/lang/Number
const #106 = Asciz	java/lang/Character;
const #107 = class	#106;	//  java/lang/Character
const #108 = Asciz	equals2;
const #109 = Asciz	(Ljava/lang/Object;Ljava/lang/Object;)Z;
const #110 = NameAndType	#108:#109;//  equals2:(Ljava/lang/Object;Ljava/lang/Object;)Z
const #111 = Method	#43.#110;	//  scala/runtime/BoxesRunTime.equals2:(Ljava/lang/Object;Ljava/lang/Object;)Z
const #112 = Method	#49.#101;	//  java/lang/Object.equals:(Ljava/lang/Object;)Z
const #113 = Asciz	x;
const #114 = Asciz	Ljava/lang/Object;;
const #115 = Asciz	temp2;
const #116 = Asciz	temp3;
const #117 = Asciz	Lscala/xml/Atom;;
const #118 = Asciz	x0;
const #119 = Asciz	y0;
const #120 = Asciz	copy$default$1;
const #121 = Asciz	productElements;
const #122 = Asciz	()Lscala/collection/Iterator;;
const #123 = Asciz	(Lscala/Product;)Lscala/collection/Iterator;;
const #124 = NameAndType	#121:#123;//  productElements:(Lscala/Product;)Lscala/collection/Iterator;
const #125 = Method	#13.#124;	//  scala/Product$class.productElements:(Lscala/Product;)Lscala/collection/Iterator;
const #126 = Asciz	Deprecated;
const #127 = Asciz	productIterator;
const #128 = NameAndType	#127:#123;//  productIterator:(Lscala/Product;)Lscala/collection/Iterator;
const #129 = Method	#13.#128;	//  scala/Product$class.productIterator:(Lscala/Product;)Lscala/collection/Iterator;
const #130 = Asciz	Lscala/xml/Atom<Ljava/lang/String;>;Lscala/ScalaObject;Lscala/Product;;
const #131 = Asciz	Signature;
const #132 = Asciz	ScalaSig;
const #133 = Asciz	scala/ScalaObject;
const #134 = class	#133;	//  scala/ScalaObject
const #135 = Asciz	scala/Product;
const #136 = class	#135;	//  scala/Product
const #137 = Asciz	java/io/Serializable;
const #138 = class	#137;	//  java/io/Serializable

{
public scala.xml.PCData(java.lang.String);
  Code:
   Stack=3, Locals=2, Args_size=2
   0:	aload_0
   1:	aload_1
   2:	invokespecial	#11; //Method scala/xml/Atom."<init>":(Ljava/lang/Object;)V
   5:	aload_0
   6:	invokestatic	#17; //Method scala/Product$class.$init$:(Lscala/Product;)V
   9:	aload_0
   10:	invokevirtual	#23; //Method data:()Ljava/lang/Object;
   13:	ifnonnull	26
   16:	new	#25; //class java/lang/IllegalArgumentException
   19:	dup
   20:	ldc	#27; //String tried to construct PCData with null
   22:	invokespecial	#29; //Method java/lang/IllegalArgumentException."<init>":(Ljava/lang/String;)V
   25:	athrow
   26:	return
  LineNumberTable: 
   line 9: 0
   line 11: 9
   line 12: 16
   line 9: 26

  LocalVariableTable: 
   Start  Length  Slot  Name   Signature
   0      27      0    this       Lscala/xml/PCData;
   0      27      1    _data       Ljava/lang/String;


public java.lang.Object productElement(int);
  Code:
   Stack=3, Locals=2, Args_size=2
   0:	iload_1
   1:	iconst_0
   2:	if_icmpne	29
   5:	iconst_1
   6:	ifeq	14
   9:	aload_0
   10:	invokevirtual	#39; //Method _data:()Ljava/lang/String;
   13:	areturn
   14:	new	#41; //class scala/MatchError
   17:	dup
   18:	iload_1
   19:	invokestatic	#47; //Method scala/runtime/BoxesRunTime.boxToInteger:(I)Ljava/lang/Integer;
   22:	invokevirtual	#52; //Method java/lang/Object.toString:()Ljava/lang/String;
   25:	invokespecial	#53; //Method scala/MatchError."<init>":(Ljava/lang/String;)V
   28:	athrow
   29:	iconst_1
   30:	ifeq	48
   33:	new	#55; //class java/lang/IndexOutOfBoundsException
   36:	dup
   37:	iload_1
   38:	invokestatic	#47; //Method scala/runtime/BoxesRunTime.boxToInteger:(I)Ljava/lang/Integer;
   41:	invokevirtual	#52; //Method java/lang/Object.toString:()Ljava/lang/String;
   44:	invokespecial	#56; //Method java/lang/IndexOutOfBoundsException."<init>":(Ljava/lang/String;)V
   47:	athrow
   48:	new	#41; //class scala/MatchError
   51:	dup
   52:	iload_1
   53:	invokestatic	#47; //Method scala/runtime/BoxesRunTime.boxToInteger:(I)Ljava/lang/Integer;
   56:	invokevirtual	#52; //Method java/lang/Object.toString:()Ljava/lang/String;
   59:	invokespecial	#53; //Method scala/MatchError."<init>":(Ljava/lang/String;)V
   62:	athrow
  LineNumberTable: 
   line 9: 0
   line 21: 5
   line 9: 9
   line 21: 29
   line 9: 33


public int productArity();
  Code:
   Stack=1, Locals=1, Args_size=1
   0:	iconst_1
   1:	ireturn
  LineNumberTable: 
   line 9: 0


public java.lang.String productPrefix();
  Code:
   Stack=1, Locals=1, Args_size=1
   0:	ldc	#61; //String PCData
   2:	areturn
  LineNumberTable: 
   line 9: 0


public scala.xml.PCData copy(java.lang.String);
  Code:
   Stack=3, Locals=2, Args_size=2
   0:	new	#19; //class scala/xml/PCData
   3:	dup
   4:	aload_1
   5:	invokespecial	#64; //Method "<init>":(Ljava/lang/String;)V
   8:	areturn
  LineNumberTable: 
   line 9: 0

  LocalVariableTable: 
   Start  Length  Slot  Name   Signature
   0      9      0    this       Lscala/xml/PCData;
   0      9      1    _data       Ljava/lang/String;


public scala.collection.mutable.StringBuilder buildString(scala.collection.mutable.StringBuilder);
  Code:
   Stack=7, Locals=2, Args_size=2
   0:	aload_1
   1:	getstatic	#72; //Field scala/Predef$.MODULE$:Lscala/Predef$;
   4:	ldc	#74; //String <![CDATA[%s]]>
   6:	invokevirtual	#78; //Method scala/Predef$.augmentString:(Ljava/lang/String;)Lscala/collection/immutable/StringOps;
   9:	getstatic	#72; //Field scala/Predef$.MODULE$:Lscala/Predef$;
   12:	iconst_1
   13:	anewarray	#49; //class java/lang/Object
   16:	dup
   17:	iconst_0
   18:	aload_0
   19:	invokevirtual	#23; //Method data:()Ljava/lang/Object;
   22:	aastore
   23:	invokevirtual	#82; //Method scala/Predef$.genericWrapArray:(Ljava/lang/Object;)Lscala/collection/mutable/WrappedArray;
   26:	invokeinterface	#88,  2; //InterfaceMethod scala/collection/immutable/StringLike.format:(Lscala/collection/Seq;)Ljava/lang/String;
   31:	invokevirtual	#94; //Method scala/collection/mutable/StringBuilder.append:(Ljava/lang/String;)Lscala/collection/mutable/StringBuilder;
   34:	areturn
  LineNumberTable: 
   line 27: 0

  LocalVariableTable: 
   Start  Length  Slot  Name   Signature
   0      35      0    this       Lscala/xml/PCData;
   0      35      1    sb       Lscala/collection/mutable/StringBuilder;


public final boolean equals(java.lang.Object);
  Code:
   Stack=3, Locals=6, Args_size=2
   0:	aload_1
   1:	instanceof	#100; //class java/lang/String
   4:	ifeq	39
   7:	aload_1
   8:	checkcast	#100; //class java/lang/String
   11:	astore_2
   12:	iconst_1
   13:	ifeq	27
   16:	aload_2
   17:	aload_0
   18:	invokevirtual	#23; //Method data:()Ljava/lang/Object;
   21:	invokevirtual	#102; //Method java/lang/String.equals:(Ljava/lang/Object;)Z
   24:	goto	148
   27:	new	#41; //class scala/MatchError
   30:	dup
   31:	aload_1
   32:	invokevirtual	#52; //Method java/lang/Object.toString:()Ljava/lang/String;
   35:	invokespecial	#53; //Method scala/MatchError."<init>":(Ljava/lang/String;)V
   38:	athrow
   39:	aload_1
   40:	instanceof	#8; //class scala/xml/Atom
   43:	ifeq	143
   46:	aload_1
   47:	checkcast	#8; //class scala/xml/Atom
   50:	astore_3
   51:	iconst_1
   52:	ifeq	131
   55:	aload_0
   56:	invokevirtual	#23; //Method data:()Ljava/lang/Object;
   59:	aload_3
   60:	invokevirtual	#103; //Method scala/xml/Atom.data:()Ljava/lang/Object;
   63:	astore	5
   65:	astore	4
   67:	aload	4
   69:	aload	5
   71:	if_acmpne	78
   74:	iconst_1
   75:	goto	120
   78:	aload	4
   80:	ifnonnull	87
   83:	iconst_0
   84:	goto	120
   87:	aload	4
   89:	instanceof	#105; //class java/lang/Number
   92:	ifne	103
   95:	aload	4
   97:	instanceof	#107; //class java/lang/Character
   100:	ifeq	113
   103:	aload	4
   105:	aload	5
   107:	invokestatic	#111; //Method scala/runtime/BoxesRunTime.equals2:(Ljava/lang/Object;Ljava/lang/Object;)Z
   110:	goto	120
   113:	aload	4
   115:	aload	5
   117:	invokevirtual	#112; //Method java/lang/Object.equals:(Ljava/lang/Object;)Z
   120:	ifeq	127
   123:	iconst_1
   124:	goto	148
   127:	iconst_0
   128:	goto	148
   131:	new	#41; //class scala/MatchError
   134:	dup
   135:	aload_1
   136:	invokevirtual	#52; //Method java/lang/Object.toString:()Ljava/lang/String;
   139:	invokespecial	#53; //Method scala/MatchError."<init>":(Ljava/lang/String;)V
   142:	athrow
   143:	iconst_1
   144:	ifeq	149
   147:	iconst_0
   148:	ireturn
   149:	new	#41; //class scala/MatchError
   152:	dup
   153:	aload_1
   154:	invokevirtual	#52; //Method java/lang/Object.toString:()Ljava/lang/String;
   157:	invokespecial	#53; //Method scala/MatchError."<init>":(Ljava/lang/String;)V
   160:	athrow
  LineNumberTable: 
   line 14: 0
   line 21: 12
   line 15: 16
   line 14: 27
   line 21: 51
   line 16: 55
   line 14: 131
   line 21: 143
   line 17: 147
   line 14: 148

  LocalVariableTable: 
   Start  Length  Slot  Name   Signature
   0      161      0    this       Lscala/xml/PCData;
   0      161      1    x       Ljava/lang/Object;
   12      27      2    temp2       Ljava/lang/String;
   51      92      3    temp3       Lscala/xml/Atom;
   74      49      4    x0       Ljava/lang/Object;
   74      49      5    y0       Ljava/lang/Object;


public java.lang.String _data();
  Code:
   Stack=1, Locals=1, Args_size=1
   0:	aload_0
   1:	invokespecial	#103; //Method scala/xml/Atom.data:()Ljava/lang/Object;
   4:	checkcast	#100; //class java/lang/String
   7:	areturn
  LineNumberTable: 
   line 9: 0


public java.lang.String copy$default$1();
  Code:
   Stack=1, Locals=1, Args_size=1
   0:	aload_0
   1:	invokevirtual	#39; //Method _data:()Ljava/lang/String;
   4:	areturn
  LineNumberTable: 
   line 9: 0


public scala.collection.Iterator productElements();
  Code:
   Stack=1, Locals=1, Args_size=1
   0:	aload_0
   1:	invokestatic	#125; //Method scala/Product$class.productElements:(Lscala/Product;)Lscala/collection/Iterator;
   4:	areturn
  LineNumberTable: 
   line 9: 0

  Deprecated: true

public scala.collection.Iterator productIterator();
  Code:
   Stack=1, Locals=1, Args_size=1
   0:	aload_0
   1:	invokestatic	#129; //Method scala/Product$class.productIterator:(Lscala/Product;)Lscala/collection/Iterator;
   4:	areturn
  LineNumberTable: 
   line 9: 0


}

