Compiled from "PCData.scala"
public class scala.xml.PCData extends scala.xml.Atom implements scala.ScalaObject,scala.Product,java.io.Serializable
  SourceFile: "PCData.scala"
  Signature: length = 0x2
   00 FFFFFF81 
  ScalaSig: length = 0x378
   05 00 FFFFFF81 0C 06 08 01 02 FFFFFF84 FFFFFF80 FFFFFF80 FFFFFF80 40 07 02 06
   50 43 44 61 74 61 0A 02 03 04 01 03 78 6D 6C 0A
   01 05 01 05 73 63 61 6C 61 03 00 13 04 00 08 14
   17 10 03 09 0A 0C 0D 01 02 09 02 0B 02 02 04 41
   74 6F 6D 10 02 0D 11 0E 02 0E 0F 0D 01 04 09 02
   10 04 01 06 50 72 65 64 65 66 09 02 12 13 02 06
   53 74 72 69 6E 67 0A 02 10 04 10 02 0E 15 09 02
   16 04 02 0B 53 63 61 6C 61 4F 62 6A 65 63 74 10
   02 0E 18 09 02 19 04 02 07 50 72 6F 64 75 63 74
   08 08 1B 00 FFFFFF82 FFFFFFCA FFFFFF80 FFFFFF84 00 1C 01 05 5F 64 61 74
   61 15 01 0C 08 09 1E 00 FFFFFF82 FFFFFF88 FFFFFFA0 FFFFFF80 04 0C 1F 01
   06 5F 64 61 74 61 20 09 02 20 0A 01 04 64 61 74
   61 08 05 22 00 FFFFFF84 00 23 01 06 3C 69 6E 69 74 3E
   14 02 24 25 10 02 09 00 08 05 1B 21 FFFFFFC0 00 0C 08
   05 27 00 FFFFFF84 22 28 01 06 65 71 75 61 6C 73 14 02
   29 2C 10 02 0E 2A 09 02 2B 04 02 07 42 6F 6F 6C
   65 61 6E 08 05 2D 26 FFFFFFC0 00 2E 01 01 78 10 02 0E
   2F 09 02 30 04 02 03 41 6E 79 08 05 32 00 FFFFFF84 20
   33 01 0B 62 75 69 6C 64 53 74 72 69 6E 67 14 02
   34 3C 10 02 35 3A 0D 01 36 0A 02 37 38 01 07 6D
   75 74 61 62 6C 65 0A 02 39 04 01 0A 63 6F 6C 6C
   65 63 74 69 6F 6E 09 02 3B 36 02 0D 53 74 72 69
   6E 67 42 75 69 6C 64 65 72 08 05 3D 31 FFFFFFC0 00 3E
   01 02 73 62 10 02 3F 47 0E 02 40 45 0E 02 41 44
   0D 01 42 0A 02 43 06 01 06 3C 72 6F 6F 74 3E 09
   01 05 09 02 46 04 01 07 70 61 63 6B 61 67 65 09
   02 3B 48 0A 02 46 04 08 07 4A 00 FFFFFF81 FFFFFF80 FFFFFF84 00 4B
   01 04 63 6F 70 79 14 02 24 4C 08 08 4D 1B 49 FFFFFF90
   FFFFFF80 FFFFFFC0 00 0C 08 07 4E 00 FFFFFF91 FFFFFF80 FFFFFF84 00 4F 01 0E 63
   6F 70 79 24 64 65 66 61 75 6C 74 24 31 15 01 50
   2A 02 0C 51 2B 01 52 10 02 53 58 0D 01 54 0A 02
   55 56 01 09 75 6E 63 68 65 63 6B 65 64 0A 02 57
   04 01 0A 61 6E 6E 6F 74 61 74 69 6F 6E 09 02 59
   54 02 11 75 6E 63 68 65 63 6B 65 64 56 61 72 69
   61 6E 63 65 08 08 5B 00 FFFFFF84 FFFFFF80 FFFFFF80 FFFFFF84 20 5C 01 0D
   70 72 6F 64 75 63 74 50 72 65 66 69 78 15 01 5D
   10 02 5E 63 0D 01 5F 0A 02 60 61 01 04 6C 61 6E
   67 0A 01 62 01 04 6A 61 76 61 09 02 12 5F 08 08
   65 00 FFFFFF84 FFFFFF80 FFFFFF80 FFFFFF84 20 66 01 0C 70 72 6F 64 75 63
   74 41 72 69 74 79 15 01 67 10 02 0E 68 09 02 69
   04 02 03 49 6E 74 08 08 6B 00 FFFFFF84 FFFFFF80 FFFFFF80 FFFFFF84 20 6C
   01 0E 70 72 6F 64 75 63 74 45 6C 65 6D 65 6E 74
   14 02 2E 6D 08 07 6E 6A FFFFFF81 FFFFFF80 FFFFFFC0 00 67 01 03 78
   24 31 28 02 00 70 10 02 0E 71 09 02 72 04 02 0C
   73 65 72 69 61 6C 69 7A 61 62 6C 65 07 07 74 02
   FFFFFF81 FFFFFF80 FFFFFF88 02 75 01 06 50 43 44 61 74 61 10 02 09
   76 06 08 01 02 FFFFFF84 FFFFFF81 FFFFFF80 FFFFFF88 02 77 13 04 76 78 7B
   14 10 02 5E 79 09 02 7A 5F 02 06 4F 62 6A 65 63
   74 10 04 0E 7C 0C 24 09 02 7D 04 02 09 46 75 6E
   63 74 69 6F 6E 31 08 05 22 76 FFFFFF84 00 7F 14 01 75
   08 09 FFFFFF81 01 76 FFFFFF81 FFFFFF80 FFFFFF84 40 FFFFFF81 02 01 05 61 70 70
   6C 79 14 03 24 FFFFFF81 03 08 06 1B FFFFFF81 00 FFFFFFC0 00 0C 08
   09 FFFFFF81 05 76 FFFFFF81 FFFFFF80 FFFFFF84 40 FFFFFF81 06 01 07 75 6E 61 70
   70 6C 79 14 04 FFFFFF81 07 FFFFFF81 0A 10 04 0E FFFFFF81 08 0C 09
   03 FFFFFF81 09 04 02 04 53 6F 6D 65 08 07 FFFFFF81 0B FFFFFF81 04
   FFFFFFC0 00 24 01 03 78 24 30 
  minor version: 0
  major version: 49
  Constant pool:
Asciz	SourceFile;
Asciz	PCData.scala;
Asciz	<init>;
Asciz	(Ljava/lang/String;)V;
Asciz	Code;
Asciz	LineNumberTable;
Asciz	scala/xml/Atom;
class	scala/xml/Atom
Asciz	(Ljava/lang/Object;)V;
NameAndType	"<init>":(Ljava/lang/Object;)V
Method	scala/xml/Atom."<init>":(Ljava/lang/Object;)V
Asciz	scala/Product$class;
class	scala/Product$class
Asciz	$init$;
Asciz	(Lscala/Product;)V;
NameAndType	$init$:(Lscala/Product;)V
Method	scala/Product$class.$init$:(Lscala/Product;)V
Asciz	scala/xml/PCData;
class	scala/xml/PCData
Asciz	data;
Asciz	()Ljava/lang/Object;;
NameAndType	data:()Ljava/lang/Object;
Method	scala/xml/PCData.data:()Ljava/lang/Object;
Asciz	java/lang/IllegalArgumentException;
class	java/lang/IllegalArgumentException
Asciz	tried to construct PCData with null;
String	tried to construct PCData with null
NameAndType	"<init>":(Ljava/lang/String;)V
Method	java/lang/IllegalArgumentException."<init>":(Ljava/lang/String;)V
Asciz	this;
Asciz	Lscala/xml/PCData;;
Asciz	_data;
Asciz	Ljava/lang/String;;
Asciz	LocalVariableTable;
Asciz	productElement;
Asciz	(I)Ljava/lang/Object;;
Asciz	()Ljava/lang/String;;
NameAndType	_data:()Ljava/lang/String;
Method	scala/xml/PCData._data:()Ljava/lang/String;
Asciz	scala/MatchError;
class	scala/MatchError
Asciz	scala/runtime/BoxesRunTime;
class	scala/runtime/BoxesRunTime
Asciz	boxToInteger;
Asciz	(I)Ljava/lang/Integer;;
NameAndType	boxToInteger:(I)Ljava/lang/Integer;
Method	scala/runtime/BoxesRunTime.boxToInteger:(I)Ljava/lang/Integer;
Asciz	java/lang/Object;
class	java/lang/Object
Asciz	toString;
NameAndType	toString:()Ljava/lang/String;
Method	java/lang/Object.toString:()Ljava/lang/String;
Method	scala/MatchError."<init>":(Ljava/lang/String;)V
Asciz	java/lang/IndexOutOfBoundsException;
class	java/lang/IndexOutOfBoundsException
Method	java/lang/IndexOutOfBoundsException."<init>":(Ljava/lang/String;)V
Asciz	productArity;
Asciz	()I;
Asciz	productPrefix;
Asciz	PCData;
String	PCData
Asciz	copy;
Asciz	(Ljava/lang/String;)Lscala/xml/PCData;;
Method	scala/xml/PCData."<init>":(Ljava/lang/String;)V
Asciz	buildString;
Asciz	(Lscala/collection/mutable/StringBuilder;)Lscala/collection/mutable/StringBuilder;;
Asciz	scala/Predef$;
class	scala/Predef$
Asciz	MODULE$;
Asciz	Lscala/Predef$;;
NameAndType	MODULE$:Lscala/Predef$;
Field	scala/Predef$.MODULE$:Lscala/Predef$;
Asciz	<![CDATA[%s]]>;
String	<![CDATA[%s]]>
Asciz	augmentString;
Asciz	(Ljava/lang/String;)Lscala/collection/immutable/StringOps;;
NameAndType	augmentString:(Ljava/lang/String;)Lscala/collection/immutable/StringOps;
Method	scala/Predef$.augmentString:(Ljava/lang/String;)Lscala/collection/immutable/StringOps;
Asciz	genericWrapArray;
Asciz	(Ljava/lang/Object;)Lscala/collection/mutable/WrappedArray;;
NameAndType	genericWrapArray:(Ljava/lang/Object;)Lscala/collection/mutable/WrappedArray;
Method	scala/Predef$.genericWrapArray:(Ljava/lang/Object;)Lscala/collection/mutable/WrappedArray;
Asciz	scala/collection/immutable/StringLike;
class	scala/collection/immutable/StringLike
Asciz	format;
Asciz	(Lscala/collection/Seq;)Ljava/lang/String;;
NameAndType	format:(Lscala/collection/Seq;)Ljava/lang/String;
InterfaceMethod	scala/collection/immutable/StringLike.format:(Lscala/collection/Seq;)Ljava/lang/String;
Asciz	scala/collection/mutable/StringBuilder;
class	scala/collection/mutable/StringBuilder
Asciz	append;
Asciz	(Ljava/lang/String;)Lscala/collection/mutable/StringBuilder;;
NameAndType	append:(Ljava/lang/String;)Lscala/collection/mutable/StringBuilder;
Method	scala/collection/mutable/StringBuilder.append:(Ljava/lang/String;)Lscala/collection/mutable/StringBuilder;
Asciz	sb;
Asciz	Lscala/collection/mutable/StringBuilder;;
Asciz	equals;
Asciz	(Ljava/lang/Object;)Z;
Asciz	java/lang/String;
class	java/lang/String
NameAndType	equals:(Ljava/lang/Object;)Z
Method	java/lang/String.equals:(Ljava/lang/Object;)Z
Method	scala/xml/Atom.data:()Ljava/lang/Object;
Asciz	java/lang/Number;
class	java/lang/Number
Asciz	java/lang/Character;
class	java/lang/Character
Asciz	equals2;
Asciz	(Ljava/lang/Object;Ljava/lang/Object;)Z;
NameAndType	equals2:(Ljava/lang/Object;Ljava/lang/Object;)Z
Method	scala/runtime/BoxesRunTime.equals2:(Ljava/lang/Object;Ljava/lang/Object;)Z
Method	java/lang/Object.equals:(Ljava/lang/Object;)Z
Asciz	x;
Asciz	Ljava/lang/Object;;
Asciz	temp2;
Asciz	temp3;
Asciz	Lscala/xml/Atom;;
Asciz	x0;
Asciz	y0;
Asciz	copy$default$1;
Asciz	productElements;
Asciz	()Lscala/collection/Iterator;;
Asciz	(Lscala/Product;)Lscala/collection/Iterator;;
NameAndType	productElements:(Lscala/Product;)Lscala/collection/Iterator;
Method	scala/Product$class.productElements:(Lscala/Product;)Lscala/collection/Iterator;
Asciz	productIterator;
NameAndType	productIterator:(Lscala/Product;)Lscala/collection/Iterator;
Method	scala/Product$class.productIterator:(Lscala/Product;)Lscala/collection/Iterator;
Asciz	Lscala/xml/Atom<Ljava/lang/String;>;Lscala/ScalaObject;Lscala/Product;;
Asciz	Signature;
Asciz	ScalaSig;
Asciz	scala/ScalaObject;
class	scala/ScalaObject
Asciz	scala/Product;
class	scala/Product
Asciz	java/io/Serializable;
class	java/io/Serializable

{
public scala.xml.PCData(java.lang.String);
  Signature: (Ljava/lang/String;)V
  Code:
   Stack=3, Locals=2, Args_size=2
	aload_0
	aload_1
	invokespecial	Method scala/xml/Atom."<init>":(Ljava/lang/Object;)V
	aload_0
	invokestatic	Method scala/Product$class.$init$:(Lscala/Product;)V
	aload_0
	invokevirtual	Method data:()Ljava/lang/Object;
	ifnonnull	l1 // return
	new	class java/lang/IllegalArgumentException
	dup
	ldc	String tried to construct PCData with null
	invokespecial	Method java/lang/IllegalArgumentException."<init>":(Ljava/lang/String;)V
	athrow
l1	return
  Labels:
   	l1 = 26 // return
  LocalVariableTable: 
   Start  Length  Slot  Name   Signature
   0      27      0    this       Lscala/xml/PCData;
   0      27      1    _data       Ljava/lang/String;


public java.lang.Object productElement(int);
  Signature: (I)Ljava/lang/Object;
  Code:
   Stack=3, Locals=2, Args_size=2
	iload_1
	iconst_0
	if_icmpne	l1 // iconst_1
	iconst_1
	ifeq	l2 // new
	aload_0
	invokevirtual	Method _data:()Ljava/lang/String;
	areturn
l2	new	class scala/MatchError
	dup
	iload_1
	invokestatic	Method scala/runtime/BoxesRunTime.boxToInteger:(I)Ljava/lang/Integer;
	invokevirtual	Method java/lang/Object.toString:()Ljava/lang/String;
	invokespecial	Method scala/MatchError."<init>":(Ljava/lang/String;)V
	athrow
l1	iconst_1
	ifeq	l3 // new
	new	class java/lang/IndexOutOfBoundsException
	dup
	iload_1
	invokestatic	Method scala/runtime/BoxesRunTime.boxToInteger:(I)Ljava/lang/Integer;
	invokevirtual	Method java/lang/Object.toString:()Ljava/lang/String;
	invokespecial	Method java/lang/IndexOutOfBoundsException."<init>":(Ljava/lang/String;)V
	athrow
l3	new	class scala/MatchError
	dup
	iload_1
	invokestatic	Method scala/runtime/BoxesRunTime.boxToInteger:(I)Ljava/lang/Integer;
	invokevirtual	Method java/lang/Object.toString:()Ljava/lang/String;
	invokespecial	Method scala/MatchError."<init>":(Ljava/lang/String;)V
	athrow
  Labels:
   	l2 = 14 // new
   	l1 = 29 // iconst_1
   	l3 = 48 // new

public int productArity();
  Signature: ()I
  Code:
   Stack=1, Locals=1, Args_size=1
	iconst_1
	ireturn
  Labels:

public java.lang.String productPrefix();
  Signature: ()Ljava/lang/String;
  Code:
   Stack=1, Locals=1, Args_size=1
	ldc	String PCData
	areturn
  Labels:

public scala.xml.PCData copy(java.lang.String);
  Signature: (Ljava/lang/String;)Lscala/xml/PCData;
  Code:
   Stack=3, Locals=2, Args_size=2
	new	class scala/xml/PCData
	dup
	aload_1
	invokespecial	Method "<init>":(Ljava/lang/String;)V
	areturn
  Labels:
  LocalVariableTable: 
   Start  Length  Slot  Name   Signature
   0      9      0    this       Lscala/xml/PCData;
   0      9      1    _data       Ljava/lang/String;


public scala.collection.mutable.StringBuilder buildString(scala.collection.mutable.StringBuilder);
  Signature: (Lscala/collection/mutable/StringBuilder;)Lscala/collection/mutable/StringBuilder;
  Code:
   Stack=7, Locals=2, Args_size=2
	aload_1
	getstatic	Field scala/Predef$.MODULE$:Lscala/Predef$;
	ldc	String <![CDATA[%s]]>
	invokevirtual	Method scala/Predef$.augmentString:(Ljava/lang/String;)Lscala/collection/immutable/StringOps;
	getstatic	Field scala/Predef$.MODULE$:Lscala/Predef$;
	iconst_1
	anewarray	class java/lang/Object
	dup
	iconst_0
	aload_0
	invokevirtual	Method data:()Ljava/lang/Object;
	aastore
	invokevirtual	Method scala/Predef$.genericWrapArray:(Ljava/lang/Object;)Lscala/collection/mutable/WrappedArray;
	invokeinterface	InterfaceMethod scala/collection/immutable/StringLike.format:(Lscala/collection/Seq;)Ljava/lang/String;
	invokevirtual	Method scala/collection/mutable/StringBuilder.append:(Ljava/lang/String;)Lscala/collection/mutable/StringBuilder;
	areturn
  Labels:
  LocalVariableTable: 
   Start  Length  Slot  Name   Signature
   0      35      0    this       Lscala/xml/PCData;
   0      35      1    sb       Lscala/collection/mutable/StringBuilder;


public final boolean equals(java.lang.Object);
  Signature: (Ljava/lang/Object;)Z
  Code:
   Stack=3, Locals=6, Args_size=2
	aload_1
	instanceof	class java/lang/String
	ifeq	l1 // aload_1
	aload_1
	checkcast	class java/lang/String
	astore_2
	iconst_1
	ifeq	l2 // new
	aload_2
	aload_0
	invokevirtual	Method data:()Ljava/lang/Object;
	invokevirtual	Method java/lang/String.equals:(Ljava/lang/Object;)Z
	goto	l3 // ireturn
l2	new	class scala/MatchError
	dup
	aload_1
	invokevirtual	Method java/lang/Object.toString:()Ljava/lang/String;
	invokespecial	Method scala/MatchError."<init>":(Ljava/lang/String;)V
	athrow
l1	aload_1
	instanceof	class scala/xml/Atom
	ifeq	l4 // iconst_1
	aload_1
	checkcast	class scala/xml/Atom
	astore_3
	iconst_1
	ifeq	l5 // new
	aload_0
	invokevirtual	Method data:()Ljava/lang/Object;
	aload_3
	invokevirtual	Method scala/xml/Atom.data:()Ljava/lang/Object;
	astore	5
	astore	4
	aload	4
	aload	5
	if_acmpne	l6 // aload
	iconst_1
	goto	l7 // ifeq
l6	aload	4
	ifnonnull	l8 // aload
	iconst_0
	goto	l7 // ifeq
l8	aload	4
	instanceof	class java/lang/Number
	ifne	l9 // aload
	aload	4
	instanceof	class java/lang/Character
	ifeq	l10 // aload
l9	aload	4
	aload	5
	invokestatic	Method scala/runtime/BoxesRunTime.equals2:(Ljava/lang/Object;Ljava/lang/Object;)Z
	goto	l7 // ifeq
l10	aload	4
	aload	5
	invokevirtual	Method java/lang/Object.equals:(Ljava/lang/Object;)Z
l7	ifeq	l11 // iconst_0
	iconst_1
	goto	l3 // ireturn
l11	iconst_0
	goto	l3 // ireturn
l5	new	class scala/MatchError
	dup
	aload_1
	invokevirtual	Method java/lang/Object.toString:()Ljava/lang/String;
	invokespecial	Method scala/MatchError."<init>":(Ljava/lang/String;)V
	athrow
l4	iconst_1
	ifeq	l12 // new
	iconst_0
l3	ireturn
l12	new	class scala/MatchError
	dup
	aload_1
	invokevirtual	Method java/lang/Object.toString:()Ljava/lang/String;
	invokespecial	Method scala/MatchError."<init>":(Ljava/lang/String;)V
	athrow
  Labels:
   	l2 = 27 // new
   	l1 = 39 // aload_1
   	l6 = 78 // aload
   	l8 = 87 // aload
   	l9 = 103 // aload
   	l10 = 113 // aload
   	l7 = 120 // ifeq
   	l11 = 127 // iconst_0
   	l5 = 131 // new
   	l4 = 143 // iconst_1
   	l3 = 148 // ireturn
   	l12 = 149 // new
  LocalVariableTable: 
   Start  Length  Slot  Name   Signature
   0      161      0    this       Lscala/xml/PCData;
   0      161      1    x       Ljava/lang/Object;
   12      27      2    temp2       Ljava/lang/String;
   51      92      3    temp3       Lscala/xml/Atom;
   74      49      4    x0       Ljava/lang/Object;
   74      49      5    y0       Ljava/lang/Object;


public java.lang.String _data();
  Signature: ()Ljava/lang/String;
  Code:
   Stack=1, Locals=1, Args_size=1
	aload_0
	invokespecial	Method scala/xml/Atom.data:()Ljava/lang/Object;
	checkcast	class java/lang/String
	areturn
  Labels:

public java.lang.String copy$default$1();
  Signature: ()Ljava/lang/String;
  Code:
   Stack=1, Locals=1, Args_size=1
	aload_0
	invokevirtual	Method _data:()Ljava/lang/String;
	areturn
  Labels:

public scala.collection.Iterator productElements();
  Signature: ()Lscala/collection/Iterator;
  Code:
   Stack=1, Locals=1, Args_size=1
	aload_0
	invokestatic	Method scala/Product$class.productElements:(Lscala/Product;)Lscala/collection/Iterator;
	areturn
  Labels:

public scala.collection.Iterator productIterator();
  Signature: ()Lscala/collection/Iterator;
  Code:
   Stack=1, Locals=1, Args_size=1
	aload_0
	invokestatic	Method scala/Product$class.productIterator:(Lscala/Product;)Lscala/collection/Iterator;
	areturn
  Labels:

}

