Compiled from "PrefixedAttribute.scala"
public final class scala.xml.PrefixedAttribute$ extends java.lang.Object implements scala.ScalaObject
  SourceFile: "PrefixedAttribute.scala"
  Scala: length = 0x
   
  minor version: 0
  major version: 49
  Constant pool:
Asciz	SourceFile;
Asciz	PrefixedAttribute.scala;
Asciz	Scala;
Asciz	MODULE$;
Asciz	Lscala/xml/PrefixedAttribute$;;
Asciz	<clinit>;
Asciz	()V;
Asciz	Code;
Asciz	scala/xml/PrefixedAttribute$;
class	scala/xml/PrefixedAttribute$
Asciz	<init>;
NameAndType	"<init>":()V
Method	scala/xml/PrefixedAttribute$."<init>":()V
Asciz	LineNumberTable;
Asciz	java/lang/Object;
class	java/lang/Object
Method	java/lang/Object."<init>":()V
NameAndType	MODULE$:Lscala/xml/PrefixedAttribute$;
Field	scala/xml/PrefixedAttribute$.MODULE$:Lscala/xml/PrefixedAttribute$;
Asciz	unapply;
Asciz	(Lscala/xml/PrefixedAttribute;)Lscala/Some;;
Asciz	scala/Some;
class	scala/Some
Asciz	scala/Tuple4;
class	scala/Tuple4
Asciz	scala/xml/PrefixedAttribute;
class	scala/xml/PrefixedAttribute
Asciz	pre;
Asciz	()Ljava/lang/String;;
NameAndType	pre:()Ljava/lang/String;
Method	scala/xml/PrefixedAttribute.pre:()Ljava/lang/String;
Asciz	key;
NameAndType	key:()Ljava/lang/String;
Method	scala/xml/PrefixedAttribute.key:()Ljava/lang/String;
Asciz	value;
Asciz	()Lscala/collection/Seq;;
NameAndType	value:()Lscala/collection/Seq;
Method	scala/xml/PrefixedAttribute.value:()Lscala/collection/Seq;
Asciz	next;
Asciz	()Lscala/xml/MetaData;;
NameAndType	next:()Lscala/xml/MetaData;
Method	scala/xml/PrefixedAttribute.next:()Lscala/xml/MetaData;
Asciz	(Ljava/lang/Object;Ljava/lang/Object;Ljava/lang/Object;Ljava/lang/Object;)V;
NameAndType	"<init>":(Ljava/lang/Object;Ljava/lang/Object;Ljava/lang/Object;Ljava/lang/Object;)V
Method	scala/Tuple4."<init>":(Ljava/lang/Object;Ljava/lang/Object;Ljava/lang/Object;Ljava/lang/Object;)V
Asciz	(Ljava/lang/Object;)V;
NameAndType	"<init>":(Ljava/lang/Object;)V
Method	scala/Some."<init>":(Ljava/lang/Object;)V
Asciz	this;
Asciz	x;
Asciz	Lscala/xml/PrefixedAttribute;;
Asciz	LocalVariableTable;
Asciz	(Lscala/xml/PrefixedAttribute;)Lscala/Some<Lscala/Tuple4<Ljava/lang/String;Ljava/lang/String;Lscala/collection/Seq<Lscala/xml/Node;>;Lscala/xml/MetaData;>;>;;
Asciz	Signature;
Asciz	scala/ScalaObject;
class	scala/ScalaObject

{
public static final scala.xml.PrefixedAttribute$ MODULE$;
  Signature: Lscala/xml/PrefixedAttribute$;

public static {};
  Signature: ()V
  Code:
   Stack=1, Locals=0, Args_size=0
	new	class scala/xml/PrefixedAttribute$
	invokespecial	Method "<init>":()V
	return
  Labels:

private scala.xml.PrefixedAttribute$();
  Signature: ()V
  Code:
   Stack=1, Locals=1, Args_size=1
	aload_0
	invokespecial	Method java/lang/Object."<init>":()V
	aload_0
	putstatic	Field MODULE$:Lscala/xml/PrefixedAttribute$;
	return
  Labels:

public scala.Some unapply(scala.xml.PrefixedAttribute);
  Signature: (Lscala/xml/PrefixedAttribute;)Lscala/Some;
  Code:
   Stack=8, Locals=2, Args_size=2
	new	class scala/Some
	dup
	new	class scala/Tuple4
	dup
	aload_1
	invokevirtual	Method scala/xml/PrefixedAttribute.pre:()Ljava/lang/String;
	aload_1
	invokevirtual	Method scala/xml/PrefixedAttribute.key:()Ljava/lang/String;
	aload_1
	invokevirtual	Method scala/xml/PrefixedAttribute.value:()Lscala/collection/Seq;
	aload_1
	invokevirtual	Method scala/xml/PrefixedAttribute.next:()Lscala/xml/MetaData;
	invokespecial	Method scala/Tuple4."<init>":(Ljava/lang/Object;Ljava/lang/Object;Ljava/lang/Object;Ljava/lang/Object;)V
	invokespecial	Method scala/Some."<init>":(Ljava/lang/Object;)V
	areturn
  Labels:
  LocalVariableTable: 
   Start  Length  Slot  Name   Signature
   0      31      0    this       Lscala/xml/PrefixedAttribute$;
   0      31      1    x       Lscala/xml/PrefixedAttribute;

  Signature: length = 0x2
   00 35 

}

