Compiled from "PrefixedAttribute.scala"
public class scala.xml.PrefixedAttribute extends scala.xml.MetaData implements scala.xml.Attribute,scala.ScalaObject
  SourceFile: "PrefixedAttribute.scala"
  ScalaSig: length = 0x43A
   05 00 FFFFFF81 21 06 08 01 02 FFFFFF84 FFFFFF80 FFFFFF80 FFFFFF80 00 07 02 11
   50 72 65 66 69 78 65 64 41 74 74 72 69 62 75 74
   65 0A 02 03 04 01 03 78 6D 6C 0A 01 05 01 05 73
   63 61 6C 61 03 00 13 04 00 08 0C 0F 10 02 09 0A
   0D 01 02 09 02 0B 02 02 08 4D 65 74 61 44 61 74
   61 10 02 09 0D 09 02 0E 02 02 09 41 74 74 72 69
   62 75 74 65 10 02 10 11 0D 01 04 09 02 12 04 02
   0B 53 63 61 6C 61 4F 62 6A 65 63 74 08 08 14 00
   FFFFFF82 FFFFFFC2 FFFFFF80 FFFFFF84 00 15 01 03 70 72 65 15 01 16 10 02
   17 1A 0E 02 10 18 09 02 19 04 01 06 50 72 65 64
   65 66 09 02 1B 1C 02 06 53 74 72 69 6E 67 0A 02
   19 04 08 08 1E 00 FFFFFF82 FFFFFF80 FFFFFFA0 FFFFFF80 04 16 01 04 70 72
   65 20 08 08 20 00 FFFFFF82 FFFFFFC2 FFFFFF80 FFFFFF84 00 15 01 03 6B 65
   79 08 08 22 00 FFFFFF82 FFFFFF80 FFFFFFA0 FFFFFF80 04 16 01 04 6B 65 79
   20 08 08 24 00 FFFFFF82 FFFFFFC2 FFFFFF80 FFFFFF84 00 25 01 05 76 61 6C
   75 65 15 01 26 10 03 27 2A 2C 0D 01 28 0A 02 29
   04 01 0A 63 6F 6C 6C 65 63 74 69 6F 6E 09 02 2B
   28 02 03 53 65 71 10 02 09 2D 09 02 2E 02 02 04
   4E 6F 64 65 08 08 30 00 FFFFFF82 FFFFFF80 FFFFFFA0 FFFFFF80 04 26 01 06
   76 61 6C 75 65 20 08 08 32 00 FFFFFF82 FFFFFFC2 FFFFFF80 FFFFFF84 00 33
   01 04 6E 65 78 74 15 01 08 08 08 35 00 FFFFFF82 FFFFFF80 FFFFFFA0
   FFFFFF80 04 08 01 05 6E 65 78 74 20 08 05 37 00 FFFFFF84 00
   38 01 06 3C 69 6E 69 74 3E 14 05 39 3A 3B 3C 3D
   10 02 09 00 08 05 14 36 FFFFFFC0 00 16 08 05 20 36 FFFFFFC0
   00 16 08 05 24 36 FFFFFFC0 00 26 08 05 32 36 FFFFFFC0 00 08
   08 05 37 00 FFFFFF84 00 3F 14 05 39 40 41 42 43 08 05
   14 3E FFFFFFC0 00 16 08 05 20 3E FFFFFFC0 00 16 08 05 24 3E
   FFFFFFC0 00 16 08 05 32 3E FFFFFFC0 00 08 08 05 45 00 FFFFFF84 00
   46 01 04 63 6F 70 79 14 02 39 47 08 05 32 44 FFFFFFC0
   00 08 08 05 49 00 FFFFFF84 00 4A 01 07 65 71 75 61 6C
   73 31 14 02 4B 4E 10 02 10 4C 09 02 4D 04 02 07
   42 6F 6F 6C 65 61 6E 08 05 4F 48 FFFFFFC0 00 08 01 01
   6D 08 05 51 00 FFFFFF84 00 52 01 0C 67 65 74 4E 61 6D
   65 73 70 61 63 65 14 02 16 53 08 05 54 50 FFFFFFC0 00
   2C 01 05 6F 77 6E 65 72 08 05 56 00 FFFFFF84 00 57 01
   05 61 70 70 6C 79 14 02 26 58 08 05 20 55 FFFFFFC0 00
   16 08 05 56 00 FFFFFF84 00 5A 14 04 26 5B 5D 62 08 05
   5C 59 FFFFFFC0 00 16 01 09 6E 61 6D 65 73 70 61 63 65
   08 05 5E 59 FFFFFFC0 00 5F 01 05 73 63 6F 70 65 10 02
   09 60 09 02 61 02 02 10 4E 61 6D 65 73 70 61 63
   65 42 69 6E 64 69 6E 67 08 05 20 59 FFFFFFC0 00 16 08
   05 64 00 FFFFFF84 02 65 01 0A 69 73 50 72 65 66 69 78
   65 64 15 01 4B 08 05 67 00 FFFFFF84 20 68 01 08 68 61
   73 68 43 6F 64 65 14 01 69 10 02 10 6A 09 02 6B
   04 02 03 49 6E 74 08 05 6D 00 FFFFFF84 00 6E 01 09 74
   6F 53 74 72 69 6E 67 31 14 02 6F 72 10 02 10 70
   09 02 71 04 02 04 55 6E 69 74 08 05 73 6C FFFFFFC0 00
   74 01 02 73 62 10 02 75 78 0D 01 76 0A 02 77 28
   01 07 6D 75 74 61 62 6C 65 09 02 79 76 02 0D 53
   74 72 69 6E 67 42 75 69 6C 64 65 72 08 05 7B 00
   FFFFFF84 00 7C 01 0A 77 65 6C 6C 66 6F 72 6D 65 64 14
   02 4B 7D 08 05 5E 7A FFFFFFC0 00 5F 08 06 7F 00 FFFFFF84 00
   FFFFFF81 00 01 06 72 65 6D 6F 76 65 14 03 39 FFFFFF81 01 08
   05 20 7E FFFFFFC0 00 16 08 06 7F 00 FFFFFF84 00 FFFFFF81 03 14 07
   08 FFFFFF81 04 FFFFFF81 05 FFFFFF81 06 08 06 5C FFFFFF81 02 FFFFFFC0 00 16 08
   06 5E FFFFFF81 02 FFFFFFC0 00 5F 08 06 20 FFFFFF81 02 FFFFFFC0 00 16 07
   07 FFFFFF81 08 02 FFFFFF88 02 FFFFFF81 09 01 11 50 72 65 66 69 78
   65 64 41 74 74 72 69 62 75 74 65 10 03 09 FFFFFF81 0A
   06 09 01 02 FFFFFF84 FFFFFF80 FFFFFF80 FFFFFF88 02 FFFFFF81 0B 13 05 FFFFFF81 0A FFFFFF81
   0C 0F 10 04 FFFFFF81 0D FFFFFF81 12 0D 02 FFFFFF81 0E 0A 04 FFFFFF81 0F
   FFFFFF81 10 01 04 6C 61 6E 67 0A 02 FFFFFF81 11 01 04 6A 61
   76 61 09 04 FFFFFF81 13 FFFFFF81 0E 02 06 4F 62 6A 65 63 74
   08 07 37 FFFFFF81 0A FFFFFF84 00 FFFFFF81 15 14 02 FFFFFF81 09 08 08 FFFFFF81
   17 FFFFFF81 0A FFFFFF84 00 FFFFFF81 18 01 07 75 6E 61 70 70 6C 79
   14 04 FFFFFF81 19 FFFFFF81 1F 10 05 10 FFFFFF81 1A FFFFFF81 1C 09 03 FFFFFF81
   1B 04 02 04 53 6F 6D 65 10 07 10 FFFFFF81 1D 16 16 26
   08 09 03 FFFFFF81 1E 04 02 06 54 75 70 6C 65 34 08 07
   FFFFFF81 20 FFFFFF81 16 FFFFFFC0 00 39 01 01 78 
  minor version: 0
  major version: 49
  Constant pool:
Asciz	SourceFile;
Asciz	PrefixedAttribute.scala;
Asciz	unapply;
Asciz	(Lscala/xml/PrefixedAttribute;)Lscala/Some;;
Asciz	Code;
Asciz	scala/xml/PrefixedAttribute$;
class	scala/xml/PrefixedAttribute$
Asciz	MODULE$;
Asciz	Lscala/xml/PrefixedAttribute$;;
NameAndType	MODULE$:Lscala/xml/PrefixedAttribute$;
Field	scala/xml/PrefixedAttribute$.MODULE$:Lscala/xml/PrefixedAttribute$;
NameAndType	unapply:(Lscala/xml/PrefixedAttribute;)Lscala/Some;
Method	scala/xml/PrefixedAttribute$.unapply:(Lscala/xml/PrefixedAttribute;)Lscala/Some;
Asciz	(Lscala/xml/PrefixedAttribute;)Lscala/Some<Lscala/Tuple4<Ljava/lang/String;Ljava/lang/String;Lscala/collection/Seq<Lscala/xml/Node;>;Lscala/xml/MetaData;>;>;;
Asciz	Signature;
Asciz	next;
Asciz	Lscala/xml/MetaData;;
Asciz	value;
Asciz	Lscala/collection/Seq;;
Asciz	Lscala/collection/Seq<Lscala/xml/Node;>;;
Asciz	key;
Asciz	Ljava/lang/String;;
Asciz	pre;
Asciz	()Ljava/lang/String;;
Asciz	LineNumberTable;
Asciz	scala/xml/PrefixedAttribute;
class	scala/xml/PrefixedAttribute
NameAndType	pre:Ljava/lang/String;
Field	scala/xml/PrefixedAttribute.pre:Ljava/lang/String;
NameAndType	key:Ljava/lang/String;
Field	scala/xml/PrefixedAttribute.key:Ljava/lang/String;
Asciz	()Lscala/collection/Seq;;
NameAndType	value:Lscala/collection/Seq;
Field	scala/xml/PrefixedAttribute.value:Lscala/collection/Seq;
Asciz	()Lscala/collection/Seq<Lscala/xml/Node;>;;
Asciz	()Lscala/xml/MetaData;;
NameAndType	next:Lscala/xml/MetaData;
Field	scala/xml/PrefixedAttribute.next:Lscala/xml/MetaData;
Asciz	<init>;
Asciz	(Ljava/lang/String;Ljava/lang/String;Ljava/lang/String;Lscala/xml/MetaData;)V;
Asciz	scala/xml/Text;
class	scala/xml/Text
Asciz	(Ljava/lang/String;)V;
NameAndType	"<init>":(Ljava/lang/String;)V
Method	scala/xml/Text."<init>":(Ljava/lang/String;)V
Asciz	(Ljava/lang/String;Ljava/lang/String;Lscala/collection/Seq;Lscala/xml/MetaData;)V;
NameAndType	"<init>":(Ljava/lang/String;Ljava/lang/String;Lscala/collection/Seq;Lscala/xml/MetaData;)V
Method	scala/xml/PrefixedAttribute."<init>":(Ljava/lang/String;Ljava/lang/String;Lscala/collection/Seq;Lscala/xml/MetaData;)V
Asciz	this;
Asciz	Lscala/xml/PrefixedAttribute;;
Asciz	LocalVariableTable;
Asciz	copy;
Asciz	(Lscala/xml/MetaData;)Lscala/xml/PrefixedAttribute;;
NameAndType	pre:()Ljava/lang/String;
Method	scala/xml/PrefixedAttribute.pre:()Ljava/lang/String;
NameAndType	key:()Ljava/lang/String;
Method	scala/xml/PrefixedAttribute.key:()Ljava/lang/String;
NameAndType	value:()Lscala/collection/Seq;
Method	scala/xml/PrefixedAttribute.value:()Lscala/collection/Seq;
Asciz	equals1;
Asciz	(Lscala/xml/MetaData;)Z;
Asciz	scala/xml/MetaData;
class	scala/xml/MetaData
Asciz	isPrefixed;
Asciz	()Z;
NameAndType	isPrefixed:()Z
Method	scala/xml/MetaData.isPrefixed:()Z
Asciz	java/lang/Object;
class	java/lang/Object
Asciz	equals;
Asciz	(Ljava/lang/Object;)Z;
NameAndType	equals:(Ljava/lang/Object;)Z
Method	java/lang/Object.equals:(Ljava/lang/Object;)Z
Method	scala/xml/MetaData.key:()Ljava/lang/String;
Method	scala/xml/MetaData.value:()Lscala/collection/Seq;
Asciz	scala/collection/IterableLike;
class	scala/collection/IterableLike
Asciz	sameElements;
Asciz	(Lscala/collection/Iterable;)Z;
NameAndType	sameElements:(Lscala/collection/Iterable;)Z
InterfaceMethod	scala/collection/IterableLike.sameElements:(Lscala/collection/Iterable;)Z
Asciz	m;
Asciz	getNamespace;
Asciz	(Lscala/xml/Node;)Ljava/lang/String;;
Asciz	scala/xml/Node;
class	scala/xml/Node
Asciz	(Ljava/lang/String;)Ljava/lang/String;;
NameAndType	getNamespace:(Ljava/lang/String;)Ljava/lang/String;
Method	scala/xml/Node.getNamespace:(Ljava/lang/String;)Ljava/lang/String;
Asciz	owner;
Asciz	Lscala/xml/Node;;
Asciz	apply;
Asciz	(Ljava/lang/String;)Lscala/collection/Seq;;
NameAndType	next:()Lscala/xml/MetaData;
Method	scala/xml/PrefixedAttribute.next:()Lscala/xml/MetaData;
NameAndType	apply:(Ljava/lang/String;)Lscala/collection/Seq;
Method	scala/xml/MetaData.apply:(Ljava/lang/String;)Lscala/collection/Seq;
Asciz	(Ljava/lang/String;)Lscala/collection/Seq<Lscala/xml/Node;>;;
Asciz	(Ljava/lang/String;Lscala/xml/NamespaceBinding;Ljava/lang/String;)Lscala/collection/Seq;;
Asciz	scala/xml/NamespaceBinding;
class	scala/xml/NamespaceBinding
Asciz	getURI;
NameAndType	getURI:(Ljava/lang/String;)Ljava/lang/String;
Method	scala/xml/NamespaceBinding.getURI:(Ljava/lang/String;)Ljava/lang/String;
NameAndType	apply:(Ljava/lang/String;Lscala/xml/NamespaceBinding;Ljava/lang/String;)Lscala/collection/Seq;
Method	scala/xml/MetaData.apply:(Ljava/lang/String;Lscala/xml/NamespaceBinding;Ljava/lang/String;)Lscala/collection/Seq;
Asciz	namespace;
Asciz	scope;
Asciz	Lscala/xml/NamespaceBinding;;
Asciz	(Ljava/lang/String;Lscala/xml/NamespaceBinding;Ljava/lang/String;)Lscala/collection/Seq<Lscala/xml/Node;>;;
Asciz	hashCode;
Asciz	()I;
Asciz	java/lang/String;
class	java/lang/String
NameAndType	hashCode:()I
Method	java/lang/String.hashCode:()I
int	41;
int	7;
Method	scala/xml/MetaData.hashCode:()I
Asciz	toString1;
Asciz	(Lscala/collection/mutable/StringBuilder;)V;
Asciz	scala/collection/mutable/StringBuilder;
class	scala/collection/mutable/StringBuilder
Asciz	append;
Asciz	(Ljava/lang/String;)Lscala/collection/mutable/StringBuilder;;
NameAndType	append:(Ljava/lang/String;)Lscala/collection/mutable/StringBuilder;
Method	scala/collection/mutable/StringBuilder.append:(Ljava/lang/String;)Lscala/collection/mutable/StringBuilder;
int	58;
Asciz	(C)Lscala/collection/mutable/StringBuilder;;
NameAndType	append:(C)Lscala/collection/mutable/StringBuilder;
Method	scala/collection/mutable/StringBuilder.append:(C)Lscala/collection/mutable/StringBuilder;
int	61;
Asciz	()V;
NameAndType	"<init>":()V
Method	scala/collection/mutable/StringBuilder."<init>":()V
Asciz	scala/xml/Utility$;
class	scala/xml/Utility$
Asciz	Lscala/xml/Utility$;;
NameAndType	MODULE$:Lscala/xml/Utility$;
Field	scala/xml/Utility$.MODULE$:Lscala/xml/Utility$;
Asciz	scala/xml/TopScope$;
class	scala/xml/TopScope$
Asciz	Lscala/xml/TopScope$;;
NameAndType	MODULE$:Lscala/xml/TopScope$;
Field	scala/xml/TopScope$.MODULE$:Lscala/xml/TopScope$;
Asciz	sequenceToXML;
Asciz	(Lscala/collection/Seq;Lscala/xml/NamespaceBinding;Lscala/collection/mutable/StringBuilder;Z)V;
NameAndType	sequenceToXML:(Lscala/collection/Seq;Lscala/xml/NamespaceBinding;Lscala/collection/mutable/StringBuilder;Z)V
Method	scala/xml/Utility$.sequenceToXML:(Lscala/collection/Seq;Lscala/xml/NamespaceBinding;Lscala/collection/mutable/StringBuilder;Z)V
Asciz	toString;
NameAndType	toString:()Ljava/lang/String;
Method	scala/collection/mutable/StringBuilder.toString:()Ljava/lang/String;
Asciz	appendQuoted;
Asciz	(Ljava/lang/String;Lscala/collection/mutable/StringBuilder;)Lscala/collection/mutable/StringBuilder;;
NameAndType	appendQuoted:(Ljava/lang/String;Lscala/collection/mutable/StringBuilder;)Lscala/collection/mutable/StringBuilder;
Method	scala/xml/Utility$.appendQuoted:(Ljava/lang/String;Lscala/collection/mutable/StringBuilder;)Lscala/collection/mutable/StringBuilder;
Asciz	sb;
Asciz	Lscala/collection/mutable/StringBuilder;;
Asciz	sb2;
Asciz	wellformed;
Asciz	(Lscala/xml/NamespaceBinding;)Z;
NameAndType	wellformed:(Lscala/xml/NamespaceBinding;)Z
Method	scala/xml/MetaData.wellformed:(Lscala/xml/NamespaceBinding;)Z
Asciz	remove;
Asciz	(Ljava/lang/String;)Lscala/xml/PrefixedAttribute;;
Asciz	(Ljava/lang/String;)Lscala/xml/MetaData;;
NameAndType	remove:(Ljava/lang/String;)Lscala/xml/MetaData;
Method	scala/xml/MetaData.remove:(Ljava/lang/String;)Lscala/xml/MetaData;
NameAndType	copy:(Lscala/xml/MetaData;)Lscala/xml/PrefixedAttribute;
Method	scala/xml/PrefixedAttribute.copy:(Lscala/xml/MetaData;)Lscala/xml/PrefixedAttribute;
Asciz	(Ljava/lang/String;Lscala/xml/NamespaceBinding;Ljava/lang/String;)Lscala/xml/MetaData;;
NameAndType	remove:(Ljava/lang/String;Lscala/xml/NamespaceBinding;Ljava/lang/String;)Lscala/xml/MetaData;
Method	scala/xml/MetaData.remove:(Ljava/lang/String;Lscala/xml/NamespaceBinding;Ljava/lang/String;)Lscala/xml/MetaData;
NameAndType	remove:(Ljava/lang/String;)Lscala/xml/PrefixedAttribute;
Method	scala/xml/PrefixedAttribute.remove:(Ljava/lang/String;)Lscala/xml/PrefixedAttribute;
Asciz	(Lscala/xml/MetaData;)Lscala/xml/MetaData;;
Asciz	(Lscala/xml/MetaData;)Lscala/xml/Attribute;;
Method	scala/xml/MetaData."<init>":()V
Asciz	java/lang/UnsupportedOperationException;
class	java/lang/UnsupportedOperationException
Asciz	value is null;
String	value is null
Method	java/lang/UnsupportedOperationException."<init>":(Ljava/lang/String;)V
Asciz	(Ljava/lang/String;Ljava/lang/String;Lscala/collection/Seq<Lscala/xml/Node;>;Lscala/xml/MetaData;)V;
Asciz	ScalaSig;
Asciz	scala/xml/Attribute;
class	scala/xml/Attribute
Asciz	scala/ScalaObject;
class	scala/ScalaObject

{
private final scala.xml.MetaData next;
  Signature: Lscala/xml/MetaData;

private final scala.collection.Seq value;
  Signature: Lscala/collection/Seq;
  Signature: length = 0x2
   00 14 

private final java.lang.String key;
  Signature: Ljava/lang/String;

private final java.lang.String pre;
  Signature: Ljava/lang/String;

public static final scala.Some unapply(scala.xml.PrefixedAttribute);
  Signature: (Lscala/xml/PrefixedAttribute;)Lscala/Some;
  Code:
   Stack=2, Locals=1, Args_size=1
	getstatic	Field scala/xml/PrefixedAttribute$.MODULE$:Lscala/xml/PrefixedAttribute$;
	aload_0
	invokevirtual	Method scala/xml/PrefixedAttribute$.unapply:(Lscala/xml/PrefixedAttribute;)Lscala/Some;
	areturn
  Labels:
  Signature: length = 0x2
   00 0E 

public java.lang.String pre();
  Signature: ()Ljava/lang/String;
  Code:
   Stack=1, Locals=1, Args_size=1
	aload_0
	getfield	Field pre:Ljava/lang/String;
	areturn
  Labels:

public java.lang.String key();
  Signature: ()Ljava/lang/String;
  Code:
   Stack=1, Locals=1, Args_size=1
	aload_0
	getfield	Field key:Ljava/lang/String;
	areturn
  Labels:

public scala.collection.Seq value();
  Signature: ()Lscala/collection/Seq;
  Code:
   Stack=1, Locals=1, Args_size=1
	aload_0
	getfield	Field value:Lscala/collection/Seq;
	areturn
  Labels:
  Signature: length = 0x2
   00 23 

public scala.xml.MetaData next();
  Signature: ()Lscala/xml/MetaData;
  Code:
   Stack=1, Locals=1, Args_size=1
	aload_0
	getfield	Field next:Lscala/xml/MetaData;
	areturn
  Labels:

public scala.xml.PrefixedAttribute(java.lang.String, java.lang.String, java.lang.String, scala.xml.MetaData);
  Signature: (Ljava/lang/String;Ljava/lang/String;Ljava/lang/String;Lscala/xml/MetaData;)V
  Code:
   Stack=6, Locals=5, Args_size=5
	aload_0
	aload_1
	aload_2
	new	class scala/xml/Text
	dup
	aload_3
	invokespecial	Method scala/xml/Text."<init>":(Ljava/lang/String;)V
	aload	4
	invokespecial	Method "<init>":(Ljava/lang/String;Ljava/lang/String;Lscala/collection/Seq;Lscala/xml/MetaData;)V
	return
  Labels:
  LocalVariableTable: 
   Start  Length  Slot  Name   Signature
   0      17      0    this       Lscala/xml/PrefixedAttribute;
   0      17      1    pre       Ljava/lang/String;
   0      17      2    key       Ljava/lang/String;
   0      17      3    value       Ljava/lang/String;
   0      17      4    next       Lscala/xml/MetaData;


public scala.xml.PrefixedAttribute copy(scala.xml.MetaData);
  Signature: (Lscala/xml/MetaData;)Lscala/xml/PrefixedAttribute;
  Code:
   Stack=6, Locals=2, Args_size=2
	new	class scala/xml/PrefixedAttribute
	dup
	aload_0
	invokevirtual	Method pre:()Ljava/lang/String;
	aload_0
	invokevirtual	Method key:()Ljava/lang/String;
	aload_0
	invokevirtual	Method value:()Lscala/collection/Seq;
	aload_1
	invokespecial	Method "<init>":(Ljava/lang/String;Ljava/lang/String;Lscala/collection/Seq;Lscala/xml/MetaData;)V
	areturn
  Labels:
  LocalVariableTable: 
   Start  Length  Slot  Name   Signature
   0      21      0    this       Lscala/xml/PrefixedAttribute;
   0      21      1    next       Lscala/xml/MetaData;


public boolean equals1(scala.xml.MetaData);
  Signature: (Lscala/xml/MetaData;)Z
  Code:
   Stack=2, Locals=4, Args_size=2
	aload_1
	invokevirtual	Method scala/xml/MetaData.isPrefixed:()Z
	ifeq	l1 // iconst_0
	aload_1
	checkcast	class scala/xml/PrefixedAttribute
	invokevirtual	Method pre:()Ljava/lang/String;
	aload_0
	invokevirtual	Method pre:()Ljava/lang/String;
	astore_2
	dup
	ifnonnull	l2 // aload_2
	pop
	aload_2
	ifnull	l3 // aload_1
	goto	l1 // iconst_0
l2	aload_2
	invokevirtual	Method java/lang/Object.equals:(Ljava/lang/Object;)Z
	ifeq	l1 // iconst_0
l3	aload_1
	invokevirtual	Method scala/xml/MetaData.key:()Ljava/lang/String;
	aload_0
	invokevirtual	Method key:()Ljava/lang/String;
	astore_3
	dup
	ifnonnull	l4 // aload_3
	pop
	aload_3
	ifnull	l5 // aload_1
	goto	l1 // iconst_0
l4	aload_3
	invokevirtual	Method java/lang/Object.equals:(Ljava/lang/Object;)Z
	ifeq	l1 // iconst_0
l5	aload_1
	invokevirtual	Method scala/xml/MetaData.value:()Lscala/collection/Seq;
	aload_0
	invokevirtual	Method value:()Lscala/collection/Seq;
	invokeinterface	InterfaceMethod scala/collection/IterableLike.sameElements:(Lscala/collection/Iterable;)Z
	ifeq	l1 // iconst_0
	iconst_1
	goto	l6 // ireturn
l1	iconst_0
l6	ireturn
  Labels:
   	l2 = 31 // aload_2
   	l3 = 38 // aload_1
   	l4 = 59 // aload_3
   	l5 = 66 // aload_1
   	l1 = 86 // iconst_0
   	l6 = 87 // ireturn
  LocalVariableTable: 
   Start  Length  Slot  Name   Signature
   0      88      0    this       Lscala/xml/PrefixedAttribute;
   0      88      1    m       Lscala/xml/MetaData;


public java.lang.String getNamespace(scala.xml.Node);
  Signature: (Lscala/xml/Node;)Ljava/lang/String;
  Code:
   Stack=2, Locals=2, Args_size=2
	aload_1
	aload_0
	invokevirtual	Method pre:()Ljava/lang/String;
	invokevirtual	Method scala/xml/Node.getNamespace:(Ljava/lang/String;)Ljava/lang/String;
	areturn
  Labels:
  LocalVariableTable: 
   Start  Length  Slot  Name   Signature
   0      9      0    this       Lscala/xml/PrefixedAttribute;
   0      9      1    owner       Lscala/xml/Node;


public scala.collection.Seq apply(java.lang.String);
  Signature: (Ljava/lang/String;)Lscala/collection/Seq;
  Code:
   Stack=2, Locals=2, Args_size=2
	aload_0
	invokevirtual	Method next:()Lscala/xml/MetaData;
	aload_1
	invokevirtual	Method scala/xml/MetaData.apply:(Ljava/lang/String;)Lscala/collection/Seq;
	areturn
  Labels:
  LocalVariableTable: 
   Start  Length  Slot  Name   Signature
   0      9      0    this       Lscala/xml/PrefixedAttribute;
   0      9      1    key       Ljava/lang/String;

  Signature: length = 0x2
   00 62 

public scala.collection.Seq apply(java.lang.String, scala.xml.NamespaceBinding, java.lang.String);
  Signature: (Ljava/lang/String;Lscala/xml/NamespaceBinding;Ljava/lang/String;)Lscala/collection/Seq;
  Code:
   Stack=4, Locals=5, Args_size=4
	aload_3
	aload_0
	invokevirtual	Method key:()Ljava/lang/String;
	astore	4
	dup
	ifnonnull	l1 // aload
	pop
	aload	4
	ifnull	l2 // aload_2
	goto	l3 // aload_0
l1	aload	4
	invokevirtual	Method java/lang/Object.equals:(Ljava/lang/Object;)Z
	ifeq	l3 // aload_0
l2	aload_2
	aload_0
	invokevirtual	Method pre:()Ljava/lang/String;
	invokevirtual	Method scala/xml/NamespaceBinding.getURI:(Ljava/lang/String;)Ljava/lang/String;
	dup
	ifnonnull	l4 // aload_1
	pop
	aload_1
	ifnull	l5 // aload_0
	goto	l3 // aload_0
l4	aload_1
	invokevirtual	Method java/lang/Object.equals:(Ljava/lang/Object;)Z
	ifeq	l3 // aload_0
l5	aload_0
	invokevirtual	Method value:()Lscala/collection/Seq;
	goto	l6 // areturn
l3	aload_0
	invokevirtual	Method next:()Lscala/xml/MetaData;
	aload_1
	aload_2
	aload_3
	invokevirtual	Method scala/xml/MetaData.apply:(Ljava/lang/String;Lscala/xml/NamespaceBinding;Ljava/lang/String;)Lscala/collection/Seq;
l6	areturn
  Labels:
   	l1 = 20 // aload
   	l2 = 28 // aload_2
   	l4 = 48 // aload_1
   	l5 = 55 // aload_0
   	l3 = 62 // aload_0
   	l6 = 72 // areturn
  LocalVariableTable: 
   Start  Length  Slot  Name   Signature
   0      73      0    this       Lscala/xml/PrefixedAttribute;
   0      73      1    namespace       Ljava/lang/String;
   0      73      2    scope       Lscala/xml/NamespaceBinding;
   0      73      3    key       Ljava/lang/String;

  Signature: length = 0x2
   00 6E 

public final boolean isPrefixed();
  Signature: ()Z
  Code:
   Stack=1, Locals=1, Args_size=1
	iconst_1
	ireturn
  Labels:

public int hashCode();
  Signature: ()I
  Code:
   Stack=3, Locals=1, Args_size=1
	aload_0
	invokevirtual	Method pre:()Ljava/lang/String;
	invokevirtual	Method java/lang/String.hashCode:()I
	ldc	int 41
	imul
	aload_0
	invokevirtual	Method key:()Ljava/lang/String;
	invokevirtual	Method java/lang/String.hashCode:()I
	ldc	int 7
	imul
	iadd
	aload_0
	invokevirtual	Method next:()Lscala/xml/MetaData;
	invokevirtual	Method scala/xml/MetaData.hashCode:()I
	iadd
	ireturn
  Labels:

public void toString1(scala.collection.mutable.StringBuilder);
  Signature: (Lscala/collection/mutable/StringBuilder;)V
  Code:
   Stack=5, Locals=3, Args_size=2
	aload_0
	invokevirtual	Method value:()Lscala/collection/Seq;
	ifnull	l1 // return
	aload_1
	aload_0
	invokevirtual	Method pre:()Ljava/lang/String;
	invokevirtual	Method scala/collection/mutable/StringBuilder.append:(Ljava/lang/String;)Lscala/collection/mutable/StringBuilder;
	pop
	aload_1
	ldc	int 58
	invokevirtual	Method scala/collection/mutable/StringBuilder.append:(C)Lscala/collection/mutable/StringBuilder;
	pop
	aload_1
	aload_0
	invokevirtual	Method key:()Ljava/lang/String;
	invokevirtual	Method scala/collection/mutable/StringBuilder.append:(Ljava/lang/String;)Lscala/collection/mutable/StringBuilder;
	pop
	aload_1
	ldc	int 61
	invokevirtual	Method scala/collection/mutable/StringBuilder.append:(C)Lscala/collection/mutable/StringBuilder;
	pop
	new	class scala/collection/mutable/StringBuilder
	dup
	invokespecial	Method scala/collection/mutable/StringBuilder."<init>":()V
	astore_2
	getstatic	Field scala/xml/Utility$.MODULE$:Lscala/xml/Utility$;
	aload_0
	invokevirtual	Method value:()Lscala/collection/Seq;
	getstatic	Field scala/xml/TopScope$.MODULE$:Lscala/xml/TopScope$;
	aload_2
	iconst_1
	invokevirtual	Method scala/xml/Utility$.sequenceToXML:(Lscala/collection/Seq;Lscala/xml/NamespaceBinding;Lscala/collection/mutable/StringBuilder;Z)V
	getstatic	Field scala/xml/Utility$.MODULE$:Lscala/xml/Utility$;
	aload_2
	invokevirtual	Method scala/collection/mutable/StringBuilder.toString:()Ljava/lang/String;
	aload_1
	invokevirtual	Method scala/xml/Utility$.appendQuoted:(Ljava/lang/String;Lscala/collection/mutable/StringBuilder;)Lscala/collection/mutable/StringBuilder;
	pop
l1	return
  Labels:
   	l1 = 74 // return
  LocalVariableTable: 
   Start  Length  Slot  Name   Signature
   0      75      0    this       Lscala/xml/PrefixedAttribute;
   0      75      1    sb       Lscala/collection/mutable/StringBuilder;
   47      27      2    sb2       Lscala/collection/mutable/StringBuilder;


public boolean wellformed(scala.xml.NamespaceBinding);
  Signature: (Lscala/xml/NamespaceBinding;)Z
  Code:
   Stack=4, Locals=2, Args_size=2
	aload_0
	invokevirtual	Method next:()Lscala/xml/MetaData;
	aload_1
	aload_0
	invokevirtual	Method pre:()Ljava/lang/String;
	invokevirtual	Method scala/xml/NamespaceBinding.getURI:(Ljava/lang/String;)Ljava/lang/String;
	aload_1
	aload_0
	invokevirtual	Method key:()Ljava/lang/String;
	invokevirtual	Method scala/xml/MetaData.apply:(Ljava/lang/String;Lscala/xml/NamespaceBinding;Ljava/lang/String;)Lscala/collection/Seq;
	ifnonnull	l1 // iconst_0
	aload_0
	invokevirtual	Method next:()Lscala/xml/MetaData;
	aload_1
	invokevirtual	Method scala/xml/MetaData.wellformed:(Lscala/xml/NamespaceBinding;)Z
	ifeq	l1 // iconst_0
	iconst_1
	goto	l2 // ireturn
l1	iconst_0
l2	ireturn
  Labels:
   	l1 = 38 // iconst_0
   	l2 = 39 // ireturn
  LocalVariableTable: 
   Start  Length  Slot  Name   Signature
   0      40      0    this       Lscala/xml/PrefixedAttribute;
   0      40      1    scope       Lscala/xml/NamespaceBinding;


public scala.xml.PrefixedAttribute remove(java.lang.String);
  Signature: (Ljava/lang/String;)Lscala/xml/PrefixedAttribute;
  Code:
   Stack=3, Locals=2, Args_size=2
	aload_0
	aload_0
	invokevirtual	Method next:()Lscala/xml/MetaData;
	aload_1
	invokevirtual	Method scala/xml/MetaData.remove:(Ljava/lang/String;)Lscala/xml/MetaData;
	invokevirtual	Method copy:(Lscala/xml/MetaData;)Lscala/xml/PrefixedAttribute;
	areturn
  Labels:
  LocalVariableTable: 
   Start  Length  Slot  Name   Signature
   0      13      0    this       Lscala/xml/PrefixedAttribute;
   0      13      1    key       Ljava/lang/String;


public scala.xml.MetaData remove(java.lang.String, scala.xml.NamespaceBinding, java.lang.String);
  Signature: (Ljava/lang/String;Lscala/xml/NamespaceBinding;Ljava/lang/String;)Lscala/xml/MetaData;
  Code:
   Stack=4, Locals=5, Args_size=4
	aload_3
	aload_0
	invokevirtual	Method key:()Ljava/lang/String;
	astore	4
	dup
	ifnonnull	l1 // aload
	pop
	aload	4
	ifnull	l2 // aload_2
	goto	l3 // aload_0
l1	aload	4
	invokevirtual	Method java/lang/Object.equals:(Ljava/lang/Object;)Z
	ifeq	l3 // aload_0
l2	aload_2
	aload_0
	invokevirtual	Method pre:()Ljava/lang/String;
	invokevirtual	Method scala/xml/NamespaceBinding.getURI:(Ljava/lang/String;)Ljava/lang/String;
	dup
	ifnonnull	l4 // aload_1
	pop
	aload_1
	ifnull	l5 // aload_0
	goto	l3 // aload_0
l4	aload_1
	invokevirtual	Method java/lang/Object.equals:(Ljava/lang/Object;)Z
	ifeq	l3 // aload_0
l5	aload_0
	invokevirtual	Method next:()Lscala/xml/MetaData;
	goto	l6 // areturn
l3	aload_0
	invokevirtual	Method next:()Lscala/xml/MetaData;
	aload_1
	aload_2
	aload_3
	invokevirtual	Method scala/xml/MetaData.remove:(Ljava/lang/String;Lscala/xml/NamespaceBinding;Ljava/lang/String;)Lscala/xml/MetaData;
l6	areturn
  Labels:
   	l1 = 20 // aload
   	l2 = 28 // aload_2
   	l4 = 48 // aload_1
   	l5 = 55 // aload_0
   	l3 = 62 // aload_0
   	l6 = 72 // areturn
  LocalVariableTable: 
   Start  Length  Slot  Name   Signature
   0      73      0    this       Lscala/xml/PrefixedAttribute;
   0      73      1    namespace       Ljava/lang/String;
   0      73      2    scope       Lscala/xml/NamespaceBinding;
   0      73      3    key       Ljava/lang/String;


public scala.xml.MetaData remove(java.lang.String);
  Signature: (Ljava/lang/String;)Lscala/xml/MetaData;
  Code:
   Stack=2, Locals=2, Args_size=2
	aload_0
	aload_1
	invokevirtual	Method remove:(Ljava/lang/String;)Lscala/xml/PrefixedAttribute;
	areturn
  Labels:
  LocalVariableTable: 
   Start  Length  Slot  Name   Signature
   0      6      0    this       Lscala/xml/PrefixedAttribute;
   0      6      1    key       Ljava/lang/String;


public scala.xml.MetaData copy(scala.xml.MetaData);
  Signature: (Lscala/xml/MetaData;)Lscala/xml/MetaData;
  Code:
   Stack=2, Locals=2, Args_size=2
	aload_0
	aload_1
	invokevirtual	Method copy:(Lscala/xml/MetaData;)Lscala/xml/PrefixedAttribute;
	areturn
  Labels:
  LocalVariableTable: 
   Start  Length  Slot  Name   Signature
   0      6      0    this       Lscala/xml/PrefixedAttribute;
   0      6      1    next       Lscala/xml/MetaData;


public scala.xml.Attribute copy(scala.xml.MetaData);
  Signature: (Lscala/xml/MetaData;)Lscala/xml/Attribute;
  Code:
   Stack=2, Locals=2, Args_size=2
	aload_0
	aload_1
	invokevirtual	Method copy:(Lscala/xml/MetaData;)Lscala/xml/PrefixedAttribute;
	areturn
  Labels:
  LocalVariableTable: 
   Start  Length  Slot  Name   Signature
   0      6      0    this       Lscala/xml/PrefixedAttribute;
   0      6      1    next       Lscala/xml/MetaData;


public scala.xml.PrefixedAttribute(java.lang.String, java.lang.String, scala.collection.Seq, scala.xml.MetaData);
  Signature: (Ljava/lang/String;Ljava/lang/String;Lscala/collection/Seq;Lscala/xml/MetaData;)V
  Code:
   Stack=3, Locals=5, Args_size=5
	aload_0
	aload_1
	putfield	Field pre:Ljava/lang/String;
	aload_0
	aload_2
	putfield	Field key:Ljava/lang/String;
	aload_0
	aload_3
	putfield	Field value:Lscala/collection/Seq;
	aload_0
	aload	4
	putfield	Field next:Lscala/xml/MetaData;
	aload_0
	invokespecial	Method scala/xml/MetaData."<init>":()V
	aload_3
	ifnonnull	l1 // return
	new	class java/lang/UnsupportedOperationException
	dup
	ldc	String value is null
	invokespecial	Method java/lang/UnsupportedOperationException."<init>":(Ljava/lang/String;)V
	athrow
l1	return
  Labels:
   	l1 = 39 // return
  LocalVariableTable: 
   Start  Length  Slot  Name   Signature
   0      40      0    this       Lscala/xml/PrefixedAttribute;
   0      40      1    pre       Ljava/lang/String;
   0      40      2    key       Ljava/lang/String;
   0      40      3    value       Lscala/collection/Seq;
   0      40      4    next       Lscala/xml/MetaData;

  Signature: length = 0x2
   00 FFFFFFB8 

}

