Compiled from "PrettyPrinter.scala"
public final class scala.xml.PrettyPrinter$$anonfun$startTag$1 extends scala.runtime.AbstractFunction1 implements java.io.Serializable
  SourceFile: "PrettyPrinter.scala"
  Scala: length = 0x
   
  InnerClass: 
   public final $anonfun$startTag$1=class scala/xml/PrettyPrinter$$anonfun$startTag$1 of class scala/xml/PrettyPrinter
  minor version: 0
  major version: 49
  Constant pool:
Asciz	SourceFile;
Asciz	PrettyPrinter.scala;
Asciz	<clinit>;
Asciz	()V;
Asciz	Code;
Asciz	serialVersionUID;
Asciz	J;
Asciz	scala/xml/PrettyPrinter$$anonfun$startTag$1;
class	scala/xml/PrettyPrinter$$anonfun$startTag$1
NameAndType	serialVersionUID:J
Field	scala/xml/PrettyPrinter$$anonfun$startTag$1.serialVersionUID:J
Asciz	i$1;
Asciz	Lscala/runtime/IntRef;;
Asciz	pscope$1;
Asciz	Lscala/xml/NamespaceBinding;;
Asciz	n$2;
Asciz	Lscala/xml/Node;;
Asciz	$outer;
Asciz	Lscala/xml/PrettyPrinter;;
Asciz	apply;
Asciz	(Lscala/collection/mutable/StringBuilder;)V;
Asciz	LineNumberTable;
NameAndType	$outer:Lscala/xml/PrettyPrinter;
Field	scala/xml/PrettyPrinter$$anonfun$startTag$1.$outer:Lscala/xml/PrettyPrinter;
NameAndType	n$2:Lscala/xml/Node;
Field	scala/xml/PrettyPrinter$$anonfun$startTag$1.n$2:Lscala/xml/Node;
NameAndType	pscope$1:Lscala/xml/NamespaceBinding;
Field	scala/xml/PrettyPrinter$$anonfun$startTag$1.pscope$1:Lscala/xml/NamespaceBinding;
NameAndType	i$1:Lscala/runtime/IntRef;
Field	scala/xml/PrettyPrinter$$anonfun$startTag$1.i$1:Lscala/runtime/IntRef;
Asciz	scala/xml/PrettyPrinter;
class	scala/xml/PrettyPrinter
Asciz	mkStart$1;
Asciz	(Lscala/collection/mutable/StringBuilder;Lscala/xml/Node;Lscala/xml/NamespaceBinding;Lscala/runtime/IntRef;)V;
NameAndType	mkStart$1:(Lscala/collection/mutable/StringBuilder;Lscala/xml/Node;Lscala/xml/NamespaceBinding;Lscala/runtime/IntRef;)V
Method	scala/xml/PrettyPrinter.mkStart$1:(Lscala/collection/mutable/StringBuilder;Lscala/xml/Node;Lscala/xml/NamespaceBinding;Lscala/runtime/IntRef;)V
Asciz	(Ljava/lang/Object;)Ljava/lang/Object;;
Asciz	scala/collection/mutable/StringBuilder;
class	scala/collection/mutable/StringBuilder
NameAndType	apply:(Lscala/collection/mutable/StringBuilder;)V
Method	scala/xml/PrettyPrinter$$anonfun$startTag$1.apply:(Lscala/collection/mutable/StringBuilder;)V
Asciz	scala/runtime/BoxedUnit;
class	scala/runtime/BoxedUnit
Asciz	UNIT;
Asciz	Lscala/runtime/BoxedUnit;;
NameAndType	UNIT:Lscala/runtime/BoxedUnit;
Field	scala/runtime/BoxedUnit.UNIT:Lscala/runtime/BoxedUnit;
Asciz	this;
Asciz	Lscala/xml/PrettyPrinter$$anonfun$startTag$1;;
Asciz	v1;
Asciz	Ljava/lang/Object;;
Asciz	LocalVariableTable;
Asciz	<init>;
Asciz	(Lscala/xml/PrettyPrinter;Lscala/xml/Node;Lscala/xml/NamespaceBinding;Lscala/runtime/IntRef;)V;
Asciz	java/lang/NullPointerException;
class	java/lang/NullPointerException
NameAndType	"<init>":()V
Method	java/lang/NullPointerException."<init>":()V
Asciz	scala/runtime/AbstractFunction1;
class	scala/runtime/AbstractFunction1
Method	scala/runtime/AbstractFunction1."<init>":()V
Asciz	Scala;
Asciz	InnerClasses;
Asciz	$anonfun$startTag$1;
Asciz	java/io/Serializable;
class	java/io/Serializable

{
public static final long serialVersionUID;
  Signature: J

private final scala.runtime.IntRef i$1;
  Signature: Lscala/runtime/IntRef;

private final scala.xml.NamespaceBinding pscope$1;
  Signature: Lscala/xml/NamespaceBinding;

private final scala.xml.Node n$2;
  Signature: Lscala/xml/Node;

private final scala.xml.PrettyPrinter $outer;
  Signature: Lscala/xml/PrettyPrinter;

public static {};
  Signature: ()V
  Code:
   Stack=2, Locals=0, Args_size=0
	lconst_0
	putstatic	Field serialVersionUID:J
	return
  Labels:

public final void apply(scala.collection.mutable.StringBuilder);
  Signature: (Lscala/collection/mutable/StringBuilder;)V
  Code:
   Stack=5, Locals=2, Args_size=2
	aload_0
	getfield	Field $outer:Lscala/xml/PrettyPrinter;
	aload_1
	aload_0
	getfield	Field n$2:Lscala/xml/Node;
	aload_0
	getfield	Field pscope$1:Lscala/xml/NamespaceBinding;
	aload_0
	getfield	Field i$1:Lscala/runtime/IntRef;
	invokevirtual	Method scala/xml/PrettyPrinter.mkStart$1:(Lscala/collection/mutable/StringBuilder;Lscala/xml/Node;Lscala/xml/NamespaceBinding;Lscala/runtime/IntRef;)V
	return
  Labels:

public final java.lang.Object apply(java.lang.Object);
  Signature: (Ljava/lang/Object;)Ljava/lang/Object;
  Code:
   Stack=2, Locals=2, Args_size=2
	aload_0
	aload_1
	checkcast	class scala/collection/mutable/StringBuilder
	invokevirtual	Method apply:(Lscala/collection/mutable/StringBuilder;)V
	getstatic	Field scala/runtime/BoxedUnit.UNIT:Lscala/runtime/BoxedUnit;
	areturn
  Labels:
  LocalVariableTable: 
   Start  Length  Slot  Name   Signature
   0      12      0    this       Lscala/xml/PrettyPrinter$$anonfun$startTag$1;
   0      12      1    v1       Ljava/lang/Object;


public scala.xml.PrettyPrinter$$anonfun$startTag$1(scala.xml.PrettyPrinter, scala.xml.Node, scala.xml.NamespaceBinding, scala.runtime.IntRef);
  Signature: (Lscala/xml/PrettyPrinter;Lscala/xml/Node;Lscala/xml/NamespaceBinding;Lscala/runtime/IntRef;)V
  Code:
   Stack=2, Locals=5, Args_size=5
	aload_1
	ifnonnull	l1 // aload_0
	new	class java/lang/NullPointerException
	dup
	invokespecial	Method java/lang/NullPointerException."<init>":()V
	athrow
l1	aload_0
	aload_1
	putfield	Field $outer:Lscala/xml/PrettyPrinter;
	aload_0
	aload_2
	putfield	Field n$2:Lscala/xml/Node;
	aload_0
	aload_3
	putfield	Field pscope$1:Lscala/xml/NamespaceBinding;
	aload_0
	aload	4
	putfield	Field i$1:Lscala/runtime/IntRef;
	aload_0
	invokespecial	Method scala/runtime/AbstractFunction1."<init>":()V
	return
  Labels:
   	l1 = 12 // aload_0
  LocalVariableTable: 
   Start  Length  Slot  Name   Signature
   0      38      0    this       Lscala/xml/PrettyPrinter$$anonfun$startTag$1;
   0      38      1    $outer       Lscala/xml/PrettyPrinter;


}

