Compiled from "PrettyPrinter.scala"
public class scala.xml.PrettyPrinter extends java.lang.Object implements scala.ScalaObject
  SourceFile: "PrettyPrinter.scala"
  ScalaSig: length = 0xB3B
   05 00 FFFFFF82 73 06 08 01 02 FFFFFF84 FFFFFF80 FFFFFF80 FFFFFF80 00 07 02 0D
   50 72 65 74 74 79 50 72 69 6E 74 65 72 0A 02 03
   04 01 03 78 6D 6C 0A 01 05 01 05 73 63 61 6C 61
   03 00 13 03 00 08 10 10 02 09 0E 0D 01 0A 0A 02
   0B 0C 01 04 6C 61 6E 67 0A 01 0D 01 04 6A 61 76
   61 09 02 0F 0A 02 06 4F 62 6A 65 63 74 10 02 11
   12 0D 01 04 09 02 13 04 02 0B 53 63 61 6C 61 4F
   62 6A 65 63 74 08 08 15 00 FFFFFF82 FFFFFF80 FFFFFFA0 FFFFFF80 04 16 01
   05 77 69 64 74 68 10 02 11 17 09 02 18 04 02 03
   49 6E 74 08 08 1A 00 FFFFFF82 FFFFFF80 FFFFFFA0 FFFFFF80 04 16 01 04 73
   74 65 70 08 05 1C 00 FFFFFF84 00 1D 01 06 3C 69 6E 69
   74 3E 14 03 1E 20 21 10 02 1F 00 0D 01 02 08 05
   15 1B FFFFFFC0 00 16 08 05 1A 1B FFFFFFC0 00 16 06 08 23 00
   FFFFFF84 FFFFFF80 FFFFFF80 FFFFFF80 00 24 02 0F 42 72 6F 6B 65 6E 45 78
   63 65 70 74 69 6F 6E 13 03 22 25 10 10 02 09 26
   09 02 27 0A 02 09 45 78 63 65 70 74 69 6F 6E 08
   05 1C 22 FFFFFF84 00 29 14 01 2A 10 02 2B 22 0D 01 00
   06 08 2D 00 FFFFFF84 FFFFFF80 FFFFFF80 FFFFFF80 00 2E 02 04 49 74 65 6D
   13 03 2C 08 10 08 05 1C 2C FFFFFF84 00 30 14 01 31 10
   02 2B 2C 07 05 33 00 FFFFFF88 42 34 01 05 42 72 65 61
   6B 10 02 2B 35 06 08 36 00 FFFFFF84 FFFFFF80 FFFFFF80 FFFFFF88 42 37 02
   05 42 72 65 61 6B 13 04 35 31 10 38 10 02 11 39
   09 02 3A 04 02 07 50 72 6F 64 75 63 74 08 05 1C
   35 FFFFFF84 00 3C 14 01 34 08 05 3E 35 FFFFFF84 20 3F 01 08
   74 6F 53 74 72 69 6E 67 14 01 40 10 02 09 41 09
   02 42 0A 02 06 53 74 72 69 6E 67 08 08 44 35 FFFFFF84
   FFFFFF80 FFFFFF80 FFFFFF84 20 45 01 0D 70 72 6F 64 75 63 74 50 72
   65 66 69 78 15 01 40 08 08 47 35 FFFFFF84 FFFFFF80 FFFFFF80 FFFFFF84 20
   48 01 0C 70 72 6F 64 75 63 74 41 72 69 74 79 15
   01 16 08 08 4A 35 FFFFFF84 FFFFFF80 FFFFFF80 FFFFFF84 20 4B 01 0E 70 72
   6F 64 75 63 74 45 6C 65 6D 65 6E 74 14 02 4C 4F
   10 02 11 4D 09 02 4E 04 02 03 41 6E 79 08 07 50
   49 FFFFFF81 FFFFFF80 FFFFFFC0 00 16 01 03 78 24 31 08 08 52 35 FFFFFF84
   FFFFFF80 FFFFFF80 FFFFFF84 20 53 01 08 63 61 6E 45 71 75 61 6C 14
   02 54 57 10 02 11 55 09 02 56 04 02 07 42 6F 6F
   6C 65 61 6E 08 07 50 51 FFFFFF81 FFFFFF80 FFFFFFC0 00 4C 08 08 59
   35 FFFFFF84 FFFFFF80 FFFFFF80 FFFFFF84 08 5A 01 0B 72 65 61 64 52 65 73
   6F 6C 76 65 14 01 08 28 02 35 5C 10 02 11 5D 09
   02 5E 04 02 0C 73 65 72 69 61 6C 69 7A 61 62 6C
   65 06 08 60 00 FFFFFF84 FFFFFF80 FFFFFF80 FFFFFF80 40 61 02 03 42 6F 78
   13 04 5F 31 10 38 08 08 63 5F FFFFFF82 FFFFFFCA FFFFFF80 FFFFFF84 00 48
   01 03 63 6F 6C 08 08 65 5F FFFFFF82 FFFFFF88 FFFFFFA0 FFFFFF80 04 16 01
   04 63 6F 6C 20 08 08 67 5F FFFFFF82 FFFFFFCA FFFFFF80 FFFFFF84 00 68 01
   01 73 15 01 69 10 02 6A 6D 0E 02 11 6B 09 02 6C
   04 01 06 50 72 65 64 65 66 09 02 42 6E 0A 02 6C
   04 08 08 70 5F FFFFFF82 FFFFFF88 FFFFFFA0 FFFFFF80 04 69 01 02 73 20 08
   05 1C 5F FFFFFF84 00 72 14 03 73 74 75 10 02 2B 5F 08
   05 63 71 FFFFFFC0 00 16 08 05 67 71 FFFFFFC0 00 69 08 07 77
   5F FFFFFF81 FFFFFF80 FFFFFF84 00 78 01 04 63 6F 70 79 14 03 73 79
   7A 08 07 63 76 FFFFFF90 FFFFFF80 FFFFFFC0 00 16 08 07 67 76 FFFFFF90 FFFFFF80
   FFFFFFC0 00 69 08 07 7C 5F FFFFFF91 FFFFFF80 FFFFFF84 00 7D 01 0E 63 6F
   70 79 24 64 65 66 61 75 6C 74 24 31 15 01 7E 2A
   02 16 7F 2B 02 FFFFFF81 00 10 04 FFFFFF81 01 FFFFFF81 06 0D 02 FFFFFF81
   02 0A 04 FFFFFF81 03 FFFFFF81 04 01 09 75 6E 63 68 65 63 6B
   65 64 0A 03 FFFFFF81 05 04 01 0A 61 6E 6E 6F 74 61 74
   69 6F 6E 09 04 FFFFFF81 07 FFFFFF81 02 02 11 75 6E 63 68 65
   63 6B 65 64 56 61 72 69 61 6E 63 65 08 09 FFFFFF81 09
   5F FFFFFF91 FFFFFF80 FFFFFF84 00 FFFFFF81 0A 01 0E 63 6F 70 79 24 64 65
   66 61 75 6C 74 24 32 15 02 FFFFFF81 0B 2A 02 69 7F 08
   0A FFFFFF81 0D 5F FFFFFF84 FFFFFF80 FFFFFF80 FFFFFF84 20 FFFFFF81 0E 01 08 68 61 73
   68 43 6F 64 65 14 01 16 08 09 3E 5F FFFFFF84 FFFFFF80 FFFFFF80 FFFFFF84
   20 FFFFFF81 10 14 01 69 08 0A FFFFFF81 12 5F FFFFFF84 FFFFFF80 FFFFFF80 FFFFFF84 20
   FFFFFF81 13 01 06 65 71 75 61 6C 73 14 03 54 FFFFFF81 14 08
   08 50 FFFFFF81 11 FFFFFF81 FFFFFF80 FFFFFFC0 00 4C 08 08 44 5F FFFFFF84 FFFFFF80 FFFFFF80
   FFFFFF84 20 45 08 08 47 5F FFFFFF84 FFFFFF80 FFFFFF80 FFFFFF84 20 48 08 09 4A
   5F FFFFFF84 FFFFFF80 FFFFFF80 FFFFFF84 20 FFFFFF81 18 14 03 4C FFFFFF81 19 08 08 50
   FFFFFF81 17 FFFFFF81 FFFFFF80 FFFFFFC0 00 16 08 09 52 5F FFFFFF84 FFFFFF80 FFFFFF80 FFFFFF84 20
   FFFFFF81 1B 14 03 54 FFFFFF81 1C 08 08 50 FFFFFF81 1A FFFFFF81 FFFFFF80 FFFFFFC0 00
   4C 28 02 5F 5C 07 09 FFFFFF81 1F 00 FFFFFF81 FFFFFF80 FFFFFF88 02 FFFFFF81 20
   01 03 42 6F 78 10 03 2B FFFFFF81 21 06 09 60 00 FFFFFF84 FFFFFF81
   FFFFFF80 FFFFFF88 02 FFFFFF81 22 13 06 FFFFFF81 21 08 FFFFFF81 23 10 10 06 11
   FFFFFF81 24 16 69 73 09 03 FFFFFF81 25 04 02 09 46 75 6E 63
   74 69 6F 6E 32 08 07 1C FFFFFF81 21 FFFFFF84 00 FFFFFF81 27 14 02
   FFFFFF81 20 08 0A FFFFFF81 29 FFFFFF81 21 FFFFFF81 FFFFFF80 FFFFFF84 40 FFFFFF81 2A 01 05
   61 70 70 6C 79 14 05 73 FFFFFF81 2B FFFFFF81 2C 08 06 63 FFFFFF81
   28 FFFFFFC0 00 16 08 06 67 FFFFFF81 28 FFFFFFC0 00 69 08 0A FFFFFF81 2E
   FFFFFF81 21 FFFFFF81 FFFFFF80 FFFFFF84 40 FFFFFF81 2F 01 07 75 6E 61 70 70 6C
   79 14 04 FFFFFF81 30 FFFFFF81 36 10 05 11 FFFFFF81 31 FFFFFF81 33 09 03
   FFFFFF81 32 04 02 04 53 6F 6D 65 10 05 11 FFFFFF81 34 16 69
   09 03 FFFFFF81 35 04 02 06 54 75 70 6C 65 32 08 07 FFFFFF81
   37 FFFFFF81 2D FFFFFFC0 00 73 01 03 78 24 30 06 0A FFFFFF81 39 00
   FFFFFF84 FFFFFF80 FFFFFF80 FFFFFF80 40 FFFFFF81 3A 02 04 50 61 72 61 13 05 FFFFFF81
   38 31 10 38 08 09 67 FFFFFF81 38 FFFFFF82 FFFFFFCA FFFFFF80 FFFFFF84 00 68 08
   09 70 FFFFFF81 38 FFFFFF82 FFFFFF88 FFFFFFA0 FFFFFF80 04 69 08 07 1C FFFFFF81 38 FFFFFF84
   00 FFFFFF81 3E 14 04 FFFFFF81 3F FFFFFF81 40 10 03 2B FFFFFF81 38 08 06
   67 FFFFFF81 3D FFFFFFC0 00 69 08 09 77 FFFFFF81 38 FFFFFF81 FFFFFF80 FFFFFF84 00 FFFFFF81
   42 14 04 FFFFFF81 3F FFFFFF81 43 08 08 67 FFFFFF81 41 FFFFFF90 FFFFFF80 FFFFFFC0 00
   69 08 09 7C FFFFFF81 38 FFFFFF91 FFFFFF80 FFFFFF84 00 FFFFFF81 0A 08 0B FFFFFF81 0D
   FFFFFF81 38 FFFFFF84 FFFFFF80 FFFFFF80 FFFFFF84 20 FFFFFF81 0E 08 0A 3E FFFFFF81 38 FFFFFF84 FFFFFF80
   FFFFFF80 FFFFFF84 20 FFFFFF81 10 08 0B FFFFFF81 12 FFFFFF81 38 FFFFFF84 FFFFFF80 FFFFFF80 FFFFFF84 20
   FFFFFF81 48 14 03 54 FFFFFF81 49 08 08 50 FFFFFF81 47 FFFFFF81 FFFFFF80 FFFFFFC0 00
   4C 08 09 44 FFFFFF81 38 FFFFFF84 FFFFFF80 FFFFFF80 FFFFFF84 20 45 08 09 47 FFFFFF81
   38 FFFFFF84 FFFFFF80 FFFFFF80 FFFFFF84 20 48 08 0A 4A FFFFFF81 38 FFFFFF84 FFFFFF80 FFFFFF80 FFFFFF84
   20 FFFFFF81 4D 14 03 4C FFFFFF81 4E 08 08 50 FFFFFF81 4C FFFFFF81 FFFFFF80 FFFFFFC0
   00 16 08 0A 52 FFFFFF81 38 FFFFFF84 FFFFFF80 FFFFFF80 FFFFFF84 20 FFFFFF81 50 14 03
   54 FFFFFF81 51 08 08 50 FFFFFF81 4F FFFFFF81 FFFFFF80 FFFFFFC0 00 4C 28 03 FFFFFF81
   38 5C 07 09 FFFFFF81 54 00 FFFFFF81 FFFFFF80 FFFFFF88 02 FFFFFF81 55 01 04 50
   61 72 61 10 03 2B FFFFFF81 56 06 0A FFFFFF81 39 00 FFFFFF84 FFFFFF81 FFFFFF80
   FFFFFF88 02 FFFFFF81 57 13 06 FFFFFF81 56 08 FFFFFF81 58 10 10 06 11 FFFFFF81
   59 69 FFFFFF81 3F 09 03 FFFFFF81 5A 04 02 09 46 75 6E 63 74
   69 6F 6E 31 08 07 1C FFFFFF81 56 FFFFFF84 00 FFFFFF81 5C 14 02 FFFFFF81
   55 08 0A FFFFFF81 29 FFFFFF81 56 FFFFFF81 FFFFFF80 FFFFFF84 40 FFFFFF81 5E 14 04 FFFFFF81
   3F FFFFFF81 5F 08 06 67 FFFFFF81 5D FFFFFFC0 00 69 08 0A FFFFFF81 2E FFFFFF81
   56 FFFFFF81 FFFFFF80 FFFFFF84 40 FFFFFF81 61 14 04 FFFFFF81 62 FFFFFF81 63 10 04 11
   FFFFFF81 31 69 08 08 FFFFFF81 37 FFFFFF81 60 FFFFFFC0 00 FFFFFF81 3F 08 09 FFFFFF81
   65 00 FFFFFFC0 FFFFFF80 FFFFFF84 08 FFFFFF81 66 01 05 69 74 65 6D 73 15
   02 FFFFFF81 67 10 05 FFFFFF81 68 FFFFFF81 70 31 0E 04 FFFFFF81 69 FFFFFF81 6E
   0E 04 FFFFFF81 6A FFFFFF81 6D 0D 02 FFFFFF81 6B 0A 03 FFFFFF81 6C 06 01
   06 3C 72 6F 6F 74 3E 09 01 05 09 03 FFFFFF81 6F 04 01
   07 70 61 63 6B 61 67 65 09 04 FFFFFF81 71 FFFFFF81 72 02 04
   4C 69 73 74 0A 03 FFFFFF81 6F 04 08 09 FFFFFF81 74 00 FFFFFFC0 FFFFFF80
   FFFFFF84 08 FFFFFF81 75 01 09 69 74 65 6D 73 5F 24 65 71 14
   04 FFFFFF81 76 FFFFFF81 79 10 03 11 FFFFFF81 77 09 03 FFFFFF81 78 04 02
   04 55 6E 69 74 08 09 50 FFFFFF81 73 FFFFFF81 FFFFFF80 FFFFFFC0 00 FFFFFF81 67
   08 08 FFFFFF81 7B 00 FFFFFFA0 FFFFFFA0 04 FFFFFF81 67 01 06 69 74 65 6D
   73 20 08 08 FFFFFF81 7D 00 FFFFFFC0 FFFFFF80 FFFFFF84 08 48 01 03 63 75
   72 08 09 FFFFFF81 7F 00 FFFFFFC0 FFFFFF80 FFFFFF84 08 FFFFFF82 00 01 07 63 75
   72 5F 24 65 71 14 04 FFFFFF81 76 FFFFFF82 01 08 08 50 FFFFFF81 7E
   FFFFFF81 FFFFFF80 FFFFFFC0 00 16 08 07 FFFFFF82 03 00 FFFFFFA0 FFFFFFA0 04 16 01 04
   63 75 72 20 08 07 FFFFFF82 05 00 FFFFFF84 08 FFFFFF82 06 01 05 72
   65 73 65 74 14 02 FFFFFF81 76 08 07 FFFFFF82 08 00 FFFFFF84 08 FFFFFF82
   09 01 03 63 75 74 14 06 FFFFFF81 67 FFFFFF82 0A FFFFFF82 0B 08 06
   67 FFFFFF82 07 FFFFFFC0 00 69 08 07 FFFFFF82 0C FFFFFF82 07 FFFFFFC0 00 16 01
   03 69 6E 64 08 07 FFFFFF82 0E 00 FFFFFF84 08 FFFFFF82 0F 01 07 6D
   61 6B 65 42 6F 78 14 06 FFFFFF81 76 FFFFFF82 10 FFFFFF82 11 08 07
   FFFFFF82 0C FFFFFF82 0D FFFFFFC0 00 16 08 06 67 FFFFFF82 0D FFFFFFC0 00 69 08
   07 FFFFFF82 13 00 FFFFFF84 08 FFFFFF82 14 01 08 6D 61 6B 65 50 61
   72 61 14 06 FFFFFF81 76 FFFFFF82 15 FFFFFF82 16 08 07 FFFFFF82 0C FFFFFF82 12
   FFFFFFC0 00 16 08 06 67 FFFFFF82 12 FFFFFFC0 00 69 08 07 FFFFFF82 18 00
   FFFFFF84 08 FFFFFF82 06 01 09 6D 61 6B 65 42 72 65 61 6B 08
   07 FFFFFF82 1A 00 FFFFFF84 08 FFFFFF82 1B 01 07 6C 65 61 66 54 61
   67 14 03 69 FFFFFF82 1C 08 08 FFFFFF82 1D FFFFFF82 19 FFFFFFC0 00 FFFFFF82 1E
   01 01 6E 10 03 1F FFFFFF82 1F 09 03 FFFFFF82 20 02 02 04 4E
   6F 64 65 08 07 FFFFFF82 22 00 FFFFFF84 08 FFFFFF82 23 01 08 73 74
   61 72 74 54 61 67 14 06 FFFFFF82 24 FFFFFF82 25 FFFFFF82 26 10 05
   11 FFFFFF81 34 69 16 08 08 FFFFFF82 1D FFFFFF82 21 FFFFFFC0 00 FFFFFF82 1E 08
   08 FFFFFF82 27 FFFFFF82 21 FFFFFFC0 00 FFFFFF82 28 01 06 70 73 63 6F 70
   65 10 03 1F FFFFFF82 29 09 03 FFFFFF82 2A 02 02 10 4E 61 6D
   65 73 70 61 63 65 42 69 6E 64 69 6E 67 08 07 FFFFFF82
   2C 00 FFFFFF84 08 FFFFFF82 2D 01 06 65 6E 64 54 61 67 14 03
   69 FFFFFF82 2E 08 08 FFFFFF82 1D FFFFFF82 2B FFFFFFC0 00 FFFFFF82 1E 08 07 FFFFFF82
   30 00 FFFFFF84 08 FFFFFF82 31 01 11 63 68 69 6C 64 72 65 6E
   41 72 65 4C 65 61 76 65 73 14 03 54 FFFFFF82 32 08 08
   FFFFFF82 1D FFFFFF82 2F FFFFFFC0 00 FFFFFF82 1E 08 07 FFFFFF82 34 00 FFFFFF84 08 FFFFFF82
   35 01 04 66 69 74 73 14 03 54 FFFFFF82 36 08 07 FFFFFF82 37
   FFFFFF82 33 FFFFFFC0 00 69 01 04 74 65 73 74 08 07 FFFFFF82 39 00
   FFFFFF84 04 FFFFFF82 3A 01 0A 64 6F 50 72 65 73 65 72 76 65
   14 03 54 FFFFFF82 3B 08 08 FFFFFF82 3C FFFFFF82 38 FFFFFFC0 00 FFFFFF82 1E 01
   04 6E 6F 64 65 08 07 FFFFFF82 3E 00 FFFFFF84 08 FFFFFF82 3F 01 08
   74 72 61 76 65 72 73 65 14 08 FFFFFF81 76 FFFFFF82 40 FFFFFF82 41
   FFFFFF82 42 08 08 FFFFFF82 3C FFFFFF82 3D FFFFFFC0 00 FFFFFF82 1E 08 08 FFFFFF82 27
   FFFFFF82 3D FFFFFFC0 00 FFFFFF82 28 08 07 FFFFFF82 0C FFFFFF82 3D FFFFFFC0 00 16 08
   07 FFFFFF82 3E 00 FFFFFF84 08 FFFFFF82 44 14 08 FFFFFF81 76 FFFFFF82 45 FFFFFF82 4A
   FFFFFF82 4C 08 08 FFFFFF82 46 FFFFFF82 43 FFFFFFC0 00 FFFFFF82 47 01 02 69 74
   10 06 FFFFFF81 68 FFFFFF82 48 FFFFFF82 1E 09 04 FFFFFF82 49 FFFFFF81 72 02 08
   49 74 65 72 61 74 6F 72 08 08 FFFFFF82 4B FFFFFF82 43 FFFFFFC0 00
   FFFFFF82 28 01 05 73 63 6F 70 65 08 07 FFFFFF82 0C FFFFFF82 43 FFFFFFC0
   00 16 08 07 FFFFFF82 4E 00 FFFFFF84 00 FFFFFF82 4F 01 06 66 6F 72
   6D 61 74 14 06 FFFFFF81 76 FFFFFF82 50 FFFFFF82 51 08 08 FFFFFF82 1D FFFFFF82
   4D FFFFFFC0 00 FFFFFF82 1E 08 08 FFFFFF82 52 FFFFFF82 4D FFFFFFC0 00 FFFFFF82 53 01
   02 73 62 10 04 FFFFFF81 68 FFFFFF82 54 09 04 FFFFFF82 55 FFFFFF81 72 02
   0D 53 74 72 69 6E 67 42 75 69 6C 64 65 72 08 07
   FFFFFF82 4E 00 FFFFFF84 00 FFFFFF82 57 14 08 FFFFFF81 76 FFFFFF82 58 FFFFFF82 59 FFFFFF82
   5A 08 08 FFFFFF82 1D FFFFFF82 56 FFFFFFC0 00 FFFFFF82 1E 08 08 FFFFFF82 27 FFFFFF82
   56 FFFFFFC0 00 FFFFFF82 28 08 08 FFFFFF82 52 FFFFFF82 56 FFFFFFC0 00 FFFFFF82 53 08
   07 FFFFFF82 4E 00 FFFFFF84 00 FFFFFF82 5C 14 05 69 FFFFFF82 5D FFFFFF82 5E 08
   08 FFFFFF82 1D FFFFFF82 5B FFFFFFC0 00 FFFFFF82 1E 08 0A FFFFFF82 27 FFFFFF82 5B FFFFFF90
   FFFFFF80 FFFFFFC0 00 FFFFFF82 28 08 07 FFFFFF82 60 00 FFFFFF84 00 FFFFFF82 61 01 0B
   66 6F 72 6D 61 74 4E 6F 64 65 73 14 05 69 FFFFFF82 62
   FFFFFF82 67 08 08 FFFFFF82 63 FFFFFF82 5F FFFFFFC0 00 FFFFFF82 64 01 05 6E 6F
   64 65 73 10 06 FFFFFF81 68 FFFFFF82 65 FFFFFF82 1E 09 04 FFFFFF82 66 FFFFFF81
   72 02 03 53 65 71 08 0A FFFFFF82 27 FFFFFF82 5F FFFFFF90 FFFFFF80 FFFFFFC0 00
   FFFFFF82 28 08 07 FFFFFF82 60 00 FFFFFF84 00 FFFFFF82 69 14 08 FFFFFF81 76 FFFFFF82
   6A FFFFFF82 6B FFFFFF82 6C 08 08 FFFFFF82 63 FFFFFF82 68 FFFFFFC0 00 FFFFFF82 64 08
   08 FFFFFF82 27 FFFFFF82 68 FFFFFFC0 00 FFFFFF82 28 08 08 FFFFFF82 52 FFFFFF82 68 FFFFFFC0
   00 FFFFFF82 53 08 09 FFFFFF82 6E 00 FFFFFF91 FFFFFF80 FFFFFF84 00 FFFFFF82 6F 01 10
   66 6F 72 6D 61 74 24 64 65 66 61 75 6C 74 24 32
   15 02 FFFFFF82 70 2A 03 FFFFFF82 28 7F 08 09 FFFFFF82 72 00 FFFFFF91 FFFFFF80
   FFFFFF84 00 FFFFFF82 6F 01 15 66 6F 72 6D 61 74 4E 6F 64 65
   73 24 64 65 66 61 75 6C 74 24 32 
  InnerClass: 
   public Box=class scala/xml/PrettyPrinter$Box of class scala/xml/PrettyPrinter
   public Item=class scala/xml/PrettyPrinter$Item of class scala/xml/PrettyPrinter
   public Para=class scala/xml/PrettyPrinter$Para of class scala/xml/PrettyPrinter
   public BrokenException=class scala/xml/PrettyPrinter$BrokenException of class scala/xml/PrettyPrinter
   public final $anonfun$format$2=class scala/xml/PrettyPrinter$$anonfun$format$2 of class scala/xml/PrettyPrinter
   public final $anonfun$endTag$1=class scala/xml/PrettyPrinter$$anonfun$endTag$1 of class scala/xml/PrettyPrinter
   public final $anonfun$format$1=class scala/xml/PrettyPrinter$$anonfun$format$1 of class scala/xml/PrettyPrinter
   public final $anonfun$leafTag$1=class scala/xml/PrettyPrinter$$anonfun$leafTag$1 of class scala/xml/PrettyPrinter
   public final $anonfun$makeBox$1=class scala/xml/PrettyPrinter$$anonfun$makeBox$1 of class scala/xml/PrettyPrinter
   public final $anonfun$startTag$1=class scala/xml/PrettyPrinter$$anonfun$startTag$1 of class scala/xml/PrettyPrinter
   public final $anonfun$traverse$1=class scala/xml/PrettyPrinter$$anonfun$traverse$1 of class scala/xml/PrettyPrinter
   public final $anonfun$doPreserve$2=class scala/xml/PrettyPrinter$$anonfun$doPreserve$2 of class scala/xml/PrettyPrinter
   public final $anonfun$doPreserve$1=class scala/xml/PrettyPrinter$$anonfun$doPreserve$1 of class scala/xml/PrettyPrinter
   public final $anonfun$formatNodes$1=class scala/xml/PrettyPrinter$$anonfun$formatNodes$1 of class scala/xml/PrettyPrinter
   public final $anonfun$formatNodes$2=class scala/xml/PrettyPrinter$$anonfun$formatNodes$2 of class scala/xml/PrettyPrinter
   public final $anonfun$childrenAreLeaves$1=class scala/xml/PrettyPrinter$$anonfun$childrenAreLeaves$1 of class scala/xml/PrettyPrinter
  minor version: 0
  major version: 49
  Constant pool:
Asciz	SourceFile;
Asciz	PrettyPrinter.scala;
Asciz	Box$module;
Asciz	Lscala/xml/PrettyPrinter$Box$;;
Asciz	Para$module;
Asciz	Lscala/xml/PrettyPrinter$Para$;;
Asciz	Break$module;
Asciz	Lscala/xml/PrettyPrinter$Break$;;
Asciz	cur;
Asciz	I;
Asciz	items;
Asciz	Lscala/collection/immutable/List;;
Asciz	Lscala/collection/immutable/List<Lscala/xml/PrettyPrinter$Item;>;;
Asciz	Signature;
Asciz	step;
Asciz	width;
Asciz	<init>;
Asciz	(II)V;
Asciz	Code;
Asciz	LineNumberTable;
Asciz	scala/xml/PrettyPrinter;
class	scala/xml/PrettyPrinter
NameAndType	width:I
Field	scala/xml/PrettyPrinter.width:I
NameAndType	step:I
Field	scala/xml/PrettyPrinter.step:I
Asciz	java/lang/Object;
class	java/lang/Object
Asciz	()V;
NameAndType	"<init>":()V
Method	java/lang/Object."<init>":()V
Asciz	scala/collection/immutable/Nil$;
class	scala/collection/immutable/Nil$
Asciz	MODULE$;
Asciz	Lscala/collection/immutable/Nil$;;
NameAndType	MODULE$:Lscala/collection/immutable/Nil$;
Field	scala/collection/immutable/Nil$.MODULE$:Lscala/collection/immutable/Nil$;
NameAndType	items:Lscala/collection/immutable/List;
Field	scala/xml/PrettyPrinter.items:Lscala/collection/immutable/List;
NameAndType	cur:I
Field	scala/xml/PrettyPrinter.cur:I
Asciz	this;
Asciz	Lscala/xml/PrettyPrinter;;
Asciz	LocalVariableTable;
Asciz	gd3$1;
Asciz	(Ljava/lang/String;)Z;
Asciz	java/lang/String;
class	java/lang/String
Asciz	trim;
Asciz	()Ljava/lang/String;;
NameAndType	trim:()Ljava/lang/String;
Method	java/lang/String.trim:()Ljava/lang/String;
Asciz	;
String	
Asciz	equals;
Asciz	(Ljava/lang/Object;)Z;
NameAndType	equals:(Ljava/lang/Object;)Z
Method	java/lang/Object.equals:(Ljava/lang/Object;)Z
Asciz	isLeaf$1;
Asciz	(Lscala/xml/Node;)Z;
Asciz	scala/xml/Atom;
class	scala/xml/Atom
Asciz	scala/xml/Comment;
class	scala/xml/Comment
Asciz	scala/xml/EntityRef;
class	scala/xml/EntityRef
Asciz	scala/xml/ProcInstr;
class	scala/xml/ProcInstr
Asciz	l;
Asciz	Lscala/xml/Node;;
Asciz	mkEnd$1;
Asciz	(Lscala/collection/mutable/StringBuilder;Lscala/xml/Node;)V;
Asciz	</;
String	</
Asciz	scala/collection/mutable/StringBuilder;
class	scala/collection/mutable/StringBuilder
Asciz	append;
Asciz	(Ljava/lang/String;)Lscala/collection/mutable/StringBuilder;;
NameAndType	append:(Ljava/lang/String;)Lscala/collection/mutable/StringBuilder;
Method	scala/collection/mutable/StringBuilder.append:(Ljava/lang/String;)Lscala/collection/mutable/StringBuilder;
Asciz	scala/xml/Node;
class	scala/xml/Node
Asciz	nameToString;
Asciz	(Lscala/collection/mutable/StringBuilder;)Lscala/collection/mutable/StringBuilder;;
NameAndType	nameToString:(Lscala/collection/mutable/StringBuilder;)Lscala/collection/mutable/StringBuilder;
Method	scala/xml/Node.nameToString:(Lscala/collection/mutable/StringBuilder;)Lscala/collection/mutable/StringBuilder;
int	62;
Asciz	(C)Lscala/collection/mutable/StringBuilder;;
NameAndType	append:(C)Lscala/collection/mutable/StringBuilder;
Method	scala/collection/mutable/StringBuilder.append:(C)Lscala/collection/mutable/StringBuilder;
Asciz	sb;
Asciz	Lscala/collection/mutable/StringBuilder;;
Asciz	mkStart$1;
Asciz	(Lscala/collection/mutable/StringBuilder;Lscala/xml/Node;Lscala/xml/NamespaceBinding;Lscala/runtime/IntRef;)V;
int	60;
Asciz	length;
Asciz	()I;
NameAndType	length:()I
Method	scala/collection/mutable/StringBuilder.length:()I
Asciz	scala/runtime/IntRef;
class	scala/runtime/IntRef
Asciz	elem;
NameAndType	elem:I
Field	scala/runtime/IntRef.elem:I
Asciz	attributes;
Asciz	()Lscala/xml/MetaData;;
NameAndType	attributes:()Lscala/xml/MetaData;
Method	scala/xml/Node.attributes:()Lscala/xml/MetaData;
Asciz	scala/xml/MetaData;
class	scala/xml/MetaData
Asciz	buildString;
NameAndType	buildString:(Lscala/collection/mutable/StringBuilder;)Lscala/collection/mutable/StringBuilder;
Method	scala/xml/MetaData.buildString:(Lscala/collection/mutable/StringBuilder;)Lscala/collection/mutable/StringBuilder;
Asciz	scope;
Asciz	()Lscala/xml/NamespaceBinding;;
NameAndType	scope:()Lscala/xml/NamespaceBinding;
Method	scala/xml/Node.scope:()Lscala/xml/NamespaceBinding;
Asciz	scala/xml/NamespaceBinding;
class	scala/xml/NamespaceBinding
Asciz	(Lscala/collection/mutable/StringBuilder;Lscala/xml/NamespaceBinding;)V;
NameAndType	buildString:(Lscala/collection/mutable/StringBuilder;Lscala/xml/NamespaceBinding;)V
Method	scala/xml/NamespaceBinding.buildString:(Lscala/collection/mutable/StringBuilder;Lscala/xml/NamespaceBinding;)V
Asciz	mkLeaf$1;
Asciz	/>;
String	/>
Asciz	Box;
Asciz	()Lscala/xml/PrettyPrinter$Box$;;
NameAndType	Box$module:Lscala/xml/PrettyPrinter$Box$;
Field	scala/xml/PrettyPrinter.Box$module:Lscala/xml/PrettyPrinter$Box$;
Asciz	scala/xml/PrettyPrinter$Box$;
class	scala/xml/PrettyPrinter$Box$
Asciz	(Lscala/xml/PrettyPrinter;)V;
NameAndType	"<init>":(Lscala/xml/PrettyPrinter;)V
Method	scala/xml/PrettyPrinter$Box$."<init>":(Lscala/xml/PrettyPrinter;)V
Asciz	Para;
Asciz	()Lscala/xml/PrettyPrinter$Para$;;
NameAndType	Para$module:Lscala/xml/PrettyPrinter$Para$;
Field	scala/xml/PrettyPrinter.Para$module:Lscala/xml/PrettyPrinter$Para$;
Asciz	scala/xml/PrettyPrinter$Para$;
class	scala/xml/PrettyPrinter$Para$
Method	scala/xml/PrettyPrinter$Para$."<init>":(Lscala/xml/PrettyPrinter;)V
Asciz	formatNodes;
Asciz	(Lscala/collection/Seq;Lscala/xml/NamespaceBinding;Lscala/collection/mutable/StringBuilder;)V;
Asciz	scala/xml/PrettyPrinter$$anonfun$formatNodes$2;
class	scala/xml/PrettyPrinter$$anonfun$formatNodes$2
Asciz	(Lscala/xml/PrettyPrinter;Lscala/xml/NamespaceBinding;Lscala/collection/mutable/StringBuilder;)V;
NameAndType	"<init>":(Lscala/xml/PrettyPrinter;Lscala/xml/NamespaceBinding;Lscala/collection/mutable/StringBuilder;)V
Method	scala/xml/PrettyPrinter$$anonfun$formatNodes$2."<init>":(Lscala/xml/PrettyPrinter;Lscala/xml/NamespaceBinding;Lscala/collection/mutable/StringBuilder;)V
Asciz	scala/collection/IterableLike;
class	scala/collection/IterableLike
Asciz	foreach;
Asciz	(Lscala/Function1;)V;
NameAndType	foreach:(Lscala/Function1;)V
InterfaceMethod	scala/collection/IterableLike.foreach:(Lscala/Function1;)V
Asciz	nodes;
Asciz	Lscala/collection/Seq;;
Asciz	pscope$4;
Asciz	Lscala/xml/NamespaceBinding;;
Asciz	sb$2;
Asciz	(Lscala/collection/Seq<Lscala/xml/Node;>;Lscala/xml/NamespaceBinding;Lscala/collection/mutable/StringBuilder;)V;
Asciz	(Lscala/collection/Seq;Lscala/xml/NamespaceBinding;)Ljava/lang/String;;
Method	scala/collection/mutable/StringBuilder."<init>":()V
NameAndType	formatNodes:(Lscala/collection/Seq;Lscala/xml/NamespaceBinding;Lscala/collection/mutable/StringBuilder;)V
Method	scala/xml/PrettyPrinter.formatNodes:(Lscala/collection/Seq;Lscala/xml/NamespaceBinding;Lscala/collection/mutable/StringBuilder;)V
Asciz	toString;
NameAndType	toString:()Ljava/lang/String;
Method	scala/collection/mutable/StringBuilder.toString:()Ljava/lang/String;
Asciz	nodes$1;
Asciz	pscope$3;
Asciz	sb0;
Asciz	(Lscala/collection/Seq<Lscala/xml/Node;>;Lscala/xml/NamespaceBinding;)Ljava/lang/String;;
Asciz	format;
Asciz	(Lscala/xml/Node;Lscala/xml/NamespaceBinding;)Ljava/lang/String;;
Asciz	(Lscala/xml/Node;Lscala/xml/NamespaceBinding;Lscala/collection/mutable/StringBuilder;)V;
NameAndType	format:(Lscala/xml/Node;Lscala/xml/NamespaceBinding;Lscala/collection/mutable/StringBuilder;)V
Method	scala/xml/PrettyPrinter.format:(Lscala/xml/Node;Lscala/xml/NamespaceBinding;Lscala/collection/mutable/StringBuilder;)V
Asciz	n$4;
Asciz	pscope$2;
Asciz	scala/runtime/BooleanRef;
class	scala/runtime/BooleanRef
Asciz	(Z)V;
NameAndType	"<init>":(Z)V
Method	scala/runtime/BooleanRef."<init>":(Z)V
Asciz	reset;
NameAndType	reset:()V
Method	scala/xml/PrettyPrinter.reset:()V
Asciz	traverse;
Asciz	(Lscala/xml/Node;Lscala/xml/NamespaceBinding;I)V;
NameAndType	traverse:(Lscala/xml/Node;Lscala/xml/NamespaceBinding;I)V
Method	scala/xml/PrettyPrinter.traverse:(Lscala/xml/Node;Lscala/xml/NamespaceBinding;I)V
Asciz	(I)V;
NameAndType	"<init>":(I)V
Method	scala/runtime/IntRef."<init>":(I)V
Asciz	()Lscala/collection/immutable/List;;
NameAndType	items:()Lscala/collection/immutable/List;
Method	scala/xml/PrettyPrinter.items:()Lscala/collection/immutable/List;
Asciz	scala/collection/immutable/List;
class	scala/collection/immutable/List
Asciz	reverse;
NameAndType	reverse:()Lscala/collection/immutable/List;
Method	scala/collection/immutable/List.reverse:()Lscala/collection/immutable/List;
Asciz	scala/xml/PrettyPrinter$$anonfun$format$1;
class	scala/xml/PrettyPrinter$$anonfun$format$1
Asciz	(Lscala/xml/PrettyPrinter;Lscala/collection/mutable/StringBuilder;Lscala/runtime/BooleanRef;Lscala/runtime/IntRef;)V;
NameAndType	"<init>":(Lscala/xml/PrettyPrinter;Lscala/collection/mutable/StringBuilder;Lscala/runtime/BooleanRef;Lscala/runtime/IntRef;)V
Method	scala/xml/PrettyPrinter$$anonfun$format$1."<init>":(Lscala/xml/PrettyPrinter;Lscala/collection/mutable/StringBuilder;Lscala/runtime/BooleanRef;Lscala/runtime/IntRef;)V
Asciz	scala/collection/LinearSeqLike;
class	scala/collection/LinearSeqLike
InterfaceMethod	scala/collection/LinearSeqLike.foreach:(Lscala/Function1;)V
Asciz	n;
Asciz	pscope;
Asciz	sb$1;
Asciz	lastwasbreak$1;
Asciz	Lscala/runtime/BooleanRef;;
Asciz	cur$1;
Asciz	Lscala/runtime/IntRef;;
Asciz	(Lscala/xml/Node;Lscala/collection/mutable/StringBuilder;)V;
Asciz	(Lscala/collection/Iterator;Lscala/xml/NamespaceBinding;I)V;
Asciz	scala/xml/PrettyPrinter$$anonfun$traverse$1;
class	scala/xml/PrettyPrinter$$anonfun$traverse$1
Asciz	(Lscala/xml/PrettyPrinter;Lscala/xml/NamespaceBinding;I)V;
NameAndType	"<init>":(Lscala/xml/PrettyPrinter;Lscala/xml/NamespaceBinding;I)V
Method	scala/xml/PrettyPrinter$$anonfun$traverse$1."<init>":(Lscala/xml/PrettyPrinter;Lscala/xml/NamespaceBinding;I)V
Asciz	scala/collection/Iterator;
class	scala/collection/Iterator
InterfaceMethod	scala/collection/Iterator.foreach:(Lscala/Function1;)V
Asciz	it;
Asciz	Lscala/collection/Iterator;;
Asciz	scope$1;
Asciz	ind$1;
Asciz	(Lscala/collection/Iterator<Lscala/xml/Node;>;Lscala/xml/NamespaceBinding;I)V;
Asciz	scala/xml/Text;
class	scala/xml/Text
Asciz	_data;
NameAndType	_data:()Ljava/lang/String;
Method	scala/xml/Text._data:()Ljava/lang/String;
NameAndType	gd3$1:(Ljava/lang/String;)Z
Method	scala/xml/PrettyPrinter.gd3$1:(Ljava/lang/String;)Z
Method	scala/xml/Node.toString:()Ljava/lang/String;
Asciz	makeBox;
Asciz	(ILjava/lang/String;)V;
NameAndType	makeBox:(ILjava/lang/String;)V
Method	scala/xml/PrettyPrinter.makeBox:(ILjava/lang/String;)V
Asciz	scala/xml/Group;
class	scala/xml/Group
Asciz	()Lscala/collection/Seq;;
NameAndType	nodes:()Lscala/collection/Seq;
Method	scala/xml/Group.nodes:()Lscala/collection/Seq;
Asciz	iterator;
Asciz	()Lscala/collection/Iterator;;
NameAndType	iterator:()Lscala/collection/Iterator;
InterfaceMethod	scala/collection/IterableLike.iterator:()Lscala/collection/Iterator;
NameAndType	traverse:(Lscala/collection/Iterator;Lscala/xml/NamespaceBinding;I)V
Method	scala/xml/PrettyPrinter.traverse:(Lscala/collection/Iterator;Lscala/xml/NamespaceBinding;I)V
Asciz	scala/xml/Utility$;
class	scala/xml/Utility$
Asciz	Lscala/xml/Utility$;;
NameAndType	MODULE$:Lscala/xml/Utility$;
Field	scala/xml/Utility$.MODULE$:Lscala/xml/Utility$;
Asciz	toXML;
Asciz	(Lscala/xml/Node;Lscala/xml/NamespaceBinding;Lscala/collection/mutable/StringBuilder;ZZZZ)Lscala/collection/mutable/StringBuilder;;
NameAndType	toXML:(Lscala/xml/Node;Lscala/xml/NamespaceBinding;Lscala/collection/mutable/StringBuilder;ZZZZ)Lscala/collection/mutable/StringBuilder;
Method	scala/xml/Utility$.toXML:(Lscala/xml/Node;Lscala/xml/NamespaceBinding;Lscala/collection/mutable/StringBuilder;ZZZZ)Lscala/collection/mutable/StringBuilder;
Asciz	doPreserve;
NameAndType	doPreserve:(Lscala/xml/Node;)Z
Method	scala/xml/PrettyPrinter.doPreserve:(Lscala/xml/Node;)Z
Asciz	scala/xml/TextBuffer;
class	scala/xml/TextBuffer
Method	scala/xml/TextBuffer."<init>":()V
Asciz	scala/Predef$;
class	scala/Predef$
Asciz	Lscala/Predef$;;
NameAndType	MODULE$:Lscala/Predef$;
Field	scala/Predef$.MODULE$:Lscala/Predef$;
Asciz	wrapString;
Asciz	(Ljava/lang/String;)Lscala/collection/immutable/WrappedString;;
NameAndType	wrapString:(Ljava/lang/String;)Lscala/collection/immutable/WrappedString;
Method	scala/Predef$.wrapString:(Ljava/lang/String;)Lscala/collection/immutable/WrappedString;
Asciz	(Lscala/collection/Seq;)Lscala/xml/TextBuffer;;
NameAndType	append:(Lscala/collection/Seq;)Lscala/xml/TextBuffer;
Method	scala/xml/TextBuffer.append:(Lscala/collection/Seq;)Lscala/xml/TextBuffer;
Asciz	toText;
NameAndType	toText:()Lscala/collection/Seq;
Method	scala/xml/TextBuffer.toText:()Lscala/collection/Seq;
Asciz	scala/collection/SeqLike;
class	scala/collection/SeqLike
Asciz	apply;
Asciz	(I)Ljava/lang/Object;;
NameAndType	apply:(I)Ljava/lang/Object;
InterfaceMethod	scala/collection/SeqLike.apply:(I)Ljava/lang/Object;
Asciz	data;
Asciz	()Ljava/lang/Object;;
NameAndType	data:()Ljava/lang/Object;
Method	scala/xml/Atom.data:()Ljava/lang/Object;
Asciz	childrenAreLeaves;
NameAndType	childrenAreLeaves:(Lscala/xml/Node;)Z
Method	scala/xml/PrettyPrinter.childrenAreLeaves:(Lscala/xml/Node;)Z
Asciz	fits;
NameAndType	fits:(Ljava/lang/String;)Z
Method	scala/xml/PrettyPrinter.fits:(Ljava/lang/String;)Z
Asciz	startTag;
Asciz	(Lscala/xml/Node;Lscala/xml/NamespaceBinding;)Lscala/Tuple2;;
NameAndType	startTag:(Lscala/xml/Node;Lscala/xml/NamespaceBinding;)Lscala/Tuple2;
Method	scala/xml/PrettyPrinter.startTag:(Lscala/xml/Node;Lscala/xml/NamespaceBinding;)Lscala/Tuple2;
Asciz	scala/Tuple2;
class	scala/Tuple2
Asciz	_1;
NameAndType	_1:()Ljava/lang/Object;
Method	scala/Tuple2._1:()Ljava/lang/Object;
Asciz	_2;
NameAndType	_2:()Ljava/lang/Object;
Method	scala/Tuple2._2:()Ljava/lang/Object;
Asciz	scala/runtime/BoxesRunTime;
class	scala/runtime/BoxesRunTime
Asciz	unboxToInt;
Asciz	(Ljava/lang/Object;)I;
NameAndType	unboxToInt:(Ljava/lang/Object;)I
Method	scala/runtime/BoxesRunTime.unboxToInt:(Ljava/lang/Object;)I
Asciz	boxToInteger;
Asciz	(I)Ljava/lang/Integer;;
NameAndType	boxToInteger:(I)Ljava/lang/Integer;
Method	scala/runtime/BoxesRunTime.boxToInteger:(I)Ljava/lang/Integer;
Asciz	(Ljava/lang/Object;Ljava/lang/Object;)V;
NameAndType	"<init>":(Ljava/lang/Object;Ljava/lang/Object;)V
Method	scala/Tuple2."<init>":(Ljava/lang/Object;Ljava/lang/Object;)V
Asciz	endTag;
Asciz	(Lscala/xml/Node;)Ljava/lang/String;;
NameAndType	endTag:(Lscala/xml/Node;)Ljava/lang/String;
Method	scala/xml/PrettyPrinter.endTag:(Lscala/xml/Node;)Ljava/lang/String;
Method	java/lang/String.length:()I
NameAndType	cur:()I
Method	scala/xml/PrettyPrinter.cur:()I
Asciz	makeBreak;
NameAndType	makeBreak:()V
Method	scala/xml/PrettyPrinter.makeBreak:()V
Asciz	child;
NameAndType	child:()Lscala/collection/Seq;
Method	scala/xml/Node.child:()Lscala/collection/Seq;
Asciz	substring;
Asciz	(II)Ljava/lang/String;;
NameAndType	substring:(II)Ljava/lang/String;
Method	java/lang/String.substring:(II)Ljava/lang/String;
Asciz	scala/MatchError;
class	scala/MatchError
Method	scala/Tuple2.toString:()Ljava/lang/String;
Asciz	(Ljava/lang/String;)V;
NameAndType	"<init>":(Ljava/lang/String;)V
Method	scala/MatchError."<init>":(Ljava/lang/String;)V
Asciz	node;
Asciz	ind;
Asciz	temp34;
Asciz	Lscala/xml/Group;;
Asciz	temp35;
Asciz	temp21;
Asciz	Ljava/lang/String;;
Asciz	temp22;
Asciz	len2;
Asciz	stg;
Asciz	etg;
Asciz	test;
Asciz	temp20;
Asciz	Lscala/Tuple2;;
Asciz	scala/xml/XML$;
class	scala/xml/XML$
Asciz	Lscala/xml/XML$;;
NameAndType	MODULE$:Lscala/xml/XML$;
Field	scala/xml/XML$.MODULE$:Lscala/xml/XML$;
Asciz	namespace;
NameAndType	namespace:()Ljava/lang/String;
Method	scala/xml/XML$.namespace:()Ljava/lang/String;
Asciz	space;
NameAndType	space:()Ljava/lang/String;
Method	scala/xml/XML$.space:()Ljava/lang/String;
Asciz	attribute;
Asciz	(Ljava/lang/String;Ljava/lang/String;)Lscala/Option;;
NameAndType	attribute:(Ljava/lang/String;Ljava/lang/String;)Lscala/Option;
Method	scala/xml/Node.attribute:(Ljava/lang/String;Ljava/lang/String;)Lscala/Option;
Asciz	scala/xml/PrettyPrinter$$anonfun$doPreserve$1;
class	scala/xml/PrettyPrinter$$anonfun$doPreserve$1
Method	scala/xml/PrettyPrinter$$anonfun$doPreserve$1."<init>":(Lscala/xml/PrettyPrinter;)V
Asciz	scala/Option;
class	scala/Option
Asciz	map;
Asciz	(Lscala/Function1;)Lscala/Option;;
NameAndType	map:(Lscala/Function1;)Lscala/Option;
Method	scala/Option.map:(Lscala/Function1;)Lscala/Option;
Asciz	scala/xml/PrettyPrinter$$anonfun$doPreserve$2;
class	scala/xml/PrettyPrinter$$anonfun$doPreserve$2
Method	scala/xml/PrettyPrinter$$anonfun$doPreserve$2."<init>":(Lscala/xml/PrettyPrinter;)V
Asciz	getOrElse;
Asciz	(Lscala/Function0;)Ljava/lang/Object;;
NameAndType	getOrElse:(Lscala/Function0;)Ljava/lang/Object;
Method	scala/Option.getOrElse:(Lscala/Function0;)Ljava/lang/Object;
Asciz	unboxToBoolean;
NameAndType	unboxToBoolean:(Ljava/lang/Object;)Z
Method	scala/runtime/BoxesRunTime.unboxToBoolean:(Ljava/lang/Object;)Z
Asciz	scala/xml/PrettyPrinter$$anonfun$childrenAreLeaves$1;
class	scala/xml/PrettyPrinter$$anonfun$childrenAreLeaves$1
Method	scala/xml/PrettyPrinter$$anonfun$childrenAreLeaves$1."<init>":(Lscala/xml/PrettyPrinter;)V
Asciz	forall;
Asciz	(Lscala/Function1;)Z;
NameAndType	forall:(Lscala/Function1;)Z
InterfaceMethod	scala/collection/IterableLike.forall:(Lscala/Function1;)Z
Asciz	n$3;
Asciz	n$2;
Asciz	pscope$1;
Asciz	i$1;
Asciz	(Lscala/xml/Node;Lscala/xml/NamespaceBinding;)Lscala/Tuple2<Ljava/lang/String;Ljava/lang/Integer;>;;
Asciz	leafTag;
Asciz	n$1;
Asciz	Break;
Asciz	()Lscala/xml/PrettyPrinter$Break$;;
NameAndType	Break:()Lscala/xml/PrettyPrinter$Break$;
Method	scala/xml/PrettyPrinter.Break:()Lscala/xml/PrettyPrinter$Break$;
Asciz	$colon$colon;
Asciz	(Ljava/lang/Object;)Lscala/collection/immutable/List;;
NameAndType	$colon$colon:(Ljava/lang/Object;)Lscala/collection/immutable/List;
Method	scala/collection/immutable/List.$colon$colon:(Ljava/lang/Object;)Lscala/collection/immutable/List;
Asciz	items_$eq;
Asciz	(Lscala/collection/immutable/List;)V;
NameAndType	items_$eq:(Lscala/collection/immutable/List;)V
Method	scala/xml/PrettyPrinter.items_$eq:(Lscala/collection/immutable/List;)V
Asciz	cur_$eq;
NameAndType	cur_$eq:(I)V
Method	scala/xml/PrettyPrinter.cur_$eq:(I)V
Asciz	makePara;
Asciz	scala/xml/PrettyPrinter$Para;
class	scala/xml/PrettyPrinter$Para
Asciz	(Lscala/xml/PrettyPrinter;Ljava/lang/String;)V;
NameAndType	"<init>":(Lscala/xml/PrettyPrinter;Ljava/lang/String;)V
Method	scala/xml/PrettyPrinter$Para."<init>":(Lscala/xml/PrettyPrinter;Ljava/lang/String;)V
Asciz	s;
Asciz	scala/xml/PrettyPrinter$Box;
class	scala/xml/PrettyPrinter$Box
Asciz	(Lscala/xml/PrettyPrinter;ILjava/lang/String;)V;
NameAndType	"<init>":(Lscala/xml/PrettyPrinter;ILjava/lang/String;)V
Method	scala/xml/PrettyPrinter$Box."<init>":(Lscala/xml/PrettyPrinter;ILjava/lang/String;)V
Asciz	cut;
Asciz	(Ljava/lang/String;I)Lscala/collection/immutable/List;;
NameAndType	cut:(Ljava/lang/String;I)Lscala/collection/immutable/List;
Method	scala/xml/PrettyPrinter.cut:(Ljava/lang/String;I)Lscala/collection/immutable/List;
Asciz	scala/xml/PrettyPrinter$$anonfun$makeBox$1;
class	scala/xml/PrettyPrinter$$anonfun$makeBox$1
Method	scala/xml/PrettyPrinter$$anonfun$makeBox$1."<init>":(Lscala/xml/PrettyPrinter;)V
NameAndType	makePara:(ILjava/lang/String;)V
Method	scala/xml/PrettyPrinter.makePara:(ILjava/lang/String;)V
Asciz	scala/xml/PrettyPrinter$BrokenException;
class	scala/xml/PrettyPrinter$BrokenException
Asciz	[Ljava/lang/Object;;
class	"[Ljava/lang/Object;"
Asciz	wrapRefArray;
Asciz	([Ljava/lang/Object;)Lscala/collection/mutable/WrappedArray;;
NameAndType	wrapRefArray:([Ljava/lang/Object;)Lscala/collection/mutable/WrappedArray;
Method	scala/Predef$.wrapRefArray:([Ljava/lang/Object;)Lscala/collection/mutable/WrappedArray;
Asciz	scala/collection/TraversableLike;
class	scala/collection/TraversableLike
Asciz	toList;
NameAndType	toList:()Lscala/collection/immutable/List;
InterfaceMethod	scala/collection/TraversableLike.toList:()Lscala/collection/immutable/List;
int	32;
Asciz	indexOf;
Asciz	(I)I;
NameAndType	indexOf:(I)I
Method	java/lang/String.indexOf:(I)I
Method	scala/xml/PrettyPrinter$BrokenException."<init>":(Lscala/xml/PrettyPrinter;)V
Asciz	(II)I;
NameAndType	indexOf:(II)I
Method	java/lang/String.indexOf:(II)I
Asciz	tail;
NameAndType	tail:()Ljava/lang/Object;
InterfaceMethod	scala/collection/TraversableLike.tail:()Ljava/lang/Object;
Asciz	head;
NameAndType	head:()Ljava/lang/Object;
InterfaceMethod	scala/collection/IterableLike.head:()Ljava/lang/Object;
Asciz	tmp;
Asciz	i;
Asciz	b;
Asciz	Lscala/xml/PrettyPrinter$Box;;
Asciz	last;
Asciz	(Ljava/lang/String;I)Lscala/collection/immutable/List<Lscala/xml/PrettyPrinter$Item;>;;
Asciz	(Lscala/collection/immutable/List<Lscala/xml/PrettyPrinter$Item;>;)V;
Asciz	()Lscala/collection/immutable/List<Lscala/xml/PrettyPrinter$Item;>;;
NameAndType	Break$module:Lscala/xml/PrettyPrinter$Break$;
Field	scala/xml/PrettyPrinter.Break$module:Lscala/xml/PrettyPrinter$Break$;
Asciz	scala/xml/PrettyPrinter$Break$;
class	scala/xml/PrettyPrinter$Break$
Method	scala/xml/PrettyPrinter$Break$."<init>":(Lscala/xml/PrettyPrinter;)V
Asciz	format$default$2;
Asciz	formatNodes$default$2;
Asciz	ScalaSig;
Asciz	InnerClasses;
Asciz	scala/xml/PrettyPrinter$Item;
class	scala/xml/PrettyPrinter$Item
Asciz	Item;
Asciz	BrokenException;
Asciz	scala/xml/PrettyPrinter$$anonfun$format$2;
class	scala/xml/PrettyPrinter$$anonfun$format$2
Asciz	$anonfun$format$2;
Asciz	scala/xml/PrettyPrinter$$anonfun$endTag$1;
class	scala/xml/PrettyPrinter$$anonfun$endTag$1
Asciz	$anonfun$endTag$1;
Asciz	$anonfun$format$1;
Asciz	scala/xml/PrettyPrinter$$anonfun$leafTag$1;
class	scala/xml/PrettyPrinter$$anonfun$leafTag$1
Asciz	$anonfun$leafTag$1;
Asciz	$anonfun$makeBox$1;
Asciz	scala/xml/PrettyPrinter$$anonfun$startTag$1;
class	scala/xml/PrettyPrinter$$anonfun$startTag$1
Asciz	$anonfun$startTag$1;
Asciz	$anonfun$traverse$1;
Asciz	$anonfun$doPreserve$2;
Asciz	$anonfun$doPreserve$1;
Asciz	scala/xml/PrettyPrinter$$anonfun$formatNodes$1;
class	scala/xml/PrettyPrinter$$anonfun$formatNodes$1
Asciz	$anonfun$formatNodes$1;
Asciz	$anonfun$formatNodes$2;
Asciz	$anonfun$childrenAreLeaves$1;
Asciz	scala/ScalaObject;
class	scala/ScalaObject

{
private scala.xml.PrettyPrinter$Box$ Box$module;
  Signature: Lscala/xml/PrettyPrinter$Box$;

private scala.xml.PrettyPrinter$Para$ Para$module;
  Signature: Lscala/xml/PrettyPrinter$Para$;

public scala.xml.PrettyPrinter$Break$ Break$module;
  Signature: Lscala/xml/PrettyPrinter$Break$;

private int cur;
  Signature: I

private scala.collection.immutable.List items;
  Signature: Lscala/collection/immutable/List;
  Signature: length = 0x2
   00 0D 

private final int step;
  Signature: I

private final int width;
  Signature: I

public scala.xml.PrettyPrinter(int, int);
  Signature: (II)V
  Code:
   Stack=2, Locals=3, Args_size=3
	aload_0
	iload_1
	putfield	Field width:I
	aload_0
	iload_2
	putfield	Field step:I
	aload_0
	invokespecial	Method java/lang/Object."<init>":()V
	aload_0
	getstatic	Field scala/collection/immutable/Nil$.MODULE$:Lscala/collection/immutable/Nil$;
	putfield	Field items:Lscala/collection/immutable/List;
	aload_0
	iconst_0
	putfield	Field cur:I
	return
  Labels:
  LocalVariableTable: 
   Start  Length  Slot  Name   Signature
   0      27      0    this       Lscala/xml/PrettyPrinter;
   0      27      1    width       I
   0      27      2    step       I


private final boolean gd3$1(java.lang.String);
  Signature: (Ljava/lang/String;)Z
  Code:
   Stack=2, Locals=3, Args_size=2
	aload_1
	invokevirtual	Method java/lang/String.trim:()Ljava/lang/String;
	ldc	String 
	astore_2
	dup
	ifnonnull	l1 // aload_2
	pop
	aload_2
	ifnull	l2 // iconst_1
	goto	l3 // iconst_0
l1	aload_2
	invokevirtual	Method java/lang/Object.equals:(Ljava/lang/Object;)Z
	ifeq	l3 // iconst_0
l2	iconst_1
	goto	l4 // ireturn
l3	iconst_0
l4	ireturn
  Labels:
   	l1 = 19 // aload_2
   	l2 = 26 // iconst_1
   	l3 = 30 // iconst_0
   	l4 = 31 // ireturn

public final boolean isLeaf$1(scala.xml.Node);
  Signature: (Lscala/xml/Node;)Z
  Code:
   Stack=1, Locals=2, Args_size=2
	aload_1
	instanceof	class scala/xml/Atom
	ifeq	l1 // aload_1
	iconst_1
	goto	l2 // ireturn
l1	aload_1
	instanceof	class scala/xml/Comment
	ifeq	l3 // aload_1
	iconst_1
	goto	l2 // ireturn
l3	aload_1
	instanceof	class scala/xml/EntityRef
	ifeq	l4 // aload_1
	iconst_1
	goto	l2 // ireturn
l4	aload_1
	instanceof	class scala/xml/ProcInstr
l2	ireturn
  Labels:
   	l1 = 11 // aload_1
   	l3 = 22 // aload_1
   	l4 = 33 // aload_1
   	l2 = 37 // ireturn
  LocalVariableTable: 
   Start  Length  Slot  Name   Signature
   0      38      0    this       Lscala/xml/PrettyPrinter;
   0      38      1    l       Lscala/xml/Node;


public final void mkEnd$1(scala.collection.mutable.StringBuilder, scala.xml.Node);
  Signature: (Lscala/collection/mutable/StringBuilder;Lscala/xml/Node;)V
  Code:
   Stack=2, Locals=3, Args_size=3
	aload_1
	ldc	String </
	invokevirtual	Method scala/collection/mutable/StringBuilder.append:(Ljava/lang/String;)Lscala/collection/mutable/StringBuilder;
	pop
	aload_2
	aload_1
	invokevirtual	Method scala/xml/Node.nameToString:(Lscala/collection/mutable/StringBuilder;)Lscala/collection/mutable/StringBuilder;
	pop
	aload_1
	ldc	int 62
	invokevirtual	Method scala/collection/mutable/StringBuilder.append:(C)Lscala/collection/mutable/StringBuilder;
	pop
	return
  Labels:
  LocalVariableTable: 
   Start  Length  Slot  Name   Signature
   0      21      0    this       Lscala/xml/PrettyPrinter;
   0      21      1    sb       Lscala/collection/mutable/StringBuilder;


public final void mkStart$1(scala.collection.mutable.StringBuilder, scala.xml.Node, scala.xml.NamespaceBinding, scala.runtime.IntRef);
  Signature: (Lscala/collection/mutable/StringBuilder;Lscala/xml/Node;Lscala/xml/NamespaceBinding;Lscala/runtime/IntRef;)V
  Code:
   Stack=3, Locals=5, Args_size=5
	aload_1
	ldc	int 60
	invokevirtual	Method scala/collection/mutable/StringBuilder.append:(C)Lscala/collection/mutable/StringBuilder;
	pop
	aload_2
	aload_1
	invokevirtual	Method scala/xml/Node.nameToString:(Lscala/collection/mutable/StringBuilder;)Lscala/collection/mutable/StringBuilder;
	pop
	aload	4
	aload_1
	invokevirtual	Method scala/collection/mutable/StringBuilder.length:()I
	iconst_1
	iadd
	putfield	Field scala/runtime/IntRef.elem:I
	aload_2
	invokevirtual	Method scala/xml/Node.attributes:()Lscala/xml/MetaData;
	aload_1
	invokevirtual	Method scala/xml/MetaData.buildString:(Lscala/collection/mutable/StringBuilder;)Lscala/collection/mutable/StringBuilder;
	pop
	aload_2
	invokevirtual	Method scala/xml/Node.scope:()Lscala/xml/NamespaceBinding;
	aload_1
	aload_3
	invokevirtual	Method scala/xml/NamespaceBinding.buildString:(Lscala/collection/mutable/StringBuilder;Lscala/xml/NamespaceBinding;)V
	aload_1
	ldc	int 62
	invokevirtual	Method scala/collection/mutable/StringBuilder.append:(C)Lscala/collection/mutable/StringBuilder;
	pop
	return
  Labels:
  LocalVariableTable: 
   Start  Length  Slot  Name   Signature
   0      50      0    this       Lscala/xml/PrettyPrinter;
   0      50      1    sb       Lscala/collection/mutable/StringBuilder;


public final void mkLeaf$1(scala.collection.mutable.StringBuilder, scala.xml.Node);
  Signature: (Lscala/collection/mutable/StringBuilder;Lscala/xml/Node;)V
  Code:
   Stack=2, Locals=3, Args_size=3
	aload_1
	ldc	int 60
	invokevirtual	Method scala/collection/mutable/StringBuilder.append:(C)Lscala/collection/mutable/StringBuilder;
	pop
	aload_2
	aload_1
	invokevirtual	Method scala/xml/Node.nameToString:(Lscala/collection/mutable/StringBuilder;)Lscala/collection/mutable/StringBuilder;
	pop
	aload_2
	invokevirtual	Method scala/xml/Node.attributes:()Lscala/xml/MetaData;
	aload_1
	invokevirtual	Method scala/xml/MetaData.buildString:(Lscala/collection/mutable/StringBuilder;)Lscala/collection/mutable/StringBuilder;
	pop
	aload_1
	ldc	String />
	invokevirtual	Method scala/collection/mutable/StringBuilder.append:(Ljava/lang/String;)Lscala/collection/mutable/StringBuilder;
	pop
	return
  Labels:
  LocalVariableTable: 
   Start  Length  Slot  Name   Signature
   0      30      0    this       Lscala/xml/PrettyPrinter;
   0      30      1    sb       Lscala/collection/mutable/StringBuilder;


public final scala.xml.PrettyPrinter$Box$ Box();
  Signature: ()Lscala/xml/PrettyPrinter$Box$;
  Code:
   Stack=4, Locals=1, Args_size=1
	aload_0
	getfield	Field Box$module:Lscala/xml/PrettyPrinter$Box$;
	ifnonnull	l1 // aload_0
	aload_0
	new	class scala/xml/PrettyPrinter$Box$
	dup
	aload_0
	invokespecial	Method scala/xml/PrettyPrinter$Box$."<init>":(Lscala/xml/PrettyPrinter;)V
	putfield	Field Box$module:Lscala/xml/PrettyPrinter$Box$;
l1	aload_0
	getfield	Field Box$module:Lscala/xml/PrettyPrinter$Box$;
	areturn
  Labels:
   	l1 = 19 // aload_0

public final scala.xml.PrettyPrinter$Para$ Para();
  Signature: ()Lscala/xml/PrettyPrinter$Para$;
  Code:
   Stack=4, Locals=1, Args_size=1
	aload_0
	getfield	Field Para$module:Lscala/xml/PrettyPrinter$Para$;
	ifnonnull	l1 // aload_0
	aload_0
	new	class scala/xml/PrettyPrinter$Para$
	dup
	aload_0
	invokespecial	Method scala/xml/PrettyPrinter$Para$."<init>":(Lscala/xml/PrettyPrinter;)V
	putfield	Field Para$module:Lscala/xml/PrettyPrinter$Para$;
l1	aload_0
	getfield	Field Para$module:Lscala/xml/PrettyPrinter$Para$;
	areturn
  Labels:
   	l1 = 19 // aload_0

public void formatNodes(scala.collection.Seq, scala.xml.NamespaceBinding, scala.collection.mutable.StringBuilder);
  Signature: (Lscala/collection/Seq;Lscala/xml/NamespaceBinding;Lscala/collection/mutable/StringBuilder;)V
  Code:
   Stack=6, Locals=4, Args_size=4
	aload_1
	new	class scala/xml/PrettyPrinter$$anonfun$formatNodes$2
	dup
	aload_0
	aload_2
	aload_3
	invokespecial	Method scala/xml/PrettyPrinter$$anonfun$formatNodes$2."<init>":(Lscala/xml/PrettyPrinter;Lscala/xml/NamespaceBinding;Lscala/collection/mutable/StringBuilder;)V
	invokeinterface	InterfaceMethod scala/collection/IterableLike.foreach:(Lscala/Function1;)V
	return
  Labels:
  LocalVariableTable: 
   Start  Length  Slot  Name   Signature
   0      17      0    this       Lscala/xml/PrettyPrinter;
   0      17      1    nodes       Lscala/collection/Seq;
   0      17      2    pscope$4       Lscala/xml/NamespaceBinding;
   0      17      3    sb$2       Lscala/collection/mutable/StringBuilder;

  Signature: length = 0x2
   00 FFFFFFA0 

public java.lang.String formatNodes(scala.collection.Seq, scala.xml.NamespaceBinding);
  Signature: (Lscala/collection/Seq;Lscala/xml/NamespaceBinding;)Ljava/lang/String;
  Code:
   Stack=4, Locals=5, Args_size=3
	new	class scala/collection/mutable/StringBuilder
	dup
	invokespecial	Method scala/collection/mutable/StringBuilder."<init>":()V
	astore	4
	aload	4
	checkcast	class scala/collection/mutable/StringBuilder
	astore_3
	aload_0
	aload_1
	aload_2
	aload_3
	invokevirtual	Method formatNodes:(Lscala/collection/Seq;Lscala/xml/NamespaceBinding;Lscala/collection/mutable/StringBuilder;)V
	aload	4
	invokevirtual	Method scala/collection/mutable/StringBuilder.toString:()Ljava/lang/String;
	areturn
  Labels:
  LocalVariableTable: 
   Start  Length  Slot  Name   Signature
   0      28      0    this       Lscala/xml/PrettyPrinter;
   0      28      1    nodes$1       Lscala/collection/Seq;
   0      28      2    pscope$3       Lscala/xml/NamespaceBinding;
   9      18      4    sb0       Lscala/collection/mutable/StringBuilder;

  Signature: length = 0x2
   00 FFFFFFAB 

public java.lang.String format(scala.xml.Node, scala.xml.NamespaceBinding);
  Signature: (Lscala/xml/Node;Lscala/xml/NamespaceBinding;)Ljava/lang/String;
  Code:
   Stack=4, Locals=5, Args_size=3
	new	class scala/collection/mutable/StringBuilder
	dup
	invokespecial	Method scala/collection/mutable/StringBuilder."<init>":()V
	astore	4
	aload	4
	checkcast	class scala/collection/mutable/StringBuilder
	astore_3
	aload_0
	aload_1
	aload_2
	aload_3
	invokevirtual	Method format:(Lscala/xml/Node;Lscala/xml/NamespaceBinding;Lscala/collection/mutable/StringBuilder;)V
	aload	4
	invokevirtual	Method scala/collection/mutable/StringBuilder.toString:()Ljava/lang/String;
	areturn
  Labels:
  LocalVariableTable: 
   Start  Length  Slot  Name   Signature
   0      28      0    this       Lscala/xml/PrettyPrinter;
   0      28      1    n$4       Lscala/xml/Node;
   0      28      2    pscope$2       Lscala/xml/NamespaceBinding;
   9      18      4    sb0       Lscala/collection/mutable/StringBuilder;


public void format(scala.xml.Node, scala.xml.NamespaceBinding, scala.collection.mutable.StringBuilder);
  Signature: (Lscala/xml/Node;Lscala/xml/NamespaceBinding;Lscala/collection/mutable/StringBuilder;)V
  Code:
   Stack=7, Locals=6, Args_size=4
	new	class scala/runtime/BooleanRef
	dup
	iconst_0
	invokespecial	Method scala/runtime/BooleanRef."<init>":(Z)V
	astore	4
	aload_0
	invokevirtual	Method reset:()V
	aload_0
	aload_1
	aload_2
	iconst_0
	invokevirtual	Method traverse:(Lscala/xml/Node;Lscala/xml/NamespaceBinding;I)V
	new	class scala/runtime/IntRef
	dup
	iconst_0
	invokespecial	Method scala/runtime/IntRef."<init>":(I)V
	astore	5
	aload_0
	invokevirtual	Method items:()Lscala/collection/immutable/List;
	invokevirtual	Method scala/collection/immutable/List.reverse:()Lscala/collection/immutable/List;
	new	class scala/xml/PrettyPrinter$$anonfun$format$1
	dup
	aload_0
	aload_3
	aload	4
	aload	5
	invokespecial	Method scala/xml/PrettyPrinter$$anonfun$format$1."<init>":(Lscala/xml/PrettyPrinter;Lscala/collection/mutable/StringBuilder;Lscala/runtime/BooleanRef;Lscala/runtime/IntRef;)V
	invokeinterface	InterfaceMethod scala/collection/LinearSeqLike.foreach:(Lscala/Function1;)V
	return
  Labels:
  LocalVariableTable: 
   Start  Length  Slot  Name   Signature
   0      57      0    this       Lscala/xml/PrettyPrinter;
   0      57      1    n       Lscala/xml/Node;
   0      57      2    pscope       Lscala/xml/NamespaceBinding;
   0      57      3    sb$1       Lscala/collection/mutable/StringBuilder;
   10      46      4    lastwasbreak$1       Lscala/runtime/BooleanRef;
   31      25      5    cur$1       Lscala/runtime/IntRef;


public void format(scala.xml.Node, scala.collection.mutable.StringBuilder);
  Signature: (Lscala/xml/Node;Lscala/collection/mutable/StringBuilder;)V
  Code:
   Stack=4, Locals=3, Args_size=3
	aload_0
	aload_1
	aconst_null
	aload_2
	invokevirtual	Method format:(Lscala/xml/Node;Lscala/xml/NamespaceBinding;Lscala/collection/mutable/StringBuilder;)V
	return
  Labels:
  LocalVariableTable: 
   Start  Length  Slot  Name   Signature
   0      8      0    this       Lscala/xml/PrettyPrinter;
   0      8      1    n       Lscala/xml/Node;
   0      8      2    sb       Lscala/collection/mutable/StringBuilder;


public void traverse(scala.collection.Iterator, scala.xml.NamespaceBinding, int);
  Signature: (Lscala/collection/Iterator;Lscala/xml/NamespaceBinding;I)V
  Code:
   Stack=6, Locals=4, Args_size=4
	aload_1
	new	class scala/xml/PrettyPrinter$$anonfun$traverse$1
	dup
	aload_0
	aload_2
	iload_3
	invokespecial	Method scala/xml/PrettyPrinter$$anonfun$traverse$1."<init>":(Lscala/xml/PrettyPrinter;Lscala/xml/NamespaceBinding;I)V
	invokeinterface	InterfaceMethod scala/collection/Iterator.foreach:(Lscala/Function1;)V
	return
  Labels:
  LocalVariableTable: 
   Start  Length  Slot  Name   Signature
   0      17      0    this       Lscala/xml/PrettyPrinter;
   0      17      1    it       Lscala/collection/Iterator;
   0      17      2    scope$1       Lscala/xml/NamespaceBinding;
   0      17      3    ind$1       I

  Signature: length = 0x2
   00 FFFFFFE7 

public void traverse(scala.xml.Node, scala.xml.NamespaceBinding, int);
  Signature: (Lscala/xml/Node;Lscala/xml/NamespaceBinding;I)V
  Code:
   Stack=8, Locals=16, Args_size=4
	aload_1
	instanceof	class scala/xml/Text
	ifeq	l1 // aload_1
	aload_0
	aload_1
	checkcast	class scala/xml/Text
	invokevirtual	Method scala/xml/Text._data:()Ljava/lang/String;
	invokespecial	Method gd3$1:(Ljava/lang/String;)Z
	ifne	l2 // return
	goto	l3 // aload_0
l1	aload_1
	instanceof	class scala/xml/Atom
	ifne	l3 // aload_0
	aload_1
	instanceof	class scala/xml/Comment
	ifne	l3 // aload_0
	aload_1
	instanceof	class scala/xml/EntityRef
	ifne	l3 // aload_0
	aload_1
	instanceof	class scala/xml/ProcInstr
	ifeq	l4 // aload_1
l3	aload_0
	iload_3
	aload_1
	invokevirtual	Method scala/xml/Node.toString:()Ljava/lang/String;
	invokevirtual	Method java/lang/String.trim:()Ljava/lang/String;
	invokevirtual	Method makeBox:(ILjava/lang/String;)V
	goto	l2 // return
l4	aload_1
	instanceof	class scala/xml/Group
	ifeq	l5 // new
	aload_1
	checkcast	class scala/xml/Group
	astore	4
	aload	4
	invokevirtual	Method scala/xml/Group.nodes:()Lscala/collection/Seq;
	astore	5
	aload_0
	aload	5
	invokeinterface	InterfaceMethod scala/collection/IterableLike.iterator:()Lscala/collection/Iterator;
	aload_2
	iload_3
	invokevirtual	Method traverse:(Lscala/collection/Iterator;Lscala/xml/NamespaceBinding;I)V
	goto	l2 // return
l5	new	class scala/collection/mutable/StringBuilder
	dup
	invokespecial	Method scala/collection/mutable/StringBuilder."<init>":()V
	astore	6
	getstatic	Field scala/xml/Utility$.MODULE$:Lscala/xml/Utility$;
	aload_1
	aload_2
	aload	6
	iconst_0
	iconst_1
	iconst_0
	iconst_0
	invokevirtual	Method scala/xml/Utility$.toXML:(Lscala/xml/Node;Lscala/xml/NamespaceBinding;Lscala/collection/mutable/StringBuilder;ZZZZ)Lscala/collection/mutable/StringBuilder;
	pop
	aload_0
	aload_1
	invokespecial	Method doPreserve:(Lscala/xml/Node;)Z
	ifeq	l6 // aload
	aload	6
	invokevirtual	Method scala/collection/mutable/StringBuilder.toString:()Ljava/lang/String;
	goto	l7 // astore
l6	aload	6
	invokevirtual	Method scala/collection/mutable/StringBuilder.toString:()Ljava/lang/String;
	astore	7
	new	class scala/xml/TextBuffer
	dup
	invokespecial	Method scala/xml/TextBuffer."<init>":()V
	getstatic	Field scala/Predef$.MODULE$:Lscala/Predef$;
	aload	7
	invokevirtual	Method scala/Predef$.wrapString:(Ljava/lang/String;)Lscala/collection/immutable/WrappedString;
	invokevirtual	Method scala/xml/TextBuffer.append:(Lscala/collection/Seq;)Lscala/xml/TextBuffer;
	invokevirtual	Method scala/xml/TextBuffer.toText:()Lscala/collection/Seq;
	iconst_0
	invokeinterface	InterfaceMethod scala/collection/SeqLike.apply:(I)Ljava/lang/Object;
	checkcast	class scala/xml/Atom
	invokevirtual	Method scala/xml/Atom.data:()Ljava/lang/Object;
	checkcast	class java/lang/String
l7	astore	14
	aload_0
	aload_1
	invokevirtual	Method childrenAreLeaves:(Lscala/xml/Node;)Z
	ifeq	l8 // aload_0
	aload_0
	aload	14
	invokevirtual	Method fits:(Ljava/lang/String;)Z
	ifeq	l8 // aload_0
	aload_0
	iload_3
	aload	14
	invokevirtual	Method makeBox:(ILjava/lang/String;)V
	goto	l2 // return
l8	aload_0
	aload_1
	aload_2
	invokevirtual	Method startTag:(Lscala/xml/Node;Lscala/xml/NamespaceBinding;)Lscala/Tuple2;
	astore	15
	aload	15
	ifnull	l9 // new
	aload	15
	invokevirtual	Method scala/Tuple2._1:()Ljava/lang/Object;
	checkcast	class java/lang/String
	astore	8
	aload	15
	invokevirtual	Method scala/Tuple2._2:()Ljava/lang/Object;
	invokestatic	Method scala/runtime/BoxesRunTime.unboxToInt:(Ljava/lang/Object;)I
	istore	9
	new	class scala/Tuple2
	dup
	aload	8
	iload	9
	invokestatic	Method scala/runtime/BoxesRunTime.boxToInteger:(I)Ljava/lang/Integer;
	invokespecial	Method scala/Tuple2."<init>":(Ljava/lang/Object;Ljava/lang/Object;)V
	astore	10
	aload	10
	invokevirtual	Method scala/Tuple2._1:()Ljava/lang/Object;
	checkcast	class java/lang/String
	astore	12
	aload	10
	invokevirtual	Method scala/Tuple2._2:()Ljava/lang/Object;
	invokestatic	Method scala/runtime/BoxesRunTime.unboxToInt:(Ljava/lang/Object;)I
	istore	11
	aload_0
	aload_1
	invokevirtual	Method endTag:(Lscala/xml/Node;)Ljava/lang/String;
	astore	13
	aload	12
	invokevirtual	Method java/lang/String.length:()I
	aload_0
	getfield	Field width:I
	aload_0
	invokevirtual	Method cur:()I
	isub
	if_icmpge	l10 // iload
	aload_0
	iload_3
	aload	12
	invokevirtual	Method makeBox:(ILjava/lang/String;)V
	aload_0
	invokevirtual	Method makeBreak:()V
	aload_0
	aload_1
	invokevirtual	Method scala/xml/Node.child:()Lscala/collection/Seq;
	invokeinterface	InterfaceMethod scala/collection/IterableLike.iterator:()Lscala/collection/Iterator;
	aload_1
	invokevirtual	Method scala/xml/Node.scope:()Lscala/xml/NamespaceBinding;
	iload_3
	aload_0
	getfield	Field step:I
	iadd
	invokevirtual	Method traverse:(Lscala/collection/Iterator;Lscala/xml/NamespaceBinding;I)V
	aload_0
	iload_3
	aload	13
	invokevirtual	Method makeBox:(ILjava/lang/String;)V
	goto	l2 // return
l10	iload	11
	aload_0
	getfield	Field width:I
	aload_0
	invokevirtual	Method cur:()I
	isub
	if_icmpge	l11 // aload_0
	aload_0
	iload_3
	aload	12
	iconst_0
	iload	11
	invokevirtual	Method java/lang/String.substring:(II)Ljava/lang/String;
	invokevirtual	Method makeBox:(ILjava/lang/String;)V
	aload_0
	invokevirtual	Method makeBreak:()V
	aload_0
	iload_3
	aload	12
	iload	11
	aload	12
	invokevirtual	Method java/lang/String.length:()I
	invokevirtual	Method java/lang/String.substring:(II)Ljava/lang/String;
	invokevirtual	Method makeBox:(ILjava/lang/String;)V
	aload_0
	invokevirtual	Method makeBreak:()V
	aload_0
	aload_1
	invokevirtual	Method scala/xml/Node.child:()Lscala/collection/Seq;
	invokeinterface	InterfaceMethod scala/collection/IterableLike.iterator:()Lscala/collection/Iterator;
	aload_1
	invokevirtual	Method scala/xml/Node.scope:()Lscala/xml/NamespaceBinding;
	iload_3
	aload_0
	getfield	Field step:I
	iadd
	invokevirtual	Method traverse:(Lscala/collection/Iterator;Lscala/xml/NamespaceBinding;I)V
	aload_0
	aload_0
	invokevirtual	Method cur:()I
	aload	13
	invokevirtual	Method makeBox:(ILjava/lang/String;)V
	aload_0
	invokevirtual	Method makeBreak:()V
	goto	l2 // return
l11	aload_0
	iload_3
	aload	14
	invokevirtual	Method makeBox:(ILjava/lang/String;)V
	aload_0
	invokevirtual	Method makeBreak:()V
l2	return
l9	new	class scala/MatchError
	dup
	aload	15
	invokevirtual	Method scala/Tuple2.toString:()Ljava/lang/String;
	invokespecial	Method scala/MatchError."<init>":(Ljava/lang/String;)V
	athrow
  Labels:
   	l1 = 24 // aload_1
   	l3 = 52 // aload_0
   	l4 = 67 // aload_1
   	l5 = 103 // new
   	l6 = 143 // aload
   	l7 = 186 // astore
   	l8 = 215 // aload_0
   	l10 = 352 // iload
   	l11 = 444 // aload_0
   	l2 = 455 // return
   	l9 = 456 // new
  LocalVariableTable: 
   Start  Length  Slot  Name   Signature
   0      469      0    this       Lscala/xml/PrettyPrinter;
   0      469      1    node       Lscala/xml/Node;
   0      469      2    pscope       Lscala/xml/NamespaceBinding;
   0      469      3    ind       I
   80      20      4    temp34       Lscala/xml/Group;
   87      13      5    temp35       Lscala/collection/Seq;
   112      84      6    sb       Lscala/collection/mutable/StringBuilder;
   238      24      8    temp21       Ljava/lang/String;
   248      14      9    temp22       I
   284      171      11    len2       I
   274      181      12    stg       Ljava/lang/String;
   291      164      13    etg       Ljava/lang/String;
   188      267      14    test       Ljava/lang/String;
   456      13      14    test       Ljava/lang/String;
   223      85      15    temp20       Lscala/Tuple2;
   456      13      15    temp20       Lscala/Tuple2;


private boolean doPreserve(scala.xml.Node);
  Signature: (Lscala/xml/Node;)Z
  Code:
   Stack=4, Locals=2, Args_size=2
	aload_1
	getstatic	Field scala/xml/XML$.MODULE$:Lscala/xml/XML$;
	invokevirtual	Method scala/xml/XML$.namespace:()Ljava/lang/String;
	getstatic	Field scala/xml/XML$.MODULE$:Lscala/xml/XML$;
	invokevirtual	Method scala/xml/XML$.space:()Ljava/lang/String;
	invokevirtual	Method scala/xml/Node.attribute:(Ljava/lang/String;Ljava/lang/String;)Lscala/Option;
	new	class scala/xml/PrettyPrinter$$anonfun$doPreserve$1
	dup
	aload_0
	invokespecial	Method scala/xml/PrettyPrinter$$anonfun$doPreserve$1."<init>":(Lscala/xml/PrettyPrinter;)V
	invokevirtual	Method scala/Option.map:(Lscala/Function1;)Lscala/Option;
	new	class scala/xml/PrettyPrinter$$anonfun$doPreserve$2
	dup
	aload_0
	invokespecial	Method scala/xml/PrettyPrinter$$anonfun$doPreserve$2."<init>":(Lscala/xml/PrettyPrinter;)V
	invokevirtual	Method scala/Option.getOrElse:(Lscala/Function0;)Ljava/lang/Object;
	invokestatic	Method scala/runtime/BoxesRunTime.unboxToBoolean:(Ljava/lang/Object;)Z
	ireturn
  Labels:
  LocalVariableTable: 
   Start  Length  Slot  Name   Signature
   0      42      0    this       Lscala/xml/PrettyPrinter;
   0      42      1    node       Lscala/xml/Node;


public boolean fits(java.lang.String);
  Signature: (Ljava/lang/String;)Z
  Code:
   Stack=3, Locals=2, Args_size=2
	aload_1
	invokevirtual	Method java/lang/String.length:()I
	aload_0
	getfield	Field width:I
	aload_0
	invokevirtual	Method cur:()I
	isub
	if_icmpge	l1 // iconst_0
	iconst_1
	goto	l2 // ireturn
l1	iconst_0
l2	ireturn
  Labels:
   	l1 = 20 // iconst_0
   	l2 = 21 // ireturn
  LocalVariableTable: 
   Start  Length  Slot  Name   Signature
   0      22      0    this       Lscala/xml/PrettyPrinter;
   0      22      1    test       Ljava/lang/String;


public boolean childrenAreLeaves(scala.xml.Node);
  Signature: (Lscala/xml/Node;)Z
  Code:
   Stack=4, Locals=2, Args_size=2
	aload_1
	invokevirtual	Method scala/xml/Node.child:()Lscala/collection/Seq;
	new	class scala/xml/PrettyPrinter$$anonfun$childrenAreLeaves$1
	dup
	aload_0
	invokespecial	Method scala/xml/PrettyPrinter$$anonfun$childrenAreLeaves$1."<init>":(Lscala/xml/PrettyPrinter;)V
	invokeinterface	InterfaceMethod scala/collection/IterableLike.forall:(Lscala/Function1;)Z
	ireturn
  Labels:
  LocalVariableTable: 
   Start  Length  Slot  Name   Signature
   0      18      0    this       Lscala/xml/PrettyPrinter;
   0      18      1    n       Lscala/xml/Node;


public java.lang.String endTag(scala.xml.Node);
  Signature: (Lscala/xml/Node;)Ljava/lang/String;
  Code:
   Stack=2, Locals=5, Args_size=2
	new	class scala/collection/mutable/StringBuilder
	dup
	invokespecial	Method scala/collection/mutable/StringBuilder."<init>":()V
	astore	4
	aload	4
	checkcast	class scala/collection/mutable/StringBuilder
	astore_3
	aload_1
	astore_2
	aload_3
	ldc	String </
	invokevirtual	Method scala/collection/mutable/StringBuilder.append:(Ljava/lang/String;)Lscala/collection/mutable/StringBuilder;
	pop
	aload_2
	aload_3
	invokevirtual	Method scala/xml/Node.nameToString:(Lscala/collection/mutable/StringBuilder;)Lscala/collection/mutable/StringBuilder;
	pop
	aload_3
	ldc	int 62
	invokevirtual	Method scala/collection/mutable/StringBuilder.append:(C)Lscala/collection/mutable/StringBuilder;
	pop
	aload	4
	invokevirtual	Method scala/collection/mutable/StringBuilder.toString:()Ljava/lang/String;
	areturn
  Labels:
  LocalVariableTable: 
   Start  Length  Slot  Name   Signature
   0      43      0    this       Lscala/xml/PrettyPrinter;
   0      43      1    n$3       Lscala/xml/Node;
   9      33      4    sb0       Lscala/collection/mutable/StringBuilder;


public scala.Tuple2 startTag(scala.xml.Node, scala.xml.NamespaceBinding);
  Signature: (Lscala/xml/Node;Lscala/xml/NamespaceBinding;)Lscala/Tuple2;
  Code:
   Stack=5, Locals=10, Args_size=3
	new	class scala/runtime/IntRef
	dup
	iconst_0
	invokespecial	Method scala/runtime/IntRef."<init>":(I)V
	astore	8
	new	class scala/Tuple2
	dup
	new	class scala/collection/mutable/StringBuilder
	dup
	invokespecial	Method scala/collection/mutable/StringBuilder."<init>":()V
	astore	7
	aload	7
	checkcast	class scala/collection/mutable/StringBuilder
	astore	6
	aload_1
	aload_2
	aload	8
	astore_3
	astore	5
	astore	4
	aload	6
	ldc	int 60
	invokevirtual	Method scala/collection/mutable/StringBuilder.append:(C)Lscala/collection/mutable/StringBuilder;
	pop
	aload	4
	aload	6
	invokevirtual	Method scala/xml/Node.nameToString:(Lscala/collection/mutable/StringBuilder;)Lscala/collection/mutable/StringBuilder;
	pop
	aload_3
	aload	6
	invokevirtual	Method scala/collection/mutable/StringBuilder.length:()I
	iconst_1
	iadd
	putfield	Field scala/runtime/IntRef.elem:I
	aload	4
	invokevirtual	Method scala/xml/Node.attributes:()Lscala/xml/MetaData;
	aload	6
	invokevirtual	Method scala/xml/MetaData.buildString:(Lscala/collection/mutable/StringBuilder;)Lscala/collection/mutable/StringBuilder;
	pop
	aload	4
	invokevirtual	Method scala/xml/Node.scope:()Lscala/xml/NamespaceBinding;
	aload	6
	aload	5
	invokevirtual	Method scala/xml/NamespaceBinding.buildString:(Lscala/collection/mutable/StringBuilder;Lscala/xml/NamespaceBinding;)V
	aload	6
	ldc	int 62
	invokevirtual	Method scala/collection/mutable/StringBuilder.append:(C)Lscala/collection/mutable/StringBuilder;
	pop
	aload	7
	invokevirtual	Method scala/collection/mutable/StringBuilder.toString:()Ljava/lang/String;
	aload	8
	getfield	Field scala/runtime/IntRef.elem:I
	istore	9
	iload	9
	invokestatic	Method scala/runtime/BoxesRunTime.boxToInteger:(I)Ljava/lang/Integer;
	invokespecial	Method scala/Tuple2."<init>":(Ljava/lang/Object;Ljava/lang/Object;)V
	areturn
  Labels:
  LocalVariableTable: 
   Start  Length  Slot  Name   Signature
   0      118      0    this       Lscala/xml/PrettyPrinter;
   0      118      1    n$2       Lscala/xml/Node;
   0      118      2    pscope$1       Lscala/xml/NamespaceBinding;
   23      79      7    sb0       Lscala/collection/mutable/StringBuilder;
   10      107      8    i$1       Lscala/runtime/IntRef;

  Signature: length = 0x2
   01 FFFFFF98 

public java.lang.String leafTag(scala.xml.Node);
  Signature: (Lscala/xml/Node;)Ljava/lang/String;
  Code:
   Stack=2, Locals=5, Args_size=2
	new	class scala/collection/mutable/StringBuilder
	dup
	invokespecial	Method scala/collection/mutable/StringBuilder."<init>":()V
	astore	4
	aload	4
	checkcast	class scala/collection/mutable/StringBuilder
	astore_3
	aload_1
	astore_2
	aload_3
	ldc	int 60
	invokevirtual	Method scala/collection/mutable/StringBuilder.append:(C)Lscala/collection/mutable/StringBuilder;
	pop
	aload_2
	aload_3
	invokevirtual	Method scala/xml/Node.nameToString:(Lscala/collection/mutable/StringBuilder;)Lscala/collection/mutable/StringBuilder;
	pop
	aload_2
	invokevirtual	Method scala/xml/Node.attributes:()Lscala/xml/MetaData;
	aload_3
	invokevirtual	Method scala/xml/MetaData.buildString:(Lscala/collection/mutable/StringBuilder;)Lscala/collection/mutable/StringBuilder;
	pop
	aload_3
	ldc	String />
	invokevirtual	Method scala/collection/mutable/StringBuilder.append:(Ljava/lang/String;)Lscala/collection/mutable/StringBuilder;
	pop
	aload	4
	invokevirtual	Method scala/collection/mutable/StringBuilder.toString:()Ljava/lang/String;
	areturn
  Labels:
  LocalVariableTable: 
   Start  Length  Slot  Name   Signature
   0      52      0    this       Lscala/xml/PrettyPrinter;
   0      52      1    n$1       Lscala/xml/Node;
   9      42      4    sb0       Lscala/collection/mutable/StringBuilder;


public void makeBreak();
  Signature: ()V
  Code:
   Stack=3, Locals=2, Args_size=1
	aload_0
	aload_0
	invokevirtual	Method Break:()Lscala/xml/PrettyPrinter$Break$;
	astore_1
	aload_0
	invokevirtual	Method items:()Lscala/collection/immutable/List;
	aload_1
	invokevirtual	Method scala/collection/immutable/List.$colon$colon:(Ljava/lang/Object;)Lscala/collection/immutable/List;
	invokevirtual	Method items_$eq:(Lscala/collection/immutable/List;)V
	aload_0
	iconst_0
	invokevirtual	Method cur_$eq:(I)V
	return
  Labels:

public void makePara(int, java.lang.String);
  Signature: (ILjava/lang/String;)V
  Code:
   Stack=5, Locals=6, Args_size=3
	aload_0
	aload_0
	invokevirtual	Method Break:()Lscala/xml/PrettyPrinter$Break$;
	astore_3
	new	class scala/xml/PrettyPrinter$Para
	dup
	aload_0
	aload_2
	invokespecial	Method scala/xml/PrettyPrinter$Para."<init>":(Lscala/xml/PrettyPrinter;Ljava/lang/String;)V
	astore	4
	aload_0
	invokevirtual	Method Break:()Lscala/xml/PrettyPrinter$Break$;
	astore	5
	aload_0
	invokevirtual	Method items:()Lscala/collection/immutable/List;
	aload	5
	invokevirtual	Method scala/collection/immutable/List.$colon$colon:(Ljava/lang/Object;)Lscala/collection/immutable/List;
	aload	4
	invokevirtual	Method scala/collection/immutable/List.$colon$colon:(Ljava/lang/Object;)Lscala/collection/immutable/List;
	aload_3
	invokevirtual	Method scala/collection/immutable/List.$colon$colon:(Ljava/lang/Object;)Lscala/collection/immutable/List;
	invokevirtual	Method items_$eq:(Lscala/collection/immutable/List;)V
	aload_0
	iload_1
	invokevirtual	Method cur_$eq:(I)V
	return
  Labels:
  LocalVariableTable: 
   Start  Length  Slot  Name   Signature
   0      50      0    this       Lscala/xml/PrettyPrinter;
   0      50      1    ind       I
   0      50      2    s       Ljava/lang/String;


public void makeBox(int, java.lang.String);
  Signature: (ILjava/lang/String;)V
  Code:
   Stack=7, Locals=3, Args_size=3
	aload_0
	invokevirtual	Method cur:()I
	aload_2
	invokevirtual	Method java/lang/String.length:()I
	iadd
	aload_0
	getfield	Field width:I
	if_icmple	l1 // aload_0
	aload_0
	aload_0
	invokevirtual	Method items:()Lscala/collection/immutable/List;
	new	class scala/xml/PrettyPrinter$Box
	dup
	aload_0
	iload_1
	aload_2
	invokespecial	Method scala/xml/PrettyPrinter$Box."<init>":(Lscala/xml/PrettyPrinter;ILjava/lang/String;)V
	invokevirtual	Method scala/collection/immutable/List.$colon$colon:(Ljava/lang/Object;)Lscala/collection/immutable/List;
	invokevirtual	Method items_$eq:(Lscala/collection/immutable/List;)V
	aload_0
	aload_0
	invokevirtual	Method cur:()I
	aload_2
	invokevirtual	Method java/lang/String.length:()I
	iadd
	invokevirtual	Method cur_$eq:(I)V
	goto	l2 // return
l1	aload_0
	aload_2
	iload_1
	invokevirtual	Method cut:(Ljava/lang/String;I)Lscala/collection/immutable/List;
	new	class scala/xml/PrettyPrinter$$anonfun$makeBox$1
	dup
	aload_0
	invokespecial	Method scala/xml/PrettyPrinter$$anonfun$makeBox$1."<init>":(Lscala/xml/PrettyPrinter;)V
	invokeinterface	InterfaceMethod scala/collection/LinearSeqLike.foreach:(Lscala/Function1;)V
	goto	l2 // return
	pop
	aload_0
	iload_1
	aload_2
	invokevirtual	Method makePara:(ILjava/lang/String;)V
l2	return
  Labels:
   	l1 = 53 // aload_0
   	l2 = 82 // return
  Exception table:
   from   to  target type
    53    75    75   Class scala/xml/PrettyPrinter$BrokenException

  LocalVariableTable: 
   Start  Length  Slot  Name   Signature
   0      83      0    this       Lscala/xml/PrettyPrinter;
   0      83      1    ind       I
   0      83      2    s       Ljava/lang/String;


public scala.collection.immutable.List cut(java.lang.String, int);
  Signature: (Ljava/lang/String;I)Lscala/collection/immutable/List;
  Code:
   Stack=9, Locals=9, Args_size=3
	aload_0
	getfield	Field width:I
	aload_0
	invokevirtual	Method cur:()I
	isub
	istore	4
	aload_1
	invokevirtual	Method java/lang/String.length:()I
	iload	4
	if_icmpgt	l1 // new
	getstatic	Field scala/Predef$.MODULE$:Lscala/Predef$;
	iconst_1
	anewarray	class scala/xml/PrettyPrinter$Box
	dup
	iconst_0
	new	class scala/xml/PrettyPrinter$Box
	dup
	aload_0
	iload_2
	aload_1
	invokespecial	Method scala/xml/PrettyPrinter$Box."<init>":(Lscala/xml/PrettyPrinter;ILjava/lang/String;)V
	aastore
	checkcast	class "[Ljava/lang/Object;"
	invokevirtual	Method scala/Predef$.wrapRefArray:([Ljava/lang/Object;)Lscala/collection/mutable/WrappedArray;
	astore_3
	aload_3
	invokeinterface	InterfaceMethod scala/collection/TraversableLike.toList:()Lscala/collection/immutable/List;
	areturn
l1	new	class scala/collection/mutable/StringBuilder
	dup
	invokespecial	Method scala/collection/mutable/StringBuilder."<init>":()V
	pop
	aload_1
	ldc_w	int 32
	invokevirtual	Method java/lang/String.indexOf:(I)I
	istore	5
	iload	5
	iload	4
	if_icmpgt	l2 // new
	iload	5
	iconst_m1
	if_icmpne	l3 // getstatic
l2	new	class scala/xml/PrettyPrinter$BrokenException
	dup
	aload_0
	invokespecial	Method scala/xml/PrettyPrinter$BrokenException."<init>":(Lscala/xml/PrettyPrinter;)V
	athrow
l3	getstatic	Field scala/collection/immutable/Nil$.MODULE$:Lscala/collection/immutable/Nil$;
	astore	8
l5	iload	5
	iconst_m1
	if_icmpeq	l4 // goto
	iload	5
	iload	4
	if_icmpge	l4 // goto
	aload	8
	iload	5
	invokestatic	Method scala/runtime/BoxesRunTime.boxToInteger:(I)Ljava/lang/Integer;
	invokevirtual	Method scala/collection/immutable/List.$colon$colon:(Ljava/lang/Object;)Lscala/collection/immutable/List;
	astore	8
	aload_1
	ldc_w	int 32
	iload	5
	iconst_1
	iadd
	invokevirtual	Method java/lang/String.indexOf:(II)I
	istore	5
	goto	l5 // iload
l4	goto	l6 // getstatic
	pop
	aload	8
	invokeinterface	InterfaceMethod scala/collection/TraversableLike.tail:()Ljava/lang/Object;
	checkcast	class scala/collection/immutable/List
	astore	8
l6	getstatic	Field scala/collection/immutable/Nil$.MODULE$:Lscala/collection/immutable/Nil$;
	dup
	ifnonnull	l7 // aload
	pop
	aload	8
	ifnull	l8 // new
	goto	l9 // new
l7	aload	8
	invokevirtual	Method java/lang/Object.equals:(Ljava/lang/Object;)Z
	ifeq	l9 // new
l8	new	class scala/xml/PrettyPrinter$BrokenException
	dup
	aload_0
	invokespecial	Method scala/xml/PrettyPrinter$BrokenException."<init>":(Lscala/xml/PrettyPrinter;)V
	athrow
l9	new	class scala/xml/PrettyPrinter$Box
	dup
	aload_0
	iload_2
	aload_1
	iconst_0
	aload	8
	invokeinterface	InterfaceMethod scala/collection/IterableLike.head:()Ljava/lang/Object;
	invokestatic	Method scala/runtime/BoxesRunTime.unboxToInt:(Ljava/lang/Object;)I
	invokevirtual	Method java/lang/String.substring:(II)Ljava/lang/String;
	invokespecial	Method scala/xml/PrettyPrinter$Box."<init>":(Lscala/xml/PrettyPrinter;ILjava/lang/String;)V
	astore	7
	aload_0
	iload_2
	invokevirtual	Method cur_$eq:(I)V
	aload_0
	invokevirtual	Method Break:()Lscala/xml/PrettyPrinter$Break$;
	astore	6
	aload_0
	aload_1
	aload	8
	invokeinterface	InterfaceMethod scala/collection/IterableLike.head:()Ljava/lang/Object;
	invokestatic	Method scala/runtime/BoxesRunTime.unboxToInt:(Ljava/lang/Object;)I
	aload_1
	invokevirtual	Method java/lang/String.length:()I
	invokevirtual	Method java/lang/String.substring:(II)Ljava/lang/String;
	iload_2
	invokevirtual	Method cut:(Ljava/lang/String;I)Lscala/collection/immutable/List;
	aload	6
	invokevirtual	Method scala/collection/immutable/List.$colon$colon:(Ljava/lang/Object;)Lscala/collection/immutable/List;
	aload	7
	invokevirtual	Method scala/collection/immutable/List.$colon$colon:(Ljava/lang/Object;)Lscala/collection/immutable/List;
	pop
	aload	8
	invokeinterface	InterfaceMethod scala/collection/TraversableLike.tail:()Ljava/lang/Object;
	checkcast	class scala/collection/immutable/List
	astore	8
	goto	l6 // getstatic
  Labels:
   	l1 = 54 // new
   	l2 = 84 // new
   	l3 = 93 // getstatic
   	l5 = 98 // iload
   	l4 = 139 // goto
   	l6 = 155 // getstatic
   	l7 = 171 // aload
   	l8 = 179 // new
   	l9 = 188 // new
  Exception table:
   from   to  target type
   188   274   142   Class scala/xml/PrettyPrinter$BrokenException

  LocalVariableTable: 
   Start  Length  Slot  Name   Signature
   0      274      0    this       Lscala/xml/PrettyPrinter;
   0      274      1    s       Ljava/lang/String;
   0      274      2    ind       I
   11      263      4    tmp       I
   71      203      5    i       I
   214      57      7    b       Lscala/xml/PrettyPrinter$Box;
   98      176      8    last       Lscala/collection/immutable/List;

  Signature: length = 0x2
   01 FFFFFFE0 

public void reset();
  Signature: ()V
  Code:
   Stack=2, Locals=1, Args_size=1
	aload_0
	iconst_0
	invokevirtual	Method cur_$eq:(I)V
	aload_0
	getstatic	Field scala/collection/immutable/Nil$.MODULE$:Lscala/collection/immutable/Nil$;
	invokevirtual	Method items_$eq:(Lscala/collection/immutable/List;)V
	return
  Labels:

public void cur_$eq(int);
  Signature: (I)V
  Code:
   Stack=2, Locals=2, Args_size=2
	aload_0
	iload_1
	putfield	Field cur:I
	return
  Labels:

public int cur();
  Signature: ()I
  Code:
   Stack=1, Locals=1, Args_size=1
	aload_0
	getfield	Field cur:I
	ireturn
  Labels:

public void items_$eq(scala.collection.immutable.List);
  Signature: (Lscala/collection/immutable/List;)V
  Code:
   Stack=2, Locals=2, Args_size=2
	aload_0
	aload_1
	putfield	Field items:Lscala/collection/immutable/List;
	return
  Labels:
  Signature: length = 0x2
   01 FFFFFFE1 

public scala.collection.immutable.List items();
  Signature: ()Lscala/collection/immutable/List;
  Code:
   Stack=1, Locals=1, Args_size=1
	aload_0
	getfield	Field items:Lscala/collection/immutable/List;
	areturn
  Labels:
  Signature: length = 0x2
   01 FFFFFFE2 

public final scala.xml.PrettyPrinter$Break$ Break();
  Signature: ()Lscala/xml/PrettyPrinter$Break$;
  Code:
   Stack=4, Locals=1, Args_size=1
	aload_0
	getfield	Field Break$module:Lscala/xml/PrettyPrinter$Break$;
	ifnonnull	l1 // aload_0
	aload_0
	new	class scala/xml/PrettyPrinter$Break$
	dup
	aload_0
	invokespecial	Method scala/xml/PrettyPrinter$Break$."<init>":(Lscala/xml/PrettyPrinter;)V
	putfield	Field Break$module:Lscala/xml/PrettyPrinter$Break$;
l1	aload_0
	getfield	Field Break$module:Lscala/xml/PrettyPrinter$Break$;
	areturn
  Labels:
   	l1 = 19 // aload_0

public scala.xml.NamespaceBinding format$default$2();
  Signature: ()Lscala/xml/NamespaceBinding;
  Code:
   Stack=1, Locals=1, Args_size=1
	aconst_null
	areturn
  Labels:

public scala.xml.NamespaceBinding formatNodes$default$2();
  Signature: ()Lscala/xml/NamespaceBinding;
  Code:
   Stack=1, Locals=1, Args_size=1
	aconst_null
	areturn
  Labels:

}

